{
  "type": "Feature",
  "properties": {
    "addr:full":"Lodewijk De Konincklaan 351 Hoogstraten Antwerpen 2320",
    "addr:housenumber":"351",
    "addr:postcode":"2320",
    "addr:street":"Lodewijk De Konincklaan",
    "iso:country":"BE",
    "sg:address":"Lodewijk De Konincklaan 351",
    "sg:city":"Hoogstraten",
    "sg:classifiers":[
        {
            "category":"Farming",
            "subcategory":"Livestock Farm",
            "type":"Manufacturing & Wholesale Goods"
        }
    ],
    "sg:phone":"+32 3 314 50 43",
    "sg:postcode":"2320",
    "sg:province":"Antwerpen",
    "sg:tags":[
        "buyer"
    ],
    "wof:name":"De Meester J",
    "wof:placetype":"venue"
},
  "geometry": {"coordinates":[4.7564740181,51.3937988281],"type":"Point"}
}