{
  "type": "Feature",
  "properties": {
    "iso:country":"BE",
    "sg:address":"Sint-godelievestraat 1",
    "sg:city":"Kortrijk",
    "sg:classifiers":[
        {
            "category":"Cafe",
            "type":"Food & Drink"
        }
    ],
    "sg:phone":"+32 56 37 20 42",
    "sg:postcode":"8501",
    "sg:province":"West-Vlaanderen",
    "sg:tags":[
        "caf\u00e9s"
    ],
    "wof:name":"Beni",
    "wof:placetype":"venue"
},
  "geometry": {"coordinates":[3.2562630177,50.8397331238],"type":"Point"}
}