{
  "type": "Feature",
  "properties": {
    "addr:full":"Rue Du Duc 23 Sint-pieters-woluwe/woluwe-saint-pierre Bruxelles-Capitale 1150",
    "addr:housenumber":"23",
    "addr:postcode":"1150",
    "addr:street":"Rue Du Duc;/",
    "iso:country":"BE",
    "sg:address":"Rue Du Duc 23",
    "sg:city":"Sint-pieters-woluwe/woluwe-saint-pierre",
    "sg:classifiers":[
        {
            "category":"Shopping Center",
            "type":"Public Place"
        }
    ],
    "sg:phone":"+32 2 779 25 00",
    "sg:postcode":"1150",
    "sg:province":"Bruxelles-Capitale",
    "sg:tags":[
        "enseignement",
        "formation"
    ],
    "wof:name":"Katarina Van Der Hoeven",
    "wof:placetype":"venue"
},
  "geometry": {"coordinates":[4.4148049355,50.8376541138],"type":"Point"}
}