{
  "type": "Feature",
  "properties": {
    "addr:full":"Rue De Li\u00c8ge 22 Tinlot Li\u00e8ge 4557",
    "addr:housenumber":"22",
    "addr:postcode":"4557",
    "addr:street":"Rue De Lie\u0300Ge",
    "iso:country":"BE",
    "sg:address":"Rue De Li\u00c8ge 22",
    "sg:city":"Tinlot",
    "sg:orig_category":"Rundveehouders",
    "sg:phone":"+32 85 51 13 86",
    "sg:postcode":"4557",
    "sg:province":"Li\u00e8ge",
    "wof:name":"Robert Jauquet",
    "wof:placetype":"venue"
},
  "geometry": {"coordinates":[5.3753452301,50.47864151],"type":"Point"}
}