{
  "type": "Feature",
  "properties": {
    "iso:country":"BE",
    "sg:address":"Poedermolenstraat 8",
    "sg:city":"Mechelen",
    "sg:classifiers":[
        {
            "category":"Personal",
            "subcategory":"Beauty Salon",
            "type":"Services"
        }
    ],
    "sg:phone":"+32 15 42 29 75",
    "sg:postcode":"2800",
    "sg:province":"Antwerpen",
    "sg:tags":[
        "de",
        "coiffure"
    ],
    "wof:name":"Chantal Van Den Avont",
    "wof:placetype":"venue"
},
  "geometry": {"coordinates":[4.4850091934,51.005191803],"type":"Point"}
}