{
  "type": "Feature",
  "properties": {
    "addr:full":"Wolfsdonksteenweg 30a Aarschot (langdorp) Vlaams-Brabant 3201",
    "addr:housenumber":"30a",
    "addr:postcode":"3201",
    "addr:street":"Wolfsdonksteenweg",
    "iso:country":"BE",
    "sg:address":"Wolfsdonksteenweg 30a",
    "sg:city":"Aarschot (langdorp)",
    "sg:classifiers":[
        {
            "category":"Building & Trades",
            "subcategory":"Cleaning & Sanitation",
            "type":"Services"
        }
    ],
    "sg:phone":"+32 13 77 62 32",
    "sg:postcode":"3201",
    "sg:province":"Vlaams-Brabant",
    "sg:tags":[
        "fa\u00e7ade",
        "maintenance"
    ],
    "wof:name":"Kubex Bvba",
    "wof:placetype":"venue"
},
  "geometry": {"coordinates":[4.9191789627,51.0271873474],"type":"Point"}
}