{
  "type": "Feature",
  "properties": {
    "iso:country":"BE",
    "sg:address":"Burg. L. Pussemierstraat 84",
    "sg:city":"Eeklo",
    "sg:classifiers":[
        {
            "category":"Personal",
            "subcategory":"Beauty Salon",
            "type":"Services"
        }
    ],
    "sg:phone":"+32 9 377 61 64",
    "sg:postcode":"9900",
    "sg:province":"Oost-Vlaanderen",
    "sg:tags":[
        "de",
        "coiffure"
    ],
    "wof:name":"Coiffure Veronique",
    "wof:placetype":"venue"
},
  "geometry": {"coordinates":[3.5763831139,51.1864547729],"type":"Point"}
}