{
  "type": "Feature",
  "properties": {
    "iso:country":"BE",
    "sg:address":"Spelaanstraat 35",
    "sg:city":"Zottegem",
    "sg:orig_category":"Editeurs de journaux. Editeurs de revues and p\u00e9riodiques",
    "sg:phone":"+32 9 360 52 24",
    "sg:postcode":"9620",
    "sg:province":"Oost-Vlaanderen",
    "wof:name":"Stephan Montsaert",
    "wof:placetype":"venue"
},
  "geometry": {"coordinates":[3.8112111092,50.871181488],"type":"Point"}
}