{
  "type": "Feature",
  "properties": {
    "iso:country":"BE",
    "sg:address":"Rue D\u00b4oth\u00c9e 27",
    "sg:city":"Ans",
    "sg:orig_category":"Quincailleries. Electrom\u00e9nager, t\u00e9l\u00e9visions and radios",
    "sg:phone":"+32 4 239 00 69",
    "sg:postcode":"4432",
    "sg:province":"Li\u00e8ge",
    "wof:name":"Spinoy & Fils",
    "wof:placetype":"venue"
},
  "geometry": {"coordinates":[5.534350872,50.6638259888],"type":"Point"}
}