{
  "type": "Feature",
  "properties": {
    "iso:country":"BE",
    "sg:address":"Chauss\u00e9e De Louvain 871",
    "sg:city":"Bruxelles (evere)",
    "sg:classifiers":[
        {
            "category":"Bakery",
            "type":"Food & Drink"
        }
    ],
    "sg:phone":"+32 2 726 75 35",
    "sg:postcode":"1140",
    "sg:province":"Bruxelles-Capitale",
    "sg:tags":[
        "confectioner",
        "baker"
    ],
    "wof:name":"Jacobs R",
    "wof:placetype":"venue"
},
  "geometry": {"coordinates":[4.4169697762,50.8598442078],"type":"Point"}
}