{
  "type": "Feature",
  "properties": {
    "addr:full":"Pieter Van Gentstraat 12 Lokeren Oost-Vlaanderen 9160",
    "addr:housenumber":"12",
    "addr:postcode":"9160",
    "addr:street":"Pieter Van Gentstraat",
    "iso:country":"BE",
    "sg:address":"Pieter Van Gentstraat 12",
    "sg:city":"Lokeren",
    "sg:orig_category":"Pain, p\u00e2tisseries and confiseries",
    "sg:phone":"+32 9 348 25 67",
    "sg:postcode":"9160",
    "sg:province":"Oost-Vlaanderen",
    "wof:name":"Koen Versele",
    "wof:placetype":"venue"
},
  "geometry": {"coordinates":[3.9497261047,51.1172981262],"type":"Point"}
}