{
  "type": "Feature",
  "properties": {
    "iso:country":"BE",
    "sg:address":"Heidestraat 8",
    "sg:city":"Kortenaken",
    "sg:orig_category":"Fruitteelt",
    "sg:phone":"+32 11 58 81 06",
    "sg:postcode":"3470",
    "sg:province":"Vlaams-Brabant",
    "wof:name":"Lemmens Paul & Gert",
    "wof:placetype":"venue"
},
  "geometry": {"coordinates":[5.0775132179,50.9059143066],"type":"Point"}
}