{
  "type": "Feature",
  "properties": {
    "iso:country":"BE",
    "sg:address":"Neerstraat 25",
    "sg:city":"Brakel (nederbrakel)",
    "sg:classifiers":[
        {
            "category":"Professional",
            "subcategory":"Credit Reporting & Collection",
            "type":"Services"
        }
    ],
    "sg:phone":"+32 55 42 03 33",
    "sg:postcode":"9660",
    "sg:province":"Oost-Vlaanderen",
    "sg:tags":[
        "bailiff"
    ],
    "wof:name":"Verschelden B",
    "wof:placetype":"venue"
},
  "geometry": {"coordinates":[3.7661290169,50.8043365479],"type":"Point"}
}