{
  "type": "Feature",
  "properties": {
    "iso:country":"BE",
    "sg:address":"Gelaagstraat 53",
    "sg:city":"Kruibeke (rupelmonde)",
    "sg:classifiers":[
        {
            "category":"Manufacturing",
            "subcategory":"Signs",
            "type":"Manufacturing & Wholesale Goods"
        }
    ],
    "sg:phone":"+32 3 740 09 00",
    "sg:postcode":"9150",
    "sg:province":"Oost-Vlaanderen",
    "sg:tags":[
        "-",
        "illuminated"
    ],
    "wof:name":"Open Nv",
    "wof:placetype":"venue"
},
  "geometry": {"coordinates":[4.2864518166,51.1254348755],"type":"Point"}
}