{
  "type": "Feature",
  "properties": {
    "addr:full":"Gentsestraat 31 Ninove Oost-Vlaanderen 9400",
    "addr:housenumber":"31",
    "addr:postcode":"9400",
    "addr:street":"Gentsestraat",
    "iso:country":"BE",
    "sg:address":"Gentsestraat 31",
    "sg:city":"Ninove",
    "sg:orig_category":"Quincailleries. Bois Gr",
    "sg:phone":"+32 54 32 20 53",
    "sg:postcode":"9400",
    "sg:province":"Oost-Vlaanderen",
    "wof:name":"Publi-six",
    "wof:placetype":"venue"
},
  "geometry": {"coordinates":[4.0131001472,50.8378791809],"type":"Point"}
}