{
  "type": "Feature",
  "properties": {
    "addr:full":"Rue Des Combattants 4c Tournai (barry - Maulde) Hainaut 7534",
    "addr:housenumber":"4c",
    "addr:postcode":"7534",
    "addr:street":"Rue Des Combattants",
    "iso:country":"BE",
    "sg:address":"Rue Des Combattants 4c",
    "sg:city":"Tournai (barry - Maulde)",
    "sg:classifiers":[
        {
            "category":"Health Services",
            "subcategory":"Doctor",
            "type":"Services"
        }
    ],
    "sg:phone":"+32 69 54 59 04",
    "sg:postcode":"7534",
    "sg:province":"Hainaut",
    "sg:tags":[
        "medicinephysicians",
        "surgeon"
    ],
    "wof:name":"Locufier J-l",
    "wof:placetype":"venue"
},
  "geometry": {"coordinates":[3.5431890488,50.5878715515],"type":"Point"}
}