{
  "type": "Feature",
  "properties": {
    "addr:full":"Bosquet De L'welle 14 Tournai (froyennes) Hainaut 7503",
    "addr:housenumber":"14",
    "addr:postcode":"7503",
    "addr:street":"Bosquet;Tournai Froyennes Hainaut",
    "iso:country":"BE",
    "sg:address":"Bosquet De L'welle 14",
    "sg:city":"Tournai (froyennes)",
    "sg:classifiers":[
        {
            "category":"Health Services",
            "subcategory":"Doctor",
            "type":"Services"
        }
    ],
    "sg:phone":"+32 69 23 24 93",
    "sg:postcode":"7503",
    "sg:province":"Hainaut",
    "sg:tags":[
        "medicinephysicians",
        "surgeon"
    ],
    "wof:name":"Bataille S",
    "wof:placetype":"venue"
},
  "geometry": {"coordinates":[3.3503820896,50.6267471313],"type":"Point"}
}