{
  "type": "Feature",
  "properties": {
    "iso:country":"BE",
    "sg:address":"Moeskroenstraat 46",
    "sg:city":"Menen",
    "sg:classifiers":[
        {
            "category":"Personal",
            "subcategory":"Beauty Salon",
            "type":"Services"
        }
    ],
    "sg:phone":"+32 56 51 33 65",
    "sg:postcode":"8930",
    "sg:province":"West-Vlaanderen",
    "sg:tags":[
        "lady",
        "-",
        "hairdressing"
    ],
    "wof:name":"Onraedt M",
    "wof:placetype":"venue"
},
  "geometry": {"coordinates":[3.1291370392,50.7874794006],"type":"Point"}
}