{
  "type": "Feature",
  "properties": {
    "addr:full":"Avenue De L' Europe 32 Courcelles Hainaut 6183",
    "addr:housenumber":"32",
    "addr:postcode":"6183",
    "addr:street":"Avenue De L ' Europe",
    "iso:country":"BE",
    "sg:address":"Avenue De L' Europe 32",
    "sg:city":"Courcelles",
    "sg:orig_category":"Diverse grafische activiteiten",
    "sg:phone":"+32 71 46 42 31",
    "sg:postcode":"6183",
    "sg:province":"Hainaut",
    "wof:name":"E. Louette",
    "wof:placetype":"venue"
},
  "geometry": {"coordinates":[4.3333468437,50.4646034241],"type":"Point"}
}