{
  "type": "Feature",
  "properties": {
    "iso:country":"BE",
    "sg:address":"Koben Geertsstraat 44bb",
    "sg:city":"Beveren",
    "sg:orig_category":"Eclairage et \u00e9quipements du foyer",
    "sg:phone":"+32 3 755 18 79",
    "sg:postcode":"9120",
    "sg:province":"Oost-Vlaanderen",
    "wof:name":"Christi Decor",
    "wof:placetype":"venue"
},
  "geometry": {"coordinates":[4.2501168251,51.217830658],"type":"Point"}
}