{
  "type": "Feature",
  "properties": {
    "addr:full":"Domaine De L'espinette 50 Wepion Namur 5100",
    "addr:housenumber":"50",
    "addr:postcode":"5100",
    "addr:street":"Wepion Namur",
    "iso:country":"BE",
    "sg:address":"Domaine De L'espinette 50",
    "sg:city":"Wepion",
    "sg:classifiers":[
        {
            "category":"Health Services",
            "subcategory":"Health Practitioner",
            "type":"Services"
        }
    ],
    "sg:phone":"+32 81 47 03 47",
    "sg:postcode":"5100",
    "sg:province":"Namur",
    "sg:tags":[
        "physiotherapist"
    ],
    "wof:name":"St\u00e9phenne M. C\u00e9cile",
    "wof:placetype":"venue"
},
  "geometry": {"coordinates":[4.8593258858,50.4300308228],"type":"Point"}
}