{
  "type": "Feature",
  "properties": {
    "iso:country":"BE",
    "sg:address":"Zagerijstraat 1a",
    "sg:city":"Grobbendonk",
    "sg:classifiers":[
        {
            "category":"Personal",
            "subcategory":"Beauty Salon",
            "type":"Services"
        }
    ],
    "sg:phone":"+32 14 50 26 09",
    "sg:postcode":"2280",
    "sg:province":"Antwerpen",
    "wof:name":"Claudia Nieviendick",
    "wof:placetype":"venue"
},
  "geometry": {"coordinates":[4.7141160965,51.1685028076],"type":"Point"}
}