{
  "type": "Feature",
  "properties": {
    "iso:country":"BE",
    "sg:address":"Genutstraat 31",
    "sg:city":"Bilzen",
    "sg:orig_category":"Babyspullen",
    "sg:phone":"+32 89 79 14 19",
    "sg:postcode":"3740",
    "sg:province":"Limburg",
    "wof:name":"Huis Gaminneke",
    "wof:placetype":"venue"
},
  "geometry": {"coordinates":[5.5148048401,50.8720970154],"type":"Point"}
}