{
  "type": "Feature",
  "properties": {
    "iso:country":"BE",
    "sg:address":"Vrijbosstraat 6",
    "sg:city":"Staden",
    "sg:orig_category":"Groententeelt",
    "sg:phone":"+32 51 70 52 11",
    "sg:postcode":"8840",
    "sg:province":"West-Vlaanderen",
    "wof:name":"Carine De Burghgraeve",
    "wof:placetype":"venue"
},
  "geometry": {"coordinates":[2.9728701115,50.9734649658],"type":"Point"}
}