{
  "type": "Feature",
  "properties": {
    "iso:country":"BE",
    "sg:address":"Stationstraat 51",
    "sg:city":"Moeskroen/mouscron",
    "sg:orig_category":"Levering aan huis restaurants",
    "sg:phone":"+32 56 84 36 56",
    "sg:postcode":"7700",
    "sg:province":"Hainaut",
    "wof:name":"Pizza Alvolo",
    "wof:placetype":"venue"
},
  "geometry": {"coordinates":[3.2323200703,50.7400932312],"type":"Point"}
}