{
  "type": "Feature",
  "properties": {
    "iso:country":"BE",
    "sg:address":"Middenweg 13",
    "sg:city":"Izegem",
    "sg:classifiers":[
        {
            "category":"Personal",
            "subcategory":"Beauty Salon",
            "type":"Services"
        }
    ],
    "sg:phone":"+32 51 30 30 28",
    "sg:postcode":"8870",
    "sg:province":"West-Vlaanderen",
    "sg:tags":[
        "lady",
        "-",
        "hairdressing"
    ],
    "wof:name":"Caresse",
    "wof:placetype":"venue"
},
  "geometry": {"coordinates":[3.2014970779,50.9191703796],"type":"Point"}
}