{
  "type": "Feature",
  "properties": {
    "addr:full":"Kerkstraat 37 Kuurne West-Vlaanderen 8520",
    "addr:housenumber":"37",
    "addr:postcode":"8520",
    "addr:street":"Kerkstraat",
    "iso:country":"BE",
    "sg:address":"Kerkstraat 37",
    "sg:city":"Kuurne",
    "sg:classifiers":[
        {
            "category":"Manufacturing",
            "subcategory":"Textiles",
            "type":"Manufacturing & Wholesale Goods"
        }
    ],
    "sg:phone":"+32 56 70 23 81",
    "sg:postcode":"8520",
    "sg:province":"West-Vlaanderen",
    "wof:name":"Huis Thalita",
    "wof:placetype":"venue"
},
  "geometry": {"coordinates":[3.286716938,50.8531494141],"type":"Point"}
}