{
  "type": "Feature",
  "properties": {
    "addr:full":"Boulevard D\u00b4avroy 190 - 1er \u00c9tage Liege-centre Li\u00e8ge 4000",
    "addr:housenumber":"190",
    "addr:postcode":"1er;4000",
    "addr:street":"Boulevard D\u00b4Avroy;Liege-Centre",
    "iso:country":"BE",
    "sg:address":"Boulevard D\u00b4avroy 190 - 1er \u00c9tage",
    "sg:city":"Liege-centre",
    "sg:orig_category":"Clubs de sport. Salles de billard and snooker",
    "sg:phone":"+32 4 222 01 34",
    "sg:postcode":"4000",
    "sg:province":"Li\u00e8ge",
    "wof:name":"Centre De Billard D'avroy",
    "wof:placetype":"venue"
},
  "geometry": {"coordinates":[6.2250900269,44.0888595581],"type":"Point"}
}