{
  "type": "Feature",
  "properties": {
    "addr:full":"Rue Des D\u00e9port\u00e9s 79 Box 3a Arlon Luxembourg 6700",
    "addr:housenumber":"79;3a",
    "addr:postcode":"6700",
    "addr:street":"Rue Des De\u0301Porte\u0301S;Box",
    "iso:country":"BE",
    "sg:address":"Rue Des D\u00e9port\u00e9s 79 Box 3a",
    "sg:city":"Arlon",
    "sg:classifiers":[
        {
            "category":"Organizations",
            "subcategory":"Professional Association",
            "type":"Services"
        }
    ],
    "sg:phone":"+32 63 24 25 35",
    "sg:postcode":"6700",
    "sg:province":"Luxembourg",
    "sg:tags":[
        "trade-union",
        "federation"
    ],
    "wof:name":"Comit\u00e9 Subregional De L'emploi Et De La Formation Du Luxembourg Belge",
    "wof:placetype":"venue"
},
  "geometry": {"coordinates":[5.8126749992,49.6823234558],"type":"Point"}
}