{
  "type": "Feature",
  "properties": {
    "addr:full":"Hoenderstraat 59a Wuustwezel Antwerpen 2990",
    "addr:housenumber":"59a",
    "addr:postcode":"2990",
    "addr:street":"Hoenderstraat",
    "iso:country":"BE",
    "sg:address":"Hoenderstraat 59a",
    "sg:city":"Wuustwezel",
    "sg:classifiers":[
        {
            "category":"Landmark",
            "subcategory":"Marketplace",
            "type":"Public Place"
        }
    ],
    "sg:phone":"+32 3 313 49 28",
    "sg:postcode":"2990",
    "sg:province":"Antwerpen",
    "sg:tags":[
        "commerce",
        "gr",
        "equipement",
        "de",
        "pour",
        "divers",
        "biens",
        "location",
        "diver"
    ],
    "wof:name":"Attraktieh-verhuur Jan Bogaerts",
    "wof:placetype":"venue"
},
  "geometry": {"coordinates":[4.6887907982,51.3820610046],"type":"Point"}
}