{
  "type": "Feature",
  "properties": {
    "addr:full":"Rue Du Boeuf 3 Florenville (fontenoille) Luxembourg 6820",
    "addr:housenumber":"3",
    "addr:postcode":"6820",
    "addr:street":"Rue Du Boeuf",
    "iso:country":"BE",
    "sg:address":"Rue Du Boeuf 3",
    "sg:city":"Florenville (fontenoille)",
    "sg:classifiers":[
        {
            "category":"Utilities",
            "subcategory":"Fuel Oil & Lpg",
            "type":"Services"
        }
    ],
    "sg:phone":"+32 61 31 42 27",
    "sg:postcode":"6820",
    "sg:province":"Luxembourg",
    "wof:name":"Thomas Combustibles Sprl",
    "wof:placetype":"venue"
},
  "geometry": {"coordinates":[5.2311258316,49.7152748108],"type":"Point"}
}