{
  "type": "Feature",
  "properties": {
    "addr:full":"Rue De Marchienne 187 Montigny-le-tilleul Hainaut 6110",
    "addr:housenumber":"187",
    "addr:postcode":"6110",
    "addr:street":"Rue De Marchienne",
    "iso:country":"BE",
    "sg:address":"Rue De Marchienne 187",
    "sg:city":"Montigny-le-tilleul",
    "sg:classifiers":[
        {
            "category":"Professional",
            "subcategory":"Accounting & Tax Preparation",
            "type":"Services"
        }
    ],
    "sg:phone":"+32 71 51 16 83",
    "sg:postcode":"6110",
    "sg:province":"Hainaut",
    "sg:tags":[
        "bookkeeper"
    ],
    "wof:name":"Schoote B",
    "wof:placetype":"venue"
},
  "geometry": {"coordinates":[4.3837661743,50.3869018555],"type":"Point"}
}