{
  "type": "Feature",
  "properties": {
    "addr:full":"Rue Hors-ch\u00c2teau 33 Li\u00c8ge Li\u00e8ge 4000",
    "addr:housenumber":"33",
    "addr:postcode":"4000",
    "addr:street":"Rue Hors-Cha\u0302Teau",
    "iso:country":"BE",
    "sg:address":"Rue Hors-ch\u00c2teau 33",
    "sg:city":"Li\u00c8ge",
    "sg:orig_category":"M\u00e9decins and sp\u00e9cialistes",
    "sg:phone":"+32 4 223 55 96",
    "sg:postcode":"4000",
    "sg:province":"Li\u00e8ge",
    "wof:name":"Bernard Daco",
    "wof:placetype":"venue"
},
  "geometry": {"coordinates":[5.5798039436,50.6475219727],"type":"Point"}
}