{
  "type": "Feature",
  "properties": {
    "addr:full":"Stationsstraat 5 Diepenbeek Limburg 3590",
    "addr:housenumber":"5",
    "addr:postcode":"3590",
    "addr:street":"Stationsstraat",
    "iso:country":"BE",
    "sg:address":"Stationsstraat 5",
    "sg:city":"Diepenbeek",
    "sg:orig_category":"M\u00e9decins and sp\u00e9cialistes",
    "sg:phone":"+32 11 32 39 06",
    "sg:postcode":"3590",
    "sg:province":"Limburg",
    "wof:name":"J. Auwerx",
    "wof:placetype":"venue"
},
  "geometry": {"coordinates":[5.4193639755,50.9094924927],"type":"Point"}
}