{
  "type": "Feature",
  "properties": {
    "addr:full":"Volpenswege 16 Evergem Oost-Vlaanderen 9940",
    "addr:housenumber":"16",
    "addr:postcode":"9940",
    "addr:street":"Volpenswege;Oost-Vlaanderen",
    "iso:country":"BE",
    "sg:address":"Volpenswege 16",
    "sg:city":"Evergem",
    "sg:orig_category":"Herstellingen and onderhoud van auto's",
    "sg:phone":"+32 9 357 78 03",
    "sg:postcode":"9940",
    "sg:province":"Oost-Vlaanderen",
    "wof:name":"Geert Caboor",
    "wof:placetype":"venue"
},
  "geometry": {"coordinates":[3.6955280304,51.1462287903],"type":"Point"}
}