{
  "type": "Feature",
  "properties": {
    "iso:country":"BE",
    "sg:address":"Chauss\u00c9e De Ninove 500",
    "sg:city":"Anderlecht",
    "sg:orig_category":"Supermarkten",
    "sg:phone":"+32 2 520 94 20",
    "sg:postcode":"1070",
    "sg:province":"Bruxelles-Capitale",
    "wof:name":"Match",
    "wof:placetype":"venue"
},
  "geometry": {"coordinates":[4.306497097,50.8474121094],"type":"Point"}
}