{
  "type": "Feature",
  "properties": {
    "iso:country":"BE",
    "sg:address":"Burgemeester De Lausnaystraat 7",
    "sg:city":"Berlare (overmere)",
    "sg:classifiers":[
        {
            "category":"Banks & Credit Unions",
            "subcategory":"Bank",
            "type":"Services"
        }
    ],
    "sg:phone":"+32 9 367 93 38",
    "sg:postcode":"9290",
    "sg:province":"Oost-Vlaanderen",
    "sg:tags":[
        "savings-banks"
    ],
    "wof:name":"An Blancquaert Zakenkantoor Bvba",
    "wof:placetype":"venue"
},
  "geometry": {"coordinates":[4.005710125,51.0165214539],"type":"Point"}
}