{
  "type": "Feature",
  "properties": {
    "addr:full":"Avenue Du Commerce 21 Enghien (petit-enghien) Hainaut 7850",
    "addr:housenumber":"21",
    "addr:postcode":"7850",
    "addr:street":"Avenue Du Commerce",
    "iso:country":"BE",
    "sg:address":"Avenue Du Commerce 21",
    "sg:city":"Enghien (petit-enghien)",
    "sg:classifiers":[
        {
            "category":"Manufacturing",
            "subcategory":"Furniture",
            "type":"Manufacturing & Wholesale Goods"
        }
    ],
    "sg:phone":"+32 2 395 56 60",
    "sg:postcode":"7850",
    "sg:province":"Hainaut",
    "sg:tags":[
        "made",
        "-",
        "custom"
    ],
    "wof:name":"Bahutier (au)",
    "wof:placetype":"venue"
},
  "geometry": {"coordinates":[4.0509500504,50.7014961243],"type":"Point"}
}