{
  "type": "Feature",
  "properties": {
    "iso:country":"BE",
    "sg:address":"Schuurstraat 76",
    "sg:city":"Gent",
    "sg:orig_category":"Activit\u00e9s diverses d'imprimerie. Imprimeries and copyshops",
    "sg:phone":"+32 9 228 88 53",
    "sg:postcode":"9040",
    "sg:province":"Oost-Vlaanderen",
    "wof:name":"Drukkerij Van Buyten",
    "wof:placetype":"venue"
},
  "geometry": {"coordinates":[3.7768828869,51.0707893372],"type":"Point"}
}