{
  "type": "Feature",
  "properties": {
    "addr:full":"Rue Grande 46 Qui\u00c9vrain Hainaut 7380",
    "addr:housenumber":"46",
    "addr:postcode":"7380",
    "addr:street":"Rue Grande",
    "iso:country":"BE",
    "sg:address":"Rue Grande 46",
    "sg:city":"Qui\u00c9vrain",
    "sg:orig_category":"Dameskledingzaken",
    "sg:phone":"+32 65 45 71 51",
    "sg:postcode":"7380",
    "sg:province":"Hainaut",
    "wof:name":"Fran\u00c7oise Glaude",
    "wof:placetype":"venue"
},
  "geometry": {"coordinates":[3.6825020313,50.4061775208],"type":"Point"}
}