{
  "type": "Feature",
  "properties": {
    "addr:full":"Voie De Li\u00c8ge 39 Chaudfontaine Li\u00e8ge 4053",
    "addr:housenumber":"39",
    "addr:postcode":"4053",
    "addr:street":"Voie De Lie\u0300Ge",
    "iso:country":"BE",
    "sg:address":"Voie De Li\u00c8ge 39",
    "sg:city":"Chaudfontaine",
    "sg:orig_category":"Artsen and specialisten",
    "sg:phone":"+32 4 365 07 85",
    "sg:postcode":"4053",
    "sg:province":"Li\u00e8ge",
    "wof:name":"Jean-fran\u00c7ois Weekers",
    "wof:placetype":"venue"
},
  "geometry": {"coordinates":[5.6159381866,50.5945091248],"type":"Point"}
}