{
  "type": "Feature",
  "properties": {
    "iso:country":"BE",
    "sg:address":"Diamantstraat 8",
    "sg:city":"Antwerpen",
    "sg:orig_category":"Reclamebureaus",
    "sg:phone":"+32 3 216 38 82",
    "sg:postcode":"2018",
    "sg:province":"Antwerpen",
    "wof:name":"Bureau Textory",
    "wof:placetype":"venue"
},
  "geometry": {"coordinates":[4.3967142105,51.2049179077],"type":"Point"}
}