{
  "type": "Feature",
  "properties": {
    "addr:full":"Molenstraat 31 Torhout West-Vlaanderen 8820",
    "addr:housenumber":"31",
    "addr:postcode":"8820",
    "addr:street":"Molenstraat",
    "iso:country":"BE",
    "sg:address":"Molenstraat 31",
    "sg:city":"Torhout",
    "sg:orig_category":"Installation de menuiserie en bois and plastique",
    "sg:phone":"+32 50 21 29 10",
    "sg:postcode":"8820",
    "sg:province":"West-Vlaanderen",
    "wof:name":"Deketelaere Gebrs",
    "wof:placetype":"venue"
},
  "geometry": {"coordinates":[3.0863609314,51.0636444092],"type":"Point"}
}