{
  "type": "Feature",
  "properties": {
    "addr:full":"Boerenkrijglaan 25 Ranst Antwerpen 2520",
    "addr:housenumber":"25",
    "addr:postcode":"2520",
    "addr:street":"Boerenkrijglaan",
    "iso:country":"BE",
    "sg:address":"Boerenkrijglaan 25",
    "sg:city":"Ranst",
    "sg:orig_category":"Dierentuinen, botanische tuinen, sterrenwachten and natuurreservaten Instellingen voor mindervalide ",
    "sg:phone":"+32 3 350 28 11",
    "sg:postcode":"2520",
    "sg:province":"Antwerpen",
    "wof:name":"Zevenbergen",
    "wof:placetype":"venue"
},
  "geometry": {"coordinates":[4.5517802238,51.1984138489],"type":"Point"}
}