{
  "type": "Feature",
  "properties": {
    "iso:country":"BE",
    "sg:address":"Rue Du Bout 8",
    "sg:city":"Ouffet",
    "sg:orig_category":"Beautyfarms, relaxatie and lichamelijk welzijn Schoonheidssalons",
    "sg:phone":"+32 86 36 73 51",
    "sg:postcode":"4590",
    "sg:province":"Li\u00e8ge",
    "wof:name":"Les Beaut\u00c9s D\u00b4ath\u00c9na",
    "wof:placetype":"venue"
},
  "geometry": {"coordinates":[5.462266922,50.4361686707],"type":"Point"}
}