{
  "type": "Feature",
  "properties": {
    "addr:full":"Hasseltsesteenweg Kortessem Limburg 3720",
    "addr:postcode":"3720",
    "addr:street":"Hasseltsesteenweg",
    "iso:country":"BE",
    "sg:address":"Hasseltsesteenweg",
    "sg:city":"Kortessem",
    "sg:classifiers":[
        {
            "category":"Utilities",
            "subcategory":"Recycling",
            "type":"Services"
        }
    ],
    "sg:phone":"+32 11 37 91 10",
    "sg:postcode":"3720",
    "sg:province":"Limburg",
    "wof:name":"Gielen Recyclage",
    "wof:placetype":"venue"
},
  "geometry": {"coordinates":[5.3865947723,50.857673645],"type":"Point"}
}