{
  "type": "Feature",
  "properties": {
    "addr:full":"Onze Lieve Vrouwlaan 88 Evere Bruxelles-Capitale 1140",
    "addr:housenumber":"88",
    "addr:postcode":"1140",
    "addr:street":"Onze Lieve Vrouwlaan",
    "iso:country":"BE",
    "sg:address":"Onze Lieve Vrouwlaan 88",
    "sg:city":"Evere",
    "sg:orig_category":"Alternatieve geneeskunde",
    "sg:phone":"+32 2 216 84 77",
    "sg:postcode":"1140",
    "sg:province":"Bruxelles-Capitale",
    "wof:name":"S. Jacobs",
    "wof:placetype":"venue"
},
  "geometry": {"coordinates":[4.3993668556,50.8708648682],"type":"Point"}
}