{
  "type": "Feature",
  "properties": {
    "addr:full":"Esenweg 157 Diksmuide West-Vlaanderen 8600",
    "addr:housenumber":"157",
    "addr:postcode":"8600",
    "iso:country":"BE",
    "sg:address":"Esenweg 157",
    "sg:city":"Diksmuide",
    "sg:orig_category":"Banques and organismes de cr\u00e9dit",
    "sg:phone":"+32 51 50 17 89",
    "sg:postcode":"8600",
    "sg:province":"West-Vlaanderen",
    "wof:name":"Kbc",
    "wof:placetype":"venue"
},
  "geometry": {"coordinates":[2.8822650909,51.0304870605],"type":"Point"}
}