{
  "type": "Feature",
  "properties": {
    "iso:country":"BE",
    "sg:address":"Charles Andrieslaan 3",
    "sg:city":"Gent",
    "sg:orig_category":"Postkantoren Verzekeringsmakelaars and experts",
    "sg:phone":"+32 9 225 29 81",
    "sg:postcode":"9000",
    "sg:province":"Oost-Vlaanderen",
    "wof:name":"De Post",
    "wof:placetype":"venue"
},
  "geometry": {"coordinates":[3.706058979,51.0490837097],"type":"Point"}
}