{
  "type": "Feature",
  "properties": {
    "iso:country":"BE",
    "sg:address":"Oscar Van Kesbeeckstraat 43",
    "sg:city":"Mechelen",
    "sg:classifiers":[
        {
            "category":"Arena",
            "subcategory":"Sports Club",
            "type":"Entertainment"
        }
    ],
    "sg:phone":"+32 15 20 08 20",
    "sg:postcode":"2800",
    "sg:province":"Antwerpen",
    "wof:name":"K R C Mechelen",
    "wof:placetype":"venue"
},
  "geometry": {"coordinates":[4.4726471901,51.0386657715],"type":"Point"}
}