{
  "type": "Feature",
  "properties": {
    "addr:full":"Sint-niklaasstraat 8 Diksmuide West-Vlaanderen 8600",
    "addr:housenumber":"8",
    "addr:postcode":"8600",
    "addr:street":"Sint-Niklaasstraat",
    "iso:country":"BE",
    "sg:address":"Sint-niklaasstraat 8",
    "sg:city":"Diksmuide",
    "sg:classifiers":[
        {
            "category":"Real Estate",
            "subcategory":"Architect",
            "type":"Services"
        }
    ],
    "sg:phone":"+32 51 55 54 64",
    "sg:postcode":"8600",
    "sg:province":"West-Vlaanderen",
    "wof:name":"Logier T",
    "wof:placetype":"venue"
},
  "geometry": {"coordinates":[2.8645761013,51.0347862244],"type":"Point"}
}