{
  "type": "Feature",
  "properties": {
    "iso:country":"BE",
    "sg:address":"Chauss\u00e9e De Hannut 150",
    "sg:city":"Jodoigne",
    "sg:classifiers":[
        {
            "category":"Bars & Pubs",
            "type":"Food & Drink"
        }
    ],
    "sg:phone":"+32 10 81 10 95",
    "sg:postcode":"1370",
    "sg:province":"Brabant Wallon",
    "wof:name":"Chant Des Oiseaux",
    "wof:placetype":"venue"
},
  "geometry": {"coordinates":[4.8834900856,50.718460083],"type":"Point"}
}