{
  "type": "Feature",
  "properties": {
    "addr:full":"Rue De L'automne 59 Bruxelles (ixelles) Bruxelles-Capitale 1050",
    "addr:housenumber":"59",
    "addr:postcode":"1050",
    "addr:street":"Rue De L'Automne",
    "iso:country":"BE",
    "sg:address":"Rue De L'automne 59",
    "sg:city":"Bruxelles (ixelles)",
    "sg:classifiers":[
        {
            "category":"Professional",
            "subcategory":"Lawyer & Legal Services",
            "type":"Services"
        }
    ],
    "sg:phone":"+32 2 639 62 66",
    "sg:postcode":"1050",
    "sg:province":"Bruxelles-Capitale",
    "wof:name":"Bollen Rudi",
    "wof:placetype":"venue"
},
  "geometry": {"coordinates":[4.390173912,50.8197593689],"type":"Point"}
}