{
  "type": "Feature",
  "properties": {
    "addr:full":"Markt 77 Geel Antwerpen 2440",
    "addr:housenumber":"77",
    "addr:postcode":"2440",
    "addr:street":"Markt",
    "iso:country":"BE",
    "sg:address":"Markt 77",
    "sg:city":"Geel",
    "sg:classifiers":[
        {
            "category":"Bars & Pubs",
            "type":"Food & Drink"
        }
    ],
    "sg:phone":"+32 14 58 06 48",
    "sg:postcode":"2440",
    "sg:province":"Antwerpen",
    "wof:name":"Brasserie De Post",
    "wof:placetype":"venue"
},
  "geometry": {"coordinates":[4.989798069,51.1608810425],"type":"Point"}
}