{
  "type": "Feature",
  "properties": {
    "addr:full":"Parc D'avroy 1 Li\u00c8ge Li\u00e8ge 4000",
    "addr:housenumber":"1",
    "addr:postcode":"4000",
    "addr:street":"D'Avroy",
    "iso:country":"BE",
    "sg:address":"Parc D'avroy 1",
    "sg:city":"Li\u00c8ge",
    "sg:orig_category":"Caf\u00e9s. Salles de spectacles",
    "sg:phone":"+32 4 222 32 95",
    "sg:postcode":"4000",
    "sg:province":"Li\u00e8ge",
    "wof:name":"Creahm",
    "wof:placetype":"venue"
},
  "geometry": {"coordinates":[5.5707540512,50.6407737732],"type":"Point"}
}