{
  "type": "Feature",
  "properties": {
    "addr:full":"Frambozenstraat 14 Hasselt Limburg 3511",
    "addr:housenumber":"14",
    "addr:postcode":"3511",
    "addr:street":"Frambozenstraat",
    "iso:country":"BE",
    "sg:address":"Frambozenstraat 14",
    "sg:city":"Hasselt",
    "sg:orig_category":"Artsen and specialisten",
    "sg:phone":"+32 11 25 68 29",
    "sg:postcode":"3511",
    "sg:province":"Limburg",
    "wof:name":"An De Cuyper",
    "wof:placetype":"venue"
},
  "geometry": {"coordinates":[5.316491127,50.9504241943],"type":"Point"}
}