{
  "type": "Feature",
  "properties": {
    "addr:full":"Vennensdreef 1 Meulebeke West-Vlaanderen 8760",
    "addr:housenumber":"1",
    "addr:postcode":"8760",
    "addr:street":"Vennensdreef",
    "iso:country":"BE",
    "sg:address":"Vennensdreef 1",
    "sg:city":"Meulebeke",
    "sg:orig_category":"Installation de menuiserie en bois and plastique",
    "sg:phone":"+32 51 48 92 30",
    "sg:postcode":"8760",
    "sg:province":"West-Vlaanderen",
    "wof:name":"J. V. H.",
    "wof:placetype":"venue"
},
  "geometry": {"coordinates":[3.2440760136,50.9546699524],"type":"Point"}
}