{
  "type": "Feature",
  "properties": {
    "addr:full":"Jan Borluutstraat 13 Harelbeke West-Vlaanderen 8530",
    "addr:housenumber":"13",
    "addr:postcode":"8530",
    "addr:street":"Borluutstraat",
    "iso:country":"BE",
    "sg:address":"Jan Borluutstraat 13",
    "sg:city":"Harelbeke",
    "sg:orig_category":"Assurances. Banques and organismes de cr\u00e9dit",
    "sg:phone":"+32 56 71 45 88",
    "sg:postcode":"8530",
    "sg:province":"West-Vlaanderen",
    "wof:name":"Pattyn",
    "wof:placetype":"venue"
},
  "geometry": {"coordinates":[3.2995159626,50.844909668],"type":"Point"}
}