{
  "type": "Feature",
  "properties": {
    "iso:country":"BE",
    "sg:address":"Rue Victor Delporte 8",
    "sg:city":"Dour",
    "sg:orig_category":"Experts-comptables",
    "sg:phone":"+32 65 65 53 19",
    "sg:postcode":"7370",
    "sg:province":"Hainaut",
    "wof:name":"Jean-pierre Hanse",
    "wof:placetype":"venue"
},
  "geometry": {"coordinates":[3.783272028,50.3949623108],"type":"Point"}
}