{
  "type": "Feature",
  "properties": {
    "addr:full":"Rue Regni\u00c9-durette 11 Namur Namur 5101",
    "addr:housenumber":"11",
    "addr:postcode":"5101",
    "addr:street":"Rue Regnie\u0301-Durette",
    "iso:country":"BE",
    "sg:address":"Rue Regni\u00c9-durette 11",
    "sg:city":"Namur",
    "sg:orig_category":"Boekhouders",
    "sg:phone":"+32 81 31 24 97",
    "sg:postcode":"5101",
    "sg:province":"Namur",
    "wof:name":"T. Raickman",
    "wof:placetype":"venue"
},
  "geometry": {"coordinates":[4.9065480232,50.4519577026],"type":"Point"}
}