{
  "type": "Feature",
  "properties": {
    "iso:country":"BE",
    "sg:address":"'t Lo 100",
    "sg:city":"Hamont-achel",
    "sg:orig_category":"Dierenartsen",
    "sg:phone":"+32 11 44 52 37",
    "sg:postcode":"3930",
    "sg:province":"Limburg",
    "wof:name":"Willem Simons",
    "wof:placetype":"venue"
},
  "geometry": {"coordinates":[5.5353178978,51.2277412415],"type":"Point"}
}