{
  "type": "Feature",
  "properties": {
    "addr:full":"F.timmermanslaan 13 Hoeilaart Vlaams-Brabant 1560",
    "addr:housenumber":"13",
    "addr:postcode":"1560",
    "addr:street":"F.Timmermanslaan",
    "iso:country":"BE",
    "sg:address":"F.timmermanslaan 13",
    "sg:city":"Hoeilaart",
    "sg:orig_category":"Eleveurs d'animaux domestiques",
    "sg:phone":"+32 2 657 36 52",
    "sg:postcode":"1560",
    "sg:province":"Vlaams-Brabant",
    "wof:name":"Of Silky's Paradise",
    "wof:placetype":"venue"
},
  "geometry": {"coordinates":[4.4743189812,50.7704315186],"type":"Point"}
}