{
  "type": "Feature",
  "properties": {
    "iso:country":"BE",
    "sg:address":"Rijselsestraat 51",
    "sg:city":"Ieper",
    "sg:orig_category":"S\u00e9curit\u00e9 sociale",
    "sg:phone":"+32 57 20 69 94",
    "sg:postcode":"8900",
    "sg:province":"West-Vlaanderen",
    "wof:name":"Vlaams Neutraal Ziekenf.",
    "wof:placetype":"venue"
},
  "geometry": {"coordinates":[2.8873739243,50.8488235474],"type":"Point"}
}