{
  "type": "Feature",
  "properties": {
    "addr:full":"Ambiorixsquare 18b25 Brussel/bruxelles Bruxelles-Capitale 1000",
    "addr:housenumber":"18b25",
    "addr:postcode":"1000",
    "addr:street":"Ambiorixsquare;/",
    "iso:country":"BE",
    "sg:address":"Ambiorixsquare 18b25",
    "sg:city":"Brussel/bruxelles",
    "sg:orig_category":"Reclamebureaus",
    "sg:phone":"+32 2 736 37 57",
    "sg:postcode":"1000",
    "sg:province":"Bruxelles-Capitale",
    "wof:name":"Brumagne Publicite",
    "wof:placetype":"venue"
},
  "geometry": {"coordinates":[4.3847489357,50.847530365],"type":"Point"}
}