{
  "type": "Feature",
  "properties": {
    "iso:country":"BE",
    "sg:address":"Industriezone Pb59",
    "sg:city":"Geraardsbergen",
    "sg:classifiers":[
        {
            "category":"Wholesale",
            "subcategory":"Construction Materials",
            "type":"Manufacturing & Wholesale Goods"
        }
    ],
    "sg:phone":"+32 54 41 80 98",
    "sg:postcode":"9500",
    "sg:province":"Oost-Vlaanderen",
    "sg:tags":[
        "la",
        "gr",
        "pour",
        "equipements"
    ],
    "wof:name":"Atlas Hydraulics",
    "wof:placetype":"venue"
},
  "geometry": {"coordinates":[3.8843801022,50.7716445923],"type":"Point"}
}