{
  "type": "Feature",
  "properties": {
    "addr:full":"Rue Bourguignon 3 Chaumont-gistoux Brabant Wallon 1325",
    "addr:housenumber":"3",
    "addr:postcode":"1325",
    "addr:street":"Rue Bourguignon",
    "iso:country":"BE",
    "sg:address":"Rue Bourguignon 3",
    "sg:city":"Chaumont-gistoux",
    "sg:classifiers":[
        {
            "category":"Professional",
            "subcategory":"Accounting & Tax Preparation",
            "type":"Services"
        }
    ],
    "sg:phone":"+32 10 68 84 64",
    "sg:postcode":"1325",
    "sg:province":"Brabant Wallon",
    "sg:tags":[
        "bookkeeper"
    ],
    "wof:name":"Straus A",
    "wof:placetype":"venue"
},
  "geometry": {"coordinates":[4.6930217743,50.6848983765],"type":"Point"}
}