{
  "type": "Feature",
  "properties": {
    "iso:country":"BE",
    "sg:address":"Rue De Bovesse 47",
    "sg:city":"Namur",
    "sg:orig_category":"Plomberie, chauffage and installations sanitaires",
    "sg:phone":"+32 81 56 92 00",
    "sg:postcode":"5081",
    "sg:province":"Namur",
    "wof:name":"Guillaume - Cmis",
    "wof:placetype":"venue"
},
  "geometry": {"coordinates":[4.7882180214,50.5460700989],"type":"Point"}
}