{
  "type": "Feature",
  "properties": {
    "addr:full":"Rue Des Combattants 115 Verviers Li\u00e8ge 4800",
    "addr:housenumber":"115",
    "addr:postcode":"4800",
    "addr:street":"Rue Des Combattants",
    "iso:country":"BE",
    "sg:address":"Rue Des Combattants 115",
    "sg:city":"Verviers",
    "sg:orig_category":"Instellingen voor probleemkinderen Kindertehuizen",
    "sg:phone":"+32 87 31 79 04",
    "sg:postcode":"4800",
    "sg:province":"Li\u00e8ge",
    "wof:name":"Les Bruyeres",
    "wof:placetype":"venue"
},
  "geometry": {"coordinates":[5.8475799561,50.5951309204],"type":"Point"}
}