{
  "type": "Feature",
  "properties": {
    "iso:country":"BE",
    "sg:address":"Large Voie 157",
    "sg:city":"Herstal",
    "sg:orig_category":"Avocats and conseillers juridiques",
    "sg:phone":"+32 4 264 13 55",
    "sg:postcode":"4040",
    "sg:province":"Li\u00e8ge",
    "wof:name":"Michel Vanden Dorpe",
    "wof:placetype":"venue"
},
  "geometry": {"coordinates":[5.636826992,50.6684188843],"type":"Point"}
}