{
  "type": "Feature",
  "properties": {
    "iso:country":"BE",
    "sg:address":"K. Albertstraat 40",
    "sg:city":"Diest",
    "sg:orig_category":"Disneyland Paris. Agences de voyages",
    "sg:phone":"+32 13 33 60 61",
    "sg:postcode":"3290",
    "sg:province":"Vlaams-Brabant",
    "wof:name":"Neckermann",
    "wof:placetype":"venue"
},
  "geometry": {"coordinates":[5.053437233,50.9863319397],"type":"Point"}
}