{
  "type": "Feature",
  "properties": {
    "addr:full":"Rue Rond Du Roi Albert 7 Awans Li\u00e8ge 4340",
    "addr:housenumber":"7",
    "addr:postcode":"4340",
    "addr:street":"Rue Rond Du Roi Albert",
    "iso:country":"BE",
    "sg:address":"Rue Rond Du Roi Albert 7",
    "sg:city":"Awans",
    "sg:classifiers":[
        {
            "category":"Personal",
            "subcategory":"Beauty Salon",
            "type":"Services"
        }
    ],
    "sg:phone":"+32 4 257 75 10",
    "sg:postcode":"4340",
    "sg:province":"Li\u00e8ge",
    "sg:tags":[
        "de",
        "coiffure"
    ],
    "wof:name":"Roger Lowet",
    "wof:placetype":"venue"
},
  "geometry": {"coordinates":[5.4403400421,50.7049293518],"type":"Point"}
}