{
  "type": "Feature",
  "properties": {
    "addr:full":"Rotemerlaan 97bb Maaseik Limburg 3680",
    "addr:housenumber":"97bb",
    "addr:postcode":"3680",
    "addr:street":"Rotemerlaan",
    "iso:country":"BE",
    "sg:address":"Rotemerlaan 97bb",
    "sg:city":"Maaseik",
    "sg:orig_category":"Quincailleries. Bois Gr",
    "sg:phone":"+32 89 86 77 94",
    "sg:postcode":"3680",
    "sg:province":"Limburg",
    "wof:name":"Goco-hout",
    "wof:placetype":"venue"
},
  "geometry": {"coordinates":[5.791285038,51.0954208374],"type":"Point"}
}