{
  "type": "Feature",
  "properties": {
    "iso:country":"BE",
    "sg:address":"Rue De Nimy 71",
    "sg:city":"Mons",
    "sg:classifiers":[
        {
            "category":"Shopping",
            "subcategory":"Gifts & Souvenirs",
            "type":"Retail Goods"
        }
    ],
    "sg:phone":"+32 65 84 15 32",
    "sg:postcode":"7000",
    "sg:province":"Hainaut",
    "sg:tags":[
        "-"
    ],
    "wof:name":"C\u00f4t\u00e9 Cour C\u00f4t\u00e9 Jardin",
    "wof:placetype":"venue"
},
  "geometry": {"coordinates":[3.9550390244,50.4574661255],"type":"Point"}
}