{
  "type": "Feature",
  "properties": {
    "addr:full":"Rue Joseph Lemaire 8 Li\u00e8ge 1 (grivegn\u00e9e) Li\u00e8ge 4030",
    "addr:housenumber":"8;1",
    "addr:postcode":"4030",
    "addr:street":"Rue Joseph Lemaire",
    "iso:country":"BE",
    "sg:address":"Rue Joseph Lemaire 8",
    "sg:city":"Li\u00e8ge 1 (grivegn\u00e9e)",
    "sg:classifiers":[
        {
            "category":"Health Services",
            "subcategory":"Doctor",
            "type":"Services"
        }
    ],
    "sg:phone":"+32 4 343 25 13",
    "sg:postcode":"4030",
    "sg:province":"Li\u00e8ge",
    "sg:tags":[
        "medicinephysicians",
        "surgeon"
    ],
    "wof:name":"Janssen N",
    "wof:placetype":"venue"
},
  "geometry": {"coordinates":[5.6112689972,50.6292076111],"type":"Point"}
}