{
  "type": "Feature",
  "properties": {
    "addr:full":"Eikhove 32 Watermaal-bosvoorde/watermael-boitsfort Bruxelles-Capitale 1170",
    "addr:housenumber":"32",
    "addr:postcode":"1170",
    "addr:street":"Eikhove",
    "iso:country":"BE",
    "sg:address":"Eikhove 32",
    "sg:city":"Watermaal-bosvoorde/watermael-boitsfort",
    "sg:orig_category":"Boekhouders",
    "sg:phone":"+32 2 673 28 84",
    "sg:postcode":"1170",
    "sg:province":"Bruxelles-Capitale",
    "wof:name":"Micheline Galopin",
    "wof:placetype":"venue"
},
  "geometry": {"coordinates":[4.4081168175,50.7935791016],"type":"Point"}
}