{
  "type": "Feature",
  "properties": {
    "iso:country":"BE",
    "sg:address":"Ruweschuurstraat 14",
    "sg:city":"Beernem",
    "sg:orig_category":"Woningbouw",
    "sg:phone":"+32 50 78 81 37",
    "sg:postcode":"8730",
    "sg:province":"West-Vlaanderen",
    "wof:name":"Luc Persyn",
    "wof:placetype":"venue"
},
  "geometry": {"coordinates":[3.3830471039,51.171421051],"type":"Point"}
}