{
  "type": "Feature",
  "properties": {
    "addr:full":"Chauss\u00c9e De Waterloo 1103 Ukkel/uccle Bruxelles-Capitale 1180",
    "addr:postcode":"1103;1180",
    "addr:street":"Chausse\u0301E De Waterloo",
    "iso:country":"BE",
    "sg:address":"Chauss\u00c9e De Waterloo 1103",
    "sg:city":"Ukkel/uccle",
    "sg:classifiers":[
        {
            "category":"Autos & Motor Vehicles",
            "subcategory":"Fuel & Gas Station",
            "type":"Retail Goods"
        }
    ],
    "sg:phone":"+32 2 374 18 70",
    "sg:postcode":"1180",
    "sg:province":"Bruxelles-Capitale",
    "sg:tags":[
        "stations-service",
        "carburants"
    ],
    "wof:name":"Sheluc",
    "wof:placetype":"venue"
},
  "geometry": {"coordinates":[4.3733119965,50.8014564514],"type":"Point"}
}