{
  "type": "Feature",
  "properties": {
    "addr:full":"Heldergemstraat 185 Haaltert Oost-Vlaanderen 9450",
    "addr:housenumber":"185",
    "addr:postcode":"9450",
    "addr:street":"Heldergemstraat",
    "iso:country":"BE",
    "sg:address":"Heldergemstraat 185",
    "sg:city":"Haaltert",
    "sg:orig_category":"Eleveurs de bovins",
    "sg:phone":"+32 53 62 34 45",
    "sg:postcode":"9450",
    "sg:province":"Oost-Vlaanderen",
    "wof:name":"Michel De Troyer",
    "wof:placetype":"venue"
},
  "geometry": {"coordinates":[3.9535388947,50.8822975159],"type":"Point"}
}