{
  "type": "Feature",
  "properties": {
    "iso:country":"BE",
    "sg:address":"Eeckbergstraat 59",
    "sg:city":"Sint-gillis-waas",
    "sg:orig_category":"Rundveehouders Varkenskwekers",
    "sg:phone":"+32 3 770 62 10",
    "sg:postcode":"9170",
    "sg:province":"Oost-Vlaanderen",
    "wof:name":"Willy Daelman",
    "wof:placetype":"venue"
},
  "geometry": {"coordinates":[4.1197018623,51.2397460938],"type":"Point"}
}