{
  "type": "Feature",
  "properties": {
    "addr:full":"Chauss\u00e9e D'aelbeke 248 Mouscron Hainaut 7700",
    "addr:housenumber":"248",
    "addr:postcode":"7700",
    "addr:street":"Chausse\u0301E D'Aelbeke",
    "iso:country":"BE",
    "sg:address":"Chauss\u00e9e D'aelbeke 248",
    "sg:city":"Mouscron",
    "sg:classifiers":[
        {
            "category":"Building & Trades",
            "subcategory":"Landscaping Services",
            "type":"Services"
        }
    ],
    "sg:phone":"+32 56 33 13 61",
    "sg:postcode":"7700",
    "sg:province":"Hainaut",
    "sg:tags":[
        "handicraft"
    ],
    "wof:name":"Artcre-gros",
    "wof:placetype":"venue"
},
  "geometry": {"coordinates":[3.2223639488,50.7573432922],"type":"Point"}
}