{
  "type": "Feature",
  "properties": {
    "iso:country":"BE",
    "sg:address":"Haenhoutstraat 256",
    "sg:city":"Destelbergen",
    "sg:classifiers":[
        {
            "category":"Personal",
            "subcategory":"Beauty Salon",
            "type":"Services"
        }
    ],
    "sg:phone":"+32 9 355 11 85",
    "sg:postcode":"9070",
    "sg:province":"Oost-Vlaanderen",
    "sg:tags":[
        "de",
        "coiffure"
    ],
    "wof:name":"Nancy Scheire",
    "wof:placetype":"venue"
},
  "geometry": {"coordinates":[3.8411810398,51.0744056702],"type":"Point"}
}