{
  "type": "Feature",
  "properties": {
    "addr:full":"President Rooseveltplein 1 Kortrijk West-Vlaanderen 8500",
    "addr:housenumber":"1",
    "addr:postcode":"8500",
    "addr:street":"President Rooseveltplein",
    "iso:country":"BE",
    "sg:address":"President Rooseveltplein 1",
    "sg:city":"Kortrijk",
    "sg:orig_category":"Advocaten and juridische adviseurs",
    "sg:phone":"+32 56 22 51 66",
    "sg:postcode":"8500",
    "sg:province":"West-Vlaanderen",
    "wof:name":"Robrecht Bauwens",
    "wof:placetype":"venue"
},
  "geometry": {"coordinates":[3.2607719898,50.8278236389],"type":"Point"}
}