{
  "type": "Feature",
  "properties": {
    "iso:country":"BE",
    "sg:address":"2540",
    "sg:city":"Hove",
    "sg:orig_category":"Pharmaciens",
    "sg:phone":"+32 900 10 500",
    "sg:postcode":"2540",
    "sg:province":"Antwerpen",
    "wof:name":"Pharmacies De Garde",
    "wof:placetype":"venue"
},
  "geometry": {"coordinates":[4.4843502045,51.1468315125],"type":"Point"}
}