{
  "type": "Feature",
  "properties": {
    "iso:country":"BE",
    "sg:address":"Lange Kroonstraat 102",
    "sg:city":"Boechout",
    "sg:classifiers":[
        {
            "category":"Home & Garden",
            "subcategory":"Building Materials",
            "type":"Retail Goods"
        }
    ],
    "sg:phone":"+32 3 454 05 00",
    "sg:postcode":"2530",
    "sg:province":"Antwerpen",
    "sg:tags":[
        "aluminium",
        "construction",
        "-"
    ],
    "wof:name":"Quality Jobs Bvba",
    "wof:placetype":"venue"
},
  "geometry": {"coordinates":[4.4867930412,51.164478302],"type":"Point"}
}