{
  "type": "Feature",
  "properties": {
    "iso:country":"BE",
    "sg:address":"Jagerpad 25",
    "sg:city":"Waarschoot",
    "sg:orig_category":"Eleveurs de bovins",
    "sg:phone":"+32 9 377 64 73",
    "sg:postcode":"9950",
    "sg:province":"Oost-Vlaanderen",
    "wof:name":"Filip De Keer",
    "wof:placetype":"venue"
},
  "geometry": {"coordinates":[3.6000978947,51.1565132141],"type":"Point"}
}