{
  "type": "Feature",
  "properties": {
    "addr:full":"Neerstraat 113 Oud-turnhout Antwerpen 2360",
    "addr:housenumber":"113",
    "addr:postcode":"2360",
    "addr:street":"Neerstraat",
    "iso:country":"BE",
    "sg:address":"Neerstraat 113",
    "sg:city":"Oud-turnhout",
    "sg:orig_category":"Instituts de beaut\u00e9",
    "sg:phone":"+32 14 45 16 57",
    "sg:postcode":"2360",
    "sg:province":"Antwerpen",
    "wof:name":"Instituut Byblus",
    "wof:placetype":"venue"
},
  "geometry": {"coordinates":[4.9877071381,51.3121604919],"type":"Point"}
}