{
  "type": "Feature",
  "properties": {
    "iso:country":"BE",
    "sg:address":"Chauss\u00c9e De Mons 218",
    "sg:city":"Anderlues",
    "sg:orig_category":"Eleveurs de bovins",
    "sg:phone":"+32 71 52 49 47",
    "sg:postcode":"6150",
    "sg:province":"Hainaut",
    "wof:name":"Simon Roosens",
    "wof:placetype":"venue"
},
  "geometry": {"coordinates":[4.2286968231,50.4077949524],"type":"Point"}
}