{
  "type": "Feature",
  "properties": {
    "addr:full":"Ter Stratenweg 5 Oelegem Antwerpen 2520",
    "addr:housenumber":"5",
    "addr:postcode":"2520",
    "addr:street":"Ter Stratenweg",
    "iso:country":"BE",
    "sg:address":"Ter Stratenweg 5",
    "sg:city":"Oelegem",
    "sg:classifiers":[
        {
            "category":"Shopping Center",
            "type":"Public Place"
        }
    ],
    "sg:phone":"+32 3 475 01 75",
    "sg:postcode":"2520",
    "sg:province":"Antwerpen",
    "sg:tags":[
        "aluminium",
        "casting"
    ],
    "wof:name":"Aluwiel Nv",
    "wof:placetype":"venue"
},
  "geometry": {"coordinates":[4.586397171,51.2072982788],"type":"Point"}
}