{
  "type": "Feature",
  "properties": {
    "addr:full":"Meylstraat 4 Hove Antwerpen 2540",
    "addr:housenumber":"4",
    "addr:postcode":"2540",
    "addr:street":"Meylstraat",
    "iso:country":"BE",
    "sg:address":"Meylstraat 4",
    "sg:city":"Hove",
    "sg:orig_category":"Non-Classified Establishments",
    "sg:phone":"+32 3 455 92 64",
    "sg:postcode":"2540",
    "sg:province":"Antwerpen",
    "wof:name":"Lvi-low Vision International",
    "wof:placetype":"venue"
},
  "geometry": {"coordinates":[4.470498085,51.1535491943],"type":"Point"}
}