{
  "type": "Feature",
  "properties": {
    "addr:full":"Dijle 15 Mechelen Antwerpen 2800",
    "addr:housenumber":"15",
    "addr:postcode":"2800",
    "addr:street":"Dijle",
    "iso:country":"BE",
    "sg:address":"Dijle 15",
    "sg:city":"Mechelen",
    "sg:classifiers":[
        {
            "category":"Wholesale",
            "subcategory":"Seafood",
            "type":"Manufacturing & Wholesale Goods"
        }
    ],
    "sg:phone":"+32 15 26 25 05",
    "sg:postcode":"2800",
    "sg:province":"Antwerpen",
    "sg:tags":[
        "whol",
        "fish",
        "-",
        "shellfish"
    ],
    "wof:name":"Mosselhandel Nees",
    "wof:placetype":"venue"
},
  "geometry": {"coordinates":[4.4738230705,51.0271720886],"type":"Point"}
}