{
  "type": "Feature",
  "properties": {
    "addr:full":"Chauss\u00e9e De Mons 711 Bruxelles (anderlecht) Bruxelles-Capitale 1070",
    "addr:housenumber":"711",
    "addr:postcode":"1070",
    "addr:street":"Chausse\u0301E De Mons",
    "iso:country":"BE",
    "sg:address":"Chauss\u00e9e De Mons 711",
    "sg:city":"Bruxelles (anderlecht)",
    "sg:classifiers":[
        {
            "category":"Professional",
            "subcategory":"Testing Lab",
            "type":"Services"
        }
    ],
    "sg:phone":"+32 2 524 14 99",
    "sg:postcode":"1070",
    "sg:province":"Bruxelles-Capitale",
    "sg:tags":[
        "laboratory",
        "photographic",
        "film"
    ],
    "wof:name":"Labo Photo Couleurs Cocozza S",
    "wof:placetype":"venue"
},
  "geometry": {"coordinates":[4.3078660965,50.8302192688],"type":"Point"}
}