{
  "type": "Feature",
  "properties": {
    "addr:full":"Stalenstraat 60 Genk Limburg 3600",
    "addr:housenumber":"60",
    "addr:postcode":"3600",
    "addr:street":"Stalenstraat",
    "iso:country":"BE",
    "sg:address":"Stalenstraat 60",
    "sg:city":"Genk",
    "sg:orig_category":"Chaussures",
    "sg:phone":"+32 89 38 20 28",
    "sg:postcode":"3600",
    "sg:province":"Limburg",
    "wof:name":"Renzi Schoenhandel",
    "wof:placetype":"venue"
},
  "geometry": {"coordinates":[5.5189070702,50.9940261841],"type":"Point"}
}