{
  "type": "Feature",
  "properties": {
    "addr:full":"Chemin Des Peupliers 21 Aat Hainaut 7800",
    "addr:housenumber":"21",
    "addr:postcode":"7800",
    "addr:street":"Chemin Des Peupliers;Hainaut",
    "iso:country":"BE",
    "sg:address":"Chemin Des Peupliers 21",
    "sg:city":"Aat",
    "sg:orig_category":"Eclairage et \u00e9quipements du foyer",
    "sg:phone":"+32 68 28 19 36",
    "sg:postcode":"7800",
    "sg:province":"Hainaut",
    "wof:name":"Must Int\u00c9rieur",
    "wof:placetype":"venue"
},
  "geometry": {"coordinates":[3.7778298855,50.6383666992],"type":"Point"}
}