{
  "type": "Feature",
  "properties": {
    "addr:full":"Dorpsstraat 23 De Panne West-Vlaanderen 8660",
    "addr:housenumber":"23",
    "addr:postcode":"8660",
    "addr:street":"Dorpsstraat",
    "iso:country":"BE",
    "sg:address":"Dorpsstraat 23",
    "sg:city":"De Panne",
    "sg:orig_category":"M\u00e9decins and sp\u00e9cialistes",
    "sg:phone":"+32 58 41 57 95",
    "sg:postcode":"8660",
    "sg:province":"West-Vlaanderen",
    "wof:name":"Anne-marie Logier",
    "wof:placetype":"venue"
},
  "geometry": {"coordinates":[2.600703001,51.0748901367],"type":"Point"}
}