{
  "type": "Feature",
  "properties": {
    "iso:country":"BE",
    "sg:address":"Boulevard A. Reyers 156",
    "sg:city":"Bruxelles",
    "sg:orig_category":"Diverse bedrijfsbeheeradviesbureaus",
    "sg:phone":"+32 2 735 09 95",
    "sg:postcode":"1030",
    "sg:province":"Bruxelles-Capitale",
    "wof:name":"Stratec",
    "wof:placetype":"venue"
},
  "geometry": {"coordinates":[4.4040060043,50.8470230103],"type":"Point"}
}