{
  "type": "Feature",
  "properties": {
    "addr:full":"Vrijheid 30 Arendonk Antwerpen 2370",
    "addr:housenumber":"30",
    "addr:postcode":"2370",
    "addr:street":"Vrijheid",
    "iso:country":"BE",
    "sg:address":"Vrijheid 30",
    "sg:city":"Arendonk",
    "sg:classifiers":[
        {
            "category":"Personal",
            "subcategory":"Beauty Salon",
            "type":"Services"
        }
    ],
    "sg:phone":"+32 14 67 80 74",
    "sg:postcode":"2370",
    "sg:province":"Antwerpen",
    "sg:tags":[
        "lady",
        "-",
        "hairdressing"
    ],
    "wof:name":"Style Coiffure",
    "wof:placetype":"venue"
},
  "geometry": {"coordinates":[5.0868091583,51.3200874329],"type":"Point"}
}