{
  "type": "Feature",
  "properties": {
    "addr:full":"Beernemsteenweg 25 Wingene West-Vlaanderen 8750",
    "addr:housenumber":"25",
    "addr:postcode":"8750",
    "addr:street":"Beernemsteenweg",
    "iso:country":"BE",
    "sg:address":"Beernemsteenweg 25",
    "sg:city":"Wingene",
    "sg:orig_category":"Eleveurs de volaille",
    "sg:phone":"+32 51 65 73 84",
    "sg:postcode":"8750",
    "sg:province":"West-Vlaanderen",
    "wof:name":"Van Haecke",
    "wof:placetype":"venue"
},
  "geometry": {"coordinates":[3.2885971069,51.0705833435],"type":"Point"}
}