{
  "type": "Feature",
  "properties": {
    "addr:full":"Rue De Tournai 68 Beloeil Hainaut 7972",
    "addr:housenumber":"68",
    "addr:postcode":"7972",
    "addr:street":"Rue De Tournai",
    "iso:country":"BE",
    "sg:address":"Rue De Tournai 68",
    "sg:city":"Beloeil",
    "sg:orig_category":"V\u00e9hicules automobiles. Entretien and r\u00e9parations de voitures",
    "sg:phone":"+32 69 57 51 26",
    "sg:postcode":"7972",
    "sg:province":"Hainaut",
    "wof:name":"Carrosserie M.p.v.",
    "wof:placetype":"venue"
},
  "geometry": {"coordinates":[3.6921050549,50.5274238586],"type":"Point"}
}