{
  "type": "Feature",
  "properties": {
    "iso:country":"BE",
    "sg:address":"Herentalsesteenweg 15",
    "sg:city":"Lille (poederlee)",
    "sg:classifiers":[
        {
            "category":"Shopping",
            "subcategory":"Florist",
            "type":"Retail Goods"
        }
    ],
    "sg:phone":"+32 14 88 11 80",
    "sg:postcode":"2275",
    "sg:province":"Antwerpen",
    "wof:name":"Bloemtiek",
    "wof:placetype":"venue"
},
  "geometry": {"coordinates":[4.8345007896,51.2253723145],"type":"Point"}
}