{
  "type": "Feature",
  "properties": {
    "iso:country":"BE",
    "sg:address":"Sinaaidorp 20",
    "sg:city":"Sint-niklaas",
    "sg:classifiers":[
        {
            "category":"Restaurant",
            "type":"Food & Drink"
        }
    ],
    "sg:phone":"+32 3 772 65 54",
    "sg:postcode":"9112",
    "sg:province":"Oost-Vlaanderen",
    "wof:name":"De Zoeten Inval",
    "wof:placetype":"venue"
},
  "geometry": {"coordinates":[4.0394630432,51.1575546265],"type":"Point"}
}