{
  "type": "Feature",
  "properties": {
    "addr:full":"Clos Des Trotteurs 6 Wezembeek-oppem Vlaams-Brabant 1970",
    "addr:housenumber":"6",
    "addr:postcode":"1970",
    "addr:street":"Clos Des Trotteurs",
    "iso:country":"BE",
    "sg:address":"Clos Des Trotteurs 6",
    "sg:city":"Wezembeek-oppem",
    "sg:classifiers":[
        {
            "category":"Health Services",
            "subcategory":"Doctor",
            "type":"Services"
        }
    ],
    "sg:phone":"+32 2 731 03 64",
    "sg:postcode":"1970",
    "sg:province":"Vlaams-Brabant",
    "sg:tags":[
        "medicinephysicians",
        "surgeon"
    ],
    "wof:name":"Hubaille Georges",
    "wof:placetype":"venue"
},
  "geometry": {"coordinates":[4.4994821548,50.8542137146],"type":"Point"}
}