{
  "type": "Feature",
  "properties": {
    "addr:full":"Vlaamspad 7 Knokke-heist West-Vlaanderen 8300",
    "addr:housenumber":"7",
    "addr:postcode":"8300",
    "addr:street":"Vlaamspad",
    "iso:country":"BE",
    "sg:address":"Vlaamspad 7",
    "sg:city":"Knokke-heist",
    "sg:orig_category":"Sportclubs",
    "sg:phone":"+32 50 60 18 91",
    "sg:postcode":"8300",
    "sg:province":"West-Vlaanderen",
    "wof:name":"H.c. Knokke",
    "wof:placetype":"venue"
},
  "geometry": {"coordinates":[3.2919790745,51.3470993042],"type":"Point"}
}