{
  "type": "Feature",
  "properties": {
    "addr:full":"Beekstraat 110 Assenede Oost-Vlaanderen 9968",
    "addr:housenumber":"110",
    "addr:postcode":"9968",
    "addr:street":"Beekstraat",
    "iso:country":"BE",
    "sg:address":"Beekstraat 110",
    "sg:city":"Assenede",
    "sg:orig_category":"Rundveehouders",
    "sg:phone":"+32 9 373 65 45",
    "sg:postcode":"9968",
    "sg:province":"Oost-Vlaanderen",
    "wof:name":"Gabriel Buysse",
    "wof:placetype":"venue"
},
  "geometry": {"coordinates":[3.6887938976,51.1923027039],"type":"Point"}
}