{
  "type": "Feature",
  "properties": {
    "iso:country":"BE",
    "sg:address":"Broekstraat 68",
    "sg:city":"Brussel/bruxelles",
    "sg:orig_category":"Maatschappelijke dienstverlening",
    "sg:phone":"+32 2 217 12 26",
    "sg:postcode":"1000",
    "sg:province":"Bruxelles-Capitale",
    "wof:name":"Centre P.m.s.",
    "wof:placetype":"venue"
},
  "geometry": {"coordinates":[4.3597769737,50.8523521423],"type":"Point"}
}