{
  "type": "Feature",
  "properties": {
    "addr:full":"Schotensesteenweg 303 Antwerpen Antwerpen 2100",
    "addr:housenumber":"303",
    "addr:postcode":"2100",
    "addr:street":"Schotensesteenweg",
    "iso:country":"BE",
    "sg:address":"Schotensesteenweg 303",
    "sg:city":"Antwerpen",
    "sg:orig_category":"Artistes ind\u00e9pendants",
    "sg:phone":"+32 3 324 52 29",
    "sg:postcode":"2100",
    "sg:province":"Antwerpen",
    "wof:name":"De Martelaere",
    "wof:placetype":"venue"
},
  "geometry": {"coordinates":[4.4586100578,51.2203941345],"type":"Point"}
}