{
  "type": "Feature",
  "properties": {
    "addr:full":"Fabriekstraat 1 Bocholt (kaulille) Limburg 3950",
    "addr:housenumber":"1",
    "addr:postcode":"3950",
    "addr:street":"Fabriekstraat",
    "iso:country":"BE",
    "sg:address":"Fabriekstraat 1",
    "sg:city":"Bocholt (kaulille)",
    "sg:classifiers":[
        {
            "category":"Home & Garden",
            "subcategory":"Home Furnishings",
            "type":"Retail Goods"
        }
    ],
    "sg:phone":"+32 11 44 10 60",
    "sg:postcode":"3950",
    "sg:province":"Limburg",
    "sg:tags":[
        "-",
        "furniture"
    ],
    "wof:name":"Ooms",
    "wof:placetype":"venue"
},
  "geometry": {"coordinates":[5.5155310631,51.1917533875],"type":"Point"}
}