{
  "type": "Feature",
  "properties": {
    "iso:country":"BE",
    "sg:address":"Rue Des Charrons 7",
    "sg:city":"H\u00e9l\u00e9cine (neerheylissem)",
    "sg:classifiers":[
        {
            "category":"Health Services",
            "subcategory":"Health Practitioner",
            "type":"Services"
        }
    ],
    "sg:phone":"+32 19 65 64 17",
    "sg:postcode":"1357",
    "sg:province":"Brabant Wallon",
    "sg:tags":[
        "physiotherapist"
    ],
    "wof:name":"Gentges N",
    "wof:placetype":"venue"
},
  "geometry": {"coordinates":[4.9859318733,50.7586097717],"type":"Point"}
}