{
  "type": "Feature",
  "properties": {
    "iso:country":"BE",
    "sg:address":"Hogeleeststraat 33",
    "sg:city":"Brussel/bruxelles",
    "sg:orig_category":"Artsen and specialisten",
    "sg:phone":"+32 2 268 40 83",
    "sg:postcode":"1120",
    "sg:province":"Bruxelles-Capitale",
    "wof:name":"L. Ramboer",
    "wof:placetype":"venue"
},
  "geometry": {"coordinates":[4.3709568977,50.8942909241],"type":"Point"}
}