{
  "type": "Feature",
  "properties": {
    "iso:country":"BE",
    "sg:address":"Sint-laureiskaai 7",
    "sg:city":"Antwerpen",
    "sg:classifiers":[
        {
            "category":"Professional",
            "type":"Services"
        }
    ],
    "sg:phone":"+32 3 203 96 00",
    "sg:postcode":"2000",
    "sg:province":"Antwerpen",
    "sg:tags":[
        "forwarding",
        "agency"
    ],
    "wof:name":"Lamberigts & Van Daelen Nv",
    "wof:placetype":"venue"
},
  "geometry": {"coordinates":[4.4042859077,51.2298851013],"type":"Point"}
}