{
  "type": "Feature",
  "properties": {
    "iso:country":"BE",
    "sg:address":"Rue De Monsville 302",
    "sg:city":"Quaregnon",
    "sg:orig_category":"Jeux de hasard",
    "sg:phone":"+32 65 78 67 22",
    "sg:postcode":"7390",
    "sg:province":"Hainaut",
    "wof:name":"Agence Hippique Dumoulin",
    "wof:placetype":"venue"
},
  "geometry": {"coordinates":[3.8633050919,50.4344749451],"type":"Point"}
}