{
  "type": "Feature",
  "properties": {
    "addr:full":"Rue De L'abbaye 12 Beloeil (aubechies) Hainaut 7972",
    "addr:housenumber":"12",
    "addr:postcode":"7972",
    "addr:street":"Rue De L'Abbaye",
    "iso:country":"BE",
    "sg:address":"Rue De L'abbaye 12",
    "sg:city":"Beloeil (aubechies)",
    "sg:classifiers":[
        {
            "category":"Personal",
            "subcategory":"Beauty Salon",
            "type":"Services"
        }
    ],
    "sg:phone":"+32 69 67 14 15",
    "sg:postcode":"7972",
    "sg:province":"Hainaut",
    "sg:tags":[
        "lady",
        "-",
        "hairdressing"
    ],
    "wof:name":"Chris",
    "wof:placetype":"venue"
},
  "geometry": {"coordinates":[3.6758499146,50.5739402771],"type":"Point"}
}