{
  "type": "Feature",
  "properties": {
    "iso:country":"BE",
    "sg:address":"Invalidenlaan 122",
    "sg:city":"Oudergem/auderghem",
    "sg:orig_category":"Artsen and specialisten",
    "sg:phone":"+32 2 673 97 96",
    "sg:postcode":"1160",
    "sg:province":"Bruxelles-Capitale",
    "wof:name":"Catherine Moiny",
    "wof:placetype":"venue"
},
  "geometry": {"coordinates":[4.4123430252,50.817489624],"type":"Point"}
}