{
  "type": "Feature",
  "properties": {
    "iso:country":"BE",
    "sg:address":"Drijtap 18",
    "sg:city":"Genk",
    "sg:classifiers":[
        {
            "category":"Cafe",
            "type":"Food & Drink"
        }
    ],
    "sg:phone":"+32 89 35 82 49",
    "sg:postcode":"3600",
    "sg:province":"Limburg",
    "sg:tags":[
        "caf\u00e9s"
    ],
    "wof:name":"Maria Goretti Te Bokrijk",
    "wof:placetype":"venue"
},
  "geometry": {"coordinates":[5.4563999176,50.9596862793],"type":"Point"}
}