{
  "type": "Feature",
  "properties": {
    "addr:full":"Maurice Van Rolleghemstr 18 Jette Bruxelles-Capitale 1090",
    "addr:housenumber":"18",
    "addr:postcode":"1090",
    "addr:street":"Maurice Van Rolleghemstr",
    "iso:country":"BE",
    "sg:address":"Maurice Van Rolleghemstr 18",
    "sg:city":"Jette",
    "sg:classifiers":[
        {
            "category":"Cafe",
            "type":"Food & Drink"
        }
    ],
    "sg:phone":"+32 2 478 93 20",
    "sg:postcode":"1090",
    "sg:province":"Bruxelles-Capitale",
    "sg:tags":[
        "caf\u00e9s"
    ],
    "wof:name":"Walter Dieltjens",
    "wof:placetype":"venue"
},
  "geometry": {"coordinates":[4.3235030174,50.8904800415],"type":"Point"}
}