{
  "type": "Feature",
  "properties": {
    "iso:country":"BE",
    "sg:address":"Rue Des Six Bonniers 12b",
    "sg:city":"Seraing",
    "sg:classifiers":[
        {
            "category":"Retail",
            "subcategory":"Veterinary Services",
            "type":"Services"
        }
    ],
    "sg:phone":"+32 4 233 06 47",
    "sg:postcode":"4100",
    "sg:province":"Li\u00e8ge",
    "sg:tags":[
        "veterinarian"
    ],
    "wof:name":"Theunissen V",
    "wof:placetype":"venue"
},
  "geometry": {"coordinates":[5.519340992,50.6018638611],"type":"Point"}
}