{
  "type": "Feature",
  "properties": {
    "iso:country":"BE",
    "sg:address":"Boulevard Lambermont 84",
    "sg:city":"Schaarbeek/schaerbeek",
    "sg:orig_category":"Agences de publicit\u00e9",
    "sg:phone":"+32 2 242 51 62",
    "sg:postcode":"1030",
    "sg:province":"Bruxelles-Capitale",
    "wof:name":"Mister Blue Sky",
    "wof:placetype":"venue"
},
  "geometry": {"coordinates":[4.3783130646,50.8732910156],"type":"Point"}
}