{
  "type": "Feature",
  "properties": {
    "addr:full":"Limburgerstrasse 69 Lontzen Li\u00e8ge 4710",
    "addr:housenumber":"69",
    "addr:postcode":"4710",
    "addr:street":"Limburgerstrasse",
    "iso:country":"BE",
    "sg:address":"Limburgerstrasse 69",
    "sg:city":"Lontzen",
    "sg:classifiers":[
        {
            "category":"Shopping",
            "subcategory":"Baby Store",
            "type":"Retail Goods"
        }
    ],
    "sg:phone":"+32 87 46 38 73",
    "sg:postcode":"4710",
    "sg:province":"Li\u00e8ge",
    "sg:tags":[
        "-",
        "accessory"
    ],
    "wof:name":"Kiddy Bips",
    "wof:placetype":"venue"
},
  "geometry": {"coordinates":[6.0046401024,50.6704711914],"type":"Point"}
}