{
  "type": "Feature",
  "properties": {
    "addr:full":"Breevendreef 57b Bornem Antwerpen 2880",
    "addr:housenumber":"57b",
    "addr:postcode":"2880",
    "addr:street":"Breevendreef",
    "iso:country":"BE",
    "sg:address":"Breevendreef 57b",
    "sg:city":"Bornem",
    "sg:classifiers":[
        {
            "category":"Organizations",
            "subcategory":"Professional Association",
            "type":"Services"
        }
    ],
    "sg:phone":"+32 3 899 62 69",
    "sg:postcode":"2880",
    "sg:province":"Antwerpen",
    "sg:tags":[
        "trade-union",
        "federation"
    ],
    "wof:name":"Beroepsvereniging Voor Bandagisten En Orthopedisten In Belgi\u00eb",
    "wof:placetype":"venue"
},
  "geometry": {"coordinates":[4.2424898148,51.0931587219],"type":"Point"}
}