{
  "type": "Feature",
  "properties": {
    "iso:country":"BE",
    "sg:address":"Ch De Waterloo",
    "sg:city":"Uccle",
    "sg:orig_category":"Agences de voyages",
    "sg:phone":"+32 2 375 84 81",
    "sg:postcode":"1180",
    "sg:province":"Bruxelles-Capitale",
    "wof:name":"Jlm Travel",
    "wof:placetype":"venue"
},
  "geometry": {"coordinates":[4.3748188019,50.7966804504],"type":"Point"}
}