{
  "type": "Feature",
  "properties": {
    "addr:full":"Rue Emile Vandervelde 1 Chaudfontaine Li\u00e8ge 4051",
    "addr:housenumber":"1",
    "addr:postcode":"4051",
    "addr:street":"Rue Emile Vandervelde",
    "iso:country":"BE",
    "sg:address":"Rue Emile Vandervelde 1",
    "sg:city":"Chaudfontaine",
    "sg:orig_category":"Brood, gebak and snoepgoed",
    "sg:phone":"+32 4 365 10 60",
    "sg:postcode":"4051",
    "sg:province":"Li\u00e8ge",
    "wof:name":"Boulangerie Loncin",
    "wof:placetype":"venue"
},
  "geometry": {"coordinates":[5.6333122253,50.6003646851],"type":"Point"}
}