{
  "type": "Feature",
  "properties": {
    "addr:full":"Rue Emile Vandervelde 26 Le Roeulx Hainaut 7070",
    "addr:housenumber":"26",
    "addr:postcode":"7070",
    "addr:street":"Rue Emile Vandervelde",
    "iso:country":"BE",
    "sg:address":"Rue Emile Vandervelde 26",
    "sg:city":"Le Roeulx",
    "sg:classifiers":[
        {
            "category":"Insurance",
            "subcategory":"Insurance Agent",
            "type":"Services"
        }
    ],
    "sg:phone":"+32 64 66 50 40",
    "sg:postcode":"7070",
    "sg:province":"Hainaut",
    "sg:tags":[
        "broker"
    ],
    "wof:name":"Bureau D'assurance L Bourgois",
    "wof:placetype":"venue"
},
  "geometry": {"coordinates":[4.1098232269,50.5033226013],"type":"Point"}
}