{
  "type": "Feature",
  "properties": {
    "iso:country":"BE",
    "sg:address":"Rue De L'ange 24-26",
    "sg:city":"Namur",
    "sg:classifiers":[
        {
            "category":"Shopping",
            "subcategory":"Clothing, Apparel, & Fashions",
            "type":"Retail Goods"
        }
    ],
    "sg:phone":"+32 81 26 32 04",
    "sg:postcode":"5000",
    "sg:province":"Namur",
    "sg:tags":[
        "boutique"
    ],
    "wof:name":"V\u00f6gele Mode",
    "wof:placetype":"venue"
},
  "geometry": {"coordinates":[4.8656349182,50.4633865356],"type":"Point"}
}