{
  "type": "Feature",
  "properties": {
    "addr:full":"Chauss\u00e9e De Perwez 251 Namur (saint-servais) Namur 5002",
    "addr:housenumber":"251",
    "addr:postcode":"5002",
    "addr:street":"Chausse\u0301E De Perwez",
    "iso:country":"BE",
    "sg:address":"Chauss\u00e9e De Perwez 251",
    "sg:city":"Namur (saint-servais)",
    "sg:classifiers":[
        {
            "category":"Retail",
            "subcategory":"Event Space",
            "type":"Services"
        }
    ],
    "sg:phone":"+32 81 73 10 11",
    "sg:postcode":"5002",
    "sg:province":"Namur",
    "sg:tags":[
        "rental",
        "-",
        "hall"
    ],
    "wof:name":"Squash Club De Namur",
    "wof:placetype":"venue"
},
  "geometry": {"coordinates":[4.8462319374,50.4782791138],"type":"Point"}
}