{
  "type": "Feature",
  "properties": {
    "addr:full":"Broustinlaan 113 Ganshoren Bruxelles-Capitale 1083",
    "addr:housenumber":"113",
    "addr:postcode":"1083",
    "addr:street":"Broustinlaan",
    "iso:country":"BE",
    "sg:address":"Broustinlaan 113",
    "sg:city":"Ganshoren",
    "sg:classifiers":[
        {
            "category":"Restaurant",
            "type":"Food & Drink"
        }
    ],
    "sg:phone":"+32 2 428 79 82",
    "sg:postcode":"1083",
    "sg:province":"Bruxelles-Capitale",
    "wof:name":"Restaurant Le Chalet",
    "wof:placetype":"venue"
},
  "geometry": {"coordinates":[4.3209252357,50.8673706055],"type":"Point"}
}