{
  "type": "Feature",
  "properties": {
    "iso:country":"BE",
    "sg:address":"Hasseltsebaan 145",
    "sg:city":"Diest",
    "sg:orig_category":"Installation \u00e9lectrique r\u00e9sidentielle. Production de films, t\u00e9l\u00e9films and vid\u00e9os",
    "sg:phone":"+32 13 66 77 71",
    "sg:postcode":"3290",
    "sg:province":"Vlaams-Brabant",
    "wof:name":"Fa. Coomans",
    "wof:placetype":"venue"
},
  "geometry": {"coordinates":[5.0901641846,51.0487442017],"type":"Point"}
}