{
  "type": "Feature",
  "properties": {
    "addr:full":"Moststraat 47 Gent (oostakker) Oost-Vlaanderen 9041",
    "addr:housenumber":"47",
    "addr:postcode":"9041",
    "addr:street":"Moststraat",
    "iso:country":"BE",
    "sg:address":"Moststraat 47",
    "sg:city":"Gent (oostakker)",
    "sg:classifiers":[
        {
            "category":"Professional",
            "type":"Services"
        }
    ],
    "sg:phone":"+32 9 251 62 30",
    "sg:postcode":"9041",
    "sg:province":"Oost-Vlaanderen",
    "sg:tags":[
        "surveyor",
        "-",
        "valuer"
    ],
    "wof:name":"Demuynck Expertisebureel",
    "wof:placetype":"venue"
},
  "geometry": {"coordinates":[3.782063961,51.1025085449],"type":"Point"}
}