{
  "type": "Feature",
  "properties": {
    "iso:country":"BE",
    "sg:address":"Stationsstraat 1",
    "sg:city":"Genk",
    "sg:orig_category":"Catering and organisatie van feesten Levering aan huis restaurants Restaurants",
    "sg:phone":"+32 89 30 37 93",
    "sg:postcode":"3600",
    "sg:province":"Limburg",
    "wof:name":"Ganghista",
    "wof:placetype":"venue"
},
  "geometry": {"coordinates":[5.5012960434,50.9656448364],"type":"Point"}
}