{
  "type": "Feature",
  "properties": {
    "iso:country":"BE",
    "sg:address":"Rue Des Postes 13",
    "sg:city":"Braine-le-comte",
    "sg:classifiers":[
        {
            "category":"Wholesale",
            "subcategory":"Meat",
            "type":"Manufacturing & Wholesale Goods"
        }
    ],
    "sg:phone":"+32 67 55 34 38",
    "sg:postcode":"7090",
    "sg:province":"Hainaut",
    "sg:tags":[
        "whol",
        "-"
    ],
    "wof:name":"Crokaert M",
    "wof:placetype":"venue"
},
  "geometry": {"coordinates":[4.1309981346,50.6124687195],"type":"Point"}
}