{
  "type": "Feature",
  "properties": {
    "addr:full":"Shoppingcenter 1 Genk Limburg 3600",
    "addr:housenumber":"1",
    "addr:postcode":"3600",
    "addr:street":"Shoppingcenter",
    "iso:country":"BE",
    "sg:address":"Shoppingcenter 1",
    "sg:city":"Genk",
    "sg:classifiers":[
        {
            "category":"Shopping",
            "subcategory":"Gifts & Souvenirs",
            "type":"Retail Goods"
        }
    ],
    "sg:phone":"+32 89 35 92 78",
    "sg:postcode":"3600",
    "sg:province":"Limburg",
    "sg:tags":[
        "geschenken"
    ],
    "wof:name":"Celini",
    "wof:placetype":"venue"
},
  "geometry": {"coordinates":[5.4990148544,50.9635848999],"type":"Point"}
}