{
  "type": "Feature",
  "properties": {
    "addr:full":"Karreveldlaan 50bb Sint-jans-molenbeek/molenbeek-saint-jean Bruxelles-Capitale 1080",
    "addr:housenumber":"50bb",
    "addr:postcode":"1080",
    "addr:street":"Karreveldlaan",
    "iso:country":"BE",
    "sg:address":"Karreveldlaan 50bb",
    "sg:city":"Sint-jans-molenbeek/molenbeek-saint-jean",
    "sg:orig_category":"Diensten voor huisdieren",
    "sg:phone":"+32 2 414 66 44",
    "sg:postcode":"1080",
    "sg:province":"Bruxelles-Capitale",
    "wof:name":"Toiletage Timmy",
    "wof:placetype":"venue"
},
  "geometry": {"coordinates":[4.3170800209,50.8612136841],"type":"Point"}
}