{
  "type": "Feature",
  "properties": {
    "addr:full":"Mechelsesteenweg 286 Bonheiden Antwerpen 2820",
    "addr:housenumber":"286",
    "addr:postcode":"2820",
    "addr:street":"Mechelsesteenweg",
    "iso:country":"BE",
    "sg:address":"Mechelsesteenweg 286",
    "sg:city":"Bonheiden",
    "sg:classifiers":[
        {
            "category":"Arts & Performance",
            "subcategory":"Art Gallery",
            "type":"Entertainment"
        }
    ],
    "sg:phone":"+32 15 55 31 74",
    "sg:postcode":"2820",
    "sg:province":"Antwerpen",
    "wof:name":"Laurent M Mattiss Bvba",
    "wof:placetype":"venue"
},
  "geometry": {"coordinates":[4.5259342194,51.0298957825],"type":"Point"}
}