{
  "type": "Feature",
  "properties": {
    "addr:full":"Steenstraat 16 Beringen Limburg 3580",
    "addr:housenumber":"16",
    "addr:postcode":"3580",
    "addr:street":"Steenstraat",
    "iso:country":"BE",
    "sg:address":"Steenstraat 16",
    "sg:city":"Beringen",
    "sg:orig_category":"Binnenhuisarchitecten",
    "sg:phone":"+32 11 43 12 50",
    "sg:postcode":"3580",
    "sg:province":"Limburg",
    "wof:name":"Creatief Ondernemen",
    "wof:placetype":"venue"
},
  "geometry": {"coordinates":[5.2226681709,51.0498085022],"type":"Point"}
}