{
  "type": "Feature",
  "properties": {
    "addr:full":"Stadenstraat 60 Kortemark (zarren-werken) West-Vlaanderen 8610",
    "addr:housenumber":"60",
    "addr:postcode":"8610",
    "addr:street":"Stadenstraat",
    "iso:country":"BE",
    "sg:address":"Stadenstraat 60",
    "sg:city":"Kortemark (zarren-werken)",
    "sg:classifiers":[
        {
            "category":"Home & Garden",
            "subcategory":"Building Materials",
            "type":"Retail Goods"
        }
    ],
    "sg:phone":"+32 51 56 60 94",
    "sg:postcode":"8610",
    "sg:province":"West-Vlaanderen",
    "sg:tags":[
        "house"
    ],
    "wof:name":"Weyne",
    "wof:placetype":"venue"
},
  "geometry": {"coordinates":[2.9635601044,51.0147476196],"type":"Point"}
}