{
  "type": "Feature",
  "properties": {
    "addr:full":"Brasschaatsesteenweg 179 Kalmthout Antwerpen 2920",
    "addr:housenumber":"179",
    "addr:postcode":"2920",
    "addr:street":"Brasschaatsesteenweg",
    "iso:country":"BE",
    "sg:address":"Brasschaatsesteenweg 179",
    "sg:city":"Kalmthout",
    "sg:orig_category":"Tuinbenodigdheden Tuinen",
    "sg:phone":"+32 3 666 53 33",
    "sg:postcode":"2920",
    "sg:province":"Antwerpen",
    "wof:name":"Crea Tuinen",
    "wof:placetype":"venue"
},
  "geometry": {"coordinates":[4.5070509911,51.3682365417],"type":"Point"}
}