{
  "type": "Feature",
  "properties": {
    "addr:full":"Rue Du Ch\u00e2teau 17 Chimay Hainaut 6460",
    "addr:housenumber":"17",
    "addr:postcode":"6460",
    "addr:street":"Rue Du Cha\u0302Teau",
    "iso:country":"BE",
    "sg:address":"Rue Du Ch\u00e2teau 17",
    "sg:city":"Chimay",
    "sg:classifiers":[
        {
            "category":"Health Services",
            "subcategory":"Health Practitioner",
            "type":"Services"
        }
    ],
    "sg:phone":"+32 60 21 24 68",
    "sg:postcode":"6460",
    "sg:province":"Hainaut",
    "sg:tags":[
        "physiotherapist"
    ],
    "wof:name":"Balestrucci Henri",
    "wof:placetype":"venue"
},
  "geometry": {"coordinates":[4.3141298294,50.0488815308],"type":"Point"}
}