{
  "type": "Feature",
  "properties": {
    "addr:full":"Les-morries 5 Couvin Namur 5660",
    "addr:housenumber":"5",
    "addr:postcode":"5660",
    "addr:street":"Les-Morries",
    "iso:country":"BE",
    "sg:address":"Les-morries 5",
    "sg:city":"Couvin",
    "sg:orig_category":"Instituts de beaut\u00e9",
    "sg:phone":"+32 60 34 42 79",
    "sg:postcode":"5660",
    "sg:province":"Namur",
    "wof:name":"Marie-christine Lorent",
    "wof:placetype":"venue"
},
  "geometry": {"coordinates":[4.458627224,50.0491447449],"type":"Point"}
}