{
  "type": "Feature",
  "properties": {
    "addr:full":"'t Walletje 80 Knokke-heist (westkapelle) West-Vlaanderen 8300",
    "addr:housenumber":"80",
    "addr:postcode":"8300",
    "addr:street":"' T Walletje",
    "iso:country":"BE",
    "sg:address":"'t Walletje 80",
    "sg:city":"Knokke-heist (westkapelle)",
    "sg:classifiers":[
        {
            "category":"Home & Garden",
            "subcategory":"Carpets & Floor Coverings",
            "type":"Retail Goods"
        }
    ],
    "sg:phone":"+32 50 62 19 75",
    "sg:postcode":"8300",
    "sg:province":"West-Vlaanderen",
    "sg:tags":[
        "parquet"
    ],
    "wof:name":"Danneels-interieur Bvba",
    "wof:placetype":"venue"
},
  "geometry": {"coordinates":[3.288079977,51.3198738098],"type":"Point"}
}