{
  "type": "Feature",
  "properties": {
    "iso:country":"BE",
    "sg:address":"Avenue Des Acacias 11",
    "sg:city":"Moeskroen/mouscron",
    "sg:orig_category":"Agences immobili\u00e8res",
    "sg:phone":"+32 56 48 96 58",
    "sg:postcode":"7711",
    "sg:province":"Hainaut",
    "wof:name":"Carcom",
    "wof:placetype":"venue"
},
  "geometry": {"coordinates":[3.2657730579,50.7366256714],"type":"Point"}
}