{
  "type": "Feature",
  "properties": {
    "addr:full":"Hamelseweg 4 Opwijk (mazenzele) Vlaams-Brabant 1745",
    "addr:housenumber":"4",
    "addr:postcode":"1745",
    "addr:street":"Hamelseweg",
    "iso:country":"BE",
    "sg:address":"Hamelseweg 4",
    "sg:city":"Opwijk (mazenzele)",
    "sg:classifiers":[
        {
            "category":"Personal",
            "subcategory":"Beauty Salon",
            "type":"Services"
        }
    ],
    "sg:phone":"+32 52 35 69 41",
    "sg:postcode":"1745",
    "sg:province":"Vlaams-Brabant",
    "sg:tags":[
        "lady",
        "-",
        "hairdressing"
    ],
    "wof:name":"Vermeir Nancy",
    "wof:placetype":"venue"
},
  "geometry": {"coordinates":[4.1677250862,50.9460296631],"type":"Point"}
}