{
  "type": "Feature",
  "properties": {
    "addr:full":"Chauss\u00e9e De Bruxelles 68 Waterloo Brabant Wallon 1410",
    "addr:housenumber":"68",
    "addr:postcode":"1410",
    "addr:street":"Chausse\u0301E De Bruxelles",
    "iso:country":"BE",
    "sg:address":"Chauss\u00e9e De Bruxelles 68",
    "sg:city":"Waterloo",
    "sg:classifiers":[
        {
            "category":"Deli",
            "type":"Food & Drink"
        }
    ],
    "sg:phone":"+32 2 351 35 35",
    "sg:postcode":"1410",
    "sg:province":"Brabant Wallon",
    "sg:tags":[
        "delicatessen"
    ],
    "wof:name":"La Maree Gourmande",
    "wof:placetype":"venue"
},
  "geometry": {"coordinates":[4.398624897,50.7281303406],"type":"Point"}
}