{
  "type": "Feature",
  "properties": {
    "iso:country":"BE",
    "sg:address":"Exelgaarden 30",
    "sg:city":"Heusden-zolder",
    "sg:orig_category":"Elektrische installaties voor woningen",
    "sg:phone":"+32 11 42 58 06",
    "sg:postcode":"3550",
    "sg:province":"Limburg",
    "wof:name":"Wim Schaeken",
    "wof:placetype":"venue"
},
  "geometry": {"coordinates":[5.2858700752,51.0403442383],"type":"Point"}
}