{
  "type": "Feature",
  "properties": {
    "addr:full":"Elisabethlaan 4 Middelkerke (lombardsijde) West-Vlaanderen 8434",
    "addr:housenumber":"4",
    "addr:postcode":"8434",
    "addr:street":"Elisabethlaan",
    "iso:country":"BE",
    "sg:address":"Elisabethlaan 4",
    "sg:city":"Middelkerke (lombardsijde)",
    "sg:classifiers":[
        {
            "category":"Recreation",
            "subcategory":"Campground",
            "type":"Entertainment"
        }
    ],
    "sg:phone":"+32 58 23 68 39",
    "sg:postcode":"8434",
    "sg:province":"West-Vlaanderen",
    "sg:tags":[
        "site",
        "camping"
    ],
    "wof:name":"De Lombarde",
    "wof:placetype":"venue"
},
  "geometry": {"coordinates":[2.7517850399,51.1548957825],"type":"Point"}
}