{
  "type": "Feature",
  "properties": {
    "addr:full":"Kerkstraat 26ba Brecht Antwerpen 2960",
    "addr:housenumber":"26ba",
    "addr:postcode":"2960",
    "addr:street":"Kerkstraat",
    "iso:country":"BE",
    "sg:address":"Kerkstraat 26ba",
    "sg:city":"Brecht",
    "sg:classifiers":[
        {
            "category":"Personal",
            "subcategory":"Beauty Salon",
            "type":"Services"
        }
    ],
    "sg:phone":"+32 3 313 68 79",
    "sg:postcode":"2960",
    "sg:province":"Antwerpen",
    "sg:tags":[
        "de",
        "coiffure"
    ],
    "wof:name":"Coiffure Sylvia",
    "wof:placetype":"venue"
},
  "geometry": {"coordinates":[4.5804839134,51.2922477722],"type":"Point"}
}