{
  "type": "Feature",
  "properties": {
    "iso:country":"BE",
    "sg:address":"Avenue Des Combattants 75b",
    "sg:city":"Genappe (bousval)",
    "sg:classifiers":[
        {
            "category":"Retail",
            "subcategory":"Auto Repair",
            "type":"Services"
        }
    ],
    "sg:phone":"+32 67 77 34 16",
    "sg:postcode":"1470",
    "sg:province":"Brabant Wallon",
    "sg:tags":[
        "automobile-body"
    ],
    "wof:name":"Carrosserie De Bousval Sprl",
    "wof:placetype":"venue"
},
  "geometry": {"coordinates":[4.5087108612,50.616230011],"type":"Point"}
}