{
  "type": "Feature",
  "properties": {
    "iso:country":"BE",
    "sg:address":"Chauss\u00c9e Dernier Patard 108",
    "sg:city":"Genappe",
    "sg:orig_category":"Articles non-alimentaires",
    "sg:phone":"+32 67 77 25 15",
    "sg:postcode":"1470",
    "sg:province":"Brabant Wallon",
    "wof:name":"Stock Am\u00c9ricain",
    "wof:placetype":"venue"
},
  "geometry": {"coordinates":[4.4544110298,50.582195282],"type":"Point"}
}