{
  "type": "Feature",
  "properties": {
    "iso:country":"BE",
    "sg:address":"Vandammestraat 5-7",
    "sg:city":"Hoeilaart",
    "sg:classifiers":[
        {
            "category":"Professional",
            "subcategory":"Management & Consulting",
            "type":"Services"
        }
    ],
    "sg:phone":"+32 2 674 13 11",
    "sg:postcode":"1560",
    "sg:province":"Vlaams-Brabant",
    "sg:tags":[
        "consultant",
        "agency",
        "advertising"
    ],
    "wof:name":"Mc Cann-erickson Co Sa",
    "wof:placetype":"venue"
},
  "geometry": {"coordinates":[4.472949028,50.76820755],"type":"Point"}
}