{
  "type": "Feature",
  "properties": {
    "iso:country":"BE",
    "sg:address":"Gemenestraat 7",
    "sg:city":"Beveren",
    "sg:orig_category":"Fruits and l\u00e9gumes Eleveurs and marchands de porcs",
    "sg:phone":"+32 3 773 44 56",
    "sg:postcode":"9130",
    "sg:province":"Oost-Vlaanderen",
    "wof:name":"Georges Van Den Bergh",
    "wof:placetype":"venue"
},
  "geometry": {"coordinates":[4.1854171753,51.2763633728],"type":"Point"}
}