{
  "type": "Feature",
  "properties": {
    "iso:country":"BE",
    "sg:address":"Kloskensstraat 20",
    "sg:city":"Herzele (hillegem)",
    "sg:orig_category":"Non-Classified Establishments",
    "sg:phone":"+32 9 361 84 94",
    "sg:postcode":"9550",
    "sg:province":"Oost-Vlaanderen",
    "wof:name":"Mortier K",
    "wof:placetype":"venue"
},
  "geometry": {"coordinates":[3.85055089,50.8940391541],"type":"Point"}
}