{
  "type": "Feature",
  "properties": {
    "iso:country":"BE",
    "sg:address":"Avenue Des Champs 45",
    "sg:city":"Pecq (warcoing)",
    "sg:classifiers":[
        {
            "category":"Home & Garden",
            "subcategory":"Carpets & Floor Coverings",
            "type":"Retail Goods"
        }
    ],
    "sg:phone":"+32 56 45 75 87",
    "sg:postcode":"7740",
    "sg:province":"Hainaut",
    "sg:tags":[
        "tile"
    ],
    "wof:name":"Carle & Fils",
    "wof:placetype":"venue"
},
  "geometry": {"coordinates":[3.3438398838,50.7068214417],"type":"Point"}
}