{
  "type": "Feature",
  "properties": {
    "addr:full":"Chauss\u00e9e Freddy Terwagne 8 Amay Li\u00e8ge 4540",
    "addr:housenumber":"8",
    "addr:postcode":"4540",
    "addr:street":"Chausse\u0301E Freddy Terwagne",
    "iso:country":"BE",
    "sg:address":"Chauss\u00e9e Freddy Terwagne 8",
    "sg:city":"Amay",
    "sg:classifiers":[
        {
            "category":"Shopping",
            "subcategory":"Florist",
            "type":"Retail Goods"
        }
    ],
    "sg:phone":"+32 85 31 40 40",
    "sg:postcode":"4540",
    "sg:province":"Li\u00e8ge",
    "wof:name":"Martin Fleurs",
    "wof:placetype":"venue"
},
  "geometry": {"coordinates":[5.3196320534,50.5485153198],"type":"Point"}
}