{
  "type": "Feature",
  "properties": {
    "addr:full":"Meersveld 2 Buggenhout Oost-Vlaanderen 9255",
    "addr:housenumber":"2",
    "addr:postcode":"9255",
    "addr:street":"Meersveld",
    "iso:country":"BE",
    "sg:address":"Meersveld 2",
    "sg:city":"Buggenhout",
    "sg:orig_category":"Diverse bedrijfsbeheeradviesbureaus",
    "sg:phone":"+32 52 39 70 37",
    "sg:postcode":"9255",
    "sg:province":"Oost-Vlaanderen",
    "wof:name":"Jds Consulting",
    "wof:placetype":"venue"
},
  "geometry": {"coordinates":[4.2164349556,51.0269012451],"type":"Point"}
}