{
  "type": "Feature",
  "properties": {
    "iso:country":"BE",
    "sg:address":"Weverslaan 28",
    "sg:city":"Lokeren",
    "sg:classifiers":[
        {
            "category":"Building & Trades",
            "subcategory":"Construction",
            "type":"Services"
        }
    ],
    "sg:phone":"+32 9 348 13 89",
    "sg:postcode":"9160",
    "sg:province":"Oost-Vlaanderen",
    "sg:tags":[
        "carpenter"
    ],
    "wof:name":"Bontinck J",
    "wof:placetype":"venue"
},
  "geometry": {"coordinates":[4.0144782066,51.1110229492],"type":"Point"}
}