{
  "type": "Feature",
  "properties": {
    "iso:country":"BE",
    "sg:address":"Luyckstraat 3",
    "sg:city":"Brecht",
    "sg:orig_category":"Eleveurs de bovins",
    "sg:phone":"+32 3 313 95 67",
    "sg:postcode":"2960",
    "sg:province":"Antwerpen",
    "wof:name":"Marcel Van Gastel",
    "wof:placetype":"venue"
},
  "geometry": {"coordinates":[4.6451449394,51.361038208],"type":"Point"}
}