{
  "type": "Feature",
  "properties": {
    "iso:country":"BE",
    "sg:address":"Leenstraat 84",
    "sg:city":"Izegem",
    "sg:orig_category":"Drukkerijen and copyshops",
    "sg:phone":"+32 51 33 20 20",
    "sg:postcode":"8870",
    "sg:province":"West-Vlaanderen",
    "wof:name":"Serfiko",
    "wof:placetype":"venue"
},
  "geometry": {"coordinates":[3.1935369968,50.905292511],"type":"Point"}
}