{
  "type": "Feature",
  "properties": {
    "addr:full":"Jean De La Hoeselaan 54 Sint-jans-molenbeek/molenbeek- Bruxelles-Capitale 1080",
    "addr:housenumber":"54",
    "addr:postcode":"1080",
    "addr:street":"Jean De La Hoeselaan;Molenbeek",
    "iso:country":"BE",
    "sg:address":"Jean De La Hoeselaan 54",
    "sg:city":"Sint-jans-molenbeek/molenbeek-",
    "sg:orig_category":"Divers amusement Diverse zakelijke dienstverlening",
    "sg:phone":"+32 2 414 31 47",
    "sg:postcode":"1080",
    "sg:province":"Bruxelles-Capitale",
    "wof:name":"Domo Entertainments",
    "wof:placetype":"venue"
},
  "geometry": {"coordinates":[4.3144760132,50.8593635559],"type":"Point"}
}