{
  "type": "Feature",
  "properties": {
    "addr:full":"Rue De Nivelles 19 Braine-le-ch\u00e2teau Brabant Wallon 1440",
    "addr:housenumber":"19",
    "addr:postcode":"1440",
    "addr:street":"Rue De Nivelles",
    "iso:country":"BE",
    "sg:address":"Rue De Nivelles 19",
    "sg:city":"Braine-le-ch\u00e2teau",
    "sg:classifiers":[
        {
            "category":"Personal",
            "subcategory":"Beauty Salon",
            "type":"Services"
        }
    ],
    "sg:phone":"+32 2 366 96 17",
    "sg:postcode":"1440",
    "sg:province":"Brabant Wallon",
    "sg:tags":[
        "lady",
        "-",
        "hairdressing"
    ],
    "wof:name":"Willy",
    "wof:placetype":"venue"
},
  "geometry": {"coordinates":[4.2733469009,50.6821327209],"type":"Point"}
}