{
  "type": "Feature",
  "properties": {
    "iso:country":"BE",
    "sg:address":"Turfputstraat 29",
    "sg:city":"Berlare",
    "sg:orig_category":"Installation \u00e9lectrique r\u00e9sidentielle",
    "sg:phone":"+32 52 42 21 60",
    "sg:postcode":"9290",
    "sg:province":"Oost-Vlaanderen",
    "wof:name":"Hans Van Acker",
    "wof:placetype":"venue"
},
  "geometry": {"coordinates":[3.9992780685,51.0290756226],"type":"Point"}
}