{
  "type": "Feature",
  "properties": {
    "iso:country":"BE",
    "sg:address":"Mechelsesteenweg 153",
    "sg:city":"Mortsel",
    "sg:orig_category":"Huishoudapparaten, televisies and radio's",
    "sg:phone":"+32 3 457 10 01",
    "sg:postcode":"2640",
    "sg:province":"Antwerpen",
    "wof:name":"Vlemac",
    "wof:placetype":"venue"
},
  "geometry": {"coordinates":[4.4547739029,51.1653022766],"type":"Point"}
}