{
  "type": "Feature",
  "properties": {
    "addr:full":"Tiensesteenweg 81 Glabbeek (glabbeek-zuurbemde) Vlaams-Brabant 3380",
    "addr:housenumber":"81",
    "addr:postcode":"3380",
    "addr:street":"Tiensesteenweg",
    "iso:country":"BE",
    "sg:address":"Tiensesteenweg 81",
    "sg:city":"Glabbeek (glabbeek-zuurbemde)",
    "sg:classifiers":[
        {
            "category":"Retail",
            "subcategory":"Auto Repair",
            "type":"Services"
        }
    ],
    "sg:phone":"+32 16 77 13 26",
    "sg:postcode":"3380",
    "sg:province":"Vlaams-Brabant",
    "sg:tags":[
        "automobile-body"
    ],
    "wof:name":"Vangoitsenhoven & Zn",
    "wof:placetype":"venue"
},
  "geometry": {"coordinates":[4.9546399117,50.8596687317],"type":"Point"}
}