{
  "type": "Feature",
  "properties": {
    "iso:country":"BE",
    "sg:address":"Avenue Des Volontaires 34",
    "sg:city":"Etterbeek",
    "sg:orig_category":"Bouwmaterialen Gh Loodgieterij and centrale verwarming Gh Loodgieterij, verwarming and sanitaire ins",
    "sg:phone":"+32 2 733 24 54",
    "sg:postcode":"1040",
    "sg:province":"Bruxelles-Capitale",
    "wof:name":"Ambiance Et Confort",
    "wof:placetype":"venue"
},
  "geometry": {"coordinates":[4.4024581909,50.826385498],"type":"Point"}
}