{
  "type": "Feature",
  "properties": {
    "iso:country":"BE",
    "sg:address":"Rue Thier Des Gottes 28",
    "sg:city":"Fleron",
    "sg:orig_category":"Plaatsen van vloer- and muurbekleding Schilders",
    "sg:phone":"+32 4 358 41 19",
    "sg:postcode":"4624",
    "sg:province":"Li\u00e8ge",
    "wof:name":"Christian Dezoppy",
    "wof:placetype":"venue"
},
  "geometry": {"coordinates":[5.6612658501,50.6006851196],"type":"Point"}
}