{
  "type": "Feature",
  "properties": {
    "iso:country":"BE",
    "sg:address":"Avenue Du Roi 181",
    "sg:city":"Vorst/forest",
    "sg:orig_category":"Installation \u00e9lectrique r\u00e9sidentielle",
    "sg:phone":"+32 2 537 07 37",
    "sg:postcode":"1190",
    "sg:province":"Bruxelles-Capitale",
    "wof:name":"Roger Musso",
    "wof:placetype":"venue"
},
  "geometry": {"coordinates":[4.3343548775,50.8254051208],"type":"Point"}
}