{
  "type": "Feature",
  "properties": {
    "addr:full":"Avenue Des P\u00e2querettes 55 Waterloo Brabant Wallon 1410",
    "addr:housenumber":"55",
    "addr:postcode":"1410",
    "addr:street":"Avenue Des Pa\u0302Querettes",
    "iso:country":"BE",
    "sg:address":"Avenue Des P\u00e2querettes 55",
    "sg:city":"Waterloo",
    "sg:classifiers":[
        {
            "category":"Social Services",
            "subcategory":"Job Training",
            "type":"Services"
        }
    ],
    "sg:phone":"+32 2 353 16 34",
    "sg:postcode":"1410",
    "sg:province":"Brabant Wallon",
    "sg:tags":[
        "condiment",
        "spice"
    ],
    "wof:name":"Caspian Tradition Sa",
    "wof:placetype":"venue"
},
  "geometry": {"coordinates":[4.3828630447,50.7151184082],"type":"Point"}
}