{
  "type": "Feature",
  "properties": {
    "addr:full":"Sint-jansstraat 110 Staden West-Vlaanderen 8840",
    "addr:housenumber":"110",
    "addr:postcode":"8840",
    "addr:street":"Sint-Jansstraat",
    "iso:country":"BE",
    "sg:address":"Sint-jansstraat 110",
    "sg:city":"Staden",
    "sg:orig_category":"Entretien and r\u00e9parations de voitures",
    "sg:phone":"+32 51 70 11 40",
    "sg:postcode":"8840",
    "sg:province":"West-Vlaanderen",
    "wof:name":"Garage De Ruyter",
    "wof:placetype":"venue"
},
  "geometry": {"coordinates":[3.0156478882,50.9737434387],"type":"Point"}
}