{
  "type": "Feature",
  "properties": {
    "iso:country":"BE",
    "sg:address":"De Maaskens 31",
    "sg:city":"Arendonk",
    "sg:orig_category":"Installation de menuiserie en bois and plastique",
    "sg:phone":"+32 14 67 79 80",
    "sg:postcode":"2370",
    "sg:province":"Antwerpen",
    "wof:name":"Wijnen-claes",
    "wof:placetype":"venue"
},
  "geometry": {"coordinates":[5.0879898071,51.3229598999],"type":"Point"}
}