{
  "type": "Feature",
  "properties": {
    "addr:full":"Wilgenlaan 86 Stabroek (hoevenen) Antwerpen 2940",
    "addr:housenumber":"86",
    "addr:postcode":"2940",
    "addr:street":"Wilgenlaan",
    "iso:country":"BE",
    "sg:address":"Wilgenlaan 86",
    "sg:city":"Stabroek (hoevenen)",
    "sg:classifiers":[
        {
            "category":"Shopping",
            "subcategory":"Gifts & Souvenirs",
            "type":"Retail Goods"
        }
    ],
    "sg:phone":"+32 3 664 99 43",
    "sg:postcode":"2940",
    "sg:province":"Antwerpen",
    "sg:tags":[
        "-"
    ],
    "wof:name":"Gielis M",
    "wof:placetype":"venue"
},
  "geometry": {"coordinates":[4.3649148941,51.331943512],"type":"Point"}
}