{
  "type": "Feature",
  "properties": {
    "addr:full":"Avenue Paul Pastur 8 Chatelet Hainaut 6200",
    "addr:housenumber":"8",
    "addr:postcode":"6200",
    "addr:street":"Avenue Paul Pastur;Hainaut",
    "iso:country":"BE",
    "sg:address":"Avenue Paul Pastur 8",
    "sg:city":"Chatelet",
    "sg:orig_category":"Banques and organismes de cr\u00e9dit",
    "sg:phone":"+32 71 39 28 06",
    "sg:postcode":"6200",
    "sg:province":"Hainaut",
    "wof:name":"Fortis",
    "wof:placetype":"venue"
},
  "geometry": {"coordinates":[4.5171318054,50.3903274536],"type":"Point"}
}