{
  "type": "Feature",
  "properties": {
    "addr:full":"Rue Germain Michiels 48 Beaumont Hainaut 6500",
    "addr:housenumber":"48",
    "addr:postcode":"6500",
    "addr:street":"Rue Germain Michiels;Hainaut",
    "iso:country":"BE",
    "sg:address":"Rue Germain Michiels 48",
    "sg:city":"Beaumont",
    "sg:orig_category":"Landmeters",
    "sg:phone":"+32 71 58 83 95",
    "sg:postcode":"6500",
    "sg:province":"Hainaut",
    "wof:name":"Frederic Descamps",
    "wof:placetype":"venue"
},
  "geometry": {"coordinates":[4.2435188293,50.2394485474],"type":"Point"}
}