{
  "type": "Feature",
  "properties": {
    "iso:country":"BE",
    "sg:address":"Damse Steenweg 29",
    "sg:city":"Dudzele",
    "sg:orig_category":"Installatie van houten of kunststof schrijnwerk Installatie van metalen schrijnwerk",
    "sg:phone":"+32 50 59 91 43",
    "sg:postcode":"8380",
    "sg:province":"West-Vlaanderen",
    "wof:name":"Bvba Brusselle En Zoon",
    "wof:placetype":"venue"
},
  "geometry": {"coordinates":[3.2328391075,51.2758369446],"type":"Point"}
}