{
  "type": "Feature",
  "properties": {
    "addr:full":"Chauss\u00e9e De Waterloo 391 Bruxelles (ixelles) Bruxelles-Capitale 1050",
    "addr:housenumber":"391",
    "addr:postcode":"1050",
    "addr:street":"Chausse\u0301E De Waterloo",
    "iso:country":"BE",
    "sg:address":"Chauss\u00e9e De Waterloo 391",
    "sg:city":"Bruxelles (ixelles)",
    "sg:classifiers":[
        {
            "category":"Professional",
            "subcategory":"Art Services",
            "type":"Services"
        }
    ],
    "sg:phone":"+32 2 346 48 49",
    "sg:postcode":"1050",
    "sg:province":"Bruxelles-Capitale",
    "sg:tags":[
        "picture",
        "framer"
    ],
    "wof:name":"Encamir",
    "wof:placetype":"venue"
},
  "geometry": {"coordinates":[4.3550319672,50.8220481873],"type":"Point"}
}