{
  "type": "Feature",
  "properties": {
    "iso:country":"BE",
    "sg:address":"Heilig-kruisplein 5",
    "sg:city":"Roeselare",
    "sg:classifiers":[
        {
            "category":"Health Services",
            "subcategory":"Health Practitioner",
            "type":"Services"
        }
    ],
    "sg:phone":"+32 51 69 01 31",
    "sg:postcode":"8800",
    "sg:province":"West-Vlaanderen",
    "sg:tags":[
        "osteopath"
    ],
    "wof:name":"Schelpe J",
    "wof:placetype":"venue"
},
  "geometry": {"coordinates":[3.1456298828,50.9680557251],"type":"Point"}
}