{
  "type": "Feature",
  "properties": {
    "iso:country":"BE",
    "sg:address":"Maantjessteenweg 159",
    "sg:city":"Merksem",
    "sg:classifiers":[
        {
            "category":"Restaurant",
            "type":"Food & Drink"
        }
    ],
    "sg:phone":"+32 3 644 28 11",
    "sg:postcode":"2170",
    "sg:province":"Antwerpen",
    "wof:name":"Sardis",
    "wof:placetype":"venue"
},
  "geometry": {"coordinates":[4.437125206,51.25522995],"type":"Point"}
}