{
  "type": "Feature",
  "properties": {
    "iso:country":"BE",
    "sg:address":"Chauss\u00e9e De Marche 83",
    "sg:city":"Assesse",
    "sg:classifiers":[
        {
            "category":"Health Services",
            "subcategory":"Dentist",
            "type":"Services"
        }
    ],
    "sg:phone":"+32 83 65 59 77",
    "sg:postcode":"5330",
    "sg:province":"Namur",
    "wof:name":"Debuisson D",
    "wof:placetype":"venue"
},
  "geometry": {"coordinates":[5.0258450508,50.367565155],"type":"Point"}
}