{
  "type": "Feature",
  "properties": {
    "iso:country":"BE",
    "sg:address":"Poperingseweg 65bbis",
    "sg:city":"Ieper",
    "sg:orig_category":"V\u00e9t\u00e9rinaires",
    "sg:phone":"+32 57 20 06 21",
    "sg:postcode":"8900",
    "sg:province":"West-Vlaanderen",
    "wof:name":"Rita Vanwildemeersch",
    "wof:placetype":"venue"
},
  "geometry": {"coordinates":[2.870429039,50.8490066528],"type":"Point"}
}