{
  "type": "Feature",
  "properties": {
    "iso:country":"BE",
    "sg:address":"Mechelsesteenweg 123b3ev",
    "sg:city":"Antwerpen",
    "sg:orig_category":"Tweedehandsgoederen",
    "sg:phone":"+32 3 218 42 92",
    "sg:postcode":"2018",
    "sg:province":"Antwerpen",
    "wof:name":"Jef Meert",
    "wof:placetype":"venue"
},
  "geometry": {"coordinates":[4.4101939201,51.2062149048],"type":"Point"}
}