{
  "type": "Feature",
  "properties": {
    "iso:country":"BE",
    "sg:address":"Waalvest 59",
    "sg:city":"Menen",
    "sg:orig_category":"Benzinestations and brandstoffen",
    "sg:phone":"+32 56 51 41 19",
    "sg:postcode":"8930",
    "sg:province":"West-Vlaanderen",
    "wof:name":"Fa. Fournier",
    "wof:placetype":"venue"
},
  "geometry": {"coordinates":[3.1264960766,50.7927703857],"type":"Point"}
}