{
  "type": "Feature",
  "properties": {
    "iso:country":"BE",
    "sg:address":"Charles De Tollenaereln 48",
    "sg:city":"Anderlecht/anderlecht",
    "sg:orig_category":"Dierenartsen",
    "sg:phone":"+32 2 521 82 71",
    "sg:postcode":"1070",
    "sg:province":"Bruxelles-Capitale",
    "wof:name":"Alain Milet",
    "wof:placetype":"venue"
},
  "geometry": {"coordinates":[4.2885351181,50.8281669617],"type":"Point"}
}