{
  "type": "Feature",
  "properties": {
    "iso:country":"BE",
    "sg:address":"Bld Albert-elisabeth 90",
    "sg:city":"Mons",
    "sg:orig_category":"V\u00e9t\u00e9rinaires",
    "sg:phone":"+32 65 35 16 69",
    "sg:postcode":"7000",
    "sg:province":"Hainaut",
    "wof:name":"Christine Jaucot",
    "wof:placetype":"venue"
},
  "geometry": {"coordinates":[3.9486188889,50.4462051392],"type":"Point"}
}