{
  "type": "Feature",
  "properties": {
    "iso:country":"BE",
    "sg:address":"Zwaantjesstraat 10",
    "sg:city":"Melle",
    "sg:orig_category":"Equipement divers pour commerces Location de biens divers. Construction de maisons",
    "sg:phone":"+32 9 231 43 22",
    "sg:postcode":"9090",
    "sg:province":"Oost-Vlaanderen",
    "wof:name":"Johan Brusseel",
    "wof:placetype":"venue"
},
  "geometry": {"coordinates":[3.7832989693,51.0124816895],"type":"Point"}
}