{
  "type": "Feature",
  "properties": {
    "iso:country":"BE",
    "sg:address":"Chauss\u00c9e De Lasne 18",
    "sg:city":"Rixensart",
    "sg:orig_category":"Boekenuitgeverijen Drukkerijen and copyshops Krantenuitgeverijen Tijdschriftenuitgeverijen",
    "sg:phone":"+32 2 653 72 89",
    "sg:postcode":"1330",
    "sg:province":"Brabant Wallon",
    "wof:name":"L'edition Locale",
    "wof:placetype":"venue"
},
  "geometry": {"coordinates":[4.510035038,50.7071418762],"type":"Point"}
}