{
  "type": "Feature",
  "properties": {
    "iso:country":"BE",
    "sg:address":"Nerenweg 43",
    "sg:city":"Laarne",
    "sg:classifiers":[
        {
            "category":"Professional",
            "subcategory":"Accounting & Tax Preparation",
            "type":"Services"
        }
    ],
    "sg:phone":"+32 9 367 91 00",
    "sg:postcode":"9270",
    "sg:province":"Oost-Vlaanderen",
    "sg:tags":[
        "accountant"
    ],
    "wof:name":"Wim Van De Walle",
    "wof:placetype":"venue"
},
  "geometry": {"coordinates":[3.9096050262,51.0356140137],"type":"Point"}
}