{
  "type": "Feature",
  "properties": {
    "iso:country":"BE",
    "sg:address":"Ieperseweg 26",
    "sg:city":"Roeselare (oekene)",
    "sg:orig_category":"Non-Classified Establishments",
    "sg:phone":"+32 51 20 15 85",
    "sg:postcode":"8800",
    "sg:province":"West-Vlaanderen",
    "wof:name":"Baele W (weverij)",
    "wof:placetype":"venue"
},
  "geometry": {"coordinates":[3.1172599792,50.9005050659],"type":"Point"}
}