{
  "type": "Feature",
  "properties": {
    "iso:country":"BE",
    "sg:address":"Rue De Courcelles 5ba",
    "sg:city":"Seneffe",
    "sg:classifiers":[
        {
            "category":"Cafe",
            "type":"Food & Drink"
        }
    ],
    "sg:phone":"+32 64 27 65 60",
    "sg:postcode":"7180",
    "sg:province":"Hainaut",
    "sg:tags":[
        "caf\u00e9s"
    ],
    "wof:name":"Guy Ockerman",
    "wof:placetype":"venue"
},
  "geometry": {"coordinates":[4.2786121368,50.5237579346],"type":"Point"}
}