{
  "type": "Feature",
  "properties": {
    "addr:full":"R Grande 104 Anhee 5198",
    "addr:housenumber":"104",
    "addr:postcode":"5198",
    "addr:street":"R Grande",
    "iso:country":"BE",
    "sg:address":"R Grande 104",
    "sg:city":"Anhee",
    "sg:classifiers":[
        {
            "category":"Banks & Credit Unions",
            "subcategory":"Bank",
            "type":"Services"
        }
    ],
    "sg:phone":"+32 82 61 34 35",
    "sg:postcode":"5198",
    "wof:name":"Banque Bruxelles Lambert Sa",
    "wof:placetype":"venue"
},
  "geometry": {"coordinates":[25.4563503265,43.3878517151],"type":"Point"}
}