{
  "type": "Feature",
  "properties": {
    "iso:country":"BE",
    "sg:address":"Route De Barvaux 1",
    "sg:city":"Somme-leuze (heure)",
    "sg:classifiers":[
        {
            "category":"Government",
            "subcategory":"Department Of Motor Vehicles",
            "type":"Public Place"
        }
    ],
    "sg:phone":"+32 86 32 31 55",
    "sg:postcode":"5377",
    "sg:province":"Namur",
    "sg:tags":[
        "planing",
        "wood",
        "sawing"
    ],
    "wof:name":"G\u00e9rard J",
    "wof:placetype":"venue"
},
  "geometry": {"coordinates":[5.3698949814,50.3404350281],"type":"Point"}
}