{
  "type": "Feature",
  "properties": {
    "iso:country":"BE",
    "sg:address":"Schulensebaan 14",
    "sg:city":"Lummen",
    "sg:classifiers":[
        {
            "category":"Professional",
            "subcategory":"Art Services",
            "type":"Services"
        }
    ],
    "sg:phone":"+32 13 52 33 10",
    "sg:postcode":"3560",
    "sg:province":"Limburg",
    "sg:tags":[
        "photographer"
    ],
    "wof:name":"Hemerijckx K",
    "wof:placetype":"venue"
},
  "geometry": {"coordinates":[5.190849781,50.9819717407],"type":"Point"}
}