{
  "type": "Feature",
  "properties": {
    "addr:full":"Rue De Montigny 122 Charleroi Hainaut 6000",
    "addr:housenumber":"122",
    "addr:postcode":"6000",
    "addr:street":"Rue De Montigny;Hainaut",
    "iso:country":"BE",
    "sg:address":"Rue De Montigny 122",
    "sg:city":"Charleroi",
    "sg:classifiers":[
        {
            "category":"Arts & Performance",
            "subcategory":"Theater",
            "type":"Entertainment"
        }
    ],
    "sg:phone":"+32 71 31 40 79",
    "sg:postcode":"6000",
    "sg:province":"Hainaut",
    "sg:tags":[
        "concert-halls",
        "theatre"
    ],
    "wof:name":"Th\u00e9\u00e2tre De L'ancre",
    "wof:placetype":"venue"
},
  "geometry": {"coordinates":[4.4490652084,50.4065246582],"type":"Point"}
}