{
  "type": "Feature",
  "properties": {
    "addr:full":"Valkerijlaan 79 Watermaal-bosvoorde/watermael-boitsfort Bruxelles-Capitale 1170",
    "addr:housenumber":"79",
    "addr:postcode":"1170",
    "addr:street":"Valkerijlaan",
    "iso:country":"BE",
    "sg:address":"Valkerijlaan 79",
    "sg:city":"Watermaal-bosvoorde/watermael-boitsfort",
    "sg:orig_category":"Fotografen and fotostudio's",
    "sg:phone":"+32 2 673 11 03",
    "sg:postcode":"1170",
    "sg:province":"Bruxelles-Capitale",
    "wof:name":"Jean Hanssens",
    "wof:placetype":"venue"
},
  "geometry": {"coordinates":[4.4186019897,50.8025474548],"type":"Point"}
}