{
  "type": "Feature",
  "properties": {
    "addr:full":"Peperstraat 1 Hamme Oost-Vlaanderen 9220",
    "addr:housenumber":"1",
    "addr:postcode":"9220",
    "addr:street":"Peperstraat",
    "iso:country":"BE",
    "sg:address":"Peperstraat 1",
    "sg:city":"Hamme",
    "sg:classifiers":[
        {
            "category":"Professional",
            "subcategory":"Art Services",
            "type":"Services"
        }
    ],
    "sg:phone":"+32 52 47 80 00",
    "sg:postcode":"9220",
    "sg:province":"Oost-Vlaanderen",
    "sg:tags":[
        "photographer"
    ],
    "wof:name":"Merckpoel N",
    "wof:placetype":"venue"
},
  "geometry": {"coordinates":[4.1393198967,51.0975036621],"type":"Point"}
}