{
  "type": "Feature",
  "properties": {
    "iso:country":"BE",
    "sg:address":"Spekmolenstraat 22",
    "sg:city":"Herentals",
    "sg:orig_category":"Newspapers, magazines, periodicals - Distribution",
    "sg:phone":"+32 14 21 96 59",
    "sg:postcode":"2200",
    "sg:province":"Antwerpen",
    "wof:name":"Schellens",
    "wof:placetype":"venue"
},
  "geometry": {"coordinates":[4.8385119438,51.1719589233],"type":"Point"}
}