{
  "type": "Feature",
  "properties": {
    "addr:full":"Jef Tinellaan 42 Maldegem Oost-Vlaanderen 9990",
    "addr:housenumber":"42",
    "addr:postcode":"9990",
    "addr:street":"Jef Tinellaan",
    "iso:country":"BE",
    "sg:address":"Jef Tinellaan 42",
    "sg:city":"Maldegem",
    "sg:orig_category":"Loodgieterij, verwarming and sanitaire installaties",
    "sg:phone":"+32 50 71 71 23",
    "sg:postcode":"9990",
    "sg:province":"Oost-Vlaanderen",
    "wof:name":"Patrick Pauwelyn",
    "wof:placetype":"venue"
},
  "geometry": {"coordinates":[3.4413130283,51.2160491943],"type":"Point"}
}