{
  "type": "Feature",
  "properties": {
    "addr:full":"Scheps 14 Balen Antwerpen 2490",
    "addr:housenumber":"14",
    "addr:postcode":"2490",
    "addr:street":"Scheps",
    "iso:country":"BE",
    "sg:address":"Scheps 14",
    "sg:city":"Balen",
    "sg:orig_category":"Eleveurs de bovins",
    "sg:phone":"+32 14 81 36 07",
    "sg:postcode":"2490",
    "sg:province":"Antwerpen",
    "wof:name":"Renata Willekens",
    "wof:placetype":"venue"
},
  "geometry": {"coordinates":[5.1805171967,51.1574897766],"type":"Point"}
}