{
  "type": "Feature",
  "properties": {
    "iso:country":"BE",
    "sg:address":"Dorpsstraat 85",
    "sg:city":"Damme (sijsele)",
    "sg:classifiers":[
        {
            "category":"Building & Trades",
            "subcategory":"Electrical",
            "type":"Services"
        }
    ],
    "sg:phone":"+32 50 35 35 88",
    "sg:postcode":"8340",
    "sg:province":"West-Vlaanderen",
    "sg:tags":[
        "-",
        "electric",
        "contractor"
    ],
    "wof:name":"Elclado Bvba",
    "wof:placetype":"venue"
},
  "geometry": {"coordinates":[3.3248341084,51.2014656067],"type":"Point"}
}