{
  "type": "Feature",
  "properties": {
    "iso:country":"BE",
    "sg:address":"Hollestraat 32bb",
    "sg:city":"Heist-op-den-berg",
    "sg:orig_category":"G\u00e9om\u00e8tres",
    "sg:phone":"+32 15 25 11 27",
    "sg:postcode":"2220",
    "sg:province":"Antwerpen",
    "wof:name":"Koenraad Vaes",
    "wof:placetype":"venue"
},
  "geometry": {"coordinates":[4.7361721992,51.0801582336],"type":"Point"}
}