{
  "type": "Feature",
  "properties": {
    "iso:country":"BE",
    "sg:address":"Burgemeesterstraat 5",
    "sg:city":"Sint-martens-latem",
    "sg:orig_category":"Advocaten and juridische adviseurs Balie van Gent",
    "sg:phone":"+32 9 282 89 19",
    "sg:postcode":"9830",
    "sg:province":"Oost-Vlaanderen",
    "wof:name":"De Clercq Claudine",
    "wof:placetype":"venue"
},
  "geometry": {"coordinates":[3.6305088997,51.0162086487],"type":"Point"}
}