{
  "type": "Feature",
  "properties": {
    "addr:full":"Dorpsstraat 30 Niel Antwerpen 2845",
    "addr:housenumber":"30",
    "addr:postcode":"2845",
    "addr:street":"Dorpsstraat",
    "iso:country":"BE",
    "sg:address":"Dorpsstraat 30",
    "sg:city":"Niel",
    "sg:classifiers":[
        {
            "category":"Arts & Performance",
            "subcategory":"Music",
            "type":"Entertainment"
        }
    ],
    "sg:phone":"+32 3 888 87 17",
    "sg:postcode":"2845",
    "sg:province":"Antwerpen",
    "sg:tags":[
        "disc-jockeys"
    ],
    "wof:name":"Carr\u00e9 Discobar",
    "wof:placetype":"venue"
},
  "geometry": {"coordinates":[4.3265309334,51.1090164185],"type":"Point"}
}