{
  "type": "Feature",
  "properties": {
    "iso:country":"BE",
    "sg:address":"Tiensestraat 276",
    "sg:city":"Leuven",
    "sg:classifiers":[
        {
            "category":"Bakery",
            "type":"Food & Drink"
        }
    ],
    "sg:phone":"+32 16 23 19 63",
    "sg:postcode":"3000",
    "sg:province":"Vlaams-Brabant",
    "sg:tags":[
        "confectioner",
        "baker"
    ],
    "wof:name":"Natuurbakkerij Leuven Bvba",
    "wof:placetype":"venue"
},
  "geometry": {"coordinates":[4.7132282257,50.8736724854],"type":"Point"}
}