{
  "type": "Feature",
  "properties": {
    "iso:country":"BE",
    "sg:address":"Dorp 0",
    "sg:city":"Zandhoven",
    "sg:classifiers":[
        {
            "category":"Fast Food",
            "type":"Food & Drink"
        }
    ],
    "sg:phone":"+32 3 484 60 84",
    "sg:postcode":"2242",
    "sg:province":"Antwerpen",
    "sg:tags":[
        "meeneem",
        "restaurant"
    ],
    "wof:name":"'t Pleintje",
    "wof:placetype":"venue"
},
  "geometry": {"coordinates":[4.6918702126,51.217124939],"type":"Point"}
}