{
  "type": "Feature",
  "properties": {
    "addr:full":"Rue Bienonsart 222 Wanze Li\u00e8ge 4520",
    "addr:housenumber":"222",
    "addr:postcode":"4520",
    "addr:street":"Rue Bienonsart",
    "iso:country":"BE",
    "sg:address":"Rue Bienonsart 222",
    "sg:city":"Wanze",
    "sg:orig_category":"Kapsalons",
    "sg:phone":"+32 85 71 31 27",
    "sg:postcode":"4520",
    "sg:province":"Li\u00e8ge",
    "wof:name":"Isabelle Daussaint",
    "wof:placetype":"venue"
},
  "geometry": {"coordinates":[5.1658477783,50.5644035339],"type":"Point"}
}