{
  "type": "Feature",
  "properties": {
    "iso:country":"BE",
    "sg:address":"Chauss\u00c9e De Louvain 915-921",
    "sg:city":"Evere",
    "sg:classifiers":[
        {
            "category":"Shopping",
            "subcategory":"Stationery & Office Supplies",
            "type":"Retail Goods"
        }
    ],
    "sg:phone":"+32 2 726 77 96",
    "sg:postcode":"1140",
    "sg:province":"Bruxelles-Capitale",
    "sg:tags":[
        "fab",
        "carton",
        "en",
        "papier",
        "emballages"
    ],
    "wof:name":"Huysmans Papeteries & Co",
    "wof:placetype":"venue"
},
  "geometry": {"coordinates":[4.41355896,50.8587036133],"type":"Point"}
}