{
  "type": "Feature",
  "properties": {
    "iso:country":"BE",
    "sg:address":"Oostlaan 10",
    "sg:city":"Genk",
    "sg:classifiers":[
        {
            "category":"Cafe",
            "type":"Food & Drink"
        }
    ],
    "sg:phone":"+32 89 35 53 30",
    "sg:postcode":"3600",
    "sg:province":"Limburg",
    "sg:tags":[
        "caf\u00e9s"
    ],
    "wof:name":"Parochiecentrum",
    "wof:placetype":"venue"
},
  "geometry": {"coordinates":[5.4864611626,50.9773101807],"type":"Point"}
}