{
  "type": "Feature",
  "properties": {
    "iso:country":"BE",
    "sg:address":"Hechtelsebaan 8",
    "sg:city":"Hechtel-eksel (eksel)",
    "sg:classifiers":[
        {
            "category":"Banks & Credit Unions",
            "subcategory":"Investment Brokerage",
            "type":"Services"
        }
    ],
    "sg:phone":"+32 11 73 15 37",
    "sg:postcode":"3941",
    "sg:province":"Limburg",
    "sg:tags":[
        "jean",
        "casual",
        "wear"
    ],
    "wof:name":"Jeans Shop Eksel Nv",
    "wof:placetype":"venue"
},
  "geometry": {"coordinates":[5.383477211,51.1408042908],"type":"Point"}
}