{
  "type": "Feature",
  "properties": {
    "addr:full":"Clos Colombes 1 Ottignies-louvain-la-neuve Brabant Wallon 1342",
    "addr:housenumber":"1",
    "addr:postcode":"1342",
    "addr:street":"Clos Colombes",
    "iso:country":"BE",
    "sg:address":"Clos Colombes 1",
    "sg:city":"Ottignies-louvain-la-neuve",
    "sg:orig_category":"Sportclubs",
    "sg:phone":"+32 10 41 49 86",
    "sg:postcode":"1342",
    "sg:province":"Brabant Wallon",
    "wof:name":"Cercle De Tennis De Table",
    "wof:placetype":"venue"
},
  "geometry": {"coordinates":[4.5568881035,50.6783905029],"type":"Point"}
}