{
  "type": "Feature",
  "properties": {
    "iso:country":"BE",
    "sg:address":"Stationsstraat 36",
    "sg:city":"Stekene (kemzeke)",
    "sg:classifiers":[
        {
            "category":"Autos & Motor Vehicles",
            "subcategory":"Recreational Vehicle Sales",
            "type":"Retail Goods"
        }
    ],
    "sg:phone":"+32 3 789 96 62",
    "sg:postcode":"9190",
    "sg:province":"Oost-Vlaanderen",
    "sg:tags":[
        "installation",
        "metal",
        "-",
        "surface",
        "machine",
        "treatment"
    ],
    "wof:name":"U.t.s. Nv",
    "wof:placetype":"venue"
},
  "geometry": {"coordinates":[4.0745210648,51.207988739],"type":"Point"}
}