{
  "type": "Feature",
  "properties": {
    "iso:country":"BE",
    "sg:address":"Reningelstsestraat 68a",
    "sg:city":"Heuvelland",
    "sg:orig_category":"Dakwerken Plaatsen van vloer- and muurbekleding",
    "sg:phone":"+32 57 44 72 16",
    "sg:postcode":"8956",
    "sg:province":"West-Vlaanderen",
    "wof:name":"Lemaire Luc",
    "wof:placetype":"venue"
},
  "geometry": {"coordinates":[2.8101739883,50.7941017151],"type":"Point"}
}