{
  "type": "Feature",
  "properties": {
    "iso:country":"BE",
    "sg:address":"Witte Hoeve 18",
    "sg:city":"Zandhoven",
    "sg:orig_category":"Antiek",
    "sg:phone":"+32 3 484 55 05",
    "sg:postcode":"2242",
    "sg:province":"Antwerpen",
    "wof:name":"Spruyt-van De Schoor",
    "wof:placetype":"venue"
},
  "geometry": {"coordinates":[4.7093920708,51.2377510071],"type":"Point"}
}