{
  "type": "Feature",
  "properties": {
    "addr:full":"Assesteenweg 113 Ternat Vlaams-Brabant 1740",
    "addr:housenumber":"113",
    "addr:postcode":"1740",
    "addr:street":"Assesteenweg",
    "iso:country":"BE",
    "sg:address":"Assesteenweg 113",
    "sg:city":"Ternat",
    "sg:classifiers":[
        {
            "category":"Autos & Motor Vehicles",
            "subcategory":"Fuel & Gas Station",
            "type":"Retail Goods"
        }
    ],
    "sg:phone":"+32 2 582 84 22",
    "sg:postcode":"1740",
    "sg:province":"Vlaams-Brabant",
    "sg:tags":[
        "stations-service",
        "carburants"
    ],
    "wof:name":"Jet",
    "wof:placetype":"venue"
},
  "geometry": {"coordinates":[4.165034771,50.8782310486],"type":"Point"}
}