{
  "type": "Feature",
  "properties": {
    "addr:full":"Heerle 30 Lille Antwerpen 2275",
    "addr:housenumber":"30",
    "addr:postcode":"2275",
    "addr:street":"Heerle",
    "iso:country":"BE",
    "sg:address":"Heerle 30",
    "sg:city":"Lille",
    "sg:orig_category":"Landbouwmachines Gh",
    "sg:phone":"+32 14 55 75 47",
    "sg:postcode":"2275",
    "sg:province":"Antwerpen",
    "wof:name":"Fa. Auwers J. & Zonen",
    "wof:placetype":"venue"
},
  "geometry": {"coordinates":[4.8640670776,51.214263916],"type":"Point"}
}