{
  "type": "Feature",
  "properties": {
    "addr:full":"Florastraat 29 Box 6 De Pinte Oost-Vlaanderen 9840",
    "addr:housenumber":"29",
    "addr:postcode":"9840",
    "addr:street":"Florastraat;Box 6",
    "iso:country":"BE",
    "sg:address":"Florastraat 29 Box 6",
    "sg:city":"De Pinte",
    "sg:classifiers":[
        {
            "category":"Utilities",
            "subcategory":"Telephone",
            "type":"Services"
        }
    ],
    "sg:phone":"+32 9 330 74 12",
    "sg:postcode":"9840",
    "sg:province":"Oost-Vlaanderen",
    "sg:tags":[
        "-",
        "internet"
    ],
    "wof:name":"Ventnet",
    "wof:placetype":"venue"
},
  "geometry": {"coordinates":[3.6580619812,51.0008354187],"type":"Point"}
}