{
  "type": "Feature",
  "properties": {
    "addr:full":"Liersesteenweg 0 Mortsel Antwerpen 2640",
    "addr:housenumber":"0",
    "addr:postcode":"2640",
    "addr:street":"Liersesteenweg",
    "iso:country":"BE",
    "sg:address":"Liersesteenweg 0",
    "sg:city":"Mortsel",
    "sg:orig_category":"Benzinestations and brandstoffen",
    "sg:phone":"+32 3 455 59 99",
    "sg:postcode":"2640",
    "sg:province":"Antwerpen",
    "wof:name":"Jet",
    "wof:placetype":"venue"
},
  "geometry": {"coordinates":[4.4695038795,51.1686401367],"type":"Point"}
}