{
  "type": "Feature",
  "properties": {
    "iso:country":"BE",
    "sg:address":"Ouderdomseweg 2",
    "sg:city":"Poperinge",
    "sg:orig_category":"R\u00e9parations d'appareils \u00e9lectrom\u00e9nagers. Electrom\u00e9nager, t\u00e9l\u00e9visions and radios",
    "sg:phone":"+32 57 33 30 04",
    "sg:postcode":"8970",
    "sg:province":"West-Vlaanderen",
    "wof:name":"Desomer-plancke",
    "wof:placetype":"venue"
},
  "geometry": {"coordinates":[2.7394280434,50.8479766846],"type":"Point"}
}