{
  "type": "Feature",
  "properties": {
    "addr:full":"Rue Du Grand Trait 103b Frameries (la Bouverie) Hainaut 7080",
    "addr:housenumber":"103b",
    "addr:postcode":"7080",
    "addr:street":"Rue Du Grand Trait",
    "iso:country":"BE",
    "sg:address":"Rue Du Grand Trait 103b",
    "sg:city":"Frameries (la Bouverie)",
    "sg:classifiers":[
        {
            "category":"Health Services",
            "subcategory":"Health Practitioner",
            "type":"Services"
        }
    ],
    "sg:phone":"+32 65 51 03 26",
    "sg:postcode":"7080",
    "sg:province":"Hainaut",
    "sg:tags":[
        "physiotherapist"
    ],
    "wof:name":"Godart Sylvie",
    "wof:placetype":"venue"
},
  "geometry": {"coordinates":[3.880959034,50.415813446],"type":"Point"}
}