{
  "type": "Feature",
  "properties": {
    "addr:full":"Place Emile Buisset 2 Charleroi Hainaut 6000",
    "addr:housenumber":"2",
    "addr:postcode":"6000",
    "addr:street":"Place Emile Buisset;Hainaut",
    "iso:country":"BE",
    "sg:address":"Place Emile Buisset 2",
    "sg:city":"Charleroi",
    "sg:classifiers":[
        {
            "category":"Travel",
            "subcategory":"Travel Agent",
            "type":"Entertainment"
        }
    ],
    "sg:phone":"+32 71 70 02 12",
    "sg:postcode":"6000",
    "sg:province":"Hainaut",
    "sg:tags":[
        "agency"
    ],
    "wof:name":"Voyages Philippart-flash Travel",
    "wof:placetype":"venue"
},
  "geometry": {"coordinates":[4.4393367767,50.4065971375],"type":"Point"}
}