{
  "type": "Feature",
  "properties": {
    "iso:country":"BE",
    "sg:address":"Rue De La Grotte 128",
    "sg:city":"Flemalle",
    "sg:orig_category":"Musea and historische gebouwen",
    "sg:phone":"+32 4 275 89 75",
    "sg:postcode":"4400",
    "sg:province":"Li\u00e8ge",
    "wof:name":"Prehistocite",
    "wof:placetype":"venue"
},
  "geometry": {"coordinates":[5.4576430321,50.5693130493],"type":"Point"}
}