{
  "type": "Feature",
  "properties": {
    "addr:full":"Wijngaard 6 Sint-martens-latem Oost-Vlaanderen 9831",
    "addr:housenumber":"6",
    "addr:postcode":"9831",
    "addr:street":"Wijngaard",
    "iso:country":"BE",
    "sg:address":"Wijngaard 6",
    "sg:city":"Sint-martens-latem",
    "sg:orig_category":"Mat\u00e9riel m\u00e9dical and orthop\u00e9dique and proth\u00e8ses Fab",
    "sg:phone":"+32 9 282 48 78",
    "sg:postcode":"9831",
    "sg:province":"Oost-Vlaanderen",
    "wof:name":"Hendrik Van Den Heede",
    "wof:placetype":"venue"
},
  "geometry": {"coordinates":[3.6075479984,50.998588562],"type":"Point"}
}