{
  "type": "Feature",
  "properties": {
    "iso:country":"BE",
    "sg:address":"Blauwe Steenstraat 27",
    "sg:city":"Dendermonde",
    "sg:orig_category":"Transports routiers de marchandises",
    "sg:phone":"+32 52 21 77 18",
    "sg:postcode":"9200",
    "sg:province":"Oost-Vlaanderen",
    "wof:name":"Karan",
    "wof:placetype":"venue"
},
  "geometry": {"coordinates":[4.117893219,51.0322952271],"type":"Point"}
}