{
  "type": "Feature",
  "properties": {
    "iso:country":"BE",
    "sg:address":"De-billemontstraat 6",
    "sg:city":"Geel",
    "sg:orig_category":"Kapsalons",
    "sg:phone":"+32 14 58 93 25",
    "sg:postcode":"2440",
    "sg:province":"Antwerpen",
    "wof:name":"Coiffure If",
    "wof:placetype":"venue"
},
  "geometry": {"coordinates":[4.9962058067,51.163433075],"type":"Point"}
}