{
  "type": "Feature",
  "properties": {
    "addr:full":"Rue De Bruxelles 50 Awans Li\u00e8ge 4340",
    "addr:housenumber":"50",
    "addr:postcode":"4340",
    "addr:street":"Rue De Bruxelles",
    "iso:country":"BE",
    "sg:address":"Rue De Bruxelles 50",
    "sg:city":"Awans",
    "sg:orig_category":"Dierenartsen",
    "sg:phone":"+32 4 257 58 59",
    "sg:postcode":"4340",
    "sg:province":"Li\u00e8ge",
    "wof:name":"B. Vilenne",
    "wof:placetype":"venue"
},
  "geometry": {"coordinates":[5.4748878479,50.6781921387],"type":"Point"}
}