{
  "type": "Feature",
  "properties": {
    "addr:full":"Leopoldlaan 126-128 Ninove Oost-Vlaanderen 9400",
    "addr:housenumber":"126-128",
    "addr:postcode":"9400",
    "addr:street":"Leopoldlaan",
    "iso:country":"BE",
    "sg:address":"Leopoldlaan 126-128",
    "sg:city":"Ninove",
    "sg:orig_category":"V\u00e9hicules automobiles. Entretien and r\u00e9parations de voitures",
    "sg:phone":"+32 54 33 14 50",
    "sg:postcode":"9400",
    "sg:province":"Oost-Vlaanderen",
    "wof:name":"Ninove Motors",
    "wof:placetype":"venue"
},
  "geometry": {"coordinates":[4.0197911263,50.8258514404],"type":"Point"}
}