{
  "type": "Feature",
  "properties": {
    "iso:country":"BE",
    "sg:address":"Rue Du R\u00e9servoir 229",
    "sg:city":"Charleroi (gilly)",
    "sg:classifiers":[
        {
            "category":"Building & Trades",
            "subcategory":"Construction",
            "type":"Services"
        }
    ],
    "sg:phone":"+32 71 40 27 50",
    "sg:postcode":"6060",
    "sg:province":"Hainaut",
    "sg:tags":[
        "stucco",
        "contractor"
    ],
    "wof:name":"Luciano Entreprise",
    "wof:placetype":"venue"
},
  "geometry": {"coordinates":[4.4880981445,50.4251937866],"type":"Point"}
}