{
  "type": "Feature",
  "properties": {
    "iso:country":"BE",
    "sg:address":"Steenstraat 35a",
    "sg:city":"Halle",
    "sg:classifiers":[
        {
            "category":"Manufacturing",
            "subcategory":"Paper Products",
            "type":"Manufacturing & Wholesale Goods"
        }
    ],
    "sg:phone":"+32 2 356 36 25",
    "sg:postcode":"1500",
    "sg:province":"Vlaams-Brabant",
    "sg:tags":[
        "bookbinding"
    ],
    "wof:name":"Janssens J",
    "wof:placetype":"venue"
},
  "geometry": {"coordinates":[4.2607760429,50.7146530151],"type":"Point"}
}