{
  "type": "Feature",
  "properties": {
    "iso:country":"BE",
    "sg:address":"Karel Van Manderstraat 21",
    "sg:city":"Kortrijk (marke)",
    "sg:classifiers":[
        {
            "category":"Shopping",
            "subcategory":"Stationery & Office Supplies",
            "type":"Retail Goods"
        }
    ],
    "sg:phone":"+32 56 21 10 95",
    "sg:postcode":"8510",
    "sg:province":"West-Vlaanderen",
    "sg:tags":[
        "fixture"
    ],
    "wof:name":"Designart",
    "wof:placetype":"venue"
},
  "geometry": {"coordinates":[3.2523839474,50.8035697937],"type":"Point"}
}