{
  "type": "Feature",
  "properties": {
    "iso:country":"BE",
    "sg:address":"Chauss\u00c9e De Namur 87",
    "sg:city":"Ramillies",
    "sg:orig_category":"Verplichte sociale verzekeringen",
    "sg:phone":"+32 81 87 78 23",
    "sg:postcode":"1367",
    "sg:province":"Brabant Wallon",
    "wof:name":"Mutualit\u00c9 Socialiste",
    "wof:placetype":"venue"
},
  "geometry": {"coordinates":[4.8448901176,50.6514205933],"type":"Point"}
}