{
  "type": "Feature",
  "properties": {
    "addr:full":"Rue Phocas Lejeune 10 Gembloux-sur-orneau (isnes) Namur 5032",
    "addr:housenumber":"10",
    "addr:postcode":"5032",
    "addr:street":"Rue Phocas Lejeune;Namur",
    "iso:country":"BE",
    "sg:address":"Rue Phocas Lejeune 10",
    "sg:city":"Gembloux-sur-orneau (isnes)",
    "sg:classifiers":[
        {
            "category":"Professional",
            "subcategory":"Testing Lab",
            "type":"Services"
        }
    ],
    "sg:phone":"+32 81 58 53 00",
    "sg:postcode":"5032",
    "sg:province":"Namur",
    "sg:tags":[
        "laboratory",
        "-"
    ],
    "wof:name":"B.f.b. Oil Research Sa",
    "wof:placetype":"venue"
},
  "geometry": {"coordinates":[4.7220830917,50.4997901917],"type":"Point"}
}