{
  "type": "Feature",
  "properties": {
    "iso:country":"BE",
    "sg:address":"Langensteenweg 49",
    "sg:city":"Merchtem",
    "sg:classifiers":[
        {
            "category":"Shopping",
            "subcategory":"Clothing, Apparel, & Fashions",
            "type":"Retail Goods"
        }
    ],
    "sg:phone":"+32 52 37 13 78",
    "sg:postcode":"1785",
    "sg:province":"Vlaams-Brabant",
    "sg:tags":[
        "underwear",
        "lingerie",
        "-"
    ],
    "wof:name":"Huis Andriessens A",
    "wof:placetype":"venue"
},
  "geometry": {"coordinates":[4.2324428558,50.9597167969],"type":"Point"}
}