{
  "type": "Feature",
  "properties": {
    "iso:country":"BE",
    "sg:address":"Place Emile De Lalieux 15",
    "sg:city":"Nivelles",
    "sg:classifiers":[
        {
            "category":"Shopping",
            "subcategory":"Stationery & Office Supplies",
            "type":"Retail Goods"
        }
    ],
    "sg:phone":"+32 67 21 76 10",
    "sg:postcode":"1400",
    "sg:province":"Brabant Wallon",
    "wof:name":"Papeterie Imprim.de Nivelles Sa",
    "wof:placetype":"venue"
},
  "geometry": {"coordinates":[4.3286151886,50.5984115601],"type":"Point"}
}