{
  "type": "Feature",
  "properties": {
    "iso:country":"BE",
    "sg:address":"Rue De L\u00b4infante 2",
    "sg:city":"Waterloo",
    "sg:orig_category":"Microsoft. Ordinateurs and \u00e9quipement informatique. Conseils en syst\u00e8mes informatiques",
    "sg:phone":"+32 2 351 19 39",
    "sg:postcode":"1410",
    "sg:province":"Brabant Wallon",
    "wof:name":"Microcomputer",
    "wof:placetype":"venue"
},
  "geometry": {"coordinates":[4.3861508369,50.7179450989],"type":"Point"}
}