{
  "type": "Feature",
  "properties": {
    "addr:full":"Rue Des Fr\u00e8res Taymans 73 Tubize Brabant Wallon 1480",
    "addr:housenumber":"73",
    "addr:postcode":"1480",
    "addr:street":"Rue Des Fre\u0300Res Taymans;Wallon",
    "iso:country":"BE",
    "sg:address":"Rue Des Fr\u00e8res Taymans 73",
    "sg:city":"Tubize",
    "sg:classifiers":[
        {
            "category":"Building & Trades",
            "subcategory":"Construction",
            "type":"Services"
        }
    ],
    "sg:phone":"+32 476 40 23 91",
    "sg:postcode":"1480",
    "sg:province":"Brabant Wallon",
    "sg:tags":[
        "carpenter"
    ],
    "wof:name":"Anton Y Salinero J",
    "wof:placetype":"venue"
},
  "geometry": {"coordinates":[4.2061648369,50.6883163452],"type":"Point"}
}