{
  "type": "Feature",
  "properties": {
    "iso:country":"BE",
    "sg:address":"Schapenstraat 114",
    "sg:city":"Lennik",
    "sg:orig_category":"Binnenhuisarchitecten",
    "sg:phone":"+32 2 532 21 94",
    "sg:postcode":"1750",
    "sg:province":"Vlaams-Brabant",
    "wof:name":"Bureau B-design",
    "wof:placetype":"venue"
},
  "geometry": {"coordinates":[4.1664290428,50.8219566345],"type":"Point"}
}