{
  "type": "Feature",
  "properties": {
    "addr:full":"Rue Vall\u00c9e 158 Chaudfontaine Li\u00e8ge 4051",
    "addr:housenumber":"158",
    "addr:postcode":"4051",
    "addr:street":"Rue Valle\u0301E",
    "iso:country":"BE",
    "sg:address":"Rue Vall\u00c9e 158",
    "sg:city":"Chaudfontaine",
    "sg:orig_category":"Alternatieve geneeskunde Artsen and specialisten",
    "sg:phone":"+32 4 365 20 21",
    "sg:postcode":"4051",
    "sg:province":"Li\u00e8ge",
    "wof:name":"Delvaux Victor",
    "wof:placetype":"venue"
},
  "geometry": {"coordinates":[5.6309738159,50.6024475098],"type":"Point"}
}