{
  "type": "Feature",
  "properties": {
    "addr:full":"Rue Jean Damard 26 Anthisnes Li\u00e8ge 4163",
    "addr:housenumber":"26",
    "addr:postcode":"4163",
    "addr:street":"Rue Jean Damard",
    "iso:country":"BE",
    "sg:address":"Rue Jean Damard 26",
    "sg:city":"Anthisnes",
    "sg:orig_category":"Eleveurs de bovins",
    "sg:phone":"+32 4 371 58 90",
    "sg:postcode":"4163",
    "sg:province":"Li\u00e8ge",
    "wof:name":"Paul Degive",
    "wof:placetype":"venue"
},
  "geometry": {"coordinates":[5.4762802124,50.5165367126],"type":"Point"}
}