{
  "type": "Feature",
  "properties": {
    "addr:full":"Keistraat 92b Sint-martens-latem Oost-Vlaanderen 9830",
    "addr:housenumber":"92b",
    "addr:postcode":"9830",
    "addr:street":"Keistraat",
    "iso:country":"BE",
    "sg:address":"Keistraat 92b",
    "sg:city":"Sint-martens-latem",
    "sg:classifiers":[
        {
            "category":"Home & Garden",
            "subcategory":"Furniture",
            "type":"Retail Goods"
        }
    ],
    "sg:phone":"+32 9 282 23 69",
    "sg:postcode":"9830",
    "sg:province":"Oost-Vlaanderen",
    "sg:tags":[
        "-"
    ],
    "wof:name":"H\u00e5g Benelux Bv",
    "wof:placetype":"venue"
},
  "geometry": {"coordinates":[3.6347239017,50.9977416992],"type":"Point"}
}