{
  "type": "Feature",
  "properties": {
    "addr:full":"Lindeplein 1 Brakel (nederbrakel) Oost-Vlaanderen 9660",
    "addr:housenumber":"1",
    "addr:postcode":"9660",
    "addr:street":"Lindeplein",
    "iso:country":"BE",
    "sg:address":"Lindeplein 1",
    "sg:city":"Brakel (nederbrakel)",
    "sg:classifiers":[
        {
            "category":"Bars & Pubs",
            "type":"Food & Drink"
        }
    ],
    "sg:phone":"+32 55 42 31 78",
    "sg:postcode":"9660",
    "sg:province":"Oost-Vlaanderen",
    "wof:name":"Labrieze",
    "wof:placetype":"venue"
},
  "geometry": {"coordinates":[3.7616560459,50.8055343628],"type":"Point"}
}