{
  "type": "Feature",
  "properties": {
    "iso:country":"BE",
    "sg:address":"Guido Gezellestraat 135",
    "sg:city":"Beringen",
    "sg:orig_category":"Traitements param\u00e9dicaux",
    "sg:phone":"+32 11 42 49 76",
    "sg:postcode":"3582",
    "sg:province":"Limburg",
    "wof:name":"I. Maesen",
    "wof:placetype":"venue"
},
  "geometry": {"coordinates":[5.2708749771,51.0595359802],"type":"Point"}
}