{
  "type": "Feature",
  "properties": {
    "iso:country":"BE",
    "sg:address":"Weversstraat 5",
    "sg:city":"Asse",
    "sg:classifiers":[
        {
            "category":"Professional",
            "subcategory":"Management & Consulting",
            "type":"Services"
        }
    ],
    "sg:phone":"+32 2 452 40 64",
    "sg:postcode":"1730",
    "sg:province":"Vlaams-Brabant",
    "sg:tags":[
        "tax-consultants"
    ],
    "wof:name":"Van De Putte W",
    "wof:placetype":"venue"
},
  "geometry": {"coordinates":[4.202357769,50.9097175598],"type":"Point"}
}