{
  "type": "Feature",
  "properties": {
    "addr:full":"Groenstraat 3 Zandhoven (pulderbos) Antwerpen 2242",
    "addr:housenumber":"3",
    "addr:postcode":"2242",
    "addr:street":"Groenstraat",
    "iso:country":"BE",
    "sg:address":"Groenstraat 3",
    "sg:city":"Zandhoven (pulderbos)",
    "sg:classifiers":[
        {
            "category":"Shopping",
            "subcategory":"Bicycles & Sporting Goods",
            "type":"Retail Goods"
        }
    ],
    "sg:phone":"+32 3 484 52 82",
    "sg:postcode":"2242",
    "sg:province":"Antwerpen",
    "sg:tags":[
        "-"
    ],
    "wof:name":"De Schutter F",
    "wof:placetype":"venue"
},
  "geometry": {"coordinates":[4.6987948418,51.2230567932],"type":"Point"}
}