{
  "type": "Feature",
  "properties": {
    "addr:full":"Zuidstraat 11 Roeselare West-Vlaanderen 8800",
    "addr:housenumber":"11",
    "addr:postcode":"8800",
    "addr:street":"Zuidstraat",
    "iso:country":"BE",
    "sg:address":"Zuidstraat 11",
    "sg:city":"Roeselare",
    "sg:orig_category":"Pain, p\u00e2tisseries and confiseries",
    "sg:phone":"+32 51 20 01 92",
    "sg:postcode":"8800",
    "sg:province":"West-Vlaanderen",
    "wof:name":"Jan Mahieu",
    "wof:placetype":"venue"
},
  "geometry": {"coordinates":[3.1243829727,50.944190979],"type":"Point"}
}