{
  "type": "Feature",
  "properties": {
    "iso:country":"BE",
    "sg:address":"Snoekstraat 19",
    "sg:city":"Elsene/ixelles",
    "sg:orig_category":"Artsen and specialisten",
    "sg:phone":"+32 2 646 43 04",
    "sg:postcode":"1050",
    "sg:province":"Bruxelles-Capitale",
    "wof:name":"De Foy",
    "wof:placetype":"venue"
},
  "geometry": {"coordinates":[4.3794178963,50.833190918],"type":"Point"}
}