{
  "type": "Feature",
  "properties": {
    "addr:full":"Noordstraat 2 Koekelare West-Vlaanderen 8680",
    "addr:housenumber":"2",
    "addr:postcode":"8680",
    "addr:street":"Noordstraat",
    "iso:country":"BE",
    "sg:address":"Noordstraat 2",
    "sg:city":"Koekelare",
    "sg:classifiers":[
        {
            "category":"Wholesale",
            "subcategory":"Fruits & Vegetables",
            "type":"Manufacturing & Wholesale Goods"
        }
    ],
    "sg:phone":"+32 51 58 94 97",
    "sg:postcode":"8680",
    "sg:province":"West-Vlaanderen",
    "sg:tags":[
        "whol",
        "-",
        "potato"
    ],
    "wof:name":"De Rycke M.j. & J Bvba",
    "wof:placetype":"venue"
},
  "geometry": {"coordinates":[2.9780960083,51.0913543701],"type":"Point"}
}