{
  "type": "Feature",
  "properties": {
    "iso:country":"BE",
    "sg:address":"Mandellaan 276",
    "sg:city":"Roeselare",
    "sg:classifiers":[
        {
            "category":"Communications",
            "subcategory":"Film & Video Production",
            "type":"Services"
        }
    ],
    "sg:phone":"+32 51 22 71 79",
    "sg:postcode":"8800",
    "sg:province":"West-Vlaanderen",
    "sg:tags":[
        "hiring",
        "-"
    ],
    "wof:name":"Movie Max",
    "wof:placetype":"venue"
},
  "geometry": {"coordinates":[3.1402928829,50.9485282898],"type":"Point"}
}