{
  "type": "Feature",
  "properties": {
    "iso:country":"BE",
    "sg:address":"Rue Baron Lambert 27",
    "sg:city":"Etterbeek/etterbeek",
    "sg:classifiers":[
        {
            "category":"Building & Trades",
            "subcategory":"Landscaping Services",
            "type":"Services"
        }
    ],
    "sg:phone":"+32 2 649 07 42",
    "sg:postcode":"1040",
    "sg:province":"Bruxelles-Capitale",
    "sg:tags":[
        "etude",
        "technique",
        "ing\u00e9nierie"
    ],
    "wof:name":"Sinep",
    "wof:placetype":"venue"
},
  "geometry": {"coordinates":[4.3886451721,50.8350830078],"type":"Point"}
}