{
  "type": "Feature",
  "properties": {
    "iso:country":"BE",
    "sg:address":"Waverse Steenweg 1465",
    "sg:city":"Oudergem/auderghem",
    "sg:orig_category":"Kruideniers Voedingsspeciaalzaken",
    "sg:phone":"+32 2 673 73 81",
    "sg:postcode":"1160",
    "sg:province":"Bruxelles-Capitale",
    "wof:name":"Asia's Food",
    "wof:placetype":"venue"
},
  "geometry": {"coordinates":[4.4152979851,50.8188476562],"type":"Point"}
}