{
  "type": "Feature",
  "properties": {
    "addr:full":"Rijksweg 11 Puurs (groot) Antwerpen 2870",
    "addr:housenumber":"11",
    "addr:postcode":"2870",
    "addr:street":"Rijksweg;Groot Antwerpen",
    "iso:country":"BE",
    "sg:address":"Rijksweg 11",
    "sg:city":"Puurs (groot)",
    "sg:orig_category":"Baby- and kinderkleding Dameskledingzaken Herenkledingzaken",
    "sg:phone":"+32 3 886 46 70",
    "sg:postcode":"2870",
    "sg:province":"Antwerpen",
    "wof:name":"Jbc Mode",
    "wof:placetype":"venue"
},
  "geometry": {"coordinates":[4.3118309975,51.0681152344],"type":"Point"}
}