{
  "type": "Feature",
  "properties": {
    "addr:full":"Grotestraat 17 Glabbeek (glabbeek-zuurbemde) Vlaams-Brabant 3380",
    "addr:housenumber":"17",
    "addr:postcode":"3380",
    "addr:street":"Grotestraat",
    "iso:country":"BE",
    "sg:address":"Grotestraat 17",
    "sg:city":"Glabbeek (glabbeek-zuurbemde)",
    "sg:classifiers":[
        {
            "category":"Food & Beverages",
            "subcategory":"Supermarket",
            "type":"Retail Goods"
        }
    ],
    "sg:phone":"+32 16 77 79 91",
    "sg:postcode":"3380",
    "sg:province":"Vlaams-Brabant",
    "sg:tags":[
        "department",
        "store"
    ],
    "wof:name":"Troonen-david Nv",
    "wof:placetype":"venue"
},
  "geometry": {"coordinates":[4.9565291405,50.8704948425],"type":"Point"}
}