{
  "type": "Feature",
  "properties": {
    "iso:country":"BE",
    "sg:address":"Kloktorenstraat 32",
    "sg:city":"Etterbeek/etterbeek",
    "sg:orig_category":"Plaatsen van vloer- and muurbekleding Schilders",
    "sg:phone":"+32 2 734 29 43",
    "sg:postcode":"1040",
    "sg:province":"Bruxelles-Capitale",
    "wof:name":"Andre Martens",
    "wof:placetype":"venue"
},
  "geometry": {"coordinates":[4.3875751495,50.8374443054],"type":"Point"}
}