{
  "type": "Feature",
  "properties": {
    "addr:full":"Kloosterstraat 2 Mol Antwerpen 2400",
    "addr:housenumber":"2",
    "addr:postcode":"2400",
    "addr:street":"Kloosterstraat",
    "iso:country":"BE",
    "sg:address":"Kloosterstraat 2",
    "sg:city":"Mol",
    "sg:orig_category":"Dameskledingzaken",
    "sg:phone":"+32 14 31 97 22",
    "sg:postcode":"2400",
    "sg:province":"Antwerpen",
    "wof:name":"Favori",
    "wof:placetype":"venue"
},
  "geometry": {"coordinates":[5.1196951866,51.1878585815],"type":"Point"}
}