{
  "type": "Feature",
  "properties": {
    "iso:country":"BE",
    "sg:address":"Armand Hertzstraat 21",
    "sg:city":"Hasselt",
    "sg:orig_category":"Art and fournitures artistiques",
    "sg:phone":"+32 11 23 14 35",
    "sg:postcode":"3500",
    "sg:province":"Limburg",
    "wof:name":"Jacobus Geerits",
    "wof:placetype":"venue"
},
  "geometry": {"coordinates":[5.3347449303,50.9373664856],"type":"Point"}
}