{
  "type": "Feature",
  "properties": {
    "iso:country":"BE",
    "sg:address":"Titiaanstraat 22",
    "sg:city":"Brussel/bruxelles",
    "sg:orig_category":"Zalen voor culturele evenementen",
    "sg:phone":"+32 2 734 74 88",
    "sg:postcode":"1000",
    "sg:province":"Bruxelles-Capitale",
    "wof:name":"Th\u00c9\u00c2tre Annexe",
    "wof:placetype":"venue"
},
  "geometry": {"coordinates":[4.3889689445,50.8465042114],"type":"Point"}
}