{
  "type": "Feature",
  "properties": {
    "addr:full":"Herentalsebaan 124 Wommelgem Antwerpen 2160",
    "addr:housenumber":"124",
    "addr:postcode":"2160",
    "addr:street":"Herentalsebaan",
    "iso:country":"BE",
    "sg:address":"Herentalsebaan 124",
    "sg:city":"Wommelgem",
    "sg:classifiers":[
        {
            "category":"Food & Beverages",
            "subcategory":"Specialty",
            "type":"Retail Goods"
        }
    ],
    "sg:phone":"+32 3 321 21 42",
    "sg:postcode":"2160",
    "sg:province":"Antwerpen",
    "sg:tags":[
        "health",
        "dietary",
        "-",
        "biological"
    ],
    "wof:name":"Herbalife-shake & Body Vitality",
    "wof:placetype":"venue"
},
  "geometry": {"coordinates":[4.5027999878,51.1958312988],"type":"Point"}
}