{
  "type": "Feature",
  "properties": {
    "addr:full":"Rue De La Station 129 Charleroi (jumet) Hainaut 6040",
    "addr:housenumber":"129",
    "addr:postcode":"6040",
    "addr:street":"Rue De La Station",
    "iso:country":"BE",
    "sg:address":"Rue De La Station 129",
    "sg:city":"Charleroi (jumet)",
    "sg:classifiers":[
        {
            "category":"Shopping",
            "subcategory":"Florist",
            "type":"Retail Goods"
        }
    ],
    "sg:phone":"+32 71 35 67 01",
    "sg:postcode":"6040",
    "sg:province":"Hainaut",
    "wof:name":"Mme Polain",
    "wof:placetype":"venue"
},
  "geometry": {"coordinates":[4.4329600334,50.4402427673],"type":"Point"}
}