{
  "type": "Feature",
  "properties": {
    "iso:country":"BE",
    "sg:address":"Bochtlaan 5",
    "sg:city":"Genk",
    "sg:orig_category":"Decoratieve kunst and kunstbenodigdheden Drukkerijen and copyshops",
    "sg:phone":"+32 89 79 15 66",
    "sg:postcode":"3600",
    "sg:province":"Limburg",
    "wof:name":"'t Atelier",
    "wof:placetype":"venue"
},
  "geometry": {"coordinates":[5.5018129349,50.9664344788],"type":"Point"}
}