{
  "type": "Feature",
  "properties": {
    "iso:country":"BE",
    "sg:address":"Rue Albert Ier 114",
    "sg:city":"Erquelinnes",
    "sg:classifiers":[
        {
            "category":"Arena",
            "subcategory":"Sports Club",
            "type":"Entertainment"
        }
    ],
    "sg:phone":"+32 71 55 64 29",
    "sg:postcode":"6560",
    "sg:province":"Hainaut",
    "sg:tags":[
        "de"
    ],
    "wof:name":"V.c. Erquelinnes",
    "wof:placetype":"venue"
},
  "geometry": {"coordinates":[4.1185030937,50.3089408875],"type":"Point"}
}