{
  "type": "Feature",
  "properties": {
    "iso:country":"BE",
    "sg:address":"Dreef 83a Box 2",
    "sg:city":"Hoogstraten (meerle)",
    "sg:classifiers":[
        {
            "category":"Transit Center",
            "subcategory":"Freight",
            "type":"Transportation"
        }
    ],
    "sg:phone":"+32 3 315 95 08",
    "sg:postcode":"2328",
    "sg:province":"Antwerpen",
    "sg:tags":[
        "import",
        "export",
        "-"
    ],
    "wof:name":"Euro Foret Invest",
    "wof:placetype":"venue"
},
  "geometry": {"coordinates":[4.8041949272,51.4741134644],"type":"Point"}
}