{
  "type": "Feature",
  "properties": {
    "iso:country":"BE",
    "sg:address":"Westendelaan 249",
    "sg:city":"Middelkerke (westende)",
    "sg:classifiers":[
        {
            "category":"Building & Trades",
            "subcategory":"Plumbing",
            "type":"Services"
        }
    ],
    "sg:phone":"+32 59 31 46 86",
    "sg:postcode":"8434",
    "sg:province":"West-Vlaanderen",
    "sg:tags":[
        "repair",
        "mainten",
        "-",
        "central",
        "heating"
    ],
    "wof:name":"Lefevre L",
    "wof:placetype":"venue"
},
  "geometry": {"coordinates":[2.7558889389,51.1391983032],"type":"Point"}
}