{
  "type": "Feature",
  "properties": {
    "addr:full":"Burg. Vandenbogaerdelaan 78 Izegem West-Vlaanderen 8870",
    "addr:housenumber":"78",
    "addr:postcode":"8870",
    "addr:street":"Burg. Vandenbogaerdelaan",
    "iso:country":"BE",
    "sg:address":"Burg. Vandenbogaerdelaan 78",
    "sg:city":"Izegem",
    "sg:orig_category":"Kapsalons",
    "sg:phone":"+32 51 30 77 55",
    "sg:postcode":"8870",
    "sg:province":"West-Vlaanderen",
    "wof:name":"Coiffure Gino",
    "wof:placetype":"venue"
},
  "geometry": {"coordinates":[3.2093880177,50.9119606018],"type":"Point"}
}