{
  "type": "Feature",
  "properties": {
    "iso:country":"BE",
    "sg:address":"2520",
    "sg:city":"Ranst (groot)",
    "sg:orig_category":"Pharmaciens",
    "sg:phone":"+32 900 10 500",
    "sg:postcode":"2520",
    "sg:province":"Antwerpen",
    "wof:name":"Pharmacies De Garde",
    "wof:placetype":"venue"
},
  "geometry": {"coordinates":[4.5622401237,51.1892051697],"type":"Point"}
}