{
  "type": "Feature",
  "properties": {
    "iso:country":"BE",
    "sg:address":"Schutterijstraat 22",
    "sg:city":"Hamont-achel (achel)",
    "sg:classifiers":[
        {
            "category":"Health Services",
            "subcategory":"Health Practitioner",
            "type":"Services"
        }
    ],
    "sg:phone":"+32 11 64 33 73",
    "sg:postcode":"3930",
    "sg:province":"Limburg",
    "sg:tags":[
        "physiotherapist"
    ],
    "wof:name":"Vervoort L",
    "wof:placetype":"venue"
},
  "geometry": {"coordinates":[5.4759678841,51.2547607422],"type":"Point"}
}