{
  "type": "Feature",
  "properties": {
    "addr:full":"Rue De La Fagne 5 Assesse Namur 5330",
    "addr:housenumber":"5",
    "addr:postcode":"5330",
    "addr:street":"Rue De La Fagne",
    "iso:country":"BE",
    "sg:address":"Rue De La Fagne 5",
    "sg:city":"Assesse",
    "sg:classifiers":[
        {
            "category":"Wholesale",
            "subcategory":"Construction Materials",
            "type":"Manufacturing & Wholesale Goods"
        }
    ],
    "sg:phone":"+32 83 66 05 83",
    "sg:postcode":"5330",
    "sg:province":"Namur",
    "sg:tags":[
        "insulation",
        "acoustical"
    ],
    "wof:name":"Pirobouw",
    "wof:placetype":"venue"
},
  "geometry": {"coordinates":[5.031703949,50.3678283691],"type":"Point"}
}