{
  "type": "Feature",
  "properties": {
    "addr:full":"Rue G\u00c9n\u00c9ral De Gaulle 31 La Hulpe Brabant Wallon 1310",
    "addr:housenumber":"31",
    "addr:postcode":"1310",
    "addr:street":"Rue Ge\u0301Ne\u0301Ral De Gaulle",
    "iso:country":"BE",
    "sg:address":"Rue G\u00c9n\u00c9ral De Gaulle 31",
    "sg:city":"La Hulpe",
    "sg:orig_category":"Producteurs de fruits",
    "sg:phone":"+32 2 653 05 06",
    "sg:postcode":"1310",
    "sg:province":"Brabant Wallon",
    "wof:name":"Ockerman",
    "wof:placetype":"venue"
},
  "geometry": {"coordinates":[4.4877500534,50.7353286743],"type":"Point"}
}