{
  "type": "Feature",
  "properties": {
    "iso:country":"BE",
    "sg:address":"Sint-katelijnestraat 16-18",
    "sg:city":"Mechelen",
    "sg:classifiers":[
        {
            "category":"Home & Garden",
            "subcategory":"Furniture",
            "type":"Retail Goods"
        }
    ],
    "sg:phone":"+32 15 20 43 43",
    "sg:postcode":"2800",
    "sg:province":"Antwerpen",
    "sg:tags":[
        "-"
    ],
    "wof:name":"New Mispelters Nv",
    "wof:placetype":"venue"
},
  "geometry": {"coordinates":[4.4776201248,51.0300102234],"type":"Point"}
}