{
  "type": "Feature",
  "properties": {
    "iso:country":"BE",
    "sg:address":"Avenue De France 189",
    "sg:city":"Marche-en-famenne",
    "sg:orig_category":"Boekhouders",
    "sg:phone":"+32 84 31 46 92",
    "sg:postcode":"6900",
    "sg:province":"Luxembourg",
    "wof:name":"Dominique Baudesson",
    "wof:placetype":"venue"
},
  "geometry": {"coordinates":[5.3261699677,50.2084693909],"type":"Point"}
}