{
  "type": "Feature",
  "properties": {
    "addr:full":"Bld De La Sauveni\u00c8re 172 Li\u00c8ge Li\u00e8ge 4000",
    "addr:housenumber":"172",
    "addr:postcode":"4000",
    "addr:street":"Bld De La Sauvenie\u0300Re",
    "iso:country":"BE",
    "sg:address":"Bld De La Sauveni\u00c8re 172",
    "sg:city":"Li\u00c8ge",
    "sg:classifiers":[
        {
            "category":"Restaurant",
            "type":"Food & Drink"
        }
    ],
    "sg:phone":"+32 4 223 01 02",
    "sg:postcode":"4000",
    "sg:province":"Li\u00e8ge",
    "wof:name":"Snack Le Routier",
    "wof:placetype":"venue"
},
  "geometry": {"coordinates":[5.5681481361,50.6405029297],"type":"Point"}
}