{
  "type": "Feature",
  "properties": {
    "addr:full":"Geraardsbergsestraat 40 Ninove Oost-Vlaanderen 9400",
    "addr:housenumber":"40",
    "addr:postcode":"9400",
    "addr:street":"Geraardsbergsestraat",
    "iso:country":"BE",
    "sg:address":"Geraardsbergsestraat 40",
    "sg:city":"Ninove",
    "sg:orig_category":"Blanchisseries and teintureries",
    "sg:phone":"+32 54 33 50 00",
    "sg:postcode":"9400",
    "sg:province":"Oost-Vlaanderen",
    "wof:name":"Celco",
    "wof:placetype":"venue"
},
  "geometry": {"coordinates":[4.0171098709,50.8363990784],"type":"Point"}
}