{
  "type": "Feature",
  "properties": {
    "iso:country":"BE",
    "sg:address":"Kortrijksestraat 2",
    "sg:city":"Roeselare",
    "sg:orig_category":"Decoratiestoffen and buitenhuistextiel Fab",
    "sg:phone":"+32 51 21 03 84",
    "sg:postcode":"8800",
    "sg:province":"West-Vlaanderen",
    "wof:name":"C.g.s. Tentenverhuur",
    "wof:placetype":"venue"
},
  "geometry": {"coordinates":[3.1477000713,50.9201202393],"type":"Point"}
}