{
  "type": "Feature",
  "properties": {
    "addr:full":"Nervi\u00ebrsstraat 7 Antwerpen Antwerpen 2018",
    "addr:housenumber":"7",
    "addr:postcode":"2018",
    "addr:street":"Nervie\u0308Rsstraat",
    "iso:country":"BE",
    "sg:address":"Nervi\u00ebrsstraat 7",
    "sg:city":"Antwerpen",
    "sg:classifiers":[
        {
            "category":"Social Services",
            "type":"Services"
        }
    ],
    "sg:phone":"+32 3 230 78 78",
    "sg:postcode":"2018",
    "sg:province":"Antwerpen",
    "wof:name":"Teledienst Vzw",
    "wof:placetype":"venue"
},
  "geometry": {"coordinates":[4.4206848145,51.2064437866],"type":"Point"}
}