{
  "type": "Feature",
  "properties": {
    "addr:full":"Hendrik Consciencestraat 1b Zwevegem West-Vlaanderen 8550",
    "addr:housenumber":"1b",
    "addr:postcode":"8550",
    "addr:street":"Hendrik Consciencestraat",
    "iso:country":"BE",
    "sg:address":"Hendrik Consciencestraat 1b",
    "sg:city":"Zwevegem",
    "sg:classifiers":[
        {
            "category":"Education",
            "subcategory":"School",
            "type":"Public Place"
        }
    ],
    "sg:phone":"+32 56 75 85 51",
    "sg:postcode":"8550",
    "sg:province":"West-Vlaanderen",
    "sg:tags":[
        "primary"
    ],
    "wof:name":"Basisschool V/h Gemeenschaps-onderwijs 'de Windroos'",
    "wof:placetype":"venue"
},
  "geometry": {"coordinates":[3.3453040123,50.8118095398],"type":"Point"}
}