{
  "type": "Feature",
  "properties": {
    "iso:country":"BE",
    "sg:address":"Rue De La Ferme 68",
    "sg:city":"Ans",
    "sg:orig_category":"Mat\u00e9riel m\u00e9dical and orthop\u00e9dique and proth\u00e8ses Fab",
    "sg:phone":"+32 4 263 16 15",
    "sg:postcode":"4430",
    "sg:province":"Li\u00e8ge",
    "wof:name":"Serge Renard",
    "wof:placetype":"venue"
},
  "geometry": {"coordinates":[5.5181422234,50.6560935974],"type":"Point"}
}