{
  "type": "Feature",
  "properties": {
    "addr:full":"Molenvoetweg 27 Lint Antwerpen 2547",
    "addr:housenumber":"27",
    "addr:postcode":"2547",
    "addr:street":"Molenvoetweg",
    "iso:country":"BE",
    "sg:address":"Molenvoetweg 27",
    "sg:city":"Lint",
    "sg:classifiers":[
        {
            "category":"Building & Trades",
            "subcategory":"Landscaping Services",
            "type":"Services"
        }
    ],
    "sg:phone":"+32 3 288 90 80",
    "sg:postcode":"2547",
    "sg:province":"Antwerpen",
    "sg:tags":[
        "etude",
        "technique",
        "ing\u00e9nierie"
    ],
    "wof:name":"2 Consult Gcv",
    "wof:placetype":"venue"
},
  "geometry": {"coordinates":[4.4907860756,51.1308021545],"type":"Point"}
}