{
  "type": "Feature",
  "properties": {
    "addr:full":"Steenstraat 15 Heusden-zolder Oost-Vlaanderen 9070",
    "addr:housenumber":"15",
    "addr:postcode":"9070",
    "addr:street":"Steenstraat",
    "iso:country":"BE",
    "sg:address":"Steenstraat 15",
    "sg:city":"Heusden-zolder",
    "sg:orig_category":"Plomberie, chauffage and installations sanitaires. Construction de maisons",
    "sg:phone":"+32 9 230 29 56",
    "sg:postcode":"9070",
    "sg:province":"Oost-Vlaanderen",
    "wof:name":"Casteleyn",
    "wof:placetype":"venue"
},
  "geometry": {"coordinates":[3.7968919277,51.0559501648],"type":"Point"}
}