{
  "type": "Feature",
  "properties": {
    "iso:country":"BE",
    "sg:address":"Chauss\u00c9e De Charleroi 669",
    "sg:city":"Fleurus",
    "sg:orig_category":"V\u00e9hicules automobiles",
    "sg:phone":"+32 71 81 03 49",
    "sg:postcode":"6220",
    "sg:province":"Hainaut",
    "wof:name":"Cardans",
    "wof:placetype":"venue"
},
  "geometry": {"coordinates":[4.5383300781,50.4679107666],"type":"Point"}
}