{
  "type": "Feature",
  "properties": {
    "iso:country":"BE",
    "sg:address":"Koning Albertstraat 21",
    "sg:city":"Lint",
    "sg:orig_category":"Begrafeniswezen",
    "sg:phone":"+32 3 449 46 46",
    "sg:postcode":"2547",
    "sg:province":"Antwerpen",
    "wof:name":"Crematie Heens H.",
    "wof:placetype":"venue"
},
  "geometry": {"coordinates":[4.4954371452,51.1275520325],"type":"Point"}
}