{
  "type": "Feature",
  "properties": {
    "addr:full":"Adegemdorp 27 Maldegem Oost-Vlaanderen 9991",
    "addr:housenumber":"27",
    "addr:postcode":"9991",
    "addr:street":"Adegemdorp",
    "iso:country":"BE",
    "sg:address":"Adegemdorp 27",
    "sg:city":"Maldegem",
    "sg:orig_category":"Film-, tv- and videoproductie Fotografen and fotostudio's",
    "sg:phone":"+32 50 71 82 67",
    "sg:postcode":"9991",
    "sg:province":"Oost-Vlaanderen",
    "wof:name":"Fake Art",
    "wof:placetype":"venue"
},
  "geometry": {"coordinates":[3.4866330624,51.2022094727],"type":"Point"}
}