{
  "type": "Feature",
  "properties": {
    "iso:country":"BE",
    "sg:address":"Frankrijklei 6",
    "sg:city":"Antwerpen",
    "sg:orig_category":"Tijdelijke werkgelegenheid and uitzendkantoren",
    "sg:phone":"+32 3 203 48 74",
    "sg:postcode":"2000",
    "sg:province":"Antwerpen",
    "wof:name":"Unique Finance",
    "wof:placetype":"venue"
},
  "geometry": {"coordinates":[4.4156088829,51.2195358276],"type":"Point"}
}