{
  "type": "Feature",
  "properties": {
    "iso:country":"BE",
    "sg:address":"Kennebekkestraat 2",
    "sg:city":"Maasmechelen",
    "sg:orig_category":"Rundveehouders",
    "sg:phone":"+32 89 76 08 80",
    "sg:postcode":"3630",
    "sg:province":"Limburg",
    "wof:name":"Johan Aerts",
    "wof:placetype":"venue"
},
  "geometry": {"coordinates":[5.6961350441,50.963848114],"type":"Point"}
}