{
  "type": "Feature",
  "properties": {
    "iso:country":"BE",
    "sg:address":"Grote Goddaard 16",
    "sg:city":"Antwerpen",
    "sg:orig_category":"Decoratieve kunst and kunstbenodigdheden Zalen voor culturele evenementen",
    "sg:phone":"+32 3 234 09 06",
    "sg:postcode":"2000",
    "sg:province":"Antwerpen",
    "wof:name":"Skerritt Contemporary Art",
    "wof:placetype":"venue"
},
  "geometry": {"coordinates":[4.4043011665,51.2219848633],"type":"Point"}
}