{
  "type": "Feature",
  "properties": {
    "addr:full":"Meensestraat 21 Ieper West-Vlaanderen 8900",
    "addr:housenumber":"21",
    "addr:postcode":"8900",
    "addr:street":"Meensestraat",
    "iso:country":"BE",
    "sg:address":"Meensestraat 21",
    "sg:city":"Ieper",
    "sg:classifiers":[
        {
            "category":"Food & Beverages",
            "subcategory":"Specialty",
            "type":"Retail Goods"
        }
    ],
    "sg:phone":"+32 57 21 65 73",
    "sg:postcode":"8900",
    "sg:province":"West-Vlaanderen",
    "sg:tags":[
        "health",
        "dietary",
        "-",
        "biological"
    ],
    "wof:name":"De Bio-vita",
    "wof:placetype":"venue"
},
  "geometry": {"coordinates":[2.8892700672,50.85181427],"type":"Point"}
}