{
  "type": "Feature",
  "properties": {
    "addr:full":"Rue Du Sablon 33 Bastogne Luxembourg 6600",
    "addr:housenumber":"33",
    "addr:postcode":"6600",
    "addr:street":"Rue Du Sablon",
    "iso:country":"BE",
    "sg:address":"Rue Du Sablon 33",
    "sg:city":"Bastogne",
    "sg:classifiers":[
        {
            "category":"Retail",
            "subcategory":"Event Space",
            "type":"Services"
        }
    ],
    "sg:phone":"+32 61 21 96 12",
    "sg:postcode":"6600",
    "sg:province":"Luxembourg",
    "sg:tags":[
        "rental",
        "-",
        "hall"
    ],
    "wof:name":"Tourelle (la)",
    "wof:placetype":"venue"
},
  "geometry": {"coordinates":[5.7171678543,50.0018157959],"type":"Point"}
}