{
  "type": "Feature",
  "properties": {
    "iso:country":"BE",
    "sg:address":"Centrum Zuid 1410",
    "sg:city":"Houthalen-helchteren (houthalen)",
    "sg:classifiers":[
        {
            "category":"Airport",
            "subcategory":"International",
            "type":"Transportation"
        }
    ],
    "sg:phone":"+32 11 52 41 37",
    "sg:postcode":"3530",
    "sg:province":"Limburg",
    "sg:tags":[
        "-",
        "transport"
    ],
    "wof:name":"Vandebeeck Transport",
    "wof:placetype":"venue"
},
  "geometry": {"coordinates":[5.3644962311,51.0231018066],"type":"Point"}
}