{
  "type": "Feature",
  "properties": {
    "addr:full":"Centrum Zuid 1410 Houthalen-helchteren (houthalen) Limburg 3530",
    "addr:housenumber":"1410",
    "addr:postcode":"3530",
    "addr:street":"Centrum Zuid",
    "iso:country":"BE",
    "sg:address":"Centrum Zuid 1410",
    "sg:city":"Houthalen-helchteren (houthalen)",
    "sg:classifiers":[
        {
            "category":"Airport",
            "subcategory":"International",
            "type":"Transportation"
        }
    ],
    "sg:phone":"+32 11 52 41 37",
    "sg:postcode":"3530",
    "sg:province":"Limburg",
    "sg:tags":[
        "-",
        "transport"
    ],
    "wof:name":"Vandebeeck Transport",
    "wof:placetype":"venue"
},
  "geometry": {"coordinates":[5.3644962311,51.0231018066],"type":"Point"}
}