{
  "type": "Feature",
  "properties": {
    "iso:country":"BE",
    "sg:address":"Mgr. Ladeuzeplein 3",
    "sg:city":"Leuven",
    "sg:orig_category":"Avocats and conseillers juridiques",
    "sg:phone":"+32 16 22 11 36",
    "sg:postcode":"3000",
    "sg:province":"Vlaams-Brabant",
    "wof:name":"J. Vanrijkel",
    "wof:placetype":"venue"
},
  "geometry": {"coordinates":[4.7056150436,50.8788032532],"type":"Point"}
}