{
  "type": "Feature",
  "properties": {
    "iso:country":"BE",
    "sg:address":"Rue David Van Bever 19",
    "sg:city":"Bruxelles (woluwe-saint-pierre)",
    "sg:classifiers":[
        {
            "category":"Real Estate",
            "subcategory":"Surveying",
            "type":"Services"
        }
    ],
    "sg:phone":"+32 2 779 05 65",
    "sg:postcode":"1150",
    "sg:province":"Bruxelles-Capitale",
    "sg:tags":[
        "surveyor",
        "land"
    ],
    "wof:name":"Van Leckwyck Th",
    "wof:placetype":"venue"
},
  "geometry": {"coordinates":[4.4397211075,50.8331871033],"type":"Point"}
}