{
  "type": "Feature",
  "properties": {
    "iso:country":"BE",
    "sg:address":"Burgemeester Henrylaan 12a",
    "sg:city":"Dilsen-stokkem (elen)",
    "sg:classifiers":[
        {
            "category":"Home & Garden",
            "subcategory":"Carpets & Floor Coverings",
            "type":"Retail Goods"
        }
    ],
    "sg:phone":"+32 89 75 65 02",
    "sg:postcode":"3650",
    "sg:province":"Limburg",
    "sg:tags":[
        "layer",
        "mosaicists"
    ],
    "wof:name":"Van Esser & Zn",
    "wof:placetype":"venue"
},
  "geometry": {"coordinates":[5.7338991165,51.0548248291],"type":"Point"}
}