{
  "type": "Feature",
  "properties": {
    "addr:full":"Bouwelven 10 Grobbendonk Antwerpen 2280",
    "addr:housenumber":"10",
    "addr:postcode":"2280",
    "addr:street":"Bouwelven",
    "iso:country":"BE",
    "sg:address":"Bouwelven 10",
    "sg:city":"Grobbendonk",
    "sg:orig_category":"Articles de jardin",
    "sg:phone":"+32 14 25 80 60",
    "sg:postcode":"2280",
    "sg:province":"Antwerpen",
    "wof:name":"Veneta",
    "wof:placetype":"venue"
},
  "geometry": {"coordinates":[4.7078671455,51.1741371155],"type":"Point"}
}