{
  "type": "Feature",
  "properties": {
    "addr:full":"Keizer Karellaan 7 Ganshoren Bruxelles-Capitale 1083",
    "addr:housenumber":"7",
    "addr:postcode":"1083",
    "addr:street":"Keizer Karellaan",
    "iso:country":"BE",
    "sg:address":"Keizer Karellaan 7",
    "sg:city":"Ganshoren",
    "sg:orig_category":"Banken and kredietinstellingen",
    "sg:phone":"+32 2 426 20 06",
    "sg:postcode":"1083",
    "sg:province":"Bruxelles-Capitale",
    "wof:name":"Bbl",
    "wof:placetype":"venue"
},
  "geometry": {"coordinates":[4.3146219254,50.8676338196],"type":"Point"}
}