{
  "type": "Feature",
  "properties": {
    "iso:country":"BE",
    "sg:address":"Houwstraat 3",
    "sg:city":"Putte",
    "sg:orig_category":"Belastingconsulenten Diverse juridische dienstverlening",
    "sg:phone":"+32 15 75 70 94",
    "sg:postcode":"2580",
    "sg:province":"Antwerpen",
    "wof:name":"Grossen Profserv",
    "wof:placetype":"venue"
},
  "geometry": {"coordinates":[4.6543111801,51.0614929199],"type":"Point"}
}