{
  "type": "Feature",
  "properties": {
    "addr:full":"Pothoekstraat 75 Antwerpen Antwerpen 2060",
    "addr:housenumber":"75",
    "addr:postcode":"2060",
    "addr:street":"Pothoekstraat",
    "iso:country":"BE",
    "sg:address":"Pothoekstraat 75",
    "sg:city":"Antwerpen",
    "sg:classifiers":[
        {
            "category":"Food & Beverages",
            "subcategory":"Groceries & Convenience Stores",
            "type":"Retail Goods"
        }
    ],
    "sg:phone":"+32 3 272 02 43",
    "sg:postcode":"2060",
    "sg:province":"Antwerpen",
    "sg:tags":[
        "grocer"
    ],
    "wof:name":"F.nur",
    "wof:placetype":"venue"
},
  "geometry": {"coordinates":[4.4366512299,51.2220802307],"type":"Point"}
}