{
  "type": "Feature",
  "properties": {
    "addr:full":"Visserijstraat 42 Oudergem/auderghem Bruxelles-Capitale 1160",
    "addr:housenumber":"42",
    "addr:postcode":"1160",
    "addr:street":"Visserijstraat;/",
    "iso:country":"BE",
    "sg:address":"Visserijstraat 42",
    "sg:city":"Oudergem/auderghem",
    "sg:orig_category":"Muziekinstrumenten Verhuisdiensten",
    "sg:phone":"+32 2 673 52 65",
    "sg:postcode":"1160",
    "sg:province":"Bruxelles-Capitale",
    "wof:name":"De Meu Debrye",
    "wof:placetype":"venue"
},
  "geometry": {"coordinates":[4.4083890915,50.8125991821],"type":"Point"}
}