{
  "type": "Feature",
  "properties": {
    "iso:country":"BE",
    "sg:address":"Kleinebeerstraat 3",
    "sg:city":"Antwerpen",
    "sg:orig_category":"Fleurs and plantes",
    "sg:phone":"+32 3 235 06 44",
    "sg:postcode":"2018",
    "sg:province":"Antwerpen",
    "wof:name":"Myra Bloem Bax",
    "wof:placetype":"venue"
},
  "geometry": {"coordinates":[4.4273281097,51.2079238892],"type":"Point"}
}