{
  "type": "Feature",
  "properties": {
    "addr:full":"Boomgaardendreef 7 B3 Tienen Vlaams-Brabant 3300",
    "addr:housenumber":"7 b3",
    "addr:postcode":"3300",
    "addr:street":"Boomgaardendreef",
    "iso:country":"BE",
    "sg:address":"Boomgaardendreef 7 B3",
    "sg:city":"Tienen",
    "sg:orig_category":"Architecten",
    "sg:phone":"+32 16 82 10 85",
    "sg:postcode":"3300",
    "sg:province":"Vlaams-Brabant",
    "wof:name":"Paul Moens",
    "wof:placetype":"venue"
},
  "geometry": {"coordinates":[4.930077076,50.8096694946],"type":"Point"}
}