{
  "type": "Feature",
  "properties": {
    "iso:country":"BE",
    "sg:address":"Rue Piretfontaine 50",
    "sg:city":"Sprimont (dolembreux)",
    "sg:classifiers":[
        {
            "category":"Professional",
            "subcategory":"Art Services",
            "type":"Services"
        }
    ],
    "sg:phone":"+32 4 368 58 86",
    "sg:postcode":"4140",
    "sg:province":"Li\u00e8ge",
    "sg:tags":[
        "designer",
        "display"
    ],
    "wof:name":"Stiz A.m.",
    "wof:placetype":"venue"
},
  "geometry": {"coordinates":[5.6415672302,50.538772583],"type":"Point"}
}