{
  "type": "Feature",
  "properties": {
    "addr:full":"Zwarte Vogelstraat 23ba Edingen/enghien Hainaut 7850",
    "addr:housenumber":"23ba",
    "addr:postcode":"7850",
    "addr:street":"Zwarte Vogelstraat",
    "iso:country":"BE",
    "sg:address":"Zwarte Vogelstraat 23ba",
    "sg:city":"Edingen/enghien",
    "sg:orig_category":"Boomkwekerijen",
    "sg:phone":"+32 2 395 75 57",
    "sg:postcode":"7850",
    "sg:province":"Hainaut",
    "wof:name":"P\u00c9pini\u00c8res D\u00b4enghien",
    "wof:placetype":"venue"
},
  "geometry": {"coordinates":[4.0630130768,50.6858711243],"type":"Point"}
}