{
  "type": "Feature",
  "properties": {
    "addr:full":"Werkenstraat 103 Kortemark West-Vlaanderen 8610",
    "addr:housenumber":"103",
    "addr:postcode":"8610",
    "addr:street":"Werkenstraat",
    "iso:country":"BE",
    "sg:address":"Werkenstraat 103",
    "sg:city":"Kortemark",
    "sg:orig_category":"Varkenskwekers",
    "sg:phone":"+32 51 56 68 14",
    "sg:postcode":"8610",
    "sg:province":"West-Vlaanderen",
    "wof:name":"Stefan Desmedt",
    "wof:placetype":"venue"
},
  "geometry": {"coordinates":[2.9820280075,51.0288276672],"type":"Point"}
}