{
  "type": "Feature",
  "properties": {
    "addr:full":"Frans Van Molderstraat 33 Machelen Vlaams-Brabant 1830",
    "addr:housenumber":"33",
    "addr:postcode":"1830",
    "addr:street":"Frans Van Molderstraat",
    "iso:country":"BE",
    "sg:address":"Frans Van Molderstraat 33",
    "sg:city":"Machelen",
    "sg:classifiers":[
        {
            "category":"Retail",
            "subcategory":"Auto Repair",
            "type":"Services"
        }
    ],
    "sg:phone":"+32 2 252 32 50",
    "sg:postcode":"1830",
    "sg:province":"Vlaams-Brabant",
    "sg:tags":[
        "automobile-body"
    ],
    "wof:name":"D W Car Design",
    "wof:placetype":"venue"
},
  "geometry": {"coordinates":[4.4360890388,50.9155693054],"type":"Point"}
}