{
  "type": "Feature",
  "properties": {
    "iso:country":"BE",
    "sg:address":"Rue De Corbais 33",
    "sg:city":"Mont-saint-guibert",
    "sg:classifiers":[
        {
            "category":"Professional",
            "subcategory":"Lawyer & Legal Services",
            "type":"Services"
        }
    ],
    "sg:phone":"+32 10 65 52 90",
    "sg:postcode":"1435",
    "sg:province":"Brabant Wallon",
    "wof:name":"Laurent J-l",
    "wof:placetype":"venue"
},
  "geometry": {"coordinates":[4.6177759171,50.6396331787],"type":"Point"}
}