{
  "type": "Feature",
  "properties": {
    "iso:country":"BE",
    "sg:address":"Zonnestraat 13",
    "sg:city":"Nazareth (eke)",
    "sg:classifiers":[
        {
            "category":"Health Services",
            "subcategory":"Nursing And Care Facility",
            "type":"Services"
        }
    ],
    "sg:phone":"+32 9 384 50 76",
    "sg:postcode":"9810",
    "sg:province":"Oost-Vlaanderen",
    "sg:tags":[
        "home",
        "rest"
    ],
    "wof:name":"Zonnehoeve",
    "wof:placetype":"venue"
},
  "geometry": {"coordinates":[3.6375999451,50.9391021729],"type":"Point"}
}