{
  "type": "Feature",
  "properties": {
    "addr:full":"Avenue De Levis Mirepoix 76 Bruxelles (jette) Bruxelles-Capitale 1090",
    "addr:housenumber":"76",
    "addr:postcode":"1090",
    "addr:street":"Avenue De Levis Mirepoix",
    "iso:country":"BE",
    "sg:address":"Avenue De Levis Mirepoix 76",
    "sg:city":"Bruxelles (jette)",
    "sg:classifiers":[
        {
            "category":"Building & Trades",
            "subcategory":"Electrical",
            "type":"Services"
        }
    ],
    "sg:phone":"+32 2 420 20 90",
    "sg:postcode":"1090",
    "sg:province":"Bruxelles-Capitale",
    "sg:tags":[
        "heating"
    ],
    "wof:name":"Ebac",
    "wof:placetype":"venue"
},
  "geometry": {"coordinates":[4.330728054,50.8714256287],"type":"Point"}
}