{
  "type": "Feature",
  "properties": {
    "iso:country":"BE",
    "sg:address":"Schoolstraat 17",
    "sg:city":"Zwalm",
    "sg:orig_category":"Woningbouw",
    "sg:phone":"+32 55 49 94 04",
    "sg:postcode":"9636",
    "sg:province":"Oost-Vlaanderen",
    "wof:name":"Bouwwerken Eeckhout",
    "wof:placetype":"venue"
},
  "geometry": {"coordinates":[3.686537981,50.8873672485],"type":"Point"}
}