{
  "type": "Feature",
  "properties": {
    "addr:full":"Rue Du Travail 48 Namur Namur 5000",
    "addr:housenumber":"48",
    "addr:postcode":"5000",
    "addr:street":"Rue Du Travail",
    "iso:country":"BE",
    "sg:address":"Rue Du Travail 48",
    "sg:city":"Namur",
    "sg:orig_category":"M\u00e9decins and sp\u00e9cialistes",
    "sg:phone":"+32 81 74 60 19",
    "sg:postcode":"5000",
    "sg:province":"Namur",
    "wof:name":"Fouzia Belbachir",
    "wof:placetype":"venue"
},
  "geometry": {"coordinates":[4.8429670334,50.4585609436],"type":"Point"}
}