{
  "type": "Feature",
  "properties": {
    "addr:full":"Klaverstraat 11 Anderlecht/anderlecht Bruxelles-Capitale 1070",
    "addr:housenumber":"11",
    "addr:postcode":"1070",
    "addr:street":"Klaverstraat",
    "iso:country":"BE",
    "sg:address":"Klaverstraat 11",
    "sg:city":"Anderlecht/anderlecht",
    "sg:orig_category":"Afval and schroot Gh",
    "sg:phone":"+32 2 521 74 12",
    "sg:postcode":"1070",
    "sg:province":"Bruxelles-Capitale",
    "wof:name":"Eugene Roobaert Peeters/e. Roobaert",
    "wof:placetype":"venue"
},
  "geometry": {"coordinates":[4.291741848,50.8192939758],"type":"Point"}
}