{
  "type": "Feature",
  "properties": {
    "addr:full":"Rue De La Cuve 20 Bruxelles (ixelles) Bruxelles-Capitale 1050",
    "addr:housenumber":"20",
    "addr:postcode":"1050",
    "addr:street":"Rue De La Cuve",
    "iso:country":"BE",
    "sg:address":"Rue De La Cuve 20",
    "sg:city":"Bruxelles (ixelles)",
    "sg:classifiers":[
        {
            "category":"Building & Trades",
            "subcategory":"Construction",
            "type":"Services"
        }
    ],
    "sg:phone":"+32 2 648 93 18",
    "sg:postcode":"1050",
    "sg:province":"Bruxelles-Capitale",
    "sg:tags":[
        "ecological"
    ],
    "wof:name":"Acte",
    "wof:placetype":"venue"
},
  "geometry": {"coordinates":[4.3755860329,50.8273506165],"type":"Point"}
}