{
  "type": "Feature",
  "properties": {
    "iso:country":"BE",
    "sg:address":"Rue De L'ar\u00c8ne 10",
    "sg:city":"Clavier",
    "sg:orig_category":"Bouwmaterialen Gh",
    "sg:phone":"+32 83 63 47 97",
    "sg:postcode":"4560",
    "sg:province":"Li\u00e8ge",
    "wof:name":"Acp-asphalt Coating Products",
    "wof:placetype":"venue"
},
  "geometry": {"coordinates":[5.3616900444,50.4105606079],"type":"Point"}
}