{
  "type": "Feature",
  "properties": {
    "iso:country":"BE",
    "sg:address":"Landergemstraat 20",
    "sg:city":"Anzegem",
    "sg:classifiers":[
        {
            "category":"Personal",
            "subcategory":"Beauty Salon",
            "type":"Services"
        }
    ],
    "sg:phone":"+32 56 68 00 17",
    "sg:postcode":"8570",
    "sg:province":"West-Vlaanderen",
    "sg:tags":[
        "lady",
        "-",
        "hairdressing"
    ],
    "wof:name":"Exel Coiffure",
    "wof:placetype":"venue"
},
  "geometry": {"coordinates":[3.4550459385,50.8301582336],"type":"Point"}
}