{
  "type": "Feature",
  "properties": {
    "iso:country":"BE",
    "sg:address":"Bruinstraat 45",
    "sg:city":"Zonhoven",
    "sg:classifiers":[
        {
            "category":"Manufacturing",
            "subcategory":"Building Materials",
            "type":"Manufacturing & Wholesale Goods"
        }
    ],
    "sg:phone":"+32 11 81 30 01",
    "sg:postcode":"3520",
    "sg:province":"Limburg",
    "sg:tags":[
        "formwork",
        "shuttering"
    ],
    "wof:name":"Exterieur Nv",
    "wof:placetype":"venue"
},
  "geometry": {"coordinates":[5.3555688858,51.0044174194],"type":"Point"}
}