{
  "type": "Feature",
  "properties": {
    "addr:full":"Diesterstraat 98 Tessenderlo Limburg 3980",
    "addr:housenumber":"98",
    "addr:postcode":"3980",
    "addr:street":"Diesterstraat",
    "iso:country":"BE",
    "sg:address":"Diesterstraat 98",
    "sg:city":"Tessenderlo",
    "sg:orig_category":"Drogueries. Cr\u00e9meries",
    "sg:phone":"+32 13 66 62 48",
    "sg:postcode":"3980",
    "sg:province":"Limburg",
    "wof:name":"Gilbert Timmers",
    "wof:placetype":"venue"
},
  "geometry": {"coordinates":[5.0886659622,51.0629043579],"type":"Point"}
}