{
  "type": "Feature",
  "properties": {
    "iso:country":"BE",
    "sg:address":"Brusselstraat 90",
    "sg:city":"Dilbeek (groot - Bijgaarden)",
    "sg:classifiers":[
        {
            "category":"Wholesale",
            "subcategory":"Scrap",
            "type":"Manufacturing & Wholesale Goods"
        }
    ],
    "sg:phone":"+32 2 466 00 38",
    "sg:postcode":"1702",
    "sg:province":"Vlaams-Brabant",
    "sg:tags":[
        "dustbin",
        "dustbagholders"
    ],
    "wof:name":"B M S Bvba",
    "wof:placetype":"venue"
},
  "geometry": {"coordinates":[4.275039196,50.8680267334],"type":"Point"}
}