{
  "type": "Feature",
  "properties": {
    "iso:country":"BE",
    "sg:address":"Rue De L'acad\u00e9mie 85",
    "sg:city":"Li\u00e8ge 1",
    "sg:classifiers":[
        {
            "category":"Landmark",
            "subcategory":"Scenic View",
            "type":"Public Place"
        }
    ],
    "sg:phone":"+32 4 221 00 19",
    "sg:postcode":"4000",
    "sg:province":"Li\u00e8ge",
    "sg:tags":[
        "setting",
        "photographic"
    ],
    "wof:name":"Guillaume M",
    "wof:placetype":"venue"
},
  "geometry": {"coordinates":[5.5650901794,50.6469459534],"type":"Point"}
}