{
  "type": "Feature",
  "properties": {
    "addr:full":"Rue Du Village 5 Eghezee Namur 5310",
    "addr:housenumber":"5",
    "addr:postcode":"5310",
    "addr:street":"Rue Du Village;Namur",
    "iso:country":"BE",
    "sg:address":"Rue Du Village 5",
    "sg:city":"Eghezee",
    "sg:classifiers":[
        {
            "category":"Shopping",
            "subcategory":"Crafts & Fabrics",
            "type":"Retail Goods"
        }
    ],
    "sg:phone":"+32 81 81 30 60",
    "sg:postcode":"5310",
    "sg:province":"Namur",
    "sg:tags":[
        "textile",
        "fab",
        "copyshops",
        "diver",
        "imprimeries"
    ],
    "wof:name":"Socobrod",
    "wof:placetype":"venue"
},
  "geometry": {"coordinates":[4.8922739029,50.6088943481],"type":"Point"}
}