{
  "type": "Feature",
  "properties": {
    "addr:full":"Place Du Pairay 8 Seraing Li\u00e8ge 4100",
    "addr:housenumber":"8",
    "addr:postcode":"4100",
    "addr:street":"Place Du Pairay",
    "iso:country":"BE",
    "sg:address":"Place Du Pairay 8",
    "sg:city":"Seraing",
    "sg:classifiers":[
        {
            "category":"Shopping",
            "subcategory":"Clothing, Apparel, & Fashions",
            "type":"Retail Goods"
        }
    ],
    "sg:phone":"+32 4 337 88 96",
    "sg:postcode":"4100",
    "sg:province":"Li\u00e8ge",
    "sg:tags":[
        "boutique"
    ],
    "wof:name":"Nuances",
    "wof:placetype":"venue"
},
  "geometry": {"coordinates":[5.5110731125,50.598274231],"type":"Point"}
}