{
  "type": "Feature",
  "properties": {
    "addr:full":"Le Piroux 5 Braine-le-comte (petit-roeulx-lez-braine) Hainaut 7090",
    "addr:housenumber":"5",
    "addr:postcode":"7090",
    "addr:street":"Braine-Le-Comte Petit-Roeulx-Lez-Braine Hainaut",
    "iso:country":"BE",
    "sg:address":"Le Piroux 5",
    "sg:city":"Braine-le-comte (petit-roeulx-lez-braine)",
    "sg:orig_category":"Fa\u00e7ade covering",
    "sg:phone":"+32 67 63 41 33",
    "sg:postcode":"7090",
    "sg:province":"Hainaut",
    "wof:name":"Platracim",
    "wof:placetype":"venue"
},
  "geometry": {"coordinates":[4.0942120552,50.6225395203],"type":"Point"}
}