{
  "type": "Feature",
  "properties": {
    "iso:country":"BE",
    "sg:address":"Kattestraat 18",
    "sg:city":"Geraardsbergen",
    "sg:orig_category":"Herstelling and restauratie van meubelen Textiel Verlichting and huishoudartikelen Vloer- and muurbe",
    "sg:phone":"+32 54 41 55 66",
    "sg:postcode":"9500",
    "sg:province":"Oost-Vlaanderen",
    "wof:name":"Mattex",
    "wof:placetype":"venue"
},
  "geometry": {"coordinates":[3.8789339066,50.7711868286],"type":"Point"}
}