{
  "type": "Feature",
  "properties": {
    "addr:full":"Av. De For\u00cat De Soignes 220 Sint-genesius-rode/rhode-saint-genese Vlaams-Brabant 1640",
    "addr:housenumber":"220",
    "addr:postcode":"1640",
    "addr:street":"Av. De Fore\u0302T De Soignes",
    "iso:country":"BE",
    "sg:address":"Av. De For\u00cat De Soignes 220",
    "sg:city":"Sint-genesius-rode/rhode-saint-genese",
    "sg:orig_category":"Pain, p\u00e2tisseries and confiseries",
    "sg:phone":"+32 2 358 15 93",
    "sg:postcode":"1640",
    "sg:province":"Vlaams-Brabant",
    "wof:name":"P\u00c2tisserie Chez Sabrina",
    "wof:placetype":"venue"
},
  "geometry": {"coordinates":[4.3657031059,50.7496490479],"type":"Point"}
}