{
  "type": "Feature",
  "properties": {
    "iso:country":"BE",
    "sg:address":"Rue Des Com\u00e9diens 20",
    "sg:city":"Bruxelles",
    "sg:classifiers":[
        {
            "category":"Bakery",
            "type":"Food & Drink"
        }
    ],
    "sg:phone":"+32 2 513 40 03",
    "sg:postcode":"1000",
    "sg:province":"Bruxelles-Capitale",
    "sg:tags":[
        "confectioner",
        "baker"
    ],
    "wof:name":"Bobol",
    "wof:placetype":"venue"
},
  "geometry": {"coordinates":[4.3586759567,50.8502388],"type":"Point"}
}