{
  "type": "Feature",
  "properties": {
    "addr:full":"Rue De La R\u00e9volution 12 Box 1 Bruxelles Bruxelles-Capitale 1000",
    "addr:housenumber":"12;1",
    "addr:postcode":"1000",
    "addr:street":"Rue De La Re\u0301Volution;Box",
    "iso:country":"BE",
    "sg:address":"Rue De La R\u00e9volution 12 Box 1",
    "sg:city":"Bruxelles",
    "sg:classifiers":[
        {
            "category":"Professional",
            "subcategory":"Computer Services",
            "type":"Services"
        }
    ],
    "sg:phone":"+32 2 250 39 30",
    "sg:postcode":"1000",
    "sg:province":"Bruxelles-Capitale",
    "sg:tags":[
        "-",
        "processing",
        "data",
        "software"
    ],
    "wof:name":"Specicom",
    "wof:placetype":"venue"
},
  "geometry": {"coordinates":[4.3667998314,50.8509216309],"type":"Point"}
}