{
  "type": "Feature",
  "properties": {
    "addr:full":"Boulevard Pr\u00e9sident Kennedy 2a Mons Hainaut 7000",
    "addr:housenumber":"2a",
    "addr:postcode":"7000",
    "addr:street":"Boulevard Pre\u0301Sident Kennedy;Hainaut",
    "iso:country":"BE",
    "sg:address":"Boulevard Pr\u00e9sident Kennedy 2a",
    "sg:city":"Mons",
    "sg:classifiers":[
        {
            "category":"Education",
            "subcategory":"University",
            "type":"Public Place"
        }
    ],
    "sg:phone":"+32 65 32 89 00",
    "sg:postcode":"7000",
    "sg:province":"Hainaut",
    "sg:tags":[
        "higher"
    ],
    "wof:name":"Inst Prov De L'enseignement Sup\u00e9rieur De Nursing",
    "wof:placetype":"venue"
},
  "geometry": {"coordinates":[3.961124897,50.4565391541],"type":"Point"}
}