{
  "type": "Feature",
  "properties": {
    "addr:full":"Warande 20 Sint-laureins Oost-Vlaanderen 9982",
    "addr:housenumber":"20",
    "addr:postcode":"9982",
    "addr:street":"Warande",
    "iso:country":"BE",
    "sg:address":"Warande 20",
    "sg:city":"Sint-laureins",
    "sg:orig_category":"Eleveurs de bovins",
    "sg:phone":"+32 9 379 94 30",
    "sg:postcode":"9982",
    "sg:province":"Oost-Vlaanderen",
    "wof:name":"Arsene Dhaese",
    "wof:placetype":"venue"
},
  "geometry": {"coordinates":[3.5862429142,51.2470817566],"type":"Point"}
}