{
  "type": "Feature",
  "properties": {
    "iso:country":"BE",
    "sg:address":"Kanegemdorp 28",
    "sg:city":"Tielt",
    "sg:classifiers":[
        {
            "category":"Restaurant",
            "type":"Food & Drink"
        }
    ],
    "sg:phone":"+32 51 68 99 62",
    "sg:postcode":"8700",
    "sg:province":"West-Vlaanderen",
    "wof:name":"Restaurant 't Lindeke",
    "wof:placetype":"venue"
},
  "geometry": {"coordinates":[3.4037470818,51.0136070251],"type":"Point"}
}