{
  "type": "Feature",
  "properties": {
    "iso:country":"BE",
    "sg:address":"Koffiestraat 27bb",
    "sg:city":"Berlare",
    "sg:orig_category":"Woningbouw",
    "sg:phone":"+32 9 367 53 30",
    "sg:postcode":"9290",
    "sg:province":"Oost-Vlaanderen",
    "wof:name":"Oosterlinck Francky",
    "wof:placetype":"venue"
},
  "geometry": {"coordinates":[3.9549500942,51.0180702209],"type":"Point"}
}