{
  "type": "Feature",
  "properties": {
    "iso:country":"BE",
    "sg:address":"Grote Heibergstraat 33a",
    "sg:city":"Hulshout",
    "sg:orig_category":"Non-Classified Establishments",
    "sg:phone":"+32 15 22 12 92",
    "sg:postcode":"2235",
    "sg:province":"Antwerpen",
    "wof:name":"Bnr Advertising Bvba",
    "wof:placetype":"venue"
},
  "geometry": {"coordinates":[4.811111927,51.0695152283],"type":"Point"}
}