{
  "type": "Feature",
  "properties": {
    "addr:full":"Rue Du Grand Enclos Orgeo Luxembourg 6880",
    "addr:postcode":"6880",
    "addr:street":"Rue Du Grand Enclos",
    "iso:country":"BE",
    "sg:address":"Rue Du Grand Enclos",
    "sg:city":"Orgeo",
    "sg:classifiers":[
        {
            "category":"Banks & Credit Unions",
            "subcategory":"Bureau De Change",
            "type":"Services"
        }
    ],
    "sg:phone":"+32 61 41 16 57",
    "sg:postcode":"6880",
    "sg:province":"Luxembourg",
    "sg:tags":[
        "melting",
        "grease",
        "-"
    ],
    "wof:name":"Protelux Sprl",
    "wof:placetype":"venue"
},
  "geometry": {"coordinates":[5.339630127,49.8309402466],"type":"Point"}
}