{
  "type": "Feature",
  "properties": {
    "iso:country":"BE",
    "sg:address":"Chauss\u00e9e De Wavre 1347",
    "sg:city":"Bruxelles (auderghem)",
    "sg:classifiers":[
        {
            "category":"Education",
            "subcategory":"School",
            "type":"Public Place"
        }
    ],
    "sg:phone":"+32 473 30 48 13",
    "sg:postcode":"1160",
    "sg:province":"Bruxelles-Capitale",
    "sg:tags":[
        "-",
        "private"
    ],
    "wof:name":"Ecole Des Devoirs Elan Asbl",
    "wof:placetype":"venue"
},
  "geometry": {"coordinates":[4.4107441902,50.8201217651],"type":"Point"}
}