{
  "type": "Feature",
  "properties": {
    "addr:full":"Rue De La Loquette 31 P\u00e9ruwelz Hainaut 7600",
    "addr:housenumber":"31",
    "addr:postcode":"7600",
    "addr:street":"Rue De La Loquette",
    "iso:country":"BE",
    "sg:address":"Rue De La Loquette 31",
    "sg:city":"P\u00e9ruwelz",
    "sg:classifiers":[
        {
            "category":"Health Services",
            "subcategory":"Health Practitioner",
            "type":"Services"
        }
    ],
    "sg:phone":"+32 69 77 47 93",
    "sg:postcode":"7600",
    "sg:province":"Hainaut",
    "sg:tags":[
        "physiotherapist"
    ],
    "wof:name":"Roussy S\u00e9verine",
    "wof:placetype":"venue"
},
  "geometry": {"coordinates":[3.5945310593,50.5160751343],"type":"Point"}
}