{
  "type": "Feature",
  "properties": {
    "addr:full":"Gentsesteenweg 83 Deinze Oost-Vlaanderen 9800",
    "addr:housenumber":"83",
    "addr:postcode":"9800",
    "addr:street":"Gentsesteenweg",
    "iso:country":"BE",
    "sg:address":"Gentsesteenweg 83",
    "sg:city":"Deinze",
    "sg:orig_category":"Schoonheidssalons",
    "sg:phone":"+32 9 386 70 86",
    "sg:postcode":"9800",
    "sg:province":"Oost-Vlaanderen",
    "wof:name":"Pedicure Linda",
    "wof:placetype":"venue"
},
  "geometry": {"coordinates":[3.5431790352,50.9808082581],"type":"Point"}
}