{
  "type": "Feature",
  "properties": {
    "addr:full":"Rue Des Muguets 23 Hotton Luxembourg 6990",
    "addr:housenumber":"23",
    "addr:postcode":"6990",
    "addr:street":"Rue Des Muguets",
    "iso:country":"BE",
    "sg:address":"Rue Des Muguets 23",
    "sg:city":"Hotton",
    "sg:classifiers":[
        {
            "category":"Professional",
            "subcategory":"Accounting & Tax Preparation",
            "type":"Services"
        }
    ],
    "sg:phone":"+32 84 46 84 05",
    "sg:postcode":"6990",
    "sg:province":"Luxembourg",
    "sg:tags":[
        "bookkeeper"
    ],
    "wof:name":"Ardenn'compta Sprl",
    "wof:placetype":"venue"
},
  "geometry": {"coordinates":[5.4334859848,50.2670860291],"type":"Point"}
}