{
  "type": "Feature",
  "properties": {
    "iso:country":"BE",
    "sg:address":"Begijnhofstraat 19",
    "sg:city":"Zoutleeuw",
    "sg:orig_category":"Beautyfarms, relaxatie and lichamelijk welzijn Schoonheidssalons",
    "sg:phone":"+32 11 78 03 64",
    "sg:postcode":"3440",
    "sg:province":"Vlaams-Brabant",
    "wof:name":"Instituut Greta",
    "wof:placetype":"venue"
},
  "geometry": {"coordinates":[5.1009960175,50.8320884705],"type":"Point"}
}