{
  "type": "Feature",
  "properties": {
    "iso:country":"BE",
    "sg:address":"Hoogveld 71",
    "sg:city":"Dendermonde (sint-gillis-bij-dendermonde)",
    "sg:classifiers":[
        {
            "category":"Home & Garden",
            "subcategory":"Hardware",
            "type":"Retail Goods"
        }
    ],
    "sg:phone":"+32 52 25 90 40",
    "sg:postcode":"9200",
    "sg:province":"Oost-Vlaanderen",
    "sg:tags":[
        "battery",
        "dry"
    ],
    "wof:name":"Interwheels Bandencentrale",
    "wof:placetype":"venue"
},
  "geometry": {"coordinates":[4.1413421631,51.0277900696],"type":"Point"}
}