{
  "type": "Feature",
  "properties": {
    "iso:country":"BE",
    "sg:address":"Rue De L'esp\u00c9rance 118",
    "sg:city":"Charleroi",
    "sg:orig_category":"Jeux de hasard",
    "sg:phone":"+32 71 41 15 30",
    "sg:postcode":"6061",
    "sg:province":"Hainaut",
    "wof:name":"Ladbrokes",
    "wof:placetype":"venue"
},
  "geometry": {"coordinates":[4.4639520645,50.4141082764],"type":"Point"}
}