{
  "type": "Feature",
  "properties": {
    "iso:country":"BE",
    "sg:address":"Sint-katelijnevest 58",
    "sg:city":"Antwerpen",
    "sg:orig_category":"Electrom\u00e9nager, t\u00e9l\u00e9visions and radios. Mat\u00e9riel de T\u00e9l\u00e9communication. R\u00e9parations d'appareils \u00e9lect",
    "sg:phone":"+32 3 233 77 82",
    "sg:postcode":"2000",
    "sg:province":"Antwerpen",
    "wof:name":"Hifinesse",
    "wof:placetype":"venue"
},
  "geometry": {"coordinates":[4.4049592018,51.2191314697],"type":"Point"}
}