{
  "type": "Feature",
  "properties": {
    "iso:country":"BE",
    "sg:address":"Rue Jean Volders 22",
    "sg:city":"Awans",
    "sg:orig_category":"Salles de conf\u00e9rences and de r\u00e9ceptions",
    "sg:phone":"+32 4 246 55 82",
    "sg:postcode":"4340",
    "sg:province":"Li\u00e8ge",
    "wof:name":"La Fontanella",
    "wof:placetype":"venue"
},
  "geometry": {"coordinates":[5.4600419998,50.671962738],"type":"Point"}
}