{
  "type": "Feature",
  "properties": {
    "addr:full":"Rue De Magn\u00c9e 22 Fl\u00c9ron Li\u00e8ge 4620",
    "addr:housenumber":"22",
    "addr:postcode":"4620",
    "addr:street":"Rue De Magne\u0301E",
    "iso:country":"BE",
    "sg:address":"Rue De Magn\u00c9e 22",
    "sg:city":"Fl\u00c9ron",
    "sg:classifiers":[
        {
            "category":"Government",
            "subcategory":"Police Station",
            "type":"Public Place"
        }
    ],
    "sg:phone":"+32 4 358 33 73",
    "sg:postcode":"4620",
    "sg:province":"Li\u00e8ge",
    "sg:tags":[
        "gendarmerie"
    ],
    "wof:name":"Police F\u00c9d\u00c9rale/federale Politie",
    "wof:placetype":"venue"
},
  "geometry": {"coordinates":[5.6814789772,50.6130638123],"type":"Point"}
}