{
  "type": "Feature",
  "properties": {
    "iso:country":"BE",
    "sg:address":"Tieltstraat 67-69",
    "sg:city":"Meulebeke",
    "sg:classifiers":[
        {
            "category":"Banks & Credit Unions",
            "subcategory":"Investment Brokerage",
            "type":"Services"
        }
    ],
    "sg:phone":"+32 51 48 08 11",
    "sg:postcode":"8760",
    "sg:province":"West-Vlaanderen",
    "sg:tags":[
        "blister",
        "card",
        "skin"
    ],
    "wof:name":"Kartonnage Bruggeman-desouter Nv",
    "wof:placetype":"venue"
},
  "geometry": {"coordinates":[3.2959699631,50.9585113525],"type":"Point"}
}