{
  "type": "Feature",
  "properties": {
    "addr:full":"Chemin Des Gardes Fronti\u00e8res 12 Welkenraedt Li\u00e8ge 4840",
    "addr:housenumber":"12",
    "addr:postcode":"4840",
    "addr:street":"Chemin Des Gardes Frontie\u0300Res",
    "iso:country":"BE",
    "sg:address":"Chemin Des Gardes Fronti\u00e8res 12",
    "sg:city":"Welkenraedt",
    "sg:classifiers":[
        {
            "category":"Professional",
            "subcategory":"Accounting & Tax Preparation",
            "type":"Services"
        }
    ],
    "sg:phone":"+32 87 88 35 25",
    "sg:postcode":"4840",
    "sg:province":"Li\u00e8ge",
    "sg:tags":[
        "bookkeeper"
    ],
    "wof:name":"Vannerum L",
    "wof:placetype":"venue"
},
  "geometry": {"coordinates":[5.9187469482,50.6565093994],"type":"Point"}
}