{
  "type": "Feature",
  "properties": {
    "iso:country":"BE",
    "sg:address":"Blaasveldstraat 99",
    "sg:city":"Willebroek",
    "sg:orig_category":"Meubelzaken, woning- and keukeninrichting",
    "sg:phone":"+32 3 886 05 34",
    "sg:postcode":"2830",
    "sg:province":"Antwerpen",
    "wof:name":"Meubelen J. Van Den Bergh",
    "wof:placetype":"venue"
},
  "geometry": {"coordinates":[4.3638548851,51.0356254578],"type":"Point"}
}