{
  "type": "Feature",
  "properties": {
    "iso:country":"BE",
    "sg:address":"Holt 113 Box 1",
    "sg:city":"Bilzen (beverst)",
    "sg:classifiers":[
        {
            "category":"Shopping",
            "subcategory":"Florist",
            "type":"Retail Goods"
        }
    ],
    "sg:phone":"+32 89 49 11 31",
    "sg:postcode":"3740",
    "sg:province":"Limburg",
    "wof:name":"Bloemkepluk",
    "wof:placetype":"venue"
},
  "geometry": {"coordinates":[5.4777560234,50.8893508911],"type":"Point"}
}