{
  "type": "Feature",
  "properties": {
    "addr:full":"Vrouweneikstraat 11 Wortegem-petegem (wortegem) Oost-Vlaanderen 9790",
    "addr:housenumber":"11",
    "addr:postcode":"9790",
    "addr:street":"Vrouweneikstraat;Wortegem",
    "iso:country":"BE",
    "sg:address":"Vrouweneikstraat 11",
    "sg:city":"Wortegem-petegem (wortegem)",
    "sg:classifiers":[
        {
            "category":"Health Services",
            "subcategory":"Dentist",
            "type":"Services"
        }
    ],
    "sg:phone":"+32 56 68 03 53",
    "sg:postcode":"9790",
    "sg:province":"Oost-Vlaanderen",
    "wof:name":"Devogelaere Kathleen",
    "wof:placetype":"venue"
},
  "geometry": {"coordinates":[3.5131180286,50.8518486023],"type":"Point"}
}