{
  "type": "Feature",
  "properties": {
    "iso:country":"BE",
    "sg:address":"Commune 2",
    "sg:city":"Flobecq",
    "sg:classifiers":[
        {
            "category":"Building & Trades",
            "subcategory":"Landscaping Services",
            "type":"Services"
        }
    ],
    "sg:phone":"+32 68 44 75 80",
    "sg:postcode":"7880",
    "sg:province":"Hainaut",
    "sg:tags":[
        "-",
        "lopping",
        "work",
        "tree",
        "felling"
    ],
    "wof:name":"Monnier T",
    "wof:placetype":"venue"
},
  "geometry": {"coordinates":[3.7627100945,50.7581558228],"type":"Point"}
}