{
  "type": "Feature",
  "properties": {
    "iso:country":"BE",
    "sg:address":"Jean-baptiste Now\u00e9lei 14-16",
    "sg:city":"Vilvoorde",
    "sg:classifiers":[
        {
            "category":"Shopping",
            "subcategory":"Shoes",
            "type":"Retail Goods"
        }
    ],
    "sg:phone":"+32 2 257 16 85",
    "sg:postcode":"1800",
    "sg:province":"Vlaams-Brabant",
    "sg:tags":[
        "slipper",
        "-"
    ],
    "wof:name":"Vilvordia Unsafe",
    "wof:placetype":"venue"
},
  "geometry": {"coordinates":[4.4261751175,50.9285621643],"type":"Point"}
}