{
  "type": "Feature",
  "properties": {
    "addr:full":"Route Nationale 4 610 Marche-en-famenne Luxembourg 6900",
    "addr:housenumber":"610",
    "addr:postcode":"6900",
    "addr:street":"Route Nationale 4",
    "iso:country":"BE",
    "sg:address":"Route Nationale 4 610",
    "sg:city":"Marche-en-famenne",
    "sg:classifiers":[
        {
            "category":"Travel",
            "subcategory":"Hotels & Motels",
            "type":"Entertainment"
        }
    ],
    "sg:phone":"+32 84 31 12 98",
    "sg:postcode":"6900",
    "sg:province":"Luxembourg",
    "sg:tags":[
        "equipment",
        "installation",
        "hotels"
    ],
    "wof:name":"Cambo Meubles",
    "wof:placetype":"venue"
},
  "geometry": {"coordinates":[5.3430151939,50.2273483276],"type":"Point"}
}