{
  "type": "Feature",
  "properties": {
    "iso:country":"BE",
    "sg:address":"All\u00e9e Des Sorbiers 11",
    "sg:city":"Erez\u00e9e",
    "sg:orig_category":"Non-Classified Establishments",
    "sg:phone":"+32 86 47 74 67",
    "sg:postcode":"6997",
    "sg:province":"Luxembourg",
    "wof:name":"Depaifve",
    "wof:placetype":"venue"
},
  "geometry": {"coordinates":[5.5577611923,50.2863388062],"type":"Point"}
}