{
  "type": "Feature",
  "properties": {
    "addr:full":"Rue Des Bruy\u00e8res 54 Chaudfontaine (beaufays) Li\u00e8ge 4052",
    "addr:housenumber":"54",
    "addr:postcode":"4052",
    "addr:street":"Rue Des Bruye\u0300Res;Beaufays",
    "iso:country":"BE",
    "sg:address":"Rue Des Bruy\u00e8res 54",
    "sg:city":"Chaudfontaine (beaufays)",
    "sg:classifiers":[
        {
            "category":"Utilities",
            "subcategory":"Telephone",
            "type":"Services"
        }
    ],
    "sg:phone":"+32 4 368 36 77",
    "sg:postcode":"4052",
    "sg:province":"Li\u00e8ge",
    "sg:tags":[
        "-",
        "internet"
    ],
    "wof:name":"Nexus Informatique",
    "wof:placetype":"venue"
},
  "geometry": {"coordinates":[5.6324501038,50.5582771301],"type":"Point"}
}