{
  "type": "Feature",
  "properties": {
    "addr:full":"Koophandelsplein 21 Gent Oost-Vlaanderen 9000",
    "addr:housenumber":"21",
    "addr:postcode":"9000",
    "addr:street":"Koophandelsplein;Oost-Vlaanderen",
    "iso:country":"BE",
    "sg:address":"Koophandelsplein 21",
    "sg:city":"Gent",
    "sg:orig_category":"Tribunaux",
    "sg:phone":"+32 9 267 44 03",
    "sg:postcode":"9000",
    "sg:province":"Oost-Vlaanderen",
    "wof:name":"Vredegerecht",
    "wof:placetype":"venue"
},
  "geometry": {"coordinates":[3.7211689949,51.0494689941],"type":"Point"}
}