{
  "type": "Feature",
  "properties": {
    "addr:full":"Avenue De La Charmille 6b54 Sint-lambrechts-woluwe/woluwe-saint-lambert Bruxelles-Capitale 1200",
    "addr:housenumber":"6b54 sint-lambrechts-woluwe",
    "addr:postcode":"1200",
    "addr:street":"Avenue De La Charmille",
    "iso:country":"BE",
    "sg:address":"Avenue De La Charmille 6b54",
    "sg:city":"Sint-lambrechts-woluwe/woluwe-saint-lambert",
    "sg:classifiers":[
        {
            "category":"Arena",
            "subcategory":"Sports Club",
            "type":"Entertainment"
        }
    ],
    "sg:phone":"+32 2 771 57 47",
    "sg:postcode":"1200",
    "sg:province":"Bruxelles-Capitale",
    "sg:tags":[
        "de"
    ],
    "wof:name":"Avia T.c.",
    "wof:placetype":"venue"
},
  "geometry": {"coordinates":[4.4338002205,50.8535003662],"type":"Point"}
}