{
  "type": "Feature",
  "properties": {
    "addr:full":"Kievitheide 58 Zoersel Antwerpen 2980",
    "addr:housenumber":"58",
    "addr:postcode":"2980",
    "addr:street":"Kievitheide",
    "iso:country":"BE",
    "sg:address":"Kievitheide 58",
    "sg:city":"Zoersel",
    "sg:classifiers":[
        {
            "category":"Professional",
            "subcategory":"Management & Consulting",
            "type":"Services"
        }
    ],
    "sg:phone":"+32 3 309 99 15",
    "sg:postcode":"2980",
    "sg:province":"Antwerpen",
    "sg:tags":[
        "consultant"
    ],
    "wof:name":"Excel Management & Quality Consultants Bvba",
    "wof:placetype":"venue"
},
  "geometry": {"coordinates":[4.7169938087,51.2807807922],"type":"Point"}
}