{
  "type": "Feature",
  "properties": {
    "addr:full":"Chauss\u00c9e D'alsemberg 31 Sint-gillis/saint-gilles Bruxelles-Capitale 1060",
    "addr:housenumber":"31",
    "addr:postcode":"1060",
    "addr:street":"Chausse\u0301E D'Alsemberg",
    "iso:country":"BE",
    "sg:address":"Chauss\u00c9e D'alsemberg 31",
    "sg:city":"Sint-gillis/saint-gilles",
    "sg:orig_category":"M\u00e9decins and sp\u00e9cialistes",
    "sg:phone":"+32 2 538 18 00",
    "sg:postcode":"1060",
    "sg:province":"Bruxelles-Capitale",
    "wof:name":"Christine Dekeyser",
    "wof:placetype":"venue"
},
  "geometry": {"coordinates":[4.3437142372,50.8258743286],"type":"Point"}
}