{
  "type": "Feature",
  "properties": {
    "iso:country":"BE",
    "sg:address":"Rue De Porto 101",
    "sg:city":"Li\u00e8ge 1 (li\u00e8ge 2)",
    "sg:classifiers":[
        {
            "category":"Building & Trades",
            "subcategory":"Equipment Rental",
            "type":"Services"
        }
    ],
    "sg:phone":"+32 4 342 46 36",
    "sg:postcode":"4020",
    "sg:province":"Li\u00e8ge",
    "sg:tags":[
        "tableware",
        "-"
    ],
    "wof:name":"Louis Ets",
    "wof:placetype":"venue"
},
  "geometry": {"coordinates":[5.5960741043,50.6434173584],"type":"Point"}
}