{
  "type": "Feature",
  "properties": {
    "addr:full":"Van Bortonnestraat 95 Jette Bruxelles-Capitale 1090",
    "addr:housenumber":"95",
    "addr:postcode":"1090",
    "addr:street":"Van Bortonnestraat",
    "iso:country":"BE",
    "sg:address":"Van Bortonnestraat 95",
    "sg:city":"Jette",
    "sg:orig_category":"Diverse grafische activiteiten",
    "sg:phone":"+32 2 426 55 75",
    "sg:postcode":"1090",
    "sg:province":"Bruxelles-Capitale",
    "wof:name":"Cuirass\u00c9 Portemine",
    "wof:placetype":"venue"
},
  "geometry": {"coordinates":[4.326374054,50.8774147034],"type":"Point"}
}