{
  "type": "Feature",
  "properties": {
    "addr:full":"Rue D'apollon 47 Frameries (la Bouverie) Hainaut 7080",
    "addr:housenumber":"47",
    "addr:postcode":"7080",
    "addr:street":"Rue D'Apollon",
    "iso:country":"BE",
    "sg:address":"Rue D'apollon 47",
    "sg:city":"Frameries (la Bouverie)",
    "sg:classifiers":[
        {
            "category":"Retail",
            "subcategory":"Auto Repair",
            "type":"Services"
        }
    ],
    "sg:phone":"+32 65 67 74 49",
    "sg:postcode":"7080",
    "sg:province":"Hainaut",
    "sg:tags":[
        "garage"
    ],
    "wof:name":"Autobel Jmd",
    "wof:placetype":"venue"
},
  "geometry": {"coordinates":[3.87864995,50.3898696899],"type":"Point"}
}