{
  "type": "Feature",
  "properties": {
    "addr:full":"Heckenweg 37 Eupen Li\u00e8ge 4700",
    "addr:housenumber":"37",
    "addr:postcode":"4700",
    "addr:street":"Heckenweg",
    "iso:country":"BE",
    "sg:address":"Heckenweg 37",
    "sg:city":"Eupen",
    "sg:classifiers":[
        {
            "category":"Professional",
            "subcategory":"Management & Consulting",
            "type":"Services"
        }
    ],
    "sg:phone":"+32 87 74 24 01",
    "sg:postcode":"4700",
    "sg:province":"Li\u00e8ge",
    "sg:tags":[
        "consultant"
    ],
    "wof:name":"Kirchner A",
    "wof:placetype":"venue"
},
  "geometry": {"coordinates":[6.0445361137,50.6309509277],"type":"Point"}
}