{
  "type": "Feature",
  "properties": {
    "iso:country":"BE",
    "sg:address":"Dorpsplein 4",
    "sg:city":"Wevelgem",
    "sg:classifiers":[
        {
            "category":"Food & Beverages",
            "subcategory":"Fruits & Vegetables",
            "type":"Retail Goods"
        }
    ],
    "sg:phone":"+32 56 40 12 20",
    "sg:postcode":"8560",
    "sg:province":"West-Vlaanderen",
    "sg:tags":[
        "l\u00e9gumes"
    ],
    "wof:name":"Fruitcentrale Descamps",
    "wof:placetype":"venue"
},
  "geometry": {"coordinates":[3.2041339874,50.8437690735],"type":"Point"}
}