{
  "type": "Feature",
  "properties": {
    "addr:full":"Rue Fran\u00c7ois-rifon 232 Hastiere Namur 5542",
    "addr:housenumber":"232",
    "addr:postcode":"5542",
    "addr:street":"Rue Franc\u0327Ois-Rifon;Namur",
    "iso:country":"BE",
    "sg:address":"Rue Fran\u00c7ois-rifon 232",
    "sg:city":"Hastiere",
    "sg:classifiers":[
        {
            "category":"Cafe",
            "type":"Food & Drink"
        }
    ],
    "sg:phone":"+32 82 64 52 64",
    "sg:postcode":"5542",
    "sg:province":"Namur",
    "sg:tags":[
        "caf\u00e9s"
    ],
    "wof:name":"Sabine Weyand",
    "wof:placetype":"venue"
},
  "geometry": {"coordinates":[4.8438239098,50.2064590454],"type":"Point"}
}