{
  "type": "Feature",
  "properties": {
    "addr:full":"Paddevijverstr 55 Ieper West-Vlaanderen 8900",
    "addr:housenumber":"55",
    "addr:postcode":"8900",
    "addr:street":"Paddevijverstr",
    "iso:country":"BE",
    "sg:address":"Paddevijverstr 55",
    "sg:city":"Ieper",
    "sg:classifiers":[
        {
            "category":"Shopping",
            "subcategory":"Luggage & Leather Goods",
            "type":"Retail Goods"
        }
    ],
    "sg:phone":"+32 57 20 15 22",
    "sg:postcode":"8900",
    "sg:province":"West-Vlaanderen",
    "sg:tags":[
        "shoe"
    ],
    "wof:name":"Gipsy Nv",
    "wof:placetype":"venue"
},
  "geometry": {"coordinates":[2.8850660324,50.8623962402],"type":"Point"}
}