{
  "type": "Feature",
  "properties": {
    "addr:full":"Rue Sans Souci 18 Bruxelles (ixelles) Bruxelles-Capitale 1050",
    "addr:housenumber":"18",
    "addr:postcode":"1050",
    "addr:street":"Rue Sans Souci",
    "iso:country":"BE",
    "sg:address":"Rue Sans Souci 18",
    "sg:city":"Bruxelles (ixelles)",
    "sg:classifiers":[
        {
            "category":"Personal",
            "subcategory":"Massage",
            "type":"Services"
        }
    ],
    "sg:phone":"+32 2 513 85 01",
    "sg:postcode":"1050",
    "sg:province":"Bruxelles-Capitale",
    "wof:name":"Centre Energ\u00e9tique Humaine",
    "wof:placetype":"venue"
},
  "geometry": {"coordinates":[4.3682789803,50.8348350525],"type":"Point"}
}