{
  "type": "Feature",
  "properties": {
    "iso:country":"BE",
    "sg:address":"Koestraat 40",
    "sg:city":"Gent",
    "sg:classifiers":[
        {
            "category":"Food & Beverages",
            "subcategory":"Meat & Fish",
            "type":"Retail Goods"
        }
    ],
    "sg:phone":"+32 9 225 36 02",
    "sg:postcode":"9000",
    "sg:province":"Oost-Vlaanderen",
    "sg:tags":[
        "poultry",
        "whol",
        "game",
        "-"
    ],
    "wof:name":"Van Hecke",
    "wof:placetype":"venue"
},
  "geometry": {"coordinates":[3.7256979942,51.0511283875],"type":"Point"}
}