{
  "type": "Feature",
  "properties": {
    "iso:country":"BE",
    "sg:address":"Vloeiende 100",
    "sg:city":"Kapellen (mariaburg)",
    "sg:classifiers":[
        {
            "category":"Professional",
            "subcategory":"Accounting & Tax Preparation",
            "type":"Services"
        }
    ],
    "sg:phone":"+32 3 605 93 88",
    "sg:postcode":"2950",
    "sg:province":"Antwerpen",
    "sg:tags":[
        "bookkeeper"
    ],
    "wof:name":"Seeuws K",
    "wof:placetype":"venue"
},
  "geometry": {"coordinates":[4.4293107986,51.2961730957],"type":"Point"}
}