{
  "type": "Feature",
  "properties": {
    "addr:full":"Oscar Van Durmelaan 11 Temse Oost-Vlaanderen 9140",
    "addr:housenumber":"11",
    "addr:postcode":"9140",
    "addr:street":"Oscar Van Durmelaan",
    "iso:country":"BE",
    "sg:address":"Oscar Van Durmelaan 11",
    "sg:city":"Temse",
    "sg:orig_category":"Non-Classified Establishments",
    "sg:phone":"+32 3 771 12 38",
    "sg:postcode":"9140",
    "sg:province":"Oost-Vlaanderen",
    "wof:name":"Pauwels F",
    "wof:placetype":"venue"
},
  "geometry": {"coordinates":[4.2095160484,51.1330947876],"type":"Point"}
}