{
  "type": "Feature",
  "properties": {
    "addr:full":"Rue Charles Piron 66 Mons (ghlin) Hainaut 7011",
    "addr:housenumber":"66",
    "addr:postcode":"7011",
    "addr:street":"Rue Charles Piron",
    "iso:country":"BE",
    "sg:address":"Rue Charles Piron 66",
    "sg:city":"Mons (ghlin)",
    "sg:classifiers":[
        {
            "category":"Home & Garden",
            "subcategory":"Household Appliances",
            "type":"Retail Goods"
        }
    ],
    "sg:phone":"+32 65 35 17 94",
    "sg:postcode":"7011",
    "sg:province":"Hainaut",
    "sg:tags":[
        "repair",
        "stove",
        "-"
    ],
    "wof:name":"Jaucot Cie Sprl",
    "wof:placetype":"venue"
},
  "geometry": {"coordinates":[3.912539959,50.4712982178],"type":"Point"}
}