{
  "type": "Feature",
  "properties": {
    "addr:full":"Tenbosch 13 Bruxelles Bruxelles-Capitale 1000",
    "addr:housenumber":"13",
    "addr:postcode":"1000",
    "addr:street":"Tenbosch",
    "iso:country":"BE",
    "sg:address":"Tenbosch 13",
    "sg:city":"Bruxelles",
    "sg:classifiers":[
        {
            "category":"Health Services",
            "subcategory":"Health Practitioner",
            "type":"Services"
        }
    ],
    "sg:phone":"+32 2 640 31 17",
    "sg:postcode":"1000",
    "sg:province":"Bruxelles-Capitale",
    "sg:tags":[
        "therapist",
        "speech"
    ],
    "wof:name":"Khronos",
    "wof:placetype":"venue"
},
  "geometry": {"coordinates":[4.3660850525,50.8239326477],"type":"Point"}
}