{
  "type": "Feature",
  "properties": {
    "addr:full":"Sur Les Joncs 24 Verviers (lambermont) Li\u00e8ge 4800",
    "addr:housenumber":"24",
    "addr:postcode":"4800",
    "addr:street":"Sur Les Joncs;Lambermont",
    "iso:country":"BE",
    "sg:address":"Sur Les Joncs 24",
    "sg:city":"Verviers (lambermont)",
    "sg:classifiers":[
        {
            "category":"Retail",
            "subcategory":"Event Space",
            "type":"Services"
        }
    ],
    "sg:phone":"+32 87 33 43 36",
    "sg:postcode":"4800",
    "sg:province":"Li\u00e8ge",
    "sg:tags":[
        "rental",
        "-",
        "hall"
    ],
    "wof:name":"Brique Pilee (la)",
    "wof:placetype":"venue"
},
  "geometry": {"coordinates":[5.8695840836,50.566078186],"type":"Point"}
}