{
  "type": "Feature",
  "properties": {
    "iso:country":"BE",
    "sg:address":"Vogelzangstraat 21",
    "sg:city":"Herk-de-stad",
    "sg:orig_category":"Eleveurs and marchands de porcs",
    "sg:phone":"+32 11 31 15 83",
    "sg:postcode":"3540",
    "sg:province":"Limburg",
    "wof:name":"Jozef Goorts",
    "wof:placetype":"venue"
},
  "geometry": {"coordinates":[5.2170000076,50.9189529419],"type":"Point"}
}