{
  "type": "Feature",
  "properties": {
    "iso:country":"BE",
    "sg:address":"Jan Baptist Corremansstraat 3",
    "sg:city":"Boom",
    "sg:classifiers":[
        {
            "category":"Social Services",
            "subcategory":"Job Training",
            "type":"Services"
        }
    ],
    "sg:phone":"+32 3 844 32 19",
    "sg:postcode":"2850",
    "sg:province":"Antwerpen",
    "sg:tags":[
        "personnel"
    ],
    "wof:name":"Descans P",
    "wof:placetype":"venue"
},
  "geometry": {"coordinates":[4.3593120575,51.0884132385],"type":"Point"}
}