{
  "type": "Feature",
  "properties": {
    "addr:full":"Rue De Longtain 43 La Louviere Hainaut 7100",
    "addr:housenumber":"43",
    "addr:postcode":"7100",
    "addr:street":"Rue De Longtain",
    "iso:country":"BE",
    "sg:address":"Rue De Longtain 43",
    "sg:city":"La Louviere",
    "sg:orig_category":"Woningbouw",
    "sg:phone":"+32 64 26 55 27",
    "sg:postcode":"7100",
    "sg:province":"Hainaut",
    "wof:name":"Construction",
    "wof:placetype":"venue"
},
  "geometry": {"coordinates":[4.2037358284,50.4803390503],"type":"Point"}
}