{
  "type": "Feature",
  "properties": {
    "iso:country":"BE",
    "sg:address":"Rue De Rianwelz 1",
    "sg:city":"Courcelles",
    "sg:classifiers":[
        {
            "category":"Home & Garden",
            "subcategory":"Garden Supply",
            "type":"Retail Goods"
        }
    ],
    "sg:phone":"+32 71 45 02 61",
    "sg:postcode":"6180",
    "sg:province":"Hainaut",
    "sg:tags":[
        "seed",
        "-"
    ],
    "wof:name":"Moulin De Rianwelz Sprl",
    "wof:placetype":"venue"
},
  "geometry": {"coordinates":[4.3728151321,50.4515953064],"type":"Point"}
}