{
  "type": "Feature",
  "properties": {
    "iso:country":"BE",
    "sg:address":"H\u00e9domont 11a",
    "sg:city":"Malmedy (beverc\u00e9)",
    "sg:classifiers":[
        {
            "category":"Home & Garden",
            "subcategory":"Garden Supply",
            "type":"Retail Goods"
        }
    ],
    "sg:phone":"+32 80 33 97 56",
    "sg:postcode":"4960",
    "sg:province":"Li\u00e8ge",
    "sg:tags":[
        "machine",
        "agricultural",
        "-"
    ],
    "wof:name":"Munster N",
    "wof:placetype":"venue"
},
  "geometry": {"coordinates":[6.0402050018,50.4044952393],"type":"Point"}
}