{
  "type": "Feature",
  "properties": {
    "iso:country":"BE",
    "sg:address":"Hoogstraat 2",
    "sg:city":"Aalst",
    "sg:orig_category":"Dameskledingzaken",
    "sg:phone":"+32 53 21 13 68",
    "sg:postcode":"9300",
    "sg:province":"Oost-Vlaanderen",
    "wof:name":"Huis Renata",
    "wof:placetype":"venue"
},
  "geometry": {"coordinates":[4.0618829727,50.949306488],"type":"Point"}
}