{
  "type": "Feature",
  "properties": {
    "iso:country":"BE",
    "sg:address":"Chauss\u00e9e De Li\u00e8ge 51",
    "sg:city":"Welkenraedt (henri-chapelle)",
    "sg:classifiers":[
        {
            "category":"Recreation",
            "subcategory":"Dance Hall",
            "type":"Entertainment"
        }
    ],
    "sg:phone":"+32 87 44 71 50",
    "sg:postcode":"4841",
    "sg:province":"Li\u00e8ge",
    "sg:tags":[
        "discotheque"
    ],
    "wof:name":"Villa (la)",
    "wof:placetype":"venue"
},
  "geometry": {"coordinates":[5.9140191078,50.6741867065],"type":"Point"}
}