{
  "type": "Feature",
  "properties": {
    "addr:full":"Rue Du Buverniat 4 Walcourt (clermont) Namur 5650",
    "addr:housenumber":"4",
    "addr:postcode":"5650",
    "addr:street":"Rue Du Buverniat",
    "iso:country":"BE",
    "sg:address":"Rue Du Buverniat 4",
    "sg:city":"Walcourt (clermont)",
    "sg:classifiers":[
        {
            "category":"Health Services",
            "subcategory":"Doctor",
            "type":"Services"
        }
    ],
    "sg:phone":"+32 71 53 41 51",
    "sg:postcode":"5650",
    "sg:province":"Namur",
    "sg:tags":[
        "medicinephysicians",
        "surgeon"
    ],
    "wof:name":"Leotard N",
    "wof:placetype":"venue"
},
  "geometry": {"coordinates":[4.3233828545,50.2577323914],"type":"Point"}
}