{
  "type": "Feature",
  "properties": {
    "iso:country":"BE",
    "sg:address":"Nieuwstraat 15a",
    "sg:city":"Zoutleeuw",
    "sg:classifiers":[
        {
            "category":"Insurance",
            "subcategory":"Insurance Agent",
            "type":"Services"
        }
    ],
    "sg:phone":"+32 11 78 41 14",
    "sg:postcode":"3440",
    "sg:province":"Vlaams-Brabant",
    "sg:tags":[
        "broker"
    ],
    "wof:name":"Thijs D",
    "wof:placetype":"venue"
},
  "geometry": {"coordinates":[5.1056318283,50.8290023804],"type":"Point"}
}