{
  "type": "Feature",
  "properties": {
    "addr:full":"Broeders Vandalestraat 4 Kortrijk West-Vlaanderen 8510",
    "addr:housenumber":"4",
    "addr:postcode":"8510",
    "addr:street":"Vandalestraat",
    "iso:country":"BE",
    "sg:address":"Broeders Vandalestraat 4",
    "sg:city":"Kortrijk",
    "sg:orig_category":"Cr\u00e9meries",
    "sg:phone":"+32 56 21 14 79",
    "sg:postcode":"8510",
    "sg:province":"West-Vlaanderen",
    "wof:name":"Vanneste",
    "wof:placetype":"venue"
},
  "geometry": {"coordinates":[3.2304608822,50.8051147461],"type":"Point"}
}