{
  "type": "Feature",
  "properties": {
    "addr:full":"Rue Bel Air 75 Tubize Brabant Wallon 1480",
    "addr:housenumber":"75",
    "addr:postcode":"1480",
    "addr:street":"Rue Bel Air;Wallon",
    "iso:country":"BE",
    "sg:address":"Rue Bel Air 75",
    "sg:city":"Tubize",
    "sg:classifiers":[
        {
            "category":"Banks & Credit Unions",
            "subcategory":"Investment Brokerage",
            "type":"Services"
        }
    ],
    "sg:phone":"+32 2 390 96 06",
    "sg:postcode":"1480",
    "sg:province":"Brabant Wallon",
    "sg:tags":[
        "fence"
    ],
    "wof:name":"Delporte",
    "wof:placetype":"venue"
},
  "geometry": {"coordinates":[4.1925430298,50.6971092224],"type":"Point"}
}