{
  "type": "Feature",
  "properties": {
    "addr:full":"Maesstraat 20f Kontich Antwerpen 2550",
    "addr:housenumber":"20f",
    "addr:postcode":"2550",
    "addr:street":"Maesstraat",
    "iso:country":"BE",
    "sg:address":"Maesstraat 20f",
    "sg:city":"Kontich",
    "sg:orig_category":"Electrom\u00e9nager, t\u00e9l\u00e9visions and radios. R\u00e9parations d'appareils \u00e9lectrom\u00e9nagers",
    "sg:phone":"+32 15 31 18 65",
    "sg:postcode":"2550",
    "sg:province":"Antwerpen",
    "wof:name":"Doms Elektro",
    "wof:placetype":"venue"
},
  "geometry": {"coordinates":[4.4727702141,51.1256446838],"type":"Point"}
}