{
  "type": "Feature",
  "properties": {
    "iso:country":"BE",
    "sg:address":"Meire 10",
    "sg:city":"Zottegem",
    "sg:orig_category":"Journaux. Tabac",
    "sg:phone":"+32 9 360 06 96",
    "sg:postcode":"9620",
    "sg:province":"Oost-Vlaanderen",
    "wof:name":"Gillis",
    "wof:placetype":"venue"
},
  "geometry": {"coordinates":[3.807874918,50.8670158386],"type":"Point"}
}