{
  "type": "Feature",
  "properties": {
    "addr:full":"Kerkhofstraat 17 Zuienkerke (houtave) West-Vlaanderen 8377",
    "addr:housenumber":"17",
    "addr:postcode":"8377",
    "addr:street":"Kerkhofstraat",
    "iso:country":"BE",
    "sg:address":"Kerkhofstraat 17",
    "sg:city":"Zuienkerke (houtave)",
    "sg:classifiers":[
        {
            "category":"Bars & Pubs",
            "type":"Food & Drink"
        }
    ],
    "sg:phone":"+32 50 31 40 60",
    "sg:postcode":"8377",
    "sg:province":"West-Vlaanderen",
    "wof:name":"Drie Koningen",
    "wof:placetype":"venue"
},
  "geometry": {"coordinates":[3.1107060909,51.2358856201],"type":"Point"}
}