{
  "type": "Feature",
  "properties": {
    "iso:country":"BE",
    "sg:address":"Varenstraat 160",
    "sg:city":"Hemiksem",
    "sg:classifiers":[
        {
            "category":"Cafe",
            "type":"Food & Drink"
        }
    ],
    "sg:phone":"+32 3 887 55 97",
    "sg:postcode":"2620",
    "sg:province":"Antwerpen",
    "sg:tags":[
        "caf\u00e9s"
    ],
    "wof:name":"Caf\u00c9 Nachtvliegers",
    "wof:placetype":"venue"
},
  "geometry": {"coordinates":[4.3494381905,51.1499671936],"type":"Point"}
}