{
  "type": "Feature",
  "properties": {
    "addr:full":"Maststraat 2ba Essen Antwerpen 2910",
    "addr:housenumber":"2ba",
    "addr:postcode":"2910",
    "addr:street":"Maststraat",
    "iso:country":"BE",
    "sg:address":"Maststraat 2ba",
    "sg:city":"Essen",
    "sg:orig_category":"Enseignement maternel and primaire",
    "sg:phone":"+32 3 667 63 47",
    "sg:postcode":"2910",
    "sg:province":"Antwerpen",
    "wof:name":"Vrije Lagere School",
    "wof:placetype":"venue"
},
  "geometry": {"coordinates":[4.4457302094,51.4577598572],"type":"Point"}
}