{
  "type": "Feature",
  "properties": {
    "iso:country":"BE",
    "sg:address":"Rue Saint-antoine 8",
    "sg:city":"Aubel",
    "sg:orig_category":"V\u00e9t\u00e9rinaires",
    "sg:phone":"+32 87 68 84 82",
    "sg:postcode":"4880",
    "sg:province":"Li\u00e8ge",
    "wof:name":"Luc Archambeau",
    "wof:placetype":"venue"
},
  "geometry": {"coordinates":[5.861779213,50.701210022],"type":"Point"}
}