{
  "type": "Feature",
  "properties": {
    "iso:country":"BE",
    "sg:address":"Ooststraat 24",
    "sg:city":"Roeselare",
    "sg:orig_category":"Slagers",
    "sg:phone":"+32 51 20 04 12",
    "sg:postcode":"8800",
    "sg:province":"West-Vlaanderen",
    "wof:name":"Beenhouwerij Fernand",
    "wof:placetype":"venue"
},
  "geometry": {"coordinates":[3.1252849102,50.9460906982],"type":"Point"}
}