{
  "type": "Feature",
  "properties": {
    "addr:full":"Smallandln 23 Hoboken Antwerpen 2660",
    "addr:housenumber":"23",
    "addr:postcode":"2660",
    "addr:street":"Smallandln",
    "iso:country":"BE",
    "sg:address":"Smallandln 23",
    "sg:city":"Hoboken",
    "sg:classifiers":[
        {
            "category":"Manufacturing",
            "subcategory":"Metals",
            "type":"Manufacturing & Wholesale Goods"
        }
    ],
    "sg:phone":"+32 3 828 90 45",
    "sg:postcode":"2660",
    "sg:province":"Antwerpen",
    "sg:tags":[
        "metallurgy",
        "metalworking",
        "processing"
    ],
    "wof:name":"Lakkerij J & P De Groof Nv",
    "wof:placetype":"venue"
},
  "geometry": {"coordinates":[4.3381252289,51.1831588745],"type":"Point"}
}