{
  "type": "Feature",
  "properties": {
    "addr:full":"Rue De La Station 49 Dinant Namur 5500",
    "addr:housenumber":"49",
    "addr:postcode":"5500",
    "addr:street":"Rue De La Station",
    "iso:country":"BE",
    "sg:address":"Rue De La Station 49",
    "sg:city":"Dinant",
    "sg:classifiers":[
        {
            "category":"Bars & Pubs",
            "type":"Food & Drink"
        }
    ],
    "sg:phone":"+32 82 22 73 39",
    "sg:postcode":"5500",
    "sg:province":"Namur",
    "sg:tags":[
        "tavern"
    ],
    "wof:name":"Taverne Bailly (le)",
    "wof:placetype":"venue"
},
  "geometry": {"coordinates":[4.9087700844,50.2608299255],"type":"Point"}
}