{
  "type": "Feature",
  "properties": {
    "iso:country":"BE",
    "sg:address":"Menenstraat 57b1",
    "sg:city":"Wevelgem",
    "sg:orig_category":"Schoonmaakbedrijven and ongediertebestrijding",
    "sg:phone":"+32 56 40 27 55",
    "sg:postcode":"8560",
    "sg:province":"West-Vlaanderen",
    "wof:name":"Parmentier",
    "wof:placetype":"venue"
},
  "geometry": {"coordinates":[3.1764829159,50.8070335388],"type":"Point"}
}