{
  "type": "Feature",
  "properties": {
    "addr:full":"Kaasrui 12 Antwerpen Antwerpen 2000",
    "addr:housenumber":"12",
    "addr:postcode":"2000",
    "addr:street":"Kaasrui",
    "iso:country":"BE",
    "sg:address":"Kaasrui 12",
    "sg:city":"Antwerpen",
    "sg:classifiers":[
        {
            "category":"Shopping",
            "subcategory":"Clothing, Apparel, & Fashions",
            "type":"Retail Goods"
        }
    ],
    "sg:phone":"+32 3 232 94 51",
    "sg:postcode":"2000",
    "sg:province":"Antwerpen",
    "sg:tags":[
        "textile",
        "clothing",
        "clothes"
    ],
    "wof:name":"Festival Bvba",
    "wof:placetype":"venue"
},
  "geometry": {"coordinates":[4.4024481773,51.2209625244],"type":"Point"}
}