{
  "type": "Feature",
  "properties": {
    "iso:country":"BE",
    "sg:address":"Leeuwerikstraat 2",
    "sg:city":"Lier",
    "sg:orig_category":"Elektrische installaties voor woningen",
    "sg:phone":"+32 15 31 08 75",
    "sg:postcode":"2500",
    "sg:province":"Antwerpen",
    "wof:name":"Dirk De Ploey",
    "wof:placetype":"venue"
},
  "geometry": {"coordinates":[4.5100240707,51.1032867432],"type":"Point"}
}