{
  "type": "Feature",
  "properties": {
    "iso:country":"BE",
    "sg:address":"Rue De Biron 3",
    "sg:city":"Ciney",
    "sg:classifiers":[
        {
            "category":"Sports & Exercise",
            "subcategory":"Golf",
            "type":"Entertainment"
        }
    ],
    "sg:phone":"+32 83 21 64 80",
    "sg:postcode":"5590",
    "sg:province":"Namur",
    "sg:tags":[
        "speelgoed",
        "diver",
        "amusement"
    ],
    "wof:name":"Imperium",
    "wof:placetype":"venue"
},
  "geometry": {"coordinates":[5.1080369949,50.2943916321],"type":"Point"}
}