{
  "type": "Feature",
  "properties": {
    "iso:country":"BE",
    "sg:address":"Guido Gezellelaan 3",
    "sg:city":"Brugge",
    "sg:orig_category":"Notarissen",
    "sg:phone":"+32 50 33 29 24",
    "sg:postcode":"8000",
    "sg:province":"West-Vlaanderen",
    "wof:name":"Pierre Van Hove",
    "wof:placetype":"venue"
},
  "geometry": {"coordinates":[3.2134079933,51.2055511475],"type":"Point"}
}