{
  "type": "Feature",
  "properties": {
    "addr:full":"Herentsesteenweg 31 Leuven Vlaams-Brabant 3012",
    "addr:housenumber":"31",
    "addr:postcode":"3012",
    "addr:street":"Herentsesteenweg",
    "iso:country":"BE",
    "sg:address":"Herentsesteenweg 31",
    "sg:city":"Leuven",
    "sg:classifiers":[
        {
            "category":"Personal",
            "subcategory":"Beauty Salon",
            "type":"Services"
        }
    ],
    "sg:phone":"+32 16 23 35 84",
    "sg:postcode":"3012",
    "sg:province":"Vlaams-Brabant",
    "sg:tags":[
        "de",
        "coiffure"
    ],
    "wof:name":"Coiffure Nicky",
    "wof:placetype":"venue"
},
  "geometry": {"coordinates":[4.6970090866,50.9034461975],"type":"Point"}
}