{
  "type": "Feature",
  "properties": {
    "addr:full":"Lakense Laan 8 Jette Bruxelles-Capitale 1090",
    "addr:housenumber":"8",
    "addr:postcode":"1090",
    "addr:street":"Laan",
    "iso:country":"BE",
    "sg:address":"Lakense Laan 8",
    "sg:city":"Jette",
    "sg:orig_category":"Groenten and fruit Gh",
    "sg:phone":"+32 2 426 65 85",
    "sg:postcode":"1090",
    "sg:province":"Bruxelles-Capitale",
    "wof:name":"Liman",
    "wof:placetype":"venue"
},
  "geometry": {"coordinates":[4.3255710602,50.87159729],"type":"Point"}
}