{
  "type": "Feature",
  "properties": {
    "addr:full":"Stoktevijver 21bb Zomergem Oost-Vlaanderen 9932",
    "addr:housenumber":"21bb",
    "addr:postcode":"9932",
    "addr:street":"Stoktevijver",
    "iso:country":"BE",
    "sg:address":"Stoktevijver 21bb",
    "sg:city":"Zomergem",
    "sg:orig_category":"Enseignement maternel and primaire",
    "sg:phone":"+32 9 372 55 45",
    "sg:postcode":"9932",
    "sg:province":"Oost-Vlaanderen",
    "wof:name":"Vrije Kleuterschool",
    "wof:placetype":"venue"
},
  "geometry": {"coordinates":[3.5610280037,51.1311149597],"type":"Point"}
}