{
  "type": "Feature",
  "properties": {
    "iso:country":"BE",
    "sg:address":"Berkenlaan 48",
    "sg:city":"Antwerpen",
    "sg:orig_category":"Activit\u00e9s diverses d'imprimerie",
    "sg:phone":"+32 3 825 57 62",
    "sg:postcode":"2610",
    "sg:province":"Antwerpen",
    "wof:name":"Bureau Art & Directions",
    "wof:placetype":"venue"
},
  "geometry": {"coordinates":[4.3944020271,51.1829833984],"type":"Point"}
}