{
  "type": "Feature",
  "properties": {
    "addr:full":"Kriekerijstraat 7 Gent (sint-amandsberg) Oost-Vlaanderen 9040",
    "addr:housenumber":"7",
    "addr:postcode":"9040",
    "addr:street":"Kriekerijstraat",
    "iso:country":"BE",
    "sg:address":"Kriekerijstraat 7",
    "sg:city":"Gent (sint-amandsberg)",
    "sg:classifiers":[
        {
            "category":"Health Services",
            "subcategory":"Health Practitioner",
            "type":"Services"
        }
    ],
    "sg:phone":"+32 9 228 91 58",
    "sg:postcode":"9040",
    "sg:province":"Oost-Vlaanderen",
    "sg:tags":[
        "physiotherapist"
    ],
    "wof:name":"Van Damme V\u00e9ronique",
    "wof:placetype":"venue"
},
  "geometry": {"coordinates":[3.7545769215,51.057258606],"type":"Point"}
}