{
  "type": "Feature",
  "properties": {
    "addr:full":"Rue St Jozef 3 Ath Hainaut 7811",
    "addr:housenumber":"3",
    "addr:postcode":"7811",
    "addr:street":"Rue St Jozef",
    "iso:country":"BE",
    "sg:address":"Rue St Jozef 3",
    "sg:city":"Ath",
    "sg:orig_category":"Installatie van houten of kunststof schrijnwerk",
    "sg:phone":"+32 68 65 85 88",
    "sg:postcode":"7811",
    "sg:province":"Hainaut",
    "wof:name":"Lva",
    "wof:placetype":"venue"
},
  "geometry": {"coordinates":[3.8159689903,50.6116752625],"type":"Point"}
}