{
  "type": "Feature",
  "properties": {
    "addr:full":"Les Floxhes 16 Anthisnes Li\u00e8ge 4160",
    "addr:housenumber":"16",
    "addr:postcode":"4160",
    "addr:street":"Floxhes",
    "iso:country":"BE",
    "sg:address":"Les Floxhes 16",
    "sg:city":"Anthisnes",
    "sg:orig_category":"D\u00e9molition d\u00b4immeubles and terrassements. Charpentes and couvertures",
    "sg:phone":"+32 4 383 62 06",
    "sg:postcode":"4160",
    "sg:province":"Li\u00e8ge",
    "wof:name":"Michel Lansival",
    "wof:placetype":"venue"
},
  "geometry": {"coordinates":[5.4931721687,50.46824646],"type":"Point"}
}