{
  "type": "Feature",
  "properties": {
    "addr:full":"Kwikstaartlaan 49 Gent (wondelgem) Oost-Vlaanderen 9032",
    "addr:housenumber":"49",
    "addr:postcode":"9032",
    "addr:street":"Kwikstaartlaan",
    "iso:country":"BE",
    "sg:address":"Kwikstaartlaan 49",
    "sg:city":"Gent (wondelgem)",
    "sg:classifiers":[
        {
            "category":"Personal",
            "subcategory":"Beauty Salon",
            "type":"Services"
        }
    ],
    "sg:phone":"+32 9 253 81 94",
    "sg:postcode":"9032",
    "sg:province":"Oost-Vlaanderen",
    "sg:tags":[
        "lady",
        "-",
        "hairdressing"
    ],
    "wof:name":"Versailles (salon)",
    "wof:placetype":"venue"
},
  "geometry": {"coordinates":[3.7162549496,51.0900535583],"type":"Point"}
}