{
  "type": "Feature",
  "properties": {
    "iso:country":"BE",
    "sg:address":"Rue De Plainevaux 39",
    "sg:city":"Seraing",
    "sg:classifiers":[
        {
            "category":"Bars & Pubs",
            "type":"Food & Drink"
        }
    ],
    "sg:phone":"+32 4 336 11 95",
    "sg:postcode":"4100",
    "sg:province":"Li\u00e8ge",
    "wof:name":"Plainevaux (le)",
    "wof:placetype":"venue"
},
  "geometry": {"coordinates":[5.5067820549,50.5850944519],"type":"Point"}
}