{
  "type": "Feature",
  "properties": {
    "iso:country":"BE",
    "sg:address":"Rue Des Archers 45",
    "sg:city":"Mons",
    "sg:classifiers":[
        {
            "category":"Wholesale",
            "subcategory":"Fruits & Vegetables",
            "type":"Manufacturing & Wholesale Goods"
        }
    ],
    "sg:phone":"+32 65 31 84 12",
    "sg:postcode":"7000",
    "sg:province":"Hainaut",
    "sg:tags":[
        "whol",
        "-"
    ],
    "wof:name":"Op De Beeck L",
    "wof:placetype":"venue"
},
  "geometry": {"coordinates":[3.9567520618,50.4512443542],"type":"Point"}
}