{
  "type": "Feature",
  "properties": {
    "addr:full":"Rue Emile Cornez 20 Honnelles Hainaut 7387",
    "addr:housenumber":"20",
    "addr:postcode":"7387",
    "addr:street":"Rue Emile Cornez;Hainaut",
    "iso:country":"BE",
    "sg:address":"Rue Emile Cornez 20",
    "sg:city":"Honnelles",
    "sg:orig_category":"Catering and organisatie van feesten Fast food and meeneem restaurants Restaurants",
    "sg:phone":"+32 65 75 04 55",
    "sg:postcode":"7387",
    "sg:province":"Hainaut",
    "wof:name":"Les Gribaumonts",
    "wof:placetype":"venue"
},
  "geometry": {"coordinates":[3.6985011101,50.3696327209],"type":"Point"}
}