{
  "type": "Feature",
  "properties": {
    "iso:country":"BE",
    "sg:address":"Rue Raide Vall\u00e9e 138",
    "sg:city":"Wanze (moha)",
    "sg:classifiers":[
        {
            "category":"Health Services",
            "subcategory":"Doctor",
            "type":"Services"
        }
    ],
    "sg:phone":"+32 85 21 22 28",
    "sg:postcode":"4520",
    "sg:province":"Li\u00e8ge",
    "sg:tags":[
        "medicinephysicians",
        "surgeon"
    ],
    "wof:name":"Jadot Armand",
    "wof:placetype":"venue"
},
  "geometry": {"coordinates":[5.1793460846,50.5496139526],"type":"Point"}
}