{
  "type": "Feature",
  "properties": {
    "addr:full":"Pr. Thuysbaertlaan 10 Lokeren Oost-Vlaanderen 9160",
    "addr:housenumber":"10",
    "addr:postcode":"9160",
    "addr:street":"Thuysbaertlaan",
    "iso:country":"BE",
    "sg:address":"Pr. Thuysbaertlaan 10",
    "sg:city":"Lokeren",
    "sg:orig_category":"Bloemen and planten",
    "sg:phone":"+32 9 348 05 53",
    "sg:postcode":"9160",
    "sg:province":"Oost-Vlaanderen",
    "wof:name":"Van Hoven En Heiligen",
    "wof:placetype":"venue"
},
  "geometry": {"coordinates":[3.9892609119,51.1061172485],"type":"Point"}
}