{
  "type": "Feature",
  "properties": {
    "addr:full":"Weststraat 3 Oudenburg West-Vlaanderen 8460",
    "addr:housenumber":"3",
    "addr:postcode":"8460",
    "addr:street":"Weststraat",
    "iso:country":"BE",
    "sg:address":"Weststraat 3",
    "sg:city":"Oudenburg",
    "sg:classifiers":[
        {
            "category":"Insurance",
            "subcategory":"Insurance Agent",
            "type":"Services"
        }
    ],
    "sg:phone":"+32 59 26 52 14",
    "sg:postcode":"8460",
    "sg:province":"West-Vlaanderen",
    "sg:tags":[
        "verzekeringsmakelaars",
        "expert"
    ],
    "wof:name":"T. Acke",
    "wof:placetype":"venue"
},
  "geometry": {"coordinates":[3.0035200119,51.182636261],"type":"Point"}
}