{
  "type": "Feature",
  "properties": {
    "iso:country":"BE",
    "sg:address":"Heesakkerstraat 99",
    "sg:city":"Overpelt",
    "sg:orig_category":"Elektrische installaties voor woningen",
    "sg:phone":"+32 11 64 88 17",
    "sg:postcode":"3900",
    "sg:province":"Limburg",
    "wof:name":"Jozef Fransen",
    "wof:placetype":"venue"
},
  "geometry": {"coordinates":[5.4363460541,51.2042121887],"type":"Point"}
}