{
  "type": "Feature",
  "properties": {
    "addr:full":"Predikherenstraat 17 Wingene West-Vlaanderen 8750",
    "addr:housenumber":"17",
    "addr:postcode":"8750",
    "addr:street":"Predikherenstraat",
    "iso:country":"BE",
    "sg:address":"Predikherenstraat 17",
    "sg:city":"Wingene",
    "sg:orig_category":"Eleveurs and marchands de porcs. Eleveurs de bovins. Eleveurs de volaille",
    "sg:phone":"+32 51 65 56 85",
    "sg:postcode":"8750",
    "sg:province":"West-Vlaanderen",
    "wof:name":"Camiel De Bel",
    "wof:placetype":"venue"
},
  "geometry": {"coordinates":[3.3154489994,51.0712203979],"type":"Point"}
}