{
  "type": "Feature",
  "properties": {
    "addr:full":"Westerlaan 9 Waregem West-Vlaanderen 8790",
    "addr:housenumber":"9",
    "addr:postcode":"8790",
    "addr:street":"Westerlaan",
    "iso:country":"BE",
    "sg:address":"Westerlaan 9",
    "sg:city":"Waregem",
    "sg:classifiers":[
        {
            "category":"Fast Food",
            "type":"Food & Drink"
        }
    ],
    "sg:phone":"+32 56 61 53 63",
    "sg:postcode":"8790",
    "sg:province":"West-Vlaanderen",
    "sg:tags":[
        "\u00c0",
        "emporter",
        "restaurants"
    ],
    "wof:name":"Frituur Eric",
    "wof:placetype":"venue"
},
  "geometry": {"coordinates":[3.4241518974,50.8839530945],"type":"Point"}
}