{
  "type": "Feature",
  "properties": {
    "iso:country":"BE",
    "sg:address":"Mechelsesteenweg 99",
    "sg:city":"Kampenhout (groot)",
    "sg:classifiers":[
        {
            "category":"Manufacturing",
            "subcategory":"Textiles",
            "type":"Manufacturing & Wholesale Goods"
        }
    ],
    "sg:phone":"+32 16 60 64 77",
    "sg:postcode":"1910",
    "sg:province":"Vlaams-Brabant",
    "wof:name":"Limbutex",
    "wof:placetype":"venue"
},
  "geometry": {"coordinates":[4.5831270218,50.9617843628],"type":"Point"}
}