{
  "type": "Feature",
  "properties": {
    "iso:country":"BE",
    "sg:address":"Avenue Eug\u00e8ne Demolder 65",
    "sg:city":"Bruxelles (schaerbeek)",
    "sg:classifiers":[
        {
            "category":"Real Estate",
            "subcategory":"Surveying",
            "type":"Services"
        }
    ],
    "sg:phone":"+32 2 241 15 00",
    "sg:postcode":"1030",
    "sg:province":"Bruxelles-Capitale",
    "sg:tags":[
        "lettering",
        "letter"
    ],
    "wof:name":"Bo\u00eete \u00e0 Lettres (la)",
    "wof:placetype":"venue"
},
  "geometry": {"coordinates":[4.3790011406,50.8721199036],"type":"Point"}
}