{
  "type": "Feature",
  "properties": {
    "iso:country":"BE",
    "sg:address":"Kwaadham 99",
    "sg:city":"Gent",
    "sg:classifiers":[
        {
            "category":"Professional",
            "subcategory":"Art Services",
            "type":"Services"
        }
    ],
    "sg:phone":"+32 9 233 61 13",
    "sg:postcode":"9000",
    "sg:province":"Oost-Vlaanderen",
    "sg:tags":[
        "graphic",
        "designer"
    ],
    "wof:name":"Everaert",
    "wof:placetype":"venue"
},
  "geometry": {"coordinates":[3.7291529179,51.0545120239],"type":"Point"}
}