{
  "type": "Feature",
  "properties": {
    "iso:country":"BE",
    "sg:address":"Brugsebaan 16",
    "sg:city":"Gistel",
    "sg:classifiers":[
        {
            "category":"Bakery",
            "type":"Food & Drink"
        }
    ],
    "sg:phone":"+32 59 27 80 36",
    "sg:postcode":"8470",
    "sg:province":"West-Vlaanderen",
    "sg:tags":[
        "confectioner",
        "baker"
    ],
    "wof:name":"Hesta",
    "wof:placetype":"venue"
},
  "geometry": {"coordinates":[2.9759380817,51.1569862366],"type":"Point"}
}