{
  "type": "Feature",
  "properties": {
    "iso:country":"BE",
    "sg:address":"Rue Lison 176",
    "sg:city":"Charleroi",
    "sg:orig_category":"R\u00e9parations de chaussures and articles en cuir",
    "sg:phone":"+32 71 38 30 92",
    "sg:postcode":"6060",
    "sg:province":"Hainaut",
    "wof:name":"Thierry Vandervelde",
    "wof:placetype":"venue"
},
  "geometry": {"coordinates":[4.4880981445,50.4251937866],"type":"Point"}
}