{
  "type": "Feature",
  "properties": {
    "addr:full":"Achelmansstraat 65 Peer (wijchmaal) Limburg 3990",
    "addr:housenumber":"65",
    "addr:postcode":"3990",
    "addr:street":"Achelmansstraat",
    "iso:country":"BE",
    "sg:address":"Achelmansstraat 65",
    "sg:city":"Peer (wijchmaal)",
    "sg:classifiers":[
        {
            "category":"Building & Trades",
            "subcategory":"Landscaping Services",
            "type":"Services"
        }
    ],
    "sg:phone":"+32 11 63 28 42",
    "sg:postcode":"3990",
    "sg:province":"Limburg",
    "sg:tags":[
        "architect",
        "landscape"
    ],
    "wof:name":"Prenten G",
    "wof:placetype":"venue"
},
  "geometry": {"coordinates":[5.4533009529,51.1329536438],"type":"Point"}
}