{
  "type": "Feature",
  "properties": {
    "addr:full":"Cicindriastraat Sint-truiden Limburg 3800",
    "addr:postcode":"3800",
    "addr:street":"Cicindriastraat",
    "iso:country":"BE",
    "sg:address":"Cicindriastraat",
    "sg:city":"Sint-truiden",
    "sg:classifiers":[
        {
            "category":"Banks & Credit Unions",
            "subcategory":"Investment Brokerage",
            "type":"Services"
        }
    ],
    "sg:phone":"+32 11 68 18 76",
    "sg:postcode":"3800",
    "sg:province":"Limburg",
    "sg:tags":[
        "jean",
        "casual",
        "wear"
    ],
    "wof:name":"Sany Jeans & Shoes",
    "wof:placetype":"venue"
},
  "geometry": {"coordinates":[5.1861109734,50.8181648254],"type":"Point"}
}