{
  "type": "Feature",
  "properties": {
    "iso:country":"BE",
    "sg:address":"Beertegemstraat 89",
    "sg:city":"Zingem (ouwegem)",
    "sg:classifiers":[
        {
            "category":"Building & Trades",
            "subcategory":"Construction",
            "type":"Services"
        }
    ],
    "sg:phone":"+32 9 384 48 06",
    "sg:postcode":"9750",
    "sg:province":"Oost-Vlaanderen",
    "sg:tags":[
        "carpenter"
    ],
    "wof:name":"Holluyn R",
    "wof:placetype":"venue"
},
  "geometry": {"coordinates":[3.6519870758,50.9060554504],"type":"Point"}
}