{
  "type": "Feature",
  "properties": {
    "iso:country":"BE",
    "sg:address":"Aspot 41",
    "sg:city":"Puurs",
    "sg:orig_category":"Groententeelt",
    "sg:phone":"+32 3 889 39 38",
    "sg:postcode":"2870",
    "sg:province":"Antwerpen",
    "wof:name":"Denis Daelemans",
    "wof:placetype":"venue"
},
  "geometry": {"coordinates":[4.30458498,51.0605125427],"type":"Point"}
}