{
  "type": "Feature",
  "properties": {
    "addr:full":"Westendelaan 302 Middelkerke West-Vlaanderen 8434",
    "addr:housenumber":"302",
    "addr:postcode":"8434",
    "addr:street":"Westendelaan",
    "iso:country":"BE",
    "sg:address":"Westendelaan 302",
    "sg:city":"Middelkerke",
    "sg:orig_category":"Cr\u00e9dits divers",
    "sg:postcode":"8434",
    "sg:province":"West-Vlaanderen",
    "wof:name":"Bancontact-mister Cash",
    "wof:placetype":"venue"
},
  "geometry": {"coordinates":[2.7558889389,51.1391983032],"type":"Point"}
}