{
  "type": "Feature",
  "properties": {
    "iso:country":"BE",
    "sg:address":"Westendelaan 302",
    "sg:city":"Middelkerke",
    "sg:orig_category":"Cr\u00e9dits divers",
    "sg:postcode":"8434",
    "sg:province":"West-Vlaanderen",
    "wof:name":"Bancontact-mister Cash",
    "wof:placetype":"venue"
},
  "geometry": {"coordinates":[2.7558889389,51.1391983032],"type":"Point"}
}