{
  "type": "Feature",
  "properties": {
    "addr:full":"Reyenstraat 7 Overpelt Limburg 3900",
    "addr:housenumber":"7",
    "addr:postcode":"3900",
    "addr:street":"Reyenstraat",
    "iso:country":"BE",
    "sg:address":"Reyenstraat 7",
    "sg:city":"Overpelt",
    "sg:orig_category":"Sportclubs",
    "sg:phone":"+32 11 64 13 35",
    "sg:postcode":"3900",
    "sg:province":"Limburg",
    "wof:name":"W.c. De Kranige Durvers",
    "wof:placetype":"venue"
},
  "geometry": {"coordinates":[5.4013447762,51.1942901611],"type":"Point"}
}