{
  "type": "Feature",
  "properties": {
    "addr:full":"Schoolstraat 3 Deinze (vinkt) Oost-Vlaanderen 9800",
    "addr:housenumber":"3",
    "addr:postcode":"9800",
    "addr:street":"Schoolstraat",
    "iso:country":"BE",
    "sg:address":"Schoolstraat 3",
    "sg:city":"Deinze (vinkt)",
    "sg:classifiers":[
        {
            "category":"Banks & Credit Unions",
            "subcategory":"Bank",
            "type":"Services"
        }
    ],
    "sg:phone":"+32 9 380 39 25",
    "sg:postcode":"9800",
    "sg:province":"Oost-Vlaanderen",
    "sg:tags":[
        "savings-banks"
    ],
    "wof:name":"Balcaen T Eural Spaarbank",
    "wof:placetype":"venue"
},
  "geometry": {"coordinates":[3.4780819416,51.0088768005],"type":"Point"}
}