{
  "type": "Feature",
  "properties": {
    "addr:full":"Slijkensesteenweg 11 Oostende West-Vlaanderen 8400",
    "addr:housenumber":"11",
    "addr:postcode":"8400",
    "addr:street":"Slijkensesteenweg",
    "iso:country":"BE",
    "sg:address":"Slijkensesteenweg 11",
    "sg:city":"Oostende",
    "sg:orig_category":"Benzinestations and brandstoffen",
    "sg:phone":"+32 59 32 14 00",
    "sg:postcode":"8400",
    "sg:province":"West-Vlaanderen",
    "wof:name":"Jet",
    "wof:placetype":"venue"
},
  "geometry": {"coordinates":[2.9386310577,51.223110199],"type":"Point"}
}