{
  "type": "Feature",
  "properties": {
    "addr:full":"Skaldenstraat 1 Oostakker Oost-Vlaanderen 9042",
    "addr:housenumber":"1",
    "addr:postcode":"9042",
    "addr:street":"Skaldenstraat",
    "iso:country":"BE",
    "sg:address":"Skaldenstraat 1",
    "sg:city":"Oostakker",
    "sg:classifiers":[
        {
            "category":"Professional",
            "type":"Services"
        }
    ],
    "sg:phone":"+32 9 251 33 44",
    "sg:postcode":"9042",
    "sg:province":"Oost-Vlaanderen",
    "sg:tags":[
        "transport",
        "road"
    ],
    "wof:name":"Sogatra Nv",
    "wof:placetype":"venue"
},
  "geometry": {"coordinates":[3.7816700935,51.1223831177],"type":"Point"}
}