{
  "type": "Feature",
  "properties": {
    "iso:country":"BE",
    "sg:address":"H. Hartlaan 26",
    "sg:city":"Tessenderlo",
    "sg:classifiers":[
        {
            "category":"Home & Garden",
            "subcategory":"Household Appliances",
            "type":"Retail Goods"
        }
    ],
    "sg:phone":"+32 13 67 23 08",
    "sg:postcode":"3980",
    "sg:province":"Limburg",
    "sg:tags":[
        "heater",
        "industrial",
        "electric",
        "us"
    ],
    "wof:name":"Bartec Belgium Nv",
    "wof:placetype":"venue"
},
  "geometry": {"coordinates":[5.0924577713,51.0571212769],"type":"Point"}
}