{
  "type": "Feature",
  "properties": {
    "iso:country":"BE",
    "sg:address":"Pladutsestraat 4",
    "sg:city":"Kluisbergen",
    "sg:orig_category":"Rundveehouders",
    "sg:phone":"+32 55 38 83 26",
    "sg:postcode":"9690",
    "sg:province":"Oost-Vlaanderen",
    "wof:name":"Gerard Depourcq",
    "wof:placetype":"venue"
},
  "geometry": {"coordinates":[3.5704679489,50.7924003601],"type":"Point"}
}