{
  "type": "Feature",
  "properties": {
    "addr:full":"Rue Albert Ier 222 Erquelinnes Hainaut 6560",
    "addr:housenumber":"222",
    "addr:postcode":"6560",
    "addr:street":"Rue Albert Ier",
    "iso:country":"BE",
    "sg:address":"Rue Albert Ier 222",
    "sg:city":"Erquelinnes",
    "sg:classifiers":[
        {
            "category":"Shopping",
            "subcategory":"Clothing, Apparel, & Fashions",
            "type":"Retail Goods"
        }
    ],
    "sg:phone":"+32 71 55 63 29",
    "sg:postcode":"6560",
    "sg:province":"Hainaut",
    "sg:tags":[
        "ondergoed",
        "lingerie"
    ],
    "wof:name":"Maison Corsouple",
    "wof:placetype":"venue"
},
  "geometry": {"coordinates":[4.1158652306,50.3064193726],"type":"Point"}
}