{
  "type": "Feature",
  "properties": {
    "iso:country":"BE",
    "sg:address":"Kerkstraat 32",
    "sg:city":"Hooglede",
    "sg:orig_category":"Producteurs de l\u00e9gumes",
    "sg:phone":"+32 51 20 58 83",
    "sg:postcode":"8830",
    "sg:province":"West-Vlaanderen",
    "wof:name":"Marc Buyse",
    "wof:placetype":"venue"
},
  "geometry": {"coordinates":[3.0822250843,50.9842224121],"type":"Point"}
}