{
  "type": "Feature",
  "properties": {
    "addr:full":"Blanchestraat 26 Sint-gillis/saint-gilles Bruxelles-Capitale 1060",
    "addr:housenumber":"26",
    "addr:postcode":"1060",
    "addr:street":"Blanchestraat",
    "iso:country":"BE",
    "sg:address":"Blanchestraat 26",
    "sg:city":"Sint-gillis/saint-gilles",
    "sg:orig_category":"Artiesten and kunstenaars",
    "sg:phone":"+32 2 537 92 11",
    "sg:postcode":"1060",
    "sg:province":"Bruxelles-Capitale",
    "wof:name":"Levy Morelle",
    "wof:placetype":"venue"
},
  "geometry": {"coordinates":[4.3580307961,50.8299217224],"type":"Point"}
}