{
  "type": "Feature",
  "properties": {
    "iso:country":"BE",
    "sg:address":"Rue Des Paons 22",
    "sg:city":"Oudergem/auderghem",
    "sg:orig_category":"Agences de presse",
    "sg:phone":"+32 2 662 28 94",
    "sg:postcode":"1160",
    "sg:province":"Bruxelles-Capitale",
    "wof:name":"Jean-fran\u00c7ois Lauwers",
    "wof:placetype":"venue"
},
  "geometry": {"coordinates":[4.4184961319,50.8196983337],"type":"Point"}
}