{
  "type": "Feature",
  "properties": {
    "iso:country":"BE",
    "sg:address":"Rue De Bernifa 23a",
    "sg:city":"Bertrix (jehonville)",
    "sg:classifiers":[
        {
            "category":"Arts & Performance",
            "subcategory":"Symphony",
            "type":"Entertainment"
        }
    ],
    "sg:phone":"+32 61 53 50 38",
    "sg:postcode":"6880",
    "sg:province":"Luxembourg",
    "sg:tags":[
        "orchestra"
    ],
    "wof:name":"Blue Night",
    "wof:placetype":"venue"
},
  "geometry": {"coordinates":[5.2535948753,49.8544845581],"type":"Point"}
}