{
  "type": "Feature",
  "properties": {
    "iso:country":"BE",
    "sg:address":"Rue De Forri\u00e8re 182",
    "sg:city":"Courcelles",
    "sg:classifiers":[
        {
            "category":"Professional",
            "subcategory":"Testing Lab",
            "type":"Services"
        }
    ],
    "sg:phone":"+32 71 45 00 41",
    "sg:postcode":"6180",
    "sg:province":"Hainaut",
    "sg:tags":[
        "chemist"
    ],
    "wof:name":"Feron V",
    "wof:placetype":"venue"
},
  "geometry": {"coordinates":[4.3618559837,50.4465637207],"type":"Point"}
}