{
  "type": "Feature",
  "properties": {
    "addr:full":"Rue Roosendael 113 Bruxelles (forest) Bruxelles-Capitale 1190",
    "addr:housenumber":"113",
    "addr:postcode":"1190",
    "addr:street":"Rue Roosendael",
    "iso:country":"BE",
    "sg:address":"Rue Roosendael 113",
    "sg:city":"Bruxelles (forest)",
    "sg:classifiers":[
        {
            "category":"Health Services",
            "subcategory":"Health Practitioner",
            "type":"Services"
        }
    ],
    "sg:phone":"+32 2 344 55 62",
    "sg:postcode":"1190",
    "sg:province":"Bruxelles-Capitale",
    "sg:tags":[
        "physiotherapist"
    ],
    "wof:name":"Bettens Y",
    "wof:placetype":"venue"
},
  "geometry": {"coordinates":[4.3319559097,50.808555603],"type":"Point"}
}