{
  "type": "Feature",
  "properties": {
    "addr:full":"Chauss\u00e9e De Ninove 403 Bruxelles (anderlecht) Bruxelles-Capitale 1070",
    "addr:housenumber":"403",
    "addr:postcode":"1070",
    "addr:street":"Chausse\u0301E De Ninove",
    "iso:country":"BE",
    "sg:address":"Chauss\u00e9e De Ninove 403",
    "sg:city":"Bruxelles (anderlecht)",
    "sg:classifiers":[
        {
            "category":"Personal",
            "subcategory":"Barber",
            "type":"Services"
        }
    ],
    "sg:phone":"+32 2 411 00 19",
    "sg:postcode":"1070",
    "sg:province":"Bruxelles-Capitale",
    "sg:tags":[
        "gentleman",
        "salon",
        "-",
        "hairdressing"
    ],
    "wof:name":"Hair-coiff'",
    "wof:placetype":"venue"
},
  "geometry": {"coordinates":[4.3097681999,50.8479690552],"type":"Point"}
}