{
  "type": "Feature",
  "properties": {
    "addr:full":"Meerstraat 7 Bornem Antwerpen 2880",
    "addr:housenumber":"7",
    "addr:postcode":"2880",
    "addr:street":"Meerstraat",
    "iso:country":"BE",
    "sg:address":"Meerstraat 7",
    "sg:city":"Bornem",
    "sg:orig_category":"Landmeters",
    "sg:phone":"+32 52 33 81 49",
    "sg:postcode":"2880",
    "sg:province":"Antwerpen",
    "wof:name":"Eric Cuyt",
    "wof:placetype":"venue"
},
  "geometry": {"coordinates":[4.2092437744,51.0640029907],"type":"Point"}
}