{
  "type": "Feature",
  "properties": {
    "addr:full":"Vissersstraat 51 Oudenburg West-Vlaanderen 8460",
    "addr:housenumber":"51",
    "addr:postcode":"8460",
    "addr:street":"Vissersstraat",
    "iso:country":"BE",
    "sg:address":"Vissersstraat 51",
    "sg:city":"Oudenburg",
    "sg:orig_category":"Verhuur textielartikelen and schoenen",
    "sg:phone":"+32 59 26 65 86",
    "sg:postcode":"8460",
    "sg:province":"West-Vlaanderen",
    "wof:name":"Karnavalshop",
    "wof:placetype":"venue"
},
  "geometry": {"coordinates":[3.0008978844,51.1902999878],"type":"Point"}
}