{
  "type": "Feature",
  "properties": {
    "iso:country":"BE",
    "sg:address":"Wijgmaalsesteenweg 30",
    "sg:city":"Leuven",
    "sg:orig_category":"Herstellingen and onderhoud van auto's",
    "sg:phone":"+32 16 29 62 96",
    "sg:postcode":"3012",
    "sg:province":"Vlaams-Brabant",
    "wof:name":"Garage Eric",
    "wof:placetype":"venue"
},
  "geometry": {"coordinates":[4.7073988914,50.9064788818],"type":"Point"}
}