{
  "type": "Feature",
  "properties": {
    "iso:country":"BE",
    "sg:address":"Oudenaardsesteenweg 20",
    "sg:city":"Avelgem",
    "sg:classifiers":[
        {
            "category":"Education",
            "subcategory":"School",
            "type":"Public Place"
        }
    ],
    "sg:phone":"+32 56 65 01 11",
    "sg:postcode":"8580",
    "sg:province":"West-Vlaanderen",
    "sg:tags":[
        "secondary"
    ],
    "wof:name":"Middenschool Van Het Gemeenschapsonderwijs",
    "wof:placetype":"venue"
},
  "geometry": {"coordinates":[3.4463400841,50.7770118713],"type":"Point"}
}