{
  "type": "Feature",
  "properties": {
    "iso:country":"BE",
    "sg:address":"146 Rue J Leclercq",
    "sg:city":"Beyne-heusay",
    "sg:classifiers":[
        {
            "category":"Manufacturing",
            "subcategory":"Rubber & Plastics",
            "type":"Manufacturing & Wholesale Goods"
        }
    ],
    "sg:phone":"+32 4 358 79 87",
    "sg:postcode":"4610",
    "sg:province":"Li\u00e8ge",
    "wof:name":"Plastiqual Sa",
    "wof:placetype":"venue"
},
  "geometry": {"coordinates":[5.6668901443,50.6259155273],"type":"Point"}
}