{
  "type": "Feature",
  "properties": {
    "iso:country":"BE",
    "sg:address":"Rue Du Zodiaque 27",
    "sg:city":"Bruxelles (forest)",
    "sg:classifiers":[
        {
            "category":"Health Services",
            "subcategory":"Nursing And Care Facility",
            "type":"Services"
        }
    ],
    "sg:phone":"+32 2 344 11 39",
    "sg:postcode":"1190",
    "sg:province":"Bruxelles-Capitale",
    "sg:tags":[
        "home",
        "rest"
    ],
    "wof:name":"R\u00e9sidence Zodiaque",
    "wof:placetype":"venue"
},
  "geometry": {"coordinates":[4.3446722031,50.8172988892],"type":"Point"}
}