{
  "type": "Feature",
  "properties": {
    "iso:country":"BE",
    "sg:address":"Wippelberg 105",
    "sg:city":"Arendonk",
    "sg:orig_category":"Woningbouw",
    "sg:phone":"+32 14 67 97 11",
    "sg:postcode":"2370",
    "sg:province":"Antwerpen",
    "wof:name":"Chappy Algemeen Bouwbedrijf",
    "wof:placetype":"venue"
},
  "geometry": {"coordinates":[5.1006379128,51.3199386597],"type":"Point"}
}