{
  "type": "Feature",
  "properties": {
    "iso:country":"BE",
    "sg:address":"Steenstraat 34a",
    "sg:city":"Erpe-mere (mere)",
    "sg:classifiers":[
        {
            "category":"Personal",
            "subcategory":"Beauty Salon",
            "type":"Services"
        }
    ],
    "sg:phone":"+32 53 83 85 95",
    "sg:postcode":"9420",
    "sg:province":"Oost-Vlaanderen",
    "sg:tags":[
        "lady",
        "-",
        "hairdressing"
    ],
    "wof:name":"Ilja",
    "wof:placetype":"venue"
},
  "geometry": {"coordinates":[3.9690890312,50.9208526611],"type":"Point"}
}