{
  "type": "Feature",
  "properties": {
    "iso:country":"BE",
    "sg:address":"Deken Darraslaan 39",
    "sg:city":"Tielt",
    "sg:classifiers":[
        {
            "category":"Building & Trades",
            "subcategory":"Cleaning & Sanitation",
            "type":"Services"
        }
    ],
    "sg:phone":"+32 51 40 63 15",
    "sg:postcode":"8700",
    "sg:province":"West-Vlaanderen",
    "sg:tags":[
        "sweep",
        "chimney"
    ],
    "wof:name":"Nemegheer Bvba",
    "wof:placetype":"venue"
},
  "geometry": {"coordinates":[3.3166019917,50.9980392456],"type":"Point"}
}