{
  "type": "Feature",
  "properties": {
    "addr:full":"Waverse Steenweg 1400 Oudergem/auderghem Bruxelles-Capitale 1160",
    "addr:postcode":"1400;1160",
    "addr:street":"Waverse Steenweg",
    "iso:country":"BE",
    "sg:address":"Waverse Steenweg 1400",
    "sg:city":"Oudergem/auderghem",
    "sg:orig_category":"Herstellingen and onderhoud van auto's Voertuigen",
    "sg:phone":"+32 2 673 34 36",
    "sg:postcode":"1160",
    "sg:province":"Bruxelles-Capitale",
    "wof:name":"Mecatecnic",
    "wof:placetype":"venue"
},
  "geometry": {"coordinates":[4.4152851105,50.819026947],"type":"Point"}
}