{
  "type": "Feature",
  "properties": {
    "addr:full":"Lindeplein 15a Mol Antwerpen 2400",
    "addr:housenumber":"15a",
    "addr:postcode":"2400",
    "addr:street":"Lindeplein",
    "iso:country":"BE",
    "sg:address":"Lindeplein 15a",
    "sg:city":"Mol",
    "sg:classifiers":[
        {
            "category":"Bars & Pubs",
            "type":"Food & Drink"
        }
    ],
    "sg:phone":"+32 14 31 40 09",
    "sg:postcode":"2400",
    "sg:province":"Antwerpen",
    "wof:name":"Lindeplein('t)",
    "wof:placetype":"venue"
},
  "geometry": {"coordinates":[5.0777978897,51.1881561279],"type":"Point"}
}