{
  "type": "Feature",
  "properties": {
    "iso:country":"BE",
    "sg:address":"Rue Edouard Marcotty 15",
    "sg:city":"Li\u00e8ge 1 (grivegn\u00e9e)",
    "sg:classifiers":[
        {
            "category":"Home & Garden",
            "subcategory":"Building Materials",
            "type":"Retail Goods"
        }
    ],
    "sg:phone":"+32 4 343 62 43",
    "sg:postcode":"4030",
    "sg:province":"Li\u00e8ge",
    "sg:tags":[
        "shutter"
    ],
    "wof:name":"Drugmant (ets)",
    "wof:placetype":"venue"
},
  "geometry": {"coordinates":[5.5958938599,50.6260223389],"type":"Point"}
}