{
  "type": "Feature",
  "properties": {
    "iso:country":"BE",
    "sg:address":"Tiensesteenweg 80",
    "sg:city":"Sint-truiden",
    "sg:classifiers":[
        {
            "category":"Banks & Credit Unions",
            "subcategory":"Investment Brokerage",
            "type":"Services"
        }
    ],
    "sg:phone":"+32 11 69 36 17",
    "sg:postcode":"3800",
    "sg:province":"Limburg",
    "sg:tags":[
        "pump",
        "industrial",
        "-"
    ],
    "wof:name":"Weir Warman",
    "wof:placetype":"venue"
},
  "geometry": {"coordinates":[5.1832799911,50.8136482239],"type":"Point"}
}