{
  "type": "Feature",
  "properties": {
    "addr:full":"Stadenstraat 14 Roeselare West-Vlaanderen 8800",
    "addr:housenumber":"14",
    "addr:postcode":"8800",
    "addr:street":"Stadenstraat",
    "iso:country":"BE",
    "sg:address":"Stadenstraat 14",
    "sg:city":"Roeselare",
    "sg:orig_category":"Traducteurs and interpr\u00e8tes",
    "sg:phone":"+32 51 22 34 58",
    "sg:postcode":"8800",
    "sg:province":"West-Vlaanderen",
    "wof:name":"Ancaert L. Cbtip/bkvtf",
    "wof:placetype":"venue"
},
  "geometry": {"coordinates":[3.1081209183,50.9564476013],"type":"Point"}
}