{
  "type": "Feature",
  "properties": {
    "addr:full":"Rue Reine Astrid 26bb Saint-georges-sur-meuse Li\u00e8ge 4470",
    "addr:housenumber":"26bb",
    "addr:postcode":"4470",
    "addr:street":"Rue Reine Astrid",
    "iso:country":"BE",
    "sg:address":"Rue Reine Astrid 26bb",
    "sg:city":"Saint-georges-sur-meuse",
    "sg:orig_category":"V\u00e9los",
    "sg:phone":"+32 4 275 42 88",
    "sg:postcode":"4470",
    "sg:province":"Li\u00e8ge",
    "wof:name":"Bourgignon",
    "wof:placetype":"venue"
},
  "geometry": {"coordinates":[5.3590202332,50.5849304199],"type":"Point"}
}