{
  "type": "Feature",
  "properties": {
    "addr:full":"Kapelleweg 25 Tielt West-Vlaanderen 8700",
    "addr:housenumber":"25",
    "addr:postcode":"8700",
    "addr:street":"Kapelleweg",
    "iso:country":"BE",
    "sg:address":"Kapelleweg 25",
    "sg:city":"Tielt",
    "sg:orig_category":"Rundveehouders Varkenskwekers",
    "sg:phone":"+32 51 65 59 06",
    "sg:postcode":"8700",
    "sg:province":"West-Vlaanderen",
    "wof:name":"Hubert Deprest",
    "wof:placetype":"venue"
},
  "geometry": {"coordinates":[3.3256809711,51.0030517578],"type":"Point"}
}