{
  "type": "Feature",
  "properties": {
    "addr:full":"Poel 45 Asse Vlaams-Brabant 1730",
    "addr:housenumber":"45",
    "addr:postcode":"1730",
    "addr:street":"Poel",
    "iso:country":"BE",
    "sg:address":"Poel 45",
    "sg:city":"Asse",
    "sg:orig_category":"Artistes ind\u00e9pendants",
    "sg:phone":"+32 2 452 75 17",
    "sg:postcode":"1730",
    "sg:province":"Vlaams-Brabant",
    "wof:name":"Sileghem",
    "wof:placetype":"venue"
},
  "geometry": {"coordinates":[4.2240571976,50.8957138062],"type":"Point"}
}