{
  "type": "Feature",
  "properties": {
    "addr:full":"Universitaire Campus 0 Diepenbeek Limburg 3590",
    "addr:postcode":"3590",
    "addr:street":"Diepenbeek Limburg",
    "iso:country":"BE",
    "sg:address":"Universitaire Campus 0",
    "sg:city":"Diepenbeek",
    "sg:orig_category":"Hoger onderwijs",
    "sg:phone":"+32 11 26 85 02",
    "sg:postcode":"3590",
    "sg:province":"Limburg",
    "wof:name":"L.u.c.-fac. Geneeskunde",
    "wof:placetype":"venue"
},
  "geometry": {"coordinates":[5.3968520164,50.9297523499],"type":"Point"}
}