{
  "type": "Feature",
  "properties": {
    "addr:full":"Chauss\u00e9e De Tirlemont 40 Jodoigne Brabant Wallon 1370",
    "addr:housenumber":"40",
    "addr:postcode":"1370",
    "addr:street":"Chausse\u0301E De Tirlemont",
    "iso:country":"BE",
    "sg:address":"Chauss\u00e9e De Tirlemont 40",
    "sg:city":"Jodoigne",
    "sg:classifiers":[
        {
            "category":"Retail",
            "subcategory":"Veterinary Services",
            "type":"Services"
        }
    ],
    "sg:phone":"+32 10 81 05 33",
    "sg:postcode":"1370",
    "sg:province":"Brabant Wallon",
    "sg:tags":[
        "veterinarian"
    ],
    "wof:name":"De Temmerman F",
    "wof:placetype":"venue"
},
  "geometry": {"coordinates":[4.873336792,50.7261695862],"type":"Point"}
}