{
  "type": "Feature",
  "properties": {
    "iso:country":"BE",
    "sg:address":"Elf-julistraat 54",
    "sg:city":"Brugge",
    "sg:classifiers":[
        {
            "category":"Health Services",
            "subcategory":"Health Practitioner",
            "type":"Services"
        }
    ],
    "sg:phone":"+32 50 33 62 01",
    "sg:postcode":"8000",
    "sg:province":"West-Vlaanderen",
    "sg:tags":[
        "physiotherapist"
    ],
    "wof:name":"Beyne J",
    "wof:placetype":"venue"
},
  "geometry": {"coordinates":[3.2195620537,51.2171020508],"type":"Point"}
}