{
  "type": "Feature",
  "properties": {
    "addr:full":"Waversesteenweg 38 Overijse Vlaams-Brabant 3090",
    "addr:housenumber":"38",
    "addr:postcode":"3090",
    "addr:street":"Waversesteenweg",
    "iso:country":"BE",
    "sg:address":"Waversesteenweg 38",
    "sg:city":"Overijse",
    "sg:classifiers":[
        {
            "category":"Personal",
            "subcategory":"Beauty Salon",
            "type":"Services"
        }
    ],
    "sg:phone":"+32 2 687 78 23",
    "sg:postcode":"3090",
    "sg:province":"Vlaams-Brabant",
    "sg:tags":[
        "lady",
        "-",
        "hairdressing"
    ],
    "wof:name":"Braun-z",
    "wof:placetype":"venue"
},
  "geometry": {"coordinates":[4.5712599754,50.7485084534],"type":"Point"}
}