{
  "type": "Feature",
  "properties": {
    "iso:country":"BE",
    "sg:address":"Leestsesteenweg 116",
    "sg:city":"Mechelen",
    "sg:classifiers":[
        {
            "category":"Professional",
            "type":"Services"
        }
    ],
    "sg:phone":"+32 15 27 74 93",
    "sg:postcode":"2800",
    "sg:province":"Antwerpen",
    "sg:tags":[
        "entertainer"
    ],
    "wof:name":"Benjamin's Kindershow",
    "wof:placetype":"venue"
},
  "geometry": {"coordinates":[4.4361901283,51.0385322571],"type":"Point"}
}