{
  "type": "Feature",
  "properties": {
    "iso:country":"BE",
    "sg:address":"Rue Arbre-courte-joie 350",
    "sg:city":"Li\u00c8ge",
    "sg:orig_category":"Gestion de media publicitaires",
    "sg:phone":"+32 4 263 18 58",
    "sg:postcode":"4000",
    "sg:province":"Li\u00e8ge",
    "wof:name":"D.w.r.",
    "wof:placetype":"venue"
},
  "geometry": {"coordinates":[5.5393471718,50.6701049805],"type":"Point"}
}