{
  "type": "Feature",
  "properties": {
    "iso:country":"BE",
    "sg:address":"Bosstraat 32",
    "sg:city":"Mortsel",
    "sg:orig_category":"Tuinen",
    "sg:phone":"+32 477 55 11 94",
    "sg:postcode":"2640",
    "sg:province":"Antwerpen",
    "wof:name":"Michel Braeken",
    "wof:placetype":"venue"
},
  "geometry": {"coordinates":[4.4410948753,51.1705970764],"type":"Point"}
}