{
  "type": "Feature",
  "properties": {
    "addr:full":"Stationsstraat 15 Herzele Oost-Vlaanderen 9550",
    "addr:housenumber":"15",
    "addr:postcode":"9550",
    "addr:street":"Stationsstraat;Oost-Vlaanderen",
    "iso:country":"BE",
    "sg:address":"Stationsstraat 15",
    "sg:city":"Herzele",
    "sg:classifiers":[
        {
            "category":"Manufacturing",
            "subcategory":"Furniture",
            "type":"Manufacturing & Wholesale Goods"
        }
    ],
    "sg:phone":"+32 53 62 20 25",
    "sg:postcode":"9550",
    "sg:province":"Oost-Vlaanderen",
    "sg:tags":[
        "juvenile",
        "-"
    ],
    "wof:name":"Beja",
    "wof:placetype":"venue"
},
  "geometry": {"coordinates":[3.8899869919,50.8887672424],"type":"Point"}
}