{
  "type": "Feature",
  "properties": {
    "iso:country":"BE",
    "sg:address":"Tarwestraat 40",
    "sg:city":"Gent",
    "sg:classifiers":[
        {
            "category":"Building & Trades",
            "subcategory":"Landscaping Services",
            "type":"Services"
        }
    ],
    "sg:phone":"+32 9 357 28 84",
    "sg:postcode":"9000",
    "sg:province":"Oost-Vlaanderen",
    "sg:tags":[
        "-",
        "lopping",
        "work",
        "tree",
        "felling"
    ],
    "wof:name":"Alfa",
    "wof:placetype":"venue"
},
  "geometry": {"coordinates":[3.7166268826,51.0612792969],"type":"Point"}
}