{
  "type": "Feature",
  "properties": {
    "addr:full":"Eikestraat 2-3 Herent (winksele) Vlaams-Brabant 3020",
    "addr:housenumber":"2-3",
    "addr:postcode":"3020",
    "addr:street":"Eikestraat",
    "iso:country":"BE",
    "sg:address":"Eikestraat 2-3",
    "sg:city":"Herent (winksele)",
    "sg:classifiers":[
        {
            "category":"Retail",
            "subcategory":"Funeral Services",
            "type":"Services"
        }
    ],
    "sg:phone":"+32 16 60 15 06",
    "sg:postcode":"3020",
    "sg:province":"Vlaams-Brabant",
    "sg:tags":[
        "director"
    ],
    "wof:name":"Begrafenissen Pues Bvba",
    "wof:placetype":"venue"
},
  "geometry": {"coordinates":[4.6749200821,50.9079055786],"type":"Point"}
}