{
  "type": "Feature",
  "properties": {
    "addr:full":"Arkstraat 39 Meeuwen-gruitrode (meeuwen) Limburg 3670",
    "addr:housenumber":"39",
    "addr:postcode":"3670",
    "addr:street":"Arkstraat",
    "iso:country":"BE",
    "sg:address":"Arkstraat 39",
    "sg:city":"Meeuwen-gruitrode (meeuwen)",
    "sg:classifiers":[
        {
            "category":"Health Services",
            "subcategory":"Health Practitioner",
            "type":"Services"
        }
    ],
    "sg:phone":"+32 11 79 24 92",
    "sg:postcode":"3670",
    "sg:province":"Limburg",
    "sg:tags":[
        "physiotherapist"
    ],
    "wof:name":"Vanwezemael H",
    "wof:placetype":"venue"
},
  "geometry": {"coordinates":[5.5277028084,51.0948829651],"type":"Point"}
}