{
  "type": "Feature",
  "properties": {
    "addr:full":"Place Emile Royer 2 Bernissart Hainaut 7321",
    "addr:housenumber":"2",
    "addr:postcode":"7321",
    "addr:street":"Place Emile Royer",
    "iso:country":"BE",
    "sg:address":"Place Emile Royer 2",
    "sg:city":"Bernissart",
    "sg:orig_category":"Textiel",
    "sg:phone":"+32 69 57 87 58",
    "sg:postcode":"7321",
    "sg:province":"Hainaut",
    "wof:name":"Chez Ren\u00c9e",
    "wof:placetype":"venue"
},
  "geometry": {"coordinates":[3.6653079987,50.5029335022],"type":"Point"}
}