{
  "type": "Feature",
  "properties": {
    "addr:full":"De Wittestraat 1 Antwerpen Antwerpen 2600",
    "addr:housenumber":"1",
    "addr:postcode":"2600",
    "addr:street":"De Wittestraat",
    "iso:country":"BE",
    "sg:address":"De Wittestraat 1",
    "sg:city":"Antwerpen",
    "sg:orig_category":"Openbare veiligheid",
    "sg:phone":"+32 3 287 64 11",
    "sg:postcode":"2600",
    "sg:province":"Antwerpen",
    "wof:name":"Federale Politie",
    "wof:placetype":"venue"
},
  "geometry": {"coordinates":[4.3867602348,51.1895599365],"type":"Point"}
}