{
  "type": "Feature",
  "properties": {
    "addr:full":"Dr\u00c8ve Des Agaves 6 Anderlecht/anderlecht Bruxelles-Capitale 1070",
    "addr:housenumber":"6",
    "addr:postcode":"1070",
    "addr:street":"Dre\u0300Ve Des Agaves",
    "iso:country":"BE",
    "sg:address":"Dr\u00c8ve Des Agaves 6",
    "sg:city":"Anderlecht/anderlecht",
    "sg:orig_category":"Traitements param\u00e9dicaux",
    "sg:phone":"+32 2 522 90 29",
    "sg:postcode":"1070",
    "sg:province":"Bruxelles-Capitale",
    "wof:name":"J. Van Laethem",
    "wof:placetype":"venue"
},
  "geometry": {"coordinates":[4.2859249115,50.8336143494],"type":"Point"}
}