{
  "type": "Feature",
  "properties": {
    "iso:country":"BE",
    "sg:address":"Ambachtenlaan 54",
    "sg:city":"Leuven",
    "sg:orig_category":"Travaux de finition and nettoyage de b\u00e2timents",
    "sg:phone":"+32 16 40 31 11",
    "sg:postcode":"3001",
    "sg:province":"Vlaams-Brabant",
    "wof:name":"Nicover",
    "wof:placetype":"venue"
},
  "geometry": {"coordinates":[4.7175779343,50.8474884033],"type":"Point"}
}