{
  "type": "Feature",
  "properties": {
    "iso:country":"BE",
    "sg:address":"Rue De La Girafe 40",
    "sg:city":"Bouillon",
    "sg:orig_category":"GROENTEN AND FRUIT Groenten and fruit Gh",
    "sg:phone":"+32 61 46 78 65",
    "sg:postcode":"6832",
    "sg:province":"Luxembourg",
    "wof:name":"J.p. Maziers",
    "wof:placetype":"venue"
},
  "geometry": {"coordinates":[5.0727958679,49.8251419067],"type":"Point"}
}