{
  "type": "Feature",
  "properties": {
    "addr:full":"Kortewildestraat 1 Diksmuide (vladslo) West-Vlaanderen 8600",
    "addr:housenumber":"1",
    "addr:postcode":"8600",
    "addr:street":"Kortewildestraat",
    "iso:country":"BE",
    "sg:address":"Kortewildestraat 1",
    "sg:city":"Diksmuide (vladslo)",
    "sg:classifiers":[
        {
            "category":"Building & Trades",
            "subcategory":"Construction",
            "type":"Services"
        }
    ],
    "sg:phone":"+32 51 50 23 06",
    "sg:postcode":"8600",
    "sg:province":"West-Vlaanderen",
    "sg:tags":[
        "carpenter"
    ],
    "wof:name":"Devreker Gebr Bvba",
    "wof:placetype":"venue"
},
  "geometry": {"coordinates":[2.9230940342,51.0461616516],"type":"Point"}
}