{
  "type": "Feature",
  "properties": {
    "addr:full":"Koning Boudewijnlaan 6 Olen Antwerpen 2250",
    "addr:housenumber":"6",
    "addr:postcode":"2250",
    "addr:street":"Koning Boudewijnlaan",
    "iso:country":"BE",
    "sg:address":"Koning Boudewijnlaan 6",
    "sg:city":"Olen",
    "sg:classifiers":[
        {
            "category":"Autos & Motor Vehicles",
            "subcategory":"Automobile Sales",
            "type":"Retail Goods"
        }
    ],
    "sg:phone":"+32 14 21 32 00",
    "sg:postcode":"2250",
    "sg:province":"Antwerpen",
    "sg:tags":[
        "car",
        "used",
        "-"
    ],
    "wof:name":"Geens G Bvba",
    "wof:placetype":"venue"
},
  "geometry": {"coordinates":[4.8586320877,51.1474342346],"type":"Point"}
}