{
  "type": "Feature",
  "properties": {
    "addr:full":"Kezeweide 54 Asse (mollem) Vlaams-Brabant 1730",
    "addr:housenumber":"54",
    "addr:postcode":"1730",
    "addr:street":"Kezeweide",
    "iso:country":"BE",
    "sg:address":"Kezeweide 54",
    "sg:city":"Asse (mollem)",
    "sg:classifiers":[
        {
            "category":"Freight",
            "type":"Transportation"
        }
    ],
    "sg:phone":"+32 2 452 66 61",
    "sg:postcode":"1730",
    "sg:province":"Vlaams-Brabant",
    "sg:tags":[
        "-",
        "transport"
    ],
    "wof:name":"Cocomtrans",
    "wof:placetype":"venue"
},
  "geometry": {"coordinates":[4.2191262245,50.9320793152],"type":"Point"}
}