{
  "type": "Feature",
  "properties": {
    "iso:country":"BE",
    "sg:address":"Rue Au Bois 240",
    "sg:city":"Bruxelles (woluwe-saint-pierre)",
    "sg:classifiers":[
        {
            "category":"Building & Trades",
            "subcategory":"Construction",
            "type":"Services"
        }
    ],
    "sg:phone":"+32 2 771 17 47",
    "sg:postcode":"1150",
    "sg:province":"Bruxelles-Capitale",
    "sg:tags":[
        "paper",
        "hanger"
    ],
    "wof:name":"Deckers J",
    "wof:placetype":"venue"
},
  "geometry": {"coordinates":[4.4495668411,50.8323364258],"type":"Point"}
}