{
  "type": "Feature",
  "properties": {
    "addr:full":"Langerbrugsestraat 81 Evergem Oost-Vlaanderen 9940",
    "addr:housenumber":"81",
    "addr:postcode":"9940",
    "addr:street":"Langerbrugsestraat;Oost-Vlaanderen",
    "iso:country":"BE",
    "sg:address":"Langerbrugsestraat 81",
    "sg:city":"Evergem",
    "sg:orig_category":"Services divers aux entreprises. Salles de conf\u00e9rences and de r\u00e9ceptions",
    "sg:phone":"+32 9 253 11 52",
    "sg:postcode":"9940",
    "sg:province":"Oost-Vlaanderen",
    "wof:name":"Bureau Van De Steene",
    "wof:placetype":"venue"
},
  "geometry": {"coordinates":[3.7225320339,51.1110305786],"type":"Point"}
}