{
  "type": "Feature",
  "properties": {
    "iso:country":"BE",
    "sg:address":"Heilige Geeststraat 10",
    "sg:city":"Lier",
    "sg:orig_category":"V\u00eatements",
    "sg:phone":"+32 3 480 79 51",
    "sg:postcode":"2500",
    "sg:province":"Antwerpen",
    "wof:name":"Angelique",
    "wof:placetype":"venue"
},
  "geometry": {"coordinates":[4.5749402046,51.1303291321],"type":"Point"}
}