{
  "type": "Feature",
  "properties": {
    "addr:full":"Hof Ter Hillestraat 2 Koksijde West-Vlaanderen 8670",
    "addr:housenumber":"2",
    "addr:postcode":"8670",
    "addr:street":"Hof Ter Hillestraat",
    "iso:country":"BE",
    "sg:address":"Hof Ter Hillestraat 2",
    "sg:city":"Koksijde",
    "sg:orig_category":"Rundveehouders",
    "sg:phone":"+32 58 23 34 99",
    "sg:postcode":"8670",
    "sg:province":"West-Vlaanderen",
    "wof:name":"Simoens Nollet",
    "wof:placetype":"venue"
},
  "geometry": {"coordinates":[2.6980988979,51.116355896],"type":"Point"}
}