{
  "type": "Feature",
  "properties": {
    "addr:full":"Speelberg 32 Overijse Vlaams-Brabant 3090",
    "addr:housenumber":"32",
    "addr:postcode":"3090",
    "iso:country":"BE",
    "sg:address":"Speelberg 32",
    "sg:city":"Overijse",
    "sg:orig_category":"Fleurs and plantes",
    "sg:phone":"+32 2 687 76 16",
    "sg:postcode":"3090",
    "sg:province":"Vlaams-Brabant",
    "wof:name":"Poriau-neptunus",
    "wof:placetype":"venue"
},
  "geometry": {"coordinates":[4.5352787971,50.7654571533],"type":"Point"}
}