{
  "type": "Feature",
  "properties": {
    "iso:country":"BE",
    "sg:address":"Rue Buisseret 2",
    "sg:city":"Mons",
    "sg:classifiers":[
        {
            "category":"Social Services",
            "type":"Services"
        }
    ],
    "sg:phone":"+32 65 84 36 60",
    "sg:postcode":"7000",
    "sg:province":"Hainaut",
    "wof:name":"Service De Pr\u00e9vention",
    "wof:placetype":"venue"
},
  "geometry": {"coordinates":[3.9435830116,50.4485778809],"type":"Point"}
}