{
  "type": "Feature",
  "properties": {
    "iso:country":"BE",
    "sg:address":"Sint-denijsstraat 112",
    "sg:city":"Vorst/forest",
    "sg:orig_category":"Huishoudapparaten, televisies and radio's",
    "sg:phone":"+32 2 340 07 70",
    "sg:postcode":"1190",
    "sg:province":"Bruxelles-Capitale",
    "wof:name":"Video Square",
    "wof:placetype":"venue"
},
  "geometry": {"coordinates":[4.3179101944,50.8105888367],"type":"Point"}
}