{
  "type": "Feature",
  "properties": {
    "addr:full":"Bld. Walter De Marvis 22 Tournai Hainaut 7500",
    "addr:housenumber":"22",
    "addr:postcode":"7500",
    "iso:country":"BE",
    "sg:address":"Bld. Walter De Marvis 22",
    "sg:city":"Tournai",
    "sg:classifiers":[
        {
            "category":"Fast Food",
            "type":"Food & Drink"
        }
    ],
    "sg:phone":"+32 69 22 69 00",
    "sg:postcode":"7500",
    "sg:province":"Hainaut",
    "sg:tags":[
        "\u00c0",
        "emporter",
        "restaurants"
    ],
    "wof:name":"Adriatic",
    "wof:placetype":"venue"
},
  "geometry": {"coordinates":[3.399586916,50.6073875427],"type":"Point"}
}