{
  "type": "Feature",
  "properties": {
    "iso:country":"BE",
    "sg:address":"Ruiterslaan 8",
    "sg:city":"Wijnegem",
    "sg:classifiers":[
        {
            "category":"Professional",
            "subcategory":"Management & Consulting",
            "type":"Services"
        }
    ],
    "sg:phone":"+32 3 353 00 05",
    "sg:postcode":"2110",
    "sg:province":"Antwerpen",
    "sg:tags":[
        "consultant",
        "-",
        "legislation",
        "social"
    ],
    "wof:name":"Claeys & Vanrobays Bvba",
    "wof:placetype":"venue"
},
  "geometry": {"coordinates":[4.5464692116,51.2263145447],"type":"Point"}
}