{
  "type": "Feature",
  "properties": {
    "addr:full":"Minister Liebaertlaan 11 Kortrijk West-Vlaanderen 8500",
    "addr:housenumber":"11",
    "addr:postcode":"8500",
    "addr:street":"Minister Liebaertlaan",
    "iso:country":"BE",
    "sg:address":"Minister Liebaertlaan 11",
    "sg:city":"Kortrijk",
    "sg:orig_category":"Binnenhuisarchitecten",
    "sg:phone":"+32 56 25 24 34",
    "sg:postcode":"8500",
    "sg:province":"West-Vlaanderen",
    "wof:name":"Kurt Vandamme",
    "wof:placetype":"venue"
},
  "geometry": {"coordinates":[3.2736139297,50.8318328857],"type":"Point"}
}