{
  "type": "Feature",
  "properties": {
    "addr:full":". Antwerpen Antwerpen 2050",
    "addr:postcode":"2050",
    "iso:country":"BE",
    "sg:address":".",
    "sg:city":"Antwerpen",
    "sg:orig_category":"Astrologen, grafologen and mediums",
    "sg:phone":"+32 496 15 45 33",
    "sg:postcode":"2050",
    "sg:province":"Antwerpen",
    "wof:name":"Anaii",
    "wof:placetype":"venue"
},
  "geometry": {"coordinates":[4.3689899445,51.2226295471],"type":"Point"}
}