{
  "type": "Feature",
  "properties": {
    "iso:country":"BE",
    "sg:address":"Meir 44a",
    "sg:city":"Antwerpen",
    "sg:classifiers":[
        {
            "category":"Professional",
            "subcategory":"Engineering",
            "type":"Services"
        }
    ],
    "sg:phone":"+32 3 202 46 71",
    "sg:postcode":"2000",
    "sg:province":"Antwerpen",
    "sg:tags":[
        "-"
    ],
    "wof:name":"Faithful & Gould Nv",
    "wof:placetype":"venue"
},
  "geometry": {"coordinates":[4.4077129364,51.2180252075],"type":"Point"}
}