{
  "type": "Feature",
  "properties": {
    "iso:country":"BE",
    "sg:address":"Hulststraat 46",
    "sg:city":"Lier",
    "sg:orig_category":"Producteurs de l\u00e9gumes",
    "sg:phone":"+32 3 480 62 15",
    "sg:postcode":"2500",
    "sg:province":"Antwerpen",
    "wof:name":"Andre Mortelmans",
    "wof:placetype":"venue"
},
  "geometry": {"coordinates":[4.5281791687,51.1223831177],"type":"Point"}
}