{
  "type": "Feature",
  "properties": {
    "iso:country":"BE",
    "sg:address":"Thomas Watsonlaan 18",
    "sg:city":"Hamont-achel (achel)",
    "sg:classifiers":[
        {
            "category":"Shopping",
            "subcategory":"Computers & Home Electronics",
            "type":"Retail Goods"
        }
    ],
    "sg:phone":"+32 11 64 81 73",
    "sg:postcode":"3930",
    "sg:province":"Limburg",
    "sg:tags":[
        "-",
        "television",
        "radio"
    ],
    "wof:name":"Breemans K",
    "wof:placetype":"venue"
},
  "geometry": {"coordinates":[5.4800190926,51.2499084473],"type":"Point"}
}