{
  "type": "Feature",
  "properties": {
    "addr:full":"Centre Commercial Du Bultia 57 Gerpinnes Hainaut 6280",
    "addr:housenumber":"57",
    "addr:postcode":"6280",
    "addr:street":"Hainaut",
    "iso:country":"BE",
    "sg:address":"Centre Commercial Du Bultia 57",
    "sg:city":"Gerpinnes",
    "sg:classifiers":[
        {
            "category":"Shopping",
            "subcategory":"Gifts & Souvenirs",
            "type":"Retail Goods"
        }
    ],
    "sg:phone":"+32 71 21 92 20",
    "sg:postcode":"6280",
    "sg:province":"Hainaut",
    "sg:tags":[
        "-"
    ],
    "wof:name":"Autre Monde (un)",
    "wof:placetype":"venue"
},
  "geometry": {"coordinates":[4.4791998863,50.3445396423],"type":"Point"}
}