{
  "type": "Feature",
  "properties": {
    "iso:country":"BE",
    "sg:address":"Hazeschransstraat",
    "sg:city":"Edegem",
    "sg:classifiers":[
        {
            "category":"Building & Trades",
            "subcategory":"Pest Control",
            "type":"Services"
        }
    ],
    "sg:phone":"+32 475 69 47 96",
    "sg:postcode":"2650",
    "sg:province":"Antwerpen",
    "sg:tags":[
        "painting",
        "contractor"
    ],
    "wof:name":"Tonas Lacroix",
    "wof:placetype":"venue"
},
  "geometry": {"coordinates":[4.4238200188,51.1650848389],"type":"Point"}
}