{
  "type": "Feature",
  "properties": {
    "addr:full":"Noendries 81a Gent Oost-Vlaanderen 9000",
    "addr:housenumber":"81a",
    "addr:postcode":"9000",
    "addr:street":"Noendries;Oost-Vlaanderen",
    "iso:country":"BE",
    "sg:address":"Noendries 81a",
    "sg:city":"Gent",
    "sg:orig_category":"Kantoormateriaal Kantoormateriaal Gh",
    "sg:phone":"+32 9 220 83 15",
    "sg:postcode":"9000",
    "sg:province":"Oost-Vlaanderen",
    "wof:name":"Topdeal",
    "wof:placetype":"venue"
},
  "geometry": {"coordinates":[3.728687048,51.0285110474],"type":"Point"}
}