{
  "type": "Feature",
  "properties": {
    "addr:full":"Chauss\u00c9e De Nivelles 3 Charleroi Hainaut 6041",
    "addr:housenumber":"3",
    "addr:postcode":"6041",
    "addr:street":"Chausse\u0301E De Nivelles;Hainaut",
    "iso:country":"BE",
    "sg:address":"Chauss\u00c9e De Nivelles 3",
    "sg:city":"Charleroi",
    "sg:classifiers":[
        {
            "category":"Fast Food",
            "type":"Food & Drink"
        }
    ],
    "sg:phone":"+32 71 37 38 15",
    "sg:postcode":"6041",
    "sg:province":"Hainaut",
    "sg:tags":[
        "\u00c0",
        "restaurants",
        "emporter",
        "restaurant"
    ],
    "wof:name":"Le Lotus Bleu",
    "wof:placetype":"venue"
},
  "geometry": {"coordinates":[4.4314317703,50.4685935974],"type":"Point"}
}