{
  "type": "Feature",
  "properties": {
    "iso:country":"BE",
    "sg:address":"Rue De Cousolre 4",
    "sg:city":"Erquelinnes (bersillies - L'abbaye)",
    "sg:classifiers":[
        {
            "category":"Bars & Pubs",
            "type":"Food & Drink"
        }
    ],
    "sg:phone":"+32 71 55 62 61",
    "sg:postcode":"6560",
    "sg:province":"Hainaut",
    "wof:name":"Sports (caf\u00e9 Des)",
    "wof:placetype":"venue"
},
  "geometry": {"coordinates":[4.1539897919,50.261631012],"type":"Point"}
}