{
  "type": "Feature",
  "properties": {
    "addr:full":"Baron Albert D'huartln 238 Kraainem/kraainem Vlaams-Brabant 1950",
    "addr:housenumber":"238",
    "addr:postcode":"1950",
    "addr:street":"Baron Albert D'Huartln",
    "iso:country":"BE",
    "sg:address":"Baron Albert D'huartln 238",
    "sg:city":"Kraainem/kraainem",
    "sg:orig_category":"Artsen and specialisten",
    "sg:phone":"+32 2 782 00 70",
    "sg:postcode":"1950",
    "sg:province":"Vlaams-Brabant",
    "wof:name":"Agn\u00c8s Tran Thi Minh Nguyet",
    "wof:placetype":"venue"
},
  "geometry": {"coordinates":[4.4102392197,50.8199768066],"type":"Point"}
}