{
  "type": "Feature",
  "properties": {
    "iso:country":"BE",
    "sg:address":"Hoge Wei 37",
    "sg:city":"Zaventem (nossegem)",
    "sg:classifiers":[
        {
            "category":"Professional",
            "subcategory":"Management & Consulting",
            "type":"Services"
        }
    ],
    "sg:phone":"+32 2 704 49 69",
    "sg:postcode":"1930",
    "sg:province":"Vlaams-Brabant",
    "sg:tags":[
        "consultant",
        "agency",
        "advertising"
    ],
    "wof:name":"Be Mind Communication",
    "wof:placetype":"venue"
},
  "geometry": {"coordinates":[4.4995207787,50.8755187988],"type":"Point"}
}