{
  "type": "Feature",
  "properties": {
    "addr:full":"Chemin Du Fournil 4 Waimes Li\u00e8ge 4950",
    "addr:housenumber":"4",
    "addr:postcode":"4950",
    "addr:street":"Chemin Du Fournil",
    "iso:country":"BE",
    "sg:address":"Chemin Du Fournil 4",
    "sg:city":"Waimes",
    "sg:orig_category":"Loodgieterij, verwarming and sanitaire installaties",
    "sg:phone":"+32 80 67 83 10",
    "sg:postcode":"4950",
    "sg:province":"Li\u00e8ge",
    "wof:name":"Fe. D\u00c9sitherm",
    "wof:placetype":"venue"
},
  "geometry": {"coordinates":[6.1110301018,50.4149055481],"type":"Point"}
}