{
  "type": "Feature",
  "properties": {
    "iso:country":"BE",
    "sg:address":"Paddenhoek 3",
    "sg:city":"Gent",
    "sg:orig_category":"Cin\u00e9mas",
    "sg:phone":"+32 9 242 80 60",
    "sg:postcode":"9000",
    "sg:province":"Oost-Vlaanderen",
    "wof:name":"Film-plateau",
    "wof:placetype":"venue"
},
  "geometry": {"coordinates":[3.7246029377,51.0515708923],"type":"Point"}
}