{
  "type": "Feature",
  "properties": {
    "addr:full":"Nijverheidsln 50 Avelgem West-Vlaanderen 8580",
    "addr:housenumber":"50",
    "addr:postcode":"8580",
    "addr:street":"Nijverheidsln",
    "iso:country":"BE",
    "sg:address":"Nijverheidsln 50",
    "sg:city":"Avelgem",
    "sg:classifiers":[
        {
            "category":"Marine",
            "type":"Transportation"
        }
    ],
    "sg:phone":"+32 56 64 67 32",
    "sg:postcode":"8580",
    "sg:province":"West-Vlaanderen",
    "sg:tags":[
        "transport",
        "sea"
    ],
    "wof:name":"One Way Trucking Avelgem Nv",
    "wof:placetype":"venue"
},
  "geometry": {"coordinates":[3.4464159012,50.75831604],"type":"Point"}
}