{
  "type": "Feature",
  "properties": {
    "addr:full":"Poststraat 2 Wevelgem West-Vlaanderen 8560",
    "addr:housenumber":"2",
    "addr:postcode":"8560",
    "addr:street":"Poststraat",
    "iso:country":"BE",
    "sg:address":"Poststraat 2",
    "sg:city":"Wevelgem",
    "sg:orig_category":"Schoenen",
    "sg:phone":"+32 56 41 61 23",
    "sg:postcode":"8560",
    "sg:province":"West-Vlaanderen",
    "wof:name":"'t Hoekske",
    "wof:placetype":"venue"
},
  "geometry": {"coordinates":[3.2045829296,50.8442840576],"type":"Point"}
}