{
  "type": "Feature",
  "properties": {
    "iso:country":"BE",
    "sg:address":"Avenue Louis Libert 1",
    "sg:city":"Aywaille",
    "sg:classifiers":[
        {
            "category":"Shopping",
            "subcategory":"Clothing, Apparel, & Fashions",
            "type":"Retail Goods"
        }
    ],
    "sg:phone":"+32 4 384 62 05",
    "sg:postcode":"4920",
    "sg:province":"Li\u00e8ge",
    "sg:tags":[
        "boutique"
    ],
    "wof:name":"Ig\u00e9 Boutique",
    "wof:placetype":"venue"
},
  "geometry": {"coordinates":[5.6764211655,50.473651886],"type":"Point"}
}