{
  "type": "Feature",
  "properties": {
    "addr:full":"Ommegangstraat 18 Zwevegem West-Vlaanderen 8550",
    "addr:housenumber":"18",
    "addr:postcode":"8550",
    "addr:street":"Ommegangstraat",
    "iso:country":"BE",
    "sg:address":"Ommegangstraat 18",
    "sg:city":"Zwevegem",
    "sg:classifiers":[
        {
            "category":"Banks & Credit Unions",
            "subcategory":"Investment Brokerage",
            "type":"Services"
        }
    ],
    "sg:phone":"+32 56 75 83 61",
    "sg:postcode":"8550",
    "sg:province":"West-Vlaanderen",
    "sg:tags":[
        "repair",
        "-",
        "installation",
        "sanitary",
        "article"
    ],
    "wof:name":"Verbrugge Sanitair Bvba",
    "wof:placetype":"venue"
},
  "geometry": {"coordinates":[3.3392350674,50.8112487793],"type":"Point"}
}