{
  "type": "Feature",
  "properties": {
    "addr:full":"President Kennedypark 18 Kortrijk West-Vlaanderen 8500",
    "addr:housenumber":"18",
    "addr:postcode":"8500",
    "addr:street":"President Kennedypark",
    "iso:country":"BE",
    "sg:address":"President Kennedypark 18",
    "sg:city":"Kortrijk",
    "sg:classifiers":[
        {
            "category":"Banks & Credit Unions",
            "subcategory":"Investment Brokerage",
            "type":"Services"
        }
    ],
    "sg:phone":"+32 3 870 18 11",
    "sg:postcode":"8500",
    "sg:province":"West-Vlaanderen",
    "sg:tags":[
        "fence"
    ],
    "wof:name":"Bekaert (ann Parrez)",
    "wof:placetype":"venue"
},
  "geometry": {"coordinates":[3.2715198994,50.7987709045],"type":"Point"}
}