{
  "type": "Feature",
  "properties": {
    "addr:full":"Avenue Jean Xxiii 6 Rixensart Brabant Wallon 1330",
    "addr:housenumber":"6",
    "addr:postcode":"1330",
    "addr:street":"Avenue Jean Xxiii;Wallon",
    "iso:country":"BE",
    "sg:address":"Avenue Jean Xxiii 6",
    "sg:city":"Rixensart",
    "sg:orig_category":"M\u00e9decins and sp\u00e9cialistes",
    "sg:phone":"+32 2 653 10 05",
    "sg:postcode":"1330",
    "sg:province":"Brabant Wallon",
    "wof:name":"Edgard Maes",
    "wof:placetype":"venue"
},
  "geometry": {"coordinates":[4.5208330154,50.7067070007],"type":"Point"}
}