{
  "type": "Feature",
  "properties": {
    "iso:country":"BE",
    "sg:address":"Koningstraat 26",
    "sg:city":"Oostende",
    "sg:orig_category":"Royal Canin. Services pour animaux domestiques",
    "sg:phone":"+32 59 51 02 01",
    "sg:postcode":"8400",
    "sg:province":"West-Vlaanderen",
    "wof:name":"Firma Tilly",
    "wof:placetype":"venue"
},
  "geometry": {"coordinates":[2.9122190475,51.2299613953],"type":"Point"}
}