{
  "type": "Feature",
  "properties": {
    "addr:full":"Avenue Edouard De Thibault 35 Bruxelles (etterbeek) Bruxelles-Capitale 1040",
    "addr:housenumber":"35",
    "addr:postcode":"1040",
    "addr:street":"Avenue Edouard De Thibault",
    "iso:country":"BE",
    "sg:address":"Avenue Edouard De Thibault 35",
    "sg:city":"Bruxelles (etterbeek)",
    "sg:classifiers":[
        {
            "category":"Social Services",
            "type":"Services"
        }
    ],
    "sg:phone":"+32 2 735 83 34",
    "sg:postcode":"1040",
    "sg:province":"Bruxelles-Capitale",
    "sg:tags":[
        "handicapped",
        "-"
    ],
    "wof:name":"Vague (la) Asbl",
    "wof:placetype":"venue"
},
  "geometry": {"coordinates":[4.397110939,50.8342590332],"type":"Point"}
}