{
  "type": "Feature",
  "properties": {
    "iso:country":"BE",
    "sg:address":"Annunciadenstraat 13",
    "sg:city":"Genk",
    "sg:orig_category":"Kinderopvang",
    "sg:phone":"+32 89 30 75 17",
    "sg:postcode":"3600",
    "sg:province":"Limburg",
    "wof:name":"Buitenschoolse Kinderopv.",
    "wof:placetype":"venue"
},
  "geometry": {"coordinates":[5.5226488113,50.974395752],"type":"Point"}
}