{
  "type": "Feature",
  "properties": {
    "iso:country":"BE",
    "sg:address":"Geraardsbergsestraat 56",
    "sg:city":"Dilbeek (schepdaal)",
    "sg:classifiers":[
        {
            "category":"Health Services",
            "subcategory":"Health Practitioner",
            "type":"Services"
        }
    ],
    "sg:phone":"+32 2 569 35 25",
    "sg:postcode":"1703",
    "sg:province":"Vlaams-Brabant",
    "sg:tags":[
        "physiotherapist"
    ],
    "wof:name":"Vande Weyer N",
    "wof:placetype":"venue"
},
  "geometry": {"coordinates":[4.2023348808,50.8359794617],"type":"Point"}
}