{
  "type": "Feature",
  "properties": {
    "iso:country":"BE",
    "sg:address":"Lindestraat 96",
    "sg:city":"Waregem",
    "sg:classifiers":[
        {
            "category":"Structure",
            "subcategory":"Warehouse",
            "type":"Public Place"
        }
    ],
    "sg:phone":"+32 3 353 92 58",
    "sg:postcode":"8790",
    "sg:province":"West-Vlaanderen",
    "sg:tags":[
        "purpose-built"
    ],
    "wof:name":"Abasid B.v.b.a.",
    "wof:placetype":"venue"
},
  "geometry": {"coordinates":[4.4150300026,51.1934204102],"type":"Point"}
}