{
  "type": "Feature",
  "properties": {
    "addr:full":"Jules Franquistraat 30 Vorst/forest Bruxelles-Capitale 1190",
    "addr:housenumber":"30",
    "addr:postcode":"1190",
    "addr:street":"Franquistraat;/ Forest",
    "iso:country":"BE",
    "sg:address":"Jules Franquistraat 30",
    "sg:city":"Vorst/forest",
    "sg:orig_category":"Zalen voor culturele evenementen",
    "sg:phone":"+32 2 374 35 86",
    "sg:postcode":"1190",
    "sg:province":"Bruxelles-Capitale",
    "wof:name":"The Primitives",
    "wof:placetype":"venue"
},
  "geometry": {"coordinates":[4.3366928101,50.8260765076],"type":"Point"}
}