{
  "type": "Feature",
  "properties": {
    "addr:full":"Rue Du Jeu De Balle 10 La Louviere Hainaut 7100",
    "addr:housenumber":"10",
    "addr:postcode":"7100",
    "addr:street":"Rue Du Jeu De Balle",
    "iso:country":"BE",
    "sg:address":"Rue Du Jeu De Balle 10",
    "sg:city":"La Louviere",
    "sg:orig_category":"Artsen and specialisten",
    "sg:phone":"+32 64 21 62 00",
    "sg:postcode":"7100",
    "sg:province":"Hainaut",
    "wof:name":"C. Haine",
    "wof:placetype":"venue"
},
  "geometry": {"coordinates":[4.1850848198,50.4748649597],"type":"Point"}
}