{
  "type": "Feature",
  "properties": {
    "addr:full":"Drongendreef 1 Moerbeke Oost-Vlaanderen 9180",
    "addr:housenumber":"1",
    "addr:postcode":"9180",
    "addr:street":"Drongendreef",
    "iso:country":"BE",
    "sg:address":"Drongendreef 1",
    "sg:city":"Moerbeke",
    "sg:orig_category":"Enseignement maternel and primaire",
    "sg:phone":"+32 9 346 88 34",
    "sg:postcode":"9180",
    "sg:province":"Oost-Vlaanderen",
    "wof:name":"Gemeentelijke Basisschool",
    "wof:placetype":"venue"
},
  "geometry": {"coordinates":[3.9409201145,51.1744804382],"type":"Point"}
}