{
  "type": "Feature",
  "properties": {
    "addr:full":"Anemonenlaan 20 Beringen (paal) Limburg 3583",
    "addr:housenumber":"20",
    "addr:postcode":"3583",
    "addr:street":"Anemonenlaan",
    "iso:country":"BE",
    "sg:address":"Anemonenlaan 20",
    "sg:city":"Beringen (paal)",
    "sg:classifiers":[
        {
            "category":"Home & Garden",
            "subcategory":"Home Furnishings",
            "type":"Retail Goods"
        }
    ],
    "sg:phone":"+32 11 43 11 12",
    "sg:postcode":"3583",
    "sg:province":"Limburg",
    "sg:tags":[
        "interior",
        "decoration"
    ],
    "wof:name":"B.n.d. Interieur",
    "wof:placetype":"venue"
},
  "geometry": {"coordinates":[5.1678857803,51.0485610962],"type":"Point"}
}