{
  "type": "Feature",
  "properties": {
    "addr:full":"Avenue Reine Astrid 11 Ottignies-louvain-la-neuve (ottignies) Brabant Wallon 1340",
    "addr:housenumber":"11",
    "addr:postcode":"ottignies-louvain-la-neuve;1340",
    "addr:street":"Avenue Reine Astrid",
    "iso:country":"BE",
    "sg:address":"Avenue Reine Astrid 11",
    "sg:city":"Ottignies-louvain-la-neuve (ottignies)",
    "sg:classifiers":[
        {
            "category":"Professional",
            "subcategory":"Testing Lab",
            "type":"Services"
        }
    ],
    "sg:phone":"+32 10 41 60 70",
    "sg:postcode":"1340",
    "sg:province":"Brabant Wallon",
    "sg:tags":[
        "chemist"
    ],
    "wof:name":"Tilkin C",
    "wof:placetype":"venue"
},
  "geometry": {"coordinates":[4.5690131187,50.6666793823],"type":"Point"}
}