{
  "type": "Feature",
  "properties": {
    "addr:full":"Rue Du Perron 202 Li\u00e8ge 1 (sclessin) Li\u00e8ge 4000",
    "addr:housenumber":"202;1",
    "addr:postcode":"4000",
    "addr:street":"Rue Du Perron;Sclessin Lie\u0300Ge",
    "iso:country":"BE",
    "sg:address":"Rue Du Perron 202",
    "sg:city":"Li\u00e8ge 1 (sclessin)",
    "sg:classifiers":[
        {
            "category":"Professional",
            "subcategory":"Testing Lab",
            "type":"Services"
        }
    ],
    "sg:phone":"+32 4 252 75 85",
    "sg:postcode":"4000",
    "sg:province":"Li\u00e8ge",
    "sg:tags":[
        "chemist"
    ],
    "wof:name":"Heynen A-m",
    "wof:placetype":"venue"
},
  "geometry": {"coordinates":[5.5575389862,50.619846344],"type":"Point"}
}