{
  "type": "Feature",
  "properties": {
    "addr:full":"Kastelsedijk 54 Dessel Antwerpen 2480",
    "addr:housenumber":"54",
    "addr:postcode":"2480",
    "addr:street":"Kastelsedijk",
    "iso:country":"BE",
    "sg:address":"Kastelsedijk 54",
    "sg:city":"Dessel",
    "sg:classifiers":[
        {
            "category":"Structure",
            "subcategory":"Building",
            "type":"Public Place"
        }
    ],
    "sg:phone":"+32 14 32 60 70",
    "sg:postcode":"2480",
    "sg:province":"Antwerpen",
    "sg:tags":[
        "door"
    ],
    "wof:name":"Hout Feyen Bvba",
    "wof:placetype":"venue"
},
  "geometry": {"coordinates":[5.0749912262,51.2324790955],"type":"Point"}
}