{
  "type": "Feature",
  "properties": {
    "iso:country":"BE",
    "sg:address":"Honsfeld 63",
    "sg:city":"B\u00dcllingen/bullange",
    "sg:orig_category":"Epiceries",
    "sg:phone":"+32 80 64 77 47",
    "sg:postcode":"4760",
    "sg:province":"Li\u00e8ge",
    "wof:name":"Theresia Kalpers",
    "wof:placetype":"venue"
},
  "geometry": {"coordinates":[6.2768030167,50.3808860779],"type":"Point"}
}