{
  "type": "Feature",
  "properties": {
    "iso:country":"BE",
    "sg:address":"Pepingensesteenweg 132",
    "sg:city":"Sint-pieters-leeuw",
    "sg:classifiers":[
        {
            "category":"Building & Trades",
            "subcategory":"Landscaping Services",
            "type":"Services"
        }
    ],
    "sg:phone":"+32 2 356 27 67",
    "sg:postcode":"1600",
    "sg:province":"Vlaams-Brabant",
    "sg:tags":[
        "forestry"
    ],
    "wof:name":"D'herde Michel Nv",
    "wof:placetype":"venue"
},
  "geometry": {"coordinates":[4.2374739647,50.7687759399],"type":"Point"}
}