{
  "type": "Feature",
  "properties": {
    "addr:full":"Rue De Bruxelles 21 Verviers Li\u00e8ge 4800",
    "addr:housenumber":"21",
    "addr:postcode":"4800",
    "addr:street":"Rue De Bruxelles",
    "iso:country":"BE",
    "sg:address":"Rue De Bruxelles 21",
    "sg:city":"Verviers",
    "sg:orig_category":"M\u00e9decins and sp\u00e9cialistes",
    "sg:phone":"+32 87 22 17 60",
    "sg:postcode":"4800",
    "sg:province":"Li\u00e8ge",
    "wof:name":"Raymond Boniver",
    "wof:placetype":"venue"
},
  "geometry": {"coordinates":[5.8555011749,50.5876998901],"type":"Point"}
}