{
  "type": "Feature",
  "properties": {
    "iso:country":"BE",
    "sg:address":"Gerhagenstraat 145",
    "sg:city":"Tessenderlo",
    "sg:classifiers":[
        {
            "category":"Health Services",
            "subcategory":"Health Practitioner",
            "type":"Services"
        }
    ],
    "sg:phone":"+32 13 67 38 17",
    "sg:postcode":"3980",
    "sg:province":"Limburg",
    "sg:tags":[
        "dietitian"
    ],
    "wof:name":"Verhaegen A",
    "wof:placetype":"venue"
},
  "geometry": {"coordinates":[5.058218956,51.0545845032],"type":"Point"}
}