{
  "type": "Feature",
  "properties": {
    "addr:full":"Loofstraat 22 Kortrijk West-Vlaanderen 8500",
    "addr:housenumber":"22",
    "addr:postcode":"8500",
    "addr:street":"Loofstraat",
    "iso:country":"BE",
    "sg:address":"Loofstraat 22",
    "sg:city":"Kortrijk",
    "sg:orig_category":"Fleurs and plantes",
    "sg:phone":"+32 56 22 21 50",
    "sg:postcode":"8500",
    "sg:province":"West-Vlaanderen",
    "wof:name":"Huis Bloemendaele",
    "wof:placetype":"venue"
},
  "geometry": {"coordinates":[3.2668299675,50.8194770813],"type":"Point"}
}