{
  "type": "Feature",
  "properties": {
    "iso:country":"BE",
    "sg:address":"Van Havermaetstraat 33",
    "sg:city":"Sint-niklaas",
    "sg:classifiers":[
        {
            "category":"Banks & Credit Unions",
            "subcategory":"Investment Brokerage",
            "type":"Services"
        }
    ],
    "sg:phone":"+32 3 776 13 13",
    "sg:postcode":"9100",
    "sg:province":"Oost-Vlaanderen",
    "sg:tags":[
        "printing",
        "-"
    ],
    "wof:name":"Printovit Nv",
    "wof:placetype":"venue"
},
  "geometry": {"coordinates":[4.1566319466,51.1711349487],"type":"Point"}
}