{
  "type": "Feature",
  "properties": {
    "addr:full":"Chauss\u00c9e De Fleurus 123 Charleroi Hainaut 6041",
    "addr:housenumber":"123",
    "addr:postcode":"6041",
    "addr:street":"Chausse\u0301E De Fleurus;Hainaut",
    "iso:country":"BE",
    "sg:address":"Chauss\u00c9e De Fleurus 123",
    "sg:city":"Charleroi",
    "sg:orig_category":"Articles de jardin. Quincailleries",
    "sg:phone":"+32 71 34 21 12",
    "sg:postcode":"6041",
    "sg:province":"Hainaut",
    "wof:name":"Libert Jardins & Loisirs",
    "wof:placetype":"venue"
},
  "geometry": {"coordinates":[4.4314317703,50.4685935974],"type":"Point"}
}