{
  "type": "Feature",
  "properties": {
    "iso:country":"BE",
    "sg:address":"Bungalowpark 1bb",
    "sg:city":"Hechtel-eksel",
    "sg:orig_category":"Dranken",
    "sg:phone":"+32 11 73 40 93",
    "sg:postcode":"3940",
    "sg:province":"Limburg",
    "wof:name":"Johan Dalemans",
    "wof:placetype":"venue"
},
  "geometry": {"coordinates":[5.3797931671,51.0936965942],"type":"Point"}
}