{
  "type": "Feature",
  "properties": {
    "iso:country":"BE",
    "sg:address":"Hallebaan 179",
    "sg:city":"Malle",
    "sg:orig_category":"Boekhouders",
    "sg:phone":"+32 3 309 30 12",
    "sg:postcode":"2390",
    "sg:province":"Antwerpen",
    "wof:name":"Marc Pelgrims",
    "wof:placetype":"venue"
},
  "geometry": {"coordinates":[4.6795091629,51.2828140259],"type":"Point"}
}