{
  "type": "Feature",
  "properties": {
    "addr:full":"Rue Grande Chenevi\u00c8re 101 Charleroi Hainaut 6001",
    "addr:housenumber":"101",
    "addr:postcode":"6001",
    "addr:street":"Rue Grande Chenevie\u0300Re;Hainaut",
    "iso:country":"BE",
    "sg:address":"Rue Grande Chenevi\u00c8re 101",
    "sg:city":"Charleroi",
    "sg:classifiers":[
        {
            "category":"Fast Food",
            "type":"Food & Drink"
        }
    ],
    "sg:phone":"+32 71 36 93 45",
    "sg:postcode":"6001",
    "sg:province":"Hainaut",
    "sg:tags":[
        "\u00c0",
        "restaurants",
        "emporter",
        "restaurant"
    ],
    "wof:name":"Restaurant L\u00b4adriatica",
    "wof:placetype":"venue"
},
  "geometry": {"coordinates":[4.4434552193,50.3882904053],"type":"Point"}
}