{
  "type": "Feature",
  "properties": {
    "iso:country":"BE",
    "sg:address":"Avenue Du Verseau 21",
    "sg:city":"Waterloo",
    "sg:orig_category":"Artsen and specialisten",
    "sg:phone":"+32 2 351 23 16",
    "sg:postcode":"1410",
    "sg:province":"Brabant Wallon",
    "wof:name":"K. Paul",
    "wof:placetype":"venue"
},
  "geometry": {"coordinates":[4.4139041901,50.7005882263],"type":"Point"}
}