{
  "type": "Feature",
  "properties": {
    "addr:full":"Goirleweg 2 Ravels (poppel) Antwerpen 2382",
    "addr:housenumber":"2",
    "addr:postcode":"2382",
    "addr:street":"Goirleweg",
    "iso:country":"BE",
    "sg:address":"Goirleweg 2",
    "sg:city":"Ravels (poppel)",
    "sg:classifiers":[
        {
            "category":"Autos & Motor Vehicles",
            "subcategory":"Automobile Sales",
            "type":"Retail Goods"
        }
    ],
    "sg:phone":"+32 14 65 80 34",
    "sg:postcode":"2382",
    "sg:province":"Antwerpen",
    "sg:tags":[
        "car",
        "used",
        "-"
    ],
    "wof:name":"Van Der Steen Willy Bvba",
    "wof:placetype":"venue"
},
  "geometry": {"coordinates":[5.041768074,51.4469108582],"type":"Point"}
}