{
  "type": "Feature",
  "properties": {
    "addr:full":"Rue De La Commune 52 Bruxelles (saint-josse-ten-noode) Bruxelles-Capitale 1210",
    "addr:housenumber":"52",
    "addr:postcode":"1210",
    "addr:street":"Rue De La Commune",
    "iso:country":"BE",
    "sg:address":"Rue De La Commune 52",
    "sg:city":"Bruxelles (saint-josse-ten-noode)",
    "sg:classifiers":[
        {
            "category":"Professional",
            "subcategory":"Advertising",
            "type":"Services"
        }
    ],
    "sg:phone":"+32 2 219 73 67",
    "sg:postcode":"1210",
    "sg:province":"Bruxelles-Capitale",
    "sg:tags":[
        "bill",
        "-",
        "posting"
    ],
    "wof:name":"City Clash",
    "wof:placetype":"venue"
},
  "geometry": {"coordinates":[4.3732910156,50.8521575928],"type":"Point"}
}