{
  "type": "Feature",
  "properties": {
    "addr:full":"Ma\u00efsstraat 4 Zelzate Oost-Vlaanderen 9060",
    "addr:housenumber":"4",
    "addr:postcode":"9060",
    "addr:street":"Mai\u0308Sstraat",
    "iso:country":"BE",
    "sg:address":"Ma\u00efsstraat 4",
    "sg:city":"Zelzate",
    "sg:classifiers":[
        {
            "category":"Communications",
            "subcategory":"Film & Video Production",
            "type":"Services"
        }
    ],
    "sg:phone":"+32 9 342 99 43",
    "sg:postcode":"9060",
    "sg:province":"Oost-Vlaanderen",
    "sg:tags":[
        "hiring",
        "-"
    ],
    "wof:name":"Videoland",
    "wof:placetype":"venue"
},
  "geometry": {"coordinates":[3.8251740932,51.1975212097],"type":"Point"}
}