{
  "type": "Feature",
  "properties": {
    "iso:country":"BE",
    "sg:address":"Victor Bocqu\u00e9straat 15",
    "sg:city":"Aalst",
    "sg:orig_category":"Autombile concessionaires",
    "sg:phone":"+32 53 78 31 13",
    "sg:postcode":"9300",
    "sg:province":"Oost-Vlaanderen",
    "wof:name":"Modern Aalst",
    "wof:placetype":"venue"
},
  "geometry": {"coordinates":[4.0379948616,50.9511680603],"type":"Point"}
}