{
  "type": "Feature",
  "properties": {
    "iso:country":"BE",
    "sg:address":"Kosterstr 209",
    "sg:city":"Machelen",
    "sg:classifiers":[
        {
            "category":"Banks & Credit Unions",
            "subcategory":"Financial Services",
            "type":"Services"
        }
    ],
    "sg:phone":"+32 2 722 77 77",
    "sg:postcode":"1831",
    "sg:province":"Vlaams-Brabant",
    "sg:tags":[
        "banking",
        "insurance",
        "institution",
        "finance"
    ],
    "wof:name":"Kbc Autolease Nv",
    "wof:placetype":"venue"
},
  "geometry": {"coordinates":[4.4381299019,50.8864517212],"type":"Point"}
}