{
  "type": "Feature",
  "properties": {
    "iso:country":"BE",
    "sg:address":"Ieperstraat 32",
    "sg:city":"Zonnebeke",
    "sg:classifiers":[
        {
            "category":"Building & Trades",
            "subcategory":"Plumbing",
            "type":"Services"
        }
    ],
    "sg:phone":"+32 51 77 71 98",
    "sg:postcode":"8980",
    "sg:province":"West-Vlaanderen",
    "sg:tags":[
        "contractor"
    ],
    "wof:name":"Muylle C",
    "wof:placetype":"venue"
},
  "geometry": {"coordinates":[2.9853758812,50.8713722229],"type":"Point"}
}