{
  "type": "Feature",
  "properties": {
    "addr:full":"Rue Hamoir 144 La Louviere Hainaut 7100",
    "addr:housenumber":"144",
    "addr:postcode":"7100",
    "addr:street":"Rue Hamoir",
    "iso:country":"BE",
    "sg:address":"Rue Hamoir 144",
    "sg:city":"La Louviere",
    "sg:orig_category":"M\u00e9decins and sp\u00e9cialistes",
    "sg:phone":"+32 64 22 27 23",
    "sg:postcode":"7100",
    "sg:province":"Hainaut",
    "wof:name":"Henri Lescart",
    "wof:placetype":"venue"
},
  "geometry": {"coordinates":[4.1947841644,50.4747390747],"type":"Point"}
}