{
  "type": "Feature",
  "properties": {
    "iso:country":"BE",
    "sg:address":"Rijselstraat 37",
    "sg:city":"Menen",
    "sg:classifiers":[
        {
            "category":"Shopping",
            "subcategory":"Luggage & Leather Goods",
            "type":"Retail Goods"
        }
    ],
    "sg:phone":"+32 56 51 20 99",
    "sg:postcode":"8930",
    "sg:province":"West-Vlaanderen",
    "sg:tags":[
        "-"
    ],
    "wof:name":"Eeckhout",
    "wof:placetype":"venue"
},
  "geometry": {"coordinates":[3.1220459938,50.7945785522],"type":"Point"}
}