{
  "type": "Feature",
  "properties": {
    "addr:full":"Boulevard Charlemagne 1 Box 24 Bruxelles Bruxelles-Capitale 1000",
    "addr:housenumber":"1 box 24",
    "addr:postcode":"1000",
    "addr:street":"Boulevard Charlemagne",
    "iso:country":"BE",
    "sg:address":"Boulevard Charlemagne 1 Box 24",
    "sg:city":"Bruxelles",
    "sg:classifiers":[
        {
            "category":"Communications",
            "subcategory":"News Services",
            "type":"Services"
        }
    ],
    "sg:phone":"+32 2 707 69 10",
    "sg:postcode":"1000",
    "sg:province":"Bruxelles-Capitale",
    "sg:tags":[
        "agency"
    ],
    "wof:name":"Anadolu Ajansi",
    "wof:placetype":"venue"
},
  "geometry": {"coordinates":[4.3823270798,50.8445777893],"type":"Point"}
}