{
  "type": "Feature",
  "properties": {
    "addr:full":"Rossemdorp 59 Meise Vlaams-Brabant 1861",
    "addr:housenumber":"59",
    "addr:postcode":"1861",
    "addr:street":"Rossemdorp",
    "iso:country":"BE",
    "sg:address":"Rossemdorp 59",
    "sg:city":"Meise",
    "sg:orig_category":"Groententeelt",
    "sg:phone":"+32 52 37 05 16",
    "sg:postcode":"1861",
    "sg:province":"Vlaams-Brabant",
    "wof:name":"Paul Maes",
    "wof:placetype":"venue"
},
  "geometry": {"coordinates":[4.2844748497,50.9760971069],"type":"Point"}
}