{
  "type": "Feature",
  "properties": {
    "iso:country":"BE",
    "sg:address":"Rue De Royenne 39",
    "sg:city":"Grez-doiceau",
    "sg:classifiers":[
        {
            "category":"Parking",
            "subcategory":"Garage",
            "type":"Transportation"
        }
    ],
    "sg:phone":"+32 10 84 52 94",
    "sg:postcode":"1390",
    "sg:province":"Brabant Wallon",
    "sg:tags":[
        "truck",
        "-",
        "dump",
        "transport"
    ],
    "wof:name":"Quintin Ch",
    "wof:placetype":"venue"
},
  "geometry": {"coordinates":[4.699783802,50.7184791565],"type":"Point"}
}