{
  "type": "Feature",
  "properties": {
    "iso:country":"BE",
    "sg:address":"Gasthuisvelden 17ba",
    "sg:city":"Sint-katelijne-waver",
    "sg:orig_category":"Groententeelt",
    "sg:phone":"+32 15 31 22 92",
    "sg:postcode":"2860",
    "sg:province":"Antwerpen",
    "wof:name":"Simonne Verbessem",
    "wof:placetype":"venue"
},
  "geometry": {"coordinates":[4.5542092323,51.0698242188],"type":"Point"}
}