{
  "type": "Feature",
  "properties": {
    "addr:full":"Aachener Strasse 1 Eupen Li\u00e8ge 4700",
    "addr:housenumber":"1",
    "addr:postcode":"4700",
    "addr:street":"Aachener Strasse",
    "iso:country":"BE",
    "sg:address":"Aachener Strasse 1",
    "sg:city":"Eupen",
    "sg:orig_category":"Herenkledingzaken",
    "sg:phone":"+32 87 74 21 51",
    "sg:postcode":"4700",
    "sg:province":"Li\u00e8ge",
    "wof:name":"Pankert Am Rathaus",
    "wof:placetype":"venue"
},
  "geometry": {"coordinates":[6.0307941437,50.6321868896],"type":"Point"}
}