{
  "type": "Feature",
  "properties": {
    "addr:full":"Paul Wemaerestraat 2 Sint-pieters-woluwe/woluwe-saint-pierre Bruxelles-Capitale 1150",
    "addr:housenumber":"2",
    "addr:postcode":"1150",
    "addr:street":"Paul Wemaerestraat;/",
    "iso:country":"BE",
    "sg:address":"Paul Wemaerestraat 2",
    "sg:city":"Sint-pieters-woluwe/woluwe-saint-pierre",
    "sg:orig_category":"Apotheken",
    "sg:phone":"+32 2 770 08 89",
    "sg:postcode":"1150",
    "sg:province":"Bruxelles-Capitale",
    "wof:name":"Medical Pharma",
    "wof:placetype":"venue"
},
  "geometry": {"coordinates":[4.431060791,50.8353767395],"type":"Point"}
}