{
  "type": "Feature",
  "properties": {
    "addr:full":"Rue Des Combattants 59 La Hulpe Brabant Wallon 1310",
    "addr:housenumber":"59",
    "addr:postcode":"1310",
    "addr:street":"Rue Des Combattants",
    "iso:country":"BE",
    "sg:address":"Rue Des Combattants 59",
    "sg:city":"La Hulpe",
    "sg:classifiers":[
        {
            "category":"Health Services",
            "subcategory":"Nursing And Care Facility",
            "type":"Services"
        }
    ],
    "sg:phone":"+32 2 529 41 20",
    "sg:postcode":"1310",
    "sg:province":"Brabant Wallon",
    "sg:tags":[
        "public"
    ],
    "wof:name":"Administration Communale",
    "wof:placetype":"venue"
},
  "geometry": {"coordinates":[4.4889822006,50.7312507629],"type":"Point"}
}