{
  "type": "Feature",
  "properties": {
    "iso:country":"BE",
    "sg:address":"Seb. Nachtegaelestraat 12",
    "sg:city":"Knokke-heist (knokke)",
    "sg:classifiers":[
        {
            "category":"Professional",
            "subcategory":"Testing Lab",
            "type":"Services"
        }
    ],
    "sg:phone":"+32 50 60 31 61",
    "sg:postcode":"8300",
    "sg:province":"West-Vlaanderen",
    "sg:tags":[
        "chemist"
    ],
    "wof:name":"Lippens H",
    "wof:placetype":"venue"
},
  "geometry": {"coordinates":[3.2886021137,51.340801239],"type":"Point"}
}