{
  "type": "Feature",
  "properties": {
    "iso:country":"BE",
    "sg:address":"Kapelstraat 55",
    "sg:city":"Kortessem",
    "sg:orig_category":"Paramedische behandelingen",
    "sg:phone":"+32 11 37 12 22",
    "sg:postcode":"3720",
    "sg:province":"Limburg",
    "wof:name":"Melisande Jeuris",
    "wof:placetype":"venue"
},
  "geometry": {"coordinates":[5.3823180199,50.8679084778],"type":"Point"}
}