{
  "type": "Feature",
  "properties": {
    "addr:full":"Mommestraat 71 Heusden-zolder Limburg 3550",
    "addr:housenumber":"71",
    "addr:postcode":"3550",
    "addr:street":"Mommestraat",
    "iso:country":"BE",
    "sg:address":"Mommestraat 71",
    "sg:city":"Heusden-zolder",
    "sg:orig_category":"HERSTELLING ELEKTRISCHE HUISHOUDAPPARATEN",
    "sg:phone":"+32 11 53 68 80",
    "sg:postcode":"3550",
    "sg:province":"Limburg",
    "wof:name":"Edgard Vangeel",
    "wof:placetype":"venue"
},
  "geometry": {"coordinates":[5.3221011162,51.0324325562],"type":"Point"}
}