{
  "type": "Feature",
  "properties": {
    "addr:full":"Abeelstraat 18 Ruiselede West-Vlaanderen 8755",
    "addr:housenumber":"18",
    "addr:postcode":"8755",
    "addr:street":"Abeelstraat",
    "iso:country":"BE",
    "sg:address":"Abeelstraat 18",
    "sg:city":"Ruiselede",
    "sg:orig_category":"Eleveurs de bovins. Eleveurs and marchands de porcs",
    "sg:phone":"+32 51 68 88 18",
    "sg:postcode":"8755",
    "sg:province":"West-Vlaanderen",
    "wof:name":"Marc Fraeyman",
    "wof:placetype":"venue"
},
  "geometry": {"coordinates":[3.3685090542,51.044254303],"type":"Point"}
}