{
  "type": "Feature",
  "properties": {
    "addr:full":"Tuinstraat 13 Melle Oost-Vlaanderen 9090",
    "addr:housenumber":"13",
    "addr:postcode":"9090",
    "addr:street":"Tuinstraat",
    "iso:country":"BE",
    "sg:address":"Tuinstraat 13",
    "sg:city":"Melle",
    "sg:classifiers":[
        {
            "category":"Health Services",
            "subcategory":"Doctor",
            "type":"Services"
        }
    ],
    "sg:phone":"+32 9 231 60 30",
    "sg:postcode":"9090",
    "sg:province":"Oost-Vlaanderen",
    "sg:tags":[
        "medicinephysicians",
        "surgeon"
    ],
    "wof:name":"De Gendt Guy",
    "wof:placetype":"venue"
},
  "geometry": {"coordinates":[3.7767410278,51.0186309814],"type":"Point"}
}