{
  "type": "Feature",
  "properties": {
    "addr:full":"Amersveldestraat 25 Hooglede West-Vlaanderen 8830",
    "addr:housenumber":"25",
    "addr:postcode":"8830",
    "addr:street":"Amersveldestraat",
    "iso:country":"BE",
    "sg:address":"Amersveldestraat 25",
    "sg:city":"Hooglede",
    "sg:orig_category":"Producteurs de l\u00e9gumes",
    "sg:phone":"+32 51 70 19 23",
    "sg:postcode":"8830",
    "sg:province":"West-Vlaanderen",
    "wof:name":"Sylvain Cordenier",
    "wof:placetype":"venue"
},
  "geometry": {"coordinates":[3.0637779236,50.999546051],"type":"Point"}
}