{
  "type": "Feature",
  "properties": {
    "iso:country":"BE",
    "sg:address":"Rue Des Tongres 12",
    "sg:city":"Etterbeek/etterbeek",
    "sg:orig_category":"V\u00eatements sur mesure Fab",
    "sg:phone":"+32 2 734 84 79",
    "sg:postcode":"1040",
    "sg:province":"Bruxelles-Capitale",
    "wof:name":"Cliff",
    "wof:placetype":"venue"
},
  "geometry": {"coordinates":[4.3993201256,50.839679718],"type":"Point"}
}