{
  "type": "Feature",
  "properties": {
    "addr:full":"Provinciale Steenweg 54 Schelle Antwerpen 2627",
    "addr:housenumber":"54",
    "addr:postcode":"2627",
    "addr:street":"Provinciale Steenweg",
    "iso:country":"BE",
    "sg:address":"Provinciale Steenweg 54",
    "sg:city":"Schelle",
    "sg:orig_category":"Postkantoren Verzekeringsmakelaars and experts",
    "sg:phone":"+32 3 887 47 92",
    "sg:postcode":"2627",
    "sg:province":"Antwerpen",
    "wof:name":"De Post",
    "wof:placetype":"venue"
},
  "geometry": {"coordinates":[4.3380661011,51.1281013489],"type":"Point"}
}