{
  "type": "Feature",
  "properties": {
    "addr:full":"Rue Du Pont Neuf 19b Charleroi Hainaut 6000",
    "addr:housenumber":"19b",
    "addr:postcode":"6000",
    "addr:street":"Rue Du Pont Neuf;Hainaut",
    "iso:country":"BE",
    "sg:address":"Rue Du Pont Neuf 19b",
    "sg:city":"Charleroi",
    "sg:classifiers":[
        {
            "category":"Personal",
            "subcategory":"Beauty Salon",
            "type":"Services"
        }
    ],
    "sg:phone":"+32 71 32 35 86",
    "sg:postcode":"6000",
    "sg:province":"Hainaut",
    "wof:name":"Miseur S",
    "wof:placetype":"venue"
},
  "geometry": {"coordinates":[4.4473819733,50.4075622559],"type":"Point"}
}