{
  "type": "Feature",
  "properties": {
    "addr:full":"Chauss\u00c9e D'ixelles 41 Elsene Bruxelles-Capitale 1050",
    "addr:housenumber":"41",
    "addr:postcode":"1050",
    "addr:street":"Chausse\u0301E D'Ixelles",
    "iso:country":"BE",
    "sg:address":"Chauss\u00c9e D'ixelles 41",
    "sg:city":"Elsene",
    "sg:orig_category":"Baby- and kinderkleding Dameskledingzaken Herenkledingzaken",
    "sg:phone":"+32 2 514 46 77",
    "sg:postcode":"1050",
    "sg:province":"Bruxelles-Capitale",
    "wof:name":"Hennes & Mauritz ( H&m)",
    "wof:placetype":"venue"
},
  "geometry": {"coordinates":[4.3624711037,50.8366546631],"type":"Point"}
}