{
  "type": "Feature",
  "properties": {
    "addr:full":"Kattenbos 6 Sint-lievens-houtem Oost-Vlaanderen 9520",
    "addr:housenumber":"6",
    "addr:postcode":"9520",
    "addr:street":"Kattenbos;Oost-Vlaanderen",
    "iso:country":"BE",
    "sg:address":"Kattenbos 6",
    "sg:city":"Sint-lievens-houtem",
    "sg:orig_category":"Groententeelt",
    "sg:phone":"+32 53 80 56 78",
    "sg:postcode":"9520",
    "sg:province":"Oost-Vlaanderen",
    "wof:name":"Paulus Roelandt",
    "wof:placetype":"venue"
},
  "geometry": {"coordinates":[3.9219710827,50.9440994263],"type":"Point"}
}