{
  "type": "Feature",
  "properties": {
    "iso:country":"BE",
    "sg:address":"Bld Fr\u00c8re Orban 1",
    "sg:city":"Li\u00c8ge",
    "sg:orig_category":"Artsen and specialisten",
    "sg:phone":"+32 4 222 32 67",
    "sg:postcode":"4000",
    "sg:province":"Li\u00e8ge",
    "wof:name":"Simone Elias",
    "wof:placetype":"venue"
},
  "geometry": {"coordinates":[5.5722341537,50.6357765198],"type":"Point"}
}