{
  "type": "Feature",
  "properties": {
    "iso:country":"BE",
    "sg:address":"Statiestraat 17a",
    "sg:city":"Nijlen",
    "sg:classifiers":[
        {
            "category":"Shopping",
            "subcategory":"Clothing, Apparel, & Fashions",
            "type":"Retail Goods"
        }
    ],
    "sg:phone":"+32 3 484 31 35",
    "sg:postcode":"2560",
    "sg:province":"Antwerpen",
    "sg:tags":[
        "underwear",
        "lingerie",
        "-"
    ],
    "wof:name":"Giovani",
    "wof:placetype":"venue"
},
  "geometry": {"coordinates":[4.6695809364,51.1607971191],"type":"Point"}
}