{
  "type": "Feature",
  "properties": {
    "addr:full":"Haanhoutstraat 37a Lochristi Oost-Vlaanderen 9080",
    "addr:housenumber":"37a",
    "addr:postcode":"9080",
    "addr:street":"Haanhoutstraat",
    "iso:country":"BE",
    "sg:address":"Haanhoutstraat 37a",
    "sg:city":"Lochristi",
    "sg:orig_category":"Plantes and fleurs Gr",
    "sg:phone":"+32 9 355 81 81",
    "sg:postcode":"9080",
    "sg:province":"Oost-Vlaanderen",
    "wof:name":"Smet E",
    "wof:placetype":"venue"
},
  "geometry": {"coordinates":[3.8680989742,51.0795516968],"type":"Point"}
}