{
  "type": "Feature",
  "properties": {
    "addr:full":"Avenue De La Belle Province 1 Braine L'alleud (braine-l'alleud) Brabant Wallon 1420",
    "addr:housenumber":"1",
    "addr:postcode":"1420",
    "addr:street":"Avenue De La Belle Province",
    "iso:country":"BE",
    "sg:address":"Avenue De La Belle Province 1",
    "sg:city":"Braine L'alleud (braine-l'alleud)",
    "sg:classifiers":[
        {
            "category":"Retail",
            "subcategory":"Auto Repair",
            "type":"Services"
        }
    ],
    "sg:phone":"+32 2 384 06 64",
    "sg:postcode":"1420",
    "sg:province":"Brabant Wallon",
    "sg:tags":[
        "garage"
    ],
    "wof:name":"Garage Fleuvy Sprl",
    "wof:placetype":"venue"
},
  "geometry": {"coordinates":[-91.9130020142,40.1174087524],"type":"Point"}
}