{
  "type": "Feature",
  "properties": {
    "addr:full":"Brugsesteenweg 333 Roeselare West-Vlaanderen 8800",
    "addr:housenumber":"333",
    "addr:postcode":"8800",
    "addr:street":"Brugsesteenweg",
    "iso:country":"BE",
    "sg:address":"Brugsesteenweg 333",
    "sg:city":"Roeselare",
    "sg:classifiers":[
        {
            "category":"Autos & Motor Vehicles",
            "subcategory":"Automobile Sales",
            "type":"Retail Goods"
        }
    ],
    "sg:phone":"+32 51 22 93 99",
    "sg:postcode":"8800",
    "sg:province":"West-Vlaanderen",
    "sg:tags":[
        "equipment",
        "motor-cars",
        "transport"
    ],
    "wof:name":"Garage Plancke-deketelaere Bvba",
    "wof:placetype":"venue"
},
  "geometry": {"coordinates":[3.1202919483,50.9662704468],"type":"Point"}
}