{
  "type": "Feature",
  "properties": {
    "iso:country":"BE",
    "sg:address":"Kouterstraat 16",
    "sg:city":"Zele",
    "sg:orig_category":"Pain, p\u00e2tisseries and confiseries",
    "sg:phone":"+32 52 44 42 53",
    "sg:postcode":"9240",
    "sg:province":"Oost-Vlaanderen",
    "wof:name":"Bakkerij Van Cauteren",
    "wof:placetype":"venue"
},
  "geometry": {"coordinates":[4.0334410667,51.0662536621],"type":"Point"}
}