{
  "type": "Feature",
  "properties": {
    "addr:full":"Chauss\u00e9e De Willemeau 177 Tournai Hainaut 7500",
    "addr:housenumber":"177",
    "addr:postcode":"7500",
    "addr:street":"Chausse\u0301E De Willemeau",
    "iso:country":"BE",
    "sg:address":"Chauss\u00e9e De Willemeau 177",
    "sg:city":"Tournai",
    "sg:classifiers":[
        {
            "category":"Arts & Performance",
            "subcategory":"Art Gallery",
            "type":"Entertainment"
        }
    ],
    "sg:phone":"+32 69 21 20 01",
    "sg:postcode":"7500",
    "sg:province":"Hainaut",
    "sg:tags":[
        "photoengravers"
    ],
    "wof:name":"Delhaie",
    "wof:placetype":"venue"
},
  "geometry": {"coordinates":[3.376390934,50.5938949585],"type":"Point"}
}