{
  "type": "Feature",
  "properties": {
    "addr:full":"Rue De Nalinnes 499 Charleroi (marcinelle) Hainaut 6001",
    "addr:housenumber":"499",
    "addr:postcode":"6001",
    "addr:street":"Rue De Nalinnes",
    "iso:country":"BE",
    "sg:address":"Rue De Nalinnes 499",
    "sg:city":"Charleroi (marcinelle)",
    "sg:classifiers":[
        {
            "category":"Parking",
            "subcategory":"Garage",
            "type":"Transportation"
        }
    ],
    "sg:phone":"+32 71 38 83 99",
    "sg:postcode":"6001",
    "sg:province":"Hainaut",
    "sg:tags":[
        "truck",
        "-",
        "dump",
        "transport"
    ],
    "wof:name":"Dutron (transport) Sprl",
    "wof:placetype":"venue"
},
  "geometry": {"coordinates":[4.4367990494,50.3685417175],"type":"Point"}
}