{
  "type": "Feature",
  "properties": {
    "addr:full":"All\u00c9e Des Renards 36 Profondeville Namur 5170",
    "addr:housenumber":"36",
    "addr:postcode":"5170",
    "addr:street":"Alle\u0301E Des Renards",
    "iso:country":"BE",
    "sg:address":"All\u00c9e Des Renards 36",
    "sg:city":"Profondeville",
    "sg:orig_category":"Boekhouders",
    "sg:phone":"+32 81 41 32 17",
    "sg:postcode":"5170",
    "sg:province":"Namur",
    "wof:name":"Alain Steinier",
    "wof:placetype":"venue"
},
  "geometry": {"coordinates":[4.8621668816,50.3881149292],"type":"Point"}
}