{
  "type": "Feature",
  "properties": {
    "iso:country":"BE",
    "sg:address":"Ichtegemstraat 143",
    "sg:city":"Koekelare",
    "sg:classifiers":[
        {
            "category":"Food & Beverages",
            "subcategory":"Fruits & Vegetables",
            "type":"Retail Goods"
        }
    ],
    "sg:phone":"+32 51 58 11 28",
    "sg:postcode":"8680",
    "sg:province":"West-Vlaanderen",
    "sg:tags":[
        "groenten"
    ],
    "wof:name":"Huis Domino",
    "wof:placetype":"venue"
},
  "geometry": {"coordinates":[2.9975349903,51.091293335],"type":"Point"}
}