{
  "type": "Feature",
  "properties": {
    "addr:full":"Jozef Reusenslei 66 Borsbeek Antwerpen 2150",
    "addr:housenumber":"66",
    "addr:postcode":"2150",
    "addr:street":"Jozef Reusenslei",
    "iso:country":"BE",
    "sg:address":"Jozef Reusenslei 66",
    "sg:city":"Borsbeek",
    "sg:orig_category":"Domotics",
    "sg:phone":"+32 3 322 56 09",
    "sg:postcode":"2150",
    "sg:province":"Antwerpen",
    "wof:name":"Delafaille",
    "wof:placetype":"venue"
},
  "geometry": {"coordinates":[4.4887890816,51.1949996948],"type":"Point"}
}