{
  "type": "Feature",
  "properties": {
    "iso:country":"BE",
    "sg:address":"Vrijheid 203-205",
    "sg:city":"Hoogstraten",
    "sg:classifiers":[
        {
            "category":"Shopping",
            "subcategory":"Clothing, Apparel, & Fashions",
            "type":"Retail Goods"
        }
    ],
    "sg:phone":"+32 3 314 58 44",
    "sg:postcode":"2320",
    "sg:province":"Antwerpen",
    "sg:tags":[
        "boutique"
    ],
    "wof:name":"De Backker Nv",
    "wof:placetype":"venue"
},
  "geometry": {"coordinates":[4.7602062225,51.39894104],"type":"Point"}
}