{
  "type": "Feature",
  "properties": {
    "iso:country":"BE",
    "sg:address":"Dorpsstraat 28",
    "sg:city":"Lummen",
    "sg:orig_category":"Chaussures. Maroquinerie and articles de voyage",
    "sg:phone":"+32 13 52 13 05",
    "sg:postcode":"3560",
    "sg:province":"Limburg",
    "wof:name":"Fantasia",
    "wof:placetype":"venue"
},
  "geometry": {"coordinates":[5.1937689781,50.987361908],"type":"Point"}
}