{
  "type": "Feature",
  "properties": {
    "iso:country":"BE",
    "sg:address":"Schorsemolenstraat 78",
    "sg:city":"Sint-katelijne-waver",
    "sg:orig_category":"Woningbouw",
    "sg:phone":"+32 15 55 25 09",
    "sg:postcode":"2860",
    "sg:province":"Antwerpen",
    "wof:name":"Van Dievel Gebrs",
    "wof:placetype":"venue"
},
  "geometry": {"coordinates":[4.5093951225,51.0405502319],"type":"Point"}
}