{
  "type": "Feature",
  "properties": {
    "addr:full":"Steenweg 95 Zwalm Oost-Vlaanderen 9630",
    "addr:housenumber":"95",
    "addr:postcode":"9630",
    "addr:street":"Steenweg;Oost-Vlaanderen",
    "iso:country":"BE",
    "sg:address":"Steenweg 95",
    "sg:city":"Zwalm",
    "sg:orig_category":"Installatie van houten of kunststof schrijnwerk",
    "sg:phone":"+32 55 49 81 20",
    "sg:postcode":"9630",
    "sg:province":"Oost-Vlaanderen",
    "wof:name":"Patrick Monsecour",
    "wof:placetype":"venue"
},
  "geometry": {"coordinates":[3.7493460178,50.8903503418],"type":"Point"}
}