{
  "type": "Feature",
  "properties": {
    "addr:full":"Oudstrijderslei 18 Brasschaat Antwerpen 2930",
    "addr:housenumber":"18",
    "addr:postcode":"2930",
    "addr:street":"Oudstrijderslei",
    "iso:country":"BE",
    "sg:address":"Oudstrijderslei 18",
    "sg:city":"Brasschaat",
    "sg:orig_category":"Huishoudapparaten, televisies and radio's",
    "sg:phone":"+32 3 644 22 75",
    "sg:postcode":"2930",
    "sg:province":"Antwerpen",
    "wof:name":"Hugo Van Praag",
    "wof:placetype":"venue"
},
  "geometry": {"coordinates":[4.466782093,51.2752342224],"type":"Point"}
}