{
  "type": "Feature",
  "properties": {
    "addr:full":"Rue L\u00c9on Colleaux 9 Virton Luxembourg 6762",
    "addr:housenumber":"9",
    "addr:postcode":"6762",
    "addr:street":"Rue Le\u0301On Colleaux",
    "iso:country":"BE",
    "sg:address":"Rue L\u00c9on Colleaux 9",
    "sg:city":"Virton",
    "sg:orig_category":"Auto-\u00e9coles",
    "sg:phone":"+32 63 57 95 45",
    "sg:postcode":"6762",
    "sg:province":"Luxembourg",
    "wof:name":"Auto-ecole Des Ardennes",
    "wof:placetype":"venue"
},
  "geometry": {"coordinates":[5.5300970078,49.5559272766],"type":"Point"}
}