{
  "type": "Feature",
  "properties": {
    "addr:full":"Diksmuidestraat 43 Middelkerke West-Vlaanderen 8433",
    "addr:housenumber":"43",
    "addr:postcode":"8433",
    "addr:street":"Diksmuidestraat",
    "iso:country":"BE",
    "sg:address":"Diksmuidestraat 43",
    "sg:city":"Middelkerke",
    "sg:orig_category":"Rundveehouders Varkenskwekers",
    "sg:phone":"+32 59 27 89 66",
    "sg:postcode":"8433",
    "sg:province":"West-Vlaanderen",
    "wof:name":"Gerard Aernoudt",
    "wof:placetype":"venue"
},
  "geometry": {"coordinates":[2.8860800266,51.1183242798],"type":"Point"}
}