{
  "type": "Feature",
  "properties": {
    "addr:full":"Rijschootstraat 39a Evergem Oost-Vlaanderen 9940",
    "addr:housenumber":"39a",
    "addr:postcode":"9940",
    "addr:street":"Rijschootstraat;Oost-Vlaanderen",
    "iso:country":"BE",
    "sg:address":"Rijschootstraat 39a",
    "sg:city":"Evergem",
    "sg:orig_category":"Bloemen and planten Gh",
    "sg:phone":"+32 9 344 51 63",
    "sg:postcode":"9940",
    "sg:province":"Oost-Vlaanderen",
    "wof:name":"Indica",
    "wof:placetype":"venue"
},
  "geometry": {"coordinates":[3.7419888973,51.1915512085],"type":"Point"}
}