{
  "type": "Feature",
  "properties": {
    "addr:full":"Grote Baan 151b Aalst (herdersem) Oost-Vlaanderen 9310",
    "addr:housenumber":"151b",
    "addr:postcode":"9310",
    "addr:street":"Grote Baan",
    "iso:country":"BE",
    "sg:address":"Grote Baan 151b",
    "sg:city":"Aalst (herdersem)",
    "sg:classifiers":[
        {
            "category":"Professional",
            "subcategory":"Accounting & Tax Preparation",
            "type":"Services"
        }
    ],
    "sg:phone":"+32 53 77 07 42",
    "sg:postcode":"9310",
    "sg:province":"Oost-Vlaanderen",
    "sg:tags":[
        "bookkeeper"
    ],
    "wof:name":"Paelstermans P",
    "wof:placetype":"venue"
},
  "geometry": {"coordinates":[4.0641651154,50.968372345],"type":"Point"}
}