{
  "type": "Feature",
  "properties": {
    "iso:country":"BE",
    "sg:address":"Keibergstraat 119",
    "sg:city":"Ichtegem",
    "sg:orig_category":"Sportclubs",
    "sg:phone":"+32 51 58 89 26",
    "sg:postcode":"8480",
    "sg:province":"West-Vlaanderen",
    "wof:name":"M.c. Ichtegem",
    "wof:placetype":"venue"
},
  "geometry": {"coordinates":[3.0299038887,51.0829391479],"type":"Point"}
}