{
  "type": "Feature",
  "properties": {
    "addr:full":"Galerie De La Reine 30 Brussel/bruxelles Bruxelles-Capitale 1000",
    "addr:housenumber":"30",
    "addr:postcode":"1000",
    "addr:street":"Galerie De La Reine;/",
    "iso:country":"BE",
    "sg:address":"Galerie De La Reine 30",
    "sg:city":"Brussel/bruxelles",
    "sg:classifiers":[
        {
            "category":"Fast Food",
            "type":"Food & Drink"
        }
    ],
    "sg:phone":"+32 2 512 37 31",
    "sg:postcode":"1000",
    "sg:province":"Bruxelles-Capitale",
    "sg:tags":[
        "\u00c0",
        "restaurants",
        "emporter",
        "restaurant"
    ],
    "wof:name":"Taverne Du Passage",
    "wof:placetype":"venue"
},
  "geometry": {"coordinates":[4.3513898849,50.8584594727],"type":"Point"}
}