{
  "type": "Feature",
  "properties": {
    "addr:full":"Kaphaanlei 36 Mortsel Antwerpen 2640",
    "addr:housenumber":"36",
    "addr:postcode":"2640",
    "addr:street":"Kaphaanlei",
    "iso:country":"BE",
    "sg:address":"Kaphaanlei 36",
    "sg:city":"Mortsel",
    "sg:orig_category":"Woningbouw",
    "sg:phone":"+32 3 455 41 60",
    "sg:postcode":"2640",
    "sg:province":"Antwerpen",
    "wof:name":"Petrus Kerremans",
    "wof:placetype":"venue"
},
  "geometry": {"coordinates":[4.4732608795,51.1672554016],"type":"Point"}
}