{
  "type": "Feature",
  "properties": {
    "iso:country":"BE",
    "sg:address":"Jonkersweg 1",
    "sg:city":"Maaseik",
    "sg:orig_category":"Diensten voor huisdieren",
    "sg:phone":"+32 89 86 66 96",
    "sg:postcode":"3680",
    "sg:province":"Limburg",
    "wof:name":"'t Zwervertje",
    "wof:placetype":"venue"
},
  "geometry": {"coordinates":[5.791285038,51.0954208374],"type":"Point"}
}