{
  "type": "Feature",
  "properties": {
    "iso:country":"BE",
    "sg:address":"Paul Van Roosbroecklaan 14",
    "sg:city":"Heist-op-den-berg",
    "sg:orig_category":"Pain, p\u00e2tisseries and confiseries. Eclairage et \u00e9quipements du foyer",
    "sg:phone":"+32 15 25 05 64",
    "sg:postcode":"2220",
    "sg:province":"Antwerpen",
    "wof:name":"Walter Van Eynde",
    "wof:placetype":"venue"
},
  "geometry": {"coordinates":[4.7248730659,51.0721092224],"type":"Point"}
}