{
  "type": "Feature",
  "properties": {
    "addr:full":"All\u00c9e Des Artisans 29 Ciney (grand) Namur 5590",
    "addr:housenumber":"29",
    "addr:postcode":"5590",
    "addr:street":"Alle\u0301E Des Artisans",
    "iso:country":"BE",
    "sg:address":"All\u00c9e Des Artisans 29",
    "sg:city":"Ciney (grand)",
    "sg:orig_category":"Catering and organisatie van feesten Ruimtes voor conferenties, recepties and feesten",
    "sg:phone":"+32 85 61 22 22",
    "sg:postcode":"5590",
    "sg:province":"Namur",
    "wof:name":"Traiteur Pierre Paulus",
    "wof:placetype":"venue"
},
  "geometry": {"coordinates":[5.1070361137,50.3111114502],"type":"Point"}
}