{
  "type": "Feature",
  "properties": {
    "addr:full":"Ardooisewegel 4 Roeselare West-Vlaanderen 8800",
    "addr:housenumber":"4",
    "addr:postcode":"8800",
    "addr:street":"Ardooisewegel",
    "iso:country":"BE",
    "sg:address":"Ardooisewegel 4",
    "sg:city":"Roeselare",
    "sg:classifiers":[
        {
            "category":"Banks & Credit Unions",
            "subcategory":"Investment Brokerage",
            "type":"Services"
        }
    ],
    "sg:phone":"+32 51 22 10 00",
    "sg:postcode":"8800",
    "sg:province":"West-Vlaanderen",
    "sg:tags":[
        "diver",
        "aux",
        "animation",
        "entreprises",
        "diverses"
    ],
    "wof:name":"Serge Gobin Produkties",
    "wof:placetype":"venue"
},
  "geometry": {"coordinates":[3.1628570557,50.9479217529],"type":"Point"}
}