{
  "type": "Feature",
  "properties": {
    "iso:country":"BE",
    "sg:address":"Lar 40",
    "sg:city":"Menen",
    "sg:orig_category":"Diverse bedrijfsbeheeradviesbureaus",
    "sg:phone":"+32 56 40 24 68",
    "sg:postcode":"8500",
    "sg:province":"West-Vlaanderen",
    "wof:name":"Iyalraod",
    "wof:placetype":"venue"
},
  "geometry": {"coordinates":[3.2650549412,50.827999115],"type":"Point"}
}