{
  "type": "Feature",
  "properties": {
    "iso:country":"BE",
    "sg:address":"Grote-edestraat 32",
    "sg:city":"Blankenberge",
    "sg:orig_category":"Services de Nettoyage and de D\u00e9sinfection. Blanchisserie, Nettoyage \u00e0 Sec and Salons-Lavoirs",
    "sg:phone":"+32 50 42 64 25",
    "sg:postcode":"8370",
    "sg:province":"West-Vlaanderen",
    "wof:name":"Schoonmaakbedrijf F En L",
    "wof:placetype":"venue"
},
  "geometry": {"coordinates":[3.1172819138,51.3072814941],"type":"Point"}
}