{
  "type": "Feature",
  "properties": {
    "iso:country":"BE",
    "sg:address":"Toleindestraat 20",
    "sg:city":"Lochristi (beervelde)",
    "sg:classifiers":[
        {
            "category":"Retail",
            "subcategory":"Event Space",
            "type":"Services"
        }
    ],
    "sg:phone":"+32 9 355 52 39",
    "sg:postcode":"9080",
    "sg:province":"Oost-Vlaanderen",
    "sg:tags":[
        "rental",
        "-",
        "hall"
    ],
    "wof:name":"Feestpaleis Nv",
    "wof:placetype":"venue"
},
  "geometry": {"coordinates":[3.8825919628,51.0800476074],"type":"Point"}
}