{
  "type": "Feature",
  "properties": {
    "iso:country":"BE",
    "sg:address":"Weg Naar As 27",
    "sg:city":"Genk",
    "sg:classifiers":[
        {
            "category":"Professional",
            "subcategory":"Management & Consulting",
            "type":"Services"
        }
    ],
    "sg:phone":"+32 89 35 69 61",
    "sg:postcode":"3600",
    "sg:province":"Limburg",
    "sg:tags":[
        "tax-consultants"
    ],
    "wof:name":"Vermeulen G",
    "wof:placetype":"venue"
},
  "geometry": {"coordinates":[5.5340800285,50.982219696],"type":"Point"}
}