{
  "type": "Feature",
  "properties": {
    "iso:country":"BE",
    "sg:address":"Prins Boudewijnlaan",
    "sg:city":"Kontich",
    "sg:orig_category":"Electric transformers, rectifiers, converters",
    "sg:phone":"+32 3 458 57 86",
    "sg:postcode":"2550",
    "sg:province":"Antwerpen",
    "wof:name":"G.m.e.",
    "wof:placetype":"venue"
},
  "geometry": {"coordinates":[4.4381151199,51.1396064758],"type":"Point"}
}