{
  "type": "Feature",
  "properties": {
    "addr:full":"Avenue D'auderghem 172 Bruxelles (etterbeek) Bruxelles-Capitale 1040",
    "addr:housenumber":"172",
    "addr:postcode":"1040",
    "addr:street":"Avenue D'Auderghem",
    "iso:country":"BE",
    "sg:address":"Avenue D'auderghem 172",
    "sg:city":"Bruxelles (etterbeek)",
    "sg:classifiers":[
        {
            "category":"Health Services",
            "subcategory":"Dentist",
            "type":"Services"
        }
    ],
    "sg:phone":"+32 2 736 03 92",
    "sg:postcode":"1040",
    "sg:province":"Bruxelles-Capitale",
    "wof:name":"Thys I",
    "wof:placetype":"venue"
},
  "geometry": {"coordinates":[4.3876729012,50.83568573],"type":"Point"}
}