{
  "type": "Feature",
  "properties": {
    "addr:full":"Boulevard Anspach 132-134 Bruxelles Bruxelles-Capitale 1000",
    "addr:postcode":"132-134;1000",
    "addr:street":"Boulevard Anspach",
    "iso:country":"BE",
    "sg:address":"Boulevard Anspach 132-134",
    "sg:city":"Bruxelles",
    "sg:classifiers":[
        {
            "category":"Shopping",
            "subcategory":"Clothing, Apparel, & Fashions",
            "type":"Retail Goods"
        }
    ],
    "sg:phone":"+32 2 513 09 95",
    "sg:postcode":"1000",
    "sg:province":"Bruxelles-Capitale",
    "sg:tags":[
        "lady",
        "clothing",
        "-"
    ],
    "wof:name":"Mony",
    "wof:placetype":"venue"
},
  "geometry": {"coordinates":[4.3483128548,50.8467521667],"type":"Point"}
}