{
  "type": "Feature",
  "properties": {
    "addr:full":"Rue Baron De Laveleye 46 Jette Bruxelles-Capitale 1090",
    "addr:housenumber":"46",
    "addr:postcode":"1090",
    "addr:street":"Rue Baron De Laveleye",
    "iso:country":"BE",
    "sg:address":"Rue Baron De Laveleye 46",
    "sg:city":"Jette",
    "sg:orig_category":"Artsen and specialisten",
    "sg:phone":"+32 2 476 21 72",
    "sg:postcode":"1090",
    "sg:province":"Bruxelles-Capitale",
    "wof:name":"Steppe",
    "wof:placetype":"venue"
},
  "geometry": {"coordinates":[4.3352918625,50.8743247986],"type":"Point"}
}