{
  "type": "Feature",
  "properties": {
    "addr:full":"Avenue Du Parc 30 Herve Li\u00e8ge 4650",
    "addr:housenumber":"30",
    "addr:postcode":"4650",
    "addr:street":"Avenue Du Parc",
    "iso:country":"BE",
    "sg:address":"Avenue Du Parc 30",
    "sg:city":"Herve",
    "sg:orig_category":"Transports routiers de marchandises. Agences d'exp\u00e9dition",
    "sg:phone":"+32 87 34 04 11",
    "sg:postcode":"4650",
    "sg:province":"Li\u00e8ge",
    "wof:name":"P. & O. Trans European",
    "wof:placetype":"venue"
},
  "geometry": {"coordinates":[5.8393688202,50.6253242493],"type":"Point"}
}