{
  "type": "Feature",
  "properties": {
    "addr:full":". Jalhay (groot) Li\u00e8ge 4845",
    "addr:postcode":"4845",
    "addr:street":"Groot Lie\u0300Ge",
    "iso:country":"BE",
    "sg:address":".",
    "sg:city":"Jalhay (groot)",
    "sg:orig_category":"Apotheken",
    "sg:phone":"+32 900 10 500",
    "sg:postcode":"4845",
    "sg:province":"Li\u00e8ge",
    "wof:name":"Apothekers Van Wacht",
    "wof:placetype":"venue"
},
  "geometry": {"coordinates":[5.9721851349,50.5571899414],"type":"Point"}
}