{
  "type": "Feature",
  "properties": {
    "addr:full":"Rue Du Ch\u00c2teau 54 Beloeil Hainaut 7970",
    "addr:housenumber":"54",
    "addr:postcode":"7970",
    "addr:street":"Rue Du Cha\u0302Teau",
    "iso:country":"BE",
    "sg:address":"Rue Du Ch\u00c2teau 54",
    "sg:city":"Beloeil",
    "sg:orig_category":"Boekhandels",
    "sg:phone":"+32 69 68 87 15",
    "sg:postcode":"7970",
    "sg:province":"Hainaut",
    "wof:name":"Librairie De Beloeil",
    "wof:placetype":"venue"
},
  "geometry": {"coordinates":[3.7347259521,50.5488243103],"type":"Point"}
}