{
  "type": "Feature",
  "properties": {
    "addr:full":"Dendermondebaan 226 Zele Oost-Vlaanderen 9240",
    "addr:housenumber":"226",
    "addr:postcode":"9240",
    "iso:country":"BE",
    "sg:address":"Dendermondebaan 226",
    "sg:city":"Zele",
    "sg:classifiers":[
        {
            "category":"Retail",
            "subcategory":"Auto Repair",
            "type":"Services"
        }
    ],
    "sg:phone":"+32 52 44 43 29",
    "sg:postcode":"9240",
    "sg:province":"Oost-Vlaanderen",
    "sg:tags":[
        "garage"
    ],
    "wof:name":"Symoens S",
    "wof:placetype":"venue"
},
  "geometry": {"coordinates":[4.0522837639,51.0629997253],"type":"Point"}
}