{
  "type": "Feature",
  "properties": {
    "addr:full":"Enneven 3 Lommel Limburg 3920",
    "addr:housenumber":"3",
    "addr:postcode":"3920",
    "addr:street":"Enneven",
    "iso:country":"BE",
    "sg:address":"Enneven 3",
    "sg:city":"Lommel",
    "sg:classifiers":[
        {
            "category":"Home & Garden",
            "subcategory":"Home Furnishings",
            "type":"Retail Goods"
        }
    ],
    "sg:phone":"+32 11 54 05 14",
    "sg:postcode":"3920",
    "sg:province":"Limburg",
    "sg:tags":[
        "wallpaper",
        "-"
    ],
    "wof:name":"Van Den Boer J",
    "wof:placetype":"venue"
},
  "geometry": {"coordinates":[5.3402161598,51.2318077087],"type":"Point"}
}