{
  "type": "Feature",
  "properties": {
    "addr:full":"Rue De Flandre 19 Bruxelles Bruxelles-Capitale 1000",
    "addr:housenumber":"19",
    "addr:postcode":"1000",
    "addr:street":"Rue De Flandre",
    "iso:country":"BE",
    "sg:address":"Rue De Flandre 19",
    "sg:city":"Bruxelles",
    "sg:classifiers":[
        {
            "category":"Personal",
            "subcategory":"Beauty Salon",
            "type":"Services"
        }
    ],
    "sg:phone":"+32 2 511 97 79",
    "sg:postcode":"1000",
    "sg:province":"Bruxelles-Capitale",
    "sg:tags":[
        "lady",
        "-",
        "hairdressing"
    ],
    "wof:name":"Infrastructure",
    "wof:placetype":"venue"
},
  "geometry": {"coordinates":[4.3469028473,50.8510513306],"type":"Point"}
}