{
  "type": "Feature",
  "properties": {
    "addr:full":"Rue De Houffalize 8 Houffalize Luxembourg 6660",
    "addr:housenumber":"8",
    "addr:postcode":"6660",
    "addr:street":"Rue De Houffalize",
    "iso:country":"BE",
    "sg:address":"Rue De Houffalize 8",
    "sg:city":"Houffalize",
    "sg:orig_category":"Slagers",
    "sg:phone":"+32 84 44 41 07",
    "sg:postcode":"6660",
    "sg:province":"Luxembourg",
    "wof:name":"Vincent Collin",
    "wof:placetype":"venue"
},
  "geometry": {"coordinates":[5.7902050018,50.1322784424],"type":"Point"}
}