{
  "type": "Feature",
  "properties": {
    "addr:full":"Christinastraat 78 Oostende West-Vlaanderen 8400",
    "addr:housenumber":"78",
    "addr:postcode":"8400",
    "addr:street":"Christinastraat",
    "iso:country":"BE",
    "sg:address":"Christinastraat 78",
    "sg:city":"Oostende",
    "sg:orig_category":"Pain, p\u00e2tisseries and confiseries",
    "sg:phone":"+32 59 70 41 72",
    "sg:postcode":"8400",
    "sg:province":"West-Vlaanderen",
    "wof:name":"Andre Devisch",
    "wof:placetype":"venue"
},
  "geometry": {"coordinates":[2.9176719189,51.2304573059],"type":"Point"}
}