{
  "type": "Feature",
  "properties": {
    "addr:full":"Kioskplaats 54 Antwerpen Antwerpen 2660",
    "addr:housenumber":"54",
    "addr:postcode":"2660",
    "addr:street":"Kioskplaats",
    "iso:country":"BE",
    "sg:address":"Kioskplaats 54",
    "sg:city":"Antwerpen",
    "sg:classifiers":[
        {
            "category":"Restaurant",
            "type":"Food & Drink"
        }
    ],
    "sg:phone":"+32 3 828 04 48",
    "sg:postcode":"2660",
    "sg:province":"Antwerpen",
    "wof:name":"Patrasche",
    "wof:placetype":"venue"
},
  "geometry": {"coordinates":[4.3397898674,51.1732788086],"type":"Point"}
}