{
  "type": "Feature",
  "properties": {
    "addr:full":"Avenue De La Paix 25-31 Rhode-saint-gen\u00e8se Vlaams-Brabant 1640",
    "addr:postcode":"25-31;1640",
    "addr:street":"Avenue De La Paix",
    "iso:country":"BE",
    "sg:address":"Avenue De La Paix 25-31",
    "sg:city":"Rhode-saint-gen\u00e8se",
    "sg:classifiers":[
        {
            "category":"Education",
            "subcategory":"School",
            "type":"Public Place"
        }
    ],
    "sg:phone":"+32 2 358 34 44",
    "sg:postcode":"1640",
    "sg:province":"Vlaams-Brabant",
    "sg:tags":[
        "primary"
    ],
    "wof:name":"Ecole De La Paix",
    "wof:placetype":"venue"
},
  "geometry": {"coordinates":[4.3904380798,50.7415122986],"type":"Point"}
}