{
  "type": "Feature",
  "properties": {
    "iso:country":"BE",
    "sg:address":"Manderfeld 101b",
    "sg:city":"B\u00fcllingen (manderfeld)",
    "sg:classifiers":[
        {
            "category":"Retail",
            "subcategory":"Auto Repair",
            "type":"Services"
        }
    ],
    "sg:phone":"+32 80 54 86 66",
    "sg:postcode":"4760",
    "sg:province":"Li\u00e8ge",
    "sg:tags":[
        "garage"
    ],
    "wof:name":"Adler F",
    "wof:placetype":"venue"
},
  "geometry": {"coordinates":[6.3412599564,50.3308792114],"type":"Point"}
}