{
  "type": "Feature",
  "properties": {
    "addr:full":"Leieweg 14 Kortrijk (marke) West-Vlaanderen 8510",
    "addr:housenumber":"14",
    "addr:postcode":"8510",
    "addr:street":"Leieweg",
    "iso:country":"BE",
    "sg:address":"Leieweg 14",
    "sg:city":"Kortrijk (marke)",
    "sg:classifiers":[
        {
            "category":"Manufacturing",
            "subcategory":"Building Materials",
            "type":"Manufacturing & Wholesale Goods"
        }
    ],
    "sg:phone":"+32 56 21 15 60",
    "sg:postcode":"8510",
    "sg:province":"West-Vlaanderen",
    "sg:tags":[
        "fixture",
        "store"
    ],
    "wof:name":"Firma Buyck Nuytens Bvba",
    "wof:placetype":"venue"
},
  "geometry": {"coordinates":[3.2269570827,50.8105163574],"type":"Point"}
}