{
  "type": "Feature",
  "properties": {
    "iso:country":"BE",
    "sg:address":"Lippenslaan 335",
    "sg:city":"Knokke-heist (knokke)",
    "sg:classifiers":[
        {
            "category":"Home & Garden",
            "subcategory":"Home Furnishings",
            "type":"Retail Goods"
        }
    ],
    "sg:phone":"+32 50 62 15 21",
    "sg:postcode":"8300",
    "sg:province":"West-Vlaanderen",
    "sg:tags":[
        "linen",
        "household",
        "-"
    ],
    "wof:name":"Cotton Bay",
    "wof:placetype":"venue"
},
  "geometry": {"coordinates":[3.2882900238,51.3466911316],"type":"Point"}
}