{
  "type": "Feature",
  "properties": {
    "iso:country":"BE",
    "sg:address":"Graatakker 189b3",
    "sg:city":"Turnhout",
    "sg:orig_category":"Boekhouders",
    "sg:phone":"+32 14 41 48 57",
    "sg:postcode":"2300",
    "sg:province":"Antwerpen",
    "wof:name":"Steven Ooms",
    "wof:placetype":"venue"
},
  "geometry": {"coordinates":[4.9489240646,51.313205719],"type":"Point"}
}