{
  "type": "Feature",
  "properties": {
    "iso:country":"BE",
    "sg:address":"Rue De L'epine 7",
    "sg:city":"Bernissart",
    "sg:orig_category":"Rundveehouders",
    "sg:phone":"+32 69 57 61 79",
    "sg:postcode":"7321",
    "sg:province":"Hainaut",
    "wof:name":"Fe. Onghena",
    "wof:placetype":"venue"
},
  "geometry": {"coordinates":[3.6566419601,50.5044059753],"type":"Point"}
}