{
  "type": "Feature",
  "properties": {
    "iso:country":"BE",
    "sg:address":"Rijfstraat 12",
    "sg:city":"Antwerpen",
    "sg:orig_category":"Produits interm\u00e9diaires Gr",
    "sg:phone":"+32 3 231 91 47",
    "sg:postcode":"2018",
    "sg:province":"Antwerpen",
    "wof:name":"Rudiam",
    "wof:placetype":"venue"
},
  "geometry": {"coordinates":[4.4187607765,51.216053009],"type":"Point"}
}