{
  "type": "Feature",
  "properties": {
    "addr:full":"Avenue De Houffalize 1 Libramont-chevigny Luxembourg 6800",
    "addr:housenumber":"1",
    "addr:postcode":"6800",
    "addr:street":"Avenue De Houffalize",
    "iso:country":"BE",
    "sg:address":"Avenue De Houffalize 1",
    "sg:city":"Libramont-chevigny",
    "sg:orig_category":"Banken and kredietinstellingen",
    "sg:phone":"+32 61 22 27 74",
    "sg:postcode":"6800",
    "sg:province":"Luxembourg",
    "wof:name":"Fortis",
    "wof:placetype":"venue"
},
  "geometry": {"coordinates":[5.3761348724,49.9199943542],"type":"Point"}
}