{
  "type": "Feature",
  "properties": {
    "addr:full":"Mechelse Steenweg 106 Antwerpen Antwerpen 2018",
    "addr:housenumber":"106",
    "addr:postcode":"2018",
    "addr:street":"Steenweg",
    "iso:country":"BE",
    "sg:address":"Mechelse Steenweg 106",
    "sg:city":"Antwerpen",
    "sg:orig_category":"Video-Equipment - Mainten. and Repair",
    "sg:postcode":"2018",
    "sg:province":"Antwerpen",
    "wof:name":"Anijs",
    "wof:placetype":"venue"
},
  "geometry": {"coordinates":[4.4091391563,51.2075653076],"type":"Point"}
}