{
  "type": "Feature",
  "properties": {
    "iso:country":"BE",
    "sg:address":"Rue P. Pastur 19",
    "sg:city":"Tournai",
    "sg:orig_category":"M\u00e9taux and minerais Gr",
    "sg:phone":"+32 69 21 56 53",
    "sg:postcode":"7500",
    "sg:province":"Hainaut",
    "wof:name":"M.g. Industie",
    "wof:placetype":"venue"
},
  "geometry": {"coordinates":[3.4027340412,50.6108512878],"type":"Point"}
}