{
  "type": "Feature",
  "properties": {
    "addr:full":"Prinses Paolalaan 35 Menen West-Vlaanderen 8930",
    "addr:housenumber":"35",
    "addr:postcode":"8930",
    "addr:street":"Prinses Paolalaan",
    "iso:country":"BE",
    "sg:address":"Prinses Paolalaan 35",
    "sg:city":"Menen",
    "sg:orig_category":"Catering and organisatie van feesten",
    "sg:phone":"+32 56 51 60 43",
    "sg:postcode":"8930",
    "sg:province":"West-Vlaanderen",
    "wof:name":"Lucas Dewitte",
    "wof:placetype":"venue"
},
  "geometry": {"coordinates":[3.1359119415,50.79088974],"type":"Point"}
}