{
  "type": "Feature",
  "properties": {
    "iso:country":"BE",
    "sg:address":"Sint-annekestraat 18",
    "sg:city":"Westerlo",
    "sg:orig_category":"P\u00e9pini\u00e9ristes",
    "sg:phone":"+32 16 68 00 85",
    "sg:postcode":"2260",
    "sg:province":"Antwerpen",
    "wof:name":"Maria Van Herbruggen",
    "wof:placetype":"venue"
},
  "geometry": {"coordinates":[4.8421697617,51.0714492798],"type":"Point"}
}