{
  "type": "Feature",
  "properties": {
    "iso:country":"BE",
    "sg:address":"Veneti\u00eb 3",
    "sg:city":"Kalmthout",
    "sg:classifiers":[
        {
            "category":"Farming",
            "subcategory":"Livestock Farm",
            "type":"Manufacturing & Wholesale Goods"
        }
    ],
    "sg:phone":"+32 3 667 22 15",
    "sg:postcode":"2920",
    "sg:province":"Antwerpen",
    "sg:tags":[
        "poultry",
        "rabbit"
    ],
    "wof:name":"Deko Bvba",
    "wof:placetype":"venue"
},
  "geometry": {"coordinates":[4.5134758949,51.4413986206],"type":"Point"}
}