{
  "type": "Feature",
  "properties": {
    "iso:country":"BE",
    "sg:address":"Chauss\u00c9e De Waterloo 1433",
    "sg:city":"Ukkel/uccle",
    "sg:orig_category":"Jardins botaniques, zoologiques, observatoires and r\u00e9serves naturelles",
    "sg:phone":"+32 2 374 02 34",
    "sg:postcode":"1180",
    "sg:province":"Bruxelles-Capitale",
    "wof:name":"Les Fermes Du Bonheur",
    "wof:placetype":"venue"
},
  "geometry": {"coordinates":[4.3776679039,50.7849769592],"type":"Point"}
}