{
  "type": "Feature",
  "properties": {
    "iso:country":"BE",
    "sg:address":"Magleinstraat 38",
    "sg:city":"Gent",
    "sg:orig_category":"Dameskledingzaken Kleding",
    "sg:phone":"+32 9 233 77 83",
    "sg:postcode":"9000",
    "sg:province":"Oost-Vlaanderen",
    "wof:name":"Cora Kemperman",
    "wof:placetype":"venue"
},
  "geometry": {"coordinates":[3.7245159149,51.0529708862],"type":"Point"}
}