{
  "type": "Feature",
  "properties": {
    "iso:country":"BE",
    "sg:address":"Rue De France 2",
    "sg:city":"Charleroi",
    "sg:classifiers":[
        {
            "category":"Cafe",
            "type":"Food & Drink"
        }
    ],
    "sg:phone":"+32 71 32 26 04",
    "sg:postcode":"6000",
    "sg:province":"Hainaut",
    "sg:tags":[
        "caf\u00e9s"
    ],
    "wof:name":"Durna Metin",
    "wof:placetype":"venue"
},
  "geometry": {"coordinates":[4.4439358711,50.4113311768],"type":"Point"}
}