{
  "type": "Feature",
  "properties": {
    "iso:country":"BE",
    "sg:address":"Veldstraat 19",
    "sg:city":"Meerhout",
    "sg:orig_category":"Services fun\u00e9raires",
    "sg:phone":"+32 14 30 06 58",
    "sg:postcode":"2450",
    "sg:province":"Antwerpen",
    "wof:name":"Schillebeeckx A.",
    "wof:placetype":"venue"
},
  "geometry": {"coordinates":[5.0796689987,51.1320877075],"type":"Point"}
}