{
  "type": "Feature",
  "properties": {
    "addr:full":"Kerkstraat 26 Tessenderlo Limburg 3980",
    "addr:housenumber":"26",
    "addr:postcode":"3980",
    "addr:street":"Kerkstraat",
    "iso:country":"BE",
    "sg:address":"Kerkstraat 26",
    "sg:city":"Tessenderlo",
    "sg:classifiers":[
        {
            "category":"Health Services",
            "subcategory":"Dentist",
            "type":"Services"
        }
    ],
    "sg:phone":"+32 13 66 41 45",
    "sg:postcode":"3980",
    "sg:province":"Limburg",
    "wof:name":"Cuypers Fernand",
    "wof:placetype":"venue"
},
  "geometry": {"coordinates":[5.0896692276,51.068813324],"type":"Point"}
}