{
  "type": "Feature",
  "properties": {
    "iso:country":"BE",
    "sg:address":"Rue Abb\u00e9 Dujardin 13",
    "sg:city":"Onhaye",
    "sg:classifiers":[
        {
            "category":"Food & Beverages",
            "subcategory":"Groceries & Convenience Stores",
            "type":"Retail Goods"
        }
    ],
    "sg:phone":"+32 82 64 59 59",
    "sg:postcode":"5520",
    "sg:province":"Namur",
    "sg:tags":[
        "grocer"
    ],
    "wof:name":"Collignon Sprl",
    "wof:placetype":"venue"
},
  "geometry": {"coordinates":[4.837375164,50.2424087524],"type":"Point"}
}