{
  "type": "Feature",
  "properties": {
    "iso:country":"BE",
    "sg:address":"Rue Neuve 13",
    "sg:city":"Juprelle",
    "sg:orig_category":"M\u00e9decins and sp\u00e9cialistes",
    "sg:phone":"+32 4 278 57 29",
    "sg:postcode":"4458",
    "sg:province":"Li\u00e8ge",
    "wof:name":"Guy Theunissen",
    "wof:placetype":"venue"
},
  "geometry": {"coordinates":[5.569712162,50.7215194702],"type":"Point"}
}