{
  "type": "Feature",
  "properties": {
    "iso:country":"BE",
    "sg:address":"Merelbekestraat 39",
    "sg:city":"Melle",
    "sg:orig_category":"Artiesten and kunstenaars Herstelling and restauratie van meubelen",
    "sg:phone":"+32 9 231 71 56",
    "sg:postcode":"9090",
    "sg:province":"Oost-Vlaanderen",
    "wof:name":"Yannik Bentein",
    "wof:placetype":"venue"
},
  "geometry": {"coordinates":[3.7708339691,51.0228347778],"type":"Point"}
}