{
  "type": "Feature",
  "properties": {
    "addr:full":"Rue De Mont St.-guibert 18 Ottignies-louvain-la-neuve Brabant Wallon 1340",
    "addr:housenumber":"18",
    "addr:postcode":"1340",
    "addr:street":"Rue De Mont St.-Guibert",
    "iso:country":"BE",
    "sg:address":"Rue De Mont St.-guibert 18",
    "sg:city":"Ottignies-louvain-la-neuve",
    "sg:orig_category":"Artsen and specialisten",
    "sg:phone":"+32 10 48 35 40",
    "sg:postcode":"1340",
    "sg:province":"Brabant Wallon",
    "wof:name":"L\u00c9on Servais",
    "wof:placetype":"venue"
},
  "geometry": {"coordinates":[4.5993118286,50.6659393311],"type":"Point"}
}