{
  "type": "Feature",
  "properties": {
    "iso:country":"BE",
    "sg:address":"Hoogbuul 43",
    "sg:city":"Olen",
    "sg:classifiers":[
        {
            "category":"Professional",
            "subcategory":"Accounting & Tax Preparation",
            "type":"Services"
        }
    ],
    "sg:phone":"+32 14 28 66 17",
    "sg:postcode":"2250",
    "sg:province":"Antwerpen",
    "sg:tags":[
        "bookkeeper"
    ],
    "wof:name":"Lambo Bvba",
    "wof:placetype":"venue"
},
  "geometry": {"coordinates":[4.8885989189,51.1495285034],"type":"Point"}
}