{
  "type": "Feature",
  "properties": {
    "addr:full":"Lambermontlaan 140 Brussel/bruxelles Bruxelles-Capitale 1030",
    "addr:housenumber":"140",
    "addr:postcode":"1030",
    "addr:street":"Lambermontlaan;/",
    "iso:country":"BE",
    "sg:address":"Lambermontlaan 140",
    "sg:city":"Brussel/bruxelles",
    "sg:orig_category":"Speciaalzaken",
    "sg:phone":"+32 2 215 58 00",
    "sg:postcode":"1030",
    "sg:province":"Bruxelles-Capitale",
    "wof:name":"Camaflex",
    "wof:placetype":"venue"
},
  "geometry": {"coordinates":[4.3807039261,50.8721046448],"type":"Point"}
}