{
  "type": "Feature",
  "properties": {
    "addr:full":"Kermtstraat 185 Hasselt Limburg 3512",
    "addr:housenumber":"185",
    "addr:postcode":"3512",
    "addr:street":"Kermtstraat",
    "iso:country":"BE",
    "sg:address":"Kermtstraat 185",
    "sg:city":"Hasselt",
    "sg:orig_category":"Tuinen",
    "sg:phone":"+32 11 31 15 24",
    "sg:postcode":"3512",
    "sg:province":"Limburg",
    "wof:name":"Piet Carrein",
    "wof:placetype":"venue"
},
  "geometry": {"coordinates":[5.249147892,50.9286689758],"type":"Point"}
}