{
  "type": "Feature",
  "properties": {
    "addr:full":"Lesbroussartstraat 28 Elsene/ixelles Bruxelles-Capitale 1050",
    "addr:housenumber":"28",
    "addr:postcode":"1050",
    "addr:street":"Lesbroussartstraat",
    "iso:country":"BE",
    "sg:address":"Lesbroussartstraat 28",
    "sg:city":"Elsene/ixelles",
    "sg:orig_category":"Kinderopvang",
    "sg:phone":"+32 2 647 92 07",
    "sg:postcode":"1050",
    "sg:province":"Bruxelles-Capitale",
    "wof:name":"Cr\u00c8che P'tits Pierrots",
    "wof:placetype":"venue"
},
  "geometry": {"coordinates":[4.3700489998,50.8276367188],"type":"Point"}
}