{
  "type": "Feature",
  "properties": {
    "addr:full":"Rue Vanderkindere 156 Bruxelles (uccle) Bruxelles-Capitale 1180",
    "addr:housenumber":"156",
    "addr:postcode":"1180",
    "addr:street":"Rue Vanderkindere",
    "iso:country":"BE",
    "sg:address":"Rue Vanderkindere 156",
    "sg:city":"Bruxelles (uccle)",
    "sg:classifiers":[
        {
            "category":"Food & Beverages",
            "subcategory":"Fruits & Vegetables",
            "type":"Retail Goods"
        }
    ],
    "sg:phone":"+32 2 344 39 66",
    "sg:postcode":"1180",
    "sg:province":"Bruxelles-Capitale",
    "sg:tags":[
        "-",
        "shirt"
    ],
    "wof:name":"Guido Chemisier",
    "wof:placetype":"venue"
},
  "geometry": {"coordinates":[4.3458051682,50.8139381409],"type":"Point"}
}