{
  "type": "Feature",
  "properties": {
    "addr:full":"Verbindingsstraat 19 Balen Antwerpen 2490",
    "addr:housenumber":"19",
    "addr:postcode":"2490",
    "addr:street":"Verbindingsstraat",
    "iso:country":"BE",
    "sg:address":"Verbindingsstraat 19",
    "sg:city":"Balen",
    "sg:classifiers":[
        {
            "category":"Recreation",
            "type":"Entertainment"
        }
    ],
    "sg:phone":"+32 14 81 31 29",
    "sg:postcode":"2490",
    "sg:province":"Antwerpen",
    "sg:tags":[
        "diver",
        "amusement"
    ],
    "wof:name":"B. & S. Sound & Light",
    "wof:placetype":"venue"
},
  "geometry": {"coordinates":[5.1570119858,51.1702880859],"type":"Point"}
}