{
  "type": "Feature",
  "properties": {
    "iso:country":"BE",
    "sg:address":"Place Communale 8",
    "sg:city":"Jemeppe-sur-sambre",
    "sg:classifiers":[
        {
            "category":"Retail",
            "subcategory":"Event Space",
            "type":"Services"
        }
    ],
    "sg:phone":"+32 71 78 19 68",
    "sg:postcode":"5190",
    "sg:province":"Namur",
    "sg:tags":[
        "dinner",
        "set",
        "-",
        "cutlery"
    ],
    "wof:name":"C\u00f4t\u00e9 Cadeaux",
    "wof:placetype":"venue"
},
  "geometry": {"coordinates":[4.6685128212,50.4656181335],"type":"Point"}
}