{
  "type": "Feature",
  "properties": {
    "iso:country":"BE",
    "sg:address":"Guido Gezellelaan 66",
    "sg:city":"Deinze",
    "sg:orig_category":"Woningbouw",
    "sg:phone":"+32 9 386 09 47",
    "sg:postcode":"9800",
    "sg:province":"Oost-Vlaanderen",
    "wof:name":"Didier De Sloovere",
    "wof:placetype":"venue"
},
  "geometry": {"coordinates":[3.5328168869,50.9833374023],"type":"Point"}
}