{
  "type": "Feature",
  "properties": {
    "addr:full":"Avenue Des Combattants 19 Vise Li\u00e8ge 4600",
    "addr:housenumber":"19",
    "addr:postcode":"4600",
    "addr:street":"Avenue Des Combattants",
    "iso:country":"BE",
    "sg:address":"Avenue Des Combattants 19",
    "sg:city":"Vise",
    "sg:orig_category":"M\u00e9decins and sp\u00e9cialistes. M\u00e9decines alternatives",
    "sg:phone":"+32 4 379 08 51",
    "sg:postcode":"4600",
    "sg:province":"Li\u00e8ge",
    "wof:name":"Marc Deru",
    "wof:placetype":"venue"
},
  "geometry": {"coordinates":[5.6978039742,50.7366371155],"type":"Point"}
}