{
  "type": "Feature",
  "properties": {
    "iso:country":"BE",
    "sg:address":"Wijnegembaan 2",
    "sg:city":"Schoten",
    "sg:classifiers":[
        {
            "category":"Manufacturing",
            "subcategory":"Motor Vehicles & Parts",
            "type":"Manufacturing & Wholesale Goods"
        }
    ],
    "sg:phone":"+32 3 326 57 27",
    "sg:postcode":"2900",
    "sg:province":"Antwerpen",
    "sg:tags":[
        "engine",
        "dual-fuel",
        "industrial",
        "use"
    ],
    "wof:name":"Verswijver C. Nv",
    "wof:placetype":"venue"
},
  "geometry": {"coordinates":[4.5012569427,51.2435150146],"type":"Point"}
}