{
  "type": "Feature",
  "properties": {
    "addr:full":"Rue De La Perche 39 Dour (elouges) Hainaut 7370",
    "addr:housenumber":"39",
    "addr:postcode":"7370",
    "addr:street":"Rue De La Perche;Elouges Hainaut",
    "iso:country":"BE",
    "sg:address":"Rue De La Perche 39",
    "sg:city":"Dour (elouges)",
    "sg:classifiers":[
        {
            "category":"Health Services",
            "subcategory":"Nursing And Care Facility",
            "type":"Services"
        }
    ],
    "sg:phone":"+32 65 46 54 78",
    "sg:postcode":"7370",
    "sg:province":"Hainaut",
    "sg:tags":[
        "home"
    ],
    "wof:name":"Abrassart F",
    "wof:placetype":"venue"
},
  "geometry": {"coordinates":[3.7785201073,50.39635849],"type":"Point"}
}