{
  "type": "Feature",
  "properties": {
    "addr:full":"Weg Op Bree 104 Meeuwen-gruitrode (meeuwen) Limburg 3670",
    "addr:housenumber":"104",
    "addr:postcode":"3670",
    "addr:street":"Weg Op Bree",
    "iso:country":"BE",
    "sg:address":"Weg Op Bree 104",
    "sg:city":"Meeuwen-gruitrode (meeuwen)",
    "sg:classifiers":[
        {
            "category":"Retail",
            "subcategory":"Auto Repair",
            "type":"Services"
        }
    ],
    "sg:phone":"+32 11 79 23 94",
    "sg:postcode":"3670",
    "sg:province":"Limburg",
    "sg:tags":[
        "garage"
    ],
    "wof:name":"Soogen M",
    "wof:placetype":"venue"
},
  "geometry": {"coordinates":[5.5347938538,51.1013641357],"type":"Point"}
}