{
  "type": "Feature",
  "properties": {
    "addr:full":"Hoogstraat 27 Evergem Oost-Vlaanderen 9940",
    "addr:housenumber":"27",
    "addr:postcode":"9940",
    "addr:street":"Hoogstraat;Oost-Vlaanderen",
    "iso:country":"BE",
    "sg:address":"Hoogstraat 27",
    "sg:city":"Evergem",
    "sg:orig_category":"Rundveehouders",
    "sg:phone":"+32 9 357 40 82",
    "sg:postcode":"9940",
    "sg:province":"Oost-Vlaanderen",
    "wof:name":"Roger Van Hyfte",
    "wof:placetype":"venue"
},
  "geometry": {"coordinates":[3.7426929474,51.1570510864],"type":"Point"}
}