{
  "type": "Feature",
  "properties": {
    "addr:full":"Rue Des B\u00e9guines 10 Profondeville (rivi\u00e8re) Namur 5170",
    "addr:housenumber":"10",
    "addr:postcode":"5170",
    "addr:street":"Rue Des Be\u0301Guines",
    "iso:country":"BE",
    "sg:address":"Rue Des B\u00e9guines 10",
    "sg:city":"Profondeville (rivi\u00e8re)",
    "sg:classifiers":[
        {
            "category":"Real Estate",
            "subcategory":"Architect",
            "type":"Services"
        }
    ],
    "sg:phone":"+32 81 26 39 51",
    "sg:postcode":"5170",
    "sg:province":"Namur",
    "wof:name":"Lambotte F",
    "wof:placetype":"venue"
},
  "geometry": {"coordinates":[4.8674049377,50.3786392212],"type":"Point"}
}