{
  "type": "Feature",
  "properties": {
    "iso:country":"BE",
    "sg:address":"Tussen Beken 39",
    "sg:city":"Sint-martens-latem",
    "sg:orig_category":"Boucheries",
    "sg:phone":"+32 9 282 73 58",
    "sg:postcode":"9830",
    "sg:province":"Oost-Vlaanderen",
    "wof:name":"Eddy Leenesonne",
    "wof:placetype":"venue"
},
  "geometry": {"coordinates":[3.6315779686,51.0021209717],"type":"Point"}
}