{
  "type": "Feature",
  "properties": {
    "iso:country":"BE",
    "sg:address":"Charles De Kerchovelaan 9",
    "sg:city":"Gent",
    "sg:classifiers":[
        {
            "category":"Social Services",
            "subcategory":"Job Training",
            "type":"Services"
        }
    ],
    "sg:phone":"+32 9 267 96 20",
    "sg:postcode":"9000",
    "sg:province":"Oost-Vlaanderen",
    "sg:tags":[
        "personnel",
        "-selection",
        "recruitment"
    ],
    "wof:name":"Adecco Select",
    "wof:placetype":"venue"
},
  "geometry": {"coordinates":[3.7210679054,51.0412216187],"type":"Point"}
}