{
  "type": "Feature",
  "properties": {
    "addr:full":"Rue Derri\u00c8re La Vaulx 43 Malmedy Li\u00e8ge 4960",
    "addr:housenumber":"43",
    "addr:postcode":"4960",
    "addr:street":"Rue Derrie\u0300Re La Vaulx",
    "iso:country":"BE",
    "sg:address":"Rue Derri\u00c8re La Vaulx 43",
    "sg:city":"Malmedy",
    "sg:orig_category":"Belastingconsulenten Diverse juridische dienstverlening",
    "sg:phone":"+32 80 33 99 50",
    "sg:postcode":"4960",
    "sg:province":"Li\u00e8ge",
    "wof:name":"Fiduciare Noblet",
    "wof:placetype":"venue"
},
  "geometry": {"coordinates":[6.0321278572,50.4253387451],"type":"Point"}
}