{
  "type": "Feature",
  "properties": {
    "addr:full":"Kerkstraat 76 Puurs Antwerpen 2870",
    "addr:housenumber":"76",
    "addr:postcode":"2870",
    "addr:street":"Kerkstraat",
    "iso:country":"BE",
    "sg:address":"Kerkstraat 76",
    "sg:city":"Puurs",
    "sg:orig_category":"Banques and organismes de cr\u00e9dit",
    "sg:phone":"+32 3 860 95 40",
    "sg:postcode":"2870",
    "sg:province":"Antwerpen",
    "wof:name":"Kbc",
    "wof:placetype":"venue"
},
  "geometry": {"coordinates":[4.3233060837,51.0831375122],"type":"Point"}
}