{
  "type": "Feature",
  "properties": {
    "addr:full":"Chemin De L'angl\u00e9e 517a Pecq (h\u00e9rinnes-lez-pecq) Hainaut 7742",
    "addr:housenumber":"517a",
    "addr:postcode":"7742",
    "addr:street":"Chemin De L'Angle \u0301E",
    "iso:country":"BE",
    "sg:address":"Chemin De L'angl\u00e9e 517a",
    "sg:city":"Pecq (h\u00e9rinnes-lez-pecq)",
    "sg:classifiers":[
        {
            "category":"Health Services",
            "subcategory":"Nursing And Care Facility",
            "type":"Services"
        }
    ],
    "sg:phone":"+32 69 55 92 55",
    "sg:postcode":"7742",
    "sg:province":"Hainaut",
    "sg:tags":[
        "home"
    ],
    "wof:name":"Herman M-c",
    "wof:placetype":"venue"
},
  "geometry": {"coordinates":[3.374270916,50.7070465088],"type":"Point"}
}