{
  "type": "Feature",
  "properties": {
    "iso:country":"BE",
    "sg:address":"Heidestraat 25",
    "sg:city":"Gooik (kester)",
    "sg:classifiers":[
        {
            "category":"Building & Trades",
            "subcategory":"Plumbing",
            "type":"Services"
        }
    ],
    "sg:phone":"+32 54 56 76 56",
    "sg:postcode":"1755",
    "sg:province":"Vlaams-Brabant",
    "sg:tags":[
        "contractor"
    ],
    "wof:name":"Verheyden S",
    "wof:placetype":"venue"
},
  "geometry": {"coordinates":[4.1047887802,50.7737350464],"type":"Point"}
}