{
  "type": "Feature",
  "properties": {
    "iso:country":"BE",
    "sg:address":"Ring 9",
    "sg:city":"Ninove",
    "sg:orig_category":"Non-Classified Establishments",
    "sg:phone":"+32 54 33 72 92",
    "sg:postcode":"9400",
    "sg:province":"Oost-Vlaanderen",
    "wof:name":"De Kegel R Bvba",
    "wof:placetype":"venue"
},
  "geometry": {"coordinates":[4.0310001373,50.8447799683],"type":"Point"}
}