{
  "type": "Feature",
  "properties": {
    "addr:full":"Franz Schollaertstraat 28bb Leuven Vlaams-Brabant 3010",
    "addr:housenumber":"28bb",
    "addr:postcode":"3010",
    "addr:street":"Franz Schollaertstraat",
    "iso:country":"BE",
    "sg:address":"Franz Schollaertstraat 28bb",
    "sg:city":"Leuven",
    "sg:orig_category":"Artistes ind\u00e9pendants. R\u00e9paration and restauration de meubles",
    "sg:phone":"+32 16 25 43 06",
    "sg:postcode":"3010",
    "sg:province":"Vlaams-Brabant",
    "wof:name":"K. Wazgird",
    "wof:placetype":"venue"
},
  "geometry": {"coordinates":[4.7304501534,50.889755249],"type":"Point"}
}