{
  "type": "Feature",
  "properties": {
    "addr:full":"Cours D'orval 8 Ottignies-louvain-la-neuve (louvain-la-neuve) Brabant Wallon 1348",
    "addr:housenumber":"8",
    "addr:postcode":"1348",
    "addr:street":"Cours D'Orval",
    "iso:country":"BE",
    "sg:address":"Cours D'orval 8",
    "sg:city":"Ottignies-louvain-la-neuve (louvain-la-neuve)",
    "sg:classifiers":[
        {
            "category":"Professional",
            "subcategory":"Lawyer & Legal Services",
            "type":"Services"
        }
    ],
    "sg:phone":"+32 10 45 74 66",
    "sg:postcode":"1348",
    "sg:province":"Brabant Wallon",
    "wof:name":"Danjou Fran\u00e7oise",
    "wof:placetype":"venue"
},
  "geometry": {"coordinates":[4.6156349182,50.6743202209],"type":"Point"}
}