{
  "type": "Feature",
  "properties": {
    "iso:country":"BE",
    "sg:address":"Chemin De Ghislenghien 23",
    "sg:city":"Brugelette",
    "sg:orig_category":"Jardinage",
    "sg:phone":"+32 68 55 28 84",
    "sg:postcode":"7942",
    "sg:province":"Hainaut",
    "wof:name":"Olieux R.",
    "wof:placetype":"venue"
},
  "geometry": {"coordinates":[3.8574299812,50.6242904663],"type":"Point"}
}