{
  "type": "Feature",
  "properties": {
    "iso:country":"BE",
    "sg:address":"Prins Bisschopsingel 50",
    "sg:city":"Hasselt",
    "sg:orig_category":"Services de Nettoyage and de D\u00e9sinfection. Plomberie, chauffage and installations sanitaires",
    "sg:phone":"+32 11 21 17 28",
    "sg:postcode":"3500",
    "sg:province":"Limburg",
    "wof:name":"Debaco",
    "wof:placetype":"venue"
},
  "geometry": {"coordinates":[5.3385901451,50.9137115479],"type":"Point"}
}