{
  "type": "Feature",
  "properties": {
    "iso:country":"BE",
    "sg:address":"Chemin Aux Gites 102",
    "sg:city":"Braine-le-comte",
    "sg:orig_category":"Eleveurs de bovins",
    "sg:phone":"+32 67 55 48 77",
    "sg:postcode":"7090",
    "sg:province":"Hainaut",
    "wof:name":"Luc Blondeau",
    "wof:placetype":"venue"
},
  "geometry": {"coordinates":[4.1167759895,50.6194038391],"type":"Point"}
}