{
  "type": "Feature",
  "properties": {
    "addr:full":"Steenbergstraat 12 Affligem Vlaams-Brabant 1790",
    "addr:housenumber":"12",
    "addr:postcode":"1790",
    "addr:street":"Steenbergstraat",
    "iso:country":"BE",
    "sg:address":"Steenbergstraat 12",
    "sg:city":"Affligem",
    "sg:orig_category":"G\u00e9om\u00e8tres",
    "sg:phone":"+32 53 66 33 62",
    "sg:postcode":"1790",
    "sg:province":"Vlaams-Brabant",
    "wof:name":"Frank Rossignol",
    "wof:placetype":"venue"
},
  "geometry": {"coordinates":[4.1024050713,50.8907966614],"type":"Point"}
}