{
  "type": "Feature",
  "properties": {
    "iso:country":"BE",
    "sg:address":"Cours Saint-guidon 12",
    "sg:city":"Bruxelles (anderlecht)",
    "sg:classifiers":[
        {
            "category":"Professional",
            "subcategory":"Detective & Security Services",
            "type":"Services"
        }
    ],
    "sg:phone":"+32 2 520 41 69",
    "sg:postcode":"1070",
    "sg:province":"Bruxelles-Capitale",
    "sg:tags":[
        "door",
        "videophones",
        "operating",
        "equipment"
    ],
    "wof:name":"Bonnet Electric Sprl",
    "wof:placetype":"venue"
},
  "geometry": {"coordinates":[4.3058991432,50.8352851868],"type":"Point"}
}