{
  "type": "Feature",
  "properties": {
    "addr:full":"Chemin Des Fagnes 27 Malmedy/malmedy Li\u00e8ge 4960",
    "addr:housenumber":"27",
    "addr:postcode":"4960",
    "addr:street":"Chemin Des Fagnes",
    "iso:country":"BE",
    "sg:address":"Chemin Des Fagnes 27",
    "sg:city":"Malmedy/malmedy",
    "sg:orig_category":"Electrom\u00e9nager, t\u00e9l\u00e9visions and radios",
    "sg:phone":"+32 80 77 04 13",
    "sg:postcode":"4960",
    "sg:province":"Li\u00e8ge",
    "wof:name":"Christa Freres",
    "wof:placetype":"venue"
},
  "geometry": {"coordinates":[6.0576348305,50.405330658],"type":"Point"}
}