{
  "type": "Feature",
  "properties": {
    "iso:country":"BE",
    "sg:address":"Grote Straat 72",
    "sg:city":"Riemst (valmeer)",
    "sg:classifiers":[
        {
            "category":"Building & Trades",
            "subcategory":"Pest Control",
            "type":"Services"
        }
    ],
    "sg:phone":"+32 476 69 09 16",
    "sg:postcode":"3770",
    "sg:province":"Limburg",
    "sg:tags":[
        "painting",
        "contractor"
    ],
    "wof:name":"L.d. Design",
    "wof:placetype":"venue"
},
  "geometry": {"coordinates":[5.5969901085,50.8109016418],"type":"Point"}
}