{
  "type": "Feature",
  "properties": {
    "addr:full":"Chauss\u00e9e De Wavre 240 Grez-doiceau (archennes) Brabant Wallon 1390",
    "addr:housenumber":"240",
    "addr:postcode":"1390",
    "addr:street":"Chausse\u0301E De Wavre;Wallon",
    "iso:country":"BE",
    "sg:address":"Chauss\u00e9e De Wavre 240",
    "sg:city":"Grez-doiceau (archennes)",
    "sg:classifiers":[
        {
            "category":"Home & Garden",
            "subcategory":"Furniture",
            "type":"Retail Goods"
        }
    ],
    "sg:phone":"+32 10 84 48 56",
    "sg:postcode":"1390",
    "sg:province":"Brabant Wallon",
    "sg:tags":[
        "-"
    ],
    "wof:name":"Etudes Et Constructions Sprl",
    "wof:placetype":"venue"
},
  "geometry": {"coordinates":[4.6841101646,50.7455215454],"type":"Point"}
}