{
  "type": "Feature",
  "properties": {
    "iso:country":"BE",
    "sg:address":"Zangvogellaan 16",
    "sg:city":"Gent",
    "sg:orig_category":"Artiesten and kunstenaars",
    "sg:phone":"+32 9 228 66 13",
    "sg:postcode":"9041",
    "sg:province":"Oost-Vlaanderen",
    "wof:name":"Alice Frangoulis",
    "wof:placetype":"venue"
},
  "geometry": {"coordinates":[3.7709920406,51.0763473511],"type":"Point"}
}