{
  "type": "Feature",
  "properties": {
    "iso:country":"BE",
    "sg:address":"Kursaalstraat 40",
    "sg:city":"Vilvoorde",
    "sg:classifiers":[
        {
            "category":"Health Services",
            "subcategory":"Nursing And Care Facility",
            "type":"Services"
        }
    ],
    "sg:phone":"+32 2 254 64 71",
    "sg:postcode":"1800",
    "sg:province":"Vlaams-Brabant",
    "sg:tags":[
        "home",
        "rest"
    ],
    "wof:name":"Woon- En Zorgcentrum ter Linde",
    "wof:placetype":"venue"
},
  "geometry": {"coordinates":[4.4209098816,50.9268112183],"type":"Point"}
}