{
  "type": "Feature",
  "properties": {
    "iso:country":"BE",
    "sg:address":"Rue Baudouin Leprince 2",
    "sg:city":"Ham-sur-heure-nalinnes (jamioulx)",
    "sg:classifiers":[
        {
            "category":"Arena",
            "subcategory":"Sports Club",
            "type":"Entertainment"
        }
    ],
    "sg:phone":"+32 71 21 42 42",
    "sg:postcode":"6120",
    "sg:province":"Hainaut",
    "wof:name":"Tennis-club De Jamioulx Asbl",
    "wof:placetype":"venue"
},
  "geometry": {"coordinates":[4.4111199379,50.3469581604],"type":"Point"}
}