{
  "type": "Feature",
  "properties": {
    "iso:country":"BE",
    "sg:address":"Pannenhuisstraat 57",
    "sg:city":"Stekene",
    "sg:orig_category":"Brood, gebak and snoepgoed",
    "sg:phone":"+32 9 346 84 84",
    "sg:postcode":"9190",
    "sg:province":"Oost-Vlaanderen",
    "wof:name":"Jurgen De Saer",
    "wof:placetype":"venue"
},
  "geometry": {"coordinates":[3.9940071106,51.1878471375],"type":"Point"}
}