{
  "type": "Feature",
  "properties": {
    "iso:country":"BE",
    "sg:address":"Gaversstraat 45a",
    "sg:city":"Harelbeke",
    "sg:classifiers":[
        {
            "category":"Professional",
            "subcategory":"Art Services",
            "type":"Services"
        }
    ],
    "sg:phone":"+32 56 71 41 15",
    "sg:postcode":"8530",
    "sg:province":"West-Vlaanderen",
    "sg:tags":[
        "graphic",
        "designer"
    ],
    "wof:name":"Van Ham Creations",
    "wof:placetype":"venue"
},
  "geometry": {"coordinates":[3.3167459965,50.8537254333],"type":"Point"}
}