{
  "type": "Feature",
  "properties": {
    "iso:country":"BE",
    "sg:address":"Geeststraat 12",
    "sg:city":"Hamme (moerzeke)",
    "sg:classifiers":[
        {
            "category":"Banks & Credit Unions",
            "subcategory":"Investment Brokerage",
            "type":"Services"
        }
    ],
    "sg:phone":"+32 52 47 18 69",
    "sg:postcode":"9220",
    "sg:province":"Oost-Vlaanderen",
    "sg:tags":[
        "fence"
    ],
    "wof:name":"De Vos Marc Bvba",
    "wof:placetype":"venue"
},
  "geometry": {"coordinates":[4.1558628082,51.0670318604],"type":"Point"}
}