{
  "type": "Feature",
  "properties": {
    "iso:country":"BE",
    "sg:address":"Beemdstraat 39",
    "sg:city":"Lommel",
    "sg:classifiers":[
        {
            "category":"Real Estate",
            "subcategory":"Architect",
            "type":"Services"
        }
    ],
    "sg:phone":"+32 11 54 13 67",
    "sg:postcode":"3920",
    "sg:province":"Limburg",
    "wof:name":"Bernaerdts E",
    "wof:placetype":"venue"
},
  "geometry": {"coordinates":[5.34288311,51.2256889343],"type":"Point"}
}