{
  "type": "Feature",
  "properties": {
    "iso:country":"BE",
    "sg:address":"Pelgrimsstraat 26",
    "sg:city":"Antwerpen",
    "sg:classifiers":[
        {
            "category":"Restaurant",
            "type":"Food & Drink"
        }
    ],
    "sg:phone":"+32 3 225 02 22",
    "sg:postcode":"2000",
    "sg:province":"Antwerpen",
    "wof:name":"Superbrochette",
    "wof:placetype":"venue"
},
  "geometry": {"coordinates":[4.3991727829,51.2195625305],"type":"Point"}
}