{
  "type": "Feature",
  "properties": {
    "iso:country":"BE",
    "sg:address":"Miksebaan 285",
    "sg:city":"Brasschaat",
    "sg:classifiers":[
        {
            "category":"Freight",
            "type":"Transportation"
        }
    ],
    "sg:phone":"+32 3 271 14 27",
    "sg:postcode":"2930",
    "sg:province":"Antwerpen",
    "sg:tags":[
        "-",
        "transport"
    ],
    "wof:name":"Cycle Nv",
    "wof:placetype":"venue"
},
  "geometry": {"coordinates":[4.5148301125,51.296131134],"type":"Point"}
}