{
  "type": "Feature",
  "properties": {
    "iso:country":"BE",
    "sg:address":"Rue Du Vingt-quatre Aout 58",
    "sg:city":"Habay",
    "sg:orig_category":"HUISBRANDOLIE",
    "sg:phone":"+32 63 41 12 28",
    "sg:postcode":"6724",
    "sg:province":"Luxembourg",
    "wof:name":"Goffinet & Fils",
    "wof:placetype":"venue"
},
  "geometry": {"coordinates":[5.5864062309,49.7188606262],"type":"Point"}
}