{
  "type": "Feature",
  "properties": {
    "iso:country":"BE",
    "sg:address":"Terlaenenstraat 12",
    "sg:city":"Huldenberg",
    "sg:orig_category":"Artistes ind\u00e9pendants",
    "sg:phone":"+32 16 47 78 90",
    "sg:postcode":"3040",
    "sg:province":"Vlaams-Brabant",
    "wof:name":"Pascal Mulpas",
    "wof:placetype":"venue"
},
  "geometry": {"coordinates":[4.6144018173,50.7530403137],"type":"Point"}
}