{
  "type": "Feature",
  "properties": {
    "iso:country":"BE",
    "sg:address":"Werkplaatsen 48",
    "sg:city":"Lommel",
    "sg:orig_category":"Electrom\u00e9nager, t\u00e9l\u00e9visions and radios. R\u00e9parations d'appareils \u00e9lectrom\u00e9nagers",
    "sg:phone":"+32 11 54 19 69",
    "sg:postcode":"3920",
    "sg:province":"Limburg",
    "wof:name":"Verreyt",
    "wof:placetype":"venue"
},
  "geometry": {"coordinates":[5.271584034,51.2303009033],"type":"Point"}
}