{
  "type": "Feature",
  "properties": {
    "addr:full":"Franslaan 162 Box 1 Nieuwpoort West-Vlaanderen 8620",
    "addr:housenumber":"162;1",
    "addr:postcode":"8620",
    "addr:street":"Franslaan;Box",
    "iso:country":"BE",
    "sg:address":"Franslaan 162 Box 1",
    "sg:city":"Nieuwpoort",
    "sg:classifiers":[
        {
            "category":"Professional",
            "subcategory":"Accounting & Tax Preparation",
            "type":"Services"
        }
    ],
    "sg:phone":"+32 58 23 02 96",
    "sg:postcode":"8620",
    "sg:province":"West-Vlaanderen",
    "sg:tags":[
        "bookkeeper"
    ],
    "wof:name":"Fiduwa Bvba",
    "wof:placetype":"venue"
},
  "geometry": {"coordinates":[2.7087159157,51.1441345215],"type":"Point"}
}