{
  "type": "Feature",
  "properties": {
    "iso:country":"BE",
    "sg:address":"Thimstrasse 6",
    "sg:city":"Kelmis",
    "sg:classifiers":[
        {
            "category":"Shopping",
            "subcategory":"Clothing, Apparel, & Fashions",
            "type":"Retail Goods"
        }
    ],
    "sg:phone":"+32 87 63 13 22",
    "sg:postcode":"4720",
    "sg:province":"Li\u00e8ge",
    "sg:tags":[
        "boutique"
    ],
    "wof:name":"Lady Look",
    "wof:placetype":"venue"
},
  "geometry": {"coordinates":[6.0117330551,50.7164611816],"type":"Point"}
}