{
  "type": "Feature",
  "properties": {
    "addr:full":"Brugsestw 106 Pittem West-Vlaanderen 8740",
    "addr:housenumber":"106",
    "addr:postcode":"8740",
    "iso:country":"BE",
    "sg:address":"Brugsestw 106",
    "sg:city":"Pittem",
    "sg:classifiers":[
        {
            "category":"Real Estate",
            "subcategory":"Architect",
            "type":"Services"
        }
    ],
    "sg:phone":"+32 51 46 65 31",
    "sg:postcode":"8740",
    "sg:province":"West-Vlaanderen",
    "sg:tags":[
        "textile",
        "clothing"
    ],
    "wof:name":"Clarysse Jules Nv",
    "wof:placetype":"venue"
},
  "geometry": {"coordinates":[3.2359199524,51.004699707],"type":"Point"}
}