{
  "type": "Feature",
  "properties": {
    "iso:country":"BE",
    "sg:address":"Dalstraat 39",
    "sg:city":"Brussel/bruxelles",
    "sg:orig_category":"Artsen and specialisten",
    "sg:phone":"+32 2 648 89 75",
    "sg:postcode":"1000",
    "sg:province":"Bruxelles-Capitale",
    "wof:name":"J. Wathelet",
    "wof:placetype":"venue"
},
  "geometry": {"coordinates":[4.3707728386,50.8231163025],"type":"Point"}
}