{
  "type": "Feature",
  "properties": {
    "addr:full":"Brusselsestw 560 Overijse Vlaams-Brabant 3090",
    "addr:housenumber":"560",
    "addr:postcode":"3090",
    "iso:country":"BE",
    "sg:address":"Brusselsestw 560",
    "sg:city":"Overijse",
    "sg:classifiers":[
        {
            "category":"Professional",
            "subcategory":"Advertising",
            "type":"Services"
        }
    ],
    "sg:phone":"+32 2 686 00 10",
    "sg:postcode":"3090",
    "sg:province":"Vlaams-Brabant",
    "sg:tags":[
        "marketing",
        "medium",
        "communication"
    ],
    "wof:name":"Luon Produkties Bvba",
    "wof:placetype":"venue"
},
  "geometry": {"coordinates":[4.4864730835,50.7920150757],"type":"Point"}
}