{
  "type": "Feature",
  "properties": {
    "addr:full":"Iz Vostert 1220 Bree Limburg 3960",
    "addr:postcode":"1220 bree;3960",
    "iso:country":"BE",
    "sg:address":"Iz Vostert 1220",
    "sg:city":"Bree",
    "sg:classifiers":[
        {
            "category":"Shopping",
            "subcategory":"Bicycles & Sporting Goods",
            "type":"Retail Goods"
        }
    ],
    "sg:phone":"+32 89 47 31 31",
    "sg:postcode":"3960",
    "sg:province":"Limburg",
    "sg:tags":[
        "tent"
    ],
    "wof:name":"European Future Structures Nv",
    "wof:placetype":"venue"
},
  "geometry": {"coordinates":[5.5883197784,51.1209182739],"type":"Point"}
}