{
  "type": "Feature",
  "properties": {
    "iso:country":"BE",
    "sg:address":"Sint-bavoplein 8",
    "sg:city":"Boechout",
    "sg:orig_category":"Caf\u00e9s Ruimtes voor conferenties, recepties and feesten",
    "sg:phone":"+32 3 455 81 93",
    "sg:postcode":"2530",
    "sg:province":"Antwerpen",
    "wof:name":"Gildenhuis St.bavo",
    "wof:placetype":"venue"
},
  "geometry": {"coordinates":[4.4928159714,51.1594543457],"type":"Point"}
}