{
  "type": "Feature",
  "properties": {
    "addr:full":"Rue Du March\u00c9 Au Charbon 83 Brussel/bruxelles Bruxelles-Capitale 1000",
    "addr:housenumber":"83",
    "addr:postcode":"1000",
    "addr:street":"Rue Du Marche\u0301 Au Charbon;/",
    "iso:country":"BE",
    "sg:address":"Rue Du March\u00c9 Au Charbon 83",
    "sg:city":"Brussel/bruxelles",
    "sg:orig_category":"M\u00e9decins and sp\u00e9cialistes",
    "sg:phone":"+32 2 512 37 97",
    "sg:postcode":"1000",
    "sg:province":"Bruxelles-Capitale",
    "wof:name":"Koen Moelants",
    "wof:placetype":"venue"
},
  "geometry": {"coordinates":[4.3480839729,50.8457527161],"type":"Point"}
}