{
  "type": "Feature",
  "properties": {
    "iso:country":"BE",
    "sg:address":"Paul Leducstraat 18",
    "sg:city":"Schaarbeek/schaerbeek",
    "sg:orig_category":"Schoonheidssalons",
    "sg:phone":"+32 2 705 70 27",
    "sg:postcode":"1030",
    "sg:province":"Bruxelles-Capitale",
    "wof:name":"Vanderhaaghen",
    "wof:placetype":"venue"
},
  "geometry": {"coordinates":[4.4020738602,50.8586502075],"type":"Point"}
}