{
  "type": "Feature",
  "properties": {
    "addr:full":"Keerstraatje 65 Waarschoot Oost-Vlaanderen 9950",
    "addr:housenumber":"65",
    "addr:postcode":"9950",
    "addr:street":"Keerstraatje",
    "iso:country":"BE",
    "sg:address":"Keerstraatje 65",
    "sg:city":"Waarschoot",
    "sg:classifiers":[
        {
            "category":"Wholesale",
            "subcategory":"Sporting Goods",
            "type":"Manufacturing & Wholesale Goods"
        }
    ],
    "sg:phone":"+32 9 378 42 17",
    "sg:postcode":"9950",
    "sg:province":"Oost-Vlaanderen",
    "sg:tags":[
        "sport-",
        "kampeermateriaal"
    ],
    "wof:name":"Iris",
    "wof:placetype":"venue"
},
  "geometry": {"coordinates":[3.595236063,51.1517944336],"type":"Point"}
}