{
  "type": "Feature",
  "properties": {
    "iso:country":"BE",
    "sg:address":"Kortrijkstraat 51",
    "sg:city":"Wevelgem",
    "sg:orig_category":"Erotische Etablissementen",
    "sg:phone":"+32 473 60 32 73",
    "sg:postcode":"8560",
    "sg:province":"West-Vlaanderen",
    "wof:name":"Relax Massage",
    "wof:placetype":"venue"
},
  "geometry": {"coordinates":[3.1883459091,50.8103599548],"type":"Point"}
}