{
  "type": "Feature",
  "properties": {
    "iso:country":"BE",
    "sg:address":"Rue De La L\u00e8che 36",
    "sg:city":"Li\u00e8ge",
    "sg:classifiers":[
        {
            "category":"Building & Trades",
            "subcategory":"Construction",
            "type":"Services"
        }
    ],
    "sg:phone":"+32 4 343 11 36",
    "sg:postcode":"4020",
    "sg:province":"Li\u00e8ge",
    "sg:tags":[
        "work",
        "public"
    ],
    "wof:name":"Entreprises Jean Moury Sa",
    "wof:placetype":"venue"
},
  "geometry": {"coordinates":[5.6105599403,50.6436080933],"type":"Point"}
}