{
  "type": "Feature",
  "properties": {
    "addr:full":"Sint-pietersaalststraat 26 Gent Oost-Vlaanderen 9000",
    "addr:housenumber":"26",
    "addr:postcode":"9000",
    "addr:street":"Sint-Pietersaalststraat;Oost-Vlaanderen",
    "iso:country":"BE",
    "sg:address":"Sint-pietersaalststraat 26",
    "sg:city":"Gent",
    "sg:classifiers":[
        {
            "category":"Building & Trades",
            "subcategory":"Construction",
            "type":"Services"
        }
    ],
    "sg:phone":"+32 9 221 30 96",
    "sg:postcode":"9000",
    "sg:province":"Oost-Vlaanderen",
    "sg:tags":[
        "ecological"
    ],
    "wof:name":"De Zevensprong",
    "wof:placetype":"venue"
},
  "geometry": {"coordinates":[3.7142109871,51.0308151245],"type":"Point"}
}