{
  "type": "Feature",
  "properties": {
    "addr:full":"Markt 25 Haacht Vlaams-Brabant 3150",
    "addr:housenumber":"25",
    "addr:postcode":"3150",
    "addr:street":"Markt",
    "iso:country":"BE",
    "sg:address":"Markt 25",
    "sg:city":"Haacht",
    "sg:orig_category":"Bloemen and planten",
    "sg:phone":"+32 2 242 29 64",
    "sg:postcode":"3150",
    "sg:province":"Vlaams-Brabant",
    "wof:name":"In 't Herberg Hofken",
    "wof:placetype":"venue"
},
  "geometry": {"coordinates":[4.6376681328,50.9765701294],"type":"Point"}
}