{
  "type": "Feature",
  "properties": {
    "addr:full":"Avenue Franklin Roosevelt 127 Bruxelles (ixelles) Bruxelles-Capitale 1050",
    "addr:housenumber":"127",
    "addr:postcode":"1050",
    "addr:street":"Avenue Franklin Roosevelt",
    "iso:country":"BE",
    "sg:address":"Avenue Franklin Roosevelt 127",
    "sg:city":"Bruxelles (ixelles)",
    "sg:classifiers":[
        {
            "category":"Health Services",
            "subcategory":"Health Practitioner",
            "type":"Services"
        }
    ],
    "sg:phone":"+32 2 672 60 93",
    "sg:postcode":"1050",
    "sg:province":"Bruxelles-Capitale",
    "sg:tags":[
        "physiotherapist"
    ],
    "wof:name":"Michaux F",
    "wof:placetype":"venue"
},
  "geometry": {"coordinates":[4.3920841217,50.7991256714],"type":"Point"}
}