{
  "type": "Feature",
  "properties": {
    "addr:full":"Chauss\u00e9e De Gand 112 Bruxelles (molenbeek-saint-jean) Bruxelles-Capitale 1080",
    "addr:housenumber":"112",
    "addr:postcode":"1080",
    "addr:street":"Chausse\u0301E De Gand",
    "iso:country":"BE",
    "sg:address":"Chauss\u00e9e De Gand 112",
    "sg:city":"Bruxelles (molenbeek-saint-jean)",
    "sg:classifiers":[
        {
            "category":"Personal",
            "subcategory":"Shoe Repair & Shine",
            "type":"Services"
        }
    ],
    "sg:phone":"+32 2 410 98 68",
    "sg:postcode":"1080",
    "sg:province":"Bruxelles-Capitale",
    "sg:tags":[
        "shoemaker"
    ],
    "wof:name":"Cordonnier 2000",
    "wof:placetype":"venue"
},
  "geometry": {"coordinates":[4.3356962204,50.8549728394],"type":"Point"}
}