{
  "type": "Feature",
  "properties": {
    "addr:full":"Gustaaf Peetersstraat 2ba Ranst Antwerpen 2520",
    "addr:housenumber":"2ba",
    "addr:postcode":"2520",
    "addr:street":"Gustaaf Peetersstraat",
    "iso:country":"BE",
    "sg:address":"Gustaaf Peetersstraat 2ba",
    "sg:city":"Ranst",
    "sg:orig_category":"Banques and organismes de cr\u00e9dit",
    "sg:phone":"+32 3 485 68 76",
    "sg:postcode":"2520",
    "sg:province":"Antwerpen",
    "wof:name":"Fortis",
    "wof:placetype":"venue"
},
  "geometry": {"coordinates":[4.602628231,51.1809005737],"type":"Point"}
}