{
  "type": "Feature",
  "properties": {
    "iso:country":"BE",
    "sg:address":"Hoeikensstraat 9",
    "sg:city":"Willebroek",
    "sg:classifiers":[
        {
            "category":"Wholesale",
            "subcategory":"Painting Supplies",
            "type":"Manufacturing & Wholesale Goods"
        }
    ],
    "sg:phone":"+32 3 886 26 37",
    "sg:postcode":"2830",
    "sg:province":"Antwerpen",
    "sg:tags":[
        "industrial",
        "-"
    ],
    "wof:name":"Containerbouw Magdaleens",
    "wof:placetype":"venue"
},
  "geometry": {"coordinates":[4.3498959541,51.0750350952],"type":"Point"}
}