{
  "type": "Feature",
  "properties": {
    "addr:full":"Rue De La Goffe 16 Li\u00c8ge Li\u00e8ge 4000",
    "addr:housenumber":"16",
    "addr:postcode":"4000",
    "addr:street":"Rue De La Goffe",
    "iso:country":"BE",
    "sg:address":"Rue De La Goffe 16",
    "sg:city":"Li\u00c8ge",
    "sg:orig_category":"Boucheries",
    "sg:phone":"+32 4 222 00 05",
    "sg:postcode":"4000",
    "sg:province":"Li\u00e8ge",
    "wof:name":"J.bourdouxhe Et Fils",
    "wof:placetype":"venue"
},
  "geometry": {"coordinates":[5.5780830383,50.6450691223],"type":"Point"}
}