{
  "type": "Feature",
  "properties": {
    "iso:country":"BE",
    "sg:address":"Scheepvaartlaan 1",
    "sg:city":"Brecht",
    "sg:classifiers":[
        {
            "category":"Professional",
            "subcategory":"Accounting & Tax Preparation",
            "type":"Services"
        }
    ],
    "sg:phone":"+32 3 219 80 80",
    "sg:postcode":"2960",
    "sg:province":"Antwerpen",
    "sg:tags":[
        "accountant"
    ],
    "wof:name":"Marcel Van De Velde",
    "wof:placetype":"venue"
},
  "geometry": {"coordinates":[4.5864510536,51.3108711243],"type":"Point"}
}