{
  "type": "Feature",
  "properties": {
    "iso:country":"BE",
    "sg:address":"Van De Wiellei 46",
    "sg:city":"Brasschaat",
    "sg:classifiers":[
        {
            "category":"Professional",
            "type":"Services"
        }
    ],
    "sg:phone":"+32 3 653 32 87",
    "sg:postcode":"2930",
    "sg:province":"Antwerpen",
    "sg:tags":[
        "entertainer"
    ],
    "wof:name":"Muse Gueule (la) Bvba",
    "wof:placetype":"venue"
},
  "geometry": {"coordinates":[4.4817070961,51.2940788269],"type":"Point"}
}