{
  "type": "Feature",
  "properties": {
    "iso:country":"BE",
    "sg:address":"Hendrik Heymanplein 16",
    "sg:city":"Sint-niklaas",
    "sg:orig_category":"Editeurs de journaux. Editeurs de revues and p\u00e9riodiques",
    "sg:phone":"+32 3 776 64 11",
    "sg:postcode":"9100",
    "sg:province":"Oost-Vlaanderen",
    "wof:name":"De Cirkel Waasland",
    "wof:placetype":"venue"
},
  "geometry": {"coordinates":[4.1413221359,51.1628227234],"type":"Point"}
}