{
  "type": "Feature",
  "properties": {
    "iso:country":"BE",
    "sg:address":"Avenue Jean-baptiste Depaire 80 Box 1",
    "sg:city":"Bruxelles",
    "sg:classifiers":[
        {
            "category":"Real Estate",
            "subcategory":"Architect",
            "type":"Services"
        }
    ],
    "sg:phone":"+32 2 479 03 59",
    "sg:postcode":"1020",
    "sg:province":"Bruxelles-Capitale",
    "wof:name":"Roos F",
    "wof:placetype":"venue"
},
  "geometry": {"coordinates":[4.3325591087,50.890625],"type":"Point"}
}