{
  "type": "Feature",
  "properties": {
    "addr:full":"Koningin Elisabethlei 54 Kapellen Antwerpen 2950",
    "addr:housenumber":"54",
    "addr:postcode":"2950",
    "addr:street":"Koningin Elisabethlei",
    "iso:country":"BE",
    "sg:address":"Koningin Elisabethlei 54",
    "sg:city":"Kapellen",
    "sg:orig_category":"Jardinage",
    "sg:phone":"+32 3 664 45 09",
    "sg:postcode":"2950",
    "sg:province":"Antwerpen",
    "wof:name":"Kristiaan Van Garsse",
    "wof:placetype":"venue"
},
  "geometry": {"coordinates":[4.4371080399,51.317363739],"type":"Point"}
}