{
  "type": "Feature",
  "properties": {
    "iso:country":"BE",
    "sg:address":"Rue De La Californie 64",
    "sg:city":"Bastogne",
    "sg:classifiers":[
        {
            "category":"Professional",
            "subcategory":"Accounting & Tax Preparation",
            "type":"Services"
        }
    ],
    "sg:phone":"+32 61 21 49 31",
    "sg:postcode":"6600",
    "sg:province":"Luxembourg",
    "sg:tags":[
        "accountant"
    ],
    "wof:name":"C. Charlier",
    "wof:placetype":"venue"
},
  "geometry": {"coordinates":[5.7279820442,49.9997444153],"type":"Point"}
}