{
  "type": "Feature",
  "properties": {
    "addr:full":"Q Matsijslei 37b16 Antwerpen Antwerpen 2018",
    "addr:housenumber":"37b16",
    "addr:postcode":"2018",
    "addr:street":"Matsijslei",
    "iso:country":"BE",
    "sg:address":"Q Matsijslei 37b16",
    "sg:city":"Antwerpen",
    "sg:orig_category":"Non-foodwinkels",
    "sg:phone":"+32 3 227 46 34",
    "sg:postcode":"2018",
    "sg:province":"Antwerpen",
    "wof:name":"Direct Bargain Supplies",
    "wof:placetype":"venue"
},
  "geometry": {"coordinates":[4.4173350334,51.2123222351],"type":"Point"}
}