{
  "type": "Feature",
  "properties": {
    "addr:full":"Rue Des Bugranes Namur (naninne) Namur 5100",
    "addr:postcode":"5100",
    "addr:street":"Rue Des Bugranes",
    "iso:country":"BE",
    "sg:address":"Rue Des Bugranes",
    "sg:city":"Namur (naninne)",
    "sg:classifiers":[
        {
            "category":"Building & Trades",
            "subcategory":"Pest Control",
            "type":"Services"
        }
    ],
    "sg:phone":"+32 81 40 01 17",
    "sg:postcode":"5100",
    "sg:province":"Namur",
    "sg:tags":[
        "painting",
        "contractor"
    ],
    "wof:name":"Humblet J-l",
    "wof:placetype":"venue"
},
  "geometry": {"coordinates":[4.8713750839,50.4566345215],"type":"Point"}
}