{
  "type": "Feature",
  "properties": {
    "addr:full":"Gaasbeekstraat 3 Sint-pieters-leeuw (oudenaken) Vlaams-Brabant 1600",
    "addr:housenumber":"3;1600",
    "addr:street":"Gaasbeekstraat;Vlaams-Brabant",
    "iso:country":"BE",
    "sg:address":"Gaasbeekstraat 3",
    "sg:city":"Sint-pieters-leeuw (oudenaken)",
    "sg:classifiers":[
        {
            "category":"Health Services",
            "subcategory":"Dentist",
            "type":"Services"
        }
    ],
    "sg:phone":"+32 2 532 00 25",
    "sg:postcode":"1600",
    "sg:province":"Vlaams-Brabant",
    "wof:name":"Lemaire V",
    "wof:placetype":"venue"
},
  "geometry": {"coordinates":[4.1928348541,50.7865600586],"type":"Point"}
}