{
  "type": "Feature",
  "properties": {
    "iso:country":"BE",
    "sg:address":"Rue D'achet 18",
    "sg:city":"Hamois",
    "sg:classifiers":[
        {
            "category":"Retail",
            "subcategory":"Veterinary Services",
            "type":"Services"
        }
    ],
    "sg:phone":"+32 83 21 86 09",
    "sg:postcode":"5360",
    "sg:province":"Namur",
    "sg:tags":[
        "veterinarian"
    ],
    "wof:name":"Daube Y",
    "wof:placetype":"venue"
},
  "geometry": {"coordinates":[5.1583957672,50.3400611877],"type":"Point"}
}