{
  "type": "Feature",
  "properties": {
    "iso:country":"BE",
    "sg:address":"Avenue Des H\u00eatres 32",
    "sg:city":"Rhode-saint-gen\u00e8se",
    "sg:classifiers":[
        {
            "category":"Health Services",
            "subcategory":"Doctor",
            "type":"Services"
        }
    ],
    "sg:phone":"+32 2 358 65 98",
    "sg:postcode":"1640",
    "sg:province":"Vlaams-Brabant",
    "sg:tags":[
        "medicinephysicians",
        "surgeon"
    ],
    "wof:name":"Cayphas Christophe",
    "wof:placetype":"venue"
},
  "geometry": {"coordinates":[4.3824510574,50.7570343018],"type":"Point"}
}