{
  "type": "Feature",
  "properties": {
    "addr:full":"Leeuwerikstraat 4 Koksijde West-Vlaanderen 8670",
    "addr:housenumber":"4",
    "addr:postcode":"8670",
    "addr:street":"Leeuwerikstraat",
    "iso:country":"BE",
    "sg:address":"Leeuwerikstraat 4",
    "sg:city":"Koksijde",
    "sg:orig_category":"Boekhouders",
    "sg:phone":"+32 58 23 24 84",
    "sg:postcode":"8670",
    "sg:province":"West-Vlaanderen",
    "wof:name":"Dirk Olislaegers",
    "wof:placetype":"venue"
},
  "geometry": {"coordinates":[2.6995279789,51.1390609741],"type":"Point"}
}