{
  "type": "Feature",
  "properties": {
    "addr:full":"Oude Baan 103 Bonheiden Antwerpen 2820",
    "addr:housenumber":"103",
    "addr:postcode":"2820",
    "addr:street":"Oude Baan",
    "iso:country":"BE",
    "sg:address":"Oude Baan 103",
    "sg:city":"Bonheiden",
    "sg:classifiers":[
        {
            "category":"Health Services",
            "subcategory":"Nursing And Care Facility",
            "type":"Services"
        }
    ],
    "sg:phone":"+32 15 55 33 48",
    "sg:postcode":"2820",
    "sg:province":"Antwerpen",
    "sg:tags":[
        "home"
    ],
    "wof:name":"Lambrecht X",
    "wof:placetype":"venue"
},
  "geometry": {"coordinates":[4.5295701027,51.0340156555],"type":"Point"}
}