{
  "type": "Feature",
  "properties": {
    "addr:full":"Nieuwkerkenstraat 168 Sint-niklaas Oost-Vlaanderen 9100",
    "addr:housenumber":"168",
    "addr:postcode":"9100",
    "addr:street":"Nieuwkerkenstraat",
    "iso:country":"BE",
    "sg:address":"Nieuwkerkenstraat 168",
    "sg:city":"Sint-niklaas",
    "sg:orig_category":"Banques and organismes de cr\u00e9dit",
    "sg:phone":"+32 3 776 65 45",
    "sg:postcode":"9100",
    "sg:province":"Oost-Vlaanderen",
    "wof:name":"Fortis",
    "wof:placetype":"venue"
},
  "geometry": {"coordinates":[4.1825838089,51.1876792908],"type":"Point"}
}