{
  "type": "Feature",
  "properties": {
    "addr:full":"Schepen Mengelslaan 9 Riemst Limburg 3770",
    "addr:housenumber":"9",
    "addr:postcode":"3770",
    "addr:street":"Schepen Mengelslaan",
    "iso:country":"BE",
    "sg:address":"Schepen Mengelslaan 9",
    "sg:city":"Riemst",
    "sg:orig_category":"Artsen and specialisten",
    "sg:phone":"+32 12 45 54 14",
    "sg:postcode":"3770",
    "sg:province":"Limburg",
    "wof:name":"Elise Bruninx",
    "wof:placetype":"venue"
},
  "geometry": {"coordinates":[5.5870299339,50.8265266418],"type":"Point"}
}