{
  "type": "Feature",
  "properties": {
    "addr:full":"Rue Salvador Allende 44 Binche Hainaut 7134",
    "addr:housenumber":"44",
    "addr:postcode":"7134",
    "addr:street":"Rue Salvador Allende",
    "iso:country":"BE",
    "sg:address":"Rue Salvador Allende 44",
    "sg:city":"Binche",
    "sg:orig_category":"Opticiens",
    "sg:phone":"+32 64 33 81 17",
    "sg:postcode":"7134",
    "sg:province":"Hainaut",
    "wof:name":"Maison Hainaut",
    "wof:placetype":"venue"
},
  "geometry": {"coordinates":[4.2187027931,50.4185066223],"type":"Point"}
}