{
  "type": "Feature",
  "properties": {
    "addr:full":"Dampoortstraat 2 Gent Oost-Vlaanderen 9000",
    "addr:housenumber":"2",
    "addr:postcode":"9000",
    "addr:street":"Dampoortstraat;Oost-Vlaanderen",
    "iso:country":"BE",
    "sg:address":"Dampoortstraat 2",
    "sg:city":"Gent",
    "sg:orig_category":"Textiel Verlichting and huishoudartikelen",
    "sg:phone":"+32 9 225 71 85",
    "sg:postcode":"9000",
    "sg:province":"Oost-Vlaanderen",
    "wof:name":"De Boeckx Ameublement",
    "wof:placetype":"venue"
},
  "geometry": {"coordinates":[3.7338109016,51.0565681458],"type":"Point"}
}