{
  "type": "Feature",
  "properties": {
    "addr:full":"Chauss\u00e9e De Louvain 417 Namur (bouge) Namur 5004",
    "addr:housenumber":"417",
    "addr:postcode":"5004",
    "addr:street":"Chausse\u0301E De Louvain",
    "iso:country":"BE",
    "sg:address":"Chauss\u00e9e De Louvain 417",
    "sg:city":"Namur (bouge)",
    "sg:classifiers":[
        {
            "category":"Professional",
            "subcategory":"Testing Lab",
            "type":"Services"
        }
    ],
    "sg:phone":"+32 81 21 07 85",
    "sg:postcode":"5004",
    "sg:province":"Namur",
    "sg:tags":[
        "chemist"
    ],
    "wof:name":"Fil\u00e9e M-c",
    "wof:placetype":"venue"
},
  "geometry": {"coordinates":[4.884578228,50.4823226929],"type":"Point"}
}