{
  "type": "Feature",
  "properties": {
    "addr:full":"Rue Valduc 70 Bruxelles (auderghem) Bruxelles-Capitale 1160",
    "addr:housenumber":"70",
    "addr:postcode":"1160",
    "addr:street":"Rue Valduc",
    "iso:country":"BE",
    "sg:address":"Rue Valduc 70",
    "sg:city":"Bruxelles (auderghem)",
    "sg:classifiers":[
        {
            "category":"Building & Trades",
            "subcategory":"Pest Control",
            "type":"Services"
        }
    ],
    "sg:phone":"+32 2 662 07 77",
    "sg:postcode":"1160",
    "sg:province":"Bruxelles-Capitale",
    "sg:tags":[
        "painting",
        "contractor"
    ],
    "wof:name":"Cop\u00e9e A",
    "wof:placetype":"venue"
},
  "geometry": {"coordinates":[4.4184222221,50.8189125061],"type":"Point"}
}