{
  "type": "Feature",
  "properties": {
    "addr:full":"Rue Jean-bapt. Serkeyn 83 Jette Bruxelles-Capitale 1090",
    "addr:housenumber":"83",
    "addr:postcode":"1090",
    "addr:street":"Rue Jean-Bapt. Serkeyn",
    "iso:country":"BE",
    "sg:address":"Rue Jean-bapt. Serkeyn 83",
    "sg:city":"Jette",
    "sg:orig_category":"Installation \u00e9lectrique industrielle. Mat\u00e9riaux de construction Constructions non r\u00e9sidentielles sp\u00e9",
    "sg:phone":"+32 2 428 44 79",
    "sg:postcode":"1090",
    "sg:province":"Bruxelles-Capitale",
    "wof:name":"T.i.b. - Ms",
    "wof:placetype":"venue"
},
  "geometry": {"coordinates":[4.3352890015,50.867477417],"type":"Point"}
}