{
  "type": "Feature",
  "properties": {
    "addr:full":"Groenenborgerlaan 16 Antwerp Antwerpen 2610",
    "addr:housenumber":"16",
    "addr:postcode":"2610",
    "addr:street":"Groenenborgerlaan",
    "iso:country":"BE",
    "sg:address":"Groenenborgerlaan 16",
    "sg:city":"Antwerp",
    "sg:classifiers":[
        {
            "category":"Industrial Area",
            "type":"Public Place"
        }
    ],
    "sg:phone":"+32 85 83 01 11",
    "sg:postcode":"2610",
    "sg:province":"Antwerpen",
    "sg:tags":[
        "large",
        "private"
    ],
    "wof:name":"Carmeuse S.a.",
    "wof:placetype":"venue"
},
  "geometry": {"coordinates":[5.077026844,50.4969902039],"type":"Point"}
}