{
  "type": "Feature",
  "properties": {
    "iso:country":"BE",
    "sg:address":"Burgstraat 28",
    "sg:city":"Gent",
    "sg:orig_category":"Alimentation sp\u00e9cialis\u00e9e",
    "sg:phone":"+32 9 223 62 92",
    "sg:postcode":"9000",
    "sg:province":"Oost-Vlaanderen",
    "wof:name":"Revogan",
    "wof:placetype":"venue"
},
  "geometry": {"coordinates":[3.7183709145,51.0566101074],"type":"Point"}
}