{
  "type": "Feature",
  "properties": {
    "addr:full":"Edegemsestraat 9 Mortsel Antwerpen 2640",
    "addr:housenumber":"9",
    "addr:postcode":"2640",
    "addr:street":"Edegemsestraat",
    "iso:country":"BE",
    "sg:address":"Edegemsestraat 9",
    "sg:city":"Mortsel",
    "sg:classifiers":[
        {
            "category":"Communications",
            "subcategory":"Film & Video Production",
            "type":"Services"
        }
    ],
    "sg:phone":"+32 3 449 75 10",
    "sg:postcode":"2640",
    "sg:province":"Antwerpen",
    "sg:tags":[
        "hiring",
        "-"
    ],
    "wof:name":"Centrum Video",
    "wof:placetype":"venue"
},
  "geometry": {"coordinates":[4.4487462044,51.1702461243],"type":"Point"}
}