{
  "type": "Feature",
  "properties": {
    "addr:full":"Nijverheidstraat 63 Mechelen Antwerpen 2800",
    "addr:housenumber":"63",
    "addr:postcode":"2800",
    "addr:street":"Nijverheidstraat",
    "iso:country":"BE",
    "sg:address":"Nijverheidstraat 63",
    "sg:city":"Mechelen",
    "sg:orig_category":"Woningbouw",
    "sg:phone":"+32 15 55 53 85",
    "sg:postcode":"2800",
    "sg:province":"Antwerpen",
    "wof:name":"Gaston De Maeyer",
    "wof:placetype":"venue"
},
  "geometry": {"coordinates":[4.4969520569,51.034198761],"type":"Point"}
}