{
  "type": "Feature",
  "properties": {
    "addr:full":"Oude Vaartstraat 37 Turnhout Antwerpen 2300",
    "addr:housenumber":"37",
    "addr:postcode":"2300",
    "addr:street":"Oude Vaartstraat",
    "iso:country":"BE",
    "sg:address":"Oude Vaartstraat 37",
    "sg:city":"Turnhout",
    "sg:classifiers":[
        {
            "category":"Utilities",
            "subcategory":"Fuel Oil & Lpg",
            "type":"Services"
        }
    ],
    "sg:phone":"+32 14 41 10 65",
    "sg:postcode":"2300",
    "sg:province":"Antwerpen",
    "wof:name":"Van Der Veken",
    "wof:placetype":"venue"
},
  "geometry": {"coordinates":[4.9463610649,51.3274803162],"type":"Point"}
}