{
  "type": "Feature",
  "properties": {
    "iso:country":"BE",
    "sg:address":"Baarzelestraat 32",
    "sg:city":"Aalter",
    "sg:orig_category":"Salles de spectacles",
    "sg:phone":"+32 9 374 56 25",
    "sg:postcode":"9880",
    "sg:province":"Oost-Vlaanderen",
    "wof:name":"Het Rat",
    "wof:placetype":"venue"
},
  "geometry": {"coordinates":[3.451406002,51.0922088623],"type":"Point"}
}