{
  "type": "Feature",
  "properties": {
    "addr:full":"Broekstraat 17 Leuven Vlaams-Brabant 3010",
    "addr:housenumber":"17",
    "addr:postcode":"3010",
    "addr:street":"Broekstraat",
    "iso:country":"BE",
    "sg:address":"Broekstraat 17",
    "sg:city":"Leuven",
    "sg:orig_category":"Services pour animaux domestiques",
    "sg:phone":"+32 16 35 01 34",
    "sg:postcode":"3010",
    "sg:province":"Vlaams-Brabant",
    "wof:name":"'t Trimmerke",
    "wof:placetype":"venue"
},
  "geometry": {"coordinates":[4.7006402016,50.8675498962],"type":"Point"}
}