{
  "type": "Feature",
  "properties": {
    "addr:full":"R Francq 47 Braine-l'alleud (grand) Brabant Wallon 1428",
    "addr:housenumber":"47",
    "addr:postcode":"1428",
    "addr:street":"Braine-L'Alleud Grand Brabant Wallon",
    "iso:country":"BE",
    "sg:address":"R Francq 47",
    "sg:city":"Braine-l'alleud (grand)",
    "sg:classifiers":[
        {
            "category":"Personal",
            "subcategory":"Beauty Salon",
            "type":"Services"
        }
    ],
    "sg:phone":"+32 2 384 17 59",
    "sg:postcode":"1428",
    "sg:province":"Brabant Wallon",
    "sg:tags":[
        "de",
        "coiffure"
    ],
    "wof:name":"Quoi Fur!...et A Mesure",
    "wof:placetype":"venue"
},
  "geometry": {"coordinates":[-0.7004899979,47.369140625],"type":"Point"}
}