{
  "type": "Feature",
  "properties": {
    "iso:country":"BE",
    "sg:address":"Rue Gaillard Cheval 144",
    "sg:city":"Vottem",
    "sg:classifiers":[
        {
            "category":"Building & Trades",
            "subcategory":"Electrical",
            "type":"Services"
        }
    ],
    "sg:phone":"+32 4 227 57 00",
    "sg:postcode":"4041",
    "sg:province":"Li\u00e8ge",
    "sg:tags":[
        "electro-mountings"
    ],
    "wof:name":"Belgorex S.a.",
    "wof:placetype":"venue"
},
  "geometry": {"coordinates":[5.5838527679,50.667591095],"type":"Point"}
}