{
  "type": "Feature",
  "properties": {
    "addr:full":"Oudstrijderslaan 16 Keerbergen Vlaams-Brabant 3140",
    "addr:housenumber":"16",
    "addr:postcode":"3140",
    "addr:street":"Oudstrijderslaan",
    "iso:country":"BE",
    "sg:address":"Oudstrijderslaan 16",
    "sg:city":"Keerbergen",
    "sg:classifiers":[
        {
            "category":"Retail",
            "subcategory":"Veterinary Services",
            "type":"Services"
        }
    ],
    "sg:phone":"+32 15 51 64 23",
    "sg:postcode":"3140",
    "sg:province":"Vlaams-Brabant",
    "sg:tags":[
        "veterinarian"
    ],
    "wof:name":"Meeus L",
    "wof:placetype":"venue"
},
  "geometry": {"coordinates":[4.6313610077,51.0027427673],"type":"Point"}
}