{
  "type": "Feature",
  "properties": {
    "addr:full":"Claeyspln 4 Mariakerke Oost-Vlaanderen 9910",
    "addr:housenumber":"4",
    "addr:postcode":"9910",
    "addr:street":"Claeyspln",
    "iso:country":"BE",
    "sg:address":"Claeyspln 4",
    "sg:city":"Mariakerke",
    "sg:classifiers":[
        {
            "category":"Banks & Credit Unions",
            "subcategory":"Bank",
            "type":"Services"
        }
    ],
    "sg:phone":"+32 52 26 69 33",
    "sg:postcode":"9910",
    "sg:province":"Oost-Vlaanderen",
    "wof:name":"Banque Bruxelles Lambert Sa",
    "wof:placetype":"venue"
},
  "geometry": {"coordinates":[3.4468200207,51.134601593],"type":"Point"}
}