{
  "type": "Feature",
  "properties": {
    "addr:full":"Rue De Nimy 137 Mons Hainaut 7000",
    "addr:housenumber":"137",
    "addr:postcode":"7000",
    "addr:street":"Rue De Nimy;Hainaut",
    "iso:country":"BE",
    "sg:address":"Rue De Nimy 137",
    "sg:city":"Mons",
    "sg:classifiers":[
        {
            "category":"Personal",
            "subcategory":"Beauty Salon",
            "type":"Services"
        }
    ],
    "sg:phone":"+32 65 33 83 79",
    "sg:postcode":"7000",
    "sg:province":"Hainaut",
    "sg:tags":[
        "de",
        "coiffure"
    ],
    "wof:name":"Coiffure Daniel",
    "wof:placetype":"venue"
},
  "geometry": {"coordinates":[3.9556438923,50.4590568542],"type":"Point"}
}