{
  "type": "Feature",
  "properties": {
    "iso:country":"BE",
    "sg:address":"Thonissenlaan 16",
    "sg:city":"Hasselt",
    "sg:classifiers":[
        {
            "category":"Personal",
            "subcategory":"Beauty Salon",
            "type":"Services"
        }
    ],
    "sg:phone":"+32 11 22 55 27",
    "sg:postcode":"3500",
    "sg:province":"Limburg",
    "sg:tags":[
        "de",
        "coiffure"
    ],
    "wof:name":"Frans Szajek",
    "wof:placetype":"venue"
},
  "geometry": {"coordinates":[5.3340401649,50.9324188232],"type":"Point"}
}