{
  "type": "Feature",
  "properties": {
    "iso:country":"BE",
    "sg:address":"Grand Place De Feluy 13",
    "sg:city":"Seneffe (feluy)",
    "sg:classifiers":[
        {
            "category":"Personal",
            "subcategory":"Beauty Salon",
            "type":"Services"
        }
    ],
    "sg:phone":"+32 67 87 76 76",
    "sg:postcode":"7181",
    "sg:province":"Hainaut",
    "sg:tags":[
        "lady",
        "-",
        "hairdressing"
    ],
    "wof:name":"Micheline",
    "wof:placetype":"venue"
},
  "geometry": {"coordinates":[4.2355780602,50.5422515869],"type":"Point"}
}