{
  "type": "Feature",
  "properties": {
    "iso:country":"BE",
    "sg:address":"Rue Prud'homme 29",
    "sg:city":"La Bruy\u00e8re (emines)",
    "sg:classifiers":[
        {
            "category":"Building & Trades",
            "subcategory":"Construction",
            "type":"Services"
        }
    ],
    "sg:phone":"+32 81 56 03 43",
    "sg:postcode":"5080",
    "sg:province":"Namur",
    "sg:tags":[
        "installation",
        "-",
        "central",
        "heating"
    ],
    "wof:name":"Duchemin M Ets",
    "wof:placetype":"venue"
},
  "geometry": {"coordinates":[4.8264899254,50.5170631409],"type":"Point"}
}