{
  "type": "Feature",
  "properties": {
    "addr:full":"Regenboogstraat 23 Bree Limburg 3960",
    "addr:housenumber":"23",
    "addr:postcode":"3960",
    "addr:street":"Regenboogstraat",
    "iso:country":"BE",
    "sg:address":"Regenboogstraat 23",
    "sg:city":"Bree",
    "sg:classifiers":[
        {
            "category":"Insurance",
            "subcategory":"Life Insurance",
            "type":"Services"
        }
    ],
    "sg:phone":"+32 89 47 17 53",
    "sg:postcode":"3960",
    "sg:province":"Limburg",
    "sg:tags":[
        "assurance"
    ],
    "wof:name":"Verzekeringen Baeten & Co",
    "wof:placetype":"venue"
},
  "geometry": {"coordinates":[5.6065812111,51.139377594],"type":"Point"}
}