{
  "type": "Feature",
  "properties": {
    "iso:country":"BE",
    "sg:address":"Liersesteenweg 114",
    "sg:city":"Ranst",
    "sg:classifiers":[
        {
            "category":"Personal",
            "subcategory":"Beauty Salon",
            "type":"Services"
        }
    ],
    "sg:phone":"+32 3 480 26 23",
    "sg:postcode":"2520",
    "sg:province":"Antwerpen",
    "sg:tags":[
        "de",
        "coiffure"
    ],
    "wof:name":"Franciscus Wuyts",
    "wof:placetype":"venue"
},
  "geometry": {"coordinates":[4.581179142,51.152923584],"type":"Point"}
}