{
  "type": "Feature",
  "properties": {
    "addr:full":"Avenue Mar\u00c9chal Foch 775 Mons Hainaut 7012",
    "addr:housenumber":"775",
    "addr:postcode":"7012",
    "addr:street":"Avenue Mare\u0301Chal Foch;Hainaut",
    "iso:country":"BE",
    "sg:address":"Avenue Mar\u00c9chal Foch 775",
    "sg:city":"Mons",
    "sg:classifiers":[
        {
            "category":"Banks & Credit Unions",
            "subcategory":"Investment Brokerage",
            "type":"Services"
        }
    ],
    "sg:phone":"+32 65 88 63 84",
    "sg:postcode":"7012",
    "sg:province":"Hainaut",
    "sg:tags":[
        "machine",
        "mat\u00e9riel",
        "de",
        "bureau",
        "gr"
    ],
    "wof:name":"Buro-tec Services Mons",
    "wof:placetype":"venue"
},
  "geometry": {"coordinates":[3.8894600868,50.4481964111],"type":"Point"}
}