{
  "type": "Feature",
  "properties": {
    "addr:full":"Rue Copernic 115 Box 1 Bruxelles (uccle) Bruxelles-Capitale 1180",
    "addr:housenumber":"115;1",
    "addr:postcode":"1180",
    "addr:street":"Rue Copernic;Box",
    "iso:country":"BE",
    "sg:address":"Rue Copernic 115 Box 1",
    "sg:city":"Bruxelles (uccle)",
    "sg:classifiers":[
        {
            "category":"Health Services",
            "subcategory":"Dentist",
            "type":"Services"
        }
    ],
    "sg:phone":"+32 2 374 63 61",
    "sg:postcode":"1180",
    "sg:province":"Bruxelles-Capitale",
    "wof:name":"Victoria D",
    "wof:placetype":"venue"
},
  "geometry": {"coordinates":[4.3642230034,50.7958717346],"type":"Point"}
}