{
  "type": "Feature",
  "properties": {
    "iso:country":"BE",
    "sg:address":"Rue De Bomer\u00c9e 134",
    "sg:city":"Montigny-le-tilleul",
    "sg:orig_category":"Agences immobili\u00e8res",
    "sg:phone":"+32 71 51 11 10",
    "sg:postcode":"6110",
    "sg:province":"Hainaut",
    "wof:name":"Trassud Immobilier",
    "wof:placetype":"venue"
},
  "geometry": {"coordinates":[4.3827137947,50.3750076294],"type":"Point"}
}