{
  "type": "Feature",
  "properties": {
    "addr:full":"Rue Oscar Thimus 34 Limbourg Li\u00e8ge 4830",
    "addr:housenumber":"34",
    "addr:postcode":"4830",
    "addr:street":"Rue Oscar Thimus",
    "iso:country":"BE",
    "sg:address":"Rue Oscar Thimus 34",
    "sg:city":"Limbourg",
    "sg:classifiers":[
        {
            "category":"Professional",
            "subcategory":"Computer Services",
            "type":"Services"
        }
    ],
    "sg:phone":"+32 80 76 36 87",
    "sg:postcode":"4830",
    "sg:province":"Li\u00e8ge",
    "sg:tags":[
        "-",
        "processing",
        "data",
        "software"
    ],
    "wof:name":"Cyber We@ver Studio",
    "wof:placetype":"venue"
},
  "geometry": {"coordinates":[5.9407401085,50.6112518311],"type":"Point"}
}