{
  "type": "Feature",
  "properties": {
    "addr:full":"Brusselsesteenweg 388 Asse Vlaams-Brabant 1730",
    "addr:housenumber":"388",
    "addr:postcode":"1730",
    "addr:street":"Brusselsesteenweg",
    "iso:country":"BE",
    "sg:address":"Brusselsesteenweg 388",
    "sg:city":"Asse",
    "sg:orig_category":"Entretien and r\u00e9parations de voitures",
    "sg:phone":"+32 2 452 30 39",
    "sg:postcode":"1730",
    "sg:province":"Vlaams-Brabant",
    "wof:name":"Mistral",
    "wof:placetype":"venue"
},
  "geometry": {"coordinates":[4.2377400398,50.8961982727],"type":"Point"}
}