{
  "type": "Feature",
  "properties": {
    "iso:country":"BE",
    "sg:address":"Rue Garibaldi 9",
    "sg:city":"Sint-gillis/saint-gilles",
    "sg:orig_category":"Rev\u00eatements de sols and murs",
    "sg:phone":"+32 2 537 90 99",
    "sg:postcode":"1060",
    "sg:province":"Bruxelles-Capitale",
    "wof:name":"Tapis Chinois",
    "wof:placetype":"venue"
},
  "geometry": {"coordinates":[4.3431181908,50.8256263733],"type":"Point"}
}