{
  "type": "Feature",
  "properties": {
    "iso:country":"BE",
    "sg:address":"Nieuwegen 24",
    "sg:city":"Kampenhout",
    "sg:orig_category":"Domotics",
    "sg:phone":"+32 16 65 69 09",
    "sg:postcode":"1910",
    "sg:province":"Vlaams-Brabant",
    "wof:name":"Astar",
    "wof:placetype":"venue"
},
  "geometry": {"coordinates":[4.5658302307,50.9486885071],"type":"Point"}
}