{
  "type": "Feature",
  "properties": {
    "iso:country":"BE",
    "sg:address":"Rue De Jemeppe 19a",
    "sg:city":"Sambreville (velaine-sur-sambre)",
    "sg:classifiers":[
        {
            "category":"Health Services",
            "subcategory":"Nursing And Care Facility",
            "type":"Services"
        }
    ],
    "sg:phone":"+32 71 71 26 15",
    "sg:postcode":"5060",
    "sg:province":"Namur",
    "sg:tags":[
        "home"
    ],
    "wof:name":"Stassart S",
    "wof:placetype":"venue"
},
  "geometry": {"coordinates":[4.6285200119,50.4448738098],"type":"Point"}
}