{
  "type": "Feature",
  "properties": {
    "iso:country":"BE",
    "sg:address":"Rue De France 14",
    "sg:city":"Erquelinnes (solre-sur-sambre)",
    "sg:classifiers":[
        {
            "category":"Building & Trades",
            "subcategory":"Landscaping Services",
            "type":"Services"
        }
    ],
    "sg:phone":"+32 71 55 67 58",
    "sg:postcode":"6560",
    "sg:province":"Hainaut",
    "sg:tags":[
        "forestry"
    ],
    "wof:name":"Bosquillon",
    "wof:placetype":"venue"
},
  "geometry": {"coordinates":[4.1422939301,50.3063812256],"type":"Point"}
}