{
  "type": "Feature",
  "properties": {
    "addr:full":"Rue Diricq 22 Epinois Hainaut 7134",
    "addr:housenumber":"22",
    "addr:postcode":"7134",
    "addr:street":"Rue Diricq;Hainaut",
    "iso:country":"BE",
    "sg:address":"Rue Diricq 22",
    "sg:city":"Epinois",
    "sg:classifiers":[
        {
            "category":"Insurance",
            "subcategory":"Life Insurance",
            "type":"Services"
        }
    ],
    "sg:phone":"+32 64 31 23 12",
    "sg:postcode":"7134",
    "sg:province":"Hainaut",
    "sg:tags":[
        "assurance"
    ],
    "wof:name":"Expert-bel",
    "wof:placetype":"venue"
},
  "geometry": {"coordinates":[4.1990962029,50.4042434692],"type":"Point"}
}