{
  "type": "Feature",
  "properties": {
    "addr:full":"Place Ferrer 15 Charleroi Hainaut 6060",
    "addr:housenumber":"15",
    "addr:postcode":"6060",
    "addr:street":"Place Ferrer;Hainaut",
    "iso:country":"BE",
    "sg:address":"Place Ferrer 15",
    "sg:city":"Charleroi",
    "sg:classifiers":[
        {
            "category":"Cafe",
            "type":"Food & Drink"
        }
    ],
    "sg:phone":"+32 71 41 28 30",
    "sg:postcode":"6060",
    "sg:province":"Hainaut",
    "sg:tags":[
        "caf\u00e9s"
    ],
    "wof:name":"Alfreda Bertinchamp",
    "wof:placetype":"venue"
},
  "geometry": {"coordinates":[4.4444818497,50.4060630798],"type":"Point"}
}