{
  "type": "Feature",
  "properties": {
    "iso:country":"BE",
    "sg:address":"Avenue Louis Libert 22",
    "sg:city":"Aywaille",
    "sg:orig_category":"Antiquit\u00e9s",
    "sg:phone":"+32 4 384 64 82",
    "sg:postcode":"4920",
    "sg:province":"Li\u00e8ge",
    "wof:name":"Maison Jade",
    "wof:placetype":"venue"
},
  "geometry": {"coordinates":[5.6765499115,50.4736099243],"type":"Point"}
}