{
  "type": "Feature",
  "properties": {
    "iso:country":"BE",
    "sg:address":"Duivelstraatje 3",
    "sg:city":"Ardooie",
    "sg:classifiers":[
        {
            "category":"Shopping",
            "subcategory":"Computers & Home Electronics",
            "type":"Retail Goods"
        }
    ],
    "sg:phone":"+32 51 74 00 00",
    "sg:postcode":"8850",
    "sg:province":"West-Vlaanderen",
    "sg:tags":[
        "computerapparatuur",
        "microsoft"
    ],
    "wof:name":"Sanders Computers",
    "wof:placetype":"venue"
},
  "geometry": {"coordinates":[3.1832818985,50.9789505005],"type":"Point"}
}