{
  "type": "Feature",
  "properties": {
    "addr:full":"Eikendreef 5a Kapellen Antwerpen 2950",
    "addr:housenumber":"5a",
    "addr:postcode":"2950",
    "addr:street":"Eikendreef",
    "iso:country":"BE",
    "sg:address":"Eikendreef 5a",
    "sg:city":"Kapellen",
    "sg:classifiers":[
        {
            "category":"Retail",
            "subcategory":"Repair Shop",
            "type":"Services"
        }
    ],
    "sg:phone":"+32 3 605 07 60",
    "sg:postcode":"2950",
    "sg:province":"Antwerpen",
    "sg:tags":[
        "radio",
        "television",
        "-",
        "maintenance"
    ],
    "wof:name":"Beeld & Klank Studio Van Havere",
    "wof:placetype":"venue"
},
  "geometry": {"coordinates":[4.4261388779,51.3119354248],"type":"Point"}
}