{
  "type": "Feature",
  "properties": {
    "addr:full":"Vezerlaan 13 Herk-de-stad Limburg 3540",
    "addr:housenumber":"13",
    "addr:postcode":"3540",
    "addr:street":"Vezerlaan",
    "iso:country":"BE",
    "sg:address":"Vezerlaan 13",
    "sg:city":"Herk-de-stad",
    "sg:classifiers":[
        {
            "category":"Personal",
            "subcategory":"Beauty Salon",
            "type":"Services"
        }
    ],
    "sg:phone":"+32 13 55 32 42",
    "sg:postcode":"3540",
    "sg:province":"Limburg",
    "sg:tags":[
        "de",
        "coiffure"
    ],
    "wof:name":"Coiffure Arlette",
    "wof:placetype":"venue"
},
  "geometry": {"coordinates":[5.1699109077,50.9408226013],"type":"Point"}
}