{
  "type": "Feature",
  "properties": {
    "iso:country":"BE",
    "sg:address":"Hendrik Consciencelaan 70",
    "sg:city":"Brugge",
    "sg:orig_category":"Kapsalons",
    "sg:phone":"+32 50 33 08 47",
    "sg:postcode":"8000",
    "sg:province":"West-Vlaanderen",
    "wof:name":"Coiffure Debonne",
    "wof:placetype":"venue"
},
  "geometry": {"coordinates":[3.2133989334,51.2045936584],"type":"Point"}
}