{
  "type": "Feature",
  "properties": {
    "addr:full":"Tieltstraat 15 Meulebeke West-Vlaanderen 8760",
    "addr:housenumber":"15",
    "addr:postcode":"8760",
    "addr:street":"Tieltstraat",
    "iso:country":"BE",
    "sg:address":"Tieltstraat 15",
    "sg:city":"Meulebeke",
    "sg:classifiers":[
        {
            "category":"Personal",
            "subcategory":"Beauty Salon",
            "type":"Services"
        }
    ],
    "sg:phone":"+32 51 48 89 71",
    "sg:postcode":"8760",
    "sg:province":"West-Vlaanderen",
    "sg:tags":[
        "de",
        "coiffure"
    ],
    "wof:name":"Eugeen Vervelghe",
    "wof:placetype":"venue"
},
  "geometry": {"coordinates":[3.2898800373,50.9522209167],"type":"Point"}
}