{
  "type": "Feature",
  "properties": {
    "addr:full":"Rue Vall\u00e9e 74b Chaudfontaine (vaux-sous-ch\u00e8vremont) Li\u00e8ge 4051",
    "addr:housenumber":"74b",
    "addr:postcode":"4051",
    "addr:street":"Rue Valle\u0301E",
    "iso:country":"BE",
    "sg:address":"Rue Vall\u00e9e 74b",
    "sg:city":"Chaudfontaine (vaux-sous-ch\u00e8vremont)",
    "sg:classifiers":[
        {
            "category":"Shopping",
            "subcategory":"Clothing, Apparel, & Fashions",
            "type":"Retail Goods"
        }
    ],
    "sg:phone":"+32 4 361 31 44",
    "sg:postcode":"4051",
    "sg:province":"Li\u00e8ge",
    "sg:tags":[
        "purchase",
        "clothing",
        "-",
        "sale",
        "second-hand"
    ],
    "wof:name":"Itineraire Bis",
    "wof:placetype":"venue"
},
  "geometry": {"coordinates":[5.6317358017,50.6022033691],"type":"Point"}
}