{
  "type": "Feature",
  "properties": {
    "addr:full":"Guillaume Lekeustraat 48 Anderlecht Bruxelles-Capitale 1070",
    "addr:housenumber":"48",
    "addr:postcode":"1070",
    "addr:street":"Guillaume Lekeustraat",
    "iso:country":"BE",
    "sg:address":"Guillaume Lekeustraat 48",
    "sg:city":"Anderlecht",
    "sg:orig_category":"Architecten",
    "sg:phone":"+32 2 522 69 93",
    "sg:postcode":"1070",
    "sg:province":"Bruxelles-Capitale",
    "wof:name":"Marc Duchesne",
    "wof:placetype":"venue"
},
  "geometry": {"coordinates":[4.2978658676,50.8285751343],"type":"Point"}
}