{
  "type": "Feature",
  "properties": {
    "addr:full":"Sint-truidersteenweg 162 Hasselt Limburg 3500",
    "addr:housenumber":"162",
    "addr:postcode":"3500",
    "addr:street":"Sint-Truidersteenweg",
    "iso:country":"BE",
    "sg:address":"Sint-truidersteenweg 162",
    "sg:city":"Hasselt",
    "sg:classifiers":[
        {
            "category":"Professional",
            "subcategory":"Management & Consulting",
            "type":"Services"
        }
    ],
    "sg:phone":"+32 11 27 29 77",
    "sg:postcode":"3500",
    "sg:province":"Limburg",
    "sg:tags":[
        "-",
        "processing",
        "data",
        "consultant"
    ],
    "wof:name":"C.c.a.",
    "wof:placetype":"venue"
},
  "geometry": {"coordinates":[5.3311800957,50.9221687317],"type":"Point"}
}