{
  "type": "Feature",
  "properties": {
    "addr:full":"Reyndersstraat 1 Antwerpen Antwerpen 2000",
    "addr:housenumber":"1",
    "addr:postcode":"2000",
    "addr:street":"Reyndersstraat",
    "iso:country":"BE",
    "sg:address":"Reyndersstraat 1",
    "sg:city":"Antwerpen",
    "sg:classifiers":[
        {
            "category":"Restaurant",
            "type":"Food & Drink"
        }
    ],
    "sg:phone":"+32 3 232 03 52",
    "sg:postcode":"2000",
    "sg:province":"Antwerpen",
    "wof:name":"Diafa",
    "wof:placetype":"venue"
},
  "geometry": {"coordinates":[4.3982357979,51.2195701599],"type":"Point"}
}