{
  "type": "Feature",
  "properties": {
    "iso:country":"BE",
    "sg:address":"Groeningestraat 33",
    "sg:city":"Kortrijk",
    "sg:orig_category":"Advocaten and juridische adviseurs",
    "sg:phone":"+32 56 22 32 77",
    "sg:postcode":"8500",
    "sg:province":"West-Vlaanderen",
    "wof:name":"Inge Vandenbroucke",
    "wof:placetype":"venue"
},
  "geometry": {"coordinates":[3.2700150013,50.8300819397],"type":"Point"}
}