{
  "type": "Feature",
  "properties": {
    "addr:full":"Zwijnaardsesteenweg 227 Gent Oost-Vlaanderen 9000",
    "addr:housenumber":"227",
    "addr:postcode":"9000",
    "addr:street":"Zwijnaardsesteenweg;Oost-Vlaanderen",
    "iso:country":"BE",
    "sg:address":"Zwijnaardsesteenweg 227",
    "sg:city":"Gent",
    "sg:classifiers":[
        {
            "category":"Food & Beverages",
            "subcategory":"Supermarket",
            "type":"Retail Goods"
        }
    ],
    "sg:phone":"+32 9 221 82 08",
    "sg:postcode":"9000",
    "sg:province":"Oost-Vlaanderen",
    "sg:tags":[
        "department",
        "store"
    ],
    "wof:name":"Profi Nv",
    "wof:placetype":"venue"
},
  "geometry": {"coordinates":[3.7306249142,51.0165290833],"type":"Point"}
}