{
  "type": "Feature",
  "properties": {
    "addr:full":"Avenue Adolphe Wansart 15 Bruxelles (uccle) Bruxelles-Capitale 1180",
    "addr:housenumber":"15",
    "addr:postcode":"1180",
    "addr:street":"Avenue Adolphe Wansart",
    "iso:country":"BE",
    "sg:address":"Avenue Adolphe Wansart 15",
    "sg:city":"Bruxelles (uccle)",
    "sg:classifiers":[
        {
            "category":"Real Estate",
            "subcategory":"Real Estate Services",
            "type":"Services"
        }
    ],
    "sg:phone":"+32 2 376 61 79",
    "sg:postcode":"1180",
    "sg:province":"Bruxelles-Capitale",
    "wof:name":"Octogone Sprl",
    "wof:placetype":"venue"
},
  "geometry": {"coordinates":[4.3312721252,50.7988357544],"type":"Point"}
}