{
  "type": "Feature",
  "properties": {
    "addr:full":"Handelslei 66 Zoersel Antwerpen 2980",
    "addr:housenumber":"66",
    "addr:postcode":"2980",
    "addr:street":"Handelslei",
    "iso:country":"BE",
    "sg:address":"Handelslei 66",
    "sg:city":"Zoersel",
    "sg:classifiers":[
        {
            "category":"Shopping",
            "subcategory":"Crafts & Fabrics",
            "type":"Retail Goods"
        }
    ],
    "sg:phone":"+32 3 481 78 36",
    "sg:postcode":"2980",
    "sg:province":"Antwerpen",
    "sg:tags":[
        "needlework",
        "lady"
    ],
    "wof:name":"Bobijntje ('t)",
    "wof:placetype":"venue"
},
  "geometry": {"coordinates":[4.6484470367,51.2730941772],"type":"Point"}
}