{
  "type": "Feature",
  "properties": {
    "iso:country":"BE",
    "sg:address":"Rue Des Tanneurs 3",
    "sg:city":"Estaimpuis",
    "sg:orig_category":"M\u00e9decins and sp\u00e9cialistes",
    "sg:phone":"+32 69 55 64 50",
    "sg:postcode":"7730",
    "sg:province":"Hainaut",
    "wof:name":"M. Hellin",
    "wof:placetype":"venue"
},
  "geometry": {"coordinates":[3.3137500286,50.6788368225],"type":"Point"}
}