{
  "type": "Feature",
  "properties": {
    "addr:full":"Muidepoort 85 Gent Oost-Vlaanderen 9000",
    "addr:housenumber":"85",
    "addr:postcode":"9000",
    "addr:street":"Muidepoort;Oost-Vlaanderen",
    "iso:country":"BE",
    "sg:address":"Muidepoort 85",
    "sg:city":"Gent",
    "sg:orig_category":"Blanchisseries and teintureries",
    "sg:phone":"+32 9 251 05 25",
    "sg:postcode":"9000",
    "sg:province":"Oost-Vlaanderen",
    "wof:name":"Rapid-was O Matic",
    "wof:placetype":"venue"
},
  "geometry": {"coordinates":[3.7312378883,51.0726318359],"type":"Point"}
}