{
  "type": "Feature",
  "properties": {
    "iso:country":"BE",
    "sg:address":"Groenstraat 1",
    "sg:city":"Lendelede",
    "sg:classifiers":[
        {
            "category":"Professional",
            "subcategory":"Accounting & Tax Preparation",
            "type":"Services"
        }
    ],
    "sg:phone":"+32 51 30 38 92",
    "sg:postcode":"8860",
    "sg:province":"West-Vlaanderen",
    "sg:tags":[
        "accountant"
    ],
    "wof:name":"Accountantskantoor Masschelein Vandencandelaere Bvba",
    "wof:placetype":"venue"
},
  "geometry": {"coordinates":[3.2346990108,50.8976020813],"type":"Point"}
}