{
  "type": "Feature",
  "properties": {
    "addr:full":"Chauss\u00e9e De Wavre 158 Grez-doiceau Brabant Wallon 1390",
    "addr:housenumber":"158",
    "addr:postcode":"1390",
    "addr:street":"Chausse\u0301E De Wavre",
    "iso:country":"BE",
    "sg:address":"Chauss\u00e9e De Wavre 158",
    "sg:city":"Grez-doiceau",
    "sg:classifiers":[
        {
            "category":"Home & Garden",
            "subcategory":"Building Materials",
            "type":"Retail Goods"
        }
    ],
    "sg:phone":"+32 10 84 24 70",
    "sg:postcode":"1390",
    "sg:province":"Brabant Wallon",
    "sg:tags":[
        "granite",
        "stone",
        "natural",
        "marble"
    ],
    "wof:name":"Louis Marbrerie",
    "wof:placetype":"venue"
},
  "geometry": {"coordinates":[4.6873898506,50.7466812134],"type":"Point"}
}