{
  "type": "Feature",
  "properties": {
    "addr:full":"Hannuitstraat 8 Gingelom Limburg 3890",
    "addr:housenumber":"8",
    "addr:postcode":"3890",
    "addr:street":"Hannuitstraat",
    "iso:country":"BE",
    "sg:address":"Hannuitstraat 8",
    "sg:city":"Gingelom",
    "sg:classifiers":[
        {
            "category":"Cafe",
            "type":"Food & Drink"
        }
    ],
    "sg:phone":"+32 11 88 36 85",
    "sg:postcode":"3890",
    "sg:province":"Limburg",
    "sg:tags":[
        "caf\u00e9s"
    ],
    "wof:name":"Sonja Lenotte",
    "wof:placetype":"venue"
},
  "geometry": {"coordinates":[5.1271967888,50.7187614441],"type":"Point"}
}