{
  "type": "Feature",
  "properties": {
    "addr:full":"Place Albert Ier 41 Malmedy Li\u00e8ge 4960",
    "addr:housenumber":"41",
    "addr:postcode":"4960",
    "addr:street":"Place Albert Ier",
    "iso:country":"BE",
    "sg:address":"Place Albert Ier 41",
    "sg:city":"Malmedy",
    "sg:classifiers":[
        {
            "category":"Restaurant",
            "type":"Food & Drink"
        }
    ],
    "sg:phone":"+32 80 33 96 36",
    "sg:postcode":"4960",
    "sg:province":"Li\u00e8ge",
    "wof:name":"Restaurant A V\u00ce M\u00c2m'd\u00ce",
    "wof:placetype":"venue"
},
  "geometry": {"coordinates":[6.0282578468,50.4255599976],"type":"Point"}
}