{
  "type": "Feature",
  "properties": {
    "iso:country":"BE",
    "sg:address":"Boulevard Sainctelette 7",
    "sg:city":"Mons",
    "sg:orig_category":"Banken and kredietinstellingen",
    "sg:phone":"+32 65 35 22 42",
    "sg:postcode":"7000",
    "sg:province":"Hainaut",
    "wof:name":"Banca Monte Paschi Belgio",
    "wof:placetype":"venue"
},
  "geometry": {"coordinates":[3.9472749233,50.4464759827],"type":"Point"}
}