{
  "type": "Feature",
  "properties": {
    "iso:country":"BE",
    "sg:address":"Rue De Celles 6",
    "sg:city":"Geer (hollogne-sur-geer)",
    "sg:classifiers":[
        {
            "category":"Recreation",
            "subcategory":"Dance Hall",
            "type":"Entertainment"
        }
    ],
    "sg:phone":"+32 19 51 17 29",
    "sg:postcode":"4250",
    "sg:province":"Li\u00e8ge",
    "sg:tags":[
        "discotheque"
    ],
    "wof:name":"Open Air",
    "wof:placetype":"venue"
},
  "geometry": {"coordinates":[5.2177119255,50.6700706482],"type":"Point"}
}