{
  "type": "Feature",
  "properties": {
    "addr:full":"Burg. Maenhautstr. 1bb Merelbeke Oost-Vlaanderen 9820",
    "addr:housenumber":"9820",
    "addr:street":"Burg.",
    "iso:country":"BE",
    "sg:address":"Burg. Maenhautstr. 1bb",
    "sg:city":"Merelbeke",
    "sg:orig_category":"Enseignement maternel and primaire",
    "sg:phone":"+32 9 252 16 95",
    "sg:postcode":"9820",
    "sg:province":"Oost-Vlaanderen",
    "wof:name":"Gemeentelijke Basisschool",
    "wof:placetype":"venue"
},
  "geometry": {"coordinates":[3.7454690933,50.9947395325],"type":"Point"}
}