{
  "type": "Feature",
  "properties": {
    "iso:country":"BE",
    "sg:address":"Sint-pietersstraat 43",
    "sg:city":"Ninove",
    "sg:orig_category":"Kapsalons",
    "sg:phone":"+32 54 33 07 68",
    "sg:postcode":"9402",
    "sg:province":"Oost-Vlaanderen",
    "wof:name":"Frans Timmermans",
    "wof:placetype":"venue"
},
  "geometry": {"coordinates":[4.0350298882,50.8243484497],"type":"Point"}
}