{
  "type": "Feature",
  "properties": {
    "iso:country":"BE",
    "sg:address":"Oude Nijvelse Baan 50ba",
    "sg:city":"Sint-genesius-rode/rhode-saint-gen\u00c8se",
    "sg:orig_category":"Boekhouders",
    "sg:phone":"+32 2 380 38 28",
    "sg:postcode":"1640",
    "sg:province":"Vlaams-Brabant",
    "wof:name":"Jean-yves Vanderheyden",
    "wof:placetype":"venue"
},
  "geometry": {"coordinates":[4.3249030113,50.7359352112],"type":"Point"}
}