{
  "type": "Feature",
  "properties": {
    "addr:full":"De Dammenlaan 17 Dendermonde Oost-Vlaanderen 9200",
    "addr:housenumber":"17",
    "addr:postcode":"9200",
    "addr:street":"De Dammenlaan;Oost-Vlaanderen",
    "iso:country":"BE",
    "sg:address":"De Dammenlaan 17",
    "sg:city":"Dendermonde",
    "sg:orig_category":"Jardinage. D\u00e9corateurs d'int\u00e9rieur",
    "sg:phone":"+32 52 22 28 79",
    "sg:postcode":"9200",
    "sg:province":"Oost-Vlaanderen",
    "wof:name":"Johan De Weerdt",
    "wof:placetype":"venue"
},
  "geometry": {"coordinates":[4.0809149742,51.0335426331],"type":"Point"}
}