{
  "type": "Feature",
  "properties": {
    "addr:full":"Avenue De L'agriculture 49 Li\u00c8ge Li\u00e8ge 4030",
    "addr:housenumber":"49",
    "addr:postcode":"4030",
    "addr:street":"Avenue De L'Agriculture",
    "iso:country":"BE",
    "sg:address":"Avenue De L'agriculture 49",
    "sg:city":"Li\u00c8ge",
    "sg:orig_category":"Textiles. Eclairage et \u00e9quipements du foyer",
    "sg:phone":"+32 4 343 06 34",
    "sg:postcode":"4030",
    "sg:province":"Li\u00e8ge",
    "wof:name":"Maison Lognoul",
    "wof:placetype":"venue"
},
  "geometry": {"coordinates":[5.606967926,50.6278305054],"type":"Point"}
}