{
  "type": "Feature",
  "properties": {
    "addr:full":"Rue Du Culot 23 Nivelles Brabant Wallon 1402",
    "addr:housenumber":"23;1402",
    "addr:street":"Rue Du Culot",
    "iso:country":"BE",
    "sg:address":"Rue Du Culot 23",
    "sg:city":"Nivelles",
    "sg:orig_category":"Loodgieterij, verwarming and sanitaire installaties",
    "sg:phone":"+32 67 84 41 17",
    "sg:postcode":"1402",
    "sg:province":"Brabant Wallon",
    "wof:name":"Jacques Heerman",
    "wof:placetype":"venue"
},
  "geometry": {"coordinates":[4.3672761917,50.6011314392],"type":"Point"}
}