{
  "type": "Feature",
  "properties": {
    "addr:full":"All\u00c9e Des Platanes 28 Vise Li\u00e8ge 4600",
    "addr:housenumber":"28",
    "addr:postcode":"4600",
    "addr:street":"Alle\u0301E Des Platanes",
    "iso:country":"BE",
    "sg:address":"All\u00c9e Des Platanes 28",
    "sg:city":"Vise",
    "sg:orig_category":"Artistes ind\u00e9pendants",
    "sg:phone":"+32 4 379 25 50",
    "sg:postcode":"4600",
    "sg:province":"Li\u00e8ge",
    "wof:name":"Marie-therese Finck",
    "wof:placetype":"venue"
},
  "geometry": {"coordinates":[5.7022600174,50.7421417236],"type":"Point"}
}