{
  "type": "Feature",
  "properties": {
    "addr:full":"Rue Des Trixhes 17 Li\u00e8ge 1 (jupille-sur-meuse) Li\u00e8ge 4020",
    "addr:housenumber":"17;1",
    "addr:postcode":"4020",
    "addr:street":"Rue Des Trixhes;Jupille-Sur-Meuse Lie\u0300Ge",
    "iso:country":"BE",
    "sg:address":"Rue Des Trixhes 17",
    "sg:city":"Li\u00e8ge 1 (jupille-sur-meuse)",
    "sg:classifiers":[
        {
            "category":"Building & Trades",
            "subcategory":"Construction",
            "type":"Services"
        }
    ],
    "sg:phone":"+32 4 362 42 33",
    "sg:postcode":"4020",
    "sg:province":"Li\u00e8ge",
    "sg:tags":[
        "installation",
        "-",
        "central",
        "heating"
    ],
    "wof:name":"Juvign\u00e9 M",
    "wof:placetype":"venue"
},
  "geometry": {"coordinates":[5.6328668594,50.6412582397],"type":"Point"}
}