{
  "type": "Feature",
  "properties": {
    "addr:full":"Drieputtenstraat 95 Zele Oost-Vlaanderen 9240",
    "addr:housenumber":"95",
    "addr:postcode":"9240",
    "addr:street":"Drieputtenstraat",
    "iso:country":"BE",
    "sg:address":"Drieputtenstraat 95",
    "sg:city":"Zele",
    "sg:orig_category":"Pain, p\u00e2tisseries and confiseries",
    "sg:phone":"+32 52 44 41 80",
    "sg:postcode":"9240",
    "sg:province":"Oost-Vlaanderen",
    "wof:name":"Oosters Brood",
    "wof:placetype":"venue"
},
  "geometry": {"coordinates":[4.0311441422,51.0683403015],"type":"Point"}
}