{
  "type": "Feature",
  "properties": {
    "addr:full":"Burg Vandenbogaerdenlaan 38 Izegem West-Vlaanderen 8870",
    "addr:housenumber":"38",
    "addr:postcode":"8870",
    "addr:street":"Burg Vandenbogaerdenlaan",
    "iso:country":"BE",
    "sg:address":"Burg Vandenbogaerdenlaan 38",
    "sg:city":"Izegem",
    "sg:classifiers":[
        {
            "category":"Building & Trades",
            "subcategory":"Plumbing",
            "type":"Services"
        }
    ],
    "sg:phone":"+32 51 30 08 39",
    "sg:postcode":"8870",
    "sg:province":"West-Vlaanderen",
    "sg:tags":[
        "diver",
        "commerce",
        "gr",
        "pour",
        "equipement"
    ],
    "wof:name":"Isybel",
    "wof:placetype":"venue"
},
  "geometry": {"coordinates":[3.211081028,50.9147224426],"type":"Point"}
}