{
  "type": "Feature",
  "properties": {
    "addr:full":"Thier De L'eglise 2 Burdinne (oteppe) Li\u00e8ge 4210",
    "addr:housenumber":"2",
    "addr:postcode":"4210",
    "addr:street":"Thier De L'Eglise",
    "iso:country":"BE",
    "sg:address":"Thier De L'eglise 2",
    "sg:city":"Burdinne (oteppe)",
    "sg:orig_category":"Non-Classified Establishments",
    "sg:phone":"+32 85 51 43 33",
    "sg:postcode":"4210",
    "sg:province":"Li\u00e8ge",
    "wof:name":"Wouters A",
    "wof:placetype":"venue"
},
  "geometry": {"coordinates":[5.1263718605,50.5817184448],"type":"Point"}
}