{
  "type": "Feature",
  "properties": {
    "iso:country":"BE",
    "sg:address":"Pottebezemstraat 43",
    "sg:city":"Torhout",
    "sg:orig_category":"V\u00e9hicules automobiles",
    "sg:phone":"+32 50 21 26 46",
    "sg:postcode":"8820",
    "sg:province":"West-Vlaanderen",
    "wof:name":"Garage Vandecaveye",
    "wof:placetype":"venue"
},
  "geometry": {"coordinates":[3.1190218925,51.0801925659],"type":"Point"}
}