{
  "type": "Feature",
  "properties": {
    "iso:country":"BE",
    "sg:address":"Rue Charles Heuze 61",
    "sg:city":"Sambreville (auvelais)",
    "sg:classifiers":[
        {
            "category":"Manufacturing",
            "subcategory":"Tools & Machinery",
            "type":"Manufacturing & Wholesale Goods"
        }
    ],
    "sg:phone":"+32 71 77 13 72",
    "sg:postcode":"5060",
    "sg:province":"Namur",
    "sg:tags":[
        "-"
    ],
    "wof:name":"Laverdeur Sprl",
    "wof:placetype":"venue"
},
  "geometry": {"coordinates":[4.6285200119,50.4448738098],"type":"Point"}
}