{
  "type": "Feature",
  "properties": {
    "iso:country":"BE",
    "sg:address":"Rue Au Bois 345bb",
    "sg:city":"Sint-pieters-woluwe/woluwe-saint-pierre",
    "sg:orig_category":"M\u00e9decins and sp\u00e9cialistes",
    "sg:phone":"+32 2 762 01 23",
    "sg:postcode":"1150",
    "sg:province":"Bruxelles-Capitale",
    "wof:name":"Robert Demol",
    "wof:placetype":"venue"
},
  "geometry": {"coordinates":[4.4537959099,50.8299217224],"type":"Point"}
}