{
  "type": "Feature",
  "properties": {
    "iso:country":"BE",
    "sg:address":"Dorpsstraat 42",
    "sg:city":"Niel",
    "sg:classifiers":[
        {
            "category":"Retail",
            "subcategory":"Event Space",
            "type":"Services"
        }
    ],
    "sg:phone":"+32 3 294 03 52",
    "sg:postcode":"2845",
    "sg:province":"Antwerpen",
    "sg:tags":[
        "rental",
        "-",
        "hall"
    ],
    "wof:name":"Feestzaal Den Tighel",
    "wof:placetype":"venue"
},
  "geometry": {"coordinates":[4.3265972137,51.1084747314],"type":"Point"}
}