{
  "type": "Feature",
  "properties": {
    "iso:country":"BE",
    "sg:address":"Route De Bouillon 16",
    "sg:city":"Bouillon (noirefontaine)",
    "sg:classifiers":[
        {
            "category":"Retail",
            "subcategory":"Auto Repair",
            "type":"Services"
        }
    ],
    "sg:phone":"+32 61 46 04 55",
    "sg:postcode":"6831",
    "sg:province":"Luxembourg",
    "sg:tags":[
        "garage"
    ],
    "wof:name":"Depierreux A",
    "wof:placetype":"venue"
},
  "geometry": {"coordinates":[5.0937948227,49.8202438354],"type":"Point"}
}