{
  "type": "Feature",
  "properties": {
    "addr:full":"Clemenceaustraat 198 Sint-katelijne-waver Antwerpen 2860",
    "addr:housenumber":"198",
    "addr:postcode":"2860",
    "addr:street":"Clemenceaustraat",
    "iso:country":"BE",
    "sg:address":"Clemenceaustraat 198",
    "sg:city":"Sint-katelijne-waver",
    "sg:orig_category":"Tuinen",
    "sg:phone":"+32 15 32 15 02",
    "sg:postcode":"2860",
    "sg:province":"Antwerpen",
    "wof:name":"De Laet",
    "wof:placetype":"venue"
},
  "geometry": {"coordinates":[4.4915561676,51.0632400513],"type":"Point"}
}