{
  "type": "Feature",
  "properties": {
    "iso:country":"BE",
    "sg:address":"Rue Chauss\u00e9e Romaine 1",
    "sg:city":"Meix-devant-virton (g\u00e9rouville)",
    "sg:classifiers":[
        {
            "category":"Farming",
            "subcategory":"Fish & Marine Products",
            "type":"Manufacturing & Wholesale Goods"
        }
    ],
    "sg:phone":"+32 63 57 60 20",
    "sg:postcode":"6769",
    "sg:province":"Luxembourg",
    "sg:tags":[
        "equipment",
        "fishery"
    ],
    "wof:name":"Fontaine Aux Truites (la)",
    "wof:placetype":"venue"
},
  "geometry": {"coordinates":[5.4125189781,49.6144256592],"type":"Point"}
}