{
  "type": "Feature",
  "properties": {
    "addr:full":"Gros Thier 77 Tinlot Li\u00e8ge 4557",
    "addr:housenumber":"77",
    "addr:postcode":"4557",
    "addr:street":"Gros Thier",
    "iso:country":"BE",
    "sg:address":"Gros Thier 77",
    "sg:city":"Tinlot",
    "sg:orig_category":"Imprimeries and copyshops. Installation de menuiserie en bois and plastique",
    "sg:phone":"+32 85 51 31 63",
    "sg:postcode":"4557",
    "sg:province":"Li\u00e8ge",
    "wof:name":"Zebre A L'envers",
    "wof:placetype":"venue"
},
  "geometry": {"coordinates":[5.4132299423,50.4516906738],"type":"Point"}
}