{
  "type": "Feature",
  "properties": {
    "addr:full":"Dorpsstraat 37 Oudenburg West-Vlaanderen 8460",
    "addr:housenumber":"37",
    "addr:postcode":"8460",
    "addr:street":"Dorpsstraat",
    "iso:country":"BE",
    "sg:address":"Dorpsstraat 37",
    "sg:city":"Oudenburg",
    "sg:orig_category":"Entretien and r\u00e9parations de voitures",
    "sg:phone":"+32 59 26 63 85",
    "sg:postcode":"8460",
    "sg:province":"West-Vlaanderen",
    "wof:name":"Garage Goemaere",
    "wof:placetype":"venue"
},
  "geometry": {"coordinates":[3.0023450851,51.1840553284],"type":"Point"}
}