{
  "type": "Feature",
  "properties": {
    "addr:full":"Stapelplein 75 Gent Oost-Vlaanderen 9000",
    "addr:housenumber":"75",
    "addr:postcode":"9000",
    "addr:street":"Stapelplein;Oost-Vlaanderen",
    "iso:country":"BE",
    "sg:address":"Stapelplein 75",
    "sg:city":"Gent",
    "sg:orig_category":"Postkantoren",
    "sg:phone":"+32 9 224 98 00",
    "sg:postcode":"9000",
    "sg:province":"Oost-Vlaanderen",
    "wof:name":"De Post",
    "wof:placetype":"venue"
},
  "geometry": {"coordinates":[3.7341051102,51.0647697449],"type":"Point"}
}