{
  "type": "Feature",
  "properties": {
    "addr:full":"Mechelsesteenweg 121 Wezembeek-oppem/wezembeek-oppem Vlaams-Brabant 1970",
    "addr:housenumber":"121",
    "addr:postcode":"1970",
    "addr:street":"Mechelsesteenweg",
    "iso:country":"BE",
    "sg:address":"Mechelsesteenweg 121",
    "sg:city":"Wezembeek-oppem/wezembeek-oppem",
    "sg:orig_category":"Dierenartsen",
    "sg:phone":"+32 2 731 65 32",
    "sg:postcode":"1970",
    "sg:province":"Vlaams-Brabant",
    "wof:name":"Roland Leroy",
    "wof:placetype":"venue"
},
  "geometry": {"coordinates":[4.4996399879,50.8444709778],"type":"Point"}
}