{
  "type": "Feature",
  "properties": {
    "addr:full":"Les Colir 55 Braine-le-ch\u00e2teau Brabant Wallon 1440",
    "addr:housenumber":"55",
    "addr:postcode":"1440",
    "iso:country":"BE",
    "sg:address":"Les Colir 55",
    "sg:city":"Braine-le-ch\u00e2teau",
    "sg:classifiers":[
        {
            "category":"Professional",
            "subcategory":"Management & Consulting",
            "type":"Services"
        }
    ],
    "sg:phone":"+32 2 366 04 22",
    "sg:postcode":"1440",
    "sg:province":"Brabant Wallon",
    "sg:tags":[
        "-",
        "processing",
        "data",
        "consultant"
    ],
    "wof:name":"Apb Consult",
    "wof:placetype":"venue"
},
  "geometry": {"coordinates":[4.2641201019,50.6790008545],"type":"Point"}
}