{
  "type": "Feature",
  "properties": {
    "addr:full":"Rue De S\u00c9vign\u00c9 1a Anderlecht/anderlecht Bruxelles-Capitale 1070",
    "addr:housenumber":"1a",
    "addr:postcode":"1070",
    "addr:street":"Rue De Se\u0301Vigne\u0301",
    "iso:country":"BE",
    "sg:address":"Rue De S\u00c9vign\u00c9 1a",
    "sg:city":"Anderlecht/anderlecht",
    "sg:classifiers":[
        {
            "category":"Arena",
            "subcategory":"Sports Club",
            "type":"Entertainment"
        }
    ],
    "sg:phone":"+32 2 523 23 20",
    "sg:postcode":"1070",
    "sg:province":"Bruxelles-Capitale",
    "sg:tags":[
        "de"
    ],
    "wof:name":"Aikido Moortebeek",
    "wof:placetype":"venue"
},
  "geometry": {"coordinates":[4.2907419205,50.8450508118],"type":"Point"}
}