{
  "type": "Feature",
  "properties": {
    "addr:full":"Rte De Philippeville 307 Couillet Hainaut 6010",
    "addr:housenumber":"307",
    "addr:postcode":"6010",
    "addr:street":"Rte De Philippeville",
    "iso:country":"BE",
    "sg:address":"Rte De Philippeville 307",
    "sg:city":"Couillet",
    "sg:classifiers":[
        {
            "category":"Manufacturing",
            "subcategory":"Metals",
            "type":"Manufacturing & Wholesale Goods"
        }
    ],
    "sg:phone":"+32 71 47 02 14",
    "sg:postcode":"6010",
    "sg:province":"Hainaut",
    "sg:tags":[
        "metallurgy",
        "metalworking"
    ],
    "wof:name":"Alexandre & Cie S.a.",
    "wof:placetype":"venue"
},
  "geometry": {"coordinates":[4.4642820358,50.3842544556],"type":"Point"}
}