{
  "type": "Feature",
  "properties": {
    "iso:country":"BE",
    "sg:address":"Rue Bruy\u00c8re De Virginal 82",
    "sg:city":"Ittre",
    "sg:orig_category":"Goederenvervoer over de weg",
    "sg:phone":"+32 67 64 66 31",
    "sg:postcode":"1460",
    "sg:province":"Brabant Wallon",
    "wof:name":"Roger Dejean",
    "wof:placetype":"venue"
},
  "geometry": {"coordinates":[4.2423901558,50.6423187256],"type":"Point"}
}