{
  "type": "Feature",
  "properties": {
    "addr:full":"Westlaan 148 Heusden-zolder Limburg 3550",
    "addr:housenumber":"148",
    "addr:postcode":"3550",
    "addr:street":"Westlaan",
    "iso:country":"BE",
    "sg:address":"Westlaan 148",
    "sg:city":"Heusden-zolder",
    "sg:orig_category":"Artsen and specialisten",
    "sg:phone":"+32 11 42 94 11",
    "sg:postcode":"3550",
    "sg:province":"Limburg",
    "wof:name":"G. Loosen",
    "wof:placetype":"venue"
},
  "geometry": {"coordinates":[5.2548718452,51.0005187988],"type":"Point"}
}