{
  "type": "Feature",
  "properties": {
    "iso:country":"BE",
    "sg:address":"Quai Vercour 121",
    "sg:city":"Li\u00e8ge 1 (sclessin)",
    "sg:classifiers":[
        {
            "category":"Food & Beverages",
            "subcategory":"Groceries & Convenience Stores",
            "type":"Retail Goods"
        }
    ],
    "sg:phone":"+32 4 252 28 18",
    "sg:postcode":"4000",
    "sg:province":"Li\u00e8ge",
    "sg:tags":[
        "baker",
        "-",
        "ingredient"
    ],
    "wof:name":"Denis Ets Sa",
    "wof:placetype":"venue"
},
  "geometry": {"coordinates":[5.5523328781,50.6079101562],"type":"Point"}
}