{
  "type": "Feature",
  "properties": {
    "iso:country":"BE",
    "sg:address":"Larumseweg 43ba",
    "sg:city":"Olen",
    "sg:orig_category":"Plaatsen van vloer- and muurbekleding Schilders",
    "sg:phone":"+32 14 22 17 64",
    "sg:postcode":"2250",
    "sg:province":"Antwerpen",
    "wof:name":"Has",
    "wof:placetype":"venue"
},
  "geometry": {"coordinates":[4.9121050835,51.1665725708],"type":"Point"}
}