{
  "type": "Feature",
  "properties": {
    "iso:country":"BE",
    "sg:address":"Rue Des Nations-unies 72",
    "sg:city":"Ans",
    "sg:orig_category":"Installation \u00e9lectrique r\u00e9sidentielle",
    "sg:phone":"+32 4 246 02 27",
    "sg:postcode":"4432",
    "sg:province":"Li\u00e8ge",
    "wof:name":"Franco Rosmarino",
    "wof:placetype":"venue"
},
  "geometry": {"coordinates":[5.522687912,50.6681175232],"type":"Point"}
}