{
  "type": "Feature",
  "properties": {
    "iso:country":"BE",
    "sg:address":"Vonderpad 24",
    "sg:city":"Retie",
    "sg:orig_category":"Architecten",
    "sg:phone":"+32 14 31 13 78",
    "sg:postcode":"2470",
    "sg:province":"Antwerpen",
    "wof:name":"Ann Schepens",
    "wof:placetype":"venue"
},
  "geometry": {"coordinates":[5.0988798141,51.2684898376],"type":"Point"}
}