{
  "type": "Feature",
  "properties": {
    "iso:country":"BE",
    "sg:address":"Hansbekestraat 69",
    "sg:city":"Wervik",
    "sg:classifiers":[
        {
            "category":"Banks & Credit Unions",
            "subcategory":"Investment Brokerage",
            "type":"Services"
        }
    ],
    "sg:phone":"+32 56 31 04 13",
    "sg:postcode":"8940",
    "sg:province":"West-Vlaanderen",
    "sg:tags":[
        "ladies'",
        "tailor",
        "tailoresses",
        "-",
        "clothing"
    ],
    "wof:name":"Vanwijnsberghe K",
    "wof:placetype":"venue"
},
  "geometry": {"coordinates":[3.0247550011,50.7765007019],"type":"Point"}
}