{
  "type": "Feature",
  "properties": {
    "addr:full":"Rue Entre Deux Portes 65 Huy Li\u00e8ge 4500",
    "addr:housenumber":"65",
    "addr:postcode":"4500",
    "addr:street":"Rue Entre Deux Portes",
    "iso:country":"BE",
    "sg:address":"Rue Entre Deux Portes 65",
    "sg:city":"Huy",
    "sg:classifiers":[
        {
            "category":"Building & Trades",
            "subcategory":"Construction",
            "type":"Services"
        }
    ],
    "sg:phone":"+32 85 21 63 43",
    "sg:postcode":"4500",
    "sg:province":"Li\u00e8ge",
    "sg:tags":[
        "installation",
        "-",
        "central",
        "heating"
    ],
    "wof:name":"Volant J",
    "wof:placetype":"venue"
},
  "geometry": {"coordinates":[5.2306399345,50.524974823],"type":"Point"}
}