{
  "type": "Feature",
  "properties": {
    "iso:country":"BE",
    "sg:address":"Rue De Diekirch 27",
    "sg:city":"Arlon",
    "sg:orig_category":"Boekhandels",
    "sg:phone":"+32 63 23 36 36",
    "sg:postcode":"6700",
    "sg:province":"Luxembourg",
    "wof:name":"Librairie Arlonnaise",
    "wof:placetype":"venue"
},
  "geometry": {"coordinates":[5.8132829666,49.6848945618],"type":"Point"}
}