{
  "type": "Feature",
  "properties": {
    "addr:full":"De Smet De Naeyerlaan 161 Blankenberge West-Vlaanderen 8370",
    "addr:housenumber":"161",
    "addr:postcode":"8370",
    "addr:street":"De Smet De Naeyerlaan",
    "iso:country":"BE",
    "sg:address":"De Smet De Naeyerlaan 161",
    "sg:city":"Blankenberge",
    "sg:classifiers":[
        {
            "category":"Professional",
            "subcategory":"Testing Lab",
            "type":"Services"
        }
    ],
    "sg:phone":"+32 50 41 35 39",
    "sg:postcode":"8370",
    "sg:province":"West-Vlaanderen",
    "sg:tags":[
        "chemist"
    ],
    "wof:name":"Cocquyt H",
    "wof:placetype":"venue"
},
  "geometry": {"coordinates":[3.130646944,51.3116798401],"type":"Point"}
}