{
  "type": "Feature",
  "properties": {
    "iso:country":"BE",
    "sg:address":"Haaggatstraat 51",
    "sg:city":"Kortenberg",
    "sg:orig_category":"Producteurs de l\u00e9gumes",
    "sg:phone":"+32 2 759 43 44",
    "sg:postcode":"3071",
    "sg:province":"Vlaams-Brabant",
    "wof:name":"Bruno Hermans",
    "wof:placetype":"venue"
},
  "geometry": {"coordinates":[4.581179142,50.906463623],"type":"Point"}
}