{
  "type": "Feature",
  "properties": {
    "addr:full":"Rue Warte 2bb Ellezelles Hainaut 7890",
    "addr:housenumber":"2bb",
    "addr:postcode":"7890",
    "addr:street":"Rue Warte",
    "iso:country":"BE",
    "sg:address":"Rue Warte 2bb",
    "sg:city":"Ellezelles",
    "sg:orig_category":"Plaatsen van vloer- and muurbekleding Woningbouw",
    "sg:phone":"+32 68 64 63 20",
    "sg:postcode":"7890",
    "sg:province":"Hainaut",
    "wof:name":"Jose Carton-delcourt",
    "wof:placetype":"venue"
},
  "geometry": {"coordinates":[3.7333960533,50.6934013367],"type":"Point"}
}