{
  "type": "Feature",
  "properties": {
    "addr:full":"Stationsstraat 52 Hulshout Antwerpen 2235",
    "addr:housenumber":"52",
    "addr:postcode":"2235",
    "addr:street":"Stationsstraat",
    "iso:country":"BE",
    "sg:address":"Stationsstraat 52",
    "sg:city":"Hulshout",
    "sg:orig_category":"Kruideniers Rundveehouders",
    "sg:phone":"+32 16 69 92 87",
    "sg:postcode":"2235",
    "sg:province":"Antwerpen",
    "wof:name":"Stanislas Van Looy",
    "wof:placetype":"venue"
},
  "geometry": {"coordinates":[4.8297791481,51.0594024658],"type":"Point"}
}