{
  "type": "Feature",
  "properties": {
    "addr:full":"Bredenakkerstraat 31 Destelbergen Oost-Vlaanderen 9070",
    "addr:housenumber":"31",
    "addr:postcode":"9070",
    "addr:street":"Bredenakkerstraat",
    "iso:country":"BE",
    "sg:address":"Bredenakkerstraat 31",
    "sg:city":"Destelbergen",
    "sg:orig_category":"Enseignement maternel and primaire",
    "sg:phone":"+32 9 228 36 69",
    "sg:postcode":"9070",
    "sg:province":"Oost-Vlaanderen",
    "wof:name":"Vrije Basisschool",
    "wof:placetype":"venue"
},
  "geometry": {"coordinates":[3.7654809952,51.0559844971],"type":"Point"}
}