{
  "type": "Feature",
  "properties": {
    "addr:full":"Place Dom Marie Albert 3 Florenville Luxembourg 6823",
    "addr:housenumber":"3",
    "addr:postcode":"6823",
    "addr:street":"Place Dom Marie Albert",
    "iso:country":"BE",
    "sg:address":"Place Dom Marie Albert 3",
    "sg:city":"Florenville",
    "sg:classifiers":[
        {
            "category":"Personal",
            "subcategory":"Beauty Salon",
            "type":"Services"
        }
    ],
    "sg:phone":"+32 61 31 14 78",
    "sg:postcode":"6823",
    "sg:province":"Luxembourg",
    "sg:tags":[
        "de",
        "coiffure"
    ],
    "wof:name":"Institut Elegance",
    "wof:placetype":"venue"
},
  "geometry": {"coordinates":[5.3297429085,49.6197280884],"type":"Point"}
}