{
  "type": "Feature",
  "properties": {
    "iso:country":"BE",
    "sg:address":"Rue De L'yser 61",
    "sg:city":"Seneffe",
    "sg:orig_category":"Warenhuizen",
    "sg:phone":"+32 64 55 63 16",
    "sg:postcode":"7180",
    "sg:province":"Hainaut",
    "wof:name":"Giuseppe Marchiol",
    "wof:placetype":"venue"
},
  "geometry": {"coordinates":[4.2673091888,50.5281257629],"type":"Point"}
}