{
  "type": "Feature",
  "properties": {
    "addr:full":"Elzenlaan 32 Lier Antwerpen 2500",
    "addr:housenumber":"32",
    "addr:postcode":"2500",
    "addr:street":"Elzenlaan",
    "iso:country":"BE",
    "sg:address":"Elzenlaan 32",
    "sg:city":"Lier",
    "sg:orig_category":"Plaatsen van vloer- and muurbekleding Schilders",
    "sg:phone":"+32 3 489 23 66",
    "sg:postcode":"2500",
    "sg:province":"Antwerpen",
    "wof:name":"Willem Van Dessel",
    "wof:placetype":"venue"
},
  "geometry": {"coordinates":[4.5596637726,51.1276512146],"type":"Point"}
}