{
  "type": "Feature",
  "properties": {
    "iso:country":"BE",
    "sg:address":"Rue Fran\u00e7ois Hittelet 120-1",
    "sg:city":"Jemeppe-sur-sambre",
    "sg:classifiers":[
        {
            "category":"Retail",
            "subcategory":"Event Space",
            "type":"Services"
        }
    ],
    "sg:phone":"+32 71 78 03 43",
    "sg:postcode":"5190",
    "sg:province":"Namur",
    "sg:tags":[
        "rental",
        "-",
        "hall"
    ],
    "wof:name":"Freschaux (les)",
    "wof:placetype":"venue"
},
  "geometry": {"coordinates":[4.6627120972,50.4586715698],"type":"Point"}
}