{
  "type": "Feature",
  "properties": {
    "iso:country":"BE",
    "sg:address":"Paddegatstraat 51",
    "sg:city":"Kapelle-op-den-bos (nieuwenrode)",
    "sg:classifiers":[
        {
            "category":"Banks & Credit Unions",
            "subcategory":"Investment Brokerage",
            "type":"Services"
        }
    ],
    "sg:phone":"+32 15 71 53 43",
    "sg:postcode":"1880",
    "sg:province":"Vlaams-Brabant",
    "sg:tags":[
        "fence"
    ],
    "wof:name":"Gi.bi.di. Benelux Nv-sa",
    "wof:placetype":"venue"
},
  "geometry": {"coordinates":[4.3588500023,50.9747161865],"type":"Point"}
}