{
  "type": "Feature",
  "properties": {
    "iso:country":"BE",
    "sg:address":"Visserij 19",
    "sg:city":"Gent",
    "sg:classifiers":[
        {
            "category":"Real Estate",
            "subcategory":"Architect",
            "type":"Services"
        }
    ],
    "sg:phone":"+32 9 223 31 08",
    "sg:postcode":"9000",
    "sg:province":"Oost-Vlaanderen",
    "wof:name":"Serck Architectenbureau",
    "wof:placetype":"venue"
},
  "geometry": {"coordinates":[3.7359619141,51.0513038635],"type":"Point"}
}