{
  "type": "Feature",
  "properties": {
    "addr:full":"Steenweg Op Jette 197 Koekelberg/koekelberg Bruxelles-Capitale 1081",
    "addr:housenumber":"197",
    "addr:postcode":"1081",
    "addr:street":"Steenweg Op Jette",
    "iso:country":"BE",
    "sg:address":"Steenweg Op Jette 197",
    "sg:city":"Koekelberg/koekelberg",
    "sg:orig_category":"Herstellingen and onderhoud van auto's",
    "sg:phone":"+32 2 411 61 77",
    "sg:postcode":"1081",
    "sg:province":"Bruxelles-Capitale",
    "wof:name":"A.b.s.",
    "wof:placetype":"venue"
},
  "geometry": {"coordinates":[4.3347029686,50.8615341187],"type":"Point"}
}