{
  "type": "Feature",
  "properties": {
    "addr:full":"Rue De L'yser 38 Mons (obourg) Hainaut 7034",
    "addr:housenumber":"38",
    "addr:postcode":"7034",
    "addr:street":"Rue De L'Yser",
    "iso:country":"BE",
    "sg:address":"Rue De L'yser 38",
    "sg:city":"Mons (obourg)",
    "sg:classifiers":[
        {
            "category":"Home & Garden",
            "subcategory":"Garden Supply",
            "type":"Retail Goods"
        }
    ],
    "sg:phone":"+32 65 36 07 11",
    "sg:postcode":"7034",
    "sg:province":"Hainaut",
    "sg:tags":[
        "seed",
        "-"
    ],
    "wof:name":"De Moor-talotti",
    "wof:placetype":"venue"
},
  "geometry": {"coordinates":[4.0088810921,50.4774246216],"type":"Point"}
}