{
  "type": "Feature",
  "properties": {
    "iso:country":"BE",
    "sg:address":"Ploegstraat 86",
    "sg:city":"Willebroek",
    "sg:classifiers":[
        {
            "category":"Building & Trades",
            "subcategory":"Plumbing",
            "type":"Services"
        }
    ],
    "sg:phone":"+32 3 886 77 78",
    "sg:postcode":"2830",
    "sg:province":"Antwerpen",
    "sg:tags":[
        "contractor"
    ],
    "wof:name":"Beauprez F",
    "wof:placetype":"venue"
},
  "geometry": {"coordinates":[4.3537039757,51.0467834473],"type":"Point"}
}