{
  "type": "Feature",
  "properties": {
    "addr:full":"Blancefloerlaan 45 Antwerpen Antwerpen 2050",
    "addr:housenumber":"45",
    "addr:postcode":"2050",
    "addr:street":"Blancefloerlaan",
    "iso:country":"BE",
    "sg:address":"Blancefloerlaan 45",
    "sg:city":"Antwerpen",
    "sg:orig_category":"Banques and organismes de cr\u00e9dit",
    "sg:phone":"+32 3 219 00 72",
    "sg:postcode":"2050",
    "sg:province":"Antwerpen",
    "wof:name":"Bbl",
    "wof:placetype":"venue"
},
  "geometry": {"coordinates":[4.3830089569,51.2201042175],"type":"Point"}
}