{
  "type": "Feature",
  "properties": {
    "iso:country":"BE",
    "sg:address":"Rue Du Dr. Edmond Isaac 29",
    "sg:city":"Quaregnon",
    "sg:orig_category":"Koerierbedrijven",
    "sg:phone":"+32 65 79 16 79",
    "sg:postcode":"7390",
    "sg:province":"Hainaut",
    "wof:name":"Messagerie Entradis",
    "wof:placetype":"venue"
},
  "geometry": {"coordinates":[3.8565149307,50.4508705139],"type":"Point"}
}