{
  "type": "Feature",
  "properties": {
    "iso:country":"BE",
    "sg:address":"Dorpsstr 16",
    "sg:city":"Olen",
    "sg:classifiers":[
        {
            "category":"Banks & Credit Unions",
            "subcategory":"Bank",
            "type":"Services"
        }
    ],
    "sg:phone":"+32 14 21 16 23",
    "sg:postcode":"2430",
    "sg:province":"Antwerpen",
    "wof:name":"Aslk-cger Bank",
    "wof:placetype":"venue"
},
  "geometry": {"coordinates":[5.0657300949,51.1005439758],"type":"Point"}
}