{
  "type": "Feature",
  "properties": {
    "addr:full":"Rue Du Progr\u00e8s 11 Nivelles Brabant Wallon 1400",
    "addr:housenumber":"11",
    "addr:postcode":"1400",
    "addr:street":"Rue Du Progre\u0300S",
    "iso:country":"BE",
    "sg:address":"Rue Du Progr\u00e8s 11",
    "sg:city":"Nivelles",
    "sg:classifiers":[
        {
            "category":"Utilities",
            "subcategory":"Fuel Oil & Lpg",
            "type":"Services"
        }
    ],
    "sg:phone":"+32 67 22 06 36",
    "sg:postcode":"1400",
    "sg:province":"Brabant Wallon",
    "wof:name":"Brandstoffen Soret",
    "wof:placetype":"venue"
},
  "geometry": {"coordinates":[4.3645401001,50.593208313],"type":"Point"}
}