{
  "type": "Feature",
  "properties": {
    "addr:full":"Lange Ambachtstraat 36 Oosterzele Oost-Vlaanderen 9860",
    "addr:housenumber":"36",
    "addr:postcode":"9860",
    "addr:street":"Lange Ambachtstraat;Oost-Vlaanderen",
    "iso:country":"BE",
    "sg:address":"Lange Ambachtstraat 36",
    "sg:city":"Oosterzele",
    "sg:classifiers":[
        {
            "category":"Retail",
            "subcategory":"Repair Shop",
            "type":"Services"
        }
    ],
    "sg:phone":"+32 9 362 42 65",
    "sg:postcode":"9860",
    "sg:province":"Oost-Vlaanderen",
    "wof:name":"Geerts Paul Cv",
    "wof:placetype":"venue"
},
  "geometry": {"coordinates":[3.8158791065,50.9472541809],"type":"Point"}
}