{
  "type": "Feature",
  "properties": {
    "iso:country":"BE",
    "sg:address":"Corbiestraat 91",
    "sg:city":"Mol",
    "sg:orig_category":"M\u00e9decins and sp\u00e9cialistes",
    "sg:phone":"+32 14 31 94 16",
    "sg:postcode":"2400",
    "sg:province":"Antwerpen",
    "wof:name":"G. Debie",
    "wof:placetype":"venue"
},
  "geometry": {"coordinates":[5.1167612076,51.1883964539],"type":"Point"}
}