{
  "type": "Feature",
  "properties": {
    "iso:country":"BE",
    "sg:address":"Mechelseweg 48",
    "sg:city":"Mechelen",
    "sg:orig_category":"Agences de presse",
    "sg:phone":"+32 15 41 93 98",
    "sg:postcode":"2811",
    "sg:province":"Antwerpen",
    "wof:name":"Karen Van Hoorick",
    "wof:placetype":"venue"
},
  "geometry": {"coordinates":[4.4479050636,51.0149497986],"type":"Point"}
}