{
  "type": "Feature",
  "properties": {
    "addr:full":"Tussenstraat 6 Neerpelt Limburg 3910",
    "addr:housenumber":"6",
    "addr:postcode":"3910",
    "addr:street":"Tussenstraat",
    "iso:country":"BE",
    "sg:address":"Tussenstraat 6",
    "sg:city":"Neerpelt",
    "sg:orig_category":"Auberges de jeunesse and refuges",
    "sg:phone":"+32 11 64 34 90",
    "sg:postcode":"3910",
    "sg:province":"Limburg",
    "wof:name":"De Dommelvallei",
    "wof:placetype":"venue"
},
  "geometry": {"coordinates":[5.4176712036,51.2467880249],"type":"Point"}
}