{
  "type": "Feature",
  "properties": {
    "iso:country":"BE",
    "sg:address":"Schoolplein 1",
    "sg:city":"Diksmuide",
    "sg:orig_category":"Dranken",
    "sg:phone":"+32 51 51 09 85",
    "sg:postcode":"8600",
    "sg:province":"West-Vlaanderen",
    "wof:name":"Wijnhuis Douchy",
    "wof:placetype":"venue"
},
  "geometry": {"coordinates":[2.8610739708,51.0331687927],"type":"Point"}
}