{
  "type": "Feature",
  "properties": {
    "addr:full":"Square Prince L\u00e9opold 34 Bruxelles Bruxelles-Capitale 1020",
    "addr:housenumber":"34",
    "addr:postcode":"1020",
    "addr:street":"Square Prince Le\u0301Opold",
    "iso:country":"BE",
    "sg:address":"Square Prince L\u00e9opold 34",
    "sg:city":"Bruxelles",
    "sg:classifiers":[
        {
            "category":"Building & Trades",
            "subcategory":"Construction",
            "type":"Services"
        }
    ],
    "sg:phone":"+32 2 478 39 13",
    "sg:postcode":"1020",
    "sg:province":"Bruxelles-Capitale",
    "sg:tags":[
        "stucco",
        "contractor"
    ],
    "wof:name":"Dekeuleneer J",
    "wof:placetype":"venue"
},
  "geometry": {"coordinates":[4.3400359154,50.884185791],"type":"Point"}
}