{
  "type": "Feature",
  "properties": {
    "addr:full":"Lindeweg 32 Zoutleeuw Vlaams-Brabant 3440",
    "addr:housenumber":"32",
    "addr:postcode":"3440",
    "addr:street":"Lindeweg;Vlaams-Brabant",
    "iso:country":"BE",
    "sg:address":"Lindeweg 32",
    "sg:city":"Zoutleeuw",
    "sg:classifiers":[
        {
            "category":"Building & Trades",
            "subcategory":"Electrical",
            "type":"Services"
        }
    ],
    "sg:phone":"+32 11 78 04 03",
    "sg:postcode":"3440",
    "sg:province":"Vlaams-Brabant",
    "sg:tags":[
        "-",
        "electric",
        "contractor"
    ],
    "wof:name":"Rego Bvba",
    "wof:placetype":"venue"
},
  "geometry": {"coordinates":[5.1335082054,50.8496627808],"type":"Point"}
}