{
  "type": "Feature",
  "properties": {
    "iso:country":"BE",
    "sg:address":"Kapellelei 38bis",
    "sg:city":"Mortsel",
    "sg:classifiers":[
        {
            "category":"Health Services",
            "subcategory":"Doctor",
            "type":"Services"
        }
    ],
    "sg:phone":"+32 3 449 49 26",
    "sg:postcode":"2640",
    "sg:province":"Antwerpen",
    "sg:tags":[
        "medicinephysicians",
        "surgeon"
    ],
    "wof:name":"Coeckelberghs Marina",
    "wof:placetype":"venue"
},
  "geometry": {"coordinates":[4.4530568123,51.1812705994],"type":"Point"}
}