{
  "type": "Feature",
  "properties": {
    "addr:full":"Avenue Commandant Vander Meeren 3 Bruxelles (anderlecht) Bruxelles-Capitale 1070",
    "addr:housenumber":"3",
    "addr:postcode":"1070",
    "addr:street":"Avenue Commandant Vander Meeren",
    "iso:country":"BE",
    "sg:address":"Avenue Commandant Vander Meeren 3",
    "sg:city":"Bruxelles (anderlecht)",
    "sg:classifiers":[
        {
            "category":"Health Services",
            "subcategory":"Doctor",
            "type":"Services"
        }
    ],
    "sg:phone":"+32 2 465 67 09",
    "sg:postcode":"1070",
    "sg:province":"Bruxelles-Capitale",
    "sg:tags":[
        "medicinephysicians",
        "surgeon"
    ],
    "wof:name":"Kuypers Stan",
    "wof:placetype":"venue"
},
  "geometry": {"coordinates":[4.3003787994,50.8438491821],"type":"Point"}
}