{
  "type": "Feature",
  "properties": {
    "addr:full":"Zuidstraat 16 Ingelmunster West-Vlaanderen 8770",
    "addr:housenumber":"16",
    "addr:postcode":"8770",
    "addr:street":"Zuidstraat",
    "iso:country":"BE",
    "sg:address":"Zuidstraat 16",
    "sg:city":"Ingelmunster",
    "sg:orig_category":"Travaux de pl\u00e2trage",
    "sg:phone":"+32 56 66 34 60",
    "sg:postcode":"8770",
    "sg:province":"West-Vlaanderen",
    "wof:name":"Plakwerken Lecluyse",
    "wof:placetype":"venue"
},
  "geometry": {"coordinates":[3.2843499184,50.9084091187],"type":"Point"}
}