{
  "type": "Feature",
  "properties": {
    "addr:full":"Kerkstraat 11 Stekene Oost-Vlaanderen 9190",
    "addr:housenumber":"11",
    "addr:postcode":"9190",
    "addr:street":"Kerkstraat",
    "iso:country":"BE",
    "sg:address":"Kerkstraat 11",
    "sg:city":"Stekene",
    "sg:classifiers":[
        {
            "category":"Fast Food",
            "type":"Food & Drink"
        }
    ],
    "sg:phone":"+32 3 779 67 66",
    "sg:postcode":"9190",
    "sg:province":"Oost-Vlaanderen",
    "sg:tags":[
        "de",
        "restaurant",
        "organisation",
        "\u00c0",
        "catering",
        "emporter",
        "f\u00cates",
        "restaurants"
    ],
    "wof:name":"De Pelgrim",
    "wof:placetype":"venue"
},
  "geometry": {"coordinates":[4.0401411057,51.2065582275],"type":"Point"}
}