{
  "type": "Feature",
  "properties": {
    "addr:full":"Stationsstraat 4 Pittem West-Vlaanderen 8740",
    "addr:housenumber":"4",
    "addr:postcode":"8740",
    "addr:street":"Stationsstraat",
    "iso:country":"BE",
    "sg:address":"Stationsstraat 4",
    "sg:city":"Pittem",
    "sg:classifiers":[
        {
            "category":"Real Estate",
            "subcategory":"Architect",
            "type":"Services"
        }
    ],
    "sg:phone":"+32 51 46 60 69",
    "sg:postcode":"8740",
    "sg:province":"West-Vlaanderen",
    "wof:name":"De Jaeghere P",
    "wof:placetype":"venue"
},
  "geometry": {"coordinates":[3.2624599934,50.9925880432],"type":"Point"}
}