{
  "type": "Feature",
  "properties": {
    "addr:full":"Boulevard Joseph Tirou 49 Charleroi (grand) Hainaut 6000",
    "addr:housenumber":"49",
    "addr:postcode":"6000",
    "addr:street":"Boulevard Joseph Tirou",
    "iso:country":"BE",
    "sg:address":"Boulevard Joseph Tirou 49",
    "sg:city":"Charleroi (grand)",
    "sg:orig_category":"Librairies",
    "sg:phone":"+32 71 31 12 50",
    "sg:postcode":"6000",
    "sg:province":"Hainaut",
    "wof:name":"Artis Historia",
    "wof:placetype":"venue"
},
  "geometry": {"coordinates":[4.4400629997,50.408782959],"type":"Point"}
}