{
  "type": "Feature",
  "properties": {
    "iso:country":"BE",
    "sg:address":"Parklaan 51",
    "sg:city":"Zaventem",
    "sg:orig_category":"Herstellingen and onderhoud van auto's",
    "sg:phone":"+32 2 720 09 13",
    "sg:postcode":"1930",
    "sg:province":"Vlaams-Brabant",
    "wof:name":"Carrosserie Centrum",
    "wof:placetype":"venue"
},
  "geometry": {"coordinates":[4.4743790627,50.8857269287],"type":"Point"}
}