{
  "type": "Feature",
  "properties": {
    "iso:country":"BE",
    "sg:address":"Vijverhoek 45",
    "sg:city":"Kuurne",
    "sg:classifiers":[
        {
            "category":"Home & Garden",
            "subcategory":"Furniture",
            "type":"Retail Goods"
        }
    ],
    "sg:phone":"+32 9 282 82 19",
    "sg:postcode":"8520",
    "sg:province":"West-Vlaanderen",
    "sg:tags":[
        "household",
        "wood"
    ],
    "wof:name":"Decor Line Nv",
    "wof:placetype":"venue"
},
  "geometry": {"coordinates":[3.6517701149,50.9923439026],"type":"Point"}
}