{
  "type": "Feature",
  "properties": {
    "addr:full":"Zeelaan 79bg1 De Panne West-Vlaanderen 8660",
    "addr:housenumber":"79bg1",
    "addr:postcode":"8660",
    "addr:street":"Zeelaan",
    "iso:country":"BE",
    "sg:address":"Zeelaan 79bg1",
    "sg:city":"De Panne",
    "sg:orig_category":"Brood, gebak and snoepgoed",
    "sg:phone":"+32 58 41 40 17",
    "sg:postcode":"8660",
    "sg:province":"West-Vlaanderen",
    "wof:name":"Frederik Bradt",
    "wof:placetype":"venue"
},
  "geometry": {"coordinates":[2.5854980946,51.1015472412],"type":"Point"}
}