{
  "type": "Feature",
  "properties": {
    "addr:full":"Rue Albert-ier 60 Jemeppe-sur-sambre Namur 5190",
    "addr:housenumber":"60",
    "addr:postcode":"5190",
    "addr:street":"Rue Albert-Ier",
    "iso:country":"BE",
    "sg:address":"Rue Albert-ier 60",
    "sg:city":"Jemeppe-sur-sambre",
    "sg:orig_category":"Loodgieterij, verwarming and sanitaire installaties",
    "sg:phone":"+32 71 78 85 30",
    "sg:postcode":"5190",
    "sg:province":"Namur",
    "wof:name":"Gafob",
    "wof:placetype":"venue"
},
  "geometry": {"coordinates":[4.6703448296,50.4645042419],"type":"Point"}
}