{
  "type": "Feature",
  "properties": {
    "addr:full":"Guffenslaan 28b13 Hasselt Limburg 3500",
    "addr:housenumber":"28b13",
    "addr:postcode":"3500",
    "addr:street":"Guffenslaan",
    "iso:country":"BE",
    "sg:address":"Guffenslaan 28b13",
    "sg:city":"Hasselt",
    "sg:orig_category":"Advocaten and juridische adviseurs",
    "sg:phone":"+32 11 23 11 85",
    "sg:postcode":"3500",
    "sg:province":"Limburg",
    "wof:name":"P. Steegmans",
    "wof:placetype":"venue"
},
  "geometry": {"coordinates":[5.3390250206,50.9276046753],"type":"Point"}
}