{
  "type": "Feature",
  "properties": {
    "iso:country":"BE",
    "sg:address":"Place Astrid 1",
    "sg:city":"Florenville",
    "sg:orig_category":"Notaires",
    "sg:phone":"+32 61 31 14 77",
    "sg:postcode":"6820",
    "sg:province":"Luxembourg",
    "wof:name":"E. Faulx",
    "wof:placetype":"venue"
},
  "geometry": {"coordinates":[5.3077111244,49.6980667114],"type":"Point"}
}