{
  "type": "Feature",
  "properties": {
    "addr:full":"Vossebergstraat 4 Diepenbeek Limburg 3590",
    "addr:housenumber":"4",
    "addr:postcode":"3590",
    "addr:street":"Vossebergstraat",
    "iso:country":"BE",
    "sg:address":"Vossebergstraat 4",
    "sg:city":"Diepenbeek",
    "sg:classifiers":[
        {
            "category":"Home & Garden",
            "subcategory":"Household Appliances",
            "type":"Retail Goods"
        }
    ],
    "sg:phone":"+32 11 32 44 37",
    "sg:postcode":"3590",
    "sg:province":"Limburg",
    "sg:tags":[
        "repair",
        "mainten",
        "-",
        "electric"
    ],
    "wof:name":"Leuraers E",
    "wof:placetype":"venue"
},
  "geometry": {"coordinates":[5.4677081108,50.9222412109],"type":"Point"}
}