{
  "type": "Feature",
  "properties": {
    "iso:country":"BE",
    "sg:address":"Grootheide 120",
    "sg:city":"Bornem",
    "sg:classifiers":[
        {
            "category":"Personal",
            "subcategory":"Beauty Salon",
            "type":"Services"
        }
    ],
    "sg:phone":"+32 3 889 37 30",
    "sg:postcode":"2880",
    "sg:province":"Antwerpen",
    "sg:tags":[
        "lady",
        "-",
        "hairdressing"
    ],
    "wof:name":"Cecile",
    "wof:placetype":"venue"
},
  "geometry": {"coordinates":[4.2215461731,51.0881500244],"type":"Point"}
}