{
  "type": "Feature",
  "properties": {
    "addr:full":"Heirstraat 331 Maasmechelen Limburg 3630",
    "addr:housenumber":"331",
    "addr:postcode":"3630",
    "addr:street":"Heirstraat",
    "iso:country":"BE",
    "sg:address":"Heirstraat 331",
    "sg:city":"Maasmechelen",
    "sg:classifiers":[
        {
            "category":"Building & Trades",
            "subcategory":"Cleaning & Sanitation",
            "type":"Services"
        }
    ],
    "sg:phone":"+32 89 76 74 03",
    "sg:postcode":"3630",
    "sg:province":"Limburg",
    "sg:tags":[
        "fa\u00e7ade",
        "maintenance"
    ],
    "wof:name":"Opdenakker A",
    "wof:placetype":"venue"
},
  "geometry": {"coordinates":[5.6878099442,50.9547233582],"type":"Point"}
}