{
  "type": "Feature",
  "properties": {
    "iso:country":"BE",
    "sg:address":"Avenue Cardinal Mercier 65",
    "sg:city":"Namur",
    "sg:orig_category":"M\u00e9decins and sp\u00e9cialistes",
    "sg:phone":"+32 81 74 28 35",
    "sg:postcode":"5000",
    "sg:province":"Namur",
    "wof:name":"C. Misson",
    "wof:placetype":"venue"
},
  "geometry": {"coordinates":[4.8500938416,50.4647598267],"type":"Point"}
}