{
  "type": "Feature",
  "properties": {
    "iso:country":"BE",
    "sg:address":"Am Waisenb\u00fcschchen 8",
    "sg:city":"Eupen",
    "sg:classifiers":[
        {
            "category":"Professional",
            "subcategory":"Art Services",
            "type":"Services"
        }
    ],
    "sg:phone":"+32 87 55 53 48",
    "sg:postcode":"4700",
    "sg:province":"Li\u00e8ge",
    "sg:tags":[
        "realization",
        "audio-visual"
    ],
    "wof:name":"Telecre",
    "wof:placetype":"venue"
},
  "geometry": {"coordinates":[6.0282020569,50.621837616],"type":"Point"}
}