{
  "type": "Feature",
  "properties": {
    "addr:full":"Reenstraat 25 Arendonk Antwerpen 2370",
    "addr:housenumber":"25",
    "addr:postcode":"2370",
    "addr:street":"Reenstraat",
    "iso:country":"BE",
    "sg:address":"Reenstraat 25",
    "sg:city":"Arendonk",
    "sg:orig_category":"Rundveehouders",
    "sg:phone":"+32 14 67 00 83",
    "sg:postcode":"2370",
    "sg:province":"Antwerpen",
    "wof:name":"Jozef Janssens",
    "wof:placetype":"venue"
},
  "geometry": {"coordinates":[5.0671157837,51.3276939392],"type":"Point"}
}