{
  "type": "Feature",
  "properties": {
    "addr:full":"Nieuwstraat 83 Avelgem West-Vlaanderen 8581",
    "addr:housenumber":"83",
    "addr:postcode":"8581",
    "addr:street":"Nieuwstraat",
    "iso:country":"BE",
    "sg:address":"Nieuwstraat 83",
    "sg:city":"Avelgem",
    "sg:orig_category":"Transports terrestres de voyageurs",
    "sg:phone":"+32 55 38 88 89",
    "sg:postcode":"8581",
    "sg:province":"West-Vlaanderen",
    "wof:name":"Den Boomgaard",
    "wof:placetype":"venue"
},
  "geometry": {"coordinates":[3.4811179638,50.7971725464],"type":"Point"}
}