{
  "type": "Feature",
  "properties": {
    "addr:full":"Grasstraat 6 Overpelt Limburg 3900",
    "addr:housenumber":"6",
    "addr:postcode":"3900",
    "addr:street":"Grasstraat",
    "iso:country":"BE",
    "sg:address":"Grasstraat 6",
    "sg:city":"Overpelt",
    "sg:orig_category":"Woningbouw",
    "sg:phone":"+32 11 64 67 48",
    "sg:postcode":"3900",
    "sg:province":"Limburg",
    "wof:name":"Haex",
    "wof:placetype":"venue"
},
  "geometry": {"coordinates":[5.4021658897,51.2075767517],"type":"Point"}
}