{
  "type": "Feature",
  "properties": {
    "iso:country":"BE",
    "sg:address":"Rue Pied Du Thier \u00e0 Li\u00e8ge 34",
    "sg:city":"Li\u00e8ge 1",
    "sg:classifiers":[
        {
            "category":"Shopping",
            "subcategory":"Bicycles & Sporting Goods",
            "type":"Retail Goods"
        }
    ],
    "sg:phone":"+32 4 227 01 30",
    "sg:postcode":"4000",
    "sg:province":"Li\u00e8ge",
    "sg:tags":[
        "tyre"
    ],
    "wof:name":"Pneus Driesen Molina",
    "wof:placetype":"venue"
},
  "geometry": {"coordinates":[5.5967898369,50.6562004089],"type":"Point"}
}