{
  "type": "Feature",
  "properties": {
    "addr:full":"Rue De La Lib\u00e9ration 68 Braine-le-ch\u00e2teau Brabant Wallon 1440",
    "addr:housenumber":"68",
    "addr:postcode":"1440",
    "addr:street":"Rue De La Libe\u0301Ration",
    "iso:country":"BE",
    "sg:address":"Rue De La Lib\u00e9ration 68",
    "sg:city":"Braine-le-ch\u00e2teau",
    "sg:classifiers":[
        {
            "category":"Cafe",
            "type":"Food & Drink"
        }
    ],
    "sg:phone":"+32 2 366 48 18",
    "sg:postcode":"1440",
    "sg:province":"Brabant Wallon",
    "sg:tags":[
        "snack-bars"
    ],
    "wof:name":"Sur Le Pouce",
    "wof:placetype":"venue"
},
  "geometry": {"coordinates":[4.2724881172,50.6829032898],"type":"Point"}
}