{
  "type": "Feature",
  "properties": {
    "iso:country":"BE",
    "sg:address":"Larumseweg 9",
    "sg:city":"Olen",
    "sg:orig_category":"V\u00e9los",
    "sg:phone":"+32 14 21 20 04",
    "sg:postcode":"2250",
    "sg:province":"Antwerpen",
    "wof:name":"Velo's De Koperen",
    "wof:placetype":"venue"
},
  "geometry": {"coordinates":[4.9106898308,51.1668891907],"type":"Point"}
}