{
  "type": "Feature",
  "properties": {
    "iso:country":"BE",
    "sg:address":"Rue De Goz\u00e9e 370",
    "sg:city":"Montigny-le-tilleul",
    "sg:classifiers":[
        {
            "category":"Shopping",
            "subcategory":"Baby Store",
            "type":"Retail Goods"
        }
    ],
    "sg:phone":"+32 71 51 60 60",
    "sg:postcode":"6110",
    "sg:province":"Hainaut",
    "sg:tags":[
        "-",
        "accessory"
    ],
    "wof:name":"Baby Look Sa",
    "wof:placetype":"venue"
},
  "geometry": {"coordinates":[4.3729219437,50.3792877197],"type":"Point"}
}