{
  "type": "Feature",
  "properties": {
    "iso:country":"BE",
    "sg:address":"Frans De L'arbrelaan 62",
    "sg:city":"Antwerpen",
    "sg:orig_category":"Schoonmaakbedrijven and ongediertebestrijding",
    "sg:phone":"+32 3 644 16 45",
    "sg:postcode":"2170",
    "sg:province":"Antwerpen",
    "wof:name":"Celkos",
    "wof:placetype":"venue"
},
  "geometry": {"coordinates":[4.4401140213,51.2390937805],"type":"Point"}
}