{
  "type": "Feature",
  "properties": {
    "addr:full":"Ardooisestraat 141b1 Izegem West-Vlaanderen 8870",
    "addr:housenumber":"141b1",
    "addr:postcode":"8870",
    "addr:street":"Ardooisestraat",
    "iso:country":"BE",
    "sg:address":"Ardooisestraat 141b1",
    "sg:city":"Izegem",
    "sg:orig_category":"Installatie van houten of kunststof schrijnwerk Verhuur bouwmachines",
    "sg:phone":"+32 51 31 18 69",
    "sg:postcode":"8870",
    "sg:province":"West-Vlaanderen",
    "wof:name":"Verma",
    "wof:placetype":"venue"
},
  "geometry": {"coordinates":[3.2069499493,50.9359588623],"type":"Point"}
}