{
  "type": "Feature",
  "properties": {
    "iso:country":"BE",
    "sg:address":"Potteriestraat 2",
    "sg:city":"Lichtervelde",
    "sg:orig_category":"S\u00e9curit\u00e9 sociale",
    "sg:phone":"+32 51 72 43 52",
    "sg:postcode":"8810",
    "sg:province":"West-Vlaanderen",
    "wof:name":"Westvl. Liberaal Ziekenf.",
    "wof:placetype":"venue"
},
  "geometry": {"coordinates":[3.1422579288,51.0273933411],"type":"Point"}
}