{
  "type": "Feature",
  "properties": {
    "iso:country":"BE",
    "sg:address":"Dendermondesteenweg 336",
    "sg:city":"Destelbergen",
    "sg:orig_category":"RESTAURANTS: BOISSONS",
    "sg:phone":"+32 9 229 28 91",
    "sg:postcode":"9070",
    "sg:province":"Oost-Vlaanderen",
    "wof:name":"Vinoland",
    "wof:placetype":"venue"
},
  "geometry": {"coordinates":[3.7902541161,51.0561256409],"type":"Point"}
}