{
  "type": "Feature",
  "properties": {
    "iso:country":"BE",
    "sg:address":"Rue Des Brasseries 29",
    "sg:city":"Wavre",
    "sg:orig_category":"Maroquinerie and articles de voyage",
    "sg:phone":"+32 10 22 88 31",
    "sg:postcode":"1300",
    "sg:province":"Brabant Wallon",
    "wof:name":"Maison Crocodile",
    "wof:placetype":"venue"
},
  "geometry": {"coordinates":[4.6108751297,50.7151832581],"type":"Point"}
}