{
  "type": "Feature",
  "properties": {
    "addr:full":"Mons. Deneckerestraat 26 Wevelgem West-Vlaanderen 8560",
    "addr:housenumber":"26",
    "addr:postcode":"8560",
    "addr:street":"Deneckerestraat",
    "iso:country":"BE",
    "sg:address":"Mons. Deneckerestraat 26",
    "sg:city":"Wevelgem",
    "sg:orig_category":"Installation de menuiserie m\u00e9tallique",
    "sg:phone":"+32 56 41 73 47",
    "sg:postcode":"8560",
    "sg:province":"West-Vlaanderen",
    "wof:name":"Freddy Delepierre",
    "wof:placetype":"venue"
},
  "geometry": {"coordinates":[3.1799249649,50.808013916],"type":"Point"}
}