{
  "type": "Feature",
  "properties": {
    "addr:full":"Rue Du Coll\u00c8ge 5 Namur Namur 5000",
    "addr:housenumber":"5",
    "addr:postcode":"5000",
    "addr:street":"Rue Du Colle\u0300Ge",
    "iso:country":"BE",
    "sg:address":"Rue Du Coll\u00c8ge 5",
    "sg:city":"Namur",
    "sg:orig_category":"RESTAURANTS: PAIN, P\u00c2TISSERIES AND CONFISERIES",
    "sg:phone":"+32 81 22 16 66",
    "sg:postcode":"5000",
    "sg:province":"Namur",
    "wof:name":"Le Pain Quotidien",
    "wof:placetype":"venue"
},
  "geometry": {"coordinates":[4.863008976,50.4638366699],"type":"Point"}
}