{
  "type": "Feature",
  "properties": {
    "iso:country":"BE",
    "sg:address":"Moriaanshoofd 27",
    "sg:city":"Oudenaarde",
    "sg:orig_category":"RESTAURANTS: FAST FOOD AND \u00c0 EMPORTER. H\u00d4TELS. RESTAURANTS. CATERING AND ORGANISATION DE F\u00caTES",
    "sg:phone":"+32 9 384 37 87",
    "sg:postcode":"9700",
    "sg:province":"Oost-Vlaanderen",
    "wof:name":"Moriaanshoofd",
    "wof:placetype":"venue"
},
  "geometry": {"coordinates":[3.6178328991,50.8980979919],"type":"Point"}
}