{
  "type": "Feature",
  "properties": {
    "iso:country":"BE",
    "sg:address":"Ukkelsesteenweg 304",
    "sg:city":"Linkebeek/linkebeek",
    "sg:orig_category":"Artsen and specialisten",
    "sg:phone":"+32 2 377 04 15",
    "sg:postcode":"1630",
    "sg:province":"Vlaams-Brabant",
    "wof:name":"M. Parmentier/marc Parmentier",
    "wof:placetype":"venue"
},
  "geometry": {"coordinates":[4.3225331306,50.7777442932],"type":"Point"}
}