{
  "type": "Feature",
  "properties": {
    "iso:country":"BE",
    "sg:address":"Dorent 25",
    "sg:city":"Erpe-mere",
    "sg:orig_category":"Boekhandels Kantoormateriaal Krantenwinkels Rookartikelen Speelgoed",
    "sg:phone":"+32 53 62 30 69",
    "sg:postcode":"9420",
    "sg:province":"Oost-Vlaanderen",
    "wof:name":"Huis Bazarke",
    "wof:placetype":"venue"
},
  "geometry": {"coordinates":[3.9202730656,50.912776947],"type":"Point"}
}