{
  "type": "Feature",
  "properties": {
    "iso:country":"BE",
    "sg:address":"Bosstraat 10",
    "sg:city":"Beveren",
    "sg:orig_category":"Producteurs de fruits",
    "sg:phone":"+32 3 775 24 31",
    "sg:postcode":"9120",
    "sg:province":"Oost-Vlaanderen",
    "wof:name":"Denis Franssens",
    "wof:placetype":"venue"
},
  "geometry": {"coordinates":[4.2494039536,51.1951065063],"type":"Point"}
}