{
  "type": "Feature",
  "properties": {
    "addr:full":"Gentstraat 2 Oostende West-Vlaanderen 8400",
    "addr:housenumber":"2",
    "addr:postcode":"8400",
    "addr:street":"Gentstraat",
    "iso:country":"BE",
    "sg:address":"Gentstraat 2",
    "sg:city":"Oostende",
    "sg:classifiers":[
        {
            "category":"Bars & Pubs",
            "type":"Food & Drink"
        }
    ],
    "sg:phone":"+32 59 51 58 78",
    "sg:postcode":"8400",
    "sg:province":"West-Vlaanderen",
    "sg:tags":[
        "tavern"
    ],
    "wof:name":"St-jozef",
    "wof:placetype":"venue"
},
  "geometry": {"coordinates":[2.9133279324,51.225692749],"type":"Point"}
}