{
  "type": "Feature",
  "properties": {
    "iso:country":"BE",
    "sg:address":"Schorestraat 43",
    "sg:city":"Diksmuide",
    "sg:orig_category":"Animaux domestiques and accessoires. Services pour animaux domestiques",
    "sg:phone":"+32 51 50 49 22",
    "sg:postcode":"8600",
    "sg:province":"West-Vlaanderen",
    "wof:name":"Sapho's Hoeve",
    "wof:placetype":"venue"
},
  "geometry": {"coordinates":[2.8661940098,51.1051330566],"type":"Point"}
}