{
  "type": "Feature",
  "properties": {
    "addr:full":"Maclinoire 26 Ellezelles Hainaut 7890",
    "addr:housenumber":"26",
    "addr:postcode":"7890",
    "addr:street":"Maclinoire",
    "iso:country":"BE",
    "sg:address":"Maclinoire 26",
    "sg:city":"Ellezelles",
    "sg:classifiers":[
        {
            "category":"Arena",
            "subcategory":"Sports Club",
            "type":"Entertainment"
        }
    ],
    "sg:phone":"+32 68 54 28 17",
    "sg:postcode":"7890",
    "sg:province":"Hainaut",
    "sg:tags":[
        "de"
    ],
    "wof:name":"V.c. P\u00c9dale Ellezelloise",
    "wof:placetype":"venue"
},
  "geometry": {"coordinates":[3.655244112,50.7312927246],"type":"Point"}
}