{
  "type": "Feature",
  "properties": {
    "addr:full":"Zuidlaan 158 Zwalm Oost-Vlaanderen 9630",
    "addr:housenumber":"158",
    "addr:postcode":"9630",
    "addr:street":"Zuidlaan;Oost-Vlaanderen",
    "iso:country":"BE",
    "sg:address":"Zuidlaan 158",
    "sg:city":"Zwalm",
    "sg:orig_category":"Pain, p\u00e2tisseries and confiseries",
    "sg:phone":"+32 55 49 68 28",
    "sg:postcode":"9630",
    "sg:province":"Oost-Vlaanderen",
    "wof:name":"Veerle Verstraeten",
    "wof:placetype":"venue"
},
  "geometry": {"coordinates":[3.7342200279,50.8682823181],"type":"Point"}
}