{
  "type": "Feature",
  "properties": {
    "iso:country":"BE",
    "sg:address":"Romershovenstraat 135",
    "sg:city":"Hoeselt",
    "sg:orig_category":"Varkenskwekers",
    "sg:phone":"+32 89 51 40 34",
    "sg:postcode":"3730",
    "sg:province":"Limburg",
    "wof:name":"Ludo Jamaer",
    "wof:placetype":"venue"
},
  "geometry": {"coordinates":[5.4615898132,50.8511390686],"type":"Point"}
}