{
  "type": "Feature",
  "properties": {
    "iso:country":"BE",
    "sg:address":"Heiveldekens 20",
    "sg:city":"Kontich",
    "sg:orig_category":"Compressoren and pompen Fab Gereedschapswerktuigen Gh",
    "sg:phone":"+32 3 458 24 00",
    "sg:postcode":"2550",
    "sg:province":"Antwerpen",
    "wof:name":"Friatec Nv",
    "wof:placetype":"venue"
},
  "geometry": {"coordinates":[4.4601340294,51.1218681335],"type":"Point"}
}