{
  "type": "Feature",
  "properties": {
    "iso:country":"BE",
    "sg:address":"Greinstraat 33",
    "sg:city":"Antwerpen",
    "sg:classifiers":[
        {
            "category":"Professional",
            "subcategory":"Art Services",
            "type":"Services"
        }
    ],
    "sg:phone":"+32 3 272 43 06",
    "sg:postcode":"2060",
    "sg:province":"Antwerpen",
    "sg:tags":[
        "designer",
        "ontwerpers"
    ],
    "wof:name":"Sarah Corynen",
    "wof:placetype":"venue"
},
  "geometry": {"coordinates":[4.425055027,51.2220001221],"type":"Point"}
}