{
  "type": "Feature",
  "properties": {
    "addr:full":"Chauss\u00e9e De Bruxelles 179 Wemmel Vlaams-Brabant 1780",
    "addr:housenumber":"179",
    "addr:postcode":"1780",
    "addr:street":"Chausse\u0301E De Bruxelles;Vlaams-Brabant",
    "iso:country":"BE",
    "sg:address":"Chauss\u00e9e De Bruxelles 179",
    "sg:city":"Wemmel",
    "sg:classifiers":[
        {
            "category":"Fast Food",
            "type":"Food & Drink"
        }
    ],
    "sg:phone":"+32 2 460 63 42",
    "sg:postcode":"1780",
    "sg:province":"Vlaams-Brabant",
    "sg:tags":[
        "fried",
        "stand",
        "potato"
    ],
    "wof:name":"Snack Lucky",
    "wof:placetype":"venue"
},
  "geometry": {"coordinates":[4.3086299896,50.9016494751],"type":"Point"}
}