{
  "type": "Feature",
  "properties": {
    "iso:country":"BE",
    "sg:address":"Mechelseweg 90",
    "sg:city":"Kapelle-op-den-bos",
    "sg:orig_category":"Non-Classified Establishments",
    "sg:phone":"+32 15 71 16 21",
    "sg:postcode":"1880",
    "sg:province":"Vlaams-Brabant",
    "wof:name":"Sanpareil Nv",
    "wof:placetype":"venue"
},
  "geometry": {"coordinates":[4.3724999428,51.0122146606],"type":"Point"}
}