{
  "type": "Feature",
  "properties": {
    "addr:full":"Impasse D'alvaux 10 Gembloux Namur 5032",
    "addr:housenumber":"10",
    "addr:postcode":"5032",
    "addr:street":"Impasse D'Alvaux;Namur",
    "iso:country":"BE",
    "sg:address":"Impasse D'alvaux 10",
    "sg:city":"Gembloux",
    "sg:orig_category":"Plomberie, chauffage and installations sanitaires",
    "sg:phone":"+32 81 63 42 89",
    "sg:postcode":"5032",
    "sg:province":"Namur",
    "wof:name":"Benoit Tasiaux",
    "wof:placetype":"venue"
},
  "geometry": {"coordinates":[4.6763281822,50.5204277039],"type":"Point"}
}