{
  "type": "Feature",
  "properties": {
    "iso:country":"BE",
    "sg:address":"Sperwerlaan 2",
    "sg:city":"Maldegem",
    "sg:orig_category":"Woningbouw",
    "sg:phone":"+32 9 377 81 67",
    "sg:postcode":"9991",
    "sg:province":"Oost-Vlaanderen",
    "wof:name":"Andries Etienne",
    "wof:placetype":"venue"
},
  "geometry": {"coordinates":[3.5106949806,51.2033805847],"type":"Point"}
}