{
  "type": "Feature",
  "properties": {
    "iso:country":"BE",
    "sg:address":"Renaumont 103",
    "sg:city":"Libramont-chevigny",
    "sg:orig_category":"Eleveurs de bovins",
    "sg:phone":"+32 61 22 43 63",
    "sg:postcode":"6800",
    "sg:province":"Luxembourg",
    "wof:name":"Claude",
    "wof:placetype":"venue"
},
  "geometry": {"coordinates":[5.4479269981,49.9294776917],"type":"Point"}
}