{
  "type": "Feature",
  "properties": {
    "iso:country":"BE",
    "sg:address":"Rue Du Page 90a",
    "sg:city":"Bruxelles",
    "sg:classifiers":[
        {
            "category":"Shopping",
            "subcategory":"Crafts & Fabrics",
            "type":"Retail Goods"
        }
    ],
    "sg:phone":"+32 2 534 51 72",
    "sg:postcode":"1050",
    "sg:province":"Bruxelles-Capitale",
    "sg:tags":[
        "textile",
        "linen",
        "clothing"
    ],
    "wof:name":"Donald Thiriar Sprl",
    "wof:placetype":"venue"
},
  "geometry": {"coordinates":[4.3573088646,50.8218078613],"type":"Point"}
}