{
  "type": "Feature",
  "properties": {
    "addr:full":"Tiensestraat 52 Leuven Vlaams-Brabant 3000",
    "addr:housenumber":"52",
    "addr:postcode":"3000",
    "addr:street":"Tiensestraat",
    "iso:country":"BE",
    "sg:address":"Tiensestraat 52",
    "sg:city":"Leuven",
    "sg:classifiers":[
        {
            "category":"Personal",
            "subcategory":"Beauty Salon",
            "type":"Services"
        }
    ],
    "sg:phone":"+32 16 23 05 64",
    "sg:postcode":"3000",
    "sg:province":"Vlaams-Brabant",
    "sg:tags":[
        "lady",
        "-",
        "hairdressing"
    ],
    "wof:name":"Demoiti\u00e9 Y",
    "wof:placetype":"venue"
},
  "geometry": {"coordinates":[4.703979969,50.8774528503],"type":"Point"}
}