{
  "type": "Feature",
  "properties": {
    "iso:country":"BE",
    "sg:address":"Lievevrouwstraat 16",
    "sg:city":"Aalst",
    "sg:orig_category":"Ordinateurs and \u00e9quipement informatique",
    "sg:phone":"+32 53 77 39 37",
    "sg:postcode":"9310",
    "sg:province":"Oost-Vlaanderen",
    "wof:name":"Myrmo",
    "wof:placetype":"venue"
},
  "geometry": {"coordinates":[4.1127591133,50.9638633728],"type":"Point"}
}