{
  "type": "Feature",
  "properties": {
    "iso:country":"BE",
    "sg:address":"Halensestraat 14a",
    "sg:city":"Halen (zelem)",
    "sg:classifiers":[
        {
            "category":"Professional",
            "subcategory":"Accounting & Tax Preparation",
            "type":"Services"
        }
    ],
    "sg:phone":"+32 13 44 47 55",
    "sg:postcode":"3545",
    "sg:province":"Limburg",
    "sg:tags":[
        "bookkeeper"
    ],
    "wof:name":"Van Eylen J",
    "wof:placetype":"venue"
},
  "geometry": {"coordinates":[5.1142220497,50.973575592],"type":"Point"}
}