{
  "type": "Feature",
  "properties": {
    "addr:full":"Avenue Solvay 4 Wavre Brabant Wallon 1300",
    "addr:housenumber":"4;1300",
    "addr:street":"Avenue Solvay",
    "iso:country":"BE",
    "sg:address":"Avenue Solvay 4",
    "sg:city":"Wavre",
    "sg:classifiers":[
        {
            "category":"Government",
            "subcategory":"Post Office",
            "type":"Public Place"
        }
    ],
    "sg:phone":"+32 10 68 62 30",
    "sg:postcode":"1300",
    "sg:province":"Brabant Wallon",
    "sg:tags":[
        "parkinggarages",
        "access",
        "-",
        "installation"
    ],
    "wof:name":"Aspark Sa",
    "wof:placetype":"venue"
},
  "geometry": {"coordinates":[4.5912489891,50.7354812622],"type":"Point"}
}