{
  "type": "Feature",
  "properties": {
    "addr:full":"Vendoorn 1 Zwijndrecht Antwerpen 2070",
    "addr:housenumber":"1",
    "addr:postcode":"2070",
    "addr:street":"Vendoorn",
    "iso:country":"BE",
    "sg:address":"Vendoorn 1",
    "sg:city":"Zwijndrecht",
    "sg:classifiers":[
        {
            "category":"Cafe",
            "type":"Food & Drink"
        }
    ],
    "sg:phone":"+32 3 254 07 73",
    "sg:postcode":"2070",
    "sg:province":"Antwerpen",
    "sg:tags":[
        "caf\u00e9s"
    ],
    "wof:name":"Caf\u00c9 Liegebeest",
    "wof:placetype":"venue"
},
  "geometry": {"coordinates":[4.3073701859,51.2171287537],"type":"Point"}
}