{
  "type": "Feature",
  "properties": {
    "iso:country":"BE",
    "sg:address":"Oedelemsesteenweg 79",
    "sg:city":"Damme",
    "sg:orig_category":"Fournitures de bureau",
    "sg:phone":"+32 50 35 51 16",
    "sg:postcode":"8340",
    "sg:province":"West-Vlaanderen",
    "wof:name":"Du Fosse",
    "wof:placetype":"venue"
},
  "geometry": {"coordinates":[3.3292400837,51.1960067749],"type":"Point"}
}