{
  "type": "Feature",
  "properties": {
    "addr:full":"Kalvariestraat 70 Kortrijk West-Vlaanderen 8510",
    "addr:housenumber":"70",
    "addr:postcode":"8510",
    "addr:street":"Kalvariestraat",
    "iso:country":"BE",
    "sg:address":"Kalvariestraat 70",
    "sg:city":"Kortrijk",
    "sg:orig_category":"Enseignement maternel and primaire",
    "sg:phone":"+32 56 21 93 54",
    "sg:postcode":"8510",
    "sg:province":"West-Vlaanderen",
    "wof:name":"B.s.g.o. Het Open Groene",
    "wof:placetype":"venue"
},
  "geometry": {"coordinates":[3.2333650589,50.8071060181],"type":"Point"}
}