{
  "type": "Feature",
  "properties": {
    "addr:full":"Rue A. Hornet 37 Merbes-le-ch\u00e2teau (fontaine-valmont) Hainaut 6567",
    "addr:housenumber":"37",
    "addr:postcode":"6567",
    "addr:street":"Rue A. Hornet",
    "iso:country":"BE",
    "sg:address":"Rue A. Hornet 37",
    "sg:city":"Merbes-le-ch\u00e2teau (fontaine-valmont)",
    "sg:classifiers":[
        {
            "category":"Health Services",
            "subcategory":"Doctor",
            "type":"Services"
        }
    ],
    "sg:phone":"+32 71 55 65 14",
    "sg:postcode":"6567",
    "sg:province":"Hainaut",
    "sg:tags":[
        "medicinephysicians",
        "surgeon"
    ],
    "wof:name":"Gahylle J",
    "wof:placetype":"venue"
},
  "geometry": {"coordinates":[4.16537714,50.3236999512],"type":"Point"}
}