{
  "type": "Feature",
  "properties": {
    "iso:country":"BE",
    "sg:address":"Rue Du Castinia 1",
    "sg:city":"Belgium",
    "sg:classifiers":[
        {
            "category":"Restaurant",
            "type":"Food & Drink"
        }
    ],
    "sg:phone":"+32 10 45 03 02",
    "sg:postcode":"1348",
    "sg:province":"Brabant Wallon",
    "wof:name":"Caf\u00c9taria Sabra",
    "wof:placetype":"venue"
},
  "geometry": {"coordinates":[4.6048989296,50.6706809998],"type":"Point"}
}