{
  "type": "Feature",
  "properties": {
    "addr:full":"Place Des Martyrs 21 Brussel/bruxelles Bruxelles-Capitale 1000",
    "addr:housenumber":"21",
    "addr:postcode":"1000",
    "addr:street":"Place Des Martyrs;/",
    "iso:country":"BE",
    "sg:address":"Place Des Martyrs 21",
    "sg:city":"Brussel/bruxelles",
    "sg:orig_category":"Production de films, t\u00e9l\u00e9films and vid\u00e9os. Agences de publicit\u00e9",
    "sg:phone":"+32 2 251 01 68",
    "sg:postcode":"1000",
    "sg:province":"Bruxelles-Capitale",
    "wof:name":"C I A M",
    "wof:placetype":"venue"
},
  "geometry": {"coordinates":[4.3562431335,50.8520584106],"type":"Point"}
}