{
  "type": "Feature",
  "properties": {
    "addr:full":"Beekseweg 18a Ravels (poppel) Antwerpen 2382",
    "addr:housenumber":"18a",
    "addr:postcode":"2382",
    "addr:street":"Beekseweg",
    "iso:country":"BE",
    "sg:address":"Beekseweg 18a",
    "sg:city":"Ravels (poppel)",
    "sg:classifiers":[
        {
            "category":"Retail",
            "subcategory":"Veterinary Services",
            "type":"Services"
        }
    ],
    "sg:phone":"+32 14 65 16 68",
    "sg:postcode":"2382",
    "sg:province":"Antwerpen",
    "sg:tags":[
        "veterinarian"
    ],
    "wof:name":"Van Heyst A",
    "wof:placetype":"venue"
},
  "geometry": {"coordinates":[5.041768074,51.4469108582],"type":"Point"}
}