{
  "type": "Feature",
  "properties": {
    "addr:full":"Aarschotsesteenweg 234 Leuven Vlaams-Brabant 3012",
    "addr:housenumber":"234",
    "addr:postcode":"3012",
    "addr:street":"Aarschotsesteenweg",
    "iso:country":"BE",
    "sg:address":"Aarschotsesteenweg 234",
    "sg:city":"Leuven",
    "sg:orig_category":"Artsen and specialisten",
    "sg:phone":"+32 16 44 34 89",
    "sg:postcode":"3012",
    "sg:province":"Vlaams-Brabant",
    "wof:name":"Brigitte Michielsen",
    "wof:placetype":"venue"
},
  "geometry": {"coordinates":[4.7107200623,50.9033584595],"type":"Point"}
}