{
  "type": "Feature",
  "properties": {
    "iso:country":"BE",
    "sg:address":"Moulin De Dison 68ba",
    "sg:city":"Jalhay",
    "sg:orig_category":"Diverse bouwafwerking and reiniging",
    "sg:phone":"+32 87 64 80 01",
    "sg:postcode":"4845",
    "sg:province":"Li\u00e8ge",
    "wof:name":"Fe. Simul",
    "wof:placetype":"venue"
},
  "geometry": {"coordinates":[5.9661078453,50.5455055237],"type":"Point"}
}