{
  "type": "Feature",
  "properties": {
    "iso:country":"BE",
    "sg:address":"Oude Laarnsesteenweg 14",
    "sg:city":"Wetteren",
    "sg:classifiers":[
        {
            "category":"Professional",
            "subcategory":"Art Services",
            "type":"Services"
        }
    ],
    "sg:phone":"+32 9 369 54 46",
    "sg:postcode":"9230",
    "sg:province":"Oost-Vlaanderen",
    "sg:tags":[
        "sculptor"
    ],
    "wof:name":"Copers L",
    "wof:placetype":"venue"
},
  "geometry": {"coordinates":[3.8707580566,51.0200157166],"type":"Point"}
}