{
  "type": "Feature",
  "properties": {
    "addr:full":"Zwanenlaan 8 Oostende (zandvoorde) West-Vlaanderen 8400",
    "addr:housenumber":"8",
    "addr:postcode":"8400",
    "addr:street":"Zwanenlaan",
    "iso:country":"BE",
    "sg:address":"Zwanenlaan 8",
    "sg:city":"Oostende (zandvoorde)",
    "sg:classifiers":[
        {
            "category":"Health Services",
            "subcategory":"Health Practitioner",
            "type":"Services"
        }
    ],
    "sg:phone":"+32 59 26 74 40",
    "sg:postcode":"8400",
    "sg:province":"West-Vlaanderen",
    "sg:tags":[
        "physiotherapist"
    ],
    "wof:name":"Taillaert R",
    "wof:placetype":"venue"
},
  "geometry": {"coordinates":[2.9685308933,51.2017707825],"type":"Point"}
}