{
  "type": "Feature",
  "properties": {
    "addr:full":"Avenue Du Laerbeek 23 Bruxelles (jette) Bruxelles-Capitale 1090",
    "addr:housenumber":"23",
    "addr:postcode":"1090",
    "addr:street":"Avenue Du Laerbeek",
    "iso:country":"BE",
    "sg:address":"Avenue Du Laerbeek 23",
    "sg:city":"Bruxelles (jette)",
    "sg:classifiers":[
        {
            "category":"Health Services",
            "subcategory":"Dentist",
            "type":"Services"
        }
    ],
    "sg:phone":"+32 2 479 53 57",
    "sg:postcode":"1090",
    "sg:province":"Bruxelles-Capitale",
    "wof:name":"Scheinok R",
    "wof:placetype":"venue"
},
  "geometry": {"coordinates":[4.3155379295,50.8857192993],"type":"Point"}
}