{
  "type": "Feature",
  "properties": {
    "iso:country":"BE",
    "sg:address":"Rue De Beaumont 262",
    "sg:city":"Charleroi (marchienne-au-pont)",
    "sg:classifiers":[
        {
            "category":"Social Services",
            "type":"Services"
        }
    ],
    "sg:phone":"+32 71 51 37 72",
    "sg:postcode":"6030",
    "sg:province":"Hainaut",
    "wof:name":"Centre Mat'zoom",
    "wof:placetype":"venue"
},
  "geometry": {"coordinates":[4.3933987617,50.3988380432],"type":"Point"}
}