{
  "type": "Feature",
  "properties": {
    "addr:full":"Bondgenotenlaan 141 Leuven Vlaams-Brabant 3000",
    "addr:housenumber":"141",
    "addr:postcode":"3000",
    "addr:street":"Bondgenotenlaan",
    "iso:country":"BE",
    "sg:address":"Bondgenotenlaan 141",
    "sg:city":"Leuven",
    "sg:orig_category":"Reisbureaus",
    "sg:phone":"+32 16 22 00 44",
    "sg:postcode":"3000",
    "sg:province":"Vlaams-Brabant",
    "wof:name":"Touring",
    "wof:placetype":"venue"
},
  "geometry": {"coordinates":[4.7119297981,50.8808746338],"type":"Point"}
}