{
  "type": "Feature",
  "properties": {
    "addr:full":"Beukestraat 10 Buggenhout Oost-Vlaanderen 9255",
    "addr:housenumber":"10",
    "addr:postcode":"9255",
    "addr:street":"Beukestraat",
    "iso:country":"BE",
    "sg:address":"Beukestraat 10",
    "sg:city":"Buggenhout",
    "sg:orig_category":"Geiger Counters, Geiger-M\u00fcller Counters",
    "sg:phone":"+32 52 33 26 39",
    "sg:postcode":"9255",
    "sg:province":"Oost-Vlaanderen",
    "wof:name":"Numeco B.v.b.a.",
    "wof:placetype":"venue"
},
  "geometry": {"coordinates":[4.1812047958,51.0101051331],"type":"Point"}
}