{
  "type": "Feature",
  "properties": {
    "iso:country":"BE",
    "sg:address":"Zwitserlandstraat 19",
    "sg:city":"Sint-gillis/saint-gilles",
    "sg:orig_category":"Boekhouders",
    "sg:phone":"+32 2 633 54 49",
    "sg:postcode":"1060",
    "sg:province":"Bruxelles-Capitale",
    "wof:name":"J. Deman",
    "wof:placetype":"venue"
},
  "geometry": {"coordinates":[4.3536028862,50.8327407837],"type":"Point"}
}