{
  "type": "Feature",
  "properties": {
    "addr:full":"Avenue Kersbeek 281 Bruxelles (uccle) Bruxelles-Capitale 1180",
    "addr:housenumber":"281",
    "addr:postcode":"1180",
    "addr:street":"Avenue Kersbeek",
    "iso:country":"BE",
    "sg:address":"Avenue Kersbeek 281",
    "sg:city":"Bruxelles (uccle)",
    "sg:classifiers":[
        {
            "category":"Professional",
            "subcategory":"Detective & Security Services",
            "type":"Services"
        }
    ],
    "sg:phone":"+32 2 376 03 07",
    "sg:postcode":"1180",
    "sg:province":"Bruxelles-Capitale",
    "sg:tags":[
        "door",
        "videophones",
        "operating",
        "equipment"
    ],
    "wof:name":"Mega-matic Benelux Sa",
    "wof:placetype":"venue"
},
  "geometry": {"coordinates":[4.3222718239,50.8011932373],"type":"Point"}
}