{
  "type": "Feature",
  "properties": {
    "addr:full":"Boulevard Lambermont 153 Bruxelles (schaerbeek) Bruxelles-Capitale 1030",
    "addr:housenumber":"153",
    "addr:postcode":"1030",
    "addr:street":"Boulevard Lambermont",
    "iso:country":"BE",
    "sg:address":"Boulevard Lambermont 153",
    "sg:city":"Bruxelles (schaerbeek)",
    "sg:classifiers":[
        {
            "category":"Wholesale",
            "subcategory":"Medical Equipment & Supplies",
            "type":"Manufacturing & Wholesale Goods"
        }
    ],
    "sg:phone":"+32 2 241 59 95",
    "sg:postcode":"1030",
    "sg:province":"Bruxelles-Capitale",
    "sg:tags":[
        "-",
        "imaging"
    ],
    "wof:name":"D.d.i. Europe Sa",
    "wof:placetype":"venue"
},
  "geometry": {"coordinates":[4.3816971779,50.8708457947],"type":"Point"}
}