{
  "type": "Feature",
  "properties": {
    "addr:full":"Bosstraat 141 Bree Limburg 3960",
    "addr:housenumber":"141",
    "addr:postcode":"3960",
    "addr:street":"Bosstraat",
    "iso:country":"BE",
    "sg:address":"Bosstraat 141",
    "sg:city":"Bree",
    "sg:orig_category":"Eleveurs and marchands de porcs",
    "sg:phone":"+32 89 86 60 67",
    "sg:postcode":"3960",
    "sg:province":"Limburg",
    "wof:name":"Maria Truyen",
    "wof:placetype":"venue"
},
  "geometry": {"coordinates":[5.6759848595,51.1390075684],"type":"Point"}
}