{
  "type": "Feature",
  "properties": {
    "iso:country":"BE",
    "sg:address":"Avenue De La Lib\u00c9ration 67",
    "sg:city":"Soumagne",
    "sg:orig_category":"Apotheken",
    "sg:phone":"+32 4 358 50 47",
    "sg:postcode":"4630",
    "sg:province":"Li\u00e8ge",
    "wof:name":"Pharmacie Dellicour",
    "wof:placetype":"venue"
},
  "geometry": {"coordinates":[5.711037159,50.6106758118],"type":"Point"}
}