{
  "type": "Feature",
  "properties": {
    "addr:full":"Molenstraat 8 Laarne Oost-Vlaanderen 9270",
    "addr:housenumber":"8",
    "addr:postcode":"9270",
    "addr:street":"Molenstraat",
    "iso:country":"BE",
    "sg:address":"Molenstraat 8",
    "sg:city":"Laarne",
    "sg:orig_category":"Notarissen",
    "sg:phone":"+32 9 369 02 74",
    "sg:postcode":"9270",
    "sg:province":"Oost-Vlaanderen",
    "wof:name":"I. Daelman",
    "wof:placetype":"venue"
},
  "geometry": {"coordinates":[3.8514759541,51.0290184021],"type":"Point"}
}