{
  "type": "Feature",
  "properties": {
    "iso:country":"BE",
    "sg:address":"Centre 17",
    "sg:city":"Plombi\u00c8res",
    "sg:orig_category":"Epiceries",
    "sg:phone":"+32 87 78 60 31",
    "sg:postcode":"4852",
    "sg:province":"Li\u00e8ge",
    "wof:name":"Super Echo",
    "wof:placetype":"venue"
},
  "geometry": {"coordinates":[5.9622411728,50.7385292053],"type":"Point"}
}