{
  "type": "Feature",
  "properties": {
    "addr:full":"Huis Ten Halve 21 Zele Oost-Vlaanderen 9240",
    "addr:housenumber":"21",
    "addr:postcode":"9240",
    "addr:street":"Huis Ten Halve",
    "iso:country":"BE",
    "sg:address":"Huis Ten Halve 21",
    "sg:city":"Zele",
    "sg:orig_category":"Entretien and r\u00e9parations de voitures",
    "sg:phone":"+32 52 44 68 11",
    "sg:postcode":"9240",
    "sg:province":"Oost-Vlaanderen",
    "wof:name":"Carrosserie Alhan",
    "wof:placetype":"venue"
},
  "geometry": {"coordinates":[4.0419669151,51.0786819458],"type":"Point"}
}