{
  "type": "Feature",
  "properties": {
    "iso:country":"BE",
    "sg:address":"Keistraat 10",
    "sg:city":"Genk",
    "sg:orig_category":"Slagers",
    "sg:phone":"+32 89 35 04 17",
    "sg:postcode":"3600",
    "sg:province":"Limburg",
    "wof:name":"M. Flak",
    "wof:placetype":"venue"
},
  "geometry": {"coordinates":[5.4537439346,50.9685745239],"type":"Point"}
}