{
  "type": "Feature",
  "properties": {
    "addr:full":"R. Novarumlaan 19 Beveren Oost-Vlaanderen 9120",
    "addr:housenumber":"19",
    "addr:postcode":"9120",
    "addr:street":"Novarumlaan",
    "iso:country":"BE",
    "sg:address":"R. Novarumlaan 19",
    "sg:city":"Beveren",
    "sg:orig_category":"Sportclubs",
    "sg:phone":"+32 3 755 19 59",
    "sg:postcode":"9120",
    "sg:province":"Oost-Vlaanderen",
    "wof:name":"De Smishoekvrienden - Vrasene",
    "wof:placetype":"venue"
},
  "geometry": {"coordinates":[4.1902618408,51.2204055786],"type":"Point"}
}