{
  "type": "Feature",
  "properties": {
    "addr:full":"Jos Verlindenstraat 27 Neerpelt Limburg 3910",
    "addr:housenumber":"27",
    "addr:postcode":"3910",
    "addr:street":"Jos Verlindenstraat",
    "iso:country":"BE",
    "sg:address":"Jos Verlindenstraat 27",
    "sg:city":"Neerpelt",
    "sg:orig_category":"Plaatsen van vloer- and muurbekleding Schilders",
    "sg:phone":"+32 11 64 07 95",
    "sg:postcode":"3910",
    "sg:province":"Limburg",
    "wof:name":"Wehenkel",
    "wof:placetype":"venue"
},
  "geometry": {"coordinates":[5.4777088165,51.2283706665],"type":"Point"}
}