{
  "type": "Feature",
  "properties": {
    "iso:country":"BE",
    "sg:address":"Kloosterstraat 33",
    "sg:city":"Beveren",
    "sg:orig_category":"Architectes",
    "sg:phone":"+32 3 755 48 34",
    "sg:postcode":"9120",
    "sg:province":"Oost-Vlaanderen",
    "wof:name":"Architectenbureau Vermeirsch",
    "wof:placetype":"venue"
},
  "geometry": {"coordinates":[4.2590799332,51.2148094177],"type":"Point"}
}