{
  "type": "Feature",
  "properties": {
    "iso:country":"BE",
    "sg:address":"Rue Des Bigarreaux 8",
    "sg:city":"Namur",
    "sg:orig_category":"Maisons de vacances",
    "sg:phone":"+32 81 58 90 56",
    "sg:postcode":"5024",
    "sg:province":"Namur",
    "wof:name":"F. Tondu",
    "wof:placetype":"venue"
},
  "geometry": {"coordinates":[4.9717798233,50.4963874817],"type":"Point"}
}