{
  "type": "Feature",
  "properties": {
    "addr:full":"Avenue De L'energie 9 Alleur Li\u00e8ge 4432",
    "addr:housenumber":"9",
    "addr:postcode":"4432",
    "addr:street":"Avenue De L'Energie",
    "iso:country":"BE",
    "sg:address":"Avenue De L'energie 9",
    "sg:city":"Alleur",
    "sg:classifiers":[
        {
            "category":"Military Area",
            "subcategory":"Armory",
            "type":"Public Place"
        }
    ],
    "sg:phone":"+32 4 263 89 90",
    "sg:postcode":"4432",
    "sg:province":"Li\u00e8ge",
    "sg:tags":[
        "also",
        "pistol",
        "ammunition",
        "rifle"
    ],
    "wof:name":"Edgard Grimard S.a.",
    "wof:placetype":"venue"
},
  "geometry": {"coordinates":[5.5251011848,50.6747016907],"type":"Point"}
}