{
  "type": "Feature",
  "properties": {
    "iso:country":"BE",
    "sg:address":"Rue Albert I 38",
    "sg:city":"Tournai (vezon)",
    "sg:classifiers":[
        {
            "category":"Parking",
            "subcategory":"Garage",
            "type":"Transportation"
        }
    ],
    "sg:phone":"+32 69 44 27 85",
    "sg:postcode":"7538",
    "sg:province":"Hainaut",
    "sg:tags":[
        "truck",
        "-",
        "dump",
        "transport"
    ],
    "wof:name":"Van Nieuwenhuyse Sa",
    "wof:placetype":"venue"
},
  "geometry": {"coordinates":[3.4978420734,50.572353363],"type":"Point"}
}