{
  "type": "Feature",
  "properties": {
    "iso:country":"BE",
    "sg:address":"Zwaanstraat 1b",
    "sg:city":"Galmaarden (tollembeek)",
    "sg:classifiers":[
        {
            "category":"Professional",
            "subcategory":"Advertising",
            "type":"Services"
        }
    ],
    "sg:phone":"+32 54 56 83 81",
    "sg:postcode":"1570",
    "sg:province":"Vlaams-Brabant",
    "sg:tags":[
        "clothes"
    ],
    "wof:name":"Plak 4 Publi",
    "wof:placetype":"venue"
},
  "geometry": {"coordinates":[3.981194973,50.7385749817],"type":"Point"}
}