{
  "type": "Feature",
  "properties": {
    "iso:country":"BE",
    "sg:address":"Albrecht Rodenbachlaan 21",
    "sg:city":"Grimbergen",
    "sg:orig_category":"Fleurs and plantes",
    "sg:phone":"+32 2 270 19 03",
    "sg:postcode":"1850",
    "sg:province":"Vlaams-Brabant",
    "wof:name":"Red Point T S",
    "wof:placetype":"venue"
},
  "geometry": {"coordinates":[4.3679251671,50.9314117432],"type":"Point"}
}