{
  "type": "Feature",
  "properties": {
    "iso:country":"BE",
    "sg:address":"Amerstraat 42",
    "sg:city":"Aarschot",
    "sg:classifiers":[
        {
            "category":"Shopping",
            "subcategory":"Crafts & Fabrics",
            "type":"Retail Goods"
        }
    ],
    "sg:phone":"+32 16 56 63 64",
    "sg:postcode":"3200",
    "sg:province":"Vlaams-Brabant",
    "sg:tags":[
        "silk",
        "-"
    ],
    "wof:name":"Schellens W",
    "wof:placetype":"venue"
},
  "geometry": {"coordinates":[4.8368468285,50.986164093],"type":"Point"}
}