{
  "type": "Feature",
  "properties": {
    "addr:full":"Schoolstraat 48 Beersel Vlaams-Brabant 1650",
    "addr:housenumber":"48",
    "addr:postcode":"1650",
    "addr:street":"Schoolstraat",
    "iso:country":"BE",
    "sg:address":"Schoolstraat 48",
    "sg:city":"Beersel",
    "sg:orig_category":"Sportcentra Sportclubs Sportterreinen and installaties behalve sportcentra",
    "sg:phone":"+32 2 377 62 83",
    "sg:postcode":"1650",
    "sg:province":"Vlaams-Brabant",
    "wof:name":"Sport Centrum Kerkeveld",
    "wof:placetype":"venue"
},
  "geometry": {"coordinates":[4.3128600121,50.7672424316],"type":"Point"}
}