{
  "type": "Feature",
  "properties": {
    "addr:full":"Moerdijkbeek Oost 34 Koekelare West-Vlaanderen 8680",
    "addr:housenumber":"34",
    "addr:postcode":"8680",
    "addr:street":"Moerdijkbeek Oost",
    "iso:country":"BE",
    "sg:address":"Moerdijkbeek Oost 34",
    "sg:city":"Koekelare",
    "sg:orig_category":"Eleveurs de volaille",
    "sg:phone":"+32 59 27 63 26",
    "sg:postcode":"8680",
    "sg:province":"West-Vlaanderen",
    "wof:name":"Herman Laveyne",
    "wof:placetype":"venue"
},
  "geometry": {"coordinates":[2.9721260071,51.1235122681],"type":"Point"}
}