{
  "type": "Feature",
  "properties": {
    "addr:full":"Gebroeders Tassetstraat 16 Leuven Vlaams-Brabant 3018",
    "addr:housenumber":"16",
    "addr:postcode":"3018",
    "addr:street":"Gebroeders Tassetstraat",
    "iso:country":"BE",
    "sg:address":"Gebroeders Tassetstraat 16",
    "sg:city":"Leuven",
    "sg:orig_category":"Plaatsen van vloer- and muurbekleding Schilders",
    "sg:phone":"+32 16 44 61 50",
    "sg:postcode":"3018",
    "sg:province":"Vlaams-Brabant",
    "wof:name":"Patrick Stroobants",
    "wof:placetype":"venue"
},
  "geometry": {"coordinates":[4.6946001053,50.9241447449],"type":"Point"}
}