{
  "type": "Feature",
  "properties": {
    "iso:country":"BE",
    "sg:address":"Brusselbaan 83",
    "sg:city":"Sint-pieters-leeuw",
    "sg:classifiers":[
        {
            "category":"Building & Trades",
            "subcategory":"Cleaning & Sanitation",
            "type":"Services"
        }
    ],
    "sg:phone":"+32 2 733 59 43",
    "sg:postcode":"1600",
    "sg:province":"Vlaams-Brabant",
    "sg:tags":[
        "fa\u00e7ade",
        "maintenance"
    ],
    "wof:name":"Fa\u00c7abel",
    "wof:placetype":"venue"
},
  "geometry": {"coordinates":[4.2810368538,50.8047943115],"type":"Point"}
}