{
  "type": "Feature",
  "properties": {
    "iso:country":"BE",
    "sg:address":"Avenue Des Liserons 3",
    "sg:city":"Bruxelles",
    "sg:classifiers":[
        {
            "category":"Professional",
            "subcategory":"Management & Consulting",
            "type":"Services"
        }
    ],
    "sg:phone":"+32 2 784 39 93",
    "sg:postcode":"1020",
    "sg:province":"Bruxelles-Capitale",
    "sg:tags":[
        "marketing",
        "-",
        "consultant"
    ],
    "wof:name":"Applied Marketing & Services",
    "wof:placetype":"venue"
},
  "geometry": {"coordinates":[4.3688378334,50.8970336914],"type":"Point"}
}