{
  "type": "Feature",
  "properties": {
    "iso:country":"BE",
    "sg:address":"Roeselarestr 89",
    "sg:city":"Zonnebeke",
    "sg:classifiers":[
        {
            "category":"Autos & Motor Vehicles",
            "subcategory":"Automobile Sales",
            "type":"Retail Goods"
        }
    ],
    "sg:phone":"+32 51 77 95 11",
    "sg:postcode":"8980",
    "sg:province":"West-Vlaanderen",
    "sg:tags":[
        "equipment",
        "transport"
    ],
    "wof:name":"Debatra Nv",
    "wof:placetype":"venue"
},
  "geometry": {"coordinates":[3.0009939671,50.8757591248],"type":"Point"}
}