{
  "type": "Feature",
  "properties": {
    "addr:full":"L\u00fctticher Strasse 158 Kelmis Li\u00e8ge 4720",
    "addr:housenumber":"158",
    "addr:postcode":"4720",
    "addr:street":"Luetticher Strasse",
    "iso:country":"BE",
    "sg:address":"L\u00fctticher Strasse 158",
    "sg:city":"Kelmis",
    "sg:classifiers":[
        {
            "category":"Retail",
            "subcategory":"Auto Repair",
            "type":"Services"
        }
    ],
    "sg:phone":"+32 87 65 84 40",
    "sg:postcode":"4720",
    "sg:province":"Li\u00e8ge",
    "sg:tags":[
        "garage"
    ],
    "wof:name":"Ohn Jean Sprl",
    "wof:placetype":"venue"
},
  "geometry": {"coordinates":[6.0170788765,50.7165374756],"type":"Point"}
}