{
  "type": "Feature",
  "properties": {
    "iso:country":"BE",
    "sg:address":"Lammerdries 16c",
    "sg:city":"Olen",
    "sg:classifiers":[
        {
            "category":"Airport",
            "subcategory":"International",
            "type":"Transportation"
        }
    ],
    "sg:phone":"+32 14 23 19 48",
    "sg:postcode":"2250",
    "sg:province":"Antwerpen",
    "sg:tags":[
        "-",
        "transport"
    ],
    "wof:name":"Somaco Bvba",
    "wof:placetype":"venue"
},
  "geometry": {"coordinates":[4.9147100449,51.1488685608],"type":"Point"}
}