{
  "type": "Feature",
  "properties": {
    "iso:country":"BE",
    "sg:address":"Avenue John-fitzgerald Kennedy 1 Box 5",
    "sg:city":"Rixensart",
    "sg:classifiers":[
        {
            "category":"Retail",
            "subcategory":"Animal Services",
            "type":"Services"
        }
    ],
    "sg:phone":"+32 2 652 50 89",
    "sg:postcode":"1330",
    "sg:province":"Brabant Wallon",
    "sg:tags":[
        "grooming",
        "-",
        "dog"
    ],
    "wof:name":"Toilettage Elody",
    "wof:placetype":"venue"
},
  "geometry": {"coordinates":[4.5332751274,50.7153015137],"type":"Point"}
}