{
  "type": "Feature",
  "properties": {
    "addr:full":"Dynamicalaan 11 Wilrijk Antwerpen 2610",
    "addr:housenumber":"11",
    "addr:postcode":"2610",
    "addr:street":"Dynamicalaan;Antwerpen",
    "iso:country":"BE",
    "sg:address":"Dynamicalaan 11",
    "sg:city":"Wilrijk",
    "sg:classifiers":[
        {
            "category":"Professional",
            "subcategory":"Engineering",
            "type":"Services"
        }
    ],
    "sg:phone":"+32 3 820 79 79",
    "sg:postcode":"2610",
    "sg:province":"Antwerpen",
    "sg:tags":[
        "machine",
        "-",
        "mechanical"
    ],
    "wof:name":"Artelli Nv",
    "wof:placetype":"venue"
},
  "geometry": {"coordinates":[4.3787322044,51.1559486389],"type":"Point"}
}