{
  "type": "Feature",
  "properties": {
    "addr:full":"Tongersesteenweg 40 Sint-truiden Limburg 3800",
    "addr:housenumber":"40",
    "addr:postcode":"3800",
    "addr:street":"Tongersesteenweg",
    "iso:country":"BE",
    "sg:address":"Tongersesteenweg 40",
    "sg:city":"Sint-truiden",
    "sg:orig_category":"Boucheries",
    "sg:phone":"+32 11 68 73 48",
    "sg:postcode":"3800",
    "sg:province":"Limburg",
    "wof:name":"Rudi Van Exel",
    "wof:placetype":"venue"
},
  "geometry": {"coordinates":[5.1919021606,50.812789917],"type":"Point"}
}