{
  "type": "Feature",
  "properties": {
    "addr:full":"Rue M. H\u00c9ron 6 Flawinne Namur 5020",
    "addr:housenumber":"6",
    "addr:postcode":"5020",
    "addr:street":"Rue M. He\u0301Ron",
    "iso:country":"BE",
    "sg:address":"Rue M. H\u00c9ron 6",
    "sg:city":"Flawinne",
    "sg:orig_category":"Quincailleries. Magasins sp\u00e9cialis\u00e9s",
    "sg:phone":"+32 81 74 12 38",
    "sg:postcode":"5020",
    "sg:province":"Namur",
    "wof:name":"Fondaire & Co",
    "wof:placetype":"venue"
},
  "geometry": {"coordinates":[4.7984027863,50.4609069824],"type":"Point"}
}