{
  "type": "Feature",
  "properties": {
    "iso:country":"BE",
    "sg:address":"Rue Maurice Van Rolleghem 18 Box 2",
    "sg:city":"Bruxelles (jette)",
    "sg:classifiers":[
        {
            "category":"Banks & Credit Unions",
            "subcategory":"Investment Brokerage",
            "type":"Services"
        }
    ],
    "sg:phone":"+32 2 479 28 07",
    "sg:postcode":"1090",
    "sg:province":"Bruxelles-Capitale",
    "sg:tags":[
        "repair",
        "-",
        "installation",
        "sanitary",
        "article"
    ],
    "wof:name":"Van Asten R",
    "wof:placetype":"venue"
},
  "geometry": {"coordinates":[4.3235030174,50.8904800415],"type":"Point"}
}