{
  "type": "Feature",
  "properties": {
    "addr:full":"Kapellestraat 50 Oostende West-Vlaanderen 8400",
    "addr:housenumber":"50",
    "addr:postcode":"8400",
    "addr:street":"Kapellestraat",
    "iso:country":"BE",
    "sg:address":"Kapellestraat 50",
    "sg:city":"Oostende",
    "sg:orig_category":"Baby- and kinderkleding Dameskledingzaken Herenkledingzaken",
    "sg:phone":"+32 59 51 63 75",
    "sg:postcode":"8400",
    "sg:province":"West-Vlaanderen",
    "wof:name":"Hennes & Mauritz ( H&m)",
    "wof:placetype":"venue"
},
  "geometry": {"coordinates":[2.9194409847,51.2300453186],"type":"Point"}
}