{
  "type": "Feature",
  "properties": {
    "iso:country":"BE",
    "sg:address":"Bogaertstraat 25",
    "sg:city":"Sint-martens-latem",
    "sg:orig_category":"M\u00e9decins and sp\u00e9cialistes",
    "sg:phone":"+32 9 281 02 80",
    "sg:postcode":"9830",
    "sg:province":"Oost-Vlaanderen",
    "wof:name":"Eric Cambie",
    "wof:placetype":"venue"
},
  "geometry": {"coordinates":[3.6156680584,51.0237159729],"type":"Point"}
}