{
  "type": "Feature",
  "properties": {
    "addr:full":"Weidestraat 12 Zottegem Oost-Vlaanderen 9620",
    "addr:housenumber":"12",
    "addr:postcode":"9620",
    "addr:street":"Weidestraat",
    "iso:country":"BE",
    "sg:address":"Weidestraat 12",
    "sg:city":"Zottegem",
    "sg:orig_category":"Maatkleding Fab",
    "sg:phone":"+32 9 360 12 74",
    "sg:postcode":"9620",
    "sg:province":"Oost-Vlaanderen",
    "wof:name":"Paul Labaere",
    "wof:placetype":"venue"
},
  "geometry": {"coordinates":[3.8043100834,50.8709907532],"type":"Point"}
}