{
  "type": "Feature",
  "properties": {
    "iso:country":"BE",
    "sg:address":"Nieuwstraat 1ba",
    "sg:city":"Ninove",
    "sg:classifiers":[
        {
            "category":"Shopping",
            "subcategory":"Clothing, Apparel, & Fashions",
            "type":"Retail Goods"
        }
    ],
    "sg:phone":"+32 54 33 90 81",
    "sg:postcode":"9402",
    "sg:province":"Oost-Vlaanderen",
    "sg:tags":[
        "ondergoed",
        "lingerie"
    ],
    "wof:name":"J. De Vos",
    "wof:placetype":"venue"
},
  "geometry": {"coordinates":[4.0410351753,50.8238677979],"type":"Point"}
}