{
  "type": "Feature",
  "properties": {
    "iso:country":"BE",
    "sg:address":"Lusthoflaan 87",
    "sg:city":"Gent",
    "sg:orig_category":"M\u00e9decins and sp\u00e9cialistes",
    "sg:phone":"+32 9 236 63 37",
    "sg:postcode":"9030",
    "sg:province":"Oost-Vlaanderen",
    "wof:name":"Frank Provenier",
    "wof:placetype":"venue"
},
  "geometry": {"coordinates":[3.6966750622,51.07862854],"type":"Point"}
}