{
  "type": "Feature",
  "properties": {
    "iso:country":"BE",
    "sg:address":"Rue D\u00b4 Ensival 20",
    "sg:city":"Verviers",
    "sg:classifiers":[
        {
            "category":"Fast Food",
            "type":"Food & Drink"
        }
    ],
    "sg:phone":"+32 87 31 20 47",
    "sg:postcode":"4800",
    "sg:province":"Li\u00e8ge",
    "sg:tags":[
        "\u00c0",
        "emporter",
        "restaurants"
    ],
    "wof:name":"Au Relais",
    "wof:placetype":"venue"
},
  "geometry": {"coordinates":[5.8545241356,50.5886306763],"type":"Point"}
}