{
  "type": "Feature",
  "properties": {
    "iso:country":"BE",
    "sg:address":"Begijnengracht 32",
    "sg:city":"Gent",
    "sg:orig_category":"Artistes ind\u00e9pendants",
    "sg:phone":"+32 9 224 00 18",
    "sg:postcode":"9000",
    "sg:province":"Oost-Vlaanderen",
    "wof:name":"Freya Van Laethem",
    "wof:placetype":"venue"
},
  "geometry": {"coordinates":[3.7132160664,51.0563583374],"type":"Point"}
}