{
  "type": "Feature",
  "properties": {
    "iso:country":"BE",
    "sg:address":"Sint-truidersteenweg 445",
    "sg:city":"Tongeren",
    "sg:orig_category":"Loodgieterij, verwarming and sanitaire installaties",
    "sg:phone":"+32 12 23 34 52",
    "sg:postcode":"3700",
    "sg:province":"Limburg",
    "wof:name":"Dama Engineering",
    "wof:placetype":"venue"
},
  "geometry": {"coordinates":[5.4055719376,50.7850608826],"type":"Point"}
}