{
  "type": "Feature",
  "properties": {
    "addr:full":"Engeldonk 3 Beringen Limburg 3583",
    "addr:housenumber":"3",
    "addr:postcode":"3583",
    "addr:street":"Engeldonk",
    "iso:country":"BE",
    "sg:address":"Engeldonk 3",
    "sg:city":"Beringen",
    "sg:orig_category":"Enseignement maternel and primaire",
    "sg:phone":"+32 13 66 35 26",
    "sg:postcode":"3583",
    "sg:province":"Limburg",
    "wof:name":"Vrije Basisschool",
    "wof:placetype":"venue"
},
  "geometry": {"coordinates":[5.1706700325,51.0389442444],"type":"Point"}
}