{
  "type": "Feature",
  "properties": {
    "iso:country":"BE",
    "sg:address":"Rue Des Religieuses 18",
    "sg:city":"Philippeville",
    "sg:classifiers":[
        {
            "category":"Structure",
            "subcategory":"Office Building",
            "type":"Public Place"
        }
    ],
    "sg:phone":"+32 71 66 68 48",
    "sg:postcode":"5600",
    "sg:province":"Namur",
    "sg:tags":[
        "roofing",
        "slate"
    ],
    "wof:name":"Drouet Pierre Sc",
    "wof:placetype":"venue"
},
  "geometry": {"coordinates":[4.5460348129,50.1971549988],"type":"Point"}
}