{
  "type": "Feature",
  "properties": {
    "iso:country":"BE",
    "sg:address":"Rue Des Cerisiers 3",
    "sg:city":"Dinant",
    "sg:classifiers":[
        {
            "category":"Food & Beverages",
            "subcategory":"Dairy",
            "type":"Retail Goods"
        }
    ],
    "sg:phone":"+32 82 22 42 38",
    "sg:postcode":"5500",
    "sg:province":"Namur",
    "sg:tags":[
        "product",
        "-"
    ],
    "wof:name":"Dardenne E",
    "wof:placetype":"venue"
},
  "geometry": {"coordinates":[4.9267930984,50.2555732727],"type":"Point"}
}