{
  "type": "Feature",
  "properties": {
    "addr:full":"Rue De Veeweyde 123 Bruxelles (anderlecht) Bruxelles-Capitale 1070",
    "addr:housenumber":"123",
    "addr:postcode":"1070",
    "addr:street":"Rue De Veeweyde",
    "iso:country":"BE",
    "sg:address":"Rue De Veeweyde 123",
    "sg:city":"Bruxelles (anderlecht)",
    "sg:classifiers":[
        {
            "category":"Home & Garden",
            "subcategory":"Kitchen Supply",
            "type":"Retail Goods"
        }
    ],
    "sg:phone":"+32 2 522 24 92",
    "sg:postcode":"1070",
    "sg:province":"Bruxelles-Capitale",
    "sg:tags":[
        "installation"
    ],
    "wof:name":"Linea Concept",
    "wof:placetype":"venue"
},
  "geometry": {"coordinates":[4.3046131134,50.8303489685],"type":"Point"}
}