{
  "type": "Feature",
  "properties": {
    "iso:country":"BE",
    "sg:address":"Ten Briele 2",
    "sg:city":"Sint-michiels",
    "sg:classifiers":[
        {
            "category":"Manufacturing",
            "subcategory":"Metals",
            "type":"Manufacturing & Wholesale Goods"
        }
    ],
    "sg:phone":"+32 50 40 88 40",
    "sg:postcode":"8200",
    "sg:province":"West-Vlaanderen",
    "sg:tags":[
        "sheet",
        "laser",
        "working"
    ],
    "wof:name":"Slabinck Laser Products Nv",
    "wof:placetype":"venue"
},
  "geometry": {"coordinates":[3.2263629436,51.1859893799],"type":"Point"}
}