{
  "type": "Feature",
  "properties": {
    "iso:country":"BE",
    "sg:address":"Segersweg 3",
    "sg:city":"Kortrijk",
    "sg:orig_category":"Architectes",
    "sg:phone":"+32 56 22 65 58",
    "sg:postcode":"8510",
    "sg:province":"West-Vlaanderen",
    "wof:name":"Marie Richard",
    "wof:placetype":"venue"
},
  "geometry": {"coordinates":[3.2627210617,50.7850990295],"type":"Point"}
}