{
  "type": "Feature",
  "properties": {
    "iso:country":"BE",
    "sg:address":"Oude Mechelsebaan 481",
    "sg:city":"Aarschot",
    "sg:orig_category":"Diensten voor huisdieren Huisdieren and benodigdheden Huisdierenkwekers",
    "sg:phone":"+32 16 56 35 59",
    "sg:postcode":"3201",
    "sg:province":"Vlaams-Brabant",
    "wof:name":"Het Boemerke",
    "wof:placetype":"venue"
},
  "geometry": {"coordinates":[4.8806428909,51.0078125],"type":"Point"}
}