{
  "type": "Feature",
  "properties": {
    "iso:country":"BE",
    "sg:address":"Kempenlaan 34",
    "sg:city":"Vorselaar",
    "sg:classifiers":[
        {
            "category":"Personal",
            "subcategory":"Beauty Salon",
            "type":"Services"
        }
    ],
    "sg:phone":"+32 14 51 32 69",
    "sg:postcode":"2290",
    "sg:province":"Antwerpen",
    "sg:tags":[
        "de",
        "coiffure"
    ],
    "wof:name":"Paul Smits",
    "wof:placetype":"venue"
},
  "geometry": {"coordinates":[4.7657117844,51.2018203735],"type":"Point"}
}