{
  "type": "Feature",
  "properties": {
    "addr:full":"Rue De Louvain 25 Incourt Brabant Wallon 1315",
    "addr:housenumber":"25",
    "addr:postcode":"1315",
    "addr:street":"Rue De Louvain",
    "iso:country":"BE",
    "sg:address":"Rue De Louvain 25",
    "sg:city":"Incourt",
    "sg:orig_category":"Diverse bedrijfsbeheeradviesbureaus",
    "sg:phone":"+32 10 85 50 00",
    "sg:postcode":"1315",
    "sg:province":"Brabant Wallon",
    "wof:name":"Bofeit",
    "wof:placetype":"venue"
},
  "geometry": {"coordinates":[4.799115181,50.6915283203],"type":"Point"}
}