{
  "type": "Feature",
  "properties": {
    "addr:full":"Rue Des Garennes 91 Watermaal-bosvoorde/watermael-boitsfort Bruxelles-Capitale 1170",
    "addr:housenumber":"91",
    "addr:postcode":"1170",
    "addr:street":"Rue Des Garennes",
    "iso:country":"BE",
    "sg:address":"Rue Des Garennes 91",
    "sg:city":"Watermaal-bosvoorde/watermael-boitsfort",
    "sg:orig_category":"M\u00e9decins and sp\u00e9cialistes",
    "sg:phone":"+32 2 672 07 88",
    "sg:postcode":"1170",
    "sg:province":"Bruxelles-Capitale",
    "wof:name":"Stephane Vanlaer/s. Vanlaer",
    "wof:placetype":"venue"
},
  "geometry": {"coordinates":[4.4162130356,50.8024635315],"type":"Point"}
}