{
  "type": "Feature",
  "properties": {
    "iso:country":"BE",
    "sg:address":"Avenue De L'or\u00e9e 23",
    "sg:city":"Bruxelles",
    "sg:classifiers":[
        {
            "category":"Real Estate",
            "subcategory":"Architect",
            "type":"Services"
        }
    ],
    "sg:phone":"+32 2 538 18 21",
    "sg:postcode":"1000",
    "sg:province":"Bruxelles-Capitale",
    "wof:name":"Jourdain S Sprl",
    "wof:placetype":"venue"
},
  "geometry": {"coordinates":[4.3854699135,50.8102989197],"type":"Point"}
}