{
  "type": "Feature",
  "properties": {
    "iso:country":"BE",
    "sg:address":"Chauss\u00c9e P\u00c9ruwelz 3",
    "sg:city":"Leuze-en-hainaut",
    "sg:orig_category":"Agences immobili\u00e8res",
    "sg:phone":"+32 69 66 20 50",
    "sg:postcode":"7900",
    "sg:province":"Hainaut",
    "wof:name":"Immobili\u00c8re Clermont Eric",
    "wof:placetype":"venue"
},
  "geometry": {"coordinates":[3.614923954,50.5693054199],"type":"Point"}
}