{
  "type": "Feature",
  "properties": {
    "iso:country":"BE",
    "sg:address":"Rue De La Concorde 78-80",
    "sg:city":"La Louviere",
    "sg:classifiers":[
        {
            "category":"Personal",
            "subcategory":"Beauty Salon",
            "type":"Services"
        }
    ],
    "sg:phone":"+32 64 22 82 77",
    "sg:postcode":"7100",
    "sg:province":"Hainaut",
    "sg:tags":[
        "de",
        "coiffure"
    ],
    "wof:name":"Studio Giovanna",
    "wof:placetype":"venue"
},
  "geometry": {"coordinates":[4.1895971298,50.48072052],"type":"Point"}
}