{
  "type": "Feature",
  "properties": {
    "iso:country":"BE",
    "sg:address":"Boulevard Pire Lef\u00c8vre Desnouettes 20",
    "sg:city":"Braine-l\u00b4alleud",
    "sg:orig_category":"Kapsalons",
    "sg:phone":"+32 2 384 82 49",
    "sg:postcode":"1420",
    "sg:province":"Brabant Wallon",
    "wof:name":"Coiffure Marechal",
    "wof:placetype":"venue"
},
  "geometry": {"coordinates":[4.3862948418,50.6760978699],"type":"Point"}
}