{
  "type": "Feature",
  "properties": {
    "addr:full":"Place Du Grand Sablon 36b1 Brussel/bruxelles Bruxelles-Capitale 1000",
    "addr:housenumber":"36b1",
    "addr:postcode":"1000",
    "addr:street":"Place Du Grand Sablon;/",
    "iso:country":"BE",
    "sg:address":"Place Du Grand Sablon 36b1",
    "sg:city":"Brussel/bruxelles",
    "sg:orig_category":"Bijouteries and horlogeries. R\u00e9parations d'horloges, montres and bijoux",
    "sg:phone":"+32 2 513 62 60",
    "sg:postcode":"1000",
    "sg:province":"Bruxelles-Capitale",
    "wof:name":"Leysen Gebrs/leysen Jewellers",
    "wof:placetype":"venue"
},
  "geometry": {"coordinates":[4.3545880318,50.8407516479],"type":"Point"}
}