{
  "type": "Feature",
  "properties": {
    "iso:country":"BE",
    "sg:address":"Hoogveld 39",
    "sg:city":"Peer (wijchmaal)",
    "sg:classifiers":[
        {
            "category":"Professional",
            "subcategory":"Detective & Security Services",
            "type":"Services"
        }
    ],
    "sg:phone":"+32 11 63 30 24",
    "sg:postcode":"3990",
    "sg:province":"Limburg",
    "sg:tags":[
        "installation",
        "alarm",
        "-",
        "system"
    ],
    "wof:name":"E.t.i. Vienne Franky",
    "wof:placetype":"venue"
},
  "geometry": {"coordinates":[5.4158148766,51.1369590759],"type":"Point"}
}