{
  "type": "Feature",
  "properties": {
    "addr:full":"Stokerijstraat 28 Tielt West-Vlaanderen 8700",
    "addr:housenumber":"28",
    "addr:postcode":"8700",
    "addr:street":"Stokerijstraat",
    "iso:country":"BE",
    "sg:address":"Stokerijstraat 28",
    "sg:city":"Tielt",
    "sg:orig_category":"Peinture. Drogueries. Rev\u00eatements pour sols and murs",
    "sg:phone":"+32 51 40 16 56",
    "sg:postcode":"8700",
    "sg:province":"West-Vlaanderen",
    "wof:name":"Jean-pierre Vanluchene",
    "wof:placetype":"venue"
},
  "geometry": {"coordinates":[3.3243451118,51.004524231],"type":"Point"}
}