{
  "type": "Feature",
  "properties": {
    "addr:full":"Rue T\u00cate-de-boeuf 15 Li\u00c8ge Li\u00e8ge 4000",
    "addr:housenumber":"15",
    "addr:postcode":"4000",
    "addr:street":"Rue Te\u0302Te-De-Boeuf",
    "iso:country":"BE",
    "sg:address":"Rue T\u00cate-de-boeuf 15",
    "sg:city":"Li\u00c8ge",
    "sg:orig_category":"Dancings and bo\u00eetes de nuit. Caf\u00e9s",
    "sg:phone":"+32 4 221 31 22",
    "sg:postcode":"4000",
    "sg:province":"Li\u00e8ge",
    "wof:name":"Caf\u00c9 Bouldou",
    "wof:placetype":"venue"
},
  "geometry": {"coordinates":[5.569524765,50.640827179],"type":"Point"}
}