{
  "type": "Feature",
  "properties": {
    "addr:full":"Rue De La Providence 50 Charleroi (gosselies) Hainaut 6041",
    "addr:housenumber":"50",
    "addr:postcode":"6041",
    "addr:street":"Rue De La Providence",
    "iso:country":"BE",
    "sg:address":"Rue De La Providence 50",
    "sg:city":"Charleroi (gosselies)",
    "sg:classifiers":[
        {
            "category":"Real Estate",
            "subcategory":"Architect",
            "type":"Services"
        }
    ],
    "sg:phone":"+32 71 34 29 04",
    "sg:postcode":"6041",
    "sg:province":"Hainaut",
    "wof:name":"Gheys J-p",
    "wof:placetype":"venue"
},
  "geometry": {"coordinates":[4.3984651566,50.4120788574],"type":"Point"}
}