{
  "type": "Feature",
  "properties": {
    "iso:country":"BE",
    "sg:address":"Sint-amandsstraat 16",
    "sg:city":"Brugge",
    "sg:orig_category":"Juwelen and horloges",
    "sg:phone":"+32 50 34 24 32",
    "sg:postcode":"8000",
    "sg:province":"West-Vlaanderen",
    "wof:name":"L'anelli Di Roma",
    "wof:placetype":"venue"
},
  "geometry": {"coordinates":[3.2228899002,51.2085838318],"type":"Point"}
}