{
  "type": "Feature",
  "properties": {
    "addr:full":"Graaf Van Loonstraat 13 Beringen Limburg 3580",
    "addr:housenumber":"13",
    "addr:postcode":"3580",
    "addr:street":"Graaf Van Loonstraat",
    "iso:country":"BE",
    "sg:address":"Graaf Van Loonstraat 13",
    "sg:city":"Beringen",
    "sg:orig_category":"Hypotheken and hypotheekbanken Verbruikerskredietinstellingen",
    "sg:phone":"+32 11 42 24 10",
    "sg:postcode":"3580",
    "sg:province":"Limburg",
    "wof:name":"St.jozefskrediet",
    "wof:placetype":"venue"
},
  "geometry": {"coordinates":[5.2263131142,51.0490226746],"type":"Point"}
}