{
  "type": "Feature",
  "properties": {
    "iso:country":"BE",
    "sg:address":"Chauss\u00c9e De Grammont 100/11",
    "sg:city":"Lessines",
    "sg:classifiers":[
        {
            "category":"Insurance",
            "subcategory":"Life Insurance",
            "type":"Services"
        }
    ],
    "sg:phone":"+32 68 33 48 60",
    "sg:postcode":"7860",
    "sg:province":"Hainaut",
    "sg:tags":[
        "assurance"
    ],
    "wof:name":"De Cock-vandenhove",
    "wof:placetype":"venue"
},
  "geometry": {"coordinates":[3.8305439949,50.7190933228],"type":"Point"}
}