{
  "type": "Feature",
  "properties": {
    "iso:country":"BE",
    "sg:address":"Rue Louis Vangrootenbruel 77",
    "sg:city":"Renaix",
    "sg:classifiers":[
        {
            "category":"Professional",
            "subcategory":"Computer Services",
            "type":"Services"
        }
    ],
    "sg:phone":"+32 477 94 82 72",
    "sg:postcode":"9600",
    "sg:province":"Oost-Vlaanderen",
    "sg:tags":[
        "webdesign",
        "-",
        "internet"
    ],
    "wof:name":"Flock Design",
    "wof:placetype":"venue"
},
  "geometry": {"coordinates":[3.5911259651,50.74477005],"type":"Point"}
}