{
  "type": "Feature",
  "properties": {
    "addr:full":"Broekstraat 11 Affligem (essene) Vlaams-Brabant 1790",
    "addr:housenumber":"11",
    "addr:postcode":"1790",
    "addr:street":"Broekstraat",
    "iso:country":"BE",
    "sg:address":"Broekstraat 11",
    "sg:city":"Affligem (essene)",
    "sg:classifiers":[
        {
            "category":"Banks & Credit Unions",
            "subcategory":"Financial Services",
            "type":"Services"
        }
    ],
    "sg:phone":"+32 53 68 10 34",
    "sg:postcode":"1790",
    "sg:province":"Vlaams-Brabant",
    "sg:tags":[
        "loan",
        "mortgage"
    ],
    "wof:name":"De Pauw A Bvba",
    "wof:placetype":"venue"
},
  "geometry": {"coordinates":[4.1306991577,50.9160385132],"type":"Point"}
}