{
  "type": "Feature",
  "properties": {
    "iso:country":"BE",
    "sg:address":"Halsesteenweg 409",
    "sg:city":"Ninove (neigem)",
    "sg:classifiers":[
        {
            "category":"Bakery",
            "type":"Food & Drink"
        }
    ],
    "sg:phone":"+32 54 33 12 52",
    "sg:postcode":"9403",
    "sg:province":"Oost-Vlaanderen",
    "sg:tags":[
        "confectioner",
        "baker"
    ],
    "wof:name":"Moonens M",
    "wof:placetype":"venue"
},
  "geometry": {"coordinates":[4.0594549179,50.8027954102],"type":"Point"}
}