{
  "type": "Feature",
  "properties": {
    "iso:country":"BE",
    "sg:address":"Battelse Bergen 28",
    "sg:city":"Mechelen",
    "sg:classifiers":[
        {
            "category":"Sports & Exercise",
            "subcategory":"Sports Center",
            "type":"Entertainment"
        }
    ],
    "sg:phone":"+32 15 27 16 36",
    "sg:postcode":"2800",
    "sg:province":"Antwerpen",
    "sg:tags":[
        "de",
        "fitness"
    ],
    "wof:name":"Bodyplan",
    "wof:placetype":"venue"
},
  "geometry": {"coordinates":[4.4434161186,51.0425186157],"type":"Point"}
}