{
  "type": "Feature",
  "properties": {
    "addr:full":"Chauss\u00e9e De Waterloo 37 Rhode-saint-gen\u00e8se Vlaams-Brabant 1640",
    "addr:housenumber":"37",
    "addr:postcode":"1640",
    "addr:street":"Chausse\u0301E De Waterloo",
    "iso:country":"BE",
    "sg:address":"Chauss\u00e9e De Waterloo 37",
    "sg:city":"Rhode-saint-gen\u00e8se",
    "sg:orig_category":"Autombile concessionaires",
    "sg:phone":"+32 2 358 10 00",
    "sg:postcode":"1640",
    "sg:province":"Vlaams-Brabant",
    "wof:name":"Sterckx Sa",
    "wof:placetype":"venue"
},
  "geometry": {"coordinates":[4.3950891495,50.7462348938],"type":"Point"}
}