{
  "type": "Feature",
  "properties": {
    "iso:country":"BE",
    "sg:address":"Weg Naar Zwartberg 87b1",
    "sg:city":"Opglabbeek",
    "sg:orig_category":"Banken and kredietinstellingen",
    "sg:phone":"+32 89 85 79 79",
    "sg:postcode":"3660",
    "sg:province":"Limburg",
    "wof:name":"Ippa",
    "wof:placetype":"venue"
},
  "geometry": {"coordinates":[5.575507164,51.0417976379],"type":"Point"}
}