{
  "type": "Feature",
  "properties": {
    "addr:full":"Rue Du Colombier 1 Havelange Namur 5372",
    "addr:housenumber":"1",
    "addr:postcode":"5372",
    "addr:street":"Rue Du Colombier",
    "iso:country":"BE",
    "sg:address":"Rue Du Colombier 1",
    "sg:city":"Havelange",
    "sg:orig_category":"Voedingsspeciaalzaken",
    "sg:phone":"+32 86 32 10 83",
    "sg:postcode":"5372",
    "sg:province":"Namur",
    "wof:name":"Marie-christine Hubin",
    "wof:placetype":"venue"
},
  "geometry": {"coordinates":[5.3346471786,50.36170578],"type":"Point"}
}