{
  "type": "Feature",
  "properties": {
    "iso:country":"BE",
    "sg:address":"Van Lintstraat 85",
    "sg:city":"Anderlecht",
    "sg:orig_category":"Artsen and specialisten",
    "sg:phone":"+32 2 521 62 05",
    "sg:postcode":"1070",
    "sg:province":"Bruxelles-Capitale",
    "wof:name":"Bouba Ousmanou",
    "wof:placetype":"venue"
},
  "geometry": {"coordinates":[4.3258647919,50.8397521973],"type":"Point"}
}