{
  "type": "Feature",
  "properties": {
    "addr:full":"Rue Des Carburants 58 Bruxelles (forest) Bruxelles-Capitale 1190",
    "addr:housenumber":"58",
    "addr:postcode":"1190",
    "addr:street":"Rue Des Carburants",
    "iso:country":"BE",
    "sg:address":"Rue Des Carburants 58",
    "sg:city":"Bruxelles (forest)",
    "sg:classifiers":[
        {
            "category":"Professional",
            "subcategory":"Lawyer & Legal Services",
            "type":"Services"
        }
    ],
    "sg:phone":"+32 2 345 24 81",
    "sg:postcode":"1190",
    "sg:province":"Bruxelles-Capitale",
    "wof:name":"Schuermans Jean-pascal",
    "wof:placetype":"venue"
},
  "geometry": {"coordinates":[4.3198571205,50.8138542175],"type":"Point"}
}