{
  "type": "Feature",
  "properties": {
    "iso:country":"BE",
    "sg:address":"Romestraat 2a",
    "sg:city":"Lebbeke",
    "sg:classifiers":[
        {
            "category":"Shopping",
            "subcategory":"Florist",
            "type":"Retail Goods"
        }
    ],
    "sg:phone":"+32 52 41 44 44",
    "sg:postcode":"9280",
    "sg:province":"Oost-Vlaanderen",
    "wof:name":"Petra Bloemen",
    "wof:placetype":"venue"
},
  "geometry": {"coordinates":[4.1284980774,50.986541748],"type":"Point"}
}