{
  "type": "Feature",
  "properties": {
    "addr:full":"Rue Nazareth 28 Herve Li\u00e8ge 4651",
    "addr:housenumber":"28",
    "addr:postcode":"4651",
    "addr:street":"Rue Nazareth",
    "iso:country":"BE",
    "sg:address":"Rue Nazareth 28",
    "sg:city":"Herve",
    "sg:orig_category":"Pleisterwerk",
    "sg:phone":"+32 87 67 81 76",
    "sg:postcode":"4651",
    "sg:province":"Li\u00e8ge",
    "wof:name":"Fe. Antunes-duarte",
    "wof:placetype":"venue"
},
  "geometry": {"coordinates":[5.8031420708,50.6460914612],"type":"Point"}
}