{
  "type": "Feature",
  "properties": {
    "iso:country":"BE",
    "sg:address":"Vrankrijkstraat 88",
    "sg:city":"Dendermonde",
    "sg:orig_category":"Fleurs and plantes",
    "sg:phone":"+32 52 42 32 16",
    "sg:postcode":"9200",
    "sg:province":"Oost-Vlaanderen",
    "wof:name":"Johan Vereeken",
    "wof:placetype":"venue"
},
  "geometry": {"coordinates":[4.0231361389,50.996006012],"type":"Point"}
}