{
  "type": "Feature",
  "properties": {
    "addr:full":"Dorpsplein 6 Rotselaar Vlaams-Brabant 3110",
    "addr:housenumber":"6",
    "addr:postcode":"3110",
    "addr:street":"Dorpsplein",
    "iso:country":"BE",
    "sg:address":"Dorpsplein 6",
    "sg:city":"Rotselaar",
    "sg:classifiers":[
        {
            "category":"Fast Food",
            "type":"Food & Drink"
        }
    ],
    "sg:phone":"+32 16 44 38 90",
    "sg:postcode":"3110",
    "sg:province":"Vlaams-Brabant",
    "sg:tags":[
        "meeneem",
        "restaurant"
    ],
    "wof:name":"Golden Lotus",
    "wof:placetype":"venue"
},
  "geometry": {"coordinates":[4.7091741562,50.9509620667],"type":"Point"}
}