{
  "type": "Feature",
  "properties": {
    "addr:full":"Wijnendalestraat 2 Kortemark West-Vlaanderen 8610",
    "addr:housenumber":"2",
    "addr:postcode":"8610",
    "addr:street":"Wijnendalestraat",
    "iso:country":"BE",
    "sg:address":"Wijnendalestraat 2",
    "sg:city":"Kortemark",
    "sg:orig_category":"Fruits and l\u00e9gumes. Producteurs de fruits",
    "sg:phone":"+32 51 57 00 43",
    "sg:postcode":"8610",
    "sg:province":"West-Vlaanderen",
    "wof:name":"Gabriel Vanacker",
    "wof:placetype":"venue"
},
  "geometry": {"coordinates":[3.0453379154,51.047668457],"type":"Point"}
}