{
  "type": "Feature",
  "properties": {
    "iso:country":"BE",
    "sg:address":"Marktstraat 37",
    "sg:city":"Harelbeke",
    "sg:orig_category":"Kunstonderwijs",
    "sg:phone":"+32 56 73 35 70",
    "sg:postcode":"8530",
    "sg:province":"West-Vlaanderen",
    "wof:name":"Acad. Beeldende Vorming",
    "wof:placetype":"venue"
},
  "geometry": {"coordinates":[3.3102030754,50.8561553955],"type":"Point"}
}