{
  "type": "Feature",
  "properties": {
    "addr:full":"Oostergem 3 Aalter Oost-Vlaanderen 9880",
    "addr:housenumber":"3",
    "addr:postcode":"9880",
    "addr:street":"Oostergem",
    "iso:country":"BE",
    "sg:address":"Oostergem 3",
    "sg:city":"Aalter",
    "sg:classifiers":[
        {
            "category":"Building & Trades",
            "subcategory":"Construction",
            "type":"Services"
        }
    ],
    "sg:phone":"+32 9 374 39 10",
    "sg:postcode":"9880",
    "sg:province":"Oost-Vlaanderen",
    "sg:tags":[
        "installation",
        "-",
        "central",
        "heating"
    ],
    "wof:name":"Maes Ch",
    "wof:placetype":"venue"
},
  "geometry": {"coordinates":[3.4618771076,51.0878982544],"type":"Point"}
}