{
  "type": "Feature",
  "properties": {
    "addr:full":"Leeuwerikendreef 4 Schilde Antwerpen 2970",
    "addr:housenumber":"4",
    "addr:postcode":"2970",
    "addr:street":"Leeuwerikendreef",
    "iso:country":"BE",
    "sg:address":"Leeuwerikendreef 4",
    "sg:city":"Schilde",
    "sg:orig_category":"Sportclubs",
    "sg:phone":"+32 3 385 12 06",
    "sg:postcode":"2970",
    "sg:province":"Antwerpen",
    "wof:name":"Bvc St. Job In-'t-goor",
    "wof:placetype":"venue"
},
  "geometry": {"coordinates":[4.6124339104,51.2499198914],"type":"Point"}
}