{
  "type": "Feature",
  "properties": {
    "iso:country":"BE",
    "sg:address":"Place Monseu 28",
    "sg:city":"Ciney (grand)",
    "sg:classifiers":[
        {
            "category":"Restaurant",
            "type":"Food & Drink"
        }
    ],
    "sg:phone":"+32 83 21 86 96",
    "sg:postcode":"5590",
    "sg:province":"Namur",
    "wof:name":"La Part Des Anges",
    "wof:placetype":"venue"
},
  "geometry": {"coordinates":[5.0990738869,50.296005249],"type":"Point"}
}