{
  "type": "Feature",
  "properties": {
    "iso:country":"BE",
    "sg:address":"Kipdorp 45-47",
    "sg:city":"Antwerpen",
    "sg:classifiers":[
        {
            "category":"Professional",
            "subcategory":"Employment Agencies",
            "type":"Services"
        }
    ],
    "sg:phone":"+32 3 222 67 00",
    "sg:postcode":"2000",
    "sg:province":"Antwerpen",
    "sg:tags":[
        "shipping"
    ],
    "wof:name":"Port Support Nv",
    "wof:placetype":"venue"
},
  "geometry": {"coordinates":[4.4086761475,51.2209358215],"type":"Point"}
}