{
  "type": "Feature",
  "properties": {
    "addr:full":"Marathonstraat 94 Gent Oost-Vlaanderen 9000",
    "addr:housenumber":"94",
    "addr:postcode":"9000",
    "addr:street":"Marathonstraat;Oost-Vlaanderen",
    "iso:country":"BE",
    "sg:address":"Marathonstraat 94",
    "sg:city":"Gent",
    "sg:orig_category":"Artsen and specialisten",
    "sg:phone":"+32 9 221 11 54",
    "sg:postcode":"9000",
    "sg:province":"Oost-Vlaanderen",
    "wof:name":"Bruno Vincke",
    "wof:placetype":"venue"
},
  "geometry": {"coordinates":[3.699960947,51.0409812927],"type":"Point"}
}