{
  "type": "Feature",
  "properties": {
    "iso:country":"BE",
    "sg:address":"Rue Jacques D\u00c9sira 20",
    "sg:city":"Awans",
    "sg:classifiers":[
        {
            "category":"Personal",
            "subcategory":"Beauty Salon",
            "type":"Services"
        }
    ],
    "sg:phone":"+32 4 257 45 89",
    "sg:postcode":"4340",
    "sg:province":"Li\u00e8ge",
    "sg:tags":[
        "de",
        "coiffure"
    ],
    "wof:name":"Coiffure Marie-claude",
    "wof:placetype":"venue"
},
  "geometry": {"coordinates":[5.4486122131,50.7027320862],"type":"Point"}
}