{
  "type": "Feature",
  "properties": {
    "iso:country":"BE",
    "sg:address":"Rempart Des Arquebusiers 11",
    "sg:city":"Vise",
    "sg:orig_category":"Landbouwmachines Gh",
    "sg:phone":"+32 4 379 29 08",
    "sg:postcode":"4600",
    "sg:province":"Li\u00e8ge",
    "wof:name":"Jean Fontaine",
    "wof:placetype":"venue"
},
  "geometry": {"coordinates":[5.6964879036,50.7351303101],"type":"Point"}
}