{
  "type": "Feature",
  "properties": {
    "addr:full":"Erfprinslaan 26 Sint-lambrechts-woluwe/woluwe-saint-lambert Bruxelles-Capitale 1200",
    "addr:housenumber":"26",
    "addr:postcode":"1200",
    "addr:street":"Erfprinslaan",
    "iso:country":"BE",
    "sg:address":"Erfprinslaan 26",
    "sg:city":"Sint-lambrechts-woluwe/woluwe-saint-lambert",
    "sg:orig_category":"Artsen and specialisten",
    "sg:phone":"+32 2 762 69 53",
    "sg:postcode":"1200",
    "sg:province":"Bruxelles-Capitale",
    "wof:name":"R. Majeres",
    "wof:placetype":"venue"
},
  "geometry": {"coordinates":[4.4117689133,50.8411521912],"type":"Point"}
}