{
  "type": "Feature",
  "properties": {
    "iso:country":"BE",
    "sg:address":"Brugstraat 25",
    "sg:city":"Ardooie",
    "sg:orig_category":"Studios photographiques",
    "sg:phone":"+32 51 74 42 52",
    "sg:postcode":"8850",
    "sg:province":"West-Vlaanderen",
    "wof:name":"Callewaert Foto",
    "wof:placetype":"venue"
},
  "geometry": {"coordinates":[3.2009921074,50.9768180847],"type":"Point"}
}