{
  "type": "Feature",
  "properties": {
    "iso:country":"BE",
    "sg:address":"Rotterdamstraat 31",
    "sg:city":"Antwerpen",
    "sg:orig_category":"Artistes ind\u00e9pendants",
    "sg:phone":"+32 3 226 97 14",
    "sg:postcode":"2060",
    "sg:province":"Antwerpen",
    "wof:name":"Rudolf Vervliet",
    "wof:placetype":"venue"
},
  "geometry": {"coordinates":[4.4187412262,51.2239685059],"type":"Point"}
}