{
  "type": "Feature",
  "properties": {
    "addr:full":"Rue Des Croisiers 37 Tournai Hainaut 7500",
    "addr:housenumber":"37",
    "addr:postcode":"7500",
    "addr:street":"Rue Des Croisiers",
    "iso:country":"BE",
    "sg:address":"Rue Des Croisiers 37",
    "sg:city":"Tournai",
    "sg:orig_category":"Bouwmaterialen Gh",
    "sg:phone":"+32 69 21 20 81",
    "sg:postcode":"7500",
    "sg:province":"Hainaut",
    "wof:name":"A.m.b. Construct",
    "wof:placetype":"venue"
},
  "geometry": {"coordinates":[3.4003350735,50.6054840088],"type":"Point"}
}