{
  "type": "Feature",
  "properties": {
    "addr:full":"Genklaan 13 Nieuwpoort West-Vlaanderen 8620",
    "addr:housenumber":"13",
    "addr:postcode":"8620",
    "addr:street":"Genklaan",
    "iso:country":"BE",
    "sg:address":"Genklaan 13",
    "sg:city":"Nieuwpoort",
    "sg:orig_category":"Experts-comptables",
    "sg:phone":"+32 58 23 55 80",
    "sg:postcode":"8620",
    "sg:province":"West-Vlaanderen",
    "wof:name":"Jacques Gombert",
    "wof:placetype":"venue"
},
  "geometry": {"coordinates":[2.7375628948,51.1302719116],"type":"Point"}
}