{
  "type": "Feature",
  "properties": {
    "addr:full":"Veldstraat 142 Meulebeke West-Vlaanderen 8760",
    "addr:housenumber":"142",
    "addr:postcode":"8760",
    "addr:street":"Veldstraat",
    "iso:country":"BE",
    "sg:address":"Veldstraat 142",
    "sg:city":"Meulebeke",
    "sg:orig_category":"Producteurs de l\u00e9gumes. Eleveurs de volaille. Eleveurs and marchands de porcs",
    "sg:phone":"+32 51 48 87 54",
    "sg:postcode":"8760",
    "sg:province":"West-Vlaanderen",
    "wof:name":"Georges Kindt",
    "wof:placetype":"venue"
},
  "geometry": {"coordinates":[3.2540750504,50.9530754089],"type":"Point"}
}