{
  "type": "Feature",
  "properties": {
    "addr:full":"Boulevard De L\u00b4empereur 3 Brussel/bruxelles Bruxelles-Capitale 1000",
    "addr:housenumber":"3",
    "addr:postcode":"1000",
    "addr:street":"Boulevard De L\u00b4Empereur;/",
    "iso:country":"BE",
    "sg:address":"Boulevard De L\u00b4empereur 3",
    "sg:city":"Brussel/bruxelles",
    "sg:orig_category":"Avocats and conseillers juridiques",
    "sg:phone":"+32 2 551 15 15",
    "sg:postcode":"1000",
    "sg:province":"Bruxelles-Capitale",
    "wof:name":"Florence De Fooz",
    "wof:placetype":"venue"
},
  "geometry": {"coordinates":[4.3546919823,50.8438568115],"type":"Point"}
}