{
  "type": "Feature",
  "properties": {
    "addr:full":"Frankrijklei 93 Antwerpen Antwerpen 2000",
    "addr:housenumber":"93",
    "addr:postcode":"2000",
    "addr:street":"Frankrijklei",
    "iso:country":"BE",
    "sg:address":"Frankrijklei 93",
    "sg:city":"Antwerpen",
    "sg:orig_category":"Advocaten and juridische adviseurs",
    "sg:phone":"+32 3 226 80 80",
    "sg:postcode":"2000",
    "sg:province":"Antwerpen",
    "wof:name":"Guy Poppe",
    "wof:placetype":"venue"
},
  "geometry": {"coordinates":[4.4113101959,51.2132072449],"type":"Point"}
}