{
  "type": "Feature",
  "properties": {
    "addr:full":"Avenue De Cortenbergh 118 Bruxelles Bruxelles-Capitale 1000",
    "addr:housenumber":"118",
    "addr:postcode":"1000",
    "addr:street":"Avenue De Cortenbergh",
    "iso:country":"BE",
    "sg:address":"Avenue De Cortenbergh 118",
    "sg:city":"Bruxelles",
    "sg:classifiers":[
        {
            "category":"Professional",
            "subcategory":"Management & Consulting",
            "type":"Services"
        }
    ],
    "sg:phone":"+32 2 740 21 40",
    "sg:postcode":"1000",
    "sg:province":"Bruxelles-Capitale",
    "sg:tags":[
        "consultant",
        "-",
        "legislation",
        "social"
    ],
    "wof:name":"Nera",
    "wof:placetype":"venue"
},
  "geometry": {"coordinates":[4.3892087936,50.8448867798],"type":"Point"}
}