{
  "type": "Feature",
  "properties": {
    "addr:full":"Stationsstraat 20 Wetteren Oost-Vlaanderen 9230",
    "addr:housenumber":"20",
    "addr:postcode":"9230",
    "addr:street":"Stationsstraat",
    "iso:country":"BE",
    "sg:address":"Stationsstraat 20",
    "sg:city":"Wetteren",
    "sg:classifiers":[
        {
            "category":"Shopping",
            "subcategory":"Clothing, Apparel, & Fashions",
            "type":"Retail Goods"
        }
    ],
    "sg:phone":"+32 9 369 22 89",
    "sg:postcode":"9230",
    "sg:province":"Oost-Vlaanderen",
    "sg:tags":[
        "underwear",
        "lingerie",
        "-"
    ],
    "wof:name":"Anny",
    "wof:placetype":"venue"
},
  "geometry": {"coordinates":[3.8833270073,51.0035209656],"type":"Point"}
}