{
  "type": "Feature",
  "properties": {
    "addr:full":"Rue De L'escaille 27 Les Bons Villers (villers-perwin) Hainaut 6210",
    "addr:housenumber":"27",
    "addr:postcode":"6210",
    "addr:street":"Rue De L'Escaille",
    "iso:country":"BE",
    "sg:address":"Rue De L'escaille 27",
    "sg:city":"Les Bons Villers (villers-perwin)",
    "sg:classifiers":[
        {
            "category":"Organizations",
            "subcategory":"Community Association",
            "type":"Services"
        }
    ],
    "sg:phone":"+32 71 85 49 68",
    "sg:postcode":"6210",
    "sg:province":"Hainaut",
    "sg:tags":[
        "purchasing"
    ],
    "wof:name":"All Rent",
    "wof:placetype":"venue"
},
  "geometry": {"coordinates":[4.4718241692,50.523475647],"type":"Point"}
}