{
  "type": "Feature",
  "properties": {
    "addr:full":"Lange Lobroekstraat 142 Antwerpen (groot) Antwerpen 2000",
    "addr:housenumber":"142",
    "addr:postcode":"2000",
    "addr:street":"Lange Lobroekstraat;Groot Antwerpen",
    "iso:country":"BE",
    "sg:address":"Lange Lobroekstraat 142",
    "sg:city":"Antwerpen (groot)",
    "sg:orig_category":"D\u00e9taillants en pi\u00e8ces and accessoires de voitures",
    "sg:phone":"+32 3 231 06 34",
    "sg:postcode":"2000",
    "sg:province":"Antwerpen",
    "wof:name":"Vanderjonkheid",
    "wof:placetype":"venue"
},
  "geometry": {"coordinates":[4.4305028915,51.2307281494],"type":"Point"}
}