{
  "type": "Feature",
  "properties": {
    "addr:full":"Rue Trieu-\u00c0-vall\u00c9e 37 La Louviere Hainaut 7110",
    "addr:housenumber":"37",
    "addr:postcode":"7110",
    "addr:street":"Rue Trieu-A\u0300-Valle\u0301E",
    "iso:country":"BE",
    "sg:address":"Rue Trieu-\u00c0-vall\u00c9e 37",
    "sg:city":"La Louviere",
    "sg:classifiers":[
        {
            "category":"Cafe",
            "type":"Food & Drink"
        }
    ],
    "sg:phone":"+32 64 28 46 18",
    "sg:postcode":"7110",
    "sg:province":"Hainaut",
    "sg:tags":[
        "caf\u00e9s"
    ],
    "wof:name":"Didier Janssens",
    "wof:placetype":"venue"
},
  "geometry": {"coordinates":[4.1505050659,50.4826698303],"type":"Point"}
}