{
  "type": "Feature",
  "properties": {
    "iso:country":"BE",
    "sg:address":"Stationsstraat 73",
    "sg:city":"Leopoldsburg",
    "sg:orig_category":"Bijouteries and horlogeries. Opticiens",
    "sg:phone":"+32 11 34 13 35",
    "sg:postcode":"3970",
    "sg:province":"Limburg",
    "wof:name":"Guido Donne",
    "wof:placetype":"venue"
},
  "geometry": {"coordinates":[5.2591309547,51.1177330017],"type":"Point"}
}