{
  "type": "Feature",
  "properties": {
    "iso:country":"BE",
    "sg:address":"Elzenstraat 23",
    "sg:city":"Hulshout (westmeerbeek)",
    "sg:classifiers":[
        {
            "category":"Building & Trades",
            "subcategory":"Construction",
            "type":"Services"
        }
    ],
    "sg:phone":"+32 16 68 04 57",
    "sg:postcode":"2235",
    "sg:province":"Antwerpen",
    "sg:tags":[
        "installation",
        "-",
        "central",
        "heating"
    ],
    "wof:name":"De Meyer G",
    "wof:placetype":"venue"
},
  "geometry": {"coordinates":[4.8299880028,51.0563392639],"type":"Point"}
}