{
  "type": "Feature",
  "properties": {
    "addr:full":"Iepersestraat 93 Kortrijk West-Vlaanderen 8500",
    "addr:housenumber":"93",
    "addr:postcode":"8500",
    "addr:street":"Iepersestraat",
    "iso:country":"BE",
    "sg:address":"Iepersestraat 93",
    "sg:city":"Kortrijk",
    "sg:orig_category":"Quincailleries",
    "sg:phone":"+32 56 37 02 75",
    "sg:postcode":"8500",
    "sg:province":"West-Vlaanderen",
    "wof:name":"Hobroco",
    "wof:placetype":"venue"
},
  "geometry": {"coordinates":[3.264425993,50.8428459167],"type":"Point"}
}