{
  "type": "Feature",
  "properties": {
    "iso:country":"BE",
    "sg:address":"Doorniksesteenweg 135",
    "sg:city":"Kortrijk",
    "sg:orig_category":"Advocaten and juridische adviseurs",
    "sg:phone":"+32 56 21 39 00",
    "sg:postcode":"8500",
    "sg:province":"West-Vlaanderen",
    "wof:name":"G. Duchi",
    "wof:placetype":"venue"
},
  "geometry": {"coordinates":[3.2696959972,50.8184776306],"type":"Point"}
}