{
  "type": "Feature",
  "properties": {
    "iso:country":"BE",
    "sg:address":"Rue De Berloz 47",
    "sg:city":"Waremme",
    "sg:classifiers":[
        {
            "category":"Insurance",
            "subcategory":"Insurance Agent",
            "type":"Services"
        }
    ],
    "sg:phone":"+32 19 32 44 86",
    "sg:postcode":"4300",
    "sg:province":"Li\u00e8ge",
    "sg:tags":[
        "verzekeringsmakelaars",
        "expert"
    ],
    "wof:name":"B.m.d.",
    "wof:placetype":"venue"
},
  "geometry": {"coordinates":[5.2388138771,50.6943626404],"type":"Point"}
}