{
  "type": "Feature",
  "properties": {
    "iso:country":"BE",
    "sg:address":"Rue Roelandts 21",
    "sg:city":"Bruxelles (schaerbeek)",
    "sg:classifiers":[
        {
            "category":"Building & Trades",
            "subcategory":"Construction",
            "type":"Services"
        }
    ],
    "sg:phone":"+32 2 241 80 17",
    "sg:postcode":"1030",
    "sg:province":"Bruxelles-Capitale",
    "sg:tags":[
        "glazier"
    ],
    "wof:name":"Dutilleul",
    "wof:placetype":"venue"
},
  "geometry": {"coordinates":[4.3769488335,50.8571166992],"type":"Point"}
}