{
  "type": "Feature",
  "properties": {
    "iso:country":"BE",
    "sg:address":"Rue Eug\u00e8ne Defraire 71",
    "sg:city":"Viroinval (treignes)",
    "sg:classifiers":[
        {
            "category":"Professional",
            "subcategory":"Testing Lab",
            "type":"Services"
        }
    ],
    "sg:phone":"+32 60 39 05 95",
    "sg:postcode":"5670",
    "sg:province":"Namur",
    "sg:tags":[
        "chemist"
    ],
    "wof:name":"Pharmacie De Treignes",
    "wof:placetype":"venue"
},
  "geometry": {"coordinates":[4.6706571579,50.0930213928],"type":"Point"}
}