{
  "type": "Feature",
  "properties": {
    "iso:country":"BE",
    "sg:address":"Rue De Dorlodot 14",
    "sg:city":"Floreffe",
    "sg:orig_category":"Gespecialiseerde residenti\u00eble bouw Woningbouw",
    "sg:phone":"+32 81 44 47 73",
    "sg:postcode":"5150",
    "sg:province":"Namur",
    "wof:name":"Patrick Lacroix",
    "wof:placetype":"venue"
},
  "geometry": {"coordinates":[4.7662158012,50.4520263672],"type":"Point"}
}