{
  "type": "Feature",
  "properties": {
    "iso:country":"BE",
    "sg:address":"Appelboom 4c",
    "sg:city":"Maldegem (adegem)",
    "sg:classifiers":[
        {
            "category":"Food & Beverages",
            "subcategory":"Meat & Fish",
            "type":"Retail Goods"
        }
    ],
    "sg:phone":"+32 9 377 55 94",
    "sg:postcode":"9991",
    "sg:province":"Oost-Vlaanderen",
    "sg:tags":[
        "-",
        "livestock"
    ],
    "wof:name":"Blomme C",
    "wof:placetype":"venue"
},
  "geometry": {"coordinates":[3.5054450035,51.17760849],"type":"Point"}
}