{
  "type": "Feature",
  "properties": {
    "iso:country":"BE",
    "sg:address":"Rue Baudouin Iv 14",
    "sg:city":"Braine-le-comte",
    "sg:orig_category":"Mat\u00e9riel m\u00e9dical and orthop\u00e9dique and proth\u00e8ses Fab",
    "sg:phone":"+32 67 55 33 52",
    "sg:postcode":"7090",
    "sg:province":"Hainaut",
    "wof:name":"Lucien Decamps",
    "wof:placetype":"venue"
},
  "geometry": {"coordinates":[4.1388721466,50.6088409424],"type":"Point"}
}