{
  "type": "Feature",
  "properties": {
    "iso:country":"BE",
    "sg:address":"Place Fran\u00c7ois Faniel 1",
    "sg:city":"Wanze",
    "sg:classifiers":[
        {
            "category":"Shopping",
            "subcategory":"Clothing, Apparel, & Fashions",
            "type":"Retail Goods"
        }
    ],
    "sg:phone":"+32 85 23 28 59",
    "sg:postcode":"4520",
    "sg:province":"Li\u00e8ge",
    "sg:tags":[
        "lingerie",
        "sous-v\u00eatements"
    ],
    "wof:name":"La Pince \u00c0 Linge",
    "wof:placetype":"venue"
},
  "geometry": {"coordinates":[5.2149472237,50.5364685059],"type":"Point"}
}