{
  "type": "Feature",
  "properties": {
    "iso:country":"BE",
    "sg:address":"Toekomstlaan 16",
    "sg:city":"Schoten",
    "sg:orig_category":"Quincailleries. Location de machines-outils and de mat\u00e9riel de bricolage",
    "sg:phone":"+32 3 645 87 47",
    "sg:postcode":"2900",
    "sg:province":"Antwerpen",
    "wof:name":"Proclima",
    "wof:placetype":"venue"
},
  "geometry": {"coordinates":[4.4569029808,51.2416648865],"type":"Point"}
}