{
  "type": "Feature",
  "properties": {
    "addr:full":"Place Verte 19 Soignies Hainaut 7060",
    "addr:housenumber":"19",
    "addr:postcode":"7060",
    "addr:street":"Place Verte",
    "iso:country":"BE",
    "sg:address":"Place Verte 19",
    "sg:city":"Soignies",
    "sg:classifiers":[
        {
            "category":"Bars & Pubs",
            "type":"Food & Drink"
        }
    ],
    "sg:phone":"+32 67 33 50 19",
    "sg:postcode":"7060",
    "sg:province":"Hainaut",
    "sg:tags":[
        "tavern"
    ],
    "wof:name":"Geweco Sprl",
    "wof:placetype":"venue"
},
  "geometry": {"coordinates":[4.0675020218,50.578868866],"type":"Point"}
}