{
  "type": "Feature",
  "properties": {
    "iso:country":"BE",
    "sg:address":"Heuvelstraat 57",
    "sg:city":"Boechout",
    "sg:classifiers":[
        {
            "category":"Manufacturing",
            "subcategory":"Printing",
            "type":"Manufacturing & Wholesale Goods"
        }
    ],
    "sg:phone":"+32 3 454 19 60",
    "sg:postcode":"2530",
    "sg:province":"Antwerpen",
    "sg:tags":[
        "textile",
        "-"
    ],
    "wof:name":"Qua-3 Bvba",
    "wof:placetype":"venue"
},
  "geometry": {"coordinates":[4.494284153,51.1631088257],"type":"Point"}
}