{
  "type": "Feature",
  "properties": {
    "iso:country":"BE",
    "sg:address":"Stuifzandstraat 45",
    "sg:city":"Overpelt",
    "sg:classifiers":[
        {
            "category":"Wholesale",
            "subcategory":"Chemicals & Plastics",
            "type":"Manufacturing & Wholesale Goods"
        }
    ],
    "sg:phone":"+32 11 64 04 21",
    "sg:postcode":"3900",
    "sg:province":"Limburg",
    "sg:tags":[
        "article",
        "articles",
        "hollow",
        "blown"
    ],
    "wof:name":"Profilex Plastic Industrie Nv",
    "wof:placetype":"venue"
},
  "geometry": {"coordinates":[5.3898458481,51.2227172852],"type":"Point"}
}