{
  "type": "Feature",
  "properties": {
    "addr:full":"Oude Veurnevaart 14 Nieuwpoort West-Vlaanderen 8620",
    "addr:housenumber":"14",
    "addr:postcode":"8620",
    "addr:street":"Oude Veurnevaart",
    "iso:country":"BE",
    "sg:address":"Oude Veurnevaart 14",
    "sg:city":"Nieuwpoort",
    "sg:classifiers":[
        {
            "category":"Professional",
            "subcategory":"Business Services",
            "type":"Services"
        }
    ],
    "sg:phone":"+32 58 23 11 56",
    "sg:postcode":"8620",
    "sg:province":"West-Vlaanderen",
    "sg:tags":[
        "aux",
        "diver",
        "entreprises"
    ],
    "wof:name":"Bureau Adrenaline",
    "wof:placetype":"venue"
},
  "geometry": {"coordinates":[2.7492160797,51.1266899109],"type":"Point"}
}