{
  "type": "Feature",
  "properties": {
    "addr:full":"Koningsbaan 81 Nijlen Antwerpen 2560",
    "addr:housenumber":"81",
    "addr:postcode":"2560",
    "addr:street":"Koningsbaan",
    "iso:country":"BE",
    "sg:address":"Koningsbaan 81",
    "sg:city":"Nijlen",
    "sg:classifiers":[
        {
            "category":"Bakery",
            "type":"Food & Drink"
        }
    ],
    "sg:phone":"+32 3 481 87 07",
    "sg:postcode":"2560",
    "sg:province":"Antwerpen",
    "sg:tags":[
        "fresh",
        "pastry",
        "bread"
    ],
    "wof:name":"Bakkerij Dockx B.v.b.a.",
    "wof:placetype":"venue"
},
  "geometry": {"coordinates":[4.6402921677,51.1604499817],"type":"Point"}
}