{
  "type": "Feature",
  "properties": {
    "addr:full":"Beukenhof 31 Sint-laureins Oost-Vlaanderen 9980",
    "addr:housenumber":"31",
    "addr:postcode":"9980",
    "addr:street":"Beukenhof",
    "iso:country":"BE",
    "sg:address":"Beukenhof 31",
    "sg:city":"Sint-laureins",
    "sg:orig_category":"Studios photographiques",
    "sg:phone":"+32 9 379 93 61",
    "sg:postcode":"9980",
    "sg:province":"Oost-Vlaanderen",
    "wof:name":"Eddy Trillet",
    "wof:placetype":"venue"
},
  "geometry": {"coordinates":[3.5201311111,51.2406692505],"type":"Point"}
}