{
  "type": "Feature",
  "properties": {
    "iso:country":"BE",
    "sg:address":"Rue De Neufch\u00c2teau 3",
    "sg:city":"Habay-la-neuve",
    "sg:orig_category":"Herstellingen motorfietsen Motorfietsen Tuinbenodigdheden",
    "sg:phone":"+32 63 42 21 43",
    "sg:postcode":"6720",
    "sg:province":"Luxembourg",
    "wof:name":"Poncin",
    "wof:placetype":"venue"
},
  "geometry": {"coordinates":[5.6420750618,49.7280769348],"type":"Point"}
}