{
  "type": "Feature",
  "properties": {
    "iso:country":"BE",
    "sg:address":"Bisschopslaan 71",
    "sg:city":"Beerse",
    "sg:classifiers":[
        {
            "category":"Home & Garden",
            "subcategory":"Building Materials",
            "type":"Retail Goods"
        }
    ],
    "sg:phone":"+32 3 226 34 56",
    "sg:postcode":"2340",
    "sg:province":"Antwerpen",
    "sg:tags":[
        "water",
        "heater"
    ],
    "wof:name":"Aa-algemene Ontstoppingsdienst",
    "wof:placetype":"venue"
},
  "geometry": {"coordinates":[4.8563680649,51.3107566833],"type":"Point"}
}