{
  "type": "Feature",
  "properties": {
    "iso:country":"BE",
    "sg:address":"Alsemweg 13",
    "sg:city":"Nevele",
    "sg:orig_category":"Eleveurs de bovins",
    "sg:phone":"+32 9 371 62 41",
    "sg:postcode":"9850",
    "sg:province":"Oost-Vlaanderen",
    "wof:name":"Astere Heye",
    "wof:placetype":"venue"
},
  "geometry": {"coordinates":[3.5980660915,51.0722465515],"type":"Point"}
}