{
  "type": "Feature",
  "properties": {
    "addr:full":"Burg. Jozef Eerdekensstr 26 Leuven Vlaams-Brabant 3001",
    "addr:housenumber":"26",
    "addr:postcode":"3001",
    "addr:street":"Burg.;Eerdekensstr",
    "iso:country":"BE",
    "sg:address":"Burg. Jozef Eerdekensstr 26",
    "sg:city":"Leuven",
    "sg:orig_category":"Diverse opleidingen and onderwijs",
    "sg:phone":"+32 16 23 81 23",
    "sg:postcode":"3001",
    "sg:province":"Vlaams-Brabant",
    "wof:name":"Eddy Schoeters",
    "wof:placetype":"venue"
},
  "geometry": {"coordinates":[4.6959400177,50.8633499146],"type":"Point"}
}