{
  "type": "Feature",
  "properties": {
    "addr:full":"Nijverheidsstraat 46a Westerlo Antwerpen 2260",
    "addr:housenumber":"46a",
    "addr:postcode":"2260",
    "addr:street":"Nijverheidsstraat",
    "iso:country":"BE",
    "sg:address":"Nijverheidsstraat 46a",
    "sg:city":"Westerlo",
    "sg:classifiers":[
        {
            "category":"Government",
            "subcategory":"Fire Station",
            "type":"Public Place"
        }
    ],
    "sg:phone":"+32 14 28 64 90",
    "sg:postcode":"2260",
    "sg:province":"Antwerpen",
    "sg:tags":[
        "insulation",
        "element"
    ],
    "wof:name":"Bovisol Nv",
    "wof:placetype":"venue"
},
  "geometry": {"coordinates":[4.898004055,51.143737793],"type":"Point"}
}