{
  "type": "Feature",
  "properties": {
    "addr:full":"Briscol 12 Erez\u00e9e Luxembourg 6997",
    "addr:housenumber":"12",
    "addr:postcode":"6997",
    "addr:street":"Briscol",
    "iso:country":"BE",
    "sg:address":"Briscol 12",
    "sg:city":"Erez\u00e9e",
    "sg:classifiers":[
        {
            "category":"Education",
            "subcategory":"School",
            "type":"Public Place"
        }
    ],
    "sg:phone":"+32 86 34 94 88",
    "sg:postcode":"6997",
    "sg:province":"Luxembourg",
    "sg:tags":[
        "secondary"
    ],
    "wof:name":"E.p.s.i. Val D'aisne-internat",
    "wof:placetype":"venue"
},
  "geometry": {"coordinates":[5.6004858017,50.2950706482],"type":"Point"}
}