{
  "type": "Feature",
  "properties": {
    "addr:full":"Bahnhofstrasse 3 Sankt Vith Li\u00e8ge 4780",
    "addr:housenumber":"3",
    "addr:postcode":"4780",
    "addr:street":"Bahnhofstrasse",
    "iso:country":"BE",
    "sg:address":"Bahnhofstrasse 3",
    "sg:city":"Sankt Vith",
    "sg:classifiers":[
        {
            "category":"Professional",
            "subcategory":"Lawyer & Legal Services",
            "type":"Services"
        }
    ],
    "sg:phone":"+32 80 22 80 42",
    "sg:postcode":"4780",
    "sg:province":"Li\u00e8ge",
    "sg:tags":[
        "notary"
    ],
    "wof:name":"Huppertz E",
    "wof:placetype":"venue"
},
  "geometry": {"coordinates":[6.1268482208,50.2821388245],"type":"Point"}
}