{
  "type": "Feature",
  "properties": {
    "addr:full":"Marie-jos\u00e9plein 5 Oostende West-Vlaanderen 8400",
    "addr:housenumber":"5",
    "addr:postcode":"8400",
    "addr:street":"Marie-Jose\u0301Plein",
    "iso:country":"BE",
    "sg:address":"Marie-jos\u00e9plein 5",
    "sg:city":"Oostende",
    "sg:classifiers":[
        {
            "category":"Professional",
            "subcategory":"Testing Lab",
            "type":"Services"
        }
    ],
    "sg:phone":"+32 59 70 11 22",
    "sg:postcode":"8400",
    "sg:province":"West-Vlaanderen",
    "sg:tags":[
        "chemist"
    ],
    "wof:name":"Dewulf A",
    "wof:placetype":"venue"
},
  "geometry": {"coordinates":[2.9136509895,51.2308654785],"type":"Point"}
}