{
  "type": "Feature",
  "properties": {
    "iso:country":"BE",
    "sg:address":"Kleine Hellekensstraat 48a",
    "sg:city":"Zonhoven",
    "sg:classifiers":[
        {
            "category":"Professional",
            "subcategory":"Art Services",
            "type":"Services"
        }
    ],
    "sg:phone":"+32 11 81 82 32",
    "sg:postcode":"3520",
    "sg:province":"Limburg",
    "sg:tags":[
        "interior",
        "designer"
    ],
    "wof:name":"Langendries/nivelle",
    "wof:placetype":"venue"
},
  "geometry": {"coordinates":[5.3614449501,50.9823417664],"type":"Point"}
}