{
  "type": "Feature",
  "properties": {
    "addr:full":"Rue L. Mar\u00c9chal 99ba Oreye Li\u00e8ge 4360",
    "addr:housenumber":"99ba",
    "addr:postcode":"4360",
    "addr:street":"Rue L. Mare\u0301Chal",
    "iso:country":"BE",
    "sg:address":"Rue L. Mar\u00c9chal 99ba",
    "sg:city":"Oreye",
    "sg:orig_category":"Hout and afgeleiden Gh IJzerwaren, bouw- and verfmaterialen Installatie van metalen schrijnwerk",
    "sg:phone":"+32 19 67 71 86",
    "sg:postcode":"4360",
    "sg:province":"Li\u00e8ge",
    "wof:name":"Anciens Jos Renard",
    "wof:placetype":"venue"
},
  "geometry": {"coordinates":[5.3350710869,50.7027587891],"type":"Point"}
}