{
  "type": "Feature",
  "properties": {
    "iso:country":"BE",
    "sg:address":"Rue De La Poste 156",
    "sg:city":"Schaarbeek/schaerbeek",
    "sg:orig_category":"Action sociale avec h\u00e9bergement",
    "sg:phone":"+32 2 218 76 88",
    "sg:postcode":"1030",
    "sg:province":"Bruxelles-Capitale",
    "wof:name":"Serv. Soc. Quartiers 1030",
    "wof:placetype":"venue"
},
  "geometry": {"coordinates":[4.3688921928,50.8609008789],"type":"Point"}
}