{
  "type": "Feature",
  "properties": {
    "addr:full":"Chauss\u00e9e De Haecht 133 Bruxelles (schaerbeek) Bruxelles-Capitale 1030",
    "addr:housenumber":"133",
    "addr:postcode":"1030",
    "addr:street":"Chausse\u0301E De Haecht",
    "iso:country":"BE",
    "sg:address":"Chauss\u00e9e De Haecht 133",
    "sg:city":"Bruxelles (schaerbeek)",
    "sg:classifiers":[
        {
            "category":"Retail",
            "subcategory":"Event Space",
            "type":"Services"
        }
    ],
    "sg:phone":"+32 2 219 99 74",
    "sg:postcode":"1030",
    "sg:province":"Bruxelles-Capitale",
    "sg:tags":[
        "rental",
        "-",
        "hall"
    ],
    "wof:name":"Nostalgie",
    "wof:placetype":"venue"
},
  "geometry": {"coordinates":[4.3701481819,50.8587150574],"type":"Point"}
}