{
  "type": "Feature",
  "properties": {
    "addr:full":"Turnhoutsebaan 406 Wijnegem Antwerpen 2110",
    "addr:housenumber":"406",
    "addr:postcode":"2110",
    "addr:street":"Turnhoutsebaan",
    "iso:country":"BE",
    "sg:address":"Turnhoutsebaan 406",
    "sg:city":"Wijnegem",
    "sg:classifiers":[
        {
            "category":"Shopping",
            "subcategory":"Gifts & Souvenirs",
            "type":"Retail Goods"
        }
    ],
    "sg:phone":"+32 3 353 62 59",
    "sg:postcode":"2110",
    "sg:province":"Antwerpen",
    "sg:tags":[
        "geschenken"
    ],
    "wof:name":"Naald & Draad",
    "wof:placetype":"venue"
},
  "geometry": {"coordinates":[4.5224108696,51.2276229858],"type":"Point"}
}