{
  "type": "Feature",
  "properties": {
    "addr:full":"Rue Du Fr\u00e8re-m\u00e9rantius 10 Virton (ruette) Luxembourg 6760",
    "addr:housenumber":"10",
    "addr:postcode":"6760",
    "addr:street":"Rue Du Fre\u0300Re-Me\u0301Rantius;Ruette Luxembourg",
    "iso:country":"BE",
    "sg:address":"Rue Du Fr\u00e8re-m\u00e9rantius 10",
    "sg:city":"Virton (ruette)",
    "sg:classifiers":[
        {
            "category":"Building & Trades",
            "subcategory":"Landscaping Services",
            "type":"Services"
        }
    ],
    "sg:phone":"+32 63 67 73 36",
    "sg:postcode":"6760",
    "sg:province":"Luxembourg",
    "sg:tags":[
        "nurseryman"
    ],
    "wof:name":"Gennebois Sprl",
    "wof:placetype":"venue"
},
  "geometry": {"coordinates":[5.5941519737,49.5367012024],"type":"Point"}
}