{
  "type": "Feature",
  "properties": {
    "iso:country":"BE",
    "sg:address":"Kwadestraat 19",
    "sg:city":"Roeselare",
    "sg:orig_category":"Sportclubs",
    "sg:phone":"+32 51 22 10 77",
    "sg:postcode":"8800",
    "sg:province":"West-Vlaanderen",
    "wof:name":"B.c. Volharding",
    "wof:placetype":"venue"
},
  "geometry": {"coordinates":[3.159528017,50.9305114746],"type":"Point"}
}