{
  "type": "Feature",
  "properties": {
    "addr:full":"Hamiltonpark 20 Brugge West-Vlaanderen 8000",
    "addr:housenumber":"20",
    "addr:postcode":"8000",
    "addr:street":"Hamiltonpark",
    "iso:country":"BE",
    "sg:address":"Hamiltonpark 20",
    "sg:city":"Brugge",
    "sg:orig_category":"Rev\u00eatements de sols and murs",
    "sg:phone":"+32 50 32 03 53",
    "sg:postcode":"8000",
    "sg:province":"West-Vlaanderen",
    "wof:name":"Tebelo",
    "wof:placetype":"venue"
},
  "geometry": {"coordinates":[3.2039470673,51.2130508423],"type":"Point"}
}