{
  "type": "Feature",
  "properties": {
    "addr:full":"Rue De Gourdinne 39 Walcourt (thy-le-ch\u00e2teau) Namur 5651",
    "addr:housenumber":"39",
    "addr:postcode":"5651",
    "addr:street":"Rue De Gourdinne",
    "iso:country":"BE",
    "sg:address":"Rue De Gourdinne 39",
    "sg:city":"Walcourt (thy-le-ch\u00e2teau)",
    "sg:classifiers":[
        {
            "category":"Education",
            "subcategory":"Dance Studio",
            "type":"Public Place"
        }
    ],
    "sg:phone":"+32 71 61 22 66",
    "sg:postcode":"5651",
    "sg:province":"Namur",
    "sg:tags":[
        "school",
        "dancing"
    ],
    "wof:name":"Ligue De La Danse",
    "wof:placetype":"venue"
},
  "geometry": {"coordinates":[4.4262080193,50.2824401855],"type":"Point"}
}