{
  "type": "Feature",
  "properties": {
    "addr:full":"Rue Du Piroy 110 Namur Namur 5020",
    "addr:housenumber":"110",
    "addr:postcode":"5020",
    "addr:street":"Rue Du Piroy",
    "iso:country":"BE",
    "sg:address":"Rue Du Piroy 110",
    "sg:city":"Namur",
    "sg:orig_category":"Installatie van houten of kunststof schrijnwerk",
    "sg:phone":"+32 81 44 58 80",
    "sg:postcode":"5020",
    "sg:province":"Namur",
    "wof:name":"Alain Lambrette",
    "wof:placetype":"venue"
},
  "geometry": {"coordinates":[4.7860841751,50.4181518555],"type":"Point"}
}