{
  "type": "Feature",
  "properties": {
    "iso:country":"BE",
    "sg:address":"Belven 52",
    "sg:city":"Raeren",
    "sg:classifiers":[
        {
            "category":"Professional",
            "subcategory":"Computer Services",
            "type":"Services"
        }
    ],
    "sg:phone":"+32 87 85 01 81",
    "sg:postcode":"4730",
    "sg:province":"Li\u00e8ge",
    "sg:tags":[
        "-",
        "processing",
        "data"
    ],
    "wof:name":"Tom's Multitech",
    "wof:placetype":"venue"
},
  "geometry": {"coordinates":[6.0838627815,50.6708030701],"type":"Point"}
}