{
  "type": "Feature",
  "properties": {
    "iso:country":"BE",
    "sg:address":"Rue De Wautier 16",
    "sg:city":"Brussel",
    "sg:orig_category":"Moteurs, transformateurs and groupes \u00e9lectrog\u00e8nes Fab",
    "sg:phone":"+32 2 426 16 96",
    "sg:postcode":"1020",
    "sg:province":"Bruxelles-Capitale",
    "wof:name":"Atelier Urbini & Co",
    "wof:placetype":"venue"
},
  "geometry": {"coordinates":[4.3574571609,50.8736610413],"type":"Point"}
}