{
  "type": "Feature",
  "properties": {
    "addr:full":"Zelle 1ba Herenthout Antwerpen 2270",
    "addr:housenumber":"1ba",
    "addr:postcode":"2270",
    "addr:street":"Zelle",
    "iso:country":"BE",
    "sg:address":"Zelle 1ba",
    "sg:city":"Herenthout",
    "sg:orig_category":"Rundveehouders",
    "sg:phone":"+32 14 51 14 32",
    "sg:postcode":"2270",
    "sg:province":"Antwerpen",
    "wof:name":"Rudy Vrins",
    "wof:placetype":"venue"
},
  "geometry": {"coordinates":[4.7697591782,51.1563262939],"type":"Point"}
}