{
  "type": "Feature",
  "properties": {
    "addr:full":"Nieuwe Steenweg 23bc Zuienkerke West-Vlaanderen 8377",
    "addr:housenumber":"23bc",
    "addr:postcode":"8377",
    "addr:street":"Nieuwe Steenweg",
    "iso:country":"BE",
    "sg:address":"Nieuwe Steenweg 23bc",
    "sg:city":"Zuienkerke",
    "sg:orig_category":"V\u00e9t\u00e9rinaires",
    "sg:phone":"+32 50 41 56 56",
    "sg:postcode":"8377",
    "sg:province":"West-Vlaanderen",
    "wof:name":"Koenraad Dehaemers",
    "wof:placetype":"venue"
},
  "geometry": {"coordinates":[3.1595580578,51.2664756775],"type":"Point"}
}