{
  "type": "Feature",
  "properties": {
    "addr:full":"Georges Simpsonstraat 24 Ganshoren/ganshoren Bruxelles-Capitale 1083",
    "addr:housenumber":"24",
    "addr:postcode":"1083",
    "addr:street":"Georges Simpsonstraat",
    "iso:country":"BE",
    "sg:address":"Georges Simpsonstraat 24",
    "sg:city":"Ganshoren/ganshoren",
    "sg:orig_category":"Woningbouw",
    "sg:phone":"+32 2 426 74 19",
    "sg:postcode":"1083",
    "sg:province":"Bruxelles-Capitale",
    "wof:name":"Habitat New",
    "wof:placetype":"venue"
},
  "geometry": {"coordinates":[4.3190498352,50.8703689575],"type":"Point"}
}