{
  "type": "Feature",
  "properties": {
    "addr:full":"Korhoenstraat 2 Gent Oost-Vlaanderen 9000",
    "addr:housenumber":"2",
    "addr:postcode":"9000",
    "addr:street":"Korhoenstraat;Oost-Vlaanderen",
    "iso:country":"BE",
    "sg:address":"Korhoenstraat 2",
    "sg:city":"Gent",
    "sg:orig_category":"Geluidsopnames",
    "sg:phone":"+32 9 236 44 11",
    "sg:postcode":"9000",
    "sg:province":"Oost-Vlaanderen",
    "wof:name":"Studio Van Roy Steven",
    "wof:placetype":"venue"
},
  "geometry": {"coordinates":[3.6996369362,51.0556907654],"type":"Point"}
}