{
  "type": "Feature",
  "properties": {
    "addr:full":"Hubert Fr\u00e8re-orbanlaan 159 Gent Oost-Vlaanderen 9000",
    "addr:housenumber":"159",
    "addr:postcode":"9000",
    "addr:street":"Hubert Fre\u0300Re-Orbanlaan;Oost-Vlaanderen",
    "iso:country":"BE",
    "sg:address":"Hubert Fr\u00e8re-orbanlaan 159",
    "sg:city":"Gent",
    "sg:classifiers":[
        {
            "category":"Retail",
            "subcategory":"Event Space",
            "type":"Services"
        }
    ],
    "sg:phone":"+32 9 224 46 40",
    "sg:postcode":"9000",
    "sg:province":"Oost-Vlaanderen",
    "sg:tags":[
        "organisation"
    ],
    "wof:name":"Courtisane Vzw",
    "wof:placetype":"venue"
},
  "geometry": {"coordinates":[3.7345209122,51.0436859131],"type":"Point"}
}