{
  "type": "Feature",
  "properties": {
    "iso:country":"BE",
    "sg:address":"Markt 9",
    "sg:city":"Ichtegem",
    "sg:classifiers":[
        {
            "category":"Bars & Pubs",
            "type":"Food & Drink"
        }
    ],
    "sg:phone":"+32 51 58 18 47",
    "sg:postcode":"8480",
    "sg:province":"West-Vlaanderen",
    "wof:name":"Hert (de)",
    "wof:placetype":"venue"
},
  "geometry": {"coordinates":[3.0092670918,51.0925941467],"type":"Point"}
}