{
  "type": "Feature",
  "properties": {
    "iso:country":"BE",
    "sg:address":"Atealaan 4c",
    "sg:city":"Herentals",
    "sg:classifiers":[
        {
            "category":"Wholesale",
            "subcategory":"Medical Equipment & Supplies",
            "type":"Manufacturing & Wholesale Goods"
        }
    ],
    "sg:phone":"+32 14 25 85 90",
    "sg:postcode":"2200",
    "sg:province":"Antwerpen",
    "sg:tags":[
        "instrument",
        "apparatus"
    ],
    "wof:name":"Iba Sterelisatie & Ionisatie Nv",
    "wof:placetype":"venue"
},
  "geometry": {"coordinates":[4.7880501747,51.1609992981],"type":"Point"}
}