{
  "type": "Feature",
  "properties": {
    "addr:full":"Route De Marche 8 Tinlot Li\u00e8ge 4557",
    "addr:housenumber":"8",
    "addr:postcode":"4557",
    "addr:street":"Route De Marche",
    "iso:country":"BE",
    "sg:address":"Route De Marche 8",
    "sg:city":"Tinlot",
    "sg:orig_category":"Tuinbenodigdheden",
    "sg:phone":"+32 85 51 25 53",
    "sg:postcode":"4557",
    "sg:province":"Li\u00e8ge",
    "wof:name":"Champagne M",
    "wof:placetype":"venue"
},
  "geometry": {"coordinates":[5.3833909035,50.4866256714],"type":"Point"}
}