{
  "type": "Feature",
  "properties": {
    "addr:full":"Koevliet 5-6 Zele Oost-Vlaanderen 9240",
    "addr:housenumber":"5-6",
    "addr:postcode":"9240",
    "addr:street":"Koevliet",
    "iso:country":"BE",
    "sg:address":"Koevliet 5-6",
    "sg:city":"Zele",
    "sg:orig_category":"Cliniques and h\u00f4pitaux",
    "sg:phone":"+32 52 45 64 00",
    "sg:postcode":"9240",
    "sg:province":"Oost-Vlaanderen",
    "wof:name":"A.z. Sint-blasius",
    "wof:placetype":"venue"
},
  "geometry": {"coordinates":[4.0270390511,51.0652427673],"type":"Point"}
}