{
  "type": "Feature",
  "properties": {
    "addr:full":"Rue Haute 56 Herve Li\u00e8ge 4650",
    "addr:housenumber":"56",
    "addr:postcode":"4650",
    "addr:street":"Rue Haute",
    "iso:country":"BE",
    "sg:address":"Rue Haute 56",
    "sg:city":"Herve",
    "sg:orig_category":"Enseignement maternel and primaire",
    "sg:phone":"+32 87 67 40 81",
    "sg:postcode":"4650",
    "sg:province":"Li\u00e8ge",
    "wof:name":"Ecole Primaire Libre",
    "wof:placetype":"venue"
},
  "geometry": {"coordinates":[5.7960290909,50.6430435181],"type":"Point"}
}