{
  "type": "Feature",
  "properties": {
    "addr:full":"Rue De L'yser 5 Aywaille Li\u00e8ge 4920",
    "addr:housenumber":"5",
    "addr:postcode":"4920",
    "addr:street":"Rue De L'Yser",
    "iso:country":"BE",
    "sg:address":"Rue De L'yser 5",
    "sg:city":"Aywaille",
    "sg:orig_category":"Bloemen and planten",
    "sg:phone":"+32 4 384 40 38",
    "sg:postcode":"4920",
    "sg:province":"Li\u00e8ge",
    "wof:name":"Fleurs Vanschoor",
    "wof:placetype":"venue"
},
  "geometry": {"coordinates":[5.6720809937,50.4748687744],"type":"Point"}
}