{
  "type": "Feature",
  "properties": {
    "iso:country":"BE",
    "sg:address":"Chauss\u00e9e De Waterloo 571",
    "sg:city":"Bruxelles (ixelles)",
    "sg:classifiers":[
        {
            "category":"Shopping",
            "subcategory":"Clothing, Apparel, & Fashions",
            "type":"Retail Goods"
        }
    ],
    "sg:phone":"+32 2 343 26 68",
    "sg:postcode":"1050",
    "sg:province":"Bruxelles-Capitale",
    "sg:tags":[
        "boutique"
    ],
    "wof:name":"Casse Pieds",
    "wof:placetype":"venue"
},
  "geometry": {"coordinates":[4.3622121811,50.8187522888],"type":"Point"}
}