{
  "type": "Feature",
  "properties": {
    "iso:country":"BE",
    "sg:address":"Grootzand 108",
    "sg:city":"Dendermonde (grembergen)",
    "sg:classifiers":[
        {
            "category":"Shopping",
            "subcategory":"Gifts & Souvenirs",
            "type":"Retail Goods"
        }
    ],
    "sg:phone":"+32 52 20 13 77",
    "sg:postcode":"9200",
    "sg:province":"Oost-Vlaanderen",
    "sg:tags":[
        "-"
    ],
    "wof:name":"Kadorama",
    "wof:placetype":"venue"
},
  "geometry": {"coordinates":[4.1059207916,51.0445289612],"type":"Point"}
}