{
  "type": "Feature",
  "properties": {
    "iso:country":"BE",
    "sg:address":"Kortemarkstraat 209",
    "sg:city":"Torhout",
    "sg:orig_category":"Eleveurs and marchands de porcs",
    "sg:phone":"+32 50 21 29 76",
    "sg:postcode":"8820",
    "sg:province":"West-Vlaanderen",
    "wof:name":"Cerdo",
    "wof:placetype":"venue"
},
  "geometry": {"coordinates":[3.0756280422,51.0516738892],"type":"Point"}
}