{
  "type": "Feature",
  "properties": {
    "addr:full":"Smidsestraat 87 Dendermonde Oost-Vlaanderen 9200",
    "addr:housenumber":"87",
    "addr:postcode":"9200",
    "addr:street":"Smidsestraat;Oost-Vlaanderen",
    "iso:country":"BE",
    "sg:address":"Smidsestraat 87",
    "sg:city":"Dendermonde",
    "sg:classifiers":[
        {
            "category":"Shopping",
            "subcategory":"Baby Store",
            "type":"Retail Goods"
        }
    ],
    "sg:phone":"+32 52 21 57 11",
    "sg:postcode":"9200",
    "sg:province":"Oost-Vlaanderen",
    "sg:tags":[
        "article",
        "b\u00e9b\u00e9s",
        "pour"
    ],
    "wof:name":"Annick Waegeman",
    "wof:placetype":"venue"
},
  "geometry": {"coordinates":[4.1122579575,51.0561599731],"type":"Point"}
}