{
  "type": "Feature",
  "properties": {
    "addr:full":"Rue Des Ma\u00cfeurs 4 Chastre Brabant Wallon 1450",
    "addr:housenumber":"4",
    "addr:postcode":"1450",
    "addr:street":"Rue Des Mai\u0308Eurs",
    "iso:country":"BE",
    "sg:address":"Rue Des Ma\u00cfeurs 4",
    "sg:city":"Chastre",
    "sg:orig_category":"Enseignement maternel and primaire",
    "sg:phone":"+32 71 87 73 37",
    "sg:postcode":"1450",
    "sg:province":"Brabant Wallon",
    "wof:name":"Ecole Fondamentale Libre",
    "wof:placetype":"venue"
},
  "geometry": {"coordinates":[4.5996098518,50.5807685852],"type":"Point"}
}