{
  "type": "Feature",
  "properties": {
    "addr:full":"Meiboom 24 Halle (groot) Vlaams-Brabant 1500",
    "addr:housenumber":"24;1500",
    "addr:street":"Meiboom;Groot Vlaams-Brabant",
    "iso:country":"BE",
    "sg:address":"Meiboom 24",
    "sg:city":"Halle (groot)",
    "sg:orig_category":"S\u00e9curit\u00e9 sociale. Secr\u00e9tariats sociaux",
    "sg:phone":"+32 2 363 88 60",
    "sg:postcode":"1500",
    "sg:province":"Vlaams-Brabant",
    "wof:name":"Partena",
    "wof:placetype":"venue"
},
  "geometry": {"coordinates":[4.2363858223,50.7383537292],"type":"Point"}
}