{
  "type": "Feature",
  "properties": {
    "iso:country":"BE",
    "sg:address":"Kapelstraat 9",
    "sg:city":"Opglabbeek",
    "sg:orig_category":"Banken and kredietinstellingen",
    "sg:phone":"+32 89 81 00 30",
    "sg:postcode":"3660",
    "sg:province":"Limburg",
    "wof:name":"Groep Argenta",
    "wof:placetype":"venue"
},
  "geometry": {"coordinates":[5.5829491615,51.0437812805],"type":"Point"}
}