{
  "type": "Feature",
  "properties": {
    "iso:country":"BE",
    "sg:address":"Izegemsestraat 132",
    "sg:city":"Kortrijk (heule)",
    "sg:classifiers":[
        {
            "category":"Personal",
            "subcategory":"Beauty Salon",
            "type":"Services"
        }
    ],
    "sg:phone":"+32 56 35 52 84",
    "sg:postcode":"8501",
    "sg:province":"West-Vlaanderen",
    "sg:tags":[
        "lady",
        "-",
        "hairdressing"
    ],
    "wof:name":"Eric",
    "wof:placetype":"venue"
},
  "geometry": {"coordinates":[3.2578570843,50.8385620117],"type":"Point"}
}