{
  "type": "Feature",
  "properties": {
    "addr:full":"Goudbloemlaan 12 Schilde Antwerpen 2970",
    "addr:housenumber":"12",
    "addr:postcode":"2970",
    "addr:street":"Goudbloemlaan",
    "iso:country":"BE",
    "sg:address":"Goudbloemlaan 12",
    "sg:city":"Schilde",
    "sg:orig_category":"Huisdieren and benodigdheden",
    "sg:phone":"+32 3 353 63 43",
    "sg:postcode":"2970",
    "sg:province":"Antwerpen",
    "wof:name":"Avicentra",
    "wof:placetype":"venue"
},
  "geometry": {"coordinates":[4.5614042282,51.2318115234],"type":"Point"}
}