{
  "type": "Feature",
  "properties": {
    "iso:country":"BE",
    "sg:address":"Kortrijksesteenweg 186",
    "sg:city":"Harelbeke",
    "sg:classifiers":[
        {
            "category":"Manufacturing",
            "subcategory":"Metals",
            "type":"Manufacturing & Wholesale Goods"
        }
    ],
    "sg:phone":"+32 56 72 85 30",
    "sg:postcode":"8530",
    "sg:province":"West-Vlaanderen",
    "sg:tags":[
        "ironwork"
    ],
    "wof:name":"Bouw- En Kunstsmederij Desmet Gebr",
    "wof:placetype":"venue"
},
  "geometry": {"coordinates":[3.2968370914,50.8466415405],"type":"Point"}
}