{
  "type": "Feature",
  "properties": {
    "addr:full":"Oudergemselaan 59b Etterbeek Bruxelles-Capitale 1040",
    "addr:housenumber":"59b",
    "addr:postcode":"1040",
    "addr:street":"Oudergemselaan",
    "iso:country":"BE",
    "sg:address":"Oudergemselaan 59b",
    "sg:city":"Etterbeek",
    "sg:orig_category":"Reisbureaus",
    "sg:phone":"+32 2 230 09 84",
    "sg:postcode":"1040",
    "sg:province":"Bruxelles-Capitale",
    "wof:name":"Voyages Melia",
    "wof:placetype":"venue"
},
  "geometry": {"coordinates":[4.3856730461,50.8385925293],"type":"Point"}
}