{
  "type": "Feature",
  "properties": {
    "addr:full":"Boulevard Joseph Tirou 161 Charleroi Hainaut 6000",
    "addr:housenumber":"161",
    "addr:postcode":"6000",
    "addr:street":"Boulevard Joseph Tirou;Hainaut",
    "iso:country":"BE",
    "sg:address":"Boulevard Joseph Tirou 161",
    "sg:city":"Charleroi",
    "sg:orig_category":"M\u00e9decins and sp\u00e9cialistes",
    "sg:phone":"+32 71 32 23 86",
    "sg:postcode":"6000",
    "sg:province":"Hainaut",
    "wof:name":"Polyclinique",
    "wof:placetype":"venue"
},
  "geometry": {"coordinates":[4.4449939728,50.4074249268],"type":"Point"}
}