{
  "type": "Feature",
  "properties": {
    "addr:full":"Roddam 15 Bornem Antwerpen 2880",
    "addr:housenumber":"15",
    "addr:postcode":"2880",
    "addr:street":"Roddam",
    "iso:country":"BE",
    "sg:address":"Roddam 15",
    "sg:city":"Bornem",
    "sg:classifiers":[
        {
            "category":"Food & Beverages",
            "subcategory":"Fruits & Vegetables",
            "type":"Retail Goods"
        }
    ],
    "sg:phone":"+32 3 889 16 32",
    "sg:postcode":"2880",
    "sg:province":"Antwerpen",
    "sg:tags":[
        "-"
    ],
    "wof:name":"Pauwels Bvba",
    "wof:placetype":"venue"
},
  "geometry": {"coordinates":[4.240457058,51.1014938354],"type":"Point"}
}