{
  "type": "Feature",
  "properties": {
    "iso:country":"BE",
    "sg:address":"Rue Chev\u00c9e 6",
    "sg:city":"Sivry-rance",
    "sg:orig_category":"Pain, p\u00e2tisseries and confiseries",
    "sg:phone":"+32 60 45 51 21",
    "sg:postcode":"6470",
    "sg:province":"Hainaut",
    "wof:name":"Rene Sol",
    "wof:placetype":"venue"
},
  "geometry": {"coordinates":[4.169271946,50.1636772156],"type":"Point"}
}