{
  "type": "Feature",
  "properties": {
    "addr:full":"Gerard Jehoelstraat 18 Hechtel-eksel (eksel) Limburg 3941",
    "addr:housenumber":"18",
    "addr:postcode":"3941",
    "addr:street":"Gerard Jehoelstraat",
    "iso:country":"BE",
    "sg:address":"Gerard Jehoelstraat 18",
    "sg:city":"Hechtel-eksel (eksel)",
    "sg:classifiers":[
        {
            "category":"Retail",
            "subcategory":"Event Space",
            "type":"Services"
        }
    ],
    "sg:phone":"+32 475 43 01 44",
    "sg:postcode":"3941",
    "sg:province":"Limburg",
    "sg:tags":[
        "organisation"
    ],
    "wof:name":"Claes & Partners",
    "wof:placetype":"venue"
},
  "geometry": {"coordinates":[5.4027562141,51.1547546387],"type":"Point"}
}