{
  "type": "Feature",
  "properties": {
    "iso:country":"BE",
    "sg:address":"Kortenbos 62",
    "sg:city":"Affligem",
    "sg:orig_category":"Installation de menuiserie en bois and plastique. R\u00e9paration and restauration de meubles",
    "sg:phone":"+32 53 66 52 54",
    "sg:postcode":"1790",
    "sg:province":"Vlaams-Brabant",
    "wof:name":"Herman De Kerpel",
    "wof:placetype":"venue"
},
  "geometry": {"coordinates":[4.0873389244,50.8984222412],"type":"Point"}
}