{
  "type": "Feature",
  "properties": {
    "addr:full":"Walburgstraat 35 Sint-niklaas Oost-Vlaanderen 9100",
    "addr:housenumber":"35",
    "addr:postcode":"9100",
    "addr:street":"Walburgstraat",
    "iso:country":"BE",
    "sg:address":"Walburgstraat 35",
    "sg:city":"Sint-niklaas",
    "sg:classifiers":[
        {
            "category":"Restaurant",
            "type":"Food & Drink"
        }
    ],
    "sg:phone":"+32 3 766 21 16",
    "sg:postcode":"9100",
    "sg:province":"Oost-Vlaanderen",
    "wof:name":"Wildmenu",
    "wof:placetype":"venue"
},
  "geometry": {"coordinates":[4.1462159157,51.1633262634],"type":"Point"}
}