{
  "type": "Feature",
  "properties": {
    "iso:country":"BE",
    "sg:address":"Chauss\u00e9e De Heusy 207",
    "sg:city":"Verviers",
    "sg:classifiers":[
        {
            "category":"Bakery",
            "type":"Food & Drink"
        }
    ],
    "sg:phone":"+32 87 22 94 35",
    "sg:postcode":"4800",
    "sg:province":"Li\u00e8ge",
    "sg:tags":[
        "confectioner",
        "baker"
    ],
    "wof:name":"Lion J-m",
    "wof:placetype":"venue"
},
  "geometry": {"coordinates":[5.8652710915,50.5841369629],"type":"Point"}
}