{
  "type": "Feature",
  "properties": {
    "addr:full":"Rue Du Homvent 30 Beyne-heusay Li\u00e8ge 4610",
    "addr:housenumber":"30",
    "addr:postcode":"4610",
    "addr:street":"Rue Du Homvent",
    "iso:country":"BE",
    "sg:address":"Rue Du Homvent 30",
    "sg:city":"Beyne-heusay",
    "sg:orig_category":"Plaatsen van vloer- and muurbekleding Vloer- and muurbekleding",
    "sg:phone":"+32 4 367 32 27",
    "sg:postcode":"4610",
    "sg:province":"Li\u00e8ge",
    "wof:name":"Velotta",
    "wof:placetype":"venue"
},
  "geometry": {"coordinates":[5.6490569115,50.6261444092],"type":"Point"}
}