{
  "type": "Feature",
  "properties": {
    "addr:full":"Grote Nieuwedijkstraat 121 Mechelen Antwerpen 2800",
    "addr:housenumber":"121",
    "addr:postcode":"2800",
    "addr:street":"Grote Nieuwedijkstraat",
    "iso:country":"BE",
    "sg:address":"Grote Nieuwedijkstraat 121",
    "sg:city":"Mechelen",
    "sg:orig_category":"Artiesten and kunstenaars",
    "sg:phone":"+32 15 55 51 44",
    "sg:postcode":"2800",
    "sg:province":"Antwerpen",
    "wof:name":"Jean De Winter",
    "wof:placetype":"venue"
},
  "geometry": {"coordinates":[4.4941711426,51.0339736938],"type":"Point"}
}