{
  "type": "Feature",
  "properties": {
    "iso:country":"BE",
    "sg:address":"Pav\u00e9 D'ath 12",
    "sg:city":"Enghien",
    "sg:orig_category":"Autombile concessionaires",
    "sg:phone":"+32 2 395 37 58",
    "sg:postcode":"7850",
    "sg:province":"Hainaut",
    "wof:name":"Nouveaux Ets Tennsted Freres",
    "wof:placetype":"venue"
},
  "geometry": {"coordinates":[4.0117511749,50.6865768433],"type":"Point"}
}