{
  "type": "Feature",
  "properties": {
    "iso:country":"BE",
    "sg:address":"Koksijdesteenweg 11",
    "sg:city":"Koksijde",
    "sg:orig_category":"Gespecialiseerde residenti\u00eble bouw",
    "sg:phone":"+32 58 52 39 43",
    "sg:postcode":"8670",
    "sg:province":"West-Vlaanderen",
    "wof:name":"Lucien Clauw",
    "wof:placetype":"venue"
},
  "geometry": {"coordinates":[2.669121027,51.1102867126],"type":"Point"}
}