{
  "type": "Feature",
  "properties": {
    "iso:country":"BE",
    "sg:address":"Kolderstraat 150",
    "sg:city":"Houthalen-helchteren",
    "sg:orig_category":"M\u00e9decins and sp\u00e9cialistes",
    "sg:phone":"+32 11 57 10 92",
    "sg:postcode":"3530",
    "sg:province":"Limburg",
    "wof:name":"F. D'agostino",
    "wof:placetype":"venue"
},
  "geometry": {"coordinates":[5.3357639313,51.0521354675],"type":"Point"}
}