{
  "type": "Feature",
  "properties": {
    "addr:full":"Rue De Wastines 8 Incourt Brabant Wallon 1315",
    "addr:housenumber":"8",
    "addr:postcode":"1315",
    "addr:street":"Rue De Wastines",
    "iso:country":"BE",
    "sg:address":"Rue De Wastines 8",
    "sg:city":"Incourt",
    "sg:orig_category":"Artsen and specialisten",
    "sg:phone":"+32 10 88 80 78",
    "sg:postcode":"1315",
    "sg:province":"Brabant Wallon",
    "wof:name":"Etienne Hennau",
    "wof:placetype":"venue"
},
  "geometry": {"coordinates":[4.7988610268,50.678565979],"type":"Point"}
}