{
  "type": "Feature",
  "properties": {
    "addr:full":"Eug\u00e8ne Gilbertstraat 4 Leuven Vlaams-Brabant 3000",
    "addr:housenumber":"4",
    "addr:postcode":"3000",
    "addr:street":"Euge\u0300Ne Gilbertstraat",
    "iso:country":"BE",
    "sg:address":"Eug\u00e8ne Gilbertstraat 4",
    "sg:city":"Leuven",
    "sg:classifiers":[
        {
            "category":"Professional",
            "subcategory":"Lawyer & Legal Services",
            "type":"Services"
        }
    ],
    "sg:phone":"+32 16 22 23 76",
    "sg:postcode":"3000",
    "sg:province":"Vlaams-Brabant",
    "wof:name":"Smets Myriam",
    "wof:placetype":"venue"
},
  "geometry": {"coordinates":[4.6997709274,50.8698501587],"type":"Point"}
}