{
  "type": "Feature",
  "properties": {
    "addr:full":"Heernisplein 8 Gent Oost-Vlaanderen 9040",
    "addr:housenumber":"8",
    "addr:postcode":"9040",
    "addr:street":"Heernisplein;Oost-Vlaanderen",
    "iso:country":"BE",
    "sg:address":"Heernisplein 8",
    "sg:city":"Gent",
    "sg:orig_category":"Banken and kredietinstellingen",
    "sg:phone":"+32 9 228 73 21",
    "sg:postcode":"9040",
    "sg:province":"Oost-Vlaanderen",
    "wof:name":"Dexia",
    "wof:placetype":"venue"
},
  "geometry": {"coordinates":[3.74873209,51.0523109436],"type":"Point"}
}