{
  "type": "Feature",
  "properties": {
    "iso:country":"BE",
    "sg:address":"Voie Blanche 54",
    "sg:city":"Dour (blaugies)",
    "sg:classifiers":[
        {
            "category":"Health Services",
            "subcategory":"Nursing And Care Facility",
            "type":"Services"
        }
    ],
    "sg:phone":"+32 65 63 02 17",
    "sg:postcode":"7370",
    "sg:province":"Hainaut",
    "sg:tags":[
        "home"
    ],
    "wof:name":"Amand Sebastien",
    "wof:placetype":"venue"
},
  "geometry": {"coordinates":[3.8111000061,50.3722801208],"type":"Point"}
}