{
  "type": "Feature",
  "properties": {
    "addr:full":"Rue Moirivay 7 Olne Li\u00e8ge 4877",
    "addr:housenumber":"7",
    "addr:postcode":"4877",
    "addr:street":"Rue Moirivay",
    "iso:country":"BE",
    "sg:address":"Rue Moirivay 7",
    "sg:city":"Olne",
    "sg:orig_category":"HUISBRANDOLIE",
    "sg:phone":"+32 87 26 82 13",
    "sg:postcode":"4877",
    "sg:province":"Li\u00e8ge",
    "wof:name":"Joseph Bollette",
    "wof:placetype":"venue"
},
  "geometry": {"coordinates":[5.7347950935,50.568572998],"type":"Point"}
}