{
  "type": "Feature",
  "properties": {
    "addr:full":"Rue De L\u00b4eglise 1 Hamoir Li\u00e8ge 4180",
    "addr:housenumber":"1",
    "addr:postcode":"4180",
    "addr:street":"Rue De L\u00b4Eglise",
    "iso:country":"BE",
    "sg:address":"Rue De L\u00b4eglise 1",
    "sg:city":"Hamoir",
    "sg:orig_category":"Herstellingen and onderhoud van auto's",
    "sg:phone":"+32 86 38 75 87",
    "sg:postcode":"4180",
    "sg:province":"Li\u00e8ge",
    "wof:name":"Guy Hody",
    "wof:placetype":"venue"
},
  "geometry": {"coordinates":[5.5435671806,50.4449653625],"type":"Point"}
}