{
  "type": "Feature",
  "properties": {
    "addr:full":"Chauss\u00c9e De Binche 101 Bergen Hainaut 7000",
    "addr:housenumber":"101",
    "addr:postcode":"7000",
    "addr:street":"Chausse\u0301E De Binche",
    "iso:country":"BE",
    "sg:address":"Chauss\u00c9e De Binche 101",
    "sg:city":"Bergen",
    "sg:orig_category":"Supermarkten",
    "sg:postcode":"7000",
    "sg:province":"Hainaut",
    "wof:name":"Aldi",
    "wof:placetype":"venue"
},
  "geometry": {"coordinates":[3.9737520218,50.4527206421],"type":"Point"}
}