{
  "type": "Feature",
  "properties": {
    "addr:full":"Dreefstraat 46 Ninove (groot) Oost-Vlaanderen 9400",
    "addr:housenumber":"46",
    "addr:postcode":"9400",
    "addr:street":"Dreefstraat;Groot Oost-Vlaanderen",
    "iso:country":"BE",
    "sg:address":"Dreefstraat 46",
    "sg:city":"Ninove (groot)",
    "sg:orig_category":"R\u00e9paration and restauration de meubles. Meubles D\u00e9taillants, Am\u00e9nagement de B\u00e2timents et de Cuisines",
    "sg:phone":"+32 54 33 56 97",
    "sg:postcode":"9400",
    "sg:province":"Oost-Vlaanderen",
    "wof:name":"'t Dreefhuys",
    "wof:placetype":"venue"
},
  "geometry": {"coordinates":[4.0248670578,50.8375930786],"type":"Point"}
}