{
  "type": "Feature",
  "properties": {
    "addr:full":"Route De L'ambleve 28 Stoumont Li\u00e8ge 4987",
    "addr:housenumber":"28",
    "addr:postcode":"4987",
    "addr:street":"Route De L'Ambleve",
    "iso:country":"BE",
    "sg:address":"Route De L'ambleve 28",
    "sg:city":"Stoumont",
    "sg:orig_category":"Apotheken",
    "sg:phone":"+32 80 78 55 21",
    "sg:postcode":"4987",
    "sg:province":"Li\u00e8ge",
    "wof:name":"Martine Vanderbruggen",
    "wof:placetype":"venue"
},
  "geometry": {"coordinates":[5.8089780807,50.4066314697],"type":"Point"}
}