{
  "type": "Feature",
  "properties": {
    "iso:country":"BE",
    "sg:address":"Binkomstraat 69",
    "sg:city":"Lubbeek",
    "sg:orig_category":"R\u00e9alisation de programmes and logiciels. Conseils en syst\u00e8mes informatiques",
    "sg:phone":"+32 16 62 94 42",
    "sg:postcode":"3210",
    "sg:province":"Vlaams-Brabant",
    "wof:name":"Live!",
    "wof:placetype":"venue"
},
  "geometry": {"coordinates":[4.857831955,50.8810195923],"type":"Point"}
}