{
  "type": "Feature",
  "properties": {
    "addr:full":"Friedenstr 6-10 Saint-vith Li\u00e8ge 4780",
    "addr:housenumber":"6-10",
    "addr:postcode":"4780",
    "addr:street":"Saint-Vith Lie\u0300Ge",
    "iso:country":"BE",
    "sg:address":"Friedenstr 6-10",
    "sg:city":"Saint-vith",
    "sg:classifiers":[
        {
            "category":"Manufacturing",
            "subcategory":"Printing",
            "type":"Manufacturing & Wholesale Goods"
        }
    ],
    "sg:phone":"+32 80 28 01 80",
    "sg:postcode":"4780",
    "sg:province":"Li\u00e8ge",
    "sg:tags":[
        "publishing"
    ],
    "wof:name":"Pro D & P Sa",
    "wof:placetype":"venue"
},
  "geometry": {"coordinates":[6.1237602234,50.2851715088],"type":"Point"}
}