{
  "type": "Feature",
  "properties": {
    "iso:country":"BE",
    "sg:address":"Keulestraat 7",
    "sg:city":"Tielt-winge (tielt)",
    "sg:classifiers":[
        {
            "category":"Parking",
            "subcategory":"Lot",
            "type":"Transportation"
        }
    ],
    "sg:phone":"+32 16 64 05 89",
    "sg:postcode":"3390",
    "sg:province":"Vlaams-Brabant",
    "sg:tags":[
        "armoured",
        "door",
        "fireproof"
    ],
    "wof:name":"Eurowood Belgium Bvba",
    "wof:placetype":"venue"
},
  "geometry": {"coordinates":[4.8894128799,50.9305725098],"type":"Point"}
}