{
  "type": "Feature",
  "properties": {
    "addr:full":"Nieuwe Kaai 25 Turnhout Antwerpen 2300",
    "addr:housenumber":"25",
    "addr:postcode":"2300",
    "addr:street":"Nieuwe Kaai",
    "iso:country":"BE",
    "sg:address":"Nieuwe Kaai 25",
    "sg:city":"Turnhout",
    "sg:classifiers":[
        {
            "category":"Insurance",
            "subcategory":"Insurance Agent",
            "type":"Services"
        }
    ],
    "sg:phone":"+32 14 47 27 77",
    "sg:postcode":"2300",
    "sg:province":"Antwerpen",
    "sg:tags":[
        "verzekeringsmakelaars",
        "expert"
    ],
    "wof:name":"I C V",
    "wof:placetype":"venue"
},
  "geometry": {"coordinates":[4.9317178726,51.3258171082],"type":"Point"}
}