{
  "type": "Feature",
  "properties": {
    "addr:full":"Westrodestraat 21 Meise (wolvertem) Vlaams-Brabant 1861",
    "addr:housenumber":"21",
    "addr:postcode":"1861",
    "addr:street":"Westrodestraat",
    "iso:country":"BE",
    "sg:address":"Westrodestraat 21",
    "sg:city":"Meise (wolvertem)",
    "sg:classifiers":[
        {
            "category":"Health Services",
            "subcategory":"Doctor",
            "type":"Services"
        }
    ],
    "sg:phone":"+32 52 30 51 97",
    "sg:postcode":"1861",
    "sg:province":"Vlaams-Brabant",
    "sg:tags":[
        "medicinephysicians",
        "surgeon"
    ],
    "wof:name":"Decleyre Peter",
    "wof:placetype":"venue"
},
  "geometry": {"coordinates":[4.3277378082,50.9976234436],"type":"Point"}
}