{
  "type": "Feature",
  "properties": {
    "addr:full":"Koningin Astridstraat 41 Asse Vlaams-Brabant 1730",
    "addr:housenumber":"41",
    "addr:postcode":"1730",
    "addr:street":"Koningin Astridstraat",
    "iso:country":"BE",
    "sg:address":"Koningin Astridstraat 41",
    "sg:city":"Asse",
    "sg:classifiers":[
        {
            "category":"Cafe",
            "type":"Food & Drink"
        }
    ],
    "sg:phone":"+32 2 452 58 36",
    "sg:postcode":"1730",
    "sg:province":"Vlaams-Brabant",
    "sg:tags":[
        "caf\u00e9s"
    ],
    "wof:name":"Dirk De Smet",
    "wof:placetype":"venue"
},
  "geometry": {"coordinates":[4.1925721169,50.9128646851],"type":"Point"}
}