{
  "type": "Feature",
  "properties": {
    "iso:country":"BE",
    "sg:address":"Tongerensteenweg 79",
    "sg:city":"Sint-truiden",
    "sg:orig_category":"V\u00eatements",
    "sg:phone":"+32 11 67 14 95",
    "sg:postcode":"3800",
    "sg:province":"Limburg",
    "wof:name":"Wyco Mode",
    "wof:placetype":"venue"
},
  "geometry": {"coordinates":[5.189084053,50.813293457],"type":"Point"}
}