{
  "type": "Feature",
  "properties": {
    "addr:full":"Zeelaan 57 Koksijde West-Vlaanderen 8670",
    "addr:housenumber":"57",
    "addr:postcode":"8670",
    "addr:street":"Zeelaan",
    "iso:country":"BE",
    "sg:address":"Zeelaan 57",
    "sg:city":"Koksijde",
    "sg:orig_category":"Pain, p\u00e2tisseries and confiseries",
    "sg:phone":"+32 58 51 15 40",
    "sg:postcode":"8670",
    "sg:province":"West-Vlaanderen",
    "wof:name":"Dirk Vanoverberghe",
    "wof:placetype":"venue"
},
  "geometry": {"coordinates":[2.6486859322,51.1064376831],"type":"Point"}
}