{
  "type": "Feature",
  "properties": {
    "addr:full":"Doorslaarstraat 58 Lokeren Oost-Vlaanderen 9160",
    "addr:housenumber":"58",
    "addr:postcode":"9160",
    "addr:street":"Doorslaarstraat",
    "iso:country":"BE",
    "sg:address":"Doorslaarstraat 58",
    "sg:city":"Lokeren",
    "sg:orig_category":"P\u00e9pini\u00e9ristes",
    "sg:phone":"+32 9 348 21 78",
    "sg:postcode":"9160",
    "sg:province":"Oost-Vlaanderen",
    "wof:name":"Henri Blancquaert",
    "wof:placetype":"venue"
},
  "geometry": {"coordinates":[3.9864850044,51.1047401428],"type":"Point"}
}