{
  "type": "Feature",
  "properties": {
    "iso:country":"BE",
    "sg:address":"Vleeshouwersstraat 23",
    "sg:city":"Sint-niklaas (sinaai)",
    "sg:classifiers":[
        {
            "category":"Retail",
            "subcategory":"Repair Shop",
            "type":"Services"
        }
    ],
    "sg:phone":"+32 3 772 44 55",
    "sg:postcode":"9112",
    "sg:province":"Oost-Vlaanderen",
    "sg:tags":[
        "radio",
        "television",
        "-",
        "maintenance"
    ],
    "wof:name":"Van Mele D",
    "wof:placetype":"venue"
},
  "geometry": {"coordinates":[4.0457601547,51.158416748],"type":"Point"}
}