{
  "type": "Feature",
  "properties": {
    "iso:country":"BE",
    "sg:address":"Tielenstraat 38",
    "sg:city":"Overpelt",
    "sg:classifiers":[
        {
            "category":"Health Services",
            "subcategory":"Health Practitioner",
            "type":"Services"
        }
    ],
    "sg:phone":"+32 11 61 23 63",
    "sg:postcode":"3900",
    "sg:province":"Limburg",
    "sg:tags":[
        "dietitian"
    ],
    "wof:name":"Cox E",
    "wof:placetype":"venue"
},
  "geometry": {"coordinates":[5.4096961021,51.1824455261],"type":"Point"}
}