{
  "type": "Feature",
  "properties": {
    "addr:full":"De Valk 45 Mortsel Antwerpen 2640",
    "addr:housenumber":"45",
    "addr:postcode":"2640",
    "addr:street":"De Valk",
    "iso:country":"BE",
    "sg:address":"De Valk 45",
    "sg:city":"Mortsel",
    "sg:classifiers":[
        {
            "category":"Professional",
            "subcategory":"Management & Consulting",
            "type":"Services"
        }
    ],
    "sg:phone":"+32 3 455 15 28",
    "sg:postcode":"2640",
    "sg:province":"Antwerpen",
    "sg:tags":[
        "tax-consultants"
    ],
    "wof:name":"Murrath A",
    "wof:placetype":"venue"
},
  "geometry": {"coordinates":[4.4748811722,51.1652107239],"type":"Point"}
}