{
  "type": "Feature",
  "properties": {
    "iso:country":"BE",
    "sg:address":"Don Boscostraat 105 Box 2",
    "sg:city":"Hechtel-eksel (hechtel)",
    "sg:classifiers":[
        {
            "category":"Shopping",
            "subcategory":"Optician",
            "type":"Retail Goods"
        }
    ],
    "sg:phone":"+32 11 73 27 67",
    "sg:postcode":"3940",
    "sg:province":"Limburg",
    "sg:tags":[
        "-"
    ],
    "wof:name":"Ann Optiek",
    "wof:placetype":"venue"
},
  "geometry": {"coordinates":[5.364795208,51.1255340576],"type":"Point"}
}