{
  "type": "Feature",
  "properties": {
    "addr:full":"Schatting 48ba Zedelgem West-Vlaanderen 8210",
    "addr:housenumber":"48ba",
    "addr:postcode":"8210",
    "addr:street":"Schatting",
    "iso:country":"BE",
    "sg:address":"Schatting 48ba",
    "sg:city":"Zedelgem",
    "sg:orig_category":"Transports routiers de marchandises",
    "sg:phone":"+32 50 24 05 95",
    "sg:postcode":"8210",
    "sg:province":"West-Vlaanderen",
    "wof:name":"Devooght-verleye",
    "wof:placetype":"venue"
},
  "geometry": {"coordinates":[3.1440279484,51.1368637085],"type":"Point"}
}