{
  "type": "Feature",
  "properties": {
    "iso:country":"BE",
    "sg:address":"Ten Hovestraat 1",
    "sg:city":"Tielt",
    "sg:orig_category":"Produits chimiques Mat\u00e9riel scientifique and technique Fab",
    "sg:phone":"+32 51 40 23 40",
    "sg:postcode":"8700",
    "sg:province":"West-Vlaanderen",
    "wof:name":"Servi-lab",
    "wof:placetype":"venue"
},
  "geometry": {"coordinates":[3.3392460346,50.9822883606],"type":"Point"}
}