{
  "type": "Feature",
  "properties": {
    "addr:full":"Rue De Templeuve 14 Estaimpuis Hainaut 7730",
    "addr:housenumber":"14",
    "addr:postcode":"7730",
    "addr:street":"Rue De Templeuve;Hainaut",
    "iso:country":"BE",
    "sg:address":"Rue De Templeuve 14",
    "sg:city":"Estaimpuis",
    "sg:orig_category":"Rundveehouders",
    "sg:phone":"+32 69 55 62 65",
    "sg:postcode":"7730",
    "sg:province":"Hainaut",
    "wof:name":"Dominique Werquin",
    "wof:placetype":"venue"
},
  "geometry": {"coordinates":[3.3152489662,50.6667861938],"type":"Point"}
}