{
  "type": "Feature",
  "properties": {
    "iso:country":"BE",
    "sg:address":"Snelwegstraat 4",
    "sg:city":"Westerlo",
    "sg:classifiers":[
        {
            "category":"Restaurant",
            "type":"Food & Drink"
        }
    ],
    "sg:phone":"+32 14 59 42 20",
    "sg:postcode":"2260",
    "sg:province":"Antwerpen",
    "wof:name":"Den Beemt",
    "wof:placetype":"venue"
},
  "geometry": {"coordinates":[4.9112768173,51.0883636475],"type":"Point"}
}