{
  "type": "Feature",
  "properties": {
    "iso:country":"BE",
    "sg:address":"Joseph Plateaustraat 7",
    "sg:city":"Oostende (stene)",
    "sg:classifiers":[
        {
            "category":"Sports & Exercise",
            "subcategory":"Ice Rink",
            "type":"Entertainment"
        }
    ],
    "sg:phone":"+32 59 70 87 01",
    "sg:postcode":"8400",
    "sg:province":"West-Vlaanderen",
    "sg:tags":[
        "machine",
        "making"
    ],
    "wof:name":"Berton Koeltechniek Bvba",
    "wof:placetype":"venue"
},
  "geometry": {"coordinates":[2.937073946,51.2092285156],"type":"Point"}
}