{
  "type": "Feature",
  "properties": {
    "addr:full":"Lucien Vande Fonteyneln 23 Oudenaarde Oost-Vlaanderen 9700",
    "addr:housenumber":"23",
    "addr:postcode":"9700",
    "addr:street":"Lucien Vande Fonteyneln",
    "iso:country":"BE",
    "sg:address":"Lucien Vande Fonteyneln 23",
    "sg:city":"Oudenaarde",
    "sg:orig_category":"Artiesten and kunstenaars",
    "sg:phone":"+32 55 31 09 04",
    "sg:postcode":"9700",
    "sg:province":"Oost-Vlaanderen",
    "wof:name":"Frank De Coninck",
    "wof:placetype":"venue"
},
  "geometry": {"coordinates":[3.6155400276,50.8393707275],"type":"Point"}
}