{
  "type": "Feature",
  "properties": {
    "iso:country":"BE",
    "sg:address":"Kerkstraat 22b101",
    "sg:city":"Middelkerke",
    "sg:classifiers":[
        {
            "category":"Cafe",
            "type":"Food & Drink"
        }
    ],
    "sg:phone":"+32 59 30 07 96",
    "sg:postcode":"8430",
    "sg:province":"West-Vlaanderen",
    "sg:tags":[
        "caf\u00e9s"
    ],
    "wof:name":"Caf\u00c9 The Gallery",
    "wof:placetype":"venue"
},
  "geometry": {"coordinates":[2.8203859329,51.18592453],"type":"Point"}
}