{
  "type": "Feature",
  "properties": {
    "iso:country":"BE",
    "sg:address":"Rue D'anderlues 146",
    "sg:city":"Lobbes",
    "sg:classifiers":[
        {
            "category":"Building & Trades",
            "subcategory":"Electrical",
            "type":"Services"
        }
    ],
    "sg:phone":"+32 71 59 01 87",
    "sg:postcode":"6540",
    "sg:province":"Hainaut",
    "sg:tags":[
        "heating"
    ],
    "wof:name":"B E P",
    "wof:placetype":"venue"
},
  "geometry": {"coordinates":[4.2781071663,50.379447937],"type":"Point"}
}