{
  "type": "Feature",
  "properties": {
    "addr:full":"Rue Branche Planchart 69 Saint-nicolas Li\u00e8ge 4420",
    "addr:housenumber":"69",
    "addr:postcode":"4420",
    "addr:street":"Rue Branche Planchart",
    "iso:country":"BE",
    "sg:address":"Rue Branche Planchart 69",
    "sg:city":"Saint-nicolas",
    "sg:orig_category":"Loodgieterij, verwarming and sanitaire installaties",
    "sg:phone":"+32 4 336 00 49",
    "sg:postcode":"4420",
    "sg:province":"Li\u00e8ge",
    "wof:name":"Thermosiphon",
    "wof:placetype":"venue"
},
  "geometry": {"coordinates":[5.5267729759,50.6467933655],"type":"Point"}
}