{
  "type": "Feature",
  "properties": {
    "addr:full":"Rue Paul Tournay 35 Gembloux-sur-orneau (gembloux) Namur 5030",
    "addr:housenumber":"35",
    "addr:postcode":"5030",
    "addr:street":"Rue Paul Tournay;Namur",
    "iso:country":"BE",
    "sg:address":"Rue Paul Tournay 35",
    "sg:city":"Gembloux-sur-orneau (gembloux)",
    "sg:classifiers":[
        {
            "category":"Real Estate",
            "subcategory":"Architect",
            "type":"Services"
        }
    ],
    "sg:phone":"+32 81 61 60 64",
    "sg:postcode":"5030",
    "sg:province":"Namur",
    "wof:name":"Heymans B",
    "wof:placetype":"venue"
},
  "geometry": {"coordinates":[4.6943721771,50.5573425293],"type":"Point"}
}