{
  "type": "Feature",
  "properties": {
    "iso:country":"BE",
    "sg:address":"Rue De Labliau 5",
    "sg:city":"Silly (hoves)",
    "sg:classifiers":[
        {
            "category":"Building & Trades",
            "subcategory":"Landscaping Services",
            "type":"Services"
        }
    ],
    "sg:phone":"+32 2 395 84 35",
    "sg:postcode":"7830",
    "sg:province":"Hainaut",
    "sg:tags":[
        "gardening",
        "garden",
        "maintenance"
    ],
    "wof:name":"Jardin De A A Z",
    "wof:placetype":"venue"
},
  "geometry": {"coordinates":[4.032957077,50.6725463867],"type":"Point"}
}