{
  "type": "Feature",
  "properties": {
    "addr:full":"Rue Grande 55 Ciney Namur 5590",
    "addr:housenumber":"55",
    "addr:postcode":"5590",
    "addr:street":"Rue Grande",
    "iso:country":"BE",
    "sg:address":"Rue Grande 55",
    "sg:city":"Ciney",
    "sg:orig_category":"M\u00e9decins and sp\u00e9cialistes",
    "sg:phone":"+32 83 21 66 33",
    "sg:postcode":"5590",
    "sg:province":"Namur",
    "wof:name":"I. Marin",
    "wof:placetype":"venue"
},
  "geometry": {"coordinates":[5.1022520065,50.297088623],"type":"Point"}
}