{
  "type": "Feature",
  "properties": {
    "addr:full":"Vossendal 9 Geel Antwerpen 2440",
    "addr:housenumber":"9",
    "addr:postcode":"2440",
    "addr:street":"Vossendal",
    "iso:country":"BE",
    "sg:address":"Vossendal 9",
    "sg:city":"Geel",
    "sg:classifiers":[
        {
            "category":"Autos & Motor Vehicles",
            "subcategory":"Automobile Sales",
            "type":"Retail Goods"
        }
    ],
    "sg:phone":"+32 14 86 70 23",
    "sg:postcode":"2440",
    "sg:province":"Antwerpen",
    "sg:tags":[
        "equipment",
        "motor-cars",
        "transport"
    ],
    "wof:name":"Hyundai Machines Belgium Nv",
    "wof:placetype":"venue"
},
  "geometry": {"coordinates":[4.9454932213,51.1255226135],"type":"Point"}
}