{
  "type": "Feature",
  "properties": {
    "iso:country":"BE",
    "sg:address":"Vliegenier Behaeghelaan 11",
    "sg:city":"Moeskroen/mouscron",
    "sg:orig_category":"Rundveehouders",
    "sg:phone":"+32 56 33 48 43",
    "sg:postcode":"7712",
    "sg:province":"Hainaut",
    "wof:name":"Guy Brouckaert",
    "wof:placetype":"venue"
},
  "geometry": {"coordinates":[3.2535879612,50.714931488],"type":"Point"}
}