{
  "type": "Feature",
  "properties": {
    "iso:country":"BE",
    "sg:address":"Rue Du Commerce 83",
    "sg:city":"Ciney",
    "sg:classifiers":[
        {
            "category":"Insurance",
            "subcategory":"Insurance Agent",
            "type":"Services"
        }
    ],
    "sg:phone":"+32 83 21 17 42",
    "sg:postcode":"5590",
    "sg:province":"Namur",
    "sg:tags":[
        "broker"
    ],
    "wof:name":"Gillard Et Rolain Sa",
    "wof:placetype":"venue"
},
  "geometry": {"coordinates":[5.0962719917,50.2921829224],"type":"Point"}
}