{
  "type": "Feature",
  "properties": {
    "iso:country":"BE",
    "sg:address":"Munthofstraat 63",
    "sg:city":"Sint-gillis/saint-gilles",
    "sg:classifiers":[
        {
            "category":"Restaurant",
            "type":"Food & Drink"
        }
    ],
    "sg:phone":"+32 2 539 25 76",
    "sg:postcode":"1060",
    "sg:province":"Bruxelles-Capitale",
    "wof:name":"Restaurant Araucana",
    "wof:placetype":"venue"
},
  "geometry": {"coordinates":[4.348388195,50.8312568665],"type":"Point"}
}