{
  "type": "Feature",
  "properties": {
    "iso:country":"BE",
    "sg:address":"Chauss\u00c9e De Bruxelles 547",
    "sg:city":"Waterloo",
    "sg:orig_category":"Herstellingen and onderhoud van auto's",
    "sg:phone":"+32 2 384 62 72",
    "sg:postcode":"1410",
    "sg:province":"Brabant Wallon",
    "wof:name":"Carglass",
    "wof:placetype":"venue"
},
  "geometry": {"coordinates":[4.4064269066,50.6908950806],"type":"Point"}
}