{
  "type": "Feature",
  "properties": {
    "iso:country":"BE",
    "sg:address":"Boulevard Adolphe Max 75",
    "sg:city":"Bruxelles",
    "sg:classifiers":[
        {
            "category":"Professional",
            "subcategory":"Employment Agencies",
            "type":"Services"
        }
    ],
    "sg:phone":"+32 2 217 40 52",
    "sg:postcode":"1000",
    "sg:province":"Bruxelles-Capitale",
    "sg:tags":[
        "temping",
        "-",
        "manual"
    ],
    "wof:name":"Amis-arrow Int\u00e9rim",
    "wof:placetype":"venue"
},
  "geometry": {"coordinates":[4.3560361862,50.8537139893],"type":"Point"}
}