{
  "type": "Feature",
  "properties": {
    "addr:full":"Longue-voie 60 Ronse/renaix Oost-Vlaanderen 9600",
    "addr:housenumber":"60",
    "addr:postcode":"9600",
    "addr:street":"Longue-Voie",
    "iso:country":"BE",
    "sg:address":"Longue-voie 60",
    "sg:city":"Ronse/renaix",
    "sg:orig_category":"Boucheries",
    "sg:phone":"+32 55 21 19 47",
    "sg:postcode":"9600",
    "sg:province":"Oost-Vlaanderen",
    "wof:name":"E. Jorion",
    "wof:placetype":"venue"
},
  "geometry": {"coordinates":[3.613601923,50.7369842529],"type":"Point"}
}