{
  "type": "Feature",
  "properties": {
    "addr:full":"Vredestraat 4 Beerse Antwerpen 2340",
    "addr:housenumber":"4",
    "addr:postcode":"2340",
    "addr:street":"Vredestraat",
    "iso:country":"BE",
    "sg:address":"Vredestraat 4",
    "sg:city":"Beerse",
    "sg:orig_category":"Groenten and fruit Gh Supermarkten",
    "sg:phone":"+32 14 61 24 63",
    "sg:postcode":"2340",
    "sg:province":"Antwerpen",
    "wof:name":"Peeters Govers",
    "wof:placetype":"venue"
},
  "geometry": {"coordinates":[4.8563199043,51.3196754456],"type":"Point"}
}