{
  "type": "Feature",
  "properties": {
    "iso:country":"BE",
    "sg:address":"Vanden Tymplestraat 4 Box 301",
    "sg:city":"Leuven",
    "sg:classifiers":[
        {
            "category":"Utilities",
            "subcategory":"Telephone",
            "type":"Services"
        }
    ],
    "sg:phone":"+32 16 23 93 79",
    "sg:postcode":"3000",
    "sg:province":"Vlaams-Brabant",
    "sg:tags":[
        "-",
        "internet"
    ],
    "wof:name":"Besite Bvba",
    "wof:placetype":"venue"
},
  "geometry": {"coordinates":[4.7116851807,50.882019043],"type":"Point"}
}