{
  "type": "Feature",
  "properties": {
    "iso:country":"BE",
    "sg:address":"Rue Des Soeurs 2",
    "sg:city":"Aywaille",
    "sg:classifiers":[
        {
            "category":"Health Services",
            "subcategory":"Dentist",
            "type":"Services"
        }
    ],
    "sg:phone":"+32 4 380 91 11",
    "sg:postcode":"4920",
    "sg:province":"Li\u00e8ge",
    "wof:name":"Finet B",
    "wof:placetype":"venue"
},
  "geometry": {"coordinates":[5.6730661392,50.473903656],"type":"Point"}
}