{
  "type": "Feature",
  "properties": {
    "addr:full":"Rue Lef\u00e9bure E. 1 Estinnes (haulchin) Hainaut 7120",
    "addr:housenumber":"1",
    "addr:postcode":"7120",
    "addr:street":"Rue Lefe\u0301Bure E.",
    "iso:country":"BE",
    "sg:address":"Rue Lef\u00e9bure E. 1",
    "sg:city":"Estinnes (haulchin)",
    "sg:classifiers":[
        {
            "category":"Health Services",
            "subcategory":"Doctor",
            "type":"Services"
        }
    ],
    "sg:phone":"+32 65 58 69 03",
    "sg:postcode":"7120",
    "sg:province":"Hainaut",
    "sg:tags":[
        "medicinephysicians",
        "surgeon"
    ],
    "wof:name":"Durez Marianne",
    "wof:placetype":"venue"
},
  "geometry": {"coordinates":[4.0968389511,50.3966941833],"type":"Point"}
}