{
  "type": "Feature",
  "properties": {
    "iso:country":"BE",
    "sg:address":"Schaapstraat 34",
    "sg:city":"Roeselare",
    "sg:orig_category":"M\u00e9decins and sp\u00e9cialistes",
    "sg:phone":"+32 51 25 27 47",
    "sg:postcode":"8800",
    "sg:province":"West-Vlaanderen",
    "wof:name":"Inge Desmedt",
    "wof:placetype":"venue"
},
  "geometry": {"coordinates":[3.1628940105,50.9250602722],"type":"Point"}
}