{
  "type": "Feature",
  "properties": {
    "addr:full":"Shopping Center Des Bastions Tournai Hainaut 7500",
    "addr:postcode":"7500",
    "addr:street":"Shopping;Des Bastions;Hainaut",
    "iso:country":"BE",
    "sg:address":"Shopping Center Des Bastions",
    "sg:city":"Tournai",
    "sg:classifiers":[
        {
            "category":"Food & Beverages",
            "subcategory":"Specialty",
            "type":"Retail Goods"
        }
    ],
    "sg:phone":"+32 69 22 77 97",
    "sg:postcode":"7500",
    "sg:province":"Hainaut",
    "sg:tags":[
        "health",
        "dietary",
        "-",
        "biological"
    ],
    "wof:name":"Ligne Sant\u00e9",
    "wof:placetype":"venue"
},
  "geometry": {"coordinates":[3.4064559937,50.601600647],"type":"Point"}
}