{
  "type": "Feature",
  "properties": {
    "addr:full":"Brugsesteenweg 90 Roeselare West-Vlaanderen 8800",
    "addr:housenumber":"90",
    "addr:postcode":"8800",
    "addr:street":"Brugsesteenweg",
    "iso:country":"BE",
    "sg:address":"Brugsesteenweg 90",
    "sg:city":"Roeselare",
    "sg:orig_category":"Biblioth\u00e8ques and archives publiques",
    "sg:phone":"+32 51 23 63 66",
    "sg:postcode":"8800",
    "sg:province":"West-Vlaanderen",
    "wof:name":"Speel-o-theek Pipo",
    "wof:placetype":"venue"
},
  "geometry": {"coordinates":[3.1221129894,50.9538230896],"type":"Point"}
}