{
  "type": "Feature",
  "properties": {
    "iso:country":"BE",
    "sg:address":"Rue Du Sart Macr\u00e9 23",
    "sg:city":"Etalle (chantemelle)",
    "sg:classifiers":[
        {
            "category":"Building & Trades",
            "subcategory":"Landscaping Services",
            "type":"Services"
        }
    ],
    "sg:phone":"+32 63 45 55 18",
    "sg:postcode":"6742",
    "sg:province":"Luxembourg",
    "sg:tags":[
        "forestry"
    ],
    "wof:name":"Legendre G",
    "wof:placetype":"venue"
},
  "geometry": {"coordinates":[5.6465749741,49.6504936218],"type":"Point"}
}