{
  "type": "Feature",
  "properties": {
    "addr:full":"Geerhoek 24 Willebroek Antwerpen 2830",
    "addr:housenumber":"24",
    "addr:postcode":"2830",
    "addr:street":"Geerhoek",
    "iso:country":"BE",
    "sg:address":"Geerhoek 24",
    "sg:city":"Willebroek",
    "sg:orig_category":"Rundveehouders",
    "sg:phone":"+32 3 886 88 94",
    "sg:postcode":"2830",
    "sg:province":"Antwerpen",
    "wof:name":"Paul Van De Ven",
    "wof:placetype":"venue"
},
  "geometry": {"coordinates":[4.3741497993,51.0488090515],"type":"Point"}
}