{
  "type": "Feature",
  "properties": {
    "addr:full":"Boulevard D'ypres 80 Box 3 Bruxelles Bruxelles-Capitale 1000",
    "addr:housenumber":"80;3",
    "addr:postcode":"1000",
    "addr:street":"Boulevard D'Ypres;Box",
    "iso:country":"BE",
    "sg:address":"Boulevard D'ypres 80 Box 3",
    "sg:city":"Bruxelles",
    "sg:classifiers":[
        {
            "category":"Professional",
            "subcategory":"Lawyer & Legal Services",
            "type":"Services"
        }
    ],
    "sg:phone":"+32 2 223 45 26",
    "sg:postcode":"1000",
    "sg:province":"Bruxelles-Capitale",
    "wof:name":"Kalombo-kalonda Kalubi",
    "wof:placetype":"venue"
},
  "geometry": {"coordinates":[4.3463969231,50.8577156067],"type":"Point"}
}