{
  "type": "Feature",
  "properties": {
    "addr:full":"Slekkebeek 36 Wetteren Oost-Vlaanderen 9230",
    "addr:housenumber":"36",
    "addr:postcode":"9230",
    "addr:street":"Slekkebeek",
    "iso:country":"BE",
    "sg:address":"Slekkebeek 36",
    "sg:city":"Wetteren",
    "sg:orig_category":"Boekhouders",
    "sg:phone":"+32 9 366 05 85",
    "sg:postcode":"9230",
    "sg:province":"Oost-Vlaanderen",
    "wof:name":"Johan Troch",
    "wof:placetype":"venue"
},
  "geometry": {"coordinates":[3.8792340755,51.0206794739],"type":"Point"}
}