{
  "type": "Feature",
  "properties": {
    "iso:country":"BE",
    "sg:address":"Rue Fr\u00e9d\u00e9ric Pelletier 8a",
    "sg:city":"Bruxelles (schaerbeek)",
    "sg:classifiers":[
        {
            "category":"Communications",
            "subcategory":"News Services",
            "type":"Services"
        }
    ],
    "sg:phone":"+32 2 740 09 70",
    "sg:postcode":"1030",
    "sg:province":"Bruxelles-Capitale",
    "sg:tags":[
        "agency"
    ],
    "wof:name":"Mediargus",
    "wof:placetype":"venue"
},
  "geometry": {"coordinates":[4.3991098404,50.845451355],"type":"Point"}
}