{
  "type": "Feature",
  "properties": {
    "iso:country":"BE",
    "sg:address":"Rue De La Montagne 58-60",
    "sg:city":"Charleroi",
    "sg:classifiers":[
        {
            "category":"Shopping",
            "subcategory":"Beauty & Cosmetics",
            "type":"Retail Goods"
        }
    ],
    "sg:phone":"+32 71 50 66 43",
    "sg:postcode":"6000",
    "sg:province":"Hainaut",
    "sg:tags":[
        "-",
        "perfumery"
    ],
    "wof:name":"Kruidvat",
    "wof:placetype":"venue"
},
  "geometry": {"coordinates":[4.4430541992,50.4104652405],"type":"Point"}
}