{
  "type": "Feature",
  "properties": {
    "iso:country":"BE",
    "sg:address":".",
    "sg:city":"Bertrix",
    "sg:orig_category":"Sportterreinen and installaties behalve sportcentra",
    "sg:phone":"+32 61 41 23 12",
    "sg:postcode":"6880",
    "sg:province":"Luxembourg",
    "wof:name":"Piste les Maugires",
    "wof:placetype":"venue"
},
  "geometry": {"coordinates":[5.2535948753,49.8544845581],"type":"Point"}
}