{
  "type": "Feature",
  "properties": {
    "addr:full":"Avenue De Tervueren 403 Bruxelles (woluwe-saint-pierre) Bruxelles-Capitale 1150",
    "addr:housenumber":"403",
    "addr:postcode":"1150",
    "addr:street":"Avenue De Tervueren",
    "iso:country":"BE",
    "sg:address":"Avenue De Tervueren 403",
    "sg:city":"Bruxelles (woluwe-saint-pierre)",
    "sg:classifiers":[
        {
            "category":"Real Estate",
            "subcategory":"Real Estate Services",
            "type":"Services"
        }
    ],
    "sg:phone":"+32 2 772 16 89",
    "sg:postcode":"1150",
    "sg:province":"Bruxelles-Capitale",
    "wof:name":"Gelimob Sprl",
    "wof:placetype":"venue"
},
  "geometry": {"coordinates":[4.4072999954,50.8374786377],"type":"Point"}
}