{
  "type": "Feature",
  "properties": {
    "addr:full":"Frederik Burvenichstraat 115 Gent Oost-Vlaanderen 9050",
    "addr:housenumber":"115",
    "addr:postcode":"9050",
    "addr:street":"Frederik Burvenichstraat;Oost-Vlaanderen",
    "iso:country":"BE",
    "sg:address":"Frederik Burvenichstraat 115",
    "sg:city":"Gent",
    "sg:orig_category":"HERSTELLING ELEKTRISCHE HUISHOUDAPPARATEN Huishoudapparaten, televisies and radio's",
    "sg:phone":"+32 9 231 12 21",
    "sg:postcode":"9050",
    "sg:province":"Oost-Vlaanderen",
    "wof:name":"Jean-pierre Baete",
    "wof:placetype":"venue"
},
  "geometry": {"coordinates":[3.7542860508,51.040561676],"type":"Point"}
}