{
  "type": "Feature",
  "properties": {
    "iso:country":"BE",
    "sg:address":"Avenue De L'europe 21",
    "sg:city":"Florennes",
    "sg:classifiers":[
        {
            "category":"Professional",
            "subcategory":"Art Services",
            "type":"Services"
        }
    ],
    "sg:phone":"+32 71 68 77 54",
    "sg:postcode":"5620",
    "sg:province":"Namur",
    "sg:tags":[
        "photography",
        "reporting",
        "-"
    ],
    "wof:name":"Baudouin H",
    "wof:placetype":"venue"
},
  "geometry": {"coordinates":[4.6137800217,50.2648735046],"type":"Point"}
}