{
  "type": "Feature",
  "properties": {
    "iso:country":"BE",
    "sg:address":"Hoogstraat 9",
    "sg:city":"Oostrozebeke",
    "sg:orig_category":"Bloemen and planten",
    "sg:phone":"+32 56 66 96 89",
    "sg:postcode":"8780",
    "sg:province":"West-Vlaanderen",
    "wof:name":"Hilaire Allaert Koenraedt",
    "wof:placetype":"venue"
},
  "geometry": {"coordinates":[3.3338549137,50.9197616577],"type":"Point"}
}