{
  "type": "Feature",
  "properties": {
    "addr:full":"Kervijnstraat 89 Harelbeke (bavikhove) West-Vlaanderen 8531",
    "addr:housenumber":"89",
    "addr:postcode":"8531",
    "addr:street":"Kervijnstraat",
    "iso:country":"BE",
    "sg:address":"Kervijnstraat 89",
    "sg:city":"Harelbeke (bavikhove)",
    "sg:classifiers":[
        {
            "category":"Building & Trades",
            "subcategory":"Construction",
            "type":"Services"
        }
    ],
    "sg:phone":"+32 56 71 14 89",
    "sg:postcode":"8531",
    "sg:province":"West-Vlaanderen",
    "sg:tags":[
        "stucco",
        "contractor"
    ],
    "wof:name":"Jason's Plakwerken",
    "wof:placetype":"venue"
},
  "geometry": {"coordinates":[3.3198990822,50.8738822937],"type":"Point"}
}