{
  "type": "Feature",
  "properties": {
    "addr:full":"Rue Du Coll\u00c8ge 12 Ath Hainaut 7800",
    "addr:housenumber":"12",
    "addr:postcode":"7800",
    "addr:street":"Rue Du Colle\u0300Ge",
    "iso:country":"BE",
    "sg:address":"Rue Du Coll\u00c8ge 12",
    "sg:city":"Ath",
    "sg:orig_category":"Bagage and lederwaren",
    "sg:phone":"+32 68 28 73 02",
    "sg:postcode":"7800",
    "sg:province":"Hainaut",
    "wof:name":"Staelens",
    "wof:placetype":"venue"
},
  "geometry": {"coordinates":[3.7770500183,50.6287384033],"type":"Point"}
}