{
  "type": "Feature",
  "properties": {
    "addr:full":"Van Aastraat 36 Elsene/ixelles Bruxelles-Capitale 1050",
    "addr:housenumber":"36",
    "addr:postcode":"1050",
    "addr:street":"Van Aastraat",
    "iso:country":"BE",
    "sg:address":"Van Aastraat 36",
    "sg:city":"Elsene/ixelles",
    "sg:classifiers":[
        {
            "category":"Restaurant",
            "type":"Food & Drink"
        }
    ],
    "sg:phone":"+32 2 513 38 97",
    "sg:postcode":"1050",
    "sg:province":"Bruxelles-Capitale",
    "wof:name":"Le Vieil Ixelles",
    "wof:placetype":"venue"
},
  "geometry": {"coordinates":[4.3696417809,50.8332633972],"type":"Point"}
}