{
  "type": "Feature",
  "properties": {
    "addr:full":"Hernerweg 65 Hoeselt Limburg 3730",
    "addr:housenumber":"65",
    "addr:postcode":"3730",
    "addr:street":"Hernerweg",
    "iso:country":"BE",
    "sg:address":"Hernerweg 65",
    "sg:city":"Hoeselt",
    "sg:orig_category":"Voedingsspeciaalzaken",
    "sg:phone":"+32 12 26 36 34",
    "sg:postcode":"3730",
    "sg:province":"Limburg",
    "wof:name":"Traiteur Paulette",
    "wof:placetype":"venue"
},
  "geometry": {"coordinates":[5.4606699944,50.8218536377],"type":"Point"}
}