{
  "type": "Feature",
  "properties": {
    "addr:full":"Kloosterstraat 48 Bilzen Limburg 3740",
    "addr:housenumber":"48",
    "addr:postcode":"3740",
    "addr:street":"Kloosterstraat",
    "iso:country":"BE",
    "sg:address":"Kloosterstraat 48",
    "sg:city":"Bilzen",
    "sg:orig_category":"Dameskledingzaken",
    "sg:phone":"+32 89 49 17 27",
    "sg:postcode":"3740",
    "sg:province":"Limburg",
    "wof:name":"Hilde Kleding",
    "wof:placetype":"venue"
},
  "geometry": {"coordinates":[5.5187339783,50.8721084595],"type":"Point"}
}