{
  "type": "Feature",
  "properties": {
    "addr:full":"Koekoekstraat 12bb Nijlen Antwerpen 2560",
    "addr:housenumber":"12bb",
    "addr:postcode":"2560",
    "addr:street":"Koekoekstraat",
    "iso:country":"BE",
    "sg:address":"Koekoekstraat 12bb",
    "sg:city":"Nijlen",
    "sg:orig_category":"Animaux domestiques and accessoires. Eleveurs d'animaux domestiques",
    "sg:phone":"+32 3 411 02 73",
    "sg:postcode":"2560",
    "sg:province":"Antwerpen",
    "wof:name":"Little Fantasy",
    "wof:placetype":"venue"
},
  "geometry": {"coordinates":[4.6856760979,51.1641921997],"type":"Point"}
}