{
  "type": "Feature",
  "properties": {
    "addr:full":"Dorp 84 Ravels Antwerpen 2382",
    "addr:housenumber":"84",
    "addr:postcode":"2382",
    "addr:street":"Dorp",
    "iso:country":"BE",
    "sg:address":"Dorp 84",
    "sg:city":"Ravels",
    "sg:orig_category":"Postkantoren Verzekeringsmakelaars and experts",
    "sg:phone":"+32 14 65 53 32",
    "sg:postcode":"2382",
    "sg:province":"Antwerpen",
    "wof:name":"De Post",
    "wof:placetype":"venue"
},
  "geometry": {"coordinates":[5.041768074,51.4469108582],"type":"Point"}
}