{
  "type": "Feature",
  "properties": {
    "iso:country":"BE",
    "sg:address":"Rue Du Petit Crespin 10bis",
    "sg:city":"Bernissart (pommeroeul)",
    "sg:classifiers":[
        {
            "category":"Building & Trades",
            "subcategory":"Pest Control",
            "type":"Services"
        }
    ],
    "sg:phone":"+32 65 52 02 03",
    "sg:postcode":"7322",
    "sg:province":"Hainaut",
    "sg:tags":[
        "painting",
        "contractor"
    ],
    "wof:name":"A B C Color",
    "wof:placetype":"venue"
},
  "geometry": {"coordinates":[3.7132179737,50.4580612183],"type":"Point"}
}