{
  "type": "Feature",
  "properties": {
    "addr:full":"Kapellestraat 9ba Evergem Oost-Vlaanderen 9940",
    "addr:housenumber":"9ba",
    "addr:postcode":"9940",
    "addr:street":"Kapellestraat;Oost-Vlaanderen",
    "iso:country":"BE",
    "sg:address":"Kapellestraat 9ba",
    "sg:city":"Evergem",
    "sg:orig_category":"Apotheken",
    "sg:phone":"+32 9 253 17 80",
    "sg:postcode":"9940",
    "sg:province":"Oost-Vlaanderen",
    "wof:name":"Claudine Van De Velde",
    "wof:placetype":"venue"
},
  "geometry": {"coordinates":[3.7096669674,51.109954834],"type":"Point"}
}