{
  "type": "Feature",
  "properties": {
    "addr:full":"Nederzwalmsesteenweg 1 Zingem Oost-Vlaanderen 9750",
    "addr:housenumber":"1",
    "addr:postcode":"9750",
    "addr:street":"Nederzwalmsesteenweg;Oost-Vlaanderen",
    "iso:country":"BE",
    "sg:address":"Nederzwalmsesteenweg 1",
    "sg:city":"Zingem",
    "sg:orig_category":"Verplichte sociale verzekeringen",
    "sg:phone":"+32 9 384 18 17",
    "sg:postcode":"9750",
    "sg:province":"Oost-Vlaanderen",
    "wof:name":"Christelijke Mutualiteit",
    "wof:placetype":"venue"
},
  "geometry": {"coordinates":[3.6539399624,50.9012794495],"type":"Point"}
}