{
  "type": "Feature",
  "properties": {
    "iso:country":"BE",
    "sg:address":"Fosselstraat 19bc",
    "sg:city":"Affligem",
    "sg:orig_category":"Alimentation sp\u00e9cialis\u00e9e",
    "sg:phone":"+32 53 66 84 93",
    "sg:postcode":"1790",
    "sg:province":"Vlaams-Brabant",
    "wof:name":"Traiteur Rik",
    "wof:placetype":"venue"
},
  "geometry": {"coordinates":[4.1134848595,50.9186325073],"type":"Point"}
}