{
  "type": "Feature",
  "properties": {
    "addr:full":"Diesterstraat 159 Tessenderlo Limburg 3980",
    "addr:housenumber":"159",
    "addr:postcode":"3980",
    "addr:street":"Diesterstraat",
    "iso:country":"BE",
    "sg:address":"Diesterstraat 159",
    "sg:city":"Tessenderlo",
    "sg:classifiers":[
        {
            "category":"Farming",
            "subcategory":"Livestock Farm",
            "type":"Manufacturing & Wholesale Goods"
        }
    ],
    "sg:phone":"+32 13 66 11 85",
    "sg:postcode":"3980",
    "sg:province":"Limburg",
    "sg:tags":[
        "buyer"
    ],
    "wof:name":"Vervoort-vandeweyer J",
    "wof:placetype":"venue"
},
  "geometry": {"coordinates":[5.0881881714,51.05493927],"type":"Point"}
}