{
  "type": "Feature",
  "properties": {
    "addr:full":"Molenstraat 139 Lokeren Oost-Vlaanderen 9160",
    "addr:housenumber":"139",
    "addr:postcode":"9160",
    "addr:street":"Molenstraat",
    "iso:country":"BE",
    "sg:address":"Molenstraat 139",
    "sg:city":"Lokeren",
    "sg:classifiers":[
        {
            "category":"Education",
            "subcategory":"Dance Studio",
            "type":"Public Place"
        }
    ],
    "sg:phone":"+32 9 348 09 11",
    "sg:postcode":"9160",
    "sg:province":"Oost-Vlaanderen",
    "sg:tags":[
        "ballet",
        "school"
    ],
    "wof:name":"Aurora",
    "wof:placetype":"venue"
},
  "geometry": {"coordinates":[3.9970738888,51.09948349],"type":"Point"}
}