{
  "type": "Feature",
  "properties": {
    "iso:country":"BE",
    "sg:address":"Avenue R\u00cave D'or 1",
    "sg:city":"La Louviere",
    "sg:orig_category":"Biblioth\u00e8ques and archives publiques",
    "sg:phone":"+32 64 22 66 29",
    "sg:postcode":"7100",
    "sg:province":"Hainaut",
    "wof:name":"Centrale Provinciale Du Hainaut",
    "wof:placetype":"venue"
},
  "geometry": {"coordinates":[4.171020031,50.4790992737],"type":"Point"}
}