{
  "type": "Feature",
  "properties": {
    "addr:full":"Lange Kievitstraat 140-142 Antwerpen Antwerpen 2018",
    "addr:postcode":"140-142;2018",
    "addr:street":"Lange Kievitstraat",
    "iso:country":"BE",
    "sg:address":"Lange Kievitstraat 140-142",
    "sg:city":"Antwerpen",
    "sg:classifiers":[
        {
            "category":"Food & Beverages",
            "subcategory":"Groceries & Convenience Stores",
            "type":"Retail Goods"
        }
    ],
    "sg:phone":"+32 3 226 26 29",
    "sg:postcode":"2018",
    "sg:province":"Antwerpen",
    "sg:tags":[
        "grocer"
    ],
    "wof:name":"Oriental Garden Bvba",
    "wof:placetype":"venue"
},
  "geometry": {"coordinates":[4.4256558418,51.2136192322],"type":"Point"}
}