{
  "type": "Feature",
  "properties": {
    "addr:full":"Nijvelsebaan 19 Bertem Vlaams-Brabant 3060",
    "addr:housenumber":"19",
    "addr:postcode":"3060",
    "addr:street":"Nijvelsebaan",
    "iso:country":"BE",
    "sg:address":"Nijvelsebaan 19",
    "sg:city":"Bertem",
    "sg:classifiers":[
        {
            "category":"Arena",
            "subcategory":"Sports Club",
            "type":"Entertainment"
        }
    ],
    "sg:phone":"+32 16 47 33 53",
    "sg:postcode":"3060",
    "sg:province":"Vlaams-Brabant",
    "sg:tags":[
        "de"
    ],
    "wof:name":"Wakou",
    "wof:placetype":"venue"
},
  "geometry": {"coordinates":[4.6469478607,50.8468971252],"type":"Point"}
}