{
  "type": "Feature",
  "properties": {
    "addr:full":"Hakkeveldstraat 6 Alken Limburg 3570",
    "addr:housenumber":"6",
    "addr:postcode":"3570",
    "addr:street":"Hakkeveldstraat",
    "iso:country":"BE",
    "sg:address":"Hakkeveldstraat 6",
    "sg:city":"Alken",
    "sg:classifiers":[
        {
            "category":"Personal",
            "subcategory":"Nail Salon",
            "type":"Services"
        }
    ],
    "sg:phone":"+32 11 31 61 24",
    "sg:postcode":"3570",
    "sg:province":"Limburg",
    "sg:tags":[
        "pedicure"
    ],
    "wof:name":"Sonja",
    "wof:placetype":"venue"
},
  "geometry": {"coordinates":[5.3157629967,50.8794021606],"type":"Point"}
}