{
  "type": "Feature",
  "properties": {
    "addr:full":"Generaal De Gaullelaan 50 Elsene/ixelles Bruxelles-Capitale 1050",
    "addr:housenumber":"50",
    "addr:postcode":"1050",
    "addr:street":"Generaal De Gaullelaan",
    "iso:country":"BE",
    "sg:address":"Generaal De Gaullelaan 50",
    "sg:city":"Elsene/ixelles",
    "sg:orig_category":"Binnenhuisarchitecten",
    "sg:phone":"+32 2 648 44 13",
    "sg:postcode":"1050",
    "sg:province":"Bruxelles-Capitale",
    "wof:name":"J. Dewindt",
    "wof:placetype":"venue"
},
  "geometry": {"coordinates":[4.3731889725,50.8225631714],"type":"Point"}
}