{
  "type": "Feature",
  "properties": {
    "iso:country":"BE",
    "sg:address":"Pont De La Warche 2",
    "sg:city":"Malmedy",
    "sg:orig_category":"D\u00e9corateurs d'int\u00e9rieur. Rev\u00eatements de sols and murs. Magasins sp\u00e9cialis\u00e9s. Rev\u00eatements pour sols a",
    "sg:phone":"+32 78 71 90 39",
    "sg:postcode":"4960",
    "sg:province":"Li\u00e8ge",
    "wof:name":"Kohnen Malmedy",
    "wof:placetype":"venue"
},
  "geometry": {"coordinates":[6.0241961479,50.4284172058],"type":"Point"}
}