{
  "type": "Feature",
  "properties": {
    "iso:country":"BE",
    "sg:address":"Rue Conrad D'argenteau 8",
    "sg:city":"Sombreffe (ligny)",
    "sg:classifiers":[
        {
            "category":"Building & Trades",
            "subcategory":"Construction",
            "type":"Services"
        }
    ],
    "sg:phone":"+32 71 88 65 45",
    "sg:postcode":"5140",
    "sg:province":"Namur",
    "sg:tags":[
        "carpenter"
    ],
    "wof:name":"Ch\u00e2ssis Erem Scrl",
    "wof:placetype":"venue"
},
  "geometry": {"coordinates":[4.57523489,50.5163650513],"type":"Point"}
}