{
  "type": "Feature",
  "properties": {
    "iso:country":"BE",
    "sg:address":"Avenue De La Chasse 36",
    "sg:city":"Etterbeek/etterbeek",
    "sg:orig_category":"M\u00e9decins and sp\u00e9cialistes",
    "sg:phone":"+32 2 640 13 75",
    "sg:postcode":"1040",
    "sg:province":"Bruxelles-Capitale",
    "wof:name":"Mokhtar Mourabit",
    "wof:placetype":"venue"
},
  "geometry": {"coordinates":[4.390704155,50.8314971924],"type":"Point"}
}