{
  "type": "Feature",
  "properties": {
    "iso:country":"BE",
    "sg:address":"Route De Pr\u00e9aix 13",
    "sg:city":"Malmedy",
    "sg:classifiers":[
        {
            "category":"Building & Trades",
            "subcategory":"Landscaping Services",
            "type":"Services"
        }
    ],
    "sg:phone":"+32 495 81 94 96",
    "sg:postcode":"4960",
    "sg:province":"Li\u00e8ge",
    "sg:tags":[
        "gardening",
        "garden",
        "maintenance"
    ],
    "wof:name":"Schaff F",
    "wof:placetype":"venue"
},
  "geometry": {"coordinates":[6.0426259041,50.4197311401],"type":"Point"}
}