{
  "type": "Feature",
  "properties": {
    "iso:country":"BE",
    "sg:address":"Rue Paul Henri Spaak 1",
    "sg:city":"Peruwelz",
    "sg:classifiers":[
        {
            "category":"Personal",
            "subcategory":"Beauty Salon",
            "type":"Services"
        }
    ],
    "sg:phone":"+32 69 77 60 79",
    "sg:postcode":"7608",
    "sg:province":"Hainaut",
    "sg:tags":[
        "de",
        "coiffure"
    ],
    "wof:name":"Jasmine Wickaert",
    "wof:placetype":"venue"
},
  "geometry": {"coordinates":[3.5355861187,50.5056648254],"type":"Point"}
}