{
  "type": "Feature",
  "properties": {
    "addr:full":"Kramersplein 5 Gent Oost-Vlaanderen 9000",
    "addr:housenumber":"5",
    "addr:postcode":"9000",
    "addr:street":"Kramersplein;Oost-Vlaanderen",
    "iso:country":"BE",
    "sg:address":"Kramersplein 5",
    "sg:city":"Gent",
    "sg:classifiers":[
        {
            "category":"Manufacturing",
            "subcategory":"Printing",
            "type":"Manufacturing & Wholesale Goods"
        }
    ],
    "sg:phone":"+32 9 220 58 36",
    "sg:postcode":"9000",
    "sg:province":"Oost-Vlaanderen",
    "sg:tags":[
        "textile",
        "-"
    ],
    "wof:name":"Quality Colors",
    "wof:placetype":"venue"
},
  "geometry": {"coordinates":[3.7259709835,51.0414123535],"type":"Point"}
}