{
  "type": "Feature",
  "properties": {
    "iso:country":"BE",
    "sg:address":"Bergstraat 32",
    "sg:city":"Hamme",
    "sg:orig_category":"Produits chimiques Gr",
    "sg:phone":"+32 13 61 12 11",
    "sg:postcode":"3945",
    "sg:province":"Limburg",
    "wof:name":"Tessenderlo Chemie",
    "wof:placetype":"venue"
},
  "geometry": {"coordinates":[5.1776199341,51.1046104431],"type":"Point"}
}