{
  "type": "Feature",
  "properties": {
    "addr:full":"Brusselsesteenweg 137 Ninove Oost-Vlaanderen 9400",
    "addr:housenumber":"137",
    "addr:postcode":"9400",
    "addr:street":"Brusselsesteenweg",
    "iso:country":"BE",
    "sg:address":"Brusselsesteenweg 137",
    "sg:city":"Ninove",
    "sg:classifiers":[
        {
            "category":"Shopping",
            "subcategory":"Computers & Home Electronics",
            "type":"Retail Goods"
        }
    ],
    "sg:phone":"+32 54 33 29 57",
    "sg:postcode":"9400",
    "sg:province":"Oost-Vlaanderen",
    "sg:tags":[
        "-",
        "television",
        "radio"
    ],
    "wof:name":"Vanderpijpen Electro Market Nv",
    "wof:placetype":"venue"
},
  "geometry": {"coordinates":[4.0288901329,50.8283500671],"type":"Point"}
}