{
  "type": "Feature",
  "properties": {
    "addr:full":"Motje 23 Zomergem Oost-Vlaanderen 9930",
    "addr:housenumber":"23",
    "addr:postcode":"9930",
    "addr:street":"Motje",
    "iso:country":"BE",
    "sg:address":"Motje 23",
    "sg:city":"Zomergem",
    "sg:classifiers":[
        {
            "category":"Home & Garden",
            "subcategory":"Carpets & Floor Coverings",
            "type":"Retail Goods"
        }
    ],
    "sg:phone":"+32 9 372 76 95",
    "sg:postcode":"9930",
    "sg:province":"Oost-Vlaanderen",
    "sg:tags":[
        "layer",
        "mosaicists"
    ],
    "wof:name":"Van Speybroeck I",
    "wof:placetype":"venue"
},
  "geometry": {"coordinates":[3.5721731186,51.1176643372],"type":"Point"}
}