{
  "type": "Feature",
  "properties": {
    "iso:country":"BE",
    "sg:address":"Daalmstraat 4",
    "sg:city":"Zomergem (ronsele)",
    "sg:classifiers":[
        {
            "category":"Building & Trades",
            "subcategory":"Construction",
            "type":"Services"
        }
    ],
    "sg:phone":"+32 9 372 68 71",
    "sg:postcode":"9932",
    "sg:province":"Oost-Vlaanderen",
    "sg:tags":[
        "carpenter"
    ],
    "wof:name":"De Poorter R",
    "wof:placetype":"venue"
},
  "geometry": {"coordinates":[3.5526299477,51.126121521],"type":"Point"}
}