{
  "type": "Feature",
  "properties": {
    "iso:country":"BE",
    "sg:address":"Rue De La Bruy\u00e8re 16",
    "sg:city":"Bruxelles (schaerbeek)",
    "sg:classifiers":[
        {
            "category":"Professional",
            "subcategory":"Secretarial Services",
            "type":"Services"
        }
    ],
    "sg:phone":"+32 2 245 65 25",
    "sg:postcode":"1030",
    "sg:province":"Bruxelles-Capitale",
    "sg:tags":[
        "firm"
    ],
    "wof:name":"Aguirre M-i",
    "wof:placetype":"venue"
},
  "geometry": {"coordinates":[4.3880991936,50.875213623],"type":"Point"}
}