{
  "type": "Feature",
  "properties": {
    "addr:full":"Heuvelstraat 107 Boechout Antwerpen 2530",
    "addr:housenumber":"107",
    "addr:postcode":"2530",
    "addr:street":"Heuvelstraat",
    "iso:country":"BE",
    "sg:address":"Heuvelstraat 107",
    "sg:city":"Boechout",
    "sg:classifiers":[
        {
            "category":"Real Estate",
            "subcategory":"Architect",
            "type":"Services"
        }
    ],
    "sg:phone":"+32 3 454 50 13",
    "sg:postcode":"2530",
    "sg:province":"Antwerpen",
    "wof:name":"Van Geet B",
    "wof:placetype":"venue"
},
  "geometry": {"coordinates":[4.4987668991,51.1640586853],"type":"Point"}
}