{
  "type": "Feature",
  "properties": {
    "addr:full":"Ruelle Dieu De Giblot 2 Leuze-en-hainaut Hainaut 7900",
    "addr:housenumber":"2",
    "addr:postcode":"7900",
    "addr:street":"Ruelle Dieu De Giblot",
    "iso:country":"BE",
    "sg:address":"Ruelle Dieu De Giblot 2",
    "sg:city":"Leuze-en-hainaut",
    "sg:classifiers":[
        {
            "category":"Real Estate",
            "subcategory":"Architect",
            "type":"Services"
        }
    ],
    "sg:phone":"+32 69 66 22 48",
    "sg:postcode":"7900",
    "sg:province":"Hainaut",
    "wof:name":"Delcourt Jl",
    "wof:placetype":"venue"
},
  "geometry": {"coordinates":[3.6237239838,50.596370697],"type":"Point"}
}