{
  "type": "Feature",
  "properties": {
    "addr:full":"De Keyserhoeve 14 Antwerpen Antwerpen 2040",
    "addr:housenumber":"14",
    "addr:postcode":"2040",
    "addr:street":"De Keyserhoeve",
    "iso:country":"BE",
    "sg:address":"De Keyserhoeve 14",
    "sg:city":"Antwerpen",
    "sg:classifiers":[
        {
            "category":"Travel",
            "subcategory":"Hotels & Motels",
            "type":"Entertainment"
        }
    ],
    "sg:phone":"+32 3 568 99 00",
    "sg:postcode":"2040",
    "sg:province":"Antwerpen",
    "sg:tags":[
        "restaurant"
    ],
    "wof:name":"Vredehof",
    "wof:placetype":"venue"
},
  "geometry": {"coordinates":[4.3141150475,51.3429756165],"type":"Point"}
}