{
  "type": "Feature",
  "properties": {
    "addr:full":"Alfred Amelotstraat 53 Zingem Oost-Vlaanderen 9750",
    "addr:housenumber":"53",
    "addr:postcode":"9750",
    "addr:street":"Amelotstraat;Oost-Vlaanderen",
    "iso:country":"BE",
    "sg:address":"Alfred Amelotstraat 53",
    "sg:city":"Zingem",
    "sg:classifiers":[
        {
            "category":"Government",
            "subcategory":"Police Station",
            "type":"Public Place"
        }
    ],
    "sg:phone":"+32 9 384 27 21",
    "sg:postcode":"9750",
    "sg:province":"Oost-Vlaanderen",
    "sg:tags":[
        "gendarmerie"
    ],
    "wof:name":"Federale Politie",
    "wof:placetype":"venue"
},
  "geometry": {"coordinates":[3.652944088,50.9070510864],"type":"Point"}
}