{
  "type": "Feature",
  "properties": {
    "addr:full":"Route De Ch\u00e2telet 267 Charleroi (couillet) Hainaut 6010",
    "addr:housenumber":"267",
    "addr:postcode":"6010",
    "addr:street":"Route De Cha\u0302Telet",
    "iso:country":"BE",
    "sg:address":"Route De Ch\u00e2telet 267",
    "sg:city":"Charleroi (couillet)",
    "sg:classifiers":[
        {
            "category":"Bars & Pubs",
            "type":"Food & Drink"
        }
    ],
    "sg:phone":"+32 71 47 73 65",
    "sg:postcode":"6010",
    "sg:province":"Hainaut",
    "wof:name":"Armes De Diekirch (aux)",
    "wof:placetype":"venue"
},
  "geometry": {"coordinates":[4.4654450417,50.3922805786],"type":"Point"}
}