{
  "type": "Feature",
  "properties": {
    "iso:country":"BE",
    "sg:address":"Nijverheidsstraat 1",
    "sg:city":"Ardooie",
    "sg:classifiers":[
        {
            "category":"Utilities",
            "subcategory":"Natural Gas",
            "type":"Services"
        }
    ],
    "sg:phone":"+32 51 46 51 92",
    "sg:postcode":"8850",
    "sg:province":"West-Vlaanderen",
    "sg:tags":[
        "baking",
        "oven"
    ],
    "wof:name":"International Coating Machines Nv",
    "wof:placetype":"venue"
},
  "geometry": {"coordinates":[3.2389740944,50.9780044556],"type":"Point"}
}