{
  "type": "Feature",
  "properties": {
    "addr:full":"Avenue Monbijou 65 Malmedy Li\u00e8ge 4960",
    "addr:housenumber":"65",
    "addr:postcode":"4960",
    "addr:street":"Avenue Monbijou",
    "iso:country":"BE",
    "sg:address":"Avenue Monbijou 65",
    "sg:city":"Malmedy",
    "sg:classifiers":[
        {
            "category":"Bars & Pubs",
            "type":"Food & Drink"
        }
    ],
    "sg:phone":"+32 80 33 02 87",
    "sg:postcode":"4960",
    "sg:province":"Li\u00e8ge",
    "wof:name":"Vieux Moulin (caf\u00e9 Du)",
    "wof:placetype":"venue"
},
  "geometry": {"coordinates":[6.0403170586,50.4215507507],"type":"Point"}
}