{
  "type": "Feature",
  "properties": {
    "addr:full":"Rue De L'embarcad\u00e8re 46 Chiny Luxembourg 6810",
    "addr:housenumber":"46",
    "addr:postcode":"6810",
    "addr:street":"Rue De L'Embarcade \u0300Re",
    "iso:country":"BE",
    "sg:address":"Rue De L'embarcad\u00e8re 46",
    "sg:city":"Chiny",
    "sg:classifiers":[
        {
            "category":"Building & Trades",
            "subcategory":"Landscaping Services",
            "type":"Services"
        }
    ],
    "sg:phone":"+32 61 32 00 95",
    "sg:postcode":"6810",
    "sg:province":"Luxembourg",
    "sg:tags":[
        "forestry"
    ],
    "wof:name":"Genin V",
    "wof:placetype":"venue"
},
  "geometry": {"coordinates":[5.3316287994,49.7379646301],"type":"Point"}
}