{
  "type": "Feature",
  "properties": {
    "addr:full":"Rue Trieu Gossiaux 67 Fleurus Hainaut 6224",
    "addr:housenumber":"67",
    "addr:postcode":"6224",
    "addr:street":"Rue Trieu Gossiaux",
    "iso:country":"BE",
    "sg:address":"Rue Trieu Gossiaux 67",
    "sg:city":"Fleurus",
    "sg:classifiers":[
        {
            "category":"Food & Beverages",
            "subcategory":"Meat & Fish",
            "type":"Retail Goods"
        }
    ],
    "sg:phone":"+32 71 81 96 54",
    "sg:postcode":"6224",
    "sg:province":"Hainaut",
    "sg:tags":[
        "vi",
        "zeevruchten"
    ],
    "wof:name":"Yves Collin",
    "wof:placetype":"venue"
},
  "geometry": {"coordinates":[4.5819687843,50.4642372131],"type":"Point"}
}