{
  "type": "Feature",
  "properties": {
    "iso:country":"BE",
    "sg:address":"Rue D'eghez\u00c9e 4",
    "sg:city":"Sambreville",
    "sg:orig_category":"Babyspullen",
    "sg:phone":"+32 71 77 17 52",
    "sg:postcode":"5060",
    "sg:province":"Namur",
    "wof:name":"Palais De L'enfant",
    "wof:placetype":"venue"
},
  "geometry": {"coordinates":[4.6347870827,50.4462928772],"type":"Point"}
}