{
  "type": "Feature",
  "properties": {
    "addr:full":"Kapelstraat 167 Schelle Antwerpen 2627",
    "addr:housenumber":"167",
    "addr:postcode":"2627",
    "addr:street":"Kapelstraat",
    "iso:country":"BE",
    "sg:address":"Kapelstraat 167",
    "sg:city":"Schelle",
    "sg:orig_category":"Producteurs de l\u00e9gumes",
    "sg:phone":"+32 3 887 99 51",
    "sg:postcode":"2627",
    "sg:province":"Antwerpen",
    "wof:name":"Jozef Van Den Bergh",
    "wof:placetype":"venue"
},
  "geometry": {"coordinates":[4.3288598061,51.1219367981],"type":"Point"}
}