{
  "type": "Feature",
  "properties": {
    "iso:country":"BE",
    "sg:address":"Vlaamsekaai 52",
    "sg:city":"Antwerpen",
    "sg:classifiers":[
        {
            "category":"Restaurant",
            "type":"Food & Drink"
        }
    ],
    "sg:phone":"+32 3 238 04 49",
    "sg:postcode":"2000",
    "sg:province":"Antwerpen",
    "wof:name":"Verdi",
    "wof:placetype":"venue"
},
  "geometry": {"coordinates":[4.3899459839,51.2089424133],"type":"Point"}
}