{
  "type": "Feature",
  "properties": {
    "iso:country":"BE",
    "sg:address":"Rue Sinton 26",
    "sg:city":"Fosses-la-ville",
    "sg:classifiers":[
        {
            "category":"Utilities",
            "subcategory":"Fuel Oil & Lpg",
            "type":"Services"
        }
    ],
    "sg:phone":"+32 71 71 10 46",
    "sg:postcode":"5070",
    "sg:province":"Namur",
    "wof:name":"Debehogne-effinier Sprl",
    "wof:placetype":"venue"
},
  "geometry": {"coordinates":[4.7027602196,50.3975639343],"type":"Point"}
}