{
  "type": "Feature",
  "properties": {
    "iso:country":"BE",
    "sg:address":"Ijzerlei 9",
    "sg:city":"Leopoldsburg",
    "sg:orig_category":"Avocats and conseillers juridiques",
    "sg:phone":"+32 11 34 30 32",
    "sg:postcode":"3970",
    "sg:province":"Limburg",
    "wof:name":"Roland Vaes",
    "wof:placetype":"venue"
},
  "geometry": {"coordinates":[5.256937027,51.1166419983],"type":"Point"}
}