{
  "type": "Feature",
  "properties": {
    "addr:full":"Fond Del'm\u00c9 3 Jodoigne Brabant Wallon 1370",
    "addr:housenumber":"3",
    "addr:postcode":"1370",
    "addr:street":"\u0301",
    "iso:country":"BE",
    "sg:address":"Fond Del'm\u00c9 3",
    "sg:city":"Jodoigne",
    "sg:orig_category":"Diensten voor huisdieren",
    "sg:phone":"+32 10 81 13 75",
    "sg:postcode":"1370",
    "sg:province":"Brabant Wallon",
    "wof:name":"La Maison \u00c0 Chats",
    "wof:placetype":"venue"
},
  "geometry": {"coordinates":[4.8314380646,50.7414245605],"type":"Point"}
}