{
  "type": "Feature",
  "properties": {
    "iso:country":"BE",
    "sg:address":"Blauwe Kei 48",
    "sg:city":"Lommel",
    "sg:classifiers":[
        {
            "category":"Restaurant",
            "type":"Food & Drink"
        }
    ],
    "sg:phone":"+32 11 54 46 50",
    "sg:postcode":"3920",
    "sg:province":"Limburg",
    "wof:name":"Ribhouse De 7 Heerlijkheden",
    "wof:placetype":"venue"
},
  "geometry": {"coordinates":[5.2239742279,51.2373695374],"type":"Point"}
}