{
  "type": "Feature",
  "properties": {
    "iso:country":"BE",
    "sg:address":"Rue De Bruxelles 15",
    "sg:city":"Genappe",
    "sg:classifiers":[
        {
            "category":"Shopping",
            "subcategory":"Books",
            "type":"Retail Goods"
        }
    ],
    "sg:phone":"+32 67 77 23 76",
    "sg:postcode":"1470",
    "sg:province":"Brabant Wallon",
    "sg:tags":[
        "bookseller"
    ],
    "wof:name":"Apostrophe (l')",
    "wof:placetype":"venue"
},
  "geometry": {"coordinates":[4.4505639076,50.6113204956],"type":"Point"}
}