{
  "type": "Feature",
  "properties": {
    "iso:country":"BE",
    "sg:address":"Rue De L\u00b4elevage 26",
    "sg:city":"Ottignies-louvain-la-neuve",
    "sg:orig_category":"Installation de menuiserie en bois and plastique",
    "sg:phone":"+32 10 45 25 88",
    "sg:postcode":"1340",
    "sg:province":"Brabant Wallon",
    "wof:name":"Andrea Cocito",
    "wof:placetype":"venue"
},
  "geometry": {"coordinates":[4.5991678238,50.6594161987],"type":"Point"}
}