{
  "type": "Feature",
  "properties": {
    "addr:full":"Wolvenstraat 26 Diest Vlaams-Brabant 3290",
    "addr:housenumber":"26",
    "addr:postcode":"3290",
    "addr:street":"Wolvenstraat",
    "iso:country":"BE",
    "sg:address":"Wolvenstraat 26",
    "sg:city":"Diest",
    "sg:classifiers":[
        {
            "category":"Health Services",
            "subcategory":"Dentist",
            "type":"Services"
        }
    ],
    "sg:phone":"+32 13 31 15 48",
    "sg:postcode":"3290",
    "sg:province":"Vlaams-Brabant",
    "wof:name":"Lambrechts J",
    "wof:placetype":"venue"
},
  "geometry": {"coordinates":[5.0537400246,50.9832229614],"type":"Point"}
}