{
  "type": "Feature",
  "properties": {
    "addr:full":"Rue Martin Sandron 67 Doische Namur 5680",
    "addr:housenumber":"67",
    "addr:postcode":"5680",
    "addr:street":"Rue Martin Sandron",
    "iso:country":"BE",
    "sg:address":"Rue Martin Sandron 67",
    "sg:city":"Doische",
    "sg:classifiers":[
        {
            "category":"Building & Trades",
            "subcategory":"Construction",
            "type":"Services"
        }
    ],
    "sg:phone":"+32 82 67 76 05",
    "sg:postcode":"5680",
    "sg:province":"Namur",
    "sg:tags":[
        "carpenter"
    ],
    "wof:name":"Chabot R",
    "wof:placetype":"venue"
},
  "geometry": {"coordinates":[4.752655983,50.1388511658],"type":"Point"}
}