{
  "type": "Feature",
  "properties": {
    "addr:full":"Stationstraat 207 Ardooie West-Vlaanderen 8850",
    "addr:housenumber":"207",
    "addr:postcode":"8850",
    "addr:street":"Stationstraat",
    "iso:country":"BE",
    "sg:address":"Stationstraat 207",
    "sg:city":"Ardooie",
    "sg:classifiers":[
        {
            "category":"Restaurant",
            "type":"Food & Drink"
        }
    ],
    "sg:phone":"+32 51 74 66 77",
    "sg:postcode":"8850",
    "sg:province":"West-Vlaanderen",
    "wof:name":"De Mythe",
    "wof:placetype":"venue"
},
  "geometry": {"coordinates":[3.2039558887,50.9898109436],"type":"Point"}
}