{
  "type": "Feature",
  "properties": {
    "iso:country":"BE",
    "sg:address":"Wettersesteenweg 104",
    "sg:city":"Sint-lievens-houtem",
    "sg:classifiers":[
        {
            "category":"Banks & Credit Unions",
            "subcategory":"Bureau De Change",
            "type":"Services"
        }
    ],
    "sg:phone":"+32 9 363 93 36",
    "sg:postcode":"9520",
    "sg:province":"Oost-Vlaanderen",
    "sg:tags":[
        "melting",
        "grease",
        "-"
    ],
    "wof:name":"Cominbel Nv",
    "wof:placetype":"venue"
},
  "geometry": {"coordinates":[3.856044054,50.9318351746],"type":"Point"}
}