{
  "type": "Feature",
  "properties": {
    "iso:country":"BE",
    "sg:address":"Nonnendijk 1",
    "sg:city":"Damme",
    "sg:orig_category":"Eleveurs and marchands de porcs",
    "sg:phone":"+32 50 50 08 45",
    "sg:postcode":"8340",
    "sg:province":"West-Vlaanderen",
    "wof:name":"Geert Dupon",
    "wof:placetype":"venue"
},
  "geometry": {"coordinates":[3.3761160374,51.2664756775],"type":"Point"}
}