{
  "type": "Feature",
  "properties": {
    "addr:full":"Quai Aux Briques 48 Bruxelles Bruxelles-Capitale 1000",
    "addr:housenumber":"48",
    "addr:postcode":"1000",
    "addr:street":"Quai Aux Briques",
    "iso:country":"BE",
    "sg:address":"Quai Aux Briques 48",
    "sg:city":"Bruxelles",
    "sg:classifiers":[
        {
            "category":"Wholesale",
            "subcategory":"Seafood",
            "type":"Manufacturing & Wholesale Goods"
        }
    ],
    "sg:phone":"+32 2 512 85 25",
    "sg:postcode":"1000",
    "sg:province":"Bruxelles-Capitale",
    "sg:tags":[
        "whol",
        "fish",
        "-",
        "shellfish"
    ],
    "wof:name":"Segers-soetens Sprl",
    "wof:placetype":"venue"
},
  "geometry": {"coordinates":[4.3472671509,50.8522186279],"type":"Point"}
}