{
  "type": "Feature",
  "properties": {
    "addr:full":"Prinsenweg 10 Tongeren Limburg 3700",
    "addr:housenumber":"10",
    "addr:postcode":"3700",
    "addr:street":"Prinsenweg",
    "iso:country":"BE",
    "sg:address":"Prinsenweg 10",
    "sg:city":"Tongeren",
    "sg:orig_category":"Ladies' Shoes",
    "sg:phone":"+32 12 45 92 10",
    "sg:postcode":"3700",
    "sg:province":"Limburg",
    "wof:name":"Ambiorix Nv",
    "wof:placetype":"venue"
},
  "geometry": {"coordinates":[5.484828949,50.7691307068],"type":"Point"}
}