{
  "type": "Feature",
  "properties": {
    "iso:country":"BE",
    "sg:address":"Ouderdomseweg 6",
    "sg:city":"Poperinge",
    "sg:orig_category":"Meubles D\u00e9taillants, Am\u00e9nagement de B\u00e2timents et de Cuisines",
    "sg:phone":"+32 57 33 67 76",
    "sg:postcode":"8970",
    "sg:province":"West-Vlaanderen",
    "wof:name":"Limo",
    "wof:placetype":"venue"
},
  "geometry": {"coordinates":[2.7401390076,50.8475151062],"type":"Point"}
}