{
  "type": "Feature",
  "properties": {
    "iso:country":"BE",
    "sg:address":"Weg Naar As 112",
    "sg:city":"Genk",
    "sg:classifiers":[
        {
            "category":"Recreation",
            "subcategory":"Arcade",
            "type":"Entertainment"
        }
    ],
    "sg:phone":"+32 89 35 16 47",
    "sg:postcode":"3600",
    "sg:province":"Limburg",
    "sg:tags":[
        "machine",
        "amusement"
    ],
    "wof:name":"W.a.g. Nv-selis Ivo",
    "wof:placetype":"venue"
},
  "geometry": {"coordinates":[5.5127477646,50.9703445435],"type":"Point"}
}