{
  "type": "Feature",
  "properties": {
    "iso:country":"BE",
    "sg:address":"Wijnzilver 6",
    "sg:city":"Lovendegem",
    "sg:classifiers":[
        {
            "category":"Health Services",
            "subcategory":"Nursing And Care Facility",
            "type":"Services"
        }
    ],
    "sg:phone":"+32 9 370 80 17",
    "sg:postcode":"9920",
    "sg:province":"Oost-Vlaanderen",
    "sg:tags":[
        "home"
    ],
    "wof:name":"Bulteel A",
    "wof:placetype":"venue"
},
  "geometry": {"coordinates":[3.6173489094,51.1039352417],"type":"Point"}
}