{
  "type": "Feature",
  "properties": {
    "addr:full":"Rue De Pintamont 37 Ath Hainaut 7800",
    "addr:housenumber":"37",
    "addr:postcode":"7800",
    "addr:street":"Rue De Pintamont",
    "iso:country":"BE",
    "sg:address":"Rue De Pintamont 37",
    "sg:city":"Ath",
    "sg:classifiers":[
        {
            "category":"Food & Beverages",
            "subcategory":"Groceries & Convenience Stores",
            "type":"Retail Goods"
        }
    ],
    "sg:phone":"+32 68 84 09 70",
    "sg:postcode":"7800",
    "sg:province":"Hainaut",
    "sg:tags":[
        "grocer"
    ],
    "wof:name":"Au Bon Coin Sprl",
    "wof:placetype":"venue"
},
  "geometry": {"coordinates":[3.7742800713,50.628578186],"type":"Point"}
}