{
  "type": "Feature",
  "properties": {
    "iso:country":"BE",
    "sg:address":"Montjoielaan 8",
    "sg:city":"Ukkel/uccle",
    "sg:orig_category":"Slagers",
    "sg:phone":"+32 2 375 22 03",
    "sg:postcode":"1180",
    "sg:province":"Bruxelles-Capitale",
    "wof:name":"Boucherie Montjoie",
    "wof:placetype":"venue"
},
  "geometry": {"coordinates":[4.3682518005,50.8104095459],"type":"Point"}
}