{
  "type": "Feature",
  "properties": {
    "iso:country":"BE",
    "sg:address":"Rue Haie-jadot 8",
    "sg:city":"Hamois",
    "sg:orig_category":"Fleurs and plantes",
    "sg:phone":"+32 83 61 12 36",
    "sg:postcode":"5360",
    "sg:province":"Namur",
    "wof:name":"Furn\u00c9mont-fleurs",
    "wof:placetype":"venue"
},
  "geometry": {"coordinates":[5.1903967857,50.3475151062],"type":"Point"}
}