{
  "type": "Feature",
  "properties": {
    "addr:full":"Rue Provinciale 291 Wavre (bierges) Brabant Wallon 1301",
    "addr:housenumber":"291;1301",
    "addr:street":"Rue Provinciale",
    "iso:country":"BE",
    "sg:address":"Rue Provinciale 291",
    "sg:city":"Wavre (bierges)",
    "sg:classifiers":[
        {
            "category":"Food & Beverages",
            "subcategory":"Groceries & Convenience Stores",
            "type":"Retail Goods"
        }
    ],
    "sg:phone":"+32 10 40 06 77",
    "sg:postcode":"1301",
    "sg:province":"Brabant Wallon",
    "sg:tags":[
        "baker",
        "-",
        "ingredient"
    ],
    "wof:name":"Pathos 2000",
    "wof:placetype":"venue"
},
  "geometry": {"coordinates":[4.5876140594,50.7048797607],"type":"Point"}
}