{
  "type": "Feature",
  "properties": {
    "iso:country":"BE",
    "sg:address":"Velodroomstraat 220",
    "sg:city":"Boom",
    "sg:classifiers":[
        {
            "category":"Health Services",
            "subcategory":"Doctor",
            "type":"Services"
        }
    ],
    "sg:phone":"+32 3 844 51 60",
    "sg:postcode":"2850",
    "sg:province":"Antwerpen",
    "sg:tags":[
        "medicinephysicians",
        "surgeon"
    ],
    "wof:name":"De Groof A",
    "wof:placetype":"venue"
},
  "geometry": {"coordinates":[4.3735208511,51.0924835205],"type":"Point"}
}