{
  "type": "Feature",
  "properties": {
    "addr:full":"Louis Melsensstraat 11b Leuven Vlaams-Brabant 3000",
    "addr:housenumber":"11b",
    "addr:postcode":"3000",
    "addr:street":"Louis Melsensstraat",
    "iso:country":"BE",
    "sg:address":"Louis Melsensstraat 11b",
    "sg:city":"Leuven",
    "sg:classifiers":[
        {
            "category":"Shopping",
            "subcategory":"Clothing, Apparel, & Fashions",
            "type":"Retail Goods"
        }
    ],
    "sg:phone":"+32 16 20 61 20",
    "sg:postcode":"3000",
    "sg:province":"Vlaams-Brabant",
    "sg:tags":[
        "hosiery"
    ],
    "wof:name":"Carissima",
    "wof:placetype":"venue"
},
  "geometry": {"coordinates":[4.7092618942,50.8808097839],"type":"Point"}
}