{
  "type": "Feature",
  "properties": {
    "addr:full":"Rue D'audiger 3 Soignies Hainaut 7060",
    "addr:housenumber":"3",
    "addr:postcode":"7060",
    "addr:street":"Rue D'Audiger",
    "iso:country":"BE",
    "sg:address":"Rue D'audiger 3",
    "sg:city":"Soignies",
    "sg:classifiers":[
        {
            "category":"Real Estate",
            "subcategory":"Architect",
            "type":"Services"
        }
    ],
    "sg:phone":"+32 67 33 40 80",
    "sg:postcode":"7060",
    "sg:province":"Hainaut",
    "wof:name":"Marbaix P",
    "wof:placetype":"venue"
},
  "geometry": {"coordinates":[4.0714759827,50.5793075562],"type":"Point"}
}