{
  "type": "Feature",
  "properties": {
    "iso:country":"BE",
    "sg:address":"Heiste 25",
    "sg:city":"Nevele (landegem)",
    "sg:classifiers":[
        {
            "category":"Wholesale",
            "subcategory":"Plants",
            "type":"Manufacturing & Wholesale Goods"
        }
    ],
    "sg:phone":"+32 9 371 60 62",
    "sg:postcode":"9850",
    "sg:province":"Oost-Vlaanderen",
    "sg:tags":[
        "whol",
        "flower",
        "-",
        "grower"
    ],
    "wof:name":"Leys E",
    "wof:placetype":"venue"
},
  "geometry": {"coordinates":[3.5800869465,51.0644836426],"type":"Point"}
}