{
  "type": "Feature",
  "properties": {
    "addr:full":"Rue Du Vicinal 27 Manhay (vaux-chavanne) Luxembourg 6960",
    "addr:housenumber":"27",
    "addr:postcode":"6960",
    "addr:street":"Rue Du Vicinal",
    "iso:country":"BE",
    "sg:address":"Rue Du Vicinal 27",
    "sg:city":"Manhay (vaux-chavanne)",
    "sg:classifiers":[
        {
            "category":"Personal",
            "subcategory":"Beauty Salon",
            "type":"Services"
        }
    ],
    "sg:phone":"+32 86 34 58 85",
    "sg:postcode":"6960",
    "sg:province":"Luxembourg",
    "sg:tags":[
        "lady",
        "-",
        "hairdressing"
    ],
    "wof:name":"Florence Coiffure",
    "wof:placetype":"venue"
},
  "geometry": {"coordinates":[5.6745300293,50.2932510376],"type":"Point"}
}