{
  "type": "Feature",
  "properties": {
    "addr:full":"La Fagnoul 4 Ferri\u00e8res Li\u00e8ge 4190",
    "addr:housenumber":"4",
    "addr:postcode":"4190",
    "iso:country":"BE",
    "sg:address":"La Fagnoul 4",
    "sg:city":"Ferri\u00e8res",
    "sg:classifiers":[
        {
            "category":"Building & Trades",
            "subcategory":"Plumbing",
            "type":"Services"
        }
    ],
    "sg:phone":"+32 86 40 05 77",
    "sg:postcode":"4190",
    "sg:province":"Li\u00e8ge",
    "sg:tags":[
        "contractor"
    ],
    "wof:name":"Joret J",
    "wof:placetype":"venue"
},
  "geometry": {"coordinates":[5.6266050339,50.3939285278],"type":"Point"}
}