{
  "type": "Feature",
  "properties": {
    "iso:country":"BE",
    "sg:address":"Boerenstraat 203",
    "sg:city":"Beveren",
    "sg:orig_category":"Transports routiers de marchandises",
    "sg:phone":"+32 3 775 78 16",
    "sg:postcode":"9120",
    "sg:province":"Oost-Vlaanderen",
    "wof:name":"Fa. Van Der Weken Gebrs",
    "wof:placetype":"venue"
},
  "geometry": {"coordinates":[4.2119002342,51.1981010437],"type":"Point"}
}