{
  "type": "Feature",
  "properties": {
    "addr:full":"Pont Walrand 1 Pepinster Li\u00e8ge 4860",
    "addr:housenumber":"1",
    "addr:postcode":"4860",
    "addr:street":"Pont Walrand",
    "iso:country":"BE",
    "sg:address":"Pont Walrand 1",
    "sg:city":"Pepinster",
    "sg:orig_category":"Enseignement maternel and primaire",
    "sg:phone":"+32 87 46 06 66",
    "sg:postcode":"4860",
    "sg:province":"Li\u00e8ge",
    "wof:name":"Ecole Fondamentale Libre",
    "wof:placetype":"venue"
},
  "geometry": {"coordinates":[5.8049240112,50.5689735413],"type":"Point"}
}