{
  "type": "Feature",
  "properties": {
    "addr:full":"Avenue Einstein 11 E Ottignies-louvain-la-neuve Brabant Wallon 1348",
    "addr:housenumber":"11 e",
    "addr:postcode":"1348",
    "addr:street":"Avenue Einstein",
    "iso:country":"BE",
    "sg:address":"Avenue Einstein 11 E",
    "sg:city":"Ottignies-louvain-la-neuve",
    "sg:orig_category":"Airconditioning and ventilatie Elektrische huishoudapparaten, radio and televisie Gh Loodgieterij an",
    "sg:phone":"+32 10 45 18 18",
    "sg:postcode":"1348",
    "sg:province":"Brabant Wallon",
    "wof:name":"Bepa",
    "wof:placetype":"venue"
},
  "geometry": {"coordinates":[4.567553997,50.6661262512],"type":"Point"}
}