{
  "type": "Feature",
  "properties": {
    "addr:full":"Oude Liersebaan 185 Duffel Antwerpen 2570",
    "addr:housenumber":"185",
    "addr:postcode":"2570",
    "addr:street":"Oude Liersebaan",
    "iso:country":"BE",
    "sg:address":"Oude Liersebaan 185",
    "sg:city":"Duffel",
    "sg:classifiers":[
        {
            "category":"Home & Garden",
            "subcategory":"Building Materials",
            "type":"Retail Goods"
        }
    ],
    "sg:phone":"+32 15 31 10 61",
    "sg:postcode":"2570",
    "sg:province":"Antwerpen",
    "sg:tags":[
        "aluminium",
        "window"
    ],
    "wof:name":"Dalco B.v.b.a.",
    "wof:placetype":"venue"
},
  "geometry": {"coordinates":[4.5293159485,51.1012115479],"type":"Point"}
}