{
  "type": "Feature",
  "properties": {
    "addr:full":"Industrielaan 17 Lichtervelde West-Vlaanderen 8810",
    "addr:housenumber":"17",
    "addr:postcode":"8810",
    "addr:street":"Industrielaan",
    "iso:country":"BE",
    "sg:address":"Industrielaan 17",
    "sg:city":"Lichtervelde",
    "sg:classifiers":[
        {
            "category":"Manufacturing",
            "subcategory":"Metals",
            "type":"Manufacturing & Wholesale Goods"
        }
    ],
    "sg:phone":"+32 51 72 96 66",
    "sg:postcode":"8810",
    "sg:province":"West-Vlaanderen",
    "sg:tags":[
        "alloy",
        "aluminium"
    ],
    "wof:name":"Rc-system",
    "wof:placetype":"venue"
},
  "geometry": {"coordinates":[3.1156589985,51.030418396],"type":"Point"}
}