{
  "type": "Feature",
  "properties": {
    "addr:full":"Avenue Jol\u00e9 1 Bruxelles Bruxelles-Capitale 1160",
    "addr:housenumber":"1",
    "addr:postcode":"1160",
    "addr:street":"Avenue Jole\u0301",
    "iso:country":"BE",
    "sg:address":"Avenue Jol\u00e9 1",
    "sg:city":"Bruxelles",
    "sg:classifiers":[
        {
            "category":"Professional",
            "subcategory":"Advertising",
            "type":"Services"
        }
    ],
    "sg:phone":"+32 2 673 58 31",
    "sg:postcode":"1160",
    "sg:province":"Bruxelles-Capitale",
    "sg:tags":[
        "communication",
        "medium"
    ],
    "wof:name":"L'univers Des Cartes Et Menus Delfosses Sprl",
    "wof:placetype":"venue"
},
  "geometry": {"coordinates":[4.4347572327,50.8124504089],"type":"Point"}
}