{
  "type": "Feature",
  "properties": {
    "iso:country":"BE",
    "sg:address":"Rue Du Nord 34",
    "sg:city":"Chapelle-lez-herlaimont",
    "sg:classifiers":[
        {
            "category":"Building & Trades",
            "subcategory":"Locksmith",
            "type":"Services"
        }
    ],
    "sg:phone":"+32 64 44 16 40",
    "sg:postcode":"7160",
    "sg:province":"Hainaut",
    "sg:tags":[
        "lock",
        "key"
    ],
    "wof:name":"Marini D",
    "wof:placetype":"venue"
},
  "geometry": {"coordinates":[4.2824110985,50.4776687622],"type":"Point"}
}