{
  "type": "Feature",
  "properties": {
    "addr:full":"Chauss\u00e9e Romaine 13a Geer (omal) Li\u00e8ge 4252",
    "addr:housenumber":"13a",
    "addr:postcode":"4252",
    "addr:street":"Chausse\u0301E Romaine;Omal",
    "iso:country":"BE",
    "sg:address":"Chauss\u00e9e Romaine 13a",
    "sg:city":"Geer (omal)",
    "sg:classifiers":[
        {
            "category":"Building & Trades",
            "subcategory":"Landscaping Services",
            "type":"Services"
        }
    ],
    "sg:phone":"+32 19 58 81 13",
    "sg:postcode":"4252",
    "sg:province":"Li\u00e8ge",
    "sg:tags":[
        "access",
        "pond",
        "laying-out",
        "-"
    ],
    "wof:name":"De Stexhe",
    "wof:placetype":"venue"
},
  "geometry": {"coordinates":[5.1957321167,50.6501998901],"type":"Point"}
}