{
  "type": "Feature",
  "properties": {
    "iso:country":"BE",
    "sg:address":"Xavier De Cocklaan 68 Box 1",
    "sg:city":"Sint-martens-latem (deurle)",
    "sg:classifiers":[
        {
            "category":"Professional",
            "subcategory":"Computer Services",
            "type":"Services"
        }
    ],
    "sg:phone":"+32 9 280 23 90",
    "sg:postcode":"9831",
    "sg:province":"Oost-Vlaanderen",
    "sg:tags":[
        "-",
        "processing",
        "data",
        "software"
    ],
    "wof:name":"Evo-soft Gent",
    "wof:placetype":"venue"
},
  "geometry": {"coordinates":[3.6009049416,51.0073394775],"type":"Point"}
}