{
  "type": "Feature",
  "properties": {
    "iso:country":"BE",
    "sg:address":"Dokter Dekemelelaan 5",
    "sg:city":"Ieper (boezinge)",
    "sg:classifiers":[
        {
            "category":"Health Services",
            "subcategory":"Health Practitioner",
            "type":"Services"
        }
    ],
    "sg:phone":"+32 57 42 24 82",
    "sg:postcode":"8904",
    "sg:province":"West-Vlaanderen",
    "sg:tags":[
        "physiotherapist"
    ],
    "wof:name":"Dewulf Mieke",
    "wof:placetype":"venue"
},
  "geometry": {"coordinates":[2.8575899601,50.8964576721],"type":"Point"}
}