{
  "type": "Feature",
  "properties": {
    "addr:full":"De Warande 41 Ham (oostham) Limburg 3945",
    "addr:housenumber":"41",
    "addr:postcode":"oostham;3945",
    "addr:street":"De Warande",
    "iso:country":"BE",
    "sg:address":"De Warande 41",
    "sg:city":"Ham (oostham)",
    "sg:classifiers":[
        {
            "category":"Cafe",
            "type":"Food & Drink"
        }
    ],
    "sg:phone":"+32 11 39 13 91",
    "sg:postcode":"3945",
    "sg:province":"Limburg",
    "sg:tags":[
        "snack-bars"
    ],
    "wof:name":"Happy Days",
    "wof:placetype":"venue"
},
  "geometry": {"coordinates":[5.1956601143,51.1063194275],"type":"Point"}
}