{
  "type": "Feature",
  "properties": {
    "addr:full":"Rue Du Palais 1 Li\u00e8ge 1 Li\u00e8ge 4000",
    "addr:housenumber":"1;1",
    "addr:postcode":"4000",
    "addr:street":"Rue Du Palais",
    "iso:country":"BE",
    "sg:address":"Rue Du Palais 1",
    "sg:city":"Li\u00e8ge 1",
    "sg:classifiers":[
        {
            "category":"Arts & Performance",
            "subcategory":"Art Gallery",
            "type":"Entertainment"
        }
    ],
    "sg:phone":"+32 4 222 93 11",
    "sg:postcode":"4000",
    "sg:province":"Li\u00e8ge",
    "wof:name":"Galerie Claude Antoine",
    "wof:placetype":"venue"
},
  "geometry": {"coordinates":[5.575876236,50.6464614868],"type":"Point"}
}