{
  "type": "Feature",
  "properties": {
    "iso:country":"BE",
    "sg:address":"Rekegemstraat 15b3",
    "sg:city":"Zwalm",
    "sg:orig_category":"Gespecialiseerde residenti\u00eble bouw",
    "sg:phone":"+32 55 49 62 79",
    "sg:postcode":"9630",
    "sg:province":"Oost-Vlaanderen",
    "wof:name":"Frank De Smet",
    "wof:placetype":"venue"
},
  "geometry": {"coordinates":[3.739415884,50.8775978088],"type":"Point"}
}