{
  "type": "Feature",
  "properties": {
    "addr:full":"Aucubaslaan 1 Kraainem Vlaams-Brabant 1950",
    "addr:housenumber":"1",
    "addr:postcode":"1950",
    "addr:street":"Aucubaslaan",
    "iso:country":"BE",
    "sg:address":"Aucubaslaan 1",
    "sg:city":"Kraainem",
    "sg:orig_category":"Sportclubs",
    "sg:phone":"+32 475 37 96 94",
    "sg:postcode":"1950",
    "sg:province":"Vlaams-Brabant",
    "wof:name":"A.s.e.k. 72",
    "wof:placetype":"venue"
},
  "geometry": {"coordinates":[4.4766731262,50.8362808228],"type":"Point"}
}