{
  "type": "Feature",
  "properties": {
    "addr:full":"Rue De Marche 112 Bastogne Luxembourg 6600",
    "addr:housenumber":"112",
    "addr:postcode":"6600",
    "addr:street":"Rue De Marche",
    "iso:country":"BE",
    "sg:address":"Rue De Marche 112",
    "sg:city":"Bastogne",
    "sg:orig_category":"Supermarkten",
    "sg:phone":"+32 61 21 70 84",
    "sg:postcode":"6600",
    "sg:province":"Luxembourg",
    "wof:name":"Ad Delhaize",
    "wof:placetype":"venue"
},
  "geometry": {"coordinates":[5.7001152039,50.0022926331],"type":"Point"}
}