{
  "type": "Feature",
  "properties": {
    "addr:full":"Grote Herreweg 125 Kluisbergen (ruien) Oost-Vlaanderen 9690",
    "addr:housenumber":"125",
    "addr:postcode":"9690",
    "addr:street":"Grote Herreweg",
    "iso:country":"BE",
    "sg:address":"Grote Herreweg 125",
    "sg:city":"Kluisbergen (ruien)",
    "sg:classifiers":[
        {
            "category":"Banks & Credit Unions",
            "subcategory":"Investment Brokerage",
            "type":"Services"
        }
    ],
    "sg:phone":"+32 55 38 63 04",
    "sg:postcode":"9690",
    "sg:province":"Oost-Vlaanderen",
    "wof:name":"Maes Verbeken Bvba",
    "wof:placetype":"venue"
},
  "geometry": {"coordinates":[3.4862658978,50.7722091675],"type":"Point"}
}