{
  "type": "Feature",
  "properties": {
    "addr:full":"Boulevard Edmond Machtens 176 Sint-jans-molenbeek/molenbeek- Bruxelles-Capitale 1080",
    "addr:housenumber":"176",
    "addr:postcode":"1080",
    "addr:street":"Boulevard Edmond Machtens;Molenbeek",
    "iso:country":"BE",
    "sg:address":"Boulevard Edmond Machtens 176",
    "sg:city":"Sint-jans-molenbeek/molenbeek-",
    "sg:orig_category":"R\u00e9parations \u00e0 domicile d'articles divers. Installation de menuiserie m\u00e9tallique. Magasins de r\u00e9parat",
    "sg:phone":"+32 475 71 11 90",
    "sg:postcode":"1080",
    "sg:province":"Bruxelles-Capitale",
    "wof:name":"Serrurerie Giammanco",
    "wof:placetype":"venue"
},
  "geometry": {"coordinates":[4.3045701981,50.8505401611],"type":"Point"}
}