{
  "type": "Feature",
  "properties": {
    "addr:full":"Buitensingel 60b4 Lommel Limburg 3920",
    "addr:housenumber":"60b4",
    "addr:postcode":"3920",
    "addr:street":"Buitensingel",
    "iso:country":"BE",
    "sg:address":"Buitensingel 60b4",
    "sg:city":"Lommel",
    "sg:orig_category":"Chaussures",
    "sg:phone":"+32 11 55 44 15",
    "sg:postcode":"3920",
    "sg:province":"Limburg",
    "wof:name":"Shoe Discount",
    "wof:placetype":"venue"
},
  "geometry": {"coordinates":[5.3159809113,51.221736908],"type":"Point"}
}