{
  "type": "Feature",
  "properties": {
    "addr:full":"Slangbeekweg 43 Zonhoven Limburg 3520",
    "addr:housenumber":"43",
    "addr:postcode":"3520",
    "addr:street":"Slangbeekweg",
    "iso:country":"BE",
    "sg:address":"Slangbeekweg 43",
    "sg:city":"Zonhoven",
    "sg:orig_category":"Non-Classified Establishments",
    "sg:phone":"+32 11 22 95 10",
    "sg:postcode":"3520",
    "sg:province":"Limburg",
    "wof:name":"Custom Bullet Shop Degol",
    "wof:placetype":"venue"
},
  "geometry": {"coordinates":[5.3444957733,50.9660873413],"type":"Point"}
}