{
  "type": "Feature",
  "properties": {
    "iso:country":"BE",
    "sg:address":"Jan Jacobsplein 7",
    "sg:city":"Brussel/bruxelles",
    "sg:orig_category":"Advocaten and juridische adviseurs",
    "sg:phone":"+32 2 502 71 88",
    "sg:postcode":"1000",
    "sg:province":"Bruxelles-Capitale",
    "wof:name":"Georges Nicolis",
    "wof:placetype":"venue"
},
  "geometry": {"coordinates":[4.3515481949,50.8351097107],"type":"Point"}
}