{
  "type": "Feature",
  "properties": {
    "iso:country":"BE",
    "sg:address":"Bld De La Ii\u00e8me Arm\u00e9e Britannique 20",
    "sg:city":"Bruxelles",
    "sg:classifiers":[
        {
            "category":"Manufacturing",
            "subcategory":"Tools & Machinery",
            "type":"Manufacturing & Wholesale Goods"
        }
    ],
    "sg:phone":"+32 2 344 19 90",
    "sg:postcode":"1190",
    "sg:province":"Bruxelles-Capitale",
    "sg:tags":[
        "binder",
        "rivet"
    ],
    "wof:name":"Usine Union Nv",
    "wof:placetype":"venue"
},
  "geometry": {"coordinates":[4.3232440948,50.8176422119],"type":"Point"}
}