{
  "type": "Feature",
  "properties": {
    "addr:full":"Diestsesteenweg 153 Leuven (kessel-lo) Vlaams-Brabant 3010",
    "addr:housenumber":"153",
    "addr:postcode":"3010",
    "addr:street":"Diestsesteenweg",
    "iso:country":"BE",
    "sg:address":"Diestsesteenweg 153",
    "sg:city":"Leuven (kessel-lo)",
    "sg:classifiers":[
        {
            "category":"Cafe",
            "type":"Food & Drink"
        }
    ],
    "sg:phone":"+32 16 25 18 00",
    "sg:postcode":"3010",
    "sg:province":"Vlaams-Brabant",
    "sg:tags":[
        "snack-bars"
    ],
    "wof:name":"Pannino E Vita",
    "wof:placetype":"venue"
},
  "geometry": {"coordinates":[4.7088489532,50.8813781738],"type":"Point"}
}