{
  "type": "Feature",
  "properties": {
    "iso:country":"BE",
    "sg:address":"Molenstraat 17",
    "sg:city":"Putte (beerzel)",
    "sg:orig_category":"Non-Classified Establishments",
    "sg:phone":"+32 15 25 09 61",
    "sg:postcode":"2580",
    "sg:province":"Antwerpen",
    "wof:name":"Joly's Paardenmelkerij",
    "wof:placetype":"venue"
},
  "geometry": {"coordinates":[4.6316781044,51.0541763306],"type":"Point"}
}