{
  "type": "Feature",
  "properties": {
    "addr:full":"Heizel Esplanade 90 Laken Bruxelles-Capitale 1020",
    "addr:housenumber":"90",
    "addr:postcode":"1020",
    "addr:street":"Heizel Esplanade",
    "iso:country":"BE",
    "sg:address":"Heizel Esplanade 90",
    "sg:city":"Laken",
    "sg:classifiers":[
        {
            "category":"Arena",
            "subcategory":"Sports Club",
            "type":"Entertainment"
        }
    ],
    "sg:phone":"+32 2 477 19 70",
    "sg:postcode":"1020",
    "sg:province":"Bruxelles-Capitale",
    "sg:tags":[
        "bathing",
        "shoes",
        "gym",
        "tennis",
        "boating",
        "shoe",
        "similar"
    ],
    "wof:name":"Bureau Design Center S.a.",
    "wof:placetype":"venue"
},
  "geometry": {"coordinates":[4.3563899994,50.8783683777],"type":"Point"}
}