{
  "type": "Feature",
  "properties": {
    "iso:country":"BE",
    "sg:address":"Avenue Victor Olivier 19",
    "sg:city":"Anderlecht",
    "sg:orig_category":"Installation de menuiserie en bois and plastique",
    "sg:phone":"+32 2 521 73 95",
    "sg:postcode":"1070",
    "sg:province":"Bruxelles-Capitale",
    "wof:name":"S.i.v.",
    "wof:placetype":"venue"
},
  "geometry": {"coordinates":[4.3100981712,50.8298912048],"type":"Point"}
}