{
  "type": "Feature",
  "properties": {
    "addr:full":"Onze Lieve Vrouwstraat 11 Nieuwpoort West-Vlaanderen 8620",
    "addr:housenumber":"11",
    "addr:postcode":"8620",
    "addr:street":"Onze Lieve Vrouwstraat",
    "iso:country":"BE",
    "sg:address":"Onze Lieve Vrouwstraat 11",
    "sg:city":"Nieuwpoort",
    "sg:orig_category":"M\u00e9decins and sp\u00e9cialistes",
    "sg:phone":"+32 58 23 73 13",
    "sg:postcode":"8620",
    "sg:province":"West-Vlaanderen",
    "wof:name":"Marie-christine Monteyne",
    "wof:placetype":"venue"
},
  "geometry": {"coordinates":[2.7497479916,51.1287498474],"type":"Point"}
}