{
  "type": "Feature",
  "properties": {
    "iso:country":"BE",
    "sg:address":"Route Du Monument 8",
    "sg:city":"Malmedy (beverc\u00e9)",
    "sg:classifiers":[
        {
            "category":"Travel",
            "subcategory":"Hotels & Motels",
            "type":"Entertainment"
        }
    ],
    "sg:phone":"+32 80 33 93 44",
    "sg:postcode":"4960",
    "sg:province":"Li\u00e8ge",
    "wof:name":"Horizon (l')",
    "wof:placetype":"venue"
},
  "geometry": {"coordinates":[6.0640268326,50.4035644531],"type":"Point"}
}