{
  "type": "Feature",
  "properties": {
    "addr:full":"Rue Eug\u00e8ne Gilles 45 Les Bons Villers (frasnes-lez-gosselies) Hainaut 6210",
    "addr:housenumber":"45",
    "addr:postcode":"6210",
    "addr:street":"Rue Euge\u0300Ne Gilles",
    "iso:country":"BE",
    "sg:address":"Rue Eug\u00e8ne Gilles 45",
    "sg:city":"Les Bons Villers (frasnes-lez-gosselies)",
    "sg:classifiers":[
        {
            "category":"Insurance",
            "subcategory":"Insurance Agent",
            "type":"Services"
        }
    ],
    "sg:phone":"+32 71 85 05 51",
    "sg:postcode":"6210",
    "sg:province":"Hainaut",
    "sg:tags":[
        "broker"
    ],
    "wof:name":"Castronuovo F",
    "wof:placetype":"venue"
},
  "geometry": {"coordinates":[4.4511561394,50.5378227234],"type":"Point"}
}