{
  "type": "Feature",
  "properties": {
    "iso:country":"BE",
    "sg:address":"Place Vieux Temps 3",
    "sg:city":"Verviers",
    "sg:classifiers":[
        {
            "category":"Insurance",
            "subcategory":"Life Insurance",
            "type":"Services"
        }
    ],
    "sg:phone":"+32 87 22 11 31",
    "sg:postcode":"4800",
    "sg:province":"Li\u00e8ge",
    "sg:tags":[
        "assurance"
    ],
    "wof:name":"Assurances Theate",
    "wof:placetype":"venue"
},
  "geometry": {"coordinates":[5.8624668121,50.5852775574],"type":"Point"}
}