{
  "type": "Feature",
  "properties": {
    "iso:country":"BE",
    "sg:address":"Avenue Secr\u00c9tin 29a",
    "sg:city":"Jette",
    "sg:orig_category":"Installation de menuiserie m\u00e9tallique. Installation de menuiserie en bois and plastique",
    "sg:phone":"+32 2 426 56 77",
    "sg:postcode":"1090",
    "sg:province":"Bruxelles-Capitale",
    "wof:name":"D\u00b4ooghe",
    "wof:placetype":"venue"
},
  "geometry": {"coordinates":[4.3321990967,50.8797302246],"type":"Point"}
}