{
  "type": "Feature",
  "properties": {
    "addr:full":"Stationsstraat 72 Geel Antwerpen 2440",
    "addr:housenumber":"72",
    "addr:postcode":"2440",
    "addr:street":"Stationsstraat",
    "iso:country":"BE",
    "sg:address":"Stationsstraat 72",
    "sg:city":"Geel",
    "sg:orig_category":"Drukkerijen and copyshops Kantoormateriaal Krantenwinkels",
    "sg:phone":"+32 14 58 85 81",
    "sg:postcode":"2440",
    "sg:province":"Antwerpen",
    "wof:name":"Drukkerij Truyen",
    "wof:placetype":"venue"
},
  "geometry": {"coordinates":[4.9891161919,51.1656951904],"type":"Point"}
}