{
  "type": "Feature",
  "properties": {
    "addr:full":". Wervik (groot) West-Vlaanderen 8940",
    "addr:postcode":"8940",
    "addr:street":"Groot West-Vlaanderen",
    "iso:country":"BE",
    "sg:address":".",
    "sg:city":"Wervik (groot)",
    "sg:orig_category":"Apotheken",
    "sg:phone":"+32 900 10 500",
    "sg:postcode":"8940",
    "sg:province":"West-Vlaanderen",
    "wof:name":"Apothekers Van Wacht",
    "wof:placetype":"venue"
},
  "geometry": {"coordinates":[3.0421171188,50.7773590088],"type":"Point"}
}