{
  "type": "Feature",
  "properties": {
    "iso:country":"BE",
    "sg:address":"Chauss\u00e9e Brunehault 176",
    "sg:city":"Morlanwelz (morlanwelz-mariemont)",
    "sg:classifiers":[
        {
            "category":"Real Estate",
            "subcategory":"Architect",
            "type":"Services"
        }
    ],
    "sg:phone":"+32 64 45 17 35",
    "sg:postcode":"7140",
    "sg:province":"Hainaut",
    "wof:name":"Demeyer J-ph",
    "wof:placetype":"venue"
},
  "geometry": {"coordinates":[4.2452301979,50.4508514404],"type":"Point"}
}