{
  "type": "Feature",
  "properties": {
    "addr:full":"Driesstr 176 Zele Oost-Vlaanderen 9240",
    "addr:housenumber":"176",
    "addr:postcode":"9240",
    "iso:country":"BE",
    "sg:address":"Driesstr 176",
    "sg:city":"Zele",
    "sg:classifiers":[
        {
            "category":"Building & Trades",
            "subcategory":"Construction",
            "type":"Services"
        }
    ],
    "sg:phone":"+32 52 45 07 00",
    "sg:postcode":"9240",
    "sg:province":"Oost-Vlaanderen",
    "sg:tags":[
        "work",
        "public"
    ],
    "wof:name":"Koze Nv",
    "wof:placetype":"venue"
},
  "geometry": {"coordinates":[4.0250401497,51.0676841736],"type":"Point"}
}