{
  "type": "Feature",
  "properties": {
    "iso:country":"BE",
    "sg:address":"Chauss\u00e9e De Bruxelles 485",
    "sg:city":"Waterloo",
    "sg:classifiers":[
        {
            "category":"Arena",
            "subcategory":"Sports Club",
            "type":"Entertainment"
        }
    ],
    "sg:phone":"+32 2 385 13 71",
    "sg:postcode":"1410",
    "sg:province":"Brabant Wallon",
    "wof:name":"Centre Ploug\u00e9e St Marine",
    "wof:placetype":"venue"
},
  "geometry": {"coordinates":[4.403927803,50.6945381165],"type":"Point"}
}