{
  "type": "Feature",
  "properties": {
    "addr:full":"Rue Bonaventure 21 Bruxelles (jette) Bruxelles-Capitale 1090",
    "addr:housenumber":"21",
    "addr:postcode":"1090",
    "addr:street":"Rue Bonaventure",
    "iso:country":"BE",
    "sg:address":"Rue Bonaventure 21",
    "sg:city":"Bruxelles (jette)",
    "sg:classifiers":[
        {
            "category":"Professional",
            "subcategory":"Computer Services",
            "type":"Services"
        }
    ],
    "sg:phone":"+32 2 479 37 77",
    "sg:postcode":"1090",
    "sg:province":"Bruxelles-Capitale",
    "sg:tags":[
        "-",
        "processing",
        "data"
    ],
    "wof:name":"T.i.p.s.",
    "wof:placetype":"venue"
},
  "geometry": {"coordinates":[4.31935215,50.884967804],"type":"Point"}
}