{
  "type": "Feature",
  "properties": {
    "iso:country":"BE",
    "sg:address":"Rue Paul Pastur 175",
    "sg:city":"Quaregnon",
    "sg:orig_category":"Non-Classified Establishments",
    "sg:phone":"+32 65 76 63 30",
    "sg:postcode":"7390",
    "sg:province":"Hainaut",
    "wof:name":"P\u00e8re Bouillon Sprl",
    "wof:placetype":"venue"
},
  "geometry": {"coordinates":[3.8599920273,50.4471626282],"type":"Point"}
}