{
  "type": "Feature",
  "properties": {
    "iso:country":"BE",
    "sg:address":"Sint-hendriksstraat 92",
    "sg:city":"Sint-lambrechts-woluwe/woluwe-saint-lambert",
    "sg:orig_category":"Kapsalons",
    "sg:phone":"+32 2 735 85 30",
    "sg:postcode":"1200",
    "sg:province":"Bruxelles-Capitale",
    "wof:name":"Trianon (le)",
    "wof:placetype":"venue"
},
  "geometry": {"coordinates":[4.4073400497,50.8415641785],"type":"Point"}
}