{
  "type": "Feature",
  "properties": {
    "addr:full":"Boulevard De La Sauveni\u00c8re 60 Liege Li\u00e8ge 4000",
    "addr:housenumber":"60",
    "addr:postcode":"4000",
    "addr:street":"Boulevard De La Sauvenie\u0300Re",
    "iso:country":"BE",
    "sg:address":"Boulevard De La Sauveni\u00c8re 60",
    "sg:city":"Liege",
    "sg:orig_category":"Tijdelijke werkgelegenheid and uitzendkantoren",
    "sg:phone":"+32 4 230 30 80",
    "sg:postcode":"4000",
    "sg:province":"Li\u00e8ge",
    "wof:name":"T Interim",
    "wof:placetype":"venue"
},
  "geometry": {"coordinates":[5.5669121742,50.6440887451],"type":"Point"}
}