{
  "type": "Feature",
  "properties": {
    "addr:full":"Rijksweg 25a Maasmechelen Limburg 3630",
    "addr:housenumber":"25a",
    "addr:postcode":"3630",
    "addr:street":"Rijksweg",
    "iso:country":"BE",
    "sg:address":"Rijksweg 25a",
    "sg:city":"Maasmechelen",
    "sg:classifiers":[
        {
            "category":"Retail",
            "subcategory":"Auto Repair",
            "type":"Services"
        }
    ],
    "sg:phone":"+32 89 79 12 68",
    "sg:postcode":"3630",
    "sg:province":"Limburg",
    "sg:tags":[
        "garage"
    ],
    "wof:name":"Wauts F",
    "wof:placetype":"venue"
},
  "geometry": {"coordinates":[5.6989679337,50.9720573425],"type":"Point"}
}