{
  "type": "Feature",
  "properties": {
    "addr:full":"Quai Andre\u00ef Sakharov 6 Tournai Hainaut 7500",
    "addr:housenumber":"6",
    "addr:postcode":"7500",
    "addr:street":"Quai Andrei\u0308 Sakharov",
    "iso:country":"BE",
    "sg:address":"Quai Andre\u00ef Sakharov 6",
    "sg:city":"Tournai",
    "sg:classifiers":[
        {
            "category":"Sports & Exercise",
            "subcategory":"Gym",
            "type":"Entertainment"
        }
    ],
    "sg:phone":"+32 69 23 20 21",
    "sg:postcode":"7500",
    "sg:province":"Hainaut",
    "sg:tags":[
        "fitness"
    ],
    "wof:name":"Parent",
    "wof:placetype":"venue"
},
  "geometry": {"coordinates":[3.3837909698,50.6140022278],"type":"Point"}
}