{
  "type": "Feature",
  "properties": {
    "addr:full":"Fazantenlaan 38 Kortenberg (everberg) Vlaams-Brabant 3078",
    "addr:housenumber":"38",
    "addr:postcode":"3078",
    "addr:street":"Fazantenlaan",
    "iso:country":"BE",
    "sg:address":"Fazantenlaan 38",
    "sg:city":"Kortenberg (everberg)",
    "sg:classifiers":[
        {
            "category":"Professional",
            "subcategory":"Accounting & Tax Preparation",
            "type":"Services"
        }
    ],
    "sg:phone":"+32 2 757 17 43",
    "sg:postcode":"3078",
    "sg:province":"Vlaams-Brabant",
    "sg:tags":[
        "accountant"
    ],
    "wof:name":"Juvel F",
    "wof:placetype":"venue"
},
  "geometry": {"coordinates":[4.5299568176,50.8707427979],"type":"Point"}
}