{
  "type": "Feature",
  "properties": {
    "addr:full":"Rue D'albroux 35 Ramillies (grand-rosi\u00e8re-hottomont) Brabant Wallon 1367",
    "addr:housenumber":"35",
    "addr:postcode":"1367",
    "addr:street":"Rue D'Albroux;Wallon",
    "iso:country":"BE",
    "sg:address":"Rue D'albroux 35",
    "sg:city":"Ramillies (grand-rosi\u00e8re-hottomont)",
    "sg:classifiers":[
        {
            "category":"Building & Trades",
            "subcategory":"Landscaping Services",
            "type":"Services"
        }
    ],
    "sg:phone":"+32 81 65 70 09",
    "sg:postcode":"1367",
    "sg:province":"Brabant Wallon",
    "sg:tags":[
        "gardening",
        "garden",
        "maintenance"
    ],
    "wof:name":"Burton J",
    "wof:placetype":"venue"
},
  "geometry": {"coordinates":[4.870552063,50.6264343262],"type":"Point"}
}