{
  "type": "Feature",
  "properties": {
    "addr:full":"Dendermondsestw 144 Willebroek Antwerpen 2830",
    "addr:housenumber":"144",
    "addr:postcode":"2830",
    "iso:country":"BE",
    "sg:address":"Dendermondsestw 144",
    "sg:city":"Willebroek",
    "sg:classifiers":[
        {
            "category":"Banks & Credit Unions",
            "subcategory":"Bank",
            "type":"Services"
        }
    ],
    "sg:phone":"+32 3 866 11 37",
    "sg:postcode":"2830",
    "sg:province":"Antwerpen",
    "wof:name":"Aslk-cger Bank",
    "wof:placetype":"venue"
},
  "geometry": {"coordinates":[4.3518118858,51.059841156],"type":"Point"}
}