{
  "type": "Feature",
  "properties": {
    "addr:full":"Diestsesteenweg 201 Lubbeek Vlaams-Brabant 3210",
    "addr:housenumber":"201",
    "addr:postcode":"3210",
    "addr:street":"Diestsesteenweg",
    "iso:country":"BE",
    "sg:address":"Diestsesteenweg 201",
    "sg:city":"Lubbeek",
    "sg:classifiers":[
        {
            "category":"Autos & Motor Vehicles",
            "subcategory":"Fuel & Gas Station",
            "type":"Retail Goods"
        }
    ],
    "sg:phone":"+32 16 62 12 35",
    "sg:postcode":"3210",
    "sg:province":"Vlaams-Brabant",
    "sg:tags":[
        "stations-service",
        "carburants"
    ],
    "wof:name":"A.c.s.",
    "wof:placetype":"venue"
},
  "geometry": {"coordinates":[4.8095397949,50.8933792114],"type":"Point"}
}