{
  "type": "Feature",
  "properties": {
    "addr:full":"Duinkerkelaan 122 De Panne West-Vlaanderen 8660",
    "addr:housenumber":"122",
    "addr:postcode":"8660",
    "addr:street":"Duinkerkelaan",
    "iso:country":"BE",
    "sg:address":"Duinkerkelaan 122",
    "sg:city":"De Panne",
    "sg:orig_category":"Blanchisseries and teintureries",
    "sg:phone":"+32 58 41 15 64",
    "sg:postcode":"8660",
    "sg:province":"West-Vlaanderen",
    "wof:name":"Presto Shop",
    "wof:placetype":"venue"
},
  "geometry": {"coordinates":[2.5831930637,51.0983467102],"type":"Point"}
}