{
  "type": "Feature",
  "properties": {
    "iso:country":"BE",
    "sg:address":"Lange Molenstr 27",
    "sg:city":"Heist-op-den-berg",
    "sg:classifiers":[
        {
            "category":"Manufacturing",
            "subcategory":"Wood Products",
            "type":"Manufacturing & Wholesale Goods"
        }
    ],
    "sg:phone":"+32 15 22 07 63",
    "sg:postcode":"2220",
    "sg:province":"Antwerpen",
    "sg:tags":[
        "household",
        "-",
        "machine",
        "engineering",
        "mechanical",
        "furniture"
    ],
    "wof:name":"Claes Center Bvba",
    "wof:placetype":"venue"
},
  "geometry": {"coordinates":[4.7173500061,51.0787620544],"type":"Point"}
}