{
  "type": "Feature",
  "properties": {
    "iso:country":"BE",
    "sg:address":"Rue Trieux-des-gouttes 9",
    "sg:city":"La Bruyere",
    "sg:orig_category":"Experts-comptables",
    "sg:phone":"+32 81 21 37 66",
    "sg:postcode":"5080",
    "sg:province":"Namur",
    "wof:name":"Pol Golard",
    "wof:placetype":"venue"
},
  "geometry": {"coordinates":[4.8467898369,50.5165481567],"type":"Point"}
}