{
  "type": "Feature",
  "properties": {
    "addr:full":"Boonhofstraat 43 Dessel Antwerpen 2480",
    "addr:housenumber":"43",
    "addr:postcode":"2480",
    "addr:street":"Boonhofstraat",
    "iso:country":"BE",
    "sg:address":"Boonhofstraat 43",
    "sg:city":"Dessel",
    "sg:classifiers":[
        {
            "category":"Health Services",
            "subcategory":"Health Practitioner",
            "type":"Services"
        }
    ],
    "sg:phone":"+32 14 37 26 31",
    "sg:postcode":"2480",
    "sg:province":"Antwerpen",
    "sg:tags":[
        "physiotherapist"
    ],
    "wof:name":"Cools J",
    "wof:placetype":"venue"
},
  "geometry": {"coordinates":[5.1188311577,51.241733551],"type":"Point"}
}