{
  "type": "Feature",
  "properties": {
    "iso:country":"BE",
    "sg:address":"Lindenstraat 117",
    "sg:city":"Sint-niklaas",
    "sg:orig_category":"M\u00e9decins and sp\u00e9cialistes",
    "sg:phone":"+32 3 777 34 81",
    "sg:postcode":"9100",
    "sg:province":"Oost-Vlaanderen",
    "wof:name":"P. Van Goethem",
    "wof:placetype":"venue"
},
  "geometry": {"coordinates":[4.15685606,51.1649475098],"type":"Point"}
}