{
  "type": "Feature",
  "properties": {
    "iso:country":"BE",
    "sg:address":"Chauss\u00c9e Romaine 39",
    "sg:city":"Oreye",
    "sg:orig_category":"Elektrische installaties voor woningen Loodgieterij, verwarming and sanitaire installaties",
    "sg:phone":"+32 19 67 82 70",
    "sg:postcode":"4360",
    "sg:province":"Li\u00e8ge",
    "wof:name":"Gerard Remy",
    "wof:placetype":"venue"
},
  "geometry": {"coordinates":[5.3494801521,50.733581543],"type":"Point"}
}