{
  "type": "Feature",
  "properties": {
    "addr:full":"Rue D'alleur 99 Li\u00e8ge 1 (rocourt) Li\u00e8ge 4000",
    "addr:housenumber":"99;1",
    "addr:postcode":"4000",
    "addr:street":"Rue D'Alleur",
    "iso:country":"BE",
    "sg:address":"Rue D'alleur 99",
    "sg:city":"Li\u00e8ge 1 (rocourt)",
    "sg:classifiers":[
        {
            "category":"Personal",
            "subcategory":"Barber",
            "type":"Services"
        }
    ],
    "sg:phone":"+32 4 246 33 56",
    "sg:postcode":"4000",
    "sg:province":"Li\u00e8ge",
    "sg:tags":[
        "gentleman",
        "salon",
        "-",
        "hairdressing"
    ],
    "wof:name":"Maryl\u00e8ne",
    "wof:placetype":"venue"
},
  "geometry": {"coordinates":[5.514359951,50.6777687073],"type":"Point"}
}