{
  "type": "Feature",
  "properties": {
    "iso:country":"BE",
    "sg:address":"Rumbeeksesteenweg 442",
    "sg:city":"Roeselare",
    "sg:orig_category":"Fietsen",
    "sg:phone":"+32 51 20 26 05",
    "sg:postcode":"8800",
    "sg:province":"West-Vlaanderen",
    "wof:name":"Fietsen Seys",
    "wof:placetype":"venue"
},
  "geometry": {"coordinates":[3.1384699345,50.9378700256],"type":"Point"}
}