{
  "type": "Feature",
  "properties": {
    "iso:country":"BE",
    "sg:address":"Hasseltsesteenweg 550",
    "sg:city":"Tongeren",
    "sg:orig_category":"Schoonheidssalons",
    "sg:phone":"+32 12 23 79 08",
    "sg:postcode":"3700",
    "sg:province":"Limburg",
    "wof:name":"Nicole Schoups",
    "wof:placetype":"venue"
},
  "geometry": {"coordinates":[5.4480662346,50.7972602844],"type":"Point"}
}