{
  "type": "Feature",
  "properties": {
    "addr:full":"Vandenpeereboomstraat 82 Halle Vlaams-Brabant 1500",
    "addr:housenumber":"82",
    "addr:postcode":"1500",
    "addr:street":"Vandenpeereboomstraat",
    "iso:country":"BE",
    "sg:address":"Vandenpeereboomstraat 82",
    "sg:city":"Halle",
    "sg:classifiers":[
        {
            "category":"Shopping",
            "subcategory":"Musical Instruments",
            "type":"Retail Goods"
        }
    ],
    "sg:phone":"+32 2 360 04 26",
    "sg:postcode":"1500",
    "sg:province":"Vlaams-Brabant",
    "sg:tags":[
        "piano",
        "-",
        "tuning"
    ],
    "wof:name":"Deville K",
    "wof:placetype":"venue"
},
  "geometry": {"coordinates":[4.242041111,50.7342643738],"type":"Point"}
}