{
  "type": "Feature",
  "properties": {
    "iso:country":"BE",
    "sg:address":"Pijpenhof 33",
    "sg:city":"Bilzen",
    "sg:classifiers":[
        {
            "category":"Health Services",
            "subcategory":"Doctor",
            "type":"Services"
        }
    ],
    "sg:phone":"+32 89 41 14 34",
    "sg:postcode":"3740",
    "sg:province":"Limburg",
    "sg:tags":[
        "medicinephysicians",
        "surgeon"
    ],
    "wof:name":"Dops J",
    "wof:placetype":"venue"
},
  "geometry": {"coordinates":[5.5189738274,50.8739776611],"type":"Point"}
}