{
  "type": "Feature",
  "properties": {
    "iso:country":"BE",
    "sg:address":"Avenue Maurice Cesar 3",
    "sg:city":"Wezembeek-oppem",
    "sg:classifiers":[
        {
            "category":"Insurance",
            "subcategory":"Insurance Agent",
            "type":"Services"
        }
    ],
    "sg:phone":"+32 2 731 58 59",
    "sg:postcode":"1970",
    "sg:province":"Vlaams-Brabant",
    "sg:tags":[
        "broker"
    ],
    "wof:name":"Georis J.m. Sprl",
    "wof:placetype":"venue"
},
  "geometry": {"coordinates":[4.4715461731,50.8437042236],"type":"Point"}
}