{
  "type": "Feature",
  "properties": {
    "addr:full":"Onafhankelijkheidsstraat 28 Box 2 Edegem Antwerpen 2650",
    "addr:housenumber":"28;2",
    "addr:postcode":"2650",
    "addr:street":"Onafhankelijkheidsstraat;Box",
    "iso:country":"BE",
    "sg:address":"Onafhankelijkheidsstraat 28 Box 2",
    "sg:city":"Edegem",
    "sg:classifiers":[
        {
            "category":"Health Services",
            "subcategory":"Health Practitioner",
            "type":"Services"
        }
    ],
    "sg:phone":"+32 3 457 73 93",
    "sg:postcode":"2650",
    "sg:province":"Antwerpen",
    "sg:tags":[
        "physiotherapist"
    ],
    "wof:name":"Brems R",
    "wof:placetype":"venue"
},
  "geometry": {"coordinates":[4.4467301369,51.1578102112],"type":"Point"}
}