{
  "type": "Feature",
  "properties": {
    "addr:full":"Rue Dr\u00e8ve D'envoz 1 H\u00e9ron (couthuin) Li\u00e8ge 4218",
    "addr:housenumber":"1",
    "addr:postcode":"4218",
    "addr:street":"Rue Dre\u0300Ve D'Envoz",
    "iso:country":"BE",
    "sg:address":"Rue Dr\u00e8ve D'envoz 1",
    "sg:city":"H\u00e9ron (couthuin)",
    "sg:classifiers":[
        {
            "category":"Retail",
            "subcategory":"Event Space",
            "type":"Services"
        }
    ],
    "sg:phone":"+32 85 25 49 25",
    "sg:postcode":"4218",
    "sg:province":"Li\u00e8ge",
    "sg:tags":[
        "rental",
        "-",
        "hall"
    ],
    "wof:name":"Ch\u00e2teau D'envoz",
    "wof:placetype":"venue"
},
  "geometry": {"coordinates":[5.14128685,50.5289840698],"type":"Point"}
}