{
  "type": "Feature",
  "properties": {
    "addr:full":"Hamaide 95 Libin Luxembourg 6890",
    "addr:housenumber":"95",
    "addr:postcode":"6890",
    "addr:street":"Hamaide",
    "iso:country":"BE",
    "sg:address":"Hamaide 95",
    "sg:city":"Libin",
    "sg:orig_category":"Verhuisdiensten",
    "sg:phone":"+32 61 65 63 38",
    "sg:postcode":"6890",
    "sg:province":"Luxembourg",
    "wof:name":"Mahin",
    "wof:placetype":"venue"
},
  "geometry": {"coordinates":[5.2562999725,49.9827537537],"type":"Point"}
}