{
  "type": "Feature",
  "properties": {
    "iso:country":"BE",
    "sg:address":"Rue Royale 314",
    "sg:city":"Sint-joost-ten-node/saint-josse-ten-noode",
    "sg:classifiers":[
        {
            "category":"Professional",
            "subcategory":"Business Services",
            "type":"Services"
        }
    ],
    "sg:phone":"+32 2 223 62 60",
    "sg:postcode":"1210",
    "sg:province":"Bruxelles-Capitale",
    "sg:tags":[
        "aux",
        "diver",
        "entreprises"
    ],
    "wof:name":"Intercommunication",
    "wof:placetype":"venue"
},
  "geometry": {"coordinates":[4.3676099777,50.8573303223],"type":"Point"}
}