{
  "type": "Feature",
  "properties": {
    "iso:country":"BE",
    "sg:address":"Roze Hoevelaan 10b26",
    "sg:city":"Ukkel/uccle",
    "sg:orig_category":"Artsen and specialisten",
    "sg:phone":"+32 2 343 82 53",
    "sg:postcode":"1180",
    "sg:province":"Bruxelles-Capitale",
    "wof:name":"Jean Grimmiaux",
    "wof:placetype":"venue"
},
  "geometry": {"coordinates":[4.3483481407,50.8064956665],"type":"Point"}
}