{
  "type": "Feature",
  "properties": {
    "addr:full":"Molenstraat 119 Sint-laureins Oost-Vlaanderen 9988",
    "addr:housenumber":"119",
    "addr:postcode":"sint-laureins;9988",
    "addr:street":"Molenstraat",
    "iso:country":"BE",
    "sg:address":"Molenstraat 119",
    "sg:city":"Sint-laureins",
    "sg:orig_category":"Landbouwmachines Gh",
    "sg:phone":"+32 9 379 85 30",
    "sg:postcode":"9988",
    "sg:province":"Oost-Vlaanderen",
    "wof:name":"F. Vervaet",
    "wof:placetype":"venue"
},
  "geometry": {"coordinates":[3.6273899078,51.2903594971],"type":"Point"}
}