{
  "type": "Feature",
  "properties": {
    "iso:country":"BE",
    "sg:address":"Rue Stud 10",
    "sg:city":"Andenne",
    "sg:orig_category":"Artistes ind\u00e9pendants",
    "sg:phone":"+32 85 84 61 78",
    "sg:postcode":"5300",
    "sg:province":"Namur",
    "wof:name":"Elisabeth De Coninck",
    "wof:placetype":"venue"
},
  "geometry": {"coordinates":[5.0791277885,50.4823036194],"type":"Point"}
}