{
  "type": "Feature",
  "properties": {
    "addr:full":"Battelsesteenweg 191 Mechelen Antwerpen 2800",
    "addr:housenumber":"191",
    "addr:postcode":"2800",
    "addr:street":"Battelsesteenweg",
    "iso:country":"BE",
    "sg:address":"Battelsesteenweg 191",
    "sg:city":"Mechelen",
    "sg:classifiers":[
        {
            "category":"Professional",
            "subcategory":"Computer Services",
            "type":"Services"
        }
    ],
    "sg:phone":"+32 475 90 30 56",
    "sg:postcode":"2800",
    "sg:province":"Antwerpen",
    "sg:tags":[
        "webdesign",
        "-",
        "internet"
    ],
    "wof:name":"Vision*r",
    "wof:placetype":"venue"
},
  "geometry": {"coordinates":[4.4640851021,51.0298881531],"type":"Point"}
}