{
  "type": "Feature",
  "properties": {
    "addr:full":"Kolonel Bourgstraat 58 Schaarbeek/schaerbeek Bruxelles-Capitale 1030",
    "addr:housenumber":"58",
    "addr:postcode":"1030",
    "addr:street":"Kolonel Bourgstraat",
    "iso:country":"BE",
    "sg:address":"Kolonel Bourgstraat 58",
    "sg:city":"Schaarbeek/schaerbeek",
    "sg:orig_category":"Loodgieterij, verwarming and sanitaire installaties",
    "sg:phone":"+32 2 705 18 90",
    "sg:postcode":"1030",
    "sg:province":"Bruxelles-Capitale",
    "wof:name":"Robert Brunin",
    "wof:placetype":"venue"
},
  "geometry": {"coordinates":[4.4060611725,50.8517913818],"type":"Point"}
}