{
  "type": "Feature",
  "properties": {
    "addr:full":"Savoiestraat 33 Sint-gillis/saint-gilles Bruxelles-Capitale 1060",
    "addr:housenumber":"33",
    "addr:postcode":"1060",
    "addr:street":"Savoiestraat",
    "iso:country":"BE",
    "sg:address":"Savoiestraat 33",
    "sg:city":"Sint-gillis/saint-gilles",
    "sg:orig_category":"Artsen and specialisten",
    "sg:phone":"+32 2 537 21 98",
    "sg:postcode":"1060",
    "sg:province":"Bruxelles-Capitale",
    "wof:name":"Joseph Makhoul",
    "wof:placetype":"venue"
},
  "geometry": {"coordinates":[4.3446750641,50.8240509033],"type":"Point"}
}