{
  "type": "Feature",
  "properties": {
    "addr:full":"Rue Armand Guerlache 33 Ramillies (autre-eglise) Brabant Wallon 1367",
    "addr:housenumber":"33",
    "addr:postcode":"1367",
    "addr:street":"Rue Armand Guerlache;Brabant Wallon",
    "iso:country":"BE",
    "sg:address":"Rue Armand Guerlache 33",
    "sg:city":"Ramillies (autre-eglise)",
    "sg:classifiers":[
        {
            "category":"Health Services",
            "subcategory":"Doctor",
            "type":"Services"
        }
    ],
    "sg:phone":"+32 81 87 77 26",
    "sg:postcode":"1367",
    "sg:province":"Brabant Wallon",
    "sg:tags":[
        "medicinephysicians",
        "surgeon"
    ],
    "wof:name":"Baugnet V",
    "wof:placetype":"venue"
},
  "geometry": {"coordinates":[4.9146900177,50.636631012],"type":"Point"}
}