{
  "type": "Feature",
  "properties": {
    "addr:full":"Chauss\u00c9e De La Hulpe 241 Watermaal-bosvoorde/watermael-boitsfort Bruxelles-Capitale 1170",
    "addr:housenumber":"241;/",
    "addr:postcode":"1170",
    "addr:street":"Chausse\u0301E De La Hulpe;Watermaal-Bosvoorde",
    "iso:country":"BE",
    "sg:address":"Chauss\u00c9e De La Hulpe 241",
    "sg:city":"Watermaal-bosvoorde/watermael-boitsfort",
    "sg:orig_category":"Studios photographiques",
    "sg:phone":"+32 2 673 95 73",
    "sg:postcode":"1170",
    "sg:province":"Bruxelles-Capitale",
    "wof:name":"Jean Segers Photographe",
    "wof:placetype":"venue"
},
  "geometry": {"coordinates":[4.4175958633,50.7939071655],"type":"Point"}
}