{
  "type": "Feature",
  "properties": {
    "addr:full":"Chauss\u00c9e Verte 155 Saint-georges-sur-meuse Li\u00e8ge 4470",
    "addr:housenumber":"155",
    "addr:postcode":"4470",
    "addr:street":"Chausse\u0301E Verte",
    "iso:country":"BE",
    "sg:address":"Chauss\u00c9e Verte 155",
    "sg:city":"Saint-georges-sur-meuse",
    "sg:orig_category":"Rundveehouders",
    "sg:phone":"+32 4 259 50 14",
    "sg:postcode":"4470",
    "sg:province":"Li\u00e8ge",
    "wof:name":"Paul Havelange",
    "wof:placetype":"venue"
},
  "geometry": {"coordinates":[5.3531208038,50.6145744324],"type":"Point"}
}