{
  "type": "Feature",
  "properties": {
    "addr:full":"De Lochtstraat 38 Schaarbeek/schaerbeek Bruxelles-Capitale 1030",
    "addr:housenumber":"38",
    "addr:postcode":"1030",
    "addr:street":"De Lochtstraat",
    "iso:country":"BE",
    "sg:address":"De Lochtstraat 38",
    "sg:city":"Schaarbeek/schaerbeek",
    "sg:classifiers":[
        {
            "category":"Taxi",
            "type":"Transportation"
        }
    ],
    "sg:phone":"+32 2 241 01 80",
    "sg:postcode":"1030",
    "sg:province":"Bruxelles-Capitale",
    "sg:tags":[
        "taxi's"
    ],
    "wof:name":"Tsiourlis Dimos",
    "wof:placetype":"venue"
},
  "geometry": {"coordinates":[4.3691158295,50.8644943237],"type":"Point"}
}