{
  "type": "Feature",
  "properties": {
    "iso:country":"BE",
    "sg:address":"Albert Panisstraat 87",
    "sg:city":"Beveren",
    "sg:orig_category":"Woningbouw",
    "sg:phone":"+32 3 775 59 85",
    "sg:postcode":"9120",
    "sg:province":"Oost-Vlaanderen",
    "wof:name":"Bosman E.",
    "wof:placetype":"venue"
},
  "geometry": {"coordinates":[4.2442388535,51.2070236206],"type":"Point"}
}