{
  "type": "Feature",
  "properties": {
    "addr:full":"Avenue Joseph Wauters 63 Virton (saint-mard) Luxembourg 6762",
    "addr:housenumber":"63",
    "addr:postcode":"6762",
    "addr:street":"Avenue Joseph Wauters",
    "iso:country":"BE",
    "sg:address":"Avenue Joseph Wauters 63",
    "sg:city":"Virton (saint-mard)",
    "sg:classifiers":[
        {
            "category":"Retail",
            "subcategory":"Auto Repair",
            "type":"Services"
        }
    ],
    "sg:phone":"+32 63 57 77 81",
    "sg:postcode":"6762",
    "sg:province":"Luxembourg",
    "sg:tags":[
        "automobile",
        "servic",
        "electrical",
        "-"
    ],
    "wof:name":"Virton Electro Diesel & Hydraulique",
    "wof:placetype":"venue"
},
  "geometry": {"coordinates":[5.5332231522,49.5546951294],"type":"Point"}
}