{
  "type": "Feature",
  "properties": {
    "iso:country":"BE",
    "sg:address":"Chauss\u00e9e De Namur 150",
    "sg:city":"Wavre",
    "sg:classifiers":[
        {
            "category":"Home & Garden",
            "subcategory":"Building Materials",
            "type":"Retail Goods"
        }
    ],
    "sg:phone":"+32 10 48 29 11",
    "sg:postcode":"1300",
    "sg:province":"Brabant Wallon",
    "sg:tags":[
        "insulation",
        "thermical"
    ],
    "wof:name":"L.m. Materiaux Sa",
    "wof:placetype":"venue"
},
  "geometry": {"coordinates":[4.6156740189,50.6974372864],"type":"Point"}
}