{
  "type": "Feature",
  "properties": {
    "iso:country":"BE",
    "sg:address":"Lage Bokstraat 1",
    "sg:city":"Sint-niklaas",
    "sg:orig_category":"Imprimeries and copyshops",
    "sg:phone":"+32 3 777 70 62",
    "sg:postcode":"9111",
    "sg:province":"Oost-Vlaanderen",
    "wof:name":"Drukkerij Iota",
    "wof:placetype":"venue"
},
  "geometry": {"coordinates":[4.1184577942,51.1651802063],"type":"Point"}
}