{
  "type": "Feature",
  "properties": {
    "iso:country":"BE",
    "sg:address":"Middelveld 29",
    "sg:city":"Meise",
    "sg:classifiers":[
        {
            "category":"Retail",
            "subcategory":"Animal Services",
            "type":"Services"
        }
    ],
    "sg:phone":"+32 2 269 87 33",
    "sg:postcode":"1860",
    "sg:province":"Vlaams-Brabant",
    "sg:tags":[
        "grooming",
        "-",
        "dog"
    ],
    "wof:name":"Anny (hondensalon)",
    "wof:placetype":"venue"
},
  "geometry": {"coordinates":[4.3382902145,50.9529495239],"type":"Point"}
}