{
  "type": "Feature",
  "properties": {
    "addr:full":"Pintestraat 37 De Pinte Oost-Vlaanderen 9840",
    "addr:housenumber":"37",
    "addr:postcode":"9840",
    "addr:street":"Pintestraat",
    "iso:country":"BE",
    "sg:address":"Pintestraat 37",
    "sg:city":"De Pinte",
    "sg:classifiers":[
        {
            "category":"Professional",
            "subcategory":"Art Services",
            "type":"Services"
        }
    ],
    "sg:phone":"+32 9 280 05 98",
    "sg:postcode":"9840",
    "sg:province":"Oost-Vlaanderen",
    "sg:tags":[
        "interior",
        "designer"
    ],
    "wof:name":"De Graeve-claeys",
    "wof:placetype":"venue"
},
  "geometry": {"coordinates":[3.6467449665,50.9907417297],"type":"Point"}
}