{
  "type": "Feature",
  "properties": {
    "iso:country":"BE",
    "sg:address":"Rue Du Ch\u00e2teau 5",
    "sg:city":"Celles (molenbaix)",
    "sg:classifiers":[
        {
            "category":"Retail",
            "subcategory":"Veterinary Services",
            "type":"Services"
        }
    ],
    "sg:phone":"+32 69 45 50 33",
    "sg:postcode":"7760",
    "sg:province":"Hainaut",
    "sg:tags":[
        "veterinarian"
    ],
    "wof:name":"Fontaine L",
    "wof:placetype":"venue"
},
  "geometry": {"coordinates":[3.4274749756,50.6952552795],"type":"Point"}
}