{
  "type": "Feature",
  "properties": {
    "addr:full":"Antwerpsesteenweg 133 Vosselaar Antwerpen 2350",
    "addr:housenumber":"133",
    "addr:postcode":"2350",
    "addr:street":"Antwerpsesteenweg",
    "iso:country":"BE",
    "sg:address":"Antwerpsesteenweg 133",
    "sg:city":"Vosselaar",
    "sg:orig_category":"Banques and organismes de cr\u00e9dit",
    "sg:phone":"+32 14 61 14 84",
    "sg:postcode":"2350",
    "sg:province":"Antwerpen",
    "wof:name":"Kbc",
    "wof:placetype":"venue"
},
  "geometry": {"coordinates":[4.8886451721,51.3147583008],"type":"Point"}
}