{
  "type": "Feature",
  "properties": {
    "addr:full":"Terelststraat 312 Edegem Antwerpen 2650",
    "addr:housenumber":"312",
    "addr:postcode":"2650",
    "addr:street":"Terelststraat",
    "iso:country":"BE",
    "sg:address":"Terelststraat 312",
    "sg:city":"Edegem",
    "sg:classifiers":[
        {
            "category":"Arena",
            "subcategory":"Sports Club",
            "type":"Entertainment"
        }
    ],
    "sg:phone":"+32 3 457 15 33",
    "sg:postcode":"2650",
    "sg:province":"Antwerpen",
    "wof:name":"Hockeyclub Victory",
    "wof:placetype":"venue"
},
  "geometry": {"coordinates":[4.4305901527,51.1505088806],"type":"Point"}
}