{
  "type": "Feature",
  "properties": {
    "addr:full":"Akkerveken 1 Wuustwezel Antwerpen 2990",
    "addr:housenumber":"1",
    "addr:postcode":"2990",
    "addr:street":"Akkerveken",
    "iso:country":"BE",
    "sg:address":"Akkerveken 1",
    "sg:city":"Wuustwezel",
    "sg:orig_category":"Varkenskwekers",
    "sg:phone":"+32 3 669 63 13",
    "sg:postcode":"2990",
    "sg:province":"Antwerpen",
    "wof:name":"Jozef Van Looveren",
    "wof:placetype":"venue"
},
  "geometry": {"coordinates":[4.5521922112,51.3759269714],"type":"Point"}
}