{
  "type": "Feature",
  "properties": {
    "iso:country":"BE",
    "sg:address":"Weertersteenweg 127",
    "sg:city":"Maaseik",
    "sg:orig_category":"Antiquit\u00e9s",
    "sg:phone":"+32 475 63 76 27",
    "sg:postcode":"3680",
    "sg:province":"Limburg",
    "wof:name":"Huis Janssen",
    "wof:placetype":"venue"
},
  "geometry": {"coordinates":[5.7783308029,51.1053009033],"type":"Point"}
}