{
  "type": "Feature",
  "properties": {
    "iso:country":"BE",
    "sg:address":"Klein-hulststraat 114",
    "sg:city":"Sint-niklaas",
    "sg:orig_category":"Epiceries",
    "sg:phone":"+32 3 777 05 48",
    "sg:postcode":"9100",
    "sg:province":"Oost-Vlaanderen",
    "wof:name":"Anne-marie D'hooghe",
    "wof:placetype":"venue"
},
  "geometry": {"coordinates":[4.1514282227,51.1674156189],"type":"Point"}
}