{
  "type": "Feature",
  "properties": {
    "addr:full":"Rue Patiaux 45 Waterloo Brabant Wallon 1410",
    "addr:housenumber":"45",
    "addr:postcode":"1410",
    "addr:street":"Rue Patiaux",
    "iso:country":"BE",
    "sg:address":"Rue Patiaux 45",
    "sg:city":"Waterloo",
    "sg:orig_category":"HUISBRANDOLIE",
    "sg:phone":"+32 2 354 50 42",
    "sg:postcode":"1410",
    "sg:province":"Brabant Wallon",
    "wof:name":"Marivoet-trans",
    "wof:placetype":"venue"
},
  "geometry": {"coordinates":[4.3705840111,50.7070388794],"type":"Point"}
}