{
  "type": "Feature",
  "properties": {
    "addr:full":"Jeroen & Peter Conventln 12 Kontich Antwerpen 2550",
    "addr:housenumber":"12",
    "addr:postcode":"2550",
    "iso:country":"BE",
    "sg:address":"Jeroen & Peter Conventln 12",
    "sg:city":"Kontich",
    "sg:orig_category":"Ziekenvervoer",
    "sg:phone":"+32 3 457 82 12",
    "sg:postcode":"2550",
    "sg:province":"Antwerpen",
    "wof:name":"Ambulance Centrum",
    "wof:placetype":"venue"
},
  "geometry": {"coordinates":[4.4331111908,51.1255950928],"type":"Point"}
}