{
  "type": "Feature",
  "properties": {
    "iso:country":"BE",
    "sg:address":"Industriepark Noord 17",
    "sg:city":"Beernem",
    "sg:orig_category":"Metaalafval, schrootrecyclage and sloperijen",
    "sg:phone":"+32 50 79 16 10",
    "sg:postcode":"8730",
    "sg:province":"West-Vlaanderen",
    "wof:name":"Volvo/cs-parts Bvba",
    "wof:placetype":"venue"
},
  "geometry": {"coordinates":[3.3411419392,51.1296653748],"type":"Point"}
}