{
  "type": "Feature",
  "properties": {
    "iso:country":"BE",
    "sg:address":"Chauss\u00c9e De Dinant 137",
    "sg:city":"Profondeville",
    "sg:orig_category":"Editeurs de revues and p\u00e9riodiques. Editeurs de journaux",
    "sg:phone":"+32 81 41 24 05",
    "sg:postcode":"5170",
    "sg:province":"Namur",
    "wof:name":"Remue-meninges",
    "wof:placetype":"venue"
},
  "geometry": {"coordinates":[4.8725409508,50.3578720093],"type":"Point"}
}