{
  "type": "Feature",
  "properties": {
    "addr:full":"Molenstraat 15 Genk Limburg 3600",
    "addr:housenumber":"15",
    "addr:postcode":"3600",
    "addr:street":"Molenstraat",
    "iso:country":"BE",
    "sg:address":"Molenstraat 15",
    "sg:city":"Genk",
    "sg:classifiers":[
        {
            "category":"Professional",
            "subcategory":"Lawyer & Legal Services",
            "type":"Services"
        }
    ],
    "sg:phone":"+32 89 35 22 70",
    "sg:postcode":"3600",
    "sg:province":"Limburg",
    "sg:tags":[
        "notary"
    ],
    "wof:name":"Van Den Hove L",
    "wof:placetype":"venue"
},
  "geometry": {"coordinates":[5.5013332367,50.9645195007],"type":"Point"}
}