{
  "type": "Feature",
  "properties": {
    "iso:country":"BE",
    "sg:address":"Vina Bovypark 61",
    "sg:city":"Gent",
    "sg:orig_category":"M\u00e9decins and sp\u00e9cialistes",
    "sg:phone":"+32 9 220 27 20",
    "sg:postcode":"9000",
    "sg:province":"Oost-Vlaanderen",
    "wof:name":"Magdalena Van Nieuwenhove",
    "wof:placetype":"venue"
},
  "geometry": {"coordinates":[3.7051301003,51.035949707],"type":"Point"}
}