{
  "type": "Feature",
  "properties": {
    "addr:full":"Frumont 23 Onhaye Namur 5520",
    "addr:housenumber":"23",
    "addr:postcode":"5520",
    "addr:street":"Frumont",
    "iso:country":"BE",
    "sg:address":"Frumont 23",
    "sg:city":"Onhaye",
    "sg:classifiers":[
        {
            "category":"Freight",
            "type":"Transportation"
        }
    ],
    "sg:phone":"+32 82 64 42 39",
    "sg:postcode":"5520",
    "sg:province":"Namur",
    "sg:tags":[
        "-",
        "transport"
    ],
    "wof:name":"Botton Grandfils",
    "wof:placetype":"venue"
},
  "geometry": {"coordinates":[4.8449950218,50.2338867188],"type":"Point"}
}