{
  "type": "Feature",
  "properties": {
    "iso:country":"BE",
    "sg:address":"Grand Enclos 4",
    "sg:city":"Comblain-au-pont (poulseur)",
    "sg:classifiers":[
        {
            "category":"Real Estate",
            "subcategory":"Real Estate Services",
            "type":"Services"
        }
    ],
    "sg:phone":"+32 4 380 45 58",
    "sg:postcode":"4171",
    "sg:province":"Li\u00e8ge",
    "wof:name":"Matassi R",
    "wof:placetype":"venue"
},
  "geometry": {"coordinates":[5.5595998764,50.5019454956],"type":"Point"}
}