{
  "type": "Feature",
  "properties": {
    "iso:country":"BE",
    "sg:address":"Rue Des Ch\u00c2taigniers 58",
    "sg:city":"La Louviere",
    "sg:classifiers":[
        {
            "category":"Arena",
            "subcategory":"Sports Club",
            "type":"Entertainment"
        }
    ],
    "sg:phone":"+32 64 21 19 01",
    "sg:postcode":"7100",
    "sg:province":"Hainaut",
    "sg:tags":[
        "terrain",
        "hors",
        "de",
        "installation",
        "sportifs"
    ],
    "wof:name":"Axial",
    "wof:placetype":"venue"
},
  "geometry": {"coordinates":[4.1711177826,50.4654197693],"type":"Point"}
}