{
  "type": "Feature",
  "properties": {
    "addr:full":"Wateringstraat 99 Mol Antwerpen 2400",
    "addr:housenumber":"99",
    "addr:postcode":"2400",
    "addr:street":"Wateringstraat",
    "iso:country":"BE",
    "sg:address":"Wateringstraat 99",
    "sg:city":"Mol",
    "sg:orig_category":"Woningbouw",
    "sg:phone":"+32 14 81 64 15",
    "sg:postcode":"2400",
    "sg:province":"Antwerpen",
    "wof:name":"A B S",
    "wof:placetype":"venue"
},
  "geometry": {"coordinates":[5.2037172318,51.2161445618],"type":"Point"}
}