{
  "type": "Feature",
  "properties": {
    "addr:full":"Molenbosweg 37 Wuustwezel Antwerpen 2990",
    "addr:housenumber":"37",
    "addr:postcode":"2990",
    "addr:street":"Molenbosweg",
    "iso:country":"BE",
    "sg:address":"Molenbosweg 37",
    "sg:city":"Wuustwezel",
    "sg:orig_category":"Installation de menuiserie m\u00e9tallique. Installation de menuiserie en bois and plastique",
    "sg:phone":"+32 3 669 74 27",
    "sg:postcode":"2990",
    "sg:province":"Antwerpen",
    "wof:name":"Stes",
    "wof:placetype":"venue"
},
  "geometry": {"coordinates":[4.648827076,51.4059753418],"type":"Point"}
}