{
  "type": "Feature",
  "properties": {
    "iso:country":"BE",
    "sg:address":"Gistelse Steenweg 200",
    "sg:city":"Brugge",
    "sg:orig_category":"Kapsalons",
    "sg:phone":"+32 50 38 92 72",
    "sg:postcode":"8200",
    "sg:province":"West-Vlaanderen",
    "wof:name":"Marie-christine Minten",
    "wof:placetype":"venue"
},
  "geometry": {"coordinates":[3.1987531185,51.2011260986],"type":"Point"}
}