{
  "type": "Feature",
  "properties": {
    "iso:country":"BE",
    "sg:address":"Zillebeke-dorp 44",
    "sg:city":"Ieper (zillebeke)",
    "sg:classifiers":[
        {
            "category":"Retail",
            "subcategory":"Repair Shop",
            "type":"Services"
        }
    ],
    "sg:phone":"+32 57 20 38 06",
    "sg:postcode":"8902",
    "sg:province":"West-Vlaanderen",
    "sg:tags":[
        "-",
        "mainten",
        "watch",
        "clock"
    ],
    "wof:name":"Lepla N",
    "wof:placetype":"venue"
},
  "geometry": {"coordinates":[2.9226160049,50.8345909119],"type":"Point"}
}