{
  "type": "Feature",
  "properties": {
    "addr:full":"Rue De Rotterdam 44 Li\u00e8ge 1 Li\u00e8ge 4000",
    "addr:housenumber":"44;1",
    "addr:postcode":"4000",
    "addr:street":"Rue De Rotterdam",
    "iso:country":"BE",
    "sg:address":"Rue De Rotterdam 44",
    "sg:city":"Li\u00e8ge 1",
    "sg:classifiers":[
        {
            "category":"Real Estate",
            "subcategory":"Architect",
            "type":"Services"
        }
    ],
    "sg:phone":"+32 4 367 67 07",
    "sg:postcode":"4000",
    "sg:province":"Li\u00e8ge",
    "wof:name":"Ziane F-x",
    "wof:placetype":"venue"
},
  "geometry": {"coordinates":[5.5663981438,50.6302757263],"type":"Point"}
}