{
  "type": "Feature",
  "properties": {
    "iso:country":"BE",
    "sg:address":"Pater Beckxstraat 10",
    "sg:city":"Scherpenheuvel-zichem",
    "sg:orig_category":"M\u00e9decins and sp\u00e9cialistes",
    "sg:phone":"+32 13 78 24 27",
    "sg:postcode":"3271",
    "sg:province":"Vlaams-Brabant",
    "wof:name":"Karine Verwimp",
    "wof:placetype":"venue"
},
  "geometry": {"coordinates":[4.9857740402,51.0009078979],"type":"Point"}
}