{
  "type": "Feature",
  "properties": {
    "addr:full":"Sint-jakobsstraat 36 Brugge West-Vlaanderen 8000",
    "addr:housenumber":"36",
    "addr:postcode":"8000",
    "addr:street":"Sint-Jakobsstraat",
    "iso:country":"BE",
    "sg:address":"Sint-jakobsstraat 36",
    "sg:city":"Brugge",
    "sg:orig_category":"Artiestenbureaus",
    "sg:phone":"+32 50 33 27 52",
    "sg:postcode":"8000",
    "sg:province":"West-Vlaanderen",
    "wof:name":"Bureau De Voogt",
    "wof:placetype":"venue"
},
  "geometry": {"coordinates":[3.2215390205,51.2101554871],"type":"Point"}
}