{
  "type": "Feature",
  "properties": {
    "iso:country":"BE",
    "sg:address":"Rue L\u00e9opold I 264",
    "sg:city":"Bruxelles",
    "sg:orig_category":"Non-Classified Establishments",
    "sg:phone":"+32 2 425 86 23",
    "sg:postcode":"1020",
    "sg:province":"Bruxelles-Capitale",
    "wof:name":"Sodami Bvba",
    "wof:placetype":"venue"
},
  "geometry": {"coordinates":[4.3392901421,50.8765029907],"type":"Point"}
}