{
  "type": "Feature",
  "properties": {
    "addr:full":"Rue De La Vigne 32 Braives Li\u00e8ge 4260",
    "addr:housenumber":"32",
    "addr:postcode":"4260",
    "addr:street":"Rue De La Vigne",
    "iso:country":"BE",
    "sg:address":"Rue De La Vigne 32",
    "sg:city":"Braives",
    "sg:orig_category":"Brood, gebak and snoepgoed",
    "sg:phone":"+32 19 69 72 75",
    "sg:postcode":"4260",
    "sg:province":"Li\u00e8ge",
    "wof:name":"Philippe Debroux",
    "wof:placetype":"venue"
},
  "geometry": {"coordinates":[5.1388177872,50.6292457581],"type":"Point"}
}