{
  "type": "Feature",
  "properties": {
    "iso:country":"BE",
    "sg:address":"Molenstraat 96",
    "sg:city":"Heist-op-den-berg",
    "sg:classifiers":[
        {
            "category":"Home & Garden",
            "subcategory":"Home Furnishings",
            "type":"Retail Goods"
        }
    ],
    "sg:phone":"+32 15 24 12 75",
    "sg:postcode":"2220",
    "sg:province":"Antwerpen",
    "sg:tags":[
        "-",
        "bed",
        "mattress"
    ],
    "wof:name":"Ledegen-verlinden Bvba",
    "wof:placetype":"venue"
},
  "geometry": {"coordinates":[4.7214689255,51.0812606812],"type":"Point"}
}