{
  "type": "Feature",
  "properties": {
    "iso:country":"BE",
    "sg:address":"Rue De L\u00b4emancipation 2",
    "sg:city":"Herstal",
    "sg:orig_category":"Enseignement maternel and primaire",
    "sg:phone":"+32 4 227 42 90",
    "sg:postcode":"4041",
    "sg:province":"Li\u00e8ge",
    "wof:name":"E.f.c. Cascogniers",
    "wof:placetype":"venue"
},
  "geometry": {"coordinates":[5.5849199295,50.6724891663],"type":"Point"}
}