{
  "type": "Feature",
  "properties": {
    "iso:country":"BE",
    "sg:address":"Oude Godstraat 19",
    "sg:city":"Edegem",
    "sg:classifiers":[
        {
            "category":"Building & Trades",
            "subcategory":"Electrical",
            "type":"Services"
        }
    ],
    "sg:phone":"+32 475 69 49 86",
    "sg:postcode":"2650",
    "sg:province":"Antwerpen",
    "sg:tags":[
        "electric",
        "-",
        "housewiring",
        "contractor"
    ],
    "wof:name":"Electro-dingeloo",
    "wof:placetype":"venue"
},
  "geometry": {"coordinates":[4.4447212219,51.1586952209],"type":"Point"}
}