{
  "type": "Feature",
  "properties": {
    "iso:country":"BE",
    "sg:address":"Rue Du Commerce 93c",
    "sg:city":"Ciney",
    "sg:classifiers":[
        {
            "category":"Health Services",
            "subcategory":"Doctor",
            "type":"Services"
        }
    ],
    "sg:phone":"+32 83 21 20 21",
    "sg:postcode":"5590",
    "sg:province":"Namur",
    "sg:tags":[
        "medicinephysicians",
        "surgeon"
    ],
    "wof:name":"Calcus C",
    "wof:placetype":"venue"
},
  "geometry": {"coordinates":[5.0956401825,50.2917976379],"type":"Point"}
}