{
  "type": "Feature",
  "properties": {
    "addr:full":"Kleine Reesdijk 67 Turnhout Antwerpen 2300",
    "addr:housenumber":"67",
    "addr:postcode":"2300",
    "addr:street":"Kleine Reesdijk",
    "iso:country":"BE",
    "sg:address":"Kleine Reesdijk 67",
    "sg:city":"Turnhout",
    "sg:orig_category":"Producteurs de l\u00e9gumes",
    "sg:phone":"+32 14 41 45 13",
    "sg:postcode":"2300",
    "sg:province":"Antwerpen",
    "wof:name":"Ludovicus Proost",
    "wof:placetype":"venue"
},
  "geometry": {"coordinates":[4.9590668678,51.2864761353],"type":"Point"}
}