{
  "type": "Feature",
  "properties": {
    "addr:full":"Avenue De Spa 31 Verviers Li\u00e8ge 4800",
    "addr:housenumber":"31",
    "addr:postcode":"4800",
    "addr:street":"Avenue De Spa",
    "iso:country":"BE",
    "sg:address":"Avenue De Spa 31",
    "sg:city":"Verviers",
    "sg:classifiers":[
        {
            "category":"Social Services",
            "type":"Services"
        }
    ],
    "sg:phone":"+32 87 22 18 18",
    "sg:postcode":"4800",
    "sg:province":"Li\u00e8ge",
    "wof:name":"Familles D'accueil Asbl",
    "wof:placetype":"venue"
},
  "geometry": {"coordinates":[5.8635549545,50.5825157166],"type":"Point"}
}