{
  "type": "Feature",
  "properties": {
    "addr:full":"Turnhoutsebaan 639 Wijnegem Antwerpen 2110",
    "addr:housenumber":"639",
    "addr:postcode":"2110",
    "addr:street":"Turnhoutsebaan",
    "iso:country":"BE",
    "sg:address":"Turnhoutsebaan 639",
    "sg:city":"Wijnegem",
    "sg:orig_category":"Plaatsen van vloer- and muurbekleding Schilders",
    "sg:phone":"+32 3 353 74 19",
    "sg:postcode":"2110",
    "sg:province":"Antwerpen",
    "wof:name":"Roland Coene",
    "wof:placetype":"venue"
},
  "geometry": {"coordinates":[4.5518298149,51.2310562134],"type":"Point"}
}