{
  "type": "Feature",
  "properties": {
    "iso:country":"BE",
    "sg:address":"Lozenberg 10",
    "sg:city":"Zaventem",
    "sg:orig_category":"Bedrijvencentra and kantoordiensten",
    "sg:phone":"+32 2 711 46 50",
    "sg:postcode":"1930",
    "sg:province":"Vlaams-Brabant",
    "wof:name":"Tclm-business Center",
    "wof:placetype":"venue"
},
  "geometry": {"coordinates":[4.4630317688,50.8691101074],"type":"Point"}
}