{
  "type": "Feature",
  "properties": {
    "iso:country":"BE",
    "sg:address":"Chemin Saint-pierre 19",
    "sg:city":"Wellin",
    "sg:classifiers":[
        {
            "category":"Retail",
            "subcategory":"Veterinary Services",
            "type":"Services"
        }
    ],
    "sg:phone":"+32 84 38 96 24",
    "sg:postcode":"6920",
    "sg:province":"Luxembourg",
    "sg:tags":[
        "veterinarian"
    ],
    "wof:name":"Dujardin M",
    "wof:placetype":"venue"
},
  "geometry": {"coordinates":[5.1255040169,50.0861968994],"type":"Point"}
}