{
  "type": "Feature",
  "properties": {
    "iso:country":"BE",
    "sg:address":"Mwami Mutaradreef 21",
    "sg:city":"Keerbergen",
    "sg:classifiers":[
        {
            "category":"Professional",
            "subcategory":"Computer Services",
            "type":"Services"
        }
    ],
    "sg:phone":"+32 16 85 09 14",
    "sg:postcode":"3140",
    "sg:province":"Vlaams-Brabant",
    "sg:tags":[
        "-",
        "processing",
        "data",
        "software"
    ],
    "wof:name":"Ecq Applications Bvba",
    "wof:placetype":"venue"
},
  "geometry": {"coordinates":[4.6901187897,51.0006980896],"type":"Point"}
}