{
  "type": "Feature",
  "properties": {
    "iso:country":"BE",
    "sg:address":"Reynaertstraat 1bb",
    "sg:city":"Wielsbeke",
    "sg:classifiers":[
        {
            "category":"Personal",
            "subcategory":"Beauty Salon",
            "type":"Services"
        }
    ],
    "sg:phone":"+32 56 66 88 98",
    "sg:postcode":"8710",
    "sg:province":"West-Vlaanderen",
    "sg:tags":[
        "de",
        "coiffure"
    ],
    "wof:name":"Coiffure Ingrid",
    "wof:placetype":"venue"
},
  "geometry": {"coordinates":[3.3637750149,50.9084587097],"type":"Point"}
}