{
  "type": "Feature",
  "properties": {
    "iso:country":"BE",
    "sg:address":"Kauwstraat 94",
    "sg:city":"Herzele",
    "sg:orig_category":"Installatie van houten of kunststof schrijnwerk Installatie van metalen schrijnwerk MEUBELONTWERP AN",
    "sg:phone":"+32 54 50 00 94",
    "sg:postcode":"9550",
    "sg:province":"Oost-Vlaanderen",
    "wof:name":"Gebr. Van Steenberghe",
    "wof:placetype":"venue"
},
  "geometry": {"coordinates":[3.9152131081,50.8580970764],"type":"Point"}
}