{
  "type": "Feature",
  "properties": {
    "iso:country":"BE",
    "sg:address":"Alfons Pieterslaan 59b4",
    "sg:city":"Oostende",
    "sg:orig_category":"Administration d'immeubles",
    "sg:phone":"+32 59 80 16 14",
    "sg:postcode":"8400",
    "sg:province":"West-Vlaanderen",
    "wof:name":"Synd. Accou Michel",
    "wof:placetype":"venue"
},
  "geometry": {"coordinates":[2.9118249416,51.2255935669],"type":"Point"}
}