{
  "type": "Feature",
  "properties": {
    "addr:full":"Speurtstraat 3 Lede Oost-Vlaanderen 9340",
    "addr:housenumber":"3",
    "addr:postcode":"9340",
    "addr:street":"Speurtstraat",
    "iso:country":"BE",
    "sg:address":"Speurtstraat 3",
    "sg:city":"Lede",
    "sg:orig_category":"Enseignement maternel and primaire",
    "sg:phone":"+32 9 369 44 46",
    "sg:postcode":"9340",
    "sg:province":"Oost-Vlaanderen",
    "wof:name":"Vrije Basisschool",
    "wof:placetype":"venue"
},
  "geometry": {"coordinates":[3.9006330967,50.9587783813],"type":"Point"}
}