{
  "type": "Feature",
  "properties": {
    "iso:country":"BE",
    "sg:address":"Snaggaardstraat 9",
    "sg:city":"Brugge",
    "sg:classifiers":[
        {
            "category":"Education",
            "subcategory":"School",
            "type":"Public Place"
        }
    ],
    "sg:phone":"+32 50 34 03 41",
    "sg:postcode":"8000",
    "sg:province":"West-Vlaanderen",
    "sg:tags":[
        "primary"
    ],
    "wof:name":"Vrije Lagere Scholen",
    "wof:placetype":"venue"
},
  "geometry": {"coordinates":[3.2250928879,51.2124214172],"type":"Point"}
}