{
  "type": "Feature",
  "properties": {
    "iso:country":"BE",
    "sg:address":"Langendamdreef 39",
    "sg:city":"Aalter",
    "sg:classifiers":[
        {
            "category":"Shopping",
            "subcategory":"Stationery & Office Supplies",
            "type":"Retail Goods"
        }
    ],
    "sg:phone":"+32 9 374 78 72",
    "sg:postcode":"9880",
    "sg:province":"Oost-Vlaanderen",
    "sg:tags":[
        "fab",
        "carton",
        "en",
        "papier",
        "emballages"
    ],
    "wof:name":"Edelmann Benelux",
    "wof:placetype":"venue"
},
  "geometry": {"coordinates":[3.4681279659,51.0785827637],"type":"Point"}
}