{
  "type": "Feature",
  "properties": {
    "iso:country":"BE",
    "sg:address":"Rue Wayez 17",
    "sg:city":"Anderlecht/anderlecht",
    "sg:orig_category":"R\u00e9parations d'appareils \u00e9lectrom\u00e9nagers. Electrom\u00e9nager, t\u00e9l\u00e9visions and radios",
    "sg:phone":"+32 2 523 42 35",
    "sg:postcode":"1070",
    "sg:province":"Bruxelles-Capitale",
    "wof:name":"Maison Electrica",
    "wof:placetype":"venue"
},
  "geometry": {"coordinates":[4.3163590431,50.836566925],"type":"Point"}
}