{
  "type": "Feature",
  "properties": {
    "iso:country":"BE",
    "sg:address":"Rue L\u00c9on Colleaux 41",
    "sg:city":"Virton",
    "sg:orig_category":"Pr\u00eats hypoth\u00e9caires and cr\u00e9dits immobiliers. Cr\u00e9dit \u00e0 la consommation",
    "sg:phone":"+32 63 57 00 93",
    "sg:postcode":"6762",
    "sg:province":"Luxembourg",
    "wof:name":"Lorraine & Ardenne Ouvr.",
    "wof:placetype":"venue"
},
  "geometry": {"coordinates":[5.5329089165,49.5549049377],"type":"Point"}
}