{
  "type": "Feature",
  "properties": {
    "addr:full":"Spartalaan 3 Zoersel Antwerpen 2980",
    "addr:housenumber":"3",
    "addr:postcode":"2980",
    "addr:street":"Spartalaan",
    "iso:country":"BE",
    "sg:address":"Spartalaan 3",
    "sg:city":"Zoersel",
    "sg:orig_category":"Bottle caps, crowncorks and stoppers",
    "sg:phone":"+32 3 385 35 59",
    "sg:postcode":"2980",
    "sg:province":"Antwerpen",
    "wof:name":"Bertels Danny",
    "wof:placetype":"venue"
},
  "geometry": {"coordinates":[4.713435173,51.269985199],"type":"Point"}
}