{
  "type": "Feature",
  "properties": {
    "iso:country":"BE",
    "sg:address":"Rue De La Montagne 9",
    "sg:city":"Incourt (pi\u00e8trebais)",
    "sg:classifiers":[
        {
            "category":"Personal",
            "subcategory":"Psychics & Astrologers",
            "type":"Services"
        }
    ],
    "sg:phone":"+32 10 84 49 61",
    "sg:postcode":"1315",
    "sg:province":"Brabant Wallon",
    "sg:tags":[
        "astrology"
    ],
    "wof:name":"Frea",
    "wof:placetype":"venue"
},
  "geometry": {"coordinates":[4.799115181,50.6915283203],"type":"Point"}
}