{
  "type": "Feature",
  "properties": {
    "addr:full":"Andr\u00c9 Dumontlaan 210 Genk Limburg 3600",
    "addr:housenumber":"210",
    "addr:postcode":"3600",
    "addr:street":"Dumontlaan",
    "iso:country":"BE",
    "sg:address":"Andr\u00c9 Dumontlaan 210",
    "sg:city":"Genk",
    "sg:orig_category":"Epiceries. Grands magasins",
    "sg:phone":"+32 89 38 32 08",
    "sg:postcode":"3600",
    "sg:province":"Limburg",
    "wof:name":"Bazar St-lambert",
    "wof:placetype":"venue"
},
  "geometry": {"coordinates":[5.4990148544,50.9635848999],"type":"Point"}
}