{
  "type": "Feature",
  "properties": {
    "iso:country":"BE",
    "sg:address":"Emanuel Hielstraat 35",
    "sg:city":"Dendermonde (sint-gillis-bij-dendermonde)",
    "sg:classifiers":[
        {
            "category":"Health Services",
            "subcategory":"Health Practitioner",
            "type":"Services"
        }
    ],
    "sg:phone":"+32 52 21 01 09",
    "sg:postcode":"9200",
    "sg:province":"Oost-Vlaanderen",
    "sg:tags":[
        "physiotherapist"
    ],
    "wof:name":"De Decker Vincent",
    "wof:placetype":"venue"
},
  "geometry": {"coordinates":[4.1065192223,51.0208930969],"type":"Point"}
}