{
  "type": "Feature",
  "properties": {
    "addr:full":"Grote Markt 79 Box 2 Zelzate Oost-Vlaanderen 9060",
    "addr:housenumber":"79;2",
    "addr:postcode":"9060",
    "addr:street":"Grote Markt;Box",
    "iso:country":"BE",
    "sg:address":"Grote Markt 79 Box 2",
    "sg:city":"Zelzate",
    "sg:classifiers":[
        {
            "category":"Real Estate",
            "subcategory":"Architect",
            "type":"Services"
        }
    ],
    "sg:phone":"+32 9 345 41 26",
    "sg:postcode":"9060",
    "sg:province":"Oost-Vlaanderen",
    "wof:name":"De Lust L",
    "wof:placetype":"venue"
},
  "geometry": {"coordinates":[3.8117470741,51.2000045776],"type":"Point"}
}