{
  "type": "Feature",
  "properties": {
    "addr:full":"Rue Du Hazoir 49 La Bruyere Namur 5080",
    "addr:housenumber":"49",
    "addr:postcode":"5080",
    "addr:street":"Rue Du Hazoir;La Bruyere",
    "iso:country":"BE",
    "sg:address":"Rue Du Hazoir 49",
    "sg:city":"La Bruyere",
    "sg:orig_category":"Messageries",
    "sg:phone":"+32 81 21 05 72",
    "sg:postcode":"5080",
    "sg:province":"Namur",
    "wof:name":"E.d.c. De Waele",
    "wof:placetype":"venue"
},
  "geometry": {"coordinates":[4.8261609077,50.5205307007],"type":"Point"}
}