{
  "type": "Feature",
  "properties": {
    "iso:country":"BE",
    "sg:address":"Rue Du Geer 28",
    "sg:city":"Geer (lens-saint-servais)",
    "sg:classifiers":[
        {
            "category":"Professional",
            "subcategory":"Management & Consulting",
            "type":"Services"
        }
    ],
    "sg:phone":"+32 19 54 64 45",
    "sg:postcode":"4250",
    "sg:province":"Li\u00e8ge",
    "sg:tags":[
        "tax-consultants"
    ],
    "wof:name":"Lenaerts M",
    "wof:placetype":"venue"
},
  "geometry": {"coordinates":[5.1585412025,50.6648445129],"type":"Point"}
}