{
  "type": "Feature",
  "properties": {
    "iso:country":"BE",
    "sg:address":"Bassevillestraat 40",
    "sg:city":"Middelkerke (westende)",
    "sg:orig_category":"Non-Classified Establishments",
    "sg:phone":"+32 58 23 40 16",
    "sg:postcode":"8434",
    "sg:province":"West-Vlaanderen",
    "wof:name":"Zuivelhandel Desaever Bvba",
    "wof:placetype":"venue"
},
  "geometry": {"coordinates":[2.7568869591,51.1495056152],"type":"Point"}
}