{
  "type": "Feature",
  "properties": {
    "iso:country":"BE",
    "sg:address":"Vrijboomstraat 1",
    "sg:city":"Hamme",
    "sg:orig_category":"Instituts de beaut\u00e9",
    "sg:phone":"+32 52 48 33 28",
    "sg:postcode":"9220",
    "sg:province":"Oost-Vlaanderen",
    "wof:name":"Magda Van Riet",
    "wof:placetype":"venue"
},
  "geometry": {"coordinates":[4.1678800583,51.0492515564],"type":"Point"}
}