{
  "type": "Feature",
  "properties": {
    "addr:full":"Av.notre-dame De Lourdes 17 Jette Bruxelles-Capitale 1090",
    "addr:housenumber":"17",
    "addr:postcode":"1090",
    "iso:country":"BE",
    "sg:address":"Av.notre-dame De Lourdes 17",
    "sg:city":"Jette",
    "sg:orig_category":"D\u00e9corateurs d'int\u00e9rieur",
    "sg:phone":"+32 2 424 25 42",
    "sg:postcode":"1090",
    "sg:province":"Bruxelles-Capitale",
    "wof:name":"High D.",
    "wof:placetype":"venue"
},
  "geometry": {"coordinates":[4.3355221748,50.8729553223],"type":"Point"}
}