{
  "type": "Feature",
  "properties": {
    "addr:full":"Esenweg 99bc Diksmuide West-Vlaanderen 8600",
    "addr:housenumber":"99bc",
    "addr:postcode":"8600",
    "addr:street":"Esenweg",
    "iso:country":"BE",
    "sg:address":"Esenweg 99bc",
    "sg:city":"Diksmuide",
    "sg:orig_category":"V\u00e9t\u00e9rinaires",
    "sg:phone":"+32 51 50 18 40",
    "sg:postcode":"8600",
    "sg:province":"West-Vlaanderen",
    "wof:name":"Paul Lemahieu",
    "wof:placetype":"venue"
},
  "geometry": {"coordinates":[2.8806550503,51.0307846069],"type":"Point"}
}