{
  "type": "Feature",
  "properties": {
    "addr:full":"Pastoorsvijverweg 3 Rijkevorsel Antwerpen 2310",
    "addr:housenumber":"3",
    "addr:postcode":"2310",
    "addr:street":"Pastoorsvijverweg",
    "iso:country":"BE",
    "sg:address":"Pastoorsvijverweg 3",
    "sg:city":"Rijkevorsel",
    "sg:classifiers":[
        {
            "category":"Building & Trades",
            "subcategory":"Landscaping Services",
            "type":"Services"
        }
    ],
    "sg:phone":"+32 495 54 14 31",
    "sg:postcode":"2310",
    "sg:province":"Antwerpen",
    "sg:tags":[
        "nurseryman"
    ],
    "wof:name":"A.a. Penninckx Sierplantenkwekerij",
    "wof:placetype":"venue"
},
  "geometry": {"coordinates":[4.7792620659,51.3409461975],"type":"Point"}
}