{
  "type": "Feature",
  "properties": {
    "iso:country":"BE",
    "sg:address":"Leopoldstraat 11",
    "sg:city":"Zwevegem",
    "sg:classifiers":[
        {
            "category":"Banks & Credit Unions",
            "subcategory":"Financial Services",
            "type":"Services"
        }
    ],
    "sg:phone":"+32 56 75 50 69",
    "sg:postcode":"8550",
    "sg:province":"West-Vlaanderen",
    "sg:tags":[
        "loan",
        "mortgage"
    ],
    "wof:name":"Amez L Bvba",
    "wof:placetype":"venue"
},
  "geometry": {"coordinates":[3.338504076,50.8117523193],"type":"Point"}
}