{
  "type": "Feature",
  "properties": {
    "iso:country":"BE",
    "sg:address":"Rue Hors-ch\u00c2teau 64",
    "sg:city":"Li\u00c8ge",
    "sg:orig_category":"RESTAURANTS: ALIMENTATION SP\u00c9CIALIS\u00c9E",
    "sg:phone":"+32 4 223 04 08",
    "sg:postcode":"4000",
    "sg:province":"Li\u00e8ge",
    "wof:name":"Restaurant Le Bourbonnais",
    "wof:placetype":"venue"
},
  "geometry": {"coordinates":[5.5792980194,50.6471748352],"type":"Point"}
}