{
  "type": "Feature",
  "properties": {
    "iso:country":"BE",
    "sg:address":"Industrielaan 5",
    "sg:city":"Waregem",
    "sg:classifiers":[
        {
            "category":"Parking",
            "subcategory":"Garage",
            "type":"Transportation"
        }
    ],
    "sg:phone":"+32 56 60 34 44",
    "sg:postcode":"8790",
    "sg:province":"West-Vlaanderen",
    "sg:tags":[
        "prefabricated",
        "-"
    ],
    "wof:name":"Collstrop",
    "wof:placetype":"venue"
},
  "geometry": {"coordinates":[3.443666935,50.864982605],"type":"Point"}
}