{
  "type": "Feature",
  "properties": {
    "iso:country":"BE",
    "sg:address":"Liersesteenweg 244",
    "sg:city":"Mechelen",
    "sg:classifiers":[
        {
            "category":"Organizations",
            "subcategory":"Professional Association",
            "type":"Services"
        }
    ],
    "sg:phone":"+32 15 21 91 53",
    "sg:postcode":"2800",
    "sg:province":"Antwerpen",
    "sg:tags":[
        "artist",
        "make-up"
    ],
    "wof:name":"Art & Beauty Studio",
    "wof:placetype":"venue"
},
  "geometry": {"coordinates":[4.4776530266,51.0421867371],"type":"Point"}
}