{
  "type": "Feature",
  "properties": {
    "addr:full":"Rue De La Loi 49 La Louvi\u00e8re Hainaut 7100",
    "addr:housenumber":"49",
    "addr:postcode":"7100",
    "addr:street":"Rue De La Loi",
    "iso:country":"BE",
    "sg:address":"Rue De La Loi 49",
    "sg:city":"La Louvi\u00e8re",
    "sg:orig_category":"Solariums",
    "sg:phone":"+32 64 37 17 00",
    "sg:postcode":"7100",
    "sg:province":"Hainaut",
    "wof:name":"P'tit Baigneur",
    "wof:placetype":"venue"
},
  "geometry": {"coordinates":[4.1867070198,50.4770011902],"type":"Point"}
}