{
  "type": "Feature",
  "properties": {
    "addr:full":"Haltertstraat 273 Tielt-winge Vlaams-Brabant 3390",
    "addr:housenumber":"273",
    "addr:postcode":"3390",
    "addr:street":"Haltertstraat",
    "iso:country":"BE",
    "sg:address":"Haltertstraat 273",
    "sg:city":"Tielt-winge",
    "sg:orig_category":"Assurances. Banques and organismes de cr\u00e9dit",
    "sg:phone":"+32 16 50 10 98",
    "sg:postcode":"3390",
    "sg:province":"Vlaams-Brabant",
    "wof:name":"Ippa",
    "wof:placetype":"venue"
},
  "geometry": {"coordinates":[4.9038281441,50.9413642883],"type":"Point"}
}