{
  "type": "Feature",
  "properties": {
    "iso:country":"BE",
    "sg:address":"Rue Du Gay 82",
    "sg:city":"Falisolle",
    "sg:orig_category":"Charpentes and couvertures",
    "sg:phone":"+32 475 47 03 72",
    "sg:postcode":"5060",
    "sg:province":"Namur",
    "wof:name":"Collin Fr\u00c8res",
    "wof:placetype":"venue"
},
  "geometry": {"coordinates":[4.6357908249,50.413898468],"type":"Point"}
}