{
  "type": "Feature",
  "properties": {
    "addr:full":"Boulevard Du R\u00e9gent 58 Bruxelles Bruxelles-Capitale 1000",
    "addr:housenumber":"58",
    "addr:postcode":"1000",
    "addr:street":"Boulevard Du Re\u0301Gent",
    "iso:country":"BE",
    "sg:address":"Boulevard Du R\u00e9gent 58",
    "sg:city":"Bruxelles",
    "sg:classifiers":[
        {
            "category":"Social Services",
            "type":"Services"
        }
    ],
    "sg:phone":"+32 2 502 43 33",
    "sg:postcode":"1000",
    "sg:province":"Bruxelles-Capitale",
    "wof:name":"Care International",
    "wof:placetype":"venue"
},
  "geometry": {"coordinates":[4.3686618805,50.8488311768],"type":"Point"}
}