{
  "type": "Feature",
  "properties": {
    "iso:country":"BE",
    "sg:address":"Westrozebekestraat 36",
    "sg:city":"Staden (oostnieuwkerke)",
    "sg:classifiers":[
        {
            "category":"Professional",
            "type":"Services"
        }
    ],
    "sg:phone":"+32 51 25 12 26",
    "sg:postcode":"8840",
    "sg:province":"West-Vlaanderen",
    "sg:tags":[
        "industrial",
        "work",
        "-",
        "maintenance"
    ],
    "wof:name":"Algemene Maintenance I.m.k. Bvba",
    "wof:placetype":"venue"
},
  "geometry": {"coordinates":[3.0508410931,50.9425048828],"type":"Point"}
}