{
  "type": "Feature",
  "properties": {
    "iso:country":"BE",
    "sg:address":"Avenue Des Sept Bonniers 41",
    "sg:city":"Bruxelles (uccle)",
    "sg:classifiers":[
        {
            "category":"Professional",
            "subcategory":"Management & Consulting",
            "type":"Services"
        }
    ],
    "sg:phone":"+32 2 343 17 04",
    "sg:postcode":"1180",
    "sg:province":"Bruxelles-Capitale",
    "sg:tags":[
        "consultant"
    ],
    "wof:name":"T M 2 Sprl",
    "wof:placetype":"venue"
},
  "geometry": {"coordinates":[4.3370890617,50.8135528564],"type":"Point"}
}