{
  "type": "Feature",
  "properties": {
    "addr:full":"Avenue Moli\u00e8re 503 Bruxelles (ixelles) Bruxelles-Capitale 1050",
    "addr:housenumber":"503",
    "addr:postcode":"1050",
    "addr:street":"Avenue Molie\u0300Re",
    "iso:country":"BE",
    "sg:address":"Avenue Moli\u00e8re 503",
    "sg:city":"Bruxelles (ixelles)",
    "sg:classifiers":[
        {
            "category":"Professional",
            "subcategory":"Accounting & Tax Preparation",
            "type":"Services"
        }
    ],
    "sg:phone":"+32 2 347 77 33",
    "sg:postcode":"1050",
    "sg:province":"Bruxelles-Capitale",
    "sg:tags":[
        "bookkeeper"
    ],
    "wof:name":"Duhem X",
    "wof:placetype":"venue"
},
  "geometry": {"coordinates":[4.3654417992,50.8165550232],"type":"Point"}
}