{
  "type": "Feature",
  "properties": {
    "addr:full":"Langekoeistalstraat 8 Middelkerke West-Vlaanderen 8432",
    "addr:housenumber":"8",
    "addr:postcode":"8432",
    "addr:street":"Langekoeistalstraat",
    "iso:country":"BE",
    "sg:address":"Langekoeistalstraat 8",
    "sg:city":"Middelkerke",
    "sg:orig_category":"Eleveurs and marchands de porcs. Eleveurs de bovins",
    "sg:phone":"+32 59 27 70 59",
    "sg:postcode":"8432",
    "sg:province":"West-Vlaanderen",
    "wof:name":"Julien Devriendt",
    "wof:placetype":"venue"
},
  "geometry": {"coordinates":[2.8773488998,51.1767501831],"type":"Point"}
}