{
  "type": "Feature",
  "properties": {
    "iso:country":"BE",
    "sg:address":"Rue Sainte-anne 4",
    "sg:city":"Pont-\u00e0-celles (luttre)",
    "sg:classifiers":[
        {
            "category":"Retail",
            "subcategory":"Auto Repair",
            "type":"Services"
        }
    ],
    "sg:phone":"+32 71 84 27 63",
    "sg:postcode":"6238",
    "sg:province":"Hainaut",
    "sg:tags":[
        "garage"
    ],
    "wof:name":"Garage Olivier",
    "wof:placetype":"venue"
},
  "geometry": {"coordinates":[4.3888850212,50.5083236694],"type":"Point"}
}