{
  "type": "Feature",
  "properties": {
    "iso:country":"BE",
    "sg:address":"Avenue Albert Elisabeth 66 Box 7",
    "sg:city":"Bruxelles (woluwe-saint-lambert)",
    "sg:classifiers":[
        {
            "category":"Professional",
            "subcategory":"Lawyer & Legal Services",
            "type":"Services"
        }
    ],
    "sg:phone":"+32 2 732 81 49",
    "sg:postcode":"1200",
    "sg:province":"Bruxelles-Capitale",
    "wof:name":"Kesteloot Vincent",
    "wof:placetype":"venue"
},
  "geometry": {"coordinates":[4.4028091431,50.8404121399],"type":"Point"}
}