{
  "type": "Feature",
  "properties": {
    "iso:country":"BE",
    "sg:address":"Korte Zavelstraat 9",
    "sg:city":"Antwerpen",
    "sg:classifiers":[
        {
            "category":"Bakery",
            "type":"Food & Drink"
        }
    ],
    "sg:phone":"+32 3 232 19 98",
    "sg:postcode":"2060",
    "sg:province":"Antwerpen",
    "sg:tags":[
        "confectioner",
        "baker"
    ],
    "wof:name":"Meftah M",
    "wof:placetype":"venue"
},
  "geometry": {"coordinates":[4.4259881973,51.2231521606],"type":"Point"}
}