{
  "type": "Feature",
  "properties": {
    "iso:country":"BE",
    "sg:address":"Bremstraat 2a",
    "sg:city":"Keerbergen",
    "sg:classifiers":[
        {
            "category":"Professional",
            "subcategory":"Management & Consulting",
            "type":"Services"
        }
    ],
    "sg:phone":"+32 15 52 51 38",
    "sg:postcode":"3140",
    "sg:province":"Vlaams-Brabant",
    "sg:tags":[
        "consultant"
    ],
    "wof:name":"Dg - Mc Bvba",
    "wof:placetype":"venue"
},
  "geometry": {"coordinates":[4.6315917969,50.9973106384],"type":"Point"}
}