{
  "type": "Feature",
  "properties": {
    "addr:full":"All\u00c9e Des Liserons 6 Gerpinnes Hainaut 6280",
    "addr:housenumber":"6",
    "addr:postcode":"6280",
    "addr:street":"Alle\u0301E Des Liserons;Hainaut",
    "iso:country":"BE",
    "sg:address":"All\u00c9e Des Liserons 6",
    "sg:city":"Gerpinnes",
    "sg:orig_category":"Landmeters",
    "sg:phone":"+32 71 21 54 84",
    "sg:postcode":"6280",
    "sg:province":"Hainaut",
    "wof:name":"Olivier Raucroix",
    "wof:placetype":"venue"
},
  "geometry": {"coordinates":[4.4818949699,50.3450965881],"type":"Point"}
}