{
  "type": "Feature",
  "properties": {
    "addr:full":"Langestraat 95 Aarschot Vlaams-Brabant 3202",
    "addr:housenumber":"95",
    "addr:postcode":"3202",
    "addr:street":"Langestraat",
    "iso:country":"BE",
    "sg:address":"Langestraat 95",
    "sg:city":"Aarschot",
    "sg:orig_category":"Installatie van houten of kunststof schrijnwerk",
    "sg:phone":"+32 16 50 02 18",
    "sg:postcode":"3202",
    "sg:province":"Vlaams-Brabant",
    "wof:name":"Tuerlinckx",
    "wof:placetype":"venue"
},
  "geometry": {"coordinates":[4.9034771919,50.9827651978],"type":"Point"}
}