{
  "type": "Feature",
  "properties": {
    "iso:country":"BE",
    "sg:address":"Henleykaai 4",
    "sg:city":"Gent",
    "sg:classifiers":[
        {
            "category":"Restaurant",
            "type":"Food & Drink"
        }
    ],
    "sg:phone":"+32 9 234 13 84",
    "sg:postcode":"9000",
    "sg:province":"Oost-Vlaanderen",
    "wof:name":"Yanko",
    "wof:placetype":"venue"
},
  "geometry": {"coordinates":[3.7166790962,51.0427398682],"type":"Point"}
}