{
  "type": "Feature",
  "properties": {
    "addr:full":"Pierstraat 425 Rumst (groot) Antwerpen 2840",
    "addr:housenumber":"425",
    "addr:postcode":"2840",
    "addr:street":"Pierstraat;Groot Antwerpen",
    "iso:country":"BE",
    "sg:address":"Pierstraat 425",
    "sg:city":"Rumst (groot)",
    "sg:orig_category":"Dancings and bo\u00eetes de nuit",
    "sg:phone":"+32 3 888 58 57",
    "sg:postcode":"2840",
    "sg:province":"Antwerpen",
    "wof:name":"Escape",
    "wof:placetype":"venue"
},
  "geometry": {"coordinates":[4.3631300926,51.1099205017],"type":"Point"}
}