{
  "type": "Feature",
  "properties": {
    "addr:full":"Rue De Waremme 29 Berloz Li\u00e8ge 4257",
    "addr:housenumber":"29",
    "addr:postcode":"4257",
    "addr:street":"Rue De Waremme",
    "iso:country":"BE",
    "sg:address":"Rue De Waremme 29",
    "sg:city":"Berloz",
    "sg:classifiers":[
        {
            "category":"Health Services",
            "subcategory":"Health Practitioner",
            "type":"Services"
        }
    ],
    "sg:phone":"+32 477 27 89 94",
    "sg:postcode":"4257",
    "sg:province":"Li\u00e8ge",
    "sg:tags":[
        "physiotherapist"
    ],
    "wof:name":"Depas C\u00e9cile",
    "wof:placetype":"venue"
},
  "geometry": {"coordinates":[5.2288541794,50.6964263916],"type":"Point"}
}