{
  "type": "Feature",
  "properties": {
    "addr:full":"Chauss\u00c9e De Charleroi 5 Charleroi Hainaut 6060",
    "addr:housenumber":"5",
    "addr:postcode":"6060",
    "addr:street":"Chausse\u0301E De Charleroi;Hainaut",
    "iso:country":"BE",
    "sg:address":"Chauss\u00c9e De Charleroi 5",
    "sg:city":"Charleroi",
    "sg:orig_category":"Cr\u00e9dits divers",
    "sg:postcode":"6060",
    "sg:province":"Hainaut",
    "wof:name":"Bancontact-mister Cash",
    "wof:placetype":"venue"
},
  "geometry": {"coordinates":[4.479060173,50.4008979797],"type":"Point"}
}