{
  "type": "Feature",
  "properties": {
    "addr:full":"Dorp 101 Berlare Oost-Vlaanderen 9290",
    "addr:housenumber":"101",
    "addr:postcode":"9290",
    "addr:street":"Dorp",
    "iso:country":"BE",
    "sg:address":"Dorp 101",
    "sg:city":"Berlare",
    "sg:classifiers":[
        {
            "category":"Education",
            "subcategory":"Library",
            "type":"Public Place"
        }
    ],
    "sg:phone":"+32 52 42 61 88",
    "sg:postcode":"9290",
    "sg:province":"Oost-Vlaanderen",
    "wof:name":"Gemeentelijke P.o.b.",
    "wof:placetype":"venue"
},
  "geometry": {"coordinates":[4.0068349838,51.0252075195],"type":"Point"}
}