{
  "type": "Feature",
  "properties": {
    "addr:full":"Sint-rochusstraat 20 Mouscron (herseaux) Hainaut 7712",
    "addr:housenumber":"20",
    "addr:postcode":"7712",
    "addr:street":"Sint-Rochusstraat",
    "iso:country":"BE",
    "sg:address":"Sint-rochusstraat 20",
    "sg:city":"Mouscron (herseaux)",
    "sg:classifiers":[
        {
            "category":"Professional",
            "subcategory":"Printing & Photocopies",
            "type":"Services"
        }
    ],
    "sg:phone":"+32 56 84 11 81",
    "sg:postcode":"7712",
    "sg:province":"Hainaut",
    "sg:tags":[
        "silkscreen",
        "-"
    ],
    "wof:name":"Six-blieck Bvba",
    "wof:placetype":"venue"
},
  "geometry": {"coordinates":[3.24187994,50.7188491821],"type":"Point"}
}