{
  "type": "Feature",
  "properties": {
    "iso:country":"BE",
    "sg:address":"Saint-antoine 72",
    "sg:city":"Chimay",
    "sg:orig_category":"Eleveurs de bovins",
    "sg:phone":"+32 60 21 23 09",
    "sg:postcode":"6460",
    "sg:province":"Hainaut",
    "wof:name":"Jose Fagnart",
    "wof:placetype":"venue"
},
  "geometry": {"coordinates":[4.2489829063,50.0583457947],"type":"Point"}
}