{
  "type": "Feature",
  "properties": {
    "addr:full":"Avenue De La Lib\u00e9ration 82 Leuze-en-hainaut Hainaut 7900",
    "addr:housenumber":"82",
    "addr:postcode":"7900",
    "addr:street":"Avenue De La Libe\u0301Ration",
    "iso:country":"BE",
    "sg:address":"Avenue De La Lib\u00e9ration 82",
    "sg:city":"Leuze-en-hainaut",
    "sg:classifiers":[
        {
            "category":"Health Services",
            "subcategory":"Nursing And Care Facility",
            "type":"Services"
        }
    ],
    "sg:phone":"+32 69 66 21 49",
    "sg:postcode":"7900",
    "sg:province":"Hainaut",
    "sg:tags":[
        "home"
    ],
    "wof:name":"Pollet B",
    "wof:placetype":"venue"
},
  "geometry": {"coordinates":[3.6028521061,50.5961380005],"type":"Point"}
}