{
  "type": "Feature",
  "properties": {
    "addr:full":"Rue Des Hayettes 3 Mettet Namur 5640",
    "addr:housenumber":"3",
    "addr:postcode":"5640",
    "addr:street":"Rue Des Hayettes",
    "iso:country":"BE",
    "sg:address":"Rue Des Hayettes 3",
    "sg:city":"Mettet",
    "sg:classifiers":[
        {
            "category":"Personal",
            "subcategory":"Beauty Salon",
            "type":"Services"
        }
    ],
    "sg:phone":"+32 71 72 71 23",
    "sg:postcode":"5640",
    "sg:province":"Namur",
    "sg:tags":[
        "de",
        "coiffure"
    ],
    "wof:name":"Maryse",
    "wof:placetype":"venue"
},
  "geometry": {"coordinates":[4.6165089607,50.3426437378],"type":"Point"}
}