{
  "type": "Feature",
  "properties": {
    "addr:full":"Beverestraat 50 Oudenaarde Oost-Vlaanderen 9700",
    "addr:housenumber":"50",
    "addr:postcode":"9700",
    "addr:street":"Beverestraat",
    "iso:country":"BE",
    "sg:address":"Beverestraat 50",
    "sg:city":"Oudenaarde",
    "sg:orig_category":"Apotheken",
    "sg:phone":"+32 55 31 21 58",
    "sg:postcode":"9700",
    "sg:province":"Oost-Vlaanderen",
    "wof:name":"Sybephar",
    "wof:placetype":"venue"
},
  "geometry": {"coordinates":[3.5990030766,50.8489875793],"type":"Point"}
}