{
  "type": "Feature",
  "properties": {
    "iso:country":"BE",
    "sg:address":"Rue Du Pourcelet 4",
    "sg:city":"Mons",
    "sg:classifiers":[
        {
            "category":"Professional",
            "subcategory":"Secretarial Services",
            "type":"Services"
        }
    ],
    "sg:phone":"+32 65 84 18 77",
    "sg:postcode":"7000",
    "sg:province":"Hainaut",
    "sg:tags":[
        "-",
        "wordprocessing"
    ],
    "wof:name":"Bougard M",
    "wof:placetype":"venue"
},
  "geometry": {"coordinates":[3.9593191147,50.4657897949],"type":"Point"}
}