{
  "type": "Feature",
  "properties": {
    "iso:country":"BE",
    "sg:address":"D\u00b4arconatistraat 80",
    "sg:city":"Dilbeek",
    "sg:orig_category":"Rev\u00eatements pour sols and murs. Peinture",
    "sg:phone":"+32 2 567 02 97",
    "sg:postcode":"1700",
    "sg:province":"Vlaams-Brabant",
    "wof:name":"Patrick De Raedemaeker",
    "wof:placetype":"venue"
},
  "geometry": {"coordinates":[4.2528247833,50.8459434509],"type":"Point"}
}