{
  "type": "Feature",
  "properties": {
    "iso:country":"BE",
    "sg:address":"Oude Tieltstraat 59",
    "sg:city":"Ruiselede",
    "sg:orig_category":"Installation de menuiserie en bois and plastique",
    "sg:phone":"+32 51 68 94 11",
    "sg:postcode":"8755",
    "sg:province":"West-Vlaanderen",
    "wof:name":"Marc Persyn",
    "wof:placetype":"venue"
},
  "geometry": {"coordinates":[3.3868620396,51.0409622192],"type":"Point"}
}