{
  "type": "Feature",
  "properties": {
    "iso:country":"BE",
    "sg:address":"Ankerstraat 2",
    "sg:city":"Oostende",
    "sg:orig_category":"Fish, Frozen",
    "sg:phone":"+32 50 54 67 80",
    "sg:postcode":"8400",
    "sg:province":"West-Vlaanderen",
    "wof:name":"Paulus Henri & Zonen Nv",
    "wof:placetype":"venue"
},
  "geometry": {"coordinates":[3.181374073,51.3294219971],"type":"Point"}
}