{
  "type": "Feature",
  "properties": {
    "iso:country":"BE",
    "sg:address":"Heikant 25ba",
    "sg:city":"Sint-amands",
    "sg:orig_category":"Sportclubs",
    "sg:phone":"+32 52 33 33 73",
    "sg:postcode":"2890",
    "sg:province":"Antwerpen",
    "wof:name":"Qui\u00c9vrainbond",
    "wof:placetype":"venue"
},
  "geometry": {"coordinates":[4.2066469193,51.0585975647],"type":"Point"}
}