{
  "type": "Feature",
  "properties": {
    "addr:full":"Domis De Semerpontlaan 35 Bonheiden Antwerpen 2820",
    "addr:housenumber":"35",
    "addr:postcode":"2820",
    "addr:street":"Domis De Semerpontlaan",
    "iso:country":"BE",
    "sg:address":"Domis De Semerpontlaan 35",
    "sg:city":"Bonheiden",
    "sg:classifiers":[
        {
            "category":"Professional",
            "subcategory":"Management & Consulting",
            "type":"Services"
        }
    ],
    "sg:phone":"+32 15 33 62 65",
    "sg:postcode":"2820",
    "sg:province":"Antwerpen",
    "sg:tags":[
        "-",
        "processing",
        "data",
        "consultant"
    ],
    "wof:name":"Proteus Consult",
    "wof:placetype":"venue"
},
  "geometry": {"coordinates":[4.5561199188,51.0194854736],"type":"Point"}
}