{
  "type": "Feature",
  "properties": {
    "addr:full":"Leon Delacroixstraat 20 Anderlecht Bruxelles-Capitale 1070",
    "addr:housenumber":"20",
    "addr:postcode":"1070",
    "addr:street":"Delacroixstraat",
    "iso:country":"BE",
    "sg:address":"Leon Delacroixstraat 20",
    "sg:city":"Anderlecht",
    "sg:classifiers":[
        {
            "category":"Cafe",
            "type":"Food & Drink"
        }
    ],
    "sg:phone":"+32 2 410 69 98",
    "sg:postcode":"1070",
    "sg:province":"Bruxelles-Capitale",
    "sg:tags":[
        "caf\u00e9s"
    ],
    "wof:name":"Hamit Bulut",
    "wof:placetype":"venue"
},
  "geometry": {"coordinates":[4.3286800385,50.8432121277],"type":"Point"}
}