{
  "type": "Feature",
  "properties": {
    "addr:full":"Lodreef 36 Leuven Vlaams-Brabant 3010",
    "addr:housenumber":"36",
    "addr:postcode":"3010",
    "addr:street":"Lodreef",
    "iso:country":"BE",
    "sg:address":"Lodreef 36",
    "sg:city":"Leuven",
    "sg:orig_category":"Transports routiers de marchandises",
    "sg:phone":"+32 16 25 11 46",
    "sg:postcode":"3010",
    "sg:province":"Vlaams-Brabant",
    "wof:name":"Guillaume Trans",
    "wof:placetype":"venue"
},
  "geometry": {"coordinates":[4.7410478592,50.8787002563],"type":"Point"}
}