{
  "type": "Feature",
  "properties": {
    "addr:full":"Sint-jansbergsteenweg 77a Huldenberg (loonbeek) Vlaams-Brabant 3040",
    "addr:housenumber":"77a",
    "addr:postcode":"3040",
    "addr:street":"Sint-Jansbergsteenweg",
    "iso:country":"BE",
    "sg:address":"Sint-jansbergsteenweg 77a",
    "sg:city":"Huldenberg (loonbeek)",
    "sg:classifiers":[
        {
            "category":"Building & Trades",
            "subcategory":"Electrical",
            "type":"Services"
        }
    ],
    "sg:phone":"+32 16 47 14 40",
    "sg:postcode":"3040",
    "sg:province":"Vlaams-Brabant",
    "sg:tags":[
        "electric",
        "-",
        "housewiring",
        "contractor"
    ],
    "wof:name":"Goossens P",
    "wof:placetype":"venue"
},
  "geometry": {"coordinates":[4.6121120453,50.8112716675],"type":"Point"}
}