{
  "type": "Feature",
  "properties": {
    "addr:full":"Rue Du Palais 66 Verviers Li\u00e8ge 4800",
    "addr:housenumber":"66",
    "addr:postcode":"4800",
    "addr:street":"Rue Du Palais",
    "iso:country":"BE",
    "sg:address":"Rue Du Palais 66",
    "sg:city":"Verviers",
    "sg:classifiers":[
        {
            "category":"Health Services",
            "subcategory":"Doctor",
            "type":"Services"
        }
    ],
    "sg:phone":"+32 87 22 30 76",
    "sg:postcode":"4800",
    "sg:province":"Li\u00e8ge",
    "sg:tags":[
        "medicinephysicians",
        "surgeon"
    ],
    "wof:name":"Gilson Marcel",
    "wof:placetype":"venue"
},
  "geometry": {"coordinates":[5.860886097,50.5900382996],"type":"Point"}
}