{
  "type": "Feature",
  "properties": {
    "iso:country":"BE",
    "sg:address":"Schaarbeeklei 189",
    "sg:city":"Vilvoorde",
    "sg:classifiers":[
        {
            "category":"Sports & Exercise",
            "subcategory":"Ski Resort",
            "type":"Entertainment"
        }
    ],
    "sg:phone":"+32 2 255 40 00",
    "sg:postcode":"1800",
    "sg:province":"Vlaams-Brabant",
    "sg:tags":[
        "pipe",
        "fitting"
    ],
    "wof:name":"Van Leeuwen Buizen Belgie Nv",
    "wof:placetype":"venue"
},
  "geometry": {"coordinates":[4.4270048141,50.920463562],"type":"Point"}
}