{
  "type": "Feature",
  "properties": {
    "addr:full":"Chauss\u00e9e De Waterloo 32 Bruxelles (saint-gilles) Bruxelles-Capitale 1060",
    "addr:housenumber":"32",
    "addr:postcode":"1060",
    "addr:street":"Chausse\u0301E De Waterloo",
    "iso:country":"BE",
    "sg:address":"Chauss\u00e9e De Waterloo 32",
    "sg:city":"Bruxelles (saint-gilles)",
    "sg:orig_category":"Non-Classified Establishments",
    "sg:phone":"+32 2 538 09 76",
    "sg:postcode":"1060",
    "sg:province":"Bruxelles-Capitale",
    "wof:name":"Antoine",
    "wof:placetype":"venue"
},
  "geometry": {"coordinates":[4.3449549675,50.8315925598],"type":"Point"}
}