{
  "type": "Feature",
  "properties": {
    "addr:full":"Bosstraat 64 Zele Oost-Vlaanderen 9240",
    "addr:housenumber":"64",
    "addr:postcode":"9240",
    "addr:street":"Bosstraat",
    "iso:country":"BE",
    "sg:address":"Bosstraat 64",
    "sg:city":"Zele",
    "sg:orig_category":"Scenery Stage-, film-, and television",
    "sg:phone":"+32 52 45 08 67",
    "sg:postcode":"9240",
    "sg:province":"Oost-Vlaanderen",
    "wof:name":"G-deco",
    "wof:placetype":"venue"
},
  "geometry": {"coordinates":[4.0064110756,51.0686035156],"type":"Point"}
}