{
  "type": "Feature",
  "properties": {
    "addr:full":"Schaliehoevestraat 88 Heist-op-den-berg Antwerpen 2220",
    "addr:housenumber":"88",
    "addr:postcode":"2220",
    "addr:street":"Schaliehoevestraat",
    "iso:country":"BE",
    "sg:address":"Schaliehoevestraat 88",
    "sg:city":"Heist-op-den-berg",
    "sg:classifiers":[
        {
            "category":"Building & Trades",
            "subcategory":"Landscaping Services",
            "type":"Services"
        }
    ],
    "sg:phone":"+32 495 17 14 37",
    "sg:postcode":"2220",
    "sg:province":"Antwerpen",
    "sg:tags":[
        "gardening",
        "garden",
        "maintenance"
    ],
    "wof:name":"Tuindesign Van De Putte S",
    "wof:placetype":"venue"
},
  "geometry": {"coordinates":[4.7057900429,51.0543708801],"type":"Point"}
}