{
  "type": "Feature",
  "properties": {
    "iso:country":"BE",
    "sg:address":"Drogebroodstraat 10",
    "sg:city":"Olen",
    "sg:orig_category":"Entretien and r\u00e9parations de voitures",
    "sg:phone":"+32 14 26 65 46",
    "sg:postcode":"2250",
    "sg:province":"Antwerpen",
    "wof:name":"Carrosserie Ennekens",
    "wof:placetype":"venue"
},
  "geometry": {"coordinates":[4.8608307838,51.1432800293],"type":"Point"}
}