{
  "type": "Feature",
  "properties": {
    "addr:full":"Rue Achille Motte 9 Orp-jauche (orp-le-grand) Brabant Wallon 1350",
    "addr:housenumber":"9",
    "addr:postcode":"1350",
    "addr:street":"Rue Achille Motte",
    "iso:country":"BE",
    "sg:address":"Rue Achille Motte 9",
    "sg:city":"Orp-jauche (orp-le-grand)",
    "sg:classifiers":[
        {
            "category":"Real Estate",
            "subcategory":"Surveying",
            "type":"Services"
        }
    ],
    "sg:phone":"+32 19 63 50 13",
    "sg:postcode":"1350",
    "sg:province":"Brabant Wallon",
    "sg:tags":[
        "surveyor",
        "land"
    ],
    "wof:name":"Jacqmotte J-m",
    "wof:placetype":"venue"
},
  "geometry": {"coordinates":[4.97920084,50.6738891602],"type":"Point"}
}