{
  "type": "Feature",
  "properties": {
    "addr:full":"Henri Horriestraat 17 Roeselare West-Vlaanderen 8800",
    "addr:housenumber":"17",
    "addr:postcode":"8800",
    "addr:street":"Henri Horriestraat",
    "iso:country":"BE",
    "sg:address":"Henri Horriestraat 17",
    "sg:city":"Roeselare",
    "sg:classifiers":[
        {
            "category":"Shopping",
            "subcategory":"Clothing, Apparel, & Fashions",
            "type":"Retail Goods"
        }
    ],
    "sg:phone":"+32 51 26 04 44",
    "sg:postcode":"8800",
    "sg:province":"West-Vlaanderen",
    "sg:tags":[
        "v\u00eatements",
        "pour",
        "dame"
    ],
    "wof:name":"Labora",
    "wof:placetype":"venue"
},
  "geometry": {"coordinates":[3.1249139309,50.9468803406],"type":"Point"}
}