{
  "type": "Feature",
  "properties": {
    "addr:full":"Valkstraat 5 Staden (oostnieuwkerke) West-Vlaanderen 8840",
    "addr:housenumber":"5",
    "addr:postcode":"8840",
    "addr:street":"Valkstraat",
    "iso:country":"BE",
    "sg:address":"Valkstraat 5",
    "sg:city":"Staden (oostnieuwkerke)",
    "sg:classifiers":[
        {
            "category":"Health Services",
            "subcategory":"Health Practitioner",
            "type":"Services"
        }
    ],
    "sg:phone":"+32 51 20 01 64",
    "sg:postcode":"8840",
    "sg:province":"West-Vlaanderen",
    "sg:tags":[
        "physiotherapist"
    ],
    "wof:name":"Deprez Karin",
    "wof:placetype":"venue"
},
  "geometry": {"coordinates":[3.0603349209,50.9376373291],"type":"Point"}
}