{
  "type": "Feature",
  "properties": {
    "addr:full":"Tervuursesteenweg 286 Mechelen Antwerpen 2800",
    "addr:housenumber":"286",
    "addr:postcode":"2800",
    "addr:street":"Tervuursesteenweg",
    "iso:country":"BE",
    "sg:address":"Tervuursesteenweg 286",
    "sg:city":"Mechelen",
    "sg:orig_category":"Koekjes, gebak and taart Fab",
    "sg:phone":"+32 15 41 56 39",
    "sg:postcode":"2800",
    "sg:province":"Antwerpen",
    "wof:name":"Van Der Goten",
    "wof:placetype":"venue"
},
  "geometry": {"coordinates":[4.4858379364,51.0062141418],"type":"Point"}
}