{
  "type": "Feature",
  "properties": {
    "iso:country":"BE",
    "sg:address":"Guffenslaan 20",
    "sg:city":"Hasselt",
    "sg:classifiers":[
        {
            "category":"Personal",
            "subcategory":"Beauty Salon",
            "type":"Services"
        }
    ],
    "sg:phone":"+32 11 22 20 94",
    "sg:postcode":"3500",
    "sg:province":"Limburg",
    "sg:tags":[
        "lady",
        "-",
        "hairdressing"
    ],
    "wof:name":"Equipe Coiffure",
    "wof:placetype":"venue"
},
  "geometry": {"coordinates":[5.3381581306,50.9270172119],"type":"Point"}
}