{
  "type": "Feature",
  "properties": {
    "addr:full":"Tillo 76 Jalhay (sart) Li\u00e8ge 4845",
    "addr:housenumber":"76",
    "addr:postcode":"4845",
    "addr:street":"Tillo;Sart Lie\u0300Ge",
    "iso:country":"BE",
    "sg:address":"Tillo 76",
    "sg:city":"Jalhay (sart)",
    "sg:classifiers":[
        {
            "category":"Building & Trades",
            "subcategory":"Landscaping Services",
            "type":"Services"
        }
    ],
    "sg:phone":"+32 87 47 42 38",
    "sg:postcode":"4845",
    "sg:province":"Li\u00e8ge",
    "sg:tags":[
        "-",
        "lopping",
        "work",
        "tree",
        "felling"
    ],
    "wof:name":"Boniver D",
    "wof:placetype":"venue"
},
  "geometry": {"coordinates":[5.9721851349,50.5571899414],"type":"Point"}
}