{
  "type": "Feature",
  "properties": {
    "addr:full":"Hannekestraat 13 Dessel Antwerpen 2480",
    "addr:housenumber":"13",
    "addr:postcode":"2480",
    "addr:street":"Hannekestraat",
    "iso:country":"BE",
    "sg:address":"Hannekestraat 13",
    "sg:city":"Dessel",
    "sg:orig_category":"Boekhouders",
    "sg:postcode":"2480",
    "sg:province":"Antwerpen",
    "wof:name":"Heidi Greif",
    "wof:placetype":"venue"
},
  "geometry": {"coordinates":[5.1103930473,51.2390785217],"type":"Point"}
}