{
  "type": "Feature",
  "properties": {
    "addr:full":"Strijbroeklei 3 Sint-katelijne-waver Antwerpen 2860",
    "addr:housenumber":"3",
    "addr:postcode":"2860",
    "addr:street":"Strijbroeklei",
    "iso:country":"BE",
    "sg:address":"Strijbroeklei 3",
    "sg:city":"Sint-katelijne-waver",
    "sg:classifiers":[
        {
            "category":"Food & Beverages",
            "subcategory":"Fruits & Vegetables",
            "type":"Retail Goods"
        }
    ],
    "sg:phone":"+32 15 31 71 61",
    "sg:postcode":"2860",
    "sg:province":"Antwerpen",
    "sg:tags":[
        "l\u00e9gumes",
        "gr"
    ],
    "wof:name":"De Swert",
    "wof:placetype":"venue"
},
  "geometry": {"coordinates":[4.5131659508,51.0611305237],"type":"Point"}
}