{
  "type": "Feature",
  "properties": {
    "iso:country":"BE",
    "sg:address":"Rue Des Rossignols 33",
    "sg:city":"Montigny-le-tilleul",
    "sg:classifiers":[
        {
            "category":"Health Services",
            "subcategory":"Doctor",
            "type":"Services"
        }
    ],
    "sg:phone":"+32 71 56 01 62",
    "sg:postcode":"6110",
    "sg:province":"Hainaut",
    "sg:tags":[
        "medicinephysicians",
        "surgeon"
    ],
    "wof:name":"Cherkaoui Soumaya",
    "wof:placetype":"venue"
},
  "geometry": {"coordinates":[4.3724532127,50.3623695374],"type":"Point"}
}