{
  "type": "Feature",
  "properties": {
    "addr:full":"Bosterestraat 11 Diest (webbekom) Vlaams-Brabant 3290",
    "addr:housenumber":"11",
    "addr:postcode":"3290",
    "addr:street":"Bosterestraat",
    "iso:country":"BE",
    "sg:address":"Bosterestraat 11",
    "sg:city":"Diest (webbekom)",
    "sg:classifiers":[
        {
            "category":"Government",
            "subcategory":"Post Office",
            "type":"Public Place"
        }
    ],
    "sg:phone":"+32 13 33 35 58",
    "sg:postcode":"3290",
    "sg:province":"Vlaams-Brabant",
    "sg:tags":[
        "yoga"
    ],
    "wof:name":"Anahata Yogacentrum",
    "wof:placetype":"venue"
},
  "geometry": {"coordinates":[5.037612915,50.9702339172],"type":"Point"}
}