{
  "type": "Feature",
  "properties": {
    "addr:full":"Henri Horriestraat 14 Roeselare West-Vlaanderen 8800",
    "addr:housenumber":"14",
    "addr:postcode":"8800",
    "addr:street":"Henri Horriestraat",
    "iso:country":"BE",
    "sg:address":"Henri Horriestraat 14",
    "sg:city":"Roeselare",
    "sg:classifiers":[
        {
            "category":"Personal",
            "subcategory":"Beauty Salon",
            "type":"Services"
        }
    ],
    "sg:phone":"+32 51 20 46 43",
    "sg:postcode":"8800",
    "sg:province":"West-Vlaanderen",
    "sg:tags":[
        "lady",
        "-",
        "hairdressing"
    ],
    "wof:name":"Elys\u00e9e",
    "wof:placetype":"venue"
},
  "geometry": {"coordinates":[3.1254959106,50.9468193054],"type":"Point"}
}