{
  "type": "Feature",
  "properties": {
    "addr:full":"Rue De Malvoisin 31 Gedinne Namur 5575",
    "addr:housenumber":"31",
    "addr:postcode":"5575",
    "addr:street":"Rue De Malvoisin",
    "iso:country":"BE",
    "sg:address":"Rue De Malvoisin 31",
    "sg:city":"Gedinne",
    "sg:classifiers":[
        {
            "category":"Wholesale",
            "subcategory":"Farm Supplies",
            "type":"Manufacturing & Wholesale Goods"
        }
    ],
    "sg:phone":"+32 61 58 88 69",
    "sg:postcode":"5575",
    "sg:province":"Namur",
    "sg:tags":[
        "machine",
        "agricoles",
        "mat\u00e9riel",
        "gr"
    ],
    "wof:name":"Marceau Chauvier",
    "wof:placetype":"venue"
},
  "geometry": {"coordinates":[4.9501070976,49.9992980957],"type":"Point"}
}