{
  "type": "Feature",
  "properties": {
    "addr:full":"Voskapelstraat 26 Zaventem Vlaams-Brabant 1933",
    "addr:housenumber":"26",
    "addr:postcode":"1933",
    "addr:street":"Voskapelstraat",
    "iso:country":"BE",
    "sg:address":"Voskapelstraat 26",
    "sg:city":"Zaventem",
    "sg:classifiers":[
        {
            "category":"Insurance",
            "subcategory":"Insurance Agent",
            "type":"Services"
        }
    ],
    "sg:phone":"+32 2 731 32 86",
    "sg:postcode":"1933",
    "sg:province":"Vlaams-Brabant",
    "sg:tags":[
        "verzekeringsmakelaars",
        "expert"
    ],
    "wof:name":"L. De Pauw",
    "wof:placetype":"venue"
},
  "geometry": {"coordinates":[4.5174598694,50.8665161133],"type":"Point"}
}