{
  "type": "Feature",
  "properties": {
    "iso:country":"BE",
    "sg:address":"24e Liniestraat 4",
    "sg:city":"Houthulst",
    "sg:orig_category":"S\u00e9curit\u00e9 sociale",
    "sg:phone":"+32 51 70 07 66",
    "sg:postcode":"8650",
    "sg:province":"West-Vlaanderen",
    "wof:name":"Christelijke Mutualiteit",
    "wof:placetype":"venue"
},
  "geometry": {"coordinates":[2.9534950256,50.9839553833],"type":"Point"}
}