{
  "type": "Feature",
  "properties": {
    "addr:full":"Hertstraat 98 Denderleeuw Oost-Vlaanderen 9473",
    "addr:housenumber":"98",
    "addr:postcode":"9473",
    "addr:street":"Hertstraat",
    "iso:country":"BE",
    "sg:address":"Hertstraat 98",
    "sg:city":"Denderleeuw",
    "sg:classifiers":[
        {
            "category":"Organizations",
            "subcategory":"Community Association",
            "type":"Services"
        }
    ],
    "sg:phone":"+32 53 66 99 97",
    "sg:postcode":"9473",
    "sg:province":"Oost-Vlaanderen",
    "sg:tags":[
        "organisation"
    ],
    "wof:name":"Jeugdhuis Pingie",
    "wof:placetype":"venue"
},
  "geometry": {"coordinates":[4.0527071953,50.9047012329],"type":"Point"}
}