{
  "type": "Feature",
  "properties": {
    "iso:country":"BE",
    "sg:address":"Place Jean Ransy 11",
    "sg:city":"Courcelles",
    "sg:classifiers":[
        {
            "category":"Personal",
            "subcategory":"Barber",
            "type":"Services"
        }
    ],
    "sg:phone":"+32 71 46 02 14",
    "sg:postcode":"6180",
    "sg:province":"Hainaut",
    "sg:tags":[
        "gentleman",
        "salon",
        "-",
        "hairdressing"
    ],
    "wof:name":"Micha\u00ebl Coiffure",
    "wof:placetype":"venue"
},
  "geometry": {"coordinates":[4.3752479553,50.4561538696],"type":"Point"}
}