{
  "type": "Feature",
  "properties": {
    "addr:full":"Rue Gouttier 19 Waterloo Brabant Wallon 1410",
    "addr:housenumber":"19",
    "addr:postcode":"1410",
    "addr:street":"Rue Gouttier",
    "iso:country":"BE",
    "sg:address":"Rue Gouttier 19",
    "sg:city":"Waterloo",
    "sg:orig_category":"Artsen and specialisten",
    "sg:phone":"+32 2 354 88 08",
    "sg:postcode":"1410",
    "sg:province":"Brabant Wallon",
    "wof:name":"Jos\u00c9e Coppens",
    "wof:placetype":"venue"
},
  "geometry": {"coordinates":[4.3810601234,50.7129516602],"type":"Point"}
}