{
  "type": "Feature",
  "properties": {
    "addr:full":"Kijkuitstraat 10 Wevelgem West-Vlaanderen 8560",
    "addr:housenumber":"10",
    "addr:postcode":"8560",
    "addr:street":"Kijkuitstraat",
    "iso:country":"BE",
    "sg:address":"Kijkuitstraat 10",
    "sg:city":"Wevelgem",
    "sg:classifiers":[
        {
            "category":"Travel",
            "subcategory":"Travel Agent",
            "type":"Entertainment"
        }
    ],
    "sg:phone":"+32 56 41 11 11",
    "sg:postcode":"8560",
    "sg:province":"West-Vlaanderen",
    "sg:tags":[
        "agency"
    ],
    "wof:name":"Herman & Vandamme Reizen",
    "wof:placetype":"venue"
},
  "geometry": {"coordinates":[3.1710150242,50.8108291626],"type":"Point"}
}