{
  "type": "Feature",
  "properties": {
    "iso:country":"BE",
    "sg:address":"Priestersstraat 2",
    "sg:city":"Ronse/renaix",
    "sg:classifiers":[
        {
            "category":"Communications",
            "subcategory":"Film & Video Production",
            "type":"Services"
        }
    ],
    "sg:phone":"+32 55 21 37 76",
    "sg:postcode":"9600",
    "sg:province":"Oost-Vlaanderen",
    "sg:tags":[
        "platen",
        "cassette",
        "cd's"
    ],
    "wof:name":"Huis Malrait",
    "wof:placetype":"venue"
},
  "geometry": {"coordinates":[3.6019089222,50.7484130859],"type":"Point"}
}