{
  "type": "Feature",
  "properties": {
    "addr:full":"Evergemsesteenweg 31 Gent (wondelgem) Oost-Vlaanderen 9032",
    "addr:housenumber":"31",
    "addr:postcode":"9032",
    "addr:street":"Evergemsesteenweg",
    "iso:country":"BE",
    "sg:address":"Evergemsesteenweg 31",
    "sg:city":"Gent (wondelgem)",
    "sg:classifiers":[
        {
            "category":"Professional",
            "subcategory":"Engineering",
            "type":"Services"
        }
    ],
    "sg:phone":"+32 9 253 90 03",
    "sg:postcode":"9032",
    "sg:province":"Oost-Vlaanderen",
    "sg:tags":[
        "-"
    ],
    "wof:name":"Dg & P Studiebureau",
    "wof:placetype":"venue"
},
  "geometry": {"coordinates":[3.7162549496,51.0900535583],"type":"Point"}
}