{
  "type": "Feature",
  "properties": {
    "iso:country":"BE",
    "sg:address":"Chemin Sauterre 6",
    "sg:city":"Soignies",
    "sg:classifiers":[
        {
            "category":"Health Services",
            "subcategory":"Health Practitioner",
            "type":"Services"
        }
    ],
    "sg:phone":"+32 67 33 39 42",
    "sg:postcode":"7060",
    "sg:province":"Hainaut",
    "sg:tags":[
        "psychologist"
    ],
    "wof:name":"Kuneben",
    "wof:placetype":"venue"
},
  "geometry": {"coordinates":[4.0454568863,50.5526733398],"type":"Point"}
}