{
  "type": "Feature",
  "properties": {
    "iso:country":"BE",
    "sg:address":"Geelsebaan 54",
    "sg:city":"Kasterlee",
    "sg:classifiers":[
        {
            "category":"Personal",
            "subcategory":"Beauty Salon",
            "type":"Services"
        }
    ],
    "sg:phone":"+32 14 85 37 45",
    "sg:postcode":"2460",
    "sg:province":"Antwerpen",
    "sg:tags":[
        "de",
        "coiffure"
    ],
    "wof:name":"Courage",
    "wof:placetype":"venue"
},
  "geometry": {"coordinates":[4.9693098068,51.2374000549],"type":"Point"}
}