{
  "type": "Feature",
  "properties": {
    "addr:full":"G\u00c9rard Kasiersplein 8b49 Moeskroen/mouscron Hainaut 7700",
    "addr:housenumber":"8b49 moeskroen;mouscron",
    "addr:postcode":"7700",
    "addr:street":"Hainaut",
    "iso:country":"BE",
    "sg:address":"G\u00c9rard Kasiersplein 8b49",
    "sg:city":"Moeskroen/mouscron",
    "sg:orig_category":"Elektrische installaties voor woningen",
    "sg:phone":"+32 56 34 84 92",
    "sg:postcode":"7700",
    "sg:province":"Hainaut",
    "wof:name":"J. Rogge/jean-pierre Rogge",
    "wof:placetype":"venue"
},
  "geometry": {"coordinates":[3.2323200703,50.7400932312],"type":"Point"}
}