{
  "type": "Feature",
  "properties": {
    "iso:country":"BE",
    "sg:address":"Rue Du Moulin 2",
    "sg:city":"Pecq",
    "sg:orig_category":"V\u00e9t\u00e9rinaires",
    "sg:phone":"+32 69 55 75 76",
    "sg:postcode":"7743",
    "sg:province":"Hainaut",
    "wof:name":"Olivier Boonaert",
    "wof:placetype":"venue"
},
  "geometry": {"coordinates":[3.3616280556,50.6536598206],"type":"Point"}
}