{
  "type": "Feature",
  "properties": {
    "iso:country":"BE",
    "sg:address":"Astridlaan 180",
    "sg:city":"Brugge",
    "sg:orig_category":"Produits chimiques Gr",
    "sg:phone":"+32 50 35 05 60",
    "sg:postcode":"8310",
    "sg:province":"West-Vlaanderen",
    "wof:name":"Verhoest",
    "wof:placetype":"venue"
},
  "geometry": {"coordinates":[3.2554330826,51.1954269409],"type":"Point"}
}