{
  "type": "Feature",
  "properties": {
    "addr:full":"Quartier Joseph Gailly 62a Charleroi Hainaut 6060",
    "addr:housenumber":"62a",
    "addr:postcode":"6060",
    "addr:street":"Quartier Joseph Gailly;Hainaut",
    "iso:country":"BE",
    "sg:address":"Quartier Joseph Gailly 62a",
    "sg:city":"Charleroi",
    "sg:orig_category":"Mat\u00e9riel de T\u00e9l\u00e9communication. Installation \u00e9lectrique industrielle",
    "sg:phone":"+32 71 24 30 30",
    "sg:postcode":"6060",
    "sg:province":"Hainaut",
    "wof:name":"Mellec",
    "wof:placetype":"venue"
},
  "geometry": {"coordinates":[4.4880981445,50.4251937866],"type":"Point"}
}