{
  "type": "Feature",
  "properties": {
    "addr:full":"Rue De La R\u00e9gence 5 Binche Hainaut 7130",
    "addr:housenumber":"5",
    "addr:postcode":"7130",
    "addr:street":"Rue De La Re\u0301Gence",
    "iso:country":"BE",
    "sg:address":"Rue De La R\u00e9gence 5",
    "sg:city":"Binche",
    "sg:classifiers":[
        {
            "category":"Building & Trades",
            "subcategory":"Electrical",
            "type":"Services"
        }
    ],
    "sg:phone":"+32 64 36 92 39",
    "sg:postcode":"7130",
    "sg:province":"Hainaut",
    "sg:tags":[
        "electric",
        "-",
        "housewiring",
        "contractor"
    ],
    "wof:name":"Arnone C",
    "wof:placetype":"venue"
},
  "geometry": {"coordinates":[4.1649470329,50.413356781],"type":"Point"}
}