{
  "type": "Feature",
  "properties": {
    "addr:full":"Nederkouter 2 Gent Oost-Vlaanderen 9000",
    "addr:housenumber":"2",
    "addr:postcode":"9000",
    "addr:street":"Nederkouter;Oost-Vlaanderen",
    "iso:country":"BE",
    "sg:address":"Nederkouter 2",
    "sg:city":"Gent",
    "sg:classifiers":[
        {
            "category":"Restaurant",
            "type":"Food & Drink"
        }
    ],
    "sg:phone":"+32 9 269 05 50",
    "sg:postcode":"9000",
    "sg:province":"Oost-Vlaanderen",
    "wof:name":"Polola",
    "wof:placetype":"venue"
},
  "geometry": {"coordinates":[3.7212541103,51.0488052368],"type":"Point"}
}