{
  "type": "Feature",
  "properties": {
    "iso:country":"BE",
    "sg:address":"Sparrenlaan 9",
    "sg:city":"Temse",
    "sg:orig_category":"Sportcentra Sportclubs Sportterreinen and installaties behalve sportcentra",
    "sg:phone":"+32 3 774 41 41",
    "sg:postcode":"9140",
    "sg:province":"Oost-Vlaanderen",
    "wof:name":"Sporthal 't Gelaag",
    "wof:placetype":"venue"
},
  "geometry": {"coordinates":[4.2757649422,51.1260719299],"type":"Point"}
}