{
  "type": "Feature",
  "properties": {
    "addr:full":"Maspelt 16 Burg-reuland/burg-reuland Li\u00e8ge 4791",
    "addr:housenumber":"16",
    "addr:postcode":"4791",
    "addr:street":"Maspelt",
    "iso:country":"BE",
    "sg:address":"Maspelt 16",
    "sg:city":"Burg-reuland/burg-reuland",
    "sg:orig_category":"Rundveehouders",
    "sg:phone":"+32 80 32 93 54",
    "sg:postcode":"4791",
    "sg:province":"Li\u00e8ge",
    "wof:name":"Joseph Herbrand",
    "wof:placetype":"venue"
},
  "geometry": {"coordinates":[6.0771751404,50.2173156738],"type":"Point"}
}