{
  "type": "Feature",
  "properties": {
    "iso:country":"BE",
    "sg:address":"Reibroekstraat 56",
    "sg:city":"Evergem",
    "sg:classifiers":[
        {
            "category":"Wholesale",
            "subcategory":"Plants",
            "type":"Manufacturing & Wholesale Goods"
        }
    ],
    "sg:phone":"+32 9 357 75 02",
    "sg:postcode":"9940",
    "sg:province":"Oost-Vlaanderen",
    "sg:tags":[
        "whol",
        "flower",
        "-",
        "grower"
    ],
    "wof:name":"De Groote A",
    "wof:placetype":"venue"
},
  "geometry": {"coordinates":[3.7055850029,51.1177406311],"type":"Point"}
}