{
  "type": "Feature",
  "properties": {
    "addr:full":"Paapsemlaan 21 Anderlecht/anderlecht Bruxelles-Capitale 1070",
    "addr:housenumber":"21",
    "addr:postcode":"1070",
    "addr:street":"Paapsemlaan",
    "iso:country":"BE",
    "sg:address":"Paapsemlaan 21",
    "sg:city":"Anderlecht/anderlecht",
    "sg:classifiers":[
        {
            "category":"Fast Food",
            "type":"Food & Drink"
        }
    ],
    "sg:phone":"+32 2 344 05 16",
    "sg:postcode":"1070",
    "sg:province":"Bruxelles-Capitale",
    "sg:tags":[
        "meeneem",
        "restaurant"
    ],
    "wof:name":"Quick",
    "wof:placetype":"venue"
},
  "geometry": {"coordinates":[4.3061847687,50.8251686096],"type":"Point"}
}