{
  "type": "Feature",
  "properties": {
    "addr:full":"Rue Antoine Dansaert 74 Bruxelles Bruxelles-Capitale 1000",
    "addr:housenumber":"74",
    "addr:postcode":"1000",
    "addr:street":"Rue Antoine Dansaert",
    "iso:country":"BE",
    "sg:address":"Rue Antoine Dansaert 74",
    "sg:city":"Bruxelles",
    "sg:classifiers":[
        {
            "category":"Shopping",
            "subcategory":"Clothing, Apparel, & Fashions",
            "type":"Retail Goods"
        }
    ],
    "sg:phone":"+32 2 512 03 13",
    "sg:postcode":"1000",
    "sg:province":"Bruxelles-Capitale",
    "sg:tags":[
        "boutique"
    ],
    "wof:name":"Stijl Nv",
    "wof:placetype":"venue"
},
  "geometry": {"coordinates":[4.3457398415,50.8504295349],"type":"Point"}
}