{
  "type": "Feature",
  "properties": {
    "addr:full":"Korte Herentalsestraat 8 Box 4 Antwerpen Antwerpen 2018",
    "addr:housenumber":"8;4",
    "addr:postcode":"2018",
    "addr:street":"Korte Herentalsestraat;Box",
    "iso:country":"BE",
    "sg:address":"Korte Herentalsestraat 8 Box 4",
    "sg:city":"Antwerpen",
    "sg:classifiers":[
        {
            "category":"Communications",
            "type":"Services"
        }
    ],
    "sg:phone":"+32 3 225 19 64",
    "sg:postcode":"2018",
    "sg:province":"Antwerpen",
    "sg:tags":[
        "telecommunication"
    ],
    "wof:name":"European Uniplex Telecom Technologies Nv",
    "wof:placetype":"venue"
},
  "geometry": {"coordinates":[4.4170079231,51.2145462036],"type":"Point"}
}