{
  "type": "Feature",
  "properties": {
    "addr:full":"Leopoldplaats 10 Box 1 Antwerpen Antwerpen 2000",
    "addr:housenumber":"10;1",
    "addr:postcode":"2000",
    "addr:street":"Leopoldplaats;Box",
    "iso:country":"BE",
    "sg:address":"Leopoldplaats 10 Box 1",
    "sg:city":"Antwerpen",
    "sg:classifiers":[
        {
            "category":"Arts & Performance",
            "subcategory":"Theater",
            "type":"Entertainment"
        }
    ],
    "sg:phone":"+32 3 225 17 02",
    "sg:postcode":"2000",
    "sg:province":"Antwerpen",
    "sg:tags":[
        "group",
        "theatre"
    ],
    "wof:name":"Muziektheater Transparant Vzw",
    "wof:placetype":"venue"
},
  "geometry": {"coordinates":[4.4070668221,51.2120933533],"type":"Point"}
}