{
  "type": "Feature",
  "properties": {
    "iso:country":"BE",
    "sg:address":"De Meulenaerstraat 5",
    "sg:city":"Sint-niklaas",
    "sg:classifiers":[
        {
            "category":"Health Services",
            "subcategory":"Doctor",
            "type":"Services"
        }
    ],
    "sg:phone":"+32 3 776 77 87",
    "sg:postcode":"9100",
    "sg:province":"Oost-Vlaanderen",
    "sg:tags":[
        "medicinephysicians",
        "surgeon"
    ],
    "wof:name":"Heyrman D",
    "wof:placetype":"venue"
},
  "geometry": {"coordinates":[4.1642518044,51.1514778137],"type":"Point"}
}