{
  "type": "Feature",
  "properties": {
    "iso:country":"BE",
    "sg:address":"Brugsestw 415",
    "sg:city":"Mariakerke",
    "sg:classifiers":[
        {
            "category":"Banks & Credit Unions",
            "subcategory":"Bank",
            "type":"Services"
        }
    ],
    "sg:phone":"+32 52 26 53 70",
    "sg:postcode":"9910",
    "sg:province":"Oost-Vlaanderen",
    "wof:name":"G\u00e9n\u00e9rale De Banque Sa",
    "wof:placetype":"venue"
},
  "geometry": {"coordinates":[3.4122149944,51.1392288208],"type":"Point"}
}