{
  "type": "Feature",
  "properties": {
    "addr:full":"Pamelstraat 109 Ninove Oost-Vlaanderen 9400",
    "addr:housenumber":"109",
    "addr:postcode":"9400",
    "addr:street":"Pamelstraat",
    "iso:country":"BE",
    "sg:address":"Pamelstraat 109",
    "sg:city":"Ninove",
    "sg:classifiers":[
        {
            "category":"Food & Beverages",
            "subcategory":"Fruits & Vegetables",
            "type":"Retail Goods"
        }
    ],
    "sg:phone":"+32 54 33 62 85",
    "sg:postcode":"9400",
    "sg:province":"Oost-Vlaanderen",
    "sg:tags":[
        "l\u00e9gumes",
        "gr"
    ],
    "wof:name":"Eduard Walravens",
    "wof:placetype":"venue"
},
  "geometry": {"coordinates":[4.0285811424,50.8373146057],"type":"Point"}
}