{
  "type": "Feature",
  "properties": {
    "iso:country":"BE",
    "sg:address":"Gouverneur Verwilghensingel 20",
    "sg:city":"Hasselt",
    "sg:classifiers":[
        {
            "category":"Utilities",
            "subcategory":"Fuel Oil & Lpg",
            "type":"Services"
        }
    ],
    "sg:phone":"+32 11 22 45 49",
    "sg:postcode":"3500",
    "sg:province":"Limburg",
    "sg:tags":[
        "petrol",
        "diesel",
        "pump",
        "-",
        "injection"
    ],
    "wof:name":"Limburgs Revisiebedrijf Bvba",
    "wof:placetype":"venue"
},
  "geometry": {"coordinates":[5.3523330688,50.9384880066],"type":"Point"}
}