{
  "type": "Feature",
  "properties": {
    "addr:full":"Gouverneur Verwilghensingel 75 Hasselt Limburg 3500",
    "addr:housenumber":"75",
    "addr:postcode":"3500",
    "addr:street":"Gouverneur Verwilghensingel",
    "iso:country":"BE",
    "sg:address":"Gouverneur Verwilghensingel 75",
    "sg:city":"Hasselt",
    "sg:orig_category":"Postkantoren Verzekeringsmakelaars and experts",
    "sg:phone":"+32 11 22 68 19",
    "sg:postcode":"3500",
    "sg:province":"Limburg",
    "wof:name":"De Post",
    "wof:placetype":"venue"
},
  "geometry": {"coordinates":[5.3591899872,50.9300460815],"type":"Point"}
}