{
  "type": "Feature",
  "properties": {
    "iso:country":"BE",
    "sg:address":"Chauss\u00e9e De Louvain 105",
    "sg:city":"Namur",
    "sg:classifiers":[
        {
            "category":"Home & Garden",
            "subcategory":"Building Materials",
            "type":"Retail Goods"
        }
    ],
    "sg:phone":"+32 81 23 18 79",
    "sg:postcode":"5000",
    "sg:province":"Namur",
    "sg:tags":[
        "bathroom",
        "installation",
        "accessory"
    ],
    "wof:name":"Dumont F",
    "wof:placetype":"venue"
},
  "geometry": {"coordinates":[4.8681697845,50.4712905884],"type":"Point"}
}