{
  "type": "Feature",
  "properties": {
    "addr:full":"Rue De P\u00e2turages 131 Colfontaine (wasmes) Hainaut 7340",
    "addr:housenumber":"131",
    "addr:postcode":"7340",
    "addr:street":"Rue De Pa\u0302Turages",
    "iso:country":"BE",
    "sg:address":"Rue De P\u00e2turages 131",
    "sg:city":"Colfontaine (wasmes)",
    "sg:classifiers":[
        {
            "category":"Professional",
            "subcategory":"Lawyer & Legal Services",
            "type":"Services"
        }
    ],
    "sg:phone":"+32 65 67 22 17",
    "sg:postcode":"7340",
    "sg:province":"Hainaut",
    "wof:name":"Hardy Thierry",
    "wof:placetype":"venue"
},
  "geometry": {"coordinates":[3.863049984,50.420539856],"type":"Point"}
}