{
  "type": "Feature",
  "properties": {
    "addr:full":"Rue De Bonne Esperance 11 Mettet Namur 5640",
    "addr:housenumber":"11",
    "addr:postcode":"5640",
    "addr:street":"Rue De Bonne Esperance",
    "iso:country":"BE",
    "sg:address":"Rue De Bonne Esperance 11",
    "sg:city":"Mettet",
    "sg:orig_category":"Quincailleries",
    "sg:phone":"+32 71 72 78 14",
    "sg:postcode":"5640",
    "sg:province":"Namur",
    "wof:name":"Dardenne J.-p.",
    "wof:placetype":"venue"
},
  "geometry": {"coordinates":[4.6671490669,50.3220367432],"type":"Point"}
}