{
  "type": "Feature",
  "properties": {
    "iso:country":"BE",
    "sg:address":"Rue Fontaine Des Miracles 1",
    "sg:city":"Perwez",
    "sg:orig_category":"Catering and organisation de f\u00eates",
    "sg:phone":"+32 81 65 71 01",
    "sg:postcode":"1360",
    "sg:province":"Brabant Wallon",
    "wof:name":"Philippe Coenen",
    "wof:placetype":"venue"
},
  "geometry": {"coordinates":[4.7845478058,50.6382102966],"type":"Point"}
}