{
  "type": "Feature",
  "properties": {
    "addr:full":"Rue Des Alli\u00c9s 56 Verviers Li\u00e8ge 4800",
    "addr:housenumber":"56",
    "addr:postcode":"4800",
    "addr:street":"Rue Des Allie\u0301S",
    "iso:country":"BE",
    "sg:address":"Rue Des Alli\u00c9s 56",
    "sg:city":"Verviers",
    "sg:orig_category":"Artsen and specialisten",
    "sg:phone":"+32 87 33 05 43",
    "sg:postcode":"4800",
    "sg:province":"Li\u00e8ge",
    "wof:name":"Maurice Jaspar",
    "wof:placetype":"venue"
},
  "geometry": {"coordinates":[5.8667531013,50.595085144],"type":"Point"}
}