{
  "type": "Feature",
  "properties": {
    "addr:full":"Rue Galliot 15b5 Namur Namur 5000",
    "addr:housenumber":"15b5",
    "addr:postcode":"5000",
    "addr:street":"Rue Galliot",
    "iso:country":"BE",
    "sg:address":"Rue Galliot 15b5",
    "sg:city":"Namur",
    "sg:orig_category":"Advocaten and juridische adviseurs",
    "sg:phone":"+32 81 22 45 74",
    "sg:postcode":"5000",
    "sg:province":"Namur",
    "wof:name":"Michel Derenne",
    "wof:placetype":"venue"
},
  "geometry": {"coordinates":[4.8674259186,50.4683761597],"type":"Point"}
}