{
  "type": "Feature",
  "properties": {
    "iso:country":"BE",
    "sg:address":"Heikant 253",
    "sg:city":"Zele",
    "sg:classifiers":[
        {
            "category":"Bakery",
            "type":"Food & Drink"
        }
    ],
    "sg:phone":"+32 52 44 41 14",
    "sg:postcode":"9240",
    "sg:province":"Oost-Vlaanderen",
    "sg:tags":[
        "confectioner",
        "baker"
    ],
    "wof:name":"D'heer P",
    "wof:placetype":"venue"
},
  "geometry": {"coordinates":[3.9904370308,51.0661811829],"type":"Point"}
}