{
  "type": "Feature",
  "properties": {
    "addr:full":"Steenweg Op Turnhout 25-1 Oud-turnhout Antwerpen 2360",
    "addr:housenumber":"25-1",
    "addr:postcode":"2360",
    "addr:street":"Steenweg Op Turnhout",
    "iso:country":"BE",
    "sg:address":"Steenweg Op Turnhout 25-1",
    "sg:city":"Oud-turnhout",
    "sg:classifiers":[
        {
            "category":"Shopping",
            "subcategory":"Clothing, Apparel, & Fashions",
            "type":"Retail Goods"
        }
    ],
    "sg:phone":"+32 14 55 51 56",
    "sg:postcode":"2360",
    "sg:province":"Antwerpen",
    "sg:tags":[
        "-",
        "clothing",
        "child"
    ],
    "wof:name":"Lene",
    "wof:placetype":"venue"
},
  "geometry": {"coordinates":[4.9788827896,51.3190841675],"type":"Point"}
}