{
  "type": "Feature",
  "properties": {
    "iso:country":"BE",
    "sg:address":"57",
    "sg:city":"Florastraat 9840 De Pinte",
    "sg:classifiers":[
        {
            "category":"Farming",
            "subcategory":"Farm",
            "type":"Manufacturing & Wholesale Goods"
        }
    ],
    "sg:phone":"+32 9 280 23 30",
    "sg:postcode":"57",
    "sg:tags":[
        "horticulture",
        "agriculture",
        "livestock"
    ],
    "wof:name":"Hofbouwonderneming Goossens Andre Bvba",
    "wof:placetype":"venue"
},
  "geometry": {"coordinates":[3.6465890408,50.9960174561],"type":"Point"}
}