{
  "type": "Feature",
  "properties": {
    "addr:full":"Rue Sainte-catherine 41 Bruxelles Bruxelles-Capitale 1000",
    "addr:housenumber":"41",
    "addr:postcode":"1000",
    "addr:street":"Rue Sainte-Catherine",
    "iso:country":"BE",
    "sg:address":"Rue Sainte-catherine 41",
    "sg:city":"Bruxelles",
    "sg:classifiers":[
        {
            "category":"Shopping",
            "subcategory":"Discount & Variety Stores",
            "type":"Retail Goods"
        }
    ],
    "sg:phone":"+32 2 513 71 67",
    "sg:postcode":"1000",
    "sg:province":"Bruxelles-Capitale",
    "sg:tags":[
        "shop",
        "night"
    ],
    "wof:name":"New Shaheen",
    "wof:placetype":"venue"
},
  "geometry": {"coordinates":[4.3477277756,50.8503303528],"type":"Point"}
}