{
  "type": "Feature",
  "properties": {
    "addr:full":"Schuurstraat 15 Gent (sint-amandsberg) Oost-Vlaanderen 9040",
    "addr:housenumber":"15",
    "addr:postcode":"9040",
    "addr:street":"Schuurstraat",
    "iso:country":"BE",
    "sg:address":"Schuurstraat 15",
    "sg:city":"Gent (sint-amandsberg)",
    "sg:classifiers":[
        {
            "category":"Building & Trades",
            "subcategory":"Pest Control",
            "type":"Services"
        }
    ],
    "sg:phone":"+32 9 228 43 00",
    "sg:postcode":"9040",
    "sg:province":"Oost-Vlaanderen",
    "sg:tags":[
        "machine",
        "vending"
    ],
    "wof:name":"Cactus Bvba",
    "wof:placetype":"venue"
},
  "geometry": {"coordinates":[3.7756168842,51.068447113],"type":"Point"}
}