{
  "type": "Feature",
  "properties": {
    "addr:full":"Heppersteenweg 19b1 Maaseik Limburg 3680",
    "addr:housenumber":"19b1",
    "addr:postcode":"3680",
    "addr:street":"Heppersteenweg",
    "iso:country":"BE",
    "sg:address":"Heppersteenweg 19b1",
    "sg:city":"Maaseik",
    "sg:orig_category":"Diverse bedrijfsbeheeradviesbureaus",
    "sg:phone":"+32 89 56 35 75",
    "sg:postcode":"3680",
    "sg:province":"Limburg",
    "wof:name":"Jos Poell Belgi\u00cb",
    "wof:placetype":"venue"
},
  "geometry": {"coordinates":[5.7916412354,51.0918121338],"type":"Point"}
}