{
  "type": "Feature",
  "properties": {
    "iso:country":"BE",
    "sg:address":"Kapellei 133",
    "sg:city":"Zoersel",
    "sg:orig_category":"Rusthuizen and serviceflats Ziekenhuizen and zorginstellingen",
    "sg:phone":"+32 3 384 56 11",
    "sg:postcode":"2980",
    "sg:province":"Antwerpen",
    "wof:name":"Joostens Verpleegtehuis",
    "wof:placetype":"venue"
},
  "geometry": {"coordinates":[4.6252059937,51.2584686279],"type":"Point"}
}