{
  "type": "Feature",
  "properties": {
    "iso:country":"BE",
    "sg:address":"Rue De Roubaix 90",
    "sg:city":"Tournai",
    "sg:orig_category":"Woningbouw",
    "sg:phone":"+32 69 35 21 22",
    "sg:postcode":"7520",
    "sg:province":"Hainaut",
    "wof:name":"C.o.c.",
    "wof:placetype":"venue"
},
  "geometry": {"coordinates":[3.2708890438,50.6454963684],"type":"Point"}
}