{
  "type": "Feature",
  "properties": {
    "iso:country":"BE",
    "sg:address":"Cousseweg 2",
    "sg:city":"Jabbeke",
    "sg:classifiers":[
        {
            "category":"Building & Trades",
            "subcategory":"Construction",
            "type":"Services"
        }
    ],
    "sg:phone":"+32 50 81 25 99",
    "sg:postcode":"8490",
    "sg:province":"West-Vlaanderen",
    "sg:tags":[
        "insulation",
        "thermical",
        "work",
        "acoustical"
    ],
    "wof:name":"Herssens G",
    "wof:placetype":"venue"
},
  "geometry": {"coordinates":[3.0831899643,51.1826057434],"type":"Point"}
}