{
  "type": "Feature",
  "properties": {
    "iso:country":"BE",
    "sg:address":"Rue De La Station 12",
    "sg:city":"Soignies",
    "sg:classifiers":[
        {
            "category":"Bars & Pubs",
            "type":"Food & Drink"
        }
    ],
    "sg:phone":"+32 67 33 93 29",
    "sg:postcode":"7060",
    "sg:province":"Hainaut",
    "wof:name":"Palace (le)",
    "wof:placetype":"venue"
},
  "geometry": {"coordinates":[4.0716958046,50.5769462585],"type":"Point"}
}