{
  "type": "Feature",
  "properties": {
    "iso:country":"BE",
    "sg:address":"Nieuwelandenweg",
    "sg:city":"Antwerpen",
    "sg:classifiers":[
        {
            "category":"Autos & Motor Vehicles",
            "subcategory":"Auto Supplies",
            "type":"Retail Goods"
        }
    ],
    "sg:phone":"+32 3 541 52 52",
    "sg:postcode":"2030",
    "sg:province":"Antwerpen",
    "sg:tags":[
        "semi-trailers",
        "industrial",
        "-",
        "trailer"
    ],
    "wof:name":"Transamerica Trailer Leasing",
    "wof:placetype":"venue"
},
  "geometry": {"coordinates":[4.3903188705,51.2748565674],"type":"Point"}
}