{
  "type": "Feature",
  "properties": {
    "iso:country":"BE",
    "sg:address":"Blauwhuisstraat 6",
    "sg:city":"Harelbeke",
    "sg:orig_category":"Woningbouw",
    "sg:phone":"+32 56 71 77 39",
    "sg:postcode":"8531",
    "sg:province":"West-Vlaanderen",
    "wof:name":"Claerhout-delombaerde",
    "wof:placetype":"venue"
},
  "geometry": {"coordinates":[3.290749073,50.8832244873],"type":"Point"}
}