{
  "type": "Feature",
  "properties": {
    "iso:country":"BE",
    "sg:address":"Rue Raymond Pieret 59",
    "sg:city":"Tubize",
    "sg:orig_category":"Plomberie, chauffage and installations sanitaires. Collecte and \u00e9puration des eaux us\u00e9es",
    "sg:phone":"+32 2 355 90 43",
    "sg:postcode":"1480",
    "sg:province":"Brabant Wallon",
    "wof:name":"Tassignon",
    "wof:placetype":"venue"
},
  "geometry": {"coordinates":[4.2325739861,50.684463501],"type":"Point"}
}