{
  "type": "Feature",
  "properties": {
    "addr:full":"Rue De Wavre 22b Hannut Li\u00e8ge 4280",
    "addr:housenumber":"22b",
    "addr:postcode":"4280",
    "addr:street":"Rue De Wavre",
    "iso:country":"BE",
    "sg:address":"Rue De Wavre 22b",
    "sg:city":"Hannut",
    "sg:classifiers":[
        {
            "category":"Education",
            "subcategory":"School",
            "type":"Public Place"
        }
    ],
    "sg:phone":"+32 19 51 17 71",
    "sg:postcode":"4280",
    "sg:province":"Li\u00e8ge",
    "sg:tags":[
        "-",
        "private"
    ],
    "wof:name":"Oasis Familial (l')-ecole De Devoirs",
    "wof:placetype":"venue"
},
  "geometry": {"coordinates":[5.0715107918,50.6691818237],"type":"Point"}
}