{
  "type": "Feature",
  "properties": {
    "iso:country":"BE",
    "sg:address":"Rue De La Jonction 4",
    "sg:city":"Bertrix",
    "sg:orig_category":"Traitements param\u00e9dicaux",
    "sg:phone":"+32 61 41 23 41",
    "sg:postcode":"6880",
    "sg:province":"Luxembourg",
    "wof:name":"A. Jacquemin",
    "wof:placetype":"venue"
},
  "geometry": {"coordinates":[5.2548670769,49.8553352356],"type":"Point"}
}