{
  "type": "Feature",
  "properties": {
    "addr:full":"August Dilslei 43 Schilde Antwerpen 2970",
    "addr:housenumber":"43",
    "addr:postcode":"2970",
    "addr:street":"August Dilslei",
    "iso:country":"BE",
    "sg:address":"August Dilslei 43",
    "sg:city":"Schilde",
    "sg:classifiers":[
        {
            "category":"Arena",
            "subcategory":"Sports Club",
            "type":"Entertainment"
        }
    ],
    "sg:phone":"+32 3 685 65 82",
    "sg:postcode":"2970",
    "sg:province":"Antwerpen",
    "sg:tags":[
        "de"
    ],
    "wof:name":"W.c. Nieuwe Hoop Tielen",
    "wof:placetype":"venue"
},
  "geometry": {"coordinates":[4.5522480011,51.2583312988],"type":"Point"}
}