{
  "type": "Feature",
  "properties": {
    "addr:full":"Plaats 2 Ledegem West-Vlaanderen 8880",
    "addr:housenumber":"2",
    "addr:postcode":"8880",
    "addr:street":"Plaats",
    "iso:country":"BE",
    "sg:address":"Plaats 2",
    "sg:city":"Ledegem",
    "sg:classifiers":[
        {
            "category":"Bars & Pubs",
            "type":"Food & Drink"
        }
    ],
    "sg:phone":"+32 56 50 63 04",
    "sg:postcode":"8880",
    "sg:province":"West-Vlaanderen",
    "wof:name":"Toren (den)",
    "wof:placetype":"venue"
},
  "geometry": {"coordinates":[3.1263968945,50.8531761169],"type":"Point"}
}