{
  "type": "Feature",
  "properties": {
    "iso:country":"BE",
    "sg:address":"Rue Du Beffroi 37",
    "sg:city":"Saint-nicolas (montegn\u00e9e)",
    "sg:classifiers":[
        {
            "category":"Bakery",
            "type":"Food & Drink"
        }
    ],
    "sg:phone":"+32 4 263 49 22",
    "sg:postcode":"4420",
    "sg:province":"Li\u00e8ge",
    "sg:tags":[
        "confectioner",
        "baker"
    ],
    "wof:name":"Beffroi (le)",
    "wof:placetype":"venue"
},
  "geometry": {"coordinates":[5.5381250381,50.6303863525],"type":"Point"}
}