{
  "type": "Feature",
  "properties": {
    "addr:full":"Willem Van Doornyckstraat 98 Beveren (haasdonk) Oost-Vlaanderen 9120",
    "addr:housenumber":"98",
    "addr:postcode":"9120",
    "addr:street":"Willem Van Doornyckstraat",
    "iso:country":"BE",
    "sg:address":"Willem Van Doornyckstraat 98",
    "sg:city":"Beveren (haasdonk)",
    "sg:classifiers":[
        {
            "category":"Food & Beverages",
            "subcategory":"Groceries & Convenience Stores",
            "type":"Retail Goods"
        }
    ],
    "sg:phone":"+32 3 775 77 03",
    "sg:postcode":"9120",
    "sg:province":"Oost-Vlaanderen",
    "sg:tags":[
        "grocer"
    ],
    "wof:name":"De Schepper H",
    "wof:placetype":"venue"
},
  "geometry": {"coordinates":[4.2324662209,51.1794242859],"type":"Point"}
}