{
  "type": "Feature",
  "properties": {
    "addr:full":"Leopoldwal 19 Tongeren Limburg 3700",
    "addr:housenumber":"19",
    "addr:postcode":"3700",
    "addr:street":"Leopoldwal",
    "iso:country":"BE",
    "sg:address":"Leopoldwal 19",
    "sg:city":"Tongeren",
    "sg:orig_category":"Antiek",
    "sg:phone":"+32 12 39 45 43",
    "sg:postcode":"3700",
    "sg:province":"Limburg",
    "wof:name":"Noella Stas",
    "wof:placetype":"venue"
},
  "geometry": {"coordinates":[5.4714078903,50.7801856995],"type":"Point"}
}