{
  "type": "Feature",
  "properties": {
    "iso:country":"BE",
    "sg:address":"Osselstr 14/2",
    "sg:city":"Brussegem",
    "sg:classifiers":[
        {
            "category":"Manufacturing",
            "subcategory":"Jewelry",
            "type":"Manufacturing & Wholesale Goods"
        }
    ],
    "sg:phone":"+32 2 461 06 07",
    "sg:postcode":"1785",
    "sg:province":"Vlaams-Brabant",
    "sg:tags":[
        "product",
        "miscellaneous",
        "jewellery"
    ],
    "wof:name":"Dhr Stephan Mac Lafferty",
    "wof:placetype":"venue"
},
  "geometry": {"coordinates":[4.2745308876,50.9223861694],"type":"Point"}
}