{
  "type": "Feature",
  "properties": {
    "addr:full":"Centrumstraat 0 Lebbeke Oost-Vlaanderen 9280",
    "addr:housenumber":"0",
    "addr:postcode":"9280",
    "addr:street":"Centrumstraat",
    "iso:country":"BE",
    "sg:address":"Centrumstraat 0",
    "sg:city":"Lebbeke",
    "sg:orig_category":"Enseignement maternel and primaire",
    "sg:phone":"+32 52 41 19 48",
    "sg:postcode":"9280",
    "sg:province":"Oost-Vlaanderen",
    "wof:name":"Basisschool",
    "wof:placetype":"venue"
},
  "geometry": {"coordinates":[4.1333761215,51.0020141602],"type":"Point"}
}