{
  "type": "Feature",
  "properties": {
    "addr:full":"Chauss\u00e9e De Mons 62 Anderlues Hainaut 6150",
    "addr:housenumber":"62",
    "addr:postcode":"6150",
    "addr:street":"Chausse\u0301E De Mons",
    "iso:country":"BE",
    "sg:address":"Chauss\u00e9e De Mons 62",
    "sg:city":"Anderlues",
    "sg:classifiers":[
        {
            "category":"Health Services",
            "subcategory":"Health Practitioner",
            "type":"Services"
        }
    ],
    "sg:phone":"+32 71 54 42 98",
    "sg:postcode":"6150",
    "sg:province":"Hainaut",
    "sg:tags":[
        "physiotherapist"
    ],
    "wof:name":"Herman Benoit",
    "wof:placetype":"venue"
},
  "geometry": {"coordinates":[4.2286968231,50.4077949524],"type":"Point"}
}