{
  "type": "Feature",
  "properties": {
    "addr:full":"Rue Du Moulin 56 Musson (mussy-la-ville) Luxembourg 6750",
    "addr:housenumber":"56",
    "addr:postcode":"6750",
    "addr:street":"Rue Du Moulin",
    "iso:country":"BE",
    "sg:address":"Rue Du Moulin 56",
    "sg:city":"Musson (mussy-la-ville)",
    "sg:classifiers":[
        {
            "category":"Manufacturing",
            "subcategory":"Textiles",
            "type":"Manufacturing & Wholesale Goods"
        }
    ],
    "sg:phone":"+32 63 22 60 58",
    "sg:postcode":"6750",
    "sg:province":"Luxembourg",
    "sg:tags":[
        "polyester"
    ],
    "wof:name":"Multi Trading",
    "wof:placetype":"venue"
},
  "geometry": {"coordinates":[5.6716160774,49.5668144226],"type":"Point"}
}