{
  "type": "Feature",
  "properties": {
    "iso:country":"BE",
    "sg:address":"Avenue Des Petits Champs 30",
    "sg:city":"Waterloo",
    "sg:classifiers":[
        {
            "category":"Real Estate",
            "subcategory":"Architect",
            "type":"Services"
        }
    ],
    "sg:phone":"+32 2 354 90 82",
    "sg:postcode":"1410",
    "sg:province":"Brabant Wallon",
    "wof:name":"Cosse J",
    "wof:placetype":"venue"
},
  "geometry": {"coordinates":[4.4049010277,50.7237434387],"type":"Point"}
}