{
  "type": "Feature",
  "properties": {
    "addr:full":"Hoogstraat 2-4 Hoeselt Limburg 3730",
    "addr:housenumber":"2-4",
    "addr:postcode":"3730",
    "addr:street":"Hoogstraat",
    "iso:country":"BE",
    "sg:address":"Hoogstraat 2-4",
    "sg:city":"Hoeselt",
    "sg:classifiers":[
        {
            "category":"Cemetery",
            "type":"Public Place"
        }
    ],
    "sg:phone":"+32 89 41 12 81",
    "sg:postcode":"3730",
    "sg:province":"Limburg",
    "sg:tags":[
        "crematory"
    ],
    "wof:name":"Hellinx Bvba",
    "wof:placetype":"venue"
},
  "geometry": {"coordinates":[5.4813008308,50.8500595093],"type":"Point"}
}