{
  "type": "Feature",
  "properties": {
    "addr:full":"Bauwelstraat 2bc Kortenaken Vlaams-Brabant 3470",
    "addr:housenumber":"2bc",
    "addr:postcode":"3470",
    "addr:street":"Bauwelstraat",
    "iso:country":"BE",
    "sg:address":"Bauwelstraat 2bc",
    "sg:city":"Kortenaken",
    "sg:classifiers":[
        {
            "category":"Cafe",
            "type":"Food & Drink"
        }
    ],
    "sg:phone":"+32 11 58 75 21",
    "sg:postcode":"3470",
    "sg:province":"Vlaams-Brabant",
    "sg:tags":[
        "caf\u00e9s"
    ],
    "wof:name":"Caf\u00c9 De Hoef",
    "wof:placetype":"venue"
},
  "geometry": {"coordinates":[5.036523819,50.8922386169],"type":"Point"}
}