{
  "type": "Feature",
  "properties": {
    "addr:full":"Hoogstraat 3 Lichtervelde West-Vlaanderen 8810",
    "addr:housenumber":"3",
    "addr:postcode":"8810",
    "addr:street":"Hoogstraat",
    "iso:country":"BE",
    "sg:address":"Hoogstraat 3",
    "sg:city":"Lichtervelde",
    "sg:orig_category":"Services pour animaux domestiques",
    "sg:phone":"+32 51 72 33 43",
    "sg:postcode":"8810",
    "sg:province":"West-Vlaanderen",
    "wof:name":"Hondenverzorg. Cartouche",
    "wof:placetype":"venue"
},
  "geometry": {"coordinates":[3.1404559612,51.0276565552],"type":"Point"}
}