{
  "type": "Feature",
  "properties": {
    "iso:country":"BE",
    "sg:address":"Grand Route 293",
    "sg:city":"Drogenbos",
    "sg:orig_category":"Chaussures",
    "sg:phone":"+32 2 270 27 77",
    "sg:postcode":"1620",
    "sg:province":"Vlaams-Brabant",
    "wof:name":"Jacques Vijfeyken",
    "wof:placetype":"venue"
},
  "geometry": {"coordinates":[4.3175368309,50.7870101929],"type":"Point"}
}