{
  "type": "Feature",
  "properties": {
    "iso:country":"BE",
    "sg:address":"Rue De La Station 2",
    "sg:city":"Ramillies (ramillies-offus)",
    "sg:classifiers":[
        {
            "category":"Real Estate",
            "subcategory":"Surveying",
            "type":"Services"
        }
    ],
    "sg:phone":"+32 81 87 76 25",
    "sg:postcode":"1367",
    "sg:province":"Brabant Wallon",
    "sg:tags":[
        "surveyor",
        "land"
    ],
    "wof:name":"Dehon X",
    "wof:placetype":"venue"
},
  "geometry": {"coordinates":[4.9075708389,50.6384925842],"type":"Point"}
}