{
  "type": "Feature",
  "properties": {
    "iso:country":"BE",
    "sg:address":"Rue De L'orniat 27",
    "sg:city":"Jemeppe-sur-sambre (spy)",
    "sg:classifiers":[
        {
            "category":"Professional",
            "subcategory":"Accounting & Tax Preparation",
            "type":"Services"
        }
    ],
    "sg:phone":"+32 71 78 90 24",
    "sg:postcode":"5190",
    "sg:province":"Namur",
    "sg:tags":[
        "bookkeeper"
    ],
    "wof:name":"Velu E",
    "wof:placetype":"venue"
},
  "geometry": {"coordinates":[4.7051639557,50.4775238037],"type":"Point"}
}