{
  "type": "Feature",
  "properties": {
    "addr:full":"Rue Du Commerce 127 Ciney Namur 5590",
    "addr:housenumber":"127",
    "addr:postcode":"5590",
    "addr:street":"Rue Du Commerce",
    "iso:country":"BE",
    "sg:address":"Rue Du Commerce 127",
    "sg:city":"Ciney",
    "sg:orig_category":"Catering and organisatie van feesten Fast food and meeneem restaurants Restaurants",
    "sg:phone":"+32 83 21 66 99",
    "sg:postcode":"5590",
    "sg:province":"Namur",
    "wof:name":"Lai-lai",
    "wof:placetype":"venue"
},
  "geometry": {"coordinates":[5.0937371254,50.2911529541],"type":"Point"}
}