{
  "type": "Feature",
  "properties": {
    "addr:full":"Rue Haie-jadot 7 Hamois Namur 5360",
    "addr:housenumber":"7",
    "addr:postcode":"5360",
    "addr:street":"Rue Haie-Jadot",
    "iso:country":"BE",
    "sg:address":"Rue Haie-jadot 7",
    "sg:city":"Hamois",
    "sg:orig_category":"Plomberie, chauffage and installations sanitaires",
    "sg:phone":"+32 83 61 16 35",
    "sg:postcode":"5360",
    "sg:province":"Namur",
    "wof:name":"Marcel Duchemin",
    "wof:placetype":"venue"
},
  "geometry": {"coordinates":[5.1898598671,50.3475914001],"type":"Point"}
}