{
  "type": "Feature",
  "properties": {
    "addr:full":"Ichtegemstraat 88 Koekelare West-Vlaanderen 8680",
    "addr:housenumber":"88",
    "addr:postcode":"8680",
    "addr:street":"Ichtegemstraat",
    "iso:country":"BE",
    "sg:address":"Ichtegemstraat 88",
    "sg:city":"Koekelare",
    "sg:orig_category":"Slagers",
    "sg:phone":"+32 51 58 15 43",
    "sg:postcode":"8680",
    "sg:province":"West-Vlaanderen",
    "wof:name":"Joan Vansevenant",
    "wof:placetype":"venue"
},
  "geometry": {"coordinates":[2.9877669811,51.0899963379],"type":"Point"}
}