{
  "type": "Feature",
  "properties": {
    "addr:full":"Alsembergsesteenweg 973 Beersel Vlaams-Brabant 1654",
    "addr:housenumber":"973",
    "addr:postcode":"1654",
    "addr:street":"Alsembergsesteenweg",
    "iso:country":"BE",
    "sg:address":"Alsembergsesteenweg 973",
    "sg:city":"Beersel",
    "sg:orig_category":"Benzinestations and brandstoffen Herstellingen and onderhoud van auto's",
    "sg:phone":"+32 2 356 03 95",
    "sg:postcode":"1654",
    "sg:province":"Vlaams-Brabant",
    "wof:name":"S.d. Car",
    "wof:placetype":"venue"
},
  "geometry": {"coordinates":[4.2693419456,50.7443313599],"type":"Point"}
}