{
  "type": "Feature",
  "properties": {
    "addr:full":"Place Chanteraine 5 La Roche-en-ardenne Luxembourg 6980",
    "addr:housenumber":"5",
    "addr:postcode":"6980",
    "addr:street":"Place Chanteraine",
    "iso:country":"BE",
    "sg:address":"Place Chanteraine 5",
    "sg:city":"La Roche-en-ardenne",
    "sg:orig_category":"Foto-uitrusting Huishoudapparaten, televisies and radio's Kantoormateriaal Gh",
    "sg:phone":"+32 84 41 18 74",
    "sg:postcode":"6980",
    "sg:province":"Luxembourg",
    "wof:name":"Burotel La Roche",
    "wof:placetype":"venue"
},
  "geometry": {"coordinates":[5.5749220848,50.1813278198],"type":"Point"}
}