{
  "type": "Feature",
  "properties": {
    "iso:country":"BE",
    "sg:address":"Steenweg 19",
    "sg:city":"Asse",
    "sg:orig_category":"Voedingsspeciaalzaken",
    "sg:phone":"+32 2 452 49 39",
    "sg:postcode":"1730",
    "sg:province":"Vlaams-Brabant",
    "wof:name":"'t, Cruydthof",
    "wof:placetype":"venue"
},
  "geometry": {"coordinates":[4.1981220245,50.9109268188],"type":"Point"}
}