{
  "type": "Feature",
  "properties": {
    "addr:full":"Rue Des Fran\u00e7ais 393-5 Ans Li\u00e8ge 4430",
    "addr:postcode":"393-5;4430",
    "addr:street":"Rue Des Franc\u0327Ais",
    "iso:country":"BE",
    "sg:address":"Rue Des Fran\u00e7ais 393-5",
    "sg:city":"Ans",
    "sg:classifiers":[
        {
            "category":"Bars & Pubs",
            "type":"Food & Drink"
        }
    ],
    "sg:phone":"+32 4 247 38 08",
    "sg:postcode":"4430",
    "sg:province":"Li\u00e8ge",
    "wof:name":"Pacific",
    "wof:placetype":"venue"
},
  "geometry": {"coordinates":[5.5385499001,50.666759491],"type":"Point"}
}