{
  "type": "Feature",
  "properties": {
    "iso:country":"BE",
    "sg:address":"De Zippe 25",
    "sg:city":"Merchtem",
    "sg:classifiers":[
        {
            "category":"Insurance",
            "subcategory":"Insurance Agent",
            "type":"Services"
        }
    ],
    "sg:phone":"+32 52 37 18 76",
    "sg:postcode":"1785",
    "sg:province":"Vlaams-Brabant",
    "sg:tags":[
        "broker"
    ],
    "wof:name":"Ringoot-maetens",
    "wof:placetype":"venue"
},
  "geometry": {"coordinates":[4.232738018,50.9534416199],"type":"Point"}
}