{
  "type": "Feature",
  "properties": {
    "addr:full":"Vlasbloemstraat 1 Ichtegem West-Vlaanderen 8480",
    "addr:housenumber":"1",
    "addr:postcode":"8480",
    "addr:street":"Vlasbloemstraat",
    "iso:country":"BE",
    "sg:address":"Vlasbloemstraat 1",
    "sg:city":"Ichtegem",
    "sg:orig_category":"Rev\u00eatements pour sols and murs. Peinture",
    "sg:phone":"+32 51 58 46 95",
    "sg:postcode":"8480",
    "sg:province":"West-Vlaanderen",
    "wof:name":"N.d. Naeyaert Donaat",
    "wof:placetype":"venue"
},
  "geometry": {"coordinates":[3.035492897,51.102481842],"type":"Point"}
}