{
  "type": "Feature",
  "properties": {
    "iso:country":"BE",
    "sg:address":"Rue Du Roi Albert 49",
    "sg:city":"Oupeye",
    "sg:orig_category":"R\u00e9cup\u00e9ration de mati\u00e8res m\u00e9talliques recyclables and d\u00e9molisseurs de voitures. Entretien et r\u00e9parati",
    "sg:phone":"+32 479 38 69 72",
    "sg:postcode":"4680",
    "sg:province":"Li\u00e8ge",
    "wof:name":"Auto Activation",
    "wof:placetype":"venue"
},
  "geometry": {"coordinates":[5.6509251595,50.7043685913],"type":"Point"}
}