{
  "type": "Feature",
  "properties": {
    "iso:country":"BE",
    "sg:address":"Terlindenstraat 2",
    "sg:city":"Pepingen",
    "sg:orig_category":"Rundveehouders",
    "sg:phone":"+32 2 396 24 62",
    "sg:postcode":"1670",
    "sg:province":"Vlaams-Brabant",
    "wof:name":"Yvan Van Onsem",
    "wof:placetype":"venue"
},
  "geometry": {"coordinates":[4.0975241661,50.7291717529],"type":"Point"}
}