{
  "type": "Feature",
  "properties": {
    "iso:country":"BE",
    "sg:address":"Rue Du Mont Saint-alban 2",
    "sg:city":"Bruxelles",
    "sg:classifiers":[
        {
            "category":"Manufacturing",
            "subcategory":"Glass & Minerals",
            "type":"Manufacturing & Wholesale Goods"
        }
    ],
    "sg:phone":"+32 477 43 23 22",
    "sg:postcode":"1020",
    "sg:province":"Bruxelles-Capitale",
    "sg:tags":[
        "automobile",
        "-"
    ],
    "wof:name":"Rapido-glass Scrl",
    "wof:placetype":"venue"
},
  "geometry": {"coordinates":[4.347219944,50.8820953369],"type":"Point"}
}