{
  "type": "Feature",
  "properties": {
    "addr:full":"Gullegemsestraat 29 Ledegem (sint-eloois-winkel) West-Vlaanderen 8880",
    "addr:housenumber":"29",
    "addr:postcode":"8880",
    "addr:street":"Gullegemsestraat",
    "iso:country":"BE",
    "sg:address":"Gullegemsestraat 29",
    "sg:city":"Ledegem (sint-eloois-winkel)",
    "sg:classifiers":[
        {
            "category":"Shopping",
            "subcategory":"Clothing, Apparel, & Fashions",
            "type":"Retail Goods"
        }
    ],
    "sg:phone":"+32 56 50 97 25",
    "sg:postcode":"8880",
    "sg:province":"West-Vlaanderen",
    "sg:tags":[
        "lady",
        "clothing",
        "-"
    ],
    "wof:name":"Romo",
    "wof:placetype":"venue"
},
  "geometry": {"coordinates":[3.180672884,50.8742294312],"type":"Point"}
}