{
  "type": "Feature",
  "properties": {
    "iso:country":"BE",
    "sg:address":"Rue L\u00e9on Fran\u00e7ois 10",
    "sg:city":"Profondeville (bois-de-villers)",
    "sg:classifiers":[
        {
            "category":"Arena",
            "subcategory":"Sports Club",
            "type":"Entertainment"
        }
    ],
    "sg:phone":"+32 81 43 30 33",
    "sg:postcode":"5170",
    "sg:province":"Namur",
    "wof:name":"Tennis Club Bois De Villers",
    "wof:placetype":"venue"
},
  "geometry": {"coordinates":[4.8266611099,50.3968353271],"type":"Point"}
}