{
  "type": "Feature",
  "properties": {
    "iso:country":"BE",
    "sg:address":"Leenbosstraat 7",
    "sg:city":"Ardooie",
    "sg:orig_category":"Rundveehouders",
    "sg:phone":"+32 51 30 11 93",
    "sg:postcode":"8850",
    "sg:province":"West-Vlaanderen",
    "wof:name":"Albert Vangansbeke",
    "wof:placetype":"venue"
},
  "geometry": {"coordinates":[3.2212080956,50.9519042969],"type":"Point"}
}