{
  "type": "Feature",
  "properties": {
    "iso:country":"BE",
    "sg:address":"Spaansemolenstraat 27",
    "sg:city":"Antwerpen",
    "sg:orig_category":"Mutualities",
    "sg:phone":"+32 3 560 91 50",
    "sg:postcode":"2040",
    "sg:province":"Antwerpen",
    "wof:name":"Christelijke Mutualiteit",
    "wof:placetype":"venue"
},
  "geometry": {"coordinates":[4.3141150475,51.3429756165],"type":"Point"}
}