{
  "type": "Feature",
  "properties": {
    "addr:full":"Du Boislei 14 Brasschaat Antwerpen 2930",
    "addr:housenumber":"14",
    "addr:postcode":"2930",
    "iso:country":"BE",
    "sg:address":"Du Boislei 14",
    "sg:city":"Brasschaat",
    "sg:classifiers":[
        {
            "category":"Professional",
            "subcategory":"Management & Consulting",
            "type":"Services"
        }
    ],
    "sg:phone":"+32 3 651 25 54",
    "sg:postcode":"2930",
    "sg:province":"Antwerpen",
    "sg:tags":[
        "consultant",
        "agency",
        "advertising"
    ],
    "wof:name":"Ronald S",
    "wof:placetype":"venue"
},
  "geometry": {"coordinates":[4.4875721931,51.2926025391],"type":"Point"}
}