{
  "type": "Feature",
  "properties": {
    "iso:country":"BE",
    "sg:address":"Clos Du Marais 14",
    "sg:city":"Durbuy",
    "sg:orig_category":"Traitements param\u00e9dicaux",
    "sg:phone":"+32 86 21 23 33",
    "sg:postcode":"6940",
    "sg:province":"Luxembourg",
    "wof:name":"Jacquinet J.",
    "wof:placetype":"venue"
},
  "geometry": {"coordinates":[5.4859881401,50.3464584351],"type":"Point"}
}