{
  "type": "Feature",
  "properties": {
    "addr:full":"Rue La Premi\u00c8re Brigade 80 Leuze-en-hainaut Hainaut 7904",
    "addr:housenumber":"80",
    "addr:postcode":"7904",
    "addr:street":"Rue La Premie\u0300Re Brigade",
    "iso:country":"BE",
    "sg:address":"Rue La Premi\u00c8re Brigade 80",
    "sg:city":"Leuze-en-hainaut",
    "sg:orig_category":"Rundveehouders",
    "sg:phone":"+32 69 67 11 20",
    "sg:postcode":"7904",
    "sg:province":"Hainaut",
    "wof:name":"Franz Van De Ginste",
    "wof:placetype":"venue"
},
  "geometry": {"coordinates":[3.6325941086,50.5672874451],"type":"Point"}
}