{
  "type": "Feature",
  "properties": {
    "iso:country":"BE",
    "sg:address":"Hulsdonk 10",
    "sg:city":"Gent",
    "sg:orig_category":"Afval and schroot Gh",
    "sg:phone":"+32 9 342 22 21",
    "sg:postcode":"9042",
    "sg:province":"Oost-Vlaanderen",
    "wof:name":"A.t.v. Edelmet",
    "wof:placetype":"venue"
},
  "geometry": {"coordinates":[3.7816700935,51.1223831177],"type":"Point"}
}