{
  "type": "Feature",
  "properties": {
    "addr:full":"Rue De Robiano 70 Binche Hainaut 7130",
    "addr:housenumber":"70",
    "addr:postcode":"7130",
    "addr:street":"Rue De Robiano",
    "iso:country":"BE",
    "sg:address":"Rue De Robiano 70",
    "sg:city":"Binche",
    "sg:classifiers":[
        {
            "category":"Health Services",
            "subcategory":"Health Practitioner",
            "type":"Services"
        }
    ],
    "sg:phone":"+32 64 33 43 99",
    "sg:postcode":"7130",
    "sg:province":"Hainaut",
    "sg:tags":[
        "physiotherapist"
    ],
    "wof:name":"Vanderheyden Bernadette",
    "wof:placetype":"venue"
},
  "geometry": {"coordinates":[4.1697468758,50.4099006653],"type":"Point"}
}