{
  "type": "Feature",
  "properties": {
    "addr:full":"Pauwelslei 19 Brasschaat Antwerpen 2930",
    "addr:housenumber":"19",
    "addr:postcode":"2930",
    "addr:street":"Pauwelslei",
    "iso:country":"BE",
    "sg:address":"Pauwelslei 19",
    "sg:city":"Brasschaat",
    "sg:orig_category":"Boekenuitgeverijen",
    "sg:phone":"+32 3 651 42 61",
    "sg:postcode":"2930",
    "sg:province":"Antwerpen",
    "wof:name":"Uitgeverij Musicprint",
    "wof:placetype":"venue"
},
  "geometry": {"coordinates":[4.5093860626,51.3061790466],"type":"Point"}
}