{
  "type": "Feature",
  "properties": {
    "iso:country":"BE",
    "sg:address":"Houtmarkt 14",
    "sg:city":"Aalst",
    "sg:classifiers":[
        {
            "category":"Food & Beverages",
            "subcategory":"Chocolate",
            "type":"Retail Goods"
        }
    ],
    "sg:phone":"+32 53 70 74 84",
    "sg:postcode":"9300",
    "sg:province":"Oost-Vlaanderen",
    "sg:tags":[
        "confectionery",
        "-"
    ],
    "wof:name":"K.d.",
    "wof:placetype":"venue"
},
  "geometry": {"coordinates":[4.0439472198,50.9342269897],"type":"Point"}
}