{
  "type": "Feature",
  "properties": {
    "iso:country":"BE",
    "sg:address":"Place Cri Du Perron 11",
    "sg:city":"Saint-nicolas (montegn\u00e9e)",
    "sg:classifiers":[
        {
            "category":"Bars & Pubs",
            "type":"Food & Drink"
        }
    ],
    "sg:phone":"+32 4 384 83 46",
    "sg:postcode":"4420",
    "sg:province":"Li\u00e8ge",
    "wof:name":"Millenium (le)",
    "wof:placetype":"venue"
},
  "geometry": {"coordinates":[5.5146398544,50.6402816772],"type":"Point"}
}