{
  "type": "Feature",
  "properties": {
    "iso:country":"BE",
    "sg:address":"Nieuwmoerse Steenweg 113a",
    "sg:city":"Wuustwezel",
    "sg:classifiers":[
        {
            "category":"Community Center",
            "type":"Public Place"
        }
    ],
    "sg:phone":"+32 3 669 96 64",
    "sg:postcode":"2990",
    "sg:province":"Antwerpen",
    "sg:tags":[
        "medical"
    ],
    "wof:name":"Revalidatiecentrum Der Noorderkempen",
    "wof:placetype":"venue"
},
  "geometry": {"coordinates":[4.5440711975,51.4054908752],"type":"Point"}
}