{
  "type": "Feature",
  "properties": {
    "iso:country":"BE",
    "sg:address":"Vurstjen 25",
    "sg:city":"Evergem",
    "sg:classifiers":[
        {
            "category":"Education",
            "subcategory":"School",
            "type":"Public Place"
        }
    ],
    "sg:phone":"+32 9 253 99 56",
    "sg:postcode":"9940",
    "sg:province":"Oost-Vlaanderen",
    "sg:tags":[
        "boarding"
    ],
    "wof:name":"M.p.i.g.o.",
    "wof:placetype":"venue"
},
  "geometry": {"coordinates":[3.7017469406,51.1068878174],"type":"Point"}
}