{
  "type": "Feature",
  "properties": {
    "iso:country":"BE",
    "sg:address":"Chemin De Wavre 20",
    "sg:city":"Fleurus (wagnel\u00e9e)",
    "sg:classifiers":[
        {
            "category":"Health Services",
            "subcategory":"Health Practitioner",
            "type":"Services"
        }
    ],
    "sg:phone":"+32 71 81 60 82",
    "sg:postcode":"6223",
    "sg:province":"Hainaut",
    "sg:tags":[
        "physiotherapist"
    ],
    "wof:name":"De Fauconval Isabelle",
    "wof:placetype":"venue"
},
  "geometry": {"coordinates":[4.5385088921,50.51953125],"type":"Point"}
}