{
  "type": "Feature",
  "properties": {
    "addr:full":"Kerkenheide 13 Kasterlee Antwerpen 2460",
    "addr:housenumber":"13",
    "addr:postcode":"2460",
    "addr:street":"Kerkenheide",
    "iso:country":"BE",
    "sg:address":"Kerkenheide 13",
    "sg:city":"Kasterlee",
    "sg:orig_category":"Plaatsen van vloer- and muurbekleding Schilders Verlichting and huishoudartikelen",
    "sg:phone":"+32 14 85 18 19",
    "sg:postcode":"2460",
    "sg:province":"Antwerpen",
    "wof:name":"Robert Pauwels",
    "wof:placetype":"venue"
},
  "geometry": {"coordinates":[4.9602189064,51.2413825989],"type":"Point"}
}