{
  "type": "Feature",
  "properties": {
    "iso:country":"BE",
    "sg:address":"Dorpsstraat 13",
    "sg:city":"Sint-genesius-rode/rhode-saint-genese",
    "sg:classifiers":[
        {
            "category":"Fast Food",
            "type":"Food & Drink"
        }
    ],
    "sg:phone":"+32 2 380 01 46",
    "sg:postcode":"1640",
    "sg:province":"Vlaams-Brabant",
    "sg:tags":[
        "meeneem",
        "restaurant"
    ],
    "wof:name":"Restaurant Tha\u00cfs Oriental",
    "wof:placetype":"venue"
},
  "geometry": {"coordinates":[4.3438010216,50.7447280884],"type":"Point"}
}