{
  "type": "Feature",
  "properties": {
    "addr:full":"Jan Emiel Mommaertslaan 18b Machelen (diegem) Vlaams-Brabant 1831",
    "addr:housenumber":"18b",
    "addr:postcode":"1831",
    "addr:street":"Jan Emiel Mommaertslaan",
    "iso:country":"BE",
    "sg:address":"Jan Emiel Mommaertslaan 18b",
    "sg:city":"Machelen (diegem)",
    "sg:classifiers":[
        {
            "category":"Banks & Credit Unions",
            "subcategory":"Investment Brokerage",
            "type":"Services"
        }
    ],
    "sg:phone":"+32 2 720 70 07",
    "sg:postcode":"1831",
    "sg:province":"Vlaams-Brabant",
    "wof:name":"Advent Management Nv",
    "wof:placetype":"venue"
},
  "geometry": {"coordinates":[4.4443287849,50.8873291016],"type":"Point"}
}