{
  "type": "Feature",
  "properties": {
    "iso:country":"BE",
    "sg:address":"Chauss\u00e9e De Lille 74",
    "sg:city":"Tournai (blandain - Hertain)",
    "sg:classifiers":[
        {
            "category":"Autos & Motor Vehicles",
            "subcategory":"Fuel & Gas Station",
            "type":"Retail Goods"
        }
    ],
    "sg:phone":"+32 69 84 66 90",
    "sg:postcode":"7522",
    "sg:province":"Hainaut",
    "wof:name":"Texaco (station Service)",
    "wof:placetype":"venue"
},
  "geometry": {"coordinates":[3.2911970615,50.6082458496],"type":"Point"}
}