{
  "type": "Feature",
  "properties": {
    "iso:country":"BE",
    "sg:address":"Eeuwfeestlaan 158",
    "sg:city":"Lier",
    "sg:classifiers":[
        {
            "category":"Professional",
            "subcategory":"Computer Services",
            "type":"Services"
        }
    ],
    "sg:phone":"+32 3 290 80 94",
    "sg:postcode":"2500",
    "sg:province":"Antwerpen",
    "sg:tags":[
        "webdesign",
        "-",
        "internet"
    ],
    "wof:name":"Wide Open Windows",
    "wof:placetype":"venue"
},
  "geometry": {"coordinates":[4.5658631325,51.1383056641],"type":"Point"}
}