{
  "type": "Feature",
  "properties": {
    "iso:country":"BE",
    "sg:address":"Lage Rooy 6",
    "sg:city":"Hoogstraten",
    "sg:orig_category":"Fruitteelt",
    "sg:phone":"+32 3 315 75 75",
    "sg:postcode":"2328",
    "sg:province":"Antwerpen",
    "wof:name":"Joannes Van Den Bogerd",
    "wof:placetype":"venue"
},
  "geometry": {"coordinates":[4.8035321236,51.4678535461],"type":"Point"}
}