{
  "type": "Feature",
  "properties": {
    "addr:full":"Kozenstraat 14 Hasselt Limburg 3512",
    "addr:housenumber":"14",
    "addr:postcode":"3512",
    "addr:street":"Kozenstraat",
    "iso:country":"BE",
    "sg:address":"Kozenstraat 14",
    "sg:city":"Hasselt",
    "sg:orig_category":"Elektrische installaties voor woningen",
    "sg:phone":"+32 11 59 24 15",
    "sg:postcode":"3512",
    "sg:province":"Limburg",
    "wof:name":"L. Busse",
    "wof:placetype":"venue"
},
  "geometry": {"coordinates":[5.2458338737,50.9099769592],"type":"Point"}
}