{
  "type": "Feature",
  "properties": {
    "iso:country":"BE",
    "sg:address":"Avenue De La Closeraie 74",
    "sg:city":"Li\u00c8ge",
    "sg:orig_category":"Installation \u00e9lectrique r\u00e9sidentielle",
    "sg:phone":"+32 4 226 06 76",
    "sg:postcode":"4000",
    "sg:province":"Li\u00e8ge",
    "wof:name":"Dico",
    "wof:placetype":"venue"
},
  "geometry": {"coordinates":[5.5496430397,50.6667938232],"type":"Point"}
}