{
  "type": "Feature",
  "properties": {
    "iso:country":"BE",
    "sg:address":"Lange Dijkstraat 68-70",
    "sg:city":"Anvers",
    "sg:orig_category":"Kantoor- and winkelmeubelen Fab",
    "sg:phone":"+32 3 225 06 56",
    "sg:postcode":"2060",
    "sg:province":"Antwerpen",
    "wof:name":"Metaplex",
    "wof:placetype":"venue"
},
  "geometry": {"coordinates":[4.4195399284,51.2283630371],"type":"Point"}
}