{
  "type": "Feature",
  "properties": {
    "iso:country":"BE",
    "sg:address":"Rue De L'aub\u00c9pine 21",
    "sg:city":"Beauraing",
    "sg:orig_category":"Boucheries",
    "sg:phone":"+32 82 71 14 04",
    "sg:postcode":"5570",
    "sg:province":"Namur",
    "wof:name":"Boucherie Lambot",
    "wof:placetype":"venue"
},
  "geometry": {"coordinates":[4.9617390633,50.1091995239],"type":"Point"}
}