{
  "type": "Feature",
  "properties": {
    "addr:full":"Nieuwstraat 97 Geel Antwerpen 2440",
    "addr:housenumber":"97",
    "addr:postcode":"2440",
    "addr:street":"Nieuwstraat",
    "iso:country":"BE",
    "sg:address":"Nieuwstraat 97",
    "sg:city":"Geel",
    "sg:orig_category":"Quincailleries. Magasins de r\u00e9parations d'articles personnels et m\u00e9nagers divers. R\u00e9parations de cha",
    "sg:phone":"+32 14 58 54 46",
    "sg:postcode":"2440",
    "sg:province":"Antwerpen",
    "wof:name":"Schoenmakerij Vivalei",
    "wof:placetype":"venue"
},
  "geometry": {"coordinates":[4.9955239296,51.163105011],"type":"Point"}
}