{
  "type": "Feature",
  "properties": {
    "iso:country":"BE",
    "sg:address":"Rue De Cortenbach 11",
    "sg:city":"Brussel/bruxelles",
    "sg:orig_category":"Action sociale avec h\u00e9bergement",
    "sg:phone":"+32 2 215 14 35",
    "sg:postcode":"1130",
    "sg:province":"Bruxelles-Capitale",
    "wof:name":"Antenne Sociale",
    "wof:placetype":"venue"
},
  "geometry": {"coordinates":[4.4176220894,50.8922538757],"type":"Point"}
}