{
  "type": "Feature",
  "properties": {
    "iso:country":"BE",
    "sg:address":"Hoevensebaan 69",
    "sg:city":"Kapellen",
    "sg:orig_category":"Brood, gebak and snoepgoed",
    "sg:phone":"+32 3 664 56 97",
    "sg:postcode":"2950",
    "sg:province":"Antwerpen",
    "wof:name":"Huis Bossuyt",
    "wof:placetype":"venue"
},
  "geometry": {"coordinates":[4.4259538651,51.3135261536],"type":"Point"}
}