{
  "type": "Feature",
  "properties": {
    "iso:country":"BE",
    "sg:address":"Gentsestraat 123",
    "sg:city":"Aalst",
    "sg:orig_category":"Sociale secretariaten",
    "sg:phone":"+32 53 21 38 59",
    "sg:postcode":"9300",
    "sg:province":"Oost-Vlaanderen",
    "wof:name":"A.s.k.z.-a.p.z.",
    "wof:placetype":"venue"
},
  "geometry": {"coordinates":[4.0289158821,50.9376106262],"type":"Point"}
}