{
  "type": "Feature",
  "properties": {
    "iso:country":"BE",
    "sg:address":"Grand\u00b4route 50ba",
    "sg:city":"Mont-saint-guibert",
    "sg:orig_category":"Rusthuizen and serviceflats",
    "sg:phone":"+32 10 65 75 34",
    "sg:postcode":"1435",
    "sg:province":"Brabant Wallon",
    "wof:name":"Home Mimas & Co",
    "wof:placetype":"venue"
},
  "geometry": {"coordinates":[4.6118340492,50.6367034912],"type":"Point"}
}