{
  "type": "Feature",
  "properties": {
    "addr:full":"Bronstraat 38 Hoegaarden Vlaams-Brabant 3320",
    "addr:housenumber":"38",
    "addr:postcode":"3320",
    "addr:street":"Bronstraat",
    "iso:country":"BE",
    "sg:address":"Bronstraat 38",
    "sg:city":"Hoegaarden",
    "sg:orig_category":"Eleveurs and marchands de porcs",
    "sg:phone":"+32 16 81 62 32",
    "sg:postcode":"3320",
    "sg:province":"Vlaams-Brabant",
    "wof:name":"William Coeckelberghs",
    "wof:placetype":"venue"
},
  "geometry": {"coordinates":[4.8718881607,50.7995452881],"type":"Point"}
}