{
  "type": "Feature",
  "properties": {
    "iso:country":"BE",
    "sg:address":"Chauss\u00c9e De Gand 1332",
    "sg:city":"Sint-agatha-berchem/berchem-sainte-agathe",
    "sg:orig_category":"Pharmaciens",
    "sg:phone":"+32 2 465 35 42",
    "sg:postcode":"1082",
    "sg:province":"Bruxelles-Capitale",
    "wof:name":"Arcofarma",
    "wof:placetype":"venue"
},
  "geometry": {"coordinates":[4.2923789024,50.8688583374],"type":"Point"}
}