{
  "type": "Feature",
  "properties": {
    "addr:full":"Leuvensesteenweg 540b5 Zaventem Vlaams-Brabant 1930",
    "addr:housenumber":"540b5",
    "addr:postcode":"1930",
    "addr:street":"Leuvensesteenweg",
    "iso:country":"BE",
    "sg:address":"Leuvensesteenweg 540b5",
    "sg:city":"Zaventem",
    "sg:orig_category":"Informaticaconsulenten Kantoormateriaal Gh Software ontwikkeling and ontwerp",
    "sg:phone":"+32 2 722 87 11",
    "sg:postcode":"1930",
    "sg:province":"Vlaams-Brabant",
    "wof:name":"Intellect",
    "wof:placetype":"venue"
},
  "geometry": {"coordinates":[4.4933848381,50.8743858337],"type":"Point"}
}