{
  "type": "Feature",
  "properties": {
    "addr:full":"Meirhoekstraat 24 Laarne Oost-Vlaanderen 9270",
    "addr:housenumber":"24",
    "addr:postcode":"9270",
    "addr:street":"Meirhoekstraat",
    "iso:country":"BE",
    "sg:address":"Meirhoekstraat 24",
    "sg:city":"Laarne",
    "sg:orig_category":"Elektrische installaties voor woningen",
    "sg:phone":"+32 9 366 31 42",
    "sg:postcode":"9270",
    "sg:province":"Oost-Vlaanderen",
    "wof:name":"Dirk Scheire",
    "wof:placetype":"venue"
},
  "geometry": {"coordinates":[3.86226511,51.0265235901],"type":"Point"}
}