{
  "type": "Feature",
  "properties": {
    "addr:full":"Grote Markt 27 Izegem West-Vlaanderen 8870",
    "addr:housenumber":"27",
    "addr:postcode":"8870",
    "addr:street":"Grote Markt",
    "iso:country":"BE",
    "sg:address":"Grote Markt 27",
    "sg:city":"Izegem",
    "sg:classifiers":[
        {
            "category":"Bars & Pubs",
            "type":"Food & Drink"
        }
    ],
    "sg:phone":"+32 51 31 67 37",
    "sg:postcode":"8870",
    "sg:province":"West-Vlaanderen",
    "wof:name":"Mozart",
    "wof:placetype":"venue"
},
  "geometry": {"coordinates":[3.2148590088,50.9198265076],"type":"Point"}
}