{
  "type": "Feature",
  "properties": {
    "addr:full":"Rue Du Ch\u00cane 25 Ciney Namur 5590",
    "addr:housenumber":"25",
    "addr:postcode":"5590",
    "addr:street":"Rue Du Che\u0302Ne",
    "iso:country":"BE",
    "sg:address":"Rue Du Ch\u00cane 25",
    "sg:city":"Ciney",
    "sg:orig_category":"Eleveurs de bovins",
    "sg:phone":"+32 83 21 14 57",
    "sg:postcode":"5590",
    "sg:province":"Namur",
    "wof:name":"Serge Chaboteaux",
    "wof:placetype":"venue"
},
  "geometry": {"coordinates":[5.1022520065,50.297088623],"type":"Point"}
}