{
  "type": "Feature",
  "properties": {
    "addr:full":"Peter Benoitstraat 39 Izegem West-Vlaanderen 8870",
    "addr:housenumber":"39",
    "addr:postcode":"8870",
    "addr:street":"Peter Benoitstraat",
    "iso:country":"BE",
    "sg:address":"Peter Benoitstraat 39",
    "sg:city":"Izegem",
    "sg:orig_category":"Artiesten and kunstenaars",
    "sg:phone":"+32 51 30 44 28",
    "sg:postcode":"8870",
    "sg:province":"West-Vlaanderen",
    "wof:name":"Raphael Werbrouck",
    "wof:placetype":"venue"
},
  "geometry": {"coordinates":[3.2215969563,50.9245109558],"type":"Point"}
}