{
  "type": "Feature",
  "properties": {
    "addr:full":"Longchamplaan 1 Oostende West-Vlaanderen 8400",
    "addr:housenumber":"1",
    "addr:postcode":"8400",
    "addr:street":"Longchamplaan",
    "iso:country":"BE",
    "sg:address":"Longchamplaan 1",
    "sg:city":"Oostende",
    "sg:orig_category":"Sportterreinen and installaties behalve sportcentra",
    "sg:phone":"+32 59 70 49 32",
    "sg:postcode":"8400",
    "sg:province":"West-Vlaanderen",
    "wof:name":"Paul Smith Racing Stables",
    "wof:placetype":"venue"
},
  "geometry": {"coordinates":[2.9126999378,51.2312583923],"type":"Point"}
}