{
  "type": "Feature",
  "properties": {
    "addr:full":"Veldstraat 307 Temse Oost-Vlaanderen 9140",
    "addr:housenumber":"307",
    "addr:postcode":"9140",
    "addr:street":"Veldstraat",
    "iso:country":"BE",
    "sg:address":"Veldstraat 307",
    "sg:city":"Temse",
    "sg:orig_category":"Herstellingen and onderhoud van auto's",
    "sg:phone":"+32 3 771 05 30",
    "sg:postcode":"9140",
    "sg:province":"Oost-Vlaanderen",
    "wof:name":"Rene Van Landeghem",
    "wof:placetype":"venue"
},
  "geometry": {"coordinates":[4.2158341408,51.1499938965],"type":"Point"}
}