{
  "type": "Feature",
  "properties": {
    "addr:full":"Rue Albert Dekkers 15 Dalhem (warsage) Li\u00e8ge 4608",
    "addr:housenumber":"15",
    "addr:postcode":"4608",
    "addr:street":"Rue Albert Dekkers",
    "iso:country":"BE",
    "sg:address":"Rue Albert Dekkers 15",
    "sg:city":"Dalhem (warsage)",
    "sg:classifiers":[
        {
            "category":"Building & Trades",
            "subcategory":"Construction",
            "type":"Services"
        }
    ],
    "sg:phone":"+32 4 376 67 30",
    "sg:postcode":"4608",
    "sg:province":"Li\u00e8ge",
    "sg:tags":[
        "carpenter"
    ],
    "wof:name":"Scheepers E",
    "wof:placetype":"venue"
},
  "geometry": {"coordinates":[5.7726111412,50.735622406],"type":"Point"}
}