{
  "type": "Feature",
  "properties": {
    "iso:country":"BE",
    "sg:address":"Chauss\u00c9e De Mont St.jean 192",
    "sg:city":"Braine-l'alleud",
    "sg:classifiers":[
        {
            "category":"Retail",
            "subcategory":"Car Wash",
            "type":"Services"
        }
    ],
    "sg:phone":"+32 2 384 77 08",
    "sg:postcode":"1420",
    "sg:province":"Brabant Wallon",
    "sg:tags":[
        "machine",
        "mat\u00e9riel",
        "de",
        "bureau",
        "fournitures"
    ],
    "wof:name":"G Bureautique",
    "wof:placetype":"venue"
},
  "geometry": {"coordinates":[4.9165067673,50.3185577393],"type":"Point"}
}