{
  "type": "Feature",
  "properties": {
    "addr:full":"Brugstraat 40 Geraardsbergen Oost-Vlaanderen 9500",
    "addr:housenumber":"40",
    "addr:postcode":"9500",
    "addr:street":"Brugstraat",
    "iso:country":"BE",
    "sg:address":"Brugstraat 40",
    "sg:city":"Geraardsbergen",
    "sg:orig_category":"Meubles D\u00e9taillants, Am\u00e9nagement de B\u00e2timents et de Cuisines",
    "sg:phone":"+32 54 41 27 78",
    "sg:postcode":"9500",
    "sg:province":"Oost-Vlaanderen",
    "wof:name":"Aime Baptist",
    "wof:placetype":"venue"
},
  "geometry": {"coordinates":[3.8802700043,50.7715988159],"type":"Point"}
}