{
  "type": "Feature",
  "properties": {
    "iso:country":"BE",
    "sg:address":"Kleempoelstraat 32",
    "sg:city":"Zemst",
    "sg:orig_category":"Instituts de beaut\u00e9",
    "sg:phone":"+32 15 61 53 60",
    "sg:postcode":"1980",
    "sg:province":"Vlaams-Brabant",
    "wof:name":"Marleen Pasteels",
    "wof:placetype":"venue"
},
  "geometry": {"coordinates":[4.454515934,50.9866333008],"type":"Point"}
}