{
  "type": "Feature",
  "properties": {
    "addr:full":"De Vunt 13 Holsbeek Vlaams-Brabant 3220",
    "addr:housenumber":"13",
    "addr:postcode":"3220",
    "iso:country":"BE",
    "sg:address":"De Vunt 13",
    "sg:city":"Holsbeek",
    "sg:orig_category":"Non-Classified Establishments",
    "sg:phone":"+32 16 44 55 85",
    "sg:postcode":"3220",
    "sg:province":"Vlaams-Brabant",
    "wof:name":"Eurolight Professional Lighting",
    "wof:placetype":"venue"
},
  "geometry": {"coordinates":[4.7167978287,50.9123573303],"type":"Point"}
}