{
  "type": "Feature",
  "properties": {
    "addr:full":"Centre 81 Plombi\u00c8res Li\u00e8ge 4852",
    "addr:housenumber":"81",
    "addr:postcode":"4852",
    "iso:country":"BE",
    "sg:address":"Centre 81",
    "sg:city":"Plombi\u00c8res",
    "sg:orig_category":"Pharmaciens",
    "sg:phone":"+32 87 78 50 53",
    "sg:postcode":"4852",
    "sg:province":"Li\u00e8ge",
    "wof:name":"Pharmacie De Hombourg",
    "wof:placetype":"venue"
},
  "geometry": {"coordinates":[5.9622411728,50.7385292053],"type":"Point"}
}