{
  "type": "Feature",
  "properties": {
    "iso:country":"BE",
    "sg:address":"Kerkhofstr 419",
    "sg:city":"Boom",
    "sg:classifiers":[
        {
            "category":"Travel",
            "subcategory":"Hotels & Motels",
            "type":"Entertainment"
        }
    ],
    "sg:phone":"+32 3 844 81 91",
    "sg:postcode":"2850",
    "sg:province":"Antwerpen",
    "sg:tags":[
        "hotels",
        "business",
        "restaurant"
    ],
    "wof:name":"De Smoutstoop Bvba",
    "wof:placetype":"venue"
},
  "geometry": {"coordinates":[4.3829312325,51.0973548889],"type":"Point"}
}