{
  "type": "Feature",
  "properties": {
    "addr:full":"Rue D'henripont 3 Ecaussinnes (ecaussinnes-d'enghien) Hainaut 7190",
    "addr:housenumber":"3",
    "addr:postcode":"7190",
    "addr:street":"Rue D'Henripont;Ecaussinnes-D'Enghien Hainaut",
    "iso:country":"BE",
    "sg:address":"Rue D'henripont 3",
    "sg:city":"Ecaussinnes (ecaussinnes-d'enghien)",
    "sg:classifiers":[
        {
            "category":"Retail",
            "subcategory":"Auto Repair",
            "type":"Services"
        }
    ],
    "sg:phone":"+32 67 49 11 33",
    "sg:postcode":"7190",
    "sg:province":"Hainaut",
    "sg:tags":[
        "garage"
    ],
    "wof:name":"Varlet-brabant Sa",
    "wof:placetype":"venue"
},
  "geometry": {"coordinates":[4.1749711037,50.5729560852],"type":"Point"}
}