{
  "type": "Feature",
  "properties": {
    "iso:country":"BE",
    "sg:address":"Tiensestraat 12",
    "sg:city":"Leuven",
    "sg:classifiers":[
        {
            "category":"Shopping",
            "subcategory":"Clothing, Apparel, & Fashions",
            "type":"Retail Goods"
        }
    ],
    "sg:phone":"+32 16 20 63 77",
    "sg:postcode":"3000",
    "sg:province":"Vlaams-Brabant",
    "sg:tags":[
        "v\u00eatements",
        "pour",
        "dame"
    ],
    "wof:name":"Huis Sei",
    "wof:placetype":"venue"
},
  "geometry": {"coordinates":[4.7031621933,50.8785400391],"type":"Point"}
}