{
  "type": "Feature",
  "properties": {
    "iso:country":"BE",
    "sg:address":"Steenstraat 115",
    "sg:city":"Meulebeke",
    "sg:orig_category":"Plomberie, chauffage and installations sanitaires",
    "sg:phone":"+32 51 48 78 26",
    "sg:postcode":"8760",
    "sg:province":"West-Vlaanderen",
    "wof:name":"Naessens Gebrs",
    "wof:placetype":"venue"
},
  "geometry": {"coordinates":[3.2840709686,50.9409561157],"type":"Point"}
}