{
  "type": "Feature",
  "properties": {
    "iso:country":"BE",
    "sg:address":"Rue De La-roche 49",
    "sg:city":"Hotton",
    "sg:classifiers":[
        {
            "category":"Restaurant",
            "type":"Food & Drink"
        }
    ],
    "sg:phone":"+32 84 46 78 52",
    "sg:postcode":"6990",
    "sg:province":"Luxembourg",
    "sg:tags":[
        "caf\u00e9s"
    ],
    "wof:name":"La Taverne",
    "wof:placetype":"venue"
},
  "geometry": {"coordinates":[5.4719419479,50.2579421997],"type":"Point"}
}