{
  "type": "Feature",
  "properties": {
    "addr:full":"Kraenepoelpad 51 Aalter Oost-Vlaanderen 9880",
    "addr:housenumber":"51",
    "addr:postcode":"9880",
    "addr:street":"Kraenepoelpad",
    "iso:country":"BE",
    "sg:address":"Kraenepoelpad 51",
    "sg:city":"Aalter",
    "sg:classifiers":[
        {
            "category":"Professional",
            "subcategory":"Art Services",
            "type":"Services"
        }
    ],
    "sg:phone":"+32 9 375 22 04",
    "sg:postcode":"9880",
    "sg:province":"Oost-Vlaanderen",
    "sg:tags":[
        "-",
        "mailing",
        "lettershops",
        "direct",
        "mail"
    ],
    "wof:name":"Kontekst",
    "wof:placetype":"venue"
},
  "geometry": {"coordinates":[3.4790589809,51.0726928711],"type":"Point"}
}