{
  "type": "Feature",
  "properties": {
    "iso:country":"BE",
    "sg:address":"Heirentstraat 4",
    "sg:city":"Meulebeke",
    "sg:orig_category":"Eleveurs and marchands de porcs",
    "sg:phone":"+32 51 40 04 74",
    "sg:postcode":"8760",
    "sg:province":"West-Vlaanderen",
    "wof:name":"Ludwig Boone",
    "wof:placetype":"venue"
},
  "geometry": {"coordinates":[3.3441300392,50.9571266174],"type":"Point"}
}