{
  "type": "Feature",
  "properties": {
    "iso:country":"BE",
    "sg:address":"Rue De La Ferme 18",
    "sg:city":"Ans",
    "sg:classifiers":[
        {
            "category":"Parking",
            "subcategory":"Lot",
            "type":"Transportation"
        }
    ],
    "sg:phone":"+32 4 246 36 74",
    "sg:postcode":"4430",
    "sg:province":"Li\u00e8ge",
    "sg:tags":[
        "parking-places",
        "laying-out"
    ],
    "wof:name":"Terpa Sprl",
    "wof:placetype":"venue"
},
  "geometry": {"coordinates":[5.5190191269,50.6570739746],"type":"Point"}
}