{
  "type": "Feature",
  "properties": {
    "addr:full":"Cleynaertstraat 10 Diest Vlaams-Brabant 3290",
    "addr:housenumber":"10",
    "addr:postcode":"3290",
    "addr:street":"Cleynaertstraat",
    "iso:country":"BE",
    "sg:address":"Cleynaertstraat 10",
    "sg:city":"Diest",
    "sg:orig_category":"S\u00e9curit\u00e9 sociale",
    "sg:phone":"+32 13 31 14 13",
    "sg:postcode":"3290",
    "sg:province":"Vlaams-Brabant",
    "wof:name":"Hulp En Arbeid",
    "wof:placetype":"venue"
},
  "geometry": {"coordinates":[5.0508131981,50.9851531982],"type":"Point"}
}