{
  "type": "Feature",
  "properties": {
    "addr:full":"Rue Marcel Barbieux 3 Momignies Hainaut 6591",
    "addr:housenumber":"3",
    "addr:postcode":"6591",
    "addr:street":"Rue Marcel Barbieux;Hainaut",
    "iso:country":"BE",
    "sg:address":"Rue Marcel Barbieux 3",
    "sg:city":"Momignies",
    "sg:orig_category":"Woningbouw",
    "sg:phone":"+32 60 51 22 98",
    "sg:postcode":"6591",
    "sg:province":"Hainaut",
    "wof:name":"Ets. Gobeaux A.",
    "wof:placetype":"venue"
},
  "geometry": {"coordinates":[4.2035579681,50.040435791],"type":"Point"}
}