{
  "type": "Feature",
  "properties": {
    "iso:country":"BE",
    "sg:address":"Eeklostraat 144",
    "sg:city":"Gent",
    "sg:orig_category":"Enseignement maternel and primaire",
    "sg:phone":"+32 9 226 39 77",
    "sg:postcode":"9030",
    "sg:province":"Oost-Vlaanderen",
    "wof:name":"Vrije Kleuterschool",
    "wof:placetype":"venue"
},
  "geometry": {"coordinates":[3.6932680607,51.0750846863],"type":"Point"}
}