{
  "type": "Feature",
  "properties": {
    "addr:full":"Oude Zilverbergstraat 82 Roeselare (rumbeke) West-Vlaanderen 8800",
    "addr:housenumber":"82",
    "addr:postcode":"8800",
    "addr:street":"Oude Zilverbergstraat",
    "iso:country":"BE",
    "sg:address":"Oude Zilverbergstraat 82",
    "sg:city":"Roeselare (rumbeke)",
    "sg:classifiers":[
        {
            "category":"Health Services",
            "subcategory":"Chiropractor",
            "type":"Services"
        }
    ],
    "sg:phone":"+32 51 20 30 89",
    "sg:postcode":"8800",
    "sg:province":"West-Vlaanderen",
    "wof:name":"Lambrecht L",
    "wof:placetype":"venue"
},
  "geometry": {"coordinates":[3.1034948826,50.9236068726],"type":"Point"}
}