{
  "type": "Feature",
  "properties": {
    "iso:country":"BE",
    "sg:address":"Atealaan 12",
    "sg:city":"Herentals",
    "sg:classifiers":[
        {
            "category":"Manufacturing",
            "subcategory":"Wood Products",
            "type":"Manufacturing & Wholesale Goods"
        }
    ],
    "sg:phone":"+32 14 22 45 85",
    "sg:postcode":"2200",
    "sg:province":"Antwerpen",
    "sg:tags":[
        "professional",
        "furniture"
    ],
    "wof:name":"Van Hoof Bvba",
    "wof:placetype":"venue"
},
  "geometry": {"coordinates":[4.7880501747,51.1609992981],"type":"Point"}
}