{
  "type": "Feature",
  "properties": {
    "iso:country":"BE",
    "sg:address":"Steenweg Wijchmaal 2b16",
    "sg:city":"Peer (groot)",
    "sg:classifiers":[
        {
            "category":"Personal",
            "subcategory":"Beauty Salon",
            "type":"Services"
        }
    ],
    "sg:phone":"+32 11 79 32 44",
    "sg:postcode":"3990",
    "sg:province":"Limburg",
    "sg:tags":[
        "de",
        "coiffure"
    ],
    "wof:name":"Coiffure l En S",
    "wof:placetype":"venue"
},
  "geometry": {"coordinates":[5.4500350952,51.1329154968],"type":"Point"}
}