{
  "type": "Feature",
  "properties": {
    "iso:country":"BE",
    "sg:address":"Avenue De La Couronne 96",
    "sg:city":"Elsene/ixelles",
    "sg:orig_category":"Syst\u00e8mes de t\u00e9l\u00e9communications. Installation \u00e9lectrique industrielle",
    "sg:phone":"+32 2 640 11 00",
    "sg:postcode":"1050",
    "sg:province":"Bruxelles-Capitale",
    "wof:name":"Telecom",
    "wof:placetype":"venue"
},
  "geometry": {"coordinates":[4.3787140846,50.8301696777],"type":"Point"}
}