{
  "type": "Feature",
  "properties": {
    "iso:country":"BE",
    "sg:address":"Rue Leopold Thonon 70",
    "sg:city":"Herstal (liers)",
    "sg:classifiers":[
        {
            "category":"Autos & Motor Vehicles",
            "subcategory":"Automobile Sales",
            "type":"Retail Goods"
        }
    ],
    "sg:phone":"+32 4 278 63 33",
    "sg:postcode":"4042",
    "sg:province":"Li\u00e8ge",
    "sg:tags":[
        "delivery",
        "-",
        "used",
        "van",
        "truck"
    ],
    "wof:name":"Surplus Arm\u00e9e",
    "wof:placetype":"venue"
},
  "geometry": {"coordinates":[5.5615339279,50.6971244812],"type":"Point"}
}