{
  "type": "Feature",
  "properties": {
    "addr:full":"Wervikstraat 12 Zonnebeke (beselare) West-Vlaanderen 8980",
    "addr:housenumber":"12",
    "addr:postcode":"8980",
    "addr:street":"Wervikstraat",
    "iso:country":"BE",
    "sg:address":"Wervikstraat 12",
    "sg:city":"Zonnebeke (beselare)",
    "sg:classifiers":[
        {
            "category":"Professional",
            "subcategory":"Testing Lab",
            "type":"Services"
        }
    ],
    "sg:phone":"+32 57 46 65 77",
    "sg:postcode":"8980",
    "sg:province":"West-Vlaanderen",
    "sg:tags":[
        "chemist"
    ],
    "wof:name":"Craeymeersch J",
    "wof:placetype":"venue"
},
  "geometry": {"coordinates":[3.0061700344,50.858795166],"type":"Point"}
}