{
  "type": "Feature",
  "properties": {
    "iso:country":"BE",
    "sg:address":"Theo Verellenlaan 44",
    "sg:city":"Wuustwezel",
    "sg:classifiers":[
        {
            "category":"Professional",
            "subcategory":"Accounting & Tax Preparation",
            "type":"Services"
        }
    ],
    "sg:phone":"+32 3 633 00 15",
    "sg:postcode":"2990",
    "sg:province":"Antwerpen",
    "sg:tags":[
        "accountant"
    ],
    "wof:name":"Poppelaars J",
    "wof:placetype":"venue"
},
  "geometry": {"coordinates":[4.5451021194,51.3563766479],"type":"Point"}
}