{
  "type": "Feature",
  "properties": {
    "iso:country":"BE",
    "sg:address":"Dolezlaan 109b2",
    "sg:city":"Ukkel/uccle",
    "sg:orig_category":"Diverse grafische activiteiten Reclamebureaus",
    "sg:phone":"+32 2 372 05 65",
    "sg:postcode":"1180",
    "sg:province":"Bruxelles-Capitale",
    "wof:name":"Fe. Defalco",
    "wof:placetype":"venue"
},
  "geometry": {"coordinates":[4.3592438698,50.7889595032],"type":"Point"}
}