{
  "type": "Feature",
  "properties": {
    "addr:full":"Belgi\u00eblei 15b Box 10 Antwerpen Antwerpen 2018",
    "addr:housenumber":"15b box 10",
    "addr:postcode":"2018",
    "addr:street":"Belgie\u0308Lei",
    "iso:country":"BE",
    "sg:address":"Belgi\u00eblei 15b Box 10",
    "sg:city":"Antwerpen",
    "sg:classifiers":[
        {
            "category":"Professional",
            "subcategory":"Lawyer & Legal Services",
            "type":"Services"
        }
    ],
    "sg:phone":"+32 3 218 72 40",
    "sg:postcode":"2018",
    "sg:province":"Antwerpen",
    "wof:name":"Belderbosch Roger",
    "wof:placetype":"venue"
},
  "geometry": {"coordinates":[4.4223279953,51.2084388733],"type":"Point"}
}