{
  "type": "Feature",
  "properties": {
    "addr:full":"Groenstraat 31 Mechelen Antwerpen 2800",
    "addr:housenumber":"31",
    "addr:postcode":"2800",
    "addr:street":"Groenstraat",
    "iso:country":"BE",
    "sg:address":"Groenstraat 31",
    "sg:city":"Mechelen",
    "sg:classifiers":[
        {
            "category":"Arts & Performance",
            "subcategory":"Theater",
            "type":"Entertainment"
        }
    ],
    "sg:phone":"+32 15 41 53 86",
    "sg:postcode":"2800",
    "sg:province":"Antwerpen",
    "sg:tags":[
        "group",
        "theatre"
    ],
    "wof:name":"Provinciaal Toneelverbond Antwerpen",
    "wof:placetype":"venue"
},
  "geometry": {"coordinates":[4.4769120216,51.0221176147],"type":"Point"}
}