{
  "type": "Feature",
  "properties": {
    "iso:country":"BE",
    "sg:address":"Jozef Vervaenestraat 58",
    "sg:city":"Gent",
    "sg:orig_category":"Binnenhuisarchitecten",
    "sg:phone":"+32 9 232 28 26",
    "sg:postcode":"9050",
    "sg:province":"Oost-Vlaanderen",
    "wof:name":"Tom Wellekens",
    "wof:placetype":"venue"
},
  "geometry": {"coordinates":[3.7451760769,51.0322113037],"type":"Point"}
}