{
  "type": "Feature",
  "properties": {
    "iso:country":"BE",
    "sg:address":"Rue D'en Haut 25",
    "sg:city":"Beaumont",
    "sg:classifiers":[
        {
            "category":"Bakery",
            "type":"Food & Drink"
        }
    ],
    "sg:phone":"+32 71 58 82 95",
    "sg:postcode":"6500",
    "sg:province":"Hainaut",
    "sg:tags":[
        "confectioner",
        "baker"
    ],
    "wof:name":"Hardy M",
    "wof:placetype":"venue"
},
  "geometry": {"coordinates":[4.2594871521,50.191444397],"type":"Point"}
}