{
  "type": "Feature",
  "properties": {
    "addr:full":"Casselstraat 34 Poperinge West-Vlaanderen 8970",
    "addr:housenumber":"34",
    "addr:postcode":"8970",
    "addr:street":"Casselstraat",
    "iso:country":"BE",
    "sg:address":"Casselstraat 34",
    "sg:city":"Poperinge",
    "sg:classifiers":[
        {
            "category":"Personal",
            "subcategory":"Beauty Salon",
            "type":"Services"
        }
    ],
    "sg:phone":"+32 57 33 98 43",
    "sg:postcode":"8970",
    "sg:province":"West-Vlaanderen",
    "wof:name":"Esthetiek Pedra",
    "wof:placetype":"venue"
},
  "geometry": {"coordinates":[2.7221961021,50.8538131714],"type":"Point"}
}