{
  "type": "Feature",
  "properties": {
    "addr:full":"Avenue De L'hippodrome 154b1 Elsene/ixelles Bruxelles-Capitale 1050",
    "addr:housenumber":"154b1",
    "addr:postcode":"1050",
    "addr:street":"Avenue De L'Hippodrome",
    "iso:country":"BE",
    "sg:address":"Avenue De L'hippodrome 154b1",
    "sg:city":"Elsene/ixelles",
    "sg:classifiers":[
        {
            "category":"Personal",
            "subcategory":"Beauty Salon",
            "type":"Services"
        }
    ],
    "sg:phone":"+32 2 648 05 70",
    "sg:postcode":"1050",
    "sg:province":"Bruxelles-Capitale",
    "sg:tags":[
        "de",
        "coiffure"
    ],
    "wof:name":"Sup'hair",
    "wof:placetype":"venue"
},
  "geometry": {"coordinates":[4.3758721352,50.8214912415],"type":"Point"}
}