{
  "type": "Feature",
  "properties": {
    "iso:country":"BE",
    "sg:address":"Rue Louis De Brouckere 30",
    "sg:city":"La Louviere",
    "sg:orig_category":"Experts-comptables",
    "sg:phone":"+32 64 21 42 57",
    "sg:postcode":"7100",
    "sg:province":"Hainaut",
    "wof:name":"Gilbert Vandeworde",
    "wof:placetype":"venue"
},
  "geometry": {"coordinates":[4.1900668144,50.4791488647],"type":"Point"}
}