{
  "type": "Feature",
  "properties": {
    "iso:country":"BE",
    "sg:address":"Festraetstraat 54",
    "sg:city":"Sint-truiden",
    "sg:classifiers":[
        {
            "category":"Taxi",
            "type":"Transportation"
        }
    ],
    "sg:phone":"+32 11 69 29 29",
    "sg:postcode":"3800",
    "sg:province":"Limburg",
    "sg:tags":[
        "sp\u00e9ciaux"
    ],
    "wof:name":"Service Taxi",
    "wof:placetype":"venue"
},
  "geometry": {"coordinates":[5.1941161156,50.8096504211],"type":"Point"}
}