{
  "type": "Feature",
  "properties": {
    "addr:full":"406 Mechelsesteenweg 1930 Zaventem 406",
    "addr:postcode":"1930;406",
    "addr:street":"Mechelsesteenweg",
    "iso:country":"BE",
    "sg:address":"406",
    "sg:city":"Mechelsesteenweg 1930 Zaventem",
    "sg:classifiers":[
        {
            "category":"Professional",
            "type":"Services"
        }
    ],
    "sg:phone":"+32 2 757 92 91",
    "sg:postcode":"406",
    "sg:tags":[
        "transport",
        "road"
    ],
    "wof:name":"Cpl Trans Bvba",
    "wof:placetype":"venue"
},
  "geometry": {"coordinates":[4.5093197823,50.887878418],"type":"Point"}
}