{
  "type": "Feature",
  "properties": {
    "addr:full":"Blaarmolenstraat 15 Tongeren Limburg 3700",
    "addr:housenumber":"15",
    "addr:postcode":"3700",
    "addr:street":"Blaarmolenstraat",
    "iso:country":"BE",
    "sg:address":"Blaarmolenstraat 15",
    "sg:city":"Tongeren",
    "sg:classifiers":[
        {
            "category":"Building & Trades",
            "subcategory":"Electrical",
            "type":"Services"
        }
    ],
    "sg:phone":"+32 12 23 70 24",
    "sg:postcode":"3700",
    "sg:province":"Limburg",
    "sg:tags":[
        "electric",
        "-",
        "housewiring",
        "contractor"
    ],
    "wof:name":"Borrelli",
    "wof:placetype":"venue"
},
  "geometry": {"coordinates":[5.4999442101,50.7814445496],"type":"Point"}
}