{
  "type": "Feature",
  "properties": {
    "addr:full":"Place Th\u00c9odore Foguenne 3 Chaudfontaine Li\u00e8ge 4051",
    "addr:housenumber":"3",
    "addr:postcode":"4051",
    "addr:street":"Place The\u0301Odore Foguenne",
    "iso:country":"BE",
    "sg:address":"Place Th\u00c9odore Foguenne 3",
    "sg:city":"Chaudfontaine",
    "sg:orig_category":"Banques and organismes de cr\u00e9dit",
    "sg:phone":"+32 4 365 71 11",
    "sg:postcode":"4051",
    "sg:province":"Li\u00e8ge",
    "wof:name":"Fortis",
    "wof:placetype":"venue"
},
  "geometry": {"coordinates":[5.6322689056,50.6009902954],"type":"Point"}
}