{
  "type": "Feature",
  "properties": {
    "iso:country":"BE",
    "sg:address":"Noordlaan 28",
    "sg:city":"Zwalm (munkzwalm)",
    "sg:classifiers":[
        {
            "category":"Building & Trades",
            "subcategory":"Construction",
            "type":"Services"
        }
    ],
    "sg:phone":"+32 55 49 63 94",
    "sg:postcode":"9630",
    "sg:province":"Oost-Vlaanderen",
    "sg:tags":[
        "carpenter"
    ],
    "wof:name":"Beeckman G",
    "wof:placetype":"venue"
},
  "geometry": {"coordinates":[3.734194994,50.8875923157],"type":"Point"}
}