{
  "type": "Feature",
  "properties": {
    "addr:full":"Oosterhoven 27 Herenthout Antwerpen 2270",
    "addr:housenumber":"27",
    "addr:postcode":"2270",
    "addr:street":"Oosterhoven",
    "iso:country":"BE",
    "sg:address":"Oosterhoven 27",
    "sg:city":"Herenthout",
    "sg:orig_category":"Eleveurs de bovins",
    "sg:phone":"+32 14 21 39 24",
    "sg:postcode":"2270",
    "sg:province":"Antwerpen",
    "wof:name":"Jozef Van Mol",
    "wof:placetype":"venue"
},
  "geometry": {"coordinates":[4.7967371941,51.1472816467],"type":"Point"}
}