{
  "type": "Feature",
  "properties": {
    "addr:full":"Chauss\u00c9e De Louvain 331 Namur Namur 5004",
    "addr:housenumber":"331",
    "addr:postcode":"5004",
    "addr:street":"Chausse\u0301E De Louvain",
    "iso:country":"BE",
    "sg:address":"Chauss\u00c9e De Louvain 331",
    "sg:city":"Namur",
    "sg:classifiers":[
        {
            "category":"Manufacturing",
            "subcategory":"Textiles",
            "type":"Manufacturing & Wholesale Goods"
        }
    ],
    "sg:phone":"+32 81 21 56 46",
    "sg:postcode":"5004",
    "sg:province":"Namur",
    "wof:name":"Phildar",
    "wof:placetype":"venue"
},
  "geometry": {"coordinates":[4.8781299591,50.4780273438],"type":"Point"}
}