{
  "type": "Feature",
  "properties": {
    "addr:full":"Sint-jacobsnieuwstraat 36 Gent Oost-Vlaanderen 9000",
    "addr:housenumber":"36",
    "addr:postcode":"9000",
    "addr:street":"Sint-Jacobsnieuwstraat;Oost-Vlaanderen",
    "iso:country":"BE",
    "sg:address":"Sint-jacobsnieuwstraat 36",
    "sg:city":"Gent",
    "sg:orig_category":"Muziekinstrumenten",
    "sg:phone":"+32 9 224 18 35",
    "sg:postcode":"9000",
    "sg:province":"Oost-Vlaanderen",
    "wof:name":"Fa. Deneys",
    "wof:placetype":"venue"
},
  "geometry": {"coordinates":[3.7294130325,51.0547943115],"type":"Point"}
}