{
  "type": "Feature",
  "properties": {
    "addr:full":"Fays De Jos\u00c9 7 Herve Li\u00e8ge 4651",
    "addr:housenumber":"7",
    "addr:postcode":"4651",
    "addr:street":"Jose\u0301",
    "iso:country":"BE",
    "sg:address":"Fays De Jos\u00c9 7",
    "sg:city":"Herve",
    "sg:orig_category":"Installation de menuiserie en bois and plastique",
    "sg:phone":"+32 87 67 81 93",
    "sg:postcode":"4651",
    "sg:province":"Li\u00e8ge",
    "wof:name":"Louis Defourny",
    "wof:placetype":"venue"
},
  "geometry": {"coordinates":[5.7721300125,50.6266784668],"type":"Point"}
}