{
  "type": "Feature",
  "properties": {
    "iso:country":"BE",
    "sg:address":"Guido Gezellelaan 58",
    "sg:city":"Mortsel",
    "sg:classifiers":[
        {
            "category":"Building & Trades",
            "subcategory":"Electrical",
            "type":"Services"
        }
    ],
    "sg:phone":"+32 3 449 28 49",
    "sg:postcode":"2640",
    "sg:province":"Antwerpen",
    "sg:tags":[
        "electric",
        "-",
        "housewiring",
        "contractor"
    ],
    "wof:name":"Eck Bvba",
    "wof:placetype":"venue"
},
  "geometry": {"coordinates":[4.4459199905,51.1743850708],"type":"Point"}
}