{
  "type": "Feature",
  "properties": {
    "iso:country":"BE",
    "sg:address":"Avenue Jean Xxlll 9",
    "sg:city":"Rixensart",
    "sg:orig_category":"Jeux and jouets",
    "sg:phone":"+32 2 652 15 65",
    "sg:postcode":"1330",
    "sg:province":"Brabant Wallon",
    "wof:name":"Ludiq-art",
    "wof:placetype":"venue"
},
  "geometry": {"coordinates":[4.5332751274,50.7153015137],"type":"Point"}
}