{
  "type": "Feature",
  "properties": {
    "addr:full":"Gerweplein 4a Waregem West-Vlaanderen 8791",
    "addr:housenumber":"4a",
    "addr:postcode":"8791",
    "addr:street":"Gerweplein",
    "iso:country":"BE",
    "sg:address":"Gerweplein 4a",
    "sg:city":"Waregem",
    "sg:orig_category":"Gestion de portefeuilles and fortunes, conseils en placements",
    "sg:phone":"+32 56 72 63 02",
    "sg:postcode":"8791",
    "sg:province":"West-Vlaanderen",
    "wof:name":"Laporte D",
    "wof:placetype":"venue"
},
  "geometry": {"coordinates":[3.3481969833,50.8774528503],"type":"Point"}
}