{
  "type": "Feature",
  "properties": {
    "addr:full":"Koersel-dorp 21b1 Beringen Limburg 3582",
    "addr:housenumber":"21b1",
    "addr:postcode":"3582",
    "addr:street":"Koersel-Dorp",
    "iso:country":"BE",
    "sg:address":"Koersel-dorp 21b1",
    "sg:city":"Beringen",
    "sg:orig_category":"Banken and kredietinstellingen",
    "sg:phone":"+32 11 42 40 24",
    "sg:postcode":"3582",
    "sg:province":"Limburg",
    "wof:name":"Bacob",
    "wof:placetype":"venue"
},
  "geometry": {"coordinates":[5.2708749771,51.0595359802],"type":"Point"}
}