{
  "type": "Feature",
  "properties": {
    "addr:full":"Rue Giletville 38 Profondeville (lesve) Namur 5170",
    "addr:housenumber":"38",
    "addr:postcode":"5170",
    "addr:street":"Rue Giletville",
    "iso:country":"BE",
    "sg:address":"Rue Giletville 38",
    "sg:city":"Profondeville (lesve)",
    "sg:classifiers":[
        {
            "category":"Autos & Motor Vehicles",
            "subcategory":"Automobile Sales",
            "type":"Retail Goods"
        }
    ],
    "sg:phone":"+32 81 43 49 65",
    "sg:postcode":"5170",
    "sg:province":"Namur",
    "sg:tags":[
        "delivery",
        "-",
        "used",
        "van",
        "truck"
    ],
    "wof:name":"Uni-trac Sa",
    "wof:placetype":"venue"
},
  "geometry": {"coordinates":[4.8674049377,50.3786392212],"type":"Point"}
}