{
  "type": "Feature",
  "properties": {
    "addr:full":"Rue De Tournai 20 Mouscron Hainaut 7700",
    "addr:housenumber":"20",
    "addr:postcode":"7700",
    "addr:street":"Rue De Tournai",
    "iso:country":"BE",
    "sg:address":"Rue De Tournai 20",
    "sg:city":"Mouscron",
    "sg:classifiers":[
        {
            "category":"Manufacturing",
            "subcategory":"Electronics",
            "type":"Manufacturing & Wholesale Goods"
        }
    ],
    "sg:phone":"+32 56 85 63 89",
    "sg:postcode":"7700",
    "sg:province":"Hainaut",
    "sg:tags":[
        "component",
        "-"
    ],
    "wof:name":"Mano Diffusion",
    "wof:placetype":"venue"
},
  "geometry": {"coordinates":[3.2165279388,50.7437286377],"type":"Point"}
}