{
  "type": "Feature",
  "properties": {
    "addr:full":"Rue Du Mayeur 1ba Somme-leuze Namur 5377",
    "addr:housenumber":"1ba",
    "addr:postcode":"5377",
    "addr:street":"Rue Du Mayeur",
    "iso:country":"BE",
    "sg:address":"Rue Du Mayeur 1ba",
    "sg:city":"Somme-leuze",
    "sg:orig_category":"Artsen and specialisten",
    "sg:phone":"+32 86 34 53 42",
    "sg:postcode":"5377",
    "sg:province":"Namur",
    "wof:name":"G. Lipcsei",
    "wof:placetype":"venue"
},
  "geometry": {"coordinates":[5.3698949814,50.3404350281],"type":"Point"}
}