{
  "type": "Feature",
  "properties": {
    "addr:full":"Dorpsplein 6 Wetteren Oost-Vlaanderen 9230",
    "addr:housenumber":"6",
    "addr:postcode":"9230",
    "addr:street":"Dorpsplein",
    "iso:country":"BE",
    "sg:address":"Dorpsplein 6",
    "sg:city":"Wetteren",
    "sg:orig_category":"Postkantoren Verzekeringsmakelaars and experts",
    "sg:phone":"+32 9 369 23 05",
    "sg:postcode":"9230",
    "sg:province":"Oost-Vlaanderen",
    "wof:name":"De Post",
    "wof:placetype":"venue"
},
  "geometry": {"coordinates":[3.8690021038,50.97215271],"type":"Point"}
}