{
  "type": "Feature",
  "properties": {
    "addr:full":"Rue De Roubaix 94 Tournai (templeuve) Hainaut 7520",
    "addr:housenumber":"94",
    "addr:postcode":"7520",
    "addr:street":"Rue De Roubaix",
    "iso:country":"BE",
    "sg:address":"Rue De Roubaix 94",
    "sg:city":"Tournai (templeuve)",
    "sg:classifiers":[
        {
            "category":"Education",
            "subcategory":"Library",
            "type":"Public Place"
        }
    ],
    "sg:phone":"+32 69 35 17 08",
    "sg:postcode":"7520",
    "sg:province":"Hainaut",
    "wof:name":"Bibliotheque Communale",
    "wof:placetype":"venue"
},
  "geometry": {"coordinates":[3.2724809647,50.6442985535],"type":"Point"}
}