{
  "type": "Feature",
  "properties": {
    "addr:full":"Brugse Steenweg 2 Brugge West-Vlaanderen 8000",
    "addr:housenumber":"2",
    "addr:postcode":"8000",
    "addr:street":"Brugse Steenweg",
    "iso:country":"BE",
    "sg:address":"Brugse Steenweg 2",
    "sg:city":"Brugge",
    "sg:orig_category":"Stations-service and carburants. Entretien and r\u00e9parations de voitures",
    "sg:phone":"+32 50 33 79 61",
    "sg:postcode":"8000",
    "sg:province":"West-Vlaanderen",
    "wof:name":"Garage Vlaminck",
    "wof:placetype":"venue"
},
  "geometry": {"coordinates":[3.2399930954,51.2297439575],"type":"Point"}
}