{
  "type": "Feature",
  "properties": {
    "addr:full":"Avenue Firmin Lecharlier 31 Jette/jette Bruxelles-Capitale 1090",
    "addr:housenumber":"31",
    "addr:postcode":"1090",
    "addr:street":"Avenue Firmin Lecharlier",
    "iso:country":"BE",
    "sg:address":"Avenue Firmin Lecharlier 31",
    "sg:city":"Jette/jette",
    "sg:orig_category":"Rev\u00eatements pour sols and murs. Peinture",
    "sg:phone":"+32 2 428 83 98",
    "sg:postcode":"1090",
    "sg:province":"Bruxelles-Capitale",
    "wof:name":"Alain Watticant",
    "wof:placetype":"venue"
},
  "geometry": {"coordinates":[4.329182148,50.8717842102],"type":"Point"}
}