{
  "type": "Feature",
  "properties": {
    "addr:full":"Rue De R\u00e8ves 9 Genappe (houtain-le-val) Brabant Wallon 1476",
    "addr:housenumber":"9",
    "addr:postcode":"1476",
    "addr:street":"Rue De Re\u0300Ves;Wallon",
    "iso:country":"BE",
    "sg:address":"Rue De R\u00e8ves 9",
    "sg:city":"Genappe (houtain-le-val)",
    "sg:classifiers":[
        {
            "category":"Building & Trades",
            "subcategory":"Landscaping Services",
            "type":"Services"
        }
    ],
    "sg:phone":"+32 67 78 03 32",
    "sg:postcode":"1476",
    "sg:province":"Brabant Wallon",
    "sg:tags":[
        "-",
        "lopping",
        "work",
        "tree",
        "felling"
    ],
    "wof:name":"Demol E",
    "wof:placetype":"venue"
},
  "geometry": {"coordinates":[4.4156780243,50.5788841248],"type":"Point"}
}