{
  "type": "Feature",
  "properties": {
    "addr:full":"Nijverheidsstraat 34 Hemiksem Antwerpen 2620",
    "addr:housenumber":"34",
    "addr:postcode":"2620",
    "addr:street":"Nijverheidsstraat",
    "iso:country":"BE",
    "sg:address":"Nijverheidsstraat 34",
    "sg:city":"Hemiksem",
    "sg:classifiers":[
        {
            "category":"Professional",
            "subcategory":"Art Services",
            "type":"Services"
        }
    ],
    "sg:phone":"+32 3 887 90 41",
    "sg:postcode":"2620",
    "sg:province":"Antwerpen",
    "sg:tags":[
        "shop",
        "paint",
        "spraying"
    ],
    "wof:name":"Duracoat Nv/van Os",
    "wof:placetype":"venue"
},
  "geometry": {"coordinates":[4.3346910477,51.134475708],"type":"Point"}
}