{
  "type": "Feature",
  "properties": {
    "addr:full":"Torhoutsesteenweg 239 Brugge West-Vlaanderen 8300",
    "addr:housenumber":"239",
    "addr:postcode":"8300",
    "addr:street":"Torhoutsesteenweg",
    "iso:country":"BE",
    "sg:address":"Torhoutsesteenweg 239",
    "sg:city":"Brugge",
    "sg:orig_category":"Kantoormateriaal Gh",
    "sg:phone":"+32 50 38 76 10",
    "sg:postcode":"8300",
    "sg:province":"West-Vlaanderen",
    "wof:name":"Luteijn Johan",
    "wof:placetype":"venue"
},
  "geometry": {"coordinates":[3.287694931,51.3467254639],"type":"Point"}
}