{
  "type": "Feature",
  "properties": {
    "addr:full":"Chaussee De Waterloo 474 Bruxelles Bruxelles-Capitale 1050",
    "addr:housenumber":"474",
    "addr:postcode":"1050",
    "addr:street":"Chaussee De Waterloo",
    "iso:country":"BE",
    "sg:address":"Chaussee De Waterloo 474",
    "sg:city":"Bruxelles",
    "sg:classifiers":[
        {
            "category":"Real Estate",
            "subcategory":"Real Estate Services",
            "type":"Services"
        }
    ],
    "sg:phone":"+32 2 538 41 62",
    "sg:postcode":"1050",
    "sg:province":"Bruxelles-Capitale",
    "sg:tags":[
        "moving"
    ],
    "wof:name":"Ets Vermeulen S.p.r.l.",
    "wof:placetype":"venue"
},
  "geometry": {"coordinates":[4.3578310013,50.821056366],"type":"Point"}
}