{
  "type": "Feature",
  "properties": {
    "iso:country":"BE",
    "sg:address":"Oostergemstraat 7a",
    "sg:city":"Nevele (merendree)",
    "sg:classifiers":[
        {
            "category":"Shopping",
            "subcategory":"Antiques",
            "type":"Retail Goods"
        }
    ],
    "sg:phone":"+32 9 371 82 21",
    "sg:postcode":"9850",
    "sg:province":"Oost-Vlaanderen",
    "sg:tags":[
        "restoration"
    ],
    "wof:name":"Antiek Lambrecht",
    "wof:placetype":"venue"
},
  "geometry": {"coordinates":[3.5894930363,51.0863265991],"type":"Point"}
}