{
  "type": "Feature",
  "properties": {
    "iso:country":"BE",
    "sg:address":"Beukenhofstraat 109",
    "sg:city":"Vichte",
    "sg:classifiers":[
        {
            "category":"Shopping",
            "subcategory":"Crafts & Fabrics",
            "type":"Retail Goods"
        }
    ],
    "sg:phone":"+32 56 77 77 96",
    "sg:postcode":"8570",
    "sg:province":"West-Vlaanderen",
    "sg:tags":[
        "textile",
        "clothing"
    ],
    "wof:name":"Nimotex Bvba",
    "wof:placetype":"venue"
},
  "geometry": {"coordinates":[3.3867549896,50.8308639526],"type":"Point"}
}