{
  "type": "Feature",
  "properties": {
    "iso:country":"BE",
    "sg:address":"Gentsesteenweg 60",
    "sg:city":"Dendermonde",
    "sg:classifiers":[
        {
            "category":"Building & Trades",
            "subcategory":"Pest Control",
            "type":"Services"
        }
    ],
    "sg:phone":"+32 52 20 01 02",
    "sg:postcode":"9200",
    "sg:province":"Oost-Vlaanderen",
    "sg:tags":[
        "painting",
        "contractor"
    ],
    "wof:name":"Leybaert D",
    "wof:placetype":"venue"
},
  "geometry": {"coordinates":[4.0878567696,51.032119751],"type":"Point"}
}