{
  "type": "Feature",
  "properties": {
    "iso:country":"BE",
    "sg:address":"Schaapsdries 1",
    "sg:city":"Genk",
    "sg:orig_category":"M\u00e9decins and sp\u00e9cialistes",
    "sg:phone":"+32 89 35 91 42",
    "sg:postcode":"3600",
    "sg:province":"Limburg",
    "wof:name":"Jacques Van Mechelen",
    "wof:placetype":"venue"
},
  "geometry": {"coordinates":[5.5163831711,50.9665565491],"type":"Point"}
}