{
  "type": "Feature",
  "properties": {
    "iso:country":"BE",
    "sg:address":"Kapellendries 39",
    "sg:city":"Melle",
    "sg:classifiers":[
        {
            "category":"Professional",
            "subcategory":"Accounting & Tax Preparation",
            "type":"Services"
        }
    ],
    "sg:phone":"+32 9 252 29 78",
    "sg:postcode":"9090",
    "sg:province":"Oost-Vlaanderen",
    "sg:tags":[
        "accountant"
    ],
    "wof:name":"Van Vlaenderen",
    "wof:placetype":"venue"
},
  "geometry": {"coordinates":[3.7920529842,50.9821014404],"type":"Point"}
}