{
  "type": "Feature",
  "properties": {
    "iso:country":"BE",
    "sg:address":"Cetturu 15",
    "sg:city":"Houffalize",
    "sg:orig_category":"Installation de menuiserie en bois and plastique",
    "sg:phone":"+32 61 28 90 79",
    "sg:postcode":"6662",
    "sg:province":"Luxembourg",
    "wof:name":"Bernard Perree",
    "wof:placetype":"venue"
},
  "geometry": {"coordinates":[5.8459839821,50.1291732788],"type":"Point"}
}