{
  "type": "Feature",
  "properties": {
    "iso:country":"BE",
    "sg:address":"Havenstraat 17",
    "sg:city":"Oostende",
    "sg:orig_category":"Traitements param\u00e9dicaux",
    "sg:phone":"+32 59 32 32 63",
    "sg:postcode":"8400",
    "sg:province":"West-Vlaanderen",
    "wof:name":"Carine Delanghe",
    "wof:placetype":"venue"
},
  "geometry": {"coordinates":[2.9126999378,51.2312583923],"type":"Point"}
}