{
  "type": "Feature",
  "properties": {
    "iso:country":"BE",
    "sg:address":"Uitvangstraat 44",
    "sg:city":"Gent (wondelgem)",
    "sg:classifiers":[
        {
            "category":"Building & Trades",
            "subcategory":"Electrical",
            "type":"Services"
        }
    ],
    "sg:phone":"+32 9 253 14 24",
    "sg:postcode":"9032",
    "sg:province":"Oost-Vlaanderen",
    "sg:tags":[
        "electric",
        "-",
        "housewiring",
        "contractor"
    ],
    "wof:name":"De Lentdecker J",
    "wof:placetype":"venue"
},
  "geometry": {"coordinates":[3.7162549496,51.0900535583],"type":"Point"}
}