{
  "type": "Feature",
  "properties": {
    "iso:country":"BE",
    "sg:address":"Rue De La Gare 53",
    "sg:city":"Couvin",
    "sg:classifiers":[
        {
            "category":"Fast Food",
            "type":"Food & Drink"
        }
    ],
    "sg:phone":"+32 60 34 66 32",
    "sg:postcode":"5660",
    "sg:province":"Namur",
    "sg:tags":[
        "meeneem",
        "restaurant"
    ],
    "wof:name":"Le Jardin De Jade",
    "wof:placetype":"venue"
},
  "geometry": {"coordinates":[4.4922919273,50.0551834106],"type":"Point"}
}