{
  "type": "Feature",
  "properties": {
    "addr:full":"Z.i. De Martinrou Rue De Rabiseau 6 Fleurus Hainaut 6220",
    "addr:housenumber":"6",
    "addr:postcode":"6220",
    "addr:street":"Z.I.;Rue De Rabiseau",
    "iso:country":"BE",
    "sg:address":"Z.i. De Martinrou Rue De Rabiseau 6",
    "sg:city":"Fleurus",
    "sg:classifiers":[
        {
            "category":"Shopping",
            "subcategory":"Computers & Home Electronics",
            "type":"Retail Goods"
        }
    ],
    "sg:phone":"+32 71 37 27 97",
    "sg:postcode":"6220",
    "sg:province":"Hainaut",
    "sg:tags":[
        "printer",
        "jet",
        "cartridge",
        "ink"
    ],
    "wof:name":"Giga Services S.a.",
    "wof:placetype":"venue"
},
  "geometry": {"coordinates":[4.5496749878,50.4825363159],"type":"Point"}
}