{
  "type": "Feature",
  "properties": {
    "iso:country":"BE",
    "sg:address":"Rue 11 Novembre 95",
    "sg:city":"Trazegnies",
    "sg:orig_category":"Bloemen and planten",
    "sg:phone":"+32 71 45 23 31",
    "sg:postcode":"6183",
    "sg:province":"Hainaut",
    "wof:name":"Fleurs Dejean",
    "wof:placetype":"venue"
},
  "geometry": {"coordinates":[4.331580162,50.4675788879],"type":"Point"}
}