{
  "type": "Feature",
  "properties": {
    "iso:country":"BE",
    "sg:address":"Zelebaan 81",
    "sg:city":"Lokeren",
    "sg:classifiers":[
        {
            "category":"Bars & Pubs",
            "type":"Food & Drink"
        }
    ],
    "sg:phone":"+32 9 348 15 07",
    "sg:postcode":"9160",
    "sg:province":"Oost-Vlaanderen",
    "wof:name":"Koekoek (de)",
    "wof:placetype":"venue"
},
  "geometry": {"coordinates":[4.0166621208,51.091594696],"type":"Point"}
}