{
  "type": "Feature",
  "properties": {
    "addr:full":"Kielenstraat 15 Tongeren Limburg 3700",
    "addr:housenumber":"15",
    "addr:postcode":"3700",
    "addr:street":"Kielenstraat",
    "iso:country":"BE",
    "sg:address":"Kielenstraat 15",
    "sg:city":"Tongeren",
    "sg:classifiers":[
        {
            "category":"Cafe",
            "type":"Food & Drink"
        }
    ],
    "sg:phone":"+32 12 39 41 57",
    "sg:postcode":"3700",
    "sg:province":"Limburg",
    "sg:tags":[
        "caf\u00e9s"
    ],
    "wof:name":"Panoramacaf\u00c9",
    "wof:placetype":"venue"
},
  "geometry": {"coordinates":[5.4658031464,50.7818145752],"type":"Point"}
}