{
  "type": "Feature",
  "properties": {
    "iso:country":"BE",
    "sg:address":"Grote Markt 17",
    "sg:city":"Wevelgem",
    "sg:orig_category":"Boucheries",
    "sg:phone":"+32 56 41 10 58",
    "sg:postcode":"8560",
    "sg:province":"West-Vlaanderen",
    "wof:name":"Bertrand Bruneel",
    "wof:placetype":"venue"
},
  "geometry": {"coordinates":[3.1706950665,50.8099708557],"type":"Point"}
}