{
  "type": "Feature",
  "properties": {
    "addr:full":"Beatrijslaan 6 Antwerpen Antwerpen 2050",
    "addr:housenumber":"6",
    "addr:postcode":"2050",
    "addr:street":"Beatrijslaan",
    "iso:country":"BE",
    "sg:address":"Beatrijslaan 6",
    "sg:city":"Antwerpen",
    "sg:classifiers":[
        {
            "category":"Retail",
            "subcategory":"Veterinary Services",
            "type":"Services"
        }
    ],
    "sg:phone":"+32 3 219 68 41",
    "sg:postcode":"2050",
    "sg:province":"Antwerpen",
    "sg:tags":[
        "veterinarian"
    ],
    "wof:name":"Janssens-van Hoye-boel Dierenartsenpraktijk",
    "wof:placetype":"venue"
},
  "geometry": {"coordinates":[4.3865151405,51.2198982239],"type":"Point"}
}