{
  "type": "Feature",
  "properties": {
    "addr:full":"Molendreef 49 Sint-niklaas Oost-Vlaanderen 9111",
    "addr:housenumber":"49",
    "addr:postcode":"9111",
    "addr:street":"Molendreef",
    "iso:country":"BE",
    "sg:address":"Molendreef 49",
    "sg:city":"Sint-niklaas",
    "sg:orig_category":"Kapsalons",
    "sg:phone":"+32 3 772 41 44",
    "sg:postcode":"9111",
    "sg:province":"Oost-Vlaanderen",
    "wof:name":"Coiffure Eric",
    "wof:placetype":"venue"
},
  "geometry": {"coordinates":[4.0928149223,51.1482696533],"type":"Point"}
}