{
  "type": "Feature",
  "properties": {
    "iso:country":"BE",
    "sg:address":"Rijweg 120",
    "sg:city":"Herent",
    "sg:orig_category":"M\u00e9decins and sp\u00e9cialistes",
    "sg:phone":"+32 16 22 18 09",
    "sg:postcode":"3020",
    "sg:province":"Vlaams-Brabant",
    "wof:name":"Frans Lafortune",
    "wof:placetype":"venue"
},
  "geometry": {"coordinates":[4.6717910767,50.8991470337],"type":"Point"}
}