{
  "type": "Feature",
  "properties": {
    "iso:country":"BE",
    "sg:address":"Maandagweg 43",
    "sg:city":"Kortrijk",
    "sg:classifiers":[
        {
            "category":"Personal",
            "subcategory":"Beauty Salon",
            "type":"Services"
        }
    ],
    "sg:phone":"+32 56 25 82 51",
    "sg:postcode":"8500",
    "sg:province":"West-Vlaanderen",
    "wof:name":"Esthetiek Femke",
    "wof:placetype":"venue"
},
  "geometry": {"coordinates":[3.2968599796,50.8100128174],"type":"Point"}
}