{
  "type": "Feature",
  "properties": {
    "iso:country":"BE",
    "sg:address":"250",
    "sg:city":"Grandroute 7530 Tournai",
    "sg:orig_category":"Miscellaneous Products",
    "sg:phone":"+32 69 54 64 22",
    "sg:postcode":"250",
    "wof:name":"Desablens-pottiez Et Enfants Sa",
    "wof:placetype":"venue"
},
  "geometry": {"coordinates":[3.5067670345,50.5959358215],"type":"Point"}
}