{
  "type": "Feature",
  "properties": {
    "iso:country":"BE",
    "sg:address":"Bernerstraat 1",
    "sg:city":"Lanaken",
    "sg:classifiers":[
        {
            "category":"Home & Garden",
            "subcategory":"Hardware",
            "type":"Retail Goods"
        }
    ],
    "sg:phone":"+32 89 71 91 91",
    "sg:postcode":"3620",
    "sg:province":"Limburg",
    "sg:tags":[
        "fixing",
        "material"
    ],
    "wof:name":"Berner Belgien Nv",
    "wof:placetype":"venue"
},
  "geometry": {"coordinates":[5.6640100479,50.8875083923],"type":"Point"}
}