{
  "type": "Feature",
  "properties": {
    "iso:country":"BE",
    "sg:address":"Rijckelstraat 61",
    "sg:city":"Dendermonde",
    "sg:classifiers":[
        {
            "category":"Arena",
            "subcategory":"Sports Club",
            "type":"Entertainment"
        }
    ],
    "sg:phone":"+32 52 22 47 21",
    "sg:postcode":"9200",
    "sg:province":"Oost-Vlaanderen",
    "sg:tags":[
        "terrain",
        "hors",
        "de",
        "installation",
        "sportifs"
    ],
    "wof:name":"Sparta Appels",
    "wof:placetype":"venue"
},
  "geometry": {"coordinates":[4.0490050316,51.0309371948],"type":"Point"}
}