{
  "type": "Feature",
  "properties": {
    "iso:country":"BE",
    "sg:address":"Heirbaan 56",
    "sg:city":"Opwijk",
    "sg:classifiers":[
        {
            "category":"Farming",
            "subcategory":"Fish & Marine Products",
            "type":"Manufacturing & Wholesale Goods"
        }
    ],
    "sg:phone":"+32 52 35 86 21",
    "sg:postcode":"1745",
    "sg:province":"Vlaams-Brabant",
    "sg:tags":[
        "fast-food"
    ],
    "wof:name":"Matthys B.v.b.a.",
    "wof:placetype":"venue"
},
  "geometry": {"coordinates":[4.184720993,50.9723854065],"type":"Point"}
}