{
  "type": "Feature",
  "properties": {
    "iso:country":"BE",
    "sg:address":"Rue Surlet 45",
    "sg:city":"Liege",
    "sg:orig_category":"Immobili\u00ebnkantoren Vakantiehuizen",
    "sg:phone":"+32 4 342 22 24",
    "sg:postcode":"4020",
    "sg:province":"Li\u00e8ge",
    "wof:name":"Euro- R\u00c9sidences",
    "wof:placetype":"venue"
},
  "geometry": {"coordinates":[5.5820498466,50.6399078369],"type":"Point"}
}