{
  "type": "Feature",
  "properties": {
    "iso:country":"BE",
    "sg:address":"Chemin Du Ch\u00e2teau 4",
    "sg:city":"Kraainem",
    "sg:classifiers":[
        {
            "category":"Retail",
            "subcategory":"Event Space",
            "type":"Services"
        }
    ],
    "sg:phone":"+32 2 719 20 45",
    "sg:postcode":"1950",
    "sg:province":"Vlaams-Brabant",
    "sg:tags":[
        "rental",
        "-",
        "hall"
    ],
    "wof:name":"Ch\u00e2teau Jourdain",
    "wof:placetype":"venue"
},
  "geometry": {"coordinates":[4.4683198929,50.8620605469],"type":"Point"}
}