{
  "type": "Feature",
  "properties": {
    "addr:full":"Route Du Crois\u00c9 13 Bouillon Luxembourg 6831",
    "addr:housenumber":"13",
    "addr:postcode":"6831",
    "addr:street":"Route Du Croise\u0301",
    "iso:country":"BE",
    "sg:address":"Route Du Crois\u00c9 13",
    "sg:city":"Bouillon",
    "sg:classifiers":[
        {
            "category":"Autos & Motor Vehicles",
            "subcategory":"Fuel & Gas Station",
            "type":"Retail Goods"
        }
    ],
    "sg:phone":"+32 61 46 79 09",
    "sg:postcode":"6831",
    "sg:province":"Luxembourg",
    "sg:tags":[
        "stations-service",
        "carburants"
    ],
    "wof:name":"Station-services Perales",
    "wof:placetype":"venue"
},
  "geometry": {"coordinates":[5.0937948227,49.8202438354],"type":"Point"}
}