{
  "type": "Feature",
  "properties": {
    "iso:country":"BE",
    "sg:address":"Rue Albert Ier 102",
    "sg:city":"Tournai",
    "sg:orig_category":"Installatie van houten of kunststof schrijnwerk",
    "sg:phone":"+32 69 44 12 71",
    "sg:postcode":"7538",
    "sg:province":"Hainaut",
    "wof:name":"E. Hansart",
    "wof:placetype":"venue"
},
  "geometry": {"coordinates":[3.500494957,50.5717964172],"type":"Point"}
}