{
  "type": "Feature",
  "properties": {
    "addr:full":"Rue Du Brou 73 Verviers Li\u00e8ge 4800",
    "addr:housenumber":"73",
    "addr:postcode":"4800",
    "addr:street":"Rue Du Brou",
    "iso:country":"BE",
    "sg:address":"Rue Du Brou 73",
    "sg:city":"Verviers",
    "sg:classifiers":[
        {
            "category":"Shopping",
            "subcategory":"Gifts & Souvenirs",
            "type":"Retail Goods"
        }
    ],
    "sg:phone":"+32 87 34 01 17",
    "sg:postcode":"4800",
    "sg:province":"Li\u00e8ge",
    "sg:tags":[
        "-"
    ],
    "wof:name":"Monsieur Couplet",
    "wof:placetype":"venue"
},
  "geometry": {"coordinates":[5.8577661514,50.5920333862],"type":"Point"}
}