{
  "type": "Feature",
  "properties": {
    "iso:country":"BE",
    "sg:address":"Rue Du Lion 2",
    "sg:city":"Frasnes",
    "sg:orig_category":"Miscellaneous Products",
    "sg:phone":"+32 60 31 15 79",
    "sg:postcode":"5660",
    "sg:province":"Namur",
    "wof:name":"Usines Sarcolux & Dubuc Sprl",
    "wof:placetype":"venue"
},
  "geometry": {"coordinates":[4.5100030899,50.0724983215],"type":"Point"}
}