{
  "type": "Feature",
  "properties": {
    "iso:country":"BE",
    "sg:address":"Broekstraat 8",
    "sg:city":"Rotselaar",
    "sg:orig_category":"HUISBRANDOLIE",
    "sg:phone":"+32 16 44 61 18",
    "sg:postcode":"3110",
    "sg:province":"Vlaams-Brabant",
    "wof:name":"Vander Elst",
    "wof:placetype":"venue"
},
  "geometry": {"coordinates":[4.7097702026,50.9630012512],"type":"Point"}
}