{
  "type": "Feature",
  "properties": {
    "iso:country":"BE",
    "sg:address":"Rue Du Pont Du Val",
    "sg:city":"Seraing",
    "sg:classifiers":[
        {
            "category":"Harbor",
            "type":"Transportation"
        }
    ],
    "sg:phone":"+32 4 330 17 13",
    "sg:postcode":"4100",
    "sg:province":"Li\u00e8ge",
    "sg:tags":[
        "port",
        "facility"
    ],
    "wof:name":"Ctb Logistics",
    "wof:placetype":"venue"
},
  "geometry": {"coordinates":[5.4814939499,50.5961074829],"type":"Point"}
}