{
  "type": "Feature",
  "properties": {
    "addr:full":"Terfakkerstraat 1bb Bilzen Limburg 3740",
    "addr:postcode":"3740",
    "addr:street":"Terfakkerstraat",
    "iso:country":"BE",
    "sg:address":"Terfakkerstraat 1bb",
    "sg:city":"Bilzen",
    "sg:orig_category":"Producteurs de fruits",
    "sg:phone":"+32 89 41 70 89",
    "sg:postcode":"3740",
    "sg:province":"Limburg",
    "wof:name":"Valentin Roosen",
    "wof:placetype":"venue"
},
  "geometry": {"coordinates":[5.4977807999,50.8658828735],"type":"Point"}
}