{
  "type": "Feature",
  "properties": {
    "iso:country":"BE",
    "sg:address":"Elektriciteitstraat 0",
    "sg:city":"Mechelen",
    "sg:orig_category":"V\u00eatements pour Hommes. V\u00eatements pour b\u00e9b\u00e9s and enfants. V\u00eatements pour Dames",
    "sg:phone":"+32 15 21 17 61",
    "sg:postcode":"2800",
    "sg:province":"Antwerpen",
    "wof:name":"E5 Mode",
    "wof:placetype":"venue"
},
  "geometry": {"coordinates":[4.4694061279,51.0367431641],"type":"Point"}
}