{
  "type": "Feature",
  "properties": {
    "addr:full":"Baljuwstraat 46 Poperinge (reningelst) West-Vlaanderen 8970",
    "addr:housenumber":"46",
    "addr:postcode":"8970",
    "addr:street":"Baljuwstraat",
    "iso:country":"BE",
    "sg:address":"Baljuwstraat 46",
    "sg:city":"Poperinge (reningelst)",
    "sg:classifiers":[
        {
            "category":"Health Services",
            "subcategory":"Health Practitioner",
            "type":"Services"
        }
    ],
    "sg:phone":"+32 57 33 65 90",
    "sg:postcode":"8970",
    "sg:province":"West-Vlaanderen",
    "sg:tags":[
        "physiotherapist"
    ],
    "wof:name":"Fiey Lucrece",
    "wof:placetype":"venue"
},
  "geometry": {"coordinates":[2.7580869198,50.8198738098],"type":"Point"}
}