{
  "type": "Feature",
  "properties": {
    "iso:country":"BE",
    "sg:address":"Hoogveldweg 95",
    "sg:city":"Lier",
    "sg:classifiers":[
        {
            "category":"Home & Garden",
            "subcategory":"Furniture",
            "type":"Retail Goods"
        }
    ],
    "sg:phone":"+32 3 491 06 90",
    "sg:postcode":"2500",
    "sg:province":"Antwerpen",
    "sg:tags":[
        "household",
        "wood"
    ],
    "wof:name":"Gova Meubelen Bvba",
    "wof:placetype":"venue"
},
  "geometry": {"coordinates":[4.5791888237,51.1247291565],"type":"Point"}
}