{
  "type": "Feature",
  "properties": {
    "iso:country":"BE",
    "sg:address":"Kapelleriestraat 5",
    "sg:city":"Staden",
    "sg:classifiers":[
        {
            "category":"Personal",
            "subcategory":"Beauty Salon",
            "type":"Services"
        }
    ],
    "sg:phone":"+32 51 70 30 19",
    "sg:postcode":"8840",
    "sg:province":"West-Vlaanderen",
    "wof:name":"Nancy Instituut",
    "wof:placetype":"venue"
},
  "geometry": {"coordinates":[3.0125820637,50.9744224548],"type":"Point"}
}