{
  "type": "Feature",
  "properties": {
    "addr:full":"Moeskroenstraat 8 Menen West-Vlaanderen 8930",
    "addr:housenumber":"8",
    "addr:postcode":"8930",
    "addr:street":"Moeskroenstraat",
    "iso:country":"BE",
    "sg:address":"Moeskroenstraat 8",
    "sg:city":"Menen",
    "sg:classifiers":[
        {
            "category":"Fast Food",
            "type":"Food & Drink"
        }
    ],
    "sg:phone":"+32 56 51 75 29",
    "sg:postcode":"8930",
    "sg:province":"West-Vlaanderen",
    "sg:tags":[
        "fried",
        "stand",
        "potato"
    ],
    "wof:name":"Temperman L",
    "wof:placetype":"venue"
},
  "geometry": {"coordinates":[3.1277580261,50.7877159119],"type":"Point"}
}