{
  "type": "Feature",
  "properties": {
    "addr:full":"Markt 5 Waregem West-Vlaanderen 8790",
    "addr:housenumber":"5",
    "addr:postcode":"8790",
    "addr:street":"Markt",
    "iso:country":"BE",
    "sg:address":"Markt 5",
    "sg:city":"Waregem",
    "sg:classifiers":[
        {
            "category":"Shopping",
            "subcategory":"Beauty & Cosmetics",
            "type":"Retail Goods"
        }
    ],
    "sg:phone":"+32 56 60 44 13",
    "sg:postcode":"8790",
    "sg:province":"West-Vlaanderen",
    "sg:tags":[
        "-",
        "perfumery"
    ],
    "wof:name":"Clo\u00eb",
    "wof:placetype":"venue"
},
  "geometry": {"coordinates":[3.4323658943,50.8865318298],"type":"Point"}
}