{
  "type": "Feature",
  "properties": {
    "iso:country":"BE",
    "sg:address":"Chauss\u00e9e De Tournai 17-19",
    "sg:city":"Tournai (ramegnies-chin)",
    "sg:classifiers":[
        {
            "category":"Food & Beverages",
            "subcategory":"Supermarket",
            "type":"Retail Goods"
        }
    ],
    "sg:phone":"+32 69 23 47 17",
    "sg:postcode":"7520",
    "sg:province":"Hainaut",
    "sg:tags":[
        "department",
        "store"
    ],
    "wof:name":"Euro Shop",
    "wof:placetype":"venue"
},
  "geometry": {"coordinates":[3.3557810783,50.6329574585],"type":"Point"}
}