{
  "type": "Feature",
  "properties": {
    "iso:country":"BE",
    "sg:address":"Engelsenlaan 10",
    "sg:city":"Ronse/renaix",
    "sg:orig_category":"Diverse bouwafwerking and reiniging Hout and afgeleiden Gh IJzerwaren, bouw- and verfmaterialen",
    "sg:phone":"+32 55 21 29 30",
    "sg:postcode":"9600",
    "sg:province":"Oost-Vlaanderen",
    "wof:name":"Delouvroy",
    "wof:placetype":"venue"
},
  "geometry": {"coordinates":[3.5908091068,50.745010376],"type":"Point"}
}