{
  "type": "Feature",
  "properties": {
    "iso:country":"BE",
    "sg:address":"Bevrijdingsplein 18",
    "sg:city":"Leopoldsburg",
    "sg:classifiers":[
        {
            "category":"Building & Trades",
            "subcategory":"Electrical",
            "type":"Services"
        }
    ],
    "sg:phone":"+32 11 34 56 34",
    "sg:postcode":"3970",
    "sg:province":"Limburg",
    "sg:tags":[
        "heating"
    ],
    "wof:name":"Aesr Koeltechniek",
    "wof:placetype":"venue"
},
  "geometry": {"coordinates":[5.263572216,51.1177978516],"type":"Point"}
}