{
  "type": "Feature",
  "properties": {
    "iso:country":"BE",
    "sg:address":"Smisstraat 5ba",
    "sg:city":"Hoeselt",
    "sg:orig_category":"Epiceries",
    "sg:phone":"+32 12 23 50 69",
    "sg:postcode":"3730",
    "sg:province":"Limburg",
    "wof:name":"Anna Liesens",
    "wof:placetype":"venue"
},
  "geometry": {"coordinates":[5.4896931648,50.8278770447],"type":"Point"}
}