{
  "type": "Feature",
  "properties": {
    "iso:country":"BE",
    "sg:address":"Werkenplein 11",
    "sg:city":"Kortemark (werken)",
    "sg:orig_category":"Leisure articles",
    "sg:phone":"+32 51 57 13 04",
    "sg:postcode":"8610",
    "sg:province":"West-Vlaanderen",
    "wof:name":"Terryn J",
    "wof:placetype":"venue"
},
  "geometry": {"coordinates":[3.0008249283,51.0262260437],"type":"Point"}
}