{
  "type": "Feature",
  "properties": {
    "addr:full":"Rue Saint-medard 10 Erquelinnes Hainaut 6560",
    "addr:housenumber":"10",
    "addr:postcode":"6560",
    "addr:street":"Rue Saint-Medard",
    "iso:country":"BE",
    "sg:address":"Rue Saint-medard 10",
    "sg:city":"Erquelinnes",
    "sg:orig_category":"Plaatsen van vloer- and muurbekleding Schilders",
    "sg:phone":"+32 71 55 81 25",
    "sg:postcode":"6560",
    "sg:province":"Hainaut",
    "wof:name":"Romuald Wauthelet",
    "wof:placetype":"venue"
},
  "geometry": {"coordinates":[4.1517648697,50.3090171814],"type":"Point"}
}