{
  "type": "Feature",
  "properties": {
    "iso:country":"BE",
    "sg:address":"Poti\u00c9rue 27",
    "sg:city":"Herve",
    "sg:orig_category":"Animations diverses",
    "sg:phone":"+32 87 66 20 22",
    "sg:postcode":"4650",
    "sg:province":"Li\u00e8ge",
    "wof:name":"Musicalement V\u00d4tre",
    "wof:placetype":"venue"
},
  "geometry": {"coordinates":[5.7941389084,50.6400985718],"type":"Point"}
}