{
  "type": "Feature",
  "properties": {
    "addr:full":"Rue Des Canadiens 151 La Louvi\u00e8re (str\u00e9py-bracquegnies) Hainaut 7110",
    "addr:housenumber":"151",
    "addr:postcode":"7110",
    "addr:street":"Rue Des Canadiens",
    "iso:country":"BE",
    "sg:address":"Rue Des Canadiens 151",
    "sg:city":"La Louvi\u00e8re (str\u00e9py-bracquegnies)",
    "sg:classifiers":[
        {
            "category":"Building & Trades",
            "subcategory":"Landscaping Services",
            "type":"Services"
        }
    ],
    "sg:phone":"+32 64 66 27 76",
    "sg:postcode":"7110",
    "sg:province":"Hainaut",
    "sg:tags":[
        "handicraft"
    ],
    "wof:name":"Delaunois M-f",
    "wof:placetype":"venue"
},
  "geometry": {"coordinates":[4.1505050659,50.4826698303],"type":"Point"}
}