{
  "type": "Feature",
  "properties": {
    "iso:country":"BE",
    "sg:address":"Visserskaai 29",
    "sg:city":"Kortrijk",
    "sg:classifiers":[
        {
            "category":"Building & Trades",
            "subcategory":"Construction",
            "type":"Services"
        }
    ],
    "sg:phone":"+32 56 24 96 09",
    "sg:postcode":"8500",
    "sg:province":"West-Vlaanderen",
    "sg:tags":[
        "roofing",
        "material",
        "-"
    ],
    "wof:name":"Littoral",
    "wof:placetype":"venue"
},
  "geometry": {"coordinates":[3.2859890461,50.8307723999],"type":"Point"}
}