{
  "type": "Feature",
  "properties": {
    "iso:country":"BE",
    "sg:address":"Henry Fordlaan 8",
    "sg:city":"Genk",
    "sg:orig_category":"Non-Classified Establishments",
    "sg:phone":"+32 89 41 74 97",
    "sg:postcode":"3600",
    "sg:province":"Limburg",
    "wof:name":"Henkel Aware Technologies",
    "wof:placetype":"venue"
},
  "geometry": {"coordinates":[5.5121808052,50.922794342],"type":"Point"}
}