{
  "type": "Feature",
  "properties": {
    "addr:full":"Burgemeester Potiaulaan 82 Dendermonde Oost-Vlaanderen 9200",
    "addr:housenumber":"82",
    "addr:postcode":"9200",
    "addr:street":"Burgemeester Potiaulaan;Oost-Vlaanderen",
    "iso:country":"BE",
    "sg:address":"Burgemeester Potiaulaan 82",
    "sg:city":"Dendermonde",
    "sg:orig_category":"Assurances. Bureaux de poste",
    "sg:phone":"+32 52 21 12 33",
    "sg:postcode":"9200",
    "sg:province":"Oost-Vlaanderen",
    "wof:name":"De Post",
    "wof:placetype":"venue"
},
  "geometry": {"coordinates":[4.1138129234,51.0212783813],"type":"Point"}
}