{
  "type": "Feature",
  "properties": {
    "iso:country":"BE",
    "sg:address":"Rue De La Waide 57",
    "sg:city":"Blegny",
    "sg:orig_category":"Diverse bouwafwerking and reiniging",
    "sg:phone":"+32 4 387 49 49",
    "sg:postcode":"4670",
    "sg:province":"Li\u00e8ge",
    "wof:name":"Lenders J.",
    "wof:placetype":"venue"
},
  "geometry": {"coordinates":[5.724919796,50.6725769043],"type":"Point"}
}