{
  "type": "Feature",
  "properties": {
    "addr:full":"Diestersteenweg 367 Maaseik Limburg 3680",
    "addr:housenumber":"367",
    "addr:postcode":"3680",
    "addr:street":"Diestersteenweg",
    "iso:country":"BE",
    "sg:address":"Diestersteenweg 367",
    "sg:city":"Maaseik",
    "sg:orig_category":"Voertuigen",
    "sg:phone":"+32 89 56 60 29",
    "sg:postcode":"3680",
    "sg:province":"Limburg",
    "wof:name":"Garage Leunissen",
    "wof:placetype":"venue"
},
  "geometry": {"coordinates":[5.7485699654,51.1021728516],"type":"Point"}
}