{
  "type": "Feature",
  "properties": {
    "iso:country":"BE",
    "sg:address":"Rue De La Chapelle 19",
    "sg:city":"Saint-ghislain",
    "sg:orig_category":"Artsen and specialisten",
    "sg:phone":"+32 65 64 38 38",
    "sg:postcode":"7331",
    "sg:province":"Hainaut",
    "wof:name":"M.h. Leclercq",
    "wof:placetype":"venue"
},
  "geometry": {"coordinates":[3.8244540691,50.4747886658],"type":"Point"}
}