{
  "type": "Feature",
  "properties": {
    "addr:full":"Avenue Du Champs De Mars 17 Mons Hainaut 7000",
    "addr:housenumber":"17",
    "addr:postcode":"7000",
    "addr:street":"Avenue Du Champs De Mars;Hainaut",
    "iso:country":"BE",
    "sg:address":"Avenue Du Champs De Mars 17",
    "sg:city":"Mons",
    "sg:orig_category":"Hoger onderwijs",
    "sg:phone":"+32 65 37 36 01",
    "sg:postcode":"7000",
    "sg:province":"Hainaut",
    "wof:name":"H.e.c.f.h.",
    "wof:placetype":"venue"
},
  "geometry": {"coordinates":[3.9528849125,50.4628486633],"type":"Point"}
}