{
  "type": "Feature",
  "properties": {
    "addr:full":"Rue Du Moncia 9 Floreffe Namur 5150",
    "addr:housenumber":"9",
    "addr:postcode":"5150",
    "addr:street":"Rue Du Moncia",
    "iso:country":"BE",
    "sg:address":"Rue Du Moncia 9",
    "sg:city":"Floreffe",
    "sg:orig_category":"Jardinage",
    "sg:phone":"+32 81 45 01 16",
    "sg:postcode":"5150",
    "sg:province":"Namur",
    "wof:name":"Steenberghs Jardin",
    "wof:placetype":"venue"
},
  "geometry": {"coordinates":[4.7668027878,50.4522514343],"type":"Point"}
}