{
  "type": "Feature",
  "properties": {
    "iso:country":"BE",
    "sg:address":"Mechelsestraat 75",
    "sg:city":"Lier",
    "sg:orig_category":"M\u00e9decins and sp\u00e9cialistes",
    "sg:phone":"+32 3 480 84 42",
    "sg:postcode":"2500",
    "sg:province":"Antwerpen",
    "wof:name":"N. Vanmaele",
    "wof:placetype":"venue"
},
  "geometry": {"coordinates":[4.5658860207,51.1314277649],"type":"Point"}
}