{
  "type": "Feature",
  "properties": {
    "addr:full":"Rue De La Chevrette 10 Chiny Luxembourg 6811",
    "addr:housenumber":"10",
    "addr:postcode":"6811",
    "addr:street":"Rue De La Chevrette",
    "iso:country":"BE",
    "sg:address":"Rue De La Chevrette 10",
    "sg:city":"Chiny",
    "sg:orig_category":"Herstelling leer and schoeisel",
    "sg:phone":"+32 61 31 20 75",
    "sg:postcode":"6811",
    "sg:province":"Luxembourg",
    "wof:name":"Philippe Meurisse",
    "wof:placetype":"venue"
},
  "geometry": {"coordinates":[5.4229531288,49.7056274414],"type":"Point"}
}