{
  "type": "Feature",
  "properties": {
    "addr:full":"Plankstraat 1 Sint-truiden Limburg 3800",
    "addr:housenumber":"1",
    "addr:postcode":"3800",
    "addr:street":"Plankstraat",
    "iso:country":"BE",
    "sg:address":"Plankstraat 1",
    "sg:city":"Sint-truiden",
    "sg:orig_category":"Chaussures",
    "sg:phone":"+32 11 68 22 11",
    "sg:postcode":"3800",
    "sg:province":"Limburg",
    "wof:name":"Yvo Herbots",
    "wof:placetype":"venue"
},
  "geometry": {"coordinates":[5.1878671646,50.8159446716],"type":"Point"}
}