{
  "type": "Feature",
  "properties": {
    "addr:full":"Rue Des Boulevards 8 Erquelinnes (hantes-wih\u00e9ries) Hainaut 6560",
    "addr:housenumber":"8",
    "addr:postcode":"6560",
    "addr:street":"Rue Des Boulevards",
    "iso:country":"BE",
    "sg:address":"Rue Des Boulevards 8",
    "sg:city":"Erquelinnes (hantes-wih\u00e9ries)",
    "sg:classifiers":[
        {
            "category":"Professional",
            "subcategory":"Accounting & Tax Preparation",
            "type":"Services"
        }
    ],
    "sg:phone":"+32 71 55 33 70",
    "sg:postcode":"6560",
    "sg:province":"Hainaut",
    "sg:tags":[
        "bookkeeper"
    ],
    "wof:name":"Taminiaux F",
    "wof:placetype":"venue"
},
  "geometry": {"coordinates":[4.1776452065,50.3042831421],"type":"Point"}
}