{
  "type": "Feature",
  "properties": {
    "addr:full":"Boulevard Des Alli\u00e9s 317 Mouscron (luingne) Hainaut 7700",
    "addr:housenumber":"317",
    "addr:postcode":"7700",
    "addr:street":"Boulevard Des Allie\u0301S",
    "iso:country":"BE",
    "sg:address":"Boulevard Des Alli\u00e9s 317",
    "sg:city":"Mouscron (luingne)",
    "sg:classifiers":[
        {
            "category":"Military Area",
            "subcategory":"Air Force Base",
            "type":"Public Place"
        }
    ],
    "sg:phone":"+32 56 33 10 68",
    "sg:postcode":"7700",
    "sg:province":"Hainaut",
    "sg:tags":[
        "fire",
        "protection"
    ],
    "wof:name":"Renard P Ets",
    "wof:placetype":"venue"
},
  "geometry": {"coordinates":[3.2441940308,50.7421417236],"type":"Point"}
}