{
  "type": "Feature",
  "properties": {
    "addr:full":"Chauss\u00e9e Verte 92a Saint-georges-sur-meuse Li\u00e8ge 4470",
    "addr:housenumber":"92a",
    "addr:postcode":"4470",
    "addr:street":"Chausse\u0301E Verte",
    "iso:country":"BE",
    "sg:address":"Chauss\u00e9e Verte 92a",
    "sg:city":"Saint-georges-sur-meuse",
    "sg:classifiers":[
        {
            "category":"Building & Trades",
            "subcategory":"Pest Control",
            "type":"Services"
        }
    ],
    "sg:phone":"+32 4 259 46 26",
    "sg:postcode":"4470",
    "sg:province":"Li\u00e8ge",
    "sg:tags":[
        "painting",
        "contractor"
    ],
    "wof:name":"Bati's Sprl",
    "wof:placetype":"venue"
},
  "geometry": {"coordinates":[5.3463602066,50.6011962891],"type":"Point"}
}