{
  "type": "Feature",
  "properties": {
    "addr:full":"Hulsen 102 Balen Antwerpen 2490",
    "addr:housenumber":"102",
    "addr:postcode":"2490",
    "addr:street":"Hulsen",
    "iso:country":"BE",
    "sg:address":"Hulsen 102",
    "sg:city":"Balen",
    "sg:orig_category":"Brood, gebak and snoepgoed",
    "sg:phone":"+32 14 30 27 92",
    "sg:postcode":"2490",
    "sg:province":"Antwerpen",
    "wof:name":"Franky Peeters",
    "wof:placetype":"venue"
},
  "geometry": {"coordinates":[5.1155247688,51.1464538574],"type":"Point"}
}