{
  "type": "Feature",
  "properties": {
    "addr:full":"Stationsstraat 13 Affligem (essene) Vlaams-Brabant 1790",
    "addr:housenumber":"13",
    "addr:postcode":"1790",
    "addr:street":"Stationsstraat",
    "iso:country":"BE",
    "sg:address":"Stationsstraat 13",
    "sg:city":"Affligem (essene)",
    "sg:classifiers":[
        {
            "category":"Farming",
            "subcategory":"Livestock Farm",
            "type":"Manufacturing & Wholesale Goods"
        }
    ],
    "sg:phone":"+32 53 66 63 14",
    "sg:postcode":"1790",
    "sg:province":"Vlaams-Brabant",
    "sg:tags":[
        "buyer"
    ],
    "wof:name":"Sonck E",
    "wof:placetype":"venue"
},
  "geometry": {"coordinates":[4.1163649559,50.8877449036],"type":"Point"}
}