{
  "type": "Feature",
  "properties": {
    "addr:full":"Priester Daensstraat 8 Lommel Limburg 3920",
    "addr:housenumber":"8",
    "addr:postcode":"3920",
    "addr:street":"Priester Daensstraat",
    "iso:country":"BE",
    "sg:address":"Priester Daensstraat 8",
    "sg:city":"Lommel",
    "sg:classifiers":[
        {
            "category":"Banks & Credit Unions",
            "subcategory":"Investment Brokerage",
            "type":"Services"
        }
    ],
    "sg:phone":"+32 11 55 01 60",
    "sg:postcode":"3920",
    "sg:province":"Limburg",
    "sg:tags":[
        "printing",
        "-"
    ],
    "wof:name":"Drukkerij Elite Nv",
    "wof:placetype":"venue"
},
  "geometry": {"coordinates":[5.2701931,51.2178955078],"type":"Point"}
}