{
  "type": "Feature",
  "properties": {
    "addr:full":"Pastorijstraat 4 Hasselt Limburg 3500",
    "addr:housenumber":"4",
    "addr:postcode":"3500",
    "addr:street":"Pastorijstraat",
    "iso:country":"BE",
    "sg:address":"Pastorijstraat 4",
    "sg:city":"Hasselt",
    "sg:orig_category":"S\u00e9curit\u00e9 sociale",
    "sg:phone":"+32 11 31 16 20",
    "sg:postcode":"3500",
    "sg:province":"Limburg",
    "wof:name":"Christelijke Mutualiteit",
    "wof:placetype":"venue"
},
  "geometry": {"coordinates":[5.3069148064,50.8987922668],"type":"Point"}
}