{
  "type": "Feature",
  "properties": {
    "iso:country":"BE",
    "sg:address":"Grotstraat 18",
    "sg:city":"Keerbergen",
    "sg:classifiers":[
        {
            "category":"Professional",
            "subcategory":"Management & Consulting",
            "type":"Services"
        }
    ],
    "sg:phone":"+32 16 53 44 23",
    "sg:postcode":"3140",
    "sg:province":"Vlaams-Brabant",
    "sg:tags":[
        "consultant"
    ],
    "wof:name":"Van De Ven M",
    "wof:placetype":"venue"
},
  "geometry": {"coordinates":[4.6733531952,50.9979133606],"type":"Point"}
}