{
  "type": "Feature",
  "properties": {
    "iso:country":"BE",
    "sg:address":"Boterstraat 4",
    "sg:city":"Aalst",
    "sg:classifiers":[
        {
            "category":"Bars & Pubs",
            "type":"Food & Drink"
        }
    ],
    "sg:phone":"+32 477 25 04 62",
    "sg:postcode":"9300",
    "sg:province":"Oost-Vlaanderen",
    "wof:name":"Barca B\u00e8re",
    "wof:placetype":"venue"
},
  "geometry": {"coordinates":[4.0366587639,50.9368209839],"type":"Point"}
}