{
  "type": "Feature",
  "properties": {
    "addr:full":"Rue Richard Heintz 48 Herstal Li\u00e8ge 4040",
    "addr:housenumber":"48",
    "addr:postcode":"4040",
    "addr:street":"Rue Richard Heintz",
    "iso:country":"BE",
    "sg:address":"Rue Richard Heintz 48",
    "sg:city":"Herstal",
    "sg:orig_category":"Enseignement maternel and primaire",
    "sg:phone":"+32 4 264 17 77",
    "sg:postcode":"4040",
    "sg:province":"Li\u00e8ge",
    "wof:name":"Ecole Fond. Communale",
    "wof:placetype":"venue"
},
  "geometry": {"coordinates":[5.6360111237,50.6660995483],"type":"Point"}
}