{
  "type": "Feature",
  "properties": {
    "addr:full":"Rue De Li\u00e8ge 16 Verviers Li\u00e8ge 4800",
    "addr:housenumber":"16",
    "addr:postcode":"4800",
    "addr:street":"Rue De Lie\u0300Ge",
    "iso:country":"BE",
    "sg:address":"Rue De Li\u00e8ge 16",
    "sg:city":"Verviers",
    "sg:classifiers":[
        {
            "category":"Professional",
            "subcategory":"Testing Lab",
            "type":"Services"
        }
    ],
    "sg:phone":"+32 87 22 76 59",
    "sg:postcode":"4800",
    "sg:province":"Li\u00e8ge",
    "sg:tags":[
        "chemist"
    ],
    "wof:name":"Simar Sa",
    "wof:placetype":"venue"
},
  "geometry": {"coordinates":[5.8567838669,50.5869445801],"type":"Point"}
}