{
  "type": "Feature",
  "properties": {
    "addr:full":"Rue Neuve 22 Brussel/bruxelles Bruxelles-Capitale 1000",
    "addr:housenumber":"22",
    "addr:postcode":"1000",
    "addr:street":"Rue Neuve;/",
    "iso:country":"BE",
    "sg:address":"Rue Neuve 22",
    "sg:city":"Brussel/bruxelles",
    "sg:orig_category":"Opticiens",
    "sg:phone":"+32 2 223 05 40",
    "sg:postcode":"1000",
    "sg:province":"Bruxelles-Capitale",
    "wof:name":"Clara-clara",
    "wof:placetype":"venue"
},
  "geometry": {"coordinates":[4.3540668488,50.851108551],"type":"Point"}
}