{
  "type": "Feature",
  "properties": {
    "iso:country":"BE",
    "sg:address":"Jan Van Rijswijcklaan 132b6",
    "sg:city":"Antwerpen",
    "sg:orig_category":"Avocats and conseillers juridiques",
    "sg:phone":"+32 3 248 10 66",
    "sg:postcode":"2018",
    "sg:province":"Antwerpen",
    "wof:name":"Luc Barthels",
    "wof:placetype":"venue"
},
  "geometry": {"coordinates":[4.4024419785,51.1946182251],"type":"Point"}
}