{
  "type": "Feature",
  "properties": {
    "addr:full":"Beenhouwersstraat 67 Brugge West-Vlaanderen 8000",
    "addr:housenumber":"67",
    "addr:postcode":"8000",
    "addr:street":"Beenhouwersstraat",
    "iso:country":"BE",
    "sg:address":"Beenhouwersstraat 67",
    "sg:city":"Brugge",
    "sg:orig_category":"Boekbinderijen and afwerking",
    "sg:phone":"+32 50 33 00 21",
    "sg:postcode":"8000",
    "sg:province":"West-Vlaanderen",
    "wof:name":"Ecrivez-moi",
    "wof:placetype":"venue"
},
  "geometry": {"coordinates":[3.2162089348,51.2102775574],"type":"Point"}
}