{
  "type": "Feature",
  "properties": {
    "iso:country":"BE",
    "sg:address":"Rue Du Bultia 85",
    "sg:city":"Gerpinnes",
    "sg:classifiers":[
        {
            "category":"Professional",
            "subcategory":"Management & Consulting",
            "type":"Services"
        }
    ],
    "sg:phone":"+32 71 21 31 79",
    "sg:postcode":"6280",
    "sg:province":"Hainaut",
    "sg:tags":[
        "consultant"
    ],
    "wof:name":"Hunin D",
    "wof:placetype":"venue"
},
  "geometry": {"coordinates":[4.4791998863,50.3445396423],"type":"Point"}
}