{
  "type": "Feature",
  "properties": {
    "addr:full":"Kouterbaan 7 Denderleeuw Oost-Vlaanderen 9470",
    "addr:housenumber":"7",
    "addr:postcode":"9470",
    "addr:street":"Kouterbaan",
    "iso:country":"BE",
    "sg:address":"Kouterbaan 7",
    "sg:city":"Denderleeuw",
    "sg:orig_category":"Slagers",
    "sg:phone":"+32 53 66 69 61",
    "sg:postcode":"9470",
    "sg:province":"Oost-Vlaanderen",
    "wof:name":"Patrick De Jaeghere",
    "wof:placetype":"venue"
},
  "geometry": {"coordinates":[4.072578907,50.887512207],"type":"Point"}
}