{
  "type": "Feature",
  "properties": {
    "addr:full":"Dr\u00c8ve Des Faisans 32 Edingen/enghien Hainaut 7850",
    "addr:housenumber":"32",
    "addr:postcode":"7850",
    "addr:street":"Dre\u0300Ve Des Faisans",
    "iso:country":"BE",
    "sg:address":"Dr\u00c8ve Des Faisans 32",
    "sg:city":"Edingen/enghien",
    "sg:orig_category":"M\u00e9decins and sp\u00e9cialistes",
    "sg:phone":"+32 2 395 53 12",
    "sg:postcode":"7850",
    "sg:province":"Hainaut",
    "wof:name":"Michel Martens",
    "wof:placetype":"venue"
},
  "geometry": {"coordinates":[4.0894107819,50.7077140808],"type":"Point"}
}