{
  "type": "Feature",
  "properties": {
    "addr:full":"Nieuwmoersesteenweg 3 Essen Antwerpen 2910",
    "addr:housenumber":"3",
    "addr:postcode":"2910",
    "addr:street":"Nieuwmoersesteenweg",
    "iso:country":"BE",
    "sg:address":"Nieuwmoersesteenweg 3",
    "sg:city":"Essen",
    "sg:orig_category":"DIVERSE RECREATIEVE ACTIVITEITEN",
    "sg:phone":"+32 3 676 16 72",
    "sg:postcode":"2910",
    "sg:province":"Antwerpen",
    "wof:name":"\u00b4t Binnepretje",
    "wof:placetype":"venue"
},
  "geometry": {"coordinates":[4.4758119583,51.4603652954],"type":"Point"}
}