{
  "type": "Feature",
  "properties": {
    "addr:full":"Broustinlaan 118 Ganshoren/ganshoren Bruxelles-Capitale 1083",
    "addr:housenumber":"118",
    "addr:postcode":"1083",
    "addr:street":"Broustinlaan",
    "iso:country":"BE",
    "sg:address":"Broustinlaan 118",
    "sg:city":"Ganshoren/ganshoren",
    "sg:classifiers":[
        {
            "category":"Travel",
            "subcategory":"Hotels & Motels",
            "type":"Entertainment"
        }
    ],
    "sg:phone":"+32 2 425 14 22",
    "sg:postcode":"1083",
    "sg:province":"Bruxelles-Capitale",
    "sg:tags":[
        "restaurant"
    ],
    "wof:name":"Hotel Fr\u00c9deriksborg",
    "wof:placetype":"venue"
},
  "geometry": {"coordinates":[4.3210411072,50.8671875],"type":"Point"}
}