{
  "type": "Feature",
  "properties": {
    "addr:full":"Chauss\u00c9e D\u00b4ixelles 8 Elsene/ixelles Bruxelles-Capitale 1050",
    "addr:housenumber":"8",
    "addr:postcode":"1050",
    "addr:street":"Chausse\u0301E D\u00b4Ixelles",
    "iso:country":"BE",
    "sg:address":"Chauss\u00c9e D\u00b4ixelles 8",
    "sg:city":"Elsene/ixelles",
    "sg:orig_category":"Syst\u00e8mes de t\u00e9l\u00e9communications. Ordinateurs and \u00e9quipement informatique",
    "sg:phone":"+32 2 511 81 21",
    "sg:postcode":"1050",
    "sg:province":"Bruxelles-Capitale",
    "wof:name":"Fnac T\u00c9l\u00c9com",
    "wof:placetype":"venue"
},
  "geometry": {"coordinates":[4.3621530533,50.8378601074],"type":"Point"}
}