{
  "type": "Feature",
  "properties": {
    "iso:country":"BE",
    "sg:address":"Fraiture 36",
    "sg:city":"Vielsalm",
    "sg:orig_category":"Eleveurs de bovins",
    "sg:phone":"+32 80 41 86 95",
    "sg:postcode":"6690",
    "sg:province":"Luxembourg",
    "wof:name":"Joseph Boulanger",
    "wof:placetype":"venue"
},
  "geometry": {"coordinates":[5.9167118073,50.28540802],"type":"Point"}
}