{
  "type": "Feature",
  "properties": {
    "addr:full":"Generaal De Ceuninckstr. 85 Mechelen Antwerpen 2800",
    "addr:housenumber":"85",
    "addr:postcode":"2800",
    "addr:street":"Generaal De Ceuninckstr.",
    "iso:country":"BE",
    "sg:address":"Generaal De Ceuninckstr. 85",
    "sg:city":"Mechelen",
    "sg:orig_category":"Informaticaconsulenten",
    "sg:phone":"+32 15 33 73 52",
    "sg:postcode":"2800",
    "sg:province":"Antwerpen",
    "wof:name":"P.j. Engineering",
    "wof:placetype":"venue"
},
  "geometry": {"coordinates":[4.4790787697,51.0353431702],"type":"Point"}
}