{
  "type": "Feature",
  "properties": {
    "addr:full":"Rue Clerbeau 46 Herstal (milmort) Li\u00e8ge 4041",
    "addr:housenumber":"46",
    "addr:postcode":"4041",
    "addr:street":"Rue Clerbeau",
    "iso:country":"BE",
    "sg:address":"Rue Clerbeau 46",
    "sg:city":"Herstal (milmort)",
    "sg:classifiers":[
        {
            "category":"Home & Garden",
            "subcategory":"Building Materials",
            "type":"Retail Goods"
        }
    ],
    "sg:phone":"+32 4 278 07 51",
    "sg:postcode":"4041",
    "sg:province":"Li\u00e8ge",
    "sg:tags":[
        "granite",
        "stone",
        "natural",
        "marble"
    ],
    "wof:name":"M.p.g.",
    "wof:placetype":"venue"
},
  "geometry": {"coordinates":[5.5956058502,50.6915016174],"type":"Point"}
}