{
  "type": "Feature",
  "properties": {
    "iso:country":"BE",
    "sg:address":"Slypsstraat 12",
    "sg:city":"Ledegem",
    "sg:orig_category":"Eleveurs de bovins. Producteurs de fruits",
    "sg:phone":"+32 56 50 97 15",
    "sg:postcode":"8880",
    "sg:province":"West-Vlaanderen",
    "wof:name":"Eric Sioen",
    "wof:placetype":"venue"
},
  "geometry": {"coordinates":[3.1043360233,50.8633003235],"type":"Point"}
}