{
  "type": "Feature",
  "properties": {
    "addr:full":"Rue De La Victoire 6 Bruxelles (saint-gilles) Bruxelles-Capitale 1060",
    "addr:housenumber":"6",
    "addr:postcode":"1060",
    "addr:street":"Rue De La Victoire",
    "iso:country":"BE",
    "sg:address":"Rue De La Victoire 6",
    "sg:city":"Bruxelles (saint-gilles)",
    "sg:classifiers":[
        {
            "category":"Bakery",
            "type":"Food & Drink"
        }
    ],
    "sg:phone":"+32 2 538 02 08",
    "sg:postcode":"1060",
    "sg:province":"Bruxelles-Capitale",
    "sg:tags":[
        "confectioner",
        "baker"
    ],
    "wof:name":"Ronde Des Pains (la)",
    "wof:placetype":"venue"
},
  "geometry": {"coordinates":[4.3458271027,50.832485199],"type":"Point"}
}