{
  "type": "Feature",
  "properties": {
    "addr:full":"Chauss\u00c9e De Bruxelles 102 Nivelles Brabant Wallon 1400",
    "addr:housenumber":"102",
    "addr:postcode":"1400",
    "addr:street":"Chausse\u0301E De Bruxelles",
    "iso:country":"BE",
    "sg:address":"Chauss\u00c9e De Bruxelles 102",
    "sg:city":"Nivelles",
    "sg:classifiers":[
        {
            "category":"Restaurant",
            "type":"Food & Drink"
        }
    ],
    "sg:phone":"+32 67 22 02 53",
    "sg:postcode":"1400",
    "sg:province":"Brabant Wallon",
    "wof:name":"Rest. Au Duc De Brabant",
    "wof:placetype":"venue"
},
  "geometry": {"coordinates":[4.3329949379,50.6069488525],"type":"Point"}
}