{
  "type": "Feature",
  "properties": {
    "iso:country":"BE",
    "sg:address":"Oostmalsesteenweg 1",
    "sg:city":"Ranst (broechem)",
    "sg:classifiers":[
        {
            "category":"Mining & Drilling",
            "type":"Manufacturing & Wholesale Goods"
        }
    ],
    "sg:phone":"+32 3 475 01 55",
    "sg:postcode":"2520",
    "sg:province":"Antwerpen",
    "sg:tags":[
        "quarry"
    ],
    "wof:name":"Van Camp Nv",
    "wof:placetype":"venue"
},
  "geometry": {"coordinates":[4.5926470757,51.1598701477],"type":"Point"}
}