{
  "type": "Feature",
  "properties": {
    "iso:country":"BE",
    "sg:address":"Rue De Gaume 14",
    "sg:city":"Musson",
    "sg:classifiers":[
        {
            "category":"Health Services",
            "subcategory":"Health Practitioner",
            "type":"Services"
        }
    ],
    "sg:phone":"+32 63 67 52 22",
    "sg:postcode":"6750",
    "sg:province":"Luxembourg",
    "sg:tags":[
        "physiotherapist"
    ],
    "wof:name":"Coos Huguette",
    "wof:placetype":"venue"
},
  "geometry": {"coordinates":[5.706510067,49.5571098328],"type":"Point"}
}