{
  "type": "Feature",
  "properties": {
    "iso:country":"BE",
    "sg:address":"R\u00e9sidence Androm\u00e8de 8",
    "sg:city":"Wavre (limal)",
    "sg:classifiers":[
        {
            "category":"Real Estate",
            "subcategory":"Surveying",
            "type":"Services"
        }
    ],
    "sg:phone":"+32 10 41 65 84",
    "sg:postcode":"1300",
    "sg:province":"Brabant Wallon",
    "sg:tags":[
        "surveyor",
        "land"
    ],
    "wof:name":"Piret G",
    "wof:placetype":"venue"
},
  "geometry": {"coordinates":[4.6116552353,50.7134132385],"type":"Point"}
}