{
  "type": "Feature",
  "properties": {
    "addr:full":"Les Golettes 30 Huy Li\u00e8ge 4500",
    "addr:housenumber":"30",
    "addr:postcode":"4500",
    "addr:street":"Golettes",
    "iso:country":"BE",
    "sg:address":"Les Golettes 30",
    "sg:city":"Huy",
    "sg:orig_category":"Binnenhuisarchitecten",
    "sg:phone":"+32 85 25 10 61",
    "sg:postcode":"4500",
    "sg:province":"Li\u00e8ge",
    "wof:name":"Bureau Intercrea",
    "wof:placetype":"venue"
},
  "geometry": {"coordinates":[5.2567071915,50.5203094482],"type":"Point"}
}