{
  "type": "Feature",
  "properties": {
    "addr:full":"Rue Alexandre-louis Vanhove 43 Renaix Oost-Vlaanderen 9600",
    "addr:housenumber":"43",
    "addr:postcode":"9600",
    "addr:street":"Rue Alexandre-Louis Vanhove",
    "iso:country":"BE",
    "sg:address":"Rue Alexandre-louis Vanhove 43",
    "sg:city":"Renaix",
    "sg:classifiers":[
        {
            "category":"Professional",
            "subcategory":"Accounting & Tax Preparation",
            "type":"Services"
        }
    ],
    "sg:phone":"+32 55 21 72 12",
    "sg:postcode":"9600",
    "sg:province":"Oost-Vlaanderen",
    "sg:tags":[
        "accountant"
    ],
    "wof:name":"Devos F",
    "wof:placetype":"venue"
},
  "geometry": {"coordinates":[3.593640089,50.7462348938],"type":"Point"}
}