{
  "type": "Feature",
  "properties": {
    "addr:full":"Rue Du Postil 26 Fosses-la-ville Namur 5070",
    "addr:housenumber":"26",
    "addr:postcode":"5070",
    "addr:street":"Rue Du Postil",
    "iso:country":"BE",
    "sg:address":"Rue Du Postil 26",
    "sg:city":"Fosses-la-ville",
    "sg:orig_category":"Pain, p\u00e2tisseries and confiseries. Eclairage et \u00e9quipements du foyer",
    "sg:phone":"+32 71 71 26 00",
    "sg:postcode":"5070",
    "sg:province":"Namur",
    "wof:name":"La Bonbonni\u00c8re",
    "wof:placetype":"venue"
},
  "geometry": {"coordinates":[4.6959571838,50.3946456909],"type":"Point"}
}