{
  "type": "Feature",
  "properties": {
    "iso:country":"BE",
    "sg:address":"Chauss\u00c9e De Mons 909",
    "sg:city":"Anderlecht",
    "sg:orig_category":"D\u00e9taillants en pi\u00e8ces and accessoires de voitures",
    "sg:phone":"+32 2 526 22 05",
    "sg:postcode":"1070",
    "sg:province":"Bruxelles-Capitale",
    "wof:name":"Stappers Belgium",
    "wof:placetype":"venue"
},
  "geometry": {"coordinates":[4.300383091,50.8270797729],"type":"Point"}
}