{
  "type": "Feature",
  "properties": {
    "iso:country":"BE",
    "sg:address":"Heppersteenweg 18",
    "sg:city":"Maaseik",
    "sg:orig_category":"Industri\u00eble and commerci\u00eble bouw Woningbouw",
    "sg:phone":"+32 89 56 62 88",
    "sg:postcode":"3680",
    "sg:province":"Limburg",
    "wof:name":"Segers M.",
    "wof:placetype":"venue"
},
  "geometry": {"coordinates":[5.7912278175,51.0917434692],"type":"Point"}
}