{
  "type": "Feature",
  "properties": {
    "addr:full":"Rue J.wauters 16 A Marchin 5270",
    "addr:housenumber":"16 a",
    "addr:postcode":"5270",
    "addr:street":"Rue J.Wauters",
    "iso:country":"BE",
    "sg:address":"Rue J.wauters 16 A",
    "sg:city":"Marchin",
    "sg:classifiers":[
        {
            "category":"Banks & Credit Unions",
            "subcategory":"Bank",
            "type":"Services"
        }
    ],
    "sg:phone":"+32 85 23 45 98",
    "sg:postcode":"5270",
    "wof:name":"Aslk-cger Bank",
    "wof:placetype":"venue"
},
  "geometry": {"coordinates":[140.57780456539999,-36.3795700073],"type":"Point"}
}