{
  "type": "Feature",
  "properties": {
    "iso:country":"BE",
    "sg:address":"Avenue Du Domaine 17",
    "sg:city":"Vorst/forest",
    "sg:orig_category":"Cr\u00e8ches and garderies d'enfants",
    "sg:phone":"+32 2 345 54 37",
    "sg:postcode":"1190",
    "sg:province":"Bruxelles-Capitale",
    "wof:name":"Cr\u00c8che Les Sept Nains",
    "wof:placetype":"venue"
},
  "geometry": {"coordinates":[4.3288531303,50.807220459],"type":"Point"}
}