{
  "type": "Feature",
  "properties": {
    "addr:full":"Bakkerstraat 45a Dendermonde (grembergen) Oost-Vlaanderen 9200",
    "addr:housenumber":"45a",
    "addr:postcode":"9200",
    "addr:street":"Bakkerstraat",
    "iso:country":"BE",
    "sg:address":"Bakkerstraat 45a",
    "sg:city":"Dendermonde (grembergen)",
    "sg:classifiers":[
        {
            "category":"Food & Beverages",
            "subcategory":"Supermarket",
            "type":"Retail Goods"
        }
    ],
    "sg:phone":"+32 52 25 60 73",
    "sg:postcode":"9200",
    "sg:province":"Oost-Vlaanderen",
    "sg:tags":[
        "department",
        "store"
    ],
    "wof:name":"Sparmarkt",
    "wof:placetype":"venue"
},
  "geometry": {"coordinates":[4.1030139923,51.0443305969],"type":"Point"}
}