{
  "type": "Feature",
  "properties": {
    "addr:full":"Hazelaardreef 4 Grobbendonk Antwerpen 2280",
    "addr:housenumber":"4",
    "addr:postcode":"2280",
    "addr:street":"Hazelaardreef",
    "iso:country":"BE",
    "sg:address":"Hazelaardreef 4",
    "sg:city":"Grobbendonk",
    "sg:orig_category":"Antiek",
    "sg:phone":"+32 14 50 05 95",
    "sg:postcode":"2280",
    "sg:province":"Antwerpen",
    "wof:name":"Hale",
    "wof:placetype":"venue"
},
  "geometry": {"coordinates":[4.7204680443,51.1721038818],"type":"Point"}
}