{
  "type": "Feature",
  "properties": {
    "iso:country":"BE",
    "sg:address":"Mommestraat 54",
    "sg:city":"Heusden-zolder",
    "sg:orig_category":"Verhuur televisie- and audiovisuele apparatuur",
    "sg:phone":"+32 11 53 71 91",
    "sg:postcode":"3550",
    "sg:province":"Limburg",
    "wof:name":"Little Big Rig Product.",
    "wof:placetype":"venue"
},
  "geometry": {"coordinates":[5.3200941086,51.0322875977],"type":"Point"}
}