{
  "type": "Feature",
  "properties": {
    "iso:country":"BE",
    "sg:address":"3500",
    "sg:city":"Hasselt",
    "sg:orig_category":"Magasins de r\u00e9parations d'articles personnels et m\u00e9nagers divers. R\u00e9parations \u00e0 domicile d'articles ",
    "sg:phone":"+32 11 25 53 38",
    "sg:postcode":"3500",
    "sg:province":"Limburg",
    "wof:name":"Nulens Alain Slotenmaker",
    "wof:placetype":"venue"
},
  "geometry": {"coordinates":[5.3372898102,50.9304008484],"type":"Point"}
}