{
  "type": "Feature",
  "properties": {
    "iso:country":"BE",
    "sg:address":"Rue De Tilleur 251",
    "sg:city":"Saint-nicolas",
    "sg:classifiers":[
        {
            "category":"Health Services",
            "subcategory":"Medical Lab",
            "type":"Services"
        }
    ],
    "sg:phone":"+32 4 252 38 44",
    "sg:postcode":"4420",
    "sg:province":"Li\u00e8ge",
    "sg:tags":[
        "laboratory",
        "dental"
    ],
    "wof:name":"Laboratoires Dentaires Vervietois Sprl",
    "wof:placetype":"venue"
},
  "geometry": {"coordinates":[5.5364899635,50.6252593994],"type":"Point"}
}