{
  "type": "Feature",
  "properties": {
    "iso:country":"BE",
    "sg:address":"Avenue Albert I 43",
    "sg:city":"Huy",
    "sg:classifiers":[
        {
            "category":"Professional",
            "type":"Services"
        }
    ],
    "sg:phone":"+32 85 21 79 90",
    "sg:postcode":"4500",
    "sg:province":"Li\u00e8ge",
    "sg:tags":[
        "auction",
        "room"
    ],
    "wof:name":"Cmo",
    "wof:placetype":"venue"
},
  "geometry": {"coordinates":[5.2347249985,50.5246887207],"type":"Point"}
}