{
  "type": "Feature",
  "properties": {
    "iso:country":"BE",
    "sg:address":"Onze Lieve Vrouwstraat 13",
    "sg:city":"Beringen",
    "sg:classifiers":[
        {
            "category":"Shopping",
            "subcategory":"Clothing, Apparel, & Fashions",
            "type":"Retail Goods"
        }
    ],
    "sg:phone":"+32 11 42 88 22",
    "sg:postcode":"3580",
    "sg:province":"Limburg",
    "sg:tags":[
        "ondergoed",
        "lingerie"
    ],
    "wof:name":"Huis Tess",
    "wof:placetype":"venue"
},
  "geometry": {"coordinates":[5.2191038132,51.0480422974],"type":"Point"}
}