{
  "type": "Feature",
  "properties": {
    "iso:country":"BE",
    "sg:address":"Rue Beaufaux 44",
    "sg:city":"Ellezelles",
    "sg:orig_category":"Artsen and specialisten",
    "sg:phone":"+32 68 54 26 17",
    "sg:postcode":"7890",
    "sg:province":"Hainaut",
    "wof:name":"R. De Meutter",
    "wof:placetype":"venue"
},
  "geometry": {"coordinates":[3.6658859253,50.747505188],"type":"Point"}
}