{
  "type": "Feature",
  "properties": {
    "iso:country":"BE",
    "sg:address":"Maastrichterstraat 45",
    "sg:city":"Bilzen",
    "sg:classifiers":[
        {
            "category":"Health Services",
            "subcategory":"Health Practitioner",
            "type":"Services"
        }
    ],
    "sg:phone":"+32 89 41 33 54",
    "sg:postcode":"3740",
    "sg:province":"Limburg",
    "sg:tags":[
        "physiotherapist"
    ],
    "wof:name":"Tans Stefan",
    "wof:placetype":"venue"
},
  "geometry": {"coordinates":[5.5227198601,50.8657684326],"type":"Point"}
}