{
  "type": "Feature",
  "properties": {
    "iso:country":"BE",
    "sg:address":"Berkenlaan 16",
    "sg:city":"Ternat",
    "sg:classifiers":[
        {
            "category":"Cafe",
            "type":"Food & Drink"
        }
    ],
    "sg:phone":"+32 2 582 49 50",
    "sg:postcode":"1740",
    "sg:province":"Vlaams-Brabant",
    "sg:tags":[
        "caf\u00e9s"
    ],
    "wof:name":"Herwin Cobbaert",
    "wof:placetype":"venue"
},
  "geometry": {"coordinates":[4.1852087975,50.8754844666],"type":"Point"}
}