{
  "type": "Feature",
  "properties": {
    "addr:full":"Gwijde Van Dampierrestraat 3 Torhout West-Vlaanderen 8820",
    "addr:housenumber":"3",
    "addr:postcode":"8820",
    "addr:street":"Dampierrestraat",
    "iso:country":"BE",
    "sg:address":"Gwijde Van Dampierrestraat 3",
    "sg:city":"Torhout",
    "sg:classifiers":[
        {
            "category":"Social Services",
            "subcategory":"Job Training",
            "type":"Services"
        }
    ],
    "sg:phone":"+32 50 21 71 57",
    "sg:postcode":"8820",
    "sg:province":"West-Vlaanderen",
    "sg:tags":[
        "personnel"
    ],
    "wof:name":"Commeine T",
    "wof:placetype":"venue"
},
  "geometry": {"coordinates":[3.0987861156,51.0739593506],"type":"Point"}
}