{
  "type": "Feature",
  "properties": {
    "addr:full":"Hoogstraat 26 Boom Antwerpen 2850",
    "addr:housenumber":"26",
    "addr:postcode":"2850",
    "addr:street":"Hoogstraat",
    "iso:country":"BE",
    "sg:address":"Hoogstraat 26",
    "sg:city":"Boom",
    "sg:orig_category":"Drogueries. Parfumeries",
    "sg:phone":"+32 3 844 14 80",
    "sg:postcode":"2850",
    "sg:province":"Antwerpen",
    "wof:name":"Kruidvat",
    "wof:placetype":"venue"
},
  "geometry": {"coordinates":[4.3654441833,51.0859527588],"type":"Point"}
}