{
  "type": "Feature",
  "properties": {
    "iso:country":"BE",
    "sg:address":"Rue Coenraets 56",
    "sg:city":"Sint-gillis/saint-gilles",
    "sg:orig_category":"Produits pharmaceutiques Fab",
    "sg:phone":"+32 2 535 02 11",
    "sg:postcode":"1060",
    "sg:province":"Bruxelles-Capitale",
    "wof:name":"Fe. Schein Henry Hospith.",
    "wof:placetype":"venue"
},
  "geometry": {"coordinates":[4.3378748894,50.8321037292],"type":"Point"}
}