{
  "type": "Feature",
  "properties": {
    "iso:country":"BE",
    "sg:address":"Rue De Robermont 14",
    "sg:city":"Li\u00e8ge 1 (li\u00e8ge 2)",
    "sg:classifiers":[
        {
            "category":"Wholesale",
            "subcategory":"Home Furnishings",
            "type":"Manufacturing & Wholesale Goods"
        }
    ],
    "sg:phone":"+32 4 342 42 42",
    "sg:postcode":"4020",
    "sg:province":"Li\u00e8ge",
    "sg:tags":[
        "storage",
        "-",
        "furniture"
    ],
    "wof:name":"Transports Routiers Et Demenagements Samo & Cie Sprl",
    "wof:placetype":"venue"
},
  "geometry": {"coordinates":[5.5928139687,50.6354827881],"type":"Point"}
}