{
  "type": "Feature",
  "properties": {
    "iso:country":"BE",
    "sg:address":"Rue Du Moulin 33",
    "sg:city":"La Bruy\u00e8re (saint-denis)",
    "sg:classifiers":[
        {
            "category":"Home & Garden",
            "subcategory":"Garden Supply",
            "type":"Retail Goods"
        }
    ],
    "sg:phone":"+32 81 56 75 85",
    "sg:postcode":"5081",
    "sg:province":"Namur",
    "sg:tags":[
        "machine",
        "agricultural",
        "-"
    ],
    "wof:name":"Laurent A",
    "wof:placetype":"venue"
},
  "geometry": {"coordinates":[4.7833161354,50.5262184143],"type":"Point"}
}