{
  "type": "Feature",
  "properties": {
    "iso:country":"BE",
    "sg:address":"Molenstraat 107",
    "sg:city":"Rumst",
    "sg:orig_category":"Banken and kredietinstellingen",
    "sg:phone":"+32 3 888 62 24",
    "sg:postcode":"2840",
    "sg:province":"Antwerpen",
    "wof:name":"Landbouwkrediet",
    "wof:placetype":"venue"
},
  "geometry": {"coordinates":[4.4055352211,51.0999717712],"type":"Point"}
}