{
  "type": "Feature",
  "properties": {
    "iso:country":"BE",
    "sg:address":"Avenue Wanderpepen 49",
    "sg:city":"Binche",
    "sg:classifiers":[
        {
            "category":"Professional",
            "subcategory":"Art Services",
            "type":"Services"
        }
    ],
    "sg:phone":"+32 64 34 22 85",
    "sg:postcode":"7130",
    "sg:province":"Hainaut",
    "sg:tags":[
        "installation",
        "cafe",
        "-",
        "equipment"
    ],
    "wof:name":"Aura Scrl",
    "wof:placetype":"venue"
},
  "geometry": {"coordinates":[4.1695227623,50.4118919373],"type":"Point"}
}