{
  "type": "Feature",
  "properties": {
    "iso:country":"BE",
    "sg:address":"Avenue De Bouillon 16a",
    "sg:city":"Libramont-chevigny (libramont)",
    "sg:classifiers":[
        {
            "category":"Building & Trades",
            "subcategory":"Construction",
            "type":"Services"
        }
    ],
    "sg:phone":"+32 61 23 43 00",
    "sg:postcode":"6800",
    "sg:province":"Luxembourg",
    "sg:tags":[
        "surveyor",
        "-"
    ],
    "wof:name":"Rossignol (bureau)",
    "wof:placetype":"venue"
},
  "geometry": {"coordinates":[5.374765873,49.9189147949],"type":"Point"}
}