{
  "type": "Feature",
  "properties": {
    "iso:country":"BE",
    "sg:address":"Rue Du Cheval Godet 6 Box 1",
    "sg:city":"Nivelles",
    "sg:classifiers":[
        {
            "category":"Health Services",
            "subcategory":"Dentist",
            "type":"Services"
        }
    ],
    "sg:phone":"+32 67 84 24 71",
    "sg:postcode":"1400",
    "sg:province":"Brabant Wallon",
    "wof:name":"Sommereyns Nadine",
    "wof:placetype":"venue"
},
  "geometry": {"coordinates":[4.3241038322,50.6038551331],"type":"Point"}
}