{
  "type": "Feature",
  "properties": {
    "iso:country":"BE",
    "sg:address":"Nieuwstraat 111",
    "sg:city":"Brussel/bruxelles",
    "sg:orig_category":"Bagage and lederwaren",
    "sg:phone":"+32 2 223 08 62",
    "sg:postcode":"1000",
    "sg:province":"Bruxelles-Capitale",
    "wof:name":"Kipling",
    "wof:placetype":"venue"
},
  "geometry": {"coordinates":[4.3571557999,50.8536758423],"type":"Point"}
}