{
  "type": "Feature",
  "properties": {
    "addr:full":"Damstraat 111 Hamme Oost-Vlaanderen 9220",
    "addr:housenumber":"111",
    "addr:postcode":"9220",
    "addr:street":"Damstraat",
    "iso:country":"BE",
    "sg:address":"Damstraat 111",
    "sg:city":"Hamme",
    "sg:classifiers":[
        {
            "category":"Professional",
            "subcategory":"Art Services",
            "type":"Services"
        }
    ],
    "sg:phone":"+32 52 47 04 53",
    "sg:postcode":"9220",
    "sg:province":"Oost-Vlaanderen",
    "sg:tags":[
        "-",
        "furniture"
    ],
    "wof:name":"Superlux",
    "wof:placetype":"venue"
},
  "geometry": {"coordinates":[4.1375727654,51.0874938965],"type":"Point"}
}