{
  "type": "Feature",
  "properties": {
    "addr:full":"Gammel 29 Rijkevorsel Antwerpen 2310",
    "addr:housenumber":"29",
    "addr:postcode":"2310",
    "addr:street":"Gammel",
    "iso:country":"BE",
    "sg:address":"Gammel 29",
    "sg:city":"Rijkevorsel",
    "sg:orig_category":"Producteurs de fruits",
    "sg:phone":"+32 3 314 75 95",
    "sg:postcode":"2310",
    "sg:province":"Antwerpen",
    "wof:name":"Constant Eelen",
    "wof:placetype":"venue"
},
  "geometry": {"coordinates":[4.7577600479,51.3687591553],"type":"Point"}
}