{
  "type": "Feature",
  "properties": {
    "addr:full":"Kasteeldreef 13 Lede Oost-Vlaanderen 9340",
    "addr:housenumber":"13",
    "addr:postcode":"9340",
    "addr:street":"Kasteeldreef",
    "iso:country":"BE",
    "sg:address":"Kasteeldreef 13",
    "sg:city":"Lede",
    "sg:orig_category":"Boucheries",
    "sg:phone":"+32 53 80 36 52",
    "sg:postcode":"9340",
    "sg:province":"Oost-Vlaanderen",
    "wof:name":"Christiane Cardon",
    "wof:placetype":"venue"
},
  "geometry": {"coordinates":[3.9800069332,50.9661636353],"type":"Point"}
}