{
  "type": "Feature",
  "properties": {
    "iso:country":"BE",
    "sg:address":"Koning Albertlaan 3",
    "sg:city":"Lochristi",
    "sg:classifiers":[
        {
            "category":"Health Services",
            "subcategory":"Dentist",
            "type":"Services"
        }
    ],
    "sg:phone":"+32 9 355 69 22",
    "sg:postcode":"9080",
    "sg:province":"Oost-Vlaanderen",
    "wof:name":"Jacobs M",
    "wof:placetype":"venue"
},
  "geometry": {"coordinates":[3.8315169811,51.0961532593],"type":"Point"}
}