{
  "type": "Feature",
  "properties": {
    "iso:country":"BE",
    "sg:address":"Rue Des Flaches 131",
    "sg:city":"Gerpinnes",
    "sg:classifiers":[
        {
            "category":"Sports & Exercise",
            "subcategory":"Stables",
            "type":"Entertainment"
        }
    ],
    "sg:phone":"+32 71 50 42 11",
    "sg:postcode":"6280",
    "sg:province":"Hainaut",
    "sg:tags":[
        "riding",
        "school"
    ],
    "wof:name":"Ferme Des 4 Vents",
    "wof:placetype":"venue"
},
  "geometry": {"coordinates":[4.5029101372,50.3350791931],"type":"Point"}
}