{
  "type": "Feature",
  "properties": {
    "addr:full":"Rue De Favarcq 82 Beloeil Hainaut 7970",
    "addr:housenumber":"82",
    "addr:postcode":"7970",
    "addr:street":"Rue De Favarcq",
    "iso:country":"BE",
    "sg:address":"Rue De Favarcq 82",
    "sg:city":"Beloeil",
    "sg:classifiers":[
        {
            "category":"Insurance",
            "subcategory":"Insurance Agent",
            "type":"Services"
        }
    ],
    "sg:phone":"+32 69 68 93 16",
    "sg:postcode":"7970",
    "sg:province":"Hainaut",
    "sg:tags":[
        "verzekeringsmakelaars",
        "expert"
    ],
    "wof:name":"Philippe Hautecoeur",
    "wof:placetype":"venue"
},
  "geometry": {"coordinates":[3.7257099152,50.5442428589],"type":"Point"}
}