{
  "type": "Feature",
  "properties": {
    "addr:full":"Zwaluwstraat 6 Grimbergen Vlaams-Brabant 1850",
    "addr:housenumber":"6",
    "addr:postcode":"1850",
    "addr:street":"Zwaluwstraat",
    "iso:country":"BE",
    "sg:address":"Zwaluwstraat 6",
    "sg:city":"Grimbergen",
    "sg:orig_category":"Agences d'exp\u00e9dition",
    "sg:phone":"+32 2 253 27 07",
    "sg:postcode":"1850",
    "sg:province":"Vlaams-Brabant",
    "wof:name":"Choctal",
    "wof:placetype":"venue"
},
  "geometry": {"coordinates":[4.3995938301,50.9280014038],"type":"Point"}
}