{
  "type": "Feature",
  "properties": {
    "iso:country":"BE",
    "sg:address":"Rue De Gravi\u00e8re 26",
    "sg:city":"Namur",
    "sg:classifiers":[
        {
            "category":"Real Estate",
            "subcategory":"Real Estate Services",
            "type":"Services"
        }
    ],
    "sg:phone":"+32 81 26 08 54",
    "sg:postcode":"5000",
    "sg:province":"Namur",
    "wof:name":"Citadelle Agence",
    "wof:placetype":"venue"
},
  "geometry": {"coordinates":[4.8701038361,50.4634208679],"type":"Point"}
}