{
  "type": "Feature",
  "properties": {
    "addr:full":"Koning Leopold 2-laan 101 Gent Oost-Vlaanderen 9000",
    "addr:housenumber":"2-laan 101",
    "addr:postcode":"9000",
    "addr:street":"Koning Leopold;Oost-Vlaanderen",
    "iso:country":"BE",
    "sg:address":"Koning Leopold 2-laan 101",
    "sg:city":"Gent",
    "sg:orig_category":"Loodgieterij, verwarming and sanitaire installaties",
    "sg:phone":"+32 9 221 83 46",
    "sg:postcode":"9000",
    "sg:province":"Oost-Vlaanderen",
    "wof:name":"Van Ootegem",
    "wof:placetype":"venue"
},
  "geometry": {"coordinates":[3.7170379162,51.0378913879],"type":"Point"}
}