{
  "type": "Feature",
  "properties": {
    "addr:full":"Kaaistraat 18 Nieuwpoort West-Vlaanderen 8620",
    "addr:housenumber":"18",
    "addr:postcode":"8620",
    "addr:street":"Kaaistraat",
    "iso:country":"BE",
    "sg:address":"Kaaistraat 18",
    "sg:city":"Nieuwpoort",
    "sg:orig_category":"Reclamebureaus",
    "sg:phone":"+32 58 23 19 23",
    "sg:postcode":"8620",
    "sg:province":"West-Vlaanderen",
    "wof:name":"Fa. Publimax",
    "wof:placetype":"venue"
},
  "geometry": {"coordinates":[2.7500851154,51.1324043274],"type":"Point"}
}