{
  "type": "Feature",
  "properties": {
    "iso:country":"BE",
    "sg:address":"Rue De Bruxelles 14",
    "sg:city":"Enghien",
    "sg:classifiers":[
        {
            "category":"Shopping",
            "subcategory":"Shoes",
            "type":"Retail Goods"
        }
    ],
    "sg:phone":"+32 2 395 95 40",
    "sg:postcode":"7850",
    "sg:province":"Hainaut",
    "sg:tags":[
        "slipper",
        "-"
    ],
    "wof:name":"Nuances",
    "wof:placetype":"venue"
},
  "geometry": {"coordinates":[4.0399222374,50.6939277649],"type":"Point"}
}