{
  "type": "Feature",
  "properties": {
    "iso:country":"BE",
    "sg:address":"Ferdinand Maesstraat 11",
    "sg:city":"Kontich (waarloos)",
    "sg:classifiers":[
        {
            "category":"Professional",
            "subcategory":"Testing Lab",
            "type":"Services"
        }
    ],
    "sg:phone":"+32 15 31 33 67",
    "sg:postcode":"2550",
    "sg:province":"Antwerpen",
    "sg:tags":[
        "chemist"
    ],
    "wof:name":"Van Aelst L",
    "wof:placetype":"venue"
},
  "geometry": {"coordinates":[4.4526939392,51.1068153381],"type":"Point"}
}