{
  "type": "Feature",
  "properties": {
    "addr:full":"Kleine Leiestraat 33 Kortrijk West-Vlaanderen 8500",
    "addr:housenumber":"33",
    "addr:postcode":"8500",
    "addr:street":"Kleine Leiestraat",
    "iso:country":"BE",
    "sg:address":"Kleine Leiestraat 33",
    "sg:city":"Kortrijk",
    "sg:classifiers":[
        {
            "category":"Shopping",
            "subcategory":"Clothing, Apparel, & Fashions",
            "type":"Retail Goods"
        }
    ],
    "sg:phone":"+32 56 21 58 22",
    "sg:postcode":"8500",
    "sg:province":"West-Vlaanderen",
    "sg:tags":[
        "boutique"
    ],
    "wof:name":"Erina",
    "wof:placetype":"venue"
},
  "geometry": {"coordinates":[3.2644209862,50.8291435242],"type":"Point"}
}