{
  "type": "Feature",
  "properties": {
    "addr:full":"De Bruynlaan 11 Begijnendijk Vlaams-Brabant 3130",
    "addr:housenumber":"11",
    "addr:postcode":"3130",
    "addr:street":"De Bruynlaan",
    "iso:country":"BE",
    "sg:address":"De Bruynlaan 11",
    "sg:city":"Begijnendijk",
    "sg:classifiers":[
        {
            "category":"Arena",
            "subcategory":"Sports Club",
            "type":"Entertainment"
        }
    ],
    "sg:phone":"+32 16 53 34 60",
    "sg:postcode":"3130",
    "sg:province":"Vlaams-Brabant",
    "sg:tags":[
        "de"
    ],
    "wof:name":"W.c. 't Rollend Ei",
    "wof:placetype":"venue"
},
  "geometry": {"coordinates":[4.7814941406,51.0218963623],"type":"Point"}
}