{
  "type": "Feature",
  "properties": {
    "addr:full":"Aarschotsestraat 47 Vilvoorde (peutie) Vlaams-Brabant 1800",
    "addr:housenumber":"47",
    "addr:postcode":"1800",
    "addr:street":"Aarschotsestraat",
    "iso:country":"BE",
    "sg:address":"Aarschotsestraat 47",
    "sg:city":"Vilvoorde (peutie)",
    "sg:classifiers":[
        {
            "category":"Manufacturing",
            "subcategory":"Tools & Machinery",
            "type":"Manufacturing & Wholesale Goods"
        }
    ],
    "sg:phone":"+32 2 251 60 50",
    "sg:postcode":"1800",
    "sg:province":"Vlaams-Brabant",
    "sg:tags":[
        "machine"
    ],
    "wof:name":"Mondiale Nv",
    "wof:placetype":"venue"
},
  "geometry": {"coordinates":[4.4511761665,50.9246826172],"type":"Point"}
}