{
  "type": "Feature",
  "properties": {
    "addr:full":"Grand-rue 55 Komen-waasten/comines-warneton Hainaut 7780",
    "addr:housenumber":"55;7780",
    "addr:street":"Grand-Rue",
    "iso:country":"BE",
    "sg:address":"Grand-rue 55",
    "sg:city":"Komen-waasten/comines-warneton",
    "sg:orig_category":"Travaux de pl\u00e2trage",
    "sg:phone":"+32 56 55 74 62",
    "sg:postcode":"7780",
    "sg:province":"Hainaut",
    "wof:name":"Fa. Demyttenaere",
    "wof:placetype":"venue"
},
  "geometry": {"coordinates":[2.9984300137,50.7863311768],"type":"Point"}
}