{
  "type": "Feature",
  "properties": {
    "iso:country":"BE",
    "sg:address":"Plein 54",
    "sg:city":"Kaprijke",
    "sg:classifiers":[
        {
            "category":"Cafe",
            "type":"Food & Drink"
        }
    ],
    "sg:phone":"+32 9 373 89 77",
    "sg:postcode":"9970",
    "sg:province":"Oost-Vlaanderen",
    "sg:tags":[
        "caf\u00e9s"
    ],
    "wof:name":"Conny Buysse",
    "wof:placetype":"venue"
},
  "geometry": {"coordinates":[3.6208879948,51.2170982361],"type":"Point"}
}