{
  "type": "Feature",
  "properties": {
    "iso:country":"BE",
    "sg:address":"Plaisantstraat 15",
    "sg:city":"Moerbeke",
    "sg:orig_category":"Transports terrestres de voyageurs",
    "sg:phone":"+32 9 346 59 95",
    "sg:postcode":"9180",
    "sg:province":"Oost-Vlaanderen",
    "wof:name":"Geert Cars",
    "wof:placetype":"venue"
},
  "geometry": {"coordinates":[3.9378979206,51.1737861633],"type":"Point"}
}