{
  "type": "Feature",
  "properties": {
    "addr:full":"Schransdreef 47 Overijse Vlaams-Brabant 3090",
    "addr:housenumber":"47",
    "addr:postcode":"3090",
    "addr:street":"Schransdreef",
    "iso:country":"BE",
    "sg:address":"Schransdreef 47",
    "sg:city":"Overijse",
    "sg:orig_category":"Fruitteelt",
    "sg:phone":"+32 2 687 67 81",
    "sg:postcode":"3090",
    "sg:province":"Vlaams-Brabant",
    "wof:name":"Ghislain Luyckx",
    "wof:placetype":"venue"
},
  "geometry": {"coordinates":[4.5065059662,50.7940483093],"type":"Point"}
}