{
  "type": "Feature",
  "properties": {
    "iso:country":"BE",
    "sg:address":"Wortegemsesteenweg 15a",
    "sg:city":"Anzegem",
    "sg:classifiers":[
        {
            "category":"Insurance",
            "subcategory":"Insurance Agent",
            "type":"Services"
        }
    ],
    "sg:phone":"+32 56 68 06 06",
    "sg:postcode":"8570",
    "sg:province":"West-Vlaanderen",
    "sg:tags":[
        "verzekeringsmakelaars",
        "expert"
    ],
    "wof:name":"Quatannens J. & Co",
    "wof:placetype":"venue"
},
  "geometry": {"coordinates":[3.4825069904,50.8340568542],"type":"Point"}
}