{
  "type": "Feature",
  "properties": {
    "addr:full":"Damstraat 55 Deinze Oost-Vlaanderen 9800",
    "addr:housenumber":"55",
    "addr:postcode":"9800",
    "addr:street":"Damstraat",
    "iso:country":"BE",
    "sg:address":"Damstraat 55",
    "sg:city":"Deinze",
    "sg:orig_category":"Installation de menuiserie en bois and plastique",
    "sg:phone":"+32 9 282 65 72",
    "sg:postcode":"9800",
    "sg:province":"Oost-Vlaanderen",
    "wof:name":"Basilius De Weirdt",
    "wof:placetype":"venue"
},
  "geometry": {"coordinates":[3.5756750107,51.0183944702],"type":"Point"}
}