{
  "type": "Feature",
  "properties": {
    "iso:country":"BE",
    "sg:address":"Chauss\u00c9e De Bruxelles 325",
    "sg:city":"Waterloo",
    "sg:orig_category":"Antiquit\u00e9s",
    "sg:phone":"+32 2 351 06 79",
    "sg:postcode":"1410",
    "sg:province":"Brabant Wallon",
    "wof:name":"Meubles Daleside",
    "wof:placetype":"venue"
},
  "geometry": {"coordinates":[4.4019331932,50.7054481506],"type":"Point"}
}