{
  "type": "Feature",
  "properties": {
    "addr:full":"Achter D'hoven 11b1 Wuustwezel Antwerpen 2990",
    "addr:housenumber":"11b1",
    "addr:postcode":"2990",
    "addr:street":"Achter D'Hoven",
    "iso:country":"BE",
    "sg:address":"Achter D'hoven 11b1",
    "sg:city":"Wuustwezel",
    "sg:orig_category":"Technische studies and ingenieursactiviteiten",
    "sg:phone":"+32 3 669 72 42",
    "sg:postcode":"2990",
    "sg:province":"Antwerpen",
    "wof:name":"Pyramid & Co",
    "wof:placetype":"venue"
},
  "geometry": {"coordinates":[4.5960998535,51.3893432617],"type":"Point"}
}