{
  "type": "Feature",
  "properties": {
    "addr:full":"Kerkstraat 1 Lokeren Oost-Vlaanderen 9160",
    "addr:housenumber":"1",
    "addr:postcode":"9160",
    "addr:street":"Kerkstraat",
    "iso:country":"BE",
    "sg:address":"Kerkstraat 1",
    "sg:city":"Lokeren",
    "sg:orig_category":"Dameskledingzaken",
    "sg:phone":"+32 9 348 58 11",
    "sg:postcode":"9160",
    "sg:province":"Oost-Vlaanderen",
    "wof:name":"M&s Mode",
    "wof:placetype":"venue"
},
  "geometry": {"coordinates":[3.9922189713,51.1038093567],"type":"Point"}
}