{
  "type": "Feature",
  "properties": {
    "addr:full":"Oostkaai 82 Ieper West-Vlaanderen 8900",
    "addr:housenumber":"82",
    "addr:postcode":"8900",
    "addr:street":"Oostkaai",
    "iso:country":"BE",
    "sg:address":"Oostkaai 82",
    "sg:city":"Ieper",
    "sg:classifiers":[
        {
            "category":"Wholesale",
            "subcategory":"Machinery & Supplies",
            "type":"Manufacturing & Wholesale Goods"
        }
    ],
    "sg:phone":"+32 57 42 94 94",
    "sg:postcode":"8900",
    "sg:province":"West-Vlaanderen",
    "sg:tags":[
        "refrigeration",
        "-",
        "industrial",
        "commercial",
        "equipment"
    ],
    "wof:name":"Feys-pattyn/akf",
    "wof:placetype":"venue"
},
  "geometry": {"coordinates":[2.8846380711,50.8590621948],"type":"Point"}
}