{
  "type": "Feature",
  "properties": {
    "addr:full":"Rue De Bruxelles 24 Edingen/enghien Hainaut 7850",
    "addr:housenumber":"24",
    "addr:postcode":"7850",
    "addr:street":"Rue De Bruxelles",
    "iso:country":"BE",
    "sg:address":"Rue De Bruxelles 24",
    "sg:city":"Edingen/enghien",
    "sg:orig_category":"Boucheries",
    "sg:phone":"+32 2 395 74 08",
    "sg:postcode":"7850",
    "sg:province":"Hainaut",
    "wof:name":"Carfood",
    "wof:placetype":"venue"
},
  "geometry": {"coordinates":[4.0402879715,50.6941604614],"type":"Point"}
}