{
  "type": "Feature",
  "properties": {
    "iso:country":"BE",
    "sg:address":"Kapellebaan 58",
    "sg:city":"Berlaar",
    "sg:orig_category":"Electrom\u00e9nager, t\u00e9l\u00e9visions and radios",
    "sg:phone":"+32 3 482 15 58",
    "sg:postcode":"2590",
    "sg:province":"Antwerpen",
    "wof:name":"Service Center Truyen",
    "wof:placetype":"venue"
},
  "geometry": {"coordinates":[4.6482901573,51.1150054932],"type":"Point"}
}