{
  "type": "Feature",
  "properties": {
    "iso:country":"BE",
    "sg:address":"Terlindenstraat 67",
    "sg:city":"Ternat",
    "sg:orig_category":"Rundveehouders",
    "sg:phone":"+32 2 582 16 19",
    "sg:postcode":"1740",
    "sg:province":"Vlaams-Brabant",
    "wof:name":"Mauritz Rooseleir",
    "wof:placetype":"venue"
},
  "geometry": {"coordinates":[4.1661500931,50.8681297302],"type":"Point"}
}