{
  "type": "Feature",
  "properties": {
    "addr:full":"Tinnenpotstraat 28 Izegem West-Vlaanderen 8870",
    "addr:housenumber":"28",
    "addr:postcode":"8870",
    "addr:street":"Tinnenpotstraat",
    "iso:country":"BE",
    "sg:address":"Tinnenpotstraat 28",
    "sg:city":"Izegem",
    "sg:orig_category":"Magasins sp\u00e9cialis\u00e9s. Mat\u00e9riaux de construction Rev\u00eatements pour sols and murs",
    "sg:phone":"+32 51 30 22 91",
    "sg:postcode":"8870",
    "sg:province":"West-Vlaanderen",
    "wof:name":"Cornillie",
    "wof:placetype":"venue"
},
  "geometry": {"coordinates":[3.2128939629,50.9368629456],"type":"Point"}
}