{
  "type": "Feature",
  "properties": {
    "iso:country":"BE",
    "sg:address":"Rozendalestraat 106",
    "sg:city":"Wingene",
    "sg:orig_category":"Groententeelt Rundveehouders",
    "sg:phone":"+32 51 65 72 22",
    "sg:postcode":"8750",
    "sg:province":"West-Vlaanderen",
    "wof:name":"Lanckriet-dendoncker",
    "wof:placetype":"venue"
},
  "geometry": {"coordinates":[3.2538321018,51.0850410461],"type":"Point"}
}