{
  "type": "Feature",
  "properties": {
    "iso:country":"BE",
    "sg:address":"Rue Du Miroir 7",
    "sg:city":"Florenville",
    "sg:orig_category":"Enseignement maternel and primaire",
    "sg:phone":"+32 61 31 12 71",
    "sg:postcode":"6820",
    "sg:province":"Luxembourg",
    "wof:name":"Ecole Fondamentale",
    "wof:placetype":"venue"
},
  "geometry": {"coordinates":[5.3120450974,49.6960105896],"type":"Point"}
}