{
  "type": "Feature",
  "properties": {
    "addr:full":"Rue Reine Astrid 236 La Louvi\u00e8re (maurage) Hainaut 7110",
    "addr:housenumber":"236",
    "addr:postcode":"7110",
    "addr:street":"Rue Reine Astrid",
    "iso:country":"BE",
    "sg:address":"Rue Reine Astrid 236",
    "sg:city":"La Louvi\u00e8re (maurage)",
    "sg:classifiers":[
        {
            "category":"Health Services",
            "subcategory":"Nursing And Care Facility",
            "type":"Services"
        }
    ],
    "sg:phone":"+32 64 66 28 65",
    "sg:postcode":"7110",
    "sg:province":"Hainaut",
    "sg:tags":[
        "home",
        "rest"
    ],
    "wof:name":"R\u00e9sidence Reine Astrid Sa",
    "wof:placetype":"venue"
},
  "geometry": {"coordinates":[4.1037449837,50.4675445557],"type":"Point"}
}