{
  "type": "Feature",
  "properties": {
    "iso:country":"BE",
    "sg:address":"Rue De Huy 61",
    "sg:city":"Waremme",
    "sg:classifiers":[
        {
            "category":"Food & Beverages",
            "subcategory":"Fruits & Vegetables",
            "type":"Retail Goods"
        }
    ],
    "sg:phone":"+32 19 33 14 74",
    "sg:postcode":"4300",
    "sg:province":"Li\u00e8ge",
    "sg:tags":[
        "l\u00e9gumes"
    ],
    "wof:name":"La Jardini\u00c8re",
    "wof:placetype":"venue"
},
  "geometry": {"coordinates":[5.2513780594,50.6919937134],"type":"Point"}
}