{
  "type": "Feature",
  "properties": {
    "addr:full":"Vrijheid 86 Hoogstraten Antwerpen 2320",
    "addr:housenumber":"86",
    "addr:postcode":"2320",
    "addr:street":"Vrijheid",
    "iso:country":"BE",
    "sg:address":"Vrijheid 86",
    "sg:city":"Hoogstraten",
    "sg:classifiers":[
        {
            "category":"Food & Beverages",
            "subcategory":"Specialty",
            "type":"Retail Goods"
        }
    ],
    "sg:phone":"+32 3 314 32 82",
    "sg:postcode":"2320",
    "sg:province":"Antwerpen",
    "sg:tags":[
        "health",
        "dietary",
        "-",
        "biological"
    ],
    "wof:name":"Pastinakel (de)",
    "wof:placetype":"venue"
},
  "geometry": {"coordinates":[4.7624502182,51.4045295715],"type":"Point"}
}