{
  "type": "Feature",
  "properties": {
    "addr:full":"Canadalaan 109 Antwerpen Antwerpen 2030",
    "addr:housenumber":"109",
    "addr:postcode":"2030",
    "addr:street":"Canadalaan",
    "iso:country":"BE",
    "sg:address":"Canadalaan 109",
    "sg:city":"Antwerpen",
    "sg:classifiers":[
        {
            "category":"Bars & Pubs",
            "type":"Food & Drink"
        }
    ],
    "sg:phone":"+32 3 541 71 94",
    "sg:postcode":"2030",
    "sg:province":"Antwerpen",
    "wof:name":"Centrum Luchtbal",
    "wof:placetype":"venue"
},
  "geometry": {"coordinates":[4.4214100838,51.2514953613],"type":"Point"}
}