{
  "type": "Feature",
  "properties": {
    "iso:country":"BE",
    "sg:address":"Stationsstraat 82",
    "sg:city":"Alken",
    "sg:classifiers":[
        {
            "category":"Personal",
            "subcategory":"Beauty Salon",
            "type":"Services"
        }
    ],
    "sg:phone":"+32 11 59 66 55",
    "sg:postcode":"3570",
    "sg:province":"Limburg",
    "sg:tags":[
        "de",
        "coiffure"
    ],
    "wof:name":"Karl-heinz Neubert",
    "wof:placetype":"venue"
},
  "geometry": {"coordinates":[5.2968521118,50.8846588135],"type":"Point"}
}