{
  "type": "Feature",
  "properties": {
    "iso:country":"BE",
    "sg:address":"Deinzestraat 7",
    "sg:city":"Deinze (vinkt)",
    "sg:classifiers":[
        {
            "category":"Retail",
            "subcategory":"Repair Shop",
            "type":"Services"
        }
    ],
    "sg:phone":"+32 9 386 91 91",
    "sg:postcode":"9800",
    "sg:province":"Oost-Vlaanderen",
    "wof:name":"Animfood",
    "wof:placetype":"venue"
},
  "geometry": {"coordinates":[3.4788789749,51.0074081421],"type":"Point"}
}