{
  "type": "Feature",
  "properties": {
    "iso:country":"BE",
    "sg:address":"Rue Du Patch 8",
    "sg:city":"Rixensart",
    "sg:orig_category":"Non-Classified Establishments",
    "sg:phone":"+32 2 653 56 28",
    "sg:postcode":"1330",
    "sg:province":"Brabant Wallon",
    "wof:name":"Pilgrim Sprl",
    "wof:placetype":"venue"
},
  "geometry": {"coordinates":[4.5294709206,50.7162475586],"type":"Point"}
}