{
  "type": "Feature",
  "properties": {
    "iso:country":"BE",
    "sg:address":"Lakenstraat 93",
    "sg:city":"Roeselare",
    "sg:classifiers":[
        {
            "category":"Health Services",
            "subcategory":"Health Practitioner",
            "type":"Services"
        }
    ],
    "sg:phone":"+32 51 24 01 20",
    "sg:postcode":"8800",
    "sg:province":"West-Vlaanderen",
    "sg:tags":[
        "physiotherapist"
    ],
    "wof:name":"Vermandere Ph",
    "wof:placetype":"venue"
},
  "geometry": {"coordinates":[3.1145150661,50.9633903503],"type":"Point"}
}