{
  "type": "Feature",
  "properties": {
    "iso:country":"BE",
    "sg:address":"Westover 7",
    "sg:city":"Alveringem",
    "sg:orig_category":"Varkenskwekers",
    "sg:phone":"+32 58 28 82 03",
    "sg:postcode":"8690",
    "sg:province":"West-Vlaanderen",
    "wof:name":"Raphael Demol",
    "wof:placetype":"venue"
},
  "geometry": {"coordinates":[2.7168428898,51.0197067261],"type":"Point"}
}