{
  "type": "Feature",
  "properties": {
    "iso:country":"BE",
    "sg:address":"Route De Beaumont 60",
    "sg:city":"Lasne",
    "sg:orig_category":"M\u00e9decins and sp\u00e9cialistes",
    "sg:phone":"+32 2 633 11 05",
    "sg:postcode":"1380",
    "sg:province":"Brabant Wallon",
    "wof:name":"Laurent Votron",
    "wof:placetype":"venue"
},
  "geometry": {"coordinates":[4.4958457947,50.6717300415],"type":"Point"}
}