{
  "type": "Feature",
  "properties": {
    "iso:country":"BE",
    "sg:address":"Rue De Jausse 242",
    "sg:city":"Namur",
    "sg:orig_category":"Electrom\u00e9nager, t\u00e9l\u00e9visions and radios. Installation \u00e9lectrique r\u00e9sidentielle. Mat\u00e9riel de contr\u00f4le ",
    "sg:phone":"+32 81 40 12 53",
    "sg:postcode":"5100",
    "sg:province":"Namur",
    "wof:name":"Philippe Pirlot",
    "wof:placetype":"venue"
},
  "geometry": {"coordinates":[4.8713750839,50.4566345215],"type":"Point"}
}