{
  "type": "Feature",
  "properties": {
    "addr:full":"Zandvoortstr 5 Mechelen Antwerpen 2800",
    "addr:housenumber":"5",
    "addr:postcode":"2800",
    "addr:street":"Zandvoortstr",
    "iso:country":"BE",
    "sg:address":"Zandvoortstr 5",
    "sg:city":"Mechelen",
    "sg:classifiers":[
        {
            "category":"Shopping",
            "subcategory":"Computers & Home Electronics",
            "type":"Retail Goods"
        }
    ],
    "sg:phone":"+32 15 28 89 60",
    "sg:postcode":"2800",
    "sg:province":"Antwerpen",
    "sg:tags":[
        "information",
        "peripheral",
        "-",
        "technology"
    ],
    "wof:name":"Dicom Benelux Nv",
    "wof:placetype":"venue"
},
  "geometry": {"coordinates":[4.4450678825,51.050151825],"type":"Point"}
}