{
  "type": "Feature",
  "properties": {
    "iso:country":"BE",
    "sg:address":"Rue De L'yser 14",
    "sg:city":"Tournai",
    "sg:classifiers":[
        {
            "category":"Shopping",
            "subcategory":"Clothing, Apparel, & Fashions",
            "type":"Retail Goods"
        }
    ],
    "sg:phone":"+32 69 23 38 76",
    "sg:postcode":"7500",
    "sg:province":"Hainaut",
    "sg:tags":[
        "lady",
        "clothing",
        "-"
    ],
    "wof:name":"Cent Facons",
    "wof:placetype":"venue"
},
  "geometry": {"coordinates":[3.3861429691,50.6077232361],"type":"Point"}
}