{
  "type": "Feature",
  "properties": {
    "addr:full":"Chauss\u00c9e D'ophain 12 Braine-le-chateau Brabant Wallon 1440",
    "addr:housenumber":"12",
    "addr:postcode":"1440",
    "addr:street":"Chausse\u0301E D'Ophain;Brabant Wallon",
    "iso:country":"BE",
    "sg:address":"Chauss\u00c9e D'ophain 12",
    "sg:city":"Braine-le-chateau",
    "sg:orig_category":"Plomberie, chauffage and installations sanitaires",
    "sg:phone":"+32 2 366 12 50",
    "sg:postcode":"1440",
    "sg:province":"Brabant Wallon",
    "wof:name":"Jean Grislain",
    "wof:placetype":"venue"
},
  "geometry": {"coordinates":[4.325387001,50.6836357117],"type":"Point"}
}