{
  "type": "Feature",
  "properties": {
    "iso:country":"BE",
    "sg:address":"Wayenborgstraat 9b2",
    "sg:city":"Mechelen",
    "sg:orig_category":"Mat\u00e9riaux de construction Gr",
    "sg:phone":"+32 15 20 64 80",
    "sg:postcode":"2800",
    "sg:province":"Antwerpen",
    "wof:name":"Rosco",
    "wof:placetype":"venue"
},
  "geometry": {"coordinates":[4.4427142143,51.0496559143],"type":"Point"}
}