{
  "type": "Feature",
  "properties": {
    "iso:country":"BE",
    "sg:address":"Stationsstraat 7",
    "sg:city":"Sint-truiden",
    "sg:orig_category":"Fotografen and fotostudio's",
    "sg:phone":"+32 11 68 76 02",
    "sg:postcode":"3800",
    "sg:province":"Limburg",
    "wof:name":"Dileen",
    "wof:placetype":"venue"
},
  "geometry": {"coordinates":[5.1798200607,50.8159828186],"type":"Point"}
}