{
  "type": "Feature",
  "properties": {
    "iso:country":"BE",
    "sg:address":"Rijselsestraat 20",
    "sg:city":"Ieper",
    "sg:classifiers":[
        {
            "category":"Shopping",
            "subcategory":"Crafts & Fabrics",
            "type":"Retail Goods"
        }
    ],
    "sg:phone":"+32 57 20 15 42",
    "sg:postcode":"8900",
    "sg:province":"West-Vlaanderen",
    "sg:tags":[
        "-",
        "wool",
        "knitting",
        "yarn"
    ],
    "wof:name":"Crealini",
    "wof:placetype":"venue"
},
  "geometry": {"coordinates":[2.8858590126,50.8502197266],"type":"Point"}
}