{
  "type": "Feature",
  "properties": {
    "iso:country":"BE",
    "sg:address":"Koning Albertstraat 8",
    "sg:city":"Ardooie",
    "sg:orig_category":"Protection civile",
    "sg:phone":"+32 51 74 58 75",
    "sg:postcode":"8850",
    "sg:province":"West-Vlaanderen",
    "wof:name":"Brandweerkazerne",
    "wof:placetype":"venue"
},
  "geometry": {"coordinates":[3.1948859692,50.9778823853],"type":"Point"}
}