{
  "type": "Feature",
  "properties": {
    "iso:country":"BE",
    "sg:address":"Rue De La Poudri\u00c8re 57",
    "sg:city":"Quaregnon",
    "sg:orig_category":"Elektrische installaties voor woningen",
    "sg:phone":"+32 65 77 72 39",
    "sg:postcode":"7390",
    "sg:province":"Hainaut",
    "wof:name":"S.t.e.c.",
    "wof:placetype":"venue"
},
  "geometry": {"coordinates":[3.8566739559,50.4349250793],"type":"Point"}
}