{
  "type": "Feature",
  "properties": {
    "iso:country":"BE",
    "sg:address":"Kruisstraat 26",
    "sg:city":"Zomergem",
    "sg:orig_category":"Rundveehouders",
    "sg:phone":"+32 9 372 72 84",
    "sg:postcode":"9930",
    "sg:province":"Oost-Vlaanderen",
    "wof:name":"Andr\u00c9 Van Den Berghe",
    "wof:placetype":"venue"
},
  "geometry": {"coordinates":[3.5839550495,51.110496521],"type":"Point"}
}