{
  "type": "Feature",
  "properties": {
    "iso:country":"BE",
    "sg:address":"Tongersesteenweg 24",
    "sg:city":"Riemst",
    "sg:orig_category":"Alternatieve geneeskunde Paramedische behandelingen",
    "sg:phone":"+32 12 45 53 60",
    "sg:postcode":"3770",
    "sg:province":"Limburg",
    "wof:name":"Wit-gele Kruis Riemst",
    "wof:placetype":"venue"
},
  "geometry": {"coordinates":[5.5914678574,50.8105354309],"type":"Point"}
}