{
  "type": "Feature",
  "properties": {
    "addr:full":"Putstraat 23 Maasmechelen Limburg 3630",
    "addr:housenumber":"23",
    "addr:postcode":"3630",
    "addr:street":"Putstraat",
    "iso:country":"BE",
    "sg:address":"Putstraat 23",
    "sg:city":"Maasmechelen",
    "sg:orig_category":"Artsen and specialisten",
    "sg:phone":"+32 89 76 57 71",
    "sg:postcode":"3630",
    "sg:province":"Limburg",
    "wof:name":"M. Scatorchia",
    "wof:placetype":"venue"
},
  "geometry": {"coordinates":[5.683344841,50.9791069031],"type":"Point"}
}