{
  "type": "Feature",
  "properties": {
    "addr:full":"Rue De Steppes 99 Li\u00c8ge Li\u00e8ge 4000",
    "addr:housenumber":"99",
    "addr:postcode":"4000",
    "addr:street":"Rue De Steppes",
    "iso:country":"BE",
    "sg:address":"Rue De Steppes 99",
    "sg:city":"Li\u00c8ge",
    "sg:orig_category":"Plaatsen van vloer- and muurbekleding Schilders",
    "sg:phone":"+32 4 228 72 43",
    "sg:postcode":"4000",
    "sg:province":"Li\u00e8ge",
    "wof:name":"Fe. Bati Paint",
    "wof:placetype":"venue"
},
  "geometry": {"coordinates":[5.6026268005,50.6552238464],"type":"Point"}
}