{
  "type": "Feature",
  "properties": {
    "iso:country":"BE",
    "sg:address":"Charles Coppensstraat 13",
    "sg:city":"Hoeilaart",
    "sg:orig_category":"Avocats and conseillers juridiques",
    "sg:phone":"+32 2 657 99 31",
    "sg:postcode":"1560",
    "sg:province":"Vlaams-Brabant",
    "wof:name":"A. Van Parijs",
    "wof:placetype":"venue"
},
  "geometry": {"coordinates":[4.471971035,50.762096405],"type":"Point"}
}