{
  "type": "Feature",
  "properties": {
    "iso:country":"BE",
    "sg:address":"Oudeheerweg Heide 133",
    "sg:city":"Waasmunster",
    "sg:classifiers":[
        {
            "category":"Shopping",
            "subcategory":"Florist",
            "type":"Retail Goods"
        }
    ],
    "sg:phone":"+32 9 348 97 30",
    "sg:postcode":"9250",
    "sg:province":"Oost-Vlaanderen",
    "wof:name":"Van Uytvanck A",
    "wof:placetype":"venue"
},
  "geometry": {"coordinates":[4.0471191406,51.1173400879],"type":"Point"}
}