{
  "type": "Feature",
  "properties": {
    "addr:full":"Hooimanstraat 112 Sint-niklaas (sinaai) Oost-Vlaanderen 9112",
    "addr:housenumber":"112",
    "addr:postcode":"9112",
    "addr:street":"Hooimanstraat",
    "iso:country":"BE",
    "sg:address":"Hooimanstraat 112",
    "sg:city":"Sint-niklaas (sinaai)",
    "sg:classifiers":[
        {
            "category":"Banks & Credit Unions",
            "subcategory":"Investment Brokerage",
            "type":"Services"
        }
    ],
    "sg:phone":"+32 3 722 02 85",
    "sg:postcode":"9112",
    "sg:province":"Oost-Vlaanderen",
    "sg:tags":[
        "auditor"
    ],
    "wof:name":"Schiltz D",
    "wof:placetype":"venue"
},
  "geometry": {"coordinates":[4.0559968948,51.1519165039],"type":"Point"}
}