{
  "type": "Feature",
  "properties": {
    "iso:country":"BE",
    "sg:address":"Bosstraat 88",
    "sg:city":"Maaseik",
    "sg:classifiers":[
        {
            "category":"Bakery",
            "type":"Food & Drink"
        }
    ],
    "sg:phone":"+32 89 56 40 62",
    "sg:postcode":"3680",
    "sg:province":"Limburg",
    "sg:tags":[
        "confectioner",
        "baker"
    ],
    "wof:name":"Schoubben",
    "wof:placetype":"venue"
},
  "geometry": {"coordinates":[5.7870550156,51.0957489014],"type":"Point"}
}