{
  "type": "Feature",
  "properties": {
    "addr:full":"Vaartstraat 2-18 Zandhoven Antwerpen 2240",
    "addr:housenumber":"2-18",
    "addr:postcode":"2240",
    "addr:street":"Vaartstraat",
    "iso:country":"BE",
    "sg:address":"Vaartstraat 2-18",
    "sg:city":"Zandhoven",
    "sg:classifiers":[
        {
            "category":"Professional",
            "type":"Services"
        }
    ],
    "sg:phone":"+32 3 484 55 69",
    "sg:postcode":"2240",
    "sg:province":"Antwerpen",
    "sg:tags":[
        "transport"
    ],
    "wof:name":"Verbiest Nv",
    "wof:placetype":"venue"
},
  "geometry": {"coordinates":[4.6432161331,51.196849823],"type":"Point"}
}