{
  "type": "Feature",
  "properties": {
    "iso:country":"BE",
    "sg:address":"Kortenberglaan 85",
    "sg:city":"Brussel/bruxelles",
    "sg:orig_category":"Instellingen voor mindervalide volwassenen",
    "sg:phone":"+32 2 736 81 28",
    "sg:postcode":"1000",
    "sg:province":"Bruxelles-Capitale",
    "wof:name":"Home La Cl\u00c9",
    "wof:placetype":"venue"
},
  "geometry": {"coordinates":[4.3900542259,50.844959259],"type":"Point"}
}