{
  "type": "Feature",
  "properties": {
    "iso:country":"BE",
    "sg:address":"Place De Belle-maison 20",
    "sg:city":"Marchin",
    "sg:classifiers":[
        {
            "category":"Professional",
            "subcategory":"Testing Lab",
            "type":"Services"
        }
    ],
    "sg:phone":"+32 85 21 36 70",
    "sg:postcode":"4570",
    "sg:province":"Li\u00e8ge",
    "sg:tags":[
        "chemist"
    ],
    "wof:name":"Biot",
    "wof:placetype":"venue"
},
  "geometry": {"coordinates":[5.2406201363,50.464756012],"type":"Point"}
}