{
  "type": "Feature",
  "properties": {
    "iso:country":"BE",
    "sg:address":"Beekstr 35",
    "sg:city":"Gent",
    "sg:classifiers":[
        {
            "category":"Professional",
            "subcategory":"Business Services",
            "type":"Services"
        }
    ],
    "sg:phone":"+32 9 226 60 30",
    "sg:postcode":"9031",
    "sg:province":"Oost-Vlaanderen",
    "sg:tags":[
        "travel",
        "fair"
    ],
    "wof:name":"Traiteur Ginneberge Nv",
    "wof:placetype":"venue"
},
  "geometry": {"coordinates":[3.6538579464,51.0691184998],"type":"Point"}
}