{
  "type": "Feature",
  "properties": {
    "addr:full":"Avenue Henri Conscience 177 Bruxelles (evere) Bruxelles-Capitale 1140",
    "addr:housenumber":"177",
    "addr:postcode":"1140",
    "addr:street":"Avenue Henri Conscience",
    "iso:country":"BE",
    "sg:address":"Avenue Henri Conscience 177",
    "sg:city":"Bruxelles (evere)",
    "sg:classifiers":[
        {
            "category":"Retail",
            "subcategory":"Laundry & Dry Cleaning",
            "type":"Services"
        }
    ],
    "sg:phone":"+32 2 241 60 12",
    "sg:postcode":"1140",
    "sg:province":"Bruxelles-Capitale",
    "sg:tags":[
        "dyer",
        "cleaner"
    ],
    "wof:name":"Castermans",
    "wof:placetype":"venue"
},
  "geometry": {"coordinates":[4.4000120163,50.8723564148],"type":"Point"}
}