{
  "type": "Feature",
  "properties": {
    "addr:full":"Rue Charles-bartholomez 60 Li\u00c8ge Li\u00e8ge 4020",
    "addr:housenumber":"60",
    "addr:postcode":"4020",
    "addr:street":"Rue Charles-Bartholomez",
    "iso:country":"BE",
    "sg:address":"Rue Charles-bartholomez 60",
    "sg:city":"Li\u00c8ge",
    "sg:orig_category":"Loodgieterij, verwarming and sanitaire installaties",
    "sg:phone":"+32 4 341 27 56",
    "sg:postcode":"4020",
    "sg:province":"Li\u00e8ge",
    "wof:name":"Energie Et Confort",
    "wof:placetype":"venue"
},
  "geometry": {"coordinates":[5.5903539658,50.6377334595],"type":"Point"}
}