{
  "type": "Feature",
  "properties": {
    "addr:full":"Rue Major P\u00e9tillon 70 Bruxelles (etterbeek) Bruxelles-Capitale 1040",
    "addr:housenumber":"70",
    "addr:postcode":"1040",
    "addr:street":"Rue Major Pe\u0301Tillon",
    "iso:country":"BE",
    "sg:address":"Rue Major P\u00e9tillon 70",
    "sg:city":"Bruxelles (etterbeek)",
    "sg:classifiers":[
        {
            "category":"Health Services",
            "subcategory":"Health Practitioner",
            "type":"Services"
        }
    ],
    "sg:phone":"+32 2 732 97 19",
    "sg:postcode":"1040",
    "sg:province":"Bruxelles-Capitale",
    "sg:tags":[
        "physiotherapist"
    ],
    "wof:name":"Lievens P-o",
    "wof:placetype":"venue"
},
  "geometry": {"coordinates":[4.4036121368,50.8269577026],"type":"Point"}
}