{
  "type": "Feature",
  "properties": {
    "iso:country":"BE",
    "sg:address":"Dorp-west 33",
    "sg:city":"Lochristi",
    "sg:classifiers":[
        {
            "category":"Bars & Pubs",
            "type":"Food & Drink"
        }
    ],
    "sg:phone":"+32 9 355 20 39",
    "sg:postcode":"9080",
    "sg:province":"Oost-Vlaanderen",
    "sg:tags":[
        "tavern"
    ],
    "wof:name":"Mikado Bvba",
    "wof:placetype":"venue"
},
  "geometry": {"coordinates":[3.8313839436,51.0956954956],"type":"Point"}
}