{
  "type": "Feature",
  "properties": {
    "iso:country":"BE",
    "sg:address":"Ieperstraat 260",
    "sg:city":"Zonnebeke",
    "sg:classifiers":[
        {
            "category":"Building & Trades",
            "subcategory":"Landscaping Services",
            "type":"Services"
        }
    ],
    "sg:phone":"+32 478 47 35 53",
    "sg:postcode":"8980",
    "sg:province":"West-Vlaanderen",
    "sg:tags":[
        "architect",
        "landscape"
    ],
    "wof:name":"Delva S",
    "wof:placetype":"venue"
},
  "geometry": {"coordinates":[2.9425001144,50.8673667908],"type":"Point"}
}