{
  "type": "Feature",
  "properties": {
    "addr:full":"Route De Bastogne 38 Nassogne Luxembourg 6950",
    "addr:housenumber":"38",
    "addr:postcode":"6950",
    "addr:street":"Route De Bastogne",
    "iso:country":"BE",
    "sg:address":"Route De Bastogne 38",
    "sg:city":"Nassogne",
    "sg:orig_category":"V\u00e9hicules automobiles. Entretien and r\u00e9parations de voitures",
    "sg:phone":"+32 84 34 42 50",
    "sg:postcode":"6950",
    "sg:province":"Luxembourg",
    "wof:name":"Carrosserie Delcourt",
    "wof:placetype":"venue"
},
  "geometry": {"coordinates":[5.341301918,50.1289215088],"type":"Point"}
}