{
  "type": "Feature",
  "properties": {
    "addr:full":"Rue Saint-agathe 69 Vresse-sur-semois (vresse) Namur 5550",
    "addr:housenumber":"69",
    "addr:postcode":"5550",
    "addr:street":"Rue Saint-Agathe",
    "iso:country":"BE",
    "sg:address":"Rue Saint-agathe 69",
    "sg:city":"Vresse-sur-semois (vresse)",
    "sg:classifiers":[
        {
            "category":"Health Services",
            "subcategory":"Health Practitioner",
            "type":"Services"
        }
    ],
    "sg:phone":"+32 61 50 09 50",
    "sg:postcode":"5550",
    "sg:province":"Namur",
    "sg:tags":[
        "physiotherapist"
    ],
    "wof:name":"B\u00e9riot A",
    "wof:placetype":"venue"
},
  "geometry": {"coordinates":[4.9307308197,49.8651008606],"type":"Point"}
}