{
  "type": "Feature",
  "properties": {
    "addr:full":"Rue Louis Pi\u00c9rard 1 Mons Hainaut 7022",
    "addr:housenumber":"1",
    "addr:postcode":"7022",
    "addr:street":"Rue Louis Pie\u0301Rard;Hainaut",
    "iso:country":"BE",
    "sg:address":"Rue Louis Pi\u00c9rard 1",
    "sg:city":"Mons",
    "sg:orig_category":"Enseignement maternel and primaire",
    "sg:phone":"+32 65 31 48 40",
    "sg:postcode":"7022",
    "sg:province":"Hainaut",
    "wof:name":"Ecole Fond. Communale",
    "wof:placetype":"venue"
},
  "geometry": {"coordinates":[3.9602999687,50.440158844],"type":"Point"}
}