{
  "type": "Feature",
  "properties": {
    "addr:full":"Drongensesteenweg 17 Gent Oost-Vlaanderen 9000",
    "addr:housenumber":"17",
    "addr:postcode":"9000",
    "addr:street":"Drongensesteenweg;Oost-Vlaanderen",
    "iso:country":"BE",
    "sg:address":"Drongensesteenweg 17",
    "sg:city":"Gent",
    "sg:orig_category":"Boucheries",
    "sg:phone":"+32 9 226 58 55",
    "sg:postcode":"9000",
    "sg:province":"Oost-Vlaanderen",
    "wof:name":"Beenhouwerij Marcel",
    "wof:placetype":"venue"
},
  "geometry": {"coordinates":[3.7014300823,51.0574417114],"type":"Point"}
}