{
  "type": "Feature",
  "properties": {
    "iso:country":"BE",
    "sg:address":"Rue Du Ruisseau 30",
    "sg:city":"Esneux (tilff)",
    "sg:classifiers":[
        {
            "category":"Health Services",
            "subcategory":"Doctor",
            "type":"Services"
        }
    ],
    "sg:phone":"+32 4 388 22 74",
    "sg:postcode":"4130",
    "sg:province":"Li\u00e8ge",
    "sg:tags":[
        "medicinephysicians",
        "surgeon"
    ],
    "wof:name":"Boca Philippe",
    "wof:placetype":"venue"
},
  "geometry": {"coordinates":[5.5954470634,50.5661010742],"type":"Point"}
}