{
  "type": "Feature",
  "properties": {
    "iso:country":"BE",
    "sg:address":"Rue De L'equip\u00e9e 69",
    "sg:city":"Seneffe (feluy)",
    "sg:classifiers":[
        {
            "category":"Food & Beverages",
            "subcategory":"Meat & Fish",
            "type":"Retail Goods"
        }
    ],
    "sg:phone":"+32 67 87 90 36",
    "sg:postcode":"7181",
    "sg:province":"Hainaut",
    "sg:tags":[
        "-",
        "livestock"
    ],
    "wof:name":"Bauduin R",
    "wof:placetype":"venue"
},
  "geometry": {"coordinates":[4.2671570778,50.5615768433],"type":"Point"}
}