{
  "type": "Feature",
  "properties": {
    "iso:country":"BE",
    "sg:address":"Hoevensebaan 100",
    "sg:city":"Kapellen",
    "sg:classifiers":[
        {
            "category":"Restaurant",
            "type":"Food & Drink"
        }
    ],
    "sg:phone":"+32 3 605 08 57",
    "sg:postcode":"2950",
    "sg:province":"Antwerpen",
    "wof:name":"'t Schuurken",
    "wof:placetype":"venue"
},
  "geometry": {"coordinates":[4.4244332314,51.3132171631],"type":"Point"}
}