{
  "type": "Feature",
  "properties": {
    "addr:full":"Sint-pieterskaai 78 Brugge West-Vlaanderen 8000",
    "addr:housenumber":"78",
    "addr:postcode":"8000",
    "addr:street":"Sint-Pieterskaai",
    "iso:country":"BE",
    "sg:address":"Sint-pieterskaai 78",
    "sg:city":"Brugge",
    "sg:orig_category":"Meubles D\u00e9taillants, Am\u00e9nagement de B\u00e2timents et de Cuisines",
    "sg:phone":"+32 50 34 53 74",
    "sg:postcode":"8000",
    "sg:province":"West-Vlaanderen",
    "wof:name":"Leder Nr1",
    "wof:placetype":"venue"
},
  "geometry": {"coordinates":[3.2270290852,51.2227554321],"type":"Point"}
}