{
  "type": "Feature",
  "properties": {
    "addr:full":"Kerkstraat 301 Blankenberge West-Vlaanderen 8370",
    "addr:housenumber":"301",
    "addr:postcode":"8370",
    "addr:street":"Kerkstraat",
    "iso:country":"BE",
    "sg:address":"Kerkstraat 301",
    "sg:city":"Blankenberge",
    "sg:orig_category":"V\u00eatements sur mesure Fab",
    "sg:phone":"+32 50 41 03 00",
    "sg:postcode":"8370",
    "sg:province":"West-Vlaanderen",
    "wof:name":"Elisabeth Pirlet",
    "wof:placetype":"venue"
},
  "geometry": {"coordinates":[3.1386539936,51.3070678711],"type":"Point"}
}