{
  "type": "Feature",
  "properties": {
    "iso:country":"BE",
    "sg:address":"Roeselarestraat 70",
    "sg:city":"Zonnebeke",
    "sg:orig_category":"Loodgieterij, verwarming and sanitaire installaties",
    "sg:phone":"+32 51 77 16 06",
    "sg:postcode":"8980",
    "sg:province":"West-Vlaanderen",
    "wof:name":"Filiep Pauwels",
    "wof:placetype":"venue"
},
  "geometry": {"coordinates":[2.998570919,50.8756866455],"type":"Point"}
}