{
  "type": "Feature",
  "properties": {
    "addr:full":"Evendijk-oost 89 Blankenberge West-Vlaanderen 8370",
    "addr:housenumber":"89",
    "addr:postcode":"8370",
    "addr:street":"Evendijk-Oost",
    "iso:country":"BE",
    "sg:address":"Evendijk-oost 89",
    "sg:city":"Blankenberge",
    "sg:orig_category":"Rev\u00eatements pour sols and murs. Rev\u00eatements de sols and murs",
    "sg:phone":"+32 50 41 22 18",
    "sg:postcode":"8370",
    "sg:province":"West-Vlaanderen",
    "wof:name":"Vander Cruysse",
    "wof:placetype":"venue"
},
  "geometry": {"coordinates":[3.1392140388,51.3084030151],"type":"Point"}
}