{
  "type": "Feature",
  "properties": {
    "iso:country":"BE",
    "sg:address":"Nijven 33",
    "sg:city":"Sint-amands",
    "sg:orig_category":"Producteurs de l\u00e9gumes",
    "sg:phone":"+32 3 899 29 12",
    "sg:postcode":"2890",
    "sg:province":"Antwerpen",
    "wof:name":"Marc Van Der Plas",
    "wof:placetype":"venue"
},
  "geometry": {"coordinates":[4.2386341095,51.0595855713],"type":"Point"}
}