{
  "type": "Feature",
  "properties": {
    "iso:country":"BE",
    "sg:address":"Markt 23",
    "sg:city":"Zele",
    "sg:classifiers":[
        {
            "category":"Shopping",
            "subcategory":"Clothing, Apparel, & Fashions",
            "type":"Retail Goods"
        }
    ],
    "sg:phone":"+32 52 44 66 08",
    "sg:postcode":"9240",
    "sg:province":"Oost-Vlaanderen",
    "sg:tags":[
        "boutique"
    ],
    "wof:name":"Ness (kleding)",
    "wof:placetype":"venue"
},
  "geometry": {"coordinates":[4.0386958122,51.0678901672],"type":"Point"}
}