{
  "type": "Feature",
  "properties": {
    "iso:country":"BE",
    "sg:address":"Boudewijnlaan 92",
    "sg:city":"Zandhoven",
    "sg:classifiers":[
        {
            "category":"Cafe",
            "type":"Food & Drink"
        }
    ],
    "sg:phone":"+32 3 484 34 34",
    "sg:postcode":"2243",
    "sg:province":"Antwerpen",
    "sg:tags":[
        "caf\u00e9s"
    ],
    "wof:name":"Het Hoefijzer",
    "wof:placetype":"venue"
},
  "geometry": {"coordinates":[4.7150168419,51.2024841309],"type":"Point"}
}