{
  "type": "Feature",
  "properties": {
    "iso:country":"BE",
    "sg:address":"Stoofstraat 11",
    "sg:city":"Merchtem",
    "sg:classifiers":[
        {
            "category":"Deli",
            "type":"Food & Drink"
        }
    ],
    "sg:phone":"+32 52 37 32 67",
    "sg:postcode":"1785",
    "sg:province":"Vlaams-Brabant",
    "sg:tags":[
        "delicatessen"
    ],
    "wof:name":"Chick & Co Bvba",
    "wof:placetype":"venue"
},
  "geometry": {"coordinates":[4.2331771851,50.9572029114],"type":"Point"}
}