{
  "type": "Feature",
  "properties": {
    "addr:full":"Dorpsplein 2 Lendelede West-Vlaanderen 8860",
    "addr:housenumber":"2",
    "addr:postcode":"8860",
    "addr:street":"Dorpsplein",
    "iso:country":"BE",
    "sg:address":"Dorpsplein 2",
    "sg:city":"Lendelede",
    "sg:classifiers":[
        {
            "category":"Education",
            "subcategory":"School",
            "type":"Public Place"
        }
    ],
    "sg:phone":"+32 51 30 20 53",
    "sg:postcode":"8860",
    "sg:province":"West-Vlaanderen",
    "sg:tags":[
        "secondary"
    ],
    "wof:name":"Middenschool St-vincentius",
    "wof:placetype":"venue"
},
  "geometry": {"coordinates":[3.2383189201,50.8861961365],"type":"Point"}
}