{
  "type": "Feature",
  "properties": {
    "iso:country":"BE",
    "sg:address":"Sterrenlaan 7",
    "sg:city":"Beersel",
    "sg:orig_category":"Agences d'exp\u00e9dition",
    "sg:phone":"+32 2 380 80 47",
    "sg:postcode":"1652",
    "sg:province":"Vlaams-Brabant",
    "wof:name":"Imexky",
    "wof:placetype":"venue"
},
  "geometry": {"coordinates":[4.3522357941,50.7519950867],"type":"Point"}
}