{
  "type": "Feature",
  "properties": {
    "addr:full":"Parvis St.-jean-baptiste 16 Sint-jans-molenbeek/molenbeek-saint-jean Bruxelles-Capitale 1080",
    "addr:housenumber":"16",
    "addr:postcode":"1080",
    "addr:street":"Parvis St.-Jean-Baptiste",
    "iso:country":"BE",
    "sg:address":"Parvis St.-jean-baptiste 16",
    "sg:city":"Sint-jans-molenbeek/molenbeek-saint-jean",
    "sg:orig_category":"M\u00e9decins and sp\u00e9cialistes",
    "sg:phone":"+32 2 410 45 64",
    "sg:postcode":"1080",
    "sg:province":"Bruxelles-Capitale",
    "wof:name":"M. Abouayad",
    "wof:placetype":"venue"
},
  "geometry": {"coordinates":[4.3390288353,50.8564414978],"type":"Point"}
}