{
  "type": "Feature",
  "properties": {
    "addr:full":"Lierseweg 258 Herentals Antwerpen 2200",
    "addr:housenumber":"258",
    "addr:postcode":"2200",
    "addr:street":"Lierseweg",
    "iso:country":"BE",
    "sg:address":"Lierseweg 258",
    "sg:city":"Herentals",
    "sg:orig_category":"Woningbouw",
    "sg:phone":"+32 14 22 03 75",
    "sg:postcode":"2200",
    "sg:province":"Antwerpen",
    "wof:name":"Bouwonderneming Vervoort",
    "wof:placetype":"venue"
},
  "geometry": {"coordinates":[4.8037600517,51.1730384827],"type":"Point"}
}