{
  "type": "Feature",
  "properties": {
    "addr:full":"Rue Du Tissage 0 Moeskroen/mouscron Hainaut 7700",
    "addr:housenumber":"0",
    "addr:postcode":"7700",
    "addr:street":"Rue Du Tissage",
    "iso:country":"BE",
    "sg:address":"Rue Du Tissage 0",
    "sg:city":"Moeskroen/mouscron",
    "sg:orig_category":"D\u00e9chets and d\u00e9bris Gr",
    "sg:phone":"+32 56 33 67 00",
    "sg:postcode":"7700",
    "sg:province":"Hainaut",
    "wof:name":"Revalor",
    "wof:placetype":"venue"
},
  "geometry": {"coordinates":[3.2323200703,50.7400932312],"type":"Point"}
}