{
  "type": "Feature",
  "properties": {
    "iso:country":"BE",
    "sg:address":"Charles Coppensstraat 46",
    "sg:city":"Hoeilaart",
    "sg:orig_category":"Diverse grafische activiteiten",
    "sg:phone":"+32 2 657 99 04",
    "sg:postcode":"1560",
    "sg:province":"Vlaams-Brabant",
    "wof:name":"Lay-out Shop",
    "wof:placetype":"venue"
},
  "geometry": {"coordinates":[4.471432209,50.7616615295],"type":"Point"}
}