{
  "type": "Feature",
  "properties": {
    "iso:country":"BE",
    "sg:address":"Eikenboslaan 56",
    "sg:city":"Ukkel/uccle",
    "sg:orig_category":"Airconditioning and ventilatie Loodgieterij and centrale verwarming Gh Loodgieterij, verwarming and ",
    "sg:phone":"+32 2 374 85 62",
    "sg:postcode":"1180",
    "sg:province":"Bruxelles-Capitale",
    "wof:name":"Airtechnic Service",
    "wof:placetype":"venue"
},
  "geometry": {"coordinates":[4.3525681496,50.7864341736],"type":"Point"}
}