{
  "type": "Feature",
  "properties": {
    "iso:country":"BE",
    "sg:address":"Rue Des Sautes 1a",
    "sg:city":"Namur",
    "sg:orig_category":"Woningbouw",
    "sg:phone":"+32 81 44 03 54",
    "sg:postcode":"5100",
    "sg:province":"Namur",
    "wof:name":"Entrepr. G\u00c9n. Vandermiege",
    "wof:placetype":"venue"
},
  "geometry": {"coordinates":[4.8713750839,50.4566345215],"type":"Point"}
}