{
  "type": "Feature",
  "properties": {
    "iso:country":"BE",
    "sg:address":"Rue De La Chapelle 3",
    "sg:city":"Somme-leuze",
    "sg:classifiers":[
        {
            "category":"Manufacturing",
            "subcategory":"Textiles",
            "type":"Manufacturing & Wholesale Goods"
        }
    ],
    "sg:phone":"+32 84 31 39 03",
    "sg:postcode":"5377",
    "sg:province":"Namur",
    "wof:name":"Th\u00c9o Kool",
    "wof:placetype":"venue"
},
  "geometry": {"coordinates":[5.3424677849,50.2800674438],"type":"Point"}
}