{
  "type": "Feature",
  "properties": {
    "iso:country":"BE",
    "sg:address":"Rue Fran\u00e7ois Dorz\u00e9e 131",
    "sg:city":"Boussu",
    "sg:classifiers":[
        {
            "category":"Real Estate",
            "subcategory":"Architect",
            "type":"Services"
        }
    ],
    "sg:phone":"+32 65 75 54 06",
    "sg:postcode":"7300",
    "sg:province":"Hainaut",
    "wof:name":"Ray S",
    "wof:placetype":"venue"
},
  "geometry": {"coordinates":[3.8025300503,50.4320297241],"type":"Point"}
}