{
  "type": "Feature",
  "properties": {
    "addr:full":"Brandenstraat 21 Leuven (wilsele) Vlaams-Brabant 3012",
    "addr:housenumber":"21",
    "addr:postcode":"3012",
    "addr:street":"Brandenstraat",
    "iso:country":"BE",
    "sg:address":"Brandenstraat 21",
    "sg:city":"Leuven (wilsele)",
    "sg:classifiers":[
        {
            "category":"Manufacturing",
            "subcategory":"Musical Instruments",
            "type":"Manufacturing & Wholesale Goods"
        }
    ],
    "sg:phone":"+32 16 20 32 13",
    "sg:postcode":"3012",
    "sg:province":"Vlaams-Brabant",
    "sg:tags":[
        "repair",
        "mainten",
        "-"
    ],
    "wof:name":"A.a.o. Joris Herman",
    "wof:placetype":"venue"
},
  "geometry": {"coordinates":[4.7050309181,50.9025802612],"type":"Point"}
}