{
  "type": "Feature",
  "properties": {
    "addr:full":"Place Verte 30 Dour Hainaut 7370",
    "addr:housenumber":"30",
    "addr:postcode":"7370",
    "addr:street":"Place Verte;Hainaut",
    "iso:country":"BE",
    "sg:address":"Place Verte 30",
    "sg:city":"Dour",
    "sg:classifiers":[
        {
            "category":"Shopping",
            "subcategory":"Gifts & Souvenirs",
            "type":"Retail Goods"
        }
    ],
    "sg:phone":"+32 65 65 24 85",
    "sg:postcode":"7370",
    "sg:province":"Hainaut",
    "sg:tags":[
        "-"
    ],
    "wof:name":"A La Bonne Source",
    "wof:placetype":"venue"
},
  "geometry": {"coordinates":[3.7881000042,50.3984794617],"type":"Point"}
}