{
  "type": "Feature",
  "properties": {
    "iso:country":"BE",
    "sg:address":"Wijnbergstraat 40-42",
    "sg:city":"Wevelgem",
    "sg:classifiers":[
        {
            "category":"Shopping",
            "subcategory":"Florist",
            "type":"Retail Goods"
        }
    ],
    "sg:phone":"+32 56 40 21 51",
    "sg:postcode":"8560",
    "sg:province":"West-Vlaanderen",
    "wof:name":"Ter Wijnberge Bloemen",
    "wof:placetype":"venue"
},
  "geometry": {"coordinates":[3.1756629944,50.8186607361],"type":"Point"}
}