{
  "type": "Feature",
  "properties": {
    "iso:country":"BE",
    "sg:address":"Rue Jean-mathieu-nisen 18",
    "sg:city":"Li\u00e8ge 1 (li\u00e8ge 2)",
    "sg:classifiers":[
        {
            "category":"Health Services",
            "subcategory":"Dentist",
            "type":"Services"
        }
    ],
    "sg:phone":"+32 4 342 62 82",
    "sg:postcode":"4020",
    "sg:province":"Li\u00e8ge",
    "wof:name":"Longdoz Monique",
    "wof:placetype":"venue"
},
  "geometry": {"coordinates":[5.6015467644,50.6461257935],"type":"Point"}
}