{
  "type": "Feature",
  "properties": {
    "iso:country":"BE",
    "sg:address":"Astridlaan 52",
    "sg:city":"Overpelt",
    "sg:classifiers":[
        {
            "category":"Shopping",
            "subcategory":"Antiques",
            "type":"Retail Goods"
        }
    ],
    "sg:phone":"+32 11 66 30 80",
    "sg:postcode":"3900",
    "sg:province":"Limburg",
    "wof:name":"Compen Bvba",
    "wof:placetype":"venue"
},
  "geometry": {"coordinates":[5.4111180305,51.2099571228],"type":"Point"}
}