{
  "type": "Feature",
  "properties": {
    "addr:full":"Vooruitgangsstraat 2 Willebroek Antwerpen 2830",
    "addr:housenumber":"2",
    "addr:postcode":"2830",
    "addr:street":"Vooruitgangsstraat",
    "iso:country":"BE",
    "sg:address":"Vooruitgangsstraat 2",
    "sg:city":"Willebroek",
    "sg:orig_category":"Newspapers, magazines, periodicals - Publishers",
    "sg:phone":"+32 3 886 65 02",
    "sg:postcode":"2830",
    "sg:province":"Antwerpen",
    "wof:name":"Fotosetting D En P",
    "wof:placetype":"venue"
},
  "geometry": {"coordinates":[4.3624582291,51.0567054749],"type":"Point"}
}