{
  "type": "Feature",
  "properties": {
    "addr:full":"Rue De Hannut 32 Orp-jauche (marilles) Brabant Wallon 1350",
    "addr:housenumber":"32",
    "addr:postcode":"1350",
    "addr:street":"Rue De Hannut",
    "iso:country":"BE",
    "sg:address":"Rue De Hannut 32",
    "sg:city":"Orp-jauche (marilles)",
    "sg:classifiers":[
        {
            "category":"Professional",
            "subcategory":"Accounting & Tax Preparation",
            "type":"Services"
        }
    ],
    "sg:phone":"+32 19 63 61 64",
    "sg:postcode":"1350",
    "sg:province":"Brabant Wallon",
    "sg:tags":[
        "bookkeeper"
    ],
    "wof:name":"Soficount Sprl",
    "wof:placetype":"venue"
},
  "geometry": {"coordinates":[4.9428400993,50.7051010132],"type":"Point"}
}