{
  "type": "Feature",
  "properties": {
    "iso:country":"BE",
    "sg:address":"Hollandstraat 64",
    "sg:city":"Heist-op-den-berg",
    "sg:orig_category":"Rundveehouders Varkenskwekers",
    "sg:phone":"+32 15 23 32 49",
    "sg:postcode":"2220",
    "sg:province":"Antwerpen",
    "wof:name":"Hendrik Spits",
    "wof:placetype":"venue"
},
  "geometry": {"coordinates":[4.7042398453,51.0447502136],"type":"Point"}
}