{
  "type": "Feature",
  "properties": {
    "iso:country":"BE",
    "sg:address":"Rue De La Paix 16",
    "sg:city":"Dour",
    "sg:orig_category":"D\u00e9taillants en pi\u00e8ces and accessoires de voitures. Entretien and r\u00e9parations de voitures",
    "sg:phone":"+32 65 65 59 12",
    "sg:postcode":"7370",
    "sg:province":"Hainaut",
    "wof:name":"Jean-paul Doye",
    "wof:placetype":"venue"
},
  "geometry": {"coordinates":[3.7553050518,50.3979682922],"type":"Point"}
}