{
  "type": "Feature",
  "properties": {
    "iso:country":"BE",
    "sg:address":"Eenbeekstraat 2",
    "sg:city":"Destelbergen",
    "sg:classifiers":[
        {
            "category":"Real Estate",
            "subcategory":"Architect",
            "type":"Services"
        }
    ],
    "sg:phone":"+32 9 228 63 21",
    "sg:postcode":"9070",
    "sg:province":"Oost-Vlaanderen",
    "wof:name":"Van Nieuwenburg E",
    "wof:placetype":"venue"
},
  "geometry": {"coordinates":[3.7910819054,51.05676651],"type":"Point"}
}