{
  "type": "Feature",
  "properties": {
    "addr:full":"Grootgodshuisstraat 22 Brussel/bruxelles Bruxelles-Capitale 1000",
    "addr:housenumber":"22",
    "addr:postcode":"1000",
    "addr:street":"Grootgodshuisstraat;/",
    "iso:country":"BE",
    "sg:address":"Grootgodshuisstraat 22",
    "sg:city":"Brussel/bruxelles",
    "sg:orig_category":"Binnenhuisarchitecten",
    "sg:phone":"+32 2 219 29 49",
    "sg:postcode":"1000",
    "sg:province":"Bruxelles-Capitale",
    "wof:name":"Raoul Cavadias",
    "wof:placetype":"venue"
},
  "geometry": {"coordinates":[4.349503994,50.853225708],"type":"Point"}
}