{
  "type": "Feature",
  "properties": {
    "iso:country":"BE",
    "sg:address":"Rue Des Couturelles 20",
    "sg:city":"Montigny-le-tilleul",
    "sg:orig_category":"Peinture. Rev\u00eatements pour sols and murs",
    "sg:phone":"+32 71 51 88 35",
    "sg:postcode":"6110",
    "sg:province":"Hainaut",
    "wof:name":"K.g. Peinture",
    "wof:placetype":"venue"
},
  "geometry": {"coordinates":[4.3728108406,50.3834686279],"type":"Point"}
}