{
  "type": "Feature",
  "properties": {
    "iso:country":"BE",
    "sg:address":"Parkstraat 9",
    "sg:city":"Sint-niklaas",
    "sg:classifiers":[
        {
            "category":"Restaurant",
            "type":"Food & Drink"
        }
    ],
    "sg:phone":"+32 3 776 77 81",
    "sg:postcode":"9100",
    "sg:province":"Oost-Vlaanderen",
    "wof:name":"Paros",
    "wof:placetype":"venue"
},
  "geometry": {"coordinates":[4.1390519142,51.1654090881],"type":"Point"}
}