{
  "type": "Feature",
  "properties": {
    "addr:full":"Chauss\u00e9e De Ruisbroek 398 Drogenbos Vlaams-Brabant 1620",
    "addr:housenumber":"398",
    "addr:postcode":"1620",
    "addr:street":"Chausse\u0301E De Ruisbroek",
    "iso:country":"BE",
    "sg:address":"Chauss\u00e9e De Ruisbroek 398",
    "sg:city":"Drogenbos",
    "sg:classifiers":[
        {
            "category":"Building & Trades",
            "subcategory":"Plumbing",
            "type":"Services"
        }
    ],
    "sg:phone":"+32 2 331 66 65",
    "sg:postcode":"1620",
    "sg:province":"Vlaams-Brabant",
    "sg:tags":[
        "contractor"
    ],
    "wof:name":"Plomberie Gilou",
    "wof:placetype":"venue"
},
  "geometry": {"coordinates":[4.3056697845,50.794090271],"type":"Point"}
}