{
  "type": "Feature",
  "properties": {
    "addr:full":"Oude Truierbaan 49 Hasselt Limburg 3500",
    "addr:housenumber":"49",
    "addr:postcode":"3500",
    "addr:street":"Oude Truierbaan",
    "iso:country":"BE",
    "sg:address":"Oude Truierbaan 49",
    "sg:city":"Hasselt",
    "sg:orig_category":"Groenten and fruit Gh",
    "sg:phone":"+32 11 28 08 08",
    "sg:postcode":"3500",
    "sg:province":"Limburg",
    "wof:name":"Fa. Arroba",
    "wof:placetype":"venue"
},
  "geometry": {"coordinates":[5.3167362213,50.9116325378],"type":"Point"}
}