{
  "type": "Feature",
  "properties": {
    "iso:country":"BE",
    "sg:address":"Rue Grande 10",
    "sg:city":"Gedinne (vencimont)",
    "sg:classifiers":[
        {
            "category":"Food & Beverages",
            "subcategory":"Groceries & Convenience Stores",
            "type":"Retail Goods"
        }
    ],
    "sg:phone":"+32 61 58 90 40",
    "sg:postcode":"5575",
    "sg:province":"Namur",
    "sg:tags":[
        "grocer"
    ],
    "wof:name":"Arcades (les)",
    "wof:placetype":"venue"
},
  "geometry": {"coordinates":[4.9252800941,50.0333900452],"type":"Point"}
}