{
  "type": "Feature",
  "properties": {
    "iso:country":"BE",
    "sg:address":"Ter Kamerenstraat 190",
    "sg:city":"Sint-lambrechts-woluwe/woluwe-saint-lambert",
    "sg:orig_category":"Kapsalons",
    "sg:phone":"+32 2 770 90 76",
    "sg:postcode":"1200",
    "sg:province":"Bruxelles-Capitale",
    "wof:name":"Coiffure Linda",
    "wof:placetype":"venue"
},
  "geometry": {"coordinates":[4.4163599014,50.8384513855],"type":"Point"}
}