{
  "type": "Feature",
  "properties": {
    "iso:country":"BE",
    "sg:address":"Ave De Wisterzee 20",
    "sg:city":"Court St. Etienne",
    "sg:classifiers":[
        {
            "category":"Banks & Credit Unions",
            "subcategory":"Bank",
            "type":"Services"
        }
    ],
    "sg:phone":"+32 10 61 22 69",
    "sg:postcode":"1490",
    "sg:province":"Brabant Wallon",
    "wof:name":"Banque Bruxelles Lambert Sa",
    "wof:placetype":"venue"
},
  "geometry": {"coordinates":[4.5649118423,50.6473579407],"type":"Point"}
}