{
  "type": "Feature",
  "properties": {
    "iso:country":"BE",
    "sg:address":"Guido Gezellelaan 1a",
    "sg:city":"Zonnebeke",
    "sg:classifiers":[
        {
            "category":"Shopping",
            "subcategory":"Stationery & Office Supplies",
            "type":"Retail Goods"
        }
    ],
    "sg:phone":"+32 51 77 85 08",
    "sg:postcode":"8980",
    "sg:province":"West-Vlaanderen",
    "sg:tags":[
        "packaging"
    ],
    "wof:name":"Food Packing Cappelle B.v.b.a.",
    "wof:placetype":"venue"
},
  "geometry": {"coordinates":[2.984110117,50.870174408],"type":"Point"}
}