{
  "type": "Feature",
  "properties": {
    "addr:full":"Polsstraat 34 Neerpelt Limburg 3910",
    "addr:housenumber":"34",
    "addr:postcode":"3910",
    "addr:street":"Polsstraat",
    "iso:country":"BE",
    "sg:address":"Polsstraat 34",
    "sg:city":"Neerpelt",
    "sg:classifiers":[
        {
            "category":"Home & Garden",
            "subcategory":"Building Materials",
            "type":"Retail Goods"
        }
    ],
    "sg:phone":"+32 11 64 14 50",
    "sg:postcode":"3910",
    "sg:province":"Limburg",
    "sg:tags":[
        "insect",
        "screen"
    ],
    "wof:name":"Coumans Jos",
    "wof:placetype":"venue"
},
  "geometry": {"coordinates":[5.4409332275,51.2498703003],"type":"Point"}
}