{
  "type": "Feature",
  "properties": {
    "iso:country":"BE",
    "sg:address":"Rijksweg 365",
    "sg:city":"Dilsen-stokkem (dilsen)",
    "sg:classifiers":[
        {
            "category":"Fast Food",
            "type":"Food & Drink"
        }
    ],
    "sg:phone":"+32 89 75 11 20",
    "sg:postcode":"3650",
    "sg:province":"Limburg",
    "sg:tags":[
        "fried",
        "stand",
        "potato"
    ],
    "wof:name":"Route 78",
    "wof:placetype":"venue"
},
  "geometry": {"coordinates":[5.7276320457,51.0290145874],"type":"Point"}
}