{
  "type": "Feature",
  "properties": {
    "iso:country":"BE",
    "sg:address":"Moorselbaan 409",
    "sg:city":"Aalst",
    "sg:orig_category":"Charpentes and couvertures",
    "sg:phone":"+32 53 78 56 25",
    "sg:postcode":"9300",
    "sg:province":"Oost-Vlaanderen",
    "wof:name":"Van Keer - Maes",
    "wof:placetype":"venue"
},
  "geometry": {"coordinates":[4.0670251846,50.9446258545],"type":"Point"}
}