{
  "type": "Feature",
  "properties": {
    "iso:country":"BE",
    "sg:address":"Mierhoopweg 63",
    "sg:city":"Nieuwerkerken",
    "sg:orig_category":"Fruitteelt",
    "sg:phone":"+32 11 59 31 83",
    "sg:postcode":"3850",
    "sg:province":"Limburg",
    "wof:name":"Danny Massoels",
    "wof:placetype":"venue"
},
  "geometry": {"coordinates":[5.1931529045,50.8640937805],"type":"Point"}
}