{
  "type": "Feature",
  "properties": {
    "iso:country":"BE",
    "sg:address":"Grootveldlaan 147",
    "sg:city":"Sint-pieters-woluwe/woluwe-saint-pierre",
    "sg:orig_category":"Rechtbanken",
    "sg:phone":"+32 2 762 00 16",
    "sg:postcode":"1150",
    "sg:province":"Bruxelles-Capitale",
    "wof:name":"Vredegerecht/justice De Paix",
    "wof:placetype":"venue"
},
  "geometry": {"coordinates":[4.4550161362,50.8382072449],"type":"Point"}
}