{
  "type": "Feature",
  "properties": {
    "addr:full":"Akkerstraat 13 Oudenburg West-Vlaanderen 8460",
    "addr:housenumber":"13",
    "addr:postcode":"8460",
    "addr:street":"Akkerstraat",
    "iso:country":"BE",
    "sg:address":"Akkerstraat 13",
    "sg:city":"Oudenburg",
    "sg:classifiers":[
        {
            "category":"Shopping",
            "subcategory":"Florist",
            "type":"Retail Goods"
        }
    ],
    "sg:phone":"+32 59 26 73 95",
    "sg:postcode":"8460",
    "sg:province":"West-Vlaanderen",
    "wof:name":"Bloemenatelier flos Romana",
    "wof:placetype":"venue"
},
  "geometry": {"coordinates":[2.9966800213,51.1857948303],"type":"Point"}
}