{
  "type": "Feature",
  "properties": {
    "iso:country":"BE",
    "sg:address":"Ninoofsesteenweg 123",
    "sg:city":"Lennik (sint-kwintens-lennik)",
    "sg:classifiers":[
        {
            "category":"Autos & Motor Vehicles",
            "subcategory":"Automobile Sales",
            "type":"Retail Goods"
        }
    ],
    "sg:phone":"+32 2 582 20 75",
    "sg:postcode":"1750",
    "sg:province":"Vlaams-Brabant",
    "sg:tags":[
        "car",
        "used",
        "-"
    ],
    "wof:name":"Raymond (autobedrijf) Bvba",
    "wof:placetype":"venue"
},
  "geometry": {"coordinates":[4.142291069,50.8348922729],"type":"Point"}
}