{
  "type": "Feature",
  "properties": {
    "addr:full":"Gasthuisstraat 14b1 Lanaken Limburg 3620",
    "addr:housenumber":"14b1",
    "addr:postcode":"3620",
    "addr:street":"Gasthuisstraat",
    "iso:country":"BE",
    "sg:address":"Gasthuisstraat 14b1",
    "sg:city":"Lanaken",
    "sg:orig_category":"Artsen and specialisten",
    "sg:phone":"+32 89 71 12 33",
    "sg:postcode":"3620",
    "sg:province":"Limburg",
    "wof:name":"Daniel Geurts",
    "wof:placetype":"venue"
},
  "geometry": {"coordinates":[5.6534438133,50.8878860474],"type":"Point"}
}