{
  "type": "Feature",
  "properties": {
    "iso:country":"BE",
    "sg:address":"Avenue Du Marouset 55",
    "sg:city":"Braine-le-comte",
    "sg:classifiers":[
        {
            "category":"Autos & Motor Vehicles",
            "subcategory":"Fuel & Gas Station",
            "type":"Retail Goods"
        }
    ],
    "sg:phone":"+32 67 48 57 20",
    "sg:postcode":"7090",
    "sg:province":"Hainaut",
    "wof:name":"Euro Plus Belgium",
    "wof:placetype":"venue"
},
  "geometry": {"coordinates":[4.158288002,50.6084327698],"type":"Point"}
}