{
  "type": "Feature",
  "properties": {
    "iso:country":"BE",
    "sg:address":"Vaartstraat 111",
    "sg:city":"Ranst (oelegem)",
    "sg:classifiers":[
        {
            "category":"Banks & Credit Unions",
            "subcategory":"Investment Brokerage",
            "type":"Services"
        }
    ],
    "sg:phone":"+32 3 485 70 89",
    "sg:postcode":"2520",
    "sg:province":"Antwerpen",
    "sg:tags":[
        "repair",
        "-",
        "installation",
        "sanitary",
        "article"
    ],
    "wof:name":"Balasco Bvba",
    "wof:placetype":"venue"
},
  "geometry": {"coordinates":[4.5858597755,51.2056312561],"type":"Point"}
}