{
  "type": "Feature",
  "properties": {
    "addr:full":"Pieter De Conincklaan 12 Kortrijk West-Vlaanderen 8500",
    "addr:housenumber":"12",
    "addr:postcode":"8500",
    "addr:street":"Pieter De Conincklaan",
    "iso:country":"BE",
    "sg:address":"Pieter De Conincklaan 12",
    "sg:city":"Kortrijk",
    "sg:classifiers":[
        {
            "category":"Social Services",
            "subcategory":"Retirement Home",
            "type":"Services"
        }
    ],
    "sg:phone":"+32 56 26 01 01",
    "sg:postcode":"8500",
    "sg:province":"West-Vlaanderen",
    "sg:tags":[
        "residence"
    ],
    "wof:name":"De Korenbloem",
    "wof:placetype":"venue"
},
  "geometry": {"coordinates":[3.2805531025,50.8297729492],"type":"Point"}
}