{
  "type": "Feature",
  "properties": {
    "addr:full":"Tielendorp 8 Kasterlee Antwerpen 2460",
    "addr:housenumber":"8",
    "addr:postcode":"2460",
    "addr:street":"Tielendorp",
    "iso:country":"BE",
    "sg:address":"Tielendorp 8",
    "sg:city":"Kasterlee",
    "sg:orig_category":"Kapsalons",
    "sg:phone":"+32 14 55 31 35",
    "sg:postcode":"2460",
    "sg:province":"Antwerpen",
    "wof:name":"Marina Coveliers",
    "wof:placetype":"venue"
},
  "geometry": {"coordinates":[4.8963041306,51.2429275513],"type":"Point"}
}