{
  "type": "Feature",
  "properties": {
    "iso:country":"BE",
    "sg:address":"Stationsstraat 90",
    "sg:city":"Liedekerke",
    "sg:classifiers":[
        {
            "category":"Shopping",
            "subcategory":"Jewelry",
            "type":"Retail Goods"
        }
    ],
    "sg:phone":"+32 53 68 28 59",
    "sg:postcode":"1770",
    "sg:province":"Vlaams-Brabant",
    "sg:tags":[
        "jeweller",
        "-"
    ],
    "wof:name":"Lanckmans",
    "wof:placetype":"venue"
},
  "geometry": {"coordinates":[4.0859642029,50.8736343384],"type":"Point"}
}