{
  "type": "Feature",
  "properties": {
    "addr:full":"Leuvensesteenweg 252 Tielt-winge Vlaams-Brabant 3390",
    "addr:housenumber":"252",
    "addr:postcode":"3390",
    "addr:street":"Leuvensesteenweg",
    "iso:country":"BE",
    "sg:address":"Leuvensesteenweg 252",
    "sg:city":"Tielt-winge",
    "sg:classifiers":[
        {
            "category":"Sports & Exercise",
            "subcategory":"Sports Center",
            "type":"Entertainment"
        }
    ],
    "sg:phone":"+32 16 63 40 53",
    "sg:postcode":"3390",
    "sg:province":"Vlaams-Brabant",
    "sg:tags":[
        "club",
        "article",
        "de",
        "camping"
    ],
    "wof:name":"Winge Golf & Country Club",
    "wof:placetype":"venue"
},
  "geometry": {"coordinates":[4.8743419647,50.9077072144],"type":"Point"}
}