{
  "type": "Feature",
  "properties": {
    "iso:country":"BE",
    "sg:address":"Heuvel 2",
    "sg:city":"Kalmthout",
    "sg:orig_category":"Dierentuinen, botanische tuinen, sterrenwachten and natuurreservaten Diverse organisaties and vereni",
    "sg:phone":"+32 3 666 67 41",
    "sg:postcode":"2920",
    "sg:province":"Antwerpen",
    "wof:name":"Vrienden Arboretum Kalmthout",
    "wof:placetype":"venue"
},
  "geometry": {"coordinates":[4.4658761024,51.3912086487],"type":"Point"}
}