{
  "type": "Feature",
  "properties": {
    "addr:full":"Kapellensteenweg 181 Kalmthout Antwerpen 2920",
    "addr:housenumber":"181",
    "addr:postcode":"2920",
    "addr:street":"Kapellensteenweg",
    "iso:country":"BE",
    "sg:address":"Kapellensteenweg 181",
    "sg:city":"Kalmthout",
    "sg:orig_category":"Boekhandels Krantenwinkels Rookartikelen",
    "sg:phone":"+32 3 666 86 87",
    "sg:postcode":"2920",
    "sg:province":"Antwerpen",
    "wof:name":"Courant",
    "wof:placetype":"venue"
},
  "geometry": {"coordinates":[4.4751501083,51.3815383911],"type":"Point"}
}