{
  "type": "Feature",
  "properties": {
    "addr:full":"Rue De Tilf 91 A Boncelles Li\u00e8ge 4100",
    "addr:housenumber":"91 a",
    "addr:postcode":"4100",
    "addr:street":"Rue De Tilf",
    "iso:country":"BE",
    "sg:address":"Rue De Tilf 91 A",
    "sg:city":"Boncelles",
    "sg:orig_category":"Royal Canin. Animaux domestiques and accessoires",
    "sg:phone":"+32 4 338 25 73",
    "sg:postcode":"4100",
    "sg:province":"Li\u00e8ge",
    "wof:name":"Tom & Co",
    "wof:placetype":"venue"
},
  "geometry": {"coordinates":[5.547932148,50.5666046143],"type":"Point"}
}