{
  "type": "Feature",
  "properties": {
    "addr:full":"Lindekensveldstraat 56 Hasselt (kermt) Limburg 3510",
    "addr:housenumber":"56",
    "addr:postcode":"3510",
    "addr:street":"Lindekensveldstraat",
    "iso:country":"BE",
    "sg:address":"Lindekensveldstraat 56",
    "sg:city":"Hasselt (kermt)",
    "sg:classifiers":[
        {
            "category":"Health Services",
            "subcategory":"Nursing And Care Facility",
            "type":"Services"
        }
    ],
    "sg:phone":"+32 11 85 83 10",
    "sg:postcode":"3510",
    "sg:province":"Limburg",
    "sg:tags":[
        "home",
        "rest"
    ],
    "wof:name":"Residentie Vinkenbosch Vzw",
    "wof:placetype":"venue"
},
  "geometry": {"coordinates":[5.2531552315,50.9474906921],"type":"Point"}
}