{
  "type": "Feature",
  "properties": {
    "addr:full":"Prins Alexanderstraat 32 Brugge West-Vlaanderen 8310",
    "addr:housenumber":"32",
    "addr:postcode":"8310",
    "addr:street":"Prins Alexanderstraat",
    "iso:country":"BE",
    "sg:address":"Prins Alexanderstraat 32",
    "sg:city":"Brugge",
    "sg:orig_category":"Loodgieterij, verwarming and sanitaire installaties",
    "sg:phone":"+32 50 35 10 95",
    "sg:postcode":"8310",
    "sg:province":"West-Vlaanderen",
    "wof:name":"Fa. Luickx R. & Zn",
    "wof:placetype":"venue"
},
  "geometry": {"coordinates":[3.2496500015,51.1967353821],"type":"Point"}
}