{
  "type": "Feature",
  "properties": {
    "addr:full":"Broeckstraat 7 Gavere Oost-Vlaanderen 9890",
    "addr:housenumber":"7",
    "addr:postcode":"9890",
    "addr:street":"Broeckstraat",
    "iso:country":"BE",
    "sg:address":"Broeckstraat 7",
    "sg:city":"Gavere",
    "sg:classifiers":[
        {
            "category":"Cafe",
            "type":"Food & Drink"
        }
    ],
    "sg:phone":"+32 9 384 56 71",
    "sg:postcode":"9890",
    "sg:province":"Oost-Vlaanderen",
    "sg:tags":[
        "caf\u00e9s"
    ],
    "wof:name":"Caf\u00c9 Biljart",
    "wof:placetype":"venue"
},
  "geometry": {"coordinates":[3.6585578918,50.9306983948],"type":"Point"}
}