{
  "type": "Feature",
  "properties": {
    "addr:full":"Rue De Ch\u00e2telet 518 Charleroi (couillet) Hainaut 6010",
    "addr:housenumber":"518",
    "addr:postcode":"6010",
    "addr:street":"Rue De Cha\u0302Telet",
    "iso:country":"BE",
    "sg:address":"Rue De Ch\u00e2telet 518",
    "sg:city":"Charleroi (couillet)",
    "sg:orig_category":"Solar protection - Inside",
    "sg:phone":"+32 71 43 08 17",
    "sg:postcode":"6010",
    "sg:province":"Hainaut",
    "wof:name":"A & S Solar",
    "wof:placetype":"venue"
},
  "geometry": {"coordinates":[4.4677200317,50.3921051025],"type":"Point"}
}