{
  "type": "Feature",
  "properties": {
    "addr:full":"Rue Verheyleweghen 30 Bruxelles (woluwe-saint-lambert) Bruxelles-Capitale 1200",
    "addr:housenumber":"30",
    "addr:postcode":"1200",
    "addr:street":"Rue Verheyleweghen",
    "iso:country":"BE",
    "sg:address":"Rue Verheyleweghen 30",
    "sg:city":"Bruxelles (woluwe-saint-lambert)",
    "sg:classifiers":[
        {
            "category":"Autos & Motor Vehicles",
            "subcategory":"Automobile Sales",
            "type":"Retail Goods"
        }
    ],
    "sg:phone":"+32 2 771 82 99",
    "sg:postcode":"1200",
    "sg:province":"Bruxelles-Capitale",
    "sg:tags":[
        "car",
        "used",
        "-"
    ],
    "wof:name":"Nabil Chedid Car Sprl",
    "wof:placetype":"venue"
},
  "geometry": {"coordinates":[4.4282660484,50.8458862305],"type":"Point"}
}