{
  "type": "Feature",
  "properties": {
    "iso:country":"BE",
    "sg:address":"Boonhoek 24",
    "sg:city":"Ledegem",
    "sg:orig_category":"Producteurs de l\u00e9gumes. Eleveurs and marchands de porcs",
    "sg:phone":"+32 56 50 04 08",
    "sg:postcode":"8880",
    "sg:province":"West-Vlaanderen",
    "wof:name":"Marcel Desplenter",
    "wof:placetype":"venue"
},
  "geometry": {"coordinates":[3.1348350048,50.8642616272],"type":"Point"}
}