{
  "type": "Feature",
  "properties": {
    "iso:country":"BE",
    "sg:address":"Chauss\u00c9e De March\u00c9 349",
    "sg:city":"Namur",
    "sg:orig_category":"Epiceries",
    "sg:phone":"+32 81 30 09 63",
    "sg:postcode":"5100",
    "sg:province":"Namur",
    "wof:name":"Poids D'or",
    "wof:placetype":"venue"
},
  "geometry": {"coordinates":[4.8713750839,50.4566345215],"type":"Point"}
}