{
  "type": "Feature",
  "properties": {
    "iso:country":"BE",
    "sg:address":"Goedlevenstraat 85",
    "sg:city":"Gent",
    "sg:classifiers":[
        {
            "category":"Recreation",
            "type":"Entertainment"
        }
    ],
    "sg:phone":"+32 9 251 68 69",
    "sg:postcode":"9041",
    "sg:province":"Oost-Vlaanderen",
    "sg:tags":[
        "diver",
        "amusement"
    ],
    "wof:name":"D.j. Mark",
    "wof:placetype":"venue"
},
  "geometry": {"coordinates":[3.7661950588,51.0779914856],"type":"Point"}
}