{
  "type": "Feature",
  "properties": {
    "iso:country":"BE",
    "sg:address":"Cardijnstraat 6",
    "sg:city":"Essen",
    "sg:orig_category":"Artsen and specialisten",
    "sg:phone":"+32 3 677 17 11",
    "sg:postcode":"2910",
    "sg:province":"Antwerpen",
    "wof:name":"Jan Schoof",
    "wof:placetype":"venue"
},
  "geometry": {"coordinates":[4.4653429985,51.4261932373],"type":"Point"}
}