{
  "type": "Feature",
  "properties": {
    "iso:country":"BE",
    "sg:address":"Leuvensesteenweg 198",
    "sg:city":"Tielt-winge",
    "sg:orig_category":"Banken and kredietinstellingen",
    "sg:phone":"+32 16 63 36 55",
    "sg:postcode":"3390",
    "sg:province":"Vlaams-Brabant",
    "wof:name":"Kbc",
    "wof:placetype":"venue"
},
  "geometry": {"coordinates":[4.882586956,50.9091262817],"type":"Point"}
}