{
  "type": "Feature",
  "properties": {
    "iso:country":"BE",
    "sg:address":"Hoekeinde 33",
    "sg:city":"Merksplas",
    "sg:orig_category":"Rundveehouders",
    "sg:phone":"+32 14 63 57 03",
    "sg:postcode":"2330",
    "sg:province":"Antwerpen",
    "wof:name":"Marc Verhoeven",
    "wof:placetype":"venue"
},
  "geometry": {"coordinates":[4.858932972,51.370300293],"type":"Point"}
}