{
  "type": "Feature",
  "properties": {
    "addr:full":"Kriephoekstraat 12 Wetteren (massemen) Oost-Vlaanderen 9230",
    "addr:housenumber":"12",
    "addr:postcode":"9230",
    "addr:street":"Kriephoekstraat",
    "iso:country":"BE",
    "sg:address":"Kriephoekstraat 12",
    "sg:city":"Wetteren (massemen)",
    "sg:classifiers":[
        {
            "category":"Utilities",
            "subcategory":"Electric",
            "type":"Services"
        }
    ],
    "sg:phone":"+32 9 366 45 00",
    "sg:postcode":"9230",
    "sg:province":"Oost-Vlaanderen",
    "sg:tags":[
        "energy",
        "renewable"
    ],
    "wof:name":"Deva Engineering Bvba",
    "wof:placetype":"venue"
},
  "geometry": {"coordinates":[3.8855400085,51.0070304871],"type":"Point"}
}