{
  "type": "Feature",
  "properties": {
    "iso:country":"BE",
    "sg:address":"Zilverpand 14",
    "sg:city":"Brugge",
    "sg:classifiers":[
        {
            "category":"Restaurant",
            "type":"Food & Drink"
        }
    ],
    "sg:phone":"+32 50 33 92 15",
    "sg:postcode":"8000",
    "sg:province":"West-Vlaanderen",
    "wof:name":"'t Zonnekind",
    "wof:placetype":"venue"
},
  "geometry": {"coordinates":[3.2221989632,51.2076301575],"type":"Point"}
}