{
  "type": "Feature",
  "properties": {
    "iso:country":"BE",
    "sg:address":"Poststraat 76",
    "sg:city":"Oosterzele",
    "sg:orig_category":"Producteurs de l\u00e9gumes",
    "sg:phone":"+32 9 362 74 09",
    "sg:postcode":"9860",
    "sg:province":"Oost-Vlaanderen",
    "wof:name":"Marc Fackaert",
    "wof:placetype":"venue"
},
  "geometry": {"coordinates":[3.7906780243,50.9219284058],"type":"Point"}
}