{
  "type": "Feature",
  "properties": {
    "addr:full":"Koning Albertstraat 20 Diest Vlaams-Brabant 3290",
    "addr:housenumber":"20",
    "addr:postcode":"3290",
    "addr:street":"Koning Albertstraat",
    "iso:country":"BE",
    "sg:address":"Koning Albertstraat 20",
    "sg:city":"Diest",
    "sg:orig_category":"Instituts de beaut\u00e9. Parfumeries. Centres de relaxation and bien-\u00eatre",
    "sg:phone":"+32 13 33 35 27",
    "sg:postcode":"3290",
    "sg:province":"Vlaams-Brabant",
    "wof:name":"Instituut Gis\u00c8le",
    "wof:placetype":"venue"
},
  "geometry": {"coordinates":[5.0528030396,50.9859085083],"type":"Point"}
}