{
  "type": "Feature",
  "properties": {
    "addr:full":"Rue Du Sablon 59 Bastogne Luxembourg 6600",
    "addr:housenumber":"59",
    "addr:postcode":"6600",
    "addr:street":"Rue Du Sablon",
    "iso:country":"BE",
    "sg:address":"Rue Du Sablon 59",
    "sg:city":"Bastogne",
    "sg:classifiers":[
        {
            "category":"Bars & Pubs",
            "type":"Food & Drink"
        }
    ],
    "sg:phone":"+32 61 21 61 31",
    "sg:postcode":"6600",
    "sg:province":"Luxembourg",
    "sg:tags":[
        "tavern"
    ],
    "wof:name":"Bistrot (le)",
    "wof:placetype":"venue"
},
  "geometry": {"coordinates":[5.7176818848,50.002243042],"type":"Point"}
}