{
  "type": "Feature",
  "properties": {
    "addr:full":"Boulevard Saint-michel 41 Bruxelles (etterbeek) Bruxelles-Capitale 1040",
    "addr:housenumber":"41",
    "addr:postcode":"1040",
    "addr:street":"Boulevard Saint-Michel",
    "iso:country":"BE",
    "sg:address":"Boulevard Saint-michel 41",
    "sg:city":"Bruxelles (etterbeek)",
    "sg:classifiers":[
        {
            "category":"Insurance",
            "subcategory":"Insurance Agent",
            "type":"Services"
        }
    ],
    "sg:phone":"+32 2 736 20 90",
    "sg:postcode":"1040",
    "sg:province":"Bruxelles-Capitale",
    "sg:tags":[
        "broker"
    ],
    "wof:name":"Wodon Sprl",
    "wof:placetype":"venue"
},
  "geometry": {"coordinates":[4.4058761597,50.8349494934],"type":"Point"}
}