{
  "type": "Feature",
  "properties": {
    "iso:country":"BE",
    "sg:address":"Rue Devillez 2a",
    "sg:city":"Charleroi (gilly)",
    "sg:classifiers":[
        {
            "category":"Real Estate",
            "subcategory":"Architect",
            "type":"Services"
        }
    ],
    "sg:phone":"+32 71 41 01 18",
    "sg:postcode":"6060",
    "sg:province":"Hainaut",
    "wof:name":"Tassin Th",
    "wof:placetype":"venue"
},
  "geometry": {"coordinates":[4.4880981445,50.4251937866],"type":"Point"}
}