{
  "type": "Feature",
  "properties": {
    "addr:full":"Bruggesteenweg 10 Hooglede (gits) West-Vlaanderen 8830",
    "addr:housenumber":"10",
    "addr:postcode":"8830",
    "addr:street":"Bruggesteenweg",
    "iso:country":"BE",
    "sg:address":"Bruggesteenweg 10",
    "sg:city":"Hooglede (gits)",
    "sg:classifiers":[
        {
            "category":"Retail",
            "subcategory":"Auto Repair",
            "type":"Services"
        }
    ],
    "sg:phone":"+32 51 72 27 70",
    "sg:postcode":"8830",
    "sg:province":"West-Vlaanderen",
    "sg:tags":[
        "automobile",
        "-",
        "wrecking"
    ],
    "wof:name":"Gryspeerdt Patriek Nv",
    "wof:placetype":"venue"
},
  "geometry": {"coordinates":[3.0835700035,50.9787635803],"type":"Point"}
}