{
  "type": "Feature",
  "properties": {
    "addr:full":"Magdalenasteenweg 9 Brussel/bruxelles Bruxelles-Capitale 1000",
    "addr:housenumber":"9",
    "addr:postcode":"1000",
    "addr:street":"Magdalenasteenweg;/",
    "iso:country":"BE",
    "sg:address":"Magdalenasteenweg 9",
    "sg:city":"Brussel/bruxelles",
    "sg:orig_category":"Brood, gebak and snoepgoed",
    "sg:phone":"+32 2 512 43 14",
    "sg:postcode":"1000",
    "sg:province":"Bruxelles-Capitale",
    "wof:name":"Corn\u00c9 Port-royal Chocolatier",
    "wof:placetype":"venue"
},
  "geometry": {"coordinates":[4.3546228409,50.8459510803],"type":"Point"}
}