{
  "type": "Feature",
  "properties": {
    "iso:country":"BE",
    "sg:address":"Smedenstraat 21",
    "sg:city":"Brugge",
    "sg:classifiers":[
        {
            "category":"Real Estate",
            "subcategory":"Real Estate Services",
            "type":"Services"
        }
    ],
    "sg:phone":"+32 50 34 84 84",
    "sg:postcode":"8000",
    "sg:province":"West-Vlaanderen",
    "wof:name":"Stubbe-denoo Bvba",
    "wof:placetype":"venue"
},
  "geometry": {"coordinates":[3.2154328823,51.2055130005],"type":"Point"}
}