{
  "type": "Feature",
  "properties": {
    "iso:country":"BE",
    "sg:address":"Knesselaarsestraat 18",
    "sg:city":"Aalter",
    "sg:orig_category":"Travaux de pl\u00e2trage",
    "sg:phone":"+32 9 375 20 80",
    "sg:postcode":"9880",
    "sg:province":"Oost-Vlaanderen",
    "wof:name":"Gipsconstruct",
    "wof:placetype":"venue"
},
  "geometry": {"coordinates":[3.4482300282,51.0872917175],"type":"Point"}
}