{
  "type": "Feature",
  "properties": {
    "iso:country":"BE",
    "sg:address":"Avenue G\u00e9n\u00e9ral Leman 4",
    "sg:city":"Seraing (jemeppe-sur-meuse)",
    "sg:classifiers":[
        {
            "category":"Bars & Pubs",
            "type":"Food & Drink"
        }
    ],
    "sg:phone":"+32 4 234 11 01",
    "sg:postcode":"4101",
    "sg:province":"Li\u00e8ge",
    "wof:name":"Metropole",
    "wof:placetype":"venue"
},
  "geometry": {"coordinates":[5.4990129471,50.6169090271],"type":"Point"}
}