{
  "type": "Feature",
  "properties": {
    "addr:full":"Rue De La Genette 54 Beauraing Namur 5570",
    "addr:housenumber":"54",
    "addr:postcode":"5570",
    "addr:street":"Rue De La Genette",
    "iso:country":"BE",
    "sg:address":"Rue De La Genette 54",
    "sg:city":"Beauraing",
    "sg:classifiers":[
        {
            "category":"Manufacturing",
            "subcategory":"Textiles",
            "type":"Manufacturing & Wholesale Goods"
        }
    ],
    "sg:phone":"+32 82 71 37 87",
    "sg:postcode":"5570",
    "sg:province":"Namur",
    "wof:name":"Maison Au Tisserin",
    "wof:placetype":"venue"
},
  "geometry": {"coordinates":[4.9577898979,50.1113090515],"type":"Point"}
}