{
  "type": "Feature",
  "properties": {
    "iso:country":"BE",
    "sg:address":"Roeland Saverystraat 22",
    "sg:city":"Kortrijk",
    "sg:orig_category":"Cr\u00e9dit \u00e0 la consommation. Pr\u00eats hypoth\u00e9caires and cr\u00e9dits immobiliers",
    "sg:phone":"+32 56 21 32 88",
    "sg:postcode":"8500",
    "sg:province":"West-Vlaanderen",
    "wof:name":"Rond Den Heerd",
    "wof:placetype":"venue"
},
  "geometry": {"coordinates":[3.2606871128,50.8261375427],"type":"Point"}
}