{
  "type": "Feature",
  "properties": {
    "addr:full":"Lokerse Baan 79 Sint-niklaas Oost-Vlaanderen 9111",
    "addr:housenumber":"79",
    "addr:postcode":"9111",
    "addr:street":"Lokerse Baan",
    "iso:country":"BE",
    "sg:address":"Lokerse Baan 79",
    "sg:city":"Sint-niklaas",
    "sg:orig_category":"Catering and organisatie van feesten Fast food and meeneem restaurants Levering aan huis restaurants",
    "sg:phone":"+32 3 772 68 31",
    "sg:postcode":"9111",
    "sg:province":"Oost-Vlaanderen",
    "wof:name":"The Rosegarden",
    "wof:placetype":"venue"
},
  "geometry": {"coordinates":[4.0703887939,51.1390571594],"type":"Point"}
}