{
  "type": "Feature",
  "properties": {
    "iso:country":"BE",
    "sg:address":"Rue De Namur 3 Box 4",
    "sg:city":"Charleroi (gosselies)",
    "sg:classifiers":[
        {
            "category":"Personal",
            "subcategory":"Beauty Salon",
            "type":"Services"
        }
    ],
    "sg:phone":"+32 71 34 50 26",
    "sg:postcode":"6041",
    "sg:province":"Hainaut",
    "sg:tags":[
        "lady",
        "-",
        "hairdressing"
    ],
    "wof:name":"Roberto (salon)",
    "wof:placetype":"venue"
},
  "geometry": {"coordinates":[4.4406380653,50.4215431213],"type":"Point"}
}