{
  "type": "Feature",
  "properties": {
    "iso:country":"BE",
    "sg:address":"Deinsesteenweg 193",
    "sg:city":"Tielt",
    "sg:classifiers":[
        {
            "category":"Cafe",
            "type":"Food & Drink"
        }
    ],
    "sg:phone":"+32 51 63 55 82",
    "sg:postcode":"8700",
    "sg:province":"West-Vlaanderen",
    "sg:tags":[
        "caf\u00e9s"
    ],
    "wof:name":"Caf\u00c9 Nichols",
    "wof:placetype":"venue"
},
  "geometry": {"coordinates":[3.382240057,50.9947509766],"type":"Point"}
}