{
  "type": "Feature",
  "properties": {
    "iso:country":"BE",
    "sg:address":"Avenue De L'europe 65",
    "sg:city":"La Louviere",
    "sg:orig_category":"Artsen and specialisten",
    "sg:phone":"+32 64 26 32 75",
    "sg:postcode":"7100",
    "sg:province":"Hainaut",
    "wof:name":"Raymond Stilmant",
    "wof:placetype":"venue"
},
  "geometry": {"coordinates":[4.1665401459,50.4629974365],"type":"Point"}
}