{
  "type": "Feature",
  "properties": {
    "addr:full":"Tientjesstraat 30 Kortrijk West-Vlaanderen 8501",
    "addr:housenumber":"30",
    "addr:postcode":"8501",
    "addr:street":"Tientjesstraat",
    "iso:country":"BE",
    "sg:address":"Tientjesstraat 30",
    "sg:city":"Kortrijk",
    "sg:orig_category":"Ordinateurs Fab",
    "sg:phone":"+32 56 37 11 17",
    "sg:postcode":"8501",
    "sg:province":"West-Vlaanderen",
    "wof:name":"Ifung Enterprises",
    "wof:placetype":"venue"
},
  "geometry": {"coordinates":[3.2245790958,50.8288497925],"type":"Point"}
}