{
  "type": "Feature",
  "properties": {
    "addr:full":"Lakensestraat 66 Grimbergen Vlaams-Brabant 1853",
    "addr:housenumber":"66",
    "addr:postcode":"1853",
    "addr:street":"Lakensestraat",
    "iso:country":"BE",
    "sg:address":"Lakensestraat 66",
    "sg:city":"Grimbergen",
    "sg:orig_category":"Brood, gebak and snoepgoed",
    "sg:phone":"+32 2 267 80 24",
    "sg:postcode":"1853",
    "sg:province":"Vlaams-Brabant",
    "wof:name":"Remy De Brabanter",
    "wof:placetype":"venue"
},
  "geometry": {"coordinates":[4.3547019958,50.9051589966],"type":"Point"}
}