{
  "type": "Feature",
  "properties": {
    "iso:country":"BE",
    "sg:address":"Mosselstraat 81",
    "sg:city":"Gistel",
    "sg:classifiers":[
        {
            "category":"Retail",
            "subcategory":"Animal Services",
            "type":"Services"
        }
    ],
    "sg:phone":"+32 59 27 39 14",
    "sg:postcode":"8470",
    "sg:province":"West-Vlaanderen",
    "sg:tags":[
        "grooming",
        "-",
        "dog"
    ],
    "wof:name":"Hondjeweltevree",
    "wof:placetype":"venue"
},
  "geometry": {"coordinates":[2.9747409821,51.1375656128],"type":"Point"}
}