{
  "type": "Feature",
  "properties": {
    "iso:country":"BE",
    "sg:address":"3800",
    "sg:city":"Sint-truiden (groot)",
    "sg:orig_category":"Pharmaciens",
    "sg:phone":"+32 900 10 500",
    "sg:postcode":"3800",
    "sg:province":"Limburg",
    "wof:name":"Pharmacies De Garde",
    "wof:placetype":"venue"
},
  "geometry": {"coordinates":[5.2097201347,50.8130111694],"type":"Point"}
}