{
  "type": "Feature",
  "properties": {
    "addr:full":"Kerkstraat 145c Berlare (overmere) Oost-Vlaanderen 9290",
    "addr:housenumber":"145c",
    "addr:postcode":"9290",
    "addr:street":"Kerkstraat",
    "iso:country":"BE",
    "sg:address":"Kerkstraat 145c",
    "sg:city":"Berlare (overmere)",
    "sg:classifiers":[
        {
            "category":"Real Estate",
            "subcategory":"Architect",
            "type":"Services"
        }
    ],
    "sg:phone":"+32 9 367 59 46",
    "sg:postcode":"9290",
    "sg:province":"Oost-Vlaanderen",
    "wof:name":"Sichien A",
    "wof:placetype":"venue"
},
  "geometry": {"coordinates":[3.9469749928,51.0720596313],"type":"Point"}
}