{
  "type": "Feature",
  "properties": {
    "iso:country":"BE",
    "sg:address":"Rue Du Port 3",
    "sg:city":"Erquelinnes",
    "sg:classifiers":[
        {
            "category":"Real Estate",
            "subcategory":"Architect",
            "type":"Services"
        }
    ],
    "sg:phone":"+32 71 55 54 28",
    "sg:postcode":"6560",
    "sg:province":"Hainaut",
    "wof:name":"Rochmans D",
    "wof:placetype":"venue"
},
  "geometry": {"coordinates":[4.1198067665,50.3073577881],"type":"Point"}
}