{
  "type": "Feature",
  "properties": {
    "addr:full":"Route D'arlon 7 Rombach 8832",
    "addr:housenumber":"7",
    "addr:postcode":"8832",
    "addr:street":"Route D'Arlon",
    "iso:country":"BE",
    "sg:address":"Route D'arlon 7",
    "sg:city":"Rombach",
    "sg:classifiers":[
        {
            "category":"Autos & Motor Vehicles",
            "subcategory":"Fuel & Gas Station",
            "type":"Retail Goods"
        }
    ],
    "sg:phone":"+32 477 41 71 55",
    "sg:postcode":"8832",
    "wof:name":"Esso Station",
    "wof:placetype":"venue"
},
  "geometry": {"coordinates":[5.7422032356,49.8324508667],"type":"Point"}
}