{
  "type": "Feature",
  "properties": {
    "addr:full":"Vleurgatsesteenweg 113 Elsene/ixelles Bruxelles-Capitale 1050",
    "addr:housenumber":"113",
    "addr:postcode":"1050",
    "addr:street":"Vleurgatsesteenweg",
    "iso:country":"BE",
    "sg:address":"Vleurgatsesteenweg 113",
    "sg:city":"Elsene/ixelles",
    "sg:orig_category":"Reisbureaus Vakantiedorpen",
    "sg:phone":"+32 2 648 81 09",
    "sg:postcode":"1050",
    "sg:province":"Bruxelles-Capitale",
    "wof:name":"A.e.p./vacances Vivantes",
    "wof:placetype":"venue"
},
  "geometry": {"coordinates":[4.3688001633,50.8247718811],"type":"Point"}
}