{
  "type": "Feature",
  "properties": {
    "iso:country":"BE",
    "sg:address":"Elzenstraat 20",
    "sg:city":"Zandhoven",
    "sg:classifiers":[
        {
            "category":"Insurance",
            "subcategory":"Insurance Agent",
            "type":"Services"
        }
    ],
    "sg:phone":"+32 3 466 01 20",
    "sg:postcode":"2242",
    "sg:province":"Antwerpen",
    "sg:tags":[
        "verzekeringsmakelaars",
        "expert"
    ],
    "wof:name":"Covaco",
    "wof:placetype":"venue"
},
  "geometry": {"coordinates":[4.6972341537,51.2143707275],"type":"Point"}
}