{
  "type": "Feature",
  "properties": {
    "addr:full":"Rue Des Eschamps 4 Vencimont Namur 5575",
    "addr:housenumber":"4",
    "addr:postcode":"5575",
    "addr:street":"Rue Des Eschamps;Namur",
    "iso:country":"BE",
    "sg:address":"Rue Des Eschamps 4",
    "sg:city":"Vencimont",
    "sg:orig_category":"Watersport-, Sport- and Kampeerbenodigdheden Verhuur",
    "sg:phone":"+32 61 58 87 54",
    "sg:postcode":"5575",
    "sg:province":"Namur",
    "wof:name":"Veloxygen",
    "wof:placetype":"venue"
},
  "geometry": {"coordinates":[4.9262080193,50.0331497192],"type":"Point"}
}