{
  "type": "Feature",
  "properties": {
    "addr:full":"Chauss\u00c9e D'ivoz 2 Flemalle Li\u00e8ge 4400",
    "addr:housenumber":"2",
    "addr:postcode":"4400",
    "addr:street":"Chausse\u0301E D'Ivoz",
    "iso:country":"BE",
    "sg:address":"Chauss\u00c9e D'ivoz 2",
    "sg:city":"Flemalle",
    "sg:orig_category":"Magasins sp\u00e9cialis\u00e9s",
    "sg:phone":"+32 4 336 94 40",
    "sg:postcode":"4400",
    "sg:province":"Li\u00e8ge",
    "wof:name":"Verreries Dumont",
    "wof:placetype":"venue"
},
  "geometry": {"coordinates":[5.4641079903,50.5885734558],"type":"Point"}
}