{
  "type": "Feature",
  "properties": {
    "iso:country":"BE",
    "sg:address":"Hulstemolenstraat 42",
    "sg:city":"Lendelede",
    "sg:orig_category":"Installation \u00e9lectrique r\u00e9sidentielle",
    "sg:phone":"+32 51 30 81 64",
    "sg:postcode":"8860",
    "sg:province":"West-Vlaanderen",
    "wof:name":"Roland Couckhuyt",
    "wof:placetype":"venue"
},
  "geometry": {"coordinates":[3.256565094,50.886390686],"type":"Point"}
}