{
  "type": "Feature",
  "properties": {
    "addr:full":"Guido Gezellestraat 107bb Denderleeuw Oost-Vlaanderen 9470",
    "addr:housenumber":"107bb",
    "addr:postcode":"9470",
    "addr:street":"Guido Gezellestraat",
    "iso:country":"BE",
    "sg:address":"Guido Gezellestraat 107bb",
    "sg:city":"Denderleeuw",
    "sg:orig_category":"Cr\u00e9dits divers",
    "sg:postcode":"9470",
    "sg:province":"Oost-Vlaanderen",
    "wof:name":"Bancontact-mister Cash",
    "wof:placetype":"venue"
},
  "geometry": {"coordinates":[4.0773801804,50.8877944946],"type":"Point"}
}