{
  "type": "Feature",
  "properties": {
    "iso:country":"BE",
    "sg:address":"Clos De La Couronne 28",
    "sg:city":"Mouscron (herseaux)",
    "sg:classifiers":[
        {
            "category":"Professional",
            "subcategory":"Computer Services",
            "type":"Services"
        }
    ],
    "sg:phone":"+32 56 48 46 00",
    "sg:postcode":"7712",
    "sg:province":"Hainaut",
    "sg:tags":[
        "-",
        "processing",
        "data",
        "software"
    ],
    "wof:name":"G T I",
    "wof:placetype":"venue"
},
  "geometry": {"coordinates":[3.2535879612,50.714931488],"type":"Point"}
}