{
  "type": "Feature",
  "properties": {
    "addr:full":"Vaartstraat 86 Ranst Antwerpen 2520",
    "addr:housenumber":"86",
    "addr:postcode":"2520",
    "addr:street":"Vaartstraat",
    "iso:country":"BE",
    "sg:address":"Vaartstraat 86",
    "sg:city":"Ranst",
    "sg:orig_category":"Bagage and lederwaren Fab",
    "sg:phone":"+32 3 485 61 88",
    "sg:postcode":"2520",
    "sg:province":"Antwerpen",
    "wof:name":"Tuigmakerij Baets Johan",
    "wof:placetype":"venue"
},
  "geometry": {"coordinates":[4.5678629875,51.2009010315],"type":"Point"}
}