{
  "type": "Feature",
  "properties": {
    "addr:full":"Fazantenlaan Hove Antwerpen 2540",
    "addr:postcode":"2540",
    "addr:street":"Fazantenlaan",
    "iso:country":"BE",
    "sg:address":"Fazantenlaan",
    "sg:city":"Hove",
    "sg:orig_category":"Gestion des d\u00e9charges and sites d\u00e9finitifs de stockage",
    "sg:phone":"+32 3 454 43 10",
    "sg:postcode":"2540",
    "sg:province":"Antwerpen",
    "wof:name":"Containerpark Hove",
    "wof:placetype":"venue"
},
  "geometry": {"coordinates":[4.4772901535,51.1477737427],"type":"Point"}
}