{
  "type": "Feature",
  "properties": {
    "addr:full":"Isabellastraat 26 Dilbeek (schepdaal) Vlaams-Brabant 1703",
    "addr:housenumber":"26",
    "addr:postcode":"1703",
    "addr:street":"Isabellastraat",
    "iso:country":"BE",
    "sg:address":"Isabellastraat 26",
    "sg:city":"Dilbeek (schepdaal)",
    "sg:classifiers":[
        {
            "category":"Personal",
            "subcategory":"Beauty Salon",
            "type":"Services"
        }
    ],
    "sg:phone":"+32 2 569 16 92",
    "sg:postcode":"1703",
    "sg:province":"Vlaams-Brabant",
    "wof:name":"Vanhecke A",
    "wof:placetype":"venue"
},
  "geometry": {"coordinates":[4.2091817856,50.8263015747],"type":"Point"}
}