{
  "type": "Feature",
  "properties": {
    "iso:country":"BE",
    "sg:address":"Rue Patenier 20",
    "sg:city":"Namur",
    "sg:orig_category":"Reisbureaus",
    "sg:phone":"+32 81 74 24 28",
    "sg:postcode":"5000",
    "sg:province":"Namur",
    "wof:name":"Art Diffusion",
    "wof:placetype":"venue"
},
  "geometry": {"coordinates":[4.8472018242,50.4640159607],"type":"Point"}
}