{
  "type": "Feature",
  "properties": {
    "iso:country":"BE",
    "sg:address":"Stationsstraat 43",
    "sg:city":"Heist-op-den-berg",
    "sg:orig_category":"Fleurs and plantes",
    "sg:phone":"+32 15 24 58 37",
    "sg:postcode":"2220",
    "sg:province":"Antwerpen",
    "wof:name":"Arte Verde",
    "wof:placetype":"venue"
},
  "geometry": {"coordinates":[4.7119221687,51.0759468079],"type":"Point"}
}