{
  "type": "Feature",
  "properties": {
    "iso:country":"BE",
    "sg:address":"Binnenblokken 5",
    "sg:city":"Geel",
    "sg:classifiers":[
        {
            "category":"Retail",
            "subcategory":"Veterinary Services",
            "type":"Services"
        }
    ],
    "sg:phone":"+32 14 72 54 47",
    "sg:postcode":"2440",
    "sg:province":"Antwerpen",
    "sg:tags":[
        "veterinarian"
    ],
    "wof:name":"Mertens E",
    "wof:placetype":"venue"
},
  "geometry": {"coordinates":[5.0175580978,51.1839370728],"type":"Point"}
}