{
  "type": "Feature",
  "properties": {
    "iso:country":"BE",
    "sg:address":"Strijdersstraat 39",
    "sg:city":"Edegem",
    "sg:orig_category":"Boissons",
    "sg:phone":"+32 3 457 01 64",
    "sg:postcode":"2650",
    "sg:province":"Antwerpen",
    "wof:name":"Beirens Center Drinks",
    "wof:placetype":"venue"
},
  "geometry": {"coordinates":[4.4438657761,51.1567382812],"type":"Point"}
}