{
  "type": "Feature",
  "properties": {
    "iso:country":"BE",
    "sg:address":"Ninoofse Steenweg 83",
    "sg:city":"Halle",
    "sg:orig_category":"Elektrische installaties voor woningen Huishoudapparaten, televisies and radio's Industri\u00eble elektri",
    "sg:phone":"+32 2 356 87 71",
    "sg:postcode":"1500",
    "sg:province":"Vlaams-Brabant",
    "wof:name":"Selexion",
    "wof:placetype":"venue"
},
  "geometry": {"coordinates":[4.233104229,50.7383155823],"type":"Point"}
}