{
  "type": "Feature",
  "properties": {
    "addr:full":"Kapellekensweg 1bb Tielt-winge Vlaams-Brabant 3391",
    "addr:housenumber":"1bb",
    "addr:postcode":"3391",
    "addr:street":"Kapellekensweg",
    "iso:country":"BE",
    "sg:address":"Kapellekensweg 1bb",
    "sg:city":"Tielt-winge",
    "sg:orig_category":"Producteurs de fruits",
    "sg:phone":"+32 16 63 23 10",
    "sg:postcode":"3391",
    "sg:province":"Vlaams-Brabant",
    "wof:name":"Jan Van Cauwenbergh",
    "wof:placetype":"venue"
},
  "geometry": {"coordinates":[4.903591156,50.8981323242],"type":"Point"}
}