{
  "type": "Feature",
  "properties": {
    "addr:full":"Avenue Brugmann 536 Bruxelles (uccle) Bruxelles-Capitale 1180",
    "addr:housenumber":"536",
    "addr:postcode":"1180",
    "addr:street":"Avenue Brugmann",
    "iso:country":"BE",
    "sg:address":"Avenue Brugmann 536",
    "sg:city":"Bruxelles (uccle)",
    "sg:classifiers":[
        {
            "category":"Health Services",
            "subcategory":"Doctor",
            "type":"Services"
        }
    ],
    "sg:phone":"+32 2 343 94 98",
    "sg:postcode":"1180",
    "sg:province":"Bruxelles-Capitale",
    "sg:tags":[
        "medicinephysicians",
        "surgeon"
    ],
    "wof:name":"Dormal Christine",
    "wof:placetype":"venue"
},
  "geometry": {"coordinates":[4.3377509117,50.8006439209],"type":"Point"}
}