{
  "type": "Feature",
  "properties": {
    "iso:country":"BE",
    "sg:address":"Rue Des Graveurs 8",
    "sg:city":"Ottignies-louvain-la-neuve",
    "sg:orig_category":"Diverse bedrijfsbeheeradviesbureaus",
    "sg:phone":"+32 10 45 73 56",
    "sg:postcode":"1348",
    "sg:province":"Brabant Wallon",
    "wof:name":"V.m.a. Consulting",
    "wof:placetype":"venue"
},
  "geometry": {"coordinates":[4.6072711945,50.6654090881],"type":"Point"}
}