{
  "type": "Feature",
  "properties": {
    "iso:country":"BE",
    "sg:address":"Rue De La Colline 72",
    "sg:city":"Chapelle-lez-herlaimont",
    "sg:classifiers":[
        {
            "category":"Home & Garden",
            "subcategory":"Hardware",
            "type":"Retail Goods"
        }
    ],
    "sg:phone":"+32 64 45 97 13",
    "sg:postcode":"7160",
    "sg:province":"Hainaut",
    "sg:tags":[
        "-"
    ],
    "wof:name":"Parc (du)",
    "wof:placetype":"venue"
},
  "geometry": {"coordinates":[4.2843489647,50.4701843262],"type":"Point"}
}