{
  "type": "Feature",
  "properties": {
    "iso:country":"BE",
    "sg:address":"Rue Gr\u00e9goire Wincqz 213",
    "sg:city":"Soignies",
    "sg:classifiers":[
        {
            "category":"Bakery",
            "type":"Food & Drink"
        }
    ],
    "sg:phone":"+32 67 33 24 28",
    "sg:postcode":"7060",
    "sg:province":"Hainaut",
    "sg:tags":[
        "confectioner",
        "baker"
    ],
    "wof:name":"Limbourg P",
    "wof:placetype":"venue"
},
  "geometry": {"coordinates":[4.0773859024,50.5714607239],"type":"Point"}
}