{
  "type": "Feature",
  "properties": {
    "addr:full":"Mechelbaan 344 Putte Antwerpen 2580",
    "addr:housenumber":"344",
    "addr:postcode":"2580",
    "addr:street":"Mechelbaan",
    "iso:country":"BE",
    "sg:address":"Mechelbaan 344",
    "sg:city":"Putte",
    "sg:classifiers":[
        {
            "category":"Health Services",
            "subcategory":"Dentist",
            "type":"Services"
        }
    ],
    "sg:phone":"+32 15 24 03 90",
    "sg:postcode":"2580",
    "sg:province":"Antwerpen",
    "wof:name":"Van De Moortel Kristien",
    "wof:placetype":"venue"
},
  "geometry": {"coordinates":[4.633784771,51.0570716858],"type":"Point"}
}