{
  "type": "Feature",
  "properties": {
    "addr:full":"Stooktstraat 161 Ronse/renaix Oost-Vlaanderen 9600",
    "addr:housenumber":"161",
    "addr:postcode":"9600",
    "addr:street":"Stooktstraat",
    "iso:country":"BE",
    "sg:address":"Stooktstraat 161",
    "sg:city":"Ronse/renaix",
    "sg:classifiers":[
        {
            "category":"Cafe",
            "type":"Food & Drink"
        }
    ],
    "sg:phone":"+32 55 21 23 38",
    "sg:postcode":"9600",
    "sg:province":"Oost-Vlaanderen",
    "sg:tags":[
        "caf\u00e9s"
    ],
    "wof:name":"Sportiva",
    "wof:placetype":"venue"
},
  "geometry": {"coordinates":[3.6094698906,50.734916687],"type":"Point"}
}