{
  "type": "Feature",
  "properties": {
    "addr:full":"Dorp 24 Nazareth Oost-Vlaanderen 9810",
    "addr:housenumber":"24",
    "addr:postcode":"9810",
    "addr:street":"Dorp",
    "iso:country":"BE",
    "sg:address":"Dorp 24",
    "sg:city":"Nazareth",
    "sg:orig_category":"R\u00e9parations de chaussures and articles en cuir",
    "sg:phone":"+32 9 385 31 33",
    "sg:postcode":"9810",
    "sg:province":"Oost-Vlaanderen",
    "wof:name":"Schoenmakerij Arthur",
    "wof:placetype":"venue"
},
  "geometry": {"coordinates":[3.5968420506,50.9597740173],"type":"Point"}
}