{
  "type": "Feature",
  "properties": {
    "addr:full":"Rue Adolphe Sax 47 Dinant Namur 5500",
    "addr:housenumber":"47",
    "addr:postcode":"5500",
    "addr:street":"Rue Adolphe Sax",
    "iso:country":"BE",
    "sg:address":"Rue Adolphe Sax 47",
    "sg:city":"Dinant",
    "sg:classifiers":[
        {
            "category":"Shopping",
            "subcategory":"Jewelry",
            "type":"Retail Goods"
        }
    ],
    "sg:phone":"+32 82 22 57 65",
    "sg:postcode":"5500",
    "sg:province":"Namur",
    "sg:tags":[
        "jeweller",
        "-"
    ],
    "wof:name":"Michaux A-m",
    "wof:placetype":"venue"
},
  "geometry": {"coordinates":[4.9106578827,50.262260437],"type":"Point"}
}