{
  "type": "Feature",
  "properties": {
    "iso:country":"BE",
    "sg:address":"Noordlaan 158",
    "sg:city":"Dendermonde",
    "sg:classifiers":[
        {
            "category":"Professional",
            "subcategory":"Accounting & Tax Preparation",
            "type":"Services"
        }
    ],
    "sg:phone":"+32 52 21 71 89",
    "sg:postcode":"9200",
    "sg:province":"Oost-Vlaanderen",
    "sg:tags":[
        "bookkeeper"
    ],
    "wof:name":"Meulebroek I",
    "wof:placetype":"venue"
},
  "geometry": {"coordinates":[4.0917410851,51.0338020325],"type":"Point"}
}