{
  "type": "Feature",
  "properties": {
    "addr:full":"Rue Du Moulin 4 Trois-ponts Li\u00e8ge 4983",
    "addr:housenumber":"4",
    "addr:postcode":"4983",
    "addr:street":"Rue Du Moulin",
    "iso:country":"BE",
    "sg:address":"Rue Du Moulin 4",
    "sg:city":"Trois-ponts",
    "sg:classifiers":[
        {
            "category":"Shopping Center",
            "type":"Public Place"
        }
    ],
    "sg:phone":"+32 80 68 49 20",
    "sg:postcode":"4983",
    "sg:province":"Li\u00e8ge",
    "sg:tags":[
        "de",
        "terrain",
        "camping",
        "restaurant"
    ],
    "wof:name":"Camping Site Du Moulin",
    "wof:placetype":"venue"
},
  "geometry": {"coordinates":[5.8363199234,50.3598594666],"type":"Point"}
}