{
  "type": "Feature",
  "properties": {
    "iso:country":"BE",
    "sg:address":"Leynseelstraat 66",
    "sg:city":"Avelgem",
    "sg:classifiers":[
        {
            "category":"Retail",
            "subcategory":"Auto Repair",
            "type":"Services"
        }
    ],
    "sg:phone":"+32 56 64 46 50",
    "sg:postcode":"8580",
    "sg:province":"West-Vlaanderen",
    "sg:tags":[
        "automobile",
        "servic",
        "electrical",
        "-"
    ],
    "wof:name":"Paret Nv",
    "wof:placetype":"venue"
},
  "geometry": {"coordinates":[3.4317650795,50.7754631042],"type":"Point"}
}