{
  "type": "Feature",
  "properties": {
    "addr:full":"Rue Dommartin 12 Saint-georges-sur-meuse Li\u00e8ge 4470",
    "addr:housenumber":"12",
    "addr:postcode":"4470",
    "addr:street":"Rue Dommartin",
    "iso:country":"BE",
    "sg:address":"Rue Dommartin 12",
    "sg:city":"Saint-georges-sur-meuse",
    "sg:classifiers":[
        {
            "category":"Professional",
            "subcategory":"Art Services",
            "type":"Services"
        }
    ],
    "sg:phone":"+32 4 259 52 87",
    "sg:postcode":"4470",
    "sg:province":"Li\u00e8ge",
    "sg:tags":[
        "decorative",
        "joinery"
    ],
    "wof:name":"Houbrechts G",
    "wof:placetype":"venue"
},
  "geometry": {"coordinates":[5.3657298088,50.6163520813],"type":"Point"}
}