{
  "type": "Feature",
  "properties": {
    "addr:full":"Malendriesstraat 40 Boutersem (kerkom) Vlaams-Brabant 3370",
    "addr:housenumber":"40",
    "addr:postcode":"3370",
    "addr:street":"Malendriesstraat",
    "iso:country":"BE",
    "sg:address":"Malendriesstraat 40",
    "sg:city":"Boutersem (kerkom)",
    "sg:classifiers":[
        {
            "category":"Bars & Pubs",
            "type":"Food & Drink"
        }
    ],
    "sg:phone":"+32 16 73 32 75",
    "sg:postcode":"3370",
    "sg:province":"Vlaams-Brabant",
    "wof:name":"Parijs-roubaix",
    "wof:placetype":"venue"
},
  "geometry": {"coordinates":[4.8700060844,50.85779953],"type":"Point"}
}