{
  "type": "Feature",
  "properties": {
    "iso:country":"BE",
    "sg:address":"Kreupelstraat 136",
    "sg:city":"Zemst",
    "sg:orig_category":"Agences immobili\u00e8res",
    "sg:phone":"+32 15 61 35 56",
    "sg:postcode":"1980",
    "sg:province":"Vlaams-Brabant",
    "wof:name":"Mathieu Verwilghen",
    "wof:placetype":"venue"
},
  "geometry": {"coordinates":[4.4457678795,50.9627189636],"type":"Point"}
}