{
  "type": "Feature",
  "properties": {
    "addr:full":"Professor Dewulfstraat 121 Poperinge West-Vlaanderen 8970",
    "addr:housenumber":"121",
    "addr:postcode":"8970",
    "addr:street":"Professor Dewulfstraat",
    "iso:country":"BE",
    "sg:address":"Professor Dewulfstraat 121",
    "sg:city":"Poperinge",
    "sg:orig_category":"Artsen and specialisten",
    "sg:phone":"+32 57 33 86 55",
    "sg:postcode":"8970",
    "sg:province":"West-Vlaanderen",
    "wof:name":"Jan De Groote",
    "wof:placetype":"venue"
},
  "geometry": {"coordinates":[2.7362821102,50.8498802185],"type":"Point"}
}