{
  "type": "Feature",
  "properties": {
    "addr:full":"Malmedyer Strasse 56 B\u00fctgenbach Li\u00e8ge 4750",
    "addr:housenumber":"56",
    "addr:postcode":"4750",
    "addr:street":"Malmedyer Strasse",
    "iso:country":"BE",
    "sg:address":"Malmedyer Strasse 56",
    "sg:city":"B\u00fctgenbach",
    "sg:classifiers":[
        {
            "category":"Retail",
            "subcategory":"Auto Repair",
            "type":"Services"
        }
    ],
    "sg:phone":"+32 80 44 65 54",
    "sg:postcode":"4750",
    "sg:province":"Li\u00e8ge",
    "sg:tags":[
        "garage"
    ],
    "wof:name":"M. Cars Sprl",
    "wof:placetype":"venue"
},
  "geometry": {"coordinates":[6.1945910454,50.4239311218],"type":"Point"}
}