{
  "type": "Feature",
  "properties": {
    "iso:country":"BE",
    "sg:address":"Sint-benedictusstraat 132b2",
    "sg:city":"Mortsel",
    "sg:orig_category":"Advocaten and juridische adviseurs",
    "sg:phone":"+32 3 449 03 77",
    "sg:postcode":"2640",
    "sg:province":"Antwerpen",
    "wof:name":"Luc Potargent",
    "wof:placetype":"venue"
},
  "geometry": {"coordinates":[4.4573721886,51.1691665649],"type":"Point"}
}