{
  "type": "Feature",
  "properties": {
    "addr:full":"Weg Naar As 14b Opglabbeek Limburg 3660",
    "addr:housenumber":"14b",
    "addr:postcode":"3660",
    "addr:street":"Weg Naar As",
    "iso:country":"BE",
    "sg:address":"Weg Naar As 14b",
    "sg:city":"Opglabbeek",
    "sg:classifiers":[
        {
            "category":"Food & Beverages",
            "subcategory":"Fruits & Vegetables",
            "type":"Retail Goods"
        }
    ],
    "sg:phone":"+32 89 65 06 15",
    "sg:postcode":"3660",
    "sg:province":"Limburg",
    "sg:tags":[
        "-"
    ],
    "wof:name":"Selderke ('t)",
    "wof:placetype":"venue"
},
  "geometry": {"coordinates":[5.5828061104,51.0404319763],"type":"Point"}
}