{
  "type": "Feature",
  "properties": {
    "addr:full":"Place Eug\u00e8ne Verboekhoven 1 Bruxelles (schaerbeek) Bruxelles-Capitale 1030",
    "addr:housenumber":"1",
    "addr:postcode":"1030",
    "addr:street":"Place Euge\u0300Ne Verboekhoven",
    "iso:country":"BE",
    "sg:address":"Place Eug\u00e8ne Verboekhoven 1",
    "sg:city":"Bruxelles (schaerbeek)",
    "sg:classifiers":[
        {
            "category":"Home & Garden",
            "subcategory":"Building Materials",
            "type":"Retail Goods"
        }
    ],
    "sg:phone":"+32 2 216 87 44",
    "sg:postcode":"1030",
    "sg:province":"Bruxelles-Capitale",
    "sg:tags":[
        "article",
        "-",
        "do-it-yourself"
    ],
    "wof:name":"Brico Genc Sprl",
    "wof:placetype":"venue"
},
  "geometry": {"coordinates":[4.3753881454,50.8709907532],"type":"Point"}
}