{
  "type": "Feature",
  "properties": {
    "addr:full":"Rue Du Moulin 19 Ottignies-louvain-la-neuve Brabant Wallon 1340",
    "addr:housenumber":"19",
    "addr:postcode":"1340",
    "addr:street":"Rue Du Moulin",
    "iso:country":"BE",
    "sg:address":"Rue Du Moulin 19",
    "sg:city":"Ottignies-louvain-la-neuve",
    "sg:orig_category":"M\u00e9decins and sp\u00e9cialistes",
    "sg:phone":"+32 10 40 13 76",
    "sg:postcode":"1340",
    "sg:province":"Brabant Wallon",
    "wof:name":"M. Meroueh",
    "wof:placetype":"venue"
},
  "geometry": {"coordinates":[4.5686511993,50.6653862],"type":"Point"}
}