{
  "type": "Feature",
  "properties": {
    "addr:full":"Ch De Lodelinsart 226 Gilly Hainaut 6060",
    "addr:housenumber":"226",
    "addr:postcode":"6060",
    "addr:street":"Ch De Lodelinsart",
    "iso:country":"BE",
    "sg:address":"Ch De Lodelinsart 226",
    "sg:city":"Gilly",
    "sg:classifiers":[
        {
            "category":"Shopping",
            "subcategory":"Computers & Home Electronics",
            "type":"Retail Goods"
        }
    ],
    "sg:phone":"+32 71 41 14 09",
    "sg:postcode":"6060",
    "sg:province":"Hainaut",
    "sg:tags":[
        "equipment",
        "household",
        "electrical",
        "appliance",
        "electronic"
    ],
    "wof:name":"Dimacom Import",
    "wof:placetype":"venue"
},
  "geometry": {"coordinates":[4.4711909294,50.4281044006],"type":"Point"}
}