{
  "type": "Feature",
  "properties": {
    "addr:full":"Menensteenweg 18 Moorslede West-Vlaanderen 8890",
    "addr:housenumber":"18",
    "addr:postcode":"8890",
    "addr:street":"Menensteenweg",
    "iso:country":"BE",
    "sg:address":"Menensteenweg 18",
    "sg:city":"Moorslede",
    "sg:orig_category":"D\u00e9taillants en pi\u00e8ces and accessoires de voitures",
    "sg:phone":"+32 56 50 03 41",
    "sg:postcode":"8890",
    "sg:province":"West-Vlaanderen",
    "wof:name":"Terryn",
    "wof:placetype":"venue"
},
  "geometry": {"coordinates":[3.098886013,50.8473625183],"type":"Point"}
}