{
  "type": "Feature",
  "properties": {
    "addr:full":"Pieter Breughellaan 1 Rumst Antwerpen 2840",
    "addr:housenumber":"1",
    "addr:postcode":"2840",
    "addr:street":"Pieter Breughellaan",
    "iso:country":"BE",
    "sg:address":"Pieter Breughellaan 1",
    "sg:city":"Rumst",
    "sg:orig_category":"M\u00e9decins and sp\u00e9cialistes",
    "sg:phone":"+32 3 844 25 42",
    "sg:postcode":"2840",
    "sg:province":"Antwerpen",
    "wof:name":"Kristine N.a. Desager",
    "wof:placetype":"venue"
},
  "geometry": {"coordinates":[4.4047198296,51.1037940979],"type":"Point"}
}