{
  "type": "Feature",
  "properties": {
    "iso:country":"BE",
    "sg:address":"Keulemansstraat 41",
    "sg:city":"Herenthout",
    "sg:orig_category":"Bloemen and planten",
    "sg:phone":"+32 14 51 78 68",
    "sg:postcode":"2270",
    "sg:province":"Antwerpen",
    "wof:name":"Josee Poelmans",
    "wof:placetype":"venue"
},
  "geometry": {"coordinates":[4.750043869,51.1368598938],"type":"Point"}
}