{
  "type": "Feature",
  "properties": {
    "iso:country":"BE",
    "sg:address":"G. Gezellelaan 100",
    "sg:city":"Heusden-zolder",
    "sg:orig_category":"Herstellingen and onderhoud van auto's Voertuigen",
    "sg:phone":"+32 11 42 47 10",
    "sg:postcode":"3550",
    "sg:province":"Limburg",
    "wof:name":"Garage Kwanten",
    "wof:placetype":"venue"
},
  "geometry": {"coordinates":[5.2744069099,51.030040741],"type":"Point"}
}