{
  "type": "Feature",
  "properties": {
    "iso:country":"BE",
    "sg:address":"Zandstraat 1a",
    "sg:city":"Kortrijk",
    "sg:orig_category":"Newspapers, magazines, periodicals - Distribution",
    "sg:phone":"+32 56 21 89 41",
    "sg:postcode":"8500",
    "sg:province":"West-Vlaanderen",
    "wof:name":"Andere Boek (het)",
    "wof:placetype":"venue"
},
  "geometry": {"coordinates":[3.2586710453,50.8254776001],"type":"Point"}
}