{
  "type": "Feature",
  "properties": {
    "iso:country":"BE",
    "sg:address":"G. Demeurslaan 71",
    "sg:city":"Huizingen",
    "sg:classifiers":[
        {
            "category":"Retail",
            "subcategory":"Event Space",
            "type":"Services"
        }
    ],
    "sg:phone":"+32 2 363 15 70",
    "sg:postcode":"1654",
    "sg:province":"Vlaams-Brabant",
    "sg:tags":[
        "pharmaceutical",
        "speciality"
    ],
    "wof:name":"Pharma Logistics Nv",
    "wof:placetype":"venue"
},
  "geometry": {"coordinates":[4.2652201653,50.7563514709],"type":"Point"}
}