{
  "type": "Feature",
  "properties": {
    "addr:full":"Lescheret 2 Vaux-sur-s\u00fbre (juseret) Luxembourg 6642",
    "addr:housenumber":"2",
    "addr:postcode":"6642",
    "addr:street":"Lescheret",
    "iso:country":"BE",
    "sg:address":"Lescheret 2",
    "sg:city":"Vaux-sur-s\u00fbre (juseret)",
    "sg:classifiers":[
        {
            "category":"Recreation",
            "subcategory":"Campground",
            "type":"Entertainment"
        }
    ],
    "sg:phone":"+32 61 25 50 49",
    "sg:postcode":"6642",
    "sg:province":"Luxembourg",
    "sg:tags":[
        "site",
        "camping"
    ],
    "wof:name":"Sources De Lescheret (aux)",
    "wof:placetype":"venue"
},
  "geometry": {"coordinates":[5.5497012138,49.8756828308],"type":"Point"}
}