{
  "type": "Feature",
  "properties": {
    "addr:full":"Parklaan Ninove Oost-Vlaanderen 9400",
    "addr:postcode":"9400",
    "addr:street":"Parklaan",
    "iso:country":"BE",
    "sg:address":"Parklaan",
    "sg:city":"Ninove",
    "sg:classifiers":[
        {
            "category":"Education",
            "subcategory":"School",
            "type":"Public Place"
        }
    ],
    "sg:phone":"+32 54 33 22 36",
    "sg:postcode":"9400",
    "sg:province":"Oost-Vlaanderen",
    "sg:tags":[
        "primary"
    ],
    "wof:name":"Stedelijke Basisschool",
    "wof:placetype":"venue"
},
  "geometry": {"coordinates":[4.0200548172,50.8293685913],"type":"Point"}
}