{
  "type": "Feature",
  "properties": {
    "addr:full":"Rue De Souvret 71 Fontaine-l'eveque Hainaut 6141",
    "addr:housenumber":"71",
    "addr:postcode":"6141",
    "addr:street":"Rue De Souvret;Hainaut",
    "iso:country":"BE",
    "sg:address":"Rue De Souvret 71",
    "sg:city":"Fontaine-l'eveque",
    "sg:orig_category":"Traitements param\u00e9dicaux",
    "sg:phone":"+32 71 52 84 04",
    "sg:postcode":"6141",
    "sg:province":"Hainaut",
    "wof:name":"D. Ceccato",
    "wof:placetype":"venue"
},
  "geometry": {"coordinates":[4.3369789124,50.4389572144],"type":"Point"}
}