{
  "type": "Feature",
  "properties": {
    "iso:country":"BE",
    "sg:address":"Grote Markt 20",
    "sg:city":"Kortrijk",
    "sg:orig_category":"Beheer onroerend goed Immobili\u00ebnkantoren Landmeters and schatters",
    "sg:phone":"+32 56 22 55 66",
    "sg:postcode":"8500",
    "sg:province":"West-Vlaanderen",
    "wof:name":"Immokortrijk",
    "wof:placetype":"venue"
},
  "geometry": {"coordinates":[3.2669301033,50.8276062012],"type":"Point"}
}