{
  "type": "Feature",
  "properties": {
    "iso:country":"BE",
    "sg:address":"Steenweg Deinze 53",
    "sg:city":"Nazareth",
    "sg:orig_category":"Catering and organisation de f\u00eates",
    "sg:phone":"+32 9 386 90 53",
    "sg:postcode":"9810",
    "sg:province":"Oost-Vlaanderen",
    "wof:name":"Peter Van Der Veken",
    "wof:placetype":"venue"
},
  "geometry": {"coordinates":[3.5753540993,50.9503669739],"type":"Point"}
}