{
  "type": "Feature",
  "properties": {
    "iso:country":"BE",
    "sg:address":"Rue De La Fourche 24",
    "sg:city":"Bruxelles",
    "sg:classifiers":[
        {
            "category":"Cafe",
            "type":"Food & Drink"
        }
    ],
    "sg:phone":"+32 2 223 06 25",
    "sg:postcode":"1000",
    "sg:province":"Bruxelles-Capitale",
    "sg:tags":[
        "snack-bars"
    ],
    "wof:name":"Pic-nic (le)",
    "wof:placetype":"venue"
},
  "geometry": {"coordinates":[4.3531389236,50.8482780457],"type":"Point"}
}