{
  "type": "Feature",
  "properties": {
    "addr:full":"Kamperbaan 30 Hechtel-eksel (hechtel) Limburg 3940",
    "addr:housenumber":"30",
    "addr:postcode":"3940",
    "addr:street":"Kamperbaan",
    "iso:country":"BE",
    "sg:address":"Kamperbaan 30",
    "sg:city":"Hechtel-eksel (hechtel)",
    "sg:classifiers":[
        {
            "category":"Home & Garden",
            "subcategory":"Home Furnishings",
            "type":"Retail Goods"
        }
    ],
    "sg:phone":"+32 11 73 41 80",
    "sg:postcode":"3940",
    "sg:province":"Limburg",
    "sg:tags":[
        "interior",
        "decoration"
    ],
    "wof:name":"Deco 2000",
    "wof:placetype":"venue"
},
  "geometry": {"coordinates":[5.364795208,51.1255340576],"type":"Point"}
}