{
  "type": "Feature",
  "properties": {
    "addr:full":"Avenue Jean Delhaye 1 Namur Namur 5001",
    "addr:housenumber":"1",
    "addr:postcode":"5001",
    "addr:street":"Avenue Jean Delhaye",
    "iso:country":"BE",
    "sg:address":"Avenue Jean Delhaye 1",
    "sg:city":"Namur",
    "sg:orig_category":"Apotheken",
    "sg:phone":"+32 81 74 11 53",
    "sg:postcode":"5001",
    "sg:province":"Namur",
    "wof:name":"La Boverie",
    "wof:placetype":"venue"
},
  "geometry": {"coordinates":[4.8242349625,50.4648857117],"type":"Point"}
}