{
  "type": "Feature",
  "properties": {
    "iso:country":"BE",
    "sg:address":"Zuidstraat 6",
    "sg:city":"Oostkamp",
    "sg:orig_category":"Meubelzaken, woning- and keukeninrichting",
    "sg:phone":"+32 50 27 79 65",
    "sg:postcode":"8020",
    "sg:province":"West-Vlaanderen",
    "wof:name":"Verhelst M En Zoon",
    "wof:placetype":"venue"
},
  "geometry": {"coordinates":[3.2245531082,51.110710144],"type":"Point"}
}