{
  "type": "Feature",
  "properties": {
    "addr:full":"Molenstraat 7 Puurs Antwerpen 2870",
    "addr:housenumber":"7",
    "addr:postcode":"2870",
    "addr:street":"Molenstraat",
    "iso:country":"BE",
    "sg:address":"Molenstraat 7",
    "sg:city":"Puurs",
    "sg:classifiers":[
        {
            "category":"Education",
            "subcategory":"School",
            "type":"Public Place"
        }
    ],
    "sg:phone":"+32 3 889 15 30",
    "sg:postcode":"2870",
    "sg:province":"Antwerpen",
    "sg:tags":[
        "primary"
    ],
    "wof:name":"B.s.g.o. Gemeenschapsonderwijs Puurs",
    "wof:placetype":"venue"
},
  "geometry": {"coordinates":[4.2890901566,51.0734825134],"type":"Point"}
}