{
  "type": "Feature",
  "properties": {
    "addr:full":"Rue Des Marlaires 22 Pont-a-celles Hainaut 6230",
    "addr:housenumber":"22",
    "addr:postcode":"6230",
    "addr:street":"Rue Des Marlaires",
    "iso:country":"BE",
    "sg:address":"Rue Des Marlaires 22",
    "sg:city":"Pont-a-celles",
    "sg:orig_category":"Entretien and r\u00e9parations de voitures",
    "sg:phone":"+32 71 34 50 03",
    "sg:postcode":"6230",
    "sg:province":"Hainaut",
    "wof:name":"Andre Buyse",
    "wof:placetype":"venue"
},
  "geometry": {"coordinates":[4.3707361221,50.507106781],"type":"Point"}
}