{
  "type": "Feature",
  "properties": {
    "iso:country":"BE",
    "sg:address":"Antwerpse Steenweg 48b5",
    "sg:city":"Temse",
    "sg:orig_category":"Artiesten and kunstenaars",
    "sg:phone":"+32 3 711 05 17",
    "sg:postcode":"9140",
    "sg:province":"Oost-Vlaanderen",
    "wof:name":"Fa. Weyers & Borms",
    "wof:placetype":"venue"
},
  "geometry": {"coordinates":[4.1790881157,51.1129341125],"type":"Point"}
}