{
  "type": "Feature",
  "properties": {
    "addr:full":"Dokter Delbekestraat 24 Roeselare West-Vlaanderen 8800",
    "addr:housenumber":"24",
    "addr:postcode":"8800",
    "addr:street":"Dokter Delbekestraat",
    "iso:country":"BE",
    "sg:address":"Dokter Delbekestraat 24",
    "sg:city":"Roeselare",
    "sg:orig_category":"Technisch and beroeps secundair onderwijs",
    "sg:phone":"+32 51 20 88 77",
    "sg:postcode":"8800",
    "sg:province":"West-Vlaanderen",
    "wof:name":"St.lutgartinstituut",
    "wof:placetype":"venue"
},
  "geometry": {"coordinates":[3.1234021187,50.939239502],"type":"Point"}
}