{
  "type": "Feature",
  "properties": {
    "addr:full":"Chauss\u00c9e De Tournai 164 Ath Hainaut 7800",
    "addr:housenumber":"164",
    "addr:postcode":"7800",
    "addr:street":"Chausse\u0301E De Tournai",
    "iso:country":"BE",
    "sg:address":"Chauss\u00c9e De Tournai 164",
    "sg:city":"Ath",
    "sg:orig_category":"Loodgieterij, verwarming and sanitaire installaties",
    "sg:phone":"+32 68 28 11 55",
    "sg:postcode":"7800",
    "sg:province":"Hainaut",
    "wof:name":"Andre Bleux",
    "wof:placetype":"venue"
},
  "geometry": {"coordinates":[3.7663600445,50.6308403015],"type":"Point"}
}