{
  "type": "Feature",
  "properties": {
    "addr:full":"Hunningen 10 Sankt Vith/saint-vith Li\u00e8ge 4784",
    "addr:housenumber":"10",
    "addr:postcode":"4784",
    "addr:street":"Hunningen",
    "iso:country":"BE",
    "sg:address":"Hunningen 10",
    "sg:city":"Sankt Vith/saint-vith",
    "sg:orig_category":"Peinture. Rev\u00eatements pour sols and murs",
    "sg:phone":"+32 80 22 85 75",
    "sg:postcode":"4784",
    "sg:province":"Li\u00e8ge",
    "wof:name":"Mathias Linnertz",
    "wof:placetype":"venue"
},
  "geometry": {"coordinates":[6.0675911903,50.2596511841],"type":"Point"}
}