{
  "type": "Feature",
  "properties": {
    "iso:country":"BE",
    "sg:address":"Z.e.h.albert Heyrbautlaan 29",
    "sg:city":"Dilbeek",
    "sg:classifiers":[
        {
            "category":"Health Services",
            "subcategory":"Doctor",
            "type":"Services"
        }
    ],
    "sg:phone":"+32 2 463 14 51",
    "sg:postcode":"1700",
    "sg:province":"Vlaams-Brabant",
    "sg:tags":[
        "psychotherapist",
        "psychoanalyst"
    ],
    "wof:name":"Van Couwenberghe H",
    "wof:placetype":"venue"
},
  "geometry": {"coordinates":[4.2496728897,50.8629837036],"type":"Point"}
}