{
  "type": "Feature",
  "properties": {
    "iso:country":"BE",
    "sg:address":"Boulevard Joseph Tirou 47b1",
    "sg:city":"Charleroi",
    "sg:orig_category":"G\u00e9n\u00e9alogistes. Services de recherches and bureaux de d\u00e9tectives",
    "sg:phone":"+32 71 30 93 09",
    "sg:postcode":"6000",
    "sg:province":"Hainaut",
    "wof:name":"Bureau Bayens",
    "wof:placetype":"venue"
},
  "geometry": {"coordinates":[4.4399862289,50.4087562561],"type":"Point"}
}