{
  "type": "Feature",
  "properties": {
    "addr:full":"Rue D'harscamp 2 Li\u00c8ge Li\u00e8ge 4020",
    "addr:housenumber":"2",
    "addr:postcode":"4020",
    "addr:street":"Rue D'Harscamp",
    "iso:country":"BE",
    "sg:address":"Rue D'harscamp 2",
    "sg:city":"Li\u00c8ge",
    "sg:orig_category":"Deurwaarders",
    "sg:phone":"+32 4 343 49 35",
    "sg:postcode":"4020",
    "sg:province":"Li\u00e8ge",
    "wof:name":"Hoge Roland",
    "wof:placetype":"venue"
},
  "geometry": {"coordinates":[5.5781598091,50.6349143982],"type":"Point"}
}