{
  "type": "Feature",
  "properties": {
    "addr:full":"Rue Du Pont 36 Andenne Namur 5300",
    "addr:housenumber":"36",
    "addr:postcode":"5300",
    "addr:street":"Rue Du Pont",
    "iso:country":"BE",
    "sg:address":"Rue Du Pont 36",
    "sg:city":"Andenne",
    "sg:classifiers":[
        {
            "category":"Retail",
            "subcategory":"Repair Shop",
            "type":"Services"
        }
    ],
    "sg:phone":"+32 85 84 33 44",
    "sg:postcode":"5300",
    "sg:province":"Namur",
    "sg:tags":[
        "-",
        "clothing",
        "alteration"
    ],
    "wof:name":"Moderny Shop",
    "wof:placetype":"venue"
},
  "geometry": {"coordinates":[5.0964097977,50.492389679],"type":"Point"}
}