{
  "type": "Feature",
  "properties": {
    "iso:country":"BE",
    "sg:address":"Azalealaan 9",
    "sg:city":"Maldegem",
    "sg:orig_category":"Woningbouw",
    "sg:phone":"+32 50 71 34 40",
    "sg:postcode":"9990",
    "sg:province":"Oost-Vlaanderen",
    "wof:name":"Marc Versieck",
    "wof:placetype":"venue"
},
  "geometry": {"coordinates":[3.4561569691,51.2010955811],"type":"Point"}
}