{
  "type": "Feature",
  "properties": {
    "addr:full":"Rue De Robiano 50 Binche Hainaut 7130",
    "addr:housenumber":"50",
    "addr:postcode":"7130",
    "addr:street":"Rue De Robiano",
    "iso:country":"BE",
    "sg:address":"Rue De Robiano 50",
    "sg:city":"Binche",
    "sg:classifiers":[
        {
            "category":"Health Services",
            "subcategory":"Doctor",
            "type":"Services"
        }
    ],
    "sg:phone":"+32 71 30 25 35",
    "sg:postcode":"7130",
    "sg:province":"Hainaut",
    "sg:tags":[
        "orthopedist"
    ],
    "wof:name":"O.m.d.-orthopedie & Medicale Diffusion",
    "wof:placetype":"venue"
},
  "geometry": {"coordinates":[4.1691632271,50.4102935791],"type":"Point"}
}