{
  "type": "Feature",
  "properties": {
    "addr:full":"Avenue Des Cottages 4 Spa Li\u00e8ge 4900",
    "addr:housenumber":"4",
    "addr:postcode":"4900",
    "addr:street":"Avenue Des Cottages",
    "iso:country":"BE",
    "sg:address":"Avenue Des Cottages 4",
    "sg:city":"Spa",
    "sg:orig_category":"Sportclubs",
    "sg:phone":"+32 87 77 31 08",
    "sg:postcode":"4900",
    "sg:province":"Li\u00e8ge",
    "wof:name":"B.c. Hermathenae Spa",
    "wof:placetype":"venue"
},
  "geometry": {"coordinates":[5.8768510818,50.4903106689],"type":"Point"}
}