{
  "type": "Feature",
  "properties": {
    "iso:country":"BE",
    "sg:address":"Rue De Bruxelles 66",
    "sg:city":"Tubize",
    "sg:orig_category":"M\u00e9decins and sp\u00e9cialistes",
    "sg:phone":"+32 2 355 84 80",
    "sg:postcode":"1480",
    "sg:province":"Brabant Wallon",
    "wof:name":"Diem Thuy Le Huu",
    "wof:placetype":"venue"
},
  "geometry": {"coordinates":[4.2039608955,50.6959228516],"type":"Point"}
}