{
  "type": "Feature",
  "properties": {
    "addr:full":"Brederodestraat 125 Antwerpen Antwerpen 2018",
    "addr:housenumber":"125",
    "addr:postcode":"2018",
    "addr:street":"Brederodestraat",
    "iso:country":"BE",
    "sg:address":"Brederodestraat 125",
    "sg:city":"Antwerpen",
    "sg:classifiers":[
        {
            "category":"Cafe",
            "type":"Food & Drink"
        }
    ],
    "sg:phone":"+32 3 216 39 50",
    "sg:postcode":"2018",
    "sg:province":"Antwerpen",
    "sg:tags":[
        "caf\u00e9s"
    ],
    "wof:name":"Albert Van Den Brande",
    "wof:placetype":"venue"
},
  "geometry": {"coordinates":[4.3936691284,51.2030067444],"type":"Point"}
}