{
  "type": "Feature",
  "properties": {
    "addr:full":"Route Du Sati 19 Bouillon Luxembourg 6836",
    "addr:housenumber":"19",
    "addr:postcode":"6836",
    "addr:street":"Route Du Sati",
    "iso:country":"BE",
    "sg:address":"Route Du Sati 19",
    "sg:city":"Bouillon",
    "sg:orig_category":"Pain, p\u00e2tisseries and confiseries. Cr\u00e9meries",
    "sg:phone":"+32 61 46 66 80",
    "sg:postcode":"6836",
    "sg:province":"Luxembourg",
    "wof:name":"Boulangerie La Chaboti\u00c8re",
    "wof:placetype":"venue"
},
  "geometry": {"coordinates":[5.1424150467,49.7956161499],"type":"Point"}
}