{
  "type": "Feature",
  "properties": {
    "addr:full":"Bosstraat 135 Brussel/bruxelles Bruxelles-Capitale 1150",
    "addr:housenumber":"135",
    "addr:postcode":"1150",
    "addr:street":"Bosstraat;/",
    "iso:country":"BE",
    "sg:address":"Bosstraat 135",
    "sg:city":"Brussel/bruxelles",
    "sg:orig_category":"Projectontwikkelaars",
    "sg:phone":"+32 477 53 08 86",
    "sg:postcode":"1150",
    "sg:province":"Bruxelles-Capitale",
    "wof:name":"Ons Ma",
    "wof:placetype":"venue"
},
  "geometry": {"coordinates":[4.4581398964,50.8232383728],"type":"Point"}
}