{
  "type": "Feature",
  "properties": {
    "iso:country":"BE",
    "sg:address":"Sint-truidersteenweg 307",
    "sg:city":"Tongeren",
    "sg:orig_category":"M\u00e9decins and sp\u00e9cialistes",
    "sg:phone":"+32 12 23 92 73",
    "sg:postcode":"3700",
    "sg:province":"Limburg",
    "wof:name":"G. Putzeys",
    "wof:placetype":"venue"
},
  "geometry": {"coordinates":[5.432926178,50.77784729],"type":"Point"}
}