{
  "type": "Feature",
  "properties": {
    "iso:country":"BE",
    "sg:address":"Binderstraat 2",
    "sg:city":"Kortrijk",
    "sg:classifiers":[
        {
            "category":"Arena",
            "subcategory":"Sports Club",
            "type":"Entertainment"
        }
    ],
    "sg:phone":"+32 56 23 86 53",
    "sg:postcode":"8510",
    "sg:province":"West-Vlaanderen",
    "sg:tags":[
        "de"
    ],
    "wof:name":"K.g.k.s. Sint Barbara Marke",
    "wof:placetype":"venue"
},
  "geometry": {"coordinates":[3.2407879829,50.8069229126],"type":"Point"}
}