{
  "type": "Feature",
  "properties": {
    "addr:full":"Rue De Luttre 21 Courcelles Hainaut 6181",
    "addr:housenumber":"21",
    "addr:postcode":"6181",
    "addr:street":"Rue De Luttre",
    "iso:country":"BE",
    "sg:address":"Rue De Luttre 21",
    "sg:city":"Courcelles",
    "sg:orig_category":"Textiel",
    "sg:phone":"+32 71 84 47 90",
    "sg:postcode":"6181",
    "sg:province":"Hainaut",
    "wof:name":"Maison Le Rouet",
    "wof:placetype":"venue"
},
  "geometry": {"coordinates":[4.3312411308,50.4898719788],"type":"Point"}
}