{
  "type": "Feature",
  "properties": {
    "addr:full":"Halmolenweg 12 Halle Antwerpen 2980",
    "addr:housenumber":"12",
    "addr:postcode":"2980",
    "addr:street":"Halmolenweg",
    "iso:country":"BE",
    "sg:address":"Halmolenweg 12",
    "sg:city":"Halle",
    "sg:orig_category":"Installatie van houten of kunststof schrijnwerk",
    "sg:phone":"+32 3 383 24 73",
    "sg:postcode":"2980",
    "sg:province":"Antwerpen",
    "wof:name":"Isoli",
    "wof:placetype":"venue"
},
  "geometry": {"coordinates":[4.6452498436,51.2366676331],"type":"Point"}
}