{
  "type": "Feature",
  "properties": {
    "iso:country":"BE",
    "sg:address":"Torhoutsesteenweg 59",
    "sg:city":"Oostende",
    "sg:classifiers":[
        {
            "category":"Restaurant",
            "type":"Food & Drink"
        }
    ],
    "sg:phone":"+32 59 70 19 02",
    "sg:postcode":"8400",
    "sg:province":"West-Vlaanderen",
    "wof:name":"Tearoom Iris",
    "wof:placetype":"venue"
},
  "geometry": {"coordinates":[2.9090459347,51.2248535156],"type":"Point"}
}