{
  "type": "Feature",
  "properties": {
    "addr:full":"Nolimpark 4011 Overpelt Limburg 3900",
    "addr:postcode":"4011 overpelt;3900",
    "addr:street":"Nolimpark",
    "iso:country":"BE",
    "sg:address":"Nolimpark 4011",
    "sg:city":"Overpelt",
    "sg:orig_category":"Mat\u00e9riaux de construction Quincailleries",
    "sg:phone":"+32 11 66 50 05",
    "sg:postcode":"3900",
    "sg:province":"Limburg",
    "wof:name":"Coram",
    "wof:placetype":"venue"
},
  "geometry": {"coordinates":[5.4235649109,51.2117614746],"type":"Point"}
}