{
  "type": "Feature",
  "properties": {
    "addr:full":"Route De Philippeville 388 Charleroi Hainaut 6010",
    "addr:housenumber":"388",
    "addr:postcode":"6010",
    "addr:street":"Route De Philippeville;Hainaut",
    "iso:country":"BE",
    "sg:address":"Route De Philippeville 388",
    "sg:city":"Charleroi",
    "sg:orig_category":"M\u00e9decins and sp\u00e9cialistes",
    "sg:phone":"+32 71 47 31 97",
    "sg:postcode":"6010",
    "sg:province":"Hainaut",
    "wof:name":"Bernard Nisot",
    "wof:placetype":"venue"
},
  "geometry": {"coordinates":[4.4653849602,50.3814697266],"type":"Point"}
}