{
  "type": "Feature",
  "properties": {
    "addr:full":"Rue De Li\u00c8ge 20 Houffalize Luxembourg 6660",
    "addr:housenumber":"20",
    "addr:postcode":"6660",
    "addr:street":"Rue De Lie\u0300Ge",
    "iso:country":"BE",
    "sg:address":"Rue De Li\u00c8ge 20",
    "sg:city":"Houffalize",
    "sg:orig_category":"Rechtbanken",
    "sg:phone":"+32 61 28 84 65",
    "sg:postcode":"6660",
    "sg:province":"Luxembourg",
    "wof:name":"Justice De Paix",
    "wof:placetype":"venue"
},
  "geometry": {"coordinates":[5.7907471657,50.1335334778],"type":"Point"}
}