{
  "type": "Feature",
  "properties": {
    "iso:country":"BE",
    "sg:address":"Sleidinge Dorp 63",
    "sg:city":"Evergem (sleidinge)",
    "sg:classifiers":[
        {
            "category":"Banks & Credit Unions",
            "subcategory":"Bank",
            "type":"Services"
        }
    ],
    "sg:phone":"+32 9 357 67 86",
    "sg:postcode":"9940",
    "sg:province":"Oost-Vlaanderen",
    "wof:name":"Axa Bank De Craene Els",
    "wof:placetype":"venue"
},
  "geometry": {"coordinates":[3.6797220707,51.1344337463],"type":"Point"}
}