{
  "type": "Feature",
  "properties": {
    "iso:country":"BE",
    "sg:address":"Rue Basse Voie 3b",
    "sg:city":"Havelange",
    "sg:classifiers":[
        {
            "category":"Professional",
            "subcategory":"Advertising",
            "type":"Services"
        }
    ],
    "sg:phone":"+32 83 61 51 16",
    "sg:postcode":"5370",
    "sg:province":"Namur",
    "sg:tags":[
        "bill",
        "-",
        "posting"
    ],
    "wof:name":"Lettering In Line",
    "wof:placetype":"venue"
},
  "geometry": {"coordinates":[5.2439351082,50.3894577026],"type":"Point"}
}