{
  "type": "Feature",
  "properties": {
    "addr:full":"Molendreef 56 Anzegem West-Vlaanderen 8570",
    "addr:housenumber":"56",
    "addr:postcode":"8570",
    "addr:street":"Molendreef",
    "iso:country":"BE",
    "sg:address":"Molendreef 56",
    "sg:city":"Anzegem",
    "sg:orig_category":"Elektrische installaties voor woningen",
    "sg:phone":"+32 56 77 22 20",
    "sg:postcode":"8570",
    "sg:province":"West-Vlaanderen",
    "wof:name":"Bart Martin",
    "wof:placetype":"venue"
},
  "geometry": {"coordinates":[3.4005401134,50.8406562805],"type":"Point"}
}