{
  "type": "Feature",
  "properties": {
    "addr:full":"Ancien Dieweg 17 Bruxelles (uccle) Bruxelles-Capitale 1180",
    "addr:housenumber":"17",
    "addr:postcode":"1180",
    "addr:street":"Ancien Dieweg",
    "iso:country":"BE",
    "sg:address":"Ancien Dieweg 17",
    "sg:city":"Bruxelles (uccle)",
    "sg:classifiers":[
        {
            "category":"Health Services",
            "subcategory":"Doctor",
            "type":"Services"
        }
    ],
    "sg:phone":"+32 495 54 32 17",
    "sg:postcode":"1180",
    "sg:province":"Bruxelles-Capitale",
    "sg:tags":[
        "medicinephysicians",
        "surgeon"
    ],
    "wof:name":"Convent S\u00e9bastien",
    "wof:placetype":"venue"
},
  "geometry": {"coordinates":[4.3344669342,50.7915458679],"type":"Point"}
}