{
  "type": "Feature",
  "properties": {
    "iso:country":"BE",
    "sg:address":"Vrijheid 207",
    "sg:city":"Hoogstraten",
    "sg:orig_category":"Diverse kredietdiensten",
    "sg:postcode":"2320",
    "sg:province":"Antwerpen",
    "wof:name":"Bancontact-mister Cash",
    "wof:placetype":"venue"
},
  "geometry": {"coordinates":[4.7601361275,51.3988265991],"type":"Point"}
}