{
  "type": "Feature",
  "properties": {
    "iso:country":"BE",
    "sg:address":"Boulevard De La Sauveniere 120b",
    "sg:city":"Liege 1",
    "sg:classifiers":[
        {
            "category":"Personal",
            "subcategory":"Beauty Salon",
            "type":"Services"
        }
    ],
    "sg:phone":"+32 4 223 43 38",
    "sg:postcode":"4000",
    "sg:province":"Li\u00e8ge",
    "sg:tags":[
        "lady",
        "-",
        "hairdressing"
    ],
    "wof:name":"Andr\u00e9 Coiffeur",
    "wof:placetype":"venue"
},
  "geometry": {"coordinates":[5.5659518242,50.6421356201],"type":"Point"}
}