{
  "type": "Feature",
  "properties": {
    "addr:full":"Boulevard Du Prince R\u00e9gent 1bis Leuze-en-hainaut Hainaut 7900",
    "addr:housenumber":"1bis",
    "addr:postcode":"7900",
    "addr:street":"Boulevard Du Prince Re\u0301Gent",
    "iso:country":"BE",
    "sg:address":"Boulevard Du Prince R\u00e9gent 1bis",
    "sg:city":"Leuze-en-hainaut",
    "sg:classifiers":[
        {
            "category":"Fast Food",
            "type":"Food & Drink"
        }
    ],
    "sg:phone":"+32 69 77 64 18",
    "sg:postcode":"7900",
    "sg:province":"Hainaut",
    "sg:tags":[
        "fried",
        "stand",
        "potato"
    ],
    "wof:name":"Friterie Du Zoning",
    "wof:placetype":"venue"
},
  "geometry": {"coordinates":[3.6419579983,50.6022071838],"type":"Point"}
}