{
  "type": "Feature",
  "properties": {
    "addr:full":"Meulenberg 5 Sint-gillis-waas (sint-pauwels) Oost-Vlaanderen 9170",
    "addr:housenumber":"5",
    "addr:postcode":"9170",
    "addr:street":"Meulenberg;Sint-Pauwels",
    "iso:country":"BE",
    "sg:address":"Meulenberg 5",
    "sg:city":"Sint-gillis-waas (sint-pauwels)",
    "sg:classifiers":[
        {
            "category":"Professional",
            "subcategory":"Computer Services",
            "type":"Services"
        }
    ],
    "sg:phone":"+32 3 765 00 85",
    "sg:postcode":"9170",
    "sg:province":"Oost-Vlaanderen",
    "sg:tags":[
        "-",
        "processing",
        "data",
        "software"
    ],
    "wof:name":"I.t.services-inghels",
    "wof:placetype":"venue"
},
  "geometry": {"coordinates":[4.0934281349,51.1904678345],"type":"Point"}
}