{
  "type": "Feature",
  "properties": {
    "addr:full":"Olekenbosstraat 120 Deerlijk West-Vlaanderen 8540",
    "addr:housenumber":"120",
    "addr:postcode":"8540",
    "addr:street":"Olekenbosstraat",
    "iso:country":"BE",
    "sg:address":"Olekenbosstraat 120",
    "sg:city":"Deerlijk",
    "sg:classifiers":[
        {
            "category":"Retail",
            "subcategory":"Auto Repair",
            "type":"Services"
        }
    ],
    "sg:phone":"+32 56 77 26 05",
    "sg:postcode":"8540",
    "sg:province":"West-Vlaanderen",
    "sg:tags":[
        "garage"
    ],
    "wof:name":"Debruyne L",
    "wof:placetype":"venue"
},
  "geometry": {"coordinates":[3.3842608929,50.8369483948],"type":"Point"}
}