{
  "type": "Feature",
  "properties": {
    "iso:country":"BE",
    "sg:address":"Muntstraat 12",
    "sg:city":"Leuven",
    "sg:classifiers":[
        {
            "category":"Cafe",
            "type":"Food & Drink"
        }
    ],
    "sg:phone":"+32 16 22 05 67",
    "sg:postcode":"3000",
    "sg:province":"Vlaams-Brabant",
    "sg:tags":[
        "caf\u00e9s"
    ],
    "wof:name":"Caf\u00c9 College",
    "wof:placetype":"venue"
},
  "geometry": {"coordinates":[4.7017359734,50.8783683777],"type":"Point"}
}