{
  "type": "Feature",
  "properties": {
    "iso:country":"BE",
    "sg:address":"Rue De La Station 164",
    "sg:city":"Havelange",
    "sg:classifiers":[
        {
            "category":"Personal",
            "subcategory":"Beauty Salon",
            "type":"Services"
        }
    ],
    "sg:phone":"+32 83 63 30 23",
    "sg:postcode":"5376",
    "sg:province":"Namur",
    "sg:tags":[
        "de",
        "coiffure"
    ],
    "wof:name":"Christine Daxhelet",
    "wof:placetype":"venue"
},
  "geometry": {"coordinates":[5.2577400208,50.3788223267],"type":"Point"}
}