{
  "type": "Feature",
  "properties": {
    "addr:full":"Pastoor Buv\u00c9straat 18 Tienen Vlaams-Brabant 3300",
    "addr:housenumber":"18",
    "addr:postcode":"3300",
    "addr:street":"Pastoor Buve\u0301Straat",
    "iso:country":"BE",
    "sg:address":"Pastoor Buv\u00c9straat 18",
    "sg:city":"Tienen",
    "sg:orig_category":"Afval and schroot Gh",
    "sg:phone":"+32 16 81 84 19",
    "sg:postcode":"3300",
    "sg:province":"Vlaams-Brabant",
    "wof:name":"K. Soetaers",
    "wof:placetype":"venue"
},
  "geometry": {"coordinates":[4.930077076,50.8096694946],"type":"Point"}
}