{
  "type": "Feature",
  "properties": {
    "addr:full":"Domeinlaan 13 Vorst/forest Bruxelles-Capitale 1190",
    "addr:housenumber":"13",
    "addr:postcode":"1190",
    "addr:street":"Domeinlaan;/ Forest",
    "iso:country":"BE",
    "sg:address":"Domeinlaan 13",
    "sg:city":"Vorst/forest",
    "sg:orig_category":"Rusthuizen and serviceflats",
    "sg:phone":"+32 2 346 13 38",
    "sg:postcode":"1190",
    "sg:province":"Bruxelles-Capitale",
    "wof:name":"Seniorie Vesper",
    "wof:placetype":"venue"
},
  "geometry": {"coordinates":[4.3288369179,50.8070755005],"type":"Point"}
}