{
  "type": "Feature",
  "properties": {
    "addr:full":"Place Saint-pierre 10 Etterbeek Bruxelles-Capitale 1040",
    "addr:housenumber":"10",
    "addr:postcode":"1040",
    "addr:street":"Place Saint-Pierre",
    "iso:country":"BE",
    "sg:address":"Place Saint-pierre 10",
    "sg:city":"Etterbeek",
    "sg:orig_category":"Journaux. Tabac. Librairies",
    "sg:phone":"+32 2 735 72 54",
    "sg:postcode":"1040",
    "sg:province":"Bruxelles-Capitale",
    "wof:name":"L\u00b4etoile De St-pierre",
    "wof:placetype":"venue"
},
  "geometry": {"coordinates":[4.3958749771,50.8370323181],"type":"Point"}
}