{
  "type": "Feature",
  "properties": {
    "iso:country":"BE",
    "sg:address":"R.emmanuel Van Driessche 49",
    "sg:city":"Elsene/ixelles",
    "sg:orig_category":"Artistes ind\u00e9pendants",
    "sg:phone":"+32 2 345 03 02",
    "sg:postcode":"1050",
    "sg:province":"Bruxelles-Capitale",
    "wof:name":"Werner Degan",
    "wof:placetype":"venue"
},
  "geometry": {"coordinates":[4.3562908173,50.8193435669],"type":"Point"}
}