{
  "type": "Feature",
  "properties": {
    "addr:full":"Hoge Weg 140 Stabroek Antwerpen 2940",
    "addr:housenumber":"140",
    "addr:postcode":"2940",
    "addr:street":"Hoge Weg",
    "iso:country":"BE",
    "sg:address":"Hoge Weg 140",
    "sg:city":"Stabroek",
    "sg:orig_category":"Divers amusement Geluidsopnames Verhuur televisie- and audiovisuele apparatuur",
    "sg:phone":"+32 3 664 80 99",
    "sg:postcode":"2940",
    "sg:province":"Antwerpen",
    "wof:name":"Sound-express",
    "wof:placetype":"venue"
},
  "geometry": {"coordinates":[4.3906998634,51.3196907043],"type":"Point"}
}