{
  "type": "Feature",
  "properties": {
    "addr:full":"Sint-annastraat 77 Aalst (hofstade) Oost-Vlaanderen 9308",
    "addr:housenumber":"77",
    "addr:postcode":"9308",
    "addr:street":"Sint-Annastraat",
    "iso:country":"BE",
    "sg:address":"Sint-annastraat 77",
    "sg:city":"Aalst (hofstade)",
    "sg:classifiers":[
        {
            "category":"Health Services",
            "subcategory":"Doctor",
            "type":"Services"
        }
    ],
    "sg:phone":"+32 53 78 45 44",
    "sg:postcode":"9308",
    "sg:province":"Oost-Vlaanderen",
    "sg:tags":[
        "medicinephysicians",
        "surgeon"
    ],
    "wof:name":"Jorissen W",
    "wof:placetype":"venue"
},
  "geometry": {"coordinates":[4.0347590446,50.9603500366],"type":"Point"}
}