{
  "type": "Feature",
  "properties": {
    "addr:full":"Rue De Durbuy 30 Hotton Luxembourg 6990",
    "addr:housenumber":"30",
    "addr:postcode":"6990",
    "addr:street":"Rue De Durbuy",
    "iso:country":"BE",
    "sg:address":"Rue De Durbuy 30",
    "sg:city":"Hotton",
    "sg:orig_category":"Eleveurs de bovins",
    "sg:phone":"+32 84 46 64 23",
    "sg:postcode":"6990",
    "sg:province":"Luxembourg",
    "wof:name":"Claudy Mathias",
    "wof:placetype":"venue"
},
  "geometry": {"coordinates":[5.4407558441,50.2854118347],"type":"Point"}
}