{
  "type": "Feature",
  "properties": {
    "addr:full":"Kleine Gammel 34 Rijkevorsel Antwerpen 2310",
    "addr:housenumber":"34",
    "addr:postcode":"2310",
    "addr:street":"Kleine Gammel",
    "iso:country":"BE",
    "sg:address":"Kleine Gammel 34",
    "sg:city":"Rijkevorsel",
    "sg:classifiers":[
        {
            "category":"Home & Garden",
            "subcategory":"Carpets & Floor Coverings",
            "type":"Retail Goods"
        }
    ],
    "sg:phone":"+32 3 314 43 89",
    "sg:postcode":"2310",
    "sg:province":"Antwerpen",
    "sg:tags":[
        "armoring"
    ],
    "wof:name":"Seeuws Luc",
    "wof:placetype":"venue"
},
  "geometry": {"coordinates":[4.7439360619,51.360874176],"type":"Point"}
}