{
  "type": "Feature",
  "properties": {
    "addr:full":"Grand Rue 31 Leuze-en-hainaut Hainaut 7900",
    "addr:housenumber":"31",
    "addr:postcode":"7900",
    "addr:street":"Grand Rue",
    "iso:country":"BE",
    "sg:address":"Grand Rue 31",
    "sg:city":"Leuze-en-hainaut",
    "sg:classifiers":[
        {
            "category":"Professional",
            "subcategory":"Printing & Photocopies",
            "type":"Services"
        }
    ],
    "sg:phone":"+32 69 66 60 41",
    "sg:postcode":"7900",
    "sg:province":"Hainaut",
    "sg:tags":[
        "digital"
    ],
    "wof:name":"Speedy-copy",
    "wof:placetype":"venue"
},
  "geometry": {"coordinates":[3.6192669868,50.6002311707],"type":"Point"}
}