{
  "type": "Feature",
  "properties": {
    "iso:country":"BE",
    "sg:address":"Pave D'ath 1",
    "sg:city":"Edingen/enghien",
    "sg:orig_category":"Enseignement maternel and primaire",
    "sg:phone":"+32 2 395 31 23",
    "sg:postcode":"7850",
    "sg:province":"Hainaut",
    "wof:name":"Ecole Fondamentale Libre",
    "wof:placetype":"venue"
},
  "geometry": {"coordinates":[4.0291719437,50.6896057129],"type":"Point"}
}