{
  "type": "Feature",
  "properties": {
    "iso:country":"BE",
    "sg:address":"Driesstraat 10",
    "sg:city":"Affligem (teralfene)",
    "sg:classifiers":[
        {
            "category":"Health Services",
            "subcategory":"Dentist",
            "type":"Services"
        }
    ],
    "sg:phone":"+32 53 68 01 60",
    "sg:postcode":"1790",
    "sg:province":"Vlaams-Brabant",
    "wof:name":"Van Schelvergem Mieke",
    "wof:placetype":"venue"
},
  "geometry": {"coordinates":[4.098388195,50.8916664124],"type":"Point"}
}