{
  "type": "Feature",
  "properties": {
    "addr:full":"Putstraat 2 Tongeren Limburg 3700",
    "addr:housenumber":"2",
    "addr:postcode":"3700",
    "addr:street":"Putstraat",
    "iso:country":"BE",
    "sg:address":"Putstraat 2",
    "sg:city":"Tongeren",
    "sg:orig_category":"Enseignement maternel and primaire",
    "sg:phone":"+32 12 39 31 09",
    "sg:postcode":"3700",
    "sg:province":"Limburg",
    "wof:name":"Vrije Kleuterschool",
    "wof:placetype":"venue"
},
  "geometry": {"coordinates":[5.4627690315,50.779094696],"type":"Point"}
}