{
  "type": "Feature",
  "properties": {
    "iso:country":"BE",
    "sg:address":"Lange Eikstraat 93",
    "sg:city":"Wezembeek-oppem",
    "sg:orig_category":"Sportclubs",
    "sg:phone":"+32 2 731 30 37",
    "sg:postcode":"1970",
    "sg:province":"Vlaams-Brabant",
    "wof:name":"H.c. Watducks",
    "wof:placetype":"venue"
},
  "geometry": {"coordinates":[4.4908900261,50.8522109985],"type":"Point"}
}