{
  "type": "Feature",
  "properties": {
    "addr:full":"Elisabethlaan 51 Ninove Oost-Vlaanderen 9400",
    "addr:housenumber":"51",
    "addr:postcode":"9400",
    "addr:street":"Elisabethlaan",
    "iso:country":"BE",
    "sg:address":"Elisabethlaan 51",
    "sg:city":"Ninove",
    "sg:classifiers":[
        {
            "category":"Retail",
            "subcategory":"Car Wash",
            "type":"Services"
        }
    ],
    "sg:phone":"+32 54 32 58 21",
    "sg:postcode":"9400",
    "sg:province":"Oost-Vlaanderen",
    "sg:tags":[
        "automobile",
        "washing",
        "-",
        "truck"
    ],
    "wof:name":"Blub",
    "wof:placetype":"venue"
},
  "geometry": {"coordinates":[4.0073537827,50.8359107971],"type":"Point"}
}