{
  "type": "Feature",
  "properties": {
    "addr:full":"Heuvelstraat 82 Tielt-winge (tielt) Vlaams-Brabant 3390",
    "addr:housenumber":"82",
    "addr:postcode":"3390",
    "addr:street":"Heuvelstraat",
    "iso:country":"BE",
    "sg:address":"Heuvelstraat 82",
    "sg:city":"Tielt-winge (tielt)",
    "sg:orig_category":"Non-Classified Establishments",
    "sg:phone":"+32 14 86 85 76",
    "sg:postcode":"3390",
    "sg:province":"Vlaams-Brabant",
    "wof:name":"Vrancken Nv",
    "wof:placetype":"venue"
},
  "geometry": {"coordinates":[4.9462680817,50.9419746399],"type":"Point"}
}