{
  "type": "Feature",
  "properties": {
    "addr:full":"Gospertstrasse 8 Eupen/eupen Li\u00e8ge 4700",
    "addr:housenumber":"8",
    "addr:postcode":"4700",
    "addr:street":"Gospertstrasse",
    "iso:country":"BE",
    "sg:address":"Gospertstrasse 8",
    "sg:city":"Eupen/eupen",
    "sg:orig_category":"Krantenuitgeverijen Tijdschriftenuitgeverijen",
    "sg:phone":"+32 87 74 25 51",
    "sg:postcode":"4700",
    "sg:province":"Li\u00e8ge",
    "wof:name":"Der Wochenspiegel",
    "wof:placetype":"venue"
},
  "geometry": {"coordinates":[6.0333538055,50.6304092407],"type":"Point"}
}