{
  "type": "Feature",
  "properties": {
    "addr:full":"Avenue Des H\u00eatres 21 La Louvi\u00e8re (chapelle Aux Puits) Hainaut 7100",
    "addr:housenumber":"21",
    "addr:postcode":"7100",
    "addr:street":"Avenue Des He\u0302Tres",
    "iso:country":"BE",
    "sg:address":"Avenue Des H\u00eatres 21",
    "sg:city":"La Louvi\u00e8re (chapelle Aux Puits)",
    "sg:classifiers":[
        {
            "category":"Arts & Performance",
            "subcategory":"Music",
            "type":"Entertainment"
        }
    ],
    "sg:phone":"+32 64 54 09 07",
    "sg:postcode":"7100",
    "sg:province":"Hainaut",
    "sg:tags":[
        "freelance",
        "musician"
    ],
    "wof:name":"Abraham Ph",
    "wof:placetype":"venue"
},
  "geometry": {"coordinates":[4.1847009659,50.5202522278],"type":"Point"}
}