{
  "type": "Feature",
  "properties": {
    "addr:full":"Avenue Moli\u00c8re 183 Vorst/forest Bruxelles-Capitale 1190",
    "addr:housenumber":"183",
    "addr:postcode":"1190",
    "addr:street":"Avenue Molie\u0300Re;/ Forest",
    "iso:country":"BE",
    "sg:address":"Avenue Moli\u00c8re 183",
    "sg:city":"Vorst/forest",
    "sg:orig_category":"Avocats and conseillers juridiques",
    "sg:phone":"+32 2 343 95 32",
    "sg:postcode":"1190",
    "sg:province":"Bruxelles-Capitale",
    "wof:name":"E. Marissens/eduard Marissens",
    "wof:placetype":"venue"
},
  "geometry": {"coordinates":[4.349943161,50.8159065247],"type":"Point"}
}