{
  "type": "Feature",
  "properties": {
    "iso:country":"BE",
    "sg:address":"Wellingstraat 21",
    "sg:city":"Evergem",
    "sg:orig_category":"Rundveehouders",
    "sg:phone":"+32 9 357 60 48",
    "sg:postcode":"9940",
    "sg:province":"Oost-Vlaanderen",
    "wof:name":"Hubert Vermeersch",
    "wof:placetype":"venue"
},
  "geometry": {"coordinates":[3.686467886,51.1550788879],"type":"Point"}
}