{
  "type": "Feature",
  "properties": {
    "iso:country":"BE",
    "sg:address":"Rue A. Vandenpeereboom 36",
    "sg:city":"Sint-jans-molenbeek/molenbeek-saint-jean",
    "sg:orig_category":"Entretien and r\u00e9parations de voitures",
    "sg:phone":"+32 2 410 32 32",
    "sg:postcode":"1080",
    "sg:province":"Bruxelles-Capitale",
    "wof:name":"Ets. Thomas & Fils",
    "wof:placetype":"venue"
},
  "geometry": {"coordinates":[4.3253440857,50.8541297913],"type":"Point"}
}