{
  "type": "Feature",
  "properties": {
    "addr:full":"Grotestraat 69 Maasmechelen (boorsem) Limburg 3631",
    "addr:housenumber":"69",
    "addr:postcode":"3631",
    "addr:street":"Grotestraat",
    "iso:country":"BE",
    "sg:address":"Grotestraat 69",
    "sg:city":"Maasmechelen (boorsem)",
    "sg:classifiers":[
        {
            "category":"Health Services",
            "subcategory":"Doctor",
            "type":"Services"
        }
    ],
    "sg:phone":"+32 89 76 74 24",
    "sg:postcode":"3631",
    "sg:province":"Limburg",
    "sg:tags":[
        "medicinephysicians",
        "surgeon"
    ],
    "wof:name":"Gulikers M",
    "wof:placetype":"venue"
},
  "geometry": {"coordinates":[5.7239232063,50.9423713684],"type":"Point"}
}