{
  "type": "Feature",
  "properties": {
    "addr:full":"Avenue Louise 170 Bruxelles (ixelles) Bruxelles-Capitale 1050",
    "addr:housenumber":"170",
    "addr:postcode":"1050",
    "addr:street":"Avenue Louise",
    "iso:country":"BE",
    "sg:address":"Avenue Louise 170",
    "sg:city":"Bruxelles (ixelles)",
    "sg:classifiers":[
        {
            "category":"Bakery",
            "type":"Food & Drink"
        }
    ],
    "sg:phone":"+32 2 644 37 44",
    "sg:postcode":"1050",
    "sg:province":"Bruxelles-Capitale",
    "sg:tags":[
        "confectioner",
        "baker"
    ],
    "wof:name":"Ilse's Croissanterie",
    "wof:placetype":"venue"
},
  "geometry": {"coordinates":[4.3572201729,50.8337287903],"type":"Point"}
}