{
  "type": "Feature",
  "properties": {
    "addr:full":"Rozenhoed 57 Lovendegem (vinderhoute) Oost-Vlaanderen 9921",
    "addr:housenumber":"57",
    "addr:postcode":"9921",
    "addr:street":"Rozenhoed",
    "iso:country":"BE",
    "sg:address":"Rozenhoed 57",
    "sg:city":"Lovendegem (vinderhoute)",
    "sg:classifiers":[
        {
            "category":"Communications",
            "subcategory":"Film & Video Production",
            "type":"Services"
        }
    ],
    "sg:phone":"+32 9 227 90 48",
    "sg:postcode":"9921",
    "sg:province":"Oost-Vlaanderen",
    "sg:tags":[
        "realisation",
        "-"
    ],
    "wof:name":"Recart",
    "wof:placetype":"venue"
},
  "geometry": {"coordinates":[3.6437110901,51.0892715454],"type":"Point"}
}