{
  "type": "Feature",
  "properties": {
    "iso:country":"BE",
    "sg:address":"Avenue De Marlagne 200",
    "sg:city":"Namur",
    "sg:classifiers":[
        {
            "category":"Real Estate",
            "subcategory":"Architect",
            "type":"Services"
        }
    ],
    "sg:phone":"+32 81 20 12 52",
    "sg:postcode":"5000",
    "sg:province":"Namur",
    "wof:name":"Lerouge A",
    "wof:placetype":"venue"
},
  "geometry": {"coordinates":[4.8396930695,50.4518470764],"type":"Point"}
}