{
  "type": "Feature",
  "properties": {
    "addr:full":"Avenue Georges-truffaut 49 Li\u00c8ge Li\u00e8ge 4020",
    "addr:housenumber":"49",
    "addr:postcode":"4020",
    "addr:street":"Avenue Georges-Truffaut",
    "iso:country":"BE",
    "sg:address":"Avenue Georges-truffaut 49",
    "sg:city":"Li\u00c8ge",
    "sg:orig_category":"Services de publipostage. Locations de machines and \u00e9quipement pour la construction. Location de mac",
    "sg:phone":"+32 4 345 99 99",
    "sg:postcode":"4020",
    "sg:province":"Li\u00e8ge",
    "wof:name":"Mondia",
    "wof:placetype":"venue"
},
  "geometry": {"coordinates":[5.615568161,50.6506881714],"type":"Point"}
}