{
  "type": "Feature",
  "properties": {
    "iso:country":"BE",
    "sg:address":"Jonkershovestraat 59a",
    "sg:city":"Houthulst",
    "sg:orig_category":"Dakwerken",
    "sg:phone":"+32 51 70 25 01",
    "sg:postcode":"8650",
    "sg:province":"West-Vlaanderen",
    "wof:name":"Gilbert Rambour",
    "wof:placetype":"venue"
},
  "geometry": {"coordinates":[2.9411940575,50.975528717],"type":"Point"}
}