{
  "type": "Feature",
  "properties": {
    "iso:country":"BE",
    "sg:address":"Keltenlaan 22",
    "sg:city":"Etterbeek/etterbeek",
    "sg:orig_category":"Antiek",
    "sg:phone":"+32 2 732 48 65",
    "sg:postcode":"1040",
    "sg:province":"Bruxelles-Capitale",
    "wof:name":"Libermann Antiques",
    "wof:placetype":"venue"
},
  "geometry": {"coordinates":[4.3980579376,50.8384742737],"type":"Point"}
}