{
  "type": "Feature",
  "properties": {
    "addr:full":"Den Outer 22 Merksplas Antwerpen 2330",
    "addr:housenumber":"22",
    "addr:postcode":"2330",
    "addr:street":"Den Outer",
    "iso:country":"BE",
    "sg:address":"Den Outer 22",
    "sg:city":"Merksplas",
    "sg:classifiers":[
        {
            "category":"Home & Garden",
            "subcategory":"Carpets & Floor Coverings",
            "type":"Retail Goods"
        }
    ],
    "sg:phone":"+32 14 63 43 07",
    "sg:postcode":"2330",
    "sg:province":"Antwerpen",
    "sg:tags":[
        "parquet"
    ],
    "wof:name":"Plankenvloer",
    "wof:placetype":"venue"
},
  "geometry": {"coordinates":[4.8588299751,51.3552513123],"type":"Point"}
}