{
  "type": "Feature",
  "properties": {
    "iso:country":"BE",
    "sg:address":"Hogeweg 19",
    "sg:city":"Erembodegem",
    "sg:orig_category":"Royal Canin. Animaux domestiques and accessoires",
    "sg:phone":"+32 53 77 97 26",
    "sg:postcode":"9320",
    "sg:province":"Oost-Vlaanderen",
    "wof:name":"De Troyer Sonja",
    "wof:placetype":"venue"
},
  "geometry": {"coordinates":[4.0617938042,50.921081543],"type":"Point"}
}