{
  "type": "Feature",
  "properties": {
    "iso:country":"BE",
    "sg:address":"Chauss\u00e9e Du Roeulx 232",
    "sg:city":"Soignies",
    "sg:classifiers":[
        {
            "category":"Building & Trades",
            "subcategory":"Plumbing",
            "type":"Services"
        }
    ],
    "sg:phone":"+32 67 33 01 60",
    "sg:postcode":"7060",
    "sg:province":"Hainaut",
    "sg:tags":[
        "contractor"
    ],
    "wof:name":"Roland",
    "wof:placetype":"venue"
},
  "geometry": {"coordinates":[4.0789551735,50.5595741272],"type":"Point"}
}