{
  "type": "Feature",
  "properties": {
    "addr:full":"Rijksweg 16 Dilsen-stokkem Limburg 3650",
    "addr:housenumber":"16",
    "addr:postcode":"3650",
    "addr:street":"Rijksweg",
    "iso:country":"BE",
    "sg:address":"Rijksweg 16",
    "sg:city":"Dilsen-stokkem",
    "sg:orig_category":"Brood, gebak and snoepgoed",
    "sg:phone":"+32 89 79 36 94",
    "sg:postcode":"3650",
    "sg:province":"Limburg",
    "wof:name":"Brigitte Kenens",
    "wof:placetype":"venue"
},
  "geometry": {"coordinates":[5.7266697884,51.0228614807],"type":"Point"}
}