{
  "type": "Feature",
  "properties": {
    "addr:full":"Kastelein 37 Turnhout Antwerpen 2300",
    "addr:housenumber":"37",
    "addr:postcode":"2300",
    "addr:street":"Kastelein",
    "iso:country":"BE",
    "sg:address":"Kastelein 37",
    "sg:city":"Turnhout",
    "sg:classifiers":[
        {
            "category":"Professional",
            "type":"Services"
        }
    ],
    "sg:phone":"+32 14 42 51 19",
    "sg:postcode":"2300",
    "sg:province":"Antwerpen",
    "sg:tags":[
        "industrial",
        "automation"
    ],
    "wof:name":"Igs",
    "wof:placetype":"venue"
},
  "geometry": {"coordinates":[4.945456028,51.3345069885],"type":"Point"}
}