{
  "type": "Feature",
  "properties": {
    "iso:country":"BE",
    "sg:address":"Route De Val Dieu 75",
    "sg:city":"Aubel",
    "sg:classifiers":[
        {
            "category":"Building & Trades",
            "subcategory":"Landscaping Services",
            "type":"Services"
        }
    ],
    "sg:phone":"+32 87 68 77 45",
    "sg:postcode":"4880",
    "sg:province":"Li\u00e8ge",
    "sg:tags":[
        "nurseryman"
    ],
    "wof:name":"Meurens A",
    "wof:placetype":"venue"
},
  "geometry": {"coordinates":[5.8471608162,50.7092475891],"type":"Point"}
}