{
  "type": "Feature",
  "properties": {
    "iso:country":"BE",
    "sg:address":"Pater Christophestraat 38",
    "sg:city":"Waasmunster",
    "sg:classifiers":[
        {
            "category":"Manufacturing",
            "subcategory":"Metals",
            "type":"Manufacturing & Wholesale Goods"
        }
    ],
    "sg:phone":"+32 3 772 33 27",
    "sg:postcode":"9250",
    "sg:province":"Oost-Vlaanderen",
    "sg:tags":[
        "steel",
        "stainless"
    ],
    "wof:name":"Smederij G Smet Van Goethem",
    "wof:placetype":"venue"
},
  "geometry": {"coordinates":[4.0652480125,51.1424407959],"type":"Point"}
}