{
  "type": "Feature",
  "properties": {
    "iso:country":"BE",
    "sg:address":"Sentier Buselotte 16",
    "sg:city":"Braine-le-ch\u00e2teau",
    "sg:classifiers":[
        {
            "category":"Professional",
            "subcategory":"Management & Consulting",
            "type":"Services"
        }
    ],
    "sg:phone":"+32 2 366 33 40",
    "sg:postcode":"1440",
    "sg:province":"Brabant Wallon",
    "sg:tags":[
        "consultant",
        "agency",
        "advertising"
    ],
    "wof:name":"De Bueger L",
    "wof:placetype":"venue"
},
  "geometry": {"coordinates":[4.2610797882,50.6718292236],"type":"Point"}
}