{
  "type": "Feature",
  "properties": {
    "addr:full":"Kanadezenlaan 34 Moeskroen/mouscron Hainaut 7711",
    "addr:housenumber":"34",
    "addr:postcode":"7711",
    "addr:street":"Kanadezenlaan",
    "iso:country":"BE",
    "sg:address":"Kanadezenlaan 34",
    "sg:city":"Moeskroen/mouscron",
    "sg:orig_category":"Hout and afgeleiden Gh IJzerwaren, bouw- and verfmaterialen",
    "sg:phone":"+32 56 48 98 48",
    "sg:postcode":"7711",
    "sg:province":"Hainaut",
    "wof:name":"Jacques Buyssens",
    "wof:placetype":"venue"
},
  "geometry": {"coordinates":[3.3127660751,50.7288475037],"type":"Point"}
}