{
  "type": "Feature",
  "properties": {
    "addr:full":"Vieille Rue Du Moulin 111 Bruxelles (uccle) Bruxelles-Capitale 1180",
    "addr:housenumber":"111",
    "addr:postcode":"1180",
    "addr:street":"Vieille Rue Du Moulin",
    "iso:country":"BE",
    "sg:address":"Vieille Rue Du Moulin 111",
    "sg:city":"Bruxelles (uccle)",
    "sg:classifiers":[
        {
            "category":"Bakery",
            "type":"Food & Drink"
        }
    ],
    "sg:phone":"+32 2 374 83 88",
    "sg:postcode":"1180",
    "sg:province":"Bruxelles-Capitale",
    "sg:tags":[
        "confectioner",
        "baker"
    ],
    "wof:name":"Gateaux Sign\u00e9s Mumu",
    "wof:placetype":"venue"
},
  "geometry": {"coordinates":[4.3662991524,50.7903060913],"type":"Point"}
}