{
  "type": "Feature",
  "properties": {
    "iso:country":"BE",
    "sg:address":"Burgstraat 49",
    "sg:city":"Gent",
    "sg:orig_category":"Agences d\u00b4interim and personnel temporaire",
    "sg:phone":"+32 9 224 09 20",
    "sg:postcode":"9000",
    "sg:province":"Oost-Vlaanderen",
    "wof:name":"T Interim",
    "wof:placetype":"venue"
},
  "geometry": {"coordinates":[3.7177100182,51.0562782288],"type":"Point"}
}