{
  "type": "Feature",
  "properties": {
    "addr:full":"Haterbeekstraat 65 Aarschot Vlaams-Brabant 3200",
    "addr:housenumber":"65",
    "addr:postcode":"3200",
    "addr:street":"Haterbeekstraat",
    "iso:country":"BE",
    "sg:address":"Haterbeekstraat 65",
    "sg:city":"Aarschot",
    "sg:classifiers":[
        {
            "category":"Shopping",
            "subcategory":"Computers & Home Electronics",
            "type":"Retail Goods"
        }
    ],
    "sg:phone":"+32 16 56 12 63",
    "sg:postcode":"3200",
    "sg:province":"Vlaams-Brabant",
    "sg:tags":[
        "sound",
        "equipment",
        "-",
        "system"
    ],
    "wof:name":"All Sound & Light Karaoke",
    "wof:placetype":"venue"
},
  "geometry": {"coordinates":[4.8575072289,50.9724006653],"type":"Point"}
}