{
  "type": "Feature",
  "properties": {
    "addr:full":"Kaaistraat 3 Roeselare West-Vlaanderen 8800",
    "addr:housenumber":"3",
    "addr:postcode":"8800",
    "addr:street":"Kaaistraat",
    "iso:country":"BE",
    "sg:address":"Kaaistraat 3",
    "sg:city":"Roeselare",
    "sg:orig_category":"Boucheries",
    "sg:phone":"+32 51 20 11 03",
    "sg:postcode":"8800",
    "sg:province":"West-Vlaanderen",
    "wof:name":"Gerard Peeters",
    "wof:placetype":"venue"
},
  "geometry": {"coordinates":[3.1326329708,50.9456939697],"type":"Point"}
}