{
  "type": "Feature",
  "properties": {
    "iso:country":"BE",
    "sg:address":"Nantimont 2",
    "sg:city":"Habay",
    "sg:orig_category":"Eleveurs de bovins",
    "sg:phone":"+32 63 42 23 22",
    "sg:postcode":"6723",
    "sg:province":"Luxembourg",
    "wof:name":"Marcel Cravatte",
    "wof:placetype":"venue"
},
  "geometry": {"coordinates":[5.622587204,49.7121734619],"type":"Point"}
}