{
  "type": "Feature",
  "properties": {
    "addr:full":"Rue Paul-joseph Carpay 26 Li\u00c8ge Li\u00e8ge 4020",
    "addr:housenumber":"26",
    "addr:postcode":"4020",
    "addr:street":"Rue Paul-Joseph Carpay",
    "iso:country":"BE",
    "sg:address":"Rue Paul-joseph Carpay 26",
    "sg:city":"Li\u00c8ge",
    "sg:orig_category":"Biens d'occasion",
    "sg:phone":"+32 4 341 70 65",
    "sg:postcode":"4020",
    "sg:province":"Li\u00e8ge",
    "wof:name":"Les Petits Riens",
    "wof:placetype":"venue"
},
  "geometry": {"coordinates":[5.6029891968,50.6465415955],"type":"Point"}
}