{
  "type": "Feature",
  "properties": {
    "iso:country":"BE",
    "sg:address":"Bodegemstraat 101",
    "sg:city":"Ternat",
    "sg:orig_category":"Woningbouw",
    "sg:phone":"+32 2 582 18 59",
    "sg:postcode":"1740",
    "sg:province":"Vlaams-Brabant",
    "wof:name":"Mark Baudewyns",
    "wof:placetype":"venue"
},
  "geometry": {"coordinates":[4.1941199303,50.8632888794],"type":"Point"}
}