{
  "type": "Feature",
  "properties": {
    "addr:full":"Boulevard G\u00c9n\u00c9ral Wahis 20ba Schaarbeek/schaerbeek Bruxelles-Capitale 1030",
    "addr:housenumber":"20ba",
    "addr:postcode":"1030",
    "addr:street":"Boulevard Ge\u0301Ne\u0301Ral Wahis",
    "iso:country":"BE",
    "sg:address":"Boulevard G\u00c9n\u00c9ral Wahis 20ba",
    "sg:city":"Schaarbeek/schaerbeek",
    "sg:orig_category":"D\u00e9taillants en pi\u00e8ces and accessoires de voitures",
    "sg:phone":"+32 2 726 08 21",
    "sg:postcode":"1030",
    "sg:province":"Bruxelles-Capitale",
    "wof:name":"Alpha Prime",
    "wof:placetype":"venue"
},
  "geometry": {"coordinates":[4.3954620361,50.8595237732],"type":"Point"}
}