{
  "type": "Feature",
  "properties": {
    "addr:full":"Sint-janstraat 9 Tielt West-Vlaanderen 8700",
    "addr:housenumber":"9",
    "addr:postcode":"8700",
    "addr:street":"Sint-Janstraat",
    "iso:country":"BE",
    "sg:address":"Sint-janstraat 9",
    "sg:city":"Tielt",
    "sg:orig_category":"Tijdelijke werkgelegenheid and uitzendkantoren",
    "sg:phone":"+32 51 40 41 16",
    "sg:postcode":"8700",
    "sg:province":"West-Vlaanderen",
    "wof:name":"T Interim",
    "wof:placetype":"venue"
},
  "geometry": {"coordinates":[3.3342199326,51.0029411316],"type":"Point"}
}