{
  "type": "Feature",
  "properties": {
    "addr:full":"Oudenbos 98 Aarschot (rillaar) Vlaams-Brabant 3202",
    "addr:housenumber":"98",
    "addr:postcode":"3202",
    "addr:street":"Oudenbos",
    "iso:country":"BE",
    "sg:address":"Oudenbos 98",
    "sg:city":"Aarschot (rillaar)",
    "sg:classifiers":[
        {
            "category":"Farming",
            "subcategory":"Farm & Veterinary Services",
            "type":"Manufacturing & Wholesale Goods"
        }
    ],
    "sg:phone":"+32 16 50 11 13",
    "sg:postcode":"3202",
    "sg:province":"Vlaams-Brabant",
    "sg:tags":[
        "agricultural",
        "contractor"
    ],
    "wof:name":"Bruyninckx L",
    "wof:placetype":"venue"
},
  "geometry": {"coordinates":[4.9045948982,50.9642486572],"type":"Point"}
}