{
  "type": "Feature",
  "properties": {
    "addr:full":"Albert Geudensstraat 4 Mechelen Antwerpen 2800",
    "addr:housenumber":"4",
    "addr:postcode":"2800",
    "addr:street":"Albert Geudensstraat",
    "iso:country":"BE",
    "sg:address":"Albert Geudensstraat 4",
    "sg:city":"Mechelen",
    "sg:classifiers":[
        {
            "category":"Health Services",
            "subcategory":"Doctor",
            "type":"Services"
        }
    ],
    "sg:phone":"+32 15 41 47 03",
    "sg:postcode":"2800",
    "sg:province":"Antwerpen",
    "sg:tags":[
        "medicinephysicians",
        "surgeon"
    ],
    "wof:name":"Govaerts Johan",
    "wof:placetype":"venue"
},
  "geometry": {"coordinates":[4.4789252281,51.0204734802],"type":"Point"}
}