{
  "type": "Feature",
  "properties": {
    "addr:full":"Rue Des Hayettes 18 Charleroi (gilly) Hainaut 6060",
    "addr:housenumber":"18",
    "addr:postcode":"6060",
    "addr:street":"Rue Des Hayettes",
    "iso:country":"BE",
    "sg:address":"Rue Des Hayettes 18",
    "sg:city":"Charleroi (gilly)",
    "sg:orig_category":"Newspapers, magazines, periodicals - Distribution",
    "sg:phone":"+32 71 41 27 17",
    "sg:postcode":"6060",
    "sg:province":"Hainaut",
    "wof:name":"Cagedis",
    "wof:placetype":"venue"
},
  "geometry": {"coordinates":[4.3989610672,50.3892555237],"type":"Point"}
}