{
  "type": "Feature",
  "properties": {
    "addr:full":"Rue Charles Bormans 24 Wanze Li\u00e8ge 4520",
    "addr:housenumber":"24",
    "addr:postcode":"4520",
    "addr:street":"Rue Charles Bormans",
    "iso:country":"BE",
    "sg:address":"Rue Charles Bormans 24",
    "sg:city":"Wanze",
    "sg:orig_category":"Enseignement maternel and primaire",
    "sg:phone":"+32 85 21 10 94",
    "sg:postcode":"4520",
    "sg:province":"Li\u00e8ge",
    "wof:name":"Ecole Fond. Communale",
    "wof:placetype":"venue"
},
  "geometry": {"coordinates":[5.1857800484,50.523273468],"type":"Point"}
}