{
  "type": "Feature",
  "properties": {
    "addr:full":"Antwerpsesteenweg 59-61 Lier Antwerpen 2500",
    "addr:postcode":"59-61;2500",
    "addr:street":"Antwerpsesteenweg",
    "iso:country":"BE",
    "sg:address":"Antwerpsesteenweg 59-61",
    "sg:city":"Lier",
    "sg:classifiers":[
        {
            "category":"Health Services",
            "subcategory":"Doctor",
            "type":"Services"
        }
    ],
    "sg:phone":"+32 3 480 83 94",
    "sg:postcode":"2500",
    "sg:province":"Antwerpen",
    "sg:tags":[
        "medicinephysicians",
        "surgeon"
    ],
    "wof:name":"Crokaerts I",
    "wof:placetype":"venue"
},
  "geometry": {"coordinates":[4.5599761009,51.1373710632],"type":"Point"}
}