{
  "type": "Feature",
  "properties": {
    "addr:full":"Rue De Taillis-pr\u00c9 21 Chatelet Hainaut 6200",
    "addr:housenumber":"21",
    "addr:postcode":"6200",
    "addr:street":"Rue De Taillis-Pre\u0301;Hainaut",
    "iso:country":"BE",
    "sg:address":"Rue De Taillis-pr\u00c9 21",
    "sg:city":"Chatelet",
    "sg:orig_category":"Brood, gebak and snoepgoed",
    "sg:phone":"+32 71 38 28 94",
    "sg:postcode":"6200",
    "sg:province":"Hainaut",
    "wof:name":"Fabian Van Acker",
    "wof:placetype":"venue"
},
  "geometry": {"coordinates":[4.5059099197,50.4324226379],"type":"Point"}
}