{
  "type": "Feature",
  "properties": {
    "iso:country":"BE",
    "sg:address":"Kortrijkstraat 341",
    "sg:city":"Wevelgem",
    "sg:orig_category":"Electrom\u00e9nager, t\u00e9l\u00e9visions and radios",
    "sg:phone":"+32 56 42 46 57",
    "sg:postcode":"8560",
    "sg:province":"West-Vlaanderen",
    "wof:name":"Kijkshop Bestsellers",
    "wof:placetype":"venue"
},
  "geometry": {"coordinates":[3.21113801,50.8170204163],"type":"Point"}
}