{
  "type": "Feature",
  "properties": {
    "addr:full":"Regelsbruggestraat 8 Aalst Oost-Vlaanderen 9300",
    "addr:housenumber":"8",
    "addr:postcode":"9300",
    "addr:street":"Regelsbruggestraat",
    "iso:country":"BE",
    "sg:address":"Regelsbruggestraat 8",
    "sg:city":"Aalst",
    "sg:classifiers":[
        {
            "category":"Shopping",
            "subcategory":"Party Supplies",
            "type":"Retail Goods"
        }
    ],
    "sg:phone":"+32 53 60 81 09",
    "sg:postcode":"9300",
    "sg:province":"Oost-Vlaanderen",
    "sg:tags":[
        "technician",
        "equipment",
        "dental",
        "-",
        "dentist"
    ],
    "wof:name":"Eki'p Dental",
    "wof:placetype":"venue"
},
  "geometry": {"coordinates":[4.0259628296,50.9375762939],"type":"Point"}
}