{
  "type": "Feature",
  "properties": {
    "iso:country":"BE",
    "sg:address":"Sint-guidostraat 17",
    "sg:city":"Anderlecht",
    "sg:orig_category":"Huishoudapparaten, televisies and radio's",
    "sg:phone":"+32 2 522 35 48",
    "sg:postcode":"1070",
    "sg:province":"Bruxelles-Capitale",
    "wof:name":"Clip Vid\u00c9o",
    "wof:placetype":"venue"
},
  "geometry": {"coordinates":[4.3057332039,50.8356513977],"type":"Point"}
}