{
  "type": "Feature",
  "properties": {
    "iso:country":"BE",
    "sg:address":"Van Lintstraat 24",
    "sg:city":"Anderlecht",
    "sg:orig_category":"Bagage and lederwaren",
    "sg:phone":"+32 2 521 62 23",
    "sg:postcode":"1070",
    "sg:province":"Bruxelles-Capitale",
    "wof:name":"Bobby\u00b4s",
    "wof:placetype":"venue"
},
  "geometry": {"coordinates":[4.3277359009,50.8393554688],"type":"Point"}
}