{
  "type": "Feature",
  "properties": {
    "iso:country":"BE",
    "sg:address":"Kerkstraat 5",
    "sg:city":"Beveren (vrasene)",
    "sg:classifiers":[
        {
            "category":"Health Services",
            "subcategory":"Dentist",
            "type":"Services"
        }
    ],
    "sg:phone":"+32 3 775 49 53",
    "sg:postcode":"9120",
    "sg:province":"Oost-Vlaanderen",
    "wof:name":"De Jonghe Guido",
    "wof:placetype":"venue"
},
  "geometry": {"coordinates":[4.1950259209,51.2190475464],"type":"Point"}
}