{
  "type": "Feature",
  "properties": {
    "iso:country":"BE",
    "sg:address":"Dorpsstraat 9",
    "sg:city":"Lubbeek",
    "sg:orig_category":"Slagers",
    "sg:phone":"+32 16 64 02 31",
    "sg:postcode":"3210",
    "sg:province":"Vlaams-Brabant",
    "wof:name":"Schotte En Van Aerschot",
    "wof:placetype":"venue"
},
  "geometry": {"coordinates":[4.8426160812,50.8799057007],"type":"Point"}
}