{
  "type": "Feature",
  "properties": {
    "addr:full":"Leeuwergemstraat 3 Zottegem Oost-Vlaanderen 9620",
    "addr:housenumber":"3",
    "addr:postcode":"9620",
    "addr:street":"Leeuwergemstraat",
    "iso:country":"BE",
    "sg:address":"Leeuwergemstraat 3",
    "sg:city":"Zottegem",
    "sg:orig_category":"Elektrische installaties voor woningen",
    "sg:phone":"+32 9 360 31 85",
    "sg:postcode":"9620",
    "sg:province":"Oost-Vlaanderen",
    "wof:name":"Elect.tech.van Crombrugge",
    "wof:placetype":"venue"
},
  "geometry": {"coordinates":[3.8112111092,50.871181488],"type":"Point"}
}