{
  "type": "Feature",
  "properties": {
    "iso:country":"BE",
    "sg:address":"Blankenbergse Steenweg 44a",
    "sg:city":"Zuienkerke",
    "sg:classifiers":[
        {
            "category":"Home & Garden",
            "subcategory":"Kitchen Supply",
            "type":"Retail Goods"
        }
    ],
    "sg:phone":"+32 50 31 36 22",
    "sg:postcode":"8377",
    "sg:province":"West-Vlaanderen",
    "sg:tags":[
        "equipment",
        "baker",
        "-"
    ],
    "wof:name":"Van Den Broucke Gilbert Nv",
    "wof:placetype":"venue"
},
  "geometry": {"coordinates":[3.1588680744,51.2659568787],"type":"Point"}
}