{
  "type": "Feature",
  "properties": {
    "addr:full":"Torenplein 19 Ranst Antwerpen 2520",
    "addr:housenumber":"19",
    "addr:postcode":"2520",
    "addr:street":"Torenplein",
    "iso:country":"BE",
    "sg:address":"Torenplein 19",
    "sg:city":"Ranst",
    "sg:orig_category":"Banques and organismes de cr\u00e9dit",
    "sg:phone":"+32 3 385 12 77",
    "sg:postcode":"2520",
    "sg:province":"Antwerpen",
    "wof:name":"Fortis",
    "wof:placetype":"venue"
},
  "geometry": {"coordinates":[4.5965628624,51.210975647],"type":"Point"}
}