{
  "type": "Feature",
  "properties": {
    "addr:full":"Hopland 44 Antwerpen Antwerpen 2000",
    "addr:housenumber":"44",
    "addr:postcode":"2000",
    "addr:street":"Hopland",
    "iso:country":"BE",
    "sg:address":"Hopland 44",
    "sg:city":"Antwerpen",
    "sg:classifiers":[
        {
            "category":"Shopping",
            "subcategory":"Shoes",
            "type":"Retail Goods"
        }
    ],
    "sg:phone":"+32 3 232 49 32",
    "sg:postcode":"2000",
    "sg:province":"Antwerpen",
    "sg:tags":[
        "slipper",
        "-"
    ],
    "wof:name":"Gab Shoe Bvba Zwitsershuis",
    "wof:placetype":"venue"
},
  "geometry": {"coordinates":[4.4126172066,51.2166061401],"type":"Point"}
}