{
  "type": "Feature",
  "properties": {
    "addr:full":"Leuvensesteenweg 100 Tervuren Vlaams-Brabant 3080",
    "addr:housenumber":"100",
    "addr:postcode":"3080",
    "addr:street":"Leuvensesteenweg",
    "iso:country":"BE",
    "sg:address":"Leuvensesteenweg 100",
    "sg:city":"Tervuren",
    "sg:orig_category":"Herstellingen and onderhoud van auto's",
    "sg:phone":"+32 2 767 62 59",
    "sg:postcode":"3080",
    "sg:province":"Vlaams-Brabant",
    "wof:name":"Christian Bogaert",
    "wof:placetype":"venue"
},
  "geometry": {"coordinates":[4.5400829315,50.8375015259],"type":"Point"}
}