{
  "type": "Feature",
  "properties": {
    "iso:country":"BE",
    "sg:address":"Lieven Bauwensstraat 15",
    "sg:city":"Brugge (sint-andries)",
    "sg:classifiers":[
        {
            "category":"Shopping",
            "subcategory":"Pets & Pet Supplies",
            "type":"Retail Goods"
        }
    ],
    "sg:phone":"+32 50 32 04 08",
    "sg:postcode":"8200",
    "sg:province":"West-Vlaanderen",
    "sg:tags":[
        "telecopiers"
    ],
    "wof:name":"Buro Center",
    "wof:placetype":"venue"
},
  "geometry": {"coordinates":[3.1946899891,51.2132072449],"type":"Point"}
}