{
  "type": "Feature",
  "properties": {
    "addr:full":"Heiken 20 Vorselaar Antwerpen 2290",
    "addr:housenumber":"20",
    "addr:postcode":"2290",
    "addr:street":"Heiken",
    "iso:country":"BE",
    "sg:address":"Heiken 20",
    "sg:city":"Vorselaar",
    "sg:orig_category":"Eleveurs de bovins",
    "sg:phone":"+32 14 51 23 95",
    "sg:postcode":"2290",
    "sg:province":"Antwerpen",
    "wof:name":"Nelis Leo Johan",
    "wof:placetype":"venue"
},
  "geometry": {"coordinates":[4.7839660645,51.1887435913],"type":"Point"}
}