{
  "type": "Feature",
  "properties": {
    "iso:country":"BE",
    "sg:address":"Trieu De La Savonnerie 2",
    "sg:city":"Pecq",
    "sg:orig_category":"G\u00e9om\u00e8tres",
    "sg:phone":"+32 69 55 93 79",
    "sg:postcode":"7740",
    "sg:province":"Hainaut",
    "wof:name":"Fabrice Pioda",
    "wof:placetype":"venue"
},
  "geometry": {"coordinates":[3.3407540321,50.6778755188],"type":"Point"}
}