{
  "type": "Feature",
  "properties": {
    "iso:country":"BE",
    "sg:address":"Rue Du Vivier 100",
    "sg:city":"Bastogne",
    "sg:classifiers":[
        {
            "category":"Wholesale",
            "subcategory":"Sporting Goods",
            "type":"Manufacturing & Wholesale Goods"
        }
    ],
    "sg:phone":"+32 61 21 14 61",
    "sg:postcode":"6600",
    "sg:province":"Luxembourg",
    "sg:tags":[
        "sport-",
        "kampeermateriaal"
    ],
    "wof:name":"Collard Sport",
    "wof:placetype":"venue"
},
  "geometry": {"coordinates":[5.7173857689,50.0019989014],"type":"Point"}
}