{
  "type": "Feature",
  "properties": {
    "addr:full":"Rue Du Basson 93 Charleroi (marcinelle) Hainaut 6001",
    "addr:housenumber":"93",
    "addr:postcode":"6001",
    "addr:street":"Rue Du Basson",
    "iso:country":"BE",
    "sg:address":"Rue Du Basson 93",
    "sg:city":"Charleroi (marcinelle)",
    "sg:classifiers":[
        {
            "category":"Professional",
            "subcategory":"Accounting & Tax Preparation",
            "type":"Services"
        }
    ],
    "sg:phone":"+32 71 47 76 68",
    "sg:postcode":"6001",
    "sg:province":"Hainaut",
    "sg:tags":[
        "bookkeeper"
    ],
    "wof:name":"Md Partners",
    "wof:placetype":"venue"
},
  "geometry": {"coordinates":[4.4426717758,50.3993377686],"type":"Point"}
}