{
  "type": "Feature",
  "properties": {
    "iso:country":"BE",
    "sg:address":"Kerkstraat 161",
    "sg:city":"Stekene",
    "sg:classifiers":[
        {
            "category":"Building & Trades",
            "subcategory":"Locksmith",
            "type":"Services"
        }
    ],
    "sg:phone":"+32 3 779 62 68",
    "sg:postcode":"9190",
    "sg:province":"Oost-Vlaanderen",
    "sg:tags":[
        "material",
        "road"
    ],
    "wof:name":"Saman P",
    "wof:placetype":"venue"
},
  "geometry": {"coordinates":[4.0331921577,51.2126502991],"type":"Point"}
}