{
  "type": "Feature",
  "properties": {
    "iso:country":"BE",
    "sg:address":"Madeliefjeslaan 32",
    "sg:city":"Bornem",
    "sg:classifiers":[
        {
            "category":"Insurance",
            "subcategory":"Life Insurance",
            "type":"Services"
        }
    ],
    "sg:phone":"+32 3 889 33 74",
    "sg:postcode":"2880",
    "sg:province":"Antwerpen",
    "sg:tags":[
        "assurance"
    ],
    "wof:name":"Engels & Co",
    "wof:placetype":"venue"
},
  "geometry": {"coordinates":[4.2158780098,51.0864524841],"type":"Point"}
}