{
  "type": "Feature",
  "properties": {
    "iso:country":"BE",
    "sg:address":"Zepstraat 13",
    "sg:city":"Mechelen",
    "sg:orig_category":"Passagiersvervoer over de weg",
    "sg:phone":"+32 15 41 13 03",
    "sg:postcode":"2811",
    "sg:province":"Antwerpen",
    "wof:name":"Autobussen De Reys",
    "wof:placetype":"venue"
},
  "geometry": {"coordinates":[4.4288578033,51.0103187561],"type":"Point"}
}