{
  "type": "Feature",
  "properties": {
    "iso:country":"BE",
    "sg:address":"Rue De France 17",
    "sg:city":"Rochefort",
    "sg:classifiers":[
        {
            "category":"Home & Garden",
            "subcategory":"Furniture",
            "type":"Retail Goods"
        }
    ],
    "sg:phone":"+32 84 21 16 16",
    "sg:postcode":"5580",
    "sg:province":"Namur",
    "sg:tags":[
        "-"
    ],
    "wof:name":"Jacli Sa",
    "wof:placetype":"venue"
},
  "geometry": {"coordinates":[5.2218427658,50.1575317383],"type":"Point"}
}