{
  "type": "Feature",
  "properties": {
    "iso:country":"BE",
    "sg:address":"Fabiolalaan 2",
    "sg:city":"Oostkamp",
    "sg:classifiers":[
        {
            "category":"Education",
            "subcategory":"School",
            "type":"Public Place"
        }
    ],
    "sg:phone":"+32 50 39 69 79",
    "sg:postcode":"8020",
    "sg:province":"West-Vlaanderen",
    "sg:tags":[
        "primary"
    ],
    "wof:name":"Freinetschool Klimop Onafhankelijke Basisschool",
    "wof:placetype":"venue"
},
  "geometry": {"coordinates":[3.2252409458,51.1563644409],"type":"Point"}
}