{
  "type": "Feature",
  "properties": {
    "addr:full":"Torhoutse Steenweg 246 Sint-andries West-Vlaanderen 8200",
    "addr:housenumber":"246",
    "addr:postcode":"8200",
    "addr:street":"Torhoutse Steenweg",
    "iso:country":"BE",
    "sg:address":"Torhoutse Steenweg 246",
    "sg:city":"Sint-andries",
    "sg:classifiers":[
        {
            "category":"Professional",
            "subcategory":"Employment Agencies",
            "type":"Services"
        }
    ],
    "sg:phone":"+32 50 40 64 90",
    "sg:postcode":"8200",
    "sg:province":"West-Vlaanderen",
    "sg:tags":[
        "cross-media",
        "publishing"
    ],
    "wof:name":"Guideline Belgium B.v.b.a.",
    "wof:placetype":"venue"
},
  "geometry": {"coordinates":[3.1975800991,51.1936340332],"type":"Point"}
}