{
  "type": "Feature",
  "properties": {
    "addr:full":"Rue Des Volontaires 6 Rixensart Brabant Wallon 1332",
    "addr:housenumber":"6",
    "addr:postcode":"1332",
    "addr:street":"Rue Des Volontaires;Wallon",
    "iso:country":"BE",
    "sg:address":"Rue Des Volontaires 6",
    "sg:city":"Rixensart",
    "sg:orig_category":"Artistes ind\u00e9pendants",
    "sg:phone":"+32 2 653 77 71",
    "sg:postcode":"1332",
    "sg:province":"Brabant Wallon",
    "wof:name":"Evrard",
    "wof:placetype":"venue"
},
  "geometry": {"coordinates":[4.4936342239,50.7172546387],"type":"Point"}
}