{
  "type": "Feature",
  "properties": {
    "iso:country":"BE",
    "sg:address":"Boulevard Clovis 12a",
    "sg:city":"Brussel/bruxelles",
    "sg:orig_category":"Editeurs de revues and p\u00e9riodiques. Editeurs de journaux",
    "sg:phone":"+32 2 732 19 80",
    "sg:postcode":"1000",
    "sg:province":"Bruxelles-Capitale",
    "wof:name":"Edition El Sol",
    "wof:placetype":"venue"
},
  "geometry": {"coordinates":[4.3826432228,50.8482131958],"type":"Point"}
}