{
  "type": "Feature",
  "properties": {
    "iso:country":"BE",
    "sg:address":"Malihoux 14ba",
    "sg:city":"Havelange",
    "sg:orig_category":"Pleisterwerk",
    "sg:phone":"+32 83 63 39 93",
    "sg:postcode":"5370",
    "sg:province":"Namur",
    "wof:name":"Melot A. & E.",
    "wof:placetype":"venue"
},
  "geometry": {"coordinates":[5.2238540649,50.3924751282],"type":"Point"}
}