{
  "type": "Feature",
  "properties": {
    "addr:full":"Rue Du Tilleul 33 Oupeye (hermalle-sous-argenteau) Li\u00e8ge 4681",
    "addr:housenumber":"33",
    "addr:postcode":"4681",
    "addr:street":"Rue Du Tilleul;Hermalle-Sous-Argenteau",
    "iso:country":"BE",
    "sg:address":"Rue Du Tilleul 33",
    "sg:city":"Oupeye (hermalle-sous-argenteau)",
    "sg:classifiers":[
        {
            "category":"Professional",
            "subcategory":"Engineering",
            "type":"Services"
        }
    ],
    "sg:phone":"+32 4 374 93 70",
    "sg:postcode":"4681",
    "sg:province":"Li\u00e8ge",
    "sg:tags":[
        "precision"
    ],
    "wof:name":"Precical Sa",
    "wof:placetype":"venue"
},
  "geometry": {"coordinates":[5.6721968651,50.7009162903],"type":"Point"}
}