{
  "type": "Feature",
  "properties": {
    "iso:country":"BE",
    "sg:address":"Maurits Lauwersplein 15",
    "sg:city":"Wevelgem",
    "sg:classifiers":[
        {
            "category":"Communications",
            "type":"Services"
        }
    ],
    "sg:phone":"+32 56 25 67 13",
    "sg:postcode":"8560",
    "sg:province":"West-Vlaanderen",
    "sg:tags":[
        "translator"
    ],
    "wof:name":"Hamels L",
    "wof:placetype":"venue"
},
  "geometry": {"coordinates":[3.1742100716,50.8171691895],"type":"Point"}
}