{
  "type": "Feature",
  "properties": {
    "addr:full":"Rue De La Station 41 Havelange Namur 5370",
    "addr:housenumber":"41",
    "addr:postcode":"5370",
    "addr:street":"Rue De La Station",
    "iso:country":"BE",
    "sg:address":"Rue De La Station 41",
    "sg:city":"Havelange",
    "sg:orig_category":"Epiceries",
    "sg:phone":"+32 83 63 32 85",
    "sg:postcode":"5370",
    "sg:province":"Namur",
    "wof:name":"Louis Delhaize",
    "wof:placetype":"venue"
},
  "geometry": {"coordinates":[5.2403650284,50.3883590698],"type":"Point"}
}