{
  "type": "Feature",
  "properties": {
    "iso:country":"BE",
    "sg:address":"Rue De Villers 9",
    "sg:city":"Gerpinnes (acoz)",
    "sg:classifiers":[
        {
            "category":"Retail",
            "subcategory":"Auto Repair",
            "type":"Services"
        }
    ],
    "sg:phone":"+32 71 50 21 73",
    "sg:postcode":"6280",
    "sg:province":"Hainaut",
    "sg:tags":[
        "garage"
    ],
    "wof:name":"Care V",
    "wof:placetype":"venue"
},
  "geometry": {"coordinates":[4.5153398514,50.3587913513],"type":"Point"}
}