{
  "type": "Feature",
  "properties": {
    "iso:country":"BE",
    "sg:address":"Hoge Steenweg 1",
    "sg:city":"Grimbergen",
    "sg:orig_category":"Opticiens",
    "sg:phone":"+32 2 270 98 82",
    "sg:postcode":"1850",
    "sg:province":"Vlaams-Brabant",
    "wof:name":"De Temmerman- Van De Velde",
    "wof:placetype":"venue"
},
  "geometry": {"coordinates":[4.371322155,50.9332275391],"type":"Point"}
}