{
  "type": "Feature",
  "properties": {
    "addr:full":"Guido Gezellelaan 10 Mechelen Antwerpen 2800",
    "addr:housenumber":"10",
    "addr:postcode":"2800",
    "addr:street":"Guido Gezellelaan",
    "iso:country":"BE",
    "sg:address":"Guido Gezellelaan 10",
    "sg:city":"Mechelen",
    "sg:classifiers":[
        {
            "category":"Education",
            "subcategory":"Dance Studio",
            "type":"Public Place"
        }
    ],
    "sg:phone":"+32 15 42 24 03",
    "sg:postcode":"2800",
    "sg:province":"Antwerpen",
    "sg:tags":[
        "ballet",
        "school"
    ],
    "wof:name":"Dansstudio Marlynes",
    "wof:placetype":"venue"
},
  "geometry": {"coordinates":[4.4720840454,51.0319061279],"type":"Point"}
}