{
  "type": "Feature",
  "properties": {
    "iso:country":"BE",
    "sg:address":"Patersstraat 47",
    "sg:city":"Turnhout",
    "sg:classifiers":[
        {
            "category":"Professional",
            "subcategory":"Accounting & Tax Preparation",
            "type":"Services"
        }
    ],
    "sg:phone":"+32 14 43 96 60",
    "sg:postcode":"2300",
    "sg:province":"Antwerpen",
    "sg:tags":[
        "accountant"
    ],
    "wof:name":"J. Lambregts",
    "wof:placetype":"venue"
},
  "geometry": {"coordinates":[4.9495902061,51.3256607056],"type":"Point"}
}