{
  "type": "Feature",
  "properties": {
    "iso:country":"BE",
    "sg:address":"Avenue Brillat Savarin 98",
    "sg:city":"Bruxelles (ixelles)",
    "sg:classifiers":[
        {
            "category":"Banks & Credit Unions",
            "subcategory":"Investment Brokerage",
            "type":"Services"
        }
    ],
    "sg:phone":"+32 2 648 89 63",
    "sg:postcode":"1050",
    "sg:province":"Bruxelles-Capitale",
    "sg:tags":[
        "printing",
        "-"
    ],
    "wof:name":"Torfs A",
    "wof:placetype":"venue"
},
  "geometry": {"coordinates":[4.3840942383,50.8157310486],"type":"Point"}
}