{
  "type": "Feature",
  "properties": {
    "addr:full":"Kempenseweg 21 Zutendaal Limburg 3690",
    "addr:housenumber":"21",
    "addr:postcode":"3690",
    "addr:street":"Kempenseweg",
    "iso:country":"BE",
    "sg:address":"Kempenseweg 21",
    "sg:city":"Zutendaal",
    "sg:orig_category":"Etablissements Erotiques",
    "sg:phone":"+32 89 61 54 21",
    "sg:postcode":"3690",
    "sg:province":"Limburg",
    "wof:name":"Club Madison",
    "wof:placetype":"venue"
},
  "geometry": {"coordinates":[5.5591249466,50.9430427551],"type":"Point"}
}