{
  "type": "Feature",
  "properties": {
    "iso:country":"BE",
    "sg:address":"Edward Van Evenstraat 2ba",
    "sg:city":"Leuven",
    "sg:orig_category":"Hoger onderwijs",
    "sg:phone":"+32 16 32 32 20",
    "sg:postcode":"3000",
    "sg:province":"Vlaams-Brabant",
    "wof:name":"K.u.l.-dep.communicatiew.",
    "wof:placetype":"venue"
},
  "geometry": {"coordinates":[4.7033238411,50.8739852905],"type":"Point"}
}