{
  "type": "Feature",
  "properties": {
    "addr:full":"Zenderstraat 10 Destelbergen Oost-Vlaanderen 9070",
    "addr:housenumber":"10",
    "addr:postcode":"9070",
    "addr:street":"Zenderstraat",
    "iso:country":"BE",
    "sg:address":"Zenderstraat 10",
    "sg:city":"Destelbergen",
    "sg:orig_category":"Farmaceutische bereidingen and geneesmiddelen Fab",
    "sg:phone":"+32 9 228 20 00",
    "sg:postcode":"9070",
    "sg:province":"Oost-Vlaanderen",
    "wof:name":"Conforma",
    "wof:placetype":"venue"
},
  "geometry": {"coordinates":[3.7826530933,51.0540847778],"type":"Point"}
}