{
  "type": "Feature",
  "properties": {
    "addr:full":"Paul De Smet De Naeyerstraat 32b Middelkerke West-Vlaanderen 8430",
    "addr:housenumber":"32b",
    "addr:postcode":"8430",
    "addr:street":"Paul De Smet De Naeyerstraat",
    "iso:country":"BE",
    "sg:address":"Paul De Smet De Naeyerstraat 32b",
    "sg:city":"Middelkerke",
    "sg:classifiers":[
        {
            "category":"Food & Beverages",
            "subcategory":"Specialty",
            "type":"Retail Goods"
        }
    ],
    "sg:phone":"+32 59 30 18 97",
    "sg:postcode":"8430",
    "sg:province":"West-Vlaanderen",
    "sg:tags":[
        "health",
        "dietary",
        "-",
        "biological"
    ],
    "wof:name":"Natuurweelde",
    "wof:placetype":"venue"
},
  "geometry": {"coordinates":[2.8175799847,51.1887016296],"type":"Point"}
}