{
  "type": "Feature",
  "properties": {
    "addr:full":"Apostelstraat 19b1 Sint-niklaas Oost-Vlaanderen 9100",
    "addr:housenumber":"19b1",
    "addr:postcode":"9100",
    "addr:street":"Apostelstraat",
    "iso:country":"BE",
    "sg:address":"Apostelstraat 19b1",
    "sg:city":"Sint-niklaas",
    "sg:orig_category":"Activit\u00e9s d\u00b4action sociale sans h\u00e9bergement",
    "sg:phone":"+32 3 776 72 22",
    "sg:postcode":"9100",
    "sg:province":"Oost-Vlaanderen",
    "wof:name":"Jongeren Advies Centrum",
    "wof:placetype":"venue"
},
  "geometry": {"coordinates":[4.1431889534,51.1640052795],"type":"Point"}
}