{
  "type": "Feature",
  "properties": {
    "addr:full":"Watermolenstraat 24 Kruibeke Oost-Vlaanderen 9150",
    "addr:housenumber":"24",
    "addr:postcode":"9150",
    "addr:street":"Watermolenstraat",
    "iso:country":"BE",
    "sg:address":"Watermolenstraat 24",
    "sg:city":"Kruibeke",
    "sg:classifiers":[
        {
            "category":"Professional",
            "subcategory":"Management & Consulting",
            "type":"Services"
        }
    ],
    "sg:phone":"+32 3 296 91 09",
    "sg:postcode":"9150",
    "sg:province":"Oost-Vlaanderen",
    "sg:tags":[
        "consultant",
        "agency",
        "advertising"
    ],
    "wof:name":"Grillhouse",
    "wof:placetype":"venue"
},
  "geometry": {"coordinates":[4.3197312355,51.181968689],"type":"Point"}
}