{
  "type": "Feature",
  "properties": {
    "iso:country":"BE",
    "sg:address":"Boondaalse Steenweg 615",
    "sg:city":"Elsene/ixelles",
    "sg:orig_category":"Zuivelproducten",
    "sg:phone":"+32 2 673 88 73",
    "sg:postcode":"1050",
    "sg:province":"Bruxelles-Capitale",
    "wof:name":"Maison Le Livarot",
    "wof:placetype":"venue"
},
  "geometry": {"coordinates":[4.3917498589,50.8115310669],"type":"Point"}
}