{
  "type": "Feature",
  "properties": {
    "addr:full":"Chauss\u00c9e De Haecht 939 Evere Bruxelles-Capitale 1140",
    "addr:housenumber":"939",
    "addr:postcode":"1140",
    "addr:street":"Chausse\u0301E De Haecht",
    "iso:country":"BE",
    "sg:address":"Chauss\u00c9e De Haecht 939",
    "sg:city":"Evere",
    "sg:orig_category":"Imprimeries and copyshops",
    "sg:phone":"+32 2 241 94 91",
    "sg:postcode":"1140",
    "sg:province":"Bruxelles-Capitale",
    "wof:name":"Imprimerie Prince Willy & Fils",
    "wof:placetype":"venue"
},
  "geometry": {"coordinates":[4.4000730515,50.8735733032],"type":"Point"}
}