{
  "type": "Feature",
  "properties": {
    "iso:country":"BE",
    "sg:address":"Chauss\u00e9e De Namur 240",
    "sg:city":"Wavre",
    "sg:orig_category":"Autombile concessionaires",
    "sg:phone":"+32 10 45 05 65",
    "sg:postcode":"1300",
    "sg:province":"Brabant Wallon",
    "wof:name":"Land Rover Wavre",
    "wof:placetype":"venue"
},
  "geometry": {"coordinates":[4.6158418655,50.693195343],"type":"Point"}
}