{
  "type": "Feature",
  "properties": {
    "iso:country":"BE",
    "sg:address":"Rue Du Cardinal 38",
    "sg:city":"Brussel/bruxelles",
    "sg:orig_category":"Studios photographiques",
    "sg:phone":"+32 2 230 17 34",
    "sg:postcode":"1000",
    "sg:province":"Bruxelles-Capitale",
    "wof:name":"Jan Van De Vel",
    "wof:placetype":"venue"
},
  "geometry": {"coordinates":[4.3791999817,50.8487358093],"type":"Point"}
}