{
  "type": "Feature",
  "properties": {
    "addr:full":"Doorniksewijk 14 Kortrijk West-Vlaanderen 8500",
    "addr:housenumber":"14",
    "addr:postcode":"8500",
    "addr:street":"Doorniksewijk",
    "iso:country":"BE",
    "sg:address":"Doorniksewijk 14",
    "sg:city":"Kortrijk",
    "sg:classifiers":[
        {
            "category":"Banks & Credit Unions",
            "subcategory":"Financial Services",
            "type":"Services"
        }
    ],
    "sg:phone":"+32 56 22 07 16",
    "sg:postcode":"8500",
    "sg:province":"West-Vlaanderen",
    "sg:tags":[
        "loan",
        "mortgage"
    ],
    "wof:name":"Cofina Bvba",
    "wof:placetype":"venue"
},
  "geometry": {"coordinates":[3.2681179047,50.8235282898],"type":"Point"}
}