{
  "type": "Feature",
  "properties": {
    "iso:country":"BE",
    "sg:address":"Rue De Ch\u00e2telet 223",
    "sg:city":"Charleroi (couillet)",
    "sg:classifiers":[
        {
            "category":"Parking",
            "subcategory":"Lot",
            "type":"Transportation"
        }
    ],
    "sg:phone":"+32 71 36 25 82",
    "sg:postcode":"6010",
    "sg:province":"Hainaut",
    "sg:tags":[
        "armoured",
        "door",
        "fireproof"
    ],
    "wof:name":"Serrurerie Folie",
    "wof:placetype":"venue"
},
  "geometry": {"coordinates":[4.4640011787,50.3922080994],"type":"Point"}
}