{
  "type": "Feature",
  "properties": {
    "iso:country":"BE",
    "sg:address":"Chauss\u00c9e Roosevelt 12",
    "sg:city":"Amay",
    "sg:orig_category":"Banques and organismes de cr\u00e9dit",
    "sg:phone":"+32 85 31 28 13",
    "sg:postcode":"4540",
    "sg:province":"Li\u00e8ge",
    "wof:name":"Fortis",
    "wof:placetype":"venue"
},
  "geometry": {"coordinates":[5.3175449371,50.5477638245],"type":"Point"}
}