{
  "type": "Feature",
  "properties": {
    "addr:full":"Rue De La Fontaine 38 Braine L'alleud (braine-l'alleud) Brabant Wallon 1420",
    "addr:housenumber":"38",
    "addr:postcode":"1420",
    "addr:street":"Rue De La Fontaine",
    "iso:country":"BE",
    "sg:address":"Rue De La Fontaine 38",
    "sg:city":"Braine L'alleud (braine-l'alleud)",
    "sg:classifiers":[
        {
            "category":"Professional",
            "type":"Services"
        }
    ],
    "sg:phone":"+32 2 387 06 94",
    "sg:postcode":"1420",
    "sg:province":"Brabant Wallon",
    "sg:tags":[
        "leasing"
    ],
    "wof:name":"Locarolo",
    "wof:placetype":"venue"
},
  "geometry": {"coordinates":[-0.7083610296,47.4617347717],"type":"Point"}
}