{
  "type": "Feature",
  "properties": {
    "addr:full":"Rue Aux Vall\u00c9es 41 Namur Namur 5024",
    "addr:housenumber":"41",
    "addr:postcode":"5024",
    "addr:street":"Rue Aux Valle\u0301Es",
    "iso:country":"BE",
    "sg:address":"Rue Aux Vall\u00c9es 41",
    "sg:city":"Namur",
    "sg:classifiers":[
        {
            "category":"Personal",
            "subcategory":"Beauty Salon",
            "type":"Services"
        }
    ],
    "sg:phone":"+32 81 58 92 80",
    "sg:postcode":"5024",
    "sg:province":"Namur",
    "sg:tags":[
        "de",
        "coiffure"
    ],
    "wof:name":"Gisele Lhoste",
    "wof:placetype":"venue"
},
  "geometry": {"coordinates":[4.9644060135,50.4872894287],"type":"Point"}
}