{
  "type": "Feature",
  "properties": {
    "addr:full":"Rue De La Sucrerie 15 Hannut (trogn\u00e9e) Li\u00e8ge 4280",
    "addr:housenumber":"15",
    "addr:postcode":"4280",
    "addr:street":"Rue De La Sucrerie;Trogne\u0301E",
    "iso:country":"BE",
    "sg:address":"Rue De La Sucrerie 15",
    "sg:city":"Hannut (trogn\u00e9e)",
    "sg:classifiers":[
        {
            "category":"Manufacturing",
            "subcategory":"Motor Vehicles & Parts",
            "type":"Manufacturing & Wholesale Goods"
        }
    ],
    "sg:phone":"+32 19 51 24 15",
    "sg:postcode":"4280",
    "sg:province":"Li\u00e8ge",
    "sg:tags":[
        "bearing"
    ],
    "wof:name":"Hesbagri-transmission",
    "wof:placetype":"venue"
},
  "geometry": {"coordinates":[5.1231250763,50.6852645874],"type":"Point"}
}