{
  "type": "Feature",
  "properties": {
    "addr:full":"Chauss\u00e9e De Boondael 362 Bruxelles (ixelles) Bruxelles-Capitale 1050",
    "addr:housenumber":"362",
    "addr:postcode":"1050",
    "addr:street":"Chausse\u0301E De Boondael",
    "iso:country":"BE",
    "sg:address":"Chauss\u00e9e De Boondael 362",
    "sg:city":"Bruxelles (ixelles)",
    "sg:classifiers":[
        {
            "category":"Home & Garden",
            "subcategory":"Home Furnishings",
            "type":"Retail Goods"
        }
    ],
    "sg:phone":"+32 2 648 61 83",
    "sg:postcode":"1050",
    "sg:province":"Bruxelles-Capitale",
    "sg:tags":[
        "interior",
        "decoration"
    ],
    "wof:name":"Mager",
    "wof:placetype":"venue"
},
  "geometry": {"coordinates":[4.3862252235,50.8180656433],"type":"Point"}
}