{
  "type": "Feature",
  "properties": {
    "addr:full":"Clos Wathy De Hombroux 1 Ans Li\u00e8ge 4432",
    "addr:housenumber":"1",
    "addr:postcode":"4432",
    "addr:street":"Clos Wathy De Hombroux",
    "iso:country":"BE",
    "sg:address":"Clos Wathy De Hombroux 1",
    "sg:city":"Ans",
    "sg:orig_category":"Landmeters",
    "sg:phone":"+32 4 246 57 98",
    "sg:postcode":"4432",
    "sg:province":"Li\u00e8ge",
    "wof:name":"Jos\u00c9 Orban",
    "wof:placetype":"venue"
},
  "geometry": {"coordinates":[5.5229320526,50.6747169495],"type":"Point"}
}