{
  "type": "Feature",
  "properties": {
    "addr:full":"Rue Rogier 30 Namur Namur 5000",
    "addr:housenumber":"30",
    "addr:postcode":"5000",
    "addr:street":"Rue Rogier",
    "iso:country":"BE",
    "sg:address":"Rue Rogier 30",
    "sg:city":"Namur",
    "sg:orig_category":"Jeux de hasard",
    "sg:phone":"+32 81 23 05 52",
    "sg:postcode":"5000",
    "sg:province":"Namur",
    "wof:name":"Normandie Club",
    "wof:placetype":"venue"
},
  "geometry": {"coordinates":[4.8667330742,50.4674987793],"type":"Point"}
}