{
  "type": "Feature",
  "properties": {
    "iso:country":"BE",
    "sg:address":"Markt 32",
    "sg:city":"Geraardsbergen",
    "sg:classifiers":[
        {
            "category":"Health Services",
            "subcategory":"Dentist",
            "type":"Services"
        }
    ],
    "sg:phone":"+32 54 41 80 78",
    "sg:postcode":"9500",
    "sg:province":"Oost-Vlaanderen",
    "wof:name":"Gosseye Bart",
    "wof:placetype":"venue"
},
  "geometry": {"coordinates":[3.8821949959,50.7717170715],"type":"Point"}
}