{
  "type": "Feature",
  "properties": {
    "addr:full":"Route De Huy 133 Lincent Li\u00e8ge 4287",
    "addr:housenumber":"133",
    "addr:postcode":"4287",
    "addr:street":"Route De Huy",
    "iso:country":"BE",
    "sg:address":"Route De Huy 133",
    "sg:city":"Lincent",
    "sg:classifiers":[
        {
            "category":"Shopping",
            "subcategory":"Books",
            "type":"Retail Goods"
        }
    ],
    "sg:phone":"+32 19 63 40 57",
    "sg:postcode":"4287",
    "sg:province":"Li\u00e8ge",
    "sg:tags":[
        "bookseller"
    ],
    "wof:name":"Servais",
    "wof:placetype":"venue"
},
  "geometry": {"coordinates":[5.0278477669,50.7204933167],"type":"Point"}
}