{
  "type": "Feature",
  "properties": {
    "iso:country":"BE",
    "sg:address":"Avenue De L'agriculture 24",
    "sg:city":"Li\u00c8ge",
    "sg:orig_category":"Boekhouders",
    "sg:phone":"+32 4 343 17 01",
    "sg:postcode":"4030",
    "sg:province":"Li\u00e8ge",
    "wof:name":"Marguerite Belluzzo",
    "wof:placetype":"venue"
},
  "geometry": {"coordinates":[5.6067290306,50.6273269653],"type":"Point"}
}