{
  "type": "Feature",
  "properties": {
    "iso:country":"BE",
    "sg:address":"Avenue De L'equerre 29-102",
    "sg:city":"Ottignies-louvain-la-neuve (louvain-la-neuve)",
    "sg:classifiers":[
        {
            "category":"Health Services",
            "subcategory":"Hospital",
            "type":"Services"
        }
    ],
    "sg:phone":"+32 10 45 35 54",
    "sg:postcode":"1348",
    "sg:province":"Brabant Wallon",
    "wof:name":"La Cord\u00e9e Asbl",
    "wof:placetype":"venue"
},
  "geometry": {"coordinates":[4.6096229553,50.6642227173],"type":"Point"}
}