{
  "type": "Feature",
  "properties": {
    "iso:country":"BE",
    "sg:address":"Voye-d'adam 77ba",
    "sg:city":"Doische",
    "sg:orig_category":"Enseignement maternel and primaire",
    "sg:phone":"+32 82 67 70 16",
    "sg:postcode":"5680",
    "sg:province":"Namur",
    "wof:name":"Ecole Fond. Communale",
    "wof:placetype":"venue"
},
  "geometry": {"coordinates":[4.7327771187,50.1702651978],"type":"Point"}
}