{
  "type": "Feature",
  "properties": {
    "addr:full":"Ledelaan 48 Evergem Oost-Vlaanderen 9940",
    "addr:housenumber":"48",
    "addr:postcode":"9940",
    "addr:street":"Ledelaan;Oost-Vlaanderen",
    "iso:country":"BE",
    "sg:address":"Ledelaan 48",
    "sg:city":"Evergem",
    "sg:orig_category":"Travaux de pl\u00e2trage",
    "sg:phone":"+32 9 357 49 68",
    "sg:postcode":"9940",
    "sg:province":"Oost-Vlaanderen",
    "wof:name":"Roger Praet",
    "wof:placetype":"venue"
},
  "geometry": {"coordinates":[3.6634669304,51.1206893921],"type":"Point"}
}