{
  "type": "Feature",
  "properties": {
    "iso:country":"BE",
    "sg:address":"Rue Du Palais 29",
    "sg:city":"Verviers",
    "sg:classifiers":[
        {
            "category":"Social Services",
            "subcategory":"Retirement Home",
            "type":"Services"
        }
    ],
    "sg:phone":"+32 87 22 21 31",
    "sg:postcode":"4800",
    "sg:province":"Li\u00e8ge",
    "sg:tags":[
        "compagnies",
        "vie",
        "assurance",
        "habitation"
    ],
    "wof:name":"Les Assurances F\u00c9d\u00c9rales",
    "wof:placetype":"venue"
},
  "geometry": {"coordinates":[5.8636422157,50.5902748108],"type":"Point"}
}