{
  "type": "Feature",
  "properties": {
    "iso:country":"BE",
    "sg:address":"Dorpstraat 34",
    "sg:city":"Wichelen",
    "sg:classifiers":[
        {
            "category":"Cafe",
            "type":"Food & Drink"
        }
    ],
    "sg:phone":"+32 9 369 95 50",
    "sg:postcode":"9260",
    "sg:province":"Oost-Vlaanderen",
    "sg:tags":[
        "caf\u00e9s"
    ],
    "wof:name":"Caf\u00c9 De Drie Rozen",
    "wof:placetype":"venue"
},
  "geometry": {"coordinates":[3.9714260101,51.0125465393],"type":"Point"}
}