{
  "type": "Feature",
  "properties": {
    "addr:full":"Rue Taillis 313 Chatelet Hainaut 6200",
    "addr:housenumber":"313",
    "addr:postcode":"chatelet;6200",
    "addr:street":"Rue Taillis",
    "iso:country":"BE",
    "sg:address":"Rue Taillis 313",
    "sg:city":"Chatelet",
    "sg:orig_category":"Graphologues, astrologues, voyants and radiesth\u00e9sistes",
    "sg:phone":"+32 476 44 06 63",
    "sg:postcode":"6200",
    "sg:province":"Hainaut",
    "wof:name":"Salvi",
    "wof:placetype":"venue"
},
  "geometry": {"coordinates":[4.5122470856,50.4393234253],"type":"Point"}
}