{
  "type": "Feature",
  "properties": {
    "iso:country":"BE",
    "sg:address":"Kaprijkstraat 18",
    "sg:city":"Kaprijke",
    "sg:orig_category":"Rundveehouders",
    "sg:phone":"+32 9 377 27 90",
    "sg:postcode":"9971",
    "sg:province":"Oost-Vlaanderen",
    "wof:name":"Bisschop",
    "wof:placetype":"venue"
},
  "geometry": {"coordinates":[3.6474089622,51.199760437],"type":"Point"}
}