{
  "type": "Feature",
  "properties": {
    "iso:country":"BE",
    "sg:address":"Canadaplein 3",
    "sg:city":"Brugge (sint-andries)",
    "sg:classifiers":[
        {
            "category":"Health Services",
            "subcategory":"Dentist",
            "type":"Services"
        }
    ],
    "sg:phone":"+32 50 38 08 09",
    "sg:postcode":"8200",
    "sg:province":"West-Vlaanderen",
    "wof:name":"Bosschem J",
    "wof:placetype":"venue"
},
  "geometry": {"coordinates":[3.2094950676,51.2039337158],"type":"Point"}
}