{
  "type": "Feature",
  "properties": {
    "addr:full":"Rijselsestraat 76a Ieper West-Vlaanderen 8900",
    "addr:housenumber":"76a",
    "addr:postcode":"8900",
    "addr:street":"Rijselsestraat",
    "iso:country":"BE",
    "sg:address":"Rijselsestraat 76a",
    "sg:city":"Ieper",
    "sg:classifiers":[
        {
            "category":"Real Estate",
            "subcategory":"Architect",
            "type":"Services"
        }
    ],
    "sg:phone":"+32 57 21 88 19",
    "sg:postcode":"8900",
    "sg:province":"West-Vlaanderen",
    "wof:name":"Breyne T",
    "wof:placetype":"venue"
},
  "geometry": {"coordinates":[2.8873269558,50.8483963013],"type":"Point"}
}