{
  "type": "Feature",
  "properties": {
    "addr:full":"Ninoofsesteenweg 229 Pepingen Vlaams-Brabant 1670",
    "addr:housenumber":"229",
    "addr:postcode":"1670",
    "addr:street":"Ninoofsesteenweg",
    "iso:country":"BE",
    "sg:address":"Ninoofsesteenweg 229",
    "sg:city":"Pepingen",
    "sg:classifiers":[
        {
            "category":"Wholesale",
            "subcategory":"Machinery & Supplies",
            "type":"Manufacturing & Wholesale Goods"
        }
    ],
    "sg:phone":"+32 2 532 48 66",
    "sg:postcode":"1670",
    "sg:province":"Vlaams-Brabant",
    "sg:tags":[
        "water",
        "pump",
        "-"
    ],
    "wof:name":"Barel R & Zn",
    "wof:placetype":"venue"
},
  "geometry": {"coordinates":[4.1462340355,50.7639694214],"type":"Point"}
}