{
  "type": "Feature",
  "properties": {
    "addr:full":"Bd. De La Plaine 17 Bruxelles Bruxelles-Capitale 1050",
    "addr:housenumber":"17",
    "addr:postcode":"1050",
    "addr:street":"Bd. De La Plaine",
    "iso:country":"BE",
    "sg:address":"Bd. De La Plaine 17",
    "sg:city":"Bruxelles",
    "sg:classifiers":[
        {
            "category":"Health Services",
            "subcategory":"Medical Lab",
            "type":"Services"
        }
    ],
    "sg:phone":"+32 2 722 02 11",
    "sg:postcode":"1050",
    "sg:province":"Bruxelles-Capitale",
    "sg:tags":[
        "chemical",
        "pharmaceutical",
        "pharmacy"
    ],
    "wof:name":"Pfizer Eur Serv Center Nv",
    "wof:placetype":"venue"
},
  "geometry": {"coordinates":[-94.99756622309999,39.1721801758],"type":"Point"}
}