{
  "type": "Feature",
  "properties": {
    "addr:full":"Boulevard Auguste Reyers 108 Bruxelles (schaerbeek) Bruxelles-Capitale 1030",
    "addr:housenumber":"108",
    "addr:postcode":"1030",
    "addr:street":"Boulevard Auguste Reyers",
    "iso:country":"BE",
    "sg:address":"Boulevard Auguste Reyers 108",
    "sg:city":"Bruxelles (schaerbeek)",
    "sg:classifiers":[
        {
            "category":"Professional",
            "subcategory":"Management & Consulting",
            "type":"Services"
        }
    ],
    "sg:phone":"+32 2 743 28 50",
    "sg:postcode":"1030",
    "sg:province":"Bruxelles-Capitale",
    "sg:tags":[
        "consultant",
        "agency",
        "advertising"
    ],
    "wof:name":"Nestor & Co",
    "wof:placetype":"venue"
},
  "geometry": {"coordinates":[4.4032649994,50.8482971191],"type":"Point"}
}