{
  "type": "Feature",
  "properties": {
    "iso:country":"BE",
    "sg:address":"Gasthuisstraat 28",
    "sg:city":"Meerhout",
    "sg:orig_category":"Openbare veiligheid",
    "sg:phone":"+32 14 30 00 03",
    "sg:postcode":"2450",
    "sg:province":"Antwerpen",
    "wof:name":"Federale Politie",
    "wof:placetype":"venue"
},
  "geometry": {"coordinates":[5.0783019066,51.1338920593],"type":"Point"}
}