{
  "type": "Feature",
  "properties": {
    "addr:full":"Th. Toyeplein 6 Zwevegem West-Vlaanderen 8550",
    "addr:housenumber":"6",
    "addr:postcode":"8550",
    "iso:country":"BE",
    "sg:address":"Th. Toyeplein 6",
    "sg:city":"Zwevegem",
    "sg:orig_category":"Salles de billard and snooker",
    "sg:phone":"+32 56 75 34 80",
    "sg:postcode":"8550",
    "sg:province":"West-Vlaanderen",
    "wof:name":"Snooker Dollar",
    "wof:placetype":"venue"
},
  "geometry": {"coordinates":[3.3335781097,50.8134498596],"type":"Point"}
}