{
  "type": "Feature",
  "properties": {
    "iso:country":"BE",
    "sg:address":"Verbondstraat 95",
    "sg:city":"Antwerpen",
    "sg:classifiers":[
        {
            "category":"Professional",
            "subcategory":"Engineering",
            "type":"Services"
        }
    ],
    "sg:phone":"+32 3 219 87 77",
    "sg:postcode":"2000",
    "sg:province":"Antwerpen",
    "sg:tags":[
        "-"
    ],
    "wof:name":"Brainbuilding",
    "wof:placetype":"venue"
},
  "geometry": {"coordinates":[4.3985657692,51.2081604004],"type":"Point"}
}