{
  "type": "Feature",
  "properties": {
    "iso:country":"BE",
    "sg:address":"Quinten Matsijslei 42b7",
    "sg:city":"Antwerpen",
    "sg:classifiers":[
        {
            "category":"Professional",
            "subcategory":"Accounting & Tax Preparation",
            "type":"Services"
        }
    ],
    "sg:phone":"+32 3 233 47 21",
    "sg:postcode":"2018",
    "sg:province":"Antwerpen",
    "sg:tags":[
        "accountant"
    ],
    "wof:name":"Alfons Van Dessel",
    "wof:placetype":"venue"
},
  "geometry": {"coordinates":[4.4176230431,51.2117424011],"type":"Point"}
}