{
  "type": "Feature",
  "properties": {
    "iso:country":"BE",
    "sg:address":"Opworpstraat 16",
    "sg:city":"Lummen",
    "sg:classifiers":[
        {
            "category":"Manufacturing",
            "subcategory":"Glass & Minerals",
            "type":"Manufacturing & Wholesale Goods"
        }
    ],
    "sg:phone":"+32 13 52 19 32",
    "sg:postcode":"3560",
    "sg:province":"Limburg",
    "sg:tags":[
        "safety"
    ],
    "wof:name":"Claes",
    "wof:placetype":"venue"
},
  "geometry": {"coordinates":[5.2234201431,50.9770698547],"type":"Point"}
}