{
  "type": "Feature",
  "properties": {
    "iso:country":"BE",
    "sg:address":"Rue Champs 19",
    "sg:city":"Tubize",
    "sg:orig_category":"Sportclubs",
    "sg:phone":"+32 2 355 54 29",
    "sg:postcode":"1480",
    "sg:province":"Brabant Wallon",
    "wof:name":"Shotokan Karate Club Tubize",
    "wof:placetype":"venue"
},
  "geometry": {"coordinates":[4.1994700432,50.6995925903],"type":"Point"}
}