{
  "type": "Feature",
  "properties": {
    "addr:full":"Barisdamstraat 18b Kortemark (zarren-werken) West-Vlaanderen 8610",
    "addr:housenumber":"18b",
    "addr:postcode":"8610",
    "addr:street":"Barisdamstraat",
    "iso:country":"BE",
    "sg:address":"Barisdamstraat 18b",
    "sg:city":"Kortemark (zarren-werken)",
    "sg:classifiers":[
        {
            "category":"Personal",
            "subcategory":"Beauty Salon",
            "type":"Services"
        }
    ],
    "sg:phone":"+32 51 57 14 42",
    "sg:postcode":"8610",
    "sg:province":"West-Vlaanderen",
    "sg:tags":[
        "lady",
        "-",
        "hairdressing"
    ],
    "wof:name":"Po\u00e8me Coiffure",
    "wof:placetype":"venue"
},
  "geometry": {"coordinates":[2.9717130661,51.0149841309],"type":"Point"}
}