{
  "type": "Feature",
  "properties": {
    "addr:full":"Rue Neuville 3 Profondeville Namur 5170",
    "addr:housenumber":"3",
    "addr:postcode":"5170",
    "addr:street":"Rue Neuville",
    "iso:country":"BE",
    "sg:address":"Rue Neuville 3",
    "sg:city":"Profondeville",
    "sg:orig_category":"Slagers",
    "sg:phone":"+32 81 41 18 71",
    "sg:postcode":"5170",
    "sg:province":"Namur",
    "wof:name":"C. Dochain",
    "wof:placetype":"venue"
},
  "geometry": {"coordinates":[4.8674049377,50.3786392212],"type":"Point"}
}