{
  "type": "Feature",
  "properties": {
    "iso:country":"BE",
    "sg:address":"Wittenonnenstraat 21",
    "sg:city":"Oostende",
    "sg:classifiers":[
        {
            "category":"Retail",
            "subcategory":"Event Space",
            "type":"Services"
        }
    ],
    "sg:phone":"+32 59 50 00 98",
    "sg:postcode":"8400",
    "sg:province":"West-Vlaanderen",
    "sg:tags":[
        "dinner",
        "set",
        "-",
        "cutlery"
    ],
    "wof:name":"Hints",
    "wof:placetype":"venue"
},
  "geometry": {"coordinates":[2.9177010059,51.2311019897],"type":"Point"}
}