{
  "type": "Feature",
  "properties": {
    "iso:country":"BE",
    "sg:address":"Goolderheideweg 11",
    "sg:city":"Bocholt",
    "sg:orig_category":"Procesbesturingssystemen Fab",
    "sg:phone":"+32 89 46 93 40",
    "sg:postcode":"3950",
    "sg:province":"Limburg",
    "wof:name":"Mk Systems",
    "wof:placetype":"venue"
},
  "geometry": {"coordinates":[5.5380139351,51.1745491028],"type":"Point"}
}