{
  "type": "Feature",
  "properties": {
    "addr:full":"Het Dorlik 5 Hasselt Limburg 3500",
    "addr:housenumber":"5",
    "addr:postcode":"3500",
    "iso:country":"BE",
    "sg:address":"Het Dorlik 5",
    "sg:city":"Hasselt",
    "sg:orig_category":"Herstellingen and onderhoud van auto's Voertuigen",
    "sg:phone":"+32 11 26 15 02",
    "sg:postcode":"3500",
    "sg:province":"Limburg",
    "wof:name":"Garage Mipaso",
    "wof:placetype":"venue"
},
  "geometry": {"coordinates":[5.3601770401,50.9246482849],"type":"Point"}
}