{
  "type": "Feature",
  "properties": {
    "addr:full":"Driehoekstraat 28 Wijnegem Antwerpen 2110",
    "addr:housenumber":"28",
    "addr:postcode":"2110",
    "addr:street":"Driehoekstraat",
    "iso:country":"BE",
    "sg:address":"Driehoekstraat 28",
    "sg:city":"Wijnegem",
    "sg:classifiers":[
        {
            "category":"Education",
            "subcategory":"School",
            "type":"Public Place"
        }
    ],
    "sg:phone":"+32 3 353 92 80",
    "sg:postcode":"2110",
    "sg:province":"Antwerpen",
    "sg:tags":[
        "-",
        "private"
    ],
    "wof:name":"Harmony Color & Style",
    "wof:placetype":"venue"
},
  "geometry": {"coordinates":[4.5164990425,51.2272720337],"type":"Point"}
}