{
  "type": "Feature",
  "properties": {
    "iso:country":"BE",
    "sg:address":"Rodenbachstraat 24",
    "sg:city":"Deerlijk",
    "sg:classifiers":[
        {
            "category":"Personal",
            "subcategory":"Beauty Salon",
            "type":"Services"
        }
    ],
    "sg:phone":"+32 56 70 52 61",
    "sg:postcode":"8540",
    "sg:province":"West-Vlaanderen",
    "sg:tags":[
        "de",
        "coiffure"
    ],
    "wof:name":"Coiffure Bellinea",
    "wof:placetype":"venue"
},
  "geometry": {"coordinates":[3.3509619236,50.852355957],"type":"Point"}
}