{
  "type": "Feature",
  "properties": {
    "iso:country":"BE",
    "sg:address":"Rue De La Carri\u00e8re 13",
    "sg:city":"Braine-le-ch\u00e2teau (wauthier-braine)",
    "sg:classifiers":[
        {
            "category":"Building & Trades",
            "subcategory":"Landscaping Services",
            "type":"Services"
        }
    ],
    "sg:phone":"+32 477 84 04 53",
    "sg:postcode":"1440",
    "sg:province":"Brabant Wallon",
    "sg:tags":[
        "gardening",
        "garden",
        "maintenance"
    ],
    "wof:name":"Cottage Garden Sprl",
    "wof:placetype":"venue"
},
  "geometry": {"coordinates":[4.3243670464,50.6840324402],"type":"Point"}
}