{
  "type": "Feature",
  "properties": {
    "addr:full":"Rue De Valenciennes 230 Bernissart Hainaut 7320",
    "addr:housenumber":"230",
    "addr:postcode":"7320",
    "addr:street":"Rue De Valenciennes",
    "iso:country":"BE",
    "sg:address":"Rue De Valenciennes 230",
    "sg:city":"Bernissart",
    "sg:orig_category":"Slagers",
    "sg:phone":"+32 69 57 60 64",
    "sg:postcode":"7320",
    "sg:province":"Hainaut",
    "wof:name":"Ghislain Lecomte",
    "wof:placetype":"venue"
},
  "geometry": {"coordinates":[3.6399281025,50.4775276184],"type":"Point"}
}