{
  "type": "Feature",
  "properties": {
    "iso:country":"BE",
    "sg:address":"Bernard Spaelaan 54",
    "sg:city":"Gent",
    "sg:classifiers":[
        {
            "category":"Personal",
            "subcategory":"Beauty Salon",
            "type":"Services"
        }
    ],
    "sg:phone":"+32 9 223 63 88",
    "sg:postcode":"9000",
    "sg:province":"Oost-Vlaanderen",
    "sg:tags":[
        "de",
        "coiffure"
    ],
    "wof:name":"Coiffure Andr\u00c9",
    "wof:placetype":"venue"
},
  "geometry": {"coordinates":[3.7098100185,51.0488700867],"type":"Point"}
}