{
  "type": "Feature",
  "properties": {
    "addr:full":"Kazerneweg 12-14 Komen Hainaut 7780",
    "addr:housenumber":"12-14",
    "addr:postcode":"7780",
    "addr:street":"Kazerneweg;Hainaut",
    "iso:country":"BE",
    "sg:address":"Kazerneweg 12-14",
    "sg:city":"Komen",
    "sg:classifiers":[
        {
            "category":"Wholesale",
            "subcategory":"Machinery & Supplies",
            "type":"Manufacturing & Wholesale Goods"
        }
    ],
    "sg:phone":"+32 56 55 95 55",
    "sg:postcode":"7780",
    "sg:province":"Hainaut",
    "sg:tags":[
        "food",
        "processing",
        "-",
        "machine",
        "equipment",
        "engineering",
        "mechanical"
    ],
    "wof:name":"Gernal Nv",
    "wof:placetype":"venue"
},
  "geometry": {"coordinates":[3.0113270283,50.7792472839],"type":"Point"}
}