{
  "type": "Feature",
  "properties": {
    "addr:full":"Berchemstraat 93 Dilbeek Vlaams-Brabant 1700",
    "addr:housenumber":"93",
    "addr:postcode":"1700",
    "addr:street":"Berchemstraat",
    "iso:country":"BE",
    "sg:address":"Berchemstraat 93",
    "sg:city":"Dilbeek",
    "sg:classifiers":[
        {
            "category":"Banks & Credit Unions",
            "subcategory":"Financial Services",
            "type":"Services"
        }
    ],
    "sg:phone":"+32 2 468 06 98",
    "sg:postcode":"1700",
    "sg:province":"Vlaams-Brabant",
    "sg:tags":[
        "franchising"
    ],
    "wof:name":"Exotic Capital Bvba",
    "wof:placetype":"venue"
},
  "geometry": {"coordinates":[4.274520874,50.8492660522],"type":"Point"}
}