{
  "type": "Feature",
  "properties": {
    "iso:country":"BE",
    "sg:address":"Bredabaan 1305",
    "sg:city":"Schoten",
    "sg:classifiers":[
        {
            "category":"Retail",
            "subcategory":"Car Wash",
            "type":"Services"
        }
    ],
    "sg:phone":"+32 3 646 92 63",
    "sg:postcode":"2900",
    "sg:province":"Antwerpen",
    "sg:tags":[
        "automobile",
        "washing",
        "-",
        "truck"
    ],
    "wof:name":"Mammoet Car Wash",
    "wof:placetype":"venue"
},
  "geometry": {"coordinates":[4.4650230408,51.2690010071],"type":"Point"}
}