{
  "type": "Feature",
  "properties": {
    "addr:full":"Wezenstraat 20 Melle Oost-Vlaanderen 9090",
    "addr:housenumber":"20",
    "addr:postcode":"9090",
    "addr:street":"Wezenstraat",
    "iso:country":"BE",
    "sg:address":"Wezenstraat 20",
    "sg:city":"Melle",
    "sg:classifiers":[
        {
            "category":"Retail",
            "subcategory":"Veterinary Services",
            "type":"Services"
        }
    ],
    "sg:phone":"+32 9 252 23 21",
    "sg:postcode":"9090",
    "sg:province":"Oost-Vlaanderen",
    "sg:tags":[
        "veterinarian"
    ],
    "wof:name":"De Knibber B",
    "wof:placetype":"venue"
},
  "geometry": {"coordinates":[3.8002409935,51.0047569275],"type":"Point"}
}