{
  "type": "Feature",
  "properties": {
    "iso:country":"BE",
    "sg:address":"Sint-martinusgaarde 16",
    "sg:city":"Ganshoren",
    "sg:orig_category":"Stoelen and zitmeubelen Fab",
    "sg:phone":"+32 2 425 61 23",
    "sg:postcode":"1083",
    "sg:province":"Bruxelles-Capitale",
    "wof:name":"Debersaques",
    "wof:placetype":"venue"
},
  "geometry": {"coordinates":[4.315571785,50.8707809448],"type":"Point"}
}