{
  "type": "Feature",
  "properties": {
    "addr:full":"Vagevuurstraat 56 Kortrijk West-Vlaanderen 8510",
    "addr:housenumber":"56",
    "addr:postcode":"8510",
    "addr:street":"Vagevuurstraat",
    "iso:country":"BE",
    "sg:address":"Vagevuurstraat 56",
    "sg:city":"Kortrijk",
    "sg:orig_category":"M\u00e9decins and sp\u00e9cialistes",
    "sg:phone":"+32 56 21 85 21",
    "sg:postcode":"8510",
    "sg:province":"West-Vlaanderen",
    "wof:name":"Paul Vanbiervliet",
    "wof:placetype":"venue"
},
  "geometry": {"coordinates":[3.2339420319,50.8041267395],"type":"Point"}
}