{
  "type": "Feature",
  "properties": {
    "iso:country":"BE",
    "sg:address":"Bredabaan 395",
    "sg:city":"Brasschaat",
    "sg:classifiers":[
        {
            "category":"Train Station",
            "subcategory":"Rail",
            "type":"Transportation"
        }
    ],
    "sg:phone":"+32 3 225 16 16",
    "sg:postcode":"2930",
    "sg:province":"Antwerpen",
    "sg:tags":[
        "ship",
        "chandler"
    ],
    "wof:name":"Gylstorff & Co",
    "wof:placetype":"venue"
},
  "geometry": {"coordinates":[4.4923968315,51.2904090881],"type":"Point"}
}