{
  "type": "Feature",
  "properties": {
    "iso:country":"BE",
    "sg:address":"Chauss\u00c9e De Valenciennes 48",
    "sg:city":"Ath",
    "sg:orig_category":"Enseignement sup\u00e9rieur",
    "sg:phone":"+32 68 84 20 15",
    "sg:postcode":"7801",
    "sg:province":"Hainaut",
    "wof:name":"Hepho-d\u00c9p. P\u00c9dagogique",
    "wof:placetype":"venue"
},
  "geometry": {"coordinates":[3.7621150017,50.6197013855],"type":"Point"}
}