{
  "type": "Feature",
  "properties": {
    "iso:country":"BE",
    "sg:address":"Ieperstraat 173",
    "sg:city":"Wevelgem (moorsele)",
    "sg:classifiers":[
        {
            "category":"Wholesale",
            "subcategory":"Plants",
            "type":"Manufacturing & Wholesale Goods"
        }
    ],
    "sg:phone":"+32 56 54 04 14",
    "sg:postcode":"8560",
    "sg:province":"West-Vlaanderen",
    "sg:tags":[
        "whol",
        "flower",
        "-",
        "grower"
    ],
    "wof:name":"Maes-reyns Kwekerij Bvba",
    "wof:placetype":"venue"
},
  "geometry": {"coordinates":[3.1063759327,50.8374290466],"type":"Point"}
}