{
  "type": "Feature",
  "properties": {
    "addr:full":"Lesbroussart 113 Bruxelles-ixelles Bruxelles-Capitale 1050",
    "addr:housenumber":"113",
    "addr:postcode":"1050",
    "addr:street":"Lesbroussart",
    "iso:country":"BE",
    "sg:address":"Lesbroussart 113",
    "sg:city":"Bruxelles-ixelles",
    "sg:orig_category":"Diverse bouwafwerking and reiniging Wasserijen, Reiniging and Droogkuis",
    "sg:phone":"+32 2 644 25 90",
    "sg:postcode":"1050",
    "sg:province":"Bruxelles-Capitale",
    "wof:name":"Dbm Mister Kool\u00b4s",
    "wof:placetype":"venue"
},
  "geometry": {"coordinates":[4.3652191162,50.8277511597],"type":"Point"}
}