{
  "type": "Feature",
  "properties": {
    "addr:full":"Rue Valduc 309 Oudergem/auderghem Bruxelles-Capitale 1160",
    "addr:housenumber":"309",
    "addr:postcode":"1160",
    "addr:street":"Rue Valduc;/",
    "iso:country":"BE",
    "sg:address":"Rue Valduc 309",
    "sg:city":"Oudergem/auderghem",
    "sg:orig_category":"D\u00e9taillants en pi\u00e8ces and accessoires de voitures",
    "sg:phone":"+32 2 675 70 36",
    "sg:postcode":"1160",
    "sg:province":"Bruxelles-Capitale",
    "wof:name":"Fe. Mig Belgium",
    "wof:placetype":"venue"
},
  "geometry": {"coordinates":[4.4115071297,50.8208808899],"type":"Point"}
}