{
  "type": "Feature",
  "properties": {
    "iso:country":"BE",
    "sg:address":"Legebaan 103",
    "sg:city":"Nijlen",
    "sg:classifiers":[
        {
            "category":"Real Estate",
            "subcategory":"Architect",
            "type":"Services"
        }
    ],
    "sg:phone":"+32 3 411 01 10",
    "sg:postcode":"2560",
    "sg:province":"Antwerpen",
    "wof:name":"Van Noten M",
    "wof:placetype":"venue"
},
  "geometry": {"coordinates":[4.6745448112,51.1504096985],"type":"Point"}
}