{
  "type": "Feature",
  "properties": {
    "iso:country":"BE",
    "sg:address":"Gouden Kruispunt",
    "sg:city":"Tielt-winge",
    "sg:orig_category":"Fujitsu Siemens. Ordinateurs and \u00e9quipement informatique",
    "sg:phone":"+32 50 34 80 03",
    "sg:postcode":"3390",
    "sg:province":"Vlaams-Brabant",
    "wof:name":"Silverminds Retail",
    "wof:placetype":"venue"
},
  "geometry": {"coordinates":[4.8715748787,50.9058761597],"type":"Point"}
}