{
  "type": "Feature",
  "properties": {
    "addr:full":"Rue Du Grand Central 71 Charleroi Hainaut 6000",
    "addr:housenumber":"71",
    "addr:postcode":"6000",
    "addr:street":"Rue Du Grand Central;Hainaut",
    "iso:country":"BE",
    "sg:address":"Rue Du Grand Central 71",
    "sg:city":"Charleroi",
    "sg:classifiers":[
        {
            "category":"Health Services",
            "subcategory":"Dentist",
            "type":"Services"
        }
    ],
    "sg:phone":"+32 71 31 26 48",
    "sg:postcode":"6000",
    "sg:province":"Hainaut",
    "wof:name":"Bacq Michel",
    "wof:placetype":"venue"
},
  "geometry": {"coordinates":[4.4366779327,50.4089279175],"type":"Point"}
}