{
  "type": "Feature",
  "properties": {
    "addr:full":"Gidsenlei 6 Heist-op-den-berg Antwerpen 2221",
    "addr:housenumber":"6",
    "addr:postcode":"2221",
    "addr:street":"Gidsenlei",
    "iso:country":"BE",
    "sg:address":"Gidsenlei 6",
    "sg:city":"Heist-op-den-berg",
    "sg:orig_category":"HERSTELLING ELEKTRISCHE HUISHOUDAPPARATEN",
    "sg:phone":"+32 15 22 25 16",
    "sg:postcode":"2221",
    "sg:province":"Antwerpen",
    "wof:name":"Maurits Claes",
    "wof:placetype":"venue"
},
  "geometry": {"coordinates":[4.7739758492,51.0512428284],"type":"Point"}
}