{
  "type": "Feature",
  "properties": {
    "iso:country":"BE",
    "sg:address":"Hamiltonpark 20",
    "sg:city":"Brugge",
    "sg:classifiers":[
        {
            "category":"Professional",
            "subcategory":"Lawyer & Legal Services",
            "type":"Services"
        }
    ],
    "sg:phone":"+32 50 34 04 07",
    "sg:postcode":"8000",
    "sg:province":"West-Vlaanderen",
    "wof:name":"Bouslama Naima",
    "wof:placetype":"venue"
},
  "geometry": {"coordinates":[3.2039470673,51.2130508423],"type":"Point"}
}