{
  "type": "Feature",
  "properties": {
    "addr:full":"Willem Herreynsstraat 37 Mechelen Antwerpen 2800",
    "addr:housenumber":"37",
    "addr:postcode":"2800",
    "addr:street":"Willem Herreynsstraat",
    "iso:country":"BE",
    "sg:address":"Willem Herreynsstraat 37",
    "sg:city":"Mechelen",
    "sg:orig_category":"Artsen and specialisten",
    "sg:phone":"+32 15 43 60 67",
    "sg:postcode":"2800",
    "sg:province":"Antwerpen",
    "wof:name":"G. Belis",
    "wof:placetype":"venue"
},
  "geometry": {"coordinates":[4.4774608612,51.0187950134],"type":"Point"}
}