{
  "type": "Feature",
  "properties": {
    "addr:full":"Antwerpseweg 10 Geel Antwerpen 2440",
    "addr:housenumber":"10",
    "addr:postcode":"2440",
    "addr:street":"Antwerpseweg",
    "iso:country":"BE",
    "sg:address":"Antwerpseweg 10",
    "sg:city":"Geel",
    "sg:orig_category":"Belastingconsulenten Diverse juridische dienstverlening",
    "sg:phone":"+32 14 56 29 80",
    "sg:postcode":"2440",
    "sg:province":"Antwerpen",
    "wof:name":"S.b.b.",
    "wof:placetype":"venue"
},
  "geometry": {"coordinates":[4.9728550911,51.1517448425],"type":"Point"}
}