{
  "type": "Feature",
  "properties": {
    "addr:full":"Antwerpsesteenweg 191 Mechelen Antwerpen 2800",
    "addr:housenumber":"191",
    "addr:postcode":"2800",
    "addr:street":"Antwerpsesteenweg",
    "iso:country":"BE",
    "sg:address":"Antwerpsesteenweg 191",
    "sg:city":"Mechelen",
    "sg:orig_category":"Autoverhuur Verhuisdiensten Verhuur voertuigen behalve auto's",
    "sg:phone":"+32 15 20 23 23",
    "sg:postcode":"2800",
    "sg:province":"Antwerpen",
    "wof:name":"Dockx",
    "wof:placetype":"venue"
},
  "geometry": {"coordinates":[4.4662661552,51.0499420166],"type":"Point"}
}