{
  "type": "Feature",
  "properties": {
    "iso:country":"BE",
    "sg:address":"Av Reine Elisabeth 29",
    "sg:city":"Waterloo",
    "sg:orig_category":"Gespecialiseerde residenti\u00eble bouw Loodgieterij, verwarming and sanitaire installaties",
    "sg:phone":"+32 2 354 84 36",
    "sg:postcode":"1410",
    "sg:province":"Brabant Wallon",
    "wof:name":"Siphons Lions",
    "wof:placetype":"venue"
},
  "geometry": {"coordinates":[4.4097371101,50.7057151794],"type":"Point"}
}