{
  "type": "Feature",
  "properties": {
    "addr:full":"Rue Du Couvent 50 Transinne Luxembourg 6890",
    "addr:housenumber":"50",
    "addr:postcode":"6890",
    "addr:street":"Rue Du Couvent",
    "iso:country":"BE",
    "sg:address":"Rue Du Couvent 50",
    "sg:city":"Transinne",
    "sg:orig_category":"H\u00f4tels",
    "sg:phone":"+32 61 65 58 74",
    "sg:postcode":"6890",
    "sg:province":"Luxembourg",
    "wof:name":"Hostellerie Du Wezerin",
    "wof:placetype":"venue"
},
  "geometry": {"coordinates":[5.1936898232,49.9972686768],"type":"Point"}
}