{
  "type": "Feature",
  "properties": {
    "iso:country":"BE",
    "sg:address":"Langestraat 137a",
    "sg:city":"Nieuwpoort",
    "sg:classifiers":[
        {
            "category":"Real Estate",
            "subcategory":"Architect",
            "type":"Services"
        }
    ],
    "sg:phone":"+32 58 23 69 76",
    "sg:postcode":"8620",
    "sg:province":"West-Vlaanderen",
    "wof:name":"Boncquet J",
    "wof:placetype":"venue"
},
  "geometry": {"coordinates":[2.7489280701,51.1324081421],"type":"Point"}
}