{
  "type": "Feature",
  "properties": {
    "addr:full":"Jan Rosierlaan 40 Lanaken Limburg 3620",
    "addr:housenumber":"40",
    "addr:postcode":"3620",
    "addr:street":"Jan Rosierlaan",
    "iso:country":"BE",
    "sg:address":"Jan Rosierlaan 40",
    "sg:city":"Lanaken",
    "sg:classifiers":[
        {
            "category":"Fast Food",
            "type":"Food & Drink"
        }
    ],
    "sg:phone":"+32 89 71 20 27",
    "sg:postcode":"3620",
    "sg:province":"Limburg",
    "sg:tags":[
        "meeneem",
        "restaurant"
    ],
    "wof:name":"Place Lambert",
    "wof:placetype":"venue"
},
  "geometry": {"coordinates":[5.6552600861,50.8885116577],"type":"Point"}
}