{
  "type": "Feature",
  "properties": {
    "iso:country":"BE",
    "sg:address":"Falconplein 3",
    "sg:city":"Antwerpen",
    "sg:orig_category":"Krantenwinkels Rookartikelen",
    "sg:phone":"+32 3 226 08 55",
    "sg:postcode":"2000",
    "sg:province":"Antwerpen",
    "wof:name":"Dagbladhandel C.a.p.",
    "wof:placetype":"venue"
},
  "geometry": {"coordinates":[4.4053378105,51.2266921997],"type":"Point"}
}