{
  "type": "Feature",
  "properties": {
    "addr:full":"Rue Modeste Cornille 41 Charleroi Hainaut 6041",
    "addr:housenumber":"41",
    "addr:postcode":"6041",
    "addr:street":"Rue Modeste Cornille;Hainaut",
    "iso:country":"BE",
    "sg:address":"Rue Modeste Cornille 41",
    "sg:city":"Charleroi",
    "sg:orig_category":"Dameskledingzaken",
    "sg:phone":"+32 71 35 40 51",
    "sg:postcode":"6041",
    "sg:province":"Hainaut",
    "wof:name":"Meli-melo",
    "wof:placetype":"venue"
},
  "geometry": {"coordinates":[4.4314317703,50.4685935974],"type":"Point"}
}