{
  "type": "Feature",
  "properties": {
    "iso:country":"BE",
    "sg:address":"Jan Jacobsplein 5",
    "sg:city":"Brussel/bruxelles",
    "sg:orig_category":"Advocaten and juridische adviseurs",
    "sg:phone":"+32 2 514 54 00",
    "sg:postcode":"1000",
    "sg:province":"Bruxelles-Capitale",
    "wof:name":"W. Platteeuw",
    "wof:placetype":"venue"
},
  "geometry": {"coordinates":[4.3514809608,50.8351211548],"type":"Point"}
}