{
  "type": "Feature",
  "properties": {
    "iso:country":"BE",
    "sg:address":"Grotstraat 10a",
    "sg:city":"Keerbergen",
    "sg:orig_category":"Diverse bedrijfsbeheeradviesbureaus",
    "sg:phone":"+32 16 53 79 53",
    "sg:postcode":"3140",
    "sg:province":"Vlaams-Brabant",
    "wof:name":"E.m. Consult",
    "wof:placetype":"venue"
},
  "geometry": {"coordinates":[4.6743059158,50.9969100952],"type":"Point"}
}