{
  "type": "Feature",
  "properties": {
    "iso:country":"BE",
    "sg:address":"Ridder Portmansstraat 2",
    "sg:city":"Hasselt",
    "sg:classifiers":[
        {
            "category":"Bars & Pubs",
            "type":"Food & Drink"
        }
    ],
    "sg:phone":"+32 11 22 55 46",
    "sg:postcode":"3500",
    "sg:province":"Limburg",
    "wof:name":"Brouwerij (de)",
    "wof:placetype":"venue"
},
  "geometry": {"coordinates":[5.3335738182,50.9293289185],"type":"Point"}
}