{
  "type": "Feature",
  "properties": {
    "addr:full":"Dennenboslaan 62 Sint-lambrechts-woluwe/woluwe-saint-lambert Bruxelles-Capitale 1200",
    "addr:housenumber":"62",
    "addr:postcode":"1200",
    "addr:street":"Dennenboslaan",
    "iso:country":"BE",
    "sg:address":"Dennenboslaan 62",
    "sg:city":"Sint-lambrechts-woluwe/woluwe-saint-lambert",
    "sg:orig_category":"Architecten Immobili\u00ebnkantoren",
    "sg:phone":"+32 2 770 41 51",
    "sg:postcode":"1200",
    "sg:province":"Bruxelles-Capitale",
    "wof:name":"Bureau Delta",
    "wof:placetype":"venue"
},
  "geometry": {"coordinates":[4.4431438446,50.8448753357],"type":"Point"}
}