{
  "type": "Feature",
  "properties": {
    "iso:country":"BE",
    "sg:address":"Scheldestraat 36",
    "sg:city":"Zwevegem (otegem)",
    "sg:classifiers":[
        {
            "category":"Manufacturing",
            "subcategory":"Textiles",
            "type":"Manufacturing & Wholesale Goods"
        }
    ],
    "sg:phone":"+32 56 65 03 30",
    "sg:postcode":"8553",
    "sg:province":"West-Vlaanderen",
    "sg:tags":[
        "spinning",
        "weaving",
        "mill"
    ],
    "wof:name":"Enya Bvba",
    "wof:placetype":"venue"
},
  "geometry": {"coordinates":[3.4283869267,50.8021354675],"type":"Point"}
}