{
  "type": "Feature",
  "properties": {
    "addr:full":"Rue Du Moulin D'havr\u00e9 29 Mons (havr\u00e9) Hainaut 7021",
    "addr:housenumber":"29",
    "addr:postcode":"7021",
    "addr:street":"Rue Du Moulin D'Havre \u0301",
    "iso:country":"BE",
    "sg:address":"Rue Du Moulin D'havr\u00e9 29",
    "sg:city":"Mons (havr\u00e9)",
    "sg:classifiers":[
        {
            "category":"Home & Garden",
            "subcategory":"Household Appliances",
            "type":"Retail Goods"
        }
    ],
    "sg:phone":"+32 65 87 50 35",
    "sg:postcode":"7021",
    "sg:province":"Hainaut",
    "sg:tags":[
        "repair",
        "mainten",
        "-",
        "electric"
    ],
    "wof:name":"Moresco",
    "wof:placetype":"venue"
},
  "geometry": {"coordinates":[4.0448040962,50.4641685486],"type":"Point"}
}