{
  "type": "Feature",
  "properties": {
    "addr:full":"Dorpsstraat 50 Hamont-achel Limburg 3930",
    "addr:housenumber":"50",
    "addr:postcode":"3930",
    "addr:street":"Dorpsstraat",
    "iso:country":"BE",
    "sg:address":"Dorpsstraat 50",
    "sg:city":"Hamont-achel",
    "sg:orig_category":"R\u00e9parations de chaussures and articles en cuir",
    "sg:phone":"+32 11 64 32 24",
    "sg:postcode":"3930",
    "sg:province":"Limburg",
    "wof:name":"Leonardus Mennen",
    "wof:placetype":"venue"
},
  "geometry": {"coordinates":[5.4793639183,51.2523269653],"type":"Point"}
}