{
  "type": "Feature",
  "properties": {
    "iso:country":"BE",
    "sg:address":"Ardooisesteenweg 209",
    "sg:city":"Roeselare",
    "sg:classifiers":[
        {
            "category":"Parking",
            "subcategory":"Lot",
            "type":"Transportation"
        }
    ],
    "sg:phone":"+32 51 20 67 03",
    "sg:postcode":"8800",
    "sg:province":"West-Vlaanderen",
    "sg:tags":[
        "pneumatic",
        "automation"
    ],
    "wof:name":"Pneuvano West Cv",
    "wof:placetype":"venue"
},
  "geometry": {"coordinates":[3.1403989792,50.9519081116],"type":"Point"}
}