{
  "type": "Feature",
  "properties": {
    "addr:full":"Kerkenbosstraat 44 Tremelo Vlaams-Brabant 3128",
    "addr:housenumber":"44",
    "addr:postcode":"3128",
    "addr:street":"Kerkenbosstraat",
    "iso:country":"BE",
    "sg:address":"Kerkenbosstraat 44",
    "sg:city":"Tremelo",
    "sg:orig_category":"Diverse bouwafwerking and reiniging Gespecialiseerde residenti\u00eble bouw Woningbouw",
    "sg:phone":"+32 16 53 08 42",
    "sg:postcode":"3128",
    "sg:province":"Vlaams-Brabant",
    "wof:name":"Renobouw",
    "wof:placetype":"venue"
},
  "geometry": {"coordinates":[4.7541508675,50.9949302673],"type":"Point"}
}