{
  "type": "Feature",
  "properties": {
    "addr:full":"Rue Du Vicinal 5 Libramont Luxembourg 6800",
    "addr:housenumber":"5",
    "addr:postcode":"6800",
    "addr:street":"Rue Du Vicinal",
    "iso:country":"BE",
    "sg:address":"Rue Du Vicinal 5",
    "sg:city":"Libramont",
    "sg:classifiers":[
        {
            "category":"Professional",
            "subcategory":"Computer Services",
            "type":"Services"
        }
    ],
    "sg:phone":"+32 61 22 90 69",
    "sg:postcode":"6800",
    "sg:province":"Luxembourg",
    "sg:tags":[
        "-",
        "processing",
        "data"
    ],
    "wof:name":"Abs Computer",
    "wof:placetype":"venue"
},
  "geometry": {"coordinates":[5.3785438538,49.9210205078],"type":"Point"}
}