{
  "type": "Feature",
  "properties": {
    "addr:full":"Liersesteenweg 8 Lint Antwerpen 2547",
    "addr:housenumber":"8",
    "addr:postcode":"2547",
    "addr:street":"Liersesteenweg",
    "iso:country":"BE",
    "sg:address":"Liersesteenweg 8",
    "sg:city":"Lint",
    "sg:classifiers":[
        {
            "category":"Personal",
            "subcategory":"Shoe Repair & Shine",
            "type":"Services"
        }
    ],
    "sg:phone":"+32 3 455 88 91",
    "sg:postcode":"2547",
    "sg:province":"Antwerpen",
    "sg:tags":[
        "shoemaker"
    ],
    "wof:name":"Ambacht ('t)",
    "wof:placetype":"venue"
},
  "geometry": {"coordinates":[4.4972558022,51.1271743774],"type":"Point"}
}