{
  "type": "Feature",
  "properties": {
    "addr:full":"Chauss\u00c9e Brunehault 450 Morlanwelz Hainaut 7140",
    "addr:housenumber":"450",
    "addr:postcode":"7140",
    "addr:street":"Chausse\u0301E Brunehault",
    "iso:country":"BE",
    "sg:address":"Chauss\u00c9e Brunehault 450",
    "sg:city":"Morlanwelz",
    "sg:orig_category":"Avocats and conseillers juridiques",
    "sg:phone":"+32 64 45 89 27",
    "sg:postcode":"7140",
    "sg:province":"Hainaut",
    "wof:name":"Marie-france Dupont",
    "wof:placetype":"venue"
},
  "geometry": {"coordinates":[4.2426509857,50.4499816895],"type":"Point"}
}