{
  "type": "Feature",
  "properties": {
    "addr:full":"Sint-michielslaan 35 Etterbeek/etterbeek Bruxelles-Capitale 1040",
    "addr:housenumber":"35",
    "addr:postcode":"1040",
    "addr:street":"Sint-Michielslaan",
    "iso:country":"BE",
    "sg:address":"Sint-michielslaan 35",
    "sg:city":"Etterbeek/etterbeek",
    "sg:orig_category":"Zalen voor culturele evenementen",
    "sg:phone":"+32 2 735 52 12",
    "sg:postcode":"1040",
    "sg:province":"Bruxelles-Capitale",
    "wof:name":"Galerie Artiscope",
    "wof:placetype":"venue"
},
  "geometry": {"coordinates":[4.4060330391,50.8353118896],"type":"Point"}
}