{
  "type": "Feature",
  "properties": {
    "addr:full":"Borreberg 8 Anzegem West-Vlaanderen 8570",
    "addr:housenumber":"8",
    "addr:postcode":"8570",
    "addr:street":"Borreberg",
    "iso:country":"BE",
    "sg:address":"Borreberg 8",
    "sg:city":"Anzegem",
    "sg:orig_category":"Elektrische installaties voor woningen",
    "sg:phone":"+32 56 68 04 56",
    "sg:postcode":"8570",
    "sg:province":"West-Vlaanderen",
    "wof:name":"Georges Verleyen",
    "wof:placetype":"venue"
},
  "geometry": {"coordinates":[3.4796988964,50.8335609436],"type":"Point"}
}