{
  "type": "Feature",
  "properties": {
    "iso:country":"BE",
    "sg:address":"Rue Emile Marcq 11bb",
    "sg:city":"Genappe",
    "sg:orig_category":"Voertuigen",
    "sg:phone":"+32 67 79 01 83",
    "sg:postcode":"1474",
    "sg:province":"Brabant Wallon",
    "wof:name":"R. Lemaire",
    "wof:placetype":"venue"
},
  "geometry": {"coordinates":[4.4630827904,50.6126594543],"type":"Point"}
}