{
  "type": "Feature",
  "properties": {
    "addr:full":"Rue Du Ch\u00eane 4 Beyne-heusay Li\u00e8ge 4610",
    "addr:housenumber":"4",
    "addr:postcode":"4610",
    "addr:street":"Rue Du Che\u0302Ne",
    "iso:country":"BE",
    "sg:address":"Rue Du Ch\u00eane 4",
    "sg:city":"Beyne-heusay",
    "sg:classifiers":[
        {
            "category":"Travel",
            "subcategory":"Hotels & Motels",
            "type":"Entertainment"
        }
    ],
    "sg:phone":"+32 4 358 32 86",
    "sg:postcode":"4610",
    "sg:province":"Li\u00e8ge",
    "sg:tags":[
        "supply",
        "hotels",
        "catering"
    ],
    "wof:name":"Eurofoodmat Sa",
    "wof:placetype":"venue"
},
  "geometry": {"coordinates":[5.6664361954,50.625793457],"type":"Point"}
}