{
  "type": "Feature",
  "properties": {
    "iso:country":"BE",
    "sg:address":"Chemin Du Stoquoi 28",
    "sg:city":"Ath",
    "sg:orig_category":"Grands magasins",
    "sg:phone":"+32 68 55 23 94",
    "sg:postcode":"7822",
    "sg:province":"Hainaut",
    "wof:name":"Les V\u00c9ritables",
    "wof:placetype":"venue"
},
  "geometry": {"coordinates":[3.8452620506,50.6482391357],"type":"Point"}
}