{
  "type": "Feature",
  "properties": {
    "iso:country":"BE",
    "sg:address":"R.ferme Du Petit Royal 1",
    "sg:city":"Grez-doiceau",
    "sg:orig_category":"Rundveehouders Varkenskwekers",
    "sg:phone":"+32 10 84 42 13",
    "sg:postcode":"1390",
    "sg:province":"Brabant Wallon",
    "wof:name":"Eddy Gillis",
    "wof:placetype":"venue"
},
  "geometry": {"coordinates":[4.7018799782,50.7714958191],"type":"Point"}
}