{
  "type": "Feature",
  "properties": {
    "iso:country":"BE",
    "sg:address":"Berkenbos 18",
    "sg:city":"Balen",
    "sg:orig_category":"Brood, gebak and snoepgoed",
    "sg:phone":"+32 14 81 24 73",
    "sg:postcode":"2490",
    "sg:province":"Antwerpen",
    "wof:name":"Frans Vermeulen",
    "wof:placetype":"venue"
},
  "geometry": {"coordinates":[5.1762142181,51.1985816956],"type":"Point"}
}