{
  "type": "Feature",
  "properties": {
    "iso:country":"BE",
    "sg:address":"Ninoofsesteenweg 75",
    "sg:city":"Dilbeek",
    "sg:orig_category":"Textiel Verlichting and huishoudartikelen",
    "sg:phone":"+32 2 569 33 04",
    "sg:postcode":"1700",
    "sg:province":"Vlaams-Brabant",
    "wof:name":"D.s.a.",
    "wof:placetype":"venue"
},
  "geometry": {"coordinates":[4.2772469521,50.8452224731],"type":"Point"}
}