{
  "type": "Feature",
  "properties": {
    "iso:country":"BE",
    "sg:address":"Merksplassesteenweg 111",
    "sg:city":"Rijkevorsel",
    "sg:classifiers":[
        {
            "category":"Professional",
            "subcategory":"Management & Consulting",
            "type":"Services"
        }
    ],
    "sg:phone":"+32 3 314 15 07",
    "sg:postcode":"2310",
    "sg:province":"Antwerpen",
    "sg:tags":[
        "consultant"
    ],
    "wof:name":"Aladin Nv",
    "wof:placetype":"venue"
},
  "geometry": {"coordinates":[4.8068208694,51.3485374451],"type":"Point"}
}