{
  "type": "Feature",
  "properties": {
    "iso:country":"BE",
    "sg:address":"Legekouter 1",
    "sg:city":"Nevele",
    "sg:classifiers":[
        {
            "category":"Retail",
            "subcategory":"Veterinary Services",
            "type":"Services"
        }
    ],
    "sg:phone":"+32 9 371 81 95",
    "sg:postcode":"9850",
    "sg:province":"Oost-Vlaanderen",
    "sg:tags":[
        "veterinarian"
    ],
    "wof:name":"Sys P",
    "wof:placetype":"venue"
},
  "geometry": {"coordinates":[3.5517990589,51.046661377],"type":"Point"}
}