{
  "type": "Feature",
  "properties": {
    "iso:country":"BE",
    "sg:address":"Moorselestraat 58",
    "sg:city":"Menen",
    "sg:orig_category":"Artsen and specialisten",
    "sg:phone":"+32 56 53 15 07",
    "sg:postcode":"8930",
    "sg:province":"West-Vlaanderen",
    "wof:name":"Y. Devlies",
    "wof:placetype":"venue"
},
  "geometry": {"coordinates":[3.1261210442,50.8050193787],"type":"Point"}
}