{
  "type": "Feature",
  "properties": {
    "addr:full":"Molenstraat 31 Schilde Antwerpen 2970",
    "addr:housenumber":"31",
    "addr:postcode":"2970",
    "addr:street":"Molenstraat",
    "iso:country":"BE",
    "sg:address":"Molenstraat 31",
    "sg:city":"Schilde",
    "sg:classifiers":[
        {
            "category":"Insurance",
            "subcategory":"Life Insurance",
            "type":"Services"
        }
    ],
    "sg:phone":"+32 3 383 10 72",
    "sg:postcode":"2970",
    "sg:province":"Antwerpen",
    "sg:tags":[
        "assurance"
    ],
    "wof:name":"V. Lenssens",
    "wof:placetype":"venue"
},
  "geometry": {"coordinates":[4.5809168816,51.2425575256],"type":"Point"}
}