{
  "type": "Feature",
  "properties": {
    "iso:country":"BE",
    "sg:address":"Rue De La Fontaine 156",
    "sg:city":"Flemalle",
    "sg:orig_category":"Bloemen and planten",
    "sg:phone":"+32 4 233 47 01",
    "sg:postcode":"4400",
    "sg:province":"Li\u00e8ge",
    "wof:name":"Au Coin Fleuri",
    "wof:placetype":"venue"
},
  "geometry": {"coordinates":[5.4761681557,50.6113510132],"type":"Point"}
}