{
  "type": "Feature",
  "properties": {
    "iso:country":"BE",
    "sg:address":"Rue Du Vieux Saule 66",
    "sg:city":"Farciennes",
    "sg:classifiers":[
        {
            "category":"Arena",
            "subcategory":"Sports Club",
            "type":"Entertainment"
        }
    ],
    "sg:phone":"+32 71 39 19 68",
    "sg:postcode":"6240",
    "sg:province":"Hainaut",
    "sg:tags":[
        "de"
    ],
    "wof:name":"Soci\u00c9t\u00c9 Colombophile",
    "wof:placetype":"venue"
},
  "geometry": {"coordinates":[4.5268149376,50.4409141541],"type":"Point"}
}