{
  "type": "Feature",
  "properties": {
    "iso:country":"BE",
    "sg:address":"Geldmuntstraat 30",
    "sg:city":"Brugge",
    "sg:orig_category":"Agences de voyages",
    "sg:phone":"+32 50 33 30 08",
    "sg:postcode":"8000",
    "sg:province":"West-Vlaanderen",
    "wof:name":"Ticket Bbl Travel",
    "wof:placetype":"venue"
},
  "geometry": {"coordinates":[3.2214939594,51.2086372375],"type":"Point"}
}