{
  "type": "Feature",
  "properties": {
    "addr:full":"Leuvensesteenweg 51 Kampenhout Vlaams-Brabant 1910",
    "addr:housenumber":"51",
    "addr:postcode":"1910",
    "addr:street":"Leuvensesteenweg",
    "iso:country":"BE",
    "sg:address":"Leuvensesteenweg 51",
    "sg:city":"Kampenhout",
    "sg:classifiers":[
        {
            "category":"Professional",
            "subcategory":"Business Services",
            "type":"Services"
        }
    ],
    "sg:phone":"+32 16 65 00 21",
    "sg:postcode":"1910",
    "sg:province":"Vlaams-Brabant",
    "sg:tags":[
        "information",
        "advice",
        "technology",
        "software"
    ],
    "wof:name":"Automation Systems Int Nv",
    "wof:placetype":"venue"
},
  "geometry": {"coordinates":[4.5961427689,50.9537658691],"type":"Point"}
}