{
  "type": "Feature",
  "properties": {
    "addr:full":"Blommestraat 83 Roeselare West-Vlaanderen 8800",
    "addr:housenumber":"83",
    "addr:postcode":"8800",
    "addr:street":"Blommestraat",
    "iso:country":"BE",
    "sg:address":"Blommestraat 83",
    "sg:city":"Roeselare",
    "sg:orig_category":"Postkantoren Verzekeringsmakelaars and experts",
    "sg:phone":"+32 51 20 21 44",
    "sg:postcode":"8800",
    "sg:province":"West-Vlaanderen",
    "wof:name":"De Post",
    "wof:placetype":"venue"
},
  "geometry": {"coordinates":[3.1408700943,50.9313774109],"type":"Point"}
}