{
  "type": "Feature",
  "properties": {
    "iso:country":"BE",
    "sg:address":"Veldstraat 92",
    "sg:city":"Stabroek",
    "sg:orig_category":"Loodgieterij, verwarming and sanitaire installaties",
    "sg:phone":"+32 3 664 57 07",
    "sg:postcode":"2940",
    "sg:province":"Antwerpen",
    "wof:name":"M J S",
    "wof:placetype":"venue"
},
  "geometry": {"coordinates":[4.3947410583,51.351348877],"type":"Point"}
}