{
  "type": "Feature",
  "properties": {
    "iso:country":"BE",
    "sg:address":"Rue De Bouillon 259",
    "sg:city":"Beauraing (pondr\u00f4me)",
    "sg:classifiers":[
        {
            "category":"Wholesale",
            "subcategory":"Furniture",
            "type":"Manufacturing & Wholesale Goods"
        }
    ],
    "sg:phone":"+32 82 21 94 32",
    "sg:postcode":"5574",
    "sg:province":"Namur",
    "sg:tags":[
        "-",
        "collectivities"
    ],
    "wof:name":"Beauraing Literie-achats Group\u00e9s Sprl",
    "wof:placetype":"venue"
},
  "geometry": {"coordinates":[4.9903378487,50.1011428833],"type":"Point"}
}