{
  "type": "Feature",
  "properties": {
    "addr:full":"Eikenlaan 30 Nijlen (kessel) Antwerpen 2560",
    "addr:housenumber":"30",
    "addr:postcode":"2560",
    "addr:street":"Eikenlaan",
    "iso:country":"BE",
    "sg:address":"Eikenlaan 30",
    "sg:city":"Nijlen (kessel)",
    "sg:classifiers":[
        {
            "category":"Health Services",
            "subcategory":"Health Practitioner",
            "type":"Services"
        }
    ],
    "sg:phone":"+32 3 489 32 04",
    "sg:postcode":"2560",
    "sg:province":"Antwerpen",
    "sg:tags":[
        "physiotherapist"
    ],
    "wof:name":"Somers Monique",
    "wof:placetype":"venue"
},
  "geometry": {"coordinates":[4.6028008461,51.1476783752],"type":"Point"}
}