{
  "type": "Feature",
  "properties": {
    "addr:full":"Avenue Du Centenaire 235a Charleroi (montignies-sur-sambre) Hainaut 6061",
    "addr:housenumber":"235a",
    "addr:postcode":"6061",
    "addr:street":"Avenue Du Centenaire",
    "iso:country":"BE",
    "sg:address":"Avenue Du Centenaire 235a",
    "sg:city":"Charleroi (montignies-sur-sambre)",
    "sg:classifiers":[
        {
            "category":"Retail",
            "subcategory":"Auto Repair",
            "type":"Services"
        }
    ],
    "sg:phone":"+32 71 70 02 30",
    "sg:postcode":"6061",
    "sg:province":"Hainaut",
    "sg:tags":[
        "automobile-body"
    ],
    "wof:name":"Tony Del & Fils",
    "wof:placetype":"venue"
},
  "geometry": {"coordinates":[4.4778218269,50.4104766846],"type":"Point"}
}