{
  "type": "Feature",
  "properties": {
    "addr:full":"Rue De Jemeppe 30 Ans (loncin) Li\u00e8ge 4431",
    "addr:housenumber":"30",
    "addr:postcode":"4431",
    "addr:street":"Rue De Jemeppe",
    "iso:country":"BE",
    "sg:address":"Rue De Jemeppe 30",
    "sg:city":"Ans (loncin)",
    "sg:classifiers":[
        {
            "category":"Building & Trades",
            "subcategory":"Construction",
            "type":"Services"
        }
    ],
    "sg:phone":"+32 4 263 55 34",
    "sg:postcode":"4431",
    "sg:province":"Li\u00e8ge",
    "sg:tags":[
        "stone",
        "cutter"
    ],
    "wof:name":"Gielen A",
    "wof:placetype":"venue"
},
  "geometry": {"coordinates":[5.5032320023,50.6653251648],"type":"Point"}
}