{
  "type": "Feature",
  "properties": {
    "addr:full":"Chauss\u00c9e De Charleroi 83 Namur Namur 5000",
    "addr:housenumber":"83",
    "addr:postcode":"5000",
    "addr:street":"Chausse\u0301E De Charleroi",
    "iso:country":"BE",
    "sg:address":"Chauss\u00c9e De Charleroi 83",
    "sg:city":"Namur",
    "sg:orig_category":"Boekhouders",
    "sg:phone":"+32 81 72 18 99",
    "sg:postcode":"5000",
    "sg:province":"Namur",
    "wof:name":"D. Delache",
    "wof:placetype":"venue"
},
  "geometry": {"coordinates":[4.8409872055,50.4619750977],"type":"Point"}
}