{
  "type": "Feature",
  "properties": {
    "iso:country":"BE",
    "sg:address":"Place De Linde 27",
    "sg:city":"Anderlecht",
    "sg:orig_category":"Kantoormateriaal Gh",
    "sg:phone":"+32 2 376 46 08",
    "sg:postcode":"1070",
    "sg:province":"Bruxelles-Capitale",
    "wof:name":"Data Perfect",
    "wof:placetype":"venue"
},
  "geometry": {"coordinates":[4.2991909981,50.8354301453],"type":"Point"}
}