{
  "type": "Feature",
  "properties": {
    "iso:country":"BE",
    "sg:address":"L\u00dctticherstrasse 52",
    "sg:city":"Lontzen/lontzen",
    "sg:orig_category":"Decoratiestoffen and buitenhuistextiel Fab",
    "sg:phone":"+32 87 88 33 66",
    "sg:postcode":"4710",
    "sg:province":"Li\u00e8ge",
    "wof:name":"Schreiber",
    "wof:placetype":"venue"
},
  "geometry": {"coordinates":[5.9602432251,50.6892852783],"type":"Point"}
}