{
  "type": "Feature",
  "properties": {
    "addr:full":". Meerhout Antwerpen 2450",
    "addr:postcode":"2450",
    "iso:country":"BE",
    "sg:address":".",
    "sg:city":"Meerhout",
    "sg:orig_category":"Apotheken",
    "sg:phone":"+32 900 10 500",
    "sg:postcode":"2450",
    "sg:province":"Antwerpen",
    "wof:name":"Apothekers Van Wacht",
    "wof:placetype":"venue"
},
  "geometry": {"coordinates":[5.0779151917,51.1319160461],"type":"Point"}
}