{
  "type": "Feature",
  "properties": {
    "addr:full":"Jan Van Rijswijcklaan 115 Antwerpen Antwerpen 2018",
    "addr:housenumber":"115",
    "addr:postcode":"2018",
    "addr:street":"Jan Van Rijswijcklaan",
    "iso:country":"BE",
    "sg:address":"Jan Van Rijswijcklaan 115",
    "sg:city":"Antwerpen",
    "sg:orig_category":"Antiek",
    "sg:phone":"+32 3 248 66 44",
    "sg:postcode":"2018",
    "sg:province":"Antwerpen",
    "wof:name":"De Zilverdistel",
    "wof:placetype":"venue"
},
  "geometry": {"coordinates":[4.4046378136,51.1955299377],"type":"Point"}
}