{
  "type": "Feature",
  "properties": {
    "addr:full":"Zeekanaalweg 3 Brugge West-Vlaanderen 8380",
    "addr:housenumber":"3",
    "addr:postcode":"8380",
    "addr:street":"Zeekanaalweg",
    "iso:country":"BE",
    "sg:address":"Zeekanaalweg 3",
    "sg:city":"Brugge",
    "sg:orig_category":"Eleveurs de bovins",
    "sg:phone":"+32 50 59 91 06",
    "sg:postcode":"8380",
    "sg:province":"West-Vlaanderen",
    "wof:name":"Eric Desutter",
    "wof:placetype":"venue"
},
  "geometry": {"coordinates":[3.2288448811,51.2742958069],"type":"Point"}
}