{
  "type": "Feature",
  "properties": {
    "addr:full":"Stationsstraat 9 Kortrijk West-Vlaanderen 8500",
    "addr:housenumber":"9",
    "addr:postcode":"8500",
    "addr:street":"Stationsstraat",
    "iso:country":"BE",
    "sg:address":"Stationsstraat 9",
    "sg:city":"Kortrijk",
    "sg:classifiers":[
        {
            "category":"Bars & Pubs",
            "type":"Food & Drink"
        }
    ],
    "sg:phone":"+32 475 62 17 45",
    "sg:postcode":"8500",
    "sg:province":"West-Vlaanderen",
    "wof:name":"Bodeguita Del Medio (la)",
    "wof:placetype":"venue"
},
  "geometry": {"coordinates":[3.2645039558,50.8256835938],"type":"Point"}
}