{
  "type": "Feature",
  "properties": {
    "addr:full":"Tweekerkenstraat 142 Sint-joost-ten-node/saint-josse-ten-noode Bruxelles-Capitale 1210",
    "addr:housenumber":"142",
    "addr:postcode":"1210",
    "addr:street":"Tweekerkenstraat;Sint-Joost-Ten-Node /",
    "iso:country":"BE",
    "sg:address":"Tweekerkenstraat 142",
    "sg:city":"Sint-joost-ten-node/saint-josse-ten-noode",
    "sg:classifiers":[
        {
            "category":"Restaurant",
            "type":"Food & Drink"
        }
    ],
    "sg:phone":"+32 2 230 91 52",
    "sg:postcode":"1210",
    "sg:province":"Bruxelles-Capitale",
    "wof:name":"Restaurant Jonque De Jade",
    "wof:placetype":"venue"
},
  "geometry": {"coordinates":[4.3740968704,50.8493690491],"type":"Point"}
}