{
  "type": "Feature",
  "properties": {
    "iso:country":"BE",
    "sg:address":"Rue L\u00c9on Dop\u00c9r\u00c9 78",
    "sg:city":"Jette/jette",
    "sg:orig_category":"Cr\u00e8ches and garderies d'enfants",
    "sg:phone":"+32 2 428 52 05",
    "sg:postcode":"1090",
    "sg:province":"Bruxelles-Capitale",
    "wof:name":"Cr\u00c8che B\u00c9b\u00c9 Nuage",
    "wof:placetype":"venue"
},
  "geometry": {"coordinates":[4.321764946,50.8750648499],"type":"Point"}
}