{
  "type": "Feature",
  "properties": {
    "addr:full":"Schepenijlaan 23 Ukkel/uccle Bruxelles-Capitale 1180",
    "addr:housenumber":"23",
    "addr:postcode":"1180",
    "addr:street":"Schepenijlaan;/",
    "iso:country":"BE",
    "sg:address":"Schepenijlaan 23",
    "sg:city":"Ukkel/uccle",
    "sg:orig_category":"Advocaten and juridische adviseurs",
    "sg:phone":"+32 2 374 19 43",
    "sg:postcode":"1180",
    "sg:province":"Bruxelles-Capitale",
    "wof:name":"J. Depoorter",
    "wof:placetype":"venue"
},
  "geometry": {"coordinates":[4.3440499306,50.8038864136],"type":"Point"}
}