{
  "type": "Feature",
  "properties": {
    "iso:country":"BE",
    "sg:address":"Route De Mons-maubeuge 6ba",
    "sg:city":"Quevy",
    "sg:orig_category":"Benzinestations and brandstoffen",
    "sg:phone":"+32 65 56 87 11",
    "sg:postcode":"7041",
    "sg:province":"Hainaut",
    "wof:name":"Ziomek",
    "wof:placetype":"venue"
},
  "geometry": {"coordinates":[3.9699149132,50.3460540771],"type":"Point"}
}