{
  "type": "Feature",
  "properties": {
    "iso:country":"BE",
    "sg:address":"Rue De La Tonne 2ba",
    "sg:city":"Ans",
    "sg:orig_category":"Verplichte sociale verzekeringen",
    "sg:phone":"+32 4 247 39 78",
    "sg:postcode":"4430",
    "sg:province":"Li\u00e8ge",
    "wof:name":"Mutualit\u00c9 Neutre",
    "wof:placetype":"venue"
},
  "geometry": {"coordinates":[5.539689064,50.6590805054],"type":"Point"}
}