{
  "type": "Feature",
  "properties": {
    "iso:country":"BE",
    "sg:address":"Kontichsesteenweg 12a",
    "sg:city":"Aartselaar",
    "sg:classifiers":[
        {
            "category":"Shopping",
            "subcategory":"Pets & Pet Supplies",
            "type":"Retail Goods"
        }
    ],
    "sg:phone":"+32 3 870 71 81",
    "sg:postcode":"2630",
    "sg:province":"Antwerpen",
    "sg:tags":[
        "aquarium",
        "accessory"
    ],
    "wof:name":"Aquaria Antwerp",
    "wof:placetype":"venue"
},
  "geometry": {"coordinates":[4.3829622269,51.1426467896],"type":"Point"}
}