{
  "type": "Feature",
  "properties": {
    "addr:full":"Rue De Clervaux 243 Bastogne Luxembourg 6600",
    "addr:housenumber":"243",
    "addr:postcode":"6600",
    "addr:street":"Rue De Clervaux",
    "iso:country":"BE",
    "sg:address":"Rue De Clervaux 243",
    "sg:city":"Bastogne",
    "sg:classifiers":[
        {
            "category":"Building & Trades",
            "subcategory":"Landscaping Services",
            "type":"Services"
        }
    ],
    "sg:phone":"+32 61 21 36 49",
    "sg:postcode":"6600",
    "sg:province":"Luxembourg",
    "sg:tags":[
        "forestry"
    ],
    "wof:name":"Lambert C",
    "wof:placetype":"venue"
},
  "geometry": {"coordinates":[5.7148199081,50.0007820129],"type":"Point"}
}