{
  "type": "Feature",
  "properties": {
    "addr:full":"Bornstraat 7 Zonnebeke (passendale) West-Vlaanderen 8980",
    "addr:housenumber":"7",
    "addr:postcode":"8980",
    "addr:street":"Bornstraat",
    "iso:country":"BE",
    "sg:address":"Bornstraat 7",
    "sg:city":"Zonnebeke (passendale)",
    "sg:classifiers":[
        {
            "category":"Freight",
            "type":"Transportation"
        }
    ],
    "sg:phone":"+32 51 77 74 56",
    "sg:postcode":"8980",
    "sg:province":"West-Vlaanderen",
    "sg:tags":[
        "-",
        "transport"
    ],
    "wof:name":"Lesage M",
    "wof:placetype":"venue"
},
  "geometry": {"coordinates":[2.9938941002,50.9041633606],"type":"Point"}
}