{
  "type": "Feature",
  "properties": {
    "addr:full":"Meierstraat 40 Kinrooi Limburg 3640",
    "addr:housenumber":"40",
    "addr:postcode":"3640",
    "addr:street":"Meierstraat",
    "iso:country":"BE",
    "sg:address":"Meierstraat 40",
    "sg:city":"Kinrooi",
    "sg:orig_category":"Enseignement maternel and primaire",
    "sg:phone":"+32 89 56 59 54",
    "sg:postcode":"3640",
    "sg:province":"Limburg",
    "wof:name":"Vrije Basisschool",
    "wof:placetype":"venue"
},
  "geometry": {"coordinates":[5.8171811104,51.1501655579],"type":"Point"}
}