{
  "type": "Feature",
  "properties": {
    "addr:full":"Stationlei 52 Vilvoorde Vlaams-Brabant 1800",
    "addr:housenumber":"52",
    "addr:postcode":"1800",
    "addr:street":"Stationlei",
    "iso:country":"BE",
    "sg:address":"Stationlei 52",
    "sg:city":"Vilvoorde",
    "sg:orig_category":"Artsen and specialisten",
    "sg:phone":"+32 2 251 11 40",
    "sg:postcode":"1800",
    "sg:province":"Vlaams-Brabant",
    "wof:name":"Paul Sacr\u00c9",
    "wof:placetype":"venue"
},
  "geometry": {"coordinates":[4.4294228554,50.9253387451],"type":"Point"}
}