{
  "type": "Feature",
  "properties": {
    "iso:country":"BE",
    "sg:address":"De Merodelei 7",
    "sg:city":"Turnhout",
    "sg:classifiers":[
        {
            "category":"Shopping",
            "subcategory":"Clothing, Apparel, & Fashions",
            "type":"Retail Goods"
        }
    ],
    "sg:phone":"+32 14 41 24 58",
    "sg:postcode":"2300",
    "sg:province":"Antwerpen",
    "sg:tags":[
        "v\u00eatements",
        "pour",
        "dame"
    ],
    "wof:name":"Couture Merode",
    "wof:placetype":"venue"
},
  "geometry": {"coordinates":[4.9424958229,51.3222045898],"type":"Point"}
}