{
  "type": "Feature",
  "properties": {
    "iso:country":"BE",
    "sg:address":"Brandestraat 4",
    "sg:city":"Berlaar",
    "sg:orig_category":"Eleveurs de bovins",
    "sg:phone":"+32 3 482 28 90",
    "sg:postcode":"2590",
    "sg:province":"Antwerpen",
    "wof:name":"Julius De Herdt",
    "wof:placetype":"venue"
},
  "geometry": {"coordinates":[4.637567997,51.1009902954],"type":"Point"}
}