{
  "type": "Feature",
  "properties": {
    "addr:full":"Rue Gustave-delperdange 9 Bastogne Luxembourg 6600",
    "addr:housenumber":"9",
    "addr:postcode":"6600",
    "addr:street":"Rue Gustave-Delperdange",
    "iso:country":"BE",
    "sg:address":"Rue Gustave-delperdange 9",
    "sg:city":"Bastogne",
    "sg:orig_category":"Rundveehouders",
    "sg:phone":"+32 61 21 55 78",
    "sg:postcode":"6600",
    "sg:province":"Luxembourg",
    "wof:name":"Pierre Lifrange",
    "wof:placetype":"venue"
},
  "geometry": {"coordinates":[5.7447929382,50.0070762634],"type":"Point"}
}