{
  "type": "Feature",
  "properties": {
    "iso:country":"BE",
    "sg:address":"Dok-noord 4",
    "sg:city":"Gent",
    "sg:orig_category":"Biogas Plants",
    "sg:phone":"+32 9 233 02 04",
    "sg:postcode":"9000",
    "sg:province":"Oost-Vlaanderen",
    "wof:name":"Ows Nv",
    "wof:placetype":"venue"
},
  "geometry": {"coordinates":[3.7095119953,51.0569648743],"type":"Point"}
}