{
  "type": "Feature",
  "properties": {
    "addr:full":"Leuvensestraat 3 Oud-heverlee (sint-joris-weert) Vlaams-Brabant 3051",
    "addr:housenumber":"3",
    "addr:postcode":"3051",
    "addr:street":"Leuvensestraat",
    "iso:country":"BE",
    "sg:address":"Leuvensestraat 3",
    "sg:city":"Oud-heverlee (sint-joris-weert)",
    "sg:classifiers":[
        {
            "category":"Health Services",
            "subcategory":"Dentist",
            "type":"Services"
        }
    ],
    "sg:phone":"+32 16 47 11 01",
    "sg:postcode":"3051",
    "sg:province":"Vlaams-Brabant",
    "wof:name":"Van Den Bosch K",
    "wof:placetype":"venue"
},
  "geometry": {"coordinates":[4.652990818,50.8032836914],"type":"Point"}
}