{
  "type": "Feature",
  "properties": {
    "iso:country":"BE",
    "sg:address":"Route D'obourg 67ba",
    "sg:city":"Mons",
    "sg:orig_category":"V\u00e9t\u00e9rinaires",
    "sg:phone":"+32 65 35 19 66",
    "sg:postcode":"7000",
    "sg:province":"Hainaut",
    "wof:name":"Brigitte Duquesne",
    "wof:placetype":"venue"
},
  "geometry": {"coordinates":[3.9871749878,50.4587974548],"type":"Point"}
}