{
  "type": "Feature",
  "properties": {
    "addr:full":"Rue Du May 49 Buzet Hainaut 6230",
    "addr:housenumber":"49",
    "addr:postcode":"6230",
    "addr:street":"Rue Du May",
    "iso:country":"BE",
    "sg:address":"Rue Du May 49",
    "sg:city":"Buzet",
    "sg:orig_category":"Microsoft. Conseils en syst\u00e8mes informatiques",
    "sg:phone":"+32 71 84 79 38",
    "sg:postcode":"6230",
    "sg:province":"Hainaut",
    "wof:name":"Micro Style",
    "wof:placetype":"venue"
},
  "geometry": {"coordinates":[4.3601050377,50.5384483337],"type":"Point"}
}