{
  "type": "Feature",
  "properties": {
    "iso:country":"BE",
    "sg:address":"Dorpsplein 2",
    "sg:city":"Dilbeek (sint-martens-bodegem)",
    "sg:classifiers":[
        {
            "category":"Health Services",
            "subcategory":"Health Practitioner",
            "type":"Services"
        }
    ],
    "sg:phone":"+32 2 582 04 30",
    "sg:postcode":"1700",
    "sg:province":"Vlaams-Brabant",
    "sg:tags":[
        "physiotherapist"
    ],
    "wof:name":"Van Cauwenbergh P",
    "wof:placetype":"venue"
},
  "geometry": {"coordinates":[4.2130641937,50.8610725403],"type":"Point"}
}