{
  "type": "Feature",
  "properties": {
    "addr:full":"Avenue Adolphe Buyl 128 Elsene/ixelles Bruxelles-Capitale 1050",
    "addr:housenumber":"128",
    "addr:postcode":"1050",
    "addr:street":"Avenue Adolphe Buyl",
    "iso:country":"BE",
    "sg:address":"Avenue Adolphe Buyl 128",
    "sg:city":"Elsene/ixelles",
    "sg:orig_category":"Avocats and conseillers juridiques",
    "sg:phone":"+32 2 646 51 24",
    "sg:postcode":"1050",
    "sg:province":"Bruxelles-Capitale",
    "wof:name":"Et. Ilunga-kabeya",
    "wof:placetype":"venue"
},
  "geometry": {"coordinates":[4.3844389915,50.8142929077],"type":"Point"}
}