{
  "type": "Feature",
  "properties": {
    "addr:full":"Rue Aviateur Thieffry 35 Etterbeek Bruxelles-Capitale 1040",
    "addr:housenumber":"35",
    "addr:postcode":"1040",
    "addr:street":"Rue Aviateur Thieffry",
    "iso:country":"BE",
    "sg:address":"Rue Aviateur Thieffry 35",
    "sg:city":"Etterbeek",
    "sg:orig_category":"M\u00e9decins and sp\u00e9cialistes",
    "sg:phone":"+32 2 734 24 32",
    "sg:postcode":"1040",
    "sg:province":"Bruxelles-Capitale",
    "wof:name":"P. De Reuse",
    "wof:placetype":"venue"
},
  "geometry": {"coordinates":[4.401611805,50.8306236267],"type":"Point"}
}