{
  "type": "Feature",
  "properties": {
    "iso:country":"BE",
    "sg:address":"Square Marie-louise 40 Box 19",
    "sg:city":"Bruxelles",
    "sg:classifiers":[
        {
            "category":"Government",
            "subcategory":"Office",
            "type":"Public Place"
        }
    ],
    "sg:phone":"+32 2 230 79 63",
    "sg:postcode":"1000",
    "sg:province":"Bruxelles-Capitale",
    "sg:tags":[
        "patent",
        "agency",
        "trademark"
    ],
    "wof:name":"Office Hanssens Sprl",
    "wof:placetype":"venue"
},
  "geometry": {"coordinates":[4.3793301582,50.8477859497],"type":"Point"}
}