{
  "type": "Feature",
  "properties": {
    "addr:full":"Avenue Albert 124 Vorst/forest Bruxelles-Capitale 1190",
    "addr:housenumber":"124",
    "addr:postcode":"1190",
    "addr:street":"Avenue Albert;/ Forest",
    "iso:country":"BE",
    "sg:address":"Avenue Albert 124",
    "sg:city":"Vorst/forest",
    "sg:orig_category":"Agences de presse",
    "sg:phone":"+32 2 345 86 76",
    "sg:postcode":"1190",
    "sg:province":"Bruxelles-Capitale",
    "wof:name":"Christian Loiseau",
    "wof:placetype":"venue"
},
  "geometry": {"coordinates":[4.3461008072,50.8188591003],"type":"Point"}
}