{
  "type": "Feature",
  "properties": {
    "addr:full":"Wittenonnenstraat 34 Oostende West-Vlaanderen 8400",
    "addr:housenumber":"34",
    "addr:postcode":"8400",
    "addr:street":"Wittenonnenstraat",
    "iso:country":"BE",
    "sg:address":"Wittenonnenstraat 34",
    "sg:city":"Oostende",
    "sg:orig_category":"Kapsalons",
    "sg:phone":"+32 59 50 53 06",
    "sg:postcode":"8400",
    "sg:province":"West-Vlaanderen",
    "wof:name":"Hair Palace",
    "wof:placetype":"venue"
},
  "geometry": {"coordinates":[2.9170560837,51.2306137085],"type":"Point"}
}