{
  "type": "Feature",
  "properties": {
    "addr:full":"Armand Verheydenstraat 19 Oud-heverlee Vlaams-Brabant 3053",
    "addr:housenumber":"19",
    "addr:postcode":"3053",
    "addr:street":"Armand Verheydenstraat",
    "iso:country":"BE",
    "sg:address":"Armand Verheydenstraat 19",
    "sg:city":"Oud-heverlee",
    "sg:orig_category":"Enseignement maternel and primaire",
    "sg:phone":"+32 16 40 19 23",
    "sg:postcode":"3053",
    "sg:province":"Vlaams-Brabant",
    "wof:name":"Gemeentelijke Basisschool",
    "wof:placetype":"venue"
},
  "geometry": {"coordinates":[4.7312002182,50.8345184326],"type":"Point"}
}