{
  "type": "Feature",
  "properties": {
    "addr:full":"Frankrijklaan 11 Poperinge West-Vlaanderen 8970",
    "addr:housenumber":"11",
    "addr:postcode":"8970",
    "addr:street":"Frankrijklaan",
    "iso:country":"BE",
    "sg:address":"Frankrijklaan 11",
    "sg:city":"Poperinge",
    "sg:classifiers":[
        {
            "category":"Ferry",
            "type":"Transportation"
        }
    ],
    "sg:phone":"+32 57 33 38 94",
    "sg:postcode":"8970",
    "sg:province":"West-Vlaanderen",
    "sg:tags":[
        "whirlpool"
    ],
    "wof:name":"Leroy Bvba",
    "wof:placetype":"venue"
},
  "geometry": {"coordinates":[2.7429449558,50.8481712341],"type":"Point"}
}