{
  "type": "Feature",
  "properties": {
    "addr:full":"Rue Des Primeurs 61-63 Bruxelles (forest) Bruxelles-Capitale 1190",
    "addr:housenumber":"61-63",
    "addr:postcode":"1190",
    "addr:street":"Rue Des Primeurs",
    "iso:country":"BE",
    "sg:address":"Rue Des Primeurs 61-63",
    "sg:city":"Bruxelles (forest)",
    "sg:classifiers":[
        {
            "category":"Transit Center",
            "subcategory":"Freight",
            "type":"Transportation"
        }
    ],
    "sg:phone":"+32 2 344 63 59",
    "sg:postcode":"1190",
    "sg:province":"Bruxelles-Capitale",
    "sg:tags":[
        "import",
        "export",
        "-"
    ],
    "wof:name":"Probel International Sa",
    "wof:placetype":"venue"
},
  "geometry": {"coordinates":[4.3217749596,50.8196907043],"type":"Point"}
}