{
  "type": "Feature",
  "properties": {
    "addr:full":"Zone Artisanale De La Rivi\u00e8rette 66 Saint-ghislain Hainaut 7330",
    "addr:housenumber":"66",
    "addr:postcode":"7330",
    "addr:street":"Zone Artisanale De La Rivie\u0300Rette;Hainaut",
    "iso:country":"BE",
    "sg:address":"Zone Artisanale De La Rivi\u00e8rette 66",
    "sg:city":"Saint-ghislain",
    "sg:classifiers":[
        {
            "category":"Banks & Credit Unions",
            "subcategory":"Investment Brokerage",
            "type":"Services"
        }
    ],
    "sg:phone":"+32 65 60 10 05",
    "sg:postcode":"7330",
    "sg:province":"Hainaut",
    "sg:tags":[
        "repair",
        "-",
        "installation",
        "sanitary",
        "article"
    ],
    "wof:name":"A.b.m.",
    "wof:placetype":"venue"
},
  "geometry": {"coordinates":[3.8127410412,50.4578742981],"type":"Point"}
}