{
  "type": "Feature",
  "properties": {
    "addr:full":"Rue De La Roche Fatale 25 Sint-lambrechts-woluwe/woluwe-saint-lambert Bruxelles-Capitale 1200",
    "addr:housenumber":"25",
    "addr:postcode":"1200",
    "addr:street":"Rue De La Roche Fatale",
    "iso:country":"BE",
    "sg:address":"Rue De La Roche Fatale 25",
    "sg:city":"Sint-lambrechts-woluwe/woluwe-saint-lambert",
    "sg:orig_category":"V\u00e9hicules automobiles",
    "sg:phone":"+32 2 771 89 46",
    "sg:postcode":"1200",
    "sg:province":"Bruxelles-Capitale",
    "wof:name":"Ez-znaidi Car",
    "wof:placetype":"venue"
},
  "geometry": {"coordinates":[4.4210391045,50.8443336487],"type":"Point"}
}