{
  "type": "Feature",
  "properties": {
    "addr:full":"Zarlardingestraat 22 Geraardsbergen (goeferdinge) Oost-Vlaanderen 9500",
    "addr:housenumber":"22",
    "addr:postcode":"9500",
    "addr:street":"Zarlardingestraat",
    "iso:country":"BE",
    "sg:address":"Zarlardingestraat 22",
    "sg:city":"Geraardsbergen (goeferdinge)",
    "sg:classifiers":[
        {
            "category":"Building & Trades",
            "subcategory":"Construction",
            "type":"Services"
        }
    ],
    "sg:phone":"+32 54 41 80 83",
    "sg:postcode":"9500",
    "sg:province":"Oost-Vlaanderen",
    "sg:tags":[
        "carpenter"
    ],
    "wof:name":"Geraard Bvba",
    "wof:placetype":"venue"
},
  "geometry": {"coordinates":[3.8843801022,50.7716445923],"type":"Point"}
}