{
  "type": "Feature",
  "properties": {
    "iso:country":"BE",
    "sg:address":"Felix Timmermansstraat 14",
    "sg:city":"Zele",
    "sg:orig_category":"Elektrische installaties voor woningen Etalage- and showroomontwerpers",
    "sg:phone":"+32 52 45 00 23",
    "sg:postcode":"9240",
    "sg:province":"Oost-Vlaanderen",
    "wof:name":"Peter Roosendans",
    "wof:placetype":"venue"
},
  "geometry": {"coordinates":[4.0331101418,51.0592575073],"type":"Point"}
}