{
  "type": "Feature",
  "properties": {
    "addr:full":"Waterstraat 18 Harelbeke (bavikhove) West-Vlaanderen 8531",
    "addr:housenumber":"18",
    "addr:postcode":"8531",
    "addr:street":"Waterstraat",
    "iso:country":"BE",
    "sg:address":"Waterstraat 18",
    "sg:city":"Harelbeke (bavikhove)",
    "sg:classifiers":[
        {
            "category":"Bars & Pubs",
            "type":"Food & Drink"
        }
    ],
    "sg:phone":"+32 56 71 82 17",
    "sg:postcode":"8531",
    "sg:province":"West-Vlaanderen",
    "sg:tags":[
        "tavern"
    ],
    "wof:name":"Landhuis (het)",
    "wof:placetype":"venue"
},
  "geometry": {"coordinates":[3.281414032,50.8754081726],"type":"Point"}
}