{
  "type": "Feature",
  "properties": {
    "iso:country":"BE",
    "sg:address":"Rue Du Dr Ronflette 29",
    "sg:city":"Beloeil",
    "sg:classifiers":[
        {
            "category":"Arena",
            "subcategory":"Sports Club",
            "type":"Entertainment"
        }
    ],
    "sg:phone":"+32 69 68 99 46",
    "sg:postcode":"7970",
    "sg:province":"Hainaut",
    "sg:tags":[
        "de"
    ],
    "wof:name":"Moto Club 2000",
    "wof:placetype":"venue"
},
  "geometry": {"coordinates":[3.7381429672,50.5493278503],"type":"Point"}
}