{
  "type": "Feature",
  "properties": {
    "iso:country":"BE",
    "sg:address":"Sleepstraat 66",
    "sg:city":"Gent",
    "sg:classifiers":[
        {
            "category":"Restaurant",
            "type":"Food & Drink"
        }
    ],
    "sg:phone":"+32 9 224 11 91",
    "sg:postcode":"9000",
    "sg:province":"Oost-Vlaanderen",
    "wof:name":"Passage To India",
    "wof:placetype":"venue"
},
  "geometry": {"coordinates":[3.7262020111,51.0609016418],"type":"Point"}
}