{
  "type": "Feature",
  "properties": {
    "iso:country":"BE",
    "sg:address":"Bredestraat 233",
    "sg:city":"Diest",
    "sg:orig_category":"Elektrische installaties voor woningen Huishoudapparaten, televisies and radio's Verlichting and hui",
    "sg:phone":"+32 13 31 48 71",
    "sg:postcode":"3293",
    "sg:province":"Vlaams-Brabant",
    "wof:name":"Multilight",
    "wof:placetype":"venue"
},
  "geometry": {"coordinates":[5.0366768837,50.9766082764],"type":"Point"}
}