{
  "type": "Feature",
  "properties": {
    "iso:country":"BE",
    "sg:address":"Gildelaan 12",
    "sg:city":"Herentals",
    "sg:orig_category":"Enseignement maternel and primaire",
    "sg:phone":"+32 14 21 14 23",
    "sg:postcode":"2200",
    "sg:province":"Antwerpen",
    "wof:name":"Vrije Lagere School",
    "wof:placetype":"venue"
},
  "geometry": {"coordinates":[4.8336200714,51.1744499207],"type":"Point"}
}