{
  "type": "Feature",
  "properties": {
    "iso:country":"BE",
    "sg:address":"Chemin De La Guelenne 64",
    "sg:city":"Soignies",
    "sg:classifiers":[
        {
            "category":"Manufacturing",
            "subcategory":"Paper Products",
            "type":"Manufacturing & Wholesale Goods"
        }
    ],
    "sg:phone":"+32 67 33 06 54",
    "sg:postcode":"7060",
    "sg:province":"Hainaut",
    "sg:tags":[
        "packing",
        "cardboard",
        "-"
    ],
    "wof:name":"Deveseleer",
    "wof:placetype":"venue"
},
  "geometry": {"coordinates":[4.072991848,50.5891494751],"type":"Point"}
}