{
  "type": "Feature",
  "properties": {
    "iso:country":"BE",
    "sg:address":"Place Matt\u00c9oti 9",
    "sg:city":"Charleroi",
    "sg:classifiers":[
        {
            "category":"Cafe",
            "type":"Food & Drink"
        }
    ],
    "sg:phone":"+32 71 37 36 49",
    "sg:postcode":"6040",
    "sg:province":"Hainaut",
    "sg:tags":[
        "caf\u00e9s"
    ],
    "wof:name":"Caf\u00c9 Nouvia't Jumet",
    "wof:placetype":"venue"
},
  "geometry": {"coordinates":[4.450150013,50.4418296814],"type":"Point"}
}