{
  "type": "Feature",
  "properties": {
    "addr:full":"Rode Kruisplein 12 Zwevegem West-Vlaanderen 8550",
    "addr:housenumber":"12",
    "addr:postcode":"8550",
    "addr:street":"Rode Kruisplein",
    "iso:country":"BE",
    "sg:address":"Rode Kruisplein 12",
    "sg:city":"Zwevegem",
    "sg:orig_category":"Dakwerken",
    "sg:phone":"+32 56 75 42 01",
    "sg:postcode":"8550",
    "sg:province":"West-Vlaanderen",
    "wof:name":"Joris Vanhessche",
    "wof:placetype":"venue"
},
  "geometry": {"coordinates":[3.3314249516,50.8102874756],"type":"Point"}
}