{
  "type": "Feature",
  "properties": {
    "addr:full":"Rue De La Station 9 Bievre Namur 5555",
    "addr:housenumber":"9",
    "addr:postcode":"5555",
    "addr:street":"Rue De La Station",
    "iso:country":"BE",
    "sg:address":"Rue De La Station 9",
    "sg:city":"Bievre",
    "sg:orig_category":"Meubelzaken, woning- and keukeninrichting",
    "sg:phone":"+32 61 51 21 65",
    "sg:postcode":"5555",
    "sg:province":"Namur",
    "wof:name":"Meubles M J M",
    "wof:placetype":"venue"
},
  "geometry": {"coordinates":[5.0670571327,49.9491653442],"type":"Point"}
}