{
  "type": "Feature",
  "properties": {
    "iso:country":"BE",
    "sg:address":"Zeggeman 21",
    "sg:city":"Meerhout",
    "sg:orig_category":"D\u00e9molition d\u00b4immeubles and terrassements",
    "sg:phone":"+32 14 30 97 87",
    "sg:postcode":"2450",
    "sg:province":"Antwerpen",
    "wof:name":"Wellens En Zonen",
    "wof:placetype":"venue"
},
  "geometry": {"coordinates":[5.0452251434,51.1145477295],"type":"Point"}
}