{
  "type": "Feature",
  "properties": {
    "iso:country":"BE",
    "sg:address":"Molenstraat 61",
    "sg:city":"Kontich",
    "sg:orig_category":"Textiles. V\u00eatements",
    "sg:phone":"+32 3 457 80 60",
    "sg:postcode":"2550",
    "sg:province":"Antwerpen",
    "wof:name":"Huis Marlinick",
    "wof:placetype":"venue"
},
  "geometry": {"coordinates":[4.4417300224,51.1362915039],"type":"Point"}
}