{
  "type": "Feature",
  "properties": {
    "addr:full":"Sint-amandusstraat 73 Hasselt Limburg 3511",
    "addr:housenumber":"73",
    "addr:postcode":"3511",
    "addr:street":"Sint-Amandusstraat",
    "iso:country":"BE",
    "sg:address":"Sint-amandusstraat 73",
    "sg:city":"Hasselt",
    "sg:orig_category":"Sportclubs Sportterreinen and installaties behalve sportcentra",
    "sg:phone":"+32 11 25 59 79",
    "sg:postcode":"3511",
    "sg:province":"Limburg",
    "wof:name":"Vict. V.v. Stokrooie",
    "wof:placetype":"venue"
},
  "geometry": {"coordinates":[5.2743639946,50.9651412964],"type":"Point"}
}