{
  "type": "Feature",
  "properties": {
    "addr:full":"Rue Des R\u00c9sistants 19 Mont-de-l\u00b4enclus Hainaut 7750",
    "addr:housenumber":"19",
    "addr:postcode":"7750",
    "addr:street":"Rue Des Re\u0301Sistants;Hainaut",
    "iso:country":"BE",
    "sg:address":"Rue Des R\u00c9sistants 19",
    "sg:city":"Mont-de-l\u00b4enclus",
    "sg:orig_category":"Imprimeries and copyshops",
    "sg:phone":"+32 69 45 60 65",
    "sg:postcode":"7750",
    "sg:province":"Hainaut",
    "wof:name":"Imprimerie Desmet-laire",
    "wof:placetype":"venue"
},
  "geometry": {"coordinates":[3.5024280548,50.7453575134],"type":"Point"}
}