{
  "type": "Feature",
  "properties": {
    "addr:full":"Rue Des Fleurs 22 Anderlues Hainaut 6150",
    "addr:housenumber":"22",
    "addr:postcode":"6150",
    "addr:street":"Rue Des Fleurs",
    "iso:country":"BE",
    "sg:address":"Rue Des Fleurs 22",
    "sg:city":"Anderlues",
    "sg:orig_category":"Plomberie, chauffage and installations sanitaires",
    "sg:phone":"+32 71 52 61 15",
    "sg:postcode":"6150",
    "sg:province":"Hainaut",
    "wof:name":"Andre Hennebert",
    "wof:placetype":"venue"
},
  "geometry": {"coordinates":[4.2706699371,50.4097290039],"type":"Point"}
}