{
  "type": "Feature",
  "properties": {
    "addr:full":"D'overschielaan 15 Grimbergen Vlaams-Brabant 1850",
    "addr:housenumber":"15",
    "addr:postcode":"1850",
    "addr:street":"D'Overschielaan",
    "iso:country":"BE",
    "sg:address":"D'overschielaan 15",
    "sg:city":"Grimbergen",
    "sg:orig_category":"Studios photographiques",
    "sg:phone":"+32 2 269 52 16",
    "sg:postcode":"1850",
    "sg:province":"Vlaams-Brabant",
    "wof:name":"Vanrijk En Partners",
    "wof:placetype":"venue"
},
  "geometry": {"coordinates":[4.3706021309,50.9395103455],"type":"Point"}
}