{
  "type": "Feature",
  "properties": {
    "addr:full":"Leuvensestraat 70 Aarschot Vlaams-Brabant 3200",
    "addr:housenumber":"70",
    "addr:postcode":"3200",
    "addr:street":"Leuvensestraat",
    "iso:country":"BE",
    "sg:address":"Leuvensestraat 70",
    "sg:city":"Aarschot",
    "sg:orig_category":"Apotheken",
    "sg:phone":"+32 16 56 68 89",
    "sg:postcode":"3200",
    "sg:province":"Vlaams-Brabant",
    "wof:name":"Multipharma",
    "wof:placetype":"venue"
},
  "geometry": {"coordinates":[4.8312458992,50.9835090637],"type":"Point"}
}