{
  "type": "Feature",
  "properties": {
    "addr:full":"Honsfeld 169 B\u00dcllingen/bullange Li\u00e8ge 4760",
    "addr:housenumber":"169",
    "addr:postcode":"4760",
    "addr:street":"Honsfeld",
    "iso:country":"BE",
    "sg:address":"Honsfeld 169",
    "sg:city":"B\u00dcllingen/bullange",
    "sg:orig_category":"Artsen and specialisten",
    "sg:phone":"+32 80 64 71 00",
    "sg:postcode":"4760",
    "sg:province":"Li\u00e8ge",
    "wof:name":"Fe. Van Lochem",
    "wof:placetype":"venue"
},
  "geometry": {"coordinates":[6.2787179947,50.3852043152],"type":"Point"}
}