{
  "type": "Feature",
  "properties": {
    "iso:country":"BE",
    "sg:address":"Rue Haute 24",
    "sg:city":"Modave",
    "sg:orig_category":"Catering and organisatie van feesten Voedingsspeciaalzaken",
    "sg:phone":"+32 85 41 13 51",
    "sg:postcode":"4577",
    "sg:province":"Li\u00e8ge",
    "wof:name":"Traiteur Du Florichamps",
    "wof:placetype":"venue"
},
  "geometry": {"coordinates":[5.2907748222,50.4811820984],"type":"Point"}
}