{
  "type": "Feature",
  "properties": {
    "iso:country":"BE",
    "sg:address":"Industrieln 15-17",
    "sg:city":"Ieper",
    "sg:classifiers":[
        {
            "category":"Government",
            "subcategory":"Department Of Motor Vehicles",
            "type":"Public Place"
        }
    ],
    "sg:phone":"+32 57 20 10 91",
    "sg:postcode":"8900",
    "sg:province":"West-Vlaanderen",
    "sg:tags":[
        "equipment",
        "industrial",
        "transport",
        "motor-cars"
    ],
    "wof:name":"Parmentier Technics Nv",
    "wof:placetype":"venue"
},
  "geometry": {"coordinates":[2.8878269196,50.8513641357],"type":"Point"}
}