{
  "type": "Feature",
  "properties": {
    "addr:full":"Sint-pietersstraat 11 Ledegem West-Vlaanderen 8880",
    "addr:housenumber":"11",
    "addr:postcode":"8880",
    "addr:street":"Sint-Pietersstraat",
    "iso:country":"BE",
    "sg:address":"Sint-pietersstraat 11",
    "sg:city":"Ledegem",
    "sg:classifiers":[
        {
            "category":"Personal",
            "type":"Services"
        }
    ],
    "sg:phone":"+32 56 50 00 23",
    "sg:postcode":"8880",
    "sg:province":"West-Vlaanderen",
    "sg:tags":[
        "party",
        "planning"
    ],
    "wof:name":"Cycloon Nv",
    "wof:placetype":"venue"
},
  "geometry": {"coordinates":[3.1134750843,50.8707504272],"type":"Point"}
}