{
  "type": "Feature",
  "properties": {
    "addr:full":"Koningin Astridlaan 159 Mechelen Antwerpen 2800",
    "addr:housenumber":"159",
    "addr:postcode":"2800",
    "addr:street":"Koningin Astridlaan",
    "iso:country":"BE",
    "sg:address":"Koningin Astridlaan 159",
    "sg:city":"Mechelen",
    "sg:classifiers":[
        {
            "category":"Health Services",
            "subcategory":"Doctor",
            "type":"Services"
        }
    ],
    "sg:phone":"+32 15 30 31 11",
    "sg:postcode":"2800",
    "sg:province":"Antwerpen",
    "sg:tags":[
        "medicinephysicians",
        "surgeon"
    ],
    "wof:name":"Claes J",
    "wof:placetype":"venue"
},
  "geometry": {"coordinates":[4.472055912,51.0236091614],"type":"Point"}
}