{
  "type": "Feature",
  "properties": {
    "addr:full":"Tweede Aardstraat 26 Harelbeke (bavikhove) West-Vlaanderen 8531",
    "addr:housenumber":"26",
    "addr:postcode":"8531",
    "addr:street":"Tweede Aardstraat",
    "iso:country":"BE",
    "sg:address":"Tweede Aardstraat 26",
    "sg:city":"Harelbeke (bavikhove)",
    "sg:classifiers":[
        {
            "category":"Farming",
            "subcategory":"Farm & Veterinary Services",
            "type":"Manufacturing & Wholesale Goods"
        }
    ],
    "sg:phone":"+32 56 71 04 24",
    "sg:postcode":"8531",
    "sg:province":"West-Vlaanderen",
    "sg:tags":[
        "agricultural",
        "contractor"
    ],
    "wof:name":"Callens C",
    "wof:placetype":"venue"
},
  "geometry": {"coordinates":[3.3224680424,50.8803634644],"type":"Point"}
}