{
  "type": "Feature",
  "properties": {
    "addr:full":"Rue Eug\u00e8ne Hambursin 14 Namur Namur 5000",
    "addr:housenumber":"14",
    "addr:postcode":"5000",
    "addr:street":"Rue Euge\u0300Ne Hambursin",
    "iso:country":"BE",
    "sg:address":"Rue Eug\u00e8ne Hambursin 14",
    "sg:city":"Namur",
    "sg:classifiers":[
        {
            "category":"Parking",
            "subcategory":"Bicycle",
            "type":"Transportation"
        }
    ],
    "sg:phone":"+32 81 73 30 97",
    "sg:postcode":"5000",
    "sg:province":"Namur",
    "sg:tags":[
        "chiropodist"
    ],
    "wof:name":"Gillard E",
    "wof:placetype":"venue"
},
  "geometry": {"coordinates":[4.85064888,50.465675354],"type":"Point"}
}