{
  "type": "Feature",
  "properties": {
    "iso:country":"BE",
    "sg:address":"Avenue De La Pairelle 11-12",
    "sg:city":"Namur",
    "sg:classifiers":[
        {
            "category":"Professional",
            "subcategory":"Engineering",
            "type":"Services"
        }
    ],
    "sg:phone":"+32 81 22 97 50",
    "sg:postcode":"5000",
    "sg:province":"Namur",
    "sg:tags":[
        "civil"
    ],
    "wof:name":"Sotegec Soci\u00e9t\u00e9 D'etudes Techniques S.p.r.l.",
    "wof:placetype":"venue"
},
  "geometry": {"coordinates":[4.8589301109,50.4436302185],"type":"Point"}
}