{
  "type": "Feature",
  "properties": {
    "addr:full":"Meeuwenlaan 6 Middelkerke West-Vlaanderen 8434",
    "addr:housenumber":"6",
    "addr:postcode":"8434",
    "addr:street":"Meeuwenlaan",
    "iso:country":"BE",
    "sg:address":"Meeuwenlaan 6",
    "sg:city":"Middelkerke",
    "sg:classifiers":[
        {
            "category":"Fast Food",
            "type":"Food & Drink"
        }
    ],
    "sg:phone":"+32 59 31 26 07",
    "sg:postcode":"8434",
    "sg:province":"West-Vlaanderen",
    "sg:tags":[
        "meeneem",
        "restaurant"
    ],
    "wof:name":"Pizzeria Rimini",
    "wof:placetype":"venue"
},
  "geometry": {"coordinates":[2.7754869461,51.1707382202],"type":"Point"}
}