{
  "type": "Feature",
  "properties": {
    "iso:country":"BE",
    "sg:address":"Liersesteenweg 395",
    "sg:city":"Mechelen",
    "sg:classifiers":[
        {
            "category":"Banks & Credit Unions",
            "subcategory":"Investment Brokerage",
            "type":"Services"
        }
    ],
    "sg:phone":"+32 15 28 01 80",
    "sg:postcode":"2800",
    "sg:province":"Antwerpen",
    "sg:tags":[
        "auditor"
    ],
    "wof:name":"Doms W",
    "wof:placetype":"venue"
},
  "geometry": {"coordinates":[4.4786200523,51.0465011597],"type":"Point"}
}