{
  "type": "Feature",
  "properties": {
    "iso:country":"BE",
    "sg:address":"Edmond Thieffrylaan 14",
    "sg:city":"Mortsel",
    "sg:orig_category":"Herstellingen and onderhoud van auto's",
    "sg:phone":"+32 3 449 53 61",
    "sg:postcode":"2640",
    "sg:province":"Antwerpen",
    "wof:name":"Publi Roelants",
    "wof:placetype":"venue"
},
  "geometry": {"coordinates":[4.4451270103,51.1666603088],"type":"Point"}
}