{
  "type": "Feature",
  "properties": {
    "addr:full":"Paterstraat 32a Zomergem Oost-Vlaanderen 9930",
    "addr:housenumber":"32a",
    "addr:postcode":"9930",
    "addr:street":"Paterstraat",
    "iso:country":"BE",
    "sg:address":"Paterstraat 32a",
    "sg:city":"Zomergem",
    "sg:orig_category":"Industri\u00eble and commerci\u00eble bouw Woningbouw",
    "sg:phone":"+32 9 372 61 29",
    "sg:postcode":"9930",
    "sg:province":"Oost-Vlaanderen",
    "wof:name":"Denis Geerard",
    "wof:placetype":"venue"
},
  "geometry": {"coordinates":[3.60217309,51.1294364929],"type":"Point"}
}