{
  "type": "Feature",
  "properties": {
    "addr:full":"Avenue De Heppignies 34 Fleurus (heppignies) Hainaut 6220",
    "addr:housenumber":"34",
    "addr:postcode":"6220",
    "addr:street":"Avenue De Heppignies",
    "iso:country":"BE",
    "sg:address":"Avenue De Heppignies 34",
    "sg:city":"Fleurus (heppignies)",
    "sg:classifiers":[
        {
            "category":"Home & Garden",
            "subcategory":"Building Materials",
            "type":"Retail Goods"
        }
    ],
    "sg:phone":"+32 71 37 20 94",
    "sg:postcode":"6220",
    "sg:province":"Hainaut",
    "sg:tags":[
        "insulation",
        "thermical"
    ],
    "wof:name":"Isothermic Sa",
    "wof:placetype":"venue"
},
  "geometry": {"coordinates":[4.5496749878,50.4825363159],"type":"Point"}
}