{
  "type": "Feature",
  "properties": {
    "addr:full":"Grand-place 41 Mons Hainaut 7000",
    "addr:housenumber":"41",
    "addr:postcode":"7000",
    "addr:street":"Grand-Place;Hainaut",
    "iso:country":"BE",
    "sg:address":"Grand-place 41",
    "sg:city":"Mons",
    "sg:classifiers":[
        {
            "category":"Cafe",
            "type":"Food & Drink"
        }
    ],
    "sg:phone":"+32 65 31 74 46",
    "sg:postcode":"7000",
    "sg:province":"Hainaut",
    "sg:tags":[
        "caf\u00e9s"
    ],
    "wof:name":"Immos",
    "wof:placetype":"venue"
},
  "geometry": {"coordinates":[3.9520909786,50.4538764954],"type":"Point"}
}