{
  "type": "Feature",
  "properties": {
    "addr:full":"Rue Am\u00c9ricaine 3 Sint-gillis/saint-gilles Bruxelles-Capitale 1060",
    "addr:housenumber":"3",
    "addr:postcode":"1060",
    "addr:street":"Rue Ame\u0301Ricaine",
    "iso:country":"BE",
    "sg:address":"Rue Am\u00c9ricaine 3",
    "sg:city":"Sint-gillis/saint-gilles",
    "sg:orig_category":"M\u00e9decins and sp\u00e9cialistes",
    "sg:phone":"+32 2 544 09 57",
    "sg:postcode":"1060",
    "sg:province":"Bruxelles-Capitale",
    "wof:name":"Catherine Meunier",
    "wof:placetype":"venue"
},
  "geometry": {"coordinates":[4.3545827866,50.8244361877],"type":"Point"}
}