{
  "type": "Feature",
  "properties": {
    "addr:full":"Windmolenstraat 23 Leuven Vlaams-Brabant 3000",
    "addr:housenumber":"23",
    "addr:postcode":"3000",
    "addr:street":"Windmolenstraat",
    "iso:country":"BE",
    "sg:address":"Windmolenstraat 23",
    "sg:city":"Leuven",
    "sg:orig_category":"Ordinateurs and \u00e9quipement informatique",
    "sg:phone":"+32 16 29 10 32",
    "sg:postcode":"3000",
    "sg:province":"Vlaams-Brabant",
    "wof:name":"Upperware",
    "wof:placetype":"venue"
},
  "geometry": {"coordinates":[4.7104239464,50.8733634949],"type":"Point"}
}