{
  "type": "Feature",
  "properties": {
    "addr:full":"Steenweg Op Oosthoven 92 Turnhout Antwerpen 2300",
    "addr:housenumber":"92",
    "addr:postcode":"2300",
    "addr:street":"Steenweg Op Oosthoven",
    "iso:country":"BE",
    "sg:address":"Steenweg Op Oosthoven 92",
    "sg:city":"Turnhout",
    "sg:orig_category":"P\u00e9pini\u00e9ristes",
    "sg:phone":"+32 14 41 18 93",
    "sg:postcode":"2300",
    "sg:province":"Antwerpen",
    "wof:name":"Bloemenfontein",
    "wof:placetype":"venue"
},
  "geometry": {"coordinates":[4.9536218643,51.330242157],"type":"Point"}
}