{
  "type": "Feature",
  "properties": {
    "addr:full":"Veldenbergstraat 97 Merksplas Antwerpen 2330",
    "addr:housenumber":"97",
    "addr:postcode":"2330",
    "addr:street":"Veldenbergstraat",
    "iso:country":"BE",
    "sg:address":"Veldenbergstraat 97",
    "sg:city":"Merksplas",
    "sg:classifiers":[
        {
            "category":"Recreation",
            "subcategory":"Campground",
            "type":"Entertainment"
        }
    ],
    "sg:phone":"+32 14 63 39 29",
    "sg:postcode":"2330",
    "sg:province":"Antwerpen",
    "sg:tags":[
        "site",
        "camping"
    ],
    "wof:name":"Caravans Molenzijdse Heide",
    "wof:placetype":"venue"
},
  "geometry": {"coordinates":[4.8390378952,51.3696327209],"type":"Point"}
}