{
  "type": "Feature",
  "properties": {
    "addr:full":"Graaf Gwijde Van Namenstraat 2 Kortrijk West-Vlaanderen 8500",
    "addr:housenumber":"2",
    "addr:postcode":"8500",
    "addr:street":"Graaf;Namenstraat",
    "iso:country":"BE",
    "sg:address":"Graaf Gwijde Van Namenstraat 2",
    "sg:city":"Kortrijk",
    "sg:classifiers":[
        {
            "category":"Education",
            "subcategory":"School",
            "type":"Public Place"
        }
    ],
    "sg:phone":"+32 56 35 51 70",
    "sg:postcode":"8500",
    "sg:province":"West-Vlaanderen",
    "sg:tags":[
        "primary"
    ],
    "wof:name":"De Bloesem",
    "wof:placetype":"venue"
},
  "geometry": {"coordinates":[3.282435894,50.8309707642],"type":"Point"}
}