{
  "type": "Feature",
  "properties": {
    "iso:country":"BE",
    "sg:address":"Rue Louis Blanqui 86",
    "sg:city":"Quaregnon",
    "sg:orig_category":"Huishoudapparaten, televisies and radio's",
    "sg:phone":"+32 65 67 26 17",
    "sg:postcode":"7390",
    "sg:province":"Hainaut",
    "wof:name":"Salvatore Lo Presti",
    "wof:placetype":"venue"
},
  "geometry": {"coordinates":[3.8739209175,50.4226875305],"type":"Point"}
}