{
  "type": "Feature",
  "properties": {
    "addr:full":"Derbystraat 293 Gent Oost-Vlaanderen 9051",
    "addr:housenumber":"293",
    "addr:postcode":"9051",
    "addr:street":"Derbystraat;Oost-Vlaanderen",
    "iso:country":"BE",
    "sg:address":"Derbystraat 293",
    "sg:city":"Gent",
    "sg:orig_category":"Diverse bedrijfsbeheeradviesbureaus",
    "sg:phone":"+32 9 220 23 36",
    "sg:postcode":"9051",
    "sg:province":"Oost-Vlaanderen",
    "wof:name":"S&v Management Consultants",
    "wof:placetype":"venue"
},
  "geometry": {"coordinates":[3.6970150471,51.0234222412],"type":"Point"}
}