{
  "type": "Feature",
  "properties": {
    "iso:country":"BE",
    "sg:address":"Zevekotestraat 58",
    "sg:city":"Gistel",
    "sg:orig_category":"Enseignement maternel and primaire",
    "sg:phone":"+32 59 27 43 51",
    "sg:postcode":"8470",
    "sg:province":"West-Vlaanderen",
    "wof:name":"Vrije Basisschool",
    "wof:placetype":"venue"
},
  "geometry": {"coordinates":[2.9188830853,51.1354408264],"type":"Point"}
}