{
  "type": "Feature",
  "properties": {
    "addr:full":"Paddegatstraat 69 Kapelle-op-den-bos (nieuwenrode) Vlaams-Brabant 1880",
    "addr:housenumber":"69",
    "addr:postcode":"1880",
    "addr:street":"Paddegatstraat",
    "iso:country":"BE",
    "sg:address":"Paddegatstraat 69",
    "sg:city":"Kapelle-op-den-bos (nieuwenrode)",
    "sg:classifiers":[
        {
            "category":"Professional",
            "subcategory":"Computer Services",
            "type":"Services"
        }
    ],
    "sg:phone":"+32 15 71 44 79",
    "sg:postcode":"1880",
    "sg:province":"Vlaams-Brabant",
    "sg:tags":[
        "-",
        "processing",
        "data",
        "software"
    ],
    "wof:name":"Mvd Software",
    "wof:placetype":"venue"
},
  "geometry": {"coordinates":[4.3518671989,50.9792785645],"type":"Point"}
}