{
  "type": "Feature",
  "properties": {
    "iso:country":"BE",
    "sg:address":"Achterstraat 110",
    "sg:city":"Peer (wijchmaal)",
    "sg:classifiers":[
        {
            "category":"Structure",
            "subcategory":"Office Building",
            "type":"Public Place"
        }
    ],
    "sg:phone":"+32 11 63 32 69",
    "sg:postcode":"3990",
    "sg:province":"Limburg",
    "sg:tags":[
        "-",
        "type",
        "door",
        "sliding",
        "overhead"
    ],
    "wof:name":"Houben Hugo",
    "wof:placetype":"venue"
},
  "geometry": {"coordinates":[5.4200367928,51.1182823181],"type":"Point"}
}