{
  "type": "Feature",
  "properties": {
    "iso:country":"BE",
    "sg:address":"Rue Saint-gilles 31",
    "sg:city":"Li\u00c8ge",
    "sg:orig_category":"Salles de conf\u00e9rences and de r\u00e9ceptions. Editeurs de journaux. Editeurs de revues and p\u00e9riodiques",
    "sg:phone":"+32 4 222 29 46",
    "sg:postcode":"4000",
    "sg:province":"Li\u00e8ge",
    "wof:name":"Ass. Ing\u00c9n. Mont\u00c9fiore",
    "wof:placetype":"venue"
},
  "geometry": {"coordinates":[5.5673251152,50.6395225525],"type":"Point"}
}