{
  "type": "Feature",
  "properties": {
    "addr:full":"Avenue De Spa 81 Verviers (heusy) Li\u00e8ge 4802",
    "addr:housenumber":"81",
    "addr:postcode":"4802",
    "addr:street":"Avenue De Spa",
    "iso:country":"BE",
    "sg:address":"Avenue De Spa 81",
    "sg:city":"Verviers (heusy)",
    "sg:classifiers":[
        {
            "category":"Professional",
            "subcategory":"Management & Consulting",
            "type":"Services"
        }
    ],
    "sg:phone":"+32 87 29 21 10",
    "sg:postcode":"4802",
    "sg:province":"Li\u00e8ge",
    "sg:tags":[
        "tax-consultants"
    ],
    "wof:name":"Sequaris A",
    "wof:placetype":"venue"
},
  "geometry": {"coordinates":[5.8671250343,50.5714111328],"type":"Point"}
}