{
  "type": "Feature",
  "properties": {
    "iso:country":"BE",
    "sg:address":"Waversestw 78",
    "sg:city":"Hoeilaart",
    "sg:classifiers":[
        {
            "category":"Professional",
            "type":"Services"
        }
    ],
    "sg:phone":"+32 2 657 02 17",
    "sg:postcode":"1560",
    "sg:province":"Vlaams-Brabant",
    "sg:tags":[
        "transport",
        "road"
    ],
    "wof:name":"Transport Debrouwer Nv",
    "wof:placetype":"venue"
},
  "geometry": {"coordinates":[4.4764938354,50.7602272034],"type":"Point"}
}