{
  "type": "Feature",
  "properties": {
    "addr:full":"Rue De Valenciennes 13 Quievrain Hainaut 7380",
    "addr:housenumber":"13",
    "addr:postcode":"7380",
    "addr:street":"Rue De Valenciennes;Hainaut",
    "iso:country":"BE",
    "sg:address":"Rue De Valenciennes 13",
    "sg:city":"Quievrain",
    "sg:orig_category":"Artsen and specialisten",
    "sg:phone":"+32 65 45 70 36",
    "sg:postcode":"7380",
    "sg:province":"Hainaut",
    "wof:name":"Pierre Masset",
    "wof:placetype":"venue"
},
  "geometry": {"coordinates":[3.6812310219,50.4048881531],"type":"Point"}
}