{
  "type": "Feature",
  "properties": {
    "iso:country":"BE",
    "sg:address":"Rue Du Buissenet 4a",
    "sg:city":"P\u00e9ruwelz (brasmenil)",
    "sg:classifiers":[
        {
            "category":"Real Estate",
            "subcategory":"Real Estate Services",
            "type":"Services"
        }
    ],
    "sg:phone":"+32 69 77 46 52",
    "sg:postcode":"7604",
    "sg:province":"Hainaut",
    "wof:name":"Ghiot S",
    "wof:placetype":"venue"
},
  "geometry": {"coordinates":[3.5480670929,50.5404930115],"type":"Point"}
}