{
  "type": "Feature",
  "properties": {
    "addr:full":"Oliemolenstraat 28 Brugge West-Vlaanderen 8310",
    "addr:housenumber":"28",
    "addr:postcode":"8310",
    "addr:street":"Oliemolenstraat",
    "iso:country":"BE",
    "sg:address":"Oliemolenstraat 28",
    "sg:city":"Brugge",
    "sg:classifiers":[
        {
            "category":"Arena",
            "subcategory":"Sports Club",
            "type":"Entertainment"
        }
    ],
    "sg:phone":"+32 50 35 07 36",
    "sg:postcode":"8310",
    "sg:province":"West-Vlaanderen",
    "sg:tags":[
        "de"
    ],
    "wof:name":"B.c. Bilj.gilde Oostkamp",
    "wof:placetype":"venue"
},
  "geometry": {"coordinates":[3.2471199036,51.197719574],"type":"Point"}
}