{
  "type": "Feature",
  "properties": {
    "addr:full":"Keizersplein 64 Aalst Oost-Vlaanderen 9300",
    "addr:housenumber":"64",
    "addr:postcode":"9300",
    "addr:street":"Keizersplein",
    "iso:country":"BE",
    "sg:address":"Keizersplein 64",
    "sg:city":"Aalst",
    "sg:orig_category":"Foto-uitrusting Fotografen and fotostudio's Fotolaboratoria",
    "sg:phone":"+32 53 78 64 67",
    "sg:postcode":"9300",
    "sg:province":"Oost-Vlaanderen",
    "wof:name":"Studio Photo-line",
    "wof:placetype":"venue"
},
  "geometry": {"coordinates":[4.0380620956,50.9357452393],"type":"Point"}
}