{
  "type": "Feature",
  "properties": {
    "iso:country":"BE",
    "sg:address":"Chauss\u00c9e De Neerstalle 332",
    "sg:city":"Vorst/forest",
    "sg:orig_category":"Pain, p\u00e2tisseries and confiseries",
    "sg:phone":"+32 2 376 01 58",
    "sg:postcode":"1190",
    "sg:province":"Bruxelles-Capitale",
    "wof:name":"De Troeye",
    "wof:placetype":"venue"
},
  "geometry": {"coordinates":[4.3181700706,50.8004493713],"type":"Point"}
}