{
  "type": "Feature",
  "properties": {
    "addr:full":"Hoging 26 Lede (oordegem) Oost-Vlaanderen 9340",
    "addr:housenumber":"26",
    "addr:postcode":"9340",
    "addr:street":"Hoging",
    "iso:country":"BE",
    "sg:address":"Hoging 26",
    "sg:city":"Lede (oordegem)",
    "sg:classifiers":[
        {
            "category":"Building & Trades",
            "subcategory":"Construction",
            "type":"Services"
        }
    ],
    "sg:phone":"+32 9 366 30 17",
    "sg:postcode":"9340",
    "sg:province":"Oost-Vlaanderen",
    "sg:tags":[
        "carpenter"
    ],
    "wof:name":"Bockstaele E",
    "wof:placetype":"venue"
},
  "geometry": {"coordinates":[3.9002969265,50.9532814026],"type":"Point"}
}