{
  "type": "Feature",
  "properties": {
    "iso:country":"BE",
    "sg:address":"Scherpeputstraat 8",
    "sg:city":"Lokeren",
    "sg:classifiers":[
        {
            "category":"Cafe",
            "type":"Food & Drink"
        }
    ],
    "sg:phone":"+32 9 348 43 58",
    "sg:postcode":"9160",
    "sg:province":"Oost-Vlaanderen",
    "sg:tags":[
        "caf\u00e9s"
    ],
    "wof:name":"Lokerse Sv",
    "wof:placetype":"venue"
},
  "geometry": {"coordinates":[4.0114622116,51.0880317688],"type":"Point"}
}