{
  "type": "Feature",
  "properties": {
    "iso:country":"BE",
    "sg:address":"Chemin Du Pont De Pierre 11",
    "sg:city":"Braine-le-comte",
    "sg:orig_category":"Rundveehouders",
    "sg:phone":"+32 67 55 21 21",
    "sg:postcode":"7090",
    "sg:province":"Hainaut",
    "wof:name":"Marcel Blondiau",
    "wof:placetype":"venue"
},
  "geometry": {"coordinates":[4.0975999832,50.607963562],"type":"Point"}
}