{
  "type": "Feature",
  "properties": {
    "addr:full":"Rue Du Trieu D\u00b4avillon 4 Assesse Namur 5336",
    "addr:housenumber":"4",
    "addr:postcode":"5336",
    "addr:street":"Rue Du Trieu D\u00b4Avillon",
    "iso:country":"BE",
    "sg:address":"Rue Du Trieu D\u00b4avillon 4",
    "sg:city":"Assesse",
    "sg:orig_category":"Enseignement maternel and primaire",
    "sg:phone":"+32 83 65 60 07",
    "sg:postcode":"5336",
    "sg:province":"Namur",
    "wof:name":"E.f.l. Sacr\u00c9-coeur",
    "wof:placetype":"venue"
},
  "geometry": {"coordinates":[4.988132,50.3936767578],"type":"Point"}
}