{
  "type": "Feature",
  "properties": {
    "addr:full":"Rigessel 135 Rotselaar Vlaams-Brabant 3111",
    "addr:housenumber":"135",
    "addr:postcode":"3111",
    "addr:street":"Rigessel",
    "iso:country":"BE",
    "sg:address":"Rigessel 135",
    "sg:city":"Rotselaar",
    "sg:orig_category":"Diverse bouwafwerking and reiniging Loodgieterij, verwarming and sanitaire installaties",
    "sg:phone":"+32 16 58 21 43",
    "sg:postcode":"3111",
    "sg:province":"Vlaams-Brabant",
    "wof:name":"Danny Dubru",
    "wof:placetype":"venue"
},
  "geometry": {"coordinates":[4.7534818649,50.9457702637],"type":"Point"}
}