{
  "type": "Feature",
  "properties": {
    "iso:country":"BE",
    "sg:address":"Tulpstraat 37",
    "sg:city":"Elsene/ixelles",
    "sg:orig_category":"Schoonmaakbedrijven and ongediertebestrijding",
    "sg:phone":"+32 2 514 34 07",
    "sg:postcode":"1050",
    "sg:province":"Bruxelles-Capitale",
    "wof:name":"Brilleclean",
    "wof:placetype":"venue"
},
  "geometry": {"coordinates":[4.3677978516,50.8347129822],"type":"Point"}
}