{
  "type": "Feature",
  "properties": {
    "addr:full":"Brugsesteenweg 307 Kuurne West-Vlaanderen 8520",
    "addr:housenumber":"307",
    "addr:postcode":"8520",
    "addr:street":"Brugsesteenweg",
    "iso:country":"BE",
    "sg:address":"Brugsesteenweg 307",
    "sg:city":"Kuurne",
    "sg:orig_category":"Enseignement maternel and primaire",
    "sg:phone":"+32 56 71 19 78",
    "sg:postcode":"8520",
    "sg:province":"West-Vlaanderen",
    "wof:name":"Gemeentelijke Basisschool",
    "wof:placetype":"venue"
},
  "geometry": {"coordinates":[3.2705559731,50.8625679016],"type":"Point"}
}