{
  "type": "Feature",
  "properties": {
    "iso:country":"BE",
    "sg:address":"Wiegstraat 8ba",
    "sg:city":"Antwerpen",
    "sg:classifiers":[
        {
            "category":"Cafe",
            "type":"Food & Drink"
        }
    ],
    "sg:phone":"+32 3 231 13 73",
    "sg:postcode":"2000",
    "sg:province":"Antwerpen",
    "sg:tags":[
        "caf\u00e9s"
    ],
    "wof:name":"Caf\u00c9 't Schaepke",
    "wof:placetype":"venue"
},
  "geometry": {"coordinates":[4.4045419693,51.2182884216],"type":"Point"}
}