{
  "type": "Feature",
  "properties": {
    "iso:country":"BE",
    "sg:address":"March\u00e9 Aux Toiles 10",
    "sg:city":"Ath",
    "sg:classifiers":[
        {
            "category":"Building & Trades",
            "subcategory":"Construction",
            "type":"Services"
        }
    ],
    "sg:phone":"+32 68 84 19 02",
    "sg:postcode":"7800",
    "sg:province":"Hainaut",
    "sg:tags":[
        "glazier"
    ],
    "wof:name":"Legrand Jose Vitrerie",
    "wof:placetype":"venue"
},
  "geometry": {"coordinates":[3.7753899097,50.631439209],"type":"Point"}
}