{
  "type": "Feature",
  "properties": {
    "addr:full":"Rue Haute 168 Brussel/bruxelles Bruxelles-Capitale 1000",
    "addr:housenumber":"168",
    "addr:postcode":"1000",
    "addr:street":"Rue Haute;/",
    "iso:country":"BE",
    "sg:address":"Rue Haute 168",
    "sg:city":"Brussel/bruxelles",
    "sg:orig_category":"Biens d'occasion",
    "sg:phone":"+32 2 512 65 05",
    "sg:postcode":"1000",
    "sg:province":"Bruxelles-Capitale",
    "wof:name":"Maison Du Bois",
    "wof:placetype":"venue"
},
  "geometry": {"coordinates":[4.350083828,50.8382873535],"type":"Point"}
}