{
  "type": "Feature",
  "properties": {
    "addr:full":"Esplanade Godefroid De Bouillon Bouillon Luxembourg 6830",
    "addr:postcode":"6830",
    "addr:street":"Esplanade Godefroid De Bouillon",
    "iso:country":"BE",
    "sg:address":"Esplanade Godefroid De Bouillon",
    "sg:city":"Bouillon",
    "sg:classifiers":[
        {
            "category":"Landmark",
            "subcategory":"Tourist Attraction",
            "type":"Public Place"
        }
    ],
    "sg:phone":"+32 61 46 42 02",
    "sg:postcode":"6830",
    "sg:province":"Luxembourg",
    "sg:tags":[
        "-",
        "tourism",
        "interest",
        "sight"
    ],
    "wof:name":"Ch\u00e2teau Fort",
    "wof:placetype":"venue"
},
  "geometry": {"coordinates":[5.0671100616,49.7943382263],"type":"Point"}
}