{
  "type": "Feature",
  "properties": {
    "iso:country":"BE",
    "sg:address":"Grootveldweg 4",
    "sg:city":"Geetbets",
    "sg:orig_category":"M\u00e9decins and sp\u00e9cialistes",
    "sg:phone":"+32 11 58 72 14",
    "sg:postcode":"3450",
    "sg:province":"Vlaams-Brabant",
    "wof:name":"Yvo Borgers",
    "wof:placetype":"venue"
},
  "geometry": {"coordinates":[5.1124100685,50.8901176453],"type":"Point"}
}