{
  "type": "Feature",
  "properties": {
    "iso:country":"BE",
    "sg:address":"Lindelaan 29",
    "sg:city":"Zandhoven (pulderbos)",
    "sg:classifiers":[
        {
            "category":"Home & Garden",
            "subcategory":"Home Furnishings",
            "type":"Retail Goods"
        }
    ],
    "sg:phone":"+32 3 484 51 08",
    "sg:postcode":"2242",
    "sg:province":"Antwerpen",
    "sg:tags":[
        "interior",
        "decoration"
    ],
    "wof:name":"Van Elsacker J",
    "wof:placetype":"venue"
},
  "geometry": {"coordinates":[4.6875600815,51.2159919739],"type":"Point"}
}