{
  "type": "Feature",
  "properties": {
    "addr:full":"St-damiaanstraat 49 Wommelgem Antwerpen 2160",
    "addr:housenumber":"49",
    "addr:postcode":"2160",
    "addr:street":"St-Damiaanstraat",
    "iso:country":"BE",
    "sg:address":"St-damiaanstraat 49",
    "sg:city":"Wommelgem",
    "sg:orig_category":"Chemicali\u00ebn Gh",
    "sg:phone":"+32 3 353 04 60",
    "sg:postcode":"2160",
    "sg:province":"Antwerpen",
    "wof:name":"Dreumex",
    "wof:placetype":"venue"
},
  "geometry": {"coordinates":[4.521736145,51.2014045715],"type":"Point"}
}