{
  "type": "Feature",
  "properties": {
    "iso:country":"BE",
    "sg:address":"Lange Leemstraat 144c Box 14",
    "sg:city":"Antwerpen",
    "sg:classifiers":[
        {
            "category":"Professional",
            "subcategory":"Art Services",
            "type":"Services"
        }
    ],
    "sg:phone":"+32 3 218 90 68",
    "sg:postcode":"2018",
    "sg:province":"Antwerpen",
    "sg:tags":[
        "interior",
        "designer"
    ],
    "wof:name":"Pelckmans & Watrin Cvba",
    "wof:placetype":"venue"
},
  "geometry": {"coordinates":[4.415473938,51.2065544128],"type":"Point"}
}