{
  "type": "Feature",
  "properties": {
    "iso:country":"BE",
    "sg:address":"Grote Markt 22",
    "sg:city":"Kortrijk",
    "sg:orig_category":"Mobistar Centres Telecommunicatieapparaten",
    "sg:phone":"+32 56 25 36 00",
    "sg:postcode":"8500",
    "sg:province":"West-Vlaanderen",
    "wof:name":"Mobistar Center Investeco",
    "wof:placetype":"venue"
},
  "geometry": {"coordinates":[3.2669119835,50.827545166],"type":"Point"}
}