{
  "type": "Feature",
  "properties": {
    "addr:full":"Dr\u00e8ve De Nivelles 178 Bruxelles (auderghem) Bruxelles-Capitale 1160",
    "addr:housenumber":"178",
    "addr:postcode":"1160",
    "addr:street":"Dre\u0300Ve De Nivelles",
    "iso:country":"BE",
    "sg:address":"Dr\u00e8ve De Nivelles 178",
    "sg:city":"Bruxelles (auderghem)",
    "sg:classifiers":[
        {
            "category":"Health Services",
            "subcategory":"Health Practitioner",
            "type":"Services"
        }
    ],
    "sg:phone":"+32 2 673 01 10",
    "sg:postcode":"1160",
    "sg:province":"Bruxelles-Capitale",
    "sg:tags":[
        "physiotherapist"
    ],
    "wof:name":"Roels Pierre",
    "wof:placetype":"venue"
},
  "geometry": {"coordinates":[4.4251499176,50.8167381287],"type":"Point"}
}