{
  "type": "Feature",
  "properties": {
    "addr:full":"Rue Du G\u00e9n\u00e9ral De Gaulle 92 Courcelles Hainaut 6180",
    "addr:housenumber":"92",
    "addr:postcode":"6180",
    "addr:street":"Rue Du Ge\u0301Ne\u0301Ral De Gaulle",
    "iso:country":"BE",
    "sg:address":"Rue Du G\u00e9n\u00e9ral De Gaulle 92",
    "sg:city":"Courcelles",
    "sg:classifiers":[
        {
            "category":"Personal",
            "subcategory":"Beauty Salon",
            "type":"Services"
        }
    ],
    "sg:phone":"+32 71 45 70 03",
    "sg:postcode":"6180",
    "sg:province":"Hainaut",
    "sg:tags":[
        "lady",
        "-",
        "hairdressing"
    ],
    "wof:name":"Mario Coiffure",
    "wof:placetype":"venue"
},
  "geometry": {"coordinates":[4.3805480003,50.4573287964],"type":"Point"}
}