{
  "type": "Feature",
  "properties": {
    "iso:country":"BE",
    "sg:address":"Commelo 11",
    "sg:city":"Beringen",
    "sg:classifiers":[
        {
            "category":"Arena",
            "subcategory":"Sports Club",
            "type":"Entertainment"
        }
    ],
    "sg:phone":"+32 11 45 32 57",
    "sg:postcode":"3580",
    "sg:province":"Limburg",
    "wof:name":"Kanaal Sportcentrum ('t)",
    "wof:placetype":"venue"
},
  "geometry": {"coordinates":[5.2145180702,51.0467224121],"type":"Point"}
}