{
  "type": "Feature",
  "properties": {
    "addr:full":"Rue Du Crucifix 8 Huy Li\u00e8ge 4500",
    "addr:housenumber":"8",
    "addr:postcode":"4500",
    "addr:street":"Rue Du Crucifix",
    "iso:country":"BE",
    "sg:address":"Rue Du Crucifix 8",
    "sg:city":"Huy",
    "sg:orig_category":"Jardinage",
    "sg:phone":"+32 85 23 55 83",
    "sg:postcode":"4500",
    "sg:province":"Li\u00e8ge",
    "wof:name":"Jean-pierre Delvaux",
    "wof:placetype":"venue"
},
  "geometry": {"coordinates":[5.1921591759,50.4835357666],"type":"Point"}
}