{
  "type": "Feature",
  "properties": {
    "iso:country":"BE",
    "sg:address":"Avenue Thiriar 15",
    "sg:city":"Bruxelles",
    "sg:classifiers":[
        {
            "category":"Manufacturing",
            "subcategory":"Tools & Machinery",
            "type":"Manufacturing & Wholesale Goods"
        }
    ],
    "sg:phone":"+32 2 478 04 17",
    "sg:postcode":"1020",
    "sg:province":"Bruxelles-Capitale",
    "sg:tags":[
        "thermometer"
    ],
    "wof:name":"Lemaire J-p Sa",
    "wof:placetype":"venue"
},
  "geometry": {"coordinates":[4.3278770447,50.892780304],"type":"Point"}
}