{
  "type": "Feature",
  "properties": {
    "iso:country":"BE",
    "sg:address":"Kamstraat 64",
    "sg:city":"Sint-pieters-leeuw",
    "sg:orig_category":"Fotogravure and zetwerk Secretariaatsdiensten",
    "sg:phone":"+32 2 532 16 15",
    "sg:postcode":"1602",
    "sg:province":"Vlaams-Brabant",
    "wof:name":"Visual Action Montage",
    "wof:placetype":"venue"
},
  "geometry": {"coordinates":[4.2297501564,50.8068389893],"type":"Point"}
}