{
  "type": "Feature",
  "properties": {
    "iso:country":"BE",
    "sg:address":"Centre Kennedy",
    "sg:city":"Li\u00e8ge 1",
    "sg:classifiers":[
        {
            "category":"Health Services",
            "subcategory":"Doctor",
            "type":"Services"
        }
    ],
    "sg:phone":"+32 4 223 48 69",
    "sg:postcode":"4000",
    "sg:province":"Li\u00e8ge",
    "sg:tags":[
        "medicinephysicians",
        "surgeon"
    ],
    "wof:name":"Gernay Jean-marie",
    "wof:placetype":"venue"
},
  "geometry": {"coordinates":[5.6854248047,50.6139297485],"type":"Point"}
}