{
  "type": "Feature",
  "properties": {
    "iso:country":"BE",
    "sg:address":"Oostakkerdorp 4",
    "sg:city":"Gent",
    "sg:classifiers":[
        {
            "category":"Cafe",
            "type":"Food & Drink"
        }
    ],
    "sg:phone":"+32 9 259 13 59",
    "sg:postcode":"9041",
    "sg:province":"Oost-Vlaanderen",
    "sg:tags":[
        "caf\u00e9s"
    ],
    "wof:name":"Eddy Peirsman",
    "wof:placetype":"venue"
},
  "geometry": {"coordinates":[3.7646028996,51.0998077393],"type":"Point"}
}