{
  "type": "Feature",
  "properties": {
    "iso:country":"BE",
    "sg:address":"Rue De Boughors 13",
    "sg:city":"Honnelles",
    "sg:classifiers":[
        {
            "category":"Food & Beverages",
            "subcategory":"Chocolate",
            "type":"Retail Goods"
        }
    ],
    "sg:phone":"+32 65 75 95 21",
    "sg:postcode":"7387",
    "sg:province":"Hainaut",
    "sg:tags":[
        "candy"
    ],
    "wof:name":"Chocolaterie Druart S.a.",
    "wof:placetype":"venue"
},
  "geometry": {"coordinates":[3.685475111,50.3532867432],"type":"Point"}
}