{
  "type": "Feature",
  "properties": {
    "iso:country":"BE",
    "sg:address":"Vestingstraat 33",
    "sg:city":"Antwerpen",
    "sg:classifiers":[
        {
            "category":"Transit Center",
            "subcategory":"Freight",
            "type":"Transportation"
        }
    ],
    "sg:phone":"+32 3 213 98 40",
    "sg:postcode":"2018",
    "sg:province":"Antwerpen",
    "sg:tags":[
        "import",
        "export",
        "-"
    ],
    "wof:name":"Transmare-antwerpen Nv",
    "wof:placetype":"venue"
},
  "geometry": {"coordinates":[4.4189581871,51.2167053223],"type":"Point"}
}