{
  "type": "Feature",
  "properties": {
    "iso:country":"BE",
    "sg:address":"Rue Edith Cavell 32",
    "sg:city":"Ukkel/uccle",
    "sg:orig_category":"Cliniques and h\u00f4pitaux. M\u00e9decins and sp\u00e9cialistes",
    "sg:phone":"+32 2 340 40 40",
    "sg:postcode":"1180",
    "sg:province":"Bruxelles-Capitale",
    "wof:name":"Institut M\u00c9dical Edith Cavell",
    "wof:placetype":"venue"
},
  "geometry": {"coordinates":[4.3565921783,50.8137283325],"type":"Point"}
}