{
  "type": "Feature",
  "properties": {
    "addr:full":"Kapellestraat 35 Wingene West-Vlaanderen 8750",
    "addr:housenumber":"35",
    "addr:postcode":"8750",
    "addr:street":"Kapellestraat",
    "iso:country":"BE",
    "sg:address":"Kapellestraat 35",
    "sg:city":"Wingene",
    "sg:orig_category":"Electrom\u00e9nager, t\u00e9l\u00e9visions and radios",
    "sg:phone":"+32 51 65 70 92",
    "sg:postcode":"8750",
    "sg:province":"West-Vlaanderen",
    "wof:name":"Guido Callens",
    "wof:placetype":"venue"
},
  "geometry": {"coordinates":[3.2788100243,51.0534553528],"type":"Point"}
}