{
  "type": "Feature",
  "properties": {
    "addr:full":"Weg Naar As 158c Genk Limburg 3600",
    "addr:housenumber":"158c",
    "addr:postcode":"3600",
    "addr:street":"Weg Naar As",
    "iso:country":"BE",
    "sg:address":"Weg Naar As 158c",
    "sg:city":"Genk",
    "sg:classifiers":[
        {
            "category":"Utilities",
            "subcategory":"Water",
            "type":"Services"
        }
    ],
    "sg:phone":"+32 89 36 24 40",
    "sg:postcode":"3600",
    "sg:province":"Limburg",
    "sg:tags":[
        "purification"
    ],
    "wof:name":"All-water Systems The Water Purifier",
    "wof:placetype":"venue"
},
  "geometry": {"coordinates":[5.5161161423,50.9722175598],"type":"Point"}
}