{
  "type": "Feature",
  "properties": {
    "iso:country":"BE",
    "sg:address":"Meensesteenweg 143-145",
    "sg:city":"Moorslede",
    "sg:orig_category":"Equipement photographique. Studios photographiques",
    "sg:phone":"+32 56 50 99 31",
    "sg:postcode":"8890",
    "sg:province":"West-Vlaanderen",
    "wof:name":"Foto Barbe",
    "wof:placetype":"venue"
},
  "geometry": {"coordinates":[3.1105289459,50.8500900269],"type":"Point"}
}