{
  "type": "Feature",
  "properties": {
    "iso:country":"BE",
    "sg:address":"Route De Philippeville 1",
    "sg:city":"Charleroi",
    "sg:orig_category":"Microsoft. Microsoft. Formation and enseignement. Ordinateurs and \u00e9quipement informatique",
    "sg:phone":"+32 71 27 02 61",
    "sg:postcode":"6010",
    "sg:province":"Hainaut",
    "wof:name":"Gil Informatique",
    "wof:placetype":"venue"
},
  "geometry": {"coordinates":[4.4576158524,50.3936157227],"type":"Point"}
}