{
  "type": "Feature",
  "properties": {
    "addr:full":"Kerkhofpad 8 Hoogstraten (minderhout) Antwerpen 2322",
    "addr:housenumber":"8",
    "addr:postcode":"2322",
    "addr:street":"Kerkhofpad",
    "iso:country":"BE",
    "sg:address":"Kerkhofpad 8",
    "sg:city":"Hoogstraten (minderhout)",
    "sg:classifiers":[
        {
            "category":"Building & Trades",
            "subcategory":"Construction",
            "type":"Services"
        }
    ],
    "sg:phone":"+32 3 314 99 96",
    "sg:postcode":"2322",
    "sg:province":"Antwerpen",
    "sg:tags":[
        "stucco",
        "contractor"
    ],
    "wof:name":"Brado Bvba",
    "wof:placetype":"venue"
},
  "geometry": {"coordinates":[4.763384819,51.4160041809],"type":"Point"}
}