{
  "type": "Feature",
  "properties": {
    "iso:country":"BE",
    "sg:address":"Deinzestraat 55 Box 2",
    "sg:city":"Oudenaarde",
    "sg:classifiers":[
        {
            "category":"Professional",
            "subcategory":"Lawyer & Legal Services",
            "type":"Services"
        }
    ],
    "sg:phone":"+32 55 31 55 91",
    "sg:postcode":"9700",
    "sg:province":"Oost-Vlaanderen",
    "wof:name":"Vancoillie Sylvie",
    "wof:placetype":"venue"
},
  "geometry": {"coordinates":[3.5939919949,50.8534660339],"type":"Point"}
}