{
  "type": "Feature",
  "properties": {
    "addr:full":"Rue Eeckelaers 23 Bruxelles (saint-josse-ten-noode) Bruxelles-Capitale 1210",
    "addr:housenumber":"23",
    "addr:postcode":"1210",
    "addr:street":"Rue Eeckelaers",
    "iso:country":"BE",
    "sg:address":"Rue Eeckelaers 23",
    "sg:city":"Bruxelles (saint-josse-ten-noode)",
    "sg:classifiers":[
        {
            "category":"Communications",
            "type":"Services"
        }
    ],
    "sg:phone":"+32 2 732 10 28",
    "sg:postcode":"1210",
    "sg:province":"Bruxelles-Capitale",
    "sg:tags":[
        "translator"
    ],
    "wof:name":"Davison M-a",
    "wof:placetype":"venue"
},
  "geometry": {"coordinates":[4.3822951317,50.8514709473],"type":"Point"}
}