{
  "type": "Feature",
  "properties": {
    "iso:country":"BE",
    "sg:address":"Rue Louvetain 40",
    "sg:city":"Esneux",
    "sg:classifiers":[
        {
            "category":"Professional",
            "subcategory":"Accounting & Tax Preparation",
            "type":"Services"
        }
    ],
    "sg:phone":"+32 4 388 26 04",
    "sg:postcode":"4130",
    "sg:province":"Li\u00e8ge",
    "sg:tags":[
        "accountant"
    ],
    "wof:name":"Rapha\u00cbl Corvilain",
    "wof:placetype":"venue"
},
  "geometry": {"coordinates":[5.5669360161,50.5327568054],"type":"Point"}
}