{
  "type": "Feature",
  "properties": {
    "addr:full":"Riddersstraat 265 Leuven Vlaams-Brabant 3000",
    "addr:housenumber":"265",
    "addr:postcode":"3000",
    "addr:street":"Riddersstraat",
    "iso:country":"BE",
    "sg:address":"Riddersstraat 265",
    "sg:city":"Leuven",
    "sg:classifiers":[
        {
            "category":"Retail",
            "subcategory":"Animal Services",
            "type":"Services"
        }
    ],
    "sg:phone":"+32 16 20 29 48",
    "sg:postcode":"3000",
    "sg:province":"Vlaams-Brabant",
    "sg:tags":[
        "grooming",
        "-",
        "dog"
    ],
    "wof:name":"Keffer (de)",
    "wof:placetype":"venue"
},
  "geometry": {"coordinates":[4.6957740784,50.8868904114],"type":"Point"}
}