{
  "type": "Feature",
  "properties": {
    "iso:country":"BE",
    "sg:address":"Wespelaarsesteenweg 31",
    "sg:city":"Haacht",
    "sg:orig_category":"Film-, tv- and videoproductie",
    "sg:phone":"+32 16 60 04 48",
    "sg:postcode":"3150",
    "sg:province":"Vlaams-Brabant",
    "wof:name":"Joan De Pauw",
    "wof:placetype":"venue"
},
  "geometry": {"coordinates":[4.6379108429,50.9738578796],"type":"Point"}
}