{
  "type": "Feature",
  "properties": {
    "iso:country":"BE",
    "sg:address":"Rue Fromenteau 24b26",
    "sg:city":"Chimay",
    "sg:orig_category":"Maatschappelijke dienstverlening",
    "sg:phone":"+32 60 21 14 05",
    "sg:postcode":"6460",
    "sg:province":"Hainaut",
    "wof:name":"Centre P.m.s.",
    "wof:placetype":"venue"
},
  "geometry": {"coordinates":[4.3156428337,50.0496520996],"type":"Point"}
}