{
  "type": "Feature",
  "properties": {
    "iso:country":"BE",
    "sg:address":"Ch. De Bruxelles 688",
    "sg:city":"Waterloo",
    "sg:orig_category":"Benzinestations and brandstoffen Telecommunicatieapparaten",
    "sg:phone":"+32 2 387 04 97",
    "sg:postcode":"1410",
    "sg:province":"Brabant Wallon",
    "wof:name":"A C S",
    "wof:placetype":"venue"
},
  "geometry": {"coordinates":[4.4043998718,50.6932296753],"type":"Point"}
}