{
  "type": "Feature",
  "properties": {
    "iso:country":"BE",
    "sg:address":"Hansadok Oostkaai 234kaai",
    "sg:city":"Antwerpen",
    "sg:classifiers":[
        {
            "category":"Food & Beverages",
            "subcategory":"Fruits & Vegetables",
            "type":"Retail Goods"
        }
    ],
    "sg:phone":"+32 3 541 24 55",
    "sg:postcode":"2030",
    "sg:province":"Antwerpen",
    "sg:tags":[
        "export",
        "-",
        "import"
    ],
    "wof:name":"Dole Fresh Fruit Europe",
    "wof:placetype":"venue"
},
  "geometry": {"coordinates":[4.4089899063,51.2353897095],"type":"Point"}
}