{
  "type": "Feature",
  "properties": {
    "iso:country":"BE",
    "sg:address":"Terenburgseweg 15",
    "sg:city":"Poperinge",
    "sg:orig_category":"Eleveurs and marchands de porcs. Eleveurs de bovins",
    "sg:phone":"+32 57 30 11 67",
    "sg:postcode":"8972",
    "sg:province":"West-Vlaanderen",
    "wof:name":"Pol Verhaeghe",
    "wof:placetype":"venue"
},
  "geometry": {"coordinates":[2.6395618916,50.8859062195],"type":"Point"}
}