{
  "type": "Feature",
  "properties": {
    "iso:country":"BE",
    "sg:address":"Rue Des Flaches 99",
    "sg:city":"Gerpinnes",
    "sg:classifiers":[
        {
            "category":"Personal",
            "subcategory":"Beauty Salon",
            "type":"Services"
        }
    ],
    "sg:phone":"+32 71 50 20 35",
    "sg:postcode":"6280",
    "sg:province":"Hainaut",
    "sg:tags":[
        "lady",
        "-",
        "hairdressing"
    ],
    "wof:name":"Rodelet",
    "wof:placetype":"venue"
},
  "geometry": {"coordinates":[4.5029101372,50.3350791931],"type":"Point"}
}