{
  "type": "Feature",
  "properties": {
    "iso:country":"BE",
    "sg:address":"Gen. Baron Jacquesstraat 27",
    "sg:city":"Diksmuide",
    "sg:orig_category":"Artsen and specialisten",
    "sg:phone":"+32 51 50 35 04",
    "sg:postcode":"8600",
    "sg:province":"West-Vlaanderen",
    "wof:name":"Els Wittouck",
    "wof:placetype":"venue"
},
  "geometry": {"coordinates":[2.8619740009,51.0335922241],"type":"Point"}
}