{
  "type": "Feature",
  "properties": {
    "iso:country":"BE",
    "sg:address":"Artanlaan 2",
    "sg:city":"Nieuwpoort",
    "sg:classifiers":[
        {
            "category":"Professional",
            "subcategory":"Accounting & Tax Preparation",
            "type":"Services"
        }
    ],
    "sg:phone":"+32 58 23 26 60",
    "sg:postcode":"8620",
    "sg:province":"West-Vlaanderen",
    "sg:tags":[
        "bookkeeper"
    ],
    "wof:name":"Neuville Bvba",
    "wof:placetype":"venue"
},
  "geometry": {"coordinates":[2.7220299244,51.1479988098],"type":"Point"}
}