{
  "type": "Feature",
  "properties": {
    "addr:full":"Rue G\u00c9n\u00c9ral De Gaulle 62 Terhulpen Brabant Wallon 1310",
    "addr:housenumber":"62;1310",
    "addr:street":"Rue Ge\u0301Ne\u0301Ral De Gaulle;Brabant Wallon",
    "iso:country":"BE",
    "sg:address":"Rue G\u00c9n\u00c9ral De Gaulle 62",
    "sg:city":"Terhulpen",
    "sg:orig_category":"Produits chimiques Gr",
    "sg:phone":"+32 2 655 21 11",
    "sg:postcode":"1310",
    "sg:province":"Brabant Wallon",
    "wof:name":"Dow Corning Europe",
    "wof:placetype":"venue"
},
  "geometry": {"coordinates":[4.4877500534,50.7353286743],"type":"Point"}
}