{
  "type": "Feature",
  "properties": {
    "iso:country":"BE",
    "sg:address":"Rue Castiau 12c",
    "sg:city":"P\u00e9ruwelz",
    "sg:classifiers":[
        {
            "category":"Personal",
            "subcategory":"Nail Salon",
            "type":"Services"
        }
    ],
    "sg:phone":"+32 69 77 46 94",
    "sg:postcode":"7600",
    "sg:province":"Hainaut",
    "sg:tags":[
        "pedicure"
    ],
    "wof:name":"Cuvelier Catherine",
    "wof:placetype":"venue"
},
  "geometry": {"coordinates":[3.6027190685,50.5103149414],"type":"Point"}
}