{
  "type": "Feature",
  "properties": {
    "addr:full":"'s Gravenstraat 197 Nazareth Oost-Vlaanderen 9810",
    "addr:housenumber":"197",
    "addr:postcode":"9810",
    "addr:street":"' S Gravenstraat",
    "iso:country":"BE",
    "sg:address":"'s Gravenstraat 197",
    "sg:city":"Nazareth",
    "sg:classifiers":[
        {
            "category":"Transit Center",
            "subcategory":"Passenger",
            "type":"Transportation"
        }
    ],
    "sg:phone":"+32 9 385 93 90",
    "sg:postcode":"9810",
    "sg:province":"Oost-Vlaanderen",
    "sg:tags":[
        "car",
        "trailer"
    ],
    "wof:name":"Weytens Aanhangwagens",
    "wof:placetype":"venue"
},
  "geometry": {"coordinates":[3.5932030678,50.9485549927],"type":"Point"}
}