{
  "type": "Feature",
  "properties": {
    "addr:full":"Rue Foss\u00c9 Botton 19 Juprelle Li\u00e8ge 4458",
    "addr:housenumber":"19",
    "addr:postcode":"4458",
    "addr:street":"Rue Fosse\u0301 Botton",
    "iso:country":"BE",
    "sg:address":"Rue Foss\u00c9 Botton 19",
    "sg:city":"Juprelle",
    "sg:orig_category":"Rusthuizen and serviceflats",
    "sg:phone":"+32 4 278 20 24",
    "sg:postcode":"4458",
    "sg:province":"Li\u00e8ge",
    "wof:name":"Home Farnientane",
    "wof:placetype":"venue"
},
  "geometry": {"coordinates":[5.5757660866,50.715637207],"type":"Point"}
}