{
  "type": "Feature",
  "properties": {
    "addr:full":"Rue De Soignies 18 Ath Hainaut 7800",
    "addr:housenumber":"18",
    "addr:postcode":"7800",
    "addr:street":"Rue De Soignies",
    "iso:country":"BE",
    "sg:address":"Rue De Soignies 18",
    "sg:city":"Ath",
    "sg:classifiers":[
        {
            "category":"Autos & Motor Vehicles",
            "subcategory":"Auto Supplies",
            "type":"Retail Goods"
        }
    ],
    "sg:phone":"+32 68 28 16 55",
    "sg:postcode":"7800",
    "sg:province":"Hainaut",
    "sg:tags":[
        "access",
        "automobile",
        "part",
        "-"
    ],
    "wof:name":"Api-bevernagie Sa",
    "wof:placetype":"venue"
},
  "geometry": {"coordinates":[3.7872440815,50.6308288574],"type":"Point"}
}