{
  "type": "Feature",
  "properties": {
    "addr:full":"Boulevard De Smet De Nayer 0 Jette Bruxelles-Capitale 1090",
    "addr:housenumber":"0",
    "addr:postcode":"1090",
    "addr:street":"Boulevard De Smet De Nayer",
    "iso:country":"BE",
    "sg:address":"Boulevard De Smet De Nayer 0",
    "sg:city":"Jette",
    "sg:orig_category":"Sportterreinen and installaties behalve sportcentra",
    "sg:phone":"+32 2 478 12 87",
    "sg:postcode":"1090",
    "sg:province":"Bruxelles-Capitale",
    "wof:name":"Parc De La Jeunesse",
    "wof:placetype":"venue"
},
  "geometry": {"coordinates":[4.3375182152,50.8843193054],"type":"Point"}
}