{
  "type": "Feature",
  "properties": {
    "iso:country":"BE",
    "sg:address":"Rue Chapelle Beaussart 59",
    "sg:city":"Charleroi",
    "sg:classifiers":[
        {
            "category":"Insurance",
            "subcategory":"Life Insurance",
            "type":"Services"
        }
    ],
    "sg:phone":"+32 71 47 32 59",
    "sg:postcode":"6032",
    "sg:province":"Hainaut",
    "sg:tags":[
        "assurance"
    ],
    "wof:name":"Bernard G.",
    "wof:placetype":"venue"
},
  "geometry": {"coordinates":[4.4146809578,50.4047546387],"type":"Point"}
}