{
  "type": "Feature",
  "properties": {
    "addr:full":"Rue Fernand-neuray 36 Etalle Luxembourg 6740",
    "addr:housenumber":"36",
    "addr:postcode":"6740",
    "addr:street":"Rue Fernand-Neuray",
    "iso:country":"BE",
    "sg:address":"Rue Fernand-neuray 36",
    "sg:city":"Etalle",
    "sg:orig_category":"Enseignement maternel and primaire",
    "sg:phone":"+32 63 45 62 10",
    "sg:postcode":"6740",
    "sg:province":"Luxembourg",
    "wof:name":"Ecole Fond. Communale",
    "wof:placetype":"venue"
},
  "geometry": {"coordinates":[5.6032891273,49.672039032],"type":"Point"}
}