{
  "type": "Feature",
  "properties": {
    "iso:country":"BE",
    "sg:address":"Onze Lieve Vrouwestraat 3",
    "sg:city":"Oostrozebeke",
    "sg:orig_category":"Jardinage. D\u00e9corateurs d'int\u00e9rieur. Forge, Moulage and Profilage des M\u00e9taux",
    "sg:phone":"+32 56 66 23 61",
    "sg:postcode":"8780",
    "sg:province":"West-Vlaanderen",
    "wof:name":"Dujardyn Artconcept",
    "wof:placetype":"venue"
},
  "geometry": {"coordinates":[3.3468799591,50.9259490967],"type":"Point"}
}