{
  "type": "Feature",
  "properties": {
    "addr:full":"Markeplaats 2 Kortrijk West-Vlaanderen 8510",
    "addr:housenumber":"2",
    "addr:postcode":"8510",
    "addr:street":"Markeplaats",
    "iso:country":"BE",
    "sg:address":"Markeplaats 2",
    "sg:city":"Kortrijk",
    "sg:orig_category":"Banques and organismes de cr\u00e9dit",
    "sg:phone":"+32 56 22 05 75",
    "sg:postcode":"8510",
    "sg:province":"West-Vlaanderen",
    "wof:name":"Bacob",
    "wof:placetype":"venue"
},
  "geometry": {"coordinates":[3.2333650589,50.8071060181],"type":"Point"}
}