{
  "type": "Feature",
  "properties": {
    "addr:full":"Heiligenborre 5 Watermaal-bosvoorde/watermael-boitsfort Bruxelles-Capitale 1170",
    "addr:housenumber":"5",
    "addr:postcode":"1170",
    "addr:street":"Heiligenborre",
    "iso:country":"BE",
    "sg:address":"Heiligenborre 5",
    "sg:city":"Watermaal-bosvoorde/watermael-boitsfort",
    "sg:orig_category":"Woningbouw",
    "sg:phone":"+32 2 675 32 91",
    "sg:postcode":"1170",
    "sg:province":"Bruxelles-Capitale",
    "wof:name":"Henri Fischer",
    "wof:placetype":"venue"
},
  "geometry": {"coordinates":[4.4217967987,50.7905960083],"type":"Point"}
}