{
  "type": "Feature",
  "properties": {
    "iso:country":"BE",
    "sg:address":"Bergstrasse 26",
    "sg:city":"Eupen/eupen",
    "sg:orig_category":"Kapsalons",
    "sg:phone":"+32 87 74 49 54",
    "sg:postcode":"4700",
    "sg:province":"Li\u00e8ge",
    "wof:name":"Corda Cr\u00c9ation Coiffure",
    "wof:placetype":"venue"
},
  "geometry": {"coordinates":[6.0338320732,50.6293678284],"type":"Point"}
}