{
  "type": "Feature",
  "properties": {
    "iso:country":"BE",
    "sg:address":"Peperstraat 48",
    "sg:city":"Schelle",
    "sg:orig_category":"Mus\u00e9es and patrimoine culturel",
    "sg:phone":"+32 3 887 47 96",
    "sg:postcode":"2627",
    "sg:province":"Antwerpen",
    "wof:name":"Heenmuseum Bysterveld",
    "wof:placetype":"venue"
},
  "geometry": {"coordinates":[4.3340530396,51.1264915466],"type":"Point"}
}