{
  "type": "Feature",
  "properties": {
    "addr:full":"Avenue Des Nymphes 27 Bruxelles (watermael-boitsfort) Bruxelles-Capitale 1170",
    "addr:housenumber":"27",
    "addr:postcode":"1170",
    "addr:street":"Avenue Des Nymphes",
    "iso:country":"BE",
    "sg:address":"Avenue Des Nymphes 27",
    "sg:city":"Bruxelles (watermael-boitsfort)",
    "sg:orig_category":"Fiduciairies",
    "sg:phone":"+32 2 673 37 38",
    "sg:postcode":"1170",
    "sg:province":"Bruxelles-Capitale",
    "wof:name":"Fiduciaire Vdh Sprl",
    "wof:placetype":"venue"
},
  "geometry": {"coordinates":[4.4144868851,50.8053627014],"type":"Point"}
}