{
  "type": "Feature",
  "properties": {
    "addr:full":"Kleine Langeheidestraat 10 Huldenberg (ottenburg) Vlaams-Brabant 3040",
    "addr:housenumber":"10",
    "addr:postcode":"3040",
    "addr:street":"Langeheidestraat",
    "iso:country":"BE",
    "sg:address":"Kleine Langeheidestraat 10",
    "sg:city":"Huldenberg (ottenburg)",
    "sg:classifiers":[
        {
            "category":"Communications",
            "subcategory":"Film & Video Production",
            "type":"Services"
        }
    ],
    "sg:phone":"+32 16 47 31 13",
    "sg:postcode":"3040",
    "sg:province":"Vlaams-Brabant",
    "sg:tags":[
        "producer",
        "realizators"
    ],
    "wof:name":"Trots Bvba",
    "wof:placetype":"venue"
},
  "geometry": {"coordinates":[4.6292409897,50.7519989014],"type":"Point"}
}