{
  "type": "Feature",
  "properties": {
    "addr:full":"Lion D\u00b4orweg 23 Aalst Oost-Vlaanderen 9300",
    "addr:housenumber":"23",
    "addr:postcode":"9300",
    "iso:country":"BE",
    "sg:address":"Lion D\u00b4orweg 23",
    "sg:city":"Aalst",
    "sg:orig_category":"Entretien and r\u00e9parations de voitures",
    "sg:phone":"+32 53 21 51 45",
    "sg:postcode":"9300",
    "sg:province":"Oost-Vlaanderen",
    "wof:name":"Carrosserie Union Car",
    "wof:placetype":"venue"
},
  "geometry": {"coordinates":[4.039080143,50.9544906616],"type":"Point"}
}