{
  "type": "Feature",
  "properties": {
    "addr:full":"Rue De Bomer\u00e9e 289 Montigny-le-tilleul Hainaut 6110",
    "addr:housenumber":"289",
    "addr:postcode":"6110",
    "addr:street":"Rue De Bomere\u0301E",
    "iso:country":"BE",
    "sg:address":"Rue De Bomer\u00e9e 289",
    "sg:city":"Montigny-le-tilleul",
    "sg:classifiers":[
        {
            "category":"Health Services",
            "subcategory":"Health Practitioner",
            "type":"Services"
        }
    ],
    "sg:phone":"+32 71 51 23 27",
    "sg:postcode":"6110",
    "sg:province":"Hainaut",
    "sg:tags":[
        "physiotherapist"
    ],
    "wof:name":"Vandercam V",
    "wof:placetype":"venue"
},
  "geometry": {"coordinates":[4.3920249939,50.3595619202],"type":"Point"}
}