{
  "type": "Feature",
  "properties": {
    "iso:country":"BE",
    "sg:address":"Rue Du Pousserou 12",
    "sg:city":"Wanze (vinalmont)",
    "sg:classifiers":[
        {
            "category":"Farming",
            "subcategory":"Farm & Veterinary Services",
            "type":"Manufacturing & Wholesale Goods"
        }
    ],
    "sg:phone":"+32 85 23 44 39",
    "sg:postcode":"4520",
    "sg:province":"Li\u00e8ge",
    "sg:tags":[
        "agricultural",
        "contractor"
    ],
    "wof:name":"Agripeeters",
    "wof:placetype":"venue"
},
  "geometry": {"coordinates":[5.2137088776,50.5650482178],"type":"Point"}
}