{
  "type": "Feature",
  "properties": {
    "addr:full":"Van Elewyckstraat 35 Elsene/ixelles Bruxelles-Capitale 1050",
    "addr:housenumber":"35",
    "addr:postcode":"1050",
    "addr:street":"Van Elewyckstraat",
    "iso:country":"BE",
    "sg:address":"Van Elewyckstraat 35",
    "sg:city":"Elsene/ixelles",
    "sg:orig_category":"Diverse organisaties and verenigingen",
    "sg:phone":"+32 2 649 07 38",
    "sg:postcode":"1050",
    "sg:province":"Bruxelles-Capitale",
    "wof:name":"Service Civil International",
    "wof:placetype":"venue"
},
  "geometry": {"coordinates":[4.3692178726,50.8282203674],"type":"Point"}
}