{
  "type": "Feature",
  "properties": {
    "addr:full":"Kruisstraat 77 Tremelo Vlaams-Brabant 3120",
    "addr:housenumber":"77",
    "addr:postcode":"3120",
    "addr:street":"Kruisstraat",
    "iso:country":"BE",
    "sg:address":"Kruisstraat 77",
    "sg:city":"Tremelo",
    "sg:orig_category":"Fotografen and fotostudio's",
    "sg:phone":"+32 16 53 56 06",
    "sg:postcode":"3120",
    "sg:province":"Vlaams-Brabant",
    "wof:name":"Dirk Vertommen",
    "wof:placetype":"venue"
},
  "geometry": {"coordinates":[4.6974110603,50.9947776794],"type":"Point"}
}