{
  "type": "Feature",
  "properties": {
    "addr:full":"Rue Mareyde 56 Sint-pieters-woluwe/woluwe-saint-pierre Bruxelles-Capitale 1150",
    "addr:housenumber":"56",
    "addr:postcode":"1150",
    "addr:street":"Rue Mareyde;/",
    "iso:country":"BE",
    "sg:address":"Rue Mareyde 56",
    "sg:city":"Sint-pieters-woluwe/woluwe-saint-pierre",
    "sg:orig_category":"Artistes ind\u00e9pendants",
    "sg:phone":"+32 2 771 83 10",
    "sg:postcode":"1150",
    "sg:province":"Bruxelles-Capitale",
    "wof:name":"Leo Kockaert",
    "wof:placetype":"venue"
},
  "geometry": {"coordinates":[4.4490919113,50.8301620483],"type":"Point"}
}