{
  "type": "Feature",
  "properties": {
    "addr:full":"Stenedorpstraat 12 Oostende (stene) West-Vlaanderen 8400",
    "addr:housenumber":"12",
    "addr:postcode":"8400",
    "addr:street":"Stenedorpstraat",
    "iso:country":"BE",
    "sg:address":"Stenedorpstraat 12",
    "sg:city":"Oostende (stene)",
    "sg:classifiers":[
        {
            "category":"Building & Trades",
            "subcategory":"Plumbing",
            "type":"Services"
        }
    ],
    "sg:phone":"+32 59 80 91 75",
    "sg:postcode":"8400",
    "sg:province":"West-Vlaanderen",
    "sg:tags":[
        "repair",
        "mainten",
        "-",
        "central",
        "heating"
    ],
    "wof:name":"Dipa",
    "wof:placetype":"venue"
},
  "geometry": {"coordinates":[2.9126999378,51.2312583923],"type":"Point"}
}