{
  "type": "Feature",
  "properties": {
    "addr:full":"Mangelaarstraat 23 Langemark-poelkapelle West-Vlaanderen 8920",
    "addr:housenumber":"23",
    "addr:postcode":"8920",
    "addr:street":"Mangelaarstraat",
    "iso:country":"BE",
    "sg:address":"Mangelaarstraat 23",
    "sg:city":"Langemark-poelkapelle",
    "sg:orig_category":"Rundveehouders Varkenskwekers",
    "sg:phone":"+32 57 48 86 82",
    "sg:postcode":"8920",
    "sg:province":"West-Vlaanderen",
    "wof:name":"Roger Courtens",
    "wof:placetype":"venue"
},
  "geometry": {"coordinates":[2.919770956,50.9132423401],"type":"Point"}
}