{
  "type": "Feature",
  "properties": {
    "iso:country":"BE",
    "sg:address":"Hellestraat 2",
    "sg:city":"Wervik",
    "sg:orig_category":"Installation de menuiserie en bois and plastique",
    "sg:phone":"+32 56 31 49 39",
    "sg:postcode":"8940",
    "sg:province":"West-Vlaanderen",
    "wof:name":"Bourez",
    "wof:placetype":"venue"
},
  "geometry": {"coordinates":[3.0537860394,50.7815361023],"type":"Point"}
}