{
  "type": "Feature",
  "properties": {
    "addr:full":"Bredestraat 179 Putte (beerzel) Antwerpen 2580",
    "addr:housenumber":"179",
    "addr:postcode":"2580",
    "addr:street":"Bredestraat",
    "iso:country":"BE",
    "sg:address":"Bredestraat 179",
    "sg:city":"Putte (beerzel)",
    "sg:classifiers":[
        {
            "category":"Personal",
            "subcategory":"Beauty Salon",
            "type":"Services"
        }
    ],
    "sg:phone":"+32 15 75 32 15",
    "sg:postcode":"2580",
    "sg:province":"Antwerpen",
    "sg:tags":[
        "lady",
        "-",
        "hairdressing"
    ],
    "wof:name":"Knipsz",
    "wof:placetype":"venue"
},
  "geometry": {"coordinates":[4.6319699287,51.0603408813],"type":"Point"}
}