{
  "type": "Feature",
  "properties": {
    "iso:country":"BE",
    "sg:address":"Rue De Bertrix 1",
    "sg:city":"Paliseul",
    "sg:orig_category":"HUISBRANDOLIE",
    "sg:phone":"+32 61 53 34 30",
    "sg:postcode":"6850",
    "sg:province":"Luxembourg",
    "wof:name":"Emmanuel Nemery",
    "wof:placetype":"venue"
},
  "geometry": {"coordinates":[5.1349849701,49.9033889771],"type":"Point"}
}