{
  "type": "Feature",
  "properties": {
    "iso:country":"BE",
    "sg:address":"Rue Victor Heine 14",
    "sg:city":"Wanze",
    "sg:orig_category":"Dakwerken Herstelling aan huis van huishoudartikelen IJzerwaren, bouw- and verfmaterialen Loodgieter",
    "sg:phone":"+32 85 21 32 21",
    "sg:postcode":"4520",
    "sg:province":"Li\u00e8ge",
    "wof:name":"Roquet",
    "wof:placetype":"venue"
},
  "geometry": {"coordinates":[5.2257552147,50.5458908081],"type":"Point"}
}