{
  "type": "Feature",
  "properties": {
    "iso:country":"BE",
    "sg:address":"Jan Breydelstraat 18",
    "sg:city":"Harelbeke",
    "sg:classifiers":[
        {
            "category":"Health Services",
            "subcategory":"Doctor",
            "type":"Services"
        }
    ],
    "sg:phone":"+32 56 71 38 44",
    "sg:postcode":"8530",
    "sg:province":"West-Vlaanderen",
    "sg:tags":[
        "medicinephysicians",
        "surgeon"
    ],
    "wof:name":"De Smet Frans",
    "wof:placetype":"venue"
},
  "geometry": {"coordinates":[3.2989890575,50.8445892334],"type":"Point"}
}