{
  "type": "Feature",
  "properties": {
    "addr:full":"Ratmolenstraat 18 Erpe-mere Oost-Vlaanderen 9420",
    "addr:housenumber":"18",
    "addr:postcode":"9420",
    "addr:street":"Ratmolenstraat",
    "iso:country":"BE",
    "sg:address":"Ratmolenstraat 18",
    "sg:city":"Erpe-mere",
    "sg:orig_category":"Avocats and conseillers juridiques",
    "sg:phone":"+32 53 62 46 48",
    "sg:postcode":"9420",
    "sg:province":"Oost-Vlaanderen",
    "wof:name":"Peter Callebaut",
    "wof:placetype":"venue"
},
  "geometry": {"coordinates":[3.9355080128,50.8880195618],"type":"Point"}
}