{
  "type": "Feature",
  "properties": {
    "iso:country":"BE",
    "sg:address":"Leliestraat 28",
    "sg:city":"Sint Katelijne Waver",
    "sg:classifiers":[
        {
            "category":"Fast Food",
            "type":"Food & Drink"
        }
    ],
    "sg:phone":"+32 15 31 55 91",
    "sg:postcode":"2860",
    "sg:province":"Antwerpen",
    "sg:tags":[
        "\u00c0",
        "restaurants",
        "emporter",
        "restaurant"
    ],
    "wof:name":"Frituur De Lelie",
    "wof:placetype":"venue"
},
  "geometry": {"coordinates":[4.5386619568,51.0674667358],"type":"Point"}
}