{
  "type": "Feature",
  "properties": {
    "addr:full":"Groenestraat 3 Ieper West-Vlaanderen 8900",
    "addr:housenumber":"3",
    "addr:postcode":"8900",
    "addr:street":"Groenestraat",
    "iso:country":"BE",
    "sg:address":"Groenestraat 3",
    "sg:city":"Ieper",
    "sg:orig_category":"M\u00e9decins and sp\u00e9cialistes",
    "sg:phone":"+32 57 20 44 24",
    "sg:postcode":"8900",
    "sg:province":"West-Vlaanderen",
    "wof:name":"Annie Moeyaert",
    "wof:placetype":"venue"
},
  "geometry": {"coordinates":[2.9037110806,50.8653717041],"type":"Point"}
}