{
  "type": "Feature",
  "properties": {
    "addr:full":"Rue De La Papyr\u00e9e 2-4 Braine L'alleud (braine-l'alleud) Brabant Wallon 1420",
    "addr:housenumber":"2-4",
    "addr:postcode":"1420",
    "addr:street":"Rue De La Papyre\u0301E",
    "iso:country":"BE",
    "sg:address":"Rue De La Papyr\u00e9e 2-4",
    "sg:city":"Braine L'alleud (braine-l'alleud)",
    "sg:classifiers":[
        {
            "category":"Manufacturing",
            "subcategory":"Chemicals & Compounds",
            "type":"Manufacturing & Wholesale Goods"
        }
    ],
    "sg:phone":"+32 2 386 12 11",
    "sg:postcode":"1420",
    "sg:province":"Brabant Wallon",
    "sg:tags":[
        "pharmaceutical",
        "product"
    ],
    "wof:name":"Thissen Laboratoires Sa",
    "wof:placetype":"venue"
},
  "geometry": {"coordinates":[-75.60595703120001,37.7877616882],"type":"Point"}
}