{
  "type": "Feature",
  "properties": {
    "addr:full":"Guido Gezellestraat 55 Aartselaar Antwerpen 2630",
    "addr:housenumber":"55",
    "addr:postcode":"2630",
    "addr:street":"Guido Gezellestraat",
    "iso:country":"BE",
    "sg:address":"Guido Gezellestraat 55",
    "sg:city":"Aartselaar",
    "sg:classifiers":[
        {
            "category":"Health Services",
            "subcategory":"Doctor",
            "type":"Services"
        }
    ],
    "sg:phone":"+32 3 877 04 72",
    "sg:postcode":"2630",
    "sg:province":"Antwerpen",
    "sg:tags":[
        "medicinephysicians",
        "surgeon"
    ],
    "wof:name":"De Bock Veerle",
    "wof:placetype":"venue"
},
  "geometry": {"coordinates":[4.3828930855,51.1359710693],"type":"Point"}
}