{
  "type": "Feature",
  "properties": {
    "addr:full":"Rozenkranslaan 8 Genk Limburg 3600",
    "addr:housenumber":"8",
    "addr:postcode":"3600",
    "addr:street":"Rozenkranslaan",
    "iso:country":"BE",
    "sg:address":"Rozenkranslaan 8",
    "sg:city":"Genk",
    "sg:orig_category":"Opticiens",
    "sg:phone":"+32 89 36 40 87",
    "sg:postcode":"3600",
    "sg:province":"Limburg",
    "wof:name":"Optiek Scherpe Steen Iii",
    "wof:placetype":"venue"
},
  "geometry": {"coordinates":[5.4863419533,50.962638855],"type":"Point"}
}