{
  "type": "Feature",
  "properties": {
    "iso:country":"BE",
    "sg:address":"Ardooiesteenweg 116",
    "sg:city":"Roeselare",
    "sg:orig_category":"Kapsalons",
    "sg:phone":"+32 51 22 15 25",
    "sg:postcode":"8800",
    "sg:province":"West-Vlaanderen",
    "wof:name":"Xantippe",
    "wof:placetype":"venue"
},
  "geometry": {"coordinates":[3.1366970539,50.9507522583],"type":"Point"}
}