{
  "type": "Feature",
  "properties": {
    "iso:country":"BE",
    "sg:address":"Middelburgstraat 94",
    "sg:city":"Watermaal-bosvoorde/watermael-boitsfort",
    "sg:orig_category":"HERSTELLING ELEKTRISCHE HUISHOUDAPPARATEN Huishoudapparaten, televisies and radio's",
    "sg:phone":"+32 2 672 42 56",
    "sg:postcode":"1170",
    "sg:province":"Bruxelles-Capitale",
    "wof:name":"Mister Ifi",
    "wof:placetype":"venue"
},
  "geometry": {"coordinates":[4.4183931351,50.7948951721],"type":"Point"}
}