{
  "type": "Feature",
  "properties": {
    "addr:full":"Thierry De Renesselaan 5 Malle Antwerpen 2390",
    "addr:housenumber":"5",
    "addr:postcode":"2390",
    "addr:street":"Thierry De Renesselaan",
    "iso:country":"BE",
    "sg:address":"Thierry De Renesselaan 5",
    "sg:city":"Malle",
    "sg:orig_category":"Plomberie, chauffage and installations sanitaires. Installation \u00e9lectrique r\u00e9sidentielle",
    "sg:phone":"+32 3 309 09 88",
    "sg:postcode":"2390",
    "sg:province":"Antwerpen",
    "wof:name":"Verma",
    "wof:placetype":"venue"
},
  "geometry": {"coordinates":[4.7251238823,51.3033256531],"type":"Point"}
}