{
  "type": "Feature",
  "properties": {
    "iso:country":"BE",
    "sg:address":"Rue De Sart Dames Avelines",
    "sg:city":"Les Bons Villers (frasnes-lez-gosselies)",
    "sg:classifiers":[
        {
            "category":"Retail",
            "subcategory":"Auto Repair",
            "type":"Services"
        }
    ],
    "sg:postcode":"6210",
    "sg:province":"Hainaut",
    "sg:tags":[
        "automobile",
        "-",
        "wrecking"
    ],
    "wof:name":"Autos 21 D\u00e9molition",
    "wof:placetype":"venue"
},
  "geometry": {"coordinates":[4.4511561394,50.5378227234],"type":"Point"}
}