{
  "type": "Feature",
  "properties": {
    "addr:full":"Oostbroekstraat 4 Houthulst West-Vlaanderen 8650",
    "addr:housenumber":"4",
    "addr:postcode":"8650",
    "addr:street":"Oostbroekstraat",
    "iso:country":"BE",
    "sg:address":"Oostbroekstraat 4",
    "sg:city":"Houthulst",
    "sg:orig_category":"Eleveurs and marchands de porcs",
    "sg:phone":"+32 51 54 43 66",
    "sg:postcode":"8650",
    "sg:province":"West-Vlaanderen",
    "wof:name":"Rene Vanassche",
    "wof:placetype":"venue"
},
  "geometry": {"coordinates":[2.9509439468,50.9778862],"type":"Point"}
}