{
  "type": "Feature",
  "properties": {
    "iso:country":"BE",
    "sg:address":"Veldstraat 14 Box 7",
    "sg:city":"Knesselare",
    "sg:classifiers":[
        {
            "category":"Health Services",
            "subcategory":"Nursing And Care Facility",
            "type":"Services"
        }
    ],
    "sg:phone":"+32 9 375 36 38",
    "sg:postcode":"9910",
    "sg:province":"Oost-Vlaanderen",
    "sg:tags":[
        "home"
    ],
    "wof:name":"Nemegeer K",
    "wof:placetype":"venue"
},
  "geometry": {"coordinates":[3.413932085,51.138507843],"type":"Point"}
}