{
  "type": "Feature",
  "properties": {
    "addr:full":"Oude Vestigingsstraat 11 Kortrijk West-Vlaanderen 8500",
    "addr:housenumber":"11",
    "addr:postcode":"8500",
    "addr:street":"Oude Vestigingsstraat",
    "iso:country":"BE",
    "sg:address":"Oude Vestigingsstraat 11",
    "sg:city":"Kortrijk",
    "sg:orig_category":"Tijdelijke werkgelegenheid and uitzendkantoren",
    "sg:phone":"+32 56 20 49 91",
    "sg:postcode":"8500",
    "sg:province":"West-Vlaanderen",
    "wof:name":"T\u00c8nce Interim",
    "wof:placetype":"venue"
},
  "geometry": {"coordinates":[3.2626240253,50.8265419006],"type":"Point"}
}