{
  "type": "Feature",
  "properties": {
    "iso:country":"BE",
    "sg:address":"Oudstrijdersstraat 66",
    "sg:city":"Oudenaarde",
    "sg:orig_category":"Kapsalons",
    "sg:phone":"+32 55 31 49 38",
    "sg:postcode":"9700",
    "sg:province":"Oost-Vlaanderen",
    "wof:name":"Norbert Vanhessche",
    "wof:placetype":"venue"
},
  "geometry": {"coordinates":[3.6352949142,50.8662147522],"type":"Point"}
}