{
  "type": "Feature",
  "properties": {
    "addr:full":"Rue Des Vennes 196 Liege Li\u00e8ge 4020",
    "addr:housenumber":"196",
    "addr:postcode":"4020",
    "addr:street":"Rue Des Vennes",
    "iso:country":"BE",
    "sg:address":"Rue Des Vennes 196",
    "sg:city":"Liege",
    "sg:orig_category":"Medische apparatuur, orthopedische artikelen and prothesen Fab",
    "sg:phone":"+32 4 342 02 69",
    "sg:postcode":"4020",
    "sg:province":"Li\u00e8ge",
    "wof:name":"La.bo.wi",
    "wof:placetype":"venue"
},
  "geometry": {"coordinates":[5.5875082016,50.6248893738],"type":"Point"}
}