{
  "type": "Feature",
  "properties": {
    "addr:full":"Rue Anti\u00e9mont 69 Marche-en-famenne (on) Luxembourg 6900",
    "addr:housenumber":"69",
    "addr:postcode":"luxembourg 6900",
    "addr:street":"Rue Antie\u0301Mont",
    "iso:country":"BE",
    "sg:address":"Rue Anti\u00e9mont 69",
    "sg:city":"Marche-en-famenne (on)",
    "sg:classifiers":[
        {
            "category":"Autos & Motor Vehicles",
            "subcategory":"Recreational Vehicle Sales",
            "type":"Retail Goods"
        }
    ],
    "sg:phone":"+32 84 21 24 80",
    "sg:postcode":"6900",
    "sg:province":"Luxembourg",
    "sg:tags":[
        "caravan",
        "accessory"
    ],
    "wof:name":"Lux Caravans",
    "wof:placetype":"venue"
},
  "geometry": {"coordinates":[5.2962579727,50.1762962341],"type":"Point"}
}