{
  "type": "Feature",
  "properties": {
    "iso:country":"BE",
    "sg:address":"All\u00e9e Des Marronniers 16",
    "sg:city":"Gembloux-sur-orneau (gembloux)",
    "sg:classifiers":[
        {
            "category":"Professional",
            "subcategory":"Lawyer & Legal Services",
            "type":"Services"
        }
    ],
    "sg:phone":"+32 81 61 10 28",
    "sg:postcode":"5030",
    "sg:province":"Namur",
    "sg:tags":[
        "notary"
    ],
    "wof:name":"Bioul P",
    "wof:placetype":"venue"
},
  "geometry": {"coordinates":[4.6897988319,50.5674324036],"type":"Point"}
}