{
  "type": "Feature",
  "properties": {
    "addr:full":"Nagelstraat 29 Kinrooi Limburg 3640",
    "addr:housenumber":"29",
    "addr:postcode":"3640",
    "addr:street":"Nagelstraat",
    "iso:country":"BE",
    "sg:address":"Nagelstraat 29",
    "sg:city":"Kinrooi",
    "sg:orig_category":"Eleveurs and marchands de porcs. Producteurs de fruits",
    "sg:phone":"+32 89 56 83 53",
    "sg:postcode":"3640",
    "sg:province":"Limburg",
    "wof:name":"Theodoor Simons",
    "wof:placetype":"venue"
},
  "geometry": {"coordinates":[5.7854819298,51.1322059631],"type":"Point"}
}