{
  "type": "Feature",
  "properties": {
    "addr:full":"Neutralstrasse 314 Lontzen/lontzen Li\u00e8ge 4710",
    "addr:housenumber":"314",
    "addr:postcode":"4710",
    "addr:street":"Neutralstrasse",
    "iso:country":"BE",
    "sg:address":"Neutralstrasse 314",
    "sg:city":"Lontzen/lontzen",
    "sg:orig_category":"Aardappelproducten Gh Groenten and fruit Gh",
    "sg:phone":"+32 87 88 33 25",
    "sg:postcode":"4710",
    "sg:province":"Li\u00e8ge",
    "wof:name":"Bonni Joseph",
    "wof:placetype":"venue"
},
  "geometry": {"coordinates":[5.99229002,50.6763191223],"type":"Point"}
}