{
  "type": "Feature",
  "properties": {
    "addr:full":"Kerkhoflei 2 Ranst (oelegem) Antwerpen 2520",
    "addr:housenumber":"2",
    "addr:postcode":"2520",
    "addr:street":"Kerkhoflei",
    "iso:country":"BE",
    "sg:address":"Kerkhoflei 2",
    "sg:city":"Ranst (oelegem)",
    "sg:orig_category":"Ice-cream parlours",
    "sg:phone":"+32 3 295 93 20",
    "sg:postcode":"2520",
    "sg:province":"Antwerpen",
    "wof:name":"De Linde",
    "wof:placetype":"venue"
},
  "geometry": {"coordinates":[4.5967550278,51.2094116211],"type":"Point"}
}