{
  "type": "Feature",
  "properties": {
    "addr:full":"Dijkstraat 34 Steenokkerzeel Vlaams-Brabant 1820",
    "addr:housenumber":"34",
    "addr:postcode":"1820",
    "addr:street":"Dijkstraat",
    "iso:country":"BE",
    "sg:address":"Dijkstraat 34",
    "sg:city":"Steenokkerzeel",
    "sg:orig_category":"Meubles D\u00e9taillants, Am\u00e9nagement de B\u00e2timents et de Cuisines",
    "sg:phone":"+32 2 759 41 61",
    "sg:postcode":"1820",
    "sg:province":"Vlaams-Brabant",
    "wof:name":"Gideco",
    "wof:placetype":"venue"
},
  "geometry": {"coordinates":[4.5176877975,50.90782547],"type":"Point"}
}