{
  "type": "Feature",
  "properties": {
    "iso:country":"BE",
    "sg:address":"Grand\u00b4rue 45",
    "sg:city":"Durbuy",
    "sg:orig_category":"Textiel",
    "sg:phone":"+32 86 21 49 80",
    "sg:postcode":"6940",
    "sg:province":"Luxembourg",
    "wof:name":"Mercerie Deborah",
    "wof:placetype":"venue"
},
  "geometry": {"coordinates":[5.493584156,50.3504943848],"type":"Point"}
}