{
  "type": "Feature",
  "properties": {
    "iso:country":"BE",
    "sg:address":"Esenstraat 48",
    "sg:city":"Kortemark",
    "sg:orig_category":"Eleveurs and marchands de porcs",
    "sg:phone":"+32 51 56 60 74",
    "sg:postcode":"8610",
    "sg:province":"West-Vlaanderen",
    "wof:name":"Stefaan Vannieuwenhuyse",
    "wof:placetype":"venue"
},
  "geometry": {"coordinates":[2.9546821117,51.0173683167],"type":"Point"}
}