{
  "type": "Feature",
  "properties": {
    "addr:full":"Grens 39 Arendonk Antwerpen 2370",
    "addr:housenumber":"39",
    "addr:postcode":"2370",
    "addr:street":"Grens",
    "iso:country":"BE",
    "sg:address":"Grens 39",
    "sg:city":"Arendonk",
    "sg:classifiers":[
        {
            "category":"Restaurant",
            "type":"Food & Drink"
        }
    ],
    "sg:phone":"+32 14 67 84 30",
    "sg:postcode":"2370",
    "sg:province":"Antwerpen",
    "wof:name":"De Bierhoeve",
    "wof:placetype":"venue"
},
  "geometry": {"coordinates":[5.113615036,51.3446884155],"type":"Point"}
}