{
  "type": "Feature",
  "properties": {
    "iso:country":"BE",
    "sg:address":"Rue De Messitert 221a",
    "sg:city":"Aubel",
    "sg:classifiers":[
        {
            "category":"Building & Trades",
            "subcategory":"Construction",
            "type":"Services"
        }
    ],
    "sg:phone":"+32 87 68 73 28",
    "sg:postcode":"4880",
    "sg:province":"Li\u00e8ge",
    "sg:tags":[
        "installation",
        "-",
        "central",
        "heating"
    ],
    "wof:name":"Lenartz F",
    "wof:placetype":"venue"
},
  "geometry": {"coordinates":[5.8530101776,50.6984786987],"type":"Point"}
}