{
  "type": "Feature",
  "properties": {
    "addr:full":"Bolimpont 11 Jalhay Li\u00e8ge 4845",
    "addr:housenumber":"11",
    "addr:postcode":"4845",
    "addr:street":"Bolimpont",
    "iso:country":"BE",
    "sg:address":"Bolimpont 11",
    "sg:city":"Jalhay",
    "sg:orig_category":"Afbraak- and draineerwerken",
    "sg:phone":"+32 87 64 82 24",
    "sg:postcode":"4845",
    "sg:province":"Li\u00e8ge",
    "wof:name":"Jacquemin",
    "wof:placetype":"venue"
},
  "geometry": {"coordinates":[5.978703022,50.554775238],"type":"Point"}
}