{
  "type": "Feature",
  "properties": {
    "addr:full":"Hoogstraat 5 Ronse/renaix Oost-Vlaanderen 9600",
    "addr:housenumber":"5",
    "addr:postcode":"9600",
    "addr:street":"Hoogstraat",
    "iso:country":"BE",
    "sg:address":"Hoogstraat 5",
    "sg:city":"Ronse/renaix",
    "sg:orig_category":"Sportclubs",
    "sg:phone":"+32 55 21 67 52",
    "sg:postcode":"9600",
    "sg:province":"Oost-Vlaanderen",
    "wof:name":"B.c. Ronse",
    "wof:placetype":"venue"
},
  "geometry": {"coordinates":[3.5976009369,50.7459068298],"type":"Point"}
}