{
  "type": "Feature",
  "properties": {
    "iso:country":"BE",
    "sg:address":"Sluisstraat 77",
    "sg:city":"Leuven",
    "sg:orig_category":"Biens d'occasion",
    "sg:phone":"+32 16 29 16 84",
    "sg:postcode":"3000",
    "sg:province":"Vlaams-Brabant",
    "wof:name":"Poverello",
    "wof:placetype":"venue"
},
  "geometry": {"coordinates":[4.6999120712,50.8872680664],"type":"Point"}
}