{
  "type": "Feature",
  "properties": {
    "iso:country":"BE",
    "sg:address":"Chauss\u00c9e D\u00b4ivoz 143",
    "sg:city":"Fl\u00c9malle",
    "sg:classifiers":[
        {
            "category":"Restaurant",
            "type":"Food & Drink"
        }
    ],
    "sg:phone":"+32 4 336 73 80",
    "sg:postcode":"4400",
    "sg:province":"Li\u00e8ge",
    "wof:name":"Le Vieux Cellier",
    "wof:placetype":"venue"
},
  "geometry": {"coordinates":[5.4576430321,50.5693130493],"type":"Point"}
}