{
  "type": "Feature",
  "properties": {
    "addr:full":"Rue Rond Du Roi Albert 12 Awans Li\u00e8ge 4340",
    "addr:housenumber":"12",
    "addr:postcode":"4340",
    "addr:street":"Rue Rond Du Roi Albert",
    "iso:country":"BE",
    "sg:address":"Rue Rond Du Roi Albert 12",
    "sg:city":"Awans",
    "sg:orig_category":"Kapsalons",
    "sg:phone":"+32 4 257 44 89",
    "sg:postcode":"4340",
    "sg:province":"Li\u00e8ge",
    "wof:name":"Evelyne Mestre",
    "wof:placetype":"venue"
},
  "geometry": {"coordinates":[5.43876791,50.7049446106],"type":"Point"}
}