{
  "type": "Feature",
  "properties": {
    "iso:country":"BE",
    "sg:address":"Avenue Des Pagodes 346",
    "sg:city":"Brussel/bruxelles",
    "sg:orig_category":"Foto-uitrusting",
    "sg:phone":"+32 2 268 15 23",
    "sg:postcode":"1020",
    "sg:province":"Bruxelles-Capitale",
    "wof:name":"Flash Joe",
    "wof:placetype":"venue"
},
  "geometry": {"coordinates":[4.3625450134,50.8959541321],"type":"Point"}
}