{
  "type": "Feature",
  "properties": {
    "iso:country":"BE",
    "sg:address":"Chauss\u00c9e Brunehault 293",
    "sg:city":"Binche",
    "sg:orig_category":"Herstellingen and onderhoud van auto's Voertuigen",
    "sg:phone":"+32 64 33 59 44",
    "sg:postcode":"7134",
    "sg:province":"Hainaut",
    "wof:name":"Garage Ciulla",
    "wof:placetype":"venue"
},
  "geometry": {"coordinates":[4.1968650818,50.4328384399],"type":"Point"}
}