{
  "type": "Feature",
  "properties": {
    "iso:country":"BE",
    "sg:address":"Noordhoutstraat 107",
    "sg:city":"Gent",
    "sg:orig_category":"Rundveehouders",
    "sg:phone":"+32 9 282 55 08",
    "sg:postcode":"9031",
    "sg:province":"Oost-Vlaanderen",
    "wof:name":"Robert Vandeputte",
    "wof:placetype":"venue"
},
  "geometry": {"coordinates":[3.5947830677,51.0302963257],"type":"Point"}
}