{
  "type": "Feature",
  "properties": {
    "iso:country":"BE",
    "sg:address":"Kloosterstraat 13",
    "sg:city":"Mol",
    "sg:orig_category":"Articles de camping and de sport. V\u00eatements",
    "sg:phone":"+32 14 31 49 52",
    "sg:postcode":"2400",
    "sg:province":"Antwerpen",
    "wof:name":"Tennis Stores",
    "wof:placetype":"venue"
},
  "geometry": {"coordinates":[5.1196951866,51.1878585815],"type":"Point"}
}