{
  "type": "Feature",
  "properties": {
    "addr:full":"Kerkstraat 6 Herzele Oost-Vlaanderen 9550",
    "addr:housenumber":"6",
    "addr:postcode":"9550",
    "addr:street":"Kerkstraat;Oost-Vlaanderen",
    "iso:country":"BE",
    "sg:address":"Kerkstraat 6",
    "sg:city":"Herzele",
    "sg:classifiers":[
        {
            "category":"Health Services",
            "subcategory":"Health Practitioner",
            "type":"Services"
        }
    ],
    "sg:phone":"+32 53 62 89 96",
    "sg:postcode":"9550",
    "sg:province":"Oost-Vlaanderen",
    "sg:tags":[
        "physiotherapist"
    ],
    "wof:name":"Matthijs Fernande",
    "wof:placetype":"venue"
},
  "geometry": {"coordinates":[3.8928968906,50.8847694397],"type":"Point"}
}