{
  "type": "Feature",
  "properties": {
    "addr:full":"P. De Smet De Naeyerstr. 34bc Middelkerke West-Vlaanderen 8430",
    "addr:housenumber":"34bc",
    "addr:postcode":"8430",
    "addr:street":"P. De Smet De Naeyerstr.",
    "iso:country":"BE",
    "sg:address":"P. De Smet De Naeyerstr. 34bc",
    "sg:city":"Middelkerke",
    "sg:orig_category":"Banques and organismes de cr\u00e9dit",
    "sg:phone":"+32 59 30 44 30",
    "sg:postcode":"8430",
    "sg:province":"West-Vlaanderen",
    "wof:name":"Bbl",
    "wof:placetype":"venue"
},
  "geometry": {"coordinates":[2.8186399937,51.1875267029],"type":"Point"}
}