{
  "type": "Feature",
  "properties": {
    "addr:full":"Zoute Dijk 1a Antwerpen Antwerpen 2040",
    "addr:housenumber":"1a",
    "addr:postcode":"2040",
    "addr:street":"Dijk",
    "iso:country":"BE",
    "sg:address":"Zoute Dijk 1a",
    "sg:city":"Antwerpen",
    "sg:classifiers":[
        {
            "category":"Utilities",
            "subcategory":"Fuel Oil & Lpg",
            "type":"Services"
        }
    ],
    "sg:phone":"+32 3 569 17 88",
    "sg:postcode":"2040",
    "sg:province":"Antwerpen",
    "wof:name":"Peka",
    "wof:placetype":"venue"
},
  "geometry": {"coordinates":[4.3060250282,51.3519096375],"type":"Point"}
}