{
  "type": "Feature",
  "properties": {
    "addr:full":"Bp 4205 Charleroi Hainaut 6000",
    "addr:housenumber":"4205",
    "addr:postcode":"6000",
    "addr:street":"Hainaut",
    "iso:country":"BE",
    "sg:address":"Bp 4205",
    "sg:city":"Charleroi",
    "sg:orig_category":"Magasins sp\u00e9cialis\u00e9s",
    "sg:phone":"+32 71 44 29 00",
    "sg:postcode":"6000",
    "sg:province":"Hainaut",
    "wof:name":"Sdm",
    "wof:placetype":"venue"
},
  "geometry": {"coordinates":[4.4434351921,50.41015625],"type":"Point"}
}