{
  "type": "Feature",
  "properties": {
    "addr:full":"Rue Jules Destr\u00c9e 81 Aiseau-presles Hainaut 6250",
    "addr:housenumber":"81",
    "addr:postcode":"6250",
    "addr:street":"Rue Jules Destre\u0301E;Hainaut",
    "iso:country":"BE",
    "sg:address":"Rue Jules Destr\u00c9e 81",
    "sg:city":"Aiseau-presles",
    "sg:orig_category":"Brood, gebak and snoepgoed",
    "sg:phone":"+32 71 77 29 01",
    "sg:postcode":"6250",
    "sg:province":"Hainaut",
    "wof:name":"Yves Faict",
    "wof:placetype":"venue"
},
  "geometry": {"coordinates":[4.5715918541,50.4209289551],"type":"Point"}
}