{
  "type": "Feature",
  "properties": {
    "addr:full":"Chauss\u00c9e Romaine 14 Qu\u00c9vy Hainaut 7041",
    "addr:housenumber":"14",
    "addr:postcode":"7041",
    "addr:street":"Chausse\u0301E Romaine;Hainaut",
    "iso:country":"BE",
    "sg:address":"Chauss\u00c9e Romaine 14",
    "sg:city":"Qu\u00c9vy",
    "sg:orig_category":"Architectes",
    "sg:phone":"+32 65 56 82 76",
    "sg:postcode":"7041",
    "sg:province":"Hainaut",
    "wof:name":"Caroline Dirix",
    "wof:placetype":"venue"
},
  "geometry": {"coordinates":[3.9808731079,50.3547096252],"type":"Point"}
}