{
  "type": "Feature",
  "properties": {
    "iso:country":"BE",
    "sg:address":"Dr\u00e8ve Dudinsart 84",
    "sg:city":"Waterloo",
    "sg:classifiers":[
        {
            "category":"Travel",
            "subcategory":"Resort",
            "type":"Entertainment"
        }
    ],
    "sg:phone":"+32 2 354 41 77",
    "sg:postcode":"1410",
    "sg:province":"Brabant Wallon",
    "sg:tags":[
        "rental",
        "accomodation",
        "holiday",
        "-"
    ],
    "wof:name":"Dachelet (chambres D'h\u00f4tes)",
    "wof:placetype":"venue"
},
  "geometry": {"coordinates":[4.3652329445,50.7167129517],"type":"Point"}
}