{
  "type": "Feature",
  "properties": {
    "addr:full":"Lavendelstraat 87 Sint-niklaas Oost-Vlaanderen 9100",
    "addr:housenumber":"87",
    "addr:postcode":"9100",
    "addr:street":"Lavendelstraat",
    "iso:country":"BE",
    "sg:address":"Lavendelstraat 87",
    "sg:city":"Sint-niklaas",
    "sg:orig_category":"Secr\u00e9tariats. Services de publipostage",
    "sg:phone":"+32 3 776 14 20",
    "sg:postcode":"9100",
    "sg:province":"Oost-Vlaanderen",
    "wof:name":"Imprint",
    "wof:placetype":"venue"
},
  "geometry": {"coordinates":[4.1399049759,51.1734352112],"type":"Point"}
}