{
  "type": "Feature",
  "properties": {
    "addr:full":"Hautes Voies 9 Durbuy (grandhan) Luxembourg 6940",
    "addr:housenumber":"9",
    "addr:postcode":"6940",
    "addr:street":"Voies",
    "iso:country":"BE",
    "sg:address":"Hautes Voies 9",
    "sg:city":"Durbuy (grandhan)",
    "sg:classifiers":[
        {
            "category":"Building & Trades",
            "subcategory":"Construction",
            "type":"Services"
        }
    ],
    "sg:phone":"+32 86 21 15 49",
    "sg:postcode":"6940",
    "sg:province":"Luxembourg",
    "sg:tags":[
        "carpenter"
    ],
    "wof:name":"Artboiserie (l')",
    "wof:placetype":"venue"
},
  "geometry": {"coordinates":[5.4344768524,50.3288726807],"type":"Point"}
}