{
  "type": "Feature",
  "properties": {
    "iso:country":"BE",
    "sg:address":"Chauss\u00c9e D'ellezelles 11ba",
    "sg:city":"Ronse/renaix",
    "sg:orig_category":"M\u00e9decines alternatives",
    "sg:phone":"+32 55 21 69 60",
    "sg:postcode":"9600",
    "sg:province":"Oost-Vlaanderen",
    "wof:name":"Michel Van Den Abeele",
    "wof:placetype":"venue"
},
  "geometry": {"coordinates":[3.6128470898,50.7433853149],"type":"Point"}
}