{
  "type": "Feature",
  "properties": {
    "addr:full":"Bellestraat 116 Ieper West-Vlaanderen 8908",
    "addr:housenumber":"116",
    "addr:postcode":"8908",
    "addr:street":"Bellestraat",
    "iso:country":"BE",
    "sg:address":"Bellestraat 116",
    "sg:city":"Ieper",
    "sg:orig_category":"Producteurs de l\u00e9gumes",
    "sg:phone":"+32 57 20 41 32",
    "sg:postcode":"8908",
    "sg:province":"West-Vlaanderen",
    "wof:name":"Bernard Detavernier",
    "wof:placetype":"venue"
},
  "geometry": {"coordinates":[2.8132739067,50.8450546265],"type":"Point"}
}