{
  "type": "Feature",
  "properties": {
    "addr:full":"Ketinglei 27 Hemiksem Antwerpen 2620",
    "addr:housenumber":"27",
    "addr:postcode":"2620",
    "addr:street":"Ketinglei",
    "iso:country":"BE",
    "sg:address":"Ketinglei 27",
    "sg:city":"Hemiksem",
    "sg:orig_category":"Plomberie, chauffage and installations sanitaires. Charpentes and couvertures",
    "sg:phone":"+32 3 887 51 95",
    "sg:postcode":"2620",
    "sg:province":"Antwerpen",
    "wof:name":"Fa.huybrechts-boussemaere",
    "wof:placetype":"venue"
},
  "geometry": {"coordinates":[4.3415579796,51.1433944702],"type":"Point"}
}