{
  "type": "Feature",
  "properties": {
    "addr:full":"Halewijnlaan 2 Bertem Vlaams-Brabant 3060",
    "addr:housenumber":"2",
    "addr:postcode":"3060",
    "addr:street":"Halewijnlaan",
    "iso:country":"BE",
    "sg:address":"Halewijnlaan 2",
    "sg:city":"Bertem",
    "sg:classifiers":[
        {
            "category":"Shopping Center",
            "type":"Public Place"
        }
    ],
    "sg:phone":"+32 16 48 83 28",
    "sg:postcode":"3060",
    "sg:province":"Vlaams-Brabant",
    "sg:tags":[
        "enseignement",
        "formation"
    ],
    "wof:name":"Stasop",
    "wof:placetype":"venue"
},
  "geometry": {"coordinates":[4.6269130707,50.8599357605],"type":"Point"}
}