{
  "type": "Feature",
  "properties": {
    "iso:country":"BE",
    "sg:address":"Haasbosstraat 35",
    "sg:city":"Overpelt",
    "sg:classifiers":[
        {
            "category":"Health Services",
            "subcategory":"Doctor",
            "type":"Services"
        }
    ],
    "sg:phone":"+32 11 39 13 74",
    "sg:postcode":"3900",
    "sg:province":"Limburg",
    "sg:tags":[
        "medicinephysicians",
        "surgeon"
    ],
    "wof:name":"Gijbels G",
    "wof:placetype":"venue"
},
  "geometry": {"coordinates":[5.4082231522,51.1914138794],"type":"Point"}
}