{
  "type": "Feature",
  "properties": {
    "iso:country":"BE",
    "sg:address":"Zijpstraat 120",
    "sg:city":"Aalst",
    "sg:orig_category":"Rundveehouders",
    "sg:phone":"+32 53 70 67 38",
    "sg:postcode":"9308",
    "sg:province":"Oost-Vlaanderen",
    "wof:name":"Clement De Winne",
    "wof:placetype":"venue"
},
  "geometry": {"coordinates":[4.0347590446,50.9603500366],"type":"Point"}
}