{
  "type": "Feature",
  "properties": {
    "iso:country":"BE",
    "sg:address":"Rue De Tenbosch 9",
    "sg:city":"Bruxelles",
    "sg:classifiers":[
        {
            "category":"Internet Cafe",
            "subcategory":"None",
            "type":"Food & Drink"
        }
    ],
    "sg:phone":"+32 2 640 91 94",
    "sg:postcode":"1050",
    "sg:province":"Bruxelles-Capitale",
    "sg:tags":[
        "web",
        "server",
        "servers"
    ],
    "wof:name":"Perceval Technologies S.a.",
    "wof:placetype":"venue"
},
  "geometry": {"coordinates":[4.3656902313,50.8235206604],"type":"Point"}
}