{
  "type": "Feature",
  "properties": {
    "addr:full":"Kerkeweg 122 Overijse Vlaams-Brabant 3090",
    "addr:housenumber":"122",
    "addr:postcode":"3090",
    "addr:street":"Kerkeweg",
    "iso:country":"BE",
    "sg:address":"Kerkeweg 122",
    "sg:city":"Overijse",
    "sg:classifiers":[
        {
            "category":"Banks & Credit Unions",
            "subcategory":"Investment Brokerage",
            "type":"Services"
        }
    ],
    "sg:phone":"+32 2 687 66 75",
    "sg:postcode":"3090",
    "sg:province":"Vlaams-Brabant",
    "sg:tags":[
        "printing",
        "-"
    ],
    "wof:name":"Dewaet Drukkerij",
    "wof:placetype":"venue"
},
  "geometry": {"coordinates":[4.5253100395,50.758731842],"type":"Point"}
}