{
  "type": "Feature",
  "properties": {
    "addr:full":"Menenstraat 78 Zonnebeke West-Vlaanderen 8980",
    "addr:housenumber":"78",
    "addr:postcode":"8980",
    "addr:street":"Menenstraat",
    "iso:country":"BE",
    "sg:address":"Menenstraat 78",
    "sg:city":"Zonnebeke",
    "sg:orig_category":"Brood, gebak and snoepgoed",
    "sg:phone":"+32 57 46 62 02",
    "sg:postcode":"8980",
    "sg:province":"West-Vlaanderen",
    "wof:name":"Bakkerij Dierynck",
    "wof:placetype":"venue"
},
  "geometry": {"coordinates":[2.9816670418,50.8373527527],"type":"Point"}
}