{
  "type": "Feature",
  "properties": {
    "iso:country":"BE",
    "sg:address":"Poelkappellestraat 60",
    "sg:city":"Staden",
    "sg:orig_category":"Installatie van houten of kunststof schrijnwerk",
    "sg:phone":"+32 51 77 73 96",
    "sg:postcode":"8840",
    "sg:province":"West-Vlaanderen",
    "wof:name":"Durnez",
    "wof:placetype":"venue"
},
  "geometry": {"coordinates":[2.9898450375,50.9242553711],"type":"Point"}
}