{
  "type": "Feature",
  "properties": {
    "iso:country":"BE",
    "sg:address":"Kruizekestraat 232",
    "sg:city":"Wervik",
    "sg:orig_category":"Royal Canin. Souvenirs and objets artisanaux. Articles de jardin. Animaux domestiques and accessoire",
    "sg:phone":"+32 56 31 28 66",
    "sg:postcode":"8940",
    "sg:province":"West-Vlaanderen",
    "wof:name":"Aveve Obin Yves",
    "wof:placetype":"venue"
},
  "geometry": {"coordinates":[3.028539896,50.7967567444],"type":"Point"}
}