{
  "type": "Feature",
  "properties": {
    "iso:country":"BE",
    "sg:address":"Doleegstraat 6",
    "sg:city":"Leuven",
    "sg:orig_category":"Enseignement maternel and primaire",
    "sg:phone":"+32 16 20 02 95",
    "sg:postcode":"3001",
    "sg:province":"Vlaams-Brabant",
    "wof:name":"Vrije Basisschool",
    "wof:placetype":"venue"
},
  "geometry": {"coordinates":[4.657886982,50.8614616394],"type":"Point"}
}