{
  "type": "Feature",
  "properties": {
    "iso:country":"BE",
    "sg:address":"Spiegelstraat 2",
    "sg:city":"Tienen",
    "sg:classifiers":[
        {
            "category":"Shopping",
            "subcategory":"Clothing, Apparel, & Fashions",
            "type":"Retail Goods"
        }
    ],
    "sg:phone":"+32 16 81 78 02",
    "sg:postcode":"3300",
    "sg:province":"Vlaams-Brabant",
    "sg:tags":[
        "lady",
        "clothing",
        "-"
    ],
    "wof:name":"Damlux",
    "wof:placetype":"venue"
},
  "geometry": {"coordinates":[4.9389882088,50.8065452576],"type":"Point"}
}