{
  "type": "Feature",
  "properties": {
    "addr:full":"Paalstraat 49 Schoten Antwerpen 2900",
    "addr:housenumber":"49",
    "addr:postcode":"2900",
    "addr:street":"Paalstraat",
    "iso:country":"BE",
    "sg:address":"Paalstraat 49",
    "sg:city":"Schoten",
    "sg:orig_category":"Animations diverses",
    "sg:phone":"+32 3 685 30 30",
    "sg:postcode":"2900",
    "sg:province":"Antwerpen",
    "wof:name":"Erokill",
    "wof:placetype":"venue"
},
  "geometry": {"coordinates":[4.5000557899,51.252117157],"type":"Point"}
}