{
  "type": "Feature",
  "properties": {
    "iso:country":"BE",
    "sg:address":"Rue De La Victoire 76",
    "sg:city":"Sint-gillis/saint-gilles",
    "sg:orig_category":"Agences Matrimoniales et de Rencontre",
    "sg:phone":"+32 2 544 06 70",
    "sg:postcode":"1060",
    "sg:province":"Bruxelles-Capitale",
    "wof:name":"Agence Hakimi",
    "wof:placetype":"venue"
},
  "geometry": {"coordinates":[4.3485097885,50.8304328918],"type":"Point"}
}