{
  "type": "Feature",
  "properties": {
    "addr:full":"Hollandse Tuin 4 Box 2 Mortsel Antwerpen 2640",
    "addr:housenumber":"4;2",
    "addr:postcode":"2640",
    "addr:street":"Hollandse Tuin;Box",
    "iso:country":"BE",
    "sg:address":"Hollandse Tuin 4 Box 2",
    "sg:city":"Mortsel",
    "sg:classifiers":[
        {
            "category":"Professional",
            "subcategory":"Management & Consulting",
            "type":"Services"
        }
    ],
    "sg:phone":"+32 3 448 37 49",
    "sg:postcode":"2640",
    "sg:province":"Antwerpen",
    "sg:tags":[
        "consultant"
    ],
    "wof:name":"Belgalink Bvba",
    "wof:placetype":"venue"
},
  "geometry": {"coordinates":[4.4608030319,51.16929245],"type":"Point"}
}