{
  "type": "Feature",
  "properties": {
    "iso:country":"BE",
    "sg:address":"Doornhut 29",
    "sg:city":"Brugge (sint-kruis)",
    "sg:classifiers":[
        {
            "category":"Arts & Performance",
            "subcategory":"Symphony",
            "type":"Entertainment"
        }
    ],
    "sg:phone":"+32 50 31 82 09",
    "sg:postcode":"8310",
    "sg:province":"West-Vlaanderen",
    "sg:tags":[
        "orchestra"
    ],
    "wof:name":"Olstein Big Band",
    "wof:placetype":"venue"
},
  "geometry": {"coordinates":[3.2658889294,51.2119903564],"type":"Point"}
}