{
  "type": "Feature",
  "properties": {
    "addr:full":"Opstal 12 Merksplas Antwerpen 2330",
    "addr:housenumber":"12",
    "addr:postcode":"2330",
    "addr:street":"Opstal",
    "iso:country":"BE",
    "sg:address":"Opstal 12",
    "sg:city":"Merksplas",
    "sg:orig_category":"Rundveehouders",
    "sg:phone":"+32 14 63 35 71",
    "sg:postcode":"2330",
    "sg:province":"Antwerpen",
    "wof:name":"Lenaerts & Boudewijns",
    "wof:placetype":"venue"
},
  "geometry": {"coordinates":[4.8752441406,51.3550758362],"type":"Point"}
}