{
  "type": "Feature",
  "properties": {
    "addr:full":"Venelle Des Marronniers 21 Bierges Brabant Wallon 1301",
    "addr:housenumber":"21;1301",
    "addr:street":"Venelle Des Marronniers",
    "iso:country":"BE",
    "sg:address":"Venelle Des Marronniers 21",
    "sg:city":"Bierges",
    "sg:orig_category":"Transports routiers de marchandises",
    "sg:phone":"+32 475 28 44 43",
    "sg:postcode":"1301",
    "sg:province":"Brabant Wallon",
    "wof:name":"J&b Trans",
    "wof:placetype":"venue"
},
  "geometry": {"coordinates":[4.6170101166,50.7006492615],"type":"Point"}
}