{
  "type": "Feature",
  "properties": {
    "addr:full":"Rumbeeksesteenweg 215 Roeselare West-Vlaanderen 8800",
    "addr:housenumber":"215",
    "addr:postcode":"8800",
    "addr:street":"Rumbeeksesteenweg",
    "iso:country":"BE",
    "sg:address":"Rumbeeksesteenweg 215",
    "sg:city":"Roeselare",
    "sg:classifiers":[
        {
            "category":"Personal",
            "subcategory":"Beauty Salon",
            "type":"Services"
        }
    ],
    "sg:phone":"+32 51 22 21 14",
    "sg:postcode":"8800",
    "sg:province":"West-Vlaanderen",
    "wof:name":"Aphrodite",
    "wof:placetype":"venue"
},
  "geometry": {"coordinates":[3.1331250668,50.9389801025],"type":"Point"}
}