{
  "type": "Feature",
  "properties": {
    "addr:full":"Chauss\u00e9e De Renaix 151 Frasnes-lez-anvaing (dergneau) Hainaut 7912",
    "addr:housenumber":"151;7912",
    "addr:street":"Chausse\u0301E De Renaix;Dergneau Hainaut",
    "iso:country":"BE",
    "sg:address":"Chauss\u00e9e De Renaix 151",
    "sg:city":"Frasnes-lez-anvaing (dergneau)",
    "sg:classifiers":[
        {
            "category":"Bars & Pubs",
            "type":"Food & Drink"
        }
    ],
    "sg:phone":"+32 69 76 64 05",
    "sg:postcode":"7912",
    "sg:province":"Hainaut",
    "wof:name":"Managuas (le)",
    "wof:placetype":"venue"
},
  "geometry": {"coordinates":[3.5829889774,50.7211532593],"type":"Point"}
}