{
  "type": "Feature",
  "properties": {
    "addr:full":"Pijpenhof 31a Bilzen Limburg 3740",
    "addr:housenumber":"31a",
    "addr:postcode":"3740",
    "addr:street":"Pijpenhof",
    "iso:country":"BE",
    "sg:address":"Pijpenhof 31a",
    "sg:city":"Bilzen",
    "sg:orig_category":"R\u00e9parations d'horloges, montres and bijoux. Bijouteries and horlogeries",
    "sg:phone":"+32 89 41 38 31",
    "sg:postcode":"3740",
    "sg:province":"Limburg",
    "wof:name":"Guy Martens",
    "wof:placetype":"venue"
},
  "geometry": {"coordinates":[5.5191121101,50.8736495972],"type":"Point"}
}