{
  "type": "Feature",
  "properties": {
    "iso:country":"BE",
    "sg:address":"Rue Du Doyenn\u00c9 30",
    "sg:city":"Ukkel/uccle",
    "sg:classifiers":[
        {
            "category":"Sports & Exercise",
            "subcategory":"Sports Center",
            "type":"Entertainment"
        }
    ],
    "sg:phone":"+32 2 343 39 43",
    "sg:postcode":"1180",
    "sg:province":"Bruxelles-Capitale",
    "sg:tags":[
        "de",
        "fitness"
    ],
    "wof:name":"New Body World",
    "wof:placetype":"venue"
},
  "geometry": {"coordinates":[4.3376698494,50.8068313599],"type":"Point"}
}