{
  "type": "Feature",
  "properties": {
    "addr:full":"Vrijdagmarkt 41 Gent Oost-Vlaanderen 9000",
    "addr:housenumber":"41",
    "addr:postcode":"9000",
    "addr:street":"Vrijdagmarkt;Oost-Vlaanderen",
    "iso:country":"BE",
    "sg:address":"Vrijdagmarkt 41",
    "sg:city":"Gent",
    "sg:classifiers":[
        {
            "category":"Home & Garden",
            "subcategory":"Home Furnishings",
            "type":"Retail Goods"
        }
    ],
    "sg:phone":"+32 9 225 14 79",
    "sg:postcode":"9000",
    "sg:province":"Oost-Vlaanderen",
    "sg:tags":[
        "curtain",
        "-",
        "fixture"
    ],
    "wof:name":"Artevelde Draperiecentrum",
    "wof:placetype":"venue"
},
  "geometry": {"coordinates":[3.7255859375,51.0564994812],"type":"Point"}
}