{
  "type": "Feature",
  "properties": {
    "addr:full":"Rue Du Rivage 1 Pecq Hainaut 7740",
    "addr:housenumber":"1",
    "addr:postcode":"7740",
    "addr:street":"Rue Du Rivage",
    "iso:country":"BE",
    "sg:address":"Rue Du Rivage 1",
    "sg:city":"Pecq",
    "sg:classifiers":[
        {
            "category":"Taxi",
            "type":"Transportation"
        }
    ],
    "sg:phone":"+32 69 55 64 56",
    "sg:postcode":"7740",
    "sg:province":"Hainaut",
    "wof:name":"L\u00b4univers Express",
    "wof:placetype":"venue"
},
  "geometry": {"coordinates":[3.3442220688,50.7042694092],"type":"Point"}
}