{
  "type": "Feature",
  "properties": {
    "iso:country":"BE",
    "sg:address":"Blekerijstraat 187",
    "sg:city":"Izegem",
    "sg:classifiers":[
        {
            "category":"Home & Garden",
            "subcategory":"Carpets & Floor Coverings",
            "type":"Retail Goods"
        }
    ],
    "sg:phone":"+32 51 30 17 80",
    "sg:postcode":"8870",
    "sg:province":"West-Vlaanderen",
    "sg:tags":[
        "layer",
        "mosaicists"
    ],
    "wof:name":"Vankeirsbilck Ronny Bvba",
    "wof:placetype":"venue"
},
  "geometry": {"coordinates":[3.2001841068,50.8993034363],"type":"Point"}
}