{
  "type": "Feature",
  "properties": {
    "iso:country":"BE",
    "sg:address":"Clem. Vanophemstraat 96",
    "sg:city":"Overijse",
    "sg:classifiers":[
        {
            "category":"Retail",
            "subcategory":"Auto Repair",
            "type":"Services"
        }
    ],
    "sg:phone":"+32 2 687 74 41",
    "sg:postcode":"3090",
    "sg:province":"Vlaams-Brabant",
    "sg:tags":[
        "garage"
    ],
    "wof:name":"Gar Michel",
    "wof:placetype":"venue"
},
  "geometry": {"coordinates":[4.529791832,50.7827148438],"type":"Point"}
}