{
  "type": "Feature",
  "properties": {
    "iso:country":"BE",
    "sg:address":"Route De Mons 245",
    "sg:city":"Binche (waudrez)",
    "sg:orig_category":"Autombile concessionaires",
    "sg:phone":"+32 64 36 75 96",
    "sg:postcode":"7131",
    "sg:province":"Hainaut",
    "wof:name":"Toyota-sturbois",
    "wof:placetype":"venue"
},
  "geometry": {"coordinates":[4.1517601013,50.4148521423],"type":"Point"}
}