{
  "type": "Feature",
  "properties": {
    "addr:full":"Oostwinkeldorp 31 Zomergem Oost-Vlaanderen 9931",
    "addr:housenumber":"31",
    "addr:postcode":"9931",
    "addr:street":"Oostwinkeldorp",
    "iso:country":"BE",
    "sg:address":"Oostwinkeldorp 31",
    "sg:city":"Zomergem",
    "sg:orig_category":"Epiceries",
    "sg:phone":"+32 9 377 07 85",
    "sg:postcode":"9931",
    "sg:province":"Oost-Vlaanderen",
    "wof:name":"M. Vercauteren",
    "wof:placetype":"venue"
},
  "geometry": {"coordinates":[3.5257570744,51.1507415771],"type":"Point"}
}