{
  "type": "Feature",
  "properties": {
    "iso:country":"BE",
    "sg:address":"Markt 1",
    "sg:city":"Ruiselede",
    "sg:orig_category":"S\u00e9lection de personnel and placement",
    "sg:phone":"+32 51 68 79 85",
    "sg:postcode":"8755",
    "sg:province":"West-Vlaanderen",
    "wof:name":"Pwa Ruiselede",
    "wof:placetype":"venue"
},
  "geometry": {"coordinates":[3.3970119953,51.0410118103],"type":"Point"}
}