{
  "type": "Feature",
  "properties": {
    "addr:full":"Quai Verboeckhoven 5 Komen-waasten/comines-warneton Hainaut 7784",
    "addr:housenumber":"5;7784",
    "addr:street":"Quai Verboeckhoven",
    "iso:country":"BE",
    "sg:address":"Quai Verboeckhoven 5",
    "sg:city":"Komen-waasten/comines-warneton",
    "sg:classifiers":[
        {
            "category":"Autos & Motor Vehicles",
            "subcategory":"Fuel & Gas Station",
            "type":"Retail Goods"
        }
    ],
    "sg:phone":"+32 56 55 79 37",
    "sg:postcode":"7784",
    "sg:province":"Hainaut",
    "sg:tags":[
        "stations-service",
        "carburants"
    ],
    "wof:name":"Ets. Laco",
    "wof:placetype":"venue"
},
  "geometry": {"coordinates":[2.9496901035,50.7516593933],"type":"Point"}
}