{
  "type": "Feature",
  "properties": {
    "iso:country":"BE",
    "sg:address":"Gentseweg 176",
    "sg:city":"Waregem",
    "sg:orig_category":"Architectes",
    "sg:phone":"+32 56 72 42 80",
    "sg:postcode":"8792",
    "sg:province":"West-Vlaanderen",
    "wof:name":"Tim Callier",
    "wof:placetype":"venue"
},
  "geometry": {"coordinates":[3.3743400574,50.8867797852],"type":"Point"}
}