{
  "type": "Feature",
  "properties": {
    "iso:country":"BE",
    "sg:address":"Wolsemstraat 38",
    "sg:city":"Dilbeek",
    "sg:orig_category":"Boekhouders",
    "sg:phone":"+32 2 463 55 83",
    "sg:postcode":"1700",
    "sg:province":"Vlaams-Brabant",
    "wof:name":"Jo\u00cblle Van Israel",
    "wof:placetype":"venue"
},
  "geometry": {"coordinates":[4.2423210144,50.8671073914],"type":"Point"}
}