{
  "type": "Feature",
  "properties": {
    "addr:full":"Rue De Fauquez 35 Ittre Brabant Wallon 1460",
    "addr:housenumber":"35;1460",
    "addr:street":"Rue De Fauquez",
    "iso:country":"BE",
    "sg:address":"Rue De Fauquez 35",
    "sg:city":"Ittre",
    "sg:classifiers":[
        {
            "category":"Health Services",
            "subcategory":"Doctor",
            "type":"Services"
        }
    ],
    "sg:phone":"+32 67 64 63 21",
    "sg:postcode":"1460",
    "sg:province":"Brabant Wallon",
    "sg:tags":[
        "medicinephysicians",
        "surgeon"
    ],
    "wof:name":"Dereme T",
    "wof:placetype":"venue"
},
  "geometry": {"coordinates":[4.2479109764,50.6299057007],"type":"Point"}
}