{
  "type": "Feature",
  "properties": {
    "addr:full":"Paterstraat 2 Deinze Oost-Vlaanderen 9800",
    "addr:housenumber":"2",
    "addr:postcode":"9800",
    "addr:street":"Paterstraat",
    "iso:country":"BE",
    "sg:address":"Paterstraat 2",
    "sg:city":"Deinze",
    "sg:orig_category":"Eleveurs de bovins. Eleveurs and marchands de porcs",
    "sg:phone":"+32 9 386 68 01",
    "sg:postcode":"9800",
    "sg:province":"Oost-Vlaanderen",
    "wof:name":"Laurent De Clercq",
    "wof:placetype":"venue"
},
  "geometry": {"coordinates":[3.5852088928,50.9831542969],"type":"Point"}
}