{
  "type": "Feature",
  "properties": {
    "addr:full":"Quinten Matsijslei 17 Box 11 Antwerpen Antwerpen 2018",
    "addr:housenumber":"17 box 11",
    "addr:postcode":"2018",
    "iso:country":"BE",
    "sg:address":"Quinten Matsijslei 17 Box 11",
    "sg:city":"Antwerpen",
    "sg:classifiers":[
        {
            "category":"Professional",
            "subcategory":"Lawyer & Legal Services",
            "type":"Services"
        }
    ],
    "sg:phone":"+32 3 231 42 75",
    "sg:postcode":"2018",
    "sg:province":"Antwerpen",
    "sg:tags":[
        "notary"
    ],
    "wof:name":"De Raeymaecker K",
    "wof:placetype":"venue"
},
  "geometry": {"coordinates":[4.4165349007,51.213886261],"type":"Point"}
}