{
  "type": "Feature",
  "properties": {
    "iso:country":"BE",
    "sg:address":"Avenue De La Pr\u00e9voyance 10",
    "sg:city":"Charleroi (marcinelle)",
    "sg:classifiers":[
        {
            "category":"Health Services",
            "subcategory":"Doctor",
            "type":"Services"
        }
    ],
    "sg:phone":"+32 71 36 66 42",
    "sg:postcode":"6001",
    "sg:province":"Hainaut",
    "sg:tags":[
        "medicinephysicians",
        "surgeon"
    ],
    "wof:name":"Dourlet A",
    "wof:placetype":"venue"
},
  "geometry": {"coordinates":[4.4564328194,50.3806762695],"type":"Point"}
}