{
  "type": "Feature",
  "properties": {
    "iso:country":"BE",
    "sg:address":"Avenue De La Station 113",
    "sg:city":"Gembloux",
    "sg:orig_category":"Entretien et r\u00e9parations de v\u00e9hicules \u00e0 domicile",
    "sg:phone":"+32 81 61 13 09",
    "sg:postcode":"5030",
    "sg:province":"Namur",
    "wof:name":"Fe. Duchene-jadot",
    "wof:placetype":"venue"
},
  "geometry": {"coordinates":[4.6921710968,50.5691986084],"type":"Point"}
}