{
  "type": "Feature",
  "properties": {
    "addr:full":"Rue Julien Lahaut 56a Morlanwelz (morlanwelz-mariemont) Hainaut 7140",
    "addr:housenumber":"56a",
    "addr:postcode":"7140",
    "addr:street":"Rue Julien Lahaut",
    "iso:country":"BE",
    "sg:address":"Rue Julien Lahaut 56a",
    "sg:city":"Morlanwelz (morlanwelz-mariemont)",
    "sg:classifiers":[
        {
            "category":"Insurance",
            "subcategory":"Insurance Agent",
            "type":"Services"
        }
    ],
    "sg:phone":"+32 64 77 29 00",
    "sg:postcode":"7140",
    "sg:province":"Hainaut",
    "sg:tags":[
        "broker"
    ],
    "wof:name":"Tacal Cemal",
    "wof:placetype":"venue"
},
  "geometry": {"coordinates":[4.2483000755,50.4520645142],"type":"Point"}
}