{
  "type": "Feature",
  "properties": {
    "addr:full":"Blijveld 10 Hoegaarden Vlaams-Brabant 3320",
    "addr:housenumber":"10",
    "addr:postcode":"3320",
    "addr:street":"Blijveld",
    "iso:country":"BE",
    "sg:address":"Blijveld 10",
    "sg:city":"Hoegaarden",
    "sg:classifiers":[
        {
            "category":"Professional",
            "subcategory":"Engineering",
            "type":"Services"
        }
    ],
    "sg:phone":"+32 16 76 08 87",
    "sg:postcode":"3320",
    "sg:province":"Vlaams-Brabant",
    "sg:tags":[
        "machine",
        "-",
        "environment",
        "equipment",
        "machinery",
        "mechanical"
    ],
    "wof:name":"B.g.s. Nv",
    "wof:placetype":"venue"
},
  "geometry": {"coordinates":[4.8881611824,50.7744941711],"type":"Point"}
}