{
  "type": "Feature",
  "properties": {
    "iso:country":"BE",
    "sg:address":"Les Sarts 16",
    "sg:city":"Vielsalm",
    "sg:orig_category":"Voertuigen",
    "sg:phone":"+32 80 41 86 94",
    "sg:postcode":"6690",
    "sg:province":"Luxembourg",
    "wof:name":"Garage Francis Monfort",
    "wof:placetype":"venue"
},
  "geometry": {"coordinates":[5.8564100266,50.2668609619],"type":"Point"}
}