{
  "type": "Feature",
  "properties": {
    "addr:full":"Rue Du Village 84 Voeren/fourons Limburg 3790",
    "addr:housenumber":"84",
    "addr:postcode":"3790",
    "addr:street":"Rue Du Village",
    "iso:country":"BE",
    "sg:address":"Rue Du Village 84",
    "sg:city":"Voeren/fourons",
    "sg:orig_category":"Editeurs de livres. Disquaires",
    "sg:phone":"+32 4 381 23 28",
    "sg:postcode":"3790",
    "sg:province":"Limburg",
    "wof:name":"Hafabra Music",
    "wof:placetype":"venue"
},
  "geometry": {"coordinates":[5.8454608917,50.7517814636],"type":"Point"}
}