{
  "type": "Feature",
  "properties": {
    "addr:full":"Chemin De Berlieren 11 Plombieres/plombieres Li\u00e8ge 4852",
    "addr:housenumber":"11",
    "addr:postcode":"4852",
    "addr:street":"Chemin De Berlieren",
    "iso:country":"BE",
    "sg:address":"Chemin De Berlieren 11",
    "sg:city":"Plombieres/plombieres",
    "sg:orig_category":"Eleveurs de bovins",
    "sg:phone":"+32 87 78 40 10",
    "sg:postcode":"4852",
    "sg:province":"Li\u00e8ge",
    "wof:name":"Rene Locht",
    "wof:placetype":"venue"
},
  "geometry": {"coordinates":[5.9204001427,50.7230834961],"type":"Point"}
}