{
  "type": "Feature",
  "properties": {
    "addr:full":"Rue Hurlugeai 10 Ham-sur-heure-nalinnes (cour-sur-heure) Hainaut 6120",
    "addr:housenumber":"10",
    "addr:postcode":"6120",
    "addr:street":"Rue Hurlugeai;Cour-Sur-Heure Hainaut",
    "iso:country":"BE",
    "sg:address":"Rue Hurlugeai 10",
    "sg:city":"Ham-sur-heure-nalinnes (cour-sur-heure)",
    "sg:classifiers":[
        {
            "category":"Health Services",
            "subcategory":"Health Practitioner",
            "type":"Services"
        }
    ],
    "sg:phone":"+32 71 21 85 55",
    "sg:postcode":"6120",
    "sg:province":"Hainaut",
    "sg:tags":[
        "therapist",
        "speech"
    ],
    "wof:name":"Panier V",
    "wof:placetype":"venue"
},
  "geometry": {"coordinates":[4.3942718506,50.3008117676],"type":"Point"}
}