{
  "type": "Feature",
  "properties": {
    "addr:full":"Kleine Schardauw 48 Waregem West-Vlaanderen 8880",
    "addr:housenumber":"48",
    "addr:postcode":"8880",
    "iso:country":"BE",
    "sg:address":"Kleine Schardauw 48",
    "sg:city":"Waregem",
    "sg:orig_category":"Verlichting and huishoudartikelen",
    "sg:phone":"+32 56 50 66 48",
    "sg:postcode":"8880",
    "sg:province":"West-Vlaanderen",
    "wof:name":"Vroman",
    "wof:placetype":"venue"
},
  "geometry": {"coordinates":[3.4314699173,50.887348175],"type":"Point"}
}