{
  "type": "Feature",
  "properties": {
    "addr:full":"Hoevenzavellaan 28 Genk (waterschei) Limburg 3600",
    "addr:housenumber":"28",
    "addr:postcode":"3600",
    "addr:street":"Hoevenzavellaan",
    "iso:country":"BE",
    "sg:address":"Hoevenzavellaan 28",
    "sg:city":"Genk (waterschei)",
    "sg:classifiers":[
        {
            "category":"Casinos & Gambling",
            "type":"Entertainment"
        }
    ],
    "sg:phone":"+32 89 84 44 21",
    "sg:postcode":"3600",
    "sg:province":"Limburg",
    "wof:name":"Royal Ascot",
    "wof:placetype":"venue"
},
  "geometry": {"coordinates":[5.5076398849,51.0010604858],"type":"Point"}
}