{
  "type": "Feature",
  "properties": {
    "iso:country":"BE",
    "sg:address":"Mechelbaan 15",
    "sg:city":"Mechelen",
    "sg:orig_category":"Advocaten and juridische adviseurs",
    "sg:phone":"+32 15 27 73 98",
    "sg:postcode":"2801",
    "sg:province":"Antwerpen",
    "wof:name":"Katrien Van Der Borcht",
    "wof:placetype":"venue"
},
  "geometry": {"coordinates":[4.4239411354,51.0439910889],"type":"Point"}
}