{
  "type": "Feature",
  "properties": {
    "iso:country":"BE",
    "sg:address":"Heirentstraat 6",
    "sg:city":"Meulebeke",
    "sg:orig_category":"Rundveehouders",
    "sg:phone":"+32 51 40 10 86",
    "sg:postcode":"8760",
    "sg:province":"West-Vlaanderen",
    "wof:name":"Jose Deriemaeker",
    "wof:placetype":"venue"
},
  "geometry": {"coordinates":[3.3465158939,50.958896637],"type":"Point"}
}