{
  "type": "Feature",
  "properties": {
    "addr:full":"Gotevlietstraat 1 Brugge West-Vlaanderen 8000",
    "addr:housenumber":"1",
    "addr:postcode":"8000",
    "addr:street":"Gotevlietstraat",
    "iso:country":"BE",
    "sg:address":"Gotevlietstraat 1",
    "sg:city":"Brugge",
    "sg:orig_category":"HUISBRANDOLIE",
    "sg:phone":"+32 50 31 76 66",
    "sg:postcode":"8000",
    "sg:province":"West-Vlaanderen",
    "wof:name":"Probelgas",
    "wof:placetype":"venue"
},
  "geometry": {"coordinates":[3.204857111,51.2641487122],"type":"Point"}
}