{
  "type": "Feature",
  "properties": {
    "iso:country":"BE",
    "sg:address":"Rue De Bois D'haine 17",
    "sg:city":"La Louvi\u00e8re (chapelle Aux Puits)",
    "sg:classifiers":[
        {
            "category":"Professional",
            "subcategory":"Testing Lab",
            "type":"Services"
        }
    ],
    "sg:phone":"+32 64 55 54 61",
    "sg:postcode":"7100",
    "sg:province":"Hainaut",
    "sg:tags":[
        "chemist"
    ],
    "wof:name":"Lamotte C",
    "wof:placetype":"venue"
},
  "geometry": {"coordinates":[4.2171669006,50.4742736816],"type":"Point"}
}