{
  "type": "Feature",
  "properties": {
    "iso:country":"BE",
    "sg:address":"Vall\u00c9e \u00c0 La Dame 8",
    "sg:city":"Lasne",
    "sg:orig_category":"Landmeters",
    "sg:phone":"+32 2 633 47 09",
    "sg:postcode":"1380",
    "sg:province":"Brabant Wallon",
    "wof:name":"Didier Neuwels",
    "wof:placetype":"venue"
},
  "geometry": {"coordinates":[4.483235836,50.6850166321],"type":"Point"}
}