{
  "type": "Feature",
  "properties": {
    "addr:full":"Gewerbestrasse 11 Eupen Li\u00e8ge 4700",
    "addr:housenumber":"11",
    "addr:postcode":"4700",
    "addr:street":"Gewerbestrasse",
    "iso:country":"BE",
    "sg:address":"Gewerbestrasse 11",
    "sg:city":"Eupen",
    "sg:classifiers":[
        {
            "category":"Home & Garden",
            "subcategory":"Carpets & Floor Coverings",
            "type":"Retail Goods"
        }
    ],
    "sg:phone":"+32 87 59 51 11",
    "sg:postcode":"4700",
    "sg:province":"Li\u00e8ge",
    "sg:tags":[
        "-"
    ],
    "wof:name":"Scholl Sa",
    "wof:placetype":"venue"
},
  "geometry": {"coordinates":[6.0131721497,50.6375770569],"type":"Point"}
}