{
  "type": "Feature",
  "properties": {
    "addr:full":"Bergstraat 79 Moeskroen Hainaut 7700",
    "addr:housenumber":"79",
    "addr:postcode":"7700",
    "addr:street":"Bergstraat;Hainaut",
    "iso:country":"BE",
    "sg:address":"Bergstraat 79",
    "sg:city":"Moeskroen",
    "sg:orig_category":"Kaardwolvezels Fab",
    "sg:phone":"+32 56 85 01 60",
    "sg:postcode":"7700",
    "sg:province":"Hainaut",
    "wof:name":"Desseaux Spinning Company",
    "wof:placetype":"venue"
},
  "geometry": {"coordinates":[3.229845047,50.7357406616],"type":"Point"}
}