{
  "type": "Feature",
  "properties": {
    "addr:full":"Nieuwstraat 69 Lede Oost-Vlaanderen 9340",
    "addr:housenumber":"69",
    "addr:postcode":"9340",
    "addr:street":"Nieuwstraat",
    "iso:country":"BE",
    "sg:address":"Nieuwstraat 69",
    "sg:city":"Lede",
    "sg:classifiers":[
        {
            "category":"Personal",
            "subcategory":"Barber",
            "type":"Services"
        }
    ],
    "sg:phone":"+32 53 80 41 11",
    "sg:postcode":"9340",
    "sg:province":"Oost-Vlaanderen",
    "sg:tags":[
        "gentleman",
        "salon",
        "-",
        "hairdressing"
    ],
    "wof:name":"Francois",
    "wof:placetype":"venue"
},
  "geometry": {"coordinates":[3.9825880527,50.9654312134],"type":"Point"}
}