{
  "type": "Feature",
  "properties": {
    "iso:country":"BE",
    "sg:address":"Grotestraat 40-42",
    "sg:city":"Geraardsbergen",
    "sg:orig_category":"Opticiens",
    "sg:phone":"+32 54 41 92 96",
    "sg:postcode":"9500",
    "sg:province":"Oost-Vlaanderen",
    "wof:name":"Lorens Optiek",
    "wof:placetype":"venue"
},
  "geometry": {"coordinates":[3.8771359921,50.7716598511],"type":"Point"}
}