{
  "type": "Feature",
  "properties": {
    "addr:full":"Koning Boudewijnlaan 16 Wuustwezel Antwerpen 2990",
    "addr:housenumber":"16",
    "addr:postcode":"2990",
    "addr:street":"Koning Boudewijnlaan",
    "iso:country":"BE",
    "sg:address":"Koning Boudewijnlaan 16",
    "sg:city":"Wuustwezel",
    "sg:orig_category":"Loodgieterij, verwarming and sanitaire installaties",
    "sg:phone":"+32 3 669 95 40",
    "sg:postcode":"2990",
    "sg:province":"Antwerpen",
    "wof:name":"R. Van Velthoven",
    "wof:placetype":"venue"
},
  "geometry": {"coordinates":[4.6439990997,51.4017295837],"type":"Point"}
}