{
  "type": "Feature",
  "properties": {
    "addr:full":"Rue Lambermont 19 Rixensart Brabant Wallon 1330",
    "addr:housenumber":"19",
    "addr:postcode":"1330",
    "addr:street":"Rue Lambermont;Wallon",
    "iso:country":"BE",
    "sg:address":"Rue Lambermont 19",
    "sg:city":"Rixensart",
    "sg:orig_category":"Dierenartsen",
    "sg:phone":"+32 2 652 04 30",
    "sg:postcode":"1330",
    "sg:province":"Brabant Wallon",
    "wof:name":"Bernard Bradfer",
    "wof:placetype":"venue"
},
  "geometry": {"coordinates":[4.5055751801,50.7088851929],"type":"Point"}
}