{
  "type": "Feature",
  "properties": {
    "iso:country":"BE",
    "sg:address":"Kruisstraat 31",
    "sg:city":"Dendermonde",
    "sg:orig_category":"Entretien and r\u00e9parations de voitures",
    "sg:phone":"+32 52 21 71 76",
    "sg:postcode":"9200",
    "sg:province":"Oost-Vlaanderen",
    "wof:name":"Garage Robert",
    "wof:placetype":"venue"
},
  "geometry": {"coordinates":[4.1136832237,51.0105209351],"type":"Point"}
}