{
  "type": "Feature",
  "properties": {
    "addr:full":"Koning Albertstraat 77 Mechelen Antwerpen 2800",
    "addr:housenumber":"77",
    "addr:postcode":"2800",
    "addr:street":"Koning Albertstraat",
    "iso:country":"BE",
    "sg:address":"Koning Albertstraat 77",
    "sg:city":"Mechelen",
    "sg:classifiers":[
        {
            "category":"Bakery",
            "type":"Food & Drink"
        }
    ],
    "sg:phone":"+32 15 20 41 99",
    "sg:postcode":"2800",
    "sg:province":"Antwerpen",
    "sg:tags":[
        "confectioner",
        "baker"
    ],
    "wof:name":"Sven",
    "wof:placetype":"venue"
},
  "geometry": {"coordinates":[4.470582962,51.025642395],"type":"Point"}
}