{
  "type": "Feature",
  "properties": {
    "iso:country":"BE",
    "sg:address":"Chauss\u00e9e D' Ellezelles 510",
    "sg:city":"Renaix",
    "sg:classifiers":[
        {
            "category":"Home & Garden",
            "subcategory":"Carpets & Floor Coverings",
            "type":"Retail Goods"
        }
    ],
    "sg:phone":"+32 55 21 53 66",
    "sg:postcode":"9600",
    "sg:province":"Oost-Vlaanderen",
    "sg:tags":[
        "tile"
    ],
    "wof:name":"Delange J",
    "wof:placetype":"venue"
},
  "geometry": {"coordinates":[3.6384840012,50.7324676514],"type":"Point"}
}