{
  "type": "Feature",
  "properties": {
    "addr:full":"Rue Nestor Jonet 118 Courcelles Hainaut 6180",
    "addr:housenumber":"118",
    "addr:postcode":"6180",
    "addr:street":"Rue Nestor Jonet",
    "iso:country":"BE",
    "sg:address":"Rue Nestor Jonet 118",
    "sg:city":"Courcelles",
    "sg:classifiers":[
        {
            "category":"Home & Garden",
            "subcategory":"Home Furnishings",
            "type":"Retail Goods"
        }
    ],
    "sg:phone":"+32 71 45 07 84",
    "sg:postcode":"6180",
    "sg:province":"Hainaut",
    "sg:tags":[
        "interior",
        "decoration"
    ],
    "wof:name":"Goossens J-l",
    "wof:placetype":"venue"
},
  "geometry": {"coordinates":[4.3872499466,50.4645347595],"type":"Point"}
}