{
  "type": "Feature",
  "properties": {
    "addr:full":"Brandstraat 23 Ruiselede West-Vlaanderen 8755",
    "addr:housenumber":"23",
    "addr:postcode":"8755",
    "addr:street":"Brandstraat",
    "iso:country":"BE",
    "sg:address":"Brandstraat 23",
    "sg:city":"Ruiselede",
    "sg:orig_category":"Jardinage",
    "sg:phone":"+32 51 68 78 27",
    "sg:postcode":"8755",
    "sg:province":"West-Vlaanderen",
    "wof:name":"Aneca D",
    "wof:placetype":"venue"
},
  "geometry": {"coordinates":[3.357667923,51.0680160522],"type":"Point"}
}