{
  "type": "Feature",
  "properties": {
    "iso:country":"BE",
    "sg:address":"Gordunakaai 56",
    "sg:city":"Gent",
    "sg:classifiers":[
        {
            "category":"Health Services",
            "subcategory":"Doctor",
            "type":"Services"
        }
    ],
    "sg:phone":"+32 9 225 12 81",
    "sg:postcode":"9000",
    "sg:province":"Oost-Vlaanderen",
    "sg:tags":[
        "medicinephysicians",
        "surgeon"
    ],
    "wof:name":"Hermans Walter",
    "wof:placetype":"venue"
},
  "geometry": {"coordinates":[3.7058880329,51.0430335999],"type":"Point"}
}