{
  "type": "Feature",
  "properties": {
    "iso:country":"BE",
    "sg:address":"Sint-bernardse Steenweg 772",
    "sg:city":"Antwerpen (hoboken)",
    "sg:classifiers":[
        {
            "category":"Shopping",
            "subcategory":"Computers & Home Electronics",
            "type":"Retail Goods"
        }
    ],
    "sg:phone":"+32 3 828 11 17",
    "sg:postcode":"2660",
    "sg:province":"Antwerpen",
    "sg:tags":[
        "-",
        "television",
        "radio"
    ],
    "wof:name":"Davits",
    "wof:placetype":"venue"
},
  "geometry": {"coordinates":[4.3397898674,51.1732788086],"type":"Point"}
}