{
  "type": "Feature",
  "properties": {
    "addr:full":"Boswegel 6 Stekene (kemzeke) Oost-Vlaanderen 9190",
    "addr:housenumber":"6",
    "addr:postcode":"9190",
    "addr:street":"Boswegel",
    "iso:country":"BE",
    "sg:address":"Boswegel 6",
    "sg:city":"Stekene (kemzeke)",
    "sg:classifiers":[
        {
            "category":"Freight",
            "type":"Transportation"
        }
    ],
    "sg:phone":"+32 3 789 25 40",
    "sg:postcode":"9190",
    "sg:province":"Oost-Vlaanderen",
    "sg:tags":[
        "express",
        "transport"
    ],
    "wof:name":"Speed",
    "wof:placetype":"venue"
},
  "geometry": {"coordinates":[4.0556540489,51.2331886292],"type":"Point"}
}