{
  "type": "Feature",
  "properties": {
    "addr:full":"Kapellei 158 Zoersel Antwerpen 2980",
    "addr:housenumber":"158",
    "addr:postcode":"2980",
    "addr:street":"Kapellei",
    "iso:country":"BE",
    "sg:address":"Kapellei 158",
    "sg:city":"Zoersel",
    "sg:classifiers":[
        {
            "category":"Shopping",
            "subcategory":"Photographic Equipment",
            "type":"Retail Goods"
        }
    ],
    "sg:phone":"+32 3 383 09 05",
    "sg:postcode":"2980",
    "sg:province":"Antwerpen",
    "sg:tags":[
        "supplie",
        "billiard",
        "-"
    ],
    "wof:name":"Biljartfabriek Duqu\u00e9",
    "wof:placetype":"venue"
},
  "geometry": {"coordinates":[4.6246089935,51.2579803467],"type":"Point"}
}