{
  "type": "Feature",
  "properties": {
    "iso:country":"BE",
    "sg:address":"Bossevelden 18",
    "sg:city":"Putte",
    "sg:orig_category":"Fietsen",
    "sg:phone":"+32 15 75 29 74",
    "sg:postcode":"2580",
    "sg:province":"Antwerpen",
    "wof:name":"Benedictus Giudici",
    "wof:placetype":"venue"
},
  "geometry": {"coordinates":[4.6288099289,51.0548591614],"type":"Point"}
}