{
  "type": "Feature",
  "properties": {
    "addr:full":"Berkenstraat 8 Maarkedal (etikhove) Oost-Vlaanderen 9680",
    "addr:housenumber":"8",
    "addr:postcode":"9680",
    "addr:street":"Berkenstraat",
    "iso:country":"BE",
    "sg:address":"Berkenstraat 8",
    "sg:city":"Maarkedal (etikhove)",
    "sg:classifiers":[
        {
            "category":"Building & Trades",
            "subcategory":"Landscaping Services",
            "type":"Services"
        }
    ],
    "sg:phone":"+32 9 228 10 25",
    "sg:postcode":"9680",
    "sg:province":"Oost-Vlaanderen",
    "sg:tags":[
        "equipment",
        "swimming",
        "-",
        "pool",
        "contractor"
    ],
    "wof:name":"Jm Pools",
    "wof:placetype":"venue"
},
  "geometry": {"coordinates":[3.6252229214,50.8136787415],"type":"Point"}
}