{
  "type": "Feature",
  "properties": {
    "iso:country":"BE",
    "sg:address":"Pannenhuisstraat 7",
    "sg:city":"Stekene",
    "sg:orig_category":"Enseignement maternel and primaire",
    "sg:phone":"+32 9 346 95 61",
    "sg:postcode":"9190",
    "sg:province":"Oost-Vlaanderen",
    "wof:name":"Vrije Basisschool",
    "wof:placetype":"venue"
},
  "geometry": {"coordinates":[3.990582943,51.1862068176],"type":"Point"}
}