{
  "type": "Feature",
  "properties": {
    "iso:country":"BE",
    "sg:address":"Eikstraat 5",
    "sg:city":"Brussel/bruxelles",
    "sg:classifiers":[
        {
            "category":"Cafe",
            "type":"Food & Drink"
        }
    ],
    "sg:phone":"+32 2 511 92 62",
    "sg:postcode":"1000",
    "sg:province":"Bruxelles-Capitale",
    "sg:tags":[
        "caf\u00e9s"
    ],
    "wof:name":"Le Poechenellekelder",
    "wof:placetype":"venue"
},
  "geometry": {"coordinates":[4.3500580788,50.844619751],"type":"Point"}
}