{
  "type": "Feature",
  "properties": {
    "iso:country":"BE",
    "sg:address":"Robaardstraat 6",
    "sg:city":"Oostkamp (ruddervoorde)",
    "sg:classifiers":[
        {
            "category":"Building & Trades",
            "subcategory":"Plumbing",
            "type":"Services"
        }
    ],
    "sg:phone":"+32 50 27 98 30",
    "sg:postcode":"8020",
    "sg:province":"West-Vlaanderen",
    "sg:tags":[
        "contractor"
    ],
    "wof:name":"Devriendt W",
    "wof:placetype":"venue"
},
  "geometry": {"coordinates":[3.2105669975,51.0797767639],"type":"Point"}
}