{
  "type": "Feature",
  "properties": {
    "iso:country":"BE",
    "sg:address":"Rue Adelin Beguin 10",
    "sg:city":"Fosses-la-ville (sart-saint-laurent)",
    "sg:classifiers":[
        {
            "category":"Shopping",
            "subcategory":"Antiques",
            "type":"Retail Goods"
        }
    ],
    "sg:phone":"+32 71 71 46 35",
    "sg:postcode":"5070",
    "sg:province":"Namur",
    "wof:name":"Lemaire C",
    "wof:placetype":"venue"
},
  "geometry": {"coordinates":[4.7374677658,50.4041938782],"type":"Point"}
}