{
  "type": "Feature",
  "properties": {
    "addr:full":"Krijgsbaan 124 Wijnegem Antwerpen 2110",
    "addr:housenumber":"124",
    "addr:postcode":"2110",
    "addr:street":"Krijgsbaan",
    "iso:country":"BE",
    "sg:address":"Krijgsbaan 124",
    "sg:city":"Wijnegem",
    "sg:orig_category":"Benzinestations and brandstoffen",
    "sg:phone":"+32 3 353 27 28",
    "sg:postcode":"2110",
    "sg:province":"Antwerpen",
    "wof:name":"Esso",
    "wof:placetype":"venue"
},
  "geometry": {"coordinates":[4.4958138466,51.2176971436],"type":"Point"}
}