{
  "type": "Feature",
  "properties": {
    "iso:country":"BE",
    "sg:address":"Rue D'antoing 61",
    "sg:city":"Tournai (vaulx)",
    "sg:classifiers":[
        {
            "category":"Building & Trades",
            "subcategory":"Plumbing",
            "type":"Services"
        }
    ],
    "sg:phone":"+32 69 84 02 98",
    "sg:postcode":"7536",
    "sg:province":"Hainaut",
    "sg:tags":[
        "repair",
        "mainten",
        "-",
        "central",
        "heating"
    ],
    "wof:name":"Deprekel Sprl",
    "wof:placetype":"venue"
},
  "geometry": {"coordinates":[3.4056789875,50.5963935852],"type":"Point"}
}