{
  "type": "Feature",
  "properties": {
    "addr:full":"Rue Des D\u00e9port\u00e9s 123 Verviers Li\u00e8ge 4800",
    "addr:housenumber":"123",
    "addr:postcode":"4800",
    "addr:street":"Rue Des De\u0301Porte\u0301S",
    "iso:country":"BE",
    "sg:address":"Rue Des D\u00e9port\u00e9s 123",
    "sg:city":"Verviers",
    "sg:classifiers":[
        {
            "category":"Professional",
            "subcategory":"Management & Consulting",
            "type":"Services"
        }
    ],
    "sg:phone":"+32 87 29 21 70",
    "sg:postcode":"4800",
    "sg:province":"Li\u00e8ge",
    "sg:tags":[
        "consultant"
    ],
    "wof:name":"Applied Quality Technologies Europe Sprl",
    "wof:placetype":"venue"
},
  "geometry": {"coordinates":[5.8507962227,50.5825996399],"type":"Point"}
}