{
  "type": "Feature",
  "properties": {
    "iso:country":"BE",
    "sg:address":"Magdalenasteenweg 18",
    "sg:city":"Mechelen (muizen)",
    "sg:classifiers":[
        {
            "category":"Bakery",
            "type":"Food & Drink"
        }
    ],
    "sg:phone":"+32 15 41 83 21",
    "sg:postcode":"2812",
    "sg:province":"Antwerpen",
    "sg:tags":[
        "confectioner",
        "baker"
    ],
    "wof:name":"Wilmar",
    "wof:placetype":"venue"
},
  "geometry": {"coordinates":[4.5152568817,51.00989151],"type":"Point"}
}