{
  "type": "Feature",
  "properties": {
    "addr:full":"Rue De L'industrie 17 Binche Hainaut 7134",
    "addr:housenumber":"17",
    "addr:postcode":"7134",
    "addr:street":"Rue De L'Industrie",
    "iso:country":"BE",
    "sg:address":"Rue De L'industrie 17",
    "sg:city":"Binche",
    "sg:orig_category":"Brood, gebak and snoepgoed",
    "sg:phone":"+32 64 33 27 09",
    "sg:postcode":"7134",
    "sg:province":"Hainaut",
    "wof:name":"Boulang. Thirion & Fils",
    "wof:placetype":"venue"
},
  "geometry": {"coordinates":[4.1894111633,50.428981781],"type":"Point"}
}