{
  "type": "Feature",
  "properties": {
    "addr:full":"Meensesteenweg 155 Kortrijk West-Vlaanderen 8501",
    "addr:housenumber":"155",
    "addr:postcode":"8501",
    "addr:street":"Meensesteenweg",
    "iso:country":"BE",
    "sg:address":"Meensesteenweg 155",
    "sg:city":"Kortrijk",
    "sg:orig_category":"Voedingsspeciaalzaken",
    "sg:phone":"+32 56 35 44 85",
    "sg:postcode":"8501",
    "sg:province":"West-Vlaanderen",
    "wof:name":"Langue D'oc",
    "wof:placetype":"venue"
},
  "geometry": {"coordinates":[3.2429089546,50.8272514343],"type":"Point"}
}