{
  "type": "Feature",
  "properties": {
    "addr:full":"Veldstraat 117 Oostrozebeke West-Vlaanderen 8780",
    "addr:housenumber":"117",
    "addr:postcode":"8780",
    "addr:street":"Veldstraat",
    "iso:country":"BE",
    "sg:address":"Veldstraat 117",
    "sg:city":"Oostrozebeke",
    "sg:orig_category":"Ramassage and traitement des d\u00e9chets m\u00e9nagers. D\u00e9molition d\u00b4immeubles and terrassements",
    "sg:phone":"+32 56 66 81 09",
    "sg:postcode":"8780",
    "sg:province":"West-Vlaanderen",
    "wof:name":"Cannie & Co",
    "wof:placetype":"venue"
},
  "geometry": {"coordinates":[3.3525259495,50.9244537354],"type":"Point"}
}