{
  "type": "Feature",
  "properties": {
    "addr:full":"Groenendaallaan 30 Oostende West-Vlaanderen 8400",
    "addr:housenumber":"30",
    "addr:postcode":"8400",
    "addr:street":"Groenendaallaan",
    "iso:country":"BE",
    "sg:address":"Groenendaallaan 30",
    "sg:city":"Oostende",
    "sg:classifiers":[
        {
            "category":"Building & Trades",
            "subcategory":"Cleaning & Sanitation",
            "type":"Services"
        }
    ],
    "sg:phone":"+32 477 46 17 64",
    "sg:postcode":"8400",
    "sg:province":"West-Vlaanderen",
    "sg:tags":[
        "janitor"
    ],
    "wof:name":"Vitro-net",
    "wof:placetype":"venue"
},
  "geometry": {"coordinates":[2.9126999378,51.2312583923],"type":"Point"}
}