{
  "type": "Feature",
  "properties": {
    "iso:country":"BE",
    "sg:address":"Gransveldestraat 39",
    "sg:city":"Wetteren",
    "sg:classifiers":[
        {
            "category":"Travel",
            "subcategory":"Hotels & Motels",
            "type":"Entertainment"
        }
    ],
    "sg:phone":"+32 9 365 06 01",
    "sg:postcode":"9230",
    "sg:province":"Oost-Vlaanderen",
    "wof:name":"Sessibon",
    "wof:placetype":"venue"
},
  "geometry": {"coordinates":[3.871794939,51.0152320862],"type":"Point"}
}