{
  "type": "Feature",
  "properties": {
    "addr:full":"Felix Roggeenmanskaai 17 Buizingen Vlaams-Brabant 1501",
    "addr:housenumber":"17",
    "addr:postcode":"1501",
    "iso:country":"BE",
    "sg:address":"Felix Roggeenmanskaai 17",
    "sg:city":"Buizingen",
    "sg:classifiers":[
        {
            "category":"Manufacturing",
            "subcategory":"Metals",
            "type":"Manufacturing & Wholesale Goods"
        }
    ],
    "sg:phone":"+32 2 360 12 82",
    "sg:postcode":"1501",
    "sg:province":"Vlaams-Brabant",
    "sg:tags":[
        "metallurgy",
        "metalworking",
        "processing"
    ],
    "wof:name":"Rap Nv",
    "wof:placetype":"venue"
},
  "geometry": {"coordinates":[4.247469902,50.7452087402],"type":"Point"}
}