{
  "type": "Feature",
  "properties": {
    "addr:full":"Molenwalstraat 6 Veurne West-Vlaanderen 8630",
    "addr:housenumber":"6",
    "addr:postcode":"8630",
    "addr:street":"Molenwalstraat",
    "iso:country":"BE",
    "sg:address":"Molenwalstraat 6",
    "sg:city":"Veurne",
    "sg:orig_category":"Eleveurs de bovins",
    "sg:phone":"+32 58 29 93 22",
    "sg:postcode":"8630",
    "sg:province":"West-Vlaanderen",
    "wof:name":"Hubert Patfoort",
    "wof:placetype":"venue"
},
  "geometry": {"coordinates":[2.5978190899,51.0096359253],"type":"Point"}
}