{
  "type": "Feature",
  "properties": {
    "addr:full":"Vinkstraat 6 Hechtel-eksel (hechtel) Limburg 3940",
    "addr:housenumber":"6",
    "addr:postcode":"3940",
    "addr:street":"Vinkstraat",
    "iso:country":"BE",
    "sg:address":"Vinkstraat 6",
    "sg:city":"Hechtel-eksel (hechtel)",
    "sg:classifiers":[
        {
            "category":"Social Services",
            "subcategory":"Job Training",
            "type":"Services"
        }
    ],
    "sg:phone":"+32 11 66 59 94",
    "sg:postcode":"3940",
    "sg:province":"Limburg",
    "sg:tags":[
        "coordinator",
        "safety"
    ],
    "wof:name":"Bouwbegeleiding Loos",
    "wof:placetype":"venue"
},
  "geometry": {"coordinates":[5.364795208,51.1255340576],"type":"Point"}
}