{
  "type": "Feature",
  "properties": {
    "iso:country":"BE",
    "sg:address":"Rue De La Vall\u00c9e 115",
    "sg:city":"Chatelet",
    "sg:orig_category":"Advocaten and juridische adviseurs",
    "sg:phone":"+32 71 38 32 85",
    "sg:postcode":"6200",
    "sg:province":"Hainaut",
    "wof:name":"F. Michaux",
    "wof:placetype":"venue"
},
  "geometry": {"coordinates":[4.5169701576,50.4116783142],"type":"Point"}
}