{
  "type": "Feature",
  "properties": {
    "addr:full":"Chauss\u00e9e De Charleroi 444 Jodoigne (jauchelette) Brabant Wallon 1370",
    "addr:housenumber":"444",
    "addr:postcode":"1370",
    "addr:street":"Chausse\u0301E De Charleroi;Wallon",
    "iso:country":"BE",
    "sg:address":"Chauss\u00e9e De Charleroi 444",
    "sg:city":"Jodoigne (jauchelette)",
    "sg:classifiers":[
        {
            "category":"Building & Trades",
            "subcategory":"Construction",
            "type":"Services"
        }
    ],
    "sg:phone":"+32 10 88 82 59",
    "sg:postcode":"1370",
    "sg:province":"Brabant Wallon",
    "sg:tags":[
        "carpenter"
    ],
    "wof:name":"Bajoit Jules Ets (e.b.j. Sprl)",
    "wof:placetype":"venue"
},
  "geometry": {"coordinates":[4.8615598679,50.7133712769],"type":"Point"}
}