{
  "type": "Feature",
  "properties": {
    "addr:full":"Lassonhoflaan 5 Stabroek Antwerpen 2940",
    "addr:housenumber":"5",
    "addr:postcode":"2940",
    "addr:street":"Lassonhoflaan",
    "iso:country":"BE",
    "sg:address":"Lassonhoflaan 5",
    "sg:city":"Stabroek",
    "sg:orig_category":"Bouwmaterialen Gh Dakwerken Plaatsen van vloer- and muurbekleding Vloer- and muurbekleding",
    "sg:phone":"+32 3 569 17 44",
    "sg:postcode":"2940",
    "sg:province":"Antwerpen",
    "wof:name":"G.k.s.",
    "wof:placetype":"venue"
},
  "geometry": {"coordinates":[4.3786430359,51.3360099792],"type":"Point"}
}