{
  "type": "Feature",
  "properties": {
    "addr:full":"879 Chauss\u00e9e De Haecht 1140 Bruxelles 879",
    "addr:housenumber":"879",
    "addr:postcode":"1140;879",
    "addr:street":"Chausse\u0301E De Haecht",
    "iso:country":"BE",
    "sg:address":"879",
    "sg:city":"Chauss\u00e9e De Haecht 1140 Bruxelles",
    "sg:classifiers":[
        {
            "category":"Autos & Motor Vehicles",
            "subcategory":"Automobile Sales",
            "type":"Retail Goods"
        }
    ],
    "sg:phone":"+32 2 242 79 80",
    "sg:postcode":"879",
    "sg:tags":[
        "equipment",
        "industrial",
        "transport"
    ],
    "wof:name":"Leburton Pierre Sprl",
    "wof:placetype":"venue"
},
  "geometry": {"coordinates":[4.4095950127,50.8777656555],"type":"Point"}
}