{
  "type": "Feature",
  "properties": {
    "iso:country":"BE",
    "sg:address":"Korte Dijkstraat 117",
    "sg:city":"Dendermonde",
    "sg:classifiers":[
        {
            "category":"Professional",
            "subcategory":"Accounting & Tax Preparation",
            "type":"Services"
        }
    ],
    "sg:phone":"+32 52 22 33 99",
    "sg:postcode":"9200",
    "sg:province":"Oost-Vlaanderen",
    "sg:tags":[
        "bookkeeper"
    ],
    "wof:name":"Degre Nv",
    "wof:placetype":"venue"
},
  "geometry": {"coordinates":[4.1206297874,51.0303497314],"type":"Point"}
}