{
  "type": "Feature",
  "properties": {
    "iso:country":"BE",
    "sg:address":"Markt 8",
    "sg:city":"Geraardsbergen",
    "sg:classifiers":[
        {
            "category":"Cafe",
            "type":"Food & Drink"
        }
    ],
    "sg:phone":"+32 54 41 92 73",
    "sg:postcode":"9500",
    "sg:province":"Oost-Vlaanderen",
    "sg:tags":[
        "caf\u00e9s"
    ],
    "wof:name":"Timmy De Brucker",
    "wof:placetype":"venue"
},
  "geometry": {"coordinates":[3.8826749325,50.7723960876],"type":"Point"}
}