{
  "type": "Feature",
  "properties": {
    "iso:country":"BE",
    "sg:address":"Pieter Breughelstraat 8",
    "sg:city":"Maaseik",
    "sg:classifiers":[
        {
            "category":"Health Services",
            "subcategory":"Health Practitioner",
            "type":"Services"
        }
    ],
    "sg:phone":"+32 89 56 32 33",
    "sg:postcode":"3680",
    "sg:province":"Limburg",
    "sg:tags":[
        "physiotherapist"
    ],
    "wof:name":"Vancleef Firmin",
    "wof:placetype":"venue"
},
  "geometry": {"coordinates":[5.7841901779,51.1002044678],"type":"Point"}
}