{
  "type": "Feature",
  "properties": {
    "iso:country":"BE",
    "sg:address":"Molenstraat 29",
    "sg:city":"Knesselare",
    "sg:classifiers":[
        {
            "category":"Personal",
            "type":"Services"
        }
    ],
    "sg:phone":"+32 9 374 20 40",
    "sg:postcode":"9910",
    "sg:province":"Oost-Vlaanderen",
    "sg:tags":[
        "clothing",
        "men's",
        "tailor",
        "-"
    ],
    "wof:name":"Caboor G",
    "wof:placetype":"venue"
},
  "geometry": {"coordinates":[3.414026022,51.136554718],"type":"Point"}
}