{
  "type": "Feature",
  "properties": {
    "addr:full":"Polderstraat 73 Londerzeel Vlaams-Brabant 1840",
    "addr:housenumber":"73",
    "addr:postcode":"1840",
    "addr:street":"Polderstraat",
    "iso:country":"BE",
    "sg:address":"Polderstraat 73",
    "sg:city":"Londerzeel",
    "sg:classifiers":[
        {
            "category":"Real Estate",
            "subcategory":"Surveying",
            "type":"Services"
        }
    ],
    "sg:phone":"+32 50 71 05 02",
    "sg:postcode":"1840",
    "sg:province":"Vlaams-Brabant",
    "sg:tags":[
        "raw",
        "material",
        "-",
        "plastic"
    ],
    "wof:name":"Immadco Nv",
    "wof:placetype":"venue"
},
  "geometry": {"coordinates":[4.2993412018,50.9985389709],"type":"Point"}
}