{
  "type": "Feature",
  "properties": {
    "addr:full":"Pr\u00e9v\u00f4champs 24 Pepinster Li\u00e8ge 4860",
    "addr:housenumber":"24",
    "addr:postcode":"4860",
    "addr:street":"Pre\u0301Vo\u0302Champs",
    "iso:country":"BE",
    "sg:address":"Pr\u00e9v\u00f4champs 24",
    "sg:city":"Pepinster",
    "sg:classifiers":[
        {
            "category":"Building & Trades",
            "subcategory":"Construction",
            "type":"Services"
        }
    ],
    "sg:phone":"+32 87 46 15 21",
    "sg:postcode":"4860",
    "sg:province":"Li\u00e8ge",
    "sg:tags":[
        "carpenter"
    ],
    "wof:name":"Delvaux J Menuiserie",
    "wof:placetype":"venue"
},
  "geometry": {"coordinates":[5.8126249313,50.5594406128],"type":"Point"}
}