{
  "type": "Feature",
  "properties": {
    "iso:country":"BE",
    "sg:address":"Spelverstr 28",
    "sg:city":"Bilzen",
    "sg:classifiers":[
        {
            "category":"Shopping",
            "subcategory":"Clothing, Apparel, & Fashions",
            "type":"Retail Goods"
        }
    ],
    "sg:phone":"+32 89 41 21 21",
    "sg:postcode":"3740",
    "sg:province":"Limburg",
    "sg:tags":[
        "textile",
        "clothing",
        "clothes"
    ],
    "wof:name":"Ambiance Belgium Nv",
    "wof:placetype":"venue"
},
  "geometry": {"coordinates":[5.5278868675,50.8718414307],"type":"Point"}
}