{
  "type": "Feature",
  "properties": {
    "iso:country":"BE",
    "sg:address":"Pi 12",
    "sg:city":"Rochefort",
    "sg:classifiers":[
        {
            "category":"Professional",
            "subcategory":"Engineering",
            "type":"Services"
        }
    ],
    "sg:phone":"+32 84 21 11 48",
    "sg:postcode":"5580",
    "sg:province":"Namur",
    "sg:tags":[
        "machine",
        "-",
        "mechanical"
    ],
    "wof:name":"Etablissements Duvivier Sa",
    "wof:placetype":"venue"
},
  "geometry": {"coordinates":[5.2081289291,50.1701087952],"type":"Point"}
}