{
  "type": "Feature",
  "properties": {
    "addr:full":"Rue Sous Les Pr\u00c9s 13 Hannut Li\u00e8ge 4280",
    "addr:housenumber":"13",
    "addr:postcode":"4280",
    "addr:street":"Rue Sous Les Pre\u0301S",
    "iso:country":"BE",
    "sg:address":"Rue Sous Les Pr\u00c9s 13",
    "sg:city":"Hannut",
    "sg:orig_category":"Loodgieterij, verwarming and sanitaire installaties",
    "sg:phone":"+32 19 63 48 37",
    "sg:postcode":"4280",
    "sg:province":"Li\u00e8ge",
    "wof:name":"M. Dengler",
    "wof:placetype":"venue"
},
  "geometry": {"coordinates":[5.0215802193,50.691078186],"type":"Point"}
}