{
  "type": "Feature",
  "properties": {
    "iso:country":"BE",
    "sg:address":"Heurstraat 38",
    "sg:city":"Tongeren",
    "sg:orig_category":"Belastingconsulenten Diverse juridische dienstverlening",
    "sg:phone":"+32 12 23 89 06",
    "sg:postcode":"3700",
    "sg:province":"Limburg",
    "wof:name":"Vanhan",
    "wof:placetype":"venue"
},
  "geometry": {"coordinates":[5.4841551781,50.7473335266],"type":"Point"}
}