{
  "type": "Feature",
  "properties": {
    "addr:full":"Nijvelsesteenweg 731 Halle Vlaams-Brabant 1500",
    "addr:housenumber":"731",
    "addr:postcode":"1500",
    "addr:street":"Nijvelsesteenweg",
    "iso:country":"BE",
    "sg:address":"Nijvelsesteenweg 731",
    "sg:city":"Halle",
    "sg:classifiers":[
        {
            "category":"Real Estate",
            "subcategory":"Real Estate Services",
            "type":"Services"
        }
    ],
    "sg:phone":"+32 2 356 81 43",
    "sg:postcode":"1500",
    "sg:province":"Vlaams-Brabant",
    "wof:name":"Immo Pletincx-immo Construct Halle Bvba",
    "wof:placetype":"venue"
},
  "geometry": {"coordinates":[4.2585802078,50.7090415955],"type":"Point"}
}