{
  "type": "Feature",
  "properties": {
    "iso:country":"BE",
    "sg:address":"Nieuwpoortsteenweg 136",
    "sg:city":"Koksijde",
    "sg:orig_category":"Eleveurs and marchands de porcs. Eleveurs de bovins",
    "sg:phone":"+32 58 23 46 37",
    "sg:postcode":"8670",
    "sg:province":"West-Vlaanderen",
    "wof:name":"Paul Rommelaere",
    "wof:placetype":"venue"
},
  "geometry": {"coordinates":[2.6492800713,51.1061401367],"type":"Point"}
}