{
  "type": "Feature",
  "properties": {
    "addr:full":"De Colfmaekerstraat 11 Zottegem Oost-Vlaanderen 9620",
    "addr:housenumber":"11",
    "addr:postcode":"9620",
    "addr:street":"Colfmaekerstraat",
    "iso:country":"BE",
    "sg:address":"De Colfmaekerstraat 11",
    "sg:city":"Zottegem",
    "sg:classifiers":[
        {
            "category":"Social Services",
            "type":"Services"
        }
    ],
    "sg:phone":"+32 9 364 99 14",
    "sg:postcode":"9620",
    "sg:province":"Oost-Vlaanderen",
    "wof:name":"Thuishulp",
    "wof:placetype":"venue"
},
  "geometry": {"coordinates":[3.814950943,50.8648834229],"type":"Point"}
}