{
  "type": "Feature",
  "properties": {
    "addr:full":"Kerkweg 56 Boortmeerbeek Vlaams-Brabant 3190",
    "addr:housenumber":"56",
    "addr:postcode":"3190",
    "addr:street":"Kerkweg",
    "iso:country":"BE",
    "sg:address":"Kerkweg 56",
    "sg:city":"Boortmeerbeek",
    "sg:classifiers":[
        {
            "category":"Professional",
            "subcategory":"Management & Consulting",
            "type":"Services"
        }
    ],
    "sg:phone":"+32 15 51 23 82",
    "sg:postcode":"3190",
    "sg:province":"Vlaams-Brabant",
    "sg:tags":[
        "consultant"
    ],
    "wof:name":"St Management Bvba",
    "wof:placetype":"venue"
},
  "geometry": {"coordinates":[4.5626029968,50.9780883789],"type":"Point"}
}