{
  "type": "Feature",
  "properties": {
    "addr:full":"Emiel Clausstraat 51 Waregem (sint-eloois-vijve) West-Vlaanderen 8793",
    "addr:housenumber":"51",
    "addr:postcode":"8793",
    "addr:street":"Emiel Clausstraat",
    "iso:country":"BE",
    "sg:address":"Emiel Clausstraat 51",
    "sg:city":"Waregem (sint-eloois-vijve)",
    "sg:classifiers":[
        {
            "category":"Ice Cream",
            "type":"Food & Drink"
        }
    ],
    "sg:phone":"+32 56 60 05 30",
    "sg:postcode":"8793",
    "sg:province":"West-Vlaanderen",
    "wof:name":"Toproomijs-vanwijnsberghe & Demeester",
    "wof:placetype":"venue"
},
  "geometry": {"coordinates":[3.4119679928,50.9098892212],"type":"Point"}
}