{
  "type": "Feature",
  "properties": {
    "addr:full":"Molenkouterslag 27 Nevele Oost-Vlaanderen 9850",
    "addr:housenumber":"27",
    "addr:postcode":"9850",
    "addr:street":"Molenkouterslag",
    "iso:country":"BE",
    "sg:address":"Molenkouterslag 27",
    "sg:city":"Nevele",
    "sg:orig_category":"S\u00e9curit\u00e9 sociale",
    "sg:phone":"+32 9 371 87 23",
    "sg:postcode":"9850",
    "sg:province":"Oost-Vlaanderen",
    "wof:name":"Liberale Mutualiteit",
    "wof:placetype":"venue"
},
  "geometry": {"coordinates":[3.5701999664,51.0797386169],"type":"Point"}
}