{
  "type": "Feature",
  "properties": {
    "iso:country":"BE",
    "sg:address":"Jan Ruusbroecstraat 21",
    "sg:city":"Sint-pieters-leeuw (ruisbroek)",
    "sg:classifiers":[
        {
            "category":"Professional",
            "subcategory":"Accounting & Tax Preparation",
            "type":"Services"
        }
    ],
    "sg:phone":"+32 2 378 11 58",
    "sg:postcode":"1601",
    "sg:province":"Vlaams-Brabant",
    "sg:tags":[
        "bookkeeper"
    ],
    "wof:name":"Otte J",
    "wof:placetype":"venue"
},
  "geometry": {"coordinates":[4.2949790955,50.7877578735],"type":"Point"}
}