{
  "type": "Feature",
  "properties": {
    "addr:full":"Lenniksesteenweg 333 Halle Vlaams-Brabant 1500",
    "addr:housenumber":"333",
    "addr:postcode":"1500",
    "addr:street":"Lenniksesteenweg",
    "iso:country":"BE",
    "sg:address":"Lenniksesteenweg 333",
    "sg:city":"Halle",
    "sg:classifiers":[
        {
            "category":"Building & Trades",
            "subcategory":"Construction",
            "type":"Services"
        }
    ],
    "sg:phone":"+32 2 356 23 66",
    "sg:postcode":"1500",
    "sg:province":"Vlaams-Brabant",
    "sg:tags":[
        "carpenter"
    ],
    "wof:name":"Van Belle",
    "wof:placetype":"venue"
},
  "geometry": {"coordinates":[4.2180938721,50.7459335327],"type":"Point"}
}