{
  "type": "Feature",
  "properties": {
    "addr:full":"Rue Des Alli\u00e9s 78-80 Bruxelles (forest) Bruxelles-Capitale 1190",
    "addr:postcode":"78-80;1190",
    "addr:street":"Rue Des Allie\u0301S",
    "iso:country":"BE",
    "sg:address":"Rue Des Alli\u00e9s 78-80",
    "sg:city":"Bruxelles (forest)",
    "sg:classifiers":[
        {
            "category":"Professional",
            "subcategory":"Testing Lab",
            "type":"Services"
        }
    ],
    "sg:phone":"+32 2 345 99 94",
    "sg:postcode":"1190",
    "sg:province":"Bruxelles-Capitale",
    "sg:tags":[
        "laboratory",
        "-",
        "machines",
        "apparatus",
        "supply"
    ],
    "wof:name":"Laborimpex Nv",
    "wof:placetype":"venue"
},
  "geometry": {"coordinates":[4.3265151978,50.8167381287],"type":"Point"}
}