{
  "type": "Feature",
  "properties": {
    "addr:full":"Casinolaan 21 Leuven Vlaams-Brabant 3018",
    "addr:housenumber":"21",
    "addr:postcode":"3018",
    "addr:street":"Casinolaan",
    "iso:country":"BE",
    "sg:address":"Casinolaan 21",
    "sg:city":"Leuven",
    "sg:orig_category":"Banken and kredietinstellingen",
    "sg:phone":"+32 16 44 55 10",
    "sg:postcode":"3018",
    "sg:province":"Vlaams-Brabant",
    "wof:name":"Fortis",
    "wof:placetype":"venue"
},
  "geometry": {"coordinates":[4.698843956,50.9259910583],"type":"Point"}
}