{
  "type": "Feature",
  "properties": {
    "addr:full":"Rue De Neufvilles 482 Soignies Hainaut 7060",
    "addr:housenumber":"482",
    "addr:postcode":"7060",
    "addr:street":"Rue De Neufvilles",
    "iso:country":"BE",
    "sg:address":"Rue De Neufvilles 482",
    "sg:city":"Soignies",
    "sg:classifiers":[
        {
            "category":"Health Services",
            "subcategory":"Doctor",
            "type":"Services"
        }
    ],
    "sg:phone":"+32 67 33 36 73",
    "sg:postcode":"7060",
    "sg:province":"Hainaut",
    "sg:tags":[
        "medicinephysicians",
        "surgeon"
    ],
    "wof:name":"Dassonville F",
    "wof:placetype":"venue"
},
  "geometry": {"coordinates":[4.0368800163,50.571849823],"type":"Point"}
}