{
  "type": "Feature",
  "properties": {
    "addr:full":"Olieslagerijstr 7 Boechout Antwerpen 2530",
    "addr:housenumber":"7",
    "addr:postcode":"2530",
    "addr:street":"Olieslagerijstr",
    "iso:country":"BE",
    "sg:address":"Olieslagerijstr 7",
    "sg:city":"Boechout",
    "sg:classifiers":[
        {
            "category":"Farming",
            "subcategory":"Farm",
            "type":"Manufacturing & Wholesale Goods"
        }
    ],
    "sg:phone":"+32 3 455 41 19",
    "sg:postcode":"2530",
    "sg:province":"Antwerpen",
    "sg:tags":[
        "horticulture",
        "agriculture",
        "livestock"
    ],
    "wof:name":"Dhr Gerard Somers",
    "wof:placetype":"venue"
},
  "geometry": {"coordinates":[4.501019001,51.1785469055],"type":"Point"}
}