{
  "type": "Feature",
  "properties": {
    "iso:country":"BE",
    "sg:address":"30",
    "sg:city":"Rue Du Grand Courant 7033 Mons",
    "sg:classifiers":[
        {
            "category":"Autos & Motor Vehicles",
            "subcategory":"Automobile Sales",
            "type":"Retail Goods"
        }
    ],
    "sg:phone":"+32 65 36 24 24",
    "sg:postcode":"30",
    "sg:tags":[
        "equipment",
        "industrial",
        "transport"
    ],
    "wof:name":"Scania Hainaut Sa",
    "wof:placetype":"venue"
},
  "geometry": {"coordinates":[3.9253261089,50.4366378784],"type":"Point"}
}