{
  "type": "Feature",
  "properties": {
    "iso:country":"BE",
    "sg:address":"Ring 10",
    "sg:city":"Ninove",
    "sg:classifiers":[
        {
            "category":"Manufacturing",
            "subcategory":"Metals",
            "type":"Manufacturing & Wholesale Goods"
        }
    ],
    "sg:phone":"+32 54 31 22 66",
    "sg:postcode":"9400",
    "sg:province":"Oost-Vlaanderen",
    "sg:tags":[
        "working"
    ],
    "wof:name":"Cematec Nv",
    "wof:placetype":"venue"
},
  "geometry": {"coordinates":[4.0310001373,50.8447799683],"type":"Point"}
}