{
  "type": "Feature",
  "properties": {
    "addr:full":"Rue De La Bourse 2 Saint-georges-sur-meuse Li\u00e8ge 4470",
    "addr:housenumber":"2",
    "addr:postcode":"4470",
    "addr:street":"Rue De La Bourse",
    "iso:country":"BE",
    "sg:address":"Rue De La Bourse 2",
    "sg:city":"Saint-georges-sur-meuse",
    "sg:orig_category":"Epiceries",
    "sg:phone":"+32 4 275 71 17",
    "sg:postcode":"4470",
    "sg:province":"Li\u00e8ge",
    "wof:name":"Super Echo",
    "wof:placetype":"venue"
},
  "geometry": {"coordinates":[5.3552961349,50.5801277161],"type":"Point"}
}