{
  "type": "Feature",
  "properties": {
    "addr:full":"Dorp 79 Bonheiden Antwerpen 2820",
    "addr:housenumber":"79",
    "addr:postcode":"2820",
    "addr:street":"Dorp",
    "iso:country":"BE",
    "sg:address":"Dorp 79",
    "sg:city":"Bonheiden",
    "sg:classifiers":[
        {
            "category":"Parking",
            "subcategory":"Lot",
            "type":"Transportation"
        }
    ],
    "sg:phone":"+32 15 51 76 82",
    "sg:postcode":"2820",
    "sg:province":"Antwerpen",
    "sg:tags":[
        "armoured",
        "door",
        "fireproof"
    ],
    "wof:name":"A & B Slotenservice Bvba",
    "wof:placetype":"venue"
},
  "geometry": {"coordinates":[4.5454440117,51.0229454041],"type":"Point"}
}