{
  "type": "Feature",
  "properties": {
    "addr:full":"Stramproyerweg 47ba Bocholt Limburg 3950",
    "addr:housenumber":"47ba",
    "addr:postcode":"3950",
    "addr:street":"Stramproyerweg",
    "iso:country":"BE",
    "sg:address":"Stramproyerweg 47ba",
    "sg:city":"Bocholt",
    "sg:orig_category":"Varkenskwekers",
    "sg:phone":"+32 89 46 28 04",
    "sg:postcode":"3950",
    "sg:province":"Limburg",
    "wof:name":"Henricus Van De Laar",
    "wof:placetype":"venue"
},
  "geometry": {"coordinates":[5.6117148399,51.1820297241],"type":"Point"}
}