{
  "type": "Feature",
  "properties": {
    "addr:full":"Zuidstraat 36 Veurne West-Vlaanderen 8630",
    "addr:housenumber":"36",
    "addr:postcode":"8630",
    "addr:street":"Zuidstraat",
    "iso:country":"BE",
    "sg:address":"Zuidstraat 36",
    "sg:city":"Veurne",
    "sg:orig_category":"Epiceries",
    "sg:phone":"+32 58 31 22 42",
    "sg:postcode":"8630",
    "sg:province":"West-Vlaanderen",
    "wof:name":"Spar",
    "wof:placetype":"venue"
},
  "geometry": {"coordinates":[2.6622619629,51.0704803467],"type":"Point"}
}