{
  "type": "Feature",
  "properties": {
    "addr:full":"Chauss\u00c9e De Beaumont 87 Froidchapelle Hainaut 6440",
    "addr:housenumber":"87",
    "addr:postcode":"6440",
    "addr:street":"Chausse\u0301E De Beaumont",
    "iso:country":"BE",
    "sg:address":"Chauss\u00c9e De Beaumont 87",
    "sg:city":"Froidchapelle",
    "sg:orig_category":"Enseignement maternel and primaire",
    "sg:phone":"+32 71 63 38 62",
    "sg:postcode":"6440",
    "sg:province":"Hainaut",
    "wof:name":"Ecole Fond. Communale",
    "wof:placetype":"venue"
},
  "geometry": {"coordinates":[4.3784599304,50.2282752991],"type":"Point"}
}