{
  "type": "Feature",
  "properties": {
    "addr:full":"Kattestraat 74 Sint-amands Antwerpen 2890",
    "addr:housenumber":"74",
    "addr:postcode":"2890",
    "addr:street":"Kattestraat",
    "iso:country":"BE",
    "sg:address":"Kattestraat 74",
    "sg:city":"Sint-amands",
    "sg:orig_category":"Installation de menuiserie en bois and plastique",
    "sg:phone":"+32 3 889 25 93",
    "sg:postcode":"2890",
    "sg:province":"Antwerpen",
    "wof:name":"Schrijnw. De Schutter",
    "wof:placetype":"venue"
},
  "geometry": {"coordinates":[4.2397928238,51.0705451965],"type":"Point"}
}