{
  "type": "Feature",
  "properties": {
    "addr:full":"Rue Julien Marsille 186 Tubize (saintes) Brabant Wallon 1480",
    "addr:housenumber":"186",
    "addr:postcode":"1480",
    "addr:street":"Rue Julien Marsille",
    "iso:country":"BE",
    "sg:address":"Rue Julien Marsille 186",
    "sg:city":"Tubize (saintes)",
    "sg:classifiers":[
        {
            "category":"Education",
            "subcategory":"Special Training",
            "type":"Public Place"
        }
    ],
    "sg:phone":"+32 2 468 15 83",
    "sg:postcode":"1480",
    "sg:province":"Brabant Wallon",
    "sg:tags":[
        "-",
        "processing",
        "data"
    ],
    "wof:name":"Jalons",
    "wof:placetype":"venue"
},
  "geometry": {"coordinates":[4.1608729362,50.7162742615],"type":"Point"}
}