{
  "type": "Feature",
  "properties": {
    "addr:full":"Rue D'antoing 25 Tournai Hainaut 7536",
    "addr:housenumber":"25",
    "addr:postcode":"7536",
    "addr:street":"Rue D'Antoing",
    "iso:country":"BE",
    "sg:address":"Rue D'antoing 25",
    "sg:city":"Tournai",
    "sg:orig_category":"Kapsalons",
    "sg:phone":"+32 69 22 80 93",
    "sg:postcode":"7536",
    "sg:province":"Hainaut",
    "wof:name":"Coiffure Anastasia",
    "wof:placetype":"venue"
},
  "geometry": {"coordinates":[3.4016990662,50.5988082886],"type":"Point"}
}