{
  "type": "Feature",
  "properties": {
    "iso:country":"BE",
    "sg:address":"Citadellaan 41",
    "sg:city":"Gent",
    "sg:orig_category":"Diensten voor huisdieren",
    "sg:phone":"+32 9 222 77 54",
    "sg:postcode":"9000",
    "sg:province":"Oost-Vlaanderen",
    "wof:name":"Nathalie Nicolai",
    "wof:placetype":"venue"
},
  "geometry": {"coordinates":[3.7277750969,51.0386772156],"type":"Point"}
}