{
  "type": "Feature",
  "properties": {
    "addr:full":"Rue De Faubourg 35 Rebecq Brabant Wallon 1430",
    "addr:housenumber":"35",
    "addr:postcode":"1430",
    "addr:street":"Rue De Faubourg",
    "iso:country":"BE",
    "sg:address":"Rue De Faubourg 35",
    "sg:city":"Rebecq",
    "sg:orig_category":"B\u00e9ton pr\u00eat \u00e0 l'emploi Fab",
    "sg:phone":"+32 2 365 02 45",
    "sg:postcode":"1430",
    "sg:province":"Brabant Wallon",
    "wof:name":"Interbeton Nv",
    "wof:placetype":"venue"
},
  "geometry": {"coordinates":[4.1317100525,50.6643714905],"type":"Point"}
}