{
  "type": "Feature",
  "properties": {
    "iso:country":"BE",
    "sg:address":"Rue Tiefry 34",
    "sg:city":"Tournai",
    "sg:orig_category":"Artsen and specialisten",
    "sg:phone":"+32 69 54 76 71",
    "sg:postcode":"7530",
    "sg:province":"Hainaut",
    "wof:name":"Nathalie Detournay",
    "wof:placetype":"venue"
},
  "geometry": {"coordinates":[3.4817249775,50.5868759155],"type":"Point"}
}