{
  "type": "Feature",
  "properties": {
    "iso:country":"BE",
    "sg:address":"Rue Sainte-henriette 208",
    "sg:city":"Morlanwelz (morlanwelz-mariemont)",
    "sg:classifiers":[
        {
            "category":"Utilities",
            "subcategory":"Recycling",
            "type":"Services"
        }
    ],
    "sg:phone":"+32 64 46 09 20",
    "sg:postcode":"7140",
    "sg:province":"Hainaut",
    "wof:name":"C.m.-containers & M\u00e9taux Sa",
    "wof:placetype":"venue"
},
  "geometry": {"coordinates":[4.2630271912,50.4643821716],"type":"Point"}
}