{
  "type": "Feature",
  "properties": {
    "iso:country":"BE",
    "sg:address":"Kerkstraat 43",
    "sg:city":"Buggenhout",
    "sg:orig_category":"Kapsalons",
    "sg:phone":"+32 52 33 35 29",
    "sg:postcode":"9255",
    "sg:province":"Oost-Vlaanderen",
    "wof:name":"Kapsalon Cools",
    "wof:placetype":"venue"
},
  "geometry": {"coordinates":[4.202521801,51.0174026489],"type":"Point"}
}