{
  "type": "Feature",
  "properties": {
    "addr:full":"Rue Henri Artisien 15 Antoing Hainaut 7641",
    "addr:housenumber":"15",
    "addr:postcode":"7641",
    "addr:street":"Rue Henri Artisien",
    "iso:country":"BE",
    "sg:address":"Rue Henri Artisien 15",
    "sg:city":"Antoing",
    "sg:orig_category":"Bouwmaterialen Gh Hout and afgeleiden Gh IJzerwaren, bouw- and verfmaterialen Installatie van metale",
    "sg:phone":"+32 69 44 25 59",
    "sg:postcode":"7641",
    "sg:province":"Hainaut",
    "wof:name":"Ets. Pollet",
    "wof:placetype":"venue"
},
  "geometry": {"coordinates":[3.4258871078,50.5592346191],"type":"Point"}
}