{
  "type": "Feature",
  "properties": {
    "iso:country":"BE",
    "sg:address":"Molenborrestraat 12",
    "sg:city":"Sint-pieters-leeuw",
    "sg:classifiers":[
        {
            "category":"Insurance",
            "subcategory":"Insurance Agent",
            "type":"Services"
        }
    ],
    "sg:phone":"+32 2 532 57 22",
    "sg:postcode":"1600",
    "sg:province":"Vlaams-Brabant",
    "sg:tags":[
        "verzekeringsmakelaars",
        "expert"
    ],
    "wof:name":"Y.d.s.-assur",
    "wof:placetype":"venue"
},
  "geometry": {"coordinates":[4.203690052,50.78881073],"type":"Point"}
}