{
  "type": "Feature",
  "properties": {
    "iso:country":"BE",
    "sg:address":"Rue S\u00e9bastien-laruelle 6",
    "sg:city":"Li\u00e8ge 1",
    "sg:classifiers":[
        {
            "category":"Shopping",
            "subcategory":"Antiques",
            "type":"Retail Goods"
        }
    ],
    "sg:phone":"+32 4 223 37 17",
    "sg:postcode":"4000",
    "sg:province":"Li\u00e8ge",
    "wof:name":"Bragardo",
    "wof:placetype":"venue"
},
  "geometry": {"coordinates":[5.5684370995,50.6431083679],"type":"Point"}
}