{
  "type": "Feature",
  "properties": {
    "iso:country":"BE",
    "sg:address":"Schoon Uitzichtlaan 84",
    "sg:city":"Ukkel/uccle",
    "sg:orig_category":"Beheer onroerend goed Immobili\u00ebnkantoren",
    "sg:phone":"+32 2 345 82 22",
    "sg:postcode":"1180",
    "sg:province":"Bruxelles-Capitale",
    "wof:name":"The Real Estate Company",
    "wof:placetype":"venue"
},
  "geometry": {"coordinates":[4.3628220558,50.8125801086],"type":"Point"}
}