{
  "type": "Feature",
  "properties": {
    "iso:country":"BE",
    "sg:address":"Markt 41",
    "sg:city":"Gavere",
    "sg:orig_category":"Banques and organismes de cr\u00e9dit",
    "sg:phone":"+32 9 384 10 45",
    "sg:postcode":"9890",
    "sg:province":"Oost-Vlaanderen",
    "wof:name":"Fortis",
    "wof:placetype":"venue"
},
  "geometry": {"coordinates":[3.6598849297,50.9299964905],"type":"Point"}
}