{
  "type": "Feature",
  "properties": {
    "iso:country":"BE",
    "sg:address":"Rue Du Congo 130",
    "sg:city":"Mouscron",
    "sg:classifiers":[
        {
            "category":"Personal",
            "subcategory":"Beauty Salon",
            "type":"Services"
        }
    ],
    "sg:phone":"+32 56 33 21 33",
    "sg:postcode":"7700",
    "sg:province":"Hainaut",
    "sg:tags":[
        "lady",
        "-",
        "hairdressing"
    ],
    "wof:name":"Nathalie",
    "wof:placetype":"venue"
},
  "geometry": {"coordinates":[3.2012059689,50.7353057861],"type":"Point"}
}