{
  "type": "Feature",
  "properties": {
    "addr:full":"Grintweg 12 Gavere (baaigem) Oost-Vlaanderen 9890",
    "addr:housenumber":"12",
    "addr:postcode":"9890",
    "addr:street":"Grintweg",
    "iso:country":"BE",
    "sg:address":"Grintweg 12",
    "sg:city":"Gavere (baaigem)",
    "sg:classifiers":[
        {
            "category":"Building & Trades",
            "subcategory":"Plumbing",
            "type":"Services"
        }
    ],
    "sg:phone":"+32 9 362 74 90",
    "sg:postcode":"9890",
    "sg:province":"Oost-Vlaanderen",
    "sg:tags":[
        "contractor"
    ],
    "wof:name":"Eeckhout Marc Bvba",
    "wof:placetype":"venue"
},
  "geometry": {"coordinates":[3.6588599682,50.9283752441],"type":"Point"}
}