{
  "type": "Feature",
  "properties": {
    "addr:full":"Noordkaai 25 Izegem West-Vlaanderen 8870",
    "addr:housenumber":"25",
    "addr:postcode":"8870",
    "addr:street":"Noordkaai",
    "iso:country":"BE",
    "sg:address":"Noordkaai 25",
    "sg:city":"Izegem",
    "sg:classifiers":[
        {
            "category":"Social Services",
            "type":"Services"
        }
    ],
    "sg:phone":"+32 51 30 41 47",
    "sg:postcode":"8870",
    "sg:province":"West-Vlaanderen",
    "wof:name":"Inzamelcentrum-sociaal Project Vzw",
    "wof:placetype":"venue"
},
  "geometry": {"coordinates":[3.1898100376,50.9288406372],"type":"Point"}
}