{
  "type": "Feature",
  "properties": {
    "addr:full":"Torhoutse Steenweg 127 Brugge (sint-andries) West-Vlaanderen 8200",
    "addr:housenumber":"127",
    "addr:postcode":"8200",
    "addr:street":"Torhoutse Steenweg",
    "iso:country":"BE",
    "sg:address":"Torhoutse Steenweg 127",
    "sg:city":"Brugge (sint-andries)",
    "sg:classifiers":[
        {
            "category":"Insurance",
            "subcategory":"Insurance Agent",
            "type":"Services"
        }
    ],
    "sg:phone":"+32 50 39 35 01",
    "sg:postcode":"8200",
    "sg:province":"West-Vlaanderen",
    "sg:tags":[
        "broker"
    ],
    "wof:name":"De Vlaemynck",
    "wof:placetype":"venue"
},
  "geometry": {"coordinates":[3.2028861046,51.1987686157],"type":"Point"}
}