{
  "type": "Feature",
  "properties": {
    "addr:full":"Verbindingsstraat 23 Zele Oost-Vlaanderen 9240",
    "addr:housenumber":"23",
    "addr:postcode":"9240",
    "addr:street":"Verbindingsstraat",
    "iso:country":"BE",
    "sg:address":"Verbindingsstraat 23",
    "sg:city":"Zele",
    "sg:classifiers":[
        {
            "category":"Arena",
            "subcategory":"Sports Club",
            "type":"Entertainment"
        }
    ],
    "sg:phone":"+32 52 44 80 00",
    "sg:postcode":"9240",
    "sg:province":"Oost-Vlaanderen",
    "sg:tags":[
        "de"
    ],
    "wof:name":"V.c. Juvenes",
    "wof:placetype":"venue"
},
  "geometry": {"coordinates":[4.0415811539,51.0650024414],"type":"Point"}
}