{
  "type": "Feature",
  "properties": {
    "addr:full":"Industriepark 18 Tienen Vlaams-Brabant 3300",
    "addr:housenumber":"18",
    "addr:postcode":"3300",
    "addr:street":"Industriepark",
    "iso:country":"BE",
    "sg:address":"Industriepark 18",
    "sg:city":"Tienen",
    "sg:orig_category":"Entreprises de travail adapt\u00e9",
    "sg:phone":"+32 16 80 46 46",
    "sg:postcode":"3300",
    "sg:province":"Vlaams-Brabant",
    "wof:name":"Blankedale",
    "wof:placetype":"venue"
},
  "geometry": {"coordinates":[4.9614491463,50.8089561462],"type":"Point"}
}