{
  "type": "Feature",
  "properties": {
    "iso:country":"BE",
    "sg:address":"Rue Des Jonquilles 34",
    "sg:city":"Seneffe",
    "sg:classifiers":[
        {
            "category":"Cafe",
            "type":"Food & Drink"
        }
    ],
    "sg:phone":"+32 64 55 86 88",
    "sg:postcode":"7180",
    "sg:province":"Hainaut",
    "sg:tags":[
        "caf\u00e9s"
    ],
    "wof:name":"Taverne Le Dailly",
    "wof:placetype":"venue"
},
  "geometry": {"coordinates":[4.263299942,50.5262680054],"type":"Point"}
}