{
  "type": "Feature",
  "properties": {
    "iso:country":"BE",
    "sg:address":"Rue Albert I 3",
    "sg:city":"Gerpinnes",
    "sg:classifiers":[
        {
            "category":"Shopping",
            "subcategory":"Florist",
            "type":"Retail Goods"
        }
    ],
    "sg:phone":"+32 71 50 49 47",
    "sg:postcode":"6280",
    "sg:province":"Hainaut",
    "wof:name":"Fleurs St-rolende",
    "wof:placetype":"venue"
},
  "geometry": {"coordinates":[4.5280580521,50.3361968994],"type":"Point"}
}