{
  "type": "Feature",
  "properties": {
    "iso:country":"BE",
    "sg:address":"R. L'h\u00d4tel Des Monnaies 101",
    "sg:city":"Sint-gillis/saint-gilles",
    "sg:classifiers":[
        {
            "category":"Insurance",
            "subcategory":"Life Insurance",
            "type":"Services"
        }
    ],
    "sg:phone":"+32 2 534 55 41",
    "sg:postcode":"1060",
    "sg:province":"Bruxelles-Capitale",
    "sg:tags":[
        "assurance"
    ],
    "wof:name":"Redasco",
    "wof:placetype":"venue"
},
  "geometry": {"coordinates":[4.3466491699,50.8294258118],"type":"Point"}
}