{
  "type": "Feature",
  "properties": {
    "iso:country":"BE",
    "sg:address":"Brouwerstraat 5",
    "sg:city":"Oud-turnhout",
    "sg:classifiers":[
        {
            "category":"Retail",
            "subcategory":"Event Space",
            "type":"Services"
        }
    ],
    "sg:phone":"+32 14 45 17 41",
    "sg:postcode":"2360",
    "sg:province":"Antwerpen",
    "sg:tags":[
        "rental",
        "-",
        "hall"
    ],
    "wof:name":"Het Corsendonk Schip-boottochten",
    "wof:placetype":"venue"
},
  "geometry": {"coordinates":[4.9796609879,51.3202667236],"type":"Point"}
}