{
  "type": "Feature",
  "properties": {
    "addr:full":"Sint-annastraat 8 Zwalm (rozebeke) Oost-Vlaanderen 9630",
    "addr:housenumber":"8",
    "addr:postcode":"9630",
    "addr:street":"Sint-Annastraat;Rozebeke",
    "iso:country":"BE",
    "sg:address":"Sint-annastraat 8",
    "sg:city":"Zwalm (rozebeke)",
    "sg:classifiers":[
        {
            "category":"Animal Shelter",
            "type":"Public Place"
        }
    ],
    "sg:phone":"+32 55 49 81 94",
    "sg:postcode":"9630",
    "sg:province":"Oost-Vlaanderen",
    "sg:tags":[
        "construction",
        "installation",
        "stable"
    ],
    "wof:name":"De Clercq",
    "wof:placetype":"venue"
},
  "geometry": {"coordinates":[3.7522799969,50.8510475159],"type":"Point"}
}