{
  "type": "Feature",
  "properties": {
    "addr:full":"Boudewijnlaan 14 Knokke-heist (knokke) West-Vlaanderen 8300",
    "addr:housenumber":"14",
    "addr:postcode":"8300",
    "addr:street":"Boudewijnlaan",
    "iso:country":"BE",
    "sg:address":"Boudewijnlaan 14",
    "sg:city":"Knokke-heist (knokke)",
    "sg:classifiers":[
        {
            "category":"Professional",
            "subcategory":"Computer Services",
            "type":"Services"
        }
    ],
    "sg:phone":"+32 50 62 56 66",
    "sg:postcode":"8300",
    "sg:province":"West-Vlaanderen",
    "sg:tags":[
        "-",
        "processing",
        "data",
        "software"
    ],
    "wof:name":"Jorosoft Bvba",
    "wof:placetype":"venue"
},
  "geometry": {"coordinates":[3.2893710136,51.3425445557],"type":"Point"}
}