{
  "type": "Feature",
  "properties": {
    "addr:full":"Orgelstraat 6 Antwerpen Antwerpen 2000",
    "addr:housenumber":"6",
    "addr:postcode":"2000",
    "addr:street":"Orgelstraat",
    "iso:country":"BE",
    "sg:address":"Orgelstraat 6",
    "sg:city":"Antwerpen",
    "sg:orig_category":"Agences maritimes. Agences d'exp\u00e9dition",
    "sg:phone":"+32 3 231 92 92",
    "sg:postcode":"2000",
    "sg:province":"Antwerpen",
    "wof:name":"Balkan & Black Sea Shipp.",
    "wof:placetype":"venue"
},
  "geometry": {"coordinates":[4.4077420235,51.2156715393],"type":"Point"}
}