{
  "type": "Feature",
  "properties": {
    "iso:country":"BE",
    "sg:address":"Wierhoekstraat 39",
    "sg:city":"Hasselt",
    "sg:orig_category":"Benzinestations and brandstoffen",
    "sg:phone":"+32 11 42 69 21",
    "sg:postcode":"3511",
    "sg:province":"Limburg",
    "wof:name":"Interoil",
    "wof:placetype":"venue"
},
  "geometry": {"coordinates":[5.2998242378,50.9449768066],"type":"Point"}
}