{
  "type": "Feature",
  "properties": {
    "addr:full":"Avenue Provinciale 94 Ottignies-louvain-la-neuve (c\u00e9roux-mousty) Brabant Wallon 1341",
    "addr:housenumber":"94",
    "addr:postcode":"1341",
    "addr:street":"Avenue Provinciale;Wallon",
    "iso:country":"BE",
    "sg:address":"Avenue Provinciale 94",
    "sg:city":"Ottignies-louvain-la-neuve (c\u00e9roux-mousty)",
    "sg:classifiers":[
        {
            "category":"Bakery",
            "type":"Food & Drink"
        }
    ],
    "sg:phone":"+32 10 61 74 71",
    "sg:postcode":"1341",
    "sg:province":"Brabant Wallon",
    "sg:tags":[
        "confectioner",
        "baker"
    ],
    "wof:name":"Fromenterie (la)",
    "wof:placetype":"venue"
},
  "geometry": {"coordinates":[4.5627598763,50.6583099365],"type":"Point"}
}