{
  "type": "Feature",
  "properties": {
    "iso:country":"BE",
    "sg:address":"Rue Boulanger-duhayon 30",
    "sg:city":"Jemeppe-sur-sambre",
    "sg:classifiers":[
        {
            "category":"Building & Trades",
            "subcategory":"Pest Control",
            "type":"Services"
        }
    ],
    "sg:phone":"+32 71 78 68 80",
    "sg:postcode":"5190",
    "sg:province":"Namur",
    "sg:tags":[
        "painting",
        "contractor"
    ],
    "wof:name":"Dirette Fabrice",
    "wof:placetype":"venue"
},
  "geometry": {"coordinates":[4.6643328667,50.4638137817],"type":"Point"}
}