{
  "type": "Feature",
  "properties": {
    "iso:country":"BE",
    "sg:address":"Rue J.b. Brabant 40",
    "sg:city":"Namur",
    "sg:classifiers":[
        {
            "category":"Home & Garden",
            "subcategory":"Household Appliances",
            "type":"Retail Goods"
        }
    ],
    "sg:phone":"+32 81 24 15 25",
    "sg:postcode":"5000",
    "sg:province":"Namur",
    "sg:tags":[
        "repair",
        "mainten",
        "-",
        "electric"
    ],
    "wof:name":"Namur Electro",
    "wof:placetype":"venue"
},
  "geometry": {"coordinates":[4.8725390434,50.4648017883],"type":"Point"}
}