{
  "type": "Feature",
  "properties": {
    "iso:country":"BE",
    "sg:address":"Chemin D'haljoux 4",
    "sg:city":"Ciney",
    "sg:classifiers":[
        {
            "category":"Utilities",
            "subcategory":"Electric",
            "type":"Services"
        }
    ],
    "sg:phone":"+32 83 21 50 71",
    "sg:postcode":"5590",
    "sg:province":"Namur",
    "sg:tags":[
        "energy",
        "renewable"
    ],
    "wof:name":"P.r.c.",
    "wof:placetype":"venue"
},
  "geometry": {"coordinates":[5.0916481018,50.3041534424],"type":"Point"}
}