{
  "type": "Feature",
  "properties": {
    "iso:country":"BE",
    "sg:address":"Maurits Noestraat 18",
    "sg:city":"Oud-heverlee",
    "sg:orig_category":"Traitements param\u00e9dicaux",
    "sg:phone":"+32 16 47 20 34",
    "sg:postcode":"3050",
    "sg:province":"Vlaams-Brabant",
    "wof:name":"L. De Ceulaer",
    "wof:placetype":"venue"
},
  "geometry": {"coordinates":[4.6712698936,50.823348999],"type":"Point"}
}