{
  "type": "Feature",
  "properties": {
    "addr:full":"Dorpstraat 70 Zelem Limburg 3545",
    "addr:housenumber":"70",
    "addr:postcode":"3545",
    "addr:street":"Dorpstraat",
    "iso:country":"BE",
    "sg:address":"Dorpstraat 70",
    "sg:city":"Zelem",
    "sg:orig_category":"Tuinen",
    "sg:phone":"+32 13 44 20 05",
    "sg:postcode":"3545",
    "sg:province":"Limburg",
    "wof:name":"Brems",
    "wof:placetype":"venue"
},
  "geometry": {"coordinates":[5.1057100296,50.9779090881],"type":"Point"}
}