{
  "type": "Feature",
  "properties": {
    "addr:full":"Torhoutsesteenweg 34b8 Brugge West-Vlaanderen 8200",
    "addr:housenumber":"34b8",
    "addr:postcode":"8200",
    "addr:street":"Torhoutsesteenweg",
    "iso:country":"BE",
    "sg:address":"Torhoutsesteenweg 34b8",
    "sg:city":"Brugge",
    "sg:orig_category":"Maatschappelijke dienstverlening",
    "sg:phone":"+32 50 39 37 82",
    "sg:postcode":"8200",
    "sg:province":"West-Vlaanderen",
    "wof:name":"Rode Kruis Brugge",
    "wof:placetype":"venue"
},
  "geometry": {"coordinates":[3.2072091103,51.2029495239],"type":"Point"}
}