{
  "type": "Feature",
  "properties": {
    "iso:country":"BE",
    "sg:address":"Veldlei 41",
    "sg:city":"Schilde",
    "sg:orig_category":"M\u00e9decins and sp\u00e9cialistes",
    "sg:phone":"+32 3 685 60 66",
    "sg:postcode":"2970",
    "sg:province":"Antwerpen",
    "wof:name":"Donald Rietmaeker",
    "wof:placetype":"venue"
},
  "geometry": {"coordinates":[4.5540342331,51.2610664368],"type":"Point"}
}