{
  "type": "Feature",
  "properties": {
    "iso:country":"BE",
    "sg:address":"Grote Branderstraat 17",
    "sg:city":"Ieper",
    "sg:classifiers":[
        {
            "category":"Cafe",
            "type":"Food & Drink"
        }
    ],
    "sg:phone":"+32 57 33 31 63",
    "sg:postcode":"8908",
    "sg:province":"West-Vlaanderen",
    "sg:tags":[
        "caf\u00e9s"
    ],
    "wof:name":"Remi Maricau",
    "wof:placetype":"venue"
},
  "geometry": {"coordinates":[2.7916390896,50.8521881104],"type":"Point"}
}