{
  "type": "Feature",
  "properties": {
    "addr:full":"Clos Des Ram\u00c9es 55 Moeskroen/mouscron Hainaut 7700",
    "addr:housenumber":"55",
    "addr:postcode":"7700",
    "addr:street":"Clos Des Rame\u0301Es",
    "iso:country":"BE",
    "sg:address":"Clos Des Ram\u00c9es 55",
    "sg:city":"Moeskroen/mouscron",
    "sg:orig_category":"Services divers aux entreprises. Editeurs de livres. Animations diverses",
    "sg:phone":"+32 56 34 14 51",
    "sg:postcode":"7700",
    "sg:province":"Hainaut",
    "wof:name":"E.c.f. Production",
    "wof:placetype":"venue"
},
  "geometry": {"coordinates":[3.2323200703,50.7400932312],"type":"Point"}
}