{
  "type": "Feature",
  "properties": {
    "iso:country":"BE",
    "sg:address":"Route De Vodec\u00c9e",
    "sg:city":"Philippeville",
    "sg:orig_category":"Gestion des d\u00e9charges and sites d\u00e9finitifs de stockage",
    "sg:phone":"+32 71 66 70 30",
    "sg:postcode":"5600",
    "sg:province":"Namur",
    "wof:name":"Parcs A Conteneurs Philippeville",
    "wof:placetype":"venue"
},
  "geometry": {"coordinates":[4.5567140579,50.1989440918],"type":"Point"}
}