{
  "type": "Feature",
  "properties": {
    "addr:full":"Neerstraat 6 Brakel (nederbrakel) Oost-Vlaanderen 9660",
    "addr:housenumber":"6",
    "addr:postcode":"9660",
    "addr:street":"Neerstraat",
    "iso:country":"BE",
    "sg:address":"Neerstraat 6",
    "sg:city":"Brakel (nederbrakel)",
    "sg:classifiers":[
        {
            "category":"Bars & Pubs",
            "type":"Food & Drink"
        }
    ],
    "sg:phone":"+32 55 42 30 41",
    "sg:postcode":"9660",
    "sg:province":"Oost-Vlaanderen",
    "sg:tags":[
        "tavern"
    ],
    "wof:name":"Ceres",
    "wof:placetype":"venue"
},
  "geometry": {"coordinates":[3.7642250061,50.8031082153],"type":"Point"}
}