{
  "type": "Feature",
  "properties": {
    "iso:country":"BE",
    "sg:address":"Graethempoort 16",
    "sg:city":"Borgloon",
    "sg:classifiers":[
        {
            "category":"Health Services",
            "subcategory":"Health Practitioner",
            "type":"Services"
        }
    ],
    "sg:phone":"+32 12 74 36 72",
    "sg:postcode":"3840",
    "sg:province":"Limburg",
    "sg:tags":[
        "physiotherapist"
    ],
    "wof:name":"Wilmots A",
    "wof:placetype":"venue"
},
  "geometry": {"coordinates":[5.3354430199,50.8038024902],"type":"Point"}
}