{
  "type": "Feature",
  "properties": {
    "addr:full":"Schupstraat 18-20 Box 24 Antwerpen Antwerpen 2018",
    "addr:housenumber":"18-20 box 24",
    "addr:postcode":"2018",
    "addr:street":"Schupstraat",
    "iso:country":"BE",
    "sg:address":"Schupstraat 18-20 Box 24",
    "sg:city":"Antwerpen",
    "sg:classifiers":[
        {
            "category":"Shopping",
            "subcategory":"Jewelry",
            "type":"Retail Goods"
        }
    ],
    "sg:phone":"+32 3 231 35 42",
    "sg:postcode":"2018",
    "sg:province":"Antwerpen",
    "sg:tags":[
        "diamond",
        "-"
    ],
    "wof:name":"Mabrodiam International Nv",
    "wof:placetype":"venue"
},
  "geometry": {"coordinates":[4.4177899361,51.2145767212],"type":"Point"}
}