{
  "type": "Feature",
  "properties": {
    "addr:full":"Ferdinand Snellaertstr. 23 Izegem West-Vlaanderen 8870",
    "addr:housenumber":"23",
    "addr:postcode":"8870",
    "iso:country":"BE",
    "sg:address":"Ferdinand Snellaertstr. 23",
    "sg:city":"Izegem",
    "sg:classifiers":[
        {
            "category":"Building & Trades",
            "subcategory":"Construction",
            "type":"Services"
        }
    ],
    "sg:phone":"+32 51 31 05 51",
    "sg:postcode":"8870",
    "sg:province":"West-Vlaanderen",
    "sg:tags":[
        "la",
        "de",
        "\u00e9quipement",
        "pour",
        "machine",
        "location"
    ],
    "wof:name":"Dekasol",
    "wof:placetype":"venue"
},
  "geometry": {"coordinates":[3.2264389992,50.9258918762],"type":"Point"}
}