{
  "type": "Feature",
  "properties": {
    "addr:full":"Wulfhagestraat 5 Brugge West-Vlaanderen 8000",
    "addr:housenumber":"5",
    "addr:postcode":"8000",
    "addr:street":"Wulfhagestraat",
    "iso:country":"BE",
    "sg:address":"Wulfhagestraat 5",
    "sg:city":"Brugge",
    "sg:orig_category":"Kapsalons",
    "sg:phone":"+32 50 33 17 97",
    "sg:postcode":"8000",
    "sg:province":"West-Vlaanderen",
    "wof:name":"Tuyttens Hairclub",
    "wof:placetype":"venue"
},
  "geometry": {"coordinates":[3.2189729214,51.2067298889],"type":"Point"}
}