{
  "type": "Feature",
  "properties": {
    "addr:full":"Rue Reine Astrid 8 Welkenraedt Li\u00e8ge 4840",
    "addr:housenumber":"8",
    "addr:postcode":"4840",
    "addr:street":"Rue Reine Astrid",
    "iso:country":"BE",
    "sg:address":"Rue Reine Astrid 8",
    "sg:city":"Welkenraedt",
    "sg:classifiers":[
        {
            "category":"Health Services",
            "subcategory":"Dentist",
            "type":"Services"
        }
    ],
    "sg:phone":"+32 87 88 10 86",
    "sg:postcode":"4840",
    "sg:province":"Li\u00e8ge",
    "wof:name":"Laschet Ch",
    "wof:placetype":"venue"
},
  "geometry": {"coordinates":[5.9779791832,50.6609115601],"type":"Point"}
}