{
  "type": "Feature",
  "properties": {
    "iso:country":"BE",
    "sg:address":"Bloemendaelelaan 4",
    "sg:city":"Maldegem",
    "sg:orig_category":"Brandweer and civiele bescherming",
    "sg:phone":"+32 50 71 12 34",
    "sg:postcode":"9990",
    "sg:province":"Oost-Vlaanderen",
    "wof:name":"Brandweerkazerne",
    "wof:placetype":"venue"
},
  "geometry": {"coordinates":[3.4526369572,51.2116508484],"type":"Point"}
}