{
  "type": "Feature",
  "properties": {
    "addr:full":"Geraardsbergsesteenweg 380 Ninove Oost-Vlaanderen 9404",
    "addr:housenumber":"380",
    "addr:postcode":"9404",
    "addr:street":"Geraardsbergsesteenweg",
    "iso:country":"BE",
    "sg:address":"Geraardsbergsesteenweg 380",
    "sg:city":"Ninove",
    "sg:orig_category":"M\u00e9decins and sp\u00e9cialistes",
    "sg:phone":"+32 54 33 47 05",
    "sg:postcode":"9404",
    "sg:province":"Oost-Vlaanderen",
    "wof:name":"Hans Van Der Haegen",
    "wof:placetype":"venue"
},
  "geometry": {"coordinates":[3.9570000172,50.8419036865],"type":"Point"}
}