{
  "type": "Feature",
  "properties": {
    "iso:country":"BE",
    "sg:address":"Rue De Savoie 22a",
    "sg:city":"Bruxelles",
    "sg:classifiers":[
        {
            "category":"Manufacturing",
            "subcategory":"Rubber & Plastics",
            "type":"Manufacturing & Wholesale Goods"
        }
    ],
    "sg:phone":"+32 2 539 25 25",
    "sg:postcode":"1060",
    "sg:province":"Bruxelles-Capitale",
    "wof:name":"Leva Parquets Sprl",
    "wof:placetype":"venue"
},
  "geometry": {"coordinates":[4.3473510742,50.8243598938],"type":"Point"}
}