{
  "type": "Feature",
  "properties": {
    "addr:full":"Markt 4 Meulebeke West-Vlaanderen 8760",
    "addr:housenumber":"4",
    "addr:postcode":"8760",
    "addr:street":"Markt",
    "iso:country":"BE",
    "sg:address":"Markt 4",
    "sg:city":"Meulebeke",
    "sg:classifiers":[
        {
            "category":"Bars & Pubs",
            "type":"Food & Drink"
        }
    ],
    "sg:phone":"+32 51 48 88 72",
    "sg:postcode":"8760",
    "sg:province":"West-Vlaanderen",
    "wof:name":"Neels C",
    "wof:placetype":"venue"
},
  "geometry": {"coordinates":[3.2879450321,50.94947052],"type":"Point"}
}