{
  "type": "Feature",
  "properties": {
    "addr:full":"Oostendse Baan 25 Gistel West-Vlaanderen 8470",
    "addr:housenumber":"25",
    "addr:postcode":"8470",
    "addr:street":"Oostendse Baan",
    "iso:country":"BE",
    "sg:address":"Oostendse Baan 25",
    "sg:city":"Gistel",
    "sg:orig_category":"Taxi's Taxi's speciale diensten",
    "sg:phone":"+32 59 27 46 00",
    "sg:postcode":"8470",
    "sg:province":"West-Vlaanderen",
    "wof:name":"Maene En Thomas",
    "wof:placetype":"venue"
},
  "geometry": {"coordinates":[2.9517381191,51.1506729126],"type":"Point"}
}