{
  "type": "Feature",
  "properties": {
    "iso:country":"BE",
    "sg:address":"Duffelsesteenweg 313",
    "sg:city":"Kontich",
    "sg:orig_category":"Fleurs and plantes",
    "sg:phone":"+32 3 288 79 51",
    "sg:postcode":"2550",
    "sg:province":"Antwerpen",
    "wof:name":"Jacky-orchiflore",
    "wof:placetype":"venue"
},
  "geometry": {"coordinates":[4.4751548767,51.1177062988],"type":"Point"}
}