{
  "type": "Feature",
  "properties": {
    "addr:full":"Guillaume Van Haelenlaan 94b3 Vorst/forest Bruxelles-Capitale 1190",
    "addr:housenumber":"94b3",
    "addr:postcode":"1190",
    "addr:street":"Guillaume Van Haelenlaan;/ Forest",
    "iso:country":"BE",
    "sg:address":"Guillaume Van Haelenlaan 94b3",
    "sg:city":"Vorst/forest",
    "sg:classifiers":[
        {
            "category":"Professional",
            "subcategory":"Accounting & Tax Preparation",
            "type":"Services"
        }
    ],
    "sg:phone":"+32 2 343 21 34",
    "sg:postcode":"1190",
    "sg:province":"Bruxelles-Capitale",
    "sg:tags":[
        "accountant"
    ],
    "wof:name":"Ernest Malrain",
    "wof:placetype":"venue"
},
  "geometry": {"coordinates":[4.3298220634,50.822052002],"type":"Point"}
}