{
  "type": "Feature",
  "properties": {
    "iso:country":"BE",
    "sg:address":"Vakeleiestraat 4",
    "sg:city":"Maldegem",
    "sg:classifiers":[
        {
            "category":"Health Services",
            "subcategory":"Nursing And Care Facility",
            "type":"Services"
        }
    ],
    "sg:phone":"+32 50 71 03 11",
    "sg:postcode":"9990",
    "sg:province":"Oost-Vlaanderen",
    "sg:tags":[
        "home"
    ],
    "wof:name":"Cornelis K",
    "wof:placetype":"venue"
},
  "geometry": {"coordinates":[3.4188370705,51.2184486389],"type":"Point"}
}