{
  "type": "Feature",
  "properties": {
    "iso:country":"BE",
    "sg:address":"Rue Mouzin 31",
    "sg:city":"Mons (nimy)",
    "sg:classifiers":[
        {
            "category":"Museum",
            "type":"Entertainment"
        }
    ],
    "sg:phone":"+32 65 31 72 51",
    "sg:postcode":"7020",
    "sg:province":"Hainaut",
    "wof:name":"Mus\u00e9e Du Vieux Nimy",
    "wof:placetype":"venue"
},
  "geometry": {"coordinates":[3.9553449154,50.4761772156],"type":"Point"}
}