{
  "type": "Feature",
  "properties": {
    "addr:full":"Kunstenaarsstraat 30 Brussel/bruxelles Bruxelles-Capitale 1020",
    "addr:housenumber":"30",
    "addr:postcode":"1020",
    "addr:street":"Kunstenaarsstraat;/",
    "iso:country":"BE",
    "sg:address":"Kunstenaarsstraat 30",
    "sg:city":"Brussel/bruxelles",
    "sg:orig_category":"Taxi's speciale diensten",
    "sg:phone":"+32 2 479 87 47",
    "sg:postcode":"1020",
    "sg:province":"Bruxelles-Capitale",
    "wof:name":"Taxis Bottemanne & Fils",
    "wof:placetype":"venue"
},
  "geometry": {"coordinates":[4.3534297943,50.8811416626],"type":"Point"}
}