{
  "type": "Feature",
  "properties": {
    "iso:country":"BE",
    "sg:address":"Lossestraat 3",
    "sg:city":"Pepingen",
    "sg:orig_category":"Eleveurs de bovins",
    "sg:phone":"+32 2 532 44 09",
    "sg:postcode":"1670",
    "sg:province":"Vlaams-Brabant",
    "wof:name":"Richard Cromphout",
    "wof:placetype":"venue"
},
  "geometry": {"coordinates":[4.1566710472,50.7702522278],"type":"Point"}
}