{
  "type": "Feature",
  "properties": {
    "iso:country":"BE",
    "sg:address":"Groene-herderstraat 80",
    "sg:city":"Roeselare",
    "sg:classifiers":[
        {
            "category":"Cafe",
            "type":"Food & Drink"
        }
    ],
    "sg:phone":"+32 51 24 10 96",
    "sg:postcode":"8800",
    "sg:province":"West-Vlaanderen",
    "sg:tags":[
        "caf\u00e9s"
    ],
    "wof:name":"Caf\u00c9 De Vink",
    "wof:placetype":"venue"
},
  "geometry": {"coordinates":[3.1404271126,50.9321594238],"type":"Point"}
}