{
  "type": "Feature",
  "properties": {
    "addr:full":"Rorenweg 3 Bree Limburg 3960",
    "addr:housenumber":"3",
    "addr:postcode":"3960",
    "addr:street":"Rorenweg",
    "iso:country":"BE",
    "sg:address":"Rorenweg 3",
    "sg:city":"Bree",
    "sg:orig_category":"Varkenskwekers",
    "sg:phone":"+32 89 46 10 93",
    "sg:postcode":"3960",
    "sg:province":"Limburg",
    "wof:name":"Hubert Knippenberg",
    "wof:placetype":"venue"
},
  "geometry": {"coordinates":[5.6211180687,51.1353759766],"type":"Point"}
}