{
  "type": "Feature",
  "properties": {
    "iso:country":"BE",
    "sg:address":"Emiel Hertecantlaan 101",
    "sg:city":"Berlare",
    "sg:classifiers":[
        {
            "category":"Insurance",
            "subcategory":"Life Insurance",
            "type":"Services"
        }
    ],
    "sg:phone":"+32 52 42 57 58",
    "sg:postcode":"9290",
    "sg:province":"Oost-Vlaanderen",
    "sg:tags":[
        "assurance"
    ],
    "wof:name":"Vanhoesen",
    "wof:placetype":"venue"
},
  "geometry": {"coordinates":[4.0052599907,51.0130882263],"type":"Point"}
}