{
  "type": "Feature",
  "properties": {
    "addr:full":"Rue De Grammont 37 Lessines Hainaut 7860",
    "addr:housenumber":"37",
    "addr:postcode":"7860",
    "addr:street":"Rue De Grammont;Hainaut",
    "iso:country":"BE",
    "sg:address":"Rue De Grammont 37",
    "sg:city":"Lessines",
    "sg:classifiers":[
        {
            "category":"Professional",
            "subcategory":"Lawyer & Legal Services",
            "type":"Services"
        }
    ],
    "sg:phone":"+32 68 33 84 14",
    "sg:postcode":"7860",
    "sg:province":"Hainaut",
    "sg:tags":[
        "notary"
    ],
    "wof:name":"Winders Ph",
    "wof:placetype":"venue"
},
  "geometry": {"coordinates":[3.828453064,50.7145385742],"type":"Point"}
}