{
  "type": "Feature",
  "properties": {
    "addr:full":"Rue Du Vingt-deux Ao\u00fbt 17 Charleroi (couillet) Hainaut 6010",
    "addr:housenumber":"17",
    "addr:postcode":"6010",
    "addr:street":"Rue Du Vingt-Deux Aou\u0302T",
    "iso:country":"BE",
    "sg:address":"Rue Du Vingt-deux Ao\u00fbt 17",
    "sg:city":"Charleroi (couillet)",
    "sg:classifiers":[
        {
            "category":"Personal",
            "subcategory":"Beauty Salon",
            "type":"Services"
        }
    ],
    "sg:phone":"+32 71 36 98 13",
    "sg:postcode":"6010",
    "sg:province":"Hainaut",
    "sg:tags":[
        "lady",
        "-",
        "hairdressing"
    ],
    "wof:name":"Duo A",
    "wof:placetype":"venue"
},
  "geometry": {"coordinates":[4.477643013,50.3837509155],"type":"Point"}
}