{
  "type": "Feature",
  "properties": {
    "iso:country":"BE",
    "sg:address":"Rue Montoyer 110",
    "sg:city":"Morlanwelz",
    "sg:orig_category":"M\u00e9decins and sp\u00e9cialistes",
    "sg:phone":"+32 64 44 96 95",
    "sg:postcode":"7140",
    "sg:province":"Hainaut",
    "wof:name":"Klaus-richard Ebinger",
    "wof:placetype":"venue"
},
  "geometry": {"coordinates":[4.2496609688,50.454990387],"type":"Point"}
}