{
  "type": "Feature",
  "properties": {
    "iso:country":"BE",
    "sg:address":"Place 55",
    "sg:city":"Flobecq",
    "sg:classifiers":[
        {
            "category":"Building & Trades",
            "subcategory":"Construction",
            "type":"Services"
        }
    ],
    "sg:phone":"+32 68 45 52 19",
    "sg:postcode":"7880",
    "sg:province":"Hainaut",
    "sg:tags":[
        "carpenter"
    ],
    "wof:name":"Laus J-p",
    "wof:placetype":"venue"
},
  "geometry": {"coordinates":[3.7384328842,50.7368049622],"type":"Point"}
}