{
  "type": "Feature",
  "properties": {
    "iso:country":"BE",
    "sg:address":"Houte 37",
    "sg:city":"Balegem",
    "sg:classifiers":[
        {
            "category":"Communications",
            "subcategory":"Television Station",
            "type":"Services"
        }
    ],
    "sg:phone":"+32 9 324 76 67",
    "sg:postcode":"9860",
    "sg:province":"Oost-Vlaanderen",
    "sg:tags":[
        "industrial",
        "network"
    ],
    "wof:name":"Ddk-group B.v.b.a.",
    "wof:placetype":"venue"
},
  "geometry": {"coordinates":[3.7914450169,50.9187049866],"type":"Point"}
}