{
  "type": "Feature",
  "properties": {
    "iso:country":"BE",
    "sg:address":"Rue Ernest Montellier 2",
    "sg:city":"Fernelmont",
    "sg:orig_category":"Pain, p\u00e2tisseries and confiseries",
    "sg:phone":"+32 81 83 47 30",
    "sg:postcode":"5380",
    "sg:province":"Namur",
    "wof:name":"Les Trois Petits Fours",
    "wof:placetype":"venue"
},
  "geometry": {"coordinates":[4.9806199074,50.5372886658],"type":"Point"}
}