{
  "type": "Feature",
  "properties": {
    "addr:full":"Autoroute E25 Ath Limburg 3790",
    "addr:postcode":"ath;3790",
    "addr:street":"Autoroute E25",
    "iso:country":"BE",
    "sg:address":"Autoroute E25",
    "sg:city":"Ath",
    "sg:orig_category":"Agences en douane",
    "sg:phone":"+32 4 381 20 10",
    "sg:postcode":"3790",
    "sg:province":"Limburg",
    "wof:name":"Expedit",
    "wof:placetype":"venue"
},
  "geometry": {"coordinates":[5.8100881577,50.7484207153],"type":"Point"}
}