{
  "type": "Feature",
  "properties": {
    "addr:full":"Elizabetlaan 271 Knokke-heist West-Vlaanderen 8300",
    "addr:housenumber":"271",
    "addr:postcode":"8300",
    "addr:street":"Elizabetlaan",
    "iso:country":"BE",
    "sg:address":"Elizabetlaan 271",
    "sg:city":"Knokke-heist",
    "sg:orig_category":"Mailing- and besteldiensten Secretariaatsdiensten",
    "sg:phone":"+32 50 51 55 95",
    "sg:postcode":"8300",
    "sg:province":"West-Vlaanderen",
    "wof:name":"Interactif",
    "wof:placetype":"venue"
},
  "geometry": {"coordinates":[3.2898099422,51.3468093872],"type":"Point"}
}