{
  "type": "Feature",
  "properties": {
    "iso:country":"BE",
    "sg:address":"Rue Edouard Dinot 89",
    "sg:city":"Ciney",
    "sg:classifiers":[
        {
            "category":"Health Services",
            "subcategory":"Health Practitioner",
            "type":"Services"
        }
    ],
    "sg:phone":"+32 83 21 31 55",
    "sg:postcode":"5590",
    "sg:province":"Namur",
    "sg:tags":[
        "physiotherapist"
    ],
    "wof:name":"Bouchat Pierre",
    "wof:placetype":"venue"
},
  "geometry": {"coordinates":[5.1008458138,50.2913398743],"type":"Point"}
}