{
  "type": "Feature",
  "properties": {
    "addr:full":"Isabellastraat 22 Dilbeek Vlaams-Brabant 1703",
    "addr:housenumber":"22",
    "addr:postcode":"1703",
    "addr:street":"Isabellastraat",
    "iso:country":"BE",
    "sg:address":"Isabellastraat 22",
    "sg:city":"Dilbeek",
    "sg:orig_category":"Woningbouw",
    "sg:phone":"+32 2 569 55 52",
    "sg:postcode":"1703",
    "sg:province":"Vlaams-Brabant",
    "wof:name":"Bell - Construct",
    "wof:placetype":"venue"
},
  "geometry": {"coordinates":[4.2083268166,50.8261375427],"type":"Point"}
}