{
  "type": "Feature",
  "properties": {
    "addr:full":"Chauss\u00e9e De Wavre 1144 Bruxelles (auderghem) Bruxelles-Capitale 1160",
    "addr:postcode":"1144;1160",
    "addr:street":"Chausse\u0301E De Wavre",
    "iso:country":"BE",
    "sg:address":"Chauss\u00e9e De Wavre 1144",
    "sg:city":"Bruxelles (auderghem)",
    "sg:classifiers":[
        {
            "category":"Social Services",
            "type":"Services"
        }
    ],
    "sg:phone":"+32 2 742 31 48",
    "sg:postcode":"1160",
    "sg:province":"Bruxelles-Capitale",
    "wof:name":"Point - Relais Infor Jeune",
    "wof:placetype":"venue"
},
  "geometry": {"coordinates":[4.4042348862,50.8222427368],"type":"Point"}
}