{
  "type": "Feature",
  "properties": {
    "addr:full":"Chauss\u00c9e De Wavre 1526 Oudergem/auderghem Bruxelles-Capitale 1160",
    "addr:postcode":"1526;1160",
    "addr:street":"Chausse\u0301E De Wavre",
    "iso:country":"BE",
    "sg:address":"Chauss\u00c9e De Wavre 1526",
    "sg:city":"Oudergem/auderghem",
    "sg:orig_category":"Eclairage et \u00e9quipements du foyer",
    "sg:phone":"+32 2 675 51 69",
    "sg:postcode":"1160",
    "sg:province":"Bruxelles-Capitale",
    "wof:name":"La Demeure Des Senteurs",
    "wof:placetype":"venue"
},
  "geometry": {"coordinates":[4.4210672379,50.8176193237],"type":"Point"}
}