{
  "type": "Feature",
  "properties": {
    "addr:full":"Route D\u00b4herbesthal 134 Eupen Li\u00e8ge 4700",
    "addr:housenumber":"134",
    "addr:postcode":"4700",
    "addr:street":"Route D\u00b4Herbesthal",
    "iso:country":"BE",
    "sg:address":"Route D\u00b4herbesthal 134",
    "sg:city":"Eupen",
    "sg:orig_category":"Electrom\u00e9nager, t\u00e9l\u00e9visions and radios",
    "sg:phone":"+32 87 59 57 57",
    "sg:postcode":"4700",
    "sg:province":"Li\u00e8ge",
    "wof:name":"Maison Niederau",
    "wof:placetype":"venue"
},
  "geometry": {"coordinates":[6.0150728226,50.6399230957],"type":"Point"}
}