{
  "type": "Feature",
  "properties": {
    "iso:country":"BE",
    "sg:address":"Zuidlaan 123",
    "sg:city":"Wetteren",
    "sg:orig_category":"Entretien and r\u00e9parations de voitures. V\u00e9hicules automobiles",
    "sg:phone":"+32 9 369 04 22",
    "sg:postcode":"9230",
    "sg:province":"Oost-Vlaanderen",
    "wof:name":"Garage Dekeukeleire",
    "wof:placetype":"venue"
},
  "geometry": {"coordinates":[3.8804650307,50.9984893799],"type":"Point"}
}