{
  "type": "Feature",
  "properties": {
    "iso:country":"BE",
    "sg:address":"Onder D'eike 46",
    "sg:city":"Arendonk",
    "sg:classifiers":[
        {
            "category":"Professional",
            "subcategory":"Computer Services",
            "type":"Services"
        }
    ],
    "sg:phone":"+32 14 71 07 08",
    "sg:postcode":"2370",
    "sg:province":"Antwerpen",
    "sg:tags":[
        "webdesign",
        "-",
        "internet"
    ],
    "wof:name":"Flemish Net Services",
    "wof:placetype":"venue"
},
  "geometry": {"coordinates":[5.099419117,51.3414306641],"type":"Point"}
}