{
  "type": "Feature",
  "properties": {
    "iso:country":"BE",
    "sg:address":"Kardinaal Mercierstraat 2",
    "sg:city":"Brugge",
    "sg:classifiers":[
        {
            "category":"Autos & Motor Vehicles",
            "subcategory":"Auto Supplies",
            "type":"Retail Goods"
        }
    ],
    "sg:phone":"+32 50 34 20 70",
    "sg:postcode":"8000",
    "sg:province":"West-Vlaanderen",
    "sg:tags":[
        "automobile",
        "-",
        "radio"
    ],
    "wof:name":"Stereoscope Bvba",
    "wof:placetype":"venue"
},
  "geometry": {"coordinates":[3.2138550282,51.2165107727],"type":"Point"}
}