{
  "type": "Feature",
  "properties": {
    "addr:full":"Latemstraat 21 Sint-martens-latem Oost-Vlaanderen 9830",
    "addr:housenumber":"21",
    "addr:postcode":"9830",
    "addr:street":"Latemstraat",
    "iso:country":"BE",
    "sg:address":"Latemstraat 21",
    "sg:city":"Sint-martens-latem",
    "sg:classifiers":[
        {
            "category":"Shopping",
            "subcategory":"Shoes",
            "type":"Retail Goods"
        }
    ],
    "sg:phone":"+32 9 282 87 10",
    "sg:postcode":"9830",
    "sg:province":"Oost-Vlaanderen",
    "sg:tags":[
        "slipper",
        "-"
    ],
    "wof:name":"Caselli",
    "wof:placetype":"venue"
},
  "geometry": {"coordinates":[3.6372580528,51.0192604065],"type":"Point"}
}