{
  "type": "Feature",
  "properties": {
    "iso:country":"BE",
    "sg:address":"Renderstraat 53",
    "sg:city":"Westerlo",
    "sg:orig_category":"Eleveurs de bovins",
    "sg:phone":"+32 14 26 42 87",
    "sg:postcode":"2260",
    "sg:province":"Antwerpen",
    "wof:name":"Theophiel Vercammen",
    "wof:placetype":"venue"
},
  "geometry": {"coordinates":[4.8539528847,51.0973777771],"type":"Point"}
}