{
  "type": "Feature",
  "properties": {
    "addr:full":"Rue De La Station 84 Braine-le-comte Hainaut 7090",
    "addr:housenumber":"84",
    "addr:postcode":"7090",
    "addr:street":"Rue De La Station",
    "iso:country":"BE",
    "sg:address":"Rue De La Station 84",
    "sg:city":"Braine-le-comte",
    "sg:orig_category":"Epiceries",
    "sg:phone":"+32 67 55 78 06",
    "sg:postcode":"7090",
    "sg:province":"Hainaut",
    "wof:name":"Carmela Spoto",
    "wof:placetype":"venue"
},
  "geometry": {"coordinates":[4.1377878189,50.6075668335],"type":"Point"}
}