{
  "type": "Feature",
  "properties": {
    "iso:country":"BE",
    "sg:address":"Rue Malev\u00e9 10",
    "sg:city":"Andenne",
    "sg:classifiers":[
        {
            "category":"Social Services",
            "subcategory":"Child Care",
            "type":"Services"
        }
    ],
    "sg:phone":"+32 85 84 38 24",
    "sg:postcode":"5300",
    "sg:province":"Namur",
    "sg:tags":[
        "baby",
        "nursery",
        "day",
        "sitting"
    ],
    "wof:name":"Benjamins (les)",
    "wof:placetype":"venue"
},
  "geometry": {"coordinates":[5.0941519737,50.4920158386],"type":"Point"}
}