{
  "type": "Feature",
  "properties": {
    "iso:country":"BE",
    "sg:address":"Rue Robersart 56",
    "sg:city":"Floreffe",
    "sg:orig_category":"D\u00e9molition d\u00b4immeubles and terrassements. Construction industrielle and commerciale. Equipements pou",
    "sg:phone":"+32 81 44 07 05",
    "sg:postcode":"5150",
    "sg:province":"Namur",
    "wof:name":"Georges Gorlier",
    "wof:placetype":"venue"
},
  "geometry": {"coordinates":[4.7487239838,50.429019928],"type":"Point"}
}