{
  "type": "Feature",
  "properties": {
    "addr:full":"Zwijgershoek 2 Sint-niklaas Oost-Vlaanderen 9100",
    "addr:housenumber":"2",
    "addr:postcode":"9100",
    "addr:street":"Zwijgershoek",
    "iso:country":"BE",
    "sg:address":"Zwijgershoek 2",
    "sg:city":"Sint-niklaas",
    "sg:orig_category":"Fairs, shows, exhibitions",
    "sg:phone":"+32 3 766 11 99",
    "sg:postcode":"9100",
    "sg:province":"Oost-Vlaanderen",
    "wof:name":"Exposervice Benelux Ebvba",
    "wof:placetype":"venue"
},
  "geometry": {"coordinates":[4.1447072029,51.1664047241],"type":"Point"}
}