{
  "type": "Feature",
  "properties": {
    "addr:full":"Heirbaan 20 Dendermonde Oost-Vlaanderen 9200",
    "addr:housenumber":"20",
    "addr:postcode":"9200",
    "addr:street":"Heirbaan;Oost-Vlaanderen",
    "iso:country":"BE",
    "sg:address":"Heirbaan 20",
    "sg:city":"Dendermonde",
    "sg:orig_category":"M\u00e9decins and sp\u00e9cialistes",
    "sg:phone":"+32 52 22 58 13",
    "sg:postcode":"9200",
    "sg:province":"Oost-Vlaanderen",
    "wof:name":"T. Van Hoeymissen",
    "wof:placetype":"venue"
},
  "geometry": {"coordinates":[4.1127519608,51.0168838501],"type":"Point"}
}