{
  "type": "Feature",
  "properties": {
    "iso:country":"BE",
    "sg:address":"Melkmarkt 8",
    "sg:city":"Antwerpen",
    "sg:classifiers":[
        {
            "category":"Professional",
            "subcategory":"Advertising",
            "type":"Services"
        }
    ],
    "sg:phone":"+32 3 232 64 58",
    "sg:postcode":"2000",
    "sg:province":"Antwerpen",
    "sg:tags":[
        "item",
        "-",
        "business",
        "gift",
        "promotional"
    ],
    "wof:name":"Wine World",
    "wof:placetype":"venue"
},
  "geometry": {"coordinates":[4.4025759697,51.2208023071],"type":"Point"}
}