{
  "type": "Feature",
  "properties": {
    "iso:country":"BE",
    "sg:address":"Ieperstraat 172",
    "sg:city":"Heuvelland",
    "sg:orig_category":"Rundveehouders",
    "sg:phone":"+32 57 44 49 04",
    "sg:postcode":"8953",
    "sg:province":"West-Vlaanderen",
    "wof:name":"Jacques Deconinck",
    "wof:placetype":"venue"
},
  "geometry": {"coordinates":[2.8919250965,50.774105072],"type":"Point"}
}