{
  "type": "Feature",
  "properties": {
    "iso:country":"BE",
    "sg:address":"Houtstraat 55",
    "sg:city":"Gingelom",
    "sg:orig_category":"Artsen and specialisten",
    "sg:phone":"+32 11 48 57 35",
    "sg:postcode":"3890",
    "sg:province":"Limburg",
    "wof:name":"Roger Masquelier",
    "wof:placetype":"venue"
},
  "geometry": {"coordinates":[5.2104282379,50.7355766296],"type":"Point"}
}