{
  "type": "Feature",
  "properties": {
    "addr:full":"Rue Sainte-anne 60 Farciennes Hainaut 6240",
    "addr:housenumber":"60",
    "addr:postcode":"6240",
    "addr:street":"Rue Sainte-Anne",
    "iso:country":"BE",
    "sg:address":"Rue Sainte-anne 60",
    "sg:city":"Farciennes",
    "sg:classifiers":[
        {
            "category":"Banks & Credit Unions",
            "subcategory":"Investment Brokerage",
            "type":"Services"
        }
    ],
    "sg:phone":"+32 71 38 21 43",
    "sg:postcode":"6240",
    "sg:province":"Hainaut",
    "sg:tags":[
        "fence"
    ],
    "wof:name":"A.d.m.",
    "wof:placetype":"venue"
},
  "geometry": {"coordinates":[4.5442380905,50.4270362854],"type":"Point"}
}