{
  "type": "Feature",
  "properties": {
    "iso:country":"BE",
    "sg:address":"Verlengstraat 11",
    "sg:city":"Opglabbeek",
    "sg:orig_category":"Kapsalons",
    "sg:phone":"+32 89 85 76 24",
    "sg:postcode":"3660",
    "sg:province":"Limburg",
    "wof:name":"Martina Gabriels",
    "wof:placetype":"venue"
},
  "geometry": {"coordinates":[5.6155171394,51.0542831421],"type":"Point"}
}