{
  "type": "Feature",
  "properties": {
    "iso:country":"BE",
    "sg:address":"Molenmeers 7",
    "sg:city":"Brugge",
    "sg:orig_category":"Begrafeniswezen",
    "sg:phone":"+32 50 34 33 13",
    "sg:postcode":"8000",
    "sg:province":"West-Vlaanderen",
    "wof:name":"Algem. Ceremonie Onderm.",
    "wof:placetype":"venue"
},
  "geometry": {"coordinates":[3.2317450047,51.2100639343],"type":"Point"}
}