{
  "type": "Feature",
  "properties": {
    "iso:country":"BE",
    "sg:address":"Grote Markt 25",
    "sg:city":"Roeselare",
    "sg:orig_category":"Kantoormateriaal Speelgoed",
    "sg:phone":"+32 51 20 85 23",
    "sg:postcode":"8800",
    "sg:province":"West-Vlaanderen",
    "wof:name":"Christiaensen",
    "wof:placetype":"venue"
},
  "geometry": {"coordinates":[3.1245501041,50.9451904297],"type":"Point"}
}