{
  "type": "Feature",
  "properties": {
    "addr:full":"Rue De Bruxelles 68 Enghien Hainaut 7850",
    "addr:housenumber":"68",
    "addr:postcode":"7850",
    "addr:street":"Rue De Bruxelles",
    "iso:country":"BE",
    "sg:address":"Rue De Bruxelles 68",
    "sg:city":"Enghien",
    "sg:classifiers":[
        {
            "category":"Health Services",
            "subcategory":"Health Practitioner",
            "type":"Services"
        }
    ],
    "sg:phone":"+32 475 83 76 47",
    "sg:postcode":"7850",
    "sg:province":"Hainaut",
    "sg:tags":[
        "physiotherapist"
    ],
    "wof:name":"Vaerewyck Sophie",
    "wof:placetype":"venue"
},
  "geometry": {"coordinates":[4.0421700478,50.6949043274],"type":"Point"}
}