{
  "type": "Feature",
  "properties": {
    "iso:country":"BE",
    "sg:address":"Jonkershovestraat 278",
    "sg:city":"Houthulst",
    "sg:classifiers":[
        {
            "category":"Insurance",
            "subcategory":"Life Insurance",
            "type":"Services"
        }
    ],
    "sg:phone":"+32 51 54 11 12",
    "sg:postcode":"8650",
    "sg:province":"West-Vlaanderen",
    "sg:tags":[
        "assurance"
    ],
    "wof:name":"Dupon",
    "wof:placetype":"venue"
},
  "geometry": {"coordinates":[2.9257929325,50.9714813232],"type":"Point"}
}