{
  "type": "Feature",
  "properties": {
    "addr:full":"Bosstraat 92 Ternat Vlaams-Brabant 1742",
    "addr:housenumber":"92",
    "addr:postcode":"1742",
    "addr:street":"Bosstraat",
    "iso:country":"BE",
    "sg:address":"Bosstraat 92",
    "sg:city":"Ternat",
    "sg:orig_category":"Installation \u00e9lectrique r\u00e9sidentielle",
    "sg:phone":"+32 53 68 27 39",
    "sg:postcode":"1742",
    "sg:province":"Vlaams-Brabant",
    "wof:name":"Intelekt",
    "wof:placetype":"venue"
},
  "geometry": {"coordinates":[4.1311049461,50.8756103516],"type":"Point"}
}