{
  "type": "Feature",
  "properties": {
    "addr:full":"Nieuwstraat 54 Aalst Oost-Vlaanderen 9300",
    "addr:housenumber":"54",
    "addr:postcode":"9300",
    "addr:street":"Nieuwstraat",
    "iso:country":"BE",
    "sg:address":"Nieuwstraat 54",
    "sg:city":"Aalst",
    "sg:orig_category":"V\u00eatements",
    "sg:phone":"+32 53 77 98 23",
    "sg:postcode":"9300",
    "sg:province":"Oost-Vlaanderen",
    "wof:name":"Jery & Co",
    "wof:placetype":"venue"
},
  "geometry": {"coordinates":[4.0344672203,50.9381332397],"type":"Point"}
}