{
  "type": "Feature",
  "properties": {
    "addr:full":"Jules Capronstraat 12 Box 1 Ieper West-Vlaanderen 8900",
    "addr:housenumber":"12;1",
    "addr:postcode":"8900",
    "addr:street":"Capronstraat;Box",
    "iso:country":"BE",
    "sg:address":"Jules Capronstraat 12 Box 1",
    "sg:city":"Ieper",
    "sg:classifiers":[
        {
            "category":"Social Services",
            "type":"Services"
        }
    ],
    "sg:phone":"+32 57 21 85 55",
    "sg:postcode":"8900",
    "sg:province":"West-Vlaanderen",
    "wof:name":"Kinderopvang Kav",
    "wof:placetype":"venue"
},
  "geometry": {"coordinates":[2.8757278919,50.8511390686],"type":"Point"}
}