{
  "type": "Feature",
  "properties": {
    "iso:country":"BE",
    "sg:address":"Brusselsestraat 76",
    "sg:city":"Brakel",
    "sg:orig_category":"Sportclubs",
    "sg:phone":"+32 55 42 51 06",
    "sg:postcode":"9660",
    "sg:province":"Oost-Vlaanderen",
    "wof:name":"De Jonge Beginners",
    "wof:placetype":"venue"
},
  "geometry": {"coordinates":[3.785490036,50.8084716797],"type":"Point"}
}