{
  "type": "Feature",
  "properties": {
    "addr:full":"Middendijk 15 Peer Limburg 3990",
    "addr:housenumber":"15",
    "addr:postcode":"3990",
    "addr:street":"Middendijk",
    "iso:country":"BE",
    "sg:address":"Middendijk 15",
    "sg:city":"Peer",
    "sg:orig_category":"Eleveurs de bovins",
    "sg:phone":"+32 11 79 32 15",
    "sg:postcode":"3990",
    "sg:province":"Limburg",
    "wof:name":"Ludo Geerits",
    "wof:placetype":"venue"
},
  "geometry": {"coordinates":[5.4711480141,51.0620803833],"type":"Point"}
}