{
  "type": "Feature",
  "properties": {
    "addr:full":"Kwadestraat 22 Wevelgem (gullegem) West-Vlaanderen 8560",
    "addr:housenumber":"22",
    "addr:postcode":"8560",
    "addr:street":"Kwadestraat",
    "iso:country":"BE",
    "sg:address":"Kwadestraat 22",
    "sg:city":"Wevelgem (gullegem)",
    "sg:classifiers":[
        {
            "category":"Health Services",
            "subcategory":"Doctor",
            "type":"Services"
        }
    ],
    "sg:phone":"+32 56 41 47 85",
    "sg:postcode":"8560",
    "sg:province":"West-Vlaanderen",
    "sg:tags":[
        "medicinephysicians",
        "surgeon"
    ],
    "wof:name":"Herman T",
    "wof:placetype":"venue"
},
  "geometry": {"coordinates":[3.2061970234,50.8477478027],"type":"Point"}
}