{
  "type": "Feature",
  "properties": {
    "addr:full":"Rue Neuve 23 Chiny Luxembourg 6810",
    "addr:housenumber":"23",
    "addr:postcode":"6810",
    "addr:street":"Rue Neuve",
    "iso:country":"BE",
    "sg:address":"Rue Neuve 23",
    "sg:city":"Chiny",
    "sg:orig_category":"Installation de menuiserie en bois and plastique. Meubles D\u00e9taillants, Am\u00e9nagement de B\u00e2timents et d",
    "sg:phone":"+32 61 31 15 26",
    "sg:postcode":"6810",
    "sg:province":"Luxembourg",
    "wof:name":"Meubles Maury",
    "wof:placetype":"venue"
},
  "geometry": {"coordinates":[5.3405580521,49.7382736206],"type":"Point"}
}