{
  "type": "Feature",
  "properties": {
    "addr:full":"Vrijhem 59 Oosterzele (balegem) Oost-Vlaanderen 9860",
    "addr:housenumber":"59",
    "addr:postcode":"9860",
    "addr:street":"Vrijhem",
    "iso:country":"BE",
    "sg:address":"Vrijhem 59",
    "sg:city":"Oosterzele (balegem)",
    "sg:classifiers":[
        {
            "category":"Freight",
            "type":"Transportation"
        }
    ],
    "sg:phone":"+32 9 362 18 80",
    "sg:postcode":"9860",
    "sg:province":"Oost-Vlaanderen",
    "sg:tags":[
        "-",
        "transport"
    ],
    "wof:name":"Gerda-trans",
    "wof:placetype":"venue"
},
  "geometry": {"coordinates":[3.7885930538,50.9282188416],"type":"Point"}
}