{
  "type": "Feature",
  "properties": {
    "addr:full":"Generaal De Wittelaan 4 Mechelen Antwerpen 2800",
    "addr:housenumber":"4",
    "addr:postcode":"2800",
    "addr:street":"Generaal De Wittelaan",
    "iso:country":"BE",
    "sg:address":"Generaal De Wittelaan 4",
    "sg:city":"Mechelen",
    "sg:classifiers":[
        {
            "category":"Shopping",
            "subcategory":"Pharmacy",
            "type":"Retail Goods"
        }
    ],
    "sg:phone":"+32 15 29 42 20",
    "sg:postcode":"2800",
    "sg:province":"Antwerpen",
    "sg:tags":[
        "preparation",
        "pharmaceutical"
    ],
    "wof:name":"Asma C.v.",
    "wof:placetype":"venue"
},
  "geometry": {"coordinates":[4.4557209015,51.0587005615],"type":"Point"}
}