{
  "type": "Feature",
  "properties": {
    "addr:full":"Botermelkdijk 278 Schoten Antwerpen 2900",
    "addr:housenumber":"278",
    "addr:postcode":"2900",
    "addr:street":"Botermelkdijk",
    "iso:country":"BE",
    "sg:address":"Botermelkdijk 278",
    "sg:city":"Schoten",
    "sg:classifiers":[
        {
            "category":"Banks & Credit Unions",
            "subcategory":"Investment Brokerage",
            "type":"Services"
        }
    ],
    "sg:phone":"+32 3 651 62 00",
    "sg:postcode":"2900",
    "sg:province":"Antwerpen",
    "sg:tags":[
        "fence"
    ],
    "wof:name":"Timeless Wood Nv",
    "wof:placetype":"venue"
},
  "geometry": {"coordinates":[4.5268011093,51.2757873535],"type":"Point"}
}