{
  "type": "Feature",
  "properties": {
    "addr:full":"Zuidstraat 100 Koekelare West-Vlaanderen 8680",
    "addr:housenumber":"100",
    "addr:postcode":"8680",
    "addr:street":"Zuidstraat",
    "iso:country":"BE",
    "sg:address":"Zuidstraat 100",
    "sg:city":"Koekelare",
    "sg:orig_category":"Varkenskwekers",
    "sg:phone":"+32 51 58 84 99",
    "sg:postcode":"8680",
    "sg:province":"West-Vlaanderen",
    "wof:name":"Luciaan Martele",
    "wof:placetype":"venue"
},
  "geometry": {"coordinates":[2.9773290157,51.0784683228],"type":"Point"}
}