{
  "type": "Feature",
  "properties": {
    "iso:country":"BE",
    "sg:address":"Nijverheidstraat 64",
    "sg:city":"Waregem (beveren-leie)",
    "sg:classifiers":[
        {
            "category":"Real Estate",
            "subcategory":"Architect",
            "type":"Services"
        }
    ],
    "sg:phone":"+32 56 71 49 26",
    "sg:postcode":"8791",
    "sg:province":"West-Vlaanderen",
    "wof:name":"Dejonghe G",
    "wof:placetype":"venue"
},
  "geometry": {"coordinates":[3.3484559059,50.8785934448],"type":"Point"}
}