{
  "type": "Feature",
  "properties": {
    "iso:country":"BE",
    "sg:address":"Kuilenstraat 33",
    "sg:city":"Genk",
    "sg:orig_category":"Fotografen and fotostudio's",
    "sg:phone":"+32 89 36 18 66",
    "sg:postcode":"3600",
    "sg:province":"Limburg",
    "wof:name":"Albert Peyffers",
    "wof:placetype":"venue"
},
  "geometry": {"coordinates":[5.4947290421,50.9706420898],"type":"Point"}
}