{
  "type": "Feature",
  "properties": {
    "iso:country":"BE",
    "sg:address":"Ardooisesteenweg 69",
    "sg:city":"Roeselare",
    "sg:classifiers":[
        {
            "category":"Shopping",
            "subcategory":"Florist",
            "type":"Retail Goods"
        }
    ],
    "sg:phone":"+32 51 24 36 01",
    "sg:postcode":"8800",
    "sg:province":"West-Vlaanderen",
    "wof:name":"Fleur",
    "wof:placetype":"venue"
},
  "geometry": {"coordinates":[3.1333649158,50.9501419067],"type":"Point"}
}