{
  "type": "Feature",
  "properties": {
    "iso:country":"BE",
    "sg:address":"Bergensesteenweg 189",
    "sg:city":"Sint-pieters-leeuw",
    "sg:orig_category":"Chemicali\u00ebn Gh",
    "sg:phone":"+32 2 331 30 04",
    "sg:postcode":"1600",
    "sg:province":"Vlaams-Brabant",
    "wof:name":"Dysseleer J & Fils",
    "wof:placetype":"venue"
},
  "geometry": {"coordinates":[4.2868828773,50.7977638245],"type":"Point"}
}