{
  "type": "Feature",
  "properties": {
    "addr:full":"Postelarenweg 121 Mol Antwerpen 2400",
    "addr:housenumber":"121",
    "addr:postcode":"2400",
    "addr:street":"Postelarenweg",
    "iso:country":"BE",
    "sg:address":"Postelarenweg 121",
    "sg:city":"Mol",
    "sg:orig_category":"M\u00e9decins and sp\u00e9cialistes",
    "sg:phone":"+32 14 31 98 87",
    "sg:postcode":"2400",
    "sg:province":"Antwerpen",
    "wof:name":"Jean Delespaul",
    "wof:placetype":"venue"
},
  "geometry": {"coordinates":[5.1041297913,51.1935310364],"type":"Point"}
}