{
  "type": "Feature",
  "properties": {
    "iso:country":"BE",
    "sg:address":"Schollebeekstraat 4",
    "sg:city":"Lier",
    "sg:orig_category":"RESTAURANTS: CAF\u00c9S",
    "sg:phone":"+32 3 480 52 42",
    "sg:postcode":"2500",
    "sg:province":"Antwerpen",
    "wof:name":"Taverne Soetemin",
    "wof:placetype":"venue"
},
  "geometry": {"coordinates":[4.5841670036,51.1178741455],"type":"Point"}
}