{
  "type": "Feature",
  "properties": {
    "addr:full":"Dr\u00e8ve Du Ch\u00e2teau 3 Rixensart Brabant Wallon 1330",
    "addr:housenumber":"3",
    "addr:postcode":"1330",
    "addr:street":"Dre\u0300Ve Du Cha\u0302Teau;Wallon",
    "iso:country":"BE",
    "sg:address":"Dr\u00e8ve Du Ch\u00e2teau 3",
    "sg:city":"Rixensart",
    "sg:classifiers":[
        {
            "category":"Insurance",
            "subcategory":"Insurance Agent",
            "type":"Services"
        }
    ],
    "sg:phone":"+32 2 653 48 87",
    "sg:postcode":"1330",
    "sg:province":"Brabant Wallon",
    "sg:tags":[
        "broker"
    ],
    "wof:name":"Hayt B",
    "wof:placetype":"venue"
},
  "geometry": {"coordinates":[4.535943985,50.712600708],"type":"Point"}
}