{
  "type": "Feature",
  "properties": {
    "iso:country":"BE",
    "sg:address":"Nederkouter 139",
    "sg:city":"Gent",
    "sg:orig_category":"Brood, gebak and snoepgoed",
    "sg:phone":"+32 9 225 70 11",
    "sg:postcode":"9000",
    "sg:province":"Oost-Vlaanderen",
    "wof:name":"Patisserie Damme",
    "wof:placetype":"venue"
},
  "geometry": {"coordinates":[3.7222349644,51.0464897156],"type":"Point"}
}