{
  "type": "Feature",
  "properties": {
    "iso:country":"BE",
    "sg:address":"Rue De Bomal 8",
    "sg:city":"Incourt",
    "sg:orig_category":"Woningbouw",
    "sg:phone":"+32 10 88 93 21",
    "sg:postcode":"1315",
    "sg:province":"Brabant Wallon",
    "wof:name":"Gerard Haesendonck",
    "wof:placetype":"venue"
},
  "geometry": {"coordinates":[4.8400650024,50.6765365601],"type":"Point"}
}