{
  "type": "Feature",
  "properties": {
    "addr:full":"Rue Du Petit Berchem 71 Bruxelles (berchem-sainte-agathe) Bruxelles-Capitale 1082",
    "addr:housenumber":"71",
    "addr:postcode":"1082",
    "addr:street":"Rue Du Petit Berchem",
    "iso:country":"BE",
    "sg:address":"Rue Du Petit Berchem 71",
    "sg:city":"Bruxelles (berchem-sainte-agathe)",
    "sg:classifiers":[
        {
            "category":"Home & Garden",
            "subcategory":"Carpets & Floor Coverings",
            "type":"Retail Goods"
        }
    ],
    "sg:phone":"+32 2 469 02 61",
    "sg:postcode":"1082",
    "sg:province":"Bruxelles-Capitale",
    "sg:tags":[
        "repair",
        "stone",
        "natural",
        "-",
        "mainten",
        "marble"
    ],
    "wof:name":"R\u00e9no Marbre",
    "wof:placetype":"venue"
},
  "geometry": {"coordinates":[4.3086562157,50.8661499023],"type":"Point"}
}