{
  "type": "Feature",
  "properties": {
    "addr:full":"Stationsstraat 108ba Landen Vlaams-Brabant 3400",
    "addr:housenumber":"108ba",
    "addr:postcode":"3400",
    "addr:street":"Stationsstraat",
    "iso:country":"BE",
    "sg:address":"Stationsstraat 108ba",
    "sg:city":"Landen",
    "sg:orig_category":"Advocaten and juridische adviseurs",
    "sg:phone":"+32 11 88 38 34",
    "sg:postcode":"3400",
    "sg:province":"Vlaams-Brabant",
    "wof:name":"Winny Tirmarche",
    "wof:placetype":"venue"
},
  "geometry": {"coordinates":[5.0806789398,50.7499923706],"type":"Point"}
}