{
  "type": "Feature",
  "properties": {
    "iso:country":"BE",
    "sg:address":"Lierbaan 79",
    "sg:city":"Putte",
    "sg:classifiers":[
        {
            "category":"Travel",
            "subcategory":"Travel Agent",
            "type":"Entertainment"
        }
    ],
    "sg:phone":"+32 16 23 69 36",
    "sg:postcode":"2580",
    "sg:province":"Antwerpen",
    "sg:tags":[
        "agency"
    ],
    "wof:name":"No Distance Nv",
    "wof:placetype":"venue"
},
  "geometry": {"coordinates":[4.6289110184,51.0577659607],"type":"Point"}
}