{
  "type": "Feature",
  "properties": {
    "iso:country":"BE",
    "sg:address":"Chauss\u00e9e De Louvain 281",
    "sg:city":"Namur (bouge)",
    "sg:classifiers":[
        {
            "category":"Retail",
            "subcategory":"Repair Shop",
            "type":"Services"
        }
    ],
    "sg:phone":"+32 81 21 26 96",
    "sg:postcode":"5004",
    "sg:province":"Namur",
    "sg:tags":[
        "machine",
        "sewing",
        "-"
    ],
    "wof:name":"Bernina-pfaff-parmentier J-c",
    "wof:placetype":"venue"
},
  "geometry": {"coordinates":[4.8770098686,50.4771232605],"type":"Point"}
}