{
  "type": "Feature",
  "properties": {
    "iso:country":"BE",
    "sg:address":"Begonialaan 32",
    "sg:city":"Wervik",
    "sg:classifiers":[
        {
            "category":"Communications",
            "subcategory":"Film & Video Production",
            "type":"Services"
        }
    ],
    "sg:phone":"+32 477 83 59 20",
    "sg:postcode":"8940",
    "sg:province":"West-Vlaanderen",
    "sg:tags":[
        "realisation",
        "-"
    ],
    "wof:name":"On",
    "wof:placetype":"venue"
},
  "geometry": {"coordinates":[3.0542550087,50.7841644287],"type":"Point"}
}