{
  "type": "Feature",
  "properties": {
    "addr:full":"Tulpenlaan 4 Jabbeke West-Vlaanderen 8490",
    "addr:housenumber":"4",
    "addr:postcode":"8490",
    "addr:street":"Tulpenlaan",
    "iso:country":"BE",
    "sg:address":"Tulpenlaan 4",
    "sg:city":"Jabbeke",
    "sg:orig_category":"Beheer van reclamemedia",
    "sg:phone":"+32 50 81 32 73",
    "sg:postcode":"8490",
    "sg:province":"West-Vlaanderen",
    "wof:name":"Maertens",
    "wof:placetype":"venue"
},
  "geometry": {"coordinates":[3.0723590851,51.1654472351],"type":"Point"}
}