{
  "type": "Feature",
  "properties": {
    "iso:country":"BE",
    "sg:address":"Boerenkrijglaan 7",
    "sg:city":"Westerlo",
    "sg:classifiers":[
        {
            "category":"Retail",
            "subcategory":"Repair Shop",
            "type":"Services"
        }
    ],
    "sg:phone":"+32 14 54 50 72",
    "sg:postcode":"2260",
    "sg:province":"Antwerpen",
    "sg:tags":[
        "photographic",
        "equipment",
        "-",
        "accessory"
    ],
    "wof:name":"Foto Karel Bvba",
    "wof:placetype":"venue"
},
  "geometry": {"coordinates":[4.9151968956,51.0868530273],"type":"Point"}
}