{
  "type": "Feature",
  "properties": {
    "iso:country":"BE",
    "sg:address":"Lesseliersdreef 55",
    "sg:city":"Beveren",
    "sg:orig_category":"Agences de publicit\u00e9",
    "sg:phone":"+32 3 755 28 05",
    "sg:postcode":"9120",
    "sg:province":"Oost-Vlaanderen",
    "wof:name":"Bureau Qualitext",
    "wof:placetype":"venue"
},
  "geometry": {"coordinates":[4.2491488457,51.2063064575],"type":"Point"}
}