{
  "type": "Feature",
  "properties": {
    "addr:full":"Everselstraat 11 Beringen Limburg 3580",
    "addr:housenumber":"11",
    "addr:postcode":"3580",
    "addr:street":"Everselstraat",
    "iso:country":"BE",
    "sg:address":"Everselstraat 11",
    "sg:city":"Beringen",
    "sg:classifiers":[
        {
            "category":"Health Services",
            "subcategory":"Doctor",
            "type":"Services"
        }
    ],
    "sg:phone":"+32 11 42 44 80",
    "sg:postcode":"3580",
    "sg:province":"Limburg",
    "sg:tags":[
        "medicinephysicians",
        "surgeon"
    ],
    "wof:name":"Lambrechts G",
    "wof:placetype":"venue"
},
  "geometry": {"coordinates":[5.2277998924,51.043258667],"type":"Point"}
}