{
  "type": "Feature",
  "properties": {
    "addr:full":"Derbystr 241 Gent Oost-Vlaanderen 9051",
    "addr:housenumber":"241",
    "addr:postcode":"9051",
    "addr:street":"Oost-Vlaanderen",
    "iso:country":"BE",
    "sg:address":"Derbystr 241",
    "sg:city":"Gent",
    "sg:orig_category":"Gestion de portefeuilles and fortunes, conseils en placements",
    "sg:phone":"+32 9 222 06 22",
    "sg:postcode":"9051",
    "sg:province":"Oost-Vlaanderen",
    "wof:name":"C.i.b. Vlaamse Gemeenschap",
    "wof:placetype":"venue"
},
  "geometry": {"coordinates":[3.6973481178,51.0233612061],"type":"Point"}
}