{
  "type": "Feature",
  "properties": {
    "iso:country":"BE",
    "sg:address":"Rue Du Stade 80",
    "sg:city":"Verviers (stembert)",
    "sg:classifiers":[
        {
            "category":"Fast Food",
            "type":"Food & Drink"
        }
    ],
    "sg:phone":"+32 87 35 27 67",
    "sg:postcode":"4801",
    "sg:province":"Li\u00e8ge",
    "sg:tags":[
        "fried",
        "stand",
        "potato"
    ],
    "wof:name":"Stade Friterie",
    "wof:placetype":"venue"
},
  "geometry": {"coordinates":[5.8791308403,50.5913276672],"type":"Point"}
}