{
  "type": "Feature",
  "properties": {
    "iso:country":"BE",
    "sg:address":"Hoogstraat 69",
    "sg:city":"Genk",
    "sg:classifiers":[
        {
            "category":"Professional",
            "subcategory":"Employment Agencies",
            "type":"Services"
        }
    ],
    "sg:phone":"+32 89 35 60 30",
    "sg:postcode":"3600",
    "sg:province":"Limburg",
    "sg:tags":[
        "personnel",
        "temporary"
    ],
    "wof:name":"Asap Interim Nv",
    "wof:placetype":"venue"
},
  "geometry": {"coordinates":[5.5052719116,50.9593315125],"type":"Point"}
}