{
  "type": "Feature",
  "properties": {
    "addr:full":"Av. Constant Grandprez 25ba Stavelot Li\u00e8ge 4970",
    "addr:housenumber":"25ba",
    "addr:postcode":"4970",
    "addr:street":"Av. Constant Grandprez",
    "iso:country":"BE",
    "sg:address":"Av. Constant Grandprez 25ba",
    "sg:city":"Stavelot",
    "sg:orig_category":"M\u00e9decins and sp\u00e9cialistes",
    "sg:phone":"+32 80 86 31 88",
    "sg:postcode":"4970",
    "sg:province":"Li\u00e8ge",
    "wof:name":"Joseph Herbrand",
    "wof:placetype":"venue"
},
  "geometry": {"coordinates":[5.9233970642,50.3891868591],"type":"Point"}
}