{
  "type": "Feature",
  "properties": {
    "addr:full":"Munt 2 Brussel/bruxelles Bruxelles-Capitale 1000",
    "addr:housenumber":"2",
    "addr:postcode":"1000",
    "addr:street":"Munt;/",
    "iso:country":"BE",
    "sg:address":"Munt 2",
    "sg:city":"Brussel/bruxelles",
    "sg:orig_category":"Tijdelijke werkgelegenheid and uitzendkantoren",
    "sg:phone":"+32 2 226 05 70",
    "sg:postcode":"1000",
    "sg:province":"Bruxelles-Capitale",
    "wof:name":"Adecco",
    "wof:placetype":"venue"
},
  "geometry": {"coordinates":[4.353741169,50.8502426147],"type":"Point"}
}