{
  "type": "Feature",
  "properties": {
    "iso:country":"BE",
    "sg:address":"Menenstraat 240",
    "sg:city":"Moeskroen/mouscron",
    "sg:classifiers":[
        {
            "category":"Restaurant",
            "type":"Food & Drink"
        }
    ],
    "sg:phone":"+32 56 34 59 60",
    "sg:postcode":"7700",
    "sg:province":"Hainaut",
    "wof:name":"Rest. Tables De Breughel",
    "wof:placetype":"venue"
},
  "geometry": {"coordinates":[3.2323200703,50.7400932312],"type":"Point"}
}