{
  "type": "Feature",
  "properties": {
    "addr:full":"Bruggestraat 104a Ichtegem West-Vlaanderen 8480",
    "addr:housenumber":"104a",
    "addr:postcode":"8480",
    "addr:street":"Bruggestraat",
    "iso:country":"BE",
    "sg:address":"Bruggestraat 104a",
    "sg:city":"Ichtegem",
    "sg:orig_category":"Installations and terrains de sport hors centres sportifs. Centres de fitness. Clubs de sport. Centr",
    "sg:phone":"+32 59 29 00 00",
    "sg:postcode":"8480",
    "sg:province":"West-Vlaanderen",
    "wof:name":"Sporthal",
    "wof:placetype":"venue"
},
  "geometry": {"coordinates":[3.0356330872,51.1315002441],"type":"Point"}
}