{
  "type": "Feature",
  "properties": {
    "addr:full":"Wee\u00cbn 7 Olen Antwerpen 2250",
    "addr:housenumber":"7",
    "addr:postcode":"2250",
    "addr:street":"Weee\u0308N",
    "iso:country":"BE",
    "sg:address":"Wee\u00cbn 7",
    "sg:city":"Olen",
    "sg:orig_category":"Woningbouw",
    "sg:phone":"+32 14 26 30 36",
    "sg:postcode":"2250",
    "sg:province":"Antwerpen",
    "wof:name":"Luc Herdewijn",
    "wof:placetype":"venue"
},
  "geometry": {"coordinates":[4.8545007706,51.1397781372],"type":"Point"}
}