{
  "type": "Feature",
  "properties": {
    "addr:full":"Kerkstraat 76 Rumst Antwerpen 2840",
    "addr:housenumber":"76",
    "addr:postcode":"2840",
    "addr:street":"Kerkstraat",
    "iso:country":"BE",
    "sg:address":"Kerkstraat 76",
    "sg:city":"Rumst",
    "sg:orig_category":"Banques and organismes de cr\u00e9dit. Assurances",
    "sg:phone":"+32 3 888 24 18",
    "sg:postcode":"2840",
    "sg:province":"Antwerpen",
    "wof:name":"Verwerft",
    "wof:placetype":"venue"
},
  "geometry": {"coordinates":[4.4303388596,51.0794944763],"type":"Point"}
}