{
  "type": "Feature",
  "properties": {
    "iso:country":"BE",
    "sg:address":"De Locht 11",
    "sg:city":"Tongeren",
    "sg:orig_category":"Producteurs de fruits",
    "sg:phone":"+32 12 26 12 89",
    "sg:postcode":"3700",
    "sg:province":"Limburg",
    "wof:name":"Malcosort",
    "wof:placetype":"venue"
},
  "geometry": {"coordinates":[5.4445691109,50.7896728516],"type":"Point"}
}