{
  "type": "Feature",
  "properties": {
    "addr:full":"Rue Lucien-petit 24 Gembloux Namur 5030",
    "addr:housenumber":"24",
    "addr:postcode":"5030",
    "addr:street":"Rue Lucien-Petit;Namur",
    "iso:country":"BE",
    "sg:address":"Rue Lucien-petit 24",
    "sg:city":"Gembloux",
    "sg:classifiers":[
        {
            "category":"Personal",
            "subcategory":"Beauty Salon",
            "type":"Services"
        }
    ],
    "sg:phone":"+32 81 61 50 77",
    "sg:postcode":"5030",
    "sg:province":"Namur",
    "sg:tags":[
        "de",
        "coiffure"
    ],
    "wof:name":"Coiffure Patricia",
    "wof:placetype":"venue"
},
  "geometry": {"coordinates":[4.6859941483,50.5575408936],"type":"Point"}
}