{
  "type": "Feature",
  "properties": {
    "iso:country":"BE",
    "sg:address":"Rue Aim\u00e9 Hoslet 8",
    "sg:city":"Grez-doiceau (bossut-gottechain)",
    "sg:orig_category":"Non-Classified Establishments",
    "sg:phone":"+32 10 84 40 45",
    "sg:postcode":"1390",
    "sg:province":"Brabant Wallon",
    "wof:name":"Timmermans Jj",
    "wof:placetype":"venue"
},
  "geometry": {"coordinates":[4.6480569839,50.7700843811],"type":"Point"}
}