{
  "type": "Feature",
  "properties": {
    "addr:full":"Gravin Johannalaan 10 Eeklo Oost-Vlaanderen 9900",
    "addr:housenumber":"10",
    "addr:postcode":"9900",
    "addr:street":"Gravin Johannalaan",
    "iso:country":"BE",
    "sg:address":"Gravin Johannalaan 10",
    "sg:city":"Eeklo",
    "sg:orig_category":"Artsen and specialisten",
    "sg:phone":"+32 9 377 07 92",
    "sg:postcode":"9900",
    "sg:province":"Oost-Vlaanderen",
    "wof:name":"Annelies Van Rie",
    "wof:placetype":"venue"
},
  "geometry": {"coordinates":[3.552973032,51.1932601929],"type":"Point"}
}