{
  "type": "Feature",
  "properties": {
    "iso:country":"BE",
    "sg:address":"Rue Des Eperonniers 61",
    "sg:city":"Brussel/bruxelles",
    "sg:orig_category":"Salles de spectacles. Bars. Biblioth\u00e8ques and archives publiques. Caf\u00e9s",
    "sg:phone":"+32 2 513 69 65",
    "sg:postcode":"1000",
    "sg:province":"Bruxelles-Capitale",
    "wof:name":"Comics Trip",
    "wof:placetype":"venue"
},
  "geometry": {"coordinates":[4.3530678749,50.8452339172],"type":"Point"}
}