{
  "type": "Feature",
  "properties": {
    "addr:full":"Koningin Astridlaan 25 Kapellen Antwerpen 2950",
    "addr:housenumber":"25",
    "addr:postcode":"2950",
    "addr:street":"Koningin Astridlaan",
    "iso:country":"BE",
    "sg:address":"Koningin Astridlaan 25",
    "sg:city":"Kapellen",
    "sg:classifiers":[
        {
            "category":"Building & Trades",
            "subcategory":"Plumbing",
            "type":"Services"
        }
    ],
    "sg:phone":"+32 3 366 15 00",
    "sg:postcode":"2950",
    "sg:province":"Antwerpen",
    "sg:tags":[
        "pipe",
        "drain",
        "unblocking"
    ],
    "wof:name":"A.a. De Ceuster",
    "wof:placetype":"venue"
},
  "geometry": {"coordinates":[4.4386000633,51.3134880066],"type":"Point"}
}