{
  "type": "Feature",
  "properties": {
    "addr:full":"Eerste-meistraat 17b1 Tongeren Limburg 3700",
    "addr:housenumber":"17b1",
    "addr:postcode":"3700",
    "addr:street":"Eerste-Meistraat",
    "iso:country":"BE",
    "sg:address":"Eerste-meistraat 17b1",
    "sg:city":"Tongeren",
    "sg:orig_category":"Boissons",
    "sg:phone":"+32 12 23 11 89",
    "sg:postcode":"3700",
    "sg:province":"Limburg",
    "wof:name":"Brouwerij Bremans",
    "wof:placetype":"venue"
},
  "geometry": {"coordinates":[5.4951000214,50.7837295532],"type":"Point"}
}