{
  "type": "Feature",
  "properties": {
    "iso:country":"BE",
    "sg:address":"Rue Du Saclet 4",
    "sg:city":"Estaimpuis",
    "sg:classifiers":[
        {
            "category":"Building & Trades",
            "subcategory":"Construction",
            "type":"Services"
        }
    ],
    "sg:phone":"+32 56 48 86 86",
    "sg:postcode":"7730",
    "sg:province":"Hainaut",
    "sg:tags":[
        "stair"
    ],
    "wof:name":"C.m. Alfiso Sprl",
    "wof:placetype":"venue"
},
  "geometry": {"coordinates":[3.2607569695,50.7057800293],"type":"Point"}
}