{
  "type": "Feature",
  "properties": {
    "addr:full":"Avenue De La Sapini\u00e8re 48 Bruxelles (uccle) Bruxelles-Capitale 1180",
    "addr:housenumber":"48",
    "addr:postcode":"1180",
    "addr:street":"Avenue De La Sapinie\u0300Re",
    "iso:country":"BE",
    "sg:address":"Avenue De La Sapini\u00e8re 48",
    "sg:city":"Bruxelles (uccle)",
    "sg:classifiers":[
        {
            "category":"Real Estate",
            "subcategory":"Real Estate Services",
            "type":"Services"
        }
    ],
    "sg:phone":"+32 2 375 73 10",
    "sg:postcode":"1180",
    "sg:province":"Bruxelles-Capitale",
    "wof:name":"A C S & T",
    "wof:placetype":"venue"
},
  "geometry": {"coordinates":[4.3735151291,50.7763404846],"type":"Point"}
}