{
  "type": "Feature",
  "properties": {
    "iso:country":"BE",
    "sg:address":"Gevaerts-zuid 18",
    "sg:city":"Beernem",
    "sg:classifiers":[
        {
            "category":"Professional",
            "subcategory":"Art Services",
            "type":"Services"
        }
    ],
    "sg:phone":"+32 50 78 08 98",
    "sg:postcode":"8730",
    "sg:province":"West-Vlaanderen",
    "sg:tags":[
        "photographer"
    ],
    "wof:name":"Goethals J",
    "wof:placetype":"venue"
},
  "geometry": {"coordinates":[3.3032150269,51.1413955688],"type":"Point"}
}