{
  "type": "Feature",
  "properties": {
    "addr:full":"Karel Oomsstraat 2 Antwerpen Antwerpen 2018",
    "addr:housenumber":"2",
    "addr:postcode":"2018",
    "addr:street":"Karel Oomsstraat",
    "iso:country":"BE",
    "sg:address":"Karel Oomsstraat 2",
    "sg:city":"Antwerpen",
    "sg:orig_category":"Bloemen and planten",
    "sg:phone":"+32 3 238 45 24",
    "sg:postcode":"2018",
    "sg:province":"Antwerpen",
    "wof:name":"Creaflower",
    "wof:placetype":"venue"
},
  "geometry": {"coordinates":[4.4102568626,51.1974830627],"type":"Point"}
}