{
  "type": "Feature",
  "properties": {
    "iso:country":"BE",
    "sg:address":"Fraikinstraat 27",
    "sg:city":"Herentals",
    "sg:orig_category":"Apotheken",
    "sg:phone":"+32 14 21 11 67",
    "sg:postcode":"2200",
    "sg:province":"Antwerpen",
    "wof:name":"Jan Haerens",
    "wof:placetype":"venue"
},
  "geometry": {"coordinates":[4.834608078,51.1805992126],"type":"Point"}
}