{
  "type": "Feature",
  "properties": {
    "addr:full":"Rue Longue Hayoulle 11b33 Fleron Li\u00e8ge 4620",
    "addr:housenumber":"11b33",
    "addr:postcode":"4620",
    "addr:street":"Rue Longue Hayoulle",
    "iso:country":"BE",
    "sg:address":"Rue Longue Hayoulle 11b33",
    "sg:city":"Fleron",
    "sg:orig_category":"Artsen and specialisten",
    "sg:phone":"+32 4 358 18 11",
    "sg:postcode":"4620",
    "sg:province":"Li\u00e8ge",
    "wof:name":"Joelle Thonar",
    "wof:placetype":"venue"
},
  "geometry": {"coordinates":[5.6880259514,50.6100273132],"type":"Point"}
}