{
  "type": "Feature",
  "properties": {
    "iso:country":"BE",
    "sg:address":"Au Fonds R\u00e2ce 25 - Zi",
    "sg:city":"Waremme",
    "sg:orig_category":"Ketchup",
    "sg:phone":"+32 19 32 27 78",
    "sg:postcode":"4300",
    "sg:province":"Li\u00e8ge",
    "wof:name":"Colona S.a.",
    "wof:placetype":"venue"
},
  "geometry": {"coordinates":[5.2565498352,50.6982498169],"type":"Point"}
}