{
  "type": "Feature",
  "properties": {
    "iso:country":"BE",
    "sg:address":"Vis\u00e9steenweg 192a",
    "sg:city":"Riemst",
    "sg:classifiers":[
        {
            "category":"Personal",
            "subcategory":"Tattoo Parlor",
            "type":"Services"
        }
    ],
    "sg:phone":"+32 12 45 57 98",
    "sg:postcode":"3770",
    "sg:province":"Limburg",
    "sg:tags":[
        "tattooists"
    ],
    "wof:name":"Wishbone Tattoo",
    "wof:placetype":"venue"
},
  "geometry": {"coordinates":[5.606347084,50.8036117554],"type":"Point"}
}