{
  "type": "Feature",
  "properties": {
    "addr:full":"Rue Du Tambour 36 Bouillon Luxembourg 6838",
    "addr:housenumber":"36",
    "addr:postcode":"6838",
    "addr:street":"Rue Du Tambour",
    "iso:country":"BE",
    "sg:address":"Rue Du Tambour 36",
    "sg:city":"Bouillon",
    "sg:orig_category":"Apotheken Medische and orthopedische apparaten",
    "sg:phone":"+32 61 46 72 32",
    "sg:postcode":"6838",
    "sg:province":"Luxembourg",
    "wof:name":"Y. Hermans",
    "wof:placetype":"venue"
},
  "geometry": {"coordinates":[5.0071702003,49.7973403931],"type":"Point"}
}