{
  "type": "Feature",
  "properties": {
    "addr:full":"Rue De Messines 1 Komen-waasten/comines-warneton Hainaut 7782",
    "addr:housenumber":"1",
    "addr:postcode":"7782",
    "addr:street":"Rue De Messines",
    "iso:country":"BE",
    "sg:address":"Rue De Messines 1",
    "sg:city":"Komen-waasten/comines-warneton",
    "sg:orig_category":"Protection civile",
    "sg:phone":"+32 56 58 83 59",
    "sg:postcode":"7782",
    "sg:province":"Hainaut",
    "wof:name":"Corps De Pompiers",
    "wof:placetype":"venue"
},
  "geometry": {"coordinates":[2.8795371056,50.7278747559],"type":"Point"}
}