{
  "type": "Feature",
  "properties": {
    "iso:country":"BE",
    "sg:address":"Rue De Rochefort 578",
    "sg:city":"Beauraing (focant)",
    "sg:classifiers":[
        {
            "category":"Fast Food",
            "type":"Food & Drink"
        }
    ],
    "sg:phone":"+32 474 99 85 43",
    "sg:postcode":"5572",
    "sg:province":"Namur",
    "sg:tags":[
        "fried",
        "stand",
        "potato"
    ],
    "wof:name":"Godin (le) Friterie",
    "wof:placetype":"venue"
},
  "geometry": {"coordinates":[5.0448889732,50.1337814331],"type":"Point"}
}