{
  "type": "Feature",
  "properties": {
    "iso:country":"BE",
    "sg:address":"Droeshoutstraat 107e",
    "sg:city":"Opwijk",
    "sg:orig_category":"Installation de menuiserie en bois and plastique",
    "sg:phone":"+32 52 35 64 50",
    "sg:postcode":"1745",
    "sg:province":"Vlaams-Brabant",
    "wof:name":"Gustaaf Willocx",
    "wof:placetype":"venue"
},
  "geometry": {"coordinates":[4.1728000641,50.9559669495],"type":"Point"}
}