{
  "type": "Feature",
  "properties": {
    "iso:country":"BE",
    "sg:address":"Rue Georges Lemoine 72",
    "sg:city":"Charleroi",
    "sg:orig_category":"Traitements param\u00e9dicaux",
    "sg:phone":"+32 71 34 05 65",
    "sg:postcode":"6043",
    "sg:province":"Hainaut",
    "wof:name":"L\u00c9onard",
    "wof:placetype":"venue"
},
  "geometry": {"coordinates":[4.4899430275,50.4504508972],"type":"Point"}
}