{
  "type": "Feature",
  "properties": {
    "iso:country":"BE",
    "sg:address":"Duffelsesteenweg 159",
    "sg:city":"Lint",
    "sg:orig_category":"Avocats and conseillers juridiques",
    "sg:phone":"+32 3 454 01 72",
    "sg:postcode":"2547",
    "sg:province":"Antwerpen",
    "wof:name":"K. Goossens",
    "wof:placetype":"venue"
},
  "geometry": {"coordinates":[4.4930729866,51.1229095459],"type":"Point"}
}