{
  "type": "Feature",
  "properties": {
    "iso:country":"BE",
    "sg:address":"De Keyserlei 58b24",
    "sg:city":"Antwerpen",
    "sg:orig_category":"D\u00e9chets and d\u00e9bris Gr",
    "sg:phone":"+32 3 231 82 83",
    "sg:postcode":"2018",
    "sg:province":"Antwerpen",
    "wof:name":"C.m.r. International",
    "wof:placetype":"venue"
},
  "geometry": {"coordinates":[4.4192619324,51.2173309326],"type":"Point"}
}