{
  "type": "Feature",
  "properties": {
    "iso:country":"BE",
    "sg:address":"Gelindenstraat 121",
    "sg:city":"Heers",
    "sg:orig_category":"Plaatsen van vloer- and muurbekleding Woningbouw",
    "sg:phone":"+32 11 48 21 89",
    "sg:postcode":"3870",
    "sg:province":"Limburg",
    "wof:name":"Patrick Bex",
    "wof:placetype":"venue"
},
  "geometry": {"coordinates":[5.2554440498,50.7408256531],"type":"Point"}
}