{
  "type": "Feature",
  "properties": {
    "iso:country":"BE",
    "sg:address":"Diestsestraat 43",
    "sg:city":"Leuven",
    "sg:orig_category":"Huishoudapparaten, televisies and radio's",
    "sg:phone":"+32 16 22 43 54",
    "sg:postcode":"3000",
    "sg:province":"Vlaams-Brabant",
    "wof:name":"Grietens Elektro",
    "wof:placetype":"venue"
},
  "geometry": {"coordinates":[4.7037148476,50.880115509],"type":"Point"}
}