{
  "type": "Feature",
  "properties": {
    "addr:full":"Aarschotsesteenweg 157 Begijnendijk Vlaams-Brabant 3130",
    "addr:housenumber":"157",
    "addr:postcode":"3130",
    "addr:street":"Aarschotsesteenweg",
    "iso:country":"BE",
    "sg:address":"Aarschotsesteenweg 157",
    "sg:city":"Begijnendijk",
    "sg:classifiers":[
        {
            "category":"Personal",
            "subcategory":"Beauty Salon",
            "type":"Services"
        }
    ],
    "sg:phone":"+32 16 56 70 04",
    "sg:postcode":"3130",
    "sg:province":"Vlaams-Brabant",
    "sg:tags":[
        "de",
        "coiffure"
    ],
    "wof:name":"Victor Wouters",
    "wof:placetype":"venue"
},
  "geometry": {"coordinates":[4.7996068001,50.9901809692],"type":"Point"}
}