{
  "type": "Feature",
  "properties": {
    "addr:full":"Peperstraat 10 Gent Oost-Vlaanderen 9000",
    "addr:housenumber":"10",
    "addr:postcode":"9000",
    "addr:street":"Peperstraat;Oost-Vlaanderen",
    "iso:country":"BE",
    "sg:address":"Peperstraat 10",
    "sg:city":"Gent",
    "sg:classifiers":[
        {
            "category":"Shopping",
            "subcategory":"Optician",
            "type":"Retail Goods"
        }
    ],
    "sg:phone":"+32 9 224 79 43",
    "sg:postcode":"9000",
    "sg:province":"Oost-Vlaanderen",
    "sg:tags":[
        "-"
    ],
    "wof:name":"Bonte J-p",
    "wof:placetype":"venue"
},
  "geometry": {"coordinates":[3.7143540382,51.0549926758],"type":"Point"}
}