{
  "type": "Feature",
  "properties": {
    "addr:full":"Ledebaan 80 Aalst Oost-Vlaanderen 9300",
    "addr:housenumber":"80",
    "addr:postcode":"9300",
    "addr:street":"Ledebaan",
    "iso:country":"BE",
    "sg:address":"Ledebaan 80",
    "sg:city":"Aalst",
    "sg:orig_category":"Kapsalons",
    "sg:phone":"+32 53 78 69 07",
    "sg:postcode":"9300",
    "sg:province":"Oost-Vlaanderen",
    "wof:name":"Coiffure Creatief",
    "wof:placetype":"venue"
},
  "geometry": {"coordinates":[4.0272388458,50.9453353882],"type":"Point"}
}