{
  "type": "Feature",
  "properties": {
    "addr:full":"Le Grand Mont 0 Aywaille Li\u00e8ge 4920",
    "addr:housenumber":"0",
    "addr:postcode":"4920",
    "addr:street":"Mont",
    "iso:country":"BE",
    "sg:address":"Le Grand Mont 0",
    "sg:city":"Aywaille",
    "sg:orig_category":"Enseignement maternel and primaire",
    "sg:phone":"+32 4 384 58 64",
    "sg:postcode":"4920",
    "sg:province":"Li\u00e8ge",
    "wof:name":"Ecole Fond. Communale",
    "wof:placetype":"venue"
},
  "geometry": {"coordinates":[5.6782069206,50.4738540649],"type":"Point"}
}