{
  "type": "Feature",
  "properties": {
    "addr:full":"Noerether Strasse 53 Eupen Li\u00e8ge 4700",
    "addr:housenumber":"53",
    "addr:postcode":"4700",
    "addr:street":"Noerether Strasse",
    "iso:country":"BE",
    "sg:address":"Noerether Strasse 53",
    "sg:city":"Eupen",
    "sg:classifiers":[
        {
            "category":"Utilities",
            "subcategory":"Recycling",
            "type":"Services"
        }
    ],
    "sg:phone":"+32 87 55 48 78",
    "sg:postcode":"4700",
    "sg:province":"Li\u00e8ge",
    "wof:name":"C.f.e.r. Asbl",
    "wof:placetype":"venue"
},
  "geometry": {"coordinates":[6.0287690163,50.637260437],"type":"Point"}
}