{
  "type": "Feature",
  "properties": {
    "addr:full":"Square Des Canadiens 4 Virton Luxembourg 6762",
    "addr:housenumber":"4",
    "addr:postcode":"6762",
    "addr:street":"Square Des Canadiens",
    "iso:country":"BE",
    "sg:address":"Square Des Canadiens 4",
    "sg:city":"Virton",
    "sg:orig_category":"Paramedische behandelingen",
    "sg:phone":"+32 63 57 19 03",
    "sg:postcode":"6762",
    "sg:province":"Luxembourg",
    "wof:name":"B. Lacave",
    "wof:placetype":"venue"
},
  "geometry": {"coordinates":[5.5332231522,49.5546951294],"type":"Point"}
}