{
  "type": "Feature",
  "properties": {
    "addr:full":"Noordstraat 163ba Maldegem Oost-Vlaanderen 9990",
    "addr:housenumber":"163ba",
    "addr:postcode":"9990",
    "addr:street":"Noordstraat",
    "iso:country":"BE",
    "sg:address":"Noordstraat 163ba",
    "sg:city":"Maldegem",
    "sg:orig_category":"Entretien and r\u00e9parations de voitures. V\u00e9hicules automobiles",
    "sg:phone":"+32 50 71 23 36",
    "sg:postcode":"9990",
    "sg:province":"Oost-Vlaanderen",
    "wof:name":"Garage De Jaeger",
    "wof:placetype":"venue"
},
  "geometry": {"coordinates":[3.4471759796,51.2149658203],"type":"Point"}
}