{
  "type": "Feature",
  "properties": {
    "addr:full":"Aisne 1 Durbuy Luxembourg 6941",
    "addr:housenumber":"1",
    "addr:postcode":"6941",
    "addr:street":"Aisne",
    "iso:country":"BE",
    "sg:address":"Aisne 1",
    "sg:city":"Durbuy",
    "sg:classifiers":[
        {
            "category":"Building & Trades",
            "subcategory":"Construction",
            "type":"Services"
        }
    ],
    "sg:phone":"+32 86 49 94 12",
    "sg:postcode":"6941",
    "sg:province":"Luxembourg",
    "sg:tags":[
        "en",
        "la",
        "el\u00e9ments",
        "pour",
        "fab",
        "b\u00e9ton"
    ],
    "wof:name":"Blocs B\u00c9ton Michel",
    "wof:placetype":"venue"
},
  "geometry": {"coordinates":[5.524184227,50.3770332336],"type":"Point"}
}