{
  "type": "Feature",
  "properties": {
    "iso:country":"BE",
    "sg:address":"Rue Du Centre 12",
    "sg:city":"Namur",
    "sg:orig_category":"Traitements param\u00e9dicaux",
    "sg:phone":"+32 81 43 45 34",
    "sg:postcode":"5003",
    "sg:province":"Namur",
    "wof:name":"Hardy",
    "wof:placetype":"venue"
},
  "geometry": {"coordinates":[4.8473348618,50.4915008545],"type":"Point"}
}