{
  "type": "Feature",
  "properties": {
    "iso:country":"BE",
    "sg:address":"Zichemseweg 93",
    "sg:city":"Diest",
    "sg:orig_category":"Peinture. Rev\u00eatements pour sols and murs",
    "sg:phone":"+32 13 33 76 81",
    "sg:postcode":"3293",
    "sg:province":"Vlaams-Brabant",
    "wof:name":"Huguette Crets",
    "wof:placetype":"venue"
},
  "geometry": {"coordinates":[5.0282001495,50.9850883484],"type":"Point"}
}