{
  "type": "Feature",
  "properties": {
    "addr:full":"Sterrenlaan 3 Schilde (groot) Antwerpen 2970",
    "addr:housenumber":"3",
    "addr:postcode":"2970",
    "addr:street":"Sterrenlaan;Groot Antwerpen",
    "iso:country":"BE",
    "sg:address":"Sterrenlaan 3",
    "sg:city":"Schilde (groot)",
    "sg:orig_category":"Diverse bedrijfsbeheeradviesbureaus",
    "sg:phone":"+32 16 46 39 74",
    "sg:postcode":"2970",
    "sg:province":"Antwerpen",
    "wof:name":"Cuyvers Greet",
    "wof:placetype":"venue"
},
  "geometry": {"coordinates":[4.5798120499,51.2392082214],"type":"Point"}
}