{
  "type": "Feature",
  "properties": {
    "iso:country":"BE",
    "sg:address":"Weverstraat 9",
    "sg:city":"Meulebeke",
    "sg:orig_category":"Domotics",
    "sg:phone":"+32 51 48 76 99",
    "sg:postcode":"8760",
    "sg:province":"West-Vlaanderen",
    "wof:name":"D'halluin G",
    "wof:placetype":"venue"
},
  "geometry": {"coordinates":[3.2952771187,50.9570274353],"type":"Point"}
}