{
  "type": "Feature",
  "properties": {
    "addr:full":"J. Van De Puttelaan 48 Blankenberge West-Vlaanderen 8370",
    "addr:housenumber":"48",
    "addr:postcode":"8370",
    "addr:street":"J. Van De Puttelaan",
    "iso:country":"BE",
    "sg:address":"J. Van De Puttelaan 48",
    "sg:city":"Blankenberge",
    "sg:classifiers":[
        {
            "category":"Professional",
            "subcategory":"Accounting & Tax Preparation",
            "type":"Services"
        }
    ],
    "sg:phone":"+32 50 41 26 24",
    "sg:postcode":"8370",
    "sg:province":"West-Vlaanderen",
    "sg:tags":[
        "accountant"
    ],
    "wof:name":"Deduytsche Bvba",
    "wof:placetype":"venue"
},
  "geometry": {"coordinates":[3.1383259296,51.3106575012],"type":"Point"}
}