{
  "type": "Feature",
  "properties": {
    "addr:full":"Sportstraat 19 Lovendegem Oost-Vlaanderen 9920",
    "addr:housenumber":"19",
    "addr:postcode":"9920",
    "addr:street":"Sportstraat",
    "iso:country":"BE",
    "sg:address":"Sportstraat 19",
    "sg:city":"Lovendegem",
    "sg:orig_category":"Avocats and conseillers juridiques",
    "sg:phone":"+32 9 372 79 13",
    "sg:postcode":"9920",
    "sg:province":"Oost-Vlaanderen",
    "wof:name":"Van Vynckt Anne-marie",
    "wof:placetype":"venue"
},
  "geometry": {"coordinates":[3.608891964,51.0995521545],"type":"Point"}
}