{
  "type": "Feature",
  "properties": {
    "addr:full":"Destelbergenstraat 86 Gent (sint-amandsberg) Oost-Vlaanderen 9040",
    "addr:housenumber":"86",
    "addr:postcode":"9040",
    "addr:street":"Destelbergenstraat",
    "iso:country":"BE",
    "sg:address":"Destelbergenstraat 86",
    "sg:city":"Gent (sint-amandsberg)",
    "sg:classifiers":[
        {
            "category":"Wholesale",
            "subcategory":"Beer",
            "type":"Manufacturing & Wholesale Goods"
        }
    ],
    "sg:phone":"+32 9 228 14 49",
    "sg:postcode":"9040",
    "sg:province":"Oost-Vlaanderen",
    "sg:tags":[
        "ale",
        "-"
    ],
    "wof:name":"Martens-algem. Drankbedrijf",
    "wof:placetype":"venue"
},
  "geometry": {"coordinates":[3.756622076,51.050655365],"type":"Point"}
}