{
  "type": "Feature",
  "properties": {
    "addr:full":"Avenue Arnold Delvaux 20 Ukkel/uccle Bruxelles-Capitale 1180",
    "addr:housenumber":"20",
    "addr:postcode":"1180",
    "addr:street":"Avenue Arnold Delvaux;/",
    "iso:country":"BE",
    "sg:address":"Avenue Arnold Delvaux 20",
    "sg:city":"Ukkel/uccle",
    "sg:orig_category":"Architectes",
    "sg:phone":"+32 2 374 54 17",
    "sg:postcode":"1180",
    "sg:province":"Bruxelles-Capitale",
    "wof:name":"Jean Claes",
    "wof:placetype":"venue"
},
  "geometry": {"coordinates":[4.3403859138,50.8001022339],"type":"Point"}
}