{
  "type": "Feature",
  "properties": {
    "addr:full":"Middelburgstraat 68 Watermaal-bosvoorde/watermael-boitsfort Bruxelles-Capitale 1170",
    "addr:housenumber":"68",
    "addr:postcode":"1170",
    "addr:street":"Middelburgstraat",
    "iso:country":"BE",
    "sg:address":"Middelburgstraat 68",
    "sg:city":"Watermaal-bosvoorde/watermael-boitsfort",
    "sg:orig_category":"Instellingen voor mindervalide volwassenen",
    "sg:phone":"+32 2 660 11 52",
    "sg:postcode":"1170",
    "sg:province":"Bruxelles-Capitale",
    "wof:name":"I.m.p. La Passerelle",
    "wof:placetype":"venue"
},
  "geometry": {"coordinates":[4.4180960655,50.7955780029],"type":"Point"}
}