{
  "type": "Feature",
  "properties": {
    "addr:full":"Gyzevennestraat 36 Lummen Limburg 3560",
    "addr:housenumber":"36",
    "addr:postcode":"3560",
    "addr:street":"Gyzevennestraat",
    "iso:country":"BE",
    "sg:address":"Gyzevennestraat 36",
    "sg:city":"Lummen",
    "sg:orig_category":"Architecten",
    "sg:phone":"+32 13 32 80 35",
    "sg:postcode":"3560",
    "sg:province":"Limburg",
    "wof:name":"Geert Houtmeyers",
    "wof:placetype":"venue"
},
  "geometry": {"coordinates":[5.1928048134,50.9866790771],"type":"Point"}
}