{
  "type": "Feature",
  "properties": {
    "addr:full":"Rue Du Monument 5c Couvin (frasnes) Namur 5660",
    "addr:housenumber":"5c",
    "addr:postcode":"5660",
    "addr:street":"Rue Du Monument",
    "iso:country":"BE",
    "sg:address":"Rue Du Monument 5c",
    "sg:city":"Couvin (frasnes)",
    "sg:classifiers":[
        {
            "category":"Home & Garden",
            "subcategory":"Carpets & Floor Coverings",
            "type":"Retail Goods"
        }
    ],
    "sg:phone":"+32 476 52 01 02",
    "sg:postcode":"5660",
    "sg:province":"Namur",
    "sg:tags":[
        "house",
        "prefabricated"
    ],
    "wof:name":"Cr\u00e9abois",
    "wof:placetype":"venue"
},
  "geometry": {"coordinates":[4.5094060898,50.0757026672],"type":"Point"}
}