{
  "type": "Feature",
  "properties": {
    "iso:country":"BE",
    "sg:address":"Rue De La Biff 123",
    "sg:city":"Arlon",
    "sg:classifiers":[
        {
            "category":"Personal",
            "subcategory":"Beauty Salon",
            "type":"Services"
        }
    ],
    "sg:phone":"+32 63 23 63 92",
    "sg:postcode":"6706",
    "sg:province":"Luxembourg",
    "sg:tags":[
        "de",
        "coiffure"
    ],
    "wof:name":"Coiffure Imagina'tif",
    "wof:placetype":"venue"
},
  "geometry": {"coordinates":[5.8697757721,49.6491928101],"type":"Point"}
}