{
  "type": "Feature",
  "properties": {
    "iso:country":"BE",
    "sg:address":"Aalststraat 59",
    "sg:city":"Oudenaarde",
    "sg:orig_category":"Kapsalons",
    "sg:phone":"+32 55 31 47 58",
    "sg:postcode":"9700",
    "sg:province":"Oost-Vlaanderen",
    "wof:name":"Coiffure Marie-th\u00c9r\u00c8se",
    "wof:placetype":"venue"
},
  "geometry": {"coordinates":[3.6139149666,50.838344574],"type":"Point"}
}