{
  "type": "Feature",
  "properties": {
    "addr:full":"6 Rue Joseph Joirkin 4357 Donceel 6",
    "addr:housenumber":"6",
    "addr:postcode":"4357",
    "addr:street":"Rue Joseph Joirkin",
    "iso:country":"BE",
    "sg:address":"6",
    "sg:city":"Rue Joseph Joirkin 4357 Donceel",
    "sg:classifiers":[
        {
            "category":"Travel",
            "subcategory":"Hotels & Motels",
            "type":"Entertainment"
        }
    ],
    "sg:phone":"+32 19 54 43 88",
    "sg:postcode":"6",
    "sg:tags":[
        "hotels",
        "business",
        "restaurant"
    ],
    "wof:name":"Damario Egidio Felice M.",
    "wof:placetype":"venue"
},
  "geometry": {"coordinates":[5.3190698624,50.6561355591],"type":"Point"}
}