{
  "type": "Feature",
  "properties": {
    "addr:full":"90 Rue Ernest Solvay 4040 Herstal 90",
    "addr:housenumber":"90;90",
    "addr:postcode":"4040",
    "addr:street":"Rue Ernest Solvay",
    "iso:country":"BE",
    "sg:address":"90",
    "sg:city":"Rue Ernest Solvay 4040 Herstal",
    "sg:classifiers":[
        {
            "category":"Travel",
            "subcategory":"Hotels & Motels",
            "type":"Entertainment"
        }
    ],
    "sg:phone":"+32 4 264 89 42",
    "sg:postcode":"90",
    "sg:tags":[
        "hotels",
        "business",
        "restaurant"
    ],
    "wof:name":"Herco Sprl",
    "wof:placetype":"venue"
},
  "geometry": {"coordinates":[5.6158638,50.654914856],"type":"Point"}
}