{
  "type": "Feature",
  "properties": {
    "iso:country":"BE",
    "sg:address":"Rue Blanche 25",
    "sg:city":"Bruxelles (ixelles)",
    "sg:classifiers":[
        {
            "category":"Professional",
            "subcategory":"Lawyer & Legal Services",
            "type":"Services"
        }
    ],
    "sg:phone":"+32 2 541 05 70",
    "sg:postcode":"1050",
    "sg:province":"Bruxelles-Capitale",
    "wof:name":"Montfort J-p",
    "wof:placetype":"venue"
},
  "geometry": {"coordinates":[4.3578090668,50.8301506042],"type":"Point"}
}