{
  "type": "Feature",
  "properties": {
    "iso:country":"BE",
    "sg:address":"Wachtebekesteenweg 45",
    "sg:city":"Moerbeke (moerbeke-waas)",
    "sg:classifiers":[
        {
            "category":"Wholesale",
            "subcategory":"Plants",
            "type":"Manufacturing & Wholesale Goods"
        }
    ],
    "sg:phone":"+32 9 346 86 85",
    "sg:postcode":"9180",
    "sg:province":"Oost-Vlaanderen",
    "sg:tags":[
        "whol",
        "flower",
        "-",
        "grower"
    ],
    "wof:name":"Verwulgen A",
    "wof:placetype":"venue"
},
  "geometry": {"coordinates":[3.9075620174,51.1722297668],"type":"Point"}
}