{
  "type": "Feature",
  "properties": {
    "addr:full":"Sint-martinusplein 4c Box 4 Hasselt Limburg 3500",
    "addr:housenumber":"4c box 4",
    "addr:postcode":"3500",
    "addr:street":"Sint-Martinusplein",
    "iso:country":"BE",
    "sg:address":"Sint-martinusplein 4c Box 4",
    "sg:city":"Hasselt",
    "sg:classifiers":[
        {
            "category":"Home & Garden",
            "subcategory":"Kitchen Supply",
            "type":"Retail Goods"
        }
    ],
    "sg:phone":"+32 11 27 41 46",
    "sg:postcode":"3500",
    "sg:province":"Limburg",
    "sg:tags":[
        "installation"
    ],
    "wof:name":"Slegers Paul Bvba",
    "wof:placetype":"venue"
},
  "geometry": {"coordinates":[5.3432312012,50.9172897339],"type":"Point"}
}