{
  "type": "Feature",
  "properties": {
    "iso:country":"BE",
    "sg:address":"Rue Vieille-montagne 22",
    "sg:city":"Li\u00c8ge",
    "sg:orig_category":"Enseignement maternel and primaire. Enseignement secondaire g\u00e9n\u00e9ral",
    "sg:phone":"+32 4 227 81 74",
    "sg:postcode":"4000",
    "sg:province":"Li\u00e8ge",
    "wof:name":"Centre Aide Educative",
    "wof:placetype":"venue"
},
  "geometry": {"coordinates":[5.5930099487,50.6500511169],"type":"Point"}
}