{
  "type": "Feature",
  "properties": {
    "addr:full":"Lauwbergstraat 97 Menen (lauwe) West-Vlaanderen 8930",
    "addr:housenumber":"97",
    "addr:postcode":"8930",
    "addr:street":"Lauwbergstraat",
    "iso:country":"BE",
    "sg:address":"Lauwbergstraat 97",
    "sg:city":"Menen (lauwe)",
    "sg:classifiers":[
        {
            "category":"Building & Trades",
            "subcategory":"Electrical",
            "type":"Services"
        }
    ],
    "sg:phone":"+32 56 41 61 13",
    "sg:postcode":"8930",
    "sg:province":"West-Vlaanderen",
    "sg:tags":[
        "electric",
        "-",
        "housewiring",
        "contractor"
    ],
    "wof:name":"Demeester B",
    "wof:placetype":"venue"
},
  "geometry": {"coordinates":[3.1209149361,50.7961845398],"type":"Point"}
}