{
  "type": "Feature",
  "properties": {
    "addr:full":"Graaf D'ursellaan 5b6 Knokke-heist West-Vlaanderen 8301",
    "addr:housenumber":"5b6",
    "addr:postcode":"8301",
    "addr:street":"Graaf D'Ursellaan",
    "iso:country":"BE",
    "sg:address":"Graaf D'ursellaan 5b6",
    "sg:city":"Knokke-heist",
    "sg:orig_category":"Artistes ind\u00e9pendants",
    "sg:phone":"+32 50 51 78 29",
    "sg:postcode":"8301",
    "sg:province":"West-Vlaanderen",
    "wof:name":"Carlos D'aubioul",
    "wof:placetype":"venue"
},
  "geometry": {"coordinates":[3.2445259094,51.3404655457],"type":"Point"}
}