{
  "type": "Feature",
  "properties": {
    "addr:full":"Rue Royale 241 Bruxelles (saint-josse-ten-noode) Bruxelles-Capitale 1210",
    "addr:housenumber":"241",
    "addr:postcode":"1210",
    "addr:street":"Rue Royale",
    "iso:country":"BE",
    "sg:address":"Rue Royale 241",
    "sg:city":"Bruxelles (saint-josse-ten-noode)",
    "sg:classifiers":[
        {
            "category":"Organizations",
            "subcategory":"Professional Association",
            "type":"Services"
        }
    ],
    "sg:phone":"+32 2 218 14 55",
    "sg:postcode":"1210",
    "sg:province":"Bruxelles-Capitale",
    "sg:tags":[
        "trade-union",
        "federation"
    ],
    "wof:name":"F.c.b.",
    "wof:placetype":"venue"
},
  "geometry": {"coordinates":[4.3679008484,50.8570213318],"type":"Point"}
}