{
  "type": "Feature",
  "properties": {
    "iso:country":"BE",
    "sg:address":"Chauss\u00c9e De Tirlemont 96",
    "sg:city":"Wanze",
    "sg:orig_category":"Pain, p\u00e2tisseries and confiseries",
    "sg:phone":"+32 85 25 19 33",
    "sg:postcode":"4520",
    "sg:province":"Li\u00e8ge",
    "wof:name":"Nancy Thonet",
    "wof:placetype":"venue"
},
  "geometry": {"coordinates":[5.220744133,50.5384483337],"type":"Point"}
}