{
  "type": "Feature",
  "properties": {
    "addr:full":"Andries Pevernagestraat 117 Harelbeke West-Vlaanderen 8530",
    "addr:housenumber":"117",
    "addr:postcode":"8530",
    "addr:street":"Andries Pevernagestraat",
    "iso:country":"BE",
    "sg:address":"Andries Pevernagestraat 117",
    "sg:city":"Harelbeke",
    "sg:classifiers":[
        {
            "category":"Manufacturing",
            "subcategory":"Textiles",
            "type":"Manufacturing & Wholesale Goods"
        }
    ],
    "sg:phone":"+32 56 70 12 45",
    "sg:postcode":"8530",
    "sg:province":"West-Vlaanderen",
    "wof:name":"Breishop Chris",
    "wof:placetype":"venue"
},
  "geometry": {"coordinates":[3.3088641167,50.8512878418],"type":"Point"}
}