{
  "type": "Feature",
  "properties": {
    "iso:country":"BE",
    "sg:address":"Chauss\u00c9e De Bruxelles 184",
    "sg:city":"Charleroi",
    "sg:orig_category":"Benzinestations and brandstoffen",
    "sg:phone":"+32 71 33 03 13",
    "sg:postcode":"6020",
    "sg:province":"Hainaut",
    "wof:name":"Phoenix Trading Company",
    "wof:placetype":"venue"
},
  "geometry": {"coordinates":[4.4399790764,50.4197654724],"type":"Point"}
}