{
  "type": "Feature",
  "properties": {
    "iso:country":"BE",
    "sg:address":"Rue Du Nouveau Monde 8",
    "sg:city":"Mouscron",
    "sg:classifiers":[
        {
            "category":"Professional",
            "subcategory":"Art Services",
            "type":"Services"
        }
    ],
    "sg:phone":"+32 56 33 11 18",
    "sg:postcode":"7700",
    "sg:province":"Hainaut",
    "sg:tags":[
        "sculptor"
    ],
    "wof:name":"Buyse F",
    "wof:placetype":"venue"
},
  "geometry": {"coordinates":[3.2066099644,50.7442855835],"type":"Point"}
}