{
  "type": "Feature",
  "properties": {
    "iso:country":"BE",
    "sg:address":"Boulevard De L'europe 145",
    "sg:city":"Wavre",
    "sg:orig_category":"Autoverhuur",
    "sg:phone":"+32 10 42 08 10",
    "sg:postcode":"1301",
    "sg:province":"Brabant Wallon",
    "wof:name":"Keddy",
    "wof:placetype":"venue"
},
  "geometry": {"coordinates":[4.5849971771,50.6995773315],"type":"Point"}
}