{
  "type": "Feature",
  "properties": {
    "iso:country":"BE",
    "sg:address":"Hasseltsesteenweg 68",
    "sg:city":"Sint-truiden",
    "sg:classifiers":[
        {
            "category":"Bakery",
            "type":"Food & Drink"
        }
    ],
    "sg:phone":"+32 11 69 66 01",
    "sg:postcode":"3800",
    "sg:province":"Limburg",
    "sg:tags":[
        "confectioner",
        "baker"
    ],
    "wof:name":"De Broodgalerij",
    "wof:placetype":"venue"
},
  "geometry": {"coordinates":[5.1992049217,50.8269348145],"type":"Point"}
}