{
  "type": "Feature",
  "properties": {
    "iso:country":"BE",
    "sg:address":"Riddersstraat 14b7",
    "sg:city":"Elsene/ixelles",
    "sg:orig_category":"Boekhouders",
    "sg:phone":"+32 2 513 61 83",
    "sg:postcode":"1050",
    "sg:province":"Bruxelles-Capitale",
    "wof:name":"Edmond Bogaert",
    "wof:placetype":"venue"
},
  "geometry": {"coordinates":[4.3595309258,50.836555481],"type":"Point"}
}