{
  "type": "Feature",
  "properties": {
    "addr:full":"Alsembergse Steenweg 726 Ukkel/uccle Bruxelles-Capitale 1180",
    "addr:housenumber":"726",
    "addr:postcode":"1180",
    "addr:street":"Alsembergse Steenweg;/",
    "iso:country":"BE",
    "sg:address":"Alsembergse Steenweg 726",
    "sg:city":"Ukkel/uccle",
    "sg:orig_category":"Textiel",
    "sg:phone":"+32 2 345 23 80",
    "sg:postcode":"1180",
    "sg:province":"Bruxelles-Capitale",
    "wof:name":"La Maison Hayoit",
    "wof:placetype":"venue"
},
  "geometry": {"coordinates":[4.3368458748,50.8017578125],"type":"Point"}
}