{
  "type": "Feature",
  "properties": {
    "addr:full":"Opheersstraat 82 Heers Limburg 3870",
    "addr:housenumber":"82",
    "addr:postcode":"3870",
    "addr:street":"Opheersstraat",
    "iso:country":"BE",
    "sg:address":"Opheersstraat 82",
    "sg:city":"Heers",
    "sg:classifiers":[
        {
            "category":"Bakery",
            "type":"Food & Drink"
        }
    ],
    "sg:phone":"+32 11 48 58 52",
    "sg:postcode":"3870",
    "sg:province":"Limburg",
    "sg:tags":[
        "confectioner",
        "baker"
    ],
    "wof:name":"Van Hove V",
    "wof:placetype":"venue"
},
  "geometry": {"coordinates":[5.2985401154,50.7415885925],"type":"Point"}
}