{
  "type": "Feature",
  "properties": {
    "iso:country":"BE",
    "sg:address":"Rue Du Montys 22",
    "sg:city":"Tinlot",
    "sg:classifiers":[
        {
            "category":"Insurance",
            "subcategory":"Life Insurance",
            "type":"Services"
        }
    ],
    "sg:phone":"+32 85 51 21 48",
    "sg:postcode":"4557",
    "sg:province":"Li\u00e8ge",
    "sg:tags":[
        "assurance"
    ],
    "wof:name":"Bureau Thomas-fabry",
    "wof:placetype":"venue"
},
  "geometry": {"coordinates":[5.3753452301,50.47864151],"type":"Point"}
}