{
  "type": "Feature",
  "properties": {
    "iso:country":"BE",
    "sg:address":"Pintestraat 85",
    "sg:city":"De Pinte",
    "sg:orig_category":"Boucheries",
    "sg:phone":"+32 9 282 52 08",
    "sg:postcode":"9840",
    "sg:province":"Oost-Vlaanderen",
    "wof:name":"Beenhouwerij Andr\u00c9",
    "wof:placetype":"venue"
},
  "geometry": {"coordinates":[3.6437830925,50.9889564514],"type":"Point"}
}