{
  "type": "Feature",
  "properties": {
    "addr:full":"Bronstraat 7 Edingen/enghien Hainaut 7850",
    "addr:housenumber":"7",
    "addr:postcode":"7850",
    "addr:street":"Bronstraat",
    "iso:country":"BE",
    "sg:address":"Bronstraat 7",
    "sg:city":"Edingen/enghien",
    "sg:orig_category":"Artsen and specialisten",
    "sg:phone":"+32 2 395 38 58",
    "sg:postcode":"7850",
    "sg:province":"Hainaut",
    "wof:name":"Bernard Gregoire",
    "wof:placetype":"venue"
},
  "geometry": {"coordinates":[4.0334601402,50.6914787292],"type":"Point"}
}