{
  "type": "Feature",
  "properties": {
    "iso:country":"BE",
    "sg:address":"Sint-katharinastraat 13bb",
    "sg:city":"Puurs",
    "sg:orig_category":"Voertuigen",
    "sg:phone":"+32 3 866 11 81",
    "sg:postcode":"2870",
    "sg:province":"Antwerpen",
    "wof:name":"Car Store",
    "wof:placetype":"venue"
},
  "geometry": {"coordinates":[4.3261218071,51.0805206299],"type":"Point"}
}