{
  "type": "Feature",
  "properties": {
    "iso:country":"BE",
    "sg:address":"Clemenceaustraat 132",
    "sg:city":"Sint-katelijne-waver",
    "sg:orig_category":"Brood, gebak and snoepgoed",
    "sg:phone":"+32 15 21 81 23",
    "sg:postcode":"2860",
    "sg:province":"Antwerpen",
    "wof:name":"Bakkerij Van Itterbeeck",
    "wof:placetype":"venue"
},
  "geometry": {"coordinates":[4.488629818,51.0621414185],"type":"Point"}
}