{
  "type": "Feature",
  "properties": {
    "addr:full":"Brusselsesteenweg 505ba Overijse Vlaams-Brabant 3090",
    "addr:postcode":"3090",
    "addr:street":"Brusselsesteenweg 505Ba",
    "iso:country":"BE",
    "sg:address":"Brusselsesteenweg 505ba",
    "sg:city":"Overijse",
    "sg:orig_category":"Groenten and fruit Gh",
    "sg:phone":"+32 2 657 38 46",
    "sg:postcode":"3090",
    "sg:province":"Vlaams-Brabant",
    "wof:name":"Martin Thore",
    "wof:placetype":"venue"
},
  "geometry": {"coordinates":[4.5082998276,50.7829399109],"type":"Point"}
}