{
  "type": "Feature",
  "properties": {
    "addr:full":"Maria-christinastraat 167 Brussel/bruxelles Bruxelles-Capitale 1020",
    "addr:housenumber":"167",
    "addr:postcode":"1020",
    "addr:street":"Maria-Christinastraat;/",
    "iso:country":"BE",
    "sg:address":"Maria-christinastraat 167",
    "sg:city":"Brussel/bruxelles",
    "sg:orig_category":"Apotheken",
    "sg:phone":"+32 2 425 16 13",
    "sg:postcode":"1020",
    "sg:province":"Bruxelles-Capitale",
    "wof:name":"Laeken-pharma",
    "wof:placetype":"venue"
},
  "geometry": {"coordinates":[4.3509120941,50.8764762878],"type":"Point"}
}