{
  "type": "Feature",
  "properties": {
    "addr:full":"Place De Brus 5 Bassenge Li\u00e8ge 4690",
    "addr:housenumber":"5",
    "addr:postcode":"4690",
    "addr:street":"Place De Brus",
    "iso:country":"BE",
    "sg:address":"Place De Brus 5",
    "sg:city":"Bassenge",
    "sg:orig_category":"Maisons de repos and r\u00e9sidences",
    "sg:phone":"+32 4 286 19 72",
    "sg:postcode":"4690",
    "sg:province":"Li\u00e8ge",
    "wof:name":"Home La Violette",
    "wof:placetype":"venue"
},
  "geometry": {"coordinates":[5.5534558296,50.7476577759],"type":"Point"}
}