{
  "type": "Feature",
  "properties": {
    "addr:full":"Rue Des Coquer\u00c9es 25 Ottignies-louvain-la-neuve Brabant Wallon 1341",
    "addr:housenumber":"25",
    "addr:postcode":"1341",
    "addr:street":"Rue Des Coquere\u0301Es",
    "iso:country":"BE",
    "sg:address":"Rue Des Coquer\u00c9es 25",
    "sg:city":"Ottignies-louvain-la-neuve",
    "sg:classifiers":[
        {
            "category":"Insurance",
            "subcategory":"Life Insurance",
            "type":"Services"
        }
    ],
    "sg:phone":"+32 10 61 37 69",
    "sg:postcode":"1341",
    "sg:province":"Brabant Wallon",
    "sg:tags":[
        "assurance"
    ],
    "wof:name":"Speed Contacts",
    "wof:placetype":"venue"
},
  "geometry": {"coordinates":[4.5627598763,50.6583099365],"type":"Point"}
}