{
  "type": "Feature",
  "properties": {
    "addr:full":"Rue Cujenne 26 Beyne-heusay Li\u00e8ge 4610",
    "addr:housenumber":"26",
    "addr:postcode":"4610",
    "addr:street":"Rue Cujenne",
    "iso:country":"BE",
    "sg:address":"Rue Cujenne 26",
    "sg:city":"Beyne-heusay",
    "sg:orig_category":"Industri\u00eble and commerci\u00eble bouw",
    "sg:phone":"+32 4 362 67 49",
    "sg:postcode":"4610",
    "sg:province":"Li\u00e8ge",
    "wof:name":"Charles Counasse",
    "wof:placetype":"venue"
},
  "geometry": {"coordinates":[5.6630249023,50.6416931152],"type":"Point"}
}