{
  "type": "Feature",
  "properties": {
    "addr:full":"Blauberg 15 Herselt Antwerpen 2230",
    "addr:housenumber":"15",
    "addr:postcode":"2230",
    "addr:street":"Blauberg",
    "iso:country":"BE",
    "sg:address":"Blauberg 15",
    "sg:city":"Herselt",
    "sg:classifiers":[
        {
            "category":"Real Estate",
            "subcategory":"Architect",
            "type":"Services"
        }
    ],
    "sg:phone":"+32 14 54 92 01",
    "sg:postcode":"2230",
    "sg:province":"Antwerpen",
    "wof:name":"Vanneylen P",
    "wof:placetype":"venue"
},
  "geometry": {"coordinates":[4.8854632378,51.052772522],"type":"Point"}
}