{
  "type": "Feature",
  "properties": {
    "iso:country":"BE",
    "sg:address":"Camping 1",
    "sg:city":"Houyet",
    "sg:classifiers":[
        {
            "category":"Restaurant",
            "type":"Food & Drink"
        }
    ],
    "sg:phone":"+32 82 66 68 22",
    "sg:postcode":"5560",
    "sg:province":"Namur",
    "wof:name":"Le Charlemagne",
    "wof:placetype":"venue"
},
  "geometry": {"coordinates":[5.006485939,50.1904411316],"type":"Point"}
}