{
  "type": "Feature",
  "properties": {
    "addr:full":"Avenue Paul Pastur 214 Charleroi (mont-sur-marchienne) Hainaut 6032",
    "addr:housenumber":"214",
    "addr:postcode":"6032",
    "addr:street":"Avenue Paul Pastur",
    "iso:country":"BE",
    "sg:address":"Avenue Paul Pastur 214",
    "sg:city":"Charleroi (mont-sur-marchienne)",
    "sg:classifiers":[
        {
            "category":"Food & Beverages",
            "subcategory":"Fruits & Vegetables",
            "type":"Retail Goods"
        }
    ],
    "sg:phone":"+32 71 47 68 04",
    "sg:postcode":"6032",
    "sg:province":"Hainaut",
    "sg:tags":[
        "-"
    ],
    "wof:name":"Echoppe (l')",
    "wof:placetype":"venue"
},
  "geometry": {"coordinates":[4.4128670692,50.3933181763],"type":"Point"}
}