{
  "type": "Feature",
  "properties": {
    "iso:country":"BE",
    "sg:address":"Rue Du Cimeti\u00e8re 25",
    "sg:city":"Vis\u00e9 (lanaye)",
    "sg:classifiers":[
        {
            "category":"Bars & Pubs",
            "type":"Food & Drink"
        }
    ],
    "sg:phone":"+32 4 379 83 52",
    "sg:postcode":"4600",
    "sg:province":"Li\u00e8ge",
    "wof:name":"Chalet (le)",
    "wof:placetype":"venue"
},
  "geometry": {"coordinates":[5.6951928139,50.7815666199],"type":"Point"}
}