{
  "type": "Feature",
  "properties": {
    "addr:full":"Rue Walter Soeur 50 Ciney Namur 5590",
    "addr:housenumber":"50",
    "addr:postcode":"5590",
    "addr:street":"Rue Walter Soeur",
    "iso:country":"BE",
    "sg:address":"Rue Walter Soeur 50",
    "sg:city":"Ciney",
    "sg:orig_category":"Brandweer and civiele bescherming",
    "sg:phone":"+32 83 21 32 30",
    "sg:postcode":"5590",
    "sg:province":"Namur",
    "wof:name":"Corps De Pompiers",
    "wof:placetype":"venue"
},
  "geometry": {"coordinates":[5.0973930359,50.2973098755],"type":"Point"}
}