{
  "type": "Feature",
  "properties": {
    "iso:country":"BE",
    "sg:address":"Kerkstraat 15b1",
    "sg:city":"Neerpelt",
    "sg:orig_category":"Alimentation sp\u00e9cialis\u00e9e",
    "sg:phone":"+32 11 64 28 98",
    "sg:postcode":"3910",
    "sg:province":"Limburg",
    "wof:name":"Huis De Dommel",
    "wof:placetype":"venue"
},
  "geometry": {"coordinates":[5.4328331947,51.2285766602],"type":"Point"}
}