{
  "type": "Feature",
  "properties": {
    "addr:full":"Grand'rue 19 Mont-saint-guibert Brabant Wallon 1435",
    "addr:housenumber":"19",
    "addr:postcode":"1435",
    "addr:street":"Grand'Rue",
    "iso:country":"BE",
    "sg:address":"Grand'rue 19",
    "sg:city":"Mont-saint-guibert",
    "sg:orig_category":"Banken and kredietinstellingen",
    "sg:phone":"+32 10 65 53 09",
    "sg:postcode":"1435",
    "sg:province":"Brabant Wallon",
    "wof:name":"Fortis",
    "wof:placetype":"venue"
},
  "geometry": {"coordinates":[4.6107521057,50.6339874268],"type":"Point"}
}