{
  "type": "Feature",
  "properties": {
    "iso:country":"BE",
    "sg:address":"Avenue T\u00e9l\u00e9maque 61",
    "sg:city":"Bruxelles (forest)",
    "sg:classifiers":[
        {
            "category":"Health Services",
            "subcategory":"Doctor",
            "type":"Services"
        }
    ],
    "sg:phone":"+32 2 344 48 89",
    "sg:postcode":"1190",
    "sg:province":"Bruxelles-Capitale",
    "sg:tags":[
        "medicinephysicians",
        "surgeon"
    ],
    "wof:name":"Beyer I",
    "wof:placetype":"venue"
},
  "geometry": {"coordinates":[4.330974102,50.8116073608],"type":"Point"}
}