{
  "type": "Feature",
  "properties": {
    "iso:country":"BE",
    "sg:address":"Veldstraat 39",
    "sg:city":"Roeselare",
    "sg:classifiers":[
        {
            "category":"Professional",
            "subcategory":"Art Services",
            "type":"Services"
        }
    ],
    "sg:phone":"+32 56 22 55 33",
    "sg:postcode":"8800",
    "sg:province":"West-Vlaanderen",
    "sg:tags":[
        "exclusive",
        "special-design",
        "carpet"
    ],
    "wof:name":"Textile Design Team Lapere Nv",
    "wof:placetype":"venue"
},
  "geometry": {"coordinates":[3.1319749355,50.942325592],"type":"Point"}
}