{
  "type": "Feature",
  "properties": {
    "iso:country":"BE",
    "sg:address":"Wenigerstraat 59",
    "sg:city":"Borsbeek",
    "sg:orig_category":"Boucheries",
    "sg:phone":"+32 3 321 43 26",
    "sg:postcode":"2150",
    "sg:province":"Antwerpen",
    "wof:name":"Slagerij Eddy & Diane",
    "wof:placetype":"venue"
},
  "geometry": {"coordinates":[4.4771690369,51.1981544495],"type":"Point"}
}