{
  "type": "Feature",
  "properties": {
    "iso:country":"BE",
    "sg:address":"Stapelstraat 21",
    "sg:city":"Sint-truiden",
    "sg:classifiers":[
        {
            "category":"Shopping",
            "subcategory":"Crafts & Fabrics",
            "type":"Retail Goods"
        }
    ],
    "sg:phone":"+32 11 58 93 22",
    "sg:postcode":"3800",
    "sg:province":"Limburg",
    "sg:tags":[
        "hi-fi",
        "equipment",
        "stereophonic",
        "-"
    ],
    "wof:name":"T&d Hifi-sound & Light",
    "wof:placetype":"venue"
},
  "geometry": {"coordinates":[5.1830968857,50.8153495789],"type":"Point"}
}