{
  "type": "Feature",
  "properties": {
    "iso:country":"BE",
    "sg:address":"Kortrijksesteenweg 1063",
    "sg:city":"Gent",
    "sg:orig_category":"Airconditioning and ventilatie",
    "sg:phone":"+32 9 222 83 21",
    "sg:postcode":"9051",
    "sg:province":"Oost-Vlaanderen",
    "wof:name":"Eurotechniek Industrie",
    "wof:placetype":"venue"
},
  "geometry": {"coordinates":[3.6822268963,51.0197525024],"type":"Point"}
}