{
  "type": "Feature",
  "properties": {
    "iso:country":"BE",
    "sg:address":"Zuidkaai 18-20",
    "sg:city":"Izegem",
    "sg:classifiers":[
        {
            "category":"Government",
            "subcategory":"Department Of Motor Vehicles",
            "type":"Public Place"
        }
    ],
    "sg:phone":"+32 51 31 78 77",
    "sg:postcode":"8870",
    "sg:province":"West-Vlaanderen",
    "sg:tags":[
        "planing",
        "wood",
        "sawing"
    ],
    "wof:name":"Veroutiz Nv",
    "wof:placetype":"venue"
},
  "geometry": {"coordinates":[3.2135500908,50.9226989746],"type":"Point"}
}