{
  "type": "Feature",
  "properties": {
    "addr:full":"Smedenstraat 28 Brugge West-Vlaanderen 8000",
    "addr:housenumber":"28",
    "addr:postcode":"8000",
    "addr:street":"Smedenstraat",
    "iso:country":"BE",
    "sg:address":"Smedenstraat 28",
    "sg:city":"Brugge",
    "sg:orig_category":"Pain, p\u00e2tisseries and confiseries",
    "sg:phone":"+32 50 33 80 70",
    "sg:postcode":"8000",
    "sg:province":"West-Vlaanderen",
    "wof:name":"Bakkerij Laurent F.",
    "wof:placetype":"venue"
},
  "geometry": {"coordinates":[3.21529603,51.2056007385],"type":"Point"}
}