{
  "type": "Feature",
  "properties": {
    "iso:country":"BE",
    "sg:address":"Rue Des Remparts 8",
    "sg:city":"Walcourt",
    "sg:orig_category":"Traitements param\u00e9dicaux",
    "sg:phone":"+32 71 61 18 40",
    "sg:postcode":"5651",
    "sg:province":"Namur",
    "wof:name":"F. Cogno",
    "wof:placetype":"venue"
},
  "geometry": {"coordinates":[4.4262080193,50.2824401855],"type":"Point"}
}