{
  "type": "Feature",
  "properties": {
    "addr:full":"Nieuwstraat 14 Oostkamp (hertsberge) West-Vlaanderen 8020",
    "addr:housenumber":"14",
    "addr:postcode":"8020",
    "addr:street":"Nieuwstraat",
    "iso:country":"BE",
    "sg:address":"Nieuwstraat 14",
    "sg:city":"Oostkamp (hertsberge)",
    "sg:classifiers":[
        {
            "category":"Building & Trades",
            "subcategory":"Landscaping Services",
            "type":"Services"
        }
    ],
    "sg:phone":"+32 50 27 69 55",
    "sg:postcode":"8020",
    "sg:province":"West-Vlaanderen",
    "sg:tags":[
        "gardening",
        "garden",
        "maintenance"
    ],
    "wof:name":"De Kesel S",
    "wof:placetype":"venue"
},
  "geometry": {"coordinates":[3.2698850632,51.1039466858],"type":"Point"}
}