{
  "type": "Feature",
  "properties": {
    "iso:country":"BE",
    "sg:address":"Molenstraat 36",
    "sg:city":"Zonnebeke",
    "sg:classifiers":[
        {
            "category":"Insurance",
            "subcategory":"Insurance Agent",
            "type":"Services"
        }
    ],
    "sg:phone":"+32 51 77 91 02",
    "sg:postcode":"8980",
    "sg:province":"West-Vlaanderen",
    "sg:tags":[
        "verzekeringsmakelaars",
        "expert"
    ],
    "wof:name":"Zakenkantoor Van Acker",
    "wof:placetype":"venue"
},
  "geometry": {"coordinates":[3.0216450691,50.9022941589],"type":"Point"}
}