{
  "type": "Feature",
  "properties": {
    "iso:country":"BE",
    "sg:address":"Avenue Nouvelle 8",
    "sg:city":"Seneffe",
    "sg:orig_category":"Studios photographiques",
    "sg:phone":"+32 64 55 92 92",
    "sg:postcode":"7180",
    "sg:province":"Hainaut",
    "wof:name":"Alain Breyer",
    "wof:placetype":"venue"
},
  "geometry": {"coordinates":[4.2648367882,50.527923584],"type":"Point"}
}