{
  "type": "Feature",
  "properties": {
    "iso:country":"BE",
    "sg:address":"Atlantische Oceaanlaan 113",
    "sg:city":"Sint-pieters-woluwe/woluwe-saint-pierre",
    "sg:orig_category":"Beautyfarms, relaxatie and lichamelijk welzijn Schoonheidssalons",
    "sg:phone":"+32 2 763 21 31",
    "sg:postcode":"1150",
    "sg:province":"Bruxelles-Capitale",
    "wof:name":"Institut La Paillote",
    "wof:placetype":"venue"
},
  "geometry": {"coordinates":[4.4180397987,50.8281288147],"type":"Point"}
}