{
  "type": "Feature",
  "properties": {
    "iso:country":"BE",
    "sg:address":"Chauss\u00e9e Solvay 5",
    "sg:city":"Charleroi (montignies-sur-sambre)",
    "sg:classifiers":[
        {
            "category":"Professional",
            "subcategory":"Testing Lab",
            "type":"Services"
        }
    ],
    "sg:phone":"+32 71 31 21 29",
    "sg:postcode":"6061",
    "sg:province":"Hainaut",
    "sg:tags":[
        "chemist"
    ],
    "wof:name":"P\u00e9riquet A",
    "wof:placetype":"venue"
},
  "geometry": {"coordinates":[4.4815711975,50.3993186951],"type":"Point"}
}