{
  "type": "Feature",
  "properties": {
    "addr:full":"Rue Chapelle-beaussart 115bis Charleroi (mont-sur-marchienne) Hainaut 6032",
    "addr:housenumber":"115bis",
    "addr:postcode":"6032",
    "addr:street":"Rue Chapelle-Beaussart",
    "iso:country":"BE",
    "sg:address":"Rue Chapelle-beaussart 115bis",
    "sg:city":"Charleroi (mont-sur-marchienne)",
    "sg:classifiers":[
        {
            "category":"Banks & Credit Unions",
            "subcategory":"Investment Brokerage",
            "type":"Services"
        }
    ],
    "sg:phone":"+32 71 36 59 14",
    "sg:postcode":"6032",
    "sg:province":"Hainaut",
    "sg:tags":[
        "coil",
        "electric",
        "winding"
    ],
    "wof:name":"Lisman A",
    "wof:placetype":"venue"
},
  "geometry": {"coordinates":[4.4227929115,50.4011459351],"type":"Point"}
}