{
  "type": "Feature",
  "properties": {
    "iso:country":"BE",
    "sg:address":"Hombeeksesteenweg 105",
    "sg:city":"Mechelen",
    "sg:classifiers":[
        {
            "category":"Professional",
            "subcategory":"Testing Lab",
            "type":"Services"
        }
    ],
    "sg:phone":"+32 15 42 29 95",
    "sg:postcode":"2800",
    "sg:province":"Antwerpen",
    "sg:tags":[
        "chemist"
    ],
    "wof:name":"Buydens G",
    "wof:placetype":"venue"
},
  "geometry": {"coordinates":[4.4698858261,51.0188484192],"type":"Point"}
}