{
  "type": "Feature",
  "properties": {
    "iso:country":"BE",
    "sg:address":"Kerkstraat 235ba",
    "sg:city":"Grimbergen",
    "sg:orig_category":"Onderdelen and accessoires voor auto's",
    "sg:phone":"+32 2 270 20 82",
    "sg:postcode":"1851",
    "sg:province":"Vlaams-Brabant",
    "wof:name":"Huis Veralon",
    "wof:placetype":"venue"
},
  "geometry": {"coordinates":[4.3888058662,50.9770126343],"type":"Point"}
}