{
  "type": "Feature",
  "properties": {
    "iso:country":"BE",
    "sg:address":"Beverbekerdijk",
    "sg:city":"Hamont-achel (achel)",
    "sg:classifiers":[
        {
            "category":"Health Services",
            "subcategory":"Nursing And Care Facility",
            "type":"Services"
        }
    ],
    "sg:phone":"+32 11 80 00 34",
    "sg:postcode":"3930",
    "sg:province":"Limburg",
    "sg:tags":[
        "home",
        "rest"
    ],
    "wof:name":"Aan De Beverdijk",
    "wof:placetype":"venue"
},
  "geometry": {"coordinates":[5.4769802094,51.2764663696],"type":"Point"}
}