{
  "type": "Feature",
  "properties": {
    "iso:country":"BE",
    "sg:address":"Lange Steenstraat 45",
    "sg:city":"Kortrijk",
    "sg:classifiers":[
        {
            "category":"Utilities",
            "subcategory":"Mobile Phone",
            "type":"Services"
        }
    ],
    "sg:phone":"+32 56 31 56 37",
    "sg:postcode":"8500",
    "sg:province":"West-Vlaanderen",
    "sg:tags":[
        "access",
        "gsm",
        "-",
        "apparatus"
    ],
    "wof:name":"Belcompany",
    "wof:placetype":"venue"
},
  "geometry": {"coordinates":[3.2687189579,50.8270072937],"type":"Point"}
}