{
  "type": "Feature",
  "properties": {
    "addr:full":"Route De Lennik 27 Bruxelles (anderlecht) Bruxelles-Capitale 1070",
    "addr:housenumber":"27",
    "addr:postcode":"1070",
    "addr:street":"Route De Lennik",
    "iso:country":"BE",
    "sg:address":"Route De Lennik 27",
    "sg:city":"Bruxelles (anderlecht)",
    "sg:classifiers":[
        {
            "category":"Retail",
            "subcategory":"Auto Rental",
            "type":"Services"
        }
    ],
    "sg:postcode":"1070",
    "sg:province":"Bruxelles-Capitale",
    "sg:tags":[
        "engine",
        "diesel",
        "-"
    ],
    "wof:name":"Podevyn Nv/wybo P Etn",
    "wof:placetype":"venue"
},
  "geometry": {"coordinates":[4.2934260368,50.8221855164],"type":"Point"}
}