{
  "type": "Feature",
  "properties": {
    "iso:country":"BE",
    "sg:address":"Fl\u00c9ronlaan 3",
    "sg:city":"Vorst/forest",
    "sg:orig_category":"Kinderopvang Maatschappelijke dienstverlening",
    "sg:phone":"+32 2 376 52 00",
    "sg:postcode":"1190",
    "sg:province":"Bruxelles-Capitale",
    "wof:name":"Cr\u00c8che Bercail Forestois",
    "wof:placetype":"venue"
},
  "geometry": {"coordinates":[4.330696106,50.8280143738],"type":"Point"}
}