{
  "type": "Feature",
  "properties": {
    "iso:country":"BE",
    "sg:address":"Sint-elooisweg 24",
    "sg:city":"Ieper",
    "sg:orig_category":"Artsen and specialisten",
    "sg:phone":"+32 57 20 58 72",
    "sg:postcode":"8902",
    "sg:province":"West-Vlaanderen",
    "wof:name":"Philippe Deheegher",
    "wof:placetype":"venue"
},
  "geometry": {"coordinates":[2.8778579235,50.8166923523],"type":"Point"}
}