{
  "type": "Feature",
  "properties": {
    "iso:country":"BE",
    "sg:address":"Lumen 7",
    "sg:city":"Vloesberg/flobecq",
    "sg:orig_category":"M\u00e9decins and sp\u00e9cialistes",
    "sg:phone":"+32 68 44 75 56",
    "sg:postcode":"7880",
    "sg:province":"Hainaut",
    "wof:name":"Francine Risselin",
    "wof:placetype":"venue"
},
  "geometry": {"coordinates":[3.7266190052,50.7651062012],"type":"Point"}
}