{
  "type": "Feature",
  "properties": {
    "addr:full":"Dorp 31 Nazareth Oost-Vlaanderen 9810",
    "addr:housenumber":"31",
    "addr:postcode":"9810",
    "addr:street":"Dorp",
    "iso:country":"BE",
    "sg:address":"Dorp 31",
    "sg:city":"Nazareth",
    "sg:orig_category":"R\u00e9parations d'horloges, montres and bijoux. Bijouteries and horlogeries",
    "sg:phone":"+32 9 385 41 62",
    "sg:postcode":"9810",
    "sg:province":"Oost-Vlaanderen",
    "wof:name":"Le Roy",
    "wof:placetype":"venue"
},
  "geometry": {"coordinates":[3.5957911015,50.9588737488],"type":"Point"}
}