{
  "type": "Feature",
  "properties": {
    "addr:full":"Lambrechtshoekenlaan 10 Merksem Antwerpen 2170",
    "addr:housenumber":"10",
    "addr:postcode":"2170",
    "addr:street":"Lambrechtshoekenlaan",
    "iso:country":"BE",
    "sg:address":"Lambrechtshoekenlaan 10",
    "sg:city":"Merksem",
    "sg:orig_category":"Beveiligingsdiensten and bewakingsbedrijven",
    "sg:phone":"+32 3 231 40 00",
    "sg:postcode":"2170",
    "sg:province":"Antwerpen",
    "wof:name":"Diamond Security Company",
    "wof:placetype":"venue"
},
  "geometry": {"coordinates":[4.4295778275,51.2439842224],"type":"Point"}
}