{
  "type": "Feature",
  "properties": {
    "addr:full":"Kloosterstraat 77 Knesselare Oost-Vlaanderen 9910",
    "addr:housenumber":"77",
    "addr:postcode":"9910",
    "addr:street":"Kloosterstraat;Oost-Vlaanderen",
    "iso:country":"BE",
    "sg:address":"Kloosterstraat 77",
    "sg:city":"Knesselare",
    "sg:classifiers":[
        {
            "category":"Social Services",
            "type":"Services"
        }
    ],
    "sg:phone":"+32 9 375 14 15",
    "sg:postcode":"9910",
    "sg:province":"Oost-Vlaanderen",
    "wof:name":"Betani\u00eb-broeders Van Liefde",
    "wof:placetype":"venue"
},
  "geometry": {"coordinates":[3.4065830708,51.1428565979],"type":"Point"}
}