{
  "type": "Feature",
  "properties": {
    "iso:country":"BE",
    "sg:address":"Tolstraat 48",
    "sg:city":"Herzele (steenhuize-wijnhuize)",
    "sg:classifiers":[
        {
            "category":"Home & Garden",
            "subcategory":"Garden Supply",
            "type":"Retail Goods"
        }
    ],
    "sg:phone":"+32 54 50 34 19",
    "sg:postcode":"9550",
    "sg:province":"Oost-Vlaanderen",
    "wof:name":"Aveve Tuincentrum",
    "wof:placetype":"venue"
},
  "geometry": {"coordinates":[3.882527113,50.8377342224],"type":"Point"}
}