{
  "type": "Feature",
  "properties": {
    "iso:country":"BE",
    "sg:address":"Tentestuk 2",
    "sg:city":"Jabbeke",
    "sg:classifiers":[
        {
            "category":"Cafe",
            "type":"Food & Drink"
        }
    ],
    "sg:phone":"+32 50 81 40 10",
    "sg:postcode":"8490",
    "sg:province":"West-Vlaanderen",
    "sg:tags":[
        "caf\u00e9s"
    ],
    "wof:name":"Patrick Derieuw",
    "wof:placetype":"venue"
},
  "geometry": {"coordinates":[3.0605900288,51.159526825],"type":"Point"}
}