{
  "type": "Feature",
  "properties": {
    "addr:full":"Rue C\u00e9sar De Paepe 44-52 Charleroi (ransart) Hainaut 6043",
    "addr:housenumber":"44-52",
    "addr:postcode":"6043",
    "addr:street":"Rue Ce\u0301Sar De Paepe",
    "iso:country":"BE",
    "sg:address":"Rue C\u00e9sar De Paepe 44-52",
    "sg:city":"Charleroi (ransart)",
    "sg:classifiers":[
        {
            "category":"Banks & Credit Unions",
            "subcategory":"Bureau De Change",
            "type":"Services"
        }
    ],
    "sg:phone":"+32 71 25 80 20",
    "sg:postcode":"6043",
    "sg:province":"Hainaut",
    "sg:tags":[
        "measuring",
        "control",
        "apparatus"
    ],
    "wof:name":"Atelier Pochet Sa",
    "wof:placetype":"venue"
},
  "geometry": {"coordinates":[4.4132070541,50.4383773804],"type":"Point"}
}