{
  "type": "Feature",
  "properties": {
    "addr:full":"Rue Grande 21 Boussu Hainaut 7301",
    "addr:housenumber":"21",
    "addr:postcode":"7301",
    "addr:street":"Rue Grande",
    "iso:country":"BE",
    "sg:address":"Rue Grande 21",
    "sg:city":"Boussu",
    "sg:orig_category":"Opticiens",
    "sg:phone":"+32 65 77 83 29",
    "sg:postcode":"7301",
    "sg:province":"Hainaut",
    "wof:name":"Optique Gobert",
    "wof:placetype":"venue"
},
  "geometry": {"coordinates":[3.8257451057,50.4362258911],"type":"Point"}
}