{
  "type": "Feature",
  "properties": {
    "iso:country":"BE",
    "sg:address":"Kolveniersvest 32a",
    "sg:city":"Lier",
    "sg:orig_category":"Scenery Stage-, film-, and television",
    "sg:phone":"+32 3 488 14 59",
    "sg:postcode":"2500",
    "sg:province":"Antwerpen",
    "wof:name":"De Beeldhouwerij Bvba",
    "wof:placetype":"venue"
},
  "geometry": {"coordinates":[4.5667600632,51.1325874329],"type":"Point"}
}