{
  "type": "Feature",
  "properties": {
    "addr:full":"Industrieweg Noord 1163 Opglabbeek Limburg 3660",
    "addr:housenumber":"1163",
    "addr:postcode":"3660",
    "addr:street":"Industrieweg Noord",
    "iso:country":"BE",
    "sg:address":"Industrieweg Noord 1163",
    "sg:city":"Opglabbeek",
    "sg:orig_category":"Fa\u00e7ade covering",
    "sg:phone":"+32 89 81 03 00",
    "sg:postcode":"3660",
    "sg:province":"Limburg",
    "wof:name":"Gijmacon",
    "wof:placetype":"venue"
},
  "geometry": {"coordinates":[5.5526041985,51.0406074524],"type":"Point"}
}