{
  "type": "Feature",
  "properties": {
    "iso:country":"BE",
    "sg:address":"Moerestraat 47",
    "sg:city":"Koekelare",
    "sg:orig_category":"Schoonheidssalons",
    "sg:phone":"+32 51 58 04 65",
    "sg:postcode":"8680",
    "sg:province":"West-Vlaanderen",
    "wof:name":"Pedicure Carla",
    "wof:placetype":"venue"
},
  "geometry": {"coordinates":[2.9798390865,51.0941009521],"type":"Point"}
}