{
  "type": "Feature",
  "properties": {
    "iso:country":"BE",
    "sg:address":"Lenclos 84",
    "sg:city":"Etalle",
    "sg:orig_category":"Architectes",
    "sg:phone":"+32 63 45 53 89",
    "sg:postcode":"6740",
    "sg:province":"Luxembourg",
    "wof:name":"St\u00c9phane Fran\u00c7ois",
    "wof:placetype":"venue"
},
  "geometry": {"coordinates":[5.6085290909,49.6738967896],"type":"Point"}
}