{
  "type": "Feature",
  "properties": {
    "addr:full":"Rue De La Station 70 Braine-le-comte Hainaut 7090",
    "addr:housenumber":"70",
    "addr:postcode":"7090",
    "addr:street":"Rue De La Station",
    "iso:country":"BE",
    "sg:address":"Rue De La Station 70",
    "sg:city":"Braine-le-comte",
    "sg:orig_category":"Salles de spectacles",
    "sg:phone":"+32 67 55 73 50",
    "sg:postcode":"7090",
    "sg:province":"Hainaut",
    "wof:name":"Th\u00c9\u00c2tre De L'epi",
    "wof:placetype":"venue"
},
  "geometry": {"coordinates":[4.1376547813,50.6081123352],"type":"Point"}
}