{
  "type": "Feature",
  "properties": {
    "iso:country":"BE",
    "sg:address":"Papenbroekstraat 209",
    "sg:city":"Diest (webbekom)",
    "sg:classifiers":[
        {
            "category":"Home & Garden",
            "subcategory":"Building Materials",
            "type":"Retail Goods"
        }
    ],
    "sg:phone":"+32 13 31 46 64",
    "sg:postcode":"3290",
    "sg:province":"Vlaams-Brabant",
    "sg:tags":[
        "window"
    ],
    "wof:name":"D & A Products Bvba",
    "wof:placetype":"venue"
},
  "geometry": {"coordinates":[5.0606198311,50.9738388062],"type":"Point"}
}