{
  "type": "Feature",
  "properties": {
    "iso:country":"BE",
    "sg:address":"Rue De Nimy 136",
    "sg:city":"Mons",
    "sg:classifiers":[
        {
            "category":"Shopping",
            "subcategory":"Books",
            "type":"Retail Goods"
        }
    ],
    "sg:phone":"+32 65 84 58 93",
    "sg:postcode":"7000",
    "sg:province":"Hainaut",
    "sg:tags":[
        "bookseller"
    ],
    "wof:name":"Librairei Du Lido",
    "wof:placetype":"venue"
},
  "geometry": {"coordinates":[3.9556360245,50.4590339661],"type":"Point"}
}