{
  "type": "Feature",
  "properties": {
    "addr:full":"Kerkstraat 2 Kalmthout Antwerpen 2920",
    "addr:housenumber":"2",
    "addr:postcode":"2920",
    "addr:street":"Kerkstraat",
    "iso:country":"BE",
    "sg:address":"Kerkstraat 2",
    "sg:city":"Kalmthout",
    "sg:orig_category":"Eleveurs de bovins",
    "sg:phone":"+32 3 667 34 21",
    "sg:postcode":"2920",
    "sg:province":"Antwerpen",
    "wof:name":"Aloisius Anthonissen",
    "wof:placetype":"venue"
},
  "geometry": {"coordinates":[4.5183329582,51.4325294495],"type":"Point"}
}