{
  "type": "Feature",
  "properties": {
    "iso:country":"BE",
    "sg:address":"Sprietstraat 7",
    "sg:city":"Staden",
    "sg:orig_category":"Varkenskwekers",
    "sg:phone":"+32 51 78 05 23",
    "sg:postcode":"8840",
    "sg:province":"West-Vlaanderen",
    "wof:name":"Robert Lavens",
    "wof:placetype":"venue"
},
  "geometry": {"coordinates":[2.9844119549,50.9337921143],"type":"Point"}
}