{
  "type": "Feature",
  "properties": {
    "addr:full":"Chauss\u00c9e De Renaix 17 Mont-de-l'enclus Hainaut 7750",
    "addr:housenumber":"17",
    "addr:postcode":"7750",
    "addr:street":"Chausse\u0301E De Renaix;Hainaut",
    "iso:country":"BE",
    "sg:address":"Chauss\u00c9e De Renaix 17",
    "sg:city":"Mont-de-l'enclus",
    "sg:orig_category":"Varkenskwekers",
    "sg:phone":"+32 69 76 90 29",
    "sg:postcode":"7750",
    "sg:province":"Hainaut",
    "wof:name":"Luc Detemmerman",
    "wof:placetype":"venue"
},
  "geometry": {"coordinates":[4.9165067673,50.3185577393],"type":"Point"}
}