{
  "type": "Feature",
  "properties": {
    "addr:full":"Ijsbroekstraat 20 Aalst Oost-Vlaanderen 9308",
    "addr:housenumber":"20",
    "addr:postcode":"9308",
    "addr:street":"Ijsbroekstraat",
    "iso:country":"BE",
    "sg:address":"Ijsbroekstraat 20",
    "sg:city":"Aalst",
    "sg:orig_category":"Elektrische installaties voor woningen",
    "sg:phone":"+32 53 78 40 98",
    "sg:postcode":"9308",
    "sg:province":"Oost-Vlaanderen",
    "wof:name":"Chris Beeckman",
    "wof:placetype":"venue"
},
  "geometry": {"coordinates":[4.0467090607,50.9830093384],"type":"Point"}
}