{
  "type": "Feature",
  "properties": {
    "iso:country":"BE",
    "sg:address":"Neerveldstraat 11",
    "sg:city":"Heusden-zolder",
    "sg:orig_category":"Rev\u00eatements pour sols and murs",
    "sg:phone":"+32 11 57 39 22",
    "sg:postcode":"3550",
    "sg:province":"Limburg",
    "wof:name":"Jean-pierre Bortels",
    "wof:placetype":"venue"
},
  "geometry": {"coordinates":[5.3372178078,51.0374336243],"type":"Point"}
}