{
  "type": "Feature",
  "properties": {
    "addr:full":"Chemin Des Douys 20 Pepinster Li\u00e8ge 4860",
    "addr:housenumber":"20",
    "addr:postcode":"4860",
    "addr:street":"Chemin Des Douys",
    "iso:country":"BE",
    "sg:address":"Chemin Des Douys 20",
    "sg:city":"Pepinster",
    "sg:classifiers":[
        {
            "category":"Travel",
            "subcategory":"Hotels & Motels",
            "type":"Entertainment"
        }
    ],
    "sg:phone":"+32 87 46 06 51",
    "sg:postcode":"4860",
    "sg:province":"Li\u00e8ge",
    "sg:tags":[
        "restaurant"
    ],
    "wof:name":"Hostellerie Lafarque",
    "wof:placetype":"venue"
},
  "geometry": {"coordinates":[5.7723040581,50.5663108826],"type":"Point"}
}