{
  "type": "Feature",
  "properties": {
    "addr:full":"Bergstraat 5 Erpe-mere Oost-Vlaanderen 9420",
    "addr:housenumber":"5",
    "addr:postcode":"9420",
    "addr:street":"Bergstraat",
    "iso:country":"BE",
    "sg:address":"Bergstraat 5",
    "sg:city":"Erpe-mere",
    "sg:orig_category":"Woningbouw",
    "sg:phone":"+32 53 83 69 56",
    "sg:postcode":"9420",
    "sg:province":"Oost-Vlaanderen",
    "wof:name":"Jozef De Saedeleer",
    "wof:placetype":"venue"
},
  "geometry": {"coordinates":[3.9719250202,50.923915863],"type":"Point"}
}