{
  "type": "Feature",
  "properties": {
    "iso:country":"BE",
    "sg:address":"Retiesebaan 32",
    "sg:city":"Kasterlee",
    "sg:orig_category":"Notarissen",
    "sg:phone":"+32 14 85 47 80",
    "sg:postcode":"2460",
    "sg:province":"Antwerpen",
    "wof:name":"Stynen Bert",
    "wof:placetype":"venue"
},
  "geometry": {"coordinates":[4.9714179039,51.2412376404],"type":"Point"}
}