{
  "type": "Feature",
  "properties": {
    "addr:full":"Fabiolalaan 43 Menen West-Vlaanderen 8930",
    "addr:housenumber":"43",
    "addr:postcode":"8930",
    "addr:street":"Fabiolalaan",
    "iso:country":"BE",
    "sg:address":"Fabiolalaan 43",
    "sg:city":"Menen",
    "sg:orig_category":"Avocats and conseillers juridiques",
    "sg:phone":"+32 56 53 13 84",
    "sg:postcode":"8930",
    "sg:province":"West-Vlaanderen",
    "wof:name":"Ann Debreuck",
    "wof:placetype":"venue"
},
  "geometry": {"coordinates":[3.1256620884,50.7953147888],"type":"Point"}
}