{
  "type": "Feature",
  "properties": {
    "addr:full":"Rue De La Chapelle 6 Tournai (templeuve) Hainaut 7520",
    "addr:housenumber":"6",
    "addr:postcode":"7520",
    "addr:street":"Rue De La Chapelle",
    "iso:country":"BE",
    "sg:address":"Rue De La Chapelle 6",
    "sg:city":"Tournai (templeuve)",
    "sg:classifiers":[
        {
            "category":"Bars & Pubs",
            "type":"Food & Drink"
        }
    ],
    "sg:phone":"+32 69 35 30 01",
    "sg:postcode":"7520",
    "sg:province":"Hainaut",
    "wof:name":"Alchimiste (l')",
    "wof:placetype":"venue"
},
  "geometry": {"coordinates":[3.3526799679,50.6036071777],"type":"Point"}
}