{
  "type": "Feature",
  "properties": {
    "addr:full":"Rue Bierwa 28 Havelange (maffe) Namur 5374",
    "addr:housenumber":"28",
    "addr:postcode":"5374",
    "addr:street":"Rue Bierwa",
    "iso:country":"BE",
    "sg:address":"Rue Bierwa 28",
    "sg:city":"Havelange (maffe)",
    "sg:classifiers":[
        {
            "category":"Food & Beverages",
            "subcategory":"Groceries & Convenience Stores",
            "type":"Retail Goods"
        }
    ],
    "sg:phone":"+32 86 32 31 85",
    "sg:postcode":"5374",
    "sg:province":"Namur",
    "sg:tags":[
        "grocer"
    ],
    "wof:name":"Fran\u00e7oise (chez)",
    "wof:placetype":"venue"
},
  "geometry": {"coordinates":[5.3074011803,50.35206604],"type":"Point"}
}