{
  "type": "Feature",
  "properties": {
    "addr:full":"Lamorini\u00c8restraat 157 Antwerpen Antwerpen 2018",
    "addr:housenumber":"157",
    "addr:postcode":"2018",
    "addr:street":"Lamorinie\u0300Restraat",
    "iso:country":"BE",
    "sg:address":"Lamorini\u00c8restraat 157",
    "sg:city":"Antwerpen",
    "sg:orig_category":"Ambassades and consulats",
    "sg:phone":"+32 3 239 55 94",
    "sg:postcode":"2018",
    "sg:province":"Antwerpen",
    "wof:name":"Consulaat Van Armeni\u00cb",
    "wof:placetype":"venue"
},
  "geometry": {"coordinates":[4.4204268456,51.2030105591],"type":"Point"}
}