{
  "type": "Feature",
  "properties": {
    "addr:full":"Foyeuru 15 Jalhay Li\u00e8ge 4845",
    "addr:housenumber":"15",
    "addr:postcode":"4845",
    "addr:street":"Foyeuru",
    "iso:country":"BE",
    "sg:address":"Foyeuru 15",
    "sg:city":"Jalhay",
    "sg:classifiers":[
        {
            "category":"Farming",
            "subcategory":"Fish & Marine Products",
            "type":"Manufacturing & Wholesale Goods"
        }
    ],
    "sg:phone":"+32 87 64 75 20",
    "sg:postcode":"4845",
    "sg:province":"Li\u00e8ge",
    "sg:tags":[
        "equipment",
        "fishery"
    ],
    "wof:name":"Foyeuru (pecheries Du)",
    "wof:placetype":"venue"
},
  "geometry": {"coordinates":[5.9597277641,50.570438385],"type":"Point"}
}