{
  "type": "Feature",
  "properties": {
    "addr:full":"Lippenslaan 216 Knokke-heist (knokke) West-Vlaanderen 8300",
    "addr:housenumber":"216",
    "addr:postcode":"8300",
    "addr:street":"Lippenslaan",
    "iso:country":"BE",
    "sg:address":"Lippenslaan 216",
    "sg:city":"Knokke-heist (knokke)",
    "sg:classifiers":[
        {
            "category":"Building & Trades",
            "subcategory":"Locksmith",
            "type":"Services"
        }
    ],
    "sg:phone":"+32 50 60 13 15",
    "sg:postcode":"8300",
    "sg:province":"West-Vlaanderen",
    "sg:tags":[
        "lock",
        "key"
    ],
    "wof:name":"Coppens P",
    "wof:placetype":"venue"
},
  "geometry": {"coordinates":[3.2888860703,51.3485641479],"type":"Point"}
}