{
  "type": "Feature",
  "properties": {
    "addr:full":"Over D\u00b4aa 114 Essen Antwerpen 2910",
    "addr:housenumber":"114",
    "addr:postcode":"2910",
    "iso:country":"BE",
    "sg:address":"Over D\u00b4aa 114",
    "sg:city":"Essen",
    "sg:orig_category":"Tijdelijke werkgelegenheid and uitzendkantoren",
    "sg:phone":"+32 3 677 10 87",
    "sg:postcode":"2910",
    "sg:province":"Antwerpen",
    "wof:name":"View Interim",
    "wof:placetype":"venue"
},
  "geometry": {"coordinates":[4.4889740944,51.4665222168],"type":"Point"}
}