{
  "type": "Feature",
  "properties": {
    "iso:country":"BE",
    "sg:address":"Rue Saint-jean 6",
    "sg:city":"Namur",
    "sg:orig_category":"Dameskledingzaken",
    "sg:phone":"+32 81 22 53 33",
    "sg:postcode":"5000",
    "sg:province":"Namur",
    "wof:name":"Rue Blanche",
    "wof:placetype":"venue"
},
  "geometry": {"coordinates":[4.8642749786,50.4631080627],"type":"Point"}
}