{
  "type": "Feature",
  "properties": {
    "addr:full":"Avenue Du G\u00d9eret 38 Wavre Brabant Wallon 1300",
    "addr:housenumber":"38;1300",
    "addr:street":"Avenue Du Gu\u0300Eret",
    "iso:country":"BE",
    "sg:address":"Avenue Du G\u00d9eret 38",
    "sg:city":"Wavre",
    "sg:orig_category":"Boekhouders",
    "sg:phone":"+32 10 40 09 88",
    "sg:postcode":"1300",
    "sg:province":"Brabant Wallon",
    "wof:name":"Berger Jacques",
    "wof:placetype":"venue"
},
  "geometry": {"coordinates":[4.5522880554,50.7068061829],"type":"Point"}
}