{
  "type": "Feature",
  "properties": {
    "iso:country":"BE",
    "sg:address":"Grote Straat 43",
    "sg:city":"Geraardsbergen",
    "sg:orig_category":"Randstad",
    "sg:phone":"+32 54 41 93 59",
    "sg:postcode":"9500",
    "sg:province":"Oost-Vlaanderen",
    "wof:name":"Randstad",
    "wof:placetype":"venue"
},
  "geometry": {"coordinates":[3.8780140877,50.7718544006],"type":"Point"}
}