{
  "type": "Feature",
  "properties": {
    "iso:country":"BE",
    "sg:address":"Chauss\u00e9e De Philippeville 128",
    "sg:city":"Gerpinnes (loverval)",
    "sg:classifiers":[
        {
            "category":"Health Services",
            "subcategory":"Nursing And Care Facility",
            "type":"Services"
        }
    ],
    "sg:phone":"+32 71 36 08 50",
    "sg:postcode":"6280",
    "sg:province":"Hainaut",
    "sg:tags":[
        "home",
        "rest"
    ],
    "wof:name":"Amarantes (les)-seigneurie De Loverval",
    "wof:placetype":"venue"
},
  "geometry": {"coordinates":[4.4697999954,50.3607711792],"type":"Point"}
}