{
  "type": "Feature",
  "properties": {
    "addr:full":"Gistelse Steenweg 380 Brugge West-Vlaanderen 8200",
    "addr:housenumber":"380",
    "addr:postcode":"8200",
    "addr:street":"Gistelse Steenweg",
    "iso:country":"BE",
    "sg:address":"Gistelse Steenweg 380",
    "sg:city":"Brugge",
    "sg:classifiers":[
        {
            "category":"Personal",
            "subcategory":"Beauty Salon",
            "type":"Services"
        }
    ],
    "sg:phone":"+32 50 67 88 42",
    "sg:postcode":"8200",
    "sg:province":"West-Vlaanderen",
    "sg:tags":[
        "de",
        "coiffure"
    ],
    "wof:name":"Coiffure Reflection",
    "wof:placetype":"venue"
},
  "geometry": {"coordinates":[3.1950199604,51.2001304626],"type":"Point"}
}