{
  "type": "Feature",
  "properties": {
    "iso:country":"BE",
    "sg:address":"Sur Les Thiers 156",
    "sg:city":"Herstal",
    "sg:orig_category":"Entretien and r\u00e9parations de voitures",
    "sg:phone":"+32 4 264 78 01",
    "sg:postcode":"4040",
    "sg:province":"Li\u00e8ge",
    "wof:name":"Carrosserie Callura",
    "wof:placetype":"venue"
},
  "geometry": {"coordinates":[5.6116518974,50.6712799072],"type":"Point"}
}