{
  "type": "Feature",
  "properties": {
    "addr:full":"Ringlaan 34b12 Kortrijk West-Vlaanderen 8500",
    "addr:housenumber":"34b12",
    "addr:postcode":"8500",
    "addr:street":"Ringlaan",
    "iso:country":"BE",
    "sg:address":"Ringlaan 34b12",
    "sg:city":"Kortrijk",
    "sg:orig_category":"Foto-uitrusting Fotografen and fotostudio's Fotolaboratoria",
    "sg:phone":"+32 56 35 29 34",
    "sg:postcode":"8500",
    "sg:province":"West-Vlaanderen",
    "wof:name":"Foto Prestige",
    "wof:placetype":"venue"
},
  "geometry": {"coordinates":[3.2646589279,50.8452682495],"type":"Point"}
}