{
  "type": "Feature",
  "properties": {
    "addr:full":"Av. Commandant Lothaire 5 Etterbeek/etterbeek Bruxelles-Capitale 1040",
    "addr:housenumber":"5",
    "addr:postcode":"1040",
    "addr:street":"Av. Commandant Lothaire",
    "iso:country":"BE",
    "sg:address":"Av. Commandant Lothaire 5",
    "sg:city":"Etterbeek/etterbeek",
    "sg:orig_category":"M\u00e9decins and sp\u00e9cialistes",
    "sg:phone":"+32 2 733 06 18",
    "sg:postcode":"1040",
    "sg:province":"Bruxelles-Capitale",
    "wof:name":"Frank Dewitte/f. Dewitte",
    "wof:placetype":"venue"
},
  "geometry": {"coordinates":[4.4037528038,50.8298225403],"type":"Point"}
}