{
  "type": "Feature",
  "properties": {
    "iso:country":"BE",
    "sg:address":"Provinciale Steenweg 370",
    "sg:city":"Schelle",
    "sg:orig_category":"Rev\u00eatements de sols and murs",
    "sg:phone":"+32 3 887 57 82",
    "sg:postcode":"2627",
    "sg:province":"Antwerpen",
    "wof:name":"Jt Tegeldepot",
    "wof:placetype":"venue"
},
  "geometry": {"coordinates":[4.3336229324,51.1180686951],"type":"Point"}
}