{
  "type": "Feature",
  "properties": {
    "addr:full":"Rue Gohyssart 27a Charleroi Hainaut 6042",
    "addr:housenumber":"27a",
    "addr:postcode":"6042",
    "addr:street":"Rue Gohyssart;Hainaut",
    "iso:country":"BE",
    "sg:address":"Rue Gohyssart 27a",
    "sg:city":"Charleroi",
    "sg:orig_category":"Travaux de pl\u00e2trage",
    "sg:phone":"+32 71 30 52 68",
    "sg:postcode":"6042",
    "sg:province":"Hainaut",
    "wof:name":"A. Danatzis",
    "wof:placetype":"venue"
},
  "geometry": {"coordinates":[4.4013371468,50.4318504333],"type":"Point"}
}