{
  "type": "Feature",
  "properties": {
    "iso:country":"BE",
    "sg:address":"Nederenamestraat 7",
    "sg:city":"Oudenaarde",
    "sg:classifiers":[
        {
            "category":"Personal",
            "subcategory":"Beauty Salon",
            "type":"Services"
        }
    ],
    "sg:phone":"+32 55 31 89 85",
    "sg:postcode":"9700",
    "sg:province":"Oost-Vlaanderen",
    "sg:tags":[
        "de",
        "coiffure"
    ],
    "wof:name":"Kapsalon Christof",
    "wof:placetype":"venue"
},
  "geometry": {"coordinates":[3.6545000076,50.8692207336],"type":"Point"}
}