{
  "type": "Feature",
  "properties": {
    "iso:country":"BE",
    "sg:address":"Statieplaats 14",
    "sg:city":"Lichtervelde",
    "sg:orig_category":"Slagers",
    "sg:phone":"+32 51 72 27 32",
    "sg:postcode":"8810",
    "sg:province":"West-Vlaanderen",
    "wof:name":"Dirk Vinckier",
    "wof:placetype":"venue"
},
  "geometry": {"coordinates":[3.1405899525,51.0262794495],"type":"Point"}
}