{
  "type": "Feature",
  "properties": {
    "iso:country":"BE",
    "sg:address":"Savoiestraat 9",
    "sg:city":"Sint-gillis/saint-gilles",
    "sg:orig_category":"Brood, gebak and snoepgoed",
    "sg:phone":"+32 2 534 00 49",
    "sg:postcode":"1060",
    "sg:province":"Bruxelles-Capitale",
    "wof:name":"Boulangerie Delestr\u00c9e",
    "wof:placetype":"venue"
},
  "geometry": {"coordinates":[4.3482117653,50.8248825073],"type":"Point"}
}