{
  "type": "Feature",
  "properties": {
    "addr:full":"Rue De L'espinette 77 Mons Hainaut 7033",
    "addr:housenumber":"77",
    "addr:postcode":"7033",
    "addr:street":"Rue De L'Espinette;Hainaut",
    "iso:country":"BE",
    "sg:address":"Rue De L'espinette 77",
    "sg:city":"Mons",
    "sg:orig_category":"Gespecialiseerde niet-residenti\u00eble bouw Metalen constructies Fab",
    "sg:phone":"+32 65 31 23 88",
    "sg:postcode":"7033",
    "sg:province":"Hainaut",
    "wof:name":"Dufrane P\u00c8re & Fils",
    "wof:placetype":"venue"
},
  "geometry": {"coordinates":[3.9293179512,50.4291801453],"type":"Point"}
}