{
  "type": "Feature",
  "properties": {
    "addr:full":"Ingooigemplaats 54 Anzegem (ingooigem) West-Vlaanderen 8570",
    "addr:housenumber":"54",
    "addr:postcode":"8570",
    "addr:street":"Ingooigemplaats",
    "iso:country":"BE",
    "sg:address":"Ingooigemplaats 54",
    "sg:city":"Anzegem (ingooigem)",
    "sg:classifiers":[
        {
            "category":"Banks & Credit Unions",
            "subcategory":"Bank",
            "type":"Services"
        }
    ],
    "sg:phone":"+32 56 77 50 29",
    "sg:postcode":"8570",
    "sg:province":"West-Vlaanderen",
    "sg:tags":[
        "savings-banks"
    ],
    "wof:name":"Verzekeringskantoor Callens Nv",
    "wof:placetype":"venue"
},
  "geometry": {"coordinates":[3.478826046,50.8326339722],"type":"Point"}
}