{
  "type": "Feature",
  "properties": {
    "iso:country":"BE",
    "sg:address":"Rue Du Bois 160",
    "sg:city":"La Louvi\u00e8re",
    "sg:classifiers":[
        {
            "category":"Building & Trades",
            "subcategory":"Electrical",
            "type":"Services"
        }
    ],
    "sg:phone":"+32 64 55 45 59",
    "sg:postcode":"7100",
    "sg:province":"Hainaut",
    "sg:tags":[
        "electric",
        "-",
        "housewiring",
        "contractor"
    ],
    "wof:name":"Patelec",
    "wof:placetype":"venue"
},
  "geometry": {"coordinates":[4.2067461014,50.5013504028],"type":"Point"}
}