{
  "type": "Feature",
  "properties": {
    "iso:country":"BE",
    "sg:address":"Bosduinstraat 71",
    "sg:city":"Wuustwezel",
    "sg:orig_category":"Elektrische installaties voor woningen",
    "sg:phone":"+32 3 459 49 68",
    "sg:postcode":"2990",
    "sg:province":"Antwerpen",
    "wof:name":"Elektro Dega",
    "wof:placetype":"venue"
},
  "geometry": {"coordinates":[4.5371098518,51.3567695618],"type":"Point"}
}