{
  "type": "Feature",
  "properties": {
    "iso:country":"BE",
    "sg:address":"Spijkerlaan 129",
    "sg:city":"Waregem (beveren-leie)",
    "sg:classifiers":[
        {
            "category":"Autos & Motor Vehicles",
            "subcategory":"Motorcycle Sales",
            "type":"Retail Goods"
        }
    ],
    "sg:phone":"+32 56 72 51 51",
    "sg:postcode":"8791",
    "sg:province":"West-Vlaanderen",
    "sg:tags":[
        "motorbike"
    ],
    "wof:name":"Lerouge Auto Moto",
    "wof:placetype":"venue"
},
  "geometry": {"coordinates":[3.3474700451,50.8605995178],"type":"Point"}
}