{
  "type": "Feature",
  "properties": {
    "addr:full":"Wijnheuvelenstraat 227 Schaarbeek/schaerbeek Bruxelles-Capitale 1030",
    "addr:housenumber":"227",
    "addr:postcode":"1030",
    "addr:street":"Wijnheuvelenstraat",
    "iso:country":"BE",
    "sg:address":"Wijnheuvelenstraat 227",
    "sg:city":"Schaarbeek/schaerbeek",
    "sg:orig_category":"Advocaten and juridische adviseurs",
    "sg:phone":"+32 2 242 69 32",
    "sg:postcode":"1030",
    "sg:province":"Bruxelles-Capitale",
    "wof:name":"M. H\u00c9bette",
    "wof:placetype":"venue"
},
  "geometry": {"coordinates":[4.3776669502,50.8601570129],"type":"Point"}
}