{
  "type": "Feature",
  "properties": {
    "iso:country":"BE",
    "sg:address":"Sint Aarnoutstraat 33",
    "sg:city":"Zedelgem",
    "sg:orig_category":"Production de films, t\u00e9l\u00e9films and vid\u00e9os",
    "sg:phone":"+32 50 20 85 10",
    "sg:postcode":"8211",
    "sg:province":"West-Vlaanderen",
    "wof:name":"Video Mario Productions",
    "wof:placetype":"venue"
},
  "geometry": {"coordinates":[3.0890660286,51.1126556396],"type":"Point"}
}