{
  "type": "Feature",
  "properties": {
    "addr:full":"Westmeerbeeksteenweg 41 Heist-op-den-berg (booischot) Antwerpen 2221",
    "addr:housenumber":"41",
    "addr:postcode":"2221",
    "addr:street":"Westmeerbeeksteenweg",
    "iso:country":"BE",
    "sg:address":"Westmeerbeeksteenweg 41",
    "sg:city":"Heist-op-den-berg (booischot)",
    "sg:classifiers":[
        {
            "category":"Structure",
            "subcategory":"Building",
            "type":"Public Place"
        }
    ],
    "sg:phone":"+32 15 22 23 79",
    "sg:postcode":"2221",
    "sg:province":"Antwerpen",
    "sg:tags":[
        "door"
    ],
    "wof:name":"Jacobs Ramen & Deuren",
    "wof:placetype":"venue"
},
  "geometry": {"coordinates":[4.7739758492,51.0512428284],"type":"Point"}
}