{
  "type": "Feature",
  "properties": {
    "addr:full":"Avenue Victor David 60 Limbourg Li\u00e8ge 4830",
    "addr:housenumber":"60",
    "addr:postcode":"4830",
    "addr:street":"Avenue Victor David",
    "iso:country":"BE",
    "sg:address":"Avenue Victor David 60",
    "sg:city":"Limbourg",
    "sg:classifiers":[
        {
            "category":"Arts & Performance",
            "subcategory":"Music",
            "type":"Entertainment"
        }
    ],
    "sg:phone":"+32 87 76 34 79",
    "sg:postcode":"4830",
    "sg:province":"Li\u00e8ge",
    "sg:tags":[
        "disc-jockeys"
    ],
    "wof:name":"Chanteux J G",
    "wof:placetype":"venue"
},
  "geometry": {"coordinates":[5.9407401085,50.6112518311],"type":"Point"}
}