{
  "type": "Feature",
  "properties": {
    "addr:full":"Rue De Grandvoir 17 Libramont-chevigny (recogne) Luxembourg 6800",
    "addr:housenumber":"17",
    "addr:postcode":"6800",
    "addr:street":"Rue De Grandvoir",
    "iso:country":"BE",
    "sg:address":"Rue De Grandvoir 17",
    "sg:city":"Libramont-chevigny (recogne)",
    "sg:classifiers":[
        {
            "category":"Real Estate",
            "subcategory":"Architect",
            "type":"Services"
        }
    ],
    "sg:phone":"+32 61 22 30 15",
    "sg:postcode":"6800",
    "sg:province":"Luxembourg",
    "wof:name":"Wauthoz P",
    "wof:placetype":"venue"
},
  "geometry": {"coordinates":[5.3761348724,49.9199943542],"type":"Point"}
}