{
  "type": "Feature",
  "properties": {
    "addr:full":"Wondelgemkaai 200 Gent Oost-Vlaanderen 9000",
    "addr:housenumber":"200",
    "addr:postcode":"9000",
    "addr:street":"Oost-Vlaanderen",
    "iso:country":"BE",
    "sg:address":"Wondelgemkaai 200",
    "sg:city":"Gent",
    "sg:classifiers":[
        {
            "category":"Manufacturing",
            "subcategory":"Printing",
            "type":"Manufacturing & Wholesale Goods"
        }
    ],
    "sg:phone":"+32 9 258 21 41",
    "sg:postcode":"9000",
    "sg:province":"Oost-Vlaanderen",
    "sg:tags":[
        "paper",
        "waste"
    ],
    "wof:name":"Vlar Papier",
    "wof:placetype":"venue"
},
  "geometry": {"coordinates":[3.7334940434,51.1098594666],"type":"Point"}
}