{
  "type": "Feature",
  "properties": {
    "addr:full":"Rue De Fragn\u00c9e 139 Li\u00c8ge Li\u00e8ge 4000",
    "addr:housenumber":"139",
    "addr:postcode":"4000",
    "addr:street":"Rue De Fragne\u0301E",
    "iso:country":"BE",
    "sg:address":"Rue De Fragn\u00c9e 139",
    "sg:city":"Li\u00c8ge",
    "sg:orig_category":"Epiceries. Cr\u00e9meries",
    "sg:phone":"+32 4 254 03 00",
    "sg:postcode":"4000",
    "sg:province":"Li\u00e8ge",
    "wof:name":"Au March\u00c9 De Fragn\u00c9e",
    "wof:placetype":"venue"
},
  "geometry": {"coordinates":[5.5733308792,50.6222038269],"type":"Point"}
}