{
  "type": "Feature",
  "properties": {
    "addr:full":"Avenue Du Commerce 6 Braine L'alleud (braine-l'alleud) Brabant Wallon 1420",
    "addr:housenumber":"6",
    "addr:postcode":"1420",
    "addr:street":"Avenue Du Commerce",
    "iso:country":"BE",
    "sg:address":"Avenue Du Commerce 6",
    "sg:city":"Braine L'alleud (braine-l'alleud)",
    "sg:classifiers":[
        {
            "category":"Home & Garden",
            "subcategory":"Building Materials",
            "type":"Retail Goods"
        }
    ],
    "sg:phone":"+32 2 387 21 60",
    "sg:postcode":"1420",
    "sg:province":"Brabant Wallon",
    "sg:tags":[
        "article",
        "-",
        "do-it-yourself"
    ],
    "wof:name":"Brico March\u00e9 Sa",
    "wof:placetype":"venue"
},
  "geometry": {"coordinates":[-0.7004899979,47.369140625],"type":"Point"}
}