{
  "type": "Feature",
  "properties": {
    "addr:full":"Kruisbergstraat 11 Ruiselede West-Vlaanderen 8755",
    "addr:housenumber":"11",
    "addr:postcode":"8755",
    "addr:street":"Kruisbergstraat",
    "iso:country":"BE",
    "sg:address":"Kruisbergstraat 11",
    "sg:city":"Ruiselede",
    "sg:orig_category":"Travaux de pl\u00e2trage",
    "sg:phone":"+32 51 68 97 76",
    "sg:postcode":"8755",
    "sg:province":"West-Vlaanderen",
    "wof:name":"Marc Sierens",
    "wof:placetype":"venue"
},
  "geometry": {"coordinates":[3.3858850002,51.0715332031],"type":"Point"}
}