{
  "type": "Feature",
  "properties": {
    "addr:full":"Stationsstraat 144 Geel Antwerpen 2440",
    "addr:housenumber":"144",
    "addr:postcode":"2440",
    "addr:street":"Stationsstraat",
    "iso:country":"BE",
    "sg:address":"Stationsstraat 144",
    "sg:city":"Geel",
    "sg:classifiers":[
        {
            "category":"Real Estate",
            "subcategory":"Real Estate Services",
            "type":"Services"
        }
    ],
    "sg:phone":"+32 14 58 80 12",
    "sg:postcode":"2440",
    "sg:province":"Antwerpen",
    "wof:name":"Studio's Van Lommel",
    "wof:placetype":"venue"
},
  "geometry": {"coordinates":[4.988617897,51.1669807434],"type":"Point"}
}