{
  "type": "Feature",
  "properties": {
    "addr:full":"Rijksweg 14 Zulte (machelen) Oost-Vlaanderen 9870",
    "addr:housenumber":"14",
    "addr:postcode":"9870",
    "addr:street":"Rijksweg",
    "iso:country":"BE",
    "sg:address":"Rijksweg 14",
    "sg:city":"Zulte (machelen)",
    "sg:classifiers":[
        {
            "category":"Food & Beverages",
            "subcategory":"Supermarket",
            "type":"Retail Goods"
        }
    ],
    "sg:phone":"+32 9 386 65 12",
    "sg:postcode":"9870",
    "sg:province":"Oost-Vlaanderen",
    "sg:tags":[
        "department",
        "store"
    ],
    "wof:name":"Profi",
    "wof:placetype":"venue"
},
  "geometry": {"coordinates":[3.5032970905,50.9616470337],"type":"Point"}
}