{
  "type": "Feature",
  "properties": {
    "addr:full":"Sint-jorisplein 31 Nieuwpoort West-Vlaanderen 8620",
    "addr:housenumber":"31",
    "addr:postcode":"8620",
    "addr:street":"Sint-Jorisplein",
    "iso:country":"BE",
    "sg:address":"Sint-jorisplein 31",
    "sg:city":"Nieuwpoort",
    "sg:orig_category":"Enseignement maternel and primaire",
    "sg:phone":"+32 58 23 51 34",
    "sg:postcode":"8620",
    "sg:province":"West-Vlaanderen",
    "wof:name":"Stedelijke Basisschool",
    "wof:placetype":"venue"
},
  "geometry": {"coordinates":[2.7774701118,51.1309013367],"type":"Point"}
}