{
  "type": "Feature",
  "properties": {
    "iso:country":"BE",
    "sg:address":"Avenue Platon 21",
    "sg:city":"Bruxelles (evere)",
    "sg:classifiers":[
        {
            "category":"Social Services",
            "type":"Services"
        }
    ],
    "sg:phone":"+32 2 726 54 83",
    "sg:postcode":"1140",
    "sg:province":"Bruxelles-Capitale",
    "wof:name":"Ieder Zijn Huis",
    "wof:placetype":"venue"
},
  "geometry": {"coordinates":[4.4213700294,50.863079071],"type":"Point"}
}