{
  "type": "Feature",
  "properties": {
    "addr:full":"Wettersesteenweg 192 Sint-lievens-houtem Oost-Vlaanderen 9520",
    "addr:housenumber":"192",
    "addr:postcode":"9520",
    "addr:street":"Wettersesteenweg;Oost-Vlaanderen",
    "iso:country":"BE",
    "sg:address":"Wettersesteenweg 192",
    "sg:city":"Sint-lievens-houtem",
    "sg:orig_category":"Kapsalons",
    "sg:phone":"+32 9 362 46 30",
    "sg:postcode":"9520",
    "sg:province":"Oost-Vlaanderen",
    "wof:name":"Studio Lin",
    "wof:placetype":"venue"
},
  "geometry": {"coordinates":[3.856044054,50.9318351746],"type":"Point"}
}