{
  "type": "Feature",
  "properties": {
    "iso:country":"BE",
    "sg:address":"Rue Wilson 84",
    "sg:city":"Colfontaine",
    "sg:orig_category":"Articles de jardin",
    "sg:phone":"+32 65 67 40 63",
    "sg:postcode":"7340",
    "sg:province":"Hainaut",
    "wof:name":"Cuvelier Gererd",
    "wof:placetype":"venue"
},
  "geometry": {"coordinates":[3.8369369507,50.4144172668],"type":"Point"}
}