{
  "type": "Feature",
  "properties": {
    "addr:full":"Overleiestraat 66 Kortrijk West-Vlaanderen 8500",
    "addr:housenumber":"66",
    "addr:postcode":"8500",
    "addr:street":"Overleiestraat",
    "iso:country":"BE",
    "sg:address":"Overleiestraat 66",
    "sg:city":"Kortrijk",
    "sg:orig_category":"Pain, p\u00e2tisseries and confiseries",
    "sg:phone":"+32 56 35 14 19",
    "sg:postcode":"8500",
    "sg:province":"West-Vlaanderen",
    "wof:name":"Gerrit Deryckere",
    "wof:placetype":"venue"
},
  "geometry": {"coordinates":[3.2590820789,50.8334884644],"type":"Point"}
}