{
  "type": "Feature",
  "properties": {
    "iso:country":"BE",
    "sg:address":"Leuvensesteenweg 152",
    "sg:city":"Tervuren",
    "sg:orig_category":"G\u00e2teaux, p\u00e2tisserie and biscuits Fab",
    "sg:phone":"+32 2 768 16 32",
    "sg:postcode":"3080",
    "sg:province":"Vlaams-Brabant",
    "wof:name":"Biscuiterie Scheldewaert",
    "wof:placetype":"venue"
},
  "geometry": {"coordinates":[4.5130701065,50.8258209229],"type":"Point"}
}