{
  "type": "Feature",
  "properties": {
    "iso:country":"BE",
    "sg:address":"Kerkstraat 7",
    "sg:city":"Hechtel-eksel",
    "sg:orig_category":"Drukkerijen and copyshops",
    "sg:phone":"+32 11 73 18 07",
    "sg:postcode":"3941",
    "sg:province":"Limburg",
    "wof:name":"Grafico Cuypers Symons",
    "wof:placetype":"venue"
},
  "geometry": {"coordinates":[5.3937139511,51.1534843445],"type":"Point"}
}