{
  "type": "Feature",
  "properties": {
    "addr:full":"Groentemarkt 27a Lokeren Oost-Vlaanderen 9160",
    "addr:housenumber":"27a",
    "addr:postcode":"9160",
    "addr:street":"Groentemarkt",
    "iso:country":"BE",
    "sg:address":"Groentemarkt 27a",
    "sg:city":"Lokeren",
    "sg:orig_category":"Journaux",
    "sg:phone":"+32 9 348 24 41",
    "sg:postcode":"9160",
    "sg:province":"Oost-Vlaanderen",
    "wof:name":"Press Shop",
    "wof:placetype":"venue"
},
  "geometry": {"coordinates":[3.989221096,51.1036987305],"type":"Point"}
}