{
  "type": "Feature",
  "properties": {
    "addr:full":"Avenue Croix De Lorraine 39 La Hulpe Brabant Wallon 1310",
    "addr:housenumber":"39",
    "addr:postcode":"1310",
    "addr:street":"Avenue Croix De Lorraine",
    "iso:country":"BE",
    "sg:address":"Avenue Croix De Lorraine 39",
    "sg:city":"La Hulpe",
    "sg:orig_category":"Studios photographiques",
    "sg:phone":"+32 2 653 01 32",
    "sg:postcode":"1310",
    "sg:province":"Brabant Wallon",
    "wof:name":"Jacques Baudhuin",
    "wof:placetype":"venue"
},
  "geometry": {"coordinates":[4.4914431572,50.7466926575],"type":"Point"}
}