{
  "type": "Feature",
  "properties": {
    "addr:full":"Samr\u00c9e 4 La Roche-en-ardenne Luxembourg 6982",
    "addr:housenumber":"4",
    "addr:postcode":"6982",
    "addr:street":"Samre\u0301E",
    "iso:country":"BE",
    "sg:address":"Samr\u00c9e 4",
    "sg:city":"La Roche-en-ardenne",
    "sg:classifiers":[
        {
            "category":"Building & Trades",
            "subcategory":"Construction",
            "type":"Services"
        }
    ],
    "sg:phone":"+32 84 44 46 31",
    "sg:postcode":"6982",
    "sg:province":"Luxembourg",
    "sg:tags":[
        "r\u00e9sidentielles",
        "machine",
        "agricoles",
        "mat\u00e9riel",
        "sp\u00e9cifiques"
    ],
    "wof:name":"Erik Leonard",
    "wof:placetype":"venue"
},
  "geometry": {"coordinates":[5.638133049,50.2120666504],"type":"Point"}
}