{
  "type": "Feature",
  "properties": {
    "iso:country":"BE",
    "sg:address":"Hanebeekstraat 37",
    "sg:city":"Langemark-poelkapelle (langemark)",
    "sg:classifiers":[
        {
            "category":"Personal",
            "subcategory":"Beauty Salon",
            "type":"Services"
        }
    ],
    "sg:phone":"+32 57 48 80 62",
    "sg:postcode":"8920",
    "sg:province":"West-Vlaanderen",
    "sg:tags":[
        "lady",
        "-",
        "hairdressing"
    ],
    "wof:name":"Nelly",
    "wof:placetype":"venue"
},
  "geometry": {"coordinates":[2.9401059151,50.89037323],"type":"Point"}
}