{
  "type": "Feature",
  "properties": {
    "addr:full":"W.degouve De Nuncquesstr 10 Schaarbeek/schaerbeek Bruxelles-Capitale 1030",
    "addr:housenumber":"10",
    "addr:postcode":"1030",
    "iso:country":"BE",
    "sg:address":"W.degouve De Nuncquesstr 10",
    "sg:city":"Schaarbeek/schaerbeek",
    "sg:orig_category":"Brood, gebak and snoepgoed",
    "sg:phone":"+32 2 734 40 87",
    "sg:postcode":"1030",
    "sg:province":"Bruxelles-Capitale",
    "wof:name":"Nathalie Kwaspen",
    "wof:placetype":"venue"
},
  "geometry": {"coordinates":[4.4085631371,50.8486747742],"type":"Point"}
}