{
  "type": "Feature",
  "properties": {
    "iso:country":"BE",
    "sg:address":"Strodekkersstraat 11",
    "sg:city":"Gent",
    "sg:classifiers":[
        {
            "category":"Government",
            "subcategory":"Post Office",
            "type":"Public Place"
        }
    ],
    "sg:phone":"+32 9 236 33 64",
    "sg:postcode":"9000",
    "sg:province":"Oost-Vlaanderen",
    "sg:tags":[
        "picture",
        "restoring"
    ],
    "wof:name":"Weisenborn H",
    "wof:placetype":"venue"
},
  "geometry": {"coordinates":[3.6984210014,51.0602302551],"type":"Point"}
}