{
  "type": "Feature",
  "properties": {
    "iso:country":"BE",
    "sg:address":"Hoogzij 48",
    "sg:city":"Genk",
    "sg:classifiers":[
        {
            "category":"Real Estate",
            "subcategory":"Architect",
            "type":"Services"
        }
    ],
    "sg:phone":"+32 89 35 61 65",
    "sg:postcode":"3600",
    "sg:province":"Limburg",
    "wof:name":"Wouters A",
    "wof:placetype":"venue"
},
  "geometry": {"coordinates":[5.5281162262,50.9654045105],"type":"Point"}
}