{
  "type": "Feature",
  "properties": {
    "addr:full":"Kloosterstraat 4 Willebroek Antwerpen 2830",
    "addr:housenumber":"4",
    "addr:postcode":"2830",
    "addr:street":"Kloosterstraat",
    "iso:country":"BE",
    "sg:address":"Kloosterstraat 4",
    "sg:city":"Willebroek",
    "sg:classifiers":[
        {
            "category":"Retail",
            "subcategory":"Repair Shop",
            "type":"Services"
        }
    ],
    "sg:phone":"+32 3 886 21 66",
    "sg:postcode":"2830",
    "sg:province":"Antwerpen",
    "sg:tags":[
        "photographic",
        "equipment",
        "-",
        "accessory"
    ],
    "wof:name":"De Bondt Bvba",
    "wof:placetype":"venue"
},
  "geometry": {"coordinates":[4.3623781204,51.0627746582],"type":"Point"}
}