{
  "type": "Feature",
  "properties": {
    "addr:full":"Servaas Daemsstraat 17 Herentals (noorderwijk) Antwerpen 2200",
    "addr:housenumber":"17",
    "addr:postcode":"2200",
    "addr:street":"Servaas Daemsstraat",
    "iso:country":"BE",
    "sg:address":"Servaas Daemsstraat 17",
    "sg:city":"Herentals (noorderwijk)",
    "sg:classifiers":[
        {
            "category":"Real Estate",
            "subcategory":"Architect",
            "type":"Services"
        }
    ],
    "sg:phone":"+32 14 23 68 64",
    "sg:postcode":"2200",
    "sg:province":"Antwerpen",
    "wof:name":"Bruyndonckx W",
    "wof:placetype":"venue"
},
  "geometry": {"coordinates":[4.8372597694,51.1416511536],"type":"Point"}
}