{
  "type": "Feature",
  "properties": {
    "iso:country":"BE",
    "sg:address":"Bollestraat 60",
    "sg:city":"Overijse",
    "sg:orig_category":"Tuinen",
    "sg:phone":"+32 16 47 27 09",
    "sg:postcode":"3090",
    "sg:province":"Vlaams-Brabant",
    "wof:name":"Arbo Muyldermans",
    "wof:placetype":"venue"
},
  "geometry": {"coordinates":[4.5914998055,50.7695808411],"type":"Point"}
}