{
  "type": "Feature",
  "properties": {
    "iso:country":"BE",
    "sg:address":"Grotesteenweg 214",
    "sg:city":"Antwerpen",
    "sg:classifiers":[
        {
            "category":"Banks & Credit Unions",
            "subcategory":"Bank",
            "type":"Services"
        }
    ],
    "sg:phone":"+32 3 286 22 11",
    "sg:postcode":"2600",
    "sg:province":"Antwerpen",
    "wof:name":"Anhyp Savingsbank",
    "wof:placetype":"venue"
},
  "geometry": {"coordinates":[4.4174151421,51.1974411011],"type":"Point"}
}