{
  "type": "Feature",
  "properties": {
    "addr:full":"Pastoor Bauwenslaan 36 Wilrijk Antwerpen 2610",
    "addr:housenumber":"36",
    "addr:postcode":"2610",
    "addr:street":"Pastoor Bauwenslaan;Antwerpen",
    "iso:country":"BE",
    "sg:address":"Pastoor Bauwenslaan 36",
    "sg:city":"Wilrijk",
    "sg:classifiers":[
        {
            "category":"Communications",
            "subcategory":"Television Station",
            "type":"Services"
        }
    ],
    "sg:phone":"+32 3 825 76 66",
    "sg:postcode":"2610",
    "sg:province":"Antwerpen",
    "sg:tags":[
        "video",
        "audio",
        "verhuur"
    ],
    "wof:name":"D & D Video",
    "wof:placetype":"venue"
},
  "geometry": {"coordinates":[4.379527092,51.1785507202],"type":"Point"}
}