{
  "type": "Feature",
  "properties": {
    "addr:full":"Rue Du Parc 6 Mons (baudour) Hainaut 7331",
    "addr:housenumber":"6",
    "addr:postcode":"7331",
    "addr:street":"Rue Du Parc",
    "iso:country":"BE",
    "sg:address":"Rue Du Parc 6",
    "sg:city":"Mons (baudour)",
    "sg:classifiers":[
        {
            "category":"Professional",
            "subcategory":"Testing Lab",
            "type":"Services"
        }
    ],
    "sg:phone":"+32 65 64 12 64",
    "sg:postcode":"7331",
    "sg:province":"Hainaut",
    "sg:tags":[
        "chemist"
    ],
    "wof:name":"Jeuniaux",
    "wof:placetype":"venue"
},
  "geometry": {"coordinates":[3.9519090652,50.4571876526],"type":"Point"}
}