{
  "type": "Feature",
  "properties": {
    "addr:full":"Mosselstraat 20 Jabbeke West-Vlaanderen 8490",
    "addr:housenumber":"20",
    "addr:postcode":"8490",
    "addr:street":"Mosselstraat",
    "iso:country":"BE",
    "sg:address":"Mosselstraat 20",
    "sg:city":"Jabbeke",
    "sg:orig_category":"Zuivelproducten",
    "sg:phone":"+32 50 81 12 18",
    "sg:postcode":"8490",
    "sg:province":"West-Vlaanderen",
    "wof:name":"Plovie",
    "wof:placetype":"venue"
},
  "geometry": {"coordinates":[3.0736548901,51.1630058289],"type":"Point"}
}