{
  "type": "Feature",
  "properties": {
    "addr:full":"Rue Fran\u00c7ois-hittelet 20 Jemeppe-sur-sambre Namur 5190",
    "addr:housenumber":"20",
    "addr:postcode":"5190",
    "addr:street":"Rue Franc\u0327Ois-Hittelet",
    "iso:country":"BE",
    "sg:address":"Rue Fran\u00c7ois-hittelet 20",
    "sg:city":"Jemeppe-sur-sambre",
    "sg:classifiers":[
        {
            "category":"Personal",
            "subcategory":"Beauty Salon",
            "type":"Services"
        }
    ],
    "sg:phone":"+32 71 78 36 57",
    "sg:postcode":"5190",
    "sg:province":"Namur",
    "sg:tags":[
        "de",
        "coiffure"
    ],
    "wof:name":"Evelyne Paquet",
    "wof:placetype":"venue"
},
  "geometry": {"coordinates":[4.661011219,50.4531211853],"type":"Point"}
}