{
  "type": "Feature",
  "properties": {
    "iso:country":"BE",
    "sg:address":"Stationsstraat 21",
    "sg:city":"Alken",
    "sg:orig_category":"Goederenvervoer over de weg",
    "sg:phone":"+32 11 59 15 15",
    "sg:postcode":"3570",
    "sg:province":"Limburg",
    "wof:name":"Vandebroek C",
    "wof:placetype":"venue"
},
  "geometry": {"coordinates":[5.3042869568,50.8793029785],"type":"Point"}
}