{
  "type": "Feature",
  "properties": {
    "addr:full":"Pittemstraat 16 Meulebeke West-Vlaanderen 8760",
    "addr:housenumber":"16",
    "addr:postcode":"8760",
    "addr:street":"Pittemstraat",
    "iso:country":"BE",
    "sg:address":"Pittemstraat 16",
    "sg:city":"Meulebeke",
    "sg:classifiers":[
        {
            "category":"Communications",
            "subcategory":"News Services",
            "type":"Services"
        }
    ],
    "sg:phone":"+32 51 48 41 33",
    "sg:postcode":"8760",
    "sg:province":"West-Vlaanderen",
    "sg:tags":[
        "illustrator"
    ],
    "wof:name":"Witte (de)",
    "wof:placetype":"venue"
},
  "geometry": {"coordinates":[3.2881588936,50.9519996643],"type":"Point"}
}