{
  "type": "Feature",
  "properties": {
    "iso:country":"BE",
    "sg:address":"Doktoorstraat 16",
    "sg:city":"Alken",
    "sg:orig_category":"Sportclubs",
    "sg:phone":"+32 11 31 67 32",
    "sg:postcode":"3570",
    "sg:province":"Limburg",
    "wof:name":"A.c. Alken",
    "wof:placetype":"venue"
},
  "geometry": {"coordinates":[5.3021249771,50.8750762939],"type":"Point"}
}