{
  "type": "Feature",
  "properties": {
    "addr:full":"Rue Bonry 33 Neupr\u00e9 (neuville-en-condroz) Li\u00e8ge 4121",
    "addr:housenumber":"33",
    "addr:postcode":"4121",
    "addr:street":"Rue Bonry",
    "iso:country":"BE",
    "sg:address":"Rue Bonry 33",
    "sg:city":"Neupr\u00e9 (neuville-en-condroz)",
    "sg:classifiers":[
        {
            "category":"Arena",
            "subcategory":"Sports Club",
            "type":"Entertainment"
        }
    ],
    "sg:phone":"+32 4 371 40 25",
    "sg:postcode":"4121",
    "sg:province":"Li\u00e8ge",
    "sg:tags":[
        "federation"
    ],
    "wof:name":"F\u00e9d\u00e9ration Belge Des Caisses \u00e0 Savon",
    "wof:placetype":"venue"
},
  "geometry": {"coordinates":[5.4792218208,50.5409164429],"type":"Point"}
}