{
  "type": "Feature",
  "properties": {
    "iso:country":"BE",
    "sg:address":"Holleweg 70",
    "sg:city":"Kalmthout",
    "sg:orig_category":"Immobili\u00ebnkantoren",
    "sg:phone":"+32 3 667 10 80",
    "sg:postcode":"2920",
    "sg:province":"Antwerpen",
    "wof:name":"Mathijssen Immo",
    "wof:placetype":"venue"
},
  "geometry": {"coordinates":[4.5072197914,51.431098938],"type":"Point"}
}