{
  "type": "Feature",
  "properties": {
    "addr:full":"R De La Soile 25 Fernelmont Namur 5380",
    "addr:housenumber":"25",
    "addr:postcode":"5380",
    "iso:country":"BE",
    "sg:address":"R De La Soile 25",
    "sg:city":"Fernelmont",
    "sg:classifiers":[
        {
            "category":"Professional",
            "subcategory":"Secretarial Services",
            "type":"Services"
        }
    ],
    "sg:phone":"+32 475 82 28 61",
    "sg:postcode":"5380",
    "sg:province":"Namur",
    "sg:tags":[
        "firm"
    ],
    "wof:name":"Renard K",
    "wof:placetype":"venue"
},
  "geometry": {"coordinates":[4.9861078262,50.5531463623],"type":"Point"}
}