{
  "type": "Feature",
  "properties": {
    "iso:country":"BE",
    "sg:address":"Avenue De Koekelberg 53",
    "sg:city":"Sint-agatha-berchem/berchem-sainte-agathe",
    "sg:orig_category":"Boucheries",
    "sg:phone":"+32 2 468 37 38",
    "sg:postcode":"1082",
    "sg:province":"Bruxelles-Capitale",
    "wof:name":"Michel Buisson",
    "wof:placetype":"venue"
},
  "geometry": {"coordinates":[4.3045558929,50.8622016907],"type":"Point"}
}