{
  "type": "Feature",
  "properties": {
    "addr:full":"Halfuurdreef 36 Zedelgem West-Vlaanderen 8210",
    "addr:housenumber":"36",
    "addr:postcode":"8210",
    "addr:street":"Halfuurdreef",
    "iso:country":"BE",
    "sg:address":"Halfuurdreef 36",
    "sg:city":"Zedelgem",
    "sg:orig_category":"Boekhouders",
    "sg:phone":"+32 50 39 05 49",
    "sg:postcode":"8210",
    "sg:province":"West-Vlaanderen",
    "wof:name":"Christ Van Eeghem",
    "wof:placetype":"venue"
},
  "geometry": {"coordinates":[3.1458399296,51.1376457214],"type":"Point"}
}