{
  "type": "Feature",
  "properties": {
    "addr:full":"Chauss\u00e9e De Mons 144 Bruxelles (anderlecht) Bruxelles-Capitale 1070",
    "addr:housenumber":"144",
    "addr:postcode":"1070",
    "addr:street":"Chausse\u0301E De Mons",
    "iso:country":"BE",
    "sg:address":"Chauss\u00e9e De Mons 144",
    "sg:city":"Bruxelles (anderlecht)",
    "sg:classifiers":[
        {
            "category":"Autos & Motor Vehicles",
            "subcategory":"Automobile Sales",
            "type":"Retail Goods"
        }
    ],
    "sg:phone":"+32 476 22 59 28",
    "sg:postcode":"1070",
    "sg:province":"Bruxelles-Capitale",
    "sg:tags":[
        "car",
        "used",
        "-"
    ],
    "wof:name":"Sikama Sprl",
    "wof:placetype":"venue"
},
  "geometry": {"coordinates":[4.3315119743,50.8423194885],"type":"Point"}
}