{
  "type": "Feature",
  "properties": {
    "addr:full":"Broekstraat 26 Bonheiden Antwerpen 2820",
    "addr:housenumber":"26",
    "addr:postcode":"2820",
    "addr:street":"Broekstraat",
    "iso:country":"BE",
    "sg:address":"Broekstraat 26",
    "sg:city":"Bonheiden",
    "sg:orig_category":"Woningbouw",
    "sg:phone":"+32 15 33 18 58",
    "sg:postcode":"2820",
    "sg:province":"Antwerpen",
    "wof:name":"Fa. Mari\u00cbn",
    "wof:placetype":"venue"
},
  "geometry": {"coordinates":[4.5496602058,51.0218009949],"type":"Point"}
}