{
  "type": "Feature",
  "properties": {
    "addr:full":"Vismarkt 8 Leuven Vlaams-Brabant 3000",
    "addr:housenumber":"8",
    "addr:postcode":"3000",
    "addr:street":"Vismarkt",
    "iso:country":"BE",
    "sg:address":"Vismarkt 8",
    "sg:city":"Leuven",
    "sg:classifiers":[
        {
            "category":"Professional",
            "subcategory":"Lawyer & Legal Services",
            "type":"Services"
        }
    ],
    "sg:phone":"+32 16 22 78 81",
    "sg:postcode":"3000",
    "sg:province":"Vlaams-Brabant",
    "wof:name":"Melotte Hilde",
    "wof:placetype":"venue"
},
  "geometry": {"coordinates":[4.7003488541,50.8814239502],"type":"Point"}
}