{
  "type": "Feature",
  "properties": {
    "addr:full":"Rijksweg 352 Wielsbeke West-Vlaanderen 8710",
    "addr:housenumber":"352",
    "addr:postcode":"8710",
    "addr:street":"Rijksweg;West-Vlaanderen",
    "iso:country":"BE",
    "sg:address":"Rijksweg 352",
    "sg:city":"Wielsbeke",
    "sg:classifiers":[
        {
            "category":"Real Estate",
            "subcategory":"Real Estate Services",
            "type":"Services"
        }
    ],
    "sg:phone":"+32 56 60 27 38",
    "sg:postcode":"8710",
    "sg:province":"West-Vlaanderen",
    "wof:name":"Aankoopbemiddeling",
    "wof:placetype":"venue"
},
  "geometry": {"coordinates":[3.3699030876,50.9120788574],"type":"Point"}
}