{
  "type": "Feature",
  "properties": {
    "addr:full":"Rue Brogniez 35 Bruxelles (anderlecht) Bruxelles-Capitale 1070",
    "addr:housenumber":"35",
    "addr:postcode":"1070",
    "addr:street":"Rue Brogniez",
    "iso:country":"BE",
    "sg:address":"Rue Brogniez 35",
    "sg:city":"Bruxelles (anderlecht)",
    "sg:classifiers":[
        {
            "category":"Real Estate",
            "subcategory":"Real Estate Services",
            "type":"Services"
        }
    ],
    "sg:phone":"+32 2 343 36 70",
    "sg:postcode":"1070",
    "sg:province":"Bruxelles-Capitale",
    "wof:name":"B.p.o. Company",
    "wof:placetype":"venue"
},
  "geometry": {"coordinates":[4.3375148773,50.8421821594],"type":"Point"}
}