{
  "type": "Feature",
  "properties": {
    "addr:full":"Avelgemstraat 59 Zwevegem West-Vlaanderen 8550",
    "addr:housenumber":"59",
    "addr:postcode":"8550",
    "addr:street":"Avelgemstraat",
    "iso:country":"BE",
    "sg:address":"Avelgemstraat 59",
    "sg:city":"Zwevegem",
    "sg:orig_category":"Secr\u00e9tariats",
    "sg:phone":"+32 56 75 97 20",
    "sg:postcode":"8550",
    "sg:province":"West-Vlaanderen",
    "wof:name":"Screen+ Grafical",
    "wof:placetype":"venue"
},
  "geometry": {"coordinates":[3.3369019032,50.8092575073],"type":"Point"}
}