{
  "type": "Feature",
  "properties": {
    "addr:full":"Hoogstraat 15 Zele Oost-Vlaanderen 9240",
    "addr:housenumber":"15",
    "addr:postcode":"9240",
    "addr:street":"Hoogstraat",
    "iso:country":"BE",
    "sg:address":"Hoogstraat 15",
    "sg:city":"Zele",
    "sg:orig_category":"Schilders",
    "sg:phone":"+32 52 44 85 49",
    "sg:postcode":"9240",
    "sg:province":"Oost-Vlaanderen",
    "wof:name":"De Strooper",
    "wof:placetype":"venue"
},
  "geometry": {"coordinates":[4.0076389313,51.0654373169],"type":"Point"}
}