{
  "type": "Feature",
  "properties": {
    "addr:full":"Egide Walschaertsstraat 2a Mechelen Antwerpen 2800",
    "addr:housenumber":"2a",
    "addr:postcode":"2800",
    "addr:street":"Egide Walschaertsstraat",
    "iso:country":"BE",
    "sg:address":"Egide Walschaertsstraat 2a",
    "sg:city":"Mechelen",
    "sg:classifiers":[
        {
            "category":"Retail",
            "subcategory":"Auto Repair",
            "type":"Services"
        }
    ],
    "sg:phone":"+32 15 42 30 00",
    "sg:postcode":"2800",
    "sg:province":"Antwerpen",
    "sg:tags":[
        "automobile-body"
    ],
    "wof:name":"Mechels Karrosseriebedrijf",
    "wof:placetype":"venue"
},
  "geometry": {"coordinates":[4.4642071724,51.0096168518],"type":"Point"}
}