{
  "type": "Feature",
  "properties": {
    "addr:full":"Kortrijksesteenweg 401 Harelbeke West-Vlaanderen 8530",
    "addr:housenumber":"401",
    "addr:postcode":"8530",
    "addr:street":"Kortrijksesteenweg",
    "iso:country":"BE",
    "sg:address":"Kortrijksesteenweg 401",
    "sg:city":"Harelbeke",
    "sg:classifiers":[
        {
            "category":"Autos & Motor Vehicles",
            "subcategory":"Automobile Sales",
            "type":"Retail Goods"
        }
    ],
    "sg:phone":"+32 56 20 10 00",
    "sg:postcode":"8530",
    "sg:province":"West-Vlaanderen",
    "sg:tags":[
        "car",
        "used",
        "-"
    ],
    "wof:name":"Vanneste Service",
    "wof:placetype":"venue"
},
  "geometry": {"coordinates":[3.2871038914,50.8395805359],"type":"Point"}
}