{
  "type": "Feature",
  "properties": {
    "iso:country":"BE",
    "sg:address":"Mekeirleweg 15",
    "sg:city":"Anzegem",
    "sg:orig_category":"Software ontwikkeling and ontwerp",
    "sg:phone":"+32 56 78 24 01",
    "sg:postcode":"8570",
    "sg:province":"West-Vlaanderen",
    "wof:name":"Texicom",
    "wof:placetype":"venue"
},
  "geometry": {"coordinates":[3.3932158947,50.8315124512],"type":"Point"}
}