{
  "type": "Feature",
  "properties": {
    "iso:country":"BE",
    "sg:address":"Rue De Mons 38",
    "sg:city":"Braine-le-comte",
    "sg:classifiers":[
        {
            "category":"Home & Garden",
            "subcategory":"Household Appliances",
            "type":"Retail Goods"
        }
    ],
    "sg:phone":"+32 67 55 20 62",
    "sg:postcode":"7090",
    "sg:province":"Hainaut",
    "sg:tags":[
        "repair",
        "mainten",
        "-",
        "electric"
    ],
    "wof:name":"Maison Stevens",
    "wof:placetype":"venue"
},
  "geometry": {"coordinates":[4.134308815,50.6086082458],"type":"Point"}
}