{
  "type": "Feature",
  "properties": {
    "iso:country":"BE",
    "sg:address":"Herpelsstraat 102",
    "sg:city":"Harelbeke",
    "sg:classifiers":[
        {
            "category":"Government",
            "subcategory":"Fire Station",
            "type":"Public Place"
        }
    ],
    "sg:phone":"+32 56 32 55 90",
    "sg:postcode":"8530",
    "sg:province":"West-Vlaanderen",
    "sg:tags":[
        "equipment",
        "protection"
    ],
    "wof:name":"Brandweermaterieel D. V Mol Bvba",
    "wof:placetype":"venue"
},
  "geometry": {"coordinates":[3.3292639256,50.8549575806],"type":"Point"}
}