{
  "type": "Feature",
  "properties": {
    "addr:full":"Dascottelei 36 Antwerpen Antwerpen 2100",
    "addr:housenumber":"36",
    "addr:postcode":"2100",
    "addr:street":"Dascottelei",
    "iso:country":"BE",
    "sg:address":"Dascottelei 36",
    "sg:city":"Antwerpen",
    "sg:orig_category":"Ecoles de pilotage de bateaux and d\u00b4avions",
    "sg:phone":"+32 3 321 09 19",
    "sg:postcode":"2100",
    "sg:province":"Antwerpen",
    "wof:name":"Ceblo",
    "wof:placetype":"venue"
},
  "geometry": {"coordinates":[4.4586100578,51.2203941345],"type":"Point"}
}