{
  "type": "Feature",
  "properties": {
    "iso:country":"BE",
    "sg:address":"Rue Simon Martin 30",
    "sg:city":"Namur (champion - Cognel\u00e9e)",
    "sg:classifiers":[
        {
            "category":"Building & Trades",
            "subcategory":"Landscaping Services",
            "type":"Services"
        }
    ],
    "sg:phone":"+32 81 21 10 45",
    "sg:postcode":"5020",
    "sg:province":"Namur",
    "sg:tags":[
        "forestry"
    ],
    "wof:name":"Rondia B",
    "wof:placetype":"venue"
},
  "geometry": {"coordinates":[4.9040322304,50.4956817627],"type":"Point"}
}