{
  "type": "Feature",
  "properties": {
    "iso:country":"BE",
    "sg:address":"Rue Du Culot 8",
    "sg:city":"Couvin",
    "sg:orig_category":"Paramedische behandelingen",
    "sg:phone":"+32 60 34 67 61",
    "sg:postcode":"5660",
    "sg:province":"Namur",
    "wof:name":"M.c. Van Alfaene",
    "wof:placetype":"venue"
},
  "geometry": {"coordinates":[4.4088549614,50.0655212402],"type":"Point"}
}