{
  "type": "Feature",
  "properties": {
    "addr:full":"Tarwestraat 35 Anderlecht/anderlecht Bruxelles-Capitale 1070",
    "addr:housenumber":"35",
    "addr:postcode":"1070",
    "addr:street":"Tarwestraat",
    "iso:country":"BE",
    "sg:address":"Tarwestraat 35",
    "sg:city":"Anderlecht/anderlecht",
    "sg:orig_category":"Loodgieterij, verwarming and sanitaire installaties",
    "sg:phone":"+32 2 527 06 73",
    "sg:postcode":"1070",
    "sg:province":"Bruxelles-Capitale",
    "wof:name":"J.p. Sanitaire",
    "wof:placetype":"venue"
},
  "geometry": {"coordinates":[4.2586760521,50.8295288086],"type":"Point"}
}