{
  "type": "Feature",
  "properties": {
    "addr:full":"Jokeven 1 Arendonk Antwerpen 2370",
    "addr:housenumber":"1",
    "addr:postcode":"2370",
    "addr:street":"Jokeven",
    "iso:country":"BE",
    "sg:address":"Jokeven 1",
    "sg:city":"Arendonk",
    "sg:orig_category":"Non-Classified Establishments",
    "sg:phone":"+32 14 67 73 41",
    "sg:postcode":"2370",
    "sg:province":"Antwerpen",
    "wof:name":"Moons Nv",
    "wof:placetype":"venue"
},
  "geometry": {"coordinates":[5.109899044,51.3440361023],"type":"Point"}
}