{
  "type": "Feature",
  "properties": {
    "addr:full":"Rue Neuve-chauss\u00c9e 113 Peruwelz Hainaut 7600",
    "addr:housenumber":"113",
    "addr:postcode":"7600",
    "addr:street":"Rue Neuve-Chausse\u0301E;Hainaut",
    "iso:country":"BE",
    "sg:address":"Rue Neuve-chauss\u00c9e 113",
    "sg:city":"Peruwelz",
    "sg:orig_category":"M\u00e9decins and sp\u00e9cialistes",
    "sg:phone":"+32 69 77 21 93",
    "sg:postcode":"7600",
    "sg:province":"Hainaut",
    "wof:name":"Claude Quinet",
    "wof:placetype":"venue"
},
  "geometry": {"coordinates":[3.6002790928,50.5184326172],"type":"Point"}
}