{
  "type": "Feature",
  "properties": {
    "addr:full":"Mechelsesteenweg 37 Zaventem (sterrebeek) Vlaams-Brabant 1933",
    "addr:housenumber":"37",
    "addr:postcode":"1933",
    "addr:street":"Mechelsesteenweg",
    "iso:country":"BE",
    "sg:address":"Mechelsesteenweg 37",
    "sg:city":"Zaventem (sterrebeek)",
    "sg:classifiers":[
        {
            "category":"Manufacturing",
            "subcategory":"Wood Products",
            "type":"Manufacturing & Wholesale Goods"
        }
    ],
    "sg:phone":"+32 2 731 51 26",
    "sg:postcode":"1933",
    "sg:province":"Vlaams-Brabant",
    "sg:tags":[
        "firewood"
    ],
    "wof:name":"Del Monte G",
    "wof:placetype":"venue"
},
  "geometry": {"coordinates":[4.5072221756,50.8514556885],"type":"Point"}
}