{
  "type": "Feature",
  "properties": {
    "iso:country":"BE",
    "sg:address":"Quai De Rome 54",
    "sg:city":"Li\u00e8ge 1",
    "sg:classifiers":[
        {
            "category":"Health Services",
            "subcategory":"Doctor",
            "type":"Services"
        }
    ],
    "sg:phone":"+32 4 253 33 54",
    "sg:postcode":"4000",
    "sg:province":"Li\u00e8ge",
    "sg:tags":[
        "medicinephysicians",
        "surgeon"
    ],
    "wof:name":"Delcour Jean-pierre",
    "wof:placetype":"venue"
},
  "geometry": {"coordinates":[5.5769600868,50.6220397949],"type":"Point"}
}