{
  "type": "Feature",
  "properties": {
    "iso:country":"BE",
    "sg:address":"Zwartzustersstraat 24-26",
    "sg:city":"Antwerpen",
    "sg:classifiers":[
        {
            "category":"Professional",
            "subcategory":"Engineering",
            "type":"Services"
        }
    ],
    "sg:phone":"+32 3 234 06 86",
    "sg:postcode":"2000",
    "sg:province":"Antwerpen",
    "sg:tags":[
        "-"
    ],
    "wof:name":"Opdesign Nv",
    "wof:placetype":"venue"
},
  "geometry": {"coordinates":[4.4018697739,51.2233886719],"type":"Point"}
}