{
  "type": "Feature",
  "properties": {
    "iso:country":"BE",
    "sg:address":"Rue Des Chartreux 7",
    "sg:city":"Fleron",
    "sg:orig_category":"Eclairage et \u00e9quipements du foyer",
    "sg:phone":"+32 4 358 91 57",
    "sg:postcode":"4621",
    "sg:province":"Li\u00e8ge",
    "wof:name":"Regine Lhoest",
    "wof:placetype":"venue"
},
  "geometry": {"coordinates":[5.6968450546,50.6343078613],"type":"Point"}
}