{
  "type": "Feature",
  "properties": {
    "addr:full":"Route Charlemagne 10b Chimay (baileux) Hainaut 6464",
    "addr:housenumber":"10b",
    "addr:postcode":"6464",
    "addr:street":"Route Charlemagne",
    "iso:country":"BE",
    "sg:address":"Route Charlemagne 10b",
    "sg:city":"Chimay (baileux)",
    "sg:classifiers":[
        {
            "category":"Wholesale",
            "subcategory":"Meat",
            "type":"Manufacturing & Wholesale Goods"
        }
    ],
    "sg:phone":"+32 60 41 41 81",
    "sg:postcode":"6464",
    "sg:province":"Hainaut",
    "sg:tags":[
        "whol",
        "-"
    ],
    "wof:name":"Bvh Meat",
    "wof:placetype":"venue"
},
  "geometry": {"coordinates":[4.3817811012,50.0356903076],"type":"Point"}
}