{
  "type": "Feature",
  "properties": {
    "addr:full":"Route De La Hesbaye 206 Eghezee Namur 5310",
    "addr:housenumber":"206",
    "addr:postcode":"5310",
    "addr:street":"Route De La Hesbaye;Namur",
    "iso:country":"BE",
    "sg:address":"Route De La Hesbaye 206",
    "sg:city":"Eghezee",
    "sg:orig_category":"Entretien and r\u00e9parations de voitures",
    "sg:phone":"+32 81 81 13 98",
    "sg:postcode":"5310",
    "sg:province":"Namur",
    "wof:name":"Paul Simonet",
    "wof:placetype":"venue"
},
  "geometry": {"coordinates":[4.9302082062,50.6176643372],"type":"Point"}
}