{
  "type": "Feature",
  "properties": {
    "iso:country":"BE",
    "sg:address":"Sint-annaweg 6ba",
    "sg:city":"Haaltert",
    "sg:orig_category":"Matrassen Fab",
    "sg:phone":"+32 54 33 16 57",
    "sg:postcode":"9450",
    "sg:province":"Oost-Vlaanderen",
    "wof:name":"Timmy-aero Sleep",
    "wof:placetype":"venue"
},
  "geometry": {"coordinates":[4.0150089264,50.8704719543],"type":"Point"}
}