{
  "type": "Feature",
  "properties": {
    "iso:country":"BE",
    "sg:address":"Voormuide 93",
    "sg:city":"Gent",
    "sg:classifiers":[
        {
            "category":"Utilities",
            "subcategory":"Electric",
            "type":"Services"
        }
    ],
    "sg:phone":"+32 9 225 57 27",
    "sg:postcode":"9000",
    "sg:province":"Oost-Vlaanderen",
    "sg:tags":[
        "electrical",
        "ship",
        "-"
    ],
    "wof:name":"Electro Zeeland",
    "wof:placetype":"venue"
},
  "geometry": {"coordinates":[3.729640007,51.0695114136],"type":"Point"}
}