{
  "type": "Feature",
  "properties": {
    "iso:country":"BE",
    "sg:address":"Ijzerlaan 25",
    "sg:city":"Middelkerke",
    "sg:orig_category":"Installation \u00e9lectrique r\u00e9sidentielle",
    "sg:phone":"+32 59 30 21 65",
    "sg:postcode":"8430",
    "sg:province":"West-Vlaanderen",
    "wof:name":"Klusjesdienst Geert",
    "wof:placetype":"venue"
},
  "geometry": {"coordinates":[2.8141050339,51.182056427],"type":"Point"}
}