{
  "type": "Feature",
  "properties": {
    "addr:full":"Moresneter Strasse 81 Kelmis Li\u00e8ge 4720",
    "addr:housenumber":"81",
    "addr:postcode":"4720",
    "addr:street":"Moresneter Strasse",
    "iso:country":"BE",
    "sg:address":"Moresneter Strasse 81",
    "sg:city":"Kelmis",
    "sg:classifiers":[
        {
            "category":"Retail",
            "subcategory":"Auto Repair",
            "type":"Services"
        }
    ],
    "sg:phone":"+32 87 65 88 33",
    "sg:postcode":"4720",
    "sg:province":"Li\u00e8ge",
    "sg:tags":[
        "automobile-body"
    ],
    "wof:name":"Lemmens Sprl",
    "wof:placetype":"venue"
},
  "geometry": {"coordinates":[6.008728981,50.7223815918],"type":"Point"}
}