{
  "type": "Feature",
  "properties": {
    "addr:full":"Guido Gezellestraat 45 Izegem West-Vlaanderen 8870",
    "addr:housenumber":"45",
    "addr:postcode":"8870",
    "addr:street":"Guido Gezellestraat",
    "iso:country":"BE",
    "sg:address":"Guido Gezellestraat 45",
    "sg:city":"Izegem",
    "sg:orig_category":"Non-Classified Establishments",
    "sg:phone":"+32 51 31 37 08",
    "sg:postcode":"8870",
    "sg:province":"West-Vlaanderen",
    "wof:name":"Coffez Nv",
    "wof:placetype":"venue"
},
  "geometry": {"coordinates":[3.2207250595,50.9260826111],"type":"Point"}
}