{
  "type": "Feature",
  "properties": {
    "addr:full":"Klokkeputstraat 61 Roeselare West-Vlaanderen 8800",
    "addr:housenumber":"61",
    "addr:postcode":"8800",
    "addr:street":"Klokkeputstraat",
    "iso:country":"BE",
    "sg:address":"Klokkeputstraat 61",
    "sg:city":"Roeselare",
    "sg:orig_category":"Activit\u00e9s r\u00e9cr\u00e9atives diverses",
    "sg:phone":"+32 51 22 21 93",
    "sg:postcode":"8800",
    "sg:province":"West-Vlaanderen",
    "wof:name":"Kring Roeselaarse Post",
    "wof:placetype":"venue"
},
  "geometry": {"coordinates":[3.1051249504,50.9621162415],"type":"Point"}
}