{
  "type": "Feature",
  "properties": {
    "iso:country":"BE",
    "sg:address":"Rue Ferrer 152",
    "sg:city":"Charleroi",
    "sg:orig_category":"Reliure and finition",
    "sg:phone":"+32 71 32 40 21",
    "sg:postcode":"6061",
    "sg:province":"Hainaut",
    "wof:name":"Fe. De Vulder",
    "wof:placetype":"venue"
},
  "geometry": {"coordinates":[4.4686598778,50.4109115601],"type":"Point"}
}