{
  "type": "Feature",
  "properties": {
    "addr:full":"Paanderstraat 93 Meulebeke West-Vlaanderen 8760",
    "addr:housenumber":"93",
    "addr:postcode":"8760",
    "addr:street":"Paanderstraat",
    "iso:country":"BE",
    "sg:address":"Paanderstraat 93",
    "sg:city":"Meulebeke",
    "sg:orig_category":"Herstellingen and onderhoud van auto's Voertuigen",
    "sg:phone":"+32 51 48 97 00",
    "sg:postcode":"8760",
    "sg:province":"West-Vlaanderen",
    "wof:name":"Garage Boucquet",
    "wof:placetype":"venue"
},
  "geometry": {"coordinates":[3.3128008842,50.9409980774],"type":"Point"}
}