{
  "type": "Feature",
  "properties": {
    "addr:full":"Leliegaarde 20 Asse Vlaams-Brabant 1730",
    "addr:housenumber":"20",
    "addr:postcode":"1730",
    "addr:street":"Leliegaarde",
    "iso:country":"BE",
    "sg:address":"Leliegaarde 20",
    "sg:city":"Asse",
    "sg:orig_category":"Agences de publicit\u00e9",
    "sg:phone":"+32 2 467 53 50",
    "sg:postcode":"1730",
    "sg:province":"Vlaams-Brabant",
    "wof:name":"Hobo Faam Groep",
    "wof:placetype":"venue"
},
  "geometry": {"coordinates":[4.2773489952,50.8864707947],"type":"Point"}
}