{
  "type": "Feature",
  "properties": {
    "addr:full":"Hellestraat 45ba Stekene Oost-Vlaanderen 9190",
    "addr:housenumber":"45ba",
    "addr:postcode":"9190",
    "addr:street":"Hellestraat",
    "iso:country":"BE",
    "sg:address":"Hellestraat 45ba",
    "sg:city":"Stekene",
    "sg:orig_category":"M\u00e9decins and sp\u00e9cialistes",
    "sg:phone":"+32 3 779 95 27",
    "sg:postcode":"9190",
    "sg:province":"Oost-Vlaanderen",
    "wof:name":"Veerle Goemans",
    "wof:placetype":"venue"
},
  "geometry": {"coordinates":[4.0366001129,51.2251396179],"type":"Point"}
}