{
  "type": "Feature",
  "properties": {
    "iso:country":"BE",
    "sg:address":"Kapelaan Staslaan 1",
    "sg:city":"Wommelgem",
    "sg:orig_category":"Woningbouw",
    "sg:phone":"+32 3 366 21 29",
    "sg:postcode":"2160",
    "sg:province":"Antwerpen",
    "wof:name":"Van Dijck",
    "wof:placetype":"venue"
},
  "geometry": {"coordinates":[4.5021800995,51.1969070435],"type":"Point"}
}