{
  "type": "Feature",
  "properties": {
    "iso:country":"BE",
    "sg:address":"Rue Kessels 4",
    "sg:city":"Bruxelles (schaerbeek)",
    "sg:classifiers":[
        {
            "category":"Social Services",
            "type":"Services"
        }
    ],
    "sg:phone":"+32 2 216 09 08",
    "sg:postcode":"1030",
    "sg:province":"Bruxelles-Capitale",
    "wof:name":"Al-anon Asbl",
    "wof:placetype":"venue"
},
  "geometry": {"coordinates":[4.3780341148,50.8612556458],"type":"Point"}
}