{
  "type": "Feature",
  "properties": {
    "addr:full":"Ezelstraat 64 Brugge West-Vlaanderen 8000",
    "addr:housenumber":"64",
    "addr:postcode":"8000",
    "addr:street":"Ezelstraat",
    "iso:country":"BE",
    "sg:address":"Ezelstraat 64",
    "sg:city":"Brugge",
    "sg:classifiers":[
        {
            "category":"Building & Trades",
            "subcategory":"Locksmith",
            "type":"Services"
        }
    ],
    "sg:phone":"+32 50 34 24 38",
    "sg:postcode":"8000",
    "sg:province":"West-Vlaanderen",
    "sg:tags":[
        "lock",
        "key"
    ],
    "wof:name":"Algemene Slotenmaker Johan Brugge",
    "wof:placetype":"venue"
},
  "geometry": {"coordinates":[3.2180509567,51.2137031555],"type":"Point"}
}