{
  "type": "Feature",
  "properties": {
    "addr:full":"Rue De La Bienvenue 13 Anderlecht Bruxelles-Capitale 1070",
    "addr:housenumber":"13",
    "addr:postcode":"1070",
    "addr:street":"Rue De La Bienvenue",
    "iso:country":"BE",
    "sg:address":"Rue De La Bienvenue 13",
    "sg:city":"Anderlecht",
    "sg:orig_category":"Epuration des eaux. Mat\u00e9riel pour plomberie and chauffage Mat\u00e9riaux de construction Gr",
    "sg:phone":"+32 2 524 11 05",
    "sg:postcode":"1070",
    "sg:province":"Bruxelles-Capitale",
    "wof:name":"Facq",
    "wof:placetype":"venue"
},
  "geometry": {"coordinates":[4.3057599068,50.8140487671],"type":"Point"}
}