{
  "type": "Feature",
  "properties": {
    "addr:full":"Rue De La Source 46 Sint-gillis Bruxelles-Capitale 1060",
    "addr:housenumber":"46",
    "addr:postcode":"1060",
    "addr:street":"Rue De La Source",
    "iso:country":"BE",
    "sg:address":"Rue De La Source 46",
    "sg:city":"Sint-gillis",
    "sg:orig_category":"Woningbouw",
    "sg:phone":"+32 2 688 28 76",
    "sg:postcode":"1060",
    "sg:province":"Bruxelles-Capitale",
    "wof:name":"B\u00c2timents & Activations",
    "wof:placetype":"venue"
},
  "geometry": {"coordinates":[4.3521261215,50.831451416],"type":"Point"}
}