{
  "type": "Feature",
  "properties": {
    "iso:country":"BE",
    "sg:address":"Gentweg 49",
    "sg:city":"Herzele (steenhuize-wijnhuize)",
    "sg:classifiers":[
        {
            "category":"Bars & Pubs",
            "type":"Food & Drink"
        }
    ],
    "sg:phone":"+32 54 50 03 05",
    "sg:postcode":"9550",
    "sg:province":"Oost-Vlaanderen",
    "wof:name":"Landhuis (het)",
    "wof:placetype":"venue"
},
  "geometry": {"coordinates":[3.8629159927,50.8501930237],"type":"Point"}
}