{
  "type": "Feature",
  "properties": {
    "addr:full":"Korte Gasthuisstraat 55 Turnhout Antwerpen 2300",
    "addr:housenumber":"55",
    "addr:postcode":"2300",
    "addr:street":"Korte Gasthuisstraat",
    "iso:country":"BE",
    "sg:address":"Korte Gasthuisstraat 55",
    "sg:city":"Turnhout",
    "sg:orig_category":"Foto-uitrusting Fotografen and fotostudio's Telecommunicatieapparaten",
    "sg:phone":"+32 14 42 12 53",
    "sg:postcode":"2300",
    "sg:province":"Antwerpen",
    "wof:name":"Studio 73",
    "wof:placetype":"venue"
},
  "geometry": {"coordinates":[4.9440879822,51.3222999573],"type":"Point"}
}