{
  "type": "Feature",
  "properties": {
    "iso:country":"BE",
    "sg:address":"Maalse Steenweg 335",
    "sg:city":"Brugge (sint-kruis)",
    "sg:classifiers":[
        {
            "category":"Real Estate",
            "subcategory":"Architect",
            "type":"Services"
        }
    ],
    "sg:phone":"+32 50 35 19 24",
    "sg:postcode":"8310",
    "sg:province":"West-Vlaanderen",
    "wof:name":"Vyncke E",
    "wof:placetype":"venue"
},
  "geometry": {"coordinates":[3.2575070858,51.2136764526],"type":"Point"}
}