{
  "type": "Feature",
  "properties": {
    "addr:full":"Pastoor Primsstraat 2 Zemst (weerde) Vlaams-Brabant 1982",
    "addr:housenumber":"2",
    "addr:postcode":"1982",
    "addr:street":"Pastoor Primsstraat",
    "iso:country":"BE",
    "sg:address":"Pastoor Primsstraat 2",
    "sg:city":"Zemst (weerde)",
    "sg:classifiers":[
        {
            "category":"Freight",
            "type":"Transportation"
        }
    ],
    "sg:phone":"+32 15 61 45 99",
    "sg:postcode":"1982",
    "sg:province":"Vlaams-Brabant",
    "sg:tags":[
        "-",
        "transport"
    ],
    "wof:name":"Piron",
    "wof:placetype":"venue"
},
  "geometry": {"coordinates":[4.4734511375,50.9734268188],"type":"Point"}
}