{
  "type": "Feature",
  "properties": {
    "addr:full":"Kerkhofstraat 40 Avelgem West-Vlaanderen 8580",
    "addr:housenumber":"40",
    "addr:postcode":"8580",
    "addr:street":"Kerkhofstraat",
    "iso:country":"BE",
    "sg:address":"Kerkhofstraat 40",
    "sg:city":"Avelgem",
    "sg:orig_category":"Architectes",
    "sg:phone":"+32 56 64 52 31",
    "sg:postcode":"8580",
    "sg:province":"West-Vlaanderen",
    "wof:name":"Sylvie Van Enys",
    "wof:placetype":"venue"
},
  "geometry": {"coordinates":[3.4459750652,50.7796783447],"type":"Point"}
}