{
  "type": "Feature",
  "properties": {
    "iso:country":"BE",
    "sg:address":"Petit Floriveau 10",
    "sg:city":"Philippeville (jamiolle)",
    "sg:classifiers":[
        {
            "category":"Building & Trades",
            "subcategory":"Construction",
            "type":"Services"
        }
    ],
    "sg:phone":"+32 71 66 76 35",
    "sg:postcode":"5600",
    "sg:province":"Namur",
    "sg:tags":[
        "installation",
        "-",
        "central",
        "heating"
    ],
    "wof:name":"De Buck Sprl",
    "wof:placetype":"venue"
},
  "geometry": {"coordinates":[4.508562088,50.2069358826],"type":"Point"}
}