{
  "type": "Feature",
  "properties": {
    "addr:full":"Staatsbaan 25 Kortemark West-Vlaanderen 8610",
    "addr:housenumber":"25",
    "addr:postcode":"8610",
    "addr:street":"Staatsbaan",
    "iso:country":"BE",
    "sg:address":"Staatsbaan 25",
    "sg:city":"Kortemark",
    "sg:orig_category":"Boissons",
    "sg:phone":"+32 51 56 73 93",
    "sg:postcode":"8610",
    "sg:province":"West-Vlaanderen",
    "wof:name":"Franky Mommerency",
    "wof:placetype":"venue"
},
  "geometry": {"coordinates":[3.060172081,51.0253181458],"type":"Point"}
}