{
  "type": "Feature",
  "properties": {
    "iso:country":"BE",
    "sg:address":"Koning Albertlei 4",
    "sg:city":"Kapellen",
    "sg:classifiers":[
        {
            "category":"Food & Beverages",
            "subcategory":"Fruits & Vegetables",
            "type":"Retail Goods"
        }
    ],
    "sg:phone":"+32 3 664 71 30",
    "sg:postcode":"2950",
    "sg:province":"Antwerpen",
    "sg:tags":[
        "l\u00e9gumes"
    ],
    "wof:name":"De Wase Fruitkorf",
    "wof:placetype":"venue"
},
  "geometry": {"coordinates":[4.4336628914,51.313835144],"type":"Point"}
}