{
  "type": "Feature",
  "properties": {
    "addr:full":"Moreelstraat 20 Denderleeuw Oost-Vlaanderen 9470",
    "addr:housenumber":"20",
    "addr:postcode":"9470",
    "addr:street":"Moreelstraat",
    "iso:country":"BE",
    "sg:address":"Moreelstraat 20",
    "sg:city":"Denderleeuw",
    "sg:orig_category":"Blanchisseries and teintureries",
    "sg:phone":"+32 53 66 89 63",
    "sg:postcode":"9470",
    "sg:province":"Oost-Vlaanderen",
    "wof:name":"Wasserij Miele",
    "wof:placetype":"venue"
},
  "geometry": {"coordinates":[4.0814127922,50.8816184998],"type":"Point"}
}