{
  "type": "Feature",
  "properties": {
    "iso:country":"BE",
    "sg:address":"Rue L\u00c9on Xiii 13",
    "sg:city":"Brussel/bruxelles",
    "sg:orig_category":"Enseignement maternel and primaire",
    "sg:phone":"+32 2 268 21 61",
    "sg:postcode":"1120",
    "sg:province":"Bruxelles-Capitale",
    "wof:name":"E.f.l. St.nicolas",
    "wof:placetype":"venue"
},
  "geometry": {"coordinates":[4.3863101006,50.8936576843],"type":"Point"}
}