{
  "type": "Feature",
  "properties": {
    "addr:full":"Koosterstraat 2 Alken Limburg 3570",
    "addr:housenumber":"2",
    "addr:postcode":"3570",
    "addr:street":"Koosterstraat",
    "iso:country":"BE",
    "sg:address":"Koosterstraat 2",
    "sg:city":"Alken",
    "sg:orig_category":"Instituts de beaut\u00e9",
    "sg:phone":"+32 11 31 20 23",
    "sg:postcode":"3570",
    "sg:province":"Limburg",
    "wof:name":"Instituut Sandra",
    "wof:placetype":"venue"
},
  "geometry": {"coordinates":[5.273665905,50.8986968994],"type":"Point"}
}