{
  "type": "Feature",
  "properties": {
    "iso:country":"BE",
    "sg:address":"Diestersteenweg 35",
    "sg:city":"Sint-truiden",
    "sg:classifiers":[
        {
            "category":"Personal",
            "subcategory":"Beauty Salon",
            "type":"Services"
        }
    ],
    "sg:phone":"+32 11 67 49 69",
    "sg:postcode":"3800",
    "sg:province":"Limburg",
    "wof:name":"Masculin-f\u00e9minin",
    "wof:placetype":"venue"
},
  "geometry": {"coordinates":[5.1854858398,50.8219680786],"type":"Point"}
}