{
  "type": "Feature",
  "properties": {
    "addr:full":"Pieter Coutereelstraat 52 Leuven Vlaams-Brabant 3000",
    "addr:housenumber":"52",
    "addr:postcode":"3000",
    "addr:street":"Pieter Coutereelstraat",
    "iso:country":"BE",
    "sg:address":"Pieter Coutereelstraat 52",
    "sg:city":"Leuven",
    "sg:orig_category":"M\u00e9decins and sp\u00e9cialistes",
    "sg:phone":"+32 16 20 12 46",
    "sg:postcode":"3000",
    "sg:province":"Vlaams-Brabant",
    "wof:name":"Anne Debeer",
    "wof:placetype":"venue"
},
  "geometry": {"coordinates":[4.6952939034,50.8821754456],"type":"Point"}
}