{
  "type": "Feature",
  "properties": {
    "addr:full":"Ambroossteenweg 69 Zemst Vlaams-Brabant 1981",
    "addr:housenumber":"69",
    "addr:postcode":"1981",
    "addr:street":"Ambroossteenweg;Vlaams-Brabant",
    "iso:country":"BE",
    "sg:address":"Ambroossteenweg 69",
    "sg:city":"Zemst",
    "sg:orig_category":"M\u00e9decins and sp\u00e9cialistes",
    "sg:phone":"+32 15 61 11 99",
    "sg:postcode":"1981",
    "sg:province":"Vlaams-Brabant",
    "wof:name":"S. Smout",
    "wof:placetype":"venue"
},
  "geometry": {"coordinates":[4.4968981743,50.9940757751],"type":"Point"}
}