{
  "type": "Feature",
  "properties": {
    "addr:full":"Provinciebaan 28ba Ledegem West-Vlaanderen 8880",
    "addr:housenumber":"28ba",
    "addr:postcode":"8880",
    "addr:street":"Provinciebaan",
    "iso:country":"BE",
    "sg:address":"Provinciebaan 28ba",
    "sg:city":"Ledegem",
    "sg:orig_category":"Boissons",
    "sg:phone":"+32 56 50 90 37",
    "sg:postcode":"8880",
    "sg:province":"West-Vlaanderen",
    "wof:name":"Vandoorne",
    "wof:placetype":"venue"
},
  "geometry": {"coordinates":[3.1098530293,50.8630409241],"type":"Point"}
}