{
  "type": "Feature",
  "properties": {
    "iso:country":"BE",
    "sg:address":"Zwaantjeslei 4",
    "sg:city":"Brasschaat",
    "sg:classifiers":[
        {
            "category":"Professional",
            "subcategory":"Engineering",
            "type":"Services"
        }
    ],
    "sg:phone":"+32 3 644 48 98",
    "sg:postcode":"2930",
    "sg:province":"Antwerpen",
    "sg:tags":[
        "machine",
        "-",
        "mechanical"
    ],
    "wof:name":"W.m. Engineering Bvba",
    "wof:placetype":"venue"
},
  "geometry": {"coordinates":[4.4643611908,51.269367218],"type":"Point"}
}