{
  "type": "Feature",
  "properties": {
    "iso:country":"BE",
    "sg:address":"Warande 18",
    "sg:city":"Sint-laureins",
    "sg:orig_category":"D\u00e9chets and d\u00e9bris Gr",
    "sg:phone":"+32 9 379 81 38",
    "sg:postcode":"9982",
    "sg:province":"Oost-Vlaanderen",
    "wof:name":"Enfralin",
    "wof:placetype":"venue"
},
  "geometry": {"coordinates":[3.5859649181,51.2472877502],"type":"Point"}
}