{
  "type": "Feature",
  "properties": {
    "iso:country":"BE",
    "sg:address":"Rue De Fleurus 20",
    "sg:city":"Sombreffe",
    "sg:orig_category":"Instituts de beaut\u00e9",
    "sg:phone":"+32 71 81 75 00",
    "sg:postcode":"5140",
    "sg:province":"Namur",
    "wof:name":"Centre D' Esth\u00c9tique Cyb\u00c8le",
    "wof:placetype":"venue"
},
  "geometry": {"coordinates":[4.5661768913,50.4928321838],"type":"Point"}
}