{
  "type": "Feature",
  "properties": {
    "addr:full":"Rue Marie-henriette 69 Elsene/ixelles Bruxelles-Capitale 1050",
    "addr:housenumber":"69",
    "addr:postcode":"1050",
    "addr:street":"Rue Marie-Henriette",
    "iso:country":"BE",
    "sg:address":"Rue Marie-henriette 69",
    "sg:city":"Elsene/ixelles",
    "sg:orig_category":"M\u00e9decins and sp\u00e9cialistes",
    "sg:phone":"+32 2 647 11 88",
    "sg:postcode":"1050",
    "sg:province":"Bruxelles-Capitale",
    "wof:name":"Catherine Luxereau",
    "wof:placetype":"venue"
},
  "geometry": {"coordinates":[4.3745098114,50.8294067383],"type":"Point"}
}