{
  "type": "Feature",
  "properties": {
    "iso:country":"BE",
    "sg:address":"Noordhofweg 1",
    "sg:city":"Ieper",
    "sg:orig_category":"Groententeelt",
    "sg:phone":"+32 57 20 63 24",
    "sg:postcode":"8900",
    "sg:province":"West-Vlaanderen",
    "wof:name":"Hendrik Legrand",
    "wof:placetype":"venue"
},
  "geometry": {"coordinates":[2.857765913,50.8666267395],"type":"Point"}
}