{
  "type": "Feature",
  "properties": {
    "addr:full":"Rue Des Rossignols 24 Montigny-le-tilleul Hainaut 6110",
    "addr:housenumber":"24",
    "addr:postcode":"6110",
    "addr:street":"Rue Des Rossignols",
    "iso:country":"BE",
    "sg:address":"Rue Des Rossignols 24",
    "sg:city":"Montigny-le-tilleul",
    "sg:classifiers":[
        {
            "category":"Health Services",
            "subcategory":"Doctor",
            "type":"Services"
        }
    ],
    "sg:phone":"+32 71 51 61 62",
    "sg:postcode":"6110",
    "sg:province":"Hainaut",
    "sg:tags":[
        "medicinephysicians",
        "surgeon"
    ],
    "wof:name":"Baudoux M",
    "wof:placetype":"venue"
},
  "geometry": {"coordinates":[4.3724188805,50.3630218506],"type":"Point"}
}