{
  "type": "Feature",
  "properties": {
    "addr:full":"Rue De Steppes 14 Li\u00e8ge 1 Li\u00e8ge 4000",
    "addr:housenumber":"14;1",
    "addr:postcode":"4000",
    "addr:street":"Rue De Steppes",
    "iso:country":"BE",
    "sg:address":"Rue De Steppes 14",
    "sg:city":"Li\u00e8ge 1",
    "sg:classifiers":[
        {
            "category":"Professional",
            "subcategory":"Printing & Photocopies",
            "type":"Services"
        }
    ],
    "sg:phone":"+32 4 289 06 97",
    "sg:postcode":"4000",
    "sg:province":"Li\u00e8ge",
    "sg:tags":[
        "silkscreen",
        "-"
    ],
    "wof:name":"Addax Screen",
    "wof:placetype":"venue"
},
  "geometry": {"coordinates":[5.5990281105,50.6546821594],"type":"Point"}
}