{
  "type": "Feature",
  "properties": {
    "addr:full":"Hogeweide 19 Asse (kobbegem) Vlaams-Brabant 1730",
    "addr:housenumber":"19",
    "addr:postcode":"1730",
    "addr:street":"Hogeweide",
    "iso:country":"BE",
    "sg:address":"Hogeweide 19",
    "sg:city":"Asse (kobbegem)",
    "sg:classifiers":[
        {
            "category":"Professional",
            "subcategory":"Management & Consulting",
            "type":"Services"
        }
    ],
    "sg:phone":"+32 2 452 64 97",
    "sg:postcode":"1730",
    "sg:province":"Vlaams-Brabant",
    "sg:tags":[
        "consultant"
    ],
    "wof:name":"Highfield Management Services",
    "wof:placetype":"venue"
},
  "geometry": {"coordinates":[4.2497611046,50.9083824158],"type":"Point"}
}