{
  "type": "Feature",
  "properties": {
    "addr:full":"Kerkhofstraat 5 Retie Antwerpen 2470",
    "addr:housenumber":"5",
    "addr:postcode":"2470",
    "addr:street":"Kerkhofstraat",
    "iso:country":"BE",
    "sg:address":"Kerkhofstraat 5",
    "sg:city":"Retie",
    "sg:classifiers":[
        {
            "category":"Farming",
            "subcategory":"Fish & Marine Products",
            "type":"Manufacturing & Wholesale Goods"
        }
    ],
    "sg:phone":"+32 14 37 04 04",
    "sg:postcode":"2470",
    "sg:province":"Antwerpen",
    "sg:tags":[
        "retail",
        "-",
        "shellfish"
    ],
    "wof:name":"Dolfijntje ('t)",
    "wof:placetype":"venue"
},
  "geometry": {"coordinates":[5.0860028267,51.268032074],"type":"Point"}
}