{
  "type": "Feature",
  "properties": {
    "iso:country":"BE",
    "sg:address":"Donkstraat 50",
    "sg:city":"Haacht (wespelaar)",
    "sg:classifiers":[
        {
            "category":"Professional",
            "subcategory":"Engineering",
            "type":"Services"
        }
    ],
    "sg:phone":"+32 16 61 90 41",
    "sg:postcode":"3150",
    "sg:province":"Vlaams-Brabant",
    "sg:tags":[
        "-"
    ],
    "wof:name":"Studie En Adviesbureau Inzake Preventie & Bescher Ming",
    "wof:placetype":"venue"
},
  "geometry": {"coordinates":[4.6144762039,50.9597473145],"type":"Point"}
}