{
  "type": "Feature",
  "properties": {
    "iso:country":"BE",
    "sg:address":"Zwartgoorweg 62",
    "sg:city":"Vosselaar",
    "sg:classifiers":[
        {
            "category":"Building & Trades",
            "subcategory":"Pest Control",
            "type":"Services"
        }
    ],
    "sg:phone":"+32 14 61 81 88",
    "sg:postcode":"2350",
    "sg:province":"Antwerpen",
    "sg:tags":[
        "painting",
        "contractor"
    ],
    "wof:name":"Mermans & Van Den Heuvel Schilderwerken Bvba",
    "wof:placetype":"venue"
},
  "geometry": {"coordinates":[4.8720021248,51.3011283875],"type":"Point"}
}