{
  "type": "Feature",
  "properties": {
    "addr:full":"Mosselstraat 3 Lichtervelde West-Vlaanderen 8810",
    "addr:housenumber":"3",
    "addr:postcode":"8810",
    "addr:street":"Mosselstraat",
    "iso:country":"BE",
    "sg:address":"Mosselstraat 3",
    "sg:city":"Lichtervelde",
    "sg:orig_category":"Sportclubs Sportterreinen and installaties behalve sportcentra",
    "sg:phone":"+32 51 72 36 55",
    "sg:postcode":"8810",
    "sg:province":"West-Vlaanderen",
    "wof:name":"K.f.c. Lichtervelde",
    "wof:placetype":"venue"
},
  "geometry": {"coordinates":[3.1454880238,51.0299682617],"type":"Point"}
}