{
  "type": "Feature",
  "properties": {
    "addr:full":"Kerkplein 28 Roeselare West-Vlaanderen 8800",
    "addr:housenumber":"28",
    "addr:postcode":"8800",
    "addr:street":"Kerkplein",
    "iso:country":"BE",
    "sg:address":"Kerkplein 28",
    "sg:city":"Roeselare",
    "sg:orig_category":"Banken and kredietinstellingen",
    "sg:phone":"+32 51 20 22 44",
    "sg:postcode":"8800",
    "sg:province":"West-Vlaanderen",
    "wof:name":"Dexia",
    "wof:placetype":"venue"
},
  "geometry": {"coordinates":[3.1540930271,50.9327011108],"type":"Point"}
}