{
  "type": "Feature",
  "properties": {
    "addr:full":"Stationsstraat 121 Oostrozebeke West-Vlaanderen 8780",
    "addr:housenumber":"121",
    "addr:postcode":"8780",
    "addr:street":"Stationsstraat",
    "iso:country":"BE",
    "sg:address":"Stationsstraat 121",
    "sg:city":"Oostrozebeke",
    "sg:orig_category":"Rundveehouders Varkenskwekers",
    "sg:phone":"+32 56 66 61 98",
    "sg:postcode":"8780",
    "sg:province":"West-Vlaanderen",
    "wof:name":"Luc Vandaele",
    "wof:placetype":"venue"
},
  "geometry": {"coordinates":[3.3308529854,50.9137802124],"type":"Point"}
}