{
  "type": "Feature",
  "properties": {
    "addr:full":"Route De Frasnes 240 Ath (mainvault) Hainaut 7812",
    "addr:housenumber":"240",
    "addr:postcode":"7812",
    "addr:street":"Route De Frasnes",
    "iso:country":"BE",
    "sg:address":"Route De Frasnes 240",
    "sg:city":"Ath (mainvault)",
    "sg:classifiers":[
        {
            "category":"Building & Trades",
            "subcategory":"Landscaping Services",
            "type":"Services"
        }
    ],
    "sg:phone":"+32 68 64 53 24",
    "sg:postcode":"7812",
    "sg:province":"Hainaut",
    "sg:tags":[
        "forestry"
    ],
    "wof:name":"Monfort Cl",
    "wof:placetype":"venue"
},
  "geometry": {"coordinates":[3.6734309196,50.6524047852],"type":"Point"}
}