{
  "type": "Feature",
  "properties": {
    "iso:country":"BE",
    "sg:address":"Avenue Du Roi 180",
    "sg:city":"Bruxelles (forest)",
    "sg:classifiers":[
        {
            "category":"Building & Trades",
            "subcategory":"Construction",
            "type":"Services"
        }
    ],
    "sg:phone":"+32 475 63 50 90",
    "sg:postcode":"1190",
    "sg:province":"Bruxelles-Capitale",
    "sg:tags":[
        "stucco",
        "contractor"
    ],
    "wof:name":"Abc Deco",
    "wof:placetype":"venue"
},
  "geometry": {"coordinates":[4.3348779678,50.8259277344],"type":"Point"}
}