{
  "type": "Feature",
  "properties": {
    "addr:full":"Deign\u00c9 78 Aywaille Li\u00e8ge 4920",
    "addr:housenumber":"78",
    "addr:postcode":"4920",
    "addr:street":"Deigne\u0301",
    "iso:country":"BE",
    "sg:address":"Deign\u00c9 78",
    "sg:city":"Aywaille",
    "sg:orig_category":"Installatie van houten of kunststof schrijnwerk",
    "sg:phone":"+32 4 360 86 43",
    "sg:postcode":"4920",
    "sg:province":"Li\u00e8ge",
    "wof:name":"Gavray",
    "wof:placetype":"venue"
},
  "geometry": {"coordinates":[5.7293400764,50.5056190491],"type":"Point"}
}