{
  "type": "Feature",
  "properties": {
    "iso:country":"BE",
    "sg:address":"Krekelstraat 40ba",
    "sg:city":"Lokeren",
    "sg:orig_category":"M\u00e9decines alternatives",
    "sg:phone":"+32 9 348 73 25",
    "sg:postcode":"9160",
    "sg:province":"Oost-Vlaanderen",
    "wof:name":"G. De Bock",
    "wof:placetype":"venue"
},
  "geometry": {"coordinates":[3.9989440441,51.0993118286],"type":"Point"}
}