{
  "type": "Feature",
  "properties": {
    "addr:full":"Veldstraat 52 Heusden-zolder (zolder) Limburg 3550",
    "addr:housenumber":"52",
    "addr:postcode":"3550",
    "addr:street":"Veldstraat",
    "iso:country":"BE",
    "sg:address":"Veldstraat 52",
    "sg:city":"Heusden-zolder (zolder)",
    "sg:classifiers":[
        {
            "category":"Utilities",
            "subcategory":"Recycling",
            "type":"Services"
        }
    ],
    "sg:postcode":"3550",
    "sg:province":"Limburg",
    "wof:name":"B & A Plastics Nv",
    "wof:placetype":"venue"
},
  "geometry": {"coordinates":[5.2432541847,50.9991149902],"type":"Point"}
}