{
  "type": "Feature",
  "properties": {
    "addr:full":"Clos Ma Campagne 7 Waterloo Brabant Wallon 1410",
    "addr:housenumber":"7",
    "addr:postcode":"1410",
    "addr:street":"Clos;Campagne",
    "iso:country":"BE",
    "sg:address":"Clos Ma Campagne 7",
    "sg:city":"Waterloo",
    "sg:orig_category":"Artsen and specialisten",
    "sg:phone":"+32 2 353 14 74",
    "sg:postcode":"1410",
    "sg:province":"Brabant Wallon",
    "wof:name":"Val\u00c9rie Michel",
    "wof:placetype":"venue"
},
  "geometry": {"coordinates":[4.3820328712,50.7061080933],"type":"Point"}
}