{
  "type": "Feature",
  "properties": {
    "iso:country":"BE",
    "sg:address":"Andr\u00c9 Dumontlaan 11",
    "sg:city":"Genk",
    "sg:orig_category":"Fruitteelt",
    "sg:phone":"+32 89 84 25 27",
    "sg:postcode":"3600",
    "sg:province":"Limburg",
    "wof:name":"Jean Hansen",
    "wof:placetype":"venue"
},
  "geometry": {"coordinates":[5.5295848846,50.9970092773],"type":"Point"}
}