{
  "type": "Feature",
  "properties": {
    "addr:full":"Koolstraat 135 Aalst Oost-Vlaanderen 9300",
    "addr:housenumber":"135",
    "addr:postcode":"9300",
    "addr:street":"Koolstraat",
    "iso:country":"BE",
    "sg:address":"Koolstraat 135",
    "sg:city":"Aalst",
    "sg:orig_category":"Bloemen and planten",
    "sg:phone":"+32 53 78 23 15",
    "sg:postcode":"9300",
    "sg:province":"Oost-Vlaanderen",
    "wof:name":"Art & Licht",
    "wof:placetype":"venue"
},
  "geometry": {"coordinates":[4.0300498009,50.9402046204],"type":"Point"}
}