{
  "type": "Feature",
  "properties": {
    "iso:country":"BE",
    "sg:address":"Guido Gezellelaan 9",
    "sg:city":"Hamme",
    "sg:classifiers":[
        {
            "category":"Bars & Pubs",
            "type":"Food & Drink"
        }
    ],
    "sg:phone":"+32 52 47 04 68",
    "sg:postcode":"9220",
    "sg:province":"Oost-Vlaanderen",
    "wof:name":"Goalkeeper",
    "wof:placetype":"venue"
},
  "geometry": {"coordinates":[4.143846035,51.0942726135],"type":"Point"}
}