{
  "type": "Feature",
  "properties": {
    "addr:full":"Boulevard Martin 2 Ottignies-louvain-la-neuve Brabant Wallon 1340",
    "addr:housenumber":"2",
    "addr:postcode":"1340",
    "addr:street":"Boulevard Martin",
    "iso:country":"BE",
    "sg:address":"Boulevard Martin 2",
    "sg:city":"Ottignies-louvain-la-neuve",
    "sg:classifiers":[
        {
            "category":"Cafe",
            "type":"Food & Drink"
        }
    ],
    "sg:phone":"+32 10 41 96 60",
    "sg:postcode":"1340",
    "sg:province":"Brabant Wallon",
    "sg:tags":[
        "caf\u00e9s"
    ],
    "wof:name":"Leonce Merienne",
    "wof:placetype":"venue"
},
  "geometry": {"coordinates":[4.5688171387,50.6654434204],"type":"Point"}
}