{
  "type": "Feature",
  "properties": {
    "iso:country":"BE",
    "sg:address":"Zomerweg 7",
    "sg:city":"Lendelede",
    "sg:orig_category":"Antiek",
    "sg:phone":"+32 51 30 26 57",
    "sg:postcode":"8860",
    "sg:province":"West-Vlaanderen",
    "wof:name":"Tijdloos Antiek",
    "wof:placetype":"venue"
},
  "geometry": {"coordinates":[3.2513320446,50.8872108459],"type":"Point"}
}