{
  "type": "Feature",
  "properties": {
    "iso:country":"BE",
    "sg:address":"Rue Des Marronniers 4",
    "sg:city":"Perwez",
    "sg:orig_category":"Rusthuizen and serviceflats",
    "sg:phone":"+32 81 65 52 77",
    "sg:postcode":"1360",
    "sg:province":"Brabant Wallon",
    "wof:name":"Home De Burlet Tr\u00c9mouroux",
    "wof:placetype":"venue"
},
  "geometry": {"coordinates":[4.8111901283,50.6218185425],"type":"Point"}
}