{
  "type": "Feature",
  "properties": {
    "addr:full":"Rue Grand Ry 31 Verviers (stembert) Li\u00e8ge 4801",
    "addr:housenumber":"31",
    "addr:postcode":"4801",
    "addr:street":"Rue Grand Ry",
    "iso:country":"BE",
    "sg:address":"Rue Grand Ry 31",
    "sg:city":"Verviers (stembert)",
    "sg:classifiers":[
        {
            "category":"Personal",
            "subcategory":"Nail Salon",
            "type":"Services"
        }
    ],
    "sg:phone":"+32 87 33 78 37",
    "sg:postcode":"4801",
    "sg:province":"Li\u00e8ge",
    "sg:tags":[
        "pedicure"
    ],
    "wof:name":"Heusschen I",
    "wof:placetype":"venue"
},
  "geometry": {"coordinates":[5.8821129799,50.5930328369],"type":"Point"}
}