{
  "type": "Feature",
  "properties": {
    "addr:full":"Grote Markt 33 Turnhout Antwerpen 2300",
    "addr:housenumber":"33",
    "addr:postcode":"2300",
    "addr:street":"Grote Markt",
    "iso:country":"BE",
    "sg:address":"Grote Markt 33",
    "sg:city":"Turnhout",
    "sg:classifiers":[
        {
            "category":"Cafe",
            "type":"Food & Drink"
        }
    ],
    "sg:phone":"+32 14 43 50 67",
    "sg:postcode":"2300",
    "sg:province":"Antwerpen",
    "sg:tags":[
        "caf\u00e9s"
    ],
    "wof:name":"Caf\u00c9 Amicitia",
    "wof:placetype":"venue"
},
  "geometry": {"coordinates":[4.94790411,51.323059082],"type":"Point"}
}