{
  "type": "Feature",
  "properties": {
    "addr:full":"Rue Des Verreries 19 Manage Hainaut 7170",
    "addr:housenumber":"19",
    "addr:postcode":"7170",
    "addr:street":"Rue Des Verreries",
    "iso:country":"BE",
    "sg:address":"Rue Des Verreries 19",
    "sg:city":"Manage",
    "sg:classifiers":[
        {
            "category":"Utilities",
            "subcategory":"Refuse",
            "type":"Services"
        }
    ],
    "sg:phone":"+32 64 55 69 01",
    "sg:postcode":"7170",
    "sg:province":"Hainaut",
    "sg:tags":[
        "management",
        "waste"
    ],
    "wof:name":"Cemepre Sprl",
    "wof:placetype":"venue"
},
  "geometry": {"coordinates":[4.2448601723,50.5037307739],"type":"Point"}
}