{
  "type": "Feature",
  "properties": {
    "addr:full":"Rue Du Sceptre 21ba Elsene/ixelles Bruxelles-Capitale 1050",
    "addr:housenumber":"21ba",
    "addr:postcode":"1050",
    "addr:street":"Rue Du Sceptre",
    "iso:country":"BE",
    "sg:address":"Rue Du Sceptre 21ba",
    "sg:city":"Elsene/ixelles",
    "sg:orig_category":"Imprimeries and copyshops",
    "sg:phone":"+32 2 649 24 47",
    "sg:postcode":"1050",
    "sg:province":"Bruxelles-Capitale",
    "wof:name":"C.b. Print",
    "wof:placetype":"venue"
},
  "geometry": {"coordinates":[4.3760061264,50.8334503174],"type":"Point"}
}