{
  "type": "Feature",
  "properties": {
    "addr:full":"Rue Des Grosses Pierres 69 Gr\u00e2ce-hollogne (hollogne-aux-pierres) Li\u00e8ge 4460",
    "addr:housenumber":"69",
    "addr:postcode":"4460",
    "addr:street":"Rue Des Grosses Pierres;Hollogne-Aux-Pierres",
    "iso:country":"BE",
    "sg:address":"Rue Des Grosses Pierres 69",
    "sg:city":"Gr\u00e2ce-hollogne (hollogne-aux-pierres)",
    "sg:classifiers":[
        {
            "category":"Professional",
            "subcategory":"Lawyer & Legal Services",
            "type":"Services"
        }
    ],
    "sg:phone":"+32 4 246 44 44",
    "sg:postcode":"4460",
    "sg:province":"Li\u00e8ge",
    "wof:name":"Lhoest H",
    "wof:placetype":"venue"
},
  "geometry": {"coordinates":[5.4738268852,50.6466827393],"type":"Point"}
}