{
  "type": "Feature",
  "properties": {
    "iso:country":"BE",
    "sg:address":"S\u00c9rez\u00c9 3",
    "sg:city":"Thimister-clermont",
    "sg:classifiers":[
        {
            "category":"Sports & Exercise",
            "subcategory":"Sports Center",
            "type":"Entertainment"
        }
    ],
    "sg:phone":"+32 87 44 51 00",
    "sg:postcode":"4890",
    "sg:province":"Li\u00e8ge",
    "sg:tags":[
        "terrain",
        "hors",
        "de",
        "installation",
        "sportifs"
    ],
    "wof:name":"Poneyland",
    "wof:placetype":"venue"
},
  "geometry": {"coordinates":[5.8644518852,50.6414985657],"type":"Point"}
}