{
  "type": "Feature",
  "properties": {
    "iso:country":"BE",
    "sg:address":"Avenue Des Alli\u00e9s 47",
    "sg:city":"Charleroi",
    "sg:classifiers":[
        {
            "category":"Professional",
            "subcategory":"Art Services",
            "type":"Services"
        }
    ],
    "sg:phone":"+32 71 70 39 99",
    "sg:postcode":"6000",
    "sg:province":"Hainaut",
    "sg:tags":[
        "model",
        "manufacturer"
    ],
    "wof:name":"Hobby-trains",
    "wof:placetype":"venue"
},
  "geometry": {"coordinates":[4.4386091232,50.411491394],"type":"Point"}
}