{
  "type": "Feature",
  "properties": {
    "iso:country":"BE",
    "sg:address":"Rue Houlette 28",
    "sg:city":"Villers-la-ville",
    "sg:orig_category":"Woningbouw",
    "sg:phone":"+32 71 87 67 90",
    "sg:postcode":"1495",
    "sg:province":"Brabant Wallon",
    "wof:name":"Vincent Guilmot",
    "wof:placetype":"venue"
},
  "geometry": {"coordinates":[4.5023450851,50.5755119324],"type":"Point"}
}