{
  "type": "Feature",
  "properties": {
    "addr:full":"Groenstraat 75 Holsbeek Vlaams-Brabant 3221",
    "addr:housenumber":"75",
    "addr:postcode":"3221",
    "addr:street":"Groenstraat",
    "iso:country":"BE",
    "sg:address":"Groenstraat 75",
    "sg:city":"Holsbeek",
    "sg:orig_category":"Epiceries",
    "sg:phone":"+32 16 64 03 11",
    "sg:postcode":"3221",
    "sg:province":"Vlaams-Brabant",
    "wof:name":"'t Winkeltje",
    "wof:placetype":"venue"
},
  "geometry": {"coordinates":[4.8318719864,50.9449615479],"type":"Point"}
}