{
  "type": "Feature",
  "properties": {
    "iso:country":"BE",
    "sg:address":"Hoge Haar 26",
    "sg:city":"Schilde ('s Gravenwezel)",
    "sg:classifiers":[
        {
            "category":"Professional",
            "subcategory":"Management & Consulting",
            "type":"Services"
        }
    ],
    "sg:phone":"+32 3 293 40 51",
    "sg:postcode":"2970",
    "sg:province":"Antwerpen",
    "sg:tags":[
        "consultant"
    ],
    "wof:name":"Financial Controllers & Consultants Nv",
    "wof:placetype":"venue"
},
  "geometry": {"coordinates":[4.5738911629,51.2530593872],"type":"Point"}
}