{
  "type": "Feature",
  "properties": {
    "iso:country":"BE",
    "sg:address":"Place De La Gare 11",
    "sg:city":"Manage",
    "sg:classifiers":[
        {
            "category":"Cafe",
            "type":"Food & Drink"
        }
    ],
    "sg:phone":"+32 64 55 77 12",
    "sg:postcode":"7170",
    "sg:province":"Hainaut",
    "sg:tags":[
        "caf\u00e9s"
    ],
    "wof:name":"Acrakas",
    "wof:placetype":"venue"
},
  "geometry": {"coordinates":[4.2351942062,50.5052452087],"type":"Point"}
}