{
  "type": "Feature",
  "properties": {
    "iso:country":"BE",
    "sg:address":"Stationsstraat 16",
    "sg:city":"Aalter",
    "sg:classifiers":[
        {
            "category":"Shopping",
            "subcategory":"Clothing, Apparel, & Fashions",
            "type":"Retail Goods"
        }
    ],
    "sg:phone":"+32 9 374 05 45",
    "sg:postcode":"9880",
    "sg:province":"Oost-Vlaanderen",
    "sg:tags":[
        "boutique"
    ],
    "wof:name":"Liliane Volslank Boetiek",
    "wof:placetype":"venue"
},
  "geometry": {"coordinates":[3.4498150349,51.0920066833],"type":"Point"}
}