{
  "type": "Feature",
  "properties": {
    "iso:country":"BE",
    "sg:address":"Omloop-zuid 3",
    "sg:city":"Vleteren",
    "sg:orig_category":"Eleveurs and marchands de porcs. Eleveurs de bovins",
    "sg:phone":"+32 57 42 24 49",
    "sg:postcode":"8640",
    "sg:province":"West-Vlaanderen",
    "wof:name":"Andre Dehouck",
    "wof:placetype":"venue"
},
  "geometry": {"coordinates":[2.792454958,50.8901367188],"type":"Point"}
}