{
  "type": "Feature",
  "properties": {
    "addr:full":"Rue De Lustin 68 Assesse (maillen) Namur 5330",
    "addr:housenumber":"68",
    "addr:postcode":"5330",
    "addr:street":"Rue De Lustin",
    "iso:country":"BE",
    "sg:address":"Rue De Lustin 68",
    "sg:city":"Assesse (maillen)",
    "sg:classifiers":[
        {
            "category":"Retail",
            "subcategory":"Auto Repair",
            "type":"Services"
        }
    ],
    "sg:phone":"+32 83 65 61 32",
    "sg:postcode":"5330",
    "sg:province":"Namur",
    "sg:tags":[
        "automobile-body"
    ],
    "wof:name":"Goffin J-m",
    "wof:placetype":"venue"
},
  "geometry": {"coordinates":[4.9579057693,50.3781509399],"type":"Point"}
}