{
  "type": "Feature",
  "properties": {
    "addr:full":"Rue Des Saules 54 Lasne (ohain) Brabant Wallon 1380",
    "addr:housenumber":"54",
    "addr:postcode":"1380",
    "addr:street":"Rue Des Saules;Wallon",
    "iso:country":"BE",
    "sg:address":"Rue Des Saules 54",
    "sg:city":"Lasne (ohain)",
    "sg:classifiers":[
        {
            "category":"Banks & Credit Unions",
            "subcategory":"Investment Brokerage",
            "type":"Services"
        }
    ],
    "sg:postcode":"1380",
    "sg:province":"Brabant Wallon",
    "sg:tags":[
        "pump",
        "industrial",
        "-"
    ],
    "wof:name":"A.c.m.r. Pompes-pompen",
    "wof:placetype":"venue"
},
  "geometry": {"coordinates":[4.483235836,50.6850166321],"type":"Point"}
}