{
  "type": "Feature",
  "properties": {
    "addr:full":"Mechelsesteenweg 113 Antwerpen Antwerpen 2000",
    "addr:housenumber":"113",
    "addr:postcode":"2000",
    "addr:street":"Mechelsesteenweg",
    "iso:country":"BE",
    "sg:address":"Mechelsesteenweg 113",
    "sg:city":"Antwerpen",
    "sg:orig_category":"Bruids- and ceremoniekledij",
    "sg:phone":"+32 3 257 29 98",
    "sg:postcode":"2000",
    "sg:province":"Antwerpen",
    "wof:name":"Steven De Wilde",
    "wof:placetype":"venue"
},
  "geometry": {"coordinates":[4.4099588394,51.2066802979],"type":"Point"}
}