{
  "type": "Feature",
  "properties": {
    "addr:full":"Rue De Ch\u00e2telet 12 Philippeville (villers-le-gambon) Namur 5600",
    "addr:housenumber":"12",
    "addr:postcode":"5600",
    "addr:street":"Rue De Cha\u0302Telet",
    "iso:country":"BE",
    "sg:address":"Rue De Ch\u00e2telet 12",
    "sg:city":"Philippeville (villers-le-gambon)",
    "sg:classifiers":[
        {
            "category":"Farming",
            "subcategory":"Fish & Marine Products",
            "type":"Manufacturing & Wholesale Goods"
        }
    ],
    "sg:phone":"+32 71 66 60 24",
    "sg:postcode":"5600",
    "sg:province":"Namur",
    "sg:tags":[
        "breeding"
    ],
    "wof:name":"Pisciculture Du Ry Des Pr\u00e9s",
    "wof:placetype":"venue"
},
  "geometry": {"coordinates":[4.6061701775,50.1923789978],"type":"Point"}
}