{
  "type": "Feature",
  "properties": {
    "addr:full":"Val D'heure 20 Ham-sur-heure-nalinnes (ham-sur-heure) Hainaut 6120",
    "addr:housenumber":"20",
    "addr:postcode":"6120",
    "addr:street":"Val D'Heure;Ham-Sur-Heure Hainaut",
    "iso:country":"BE",
    "sg:address":"Val D'heure 20",
    "sg:city":"Ham-sur-heure-nalinnes (ham-sur-heure)",
    "sg:classifiers":[
        {
            "category":"Health Services",
            "subcategory":"Nursing And Care Facility",
            "type":"Services"
        }
    ],
    "sg:phone":"+32 71 21 50 31",
    "sg:postcode":"6120",
    "sg:province":"Hainaut",
    "sg:tags":[
        "home"
    ],
    "wof:name":"Lefevre F",
    "wof:placetype":"venue"
},
  "geometry": {"coordinates":[4.4026479721,50.34715271],"type":"Point"}
}