{
  "type": "Feature",
  "properties": {
    "iso:country":"BE",
    "sg:address":"Oneux 120",
    "sg:city":"Comblain-au-pont",
    "sg:classifiers":[
        {
            "category":"Health Services",
            "subcategory":"Health Practitioner",
            "type":"Services"
        }
    ],
    "sg:phone":"+32 4 369 23 95",
    "sg:postcode":"4170",
    "sg:province":"Li\u00e8ge",
    "sg:tags":[
        "physiotherapist"
    ],
    "wof:name":"Pinchard J F",
    "wof:placetype":"venue"
},
  "geometry": {"coordinates":[5.5898509026,50.46849823],"type":"Point"}
}