{
  "type": "Feature",
  "properties": {
    "addr:full":"Grote Hoef 30 Lommel Limburg 3920",
    "addr:housenumber":"30",
    "addr:postcode":"3920",
    "addr:street":"Grote Hoef",
    "iso:country":"BE",
    "sg:address":"Grote Hoef 30",
    "sg:city":"Lommel",
    "sg:classifiers":[
        {
            "category":"Professional",
            "subcategory":"Art Services",
            "type":"Services"
        }
    ],
    "sg:phone":"+32 11 54 59 42",
    "sg:postcode":"3920",
    "sg:province":"Limburg",
    "sg:tags":[
        "interior",
        "designer"
    ],
    "wof:name":"Delchambre Dirk",
    "wof:placetype":"venue"
},
  "geometry": {"coordinates":[5.3288769722,51.2233963013],"type":"Point"}
}