{
  "type": "Feature",
  "properties": {
    "iso:country":"BE",
    "sg:address":"Avenue B. De Constantinople 10",
    "sg:city":"Mons",
    "sg:classifiers":[
        {
            "category":"Health Services",
            "subcategory":"Nursing And Care Facility",
            "type":"Services"
        }
    ],
    "sg:phone":"+32 65 39 51 11",
    "sg:postcode":"7000",
    "sg:province":"Hainaut",
    "sg:tags":[
        "home",
        "rest"
    ],
    "wof:name":"Foyers St-joseph (les)",
    "wof:placetype":"venue"
},
  "geometry": {"coordinates":[3.9599699974,50.4535636902],"type":"Point"}
}