{
  "type": "Feature",
  "properties": {
    "iso:country":"BE",
    "sg:address":"Dr\u00e8ve Nantaise 16a",
    "sg:city":"Genappe (bousval)",
    "sg:classifiers":[
        {
            "category":"Organizations",
            "subcategory":"Community Association",
            "type":"Services"
        }
    ],
    "sg:phone":"+32 10 61 70 60",
    "sg:postcode":"1470",
    "sg:province":"Brabant Wallon",
    "sg:tags":[
        "cultural"
    ],
    "wof:name":"Fun Factory Unltd Asbl",
    "wof:placetype":"venue"
},
  "geometry": {"coordinates":[4.5366210938,50.6411895752],"type":"Point"}
}