{
  "type": "Feature",
  "properties": {
    "iso:country":"BE",
    "sg:address":"Langestraat 135",
    "sg:city":"Nieuwpoort",
    "sg:orig_category":"Non-Classified Establishments",
    "sg:phone":"+32 58 23 52 03",
    "sg:postcode":"8620",
    "sg:province":"West-Vlaanderen",
    "wof:name":"Vanhoucke P",
    "wof:placetype":"venue"
},
  "geometry": {"coordinates":[2.7490570545,51.1324081421],"type":"Point"}
}