{
  "type": "Feature",
  "properties": {
    "iso:country":"BE",
    "sg:address":"Place Maurice Servais 8",
    "sg:city":"Namur",
    "sg:classifiers":[
        {
            "category":"Shopping",
            "subcategory":"Computers & Home Electronics",
            "type":"Retail Goods"
        }
    ],
    "sg:phone":"+32 81 65 76 90",
    "sg:postcode":"5000",
    "sg:province":"Namur",
    "sg:tags":[
        "telephone",
        "apparatus",
        "accessory"
    ],
    "wof:name":"Telefono",
    "wof:placetype":"venue"
},
  "geometry": {"coordinates":[4.8647351265,50.4622840881],"type":"Point"}
}