{
  "type": "Feature",
  "properties": {
    "iso:country":"BE",
    "sg:address":"Hoogleedsesteenweg 108",
    "sg:city":"Roeselare",
    "sg:classifiers":[
        {
            "category":"Professional",
            "type":"Services"
        }
    ],
    "sg:phone":"+32 51 25 48 61",
    "sg:postcode":"8800",
    "sg:province":"West-Vlaanderen",
    "sg:tags":[
        "entertainer"
    ],
    "wof:name":"G\u00e9rard B",
    "wof:placetype":"venue"
},
  "geometry": {"coordinates":[3.1167929173,50.9533424377],"type":"Point"}
}