{
  "type": "Feature",
  "properties": {
    "iso:country":"BE",
    "sg:address":"Koestraat 3",
    "sg:city":"Stekene",
    "sg:orig_category":"Woningbouw",
    "sg:phone":"+32 3 779 78 00",
    "sg:postcode":"9190",
    "sg:province":"Oost-Vlaanderen",
    "wof:name":"Metropool Immobilien",
    "wof:placetype":"venue"
},
  "geometry": {"coordinates":[4.0700130463,51.230342865],"type":"Point"}
}