{
  "type": "Feature",
  "properties": {
    "iso:country":"BE",
    "sg:address":"Grote Pieter Potstraat 8",
    "sg:city":"Antwerpen",
    "sg:classifiers":[
        {
            "category":"Bars & Pubs",
            "type":"Food & Drink"
        }
    ],
    "sg:phone":"+32 3 231 22 79",
    "sg:postcode":"2000",
    "sg:province":"Antwerpen",
    "wof:name":"Cuba Bella Bvba",
    "wof:placetype":"venue"
},
  "geometry": {"coordinates":[4.3974409103,51.2209014893],"type":"Point"}
}