{
  "type": "Feature",
  "properties": {
    "iso:country":"BE",
    "sg:address":"Nieuwmoersesteenweg 52",
    "sg:city":"Essen",
    "sg:orig_category":"RESTAURANTS: SALLES DE CONF\u00c9RENCES AND DE R\u00c9CEPTIONS",
    "sg:phone":"+32 3 677 13 13",
    "sg:postcode":"2910",
    "sg:province":"Antwerpen",
    "wof:name":"Oost Speykers Hoef",
    "wof:placetype":"venue"
},
  "geometry": {"coordinates":[4.4866251945,51.4520759583],"type":"Point"}
}