{
  "type": "Feature",
  "properties": {
    "addr:full":"Beversesteenweg 350 Roeselare West-Vlaanderen 8800",
    "addr:housenumber":"350",
    "addr:postcode":"8800",
    "addr:street":"Beversesteenweg",
    "iso:country":"BE",
    "sg:address":"Beversesteenweg 350",
    "sg:city":"Roeselare",
    "sg:orig_category":"Herstellingen and onderhoud van auto's",
    "sg:phone":"+32 51 24 28 72",
    "sg:postcode":"8800",
    "sg:province":"West-Vlaanderen",
    "wof:name":"Garage Callant",
    "wof:placetype":"venue"
},
  "geometry": {"coordinates":[3.1337099075,50.9615402222],"type":"Point"}
}