{
  "type": "Feature",
  "properties": {
    "addr:full":"Boulevard De L'imp\u00c9ratrice 0 Brussel Bruxelles-Capitale 1000",
    "addr:housenumber":"0",
    "addr:postcode":"1000",
    "addr:street":"Boulevard De L'Impe \u0301Ratrice",
    "iso:country":"BE",
    "sg:address":"Boulevard De L'imp\u00c9ratrice 0",
    "sg:city":"Brussel",
    "sg:orig_category":"Diverse kredietdiensten",
    "sg:postcode":"1000",
    "sg:province":"Bruxelles-Capitale",
    "wof:name":"Bancontac-mister Cash",
    "wof:placetype":"venue"
},
  "geometry": {"coordinates":[4.3570809364,50.8473930359],"type":"Point"}
}