{
  "type": "Feature",
  "properties": {
    "addr:full":"Av. De La Belle Province 27 Braine-l'alleud Brabant Wallon 1420",
    "addr:housenumber":"27",
    "addr:postcode":"1420",
    "addr:street":"Av. De La Belle Province",
    "iso:country":"BE",
    "sg:address":"Av. De La Belle Province 27",
    "sg:city":"Braine-l'alleud",
    "sg:classifiers":[
        {
            "category":"Food & Beverages",
            "subcategory":"Fruits & Vegetables",
            "type":"Retail Goods"
        }
    ],
    "sg:phone":"+32 2 387 21 53",
    "sg:postcode":"1420",
    "sg:province":"Brabant Wallon",
    "sg:tags":[
        "groenten"
    ],
    "wof:name":"Maison Servis Frais",
    "wof:placetype":"venue"
},
  "geometry": {"coordinates":[-91.9130020142,40.1174087524],"type":"Point"}
}