{
  "type": "Feature",
  "properties": {
    "addr:full":"Chauss\u00c9e De Mons 33 Rebecq Brabant Wallon 1430",
    "addr:housenumber":"33",
    "addr:postcode":"1430",
    "addr:street":"Chausse\u0301E De Mons",
    "iso:country":"BE",
    "sg:address":"Chauss\u00c9e De Mons 33",
    "sg:city":"Rebecq",
    "sg:orig_category":"Plaatsen van vloer- and muurbekleding Schilders",
    "sg:phone":"+32 67 63 67 69",
    "sg:postcode":"1430",
    "sg:province":"Brabant Wallon",
    "wof:name":"Maison Tubi D\u00c9cor",
    "wof:placetype":"venue"
},
  "geometry": {"coordinates":[4.1669697762,50.6586303711],"type":"Point"}
}