{
  "type": "Feature",
  "properties": {
    "iso:country":"BE",
    "sg:address":"Rue Joseph Wauters 74",
    "sg:city":"Waremme",
    "sg:orig_category":"Brood, gebak and snoepgoed",
    "sg:phone":"+32 19 32 71 11",
    "sg:postcode":"4300",
    "sg:province":"Li\u00e8ge",
    "wof:name":"Maison Delfor",
    "wof:placetype":"venue"
},
  "geometry": {"coordinates":[5.2529301643,50.6957969666],"type":"Point"}
}