{
  "type": "Feature",
  "properties": {
    "addr:full":"F\u00c9ronstr\u00c9e 28 Li\u00c8ge Li\u00e8ge 4000",
    "addr:housenumber":"28",
    "addr:postcode":"4000",
    "addr:street":"Fe\u0301Ronstre\u0301E",
    "iso:country":"BE",
    "sg:address":"F\u00c9ronstr\u00c9e 28",
    "sg:city":"Li\u00c8ge",
    "sg:orig_category":"Dameskledingzaken",
    "sg:phone":"+32 4 223 71 72",
    "sg:postcode":"4000",
    "sg:province":"Li\u00e8ge",
    "wof:name":"Studio-modes Jeun. Cr\u00c9at.",
    "wof:placetype":"venue"
},
  "geometry": {"coordinates":[5.5782470703,50.646068573],"type":"Point"}
}