{
  "type": "Feature",
  "properties": {
    "addr:full":"Rue Mitoyenne 346 Lontzen Li\u00e8ge 4710",
    "addr:housenumber":"346",
    "addr:postcode":"4710",
    "addr:street":"Rue Mitoyenne",
    "iso:country":"BE",
    "sg:address":"Rue Mitoyenne 346",
    "sg:city":"Lontzen",
    "sg:orig_category":"Jardinage",
    "sg:phone":"+32 87 89 06 36",
    "sg:postcode":"4710",
    "sg:province":"Li\u00e8ge",
    "wof:name":"Bureau Szlachta T.",
    "wof:placetype":"venue"
},
  "geometry": {"coordinates":[5.9656300545,50.6769104004],"type":"Point"}
}