{
  "type": "Feature",
  "properties": {
    "iso:country":"BE",
    "sg:address":"Lammerendries 25",
    "sg:city":"Oudergem/auderghem",
    "sg:orig_category":"Brood, gebak and snoepgoed",
    "sg:phone":"+32 2 673 36 16",
    "sg:postcode":"1160",
    "sg:province":"Bruxelles-Capitale",
    "wof:name":"Au Pays De L\u00b4epeautre",
    "wof:placetype":"venue"
},
  "geometry": {"coordinates":[4.4220170975,50.8108673096],"type":"Point"}
}