{
  "type": "Feature",
  "properties": {
    "iso:country":"BE",
    "sg:address":"Stationsstraat 11",
    "sg:city":"Ravels (weelde)",
    "sg:classifiers":[
        {
            "category":"Professional",
            "subcategory":"Accounting & Tax Preparation",
            "type":"Services"
        }
    ],
    "sg:phone":"+32 14 65 95 42",
    "sg:postcode":"2381",
    "sg:province":"Antwerpen",
    "sg:tags":[
        "accountant"
    ],
    "wof:name":"Mercelis L",
    "wof:placetype":"venue"
},
  "geometry": {"coordinates":[4.9368309975,51.3988418579],"type":"Point"}
}