{
  "type": "Feature",
  "properties": {
    "iso:country":"BE",
    "sg:address":"Engelsenlaan 266bd",
    "sg:city":"Ronse/renaix",
    "sg:orig_category":"Woningbouw",
    "sg:phone":"+32 55 20 97 02",
    "sg:postcode":"9600",
    "sg:province":"Oost-Vlaanderen",
    "wof:name":"Renomas",
    "wof:placetype":"venue"
},
  "geometry": {"coordinates":[3.579116106,50.7417907715],"type":"Point"}
}