{
  "type": "Feature",
  "properties": {
    "iso:country":"BE",
    "sg:address":"Klinkaert 3",
    "sg:city":"Halle",
    "sg:orig_category":"Chaussures",
    "sg:phone":"+32 2 356 60 69",
    "sg:postcode":"1500",
    "sg:province":"Vlaams-Brabant",
    "wof:name":"Devos H.",
    "wof:placetype":"venue"
},
  "geometry": {"coordinates":[4.2371377945,50.7369422913],"type":"Point"}
}