{
  "type": "Feature",
  "properties": {
    "iso:country":"BE",
    "sg:address":"Rue De Bomal 14",
    "sg:city":"Incourt",
    "sg:orig_category":"Installation de menuiserie en bois and plastique",
    "sg:phone":"+32 10 88 98 66",
    "sg:postcode":"1315",
    "sg:province":"Brabant Wallon",
    "wof:name":"Margareth De Cannart D'hamale",
    "wof:placetype":"venue"
},
  "geometry": {"coordinates":[4.8431210518,50.6744499207],"type":"Point"}
}