{
  "type": "Feature",
  "properties": {
    "addr:full":"Rue Du Centre Bernadette 2 Geer Li\u00e8ge 4250",
    "addr:housenumber":"2",
    "addr:postcode":"4250",
    "addr:street":"Rue Du Centre Bernadette",
    "iso:country":"BE",
    "sg:address":"Rue Du Centre Bernadette 2",
    "sg:city":"Geer",
    "sg:orig_category":"Instituts pour adultes moins valides",
    "sg:phone":"+32 19 58 80 57",
    "sg:postcode":"4250",
    "sg:province":"Li\u00e8ge",
    "wof:name":"La Bernache",
    "wof:placetype":"venue"
},
  "geometry": {"coordinates":[5.1743597984,50.6690559387],"type":"Point"}
}