{
  "type": "Feature",
  "properties": {
    "addr:full":"Puntweg 18 Destelbergen Oost-Vlaanderen 9070",
    "addr:housenumber":"18",
    "addr:postcode":"9070",
    "addr:street":"Puntweg",
    "iso:country":"BE",
    "sg:address":"Puntweg 18",
    "sg:city":"Destelbergen",
    "sg:orig_category":"Informaticaconsulenten",
    "sg:phone":"+32 9 252 43 42",
    "sg:postcode":"9070",
    "sg:province":"Oost-Vlaanderen",
    "wof:name":"Adviesbureau Voor Bedrijfsbeheer",
    "wof:placetype":"venue"
},
  "geometry": {"coordinates":[3.8238420486,50.9985160828],"type":"Point"}
}