{
  "type": "Feature",
  "properties": {
    "addr:full":"Weststraat 35 Moorslede West-Vlaanderen 8890",
    "addr:housenumber":"35",
    "addr:postcode":"8890",
    "addr:street":"Weststraat",
    "iso:country":"BE",
    "sg:address":"Weststraat 35",
    "sg:city":"Moorslede",
    "sg:orig_category":"Sportclubs",
    "sg:phone":"+32 51 78 07 71",
    "sg:postcode":"8890",
    "sg:province":"West-Vlaanderen",
    "wof:name":"H.c. Roeselare",
    "wof:placetype":"venue"
},
  "geometry": {"coordinates":[3.0617671013,50.8946342468],"type":"Point"}
}