{
  "type": "Feature",
  "properties": {
    "iso:country":"BE",
    "sg:address":"Rue Notre-dame 6",
    "sg:city":"Binche",
    "sg:orig_category":"Industri\u00eble wasserijen and droogkuis",
    "sg:phone":"+32 64 33 67 06",
    "sg:postcode":"7130",
    "sg:province":"Hainaut",
    "wof:name":"Pressing No 1",
    "wof:placetype":"venue"
},
  "geometry": {"coordinates":[4.1655888557,50.4114532471],"type":"Point"}
}