{
  "type": "Feature",
  "properties": {
    "addr:full":"Rue Saint-jacques 1 Beauraing Namur 5572",
    "addr:housenumber":"1",
    "addr:postcode":"5572",
    "addr:street":"Rue Saint-Jacques",
    "iso:country":"BE",
    "sg:address":"Rue Saint-jacques 1",
    "sg:city":"Beauraing",
    "sg:orig_category":"Woningbouw",
    "sg:phone":"+32 82 71 25 27",
    "sg:postcode":"5572",
    "sg:province":"Namur",
    "wof:name":"Camiel Tant",
    "wof:placetype":"venue"
},
  "geometry": {"coordinates":[5.0282378197,50.1295433044],"type":"Point"}
}