{
  "type": "Feature",
  "properties": {
    "addr:full":"Karel Picqu\u00c9laan 10 Deinze Oost-Vlaanderen 9800",
    "addr:housenumber":"10",
    "addr:postcode":"9800",
    "addr:street":"Karel Picque\u0301Laan",
    "iso:country":"BE",
    "sg:address":"Karel Picqu\u00c9laan 10",
    "sg:city":"Deinze",
    "sg:orig_category":"Artiesten and kunstenaars",
    "sg:phone":"+32 9 386 19 00",
    "sg:postcode":"9800",
    "sg:province":"Oost-Vlaanderen",
    "wof:name":"Jos Smith",
    "wof:placetype":"venue"
},
  "geometry": {"coordinates":[3.5316910744,50.9858207703],"type":"Point"}
}