{
  "type": "Feature",
  "properties": {
    "addr:full":"R Des Alli\u00e9s 26 Nassogne Luxembourg 6953",
    "addr:housenumber":"26",
    "addr:postcode":"6953",
    "addr:street":"Des Allie\u0301S",
    "iso:country":"BE",
    "sg:address":"R Des Alli\u00e9s 26",
    "sg:city":"Nassogne",
    "sg:classifiers":[
        {
            "category":"Professional",
            "type":"Services"
        }
    ],
    "sg:phone":"+32 84 21 35 87",
    "sg:postcode":"6953",
    "sg:province":"Luxembourg",
    "sg:tags":[
        "transport",
        "road"
    ],
    "wof:name":"Euro Famenne Trucks Sprl",
    "wof:placetype":"venue"
},
  "geometry": {"coordinates":[5.2804489136,50.1335945129],"type":"Point"}
}