{
  "type": "Feature",
  "properties": {
    "addr:full":"Rue Des Croix 12 Saint-ghislain (villerot) Hainaut 7334",
    "addr:housenumber":"12",
    "addr:postcode":"7334",
    "addr:street":"Rue Des Croix",
    "iso:country":"BE",
    "sg:address":"Rue Des Croix 12",
    "sg:city":"Saint-ghislain (villerot)",
    "sg:classifiers":[
        {
            "category":"Health Services",
            "subcategory":"Nursing And Care Facility",
            "type":"Services"
        }
    ],
    "sg:phone":"+32 65 52 01 41",
    "sg:postcode":"7334",
    "sg:province":"Hainaut",
    "sg:tags":[
        "home"
    ],
    "wof:name":"Ryckoort S",
    "wof:placetype":"venue"
},
  "geometry": {"coordinates":[3.7644500732,50.479675293],"type":"Point"}
}