{
  "type": "Feature",
  "properties": {
    "iso:country":"BE",
    "sg:address":"Avenue Jean-baptiste Nothomb 77",
    "sg:city":"Arlon",
    "sg:classifiers":[
        {
            "category":"Health Services",
            "subcategory":"Health Practitioner",
            "type":"Services"
        }
    ],
    "sg:phone":"+32 63 44 64 24",
    "sg:postcode":"6700",
    "sg:province":"Luxembourg",
    "sg:tags":[
        "therapist",
        "speech"
    ],
    "wof:name":"Bossu P",
    "wof:placetype":"venue"
},
  "geometry": {"coordinates":[5.8062591553,49.6818351746],"type":"Point"}
}