{
  "type": "Feature",
  "properties": {
    "addr:full":"Leyssenstraat 27 Opglabbeek Limburg 3660",
    "addr:housenumber":"27",
    "addr:postcode":"3660",
    "addr:street":"Leyssenstraat",
    "iso:country":"BE",
    "sg:address":"Leyssenstraat 27",
    "sg:city":"Opglabbeek",
    "sg:orig_category":"Maatschappelijke dienstverlening",
    "sg:phone":"+32 89 85 80 10",
    "sg:postcode":"3660",
    "sg:province":"Limburg",
    "wof:name":"Rode Kruis Zwartberg",
    "wof:placetype":"venue"
},
  "geometry": {"coordinates":[5.6085629463,51.0530776978],"type":"Point"}
}