{
  "type": "Feature",
  "properties": {
    "iso:country":"BE",
    "sg:address":"Vredestraat 29",
    "sg:city":"Machelen",
    "sg:classifiers":[
        {
            "category":"Health Services",
            "subcategory":"Doctor",
            "type":"Services"
        }
    ],
    "sg:phone":"+32 2 252 45 21",
    "sg:postcode":"1830",
    "sg:province":"Vlaams-Brabant",
    "sg:tags":[
        "medicinephysicians",
        "surgeon"
    ],
    "wof:name":"Busschodts Marina",
    "wof:placetype":"venue"
},
  "geometry": {"coordinates":[4.4377188683,50.9111328125],"type":"Point"}
}