{
  "type": "Feature",
  "properties": {
    "addr:full":"Rue De Herve 143 Herve (battice) Li\u00e8ge 4651",
    "addr:housenumber":"143",
    "addr:postcode":"4651",
    "addr:street":"Rue De Herve",
    "iso:country":"BE",
    "sg:address":"Rue De Herve 143",
    "sg:city":"Herve (battice)",
    "sg:classifiers":[
        {
            "category":"Arts & Performance",
            "subcategory":"Symphony",
            "type":"Entertainment"
        }
    ],
    "sg:phone":"+32 87 67 42 46",
    "sg:postcode":"4651",
    "sg:province":"Li\u00e8ge",
    "sg:tags":[
        "orchestra"
    ],
    "wof:name":"Virginia",
    "wof:placetype":"venue"
},
  "geometry": {"coordinates":[5.8039450645,50.6448554993],"type":"Point"}
}