{
  "type": "Feature",
  "properties": {
    "addr:full":"Kortrijksesteenweg 303 Sint-martens-latem Oost-Vlaanderen 9830",
    "addr:housenumber":"303",
    "addr:postcode":"9830",
    "addr:street":"Kortrijksesteenweg",
    "iso:country":"BE",
    "sg:address":"Kortrijksesteenweg 303",
    "sg:city":"Sint-martens-latem",
    "sg:classifiers":[
        {
            "category":"Building & Trades",
            "subcategory":"Landscaping Services",
            "type":"Services"
        }
    ],
    "sg:phone":"+32 9 282 70 75",
    "sg:postcode":"9830",
    "sg:province":"Oost-Vlaanderen",
    "sg:tags":[
        "gardening",
        "garden",
        "maintenance"
    ],
    "wof:name":"Vandeputte Eric",
    "wof:placetype":"venue"
},
  "geometry": {"coordinates":[3.625469923,51.0055885315],"type":"Point"}
}