{
  "type": "Feature",
  "properties": {
    "addr:full":"Tintange 59 Fauvillers Luxembourg 6637",
    "addr:housenumber":"59",
    "addr:postcode":"6637",
    "addr:street":"Tintange",
    "iso:country":"BE",
    "sg:address":"Tintange 59",
    "sg:city":"Fauvillers",
    "sg:orig_category":"Rundveehouders",
    "sg:phone":"+32 63 60 02 32",
    "sg:postcode":"6637",
    "sg:province":"Luxembourg",
    "wof:name":"Jean Gabriel",
    "wof:placetype":"venue"
},
  "geometry": {"coordinates":[5.7515621185,49.8764419556],"type":"Point"}
}