{
  "type": "Feature",
  "properties": {
    "iso:country":"BE",
    "sg:address":"Gaversesteenweg 417",
    "sg:city":"Merelbeke",
    "sg:orig_category":"Fleurs and plantes",
    "sg:phone":"+32 9 230 00 41",
    "sg:postcode":"9820",
    "sg:province":"Oost-Vlaanderen",
    "wof:name":"Huis Helderweirds",
    "wof:placetype":"venue"
},
  "geometry": {"coordinates":[3.7272090912,50.9840087891],"type":"Point"}
}