{
  "type": "Feature",
  "properties": {
    "addr:full":"Romeinse Kassei 174 Tongeren (groot) Limburg 3700",
    "addr:housenumber":"174",
    "addr:postcode":"3700",
    "addr:street":"Romeinse Kassei;Groot Limburg",
    "iso:country":"BE",
    "sg:address":"Romeinse Kassei 174",
    "sg:city":"Tongeren (groot)",
    "sg:classifiers":[
        {
            "category":"Personal",
            "subcategory":"Beauty Salon",
            "type":"Services"
        }
    ],
    "sg:phone":"+32 12 23 56 01",
    "sg:postcode":"3700",
    "sg:province":"Limburg",
    "sg:tags":[
        "de",
        "coiffure"
    ],
    "wof:name":"Estee Coiffure",
    "wof:placetype":"venue"
},
  "geometry": {"coordinates":[5.4472098351,50.7735290527],"type":"Point"}
}