{
  "type": "Feature",
  "properties": {
    "addr:full":"Wiegstraat 11 Antwerpen Antwerpen 2000",
    "addr:housenumber":"11",
    "addr:postcode":"2000",
    "addr:street":"Wiegstraat",
    "iso:country":"BE",
    "sg:address":"Wiegstraat 11",
    "sg:city":"Antwerpen",
    "sg:classifiers":[
        {
            "category":"Shopping",
            "subcategory":"Clothing, Apparel, & Fashions",
            "type":"Retail Goods"
        }
    ],
    "sg:phone":"+32 3 225 05 49",
    "sg:postcode":"2000",
    "sg:province":"Antwerpen",
    "sg:tags":[
        "clothing",
        "-",
        "gentleman"
    ],
    "wof:name":"Ponte Vecchio",
    "wof:placetype":"venue"
},
  "geometry": {"coordinates":[4.4048500061,51.2180786133],"type":"Point"}
}