{
  "type": "Feature",
  "properties": {
    "iso:country":"BE",
    "sg:address":"Stationsstraat 100ba",
    "sg:city":"Haaltert",
    "sg:classifiers":[
        {
            "category":"Fast Food",
            "type":"Food & Drink"
        }
    ],
    "sg:phone":"+32 53 83 14 74",
    "sg:postcode":"9450",
    "sg:province":"Oost-Vlaanderen",
    "sg:tags":[
        "meeneem",
        "restaurant"
    ],
    "wof:name":"Frituur 't Snacksken",
    "wof:placetype":"venue"
},
  "geometry": {"coordinates":[4.0148501396,50.9028511047],"type":"Point"}
}