{
  "type": "Feature",
  "properties": {
    "iso:country":"BE",
    "sg:address":"Luciendal 17",
    "sg:city":"Sint-truiden",
    "sg:orig_category":"Slagers",
    "sg:phone":"+32 11 68 96 59",
    "sg:postcode":"3800",
    "sg:province":"Limburg",
    "wof:name":"Richard Vandenreyt",
    "wof:placetype":"venue"
},
  "geometry": {"coordinates":[5.1841449738,50.8245429993],"type":"Point"}
}