{
  "type": "Feature",
  "properties": {
    "addr:full":"Grote Hoef 28 Lommel Limburg 3920",
    "addr:housenumber":"28",
    "addr:postcode":"3920",
    "addr:street":"Grote Hoef",
    "iso:country":"BE",
    "sg:address":"Grote Hoef 28",
    "sg:city":"Lommel",
    "sg:orig_category":"Kapsalons",
    "sg:phone":"+32 11 54 16 98",
    "sg:postcode":"3920",
    "sg:province":"Limburg",
    "wof:name":"Marc Wouters",
    "wof:placetype":"venue"
},
  "geometry": {"coordinates":[5.328622818,51.2233467102],"type":"Point"}
}