{
  "type": "Feature",
  "properties": {
    "addr:full":"Moenstraat 9bb Zwevegem West-Vlaanderen 8554",
    "addr:housenumber":"9bb",
    "addr:postcode":"8554",
    "addr:street":"Moenstraat",
    "iso:country":"BE",
    "sg:address":"Moenstraat 9bb",
    "sg:city":"Zwevegem",
    "sg:orig_category":"Elektrische installaties voor woningen",
    "sg:phone":"+32 56 45 72 45",
    "sg:postcode":"8554",
    "sg:province":"West-Vlaanderen",
    "wof:name":"Electro Meurisse",
    "wof:placetype":"venue"
},
  "geometry": {"coordinates":[3.3671278954,50.7572288513],"type":"Point"}
}