{
  "type": "Feature",
  "properties": {
    "addr:full":"Avenue De La Cooperation 9 Micheroux Li\u00e8ge 4630",
    "addr:housenumber":"9",
    "addr:postcode":"4630",
    "addr:street":"Avenue De La Cooperation",
    "iso:country":"BE",
    "sg:address":"Avenue De La Cooperation 9",
    "sg:city":"Micheroux",
    "sg:classifiers":[
        {
            "category":"Shopping",
            "subcategory":"Pets & Pet Supplies",
            "type":"Retail Goods"
        }
    ],
    "sg:phone":"+32 4 377 30 26",
    "sg:postcode":"4630",
    "sg:province":"Li\u00e8ge",
    "sg:tags":[
        "orthopaedic"
    ],
    "wof:name":"Runlite S.a.",
    "wof:placetype":"venue"
},
  "geometry": {"coordinates":[5.7318539619,50.6325111389],"type":"Point"}
}