{
  "type": "Feature",
  "properties": {
    "iso:country":"BE",
    "sg:address":"Rue Tribomont 69",
    "sg:city":"Pepinster (wegnez)",
    "sg:classifiers":[
        {
            "category":"Organizations",
            "subcategory":"Community Association",
            "type":"Services"
        }
    ],
    "sg:phone":"+32 87 46 84 12",
    "sg:postcode":"4860",
    "sg:province":"Li\u00e8ge",
    "sg:tags":[
        "environment",
        "organisation",
        "-"
    ],
    "wof:name":"Or\u00e9e",
    "wof:placetype":"venue"
},
  "geometry": {"coordinates":[5.8107738495,50.5896186829],"type":"Point"}
}