{
  "type": "Feature",
  "properties": {
    "addr:full":"All\u00e9e Verte 62 Vis\u00e9 Li\u00e8ge 4600",
    "addr:housenumber":"62",
    "addr:postcode":"4600",
    "addr:street":"Alle\u0301E Verte",
    "iso:country":"BE",
    "sg:address":"All\u00e9e Verte 62",
    "sg:city":"Vis\u00e9",
    "sg:orig_category":"Autombile concessionaires",
    "sg:phone":"+32 4 379 22 31",
    "sg:postcode":"4600",
    "sg:province":"Li\u00e8ge",
    "wof:name":"Gar Schyns",
    "wof:placetype":"venue"
},
  "geometry": {"coordinates":[5.6790509224,50.7355384827],"type":"Point"}
}