{
  "type": "Feature",
  "properties": {
    "addr:full":"Breulstraat 77a Moorslede West-Vlaanderen 8890",
    "addr:housenumber":"77a",
    "addr:postcode":"8890",
    "addr:street":"Breulstraat",
    "iso:country":"BE",
    "sg:address":"Breulstraat 77a",
    "sg:city":"Moorslede",
    "sg:classifiers":[
        {
            "category":"Professional",
            "subcategory":"Engineering",
            "type":"Services"
        }
    ],
    "sg:phone":"+32 51 77 91 77",
    "sg:postcode":"8890",
    "sg:province":"West-Vlaanderen",
    "sg:tags":[
        "workshop"
    ],
    "wof:name":"Vercaigne Constructies Nv",
    "wof:placetype":"venue"
},
  "geometry": {"coordinates":[3.0777349472,50.887638092],"type":"Point"}
}