{
  "type": "Feature",
  "properties": {
    "iso:country":"BE",
    "sg:address":"De Valken 26",
    "sg:city":"Arendonk",
    "sg:orig_category":"Eclairage et \u00e9quipements du foyer. Biens d'occasion",
    "sg:phone":"+32 14 67 74 07",
    "sg:postcode":"2370",
    "sg:province":"Antwerpen",
    "wof:name":"Oxfam Wereldwinkel",
    "wof:placetype":"venue"
},
  "geometry": {"coordinates":[5.086771965,51.3202438354],"type":"Point"}
}