{
  "type": "Feature",
  "properties": {
    "addr:full":"Vinkstraat 11 Willebroek Antwerpen 2830",
    "addr:housenumber":"11",
    "addr:postcode":"2830",
    "addr:street":"Vinkstraat",
    "iso:country":"BE",
    "sg:address":"Vinkstraat 11",
    "sg:city":"Willebroek",
    "sg:orig_category":"Installation \u00e9lectrique r\u00e9sidentielle",
    "sg:phone":"+32 3 886 06 19",
    "sg:postcode":"2830",
    "sg:province":"Antwerpen",
    "wof:name":"Rudiger Willaert",
    "wof:placetype":"venue"
},
  "geometry": {"coordinates":[4.3533291817,51.0580558777],"type":"Point"}
}