{
  "type": "Feature",
  "properties": {
    "addr:full":"Mariastraat 38 Brugge West-Vlaanderen 8000",
    "addr:housenumber":"38",
    "addr:postcode":"8000",
    "addr:street":"Mariastraat",
    "iso:country":"BE",
    "sg:address":"Mariastraat 38",
    "sg:city":"Brugge",
    "sg:classifiers":[
        {
            "category":"Bars & Pubs",
            "type":"Food & Drink"
        }
    ],
    "sg:phone":"+32 50 34 99 73",
    "sg:postcode":"8000",
    "sg:province":"West-Vlaanderen",
    "wof:name":"The Coffee Link",
    "wof:placetype":"venue"
},
  "geometry": {"coordinates":[3.2239830494,51.2041854858],"type":"Point"}
}