{
  "type": "Feature",
  "properties": {
    "addr:full":"Pastorijstraat 45 Wingene West-Vlaanderen 8750",
    "addr:housenumber":"45",
    "addr:postcode":"8750",
    "addr:street":"Pastorijstraat",
    "iso:country":"BE",
    "sg:address":"Pastorijstraat 45",
    "sg:city":"Wingene",
    "sg:orig_category":"Brood, gebak and snoepgoed",
    "sg:phone":"+32 51 61 15 66",
    "sg:postcode":"8750",
    "sg:province":"West-Vlaanderen",
    "wof:name":"Filip Schatteman",
    "wof:placetype":"venue"
},
  "geometry": {"coordinates":[3.215708971,51.0368041992],"type":"Point"}
}