{
  "type": "Feature",
  "properties": {
    "iso:country":"BE",
    "sg:address":"Parc Ind. Des Hauts Sarts",
    "sg:city":"Herstal",
    "sg:classifiers":[
        {
            "category":"Professional",
            "subcategory":"Computer Services",
            "type":"Services"
        }
    ],
    "sg:phone":"+32 4 264 58 16",
    "sg:postcode":"4040",
    "sg:province":"Li\u00e8ge",
    "sg:tags":[
        "-",
        "processing",
        "data"
    ],
    "wof:name":"S.a.t.i. Sa",
    "wof:placetype":"venue"
},
  "geometry": {"coordinates":[5.6277627945,50.6893463135],"type":"Point"}
}