{
  "type": "Feature",
  "properties": {
    "addr:full":"Bijkhoevelaan 7 Wijnegem Antwerpen 2110",
    "addr:housenumber":"7",
    "addr:postcode":"2110",
    "addr:street":"Bijkhoevelaan",
    "iso:country":"BE",
    "sg:address":"Bijkhoevelaan 7",
    "sg:city":"Wijnegem",
    "sg:classifiers":[
        {
            "category":"Manufacturing",
            "subcategory":"Rubber & Plastics",
            "type":"Manufacturing & Wholesale Goods"
        }
    ],
    "sg:phone":"+32 3 326 63 00",
    "sg:postcode":"2110",
    "sg:province":"Antwerpen",
    "sg:tags":[
        "hose"
    ],
    "wof:name":"Hydromeka Nv",
    "wof:placetype":"venue"
},
  "geometry": {"coordinates":[4.4941449165,51.2327423096],"type":"Point"}
}