{
  "type": "Feature",
  "properties": {
    "addr:full":"Jean-baptiste Now\u00c9lei 35 B1 Vilvoorde Vlaams-Brabant 1800",
    "addr:housenumber":"35 b1",
    "addr:postcode":"1800",
    "iso:country":"BE",
    "sg:address":"Jean-baptiste Now\u00c9lei 35 B1",
    "sg:city":"Vilvoorde",
    "sg:orig_category":"Chaussures. Maroquinerie and articles de voyage",
    "sg:phone":"+32 2 252 37 49",
    "sg:postcode":"1800",
    "sg:province":"Vlaams-Brabant",
    "wof:name":"Carpe Diem",
    "wof:placetype":"venue"
},
  "geometry": {"coordinates":[4.4258608818,50.9269294739],"type":"Point"}
}