{
  "type": "Feature",
  "properties": {
    "iso:country":"BE",
    "sg:address":"Rue De L'industrie 10",
    "sg:city":"Welkenraedt/welkenraedt",
    "sg:orig_category":"Fotogravure and zetwerk Secretariaatsdiensten",
    "sg:phone":"+32 87 88 02 64",
    "sg:postcode":"4840",
    "sg:province":"Li\u00e8ge",
    "wof:name":"Nyssen Imprimerie",
    "wof:placetype":"venue"
},
  "geometry": {"coordinates":[5.9752259254,50.6533470154],"type":"Point"}
}