{
  "type": "Feature",
  "properties": {
    "iso:country":"BE",
    "sg:address":"Rue Du March\u00c9 52",
    "sg:city":"Mons",
    "sg:orig_category":"Imprimeries and copyshops",
    "sg:phone":"+32 65 88 64 00",
    "sg:postcode":"7012",
    "sg:province":"Hainaut",
    "wof:name":"Ateliers Du Passe",
    "wof:placetype":"venue"
},
  "geometry": {"coordinates":[3.8894600868,50.4481964111],"type":"Point"}
}