{
  "type": "Feature",
  "properties": {
    "addr:full":"Hanswijkvaart 14 Mechelen Antwerpen 2800",
    "addr:housenumber":"14",
    "addr:postcode":"2800",
    "addr:street":"Hanswijkvaart",
    "iso:country":"BE",
    "sg:address":"Hanswijkvaart 14",
    "sg:city":"Mechelen",
    "sg:classifiers":[
        {
            "category":"Bars & Pubs",
            "type":"Food & Drink"
        }
    ],
    "sg:phone":"+32 15 41 03 22",
    "sg:postcode":"2800",
    "sg:province":"Antwerpen",
    "wof:name":"A.b.c.",
    "wof:placetype":"venue"
},
  "geometry": {"coordinates":[4.4833130836,51.0147285461],"type":"Point"}
}