{
  "type": "Feature",
  "properties": {
    "iso:country":"BE",
    "sg:address":"Nielerlochsstraat 4",
    "sg:city":"Maaseik",
    "sg:orig_category":"Charpentes and couvertures",
    "sg:phone":"+32 89 85 47 06",
    "sg:postcode":"3680",
    "sg:province":"Limburg",
    "wof:name":"De Nok",
    "wof:placetype":"venue"
},
  "geometry": {"coordinates":[5.791285038,51.0954208374],"type":"Point"}
}