{
  "type": "Feature",
  "properties": {
    "iso:country":"BE",
    "sg:address":"Kapellestraat 65",
    "sg:city":"Aartselaar",
    "sg:classifiers":[
        {
            "category":"Cafe",
            "type":"Food & Drink"
        }
    ],
    "sg:phone":"+32 3 887 34 24",
    "sg:postcode":"2630",
    "sg:province":"Antwerpen",
    "sg:tags":[
        "caf\u00e9s"
    ],
    "wof:name":"Caf\u00c9 Ten Dorpe",
    "wof:placetype":"venue"
},
  "geometry": {"coordinates":[4.3893890381,51.1315879822],"type":"Point"}
}