{
  "type": "Feature",
  "properties": {
    "iso:country":"BE",
    "sg:address":"Zandstraat 51",
    "sg:city":"Balen",
    "sg:orig_category":"Newspapers, magazines, periodicals - Distribution",
    "sg:phone":"+32 14 81 17 48",
    "sg:postcode":"2490",
    "sg:province":"Antwerpen",
    "wof:name":"Hinsch (dagbladhandel) Nv",
    "wof:placetype":"venue"
},
  "geometry": {"coordinates":[5.1684827805,51.1727905273],"type":"Point"}
}