{
  "type": "Feature",
  "properties": {
    "iso:country":"BE",
    "sg:address":"Overwinningsstraat 49b62",
    "sg:city":"Niel",
    "sg:orig_category":"Loodgieterij, verwarming and sanitaire installaties",
    "sg:phone":"+32 3 888 70 86",
    "sg:postcode":"2845",
    "sg:province":"Antwerpen",
    "wof:name":"Marc Van Camp",
    "wof:placetype":"venue"
},
  "geometry": {"coordinates":[4.3283100128,51.1128616333],"type":"Point"}
}