{
  "type": "Feature",
  "properties": {
    "addr:full":"Stationsstraat 63a Beernem West-Vlaanderen 8730",
    "addr:housenumber":"63a",
    "addr:postcode":"8730",
    "addr:street":"Stationsstraat",
    "iso:country":"BE",
    "sg:address":"Stationsstraat 63a",
    "sg:city":"Beernem",
    "sg:classifiers":[
        {
            "category":"Shopping",
            "subcategory":"Stationery & Office Supplies",
            "type":"Retail Goods"
        }
    ],
    "sg:phone":"+32 50 78 95 43",
    "sg:postcode":"8730",
    "sg:province":"West-Vlaanderen",
    "wof:name":"Dagbladhandel Kiekeboek",
    "wof:placetype":"venue"
},
  "geometry": {"coordinates":[3.3305470943,51.1302223206],"type":"Point"}
}