{
  "type": "Feature",
  "properties": {
    "addr:full":"Waelpoelstraat 1 Assenede Oost-Vlaanderen 9960",
    "addr:housenumber":"1",
    "addr:postcode":"9960",
    "addr:street":"Waelpoelstraat",
    "iso:country":"BE",
    "sg:address":"Waelpoelstraat 1",
    "sg:city":"Assenede",
    "sg:orig_category":"Installation \u00e9lectrique r\u00e9sidentielle",
    "sg:phone":"+32 9 344 81 98",
    "sg:postcode":"9960",
    "sg:province":"Oost-Vlaanderen",
    "wof:name":"Yvan Schaght",
    "wof:placetype":"venue"
},
  "geometry": {"coordinates":[3.7427930832,51.2208175659],"type":"Point"}
}