{
  "type": "Feature",
  "properties": {
    "addr:full":"Stationsstraat 27 Lede Oost-Vlaanderen 9340",
    "addr:housenumber":"27",
    "addr:postcode":"9340",
    "addr:street":"Stationsstraat",
    "iso:country":"BE",
    "sg:address":"Stationsstraat 27",
    "sg:city":"Lede",
    "sg:classifiers":[
        {
            "category":"Health Services",
            "subcategory":"Health Practitioner",
            "type":"Services"
        }
    ],
    "sg:phone":"+32 53 80 33 41",
    "sg:postcode":"9340",
    "sg:province":"Oost-Vlaanderen",
    "sg:tags":[
        "physiotherapist"
    ],
    "wof:name":"Keppens G",
    "wof:placetype":"venue"
},
  "geometry": {"coordinates":[3.986260891,50.9698753357],"type":"Point"}
}