{
  "type": "Feature",
  "properties": {
    "addr:full":"Bisschoppenhoslaan 643 Antwerpen (groot) Antwerpen 2100",
    "addr:housenumber":"643",
    "addr:postcode":"2100",
    "addr:street":"Bisschoppenhoslaan;Groot Antwerpen",
    "iso:country":"BE",
    "sg:address":"Bisschoppenhoslaan 643",
    "sg:city":"Antwerpen (groot)",
    "sg:orig_category":"Voedings- and genotsmiddelen Gh",
    "sg:phone":"+32 3 350 10 00",
    "sg:postcode":"2100",
    "sg:province":"Antwerpen",
    "wof:name":"Makro",
    "wof:placetype":"venue"
},
  "geometry": {"coordinates":[4.4586100578,51.2203941345],"type":"Point"}
}