{
  "type": "Feature",
  "properties": {
    "iso:country":"BE",
    "sg:address":"Molenhoekstraat 2",
    "sg:city":"Sint-gillis-waas",
    "sg:orig_category":"Fruitteelt",
    "sg:phone":"+32 3 770 74 37",
    "sg:postcode":"9170",
    "sg:province":"Oost-Vlaanderen",
    "wof:name":"Michel Thielman",
    "wof:placetype":"venue"
},
  "geometry": {"coordinates":[4.1270599365,51.2693786621],"type":"Point"}
}