{
  "type": "Feature",
  "properties": {
    "addr:full":"Antwerpsesteenweg 230 Malle Antwerpen 2390",
    "addr:housenumber":"230",
    "addr:postcode":"2390",
    "addr:street":"Antwerpsesteenweg",
    "iso:country":"BE",
    "sg:address":"Antwerpsesteenweg 230",
    "sg:city":"Malle",
    "sg:orig_category":"Assurances. Bureaux de poste",
    "sg:phone":"+32 3 312 01 34",
    "sg:postcode":"2390",
    "sg:province":"Antwerpen",
    "wof:name":"De Post",
    "wof:placetype":"venue"
},
  "geometry": {"coordinates":[4.7148151398,51.2992706299],"type":"Point"}
}