{
  "type": "Feature",
  "properties": {
    "addr:full":"Avenue De Merode 75 Rixensart Brabant Wallon 1330",
    "addr:housenumber":"75",
    "addr:postcode":"1330",
    "addr:street":"Avenue De Merode;Wallon",
    "iso:country":"BE",
    "sg:address":"Avenue De Merode 75",
    "sg:city":"Rixensart",
    "sg:orig_category":"Overheidsdiensten",
    "sg:phone":"+32 2 634 21 21",
    "sg:postcode":"1330",
    "sg:province":"Brabant Wallon",
    "wof:name":"Administration Communale",
    "wof:placetype":"venue"
},
  "geometry": {"coordinates":[4.5216231346,50.7125930786],"type":"Point"}
}