{
  "type": "Feature",
  "properties": {
    "iso:country":"BE",
    "sg:address":"Kleine Liebaardstraat 20",
    "sg:city":"Waregem",
    "sg:orig_category":"Restaurants Ruimtes voor conferenties, recepties and feesten",
    "sg:phone":"+32 56 71 97 56",
    "sg:postcode":"8792",
    "sg:province":"West-Vlaanderen",
    "wof:name":"Damberd",
    "wof:placetype":"venue"
},
  "geometry": {"coordinates":[3.3493750095,50.8861465454],"type":"Point"}
}