{
  "type": "Feature",
  "properties": {
    "iso:country":"BE",
    "sg:address":"Heerbaan 22",
    "sg:city":"Kortenaken (kersbeek-miskom)",
    "sg:classifiers":[
        {
            "category":"Building & Trades",
            "subcategory":"Construction",
            "type":"Services"
        }
    ],
    "sg:phone":"+32 16 77 72 40",
    "sg:postcode":"3472",
    "sg:province":"Vlaams-Brabant",
    "sg:tags":[
        "industrial",
        "design"
    ],
    "wof:name":"Code B",
    "wof:placetype":"venue"
},
  "geometry": {"coordinates":[4.9957590103,50.885093689],"type":"Point"}
}