{
  "type": "Feature",
  "properties": {
    "iso:country":"BE",
    "sg:address":"Esdonk 7",
    "sg:city":"Wommelgem",
    "sg:classifiers":[
        {
            "category":"Shopping",
            "subcategory":"Jewelry",
            "type":"Retail Goods"
        }
    ],
    "sg:phone":"+32 3 322 27 15",
    "sg:postcode":"2160",
    "sg:province":"Antwerpen",
    "sg:tags":[
        "jeweller",
        "-"
    ],
    "wof:name":"Janssens",
    "wof:placetype":"venue"
},
  "geometry": {"coordinates":[4.4948468208,51.2086181641],"type":"Point"}
}