{
  "type": "Feature",
  "properties": {
    "iso:country":"BE",
    "sg:address":"Motte 50",
    "sg:city":"Wemmel",
    "sg:classifiers":[
        {
            "category":"Sports & Exercise",
            "subcategory":"Sports Center",
            "type":"Entertainment"
        }
    ],
    "sg:phone":"+32 2 460 26 52",
    "sg:postcode":"1780",
    "sg:province":"Vlaams-Brabant",
    "sg:tags":[
        "terrain",
        "hors",
        "de",
        "installation",
        "sportifs"
    ],
    "wof:name":"Manege La Motte",
    "wof:placetype":"venue"
},
  "geometry": {"coordinates":[4.2944898605,50.9002914429],"type":"Point"}
}