{
  "type": "Feature",
  "properties": {
    "addr:full":"Diestsesteenweg 104 Kessel-lo Vlaams-Brabant 3010",
    "addr:housenumber":"104",
    "addr:postcode":"3010",
    "addr:street":"Diestsesteenweg",
    "iso:country":"BE",
    "sg:address":"Diestsesteenweg 104",
    "sg:city":"Kessel-lo",
    "sg:orig_category":"Quincailleries. Mat\u00e9riaux de construction Travaux d'isolation",
    "sg:phone":"+32 16 25 98 26",
    "sg:postcode":"3010",
    "sg:province":"Vlaams-Brabant",
    "wof:name":"Amphion Finition Et Acoustique",
    "wof:placetype":"venue"
},
  "geometry": {"coordinates":[4.7210597992,50.8837471008],"type":"Point"}
}