{
  "type": "Feature",
  "properties": {
    "addr:full":"Rue Croix-ou-pile 2 Frasnes-lez-anvaing Hainaut 7912",
    "addr:housenumber":"2",
    "addr:postcode":"7912",
    "addr:street":"Rue Croix-Ou-Pile",
    "iso:country":"BE",
    "sg:address":"Rue Croix-ou-pile 2",
    "sg:city":"Frasnes-lez-anvaing",
    "sg:orig_category":"Rundveehouders",
    "sg:phone":"+32 69 76 80 06",
    "sg:postcode":"7912",
    "sg:province":"Hainaut",
    "wof:name":"Andre De Smet",
    "wof:placetype":"venue"
},
  "geometry": {"coordinates":[3.6177120209,50.7198982239],"type":"Point"}
}