{
  "type": "Feature",
  "properties": {
    "iso:country":"BE",
    "sg:address":"Rue Louis De Brouck\u00e8re 46",
    "sg:city":"Charleroi (roux)",
    "sg:classifiers":[
        {
            "category":"Health Services",
            "subcategory":"Nursing And Care Facility",
            "type":"Services"
        }
    ],
    "sg:phone":"+32 71 45 22 45",
    "sg:postcode":"6044",
    "sg:province":"Hainaut",
    "sg:tags":[
        "home"
    ],
    "wof:name":"Adant Laurent",
    "wof:placetype":"venue"
},
  "geometry": {"coordinates":[4.3904280663,50.4440498352],"type":"Point"}
}