{
  "type": "Feature",
  "properties": {
    "iso:country":"BE",
    "sg:address":"Interleuvenlaan 23b2",
    "sg:city":"Leuven",
    "sg:orig_category":"R\u00e9alisation de programmes and logiciels",
    "sg:phone":"+32 16 39 30 60",
    "sg:postcode":"3001",
    "sg:province":"Vlaams-Brabant",
    "wof:name":"Application Engineers",
    "wof:placetype":"venue"
},
  "geometry": {"coordinates":[4.7344589233,50.8467216492],"type":"Point"}
}