{
  "type": "Feature",
  "properties": {
    "iso:country":"BE",
    "sg:address":"Molenstraat 96",
    "sg:city":"Heusden-zolder",
    "sg:orig_category":"Rev\u00eatements pour sols and murs. Peinture. Eclairage et \u00e9quipements du foyer",
    "sg:phone":"+32 11 53 66 55",
    "sg:postcode":"3550",
    "sg:province":"Limburg",
    "wof:name":"Serge Tognon Etore",
    "wof:placetype":"venue"
},
  "geometry": {"coordinates":[5.3108301163,51.0294303894],"type":"Point"}
}