{
  "type": "Feature",
  "properties": {
    "addr:full":"Lintsesteenweg 308b Duffel Antwerpen 2570",
    "addr:housenumber":"308b",
    "addr:postcode":"2570",
    "addr:street":"Lintsesteenweg",
    "iso:country":"BE",
    "sg:address":"Lintsesteenweg 308b",
    "sg:city":"Duffel",
    "sg:classifiers":[
        {
            "category":"Farming",
            "subcategory":"Crops",
            "type":"Manufacturing & Wholesale Goods"
        }
    ],
    "sg:phone":"+32 15 31 56 89",
    "sg:postcode":"2570",
    "sg:province":"Antwerpen",
    "sg:tags":[
        "vegetable",
        "fruit",
        "-",
        "grower"
    ],
    "wof:name":"Lauwers W Bvba",
    "wof:placetype":"venue"
},
  "geometry": {"coordinates":[4.4950799942,51.1153755188],"type":"Point"}
}