{
  "type": "Feature",
  "properties": {
    "iso:country":"BE",
    "sg:address":"Tasseniersstraat 22",
    "sg:city":"Galmaarden",
    "sg:orig_category":"Elektrische installaties voor woningen",
    "sg:phone":"+32 54 58 06 15",
    "sg:postcode":"1570",
    "sg:province":"Vlaams-Brabant",
    "wof:name":"Pascal Somers",
    "wof:placetype":"venue"
},
  "geometry": {"coordinates":[3.978718996,50.7584457397],"type":"Point"}
}