{
  "type": "Feature",
  "properties": {
    "addr:full":"Rue Grand'rue 1 Trooz (for\u00eat) Li\u00e8ge 4870",
    "addr:housenumber":"1",
    "addr:postcode":"4870",
    "addr:street":"Rue Grand'Rue;Fore\u0302T",
    "iso:country":"BE",
    "sg:address":"Rue Grand'rue 1",
    "sg:city":"Trooz (for\u00eat)",
    "sg:classifiers":[
        {
            "category":"Retail",
            "subcategory":"Auto Repair",
            "type":"Services"
        }
    ],
    "sg:phone":"+32 4 351 64 14",
    "sg:postcode":"4870",
    "sg:province":"Li\u00e8ge",
    "sg:tags":[
        "garage"
    ],
    "wof:name":"Markiewicz",
    "wof:placetype":"venue"
},
  "geometry": {"coordinates":[5.673429966,50.5785293579],"type":"Point"}
}