{
  "type": "Feature",
  "properties": {
    "iso:country":"BE",
    "sg:address":"Heerweg 75",
    "sg:city":"Halle",
    "sg:orig_category":"Enseignement maternel and primaire",
    "sg:phone":"+32 2 361 13 62",
    "sg:postcode":"1502",
    "sg:province":"Vlaams-Brabant",
    "wof:name":"Vrije Basisschool",
    "wof:placetype":"venue"
},
  "geometry": {"coordinates":[4.2239050865,50.7178115845],"type":"Point"}
}