{
  "type": "Feature",
  "properties": {
    "addr:full":"Halven Akker 7 Wetteren Oost-Vlaanderen 9230",
    "addr:housenumber":"7",
    "addr:postcode":"9230",
    "addr:street":"Halven Akker",
    "iso:country":"BE",
    "sg:address":"Halven Akker 7",
    "sg:city":"Wetteren",
    "sg:orig_category":"Woningbouw",
    "sg:phone":"+32 9 369 97 03",
    "sg:postcode":"9230",
    "sg:province":"Oost-Vlaanderen",
    "wof:name":"Dirk De Mulder",
    "wof:placetype":"venue"
},
  "geometry": {"coordinates":[3.8932170868,50.9979782104],"type":"Point"}
}