{
  "type": "Feature",
  "properties": {
    "addr:full":"Avenue Des Alouettes 25 Wemmel Vlaams-Brabant 1780",
    "addr:housenumber":"25",
    "addr:postcode":"1780",
    "addr:street":"Avenue Des Alouettes;Vlaams-Brabant",
    "iso:country":"BE",
    "sg:address":"Avenue Des Alouettes 25",
    "sg:city":"Wemmel",
    "sg:classifiers":[
        {
            "category":"Professional",
            "subcategory":"Art Services",
            "type":"Services"
        }
    ],
    "sg:phone":"+32 2 460 73 99",
    "sg:postcode":"1780",
    "sg:province":"Vlaams-Brabant",
    "sg:tags":[
        "photographer"
    ],
    "wof:name":"Blizzard",
    "wof:placetype":"venue"
},
  "geometry": {"coordinates":[4.315759182,50.9229049683],"type":"Point"}
}