{
  "type": "Feature",
  "properties": {
    "iso:country":"BE",
    "sg:address":"Avenue Charles-quint 111",
    "sg:city":"Ganshoren",
    "sg:classifiers":[
        {
            "category":"Fast Food",
            "type":"Food & Drink"
        }
    ],
    "sg:phone":"+32 2 427 82 74",
    "sg:postcode":"1083",
    "sg:province":"Bruxelles-Capitale",
    "sg:tags":[
        "\u00c0",
        "emporter",
        "restaurants"
    ],
    "wof:name":"Asia Fast Food",
    "wof:placetype":"venue"
},
  "geometry": {"coordinates":[4.3108081818,50.8686904907],"type":"Point"}
}