{
  "type": "Feature",
  "properties": {
    "iso:country":"BE",
    "sg:address":"Espace Du Coeur De Ville 11 Box 101",
    "sg:city":"Ottignies-louvain-la-neuve (ottignies)",
    "sg:classifiers":[
        {
            "category":"Professional",
            "subcategory":"Management & Consulting",
            "type":"Services"
        }
    ],
    "sg:phone":"+32 10 43 51 20",
    "sg:postcode":"1340",
    "sg:province":"Brabant Wallon",
    "sg:tags":[
        "marketing",
        "-",
        "consultant"
    ],
    "wof:name":"Everaets & Co Sprl",
    "wof:placetype":"venue"
},
  "geometry": {"coordinates":[4.5677790642,50.6650123596],"type":"Point"}
}