{
  "type": "Feature",
  "properties": {
    "addr:full":"Joseph Baecqstraat 28 Molenbeek Bruxelles-Capitale 1080",
    "addr:housenumber":"28",
    "addr:postcode":"1080",
    "addr:street":"Baecqstraat",
    "iso:country":"BE",
    "sg:address":"Joseph Baecqstraat 28",
    "sg:city":"Molenbeek",
    "sg:orig_category":"Huisdieren and benodigdheden Royal Canin",
    "sg:phone":"+32 2 414 56 11",
    "sg:postcode":"1080",
    "sg:province":"Bruxelles-Capitale",
    "wof:name":"Tom & Co",
    "wof:placetype":"venue"
},
  "geometry": {"coordinates":[4.3186640739,50.8495368958],"type":"Point"}
}