{
  "type": "Feature",
  "properties": {
    "addr:full":"Rue De Wavre 100 Hannut Li\u00e8ge 4280",
    "addr:housenumber":"100",
    "addr:postcode":"4280",
    "addr:street":"Rue De Wavre",
    "iso:country":"BE",
    "sg:address":"Rue De Wavre 100",
    "sg:city":"Hannut",
    "sg:classifiers":[
        {
            "category":"Health Services",
            "subcategory":"Doctor",
            "type":"Services"
        }
    ],
    "sg:phone":"+32 19 58 88 27",
    "sg:postcode":"4280",
    "sg:province":"Li\u00e8ge",
    "sg:tags":[
        "medicinephysicians",
        "surgeon"
    ],
    "wof:name":"Bataille Anne-christine",
    "wof:placetype":"venue"
},
  "geometry": {"coordinates":[5.0638399124,50.6689682007],"type":"Point"}
}