{
  "type": "Feature",
  "properties": {
    "addr:full":"E. Eylenboschstraat 25 Dilbeek Vlaams-Brabant 1703",
    "addr:housenumber":"25",
    "addr:postcode":"1703",
    "addr:street":"E. Eylenboschstraat",
    "iso:country":"BE",
    "sg:address":"E. Eylenboschstraat 25",
    "sg:city":"Dilbeek",
    "sg:orig_category":"Krantenwinkels Rookartikelen",
    "sg:phone":"+32 2 569 80 38",
    "sg:postcode":"1703",
    "sg:province":"Vlaams-Brabant",
    "wof:name":"Boekhandel De Markt",
    "wof:placetype":"venue"
},
  "geometry": {"coordinates":[4.1927580833,50.8350601196],"type":"Point"}
}