{
  "type": "Feature",
  "properties": {
    "iso:country":"BE",
    "sg:address":"Boulevard Du Parc 15",
    "sg:city":"Ath",
    "sg:orig_category":"Dranken Gh",
    "sg:phone":"+32 68 28 23 41",
    "sg:postcode":"7800",
    "sg:province":"Hainaut",
    "wof:name":"Jean Provost",
    "wof:placetype":"venue"
},
  "geometry": {"coordinates":[3.7823359966,50.6333465576],"type":"Point"}
}