{
  "type": "Feature",
  "properties": {
    "iso:country":"BE",
    "sg:address":"Place Notre-dame De La Paix 4",
    "sg:city":"Namur (erpent)",
    "sg:classifiers":[
        {
            "category":"Arena",
            "subcategory":"Sports Club",
            "type":"Entertainment"
        }
    ],
    "sg:phone":"+32 81 30 74 64",
    "sg:postcode":"5101",
    "sg:province":"Namur",
    "wof:name":"T.t. Champ D'en - Haut",
    "wof:placetype":"venue"
},
  "geometry": {"coordinates":[4.8935599327,50.4421081543],"type":"Point"}
}