{
  "type": "Feature",
  "properties": {
    "iso:country":"BE",
    "sg:address":"Nassaustraat 7",
    "sg:city":"Antwerpen",
    "sg:classifiers":[
        {
            "category":"Shopping",
            "subcategory":"Computers & Home Electronics",
            "type":"Retail Goods"
        }
    ],
    "sg:phone":"+32 3 226 95 32",
    "sg:postcode":"2000",
    "sg:province":"Antwerpen",
    "sg:tags":[
        "marine",
        "-"
    ],
    "wof:name":"A M E Bvba Bvba",
    "wof:placetype":"venue"
},
  "geometry": {"coordinates":[4.4056539536,51.2308120728],"type":"Point"}
}