{
  "type": "Feature",
  "properties": {
    "addr:full":"Onze-lieve-vrouwstraat 82 Mol Antwerpen 2400",
    "addr:housenumber":"82",
    "addr:postcode":"2400",
    "addr:street":"Onze-Lieve-Vrouwstraat",
    "iso:country":"BE",
    "sg:address":"Onze-lieve-vrouwstraat 82",
    "sg:city":"Mol",
    "sg:orig_category":"Kinderopvang",
    "sg:phone":"+32 14 32 24 13",
    "sg:postcode":"2400",
    "sg:province":"Antwerpen",
    "wof:name":"Mowgli",
    "wof:placetype":"venue"
},
  "geometry": {"coordinates":[5.1492609978,51.1925430298],"type":"Point"}
}