{
  "type": "Feature",
  "properties": {
    "addr:full":"Berkenlaan 35 Balen (olmen) Antwerpen 2491",
    "addr:housenumber":"35",
    "addr:postcode":"2491",
    "addr:street":"Berkenlaan",
    "iso:country":"BE",
    "sg:address":"Berkenlaan 35",
    "sg:city":"Balen (olmen)",
    "sg:classifiers":[
        {
            "category":"Recreation",
            "subcategory":"Amusement Park",
            "type":"Entertainment"
        }
    ],
    "sg:phone":"+32 14 30 46 21",
    "sg:postcode":"2491",
    "sg:province":"Antwerpen",
    "sg:tags":[
        "attraction",
        "-",
        "sale",
        "fair",
        "hiring"
    ],
    "wof:name":"Go-carts Mammoet",
    "wof:placetype":"venue"
},
  "geometry": {"coordinates":[5.1542630196,51.139919281],"type":"Point"}
}