{
  "type": "Feature",
  "properties": {
    "addr:full":"Krepelstr 2 Denderwindeke 9490",
    "addr:housenumber":"2",
    "addr:postcode":"9490",
    "addr:street":"Krepelstr",
    "iso:country":"BE",
    "sg:address":"Krepelstr 2",
    "sg:city":"Denderwindeke",
    "sg:classifiers":[
        {
            "category":"Banks & Credit Unions",
            "subcategory":"Bank",
            "type":"Services"
        }
    ],
    "sg:phone":"+32 54 32 58 06",
    "sg:postcode":"9490",
    "wof:name":"Kredietbank",
    "wof:placetype":"venue"
},
  "geometry": {"coordinates":[6.5464601517,53.0481491089],"type":"Point"}
}