{
  "type": "Feature",
  "properties": {
    "iso:country":"BE",
    "sg:address":"Chauss\u00e9e De Bruxelles 198",
    "sg:city":"Tournai",
    "sg:classifiers":[
        {
            "category":"Professional",
            "subcategory":"Accounting & Tax Preparation",
            "type":"Services"
        }
    ],
    "sg:phone":"+32 69 22 74 78",
    "sg:postcode":"7500",
    "sg:province":"Hainaut",
    "sg:tags":[
        "accountant"
    ],
    "wof:name":"Sinaf B",
    "wof:placetype":"venue"
},
  "geometry": {"coordinates":[3.4402389526,50.6003799438],"type":"Point"}
}