{
  "type": "Feature",
  "properties": {
    "iso:country":"BE",
    "sg:address":"Izegemseaardeweg 144",
    "sg:city":"Roeselare",
    "sg:classifiers":[
        {
            "category":"Manufacturing",
            "subcategory":"Tools & Machinery",
            "type":"Manufacturing & Wholesale Goods"
        }
    ],
    "sg:phone":"+32 51 26 04 30",
    "sg:postcode":"8800",
    "sg:province":"West-Vlaanderen",
    "sg:tags":[
        "boring",
        "drilling"
    ],
    "wof:name":"Target Cnc Machinery Nv",
    "wof:placetype":"venue"
},
  "geometry": {"coordinates":[3.1512858868,50.9596862793],"type":"Point"}
}