{
  "type": "Feature",
  "properties": {
    "addr:full":"Rue Des Combattants 3 Tournai Hainaut 7538",
    "addr:housenumber":"3",
    "addr:postcode":"7538",
    "addr:street":"Rue Des Combattants",
    "iso:country":"BE",
    "sg:address":"Rue Des Combattants 3",
    "sg:city":"Tournai",
    "sg:classifiers":[
        {
            "category":"Cafe",
            "type":"Food & Drink"
        }
    ],
    "sg:phone":"+32 69 44 47 25",
    "sg:postcode":"7538",
    "sg:province":"Hainaut",
    "sg:tags":[
        "caf\u00e9s"
    ],
    "wof:name":"Juliane Gosseye",
    "wof:placetype":"venue"
},
  "geometry": {"coordinates":[3.5003180504,50.5690383911],"type":"Point"}
}