{
  "type": "Feature",
  "properties": {
    "iso:country":"BE",
    "sg:address":"Grand-rue 70",
    "sg:city":"Leuze-en-hainaut",
    "sg:classifiers":[
        {
            "category":"Shopping",
            "subcategory":"Bicycles & Sporting Goods",
            "type":"Retail Goods"
        }
    ],
    "sg:phone":"+32 69 66 14 41",
    "sg:postcode":"7900",
    "sg:province":"Hainaut",
    "sg:tags":[
        "article",
        "de",
        "sport",
        "camping"
    ],
    "wof:name":"Maison Sport Equip",
    "wof:placetype":"venue"
},
  "geometry": {"coordinates":[3.6179571152,50.5996017456],"type":"Point"}
}