{
  "type": "Feature",
  "properties": {
    "addr:full":"Rue De Jemeppe 18 Ans Li\u00e8ge 4431",
    "addr:housenumber":"18",
    "addr:postcode":"4431",
    "addr:street":"Rue De Jemeppe",
    "iso:country":"BE",
    "sg:address":"Rue De Jemeppe 18",
    "sg:city":"Ans",
    "sg:orig_category":"M\u00e9decins and sp\u00e9cialistes",
    "sg:phone":"+32 4 246 43 39",
    "sg:postcode":"4431",
    "sg:province":"Li\u00e8ge",
    "wof:name":"Antonio Sticca",
    "wof:placetype":"venue"
},
  "geometry": {"coordinates":[5.504034996,50.6656265259],"type":"Point"}
}