{
  "type": "Feature",
  "properties": {
    "iso:country":"BE",
    "sg:address":"Vlaanderenstraat 25",
    "sg:city":"Koekelare",
    "sg:classifiers":[
        {
            "category":"Professional",
            "subcategory":"Accounting & Tax Preparation",
            "type":"Services"
        }
    ],
    "sg:phone":"+32 51 58 04 34",
    "sg:postcode":"8680",
    "sg:province":"West-Vlaanderen",
    "sg:tags":[
        "bookkeeper"
    ],
    "wof:name":"Lagrou F",
    "wof:placetype":"venue"
},
  "geometry": {"coordinates":[2.982820034,51.0813484192],"type":"Point"}
}