{
  "type": "Feature",
  "properties": {
    "addr:full":"Avenue De Norv\u00c8ge 3ba Malmedy Li\u00e8ge 4960",
    "addr:housenumber":"3ba",
    "addr:postcode":"4960",
    "addr:street":"Avenue De Norve\u0300Ge",
    "iso:country":"BE",
    "sg:address":"Avenue De Norv\u00c8ge 3ba",
    "sg:city":"Malmedy",
    "sg:orig_category":"P\u00e9pini\u00e9ristes",
    "sg:phone":"+32 80 77 14 16",
    "sg:postcode":"4960",
    "sg:province":"Li\u00e8ge",
    "wof:name":"Fe. Pamwood-van Zuylen",
    "wof:placetype":"venue"
},
  "geometry": {"coordinates":[6.005010128,50.4160919189],"type":"Point"}
}