{
  "type": "Feature",
  "properties": {
    "addr:full":"Rue Grande 75 Dinant Namur 5500",
    "addr:housenumber":"75",
    "addr:postcode":"5500",
    "addr:street":"Rue Grande",
    "iso:country":"BE",
    "sg:address":"Rue Grande 75",
    "sg:city":"Dinant",
    "sg:orig_category":"Electrom\u00e9nager, t\u00e9l\u00e9visions and radios. Eclairage et \u00e9quipements du foyer. Jeux and jouets. Souvenir",
    "sg:phone":"+32 82 22 66 53",
    "sg:postcode":"5500",
    "sg:province":"Namur",
    "wof:name":"Blokker",
    "wof:placetype":"venue"
},
  "geometry": {"coordinates":[4.9145231247,50.2580947876],"type":"Point"}
}