{
  "type": "Feature",
  "properties": {
    "addr:full":"Markt 36 Oudenaarde Oost-Vlaanderen 9700",
    "addr:housenumber":"36",
    "addr:postcode":"9700",
    "addr:street":"Markt",
    "iso:country":"BE",
    "sg:address":"Markt 36",
    "sg:city":"Oudenaarde",
    "sg:classifiers":[
        {
            "category":"Restaurant",
            "type":"Food & Drink"
        }
    ],
    "sg:phone":"+32 55 31 03 46",
    "sg:postcode":"9700",
    "sg:province":"Oost-Vlaanderen",
    "wof:name":"Restaurant Verly",
    "wof:placetype":"venue"
},
  "geometry": {"coordinates":[3.6040160656,50.8425102234],"type":"Point"}
}