{
  "type": "Feature",
  "properties": {
    "iso:country":"BE",
    "sg:address":"Rue De La Go\u00cbtte 85",
    "sg:city":"Braine-l\u00b4alleud",
    "sg:orig_category":"Binnenhuisarchitecten Verlichting and huishoudartikelen",
    "sg:phone":"+32 2 384 67 60",
    "sg:postcode":"1420",
    "sg:province":"Brabant Wallon",
    "wof:name":"Int\u00c9rieur",
    "wof:placetype":"venue"
},
  "geometry": {"coordinates":[4.3656611443,50.684211731],"type":"Point"}
}