{
  "type": "Feature",
  "properties": {
    "addr:full":"Rommekensbergstraat 59 Mechelen Antwerpen 2800",
    "addr:housenumber":"59",
    "addr:postcode":"2800",
    "addr:street":"Rommekensbergstraat",
    "iso:country":"BE",
    "sg:address":"Rommekensbergstraat 59",
    "sg:city":"Mechelen",
    "sg:orig_category":"Verhuur televisie- and audiovisuele apparatuur",
    "sg:phone":"+32 15 21 09 63",
    "sg:postcode":"2800",
    "sg:province":"Antwerpen",
    "wof:name":"Tropical",
    "wof:placetype":"venue"
},
  "geometry": {"coordinates":[4.4622402191,51.0424385071],"type":"Point"}
}