{
  "type": "Feature",
  "properties": {
    "addr:full":"Heirbrugstraat 155 Lokeren Oost-Vlaanderen 9160",
    "addr:housenumber":"155",
    "addr:postcode":"9160",
    "addr:street":"Heirbrugstraat",
    "iso:country":"BE",
    "sg:address":"Heirbrugstraat 155",
    "sg:city":"Lokeren",
    "sg:classifiers":[
        {
            "category":"Bars & Pubs",
            "type":"Food & Drink"
        }
    ],
    "sg:phone":"+32 9 348 07 35",
    "sg:postcode":"9160",
    "sg:province":"Oost-Vlaanderen",
    "wof:name":"De Droge Keel",
    "wof:placetype":"venue"
},
  "geometry": {"coordinates":[3.9768929482,51.1052513123],"type":"Point"}
}