{
  "type": "Feature",
  "properties": {
    "iso:country":"BE",
    "sg:address":"Legen Heirweg 36",
    "sg:city":"Temse (elversele)",
    "sg:classifiers":[
        {
            "category":"Banks & Credit Unions",
            "subcategory":"Investment Brokerage",
            "type":"Services"
        }
    ],
    "sg:phone":"+32 52 46 19 22",
    "sg:postcode":"9140",
    "sg:province":"Oost-Vlaanderen",
    "wof:name":"Baert & Rooms Bvba",
    "wof:placetype":"venue"
},
  "geometry": {"coordinates":[4.1454157829,51.1139030457],"type":"Point"}
}