{
  "type": "Feature",
  "properties": {
    "addr:full":"Eichenberg 9a Eupen Li\u00e8ge 4700",
    "addr:housenumber":"9a",
    "addr:postcode":"4700",
    "addr:street":"Eichenberg",
    "iso:country":"BE",
    "sg:address":"Eichenberg 9a",
    "sg:city":"Eupen",
    "sg:classifiers":[
        {
            "category":"Professional",
            "subcategory":"Management & Consulting",
            "type":"Services"
        }
    ],
    "sg:phone":"+32 87 56 16 94",
    "sg:postcode":"4700",
    "sg:province":"Li\u00e8ge",
    "sg:tags":[
        "consultant"
    ],
    "wof:name":"Emmanuel Noel Management Consulting",
    "wof:placetype":"venue"
},
  "geometry": {"coordinates":[6.0483651161,50.6237106323],"type":"Point"}
}