{
  "type": "Feature",
  "properties": {
    "iso:country":"BE",
    "sg:address":"Quai Jean-baptiste Culot 5 Box 3",
    "sg:city":"Dinant",
    "sg:classifiers":[
        {
            "category":"Health Services",
            "subcategory":"Doctor",
            "type":"Services"
        }
    ],
    "sg:phone":"+32 82 22 44 22",
    "sg:postcode":"5500",
    "sg:province":"Namur",
    "sg:tags":[
        "medicinephysicians",
        "surgeon"
    ],
    "wof:name":"Frippiat M",
    "wof:placetype":"venue"
},
  "geometry": {"coordinates":[4.9087572098,50.2631721497],"type":"Point"}
}