{
  "type": "Feature",
  "properties": {
    "iso:country":"BE",
    "sg:address":"Rue De La Fontaine 23",
    "sg:city":"Florenville",
    "sg:classifiers":[
        {
            "category":"Health Services",
            "subcategory":"Health Practitioner",
            "type":"Services"
        }
    ],
    "sg:phone":"+32 61 32 83 08",
    "sg:postcode":"6820",
    "sg:province":"Luxembourg",
    "sg:tags":[
        "physiotherapist"
    ],
    "wof:name":"Van Leuven Nathalie",
    "wof:placetype":"venue"
},
  "geometry": {"coordinates":[5.3087158203,49.6981964111],"type":"Point"}
}