{
  "type": "Feature",
  "properties": {
    "iso:country":"BE",
    "sg:address":"Baron Jacques De Dixmudestraat 18",
    "sg:city":"Hoeilaart",
    "sg:classifiers":[
        {
            "category":"Professional",
            "type":"Services"
        }
    ],
    "sg:phone":"+32 2 657 25 32",
    "sg:postcode":"1560",
    "sg:province":"Vlaams-Brabant",
    "sg:tags":[
        "packing",
        "-"
    ],
    "wof:name":"M & Bee",
    "wof:placetype":"venue"
},
  "geometry": {"coordinates":[4.4704380035,50.7580986023],"type":"Point"}
}