{
  "type": "Feature",
  "properties": {
    "addr:full":"Rue Sous-le-ch\u00e2teau 87 Huy Li\u00e8ge 4500",
    "addr:housenumber":"87",
    "addr:postcode":"4500",
    "addr:street":"Rue Sous-Le-Cha\u0302Teau",
    "iso:country":"BE",
    "sg:address":"Rue Sous-le-ch\u00e2teau 87",
    "sg:city":"Huy",
    "sg:classifiers":[
        {
            "category":"Personal",
            "subcategory":"Beauty Salon",
            "type":"Services"
        }
    ],
    "sg:phone":"+32 85 21 12 90",
    "sg:postcode":"4500",
    "sg:province":"Li\u00e8ge",
    "sg:tags":[
        "lady",
        "-",
        "hairdressing"
    ],
    "wof:name":"Monique",
    "wof:placetype":"venue"
},
  "geometry": {"coordinates":[5.2377200127,50.5155410767],"type":"Point"}
}