{
  "type": "Feature",
  "properties": {
    "addr:full":"Groeneweg 87 Overijse Vlaams-Brabant 3090",
    "addr:housenumber":"87",
    "addr:postcode":"3090",
    "addr:street":"Groeneweg",
    "iso:country":"BE",
    "sg:address":"Groeneweg 87",
    "sg:city":"Overijse",
    "sg:orig_category":"Producteurs de fruits",
    "sg:phone":"+32 2 687 84 96",
    "sg:postcode":"3090",
    "sg:province":"Vlaams-Brabant",
    "wof:name":"Joseph Goossens",
    "wof:placetype":"venue"
},
  "geometry": {"coordinates":[4.5401668549,50.7867736816],"type":"Point"}
}