{
  "type": "Feature",
  "properties": {
    "addr:full":"Rue Des Ecoles 30 Court-saint-etienne Brabant Wallon 1490",
    "addr:housenumber":"30;1490",
    "addr:street":"Rue Des Ecoles",
    "iso:country":"BE",
    "sg:address":"Rue Des Ecoles 30",
    "sg:city":"Court-saint-etienne",
    "sg:classifiers":[
        {
            "category":"Health Services",
            "subcategory":"Health Practitioner",
            "type":"Services"
        }
    ],
    "sg:phone":"+32 10 61 27 79",
    "sg:postcode":"1490",
    "sg:province":"Brabant Wallon",
    "sg:tags":[
        "physiotherapist"
    ],
    "wof:name":"Nolet Jocelyne",
    "wof:placetype":"venue"
},
  "geometry": {"coordinates":[4.5715198517,50.6472930908],"type":"Point"}
}