{
  "type": "Feature",
  "properties": {
    "addr:full":"Waterstraat 64 Tienen Vlaams-Brabant 3300",
    "addr:housenumber":"64",
    "addr:postcode":"3300",
    "addr:street":"Waterstraat",
    "iso:country":"BE",
    "sg:address":"Waterstraat 64",
    "sg:city":"Tienen",
    "sg:orig_category":"Diverse meubelen Fab Installatie van houten of kunststof schrijnwerk Installatie van metalen schrijn",
    "sg:phone":"+32 16 82 33 95",
    "sg:postcode":"3300",
    "sg:province":"Vlaams-Brabant",
    "wof:name":"R. Vandenbosch",
    "wof:placetype":"venue"
},
  "geometry": {"coordinates":[4.930077076,50.8096694946],"type":"Point"}
}