{
  "type": "Feature",
  "properties": {
    "addr:full":"Rue De Deminche 115 Floreffe Namur 5150",
    "addr:housenumber":"115",
    "addr:postcode":"5150",
    "addr:street":"Rue De Deminche",
    "iso:country":"BE",
    "sg:address":"Rue De Deminche 115",
    "sg:city":"Floreffe",
    "sg:orig_category":"D\u00e9molition d\u00b4immeubles and terrassements",
    "sg:phone":"+32 81 44 48 16",
    "sg:postcode":"5150",
    "sg:province":"Namur",
    "wof:name":"Andre Verstraete",
    "wof:placetype":"venue"
},
  "geometry": {"coordinates":[4.7128667831,50.4318618774],"type":"Point"}
}