{
  "type": "Feature",
  "properties": {
    "iso:country":"BE",
    "sg:address":"Trieu De La Bouve 2",
    "sg:city":"Honnelles",
    "sg:classifiers":[
        {
            "category":"Building & Trades",
            "subcategory":"Construction",
            "type":"Services"
        }
    ],
    "sg:phone":"+32 65 65 20 26",
    "sg:postcode":"7387",
    "sg:province":"Hainaut",
    "sg:tags":[
        "commerce",
        "equipement",
        "de",
        "\u00e9v\u00e9nements",
        "pour",
        "banquet",
        "mat\u00e9riel",
        "location",
        "diver"
    ],
    "wof:name":"Brasserie Fayt-le-franc",
    "wof:placetype":"venue"
},
  "geometry": {"coordinates":[3.6959199905,50.3683853149],"type":"Point"}
}