{
  "type": "Feature",
  "properties": {
    "iso:country":"BE",
    "sg:address":"Grand'route 22",
    "sg:city":"Mons",
    "sg:classifiers":[
        {
            "category":"Retail",
            "subcategory":"Veterinary Services",
            "type":"Services"
        }
    ],
    "sg:phone":"+32 65 33 90 30",
    "sg:postcode":"7000",
    "sg:province":"Hainaut",
    "sg:tags":[
        "veterinarian"
    ],
    "wof:name":"Soudans G",
    "wof:placetype":"venue"
},
  "geometry": {"coordinates":[3.952878952,50.4551277161],"type":"Point"}
}