{
  "type": "Feature",
  "properties": {
    "iso:country":"BE",
    "sg:address":"Lippenslaan 349",
    "sg:city":"Knokke",
    "sg:classifiers":[
        {
            "category":"Government",
            "subcategory":"Fire Station",
            "type":"Public Place"
        }
    ],
    "sg:phone":"+32 50 61 30 46",
    "sg:postcode":"8300",
    "sg:province":"West-Vlaanderen",
    "sg:tags":[
        "packard",
        "nec",
        "bell"
    ],
    "wof:name":"Photo-hall Knokke",
    "wof:placetype":"venue"
},
  "geometry": {"coordinates":[3.2886390686,51.3516426086],"type":"Point"}
}