{
  "type": "Feature",
  "properties": {
    "addr:full":"Everdijkruis 17 Wuustwezel Antwerpen 2990",
    "addr:housenumber":"17",
    "addr:postcode":"2990",
    "addr:street":"Everdijkruis",
    "iso:country":"BE",
    "sg:address":"Everdijkruis 17",
    "sg:city":"Wuustwezel",
    "sg:orig_category":"Epiceries",
    "sg:phone":"+32 3 663 65 39",
    "sg:postcode":"2990",
    "sg:province":"Antwerpen",
    "wof:name":"Jan Eelens",
    "wof:placetype":"venue"
},
  "geometry": {"coordinates":[4.5446557999,51.3421859741],"type":"Point"}
}