{
  "type": "Feature",
  "properties": {
    "addr:full":"F Smeyersstraat 8 Scherpenheuvel Vlaams-Brabant 3270",
    "addr:housenumber":"8",
    "addr:postcode":"3270",
    "addr:street":"Smeyersstraat",
    "iso:country":"BE",
    "sg:address":"F Smeyersstraat 8",
    "sg:city":"Scherpenheuvel",
    "sg:orig_category":"Afbraak- and draineerwerken Afvalwaterverwerking and ontstoppingsdiensten",
    "sg:phone":"+32 13 77 15 31",
    "sg:postcode":"3270",
    "sg:province":"Vlaams-Brabant",
    "wof:name":"Land- En Tuinbouw",
    "wof:placetype":"venue"
},
  "geometry": {"coordinates":[4.9781332016,50.9695358276],"type":"Point"}
}