{
  "type": "Feature",
  "properties": {
    "iso:country":"BE",
    "sg:address":"Mechelsesteenweg 3",
    "sg:city":"Antwerpen",
    "sg:orig_category":"Assurances. Agences immobili\u00e8res. Location d'habitations",
    "sg:phone":"+32 3 234 14 66",
    "sg:postcode":"2018",
    "sg:province":"Antwerpen",
    "wof:name":"Immovast",
    "wof:placetype":"venue"
},
  "geometry": {"coordinates":[4.408041954,51.2106628418],"type":"Point"}
}