{
  "type": "Feature",
  "properties": {
    "iso:country":"BE",
    "sg:address":"Vilvoordsesteenweg 83",
    "sg:city":"Steenokkerzeel",
    "sg:orig_category":"Producteurs de l\u00e9gumes",
    "sg:phone":"+32 2 751 75 11",
    "sg:postcode":"1820",
    "sg:province":"Vlaams-Brabant",
    "wof:name":"Paul Bohets",
    "wof:placetype":"venue"
},
  "geometry": {"coordinates":[4.4877800941,50.9348106384],"type":"Point"}
}