{
  "type": "Feature",
  "properties": {
    "iso:country":"BE",
    "sg:address":"Oude Mechelsebaan 432",
    "sg:city":"Langdorp",
    "sg:orig_category":"Location de biens divers. Restaurants",
    "sg:phone":"+32 16 69 48 88",
    "sg:postcode":"3201",
    "sg:province":"Vlaams-Brabant",
    "wof:name":"The Forests",
    "wof:placetype":"venue"
},
  "geometry": {"coordinates":[4.8833708763,51.0086708069],"type":"Point"}
}