{
  "type": "Feature",
  "properties": {
    "iso:country":"BE",
    "sg:address":"Rue Du Quevaucamps 25 Box 4",
    "sg:city":"Mouscron (dottignies)",
    "sg:classifiers":[
        {
            "category":"Health Services",
            "subcategory":"Health Practitioner",
            "type":"Services"
        }
    ],
    "sg:phone":"+32 56 48 48 88",
    "sg:postcode":"7711",
    "sg:province":"Hainaut",
    "sg:tags":[
        "physiotherapist"
    ],
    "wof:name":"Lebrun Christophe",
    "wof:placetype":"venue"
},
  "geometry": {"coordinates":[3.3080399036,50.7282752991],"type":"Point"}
}