{
  "type": "Feature",
  "properties": {
    "addr:full":"114 Elewijtsesteenweg 1980 Zemst - Eppegem 114",
    "addr:housenumber":"114;114",
    "addr:postcode":"1980",
    "addr:street":"Elewijtsesteenweg;Eppegem",
    "iso:country":"BE",
    "sg:address":"114",
    "sg:city":"Elewijtsesteenweg 1980 Zemst - Eppegem",
    "sg:classifiers":[
        {
            "category":"Wholesale",
            "subcategory":"Farm Supplies",
            "type":"Manufacturing & Wholesale Goods"
        }
    ],
    "sg:phone":"+32 15 61 72 72",
    "sg:postcode":"114",
    "sg:tags":[
        "-",
        "machine",
        "equipment",
        "engineering",
        "machinery",
        "mechanical",
        "agriculture"
    ],
    "wof:name":"Gebr Thomas Bvba",
    "wof:placetype":"venue"
},
  "geometry": {"coordinates":[4.4645547867,50.9849433899],"type":"Point"}
}