{
  "type": "Feature",
  "properties": {
    "iso:country":"BE",
    "sg:address":"Juul Grietensstraat 18",
    "sg:city":"Meerhout",
    "sg:orig_category":"Traitements param\u00e9dicaux",
    "sg:phone":"+32 14 30 13 46",
    "sg:postcode":"2450",
    "sg:province":"Antwerpen",
    "wof:name":"C. Clymans",
    "wof:placetype":"venue"
},
  "geometry": {"coordinates":[5.0552411079,51.1197929382],"type":"Point"}
}