{
  "type": "Feature",
  "properties": {
    "addr:full":"Avenue Des Platanes 6 Hannut Li\u00e8ge 4280",
    "addr:housenumber":"6",
    "addr:postcode":"4280",
    "addr:street":"Avenue Des Platanes",
    "iso:country":"BE",
    "sg:address":"Avenue Des Platanes 6",
    "sg:city":"Hannut",
    "sg:orig_category":"Artiesten and kunstenaars Meubelzaken, woning- and keukeninrichting",
    "sg:phone":"+32 19 51 11 69",
    "sg:postcode":"4280",
    "sg:province":"Li\u00e8ge",
    "wof:name":"Meubles Le Bois De Rose",
    "wof:placetype":"venue"
},
  "geometry": {"coordinates":[5.0755991936,50.6697883606],"type":"Point"}
}