{
  "type": "Feature",
  "properties": {
    "addr:full":"Ninoofsesteenweg 747 Dilbeek Vlaams-Brabant 1701",
    "addr:housenumber":"747",
    "addr:postcode":"1701",
    "addr:street":"Ninoofsesteenweg",
    "iso:country":"BE",
    "sg:address":"Ninoofsesteenweg 747",
    "sg:city":"Dilbeek",
    "sg:orig_category":"Boissons",
    "sg:phone":"+32 2 567 02 21",
    "sg:postcode":"1701",
    "sg:province":"Vlaams-Brabant",
    "wof:name":"L. Van Laethem",
    "wof:placetype":"venue"
},
  "geometry": {"coordinates":[4.2237071991,50.8407096863],"type":"Point"}
}