{
  "type": "Feature",
  "properties": {
    "iso:country":"BE",
    "sg:address":"Vecmont 1bd",
    "sg:city":"La Roche-en-ardenne",
    "sg:orig_category":"V\u00e9t\u00e9rinaires",
    "sg:phone":"+32 84 41 14 55",
    "sg:postcode":"6980",
    "sg:province":"Luxembourg",
    "wof:name":"Christian Thill",
    "wof:placetype":"venue"
},
  "geometry": {"coordinates":[5.521420002,50.1499481201],"type":"Point"}
}