{
  "type": "Feature",
  "properties": {
    "addr:full":"Ijzerheemplein 4 Diksmuide West-Vlaanderen 8600",
    "addr:housenumber":"4",
    "addr:postcode":"8600",
    "addr:street":"Ijzerheemplein",
    "iso:country":"BE",
    "sg:address":"Ijzerheemplein 4",
    "sg:city":"Diksmuide",
    "sg:classifiers":[
        {
            "category":"Health Services",
            "subcategory":"Nursing And Care Facility",
            "type":"Services"
        }
    ],
    "sg:phone":"+32 51 50 04 06",
    "sg:postcode":"8600",
    "sg:province":"West-Vlaanderen",
    "sg:tags":[
        "public"
    ],
    "wof:name":"O.c.m.w.",
    "wof:placetype":"venue"
},
  "geometry": {"coordinates":[2.8610389233,51.0313453674],"type":"Point"}
}