{
  "type": "Feature",
  "properties": {
    "addr:full":"Rue Ferrer 2 Chapelle-lez-herlaimont (godarville) Hainaut 7160",
    "addr:housenumber":"2",
    "addr:postcode":"7160",
    "addr:street":"Rue Ferrer;Hainaut",
    "iso:country":"BE",
    "sg:address":"Rue Ferrer 2",
    "sg:city":"Chapelle-lez-herlaimont (godarville)",
    "sg:classifiers":[
        {
            "category":"Bars & Pubs",
            "type":"Food & Drink"
        }
    ],
    "sg:phone":"+32 64 44 96 58",
    "sg:postcode":"7160",
    "sg:province":"Hainaut",
    "wof:name":"Caf\u00e9 Du Village (le)",
    "wof:placetype":"venue"
},
  "geometry": {"coordinates":[4.2812700272,50.4893264771],"type":"Point"}
}