{
  "type": "Feature",
  "properties": {
    "addr:full":"Polenlaan 51 Sint-gillis-waas (de Klinge) Oost-Vlaanderen 9170",
    "addr:housenumber":"51",
    "addr:postcode":"9170",
    "addr:street":"Polenlaan;Oost-Vlaanderen",
    "iso:country":"BE",
    "sg:address":"Polenlaan 51",
    "sg:city":"Sint-gillis-waas (de Klinge)",
    "sg:classifiers":[
        {
            "category":"Building & Trades",
            "subcategory":"Cleaning & Sanitation",
            "type":"Services"
        }
    ],
    "sg:phone":"+32 3 770 56 12",
    "sg:postcode":"9170",
    "sg:province":"Oost-Vlaanderen",
    "sg:tags":[
        "sweep",
        "chimney"
    ],
    "wof:name":"Bentol's Nv",
    "wof:placetype":"venue"
},
  "geometry": {"coordinates":[4.0822319984,51.252948761],"type":"Point"}
}