{
  "type": "Feature",
  "properties": {
    "iso:country":"BE",
    "sg:address":"Aartrijksesteenweg 50",
    "sg:city":"Jabbeke",
    "sg:orig_category":"Autombile concessionaires",
    "sg:phone":"+32 50 81 16 17",
    "sg:postcode":"8490",
    "sg:province":"West-Vlaanderen",
    "wof:name":"Gar Malfait",
    "wof:placetype":"venue"
},
  "geometry": {"coordinates":[3.087446928,51.1762924194],"type":"Point"}
}