{
  "type": "Feature",
  "properties": {
    "addr:full":"Rue Du Fays 1 Faimes Li\u00e8ge 4317",
    "addr:housenumber":"1",
    "addr:postcode":"4317",
    "addr:street":"Rue Du Fays",
    "iso:country":"BE",
    "sg:address":"Rue Du Fays 1",
    "sg:city":"Faimes",
    "sg:orig_category":"Loodgieterij, verwarming and sanitaire installaties",
    "sg:phone":"+32 19 32 77 38",
    "sg:postcode":"4317",
    "sg:province":"Li\u00e8ge",
    "wof:name":"Benoit Lecocq",
    "wof:placetype":"venue"
},
  "geometry": {"coordinates":[5.2674307823,50.6420097351],"type":"Point"}
}