{
  "type": "Feature",
  "properties": {
    "iso:country":"BE",
    "sg:address":"Chauss\u00e9e De Charleroi 96",
    "sg:city":"Bruxelles (saint-gilles)",
    "sg:classifiers":[
        {
            "category":"Professional",
            "subcategory":"Management & Consulting",
            "type":"Services"
        }
    ],
    "sg:phone":"+32 2 534 66 86",
    "sg:postcode":"1060",
    "sg:province":"Bruxelles-Capitale",
    "sg:tags":[
        "consultant",
        "relation",
        "public"
    ],
    "wof:name":"Decitime",
    "wof:placetype":"venue"
},
  "geometry": {"coordinates":[4.3557047844,50.8286170959],"type":"Point"}
}