{
  "type": "Feature",
  "properties": {
    "iso:country":"BE",
    "sg:address":"Ijselaars 14",
    "sg:city":"Nazareth",
    "sg:orig_category":"Parfumeries",
    "sg:phone":"+32 9 385 86 69",
    "sg:postcode":"9810",
    "sg:province":"Oost-Vlaanderen",
    "wof:name":"Perrin Mestdag",
    "wof:placetype":"venue"
},
  "geometry": {"coordinates":[3.6651239395,50.9736595154],"type":"Point"}
}