{
  "type": "Feature",
  "properties": {
    "addr:full":"Jules Van Ooststraat 26 Tielt (aarsele) West-Vlaanderen 8700",
    "addr:housenumber":"26",
    "addr:postcode":"8700",
    "addr:street":"Jules Van Ooststraat",
    "iso:country":"BE",
    "sg:address":"Jules Van Ooststraat 26",
    "sg:city":"Tielt (aarsele)",
    "sg:classifiers":[
        {
            "category":"Home & Garden",
            "subcategory":"Kitchen Supply",
            "type":"Retail Goods"
        }
    ],
    "sg:phone":"+32 51 63 36 30",
    "sg:postcode":"8700",
    "sg:province":"West-Vlaanderen",
    "sg:tags":[
        "installation"
    ],
    "wof:name":"Deloof F",
    "wof:placetype":"venue"
},
  "geometry": {"coordinates":[3.4204490185,50.9984817505],"type":"Point"}
}