{
  "type": "Feature",
  "properties": {
    "iso:country":"BE",
    "sg:address":"Heid Du Moulin 7",
    "sg:city":"Neupre",
    "sg:orig_category":"Kapsalons",
    "sg:phone":"+32 4 371 40 96",
    "sg:postcode":"4122",
    "sg:province":"Li\u00e8ge",
    "wof:name":"Nicole Piette",
    "wof:placetype":"venue"
},
  "geometry": {"coordinates":[5.5280709267,50.5404968262],"type":"Point"}
}