{
  "type": "Feature",
  "properties": {
    "addr:full":"Karel Van Wijnendaeleln 20 Sint-martens-latem Oost-Vlaanderen 9830",
    "addr:housenumber":"20",
    "addr:postcode":"9830",
    "addr:street":"Karel Van Wijnendaeleln",
    "iso:country":"BE",
    "sg:address":"Karel Van Wijnendaeleln 20",
    "sg:city":"Sint-martens-latem",
    "sg:orig_category":"Artistes ind\u00e9pendants",
    "sg:phone":"+32 9 282 56 86",
    "sg:postcode":"9830",
    "sg:province":"Oost-Vlaanderen",
    "wof:name":"B\u00c9r\u00c9nice Malbrain",
    "wof:placetype":"venue"
},
  "geometry": {"coordinates":[3.6382610798,51.0081443787],"type":"Point"}
}