{
  "type": "Feature",
  "properties": {
    "addr:full":"Chauss\u00c9e De Li\u00c8ge 51 Welkenraedt Li\u00e8ge 4841",
    "addr:housenumber":"51",
    "addr:postcode":"4841",
    "addr:street":"Chausse\u0301E De Lie\u0300Ge",
    "iso:country":"BE",
    "sg:address":"Chauss\u00c9e De Li\u00c8ge 51",
    "sg:city":"Welkenraedt",
    "sg:orig_category":"Dancings and bo\u00eetes de nuit. Location d'appareils audio-visuels",
    "sg:phone":"+32 87 44 71 50",
    "sg:postcode":"4841",
    "sg:province":"Li\u00e8ge",
    "wof:name":"La Villa",
    "wof:placetype":"venue"
},
  "geometry": {"coordinates":[5.9140191078,50.6741867065],"type":"Point"}
}