{
  "type": "Feature",
  "properties": {
    "addr:full":"Rue Gr\u00e9try 79 Bruxelles Bruxelles-Capitale 1000",
    "addr:housenumber":"79",
    "addr:postcode":"1000",
    "addr:street":"Rue Gre\u0301Try",
    "iso:country":"BE",
    "sg:address":"Rue Gr\u00e9try 79",
    "sg:city":"Bruxelles",
    "sg:classifiers":[
        {
            "category":"Shopping",
            "subcategory":"Books",
            "type":"Retail Goods"
        }
    ],
    "sg:phone":"+32 2 218 14 66",
    "sg:postcode":"1000",
    "sg:province":"Bruxelles-Capitale",
    "sg:tags":[
        "bookseller"
    ],
    "wof:name":"Edward",
    "wof:placetype":"venue"
},
  "geometry": {"coordinates":[4.3531908989,50.8484992981],"type":"Point"}
}