{
  "type": "Feature",
  "properties": {
    "addr:full":"Rue De La Maison-forte 1 Bastogne Luxembourg 6600",
    "addr:housenumber":"1",
    "addr:postcode":"6600",
    "addr:street":"Rue De La Maison-Forte",
    "iso:country":"BE",
    "sg:address":"Rue De La Maison-forte 1",
    "sg:city":"Bastogne",
    "sg:orig_category":"Artsen and specialisten",
    "sg:phone":"+32 61 21 14 12",
    "sg:postcode":"6600",
    "sg:province":"Luxembourg",
    "wof:name":"Pierre Falisse",
    "wof:placetype":"venue"
},
  "geometry": {"coordinates":[5.7182230949,50.0051498413],"type":"Point"}
}