{
  "type": "Feature",
  "properties": {
    "iso:country":"BE",
    "sg:address":"Sint-martinusplein 11-59b",
    "sg:city":"Genk",
    "sg:classifiers":[
        {
            "category":"Personal",
            "subcategory":"Beauty Salon",
            "type":"Services"
        }
    ],
    "sg:phone":"+32 89 35 70 65",
    "sg:postcode":"3600",
    "sg:province":"Limburg",
    "sg:tags":[
        "lady",
        "-",
        "hairdressing"
    ],
    "wof:name":"New Image Salon System",
    "wof:placetype":"venue"
},
  "geometry": {"coordinates":[5.4979271889,50.9649467468],"type":"Point"}
}