{
  "type": "Feature",
  "properties": {
    "addr:full":"Avenue Brugmann 424-426 Box 7 Bruxelles (uccle) Bruxelles-Capitale 1180",
    "addr:housenumber":"424-426;7",
    "addr:postcode":"1180",
    "addr:street":"Avenue Brugmann;Box",
    "iso:country":"BE",
    "sg:address":"Avenue Brugmann 424-426 Box 7",
    "sg:city":"Bruxelles (uccle)",
    "sg:classifiers":[
        {
            "category":"Health Services",
            "subcategory":"Dentist",
            "type":"Services"
        }
    ],
    "sg:phone":"+32 2 374 90 20",
    "sg:postcode":"1180",
    "sg:province":"Bruxelles-Capitale",
    "wof:name":"Aronis Henri",
    "wof:placetype":"venue"
},
  "geometry": {"coordinates":[4.3478999138,50.8135490417],"type":"Point"}
}