{
  "type": "Feature",
  "properties": {
    "iso:country":"BE",
    "sg:address":"Oudstrijdersstraat 28",
    "sg:city":"Kapelle-op-den-bos",
    "sg:orig_category":"Enseignement maternel and primaire",
    "sg:phone":"+32 15 71 15 41",
    "sg:postcode":"1880",
    "sg:province":"Vlaams-Brabant",
    "wof:name":"Basisschool",
    "wof:placetype":"venue"
},
  "geometry": {"coordinates":[4.3547048569,51.0124511719],"type":"Point"}
}