{
  "type": "Feature",
  "properties": {
    "iso:country":"BE",
    "sg:address":"Reynaertstraat 20ba",
    "sg:city":"Wielsbeke",
    "sg:orig_category":"Winkelinrichting and handelsuitrusting Gh",
    "sg:phone":"+32 56 66 49 82",
    "sg:postcode":"8710",
    "sg:province":"West-Vlaanderen",
    "wof:name":"Delputte Automatic Comp.",
    "wof:placetype":"venue"
},
  "geometry": {"coordinates":[3.3606650829,50.9128341675],"type":"Point"}
}