{
  "type": "Feature",
  "properties": {
    "iso:country":"BE",
    "sg:address":"Oude Antwerpsebaan 95",
    "sg:city":"Mechelen",
    "sg:classifiers":[
        {
            "category":"Professional",
            "subcategory":"Computer Services",
            "type":"Services"
        }
    ],
    "sg:phone":"+32 15 34 78 84",
    "sg:postcode":"2800",
    "sg:province":"Antwerpen",
    "sg:tags":[
        "-",
        "processing",
        "data"
    ],
    "wof:name":"Wallabie Bvba",
    "wof:placetype":"venue"
},
  "geometry": {"coordinates":[4.4674458504,51.0416908264],"type":"Point"}
}