{
  "type": "Feature",
  "properties": {
    "addr:full":"Diestsevest 58 Leuven Vlaams-Brabant 3000",
    "addr:housenumber":"58",
    "addr:postcode":"3000",
    "addr:street":"Diestsevest",
    "iso:country":"BE",
    "sg:address":"Diestsevest 58",
    "sg:city":"Leuven",
    "sg:classifiers":[
        {
            "category":"Professional",
            "subcategory":"Management & Consulting",
            "type":"Services"
        }
    ],
    "sg:phone":"+32 16 27 00 80",
    "sg:postcode":"3000",
    "sg:province":"Vlaams-Brabant",
    "sg:tags":[
        "-",
        "processing",
        "data",
        "consultant"
    ],
    "wof:name":"Vision Web Belgium Nv",
    "wof:placetype":"venue"
},
  "geometry": {"coordinates":[4.7133622169,50.8833007812],"type":"Point"}
}