{
  "type": "Feature",
  "properties": {
    "iso:country":"BE",
    "sg:address":"Mechelsesteenweg 148",
    "sg:city":"Antwerpen",
    "sg:orig_category":"Produits interm\u00e9diaires Gr",
    "sg:phone":"+32 3 237 37 11",
    "sg:postcode":"2018",
    "sg:province":"Antwerpen",
    "wof:name":"Pridan",
    "wof:placetype":"venue"
},
  "geometry": {"coordinates":[4.4096851349,51.2057266235],"type":"Point"}
}