{
  "type": "Feature",
  "properties": {
    "iso:country":"BE",
    "sg:address":"Rue Docteur J. Olyff 4",
    "sg:city":"Marchin",
    "sg:classifiers":[
        {
            "category":"Health Services",
            "subcategory":"Doctor",
            "type":"Services"
        }
    ],
    "sg:phone":"+32 85 61 16 96",
    "sg:postcode":"4570",
    "sg:province":"Li\u00e8ge",
    "sg:tags":[
        "psychotherapist",
        "psychoanalyst"
    ],
    "wof:name":"Bonsignore G",
    "wof:placetype":"venue"
},
  "geometry": {"coordinates":[5.2265357971,50.4784851074],"type":"Point"}
}