{
  "type": "Feature",
  "properties": {
    "iso:country":"BE",
    "sg:address":"Colonel Silvertopstraat 19-23",
    "sg:city":"Boom",
    "sg:classifiers":[
        {
            "category":"Building & Trades",
            "subcategory":"Construction",
            "type":"Services"
        }
    ],
    "sg:phone":"+32 3 888 33 44",
    "sg:postcode":"2850",
    "sg:province":"Antwerpen",
    "sg:tags":[
        "installation",
        "-",
        "central",
        "heating"
    ],
    "wof:name":"Forceville Nv",
    "wof:placetype":"venue"
},
  "geometry": {"coordinates":[4.3613758087,51.0864639282],"type":"Point"}
}