{
  "type": "Feature",
  "properties": {
    "iso:country":"BE",
    "sg:address":"Vierweegsestraat 57",
    "sg:city":"Wondelgem",
    "sg:orig_category":"V\u00eatements pour Dames. V\u00eatements pour Hommes. V\u00eatements pour b\u00e9b\u00e9s and enfants",
    "sg:phone":"+32 478 23 09 78",
    "sg:postcode":"9032",
    "sg:province":"Oost-Vlaanderen",
    "wof:name":"Texas Store",
    "wof:placetype":"venue"
},
  "geometry": {"coordinates":[3.7184290886,51.09034729],"type":"Point"}
}