{
  "type": "Feature",
  "properties": {
    "addr:full":"Manitobaplein 15 Blankenberge West-Vlaanderen 8370",
    "addr:housenumber":"15",
    "addr:postcode":"8370",
    "addr:street":"Manitobaplein",
    "iso:country":"BE",
    "sg:address":"Manitobaplein 15",
    "sg:city":"Blankenberge",
    "sg:classifiers":[
        {
            "category":"Restaurant",
            "type":"Food & Drink"
        }
    ],
    "sg:phone":"+32 50 41 22 42",
    "sg:postcode":"8370",
    "sg:province":"West-Vlaanderen",
    "wof:name":"St. Hubert",
    "wof:placetype":"venue"
},
  "geometry": {"coordinates":[3.1282389164,51.3142738342],"type":"Point"}
}