{
  "type": "Feature",
  "properties": {
    "addr:full":"Aalbekekerkstraat 12 Kortrijk West-Vlaanderen 8511",
    "addr:housenumber":"12",
    "addr:postcode":"8511",
    "addr:street":"Aalbekekerkstraat",
    "iso:country":"BE",
    "sg:address":"Aalbekekerkstraat 12",
    "sg:city":"Kortrijk",
    "sg:orig_category":"Imprimeries and copyshops",
    "sg:phone":"+32 56 41 88 85",
    "sg:postcode":"8511",
    "sg:province":"West-Vlaanderen",
    "wof:name":"Fa. Moulin",
    "wof:placetype":"venue"
},
  "geometry": {"coordinates":[3.2290000916,50.7793426514],"type":"Point"}
}