{
  "type": "Feature",
  "properties": {
    "addr:full":"Brandstraat 6 Lokeren Oost-Vlaanderen 9160",
    "addr:housenumber":"6",
    "addr:postcode":"9160",
    "addr:street":"Brandstraat",
    "iso:country":"BE",
    "sg:address":"Brandstraat 6",
    "sg:city":"Lokeren",
    "sg:classifiers":[
        {
            "category":"Professional",
            "subcategory":"Advertising",
            "type":"Services"
        }
    ],
    "sg:phone":"+32 9 340 66 40",
    "sg:postcode":"9160",
    "sg:province":"Oost-Vlaanderen",
    "sg:tags":[
        "painter"
    ],
    "wof:name":"Argo Bvba",
    "wof:placetype":"venue"
},
  "geometry": {"coordinates":[4.0148539543,51.0857963562],"type":"Point"}
}