{
  "type": "Feature",
  "properties": {
    "iso:country":"BE",
    "sg:address":"Rekhof 22",
    "sg:city":"Poperinge",
    "sg:orig_category":"Activit\u00e9s d\u00b4action sociale sans h\u00e9bergement",
    "sg:phone":"+32 57 33 43 28",
    "sg:postcode":"8970",
    "sg:province":"West-Vlaanderen",
    "wof:name":"Vclb-centrum",
    "wof:placetype":"venue"
},
  "geometry": {"coordinates":[2.7280569077,50.8531188965],"type":"Point"}
}