{
  "type": "Feature",
  "properties": {
    "addr:full":"Onderwijslaan 99 Diepenbeek Limburg 3590",
    "addr:housenumber":"99",
    "addr:postcode":"3590",
    "addr:street":"Onderwijslaan",
    "iso:country":"BE",
    "sg:address":"Onderwijslaan 99",
    "sg:city":"Diepenbeek",
    "sg:classifiers":[
        {
            "category":"Personal",
            "subcategory":"Nail Salon",
            "type":"Services"
        }
    ],
    "sg:phone":"+32 11 32 42 64",
    "sg:postcode":"3590",
    "sg:province":"Limburg",
    "sg:tags":[
        "pedicure"
    ],
    "wof:name":"Hardy",
    "wof:placetype":"venue"
},
  "geometry": {"coordinates":[5.4647197723,50.9253082275],"type":"Point"}
}