{
  "type": "Feature",
  "properties": {
    "addr:full":"Meensesteenweg 201 Moorslede West-Vlaanderen 8890",
    "addr:housenumber":"201",
    "addr:postcode":"8890",
    "addr:street":"Meensesteenweg",
    "iso:country":"BE",
    "sg:address":"Meensesteenweg 201",
    "sg:city":"Moorslede",
    "sg:classifiers":[
        {
            "category":"Travel",
            "subcategory":"Hotels & Motels",
            "type":"Entertainment"
        }
    ],
    "sg:phone":"+32 56 50 94 90",
    "sg:postcode":"8890",
    "sg:province":"West-Vlaanderen",
    "sg:tags":[
        "restaurant"
    ],
    "wof:name":"Daisel Daele",
    "wof:placetype":"venue"
},
  "geometry": {"coordinates":[3.112085104,50.8437194824],"type":"Point"}
}