{
  "type": "Feature",
  "properties": {
    "addr:full":"Poperingseweg 323 Ieper West-Vlaanderen 8908",
    "addr:housenumber":"323",
    "addr:postcode":"8908",
    "addr:street":"Poperingseweg",
    "iso:country":"BE",
    "sg:address":"Poperingseweg 323",
    "sg:city":"Ieper",
    "sg:classifiers":[
        {
            "category":"Restaurant",
            "type":"Food & Drink"
        }
    ],
    "sg:phone":"+32 57 20 43 19",
    "sg:postcode":"8908",
    "sg:province":"West-Vlaanderen",
    "wof:name":"Restaurant 't Fonteintje",
    "wof:placetype":"venue"
},
  "geometry": {"coordinates":[2.8262441158,50.8532371521],"type":"Point"}
}