{
  "type": "Feature",
  "properties": {
    "iso:country":"BE",
    "sg:address":"Rue Arthur Snaps 59",
    "sg:city":"Grez-doiceau",
    "sg:orig_category":"Immobili\u00ebnkantoren",
    "sg:phone":"+32 10 84 07 00",
    "sg:postcode":"1390",
    "sg:province":"Brabant Wallon",
    "wof:name":"Vanhimmo",
    "wof:placetype":"venue"
},
  "geometry": {"coordinates":[4.6585841179,50.7726821899],"type":"Point"}
}