{
  "type": "Feature",
  "properties": {
    "iso:country":"BE",
    "sg:address":"Prins Boudewijnstraat 104",
    "sg:city":"Ganshoren",
    "sg:orig_category":"Medische apparatuur, orthopedische artikelen and prothesen Fab",
    "sg:phone":"+32 2 427 50 37",
    "sg:postcode":"1083",
    "sg:province":"Bruxelles-Capitale",
    "wof:name":"Dental Labo Cocquet",
    "wof:placetype":"venue"
},
  "geometry": {"coordinates":[4.3198161125,50.8714294434],"type":"Point"}
}