{
  "type": "Feature",
  "properties": {
    "addr:full":"Provinciale Steenweg 435 Schelle Antwerpen 2627",
    "addr:housenumber":"435",
    "addr:postcode":"2627",
    "addr:street":"Provinciale Steenweg",
    "iso:country":"BE",
    "sg:address":"Provinciale Steenweg 435",
    "sg:city":"Schelle",
    "sg:orig_category":"Entretien and r\u00e9parations de voitures",
    "sg:phone":"+32 3 887 05 75",
    "sg:postcode":"2627",
    "sg:province":"Antwerpen",
    "wof:name":"Garage Perfect Car",
    "wof:placetype":"venue"
},
  "geometry": {"coordinates":[4.3337440491,51.117389679],"type":"Point"}
}