{
  "type": "Feature",
  "properties": {
    "addr:full":"Joe Englishstraat 54 Borgerhout Antwerpen 2140",
    "addr:housenumber":"54",
    "addr:postcode":"2140",
    "addr:street":"Joe Englishstraat",
    "iso:country":"BE",
    "sg:address":"Joe Englishstraat 54",
    "sg:city":"Borgerhout",
    "sg:classifiers":[
        {
            "category":"Manufacturing",
            "subcategory":"Jewelry",
            "type":"Manufacturing & Wholesale Goods"
        }
    ],
    "sg:phone":"+32 3 231 21 03",
    "sg:postcode":"2140",
    "sg:province":"Antwerpen",
    "sg:tags":[
        "product",
        "miscellaneous",
        "jewellery"
    ],
    "wof:name":"Antwerp United Diamonds Nv",
    "wof:placetype":"venue"
},
  "geometry": {"coordinates":[4.4468231201,51.2099609375],"type":"Point"}
}