{
  "type": "Feature",
  "properties": {
    "addr:full":"Burg 37 Torhout West-Vlaanderen 8820",
    "addr:housenumber":"37",
    "addr:postcode":"8820",
    "addr:street":"Burg",
    "iso:country":"BE",
    "sg:address":"Burg 37",
    "sg:city":"Torhout",
    "sg:orig_category":"Pharmaciens",
    "sg:phone":"+32 50 21 22 81",
    "sg:postcode":"8820",
    "sg:province":"West-Vlaanderen",
    "wof:name":"Carlos Depuydt",
    "wof:placetype":"venue"
},
  "geometry": {"coordinates":[3.1015479565,51.0664367676],"type":"Point"}
}