{
  "type": "Feature",
  "properties": {
    "addr:full":"Antwerpsestraat 119 Boom Antwerpen 2850",
    "addr:housenumber":"119",
    "addr:postcode":"2850",
    "addr:street":"Antwerpsestraat",
    "iso:country":"BE",
    "sg:address":"Antwerpsestraat 119",
    "sg:city":"Boom",
    "sg:orig_category":"Onderdelen and accessoires voor auto's",
    "sg:phone":"+32 3 888 52 43",
    "sg:postcode":"2850",
    "sg:province":"Antwerpen",
    "wof:name":"Interband",
    "wof:placetype":"venue"
},
  "geometry": {"coordinates":[4.3647742271,51.0909805298],"type":"Point"}
}