{
  "type": "Feature",
  "properties": {
    "addr:full":"Rue Gr\u00c9try 105 Li\u00c8ge Li\u00e8ge 4020",
    "addr:housenumber":"105",
    "addr:postcode":"4020",
    "addr:street":"Rue Gre\u0301Try",
    "iso:country":"BE",
    "sg:address":"Rue Gr\u00c9try 105",
    "sg:city":"Li\u00c8ge",
    "sg:orig_category":"Diverse kredietdiensten",
    "sg:postcode":"4020",
    "sg:province":"Li\u00e8ge",
    "wof:name":"Bancontact-mister Cash",
    "wof:placetype":"venue"
},
  "geometry": {"coordinates":[5.5819988251,50.6343078613],"type":"Point"}
}