{
  "type": "Feature",
  "properties": {
    "addr:full":"De Daries 6 Arendonk Antwerpen 2370",
    "addr:housenumber":"6",
    "addr:postcode":"2370",
    "addr:street":"De Daries",
    "iso:country":"BE",
    "sg:address":"De Daries 6",
    "sg:city":"Arendonk",
    "sg:orig_category":"Rundveehouders Varkenskwekers",
    "sg:phone":"+32 14 67 74 00",
    "sg:postcode":"2370",
    "sg:province":"Antwerpen",
    "wof:name":"Jozef Dickens",
    "wof:placetype":"venue"
},
  "geometry": {"coordinates":[5.0808210373,51.3198471069],"type":"Point"}
}