{
  "type": "Feature",
  "properties": {
    "addr:full":"Lenclos 117 Etalle Luxembourg 6740",
    "addr:housenumber":"117",
    "addr:postcode":"6740",
    "addr:street":"Lenclos",
    "iso:country":"BE",
    "sg:address":"Lenclos 117",
    "sg:city":"Etalle",
    "sg:orig_category":"Rusthuizen and serviceflats",
    "sg:phone":"+32 63 45 67 99",
    "sg:postcode":"6740",
    "sg:province":"Luxembourg",
    "wof:name":"S\u00c9niorie De L'enclos",
    "wof:placetype":"venue"
},
  "geometry": {"coordinates":[5.6102161407,49.6733131409],"type":"Point"}
}