{
  "type": "Feature",
  "properties": {
    "iso:country":"BE",
    "sg:address":"Adolf Reydamslaan 27",
    "sg:city":"Mol",
    "sg:classifiers":[
        {
            "category":"Building & Trades",
            "subcategory":"Construction",
            "type":"Services"
        }
    ],
    "sg:phone":"+32 14 31 37 09",
    "sg:postcode":"2400",
    "sg:province":"Antwerpen",
    "sg:tags":[
        "surveyor",
        "-"
    ],
    "wof:name":"Van Der Voort J",
    "wof:placetype":"venue"
},
  "geometry": {"coordinates":[5.112883091,51.1880531311],"type":"Point"}
}