{
  "type": "Feature",
  "properties": {
    "addr:full":"Abdijstraat 3 Koksijde West-Vlaanderen 8670",
    "addr:housenumber":"3",
    "addr:postcode":"8670",
    "addr:street":"Abdijstraat",
    "iso:country":"BE",
    "sg:address":"Abdijstraat 3",
    "sg:city":"Koksijde",
    "sg:classifiers":[
        {
            "category":"Wholesale",
            "subcategory":"Fruits & Vegetables",
            "type":"Manufacturing & Wholesale Goods"
        }
    ],
    "sg:phone":"+32 58 51 38 72",
    "sg:postcode":"8670",
    "sg:province":"West-Vlaanderen",
    "sg:tags":[
        "whol",
        "-"
    ],
    "wof:name":"Velle Toon",
    "wof:placetype":"venue"
},
  "geometry": {"coordinates":[2.6470301151,51.1081581116],"type":"Point"}
}