{
  "type": "Feature",
  "properties": {
    "iso:country":"BE",
    "sg:address":"Kanonniersweg 47",
    "sg:city":"Bonheiden",
    "sg:orig_category":"Levering aan huis restaurants",
    "sg:phone":"+32 15 52 83 60",
    "sg:postcode":"2820",
    "sg:province":"Antwerpen",
    "wof:name":"Pizza Bon",
    "wof:placetype":"venue"
},
  "geometry": {"coordinates":[4.5729317665,51.0207290649],"type":"Point"}
}