{
  "type": "Feature",
  "properties": {
    "addr:full":"Karel Janssenslaan 37b16 Oostende West-Vlaanderen 8400",
    "addr:housenumber":"37b16",
    "addr:postcode":"8400",
    "addr:street":"Karel Janssenslaan",
    "iso:country":"BE",
    "sg:address":"Karel Janssenslaan 37b16",
    "sg:city":"Oostende",
    "sg:orig_category":"Vertalers and tolken",
    "sg:phone":"+32 59 80 13 56",
    "sg:postcode":"8400",
    "sg:province":"West-Vlaanderen",
    "wof:name":"Samyn J-p Cbtip/bkvtf",
    "wof:placetype":"venue"
},
  "geometry": {"coordinates":[2.9118950367,51.2288246155],"type":"Point"}
}