{
  "type": "Feature",
  "properties": {
    "iso:country":"BE",
    "sg:address":"Kruiskenslei 139",
    "sg:city":"Boom",
    "sg:classifiers":[
        {
            "category":"Building & Trades",
            "subcategory":"Construction",
            "type":"Services"
        }
    ],
    "sg:phone":"+32 3 844 37 60",
    "sg:postcode":"2850",
    "sg:province":"Antwerpen",
    "sg:tags":[
        "stucco",
        "contractor"
    ],
    "wof:name":"Wauters Mike",
    "wof:placetype":"venue"
},
  "geometry": {"coordinates":[4.3649997711,51.104057312],"type":"Point"}
}