{
  "type": "Feature",
  "properties": {
    "iso:country":"BE",
    "sg:address":"Avenue De L'universit\u00c9 31",
    "sg:city":"Mons",
    "sg:orig_category":"Artistes ind\u00e9pendants",
    "sg:phone":"+32 65 34 01 55",
    "sg:postcode":"7000",
    "sg:province":"Hainaut",
    "wof:name":"Bernard Descamps",
    "wof:placetype":"venue"
},
  "geometry": {"coordinates":[3.9448320866,50.4610443115],"type":"Point"}
}