{
  "type": "Feature",
  "properties": {
    "iso:country":"BE",
    "sg:address":"Rue P\u00e8re Heugens 51",
    "sg:city":"Philippeville (villers-le-gambon)",
    "sg:classifiers":[
        {
            "category":"Personal",
            "subcategory":"Beauty Salon",
            "type":"Services"
        }
    ],
    "sg:phone":"+32 71 66 66 86",
    "sg:postcode":"5600",
    "sg:province":"Namur",
    "sg:tags":[
        "lady",
        "-",
        "hairdressing"
    ],
    "wof:name":"Coif-mod",
    "wof:placetype":"venue"
},
  "geometry": {"coordinates":[4.6074647903,50.1935424805],"type":"Point"}
}