{
  "type": "Feature",
  "properties": {
    "iso:country":"BE",
    "sg:address":"Rue Des Jardinets 43",
    "sg:city":"Leglise",
    "sg:orig_category":"Eleveurs de bovins",
    "sg:phone":"+32 63 43 36 88",
    "sg:postcode":"6860",
    "sg:province":"Luxembourg",
    "wof:name":"Simon Wauthier",
    "wof:placetype":"venue"
},
  "geometry": {"coordinates":[5.508810997,49.7992477417],"type":"Point"}
}