{
  "type": "Feature",
  "properties": {
    "iso:country":"BE",
    "sg:address":"Wemmelse Steenweg 22",
    "sg:city":"Jette/jette",
    "sg:orig_category":"Tweedehandsgoederen",
    "sg:phone":"+32 2 426 23 82",
    "sg:postcode":"1090",
    "sg:province":"Bruxelles-Capitale",
    "wof:name":"Jardin De Claire-monique",
    "wof:placetype":"venue"
},
  "geometry": {"coordinates":[4.3251919746,50.8737564087],"type":"Point"}
}