{
  "type": "Feature",
  "properties": {
    "addr:full":"Rumbeeksesteenweg 356 Roeselare (rumbeke) West-Vlaanderen 8800",
    "addr:housenumber":"356",
    "addr:postcode":"8800",
    "addr:street":"Rumbeeksesteenweg",
    "iso:country":"BE",
    "sg:address":"Rumbeeksesteenweg 356",
    "sg:city":"Roeselare (rumbeke)",
    "sg:classifiers":[
        {
            "category":"Professional",
            "subcategory":"Testing Lab",
            "type":"Services"
        }
    ],
    "sg:phone":"+32 51 20 22 67",
    "sg:postcode":"8800",
    "sg:province":"West-Vlaanderen",
    "sg:tags":[
        "chemist"
    ],
    "wof:name":"Pluym B",
    "wof:placetype":"venue"
},
  "geometry": {"coordinates":[3.1381750107,50.9377593994],"type":"Point"}
}