{
  "type": "Feature",
  "properties": {
    "iso:country":"BE",
    "sg:address":"Chauss\u00c9e De Waterloo 85",
    "sg:city":"Sint-gillis",
    "sg:orig_category":"Verlichting and huishoudartikelen",
    "sg:phone":"+32 2 534 77 02",
    "sg:postcode":"1060",
    "sg:province":"Bruxelles-Capitale",
    "wof:name":"Amicrack",
    "wof:placetype":"venue"
},
  "geometry": {"coordinates":[4.3442001343,50.8294143677],"type":"Point"}
}