{
  "type": "Feature",
  "properties": {
    "addr:full":"Warempage 15 La Roche-en-ardenne Luxembourg 6983",
    "addr:housenumber":"15",
    "addr:postcode":"6983",
    "addr:street":"Warempage",
    "iso:country":"BE",
    "sg:address":"Warempage 15",
    "sg:city":"La Roche-en-ardenne",
    "sg:orig_category":"M\u00e9decins and sp\u00e9cialistes",
    "sg:phone":"+32 84 43 30 18",
    "sg:postcode":"6983",
    "sg:province":"Luxembourg",
    "wof:name":"Michel Hariga",
    "wof:placetype":"venue"
},
  "geometry": {"coordinates":[5.6033000946,50.1450004578],"type":"Point"}
}