{
  "type": "Feature",
  "properties": {
    "iso:country":"BE",
    "sg:address":"Portweg 6",
    "sg:city":"Koekelare",
    "sg:orig_category":"Eleveurs and marchands de porcs",
    "sg:phone":"+32 51 58 86 01",
    "sg:postcode":"8680",
    "sg:province":"West-Vlaanderen",
    "wof:name":"Vanryckeghem",
    "wof:placetype":"venue"
},
  "geometry": {"coordinates":[2.9957129955,51.0660705566],"type":"Point"}
}