{
  "type": "Feature",
  "properties": {
    "iso:country":"BE",
    "sg:address":"Rue Adolphe Bastin 11",
    "sg:city":"Huy",
    "sg:classifiers":[
        {
            "category":"Health Services",
            "subcategory":"Doctor",
            "type":"Services"
        }
    ],
    "sg:phone":"+32 85 25 11 56",
    "sg:postcode":"4500",
    "sg:province":"Li\u00e8ge",
    "sg:tags":[
        "medicinephysicians",
        "surgeon"
    ],
    "wof:name":"Joassin Roxane",
    "wof:placetype":"venue"
},
  "geometry": {"coordinates":[5.2424139977,50.5253219604],"type":"Point"}
}