{
  "type": "Feature",
  "properties": {
    "iso:country":"BE",
    "sg:address":"Capucienenlaan 62",
    "sg:city":"Aalst",
    "sg:orig_category":"Traitements param\u00e9dicaux",
    "sg:phone":"+32 53 77 75 38",
    "sg:postcode":"9300",
    "sg:province":"Oost-Vlaanderen",
    "wof:name":"S. Baeyens",
    "wof:placetype":"venue"
},
  "geometry": {"coordinates":[4.0297908783,50.9348182678],"type":"Point"}
}