{
  "type": "Feature",
  "properties": {
    "iso:country":"BE",
    "sg:address":"Rue De Heigne 36a",
    "sg:city":"Charleroi (jumet)",
    "sg:classifiers":[
        {
            "category":"Structure",
            "subcategory":"Office Building",
            "type":"Public Place"
        }
    ],
    "sg:phone":"+32 71 34 50 32",
    "sg:postcode":"6040",
    "sg:province":"Hainaut",
    "sg:tags":[
        "roofing",
        "slate"
    ],
    "wof:name":"Servidio Sprl",
    "wof:placetype":"venue"
},
  "geometry": {"coordinates":[4.4175992012,50.4479598999],"type":"Point"}
}