{
  "type": "Feature",
  "properties": {
    "iso:country":"BE",
    "sg:address":"Lennikseweg 179",
    "sg:city":"Dilbeek",
    "sg:classifiers":[
        {
            "category":"Personal",
            "subcategory":"Beauty Salon",
            "type":"Services"
        }
    ],
    "sg:phone":"+32 2 569 81 31",
    "sg:postcode":"1700",
    "sg:province":"Vlaams-Brabant",
    "sg:tags":[
        "lady",
        "-",
        "hairdressing"
    ],
    "wof:name":"Stas M",
    "wof:placetype":"venue"
},
  "geometry": {"coordinates":[4.2433700562,50.8241691589],"type":"Point"}
}