{
  "type": "Feature",
  "properties": {
    "addr:full":"Minister A. De Clercklaan 35 Kortrijk West-Vlaanderen 8500",
    "addr:housenumber":"35",
    "addr:postcode":"8500",
    "addr:street":"Minister A. De Clercklaan",
    "iso:country":"BE",
    "sg:address":"Minister A. De Clercklaan 35",
    "sg:city":"Kortrijk",
    "sg:classifiers":[
        {
            "category":"Home & Garden",
            "subcategory":"Hardware",
            "type":"Retail Goods"
        }
    ],
    "sg:phone":"+32 56 21 84 89",
    "sg:postcode":"8500",
    "sg:province":"West-Vlaanderen",
    "sg:tags":[
        "gate",
        "opener",
        "door",
        "automatic"
    ],
    "wof:name":"Valcke Nv",
    "wof:placetype":"venue"
},
  "geometry": {"coordinates":[3.2830719948,50.8106689453],"type":"Point"}
}