{
  "type": "Feature",
  "properties": {
    "addr:full":"Kortrijksestraat 50 Oostkamp West-Vlaanderen 8020",
    "addr:housenumber":"50",
    "addr:postcode":"8020",
    "addr:street":"Kortrijksestraat",
    "iso:country":"BE",
    "sg:address":"Kortrijksestraat 50",
    "sg:city":"Oostkamp",
    "sg:classifiers":[
        {
            "category":"Shopping",
            "subcategory":"Clothing, Apparel, & Fashions",
            "type":"Retail Goods"
        }
    ],
    "sg:phone":"+32 50 82 53 01",
    "sg:postcode":"8020",
    "sg:province":"West-Vlaanderen",
    "sg:tags":[
        "clothing",
        "-",
        "gentleman"
    ],
    "wof:name":"Valentino Herenboetiek Bvba",
    "wof:placetype":"venue"
},
  "geometry": {"coordinates":[3.2345850468,51.1523666382],"type":"Point"}
}