{
  "type": "Feature",
  "properties": {
    "addr:full":"Gentstraat 331 Gent (oostakker) Oost-Vlaanderen 9041",
    "addr:housenumber":"331",
    "addr:postcode":"9041",
    "addr:street":"Gentstraat",
    "iso:country":"BE",
    "sg:address":"Gentstraat 331",
    "sg:city":"Gent (oostakker)",
    "sg:classifiers":[
        {
            "category":"Personal",
            "subcategory":"Beauty Salon",
            "type":"Services"
        }
    ],
    "sg:phone":"+32 9 251 38 98",
    "sg:postcode":"9041",
    "sg:province":"Oost-Vlaanderen",
    "sg:tags":[
        "lady",
        "-",
        "hairdressing"
    ],
    "wof:name":"Aphrodite",
    "wof:placetype":"venue"
},
  "geometry": {"coordinates":[3.760876894,51.0966415405],"type":"Point"}
}