{
  "type": "Feature",
  "properties": {
    "iso:country":"BE",
    "sg:address":"Place De Bronckart 25",
    "sg:city":"Li\u00e8ge 1",
    "sg:classifiers":[
        {
            "category":"Health Services",
            "subcategory":"Doctor",
            "type":"Services"
        }
    ],
    "sg:phone":"+32 4 224 89 60",
    "sg:postcode":"4000",
    "sg:province":"Li\u00e8ge",
    "sg:tags":[
        "medicinephysicians",
        "surgeon"
    ],
    "wof:name":"Demoulin Jean-claude",
    "wof:placetype":"venue"
},
  "geometry": {"coordinates":[5.5661997795,50.629032135],"type":"Point"}
}