{
  "type": "Feature",
  "properties": {
    "iso:country":"BE",
    "sg:address":"Amsterdamstraat 41",
    "sg:city":"Oostende",
    "sg:classifiers":[
        {
            "category":"Professional",
            "subcategory":"Testing Lab",
            "type":"Services"
        }
    ],
    "sg:phone":"+32 59 70 08 35",
    "sg:postcode":"8400",
    "sg:province":"West-Vlaanderen",
    "sg:tags":[
        "chemist"
    ],
    "wof:name":"Coopfarma 1",
    "wof:placetype":"venue"
},
  "geometry": {"coordinates":[2.9144690037,51.2251319885],"type":"Point"}
}