{
  "type": "Feature",
  "properties": {
    "addr:full":"Riddersdal 4 Overijse Vlaams-Brabant 3090",
    "addr:housenumber":"4",
    "addr:postcode":"3090",
    "addr:street":"Riddersdal",
    "iso:country":"BE",
    "sg:address":"Riddersdal 4",
    "sg:city":"Overijse",
    "sg:orig_category":"Installation \u00e9lectrique r\u00e9sidentielle",
    "sg:phone":"+32 2 657 17 03",
    "sg:postcode":"3090",
    "sg:province":"Vlaams-Brabant",
    "wof:name":"Didier Groffils",
    "wof:placetype":"venue"
},
  "geometry": {"coordinates":[4.484744072,50.784778595],"type":"Point"}
}