{
  "type": "Feature",
  "properties": {
    "addr:full":"Peerschat 47 Haacht (wespelaar) Vlaams-Brabant 3150",
    "addr:housenumber":"47",
    "addr:postcode":"3150",
    "addr:street":"Peerschat",
    "iso:country":"BE",
    "sg:address":"Peerschat 47",
    "sg:city":"Haacht (wespelaar)",
    "sg:classifiers":[
        {
            "category":"Professional",
            "subcategory":"Management & Consulting",
            "type":"Services"
        }
    ],
    "sg:phone":"+32 16 60 08 40",
    "sg:postcode":"3150",
    "sg:province":"Vlaams-Brabant",
    "sg:tags":[
        "consultant"
    ],
    "wof:name":"Van Lishout G",
    "wof:placetype":"venue"
},
  "geometry": {"coordinates":[4.6470828056,50.957447052],"type":"Point"}
}