{
  "type": "Feature",
  "properties": {
    "addr:full":"Marktplein 2 Wingene West-Vlaanderen 8750",
    "addr:housenumber":"2",
    "addr:postcode":"8750",
    "addr:street":"Marktplein",
    "iso:country":"BE",
    "sg:address":"Marktplein 2",
    "sg:city":"Wingene",
    "sg:classifiers":[
        {
            "category":"Cafe",
            "type":"Food & Drink"
        }
    ],
    "sg:phone":"+32 51 61 25 46",
    "sg:postcode":"8750",
    "sg:province":"West-Vlaanderen",
    "sg:tags":[
        "caf\u00e9s"
    ],
    "wof:name":"De Hobbit",
    "wof:placetype":"venue"
},
  "geometry": {"coordinates":[3.2783529758,51.0578422546],"type":"Point"}
}