{
  "type": "Feature",
  "properties": {
    "iso:country":"BE",
    "sg:address":"Merelstraat 39",
    "sg:city":"Peer",
    "sg:classifiers":[
        {
            "category":"Building & Trades",
            "subcategory":"Cleaning & Sanitation",
            "type":"Services"
        }
    ],
    "sg:phone":"+32 11 63 10 76",
    "sg:postcode":"3990",
    "sg:province":"Limburg",
    "sg:tags":[
        "janitor"
    ],
    "wof:name":"Aerts J",
    "wof:placetype":"venue"
},
  "geometry": {"coordinates":[5.4560470581,51.1382408142],"type":"Point"}
}