{
  "type": "Feature",
  "properties": {
    "addr:full":"Begijnenstraat 3 Ieper West-Vlaanderen 8900",
    "addr:housenumber":"3",
    "addr:postcode":"8900",
    "addr:street":"Begijnenstraat",
    "iso:country":"BE",
    "sg:address":"Begijnenstraat 3",
    "sg:city":"Ieper",
    "sg:orig_category":"Installation de menuiserie en bois and plastique",
    "sg:phone":"+32 57 20 35 07",
    "sg:postcode":"8900",
    "sg:province":"West-Vlaanderen",
    "wof:name":"Vitse Rudy",
    "wof:placetype":"venue"
},
  "geometry": {"coordinates":[2.8726780415,50.8491439819],"type":"Point"}
}