{
  "type": "Feature",
  "properties": {
    "addr:full":"Markt 27 Mol Antwerpen 2400",
    "addr:housenumber":"27",
    "addr:postcode":"2400",
    "addr:street":"Markt",
    "iso:country":"BE",
    "sg:address":"Markt 27",
    "sg:city":"Mol",
    "sg:orig_category":"Banken and kredietinstellingen",
    "sg:phone":"+32 14 31 97 84",
    "sg:postcode":"2400",
    "sg:province":"Antwerpen",
    "wof:name":"Bacob",
    "wof:placetype":"venue"
},
  "geometry": {"coordinates":[5.116517067,51.1846046448],"type":"Point"}
}