{
  "type": "Feature",
  "properties": {
    "addr:full":"Koolmijnin 26 Heusden-zolder Limburg 3550",
    "addr:housenumber":"26",
    "addr:postcode":"3550",
    "addr:street":"Koolmijnin",
    "iso:country":"BE",
    "sg:address":"Koolmijnin 26",
    "sg:city":"Heusden-zolder",
    "sg:orig_category":"Speelgoed",
    "sg:phone":"+32 11 57 01 20",
    "sg:postcode":"3550",
    "sg:province":"Limburg",
    "wof:name":"Moderna",
    "wof:placetype":"venue"
},
  "geometry": {"coordinates":[5.2961740494,51.0381622314],"type":"Point"}
}