{
  "type": "Feature",
  "properties": {
    "addr:full":"Rue De Hal 17 Vorst Bruxelles-Capitale 1190",
    "addr:housenumber":"17",
    "addr:postcode":"1190",
    "addr:street":"Rue De Hal",
    "iso:country":"BE",
    "sg:address":"Rue De Hal 17",
    "sg:city":"Vorst",
    "sg:orig_category":"D\u00e9taillants en pi\u00e8ces and accessoires de voitures",
    "sg:phone":"+32 2 332 31 00",
    "sg:postcode":"1190",
    "sg:province":"Bruxelles-Capitale",
    "wof:name":"Madex Car-airco",
    "wof:placetype":"venue"
},
  "geometry": {"coordinates":[4.3136558533,50.8090705872],"type":"Point"}
}