{
  "type": "Feature",
  "properties": {
    "iso:country":"BE",
    "sg:address":"Bosstraat 53",
    "sg:city":"Waregem",
    "sg:classifiers":[
        {
            "category":"Restaurant",
            "type":"Food & Drink"
        }
    ],
    "sg:phone":"+32 56 60 19 37",
    "sg:postcode":"8790",
    "sg:province":"West-Vlaanderen",
    "wof:name":"'t Oud Konijntje",
    "wof:placetype":"venue"
},
  "geometry": {"coordinates":[3.4558389187,50.8769302368],"type":"Point"}
}