{
  "type": "Feature",
  "properties": {
    "iso:country":"BE",
    "sg:address":"Gildenstraat 15",
    "sg:city":"Ieper",
    "sg:orig_category":"Advocaten and juridische adviseurs",
    "sg:phone":"+32 486 42 16 16",
    "sg:postcode":"8900",
    "sg:province":"West-Vlaanderen",
    "wof:name":"Albert Menu",
    "wof:placetype":"venue"
},
  "geometry": {"coordinates":[2.8945260048,50.8520278931],"type":"Point"}
}