{
  "type": "Feature",
  "properties": {
    "iso:country":"BE",
    "sg:address":"Boulevard Lambermont 78",
    "sg:city":"Schaarbeek/schaerbeek",
    "sg:orig_category":"Textiles. Eclairage et \u00e9quipements du foyer. D\u00e9corateurs d'int\u00e9rieur",
    "sg:phone":"+32 2 242 91 50",
    "sg:postcode":"1030",
    "sg:province":"Bruxelles-Capitale",
    "wof:name":"Arch Nova",
    "wof:placetype":"venue"
},
  "geometry": {"coordinates":[4.3780832291,50.8733787537],"type":"Point"}
}