{
  "type": "Feature",
  "properties": {
    "iso:country":"BE",
    "sg:address":"All\u00c9e Des Chardonnerets 3",
    "sg:city":"Walcourt",
    "sg:orig_category":"Schoonheidssalons",
    "sg:phone":"+32 71 21 41 77",
    "sg:postcode":"5651",
    "sg:province":"Namur",
    "wof:name":"Radmila Radinovic",
    "wof:placetype":"venue"
},
  "geometry": {"coordinates":[4.4262080193,50.2824401855],"type":"Point"}
}