{
  "type": "Feature",
  "properties": {
    "addr:full":"Temselaan 100 Strombeek-bever Vlaams-Brabant 1853",
    "addr:housenumber":"100",
    "addr:postcode":"1853",
    "addr:street":"Temselaan",
    "iso:country":"BE",
    "sg:address":"Temselaan 100",
    "sg:city":"Strombeek-bever",
    "sg:classifiers":[
        {
            "category":"Manufacturing",
            "subcategory":"Chemicals & Compounds",
            "type":"Manufacturing & Wholesale Goods"
        }
    ],
    "sg:phone":"+32 2 456 45 11",
    "sg:postcode":"1853",
    "sg:province":"Vlaams-Brabant",
    "sg:tags":[
        "pharmaceutical",
        "-",
        "cosmetic",
        "pharmacy",
        "chemistry",
        "by-product"
    ],
    "wof:name":"Procter & Gamble Pharmac Nv",
    "wof:placetype":"venue"
},
  "geometry": {"coordinates":[4.3428201675,50.904548645],"type":"Point"}
}