{
  "type": "Feature",
  "properties": {
    "addr:full":"Oudenburgweg 59 Jabbeke (varsenare) West-Vlaanderen 8490",
    "addr:housenumber":"59",
    "addr:postcode":"8490",
    "addr:street":"Oudenburgweg",
    "iso:country":"BE",
    "sg:address":"Oudenburgweg 59",
    "sg:city":"Jabbeke (varsenare)",
    "sg:classifiers":[
        {
            "category":"Building & Trades",
            "subcategory":"Construction",
            "type":"Services"
        }
    ],
    "sg:phone":"+32 50 38 72 74",
    "sg:postcode":"8490",
    "sg:province":"West-Vlaanderen",
    "sg:tags":[
        "surveyor",
        "-"
    ],
    "wof:name":"Declercq H",
    "wof:placetype":"venue"
},
  "geometry": {"coordinates":[3.1319019794,51.186416626],"type":"Point"}
}