{
  "type": "Feature",
  "properties": {
    "iso:country":"BE",
    "sg:address":"De Praeterestraat 15",
    "sg:city":"Elsene/ixelles",
    "sg:orig_category":"Immobili\u00ebnkantoren",
    "sg:phone":"+32 2 646 24 23",
    "sg:postcode":"1050",
    "sg:province":"Bruxelles-Capitale",
    "wof:name":"Optim",
    "wof:placetype":"venue"
},
  "geometry": {"coordinates":[4.3691058159,50.8167991638],"type":"Point"}
}