{
  "type": "Feature",
  "properties": {
    "iso:country":"BE",
    "sg:address":"Oude Burkelslag 9",
    "sg:city":"Maldegem",
    "sg:classifiers":[
        {
            "category":"Real Estate",
            "subcategory":"Surveying",
            "type":"Services"
        }
    ],
    "sg:phone":"+32 50 71 76 64",
    "sg:postcode":"9990",
    "sg:province":"Oost-Vlaanderen",
    "sg:tags":[
        "surveyor",
        "land"
    ],
    "wof:name":"Depuydt S",
    "wof:placetype":"venue"
},
  "geometry": {"coordinates":[3.4161128998,51.1917076111],"type":"Point"}
}