{
  "type": "Feature",
  "properties": {
    "addr:full":"Geraardsbergsesteenweg 27 Melle Oost-Vlaanderen 9090",
    "addr:housenumber":"27",
    "addr:postcode":"9090",
    "addr:street":"Geraardsbergsesteenweg",
    "iso:country":"BE",
    "sg:address":"Geraardsbergsesteenweg 27",
    "sg:city":"Melle",
    "sg:classifiers":[
        {
            "category":"Freight",
            "type":"Transportation"
        }
    ],
    "sg:phone":"+32 9 252 51 72",
    "sg:postcode":"9090",
    "sg:province":"Oost-Vlaanderen",
    "sg:tags":[
        "-",
        "transport"
    ],
    "wof:name":"Mattheeuws C",
    "wof:placetype":"venue"
},
  "geometry": {"coordinates":[3.800538063,50.9928207397],"type":"Point"}
}