{
  "type": "Feature",
  "properties": {
    "iso:country":"BE",
    "sg:address":"Wilde Rozenweg 2",
    "sg:city":"Kraainem",
    "sg:orig_category":"Meubelzaken, woning- and keukeninrichting",
    "sg:phone":"+32 2 731 01 79",
    "sg:postcode":"1950",
    "sg:province":"Vlaams-Brabant",
    "wof:name":"Rene Gerardy",
    "wof:placetype":"venue"
},
  "geometry": {"coordinates":[4.4679961205,50.8451118469],"type":"Point"}
}