{
  "type": "Feature",
  "properties": {
    "iso:country":"BE",
    "sg:address":"Gewerbestrasse 13",
    "sg:city":"Eupen/eupen",
    "sg:orig_category":"Entreprises de travail adapt\u00e9",
    "sg:phone":"+32 87 56 01 83",
    "sg:postcode":"4700",
    "sg:province":"Li\u00e8ge",
    "wof:name":"Besch\u00dctzende Werkst\u00c4tte",
    "wof:placetype":"venue"
},
  "geometry": {"coordinates":[6.0126399994,50.6373901367],"type":"Point"}
}