{
  "type": "Feature",
  "properties": {
    "addr:full":"Rue Seraing-le-ch\u00c2teau 27 Verlaine Li\u00e8ge 4537",
    "addr:housenumber":"27",
    "addr:postcode":"4537",
    "addr:street":"Rue Seraing-Le-Cha\u0302Teau",
    "iso:country":"BE",
    "sg:address":"Rue Seraing-le-ch\u00c2teau 27",
    "sg:city":"Verlaine",
    "sg:orig_category":"Experts-comptables",
    "sg:phone":"+32 19 56 64 34",
    "sg:postcode":"4537",
    "sg:province":"Li\u00e8ge",
    "wof:name":"Gerard Laruelle",
    "wof:placetype":"venue"
},
  "geometry": {"coordinates":[5.2753181458,50.6112327576],"type":"Point"}
}