{
  "type": "Feature",
  "properties": {
    "iso:country":"BE",
    "sg:address":"Rue De Genval 21",
    "sg:city":"Rixensart (rosi\u00e8res)",
    "sg:classifiers":[
        {
            "category":"Insurance",
            "subcategory":"Insurance Agent",
            "type":"Services"
        }
    ],
    "sg:phone":"+32 2 654 17 08",
    "sg:postcode":"1331",
    "sg:province":"Brabant Wallon",
    "sg:tags":[
        "broker"
    ],
    "wof:name":"Damiens J",
    "wof:placetype":"venue"
},
  "geometry": {"coordinates":[4.5268168449,50.7286872864],"type":"Point"}
}