{
  "type": "Feature",
  "properties": {
    "iso:country":"BE",
    "sg:address":"Hammestraat 59k",
    "sg:city":"Hamme (moerzeke)",
    "sg:classifiers":[
        {
            "category":"Real Estate",
            "subcategory":"Architect",
            "type":"Services"
        }
    ],
    "sg:phone":"+32 52 47 83 12",
    "sg:postcode":"9220",
    "sg:province":"Oost-Vlaanderen",
    "wof:name":"Pieters A",
    "wof:placetype":"venue"
},
  "geometry": {"coordinates":[4.1499381065,51.0723114014],"type":"Point"}
}