{
  "type": "Feature",
  "properties": {
    "addr:full":"Ambachtstraat 41 Beerse Antwerpen 2340",
    "addr:housenumber":"41",
    "addr:postcode":"2340",
    "addr:street":"Ambachtstraat",
    "iso:country":"BE",
    "sg:address":"Ambachtstraat 41",
    "sg:city":"Beerse",
    "sg:classifiers":[
        {
            "category":"Autos & Motor Vehicles",
            "subcategory":"Motorcycle Sales",
            "type":"Retail Goods"
        }
    ],
    "sg:phone":"+32 14 61 03 95",
    "sg:postcode":"2340",
    "sg:province":"Antwerpen",
    "sg:tags":[
        "motorbike"
    ],
    "wof:name":"R.v.m. Bvba",
    "wof:placetype":"venue"
},
  "geometry": {"coordinates":[4.8346581459,51.3033294678],"type":"Point"}
}