{
  "type": "Feature",
  "properties": {
    "addr:full":"Brouwersvliet 34 Antwerpen Antwerpen 2000",
    "addr:housenumber":"34",
    "addr:postcode":"2000",
    "addr:street":"Brouwersvliet",
    "iso:country":"BE",
    "sg:address":"Brouwersvliet 34",
    "sg:city":"Antwerpen",
    "sg:classifiers":[
        {
            "category":"Cafe",
            "type":"Food & Drink"
        }
    ],
    "sg:phone":"+32 3 226 84 76",
    "sg:postcode":"2000",
    "sg:province":"Antwerpen",
    "sg:tags":[
        "caf\u00e9s"
    ],
    "wof:name":"Caf\u00c9 The Caterpillar",
    "wof:placetype":"venue"
},
  "geometry": {"coordinates":[4.4044737816,51.2267303467],"type":"Point"}
}