{
  "type": "Feature",
  "properties": {
    "iso:country":"BE",
    "sg:address":"Rue Verte 270",
    "sg:city":"Herstal",
    "sg:classifiers":[
        {
            "category":"Arena",
            "subcategory":"Sports Club",
            "type":"Entertainment"
        }
    ],
    "sg:phone":"+32 4 240 09 29",
    "sg:postcode":"4040",
    "sg:province":"Li\u00e8ge",
    "sg:tags":[
        "de"
    ],
    "wof:name":"B.c. Pres Carats Sports",
    "wof:placetype":"venue"
},
  "geometry": {"coordinates":[5.6049528122,50.6761741638],"type":"Point"}
}