{
  "type": "Feature",
  "properties": {
    "addr:full":"Rue Reine Astrid 3 Welkenraedt Li\u00e8ge 4840",
    "addr:housenumber":"3",
    "addr:postcode":"4840",
    "addr:street":"Rue Reine Astrid",
    "iso:country":"BE",
    "sg:address":"Rue Reine Astrid 3",
    "sg:city":"Welkenraedt",
    "sg:orig_category":"Fietsen Sport- and kampeermateriaal",
    "sg:phone":"+32 87 88 23 24",
    "sg:postcode":"4840",
    "sg:province":"Li\u00e8ge",
    "wof:name":"Helios",
    "wof:placetype":"venue"
},
  "geometry": {"coordinates":[5.9775800705,50.6607017517],"type":"Point"}
}