{
  "type": "Feature",
  "properties": {
    "addr:full":"Rue Bay Bonnet 4 Fl\u00e9ron Li\u00e8ge 4620",
    "addr:housenumber":"4",
    "addr:postcode":"4620",
    "addr:street":"Rue Bay Bonnet",
    "iso:country":"BE",
    "sg:address":"Rue Bay Bonnet 4",
    "sg:city":"Fl\u00e9ron",
    "sg:classifiers":[
        {
            "category":"Shopping",
            "subcategory":"Clothing, Apparel, & Fashions",
            "type":"Retail Goods"
        }
    ],
    "sg:phone":"+32 4 355 06 41",
    "sg:postcode":"4620",
    "sg:province":"Li\u00e8ge",
    "sg:tags":[
        "boutique"
    ],
    "wof:name":"Benetton",
    "wof:placetype":"venue"
},
  "geometry": {"coordinates":[5.6900510788,50.6101875305],"type":"Point"}
}