{
  "type": "Feature",
  "properties": {
    "iso:country":"BE",
    "sg:address":"Turnhoutsebaan 5 B247",
    "sg:city":"Wijnegem",
    "sg:classifiers":[
        {
            "category":"Restaurant",
            "type":"Food & Drink"
        }
    ],
    "sg:phone":"+32 3 353 60 07",
    "sg:postcode":"2110",
    "sg:province":"Antwerpen",
    "wof:name":"Mendy's",
    "wof:placetype":"venue"
},
  "geometry": {"coordinates":[4.5248470306,51.2279434204],"type":"Point"}
}