{
  "type": "Feature",
  "properties": {
    "addr:full":"Boulevard Du Tivoli 47 La Louvi\u00e8re Hainaut 7100",
    "addr:housenumber":"47",
    "addr:postcode":"7100",
    "addr:street":"Boulevard Du Tivoli",
    "iso:country":"BE",
    "sg:address":"Boulevard Du Tivoli 47",
    "sg:city":"La Louvi\u00e8re",
    "sg:classifiers":[
        {
            "category":"Health Services",
            "subcategory":"Dentist",
            "type":"Services"
        }
    ],
    "sg:phone":"+32 64 22 65 16",
    "sg:postcode":"7100",
    "sg:province":"Hainaut",
    "wof:name":"Comp\u00e8re Jean-pierre",
    "wof:placetype":"venue"
},
  "geometry": {"coordinates":[4.1993951797,50.4784049988],"type":"Point"}
}