{
  "type": "Feature",
  "properties": {
    "iso:country":"BE",
    "sg:address":"Ferme-de-harroy 1",
    "sg:city":"Houyet",
    "sg:orig_category":"Catering and organisation de f\u00eates. Salles de conf\u00e9rences and de r\u00e9ceptions",
    "sg:phone":"+32 82 66 69 48",
    "sg:postcode":"5563",
    "sg:province":"Namur",
    "wof:name":"La Ferme D'harroy",
    "wof:placetype":"venue"
},
  "geometry": {"coordinates":[5.0382847786,50.1614189148],"type":"Point"}
}