{
  "type": "Feature",
  "properties": {
    "addr:full":"Parkstraat 2 Ravels Antwerpen 2381",
    "addr:housenumber":"2",
    "addr:postcode":"2381",
    "addr:street":"Parkstraat",
    "iso:country":"BE",
    "sg:address":"Parkstraat 2",
    "sg:city":"Ravels",
    "sg:orig_category":"Woningbouw",
    "sg:phone":"+32 14 65 89 27",
    "sg:postcode":"2381",
    "sg:province":"Antwerpen",
    "wof:name":"Jan Sommen",
    "wof:placetype":"venue"
},
  "geometry": {"coordinates":[4.9453802109,51.3954353333],"type":"Point"}
}