{
  "type": "Feature",
  "properties": {
    "iso:country":"BE",
    "sg:address":"Bredabaan 800",
    "sg:city":"Wuustwezel",
    "sg:orig_category":"Charpentes and couvertures. Plomberie, chauffage and installations sanitaires. Quincailleries",
    "sg:phone":"+32 3 663 19 49",
    "sg:postcode":"2990",
    "sg:province":"Antwerpen",
    "wof:name":"Lambrechts",
    "wof:placetype":"venue"
},
  "geometry": {"coordinates":[4.5545501709,51.3597984314],"type":"Point"}
}