{
  "type": "Feature",
  "properties": {
    "addr:full":"Grote Steenweg 27 Lede Oost-Vlaanderen 9340",
    "addr:housenumber":"27",
    "addr:postcode":"9340",
    "addr:street":"Grote Steenweg",
    "iso:country":"BE",
    "sg:address":"Grote Steenweg 27",
    "sg:city":"Lede",
    "sg:orig_category":"Luchtvaart volgens dienstregeling",
    "sg:phone":"+32 9 369 01 24",
    "sg:postcode":"9340",
    "sg:province":"Oost-Vlaanderen",
    "wof:name":"Flanair",
    "wof:placetype":"venue"
},
  "geometry": {"coordinates":[4.0002598763,50.9636230469],"type":"Point"}
}