{
  "type": "Feature",
  "properties": {
    "addr:full":"Astridlaan 58 Brugge West-Vlaanderen 8310",
    "addr:housenumber":"58",
    "addr:postcode":"8310",
    "addr:street":"Astridlaan",
    "iso:country":"BE",
    "sg:address":"Astridlaan 58",
    "sg:city":"Brugge",
    "sg:orig_category":"Brood, gebak and snoepgoed",
    "sg:phone":"+32 50 35 48 62",
    "sg:postcode":"8310",
    "sg:province":"West-Vlaanderen",
    "wof:name":"Bakkerij Poupaert-thoon",
    "wof:placetype":"venue"
},
  "geometry": {"coordinates":[3.2485530376,51.1996536255],"type":"Point"}
}