{
  "type": "Feature",
  "properties": {
    "iso:country":"BE",
    "sg:address":"Guillaume Lambertlaan 63",
    "sg:city":"Genk",
    "sg:classifiers":[
        {
            "category":"Fast Food",
            "type":"Food & Drink"
        }
    ],
    "sg:phone":"+32 89 38 20 97",
    "sg:postcode":"3600",
    "sg:province":"Limburg",
    "sg:tags":[
        "\u00c0",
        "restaurants",
        "emporter",
        "restaurant"
    ],
    "wof:name":"Perfecta",
    "wof:placetype":"venue"
},
  "geometry": {"coordinates":[5.4956240654,51.0032920837],"type":"Point"}
}