{
  "type": "Feature",
  "properties": {
    "iso:country":"BE",
    "sg:address":"Verstrekenstraat 23",
    "sg:city":"Huldenberg",
    "sg:orig_category":"Meubles D\u00e9taillants, Am\u00e9nagement de B\u00e2timents et de Cuisines",
    "sg:phone":"+32 16 47 79 37",
    "sg:postcode":"3040",
    "sg:province":"Vlaams-Brabant",
    "wof:name":"W Leenaerts-magosse",
    "wof:placetype":"venue"
},
  "geometry": {"coordinates":[4.6301779747,50.7675132751],"type":"Point"}
}