{
  "type": "Feature",
  "properties": {
    "addr:full":"Rue Charles Cammaert 38 Bruxelles Bruxelles-Capitale 1120",
    "addr:housenumber":"38",
    "addr:postcode":"1120",
    "addr:street":"Rue Charles Cammaert",
    "iso:country":"BE",
    "sg:address":"Rue Charles Cammaert 38",
    "sg:city":"Bruxelles",
    "sg:classifiers":[
        {
            "category":"Communications",
            "subcategory":"Film & Video Production",
            "type":"Services"
        }
    ],
    "sg:phone":"+32 2 640 10 20",
    "sg:postcode":"1120",
    "sg:province":"Bruxelles-Capitale",
    "sg:tags":[
        "realisation",
        "-"
    ],
    "wof:name":"Mediadreams Production",
    "wof:placetype":"venue"
},
  "geometry": {"coordinates":[4.3837609291,50.8953933716],"type":"Point"}
}