{
  "type": "Feature",
  "properties": {
    "addr:full":"Langestraat 110 Zottegem Oost-Vlaanderen 9620",
    "addr:housenumber":"110",
    "addr:postcode":"9620",
    "addr:street":"Langestraat",
    "iso:country":"BE",
    "sg:address":"Langestraat 110",
    "sg:city":"Zottegem",
    "sg:orig_category":"Travaux de pl\u00e2trage. Travaux de finition and nettoyage de b\u00e2timents",
    "sg:phone":"+32 9 360 80 18",
    "sg:postcode":"9620",
    "sg:province":"Oost-Vlaanderen",
    "wof:name":"Philippe Velghe",
    "wof:placetype":"venue"
},
  "geometry": {"coordinates":[3.8112111092,50.871181488],"type":"Point"}
}