{
  "type": "Feature",
  "properties": {
    "addr:full":"Oeverstraat 20 Kruibeke Oost-Vlaanderen 9150",
    "addr:housenumber":"20",
    "addr:postcode":"9150",
    "addr:street":"Oeverstraat",
    "iso:country":"BE",
    "sg:address":"Oeverstraat 20",
    "sg:city":"Kruibeke",
    "sg:orig_category":"Drogisterijen IJzerwaren, bouw- and verfmaterialen Verlichting and huishoudartikelen Vloer- and muur",
    "sg:phone":"+32 3 774 13 54",
    "sg:postcode":"9150",
    "sg:province":"Oost-Vlaanderen",
    "wof:name":"Huis Moors - Vercammen",
    "wof:placetype":"venue"
},
  "geometry": {"coordinates":[4.2900028229,51.1261482239],"type":"Point"}
}