{
  "type": "Feature",
  "properties": {
    "addr:full":"Rue De Sebles 14 Celles (pottes) Hainaut 7760",
    "addr:housenumber":"14",
    "addr:postcode":"7760",
    "addr:street":"Rue De Sebles",
    "iso:country":"BE",
    "sg:address":"Rue De Sebles 14",
    "sg:city":"Celles (pottes)",
    "sg:classifiers":[
        {
            "category":"Building & Trades",
            "subcategory":"Landscaping Services",
            "type":"Services"
        }
    ],
    "sg:phone":"+32 69 45 61 60",
    "sg:postcode":"7760",
    "sg:province":"Hainaut",
    "sg:tags":[
        "gardening",
        "garden",
        "maintenance"
    ],
    "wof:name":"Le Vert \u00e0 Soi",
    "wof:placetype":"venue"
},
  "geometry": {"coordinates":[3.3990869522,50.7188148499],"type":"Point"}
}