{
  "type": "Feature",
  "properties": {
    "iso:country":"BE",
    "sg:address":"Kozakstraat 43",
    "sg:city":"Wevelgem",
    "sg:classifiers":[
        {
            "category":"Shopping",
            "subcategory":"Musical Instruments",
            "type":"Retail Goods"
        }
    ],
    "sg:phone":"+32 56 40 13 57",
    "sg:postcode":"8560",
    "sg:province":"West-Vlaanderen",
    "sg:tags":[
        "piano",
        "-",
        "tuning"
    ],
    "wof:name":"Laperre Piano's",
    "wof:placetype":"venue"
},
  "geometry": {"coordinates":[3.1885280609,50.8089179993],"type":"Point"}
}