{
  "type": "Feature",
  "properties": {
    "addr:full":"Rue De Limoges 1 Esneux (tilff) Li\u00e8ge 4130",
    "addr:housenumber":"1",
    "addr:postcode":"4130",
    "addr:street":"Rue De Limoges",
    "iso:country":"BE",
    "sg:address":"Rue De Limoges 1",
    "sg:city":"Esneux (tilff)",
    "sg:classifiers":[
        {
            "category":"Building & Trades",
            "subcategory":"Pest Control",
            "type":"Services"
        }
    ],
    "sg:phone":"+32 4 388 14 58",
    "sg:postcode":"4130",
    "sg:province":"Li\u00e8ge",
    "sg:tags":[
        "painting",
        "contractor"
    ],
    "wof:name":"Gillot D",
    "wof:placetype":"venue"
},
  "geometry": {"coordinates":[5.5840978622,50.571685791],"type":"Point"}
}