{
  "type": "Feature",
  "properties": {
    "addr:full":"Francis De Meeuslaan 23 Maldegem Oost-Vlaanderen 9990",
    "addr:housenumber":"23",
    "addr:postcode":"9990",
    "addr:street":"Meeuslaan",
    "iso:country":"BE",
    "sg:address":"Francis De Meeuslaan 23",
    "sg:city":"Maldegem",
    "sg:orig_category":"Herstellingen and onderhoud van auto's",
    "sg:phone":"+32 50 71 20 09",
    "sg:postcode":"9990",
    "sg:province":"Oost-Vlaanderen",
    "wof:name":"Dan Van Deynse",
    "wof:placetype":"venue"
},
  "geometry": {"coordinates":[3.4117100239,51.1930541992],"type":"Point"}
}