{
  "type": "Feature",
  "properties": {
    "addr:full":"Beveldorp 116 Nijlen Antwerpen 2560",
    "addr:housenumber":"116",
    "addr:postcode":"2560",
    "addr:street":"Beveldorp",
    "iso:country":"BE",
    "sg:address":"Beveldorp 116",
    "sg:city":"Nijlen",
    "sg:orig_category":"Boucheries",
    "sg:phone":"+32 3 481 68 88",
    "sg:postcode":"2560",
    "sg:province":"Antwerpen",
    "wof:name":"Jan Peeters",
    "wof:placetype":"venue"
},
  "geometry": {"coordinates":[4.6836791039,51.1362075806],"type":"Point"}
}