{
  "type": "Feature",
  "properties": {
    "addr:full":"Rue De Chaumont 19 Chaumont-gistoux Brabant Wallon 1325",
    "addr:housenumber":"19",
    "addr:postcode":"1325",
    "addr:street":"Rue De Chaumont",
    "iso:country":"BE",
    "sg:address":"Rue De Chaumont 19",
    "sg:city":"Chaumont-gistoux",
    "sg:orig_category":"Artistes ind\u00e9pendants",
    "sg:phone":"+32 10 88 95 83",
    "sg:postcode":"1325",
    "sg:province":"Brabant Wallon",
    "wof:name":"Lemercier",
    "wof:placetype":"venue"
},
  "geometry": {"coordinates":[4.7303681374,50.6923751831],"type":"Point"}
}