{
  "type": "Feature",
  "properties": {
    "addr:full":"Walgoedstraat 6 Temse Oost-Vlaanderen 9140",
    "addr:housenumber":"6",
    "addr:postcode":"9140",
    "addr:street":"Walgoedstraat",
    "iso:country":"BE",
    "sg:address":"Walgoedstraat 6",
    "sg:city":"Temse",
    "sg:orig_category":"Herstellingen and onderhoud van auto's",
    "sg:phone":"+32 3 771 22 71",
    "sg:postcode":"9140",
    "sg:province":"Oost-Vlaanderen",
    "wof:name":"Garage Neefs R",
    "wof:placetype":"venue"
},
  "geometry": {"coordinates":[4.1907119751,51.140007019],"type":"Point"}
}