{
  "type": "Feature",
  "properties": {
    "iso:country":"BE",
    "sg:address":"Avenue Paul Janson 51",
    "sg:city":"Anderlecht/anderlecht",
    "sg:orig_category":"M\u00e9decins and sp\u00e9cialistes",
    "sg:phone":"+32 2 521 11 52",
    "sg:postcode":"1070",
    "sg:province":"Bruxelles-Capitale",
    "wof:name":"A. Depaepe",
    "wof:placetype":"venue"
},
  "geometry": {"coordinates":[4.3044939041,50.8341674805],"type":"Point"}
}