{
  "type": "Feature",
  "properties": {
    "addr:full":"Oude Dorpsweg 114 Jabbeke West-Vlaanderen 8490",
    "addr:housenumber":"114",
    "addr:postcode":"8490",
    "addr:street":"Oude Dorpsweg",
    "iso:country":"BE",
    "sg:address":"Oude Dorpsweg 114",
    "sg:city":"Jabbeke",
    "sg:orig_category":"Kapsalons",
    "sg:phone":"+32 50 39 25 12",
    "sg:postcode":"8490",
    "sg:province":"West-Vlaanderen",
    "wof:name":"Coiffure Arany",
    "wof:placetype":"venue"
},
  "geometry": {"coordinates":[3.142168045,51.1851730347],"type":"Point"}
}