{
  "type": "Feature",
  "properties": {
    "iso:country":"BE",
    "sg:address":"Rue De La Gilette 1",
    "sg:city":"Mettet (stave)",
    "sg:classifiers":[
        {
            "category":"Autos & Motor Vehicles",
            "subcategory":"Motorcycle Sales",
            "type":"Retail Goods"
        }
    ],
    "sg:phone":"+32 71 72 57 20",
    "sg:postcode":"5646",
    "sg:province":"Namur",
    "sg:tags":[
        "motorbike"
    ],
    "wof:name":"H B Moteur",
    "wof:placetype":"venue"
},
  "geometry": {"coordinates":[4.6609611511,50.2835845947],"type":"Point"}
}