{
  "type": "Feature",
  "properties": {
    "iso:country":"BE",
    "sg:address":"Bosstraat 63",
    "sg:city":"Sint-katelijne-waver (onze-lieve-vrouw-waver)",
    "sg:classifiers":[
        {
            "category":"Personal",
            "subcategory":"Beauty Salon",
            "type":"Services"
        }
    ],
    "sg:phone":"+32 15 75 47 77",
    "sg:postcode":"2861",
    "sg:province":"Antwerpen",
    "sg:tags":[
        "lady",
        "-",
        "hairdressing"
    ],
    "wof:name":"Diane",
    "wof:placetype":"venue"
},
  "geometry": {"coordinates":[4.5742931366,51.071056366],"type":"Point"}
}