{
  "type": "Feature",
  "properties": {
    "addr:full":"Museumlaan 20 Sint-martens-latem Oost-Vlaanderen 9831",
    "addr:housenumber":"20",
    "addr:postcode":"9831",
    "addr:street":"Museumlaan",
    "iso:country":"BE",
    "sg:address":"Museumlaan 20",
    "sg:city":"Sint-martens-latem",
    "sg:classifiers":[
        {
            "category":"Arena",
            "subcategory":"Sports Club",
            "type":"Entertainment"
        }
    ],
    "sg:phone":"+32 9 282 20 20",
    "sg:postcode":"9831",
    "sg:province":"Oost-Vlaanderen",
    "sg:tags":[
        "de"
    ],
    "wof:name":"H.c. Leopard",
    "wof:placetype":"venue"
},
  "geometry": {"coordinates":[3.6016900539,51.0127449036],"type":"Point"}
}