{
  "type": "Feature",
  "properties": {
    "addr:full":"Rue Des Grands Pr\u00c9s 48 Mons Hainaut 7000",
    "addr:housenumber":"48",
    "addr:postcode":"7000",
    "addr:street":"Rue Des Grands Pre\u0301S;Hainaut",
    "iso:country":"BE",
    "sg:address":"Rue Des Grands Pr\u00c9s 48",
    "sg:city":"Mons",
    "sg:orig_category":"Entretien et r\u00e9parations de v\u00e9hicules \u00e0 domicile",
    "sg:phone":"+32 65 84 40 05",
    "sg:postcode":"7000",
    "sg:province":"Hainaut",
    "wof:name":"M.d.s.",
    "wof:placetype":"venue"
},
  "geometry": {"coordinates":[3.9514250755,50.4502868652],"type":"Point"}
}