{
  "type": "Feature",
  "properties": {
    "addr:full":"Prins Leopoldlei 24 Mortsel Antwerpen 2640",
    "addr:housenumber":"24",
    "addr:postcode":"2640",
    "addr:street":"Prins Leopoldlei",
    "iso:country":"BE",
    "sg:address":"Prins Leopoldlei 24",
    "sg:city":"Mortsel",
    "sg:orig_category":"Herstelling leer and schoeisel",
    "sg:phone":"+32 3 449 26 13",
    "sg:postcode":"2640",
    "sg:province":"Antwerpen",
    "wof:name":"Guy Van Put",
    "wof:placetype":"venue"
},
  "geometry": {"coordinates":[4.4542708397,51.1694374084],"type":"Point"}
}