{
  "type": "Feature",
  "properties": {
    "iso:country":"BE",
    "sg:address":"Rue De La Terre \u00e0 Briques 6",
    "sg:city":"Tournai (blandain - Hertain)",
    "sg:classifiers":[
        {
            "category":"Professional",
            "subcategory":"Management & Consulting",
            "type":"Services"
        }
    ],
    "sg:phone":"+32 69 34 39 10",
    "sg:postcode":"7522",
    "sg:province":"Hainaut",
    "sg:tags":[
        "consultant",
        "promotion",
        "-",
        "sale"
    ],
    "wof:name":"Primo Sep",
    "wof:placetype":"venue"
},
  "geometry": {"coordinates":[3.3341469765,50.6075248718],"type":"Point"}
}