{
  "type": "Feature",
  "properties": {
    "iso:country":"BE",
    "sg:address":"Gasthuisstraat 18",
    "sg:city":"Balen",
    "sg:orig_category":"Sportclubs",
    "sg:phone":"+32 14 81 37 64",
    "sg:postcode":"2490",
    "sg:province":"Antwerpen",
    "wof:name":"T.c. Wezel",
    "wof:placetype":"venue"
},
  "geometry": {"coordinates":[5.1648488045,51.1685028076],"type":"Point"}
}