{
  "type": "Feature",
  "properties": {
    "addr:full":"Herstappelstraat 5 Tongeren Limburg 3700",
    "addr:housenumber":"5",
    "addr:postcode":"3700",
    "addr:street":"Herstappelstraat",
    "iso:country":"BE",
    "sg:address":"Herstappelstraat 5",
    "sg:city":"Tongeren",
    "sg:orig_category":"Pleisterwerk",
    "sg:phone":"+32 12 23 39 70",
    "sg:postcode":"3700",
    "sg:province":"Limburg",
    "wof:name":"Plex",
    "wof:placetype":"venue"
},
  "geometry": {"coordinates":[5.4636240005,50.7807197571],"type":"Point"}
}