{
  "type": "Feature",
  "properties": {
    "iso:country":"BE",
    "sg:address":"Rue De Vis\u00e9 414",
    "sg:city":"Li\u00e8ge 1 (wandre)",
    "sg:classifiers":[
        {
            "category":"Professional",
            "subcategory":"Printing & Photocopies",
            "type":"Services"
        }
    ],
    "sg:phone":"+32 4 362 61 45",
    "sg:postcode":"4020",
    "sg:province":"Li\u00e8ge",
    "sg:tags":[
        "silkscreen",
        "-"
    ],
    "wof:name":"Design 3-2 Sprl",
    "wof:placetype":"venue"
},
  "geometry": {"coordinates":[5.6501698494,50.6570053101],"type":"Point"}
}