{
  "type": "Feature",
  "properties": {
    "addr:full":"Route De Philippeville 48 Charleroi Hainaut 6010",
    "addr:housenumber":"48",
    "addr:postcode":"6010",
    "addr:street":"Route De Philippeville;Hainaut",
    "iso:country":"BE",
    "sg:address":"Route De Philippeville 48",
    "sg:city":"Charleroi",
    "sg:orig_category":"Cr\u00e9dits divers",
    "sg:postcode":"6010",
    "sg:province":"Hainaut",
    "wof:name":"Bancontact-mister Cash",
    "wof:placetype":"venue"
},
  "geometry": {"coordinates":[4.4584698677,50.3918151855],"type":"Point"}
}