{
  "type": "Feature",
  "properties": {
    "iso:country":"BE",
    "sg:address":"Rue Des Hayettes 14",
    "sg:city":"Profondeville",
    "sg:orig_category":"Forge, Moulage and Profilage des M\u00e9taux",
    "sg:phone":"+32 81 43 32 48",
    "sg:postcode":"5170",
    "sg:province":"Namur",
    "wof:name":"Massin",
    "wof:placetype":"venue"
},
  "geometry": {"coordinates":[4.7903928757,50.373626709],"type":"Point"}
}