{
  "type": "Feature",
  "properties": {
    "addr:full":"St-gillisln 6b Dendermonde Oost-Vlaanderen 9200",
    "addr:housenumber":"6b",
    "addr:postcode":"9200",
    "addr:street":"St-Gillisln;Oost-Vlaanderen",
    "iso:country":"BE",
    "sg:address":"St-gillisln 6b",
    "sg:city":"Dendermonde",
    "sg:classifiers":[
        {
            "category":"Professional",
            "subcategory":"Engineering",
            "type":"Services"
        }
    ],
    "sg:phone":"+32 52 21 13 51",
    "sg:postcode":"9200",
    "sg:province":"Oost-Vlaanderen",
    "sg:tags":[
        "machine",
        "-",
        "mechanical"
    ],
    "wof:name":"Stahl Nv",
    "wof:placetype":"venue"
},
  "geometry": {"coordinates":[4.1074028015,51.0218276978],"type":"Point"}
}