{
  "type": "Feature",
  "properties": {
    "iso:country":"BE",
    "sg:address":"Provinciale Steenweg 145",
    "sg:city":"Schelle",
    "sg:classifiers":[
        {
            "category":"Health Services",
            "subcategory":"Doctor",
            "type":"Services"
        }
    ],
    "sg:phone":"+32 3 887 33 33",
    "sg:postcode":"2627",
    "sg:province":"Antwerpen",
    "sg:tags":[
        "medicinephysicians",
        "surgeon"
    ],
    "wof:name":"De Backer Wim",
    "wof:placetype":"venue"
},
  "geometry": {"coordinates":[4.3393158913,51.1260604858],"type":"Point"}
}