{
  "type": "Feature",
  "properties": {
    "addr:full":"Place De Mainvault 83 Ath (mainvault) Hainaut 7812",
    "addr:housenumber":"83",
    "addr:postcode":"7812",
    "addr:street":"Place De Mainvault",
    "iso:country":"BE",
    "sg:address":"Place De Mainvault 83",
    "sg:city":"Ath (mainvault)",
    "sg:classifiers":[
        {
            "category":"Home & Garden",
            "subcategory":"Building Materials",
            "type":"Retail Goods"
        }
    ],
    "sg:phone":"+32 68 64 64 08",
    "sg:postcode":"7812",
    "sg:province":"Hainaut",
    "sg:tags":[
        "house"
    ],
    "wof:name":"Mainvault (scierie De)",
    "wof:placetype":"venue"
},
  "geometry": {"coordinates":[3.7163300514,50.6490135193],"type":"Point"}
}