{
  "type": "Feature",
  "properties": {
    "iso:country":"BE",
    "sg:address":"Chauss\u00c9e De Bruxelles 8",
    "sg:city":"Court-saint-etienne",
    "sg:orig_category":"Epiceries",
    "sg:phone":"+32 10 61 57 98",
    "sg:postcode":"1490",
    "sg:province":"Brabant Wallon",
    "wof:name":"Gilbert De Pooter",
    "wof:placetype":"venue"
},
  "geometry": {"coordinates":[4.5624341965,50.6529884338],"type":"Point"}
}