{
  "type": "Feature",
  "properties": {
    "addr:full":"Boomsesteenweg 560 Antwerpen Antwerpen 2610",
    "addr:housenumber":"560",
    "addr:postcode":"2610",
    "addr:street":"Boomsesteenweg",
    "iso:country":"BE",
    "sg:address":"Boomsesteenweg 560",
    "sg:city":"Antwerpen",
    "sg:orig_category":"Autoverhuur",
    "sg:phone":"+32 3 829 10 00",
    "sg:postcode":"2610",
    "sg:province":"Antwerpen",
    "wof:name":"Avis",
    "wof:placetype":"venue"
},
  "geometry": {"coordinates":[4.3946051598,51.1691131592],"type":"Point"}
}