{
  "type": "Feature",
  "properties": {
    "iso:country":"BE",
    "sg:address":"Sint-jobstraat 163ba",
    "sg:city":"Heusden-zolder",
    "sg:classifiers":[
        {
            "category":"Fast Food",
            "type":"Food & Drink"
        }
    ],
    "sg:phone":"+32 11 87 32 00",
    "sg:postcode":"3550",
    "sg:province":"Limburg",
    "sg:tags":[
        "\u00c0",
        "restaurants",
        "emporter",
        "restaurant"
    ],
    "wof:name":"Frituur Pierrot",
    "wof:placetype":"venue"
},
  "geometry": {"coordinates":[5.2744550705,50.9819374084],"type":"Point"}
}