{
  "type": "Feature",
  "properties": {
    "addr:full":"Rue Des Alli\u00c9s 35 Charleroi Hainaut 6044",
    "addr:housenumber":"35",
    "addr:postcode":"6044",
    "addr:street":"Rue Des Allie\u0301S;Hainaut",
    "iso:country":"BE",
    "sg:address":"Rue Des Alli\u00c9s 35",
    "sg:city":"Charleroi",
    "sg:orig_category":"Electrom\u00e9nager, t\u00e9l\u00e9visions and radios",
    "sg:phone":"+32 71 46 17 66",
    "sg:postcode":"6044",
    "sg:province":"Hainaut",
    "wof:name":"Emplis",
    "wof:placetype":"venue"
},
  "geometry": {"coordinates":[4.3906149864,50.4403190613],"type":"Point"}
}