{
  "type": "Feature",
  "properties": {
    "addr:full":"Hentjenslaan 9a Hasselt Limburg 3511",
    "addr:housenumber":"9a",
    "addr:postcode":"3511",
    "addr:street":"Hentjenslaan",
    "iso:country":"BE",
    "sg:address":"Hentjenslaan 9a",
    "sg:city":"Hasselt",
    "sg:orig_category":"Eclairage et \u00e9quipements du foyer. D\u00e9corateurs d'int\u00e9rieur. Installation de menuiserie en bois and p",
    "sg:phone":"+32 11 25 35 02",
    "sg:postcode":"3511",
    "sg:province":"Limburg",
    "wof:name":"Simoni Interieur",
    "wof:placetype":"venue"
},
  "geometry": {"coordinates":[5.2956199646,50.942741394],"type":"Point"}
}