{
  "type": "Feature",
  "properties": {
    "addr:full":"Avenue Fran\u00e7ois Cornesse 25 Aywaille Li\u00e8ge 4920",
    "addr:housenumber":"25",
    "addr:postcode":"4920",
    "addr:street":"Avenue Franc\u0327Ois Cornesse",
    "iso:country":"BE",
    "sg:address":"Avenue Fran\u00e7ois Cornesse 25",
    "sg:city":"Aywaille",
    "sg:classifiers":[
        {
            "category":"Building & Trades",
            "subcategory":"Plumbing",
            "type":"Services"
        }
    ],
    "sg:phone":"+32 4 384 55 70",
    "sg:postcode":"4920",
    "sg:province":"Li\u00e8ge",
    "sg:tags":[
        "repair",
        "mainten",
        "-",
        "central",
        "heating"
    ],
    "wof:name":"Castro J",
    "wof:placetype":"venue"
},
  "geometry": {"coordinates":[5.673915863,50.474407196],"type":"Point"}
}