{
  "type": "Feature",
  "properties": {
    "iso:country":"BE",
    "sg:address":"Alfons Jeurissenstraat 112",
    "sg:city":"Diepenbeek",
    "sg:orig_category":"Airconditioning and ventilatie Elektrische installaties voor woningen Winkelinrichting and handelsui",
    "sg:phone":"+32 89 36 41 92",
    "sg:postcode":"3590",
    "sg:province":"Limburg",
    "wof:name":"H.v.a. Koeling",
    "wof:placetype":"venue"
},
  "geometry": {"coordinates":[5.4295549393,50.9302482605],"type":"Point"}
}