{
  "type": "Feature",
  "properties": {
    "addr:full":"Chauss\u00c9e De Wavre 29b1 Wanze Li\u00e8ge 4520",
    "addr:housenumber":"29b1",
    "addr:postcode":"4520",
    "addr:street":"Chausse\u0301E De Wavre",
    "iso:country":"BE",
    "sg:address":"Chauss\u00c9e De Wavre 29b1",
    "sg:city":"Wanze",
    "sg:orig_category":"Epiceries",
    "sg:phone":"+32 85 25 32 59",
    "sg:postcode":"4520",
    "sg:province":"Li\u00e8ge",
    "wof:name":"Au Gourmet Gourmand",
    "wof:placetype":"venue"
},
  "geometry": {"coordinates":[5.2160382271,50.5356407166],"type":"Point"}
}