{
  "type": "Feature",
  "properties": {
    "iso:country":"BE",
    "sg:address":"Dokter Haekstraat 70b1",
    "sg:city":"Dendermonde",
    "sg:orig_category":"Quincailleries",
    "sg:phone":"+32 52 21 27 09",
    "sg:postcode":"9200",
    "sg:province":"Oost-Vlaanderen",
    "wof:name":"Maria-louisa Everaert",
    "wof:placetype":"venue"
},
  "geometry": {"coordinates":[4.1074638367,51.050239563],"type":"Point"}
}