{
  "type": "Feature",
  "properties": {
    "addr:full":"Beulk 5-7 Lille (wechelderzande) Antwerpen 2275",
    "addr:housenumber":"5-7",
    "addr:postcode":"2275",
    "addr:street":"Beulk",
    "iso:country":"BE",
    "sg:address":"Beulk 5-7",
    "sg:city":"Lille (wechelderzande)",
    "sg:classifiers":[
        {
            "category":"Manufacturing",
            "subcategory":"Lumber",
            "type":"Manufacturing & Wholesale Goods"
        }
    ],
    "sg:phone":"+32 3 309 14 50",
    "sg:postcode":"2275",
    "sg:province":"Antwerpen",
    "sg:tags":[
        "timber"
    ],
    "wof:name":"Helsen Houtbedrijf Nv",
    "wof:placetype":"venue"
},
  "geometry": {"coordinates":[4.7826452255,51.2638664246],"type":"Point"}
}