{
  "type": "Feature",
  "properties": {
    "iso:country":"BE",
    "sg:address":"Truweelstraat 22",
    "sg:city":"Sint-niklaas",
    "sg:orig_category":"Huishoudapparaten, televisies and radio's Verlichting and huishoudartikelen",
    "sg:phone":"+32 3 776 39 70",
    "sg:postcode":"9100",
    "sg:province":"Oost-Vlaanderen",
    "wof:name":"Lampenhuis",
    "wof:placetype":"venue"
},
  "geometry": {"coordinates":[4.148337841,51.1686973572],"type":"Point"}
}