{
  "type": "Feature",
  "properties": {
    "iso:country":"BE",
    "sg:address":"Rue De Seumay 38",
    "sg:city":"Perwijs (groot)",
    "sg:orig_category":"Elektrische installaties voor woningen",
    "sg:phone":"+32 81 65 63 67",
    "sg:postcode":"1360",
    "sg:province":"Brabant Wallon",
    "wof:name":"Martougin R.",
    "wof:placetype":"venue"
},
  "geometry": {"coordinates":[4.823600769,50.6269989014],"type":"Point"}
}