{
  "type": "Feature",
  "properties": {
    "addr:full":"Rue De Namur 87 Charleroi Hainaut 6041",
    "addr:housenumber":"87",
    "addr:postcode":"6041",
    "addr:street":"Rue De Namur;Hainaut",
    "iso:country":"BE",
    "sg:address":"Rue De Namur 87",
    "sg:city":"Charleroi",
    "sg:classifiers":[
        {
            "category":"Cinema",
            "subcategory":"Movie Rental",
            "type":"Entertainment"
        }
    ],
    "sg:phone":"+32 71 35 34 00",
    "sg:postcode":"6041",
    "sg:province":"Hainaut",
    "sg:tags":[
        "de",
        "cassette",
        "location",
        "vid\u00e9o",
        "audio"
    ],
    "wof:name":"Vid\u00c9oth\u00c8que Image",
    "wof:placetype":"venue"
},
  "geometry": {"coordinates":[4.441824913,50.4213256836],"type":"Point"}
}