{
  "type": "Feature",
  "properties": {
    "iso:country":"BE",
    "sg:address":"Leeuwerikstraat 6",
    "sg:city":"Lokeren",
    "sg:classifiers":[
        {
            "category":"Shopping",
            "subcategory":"Computers & Home Electronics",
            "type":"Retail Goods"
        }
    ],
    "sg:phone":"+32 475 38 69 96",
    "sg:postcode":"9160",
    "sg:province":"Oost-Vlaanderen",
    "sg:tags":[
        "spare",
        "part",
        "processing",
        "-",
        "data"
    ],
    "wof:name":"Robc@computers",
    "wof:placetype":"venue"
},
  "geometry": {"coordinates":[4.0057530403,51.109703064],"type":"Point"}
}