{
  "type": "Feature",
  "properties": {
    "addr:full":"Chauss\u00e9e De Lodelinsart 219 Charleroi (gilly) Hainaut 6060",
    "addr:housenumber":"219",
    "addr:postcode":"6060",
    "addr:street":"Chausse\u0301E De Lodelinsart",
    "iso:country":"BE",
    "sg:address":"Chauss\u00e9e De Lodelinsart 219",
    "sg:city":"Charleroi (gilly)",
    "sg:classifiers":[
        {
            "category":"Health Services",
            "subcategory":"Dentist",
            "type":"Services"
        }
    ],
    "sg:phone":"+32 71 48 66 48",
    "sg:postcode":"6060",
    "sg:province":"Hainaut",
    "wof:name":"Vincart B",
    "wof:placetype":"venue"
},
  "geometry": {"coordinates":[4.4880981445,50.4251937866],"type":"Point"}
}