{
  "type": "Feature",
  "properties": {
    "iso:country":"BE",
    "sg:address":"Kruisbeeldstraat 72",
    "sg:city":"Hamme",
    "sg:classifiers":[
        {
            "category":"Bakery",
            "type":"Food & Drink"
        }
    ],
    "sg:phone":"+32 52 47 75 56",
    "sg:postcode":"9220",
    "sg:province":"Oost-Vlaanderen",
    "sg:tags":[
        "confectioner",
        "baker"
    ],
    "wof:name":"Mariman Nv",
    "wof:placetype":"venue"
},
  "geometry": {"coordinates":[4.1145181656,51.0960426331],"type":"Point"}
}