{
  "type": "Feature",
  "properties": {
    "addr:full":"Avenue De La Toison D'or 70 Marche-en-famenne Luxembourg 6900",
    "addr:housenumber":"70",
    "addr:postcode":"6900",
    "addr:street":"Avenue De La Toison D'Or",
    "iso:country":"BE",
    "sg:address":"Avenue De La Toison D'or 70",
    "sg:city":"Marche-en-famenne",
    "sg:orig_category":"Agences immobili\u00e8res",
    "sg:phone":"+32 84 31 42 26",
    "sg:postcode":"6900",
    "sg:province":"Luxembourg",
    "wof:name":"Bureau Compagnie Rochez",
    "wof:placetype":"venue"
},
  "geometry": {"coordinates":[5.3430099487,50.2273483276],"type":"Point"}
}