{
  "type": "Feature",
  "properties": {
    "addr:full":"Pav\u00c9 De Warquignies 112 Colfontaine Hainaut 7340",
    "addr:housenumber":"112",
    "addr:postcode":"7340",
    "iso:country":"BE",
    "sg:address":"Pav\u00c9 De Warquignies 112",
    "sg:city":"Colfontaine",
    "sg:orig_category":"Epiceries",
    "sg:phone":"+32 65 65 35 35",
    "sg:postcode":"7340",
    "sg:province":"Hainaut",
    "wof:name":"Spar",
    "wof:placetype":"venue"
},
  "geometry": {"coordinates":[3.8211929798,50.4002342224],"type":"Point"}
}