{
  "type": "Feature",
  "properties": {
    "addr:full":"Rue Des Raines 38 Verviers Li\u00e8ge 4800",
    "addr:housenumber":"38",
    "addr:postcode":"4800",
    "addr:street":"Rue Des Raines",
    "iso:country":"BE",
    "sg:address":"Rue Des Raines 38",
    "sg:city":"Verviers",
    "sg:classifiers":[
        {
            "category":"Bakery",
            "type":"Food & Drink"
        }
    ],
    "sg:phone":"+32 87 33 27 12",
    "sg:postcode":"4800",
    "sg:province":"Li\u00e8ge",
    "sg:tags":[
        "confectioner",
        "baker"
    ],
    "wof:name":"Maquinay Sprl",
    "wof:placetype":"venue"
},
  "geometry": {"coordinates":[5.8685040474,50.5947265625],"type":"Point"}
}