{
  "type": "Feature",
  "properties": {
    "iso:country":"BE",
    "sg:address":"Katelijnevest 13",
    "sg:city":"Brugge",
    "sg:classifiers":[
        {
            "category":"Banks & Credit Unions",
            "subcategory":"Investment Brokerage",
            "type":"Services"
        }
    ],
    "sg:phone":"+32 50 33 61 08",
    "sg:postcode":"8000",
    "sg:province":"West-Vlaanderen",
    "sg:tags":[
        "repair",
        "-",
        "installation",
        "sanitary",
        "article"
    ],
    "wof:name":"Paul Vandenbussche-lampo Bvba",
    "wof:placetype":"venue"
},
  "geometry": {"coordinates":[3.2273929119,51.1992912292],"type":"Point"}
}