{
  "type": "Feature",
  "properties": {
    "iso:country":"BE",
    "sg:address":"Chauss\u00c9e De Gramptinne 128",
    "sg:city":"Gesves",
    "sg:orig_category":"Kapsalons",
    "sg:phone":"+32 83 67 79 51",
    "sg:postcode":"5340",
    "sg:province":"Namur",
    "wof:name":"F\u00c9minin-masculin",
    "wof:placetype":"venue"
},
  "geometry": {"coordinates":[5.0688729286,50.4067115784],"type":"Point"}
}