{
  "type": "Feature",
  "properties": {
    "iso:country":"BE",
    "sg:address":"Ferme Du Fresnoy 1",
    "sg:city":"Ittre",
    "sg:orig_category":"Rundveehouders Varkenskwekers",
    "sg:phone":"+32 67 64 61 09",
    "sg:postcode":"1460",
    "sg:province":"Brabant Wallon",
    "wof:name":"Daniel Van Landuyt",
    "wof:placetype":"venue"
},
  "geometry": {"coordinates":[4.2677350044,50.6369895935],"type":"Point"}
}