{
  "type": "Feature",
  "properties": {
    "iso:country":"BE",
    "sg:address":"Verloren Kreek 2",
    "sg:city":"Maldegem",
    "sg:orig_category":"Rundveehouders",
    "sg:phone":"+32 50 50 05 97",
    "sg:postcode":"9992",
    "sg:province":"Oost-Vlaanderen",
    "wof:name":"Antonius Raeman",
    "wof:placetype":"venue"
},
  "geometry": {"coordinates":[3.401927948,51.2606658936],"type":"Point"}
}