{
  "type": "Feature",
  "properties": {
    "addr:full":"Rue De La Poterie 51 Chimay (forges) Hainaut 6464",
    "addr:housenumber":"51",
    "addr:postcode":"6464",
    "addr:street":"Rue De La Poterie",
    "iso:country":"BE",
    "sg:address":"Rue De La Poterie 51",
    "sg:city":"Chimay (forges)",
    "sg:classifiers":[
        {
            "category":"Health Services",
            "subcategory":"Doctor",
            "type":"Services"
        }
    ],
    "sg:phone":"+32 60 21 33 50",
    "sg:postcode":"6464",
    "sg:province":"Hainaut",
    "sg:tags":[
        "psychotherapist",
        "psychoanalyst"
    ],
    "wof:name":"Declerck P",
    "wof:placetype":"venue"
},
  "geometry": {"coordinates":[4.3314599991,50.0269889832],"type":"Point"}
}