{
  "type": "Feature",
  "properties": {
    "addr:full":"Ezenhoek 59 Berlaar Antwerpen 2590",
    "addr:housenumber":"59",
    "addr:postcode":"2590",
    "addr:street":"Ezenhoek",
    "iso:country":"BE",
    "sg:address":"Ezenhoek 59",
    "sg:city":"Berlaar",
    "sg:orig_category":"Eleveurs de bovins",
    "sg:phone":"+32 15 24 16 24",
    "sg:postcode":"2590",
    "sg:province":"Antwerpen",
    "wof:name":"Jos Van Hove",
    "wof:placetype":"venue"
},
  "geometry": {"coordinates":[4.688934803,51.1040153503],"type":"Point"}
}