{
  "type": "Feature",
  "properties": {
    "iso:country":"BE",
    "sg:address":"Rue Joseph Wettinck 22",
    "sg:city":"Seraing (jemeppe-sur-meuse)",
    "sg:classifiers":[
        {
            "category":"Shopping",
            "subcategory":"Clothing, Apparel, & Fashions",
            "type":"Retail Goods"
        }
    ],
    "sg:phone":"+32 4 233 41 84",
    "sg:postcode":"4101",
    "sg:province":"Li\u00e8ge",
    "sg:tags":[
        "-",
        "haberdashery"
    ],
    "wof:name":"Podziukas Tissus",
    "wof:placetype":"venue"
},
  "geometry": {"coordinates":[5.5025339127,50.6157798767],"type":"Point"}
}