{
  "type": "Feature",
  "properties": {
    "iso:country":"BE",
    "sg:address":"Avenue Bourg. Jean Materne 101",
    "sg:city":"Namur",
    "sg:orig_category":"Opticiens",
    "sg:phone":"+32 81 31 18 02",
    "sg:postcode":"5100",
    "sg:province":"Namur",
    "wof:name":"Optique Lema\u00cetre",
    "wof:placetype":"venue"
},
  "geometry": {"coordinates":[4.8713750839,50.4566345215],"type":"Point"}
}