{
  "type": "Feature",
  "properties": {
    "addr:full":"Schoolstraat 54 Temse Oost-Vlaanderen 9140",
    "addr:housenumber":"54",
    "addr:postcode":"9140",
    "addr:street":"Schoolstraat",
    "iso:country":"BE",
    "sg:address":"Schoolstraat 54",
    "sg:city":"Temse",
    "sg:orig_category":"Computers Fab Computers and computerapparatuur Informaticaconsulenten Kantoormateriaal Onderhoud van",
    "sg:phone":"+32 3 711 08 42",
    "sg:postcode":"9140",
    "sg:province":"Oost-Vlaanderen",
    "wof:name":"Us-connect Temse",
    "wof:placetype":"venue"
},
  "geometry": {"coordinates":[4.2085781097,51.1268806458],"type":"Point"}
}