{
  "type": "Feature",
  "properties": {
    "iso:country":"BE",
    "sg:address":"Isabellastraat 52b4",
    "sg:city":"Hasselt",
    "sg:orig_category":"Avocats and conseillers juridiques",
    "sg:phone":"+32 11 22 13 00",
    "sg:postcode":"3500",
    "sg:province":"Limburg",
    "wof:name":"Willem Descamps",
    "wof:placetype":"venue"
},
  "geometry": {"coordinates":[5.3365721703,50.9332427979],"type":"Point"}
}