{
  "type": "Feature",
  "properties": {
    "iso:country":"BE",
    "sg:address":"Beho 35",
    "sg:city":"Gouvy (beho)",
    "sg:classifiers":[
        {
            "category":"Farming",
            "subcategory":"Farm & Veterinary Services",
            "type":"Manufacturing & Wholesale Goods"
        }
    ],
    "sg:phone":"+32 80 51 73 78",
    "sg:postcode":"6672",
    "sg:province":"Luxembourg",
    "sg:tags":[
        "agricultural",
        "contractor"
    ],
    "wof:name":"Blesses A",
    "wof:placetype":"venue"
},
  "geometry": {"coordinates":[5.9929800034,50.2188682556],"type":"Point"}
}