{
  "type": "Feature",
  "properties": {
    "addr:full":"Risquons-toutsteenweg 479 Moeskroen/mouscron Hainaut 7700",
    "addr:housenumber":"479 moeskroen;mouscron",
    "addr:postcode":"7700",
    "addr:street":"Hainaut",
    "iso:country":"BE",
    "sg:address":"Risquons-toutsteenweg 479",
    "sg:city":"Moeskroen/mouscron",
    "sg:orig_category":"Instellingen voor probleemkinderen Kindertehuizen",
    "sg:phone":"+32 56 33 25 25",
    "sg:postcode":"7700",
    "sg:province":"Hainaut",
    "wof:name":"Le Foyer",
    "wof:placetype":"venue"
},
  "geometry": {"coordinates":[3.2323200703,50.7400932312],"type":"Point"}
}