{
  "type": "Feature",
  "properties": {
    "iso:country":"BE",
    "sg:address":"Kortrijkstraat 92d",
    "sg:city":"Zwevegem",
    "sg:classifiers":[
        {
            "category":"Bars & Pubs",
            "type":"Food & Drink"
        }
    ],
    "sg:phone":"+32 56 75 49 92",
    "sg:postcode":"8550",
    "sg:province":"West-Vlaanderen",
    "wof:name":"Regent's (the)",
    "wof:placetype":"venue"
},
  "geometry": {"coordinates":[3.3216071129,50.8139762878],"type":"Point"}
}