{
  "type": "Feature",
  "properties": {
    "addr:full":"Sint-jacobsplein 19 Leuven Vlaams-Brabant 3000",
    "addr:housenumber":"19",
    "addr:postcode":"3000",
    "addr:street":"Sint-Jacobsplein",
    "iso:country":"BE",
    "sg:address":"Sint-jacobsplein 19",
    "sg:city":"Leuven",
    "sg:orig_category":"Avocats and conseillers juridiques",
    "sg:phone":"+32 16 22 30 23",
    "sg:postcode":"3000",
    "sg:province":"Vlaams-Brabant",
    "wof:name":"Ivo Mercelis",
    "wof:placetype":"venue"
},
  "geometry": {"coordinates":[4.6899719238,50.8797874451],"type":"Point"}
}