{
  "type": "Feature",
  "properties": {
    "iso:country":"BE",
    "sg:address":"Patersstraat 33-35",
    "sg:city":"Turnhout",
    "sg:classifiers":[
        {
            "category":"Shopping",
            "subcategory":"Baby Store",
            "type":"Retail Goods"
        }
    ],
    "sg:phone":"+32 14 42 68 37",
    "sg:postcode":"2300",
    "sg:province":"Antwerpen",
    "sg:tags":[
        "-",
        "accessory"
    ],
    "wof:name":"B\u00e9b\u00e9-lux",
    "wof:placetype":"venue"
},
  "geometry": {"coordinates":[4.9495902061,51.3249397278],"type":"Point"}
}