{
  "type": "Feature",
  "properties": {
    "addr:full":"Avenue D\u00b4auderghem 280 Etterbeek Bruxelles-Capitale 1040",
    "addr:housenumber":"280",
    "addr:postcode":"1040",
    "addr:street":"Avenue D\u00b4Auderghem",
    "iso:country":"BE",
    "sg:address":"Avenue D\u00b4auderghem 280",
    "sg:city":"Etterbeek",
    "sg:classifiers":[
        {
            "category":"Fast Food",
            "type":"Food & Drink"
        }
    ],
    "sg:phone":"+32 2 646 13 86",
    "sg:postcode":"1040",
    "sg:province":"Bruxelles-Capitale",
    "sg:tags":[
        "\u00c0",
        "restaurants",
        "emporter",
        "restaurant"
    ],
    "wof:name":"Salam Bombay",
    "wof:placetype":"venue"
},
  "geometry": {"coordinates":[4.3894281387,50.8323554993],"type":"Point"}
}