{
  "type": "Feature",
  "properties": {
    "addr:full":"Kasteelstraat 39 Kortenberg Vlaams-Brabant 3071",
    "addr:housenumber":"39",
    "addr:postcode":"3071",
    "addr:street":"Kasteelstraat;Vlaams-Brabant",
    "iso:country":"BE",
    "sg:address":"Kasteelstraat 39",
    "sg:city":"Kortenberg",
    "sg:orig_category":"Meubelzaken, woning- and keukeninrichting",
    "sg:phone":"+32 2 759 80 21",
    "sg:postcode":"3071",
    "sg:province":"Vlaams-Brabant",
    "wof:name":"Jeca",
    "wof:placetype":"venue"
},
  "geometry": {"coordinates":[4.5679278374,50.9060707092],"type":"Point"}
}