{
  "type": "Feature",
  "properties": {
    "addr:full":"Rumstsestraat 6 Rumst (reet) Antwerpen 2840",
    "addr:housenumber":"6",
    "addr:postcode":"2840",
    "addr:street":"Rumstsestraat",
    "iso:country":"BE",
    "sg:address":"Rumstsestraat 6",
    "sg:city":"Rumst (reet)",
    "sg:classifiers":[
        {
            "category":"Retail",
            "subcategory":"Veterinary Services",
            "type":"Services"
        }
    ],
    "sg:phone":"+32 3 844 16 16",
    "sg:postcode":"2840",
    "sg:province":"Antwerpen",
    "sg:tags":[
        "veterinarian"
    ],
    "wof:name":"Vanherberghen D",
    "wof:placetype":"venue"
},
  "geometry": {"coordinates":[4.4227218628,51.0800132751],"type":"Point"}
}