{
  "type": "Feature",
  "properties": {
    "addr:full":"Pamelse Klei 16 Roosdaal Vlaams-Brabant 1760",
    "addr:housenumber":"16",
    "addr:postcode":"1760",
    "addr:street":"Klei",
    "iso:country":"BE",
    "sg:address":"Pamelse Klei 16",
    "sg:city":"Roosdaal",
    "sg:classifiers":[
        {
            "category":"Shopping",
            "subcategory":"Computers & Home Electronics",
            "type":"Retail Goods"
        }
    ],
    "sg:phone":"+32 54 32 13 50",
    "sg:postcode":"1760",
    "sg:province":"Vlaams-Brabant",
    "sg:tags":[
        "-",
        "television",
        "radio"
    ],
    "wof:name":"Pletinckx Electro",
    "wof:placetype":"venue"
},
  "geometry": {"coordinates":[4.0744271278,50.8435707092],"type":"Point"}
}