{
  "type": "Feature",
  "properties": {
    "iso:country":"BE",
    "sg:address":"Chauss\u00e9e De Dinant 154",
    "sg:city":"Profondeville",
    "sg:classifiers":[
        {
            "category":"Food & Beverages",
            "subcategory":"Groceries & Convenience Stores",
            "type":"Retail Goods"
        }
    ],
    "sg:phone":"+32 81 41 11 49",
    "sg:postcode":"5170",
    "sg:province":"Namur",
    "sg:tags":[
        "grocer"
    ],
    "wof:name":"Epicerie Du Burnot (l')",
    "wof:placetype":"venue"
},
  "geometry": {"coordinates":[4.8700947762,50.3611068726],"type":"Point"}
}