{
  "type": "Feature",
  "properties": {
    "addr:full":"Avenue John Kennedy 32bb/2 Rixensart Brabant Wallon 1330",
    "addr:housenumber":"32bb / 2",
    "addr:postcode":"1330",
    "addr:street":"Avenue John Kennedy;Wallon",
    "iso:country":"BE",
    "sg:address":"Avenue John Kennedy 32bb/2",
    "sg:city":"Rixensart",
    "sg:orig_category":"V\u00e9hicules automobiles",
    "sg:phone":"+32 2 653 36 33",
    "sg:postcode":"1330",
    "sg:province":"Brabant Wallon",
    "wof:name":"Philippe Brahy",
    "wof:placetype":"venue"
},
  "geometry": {"coordinates":[4.5229330063,50.7060317993],"type":"Point"}
}