{
  "type": "Feature",
  "properties": {
    "addr:full":"Place Saint-s\u00c9bastien 54 Braine-l'alleud Brabant Wallon 1420",
    "addr:housenumber":"54",
    "addr:postcode":"1420",
    "addr:street":"Place Saint-Se\u0301Bastien",
    "iso:country":"BE",
    "sg:address":"Place Saint-s\u00c9bastien 54",
    "sg:city":"Braine-l'alleud",
    "sg:orig_category":"Postkantoren Verzekeringsmakelaars and experts",
    "sg:phone":"+32 2 384 39 69",
    "sg:postcode":"1420",
    "sg:province":"Brabant Wallon",
    "wof:name":"La Poste",
    "wof:placetype":"venue"
},
  "geometry": {"coordinates":[1.6028620005,46.3833007812],"type":"Point"}
}