{
  "type": "Feature",
  "properties": {
    "iso:country":"BE",
    "sg:address":"Jacob Jordaensstraat 71",
    "sg:city":"Antwerpen",
    "sg:classifiers":[
        {
            "category":"Cafe",
            "type":"Food & Drink"
        }
    ],
    "sg:phone":"+32 3 239 01 74",
    "sg:postcode":"2018",
    "sg:province":"Antwerpen",
    "sg:tags":[
        "snack-bars"
    ],
    "wof:name":"Marnic",
    "wof:placetype":"venue"
},
  "geometry": {"coordinates":[4.4144668579,51.2087135315],"type":"Point"}
}