{
  "type": "Feature",
  "properties": {
    "iso:country":"BE",
    "sg:address":"Grand'rue 11",
    "sg:city":"Walcourt",
    "sg:orig_category":"Foto-uitrusting Fotografen and fotostudio's",
    "sg:phone":"+32 71 21 56 13",
    "sg:postcode":"5651",
    "sg:province":"Namur",
    "wof:name":"J.m. Antoine",
    "wof:placetype":"venue"
},
  "geometry": {"coordinates":[4.4332799911,50.2857818604],"type":"Point"}
}