{
  "type": "Feature",
  "properties": {
    "iso:country":"BE",
    "sg:address":"Square De La Libert\u00e9 6",
    "sg:city":"Tubize",
    "sg:classifiers":[
        {
            "category":"Personal",
            "subcategory":"Barber",
            "type":"Services"
        }
    ],
    "sg:phone":"+32 2 355 71 02",
    "sg:postcode":"1480",
    "sg:province":"Brabant Wallon",
    "sg:tags":[
        "gentleman",
        "salon",
        "-",
        "hairdressing"
    ],
    "wof:name":"Sprl Coiffure Crea Sprl",
    "wof:placetype":"venue"
},
  "geometry": {"coordinates":[4.1986050606,50.6879997253],"type":"Point"}
}