{
  "type": "Feature",
  "properties": {
    "addr:full":"Oostmoer 155 Waarschoot Oost-Vlaanderen 9950",
    "addr:housenumber":"155",
    "addr:postcode":"9950",
    "addr:street":"Oostmoer",
    "iso:country":"BE",
    "sg:address":"Oostmoer 155",
    "sg:city":"Waarschoot",
    "sg:classifiers":[
        {
            "category":"Building & Trades",
            "subcategory":"Construction",
            "type":"Services"
        }
    ],
    "sg:phone":"+32 9 377 89 60",
    "sg:postcode":"9950",
    "sg:province":"Oost-Vlaanderen",
    "sg:tags":[
        "installation",
        "-",
        "central",
        "heating"
    ],
    "wof:name":"Criel M",
    "wof:placetype":"venue"
},
  "geometry": {"coordinates":[3.6307170391,51.1599121094],"type":"Point"}
}