{
  "type": "Feature",
  "properties": {
    "addr:full":"Elisabethlaan 352 Oostende West-Vlaanderen 8400",
    "addr:housenumber":"352",
    "addr:postcode":"8400",
    "addr:street":"Elisabethlaan",
    "iso:country":"BE",
    "sg:address":"Elisabethlaan 352",
    "sg:city":"Oostende",
    "sg:orig_category":"M\u00e9decins and sp\u00e9cialistes",
    "sg:phone":"+32 59 70 55 19",
    "sg:postcode":"8400",
    "sg:province":"West-Vlaanderen",
    "wof:name":"Guy Steen",
    "wof:placetype":"venue"
},
  "geometry": {"coordinates":[2.9089388847,51.2147331238],"type":"Point"}
}