{
  "type": "Feature",
  "properties": {
    "iso:country":"BE",
    "sg:address":"Waterloolaan 65",
    "sg:city":"Brussel/bruxelles",
    "sg:orig_category":"Bagage and lederwaren Dameskledingzaken Schoenen",
    "sg:phone":"+32 2 512 52 06",
    "sg:postcode":"1000",
    "sg:province":"Bruxelles-Capitale",
    "wof:name":"Maison Marasti",
    "wof:placetype":"venue"
},
  "geometry": {"coordinates":[4.3552417755,50.8360786438],"type":"Point"}
}