{
  "type": "Feature",
  "properties": {
    "addr:full":"Avenue Marie De Hongrie 60 Ganshoren Bruxelles-Capitale 1083",
    "addr:housenumber":"60",
    "addr:postcode":"1083",
    "addr:street":"Avenue Marie De Hongrie",
    "iso:country":"BE",
    "sg:address":"Avenue Marie De Hongrie 60",
    "sg:city":"Ganshoren",
    "sg:orig_category":"Enseignement maternel and primaire",
    "sg:phone":"+32 2 465 14 65",
    "sg:postcode":"1083",
    "sg:province":"Bruxelles-Capitale",
    "wof:name":"Ecole Fondamentale",
    "wof:placetype":"venue"
},
  "geometry": {"coordinates":[4.3041191101,50.8722381592],"type":"Point"}
}