{
  "type": "Feature",
  "properties": {
    "addr:full":"Linterpoortenlaan 132 Zemst Vlaams-Brabant 1980",
    "addr:housenumber":"132",
    "addr:postcode":"1980",
    "addr:street":"Linterpoortenlaan;Vlaams-Brabant",
    "iso:country":"BE",
    "sg:address":"Linterpoortenlaan 132",
    "sg:city":"Zemst",
    "sg:orig_category":"Assistances juridiques. Conseillers fiscaux",
    "sg:phone":"+32 15 61 30 81",
    "sg:postcode":"1980",
    "sg:province":"Vlaams-Brabant",
    "wof:name":"Stefaan Vanhoegaerden",
    "wof:placetype":"venue"
},
  "geometry": {"coordinates":[4.4459218979,50.9796333313],"type":"Point"}
}