{
  "type": "Feature",
  "properties": {
    "addr:full":"Lerestraat 2 Tongeren Limburg 3700",
    "addr:housenumber":"2",
    "addr:postcode":"3700",
    "addr:street":"Lerestraat",
    "iso:country":"BE",
    "sg:address":"Lerestraat 2",
    "sg:city":"Tongeren",
    "sg:classifiers":[
        {
            "category":"Restaurant",
            "type":"Food & Drink"
        }
    ],
    "sg:phone":"+32 12 23 91 86",
    "sg:postcode":"3700",
    "sg:province":"Limburg",
    "wof:name":"\u00b4t Repenhof",
    "wof:placetype":"venue"
},
  "geometry": {"coordinates":[5.4636240005,50.7807197571],"type":"Point"}
}