{
  "type": "Feature",
  "properties": {
    "addr:full":"Ronsaerdbekestraat 82 Brugge West-Vlaanderen 8000",
    "addr:housenumber":"82",
    "addr:postcode":"8000",
    "addr:street":"Ronsaerdbekestraat",
    "iso:country":"BE",
    "sg:address":"Ronsaerdbekestraat 82",
    "sg:city":"Brugge",
    "sg:orig_category":"Opticiens",
    "sg:phone":"+32 50 34 53 36",
    "sg:postcode":"8000",
    "sg:province":"West-Vlaanderen",
    "wof:name":"Optiek Acke",
    "wof:placetype":"venue"
},
  "geometry": {"coordinates":[3.2328429222,51.2249755859],"type":"Point"}
}