{
  "type": "Feature",
  "properties": {
    "iso:country":"BE",
    "sg:address":"Avenue Albert Jonnart 79",
    "sg:city":"Sint-lambrechts-woluwe/woluwe-saint-lambert",
    "sg:orig_category":"Architectes. Administration d'immeubles",
    "sg:phone":"+32 2 734 18 48",
    "sg:postcode":"1200",
    "sg:province":"Bruxelles-Capitale",
    "wof:name":"Philippe Colpaert",
    "wof:placetype":"venue"
},
  "geometry": {"coordinates":[4.4020991325,50.8428421021],"type":"Point"}
}