{
  "type": "Feature",
  "properties": {
    "iso:country":"BE",
    "sg:address":"Rue G\u00c9n\u00c9ral De Gaulle 274",
    "sg:city":"Courcelles",
    "sg:orig_category":"Afbraak- and draineerwerken",
    "sg:phone":"+32 71 45 86 21",
    "sg:postcode":"6180",
    "sg:province":"Hainaut",
    "wof:name":"De Meyer",
    "wof:placetype":"venue"
},
  "geometry": {"coordinates":[4.3824458122,50.4520187378],"type":"Point"}
}