{
  "type": "Feature",
  "properties": {
    "addr:full":"Rue Du Ruisseau 172 Wezembeek-oppem/wezembeek-oppem Vlaams-Brabant 1970",
    "addr:housenumber":"172",
    "addr:postcode":"1970",
    "addr:street":"Rue Du Ruisseau",
    "iso:country":"BE",
    "sg:address":"Rue Du Ruisseau 172",
    "sg:city":"Wezembeek-oppem/wezembeek-oppem",
    "sg:orig_category":"Salles de conf\u00e9rences and de r\u00e9ceptions. Salles de spectacles",
    "sg:phone":"+32 2 731 43 31",
    "sg:postcode":"1970",
    "sg:province":"Vlaams-Brabant",
    "wof:name":"Cultureel Centrum De Kam",
    "wof:placetype":"venue"
},
  "geometry": {"coordinates":[4.4915127754,50.8514060974],"type":"Point"}
}