{
  "type": "Feature",
  "properties": {
    "iso:country":"BE",
    "sg:address":"Penelopelaan 24",
    "sg:city":"Forest",
    "sg:orig_category":"Belastingconsulenten Diverse juridische dienstverlening",
    "sg:phone":"+32 2 344 64 24",
    "sg:postcode":"1190",
    "sg:province":"Bruxelles-Capitale",
    "wof:name":"Euro P.m.e. Consult",
    "wof:placetype":"venue"
},
  "geometry": {"coordinates":[4.3334188461,50.8127670288],"type":"Point"}
}