{
  "type": "Feature",
  "properties": {
    "iso:country":"BE",
    "sg:address":"Rue Gendebien 56",
    "sg:city":"Ch\u00e2telet (ch\u00e2telineau)",
    "sg:classifiers":[
        {
            "category":"Professional",
            "subcategory":"Lawyer & Legal Services",
            "type":"Services"
        }
    ],
    "sg:phone":"+32 71 24 31 00",
    "sg:postcode":"6200",
    "sg:province":"Hainaut",
    "wof:name":"Beia K",
    "wof:placetype":"venue"
},
  "geometry": {"coordinates":[4.5229701996,50.4163093567],"type":"Point"}
}