{
  "type": "Feature",
  "properties": {
    "iso:country":"BE",
    "sg:address":"G. Gezellestraat 19",
    "sg:city":"Staden",
    "sg:orig_category":"Banken and kredietinstellingen",
    "sg:phone":"+32 51 21 08 94",
    "sg:postcode":"8840",
    "sg:province":"West-Vlaanderen",
    "wof:name":"Anhyp",
    "wof:placetype":"venue"
},
  "geometry": {"coordinates":[3.0591819286,50.9393424988],"type":"Point"}
}