{
  "type": "Feature",
  "properties": {
    "iso:country":"BE",
    "sg:address":"Route Des Forges 3",
    "sg:city":"Saint-hubert (arville)",
    "sg:classifiers":[
        {
            "category":"Travel",
            "subcategory":"Resort",
            "type":"Entertainment"
        }
    ],
    "sg:phone":"+32 61 61 14 33",
    "sg:postcode":"6870",
    "sg:province":"Luxembourg",
    "sg:tags":[
        "vacation"
    ],
    "wof:name":"Vacances Vivantes Les Forges",
    "wof:placetype":"venue"
},
  "geometry": {"coordinates":[5.3177161217,50.0181045532],"type":"Point"}
}