{
  "type": "Feature",
  "properties": {
    "iso:country":"BE",
    "sg:address":"Rue G. Gibon 10",
    "sg:city":"Sint-pieters-leeuw",
    "sg:classifiers":[
        {
            "category":"Shopping",
            "subcategory":"Clothing, Apparel, & Fashions",
            "type":"Retail Goods"
        }
    ],
    "sg:phone":"+32 2 377 87 26",
    "sg:postcode":"1600",
    "sg:province":"Vlaams-Brabant",
    "sg:tags":[
        "v\u00eatements",
        "pour",
        "dame"
    ],
    "wof:name":"Huis Tentation",
    "wof:placetype":"venue"
},
  "geometry": {"coordinates":[4.2842001915,50.8047294617],"type":"Point"}
}