{
  "type": "Feature",
  "properties": {
    "addr:full":"Schoorbakkestraat 61 Diksmuide West-Vlaanderen 8600",
    "addr:housenumber":"61",
    "addr:postcode":"8600",
    "addr:street":"Schoorbakkestraat",
    "iso:country":"BE",
    "sg:address":"Schoorbakkestraat 61",
    "sg:city":"Diksmuide",
    "sg:orig_category":"Eleveurs de bovins. Eleveurs and marchands de porcs",
    "sg:phone":"+32 51 55 53 66",
    "sg:postcode":"8600",
    "sg:province":"West-Vlaanderen",
    "wof:name":"Lucien Kimpe",
    "wof:placetype":"venue"
},
  "geometry": {"coordinates":[2.8657801151,51.0334663391],"type":"Point"}
}