{
  "type": "Feature",
  "properties": {
    "addr:full":"Gerdingerstraat 13 Bree Limburg 3960",
    "addr:housenumber":"13",
    "addr:postcode":"3960",
    "addr:street":"Gerdingerstraat",
    "iso:country":"BE",
    "sg:address":"Gerdingerstraat 13",
    "sg:city":"Bree",
    "sg:orig_category":"Opticiens",
    "sg:phone":"+32 89 46 75 40",
    "sg:postcode":"3960",
    "sg:province":"Limburg",
    "wof:name":"Optiek Leurs",
    "wof:placetype":"venue"
},
  "geometry": {"coordinates":[5.5955181122,51.141708374],"type":"Point"}
}