{
  "type": "Feature",
  "properties": {
    "addr:full":"Rue Du Vivier 6 Marche-en-famenne Luxembourg 6900",
    "addr:housenumber":"6",
    "addr:postcode":"6900",
    "addr:street":"Rue Du Vivier",
    "iso:country":"BE",
    "sg:address":"Rue Du Vivier 6",
    "sg:city":"Marche-en-famenne",
    "sg:orig_category":"Jeux and jouets. Articles pour b\u00e9b\u00e9s. V\u00eatements pour b\u00e9b\u00e9s and enfants",
    "sg:phone":"+32 843211968",
    "sg:postcode":"6900",
    "sg:province":"Luxembourg",
    "wof:name":"Maison Frimousse",
    "wof:placetype":"venue"
},
  "geometry": {"coordinates":[5.3279361725,50.2292137146],"type":"Point"}
}