{
  "type": "Feature",
  "properties": {
    "addr:full":"Kezelberg 52 Wevelgem West-Vlaanderen 8560",
    "addr:housenumber":"52",
    "addr:postcode":"8560",
    "addr:street":"Kezelberg",
    "iso:country":"BE",
    "sg:address":"Kezelberg 52",
    "sg:city":"Wevelgem",
    "sg:classifiers":[
        {
            "category":"Autos & Motor Vehicles",
            "subcategory":"Fuel & Gas Station",
            "type":"Retail Goods"
        }
    ],
    "sg:phone":"+32 56 50 02 66",
    "sg:postcode":"8560",
    "sg:province":"West-Vlaanderen",
    "sg:tags":[
        "stations-service",
        "carburants"
    ],
    "wof:name":"Christiane Dumont",
    "wof:placetype":"venue"
},
  "geometry": {"coordinates":[3.1137828827,50.8376502991],"type":"Point"}
}