{
  "type": "Feature",
  "properties": {
    "iso:country":"BE",
    "sg:address":"Avenue Wilmart 8",
    "sg:city":"Perwez",
    "sg:classifiers":[
        {
            "category":"Bars & Pubs",
            "type":"Food & Drink"
        }
    ],
    "sg:phone":"+32 81 65 82 46",
    "sg:postcode":"1360",
    "sg:province":"Brabant Wallon",
    "wof:name":"Cafe De L'avenue",
    "wof:placetype":"venue"
},
  "geometry": {"coordinates":[4.8156151772,50.6243896484],"type":"Point"}
}