{
  "type": "Feature",
  "properties": {
    "iso:country":"BE",
    "sg:address":"Waubrechts 18",
    "sg:city":"Kuurne",
    "sg:orig_category":"Artsen and specialisten",
    "sg:phone":"+32 56 35 57 77",
    "sg:postcode":"8520",
    "sg:province":"West-Vlaanderen",
    "wof:name":"Els Dufraimont",
    "wof:placetype":"venue"
},
  "geometry": {"coordinates":[3.2434799671,50.8711357117],"type":"Point"}
}