{
  "type": "Feature",
  "properties": {
    "addr:full":"Place Des Carabiniers 7 Bruxelles (schaerbeek) Bruxelles-Capitale 1030",
    "addr:housenumber":"7",
    "addr:postcode":"1030",
    "addr:street":"Place Des Carabiniers",
    "iso:country":"BE",
    "sg:address":"Place Des Carabiniers 7",
    "sg:city":"Bruxelles (schaerbeek)",
    "sg:classifiers":[
        {
            "category":"Communications",
            "subcategory":"Film & Video Production",
            "type":"Services"
        }
    ],
    "sg:phone":"+32 2 745 04 35",
    "sg:postcode":"1030",
    "sg:province":"Bruxelles-Capitale",
    "sg:tags":[
        "sound",
        "recording",
        "studio"
    ],
    "wof:name":"Twins",
    "wof:placetype":"venue"
},
  "geometry": {"coordinates":[4.4000911713,50.8539199829],"type":"Point"}
}