{
  "type": "Feature",
  "properties": {
    "iso:country":"BE",
    "sg:address":"Leenstraat 5",
    "sg:city":"Nazareth",
    "sg:orig_category":"Mat\u00e9riel \u00e9lectrique and \u00e9lectronique Gr",
    "sg:phone":"+32 9 384 79 92",
    "sg:postcode":"9810",
    "sg:province":"Oost-Vlaanderen",
    "wof:name":"Schrack Energietechnik",
    "wof:placetype":"venue"
},
  "geometry": {"coordinates":[3.6225650311,50.9302482605],"type":"Point"}
}