{
  "type": "Feature",
  "properties": {
    "addr:full":"Rue Des Ecoles 16 Verviers Li\u00e8ge 4800",
    "addr:housenumber":"16",
    "addr:postcode":"4800",
    "addr:street":"Rue Des Ecoles",
    "iso:country":"BE",
    "sg:address":"Rue Des Ecoles 16",
    "sg:city":"Verviers",
    "sg:orig_category":"Grands magasins",
    "sg:phone":"+32 87 22 83 63",
    "sg:postcode":"4800",
    "sg:province":"Li\u00e8ge",
    "wof:name":"Guy Goflette",
    "wof:placetype":"venue"
},
  "geometry": {"coordinates":[5.8645272255,50.5903625488],"type":"Point"}
}