{
  "type": "Feature",
  "properties": {
    "addr:full":"Renier Sniedersstraat 95-97 Turnhout Antwerpen 2300",
    "addr:postcode":"95-97;2300",
    "addr:street":"Renier Sniedersstraat",
    "iso:country":"BE",
    "sg:address":"Renier Sniedersstraat 95-97",
    "sg:city":"Turnhout",
    "sg:classifiers":[
        {
            "category":"Recreation",
            "subcategory":"Fishing",
            "type":"Entertainment"
        }
    ],
    "sg:phone":"+32 14 43 94 66",
    "sg:postcode":"2300",
    "sg:province":"Antwerpen",
    "sg:tags":[
        "tackle"
    ],
    "wof:name":"Fish-mix",
    "wof:placetype":"venue"
},
  "geometry": {"coordinates":[4.9394659996,51.3245735168],"type":"Point"}
}