{
  "type": "Feature",
  "properties": {
    "addr:full":"Beersebaan 55 Rijkevorsel Antwerpen 2310",
    "addr:housenumber":"55",
    "addr:postcode":"2310",
    "addr:street":"Beersebaan",
    "iso:country":"BE",
    "sg:address":"Beersebaan 55",
    "sg:city":"Rijkevorsel",
    "sg:classifiers":[
        {
            "category":"Freight",
            "type":"Transportation"
        }
    ],
    "sg:phone":"+32 3 314 83 14",
    "sg:postcode":"2310",
    "sg:province":"Antwerpen",
    "sg:tags":[
        "-",
        "transport"
    ],
    "wof:name":"I.a.b. Nv",
    "wof:placetype":"venue"
},
  "geometry": {"coordinates":[4.7811059952,51.3423080444],"type":"Point"}
}