{
  "type": "Feature",
  "properties": {
    "iso:country":"BE",
    "sg:address":"Rodenrijt 112",
    "sg:city":"Hamont-achel (achel)",
    "sg:classifiers":[
        {
            "category":"Home & Garden",
            "subcategory":"Carpets & Floor Coverings",
            "type":"Retail Goods"
        }
    ],
    "sg:phone":"+32 11 64 91 78",
    "sg:postcode":"3930",
    "sg:province":"Limburg",
    "sg:tags":[
        "layer",
        "mosaicists"
    ],
    "wof:name":"De Vloerder Bvba",
    "wof:placetype":"venue"
},
  "geometry": {"coordinates":[5.4698081017,51.2716407776],"type":"Point"}
}