{
  "type": "Feature",
  "properties": {
    "iso:country":"BE",
    "sg:address":"Maststraat 14",
    "sg:city":"Essen",
    "sg:orig_category":"Promoteurs immobiliers. Construction de maisons",
    "sg:phone":"+32 3 667 10 67",
    "sg:postcode":"2910",
    "sg:province":"Antwerpen",
    "wof:name":"Tradipartners",
    "wof:placetype":"venue"
},
  "geometry": {"coordinates":[4.4436788559,51.4547386169],"type":"Point"}
}