{
  "type": "Feature",
  "properties": {
    "addr:full":"Place Communale 15 Pont-a-celles Hainaut 6230",
    "addr:housenumber":"15",
    "addr:postcode":"6230",
    "addr:street":"Place Communale",
    "iso:country":"BE",
    "sg:address":"Place Communale 15",
    "sg:city":"Pont-a-celles",
    "sg:orig_category":"Pharmaciens",
    "sg:phone":"+32 71 84 32 40",
    "sg:postcode":"6230",
    "sg:province":"Hainaut",
    "wof:name":"Anny-claire Joassin",
    "wof:placetype":"venue"
},
  "geometry": {"coordinates":[4.3615498543,50.5119285583],"type":"Point"}
}