{
  "type": "Feature",
  "properties": {
    "addr:full":"Rue Neuf Moulin 10 Andenne (seilles) Namur 5300",
    "addr:housenumber":"10",
    "addr:postcode":"5300",
    "addr:street":"Rue Neuf Moulin",
    "iso:country":"BE",
    "sg:address":"Rue Neuf Moulin 10",
    "sg:city":"Andenne (seilles)",
    "sg:classifiers":[
        {
            "category":"Food & Beverages",
            "subcategory":"Fruits & Vegetables",
            "type":"Retail Goods"
        }
    ],
    "sg:phone":"+32 84 31 23 06",
    "sg:postcode":"5300",
    "sg:province":"Namur",
    "sg:tags":[
        "-"
    ],
    "wof:name":"Fruiland",
    "wof:placetype":"venue"
},
  "geometry": {"coordinates":[5.1124610901,50.494228363],"type":"Point"}
}