{
  "type": "Feature",
  "properties": {
    "iso:country":"BE",
    "sg:address":"Mechelsesteenweg 2",
    "sg:city":"Sint-katelijne-waver",
    "sg:orig_category":"Landbouwmachines Gh Onderdelen and accessoires voertuigen Gh",
    "sg:phone":"+32 15 31 11 55",
    "sg:postcode":"2860",
    "sg:province":"Antwerpen",
    "wof:name":"Trakat",
    "wof:placetype":"venue"
},
  "geometry": {"coordinates":[4.5356698036,51.0669136047],"type":"Point"}
}