{
  "type": "Feature",
  "properties": {
    "addr:full":"Rue De Vezonchaux 12 Antoing (maubray) Hainaut 7640",
    "addr:housenumber":"12",
    "addr:postcode":"7640",
    "addr:street":"Rue De Vezonchaux",
    "iso:country":"BE",
    "sg:address":"Rue De Vezonchaux 12",
    "sg:city":"Antoing (maubray)",
    "sg:classifiers":[
        {
            "category":"Professional",
            "subcategory":"Detective & Security Services",
            "type":"Services"
        }
    ],
    "sg:phone":"+32 69 44 17 30",
    "sg:postcode":"7640",
    "sg:province":"Hainaut",
    "sg:tags":[
        "guard"
    ],
    "wof:name":"Sng-services De Gardiennage",
    "wof:placetype":"venue"
},
  "geometry": {"coordinates":[3.4741289616,50.5510520935],"type":"Point"}
}