{
  "type": "Feature",
  "properties": {
    "addr:full":"Staatsbaan 165 Zulte Oost-Vlaanderen 9870",
    "addr:housenumber":"165",
    "addr:postcode":"9870",
    "addr:street":"Staatsbaan",
    "iso:country":"BE",
    "sg:address":"Staatsbaan 165",
    "sg:city":"Zulte",
    "sg:classifiers":[
        {
            "category":"Insurance",
            "subcategory":"Life Insurance",
            "type":"Services"
        }
    ],
    "sg:phone":"+32 9 388 95 55",
    "sg:postcode":"9870",
    "sg:province":"Oost-Vlaanderen",
    "sg:tags":[
        "assurance"
    ],
    "wof:name":"Kantoor R. Vanhoutte",
    "wof:placetype":"venue"
},
  "geometry": {"coordinates":[3.4424660206,50.9207687378],"type":"Point"}
}