{
  "type": "Feature",
  "properties": {
    "iso:country":"BE",
    "sg:address":"Stockmansstraat 5",
    "sg:city":"Antwerpen",
    "sg:classifiers":[
        {
            "category":"Bars & Pubs",
            "type":"Food & Drink"
        }
    ],
    "sg:phone":"+32 3 248 37 28",
    "sg:postcode":"2018",
    "sg:province":"Antwerpen",
    "wof:name":"In 't Ongelijk",
    "wof:placetype":"venue"
},
  "geometry": {"coordinates":[4.4047551155,51.2089042664],"type":"Point"}
}