{
  "type": "Feature",
  "properties": {
    "iso:country":"BE",
    "sg:address":"Beursstraat 36",
    "sg:city":"Brussel/bruxelles",
    "sg:orig_category":"Warenhuizen",
    "sg:phone":"+32 2 502 74 93",
    "sg:postcode":"1000",
    "sg:province":"Bruxelles-Capitale",
    "wof:name":"Bonanza",
    "wof:placetype":"venue"
},
  "geometry": {"coordinates":[4.3509411812,50.8481941223],"type":"Point"}
}