{
  "type": "Feature",
  "properties": {
    "iso:country":"BE",
    "sg:address":"Halsesteenweg 40",
    "sg:city":"Ninove",
    "sg:orig_category":"Imprimeries and copyshops",
    "sg:phone":"+32 54 33 25 20",
    "sg:postcode":"9402",
    "sg:province":"Oost-Vlaanderen",
    "wof:name":"A.b.c.",
    "wof:placetype":"venue"
},
  "geometry": {"coordinates":[4.0395750999,50.8249015808],"type":"Point"}
}