{
  "type": "Feature",
  "properties": {
    "addr:full":"Heestertstraat 29 Avelgem (outrijve) West-Vlaanderen 8582",
    "addr:housenumber":"29",
    "addr:postcode":"8582",
    "addr:street":"Heestertstraat",
    "iso:country":"BE",
    "sg:address":"Heestertstraat 29",
    "sg:city":"Avelgem (outrijve)",
    "sg:classifiers":[
        {
            "category":"Professional",
            "type":"Services"
        }
    ],
    "sg:phone":"+32 56 64 76 77",
    "sg:postcode":"8582",
    "sg:province":"West-Vlaanderen",
    "sg:tags":[
        "ceremony",
        "master"
    ],
    "wof:name":"De Keyser Eddy",
    "wof:placetype":"venue"
},
  "geometry": {"coordinates":[3.4272499084,50.7575492859],"type":"Point"}
}