{
  "type": "Feature",
  "properties": {
    "iso:country":"BE",
    "sg:address":"Watertorenstraat 11",
    "sg:city":"Tongeren",
    "sg:classifiers":[
        {
            "category":"Health Services",
            "subcategory":"Health Practitioner",
            "type":"Services"
        }
    ],
    "sg:phone":"+32 12 26 13 37",
    "sg:postcode":"3700",
    "sg:province":"Limburg",
    "sg:tags":[
        "physiotherapist"
    ],
    "wof:name":"Meyers Peter",
    "wof:placetype":"venue"
},
  "geometry": {"coordinates":[5.459359169,50.7810630798],"type":"Point"}
}