{
  "type": "Feature",
  "properties": {
    "addr:full":"Nieuwpoortstraat 28 Veurne West-Vlaanderen 8630",
    "addr:housenumber":"28",
    "addr:postcode":"8630",
    "addr:street":"Nieuwpoortstraat",
    "iso:country":"BE",
    "sg:address":"Nieuwpoortstraat 28",
    "sg:city":"Veurne",
    "sg:orig_category":"Entretien and r\u00e9parations de voitures",
    "sg:phone":"+32 58 31 12 43",
    "sg:postcode":"8630",
    "sg:province":"West-Vlaanderen",
    "wof:name":"Garage Veurne Auto",
    "wof:placetype":"venue"
},
  "geometry": {"coordinates":[2.6648499966,51.0723114014],"type":"Point"}
}