{
  "type": "Feature",
  "properties": {
    "addr:full":"Veurnseweg 146 Ieper West-Vlaanderen 8900",
    "addr:housenumber":"146",
    "addr:postcode":"8900",
    "addr:street":"Veurnseweg",
    "iso:country":"BE",
    "sg:address":"Veurnseweg 146",
    "sg:city":"Ieper",
    "sg:orig_category":"Eleveurs and marchands de porcs. Eleveurs de bovins",
    "sg:phone":"+32 57 42 22 77",
    "sg:postcode":"8900",
    "sg:province":"West-Vlaanderen",
    "wof:name":"Luc Parret",
    "wof:placetype":"venue"
},
  "geometry": {"coordinates":[2.8440198898,50.8708496094],"type":"Point"}
}