{
  "type": "Feature",
  "properties": {
    "iso:country":"BE",
    "sg:address":"Astridplein 36",
    "sg:city":"Grobbendonk",
    "sg:classifiers":[
        {
            "category":"Shopping",
            "subcategory":"Clothing, Apparel, & Fashions",
            "type":"Retail Goods"
        }
    ],
    "sg:phone":"+32 14 50 18 94",
    "sg:postcode":"2280",
    "sg:province":"Antwerpen",
    "sg:tags":[
        "-",
        "haberdashery"
    ],
    "wof:name":"Katrien (naaimode)",
    "wof:placetype":"venue"
},
  "geometry": {"coordinates":[4.7395200729,51.1921081543],"type":"Point"}
}