{
  "type": "Feature",
  "properties": {
    "iso:country":"BE",
    "sg:address":"Stationstraat 56",
    "sg:city":"Essen",
    "sg:orig_category":"Etalage- and showroomontwerpers Verlichting and huishoudartikelen",
    "sg:phone":"+32 3 677 09 49",
    "sg:postcode":"2910",
    "sg:province":"Antwerpen",
    "wof:name":"De Gondel",
    "wof:placetype":"venue"
},
  "geometry": {"coordinates":[4.4642782211,51.4662628174],"type":"Point"}
}