{
  "type": "Feature",
  "properties": {
    "iso:country":"BE",
    "sg:address":"Beho 81",
    "sg:city":"Gouvy",
    "sg:orig_category":"Eleveurs de bovins",
    "sg:phone":"+32 80 51 71 05",
    "sg:postcode":"6672",
    "sg:province":"Luxembourg",
    "wof:name":"Jacques Schmitz",
    "wof:placetype":"venue"
},
  "geometry": {"coordinates":[5.9929800034,50.2188682556],"type":"Point"}
}