{
  "type": "Feature",
  "properties": {
    "addr:full":"Maaseikerbaan 147 Genk (waterschei) Limburg 3600",
    "addr:housenumber":"147",
    "addr:postcode":"3600",
    "addr:street":"Maaseikerbaan",
    "iso:country":"BE",
    "sg:address":"Maaseikerbaan 147",
    "sg:city":"Genk (waterschei)",
    "sg:classifiers":[
        {
            "category":"Shopping",
            "subcategory":"Bicycles & Sporting Goods",
            "type":"Retail Goods"
        }
    ],
    "sg:phone":"+32 89 65 78 47",
    "sg:postcode":"3600",
    "sg:province":"Limburg",
    "sg:tags":[
        "-"
    ],
    "wof:name":"Du Bois Fietsenhandel",
    "wof:placetype":"venue"
},
  "geometry": {"coordinates":[5.551897049,50.9940910339],"type":"Point"}
}