{
  "type": "Feature",
  "properties": {
    "iso:country":"BE",
    "sg:address":"Handelslei 12",
    "sg:city":"Zoersel (groot)",
    "sg:classifiers":[
        {
            "category":"Food & Beverages",
            "subcategory":"Fruits & Vegetables",
            "type":"Retail Goods"
        }
    ],
    "sg:phone":"+32 3 385 18 04",
    "sg:postcode":"2980",
    "sg:province":"Antwerpen",
    "sg:tags":[
        "groenten"
    ],
    "wof:name":"Vawi",
    "wof:placetype":"venue"
},
  "geometry": {"coordinates":[4.6484470367,51.2730941772],"type":"Point"}
}