{
  "type": "Feature",
  "properties": {
    "addr:full":"Rue Van Soust 309 Bruxelles (anderlecht) Bruxelles-Capitale 1070",
    "addr:housenumber":"309",
    "addr:postcode":"1070",
    "addr:street":"Rue Van Soust",
    "iso:country":"BE",
    "sg:address":"Rue Van Soust 309",
    "sg:city":"Bruxelles (anderlecht)",
    "sg:classifiers":[
        {
            "category":"Home & Garden",
            "subcategory":"Building Materials",
            "type":"Retail Goods"
        }
    ],
    "sg:phone":"+32 2 522 14 02",
    "sg:postcode":"1070",
    "sg:province":"Bruxelles-Capitale",
    "sg:tags":[
        "window"
    ],
    "wof:name":"Atelier Ferin Sc",
    "wof:placetype":"venue"
},
  "geometry": {"coordinates":[4.3003029823,50.8464050293],"type":"Point"}
}