{
  "type": "Feature",
  "properties": {
    "iso:country":"BE",
    "sg:address":"Schijfstraat 34",
    "sg:city":"Brussel/bruxelles",
    "sg:orig_category":"Diverse organisaties and verenigingen",
    "sg:phone":"+32 2 478 79 81",
    "sg:postcode":"1020",
    "sg:province":"Bruxelles-Capitale",
    "wof:name":"Jeugdhuis De Branding",
    "wof:placetype":"venue"
},
  "geometry": {"coordinates":[4.3285040855,50.8942985535],"type":"Point"}
}