{
  "type": "Feature",
  "properties": {
    "addr:full":"Molenstraat 10 Eeklo Oost-Vlaanderen 9900",
    "addr:housenumber":"10",
    "addr:postcode":"9900",
    "addr:street":"Molenstraat",
    "iso:country":"BE",
    "sg:address":"Molenstraat 10",
    "sg:city":"Eeklo",
    "sg:orig_category":"Articles pour b\u00e9b\u00e9s. V\u00eatements pour b\u00e9b\u00e9s and enfants. V\u00eatements pour Dames",
    "sg:phone":"+32 9 378 00 80",
    "sg:postcode":"9900",
    "sg:province":"Oost-Vlaanderen",
    "wof:name":"Pr\u00c9maman",
    "wof:placetype":"venue"
},
  "geometry": {"coordinates":[3.5638859272,51.1856117249],"type":"Point"}
}