{
  "type": "Feature",
  "properties": {
    "addr:full":"Chauss\u00c9e De Louvain 1081 Namur Namur 5022",
    "addr:postcode":"1081;5022",
    "addr:street":"Chausse\u0301E De Louvain",
    "iso:country":"BE",
    "sg:address":"Chauss\u00c9e De Louvain 1081",
    "sg:city":"Namur",
    "sg:orig_category":"R\u00e9parations d'appareils \u00e9lectrom\u00e9nagers. Electrom\u00e9nager, t\u00e9l\u00e9visions and radios",
    "sg:phone":"+32 81 51 01 51",
    "sg:postcode":"5022",
    "sg:province":"Namur",
    "wof:name":"Kirby-ki System",
    "wof:placetype":"venue"
},
  "geometry": {"coordinates":[4.902985096,50.513671875],"type":"Point"}
}