{
  "type": "Feature",
  "properties": {
    "addr:full":"Oude Bruggestraat 76 Wingene West-Vlaanderen 8750",
    "addr:housenumber":"76",
    "addr:postcode":"8750",
    "addr:street":"Oude Bruggestraat",
    "iso:country":"BE",
    "sg:address":"Oude Bruggestraat 76",
    "sg:city":"Wingene",
    "sg:classifiers":[
        {
            "category":"Professional",
            "subcategory":"Printing & Photocopies",
            "type":"Services"
        }
    ],
    "sg:phone":"+32 51 65 67 18",
    "sg:postcode":"8750",
    "sg:province":"West-Vlaanderen",
    "sg:tags":[
        "engraving"
    ],
    "wof:name":"Coopman-cannoot W & R",
    "wof:placetype":"venue"
},
  "geometry": {"coordinates":[3.2708859444,51.0577316284],"type":"Point"}
}