{
  "type": "Feature",
  "properties": {
    "iso:country":"BE",
    "sg:address":"Rue De Saint-remy 28",
    "sg:city":"Vise",
    "sg:orig_category":"Boucheries",
    "sg:phone":"+32 4 387 45 33",
    "sg:postcode":"4601",
    "sg:province":"Li\u00e8ge",
    "wof:name":"Boucherie Demonceau",
    "wof:placetype":"venue"
},
  "geometry": {"coordinates":[5.6970801353,50.6938323975],"type":"Point"}
}