{
  "type": "Feature",
  "properties": {
    "addr:full":"Kaulillerdorp 19 Bocholt Limburg 3950",
    "addr:housenumber":"19",
    "addr:postcode":"3950",
    "addr:street":"Kaulillerdorp",
    "iso:country":"BE",
    "sg:address":"Kaulillerdorp 19",
    "sg:city":"Bocholt",
    "sg:orig_category":"Banques and organismes de cr\u00e9dit",
    "sg:phone":"+32 11 44 12 62",
    "sg:postcode":"3950",
    "sg:province":"Limburg",
    "wof:name":"Fortis",
    "wof:placetype":"venue"
},
  "geometry": {"coordinates":[5.5164999962,51.1901779175],"type":"Point"}
}