{
  "type": "Feature",
  "properties": {
    "addr:full":"268 Ronsesestraat 9660 Brakel 268",
    "addr:housenumber":"268",
    "addr:postcode":"9660;268",
    "addr:street":"Ronsesestraat",
    "iso:country":"BE",
    "sg:address":"268",
    "sg:city":"Ronsesestraat 9660 Brakel",
    "sg:classifiers":[
        {
            "category":"Shopping",
            "subcategory":"Clothing, Apparel, & Fashions",
            "type":"Retail Goods"
        }
    ],
    "sg:phone":"+32 55 42 30 13",
    "sg:postcode":"268",
    "sg:tags":[
        "textile",
        "clothing",
        "clothes"
    ],
    "wof:name":"Confectiebedrijf Ternoot Bvba",
    "wof:placetype":"venue"
},
  "geometry": {"coordinates":[3.7561590672,50.7970352173],"type":"Point"}
}