{
  "type": "Feature",
  "properties": {
    "addr:full":"Avenue Ars\u00c8ne Tournay 2 Villers-la-ville Brabant Wallon 1495",
    "addr:housenumber":"2",
    "addr:postcode":"1495",
    "addr:street":"Avenue Arse\u0300Ne Tournay",
    "iso:country":"BE",
    "sg:address":"Avenue Ars\u00c8ne Tournay 2",
    "sg:city":"Villers-la-ville",
    "sg:orig_category":"V\u00e9hicules automobiles. Entretien and r\u00e9parations de voitures",
    "sg:phone":"+32 71 87 71 49",
    "sg:postcode":"1495",
    "sg:province":"Brabant Wallon",
    "wof:name":"Labar Automobile",
    "wof:placetype":"venue"
},
  "geometry": {"coordinates":[4.5307297707,50.5781402588],"type":"Point"}
}