{
  "type": "Feature",
  "properties": {
    "addr:full":"Kortenhoekstraat 16 Aalst (hofstade) Oost-Vlaanderen 9308",
    "addr:housenumber":"16",
    "addr:postcode":"9308",
    "addr:street":"Kortenhoekstraat",
    "iso:country":"BE",
    "sg:address":"Kortenhoekstraat 16",
    "sg:city":"Aalst (hofstade)",
    "sg:classifiers":[
        {
            "category":"Health Services",
            "subcategory":"Doctor",
            "type":"Services"
        }
    ],
    "sg:phone":"+32 53 21 32 14",
    "sg:postcode":"9308",
    "sg:province":"Oost-Vlaanderen",
    "sg:tags":[
        "medicinephysicians",
        "surgeon"
    ],
    "wof:name":"Corbey R",
    "wof:placetype":"venue"
},
  "geometry": {"coordinates":[4.0347590446,50.9603500366],"type":"Point"}
}