{
  "type": "Feature",
  "properties": {
    "addr:full":"Schuttersstraat 18 Herentals Antwerpen 2200",
    "addr:housenumber":"18",
    "addr:postcode":"2200",
    "addr:street":"Schuttersstraat",
    "iso:country":"BE",
    "sg:address":"Schuttersstraat 18",
    "sg:city":"Herentals",
    "sg:orig_category":"Plomberie, chauffage and installations sanitaires",
    "sg:phone":"+32 14 21 55 98",
    "sg:postcode":"2200",
    "sg:province":"Antwerpen",
    "wof:name":"Jacques Kinnaer",
    "wof:placetype":"venue"
},
  "geometry": {"coordinates":[4.8545980453,51.1797180176],"type":"Point"}
}