{
  "type": "Feature",
  "properties": {
    "addr:full":"Moerestraat 6 Koekelare West-Vlaanderen 8680",
    "addr:housenumber":"6",
    "addr:postcode":"8680",
    "addr:street":"Moerestraat",
    "iso:country":"BE",
    "sg:address":"Moerestraat 6",
    "sg:city":"Koekelare",
    "sg:classifiers":[
        {
            "category":"Health Services",
            "subcategory":"Doctor",
            "type":"Services"
        }
    ],
    "sg:phone":"+32 51 58 80 17",
    "sg:postcode":"8680",
    "sg:province":"West-Vlaanderen",
    "sg:tags":[
        "medicinephysicians",
        "surgeon"
    ],
    "wof:name":"De Vlieger Andr\u00e9",
    "wof:placetype":"venue"
},
  "geometry": {"coordinates":[2.9792098999,51.0919113159],"type":"Point"}
}