{
  "type": "Feature",
  "properties": {
    "addr:full":"Oostmalsesteenweg 90b Ranst (emblem) Antwerpen 2520",
    "addr:housenumber":"90b",
    "addr:postcode":"2520",
    "addr:street":"Oostmalsesteenweg",
    "iso:country":"BE",
    "sg:address":"Oostmalsesteenweg 90b",
    "sg:city":"Ranst (emblem)",
    "sg:classifiers":[
        {
            "category":"Professional",
            "subcategory":"Engineering",
            "type":"Services"
        }
    ],
    "sg:phone":"+32 3 489 13 94",
    "sg:postcode":"2520",
    "sg:province":"Antwerpen",
    "sg:tags":[
        "precision"
    ],
    "wof:name":"Serneels R",
    "wof:placetype":"venue"
},
  "geometry": {"coordinates":[4.6203689575,51.1703071594],"type":"Point"}
}