{
  "type": "Feature",
  "properties": {
    "addr:full":"Rue Emile Dury 240 Waterloo Brabant Wallon 1410",
    "addr:housenumber":"240",
    "addr:postcode":"1410",
    "addr:street":"Rue Emile Dury",
    "iso:country":"BE",
    "sg:address":"Rue Emile Dury 240",
    "sg:city":"Waterloo",
    "sg:orig_category":"Instituts de beaut\u00e9",
    "sg:phone":"+32 2 354 41 23",
    "sg:postcode":"1410",
    "sg:province":"Brabant Wallon",
    "wof:name":"Collin Astrid",
    "wof:placetype":"venue"
},
  "geometry": {"coordinates":[4.3773541451,50.7057037354],"type":"Point"}
}