{
  "type": "Feature",
  "properties": {
    "iso:country":"BE",
    "sg:address":"Route De L'etat 22",
    "sg:city":"Wanze",
    "sg:classifiers":[
        {
            "category":"Sports & Exercise",
            "subcategory":"Sports Center",
            "type":"Entertainment"
        }
    ],
    "sg:phone":"+32 85 71 29 41",
    "sg:postcode":"4520",
    "sg:province":"Li\u00e8ge",
    "sg:tags":[
        "installation",
        "sportifs",
        "club",
        "de",
        "terrain",
        "hors",
        "caf\u00e9s"
    ],
    "wof:name":"Huccorgne Sports",
    "wof:placetype":"venue"
},
  "geometry": {"coordinates":[5.1680908203,50.5675849915],"type":"Point"}
}