{
  "type": "Feature",
  "properties": {
    "addr:full":"Molenstraat 41 Galmaarden Vlaams-Brabant 1570",
    "addr:housenumber":"41",
    "addr:postcode":"1570",
    "addr:street":"Molenstraat",
    "iso:country":"BE",
    "sg:address":"Molenstraat 41",
    "sg:city":"Galmaarden",
    "sg:orig_category":"Installation \u00e9lectrique r\u00e9sidentielle",
    "sg:phone":"+32 54 56 84 95",
    "sg:postcode":"1570",
    "sg:province":"Vlaams-Brabant",
    "wof:name":"Patrick Van Belle",
    "wof:placetype":"venue"
},
  "geometry": {"coordinates":[4.026679039,50.7672157288],"type":"Point"}
}