{
  "type": "Feature",
  "properties": {
    "addr:full":"Odiliastraat 2 Borgloon (kerniel) Limburg 3840",
    "addr:housenumber":"2",
    "addr:postcode":"3840",
    "addr:street":"Odiliastraat",
    "iso:country":"BE",
    "sg:address":"Odiliastraat 2",
    "sg:city":"Borgloon (kerniel)",
    "sg:classifiers":[
        {
            "category":"Farming",
            "subcategory":"Crops",
            "type":"Manufacturing & Wholesale Goods"
        }
    ],
    "sg:phone":"+32 12 74 49 60",
    "sg:postcode":"3840",
    "sg:province":"Limburg",
    "sg:tags":[
        "vegetable",
        "fruit",
        "-",
        "grower"
    ],
    "wof:name":"Pexters G",
    "wof:placetype":"venue"
},
  "geometry": {"coordinates":[5.3441700935,50.8012466431],"type":"Point"}
}