{
  "type": "Feature",
  "properties": {
    "iso:country":"BE",
    "sg:address":"Boulevard De Smet De Naeyer 484",
    "sg:city":"Bruxelles (jette)",
    "sg:classifiers":[
        {
            "category":"Personal",
            "subcategory":"Beauty Salon",
            "type":"Services"
        }
    ],
    "sg:phone":"+32 2 479 39 63",
    "sg:postcode":"1090",
    "sg:province":"Bruxelles-Capitale",
    "sg:tags":[
        "child",
        "-",
        "hairdressing"
    ],
    "wof:name":"Atelier M & F",
    "wof:placetype":"venue"
},
  "geometry": {"coordinates":[4.3373699188,50.8838310242],"type":"Point"}
}