{
  "type": "Feature",
  "properties": {
    "iso:country":"BE",
    "sg:address":"Houtmarkt 18",
    "sg:city":"Aalst",
    "sg:orig_category":"Pain, p\u00e2tisseries and confiseries",
    "sg:phone":"+32 53 78 70 92",
    "sg:postcode":"9300",
    "sg:province":"Oost-Vlaanderen",
    "wof:name":"Patisserie Baillius",
    "wof:placetype":"venue"
},
  "geometry": {"coordinates":[4.0436248779,50.9341163635],"type":"Point"}
}