{
  "type": "Feature",
  "properties": {
    "addr:full":"Diestsestraat 205 Leuven Vlaams-Brabant 3000",
    "addr:housenumber":"205",
    "addr:postcode":"3000",
    "addr:street":"Diestsestraat",
    "iso:country":"BE",
    "sg:address":"Diestsestraat 205",
    "sg:city":"Leuven",
    "sg:classifiers":[
        {
            "category":"Shopping",
            "subcategory":"Bicycles & Sporting Goods",
            "type":"Retail Goods"
        }
    ],
    "sg:phone":"+32 16 22 12 20",
    "sg:postcode":"3000",
    "sg:province":"Vlaams-Brabant",
    "sg:tags":[
        "-"
    ],
    "wof:name":"Boydens Bvba (huis) Bvba",
    "wof:placetype":"venue"
},
  "geometry": {"coordinates":[4.7106699944,50.8817024231],"type":"Point"}
}