{
  "type": "Feature",
  "properties": {
    "addr:full":"Rue Des Capucins 34 Ciney Namur 5590",
    "addr:housenumber":"34",
    "addr:postcode":"5590",
    "addr:street":"Rue Des Capucins",
    "iso:country":"BE",
    "sg:address":"Rue Des Capucins 34",
    "sg:city":"Ciney",
    "sg:classifiers":[
        {
            "category":"Health Services",
            "subcategory":"Health Practitioner",
            "type":"Services"
        }
    ],
    "sg:phone":"+32 83 21 39 86",
    "sg:postcode":"5590",
    "sg:province":"Namur",
    "sg:tags":[
        "physiotherapist"
    ],
    "wof:name":"Chamberlan St\u00e9phan",
    "wof:placetype":"venue"
},
  "geometry": {"coordinates":[5.0933828354,50.2903251648],"type":"Point"}
}