{
  "type": "Feature",
  "properties": {
    "addr:full":"Rue Du Press\u00e9 22 Binche (leval-trahegnies) Hainaut 7134",
    "addr:housenumber":"22",
    "addr:postcode":"7134",
    "addr:street":"Rue Du Presse\u0301",
    "iso:country":"BE",
    "sg:address":"Rue Du Press\u00e9 22",
    "sg:city":"Binche (leval-trahegnies)",
    "sg:classifiers":[
        {
            "category":"Health Services",
            "subcategory":"Doctor",
            "type":"Services"
        }
    ],
    "sg:phone":"+32 64 33 33 33",
    "sg:postcode":"7134",
    "sg:province":"Hainaut",
    "sg:tags":[
        "medicinephysicians",
        "surgeon"
    ],
    "wof:name":"Cerf",
    "wof:placetype":"venue"
},
  "geometry": {"coordinates":[4.2192788124,50.4161834717],"type":"Point"}
}