{
  "type": "Feature",
  "properties": {
    "addr:full":"Sint-pieterskaai 69 Brugge West-Vlaanderen 8000",
    "addr:housenumber":"69",
    "addr:postcode":"8000",
    "addr:street":"Sint-Pieterskaai",
    "iso:country":"BE",
    "sg:address":"Sint-pieterskaai 69",
    "sg:city":"Brugge",
    "sg:classifiers":[
        {
            "category":"Communications",
            "subcategory":"Film & Video Production",
            "type":"Services"
        }
    ],
    "sg:phone":"+32 50 33 79 09",
    "sg:postcode":"8000",
    "sg:province":"West-Vlaanderen",
    "sg:tags":[
        "hiring",
        "-"
    ],
    "wof:name":"Erotic Megastore",
    "wof:placetype":"venue"
},
  "geometry": {"coordinates":[3.2235720158,51.22265625],"type":"Point"}
}