{
  "type": "Feature",
  "properties": {
    "iso:country":"BE",
    "sg:address":"Kaaistraat 63",
    "sg:city":"Roeselare",
    "sg:classifiers":[
        {
            "category":"Utilities",
            "subcategory":"Fuel Oil & Lpg",
            "type":"Services"
        }
    ],
    "sg:phone":"+32 51 20 88 09",
    "sg:postcode":"8800",
    "sg:province":"West-Vlaanderen",
    "wof:name":"Pillen Roland & Zn",
    "wof:placetype":"venue"
},
  "geometry": {"coordinates":[3.1453630924,50.9435348511],"type":"Point"}
}