{
  "type": "Feature",
  "properties": {
    "addr:full":"Stationsstraat 30-201 Mechelen Antwerpen 2800",
    "addr:housenumber":"30-201",
    "addr:postcode":"2800",
    "addr:street":"Stationsstraat",
    "iso:country":"BE",
    "sg:address":"Stationsstraat 30-201",
    "sg:city":"Mechelen",
    "sg:classifiers":[
        {
            "category":"Professional",
            "subcategory":"Art Services",
            "type":"Services"
        }
    ],
    "sg:phone":"+32 15 41 80 05",
    "sg:postcode":"2800",
    "sg:province":"Antwerpen",
    "sg:tags":[
        "-",
        "painter",
        "artist"
    ],
    "wof:name":"Van Eeckhout W",
    "wof:placetype":"venue"
},
  "geometry": {"coordinates":[4.4844880104,51.0198249817],"type":"Point"}
}