{
  "type": "Feature",
  "properties": {
    "addr:full":"Roggelaan 8 Lier Antwerpen 2500",
    "addr:housenumber":"8",
    "addr:postcode":"2500",
    "addr:street":"Roggelaan",
    "iso:country":"BE",
    "sg:address":"Roggelaan 8",
    "sg:city":"Lier",
    "sg:orig_category":"Experts-comptables",
    "sg:phone":"+32 3 422 58 64",
    "sg:postcode":"2500",
    "sg:province":"Antwerpen",
    "wof:name":"Luc Van Dessel",
    "wof:placetype":"venue"
},
  "geometry": {"coordinates":[4.6143980026,51.0888328552],"type":"Point"}
}