{
  "type": "Feature",
  "properties": {
    "addr:full":"Neerveld 10 Kontich Antwerpen 2550",
    "addr:housenumber":"10",
    "addr:postcode":"2550",
    "addr:street":"Neerveld",
    "iso:country":"BE",
    "sg:address":"Neerveld 10",
    "sg:city":"Kontich",
    "sg:classifiers":[
        {
            "category":"Building & Trades",
            "subcategory":"Plumbing",
            "type":"Services"
        }
    ],
    "sg:phone":"+32 3 450 88 66",
    "sg:postcode":"2550",
    "sg:province":"Antwerpen",
    "sg:tags":[
        "contractor"
    ],
    "wof:name":"A. Van Den Bosch Bvba",
    "wof:placetype":"venue"
},
  "geometry": {"coordinates":[4.4528889656,51.1209526062],"type":"Point"}
}