{
  "type": "Feature",
  "properties": {
    "addr:full":"Valkenstraat 7 Londerzeel Vlaams-Brabant 1840",
    "addr:housenumber":"7",
    "addr:postcode":"1840",
    "addr:street":"Valkenstraat",
    "iso:country":"BE",
    "sg:address":"Valkenstraat 7",
    "sg:city":"Londerzeel",
    "sg:classifiers":[
        {
            "category":"Industrial Area",
            "type":"Public Place"
        }
    ],
    "sg:phone":"+32 477 27 18 25",
    "sg:postcode":"1840",
    "sg:province":"Vlaams-Brabant",
    "sg:tags":[
        "centrifugals"
    ],
    "wof:name":"Tema Bv Nv",
    "wof:placetype":"venue"
},
  "geometry": {"coordinates":[4.3004431725,51.0118408203],"type":"Point"}
}