{
  "type": "Feature",
  "properties": {
    "iso:country":"BE",
    "sg:address":"Astridlaan 181",
    "sg:city":"Overpelt",
    "sg:orig_category":"Pain, p\u00e2tisseries and confiseries",
    "sg:phone":"+32 11 64 76 41",
    "sg:postcode":"3900",
    "sg:province":"Limburg",
    "wof:name":"Bakkerij Kramik",
    "wof:placetype":"venue"
},
  "geometry": {"coordinates":[5.3781290054,51.2147636414],"type":"Point"}
}