{
  "type": "Feature",
  "properties": {
    "addr:full":"Torhoutsesteenweg 95a Oostende West-Vlaanderen 8400",
    "addr:housenumber":"95a",
    "addr:postcode":"8400",
    "addr:street":"Torhoutsesteenweg",
    "iso:country":"BE",
    "sg:address":"Torhoutsesteenweg 95a",
    "sg:city":"Oostende",
    "sg:classifiers":[
        {
            "category":"Shopping",
            "subcategory":"Optician",
            "type":"Retail Goods"
        }
    ],
    "sg:phone":"+32 59 50 24 60",
    "sg:postcode":"8400",
    "sg:province":"West-Vlaanderen",
    "sg:tags":[
        "-"
    ],
    "wof:name":"Wauters G",
    "wof:placetype":"venue"
},
  "geometry": {"coordinates":[2.9085130692,51.2231178284],"type":"Point"}
}