{
  "type": "Feature",
  "properties": {
    "addr:full":"Maalderijstraat 7 Antwerpen Antwerpen 2000",
    "addr:housenumber":"7",
    "addr:postcode":"2000",
    "addr:street":"Maalderijstraat",
    "iso:country":"BE",
    "sg:address":"Maalderijstraat 7",
    "sg:city":"Antwerpen",
    "sg:classifiers":[
        {
            "category":"Bars & Pubs",
            "type":"Food & Drink"
        }
    ],
    "sg:phone":"+32 3 213 15 80",
    "sg:postcode":"2000",
    "sg:province":"Antwerpen",
    "wof:name":"Blauwmoezel",
    "wof:placetype":"venue"
},
  "geometry": {"coordinates":[4.4004940987,51.2207717896],"type":"Point"}
}