{
  "type": "Feature",
  "properties": {
    "iso:country":"BE",
    "sg:address":"Rue De La Biche 18",
    "sg:city":"Mons",
    "sg:orig_category":"Avocats and conseillers juridiques",
    "sg:phone":"+32 65 31 43 68",
    "sg:postcode":"7000",
    "sg:province":"Hainaut",
    "wof:name":"Jean-maurice Arnould",
    "wof:placetype":"venue"
},
  "geometry": {"coordinates":[3.956043005,50.4540672302],"type":"Point"}
}