{
  "type": "Feature",
  "properties": {
    "iso:country":"BE",
    "sg:address":"Rue De Hodeige 134",
    "sg:city":"Waremme (lantremange)",
    "sg:classifiers":[
        {
            "category":"Shopping",
            "subcategory":"Antiques",
            "type":"Retail Goods"
        }
    ],
    "sg:phone":"+32 19 32 50 22",
    "sg:postcode":"4300",
    "sg:province":"Li\u00e8ge",
    "wof:name":"Jori Antiquit\u00e9s",
    "wof:placetype":"venue"
},
  "geometry": {"coordinates":[5.301240921,50.7110939026],"type":"Point"}
}