{
  "type": "Feature",
  "properties": {
    "iso:country":"BE",
    "sg:address":"Guido Gezellestraat 1",
    "sg:city":"Diest",
    "sg:orig_category":"Boekhandels",
    "sg:phone":"+32 13 32 79 29",
    "sg:postcode":"3290",
    "sg:province":"Vlaams-Brabant",
    "wof:name":"Huis Ot En Sien",
    "wof:placetype":"venue"
},
  "geometry": {"coordinates":[5.0523471832,50.9843025208],"type":"Point"}
}