{
  "type": "Feature",
  "properties": {
    "iso:country":"BE",
    "sg:address":"Chauss\u00c9e De Wavre 24-28",
    "sg:city":"Hannuit",
    "sg:orig_category":"Rev\u00eatements de sols and murs. Traitement and fa\u00e7onnage de la pierre",
    "sg:phone":"+32 19 51 12 15",
    "sg:postcode":"4280",
    "sg:province":"Li\u00e8ge",
    "wof:name":"Nouvelle Taille",
    "wof:placetype":"venue"
},
  "geometry": {"coordinates":[5.0696649551,50.6689376831],"type":"Point"}
}