{
  "type": "Feature",
  "properties": {
    "addr:full":"Kempischveldweg 85 Schilde Antwerpen 2970",
    "addr:housenumber":"85",
    "addr:postcode":"2970",
    "addr:street":"Kempischveldweg",
    "iso:country":"BE",
    "sg:address":"Kempischveldweg 85",
    "sg:city":"Schilde",
    "sg:orig_category":"Paramedische behandelingen",
    "sg:phone":"+32 3 646 42 85",
    "sg:postcode":"2970",
    "sg:province":"Antwerpen",
    "wof:name":"Hilemgeer",
    "wof:placetype":"venue"
},
  "geometry": {"coordinates":[4.5869297981,51.225982666],"type":"Point"}
}