{
  "type": "Feature",
  "properties": {
    "iso:country":"BE",
    "sg:address":"Hulst 15",
    "sg:city":"Scherpenheuvel-zichem (testelt)",
    "sg:classifiers":[
        {
            "category":"Home & Garden",
            "subcategory":"Furniture",
            "type":"Retail Goods"
        }
    ],
    "sg:phone":"+32 13 77 36 02",
    "sg:postcode":"3272",
    "sg:province":"Vlaams-Brabant",
    "sg:tags":[
        "-"
    ],
    "wof:name":"D.i.lemma",
    "wof:placetype":"venue"
},
  "geometry": {"coordinates":[4.9491639137,51.0114517212],"type":"Point"}
}