{
  "type": "Feature",
  "properties": {
    "addr:full":"Grote Laakweg 21 Aarschot Vlaams-Brabant 3200",
    "addr:housenumber":"21",
    "addr:postcode":"3200",
    "addr:street":"Grote Laakweg",
    "iso:country":"BE",
    "sg:address":"Grote Laakweg 21",
    "sg:city":"Aarschot",
    "sg:classifiers":[
        {
            "category":"Insurance",
            "subcategory":"Insurance Agent",
            "type":"Services"
        }
    ],
    "sg:phone":"+32 16 57 17 87",
    "sg:postcode":"3200",
    "sg:province":"Vlaams-Brabant",
    "sg:tags":[
        "broker"
    ],
    "wof:name":"Vrancken C",
    "wof:placetype":"venue"
},
  "geometry": {"coordinates":[4.8347301483,50.9912414551],"type":"Point"}
}