{
  "type": "Feature",
  "properties": {
    "addr:full":"Avenue De Ninove 77 Rochefort (jemelle) Namur 5580",
    "addr:housenumber":"77",
    "addr:postcode":"5580",
    "addr:street":"Avenue De Ninove",
    "iso:country":"BE",
    "sg:address":"Avenue De Ninove 77",
    "sg:city":"Rochefort (jemelle)",
    "sg:classifiers":[
        {
            "category":"Community Center",
            "type":"Public Place"
        }
    ],
    "sg:phone":"+32 84 22 18 22",
    "sg:postcode":"5580",
    "sg:province":"Namur",
    "sg:tags":[
        "medical"
    ],
    "wof:name":"Planning De Rochefort",
    "wof:placetype":"venue"
},
  "geometry": {"coordinates":[5.2618618011,50.1630973816],"type":"Point"}
}