{
  "type": "Feature",
  "properties": {
    "addr:full":"Avenue Du Cimeti\u00e8re De Bruxelles 57 Bruxelles (evere) Bruxelles-Capitale 1140",
    "addr:housenumber":"57",
    "addr:postcode":"1140",
    "addr:street":"Avenue Du Cimetie\u0300Re De Bruxelles",
    "iso:country":"BE",
    "sg:address":"Avenue Du Cimeti\u00e8re De Bruxelles 57",
    "sg:city":"Bruxelles (evere)",
    "sg:classifiers":[
        {
            "category":"Building & Trades",
            "subcategory":"Pest Control",
            "type":"Services"
        }
    ],
    "sg:phone":"+32 2 726 75 83",
    "sg:postcode":"1140",
    "sg:province":"Bruxelles-Capitale",
    "sg:tags":[
        "painting",
        "contractor"
    ],
    "wof:name":"Van Meerbeeck Bvba",
    "wof:placetype":"venue"
},
  "geometry": {"coordinates":[4.4152770042,50.8607788086],"type":"Point"}
}