{
  "type": "Feature",
  "properties": {
    "addr:full":"Kapelsesteenweg 202 Brasschaat Antwerpen 2930",
    "addr:housenumber":"202",
    "addr:postcode":"2930",
    "addr:street":"Kapelsesteenweg",
    "iso:country":"BE",
    "sg:address":"Kapelsesteenweg 202",
    "sg:city":"Brasschaat",
    "sg:orig_category":"M\u00e9decins and sp\u00e9cialistes",
    "sg:phone":"+32 3 645 81 24",
    "sg:postcode":"2930",
    "sg:province":"Antwerpen",
    "wof:name":"A. Van Riet",
    "wof:placetype":"venue"
},
  "geometry": {"coordinates":[4.4533061981,51.2796516418],"type":"Point"}
}