{
  "type": "Feature",
  "properties": {
    "iso:country":"BE",
    "sg:address":"Boulevard Du Roi Albert Ii 1",
    "sg:city":"Bruxelles (saint-josse-ten-noode)",
    "sg:classifiers":[
        {
            "category":"Banks & Credit Unions",
            "subcategory":"Financial Services",
            "type":"Services"
        }
    ],
    "sg:phone":"+32 2 208 88 11",
    "sg:postcode":"1210",
    "sg:province":"Bruxelles-Capitale",
    "sg:tags":[
        "loan",
        "mortgage"
    ],
    "wof:name":"Jp Morgan Chase Bank",
    "wof:placetype":"venue"
},
  "geometry": {"coordinates":[4.3559098244,50.856426239],"type":"Point"}
}