{
  "type": "Feature",
  "properties": {
    "iso:country":"BE",
    "sg:address":"Rue De La Croix-rouge 44",
    "sg:city":"Tubize",
    "sg:orig_category":"M\u00e9decins and sp\u00e9cialistes",
    "sg:phone":"+32 2 355 81 84",
    "sg:postcode":"1480",
    "sg:province":"Brabant Wallon",
    "wof:name":"Andr\u00c9 Kivits",
    "wof:placetype":"venue"
},
  "geometry": {"coordinates":[4.1965479851,50.6844482422],"type":"Point"}
}