{
  "type": "Feature",
  "properties": {
    "iso:country":"BE",
    "sg:address":"Rue De La Maladrerie 24",
    "sg:city":"Bouillon",
    "sg:classifiers":[
        {
            "category":"Home & Garden",
            "subcategory":"Carpets & Floor Coverings",
            "type":"Retail Goods"
        }
    ],
    "sg:phone":"+32 61 46 61 90",
    "sg:postcode":"6830",
    "sg:province":"Luxembourg",
    "sg:tags":[
        "carpeting"
    ],
    "wof:name":"Collignon Guy S.p.r.l.",
    "wof:placetype":"venue"
},
  "geometry": {"coordinates":[5.0709600449,49.7951507568],"type":"Point"}
}