{
  "type": "Feature",
  "properties": {
    "iso:country":"BE",
    "sg:address":"Rue Du Foss\u00c9 Aux Loups 47",
    "sg:city":"Brussel/bruxelles",
    "sg:classifiers":[
        {
            "category":"Restaurant",
            "type":"Food & Drink"
        }
    ],
    "sg:phone":"+32 2 227 31 20",
    "sg:postcode":"1000",
    "sg:province":"Bruxelles-Capitale",
    "wof:name":"H\u00d4tel Radisson S.a.s.-sea Grill Le Divellec",
    "wof:placetype":"venue"
},
  "geometry": {"coordinates":[4.3562831879,50.8496437073],"type":"Point"}
}