{
  "type": "Feature",
  "properties": {
    "addr:full":"Preulegem 60 Ninove Oost-Vlaanderen 9400",
    "addr:housenumber":"60",
    "addr:postcode":"9400",
    "addr:street":"Preulegem",
    "iso:country":"BE",
    "sg:address":"Preulegem 60",
    "sg:city":"Ninove",
    "sg:classifiers":[
        {
            "category":"Restaurant",
            "type":"Food & Drink"
        }
    ],
    "sg:phone":"+32 54 33 12 90",
    "sg:postcode":"9400",
    "sg:province":"Oost-Vlaanderen",
    "wof:name":"Ijssalon Julienne",
    "wof:placetype":"venue"
},
  "geometry": {"coordinates":[4.0112929344,50.8364524841],"type":"Point"}
}