{
  "type": "Feature",
  "properties": {
    "addr:full":"Wittemolenstraat 44 Gent Oost-Vlaanderen 9040",
    "addr:housenumber":"44",
    "addr:postcode":"9040",
    "addr:street":"Wittemolenstraat;Oost-Vlaanderen",
    "iso:country":"BE",
    "sg:address":"Wittemolenstraat 44",
    "sg:city":"Gent",
    "sg:orig_category":"Pleisterwerk",
    "sg:phone":"+32 9 228 69 18",
    "sg:postcode":"9040",
    "sg:province":"Oost-Vlaanderen",
    "wof:name":"Julien De Wilde",
    "wof:placetype":"venue"
},
  "geometry": {"coordinates":[3.7492029667,51.0564613342],"type":"Point"}
}