{
  "type": "Feature",
  "properties": {
    "addr:full":"Grensstraat 8 Keerbergen Vlaams-Brabant 3140",
    "addr:housenumber":"8",
    "addr:postcode":"3140",
    "addr:street":"Grensstraat",
    "iso:country":"BE",
    "sg:address":"Grensstraat 8",
    "sg:city":"Keerbergen",
    "sg:classifiers":[
        {
            "category":"Communications",
            "subcategory":"Film & Video Production",
            "type":"Services"
        }
    ],
    "sg:phone":"+32 15 52 07 48",
    "sg:postcode":"3140",
    "sg:province":"Vlaams-Brabant",
    "sg:tags":[
        "realisation",
        "-"
    ],
    "wof:name":"Broadcast Recording Bvba",
    "wof:placetype":"venue"
},
  "geometry": {"coordinates":[4.6334319115,51.016002655],"type":"Point"}
}