{
  "type": "Feature",
  "properties": {
    "iso:country":"BE",
    "sg:address":"Rue Saint-martin 13",
    "sg:city":"Fernelmont",
    "sg:orig_category":"Alimentation sp\u00e9cialis\u00e9e",
    "sg:phone":"+32 81 83 41 77",
    "sg:postcode":"5380",
    "sg:province":"Namur",
    "wof:name":"Bernard Toune",
    "wof:placetype":"venue"
},
  "geometry": {"coordinates":[4.9561657906,50.5665664673],"type":"Point"}
}