{
  "type": "Feature",
  "properties": {
    "iso:country":"BE",
    "sg:address":"Bremheidelaan 2",
    "sg:city":"Turnhout",
    "sg:classifiers":[
        {
            "category":"Shopping",
            "type":"Retail Goods"
        }
    ],
    "sg:phone":"+32 14 43 90 21",
    "sg:postcode":"2300",
    "sg:province":"Antwerpen",
    "sg:tags":[
        "metallurgy",
        "finished",
        "-",
        "metalworking",
        "metallic"
    ],
    "wof:name":"Tumag Bvba",
    "wof:placetype":"venue"
},
  "geometry": {"coordinates":[4.9190411568,51.2911872864],"type":"Point"}
}