{
  "type": "Feature",
  "properties": {
    "addr:full":"Schouwburgplein 6 Kortrijk West-Vlaanderen 8500",
    "addr:housenumber":"6",
    "addr:postcode":"8500",
    "addr:street":"Schouwburgplein",
    "iso:country":"BE",
    "sg:address":"Schouwburgplein 6",
    "sg:city":"Kortrijk",
    "sg:classifiers":[
        {
            "category":"Bars & Pubs",
            "type":"Food & Drink"
        }
    ],
    "sg:phone":"+32 56 20 23 89",
    "sg:postcode":"8500",
    "sg:province":"West-Vlaanderen",
    "wof:name":"Teaterkaffee",
    "wof:placetype":"venue"
},
  "geometry": {"coordinates":[3.2662680149,50.8256568909],"type":"Point"}
}