{
  "type": "Feature",
  "properties": {
    "addr:full":"L. Van Buekenhoudtstraat 31 Bertem (leefdaal) Vlaams-Brabant 3061",
    "addr:housenumber":"31",
    "addr:postcode":"3061",
    "addr:street":"L. Van Buekenhoudtstraat",
    "iso:country":"BE",
    "sg:address":"L. Van Buekenhoudtstraat 31",
    "sg:city":"Bertem (leefdaal)",
    "sg:classifiers":[
        {
            "category":"Utilities",
            "subcategory":"Telephone",
            "type":"Services"
        }
    ],
    "sg:phone":"+32 2 767 62 27",
    "sg:postcode":"3061",
    "sg:province":"Vlaams-Brabant",
    "sg:tags":[
        "installation"
    ],
    "wof:name":"De Vadder",
    "wof:placetype":"venue"
},
  "geometry": {"coordinates":[4.5872831345,50.8486747742],"type":"Point"}
}