{
  "type": "Feature",
  "properties": {
    "iso:country":"BE",
    "sg:address":"Stationsstraat 125",
    "sg:city":"Sint-katelijne-waver",
    "sg:orig_category":"Advocaten and juridische adviseurs",
    "sg:phone":"+32 15 31 13 21",
    "sg:postcode":"2860",
    "sg:province":"Antwerpen",
    "wof:name":"Machteld Vercruysse",
    "wof:placetype":"venue"
},
  "geometry": {"coordinates":[4.5191102028,51.0704154968],"type":"Point"}
}