{
  "type": "Feature",
  "properties": {
    "addr:full":"Prins Leopoldlei 85 Mortsel Antwerpen 2640",
    "addr:housenumber":"85",
    "addr:postcode":"2640",
    "addr:street":"Prins Leopoldlei",
    "iso:country":"BE",
    "sg:address":"Prins Leopoldlei 85",
    "sg:city":"Mortsel",
    "sg:classifiers":[
        {
            "category":"Arena",
            "subcategory":"Sports Club",
            "type":"Entertainment"
        }
    ],
    "sg:phone":"+32 3 440 21 85",
    "sg:postcode":"2640",
    "sg:province":"Antwerpen",
    "sg:tags":[
        "de"
    ],
    "wof:name":"Jigo Antwerpen",
    "wof:placetype":"venue"
},
  "geometry": {"coordinates":[4.453166008,51.1681175232],"type":"Point"}
}