{
  "type": "Feature",
  "properties": {
    "addr:full":"Guffenslaan 14 Hasselt Limburg 3500",
    "addr:housenumber":"14",
    "addr:postcode":"3500",
    "addr:street":"Guffenslaan",
    "iso:country":"BE",
    "sg:address":"Guffenslaan 14",
    "sg:city":"Hasselt",
    "sg:orig_category":"Disneyland Paris. Agences de voyages",
    "sg:phone":"+32 11 22 97 45",
    "sg:postcode":"3500",
    "sg:province":"Limburg",
    "wof:name":"Neckermann",
    "wof:placetype":"venue"
},
  "geometry": {"coordinates":[5.3377518654,50.9274291992],"type":"Point"}
}