{
  "type": "Feature",
  "properties": {
    "iso:country":"BE",
    "sg:address":"Beverlo Dorp 27-29",
    "sg:city":"Beringen (beverlo)",
    "sg:classifiers":[
        {
            "category":"Bars & Pubs",
            "type":"Food & Drink"
        }
    ],
    "sg:phone":"+32 11 34 15 13",
    "sg:postcode":"3581",
    "sg:province":"Limburg",
    "wof:name":"Stella",
    "wof:placetype":"venue"
},
  "geometry": {"coordinates":[5.2207198143,51.0878562927],"type":"Point"}
}