{
  "type": "Feature",
  "properties": {
    "addr:full":"Meulebrouckstraat 11 Moorslede West-Vlaanderen 8890",
    "addr:housenumber":"11",
    "addr:postcode":"8890",
    "addr:street":"Meulebrouckstraat",
    "iso:country":"BE",
    "sg:address":"Meulebrouckstraat 11",
    "sg:city":"Moorslede",
    "sg:orig_category":"Rundveehouders",
    "sg:phone":"+32 51 77 80 96",
    "sg:postcode":"8890",
    "sg:province":"West-Vlaanderen",
    "wof:name":"Antoon Opsomer",
    "wof:placetype":"venue"
},
  "geometry": {"coordinates":[3.0562839508,50.8768959045],"type":"Point"}
}