{
  "type": "Feature",
  "properties": {
    "iso:country":"BE",
    "sg:address":"Kattestraat 5",
    "sg:city":"Sint-gillis-waas",
    "sg:orig_category":"Goederenvervoer over de weg",
    "sg:phone":"+32 3 707 03 77",
    "sg:postcode":"9170",
    "sg:province":"Oost-Vlaanderen",
    "wof:name":"Buys Marc",
    "wof:placetype":"venue"
},
  "geometry": {"coordinates":[4.0808701515,51.2207756042],"type":"Point"}
}