{
  "type": "Feature",
  "properties": {
    "iso:country":"BE",
    "sg:address":"De Meulenaerstraat 54",
    "sg:city":"Sint-niklaas",
    "sg:classifiers":[
        {
            "category":"Health Services",
            "subcategory":"Health Practitioner",
            "type":"Services"
        }
    ],
    "sg:phone":"+32 3 766 14 22",
    "sg:postcode":"9100",
    "sg:province":"Oost-Vlaanderen",
    "sg:tags":[
        "physiotherapist"
    ],
    "wof:name":"Dehaen Dirk",
    "wof:placetype":"venue"
},
  "geometry": {"coordinates":[4.1612272263,51.1522636414],"type":"Point"}
}