{
  "type": "Feature",
  "properties": {
    "iso:country":"BE",
    "sg:address":"Messidorlaan 173",
    "sg:city":"Ukkel/uccle",
    "sg:orig_category":"Artiesten and kunstenaars",
    "sg:phone":"+32 2 345 55 97",
    "sg:postcode":"1180",
    "sg:province":"Bruxelles-Capitale",
    "wof:name":"Lavachery",
    "wof:placetype":"venue"
},
  "geometry": {"coordinates":[4.344189167,50.8100585938],"type":"Point"}
}