{
  "type": "Feature",
  "properties": {
    "addr:full":"Vilsterbron 37 Borgloon Limburg 3840",
    "addr:housenumber":"37",
    "addr:postcode":"3840",
    "addr:street":"Vilsterbron",
    "iso:country":"BE",
    "sg:address":"Vilsterbron 37",
    "sg:city":"Borgloon",
    "sg:orig_category":"Dameskledingzaken Herenkledingzaken",
    "sg:phone":"+32 12 74 31 80",
    "sg:postcode":"3840",
    "sg:province":"Limburg",
    "wof:name":"Boetiek A Propos",
    "wof:placetype":"venue"
},
  "geometry": {"coordinates":[5.3573741913,50.8027153015],"type":"Point"}
}