{
  "type": "Feature",
  "properties": {
    "addr:full":"Neustrasse 22 Eupen Li\u00e8ge 4700",
    "addr:housenumber":"22",
    "addr:postcode":"4700",
    "addr:street":"Neustrasse",
    "iso:country":"BE",
    "sg:address":"Neustrasse 22",
    "sg:city":"Eupen",
    "sg:orig_category":"Industri\u00eble wasserijen and droogkuis",
    "sg:phone":"+32 87 55 38 19",
    "sg:postcode":"4700",
    "sg:province":"Li\u00e8ge",
    "wof:name":"Vitalux",
    "wof:placetype":"venue"
},
  "geometry": {"coordinates":[6.0325088501,50.627281189],"type":"Point"}
}