{
  "type": "Feature",
  "properties": {
    "addr:full":"Vlierbeekberg 128 Overijse Vlaams-Brabant 3090",
    "addr:housenumber":"128",
    "addr:postcode":"3090",
    "addr:street":"Vlierbeekberg",
    "iso:country":"BE",
    "sg:address":"Vlierbeekberg 128",
    "sg:city":"Overijse",
    "sg:classifiers":[
        {
            "category":"Professional",
            "subcategory":"Management & Consulting",
            "type":"Services"
        }
    ],
    "sg:phone":"+32 476 52 35 96",
    "sg:postcode":"3090",
    "sg:province":"Vlaams-Brabant",
    "sg:tags":[
        "consultant"
    ],
    "wof:name":"Coufinco",
    "wof:placetype":"venue"
},
  "geometry": {"coordinates":[4.4960360527,50.7759475708],"type":"Point"}
}