{
  "type": "Feature",
  "properties": {
    "addr:full":"Rue Corneil Gomz\u00e9 20 Verviers Li\u00e8ge 4800",
    "addr:housenumber":"20",
    "addr:postcode":"4800",
    "addr:street":"Rue Corneil Gomze\u0301",
    "iso:country":"BE",
    "sg:address":"Rue Corneil Gomz\u00e9 20",
    "sg:city":"Verviers",
    "sg:classifiers":[
        {
            "category":"Banks & Credit Unions",
            "subcategory":"Investment Brokerage",
            "type":"Services"
        }
    ],
    "sg:phone":"+32 87 22 49 32",
    "sg:postcode":"4800",
    "sg:province":"Li\u00e8ge",
    "sg:tags":[
        "serigraphy",
        "machine",
        "-",
        "supply"
    ],
    "wof:name":"Mengelbier E Ets",
    "wof:placetype":"venue"
},
  "geometry": {"coordinates":[5.8704800606,50.5820732117],"type":"Point"}
}