{
  "type": "Feature",
  "properties": {
    "addr:full":"Arthur Borghijsstraat 68 Puurs Antwerpen 2870",
    "addr:housenumber":"68",
    "addr:postcode":"2870",
    "addr:street":"Borghijsstraat",
    "iso:country":"BE",
    "sg:address":"Arthur Borghijsstraat 68",
    "sg:city":"Puurs",
    "sg:orig_category":"Messageries",
    "sg:phone":"+32 3 886 69 99",
    "sg:postcode":"2870",
    "sg:province":"Antwerpen",
    "wof:name":"Guido Van Gijseghem",
    "wof:placetype":"venue"
},
  "geometry": {"coordinates":[4.3248648643,51.0773391724],"type":"Point"}
}