{
  "type": "Feature",
  "properties": {
    "iso:country":"BE",
    "sg:address":"Rue Du Village 148",
    "sg:city":"Quaregnon",
    "sg:classifiers":[
        {
            "category":"Shopping",
            "subcategory":"Jewelry",
            "type":"Retail Goods"
        }
    ],
    "sg:phone":"+32 65 78 56 88",
    "sg:postcode":"7390",
    "sg:province":"Hainaut",
    "sg:tags":[
        "jeweller",
        "-"
    ],
    "wof:name":"Odas",
    "wof:placetype":"venue"
},
  "geometry": {"coordinates":[3.8654510975,50.4413986206],"type":"Point"}
}