{
  "type": "Feature",
  "properties": {
    "addr:full":"Chauss\u00e9e De Gand 678 Bruxelles (molenbeek-saint-jean) Bruxelles-Capitale 1080",
    "addr:housenumber":"678",
    "addr:postcode":"1080",
    "addr:street":"Chausse\u0301E De Gand",
    "iso:country":"BE",
    "sg:address":"Chauss\u00e9e De Gand 678",
    "sg:city":"Bruxelles (molenbeek-saint-jean)",
    "sg:classifiers":[
        {
            "category":"Autos & Motor Vehicles",
            "subcategory":"Motorcycle Sales",
            "type":"Retail Goods"
        }
    ],
    "sg:phone":"+32 2 465 25 88",
    "sg:postcode":"1080",
    "sg:province":"Bruxelles-Capitale",
    "sg:tags":[
        "scooter",
        "-",
        "moped"
    ],
    "wof:name":"Vandenhoute Norman Etn",
    "wof:placetype":"venue"
},
  "geometry": {"coordinates":[4.3083481789,50.8596038818],"type":"Point"}
}