{
  "type": "Feature",
  "properties": {
    "iso:country":"BE",
    "sg:address":"Rue Arthur Pouplier 24",
    "sg:city":"Ecaussinnes",
    "sg:orig_category":"Begrafeniswezen Bloemen and planten",
    "sg:phone":"+32 67 44 25 11",
    "sg:postcode":"7190",
    "sg:province":"Hainaut",
    "wof:name":"Maucq R",
    "wof:placetype":"venue"
},
  "geometry": {"coordinates":[4.155069828,50.5621528625],"type":"Point"}
}