{
  "type": "Feature",
  "properties": {
    "iso:country":"BE",
    "sg:address":"Heist-goorstraat 42",
    "sg:city":"Heist-op-den-berg",
    "sg:orig_category":"Drukkerijen and copyshops",
    "sg:phone":"+32 15 22 05 69",
    "sg:postcode":"2220",
    "sg:province":"Antwerpen",
    "wof:name":"Drukkerij Marc Jacobs",
    "wof:placetype":"venue"
},
  "geometry": {"coordinates":[4.7276301384,51.0509300232],"type":"Point"}
}