{
  "type": "Feature",
  "properties": {
    "iso:country":"BE",
    "sg:address":"Groenestraat 46",
    "sg:city":"Zedelgem",
    "sg:classifiers":[
        {
            "category":"Autos & Motor Vehicles",
            "subcategory":"Fuel & Gas Station",
            "type":"Retail Goods"
        }
    ],
    "sg:phone":"+32 50 20 91 10",
    "sg:postcode":"8210",
    "sg:province":"West-Vlaanderen",
    "sg:tags":[
        "stations-service",
        "carburants"
    ],
    "wof:name":"Tankstation Fuel & Bikes",
    "wof:placetype":"venue"
},
  "geometry": {"coordinates":[3.140486002,51.1393165588],"type":"Point"}
}