{
  "type": "Feature",
  "properties": {
    "addr:full":"Rue De La Vignette 223 Bruxelles (auderghem) Bruxelles-Capitale 1160",
    "addr:housenumber":"223",
    "addr:postcode":"1160",
    "addr:street":"Rue De La Vignette",
    "iso:country":"BE",
    "sg:address":"Rue De La Vignette 223",
    "sg:city":"Bruxelles (auderghem)",
    "sg:classifiers":[
        {
            "category":"Professional",
            "subcategory":"Detective & Security Services",
            "type":"Services"
        }
    ],
    "sg:phone":"+32 2 673 58 86",
    "sg:postcode":"1160",
    "sg:province":"Bruxelles-Capitale",
    "sg:tags":[
        "guard"
    ],
    "wof:name":"Confidence Partner Security",
    "wof:placetype":"venue"
},
  "geometry": {"coordinates":[4.4171700478,50.8138122559],"type":"Point"}
}