{
  "type": "Feature",
  "properties": {
    "iso:country":"BE",
    "sg:address":"Samberstraat 42",
    "sg:city":"Antwerpen",
    "sg:orig_category":"Non-Classified Establishments",
    "sg:phone":"+32 3 226 41 60",
    "sg:postcode":"2060",
    "sg:province":"Antwerpen",
    "wof:name":"Carda Bvba",
    "wof:placetype":"venue"
},
  "geometry": {"coordinates":[4.4281711578,51.2332839966],"type":"Point"}
}