{
  "type": "Feature",
  "properties": {
    "addr:full":"Antwerpsesteenweg 526 Gent Oost-Vlaanderen 9040",
    "addr:housenumber":"526",
    "addr:postcode":"9040",
    "addr:street":"Antwerpsesteenweg;Oost-Vlaanderen",
    "iso:country":"BE",
    "sg:address":"Antwerpsesteenweg 526",
    "sg:city":"Gent",
    "sg:orig_category":"Bloemen and planten",
    "sg:phone":"+32 9 238 18 87",
    "sg:postcode":"9040",
    "sg:province":"Oost-Vlaanderen",
    "wof:name":"Huis Folial",
    "wof:placetype":"venue"
},
  "geometry": {"coordinates":[3.7526600361,51.0644760132],"type":"Point"}
}