{
  "type": "Feature",
  "properties": {
    "addr:full":"Veldstraat 41 Lochristi Oost-Vlaanderen 9080",
    "addr:housenumber":"41",
    "addr:postcode":"9080",
    "addr:street":"Veldstraat",
    "iso:country":"BE",
    "sg:address":"Veldstraat 41",
    "sg:city":"Lochristi",
    "sg:orig_category":"Bloemen and planten Gh",
    "sg:phone":"+32 9 355 02 71",
    "sg:postcode":"9080",
    "sg:province":"Oost-Vlaanderen",
    "wof:name":"De Wilde",
    "wof:placetype":"venue"
},
  "geometry": {"coordinates":[3.7999300957,51.1033287048],"type":"Point"}
}