{
  "type": "Feature",
  "properties": {
    "iso:country":"BE",
    "sg:address":"Rue De Namur 24a",
    "sg:city":"Wavre",
    "sg:classifiers":[
        {
            "category":"Home & Garden",
            "subcategory":"Building Materials",
            "type":"Retail Goods"
        }
    ],
    "sg:phone":"+32 475 98 44 12",
    "sg:postcode":"1300",
    "sg:province":"Brabant Wallon",
    "sg:tags":[
        "wall",
        "cupboard"
    ],
    "wof:name":"Bulinckx Hugues",
    "wof:placetype":"venue"
},
  "geometry": {"coordinates":[4.6118907928,50.7128143311],"type":"Point"}
}