{
  "type": "Feature",
  "properties": {
    "iso:country":"BE",
    "sg:address":"Hoenderbroekstraat 26",
    "sg:city":"Lanaken",
    "sg:classifiers":[
        {
            "category":"Communications",
            "subcategory":"Film & Video Production",
            "type":"Services"
        }
    ],
    "sg:phone":"+32 89 72 10 37",
    "sg:postcode":"3620",
    "sg:province":"Limburg",
    "sg:tags":[
        "hiring",
        "-"
    ],
    "wof:name":"Video 21",
    "wof:placetype":"venue"
},
  "geometry": {"coordinates":[5.6420331001,50.8949546814],"type":"Point"}
}