{
  "type": "Feature",
  "properties": {
    "iso:country":"BE",
    "sg:address":"Ruelle Scaffart 1",
    "sg:city":"Soignies",
    "sg:classifiers":[
        {
            "category":"Professional",
            "subcategory":"Accounting & Tax Preparation",
            "type":"Services"
        }
    ],
    "sg:phone":"+32 67 34 69 10",
    "sg:postcode":"7060",
    "sg:province":"Hainaut",
    "sg:tags":[
        "accountant"
    ],
    "wof:name":"Roland P",
    "wof:placetype":"venue"
},
  "geometry": {"coordinates":[4.0695800781,50.5796585083],"type":"Point"}
}