{
  "type": "Feature",
  "properties": {
    "addr:full":"R. Charles Radoux Rogier 4 Chaudfontaine Li\u00e8ge 4053",
    "addr:housenumber":"4",
    "addr:postcode":"4053",
    "addr:street":"R. Charles Radoux Rogier",
    "iso:country":"BE",
    "sg:address":"R. Charles Radoux Rogier 4",
    "sg:city":"Chaudfontaine",
    "sg:orig_category":"M\u00e9decins and sp\u00e9cialistes",
    "sg:phone":"+32 4 367 28 98",
    "sg:postcode":"4053",
    "sg:province":"Li\u00e8ge",
    "wof:name":"St\u00c9phan Sepulchre",
    "wof:placetype":"venue"
},
  "geometry": {"coordinates":[5.603746891,50.5942726135],"type":"Point"}
}