{
  "type": "Feature",
  "properties": {
    "iso:country":"BE",
    "sg:address":"Boterbergweg 7",
    "sg:city":"Beersel",
    "sg:orig_category":"Werk and personeelsselectie",
    "sg:phone":"+32 2 377 02 62",
    "sg:postcode":"1650",
    "sg:province":"Vlaams-Brabant",
    "wof:name":"Bureau Darcor Belgique",
    "wof:placetype":"venue"
},
  "geometry": {"coordinates":[4.3219861984,50.7716293335],"type":"Point"}
}