{
  "type": "Feature",
  "properties": {
    "addr:full":"Hoge Ieperweg 18 Houthulst West-Vlaanderen 8650",
    "addr:housenumber":"18",
    "addr:postcode":"8650",
    "addr:street":"Hoge Ieperweg",
    "iso:country":"BE",
    "sg:address":"Hoge Ieperweg 18",
    "sg:city":"Houthulst",
    "sg:classifiers":[
        {
            "category":"Food & Beverages",
            "subcategory":"Fruits & Vegetables",
            "type":"Retail Goods"
        }
    ],
    "sg:phone":"+32 51 54 41 02",
    "sg:postcode":"8650",
    "sg:province":"West-Vlaanderen",
    "sg:tags":[
        "l\u00e9gumes",
        "gr"
    ],
    "wof:name":"Lucien Decancq",
    "wof:placetype":"venue"
},
  "geometry": {"coordinates":[2.8855829239,50.9465179443],"type":"Point"}
}