{
  "type": "Feature",
  "properties": {
    "addr:full":"Molenstraat 105 Kaprijke Oost-Vlaanderen 9970",
    "addr:housenumber":"105",
    "addr:postcode":"9970",
    "addr:street":"Molenstraat",
    "iso:country":"BE",
    "sg:address":"Molenstraat 105",
    "sg:city":"Kaprijke",
    "sg:classifiers":[
        {
            "category":"Health Services",
            "subcategory":"Health Practitioner",
            "type":"Services"
        }
    ],
    "sg:phone":"+32 9 373 79 24",
    "sg:postcode":"9970",
    "sg:province":"Oost-Vlaanderen",
    "sg:tags":[
        "physiotherapist"
    ],
    "wof:name":"Wouters Rob",
    "wof:placetype":"venue"
},
  "geometry": {"coordinates":[3.6192109585,51.2262153625],"type":"Point"}
}