{
  "type": "Feature",
  "properties": {
    "addr:full":"Gosperstr 17 Eupen Li\u00e8ge 4700",
    "addr:housenumber":"17",
    "addr:postcode":"4700",
    "addr:street":"Gosperstr",
    "iso:country":"BE",
    "sg:address":"Gosperstr 17",
    "sg:city":"Eupen",
    "sg:orig_category":"Effectenmakelaars and vermogensbeheer",
    "sg:phone":"+32 87 74 06 60",
    "sg:postcode":"4700",
    "sg:province":"Li\u00e8ge",
    "wof:name":"Oost Belgieninvest",
    "wof:placetype":"venue"
},
  "geometry": {"coordinates":[6.0344820023,50.6309967041],"type":"Point"}
}