{
  "type": "Feature",
  "properties": {
    "addr:full":"Sint-maurusweg 31 Tienen Vlaams-Brabant 3300",
    "addr:housenumber":"31",
    "addr:postcode":"3300",
    "addr:street":"Sint-Maurusweg",
    "iso:country":"BE",
    "sg:address":"Sint-maurusweg 31",
    "sg:city":"Tienen",
    "sg:orig_category":"D\u00e9taillants en pi\u00e8ces and accessoires de voitures",
    "sg:phone":"+32 16 81 21 30",
    "sg:postcode":"3300",
    "sg:province":"Vlaams-Brabant",
    "wof:name":"Profile Tyrecenter Gaston",
    "wof:placetype":"venue"
},
  "geometry": {"coordinates":[4.9590010643,50.7964363098],"type":"Point"}
}