{
  "type": "Feature",
  "properties": {
    "iso:country":"BE",
    "sg:address":"Rue De La Chauss\u00e9e 70c",
    "sg:city":"Mons",
    "sg:classifiers":[
        {
            "category":"Shopping",
            "subcategory":"Stationery & Office Supplies",
            "type":"Retail Goods"
        }
    ],
    "sg:phone":"+32 65 31 12 07",
    "sg:postcode":"7000",
    "sg:province":"Hainaut",
    "wof:name":"Palette (la)",
    "wof:placetype":"venue"
},
  "geometry": {"coordinates":[3.9500100613,50.452507019],"type":"Point"}
}