{
  "type": "Feature",
  "properties": {
    "addr:full":"Werft 20 Geel Antwerpen 2440",
    "addr:housenumber":"20",
    "addr:postcode":"2440",
    "addr:street":"Werft",
    "iso:country":"BE",
    "sg:address":"Werft 20",
    "sg:city":"Geel",
    "sg:orig_category":"S\u00e9lection de personnel and placement",
    "sg:phone":"+32 14 57 09 94",
    "sg:postcode":"2440",
    "sg:province":"Antwerpen",
    "wof:name":"Pwa Geel",
    "wof:placetype":"venue"
},
  "geometry": {"coordinates":[4.9874591827,51.1616668701],"type":"Point"}
}