{
  "type": "Feature",
  "properties": {
    "iso:country":"BE",
    "sg:address":"Rue De La Poste 4",
    "sg:city":"Chastre (chastre-villeroux-blanmont)",
    "sg:classifiers":[
        {
            "category":"Community Center",
            "subcategory":"Youth",
            "type":"Public Place"
        }
    ],
    "sg:phone":"+32 10 65 93 03",
    "sg:postcode":"1450",
    "sg:province":"Brabant Wallon",
    "sg:tags":[
        "club"
    ],
    "wof:name":"Infor Jeunes",
    "wof:placetype":"venue"
},
  "geometry": {"coordinates":[4.6370530128,50.6088943481],"type":"Point"}
}