{
  "type": "Feature",
  "properties": {
    "addr:full":"Rue Fr. Jos. Peterinck 1b4 Tournai Hainaut 7500",
    "addr:housenumber":"1b4",
    "addr:postcode":"7500",
    "addr:street":"Rue Fr. Jos. Peterinck",
    "iso:country":"BE",
    "sg:address":"Rue Fr. Jos. Peterinck 1b4",
    "sg:city":"Tournai",
    "sg:orig_category":"M\u00e9decins and sp\u00e9cialistes",
    "sg:phone":"+32 69 21 25 84",
    "sg:postcode":"7500",
    "sg:province":"Hainaut",
    "wof:name":"A. Dorosev",
    "wof:placetype":"venue"
},
  "geometry": {"coordinates":[3.3829860687,50.6125526428],"type":"Point"}
}