{
  "type": "Feature",
  "properties": {
    "addr:full":"Riemsterweg 16 Bilzen (grand) Limburg 3740",
    "addr:housenumber":"16",
    "addr:postcode":"3740",
    "addr:street":"Riemsterweg",
    "iso:country":"BE",
    "sg:address":"Riemsterweg 16",
    "sg:city":"Bilzen (grand)",
    "sg:orig_category":"Schoonheidssalons",
    "sg:phone":"+32 89 51 12 22",
    "sg:postcode":"3740",
    "sg:province":"Limburg",
    "wof:name":"Fanny",
    "wof:placetype":"venue"
},
  "geometry": {"coordinates":[5.5262351036,50.8632736206],"type":"Point"}
}