{
  "type": "Feature",
  "properties": {
    "iso:country":"BE",
    "sg:address":"Naamsesteenweg 146",
    "sg:city":"Sint-truiden",
    "sg:classifiers":[
        {
            "category":"Professional",
            "subcategory":"Computer Services",
            "type":"Services"
        }
    ],
    "sg:phone":"+32 11 70 28 70",
    "sg:postcode":"3800",
    "sg:province":"Limburg",
    "sg:tags":[
        "development",
        "software"
    ],
    "wof:name":"Telesoft Nv",
    "wof:placetype":"venue"
},
  "geometry": {"coordinates":[5.1832132339,50.8105964661],"type":"Point"}
}