{
  "type": "Feature",
  "properties": {
    "addr:full":"Ridderstraat 13 Herk-de-stad Limburg 3540",
    "addr:housenumber":"13",
    "addr:postcode":"3540",
    "addr:street":"Ridderstraat",
    "iso:country":"BE",
    "sg:address":"Ridderstraat 13",
    "sg:city":"Herk-de-stad",
    "sg:classifiers":[
        {
            "category":"Shopping",
            "subcategory":"Shoes",
            "type":"Retail Goods"
        }
    ],
    "sg:phone":"+32 13 55 17 98",
    "sg:postcode":"3540",
    "sg:province":"Limburg",
    "sg:tags":[
        "slipper",
        "-"
    ],
    "wof:name":"Step By Step",
    "wof:placetype":"venue"
},
  "geometry": {"coordinates":[5.1682038307,50.940700531],"type":"Point"}
}