{
  "type": "Feature",
  "properties": {
    "iso:country":"BE",
    "sg:address":"Stormstraat 2",
    "sg:city":"Bruxelles-centre",
    "sg:orig_category":"Boekhandels Microsoft",
    "sg:phone":"+32 2 210 12 23",
    "sg:postcode":"1000",
    "sg:province":"Bruxelles-Capitale",
    "wof:name":"Standaard Boekhandel Brussel Campus",
    "wof:placetype":"venue"
},
  "geometry": {"coordinates":[4.3573021889,50.8488197327],"type":"Point"}
}