{
  "type": "Feature",
  "properties": {
    "addr:full":"Joris Helleputtestraat 2 Lommel Limburg 3920",
    "addr:housenumber":"2",
    "addr:postcode":"3920",
    "addr:street":"Joris Helleputtestraat",
    "iso:country":"BE",
    "sg:address":"Joris Helleputtestraat 2",
    "sg:city":"Lommel",
    "sg:classifiers":[
        {
            "category":"Government",
            "subcategory":"Fire Station",
            "type":"Public Place"
        }
    ],
    "sg:phone":"+32 11 54 63 45",
    "sg:postcode":"3920",
    "sg:province":"Limburg",
    "sg:tags":[
        "installation",
        "-",
        "air conditioning"
    ],
    "wof:name":"Jansen Electro Techniek Bvba",
    "wof:placetype":"venue"
},
  "geometry": {"coordinates":[5.2661738396,51.2159347534],"type":"Point"}
}