{
  "type": "Feature",
  "properties": {
    "addr:full":"Hoekestraat 29 Knesselare Oost-Vlaanderen 9910",
    "addr:housenumber":"29",
    "addr:postcode":"9910",
    "addr:street":"Hoekestraat;Oost-Vlaanderen",
    "iso:country":"BE",
    "sg:address":"Hoekestraat 29",
    "sg:city":"Knesselare",
    "sg:classifiers":[
        {
            "category":"Autos & Motor Vehicles",
            "subcategory":"Motorcycle Sales",
            "type":"Retail Goods"
        }
    ],
    "sg:postcode":"9910",
    "sg:province":"Oost-Vlaanderen",
    "sg:tags":[
        "motorbike"
    ],
    "wof:name":"S & T Harley Davidson",
    "wof:placetype":"venue"
},
  "geometry": {"coordinates":[3.4147720337,51.1342353821],"type":"Point"}
}