{
  "type": "Feature",
  "properties": {
    "addr:full":"Rue Edouard Remouchamps 2 Li\u00c8ge Li\u00e8ge 4020",
    "addr:housenumber":"2",
    "addr:postcode":"4020",
    "addr:street":"Rue Edouard Remouchamps",
    "iso:country":"BE",
    "sg:address":"Rue Edouard Remouchamps 2",
    "sg:city":"Li\u00c8ge",
    "sg:orig_category":"Cr\u00e9dit \u00e0 la consommation",
    "sg:phone":"+32 4 342 11 11",
    "sg:postcode":"4020",
    "sg:province":"Li\u00e8ge",
    "wof:name":"Cr\u00c9dit Deux Mille",
    "wof:placetype":"venue"
},
  "geometry": {"coordinates":[5.5833010674,50.6349105835],"type":"Point"}
}