{
  "type": "Feature",
  "properties": {
    "iso:country":"BE",
    "sg:address":"Plaats 5",
    "sg:city":"Menen",
    "sg:orig_category":"Elektrische installaties voor woningen",
    "sg:phone":"+32 56 42 49 39",
    "sg:postcode":"8930",
    "sg:province":"West-Vlaanderen",
    "wof:name":"P. Fabry",
    "wof:placetype":"venue"
},
  "geometry": {"coordinates":[3.1209149361,50.7961845398],"type":"Point"}
}