{
  "type": "Feature",
  "properties": {
    "addr:full":"9avenue De L'ind\u00c9pendance Belge 99 Koekelberg Bruxelles-Capitale 1081",
    "addr:housenumber":"99",
    "addr:postcode":"1081",
    "addr:street":"Belge",
    "iso:country":"BE",
    "sg:address":"9avenue De L'ind\u00c9pendance Belge 99",
    "sg:city":"Koekelberg",
    "sg:orig_category":"Computers and computerapparatuur Informaticaconsulenten Microsoft",
    "sg:phone":"+32 2 421 78 80",
    "sg:postcode":"1081",
    "sg:province":"Bruxelles-Capitale",
    "wof:name":"Tott Systems",
    "wof:placetype":"venue"
},
  "geometry": {"coordinates":[4.319270134,50.8630218506],"type":"Point"}
}