{
  "type": "Feature",
  "properties": {
    "addr:full":"Grote Markt 5 Roeselare West-Vlaanderen 8800",
    "addr:housenumber":"5",
    "addr:postcode":"8800",
    "addr:street":"Grote Markt",
    "iso:country":"BE",
    "sg:address":"Grote Markt 5",
    "sg:city":"Roeselare",
    "sg:classifiers":[
        {
            "category":"Tea Room",
            "subcategory":"None",
            "type":"Food & Drink"
        }
    ],
    "sg:phone":"+32 51 24 09 41",
    "sg:postcode":"8800",
    "sg:province":"West-Vlaanderen",
    "wof:name":"Matuvu",
    "wof:placetype":"venue"
},
  "geometry": {"coordinates":[3.1239309311,50.9446792603],"type":"Point"}
}