{
  "type": "Feature",
  "properties": {
    "addr:full":"Miksebaan 231 Brasschaat Antwerpen 2930",
    "addr:housenumber":"231",
    "addr:postcode":"2930",
    "addr:street":"Miksebaan",
    "iso:country":"BE",
    "sg:address":"Miksebaan 231",
    "sg:city":"Brasschaat",
    "sg:classifiers":[
        {
            "category":"Health Services",
            "subcategory":"Doctor",
            "type":"Services"
        }
    ],
    "sg:phone":"+32 3 651 69 64",
    "sg:postcode":"2930",
    "sg:province":"Antwerpen",
    "sg:tags":[
        "medicinephysicians",
        "surgeon"
    ],
    "wof:name":"Jacobs J",
    "wof:placetype":"venue"
},
  "geometry": {"coordinates":[4.511220932,51.2947502136],"type":"Point"}
}