{
  "type": "Feature",
  "properties": {
    "iso:country":"BE",
    "sg:address":"Minneveldstraat 44",
    "sg:city":"Kortenberg",
    "sg:classifiers":[
        {
            "category":"Manufacturing",
            "subcategory":"Tools & Machinery",
            "type":"Manufacturing & Wholesale Goods"
        }
    ],
    "sg:phone":"+32 2 759 68 14",
    "sg:postcode":"3070",
    "sg:province":"Vlaams-Brabant",
    "sg:tags":[
        "-"
    ],
    "wof:name":"Le Cygne",
    "wof:placetype":"venue"
},
  "geometry": {"coordinates":[4.5453262329,50.8867340088],"type":"Point"}
}