{
  "type": "Feature",
  "properties": {
    "iso:country":"BE",
    "sg:address":"Heikant 181",
    "sg:city":"Zele",
    "sg:orig_category":"Zuivelproducten",
    "sg:phone":"+32 52 44 81 16",
    "sg:postcode":"9240",
    "sg:province":"Oost-Vlaanderen",
    "wof:name":"Kris Van Den Abbeele",
    "wof:placetype":"venue"
},
  "geometry": {"coordinates":[3.9964549541,51.0638313293],"type":"Point"}
}