{
  "type": "Feature",
  "properties": {
    "iso:country":"BE",
    "sg:address":"De Stockheimlaan 30",
    "sg:city":"Hasselt",
    "sg:orig_category":"Installation de menuiserie en bois and plastique",
    "sg:phone":"+32 11 25 13 29",
    "sg:postcode":"3510",
    "sg:province":"Limburg",
    "wof:name":"Dullers",
    "wof:placetype":"venue"
},
  "geometry": {"coordinates":[5.2531552315,50.9474906921],"type":"Point"}
}