{
  "type": "Feature",
  "properties": {
    "addr:full":"Markt 1 Zomergem Oost-Vlaanderen 9930",
    "addr:housenumber":"1",
    "addr:postcode":"9930",
    "addr:street":"Markt",
    "iso:country":"BE",
    "sg:address":"Markt 1",
    "sg:city":"Zomergem",
    "sg:orig_category":"Overheidsdiensten",
    "sg:phone":"+32 9 370 75 70",
    "sg:postcode":"9930",
    "sg:province":"Oost-Vlaanderen",
    "wof:name":"O.c.m.w.",
    "wof:placetype":"venue"
},
  "geometry": {"coordinates":[3.5599091053,51.118144989],"type":"Point"}
}