{
  "type": "Feature",
  "properties": {
    "iso:country":"BE",
    "sg:address":"Schaapdries 19",
    "sg:city":"Lint",
    "sg:classifiers":[
        {
            "category":"Building & Trades",
            "subcategory":"Electrical",
            "type":"Services"
        }
    ],
    "sg:phone":"+32 3 288 77 97",
    "sg:postcode":"2547",
    "sg:province":"Antwerpen",
    "sg:tags":[
        "electric",
        "-",
        "housewiring",
        "contractor"
    ],
    "wof:name":"Fnc Solar",
    "wof:placetype":"venue"
},
  "geometry": {"coordinates":[4.4839038849,51.1227149963],"type":"Point"}
}