{
  "type": "Feature",
  "properties": {
    "addr:full":"Zemstsesteenweg 1 Zemst Vlaams-Brabant 1981",
    "addr:housenumber":"1",
    "addr:postcode":"1981",
    "addr:street":"Zemstsesteenweg;Vlaams-Brabant",
    "iso:country":"BE",
    "sg:address":"Zemstsesteenweg 1",
    "sg:city":"Zemst",
    "sg:orig_category":"Fabrication and montage de mobilier",
    "sg:phone":"+32 15 62 18 08",
    "sg:postcode":"1981",
    "sg:province":"Vlaams-Brabant",
    "wof:name":"Dw Interieur",
    "wof:placetype":"venue"
},
  "geometry": {"coordinates":[4.4920969009,50.991645813],"type":"Point"}
}