{
  "type": "Feature",
  "properties": {
    "iso:country":"BE",
    "sg:address":"Boulevard Du Rectorat 29",
    "sg:city":"Li\u00e8ge 1",
    "sg:classifiers":[
        {
            "category":"Manufacturing",
            "subcategory":"Chemicals & Compounds",
            "type":"Manufacturing & Wholesale Goods"
        }
    ],
    "sg:phone":"+32 4 366 39 83",
    "sg:postcode":"4000",
    "sg:province":"Li\u00e8ge",
    "sg:tags":[
        "pharmaceutical",
        "product"
    ],
    "wof:name":"Biores Laboratoires Sa",
    "wof:placetype":"venue"
},
  "geometry": {"coordinates":[5.5693669319,50.5854759216],"type":"Point"}
}