{
  "type": "Feature",
  "properties": {
    "iso:country":"BE",
    "sg:address":"Stoepestraat 21",
    "sg:city":"Assenede",
    "sg:classifiers":[
        {
            "category":"Restaurant",
            "type":"Food & Drink"
        }
    ],
    "sg:phone":"+32 9 344 32 45",
    "sg:postcode":"9960",
    "sg:province":"Oost-Vlaanderen",
    "wof:name":"Koperen Klink",
    "wof:placetype":"venue"
},
  "geometry": {"coordinates":[3.7568409443,51.1932373047],"type":"Point"}
}