{
  "type": "Feature",
  "properties": {
    "iso:country":"BE",
    "sg:address":"Bastenakkerstraat 6b6",
    "sg:city":"Destelbergen",
    "sg:orig_category":"Architecten",
    "sg:phone":"+32 9 252 27 12",
    "sg:postcode":"9070",
    "sg:province":"Oost-Vlaanderen",
    "wof:name":"Joris Vrielynck",
    "wof:placetype":"venue"
},
  "geometry": {"coordinates":[3.8289449215,50.999256134],"type":"Point"}
}