{
  "type": "Feature",
  "properties": {
    "addr:full":"Mechelseweg 333 Kapelle-op-den-bos Vlaams-Brabant 1880",
    "addr:housenumber":"333",
    "addr:postcode":"1880",
    "addr:street":"Mechelseweg",
    "iso:country":"BE",
    "sg:address":"Mechelseweg 333",
    "sg:city":"Kapelle-op-den-bos",
    "sg:classifiers":[
        {
            "category":"Food & Beverages",
            "subcategory":"Groceries & Convenience Stores",
            "type":"Retail Goods"
        }
    ],
    "sg:phone":"+32 15 71 13 89",
    "sg:postcode":"1880",
    "sg:province":"Vlaams-Brabant",
    "sg:tags":[
        "grocer"
    ],
    "wof:name":"Vallentine",
    "wof:placetype":"venue"
},
  "geometry": {"coordinates":[4.3679180145,51.0122261047],"type":"Point"}
}