{
  "type": "Feature",
  "properties": {
    "iso:country":"BE",
    "sg:address":"Voskenslaan 375",
    "sg:city":"Gent",
    "sg:classifiers":[
        {
            "category":"Real Estate",
            "subcategory":"Real Estate Services",
            "type":"Services"
        }
    ],
    "sg:phone":"+32 9 222 46 74",
    "sg:postcode":"9000",
    "sg:province":"Oost-Vlaanderen",
    "sg:tags":[
        "-",
        "abroad"
    ],
    "wof:name":"Immo Pannier",
    "wof:placetype":"venue"
},
  "geometry": {"coordinates":[3.708491087,51.0279655457],"type":"Point"}
}