{
  "type": "Feature",
  "properties": {
    "iso:country":"BE",
    "sg:address":"Fortstraat 4",
    "sg:city":"Lebbeke",
    "sg:orig_category":"Drukkerijen and copyshops",
    "sg:phone":"+32 52 41 11 05",
    "sg:postcode":"9280",
    "sg:province":"Oost-Vlaanderen",
    "wof:name":"Jan De Wolf",
    "wof:placetype":"venue"
},
  "geometry": {"coordinates":[4.1287240982,51.0086517334],"type":"Point"}
}