{
  "type": "Feature",
  "properties": {
    "iso:country":"BE",
    "sg:address":"Avenue Des Pommiers 37",
    "sg:city":"Montigny-le-tilleul",
    "sg:orig_category":"Artsen and specialisten",
    "sg:phone":"+32 71 51 05 44",
    "sg:postcode":"6110",
    "sg:province":"Hainaut",
    "wof:name":"A. Dernovoi",
    "wof:placetype":"venue"
},
  "geometry": {"coordinates":[4.3738398552,50.3720283508],"type":"Point"}
}