{
  "type": "Feature",
  "properties": {
    "addr:full":"Bohemen 101 Wichelen Oost-Vlaanderen 9260",
    "addr:housenumber":"101",
    "addr:postcode":"9260",
    "addr:street":"Bohemen",
    "iso:country":"BE",
    "sg:address":"Bohemen 101",
    "sg:city":"Wichelen",
    "sg:classifiers":[
        {
            "category":"Bars & Pubs",
            "subcategory":"Hookah Bar",
            "type":"Food & Drink"
        }
    ],
    "sg:phone":"+32 52 42 46 67",
    "sg:postcode":"9260",
    "sg:province":"Oost-Vlaanderen",
    "sg:tags":[
        "barrel",
        "reconditioning",
        "cask"
    ],
    "wof:name":"Blagden Packaging Wichelen Nv",
    "wof:placetype":"venue"
},
  "geometry": {"coordinates":[3.9922790527,51.001991272],"type":"Point"}
}