{
  "type": "Feature",
  "properties": {
    "addr:full":"Steenovenstraat 11 Tessenderlo Limburg 3980",
    "addr:housenumber":"11",
    "addr:postcode":"3980",
    "addr:street":"Steenovenstraat",
    "iso:country":"BE",
    "sg:address":"Steenovenstraat 11",
    "sg:city":"Tessenderlo",
    "sg:classifiers":[
        {
            "category":"Manufacturing",
            "subcategory":"Furniture",
            "type":"Manufacturing & Wholesale Goods"
        }
    ],
    "sg:phone":"+32 13 33 43 06",
    "sg:postcode":"3980",
    "sg:province":"Limburg",
    "sg:tags":[
        "made",
        "-",
        "custom"
    ],
    "wof:name":"Mitrasena Bvba",
    "wof:placetype":"venue"
},
  "geometry": {"coordinates":[5.0697932243,51.0221366882],"type":"Point"}
}