{
  "type": "Feature",
  "properties": {
    "iso:country":"BE",
    "sg:address":"Plaats 31",
    "sg:city":"Menen",
    "sg:classifiers":[
        {
            "category":"Manufacturing",
            "subcategory":"Textiles",
            "type":"Manufacturing & Wholesale Goods"
        }
    ],
    "sg:phone":"+32 56 41 23 72",
    "sg:postcode":"8930",
    "sg:province":"West-Vlaanderen",
    "wof:name":"Ghislaine Delrue",
    "wof:placetype":"venue"
},
  "geometry": {"coordinates":[3.1638050079,50.783870697],"type":"Point"}
}