{
  "type": "Feature",
  "properties": {
    "iso:country":"BE",
    "sg:address":"Rue N.-d.-du-mont-carmel 118",
    "sg:city":"Florennes",
    "sg:orig_category":"Rundveehouders",
    "sg:phone":"+32 71 68 81 92",
    "sg:postcode":"5620",
    "sg:province":"Namur",
    "wof:name":"Pierre Capron",
    "wof:placetype":"venue"
},
  "geometry": {"coordinates":[4.5769968033,50.2478294373],"type":"Point"}
}