{
  "type": "Feature",
  "properties": {
    "addr:full":"Rue Du Moulin 56 Li\u00e8ge 1 (bressoux) Li\u00e8ge 4020",
    "addr:housenumber":"56;1",
    "addr:postcode":"4020",
    "addr:street":"Rue Du Moulin",
    "iso:country":"BE",
    "sg:address":"Rue Du Moulin 56",
    "sg:city":"Li\u00e8ge 1 (bressoux)",
    "sg:classifiers":[
        {
            "category":"Bakery",
            "type":"Food & Drink"
        }
    ],
    "sg:phone":"+32 4 343 24 91",
    "sg:postcode":"4020",
    "sg:province":"Li\u00e8ge",
    "sg:tags":[
        "confectioner",
        "baker"
    ],
    "wof:name":"Fanchamps J",
    "wof:placetype":"venue"
},
  "geometry": {"coordinates":[5.5952529907,50.6405525208],"type":"Point"}
}