{
  "type": "Feature",
  "properties": {
    "iso:country":"BE",
    "sg:address":"Kobbestraat 32bb",
    "sg:city":"Kortrijk",
    "sg:orig_category":"Fruits and l\u00e9gumes. Fruits and l\u00e9gumes Produits \u00e0 base de pommes de terre Eleveurs de bovins",
    "sg:phone":"+32 56 41 43 13",
    "sg:postcode":"8511",
    "sg:province":"West-Vlaanderen",
    "wof:name":"Geert Margo",
    "wof:placetype":"venue"
},
  "geometry": {"coordinates":[3.208288908,50.7812080383],"type":"Point"}
}