{
  "type": "Feature",
  "properties": {
    "iso:country":"BE",
    "sg:address":"Kasteelstraat 30",
    "sg:city":"Begijnendijk",
    "sg:orig_category":"Eclairage et \u00e9quipements du foyer",
    "sg:phone":"+32 16 53 01 09",
    "sg:postcode":"3130",
    "sg:province":"Vlaams-Brabant",
    "wof:name":"Eddy Pauwels",
    "wof:placetype":"venue"
},
  "geometry": {"coordinates":[4.7859368324,51.0295333862],"type":"Point"}
}