{
  "type": "Feature",
  "properties": {
    "addr:full":"Heyaard 38 Brecht (sint-job-in-'t Goor) Antwerpen 2960",
    "addr:housenumber":"38",
    "addr:postcode":"2960",
    "addr:street":"Heyaard;' T Goor",
    "iso:country":"BE",
    "sg:address":"Heyaard 38",
    "sg:city":"Brecht (sint-job-in-'t Goor)",
    "sg:classifiers":[
        {
            "category":"Professional",
            "subcategory":"Computer Services",
            "type":"Services"
        }
    ],
    "sg:phone":"+32 3 636 04 97",
    "sg:postcode":"2960",
    "sg:province":"Antwerpen",
    "sg:tags":[
        "-",
        "processing",
        "data",
        "software"
    ],
    "wof:name":"Itech",
    "wof:placetype":"venue"
},
  "geometry": {"coordinates":[4.6415200233,51.3512115479],"type":"Point"}
}