{
  "type": "Feature",
  "properties": {
    "iso:country":"BE",
    "sg:address":"Schouwvegersstraat 15",
    "sg:city":"Antwerpen",
    "sg:classifiers":[
        {
            "category":"Wholesale",
            "subcategory":"Wine & Distilled Alcoholic Beverages",
            "type":"Manufacturing & Wholesale Goods"
        }
    ],
    "sg:phone":"+32 3 569 08 21",
    "sg:postcode":"2040",
    "sg:province":"Antwerpen",
    "sg:tags":[
        "whol",
        "-",
        "spirit",
        "mfg"
    ],
    "wof:name":"Halewijn Bvba",
    "wof:placetype":"venue"
},
  "geometry": {"coordinates":[4.3141150475,51.3429756165],"type":"Point"}
}