{
  "type": "Feature",
  "properties": {
    "iso:country":"BE",
    "sg:address":"Rue De La Procession 49",
    "sg:city":"La Hulpe",
    "sg:classifiers":[
        {
            "category":"Arena",
            "subcategory":"Sports Club",
            "type":"Entertainment"
        }
    ],
    "sg:phone":"+32 2 653 96 48",
    "sg:postcode":"1310",
    "sg:province":"Brabant Wallon",
    "sg:tags":[
        "de"
    ],
    "wof:name":"Les Marcheurs Du Hain",
    "wof:placetype":"venue"
},
  "geometry": {"coordinates":[4.494702816,50.7323036194],"type":"Point"}
}