{
  "type": "Feature",
  "properties": {
    "iso:country":"BE",
    "sg:address":"Manaihant 22",
    "sg:city":"Herve",
    "sg:orig_category":"Diverse zakelijke dienstverlening Organisatie van beurzen, congressen and tentoonstellingen Restaura",
    "sg:phone":"+32 87 66 08 68",
    "sg:postcode":"4651",
    "sg:province":"Li\u00e8ge",
    "wof:name":"Salons La Renardi\u00c8re Du Bois Chaffoux",
    "wof:placetype":"venue"
},
  "geometry": {"coordinates":[5.8221597672,50.6231193542],"type":"Point"}
}