{
  "type": "Feature",
  "properties": {
    "iso:country":"BE",
    "sg:address":"Boulevard Louis Schmidt 35b11",
    "sg:city":"Etterbeek",
    "sg:orig_category":"Hypotheken and hypotheekbanken Verzekeringsmakelaars and experts",
    "sg:phone":"+32 2 732 51 00",
    "sg:postcode":"1040",
    "sg:province":"Bruxelles-Capitale",
    "wof:name":"Charles Lambinet Et Fils",
    "wof:placetype":"venue"
},
  "geometry": {"coordinates":[4.4002699852,50.8275413513],"type":"Point"}
}