{
  "type": "Feature",
  "properties": {
    "iso:country":"BE",
    "sg:address":"Robert Ramlotstraat 89",
    "sg:city":"Sint-gillis-dendermonde",
    "sg:classifiers":[
        {
            "category":"Manufacturing",
            "subcategory":"Textiles",
            "type":"Manufacturing & Wholesale Goods"
        }
    ],
    "sg:phone":"+32 52 26 24 11",
    "sg:postcode":"9200",
    "sg:province":"Oost-Vlaanderen",
    "sg:tags":[
        "linen",
        "clothing",
        "fabric"
    ],
    "wof:name":"Desso Nv",
    "wof:placetype":"venue"
},
  "geometry": {"coordinates":[4.1125998497,51.0173988342],"type":"Point"}
}