{
  "type": "Feature",
  "properties": {
    "addr:full":"Waterpachtgoedsstraat 4 Ledegem West-Vlaanderen 8880",
    "addr:housenumber":"4",
    "addr:postcode":"8880",
    "addr:street":"Waterpachtgoedsstraat",
    "iso:country":"BE",
    "sg:address":"Waterpachtgoedsstraat 4",
    "sg:city":"Ledegem",
    "sg:orig_category":"Eleveurs and marchands de porcs",
    "sg:phone":"+32 56 50 00 89",
    "sg:postcode":"8880",
    "sg:province":"West-Vlaanderen",
    "wof:name":"Jean Scheldeman",
    "wof:placetype":"venue"
},
  "geometry": {"coordinates":[3.1573700905,50.8650932312],"type":"Point"}
}