{
  "type": "Feature",
  "properties": {
    "iso:country":"BE",
    "sg:address":"Miksebaan 243b5",
    "sg:city":"Brasschaat",
    "sg:orig_category":"Reclamebureaus",
    "sg:phone":"+32 3 651 50 30",
    "sg:postcode":"2930",
    "sg:province":"Antwerpen",
    "wof:name":"Bureau Boeye G.",
    "wof:placetype":"venue"
},
  "geometry": {"coordinates":[4.5119757652,51.2951622009],"type":"Point"}
}