{
  "type": "Feature",
  "properties": {
    "iso:country":"BE",
    "sg:address":"H. Torleylaan 4",
    "sg:city":"Beersel (huizingen)",
    "sg:classifiers":[
        {
            "category":"Retail",
            "subcategory":"Repair Shop",
            "type":"Services"
        }
    ],
    "sg:phone":"+32 2 356 50 68",
    "sg:postcode":"1654",
    "sg:province":"Vlaams-Brabant",
    "sg:tags":[
        "upholsterer"
    ],
    "wof:name":"Smeeks S",
    "wof:placetype":"venue"
},
  "geometry": {"coordinates":[4.2748279572,50.7472419739],"type":"Point"}
}