{
  "type": "Feature",
  "properties": {
    "addr:full":"Rue Du Cur\u00e9 6 Rixensart (rosi\u00e8res) Brabant Wallon 1331",
    "addr:housenumber":"6;1331",
    "addr:street":"Rue Du Cure\u0301",
    "iso:country":"BE",
    "sg:address":"Rue Du Cur\u00e9 6",
    "sg:city":"Rixensart (rosi\u00e8res)",
    "sg:classifiers":[
        {
            "category":"Building & Trades",
            "subcategory":"Plumbing",
            "type":"Services"
        }
    ],
    "sg:phone":"+32 2 652 21 97",
    "sg:postcode":"1331",
    "sg:province":"Brabant Wallon",
    "sg:tags":[
        "repair",
        "mainten",
        "-",
        "central",
        "heating"
    ],
    "wof:name":"Danze Chaleur & Confort Sprl",
    "wof:placetype":"venue"
},
  "geometry": {"coordinates":[4.5334172249,50.7312889099],"type":"Point"}
}