{
  "type": "Feature",
  "properties": {
    "iso:country":"BE",
    "sg:address":"Korte Ieperstraat 27",
    "sg:city":"Langemark-poelkapelle",
    "sg:orig_category":"Enseignement maternel and primaire",
    "sg:phone":"+32 57 48 85 87",
    "sg:postcode":"8920",
    "sg:province":"West-Vlaanderen",
    "wof:name":"Basisschool",
    "wof:placetype":"venue"
},
  "geometry": {"coordinates":[2.919770956,50.9132423401],"type":"Point"}
}