{
  "type": "Feature",
  "properties": {
    "iso:country":"BE",
    "sg:address":"Wippelberg 112",
    "sg:city":"Arendonk",
    "sg:classifiers":[
        {
            "category":"Recreation",
            "subcategory":"Amusement Park",
            "type":"Entertainment"
        }
    ],
    "sg:phone":"+32 14 67 27 18",
    "sg:postcode":"2370",
    "sg:province":"Antwerpen",
    "sg:tags":[
        "attraction",
        "-",
        "sale",
        "fair",
        "hiring"
    ],
    "wof:name":"Patotter",
    "wof:placetype":"venue"
},
  "geometry": {"coordinates":[5.1008620262,51.3196716309],"type":"Point"}
}