{
  "type": "Feature",
  "properties": {
    "addr:full":"Rue Vandervelde 19 Quevaucamps Hainaut 7972",
    "addr:housenumber":"19",
    "addr:postcode":"7972",
    "addr:street":"Rue Vandervelde",
    "iso:country":"BE",
    "sg:address":"Rue Vandervelde 19",
    "sg:city":"Quevaucamps",
    "sg:orig_category":"Vertalers and tolken",
    "sg:phone":"+32 69 56 07 28",
    "sg:postcode":"7972",
    "sg:province":"Hainaut",
    "wof:name":"Debaye Pierre",
    "wof:placetype":"venue"
},
  "geometry": {"coordinates":[3.6831259727,50.5199928284],"type":"Point"}
}