{
  "type": "Feature",
  "properties": {
    "addr:full":"Dikkebusseweg 208 Ieper West-Vlaanderen 8900",
    "addr:housenumber":"208",
    "addr:postcode":"8900",
    "iso:country":"BE",
    "sg:address":"Dikkebusseweg 208",
    "sg:city":"Ieper",
    "sg:orig_category":"Forge, Moulage and Profilage des M\u00e9taux",
    "sg:phone":"+32 57 21 77 51",
    "sg:postcode":"8900",
    "sg:province":"West-Vlaanderen",
    "wof:name":"Declercq",
    "wof:placetype":"venue"
},
  "geometry": {"coordinates":[2.8684680462,50.8405570984],"type":"Point"}
}