{
  "type": "Feature",
  "properties": {
    "addr:full":"Kerkstraat 64 Dendermonde Oost-Vlaanderen 9200",
    "addr:housenumber":"64",
    "addr:postcode":"9200",
    "addr:street":"Kerkstraat;Oost-Vlaanderen",
    "iso:country":"BE",
    "sg:address":"Kerkstraat 64",
    "sg:city":"Dendermonde",
    "sg:orig_category":"Banques and organismes de cr\u00e9dit",
    "sg:phone":"+32 52 21 72 72",
    "sg:postcode":"9200",
    "sg:province":"Oost-Vlaanderen",
    "wof:name":"Bacob",
    "wof:placetype":"venue"
},
  "geometry": {"coordinates":[4.0955858231,51.0317878723],"type":"Point"}
}