{
  "type": "Feature",
  "properties": {
    "iso:country":"BE",
    "sg:address":"Stokstraat 20",
    "sg:city":"Kruishoutem",
    "sg:classifiers":[
        {
            "category":"Freight",
            "type":"Transportation"
        }
    ],
    "sg:phone":"+32 9 280 72 00",
    "sg:postcode":"9770",
    "sg:province":"Oost-Vlaanderen",
    "sg:tags":[
        "-",
        "transport"
    ],
    "wof:name":"Decotra",
    "wof:placetype":"venue"
},
  "geometry": {"coordinates":[3.4859530926,50.9089393616],"type":"Point"}
}