{
  "type": "Feature",
  "properties": {
    "addr:full":"Galerie Des Halles Ottignies-louvain-la-neuve (louvain-la-neuve) Brabant Wallon 1348",
    "addr:postcode":"1348",
    "addr:street":"Galerie;Brabant",
    "iso:country":"BE",
    "sg:address":"Galerie Des Halles",
    "sg:city":"Ottignies-louvain-la-neuve (louvain-la-neuve)",
    "sg:classifiers":[
        {
            "category":"Real Estate",
            "subcategory":"Real Estate Services",
            "type":"Services"
        }
    ],
    "sg:phone":"+32 10 47 47 47",
    "sg:postcode":"1348",
    "sg:province":"Brabant Wallon",
    "wof:name":"Inforville",
    "wof:placetype":"venue"
},
  "geometry": {"coordinates":[4.567553997,50.6661262512],"type":"Point"}
}