{
  "type": "Feature",
  "properties": {
    "iso:country":"BE",
    "sg:address":"Albertkanaalstraat 22",
    "sg:city":"Hasselt (kuringen)",
    "sg:classifiers":[
        {
            "category":"Health Services",
            "subcategory":"Health Practitioner",
            "type":"Services"
        }
    ],
    "sg:phone":"+32 11 25 66 48",
    "sg:postcode":"3511",
    "sg:province":"Limburg",
    "sg:tags":[
        "physiotherapist"
    ],
    "wof:name":"Rondel Griet",
    "wof:placetype":"venue"
},
  "geometry": {"coordinates":[5.3081507683,50.9491767883],"type":"Point"}
}