{
  "type": "Feature",
  "properties": {
    "iso:country":"BE",
    "sg:address":"Rue Du Centre 1",
    "sg:city":"Somme-leuze",
    "sg:orig_category":"Overheidsdiensten",
    "sg:phone":"+32 86 32 21 22",
    "sg:postcode":"5377",
    "sg:province":"Namur",
    "wof:name":"Administration Communale",
    "wof:placetype":"venue"
},
  "geometry": {"coordinates":[5.3411860466,50.2794303894],"type":"Point"}
}