{
  "type": "Feature",
  "properties": {
    "addr:full":"Broelkaai 1be Kortrijk West-Vlaanderen 8500",
    "addr:postcode":"8500",
    "iso:country":"BE",
    "sg:address":"Broelkaai 1be",
    "sg:city":"Kortrijk",
    "sg:orig_category":"Agences d\u00b4interim and personnel temporaire",
    "sg:phone":"+32 56 23 41 34",
    "sg:postcode":"8500",
    "sg:province":"West-Vlaanderen",
    "wof:name":"Accent Interim",
    "wof:placetype":"venue"
},
  "geometry": {"coordinates":[3.2648129463,50.8300895691],"type":"Point"}
}