{
  "type": "Feature",
  "properties": {
    "addr:full":"Groenveldstraat 46 Leuven Vlaams-Brabant 3001",
    "addr:housenumber":"46",
    "addr:postcode":"3001",
    "addr:street":"Groenveldstraat",
    "iso:country":"BE",
    "sg:address":"Groenveldstraat 46",
    "sg:city":"Leuven",
    "sg:orig_category":"Enseignement maternel and primaire. Enseignement secondaire g\u00e9n\u00e9ral",
    "sg:phone":"+32 16 20 80 26",
    "sg:postcode":"3001",
    "sg:province":"Vlaams-Brabant",
    "wof:name":"Vrije Basisschool",
    "wof:placetype":"venue"
},
  "geometry": {"coordinates":[4.6836409569,50.8730697632],"type":"Point"}
}