{
  "type": "Feature",
  "properties": {
    "iso:country":"BE",
    "sg:address":"Vleugelsstraat 39b7",
    "sg:city":"Schaarbeek/schaerbeek",
    "sg:orig_category":"Informaticaconsulenten",
    "sg:phone":"+32 475 97 68 53",
    "sg:postcode":"1030",
    "sg:province":"Bruxelles-Capitale",
    "wof:name":"Johnyco Soft Service",
    "wof:placetype":"venue"
},
  "geometry": {"coordinates":[4.3752942085,50.8681373596],"type":"Point"}
}