{
  "type": "Feature",
  "properties": {
    "addr:full":"Haltstraat 90 Overpelt Limburg 3900",
    "addr:housenumber":"90",
    "addr:postcode":"3900",
    "addr:street":"Haltstraat",
    "iso:country":"BE",
    "sg:address":"Haltstraat 90",
    "sg:city":"Overpelt",
    "sg:classifiers":[
        {
            "category":"Manufacturing",
            "subcategory":"Metals",
            "type":"Manufacturing & Wholesale Goods"
        }
    ],
    "sg:phone":"+32 11 66 62 13",
    "sg:postcode":"3900",
    "sg:province":"Limburg",
    "sg:tags":[
        "working"
    ],
    "wof:name":"D.p.m Bvba",
    "wof:placetype":"venue"
},
  "geometry": {"coordinates":[5.3845291138,51.2196350098],"type":"Point"}
}