{
  "type": "Feature",
  "properties": {
    "addr:full":"Opitterstraat 13-15 Bree Limburg 3960",
    "addr:postcode":"13-15;3960",
    "addr:street":"Opitterstraat",
    "iso:country":"BE",
    "sg:address":"Opitterstraat 13-15",
    "sg:city":"Bree",
    "sg:classifiers":[
        {
            "category":"Shopping",
            "subcategory":"Jewelry",
            "type":"Retail Goods"
        }
    ],
    "sg:phone":"+32 89 46 19 20",
    "sg:postcode":"3960",
    "sg:province":"Limburg",
    "sg:tags":[
        "jeweller",
        "-"
    ],
    "wof:name":"Tijskens Lode",
    "wof:placetype":"venue"
},
  "geometry": {"coordinates":[5.5998258591,51.1411247253],"type":"Point"}
}