{
  "type": "Feature",
  "properties": {
    "iso:country":"BE",
    "sg:address":"Everspoelstraat 14",
    "sg:city":"Landen",
    "sg:orig_category":"Eleveurs de bovins",
    "sg:phone":"+32 16 78 85 82",
    "sg:postcode":"3400",
    "sg:province":"Vlaams-Brabant",
    "wof:name":"Bernard Moyens",
    "wof:placetype":"venue"
},
  "geometry": {"coordinates":[5.025780201,50.7700881958],"type":"Point"}
}