{
  "type": "Feature",
  "properties": {
    "addr:full":"Rue Buraufosse 11 Saint-nicolas Li\u00e8ge 4420",
    "addr:housenumber":"11",
    "addr:postcode":"4420",
    "addr:street":"Rue Buraufosse",
    "iso:country":"BE",
    "sg:address":"Rue Buraufosse 11",
    "sg:city":"Saint-nicolas",
    "sg:classifiers":[
        {
            "category":"Food & Beverages",
            "subcategory":"Fruits & Vegetables",
            "type":"Retail Goods"
        }
    ],
    "sg:phone":"+32 4 234 05 24",
    "sg:postcode":"4420",
    "sg:province":"Li\u00e8ge",
    "sg:tags":[
        "l\u00e9gumes"
    ],
    "wof:name":"Francesco Coniglio",
    "wof:placetype":"venue"
},
  "geometry": {"coordinates":[5.5297079086,50.6261024475],"type":"Point"}
}