{
  "type": "Feature",
  "properties": {
    "addr:full":"Duinenweg 8 Hechtel-eksel Limburg 3940",
    "addr:housenumber":"8",
    "addr:postcode":"3940",
    "addr:street":"Duinenweg",
    "iso:country":"BE",
    "sg:address":"Duinenweg 8",
    "sg:city":"Hechtel-eksel",
    "sg:orig_category":"Woningbouw",
    "sg:phone":"+32 11 73 61 13",
    "sg:postcode":"3940",
    "sg:province":"Limburg",
    "wof:name":"Maas",
    "wof:placetype":"venue"
},
  "geometry": {"coordinates":[5.364795208,51.1255340576],"type":"Point"}
}