{
  "type": "Feature",
  "properties": {
    "addr:full":"Rijkmakerlaan 6 Essen Antwerpen 2910",
    "addr:housenumber":"6",
    "addr:postcode":"2910",
    "addr:street":"Rijkmakerlaan",
    "iso:country":"BE",
    "sg:address":"Rijkmakerlaan 6",
    "sg:city":"Essen",
    "sg:classifiers":[
        {
            "category":"Autos & Motor Vehicles",
            "subcategory":"Automobile Sales",
            "type":"Retail Goods"
        }
    ],
    "sg:phone":"+32 3 667 57 58",
    "sg:postcode":"2910",
    "sg:province":"Antwerpen",
    "sg:tags":[
        "car",
        "used",
        "-"
    ],
    "wof:name":"Lm Motors",
    "wof:placetype":"venue"
},
  "geometry": {"coordinates":[4.4992542267,51.4451560974],"type":"Point"}
}