{
  "type": "Feature",
  "properties": {
    "iso:country":"BE",
    "sg:address":"Rue Emile Vandervelde 30",
    "sg:city":"Fl\u00c9ron (grand)",
    "sg:orig_category":"Apotheken",
    "sg:phone":"+32 4 358 83 84",
    "sg:postcode":"4624",
    "sg:province":"Li\u00e8ge",
    "wof:name":"Pharmacie Fonze",
    "wof:placetype":"venue"
},
  "geometry": {"coordinates":[5.6680140495,50.610912323],"type":"Point"}
}