{
  "type": "Feature",
  "properties": {
    "iso:country":"BE",
    "sg:address":"Ninoofsesteenweg 278",
    "sg:city":"Halle (groot)",
    "sg:orig_category":"Agences immobili\u00e8res",
    "sg:phone":"+32 2 361 62 12",
    "sg:postcode":"1500",
    "sg:province":"Vlaams-Brabant",
    "wof:name":"Era Visie Plus",
    "wof:placetype":"venue"
},
  "geometry": {"coordinates":[4.2234039307,50.7410774231],"type":"Point"}
}