{
  "type": "Feature",
  "properties": {
    "iso:country":"BE",
    "sg:address":"Rue 600 Franchimontois 1",
    "sg:city":"Theux",
    "sg:orig_category":"S\u00e9lection de personnel and placement",
    "sg:phone":"+32 87 53 93 26",
    "sg:postcode":"4910",
    "sg:province":"Li\u00e8ge",
    "wof:name":"Ale Theux",
    "wof:placetype":"venue"
},
  "geometry": {"coordinates":[5.8168897629,50.5284881592],"type":"Point"}
}