{
  "type": "Feature",
  "properties": {
    "iso:country":"BE",
    "sg:address":"Kortrijkstraat 40",
    "sg:city":"Wevelgem",
    "sg:orig_category":"Plaatsen van vloer- and muurbekleding",
    "sg:phone":"+32 56 41 15 62",
    "sg:postcode":"8560",
    "sg:province":"West-Vlaanderen",
    "wof:name":"Josson Omer & Marc",
    "wof:placetype":"venue"
},
  "geometry": {"coordinates":[3.1876540184,50.8101577759],"type":"Point"}
}