{
  "type": "Feature",
  "properties": {
    "iso:country":"BE",
    "sg:address":"Gistelse Steenweg 228",
    "sg:city":"Brugge (sint-andries)",
    "sg:classifiers":[
        {
            "category":"Food & Beverages",
            "subcategory":"Liquor & Beverages",
            "type":"Retail Goods"
        }
    ],
    "sg:phone":"+32 50 38 63 80",
    "sg:postcode":"8200",
    "sg:province":"West-Vlaanderen",
    "sg:tags":[
        "-",
        "spirit",
        "wine"
    ],
    "wof:name":"Matthys Wijnimport Nv",
    "wof:placetype":"venue"
},
  "geometry": {"coordinates":[3.1975340843,51.2008628845],"type":"Point"}
}