{
  "type": "Feature",
  "properties": {
    "addr:full":"Kronenhoekstraat 37 Sint-gillis-waas Oost-Vlaanderen 9170",
    "addr:housenumber":"37",
    "addr:postcode":"9170",
    "addr:street":"Kronenhoekstraat",
    "iso:country":"BE",
    "sg:address":"Kronenhoekstraat 37",
    "sg:city":"Sint-gillis-waas",
    "sg:orig_category":"Brood, gebak and snoepgoed",
    "sg:phone":"+32 3 770 51 75",
    "sg:postcode":"9170",
    "sg:province":"Oost-Vlaanderen",
    "wof:name":"De Paepe-daelman",
    "wof:placetype":"venue"
},
  "geometry": {"coordinates":[4.123401165,51.2210273743],"type":"Point"}
}