{
  "type": "Feature",
  "properties": {
    "iso:country":"BE",
    "sg:address":"Rue Uyttenhove 39b",
    "sg:city":"Bruxelles (jette)",
    "sg:classifiers":[
        {
            "category":"Sports & Exercise",
            "subcategory":"Sports Center",
            "type":"Entertainment"
        }
    ],
    "sg:phone":"+32 2 420 37 97",
    "sg:postcode":"1090",
    "sg:province":"Bruxelles-Capitale",
    "sg:tags":[
        "holiday",
        "language"
    ],
    "wof:name":"Formasport Vzw",
    "wof:placetype":"venue"
},
  "geometry": {"coordinates":[4.3364109993,50.8706130981],"type":"Point"}
}