{
  "type": "Feature",
  "properties": {
    "addr:full":"Cond\u00e9dreef 52 Kortrijk West-Vlaanderen 8500",
    "addr:housenumber":"52",
    "addr:postcode":"8500",
    "addr:street":"Conde\u0301Dreef",
    "iso:country":"BE",
    "sg:address":"Cond\u00e9dreef 52",
    "sg:city":"Kortrijk",
    "sg:classifiers":[
        {
            "category":"Real Estate",
            "subcategory":"Surveying",
            "type":"Services"
        }
    ],
    "sg:phone":"+32 56 22 05 65",
    "sg:postcode":"8500",
    "sg:province":"West-Vlaanderen",
    "sg:tags":[
        "lettering",
        "letter"
    ],
    "wof:name":"Cre-art Publi Cv",
    "wof:placetype":"venue"
},
  "geometry": {"coordinates":[3.2593109608,50.8187942505],"type":"Point"}
}