{
  "type": "Feature",
  "properties": {
    "addr:full":"Grote Markt 6 Hasselt Limburg 3500",
    "addr:housenumber":"6",
    "addr:postcode":"3500",
    "addr:street":"Grote Markt",
    "iso:country":"BE",
    "sg:address":"Grote Markt 6",
    "sg:city":"Hasselt",
    "sg:orig_category":"Diverse kredietdiensten",
    "sg:postcode":"3500",
    "sg:province":"Limburg",
    "wof:name":"Bancontact-mister Cash",
    "wof:placetype":"venue"
},
  "geometry": {"coordinates":[5.3376631737,50.9296607971],"type":"Point"}
}