{
  "type": "Feature",
  "properties": {
    "iso:country":"BE",
    "sg:address":"Rue Du Mouton Blanc 13",
    "sg:city":"Li\u00c8ge",
    "sg:orig_category":"Instituts de beaut\u00e9",
    "sg:phone":"+32 4 223 62 64",
    "sg:postcode":"4000",
    "sg:province":"Li\u00e8ge",
    "wof:name":"Institut Dominic",
    "wof:placetype":"venue"
},
  "geometry": {"coordinates":[5.570543766,50.6413955688],"type":"Point"}
}