{
  "type": "Feature",
  "properties": {
    "iso:country":"BE",
    "sg:address":"Rue Provinciale 580",
    "sg:city":"Juprelle (fexhe-slins)",
    "sg:classifiers":[
        {
            "category":"Shopping",
            "subcategory":"Florist",
            "type":"Retail Goods"
        }
    ],
    "sg:phone":"+32 4 289 06 67",
    "sg:postcode":"4458",
    "sg:province":"Li\u00e8ge",
    "wof:name":"Marguerite",
    "wof:placetype":"venue"
},
  "geometry": {"coordinates":[5.5669198036,50.7078514099],"type":"Point"}
}