{
  "type": "Feature",
  "properties": {
    "addr:full":"Grand'place 61 Tournai Hainaut 7500",
    "addr:housenumber":"61",
    "addr:postcode":"7500",
    "addr:street":"Grand'Place",
    "iso:country":"BE",
    "sg:address":"Grand'place 61",
    "sg:city":"Tournai",
    "sg:orig_category":"Banken and kredietinstellingen",
    "sg:phone":"+32 69 22 40 90",
    "sg:postcode":"7500",
    "sg:province":"Hainaut",
    "wof:name":"Bbl",
    "wof:placetype":"venue"
},
  "geometry": {"coordinates":[3.3858730793,50.6069221497],"type":"Point"}
}