{
  "type": "Feature",
  "properties": {
    "addr:full":"Rue Paradis 31 Vise Li\u00e8ge 4600",
    "addr:housenumber":"31",
    "addr:postcode":"4600",
    "addr:street":"Rue Paradis",
    "iso:country":"BE",
    "sg:address":"Rue Paradis 31",
    "sg:city":"Vise",
    "sg:orig_category":"Afbraak- and draineerwerken Industri\u00eble and commerci\u00eble bouw",
    "sg:phone":"+32 4 379 16 48",
    "sg:postcode":"4600",
    "sg:province":"Li\u00e8ge",
    "wof:name":"Lacroix Fils",
    "wof:placetype":"venue"
},
  "geometry": {"coordinates":[5.6952648163,50.7378158569],"type":"Point"}
}