{
  "type": "Feature",
  "properties": {
    "iso:country":"BE",
    "sg:address":"Rue De L'etang Derbaix 14",
    "sg:city":"Mons (cuesmes)",
    "sg:classifiers":[
        {
            "category":"Food & Beverages",
            "subcategory":"Supermarket",
            "type":"Retail Goods"
        }
    ],
    "sg:phone":"+32 65 31 89 25",
    "sg:postcode":"7033",
    "sg:province":"Hainaut",
    "sg:tags":[
        "department",
        "store"
    ],
    "wof:name":"Profi Sa",
    "wof:placetype":"venue"
},
  "geometry": {"coordinates":[3.923060894,50.4387168884],"type":"Point"}
}