{
  "type": "Feature",
  "properties": {
    "addr:full":"Chauss\u00c9e De Li\u00c8ge 75 Jambes Namur 5100",
    "addr:housenumber":"75",
    "addr:postcode":"5100",
    "addr:street":"Chausse\u0301E De Lie\u0300Ge",
    "iso:country":"BE",
    "sg:address":"Chauss\u00c9e De Li\u00c8ge 75",
    "sg:city":"Jambes",
    "sg:orig_category":"Charpentes and couvertures",
    "sg:phone":"+32 81 30 54 84",
    "sg:postcode":"5100",
    "sg:province":"Namur",
    "wof:name":"Jean Calonne",
    "wof:placetype":"venue"
},
  "geometry": {"coordinates":[4.8811092377,50.4571533203],"type":"Point"}
}