{
  "type": "Feature",
  "properties": {
    "addr:full":"Hoogbaan 6ba Dilsen-stokkem Limburg 3650",
    "addr:postcode":"3650",
    "addr:street":"Hoogbaan",
    "iso:country":"BE",
    "sg:address":"Hoogbaan 6ba",
    "sg:city":"Dilsen-stokkem",
    "sg:orig_category":"V\u00e9hicules automobiles. Entretien and r\u00e9parations de voitures",
    "sg:phone":"+32 89 79 20 18",
    "sg:postcode":"3650",
    "sg:province":"Limburg",
    "wof:name":"Auto\u00b4s Brouns",
    "wof:placetype":"venue"
},
  "geometry": {"coordinates":[5.7301869392,51.0391311646],"type":"Point"}
}