{
  "type": "Feature",
  "properties": {
    "addr:full":"Koning Leopoldlaan 20d Maldegem Oost-Vlaanderen 9990",
    "addr:housenumber":"20d",
    "addr:postcode":"9990",
    "addr:street":"Koning Leopoldlaan",
    "iso:country":"BE",
    "sg:address":"Koning Leopoldlaan 20d",
    "sg:city":"Maldegem",
    "sg:classifiers":[
        {
            "category":"Professional",
            "subcategory":"Computer Services",
            "type":"Services"
        }
    ],
    "sg:phone":"+32 50 71 94 29",
    "sg:postcode":"9990",
    "sg:province":"Oost-Vlaanderen",
    "sg:tags":[
        "-",
        "processing",
        "data"
    ],
    "wof:name":"Dcs-coppens Nv",
    "wof:placetype":"venue"
},
  "geometry": {"coordinates":[3.4638059139,51.2042198181],"type":"Point"}
}