{
  "type": "Feature",
  "properties": {
    "addr:full":"Kaplan-arnolds-strasse 9 Eupen Li\u00e8ge 4700",
    "addr:housenumber":"9",
    "addr:postcode":"4700",
    "addr:street":"Kaplan-Arnolds-Strasse",
    "iso:country":"BE",
    "sg:address":"Kaplan-arnolds-strasse 9",
    "sg:city":"Eupen",
    "sg:classifiers":[
        {
            "category":"Health Services",
            "subcategory":"Health Practitioner",
            "type":"Services"
        }
    ],
    "sg:phone":"+32 87 55 61 89",
    "sg:postcode":"4700",
    "sg:province":"Li\u00e8ge",
    "sg:tags":[
        "physiotherapist"
    ],
    "wof:name":"F\u00f6rster J\u00fcrgen",
    "wof:placetype":"venue"
},
  "geometry": {"coordinates":[6.0619411469,50.6104850769],"type":"Point"}
}