{
  "type": "Feature",
  "properties": {
    "iso:country":"BE",
    "sg:address":"Rue Remenpont 6",
    "sg:city":"Lessines (ogy)",
    "sg:classifiers":[
        {
            "category":"Building & Trades",
            "subcategory":"Construction",
            "type":"Services"
        }
    ],
    "sg:phone":"+32 68 56 81 74",
    "sg:postcode":"7862",
    "sg:province":"Hainaut",
    "sg:tags":[
        "ventilating",
        "system"
    ],
    "wof:name":"Euro Vent Sprl",
    "wof:placetype":"venue"
},
  "geometry": {"coordinates":[3.7776451111,50.7139511108],"type":"Point"}
}