{
  "type": "Feature",
  "properties": {
    "addr:full":"Rue Fran\u00c7ois Gay 8 Sint-pieters-woluwe/woluwe-saint-pierre Bruxelles-Capitale 1150",
    "addr:housenumber":"8",
    "addr:postcode":"1150",
    "addr:street":"Rue Franc\u0327Ois Gay;/",
    "iso:country":"BE",
    "sg:address":"Rue Fran\u00c7ois Gay 8",
    "sg:city":"Sint-pieters-woluwe/woluwe-saint-pierre",
    "sg:orig_category":"V\u00e9los. Motos. Location d'articles de sport, de sport nautique and de camping",
    "sg:phone":"+32 2 770 02 42",
    "sg:postcode":"1150",
    "sg:province":"Bruxelles-Capitale",
    "wof:name":"Maison Best Bike",
    "wof:placetype":"venue"
},
  "geometry": {"coordinates":[4.4307770729,50.8379745483],"type":"Point"}
}