{
  "type": "Feature",
  "properties": {
    "iso:country":"BE",
    "sg:address":"Nijlense Steenweg 15",
    "sg:city":"Herenthout",
    "sg:classifiers":[
        {
            "category":"Personal",
            "subcategory":"Beauty Salon",
            "type":"Services"
        }
    ],
    "sg:phone":"+32 14 51 16 64",
    "sg:postcode":"2270",
    "sg:province":"Antwerpen",
    "sg:tags":[
        "lady",
        "-",
        "hairdressing"
    ],
    "wof:name":"Willems J",
    "wof:placetype":"venue"
},
  "geometry": {"coordinates":[4.7542161942,51.1397171021],"type":"Point"}
}