{
  "type": "Feature",
  "properties": {
    "iso:country":"BE",
    "sg:address":"Rue Notre Dame 50",
    "sg:city":"Lessines",
    "sg:orig_category":"Woningbouw",
    "sg:phone":"+32 68 33 65 49",
    "sg:postcode":"7866",
    "sg:province":"Hainaut",
    "wof:name":"Antoine Bohez",
    "wof:placetype":"venue"
},
  "geometry": {"coordinates":[3.8941729069,50.7062797546],"type":"Point"}
}