{
  "type": "Feature",
  "properties": {
    "addr:full":"Weststraat 37 Blankenberge West-Vlaanderen 8370",
    "addr:housenumber":"37",
    "addr:postcode":"8370",
    "addr:street":"Weststraat",
    "iso:country":"BE",
    "sg:address":"Weststraat 37",
    "sg:city":"Blankenberge",
    "sg:classifiers":[
        {
            "category":"Restaurant",
            "type":"Food & Drink"
        }
    ],
    "sg:phone":"+32 50 41 58 16",
    "sg:postcode":"8370",
    "sg:province":"West-Vlaanderen",
    "wof:name":"Rimini",
    "wof:placetype":"venue"
},
  "geometry": {"coordinates":[3.1258900166,51.3144569397],"type":"Point"}
}