{
  "type": "Feature",
  "properties": {
    "iso:country":"BE",
    "sg:address":"Rue Du Cur\u00e9 Verdin 2",
    "sg:city":"Juprelle (lantin)",
    "sg:classifiers":[
        {
            "category":"Professional",
            "subcategory":"Accounting & Tax Preparation",
            "type":"Services"
        }
    ],
    "sg:phone":"+32 4 263 45 80",
    "sg:postcode":"4450",
    "sg:province":"Li\u00e8ge",
    "sg:tags":[
        "bookkeeper"
    ],
    "wof:name":"Tilkin C",
    "wof:placetype":"venue"
},
  "geometry": {"coordinates":[5.527659893,50.7088737488],"type":"Point"}
}