{
  "type": "Feature",
  "properties": {
    "addr:full":"Jonkershovestraat 158 Houthulst West-Vlaanderen 8650",
    "addr:housenumber":"158",
    "addr:postcode":"8650",
    "addr:street":"Jonkershovestraat",
    "iso:country":"BE",
    "sg:address":"Jonkershovestraat 158",
    "sg:city":"Houthulst",
    "sg:orig_category":"Groententeelt Varkenskwekers",
    "sg:phone":"+32 51 54 41 27",
    "sg:postcode":"8650",
    "sg:province":"West-Vlaanderen",
    "wof:name":"Joel Delheye",
    "wof:placetype":"venue"
},
  "geometry": {"coordinates":[2.9257929325,50.9714813232],"type":"Point"}
}