{
  "type": "Feature",
  "properties": {
    "addr:full":"Van Craenenbroeckstraat 33 Beveren (beveren-waas) Oost-Vlaanderen 9120",
    "addr:housenumber":"33",
    "addr:postcode":"9120",
    "addr:street":"Craenenbroeckstraat;Oost-Vlaanderen",
    "iso:country":"BE",
    "sg:address":"Van Craenenbroeckstraat 33",
    "sg:city":"Beveren (beveren-waas)",
    "sg:classifiers":[
        {
            "category":"Personal",
            "subcategory":"Nail Salon",
            "type":"Services"
        }
    ],
    "sg:phone":"+32 3 775 46 65",
    "sg:postcode":"9120",
    "sg:province":"Oost-Vlaanderen",
    "sg:tags":[
        "pedicure"
    ],
    "wof:name":"Instituut Sofie",
    "wof:placetype":"venue"
},
  "geometry": {"coordinates":[4.2495741844,51.2208976746],"type":"Point"}
}