{
  "type": "Feature",
  "properties": {
    "addr:full":"Rue Hauzeur De Simony 57 Verviers Li\u00e8ge 4800",
    "addr:housenumber":"57",
    "addr:postcode":"4800",
    "addr:street":"Rue Hauzeur De Simony",
    "iso:country":"BE",
    "sg:address":"Rue Hauzeur De Simony 57",
    "sg:city":"Verviers",
    "sg:orig_category":"Bloemen and planten",
    "sg:phone":"+32 87 22 97 77",
    "sg:postcode":"4800",
    "sg:province":"Li\u00e8ge",
    "wof:name":"La Fleuristerie De Seroule",
    "wof:placetype":"venue"
},
  "geometry": {"coordinates":[5.8600201607,50.5811882019],"type":"Point"}
}