{
  "type": "Feature",
  "properties": {
    "iso:country":"BE",
    "sg:address":"Place Cardinal Mercier 17",
    "sg:city":"Wavre",
    "sg:classifiers":[
        {
            "category":"Shopping",
            "subcategory":"Jewelry",
            "type":"Retail Goods"
        }
    ],
    "sg:phone":"+32 10 22 39 17",
    "sg:postcode":"1300",
    "sg:province":"Brabant Wallon",
    "sg:tags":[
        "jeweller",
        "-"
    ],
    "wof:name":"De Saedeleer J-p",
    "wof:placetype":"venue"
},
  "geometry": {"coordinates":[4.6105642319,50.7168426514],"type":"Point"}
}