{
  "type": "Feature",
  "properties": {
    "addr:full":"Rue Dumont 19 Saint-ghislain Hainaut 7332",
    "addr:housenumber":"19",
    "addr:postcode":"7332",
    "addr:street":"Rue Dumont;Hainaut",
    "iso:country":"BE",
    "sg:address":"Rue Dumont 19",
    "sg:city":"Saint-ghislain",
    "sg:orig_category":"Eleveurs de bovins",
    "sg:phone":"+32 65 62 06 02",
    "sg:postcode":"7332",
    "sg:province":"Hainaut",
    "wof:name":"Jean Descornet",
    "wof:placetype":"venue"
},
  "geometry": {"coordinates":[3.786839962,50.5054969788],"type":"Point"}
}