{
  "type": "Feature",
  "properties": {
    "addr:full":"Rue De La Casquette 6 Li\u00e8ge 1 Li\u00e8ge 4000",
    "addr:housenumber":"6;1",
    "addr:postcode":"4000",
    "addr:street":"Rue De La Casquette",
    "iso:country":"BE",
    "sg:address":"Rue De La Casquette 6",
    "sg:city":"Li\u00e8ge 1",
    "sg:orig_category":"Non-Classified Establishments",
    "sg:phone":"+32 4 221 36 14",
    "sg:postcode":"4000",
    "sg:province":"Li\u00e8ge",
    "wof:name":"Kan M\u00e9dic",
    "wof:placetype":"venue"
},
  "geometry": {"coordinates":[5.5690321922,50.6427459717],"type":"Point"}
}