{
  "type": "Feature",
  "properties": {
    "iso:country":"BE",
    "sg:address":"Stijfselrui 44",
    "sg:city":"Antwerpen",
    "sg:classifiers":[
        {
            "category":"Transit Center",
            "subcategory":"Freight",
            "type":"Transportation"
        }
    ],
    "sg:phone":"+32 3 222 17 11",
    "sg:postcode":"2000",
    "sg:province":"Antwerpen",
    "sg:tags":[
        "forwarding",
        "agency"
    ],
    "wof:name":"Cosco Belgium Nv",
    "wof:placetype":"venue"
},
  "geometry": {"coordinates":[4.4129948616,51.2258262634],"type":"Point"}
}