{
  "type": "Feature",
  "properties": {
    "addr:full":"Rue Du Crucifix 14 Herstal Li\u00e8ge 4040",
    "addr:housenumber":"14",
    "addr:postcode":"4040",
    "addr:street":"Rue Du Crucifix",
    "iso:country":"BE",
    "sg:address":"Rue Du Crucifix 14",
    "sg:city":"Herstal",
    "sg:classifiers":[
        {
            "category":"Home & Garden",
            "subcategory":"Carpets & Floor Coverings",
            "type":"Retail Goods"
        }
    ],
    "sg:phone":"+32 4 240 02 45",
    "sg:postcode":"4040",
    "sg:province":"Li\u00e8ge",
    "sg:tags":[
        "material",
        "waterproofing"
    ],
    "wof:name":"Abrisec Sc",
    "wof:placetype":"venue"
},
  "geometry": {"coordinates":[5.6397371292,50.6742744446],"type":"Point"}
}