{
  "type": "Feature",
  "properties": {
    "iso:country":"BE",
    "sg:address":"Driesdreef 12",
    "sg:city":"Gent",
    "sg:classifiers":[
        {
            "category":"Cafe",
            "type":"Food & Drink"
        }
    ],
    "sg:phone":"+32 9 227 75 23",
    "sg:postcode":"9030",
    "sg:province":"Oost-Vlaanderen",
    "sg:tags":[
        "caf\u00e9s"
    ],
    "wof:name":"Caf\u00c9 De Bargie",
    "wof:placetype":"venue"
},
  "geometry": {"coordinates":[3.6591069698,51.0714378357],"type":"Point"}
}