{
  "type": "Feature",
  "properties": {
    "addr:full":"Kolonel Bourgstraat 153 Evere Bruxelles-Capitale 1140",
    "addr:housenumber":"153",
    "addr:postcode":"1140",
    "addr:street":"Kolonel Bourgstraat",
    "iso:country":"BE",
    "sg:address":"Kolonel Bourgstraat 153",
    "sg:city":"Evere",
    "sg:classifiers":[
        {
            "category":"Insurance",
            "subcategory":"Insurance Agent",
            "type":"Services"
        }
    ],
    "sg:phone":"+32 2 730 99 69",
    "sg:postcode":"1140",
    "sg:province":"Bruxelles-Capitale",
    "sg:tags":[
        "verzekeringsmakelaars",
        "expert"
    ],
    "wof:name":"Aon. Warranty Groep Ltd",
    "wof:placetype":"venue"
},
  "geometry": {"coordinates":[4.4208297729,50.8571510315],"type":"Point"}
}