{
  "type": "Feature",
  "properties": {
    "addr:full":"Trommelstraat 37 Heist-op-den-berg Antwerpen 2223",
    "addr:housenumber":"37",
    "addr:postcode":"2223",
    "addr:street":"Trommelstraat",
    "iso:country":"BE",
    "sg:address":"Trommelstraat 37",
    "sg:city":"Heist-op-den-berg",
    "sg:orig_category":"HUISBRANDOLIE",
    "sg:phone":"+32 15 23 48 88",
    "sg:postcode":"2223",
    "sg:province":"Antwerpen",
    "wof:name":"Esso",
    "wof:placetype":"venue"
},
  "geometry": {"coordinates":[4.6935648918,51.0282707214],"type":"Point"}
}