{
  "type": "Feature",
  "properties": {
    "addr:full":"Postbus 62 Maaseik Limburg 3680",
    "addr:housenumber":"62",
    "addr:postcode":"3680",
    "addr:street":"Postbus",
    "iso:country":"BE",
    "sg:address":"Postbus 62",
    "sg:city":"Maaseik",
    "sg:classifiers":[
        {
            "category":"Shopping",
            "subcategory":"Party Supplies",
            "type":"Retail Goods"
        }
    ],
    "sg:phone":"+32 89 56 85 56",
    "sg:postcode":"3680",
    "sg:province":"Limburg",
    "wof:name":"Wimmers-hermans",
    "wof:placetype":"venue"
},
  "geometry": {"coordinates":[5.791285038,51.0954208374],"type":"Point"}
}