{
  "type": "Feature",
  "properties": {
    "addr:full":"Alfons De Cockstraat 34 Antwerpen Antwerpen 2020",
    "addr:housenumber":"34",
    "addr:postcode":"2020",
    "addr:street":"Alfons De Cockstraat",
    "iso:country":"BE",
    "sg:address":"Alfons De Cockstraat 34",
    "sg:city":"Antwerpen",
    "sg:classifiers":[
        {
            "category":"Building & Trades",
            "subcategory":"Construction",
            "type":"Services"
        }
    ],
    "sg:phone":"+32 3 830 43 06",
    "sg:postcode":"2020",
    "sg:province":"Antwerpen",
    "sg:tags":[
        "installation",
        "-",
        "central",
        "heating"
    ],
    "wof:name":"Crauwels Sanitair Bvba",
    "wof:placetype":"venue"
},
  "geometry": {"coordinates":[4.3749160767,51.1895446777],"type":"Point"}
}