{
  "type": "Feature",
  "properties": {
    "iso:country":"BE",
    "sg:address":"Rue De La Vou\u00c9e 13bis",
    "sg:city":"Vise",
    "sg:orig_category":"Plomberie, chauffage and installations sanitaires",
    "sg:phone":"+32 4 379 33 05",
    "sg:postcode":"4600",
    "sg:province":"Li\u00e8ge",
    "wof:name":"Gerard Et Cie",
    "wof:placetype":"venue"
},
  "geometry": {"coordinates":[5.6952648163,50.7378158569],"type":"Point"}
}