{
  "type": "Feature",
  "properties": {
    "addr:full":"Sint-juliaanstraat 2 Langemark-poelkapelle West-Vlaanderen 8920",
    "addr:housenumber":"2",
    "addr:postcode":"8920",
    "addr:street":"Sint-Juliaanstraat",
    "iso:country":"BE",
    "sg:address":"Sint-juliaanstraat 2",
    "sg:city":"Langemark-poelkapelle",
    "sg:orig_category":"Enseignement maternel and primaire",
    "sg:phone":"+32 57 48 92 89",
    "sg:postcode":"8920",
    "sg:province":"West-Vlaanderen",
    "wof:name":"Vrije Basisschool",
    "wof:placetype":"venue"
},
  "geometry": {"coordinates":[2.9376819134,50.8898849487],"type":"Point"}
}