{
  "type": "Feature",
  "properties": {
    "addr:full":"Rue Du Moulin \u00c0 Eau 3 Beauvechain Brabant Wallon 1320",
    "addr:housenumber":"3",
    "addr:postcode":"1320",
    "addr:street":"Rue Du Moulin A\u0300 Eau",
    "iso:country":"BE",
    "sg:address":"Rue Du Moulin \u00c0 Eau 3",
    "sg:city":"Beauvechain",
    "sg:orig_category":"Banques and organismes de cr\u00e9dit",
    "sg:phone":"+32 10 86 64 58",
    "sg:postcode":"1320",
    "sg:province":"Brabant Wallon",
    "wof:name":"Bbl",
    "wof:placetype":"venue"
},
  "geometry": {"coordinates":[4.7703499794,50.7786483765],"type":"Point"}
}