{
  "type": "Feature",
  "properties": {
    "iso:country":"BE",
    "sg:address":"Rue Du Moulin \u00c0 Eau 3",
    "sg:city":"Beauvechain",
    "sg:orig_category":"Banques and organismes de cr\u00e9dit",
    "sg:phone":"+32 10 86 64 58",
    "sg:postcode":"1320",
    "sg:province":"Brabant Wallon",
    "wof:name":"Bbl",
    "wof:placetype":"venue"
},
  "geometry": {"coordinates":[4.7703499794,50.7786483765],"type":"Point"}
}