{
  "type": "Feature",
  "properties": {
    "addr:full":"Woumenweg 131 Diksmuide West-Vlaanderen 8600",
    "addr:housenumber":"131",
    "addr:postcode":"8600",
    "addr:street":"Woumenweg",
    "iso:country":"BE",
    "sg:address":"Woumenweg 131",
    "sg:city":"Diksmuide",
    "sg:orig_category":"Eleveurs and marchands de porcs",
    "sg:phone":"+32 51 50 19 50",
    "sg:postcode":"8600",
    "sg:province":"West-Vlaanderen",
    "wof:name":"Hugo Merlevede",
    "wof:placetype":"venue"
},
  "geometry": {"coordinates":[2.8674230576,51.015045166],"type":"Point"}
}