{
  "type": "Feature",
  "properties": {
    "iso:country":"BE",
    "sg:address":"Van Couwenhovelaan 32",
    "sg:city":"Herent",
    "sg:orig_category":"Technische studies and ingenieursactiviteiten",
    "sg:phone":"+32 16 22 40 30",
    "sg:postcode":"3020",
    "sg:province":"Vlaams-Brabant",
    "wof:name":"Vanderbeeken G",
    "wof:placetype":"venue"
},
  "geometry": {"coordinates":[4.6590070724,50.8849487305],"type":"Point"}
}