{
  "type": "Feature",
  "properties": {
    "addr:full":"Strijp 55bc Wichelen Oost-Vlaanderen 9260",
    "addr:housenumber":"55bc",
    "addr:postcode":"9260",
    "addr:street":"Strijp",
    "iso:country":"BE",
    "sg:address":"Strijp 55bc",
    "sg:city":"Wichelen",
    "sg:orig_category":"Loodgieterij, verwarming and sanitaire installaties",
    "sg:phone":"+32 52 42 22 48",
    "sg:postcode":"9260",
    "sg:province":"Oost-Vlaanderen",
    "wof:name":"Hubert Missotten",
    "wof:placetype":"venue"
},
  "geometry": {"coordinates":[3.9760069847,51.0014877319],"type":"Point"}
}