{
  "type": "Feature",
  "properties": {
    "addr:full":"Diepestraat 6 Hove Antwerpen 2540",
    "addr:housenumber":"6",
    "addr:postcode":"2540",
    "addr:street":"Diepestraat",
    "iso:country":"BE",
    "sg:address":"Diepestraat 6",
    "sg:city":"Hove",
    "sg:classifiers":[
        {
            "category":"Professional",
            "subcategory":"Management & Consulting",
            "type":"Services"
        }
    ],
    "sg:phone":"+32 3 288 70 32",
    "sg:postcode":"2540",
    "sg:province":"Antwerpen",
    "sg:tags":[
        "consultant"
    ],
    "wof:name":"Haemstede Bvba",
    "wof:placetype":"venue"
},
  "geometry": {"coordinates":[4.4779758453,51.1488723755],"type":"Point"}
}