{
  "type": "Feature",
  "properties": {
    "iso:country":"BE",
    "sg:address":"Route De Mons 75",
    "sg:city":"Quaregnon",
    "sg:orig_category":"V\u00e9hicules automobiles",
    "sg:phone":"+32 65 78 19 21",
    "sg:postcode":"7390",
    "sg:province":"Hainaut",
    "wof:name":"Occas Center",
    "wof:placetype":"venue"
},
  "geometry": {"coordinates":[3.8447499275,50.4402198792],"type":"Point"}
}