{
  "type": "Feature",
  "properties": {
    "iso:country":"BE",
    "sg:address":"Wijngaardstraat 57",
    "sg:city":"Kortrijk",
    "sg:classifiers":[
        {
            "category":"Bars & Pubs",
            "type":"Food & Drink"
        }
    ],
    "sg:phone":"+32 56 22 05 69",
    "sg:postcode":"8500",
    "sg:province":"West-Vlaanderen",
    "wof:name":"Petit Paris Bvba",
    "wof:placetype":"venue"
},
  "geometry": {"coordinates":[3.2713971138,50.8263092041],"type":"Point"}
}