{
  "type": "Feature",
  "properties": {
    "addr:full":"Paepemunte 54 Lierde (hemelveerdegem) Oost-Vlaanderen 9571",
    "addr:housenumber":"54",
    "addr:postcode":"9571",
    "addr:street":"Paepemunte",
    "iso:country":"BE",
    "sg:address":"Paepemunte 54",
    "sg:city":"Lierde (hemelveerdegem)",
    "sg:classifiers":[
        {
            "category":"Professional",
            "subcategory":"Accounting & Tax Preparation",
            "type":"Services"
        }
    ],
    "sg:phone":"+32 54 42 24 13",
    "sg:postcode":"9571",
    "sg:province":"Oost-Vlaanderen",
    "sg:tags":[
        "bookkeeper"
    ],
    "wof:name":"Van Audenaerde W",
    "wof:placetype":"venue"
},
  "geometry": {"coordinates":[3.8623120785,50.8081130981],"type":"Point"}
}