{
  "type": "Feature",
  "properties": {
    "addr:full":"Rue L\u00e9on Delval 62 Merbes-le-ch\u00e2teau (fontaine-valmont) Hainaut 6567",
    "addr:housenumber":"62",
    "addr:postcode":"6567",
    "addr:street":"Rue Le\u0301On Delval",
    "iso:country":"BE",
    "sg:address":"Rue L\u00e9on Delval 62",
    "sg:city":"Merbes-le-ch\u00e2teau (fontaine-valmont)",
    "sg:classifiers":[
        {
            "category":"Health Services",
            "subcategory":"Doctor",
            "type":"Services"
        }
    ],
    "sg:phone":"+32 71 55 70 16",
    "sg:postcode":"6567",
    "sg:province":"Hainaut",
    "sg:tags":[
        "medicinephysicians",
        "surgeon"
    ],
    "wof:name":"Bournonville Anne",
    "wof:placetype":"venue"
},
  "geometry": {"coordinates":[4.2153539658,50.3121986389],"type":"Point"}
}