{
  "type": "Feature",
  "properties": {
    "iso:country":"BE",
    "sg:address":"Rue De L'angle 19",
    "sg:city":"Antoing",
    "sg:orig_category":"Artsen and specialisten",
    "sg:phone":"+32 69 44 48 71",
    "sg:postcode":"7640",
    "sg:province":"Hainaut",
    "wof:name":"Chantal Van Winckel",
    "wof:placetype":"venue"
},
  "geometry": {"coordinates":[3.4528069496,50.5508613586],"type":"Point"}
}