{
  "type": "Feature",
  "properties": {
    "iso:country":"BE",
    "sg:address":"Aarschotseweg 30",
    "sg:city":"Herentals",
    "sg:classifiers":[
        {
            "category":"Utilities",
            "subcategory":"Fuel Oil & Lpg",
            "type":"Services"
        }
    ],
    "sg:phone":"+32 14 22 15 73",
    "sg:postcode":"2200",
    "sg:province":"Antwerpen",
    "sg:tags":[
        "stations-service",
        "combustible",
        "carburants"
    ],
    "wof:name":"Gepex",
    "wof:placetype":"venue"
},
  "geometry": {"coordinates":[4.8461208344,51.1597671509],"type":"Point"}
}