{
  "type": "Feature",
  "properties": {
    "addr:full":"Brusselbaan 463 Sint-pieters-leeuw Vlaams-Brabant 1600",
    "addr:housenumber":"463",
    "addr:postcode":"1600",
    "addr:street":"Brusselbaan",
    "iso:country":"BE",
    "sg:address":"Brusselbaan 463",
    "sg:city":"Sint-pieters-leeuw",
    "sg:classifiers":[
        {
            "category":"Arena",
            "subcategory":"Sports Club",
            "type":"Entertainment"
        }
    ],
    "sg:phone":"+32 2 331 60 31",
    "sg:postcode":"1600",
    "sg:province":"Vlaams-Brabant",
    "sg:tags":[
        "federation"
    ],
    "wof:name":"Ligue Francophone Du Squash",
    "wof:placetype":"venue"
},
  "geometry": {"coordinates":[4.2459812164,50.7858276367],"type":"Point"}
}