{
  "type": "Feature",
  "properties": {
    "addr:full":"Rue Du Mont \u00e0 Leux 154-115 Mouscron Hainaut 7700",
    "addr:postcode":"154-115;7700",
    "addr:street":"Rue Du Mont A\u0300 Leux;Hainaut",
    "iso:country":"BE",
    "sg:address":"Rue Du Mont \u00e0 Leux 154-115",
    "sg:city":"Mouscron",
    "sg:classifiers":[
        {
            "category":"Shopping",
            "subcategory":"Bicycles & Sporting Goods",
            "type":"Retail Goods"
        }
    ],
    "sg:phone":"+32 56 33 13 18",
    "sg:postcode":"7700",
    "sg:province":"Hainaut",
    "sg:tags":[
        "-"
    ],
    "wof:name":"Cycles Tuyttens Sports Sa",
    "wof:placetype":"venue"
},
  "geometry": {"coordinates":[3.1988899708,50.7297439575],"type":"Point"}
}