{
  "type": "Feature",
  "properties": {
    "addr:full":"Heirbaan 86 Beveren (haasdonk) Oost-Vlaanderen 9120",
    "addr:housenumber":"86",
    "addr:postcode":"9120",
    "addr:street":"Heirbaan",
    "iso:country":"BE",
    "sg:address":"Heirbaan 86",
    "sg:city":"Beveren (haasdonk)",
    "sg:classifiers":[
        {
            "category":"Retail",
            "subcategory":"Veterinary Services",
            "type":"Services"
        }
    ],
    "sg:phone":"+32 3 775 18 86",
    "sg:postcode":"9120",
    "sg:province":"Oost-Vlaanderen",
    "sg:tags":[
        "veterinarian"
    ],
    "wof:name":"Meeus J",
    "wof:placetype":"venue"
},
  "geometry": {"coordinates":[4.2588510513,51.1830101013],"type":"Point"}
}