{
  "type": "Feature",
  "properties": {
    "addr:full":"Rue Edmond Delcourt 30 Bruxelles (anderlecht) Bruxelles-Capitale 1070",
    "addr:housenumber":"30",
    "addr:postcode":"1070",
    "addr:street":"Rue Edmond Delcourt",
    "iso:country":"BE",
    "sg:address":"Rue Edmond Delcourt 30",
    "sg:city":"Bruxelles (anderlecht)",
    "sg:classifiers":[
        {
            "category":"Shopping",
            "subcategory":"Pharmacy",
            "type":"Retail Goods"
        }
    ],
    "sg:phone":"+32 2 521 74 23",
    "sg:postcode":"1070",
    "sg:province":"Bruxelles-Capitale",
    "sg:tags":[
        "store",
        "drug"
    ],
    "wof:name":"Erasme J.v.",
    "wof:placetype":"venue"
},
  "geometry": {"coordinates":[4.3070111275,50.8380622864],"type":"Point"}
}