{
  "type": "Feature",
  "properties": {
    "iso:country":"BE",
    "sg:address":"Van De Wiellei 166",
    "sg:city":"Brasschaat",
    "sg:orig_category":"D\u00e9corateurs d'int\u00e9rieur",
    "sg:phone":"+32 3 653 48 94",
    "sg:postcode":"2930",
    "sg:province":"Antwerpen",
    "wof:name":"Alain Van Geuns",
    "wof:placetype":"venue"
},
  "geometry": {"coordinates":[4.4803619385,51.2977409363],"type":"Point"}
}