{
  "type": "Feature",
  "properties": {
    "iso:country":"BE",
    "sg:address":"Sprietestraat 15",
    "sg:city":"Waregem",
    "sg:orig_category":"Location de v\u00eatements, chaussures and textiles",
    "sg:phone":"+32 56 71 30 92",
    "sg:postcode":"8792",
    "sg:province":"West-Vlaanderen",
    "wof:name":"Willaert Fantasiekledij",
    "wof:placetype":"venue"
},
  "geometry": {"coordinates":[3.360886097,50.8791465759],"type":"Point"}
}