{
  "type": "Feature",
  "properties": {
    "iso:country":"BE",
    "sg:address":"Beukendreef 7",
    "sg:city":"Kapellen",
    "sg:orig_category":"Fleurs and plantes",
    "sg:phone":"+32 3 664 06 61",
    "sg:postcode":"2950",
    "sg:province":"Antwerpen",
    "wof:name":"Josepha De Herdt",
    "wof:placetype":"venue"
},
  "geometry": {"coordinates":[4.4291558266,51.3068313599],"type":"Point"}
}