{
  "type": "Feature",
  "properties": {
    "iso:country":"BE",
    "sg:address":"G. Gezellestraat 10",
    "sg:city":"Sint-martens-latem",
    "sg:orig_category":"Diverse zakelijke dienstverlening Modellenbureaus Ruimtes voor conferenties, recepties and feesten",
    "sg:phone":"+32 9 282 60 66",
    "sg:postcode":"9830",
    "sg:province":"Oost-Vlaanderen",
    "wof:name":"Nec + Ultra",
    "wof:placetype":"venue"
},
  "geometry": {"coordinates":[3.6314198971,51.00963974],"type":"Point"}
}