{
  "type": "Feature",
  "properties": {
    "iso:country":"BE",
    "sg:address":"Rue Des Pair\u00e9es 7",
    "sg:city":"Rochefort (wavreille)",
    "sg:classifiers":[
        {
            "category":"Travel",
            "subcategory":"Hotels & Motels",
            "type":"Entertainment"
        }
    ],
    "sg:phone":"+32 84 36 63 75",
    "sg:postcode":"5580",
    "sg:province":"Namur",
    "wof:name":"Auberge Du Moulin",
    "wof:placetype":"venue"
},
  "geometry": {"coordinates":[5.1950249672,50.1069946289],"type":"Point"}
}