{
  "type": "Feature",
  "properties": {
    "addr:full":"Avenue Victor-emmanuel Iii 12 Bruxelles (uccle) Bruxelles-Capitale 1180",
    "addr:housenumber":"12",
    "addr:postcode":"1180",
    "addr:street":"Avenue Victor-Emmanuel Iii",
    "iso:country":"BE",
    "sg:address":"Avenue Victor-emmanuel Iii 12",
    "sg:city":"Bruxelles (uccle)",
    "sg:classifiers":[
        {
            "category":"Health Services",
            "subcategory":"Health Practitioner",
            "type":"Services"
        }
    ],
    "sg:phone":"+32 2 374 81 38",
    "sg:postcode":"1180",
    "sg:province":"Bruxelles-Capitale",
    "sg:tags":[
        "physiotherapist"
    ],
    "wof:name":"Van Enis Henri",
    "wof:placetype":"venue"
},
  "geometry": {"coordinates":[4.3731350899,50.794670105],"type":"Point"}
}