{
  "type": "Feature",
  "properties": {
    "addr:full":"Stationsstraat 114 Waregem West-Vlaanderen 8790",
    "addr:housenumber":"114",
    "addr:postcode":"8790",
    "addr:street":"Stationsstraat",
    "iso:country":"BE",
    "sg:address":"Stationsstraat 114",
    "sg:city":"Waregem",
    "sg:orig_category":"Alimentation sp\u00e9cialis\u00e9e",
    "sg:phone":"+32 56 60 12 23",
    "sg:postcode":"8790",
    "sg:province":"West-Vlaanderen",
    "wof:name":"Natuurhuis Spillebeen",
    "wof:placetype":"venue"
},
  "geometry": {"coordinates":[3.4286999702,50.8908424377],"type":"Point"}
}