{
  "type": "Feature",
  "properties": {
    "iso:country":"BE",
    "sg:address":"Platanendreef 21",
    "sg:city":"Kruishoutem",
    "sg:orig_category":"Ergotherapists",
    "sg:phone":"+32 9 383 74 28",
    "sg:postcode":"9770",
    "sg:province":"Oost-Vlaanderen",
    "wof:name":"Vandevelde D",
    "wof:placetype":"venue"
},
  "geometry": {"coordinates":[3.5675830841,50.9220085144],"type":"Point"}
}