{
  "type": "Feature",
  "properties": {
    "addr:full":"C. Van Den Busschestraat 23 Brugge West-Vlaanderen 8310",
    "addr:housenumber":"23",
    "addr:postcode":"8310",
    "addr:street":"C. Van Den Busschestraat",
    "iso:country":"BE",
    "sg:address":"C. Van Den Busschestraat 23",
    "sg:city":"Brugge",
    "sg:classifiers":[
        {
            "category":"Personal",
            "subcategory":"Beauty Salon",
            "type":"Services"
        }
    ],
    "sg:phone":"+32 50 35 82 18",
    "sg:postcode":"8310",
    "sg:province":"West-Vlaanderen",
    "sg:tags":[
        "de",
        "coiffure"
    ],
    "wof:name":"Coiffure Marina",
    "wof:placetype":"venue"
},
  "geometry": {"coordinates":[3.2445108891,51.1975898743],"type":"Point"}
}