{
  "type": "Feature",
  "properties": {
    "addr:full":"Sint-jacobsnieuwstraat 38 Gent Oost-Vlaanderen 9000",
    "addr:housenumber":"38",
    "addr:postcode":"9000",
    "addr:street":"Sint-Jacobsnieuwstraat;Oost-Vlaanderen",
    "iso:country":"BE",
    "sg:address":"Sint-jacobsnieuwstraat 38",
    "sg:city":"Gent",
    "sg:orig_category":"Bijouteries and horlogeries. R\u00e9parations d'horloges, montres and bijoux",
    "sg:phone":"+32 9 225 41 74",
    "sg:postcode":"9000",
    "sg:province":"Oost-Vlaanderen",
    "wof:name":"Paul De Winne",
    "wof:placetype":"venue"
},
  "geometry": {"coordinates":[3.7295770645,51.0547714233],"type":"Point"}
}