{
  "type": "Feature",
  "properties": {
    "iso:country":"BE",
    "sg:address":"Rue Du Renard 230",
    "sg:city":"Tournai",
    "sg:orig_category":"Eleveurs d'animaux domestiques",
    "sg:phone":"+32 69 54 77 16",
    "sg:postcode":"7531",
    "sg:province":"Hainaut",
    "wof:name":"Chenil \u00c9levage De La Brise Qui Chante",
    "wof:placetype":"venue"
},
  "geometry": {"coordinates":[3.4597780704,50.6204833984],"type":"Point"}
}