{
  "type": "Feature",
  "properties": {
    "addr:full":"Rue Emile Pirson 55 Gembloux-sur-orneau (mazy) Namur 5032",
    "addr:housenumber":"55",
    "addr:postcode":"5032",
    "addr:street":"Rue Emile Pirson;Mazy",
    "iso:country":"BE",
    "sg:address":"Rue Emile Pirson 55",
    "sg:city":"Gembloux-sur-orneau (mazy)",
    "sg:classifiers":[
        {
            "category":"Shopping",
            "subcategory":"Bicycles & Sporting Goods",
            "type":"Retail Goods"
        }
    ],
    "sg:phone":"+32 81 63 30 90",
    "sg:postcode":"5032",
    "sg:province":"Namur",
    "sg:tags":[
        "sport",
        "-"
    ],
    "wof:name":"Golf De Falnu\u00e9e",
    "wof:placetype":"venue"
},
  "geometry": {"coordinates":[4.6703858376,50.5039253235],"type":"Point"}
}