{
  "type": "Feature",
  "properties": {
    "iso:country":"BE",
    "sg:address":"Mechelsesteenweg 136",
    "sg:city":"Zaventem (sterrebeek)",
    "sg:classifiers":[
        {
            "category":"Health Services",
            "subcategory":"Dentist",
            "type":"Services"
        }
    ],
    "sg:phone":"+32 2 657 57 11",
    "sg:postcode":"1933",
    "sg:province":"Vlaams-Brabant",
    "sg:tags":[
        "dental",
        "clinic"
    ],
    "wof:name":"Dentisceram",
    "wof:placetype":"venue"
},
  "geometry": {"coordinates":[4.5136151314,50.8592567444],"type":"Point"}
}