{
  "type": "Feature",
  "properties": {
    "addr:full":"Rue De L'eglise 1 H\u00e9l\u00e9cine (linsmeau) Brabant Wallon 1357",
    "addr:housenumber":"1",
    "addr:postcode":"1357",
    "addr:street":"Rue De L'Eglise;Wallon",
    "iso:country":"BE",
    "sg:address":"Rue De L'eglise 1",
    "sg:city":"H\u00e9l\u00e9cine (linsmeau)",
    "sg:classifiers":[
        {
            "category":"Real Estate",
            "subcategory":"Surveying",
            "type":"Services"
        }
    ],
    "sg:phone":"+32 476 66 68 06",
    "sg:postcode":"1357",
    "sg:province":"Brabant Wallon",
    "sg:tags":[
        "surveyor",
        "land"
    ],
    "wof:name":"Quintin J-f",
    "wof:placetype":"venue"
},
  "geometry": {"coordinates":[5.0031471252,50.7334327698],"type":"Point"}
}