{
  "type": "Feature",
  "properties": {
    "addr:full":"Verbindingsstraat 57 Tienen Vlaams-Brabant 3300",
    "addr:housenumber":"57",
    "addr:postcode":"3300",
    "addr:street":"Verbindingsstraat",
    "iso:country":"BE",
    "sg:address":"Verbindingsstraat 57",
    "sg:city":"Tienen",
    "sg:classifiers":[
        {
            "category":"Personal",
            "subcategory":"Beauty Salon",
            "type":"Services"
        }
    ],
    "sg:phone":"+32 16 82 33 13",
    "sg:postcode":"3300",
    "sg:province":"Vlaams-Brabant",
    "sg:tags":[
        "lady",
        "-",
        "hairdressing"
    ],
    "wof:name":"Wendy",
    "wof:placetype":"venue"
},
  "geometry": {"coordinates":[4.9604401588,50.8028411865],"type":"Point"}
}