{
  "type": "Feature",
  "properties": {
    "iso:country":"BE",
    "sg:address":"Brusselstraat 3",
    "sg:city":"Ninove",
    "sg:classifiers":[
        {
            "category":"Health Services",
            "subcategory":"Medical Lab",
            "type":"Services"
        }
    ],
    "sg:phone":"+32 54 30 03 16",
    "sg:postcode":"9400",
    "sg:province":"Oost-Vlaanderen",
    "sg:tags":[
        "laboratory",
        "dental"
    ],
    "wof:name":"Van Oudenhove Johan Tandlabo",
    "wof:placetype":"venue"
},
  "geometry": {"coordinates":[4.0224251747,50.8297348022],"type":"Point"}
}