{
  "type": "Feature",
  "properties": {
    "iso:country":"BE",
    "sg:address":"Rue Georges Tondeur 63",
    "sg:city":"Quevy",
    "sg:orig_category":"Woningbouw",
    "sg:phone":"+32 65 56 99 60",
    "sg:postcode":"7040",
    "sg:province":"Hainaut",
    "wof:name":"Jean Vanboquestaels",
    "wof:placetype":"venue"
},
  "geometry": {"coordinates":[3.9427890778,50.3577613831],"type":"Point"}
}