{
  "type": "Feature",
  "properties": {
    "addr:full":"Ieperweg 106 Roeselare West-Vlaanderen 8800",
    "addr:housenumber":"106",
    "addr:postcode":"8800",
    "iso:country":"BE",
    "sg:address":"Ieperweg 106",
    "sg:city":"Roeselare",
    "sg:orig_category":"Restaurants Ruimtes voor conferenties, recepties and feesten",
    "sg:phone":"+32 51 20 02 15",
    "sg:postcode":"8800",
    "sg:province":"West-Vlaanderen",
    "wof:name":"Beythem-statie",
    "wof:placetype":"venue"
},
  "geometry": {"coordinates":[3.1236050129,50.9006958008],"type":"Point"}
}