{
  "type": "Feature",
  "properties": {
    "addr:full":"Stationsstraat 19 Tessenderlo Limburg 3980",
    "addr:housenumber":"19",
    "addr:postcode":"3980",
    "addr:street":"Stationsstraat",
    "iso:country":"BE",
    "sg:address":"Stationsstraat 19",
    "sg:city":"Tessenderlo",
    "sg:orig_category":"Textiel",
    "sg:phone":"+32 13 66 88 03",
    "sg:postcode":"3980",
    "sg:province":"Limburg",
    "wof:name":"Huis Eleganta",
    "wof:placetype":"venue"
},
  "geometry": {"coordinates":[5.0916099548,51.0676002502],"type":"Point"}
}