{
  "type": "Feature",
  "properties": {
    "addr:full":"Route De Henri-chapelle 180 Dison Li\u00e8ge 4821",
    "addr:housenumber":"180",
    "addr:postcode":"4821",
    "addr:street":"Route De Henri-Chapelle",
    "iso:country":"BE",
    "sg:address":"Route De Henri-chapelle 180",
    "sg:city":"Dison",
    "sg:orig_category":"Rundveehouders Varkenskwekers",
    "sg:phone":"+32 87 31 15 14",
    "sg:postcode":"4821",
    "sg:province":"Li\u00e8ge",
    "wof:name":"Guy Lambert",
    "wof:placetype":"venue"
},
  "geometry": {"coordinates":[5.8883161545,50.6270637512],"type":"Point"}
}