{
  "type": "Feature",
  "properties": {
    "addr:full":"Avenue Des Lucioles 44 Waterloo Brabant Wallon 1410",
    "addr:housenumber":"44",
    "addr:postcode":"1410",
    "addr:street":"Avenue Des Lucioles",
    "iso:country":"BE",
    "sg:address":"Avenue Des Lucioles 44",
    "sg:city":"Waterloo",
    "sg:classifiers":[
        {
            "category":"Health Services",
            "subcategory":"Health Practitioner",
            "type":"Services"
        }
    ],
    "sg:phone":"+32 2 354 19 82",
    "sg:postcode":"1410",
    "sg:province":"Brabant Wallon",
    "sg:tags":[
        "physiotherapist"
    ],
    "wof:name":"Delhalle Jacqueline",
    "wof:placetype":"venue"
},
  "geometry": {"coordinates":[4.3634290695,50.7138023376],"type":"Point"}
}