{
  "type": "Feature",
  "properties": {
    "addr:full":"Westbilklaan 4 Gistel West-Vlaanderen 8470",
    "addr:housenumber":"4",
    "addr:postcode":"8470",
    "addr:street":"Westbilklaan",
    "iso:country":"BE",
    "sg:address":"Westbilklaan 4",
    "sg:city":"Gistel",
    "sg:orig_category":"Traitements param\u00e9dicaux",
    "sg:phone":"+32 59 27 78 70",
    "sg:postcode":"8470",
    "sg:province":"West-Vlaanderen",
    "wof:name":"L. Depestele",
    "wof:placetype":"venue"
},
  "geometry": {"coordinates":[2.97687006,51.1622123718],"type":"Point"}
}