{
  "type": "Feature",
  "properties": {
    "iso:country":"BE",
    "sg:address":"Avenue Theodule Gonda 2",
    "sg:city":"Flemalle",
    "sg:orig_category":"Winkelinrichting and handelsuitrusting Gh",
    "sg:phone":"+32 4 337 37 07",
    "sg:postcode":"4400",
    "sg:province":"Li\u00e8ge",
    "wof:name":"Olympian Games",
    "wof:placetype":"venue"
},
  "geometry": {"coordinates":[5.4413762093,50.6142082214],"type":"Point"}
}