{
  "type": "Feature",
  "properties": {
    "addr:full":"Pontstraat 62 Maarkedal Oost-Vlaanderen 9681",
    "addr:housenumber":"62",
    "addr:postcode":"9681",
    "addr:street":"Pontstraat",
    "iso:country":"BE",
    "sg:address":"Pontstraat 62",
    "sg:city":"Maarkedal",
    "sg:orig_category":"Rundveehouders Varkenskwekers",
    "sg:phone":"+32 55 21 44 35",
    "sg:postcode":"9681",
    "sg:province":"Oost-Vlaanderen",
    "wof:name":"Guy Heuvick",
    "wof:placetype":"venue"
},
  "geometry": {"coordinates":[3.6003339291,50.7946472168],"type":"Point"}
}