{
  "type": "Feature",
  "properties": {
    "addr:full":"Rue De La Buissi\u00c8re 62 La Louvi\u00c8re Hainaut 7100",
    "addr:housenumber":"62",
    "addr:postcode":"7100",
    "addr:street":"Rue De La Buissie\u0300Re",
    "iso:country":"BE",
    "sg:address":"Rue De La Buissi\u00c8re 62",
    "sg:city":"La Louvi\u00c8re",
    "sg:orig_category":"Boekhouders",
    "sg:phone":"+32 64 28 32 12",
    "sg:postcode":"7100",
    "sg:province":"Hainaut",
    "wof:name":"Christian Cantiniau",
    "wof:placetype":"venue"
},
  "geometry": {"coordinates":[4.1850848198,50.4748649597],"type":"Point"}
}