{
  "type": "Feature",
  "properties": {
    "addr:full":"Leuvense Steenweg 107 Sint-joost-ten-node/saint-josse-ten-noode Bruxelles-Capitale 1210",
    "addr:housenumber":"107",
    "addr:postcode":"1210",
    "addr:street":"Leuvense Steenweg",
    "iso:country":"BE",
    "sg:address":"Leuvense Steenweg 107",
    "sg:city":"Sint-joost-ten-node/saint-josse-ten-noode",
    "sg:classifiers":[
        {
            "category":"Cafe",
            "type":"Food & Drink"
        }
    ],
    "sg:phone":"+32 2 219 62 92",
    "sg:postcode":"1210",
    "sg:province":"Bruxelles-Capitale",
    "sg:tags":[
        "caf\u00e9s"
    ],
    "wof:name":"Gambrinus",
    "wof:placetype":"venue"
},
  "geometry": {"coordinates":[4.3754200935,50.8501358032],"type":"Point"}
}