{
  "type": "Feature",
  "properties": {
    "addr:full":"Rue Des Faubourgs 81 Arlon Luxembourg 6700",
    "addr:housenumber":"81",
    "addr:postcode":"6700",
    "addr:street":"Rue Des Faubourgs",
    "iso:country":"BE",
    "sg:address":"Rue Des Faubourgs 81",
    "sg:city":"Arlon",
    "sg:classifiers":[
        {
            "category":"Fast Food",
            "type":"Food & Drink"
        }
    ],
    "sg:phone":"+32 63 23 64 57",
    "sg:postcode":"6700",
    "sg:province":"Luxembourg",
    "sg:tags":[
        "\u00c0",
        "emporter",
        "restaurants"
    ],
    "wof:name":"Le Pitta Turque",
    "wof:placetype":"venue"
},
  "geometry": {"coordinates":[5.8106951714,49.6849441528],"type":"Point"}
}