{
  "type": "Feature",
  "properties": {
    "addr:full":"Chauss\u00e9e De Boondael 441 Bruxelles (ixelles) Bruxelles-Capitale 1050",
    "addr:housenumber":"441",
    "addr:postcode":"1050",
    "addr:street":"Chausse\u0301E De Boondael",
    "iso:country":"BE",
    "sg:address":"Chauss\u00e9e De Boondael 441",
    "sg:city":"Bruxelles (ixelles)",
    "sg:classifiers":[
        {
            "category":"Home & Garden",
            "subcategory":"Household Appliances",
            "type":"Retail Goods"
        }
    ],
    "sg:phone":"+32 2 647 94 85",
    "sg:postcode":"1050",
    "sg:province":"Bruxelles-Capitale",
    "sg:tags":[
        "repair",
        "mainten",
        "-",
        "electric"
    ],
    "wof:name":"Van Hoof",
    "wof:placetype":"venue"
},
  "geometry": {"coordinates":[4.3888039589,50.8167648315],"type":"Point"}
}