{
  "type": "Feature",
  "properties": {
    "addr:full":"Lodewijk Maesstraat 1 Kortenberg Vlaams-Brabant 3070",
    "addr:housenumber":"1",
    "addr:postcode":"3070",
    "addr:street":"Lodewijk Maesstraat;Vlaams-Brabant",
    "iso:country":"BE",
    "sg:address":"Lodewijk Maesstraat 1",
    "sg:city":"Kortenberg",
    "sg:orig_category":"Banken and kredietinstellingen",
    "sg:phone":"+32 2 759 86 04",
    "sg:postcode":"3070",
    "sg:province":"Vlaams-Brabant",
    "wof:name":"Fortis",
    "wof:placetype":"venue"
},
  "geometry": {"coordinates":[4.5408301353,50.8858184814],"type":"Point"}
}