{
  "type": "Feature",
  "properties": {
    "addr:full":"Stationsstraat 280 Dilbeek Vlaams-Brabant 1700",
    "addr:housenumber":"280",
    "addr:postcode":"1700",
    "addr:street":"Stationsstraat",
    "iso:country":"BE",
    "sg:address":"Stationsstraat 280",
    "sg:city":"Dilbeek",
    "sg:classifiers":[
        {
            "category":"Bakery",
            "type":"Food & Drink"
        }
    ],
    "sg:phone":"+32 2 463 35 10",
    "sg:postcode":"1700",
    "sg:province":"Vlaams-Brabant",
    "sg:tags":[
        "confectioner",
        "baker"
    ],
    "wof:name":"Van Dessel W",
    "wof:placetype":"venue"
},
  "geometry": {"coordinates":[4.2451891899,50.8649330139],"type":"Point"}
}