{
  "type": "Feature",
  "properties": {
    "addr:full":"Prieelstraat 4 Asse Vlaams-Brabant 1730",
    "addr:housenumber":"4",
    "addr:postcode":"1730",
    "addr:street":"Prieelstraat",
    "iso:country":"BE",
    "sg:address":"Prieelstraat 4",
    "sg:city":"Asse",
    "sg:orig_category":"Postkantoren Verzekeringsmakelaars and experts",
    "sg:phone":"+32 2 452 62 82",
    "sg:postcode":"1730",
    "sg:province":"Vlaams-Brabant",
    "wof:name":"De Post",
    "wof:placetype":"venue"
},
  "geometry": {"coordinates":[4.1965961456,50.9122009277],"type":"Point"}
}