{
  "type": "Feature",
  "properties": {
    "addr:full":"Rue De La Cit\u00e9 38 Oupeye (vivegnis) Li\u00e8ge 4683",
    "addr:housenumber":"38",
    "addr:postcode":"4683",
    "addr:street":"Rue De La Cite\u0301;Vivegnis",
    "iso:country":"BE",
    "sg:address":"Rue De La Cit\u00e9 38",
    "sg:city":"Oupeye (vivegnis)",
    "sg:classifiers":[
        {
            "category":"Health Services",
            "subcategory":"Nursing And Care Facility",
            "type":"Services"
        }
    ],
    "sg:phone":"+32 4 248 12 46",
    "sg:postcode":"4683",
    "sg:province":"Li\u00e8ge",
    "sg:tags":[
        "home"
    ],
    "wof:name":"Wauters Y",
    "wof:placetype":"venue"
},
  "geometry": {"coordinates":[5.6495499611,50.6958198547],"type":"Point"}
}