{
  "type": "Feature",
  "properties": {
    "addr:full":"Hondenstraat 12 Scherpenheuvel-zichem (zichem) Vlaams-Brabant 3271",
    "addr:housenumber":"12",
    "addr:postcode":"3271",
    "addr:street":"Hondenstraat",
    "iso:country":"BE",
    "sg:address":"Hondenstraat 12",
    "sg:city":"Scherpenheuvel-zichem (zichem)",
    "sg:classifiers":[
        {
            "category":"Recreation",
            "subcategory":"Amusement Park",
            "type":"Entertainment"
        }
    ],
    "sg:phone":"+32 13 33 69 53",
    "sg:postcode":"3271",
    "sg:province":"Vlaams-Brabant",
    "sg:tags":[
        "attraction",
        "-",
        "sale",
        "fair",
        "hiring"
    ],
    "wof:name":"Struyf D",
    "wof:placetype":"venue"
},
  "geometry": {"coordinates":[4.9878220558,50.9989929199],"type":"Point"}
}