{
  "type": "Feature",
  "properties": {
    "iso:country":"BE",
    "sg:address":"Wolvertemsesteenweg 103",
    "sg:city":"Grimbergen",
    "sg:orig_category":"Entretien and r\u00e9parations de voitures. V\u00e9hicules automobiles",
    "sg:phone":"+32 2 269 11 45",
    "sg:postcode":"1850",
    "sg:province":"Vlaams-Brabant",
    "wof:name":"Mertens",
    "wof:placetype":"venue"
},
  "geometry": {"coordinates":[4.3648838997,50.9358520508],"type":"Point"}
}