{
  "type": "Feature",
  "properties": {
    "addr:full":"Bergstrasse 35 Eupen Li\u00e8ge 4700",
    "addr:housenumber":"35",
    "addr:postcode":"4700",
    "addr:street":"Bergstrasse",
    "iso:country":"BE",
    "sg:address":"Bergstrasse 35",
    "sg:city":"Eupen",
    "sg:classifiers":[
        {
            "category":"Shopping",
            "subcategory":"Clothing, Apparel, & Fashions",
            "type":"Retail Goods"
        }
    ],
    "sg:phone":"+32 87 55 56 66",
    "sg:postcode":"4700",
    "sg:province":"Li\u00e8ge",
    "sg:tags":[
        "boutique"
    ],
    "wof:name":"Vogue",
    "wof:placetype":"venue"
},
  "geometry": {"coordinates":[6.0333991051,50.6292114258],"type":"Point"}
}