{
  "type": "Feature",
  "properties": {
    "iso:country":"BE",
    "sg:address":"Oostkade 1",
    "sg:city":"Zelzate",
    "sg:orig_category":"Sportterreinen and installaties behalve sportcentra",
    "sg:phone":"+32 9 345 74 22",
    "sg:postcode":"9060",
    "sg:province":"Oost-Vlaanderen",
    "wof:name":"Sportcomplex Eurohal",
    "wof:placetype":"venue"
},
  "geometry": {"coordinates":[3.8093891144,51.2012252808],"type":"Point"}
}