{
  "type": "Feature",
  "properties": {
    "iso:country":"BE",
    "sg:address":"Avenue Paul Pastur 55",
    "sg:city":"Charleroi (mont-sur-marchienne)",
    "sg:classifiers":[
        {
            "category":"Personal",
            "subcategory":"Beauty Salon",
            "type":"Services"
        }
    ],
    "sg:phone":"+32 71 43 46 96",
    "sg:postcode":"6032",
    "sg:province":"Hainaut",
    "wof:name":"Rive Gauche",
    "wof:placetype":"venue"
},
  "geometry": {"coordinates":[4.4066100121,50.3895492554],"type":"Point"}
}