{
  "type": "Feature",
  "properties": {
    "iso:country":"BE",
    "sg:address":"Nellekenstraat 32",
    "sg:city":"Lennik (sint-kwintens-lennik)",
    "sg:classifiers":[
        {
            "category":"Farming",
            "subcategory":"Crops",
            "type":"Manufacturing & Wholesale Goods"
        }
    ],
    "sg:phone":"+32 2 532 12 02",
    "sg:postcode":"1750",
    "sg:province":"Vlaams-Brabant",
    "sg:tags":[
        "vegetable",
        "fruit",
        "-",
        "grower"
    ],
    "wof:name":"Van Der Meulen R",
    "wof:placetype":"venue"
},
  "geometry": {"coordinates":[4.1327381134,50.8204612732],"type":"Point"}
}