{
  "type": "Feature",
  "properties": {
    "addr:full":"Rue Astrid 60 P\u00c9ruwelz Hainaut 7600",
    "addr:housenumber":"60",
    "addr:postcode":"7600",
    "addr:street":"Rue Astrid",
    "iso:country":"BE",
    "sg:address":"Rue Astrid 60",
    "sg:city":"P\u00c9ruwelz",
    "sg:classifiers":[
        {
            "category":"Fast Food",
            "type":"Food & Drink"
        }
    ],
    "sg:phone":"+32 69 78 04 70",
    "sg:postcode":"7600",
    "sg:province":"Hainaut",
    "sg:tags":[
        "huis",
        "aan",
        "levering",
        "meeneem",
        "restaurant"
    ],
    "wof:name":"Pita Ramses",
    "wof:placetype":"venue"
},
  "geometry": {"coordinates":[3.5917749405,50.5128707886],"type":"Point"}
}