{
  "type": "Feature",
  "properties": {
    "addr:full":"Avenue Des Celtes 56 Bruxelles (etterbeek) Bruxelles-Capitale 1040",
    "addr:housenumber":"56",
    "addr:postcode":"1040",
    "addr:street":"Avenue Des Celtes",
    "iso:country":"BE",
    "sg:address":"Avenue Des Celtes 56",
    "sg:city":"Bruxelles (etterbeek)",
    "sg:classifiers":[
        {
            "category":"Travel",
            "subcategory":"Travel Agent",
            "type":"Entertainment"
        }
    ],
    "sg:phone":"+32 2 736 39 28",
    "sg:postcode":"1040",
    "sg:province":"Bruxelles-Capitale",
    "sg:tags":[
        "agency"
    ],
    "wof:name":"Bonvoyages Sa",
    "wof:placetype":"venue"
},
  "geometry": {"coordinates":[4.3967599869,50.8375778198],"type":"Point"}
}