{
  "type": "Feature",
  "properties": {
    "iso:country":"BE",
    "sg:address":"Rue D'enhaive 305",
    "sg:city":"Namur (jambes)",
    "sg:classifiers":[
        {
            "category":"Real Estate",
            "subcategory":"Real Estate Services",
            "type":"Services"
        }
    ],
    "sg:phone":"+32 81 30 33 94",
    "sg:postcode":"5100",
    "sg:province":"Namur",
    "wof:name":"Euro Transaction",
    "wof:placetype":"venue"
},
  "geometry": {"coordinates":[4.8872580528,50.4613761902],"type":"Point"}
}