{
  "type": "Feature",
  "properties": {
    "addr:full":"Rue Du Lambais 48 Grez-doiceau Brabant Wallon 1390",
    "addr:housenumber":"48",
    "addr:postcode":"1390",
    "addr:street":"Rue Du Lambais",
    "iso:country":"BE",
    "sg:address":"Rue Du Lambais 48",
    "sg:city":"Grez-doiceau",
    "sg:classifiers":[
        {
            "category":"Shopping",
            "subcategory":"Florist",
            "type":"Retail Goods"
        }
    ],
    "sg:phone":"+32 10 84 42 78",
    "sg:postcode":"1390",
    "sg:province":"Brabant Wallon",
    "wof:name":"Fleurs De Marie (les)",
    "wof:placetype":"venue"
},
  "geometry": {"coordinates":[4.6958799362,50.7423591614],"type":"Point"}
}