{
  "type": "Feature",
  "properties": {
    "iso:country":"BE",
    "sg:address":"Roterijstraat 41",
    "sg:city":"Waregem",
    "sg:classifiers":[
        {
            "category":"Personal",
            "subcategory":"Beauty Salon",
            "type":"Services"
        }
    ],
    "sg:phone":"+32 56 61 13 50",
    "sg:postcode":"8790",
    "sg:province":"West-Vlaanderen",
    "sg:tags":[
        "lady",
        "-",
        "hairdressing"
    ],
    "wof:name":"Clo\u00eb",
    "wof:placetype":"venue"
},
  "geometry": {"coordinates":[3.409569025,50.8895835876],"type":"Point"}
}