{
  "type": "Feature",
  "properties": {
    "addr:full":"Rue De N\u00c9chin 82 Tournai Hainaut 7520",
    "addr:housenumber":"82",
    "addr:postcode":"7520",
    "addr:street":"Rue De Ne\u0301Chin",
    "iso:country":"BE",
    "sg:address":"Rue De N\u00c9chin 82",
    "sg:city":"Tournai",
    "sg:orig_category":"Houtbewerking and -behandeling",
    "sg:phone":"+32 69 36 01 63",
    "sg:postcode":"7520",
    "sg:province":"Hainaut",
    "wof:name":"Decowall",
    "wof:placetype":"venue"
},
  "geometry": {"coordinates":[3.2755119801,50.6488609314],"type":"Point"}
}