{
  "type": "Feature",
  "properties": {
    "iso:country":"BE",
    "sg:address":"Pl Des Braban\u00e7ons 1",
    "sg:city":"Louvain-la-neuve",
    "sg:classifiers":[
        {
            "category":"Travel",
            "subcategory":"Hotels & Motels",
            "type":"Entertainment"
        }
    ],
    "sg:phone":"+32 10 45 15 85",
    "sg:postcode":"1348",
    "sg:province":"Brabant Wallon",
    "sg:tags":[
        "hotels",
        "business",
        "restaurant"
    ],
    "wof:name":"Ruco Sprl",
    "wof:placetype":"venue"
},
  "geometry": {"coordinates":[4.616256237,50.6686515808],"type":"Point"}
}