{
  "type": "Feature",
  "properties": {
    "addr:full":"Rue Hamente 29 Verlaine Li\u00e8ge 4537",
    "addr:housenumber":"29",
    "addr:postcode":"4537",
    "addr:street":"Rue Hamente",
    "iso:country":"BE",
    "sg:address":"Rue Hamente 29",
    "sg:city":"Verlaine",
    "sg:orig_category":"Artsen and specialisten",
    "sg:phone":"+32 4 259 54 86",
    "sg:postcode":"4537",
    "sg:province":"Li\u00e8ge",
    "wof:name":"C\u00c9cile Andris",
    "wof:placetype":"venue"
},
  "geometry": {"coordinates":[5.3175568581,50.6044158936],"type":"Point"}
}