{
  "type": "Feature",
  "properties": {
    "iso:country":"BE",
    "sg:address":"'t Hoge 2",
    "sg:city":"Kortrijk",
    "sg:orig_category":"Benzinestations and brandstoffen Herstellingen and onderhoud van auto's",
    "sg:phone":"+32 56 22 24 10",
    "sg:postcode":"8500",
    "sg:province":"West-Vlaanderen",
    "wof:name":"Garage Ameye Jan",
    "wof:placetype":"venue"
},
  "geometry": {"coordinates":[3.2838509083,50.8012771606],"type":"Point"}
}