{
  "type": "Feature",
  "properties": {
    "iso:country":"BE",
    "sg:address":"Rue De Tournai 66ba",
    "sg:city":"Tournai",
    "sg:orig_category":"M\u00e9decins and sp\u00e9cialistes",
    "sg:phone":"+32 69 35 32 40",
    "sg:postcode":"7520",
    "sg:province":"Hainaut",
    "wof:name":"I. Fockedey",
    "wof:placetype":"venue"
},
  "geometry": {"coordinates":[3.2897439003,50.6425743103],"type":"Point"}
}