{
  "type": "Feature",
  "properties": {
    "addr:full":"Blankenbergestraat 38 Gent Oost-Vlaanderen 9000",
    "addr:housenumber":"38",
    "addr:postcode":"9000",
    "addr:street":"Blankenbergestraat;Oost-Vlaanderen",
    "iso:country":"BE",
    "sg:address":"Blankenbergestraat 38",
    "sg:city":"Gent",
    "sg:classifiers":[
        {
            "category":"Real Estate",
            "subcategory":"Real Estate Operator",
            "type":"Services"
        }
    ],
    "sg:phone":"+32 9 280 08 15",
    "sg:postcode":"9000",
    "sg:province":"Oost-Vlaanderen",
    "sg:tags":[
        "sample",
        "brochure",
        "-",
        "distributors"
    ],
    "wof:name":"Distri Gent & Rand Cvoha",
    "wof:placetype":"venue"
},
  "geometry": {"coordinates":[3.7145619392,51.0371398926],"type":"Point"}
}