{
  "type": "Feature",
  "properties": {
    "addr:full":"Jacob Besagestraat 29 Oostende West-Vlaanderen 8400",
    "addr:housenumber":"29",
    "addr:postcode":"8400",
    "addr:street":"Besagestraat",
    "iso:country":"BE",
    "sg:address":"Jacob Besagestraat 29",
    "sg:city":"Oostende",
    "sg:orig_category":"Pain, p\u00e2tisseries and confiseries",
    "sg:phone":"+32 59 32 22 36",
    "sg:postcode":"8400",
    "sg:province":"West-Vlaanderen",
    "wof:name":"Gabriel De Schoemaeker",
    "wof:placetype":"venue"
},
  "geometry": {"coordinates":[2.9126999378,51.2312583923],"type":"Point"}
}