{
  "type": "Feature",
  "properties": {
    "iso:country":"BE",
    "sg:address":"Van Aertselaerstraat 53",
    "sg:city":"Hoogstraten",
    "sg:orig_category":"V\u00e9t\u00e9rinaires",
    "sg:phone":"+32 3 314 48 20",
    "sg:postcode":"2320",
    "sg:province":"Antwerpen",
    "wof:name":"Augustinus Van Erck",
    "wof:placetype":"venue"
},
  "geometry": {"coordinates":[4.763504982,51.4115524292],"type":"Point"}
}