{
  "type": "Feature",
  "properties": {
    "iso:country":"BE",
    "sg:address":"Rue Des Tanneurs 14",
    "sg:city":"Marche-en-famenne",
    "sg:orig_category":"Diverse grafische activiteiten Reclamebureaus",
    "sg:phone":"+32 84 31 17 17",
    "sg:postcode":"6900",
    "sg:province":"Luxembourg",
    "wof:name":"Art & Publicit\u00c9 Templiers",
    "wof:placetype":"venue"
},
  "geometry": {"coordinates":[5.3462867737,50.2266845703],"type":"Point"}
}