{
  "type": "Feature",
  "properties": {
    "iso:country":"BE",
    "sg:address":"Velodroomstraat 21",
    "sg:city":"Evergem",
    "sg:orig_category":"Epiceries",
    "sg:phone":"+32 9 253 11 03",
    "sg:postcode":"9940",
    "sg:province":"Oost-Vlaanderen",
    "wof:name":"Nicolas Van Hoecke",
    "wof:placetype":"venue"
},
  "geometry": {"coordinates":[3.7060270309,51.1114845276],"type":"Point"}
}