{
  "type": "Feature",
  "properties": {
    "addr:full":"Zinkstr. 2 Halle Vlaams-Brabant 1502",
    "addr:housenumber":"2;1502",
    "addr:street":"Zinkstr.",
    "iso:country":"BE",
    "sg:address":"Zinkstr. 2",
    "sg:city":"Halle",
    "sg:classifiers":[
        {
            "category":"Shopping",
            "subcategory":"Computers & Home Electronics",
            "type":"Retail Goods"
        }
    ],
    "sg:phone":"+32 2 358 35 75",
    "sg:postcode":"1502",
    "sg:province":"Vlaams-Brabant",
    "sg:tags":[
        "equipment",
        "electrical",
        "component",
        "electric",
        "electronic"
    ],
    "wof:name":"Automation Nv",
    "wof:placetype":"venue"
},
  "geometry": {"coordinates":[4.2074689865,50.7266998291],"type":"Point"}
}