{
  "type": "Feature",
  "properties": {
    "addr:full":"Avenue Louise 149 Box 16 Bruxelles (ixelles) Bruxelles-Capitale 1050",
    "addr:housenumber":"149 box 16",
    "addr:postcode":"1050",
    "addr:street":"Avenue Louise",
    "iso:country":"BE",
    "sg:address":"Avenue Louise 149 Box 16",
    "sg:city":"Bruxelles (ixelles)",
    "sg:classifiers":[
        {
            "category":"Professional",
            "subcategory":"Lawyer & Legal Services",
            "type":"Services"
        }
    ],
    "sg:phone":"+32 2 542 09 66",
    "sg:postcode":"1050",
    "sg:province":"Bruxelles-Capitale",
    "wof:name":"Slotboom Marco M M",
    "wof:placetype":"venue"
},
  "geometry": {"coordinates":[4.3618850708,50.8286476135],"type":"Point"}
}