{
  "type": "Feature",
  "properties": {
    "addr:full":"Place Louis De Brouck\u00c8re 9 Ch\u00c2telet Hainaut 6200",
    "addr:housenumber":"9",
    "addr:postcode":"6200",
    "addr:street":"Place Louis De Broucke\u0300Re",
    "iso:country":"BE",
    "sg:address":"Place Louis De Brouck\u00c8re 9",
    "sg:city":"Ch\u00c2telet",
    "sg:orig_category":"Bloemen and planten",
    "sg:phone":"+32 71 38 72 60",
    "sg:postcode":"6200",
    "sg:province":"Hainaut",
    "wof:name":"Dites-le Avec Des Fleures",
    "wof:placetype":"venue"
},
  "geometry": {"coordinates":[4.5192117691,50.4176254272],"type":"Point"}
}