{
  "type": "Feature",
  "properties": {
    "iso:country":"BE",
    "sg:address":"Wissekerkelaan 23",
    "sg:city":"Kruibeke (bazel)",
    "sg:classifiers":[
        {
            "category":"Professional",
            "subcategory":"Accounting & Tax Preparation",
            "type":"Services"
        }
    ],
    "sg:phone":"+32 3 774 19 54",
    "sg:postcode":"9150",
    "sg:province":"Oost-Vlaanderen",
    "sg:tags":[
        "accountant"
    ],
    "wof:name":"Teugels H",
    "wof:placetype":"venue"
},
  "geometry": {"coordinates":[4.2970299721,51.1415863037],"type":"Point"}
}