{
  "type": "Feature",
  "properties": {
    "addr:full":"Kortrijksesteenweg 320a Harelbeke West-Vlaanderen 8530",
    "addr:housenumber":"320a",
    "addr:postcode":"8530",
    "addr:street":"Kortrijksesteenweg",
    "iso:country":"BE",
    "sg:address":"Kortrijksesteenweg 320a",
    "sg:city":"Harelbeke",
    "sg:classifiers":[
        {
            "category":"Retail",
            "subcategory":"Auto Repair",
            "type":"Services"
        }
    ],
    "sg:phone":"+32 56 72 59 09",
    "sg:postcode":"8530",
    "sg:province":"West-Vlaanderen",
    "sg:tags":[
        "garage"
    ],
    "wof:name":"Lexus West Flanders Nv",
    "wof:placetype":"venue"
},
  "geometry": {"coordinates":[3.2915771008,50.8430137634],"type":"Point"}
}