{
  "type": "Feature",
  "properties": {
    "addr:full":"Rue Des Ecoliers 77 Seraing Li\u00e8ge 4100",
    "addr:housenumber":"77",
    "addr:postcode":"4100",
    "addr:street":"Rue Des Ecoliers",
    "iso:country":"BE",
    "sg:address":"Rue Des Ecoliers 77",
    "sg:city":"Seraing",
    "sg:orig_category":"Boekhouders",
    "sg:phone":"+32 4 338 89 01",
    "sg:postcode":"4100",
    "sg:province":"Li\u00e8ge",
    "wof:name":"Dominique Dantinne",
    "wof:placetype":"venue"
},
  "geometry": {"coordinates":[5.5085349083,50.5970649719],"type":"Point"}
}