{
  "type": "Feature",
  "properties": {
    "iso:country":"BE",
    "sg:address":"Bien 6",
    "sg:city":"Hamont-achel",
    "sg:orig_category":"Auto-\u00e9coles",
    "sg:phone":"+32 11 64 75 15",
    "sg:postcode":"3930",
    "sg:province":"Limburg",
    "wof:name":"Autorijschool Hendriks",
    "wof:placetype":"venue"
},
  "geometry": {"coordinates":[5.4722452164,51.2535095215],"type":"Point"}
}