{
  "type": "Feature",
  "properties": {
    "iso:country":"BE",
    "sg:address":"Rue Burenville 110",
    "sg:city":"Li\u00c8ge",
    "sg:orig_category":"Installation de menuiserie m\u00e9tallique. Services fun\u00e9raires",
    "sg:phone":"+32 4 224 04 43",
    "sg:postcode":"4000",
    "sg:province":"Li\u00e8ge",
    "wof:name":"Francis Peuteman",
    "wof:placetype":"venue"
},
  "geometry": {"coordinates":[5.5413761139,50.6398010254],"type":"Point"}
}