{
  "type": "Feature",
  "properties": {
    "iso:country":"BE",
    "sg:address":"Rue De Virton 9",
    "sg:city":"Etalle",
    "sg:classifiers":[
        {
            "category":"Health Services",
            "subcategory":"Doctor",
            "type":"Services"
        }
    ],
    "sg:phone":"+32 63 45 52 83",
    "sg:postcode":"6740",
    "sg:province":"Luxembourg",
    "sg:tags":[
        "medicinephysicians",
        "surgeon"
    ],
    "wof:name":"Claude Anne-marie",
    "wof:placetype":"venue"
},
  "geometry": {"coordinates":[5.6000561714,49.6714134216],"type":"Point"}
}