{
  "type": "Feature",
  "properties": {
    "addr:full":"Zuurbemdesteenweg 10 Kortenaken (hoeleden) Vlaams-Brabant 3471",
    "addr:housenumber":"10",
    "addr:postcode":"3471",
    "addr:street":"Zuurbemdesteenweg",
    "iso:country":"BE",
    "sg:address":"Zuurbemdesteenweg 10",
    "sg:city":"Kortenaken (hoeleden)",
    "sg:classifiers":[
        {
            "category":"Health Services",
            "subcategory":"Health Practitioner",
            "type":"Services"
        }
    ],
    "sg:phone":"+32 16 77 08 51",
    "sg:postcode":"3471",
    "sg:province":"Vlaams-Brabant",
    "sg:tags":[
        "psychologist"
    ],
    "wof:name":"Bertrand I",
    "wof:placetype":"venue"
},
  "geometry": {"coordinates":[4.983150959,50.8672676086],"type":"Point"}
}