{
  "type": "Feature",
  "properties": {
    "iso:country":"BE",
    "sg:address":"Linde 76",
    "sg:city":"Evergem",
    "sg:orig_category":"Eleveurs de bovins",
    "sg:phone":"+32 9 357 37 46",
    "sg:postcode":"9940",
    "sg:province":"Oost-Vlaanderen",
    "wof:name":"Antoine Van Kerckvoorde",
    "wof:placetype":"venue"
},
  "geometry": {"coordinates":[3.6487700939,51.1250495911],"type":"Point"}
}