{
  "type": "Feature",
  "properties": {
    "addr:full":"Brusselstraat 118 Dilbeek Vlaams-Brabant 1700",
    "addr:housenumber":"118",
    "addr:postcode":"1700",
    "addr:street":"Brusselstraat",
    "iso:country":"BE",
    "sg:address":"Brusselstraat 118",
    "sg:city":"Dilbeek",
    "sg:orig_category":"Installatie van houten of kunststof schrijnwerk",
    "sg:phone":"+32 2 453 91 99",
    "sg:postcode":"1700",
    "sg:province":"Vlaams-Brabant",
    "wof:name":"Lichtert",
    "wof:placetype":"venue"
},
  "geometry": {"coordinates":[4.2396998405,50.876159668],"type":"Point"}
}