{
  "type": "Feature",
  "properties": {
    "addr:full":"Avenue Des Croix De Guerre 197b10 Brussel/bruxelles Bruxelles-Capitale 1120",
    "addr:housenumber":"197b10",
    "addr:postcode":"1120",
    "addr:street":"Avenue Des Croix De Guerre;/",
    "iso:country":"BE",
    "sg:address":"Avenue Des Croix De Guerre 197b10",
    "sg:city":"Brussel/bruxelles",
    "sg:classifiers":[
        {
            "category":"Manufacturing",
            "subcategory":"Textiles",
            "type":"Manufacturing & Wholesale Goods"
        }
    ],
    "sg:phone":"+32 2 245 90 95",
    "sg:postcode":"1120",
    "sg:province":"Bruxelles-Capitale",
    "wof:name":"Martha Hanquet",
    "wof:placetype":"venue"
},
  "geometry": {"coordinates":[4.3854432106,50.8917655945],"type":"Point"}
}