{
  "type": "Feature",
  "properties": {
    "iso:country":"BE",
    "sg:address":"Christoffelweg 4",
    "sg:city":"Evergem",
    "sg:orig_category":"Artsen and specialisten",
    "sg:phone":"+32 9 253 93 93",
    "sg:postcode":"9940",
    "sg:province":"Oost-Vlaanderen",
    "wof:name":"W. Verstringe",
    "wof:placetype":"venue"
},
  "geometry": {"coordinates":[3.7035329342,51.1087799072],"type":"Point"}
}