{
  "type": "Feature",
  "properties": {
    "addr:full":"Rue De La Station 144 Ch\u00c2telet Hainaut 6200",
    "addr:housenumber":"144",
    "addr:postcode":"6200",
    "addr:street":"Rue De La Station",
    "iso:country":"BE",
    "sg:address":"Rue De La Station 144",
    "sg:city":"Ch\u00c2telet",
    "sg:orig_category":"Boekhandels Kantoormateriaal Krantenwinkels Rookartikelen",
    "sg:phone":"+32 71 38 22 08",
    "sg:postcode":"6200",
    "sg:province":"Hainaut",
    "wof:name":"Maison Le Parchemin",
    "wof:placetype":"venue"
},
  "geometry": {"coordinates":[4.5286221504,50.4050674438],"type":"Point"}
}