{
  "type": "Feature",
  "properties": {
    "iso:country":"BE",
    "sg:address":"Avenue Du Centre Sportif",
    "sg:city":"Wavre",
    "sg:orig_category":"Cafetarias and selfservice restaurants",
    "sg:phone":"+32 10 22 74 34",
    "sg:postcode":"1300",
    "sg:province":"Brabant Wallon",
    "wof:name":"Sponsor",
    "wof:placetype":"venue"
},
  "geometry": {"coordinates":[4.6182518005,50.7222747803],"type":"Point"}
}