{
  "type": "Feature",
  "properties": {
    "iso:country":"BE",
    "sg:address":"Avenue De La Lib\u00e9ration 29",
    "sg:city":"Couvin",
    "sg:classifiers":[
        {
            "category":"Retail",
            "subcategory":"Driving School",
            "type":"Services"
        }
    ],
    "sg:phone":"+32 60 34 49 26",
    "sg:postcode":"5660",
    "sg:province":"Namur",
    "sg:tags":[
        "automobile",
        "officially",
        "-",
        "recognized"
    ],
    "wof:name":"Auto Ecole Willem Sprl",
    "wof:placetype":"venue"
},
  "geometry": {"coordinates":[4.4879198074,50.0552215576],"type":"Point"}
}