{
  "type": "Feature",
  "properties": {
    "iso:country":"BE",
    "sg:address":"Rue Gaucheret 124a",
    "sg:city":"Bruxelles (schaerbeek)",
    "sg:classifiers":[
        {
            "category":"Education",
            "subcategory":"School",
            "type":"Public Place"
        }
    ],
    "sg:phone":"+32 2 201 16 76",
    "sg:postcode":"1030",
    "sg:province":"Bruxelles-Capitale",
    "sg:tags":[
        "primary"
    ],
    "wof:name":"Ecole Communale No 8",
    "wof:placetype":"venue"
},
  "geometry": {"coordinates":[4.3612427711,50.8650665283],"type":"Point"}
}