{
  "type": "Feature",
  "properties": {
    "addr:full":"Chauss\u00c9e De Bruxelles 639 Les Bons Villers Hainaut 6210",
    "addr:housenumber":"639",
    "addr:postcode":"6210",
    "addr:street":"Chausse\u0301E De Bruxelles",
    "iso:country":"BE",
    "sg:address":"Chauss\u00c9e De Bruxelles 639",
    "sg:city":"Les Bons Villers",
    "sg:orig_category":"Herstellingen and onderhoud van auto's Voertuigen",
    "sg:phone":"+32 71 85 30 46",
    "sg:postcode":"6210",
    "sg:province":"Hainaut",
    "wof:name":"Concessionnaire Mazda Garage Rucquoy",
    "wof:placetype":"venue"
},
  "geometry": {"coordinates":[4.4511561394,50.5378227234],"type":"Point"}
}