{
  "type": "Feature",
  "properties": {
    "addr:full":"Bollaarstraat 10 Lier Antwerpen 2500",
    "addr:housenumber":"10",
    "addr:postcode":"2500",
    "addr:street":"Bollaarstraat",
    "iso:country":"BE",
    "sg:address":"Bollaarstraat 10",
    "sg:city":"Lier",
    "sg:orig_category":"Installation de menuiserie m\u00e9tallique",
    "sg:phone":"+32 3 480 64 62",
    "sg:postcode":"2500",
    "sg:province":"Antwerpen",
    "wof:name":"Van Den Bergh",
    "wof:placetype":"venue"
},
  "geometry": {"coordinates":[4.553041935,51.142742157],"type":"Point"}
}