{
  "type": "Feature",
  "properties": {
    "iso:country":"BE",
    "sg:address":"Avenue De L\u00b4observatoire 217b51",
    "sg:city":"Li\u00c8ge",
    "sg:orig_category":"Installation de menuiserie en bois and plastique",
    "sg:phone":"+32 4 254 01 27",
    "sg:postcode":"4000",
    "sg:province":"Li\u00e8ge",
    "wof:name":"E.v.m.",
    "wof:placetype":"venue"
},
  "geometry": {"coordinates":[5.5641198158,50.6251945496],"type":"Point"}
}