{
  "type": "Feature",
  "properties": {
    "addr:full":"Nijverheidsstraat 30 Oevel Antwerpen 2260",
    "addr:housenumber":"30",
    "addr:postcode":"2260",
    "addr:street":"Nijverheidsstraat",
    "iso:country":"BE",
    "sg:address":"Nijverheidsstraat 30",
    "sg:city":"Oevel",
    "sg:classifiers":[
        {
            "category":"Manufacturing",
            "subcategory":"Paper Products",
            "type":"Manufacturing & Wholesale Goods"
        }
    ],
    "sg:phone":"+32 14 24 16 11",
    "sg:postcode":"2260",
    "sg:province":"Antwerpen",
    "sg:tags":[
        "raw",
        "material",
        "preliminary",
        "plastic"
    ],
    "wof:name":"Bf Goodrich Performance Materials",
    "wof:placetype":"venue"
},
  "geometry": {"coordinates":[4.9054951668,51.1422386169],"type":"Point"}
}