{
  "type": "Feature",
  "properties": {
    "addr:full":"Grand\u00b4place 37 Walcourt Namur 5650",
    "addr:housenumber":"37",
    "addr:postcode":"5650",
    "addr:street":"Grand\u00b4Place",
    "iso:country":"BE",
    "sg:address":"Grand\u00b4place 37",
    "sg:city":"Walcourt",
    "sg:classifiers":[
        {
            "category":"Restaurant",
            "type":"Food & Drink"
        }
    ],
    "sg:phone":"+32 71 61 39 05",
    "sg:postcode":"5650",
    "sg:province":"Namur",
    "wof:name":"Le Capri",
    "wof:placetype":"venue"
},
  "geometry": {"coordinates":[4.4323620796,50.2521896362],"type":"Point"}
}