{
  "type": "Feature",
  "properties": {
    "addr:full":"Rue De Dinant 16 Verviers Li\u00e8ge 4800",
    "addr:housenumber":"16",
    "addr:postcode":"4800",
    "addr:street":"Rue De Dinant",
    "iso:country":"BE",
    "sg:address":"Rue De Dinant 16",
    "sg:city":"Verviers",
    "sg:classifiers":[
        {
            "category":"Professional",
            "type":"Services"
        }
    ],
    "sg:phone":"+32 87 22 09 86",
    "sg:postcode":"4800",
    "sg:province":"Li\u00e8ge",
    "sg:tags":[
        "equipment",
        "installation",
        "restaurants"
    ],
    "wof:name":"Boumans J",
    "wof:placetype":"venue"
},
  "geometry": {"coordinates":[5.8561358452,50.5874061584],"type":"Point"}
}