{
  "type": "Feature",
  "properties": {
    "addr:full":"Rue Zeecrabbe 79 Ukkel/uccle Bruxelles-Capitale 1180",
    "addr:housenumber":"79",
    "addr:postcode":"1180",
    "addr:street":"Rue Zeecrabbe;/",
    "iso:country":"BE",
    "sg:address":"Rue Zeecrabbe 79",
    "sg:city":"Ukkel/uccle",
    "sg:orig_category":"Jardinage",
    "sg:phone":"+32 2 374 02 86",
    "sg:postcode":"1180",
    "sg:province":"Bruxelles-Capitale",
    "wof:name":"Spegelaere B.",
    "wof:placetype":"venue"
},
  "geometry": {"coordinates":[4.3572540283,50.8060722351],"type":"Point"}
}