{
  "type": "Feature",
  "properties": {
    "iso:country":"BE",
    "sg:address":"Steenstratenlaan 9",
    "sg:city":"Kortrijk",
    "sg:classifiers":[
        {
            "category":"Recreation",
            "type":"Entertainment"
        }
    ],
    "sg:phone":"+32 56 21 41 03",
    "sg:postcode":"8500",
    "sg:province":"West-Vlaanderen",
    "sg:tags":[
        "diver",
        "amusement"
    ],
    "wof:name":"Striptease Angelino",
    "wof:placetype":"venue"
},
  "geometry": {"coordinates":[3.2775409222,50.8148765564],"type":"Point"}
}