{
  "type": "Feature",
  "properties": {
    "addr:full":"Tempelstraat 24 Gavere Oost-Vlaanderen 9890",
    "addr:housenumber":"24",
    "addr:postcode":"9890",
    "addr:street":"Tempelstraat",
    "iso:country":"BE",
    "sg:address":"Tempelstraat 24",
    "sg:city":"Gavere",
    "sg:orig_category":"Brood, gebak and snoepgoed",
    "sg:phone":"+32 9 384 34 06",
    "sg:postcode":"9890",
    "sg:province":"Oost-Vlaanderen",
    "wof:name":"Geert De Clercq",
    "wof:placetype":"venue"
},
  "geometry": {"coordinates":[3.6454560757,50.9183349609],"type":"Point"}
}