{
  "type": "Feature",
  "properties": {
    "addr:full":"Grauwe Torenwal 11 Bree (groot) Limburg 3960",
    "addr:housenumber":"11",
    "addr:postcode":"3960",
    "addr:street":"Grauwe Torenwal;Groot Limburg",
    "iso:country":"BE",
    "sg:address":"Grauwe Torenwal 11",
    "sg:city":"Bree (groot)",
    "sg:orig_category":"Maatschappelijke dienstverlening",
    "sg:phone":"+32 89 46 97 30",
    "sg:postcode":"3960",
    "sg:province":"Limburg",
    "wof:name":"Clb",
    "wof:placetype":"venue"
},
  "geometry": {"coordinates":[5.5994091034,51.1400413513],"type":"Point"}
}