{
  "type": "Feature",
  "properties": {
    "iso:country":"BE",
    "sg:address":"Vroentestraat 40",
    "sg:city":"Scherpenheuvel-zichem",
    "sg:orig_category":"Installation de menuiserie en bois and plastique",
    "sg:phone":"+32 13 77 72 70",
    "sg:postcode":"3270",
    "sg:province":"Vlaams-Brabant",
    "wof:name":"Danny Berghen",
    "wof:placetype":"venue"
},
  "geometry": {"coordinates":[4.9478178024,50.9631195068],"type":"Point"}
}