{
  "type": "Feature",
  "properties": {
    "iso:country":"BE",
    "sg:address":"Avenue Du G\u00e9n\u00e9ral De Gaulle 10",
    "sg:city":"Bruxelles (ixelles)",
    "sg:classifiers":[
        {
            "category":"Health Services",
            "subcategory":"Dentist",
            "type":"Services"
        }
    ],
    "sg:phone":"+32 2 647 03 57",
    "sg:postcode":"1050",
    "sg:province":"Bruxelles-Capitale",
    "wof:name":"Mercier Edith",
    "wof:placetype":"venue"
},
  "geometry": {"coordinates":[4.3709378242,50.8267593384],"type":"Point"}
}