{
  "type": "Feature",
  "properties": {
    "iso:country":"BE",
    "sg:address":"Rue De Mons 160",
    "sg:city":"Qui\u00e9vrain",
    "sg:classifiers":[
        {
            "category":"Home & Garden",
            "subcategory":"Home Furnishings",
            "type":"Retail Goods"
        }
    ],
    "sg:phone":"+32 65 45 76 05",
    "sg:postcode":"7380",
    "sg:province":"Hainaut",
    "sg:tags":[
        "-",
        "furniture"
    ],
    "wof:name":"Expo-meubles",
    "wof:placetype":"venue"
},
  "geometry": {"coordinates":[3.6979489326,50.4092063904],"type":"Point"}
}