{
  "type": "Feature",
  "properties": {
    "addr:full":"Rahier 36 Stoumont Li\u00e8ge 4987",
    "addr:housenumber":"36",
    "addr:postcode":"4987",
    "addr:street":"Rahier",
    "iso:country":"BE",
    "sg:address":"Rahier 36",
    "sg:city":"Stoumont",
    "sg:orig_category":"Agences de presse",
    "sg:phone":"+32 80 78 59 41",
    "sg:postcode":"4987",
    "sg:province":"Li\u00e8ge",
    "wof:name":"Olivier Gaspard",
    "wof:placetype":"venue"
},
  "geometry": {"coordinates":[5.8098897934,50.4056663513],"type":"Point"}
}