{
  "type": "Feature",
  "properties": {
    "addr:full":"Rue Des Canonniers 8 Nivelles Brabant Wallon 1400",
    "addr:housenumber":"8",
    "addr:postcode":"1400",
    "addr:street":"Rue Des Canonniers",
    "iso:country":"BE",
    "sg:address":"Rue Des Canonniers 8",
    "sg:city":"Nivelles",
    "sg:classifiers":[
        {
            "category":"Health Services",
            "subcategory":"Health Practitioner",
            "type":"Services"
        }
    ],
    "sg:phone":"+32 67 21 84 24",
    "sg:postcode":"1400",
    "sg:province":"Brabant Wallon",
    "sg:tags":[
        "physiotherapist"
    ],
    "wof:name":"Deswaef Tanguy",
    "wof:placetype":"venue"
},
  "geometry": {"coordinates":[4.3248910904,50.5999946594],"type":"Point"}
}