{
  "type": "Feature",
  "properties": {
    "addr:full":"8 Boulevard Des Nerviens 7500 Tournai 8",
    "addr:housenumber":"8",
    "addr:postcode":"7500",
    "addr:street":"Boulevard Des Nerviens",
    "iso:country":"BE",
    "sg:address":"8",
    "sg:city":"Boulevard Des Nerviens 7500 Tournai",
    "sg:classifiers":[
        {
            "category":"Travel",
            "subcategory":"Hotels & Motels",
            "type":"Entertainment"
        }
    ],
    "sg:phone":"+32 69 22 43 15",
    "sg:postcode":"8",
    "sg:tags":[
        "hotels",
        "business",
        "restaurant"
    ],
    "wof:name":"Taverne Binchoise Sprl",
    "wof:placetype":"venue"
},
  "geometry": {"coordinates":[3.3910779953,50.6138572693],"type":"Point"}
}