{
  "type": "Feature",
  "properties": {
    "iso:country":"BE",
    "sg:address":"Vuurkruisenlaan 40a",
    "sg:city":"Wijnegem",
    "sg:classifiers":[
        {
            "category":"Building & Trades",
            "subcategory":"Pest Control",
            "type":"Services"
        }
    ],
    "sg:phone":"+32 3 353 82 12",
    "sg:postcode":"2110",
    "sg:province":"Antwerpen",
    "sg:tags":[
        "painting",
        "contractor"
    ],
    "wof:name":"Maes K",
    "wof:placetype":"venue"
},
  "geometry": {"coordinates":[4.5117211342,51.228263855],"type":"Point"}
}