{
  "type": "Feature",
  "properties": {
    "addr:full":"Sint-margriete-houtemlaan 18 Kortrijk West-Vlaanderen 8500",
    "addr:housenumber":"18",
    "addr:postcode":"8500",
    "addr:street":"Sint-Margriete-Houtemlaan",
    "iso:country":"BE",
    "sg:address":"Sint-margriete-houtemlaan 18",
    "sg:city":"Kortrijk",
    "sg:classifiers":[
        {
            "category":"Manufacturing",
            "subcategory":"Textiles",
            "type":"Manufacturing & Wholesale Goods"
        }
    ],
    "sg:phone":"+32 56 22 02 65",
    "sg:postcode":"8500",
    "sg:province":"West-Vlaanderen",
    "sg:tags":[
        "spinning",
        "weaving",
        "mill"
    ],
    "wof:name":"Oosterlynck-servais",
    "wof:placetype":"venue"
},
  "geometry": {"coordinates":[3.2810609341,50.8137664795],"type":"Point"}
}