{
  "type": "Feature",
  "properties": {
    "iso:country":"BE",
    "sg:address":"Liersesteenweg 98",
    "sg:city":"Ranst (emblem)",
    "sg:classifiers":[
        {
            "category":"Professional",
            "subcategory":"Management & Consulting",
            "type":"Services"
        }
    ],
    "sg:phone":"+32 3 480 80 44",
    "sg:postcode":"2520",
    "sg:province":"Antwerpen",
    "sg:tags":[
        "-",
        "processing",
        "data",
        "consultant"
    ],
    "wof:name":"E D M Nv",
    "wof:placetype":"venue"
},
  "geometry": {"coordinates":[4.5824108124,51.1536941528],"type":"Point"}
}