{
  "type": "Feature",
  "properties": {
    "addr:full":"Rue Jean G\u00e9rard Eggericx 28 Bruxelles (woluwe-saint-pierre) Bruxelles-Capitale 1150",
    "addr:housenumber":"28",
    "addr:postcode":"1150",
    "addr:street":"Rue Jean Ge\u0301Rard Eggericx",
    "iso:country":"BE",
    "sg:address":"Rue Jean G\u00e9rard Eggericx 28",
    "sg:city":"Bruxelles (woluwe-saint-pierre)",
    "sg:classifiers":[
        {
            "category":"Health Services",
            "subcategory":"Hospital",
            "type":"Services"
        }
    ],
    "sg:phone":"+32 2 762 58 15",
    "sg:postcode":"1150",
    "sg:province":"Bruxelles-Capitale",
    "wof:name":"chien Vert (le) Service De Sant\u00e9 Mentale Agr\u00e9e Par La Cocof",
    "wof:placetype":"venue"
},
  "geometry": {"coordinates":[4.417992115,50.8379135132],"type":"Point"}
}