{
  "type": "Feature",
  "properties": {
    "addr:full":"Rue D'horrues 195 Braine-le-comte Hainaut 7090",
    "addr:housenumber":"195",
    "addr:postcode":"7090",
    "addr:street":"Rue D'Horrues",
    "iso:country":"BE",
    "sg:address":"Rue D'horrues 195",
    "sg:city":"Braine-le-comte",
    "sg:orig_category":"Artiesten and kunstenaars",
    "sg:phone":"+32 67 55 51 22",
    "sg:postcode":"7090",
    "sg:province":"Hainaut",
    "wof:name":"Alain Deplechin",
    "wof:placetype":"venue"
},
  "geometry": {"coordinates":[4.0905909538,50.6249694824],"type":"Point"}
}