{
  "type": "Feature",
  "properties": {
    "addr:full":". Geel Antwerpen 2440",
    "addr:postcode":"2440",
    "iso:country":"BE",
    "sg:address":".",
    "sg:city":"Geel",
    "sg:orig_category":"Apotheken",
    "sg:phone":"+32 900 10 500",
    "sg:postcode":"2440",
    "sg:province":"Antwerpen",
    "wof:name":"Apothekers Van Wacht",
    "wof:placetype":"venue"
},
  "geometry": {"coordinates":[4.9906659126,51.1610794067],"type":"Point"}
}