{
  "type": "Feature",
  "properties": {
    "addr:full":"Klein Bien 30 Hamont-achel Limburg 3930",
    "addr:housenumber":"30",
    "addr:postcode":"3930",
    "addr:street":"Klein Bien",
    "iso:country":"BE",
    "sg:address":"Klein Bien 30",
    "sg:city":"Hamont-achel",
    "sg:orig_category":"Artistes ind\u00e9pendants. Salles de spectacles",
    "sg:phone":"+32 11 64 44 64",
    "sg:postcode":"3930",
    "sg:province":"Limburg",
    "wof:name":"Rene Moret",
    "wof:placetype":"venue"
},
  "geometry": {"coordinates":[5.471848011,51.2514572144],"type":"Point"}
}