{
  "type": "Feature",
  "properties": {
    "addr:full":"Dorpsstraat 125 Damme West-Vlaanderen 8340",
    "addr:housenumber":"125",
    "addr:postcode":"8340",
    "addr:street":"Dorpsstraat",
    "iso:country":"BE",
    "sg:address":"Dorpsstraat 125",
    "sg:city":"Damme",
    "sg:orig_category":"Banken and kredietinstellingen",
    "sg:phone":"+32 50 35 34 80",
    "sg:postcode":"8340",
    "sg:province":"West-Vlaanderen",
    "wof:name":"Kbc",
    "wof:placetype":"venue"
},
  "geometry": {"coordinates":[3.3217949867,51.2016792297],"type":"Point"}
}