{
  "type": "Feature",
  "properties": {
    "addr:full":"Rue De La Ruche 19 Brussel Bruxelles-Capitale 1030",
    "addr:housenumber":"19",
    "addr:postcode":"1030",
    "addr:street":"Rue De La Ruche",
    "iso:country":"BE",
    "sg:address":"Rue De La Ruche 19",
    "sg:city":"Brussel",
    "sg:orig_category":"Woningbouw",
    "sg:phone":"+32 2 216 15 12",
    "sg:postcode":"1030",
    "sg:province":"Bruxelles-Capitale",
    "wof:name":"Guns",
    "wof:placetype":"venue"
},
  "geometry": {"coordinates":[4.3737878799,50.8626480103],"type":"Point"}
}