{
  "type": "Feature",
  "properties": {
    "iso:country":"BE",
    "sg:address":"Avenue Rogier 400",
    "sg:city":"Schaarbeek/schaerbeek",
    "sg:orig_category":"V\u00eatements sur mesure Fab. V\u00eatements. V\u00eatements de mariage and c\u00e9r\u00e9monies",
    "sg:phone":"+32 2 705 77 03",
    "sg:postcode":"1030",
    "sg:province":"Bruxelles-Capitale",
    "wof:name":"Creation Stepha",
    "wof:placetype":"venue"
},
  "geometry": {"coordinates":[4.3969631195,50.8554534912],"type":"Point"}
}