{
  "type": "Feature",
  "properties": {
    "addr:full":"Rue De La Cr\u00eate 32 Flobecq Hainaut 7880",
    "addr:housenumber":"32",
    "addr:postcode":"7880",
    "addr:street":"Rue De La Cre\u0302Te;Hainaut",
    "iso:country":"BE",
    "sg:address":"Rue De La Cr\u00eate 32",
    "sg:city":"Flobecq",
    "sg:classifiers":[
        {
            "category":"Education",
            "subcategory":"School",
            "type":"Public Place"
        }
    ],
    "sg:phone":"+32 68 44 66 50",
    "sg:postcode":"7880",
    "sg:province":"Hainaut",
    "sg:tags":[
        "primary"
    ],
    "wof:name":"Ecole Fondamentale Autonome De La Communaut\u00e9 Fran\u00e7aise",
    "wof:placetype":"venue"
},
  "geometry": {"coordinates":[3.739356041,50.7336120605],"type":"Point"}
}