{
  "type": "Feature",
  "properties": {
    "iso:country":"BE",
    "sg:address":"De Schiervelstraat 39",
    "sg:city":"Tongeren",
    "sg:orig_category":"Antiek",
    "sg:phone":"+32 12 23 19 46",
    "sg:postcode":"3700",
    "sg:province":"Limburg",
    "wof:name":"Huis Claes-gielen",
    "wof:placetype":"venue"
},
  "geometry": {"coordinates":[5.4684038162,50.7815475464],"type":"Point"}
}