{
  "type": "Feature",
  "properties": {
    "addr:full":"Joseph Smeetslaan 96 Maasmechelen Limburg 3630",
    "addr:housenumber":"96",
    "addr:postcode":"3630",
    "addr:street":"Joseph Smeetslaan",
    "iso:country":"BE",
    "sg:address":"Joseph Smeetslaan 96",
    "sg:city":"Maasmechelen",
    "sg:orig_category":"Installation de menuiserie en bois and plastique. Installation de menuiserie m\u00e9tallique. Quincailler",
    "sg:phone":"+32 89 76 06 86",
    "sg:postcode":"3630",
    "sg:province":"Limburg",
    "wof:name":"Dubois",
    "wof:placetype":"venue"
},
  "geometry": {"coordinates":[5.6894168854,50.9668693542],"type":"Point"}
}