{
  "type": "Feature",
  "properties": {
    "addr:full":"Boulevard Du Midi 4 Bruxelles Bruxelles-Capitale 1000",
    "addr:housenumber":"4",
    "addr:postcode":"1000",
    "addr:street":"Boulevard Du Midi",
    "iso:country":"BE",
    "sg:address":"Boulevard Du Midi 4",
    "sg:city":"Bruxelles",
    "sg:classifiers":[
        {
            "category":"Bus Station",
            "type":"Transportation"
        }
    ],
    "sg:phone":"+32 2 513 30 01",
    "sg:postcode":"1000",
    "sg:province":"Bruxelles-Capitale",
    "sg:tags":[
        "automobile",
        "-",
        "transport"
    ],
    "wof:name":"Car-sol",
    "wof:placetype":"venue"
},
  "geometry": {"coordinates":[4.3395018578,50.8445320129],"type":"Point"}
}