{
  "type": "Feature",
  "properties": {
    "addr:full":"Galgestraat 33 Dilbeek Vlaams-Brabant 1703",
    "addr:housenumber":"33",
    "addr:postcode":"1703",
    "addr:street":"Galgestraat",
    "iso:country":"BE",
    "sg:address":"Galgestraat 33",
    "sg:city":"Dilbeek",
    "sg:orig_category":"Installation de menuiserie en bois and plastique",
    "sg:phone":"+32 2 582 43 54",
    "sg:postcode":"1703",
    "sg:province":"Vlaams-Brabant",
    "wof:name":"Kontibouw",
    "wof:placetype":"venue"
},
  "geometry": {"coordinates":[4.1737799644,50.8362884521],"type":"Point"}
}