{
  "type": "Feature",
  "properties": {
    "addr:full":"Avenue Jean Dubrucq 82 Sint-jans-molenbeek/molenbeek-saint-jean Bruxelles-Capitale 1080",
    "addr:housenumber":"82",
    "addr:postcode":"1080",
    "addr:street":"Avenue Jean Dubrucq",
    "iso:country":"BE",
    "sg:address":"Avenue Jean Dubrucq 82",
    "sg:city":"Sint-jans-molenbeek/molenbeek-saint-jean",
    "sg:classifiers":[
        {
            "category":"Health Services",
            "subcategory":"Nursing And Care Facility",
            "type":"Services"
        }
    ],
    "sg:phone":"+32 2 422 06 11",
    "sg:postcode":"1080",
    "sg:province":"Bruxelles-Capitale",
    "sg:tags":[
        "public"
    ],
    "wof:name":"C.p.a.s.",
    "wof:placetype":"venue"
},
  "geometry": {"coordinates":[4.3353180885,50.8660049438],"type":"Point"}
}