{
  "type": "Feature",
  "properties": {
    "addr:full":"Naalstraat 32 Duffel Antwerpen 2570",
    "addr:housenumber":"32",
    "addr:postcode":"2570",
    "addr:street":"Naalstraat",
    "iso:country":"BE",
    "sg:address":"Naalstraat 32",
    "sg:city":"Duffel",
    "sg:orig_category":"Woningbouw",
    "sg:phone":"+32 15 31 21 20",
    "sg:postcode":"2570",
    "sg:province":"Antwerpen",
    "wof:name":"Roger De Vos",
    "wof:placetype":"venue"
},
  "geometry": {"coordinates":[4.5083651543,51.0853805542],"type":"Point"}
}