{
  "type": "Feature",
  "properties": {
    "iso:country":"BE",
    "sg:address":"Avenue De Jette 126a",
    "sg:city":"Bruxelles (jette)",
    "sg:classifiers":[
        {
            "category":"Home & Garden",
            "subcategory":"Carpets & Floor Coverings",
            "type":"Retail Goods"
        }
    ],
    "sg:phone":"+32 2 426 70 07",
    "sg:postcode":"1090",
    "sg:province":"Bruxelles-Capitale",
    "sg:tags":[
        "parquet"
    ],
    "wof:name":"Parquet Je-c Sa",
    "wof:placetype":"venue"
},
  "geometry": {"coordinates":[4.3267650604,50.8678512573],"type":"Point"}
}