{
  "type": "Feature",
  "properties": {
    "iso:country":"BE",
    "sg:address":"Voetbalstraat 7",
    "sg:city":"Gent",
    "sg:classifiers":[
        {
            "category":"Personal",
            "subcategory":"Beauty Salon",
            "type":"Services"
        }
    ],
    "sg:phone":"+32 9 230 87 33",
    "sg:postcode":"9050",
    "sg:province":"Oost-Vlaanderen",
    "sg:tags":[
        "de",
        "coiffure"
    ],
    "wof:name":"Annik's Coiffure",
    "wof:placetype":"venue"
},
  "geometry": {"coordinates":[3.7669210434,51.0294456482],"type":"Point"}
}