{
  "type": "Feature",
  "properties": {
    "iso:country":"BE",
    "sg:address":"Rekerstraat 27",
    "sg:city":"Sint-pieters-leeuw (vlezenbeek)",
    "sg:classifiers":[
        {
            "category":"Health Services",
            "subcategory":"Health Practitioner",
            "type":"Services"
        }
    ],
    "sg:phone":"+32 2 532 25 93",
    "sg:postcode":"1602",
    "sg:province":"Vlaams-Brabant",
    "sg:tags":[
        "physiotherapist"
    ],
    "wof:name":"Vanderheyden Damien",
    "wof:placetype":"venue"
},
  "geometry": {"coordinates":[4.2374901772,50.8025131226],"type":"Point"}
}