{
  "type": "Feature",
  "properties": {
    "iso:country":"BE",
    "sg:address":"Rue Joseph Lizon 2",
    "sg:city":"Chievres",
    "sg:classifiers":[
        {
            "category":"Cafe",
            "type":"Food & Drink"
        }
    ],
    "sg:phone":"+32 69 68 89 10",
    "sg:postcode":"7950",
    "sg:province":"Hainaut",
    "sg:tags":[
        "caf\u00e9s"
    ],
    "wof:name":"Mireille Boucq",
    "wof:placetype":"venue"
},
  "geometry": {"coordinates":[3.7464530468,50.5661201477],"type":"Point"}
}