{
  "type": "Feature",
  "properties": {
    "addr:full":"Noordstraat 21-23 Roeselare West-Vlaanderen 8800",
    "addr:housenumber":"21-23",
    "addr:postcode":"8800",
    "addr:street":"Noordstraat",
    "iso:country":"BE",
    "sg:address":"Noordstraat 21-23",
    "sg:city":"Roeselare",
    "sg:classifiers":[
        {
            "category":"Shopping",
            "subcategory":"Clothing, Apparel, & Fashions",
            "type":"Retail Goods"
        }
    ],
    "sg:phone":"+32 51 22 61 38",
    "sg:postcode":"8800",
    "sg:province":"West-Vlaanderen",
    "sg:tags":[
        "clothing",
        "-",
        "gentleman"
    ],
    "wof:name":"Mac James Confecta Bvba",
    "wof:placetype":"venue"
},
  "geometry": {"coordinates":[3.1230800152,50.9456634521],"type":"Point"}
}