{
  "type": "Feature",
  "properties": {
    "addr:full":"Denderweg 9 Aalst Oost-Vlaanderen 9308",
    "addr:housenumber":"9",
    "addr:postcode":"9308",
    "addr:street":"Denderweg",
    "iso:country":"BE",
    "sg:address":"Denderweg 9",
    "sg:city":"Aalst",
    "sg:orig_category":"Fleurs and plantes",
    "sg:phone":"+32 53 70 11 30",
    "sg:postcode":"9308",
    "sg:province":"Oost-Vlaanderen",
    "wof:name":"Geldhof - Verweire",
    "wof:placetype":"venue"
},
  "geometry": {"coordinates":[4.0518598557,50.9830093384],"type":"Point"}
}