{
  "type": "Feature",
  "properties": {
    "iso:country":"BE",
    "sg:address":"Gouverneur Roppesingel 81 Box 4",
    "sg:city":"Hasselt",
    "sg:classifiers":[
        {
            "category":"Professional",
            "subcategory":"Employment Agencies",
            "type":"Services"
        }
    ],
    "sg:phone":"+32 11 27 90 80",
    "sg:postcode":"3500",
    "sg:province":"Limburg",
    "sg:tags":[
        "temping",
        "-",
        "manual"
    ],
    "wof:name":"Actief Construct Nv",
    "wof:placetype":"venue"
},
  "geometry": {"coordinates":[5.353823185,50.92004776],"type":"Point"}
}