{
  "type": "Feature",
  "properties": {
    "iso:country":"BE",
    "sg:address":"Zandbergstraat 2",
    "sg:city":"Kortrijk",
    "sg:orig_category":"Krantenwinkels Rookartikelen Speelgoed",
    "sg:phone":"+32 56 22 23 71",
    "sg:postcode":"8500",
    "sg:province":"West-Vlaanderen",
    "wof:name":"Huis 't Schrijverke",
    "wof:placetype":"venue"
},
  "geometry": {"coordinates":[3.2849400043,50.836605072],"type":"Point"}
}