{
  "type": "Feature",
  "properties": {
    "iso:country":"BE",
    "sg:address":"Ferdinand Van Hoeymissenstraat 1",
    "sg:city":"Haaltert (kerksken)",
    "sg:classifiers":[
        {
            "category":"Food & Beverages",
            "subcategory":"Meat & Fish",
            "type":"Retail Goods"
        }
    ],
    "sg:phone":"+32 53 83 53 97",
    "sg:postcode":"9451",
    "sg:province":"Oost-Vlaanderen",
    "sg:tags":[
        "poultry",
        "whol",
        "game",
        "-"
    ],
    "wof:name":"Bogaert",
    "wof:placetype":"venue"
},
  "geometry": {"coordinates":[3.9937279224,50.8899841309],"type":"Point"}
}