{
  "type": "Feature",
  "properties": {
    "addr:full":"Rue De La Miraine 46 Silly Hainaut 7830",
    "addr:housenumber":"46",
    "addr:postcode":"7830",
    "addr:street":"Rue De La Miraine",
    "iso:country":"BE",
    "sg:address":"Rue De La Miraine 46",
    "sg:city":"Silly",
    "sg:orig_category":"Elektrische installaties voor woningen",
    "sg:phone":"+32 68 55 26 77",
    "sg:postcode":"7830",
    "sg:province":"Hainaut",
    "wof:name":"Christophe Urban",
    "wof:placetype":"venue"
},
  "geometry": {"coordinates":[3.9294600487,50.6263084412],"type":"Point"}
}