{
  "type": "Feature",
  "properties": {
    "iso:country":"BE",
    "sg:address":"Rue Di\u00e9rain Patar 63",
    "sg:city":"Gr\u00e2ce-hollogne (hollogne-aux-pierres)",
    "sg:classifiers":[
        {
            "category":"Health Services",
            "subcategory":"Health Practitioner",
            "type":"Services"
        }
    ],
    "sg:phone":"+32 4 233 06 17",
    "sg:postcode":"4460",
    "sg:province":"Li\u00e8ge",
    "sg:tags":[
        "physiotherapist"
    ],
    "wof:name":"Quevrin Marie-aline",
    "wof:placetype":"venue"
},
  "geometry": {"coordinates":[5.4564437866,50.6363067627],"type":"Point"}
}