{
  "type": "Feature",
  "properties": {
    "iso:country":"BE",
    "sg:address":"Beekstraat 6",
    "sg:city":"Ham",
    "sg:orig_category":"Boekhouders",
    "sg:phone":"+32 13 66 41 63",
    "sg:postcode":"3945",
    "sg:province":"Limburg",
    "wof:name":"Sandra Schepers",
    "wof:placetype":"venue"
},
  "geometry": {"coordinates":[5.1776199341,51.1046104431],"type":"Point"}
}