{
  "type": "Feature",
  "properties": {
    "iso:country":"BE",
    "sg:address":"Zeelaan 62",
    "sg:city":"De Panne",
    "sg:orig_category":"Lingerie and ondergoed Textiel",
    "sg:phone":"+32 58 41 42 68",
    "sg:postcode":"8660",
    "sg:province":"West-Vlaanderen",
    "wof:name":"Huis Green Cotton",
    "wof:placetype":"venue"
},
  "geometry": {"coordinates":[2.5908970833,51.0977554321],"type":"Point"}
}