{
  "type": "Feature",
  "properties": {
    "iso:country":"BE",
    "sg:address":"Rue L\u00c9on Hiard 61",
    "sg:city":"La Louviere",
    "sg:orig_category":"Brood, gebak and snoepgoed",
    "sg:phone":"+32 64 26 13 47",
    "sg:postcode":"7100",
    "sg:province":"Hainaut",
    "wof:name":"Nancy Miot",
    "wof:placetype":"venue"
},
  "geometry": {"coordinates":[4.2080030441,50.4563407898],"type":"Point"}
}