{
  "type": "Feature",
  "properties": {
    "iso:country":"BE",
    "sg:address":"Rue Des Faubourgs 32",
    "sg:city":"Arlon",
    "sg:orig_category":"Beautyfarms, relaxatie and lichamelijk welzijn Kapsalons",
    "sg:phone":"+32 63 22 84 72",
    "sg:postcode":"6700",
    "sg:province":"Luxembourg",
    "wof:name":"M\u00c9tamorphose",
    "wof:placetype":"venue"
},
  "geometry": {"coordinates":[5.8109440804,49.6846008301],"type":"Point"}
}