{
  "type": "Feature",
  "properties": {
    "addr:full":"Avenue De Tervueren 166 Bruxelles (woluwe-saint-pierre) Bruxelles-Capitale 1150",
    "addr:housenumber":"166",
    "addr:postcode":"1150",
    "addr:street":"Avenue De Tervueren",
    "iso:country":"BE",
    "sg:address":"Avenue De Tervueren 166",
    "sg:city":"Bruxelles (woluwe-saint-pierre)",
    "sg:classifiers":[
        {
            "category":"Professional",
            "subcategory":"Lawyer & Legal Services",
            "type":"Services"
        }
    ],
    "sg:phone":"+32 2 538 08 04",
    "sg:postcode":"1150",
    "sg:province":"Bruxelles-Capitale",
    "wof:name":"Sainlez Sylvie",
    "wof:placetype":"venue"
},
  "geometry": {"coordinates":[4.4102511406,50.837223053],"type":"Point"}
}