{
  "type": "Feature",
  "properties": {
    "iso:country":"BE",
    "sg:address":"Tynecotstraat 29",
    "sg:city":"Zonnebeke (passendale)",
    "sg:classifiers":[
        {
            "category":"Building & Trades",
            "subcategory":"Construction",
            "type":"Services"
        }
    ],
    "sg:phone":"+32 51 77 90 12",
    "sg:postcode":"8980",
    "sg:province":"West-Vlaanderen",
    "sg:tags":[
        "carpenter"
    ],
    "wof:name":"De Wulf J",
    "wof:placetype":"venue"
},
  "geometry": {"coordinates":[3.0031759739,50.8840942383],"type":"Point"}
}