{
  "type": "Feature",
  "properties": {
    "addr:full":"Rue De La Coupe 37 Mons Hainaut 7000",
    "addr:housenumber":"37",
    "addr:postcode":"7000",
    "addr:street":"Rue De La Coupe;Hainaut",
    "iso:country":"BE",
    "sg:address":"Rue De La Coupe 37",
    "sg:city":"Mons",
    "sg:classifiers":[
        {
            "category":"Deli",
            "type":"Food & Drink"
        }
    ],
    "sg:phone":"+32 65 35 14 53",
    "sg:postcode":"7000",
    "sg:province":"Hainaut",
    "sg:tags":[
        "delicatessen"
    ],
    "wof:name":"Gariotte (la)",
    "wof:placetype":"venue"
},
  "geometry": {"coordinates":[3.9522230625,50.4529685974],"type":"Point"}
}