{
  "type": "Feature",
  "properties": {
    "addr:full":"Rue La Coul\u00e9e 2 Modave (vierset-barse) Li\u00e8ge 4577",
    "addr:housenumber":"2",
    "addr:postcode":"4577",
    "addr:street":"Rue La Coule\u0301E;Vierset-Barse",
    "iso:country":"BE",
    "sg:address":"Rue La Coul\u00e9e 2",
    "sg:city":"Modave (vierset-barse)",
    "sg:classifiers":[
        {
            "category":"Farming",
            "subcategory":"Farm & Veterinary Services",
            "type":"Manufacturing & Wholesale Goods"
        }
    ],
    "sg:phone":"+32 85 41 23 88",
    "sg:postcode":"4577",
    "sg:province":"Li\u00e8ge",
    "sg:tags":[
        "agricultural",
        "contractor"
    ],
    "wof:name":"Van Wonterghem Ph",
    "wof:placetype":"venue"
},
  "geometry": {"coordinates":[5.2986779213,50.4815444946],"type":"Point"}
}