{
  "type": "Feature",
  "properties": {
    "addr:full":"Breemakkers 62 Kasterlee (tielen) Antwerpen 2460",
    "addr:housenumber":"62",
    "addr:postcode":"2460",
    "addr:street":"Breemakkers",
    "iso:country":"BE",
    "sg:address":"Breemakkers 62",
    "sg:city":"Kasterlee (tielen)",
    "sg:classifiers":[
        {
            "category":"Building & Trades",
            "subcategory":"Pest Control",
            "type":"Services"
        }
    ],
    "sg:phone":"+32 14 55 73 09",
    "sg:postcode":"2460",
    "sg:province":"Antwerpen",
    "sg:tags":[
        "painting",
        "contractor"
    ],
    "wof:name":"Straetmans",
    "wof:placetype":"venue"
},
  "geometry": {"coordinates":[4.9012532234,51.2472000122],"type":"Point"}
}