{
  "type": "Feature",
  "properties": {
    "addr:full":"Rue Rouge-croix 6 Seneffe Hainaut 7180",
    "addr:housenumber":"6",
    "addr:postcode":"7180",
    "addr:street":"Rue Rouge-Croix",
    "iso:country":"BE",
    "sg:address":"Rue Rouge-croix 6",
    "sg:city":"Seneffe",
    "sg:classifiers":[
        {
            "category":"Government",
            "subcategory":"Post Office",
            "type":"Public Place"
        }
    ],
    "sg:phone":"+32 64 52 19 11",
    "sg:postcode":"7180",
    "sg:province":"Hainaut",
    "sg:tags":[
        "telecommunication",
        "cable"
    ],
    "wof:name":"Commscope Europe S.p.r.l.",
    "wof:placetype":"venue"
},
  "geometry": {"coordinates":[4.2567501068,50.5332489014],"type":"Point"}
}