{
  "type": "Feature",
  "properties": {
    "addr:full":"Route De Philippeville 158-160 Charleroi (couillet) Hainaut 6010",
    "addr:postcode":"158-160;6010",
    "addr:street":"Route De Philippeville",
    "iso:country":"BE",
    "sg:address":"Route De Philippeville 158-160",
    "sg:city":"Charleroi (couillet)",
    "sg:classifiers":[
        {
            "category":"Professional",
            "subcategory":"Art Services",
            "type":"Services"
        }
    ],
    "sg:phone":"+32 71 36 98 37",
    "sg:postcode":"6010",
    "sg:province":"Hainaut",
    "sg:tags":[
        "photographer"
    ],
    "wof:name":"Aaton-delalieux",
    "wof:placetype":"venue"
},
  "geometry": {"coordinates":[4.4609007835,50.3883552551],"type":"Point"}
}