{
  "type": "Feature",
  "properties": {
    "iso:country":"BE",
    "sg:address":"Oostnieuwkerksesteenweg 14",
    "sg:city":"Roeselare",
    "sg:classifiers":[
        {
            "category":"Real Estate",
            "subcategory":"Architect",
            "type":"Services"
        }
    ],
    "sg:phone":"+32 51 20 88 97",
    "sg:postcode":"8800",
    "sg:province":"West-Vlaanderen",
    "wof:name":"Hostens N",
    "wof:placetype":"venue"
},
  "geometry": {"coordinates":[3.1080799103,50.9479751587],"type":"Point"}
}