{
  "type": "Feature",
  "properties": {
    "addr:full":"Pullaarsteenweg 132 Puurs Antwerpen 2870",
    "addr:housenumber":"132",
    "addr:postcode":"2870",
    "addr:street":"Pullaarsteenweg",
    "iso:country":"BE",
    "sg:address":"Pullaarsteenweg 132",
    "sg:city":"Puurs",
    "sg:classifiers":[
        {
            "category":"Personal",
            "subcategory":"Beauty Salon",
            "type":"Services"
        }
    ],
    "sg:phone":"+32 3 866 21 42",
    "sg:postcode":"2870",
    "sg:province":"Antwerpen",
    "sg:tags":[
        "de",
        "coiffure"
    ],
    "wof:name":"Nancy Moons",
    "wof:placetype":"venue"
},
  "geometry": {"coordinates":[4.3233890533,51.0736923218],"type":"Point"}
}