{
  "type": "Feature",
  "properties": {
    "iso:country":"BE",
    "sg:address":"Rue Pierreuse 11",
    "sg:city":"Li\u00c8ge",
    "sg:orig_category":"Antiquit\u00e9s",
    "sg:phone":"+32 4 377 16 46",
    "sg:postcode":"4000",
    "sg:province":"Li\u00e8ge",
    "wof:name":"Le Fa\u00cfencier De Pierreuse",
    "wof:placetype":"venue"
},
  "geometry": {"coordinates":[5.5735521317,50.6466178894],"type":"Point"}
}