{
  "type": "Feature",
  "properties": {
    "iso:country":"BE",
    "sg:address":"Vosstraat 35",
    "sg:city":"Antwerpen",
    "sg:classifiers":[
        {
            "category":"Fast Food",
            "type":"Food & Drink"
        }
    ],
    "sg:phone":"+32 3 322 50 50",
    "sg:postcode":"2140",
    "sg:province":"Antwerpen",
    "sg:tags":[
        "\u00c0",
        "emporter",
        "restaurants"
    ],
    "wof:name":"Pizza Pompeje",
    "wof:placetype":"venue"
},
  "geometry": {"coordinates":[4.4332199097,51.2137565613],"type":"Point"}
}