{
  "type": "Feature",
  "properties": {
    "addr:full":"Brugsesteenweg 4 Veurne West-Vlaanderen 8630",
    "addr:housenumber":"4",
    "addr:postcode":"8630",
    "addr:street":"Brugsesteenweg",
    "iso:country":"BE",
    "sg:address":"Brugsesteenweg 4",
    "sg:city":"Veurne",
    "sg:classifiers":[
        {
            "category":"Shopping",
            "subcategory":"Bicycles & Sporting Goods",
            "type":"Retail Goods"
        }
    ],
    "sg:phone":"+32 58 31 10 64",
    "sg:postcode":"8630",
    "sg:province":"West-Vlaanderen",
    "sg:tags":[
        "-"
    ],
    "wof:name":"Coutteau J",
    "wof:placetype":"venue"
},
  "geometry": {"coordinates":[2.6692910194,51.0742835999],"type":"Point"}
}