{
  "type": "Feature",
  "properties": {
    "addr:full":"Rue Des Cortils 43 Profondeville Namur 5170",
    "addr:housenumber":"43",
    "addr:postcode":"5170",
    "addr:street":"Rue Des Cortils",
    "iso:country":"BE",
    "sg:address":"Rue Des Cortils 43",
    "sg:city":"Profondeville",
    "sg:classifiers":[
        {
            "category":"Social Services",
            "subcategory":"Job Training",
            "type":"Services"
        }
    ],
    "sg:phone":"+32 81 41 28 22",
    "sg:postcode":"5170",
    "sg:province":"Namur",
    "sg:tags":[
        "de",
        "terrain",
        "camping"
    ],
    "wof:name":"Camping 7 Meuses",
    "wof:placetype":"venue"
},
  "geometry": {"coordinates":[4.8674049377,50.3786392212],"type":"Point"}
}