{
  "type": "Feature",
  "properties": {
    "iso:country":"BE",
    "sg:address":"Stationsstraat 84",
    "sg:city":"Waregem",
    "sg:orig_category":"M\u00e9decins and sp\u00e9cialistes",
    "sg:phone":"+32 56 61 38 00",
    "sg:postcode":"8790",
    "sg:province":"West-Vlaanderen",
    "wof:name":"Godelieve Constandt",
    "wof:placetype":"venue"
},
  "geometry": {"coordinates":[3.429377079,50.890083313],"type":"Point"}
}