{
  "type": "Feature",
  "properties": {
    "iso:country":"BE",
    "sg:address":"Filips Van De Elzaslaan 122",
    "sg:city":"Kortrijk",
    "sg:orig_category":"Blanchisseries and teintureries",
    "sg:phone":"+32 56 21 72 87",
    "sg:postcode":"8500",
    "sg:province":"West-Vlaanderen",
    "wof:name":"Super-shop",
    "wof:placetype":"venue"
},
  "geometry": {"coordinates":[3.2777531147,50.8226242065],"type":"Point"}
}