{
  "type": "Feature",
  "properties": {
    "iso:country":"BE",
    "sg:address":"Lieven Bauwensstraat 33",
    "sg:city":"Brugge",
    "sg:orig_category":"Databanken",
    "sg:phone":"+32 50 32 08 59",
    "sg:postcode":"8200",
    "sg:province":"West-Vlaanderen",
    "wof:name":"Vanden Broele Grafische Groep",
    "wof:placetype":"venue"
},
  "geometry": {"coordinates":[3.195884943,51.2152061462],"type":"Point"}
}