{
  "type": "Feature",
  "properties": {
    "iso:country":"BE",
    "sg:address":"Ketelaarsgras 15",
    "sg:city":"Stekene",
    "sg:orig_category":"Transports routiers de marchandises",
    "sg:phone":"+32 3 779 78 37",
    "sg:postcode":"9190",
    "sg:province":"Oost-Vlaanderen",
    "wof:name":"Transport Persoon",
    "wof:placetype":"venue"
},
  "geometry": {"coordinates":[4.0384879112,51.2162818909],"type":"Point"}
}