{
  "type": "Feature",
  "properties": {
    "iso:country":"BE",
    "sg:address":"Pl.docteur E. Lodewijckx 12",
    "sg:city":"Jodoigne",
    "sg:orig_category":"Editeurs de livres. Instruments de musique",
    "sg:phone":"+32 10 81 48 52",
    "sg:postcode":"1370",
    "sg:province":"Brabant Wallon",
    "wof:name":"Editions Musiqid\u00c9e",
    "wof:placetype":"venue"
},
  "geometry": {"coordinates":[4.8690052032,50.7250747681],"type":"Point"}
}