{
  "type": "Feature",
  "properties": {
    "addr:full":"Nijverheidsstraat 18 Destelbergen Oost-Vlaanderen 9070",
    "addr:housenumber":"18",
    "addr:postcode":"9070",
    "addr:street":"Nijverheidsstraat",
    "iso:country":"BE",
    "sg:address":"Nijverheidsstraat 18",
    "sg:city":"Destelbergen",
    "sg:classifiers":[
        {
            "category":"Shopping",
            "subcategory":"Discount & Variety Stores",
            "type":"Retail Goods"
        }
    ],
    "sg:phone":"+32 9 228 19 61",
    "sg:postcode":"9070",
    "sg:province":"Oost-Vlaanderen",
    "sg:tags":[
        "warehouse",
        "-",
        "merchandise"
    ],
    "wof:name":"Atramef",
    "wof:placetype":"venue"
},
  "geometry": {"coordinates":[3.7710568905,51.0520935059],"type":"Point"}
}