{
  "type": "Feature",
  "properties": {
    "iso:country":"BE",
    "sg:address":"Heidestraat 8",
    "sg:city":"Zulte",
    "sg:orig_category":"Goederenvervoer over de weg",
    "sg:phone":"+32 9 388 41 00",
    "sg:postcode":"9870",
    "sg:province":"Oost-Vlaanderen",
    "wof:name":"Manatrans",
    "wof:placetype":"venue"
},
  "geometry": {"coordinates":[3.469894886,50.9112052917],"type":"Point"}
}