{
  "type": "Feature",
  "properties": {
    "iso:country":"BE",
    "sg:address":"Buitenland 33a",
    "sg:city":"Bornem",
    "sg:orig_category":"Artiesten and kunstenaars",
    "sg:phone":"+32 3 889 49 79",
    "sg:postcode":"2880",
    "sg:province":"Antwerpen",
    "wof:name":"Talaga",
    "wof:placetype":"venue"
},
  "geometry": {"coordinates":[4.2285699844,51.1158905029],"type":"Point"}
}