{
  "type": "Feature",
  "properties": {
    "iso:country":"BE",
    "sg:address":"Steenweg Op Turnhout 54",
    "sg:city":"Oud-turnhout",
    "sg:orig_category":"Services fun\u00e9raires",
    "sg:phone":"+32 14 45 33 19",
    "sg:postcode":"2360",
    "sg:province":"Antwerpen",
    "wof:name":"Fa. Schillebeeckx & Co",
    "wof:placetype":"venue"
},
  "geometry": {"coordinates":[4.9781188965,51.3196029663],"type":"Point"}
}