{
  "type": "Feature",
  "properties": {
    "addr:full":"Route De Herbesthal 146 Eupen Li\u00e8ge 4700",
    "addr:housenumber":"146",
    "addr:postcode":"4700",
    "addr:street":"Route De Herbesthal",
    "iso:country":"BE",
    "sg:address":"Route De Herbesthal 146",
    "sg:city":"Eupen",
    "sg:orig_category":"Goederenvervoer over de weg",
    "sg:phone":"+32 87 30 56 11",
    "sg:postcode":"4700",
    "sg:province":"Li\u00e8ge",
    "wof:name":"Ghemar",
    "wof:placetype":"venue"
},
  "geometry": {"coordinates":[6.0125341415,50.6415939331],"type":"Point"}
}