{
  "type": "Feature",
  "properties": {
    "iso:country":"BE",
    "sg:address":"Eendrachtstraat 6",
    "sg:city":"Lommel",
    "sg:orig_category":"Etalage- and showroomontwerpers",
    "sg:phone":"+32 11 55 19 60",
    "sg:postcode":"3920",
    "sg:province":"Limburg",
    "wof:name":"Monique Janssen",
    "wof:placetype":"venue"
},
  "geometry": {"coordinates":[5.3248810768,51.2294807434],"type":"Point"}
}