{
  "type": "Feature",
  "properties": {
    "addr:full":"Salisburylaan 98-100 Merelbeke Oost-Vlaanderen 9820",
    "addr:postcode":"98-100;9820",
    "addr:street":"Salisburylaan",
    "iso:country":"BE",
    "sg:address":"Salisburylaan 98-100",
    "sg:city":"Merelbeke",
    "sg:classifiers":[
        {
            "category":"Health Services",
            "subcategory":"Nursing And Care Facility",
            "type":"Services"
        }
    ],
    "sg:phone":"+32 9 272 20 00",
    "sg:postcode":"9820",
    "sg:province":"Oost-Vlaanderen",
    "sg:tags":[
        "home",
        "rest"
    ],
    "wof:name":"Rustoord/rvt Lemberge",
    "wof:placetype":"venue"
},
  "geometry": {"coordinates":[3.7695949078,50.9978408813],"type":"Point"}
}