{
  "type": "Feature",
  "properties": {
    "addr:full":"Rue Eloi Fouarge 21 Saint-georges-sur-meuse Li\u00e8ge 4470",
    "addr:housenumber":"21",
    "addr:postcode":"4470",
    "addr:street":"Rue Eloi Fouarge",
    "iso:country":"BE",
    "sg:address":"Rue Eloi Fouarge 21",
    "sg:city":"Saint-georges-sur-meuse",
    "sg:classifiers":[
        {
            "category":"Food & Beverages",
            "subcategory":"Groceries & Convenience Stores",
            "type":"Retail Goods"
        }
    ],
    "sg:phone":"+32 4 275 78 66",
    "sg:postcode":"4470",
    "sg:province":"Li\u00e8ge",
    "sg:tags":[
        "grocer"
    ],
    "wof:name":"Super Gb",
    "wof:placetype":"venue"
},
  "geometry": {"coordinates":[5.3612351418,50.5895843506],"type":"Point"}
}