{
  "type": "Feature",
  "properties": {
    "iso:country":"BE",
    "sg:address":"Adrinkhovenlaan 32",
    "sg:city":"Borsbeek",
    "sg:orig_category":"Ordinateurs and \u00e9quipement informatique",
    "sg:phone":"+32 3 322 15 99",
    "sg:postcode":"2150",
    "sg:province":"Antwerpen",
    "wof:name":"Cebit",
    "wof:placetype":"venue"
},
  "geometry": {"coordinates":[4.483063221,51.201789856],"type":"Point"}
}