{
  "type": "Feature",
  "properties": {
    "addr:full":"Strostraat 9 Brussel/bruxelles Bruxelles-Capitale 1000",
    "addr:housenumber":"9",
    "addr:postcode":"1000",
    "addr:street":"Strostraat;/",
    "iso:country":"BE",
    "sg:address":"Strostraat 9",
    "sg:city":"Brussel/bruxelles",
    "sg:orig_category":"Decoratieve kunst and kunstbenodigdheden Zalen voor culturele evenementen",
    "sg:phone":"+32 2 511 35 80",
    "sg:postcode":"1000",
    "sg:province":"Bruxelles-Capitale",
    "wof:name":"Maurice Keitelman Gallery",
    "wof:placetype":"venue"
},
  "geometry": {"coordinates":[4.3545498848,50.8420906067],"type":"Point"}
}