{
  "type": "Feature",
  "properties": {
    "iso:country":"BE",
    "sg:address":"Beurtstraat 40",
    "sg:city":"Tielt-winge",
    "sg:classifiers":[
        {
            "category":"Taxi",
            "type":"Transportation"
        }
    ],
    "sg:phone":"+32 16 50 32 50",
    "sg:postcode":"3390",
    "sg:province":"Vlaams-Brabant",
    "sg:tags":[
        "taxi's"
    ],
    "wof:name":"D.b.a. Shuttle Service",
    "wof:placetype":"venue"
},
  "geometry": {"coordinates":[4.938521862,50.9493179321],"type":"Point"}
}