{
  "type": "Feature",
  "properties": {
    "addr:full":"Rue Au Vin 69 Renaix Oost-Vlaanderen 9600",
    "addr:housenumber":"69",
    "addr:postcode":"9600",
    "addr:street":"Rue Au Vin",
    "iso:country":"BE",
    "sg:address":"Rue Au Vin 69",
    "sg:city":"Renaix",
    "sg:classifiers":[
        {
            "category":"Manufacturing",
            "subcategory":"Furniture",
            "type":"Manufacturing & Wholesale Goods"
        }
    ],
    "sg:phone":"+32 55 21 15 03",
    "sg:postcode":"9600",
    "sg:province":"Oost-Vlaanderen",
    "sg:tags":[
        "design",
        "-"
    ],
    "wof:name":"Maison (la)",
    "wof:placetype":"venue"
},
  "geometry": {"coordinates":[3.5975630283,50.7493667603],"type":"Point"}
}