{
  "type": "Feature",
  "properties": {
    "iso:country":"BE",
    "sg:address":"Bourcy 60",
    "sg:city":"Bastogne",
    "sg:orig_category":"Rundveehouders",
    "sg:phone":"+32 61 21 36 38",
    "sg:postcode":"6600",
    "sg:province":"Luxembourg",
    "wof:name":"Augustin Zabus",
    "wof:placetype":"venue"
},
  "geometry": {"coordinates":[5.8077020645,50.0604019165],"type":"Point"}
}