{
  "type": "Feature",
  "properties": {
    "addr:full":"Gill\u00e8s De P\u00e9lichylei 133a Schilde ('s Gravenwezel) Antwerpen 2970",
    "addr:housenumber":"133a",
    "addr:postcode":"2970",
    "addr:street":"Schilde;S",
    "iso:country":"BE",
    "sg:address":"Gill\u00e8s De P\u00e9lichylei 133a",
    "sg:city":"Schilde ('s Gravenwezel)",
    "sg:classifiers":[
        {
            "category":"Health Services",
            "subcategory":"Doctor",
            "type":"Services"
        }
    ],
    "sg:phone":"+32 3 384 00 30",
    "sg:postcode":"2970",
    "sg:province":"Antwerpen",
    "sg:tags":[
        "medicinephysicians",
        "surgeon"
    ],
    "wof:name":"Brugmans J",
    "wof:placetype":"venue"
},
  "geometry": {"coordinates":[4.5702490807,51.2495040894],"type":"Point"}
}