{
  "type": "Feature",
  "properties": {
    "addr:full":"L\u00c9on Houyouxlaan 18 Oudergem/auderghem Bruxelles-Capitale 1160",
    "addr:housenumber":"18",
    "addr:postcode":"1160",
    "addr:street":"Le\u0301On Houyouxlaan;/",
    "iso:country":"BE",
    "sg:address":"L\u00c9on Houyouxlaan 18",
    "sg:city":"Oudergem/auderghem",
    "sg:orig_category":"Artsen and specialisten",
    "sg:phone":"+32 2 673 33 74",
    "sg:postcode":"1160",
    "sg:province":"Bruxelles-Capitale",
    "wof:name":"Bernard Thon",
    "wof:placetype":"venue"
},
  "geometry": {"coordinates":[4.4029297829,50.8256645203],"type":"Point"}
}