{
  "type": "Feature",
  "properties": {
    "iso:country":"BE",
    "sg:address":"Rue Du Pige 110",
    "sg:city":"Doische (vodel\u00e9e)",
    "sg:classifiers":[
        {
            "category":"Food & Beverages",
            "subcategory":"Liquor & Beverages",
            "type":"Retail Goods"
        }
    ],
    "sg:phone":"+32 82 67 83 97",
    "sg:postcode":"5680",
    "sg:province":"Namur",
    "sg:tags":[
        "-",
        "spirit",
        "wine"
    ],
    "wof:name":"Clos Du Soleil Sprl",
    "wof:placetype":"venue"
},
  "geometry": {"coordinates":[4.7314600945,50.1676597595],"type":"Point"}
}