{
  "type": "Feature",
  "properties": {
    "iso:country":"BE",
    "sg:address":"Edmond Helderweirdtstraat 1",
    "sg:city":"Gent (oostakker)",
    "sg:classifiers":[
        {
            "category":"Home & Garden",
            "subcategory":"Carpets & Floor Coverings",
            "type":"Retail Goods"
        }
    ],
    "sg:phone":"+32 9 259 00 59",
    "sg:postcode":"9041",
    "sg:province":"Oost-Vlaanderen",
    "sg:tags":[
        "layer",
        "mosaicists"
    ],
    "wof:name":"Vanpoucke Eric",
    "wof:placetype":"venue"
},
  "geometry": {"coordinates":[3.7755129337,51.0822982788],"type":"Point"}
}