{
  "type": "Feature",
  "properties": {
    "iso:country":"BE",
    "sg:address":"Rue Du Vingt-huit Juin 1919 40",
    "sg:city":"Courcelles",
    "sg:classifiers":[
        {
            "category":"Building & Trades",
            "subcategory":"Cleaning & Sanitation",
            "type":"Services"
        }
    ],
    "sg:phone":"+32 71 46 14 58",
    "sg:postcode":"6180",
    "sg:province":"Hainaut",
    "sg:tags":[
        "fa\u00e7ade",
        "maintenance"
    ],
    "wof:name":"Renovancienne (la)",
    "wof:placetype":"venue"
},
  "geometry": {"coordinates":[4.3646597862,50.4614906311],"type":"Point"}
}