{
  "type": "Feature",
  "properties": {
    "iso:country":"BE",
    "sg:address":"Smisveld 20",
    "sg:city":"Wellen (ulbeek)",
    "sg:classifiers":[
        {
            "category":"Professional",
            "subcategory":"Art Services",
            "type":"Services"
        }
    ],
    "sg:phone":"+32 12 74 32 11",
    "sg:postcode":"3832",
    "sg:province":"Limburg",
    "sg:tags":[
        "graphic",
        "designer"
    ],
    "wof:name":"Idefix Bvba",
    "wof:placetype":"venue"
},
  "geometry": {"coordinates":[5.3033227921,50.8416290283],"type":"Point"}
}