{
  "type": "Feature",
  "properties": {
    "iso:country":"BE",
    "sg:address":"Avenue Roi Albert 131",
    "sg:city":"Andenne",
    "sg:orig_category":"Boucheries",
    "sg:phone":"+32 85 84 47 41",
    "sg:postcode":"5300",
    "sg:province":"Namur",
    "wof:name":"Renmans",
    "wof:placetype":"venue"
},
  "geometry": {"coordinates":[5.1067700386,50.493598938],"type":"Point"}
}