{
  "type": "Feature",
  "properties": {
    "addr:full":"Kosterstraat 7 Linter (drieslinter) Vlaams-Brabant 3350",
    "addr:housenumber":"7",
    "addr:postcode":"3350",
    "addr:street":"Kosterstraat",
    "iso:country":"BE",
    "sg:address":"Kosterstraat 7",
    "sg:city":"Linter (drieslinter)",
    "sg:classifiers":[
        {
            "category":"Professional",
            "subcategory":"Accounting & Tax Preparation",
            "type":"Services"
        }
    ],
    "sg:phone":"+32 11 78 24 88",
    "sg:postcode":"3350",
    "sg:province":"Vlaams-Brabant",
    "sg:tags":[
        "accountant"
    ],
    "wof:name":"Closset S",
    "wof:placetype":"venue"
},
  "geometry": {"coordinates":[5.0546507835,50.8445930481],"type":"Point"}
}