{
  "type": "Feature",
  "properties": {
    "addr:full":"Duiventorenstraat 12 Essen Antwerpen 2910",
    "addr:housenumber":"12",
    "addr:postcode":"2910",
    "addr:street":"Duiventorenstraat",
    "iso:country":"BE",
    "sg:address":"Duiventorenstraat 12",
    "sg:city":"Essen",
    "sg:classifiers":[
        {
            "category":"Shopping",
            "subcategory":"Florist",
            "type":"Retail Goods"
        }
    ],
    "sg:phone":"+32 3 667 62 01",
    "sg:postcode":"2910",
    "sg:province":"Antwerpen",
    "wof:name":"Anbasa Bvba",
    "wof:placetype":"venue"
},
  "geometry": {"coordinates":[4.5031318665,51.4514503479],"type":"Point"}
}