{
  "type": "Feature",
  "properties": {
    "iso:country":"BE",
    "sg:address":"Wersbeekstraat 25",
    "sg:city":"Tielt-winge (meensel-kiezegem)",
    "sg:classifiers":[
        {
            "category":"Manufacturing",
            "subcategory":"Lumber",
            "type":"Manufacturing & Wholesale Goods"
        }
    ],
    "sg:phone":"+32 16 63 30 23",
    "sg:postcode":"3391",
    "sg:province":"Vlaams-Brabant",
    "sg:tags":[
        "timber"
    ],
    "wof:name":"Vande Gaer Doe-het-zelf Nv",
    "wof:placetype":"venue"
},
  "geometry": {"coordinates":[4.9282550812,50.9001159668],"type":"Point"}
}