{
  "type": "Feature",
  "properties": {
    "iso:country":"BE",
    "sg:address":"Rue De La Station 6",
    "sg:city":"Aubange",
    "sg:orig_category":"Enseignement maternel and primaire",
    "sg:phone":"+32 63 38 12 27",
    "sg:postcode":"6791",
    "sg:province":"Luxembourg",
    "wof:name":"Ecole Fondamentale Libre",
    "wof:placetype":"venue"
},
  "geometry": {"coordinates":[5.8284797668,49.564540863],"type":"Point"}
}