{
  "type": "Feature",
  "properties": {
    "addr:full":"Dorpstraat Tielt-winge Vlaams-Brabant 3390",
    "addr:postcode":"3390",
    "addr:street":"Dorpstraat",
    "iso:country":"BE",
    "sg:address":"Dorpstraat",
    "sg:city":"Tielt-winge",
    "sg:orig_category":"Beheer van afvalopslag- and stortplaatsen",
    "sg:phone":"+32 16 50 29 11",
    "sg:postcode":"3390",
    "sg:province":"Vlaams-Brabant",
    "wof:name":"Containerpark Tielt-winge",
    "wof:placetype":"venue"
},
  "geometry": {"coordinates":[4.9142618179,50.9435386658],"type":"Point"}
}