{
  "type": "Feature",
  "properties": {
    "iso:country":"BE",
    "sg:address":"Rue Cron 1",
    "sg:city":"Antoing (p\u00e9ronnes-lez-antoing)",
    "sg:classifiers":[
        {
            "category":"Home & Garden",
            "subcategory":"Home Furnishings",
            "type":"Retail Goods"
        }
    ],
    "sg:phone":"+32 69 44 15 40",
    "sg:postcode":"7640",
    "sg:province":"Hainaut",
    "sg:tags":[
        "-",
        "furniture"
    ],
    "wof:name":"Greniers De P\u00e9ronnes (les)",
    "wof:placetype":"venue"
},
  "geometry": {"coordinates":[3.4518949986,50.5536842346],"type":"Point"}
}