{
  "type": "Feature",
  "properties": {
    "iso:country":"BE",
    "sg:address":"Avenue Franklin Roosevelt 104 Box 3",
    "sg:city":"Rixensart",
    "sg:classifiers":[
        {
            "category":"Social Services",
            "subcategory":"Job Training",
            "type":"Services"
        }
    ],
    "sg:phone":"+32 2 652 08 66",
    "sg:postcode":"1330",
    "sg:province":"Brabant Wallon",
    "sg:tags":[
        "personnel"
    ],
    "wof:name":"Dynaconsult Sa",
    "wof:placetype":"venue"
},
  "geometry": {"coordinates":[4.516040802,50.7213096619],"type":"Point"}
}