{
  "type": "Feature",
  "properties": {
    "iso:country":"BE",
    "sg:address":"Hoevestraat 29",
    "sg:city":"Kortrijk",
    "sg:classifiers":[
        {
            "category":"Building & Trades",
            "subcategory":"Construction",
            "type":"Services"
        }
    ],
    "sg:phone":"+32 56 25 94 79",
    "sg:postcode":"8500",
    "sg:province":"West-Vlaanderen",
    "sg:tags":[
        "carpenter"
    ],
    "wof:name":"Marwin Bvba",
    "wof:placetype":"venue"
},
  "geometry": {"coordinates":[3.2929899693,50.8319549561],"type":"Point"}
}