{
  "type": "Feature",
  "properties": {
    "iso:country":"BE",
    "sg:address":"Oostereindestraat 65-67",
    "sg:city":"Lummen",
    "sg:classifiers":[
        {
            "category":"Building & Trades",
            "subcategory":"Electrical",
            "type":"Services"
        }
    ],
    "sg:phone":"+32 13 52 15 55",
    "sg:postcode":"3560",
    "sg:province":"Limburg",
    "sg:tags":[
        "electric",
        "-",
        "housewiring",
        "contractor"
    ],
    "wof:name":"Schepers J",
    "wof:placetype":"venue"
},
  "geometry": {"coordinates":[5.2036709785,50.9899902344],"type":"Point"}
}