{
  "type": "Feature",
  "properties": {
    "iso:country":"BE",
    "sg:address":"Fortstraat 33a",
    "sg:city":"Lebbeke",
    "sg:classifiers":[
        {
            "category":"Wholesale",
            "subcategory":"Machinery & Supplies",
            "type":"Manufacturing & Wholesale Goods"
        }
    ],
    "sg:phone":"+32 52 41 55 00",
    "sg:postcode":"9280",
    "sg:province":"Oost-Vlaanderen",
    "sg:tags":[
        "refrigeration",
        "-",
        "industrial",
        "commercial",
        "equipment"
    ],
    "wof:name":"L.v.s. Bvba",
    "wof:placetype":"venue"
},
  "geometry": {"coordinates":[4.1299791336,51.00806427],"type":"Point"}
}