{
  "type": "Feature",
  "properties": {
    "addr:full":"Scheepsdalelaan 17 Brugge West-Vlaanderen 8000",
    "addr:housenumber":"17",
    "addr:postcode":"8000",
    "addr:street":"Scheepsdalelaan",
    "iso:country":"BE",
    "sg:address":"Scheepsdalelaan 17",
    "sg:city":"Brugge",
    "sg:classifiers":[
        {
            "category":"Health Services",
            "subcategory":"Dentist",
            "type":"Services"
        }
    ],
    "sg:phone":"+32 50 32 00 90",
    "sg:postcode":"8000",
    "sg:province":"West-Vlaanderen",
    "wof:name":"Croenen F",
    "wof:placetype":"venue"
},
  "geometry": {"coordinates":[3.212198019,51.2172584534],"type":"Point"}
}