{
  "type": "Feature",
  "properties": {
    "addr:full":"Rue De Custinne 111bb Ciney Namur 5590",
    "addr:housenumber":"111bb",
    "addr:postcode":"5590",
    "addr:street":"Rue De Custinne",
    "iso:country":"BE",
    "sg:address":"Rue De Custinne 111bb",
    "sg:city":"Ciney",
    "sg:classifiers":[
        {
            "category":"Arena",
            "subcategory":"Sports Club",
            "type":"Entertainment"
        }
    ],
    "sg:phone":"+32 83 21 40 00",
    "sg:postcode":"5590",
    "sg:province":"Namur",
    "sg:tags":[
        "terrain",
        "hors",
        "de",
        "installation",
        "sportifs"
    ],
    "wof:name":"Chevetogne-football",
    "wof:placetype":"venue"
},
  "geometry": {"coordinates":[5.1022520065,50.297088623],"type":"Point"}
}