{
  "type": "Feature",
  "properties": {
    "iso:country":"BE",
    "sg:address":"Ter Olmen 51",
    "sg:city":"Ieper",
    "sg:orig_category":"Meubelzaken, woning- and keukeninrichting",
    "sg:phone":"+32 57 20 14 70",
    "sg:postcode":"8900",
    "sg:province":"West-Vlaanderen",
    "wof:name":"Luc Del'haye",
    "wof:placetype":"venue"
},
  "geometry": {"coordinates":[2.877931118,50.8373374939],"type":"Point"}
}