{
  "type": "Feature",
  "properties": {
    "iso:country":"BE",
    "sg:address":"Violierenlaan 17",
    "sg:city":"Bredene",
    "sg:orig_category":"Services de recherches and bureaux de d\u00e9tectives",
    "sg:phone":"+32 59 32 23 66",
    "sg:postcode":"8450",
    "sg:province":"West-Vlaanderen",
    "wof:name":"Patrick Hendriks",
    "wof:placetype":"venue"
},
  "geometry": {"coordinates":[2.9844810963,51.2530555725],"type":"Point"}
}