{
  "type": "Feature",
  "properties": {
    "addr:full":"Torhoutsesteenweg 380 Oostende West-Vlaanderen 8400",
    "addr:housenumber":"380",
    "addr:postcode":"8400",
    "addr:street":"Torhoutsesteenweg",
    "iso:country":"BE",
    "sg:address":"Torhoutsesteenweg 380",
    "sg:city":"Oostende",
    "sg:classifiers":[
        {
            "category":"Bars & Pubs",
            "type":"Food & Drink"
        }
    ],
    "sg:phone":"+32 59 70 51 36",
    "sg:postcode":"8400",
    "sg:province":"West-Vlaanderen",
    "wof:name":"Cafe Westrozebeke",
    "wof:placetype":"venue"
},
  "geometry": {"coordinates":[2.9060668945,51.2135772705],"type":"Point"}
}