{
  "type": "Feature",
  "properties": {
    "iso:country":"BE",
    "sg:address":"Chauss\u00e9e De Charleroi 91 Box 1",
    "sg:city":"Charleroi (gilly)",
    "sg:classifiers":[
        {
            "category":"Shopping",
            "subcategory":"Crafts & Fabrics",
            "type":"Retail Goods"
        }
    ],
    "sg:phone":"+32 71 28 76 15",
    "sg:postcode":"6060",
    "sg:province":"Hainaut",
    "sg:tags":[
        "hi-fi",
        "equipment",
        "stereophonic",
        "-"
    ],
    "wof:name":"Go Tech",
    "wof:placetype":"venue"
},
  "geometry": {"coordinates":[4.4738240242,50.4016075134],"type":"Point"}
}