{
  "type": "Feature",
  "properties": {
    "iso:country":"BE",
    "sg:address":"Staatsbaan 15",
    "sg:city":"Bekkevoort",
    "sg:classifiers":[
        {
            "category":"Recreation",
            "subcategory":"Dance Hall",
            "type":"Entertainment"
        }
    ],
    "sg:phone":"+32 13 33 47 75",
    "sg:postcode":"3460",
    "sg:province":"Vlaams-Brabant",
    "sg:tags":[
        "discotheque"
    ],
    "wof:name":"De Casteleyn",
    "wof:placetype":"venue"
},
  "geometry": {"coordinates":[4.9852399826,50.9479370117],"type":"Point"}
}