{
  "type": "Feature",
  "properties": {
    "addr:full":"Beringersteenweg 60 Heusden-zolder Limburg 3550",
    "addr:housenumber":"60",
    "addr:postcode":"3550",
    "addr:street":"Beringersteenweg",
    "iso:country":"BE",
    "sg:address":"Beringersteenweg 60",
    "sg:city":"Heusden-zolder",
    "sg:classifiers":[
        {
            "category":"Shopping",
            "subcategory":"Clothing, Apparel, & Fashions",
            "type":"Retail Goods"
        }
    ],
    "sg:phone":"+32 11 43 15 91",
    "sg:postcode":"3550",
    "sg:province":"Limburg",
    "sg:tags":[
        "v\u00eatements",
        "pour",
        "dame"
    ],
    "wof:name":"Darros",
    "wof:placetype":"venue"
},
  "geometry": {"coordinates":[5.2598190308,51.0296440125],"type":"Point"}
}