{
  "type": "Feature",
  "properties": {
    "addr:full":"Rue De Flandre 20 Brussel Bruxelles-Capitale 1000",
    "addr:housenumber":"20",
    "addr:postcode":"1000",
    "addr:street":"Rue De Flandre",
    "iso:country":"BE",
    "sg:address":"Rue De Flandre 20",
    "sg:city":"Brussel",
    "sg:classifiers":[
        {
            "category":"Restaurant",
            "type":"Food & Drink"
        }
    ],
    "sg:phone":"+32 2 513 43 23",
    "sg:postcode":"1000",
    "sg:province":"Bruxelles-Capitale",
    "wof:name":"Le Pr\u00c9 Sal\u00c9",
    "wof:placetype":"venue"
},
  "geometry": {"coordinates":[4.3468370438,50.8508377075],"type":"Point"}
}