{
  "type": "Feature",
  "properties": {
    "iso:country":"BE",
    "sg:address":"Rue Abb\u00c9 Toussaint 48",
    "sg:city":"Waimes/waimes",
    "sg:orig_category":"Woningbouw",
    "sg:phone":"+32 80 44 57 35",
    "sg:postcode":"4950",
    "sg:province":"Li\u00e8ge",
    "wof:name":"Heukemes Ren\u00c9",
    "wof:placetype":"venue"
},
  "geometry": {"coordinates":[6.1406908035,50.4036178589],"type":"Point"}
}