{
  "type": "Feature",
  "properties": {
    "iso:country":"BE",
    "sg:address":"Place Franklin Roosevelt 4",
    "sg:city":"Renaix",
    "sg:classifiers":[
        {
            "category":"Sports & Exercise",
            "subcategory":"Ski Slope",
            "type":"Entertainment"
        }
    ],
    "sg:phone":"+32 55 21 10 71",
    "sg:postcode":"9600",
    "sg:province":"Oost-Vlaanderen",
    "sg:tags":[
        "equipment"
    ],
    "wof:name":"Vallez Sport (intersport)",
    "wof:placetype":"venue"
},
  "geometry": {"coordinates":[3.599230051,50.7471504211],"type":"Point"}
}