{
  "type": "Feature",
  "properties": {
    "iso:country":"BE",
    "sg:address":"Pastoor Weytslaan 28 Box 6",
    "sg:city":"Kalmthout",
    "sg:classifiers":[
        {
            "category":"Banks & Credit Unions",
            "subcategory":"Investment Brokerage",
            "type":"Services"
        }
    ],
    "sg:phone":"+32 3 666 05 59",
    "sg:postcode":"2920",
    "sg:province":"Antwerpen",
    "sg:tags":[
        "jean",
        "casual",
        "wear"
    ],
    "wof:name":"Davanzo",
    "wof:placetype":"venue"
},
  "geometry": {"coordinates":[4.4734101295,51.3928070068],"type":"Point"}
}