{
  "type": "Feature",
  "properties": {
    "addr:full":"Papenvoort 3 Rijkevorsel Antwerpen 2310",
    "addr:housenumber":"3",
    "addr:postcode":"2310",
    "addr:street":"Papenvoort",
    "iso:country":"BE",
    "sg:address":"Papenvoort 3",
    "sg:city":"Rijkevorsel",
    "sg:classifiers":[
        {
            "category":"Professional",
            "subcategory":"Accounting & Tax Preparation",
            "type":"Services"
        }
    ],
    "sg:phone":"+32 3 314 68 09",
    "sg:postcode":"2310",
    "sg:province":"Antwerpen",
    "sg:tags":[
        "accountant"
    ],
    "wof:name":"Guy Dielen",
    "wof:placetype":"venue"
},
  "geometry": {"coordinates":[4.8057041168,51.3752632141],"type":"Point"}
}