{
  "type": "Feature",
  "properties": {
    "addr:full":"Fortsesteenweg 17 Sint-katelijne-waver Antwerpen 2860",
    "addr:housenumber":"17",
    "addr:postcode":"2860",
    "addr:street":"Fortsesteenweg",
    "iso:country":"BE",
    "sg:address":"Fortsesteenweg 17",
    "sg:city":"Sint-katelijne-waver",
    "sg:classifiers":[
        {
            "category":"Food & Beverages",
            "subcategory":"Fruits & Vegetables",
            "type":"Retail Goods"
        }
    ],
    "sg:phone":"+32 15 30 61 50",
    "sg:postcode":"2860",
    "sg:province":"Antwerpen",
    "sg:tags":[
        "export",
        "-",
        "import"
    ],
    "wof:name":"Dries Sebrechts Fruit Bvba",
    "wof:placetype":"venue"
},
  "geometry": {"coordinates":[4.5073747635,51.0661697388],"type":"Point"}
}