{
  "type": "Feature",
  "properties": {
    "addr:full":"Waubergstraat 30 Peer Limburg 3990",
    "addr:housenumber":"30",
    "addr:postcode":"3990",
    "addr:street":"Waubergstraat",
    "iso:country":"BE",
    "sg:address":"Waubergstraat 30",
    "sg:city":"Peer",
    "sg:orig_category":"Tuinbenodigdheden",
    "sg:phone":"+32 11 79 13 45",
    "sg:postcode":"3990",
    "sg:province":"Limburg",
    "wof:name":"Vandijck",
    "wof:placetype":"venue"
},
  "geometry": {"coordinates":[5.4587230682,51.0901451111],"type":"Point"}
}