{
  "type": "Feature",
  "properties": {
    "iso:country":"BE",
    "sg:address":"Kruisstraat 70",
    "sg:city":"Lierde (deftinge)",
    "sg:classifiers":[
        {
            "category":"Professional",
            "subcategory":"Accounting & Tax Preparation",
            "type":"Services"
        }
    ],
    "sg:phone":"+32 54 41 27 99",
    "sg:postcode":"9570",
    "sg:province":"Oost-Vlaanderen",
    "sg:tags":[
        "bookkeeper"
    ],
    "wof:name":"Eeman G",
    "wof:placetype":"venue"
},
  "geometry": {"coordinates":[3.8323860168,50.7850036621],"type":"Point"}
}