{
  "type": "Feature",
  "properties": {
    "addr:full":"Rue Trieu Albart 60 Gilly Hainaut 6060",
    "addr:housenumber":"60",
    "addr:postcode":"6060",
    "addr:street":"Rue Trieu Albart",
    "iso:country":"BE",
    "sg:address":"Rue Trieu Albart 60",
    "sg:city":"Gilly",
    "sg:orig_category":"Herstellingen and onderhoud van auto's Voertuigen",
    "sg:phone":"+32 71 41 10 22",
    "sg:postcode":"6060",
    "sg:province":"Hainaut",
    "wof:name":"Le Garage De Trieu",
    "wof:placetype":"venue"
},
  "geometry": {"coordinates":[4.4710302353,50.4299697876],"type":"Point"}
}