{
  "type": "Feature",
  "properties": {
    "iso:country":"BE",
    "sg:address":"Minervastraat 18",
    "sg:city":"Mortsel",
    "sg:orig_category":"Speciaalzaken",
    "sg:phone":"+32 3 440 36 19",
    "sg:postcode":"2640",
    "sg:province":"Antwerpen",
    "wof:name":"Nicomatic",
    "wof:placetype":"venue"
},
  "geometry": {"coordinates":[4.4407219887,51.1722373962],"type":"Point"}
}