{
  "type": "Feature",
  "properties": {
    "iso:country":"BE",
    "sg:address":"Avenue Des Rogations 93",
    "sg:city":"Bruxelles (woluwe-saint-lambert)",
    "sg:classifiers":[
        {
            "category":"Professional",
            "subcategory":"Art Services",
            "type":"Services"
        }
    ],
    "sg:phone":"+32 2 736 28 59",
    "sg:postcode":"1200",
    "sg:province":"Bruxelles-Capitale",
    "sg:tags":[
        "photographer",
        "-",
        "portrait"
    ],
    "wof:name":"Veldeman Photo Brussels",
    "wof:placetype":"venue"
},
  "geometry": {"coordinates":[4.4023017883,50.8421401978],"type":"Point"}
}