{
  "type": "Feature",
  "properties": {
    "addr:full":"Place Roi Baudouin 10d Manage Hainaut 7170",
    "addr:housenumber":"10d",
    "addr:postcode":"7170",
    "addr:street":"Place Roi Baudouin",
    "iso:country":"BE",
    "sg:address":"Place Roi Baudouin 10d",
    "sg:city":"Manage",
    "sg:orig_category":"Journaux. Tabac",
    "sg:phone":"+32 64 54 09 15",
    "sg:postcode":"7170",
    "sg:province":"Hainaut",
    "wof:name":"Maison L'impr\u00c9vu",
    "wof:placetype":"venue"
},
  "geometry": {"coordinates":[4.2166380882,50.5024871826],"type":"Point"}
}