{
  "type": "Feature",
  "properties": {
    "addr:full":"Rue Du Tournay 72b Oupeye Li\u00e8ge 4683",
    "addr:housenumber":"72b",
    "addr:postcode":"4683",
    "addr:street":"Rue Du Tournay",
    "iso:country":"BE",
    "sg:address":"Rue Du Tournay 72b",
    "sg:city":"Oupeye",
    "sg:orig_category":"Plaatsen van vloer- and muurbekleding Schilders",
    "sg:phone":"+32 4 248 28 58",
    "sg:postcode":"4683",
    "sg:province":"Li\u00e8ge",
    "wof:name":"Jean-marie Horrion",
    "wof:placetype":"venue"
},
  "geometry": {"coordinates":[5.6495499611,50.6958198547],"type":"Point"}
}