{
  "type": "Feature",
  "properties": {
    "iso:country":"BE",
    "sg:address":"Brusselsesteenweg 4",
    "sg:city":"Gent",
    "sg:orig_category":"Boucheries",
    "sg:phone":"+32 9 231 52 84",
    "sg:postcode":"9050",
    "sg:province":"Oost-Vlaanderen",
    "wof:name":"Renmans",
    "wof:placetype":"venue"
},
  "geometry": {"coordinates":[3.7409698963,51.0414886475],"type":"Point"}
}