{
  "type": "Feature",
  "properties": {
    "addr:full":"Kruisboogstraat 58 Herentals Antwerpen 2200",
    "addr:housenumber":"58",
    "addr:postcode":"2200",
    "addr:street":"Kruisboogstraat",
    "iso:country":"BE",
    "sg:address":"Kruisboogstraat 58",
    "sg:city":"Herentals",
    "sg:classifiers":[
        {
            "category":"Arena",
            "subcategory":"Sports Club",
            "type":"Entertainment"
        }
    ],
    "sg:phone":"+32 14 70 76 67",
    "sg:postcode":"2200",
    "sg:province":"Antwerpen",
    "wof:name":"Akyama Ju-jitsu Vzw",
    "wof:placetype":"venue"
},
  "geometry": {"coordinates":[4.8611941338,51.1805305481],"type":"Point"}
}