{
  "type": "Feature",
  "properties": {
    "addr:full":"Essenestraat 24 Ternat Vlaams-Brabant 1740",
    "addr:housenumber":"24",
    "addr:postcode":"1740",
    "addr:street":"Essenestraat",
    "iso:country":"BE",
    "sg:address":"Essenestraat 24",
    "sg:city":"Ternat",
    "sg:classifiers":[
        {
            "category":"Professional",
            "subcategory":"Engineering",
            "type":"Services"
        }
    ],
    "sg:phone":"+32 2 582 15 05",
    "sg:postcode":"1740",
    "sg:province":"Vlaams-Brabant",
    "sg:tags":[
        "-"
    ],
    "wof:name":"Tsm Logistic",
    "wof:placetype":"venue"
},
  "geometry": {"coordinates":[4.1602787971,50.8840179443],"type":"Point"}
}