{
  "type": "Feature",
  "properties": {
    "addr:full":"Pannestraat 97 Lanaken Limburg 3620",
    "addr:housenumber":"97",
    "addr:postcode":"3620",
    "addr:street":"Pannestraat",
    "iso:country":"BE",
    "sg:address":"Pannestraat 97",
    "sg:city":"Lanaken",
    "sg:classifiers":[
        {
            "category":"Arena",
            "subcategory":"Sports Club",
            "type":"Entertainment"
        }
    ],
    "sg:phone":"+32 89 71 82 49",
    "sg:postcode":"3620",
    "sg:province":"Limburg",
    "sg:tags":[
        "de"
    ],
    "wof:name":"P.c. Sparrendal",
    "wof:placetype":"venue"
},
  "geometry": {"coordinates":[5.6368231773,50.8890914917],"type":"Point"}
}