{
  "type": "Feature",
  "properties": {
    "iso:country":"BE",
    "sg:address":"Lode Baekelmanslaan 13",
    "sg:city":"Kapellen",
    "sg:classifiers":[
        {
            "category":"Professional",
            "subcategory":"Computer Services",
            "type":"Services"
        }
    ],
    "sg:phone":"+32 3 295 88 04",
    "sg:postcode":"2950",
    "sg:province":"Antwerpen",
    "sg:tags":[
        "webdesign",
        "-",
        "internet"
    ],
    "wof:name":"Squirrel",
    "wof:placetype":"venue"
},
  "geometry": {"coordinates":[4.4482941628,51.3275299072],"type":"Point"}
}