{
  "type": "Feature",
  "properties": {
    "addr:full":"Koningin Astridstraat 2 Sint-truiden Limburg 3800",
    "addr:housenumber":"2",
    "addr:postcode":"3800",
    "addr:street":"Koningin Astridstraat",
    "iso:country":"BE",
    "sg:address":"Koningin Astridstraat 2",
    "sg:city":"Sint-truiden",
    "sg:orig_category":"Artsen and specialisten",
    "sg:phone":"+32 11 68 98 12",
    "sg:postcode":"3800",
    "sg:province":"Limburg",
    "wof:name":"Remy Matterne",
    "wof:placetype":"venue"
},
  "geometry": {"coordinates":[5.1792788506,50.8171577454],"type":"Point"}
}