{
  "type": "Feature",
  "properties": {
    "iso:country":"BE",
    "sg:address":"H\u00e9 De La Bruy\u00e8re 16",
    "sg:city":"Malmedy",
    "sg:classifiers":[
        {
            "category":"Health Services",
            "subcategory":"Doctor",
            "type":"Services"
        }
    ],
    "sg:phone":"+32 80 77 07 18",
    "sg:postcode":"4960",
    "sg:province":"Li\u00e8ge",
    "sg:tags":[
        "medicinephysicians",
        "surgeon"
    ],
    "wof:name":"Kouam Bolivie",
    "wof:placetype":"venue"
},
  "geometry": {"coordinates":[6.0431489944,50.425617218],"type":"Point"}
}