{
  "type": "Feature",
  "properties": {
    "iso:country":"BE",
    "sg:address":"Abeelstraat 21a",
    "sg:city":"Ronse",
    "sg:orig_category":"Voedingsspeciaalzaken",
    "sg:phone":"+32 55 21 50 09",
    "sg:postcode":"9600",
    "sg:province":"Oost-Vlaanderen",
    "wof:name":"Haelters",
    "wof:placetype":"venue"
},
  "geometry": {"coordinates":[3.5999031067,50.7453384399],"type":"Point"}
}