{
  "type": "Feature",
  "properties": {
    "addr:full":"Place Werth 6 Eupen (grand) Li\u00e8ge 4700",
    "addr:housenumber":"6",
    "addr:postcode":"4700",
    "addr:street":"Place Werth;Grand Lie\u0300Ge",
    "iso:country":"BE",
    "sg:address":"Place Werth 6",
    "sg:city":"Eupen (grand)",
    "sg:orig_category":"Supermarch\u00e9s",
    "sg:phone":"+32 87 74 01 48",
    "sg:postcode":"4700",
    "sg:province":"Li\u00e8ge",
    "wof:name":"Colruyt",
    "wof:placetype":"venue"
},
  "geometry": {"coordinates":[6.0386109352,50.6328964233],"type":"Point"}
}