{
  "type": "Feature",
  "properties": {
    "iso:country":"BE",
    "sg:address":"Avenue Des Capucines 27",
    "sg:city":"Schaarbeek/schaerbeek",
    "sg:orig_category":"Artistes ind\u00e9pendants",
    "sg:phone":"+32 2 215 22 47",
    "sg:postcode":"1030",
    "sg:province":"Bruxelles-Capitale",
    "wof:name":"Anne Bailleux",
    "wof:placetype":"venue"
},
  "geometry": {"coordinates":[4.3876028061,50.865032196],"type":"Point"}
}