{
  "type": "Feature",
  "properties": {
    "addr:full":"Vismarkt 4 Kortrijk West-Vlaanderen 8500",
    "addr:housenumber":"4",
    "addr:postcode":"8500",
    "addr:street":"Vismarkt",
    "iso:country":"BE",
    "sg:address":"Vismarkt 4",
    "sg:city":"Kortrijk",
    "sg:orig_category":"Instituts de beaut\u00e9",
    "sg:phone":"+32 56 22 77 05",
    "sg:postcode":"8500",
    "sg:province":"West-Vlaanderen",
    "wof:name":"Celine",
    "wof:placetype":"venue"
},
  "geometry": {"coordinates":[3.2627799511,50.8292274475],"type":"Point"}
}