{
  "type": "Feature",
  "properties": {
    "iso:country":"BE",
    "sg:address":"Paviljoenstraat 4",
    "sg:city":"Brussel/bruxelles",
    "sg:orig_category":"Projectontwikkelaars",
    "sg:phone":"+32 2 245 02 50",
    "sg:postcode":"1000",
    "sg:province":"Bruxelles-Capitale",
    "wof:name":"Conceptimo",
    "wof:placetype":"venue"
},
  "geometry": {"coordinates":[4.3666000366,50.8695983887],"type":"Point"}
}