{
  "type": "Feature",
  "properties": {
    "addr:full":"Luitenant-generaal G\u00e9rardstraat 45 Kuurne West-Vlaanderen 8520",
    "addr:housenumber":"45",
    "addr:postcode":"8520",
    "addr:street":"Ge\u0301Rardstraat",
    "iso:country":"BE",
    "sg:address":"Luitenant-generaal G\u00e9rardstraat 45",
    "sg:city":"Kuurne",
    "sg:classifiers":[
        {
            "category":"Banks & Credit Unions",
            "subcategory":"Investment Brokerage",
            "type":"Services"
        }
    ],
    "sg:phone":"+32 56 71 70 20",
    "sg:postcode":"8520",
    "sg:province":"West-Vlaanderen",
    "sg:tags":[
        "-",
        "sale",
        "yachts",
        "accessory",
        "pleasure",
        "boat"
    ],
    "wof:name":"Demar Marine Cv",
    "wof:placetype":"venue"
},
  "geometry": {"coordinates":[3.2901289463,50.8483352661],"type":"Point"}
}