{
  "type": "Feature",
  "properties": {
    "iso:country":"BE",
    "sg:address":"Donkerstraat 50",
    "sg:city":"Bonheiden",
    "sg:orig_category":"Plomberie, chauffage and installations sanitaires",
    "sg:phone":"+32 15 51 75 62",
    "sg:postcode":"2820",
    "sg:province":"Antwerpen",
    "wof:name":"Rene Storms",
    "wof:placetype":"venue"
},
  "geometry": {"coordinates":[4.5496602058,51.0218009949],"type":"Point"}
}