{
  "type": "Feature",
  "properties": {
    "addr:full":"Chauss\u00e9e D'ixelles 296-325 Bruxelles (ixelles) Bruxelles-Capitale 1050",
    "addr:postcode":"296-325;1050",
    "addr:street":"Chausse\u0301E D'Ixelles",
    "iso:country":"BE",
    "sg:address":"Chauss\u00e9e D'ixelles 296-325",
    "sg:city":"Bruxelles (ixelles)",
    "sg:classifiers":[
        {
            "category":"Home & Garden",
            "subcategory":"Home Furnishings",
            "type":"Retail Goods"
        }
    ],
    "sg:phone":"+32 2 647 93 29",
    "sg:postcode":"1050",
    "sg:province":"Bruxelles-Capitale",
    "sg:tags":[
        "curtain",
        "-",
        "fixture"
    ],
    "wof:name":"Xl D\u00e9cor Sprl",
    "wof:placetype":"venue"
},
  "geometry": {"coordinates":[4.3709058762,50.8287773132],"type":"Point"}
}