{
  "type": "Feature",
  "properties": {
    "addr:full":"Place Communale 1 Courcelles Hainaut 6181",
    "addr:housenumber":"1",
    "addr:postcode":"6181",
    "addr:street":"Place Communale",
    "iso:country":"BE",
    "sg:address":"Place Communale 1",
    "sg:city":"Courcelles",
    "sg:orig_category":"Openbare veiligheid",
    "sg:phone":"+32 71 84 41 27",
    "sg:postcode":"6181",
    "sg:province":"Hainaut",
    "wof:name":"Police F\u00c9d\u00c9rale/federale Politie",
    "wof:placetype":"venue"
},
  "geometry": {"coordinates":[4.3283648491,50.4866065979],"type":"Point"}
}