{
  "type": "Feature",
  "properties": {
    "iso:country":"BE",
    "sg:address":"Doorniksesteenweg 202",
    "sg:city":"Avelgem",
    "sg:classifiers":[
        {
            "category":"Home & Garden",
            "subcategory":"Building Materials",
            "type":"Retail Goods"
        }
    ],
    "sg:phone":"+32 56 64 40 42",
    "sg:postcode":"8580",
    "sg:province":"West-Vlaanderen",
    "sg:tags":[
        "article",
        "-",
        "do-it-yourself"
    ],
    "wof:name":"Houtmagazijn Verdonckt Sa",
    "wof:placetype":"venue"
},
  "geometry": {"coordinates":[3.4453070164,50.7709579468],"type":"Point"}
}