{
  "type": "Feature",
  "properties": {
    "iso:country":"BE",
    "sg:address":"Sint-martinusplein 11b11b",
    "sg:city":"Genk",
    "sg:classifiers":[
        {
            "category":"Shopping",
            "subcategory":"Clothing, Apparel, & Fashions",
            "type":"Retail Goods"
        }
    ],
    "sg:phone":"+32 89 30 36 27",
    "sg:postcode":"3600",
    "sg:province":"Limburg",
    "sg:tags":[
        "v\u00eatements",
        "pour",
        "dame"
    ],
    "wof:name":"Huis Sharivari",
    "wof:placetype":"venue"
},
  "geometry": {"coordinates":[5.4979271889,50.9649467468],"type":"Point"}
}