{
  "type": "Feature",
  "properties": {
    "addr:full":"Rue Lieutenant Liedel 87 Anderlecht Bruxelles-Capitale 1070",
    "addr:housenumber":"87",
    "addr:postcode":"1070",
    "addr:street":"Rue Lieutenant Liedel",
    "iso:country":"BE",
    "sg:address":"Rue Lieutenant Liedel 87",
    "sg:city":"Anderlecht",
    "sg:classifiers":[
        {
            "category":"Personal",
            "subcategory":"Beauty Salon",
            "type":"Services"
        }
    ],
    "sg:phone":"+32 2 521 68 40",
    "sg:postcode":"1070",
    "sg:province":"Bruxelles-Capitale",
    "sg:tags":[
        "de",
        "coiffure"
    ],
    "wof:name":"Coiffure Erik",
    "wof:placetype":"venue"
},
  "geometry": {"coordinates":[4.3025407791,50.8319702148],"type":"Point"}
}