{
  "type": "Feature",
  "properties": {
    "addr:full":"Chauss\u00e9e De Wavre 88 Bruxelles (ixelles) Bruxelles-Capitale 1050",
    "addr:housenumber":"88",
    "addr:postcode":"1050",
    "addr:street":"Chausse\u0301E De Wavre",
    "iso:country":"BE",
    "sg:address":"Chauss\u00e9e De Wavre 88",
    "sg:city":"Bruxelles (ixelles)",
    "sg:classifiers":[
        {
            "category":"Professional",
            "subcategory":"Testing Lab",
            "type":"Services"
        }
    ],
    "sg:phone":"+32 2 511 15 87",
    "sg:postcode":"1050",
    "sg:province":"Bruxelles-Capitale",
    "sg:tags":[
        "chemist"
    ],
    "wof:name":"Paix (pharmacie De La)",
    "wof:placetype":"venue"
},
  "geometry": {"coordinates":[4.3661551476,50.8367958069],"type":"Point"}
}