{
  "type": "Feature",
  "properties": {
    "addr:full":"Rue Des Pignons 20 Rouvroy Luxembourg 6767",
    "addr:housenumber":"20",
    "addr:postcode":"6767",
    "addr:street":"Rue Des Pignons",
    "iso:country":"BE",
    "sg:address":"Rue Des Pignons 20",
    "sg:city":"Rouvroy",
    "sg:orig_category":"Voedingsspeciaalzaken",
    "sg:phone":"+32 63 58 22 44",
    "sg:postcode":"6767",
    "sg:province":"Luxembourg",
    "wof:name":"Serge Dehareng",
    "wof:placetype":"venue"
},
  "geometry": {"coordinates":[5.4905800819,49.5384864807],"type":"Point"}
}