{
  "type": "Feature",
  "properties": {
    "iso:country":"BE",
    "sg:address":"Molenstede 9",
    "sg:city":"Knokke-heist",
    "sg:orig_category":"Epiceries",
    "sg:phone":"+32 50 61 23 70",
    "sg:postcode":"8300",
    "sg:province":"West-Vlaanderen",
    "wof:name":"Christel Gheselle",
    "wof:placetype":"venue"
},
  "geometry": {"coordinates":[3.3144600391,51.3394546509],"type":"Point"}
}