{
  "type": "Feature",
  "properties": {
    "addr:full":"Berchemstraat 38 Dilbeek Vlaams-Brabant 1700",
    "addr:housenumber":"38",
    "addr:postcode":"1700",
    "addr:street":"Berchemstraat",
    "iso:country":"BE",
    "sg:address":"Berchemstraat 38",
    "sg:city":"Dilbeek",
    "sg:classifiers":[
        {
            "category":"Building & Trades",
            "subcategory":"Landscaping Services",
            "type":"Services"
        }
    ],
    "sg:phone":"+32 2 567 12 06",
    "sg:postcode":"1700",
    "sg:province":"Vlaams-Brabant",
    "sg:tags":[
        "gardening",
        "garden",
        "maintenance"
    ],
    "wof:name":"Tuingaston",
    "wof:placetype":"venue"
},
  "geometry": {"coordinates":[4.2677807808,50.845993042],"type":"Point"}
}