{
  "type": "Feature",
  "properties": {
    "addr:full":"Hoevedreef 36 Kuurne West-Vlaanderen 8520",
    "addr:housenumber":"36",
    "addr:postcode":"8520",
    "addr:street":"Hoevedreef",
    "iso:country":"BE",
    "sg:address":"Hoevedreef 36",
    "sg:city":"Kuurne",
    "sg:orig_category":"Plaatsen van vloer- and muurbekleding Schilders",
    "sg:phone":"+32 56 35 13 88",
    "sg:postcode":"8520",
    "sg:province":"West-Vlaanderen",
    "wof:name":"Raphael Buyze",
    "wof:placetype":"venue"
},
  "geometry": {"coordinates":[3.2759819031,50.8502159119],"type":"Point"}
}