{
  "type": "Feature",
  "properties": {
    "iso:country":"BE",
    "sg:address":"Schaluin 121",
    "sg:city":"Aarschot",
    "sg:classifiers":[
        {
            "category":"Sports & Exercise",
            "subcategory":"Ski Slope",
            "type":"Entertainment"
        }
    ],
    "sg:phone":"+32 16 56 36 59",
    "sg:postcode":"3200",
    "sg:province":"Vlaams-Brabant",
    "sg:tags":[
        "equipment"
    ],
    "wof:name":"Trendsport Nv",
    "wof:placetype":"venue"
},
  "geometry": {"coordinates":[4.8409910202,50.9910888672],"type":"Point"}
}