{
  "type": "Feature",
  "properties": {
    "iso:country":"BE",
    "sg:address":"Lion D'orweg 10",
    "sg:city":"Aalst",
    "sg:orig_category":"Non-Classified Establishments",
    "sg:phone":"+32 53 82 55 55",
    "sg:postcode":"9300",
    "sg:province":"Oost-Vlaanderen",
    "wof:name":"New Limalux Bvba",
    "wof:placetype":"venue"
},
  "geometry": {"coordinates":[4.0398421288,50.9537353516],"type":"Point"}
}