{
  "type": "Feature",
  "properties": {
    "addr:full":"Zandvliet 42 Dessel Antwerpen 2480",
    "addr:housenumber":"42",
    "addr:postcode":"2480",
    "addr:street":"Zandvliet",
    "iso:country":"BE",
    "sg:address":"Zandvliet 42",
    "sg:city":"Dessel",
    "sg:classifiers":[
        {
            "category":"Health Services",
            "subcategory":"Dentist",
            "type":"Services"
        }
    ],
    "sg:phone":"+32 14 37 97 81",
    "sg:postcode":"2480",
    "sg:province":"Antwerpen",
    "wof:name":"Neyens Alice",
    "wof:placetype":"venue"
},
  "geometry": {"coordinates":[5.1223359108,51.2374000549],"type":"Point"}
}