{
  "type": "Feature",
  "properties": {
    "iso:country":"BE",
    "sg:address":"Hameau Rosi\u00e8re 83g",
    "sg:city":"Vaux-sur-s\u00fbre (vaux-lez-rosi\u00e8res)",
    "sg:classifiers":[
        {
            "category":"Personal",
            "subcategory":"Beauty Salon",
            "type":"Services"
        }
    ],
    "sg:phone":"+32 61 26 69 18",
    "sg:postcode":"6640",
    "sg:province":"Luxembourg",
    "wof:name":"Louis Ch",
    "wof:placetype":"venue"
},
  "geometry": {"coordinates":[5.5671000481,49.91065979],"type":"Point"}
}