{
  "type": "Feature",
  "properties": {
    "addr:full":"Mechelsestw 8 Mortsel 2510",
    "addr:housenumber":"8",
    "addr:postcode":"2510",
    "addr:street":"Mechelsestw",
    "iso:country":"BE",
    "sg:address":"Mechelsestw 8",
    "sg:city":"Mortsel",
    "sg:classifiers":[
        {
            "category":"Banks & Credit Unions",
            "subcategory":"Bank",
            "type":"Services"
        }
    ],
    "sg:phone":"+32 3 440 06 46",
    "sg:postcode":"2510",
    "wof:name":"Aslk-cger Bank",
    "wof:placetype":"venue"
},
  "geometry": {"coordinates":[4.4624400139,51.1656799316],"type":"Point"}
}