{
  "type": "Feature",
  "properties": {
    "iso:country":"BE",
    "sg:address":"Hollevoordestraat 23",
    "sg:city":"Zedelgem",
    "sg:orig_category":"Woningbouw",
    "sg:phone":"+32 50 27 74 71",
    "sg:postcode":"8210",
    "sg:province":"West-Vlaanderen",
    "wof:name":"Umberto Anseeuw",
    "wof:placetype":"venue"
},
  "geometry": {"coordinates":[3.1333250999,51.1156158447],"type":"Point"}
}