{
  "type": "Feature",
  "properties": {
    "iso:country":"BE",
    "sg:address":"Rue Mathieu-laensbergh 46",
    "sg:city":"Li\u00e8ge 1",
    "sg:classifiers":[
        {
            "category":"Home & Garden",
            "subcategory":"Hardware",
            "type":"Retail Goods"
        }
    ],
    "sg:phone":"+32 4 227 14 47",
    "sg:postcode":"4000",
    "sg:province":"Li\u00e8ge",
    "sg:tags":[
        "-"
    ],
    "wof:name":"Rigot Vve",
    "wof:placetype":"venue"
},
  "geometry": {"coordinates":[5.5845718384,50.6496658325],"type":"Point"}
}