{
  "type": "Feature",
  "properties": {
    "iso:country":"BE",
    "sg:address":"Vilvoordesteenweg 435",
    "sg:city":"Grimbergen",
    "sg:orig_category":"Sportclubs",
    "sg:phone":"+32 2 251 18 37",
    "sg:postcode":"1850",
    "sg:province":"Vlaams-Brabant",
    "wof:name":"Wielerclub Borgt",
    "wof:placetype":"venue"
},
  "geometry": {"coordinates":[4.4018559456,50.9255371094],"type":"Point"}
}