{
  "type": "Feature",
  "properties": {
    "addr:full":"Rue Chapelle-de-la-paix 4 Fosses-la-ville Namur 5070",
    "addr:housenumber":"4",
    "addr:postcode":"5070",
    "addr:street":"Rue Chapelle-De-La-Paix",
    "iso:country":"BE",
    "sg:address":"Rue Chapelle-de-la-paix 4",
    "sg:city":"Fosses-la-ville",
    "sg:orig_category":"Services pour animaux domestiques",
    "sg:phone":"+32 71 71 25 84",
    "sg:postcode":"5070",
    "sg:province":"Namur",
    "wof:name":"L'hachienda",
    "wof:placetype":"venue"
},
  "geometry": {"coordinates":[4.6851477623,50.4055862427],"type":"Point"}
}