{
  "type": "Feature",
  "properties": {
    "iso:country":"BE",
    "sg:address":"Vogelzang 52",
    "sg:city":"Sint-pieters-woluwe/woluwe-saint-pierre",
    "sg:orig_category":"Dierenartsen",
    "sg:phone":"+32 2 675 44 47",
    "sg:postcode":"1150",
    "sg:province":"Bruxelles-Capitale",
    "wof:name":"F. Carpet",
    "wof:placetype":"venue"
},
  "geometry": {"coordinates":[4.4159660339,50.8251571655],"type":"Point"}
}