{
  "type": "Feature",
  "properties": {
    "addr:full":"Astridlaan 29 Brugge West-Vlaanderen 8310",
    "addr:housenumber":"29",
    "addr:postcode":"8310",
    "addr:street":"Astridlaan",
    "iso:country":"BE",
    "sg:address":"Astridlaan 29",
    "sg:city":"Brugge",
    "sg:classifiers":[
        {
            "category":"Insurance",
            "subcategory":"Life Insurance",
            "type":"Services"
        }
    ],
    "sg:phone":"+32 50 39 00 93",
    "sg:postcode":"8310",
    "sg:province":"West-Vlaanderen",
    "sg:tags":[
        "assurance"
    ],
    "wof:name":"A.g.f.",
    "wof:placetype":"venue"
},
  "geometry": {"coordinates":[3.2487030029,51.1999588013],"type":"Point"}
}