{
  "type": "Feature",
  "properties": {
    "addr:full":"Rue De L'usine 9 Musson Luxembourg 6750",
    "addr:housenumber":"9",
    "addr:postcode":"6750",
    "addr:street":"Rue De L'Usine",
    "iso:country":"BE",
    "sg:address":"Rue De L'usine 9",
    "sg:city":"Musson",
    "sg:classifiers":[
        {
            "category":"Insurance",
            "subcategory":"Insurance Agent",
            "type":"Services"
        }
    ],
    "sg:phone":"+32 63 67 82 15",
    "sg:postcode":"6750",
    "sg:province":"Luxembourg",
    "sg:tags":[
        "broker"
    ],
    "wof:name":"Dauvent J-p",
    "wof:placetype":"venue"
},
  "geometry": {"coordinates":[5.7187509537,49.5603599548],"type":"Point"}
}