{
  "type": "Feature",
  "properties": {
    "addr:full":"Bld Alfred De Fontaine 11 Charleroi Hainaut 6000",
    "addr:housenumber":"11",
    "addr:postcode":"6000",
    "addr:street":"Bld Alfred De Fontaine;Hainaut",
    "iso:country":"BE",
    "sg:address":"Bld Alfred De Fontaine 11",
    "sg:city":"Charleroi",
    "sg:orig_category":"Artsen and specialisten",
    "sg:phone":"+32 71 33 04 59",
    "sg:postcode":"6000",
    "sg:province":"Hainaut",
    "wof:name":"R. Mal",
    "wof:placetype":"venue"
},
  "geometry": {"coordinates":[4.4463200569,50.4102516174],"type":"Point"}
}