{
  "type": "Feature",
  "properties": {
    "iso:country":"BE",
    "sg:address":"Rue Sainte-marguerite 355",
    "sg:city":"Li\u00e8ge 1",
    "sg:classifiers":[
        {
            "category":"Professional",
            "subcategory":"Art Services",
            "type":"Services"
        }
    ],
    "sg:phone":"+32 4 224 70 50",
    "sg:postcode":"4000",
    "sg:province":"Li\u00e8ge",
    "sg:tags":[
        "photographer"
    ],
    "wof:name":"Daylight Sprl",
    "wof:placetype":"venue"
},
  "geometry": {"coordinates":[5.5512628555,50.6478385925],"type":"Point"}
}