{
  "type": "Feature",
  "properties": {
    "addr:full":"Ch\u00c9e De Philippeville Gerpinnes Hainaut 6280",
    "addr:postcode":"6280",
    "addr:street":"Hainaut",
    "iso:country":"BE",
    "sg:address":"Ch\u00c9e De Philippeville",
    "sg:city":"Gerpinnes",
    "sg:orig_category":"Huisdieren and benodigdheden Royal Canin",
    "sg:phone":"+32 71 36 59 35",
    "sg:postcode":"6280",
    "sg:province":"Hainaut",
    "wof:name":"Pierard",
    "wof:placetype":"venue"
},
  "geometry": {"coordinates":[4.4697208405,50.3601608276],"type":"Point"}
}