{
  "type": "Feature",
  "properties": {
    "iso:country":"BE",
    "sg:address":"Stationsstraat 73",
    "sg:city":"Wetteren",
    "sg:classifiers":[
        {
            "category":"Fast Food",
            "type":"Food & Drink"
        }
    ],
    "sg:phone":"+32 9 366 18 36",
    "sg:postcode":"9230",
    "sg:province":"Oost-Vlaanderen",
    "sg:tags":[
        "fried",
        "stand",
        "potato"
    ],
    "wof:name":"Dany's Friethoek",
    "wof:placetype":"venue"
},
  "geometry": {"coordinates":[3.8838059902,51.002204895],"type":"Point"}
}