{
  "type": "Feature",
  "properties": {
    "addr:full":"Rue Collart 5 Lasne Brabant Wallon 1380",
    "addr:housenumber":"5",
    "addr:postcode":"1380",
    "addr:street":"Rue Collart",
    "iso:country":"BE",
    "sg:address":"Rue Collart 5",
    "sg:city":"Lasne",
    "sg:orig_category":"Artistes ind\u00e9pendants",
    "sg:phone":"+32 2 633 30 85",
    "sg:postcode":"1380",
    "sg:province":"Brabant Wallon",
    "wof:name":"Yves Marien",
    "wof:placetype":"venue"
},
  "geometry": {"coordinates":[4.4929661751,50.664768219],"type":"Point"}
}