{
  "type": "Feature",
  "properties": {
    "iso:country":"BE",
    "sg:address":"Brusselsestraat 125",
    "sg:city":"Leuven",
    "sg:orig_category":"Ordinateurs and \u00e9quipement informatique",
    "sg:phone":"+32 16 31 08 80",
    "sg:postcode":"3000",
    "sg:province":"Vlaams-Brabant",
    "wof:name":"P.s. Testware",
    "wof:placetype":"venue"
},
  "geometry": {"coordinates":[4.6907229424,50.8809967041],"type":"Point"}
}