{
  "type": "Feature",
  "properties": {
    "iso:country":"BE",
    "sg:address":"Vierstraat 7",
    "sg:city":"Heuvelland (wijtschate)",
    "sg:classifiers":[
        {
            "category":"Building & Trades",
            "subcategory":"Pest Control",
            "type":"Services"
        }
    ],
    "sg:phone":"+32 57 44 44 40",
    "sg:postcode":"8953",
    "sg:province":"West-Vlaanderen",
    "sg:tags":[
        "painting",
        "contractor"
    ],
    "wof:name":"Gouwy N",
    "wof:placetype":"venue"
},
  "geometry": {"coordinates":[2.8630568981,50.7976951599],"type":"Point"}
}