{
  "type": "Feature",
  "properties": {
    "iso:country":"BE",
    "sg:address":"Recogne 23",
    "sg:city":"Bastogne",
    "sg:orig_category":"Installation \u00e9lectrique r\u00e9sidentielle",
    "sg:phone":"+32 61 21 61 45",
    "sg:postcode":"6600",
    "sg:province":"Luxembourg",
    "wof:name":"Francis Girs",
    "wof:placetype":"venue"
},
  "geometry": {"coordinates":[5.7148199081,50.0007820129],"type":"Point"}
}