{
  "type": "Feature",
  "properties": {
    "iso:country":"BE",
    "sg:address":"En Hayeneux 41",
    "sg:city":"Herstal",
    "sg:classifiers":[
        {
            "category":"Wholesale",
            "subcategory":"Machinery & Supplies",
            "type":"Manufacturing & Wholesale Goods"
        }
    ],
    "sg:phone":"+32 4 264 28 64",
    "sg:postcode":"4040",
    "sg:province":"Li\u00e8ge",
    "sg:tags":[
        "retail",
        "-",
        "electric"
    ],
    "wof:name":"Paques J M Ets",
    "wof:placetype":"venue"
},
  "geometry": {"coordinates":[5.6198611259,50.6573600769],"type":"Point"}
}