{
  "type": "Feature",
  "properties": {
    "addr:full":"Krekelpad 1 Knokke-heist West-Vlaanderen 8301",
    "addr:housenumber":"1",
    "addr:postcode":"8301",
    "addr:street":"Krekelpad",
    "iso:country":"BE",
    "sg:address":"Krekelpad 1",
    "sg:city":"Knokke-heist",
    "sg:orig_category":"Belastingconsulenten Diverse juridische dienstverlening",
    "sg:phone":"+32 50 51 69 35",
    "sg:postcode":"8301",
    "sg:province":"West-Vlaanderen",
    "wof:name":"Dirk Nollet",
    "wof:placetype":"venue"
},
  "geometry": {"coordinates":[3.2596340179,51.342010498],"type":"Point"}
}