{
  "type": "Feature",
  "properties": {
    "addr:full":"Vinkemolenstraat 74 Oosterzele Oost-Vlaanderen 9860",
    "addr:housenumber":"74",
    "addr:postcode":"9860",
    "addr:street":"Vinkemolenstraat;Oost-Vlaanderen",
    "iso:country":"BE",
    "sg:address":"Vinkemolenstraat 74",
    "sg:city":"Oosterzele",
    "sg:classifiers":[
        {
            "category":"Farming",
            "subcategory":"Livestock Farm",
            "type":"Manufacturing & Wholesale Goods"
        }
    ],
    "sg:phone":"+32 52 42 45 09",
    "sg:postcode":"9860",
    "sg:province":"Oost-Vlaanderen",
    "sg:tags":[
        "stud"
    ],
    "wof:name":"Stoeterij Ariane",
    "wof:placetype":"venue"
},
  "geometry": {"coordinates":[3.8090209961,50.9515037537],"type":"Point"}
}