{
  "type": "Feature",
  "properties": {
    "addr:full":"Bromstraat 1 Poperinge West-Vlaanderen 8972",
    "addr:housenumber":"1",
    "addr:postcode":"8972",
    "addr:street":"Bromstraat",
    "iso:country":"BE",
    "sg:address":"Bromstraat 1",
    "sg:city":"Poperinge",
    "sg:orig_category":"Eleveurs de volaille. Eleveurs and marchands de porcs",
    "sg:phone":"+32 57 30 05 52",
    "sg:postcode":"8972",
    "sg:province":"West-Vlaanderen",
    "wof:name":"Guido Parret",
    "wof:placetype":"venue"
},
  "geometry": {"coordinates":[2.6692841053,50.906124115],"type":"Point"}
}