{
  "type": "Feature",
  "properties": {
    "addr:full":"Rue C\u00c9sar Franck 28 Elsene Bruxelles-Capitale 1050",
    "addr:housenumber":"28",
    "addr:postcode":"1050",
    "addr:street":"Rue Ce\u0301Sar Franck",
    "iso:country":"BE",
    "sg:address":"Rue C\u00c9sar Franck 28",
    "sg:city":"Elsene",
    "sg:orig_category":"Dakwerken",
    "sg:phone":"+32 2 640 50 08",
    "sg:postcode":"1050",
    "sg:province":"Bruxelles-Capitale",
    "wof:name":"Ba-te-co",
    "wof:placetype":"venue"
},
  "geometry": {"coordinates":[4.3905100822,50.8189201355],"type":"Point"}
}