{
  "type": "Feature",
  "properties": {
    "iso:country":"BE",
    "sg:address":"Diepestraat 3",
    "sg:city":"Nevele",
    "sg:orig_category":"Plomberie, chauffage and installations sanitaires",
    "sg:phone":"+32 9 371 62 57",
    "sg:postcode":"9850",
    "sg:province":"Oost-Vlaanderen",
    "wof:name":"Wille",
    "wof:placetype":"venue"
},
  "geometry": {"coordinates":[3.5763709545,51.0741958618],"type":"Point"}
}