{
  "type": "Feature",
  "properties": {
    "addr:full":"Meersstraat 65 Destelbergen Oost-Vlaanderen 9070",
    "addr:housenumber":"65",
    "addr:postcode":"9070",
    "addr:street":"Meersstraat",
    "iso:country":"BE",
    "sg:address":"Meersstraat 65",
    "sg:city":"Destelbergen",
    "sg:orig_category":"D\u00e9molition d\u00b4immeubles and terrassements. D\u00e9chets and d\u00e9bris Gr",
    "sg:phone":"+32 9 230 95 25",
    "sg:postcode":"9070",
    "sg:province":"Oost-Vlaanderen",
    "wof:name":"Clincke",
    "wof:placetype":"venue"
},
  "geometry": {"coordinates":[3.7942650318,51.0401802063],"type":"Point"}
}