{
  "type": "Feature",
  "properties": {
    "addr:full":"Avenue Robert Dalechamp 11 Brussel/bruxelles Bruxelles-Capitale 1200",
    "addr:housenumber":"11",
    "addr:postcode":"1200",
    "addr:street":"Avenue Robert Dalechamp;/",
    "iso:country":"BE",
    "sg:address":"Avenue Robert Dalechamp 11",
    "sg:city":"Brussel/bruxelles",
    "sg:orig_category":"Reisbureaus",
    "sg:phone":"+32 2 742 99 82",
    "sg:postcode":"1200",
    "sg:province":"Bruxelles-Capitale",
    "wof:name":"Geolidays",
    "wof:placetype":"venue"
},
  "geometry": {"coordinates":[4.4140691757,50.846912384],"type":"Point"}
}