{
  "type": "Feature",
  "properties": {
    "iso:country":"BE",
    "sg:address":"Onafhankelijkheidslaan 7",
    "sg:city":"Gent",
    "sg:orig_category":"M\u00e9decins and sp\u00e9cialistes",
    "sg:phone":"+32 9 222 50 11",
    "sg:postcode":"9000",
    "sg:province":"Oost-Vlaanderen",
    "wof:name":"Eric Derie",
    "wof:placetype":"venue"
},
  "geometry": {"coordinates":[3.7157690525,51.0332298279],"type":"Point"}
}