{
  "type": "Feature",
  "properties": {
    "addr:full":"Hooplaan 12 Koksijde West-Vlaanderen 8670",
    "addr:housenumber":"12",
    "addr:postcode":"8670",
    "addr:street":"Hooplaan",
    "iso:country":"BE",
    "sg:address":"Hooplaan 12",
    "sg:city":"Koksijde",
    "sg:classifiers":[
        {
            "category":"Health Services",
            "subcategory":"Health Practitioner",
            "type":"Services"
        }
    ],
    "sg:phone":"+32 58 51 60 97",
    "sg:postcode":"8670",
    "sg:province":"West-Vlaanderen",
    "sg:tags":[
        "therapist",
        "speech"
    ],
    "wof:name":"Dienst Logopedie",
    "wof:placetype":"venue"
},
  "geometry": {"coordinates":[2.648663044,51.1172180176],"type":"Point"}
}