{
  "type": "Feature",
  "properties": {
    "addr:full":"Chauss\u00c9e De La Hulpe 181b11 Bruxelles Bruxelles-Capitale 1170",
    "addr:housenumber":"181b11",
    "addr:postcode":"1170",
    "addr:street":"Chausse\u0301E De La Hulpe",
    "iso:country":"BE",
    "sg:address":"Chauss\u00c9e De La Hulpe 181b11",
    "sg:city":"Bruxelles",
    "sg:orig_category":"HUISBRANDOLIE",
    "sg:phone":"+32 2 663 19 00",
    "sg:postcode":"1170",
    "sg:province":"Bruxelles-Capitale",
    "wof:name":"Transcor Energy",
    "wof:placetype":"venue"
},
  "geometry": {"coordinates":[4.4043002129,50.7956581116],"type":"Point"}
}