{
  "type": "Feature",
  "properties": {
    "iso:country":"BE",
    "sg:address":"Gros Ch\u00eane 2",
    "sg:city":"Havelange (m\u00e9an)",
    "sg:orig_category":"Non-Classified Establishments",
    "sg:phone":"+32 86 32 27 63",
    "sg:postcode":"5372",
    "sg:province":"Namur",
    "wof:name":"Fromagerie Du Gros Chene Scrl",
    "wof:placetype":"venue"
},
  "geometry": {"coordinates":[5.347990036,50.3534736633],"type":"Point"}
}