{
  "type": "Feature",
  "properties": {
    "iso:country":"BE",
    "sg:address":"Diksmuidse Heerweg 126",
    "sg:city":"Brugge",
    "sg:orig_category":"Avocats and conseillers juridiques",
    "sg:phone":"+32 50 39 35 55",
    "sg:postcode":"8200",
    "sg:province":"West-Vlaanderen",
    "wof:name":"Kristoff Soete",
    "wof:placetype":"venue"
},
  "geometry": {"coordinates":[3.1961910725,51.1974143982],"type":"Point"}
}