{
  "type": "Feature",
  "properties": {
    "addr:full":"Rue De La Vall\u00e9e 10 Hotton Luxembourg 6990",
    "addr:housenumber":"10",
    "addr:postcode":"6990",
    "addr:street":"Rue De La Valle\u0301E",
    "iso:country":"BE",
    "sg:address":"Rue De La Vall\u00e9e 10",
    "sg:city":"Hotton",
    "sg:classifiers":[
        {
            "category":"Health Services",
            "subcategory":"Health Practitioner",
            "type":"Services"
        }
    ],
    "sg:phone":"+32 84 46 64 40",
    "sg:postcode":"6990",
    "sg:province":"Luxembourg",
    "sg:tags":[
        "physiotherapist"
    ],
    "wof:name":"Adam Jean-marie",
    "wof:placetype":"venue"
},
  "geometry": {"coordinates":[5.4463038445,50.2689056396],"type":"Point"}
}