{
  "type": "Feature",
  "properties": {
    "iso:country":"BE",
    "sg:address":"Brugstraat 53",
    "sg:city":"Ardooie",
    "sg:classifiers":[
        {
            "category":"Professional",
            "subcategory":"Art Services",
            "type":"Services"
        }
    ],
    "sg:phone":"+32 51 74 89 76",
    "sg:postcode":"8850",
    "sg:province":"West-Vlaanderen",
    "sg:tags":[
        "interior",
        "designer"
    ],
    "wof:name":"Kielemoes F",
    "wof:placetype":"venue"
},
  "geometry": {"coordinates":[3.2023990154,50.9767112732],"type":"Point"}
}