{
  "type": "Feature",
  "properties": {
    "iso:country":"BE",
    "sg:address":"Rue Nouvelle 69",
    "sg:city":"Pepinster",
    "sg:classifiers":[
        {
            "category":"Arena",
            "subcategory":"Sports Club",
            "type":"Entertainment"
        }
    ],
    "sg:phone":"+32 87 31 23 82",
    "sg:postcode":"4860",
    "sg:province":"Li\u00e8ge",
    "sg:tags":[
        "de"
    ],
    "wof:name":"Royal Rouheid B.c.",
    "wof:placetype":"venue"
},
  "geometry": {"coordinates":[5.831384182,50.5772323608],"type":"Point"}
}