{
  "type": "Feature",
  "properties": {
    "addr:full":"Roodhuisweg 33 Kortrijk West-Vlaanderen 8510",
    "addr:housenumber":"33",
    "addr:postcode":"8510",
    "addr:street":"Roodhuisweg",
    "iso:country":"BE",
    "sg:address":"Roodhuisweg 33",
    "sg:city":"Kortrijk",
    "sg:orig_category":"Rev\u00eatements pour sols and murs",
    "sg:phone":"+32 56 21 23 57",
    "sg:postcode":"8510",
    "sg:province":"West-Vlaanderen",
    "wof:name":"Blomme - Waelkens",
    "wof:placetype":"venue"
},
  "geometry": {"coordinates":[3.2855010033,50.7790718079],"type":"Point"}
}