{
  "type": "Feature",
  "properties": {
    "addr:full":"Route De Battice 71 Thimister-clermont (thimister) Li\u00e8ge 4890",
    "addr:housenumber":"71",
    "addr:postcode":"4890",
    "addr:street":"Route De Battice",
    "iso:country":"BE",
    "sg:address":"Route De Battice 71",
    "sg:city":"Thimister-clermont (thimister)",
    "sg:classifiers":[
        {
            "category":"Retail",
            "subcategory":"Car Wash",
            "type":"Services"
        }
    ],
    "sg:phone":"+32 87 44 59 59",
    "sg:postcode":"4890",
    "sg:province":"Li\u00e8ge",
    "sg:tags":[
        "automobile",
        "-",
        "washing",
        "truck",
        "equipment"
    ],
    "wof:name":"Deckers Sa",
    "wof:placetype":"venue"
},
  "geometry": {"coordinates":[5.8398590088,50.667640686],"type":"Point"}
}