{
  "type": "Feature",
  "properties": {
    "addr:full":"Kesselsesteenweg 12 Ranst Antwerpen 2520",
    "addr:housenumber":"12",
    "addr:postcode":"2520",
    "addr:street":"Kesselsesteenweg",
    "iso:country":"BE",
    "sg:address":"Kesselsesteenweg 12",
    "sg:city":"Ranst",
    "sg:orig_category":"Loodgieterij, verwarming and sanitaire installaties",
    "sg:phone":"+32 3 489 07 70",
    "sg:postcode":"2520",
    "sg:province":"Antwerpen",
    "wof:name":"Van Den Wijngaert W",
    "wof:placetype":"venue"
},
  "geometry": {"coordinates":[4.6060438156,51.1598472595],"type":"Point"}
}