{
  "type": "Feature",
  "properties": {
    "addr:full":"Bellestraat 40b6 Sint-niklaas Oost-Vlaanderen 9100",
    "addr:housenumber":"40b6",
    "addr:postcode":"9100",
    "addr:street":"Bellestraat",
    "iso:country":"BE",
    "sg:address":"Bellestraat 40b6",
    "sg:city":"Sint-niklaas",
    "sg:orig_category":"G\u00e9om\u00e8tres. Evaluation and estimation de biens immobiliers",
    "sg:phone":"+32 3 776 57 98",
    "sg:postcode":"9100",
    "sg:province":"Oost-Vlaanderen",
    "wof:name":"Bureau Mensura",
    "wof:placetype":"venue"
},
  "geometry": {"coordinates":[4.1698451042,51.1738090515],"type":"Point"}
}