{
  "type": "Feature",
  "properties": {
    "addr:full":"Boshoek 312 Boechout Antwerpen 2530",
    "addr:housenumber":"312",
    "addr:postcode":"2530",
    "addr:street":"Boshoek",
    "iso:country":"BE",
    "sg:address":"Boshoek 312",
    "sg:city":"Boechout",
    "sg:orig_category":"Articles de jardin. Machines and mat\u00e9riel agricoles Quincailleries",
    "sg:phone":"+32 3 480 77 07",
    "sg:postcode":"2530",
    "sg:province":"Antwerpen",
    "wof:name":"Ceulemans",
    "wof:placetype":"venue"
},
  "geometry": {"coordinates":[4.5211958885,51.13489151],"type":"Point"}
}