{
  "type": "Feature",
  "properties": {
    "addr:full":"Tiendagwandstraat 6 Geraardsbergen (grimminge) Oost-Vlaanderen 9506",
    "addr:housenumber":"6",
    "addr:postcode":"9506",
    "addr:street":"Tiendagwandstraat",
    "iso:country":"BE",
    "sg:address":"Tiendagwandstraat 6",
    "sg:city":"Geraardsbergen (grimminge)",
    "sg:classifiers":[
        {
            "category":"Health Services",
            "subcategory":"Health Practitioner",
            "type":"Services"
        }
    ],
    "sg:phone":"+32 477 26 27 66",
    "sg:postcode":"9506",
    "sg:province":"Oost-Vlaanderen",
    "sg:tags":[
        "therapist",
        "speech"
    ],
    "wof:name":"Burggraeve Kathleen",
    "wof:placetype":"venue"
},
  "geometry": {"coordinates":[3.8985300064,50.7987060547],"type":"Point"}
}