{
  "type": "Feature",
  "properties": {
    "addr:full":"Beukenlaan 28 Hoegaarden Vlaams-Brabant 3320",
    "addr:housenumber":"28",
    "addr:postcode":"3320",
    "addr:street":"Beukenlaan",
    "iso:country":"BE",
    "sg:address":"Beukenlaan 28",
    "sg:city":"Hoegaarden",
    "sg:orig_category":"Woningbouw",
    "sg:phone":"+32 16 76 68 51",
    "sg:postcode":"3320",
    "sg:province":"Vlaams-Brabant",
    "wof:name":"Vanolst",
    "wof:placetype":"venue"
},
  "geometry": {"coordinates":[4.8961992264,50.7756843567],"type":"Point"}
}