{
  "type": "Feature",
  "properties": {
    "addr:full":"Rue G\u00e9n\u00e9ral Michel 17 Namur Namur 5000",
    "addr:housenumber":"17",
    "addr:postcode":"5000",
    "addr:street":"Rue Ge\u0301Ne\u0301Ral Michel",
    "iso:country":"BE",
    "sg:address":"Rue G\u00e9n\u00e9ral Michel 17",
    "sg:city":"Namur",
    "sg:classifiers":[
        {
            "category":"Tea Room",
            "subcategory":"None",
            "type":"Food & Drink"
        }
    ],
    "sg:phone":"+32 81 22 85 78",
    "sg:postcode":"5000",
    "sg:province":"Namur",
    "sg:tags":[
        "whol",
        "-",
        "broker"
    ],
    "wof:name":"Delahaut Cafes",
    "wof:placetype":"venue"
},
  "geometry": {"coordinates":[4.8710861206,50.4672012329],"type":"Point"}
}