{
  "type": "Feature",
  "properties": {
    "iso:country":"BE",
    "sg:address":"Avenue De La Gare 39",
    "sg:city":"Belgium",
    "sg:orig_category":"Autoverhuur Herstellingen and onderhoud van auto's Voertuigen",
    "sg:phone":"+32 61 27 74 44",
    "sg:postcode":"6840",
    "sg:province":"Luxembourg",
    "wof:name":"Garage De La Vierre",
    "wof:placetype":"venue"
},
  "geometry": {"coordinates":[5.438144207,49.8429641724],"type":"Point"}
}