{
  "type": "Feature",
  "properties": {
    "iso:country":"BE",
    "sg:address":"Charles Woestelaan 154",
    "sg:city":"Jette",
    "sg:orig_category":"Rusthuizen and serviceflats",
    "sg:phone":"+32 2 425 78 63",
    "sg:postcode":"1090",
    "sg:province":"Bruxelles-Capitale",
    "wof:name":"Home Bois D'emeraude",
    "wof:placetype":"venue"
},
  "geometry": {"coordinates":[4.3341188431,50.8741493225],"type":"Point"}
}