{
  "type": "Feature",
  "properties": {
    "addr:full":"De Bruynlaan 12b1 Begijnendijk Vlaams-Brabant 3130",
    "addr:housenumber":"12b1",
    "addr:postcode":"3130",
    "addr:street":"De Bruynlaan",
    "iso:country":"BE",
    "sg:address":"De Bruynlaan 12b1",
    "sg:city":"Begijnendijk",
    "sg:orig_category":"Installation \u00e9lectrique industrielle",
    "sg:phone":"+32 16 53 53 24",
    "sg:postcode":"3130",
    "sg:province":"Vlaams-Brabant",
    "wof:name":"Debontridder & Co",
    "wof:placetype":"venue"
},
  "geometry": {"coordinates":[4.7810659409,51.022064209],"type":"Point"}
}