{
  "type": "Feature",
  "properties": {
    "iso:country":"BE",
    "sg:address":"Boulevard Lalaing 43b",
    "sg:city":"Tournai",
    "sg:classifiers":[
        {
            "category":"Health Services",
            "subcategory":"Nursing And Care Facility",
            "type":"Services"
        }
    ],
    "sg:phone":"+32 69 88 45 35",
    "sg:postcode":"7500",
    "sg:province":"Hainaut",
    "sg:tags":[
        "home",
        "rest"
    ],
    "wof:name":"Soeurs De La Charit\u00e9 C.p.a.s.",
    "wof:placetype":"venue"
},
  "geometry": {"coordinates":[3.3869860172,50.6003417969],"type":"Point"}
}