{
  "type": "Feature",
  "properties": {
    "addr:full":"Chauss\u00e9e De Bruxelles 192 Box 2 Nivelles Brabant Wallon 1400",
    "addr:housenumber":"192;2",
    "addr:postcode":"1400",
    "addr:street":"Chausse\u0301E De Bruxelles;Box",
    "iso:country":"BE",
    "sg:address":"Chauss\u00e9e De Bruxelles 192 Box 2",
    "sg:city":"Nivelles",
    "sg:classifiers":[
        {
            "category":"Professional",
            "subcategory":"Accounting & Tax Preparation",
            "type":"Services"
        }
    ],
    "sg:phone":"+32 67 22 08 55",
    "sg:postcode":"1400",
    "sg:province":"Brabant Wallon",
    "sg:tags":[
        "bookkeeper"
    ],
    "wof:name":"Arpigny E",
    "wof:placetype":"venue"
},
  "geometry": {"coordinates":[4.3377399445,50.6118507385],"type":"Point"}
}