{
  "type": "Feature",
  "properties": {
    "addr:full":"Galgstraat 38 Sint-pieters-leeuw Vlaams-Brabant 1600",
    "addr:housenumber":"38",
    "addr:postcode":"1600",
    "addr:street":"Galgstraat",
    "iso:country":"BE",
    "sg:address":"Galgstraat 38",
    "sg:city":"Sint-pieters-leeuw",
    "sg:classifiers":[
        {
            "category":"Food & Beverages",
            "subcategory":"Cheese",
            "type":"Retail Goods"
        }
    ],
    "sg:phone":"+32 2 378 26 90",
    "sg:postcode":"1600",
    "sg:province":"Vlaams-Brabant",
    "sg:tags":[
        "soft"
    ],
    "wof:name":"Vander Gucht B.v.b.a.",
    "wof:placetype":"venue"
},
  "geometry": {"coordinates":[4.2673630714,50.7866744995],"type":"Point"}
}