{
  "type": "Feature",
  "properties": {
    "iso:country":"BE",
    "sg:address":"Rue Du Mambourg 76",
    "sg:city":"Charleroi",
    "sg:orig_category":"V\u00e9los. R\u00e9parations and entretien de motos",
    "sg:phone":"+32 71 32 21 62",
    "sg:postcode":"6000",
    "sg:province":"Hainaut",
    "wof:name":"Maison Doumont",
    "wof:placetype":"venue"
},
  "geometry": {"coordinates":[4.4450731277,50.417591095],"type":"Point"}
}