{
  "type": "Feature",
  "properties": {
    "addr:full":"Winkelhaakstraat 31 Kapellen (mariaburg) Antwerpen 2950",
    "addr:housenumber":"31",
    "addr:postcode":"2950",
    "addr:street":"Winkelhaakstraat",
    "iso:country":"BE",
    "sg:address":"Winkelhaakstraat 31",
    "sg:city":"Kapellen (mariaburg)",
    "sg:classifiers":[
        {
            "category":"Home & Garden",
            "subcategory":"Home Furnishings",
            "type":"Retail Goods"
        }
    ],
    "sg:phone":"+32 3 605 26 75",
    "sg:postcode":"2950",
    "sg:province":"Antwerpen",
    "sg:tags":[
        "decoration"
    ],
    "wof:name":"Elektro Service Ramon Hans",
    "wof:placetype":"venue"
},
  "geometry": {"coordinates":[4.432489872,51.3066329956],"type":"Point"}
}