{
  "type": "Feature",
  "properties": {
    "addr:full":"Kleinven 5 Genk Limburg 3600",
    "addr:housenumber":"5",
    "addr:postcode":"3600",
    "addr:street":"Kleinven",
    "iso:country":"BE",
    "sg:address":"Kleinven 5",
    "sg:city":"Genk",
    "sg:classifiers":[
        {
            "category":"Health Services",
            "subcategory":"Nursing And Care Facility",
            "type":"Services"
        }
    ],
    "sg:phone":"+32 89 30 72 67",
    "sg:postcode":"3600",
    "sg:province":"Limburg",
    "sg:tags":[
        "home"
    ],
    "wof:name":"Honinx Miet",
    "wof:placetype":"venue"
},
  "geometry": {"coordinates":[5.4480500221,50.9690475464],"type":"Point"}
}