{
  "type": "Feature",
  "properties": {
    "iso:country":"BE",
    "sg:address":"Rue Du Trois Juin 52",
    "sg:city":"Herstal",
    "sg:orig_category":"Brood, gebak and snoepgoed",
    "sg:phone":"+32 4 264 41 00",
    "sg:postcode":"4040",
    "sg:province":"Li\u00e8ge",
    "wof:name":"Maison Lemmens-demoulin",
    "wof:placetype":"venue"
},
  "geometry": {"coordinates":[5.63104105,50.6747398376],"type":"Point"}
}