{
  "type": "Feature",
  "properties": {
    "addr:full":"Ieperse Steenweg 127b Veurne West-Vlaanderen 8630",
    "addr:housenumber":"127b",
    "addr:postcode":"8630",
    "addr:street":"Steenweg",
    "iso:country":"BE",
    "sg:address":"Ieperse Steenweg 127b",
    "sg:city":"Veurne",
    "sg:classifiers":[
        {
            "category":"Autos & Motor Vehicles",
            "subcategory":"Automobile Sales",
            "type":"Retail Goods"
        }
    ],
    "sg:phone":"+32 58 31 15 16",
    "sg:postcode":"8630",
    "sg:province":"West-Vlaanderen",
    "sg:tags":[
        "-",
        "truck"
    ],
    "wof:name":"Autostar Nv",
    "wof:placetype":"venue"
},
  "geometry": {"coordinates":[2.6674098969,51.0584754944],"type":"Point"}
}