{
  "type": "Feature",
  "properties": {
    "addr:full":"Weitingstraat 10a Aalter (bellem) Oost-Vlaanderen 9881",
    "addr:housenumber":"10a",
    "addr:postcode":"9881",
    "addr:street":"Weitingstraat",
    "iso:country":"BE",
    "sg:address":"Weitingstraat 10a",
    "sg:city":"Aalter (bellem)",
    "sg:classifiers":[
        {
            "category":"Casinos & Gambling",
            "type":"Entertainment"
        }
    ],
    "sg:phone":"+32 9 374 70 74",
    "sg:postcode":"9881",
    "sg:province":"Oost-Vlaanderen",
    "wof:name":"Aalter Casino Service Las Vegas",
    "wof:placetype":"venue"
},
  "geometry": {"coordinates":[3.4962079525,51.0724334717],"type":"Point"}
}