{
  "type": "Feature",
  "properties": {
    "addr:full":"Kwadenplasstraat 4 Destelbergen Oost-Vlaanderen 9070",
    "addr:housenumber":"4",
    "addr:postcode":"9070",
    "addr:street":"Kwadenplasstraat",
    "iso:country":"BE",
    "sg:address":"Kwadenplasstraat 4",
    "sg:city":"Destelbergen",
    "sg:orig_category":"Artsen and specialisten",
    "sg:phone":"+32 9 228 47 77",
    "sg:postcode":"9070",
    "sg:province":"Oost-Vlaanderen",
    "wof:name":"Henri Van Der Eecken",
    "wof:placetype":"venue"
},
  "geometry": {"coordinates":[3.7846701145,51.063621521],"type":"Point"}
}