{
  "type": "Feature",
  "properties": {
    "addr:full":"Kloosterstraat 94 Moeskroen/mouscron Hainaut 7700",
    "addr:housenumber":"94",
    "addr:postcode":"7700",
    "addr:street":"Kloosterstraat",
    "iso:country":"BE",
    "sg:address":"Kloosterstraat 94",
    "sg:city":"Moeskroen/mouscron",
    "sg:orig_category":"Woningbouw",
    "sg:phone":"+32 56 84 34 12",
    "sg:postcode":"7700",
    "sg:province":"Hainaut",
    "wof:name":"Batistyl",
    "wof:placetype":"venue"
},
  "geometry": {"coordinates":[3.2323200703,50.7400932312],"type":"Point"}
}