{
  "type": "Feature",
  "properties": {
    "iso:country":"BE",
    "sg:address":"Rue Du G\u00e9n\u00e9ral De Gaulle 7",
    "sg:city":"Courcelles",
    "sg:classifiers":[
        {
            "category":"Shopping",
            "subcategory":"Crafts & Fabrics",
            "type":"Retail Goods"
        }
    ],
    "sg:phone":"+32 71 45 08 26",
    "sg:postcode":"6180",
    "sg:province":"Hainaut",
    "sg:tags":[
        "upholstery",
        "-"
    ],
    "wof:name":"Jardini\u00e8re (la)",
    "wof:placetype":"venue"
},
  "geometry": {"coordinates":[4.3802599907,50.4588394165],"type":"Point"}
}