{
  "type": "Feature",
  "properties": {
    "iso:country":"BE",
    "sg:address":"Rue De St\u00c9houx 16",
    "sg:city":"Tubize",
    "sg:orig_category":"Installation de menuiserie en bois and plastique",
    "sg:phone":"+32 2 355 91 45",
    "sg:postcode":"1480",
    "sg:province":"Brabant Wallon",
    "wof:name":"Andre Saublen",
    "wof:placetype":"venue"
},
  "geometry": {"coordinates":[4.2149600983,50.671421051],"type":"Point"}
}