{
  "type": "Feature",
  "properties": {
    "addr:full":"Boniverlei 172b6 Edegem Antwerpen 2650",
    "addr:housenumber":"172b6",
    "addr:postcode":"2650",
    "addr:street":"Boniverlei",
    "iso:country":"BE",
    "sg:address":"Boniverlei 172b6",
    "sg:city":"Edegem",
    "sg:orig_category":"Persagentschappen",
    "sg:phone":"+32 3 458 21 01",
    "sg:postcode":"2650",
    "sg:province":"Antwerpen",
    "wof:name":"Diederik Van Den Abeele",
    "wof:placetype":"venue"
},
  "geometry": {"coordinates":[4.4488768578,51.1482391357],"type":"Point"}
}