{
  "type": "Feature",
  "properties": {
    "addr:full":"Geldenaaksebaan 260 Leuven (heverlee) Vlaams-Brabant 3001",
    "addr:housenumber":"260",
    "addr:postcode":"3001",
    "addr:street":"Geldenaaksebaan",
    "iso:country":"BE",
    "sg:address":"Geldenaaksebaan 260",
    "sg:city":"Leuven (heverlee)",
    "sg:classifiers":[
        {
            "category":"Health Services",
            "subcategory":"Dentist",
            "type":"Services"
        }
    ],
    "sg:phone":"+32 16 40 39 44",
    "sg:postcode":"3001",
    "sg:province":"Vlaams-Brabant",
    "wof:name":"Robberechts Ingrid",
    "wof:placetype":"venue"
},
  "geometry": {"coordinates":[4.7122139931,50.861530304],"type":"Point"}
}