{
  "type": "Feature",
  "properties": {
    "addr:full":"Place Pi\u00c8rre Nothomb 0 Habay Luxembourg 6720",
    "addr:housenumber":"0",
    "addr:postcode":"6720",
    "addr:street":"Place Pie\u0300Rre Nothomb",
    "iso:country":"BE",
    "sg:address":"Place Pi\u00c8rre Nothomb 0",
    "sg:city":"Habay",
    "sg:orig_category":"Openbare bibliotheken and archieven",
    "sg:phone":"+32 61 22 43 20",
    "sg:postcode":"6720",
    "sg:province":"Luxembourg",
    "wof:name":"Discobus",
    "wof:placetype":"venue"
},
  "geometry": {"coordinates":[5.6468100548,49.7278633118],"type":"Point"}
}