{
  "type": "Feature",
  "properties": {
    "iso:country":"BE",
    "sg:address":"Rue Saint-remy 5",
    "sg:city":"Li\u00e8ge 1",
    "sg:classifiers":[
        {
            "category":"Real Estate",
            "subcategory":"Architect",
            "type":"Services"
        }
    ],
    "sg:phone":"+32 4 221 40 55",
    "sg:postcode":"4000",
    "sg:province":"Li\u00e8ge",
    "wof:name":"Atelier Architecture Dessart Philippe Hody Geoffrey-sherrington Thierry",
    "wof:placetype":"venue"
},
  "geometry": {"coordinates":[5.5704312325,50.6390113831],"type":"Point"}
}