{
  "type": "Feature",
  "properties": {
    "iso:country":"BE",
    "sg:address":"Damburgstraat 49",
    "sg:city":"Bocholt",
    "sg:orig_category":"Artsen and specialisten",
    "sg:phone":"+32 89 46 45 00",
    "sg:postcode":"3950",
    "sg:province":"Limburg",
    "wof:name":"Jos Claessens",
    "wof:placetype":"venue"
},
  "geometry": {"coordinates":[5.575261116,51.1691932678],"type":"Point"}
}