{
  "type": "Feature",
  "properties": {
    "iso:country":"BE",
    "sg:address":"Avenue Des Villas 54 Box 2",
    "sg:city":"Ottignies-louvain-la-neuve (ottignies)",
    "sg:classifiers":[
        {
            "category":"Health Services",
            "subcategory":"Doctor",
            "type":"Services"
        }
    ],
    "sg:phone":"+32 10 41 66 60",
    "sg:postcode":"1340",
    "sg:province":"Brabant Wallon",
    "sg:tags":[
        "psychotherapist",
        "psychoanalyst"
    ],
    "wof:name":"Gerard P",
    "wof:placetype":"venue"
},
  "geometry": {"coordinates":[4.5667700768,50.6740188599],"type":"Point"}
}