{
  "type": "Feature",
  "properties": {
    "addr:full":"Kerkhovensestw 92 Lommel Limburg 3920",
    "addr:housenumber":"92",
    "addr:postcode":"3920",
    "addr:street":"Kerkhovensestw",
    "iso:country":"BE",
    "sg:address":"Kerkhovensestw 92",
    "sg:city":"Lommel",
    "sg:classifiers":[
        {
            "category":"Manufacturing",
            "subcategory":"Paper Products",
            "type":"Manufacturing & Wholesale Goods"
        }
    ],
    "sg:phone":"+32 11 55 01 60",
    "sg:postcode":"3920",
    "sg:province":"Limburg",
    "sg:tags":[
        "finished",
        "cardboard",
        "-"
    ],
    "wof:name":"Elite Druckerei",
    "wof:placetype":"venue"
},
  "geometry": {"coordinates":[5.3089981079,51.2305793762],"type":"Point"}
}