{
  "type": "Feature",
  "properties": {
    "addr:full":"D'herbouvillekaai 100 Antwerpen Antwerpen 2020",
    "addr:housenumber":"100",
    "addr:postcode":"2020",
    "iso:country":"BE",
    "sg:address":"D'herbouvillekaai 100",
    "sg:city":"Antwerpen",
    "sg:classifiers":[
        {
            "category":"Utilities",
            "subcategory":"Fuel Oil & Lpg",
            "type":"Services"
        }
    ],
    "sg:phone":"+32 3 244 92 10",
    "sg:postcode":"2020",
    "sg:province":"Antwerpen",
    "sg:tags":[
        "product"
    ],
    "wof:name":"Avia Belgomazout",
    "wof:placetype":"venue"
},
  "geometry": {"coordinates":[4.3541722298,51.1980361938],"type":"Point"}
}