{
  "type": "Feature",
  "properties": {
    "iso:country":"BE",
    "sg:address":"Albert I Laan 151",
    "sg:city":"Nieuwpoort",
    "sg:orig_category":"Beheer onroerend goed Immobili\u00ebnkantoren Vakantiehuizen Verzekeringsmakelaars and experts",
    "sg:phone":"+32 58 23 57 95",
    "sg:postcode":"8620",
    "sg:province":"West-Vlaanderen",
    "wof:name":"Immo M.d.",
    "wof:placetype":"venue"
},
  "geometry": {"coordinates":[2.7210330963,51.1500053406],"type":"Point"}
}