{
  "type": "Feature",
  "properties": {
    "iso:country":"BE",
    "sg:address":"Rue Anatole France 69",
    "sg:city":"La Louviere",
    "sg:orig_category":"Kapsalons",
    "sg:phone":"+32 64 22 79 92",
    "sg:postcode":"7100",
    "sg:province":"Hainaut",
    "wof:name":"Coiffure Nadine",
    "wof:placetype":"venue"
},
  "geometry": {"coordinates":[4.1901230812,50.4805030823],"type":"Point"}
}