{
  "type": "Feature",
  "properties": {
    "addr:full":"Rue Braemt 47 Sint-joost-ten-node/saint-josse-ten-noode Bruxelles-Capitale 1210",
    "addr:housenumber":"47",
    "addr:postcode":"1210",
    "addr:street":"Rue Braemt",
    "iso:country":"BE",
    "sg:address":"Rue Braemt 47",
    "sg:city":"Sint-joost-ten-node/saint-josse-ten-noode",
    "sg:orig_category":"Cr\u00e8ches and garderies d'enfants",
    "sg:phone":"+32 2 220 27 45",
    "sg:postcode":"1210",
    "sg:province":"Bruxelles-Capitale",
    "wof:name":"Kinderdagverblijf K. & G.",
    "wof:placetype":"venue"
},
  "geometry": {"coordinates":[4.3765568733,50.8509216309],"type":"Point"}
}