{
  "type": "Feature",
  "properties": {
    "addr:full":"Merksplassesteenweg 104a Rijkevorsel Antwerpen 2310",
    "addr:housenumber":"104a",
    "addr:postcode":"2310",
    "addr:street":"Merksplassesteenweg",
    "iso:country":"BE",
    "sg:address":"Merksplassesteenweg 104a",
    "sg:city":"Rijkevorsel",
    "sg:classifiers":[
        {
            "category":"Home & Garden",
            "subcategory":"Furniture",
            "type":"Retail Goods"
        }
    ],
    "sg:phone":"+32 3 314 09 75",
    "sg:postcode":"2310",
    "sg:province":"Antwerpen",
    "sg:tags":[
        "-"
    ],
    "wof:name":"Royal Arrow Int",
    "wof:placetype":"venue"
},
  "geometry": {"coordinates":[4.7773098946,51.3453598022],"type":"Point"}
}