{
  "type": "Feature",
  "properties": {
    "addr:full":"Dorpsplaats 20 Koksijde West-Vlaanderen 8670",
    "addr:housenumber":"20",
    "addr:postcode":"8670",
    "addr:street":"Dorpsplaats",
    "iso:country":"BE",
    "sg:address":"Dorpsplaats 20",
    "sg:city":"Koksijde",
    "sg:orig_category":"Eleveurs and marchands de porcs",
    "sg:phone":"+32 58 31 15 36",
    "sg:postcode":"8670",
    "sg:province":"West-Vlaanderen",
    "wof:name":"Wim Goderis",
    "wof:placetype":"venue"
},
  "geometry": {"coordinates":[2.6839439869,51.1163444519],"type":"Point"}
}