{
  "type": "Feature",
  "properties": {
    "addr:full":"Pastoor J. De Harduynstraat 32 Dendermonde (oudegem) Oost-Vlaanderen 9200",
    "addr:housenumber":"32",
    "addr:postcode":"9200",
    "addr:street":"Pastoor J. De Harduynstraat",
    "iso:country":"BE",
    "sg:address":"Pastoor J. De Harduynstraat 32",
    "sg:city":"Dendermonde (oudegem)",
    "sg:classifiers":[
        {
            "category":"Communications",
            "subcategory":"Television Station",
            "type":"Services"
        }
    ],
    "sg:phone":"+32 52 21 55 87",
    "sg:postcode":"9200",
    "sg:province":"Oost-Vlaanderen",
    "sg:tags":[
        "report",
        "video"
    ],
    "wof:name":"D-v Productions",
    "wof:placetype":"venue"
},
  "geometry": {"coordinates":[4.0983099937,51.0315208435],"type":"Point"}
}