{
  "type": "Feature",
  "properties": {
    "addr:full":"Av Tedesco 5-7 Bruxelles Bruxelles-Capitale 1160",
    "addr:housenumber":"5-7",
    "addr:postcode":"1160",
    "addr:street":"Av Tedesco",
    "iso:country":"BE",
    "sg:address":"Av Tedesco 5-7",
    "sg:city":"Bruxelles",
    "sg:classifiers":[
        {
            "category":"Professional",
            "subcategory":"Engineering",
            "type":"Services"
        }
    ],
    "sg:phone":"+32 2 672 23 73",
    "sg:postcode":"1160",
    "sg:province":"Bruxelles-Capitale",
    "sg:tags":[
        "machine",
        "-",
        "mechanical"
    ],
    "wof:name":"Vente Equipements Trane Sa",
    "wof:placetype":"venue"
},
  "geometry": {"coordinates":[4.4278721809,50.8196678162],"type":"Point"}
}