{
  "type": "Feature",
  "properties": {
    "addr:full":"Schurhovenveld 3231 Sint-truiden Limburg 3800",
    "addr:postcode":"3231;3800",
    "addr:street":"Schurhovenveld",
    "iso:country":"BE",
    "sg:address":"Schurhovenveld 3231",
    "sg:city":"Sint-truiden",
    "sg:orig_category":"Groenten and fruit Gh",
    "sg:phone":"+32 11 68 66 40",
    "sg:postcode":"3800",
    "sg:province":"Limburg",
    "wof:name":"Appeltans",
    "wof:placetype":"venue"
},
  "geometry": {"coordinates":[5.1863641739,50.8153343201],"type":"Point"}
}