{
  "type": "Feature",
  "properties": {
    "iso:country":"BE",
    "sg:address":"Rue De La Poste 2",
    "sg:city":"Bouillon",
    "sg:classifiers":[
        {
            "category":"Restaurant",
            "type":"Food & Drink"
        }
    ],
    "sg:phone":"+32 61 46 90 17",
    "sg:postcode":"6830",
    "sg:province":"Luxembourg",
    "wof:name":"La Pommeraie",
    "wof:placetype":"venue"
},
  "geometry": {"coordinates":[5.0676221848,49.791759491],"type":"Point"}
}