{
  "type": "Feature",
  "properties": {
    "iso:country":"BE",
    "sg:address":"Meuschemen 7c",
    "sg:city":"Baelen",
    "sg:classifiers":[
        {
            "category":"Professional",
            "subcategory":"Art Services",
            "type":"Services"
        }
    ],
    "sg:phone":"+32 87 46 02 66",
    "sg:postcode":"4837",
    "sg:province":"Li\u00e8ge",
    "sg:tags":[
        "interior",
        "designer"
    ],
    "wof:name":"Jousten J C",
    "wof:placetype":"venue"
},
  "geometry": {"coordinates":[5.9445290565,50.6458892822],"type":"Point"}
}