{
  "type": "Feature",
  "properties": {
    "addr:full":"Arthur Coussensstraat 50 Ichtegem West-Vlaanderen 8480",
    "addr:housenumber":"50",
    "addr:postcode":"8480",
    "addr:street":"Coussensstraat",
    "iso:country":"BE",
    "sg:address":"Arthur Coussensstraat 50",
    "sg:city":"Ichtegem",
    "sg:classifiers":[
        {
            "category":"Health Services",
            "subcategory":"Dentist",
            "type":"Services"
        }
    ],
    "sg:phone":"+32 51 58 35 76",
    "sg:postcode":"8480",
    "sg:province":"West-Vlaanderen",
    "wof:name":"Lewille Sofie",
    "wof:placetype":"venue"
},
  "geometry": {"coordinates":[3.0154259205,51.0875854492],"type":"Point"}
}