{
  "type": "Feature",
  "properties": {
    "iso:country":"BE",
    "sg:address":"Rue Reine De Hongrie 102",
    "sg:city":"Soignies",
    "sg:orig_category":"Rundveehouders Varkenskwekers",
    "sg:phone":"+32 65 72 88 23",
    "sg:postcode":"7061",
    "sg:province":"Hainaut",
    "wof:name":"Francis Descamps",
    "wof:placetype":"venue"
},
  "geometry": {"coordinates":[4.0133500099,50.5159416199],"type":"Point"}
}