{
  "type": "Feature",
  "properties": {
    "addr:full":"Rue Pire Pierre 28 Dison (andrimont) Li\u00e8ge 4821",
    "addr:housenumber":"28",
    "addr:postcode":"4821",
    "addr:street":"Rue Pire Pierre",
    "iso:country":"BE",
    "sg:address":"Rue Pire Pierre 28",
    "sg:city":"Dison (andrimont)",
    "sg:classifiers":[
        {
            "category":"Health Services",
            "subcategory":"Nursing And Care Facility",
            "type":"Services"
        }
    ],
    "sg:phone":"+32 87 33 30 06",
    "sg:postcode":"4821",
    "sg:province":"Li\u00e8ge",
    "sg:tags":[
        "home"
    ],
    "wof:name":"Evrard A",
    "wof:placetype":"venue"
},
  "geometry": {"coordinates":[5.8700838089,50.602481842],"type":"Point"}
}