{
  "type": "Feature",
  "properties": {
    "addr:full":"Place De Cuesmes 16-17 Mons (cuesmes) Hainaut 7033",
    "addr:housenumber":"16-17",
    "addr:postcode":"7033",
    "addr:street":"Place De Cuesmes",
    "iso:country":"BE",
    "sg:address":"Place De Cuesmes 16-17",
    "sg:city":"Mons (cuesmes)",
    "sg:classifiers":[
        {
            "category":"Shopping",
            "subcategory":"Pets & Pet Supplies",
            "type":"Retail Goods"
        }
    ],
    "sg:phone":"+32 65 34 60 09",
    "sg:postcode":"7033",
    "sg:province":"Hainaut",
    "sg:tags":[
        "shop",
        "-"
    ],
    "wof:name":"Neptune (le)",
    "wof:placetype":"venue"
},
  "geometry": {"coordinates":[3.9441490173,50.4408607483],"type":"Point"}
}