{
  "type": "Feature",
  "properties": {
    "iso:country":"BE",
    "sg:address":"Waverse Steenweg 259",
    "sg:city":"Elsene/ixelles",
    "sg:orig_category":"Muziekinstrumenten",
    "sg:phone":"+32 2 646 27 65",
    "sg:postcode":"1050",
    "sg:province":"Bruxelles-Capitale",
    "wof:name":"Philippe Dony",
    "wof:placetype":"venue"
},
  "geometry": {"coordinates":[4.3778500557,50.8357162476],"type":"Point"}
}