{
  "type": "Feature",
  "properties": {
    "addr:full":"Klepperstraat 16 Meise Vlaams-Brabant 1861",
    "addr:housenumber":"16",
    "addr:postcode":"1861",
    "addr:street":"Klepperstraat",
    "iso:country":"BE",
    "sg:address":"Klepperstraat 16",
    "sg:city":"Meise",
    "sg:orig_category":"Diverse bedrijfsbeheeradviesbureaus",
    "sg:phone":"+32 2 270 44 31",
    "sg:postcode":"1861",
    "sg:province":"Vlaams-Brabant",
    "wof:name":"Cemco",
    "wof:placetype":"venue"
},
  "geometry": {"coordinates":[4.3109788895,50.9416046143],"type":"Point"}
}