{
  "type": "Feature",
  "properties": {
    "addr:full":"Koninklijke Baan 170 Koksijde West-Vlaanderen 8670",
    "addr:housenumber":"170",
    "addr:postcode":"8670",
    "addr:street":"Koninklijke Baan",
    "iso:country":"BE",
    "sg:address":"Koninklijke Baan 170",
    "sg:city":"Koksijde",
    "sg:classifiers":[
        {
            "category":"Bars & Pubs",
            "type":"Food & Drink"
        }
    ],
    "sg:phone":"+32 58 52 17 93",
    "sg:postcode":"8670",
    "sg:province":"West-Vlaanderen",
    "sg:tags":[
        "tavern"
    ],
    "wof:name":"Carpe Diem",
    "wof:placetype":"venue"
},
  "geometry": {"coordinates":[2.6330599785,51.1198005676],"type":"Point"}
}