{
  "type": "Feature",
  "properties": {
    "addr:full":"Molenstraat 23 Genk Limburg 3600",
    "addr:housenumber":"23",
    "addr:postcode":"3600",
    "addr:street":"Molenstraat",
    "iso:country":"BE",
    "sg:address":"Molenstraat 23",
    "sg:city":"Genk",
    "sg:classifiers":[
        {
            "category":"Professional",
            "subcategory":"Art Services",
            "type":"Services"
        }
    ],
    "sg:phone":"+32 89 30 64 17",
    "sg:postcode":"3600",
    "sg:province":"Limburg",
    "sg:tags":[
        "picture",
        "framer"
    ],
    "wof:name":"Kunstzaken",
    "wof:placetype":"venue"
},
  "geometry": {"coordinates":[5.5017981529,50.9644851685],"type":"Point"}
}