{
  "type": "Feature",
  "properties": {
    "addr:full":"Oude Haachtsesteenweg 117d Steenokkerzeel Vlaams-Brabant 1820",
    "addr:housenumber":"117d",
    "addr:postcode":"1820",
    "addr:street":"Oude Haachtsesteenweg",
    "iso:country":"BE",
    "sg:address":"Oude Haachtsesteenweg 117d",
    "sg:city":"Steenokkerzeel",
    "sg:orig_category":"Aircraft Maintenance Equipment",
    "sg:phone":"+32 2 752 86 60",
    "sg:postcode":"1820",
    "sg:province":"Vlaams-Brabant",
    "wof:name":"Lufthansa Technik Brussels Nv",
    "wof:placetype":"venue"
},
  "geometry": {"coordinates":[4.499876976,50.9181289673],"type":"Point"}
}