{
  "type": "Feature",
  "properties": {
    "iso:country":"BE",
    "sg:address":"Hoevensebaan 209",
    "sg:city":"Kapellen",
    "sg:classifiers":[
        {
            "category":"Health Services",
            "subcategory":"Health Practitioner",
            "type":"Services"
        }
    ],
    "sg:phone":"+32 3 664 41 17",
    "sg:postcode":"2950",
    "sg:province":"Antwerpen",
    "sg:tags":[
        "physiotherapist"
    ],
    "wof:name":"Vanderschueren F",
    "wof:placetype":"venue"
},
  "geometry": {"coordinates":[4.4204101562,51.3112335205],"type":"Point"}
}