{
  "type": "Feature",
  "properties": {
    "addr:full":"Havenplein 3 Blankenberge West-Vlaanderen 8370",
    "addr:housenumber":"3",
    "addr:postcode":"8370",
    "addr:street":"Havenplein",
    "iso:country":"BE",
    "sg:address":"Havenplein 3",
    "sg:city":"Blankenberge",
    "sg:classifiers":[
        {
            "category":"Restaurant",
            "type":"Food & Drink"
        }
    ],
    "sg:phone":"+32 50 41 97 15",
    "sg:postcode":"8370",
    "sg:province":"West-Vlaanderen",
    "sg:tags":[
        "caf\u00e9s",
        "sportclubs"
    ],
    "wof:name":"Scarphout",
    "wof:placetype":"venue"
},
  "geometry": {"coordinates":[3.1209080219,51.3123321533],"type":"Point"}
}