{
  "type": "Feature",
  "properties": {
    "addr:full":"Watervlietsesteenweg 28 Sint-laureins Oost-Vlaanderen 9988",
    "addr:housenumber":"28",
    "addr:postcode":"9988",
    "addr:street":"Watervlietsesteenweg",
    "iso:country":"BE",
    "sg:address":"Watervlietsesteenweg 28",
    "sg:city":"Sint-laureins",
    "sg:orig_category":"Jardinage",
    "sg:phone":"+32 9 379 94 23",
    "sg:postcode":"9988",
    "sg:province":"Oost-Vlaanderen",
    "wof:name":"Bureau De Pauw-bosch",
    "wof:placetype":"venue"
},
  "geometry": {"coordinates":[3.5921339989,51.2873191833],"type":"Point"}
}