{
  "type": "Feature",
  "properties": {
    "iso:country":"BE",
    "sg:address":"Schokkaartstr 6",
    "sg:city":"Gavere (groot)",
    "sg:orig_category":"Kapsalons",
    "sg:phone":"+32 9 384 54 80",
    "sg:postcode":"9890",
    "sg:province":"Oost-Vlaanderen",
    "wof:name":"Intercoiffure Nick",
    "wof:placetype":"venue"
},
  "geometry": {"coordinates":[3.6617219448,50.9409294128],"type":"Point"}
}