{
  "type": "Feature",
  "properties": {
    "addr:full":"Marktstraat 6 Ninove Oost-Vlaanderen 9400",
    "addr:housenumber":"6",
    "addr:postcode":"9400",
    "addr:street":"Marktstraat",
    "iso:country":"BE",
    "sg:address":"Marktstraat 6",
    "sg:city":"Ninove",
    "sg:orig_category":"Textiel",
    "sg:phone":"+32 54 33 36 31",
    "sg:postcode":"9400",
    "sg:province":"Oost-Vlaanderen",
    "wof:name":"Breiboetiek",
    "wof:placetype":"venue"
},
  "geometry": {"coordinates":[4.0230097771,50.835018158],"type":"Point"}
}