{
  "type": "Feature",
  "properties": {
    "iso:country":"BE",
    "sg:address":"Sint Maartenskerkstraat 1",
    "sg:city":"Kortrijk",
    "sg:orig_category":"Pain, p\u00e2tisseries and confiseries",
    "sg:phone":"+32 56 22 17 61",
    "sg:postcode":"8500",
    "sg:province":"West-Vlaanderen",
    "wof:name":"Hoornaert Brood & Banket",
    "wof:placetype":"venue"
},
  "geometry": {"coordinates":[3.2672688961,50.8274383545],"type":"Point"}
}