{
  "type": "Feature",
  "properties": {
    "addr:full":"Lindendreef 3 Ieper West-Vlaanderen 8900",
    "addr:housenumber":"3",
    "addr:postcode":"8900",
    "addr:street":"Lindendreef",
    "iso:country":"BE",
    "sg:address":"Lindendreef 3",
    "sg:city":"Ieper",
    "sg:orig_category":"Enseignement maternel and primaire",
    "sg:phone":"+32 57 20 03 80",
    "sg:postcode":"8900",
    "sg:province":"West-Vlaanderen",
    "wof:name":"Vrije Kleuterschool",
    "wof:placetype":"venue"
},
  "geometry": {"coordinates":[2.8734090328,50.8404960632],"type":"Point"}
}