{
  "type": "Feature",
  "properties": {
    "iso:country":"BE",
    "sg:address":"Molenstraat 3",
    "sg:city":"Aalter",
    "sg:orig_category":"Artistes ind\u00e9pendants",
    "sg:phone":"+32 9 374 20 77",
    "sg:postcode":"9880",
    "sg:province":"Oost-Vlaanderen",
    "wof:name":"Antoine De Clerck",
    "wof:placetype":"venue"
},
  "geometry": {"coordinates":[3.455039978,51.0861434937],"type":"Point"}
}