{
  "type": "Feature",
  "properties": {
    "iso:country":"BE",
    "sg:address":"Vlekkemdorp 1",
    "sg:city":"Erpe-mere",
    "sg:orig_category":"Boekhouders",
    "sg:phone":"+32 53 80 85 95",
    "sg:postcode":"9420",
    "sg:province":"Oost-Vlaanderen",
    "wof:name":"Raf Roelandt",
    "wof:placetype":"venue"
},
  "geometry": {"coordinates":[3.9316129684,50.9349899292],"type":"Point"}
}