{
  "type": "Feature",
  "properties": {
    "addr:full":"Pierre-victor Jacobsstr 24 Brussel Bruxelles-Capitale 1080",
    "addr:housenumber":"24",
    "addr:postcode":"1080",
    "addr:street":"Brussel",
    "iso:country":"BE",
    "sg:address":"Pierre-victor Jacobsstr 24",
    "sg:city":"Brussel",
    "sg:classifiers":[
        {
            "category":"Ice Cream",
            "type":"Food & Drink"
        }
    ],
    "sg:phone":"+32 2 427 42 94",
    "sg:postcode":"1080",
    "sg:province":"Bruxelles-Capitale",
    "sg:tags":[
        "preserve",
        "vegetable",
        "product",
        "fruit",
        "related"
    ],
    "wof:name":"Etablissementen Theunissen Bvba",
    "wof:placetype":"venue"
},
  "geometry": {"coordinates":[4.3398890495,50.8635025024],"type":"Point"}
}