{
  "type": "Feature",
  "properties": {
    "addr:full":"Rue Laid Pachis 8 Gembloux-sur-orneau (grand-leez) Namur 5031",
    "addr:housenumber":"8",
    "addr:postcode":"5031",
    "addr:street":"Rue Laid Pachis;Grand-Leez",
    "iso:country":"BE",
    "sg:address":"Rue Laid Pachis 8",
    "sg:city":"Gembloux-sur-orneau (grand-leez)",
    "sg:classifiers":[
        {
            "category":"Health Services",
            "subcategory":"Health Practitioner",
            "type":"Services"
        }
    ],
    "sg:phone":"+32 81 64 00 57",
    "sg:postcode":"5031",
    "sg:province":"Namur",
    "sg:tags":[
        "physiotherapist"
    ],
    "wof:name":"Staelens A",
    "wof:placetype":"venue"
},
  "geometry": {"coordinates":[4.7790398598,50.5868492126],"type":"Point"}
}