{
  "type": "Feature",
  "properties": {
    "addr:full":"Konkelstraat 142 Sint-lambrechts-woluwe/woluwe-saint-lambert Bruxelles-Capitale 1200",
    "addr:housenumber":"142;/",
    "addr:postcode":"1200",
    "addr:street":"Konkelstraat;Sint-Lambrechts-Woluwe",
    "iso:country":"BE",
    "sg:address":"Konkelstraat 142",
    "sg:city":"Sint-lambrechts-woluwe/woluwe-saint-lambert",
    "sg:orig_category":"Apotheken",
    "sg:phone":"+32 2 771 10 05",
    "sg:postcode":"1200",
    "sg:province":"Bruxelles-Capitale",
    "wof:name":"Pharm. Schnitzler-fievet",
    "wof:placetype":"venue"
},
  "geometry": {"coordinates":[4.4416708946,50.8382339478],"type":"Point"}
}