{
  "type": "Feature",
  "properties": {
    "addr:full":"Grand Rue 52 Courcelles (trazegnies) Hainaut 6183",
    "addr:housenumber":"52",
    "addr:postcode":"6183",
    "addr:street":"Grand Rue",
    "iso:country":"BE",
    "sg:address":"Grand Rue 52",
    "sg:city":"Courcelles (trazegnies)",
    "sg:classifiers":[
        {
            "category":"Professional",
            "subcategory":"Management & Consulting",
            "type":"Services"
        }
    ],
    "sg:phone":"+32 71 45 55 63",
    "sg:postcode":"6183",
    "sg:province":"Hainaut",
    "sg:tags":[
        "tax-consultants"
    ],
    "wof:name":"Houba R",
    "wof:placetype":"venue"
},
  "geometry": {"coordinates":[4.3350520134,50.4609794617],"type":"Point"}
}