{
  "type": "Feature",
  "properties": {
    "iso:country":"BE",
    "sg:address":"Avenue De Hinnisdael 6",
    "sg:city":"Bruxelles (woluwe-saint-pierre)",
    "sg:classifiers":[
        {
            "category":"Shopping",
            "subcategory":"Baby Store",
            "type":"Retail Goods"
        }
    ],
    "sg:phone":"+32 2 779 35 44",
    "sg:postcode":"1150",
    "sg:province":"Bruxelles-Capitale",
    "sg:tags":[
        "hostess"
    ],
    "wof:name":"M.s.a.",
    "wof:placetype":"venue"
},
  "geometry": {"coordinates":[4.4651122093,50.8415985107],"type":"Point"}
}