{
  "type": "Feature",
  "properties": {
    "iso:country":"BE",
    "sg:address":"Les Etangs 5",
    "sg:city":"Stavelot",
    "sg:orig_category":"Diverse meubelen Fab Elektrische installaties voor woningen",
    "sg:phone":"+32 80 88 06 22",
    "sg:postcode":"4970",
    "sg:province":"Li\u00e8ge",
    "wof:name":"Philippe Tombeux",
    "wof:placetype":"venue"
},
  "geometry": {"coordinates":[5.9282031059,50.3884811401],"type":"Point"}
}