{
  "type": "Feature",
  "properties": {
    "iso:country":"BE",
    "sg:address":"Diestsesteenweg 2",
    "sg:city":"Lubbeek",
    "sg:orig_category":"Installatie van houten of kunststof schrijnwerk Woningbouw",
    "sg:phone":"+32 16 35 30 90",
    "sg:postcode":"3212",
    "sg:province":"Vlaams-Brabant",
    "wof:name":"Fami-bouw",
    "wof:placetype":"venue"
},
  "geometry": {"coordinates":[4.7942500114,50.8916969299],"type":"Point"}
}