{
  "type": "Feature",
  "properties": {
    "addr:full":"Henri Caronstraat 14 Hoeilaart Vlaams-Brabant 1560",
    "addr:housenumber":"14",
    "addr:postcode":"1560",
    "addr:street":"Henri Caronstraat",
    "iso:country":"BE",
    "sg:address":"Henri Caronstraat 14",
    "sg:city":"Hoeilaart",
    "sg:orig_category":"Fleurs and plantes",
    "sg:phone":"+32 2 657 33 72",
    "sg:postcode":"1560",
    "sg:province":"Vlaams-Brabant",
    "wof:name":"Strelitzia",
    "wof:placetype":"venue"
},
  "geometry": {"coordinates":[4.4757671356,50.7671775818],"type":"Point"}
}