{
  "type": "Feature",
  "properties": {
    "addr:full":"Rue Emile Cornez 10 Honnelles Hainaut 7387",
    "addr:housenumber":"10",
    "addr:postcode":"7387",
    "addr:street":"Rue Emile Cornez;Hainaut",
    "iso:country":"BE",
    "sg:address":"Rue Emile Cornez 10",
    "sg:city":"Honnelles",
    "sg:classifiers":[
        {
            "category":"Military Area",
            "subcategory":"Air Force Base",
            "type":"Public Place"
        }
    ],
    "sg:phone":"+32 65 75 95 76",
    "sg:postcode":"7387",
    "sg:province":"Hainaut",
    "sg:tags":[
        "commerce",
        "gr",
        "equipement",
        "de",
        "\u00e9v\u00e9nements",
        "pour",
        "diver",
        "mat\u00e9riel",
        "location",
        "banquet"
    ],
    "wof:name":"Yves Potvin",
    "wof:placetype":"venue"
},
  "geometry": {"coordinates":[3.6983659267,50.3684501648],"type":"Point"}
}