{
  "type": "Feature",
  "properties": {
    "addr:full":"Markt 6a Nevele Oost-Vlaanderen 9850",
    "addr:housenumber":"6a",
    "addr:postcode":"9850",
    "addr:street":"Markt",
    "iso:country":"BE",
    "sg:address":"Markt 6a",
    "sg:city":"Nevele",
    "sg:classifiers":[
        {
            "category":"Personal",
            "subcategory":"Shoe Repair & Shine",
            "type":"Services"
        }
    ],
    "sg:phone":"+32 9 371 67 33",
    "sg:postcode":"9850",
    "sg:province":"Oost-Vlaanderen",
    "sg:tags":[
        "shoemaker"
    ],
    "wof:name":"Tatsevoet (den)",
    "wof:placetype":"venue"
},
  "geometry": {"coordinates":[3.5500509739,51.0330657959],"type":"Point"}
}