{
  "type": "Feature",
  "properties": {
    "iso:country":"BE",
    "sg:address":"Kloosterstraat 122",
    "sg:city":"Lille",
    "sg:orig_category":"Plaatsen van vloer- and muurbekleding",
    "sg:phone":"+32 14 55 24 87",
    "sg:postcode":"2275",
    "sg:province":"Antwerpen",
    "wof:name":"Laureys Louis En Zoon",
    "wof:placetype":"venue"
},
  "geometry": {"coordinates":[4.8621029854,51.2631378174],"type":"Point"}
}