{
  "type": "Feature",
  "properties": {
    "iso:country":"BE",
    "sg:address":"Chemin Du Warichaix 7",
    "sg:city":"Braine-le-comte",
    "sg:orig_category":"Immobili\u00ebnkantoren Woningbouw",
    "sg:phone":"+32 67 63 63 57",
    "sg:postcode":"7090",
    "sg:province":"Hainaut",
    "wof:name":"Abita Immo Construct",
    "wof:placetype":"venue"
},
  "geometry": {"coordinates":[4.1784300804,50.6523094177],"type":"Point"}
}