{
  "type": "Feature",
  "properties": {
    "addr:full":"Kolvestraat 29 Brugge West-Vlaanderen 8000",
    "addr:housenumber":"29",
    "addr:postcode":"8000",
    "addr:street":"Kolvestraat",
    "iso:country":"BE",
    "sg:address":"Kolvestraat 29",
    "sg:city":"Brugge",
    "sg:orig_category":"Autokeuringen",
    "sg:phone":"+32 50 31 36 42",
    "sg:postcode":"8000",
    "sg:province":"West-Vlaanderen",
    "wof:name":"Autokeuring",
    "wof:placetype":"venue"
},
  "geometry": {"coordinates":[3.2177019119,51.2149124146],"type":"Point"}
}