{
  "type": "Feature",
  "properties": {
    "addr:full":"Steenstratelaan 9 Kortrijk West-Vlaanderen 8500",
    "addr:housenumber":"9",
    "addr:postcode":"8500",
    "addr:street":"Steenstratelaan",
    "iso:country":"BE",
    "sg:address":"Steenstratelaan 9",
    "sg:city":"Kortrijk",
    "sg:classifiers":[
        {
            "category":"Professional",
            "type":"Services"
        }
    ],
    "sg:phone":"+32 56 21 41 03",
    "sg:postcode":"8500",
    "sg:province":"West-Vlaanderen",
    "sg:tags":[
        "entertainer"
    ],
    "wof:name":"Strip-acts Angelino",
    "wof:placetype":"venue"
},
  "geometry": {"coordinates":[3.2775409222,50.8148765564],"type":"Point"}
}