{
  "type": "Feature",
  "properties": {
    "iso:country":"BE",
    "sg:address":"Verheydenstraat 57",
    "sg:city":"Dilbeek",
    "sg:orig_category":"Artsen and specialisten",
    "sg:phone":"+32 2 569 35 59",
    "sg:postcode":"1700",
    "sg:province":"Vlaams-Brabant",
    "wof:name":"A. Verheyden",
    "wof:placetype":"venue"
},
  "geometry": {"coordinates":[4.2610931396,50.8444328308],"type":"Point"}
}