{
  "type": "Feature",
  "properties": {
    "iso:country":"BE",
    "sg:address":"Leo De B\u00c9thunelaan 125a",
    "sg:city":"Aalst",
    "sg:orig_category":"Agences de voyages",
    "sg:phone":"+32 53 78 98 38",
    "sg:postcode":"9300",
    "sg:province":"Oost-Vlaanderen",
    "wof:name":"Roelant-reizen",
    "wof:placetype":"venue"
},
  "geometry": {"coordinates":[4.031165123,50.9322891235],"type":"Point"}
}