{
  "type": "Feature",
  "properties": {
    "iso:country":"BE",
    "sg:address":"Stationsstraat 74",
    "sg:city":"Stekene",
    "sg:classifiers":[
        {
            "category":"Cafe",
            "type":"Food & Drink"
        }
    ],
    "sg:phone":"+32 3 779 80 20",
    "sg:postcode":"9190",
    "sg:province":"Oost-Vlaanderen",
    "sg:tags":[
        "caf\u00e9s"
    ],
    "wof:name":"Caf\u00c9 Stuyvenberg",
    "wof:placetype":"venue"
},
  "geometry": {"coordinates":[4.0730400085,51.2103347778],"type":"Point"}
}