{
  "type": "Feature",
  "properties": {
    "iso:country":"BE",
    "sg:address":"Bollestraat 1",
    "sg:city":"Lichtervelde",
    "sg:orig_category":"Fruitteelt Groententeelt",
    "sg:phone":"+32 51 72 62 85",
    "sg:postcode":"8810",
    "sg:province":"West-Vlaanderen",
    "wof:name":"Roger Huyghe",
    "wof:placetype":"venue"
},
  "geometry": {"coordinates":[3.122232914,51.0253677368],"type":"Point"}
}