{
  "type": "Feature",
  "properties": {
    "iso:country":"BE",
    "sg:address":"Kerklaan 57",
    "sg:city":"Machelen",
    "sg:orig_category":"Installation \u00e9lectrique r\u00e9sidentielle",
    "sg:phone":"+32 2 251 41 08",
    "sg:postcode":"1830",
    "sg:province":"Vlaams-Brabant",
    "wof:name":"Vse-cei",
    "wof:placetype":"venue"
},
  "geometry": {"coordinates":[4.4278569221,50.9132423401],"type":"Point"}
}