{
  "type": "Feature",
  "properties": {
    "iso:country":"BE",
    "sg:address":"Rue De La Courbette 2",
    "sg:city":"Honnelles (athis)",
    "sg:classifiers":[
        {
            "category":"Manufacturing",
            "subcategory":"Tools & Machinery",
            "type":"Manufacturing & Wholesale Goods"
        }
    ],
    "sg:phone":"+32 65 69 10 02",
    "sg:postcode":"7387",
    "sg:province":"Hainaut",
    "sg:tags":[
        "-",
        "second-hand",
        "apparatus",
        "machines"
    ],
    "wof:name":"Technitelec Sprl",
    "wof:placetype":"venue"
},
  "geometry": {"coordinates":[3.6959199905,50.3683853149],"type":"Point"}
}