{
  "type": "Feature",
  "properties": {
    "addr:full":"Boterstraat 20 Wingene West-Vlaanderen 8750",
    "addr:housenumber":"20",
    "addr:postcode":"8750",
    "addr:street":"Boterstraat",
    "iso:country":"BE",
    "sg:address":"Boterstraat 20",
    "sg:city":"Wingene",
    "sg:orig_category":"Entretien and r\u00e9parations de voitures",
    "sg:phone":"+32 51 61 11 82",
    "sg:postcode":"8750",
    "sg:province":"West-Vlaanderen",
    "wof:name":"Garage Vandeweghe",
    "wof:placetype":"venue"
},
  "geometry": {"coordinates":[3.2381300926,51.0525474548],"type":"Point"}
}