{
  "type": "Feature",
  "properties": {
    "iso:country":"BE",
    "sg:address":"Hazelaardreef 13",
    "sg:city":"Grobbendonk",
    "sg:orig_category":"Industri\u00eble and commerci\u00eble bouw",
    "sg:phone":"+32 14 51 37 11",
    "sg:postcode":"2280",
    "sg:province":"Antwerpen",
    "wof:name":"Nelis Bouwonderneming",
    "wof:placetype":"venue"
},
  "geometry": {"coordinates":[4.720179081,51.1708946228],"type":"Point"}
}