{
  "type": "Feature",
  "properties": {
    "addr:full":"Dronkaardstraat 531 Menen West-Vlaanderen 8930",
    "addr:housenumber":"531",
    "addr:postcode":"8930",
    "addr:street":"Dronkaardstraat",
    "iso:country":"BE",
    "sg:address":"Dronkaardstraat 531",
    "sg:city":"Menen",
    "sg:orig_category":"V\u00e9los",
    "sg:phone":"+32 56 42 29 62",
    "sg:postcode":"8930",
    "sg:province":"West-Vlaanderen",
    "wof:name":"Cycli Imola",
    "wof:placetype":"venue"
},
  "geometry": {"coordinates":[3.1209149361,50.7961845398],"type":"Point"}
}