{
  "type": "Feature",
  "properties": {
    "iso:country":"BE",
    "sg:address":"Rue Du Val-saint-lambert 225",
    "sg:city":"Seraing",
    "sg:classifiers":[
        {
            "category":"Fast Food",
            "type":"Food & Drink"
        }
    ],
    "sg:phone":"+32 4 338 08 13",
    "sg:postcode":"4100",
    "sg:province":"Li\u00e8ge",
    "sg:tags":[
        "\u00c0",
        "restaurants",
        "emporter",
        "restaurant"
    ],
    "wof:name":"Snack Fran\u00c7ois",
    "wof:placetype":"venue"
},
  "geometry": {"coordinates":[5.4937901497,50.6035003662],"type":"Point"}
}