{
  "type": "Feature",
  "properties": {
    "iso:country":"BE",
    "sg:address":"Rue Bonaventure 117",
    "sg:city":"Jette",
    "sg:classifiers":[
        {
            "category":"Insurance",
            "subcategory":"Insurance Agent",
            "type":"Services"
        }
    ],
    "sg:phone":"+32 2 479 58 10",
    "sg:postcode":"1090",
    "sg:province":"Bruxelles-Capitale",
    "sg:tags":[
        "verzekeringsmakelaars",
        "expert"
    ],
    "wof:name":"Dewachter & Fils -finassur",
    "wof:placetype":"venue"
},
  "geometry": {"coordinates":[4.3236560822,50.8847846985],"type":"Point"}
}