{
  "type": "Feature",
  "properties": {
    "addr:full":"Frankrijklei 58 Antwerpen Antwerpen 2000",
    "addr:housenumber":"58",
    "addr:postcode":"2000",
    "addr:street":"Frankrijklei",
    "iso:country":"BE",
    "sg:address":"Frankrijklei 58",
    "sg:city":"Antwerpen",
    "sg:orig_category":"Bagage and lederwaren",
    "sg:phone":"+32 3 233 01 31",
    "sg:postcode":"2000",
    "sg:province":"Antwerpen",
    "wof:name":"Boutique Dominique",
    "wof:placetype":"venue"
},
  "geometry": {"coordinates":[4.4142160416,51.2171211243],"type":"Point"}
}