{
  "type": "Feature",
  "properties": {
    "iso:country":"BE",
    "sg:address":"Driekoningenstraat 76",
    "sg:city":"Sint-niklaas",
    "sg:orig_category":"Boucheries",
    "sg:phone":"+32 3 776 39 99",
    "sg:postcode":"9100",
    "sg:province":"Oost-Vlaanderen",
    "wof:name":"Slagerij Driekoningen",
    "wof:placetype":"venue"
},
  "geometry": {"coordinates":[4.141076088,51.1740531921],"type":"Point"}
}