{
  "type": "Feature",
  "properties": {
    "addr:full":"Sint-andriessteenweg 35 Zottegem (strijpen) Oost-Vlaanderen 9620",
    "addr:housenumber":"35",
    "addr:postcode":"9620",
    "addr:street":"Sint-Andriessteenweg",
    "iso:country":"BE",
    "sg:address":"Sint-andriessteenweg 35",
    "sg:city":"Zottegem (strijpen)",
    "sg:classifiers":[
        {
            "category":"Bars & Pubs",
            "type":"Food & Drink"
        }
    ],
    "sg:phone":"+32 9 360 26 97",
    "sg:postcode":"9620",
    "sg:province":"Oost-Vlaanderen",
    "wof:name":"Sportman",
    "wof:placetype":"venue"
},
  "geometry": {"coordinates":[3.7982850075,50.8678321838],"type":"Point"}
}