{
  "type": "Feature",
  "properties": {
    "iso:country":"BE",
    "sg:address":"Laarstraat 48a",
    "sg:city":"Landen (neerwinden)",
    "sg:classifiers":[
        {
            "category":"Professional",
            "subcategory":"Lawyer & Legal Services",
            "type":"Services"
        }
    ],
    "sg:phone":"+32 16 78 86 06",
    "sg:postcode":"3400",
    "sg:province":"Vlaams-Brabant",
    "wof:name":"Cans Johan",
    "wof:placetype":"venue"
},
  "geometry": {"coordinates":[5.033094883,50.7665328979],"type":"Point"}
}