{
  "type": "Feature",
  "properties": {
    "iso:country":"BE",
    "sg:address":"Rue De Stalle 97",
    "sg:city":"Bruxelles",
    "sg:classifiers":[
        {
            "category":"Government",
            "subcategory":"Fire Station",
            "type":"Public Place"
        }
    ],
    "sg:phone":"+32 2 370 28 28",
    "sg:postcode":"1180",
    "sg:province":"Bruxelles-Capitale",
    "sg:tags":[
        "colour",
        "laser",
        "photocopiers",
        "photocopier",
        "digital"
    ],
    "wof:name":"Business Office Products S.a.",
    "wof:placetype":"venue"
},
  "geometry": {"coordinates":[4.3271670341,50.7964019775],"type":"Point"}
}