{
  "type": "Feature",
  "properties": {
    "addr:full":"Elsense Steenweg 114a Elsene/ixelles Bruxelles-Capitale 1050",
    "addr:housenumber":"114a",
    "addr:postcode":"1050",
    "addr:street":"Elsense Steenweg",
    "iso:country":"BE",
    "sg:address":"Elsense Steenweg 114a",
    "sg:city":"Elsene/ixelles",
    "sg:orig_category":"Tweedehandsgoederen",
    "sg:phone":"+32 2 503 25 42",
    "sg:postcode":"1050",
    "sg:province":"Bruxelles-Capitale",
    "wof:name":"Cash Converters",
    "wof:placetype":"venue"
},
  "geometry": {"coordinates":[4.3641867638,50.8350944519],"type":"Point"}
}