{
  "type": "Feature",
  "properties": {
    "addr:full":"Sint-laurentiusstraat 10 Zedelgem West-Vlaanderen 8210",
    "addr:housenumber":"10",
    "addr:postcode":"8210",
    "addr:street":"Sint-Laurentiusstraat",
    "iso:country":"BE",
    "sg:address":"Sint-laurentiusstraat 10",
    "sg:city":"Zedelgem",
    "sg:classifiers":[
        {
            "category":"Bakery",
            "type":"Food & Drink"
        }
    ],
    "sg:phone":"+32 50 20 94 76",
    "sg:postcode":"8210",
    "sg:province":"West-Vlaanderen",
    "sg:tags":[
        "confectioner",
        "baker"
    ],
    "wof:name":"Van De Beek",
    "wof:placetype":"venue"
},
  "geometry": {"coordinates":[3.1357309818,51.1435623169],"type":"Point"}
}