{
  "type": "Feature",
  "properties": {
    "iso:country":"BE",
    "sg:address":"Keizerinlaan 56",
    "sg:city":"Meise",
    "sg:orig_category":"Architectes",
    "sg:phone":"+32 2 269 76 03",
    "sg:postcode":"1860",
    "sg:province":"Vlaams-Brabant",
    "wof:name":"Patrice Croizette Desnoyers",
    "wof:placetype":"venue"
},
  "geometry": {"coordinates":[4.3394050598,50.9333839417],"type":"Point"}
}