{
  "type": "Feature",
  "properties": {
    "iso:country":"BE",
    "sg:address":"Koningin Elisabethstraat 12",
    "sg:city":"Kuurne",
    "sg:orig_category":"Alimentation sp\u00e9cialis\u00e9e",
    "sg:phone":"+32 56 70 42 30",
    "sg:postcode":"8520",
    "sg:province":"West-Vlaanderen",
    "wof:name":"Huis Puur Natuur",
    "wof:placetype":"venue"
},
  "geometry": {"coordinates":[3.2856020927,50.851146698],"type":"Point"}
}