{
  "type": "Feature",
  "properties": {
    "addr:full":"Rue De Wespin 74 Dinant Namur 5500",
    "addr:housenumber":"74",
    "addr:postcode":"5500",
    "addr:street":"Rue De Wespin",
    "iso:country":"BE",
    "sg:address":"Rue De Wespin 74",
    "sg:city":"Dinant",
    "sg:classifiers":[
        {
            "category":"Building & Trades",
            "subcategory":"Pest Control",
            "type":"Services"
        }
    ],
    "sg:phone":"+32 82 22 95 26",
    "sg:postcode":"5500",
    "sg:province":"Namur",
    "sg:tags":[
        "painting",
        "contractor"
    ],
    "wof:name":"Permanne Y",
    "wof:placetype":"venue"
},
  "geometry": {"coordinates":[4.8994870186,50.2587394714],"type":"Point"}
}