{
  "type": "Feature",
  "properties": {
    "addr:full":"Avenue Des Tilleuls 50 Li\u00c8ge Li\u00e8ge 4000",
    "addr:housenumber":"50",
    "addr:postcode":"4000",
    "addr:street":"Avenue Des Tilleuls",
    "iso:country":"BE",
    "sg:address":"Avenue Des Tilleuls 50",
    "sg:city":"Li\u00c8ge",
    "sg:orig_category":"Boekhouders",
    "sg:phone":"+32 4 254 00 05",
    "sg:postcode":"4000",
    "sg:province":"Li\u00e8ge",
    "wof:name":"Michel Matroule",
    "wof:placetype":"venue"
},
  "geometry": {"coordinates":[5.5747900009,50.6174201965],"type":"Point"}
}