{
  "type": "Feature",
  "properties": {
    "addr:full":"Rue L\u00c9opold 11 Gembloux Namur 5030",
    "addr:housenumber":"11",
    "addr:postcode":"5030",
    "addr:street":"Rue Le\u0301Opold;Namur",
    "iso:country":"BE",
    "sg:address":"Rue L\u00c9opold 11",
    "sg:city":"Gembloux",
    "sg:classifiers":[
        {
            "category":"Restaurant",
            "type":"Food & Drink"
        }
    ],
    "sg:phone":"+32 81 61 08 50",
    "sg:postcode":"5030",
    "sg:province":"Namur",
    "wof:name":"F. Paninoteca",
    "wof:placetype":"venue"
},
  "geometry": {"coordinates":[4.6928691864,50.5600738525],"type":"Point"}
}