{
  "type": "Feature",
  "properties": {
    "addr:full":"Ster 3b Stavelot Li\u00e8ge 4970",
    "addr:housenumber":"3b",
    "addr:postcode":"4970",
    "addr:street":"Ster",
    "iso:country":"BE",
    "sg:address":"Ster 3b",
    "sg:city":"Stavelot",
    "sg:classifiers":[
        {
            "category":"Travel",
            "subcategory":"Resort",
            "type":"Entertainment"
        }
    ],
    "sg:phone":"+32 80 42 08 39",
    "sg:postcode":"4970",
    "sg:province":"Li\u00e8ge",
    "sg:tags":[
        "rental",
        "accomodation",
        "holiday",
        "-"
    ],
    "wof:name":"Ardennes-villa.com",
    "wof:placetype":"venue"
},
  "geometry": {"coordinates":[5.9035658836,50.393913269],"type":"Point"}
}