{
  "type": "Feature",
  "properties": {
    "iso:country":"BE",
    "sg:address":"Markebekestraat 86",
    "sg:city":"Kortrijk",
    "sg:classifiers":[
        {
            "category":"Cafe",
            "type":"Food & Drink"
        }
    ],
    "sg:phone":"+32 56 21 66 47",
    "sg:postcode":"8510",
    "sg:province":"West-Vlaanderen",
    "sg:tags":[
        "caf\u00e9s"
    ],
    "wof:name":"Caf\u00c9 De Vlasbloem",
    "wof:placetype":"venue"
},
  "geometry": {"coordinates":[3.2401659489,50.8158378601],"type":"Point"}
}