{
  "type": "Feature",
  "properties": {
    "iso:country":"BE",
    "sg:address":"Wallestraat 40a",
    "sg:city":"Geraardsbergen (waarbeke)",
    "sg:classifiers":[
        {
            "category":"Banks & Credit Unions",
            "subcategory":"Investment Brokerage",
            "type":"Services"
        }
    ],
    "sg:phone":"+32 54 32 68 85",
    "sg:postcode":"9506",
    "sg:province":"Oost-Vlaanderen",
    "sg:tags":[
        "railroad",
        "work"
    ],
    "wof:name":"Lauwaert - De Nutte Nv",
    "wof:placetype":"venue"
},
  "geometry": {"coordinates":[3.8985300064,50.7987060547],"type":"Point"}
}