{
  "type": "Feature",
  "properties": {
    "iso:country":"BE",
    "sg:address":"Mechelsesteenweg 57",
    "sg:city":"Hove",
    "sg:orig_category":"Light Containers For Canned Foods",
    "sg:phone":"+32 3 455 18 61",
    "sg:postcode":"2540",
    "sg:province":"Antwerpen",
    "wof:name":"Hottlet International Agencies Nv",
    "wof:placetype":"venue"
},
  "geometry": {"coordinates":[4.4640231133,51.1494216919],"type":"Point"}
}