{
  "type": "Feature",
  "properties": {
    "iso:country":"BE",
    "sg:address":"Torhoutse Baan 111",
    "sg:city":"Gistel",
    "sg:orig_category":"Etablissements Erotiques",
    "sg:phone":"+32 59 27 64 91",
    "sg:postcode":"8470",
    "sg:province":"West-Vlaanderen",
    "wof:name":"The Carolines",
    "wof:placetype":"venue"
},
  "geometry": {"coordinates":[2.9588999748,51.1464691162],"type":"Point"}
}