{
  "type": "Feature",
  "properties": {
    "iso:country":"BE",
    "sg:address":"Rue Du Malakoff 4",
    "sg:city":"Herve",
    "sg:classifiers":[
        {
            "category":"Building & Trades",
            "subcategory":"Plumbing",
            "type":"Services"
        }
    ],
    "sg:phone":"+32 87 67 81 18",
    "sg:postcode":"4650",
    "sg:province":"Li\u00e8ge",
    "sg:tags":[
        "pipe",
        "drain",
        "unblocking"
    ],
    "wof:name":"Moreau R (entreprise)",
    "wof:placetype":"venue"
},
  "geometry": {"coordinates":[5.7933712006,50.6447067261],"type":"Point"}
}