{
  "type": "Feature",
  "properties": {
    "addr:full":"Stationsstraat 156 Oostrozebeke West-Vlaanderen 8780",
    "addr:housenumber":"156",
    "addr:postcode":"8780",
    "addr:street":"Stationsstraat",
    "iso:country":"BE",
    "sg:address":"Stationsstraat 156",
    "sg:city":"Oostrozebeke",
    "sg:classifiers":[
        {
            "category":"Retail",
            "subcategory":"Funeral Services",
            "type":"Services"
        }
    ],
    "sg:phone":"+32 56 66 72 10",
    "sg:postcode":"8780",
    "sg:province":"West-Vlaanderen",
    "sg:tags":[
        "director"
    ],
    "wof:name":"Lambrecht",
    "wof:placetype":"venue"
},
  "geometry": {"coordinates":[3.3275630474,50.9115447998],"type":"Point"}
}