{
  "type": "Feature",
  "properties": {
    "iso:country":"BE",
    "sg:address":"Rue Grand'ville 65",
    "sg:city":"Verviers (ensival)",
    "sg:classifiers":[
        {
            "category":"Personal",
            "subcategory":"Nail Salon",
            "type":"Services"
        }
    ],
    "sg:phone":"+32 87 33 55 84",
    "sg:postcode":"4800",
    "sg:province":"Li\u00e8ge",
    "sg:tags":[
        "pedicure"
    ],
    "wof:name":"Hubert N",
    "wof:placetype":"venue"
},
  "geometry": {"coordinates":[5.842634201,50.5815086365],"type":"Point"}
}