{
  "type": "Feature",
  "properties": {
    "addr:full":"Monnikenhofstraat 25 Antwerpen Antwerpen 2040",
    "addr:housenumber":"25",
    "addr:postcode":"2040",
    "addr:street":"Monnikenhofstraat",
    "iso:country":"BE",
    "sg:address":"Monnikenhofstraat 25",
    "sg:city":"Antwerpen",
    "sg:orig_category":"Enseignement maternel and primaire",
    "sg:phone":"+32 3 568 66 21",
    "sg:postcode":"2040",
    "sg:province":"Antwerpen",
    "wof:name":"Stedelijke Basisschool",
    "wof:placetype":"venue"
},
  "geometry": {"coordinates":[4.3280501366,51.3489608765],"type":"Point"}
}