{
  "type": "Feature",
  "properties": {
    "iso:country":"BE",
    "sg:address":"Wijtschotbaan 9",
    "sg:city":"Schoten",
    "sg:orig_category":"Mat\u00e9riel pour plomberie and chauffage Electrom\u00e9nager, t\u00e9l\u00e9visions and radios Air conditionn\u00e9 and ven",
    "sg:phone":"+32 3 658 39 24",
    "sg:postcode":"2900",
    "sg:province":"Antwerpen",
    "wof:name":"A.a.c.t.",
    "wof:placetype":"venue"
},
  "geometry": {"coordinates":[4.506811142,51.2419090271],"type":"Point"}
}