{
  "type": "Feature",
  "properties": {
    "addr:full":"Veerstraat 26b1 Dendermonde Oost-Vlaanderen 9200",
    "addr:housenumber":"26b1",
    "addr:postcode":"9200",
    "addr:street":"Veerstraat;Oost-Vlaanderen",
    "iso:country":"BE",
    "sg:address":"Veerstraat 26b1",
    "sg:city":"Dendermonde",
    "sg:orig_category":"Brood, gebak and snoepgoed",
    "sg:phone":"+32 52 21 18 54",
    "sg:postcode":"9200",
    "sg:province":"Oost-Vlaanderen",
    "wof:name":"Chanty",
    "wof:placetype":"venue"
},
  "geometry": {"coordinates":[4.1020889282,51.0330619812],"type":"Point"}
}