{
  "type": "Feature",
  "properties": {
    "addr:full":"Route De Philippeville 307 Charleroi Hainaut 6010",
    "addr:housenumber":"307",
    "addr:postcode":"6010",
    "addr:street":"Route De Philippeville;Hainaut",
    "iso:country":"BE",
    "sg:address":"Route De Philippeville 307",
    "sg:city":"Charleroi",
    "sg:classifiers":[
        {
            "category":"Autos & Motor Vehicles",
            "subcategory":"Recreational Vehicle Sales",
            "type":"Retail Goods"
        }
    ],
    "sg:phone":"+32 71 36 08 29",
    "sg:postcode":"6010",
    "sg:province":"Hainaut",
    "sg:tags":[
        "quincailleries",
        "machine",
        "agricoles",
        "mat\u00e9riel",
        "gr"
    ],
    "wof:name":"Alexandre",
    "wof:placetype":"venue"
},
  "geometry": {"coordinates":[4.4642820358,50.3842544556],"type":"Point"}
}