{
  "type": "Feature",
  "properties": {
    "iso:country":"BE",
    "sg:address":"Bouwelsesteenweg 29",
    "sg:city":"Nijlen",
    "sg:classifiers":[
        {
            "category":"Fast Food",
            "type":"Food & Drink"
        }
    ],
    "sg:phone":"+32 3 411 06 85",
    "sg:postcode":"2560",
    "sg:province":"Antwerpen",
    "sg:tags":[
        "fried",
        "stand",
        "potato"
    ],
    "wof:name":"Spinneke ('t)",
    "wof:placetype":"venue"
},
  "geometry": {"coordinates":[4.6776399612,51.1634674072],"type":"Point"}
}