{
  "type": "Feature",
  "properties": {
    "iso:country":"BE",
    "sg:address":"Begijnestraat 12",
    "sg:city":"Lede",
    "sg:orig_category":"Afbraak- and draineerwerken",
    "sg:phone":"+32 56 50 95 87",
    "sg:postcode":"8880",
    "sg:province":"West-Vlaanderen",
    "wof:name":"Baert",
    "wof:placetype":"venue"
},
  "geometry": {"coordinates":[3.1315939426,50.8708877563],"type":"Point"}
}