{
  "type": "Feature",
  "properties": {
    "iso:country":"BE",
    "sg:address":"Kerkstraat 22",
    "sg:city":"Nieuwerkerken",
    "sg:orig_category":"Charpentes and couvertures. Plomberie, chauffage and installations sanitaires",
    "sg:phone":"+32 11 68 75 21",
    "sg:postcode":"3850",
    "sg:province":"Limburg",
    "wof:name":"Limburgse Waterdichtingswerken",
    "wof:placetype":"venue"
},
  "geometry": {"coordinates":[5.1905260086,50.8584785461],"type":"Point"}
}