{
  "type": "Feature",
  "properties": {
    "iso:country":"BE",
    "sg:address":"Brusselsepoortstraat 5",
    "sg:city":"Mechelen",
    "sg:classifiers":[
        {
            "category":"Bakery",
            "type":"Food & Drink"
        }
    ],
    "sg:phone":"+32 15 45 05 83",
    "sg:postcode":"2800",
    "sg:province":"Antwerpen",
    "sg:tags":[
        "confectioner",
        "baker"
    ],
    "wof:name":"Verstraelen",
    "wof:placetype":"venue"
},
  "geometry": {"coordinates":[4.4736890793,51.0216331482],"type":"Point"}
}