{
  "type": "Feature",
  "properties": {
    "addr:full":"Oudenaardse Heerweg 66 Deerlijk West-Vlaanderen 8540",
    "addr:housenumber":"66",
    "addr:postcode":"8540",
    "addr:street":"Heerweg",
    "iso:country":"BE",
    "sg:address":"Oudenaardse Heerweg 66",
    "sg:city":"Deerlijk",
    "sg:classifiers":[
        {
            "category":"Banks & Credit Unions",
            "subcategory":"Investment Brokerage",
            "type":"Services"
        }
    ],
    "sg:phone":"+32 56 71 16 48",
    "sg:postcode":"8540",
    "sg:province":"West-Vlaanderen",
    "sg:tags":[
        "box",
        "small",
        "folding"
    ],
    "wof:name":"Kartonnage D. Lambrecht Nv",
    "wof:placetype":"venue"
},
  "geometry": {"coordinates":[3.3689520359,50.8305282593],"type":"Point"}
}