{
  "type": "Feature",
  "properties": {
    "iso:country":"BE",
    "sg:address":"Kapelsestraat 139",
    "sg:city":"Kapellen",
    "sg:classifiers":[
        {
            "category":"Shopping",
            "subcategory":"Florist",
            "type":"Retail Goods"
        }
    ],
    "sg:phone":"+32 3 313 87 89",
    "sg:postcode":"2950",
    "sg:province":"Antwerpen",
    "wof:name":"Attentie (d')",
    "wof:placetype":"venue"
},
  "geometry": {"coordinates":[4.4127159119,51.3315925598],"type":"Point"}
}