{
  "type": "Feature",
  "properties": {
    "iso:country":"BE",
    "sg:address":"Engelsesteenweg 29",
    "sg:city":"Beveren",
    "sg:classifiers":[
        {
            "category":"Cafe",
            "type":"Food & Drink"
        }
    ],
    "sg:phone":"+32 3 575 84 37",
    "sg:postcode":"9130",
    "sg:province":"Oost-Vlaanderen",
    "sg:tags":[
        "caf\u00e9s"
    ],
    "wof:name":"Caf\u00c9 Saxonia",
    "wof:placetype":"venue"
},
  "geometry": {"coordinates":[4.2641181946,51.311756134],"type":"Point"}
}