{
  "type": "Feature",
  "properties": {
    "addr:full":"Oude Tramlijn 1 Laakdal Antwerpen 2430",
    "addr:housenumber":"1",
    "addr:postcode":"2430",
    "addr:street":"Oude Tramlijn",
    "iso:country":"BE",
    "sg:address":"Oude Tramlijn 1",
    "sg:city":"Laakdal",
    "sg:classifiers":[
        {
            "category":"Insurance",
            "subcategory":"Life Insurance",
            "type":"Services"
        }
    ],
    "sg:phone":"+32 14 86 60 94",
    "sg:postcode":"2430",
    "sg:province":"Antwerpen",
    "sg:tags":[
        "assurance"
    ],
    "wof:name":"Sprengers Ren\u00c9",
    "wof:placetype":"venue"
},
  "geometry": {"coordinates":[5.0050530434,51.1045417786],"type":"Point"}
}