{
  "type": "Feature",
  "properties": {
    "iso:country":"BE",
    "sg:address":"Hems Rode 3",
    "sg:city":"Anzegem",
    "sg:orig_category":"Maatschappelijke dienstverlening",
    "sg:phone":"+32 56 68 97 27",
    "sg:postcode":"8570",
    "sg:province":"West-Vlaanderen",
    "wof:name":"Rode Kruis Anzegem",
    "wof:placetype":"venue"
},
  "geometry": {"coordinates":[3.4739420414,50.8428878784],"type":"Point"}
}