{
  "type": "Feature",
  "properties": {
    "addr:full":"Aardseweg 161 Geel Antwerpen 2440",
    "addr:housenumber":"161",
    "addr:postcode":"2440",
    "addr:street":"Aardseweg",
    "iso:country":"BE",
    "sg:address":"Aardseweg 161",
    "sg:city":"Geel",
    "sg:classifiers":[
        {
            "category":"Professional",
            "subcategory":"Management & Consulting",
            "type":"Services"
        }
    ],
    "sg:phone":"+32 14 85 07 26",
    "sg:postcode":"2440",
    "sg:province":"Antwerpen",
    "sg:tags":[
        "consultant"
    ],
    "wof:name":"T.m.e.",
    "wof:placetype":"venue"
},
  "geometry": {"coordinates":[5.0070700645,51.2123603821],"type":"Point"}
}