{
  "type": "Feature",
  "properties": {
    "addr:full":"Rue Provinciale 155 Wavre (bierges) Brabant Wallon 1301",
    "addr:housenumber":"155;1301",
    "addr:street":"Rue Provinciale",
    "iso:country":"BE",
    "sg:address":"Rue Provinciale 155",
    "sg:city":"Wavre (bierges)",
    "sg:classifiers":[
        {
            "category":"Shopping",
            "subcategory":"Books",
            "type":"Retail Goods"
        }
    ],
    "sg:phone":"+32 10 41 01 31",
    "sg:postcode":"1301",
    "sg:province":"Brabant Wallon",
    "sg:tags":[
        "bookseller"
    ],
    "wof:name":"Librairie De Bierges Sprl",
    "wof:placetype":"venue"
},
  "geometry": {"coordinates":[4.5958909988,50.7092285156],"type":"Point"}
}