{
  "type": "Feature",
  "properties": {
    "addr:full":"Winkelsestraat 15 Lendelede West-Vlaanderen 8860",
    "addr:housenumber":"15",
    "addr:postcode":"8860",
    "addr:street":"Winkelsestraat",
    "iso:country":"BE",
    "sg:address":"Winkelsestraat 15",
    "sg:city":"Lendelede",
    "sg:orig_category":"Protection civile",
    "sg:phone":"+32 51 30 82 41",
    "sg:postcode":"8860",
    "sg:province":"West-Vlaanderen",
    "wof:name":"Brandweerkazerne",
    "wof:placetype":"venue"
},
  "geometry": {"coordinates":[3.2345879078,50.8854255676],"type":"Point"}
}