{
  "type": "Feature",
  "properties": {
    "addr:full":"Lincolnstraat 37 Ukkel/uccle Bruxelles-Capitale 1180",
    "addr:housenumber":"37",
    "addr:postcode":"1180",
    "addr:street":"Lincolnstraat;/",
    "iso:country":"BE",
    "sg:address":"Lincolnstraat 37",
    "sg:city":"Ukkel/uccle",
    "sg:orig_category":"Landmeters",
    "sg:phone":"+32 2 347 33 62",
    "sg:postcode":"1180",
    "sg:province":"Bruxelles-Capitale",
    "wof:name":"P. Deffense",
    "wof:placetype":"venue"
},
  "geometry": {"coordinates":[4.3631339073,50.8148612976],"type":"Point"}
}