{
  "type": "Feature",
  "properties": {
    "iso:country":"BE",
    "sg:address":"Begoniastraat 18",
    "sg:city":"Nazareth (eke)",
    "sg:orig_category":"Non-Classified Establishments",
    "sg:phone":"+32 9 385 62 71",
    "sg:postcode":"9810",
    "sg:province":"Oost-Vlaanderen",
    "wof:name":"Riello Service Center",
    "wof:placetype":"venue"
},
  "geometry": {"coordinates":[3.65873909,50.9737854004],"type":"Point"}
}