{
  "type": "Feature",
  "properties": {
    "addr:full":"Albertwal 10 Tongeren Limburg 3700",
    "addr:housenumber":"10",
    "addr:postcode":"3700",
    "addr:street":"Albertwal",
    "iso:country":"BE",
    "sg:address":"Albertwal 10",
    "sg:city":"Tongeren",
    "sg:orig_category":"Parfumeries. Salons de coiffure",
    "sg:phone":"+32 12 23 56 43",
    "sg:postcode":"3700",
    "sg:province":"Limburg",
    "wof:name":"Coiffure Maryse",
    "wof:placetype":"venue"
},
  "geometry": {"coordinates":[5.4600391388,50.777545929],"type":"Point"}
}