{
  "type": "Feature",
  "properties": {
    "addr:full":"Steenweg 36 Heers Limburg 3870",
    "addr:housenumber":"36",
    "addr:postcode":"3870",
    "addr:street":"Steenweg",
    "iso:country":"BE",
    "sg:address":"Steenweg 36",
    "sg:city":"Heers",
    "sg:classifiers":[
        {
            "category":"Retail",
            "subcategory":"Auto Repair",
            "type":"Services"
        }
    ],
    "sg:phone":"+32 11 48 19 40",
    "sg:postcode":"3870",
    "sg:province":"Limburg",
    "sg:tags":[
        "automobile-body"
    ],
    "wof:name":"Velkeneers G",
    "wof:placetype":"venue"
},
  "geometry": {"coordinates":[5.2802300453,50.7583084106],"type":"Point"}
}