{
  "type": "Feature",
  "properties": {
    "addr:full":"Boulevard Lambermont 79 Bruxelles (schaerbeek) Bruxelles-Capitale 1030",
    "addr:housenumber":"79",
    "addr:postcode":"1030",
    "addr:street":"Boulevard Lambermont",
    "iso:country":"BE",
    "sg:address":"Boulevard Lambermont 79",
    "sg:city":"Bruxelles (schaerbeek)",
    "sg:classifiers":[
        {
            "category":"Banks & Credit Unions",
            "subcategory":"Investment Brokerage",
            "type":"Services"
        }
    ],
    "sg:phone":"+32 2 247 88 00",
    "sg:postcode":"1030",
    "sg:province":"Bruxelles-Capitale",
    "sg:tags":[
        "supply",
        "processing",
        "-",
        "access",
        "carrier",
        "data"
    ],
    "wof:name":"Emtec Magnetics Benelux Sa",
    "wof:placetype":"venue"
},
  "geometry": {"coordinates":[4.3783612251,50.8726425171],"type":"Point"}
}