{
  "type": "Feature",
  "properties": {
    "addr:full":"Kiezelweg 181 Mol Antwerpen 2400",
    "addr:housenumber":"181",
    "addr:postcode":"2400",
    "addr:street":"Kiezelweg",
    "iso:country":"BE",
    "sg:address":"Kiezelweg 181",
    "sg:city":"Mol",
    "sg:classifiers":[
        {
            "category":"Restaurant",
            "type":"Food & Drink"
        }
    ],
    "sg:phone":"+32 14 82 11 82",
    "sg:postcode":"2400",
    "sg:province":"Antwerpen",
    "wof:name":"Hof Van 't Rauw",
    "wof:placetype":"venue"
},
  "geometry": {"coordinates":[5.1930098534,51.2158508301],"type":"Point"}
}