{
  "type": "Feature",
  "properties": {
    "addr:full":"Rue Jean D'outremeuse 11 Luik Li\u00e8ge 4020",
    "addr:housenumber":"11",
    "addr:postcode":"4020",
    "addr:street":"Rue Jean D'Outremeuse;Luik Lie\u0300Ge",
    "iso:country":"BE",
    "sg:address":"Rue Jean D'outremeuse 11",
    "sg:city":"Luik",
    "sg:orig_category":"Telecommunicatieapparaten",
    "sg:phone":"+32 4 342 05 05",
    "sg:postcode":"4020",
    "sg:province":"Li\u00e8ge",
    "wof:name":"Adcar",
    "wof:placetype":"venue"
},
  "geometry": {"coordinates":[5.5825138092,50.6391677856],"type":"Point"}
}