{
  "type": "Feature",
  "properties": {
    "addr:full":"Rue De Brabant 131 Bruxelles (schaerbeek) Bruxelles-Capitale 1030",
    "addr:housenumber":"131",
    "addr:postcode":"1030",
    "addr:street":"Rue De Brabant",
    "iso:country":"BE",
    "sg:address":"Rue De Brabant 131",
    "sg:city":"Bruxelles (schaerbeek)",
    "sg:classifiers":[
        {
            "category":"Shopping",
            "subcategory":"Gifts & Souvenirs",
            "type":"Retail Goods"
        }
    ],
    "sg:phone":"+32 2 218 27 42",
    "sg:postcode":"1030",
    "sg:province":"Bruxelles-Capitale",
    "sg:tags":[
        "-"
    ],
    "wof:name":"Euro-giga",
    "wof:placetype":"venue"
},
  "geometry": {"coordinates":[4.3644919395,50.8619651794],"type":"Point"}
}