{
  "type": "Feature",
  "properties": {
    "iso:country":"BE",
    "sg:address":"Kleinhoefstraat 5",
    "sg:city":"Geel",
    "sg:classifiers":[
        {
            "category":"Professional",
            "subcategory":"Computer Services",
            "type":"Services"
        }
    ],
    "sg:phone":"+32 14 56 23 60",
    "sg:postcode":"2440",
    "sg:province":"Antwerpen",
    "sg:tags":[
        "-",
        "processing",
        "data",
        "software"
    ],
    "wof:name":"Qso",
    "wof:placetype":"venue"
},
  "geometry": {"coordinates":[4.9651899338,51.1611480713],"type":"Point"}
}