{
  "type": "Feature",
  "properties": {
    "iso:country":"BE",
    "sg:address":"Markt 69",
    "sg:city":"Lokeren",
    "sg:orig_category":"Schoenen",
    "sg:phone":"+32 9 348 13 04",
    "sg:postcode":"9160",
    "sg:province":"Oost-Vlaanderen",
    "wof:name":"Shoes In The Box",
    "wof:placetype":"venue"
},
  "geometry": {"coordinates":[3.9900479317,51.1039352417],"type":"Point"}
}