{
  "type": "Feature",
  "properties": {
    "addr:full":"Ijzer 47 Nieuwpoort West-Vlaanderen 8620",
    "addr:housenumber":"47",
    "addr:postcode":"8620",
    "addr:street":"Ijzer",
    "iso:country":"BE",
    "sg:address":"Ijzer 47",
    "sg:city":"Nieuwpoort",
    "sg:classifiers":[
        {
            "category":"Building & Trades",
            "subcategory":"Construction",
            "type":"Services"
        }
    ],
    "sg:phone":"+32 58 23 87 68",
    "sg:postcode":"8620",
    "sg:province":"West-Vlaanderen",
    "sg:tags":[
        "stucco",
        "contractor"
    ],
    "wof:name":"Struelens J",
    "wof:placetype":"venue"
},
  "geometry": {"coordinates":[2.7640180588,51.134311676],"type":"Point"}
}