{
  "type": "Feature",
  "properties": {
    "iso:country":"BE",
    "sg:address":"Rue Collin Leloup 41",
    "sg:city":"Spa",
    "sg:orig_category":"Rijscholen",
    "sg:phone":"+32 87 77 12 20",
    "sg:postcode":"4900",
    "sg:province":"Li\u00e8ge",
    "wof:name":"Auto-ecole Spadoise-racb",
    "wof:placetype":"venue"
},
  "geometry": {"coordinates":[5.8629179001,50.4909362793],"type":"Point"}
}