{
  "type": "Feature",
  "properties": {
    "addr:full":"Oude Kortrijkstraat 108 Zonnebeke West-Vlaanderen 8980",
    "addr:housenumber":"108",
    "addr:postcode":"8980",
    "addr:street":"Oude Kortrijkstraat",
    "iso:country":"BE",
    "sg:address":"Oude Kortrijkstraat 108",
    "sg:city":"Zonnebeke",
    "sg:classifiers":[
        {
            "category":"Building & Trades",
            "subcategory":"Plumbing",
            "type":"Services"
        }
    ],
    "sg:phone":"+32 57 46 63 64",
    "sg:postcode":"8980",
    "sg:province":"West-Vlaanderen",
    "sg:tags":[
        "contractor"
    ],
    "wof:name":"Vermeeren Rik",
    "wof:placetype":"venue"
},
  "geometry": {"coordinates":[2.9602370262,50.8447341919],"type":"Point"}
}