{
  "type": "Feature",
  "properties": {
    "iso:country":"BE",
    "sg:address":"Gaasbeekstraat 38",
    "sg:city":"Dilbeek (itterbeek)",
    "sg:classifiers":[
        {
            "category":"Utilities",
            "subcategory":"Telephone",
            "type":"Services"
        }
    ],
    "sg:phone":"+32 2 569 24 04",
    "sg:postcode":"1701",
    "sg:province":"Vlaams-Brabant",
    "sg:tags":[
        "-",
        "internet"
    ],
    "wof:name":"3b Leasing Services",
    "wof:placetype":"venue"
},
  "geometry": {"coordinates":[4.2413339615,50.8167724609],"type":"Point"}
}