{
  "type": "Feature",
  "properties": {
    "iso:country":"BE",
    "sg:address":"Rue Des Champs 8",
    "sg:city":"Faimes",
    "sg:orig_category":"Eleveurs de bovins",
    "sg:phone":"+32 19 32 44 44",
    "sg:postcode":"4317",
    "sg:province":"Li\u00e8ge",
    "wof:name":"Lucien Humblet",
    "wof:placetype":"venue"
},
  "geometry": {"coordinates":[5.2622089386,50.6669158936],"type":"Point"}
}