{
  "type": "Feature",
  "properties": {
    "iso:country":"BE",
    "sg:address":"Kerkenbosstraat 32",
    "sg:city":"Tremelo",
    "sg:orig_category":"Plomberie, chauffage and installations sanitaires",
    "sg:phone":"+32 16 53 62 36",
    "sg:postcode":"3128",
    "sg:province":"Vlaams-Brabant",
    "wof:name":"Verlinden Tim",
    "wof:placetype":"venue"
},
  "geometry": {"coordinates":[4.7541508675,50.9949302673],"type":"Point"}
}