{
  "type": "Feature",
  "properties": {
    "iso:country":"BE",
    "sg:address":"Rue De Rochefort 125",
    "sg:city":"Beauraing",
    "sg:classifiers":[
        {
            "category":"Retail",
            "subcategory":"Veterinary Services",
            "type":"Services"
        }
    ],
    "sg:phone":"+32 82 71 22 22",
    "sg:postcode":"5570",
    "sg:province":"Namur",
    "sg:tags":[
        "veterinarian"
    ],
    "wof:name":"Dardenne J",
    "wof:placetype":"venue"
},
  "geometry": {"coordinates":[4.9683132172,50.1148605347],"type":"Point"}
}