{
  "type": "Feature",
  "properties": {
    "iso:country":"BE",
    "sg:address":"Rue Nestor-bouillon 3",
    "sg:city":"Somme-leuze",
    "sg:orig_category":"Elektrische installaties voor woningen",
    "sg:phone":"+32 83 68 83 63",
    "sg:postcode":"5377",
    "sg:province":"Namur",
    "wof:name":"Adolphe Rousseau",
    "wof:placetype":"venue"
},
  "geometry": {"coordinates":[5.2486948967,50.2696113586],"type":"Point"}
}