{
  "type": "Feature",
  "properties": {
    "addr:full":"Rue De Sondeville 133 P\u00c9ruwelz Hainaut 7600",
    "addr:housenumber":"133",
    "addr:postcode":"7600",
    "addr:street":"Rue De Sondeville",
    "iso:country":"BE",
    "sg:address":"Rue De Sondeville 133",
    "sg:city":"P\u00c9ruwelz",
    "sg:orig_category":"Action sociale avec h\u00e9bergement",
    "sg:phone":"+32 69 77 48 44",
    "sg:postcode":"7600",
    "sg:province":"Hainaut",
    "wof:name":"Maison Accueil La Bo\u00cetrie",
    "wof:placetype":"venue"
},
  "geometry": {"coordinates":[3.5889160633,50.5033073425],"type":"Point"}
}