{
  "type": "Feature",
  "properties": {
    "iso:country":"BE",
    "sg:address":"Rue De La Barri\u00e8re De Fer 155",
    "sg:city":"Mouscron (dottignies)",
    "sg:classifiers":[
        {
            "category":"Manufacturing",
            "subcategory":"Lumber",
            "type":"Manufacturing & Wholesale Goods"
        }
    ],
    "sg:phone":"+32 56 48 98 31",
    "sg:postcode":"7711",
    "sg:province":"Hainaut",
    "sg:tags":[
        "timber"
    ],
    "wof:name":"Dekimpe Fr\u00e8res",
    "wof:placetype":"venue"
},
  "geometry": {"coordinates":[3.3187088966,50.7274398804],"type":"Point"}
}