{
  "type": "Feature",
  "properties": {
    "iso:country":"BE",
    "sg:address":"Beversesteenweg 558",
    "sg:city":"Roeselare",
    "sg:orig_category":"Installation de menuiserie en bois and plastique",
    "sg:phone":"+32 51 24 96 12",
    "sg:postcode":"8800",
    "sg:province":"West-Vlaanderen",
    "wof:name":"Defoer Willy",
    "wof:placetype":"venue"
},
  "geometry": {"coordinates":[3.1560239792,50.9713783264],"type":"Point"}
}