{
  "type": "Feature",
  "properties": {
    "iso:country":"BE",
    "sg:address":"Ardoystraat 57",
    "sg:city":"Hamme",
    "sg:orig_category":"Eleveurs de bovins",
    "sg:phone":"+32 52 47 86 05",
    "sg:postcode":"9220",
    "sg:province":"Oost-Vlaanderen",
    "wof:name":"Suzanne Michiels",
    "wof:placetype":"venue"
},
  "geometry": {"coordinates":[4.095099926,51.0928497314],"type":"Point"}
}