{
  "type": "Feature",
  "properties": {
    "addr:full":"Rue Saint-guidon 16 Bruxelles (anderlecht) Bruxelles-Capitale 1070",
    "addr:housenumber":"16",
    "addr:postcode":"1070",
    "addr:street":"Rue Saint-Guidon",
    "iso:country":"BE",
    "sg:address":"Rue Saint-guidon 16",
    "sg:city":"Bruxelles (anderlecht)",
    "sg:classifiers":[
        {
            "category":"Professional",
            "subcategory":"Accounting & Tax Preparation",
            "type":"Services"
        }
    ],
    "sg:phone":"+32 2 523 98 28",
    "sg:postcode":"1070",
    "sg:province":"Bruxelles-Capitale",
    "sg:tags":[
        "accountant"
    ],
    "wof:name":"Baukens J",
    "wof:placetype":"venue"
},
  "geometry": {"coordinates":[4.3054718971,50.8354454041],"type":"Point"}
}