{
  "type": "Feature",
  "properties": {
    "iso:country":"BE",
    "sg:address":"Chemin Des Marronnier 50",
    "sg:city":"Namur",
    "sg:orig_category":"Sportclubs",
    "sg:phone":"+32 81 46 12 45",
    "sg:postcode":"5100",
    "sg:province":"Namur",
    "wof:name":"B.s.c. Namur Angels",
    "wof:placetype":"venue"
},
  "geometry": {"coordinates":[4.8448810577,50.4272155762],"type":"Point"}
}