{
  "type": "Feature",
  "properties": {
    "iso:country":"BE",
    "sg:address":"Avenue De La Belle Voie 21",
    "sg:city":"Wavre",
    "sg:classifiers":[
        {
            "category":"Real Estate",
            "subcategory":"Architect",
            "type":"Services"
        }
    ],
    "sg:phone":"+32 10 22 78 57",
    "sg:postcode":"1300",
    "sg:province":"Brabant Wallon",
    "wof:name":"De Laminne De Bex Et Associ\u00e9s Sc",
    "wof:placetype":"venue"
},
  "geometry": {"coordinates":[4.6179251671,50.7196998596],"type":"Point"}
}