{
  "type": "Feature",
  "properties": {
    "addr:full":"Korte Lane 20 Brugge West-Vlaanderen 8000",
    "addr:housenumber":"20",
    "addr:postcode":"8000",
    "addr:street":"Korte Lane",
    "iso:country":"BE",
    "sg:address":"Korte Lane 20",
    "sg:city":"Brugge",
    "sg:classifiers":[
        {
            "category":"Restaurant",
            "type":"Food & Drink"
        }
    ],
    "sg:phone":"+32 50 34 46 05",
    "sg:postcode":"8000",
    "sg:province":"West-Vlaanderen",
    "wof:name":"Guillaume",
    "wof:placetype":"venue"
},
  "geometry": {"coordinates":[3.2164769173,51.2076873779],"type":"Point"}
}