{
  "type": "Feature",
  "properties": {
    "iso:country":"BE",
    "sg:address":"Rue Traversi\u00e8re 68",
    "sg:city":"Bruxelles (saint-josse-ten-noode)",
    "sg:classifiers":[
        {
            "category":"Professional",
            "subcategory":"Management & Consulting",
            "type":"Services"
        }
    ],
    "sg:phone":"+32 2 223 14 94",
    "sg:postcode":"1210",
    "sg:province":"Bruxelles-Capitale",
    "sg:tags":[
        "consultant"
    ],
    "wof:name":"Crickey Bvba",
    "wof:placetype":"venue"
},
  "geometry": {"coordinates":[4.3714361191,50.8535423279],"type":"Point"}
}