{
  "type": "Feature",
  "properties": {
    "addr:full":"Voetbalstraat 21 Beringen Limburg 3580",
    "addr:housenumber":"21",
    "addr:postcode":"3580",
    "addr:street":"Voetbalstraat",
    "iso:country":"BE",
    "sg:address":"Voetbalstraat 21",
    "sg:city":"Beringen",
    "sg:classifiers":[
        {
            "category":"Health Services",
            "subcategory":"Health Practitioner",
            "type":"Services"
        }
    ],
    "sg:phone":"+32 11 43 37 09",
    "sg:postcode":"3580",
    "sg:province":"Limburg",
    "sg:tags":[
        "physiotherapist"
    ],
    "wof:name":"Beaufays Alain",
    "wof:placetype":"venue"
},
  "geometry": {"coordinates":[5.2251148224,51.0527267456],"type":"Point"}
}