{
  "type": "Feature",
  "properties": {
    "addr:full":"Avenue Rommelaere 49 Bruxelles Bruxelles-Capitale 1020",
    "addr:housenumber":"49",
    "addr:postcode":"1020",
    "addr:street":"Avenue Rommelaere",
    "iso:country":"BE",
    "sg:address":"Avenue Rommelaere 49",
    "sg:city":"Bruxelles",
    "sg:orig_category":"Non-Classified Establishments",
    "sg:phone":"+32 2 478 43 89",
    "sg:postcode":"1020",
    "sg:province":"Bruxelles-Capitale",
    "wof:name":"Jamart Chocolatier",
    "wof:placetype":"venue"
},
  "geometry": {"coordinates":[4.3341779709,50.8893814087],"type":"Point"}
}