{
  "type": "Feature",
  "properties": {
    "addr:full":"Beemdenstraat 53 Brasschaat Antwerpen 2930",
    "addr:housenumber":"53",
    "addr:postcode":"2930",
    "addr:street":"Beemdenstraat",
    "iso:country":"BE",
    "sg:address":"Beemdenstraat 53",
    "sg:city":"Brasschaat",
    "sg:orig_category":"Artistes ind\u00e9pendants",
    "sg:phone":"+32 3 651 48 88",
    "sg:postcode":"2930",
    "sg:province":"Antwerpen",
    "wof:name":"Timmermans Johan",
    "wof:placetype":"venue"
},
  "geometry": {"coordinates":[4.507630825,51.2913208008],"type":"Point"}
}