{
  "type": "Feature",
  "properties": {
    "addr:full":"Rue Des Grives 3 Aubange Luxembourg 6790",
    "addr:housenumber":"3",
    "addr:postcode":"6790",
    "addr:street":"Rue Des Grives",
    "iso:country":"BE",
    "sg:address":"Rue Des Grives 3",
    "sg:city":"Aubange",
    "sg:orig_category":"Woningbouw",
    "sg:phone":"+32 63 37 02 70",
    "sg:postcode":"6790",
    "sg:province":"Luxembourg",
    "wof:name":"Ali Zerrouki",
    "wof:placetype":"venue"
},
  "geometry": {"coordinates":[5.7958989143,49.5590171814],"type":"Point"}
}