{
  "type": "Feature",
  "properties": {
    "addr:full":"Aarschotsesteenweg 856 Leuven Vlaams-Brabant 3012",
    "addr:housenumber":"856",
    "addr:postcode":"3012",
    "addr:street":"Aarschotsesteenweg",
    "iso:country":"BE",
    "sg:address":"Aarschotsesteenweg 856",
    "sg:city":"Leuven",
    "sg:orig_category":"Quincailleries. Bois Gr",
    "sg:phone":"+32 16 44 10 33",
    "sg:postcode":"3012",
    "sg:province":"Vlaams-Brabant",
    "wof:name":"Kimac-tool Max",
    "wof:placetype":"venue"
},
  "geometry": {"coordinates":[4.7270278931,50.9341659546],"type":"Point"}
}