{
  "type": "Feature",
  "properties": {
    "addr:full":"Rue De Leumont 118 Wanze (antheit) Li\u00e8ge 4520",
    "addr:housenumber":"118",
    "addr:postcode":"4520",
    "addr:street":"Rue De Leumont",
    "iso:country":"BE",
    "sg:address":"Rue De Leumont 118",
    "sg:city":"Wanze (antheit)",
    "sg:classifiers":[
        {
            "category":"Social Services",
            "type":"Services"
        }
    ],
    "sg:phone":"+32 85 23 40 88",
    "sg:postcode":"4520",
    "sg:province":"Li\u00e8ge",
    "wof:name":"Horizons Nouveaux Asbl",
    "wof:placetype":"venue"
},
  "geometry": {"coordinates":[5.2229790688,50.5348472595],"type":"Point"}
}