{
  "type": "Feature",
  "properties": {
    "addr:full":"Merksplassesteenweg 105 Rijkevorsel Antwerpen 2310",
    "addr:housenumber":"105",
    "addr:postcode":"2310",
    "addr:street":"Merksplassesteenweg",
    "iso:country":"BE",
    "sg:address":"Merksplassesteenweg 105",
    "sg:city":"Rijkevorsel",
    "sg:orig_category":"Woningbouw",
    "sg:phone":"+32 3 314 14 12",
    "sg:postcode":"2310",
    "sg:province":"Antwerpen",
    "wof:name":"Van De Mierop Gust",
    "wof:placetype":"venue"
},
  "geometry": {"coordinates":[4.8058490753,51.3483505249],"type":"Point"}
}