{
  "type": "Feature",
  "properties": {
    "addr:full":"Avenue Adolphe Schattens 26b5 Waterloo Brabant Wallon 1410",
    "addr:housenumber":"26b5",
    "addr:postcode":"1410",
    "addr:street":"Avenue Adolphe Schattens",
    "iso:country":"BE",
    "sg:address":"Avenue Adolphe Schattens 26b5",
    "sg:city":"Waterloo",
    "sg:orig_category":"Rev\u00eatements pour sols and murs. Peinture",
    "sg:phone":"+32 2 353 12 89",
    "sg:postcode":"1410",
    "sg:province":"Brabant Wallon",
    "wof:name":"Fe. Usuwiel H. & Fils",
    "wof:placetype":"venue"
},
  "geometry": {"coordinates":[4.3927598,50.7142372131],"type":"Point"}
}