{
  "type": "Feature",
  "properties": {
    "iso:country":"BE",
    "sg:address":"Regentwijk 56",
    "sg:city":"Gingelom",
    "sg:orig_category":"M\u00e9decins and sp\u00e9cialistes",
    "sg:phone":"+32 11 88 42 92",
    "sg:postcode":"3890",
    "sg:province":"Limburg",
    "wof:name":"J. Delorge",
    "wof:placetype":"venue"
},
  "geometry": {"coordinates":[5.1301131248,50.7506484985],"type":"Point"}
}