{
  "type": "Feature",
  "properties": {
    "iso:country":"BE",
    "sg:address":"Ieperstraat 146-148",
    "sg:city":"Staden",
    "sg:classifiers":[
        {
            "category":"Bars & Pubs",
            "type":"Food & Drink"
        }
    ],
    "sg:phone":"+32 51 70 35 70",
    "sg:postcode":"8840",
    "sg:province":"West-Vlaanderen",
    "wof:name":"Stadenberg",
    "wof:placetype":"venue"
},
  "geometry": {"coordinates":[3.0069410801,50.9683685303],"type":"Point"}
}