{
  "type": "Feature",
  "properties": {
    "addr:full":"Avenue Baron De Lhoneux 28 Namur Namur 5100",
    "addr:housenumber":"28",
    "addr:postcode":"5100",
    "addr:street":"Avenue Baron De Lhoneux",
    "iso:country":"BE",
    "sg:address":"Avenue Baron De Lhoneux 28",
    "sg:city":"Namur",
    "sg:orig_category":"Bloemen and planten",
    "sg:phone":"+32 81 31 04 69",
    "sg:postcode":"5100",
    "sg:province":"Namur",
    "wof:name":"Philippe Alardeau",
    "wof:placetype":"venue"
},
  "geometry": {"coordinates":[4.8713750839,50.4566345215],"type":"Point"}
}