{
  "type": "Feature",
  "properties": {
    "iso:country":"BE",
    "sg:address":"Brouwersstraat 100",
    "sg:city":"De Panne",
    "sg:classifiers":[
        {
            "category":"Organizations",
            "subcategory":"Professional Association",
            "type":"Services"
        }
    ],
    "sg:phone":"+32 58 41 54 65",
    "sg:postcode":"8660",
    "sg:province":"West-Vlaanderen",
    "sg:tags":[
        "organisation",
        "seminar"
    ],
    "wof:name":"Synergy Relations",
    "wof:placetype":"venue"
},
  "geometry": {"coordinates":[2.5953249931,51.0968933105],"type":"Point"}
}