{
  "type": "Feature",
  "properties": {
    "addr:full":"Lion D'orweg 17 Aalst Oost-Vlaanderen 9300",
    "addr:housenumber":"17",
    "addr:postcode":"9300",
    "iso:country":"BE",
    "sg:address":"Lion D'orweg 17",
    "sg:city":"Aalst",
    "sg:classifiers":[
        {
            "category":"Banks & Credit Unions",
            "subcategory":"Investment Brokerage",
            "type":"Services"
        }
    ],
    "sg:phone":"+32 53 21 45 91",
    "sg:postcode":"9300",
    "sg:province":"Oost-Vlaanderen",
    "sg:tags":[
        "fence"
    ],
    "wof:name":"De Metaalbewerkers Nv",
    "wof:placetype":"venue"
},
  "geometry": {"coordinates":[4.0399198532,50.9540710449],"type":"Point"}
}