{
  "type": "Feature",
  "properties": {
    "addr:full":"Doemstraat 4 Glabbeek Vlaams-Brabant 3384",
    "addr:housenumber":"4",
    "addr:postcode":"3384",
    "addr:street":"Doemstraat",
    "iso:country":"BE",
    "sg:address":"Doemstraat 4",
    "sg:city":"Glabbeek",
    "sg:orig_category":"Eleveurs de bovins",
    "sg:phone":"+32 16 77 80 22",
    "sg:postcode":"3384",
    "sg:province":"Vlaams-Brabant",
    "wof:name":"Paul Dormaels",
    "wof:placetype":"venue"
},
  "geometry": {"coordinates":[4.9200649261,50.8600273132],"type":"Point"}
}