{
  "type": "Feature",
  "properties": {
    "addr:full":"Vladslostraat 8 Diksmuide West-Vlaanderen 8600",
    "addr:housenumber":"8",
    "addr:postcode":"8600",
    "addr:street":"Vladslostraat",
    "iso:country":"BE",
    "sg:address":"Vladslostraat 8",
    "sg:city":"Diksmuide",
    "sg:classifiers":[
        {
            "category":"Restaurant",
            "type":"Food & Drink"
        }
    ],
    "sg:phone":"+32 51 51 15 05",
    "sg:postcode":"8600",
    "sg:province":"West-Vlaanderen",
    "wof:name":"Het Esenhof",
    "wof:placetype":"venue"
},
  "geometry": {"coordinates":[2.902780056,51.0307884216],"type":"Point"}
}