{
  "type": "Feature",
  "properties": {
    "addr:full":"Rue De Campine 187 Li\u00e8ge 1 Li\u00e8ge 4000",
    "addr:housenumber":"187;1",
    "addr:postcode":"4000",
    "addr:street":"Rue De Campine",
    "iso:country":"BE",
    "sg:address":"Rue De Campine 187",
    "sg:city":"Li\u00e8ge 1",
    "sg:classifiers":[
        {
            "category":"Utilities",
            "subcategory":"Mobile Phone",
            "type":"Services"
        }
    ],
    "sg:phone":"+32 4 226 18 59",
    "sg:postcode":"4000",
    "sg:province":"Li\u00e8ge",
    "sg:tags":[
        "moulding"
    ],
    "wof:name":"Beine W",
    "wof:placetype":"venue"
},
  "geometry": {"coordinates":[5.5684309006,50.6525917053],"type":"Point"}
}