{
  "type": "Feature",
  "properties": {
    "iso:country":"BE",
    "sg:address":"Avenue De Roodebeek 104",
    "sg:city":"Schaarbeek/schaerbeek",
    "sg:orig_category":"Bijouteries and horlogeries. R\u00e9parations d'horloges, montres and bijoux",
    "sg:phone":"+32 2 736 86 92",
    "sg:postcode":"1030",
    "sg:province":"Bruxelles-Capitale",
    "wof:name":"Maison Phenix",
    "wof:placetype":"venue"
},
  "geometry": {"coordinates":[4.4005169868,50.8484992981],"type":"Point"}
}