{
  "type": "Feature",
  "properties": {
    "addr:full":"Rue De Retinne 9 Fleron Li\u00e8ge 4620",
    "addr:housenumber":"9",
    "addr:postcode":"4620",
    "addr:street":"Rue De Retinne",
    "iso:country":"BE",
    "sg:address":"Rue De Retinne 9",
    "sg:city":"Fleron",
    "sg:orig_category":"Pain, p\u00e2tisseries and confiseries. Journaux. Fournitures de bureau. Tabac",
    "sg:phone":"+32 4 358 39 32",
    "sg:postcode":"4620",
    "sg:province":"Li\u00e8ge",
    "wof:name":"Bruls",
    "wof:placetype":"venue"
},
  "geometry": {"coordinates":[5.6874542236,50.6209106445],"type":"Point"}
}