{
  "type": "Feature",
  "properties": {
    "addr:full":"Heldergemstraat 147 Haaltert Oost-Vlaanderen 9450",
    "addr:housenumber":"147",
    "addr:postcode":"9450",
    "addr:street":"Heldergemstraat",
    "iso:country":"BE",
    "sg:address":"Heldergemstraat 147",
    "sg:city":"Haaltert",
    "sg:orig_category":"M\u00e9decins and sp\u00e9cialistes",
    "sg:phone":"+32 53 62 49 10",
    "sg:postcode":"9450",
    "sg:province":"Oost-Vlaanderen",
    "wof:name":"A. Goeman",
    "wof:placetype":"venue"
},
  "geometry": {"coordinates":[3.9552800655,50.879699707],"type":"Point"}
}