{
  "type": "Feature",
  "properties": {
    "iso:country":"BE",
    "sg:address":"Rue De Mouscron 36",
    "sg:city":"Estaimpuis",
    "sg:orig_category":"Entretien and r\u00e9parations de voitures",
    "sg:phone":"+32 56 33 30 80",
    "sg:postcode":"7730",
    "sg:province":"Hainaut",
    "wof:name":"Carrosserie Vancraynest",
    "wof:placetype":"venue"
},
  "geometry": {"coordinates":[3.2499508858,50.709854126],"type":"Point"}
}