{
  "type": "Feature",
  "properties": {
    "iso:country":"BE",
    "sg:address":"Voorthoek 83",
    "sg:city":"Stekene",
    "sg:orig_category":"Traitements param\u00e9dicaux",
    "sg:phone":"+32 3 779 70 02",
    "sg:postcode":"9190",
    "sg:province":"Oost-Vlaanderen",
    "wof:name":"O. Broeckaert",
    "wof:placetype":"venue"
},
  "geometry": {"coordinates":[4.0494298935,51.2315292358],"type":"Point"}
}