{
  "type": "Feature",
  "properties": {
    "iso:country":"BE",
    "sg:address":"Meerstraat 339",
    "sg:city":"Londerzeel",
    "sg:orig_category":"Loodgieterij, verwarming and sanitaire installaties",
    "sg:phone":"+32 52 31 23 03",
    "sg:postcode":"1840",
    "sg:province":"Vlaams-Brabant",
    "wof:name":"De Bondt",
    "wof:placetype":"venue"
},
  "geometry": {"coordinates":[4.3180818558,51.0259590149],"type":"Point"}
}