{
  "type": "Feature",
  "properties": {
    "iso:country":"BE",
    "sg:address":"Rue De L\u00b4ecole 24",
    "sg:city":"Wemmel",
    "sg:orig_category":"Quincailleries. Travail and traitement du bois. Bois Gr",
    "sg:phone":"+32 2 461 24 74",
    "sg:postcode":"1780",
    "sg:province":"Vlaams-Brabant",
    "wof:name":"Decoup\u00b4center",
    "wof:placetype":"venue"
},
  "geometry": {"coordinates":[4.3035302162,50.9099006653],"type":"Point"}
}