{
  "type": "Feature",
  "properties": {
    "addr:full":"Eikestraat 5 Herzele (steenhuize-wijnhuize) Oost-Vlaanderen 9550",
    "addr:housenumber":"5",
    "addr:postcode":"9550",
    "addr:street":"Eikestraat;Steenhuize-Wijnhuize Oost-Vlaanderen",
    "iso:country":"BE",
    "sg:address":"Eikestraat 5",
    "sg:city":"Herzele (steenhuize-wijnhuize)",
    "sg:classifiers":[
        {
            "category":"Bakery",
            "type":"Food & Drink"
        }
    ],
    "sg:phone":"+32 54 50 03 47",
    "sg:postcode":"9550",
    "sg:province":"Oost-Vlaanderen",
    "sg:tags":[
        "confectioner",
        "baker"
    ],
    "wof:name":"Beerens E",
    "wof:placetype":"venue"
},
  "geometry": {"coordinates":[3.8897190094,50.8384513855],"type":"Point"}
}