{
  "type": "Feature",
  "properties": {
    "addr:full":"Boussire 0 Malmedy Li\u00e8ge 4960",
    "addr:housenumber":"0",
    "addr:postcode":"4960",
    "addr:street":"Boussire",
    "iso:country":"BE",
    "sg:address":"Boussire 0",
    "sg:city":"Malmedy",
    "sg:orig_category":"Vakantiehuizen",
    "sg:phone":"+32 80 33 72 55",
    "sg:postcode":"4960",
    "sg:province":"Li\u00e8ge",
    "wof:name":"N. Solheid",
    "wof:placetype":"venue"
},
  "geometry": {"coordinates":[6.0306248665,50.4252433777],"type":"Point"}
}