{
  "type": "Feature",
  "properties": {
    "iso:country":"BE",
    "sg:address":"Nobelstraat 212",
    "sg:city":"Tremelo",
    "sg:orig_category":"Installation de menuiserie en bois and plastique",
    "sg:phone":"+32 15 23 33 50",
    "sg:postcode":"3128",
    "sg:province":"Vlaams-Brabant",
    "wof:name":"De Haes",
    "wof:placetype":"venue"
},
  "geometry": {"coordinates":[4.7429947853,51.0217056274],"type":"Point"}
}