{
  "type": "Feature",
  "properties": {
    "addr:full":"Kerkstraat 32 Lierde (deftinge) Oost-Vlaanderen 9570",
    "addr:housenumber":"32",
    "addr:postcode":"9570",
    "addr:street":"Kerkstraat",
    "iso:country":"BE",
    "sg:address":"Kerkstraat 32",
    "sg:city":"Lierde (deftinge)",
    "sg:classifiers":[
        {
            "category":"Professional",
            "subcategory":"Testing Lab",
            "type":"Services"
        }
    ],
    "sg:phone":"+32 54 43 87 43",
    "sg:postcode":"9570",
    "sg:province":"Oost-Vlaanderen",
    "sg:tags":[
        "chemist"
    ],
    "wof:name":"Willemsen M",
    "wof:placetype":"venue"
},
  "geometry": {"coordinates":[3.8436689377,50.7850761414],"type":"Point"}
}