{
  "type": "Feature",
  "properties": {
    "iso:country":"BE",
    "sg:address":"Passendalestraat 200",
    "sg:city":"Zonnebeke",
    "sg:orig_category":"V\u00e9los",
    "sg:phone":"+32 51 77 71 20",
    "sg:postcode":"8980",
    "sg:province":"West-Vlaanderen",
    "wof:name":"Jan Moyaert",
    "wof:placetype":"venue"
},
  "geometry": {"coordinates":[3.0089900494,50.887348175],"type":"Point"}
}