{
  "type": "Feature",
  "properties": {
    "addr:full":"Rue Des Grands Terrains 6 Namur (w\u00e9pion) Namur 5100",
    "addr:housenumber":"6",
    "addr:postcode":"5100",
    "addr:street":"Rue Des Grands Terrains",
    "iso:country":"BE",
    "sg:address":"Rue Des Grands Terrains 6",
    "sg:city":"Namur (w\u00e9pion)",
    "sg:classifiers":[
        {
            "category":"Real Estate",
            "subcategory":"Real Estate Services",
            "type":"Services"
        }
    ],
    "sg:phone":"+32 81 46 08 29",
    "sg:postcode":"5100",
    "sg:province":"Namur",
    "wof:name":"Bureau De Gestion Marchal Thiry",
    "wof:placetype":"venue"
},
  "geometry": {"coordinates":[4.8619608879,50.4257736206],"type":"Point"}
}