{
  "type": "Feature",
  "properties": {
    "iso:country":"BE",
    "sg:address":"Diestersteenweg 179",
    "sg:city":"Hasselt",
    "sg:orig_category":"Traitements param\u00e9dicaux",
    "sg:phone":"+32 11 87 30 69",
    "sg:postcode":"3510",
    "sg:province":"Limburg",
    "wof:name":"S. Bex",
    "wof:placetype":"venue"
},
  "geometry": {"coordinates":[5.2359399796,50.947719574],"type":"Point"}
}