{
  "type": "Feature",
  "properties": {
    "addr:full":"Rue Sainte-catherine 29 Brussel/bruxelles Bruxelles-Capitale 1000",
    "addr:housenumber":"29",
    "addr:postcode":"1000",
    "addr:street":"Rue Sainte-Catherine;/",
    "iso:country":"BE",
    "sg:address":"Rue Sainte-catherine 29",
    "sg:city":"Brussel/bruxelles",
    "sg:orig_category":"Artistes ind\u00e9pendants",
    "sg:phone":"+32 2 511 63 50",
    "sg:postcode":"1000",
    "sg:province":"Bruxelles-Capitale",
    "wof:name":"Germinal Casado",
    "wof:placetype":"venue"
},
  "geometry": {"coordinates":[4.3482089043,50.8500404358],"type":"Point"}
}