{
  "type": "Feature",
  "properties": {
    "addr:full":"Rue Les Fonds 164 Gesves Namur 5340",
    "addr:housenumber":"164",
    "addr:postcode":"5340",
    "addr:street":"Rue Les Fonds",
    "iso:country":"BE",
    "sg:address":"Rue Les Fonds 164",
    "sg:city":"Gesves",
    "sg:orig_category":"Elektrische installaties voor woningen",
    "sg:phone":"+32 83 67 79 86",
    "sg:postcode":"5340",
    "sg:province":"Namur",
    "wof:name":"Louis Delree",
    "wof:placetype":"venue"
},
  "geometry": {"coordinates":[5.0832819939,50.4158439636],"type":"Point"}
}