{
  "type": "Feature",
  "properties": {
    "addr:full":"Avenue Du Centenaire 27 Seraing Li\u00e8ge 4102",
    "addr:housenumber":"27",
    "addr:postcode":"4102",
    "addr:street":"Avenue Du Centenaire",
    "iso:country":"BE",
    "sg:address":"Avenue Du Centenaire 27",
    "sg:city":"Seraing",
    "sg:orig_category":"Enseignement maternel and primaire",
    "sg:phone":"+32 4 336 59 34",
    "sg:postcode":"4102",
    "sg:province":"Li\u00e8ge",
    "wof:name":"Ecole Prim. Communale",
    "wof:placetype":"venue"
},
  "geometry": {"coordinates":[5.5383777618,50.5944747925],"type":"Point"}
}