{
  "type": "Feature",
  "properties": {
    "addr:full":"Rue Gr\u00c9try 235 Luik (groot) Li\u00e8ge 4020",
    "addr:housenumber":"235",
    "addr:postcode":"4020",
    "addr:street":"Rue Gre\u0301Try;Groot Lie\u0300Ge",
    "iso:country":"BE",
    "sg:address":"Rue Gr\u00c9try 235",
    "sg:city":"Luik (groot)",
    "sg:orig_category":"Supermarkten",
    "sg:phone":"+32 4 341 36 99",
    "sg:postcode":"4020",
    "sg:province":"Li\u00e8ge",
    "wof:name":"Colruyt",
    "wof:placetype":"venue"
},
  "geometry": {"coordinates":[5.5864691734,50.6302566528],"type":"Point"}
}