{
  "type": "Feature",
  "properties": {
    "iso:country":"BE",
    "sg:address":"Kremerslei 6",
    "sg:city":"Duffel",
    "sg:classifiers":[
        {
            "category":"Personal",
            "subcategory":"Beauty Salon",
            "type":"Services"
        }
    ],
    "sg:phone":"+32 15 31 82 88",
    "sg:postcode":"2570",
    "sg:province":"Antwerpen",
    "sg:tags":[
        "de",
        "coiffure"
    ],
    "wof:name":"Coiffure Rita",
    "wof:placetype":"venue"
},
  "geometry": {"coordinates":[4.5015439987,51.1005744934],"type":"Point"}
}