{
  "type": "Feature",
  "properties": {
    "addr:full":"Ernest Claesstraat 6 Zele Oost-Vlaanderen 9240",
    "addr:housenumber":"6",
    "addr:postcode":"9240",
    "addr:street":"Ernest Claesstraat",
    "iso:country":"BE",
    "sg:address":"Ernest Claesstraat 6",
    "sg:city":"Zele",
    "sg:orig_category":"Woningbouw",
    "sg:phone":"+32 52 44 53 47",
    "sg:postcode":"9240",
    "sg:province":"Oost-Vlaanderen",
    "wof:name":"Geert De Wilde",
    "wof:placetype":"venue"
},
  "geometry": {"coordinates":[4.0365262032,51.0586853027],"type":"Point"}
}