{
  "type": "Feature",
  "properties": {
    "addr:full":"Hertogenlaan 45 Wezembeek-oppem/wezembeek-oppem Vlaams-Brabant 1970",
    "addr:housenumber":"45",
    "addr:postcode":"1970",
    "addr:street":"Hertogenlaan",
    "iso:country":"BE",
    "sg:address":"Hertogenlaan 45",
    "sg:city":"Wezembeek-oppem/wezembeek-oppem",
    "sg:orig_category":"Artsen and specialisten",
    "sg:phone":"+32 2 731 14 14",
    "sg:postcode":"1970",
    "sg:province":"Vlaams-Brabant",
    "wof:name":"Val\u00c9rie Vandresse",
    "wof:placetype":"venue"
},
  "geometry": {"coordinates":[4.4879150391,50.8357658386],"type":"Point"}
}