{
  "type": "Feature",
  "properties": {
    "addr:full":"Klapscheutstraat 80 Ternat Vlaams-Brabant 1741",
    "addr:housenumber":"80",
    "addr:postcode":"1741",
    "addr:street":"Klapscheutstraat",
    "iso:country":"BE",
    "sg:address":"Klapscheutstraat 80",
    "sg:city":"Ternat",
    "sg:classifiers":[
        {
            "category":"Food & Beverages",
            "subcategory":"Fruits & Vegetables",
            "type":"Retail Goods"
        }
    ],
    "sg:phone":"+32 2 582 60 14",
    "sg:postcode":"1741",
    "sg:province":"Vlaams-Brabant",
    "sg:tags":[
        "l\u00e9gumes"
    ],
    "wof:name":"Joseph Jans",
    "wof:placetype":"venue"
},
  "geometry": {"coordinates":[4.1546220779,50.8447608948],"type":"Point"}
}