{
  "type": "Feature",
  "properties": {
    "addr:full":"Oudenaartsesteenweg 26 Erpe-mere Oost-Vlaanderen 9420",
    "addr:housenumber":"26",
    "addr:postcode":"9420",
    "addr:street":"Oudenaartsesteenweg",
    "iso:country":"BE",
    "sg:address":"Oudenaartsesteenweg 26",
    "sg:city":"Erpe-mere",
    "sg:orig_category":"Agences d'exp\u00e9dition",
    "sg:phone":"+32 53 80 04 47",
    "sg:postcode":"9420",
    "sg:province":"Oost-Vlaanderen",
    "wof:name":"Berthouil E.",
    "wof:placetype":"venue"
},
  "geometry": {"coordinates":[3.9906520844,50.9410552979],"type":"Point"}
}