{
  "type": "Feature",
  "properties": {
    "iso:country":"BE",
    "sg:address":"Industrielaan 6",
    "sg:city":"Menen",
    "sg:classifiers":[
        {
            "category":"Freight",
            "type":"Transportation"
        }
    ],
    "sg:phone":"+32 56 22 59 40",
    "sg:postcode":"8930",
    "sg:province":"West-Vlaanderen",
    "sg:tags":[
        "-",
        "transport"
    ],
    "wof:name":"Best-bikes",
    "wof:placetype":"venue"
},
  "geometry": {"coordinates":[3.1051619053,50.7925109863],"type":"Point"}
}