{
  "type": "Feature",
  "properties": {
    "addr:full":"Loobeekstraat 21 Maasmechelen (vucht) Limburg 3630",
    "addr:housenumber":"21",
    "addr:postcode":"3630",
    "addr:street":"Loobeekstraat",
    "iso:country":"BE",
    "sg:address":"Loobeekstraat 21",
    "sg:city":"Maasmechelen (vucht)",
    "sg:classifiers":[
        {
            "category":"Building & Trades",
            "subcategory":"Plumbing",
            "type":"Services"
        }
    ],
    "sg:postcode":"3630",
    "sg:province":"Limburg",
    "sg:tags":[
        "repair",
        "mainten",
        "-",
        "central",
        "heating"
    ],
    "wof:name":"Janssen Harry",
    "wof:placetype":"venue"
},
  "geometry": {"coordinates":[5.6961350441,50.963848114],"type":"Point"}
}