{
  "type": "Feature",
  "properties": {
    "iso:country":"BE",
    "sg:address":"Rue De L'industrie 278",
    "sg:city":"Frameries",
    "sg:classifiers":[
        {
            "category":"Restaurant",
            "type":"Food & Drink"
        }
    ],
    "sg:phone":"+32 65 67 76 73",
    "sg:postcode":"7080",
    "sg:province":"Hainaut",
    "sg:tags":[
        "de",
        "organisation",
        "\u00e0",
        "fast",
        "catering",
        "emporter",
        "f\u00eates",
        "restaurants"
    ],
    "wof:name":"Assiette Au Beurre",
    "wof:placetype":"venue"
},
  "geometry": {"coordinates":[3.8875699043,50.4078826904],"type":"Point"}
}