{
  "type": "Feature",
  "properties": {
    "iso:country":"BE",
    "sg:address":"Rue Du Tocsin 6",
    "sg:city":"Bruxelles",
    "sg:classifiers":[
        {
            "category":"Education",
            "subcategory":"Special Training",
            "type":"Public Place"
        }
    ],
    "sg:phone":"+32 2 733 50 34",
    "sg:postcode":"1000",
    "sg:province":"Bruxelles-Capitale",
    "sg:tags":[
        "school",
        "sailing"
    ],
    "wof:name":"Du Vent Et Des Voiles Asbl",
    "wof:placetype":"venue"
},
  "geometry": {"coordinates":[4.3876190186,50.8477745056],"type":"Point"}
}