{
  "type": "Feature",
  "properties": {
    "addr:full":"Gemeenteplaats 18 Brecht Antwerpen 2960",
    "addr:housenumber":"18",
    "addr:postcode":"2960",
    "addr:street":"Gemeenteplaats",
    "iso:country":"BE",
    "sg:address":"Gemeenteplaats 18",
    "sg:city":"Brecht",
    "sg:orig_category":"Reclamebureaus",
    "sg:phone":"+32 3 313 66 70",
    "sg:postcode":"2960",
    "sg:province":"Antwerpen",
    "wof:name":"Zeno Texts",
    "wof:placetype":"venue"
},
  "geometry": {"coordinates":[4.6392288208,51.3483543396],"type":"Point"}
}