{
  "type": "Feature",
  "properties": {
    "addr:full":"Pachtgoedstraat 5 Sint-niklaas Oost-Vlaanderen 9100",
    "addr:housenumber":"5",
    "addr:postcode":"9100",
    "addr:street":"Pachtgoedstraat",
    "iso:country":"BE",
    "sg:address":"Pachtgoedstraat 5",
    "sg:city":"Sint-niklaas",
    "sg:classifiers":[
        {
            "category":"Airport",
            "subcategory":"International",
            "type":"Transportation"
        }
    ],
    "sg:phone":"+32 3 760 15 00",
    "sg:postcode":"9100",
    "sg:province":"Oost-Vlaanderen",
    "sg:tags":[
        "-",
        "transport"
    ],
    "wof:name":"Alkoko-transport Maes",
    "wof:placetype":"venue"
},
  "geometry": {"coordinates":[4.1893701553,51.1470603943],"type":"Point"}
}