{
  "type": "Feature",
  "properties": {
    "iso:country":"BE",
    "sg:address":"Singelstraat 90",
    "sg:city":"Ravels",
    "sg:orig_category":"Eleveurs and marchands de porcs. Eleveurs de bovins",
    "sg:phone":"+32 14 65 56 33",
    "sg:postcode":"2381",
    "sg:province":"Antwerpen",
    "wof:name":"Willemse",
    "wof:placetype":"venue"
},
  "geometry": {"coordinates":[4.9901571274,51.3961830139],"type":"Point"}
}