{
  "type": "Feature",
  "properties": {
    "iso:country":"BE",
    "sg:address":"Brugsestraat 107",
    "sg:city":"Harelbeke",
    "sg:orig_category":"Supermarch\u00e9s",
    "sg:phone":"+32 56 71 33 28",
    "sg:postcode":"8531",
    "sg:province":"West-Vlaanderen",
    "wof:name":"Huis Maria",
    "wof:placetype":"venue"
},
  "geometry": {"coordinates":[3.2843110561,50.881942749],"type":"Point"}
}