{
  "type": "Feature",
  "properties": {
    "iso:country":"BE",
    "sg:address":"Rue Beriot 213c",
    "sg:city":"Sirault",
    "sg:orig_category":"Bloemen and planten",
    "sg:phone":"+32 65 52 01 34",
    "sg:postcode":"7332",
    "sg:province":"Hainaut",
    "wof:name":"Fleurs Emotions",
    "wof:placetype":"venue"
},
  "geometry": {"coordinates":[3.7651979923,50.5150718689],"type":"Point"}
}