{
  "type": "Feature",
  "properties": {
    "addr:full":"Breulstraat 61ba Moorslede West-Vlaanderen 8890",
    "addr:housenumber":"61ba",
    "addr:postcode":"8890",
    "addr:street":"Breulstraat",
    "iso:country":"BE",
    "sg:address":"Breulstraat 61ba",
    "sg:city":"Moorslede",
    "sg:classifiers":[
        {
            "category":"Food & Beverages",
            "subcategory":"Fruits & Vegetables",
            "type":"Retail Goods"
        }
    ],
    "sg:phone":"+32 51 77 07 36",
    "sg:postcode":"8890",
    "sg:province":"West-Vlaanderen",
    "sg:tags":[
        "groenten"
    ],
    "wof:name":"Willy Vandevoorde",
    "wof:placetype":"venue"
},
  "geometry": {"coordinates":[3.0686159134,50.8901824951],"type":"Point"}
}