{
  "type": "Feature",
  "properties": {
    "iso:country":"BE",
    "sg:address":"Chauss\u00e9e De Bruxelles 562",
    "sg:city":"Waterloo",
    "sg:classifiers":[
        {
            "category":"Arena",
            "subcategory":"Sports Club",
            "type":"Entertainment"
        }
    ],
    "sg:phone":"+32 479 56 89 07",
    "sg:postcode":"1410",
    "sg:province":"Brabant Wallon",
    "wof:name":"Saint-barth Diving",
    "wof:placetype":"venue"
},
  "geometry": {"coordinates":[4.401966095,50.7004356384],"type":"Point"}
}