{
  "type": "Feature",
  "properties": {
    "addr:full":"Aarlenstraat 39-41 Brussel/bruxelles Bruxelles-Capitale 1000",
    "addr:postcode":"39-41;/ bruxelles;1000",
    "addr:street":"Aarlenstraat",
    "iso:country":"BE",
    "sg:address":"Aarlenstraat 39-41",
    "sg:city":"Brussel/bruxelles",
    "sg:orig_category":"Informaticaconsulenten Werk and personeelsselectie",
    "sg:phone":"+32 2 285 40 10",
    "sg:postcode":"1000",
    "sg:province":"Bruxelles-Capitale",
    "wof:name":"Eurocity",
    "wof:placetype":"venue"
},
  "geometry": {"coordinates":[4.373155117,50.840839386],"type":"Point"}
}