{
  "type": "Feature",
  "properties": {
    "iso:country":"BE",
    "sg:address":"Hagewindestraat 127",
    "sg:city":"Menen",
    "sg:classifiers":[
        {
            "category":"Real Estate",
            "subcategory":"Surveying",
            "type":"Services"
        }
    ],
    "sg:phone":"+32 56 51 23 31",
    "sg:postcode":"8930",
    "sg:province":"West-Vlaanderen",
    "sg:tags":[
        "lettering",
        "letter"
    ],
    "wof:name":"Gold'or Exclusive Products",
    "wof:placetype":"venue"
},
  "geometry": {"coordinates":[3.1282711029,50.8031463623],"type":"Point"}
}