{
  "type": "Feature",
  "properties": {
    "iso:country":"BE",
    "sg:address":"Monseigneur Stillemansstraat 15",
    "sg:city":"Sint-niklaas",
    "sg:classifiers":[
        {
            "category":"Health Services",
            "subcategory":"Dentist",
            "type":"Services"
        }
    ],
    "sg:phone":"+32 3 776 41 49",
    "sg:postcode":"9100",
    "sg:province":"Oost-Vlaanderen",
    "wof:name":"Philippe Ann",
    "wof:placetype":"venue"
},
  "geometry": {"coordinates":[4.1406421661,51.1613311768],"type":"Point"}
}