{
  "type": "Feature",
  "properties": {
    "iso:country":"BE",
    "sg:address":"Grand Rue 96",
    "sg:city":"Mons",
    "sg:orig_category":"Solariums",
    "sg:phone":"+32 65 31 13 08",
    "sg:postcode":"7000",
    "sg:province":"Hainaut",
    "wof:name":"Espace Soleil",
    "wof:placetype":"venue"
},
  "geometry": {"coordinates":[3.9492309093,50.4500312805],"type":"Point"}
}