{
  "type": "Feature",
  "properties": {
    "addr:full":"Chauss\u00c9e De Dinant 1082 Namur Namur 5100",
    "addr:postcode":"1082;5100",
    "addr:street":"Chausse\u0301E De Dinant",
    "iso:country":"BE",
    "sg:address":"Chauss\u00c9e De Dinant 1082",
    "sg:city":"Namur",
    "sg:orig_category":"Pain, p\u00e2tisseries and confiseries",
    "sg:phone":"+32 81 46 06 80",
    "sg:postcode":"5100",
    "sg:province":"Namur",
    "wof:name":"P\u00c2tisserie Beguin",
    "wof:placetype":"venue"
},
  "geometry": {"coordinates":[4.8790678978,50.4162101746],"type":"Point"}
}