{
  "type": "Feature",
  "properties": {
    "addr:full":"Tiensevest 158 Leuven Vlaams-Brabant 3000",
    "addr:housenumber":"158",
    "addr:postcode":"3000",
    "addr:street":"Tiensevest",
    "iso:country":"BE",
    "sg:address":"Tiensevest 158",
    "sg:city":"Leuven",
    "sg:classifiers":[
        {
            "category":"Health Services",
            "subcategory":"Doctor",
            "type":"Services"
        }
    ],
    "sg:phone":"+32 16 23 51 47",
    "sg:postcode":"3000",
    "sg:province":"Vlaams-Brabant",
    "sg:tags":[
        "medicinephysicians",
        "surgeon"
    ],
    "wof:name":"Brems A",
    "wof:placetype":"venue"
},
  "geometry": {"coordinates":[4.7145218849,50.8747901917],"type":"Point"}
}