{
  "type": "Feature",
  "properties": {
    "iso:country":"BE",
    "sg:address":"Geraardsbergsesteenweg 202",
    "sg:city":"Oosterzele",
    "sg:orig_category":"Epiceries",
    "sg:phone":"+32 9 362 54 67",
    "sg:postcode":"9860",
    "sg:province":"Oost-Vlaanderen",
    "wof:name":"Johan Van Bever",
    "wof:placetype":"venue"
},
  "geometry": {"coordinates":[3.8187439442,50.9445037842],"type":"Point"}
}