{
  "type": "Feature",
  "properties": {
    "addr:full":"Steenweg Op Mol 53 Turnhout Antwerpen 2300",
    "addr:housenumber":"53",
    "addr:postcode":"2300",
    "addr:street":"Steenweg Op Mol",
    "iso:country":"BE",
    "sg:address":"Steenweg Op Mol 53",
    "sg:city":"Turnhout",
    "sg:orig_category":"Diverse kredietdiensten",
    "sg:postcode":"2300",
    "sg:province":"Antwerpen",
    "wof:name":"Bancontact-mister Cash",
    "wof:placetype":"venue"
},
  "geometry": {"coordinates":[4.9408559799,51.321521759],"type":"Point"}
}