{
  "type": "Feature",
  "properties": {
    "addr:full":"Rue Du Pays De Li\u00c8ge 8 Blegny Li\u00e8ge 4671",
    "addr:housenumber":"8",
    "addr:postcode":"4671",
    "addr:street":"Rue Du Pays De Lie\u0300Ge",
    "iso:country":"BE",
    "sg:address":"Rue Du Pays De Li\u00c8ge 8",
    "sg:city":"Blegny",
    "sg:classifiers":[
        {
            "category":"Arena",
            "subcategory":"Sports Club",
            "type":"Entertainment"
        }
    ],
    "sg:phone":"+32 4 362 96 57",
    "sg:postcode":"4671",
    "sg:province":"Li\u00e8ge",
    "sg:tags":[
        "de"
    ],
    "wof:name":"Cercle Marcheurs Saive",
    "wof:placetype":"venue"
},
  "geometry": {"coordinates":[5.6820588112,50.6480712891],"type":"Point"}
}