{
  "type": "Feature",
  "properties": {
    "iso:country":"BE",
    "sg:address":"Jozef Reusenslei 146",
    "sg:city":"Borsbeek",
    "sg:orig_category":"Diverse bouwafwerking and reiniging Loodgieterij, verwarming and sanitaire installaties",
    "sg:phone":"+32 3 321 03 19",
    "sg:postcode":"2150",
    "sg:province":"Antwerpen",
    "wof:name":"Michel Bousard",
    "wof:placetype":"venue"
},
  "geometry": {"coordinates":[4.4900150299,51.1973953247],"type":"Point"}
}