{
  "type": "Feature",
  "properties": {
    "addr:full":"Huinegem 47 Asse Vlaams-Brabant 1730",
    "addr:housenumber":"47",
    "addr:postcode":"1730",
    "addr:street":"Huinegem",
    "iso:country":"BE",
    "sg:address":"Huinegem 47",
    "sg:city":"Asse",
    "sg:classifiers":[
        {
            "category":"Utilities",
            "subcategory":"Water",
            "type":"Services"
        }
    ],
    "sg:phone":"+32 2 454 12 11",
    "sg:postcode":"1730",
    "sg:province":"Vlaams-Brabant",
    "sg:tags":[
        "distribution"
    ],
    "wof:name":"T M V W",
    "wof:placetype":"venue"
},
  "geometry": {"coordinates":[4.2061338425,50.9138755798],"type":"Point"}
}