{
  "type": "Feature",
  "properties": {
    "iso:country":"BE",
    "sg:address":"Kiezelstraat 185",
    "sg:city":"Hasselt",
    "sg:classifiers":[
        {
            "category":"Arena",
            "subcategory":"Sports Club",
            "type":"Entertainment"
        }
    ],
    "sg:phone":"+32 11 23 35 48",
    "sg:postcode":"3500",
    "sg:province":"Limburg",
    "sg:tags":[
        "terrain",
        "hors",
        "de",
        "installation",
        "sportifs"
    ],
    "wof:name":"Godsheide V.v.",
    "wof:placetype":"venue"
},
  "geometry": {"coordinates":[5.3740749359,50.9294395447],"type":"Point"}
}