{
  "type": "Feature",
  "properties": {
    "iso:country":"BE",
    "sg:address":"Waalstraat 39",
    "sg:city":"Zulte",
    "sg:orig_category":"Epiceries",
    "sg:phone":"+32 9 388 63 32",
    "sg:postcode":"9870",
    "sg:province":"Oost-Vlaanderen",
    "wof:name":"Delhaize",
    "wof:placetype":"venue"
},
  "geometry": {"coordinates":[3.4491429329,50.921546936],"type":"Point"}
}