{
  "type": "Feature",
  "properties": {
    "addr:full":"Rue Prolong\u00c9e De Stalle 215 Drogenbos/drogenbos Vlaams-Brabant 1620",
    "addr:housenumber":"215",
    "addr:postcode":"1620",
    "addr:street":"Rue Prolonge\u0301E De Stalle",
    "iso:country":"BE",
    "sg:address":"Rue Prolong\u00c9e De Stalle 215",
    "sg:city":"Drogenbos/drogenbos",
    "sg:orig_category":"Ordinateurs and \u00e9quipement informatique",
    "sg:phone":"+32 2 377 14 68",
    "sg:postcode":"1620",
    "sg:province":"Vlaams-Brabant",
    "wof:name":"Bison Soft",
    "wof:placetype":"venue"
},
  "geometry": {"coordinates":[4.3107619286,50.7936935425],"type":"Point"}
}