{
  "type": "Feature",
  "properties": {
    "addr:full":"Parklaan 31 Sint-niklaas Oost-Vlaanderen 9100",
    "addr:housenumber":"31",
    "addr:postcode":"9100",
    "addr:street":"Parklaan",
    "iso:country":"BE",
    "sg:address":"Parklaan 31",
    "sg:city":"Sint-niklaas",
    "sg:classifiers":[
        {
            "category":"Personal",
            "subcategory":"Beauty Salon",
            "type":"Services"
        }
    ],
    "sg:phone":"+32 3 776 06 57",
    "sg:postcode":"9100",
    "sg:province":"Oost-Vlaanderen",
    "wof:name":"Verniers G",
    "wof:placetype":"venue"
},
  "geometry": {"coordinates":[4.144616127,51.161655426],"type":"Point"}
}