{
  "type": "Feature",
  "properties": {
    "addr:full":"Bakkersstraat 36 Blankenberge West-Vlaanderen 8370",
    "addr:housenumber":"36",
    "addr:postcode":"8370",
    "addr:street":"Bakkersstraat",
    "iso:country":"BE",
    "sg:address":"Bakkersstraat 36",
    "sg:city":"Blankenberge",
    "sg:orig_category":"Boucheries",
    "sg:phone":"+32 50 41 10 97",
    "sg:postcode":"8370",
    "sg:province":"West-Vlaanderen",
    "wof:name":"Beenhouwerij Dobbelaere",
    "wof:placetype":"venue"
},
  "geometry": {"coordinates":[3.1279900074,51.3148994446],"type":"Point"}
}