{
  "type": "Feature",
  "properties": {
    "iso:country":"BE",
    "sg:address":"Bellevaux 19",
    "sg:city":"Malmedy (bellevaux-lignueville)",
    "sg:classifiers":[
        {
            "category":"Retail",
            "subcategory":"Event Space",
            "type":"Services"
        }
    ],
    "sg:phone":"+32 80 57 01 95",
    "sg:postcode":"4960",
    "sg:province":"Li\u00e8ge",
    "sg:tags":[
        "rental",
        "-",
        "hall"
    ],
    "wof:name":"De Belva Asbl",
    "wof:placetype":"venue"
},
  "geometry": {"coordinates":[6.0104761124,50.3876342773],"type":"Point"}
}