{
  "type": "Feature",
  "properties": {
    "addr:full":"Quai De L'ourthe 11 Comblain-au-pont Li\u00e8ge 4170",
    "addr:housenumber":"11",
    "addr:postcode":"4170",
    "addr:street":"Quai De L'Ourthe",
    "iso:country":"BE",
    "sg:address":"Quai De L'ourthe 11",
    "sg:city":"Comblain-au-pont",
    "sg:classifiers":[
        {
            "category":"Bars & Pubs",
            "type":"Food & Drink"
        }
    ],
    "sg:phone":"+32 4 369 11 04",
    "sg:postcode":"4170",
    "sg:province":"Li\u00e8ge",
    "wof:name":"Belle Vue",
    "wof:placetype":"venue"
},
  "geometry": {"coordinates":[5.5777578354,50.4759788513],"type":"Point"}
}