{
  "type": "Feature",
  "properties": {
    "addr:full":"Lamperstraat 27 Kruibeke (bazel) Oost-Vlaanderen 9150",
    "addr:housenumber":"27",
    "addr:postcode":"9150",
    "addr:street":"Lamperstraat",
    "iso:country":"BE",
    "sg:address":"Lamperstraat 27",
    "sg:city":"Kruibeke (bazel)",
    "sg:classifiers":[
        {
            "category":"Personal",
            "subcategory":"Beauty Salon",
            "type":"Services"
        }
    ],
    "sg:phone":"+32 3 744 03 96",
    "sg:postcode":"9150",
    "sg:province":"Oost-Vlaanderen",
    "sg:tags":[
        "lady",
        "-",
        "hairdressing"
    ],
    "wof:name":"Intensive Hair",
    "wof:placetype":"venue"
},
  "geometry": {"coordinates":[4.2990098,51.1460571289],"type":"Point"}
}