{
  "type": "Feature",
  "properties": {
    "addr:full":"Maldingen 39 Burg-reuland Li\u00e8ge 4791",
    "addr:housenumber":"39",
    "addr:postcode":"4791",
    "addr:street":"Maldingen",
    "iso:country":"BE",
    "sg:address":"Maldingen 39",
    "sg:city":"Burg-reuland",
    "sg:orig_category":"Rundveehouders",
    "sg:phone":"+32 80 22 81 26",
    "sg:postcode":"4791",
    "sg:province":"Li\u00e8ge",
    "wof:name":"Raymond Peiffer",
    "wof:placetype":"venue"
},
  "geometry": {"coordinates":[6.0944099426,50.2024497986],"type":"Point"}
}