{
  "type": "Feature",
  "properties": {
    "addr:full":"Rue Hattain 7 Genappe (baisy-thy) Brabant Wallon 1470",
    "addr:housenumber":"7",
    "addr:postcode":"1470",
    "addr:street":"Rue Hattain",
    "iso:country":"BE",
    "sg:address":"Rue Hattain 7",
    "sg:city":"Genappe (baisy-thy)",
    "sg:classifiers":[
        {
            "category":"Home & Garden",
            "subcategory":"Building Materials",
            "type":"Retail Goods"
        }
    ],
    "sg:phone":"+32 67 78 05 20",
    "sg:postcode":"1470",
    "sg:province":"Brabant Wallon",
    "sg:tags":[
        "wall",
        "cupboard"
    ],
    "wof:name":"L.b. Bois Scrl",
    "wof:placetype":"venue"
},
  "geometry": {"coordinates":[4.4878740311,50.5976676941],"type":"Point"}
}