{
  "type": "Feature",
  "properties": {
    "addr:full":"Rue Des Chanterelles 111 Seraing Li\u00e8ge 4100",
    "addr:housenumber":"111",
    "addr:postcode":"4100",
    "addr:street":"Rue Des Chanterelles",
    "iso:country":"BE",
    "sg:address":"Rue Des Chanterelles 111",
    "sg:city":"Seraing",
    "sg:classifiers":[
        {
            "category":"Parking",
            "subcategory":"Garage",
            "type":"Transportation"
        }
    ],
    "sg:phone":"+32 4 336 09 94",
    "sg:postcode":"4100",
    "sg:province":"Li\u00e8ge",
    "sg:tags":[
        "truck",
        "-",
        "dump",
        "transport"
    ],
    "wof:name":"Wathieu S",
    "wof:placetype":"venue"
},
  "geometry": {"coordinates":[5.5184221268,50.5957183838],"type":"Point"}
}