{
  "type": "Feature",
  "properties": {
    "addr:full":"Rue De Nimy 6 Mons Hainaut 7000",
    "addr:housenumber":"6",
    "addr:postcode":"7000",
    "addr:street":"Rue De Nimy;Hainaut",
    "iso:country":"BE",
    "sg:address":"Rue De Nimy 6",
    "sg:city":"Mons",
    "sg:classifiers":[
        {
            "category":"Restaurant",
            "type":"Food & Drink"
        }
    ],
    "sg:phone":"+32 65 35 52 60",
    "sg:postcode":"7000",
    "sg:province":"Hainaut",
    "sg:tags":[
        "organisatie",
        "feesten",
        "van",
        "catering"
    ],
    "wof:name":"Alter Ego",
    "wof:placetype":"venue"
},
  "geometry": {"coordinates":[3.9533410072,50.4551887512],"type":"Point"}
}