{
  "type": "Feature",
  "properties": {
    "iso:country":"BE",
    "sg:address":"Budasesteenweg 49",
    "sg:city":"Brussel/bruxelles",
    "sg:orig_category":"Diverse opleidingen and onderwijs",
    "sg:phone":"+32 2 248 25 93",
    "sg:postcode":"1130",
    "sg:province":"Bruxelles-Capitale",
    "wof:name":"Inst.magasinage-transport",
    "wof:placetype":"venue"
},
  "geometry": {"coordinates":[4.4130039215,50.9065513611],"type":"Point"}
}