{
  "type": "Feature",
  "properties": {
    "iso:country":"BE",
    "sg:address":"Rue Auguste Ponson 33",
    "sg:city":"Liege",
    "sg:orig_category":"Boekhouders",
    "sg:phone":"+32 4 362 22 61",
    "sg:postcode":"4020",
    "sg:province":"Li\u00e8ge",
    "wof:name":"Antoine Marc",
    "wof:placetype":"venue"
},
  "geometry": {"coordinates":[5.5982370377,50.6355819702],"type":"Point"}
}