{
  "type": "Feature",
  "properties": {
    "addr:full":"Kapelstraat 258 Temse Oost-Vlaanderen 9140",
    "addr:housenumber":"258",
    "addr:postcode":"9140",
    "addr:street":"Kapelstraat",
    "iso:country":"BE",
    "sg:address":"Kapelstraat 258",
    "sg:city":"Temse",
    "sg:orig_category":"Woningbouw",
    "sg:phone":"+32 3 774 45 17",
    "sg:postcode":"9140",
    "sg:province":"Oost-Vlaanderen",
    "wof:name":"M. De Roeck",
    "wof:placetype":"venue"
},
  "geometry": {"coordinates":[4.2483592033,51.1286735535],"type":"Point"}
}