{
  "type": "Feature",
  "properties": {
    "iso:country":"BE",
    "sg:address":"Stationsplein 2-4",
    "sg:city":"Hasselt",
    "sg:classifiers":[
        {
            "category":"Bars & Pubs",
            "type":"Food & Drink"
        }
    ],
    "sg:phone":"+32 11 22 60 40",
    "sg:postcode":"3500",
    "sg:province":"Limburg",
    "wof:name":"Buffet Station",
    "wof:placetype":"venue"
},
  "geometry": {"coordinates":[5.3275098801,50.9309463501],"type":"Point"}
}