{
  "type": "Feature",
  "properties": {
    "iso:country":"BE",
    "sg:address":"Schotlandstraat 24",
    "sg:city":"Sint-gillis/saint-gilles",
    "sg:orig_category":"Advocaten and juridische adviseurs",
    "sg:phone":"+32 2 538 41 41",
    "sg:postcode":"1060",
    "sg:province":"Bruxelles-Capitale",
    "wof:name":"M.chr. De Luyck",
    "wof:placetype":"venue"
},
  "geometry": {"coordinates":[4.3526067734,50.8327560425],"type":"Point"}
}