{
  "type": "Feature",
  "properties": {
    "iso:country":"BE",
    "sg:address":"Ruelle Scaffart 0",
    "sg:city":"Soignies",
    "sg:orig_category":"Maatschappelijke dienstverlening",
    "sg:phone":"+32 67 33 36 42",
    "sg:postcode":"7060",
    "sg:province":"Hainaut",
    "wof:name":"Centre P.m.s.",
    "wof:placetype":"venue"
},
  "geometry": {"coordinates":[4.0695800781,50.5796585083],"type":"Point"}
}