{
  "type": "Feature",
  "properties": {
    "addr:full":"Ter Cuereplein 18 Bredene West-Vlaanderen 8450",
    "addr:housenumber":"18",
    "addr:postcode":"8450",
    "iso:country":"BE",
    "sg:address":"Ter Cuereplein 18",
    "sg:city":"Bredene",
    "sg:classifiers":[
        {
            "category":"Insurance",
            "subcategory":"Insurance Agent",
            "type":"Services"
        }
    ],
    "sg:phone":"+32 59 32 31 07",
    "sg:postcode":"8450",
    "sg:province":"West-Vlaanderen",
    "sg:tags":[
        "broker"
    ],
    "wof:name":"Gruwet L",
    "wof:placetype":"venue"
},
  "geometry": {"coordinates":[2.9585559368,51.2367858887],"type":"Point"}
}