{
  "type": "Feature",
  "properties": {
    "iso:country":"BE",
    "sg:address":"Paalstraat 10",
    "sg:city":"Schoten",
    "sg:classifiers":[
        {
            "category":"Food & Beverages",
            "subcategory":"Chocolate",
            "type":"Retail Goods"
        }
    ],
    "sg:phone":"+32 3 658 25 25",
    "sg:postcode":"2900",
    "sg:province":"Antwerpen",
    "sg:tags":[
        "confectionery",
        "-"
    ],
    "wof:name":"Confiserie Chris",
    "wof:placetype":"venue"
},
  "geometry": {"coordinates":[4.4991130829,51.2513465881],"type":"Point"}
}