{
  "type": "Feature",
  "properties": {
    "addr:full":"Pasteelsblokweg 9 Leuven Vlaams-Brabant 3010",
    "addr:housenumber":"9",
    "addr:postcode":"3010",
    "addr:street":"Pasteelsblokweg",
    "iso:country":"BE",
    "sg:address":"Pasteelsblokweg 9",
    "sg:city":"Leuven",
    "sg:orig_category":"Loodgieterij, verwarming and sanitaire installaties",
    "sg:phone":"+32 16 35 08 40",
    "sg:postcode":"3010",
    "sg:province":"Vlaams-Brabant",
    "wof:name":"Sanilux",
    "wof:placetype":"venue"
},
  "geometry": {"coordinates":[4.7304501534,50.889755249],"type":"Point"}
}