{
  "type": "Feature",
  "properties": {
    "iso:country":"BE",
    "sg:address":"Willemsplein",
    "sg:city":"Neerpelt",
    "sg:orig_category":"Activit\u00e9s d\u00b4action sociale sans h\u00e9bergement",
    "sg:phone":"+32 11 66 45 59",
    "sg:postcode":"3910",
    "sg:province":"Limburg",
    "wof:name":"Medisch Schooltoezicht",
    "wof:placetype":"venue"
},
  "geometry": {"coordinates":[5.4324188232,51.2294120789],"type":"Point"}
}