{
  "type": "Feature",
  "properties": {
    "iso:country":"BE",
    "sg:address":"Rue Saint-hubert 9",
    "sg:city":"Manage",
    "sg:orig_category":"Artsen and specialisten",
    "sg:phone":"+32 64 54 82 42",
    "sg:postcode":"7170",
    "sg:province":"Hainaut",
    "wof:name":"J. Leban",
    "wof:placetype":"venue"
},
  "geometry": {"coordinates":[4.2251191139,50.4951057434],"type":"Point"}
}