{
  "type": "Feature",
  "properties": {
    "iso:country":"BE",
    "sg:address":"Rue Louis S\u00e9culier 30",
    "sg:city":"Genappe (vieux-genappe)",
    "sg:classifiers":[
        {
            "category":"Arts & Performance",
            "subcategory":"Theater",
            "type":"Entertainment"
        }
    ],
    "sg:phone":"+32 67 79 03 09",
    "sg:postcode":"1472",
    "sg:province":"Brabant Wallon",
    "sg:tags":[
        "group",
        "theatre"
    ],
    "wof:name":"Tof Th\u00e9\u00e2tre Asbl",
    "wof:placetype":"venue"
},
  "geometry": {"coordinates":[4.4421300888,50.613155365],"type":"Point"}
}