{
  "type": "Feature",
  "properties": {
    "iso:country":"BE",
    "sg:address":"Houtmolenstraat 66",
    "sg:city":"Overpelt",
    "sg:classifiers":[
        {
            "category":"Real Estate",
            "subcategory":"Real Estate Services",
            "type":"Services"
        }
    ],
    "sg:phone":"+32 11 80 60 51",
    "sg:postcode":"3900",
    "sg:province":"Limburg",
    "wof:name":"Els Lenaerts (groep) Cvba",
    "wof:placetype":"venue"
},
  "geometry": {"coordinates":[5.4201779366,51.2185173035],"type":"Point"}
}