{
  "type": "Feature",
  "properties": {
    "iso:country":"BE",
    "sg:address":"Rue De Tournai 22",
    "sg:city":"Mouscron",
    "sg:classifiers":[
        {
            "category":"Professional",
            "subcategory":"Testing Lab",
            "type":"Services"
        }
    ],
    "sg:phone":"+32 56 33 09 98",
    "sg:postcode":"7700",
    "sg:province":"Hainaut",
    "sg:tags":[
        "chemist"
    ],
    "wof:name":"Vandeputte P",
    "wof:placetype":"venue"
},
  "geometry": {"coordinates":[3.2166099548,50.7436828613],"type":"Point"}
}