{
  "type": "Feature",
  "properties": {
    "iso:country":"BE",
    "sg:address":"Rue Des Bonniers 92",
    "sg:city":"Lobbes",
    "sg:classifiers":[
        {
            "category":"Real Estate",
            "subcategory":"Surveying",
            "type":"Services"
        }
    ],
    "sg:phone":"+32 71 59 26 81",
    "sg:postcode":"6540",
    "sg:province":"Hainaut",
    "sg:tags":[
        "surveyor",
        "land"
    ],
    "wof:name":"Cocciolone A",
    "wof:placetype":"venue"
},
  "geometry": {"coordinates":[4.2749028206,50.3684577942],"type":"Point"}
}