{
  "type": "Feature",
  "properties": {
    "addr:full":"Doornstraat 28 Brugge (sint-andries) West-Vlaanderen 8200",
    "addr:housenumber":"28",
    "addr:postcode":"8200",
    "addr:street":"Doornstraat",
    "iso:country":"BE",
    "sg:address":"Doornstraat 28",
    "sg:city":"Brugge (sint-andries)",
    "sg:classifiers":[
        {
            "category":"Shopping",
            "subcategory":"Bicycles & Sporting Goods",
            "type":"Retail Goods"
        }
    ],
    "sg:phone":"+32 50 67 77 72",
    "sg:postcode":"8200",
    "sg:province":"West-Vlaanderen",
    "sg:tags":[
        "-"
    ],
    "wof:name":"Seery Rijwielen",
    "wof:placetype":"venue"
},
  "geometry": {"coordinates":[3.1888821125,51.1926727295],"type":"Point"}
}