{
  "type": "Feature",
  "properties": {
    "iso:country":"BE",
    "sg:address":"Chauss\u00c9e De Waterloo 1474",
    "sg:city":"Ukkel/uccle",
    "sg:orig_category":"Goederenvervoer over de weg Huisvuilophaling and -verwerking",
    "sg:phone":"+32 2 374 37 36",
    "sg:postcode":"1180",
    "sg:province":"Bruxelles-Capitale",
    "wof:name":"Transports R. Figeys",
    "wof:placetype":"venue"
},
  "geometry": {"coordinates":[4.3784008026,50.7846260071],"type":"Point"}
}