{
  "type": "Feature",
  "properties": {
    "addr:full":"Rue Warichet 11 Nivelles Brabant Wallon 1401",
    "addr:housenumber":"11;1401",
    "addr:street":"Rue Warichet",
    "iso:country":"BE",
    "sg:address":"Rue Warichet 11",
    "sg:city":"Nivelles",
    "sg:orig_category":"Installation \u00e9lectrique industrielle",
    "sg:phone":"+32 67 22 08 08",
    "sg:postcode":"1401",
    "sg:province":"Brabant Wallon",
    "wof:name":"V.a.g. Security Systems",
    "wof:placetype":"venue"
},
  "geometry": {"coordinates":[4.3595108986,50.6090316772],"type":"Point"}
}