{
  "type": "Feature",
  "properties": {
    "addr:full":"Rue De La Cordonnerie 6 Tournai Hainaut 7500",
    "addr:housenumber":"6",
    "addr:postcode":"7500",
    "addr:street":"Rue De La Cordonnerie",
    "iso:country":"BE",
    "sg:address":"Rue De La Cordonnerie 6",
    "sg:city":"Tournai",
    "sg:classifiers":[
        {
            "category":"Shopping",
            "subcategory":"Luggage & Leather Goods",
            "type":"Retail Goods"
        }
    ],
    "sg:phone":"+32 69 22 86 21",
    "sg:postcode":"7500",
    "sg:province":"Hainaut",
    "sg:tags":[
        "-"
    ],
    "wof:name":"La Gondole",
    "wof:placetype":"venue"
},
  "geometry": {"coordinates":[3.3902111053,50.606716156],"type":"Point"}
}