{
  "type": "Feature",
  "properties": {
    "addr:full":"Boulevard Maurice Car\u00eame 8 Bruxelles (anderlecht) Bruxelles-Capitale 1070",
    "addr:housenumber":"8",
    "addr:postcode":"1070",
    "addr:street":"Boulevard Maurice Care\u0302Me",
    "iso:country":"BE",
    "sg:address":"Boulevard Maurice Car\u00eame 8",
    "sg:city":"Bruxelles (anderlecht)",
    "sg:classifiers":[
        {
            "category":"Professional",
            "subcategory":"Management & Consulting",
            "type":"Services"
        }
    ],
    "sg:phone":"+32 2 522 82 28",
    "sg:postcode":"1070",
    "sg:province":"Bruxelles-Capitale",
    "sg:tags":[
        "tax-consultants"
    ],
    "wof:name":"Hankard N",
    "wof:placetype":"venue"
},
  "geometry": {"coordinates":[4.284263134,50.8211364746],"type":"Point"}
}