{
  "type": "Feature",
  "properties": {
    "addr:full":"Oudestraat 51 Antwerpen (hoboken) Antwerpen 2660",
    "addr:housenumber":"51",
    "addr:postcode":"2660",
    "addr:street":"Oudestraat",
    "iso:country":"BE",
    "sg:address":"Oudestraat 51",
    "sg:city":"Antwerpen (hoboken)",
    "sg:classifiers":[
        {
            "category":"Arena",
            "subcategory":"Sports Club",
            "type":"Entertainment"
        }
    ],
    "sg:phone":"+32 3 827 10 26",
    "sg:postcode":"2660",
    "sg:province":"Antwerpen",
    "wof:name":"Sportzaal",
    "wof:placetype":"venue"
},
  "geometry": {"coordinates":[4.4202041626,51.2260055542],"type":"Point"}
}