{
  "type": "Feature",
  "properties": {
    "addr:full":"Keyartstraat 2 Bree (tongerlo) Limburg 3960",
    "addr:housenumber":"2",
    "addr:postcode":"3960",
    "addr:street":"Keyartstraat",
    "iso:country":"BE",
    "sg:address":"Keyartstraat 2",
    "sg:city":"Bree (tongerlo)",
    "sg:classifiers":[
        {
            "category":"Bars & Pubs",
            "type":"Food & Drink"
        }
    ],
    "sg:phone":"+32 89 86 13 27",
    "sg:postcode":"3960",
    "sg:province":"Limburg",
    "wof:name":"De Kipper Brouwerijcaf\u00e9",
    "wof:placetype":"venue"
},
  "geometry": {"coordinates":[5.6554279327,51.1242752075],"type":"Point"}
}