{
  "type": "Feature",
  "properties": {
    "iso:country":"BE",
    "sg:address":"Dekenijstraat 26",
    "sg:city":"Zomergem",
    "sg:classifiers":[
        {
            "category":"Professional",
            "subcategory":"Lawyer & Legal Services",
            "type":"Services"
        }
    ],
    "sg:phone":"+32 9 372 41 63",
    "sg:postcode":"9930",
    "sg:province":"Oost-Vlaanderen",
    "wof:name":"Georges Coralie",
    "wof:placetype":"venue"
},
  "geometry": {"coordinates":[3.5605359077,51.1161270142],"type":"Point"}
}