{
  "type": "Feature",
  "properties": {
    "iso:country":"BE",
    "sg:address":"Kellenstraat 2",
    "sg:city":"Tongeren",
    "sg:orig_category":"Woningbouw",
    "sg:phone":"+32 12 39 43 79",
    "sg:postcode":"3700",
    "sg:province":"Limburg",
    "wof:name":"Singh Amarjit",
    "wof:placetype":"venue"
},
  "geometry": {"coordinates":[5.4674801826,50.780960083],"type":"Point"}
}