{
  "type": "Feature",
  "properties": {
    "addr:full":"Leopoldlaan 55 Overpelt Limburg 3900",
    "addr:housenumber":"55",
    "addr:postcode":"3900",
    "addr:street":"Leopoldlaan",
    "iso:country":"BE",
    "sg:address":"Leopoldlaan 55",
    "sg:city":"Overpelt",
    "sg:classifiers":[
        {
            "category":"Building & Trades",
            "subcategory":"Plumbing",
            "type":"Services"
        }
    ],
    "sg:phone":"+32 11 64 45 46",
    "sg:postcode":"3900",
    "sg:province":"Limburg",
    "sg:tags":[
        "diver",
        "commerce",
        "gr",
        "pour",
        "equipement"
    ],
    "wof:name":"Food Express",
    "wof:placetype":"venue"
},
  "geometry": {"coordinates":[5.4267239571,51.219291687],"type":"Point"}
}