{
  "type": "Feature",
  "properties": {
    "addr:full":"Kapellenstr 1a Glabbeek Vlaams-Brabant 3380",
    "addr:housenumber":"1a",
    "addr:postcode":"3380",
    "addr:street":"Kapellenstr",
    "iso:country":"BE",
    "sg:address":"Kapellenstr 1a",
    "sg:city":"Glabbeek",
    "sg:classifiers":[
        {
            "category":"Health Services",
            "subcategory":"Doctor",
            "type":"Services"
        }
    ],
    "sg:phone":"+32 16 26 28 01",
    "sg:postcode":"3380",
    "sg:province":"Vlaams-Brabant",
    "sg:tags":[
        "psychotherapist",
        "psychoanalyst"
    ],
    "wof:name":"Gellens C",
    "wof:placetype":"venue"
},
  "geometry": {"coordinates":[4.9427499771,50.8808021545],"type":"Point"}
}