{
  "type": "Feature",
  "properties": {
    "addr:full":"Rijksweg 881 Elen Limburg 3650",
    "addr:housenumber":"881",
    "addr:postcode":"3650",
    "addr:street":"Rijksweg",
    "iso:country":"BE",
    "sg:address":"Rijksweg 881",
    "sg:city":"Elen",
    "sg:classifiers":[
        {
            "category":"Manufacturing",
            "subcategory":"Glass & Minerals",
            "type":"Manufacturing & Wholesale Goods"
        }
    ],
    "sg:phone":"+32 89 56 75 21",
    "sg:postcode":"3650",
    "sg:province":"Limburg",
    "sg:tags":[
        "building",
        "material"
    ],
    "wof:name":"Deckers Bouwmaterialen Nv",
    "wof:placetype":"venue"
},
  "geometry": {"coordinates":[5.751101017,51.0666618347],"type":"Point"}
}