{
  "type": "Feature",
  "properties": {
    "addr:full":"Oude Pastorijstraat 19 Hamont-achel Limburg 3930",
    "addr:housenumber":"19",
    "addr:postcode":"3930",
    "addr:street":"Oude Pastorijstraat",
    "iso:country":"BE",
    "sg:address":"Oude Pastorijstraat 19",
    "sg:city":"Hamont-achel",
    "sg:orig_category":"Woningbouw",
    "sg:phone":"+32 11 64 97 89",
    "sg:postcode":"3930",
    "sg:province":"Limburg",
    "wof:name":"Luc Van Den Dungen",
    "wof:placetype":"venue"
},
  "geometry": {"coordinates":[5.5450549126,51.2511863708],"type":"Point"}
}