{
  "type": "Feature",
  "properties": {
    "iso:country":"BE",
    "sg:address":"Rue De La Scierie 20",
    "sg:city":"Opont",
    "sg:classifiers":[
        {
            "category":"Home & Garden",
            "subcategory":"Furniture",
            "type":"Retail Goods"
        }
    ],
    "sg:phone":"+32 61 53 30 95",
    "sg:postcode":"6852",
    "sg:province":"Luxembourg",
    "sg:tags":[
        "wood"
    ],
    "wof:name":"Scierie Collard Sa",
    "wof:placetype":"venue"
},
  "geometry": {"coordinates":[5.1280241013,49.932975769],"type":"Point"}
}