{
  "type": "Feature",
  "properties": {
    "addr:full":"Hortweidenweg 46 Zonhoven Limburg 3520",
    "addr:housenumber":"46",
    "addr:postcode":"3520",
    "addr:street":"Hortweidenweg",
    "iso:country":"BE",
    "sg:address":"Hortweidenweg 46",
    "sg:city":"Zonhoven",
    "sg:classifiers":[
        {
            "category":"Personal",
            "subcategory":"Beauty Salon",
            "type":"Services"
        }
    ],
    "sg:phone":"+32 11 81 64 14",
    "sg:postcode":"3520",
    "sg:province":"Limburg",
    "sg:tags":[
        "lady",
        "-",
        "hairdressing"
    ],
    "wof:name":"Chris",
    "wof:placetype":"venue"
},
  "geometry": {"coordinates":[5.3572478294,51.0011558533],"type":"Point"}
}