{
  "type": "Feature",
  "properties": {
    "iso:country":"BE",
    "sg:address":"Acacialaan 14",
    "sg:city":"Herentals",
    "sg:classifiers":[
        {
            "category":"Building & Trades",
            "subcategory":"Electrical",
            "type":"Services"
        }
    ],
    "sg:phone":"+32 14 23 44 17",
    "sg:postcode":"2200",
    "sg:province":"Antwerpen",
    "sg:tags":[
        "industrial",
        "-",
        "electric",
        "contractor"
    ],
    "wof:name":"Tendo-electro Bvba",
    "wof:placetype":"venue"
},
  "geometry": {"coordinates":[4.8320698738,51.1637954712],"type":"Point"}
}