{
  "type": "Feature",
  "properties": {
    "iso:country":"BE",
    "sg:address":"Karel Keymolenstraat 73",
    "sg:city":"Lennik",
    "sg:orig_category":"Rev\u00eatements pour sols and murs. Peinture. Conception d'\u00e9talages and de showrooms",
    "sg:phone":"+32 2 532 46 22",
    "sg:postcode":"1750",
    "sg:province":"Vlaams-Brabant",
    "wof:name":"Ann Wispenninck",
    "wof:placetype":"venue"
},
  "geometry": {"coordinates":[4.1506662369,50.8086128235],"type":"Point"}
}