{
  "type": "Feature",
  "properties": {
    "iso:country":"BE",
    "sg:address":"Alsembergsesteenweg 973",
    "sg:city":"Ukkel (brussel)",
    "sg:classifiers":[
        {
            "category":"Restaurant",
            "type":"Food & Drink"
        }
    ],
    "sg:phone":"+32 2 332 37 81",
    "sg:postcode":"1180",
    "sg:province":"Bruxelles-Capitale",
    "wof:name":"Memphis",
    "wof:placetype":"venue"
},
  "geometry": {"coordinates":[4.335477829,50.7964935303],"type":"Point"}
}