{
  "type": "Feature",
  "properties": {
    "iso:country":"BE",
    "sg:address":"Rue De La Serpentine 8",
    "sg:city":"Ottignies-louvain-la-neuve",
    "sg:orig_category":"Instellingen voor mindervalide volwassenen",
    "sg:phone":"+32 10 45 17 82",
    "sg:postcode":"1348",
    "sg:province":"Brabant Wallon",
    "wof:name":"Home La Serpentine",
    "wof:placetype":"venue"
},
  "geometry": {"coordinates":[4.6159968376,50.6633110046],"type":"Point"}
}