{
  "type": "Feature",
  "properties": {
    "addr:full":"Place Du Parc 17 Malmedy/malmedy Li\u00e8ge 4960",
    "addr:housenumber":"17",
    "addr:postcode":"4960",
    "addr:street":"Place Du Parc",
    "iso:country":"BE",
    "sg:address":"Place Du Parc 17",
    "sg:city":"Malmedy/malmedy",
    "sg:classifiers":[
        {
            "category":"Cafe",
            "type":"Food & Drink"
        }
    ],
    "sg:phone":"+32 80 33 89 42",
    "sg:postcode":"4960",
    "sg:province":"Li\u00e8ge",
    "sg:tags":[
        "caf\u00e9s"
    ],
    "wof:name":"Caf\u00c9 Le Parc",
    "wof:placetype":"venue"
},
  "geometry": {"coordinates":[6.0551772118,50.37657547],"type":"Point"}
}