{
  "type": "Feature",
  "properties": {
    "addr:full":"Chemin Du Foubertsart 95 Lessines Hainaut 7860",
    "addr:housenumber":"95",
    "addr:postcode":"7860",
    "addr:street":"Chemin Du Foubertsart;Hainaut",
    "iso:country":"BE",
    "sg:address":"Chemin Du Foubertsart 95",
    "sg:city":"Lessines",
    "sg:orig_category":"Entretien and r\u00e9parations de voitures",
    "sg:phone":"+32 68 33 84 69",
    "sg:postcode":"7860",
    "sg:province":"Hainaut",
    "wof:name":"Paul Andre",
    "wof:placetype":"venue"
},
  "geometry": {"coordinates":[3.8400640488,50.7147331238],"type":"Point"}
}