{
  "type": "Feature",
  "properties": {
    "addr:full":"Bieststraat 21 Waregem West-Vlaanderen 8790",
    "addr:housenumber":"21",
    "addr:postcode":"8790",
    "addr:street":"Bieststraat",
    "iso:country":"BE",
    "sg:address":"Bieststraat 21",
    "sg:city":"Waregem",
    "sg:classifiers":[
        {
            "category":"Bakery",
            "type":"Food & Drink"
        }
    ],
    "sg:phone":"+32 56 60 59 10",
    "sg:postcode":"8790",
    "sg:province":"West-Vlaanderen",
    "sg:tags":[
        "confectioner",
        "baker"
    ],
    "wof:name":"Dalewyn C",
    "wof:placetype":"venue"
},
  "geometry": {"coordinates":[3.4229850769,50.8750648499],"type":"Point"}
}