{
  "type": "Feature",
  "properties": {
    "addr:full":"Avenue Joseph Merlot 198 Li\u00e8ge 1 (bressoux) Li\u00e8ge 4020",
    "addr:housenumber":"198;1",
    "addr:postcode":"4020",
    "addr:street":"Avenue Joseph Merlot",
    "iso:country":"BE",
    "sg:address":"Avenue Joseph Merlot 198",
    "sg:city":"Li\u00e8ge 1 (bressoux)",
    "sg:classifiers":[
        {
            "category":"Structure",
            "subcategory":"Office Building",
            "type":"Public Place"
        }
    ],
    "sg:phone":"+32 4 343 53 71",
    "sg:postcode":"4020",
    "sg:province":"Li\u00e8ge",
    "sg:tags":[
        "roofing",
        "slate"
    ],
    "wof:name":"T.i.s.",
    "wof:placetype":"venue"
},
  "geometry": {"coordinates":[5.6036481857,50.6349868774],"type":"Point"}
}