{
  "type": "Feature",
  "properties": {
    "iso:country":"BE",
    "sg:address":"Bredabaan 429",
    "sg:city":"Brasschaat",
    "sg:classifiers":[
        {
            "category":"Sports & Exercise",
            "subcategory":"Sports Center",
            "type":"Entertainment"
        }
    ],
    "sg:phone":"+32 3 651 75 34",
    "sg:postcode":"2930",
    "sg:province":"Antwerpen",
    "sg:tags":[
        "terrain",
        "hors",
        "de",
        "installation",
        "sportifs"
    ],
    "wof:name":"Verheyden Alfons",
    "wof:placetype":"venue"
},
  "geometry": {"coordinates":[4.4939231873,51.2916946411],"type":"Point"}
}