{
  "type": "Feature",
  "properties": {
    "addr:full":"Rue Du Nouveau Monde 174 Mouscron Hainaut 7700",
    "addr:housenumber":"174",
    "addr:postcode":"7700",
    "addr:street":"Rue Du Nouveau Monde",
    "iso:country":"BE",
    "sg:address":"Rue Du Nouveau Monde 174",
    "sg:city":"Mouscron",
    "sg:classifiers":[
        {
            "category":"Health Services",
            "subcategory":"Dentist",
            "type":"Services"
        }
    ],
    "sg:phone":"+32 56 34 44 08",
    "sg:postcode":"7700",
    "sg:province":"Hainaut",
    "wof:name":"Debruycker Hendrik",
    "wof:placetype":"venue"
},
  "geometry": {"coordinates":[3.20221591,50.7481269836],"type":"Point"}
}