{
  "type": "Feature",
  "properties": {
    "addr:full":"Hanegoor 6 Grobbendonk Antwerpen 2280",
    "addr:housenumber":"6",
    "addr:postcode":"2280",
    "addr:street":"Hanegoor",
    "iso:country":"BE",
    "sg:address":"Hanegoor 6",
    "sg:city":"Grobbendonk",
    "sg:orig_category":"Articles de jardin",
    "sg:phone":"+32 14 51 49 10",
    "sg:postcode":"2280",
    "sg:province":"Antwerpen",
    "wof:name":"Van Looy",
    "wof:placetype":"venue"
},
  "geometry": {"coordinates":[4.7474689484,51.1599731445],"type":"Point"}
}