{
  "type": "Feature",
  "properties": {
    "iso:country":"BE",
    "sg:address":"Dorpstraat 76",
    "sg:city":"Jabbeke",
    "sg:orig_category":"V\u00eatements pour b\u00e9b\u00e9s and enfants",
    "sg:phone":"+32 50 81 55 73",
    "sg:postcode":"8490",
    "sg:province":"West-Vlaanderen",
    "wof:name":"Huis Fidel",
    "wof:placetype":"venue"
},
  "geometry": {"coordinates":[3.0893518925,51.181930542],"type":"Point"}
}