{
  "type": "Feature",
  "properties": {
    "iso:country":"BE",
    "sg:address":"Rue Bois-d'avroy 43",
    "sg:city":"Li\u00c8ge",
    "sg:orig_category":"Experts-comptables",
    "sg:phone":"+32 4 252 74 37",
    "sg:postcode":"4000",
    "sg:province":"Li\u00e8ge",
    "wof:name":"A. Soultanbeieff",
    "wof:placetype":"venue"
},
  "geometry": {"coordinates":[5.5693330765,50.6402168274],"type":"Point"}
}