{
  "type": "Feature",
  "properties": {
    "iso:country":"BE",
    "sg:address":"Herentalsebaan 124",
    "sg:city":"Zoersel",
    "sg:orig_category":"Articles de camping and de sport. Maroquinerie Fab",
    "sg:phone":"+32 3 309 90 91",
    "sg:postcode":"2980",
    "sg:province":"Antwerpen",
    "wof:name":"Hippo-shop",
    "wof:placetype":"venue"
},
  "geometry": {"coordinates":[4.7191510201,51.2620887756],"type":"Point"}
}