{
  "type": "Feature",
  "properties": {
    "addr:full":"Churchilllaan 5 Schoten Antwerpen 2900",
    "addr:housenumber":"5",
    "addr:postcode":"2900",
    "addr:street":"Churchilllaan",
    "iso:country":"BE",
    "sg:address":"Churchilllaan 5",
    "sg:city":"Schoten",
    "sg:classifiers":[
        {
            "category":"Shopping",
            "subcategory":"Clothing, Apparel, & Fashions",
            "type":"Retail Goods"
        }
    ],
    "sg:phone":"+32 3 685 25 08",
    "sg:postcode":"2900",
    "sg:province":"Antwerpen",
    "sg:tags":[
        "-",
        "haberdashery"
    ],
    "wof:name":"Ida (huis)",
    "wof:placetype":"venue"
},
  "geometry": {"coordinates":[4.4974451065,51.2507324219],"type":"Point"}
}