{
  "type": "Feature",
  "properties": {
    "addr:full":"Ganzenstraat 68 Brugge West-Vlaanderen 8000",
    "addr:housenumber":"68",
    "addr:postcode":"8000",
    "addr:street":"Ganzenstraat",
    "iso:country":"BE",
    "sg:address":"Ganzenstraat 68",
    "sg:city":"Brugge",
    "sg:classifiers":[
        {
            "category":"Structure",
            "subcategory":"Building",
            "type":"Public Place"
        }
    ],
    "sg:phone":"+32 50 33 08 79",
    "sg:postcode":"8000",
    "sg:province":"West-Vlaanderen",
    "sg:tags":[
        "door"
    ],
    "wof:name":"Blomme Mass",
    "wof:placetype":"venue"
},
  "geometry": {"coordinates":[3.2359309196,51.2080535889],"type":"Point"}
}