{
  "type": "Feature",
  "properties": {
    "addr:full":"Leuvenselaan 293 Tienen Vlaams-Brabant 3300",
    "addr:housenumber":"293",
    "addr:postcode":"3300",
    "addr:street":"Leuvenselaan",
    "iso:country":"BE",
    "sg:address":"Leuvenselaan 293",
    "sg:city":"Tienen",
    "sg:orig_category":"Benzinestations and brandstoffen",
    "sg:phone":"+32 16 81 67 43",
    "sg:postcode":"3300",
    "sg:province":"Vlaams-Brabant",
    "wof:name":"Q8",
    "wof:placetype":"venue"
},
  "geometry": {"coordinates":[4.9171590805,50.8139343262],"type":"Point"}
}