{
  "type": "Feature",
  "properties": {
    "addr:full":"Place De L'universit\u00c9 Ottignies-louvain-la-neuve Brabant Wallon 1348",
    "addr:postcode":"1348",
    "addr:street":"Place De L'Universite \u0301",
    "iso:country":"BE",
    "sg:address":"Place De L'universit\u00c9",
    "sg:city":"Ottignies-louvain-la-neuve",
    "sg:orig_category":"Agences de voyages",
    "sg:phone":"+32 10 47 54 90",
    "sg:postcode":"1348",
    "sg:province":"Brabant Wallon",
    "wof:name":"Carlson Wagonlit Travel",
    "wof:placetype":"venue"
},
  "geometry": {"coordinates":[4.6154251099,50.6697273254],"type":"Point"}
}