{
  "type": "Feature",
  "properties": {
    "iso:country":"BE",
    "sg:address":"Hundelgemsesteenweg 766",
    "sg:city":"Merelbeke",
    "sg:classifiers":[
        {
            "category":"Professional",
            "subcategory":"Employment Agencies",
            "type":"Services"
        }
    ],
    "sg:phone":"+32 9 231 02 02",
    "sg:postcode":"9820",
    "sg:province":"Oost-Vlaanderen",
    "sg:tags":[
        "matrimonial"
    ],
    "wof:name":"Regi-amigo Club",
    "wof:placetype":"venue"
},
  "geometry": {"coordinates":[3.7460269928,50.9870033264],"type":"Point"}
}