{
  "type": "Feature",
  "properties": {
    "addr:full":"Croix-de-journal 2 Tenneville Luxembourg 6971",
    "addr:housenumber":"2",
    "addr:postcode":"6971",
    "addr:street":"Croix-De-Journal",
    "iso:country":"BE",
    "sg:address":"Croix-de-journal 2",
    "sg:city":"Tenneville",
    "sg:orig_category":"Entretien and r\u00e9parations de voitures",
    "sg:phone":"+32 84 45 58 46",
    "sg:postcode":"6971",
    "sg:province":"Luxembourg",
    "wof:name":"Robert Falla",
    "wof:placetype":"venue"
},
  "geometry": {"coordinates":[5.5050268173,50.1115913391],"type":"Point"}
}