{
  "type": "Feature",
  "properties": {
    "iso:country":"BE",
    "sg:address":"Rue Du Coll\u00c8ge 26",
    "sg:city":"Fleurus",
    "sg:orig_category":"Notaires",
    "sg:phone":"+32 71 81 48 92",
    "sg:postcode":"6220",
    "sg:province":"Hainaut",
    "wof:name":"M. Ghigny",
    "wof:placetype":"venue"
},
  "geometry": {"coordinates":[4.5505709648,50.4833946228],"type":"Point"}
}