{
  "type": "Feature",
  "properties": {
    "iso:country":"BE",
    "sg:address":"L\u00c9on Theodorstraat 16",
    "sg:city":"Jette",
    "sg:orig_category":"Industri\u00eble wasserijen and droogkuis",
    "sg:phone":"+32 2 425 67 19",
    "sg:postcode":"1090",
    "sg:province":"Bruxelles-Capitale",
    "wof:name":"Super Forum Shop",
    "wof:placetype":"venue"
},
  "geometry": {"coordinates":[4.3258118629,50.8737449646],"type":"Point"}
}