{
  "type": "Feature",
  "properties": {
    "addr:full":"Rue Emile Vandervelde 20 Pepinster Li\u00e8ge 4860",
    "addr:housenumber":"20",
    "addr:postcode":"4860",
    "addr:street":"Rue Emile Vandervelde",
    "iso:country":"BE",
    "sg:address":"Rue Emile Vandervelde 20",
    "sg:city":"Pepinster",
    "sg:orig_category":"M\u00e9decins and sp\u00e9cialistes",
    "sg:phone":"+32 87 46 23 23",
    "sg:postcode":"4860",
    "sg:province":"Li\u00e8ge",
    "wof:name":"Jean-louis Piette",
    "wof:placetype":"venue"
},
  "geometry": {"coordinates":[5.8215842247,50.5805206299],"type":"Point"}
}