{
  "type": "Feature",
  "properties": {
    "addr:full":"Zeelaan 39b201 De Panne West-Vlaanderen 8660",
    "addr:housenumber":"39b201",
    "addr:postcode":"8660",
    "addr:street":"Zeelaan",
    "iso:country":"BE",
    "sg:address":"Zeelaan 39b201",
    "sg:city":"De Panne",
    "sg:orig_category":"Antiek",
    "sg:phone":"+32 58 41 51 23",
    "sg:postcode":"8660",
    "sg:province":"West-Vlaanderen",
    "wof:name":"Yves Schuddinck",
    "wof:placetype":"venue"
},
  "geometry": {"coordinates":[2.5897409916,51.0972137451],"type":"Point"}
}