{
  "type": "Feature",
  "properties": {
    "addr:full":"Chaussee De Charleroi 731 Fleurus Hainaut 6220",
    "addr:housenumber":"731",
    "addr:postcode":"6220",
    "addr:street":"Chaussee De Charleroi",
    "iso:country":"BE",
    "sg:address":"Chaussee De Charleroi 731",
    "sg:city":"Fleurus",
    "sg:classifiers":[
        {
            "category":"Structure",
            "subcategory":"Bridge",
            "type":"Public Place"
        }
    ],
    "sg:phone":"+32 71 81 37 23",
    "sg:postcode":"6220",
    "sg:province":"Hainaut",
    "sg:tags":[
        "steel",
        "stair"
    ],
    "wof:name":"M\u00e9talforg\u00e9 S.p.r.l.",
    "wof:placetype":"venue"
},
  "geometry": {"coordinates":[4.5383300781,50.4679107666],"type":"Point"}
}