{
  "type": "Feature",
  "properties": {
    "addr:full":"Quai Des Ardennes 161 Li\u00c8ge Li\u00e8ge 4032",
    "addr:housenumber":"161",
    "addr:postcode":"4032",
    "addr:street":"Quai Des Ardennes",
    "iso:country":"BE",
    "sg:address":"Quai Des Ardennes 161",
    "sg:city":"Li\u00c8ge",
    "sg:orig_category":"Banken and kredietinstellingen",
    "sg:phone":"+32 4 367 30 16",
    "sg:postcode":"4032",
    "sg:province":"Li\u00e8ge",
    "wof:name":"Groupe Argenta",
    "wof:placetype":"venue"
},
  "geometry": {"coordinates":[5.619579792,50.6117401123],"type":"Point"}
}