{
  "type": "Feature",
  "properties": {
    "addr:full":"Rue Princesse Cl\u00e9mentine 11 Bruxelles Bruxelles-Capitale 1020",
    "addr:housenumber":"11",
    "addr:postcode":"1020",
    "addr:street":"Rue Princesse Cle\u0301Mentine",
    "iso:country":"BE",
    "sg:address":"Rue Princesse Cl\u00e9mentine 11",
    "sg:city":"Bruxelles",
    "sg:classifiers":[
        {
            "category":"Home & Garden",
            "subcategory":"Carpets & Floor Coverings",
            "type":"Retail Goods"
        }
    ],
    "sg:phone":"+32 2 478 71 34",
    "sg:postcode":"1020",
    "sg:province":"Bruxelles-Capitale",
    "sg:tags":[
        "industrial",
        "-"
    ],
    "wof:name":"S.e.b.m. Sprl",
    "wof:placetype":"venue"
},
  "geometry": {"coordinates":[4.3549399376,50.8766593933],"type":"Point"}
}