{
  "type": "Feature",
  "properties": {
    "iso:country":"BE",
    "sg:address":"Vijverstraat 27",
    "sg:city":"Oosterzele (moortsele)",
    "sg:classifiers":[
        {
            "category":"Food & Beverages",
            "subcategory":"Groceries & Convenience Stores",
            "type":"Retail Goods"
        }
    ],
    "sg:phone":"+32 9 362 82 13",
    "sg:postcode":"9860",
    "sg:province":"Oost-Vlaanderen",
    "sg:tags":[
        "grocer"
    ],
    "wof:name":"Sachem M",
    "wof:placetype":"venue"
},
  "geometry": {"coordinates":[3.7762908936,50.9600296021],"type":"Point"}
}