{
  "type": "Feature",
  "properties": {
    "addr:full":"Bleumerstraat 26 Maaseik Limburg 3680",
    "addr:housenumber":"26",
    "addr:postcode":"3680",
    "addr:street":"Bleumerstraat",
    "iso:country":"BE",
    "sg:address":"Bleumerstraat 26",
    "sg:city":"Maaseik",
    "sg:orig_category":"Plaatsen van vloer- and muurbekleding Schilders",
    "sg:phone":"+32 89 56 51 85",
    "sg:postcode":"3680",
    "sg:province":"Limburg",
    "wof:name":"Dubois",
    "wof:placetype":"venue"
},
  "geometry": {"coordinates":[5.7934288979,51.0945167542],"type":"Point"}
}