{
  "type": "Feature",
  "properties": {
    "iso:country":"BE",
    "sg:address":"Oudler 33ba",
    "sg:city":"Burg-reuland/burg-reuland",
    "sg:orig_category":"Apotheken",
    "sg:phone":"+32 80 32 96 40",
    "sg:postcode":"4791",
    "sg:province":"Li\u00e8ge",
    "wof:name":"Jean Van Den Bossche",
    "wof:placetype":"venue"
},
  "geometry": {"coordinates":[6.0944099426,50.2024497986],"type":"Point"}
}