{
  "type": "Feature",
  "properties": {
    "iso:country":"BE",
    "sg:address":"Hendrik Ghijselenstraat 16",
    "sg:city":"Lennik",
    "sg:orig_category":"Artsen and specialisten",
    "sg:phone":"+32 2 532 41 59",
    "sg:postcode":"1750",
    "sg:province":"Vlaams-Brabant",
    "wof:name":"P. Vandekerckhove",
    "wof:placetype":"venue"
},
  "geometry": {"coordinates":[4.1523180008,50.8058052063],"type":"Point"}
}