{
  "type": "Feature",
  "properties": {
    "iso:country":"BE",
    "sg:address":"Lindenstraat",
    "sg:city":"Zwijndrecht",
    "sg:orig_category":"Herstellingen and onderhoud van auto's",
    "sg:phone":"+32 3 254 10 20",
    "sg:postcode":"2070",
    "sg:province":"Antwerpen",
    "wof:name":"Paco's Clean Car",
    "wof:placetype":"venue"
},
  "geometry": {"coordinates":[4.3278198242,51.2098617554],"type":"Point"}
}