{
  "type": "Feature",
  "properties": {
    "iso:country":"BE",
    "sg:address":"Rue Du Village 146",
    "sg:city":"Liege",
    "sg:orig_category":"Traitement and rev\u00eatement des m\u00e9taux",
    "sg:phone":"+32 4 246 45 44",
    "sg:postcode":"4000",
    "sg:province":"Li\u00e8ge",
    "wof:name":"Aaa Meca-cycle",
    "wof:placetype":"venue"
},
  "geometry": {"coordinates":[5.5595870018,50.6744232178],"type":"Point"}
}