{
  "type": "Feature",
  "properties": {
    "addr:full":"Assesteenweg 9c Asse Vlaams-Brabant 1730",
    "addr:housenumber":"9c",
    "addr:postcode":"1730",
    "addr:street":"Assesteenweg",
    "iso:country":"BE",
    "sg:address":"Assesteenweg 9c",
    "sg:city":"Asse",
    "sg:orig_category":"Onderdelen and accessoires voor auto's",
    "sg:phone":"+32 2 452 24 15",
    "sg:postcode":"1730",
    "sg:province":"Vlaams-Brabant",
    "wof:name":"Radiateurs L'auto",
    "wof:placetype":"venue"
},
  "geometry": {"coordinates":[4.1594591141,50.9177627563],"type":"Point"}
}