{
  "type": "Feature",
  "properties": {
    "addr:full":"Aarschotsesteenweg 74 Tienen Vlaams-Brabant 3300",
    "addr:housenumber":"74",
    "addr:postcode":"3300",
    "addr:street":"Aarschotsesteenweg",
    "iso:country":"BE",
    "sg:address":"Aarschotsesteenweg 74",
    "sg:city":"Tienen",
    "sg:classifiers":[
        {
            "category":"Cemetery",
            "type":"Public Place"
        }
    ],
    "sg:phone":"+32 16 81 26 83",
    "sg:postcode":"3300",
    "sg:province":"Vlaams-Brabant",
    "sg:tags":[
        "crematory"
    ],
    "wof:name":"Winnen M Bvba",
    "wof:placetype":"venue"
},
  "geometry": {"coordinates":[4.9271411896,50.81457901],"type":"Point"}
}