{
  "type": "Feature",
  "properties": {
    "iso:country":"BE",
    "sg:address":"Stationsstraat 51-53",
    "sg:city":"Lommel",
    "sg:classifiers":[
        {
            "category":"Home & Garden",
            "subcategory":"Hardware",
            "type":"Retail Goods"
        }
    ],
    "sg:phone":"+32 11 54 40 36",
    "sg:postcode":"3920",
    "sg:province":"Limburg",
    "sg:tags":[
        "-"
    ],
    "wof:name":"Brans",
    "wof:placetype":"venue"
},
  "geometry": {"coordinates":[5.3143939972,51.2252960205],"type":"Point"}
}