{
  "type": "Feature",
  "properties": {
    "addr:full":"H. Consciencelaan 77 Waarschoot Oost-Vlaanderen 9950",
    "addr:housenumber":"77",
    "addr:postcode":"9950",
    "addr:street":"Consciencelaan",
    "iso:country":"BE",
    "sg:address":"H. Consciencelaan 77",
    "sg:city":"Waarschoot",
    "sg:orig_category":"Installation \u00e9lectrique r\u00e9sidentielle",
    "sg:phone":"+32 9 377 24 24",
    "sg:postcode":"9950",
    "sg:province":"Oost-Vlaanderen",
    "wof:name":"Reyniers",
    "wof:placetype":"venue"
},
  "geometry": {"coordinates":[3.6022560596,51.1422653198],"type":"Point"}
}