{
  "type": "Feature",
  "properties": {
    "addr:full":"Hertsvelde 46b1 Brugge West-Vlaanderen 8200",
    "addr:housenumber":"46b1",
    "addr:postcode":"8200",
    "addr:street":"Hertsvelde",
    "iso:country":"BE",
    "sg:address":"Hertsvelde 46b1",
    "sg:city":"Brugge",
    "sg:orig_category":"Sportclubs",
    "sg:phone":"+32 50 31 29 33",
    "sg:postcode":"8200",
    "sg:province":"West-Vlaanderen",
    "wof:name":"Zwemclub de Valkaart",
    "wof:placetype":"venue"
},
  "geometry": {"coordinates":[3.1970291138,51.205947876],"type":"Point"}
}