{
  "type": "Feature",
  "properties": {
    "iso:country":"BE",
    "sg:address":"Oostendestraat 16b5",
    "sg:city":"Torhout",
    "sg:orig_category":"Woningbouw",
    "sg:phone":"+32 50 21 13 31",
    "sg:postcode":"8820",
    "sg:province":"West-Vlaanderen",
    "wof:name":"P. Wydooghe",
    "wof:placetype":"venue"
},
  "geometry": {"coordinates":[3.099850893,51.0655250549],"type":"Point"}
}