{
  "type": "Feature",
  "properties": {
    "addr:full":"La Vaulx Richard 6bd Stavelot Li\u00e8ge 4970",
    "addr:housenumber":"6bd",
    "addr:postcode":"4970",
    "addr:street":"La Vaulx Richard",
    "iso:country":"BE",
    "sg:address":"La Vaulx Richard 6bd",
    "sg:city":"Stavelot",
    "sg:orig_category":"Woningbouw",
    "sg:phone":"+32 80 86 30 69",
    "sg:postcode":"4970",
    "sg:province":"Li\u00e8ge",
    "wof:name":"Daniel Antoine",
    "wof:placetype":"venue"
},
  "geometry": {"coordinates":[5.9533829689,50.3878326416],"type":"Point"}
}