{
  "type": "Feature",
  "properties": {
    "addr:full":"Tiensevest 41 Leuven Vlaams-Brabant 3000",
    "addr:housenumber":"41",
    "addr:postcode":"3000",
    "addr:street":"Tiensevest",
    "iso:country":"BE",
    "sg:address":"Tiensevest 41",
    "sg:city":"Leuven",
    "sg:classifiers":[
        {
            "category":"Health Services",
            "subcategory":"Doctor",
            "type":"Services"
        }
    ],
    "sg:phone":"+32 16 58 59 58",
    "sg:postcode":"3000",
    "sg:province":"Vlaams-Brabant",
    "sg:tags":[
        "medicinephysicians",
        "surgeon"
    ],
    "wof:name":"De Maerteleire Wim",
    "wof:placetype":"venue"
},
  "geometry": {"coordinates":[4.7041082382,50.8777313232],"type":"Point"}
}