{
  "type": "Feature",
  "properties": {
    "iso:country":"BE",
    "sg:address":"Mergelbeek 13",
    "sg:city":"Hamme",
    "sg:classifiers":[
        {
            "category":"Arena",
            "subcategory":"Sports Club",
            "type":"Entertainment"
        }
    ],
    "sg:phone":"+32 52 47 76 72",
    "sg:postcode":"9220",
    "sg:province":"Oost-Vlaanderen",
    "sg:tags":[
        "de"
    ],
    "wof:name":"B.b.c.onderons Grembergen",
    "wof:placetype":"venue"
},
  "geometry": {"coordinates":[4.1253290176,51.0884132385],"type":"Point"}
}