{
  "type": "Feature",
  "properties": {
    "iso:country":"BE",
    "sg:address":"Galglaan 107",
    "sg:city":"Gent",
    "sg:classifiers":[
        {
            "category":"Personal",
            "subcategory":"Psychics & Astrologers",
            "type":"Services"
        }
    ],
    "sg:phone":"+32 9 245 21 25",
    "sg:postcode":"9000",
    "sg:province":"Oost-Vlaanderen",
    "sg:tags":[
        "astrology"
    ],
    "wof:name":"Wallaert D",
    "wof:placetype":"venue"
},
  "geometry": {"coordinates":[3.7207009792,51.02602005],"type":"Point"}
}