{
  "type": "Feature",
  "properties": {
    "addr:full":"Ichtegemstraat 80 Koekelare West-Vlaanderen 8680",
    "addr:housenumber":"80",
    "addr:postcode":"8680",
    "addr:street":"Ichtegemstraat",
    "iso:country":"BE",
    "sg:address":"Ichtegemstraat 80",
    "sg:city":"Koekelare",
    "sg:classifiers":[
        {
            "category":"Animal Shelter",
            "type":"Public Place"
        }
    ],
    "sg:phone":"+32 51 58 83 56",
    "sg:postcode":"8680",
    "sg:province":"West-Vlaanderen",
    "sg:tags":[
        "feedstuff",
        "raw",
        "material"
    ],
    "wof:name":"A. Plaisier",
    "wof:placetype":"venue"
},
  "geometry": {"coordinates":[2.9871730804,51.0898666382],"type":"Point"}
}