{
  "type": "Feature",
  "properties": {
    "iso:country":"BE",
    "sg:address":"Rue Joseph Garnier 1a",
    "sg:city":"Houyet (custinne)",
    "sg:classifiers":[
        {
            "category":"Communications",
            "type":"Services"
        }
    ],
    "sg:phone":"+32 82 66 70 24",
    "sg:postcode":"5562",
    "sg:province":"Namur",
    "sg:tags":[
        "translator"
    ],
    "wof:name":"Istas D",
    "wof:placetype":"venue"
},
  "geometry": {"coordinates":[5.0522198677,50.2120056152],"type":"Point"}
}