{
  "type": "Feature",
  "properties": {
    "iso:country":"BE",
    "sg:address":"Meensesteenweg 168",
    "sg:city":"Kortrijk",
    "sg:orig_category":"Installation \u00e9lectrique r\u00e9sidentielle. Plomberie, chauffage and installations sanitaires",
    "sg:phone":"+32 56 35 60 45",
    "sg:postcode":"8501",
    "sg:province":"West-Vlaanderen",
    "wof:name":"Fa. Beheydt",
    "wof:placetype":"venue"
},
  "geometry": {"coordinates":[3.2369968891,50.8259735107],"type":"Point"}
}