{
  "type": "Feature",
  "properties": {
    "iso:country":"BE",
    "sg:address":"Rue Neuve 84",
    "sg:city":"Pepinster",
    "sg:orig_category":"Jeux de hasard",
    "sg:phone":"+32 87 46 93 04",
    "sg:postcode":"4860",
    "sg:province":"Li\u00e8ge",
    "wof:name":"Tierc\u00c9 Franco Belge",
    "wof:placetype":"venue"
},
  "geometry": {"coordinates":[5.8036727905,50.5661888123],"type":"Point"}
}