{
  "type": "Feature",
  "properties": {
    "addr:full":"Vlaanderenstraat 70 Gent Oost-Vlaanderen 9000",
    "addr:housenumber":"70",
    "addr:postcode":"9000",
    "addr:street":"Vlaanderenstraat;Oost-Vlaanderen",
    "iso:country":"BE",
    "sg:address":"Vlaanderenstraat 70",
    "sg:city":"Gent",
    "sg:orig_category":"Agences d\u00b4interim and personnel temporaire",
    "sg:phone":"+32 9 269 83 83",
    "sg:postcode":"9000",
    "sg:province":"Oost-Vlaanderen",
    "wof:name":"Adecco",
    "wof:placetype":"venue"
},
  "geometry": {"coordinates":[3.7300810814,51.0505027771],"type":"Point"}
}