{
  "type": "Feature",
  "properties": {
    "addr:full":"Dorp 22 Herselt Antwerpen 2230",
    "addr:housenumber":"22",
    "addr:postcode":"2230",
    "addr:street":"Dorp",
    "iso:country":"BE",
    "sg:address":"Dorp 22",
    "sg:city":"Herselt",
    "sg:classifiers":[
        {
            "category":"Insurance",
            "subcategory":"Insurance Agent",
            "type":"Services"
        }
    ],
    "sg:phone":"+32 14 54 31 87",
    "sg:postcode":"2230",
    "sg:province":"Antwerpen",
    "sg:tags":[
        "verzekeringsmakelaars",
        "expert"
    ],
    "wof:name":"Pauwels & Co",
    "wof:placetype":"venue"
},
  "geometry": {"coordinates":[4.8798780441,51.05210495],"type":"Point"}
}