{
  "type": "Feature",
  "properties": {
    "addr:full":"Gravin De Merodestraat 5 Westerlo Antwerpen 2260",
    "addr:housenumber":"5",
    "addr:postcode":"2260",
    "addr:street":"Gravin De Merodestraat",
    "iso:country":"BE",
    "sg:address":"Gravin De Merodestraat 5",
    "sg:city":"Westerlo",
    "sg:classifiers":[
        {
            "category":"Bars & Pubs",
            "type":"Food & Drink"
        }
    ],
    "sg:phone":"+32 16 69 80 59",
    "sg:postcode":"2260",
    "sg:province":"Antwerpen",
    "wof:name":"De Welkom",
    "wof:placetype":"venue"
},
  "geometry": {"coordinates":[4.8366241455,51.0866470337],"type":"Point"}
}