{
  "type": "Feature",
  "properties": {
    "iso:country":"BE",
    "sg:address":"Daniel Dehaenelaan 2a",
    "sg:city":"Veurne",
    "sg:classifiers":[
        {
            "category":"Government",
            "subcategory":"Fire Station",
            "type":"Public Place"
        }
    ],
    "sg:phone":"+32 58 28 72 72",
    "sg:postcode":"8630",
    "sg:province":"West-Vlaanderen",
    "sg:tags":[
        "packard",
        "nec",
        "bell"
    ],
    "wof:name":"Bruneel Elektro",
    "wof:placetype":"venue"
},
  "geometry": {"coordinates":[2.6584470272,51.0735321045],"type":"Point"}
}