{
  "type": "Feature",
  "properties": {
    "addr:full":"Rue Des D\u00c9port\u00c9s 1 Brugelette Hainaut 7940",
    "addr:housenumber":"1",
    "addr:postcode":"7940",
    "addr:street":"Rue Des De\u0301Porte\u0301S;Hainaut",
    "iso:country":"BE",
    "sg:address":"Rue Des D\u00c9port\u00c9s 1",
    "sg:city":"Brugelette",
    "sg:orig_category":"Overheidsdiensten",
    "sg:phone":"+32 68 45 73 25",
    "sg:postcode":"7940",
    "sg:province":"Hainaut",
    "wof:name":"C.p.a.s.",
    "wof:placetype":"venue"
},
  "geometry": {"coordinates":[3.8517549038,50.5953407288],"type":"Point"}
}