{
  "type": "Feature",
  "properties": {
    "iso:country":"BE",
    "sg:address":"Warandestraat 19",
    "sg:city":"Lovendegem",
    "sg:classifiers":[
        {
            "category":"Military Area",
            "subcategory":"Air Force Base",
            "type":"Public Place"
        }
    ],
    "sg:phone":"+32 9 372 89 32",
    "sg:postcode":"9920",
    "sg:province":"Oost-Vlaanderen",
    "sg:tags":[
        "water",
        "treatment"
    ],
    "wof:name":"Alguma Bvba",
    "wof:placetype":"venue"
},
  "geometry": {"coordinates":[3.6070380211,51.0992851257],"type":"Point"}
}