{
  "type": "Feature",
  "properties": {
    "iso:country":"BE",
    "sg:address":"Langerodestraat 38",
    "sg:city":"Huldenberg (neerijse)",
    "sg:classifiers":[
        {
            "category":"Professional",
            "type":"Services"
        }
    ],
    "sg:phone":"+32 16 47 17 13",
    "sg:postcode":"3040",
    "sg:province":"Vlaams-Brabant",
    "sg:tags":[
        "entertainer"
    ],
    "wof:name":"Vanuytsel Z",
    "wof:placetype":"venue"
},
  "geometry": {"coordinates":[4.6319007874,50.8220405579],"type":"Point"}
}