{
  "type": "Feature",
  "properties": {
    "iso:country":"BE",
    "sg:address":"Boondaalse Steenweg 518",
    "sg:city":"Elsene/ixelles",
    "sg:classifiers":[
        {
            "category":"Cafe",
            "type":"Food & Drink"
        }
    ],
    "sg:phone":"+32 2 644 32 90",
    "sg:postcode":"1050",
    "sg:province":"Bruxelles-Capitale",
    "sg:tags":[
        "caf\u00e9s"
    ],
    "wof:name":"Caf\u00c9 Guet-a-pinte",
    "wof:placetype":"venue"
},
  "geometry": {"coordinates":[4.3913240433,50.8124198914],"type":"Point"}
}