{
  "type": "Feature",
  "properties": {
    "iso:country":"BE",
    "sg:address":"Weg Naar Zwartberg 127",
    "sg:city":"Houthalen-helchteren",
    "sg:orig_category":"Electrom\u00e9nager, t\u00e9l\u00e9visions and radios. R\u00e9parations d'appareils \u00e9lectrom\u00e9nagers",
    "sg:phone":"+32 89 38 65 72",
    "sg:postcode":"3530",
    "sg:province":"Limburg",
    "wof:name":"Radtel Electro",
    "wof:placetype":"venue"
},
  "geometry": {"coordinates":[5.4695048332,51.0217094421],"type":"Point"}
}