{
  "type": "Feature",
  "properties": {
    "addr:full":"Place De La Wallonie 9 Fontaine-l'eveque Hainaut 6140",
    "addr:housenumber":"9",
    "addr:postcode":"6140",
    "addr:street":"Place De La Wallonie;Hainaut",
    "iso:country":"BE",
    "sg:address":"Place De La Wallonie 9",
    "sg:city":"Fontaine-l'eveque",
    "sg:classifiers":[
        {
            "category":"Cafe",
            "type":"Food & Drink"
        }
    ],
    "sg:phone":"+32 71 52 18 45",
    "sg:postcode":"6140",
    "sg:province":"Hainaut",
    "sg:tags":[
        "caf\u00e9s"
    ],
    "wof:name":"Caf\u00c9 Bellino Ii",
    "wof:placetype":"venue"
},
  "geometry": {"coordinates":[4.3243870735,50.4106674194],"type":"Point"}
}