{
  "type": "Feature",
  "properties": {
    "iso:country":"BE",
    "sg:address":"Avenue De Stassart 3",
    "sg:city":"Namur",
    "sg:classifiers":[
        {
            "category":"Health Services",
            "subcategory":"Dentist",
            "type":"Services"
        }
    ],
    "sg:phone":"+32 81 74 64 94",
    "sg:postcode":"5000",
    "sg:province":"Namur",
    "wof:name":"Servais Isabelle",
    "wof:placetype":"venue"
},
  "geometry": {"coordinates":[4.8552999496,50.4670410156],"type":"Point"}
}