{
  "type": "Feature",
  "properties": {
    "addr:full":"Heldenlaan 65 Zottegem Oost-Vlaanderen 9620",
    "addr:housenumber":"65",
    "addr:postcode":"9620",
    "addr:street":"Heldenlaan",
    "iso:country":"BE",
    "sg:address":"Heldenlaan 65",
    "sg:city":"Zottegem",
    "sg:classifiers":[
        {
            "category":"Shopping",
            "subcategory":"Clothing, Apparel, & Fashions",
            "type":"Retail Goods"
        }
    ],
    "sg:phone":"+32 9 361 82 00",
    "sg:postcode":"9620",
    "sg:province":"Oost-Vlaanderen",
    "sg:tags":[
        "underwear",
        "lingerie",
        "-"
    ],
    "wof:name":"Nancy",
    "wof:placetype":"venue"
},
  "geometry": {"coordinates":[3.8101398945,50.8716392517],"type":"Point"}
}