{
  "type": "Feature",
  "properties": {
    "addr:full":"Rue Du Bourdon Saint-jacques 4 Tournai Hainaut 7500",
    "addr:housenumber":"4",
    "addr:postcode":"7500",
    "addr:street":"Rue Du Bourdon Saint-Jacques",
    "iso:country":"BE",
    "sg:address":"Rue Du Bourdon Saint-jacques 4",
    "sg:city":"Tournai",
    "sg:orig_category":"Newspapers, magazines, periodicals - Publishers",
    "sg:phone":"+32 69 22 10 93",
    "sg:postcode":"7500",
    "sg:province":"Hainaut",
    "wof:name":"Derni\u00e8re Heure-les Sports (la)",
    "wof:placetype":"venue"
},
  "geometry": {"coordinates":[3.386275053,50.6086616516],"type":"Point"}
}