{
  "type": "Feature",
  "properties": {
    "iso:country":"BE",
    "sg:address":"Landhuisjesstraat 72",
    "sg:city":"Ukkel/uccle",
    "sg:orig_category":"Apotheken",
    "sg:phone":"+32 2 343 27 06",
    "sg:postcode":"1180",
    "sg:province":"Bruxelles-Capitale",
    "wof:name":"Pharmacie Retif",
    "wof:placetype":"venue"
},
  "geometry": {"coordinates":[4.3420300484,50.8117446899],"type":"Point"}
}