{
  "type": "Feature",
  "properties": {
    "addr:full":"Schuttershofstraat 47 Antwerpen Antwerpen 2000",
    "addr:housenumber":"47",
    "addr:postcode":"2000",
    "addr:street":"Schuttershofstraat",
    "iso:country":"BE",
    "sg:address":"Schuttershofstraat 47",
    "sg:city":"Antwerpen",
    "sg:orig_category":"Quincailleries",
    "sg:phone":"+32 3 226 75 86",
    "sg:postcode":"2000",
    "sg:province":"Antwerpen",
    "wof:name":"Waterl'eau",
    "wof:placetype":"venue"
},
  "geometry": {"coordinates":[4.4083099365,51.2166252136],"type":"Point"}
}