{
  "type": "Feature",
  "properties": {
    "addr:full":"Mechelse Steenweg 210a Antwerpen Antwerpen 2018",
    "addr:housenumber":"210a",
    "addr:postcode":"2018",
    "addr:street":"Steenweg",
    "iso:country":"BE",
    "sg:address":"Mechelse Steenweg 210a",
    "sg:city":"Antwerpen",
    "sg:classifiers":[
        {
            "category":"Professional",
            "subcategory":"Lawyer & Legal Services",
            "type":"Services"
        }
    ],
    "sg:phone":"+32 3 238 58 55",
    "sg:postcode":"2018",
    "sg:province":"Antwerpen",
    "wof:name":"Dyck J",
    "wof:placetype":"venue"
},
  "geometry": {"coordinates":[4.4114441872,51.2030181885],"type":"Point"}
}