{
  "type": "Feature",
  "properties": {
    "addr:full":"Rue Des Fran\u00c7ais 273 Ans Li\u00e8ge 4430",
    "addr:housenumber":"273",
    "addr:postcode":"4430",
    "addr:street":"Rue Des Franc\u0327Ais",
    "iso:country":"BE",
    "sg:address":"Rue Des Fran\u00c7ais 273",
    "sg:city":"Ans",
    "sg:classifiers":[
        {
            "category":"Shopping",
            "subcategory":"Bicycles & Sporting Goods",
            "type":"Retail Goods"
        }
    ],
    "sg:phone":"+32 4 247 19 78",
    "sg:postcode":"4430",
    "sg:province":"Li\u00e8ge",
    "sg:tags":[
        "article",
        "de",
        "sport",
        "camping"
    ],
    "wof:name":"Ippon Sport",
    "wof:placetype":"venue"
},
  "geometry": {"coordinates":[5.5364618301,50.6641082764],"type":"Point"}
}