{
  "type": "Feature",
  "properties": {
    "addr:full":"Avenue Louis Berlaimont 5 Bruxelles (auderghem) Bruxelles-Capitale 1160",
    "addr:housenumber":"5",
    "addr:postcode":"1160",
    "addr:street":"Avenue Louis Berlaimont",
    "iso:country":"BE",
    "sg:address":"Avenue Louis Berlaimont 5",
    "sg:city":"Bruxelles (auderghem)",
    "sg:classifiers":[
        {
            "category":"Health Services",
            "subcategory":"Nursing And Care Facility",
            "type":"Services"
        }
    ],
    "sg:phone":"+32 2 672 62 64",
    "sg:postcode":"1160",
    "sg:province":"Bruxelles-Capitale",
    "sg:tags":[
        "home",
        "rest"
    ],
    "wof:name":"Berlaimont (r\u00e9sidence)",
    "wof:placetype":"venue"
},
  "geometry": {"coordinates":[4.4234418869,50.8186988831],"type":"Point"}
}