{
  "type": "Feature",
  "properties": {
    "addr:full":"Culot Des Garennes 9 Jurbise Hainaut 7050",
    "addr:housenumber":"9",
    "addr:postcode":"7050",
    "addr:street":"Des Garennes",
    "iso:country":"BE",
    "sg:address":"Culot Des Garennes 9",
    "sg:city":"Jurbise",
    "sg:orig_category":"Textiel",
    "sg:phone":"+32 65 22 79 21",
    "sg:postcode":"7050",
    "sg:province":"Hainaut",
    "wof:name":"Michel Colin",
    "wof:placetype":"venue"
},
  "geometry": {"coordinates":[3.8682479858,50.5084686279],"type":"Point"}
}