{
  "type": "Feature",
  "properties": {
    "addr:full":"Gemeentehuisstraat 7 Beersel (dworp) Vlaams-Brabant 1653",
    "addr:housenumber":"7",
    "addr:postcode":"1653",
    "addr:street":"Gemeentehuisstraat",
    "iso:country":"BE",
    "sg:address":"Gemeentehuisstraat 7",
    "sg:city":"Beersel (dworp)",
    "sg:classifiers":[
        {
            "category":"Professional",
            "subcategory":"Computer Services",
            "type":"Services"
        }
    ],
    "sg:phone":"+32 2 381 00 15",
    "sg:postcode":"1653",
    "sg:province":"Vlaams-Brabant",
    "sg:tags":[
        "-",
        "processing",
        "data",
        "software"
    ],
    "wof:name":"Devos S",
    "wof:placetype":"venue"
},
  "geometry": {"coordinates":[4.2991251945,50.7301254272],"type":"Point"}
}