{
  "type": "Feature",
  "properties": {
    "iso:country":"BE",
    "sg:address":"Rue De Bastogne 36",
    "sg:city":"Houffalize",
    "sg:orig_category":"Antiquit\u00e9s",
    "sg:postcode":"6660",
    "sg:province":"Luxembourg",
    "wof:name":"Jean-paul Bernard",
    "wof:placetype":"venue"
},
  "geometry": {"coordinates":[5.7940659523,50.1272392273],"type":"Point"}
}