{
  "type": "Feature",
  "properties": {
    "addr:full":"Ieperweg 61 Zedelgem West-Vlaanderen 8210",
    "addr:housenumber":"61",
    "addr:postcode":"8210",
    "addr:street":"Ieperweg",
    "iso:country":"BE",
    "sg:address":"Ieperweg 61",
    "sg:city":"Zedelgem",
    "sg:orig_category":"Jardinage",
    "sg:phone":"+32 50 84 21 43",
    "sg:postcode":"8210",
    "sg:province":"West-Vlaanderen",
    "wof:name":"Hagymasi S.",
    "wof:placetype":"venue"
},
  "geometry": {"coordinates":[3.1458399296,51.1376457214],"type":"Point"}
}