{
  "type": "Feature",
  "properties": {
    "iso:country":"BE",
    "sg:address":"Brouwerijstraat 40",
    "sg:city":"Nevele",
    "sg:orig_category":"Elektrische installaties voor woningen",
    "sg:phone":"+32 9 371 71 03",
    "sg:postcode":"9850",
    "sg:province":"Oost-Vlaanderen",
    "wof:name":"Naessens Yves",
    "wof:placetype":"venue"
},
  "geometry": {"coordinates":[3.5605740547,51.0596923828],"type":"Point"}
}