{
  "type": "Feature",
  "properties": {
    "iso:country":"BE",
    "sg:address":"Grote Leiestraat 125",
    "sg:city":"Anzegem",
    "sg:orig_category":"Elektrische installaties voor woningen",
    "sg:phone":"+32 56 68 76 26",
    "sg:postcode":"8570",
    "sg:province":"West-Vlaanderen",
    "wof:name":"Elicati",
    "wof:placetype":"venue"
},
  "geometry": {"coordinates":[3.4551680088,50.8545455933],"type":"Point"}
}