{
  "type": "Feature",
  "properties": {
    "addr:full":"Avenue J Et M Tournay 6 Ottignies-louvain-la-neuve Brabant Wallon 1342",
    "addr:housenumber":"6",
    "addr:postcode":"1342",
    "addr:street":"Avenue J Et M Tournay",
    "iso:country":"BE",
    "sg:address":"Avenue J Et M Tournay 6",
    "sg:city":"Ottignies-louvain-la-neuve",
    "sg:orig_category":"Artsen and specialisten",
    "sg:phone":"+32 10 41 45 72",
    "sg:postcode":"1342",
    "sg:province":"Brabant Wallon",
    "wof:name":"W. Janssens",
    "wof:placetype":"venue"
},
  "geometry": {"coordinates":[4.5728960037,50.6801300049],"type":"Point"}
}