{
  "type": "Feature",
  "properties": {
    "addr:full":"Kardinaal Cardijnstraat 14 Brugge (sint-andries) West-Vlaanderen 8200",
    "addr:housenumber":"14",
    "addr:postcode":"8200",
    "addr:street":"Kardinaal Cardijnstraat",
    "iso:country":"BE",
    "sg:address":"Kardinaal Cardijnstraat 14",
    "sg:city":"Brugge (sint-andries)",
    "sg:classifiers":[
        {
            "category":"Shopping",
            "subcategory":"Crafts & Fabrics",
            "type":"Retail Goods"
        }
    ],
    "sg:phone":"+32 50 38 74 31",
    "sg:postcode":"8200",
    "sg:province":"West-Vlaanderen",
    "sg:tags":[
        "paints",
        "varnish",
        "-",
        "lacquers",
        "enamel"
    ],
    "wof:name":"Color Mix Bvba",
    "wof:placetype":"venue"
},
  "geometry": {"coordinates":[3.2047629356,51.2013931274],"type":"Point"}
}