{
  "type": "Feature",
  "properties": {
    "iso:country":"BE",
    "sg:address":"Turnhoutsebaan 316",
    "sg:city":"Schilde",
    "sg:orig_category":"Bloemen and planten",
    "sg:phone":"+32 3 383 01 02",
    "sg:postcode":"2970",
    "sg:province":"Antwerpen",
    "wof:name":"De Potterie",
    "wof:placetype":"venue"
},
  "geometry": {"coordinates":[4.584528923,51.2411651611],"type":"Point"}
}