{
  "type": "Feature",
  "properties": {
    "iso:country":"BE",
    "sg:address":"Zwijnaardsesteenweg 747",
    "sg:city":"Gent",
    "sg:orig_category":"Advocaten and juridische adviseurs",
    "sg:phone":"+32 9 222 26 58",
    "sg:postcode":"9000",
    "sg:province":"Oost-Vlaanderen",
    "wof:name":"Guy De Ruyck",
    "wof:placetype":"venue"
},
  "geometry": {"coordinates":[3.7198638916,51.0187034607],"type":"Point"}
}