{
  "type": "Feature",
  "properties": {
    "iso:country":"BE",
    "sg:address":"Hollange 50",
    "sg:city":"Fauvillers",
    "sg:orig_category":"Diverse bouwafwerking and reiniging",
    "sg:phone":"+32 61 26 71 45",
    "sg:postcode":"6637",
    "sg:province":"Luxembourg",
    "wof:name":"Deco Facades Eric Pondant",
    "wof:placetype":"venue"
},
  "geometry": {"coordinates":[5.686797142,49.9057006836],"type":"Point"}
}