{
  "type": "Feature",
  "properties": {
    "iso:country":"BE",
    "sg:address":"Amberloup 117",
    "sg:city":"Sainte-ode",
    "sg:orig_category":"Eleveurs de bovins",
    "sg:phone":"+32 61 68 82 77",
    "sg:postcode":"6680",
    "sg:province":"Luxembourg",
    "wof:name":"Poids D'or",
    "wof:placetype":"venue"
},
  "geometry": {"coordinates":[5.515004158,50.0244216919],"type":"Point"}
}