{
  "type": "Feature",
  "properties": {
    "addr:full":"Boulevard Emile Bockstael 360a Bruxelles Bruxelles-Capitale 1020",
    "addr:housenumber":"360a",
    "addr:postcode":"1020",
    "addr:street":"Boulevard Emile Bockstael",
    "iso:country":"BE",
    "sg:address":"Boulevard Emile Bockstael 360a",
    "sg:city":"Bruxelles",
    "sg:classifiers":[
        {
            "category":"Banks & Credit Unions",
            "subcategory":"Financial Services",
            "type":"Services"
        }
    ],
    "sg:phone":"+32 2 479 98 38",
    "sg:postcode":"1020",
    "sg:province":"Bruxelles-Capitale",
    "sg:tags":[
        "loan",
        "mortgage"
    ],
    "wof:name":"Immoth\u00e9cien (l')",
    "wof:placetype":"venue"
},
  "geometry": {"coordinates":[4.3463568687,50.8823356628],"type":"Point"}
}