{
  "type": "Feature",
  "properties": {
    "addr:full":"Jan Van Heelulaan 19 Antwerpen Antwerpen 2050",
    "addr:housenumber":"19",
    "addr:postcode":"2050",
    "addr:street":"Jan Van Heelulaan",
    "iso:country":"BE",
    "sg:address":"Jan Van Heelulaan 19",
    "sg:city":"Antwerpen",
    "sg:classifiers":[
        {
            "category":"Professional",
            "subcategory":"Accounting & Tax Preparation",
            "type":"Services"
        }
    ],
    "sg:phone":"+32 3 219 10 74",
    "sg:postcode":"2050",
    "sg:province":"Antwerpen",
    "sg:tags":[
        "accountant"
    ],
    "wof:name":"J. Lambertz",
    "wof:placetype":"venue"
},
  "geometry": {"coordinates":[4.3810019493,51.2322654724],"type":"Point"}
}