{
  "type": "Feature",
  "properties": {
    "iso:country":"BE",
    "sg:address":"Vlasmarkt 33b12",
    "sg:city":"Dendermonde",
    "sg:orig_category":"S\u00e9curit\u00e9 sociale",
    "sg:phone":"+32 52 21 16 08",
    "sg:postcode":"9200",
    "sg:province":"Oost-Vlaanderen",
    "wof:name":"Vl. Neutraal Ziekenfonds",
    "wof:placetype":"venue"
},
  "geometry": {"coordinates":[4.0991921425,51.0292778015],"type":"Point"}
}