{
  "type": "Feature",
  "properties": {
    "iso:country":"BE",
    "sg:address":"Hazenwegel 8",
    "sg:city":"Oosterzele",
    "sg:classifiers":[
        {
            "category":"Professional",
            "subcategory":"Computer Services",
            "type":"Services"
        }
    ],
    "sg:phone":"+32 9 362 29 40",
    "sg:postcode":"9860",
    "sg:province":"Oost-Vlaanderen",
    "sg:tags":[
        "network"
    ],
    "wof:name":"De Visscher Micro",
    "wof:placetype":"venue"
},
  "geometry": {"coordinates":[3.8122138977,50.9465408325],"type":"Point"}
}