{
  "type": "Feature",
  "properties": {
    "iso:country":"BE",
    "sg:address":"Korenmarkt 17",
    "sg:city":"Gent",
    "sg:classifiers":[
        {
            "category":"Fast Food",
            "type":"Food & Drink"
        }
    ],
    "sg:phone":"+32 9 225 93 82",
    "sg:postcode":"9000",
    "sg:province":"Oost-Vlaanderen",
    "sg:tags":[
        "meeneem",
        "restaurant"
    ],
    "wof:name":"Restaurant Peking",
    "wof:placetype":"venue"
},
  "geometry": {"coordinates":[3.7218229771,51.0547065735],"type":"Point"}
}