{
  "type": "Feature",
  "properties": {
    "addr:full":"Tomberg 225 Sint-lambrechts-woluwe/woluwe-saint-lambert Bruxelles-Capitale 1200",
    "addr:housenumber":"225",
    "addr:postcode":"1200",
    "addr:street":"Tomberg",
    "iso:country":"BE",
    "sg:address":"Tomberg 225",
    "sg:city":"Sint-lambrechts-woluwe/woluwe-saint-lambert",
    "sg:orig_category":"Landmeters",
    "sg:phone":"+32 2 771 61 95",
    "sg:postcode":"1200",
    "sg:province":"Bruxelles-Capitale",
    "wof:name":"Marc Henrioul",
    "wof:placetype":"venue"
},
  "geometry": {"coordinates":[4.4218850136,50.8436431885],"type":"Point"}
}