{
  "type": "Feature",
  "properties": {
    "addr:full":"Bruinbekestraat 52 Wichelen Oost-Vlaanderen 9260",
    "addr:housenumber":"52",
    "addr:postcode":"9260",
    "addr:street":"Bruinbekestraat",
    "iso:country":"BE",
    "sg:address":"Bruinbekestraat 52",
    "sg:city":"Wichelen",
    "sg:orig_category":"Entretien and r\u00e9parations de voitures",
    "sg:phone":"+32 9 369 21 19",
    "sg:postcode":"9260",
    "sg:province":"Oost-Vlaanderen",
    "wof:name":"Marcel Mertens",
    "wof:placetype":"venue"
},
  "geometry": {"coordinates":[3.9476270676,51.0002059937],"type":"Point"}
}