{
  "type": "Feature",
  "properties": {
    "addr:full":"Itterplein 15ba Bree Limburg 3960",
    "addr:housenumber":"15ba",
    "addr:postcode":"3960",
    "addr:street":"Itterplein",
    "iso:country":"BE",
    "sg:address":"Itterplein 15ba",
    "sg:city":"Bree",
    "sg:classifiers":[
        {
            "category":"Cafe",
            "type":"Food & Drink"
        }
    ],
    "sg:phone":"+32 89 86 82 29",
    "sg:postcode":"3960",
    "sg:province":"Limburg",
    "sg:tags":[
        "caf\u00e9s"
    ],
    "wof:name":"Maria Vaesen",
    "wof:placetype":"venue"
},
  "geometry": {"coordinates":[5.5944190025,51.1405677795],"type":"Point"}
}