{
  "type": "Feature",
  "properties": {
    "addr:full":"Hellebeemden 3 Hasselt Limburg 3500",
    "addr:housenumber":"3",
    "addr:postcode":"3500",
    "addr:street":"Hellebeemden",
    "iso:country":"BE",
    "sg:address":"Hellebeemden 3",
    "sg:city":"Hasselt",
    "sg:classifiers":[
        {
            "category":"Manufacturing",
            "subcategory":"Food",
            "type":"Manufacturing & Wholesale Goods"
        }
    ],
    "sg:phone":"+32 11 28 10 00",
    "sg:postcode":"3500",
    "sg:province":"Limburg",
    "sg:tags":[
        "industry",
        "-",
        "ingredient"
    ],
    "wof:name":"Eurofood Belgium Nv",
    "wof:placetype":"venue"
},
  "geometry": {"coordinates":[5.3383088112,50.91248703],"type":"Point"}
}