{
  "type": "Feature",
  "properties": {
    "addr:full":"Hendrik Consciencestraat 11 Kortrijk West-Vlaanderen 8500",
    "addr:housenumber":"11",
    "addr:postcode":"8500",
    "addr:street":"Hendrik Consciencestraat",
    "iso:country":"BE",
    "sg:address":"Hendrik Consciencestraat 11",
    "sg:city":"Kortrijk",
    "sg:classifiers":[
        {
            "category":"Health Services",
            "subcategory":"Health Practitioner",
            "type":"Services"
        }
    ],
    "sg:phone":"+32 56 20 28 88",
    "sg:postcode":"8500",
    "sg:province":"West-Vlaanderen",
    "sg:tags":[
        "physiotherapist"
    ],
    "wof:name":"Vangheluwe B",
    "wof:placetype":"venue"
},
  "geometry": {"coordinates":[3.2597720623,50.8262252808],"type":"Point"}
}