{
  "type": "Feature",
  "properties": {
    "addr:full":"Rue De Champ 31 Eupen Li\u00e8ge 4701",
    "addr:housenumber":"31",
    "addr:postcode":"4701",
    "addr:street":"Rue De Champ",
    "iso:country":"BE",
    "sg:address":"Rue De Champ 31",
    "sg:city":"Eupen",
    "sg:classifiers":[
        {
            "category":"Personal",
            "subcategory":"Beauty Salon",
            "type":"Services"
        }
    ],
    "sg:phone":"+32 87 55 71 44",
    "sg:postcode":"4701",
    "sg:province":"Li\u00e8ge",
    "sg:tags":[
        "de",
        "coiffure"
    ],
    "wof:name":"Birgit Offermann",
    "wof:placetype":"venue"
},
  "geometry": {"coordinates":[6.0461649895,50.6460838318],"type":"Point"}
}