{
  "type": "Feature",
  "properties": {
    "addr:full":"Rue Du Canada 43 Moeskroen/mouscron Hainaut 7700",
    "addr:housenumber":"43",
    "addr:postcode":"7700",
    "addr:street":"Rue Du Canada",
    "iso:country":"BE",
    "sg:address":"Rue Du Canada 43",
    "sg:city":"Moeskroen/mouscron",
    "sg:orig_category":"Instituts pour enfants en difficult\u00e9. Orphelinats",
    "sg:phone":"+32 56 33 59 88",
    "sg:postcode":"7700",
    "sg:province":"Hainaut",
    "wof:name":"Home Rencontre",
    "wof:placetype":"venue"
},
  "geometry": {"coordinates":[3.2323200703,50.7400932312],"type":"Point"}
}