{
  "type": "Feature",
  "properties": {
    "iso:country":"BE",
    "sg:address":"Yzerhand 19",
    "sg:city":"Beveren",
    "sg:orig_category":"Apotheken",
    "sg:phone":"+32 3 775 90 01",
    "sg:postcode":"9120",
    "sg:province":"Oost-Vlaanderen",
    "wof:name":"Zwitserse Apotheek",
    "wof:placetype":"venue"
},
  "geometry": {"coordinates":[4.2520689964,51.2153663635],"type":"Point"}
}