{
  "type": "Feature",
  "properties": {
    "addr:full":"De Pannelaan 187 De Panne West-Vlaanderen 8660",
    "addr:housenumber":"187",
    "addr:postcode":"8660",
    "addr:street":"De Pannelaan",
    "iso:country":"BE",
    "sg:address":"De Pannelaan 187",
    "sg:city":"De Panne",
    "sg:orig_category":"Salles de conf\u00e9rences and de r\u00e9ceptions. Restaurants",
    "sg:phone":"+32 58 42 02 77",
    "sg:postcode":"8660",
    "sg:province":"West-Vlaanderen",
    "wof:name":"Le Bercail",
    "wof:placetype":"venue"
},
  "geometry": {"coordinates":[2.6010830402,51.0853919983],"type":"Point"}
}