{
  "type": "Feature",
  "properties": {
    "addr:full":"Mechelbaan 272 Putte Antwerpen 2580",
    "addr:housenumber":"272",
    "addr:postcode":"2580",
    "addr:street":"Mechelbaan",
    "iso:country":"BE",
    "sg:address":"Mechelbaan 272",
    "sg:city":"Putte",
    "sg:classifiers":[
        {
            "category":"Utilities",
            "subcategory":"Fuel Oil & Lpg",
            "type":"Services"
        }
    ],
    "sg:phone":"+32 15 75 51 36",
    "sg:postcode":"2580",
    "sg:province":"Antwerpen",
    "wof:name":"Fina Europe Vervoort Wim Bvba",
    "wof:placetype":"venue"
},
  "geometry": {"coordinates":[4.6438708305,51.0596961975],"type":"Point"}
}