{
  "type": "Feature",
  "properties": {
    "iso:country":"BE",
    "sg:address":"Pruimenstraat 11",
    "sg:city":"Sint-truiden",
    "sg:classifiers":[
        {
            "category":"Building & Trades",
            "subcategory":"Pest Control",
            "type":"Services"
        }
    ],
    "sg:phone":"+32 11 68 16 67",
    "sg:postcode":"3800",
    "sg:province":"Limburg",
    "sg:tags":[
        "painting",
        "contractor"
    ],
    "wof:name":"Heeren M",
    "wof:placetype":"venue"
},
  "geometry": {"coordinates":[5.1719341278,50.8114356995],"type":"Point"}
}