{
  "type": "Feature",
  "properties": {
    "iso:country":"BE",
    "sg:address":"Gentsesteenweg 325",
    "sg:city":"Erpe-mere",
    "sg:orig_category":"Electrom\u00e9nager, t\u00e9l\u00e9visions and radios",
    "sg:phone":"+32 53 80 86 96",
    "sg:postcode":"9420",
    "sg:province":"Oost-Vlaanderen",
    "wof:name":"Satteliet Service",
    "wof:placetype":"venue"
},
  "geometry": {"coordinates":[3.9630200863,50.9457702637],"type":"Point"}
}