{
  "type": "Feature",
  "properties": {
    "addr:full":"Rue Du Ch\u00c2teau-le-duc 14 Bouillon Luxembourg 6833",
    "addr:housenumber":"14",
    "addr:postcode":"6833",
    "addr:street":"Rue Du Cha\u0302Teau-Le-Duc",
    "iso:country":"BE",
    "sg:address":"Rue Du Ch\u00c2teau-le-duc 14",
    "sg:city":"Bouillon",
    "sg:orig_category":"P\u00e9pini\u00e9ristes",
    "sg:phone":"+32 61 46 74 42",
    "sg:postcode":"6833",
    "sg:province":"Luxembourg",
    "wof:name":"Jean-louis Gregoire",
    "wof:placetype":"venue"
},
  "geometry": {"coordinates":[5.0365228653,49.865940094],"type":"Point"}
}