{
  "type": "Feature",
  "properties": {
    "iso:country":"BE",
    "sg:address":"Beneluxlaan 4",
    "sg:city":"Tielt",
    "sg:classifiers":[
        {
            "category":"Professional",
            "type":"Services"
        }
    ],
    "sg:phone":"+32 51 40 23 92",
    "sg:postcode":"8700",
    "sg:province":"West-Vlaanderen",
    "sg:tags":[
        "surveyor",
        "-",
        "valuer"
    ],
    "wof:name":"De Poortere J",
    "wof:placetype":"venue"
},
  "geometry": {"coordinates":[3.3345229626,50.9988975525],"type":"Point"}
}