{
  "type": "Feature",
  "properties": {
    "addr:full":"Kloosterstraat 15-19 Beveren Oost-Vlaanderen 9120",
    "addr:postcode":"15-19;9120",
    "addr:street":"Kloosterstraat",
    "iso:country":"BE",
    "sg:address":"Kloosterstraat 15-19",
    "sg:city":"Beveren",
    "sg:orig_category":"Notaires",
    "sg:phone":"+32 3 775 71 55",
    "sg:postcode":"9120",
    "sg:province":"Oost-Vlaanderen",
    "wof:name":"Nicolas Van Raemdonck",
    "wof:placetype":"venue"
},
  "geometry": {"coordinates":[4.2581381798,51.214389801],"type":"Point"}
}