{
  "type": "Feature",
  "properties": {
    "iso:country":"BE",
    "sg:address":"Rue J D'ardenne 62",
    "sg:city":"Elsene/ixelles",
    "sg:orig_category":"Alimentation sp\u00e9cialis\u00e9e",
    "sg:phone":"+32 2 512 51 65",
    "sg:postcode":"1050",
    "sg:province":"Bruxelles-Capitale",
    "wof:name":"Brussel's Pralines",
    "wof:placetype":"venue"
},
  "geometry": {"coordinates":[4.3616838455,50.8314361572],"type":"Point"}
}