{
  "type": "Feature",
  "properties": {
    "addr:full":"Sint-jorisstraat 10 Aalst Oost-Vlaanderen 9300",
    "addr:housenumber":"10",
    "addr:postcode":"9300",
    "addr:street":"Sint-Jorisstraat",
    "iso:country":"BE",
    "sg:address":"Sint-jorisstraat 10",
    "sg:city":"Aalst",
    "sg:classifiers":[
        {
            "category":"Shopping",
            "subcategory":"Clothing, Apparel, & Fashions",
            "type":"Retail Goods"
        }
    ],
    "sg:phone":"+32 53 77 81 03",
    "sg:postcode":"9300",
    "sg:province":"Oost-Vlaanderen",
    "sg:tags":[
        "-",
        "clothing",
        "child"
    ],
    "wof:name":"Amantine",
    "wof:placetype":"venue"
},
  "geometry": {"coordinates":[4.0387349129,50.9371681213],"type":"Point"}
}