{
  "type": "Feature",
  "properties": {
    "addr:full":"Rue Du Fond D\u00b4or 49 Waremme Li\u00e8ge 4300",
    "addr:housenumber":"49",
    "addr:postcode":"4300",
    "addr:street":"Rue Du Fond D\u00b4Or",
    "iso:country":"BE",
    "sg:address":"Rue Du Fond D\u00b4or 49",
    "sg:city":"Waremme",
    "sg:orig_category":"Sportclubs",
    "sg:phone":"+32 19 32 54 63",
    "sg:postcode":"4300",
    "sg:province":"Li\u00e8ge",
    "wof:name":"L\u00b4eclair",
    "wof:placetype":"venue"
},
  "geometry": {"coordinates":[5.2650909424,50.6926803589],"type":"Point"}
}