{
  "type": "Feature",
  "properties": {
    "iso:country":"BE",
    "sg:address":"Rue D\u00b4oignies 119",
    "sg:city":"Aiseau-presles",
    "sg:orig_category":"RESTAURANTS: CAF\u00c9S",
    "sg:phone":"+32 71 74 32 72",
    "sg:postcode":"6250",
    "sg:province":"Hainaut",
    "wof:name":"Caves D\u00b4artois",
    "wof:placetype":"venue"
},
  "geometry": {"coordinates":[4.60704422,50.4259033203],"type":"Point"}
}