{
  "type": "Feature",
  "properties": {
    "iso:country":"BE",
    "sg:address":"Avenue Des D\u00e9port\u00e9s 50",
    "sg:city":"Wavre",
    "sg:classifiers":[
        {
            "category":"Retail",
            "subcategory":"Laundry & Dry Cleaning",
            "type":"Services"
        }
    ],
    "sg:phone":"+32 10 22 81 49",
    "sg:postcode":"1300",
    "sg:province":"Brabant Wallon",
    "wof:name":"Blanchisserie Top Net",
    "wof:placetype":"venue"
},
  "geometry": {"coordinates":[4.6145648956,50.7165527344],"type":"Point"}
}