{
  "type": "Feature",
  "properties": {
    "iso:country":"BE",
    "sg:address":"Grand Rue 70",
    "sg:city":"Pecq (obigies)",
    "sg:classifiers":[
        {
            "category":"Professional",
            "subcategory":"Accounting & Tax Preparation",
            "type":"Services"
        }
    ],
    "sg:phone":"+32 69 45 28 82",
    "sg:postcode":"7743",
    "sg:province":"Hainaut",
    "sg:tags":[
        "bookkeeper"
    ],
    "wof:name":"F.o.c. Sprl",
    "wof:placetype":"venue"
},
  "geometry": {"coordinates":[3.3629209995,50.6570587158],"type":"Point"}
}