{
  "type": "Feature",
  "properties": {
    "addr:full":"Heulsestraat 11 Kortrijk West-Vlaanderen 8501",
    "addr:housenumber":"11",
    "addr:postcode":"8501",
    "addr:street":"Heulsestraat",
    "iso:country":"BE",
    "sg:address":"Heulsestraat 11",
    "sg:city":"Kortrijk",
    "sg:orig_category":"Cr\u00e8ches and garderies d'enfants",
    "sg:phone":"+32 56 37 12 14",
    "sg:postcode":"8501",
    "sg:province":"West-Vlaanderen",
    "wof:name":"Kribbe De Speelboom",
    "wof:placetype":"venue"
},
  "geometry": {"coordinates":[3.2282600403,50.82472229],"type":"Point"}
}