{
  "type": "Feature",
  "properties": {
    "iso:country":"BE",
    "sg:address":"Rue De Sart-lez-moulin 108",
    "sg:city":"Courcelles",
    "sg:orig_category":"Biens d'occasion. Eclairage et \u00e9quipements du foyer",
    "sg:phone":"+32 71 46 54 34",
    "sg:postcode":"6180",
    "sg:province":"Hainaut",
    "wof:name":"Maison Brocantic",
    "wof:placetype":"venue"
},
  "geometry": {"coordinates":[4.3588461876,50.4393424988],"type":"Point"}
}