{
  "type": "Feature",
  "properties": {
    "addr:full":"Avenue Du Champs De Mars 91 Mons Hainaut 7000",
    "addr:housenumber":"91",
    "addr:postcode":"7000",
    "addr:street":"Avenue Du Champs De Mars;Hainaut",
    "iso:country":"BE",
    "sg:address":"Avenue Du Champs De Mars 91",
    "sg:city":"Mons",
    "sg:orig_category":"Herstellingen and onderhoud aan huis voor voertuigen",
    "sg:phone":"+32 65 31 57 23",
    "sg:postcode":"7000",
    "sg:province":"Hainaut",
    "wof:name":"S.o.s. D\u00c9pannage",
    "wof:placetype":"venue"
},
  "geometry": {"coordinates":[3.9567461014,50.4658164978],"type":"Point"}
}