{
  "type": "Feature",
  "properties": {
    "addr:full":"Grotestraat 54 Geraardsbergen Oost-Vlaanderen 9500",
    "addr:housenumber":"54",
    "addr:postcode":"9500",
    "addr:street":"Grotestraat",
    "iso:country":"BE",
    "sg:address":"Grotestraat 54",
    "sg:city":"Geraardsbergen",
    "sg:orig_category":"Disquaires",
    "sg:phone":"+32 54 41 50 67",
    "sg:postcode":"9500",
    "sg:province":"Oost-Vlaanderen",
    "wof:name":"Musikladen",
    "wof:placetype":"venue"
},
  "geometry": {"coordinates":[3.8776249886,50.7716712952],"type":"Point"}
}