{
  "type": "Feature",
  "properties": {
    "addr:full":"Rue Des Eglantines 28 Li\u00e8ge 1 (bressoux) Li\u00e8ge 4020",
    "addr:housenumber":"28;1",
    "addr:postcode":"4020",
    "addr:street":"Rue Des Eglantines",
    "iso:country":"BE",
    "sg:address":"Rue Des Eglantines 28",
    "sg:city":"Li\u00e8ge 1 (bressoux)",
    "sg:classifiers":[
        {
            "category":"Banks & Credit Unions",
            "subcategory":"Investment Brokerage",
            "type":"Services"
        }
    ],
    "sg:phone":"+32 4 342 60 96",
    "sg:postcode":"4020",
    "sg:province":"Li\u00e8ge",
    "sg:tags":[
        "auditor"
    ],
    "wof:name":"Pirlot Ph",
    "wof:placetype":"venue"
},
  "geometry": {"coordinates":[5.6013059616,50.6365814209],"type":"Point"}
}