{
  "type": "Feature",
  "properties": {
    "addr:full":"Avenue George Bergmann 16 Bruxelles (ixelles) Bruxelles-Capitale 1050",
    "addr:housenumber":"16",
    "addr:postcode":"1050",
    "addr:street":"Avenue George Bergmann",
    "iso:country":"BE",
    "sg:address":"Avenue George Bergmann 16",
    "sg:city":"Bruxelles (ixelles)",
    "sg:classifiers":[
        {
            "category":"Personal",
            "subcategory":"Nail Salon",
            "type":"Services"
        }
    ],
    "sg:phone":"+32 2 672 67 86",
    "sg:postcode":"1050",
    "sg:province":"Bruxelles-Capitale",
    "sg:tags":[
        "pedicure"
    ],
    "wof:name":"Doriaux Francoise Institut",
    "wof:placetype":"venue"
},
  "geometry": {"coordinates":[4.3935427666,50.8097496033],"type":"Point"}
}