{
  "type": "Feature",
  "properties": {
    "addr:full":"Rue Neuve Chauss\u00e9e 7 P\u00e9ruwelz Hainaut 7600",
    "addr:housenumber":"7",
    "addr:postcode":"7600",
    "addr:street":"Rue;Chausse\u0301E",
    "iso:country":"BE",
    "sg:address":"Rue Neuve Chauss\u00e9e 7",
    "sg:city":"P\u00e9ruwelz",
    "sg:classifiers":[
        {
            "category":"Personal",
            "subcategory":"Beauty Salon",
            "type":"Services"
        }
    ],
    "sg:phone":"+32 69 77 70 71",
    "sg:postcode":"7600",
    "sg:province":"Hainaut",
    "wof:name":"Ile De Beaut\u00e9",
    "wof:placetype":"venue"
},
  "geometry": {"coordinates":[3.5993680954,50.5126457214],"type":"Point"}
}