{
  "type": "Feature",
  "properties": {
    "addr:full":"All\u00c9e Des Freesias 18 Brussel/bruxelles Bruxelles-Capitale 1030",
    "addr:housenumber":"18",
    "addr:postcode":"1030",
    "addr:street":"Alle\u0301E Des Freesias;/",
    "iso:country":"BE",
    "sg:address":"All\u00c9e Des Freesias 18",
    "sg:city":"Brussel/bruxelles",
    "sg:classifiers":[
        {
            "category":"Travel",
            "subcategory":"Hotels & Motels",
            "type":"Entertainment"
        }
    ],
    "sg:phone":"+32 2 246 02 11",
    "sg:postcode":"1030",
    "sg:province":"Bruxelles-Capitale",
    "wof:name":"Aparthotel Lambermont",
    "wof:placetype":"venue"
},
  "geometry": {"coordinates":[4.3904280663,50.8650093079],"type":"Point"}
}