{
  "type": "Feature",
  "properties": {
    "addr:full":"Sint-jansstraat 103 Beveren-leie West-Vlaanderen 8791",
    "addr:housenumber":"103",
    "addr:postcode":"8791",
    "addr:street":"Sint-Jansstraat;West-Vlaanderen",
    "iso:country":"BE",
    "sg:address":"Sint-jansstraat 103",
    "sg:city":"Beveren-leie",
    "sg:classifiers":[
        {
            "category":"Manufacturing",
            "subcategory":"Tools & Machinery",
            "type":"Manufacturing & Wholesale Goods"
        }
    ],
    "sg:phone":"+32 56 73 00 11",
    "sg:postcode":"8791",
    "sg:province":"West-Vlaanderen",
    "sg:tags":[
        "metallurgy",
        "metalworking"
    ],
    "wof:name":"Egetra Nv",
    "wof:placetype":"venue"
},
  "geometry": {"coordinates":[3.3315749168,50.8731384277],"type":"Point"}
}