{
  "type": "Feature",
  "properties": {
    "iso:country":"BE",
    "sg:address":"Rammelstraat 30",
    "sg:city":"Lede",
    "sg:classifiers":[
        {
            "category":"Restaurant",
            "type":"Food & Drink"
        }
    ],
    "sg:phone":"+32 53 80 20 80",
    "sg:postcode":"9340",
    "sg:province":"Oost-Vlaanderen",
    "sg:tags":[
        "de",
        "organisation",
        "\u00c0",
        "fast",
        "catering",
        "emporter",
        "f\u00cates",
        "restaurants"
    ],
    "wof:name":"Restaurant Lai's Garden",
    "wof:placetype":"venue"
},
  "geometry": {"coordinates":[3.9769499302,50.9671974182],"type":"Point"}
}