{
  "type": "Feature",
  "properties": {
    "addr:full":"Ridderstraat 36 Sint-truiden Limburg 3800",
    "addr:housenumber":"36",
    "addr:postcode":"3800",
    "addr:street":"Ridderstraat",
    "iso:country":"BE",
    "sg:address":"Ridderstraat 36",
    "sg:city":"Sint-truiden",
    "sg:classifiers":[
        {
            "category":"Real Estate",
            "subcategory":"Surveying",
            "type":"Services"
        }
    ],
    "sg:phone":"+32 11 67 11 90",
    "sg:postcode":"3800",
    "sg:province":"Limburg",
    "sg:tags":[
        "surveyor",
        "land"
    ],
    "wof:name":"Vanmechelen J",
    "wof:placetype":"venue"
},
  "geometry": {"coordinates":[5.1893630028,50.815448761],"type":"Point"}
}