{
  "type": "Feature",
  "properties": {
    "iso:country":"BE",
    "sg:address":"Avenue Du Ch\u00cane Madame 21",
    "sg:city":"Neupre",
    "sg:orig_category":"Gespecialiseerde residenti\u00eble bouw Industri\u00eble and commerci\u00eble bouw Woningbouw",
    "sg:phone":"+32 4 371 44 84",
    "sg:postcode":"4121",
    "sg:province":"Li\u00e8ge",
    "wof:name":"Denis",
    "wof:placetype":"venue"
},
  "geometry": {"coordinates":[5.4855408669,50.5461959839],"type":"Point"}
}