{
  "type": "Feature",
  "properties": {
    "addr:full":"Prins Boudewijnlaan 152a Edegem Antwerpen 2650",
    "addr:housenumber":"152a",
    "addr:postcode":"2650",
    "addr:street":"Prins Boudewijnlaan",
    "iso:country":"BE",
    "sg:address":"Prins Boudewijnlaan 152a",
    "sg:city":"Edegem",
    "sg:classifiers":[
        {
            "category":"Manufacturing",
            "subcategory":"Food",
            "type":"Manufacturing & Wholesale Goods"
        }
    ],
    "sg:phone":"+32 3 450 72 30",
    "sg:postcode":"2650",
    "sg:province":"Antwerpen",
    "sg:tags":[
        "industry",
        "-",
        "ingredient"
    ],
    "wof:name":"De Block M.p.m.",
    "wof:placetype":"venue"
},
  "geometry": {"coordinates":[4.4348869324,51.1487159729],"type":"Point"}
}