{
  "type": "Feature",
  "properties": {
    "addr:full":"Rue Du Tige 5 Gembloux-sur-orneau (gembloux) Namur 5030",
    "addr:housenumber":"5",
    "addr:postcode":"5030",
    "addr:street":"Rue Du Tige;Namur",
    "iso:country":"BE",
    "sg:address":"Rue Du Tige 5",
    "sg:city":"Gembloux-sur-orneau (gembloux)",
    "sg:classifiers":[
        {
            "category":"Health Services",
            "subcategory":"Doctor",
            "type":"Services"
        }
    ],
    "sg:phone":"+32 81 61 43 59",
    "sg:postcode":"5030",
    "sg:province":"Namur",
    "sg:tags":[
        "medicinephysicians",
        "surgeon"
    ],
    "wof:name":"Demelenne Jacques",
    "wof:placetype":"venue"
},
  "geometry": {"coordinates":[4.7287020683,50.5896339417],"type":"Point"}
}