{
  "type": "Feature",
  "properties": {
    "iso:country":"BE",
    "sg:address":"Grote Nieuwedijkstraat 409",
    "sg:city":"Mechelen",
    "sg:classifiers":[
        {
            "category":"Home & Garden",
            "subcategory":"Home Furnishings",
            "type":"Retail Goods"
        }
    ],
    "sg:phone":"+32 15 55 46 65",
    "sg:postcode":"2800",
    "sg:province":"Antwerpen",
    "sg:tags":[
        "interior",
        "decoration"
    ],
    "wof:name":"Coloma Design",
    "wof:placetype":"venue"
},
  "geometry": {"coordinates":[4.4960198402,51.0412597656],"type":"Point"}
}