{
  "type": "Feature",
  "properties": {
    "addr:full":"Avenue De Fr\u00e9 102 Box 1 Bruxelles (uccle) Bruxelles-Capitale 1180",
    "addr:housenumber":"102;1",
    "addr:postcode":"1180",
    "addr:street":"Avenue De Fre\u0301;Box",
    "iso:country":"BE",
    "sg:address":"Avenue De Fr\u00e9 102 Box 1",
    "sg:city":"Bruxelles (uccle)",
    "sg:classifiers":[
        {
            "category":"Professional",
            "subcategory":"Art Services",
            "type":"Services"
        }
    ],
    "sg:phone":"+32 2 372 12 75",
    "sg:postcode":"1180",
    "sg:province":"Bruxelles-Capitale",
    "sg:tags":[
        "interior",
        "designer"
    ],
    "wof:name":"Demeester B",
    "wof:placetype":"venue"
},
  "geometry": {"coordinates":[4.3589930534,50.8040161133],"type":"Point"}
}