{
  "type": "Feature",
  "properties": {
    "addr:full":"Mortagnestraat 8 Pepingen Vlaams-Brabant 1670",
    "addr:housenumber":"8",
    "addr:postcode":"1670",
    "addr:street":"Mortagnestraat",
    "iso:country":"BE",
    "sg:address":"Mortagnestraat 8",
    "sg:city":"Pepingen",
    "sg:orig_category":"Binnenhuisarchitecten",
    "sg:phone":"+32 2 396 18 72",
    "sg:postcode":"1670",
    "sg:province":"Vlaams-Brabant",
    "wof:name":"Topdesign",
    "wof:placetype":"venue"
},
  "geometry": {"coordinates":[4.1027340889,50.7282218933],"type":"Point"}
}