{
  "type": "Feature",
  "properties": {
    "addr:full":"Haachtsebaan 33 Keerbergen Vlaams-Brabant 3140",
    "addr:housenumber":"33",
    "addr:postcode":"3140",
    "addr:street":"Haachtsebaan",
    "iso:country":"BE",
    "sg:address":"Haachtsebaan 33",
    "sg:city":"Keerbergen",
    "sg:orig_category":"Beautyfarms, relaxatie and lichamelijk welzijn Cosmetica and toiletartikelen Schoonheidssalons",
    "sg:phone":"+32 15 52 09 29",
    "sg:postcode":"3140",
    "sg:province":"Vlaams-Brabant",
    "wof:name":"Parfumerie Kiani",
    "wof:placetype":"venue"
},
  "geometry": {"coordinates":[4.6301817894,51.0041618347],"type":"Point"}
}