{
  "type": "Feature",
  "properties": {
    "addr:full":"Kapellestraat 88 Evergem Oost-Vlaanderen 9940",
    "addr:housenumber":"88",
    "addr:postcode":"9940",
    "addr:street":"Kapellestraat;Oost-Vlaanderen",
    "iso:country":"BE",
    "sg:address":"Kapellestraat 88",
    "sg:city":"Evergem",
    "sg:classifiers":[
        {
            "category":"Bars & Pubs",
            "type":"Food & Drink"
        }
    ],
    "sg:phone":"+32 9 253 50 87",
    "sg:postcode":"9940",
    "sg:province":"Oost-Vlaanderen",
    "wof:name":"Kleine Venus (de)",
    "wof:placetype":"venue"
},
  "geometry": {"coordinates":[3.7114260197,51.1130638123],"type":"Point"}
}