{
  "type": "Feature",
  "properties": {
    "addr:full":"Rue Saint-l\u00e9onard 13 Li\u00e8ge 1 Li\u00e8ge 4000",
    "addr:housenumber":"13;1",
    "addr:postcode":"4000",
    "addr:street":"Rue Saint-Le\u0301Onard",
    "iso:country":"BE",
    "sg:address":"Rue Saint-l\u00e9onard 13",
    "sg:city":"Li\u00e8ge 1",
    "sg:classifiers":[
        {
            "category":"Professional",
            "subcategory":"Accounting & Tax Preparation",
            "type":"Services"
        }
    ],
    "sg:phone":"+32 4 227 15 99",
    "sg:postcode":"4000",
    "sg:province":"Li\u00e8ge",
    "sg:tags":[
        "bookkeeper"
    ],
    "wof:name":"Swinnen J",
    "wof:placetype":"venue"
},
  "geometry": {"coordinates":[5.5866041183,50.6483078003],"type":"Point"}
}