{
  "type": "Feature",
  "properties": {
    "addr:full":"Beekstraat 17 Kortrijk West-Vlaanderen 8500",
    "addr:housenumber":"17",
    "addr:postcode":"8500",
    "addr:street":"Beekstraat",
    "iso:country":"BE",
    "sg:address":"Beekstraat 17",
    "sg:city":"Kortrijk",
    "sg:classifiers":[
        {
            "category":"Personal",
            "subcategory":"Beauty Salon",
            "type":"Services"
        }
    ],
    "sg:phone":"+32 56 21 90 54",
    "sg:postcode":"8500",
    "sg:province":"West-Vlaanderen",
    "sg:tags":[
        "lady",
        "-",
        "hairdressing"
    ],
    "wof:name":"Pattyn J",
    "wof:placetype":"venue"
},
  "geometry": {"coordinates":[3.2849459648,50.8199043274],"type":"Point"}
}