{
  "type": "Feature",
  "properties": {
    "iso:country":"BE",
    "sg:address":"Sint-truidensesteenweg 5",
    "sg:city":"Linter",
    "sg:orig_category":"Meubelzaken, woning- and keukeninrichting",
    "sg:phone":"+32 16 78 91 16",
    "sg:postcode":"3350",
    "sg:province":"Vlaams-Brabant",
    "wof:name":"Alfred Engels",
    "wof:placetype":"venue"
},
  "geometry": {"coordinates":[5.0515198708,50.802230835],"type":"Point"}
}