{
  "type": "Feature",
  "properties": {
    "iso:country":"BE",
    "sg:address":"Sparrenweg 38",
    "sg:city":"Zonhoven",
    "sg:orig_category":"Epiceries",
    "sg:phone":"+32 11 81 43 58",
    "sg:postcode":"3520",
    "sg:province":"Limburg",
    "wof:name":"Tempo Service Termolen",
    "wof:placetype":"venue"
},
  "geometry": {"coordinates":[5.409963131,50.9825363159],"type":"Point"}
}