{
  "type": "Feature",
  "properties": {
    "addr:full":"New-yorkstraat 2bg Gent Oost-Vlaanderen 9000",
    "addr:housenumber":"2bg",
    "addr:postcode":"9000",
    "addr:street":"New-Yorkstraat;Oost-Vlaanderen",
    "iso:country":"BE",
    "sg:address":"New-yorkstraat 2bg",
    "sg:city":"Gent",
    "sg:orig_category":"Studios photographiques",
    "sg:phone":"+32 9 259 24 05",
    "sg:postcode":"9000",
    "sg:province":"Oost-Vlaanderen",
    "wof:name":"S.w.a.d.",
    "wof:placetype":"venue"
},
  "geometry": {"coordinates":[3.7297270298,51.0776596069],"type":"Point"}
}