{
  "type": "Feature",
  "properties": {
    "addr:full":"Avenue Du Marly 8 Brussel/bruxelles Bruxelles-Capitale 1120",
    "addr:housenumber":"8",
    "addr:postcode":"1120",
    "addr:street":"Avenue Du Marly;/",
    "iso:country":"BE",
    "sg:address":"Avenue Du Marly 8",
    "sg:city":"Brussel/bruxelles",
    "sg:orig_category":"Entretien and r\u00e9parations de voitures",
    "sg:phone":"+32 2 268 54 70",
    "sg:postcode":"1120",
    "sg:province":"Bruxelles-Capitale",
    "wof:name":"Garage R.s.",
    "wof:placetype":"venue"
},
  "geometry": {"coordinates":[4.3993268013,50.899017334],"type":"Point"}
}