{
  "type": "Feature",
  "properties": {
    "iso:country":"BE",
    "sg:address":"Meerlaanstraat 8",
    "sg:city":"Meulebeke",
    "sg:classifiers":[
        {
            "category":"Bars & Pubs",
            "type":"Food & Drink"
        }
    ],
    "sg:phone":"+32 51 48 62 25",
    "sg:postcode":"8760",
    "sg:province":"West-Vlaanderen",
    "wof:name":"Hof Ter Velde",
    "wof:placetype":"venue"
},
  "geometry": {"coordinates":[3.2621181011,50.9551086426],"type":"Point"}
}