{
  "type": "Feature",
  "properties": {
    "iso:country":"BE",
    "sg:address":"Stationsstraat 85",
    "sg:city":"Lebbeke",
    "sg:orig_category":"Grands magasins",
    "sg:phone":"+32 52 41 02 54",
    "sg:postcode":"9280",
    "sg:province":"Oost-Vlaanderen",
    "wof:name":"Beeckman - Deneve",
    "wof:placetype":"venue"
},
  "geometry": {"coordinates":[4.1339578629,51.0053367615],"type":"Point"}
}