{
  "type": "Feature",
  "properties": {
    "addr:full":"Bospoort 16 Maaseik Limburg 3680",
    "addr:housenumber":"16",
    "addr:postcode":"3680",
    "addr:street":"Bospoort",
    "iso:country":"BE",
    "sg:address":"Bospoort 16",
    "sg:city":"Maaseik",
    "sg:classifiers":[
        {
            "category":"Shopping",
            "subcategory":"Jewelry",
            "type":"Retail Goods"
        }
    ],
    "sg:phone":"+32 89 56 58 49",
    "sg:postcode":"3680",
    "sg:province":"Limburg",
    "sg:tags":[
        "jeweller",
        "-"
    ],
    "wof:name":"Plaghki Juwelier",
    "wof:placetype":"venue"
},
  "geometry": {"coordinates":[5.7902159691,51.0948562622],"type":"Point"}
}