{
  "type": "Feature",
  "properties": {
    "addr:full":"Kortrijkstraat 98 Ingelmunster West-Vlaanderen 8770",
    "addr:housenumber":"98",
    "addr:postcode":"8770",
    "addr:street":"Kortrijkstraat",
    "iso:country":"BE",
    "sg:address":"Kortrijkstraat 98",
    "sg:city":"Ingelmunster",
    "sg:classifiers":[
        {
            "category":"Building & Trades",
            "subcategory":"Pest Control",
            "type":"Services"
        }
    ],
    "sg:phone":"+32 51 30 76 66",
    "sg:postcode":"8770",
    "sg:province":"West-Vlaanderen",
    "sg:tags":[
        "painting",
        "contractor"
    ],
    "wof:name":"Rooryck L",
    "wof:placetype":"venue"
},
  "geometry": {"coordinates":[3.2605090141,50.907245636],"type":"Point"}
}