{
  "type": "Feature",
  "properties": {
    "iso:country":"BE",
    "sg:address":"Rue Maur. Van Rolleghem 33b1",
    "sg:city":"Jette/jette",
    "sg:orig_category":"Plomberie, chauffage and installations sanitaires",
    "sg:phone":"+32 2 479 01 44",
    "sg:postcode":"1090",
    "sg:province":"Bruxelles-Capitale",
    "wof:name":"Eric Coppens",
    "wof:placetype":"venue"
},
  "geometry": {"coordinates":[4.3224811554,50.8907928467],"type":"Point"}
}