{
  "type": "Feature",
  "properties": {
    "iso:country":"BE",
    "sg:address":"Steenweg Op Turnhout 39",
    "sg:city":"Oud-turnhout",
    "sg:classifiers":[
        {
            "category":"Banks & Credit Unions",
            "subcategory":"Financial Services",
            "type":"Services"
        }
    ],
    "sg:phone":"+32 14 45 37 80",
    "sg:postcode":"2360",
    "sg:province":"Antwerpen",
    "sg:tags":[
        "loan",
        "mortgage"
    ],
    "wof:name":"Haesen Patrick",
    "wof:placetype":"venue"
},
  "geometry": {"coordinates":[4.9780058861,51.3194084167],"type":"Point"}
}