{
  "type": "Feature",
  "properties": {
    "iso:country":"BE",
    "sg:address":"Liebaardstraat 74",
    "sg:city":"Waregem",
    "sg:orig_category":"Notarissen",
    "sg:phone":"+32 56 71 24 95",
    "sg:postcode":"8792",
    "sg:province":"West-Vlaanderen",
    "wof:name":"M. De Gomme",
    "wof:placetype":"venue"
},
  "geometry": {"coordinates":[3.3523569107,50.8842124939],"type":"Point"}
}