{
  "type": "Feature",
  "properties": {
    "iso:country":"BE",
    "sg:address":"Graanmolenstraat 12",
    "sg:city":"Assenede",
    "sg:orig_category":"Artsen and specialisten",
    "sg:phone":"+32 9 373 91 50",
    "sg:postcode":"9968",
    "sg:province":"Oost-Vlaanderen",
    "wof:name":"A. Anckaert",
    "wof:placetype":"venue"
},
  "geometry": {"coordinates":[3.6887938976,51.1923027039],"type":"Point"}
}