{
  "type": "Feature",
  "properties": {
    "iso:country":"BE",
    "sg:address":"Route No 624 Wallonie 624",
    "sg:city":"Hautrage",
    "sg:orig_category":"Resin Glues",
    "sg:phone":"+32 65 52 92 11",
    "sg:postcode":"7334",
    "sg:province":"Hainaut",
    "wof:name":"Woodchem Europe S.a.",
    "wof:placetype":"venue"
},
  "geometry": {"coordinates":[3.7644500732,50.479675293],"type":"Point"}
}