{
  "type": "Feature",
  "properties": {
    "iso:country":"BE",
    "sg:address":"Herentalse Steenweg 44",
    "sg:city":"Herenthout",
    "sg:classifiers":[
        {
            "category":"Retail",
            "subcategory":"Repair Shop",
            "type":"Services"
        }
    ],
    "sg:phone":"+32 14 51 76 16",
    "sg:postcode":"2270",
    "sg:province":"Antwerpen",
    "sg:tags":[
        "radio",
        "television",
        "-",
        "maintenance"
    ],
    "wof:name":"Video Service Bvba",
    "wof:placetype":"venue"
},
  "geometry": {"coordinates":[4.7786941528,51.1420288086],"type":"Point"}
}