{
  "type": "Feature",
  "properties": {
    "iso:country":"BE",
    "sg:address":"Oudstrijderslaan 2",
    "sg:city":"Kraainem/kraainem",
    "sg:orig_category":"Apotheken",
    "sg:phone":"+32 2 720 16 38",
    "sg:postcode":"1950",
    "sg:province":"Vlaams-Brabant",
    "wof:name":"E. Wils",
    "wof:placetype":"venue"
},
  "geometry": {"coordinates":[4.4638152122,50.8623313904],"type":"Point"}
}