{
  "type": "Feature",
  "properties": {
    "iso:country":"BE",
    "sg:address":"Rue Du Pont Neuf 48",
    "sg:city":"Charleroi",
    "sg:orig_category":"Agences d\u00b4interim and personnel temporaire",
    "sg:phone":"+32 71 20 72 10",
    "sg:postcode":"6000",
    "sg:province":"Hainaut",
    "wof:name":"Unique Interim",
    "wof:placetype":"venue"
},
  "geometry": {"coordinates":[4.4467201233,50.407535553],"type":"Point"}
}