{
  "type": "Feature",
  "properties": {
    "iso:country":"BE",
    "sg:address":"Kachtemsestraat 142",
    "sg:city":"Izegem",
    "sg:classifiers":[
        {
            "category":"Shopping",
            "subcategory":"Bicycles & Sporting Goods",
            "type":"Retail Goods"
        }
    ],
    "sg:phone":"+32 51 30 43 07",
    "sg:postcode":"8870",
    "sg:province":"West-Vlaanderen",
    "sg:tags":[
        "-"
    ],
    "wof:name":"Deprauw",
    "wof:placetype":"venue"
},
  "geometry": {"coordinates":[3.1957030296,50.9318962097],"type":"Point"}
}