{
  "type": "Feature",
  "properties": {
    "iso:country":"BE",
    "sg:address":"Amelbergstraat 74",
    "sg:city":"Zandhoven",
    "sg:orig_category":"HUISBRANDOLIE Royal Canin Tuinbenodigdheden",
    "sg:phone":"+32 3 484 47 57",
    "sg:postcode":"2240",
    "sg:province":"Antwerpen",
    "wof:name":"Garden Cenetr. Verelst- Cools Dirk",
    "wof:placetype":"venue"
},
  "geometry": {"coordinates":[4.6657252312,51.21875],"type":"Point"}
}