{
  "type": "Feature",
  "properties": {
    "addr:full":"Hollevoordestraat 12ba Zedelgem West-Vlaanderen 8210",
    "addr:housenumber":"12ba",
    "addr:postcode":"8210",
    "addr:street":"Hollevoordestraat",
    "iso:country":"BE",
    "sg:address":"Hollevoordestraat 12ba",
    "sg:city":"Zedelgem",
    "sg:orig_category":"Artiesten and kunstenaars",
    "sg:phone":"+32 50 20 01 68",
    "sg:postcode":"8210",
    "sg:province":"West-Vlaanderen",
    "wof:name":"S. Christensen",
    "wof:placetype":"venue"
},
  "geometry": {"coordinates":[3.1354930401,51.1195602417],"type":"Point"}
}