{
  "type": "Feature",
  "properties": {
    "iso:country":"BE",
    "sg:address":"Populierenlaan 76",
    "sg:city":"Bredene",
    "sg:orig_category":"Imprimeries and copyshops",
    "sg:phone":"+32 59 32 30 25",
    "sg:postcode":"8450",
    "sg:province":"West-Vlaanderen",
    "wof:name":"Deleu",
    "wof:placetype":"venue"
},
  "geometry": {"coordinates":[2.9650669098,51.2423973083],"type":"Point"}
}