{
  "type": "Feature",
  "properties": {
    "iso:country":"BE",
    "sg:address":"Avenue De La Toison D\u00b4or 31-32",
    "sg:city":"Elsene/ixelles",
    "sg:orig_category":"Services de t\u00e9l\u00e9communications. Mobistar Centres",
    "sg:phone":"+32 2 502 63 55",
    "sg:postcode":"1050",
    "sg:province":"Bruxelles-Capitale",
    "wof:name":"Mobistar Center Toison D\u00b4or",
    "wof:placetype":"venue"
},
  "geometry": {"coordinates":[4.3577098846,50.8363456726],"type":"Point"}
}