{
  "type": "Feature",
  "properties": {
    "iso:country":"BE",
    "sg:address":"Rijksweg 858",
    "sg:city":"Dilsen-stokkem",
    "sg:orig_category":"V\u00e9hicules automobiles. Taxis services sp\u00e9ciaux. Entretien and r\u00e9parations de voitures",
    "sg:phone":"+32 89 56 60 15",
    "sg:postcode":"3650",
    "sg:province":"Limburg",
    "wof:name":"Pergens Motors",
    "wof:placetype":"venue"
},
  "geometry": {"coordinates":[5.7348308563,51.0439147949],"type":"Point"}
}