{
  "type": "Feature",
  "properties": {
    "addr:full":"Lutselusstraat 180 Diepenbeek Limburg 3590",
    "addr:housenumber":"180",
    "addr:postcode":"3590",
    "addr:street":"Lutselusstraat",
    "iso:country":"BE",
    "sg:address":"Lutselusstraat 180",
    "sg:city":"Diepenbeek",
    "sg:orig_category":"Kapsalons Schoonheidssalons",
    "sg:phone":"+32 11 32 12 97",
    "sg:postcode":"3590",
    "sg:province":"Limburg",
    "wof:name":"Maria Degraen",
    "wof:placetype":"venue"
},
  "geometry": {"coordinates":[5.457930088,50.9132499695],"type":"Point"}
}