{
  "type": "Feature",
  "properties": {
    "addr:full":"Augustijnslei 147 Brasschaat Antwerpen 2930",
    "addr:housenumber":"147",
    "addr:postcode":"2930",
    "iso:country":"BE",
    "sg:address":"Augustijnslei 147",
    "sg:city":"Brasschaat",
    "sg:classifiers":[
        {
            "category":"Food & Beverages",
            "subcategory":"Groceries & Convenience Stores",
            "type":"Retail Goods"
        }
    ],
    "sg:phone":"+32 3 651 84 53",
    "sg:postcode":"2930",
    "sg:province":"Antwerpen",
    "sg:tags":[
        "grocer"
    ],
    "wof:name":"Voeding Giebens",
    "wof:placetype":"venue"
},
  "geometry": {"coordinates":[4.4885220528,51.2967643738],"type":"Point"}
}