{
  "type": "Feature",
  "properties": {
    "iso:country":"BE",
    "sg:address":"Rue Paul Verlaine 20",
    "sg:city":"Bouillon",
    "sg:orig_category":"Hout and afgeleiden Gh Houtbewerking and -behandeling",
    "sg:phone":"+32 61 46 86 16",
    "sg:postcode":"6838",
    "sg:province":"Luxembourg",
    "wof:name":"Scierie Danloy",
    "wof:placetype":"venue"
},
  "geometry": {"coordinates":[5.0071702003,49.7973403931],"type":"Point"}
}