{
  "type": "Feature",
  "properties": {
    "addr:full":"Elshaag 14 Genk Limburg 3600",
    "addr:housenumber":"14",
    "addr:postcode":"3600",
    "addr:street":"Elshaag",
    "iso:country":"BE",
    "sg:address":"Elshaag 14",
    "sg:city":"Genk",
    "sg:orig_category":"Etalage- and showroomontwerpers",
    "sg:phone":"+32 89 36 25 00",
    "sg:postcode":"3600",
    "sg:province":"Limburg",
    "wof:name":"Jacobus Boer",
    "wof:placetype":"venue"
},
  "geometry": {"coordinates":[5.4733657837,50.9571495056],"type":"Point"}
}