{
  "type": "Feature",
  "properties": {
    "iso:country":"BE",
    "sg:address":"Huickstraat 6",
    "sg:city":"Stekene",
    "sg:orig_category":"Voedingsspeciaalzaken",
    "sg:phone":"+32 3 789 27 26",
    "sg:postcode":"9190",
    "sg:province":"Oost-Vlaanderen",
    "wof:name":"De Lotusbloem",
    "wof:placetype":"venue"
},
  "geometry": {"coordinates":[4.0305490494,51.1987113953],"type":"Point"}
}