{
  "type": "Feature",
  "properties": {
    "addr:full":"Hasseltsestraat 98 Diest Vlaams-Brabant 3290",
    "addr:housenumber":"98",
    "addr:postcode":"3290",
    "addr:street":"Hasseltsestraat",
    "iso:country":"BE",
    "sg:address":"Hasseltsestraat 98",
    "sg:city":"Diest",
    "sg:classifiers":[
        {
            "category":"Banks & Credit Unions",
            "subcategory":"Bank",
            "type":"Services"
        }
    ],
    "sg:phone":"+32 13 31 30 92",
    "sg:postcode":"3290",
    "sg:province":"Vlaams-Brabant",
    "wof:name":"Caisse Nationale De, Credit Professionnel",
    "wof:placetype":"venue"
},
  "geometry": {"coordinates":[5.0554280281,50.9799613953],"type":"Point"}
}