{
  "type": "Feature",
  "properties": {
    "addr:full":"Pontstraat 20 Zulte Oost-Vlaanderen 9870",
    "addr:housenumber":"20",
    "addr:postcode":"9870",
    "addr:street":"Pontstraat",
    "iso:country":"BE",
    "sg:address":"Pontstraat 20",
    "sg:city":"Zulte",
    "sg:orig_category":"Enseignement maternel and primaire",
    "sg:phone":"+32 9 388 91 82",
    "sg:postcode":"9870",
    "sg:province":"Oost-Vlaanderen",
    "wof:name":"Vrije Kleuterschool",
    "wof:placetype":"venue"
},
  "geometry": {"coordinates":[3.438380003,50.9211883545],"type":"Point"}
}