{
  "type": "Feature",
  "properties": {
    "iso:country":"BE",
    "sg:address":"Leopold Ii Laan 235",
    "sg:city":"Koksijde (oostduinkerke)",
    "sg:orig_category":"Newspapers, magazines, periodicals - Distribution",
    "sg:phone":"+32 58 51 15 09",
    "sg:postcode":"8670",
    "sg:province":"West-Vlaanderen",
    "wof:name":"Unex",
    "wof:placetype":"venue"
},
  "geometry": {"coordinates":[2.6720569134,51.1313285828],"type":"Point"}
}