{
  "type": "Feature",
  "properties": {
    "iso:country":"BE",
    "sg:address":"Hoenderstraat 24",
    "sg:city":"Wetteren",
    "sg:orig_category":"Boekenuitgeverijen Drukkerijen and copyshops",
    "sg:phone":"+32 9 369 15 63",
    "sg:postcode":"9230",
    "sg:province":"Oost-Vlaanderen",
    "wof:name":"Uitgeverij Universa",
    "wof:placetype":"venue"
},
  "geometry": {"coordinates":[3.8821570873,51.0041313171],"type":"Point"}
}