{
  "type": "Feature",
  "properties": {
    "iso:country":"BE",
    "sg:address":"Rue De L'avenir 43",
    "sg:city":"Bruxelles (molenbeek-saint-jean)",
    "sg:classifiers":[
        {
            "category":"Shopping",
            "subcategory":"Clothing, Apparel, & Fashions",
            "type":"Retail Goods"
        }
    ],
    "sg:phone":"+32 2 412 55 55",
    "sg:postcode":"1080",
    "sg:province":"Bruxelles-Capitale",
    "sg:tags":[
        "supply",
        "material",
        "-",
        "access",
        "ready-made",
        "clothing"
    ],
    "wof:name":"Euro Buttons Nv",
    "wof:placetype":"venue"
},
  "geometry": {"coordinates":[4.3424267769,50.8553352356],"type":"Point"}
}