{
  "type": "Feature",
  "properties": {
    "addr:full":"Leopoldplein 12 Menen West-Vlaanderen 8930",
    "addr:housenumber":"12",
    "addr:postcode":"8930",
    "addr:street":"Leopoldplein",
    "iso:country":"BE",
    "sg:address":"Leopoldplein 12",
    "sg:city":"Menen",
    "sg:classifiers":[
        {
            "category":"Health Services",
            "subcategory":"Nursing And Care Facility",
            "type":"Services"
        }
    ],
    "sg:phone":"+32 56 52 11 11",
    "sg:postcode":"8930",
    "sg:province":"West-Vlaanderen",
    "sg:tags":[
        "public"
    ],
    "wof:name":"O.c.m.w.",
    "wof:placetype":"venue"
},
  "geometry": {"coordinates":[3.1270198822,50.7959365845],"type":"Point"}
}