{
  "type": "Feature",
  "properties": {
    "addr:full":"Toekomstlaan 51 Grobbendonk Antwerpen 2280",
    "addr:housenumber":"51",
    "addr:postcode":"2280",
    "addr:street":"Toekomstlaan",
    "iso:country":"BE",
    "sg:address":"Toekomstlaan 51",
    "sg:city":"Grobbendonk",
    "sg:classifiers":[
        {
            "category":"Social Services",
            "subcategory":"Job Training",
            "type":"Services"
        }
    ],
    "sg:phone":"+32 14 84 27 68",
    "sg:postcode":"2280",
    "sg:province":"Antwerpen",
    "sg:tags":[
        "personnel"
    ],
    "wof:name":"B1 Opleidingscentrum",
    "wof:placetype":"venue"
},
  "geometry": {"coordinates":[4.7832999229,51.1687164307],"type":"Point"}
}