{
  "type": "Feature",
  "properties": {
    "iso:country":"BE",
    "sg:address":"Radiostraat 89",
    "sg:city":"Tongeren",
    "sg:classifiers":[
        {
            "category":"Professional",
            "subcategory":"Accounting & Tax Preparation",
            "type":"Services"
        }
    ],
    "sg:phone":"+32 12 26 19 78",
    "sg:postcode":"3700",
    "sg:province":"Limburg",
    "sg:tags":[
        "accountant"
    ],
    "wof:name":"Houbrechts M",
    "wof:placetype":"venue"
},
  "geometry": {"coordinates":[5.4707698822,50.7886581421],"type":"Point"}
}