{
  "type": "Feature",
  "properties": {
    "addr:full":"Logebeekstraat 2 Gingelom Limburg 3891",
    "addr:housenumber":"2",
    "addr:postcode":"3891",
    "addr:street":"Logebeekstraat",
    "iso:country":"BE",
    "sg:address":"Logebeekstraat 2",
    "sg:city":"Gingelom",
    "sg:orig_category":"Installatie van metalen schrijnwerk Metaalbehandeling and -bekleding",
    "sg:phone":"+32 11 48 66 80",
    "sg:postcode":"3891",
    "sg:province":"Limburg",
    "wof:name":"Froyen",
    "wof:placetype":"venue"
},
  "geometry": {"coordinates":[5.2143177986,50.7582168579],"type":"Point"}
}