{
  "type": "Feature",
  "properties": {
    "addr:full":"Wirzfeld 77 Bullingen Li\u00e8ge 4761",
    "addr:housenumber":"77",
    "addr:postcode":"4761",
    "addr:street":"Wirzfeld",
    "iso:country":"BE",
    "sg:address":"Wirzfeld 77",
    "sg:city":"Bullingen",
    "sg:orig_category":"Maisons de vacances",
    "sg:phone":"+32 80 64 74 59",
    "sg:postcode":"4761",
    "sg:province":"Li\u00e8ge",
    "wof:name":"O. Schmidt",
    "wof:placetype":"venue"
},
  "geometry": {"coordinates":[6.2963399887,50.4319496155],"type":"Point"}
}