{
  "type": "Feature",
  "properties": {
    "addr:full":"Rue De Dalhem 15 Vise Li\u00e8ge 4600",
    "addr:housenumber":"15",
    "addr:postcode":"4600",
    "addr:street":"Rue De Dalhem",
    "iso:country":"BE",
    "sg:address":"Rue De Dalhem 15",
    "sg:city":"Vise",
    "sg:orig_category":"Supermarch\u00e9s",
    "sg:phone":"+32 4 379 85 41",
    "sg:postcode":"4600",
    "sg:province":"Li\u00e8ge",
    "wof:name":"Ad Delhaize",
    "wof:placetype":"venue"
},
  "geometry": {"coordinates":[5.6984410286,50.7302589417],"type":"Point"}
}