{
  "type": "Feature",
  "properties": {
    "addr:full":"Rue J-b Lepage 30 Sint-pieters-woluwe/woluwe-sai Bruxelles-Capitale 1150",
    "addr:housenumber":"30",
    "addr:postcode":"1150",
    "addr:street":"Rue J-B Lepage",
    "iso:country":"BE",
    "sg:address":"Rue J-b Lepage 30",
    "sg:city":"Sint-pieters-woluwe/woluwe-sai",
    "sg:orig_category":"Loodgieterij, verwarming and sanitaire installaties",
    "sg:phone":"+32 2 779 83 93",
    "sg:postcode":"1150",
    "sg:province":"Bruxelles-Capitale",
    "wof:name":"Feman Sprl",
    "wof:placetype":"venue"
},
  "geometry": {"coordinates":[4.4305348396,50.837020874],"type":"Point"}
}