{
  "type": "Feature",
  "properties": {
    "addr:full":"Schaliehoevestr. 14 Heist-op-den-berg Antwerpen 2220",
    "addr:housenumber":"14",
    "addr:postcode":"2220",
    "addr:street":"Schaliehoevestr.",
    "iso:country":"BE",
    "sg:address":"Schaliehoevestr. 14",
    "sg:city":"Heist-op-den-berg",
    "sg:classifiers":[
        {
            "category":"Wholesale",
            "subcategory":"Machinery & Supplies",
            "type":"Manufacturing & Wholesale Goods"
        }
    ],
    "sg:phone":"+32 15 55 54 61",
    "sg:postcode":"2220",
    "sg:province":"Antwerpen",
    "sg:tags":[
        "food",
        "processing",
        "-",
        "machine",
        "equipment",
        "engineering",
        "mechanical"
    ],
    "wof:name":"Werkhuizen J. Verbeemen Bvba",
    "wof:placetype":"venue"
},
  "geometry": {"coordinates":[4.7061500549,51.0558395386],"type":"Point"}
}