{
  "type": "Feature",
  "properties": {
    "iso:country":"BE",
    "sg:address":"Lindeweg 28",
    "sg:city":"Zoutleeuw",
    "sg:classifiers":[
        {
            "category":"Arena",
            "subcategory":"Sports Club",
            "type":"Entertainment"
        }
    ],
    "sg:phone":"+32 11 78 53 03",
    "sg:postcode":"3440",
    "sg:province":"Vlaams-Brabant",
    "sg:tags":[
        "de"
    ],
    "wof:name":"Satori Tienen",
    "wof:placetype":"venue"
},
  "geometry": {"coordinates":[5.1338338852,50.8494682312],"type":"Point"}
}