{
  "type": "Feature",
  "properties": {
    "addr:full":"Rue D'erbaut 8 Lens Hainaut 7870",
    "addr:housenumber":"8",
    "addr:postcode":"7870",
    "addr:street":"Rue D'Erbaut",
    "iso:country":"BE",
    "sg:address":"Rue D'erbaut 8",
    "sg:city":"Lens",
    "sg:classifiers":[
        {
            "category":"Health Services",
            "subcategory":"Health Practitioner",
            "type":"Services"
        }
    ],
    "sg:phone":"+32 65 35 38 11",
    "sg:postcode":"7870",
    "sg:province":"Hainaut",
    "sg:tags":[
        "physiotherapist"
    ],
    "wof:name":"Dutrannoit Anne-marie",
    "wof:placetype":"venue"
},
  "geometry": {"coordinates":[3.8827950954,50.5531845093],"type":"Point"}
}