{
  "type": "Feature",
  "properties": {
    "addr:full":"Route De Cockaifagne 22 Stavelot Li\u00e8ge 4970",
    "addr:housenumber":"22",
    "addr:postcode":"4970",
    "addr:street":"Route De Cockaifagne",
    "iso:country":"BE",
    "sg:address":"Route De Cockaifagne 22",
    "sg:city":"Stavelot",
    "sg:orig_category":"Fotografen and fotostudio's",
    "sg:phone":"+32 87 27 58 27",
    "sg:postcode":"4970",
    "sg:province":"Li\u00e8ge",
    "wof:name":"Patrick Tips",
    "wof:placetype":"venue"
},
  "geometry": {"coordinates":[5.9846858978,50.4852256775],"type":"Point"}
}