{
  "type": "Feature",
  "properties": {
    "addr:full":"Schoolstraat 15 Moerbeke (moerbeke-waas) Oost-Vlaanderen 9180",
    "addr:housenumber":"15",
    "addr:postcode":"9180",
    "addr:street":"Schoolstraat",
    "iso:country":"BE",
    "sg:address":"Schoolstraat 15",
    "sg:city":"Moerbeke (moerbeke-waas)",
    "sg:classifiers":[
        {
            "category":"Bakery",
            "type":"Food & Drink"
        }
    ],
    "sg:phone":"+32 3 779 87 33",
    "sg:postcode":"9180",
    "sg:province":"Oost-Vlaanderen",
    "sg:tags":[
        "confectioner",
        "baker"
    ],
    "wof:name":"De Moor R",
    "wof:placetype":"venue"
},
  "geometry": {"coordinates":[3.977107048,51.2248687744],"type":"Point"}
}