{
  "type": "Feature",
  "properties": {
    "addr:full":"Rue Des Archers 4 Mons Hainaut 7000",
    "addr:housenumber":"4",
    "addr:postcode":"7000",
    "addr:street":"Rue Des Archers;Hainaut",
    "iso:country":"BE",
    "sg:address":"Rue Des Archers 4",
    "sg:city":"Mons",
    "sg:classifiers":[
        {
            "category":"Banks & Credit Unions",
            "subcategory":"Investment Brokerage",
            "type":"Services"
        }
    ],
    "sg:phone":"+32 65 33 59 71",
    "sg:postcode":"7000",
    "sg:province":"Hainaut",
    "wof:name":"Mons-assur Sprl",
    "wof:placetype":"venue"
},
  "geometry": {"coordinates":[3.9577760696,50.4524497986],"type":"Point"}
}