{
  "type": "Feature",
  "properties": {
    "addr:full":"Aartstraat 62 Aalst Oost-Vlaanderen 9310",
    "addr:housenumber":"62",
    "addr:postcode":"9310",
    "addr:street":"Aartstraat",
    "iso:country":"BE",
    "sg:address":"Aartstraat 62",
    "sg:city":"Aalst",
    "sg:orig_category":"Bouwmaterialen Gh",
    "sg:phone":"+32 53 21 46 61",
    "sg:postcode":"9310",
    "sg:province":"Oost-Vlaanderen",
    "wof:name":"A&j De Witte Gebroeders",
    "wof:placetype":"venue"
},
  "geometry": {"coordinates":[4.0647702217,50.9771003723],"type":"Point"}
}