{
  "type": "Feature",
  "properties": {
    "iso:country":"BE",
    "sg:address":"Pelikaanstraat 46",
    "sg:city":"Evergem",
    "sg:orig_category":"Elektrische installaties voor woningen",
    "sg:phone":"+32 9 344 71 09",
    "sg:postcode":"9940",
    "sg:province":"Oost-Vlaanderen",
    "wof:name":"Didier Majeleine",
    "wof:placetype":"venue"
},
  "geometry": {"coordinates":[3.7631480694,51.1693305969],"type":"Point"}
}