{
  "type": "Feature",
  "properties": {
    "addr:full":"Rue Pont Des Chaines 4 Huy Li\u00e8ge 4500",
    "addr:housenumber":"4",
    "addr:postcode":"4500",
    "addr:street":"Rue Pont Des Chaines",
    "iso:country":"BE",
    "sg:address":"Rue Pont Des Chaines 4",
    "sg:city":"Huy",
    "sg:orig_category":"Brood, gebak and snoepgoed Zuivelproducten",
    "sg:phone":"+32 85 21 39 28",
    "sg:postcode":"4500",
    "sg:province":"Li\u00e8ge",
    "wof:name":"Niessen Boulangerie Patisserie",
    "wof:placetype":"venue"
},
  "geometry": {"coordinates":[5.2394890785,50.5187110901],"type":"Point"}
}