{
  "type": "Feature",
  "properties": {
    "addr:full":"Chauss\u00e9e De Devant La Ville 3 P\u00e9ruwelz (callenelle) Hainaut 7604",
    "addr:housenumber":"3",
    "addr:postcode":"7604",
    "addr:street":"Chausse\u0301E De Devant La Ville",
    "iso:country":"BE",
    "sg:address":"Chauss\u00e9e De Devant La Ville 3",
    "sg:city":"P\u00e9ruwelz (callenelle)",
    "sg:orig_category":"Non-Classified Establishments",
    "sg:phone":"+32 69 77 38 16",
    "sg:postcode":"7604",
    "sg:province":"Hainaut",
    "wof:name":"Pro Pac Petfoods-s.i.p.o.c.",
    "wof:placetype":"venue"
},
  "geometry": {"coordinates":[3.5207300186,50.5319252014],"type":"Point"}
}