{
  "type": "Feature",
  "properties": {
    "addr:full":"Industrielaan 7 Maldegem Oost-Vlaanderen 9990",
    "addr:housenumber":"7",
    "addr:postcode":"9990",
    "addr:street":"Industrielaan",
    "iso:country":"BE",
    "sg:address":"Industrielaan 7",
    "sg:city":"Maldegem",
    "sg:orig_category":"Meubles D\u00e9taillants, Am\u00e9nagement de B\u00e2timents et de Cuisines",
    "sg:phone":"+32 50 71 99 61",
    "sg:postcode":"9990",
    "sg:province":"Oost-Vlaanderen",
    "wof:name":"Luxor",
    "wof:placetype":"venue"
},
  "geometry": {"coordinates":[3.4647979736,51.1995620728],"type":"Point"}
}