{
  "type": "Feature",
  "properties": {
    "addr:full":"Quai De L'entrep\u00f4t 11 Ath Hainaut 7800",
    "addr:housenumber":"11",
    "addr:postcode":"7800",
    "addr:street":"Quai De L'Entrepo \u0302T",
    "iso:country":"BE",
    "sg:address":"Quai De L'entrep\u00f4t 11",
    "sg:city":"Ath",
    "sg:classifiers":[
        {
            "category":"Home & Garden",
            "subcategory":"Garden Supply",
            "type":"Retail Goods"
        }
    ],
    "sg:phone":"+32 68 28 19 19",
    "sg:postcode":"7800",
    "sg:province":"Hainaut",
    "wof:name":"Hobby Vert Ath",
    "wof:placetype":"venue"
},
  "geometry": {"coordinates":[3.7772459984,50.6258850098],"type":"Point"}
}