{
  "type": "Feature",
  "properties": {
    "iso:country":"BE",
    "sg:address":"Stadenstraat 33",
    "sg:city":"Kortemark (zarren-werken)",
    "sg:orig_category":"Non-Classified Establishments",
    "sg:phone":"+32 51 56 66 79",
    "sg:postcode":"8610",
    "sg:province":"West-Vlaanderen",
    "wof:name":"Theuninck Firma Bvba",
    "wof:placetype":"venue"
},
  "geometry": {"coordinates":[2.9619710445,51.0160675049],"type":"Point"}
}