{
  "type": "Feature",
  "properties": {
    "iso:country":"BE",
    "sg:address":"Rue Cachette Hanicq 1",
    "sg:city":"Celles",
    "sg:orig_category":"Kapsalons",
    "sg:phone":"+32 69 85 91 59",
    "sg:postcode":"7760",
    "sg:province":"Hainaut",
    "wof:name":"Coiffure Doroth\u00c9e",
    "wof:placetype":"venue"
},
  "geometry": {"coordinates":[3.4797780514,50.6869735718],"type":"Point"}
}