{
  "type": "Feature",
  "properties": {
    "addr:full":"Werviksestraat 53 Ieper (zillebeke) West-Vlaanderen 8902",
    "addr:housenumber":"53",
    "addr:postcode":"8902",
    "addr:street":"Werviksestraat",
    "iso:country":"BE",
    "sg:address":"Werviksestraat 53",
    "sg:city":"Ieper (zillebeke)",
    "sg:orig_category":"Non-Classified Establishments",
    "sg:phone":"+32 57 20 28 63",
    "sg:postcode":"8902",
    "sg:province":"West-Vlaanderen",
    "wof:name":"Devaltex Bvba",
    "wof:placetype":"venue"
},
  "geometry": {"coordinates":[2.9259150028,50.8319015503],"type":"Point"}
}