{
  "type": "Feature",
  "properties": {
    "iso:country":"BE",
    "sg:address":"Leiestraat 36",
    "sg:city":"Kortrijk",
    "sg:classifiers":[
        {
            "category":"Deli",
            "type":"Food & Drink"
        }
    ],
    "sg:phone":"+32 56 22 68 17",
    "sg:postcode":"8500",
    "sg:province":"West-Vlaanderen",
    "sg:tags":[
        "delicatessen"
    ],
    "wof:name":"Hannon",
    "wof:placetype":"venue"
},
  "geometry": {"coordinates":[3.2647180557,50.8289985657],"type":"Point"}
}