{
  "type": "Feature",
  "properties": {
    "addr:full":"Rode Beukendreef 11 Zaventem (nossegem) Vlaams-Brabant 1930",
    "addr:housenumber":"11",
    "addr:postcode":"1930",
    "addr:street":"Rode Beukendreef",
    "iso:country":"BE",
    "sg:address":"Rode Beukendreef 11",
    "sg:city":"Zaventem (nossegem)",
    "sg:classifiers":[
        {
            "category":"Health Services",
            "subcategory":"Dentist",
            "type":"Services"
        }
    ],
    "sg:phone":"+32 2 757 90 16",
    "sg:postcode":"1930",
    "sg:province":"Vlaams-Brabant",
    "wof:name":"Roosen Lieve",
    "wof:placetype":"venue"
},
  "geometry": {"coordinates":[4.5154509544,50.8783149719],"type":"Point"}
}