{
  "type": "Feature",
  "properties": {
    "addr:full":"Rue Du Pige 85 Chatelet Hainaut 6200",
    "addr:housenumber":"85",
    "addr:postcode":"6200",
    "addr:street":"Rue Du Pige;Hainaut",
    "iso:country":"BE",
    "sg:address":"Rue Du Pige 85",
    "sg:city":"Chatelet",
    "sg:orig_category":"Artsen and specialisten",
    "sg:phone":"+32 71 39 71 33",
    "sg:postcode":"6200",
    "sg:province":"Hainaut",
    "wof:name":"Francesco Cacciatore",
    "wof:placetype":"venue"
},
  "geometry": {"coordinates":[4.5241708755,50.4071388245],"type":"Point"}
}