{
  "type": "Feature",
  "properties": {
    "addr:full":"Bld Alfred De Fontaine 11b07 Charleroi Hainaut 6000",
    "addr:housenumber":"11b07",
    "addr:postcode":"6000",
    "addr:street":"Bld Alfred De Fontaine;Hainaut",
    "iso:country":"BE",
    "sg:address":"Bld Alfred De Fontaine 11b07",
    "sg:city":"Charleroi",
    "sg:orig_category":"Advocaten and juridische adviseurs",
    "sg:phone":"+32 71 30 68 23",
    "sg:postcode":"6000",
    "sg:province":"Hainaut",
    "wof:name":"Sophie Labeye",
    "wof:placetype":"venue"
},
  "geometry": {"coordinates":[4.4463200569,50.4102516174],"type":"Point"}
}