{
  "type": "Feature",
  "properties": {
    "iso:country":"BE",
    "sg:address":"Rue Des Combattants 57",
    "sg:city":"Tubize",
    "sg:orig_category":"D\u00e9taillants en pi\u00e8ces and accessoires de voitures",
    "sg:phone":"+32 2 355 55 49",
    "sg:postcode":"1480",
    "sg:province":"Brabant Wallon",
    "wof:name":"Distri Pneus Jantes",
    "wof:placetype":"venue"
},
  "geometry": {"coordinates":[4.2355499268,50.6799812317],"type":"Point"}
}