{
  "type": "Feature",
  "properties": {
    "addr:full":"Rue Du Peuple 16 Saint-ghislain Hainaut 7333",
    "addr:housenumber":"16",
    "addr:postcode":"7333",
    "addr:street":"Rue Du Peuple;Hainaut",
    "iso:country":"BE",
    "sg:address":"Rue Du Peuple 16",
    "sg:city":"Saint-ghislain",
    "sg:classifiers":[
        {
            "category":"Personal",
            "subcategory":"Beauty Salon",
            "type":"Services"
        }
    ],
    "sg:phone":"+32 65 64 35 79",
    "sg:postcode":"7333",
    "sg:province":"Hainaut",
    "sg:tags":[
        "de",
        "coiffure"
    ],
    "wof:name":"Coiffure Christine",
    "wof:placetype":"venue"
},
  "geometry": {"coordinates":[3.8111400604,50.4655151367],"type":"Point"}
}