{
  "type": "Feature",
  "properties": {
    "addr:full":"Rue De La For\u00cat 74 Marche-en-famenne Luxembourg 6900",
    "addr:housenumber":"74",
    "addr:postcode":"6900",
    "addr:street":"Rue De La Fore\u0302T",
    "iso:country":"BE",
    "sg:address":"Rue De La For\u00cat 74",
    "sg:city":"Marche-en-famenne",
    "sg:orig_category":"Tuinen",
    "sg:phone":"+32 84 31 42 31",
    "sg:postcode":"6900",
    "sg:province":"Luxembourg",
    "wof:name":"L' Odyss\u00c9e",
    "wof:placetype":"venue"
},
  "geometry": {"coordinates":[5.3854517937,50.2167167664],"type":"Point"}
}