{
  "type": "Feature",
  "properties": {
    "addr:full":"Avenue Everard 40 Bruxelles (forest) Bruxelles-Capitale 1190",
    "addr:housenumber":"40",
    "addr:postcode":"1190",
    "addr:street":"Avenue Everard",
    "iso:country":"BE",
    "sg:address":"Avenue Everard 40",
    "sg:city":"Bruxelles (forest)",
    "sg:orig_category":"Non-Classified Establishments",
    "sg:phone":"+32 2 344 35 17",
    "sg:postcode":"1190",
    "sg:province":"Bruxelles-Capitale",
    "wof:name":"Van Den Berg",
    "wof:placetype":"venue"
},
  "geometry": {"coordinates":[4.3390197754,50.8159103394],"type":"Point"}
}