{
  "type": "Feature",
  "properties": {
    "addr:full":"Chauss\u00e9e De Mons 814 Box 20 Bruxelles (anderlecht) Bruxelles-Capitale 1070",
    "addr:housenumber":"814 box 20",
    "addr:postcode":"1070",
    "addr:street":"Chausse\u0301E De Mons",
    "iso:country":"BE",
    "sg:address":"Chauss\u00e9e De Mons 814 Box 20",
    "sg:city":"Bruxelles (anderlecht)",
    "sg:classifiers":[
        {
            "category":"Building & Trades",
            "subcategory":"Cleaning & Sanitation",
            "type":"Services"
        }
    ],
    "sg:phone":"+32 2 520 03 82",
    "sg:postcode":"1070",
    "sg:province":"Bruxelles-Capitale",
    "sg:tags":[
        "cleaner",
        "window"
    ],
    "wof:name":"Vander Perre",
    "wof:placetype":"venue"
},
  "geometry": {"coordinates":[4.3032579422,50.8281517029],"type":"Point"}
}