{
  "type": "Feature",
  "properties": {
    "addr:full":"Rue L\u00c9on Theodor 77 Jette/jette Bruxelles-Capitale 1090",
    "addr:housenumber":"77",
    "addr:postcode":"1090",
    "addr:street":"Rue Le\u0301On Theodor",
    "iso:country":"BE",
    "sg:address":"Rue L\u00c9on Theodor 77",
    "sg:city":"Jette/jette",
    "sg:orig_category":"Artistes ind\u00e9pendants",
    "sg:phone":"+32 2 428 94 91",
    "sg:postcode":"1090",
    "sg:province":"Bruxelles-Capitale",
    "wof:name":"F. Engelmann",
    "wof:placetype":"venue"
},
  "geometry": {"coordinates":[4.327299118,50.8751449585],"type":"Point"}
}