{
  "type": "Feature",
  "properties": {
    "iso:country":"BE",
    "sg:address":"Rue Saint-paul 26-28",
    "sg:city":"Li\u00e8ge 1",
    "sg:classifiers":[
        {
            "category":"Home & Garden",
            "subcategory":"Home Furnishings",
            "type":"Retail Goods"
        }
    ],
    "sg:phone":"+32 4 223 54 38",
    "sg:postcode":"4000",
    "sg:province":"Li\u00e8ge",
    "sg:tags":[
        "lighting",
        "fixture",
        "-"
    ],
    "wof:name":"Modulight Sprl",
    "wof:placetype":"venue"
},
  "geometry": {"coordinates":[5.5728859901,50.6397094727],"type":"Point"}
}