{
  "type": "Feature",
  "properties": {
    "iso:country":"BE",
    "sg:address":"Verbondstraat 58",
    "sg:city":"Antwerpen",
    "sg:classifiers":[
        {
            "category":"Fast Food",
            "type":"Food & Drink"
        }
    ],
    "sg:phone":"+32 3 288 62 51",
    "sg:postcode":"2000",
    "sg:province":"Antwerpen",
    "sg:tags":[
        "meeneem",
        "restaurant"
    ],
    "wof:name":"Suri Food",
    "wof:placetype":"venue"
},
  "geometry": {"coordinates":[4.3995728493,51.2096099854],"type":"Point"}
}