{
  "type": "Feature",
  "properties": {
    "addr:full":"Houtmarkt 23 Aalst Oost-Vlaanderen 9300",
    "addr:housenumber":"23",
    "addr:postcode":"9300",
    "addr:street":"Houtmarkt",
    "iso:country":"BE",
    "sg:address":"Houtmarkt 23",
    "sg:city":"Aalst",
    "sg:orig_category":"Peinture. Rev\u00eatements de sols and murs. Rev\u00eatements pour sols and murs",
    "sg:phone":"+32 475 49 22 94",
    "sg:postcode":"9300",
    "sg:province":"Oost-Vlaanderen",
    "wof:name":"De Vijlder Gebroeders",
    "wof:placetype":"venue"
},
  "geometry": {"coordinates":[4.0430669785,50.9345817566],"type":"Point"}
}