{
  "type": "Feature",
  "properties": {
    "addr:full":"Kanaalstraat 9b2 Lanaken Limburg 3621",
    "addr:housenumber":"9b2",
    "addr:postcode":"3621",
    "addr:street":"Kanaalstraat",
    "iso:country":"BE",
    "sg:address":"Kanaalstraat 9b2",
    "sg:city":"Lanaken",
    "sg:orig_category":"Zalen voor culturele evenementen",
    "sg:phone":"+32 89 71 18 05",
    "sg:postcode":"3621",
    "sg:province":"Limburg",
    "wof:name":"Galerie Van Laethem",
    "wof:placetype":"venue"
},
  "geometry": {"coordinates":[5.7067928314,50.9237365723],"type":"Point"}
}