{
  "type": "Feature",
  "properties": {
    "addr:full":"Brugse Steenweg 12 Veurne West-Vlaanderen 8630",
    "addr:housenumber":"12",
    "addr:postcode":"8630",
    "addr:street":"Brugse Steenweg",
    "iso:country":"BE",
    "sg:address":"Brugse Steenweg 12",
    "sg:city":"Veurne",
    "sg:classifiers":[
        {
            "category":"Personal",
            "subcategory":"Beauty Salon",
            "type":"Services"
        }
    ],
    "sg:phone":"+32 58 31 44 36",
    "sg:postcode":"8630",
    "sg:province":"West-Vlaanderen",
    "sg:tags":[
        "de",
        "coiffure"
    ],
    "wof:name":"Benny Finaut",
    "wof:placetype":"venue"
},
  "geometry": {"coordinates":[2.6698200703,51.0746994019],"type":"Point"}
}