{
  "type": "Feature",
  "properties": {
    "addr:full":"Mannebeekstr. 21 Waregem West-Vlaanderen 8790",
    "addr:housenumber":"21",
    "addr:postcode":"8790",
    "addr:street":"Mannebeekstr.",
    "iso:country":"BE",
    "sg:address":"Mannebeekstr. 21",
    "sg:city":"Waregem",
    "sg:classifiers":[
        {
            "category":"Shopping",
            "type":"Retail Goods"
        }
    ],
    "sg:phone":"+32 56 77 27 66",
    "sg:postcode":"8790",
    "sg:province":"West-Vlaanderen",
    "sg:tags":[
        "metallurgy",
        "finished",
        "-",
        "metalworking",
        "metallic"
    ],
    "wof:name":"Locinox Nv",
    "wof:placetype":"venue"
},
  "geometry": {"coordinates":[3.4272499084,50.8599281311],"type":"Point"}
}