{
  "type": "Feature",
  "properties": {
    "iso:country":"BE",
    "sg:address":"Rue Des Arquebusiers 41",
    "sg:city":"Binche",
    "sg:orig_category":"Enseignement maternel and primaire",
    "sg:phone":"+32 64 33 54 37",
    "sg:postcode":"7130",
    "sg:province":"Hainaut",
    "wof:name":"Ecole Matern. Communale",
    "wof:placetype":"venue"
},
  "geometry": {"coordinates":[4.162293911,50.411239624],"type":"Point"}
}