{
  "type": "Feature",
  "properties": {
    "addr:full":"Demerlaan 3 Bilzen Limburg 3740",
    "addr:housenumber":"3",
    "addr:postcode":"3740",
    "addr:street":"Demerlaan",
    "iso:country":"BE",
    "sg:address":"Demerlaan 3",
    "sg:city":"Bilzen",
    "sg:orig_category":"Banken and kredietinstellingen",
    "sg:phone":"+32 89 50 32 40",
    "sg:postcode":"3740",
    "sg:province":"Limburg",
    "wof:name":"Anhyp",
    "wof:placetype":"venue"
},
  "geometry": {"coordinates":[5.5168280602,50.8696022034],"type":"Point"}
}