{
  "type": "Feature",
  "properties": {
    "iso:country":"BE",
    "sg:address":"Kerkstraat 52",
    "sg:city":"Sint-gillis-waas",
    "sg:classifiers":[
        {
            "category":"Professional",
            "subcategory":"Computer Services",
            "type":"Services"
        }
    ],
    "sg:phone":"+32 3 727 12 12",
    "sg:postcode":"9170",
    "sg:province":"Oost-Vlaanderen",
    "sg:tags":[
        "network"
    ],
    "wof:name":"Brainstorm Bvba",
    "wof:placetype":"venue"
},
  "geometry": {"coordinates":[4.1284098625,51.2170715332],"type":"Point"}
}