{
  "type": "Feature",
  "properties": {
    "addr:full":"Rue De La Science 29 Courcelles (souvret) Hainaut 6182",
    "addr:housenumber":"29",
    "addr:postcode":"6182",
    "addr:street":"Rue De La Science",
    "iso:country":"BE",
    "sg:address":"Rue De La Science 29",
    "sg:city":"Courcelles (souvret)",
    "sg:classifiers":[
        {
            "category":"Professional",
            "subcategory":"Accounting & Tax Preparation",
            "type":"Services"
        }
    ],
    "sg:phone":"+32 71 45 88 19",
    "sg:postcode":"6182",
    "sg:province":"Hainaut",
    "sg:tags":[
        "bookkeeper"
    ],
    "wof:name":"Vanoverbeke J-m",
    "wof:placetype":"venue"
},
  "geometry": {"coordinates":[4.3471140862,50.442943573],"type":"Point"}
}