{
  "type": "Feature",
  "properties": {
    "addr:full":"Den Eenen Boom 2 Brecht Antwerpen 2960",
    "addr:housenumber":"2",
    "addr:postcode":"2960",
    "addr:street":"Den Eenen Boom",
    "iso:country":"BE",
    "sg:address":"Den Eenen Boom 2",
    "sg:city":"Brecht",
    "sg:classifiers":[
        {
            "category":"Utilities",
            "subcategory":"Telephone",
            "type":"Services"
        }
    ],
    "sg:phone":"+32 3 288 16 91",
    "sg:postcode":"2960",
    "sg:province":"Antwerpen",
    "sg:tags":[
        "-",
        "internet"
    ],
    "wof:name":"Cipido Computerservices",
    "wof:placetype":"venue"
},
  "geometry": {"coordinates":[4.6076450348,51.3416442871],"type":"Point"}
}