{
  "type": "Feature",
  "properties": {
    "iso:country":"BE",
    "sg:address":"Rue De La Station 28",
    "sg:city":"Deux-acren",
    "sg:classifiers":[
        {
            "category":"Shopping",
            "subcategory":"Clothing, Apparel, & Fashions",
            "type":"Retail Goods"
        }
    ],
    "sg:phone":"+32 68 33 33 90",
    "sg:postcode":"7864",
    "sg:province":"Hainaut",
    "sg:tags":[
        "textile",
        "clothing",
        "clothes"
    ],
    "wof:name":"Sartoise De Confect Bvba",
    "wof:placetype":"venue"
},
  "geometry": {"coordinates":[3.8465349674,50.733215332],"type":"Point"}
}