{
  "type": "Feature",
  "properties": {
    "addr:full":"G. Le Fevere Ten Hoveln 5 Gent Oost-Vlaanderen 9050",
    "addr:housenumber":"5",
    "addr:postcode":"9050",
    "addr:street":"G.;Hoveln;Oost-Vlaanderen",
    "iso:country":"BE",
    "sg:address":"G. Le Fevere Ten Hoveln 5",
    "sg:city":"Gent",
    "sg:orig_category":"Landmeters",
    "sg:phone":"+32 9 230 45 84",
    "sg:postcode":"9050",
    "sg:province":"Oost-Vlaanderen",
    "wof:name":"Marc Timbremont",
    "wof:placetype":"venue"
},
  "geometry": {"coordinates":[3.7589480877,51.0448532104],"type":"Point"}
}