{
  "type": "Feature",
  "properties": {
    "iso:country":"BE",
    "sg:address":"Katelijnestraat 73-75",
    "sg:city":"Brugge",
    "sg:orig_category":"Machines \u00e0 coudre and tricoter",
    "sg:phone":"+32 50 33 16 73",
    "sg:postcode":"8500",
    "sg:province":"West-Vlaanderen",
    "wof:name":"Puype Consulting Computing",
    "wof:placetype":"venue"
},
  "geometry": {"coordinates":[3.2268249989,51.2021713257],"type":"Point"}
}