{
  "type": "Feature",
  "properties": {
    "addr:full":"Koninkjestraat 13 Moeskroen/mouscron Hainaut 7700",
    "addr:housenumber":"13",
    "addr:postcode":"7700",
    "addr:street":"Koninkjestraat",
    "iso:country":"BE",
    "sg:address":"Koninkjestraat 13",
    "sg:city":"Moeskroen/mouscron",
    "sg:orig_category":"Landmeters",
    "sg:phone":"+32 56 84 38 28",
    "sg:postcode":"7700",
    "sg:province":"Hainaut",
    "wof:name":"Christian George",
    "wof:placetype":"venue"
},
  "geometry": {"coordinates":[3.2323200703,50.7400932312],"type":"Point"}
}