{
  "type": "Feature",
  "properties": {
    "addr:full":"Appelboom 18c Maldegem (adegem) Oost-Vlaanderen 9991",
    "addr:housenumber":"18c",
    "addr:postcode":"9991",
    "addr:street":"Appelboom",
    "iso:country":"BE",
    "sg:address":"Appelboom 18c",
    "sg:city":"Maldegem (adegem)",
    "sg:classifiers":[
        {
            "category":"Home & Garden",
            "subcategory":"Home Furnishings",
            "type":"Retail Goods"
        }
    ],
    "sg:phone":"+32 9 377 96 21",
    "sg:postcode":"9991",
    "sg:province":"Oost-Vlaanderen",
    "sg:tags":[
        "curtain",
        "-",
        "fixture"
    ],
    "wof:name":"Rommelaere F",
    "wof:placetype":"venue"
},
  "geometry": {"coordinates":[3.5069770813,51.172454834],"type":"Point"}
}