{
  "type": "Feature",
  "properties": {
    "iso:country":"BE",
    "sg:address":"Rue De Paris 11",
    "sg:city":"Orp-jauche (jandrain-jandrenouille)",
    "sg:classifiers":[
        {
            "category":"Building & Trades",
            "subcategory":"Landscaping Services",
            "type":"Services"
        }
    ],
    "sg:phone":"+32 19 63 74 12",
    "sg:postcode":"1350",
    "sg:province":"Brabant Wallon",
    "sg:tags":[
        "gardening",
        "garden",
        "maintenance"
    ],
    "wof:name":"Delbeke Ph",
    "wof:placetype":"venue"
},
  "geometry": {"coordinates":[4.9743680954,50.6542816162],"type":"Point"}
}