{
  "type": "Feature",
  "properties": {
    "iso:country":"BE",
    "sg:address":"Lintsesteenweg 18",
    "sg:city":"Lier",
    "sg:orig_category":"Producteurs de l\u00e9gumes",
    "sg:phone":"+32 3 480 74 71",
    "sg:postcode":"2500",
    "sg:province":"Antwerpen",
    "wof:name":"Tielemans Dirk En Patrick",
    "wof:placetype":"venue"
},
  "geometry": {"coordinates":[4.547399044,51.1253814697],"type":"Point"}
}