{
  "type": "Feature",
  "properties": {
    "addr:full":"Koning Albertlaan 53 Lanaken Limburg 3620",
    "addr:housenumber":"53",
    "addr:postcode":"3620",
    "addr:street":"Koning Albertlaan",
    "iso:country":"BE",
    "sg:address":"Koning Albertlaan 53",
    "sg:city":"Lanaken",
    "sg:orig_category":"Avocats and conseillers juridiques",
    "sg:phone":"+32 89 71 57 84",
    "sg:postcode":"3620",
    "sg:province":"Limburg",
    "wof:name":"Ludo Christoffels",
    "wof:placetype":"venue"
},
  "geometry": {"coordinates":[5.6566991806,50.8919410706],"type":"Point"}
}