{
  "type": "Feature",
  "properties": {
    "iso:country":"BE",
    "sg:address":"Mgr. Stillemansstraat 82",
    "sg:city":"Sint-niklaas",
    "sg:orig_category":"Verbruikerskredietinstellingen",
    "sg:phone":"+32 3 777 19 32",
    "sg:postcode":"9100",
    "sg:province":"Oost-Vlaanderen",
    "wof:name":"Krevobex",
    "wof:placetype":"venue"
},
  "geometry": {"coordinates":[4.1381998062,51.160900116],"type":"Point"}
}