{
  "type": "Feature",
  "properties": {
    "addr:full":"Kleinendries 24 Affligem (teralfene) Vlaams-Brabant 1790",
    "addr:housenumber":"24",
    "addr:postcode":"1790",
    "addr:street":"Kleinendries",
    "iso:country":"BE",
    "sg:address":"Kleinendries 24",
    "sg:city":"Affligem (teralfene)",
    "sg:classifiers":[
        {
            "category":"Building & Trades",
            "subcategory":"Landscaping Services",
            "type":"Services"
        }
    ],
    "sg:phone":"+32 53 66 64 44",
    "sg:postcode":"1790",
    "sg:province":"Vlaams-Brabant",
    "sg:tags":[
        "gardening",
        "garden",
        "maintenance"
    ],
    "wof:name":"Baten Wegeniswerken",
    "wof:placetype":"venue"
},
  "geometry": {"coordinates":[4.1041049957,50.8856506348],"type":"Point"}
}