{
  "type": "Feature",
  "properties": {
    "iso:country":"BE",
    "sg:address":"Naamsepoortgalerij 23 Box 7",
    "sg:city":"Bruxelles (ixelles)",
    "sg:classifiers":[
        {
            "category":"Professional",
            "subcategory":"Business Services",
            "type":"Services"
        }
    ],
    "sg:phone":"+32 2 511 39 45",
    "sg:postcode":"1050",
    "sg:province":"Bruxelles-Capitale",
    "sg:tags":[
        "bookkeeping"
    ],
    "wof:name":"Fiduciaire De Bruxelles",
    "wof:placetype":"venue"
},
  "geometry": {"coordinates":[4.3627858162,50.8375511169],"type":"Point"}
}