{
  "type": "Feature",
  "properties": {
    "addr:full":"Verlorengoedstraat 1 Wingene West-Vlaanderen 8750",
    "addr:housenumber":"1",
    "addr:postcode":"8750",
    "addr:street":"Verlorengoedstraat",
    "iso:country":"BE",
    "sg:address":"Verlorengoedstraat 1",
    "sg:city":"Wingene",
    "sg:orig_category":"Non-Classified Establishments",
    "sg:phone":"+32 51 65 54 94",
    "sg:postcode":"8750",
    "sg:province":"West-Vlaanderen",
    "wof:name":"De Melkhoeve",
    "wof:placetype":"venue"
},
  "geometry": {"coordinates":[3.2879180908,51.0717048645],"type":"Point"}
}