{
  "type": "Feature",
  "properties": {
    "iso:country":"BE",
    "sg:address":"Burggravenstraat 13",
    "sg:city":"Eeklo",
    "sg:classifiers":[
        {
            "category":"Taxi",
            "type":"Transportation"
        }
    ],
    "sg:phone":"+32 9 377 77 97",
    "sg:postcode":"9900",
    "sg:province":"Oost-Vlaanderen",
    "sg:tags":[
        "taxicab"
    ],
    "wof:name":"Taxi 2000",
    "wof:placetype":"venue"
},
  "geometry": {"coordinates":[3.5637249947,51.1804428101],"type":"Point"}
}