{
  "type": "Feature",
  "properties": {
    "iso:country":"BE",
    "sg:address":"Rue L\u00c9opold I 147",
    "sg:city":"Brussel/bruxelles",
    "sg:orig_category":"Pharmaciens",
    "sg:phone":"+32 2 426 30 55",
    "sg:postcode":"1020",
    "sg:province":"Bruxelles-Capitale",
    "wof:name":"Guy Nestour",
    "wof:placetype":"venue"
},
  "geometry": {"coordinates":[4.3464250565,50.87758255],"type":"Point"}
}