{
  "type": "Feature",
  "properties": {
    "iso:country":"BE",
    "sg:address":"Wagenmakersstraat 2b",
    "sg:city":"Kortrijk",
    "sg:orig_category":"Herstellingen and onderhoud van auto's Voertuigen",
    "sg:phone":"+32 56 20 22 20",
    "sg:postcode":"8500",
    "sg:province":"West-Vlaanderen",
    "wof:name":"Garage Carrosserie Mondy",
    "wof:placetype":"venue"
},
  "geometry": {"coordinates":[3.269769907,50.8188667297],"type":"Point"}
}