{
  "type": "Feature",
  "properties": {
    "addr:full":"Rue Des Croix Du Feu 1b26 La Louviere Hainaut 7100",
    "addr:housenumber":"1b26",
    "addr:postcode":"7100",
    "addr:street":"Rue Des Croix Du Feu",
    "iso:country":"BE",
    "sg:address":"Rue Des Croix Du Feu 1b26",
    "sg:city":"La Louviere",
    "sg:orig_category":"Epiceries",
    "sg:phone":"+32 64 22 35 18",
    "sg:postcode":"7100",
    "sg:province":"Hainaut",
    "wof:name":"Andre Van Eesbeek",
    "wof:placetype":"venue"
},
  "geometry": {"coordinates":[4.2008948326,50.4794387817],"type":"Point"}
}