{
  "type": "Feature",
  "properties": {
    "iso:country":"BE",
    "sg:address":"Grotehoeveweg 34",
    "sg:city":"Boechout",
    "sg:orig_category":"Voertuigen",
    "sg:phone":"+32 3 475 06 55",
    "sg:postcode":"2531",
    "sg:province":"Antwerpen",
    "wof:name":"Erwin Bollansee",
    "wof:placetype":"venue"
},
  "geometry": {"coordinates":[4.5586829185,51.169254303],"type":"Point"}
}