{
  "type": "Feature",
  "properties": {
    "iso:country":"BE",
    "sg:address":"Avenue Louis Libert 14",
    "sg:city":"Aywaille",
    "sg:classifiers":[
        {
            "category":"Bars & Pubs",
            "type":"Food & Drink"
        }
    ],
    "sg:phone":"+32 4 384 45 99",
    "sg:postcode":"4920",
    "sg:province":"Li\u00e8ge",
    "wof:name":"Maria (chez)",
    "wof:placetype":"venue"
},
  "geometry": {"coordinates":[5.6782579422,50.4737205505],"type":"Point"}
}