{
  "type": "Feature",
  "properties": {
    "addr:full":"Rue Du Fourneau Saint-michel 22 Saint-hubert (awenne) Luxembourg 6870",
    "addr:housenumber":"22",
    "addr:postcode":"6870",
    "addr:street":"Rue Du Fourneau Saint-Michel;Awenne",
    "iso:country":"BE",
    "sg:address":"Rue Du Fourneau Saint-michel 22",
    "sg:city":"Saint-hubert (awenne)",
    "sg:classifiers":[
        {
            "category":"Building & Trades",
            "subcategory":"Landscaping Services",
            "type":"Services"
        }
    ],
    "sg:phone":"+32 84 36 62 53",
    "sg:postcode":"6870",
    "sg:province":"Luxembourg",
    "sg:tags":[
        "nurseryman"
    ],
    "wof:name":"Travert (au)",
    "wof:placetype":"venue"
},
  "geometry": {"coordinates":[5.3732600212,50.0284767151],"type":"Point"}
}