{
  "type": "Feature",
  "properties": {
    "iso:country":"BE",
    "sg:address":"Rue De Liverpool 46",
    "sg:city":"Sint-jans-molenbeek/molenbeek-saint-jean",
    "sg:orig_category":"V\u00e9hicules automobiles",
    "sg:phone":"+32 2 523 40 00",
    "sg:postcode":"1080",
    "sg:province":"Bruxelles-Capitale",
    "wof:name":"Garage Qualicar",
    "wof:placetype":"venue"
},
  "geometry": {"coordinates":[4.3311228752,50.8462638855],"type":"Point"}
}