{
  "type": "Feature",
  "properties": {
    "iso:country":"BE",
    "sg:address":"Avenue H. Conscience 9",
    "sg:city":"Wemmel",
    "sg:classifiers":[
        {
            "category":"Insurance",
            "subcategory":"Insurance Agent",
            "type":"Services"
        }
    ],
    "sg:phone":"+32 2 460 05 32",
    "sg:postcode":"1780",
    "sg:province":"Vlaams-Brabant",
    "sg:tags":[
        "-",
        "representative"
    ],
    "wof:name":"Joris Lambert Sprl",
    "wof:placetype":"venue"
},
  "geometry": {"coordinates":[4.2944121361,50.9056243896],"type":"Point"}
}