{
  "type": "Feature",
  "properties": {
    "iso:country":"BE",
    "sg:address":"Poelkapellestraat 21",
    "sg:city":"Houthulst",
    "sg:orig_category":"V\u00eatements sur mesure Fab",
    "sg:phone":"+32 51 70 00 13",
    "sg:postcode":"8650",
    "sg:province":"West-Vlaanderen",
    "wof:name":"Mariette Veryser",
    "wof:placetype":"venue"
},
  "geometry": {"coordinates":[2.9470100403,50.9736328125],"type":"Point"}
}