{
  "type": "Feature",
  "properties": {
    "iso:country":"BE",
    "sg:address":"Laakakker 27",
    "sg:city":"Lille",
    "sg:orig_category":"Textiles. Eclairage et \u00e9quipements du foyer",
    "sg:phone":"+32 14 88 17 60",
    "sg:postcode":"2275",
    "sg:province":"Antwerpen",
    "wof:name":"Mertens Decoratie",
    "wof:placetype":"venue"
},
  "geometry": {"coordinates":[4.8426380157,51.2273597717],"type":"Point"}
}