{
  "type": "Feature",
  "properties": {
    "addr:full":"Solleveld 17 Herzele Oost-Vlaanderen 9550",
    "addr:housenumber":"17",
    "addr:postcode":"9550",
    "addr:street":"Solleveld;Oost-Vlaanderen",
    "iso:country":"BE",
    "sg:address":"Solleveld 17",
    "sg:city":"Herzele",
    "sg:classifiers":[
        {
            "category":"Structure",
            "subcategory":"Building",
            "type":"Public Place"
        }
    ],
    "sg:phone":"+32 53 62 24 55",
    "sg:postcode":"9550",
    "sg:province":"Oost-Vlaanderen",
    "sg:tags":[
        "apartment"
    ],
    "wof:name":"De Clippel B.v.b.a.",
    "wof:placetype":"venue"
},
  "geometry": {"coordinates":[3.8888070583,50.8821105957],"type":"Point"}
}