{
  "type": "Feature",
  "properties": {
    "addr:full":"Chauss\u00e9e De Louvain 647 Bruxelles (schaerbeek) Bruxelles-Capitale 1030",
    "addr:housenumber":"647",
    "addr:postcode":"1030",
    "addr:street":"Chausse\u0301E De Louvain",
    "iso:country":"BE",
    "sg:address":"Chauss\u00e9e De Louvain 647",
    "sg:city":"Bruxelles (schaerbeek)",
    "sg:classifiers":[
        {
            "category":"Social Services",
            "type":"Services"
        }
    ],
    "sg:phone":"+32 2 705 31 30",
    "sg:postcode":"1030",
    "sg:province":"Bruxelles-Capitale",
    "wof:name":"Fogolar Furlan Di Bruxelles",
    "wof:placetype":"venue"
},
  "geometry": {"coordinates":[4.4055280685,50.8569755554],"type":"Point"}
}