{
  "type": "Feature",
  "properties": {
    "iso:country":"BE",
    "sg:address":"Rue De La Fonderie 22",
    "sg:city":"Fleurus",
    "sg:orig_category":"Boissons",
    "sg:phone":"+32 71 81 22 81",
    "sg:postcode":"6220",
    "sg:province":"Hainaut",
    "wof:name":"Caves Alsaciennes",
    "wof:placetype":"venue"
},
  "geometry": {"coordinates":[4.5418171883,50.4816207886],"type":"Point"}
}