{
  "type": "Feature",
  "properties": {
    "iso:country":"BE",
    "sg:address":"Ave Charles Woeste 310",
    "sg:city":"Jette",
    "sg:classifiers":[
        {
            "category":"Banks & Credit Unions",
            "subcategory":"Bank",
            "type":"Services"
        }
    ],
    "sg:phone":"+32 2 425 75 82",
    "sg:postcode":"1090",
    "sg:province":"Bruxelles-Capitale",
    "wof:name":"Kredietbank Nv",
    "wof:placetype":"venue"
},
  "geometry": {"coordinates":[4.3350667953,50.8682632446],"type":"Point"}
}