{
  "type": "Feature",
  "properties": {
    "iso:country":"BE",
    "sg:address":"Alsembergsesteenweg 34bc",
    "sg:city":"Linkebeek",
    "sg:orig_category":"Voertuigen",
    "sg:phone":"+32 2 377 60 14",
    "sg:postcode":"1630",
    "sg:province":"Vlaams-Brabant",
    "wof:name":"Capotes Euro-cabrio",
    "wof:placetype":"venue"
},
  "geometry": {"coordinates":[4.3260498047,50.7759513855],"type":"Point"}
}