{
  "type": "Feature",
  "properties": {
    "iso:country":"BE",
    "sg:address":"Gabriel Emile Lebonlaan 27",
    "sg:city":"Grez-doiceau",
    "sg:classifiers":[
        {
            "category":"Insurance",
            "subcategory":"Insurance Agent",
            "type":"Services"
        }
    ],
    "sg:phone":"+32 10 84 08 32",
    "sg:postcode":"1390",
    "sg:province":"Brabant Wallon",
    "sg:tags":[
        "verzekeringsmakelaars",
        "expert"
    ],
    "wof:name":"Jean Verhasselt",
    "wof:placetype":"venue"
},
  "geometry": {"coordinates":[4.6970720291,50.7384757996],"type":"Point"}
}