{
  "type": "Feature",
  "properties": {
    "iso:country":"BE",
    "sg:address":"Victoriestraat 2",
    "sg:city":"Turnhout",
    "sg:classifiers":[
        {
            "category":"Restaurant",
            "type":"Food & Drink"
        }
    ],
    "sg:phone":"+32 14 42 60 80",
    "sg:postcode":"2300",
    "sg:province":"Antwerpen",
    "wof:name":"Tea-room Pinokkio",
    "wof:placetype":"venue"
},
  "geometry": {"coordinates":[4.9430742264,51.3210334778],"type":"Point"}
}