{
  "type": "Feature",
  "properties": {
    "iso:country":"BE",
    "sg:address":"Chauss\u00e9e D'alsemberg 93",
    "sg:city":"Linkebeek",
    "sg:classifiers":[
        {
            "category":"Personal",
            "subcategory":"Beauty Salon",
            "type":"Services"
        }
    ],
    "sg:phone":"+32 2 361 85 05",
    "sg:postcode":"1630",
    "sg:province":"Vlaams-Brabant",
    "wof:name":"Bleu Du Nil",
    "wof:placetype":"venue"
},
  "geometry": {"coordinates":[4.3271369934,50.7727775574],"type":"Point"}
}