{
  "type": "Feature",
  "properties": {
    "iso:country":"BE",
    "sg:address":"Rue Gaston Ragon 43",
    "sg:city":"Profondeville (bois-de-villers)",
    "sg:classifiers":[
        {
            "category":"Train Station",
            "subcategory":"Light Rail",
            "type":"Transportation"
        }
    ],
    "sg:phone":"+32 81 43 35 84",
    "sg:postcode":"5170",
    "sg:province":"Namur",
    "sg:tags":[
        "varnishing",
        "plasticizing",
        "document"
    ],
    "wof:name":"Cadacom",
    "wof:placetype":"venue"
},
  "geometry": {"coordinates":[4.8293128014,50.3879165649],"type":"Point"}
}