{
  "type": "Feature",
  "properties": {
    "addr:full":"Wakkensteenweg 20 Wielsbeke West-Vlaanderen 8710",
    "addr:housenumber":"20",
    "addr:postcode":"8710",
    "addr:street":"Wakkensteenweg;West-Vlaanderen",
    "iso:country":"BE",
    "sg:address":"Wakkensteenweg 20",
    "sg:city":"Wielsbeke",
    "sg:orig_category":"Boissons",
    "sg:phone":"+32 56 60 37 34",
    "sg:postcode":"8710",
    "sg:province":"West-Vlaanderen",
    "wof:name":"Lapierre",
    "wof:placetype":"venue"
},
  "geometry": {"coordinates":[3.3958981037,50.9156990051],"type":"Point"}
}