{
  "type": "Feature",
  "properties": {
    "addr:full":"Dreef 9 Zomergem Oost-Vlaanderen 9930",
    "addr:housenumber":"9",
    "addr:postcode":"9930",
    "addr:street":"Dreef",
    "iso:country":"BE",
    "sg:address":"Dreef 9",
    "sg:city":"Zomergem",
    "sg:orig_category":"Poissonniers and \u00e9caillers",
    "sg:phone":"+32 9 372 52 52",
    "sg:postcode":"9930",
    "sg:province":"Oost-Vlaanderen",
    "wof:name":"Huis Karien",
    "wof:placetype":"venue"
},
  "geometry": {"coordinates":[3.561784029,51.1187782288],"type":"Point"}
}