{
  "type": "Feature",
  "properties": {
    "iso:country":"BE",
    "sg:address":"Eldestraat 12",
    "sg:city":"Meulebeke",
    "sg:orig_category":"Charpentes and couvertures. Quincailleries",
    "sg:phone":"+32 51 48 90 87",
    "sg:postcode":"8760",
    "sg:province":"West-Vlaanderen",
    "wof:name":"Verhoye",
    "wof:placetype":"venue"
},
  "geometry": {"coordinates":[3.2889699936,50.9495239258],"type":"Point"}
}