{
  "type": "Feature",
  "properties": {
    "iso:country":"BE",
    "sg:address":"Rue Sainte-henriette 210",
    "sg:city":"Morlanwelz (morlanwelz-mariemont)",
    "sg:classifiers":[
        {
            "category":"Building & Trades",
            "subcategory":"Cleaning & Sanitation",
            "type":"Services"
        }
    ],
    "sg:phone":"+32 64 45 80 70",
    "sg:postcode":"7140",
    "sg:province":"Hainaut",
    "sg:tags":[
        "equipment",
        "blast",
        "supply"
    ],
    "wof:name":"Gre-sa-s",
    "wof:placetype":"venue"
},
  "geometry": {"coordinates":[4.2630271912,50.4643821716],"type":"Point"}
}