{
  "type": "Feature",
  "properties": {
    "iso:country":"BE",
    "sg:address":"Res. Du Grand Colombier 7",
    "sg:city":"Tournai",
    "sg:classifiers":[
        {
            "category":"Professional",
            "subcategory":"Accounting & Tax Preparation",
            "type":"Services"
        }
    ],
    "sg:phone":"+32 69 22 46 29",
    "sg:postcode":"7500",
    "sg:province":"Hainaut",
    "sg:tags":[
        "accountant"
    ],
    "wof:name":"Gerard Taverne",
    "wof:placetype":"venue"
},
  "geometry": {"coordinates":[3.3722100258,50.6119499207],"type":"Point"}
}