{
  "type": "Feature",
  "properties": {
    "addr:full":"Kleine Molenweg 110 Stabroek Antwerpen 2940",
    "addr:housenumber":"110",
    "addr:postcode":"2940",
    "addr:street":"Kleine Molenweg",
    "iso:country":"BE",
    "sg:address":"Kleine Molenweg 110",
    "sg:city":"Stabroek",
    "sg:classifiers":[
        {
            "category":"Bars & Pubs",
            "type":"Food & Drink"
        }
    ],
    "sg:phone":"+32 3 569 12 00",
    "sg:postcode":"2940",
    "sg:province":"Antwerpen",
    "wof:name":"Pierrot",
    "wof:placetype":"venue"
},
  "geometry": {"coordinates":[4.3707079887,51.3279762268],"type":"Point"}
}