{
  "type": "Feature",
  "properties": {
    "addr:full":"Rue De Tubize 6 Tubize Brabant Wallon 1480",
    "addr:housenumber":"6",
    "addr:postcode":"1480",
    "addr:street":"Rue De Tubize;Wallon",
    "iso:country":"BE",
    "sg:address":"Rue De Tubize 6",
    "sg:city":"Tubize",
    "sg:orig_category":"Jardinage",
    "sg:phone":"+32 2 355 45 48",
    "sg:postcode":"1480",
    "sg:province":"Brabant Wallon",
    "wof:name":"Monti C.",
    "wof:placetype":"venue"
},
  "geometry": {"coordinates":[4.204308033,50.6932029724],"type":"Point"}
}