{
  "type": "Feature",
  "properties": {
    "iso:country":"BE",
    "sg:address":"Avenue Reine Astrid 270 Box 13",
    "sg:city":"Kraainem",
    "sg:classifiers":[
        {
            "category":"Real Estate",
            "subcategory":"Surveying",
            "type":"Services"
        }
    ],
    "sg:phone":"+32 2 731 71 96",
    "sg:postcode":"1950",
    "sg:province":"Vlaams-Brabant",
    "sg:tags":[
        "surveyor",
        "land"
    ],
    "wof:name":"Delarue M",
    "wof:placetype":"venue"
},
  "geometry": {"coordinates":[4.4661860466,50.8486022949],"type":"Point"}
}