{
  "type": "Feature",
  "properties": {
    "addr:full":"Elsaute 6 Thimister-clermont Li\u00e8ge 4890",
    "addr:housenumber":"6",
    "addr:postcode":"4890",
    "addr:street":"Elsaute",
    "iso:country":"BE",
    "sg:address":"Elsaute 6",
    "sg:city":"Thimister-clermont",
    "sg:orig_category":"Eleveurs de bovins",
    "sg:phone":"+32 87 44 68 01",
    "sg:postcode":"4890",
    "sg:province":"Li\u00e8ge",
    "wof:name":"Rene Brandt",
    "wof:placetype":"venue"
},
  "geometry": {"coordinates":[5.8840408325,50.6593093872],"type":"Point"}
}