{
  "type": "Feature",
  "properties": {
    "addr:full":"Rue De La Colire 5 Houyet (ciergnon) Namur 5560",
    "addr:housenumber":"5",
    "addr:postcode":"5560",
    "addr:street":"Rue De La Colire",
    "iso:country":"BE",
    "sg:address":"Rue De La Colire 5",
    "sg:city":"Houyet (ciergnon)",
    "sg:classifiers":[
        {
            "category":"Bars & Pubs",
            "type":"Food & Drink"
        }
    ],
    "sg:phone":"+32 84 37 91 46",
    "sg:postcode":"5560",
    "sg:province":"Namur",
    "wof:name":"Li P'tit Bambou",
    "wof:placetype":"venue"
},
  "geometry": {"coordinates":[5.0947480202,50.1650123596],"type":"Point"}
}