{
  "type": "Feature",
  "properties": {
    "addr:full":"Rue Provinciale 172 Celles Hainaut 7760",
    "addr:housenumber":"172",
    "addr:postcode":"7760",
    "addr:street":"Rue Provinciale",
    "iso:country":"BE",
    "sg:address":"Rue Provinciale 172",
    "sg:city":"Celles",
    "sg:orig_category":"Sportclubs Sportterreinen and installaties behalve sportcentra",
    "sg:phone":"+32 69 45 57 89",
    "sg:postcode":"7760",
    "sg:province":"Hainaut",
    "wof:name":"R.c.s. Escanaffles",
    "wof:placetype":"venue"
},
  "geometry": {"coordinates":[3.455329895,50.7194595337],"type":"Point"}
}