{
  "type": "Feature",
  "properties": {
    "iso:country":"BE",
    "sg:address":"Prinskensmolenweg 8",
    "sg:city":"Meerhout",
    "sg:classifiers":[
        {
            "category":"Wholesale",
            "subcategory":"Plants",
            "type":"Manufacturing & Wholesale Goods"
        }
    ],
    "sg:phone":"+32 14 30 05 91",
    "sg:postcode":"2450",
    "sg:province":"Antwerpen",
    "sg:tags":[
        "whol",
        "flower",
        "-",
        "grower"
    ],
    "wof:name":"Multi-green-services",
    "wof:placetype":"venue"
},
  "geometry": {"coordinates":[5.090555191,51.1274261475],"type":"Point"}
}