{
  "type": "Feature",
  "properties": {
    "addr:full":"Rue De Templeuve 13 Estaimpuis Hainaut 7730",
    "addr:housenumber":"13",
    "addr:postcode":"7730",
    "addr:street":"Rue De Templeuve;Hainaut",
    "iso:country":"BE",
    "sg:address":"Rue De Templeuve 13",
    "sg:city":"Estaimpuis",
    "sg:orig_category":"V\u00e9t\u00e9rinaires",
    "sg:phone":"+32 69 55 77 20",
    "sg:postcode":"7730",
    "sg:province":"Hainaut",
    "wof:name":"Sophie Colbrant",
    "wof:placetype":"venue"
},
  "geometry": {"coordinates":[3.3174519539,50.6623458862],"type":"Point"}
}