{
  "type": "Feature",
  "properties": {
    "addr:full":"Christiaan Pallemansstraat 56 Kapellen Antwerpen 2950",
    "addr:housenumber":"56",
    "addr:postcode":"2950",
    "addr:street":"Christiaan Pallemansstraat",
    "iso:country":"BE",
    "sg:address":"Christiaan Pallemansstraat 56",
    "sg:city":"Kapellen",
    "sg:classifiers":[
        {
            "category":"Personal",
            "subcategory":"Beauty Salon",
            "type":"Services"
        }
    ],
    "sg:phone":"+32 3 664 35 75",
    "sg:postcode":"2950",
    "sg:province":"Antwerpen",
    "sg:tags":[
        "lady",
        "-",
        "hairdressing"
    ],
    "wof:name":"Capelli",
    "wof:placetype":"venue"
},
  "geometry": {"coordinates":[4.4313931465,51.3164558411],"type":"Point"}
}