{
  "type": "Feature",
  "properties": {
    "iso:country":"BE",
    "sg:address":"Rue Trapp\u00c9 1",
    "sg:city":"Li\u00c8ge",
    "sg:orig_category":"V\u00eatements pour b\u00e9b\u00e9s and enfants. Biens d'occasion",
    "sg:phone":"+32 4 223 01 56",
    "sg:postcode":"4000",
    "sg:province":"Li\u00e8ge",
    "wof:name":"Maison Antoine & Aur\u00c9lie",
    "wof:placetype":"venue"
},
  "geometry": {"coordinates":[5.5647192001,50.6402740479],"type":"Point"}
}