{
  "type": "Feature",
  "properties": {
    "iso:country":"BE",
    "sg:address":"Jean Deschampsstraat 80",
    "sg:city":"Grimbergen",
    "sg:orig_category":"Instituts de beaut\u00e9",
    "sg:phone":"+32 2 252 30 64",
    "sg:postcode":"1850",
    "sg:province":"Vlaams-Brabant",
    "wof:name":"Gilda Peeters",
    "wof:placetype":"venue"
},
  "geometry": {"coordinates":[4.4086198807,50.9284629822],"type":"Point"}
}