{
  "type": "Feature",
  "properties": {
    "iso:country":"BE",
    "sg:address":"Place Albert I 11",
    "sg:city":"Courcelles (trazegnies)",
    "sg:classifiers":[
        {
            "category":"Government",
            "subcategory":"Department Of Motor Vehicles",
            "type":"Public Place"
        }
    ],
    "sg:phone":"+32 71 46 21 99",
    "sg:postcode":"6183",
    "sg:province":"Hainaut",
    "sg:tags":[
        "painting",
        "picture",
        "-",
        "sale",
        "purchase"
    ],
    "wof:name":"Cambier K",
    "wof:placetype":"venue"
},
  "geometry": {"coordinates":[4.3305897713,50.4651794434],"type":"Point"}
}