{
  "type": "Feature",
  "properties": {
    "iso:country":"BE",
    "sg:address":"Begoniastraat 38",
    "sg:city":"Nazareth",
    "sg:orig_category":"Diverse bouwafwerking and reiniging Gespecialiseerde residenti\u00eble bouw Woningbouw",
    "sg:phone":"+32 9 385 93 27",
    "sg:postcode":"9810",
    "sg:province":"Oost-Vlaanderen",
    "wof:name":"Bagrat Belgien",
    "wof:placetype":"venue"
},
  "geometry": {"coordinates":[3.6567559242,50.9775085449],"type":"Point"}
}