{
  "type": "Feature",
  "properties": {
    "iso:country":"BE",
    "sg:address":"Avenue Du Zodiaque 7",
    "sg:city":"Waterloo",
    "sg:orig_category":"Informaticaconsulenten",
    "sg:phone":"+32 2 354 99 37",
    "sg:postcode":"1410",
    "sg:province":"Brabant Wallon",
    "wof:name":"Your Soft",
    "wof:placetype":"venue"
},
  "geometry": {"coordinates":[4.4203281403,50.7015991211],"type":"Point"}
}