{
  "type": "Feature",
  "properties": {
    "addr:full":"Oude Koornmarkt 17-19 Antwerpen Antwerpen 2000",
    "addr:housenumber":"17-19",
    "addr:postcode":"2000",
    "addr:street":"Oude Koornmarkt",
    "iso:country":"BE",
    "sg:address":"Oude Koornmarkt 17-19",
    "sg:city":"Antwerpen",
    "sg:classifiers":[
        {
            "category":"Fast Food",
            "type":"Food & Drink"
        }
    ],
    "sg:phone":"+32 3 225 07 97",
    "sg:postcode":"2000",
    "sg:province":"Antwerpen",
    "sg:tags":[
        "\u00c0",
        "restaurants",
        "emporter",
        "restaurant"
    ],
    "wof:name":"Pitta House",
    "wof:placetype":"venue"
},
  "geometry": {"coordinates":[4.3999390602,51.2203445435],"type":"Point"}
}