{
  "type": "Feature",
  "properties": {
    "addr:full":"Sint-gillisbaan Sint-niklaas Oost-Vlaanderen 9100",
    "addr:postcode":"9100",
    "iso:country":"BE",
    "sg:address":"Sint-gillisbaan",
    "sg:city":"Sint-niklaas",
    "sg:classifiers":[
        {
            "category":"Professional",
            "subcategory":"Management & Consulting",
            "type":"Services"
        }
    ],
    "sg:phone":"+32 3 766 23 98",
    "sg:postcode":"9100",
    "sg:province":"Oost-Vlaanderen",
    "sg:tags":[
        "consultant"
    ],
    "wof:name":"Qubizz",
    "wof:placetype":"venue"
},
  "geometry": {"coordinates":[4.14270401,51.187210083],"type":"Point"}
}