{
  "type": "Feature",
  "properties": {
    "addr:full":"Bosstraat 53 Sint-katelijne-waver Antwerpen 2861",
    "addr:housenumber":"53",
    "addr:postcode":"2861",
    "addr:street":"Bosstraat",
    "iso:country":"BE",
    "sg:address":"Bosstraat 53",
    "sg:city":"Sint-katelijne-waver",
    "sg:classifiers":[
        {
            "category":"Cafe",
            "type":"Food & Drink"
        }
    ],
    "sg:phone":"+32 15 75 63 07",
    "sg:postcode":"2861",
    "sg:province":"Antwerpen",
    "sg:tags":[
        "caf\u00e9s"
    ],
    "wof:name":"Caf\u00c9 De Vlashoeve",
    "wof:placetype":"venue"
},
  "geometry": {"coordinates":[4.5748071671,51.0703392029],"type":"Point"}
}