{
  "type": "Feature",
  "properties": {
    "addr:full":"Rue De Roubaix 265 Mouscron Hainaut 7700",
    "addr:housenumber":"265",
    "addr:postcode":"7700",
    "addr:street":"Rue De Roubaix",
    "iso:country":"BE",
    "sg:address":"Rue De Roubaix 265",
    "sg:city":"Mouscron",
    "sg:orig_category":"Non-Classified Establishments",
    "sg:phone":"+32 56 33 07 31",
    "sg:postcode":"7700",
    "sg:province":"Hainaut",
    "wof:name":"Malysse",
    "wof:placetype":"venue"
},
  "geometry": {"coordinates":[3.2058720589,50.7340278625],"type":"Point"}
}