{
  "type": "Feature",
  "properties": {
    "iso:country":"BE",
    "sg:address":"Bornstraat 23",
    "sg:city":"Kortessem",
    "sg:orig_category":"Air conditionn\u00e9 and ventilation. Plomberie, chauffage and installations sanitaires",
    "sg:phone":"+32 11 37 50 47",
    "sg:postcode":"3721",
    "sg:province":"Limburg",
    "wof:name":"Thoelen Maurice",
    "wof:placetype":"venue"
},
  "geometry": {"coordinates":[5.4290709496,50.8687973022],"type":"Point"}
}