{
  "type": "Feature",
  "properties": {
    "addr:full":"Klaverveld 3 Buggenhout Oost-Vlaanderen 9255",
    "addr:housenumber":"3",
    "addr:postcode":"9255",
    "addr:street":"Klaverveld",
    "iso:country":"BE",
    "sg:address":"Klaverveld 3",
    "sg:city":"Buggenhout",
    "sg:classifiers":[
        {
            "category":"Community Center",
            "type":"Public Place"
        }
    ],
    "sg:phone":"+32 52 33 44 18",
    "sg:postcode":"9255",
    "sg:province":"Oost-Vlaanderen",
    "sg:tags":[
        "medical"
    ],
    "wof:name":"Revalidatiecentrum Vzw",
    "wof:placetype":"venue"
},
  "geometry": {"coordinates":[4.194642067,51.0150985718],"type":"Point"}
}