{
  "type": "Feature",
  "properties": {
    "addr:full":"Rue De La Lib\u00c9ration 33ba Anhee Namur 5537",
    "addr:housenumber":"33ba",
    "addr:postcode":"5537",
    "addr:street":"Rue De La Libe\u0301Ration;Namur",
    "iso:country":"BE",
    "sg:address":"Rue De La Lib\u00c9ration 33ba",
    "sg:city":"Anhee",
    "sg:classifiers":[
        {
            "category":"Cafe",
            "type":"Food & Drink"
        }
    ],
    "sg:phone":"+32 82 61 39 37",
    "sg:postcode":"5537",
    "sg:province":"Namur",
    "sg:tags":[
        "caf\u00e9s"
    ],
    "wof:name":"Caf\u00c9 Le Stanley",
    "wof:placetype":"venue"
},
  "geometry": {"coordinates":[4.8785319328,50.3118896484],"type":"Point"}
}