{
  "type": "Feature",
  "properties": {
    "addr:full":"Rue De La Poudri\u00e8re 52-54 Bruxelles Bruxelles-Capitale 1000",
    "addr:postcode":"52-54;1000",
    "addr:street":"Rue De La Poudrie\u0300Re",
    "iso:country":"BE",
    "sg:address":"Rue De La Poudri\u00e8re 52-54",
    "sg:city":"Bruxelles",
    "sg:classifiers":[
        {
            "category":"Recreation",
            "subcategory":"Arcade",
            "type":"Entertainment"
        }
    ],
    "sg:phone":"+32 2 512 33 12",
    "sg:postcode":"1000",
    "sg:province":"Bruxelles-Capitale",
    "sg:tags":[
        "machine",
        "amusement"
    ],
    "wof:name":"Jupiter Amumatic Sprl",
    "wof:placetype":"venue"
},
  "geometry": {"coordinates":[4.3389830589,50.8488311768],"type":"Point"}
}