{
  "type": "Feature",
  "properties": {
    "iso:country":"BE",
    "sg:address":"Boomforeeststraat 3",
    "sg:city":"Izegem",
    "sg:classifiers":[
        {
            "category":"Building & Trades",
            "subcategory":"Plumbing",
            "type":"Services"
        }
    ],
    "sg:phone":"+32 51 30 19 82",
    "sg:postcode":"8870",
    "sg:province":"West-Vlaanderen",
    "sg:tags":[
        "diver",
        "commerce",
        "gr",
        "pour",
        "equipement"
    ],
    "wof:name":"Descla",
    "wof:placetype":"venue"
},
  "geometry": {"coordinates":[3.2228479385,50.9155540466],"type":"Point"}
}