{
  "type": "Feature",
  "properties": {
    "iso:country":"BE",
    "sg:address":"Weggevoerdenstraat 1",
    "sg:city":"Tessenderlo",
    "sg:classifiers":[
        {
            "category":"Shopping",
            "subcategory":"Clothing, Apparel, & Fashions",
            "type":"Retail Goods"
        }
    ],
    "sg:phone":"+32 13 66 27 10",
    "sg:postcode":"3980",
    "sg:province":"Limburg",
    "sg:tags":[
        "-",
        "clothing",
        "child"
    ],
    "wof:name":"Pirouette",
    "wof:placetype":"venue"
},
  "geometry": {"coordinates":[5.0912761688,51.0673141479],"type":"Point"}
}