{
  "type": "Feature",
  "properties": {
    "iso:country":"BE",
    "sg:address":"Nederwijk 167",
    "sg:city":"Ninove",
    "sg:orig_category":"D\u00e9chets and d\u00e9bris Gr",
    "sg:phone":"+32 54 33 44 69",
    "sg:postcode":"9400",
    "sg:province":"Oost-Vlaanderen",
    "wof:name":"Petrus Van Waeyenberghe",
    "wof:placetype":"venue"
},
  "geometry": {"coordinates":[4.0313200951,50.8371429443],"type":"Point"}
}