{
  "type": "Feature",
  "properties": {
    "addr:full":"Chauss\u00c9e De Li\u00c8ge 290 Gr\u00c2ce-hollogne Li\u00e8ge 4460",
    "addr:housenumber":"290",
    "addr:postcode":"4460",
    "addr:street":"Chausse\u0301E De Lie\u0300Ge",
    "iso:country":"BE",
    "sg:address":"Chauss\u00c9e De Li\u00c8ge 290",
    "sg:city":"Gr\u00c2ce-hollogne",
    "sg:classifiers":[
        {
            "category":"Restaurant",
            "type":"Food & Drink"
        }
    ],
    "sg:phone":"+32 4 239 11 40",
    "sg:postcode":"4460",
    "sg:province":"Li\u00e8ge",
    "wof:name":"Snack-bar La Valentine",
    "wof:placetype":"venue"
},
  "geometry": {"coordinates":[5.4879860878,50.6470375061],"type":"Point"}
}