{
  "type": "Feature",
  "properties": {
    "iso:country":"BE",
    "sg:address":"Heldenplein 12",
    "sg:city":"Vilvoorde",
    "sg:classifiers":[
        {
            "category":"Health Services",
            "subcategory":"Dentist",
            "type":"Services"
        }
    ],
    "sg:phone":"+32 2 251 05 55",
    "sg:postcode":"1800",
    "sg:province":"Vlaams-Brabant",
    "wof:name":"Hendrickx Elke",
    "wof:placetype":"venue"
},
  "geometry": {"coordinates":[4.4251060486,50.9263877869],"type":"Point"}
}