{
  "type": "Feature",
  "properties": {
    "iso:country":"BE",
    "sg:address":"Filips De Goedelaan 10b5",
    "sg:city":"Brugge",
    "sg:orig_category":"Advocaten and juridische adviseurs",
    "sg:phone":"+32 50 31 27 89",
    "sg:postcode":"8000",
    "sg:province":"West-Vlaanderen",
    "wof:name":"A. Rommel",
    "wof:placetype":"venue"
},
  "geometry": {"coordinates":[3.2137811184,51.2135696411],"type":"Point"}
}