{
  "type": "Feature",
  "properties": {
    "iso:country":"BE",
    "sg:address":"Dorp 73",
    "sg:city":"Bonheiden",
    "sg:classifiers":[
        {
            "category":"Personal",
            "subcategory":"Barber",
            "type":"Services"
        }
    ],
    "sg:phone":"+32 15 51 37 46",
    "sg:postcode":"2820",
    "sg:province":"Antwerpen",
    "sg:tags":[
        "gentleman",
        "salon",
        "-",
        "hairdressing"
    ],
    "wof:name":"Haartooi Guy",
    "wof:placetype":"venue"
},
  "geometry": {"coordinates":[4.5456647873,51.0228652954],"type":"Point"}
}