{
  "type": "Feature",
  "properties": {
    "addr:full":"Albert I Laan 173bf Nieuwpoort West-Vlaanderen 8620",
    "addr:postcode":"8620",
    "addr:street":"Albert I Laan 173Bf",
    "iso:country":"BE",
    "sg:address":"Albert I Laan 173bf",
    "sg:city":"Nieuwpoort",
    "sg:orig_category":"Poissonniers and \u00e9caillers",
    "sg:phone":"+32 58 23 31 69",
    "sg:postcode":"8620",
    "sg:province":"West-Vlaanderen",
    "wof:name":"Huis Devos",
    "wof:placetype":"venue"
},
  "geometry": {"coordinates":[2.7188398838,51.1494140625],"type":"Point"}
}