{
  "type": "Feature",
  "properties": {
    "iso:country":"BE",
    "sg:address":"Maastrichterstraat 74",
    "sg:city":"Tongeren",
    "sg:classifiers":[
        {
            "category":"Shopping",
            "subcategory":"Clothing, Apparel, & Fashions",
            "type":"Retail Goods"
        }
    ],
    "sg:phone":"+32 12 24 10 36",
    "sg:postcode":"3700",
    "sg:province":"Limburg",
    "sg:tags":[
        "v\u00eatements",
        "pour",
        "dame"
    ],
    "wof:name":"Huis Alpina",
    "wof:placetype":"venue"
},
  "geometry": {"coordinates":[5.4667830467,50.7824668884],"type":"Point"}
}