{
  "type": "Feature",
  "properties": {
    "iso:country":"BE",
    "sg:address":"Eeuwfeestlaan 171",
    "sg:city":"Lier",
    "sg:classifiers":[
        {
            "category":"Professional",
            "subcategory":"Accounting & Tax Preparation",
            "type":"Services"
        }
    ],
    "sg:phone":"+32 3 480 16 44",
    "sg:postcode":"2500",
    "sg:province":"Antwerpen",
    "sg:tags":[
        "accountant"
    ],
    "wof:name":"Van Looy E",
    "wof:placetype":"venue"
},
  "geometry": {"coordinates":[4.5659608841,51.1385955811],"type":"Point"}
}