{
  "type": "Feature",
  "properties": {
    "iso:country":"BE",
    "sg:address":"Capucienenstraat 28",
    "sg:city":"Hasselt",
    "sg:classifiers":[
        {
            "category":"Education",
            "subcategory":"School",
            "type":"Public Place"
        }
    ],
    "sg:phone":"+32 11 22 36 65",
    "sg:postcode":"3500",
    "sg:province":"Limburg",
    "sg:tags":[
        "secondary"
    ],
    "wof:name":"Koninklijk Atheneum I Hasselt",
    "wof:placetype":"venue"
},
  "geometry": {"coordinates":[5.3410358429,50.9288673401],"type":"Point"}
}