{
  "type": "Feature",
  "properties": {
    "iso:country":"BE",
    "sg:address":"Rue Du Pont 1",
    "sg:city":"Seraing",
    "sg:orig_category":"Pharmaciens",
    "sg:phone":"+32 4 233 80 01",
    "sg:postcode":"4101",
    "sg:province":"Li\u00e8ge",
    "wof:name":"Pharma-diet",
    "wof:placetype":"venue"
},
  "geometry": {"coordinates":[5.5074210167,50.6174087524],"type":"Point"}
}