{
  "type": "Feature",
  "properties": {
    "addr:full":"Deidenberg 141 Amel Li\u00e8ge 4770",
    "addr:housenumber":"141",
    "addr:postcode":"4770",
    "addr:street":"Deidenberg",
    "iso:country":"BE",
    "sg:address":"Deidenberg 141",
    "sg:city":"Amel",
    "sg:classifiers":[
        {
            "category":"Recreation",
            "subcategory":"Campground",
            "type":"Entertainment"
        }
    ],
    "sg:phone":"+32 80 34 97 47",
    "sg:postcode":"4770",
    "sg:province":"Li\u00e8ge",
    "sg:tags":[
        "site",
        "camping"
    ],
    "wof:name":"Czenier D",
    "wof:placetype":"venue"
},
  "geometry": {"coordinates":[6.1512641907,50.3556022644],"type":"Point"}
}