{
  "type": "Feature",
  "properties": {
    "iso:country":"BE",
    "sg:address":"Rue Albert 1er 72",
    "sg:city":"Beyne-heusay",
    "sg:orig_category":"Installatie van metalen schrijnwerk",
    "sg:phone":"+32 4 358 37 17",
    "sg:postcode":"4610",
    "sg:province":"Li\u00e8ge",
    "wof:name":"Savo Fr\u00c8res",
    "wof:placetype":"venue"
},
  "geometry": {"coordinates":[5.6551218033,50.6202926636],"type":"Point"}
}