{
  "type": "Feature",
  "properties": {
    "addr:full":"Grote Markt 8 Roeselare West-Vlaanderen 8800",
    "addr:housenumber":"8",
    "addr:postcode":"8800",
    "addr:street":"Grote Markt",
    "iso:country":"BE",
    "sg:address":"Grote Markt 8",
    "sg:city":"Roeselare",
    "sg:classifiers":[
        {
            "category":"Restaurant",
            "type":"Food & Drink"
        }
    ],
    "sg:phone":"+32 51 20 40 85",
    "sg:postcode":"8800",
    "sg:province":"West-Vlaanderen",
    "wof:name":"Brasserie Othello",
    "wof:placetype":"venue"
},
  "geometry": {"coordinates":[3.1238350868,50.9448013306],"type":"Point"}
}