{
  "type": "Feature",
  "properties": {
    "addr:full":"Notelarenhof 14 Beveren (beveren-waas) Oost-Vlaanderen 9120",
    "addr:housenumber":"14",
    "addr:postcode":"9120",
    "addr:street":"Notelarenhof;Oost-Vlaanderen",
    "iso:country":"BE",
    "sg:address":"Notelarenhof 14",
    "sg:city":"Beveren (beveren-waas)",
    "sg:classifiers":[
        {
            "category":"Building & Trades",
            "subcategory":"Electrical",
            "type":"Services"
        }
    ],
    "sg:phone":"+32 3 789 09 36",
    "sg:postcode":"9120",
    "sg:province":"Oost-Vlaanderen",
    "sg:tags":[
        "electric",
        "-",
        "housewiring",
        "contractor"
    ],
    "wof:name":"Van Herck",
    "wof:placetype":"venue"
},
  "geometry": {"coordinates":[4.2464389801,51.2197189331],"type":"Point"}
}