{
  "type": "Feature",
  "properties": {
    "iso:country":"BE",
    "sg:address":"Sint-hubrechtsstraat 14",
    "sg:city":"Roeselare",
    "sg:classifiers":[
        {
            "category":"Organizations",
            "subcategory":"Community Association",
            "type":"Services"
        }
    ],
    "sg:phone":"+32 51 24 02 15",
    "sg:postcode":"8800",
    "sg:province":"West-Vlaanderen",
    "sg:tags":[
        "de",
        "h\u00d4tels",
        "restaurant",
        "food",
        "organisation",
        "\u00c0",
        "fast",
        "catering",
        "emporter",
        "f\u00cates",
        "restaurants"
    ],
    "wof:name":"Hotel De Bonte Os",
    "wof:placetype":"venue"
},
  "geometry": {"coordinates":[3.1319000721,50.9483070374],"type":"Point"}
}