{
  "type": "Feature",
  "properties": {
    "iso:country":"BE",
    "sg:address":"Rue L\u00c9on Roger 4",
    "sg:city":"Le Roeulx",
    "sg:classifiers":[
        {
            "category":"Cafe",
            "type":"Food & Drink"
        }
    ],
    "sg:phone":"+32 67 49 02 32",
    "sg:postcode":"7070",
    "sg:province":"Hainaut",
    "sg:tags":[
        "caf\u00e9s"
    ],
    "wof:name":"Caf\u00c9 Le Vert Chasseur",
    "wof:placetype":"venue"
},
  "geometry": {"coordinates":[4.1310768127,50.5409088135],"type":"Point"}
}