{
  "type": "Feature",
  "properties": {
    "addr:full":"Rue De La Pr\u00e2le 32 Hannut (villers-le-peuplier) Li\u00e8ge 4280",
    "addr:housenumber":"32",
    "addr:postcode":"4280",
    "addr:street":"Rue De La Pra\u0302Le;Villers-Le-Peuplier",
    "iso:country":"BE",
    "sg:address":"Rue De La Pr\u00e2le 32",
    "sg:city":"Hannut (villers-le-peuplier)",
    "sg:classifiers":[
        {
            "category":"Building & Trades",
            "subcategory":"Cleaning & Sanitation",
            "type":"Services"
        }
    ],
    "sg:phone":"+32 19 51 49 91",
    "sg:postcode":"4280",
    "sg:province":"Li\u00e8ge",
    "sg:tags":[
        "industrial",
        "-"
    ],
    "wof:name":"Verhulst D",
    "wof:placetype":"venue"
},
  "geometry": {"coordinates":[5.0994720459,50.6595344543],"type":"Point"}
}