{
  "type": "Feature",
  "properties": {
    "iso:country":"BE",
    "sg:address":"Kerkplein 2-4",
    "sg:city":"Ninove",
    "sg:classifiers":[
        {
            "category":"Restaurant",
            "type":"Food & Drink"
        }
    ],
    "sg:phone":"+32 54 33 31 97",
    "sg:postcode":"9400",
    "sg:province":"Oost-Vlaanderen",
    "wof:name":"De Hommel",
    "wof:placetype":"venue"
},
  "geometry": {"coordinates":[4.0216860771,50.8374023438],"type":"Point"}
}