{
  "type": "Feature",
  "properties": {
    "addr:full":"Ambachtenstraat 3 Westerlo Antwerpen 2260",
    "addr:housenumber":"3",
    "addr:postcode":"2260",
    "addr:street":"Ambachtenstraat",
    "iso:country":"BE",
    "sg:address":"Ambachtenstraat 3",
    "sg:city":"Westerlo",
    "sg:classifiers":[
        {
            "category":"Home & Garden",
            "subcategory":"Carpets & Floor Coverings",
            "type":"Retail Goods"
        }
    ],
    "sg:phone":"+32 14 54 46 49",
    "sg:postcode":"2260",
    "sg:province":"Antwerpen",
    "sg:tags":[
        "layer",
        "mosaicists"
    ],
    "wof:name":"Croonenborghs R",
    "wof:placetype":"venue"
},
  "geometry": {"coordinates":[4.9342899323,51.0945320129],"type":"Point"}
}