{
  "type": "Feature",
  "properties": {
    "addr:full":"Beauduinstraat 99 Tienen Vlaams-Brabant 3300",
    "addr:housenumber":"99",
    "addr:postcode":"3300",
    "addr:street":"Beauduinstraat",
    "iso:country":"BE",
    "sg:address":"Beauduinstraat 99",
    "sg:city":"Tienen",
    "sg:classifiers":[
        {
            "category":"Shopping",
            "subcategory":"Musical Instruments",
            "type":"Retail Goods"
        }
    ],
    "sg:phone":"+32 16 82 36 71",
    "sg:postcode":"3300",
    "sg:province":"Vlaams-Brabant",
    "sg:tags":[
        "-"
    ],
    "wof:name":"Music Line",
    "wof:placetype":"venue"
},
  "geometry": {"coordinates":[4.9444289207,50.8035583496],"type":"Point"}
}