{
  "type": "Feature",
  "properties": {
    "addr:full":"Groenendaallaan 96 Antwerpen (merksem) Antwerpen 2170",
    "addr:housenumber":"96",
    "addr:postcode":"2170",
    "addr:street":"Groenendaallaan",
    "iso:country":"BE",
    "sg:address":"Groenendaallaan 96",
    "sg:city":"Antwerpen (merksem)",
    "sg:classifiers":[
        {
            "category":"Health Services",
            "subcategory":"Dentist",
            "type":"Services"
        }
    ],
    "sg:phone":"+32 3 646 67 76",
    "sg:postcode":"2170",
    "sg:province":"Antwerpen",
    "wof:name":"Beosier Michel",
    "wof:placetype":"venue"
},
  "geometry": {"coordinates":[4.4505147934,51.246723175],"type":"Point"}
}