{
  "type": "Feature",
  "properties": {
    "addr:full":"August De Boeckstraat 80 Merchtem Vlaams-Brabant 1785",
    "addr:housenumber":"80",
    "addr:postcode":"1785",
    "addr:street":"August De Boeckstraat",
    "iso:country":"BE",
    "sg:address":"August De Boeckstraat 80",
    "sg:city":"Merchtem",
    "sg:orig_category":"Agences de voyages. Transports terrestres de voyageurs",
    "sg:phone":"+32 52 37 00 43",
    "sg:postcode":"1785",
    "sg:province":"Vlaams-Brabant",
    "wof:name":"Rantour",
    "wof:placetype":"venue"
},
  "geometry": {"coordinates":[4.2255649567,50.9621810913],"type":"Point"}
}