{
  "type": "Feature",
  "properties": {
    "addr:full":"Rue De Monstreux 31 Nivelles Brabant Wallon 1400",
    "addr:housenumber":"31",
    "addr:postcode":"1400",
    "addr:street":"Rue De Monstreux",
    "iso:country":"BE",
    "sg:address":"Rue De Monstreux 31",
    "sg:city":"Nivelles",
    "sg:classifiers":[
        {
            "category":"Health Services",
            "subcategory":"Doctor",
            "type":"Services"
        }
    ],
    "sg:phone":"+32 67 84 16 26",
    "sg:postcode":"1400",
    "sg:province":"Brabant Wallon",
    "sg:tags":[
        "medicinephysicians",
        "surgeon"
    ],
    "wof:name":"Hosselet J-l",
    "wof:placetype":"venue"
},
  "geometry": {"coordinates":[4.3104891777,50.5966339111],"type":"Point"}
}