{
  "type": "Feature",
  "properties": {
    "iso:country":"BE",
    "sg:address":"Rue Du Paradis 79",
    "sg:city":"Fontaine-l\u00b4ev\u00caque",
    "sg:orig_category":"Airconditioning and ventilatie Winkelinrichting and handelsuitrusting Gh",
    "sg:phone":"+32 71 54 16 91",
    "sg:postcode":"6142",
    "sg:province":"Hainaut",
    "wof:name":"Technifrigo",
    "wof:placetype":"venue"
},
  "geometry": {"coordinates":[4.3317341805,50.3967247009],"type":"Point"}
}