{
  "type": "Feature",
  "properties": {
    "iso:country":"BE",
    "sg:address":"Staatsbaan 77a",
    "sg:city":"Ham (kwaadmechelen)",
    "sg:classifiers":[
        {
            "category":"Building & Trades",
            "subcategory":"Construction",
            "type":"Services"
        }
    ],
    "sg:phone":"+32 13 67 77 97",
    "sg:postcode":"3945",
    "sg:province":"Limburg",
    "sg:tags":[
        "ceiling"
    ],
    "wof:name":"Van Hoolst M",
    "wof:placetype":"venue"
},
  "geometry": {"coordinates":[5.1776199341,51.1046104431],"type":"Point"}
}