{
  "type": "Feature",
  "properties": {
    "addr:full":"Rue Grande 27 Beloeil (bas\u00e8cles) Hainaut 7971",
    "addr:housenumber":"27",
    "addr:postcode":"7971",
    "addr:street":"Rue Grande",
    "iso:country":"BE",
    "sg:address":"Rue Grande 27",
    "sg:city":"Beloeil (bas\u00e8cles)",
    "sg:classifiers":[
        {
            "category":"Shopping",
            "subcategory":"Florist",
            "type":"Retail Goods"
        }
    ],
    "sg:phone":"+32 69 66 77 08",
    "sg:postcode":"7971",
    "sg:province":"Hainaut",
    "wof:name":"Hors Saison",
    "wof:placetype":"venue"
},
  "geometry": {"coordinates":[3.6594901085,50.521030426],"type":"Point"}
}