{
  "type": "Feature",
  "properties": {
    "iso:country":"BE",
    "sg:address":"Kloosterstraat 65",
    "sg:city":"Lille",
    "sg:orig_category":"Goederenvervoer over de weg Herstellingen and onderhoud van auto's",
    "sg:phone":"+32 14 55 60 78",
    "sg:postcode":"2275",
    "sg:province":"Antwerpen",
    "wof:name":"Willy Marien",
    "wof:placetype":"venue"
},
  "geometry": {"coordinates":[4.8645701408,51.2649307251],"type":"Point"}
}