{
  "type": "Feature",
  "properties": {
    "addr:full":"Kortrijksesteenweg 685 Gent Oost-Vlaanderen 9000",
    "addr:housenumber":"685",
    "addr:postcode":"9000",
    "addr:street":"Kortrijksesteenweg;Oost-Vlaanderen",
    "iso:country":"BE",
    "sg:address":"Kortrijksesteenweg 685",
    "sg:city":"Gent",
    "sg:classifiers":[
        {
            "category":"Shopping",
            "subcategory":"Discount & Variety Stores",
            "type":"Retail Goods"
        }
    ],
    "sg:phone":"+32 9 329 72 55",
    "sg:postcode":"9000",
    "sg:province":"Oost-Vlaanderen",
    "sg:tags":[
        "shop",
        "night"
    ],
    "wof:name":"Moon Star",
    "wof:placetype":"venue"
},
  "geometry": {"coordinates":[3.7123138905,51.0297088623],"type":"Point"}
}