{
  "type": "Feature",
  "properties": {
    "iso:country":"BE",
    "sg:address":"Grasdreef 39",
    "sg:city":"Waregem",
    "sg:orig_category":"Artiesten and kunstenaars",
    "sg:phone":"+32 56 60 42 78",
    "sg:postcode":"8790",
    "sg:province":"West-Vlaanderen",
    "wof:name":"Geert Opsomer",
    "wof:placetype":"venue"
},
  "geometry": {"coordinates":[3.4539499283,50.893196106],"type":"Point"}
}