{
  "type": "Feature",
  "properties": {
    "iso:country":"BE",
    "sg:address":"Beemdenstraat 7",
    "sg:city":"Ranst",
    "sg:orig_category":"Afval and schroot Gh",
    "sg:phone":"+32 3 485 54 37",
    "sg:postcode":"2520",
    "sg:province":"Antwerpen",
    "wof:name":"Christiaan Smets",
    "wof:placetype":"venue"
},
  "geometry": {"coordinates":[4.6198868752,51.1840820312],"type":"Point"}
}