{
  "type": "Feature",
  "properties": {
    "addr:full":"Tiensestraat 278 Leuven Vlaams-Brabant 3000",
    "addr:housenumber":"278",
    "addr:postcode":"3000",
    "addr:street":"Tiensestraat",
    "iso:country":"BE",
    "sg:address":"Tiensestraat 278",
    "sg:city":"Leuven",
    "sg:classifiers":[
        {
            "category":"Home & Garden",
            "subcategory":"Kitchen Supply",
            "type":"Retail Goods"
        }
    ],
    "sg:phone":"+32 16 20 23 56",
    "sg:postcode":"3000",
    "sg:province":"Vlaams-Brabant",
    "sg:tags":[
        "-",
        "industrial",
        "installation",
        "equipment"
    ],
    "wof:name":"M.r. Grootkeukens & Cooling Bvba",
    "wof:placetype":"venue"
},
  "geometry": {"coordinates":[4.7132778168,50.8736495972],"type":"Point"}
}