{
  "type": "Feature",
  "properties": {
    "iso:country":"BE",
    "sg:address":"Heistraat 217",
    "sg:city":"Sint-niklaas",
    "sg:classifiers":[
        {
            "category":"Health Services",
            "subcategory":"Health Practitioner",
            "type":"Services"
        }
    ],
    "sg:phone":"+32 3 776 37 67",
    "sg:postcode":"9100",
    "sg:province":"Oost-Vlaanderen",
    "sg:tags":[
        "physiotherapist"
    ],
    "wof:name":"Otten Marleen",
    "wof:placetype":"venue"
},
  "geometry": {"coordinates":[4.1378550529,51.1757850647],"type":"Point"}
}