{
  "type": "Feature",
  "properties": {
    "iso:country":"BE",
    "sg:address":"Grote Goddaard 32",
    "sg:city":"Antwerpen",
    "sg:orig_category":"V\u00eatements",
    "sg:phone":"+32 3 227 12 27",
    "sg:postcode":"2000",
    "sg:province":"Antwerpen",
    "wof:name":"Gwendoline Eeckels",
    "wof:placetype":"venue"
},
  "geometry": {"coordinates":[4.4045948982,51.2215538025],"type":"Point"}
}