{
  "type": "Feature",
  "properties": {
    "addr:full":"Rue Du Corbeau 53 Dison Li\u00e8ge 4820",
    "addr:housenumber":"53",
    "addr:postcode":"4820",
    "addr:street":"Rue Du Corbeau",
    "iso:country":"BE",
    "sg:address":"Rue Du Corbeau 53",
    "sg:city":"Dison",
    "sg:orig_category":"Architectes",
    "sg:phone":"+32 87 33 83 03",
    "sg:postcode":"4820",
    "sg:province":"Li\u00e8ge",
    "wof:name":"Kara Nahit",
    "wof:placetype":"venue"
},
  "geometry": {"coordinates":[5.8558588028,50.6174583435],"type":"Point"}
}