{
  "type": "Feature",
  "properties": {
    "addr:full":"Perronstraat 8 Bilzen Limburg 3740",
    "addr:housenumber":"8",
    "addr:postcode":"3740",
    "addr:street":"Perronstraat",
    "iso:country":"BE",
    "sg:address":"Perronstraat 8",
    "sg:city":"Bilzen",
    "sg:orig_category":"Journaux",
    "sg:phone":"+32 89 50 22 76",
    "sg:postcode":"3740",
    "sg:province":"Limburg",
    "wof:name":"Landrada",
    "wof:placetype":"venue"
},
  "geometry": {"coordinates":[5.5268740654,50.8890342712],"type":"Point"}
}