{
  "type": "Feature",
  "properties": {
    "addr:full":"Chauss\u00c9e De Renaix 10 Tournai Hainaut 7500",
    "addr:housenumber":"10",
    "addr:postcode":"7500",
    "addr:street":"Chausse\u0301E De Renaix",
    "iso:country":"BE",
    "sg:address":"Chauss\u00c9e De Renaix 10",
    "sg:city":"Tournai",
    "sg:orig_category":"Epiceries. Fleurs and plantes",
    "sg:phone":"+32 69 84 45 17",
    "sg:postcode":"7500",
    "sg:province":"Hainaut",
    "wof:name":"Fleurs Jo\u00cblle",
    "wof:placetype":"venue"
},
  "geometry": {"coordinates":[3.4032280445,50.6126747131],"type":"Point"}
}