{
  "type": "Feature",
  "properties": {
    "addr:full":"Rue Des Chardonnerets 2b11 Wanze Li\u00e8ge 4520",
    "addr:housenumber":"2b11",
    "addr:postcode":"4520",
    "addr:street":"Rue Des Chardonnerets",
    "iso:country":"BE",
    "sg:address":"Rue Des Chardonnerets 2b11",
    "sg:city":"Wanze",
    "sg:classifiers":[
        {
            "category":"Arena",
            "subcategory":"Sports Club",
            "type":"Entertainment"
        }
    ],
    "sg:phone":"+32 85 25 47 75",
    "sg:postcode":"4520",
    "sg:province":"Li\u00e8ge",
    "sg:tags":[
        "terrain",
        "hors",
        "de",
        "installation",
        "sportifs"
    ],
    "wof:name":"Racing Club Ahin",
    "wof:placetype":"venue"
},
  "geometry": {"coordinates":[5.204788208,50.5333061218],"type":"Point"}
}