{
  "type": "Feature",
  "properties": {
    "addr:full":"Rue De Thirimont 2 Mons Hainaut 7000",
    "addr:housenumber":"2",
    "addr:postcode":"7000",
    "addr:street":"Rue De Thirimont;Hainaut",
    "iso:country":"BE",
    "sg:address":"Rue De Thirimont 2",
    "sg:city":"Mons",
    "sg:orig_category":"Plomberie, chauffage and installations sanitaires. Charpentes and couvertures",
    "sg:phone":"+32 65 84 56 18",
    "sg:postcode":"7000",
    "sg:province":"Hainaut",
    "wof:name":"Luc Et Poivre",
    "wof:placetype":"venue"
},
  "geometry": {"coordinates":[3.9523320198,50.446269989],"type":"Point"}
}