{
  "type": "Feature",
  "properties": {
    "addr:full":"Rue D\u00e9sir\u00e9 Maroille 27 Saint-ghislain (tertre) Hainaut 7333",
    "addr:housenumber":"27",
    "addr:postcode":"7333",
    "addr:street":"Rue De\u0301Sire\u0301 Maroille",
    "iso:country":"BE",
    "sg:address":"Rue D\u00e9sir\u00e9 Maroille 27",
    "sg:city":"Saint-ghislain (tertre)",
    "sg:classifiers":[
        {
            "category":"Retail",
            "subcategory":"Auto Repair",
            "type":"Services"
        }
    ],
    "sg:phone":"+32 65 64 47 30",
    "sg:postcode":"7333",
    "sg:province":"Hainaut",
    "sg:tags":[
        "automobile-body"
    ],
    "wof:name":"Carrosserie Franzese",
    "wof:placetype":"venue"
},
  "geometry": {"coordinates":[3.8111400604,50.4655151367],"type":"Point"}
}