{
  "type": "Feature",
  "properties": {
    "addr:full":"Minderbroedersstraat 1 Brugge West-Vlaanderen 8000",
    "addr:housenumber":"1",
    "addr:postcode":"8000",
    "addr:street":"Minderbroedersstraat",
    "iso:country":"BE",
    "sg:address":"Minderbroedersstraat 1",
    "sg:city":"Brugge",
    "sg:orig_category":"Eclairage et \u00e9quipements du foyer. Restaurants",
    "sg:phone":"+32 50 34 64 42",
    "sg:postcode":"8000",
    "sg:province":"West-Vlaanderen",
    "wof:name":"Restaurant Home Fleuri",
    "wof:placetype":"venue"
},
  "geometry": {"coordinates":[3.2308530807,51.2073478699],"type":"Point"}
}