{
  "type": "Feature",
  "properties": {
    "addr:full":"Trieu Bouton 24 Chimay Hainaut 6464",
    "addr:housenumber":"24",
    "addr:postcode":"6464",
    "addr:street":"Bouton",
    "iso:country":"BE",
    "sg:address":"Trieu Bouton 24",
    "sg:city":"Chimay",
    "sg:orig_category":"Plomberie, chauffage and installations sanitaires",
    "sg:phone":"+32 60 21 23 67",
    "sg:postcode":"6464",
    "sg:province":"Hainaut",
    "wof:name":"Dominique Gillard",
    "wof:placetype":"venue"
},
  "geometry": {"coordinates":[4.3740539551,50.0203971863],"type":"Point"}
}