{
  "type": "Feature",
  "properties": {
    "iso:country":"BE",
    "sg:address":"Rue Du Bureau 16",
    "sg:city":"Fleron",
    "sg:orig_category":"Fleurs and plantes",
    "sg:phone":"+32 4 355 10 81",
    "sg:postcode":"4621",
    "sg:province":"Li\u00e8ge",
    "wof:name":"Fleurs Vegetal",
    "wof:placetype":"venue"
},
  "geometry": {"coordinates":[5.689371109,50.6141052246],"type":"Point"}
}