{
  "type": "Feature",
  "properties": {
    "addr:full":"Rue De Huy 67 Waremme Li\u00e8ge 4300",
    "addr:housenumber":"67",
    "addr:postcode":"4300",
    "addr:street":"Rue De Huy",
    "iso:country":"BE",
    "sg:address":"Rue De Huy 67",
    "sg:city":"Waremme",
    "sg:classifiers":[
        {
            "category":"Personal",
            "subcategory":"Barber",
            "type":"Services"
        }
    ],
    "sg:phone":"+32 19 32 81 21",
    "sg:postcode":"4300",
    "sg:province":"Li\u00e8ge",
    "sg:tags":[
        "gentleman",
        "salon",
        "-",
        "hairdressing"
    ],
    "wof:name":"Coupe-tifs Constant",
    "wof:placetype":"venue"
},
  "geometry": {"coordinates":[5.2513160706,50.6917877197],"type":"Point"}
}