{
  "type": "Feature",
  "properties": {
    "addr:full":"Parklaan 48fb2 Aalst Oost-Vlaanderen 9300",
    "addr:housenumber":"48fb2",
    "addr:postcode":"9300",
    "addr:street":"Parklaan",
    "iso:country":"BE",
    "sg:address":"Parklaan 48fb2",
    "sg:city":"Aalst",
    "sg:classifiers":[
        {
            "category":"Insurance",
            "subcategory":"Life Insurance",
            "type":"Services"
        }
    ],
    "sg:phone":"+32 53 77 45 90",
    "sg:postcode":"9300",
    "sg:province":"Oost-Vlaanderen",
    "sg:tags":[
        "assurance"
    ],
    "wof:name":"Roelant",
    "wof:placetype":"venue"
},
  "geometry": {"coordinates":[4.0366950035,50.9280509949],"type":"Point"}
}