{
  "type": "Feature",
  "properties": {
    "iso:country":"BE",
    "sg:address":"Leugenberg 55",
    "sg:city":"Antwerpen",
    "sg:orig_category":"Voedingsspeciaalzaken",
    "sg:phone":"+32 3 605 18 13",
    "sg:postcode":"2030",
    "sg:province":"Antwerpen",
    "wof:name":"Traiteur De Genieter",
    "wof:placetype":"venue"
},
  "geometry": {"coordinates":[4.4118819237,51.2909164429],"type":"Point"}
}