{
  "type": "Feature",
  "properties": {
    "iso:country":"BE",
    "sg:address":"Vrijdagmarkt 48",
    "sg:city":"Gent",
    "sg:orig_category":"Eclairage et \u00e9quipements du foyer. Textiles",
    "sg:phone":"+32 9 225 14 79",
    "sg:postcode":"9000",
    "sg:province":"Oost-Vlaanderen",
    "wof:name":"Artstof",
    "wof:placetype":"venue"
},
  "geometry": {"coordinates":[3.7253389359,51.0565338135],"type":"Point"}
}