{
  "type": "Feature",
  "properties": {
    "addr:full":"Kruisstraat 37 Overijse Vlaams-Brabant 3090",
    "addr:housenumber":"37",
    "addr:postcode":"3090",
    "addr:street":"Kruisstraat",
    "iso:country":"BE",
    "sg:address":"Kruisstraat 37",
    "sg:city":"Overijse",
    "sg:classifiers":[
        {
            "category":"Personal",
            "subcategory":"Nail Salon",
            "type":"Services"
        }
    ],
    "sg:phone":"+32 2 687 39 34",
    "sg:postcode":"3090",
    "sg:province":"Vlaams-Brabant",
    "sg:tags":[
        "pedicure"
    ],
    "wof:name":"Martine",
    "wof:placetype":"venue"
},
  "geometry": {"coordinates":[4.5249028206,50.7644081116],"type":"Point"}
}