{
  "type": "Feature",
  "properties": {
    "addr:full":"Rue Du Ch\u00c2teau 7ba Tournai Hainaut 7543",
    "addr:postcode":"7ba;7543",
    "addr:street":"Rue Du Cha\u0302Teau;Hainaut",
    "iso:country":"BE",
    "sg:address":"Rue Du Ch\u00c2teau 7ba",
    "sg:city":"Tournai",
    "sg:orig_category":"Evaluation and estimation de biens immobiliers. G\u00e9om\u00e8tres",
    "sg:phone":"+32 69 85 95 13",
    "sg:postcode":"7543",
    "sg:province":"Hainaut",
    "wof:name":"Christian De Viron",
    "wof:placetype":"venue"
},
  "geometry": {"coordinates":[3.3876080513,50.6111450195],"type":"Point"}
}