{
  "type": "Feature",
  "properties": {
    "addr:full":"Rue Jean Deremince 23 Namur Namur 5000",
    "addr:housenumber":"23",
    "addr:postcode":"5000",
    "addr:street":"Rue Jean Deremince",
    "iso:country":"BE",
    "sg:address":"Rue Jean Deremince 23",
    "sg:city":"Namur",
    "sg:orig_category":"Etalage- and showroomontwerpers",
    "sg:phone":"+32 81 22 14 61",
    "sg:postcode":"5000",
    "sg:province":"Namur",
    "wof:name":"Monique Flahaux",
    "wof:placetype":"venue"
},
  "geometry": {"coordinates":[4.9116330147,50.4697151184],"type":"Point"}
}