{
  "type": "Feature",
  "properties": {
    "addr:full":"Chauss\u00c9e De Waterloo 1359c Ukkel/uccle Bruxelles-Capitale 1180",
    "addr:housenumber":"1359c",
    "addr:postcode":"1180",
    "addr:street":"Chausse\u0301E De Waterloo;/",
    "iso:country":"BE",
    "sg:address":"Chauss\u00c9e De Waterloo 1359c",
    "sg:city":"Ukkel/uccle",
    "sg:orig_category":"Instituts de beaut\u00e9",
    "sg:phone":"+32 2 375 38 98",
    "sg:postcode":"1180",
    "sg:province":"Bruxelles-Capitale",
    "wof:name":"Institut De Soins Esth\u00c9tique Fort Jaco",
    "wof:placetype":"venue"
},
  "geometry": {"coordinates":[4.3748860359,50.7888832092],"type":"Point"}
}