{
  "type": "Feature",
  "properties": {
    "iso:country":"BE",
    "sg:address":"Goronne 30",
    "sg:city":"Vielsalm",
    "sg:classifiers":[
        {
            "category":"Real Estate",
            "subcategory":"Architect",
            "type":"Services"
        }
    ],
    "sg:phone":"+32 80 21 58 06",
    "sg:postcode":"6690",
    "sg:province":"Luxembourg",
    "wof:name":"Molhan R",
    "wof:placetype":"venue"
},
  "geometry": {"coordinates":[5.865650177,50.289100647],"type":"Point"}
}