{
  "type": "Feature",
  "properties": {
    "addr:full":"Potaardestraat 16 Kraainem Vlaams-Brabant 1950",
    "addr:housenumber":"16",
    "addr:postcode":"1950",
    "addr:street":"Potaardestraat",
    "iso:country":"BE",
    "sg:address":"Potaardestraat 16",
    "sg:city":"Kraainem",
    "sg:orig_category":"Tuinbenodigdheden",
    "sg:phone":"+32 2 731 45 58",
    "sg:postcode":"1950",
    "sg:province":"Vlaams-Brabant",
    "wof:name":"Stock L. Garden",
    "wof:placetype":"venue"
},
  "geometry": {"coordinates":[4.4677062035,50.8402137756],"type":"Point"}
}