{
  "type": "Feature",
  "properties": {
    "iso:country":"BE",
    "sg:address":"Rue Fontaine Saint-pierre 1fbis",
    "sg:city":"Assesse",
    "sg:classifiers":[
        {
            "category":"Retail",
            "subcategory":"Repair Shop",
            "type":"Services"
        }
    ],
    "sg:phone":"+32 83 65 68 72",
    "sg:postcode":"5330",
    "sg:province":"Namur",
    "sg:tags":[
        "radio",
        "television",
        "-",
        "maintenance"
    ],
    "wof:name":"Delta Electronics Sprl",
    "wof:placetype":"venue"
},
  "geometry": {"coordinates":[5.0442857742,50.3694496155],"type":"Point"}
}