{
  "type": "Feature",
  "properties": {
    "iso:country":"BE",
    "sg:address":"Avenue De Philippeville 211 Box 5",
    "sg:city":"Charleroi (marcinelle)",
    "sg:classifiers":[
        {
            "category":"Shopping",
            "subcategory":"Computers & Home Electronics",
            "type":"Retail Goods"
        }
    ],
    "sg:phone":"+32 71 43 90 81",
    "sg:postcode":"6001",
    "sg:province":"Hainaut",
    "sg:tags":[
        "sound",
        "equipment",
        "-",
        "system"
    ],
    "wof:name":"Sono-sim Sprl",
    "wof:placetype":"venue"
},
  "geometry": {"coordinates":[4.4560809135,50.3957328796],"type":"Point"}
}