{
  "type": "Feature",
  "properties": {
    "addr:full":"Spinnerijstraat 12 Zele Oost-Vlaanderen 9240",
    "addr:housenumber":"12",
    "addr:postcode":"9240",
    "addr:street":"Spinnerijstraat",
    "iso:country":"BE",
    "sg:address":"Spinnerijstraat 12",
    "sg:city":"Zele",
    "sg:orig_category":"Drukkerijen and copyshops",
    "sg:phone":"+32 52 45 42 00",
    "sg:postcode":"9240",
    "sg:province":"Oost-Vlaanderen",
    "wof:name":"Ahrend",
    "wof:placetype":"venue"
},
  "geometry": {"coordinates":[4.0470399857,51.0749092102],"type":"Point"}
}