{
  "type": "Feature",
  "properties": {
    "iso:country":"BE",
    "sg:address":"Basiliekstraat 101",
    "sg:city":"Halle",
    "sg:orig_category":"V\u00eatements",
    "sg:phone":"+32 2 361 07 30",
    "sg:postcode":"1500",
    "sg:province":"Vlaams-Brabant",
    "wof:name":"Rapido",
    "wof:placetype":"venue"
},
  "geometry": {"coordinates":[4.2362031937,50.7338638306],"type":"Point"}
}