{
  "type": "Feature",
  "properties": {
    "addr:full":"Hogestraat 63 Staden West-Vlaanderen 8840",
    "addr:housenumber":"63",
    "addr:postcode":"8840",
    "addr:street":"Hogestraat",
    "iso:country":"BE",
    "sg:address":"Hogestraat 63",
    "sg:city":"Staden",
    "sg:orig_category":"Varkenskwekers",
    "sg:phone":"+32 51 70 16 29",
    "sg:postcode":"8840",
    "sg:province":"West-Vlaanderen",
    "wof:name":"Luc Van Raes",
    "wof:placetype":"venue"
},
  "geometry": {"coordinates":[2.9872400761,50.9810218811],"type":"Point"}
}