{
  "type": "Feature",
  "properties": {
    "iso:country":"BE",
    "sg:address":"Hayenhoek 92",
    "sg:city":"Neerpelt",
    "sg:orig_category":"Kapsalons",
    "sg:phone":"+32 11 66 37 87",
    "sg:postcode":"3910",
    "sg:province":"Limburg",
    "wof:name":"Coiffure Simona",
    "wof:placetype":"venue"
},
  "geometry": {"coordinates":[5.4337000847,51.2365913391],"type":"Point"}
}