{
  "type": "Feature",
  "properties": {
    "addr:full":"Rue L\u00e9on Hanozet 4 Eghez\u00e9e (bolinne) Namur 5310",
    "addr:housenumber":"4",
    "addr:postcode":"5310",
    "addr:street":"Rue Le\u0301On Hanozet;Bolinne",
    "iso:country":"BE",
    "sg:address":"Rue L\u00e9on Hanozet 4",
    "sg:city":"Eghez\u00e9e (bolinne)",
    "sg:classifiers":[
        {
            "category":"Home & Garden",
            "subcategory":"Carpets & Floor Coverings",
            "type":"Retail Goods"
        }
    ],
    "sg:phone":"+32 81 43 59 82",
    "sg:postcode":"5310",
    "sg:province":"Namur",
    "sg:tags":[
        "-"
    ],
    "wof:name":"Bocca E",
    "wof:placetype":"venue"
},
  "geometry": {"coordinates":[4.9161930084,50.6084823608],"type":"Point"}
}