{
  "type": "Feature",
  "properties": {
    "addr:full":"Av. G\u00c9ner. Med. Derache 94b9 Elsene/ixelles Bruxelles-Capitale 1050",
    "addr:housenumber":"94b9",
    "addr:postcode":"1050",
    "addr:street":"Av. Ge\u0301Ner Med. Derache",
    "iso:country":"BE",
    "sg:address":"Av. G\u00c9ner. Med. Derache 94b9",
    "sg:city":"Elsene/ixelles",
    "sg:orig_category":"Avocats and conseillers juridiques",
    "sg:phone":"+32 2 640 15 99",
    "sg:postcode":"1050",
    "sg:province":"Bruxelles-Capitale",
    "wof:name":"J.p. Arends",
    "wof:placetype":"venue"
},
  "geometry": {"coordinates":[4.3882131577,50.8147201538],"type":"Point"}
}