{
  "type": "Feature",
  "properties": {
    "iso:country":"BE",
    "sg:address":"Doorniksewijk 52",
    "sg:city":"Kortrijk",
    "sg:orig_category":"Elektrische installaties voor woningen HERSTELLING ELEKTRISCHE HUISHOUDAPPARATEN Huishoudapparaten, ",
    "sg:phone":"+32 56 22 23 32",
    "sg:postcode":"8500",
    "sg:province":"West-Vlaanderen",
    "wof:name":"Electro Dobbeleir",
    "wof:placetype":"venue"
},
  "geometry": {"coordinates":[3.2685039043,50.8219642639],"type":"Point"}
}