{
  "type": "Feature",
  "properties": {
    "iso:country":"BE",
    "sg:address":"Stationsstraat 47a",
    "sg:city":"Sint-truiden",
    "sg:classifiers":[
        {
            "category":"Building & Trades",
            "subcategory":"Electrical",
            "type":"Services"
        }
    ],
    "sg:phone":"+32 11 68 50 44",
    "sg:postcode":"3800",
    "sg:province":"Limburg",
    "sg:tags":[
        "electric",
        "-",
        "housewiring",
        "contractor"
    ],
    "wof:name":"Selis Bvba",
    "wof:placetype":"venue"
},
  "geometry": {"coordinates":[5.1778459549,50.8169250488],"type":"Point"}
}