{
  "type": "Feature",
  "properties": {
    "iso:country":"BE",
    "sg:address":"Laagweg 93",
    "sg:city":"Wervik",
    "sg:orig_category":"Rundveehouders",
    "sg:phone":"+32 56 31 47 49",
    "sg:postcode":"8940",
    "sg:province":"West-Vlaanderen",
    "wof:name":"Jean Feys",
    "wof:placetype":"venue"
},
  "geometry": {"coordinates":[3.0727519989,50.7831993103],"type":"Point"}
}