{
  "type": "Feature",
  "properties": {
    "addr:full":"Oostmalsebaan 66 Brecht Antwerpen 2960",
    "addr:housenumber":"66",
    "addr:postcode":"2960",
    "addr:street":"Oostmalsebaan",
    "iso:country":"BE",
    "sg:address":"Oostmalsebaan 66",
    "sg:city":"Brecht",
    "sg:orig_category":"Entretien and r\u00e9parations de voitures. Entretien et r\u00e9parations de v\u00e9hicules \u00e0 domicile. R\u00e9cup\u00e9ratio",
    "sg:phone":"+32 3 313 86 59",
    "sg:postcode":"2960",
    "sg:province":"Antwerpen",
    "wof:name":"De Bruyn",
    "wof:placetype":"venue"
},
  "geometry": {"coordinates":[4.6415200233,51.3512115479],"type":"Point"}
}