{
  "type": "Feature",
  "properties": {
    "iso:country":"BE",
    "sg:address":"Place Albert-ier 13",
    "sg:city":"Nivelles",
    "sg:orig_category":"Advocaten and juridische adviseurs",
    "sg:phone":"+32 67 21 79 95",
    "sg:postcode":"1400",
    "sg:province":"Brabant Wallon",
    "wof:name":"J.f. Funck",
    "wof:placetype":"venue"
},
  "geometry": {"coordinates":[4.3224987984,50.5977478027],"type":"Point"}
}