{
  "type": "Feature",
  "properties": {
    "iso:country":"BE",
    "sg:address":"Rue Des Mimosas 13",
    "sg:city":"Beyne-heusay",
    "sg:classifiers":[
        {
            "category":"Professional",
            "subcategory":"Accounting & Tax Preparation",
            "type":"Services"
        }
    ],
    "sg:phone":"+32 4 358 94 25",
    "sg:postcode":"4610",
    "sg:province":"Li\u00e8ge",
    "sg:tags":[
        "bookkeeper"
    ],
    "wof:name":"Bury Ph",
    "wof:placetype":"venue"
},
  "geometry": {"coordinates":[5.6656742096,50.6273002625],"type":"Point"}
}