{
  "type": "Feature",
  "properties": {
    "iso:country":"BE",
    "sg:address":"Poti\u00c9rue 45",
    "sg:city":"Herve",
    "sg:orig_category":"Apotheken",
    "sg:phone":"+32 87 67 40 59",
    "sg:postcode":"4650",
    "sg:province":"Li\u00e8ge",
    "wof:name":"Pharmacie Braham",
    "wof:placetype":"venue"
},
  "geometry": {"coordinates":[5.7942991257,50.6403923035],"type":"Point"}
}