{
  "type": "Feature",
  "properties": {
    "addr:full":"Koningin Astridlaan 27 Maldegem Oost-Vlaanderen 9990",
    "addr:housenumber":"27",
    "addr:postcode":"9990",
    "addr:street":"Koningin Astridlaan",
    "iso:country":"BE",
    "sg:address":"Koningin Astridlaan 27",
    "sg:city":"Maldegem",
    "sg:orig_category":"Pain, p\u00e2tisseries and confiseries",
    "sg:phone":"+32 50 71 23 11",
    "sg:postcode":"9990",
    "sg:province":"Oost-Vlaanderen",
    "wof:name":"Daniel Blomme",
    "wof:placetype":"venue"
},
  "geometry": {"coordinates":[3.4312009811,51.2066612244],"type":"Point"}
}