{
  "type": "Feature",
  "properties": {
    "addr:full":"Place De Cuesmes 43 Mons (cuesmes) Hainaut 7033",
    "addr:housenumber":"43",
    "addr:postcode":"7033",
    "addr:street":"Place De Cuesmes",
    "iso:country":"BE",
    "sg:address":"Place De Cuesmes 43",
    "sg:city":"Mons (cuesmes)",
    "sg:classifiers":[
        {
            "category":"Shopping",
            "subcategory":"Jewelry",
            "type":"Retail Goods"
        }
    ],
    "sg:phone":"+32 65 35 39 06",
    "sg:postcode":"7033",
    "sg:province":"Hainaut",
    "sg:tags":[
        "jeweller",
        "-"
    ],
    "wof:name":"Stievenart",
    "wof:placetype":"venue"
},
  "geometry": {"coordinates":[3.9405260086,50.4501457214],"type":"Point"}
}