{
  "type": "Feature",
  "properties": {
    "addr:full":"Statiestraat 142 Zwijndrecht Antwerpen 2070",
    "addr:housenumber":"142",
    "addr:postcode":"2070",
    "addr:street":"Statiestraat",
    "iso:country":"BE",
    "sg:address":"Statiestraat 142",
    "sg:city":"Zwijndrecht",
    "sg:orig_category":"Sportclubs Sportterreinen and installaties behalve sportcentra",
    "sg:phone":"+32 3 252 56 96",
    "sg:postcode":"2070",
    "sg:province":"Antwerpen",
    "wof:name":"Meteoor",
    "wof:placetype":"venue"
},
  "geometry": {"coordinates":[4.3294830322,51.2148742676],"type":"Point"}
}