{
  "type": "Feature",
  "properties": {
    "iso:country":"BE",
    "sg:address":"Warandestraat 2",
    "sg:city":"Torhout",
    "sg:orig_category":"Installation \u00e9lectrique r\u00e9sidentielle",
    "sg:phone":"+32 50 21 47 22",
    "sg:postcode":"8820",
    "sg:province":"West-Vlaanderen",
    "wof:name":"Andy De Min",
    "wof:placetype":"venue"
},
  "geometry": {"coordinates":[3.0960550308,51.0795173645],"type":"Point"}
}