{
  "type": "Feature",
  "properties": {
    "addr:full":"Grand Place 27 Mons Hainaut 7000",
    "addr:housenumber":"27",
    "addr:postcode":"7000",
    "addr:street":"Grand Place;Hainaut",
    "iso:country":"BE",
    "sg:address":"Grand Place 27",
    "sg:city":"Mons",
    "sg:classifiers":[
        {
            "category":"Fast Food",
            "type":"Food & Drink"
        }
    ],
    "sg:phone":"+32 65 59 03 90",
    "sg:postcode":"7000",
    "sg:province":"Hainaut",
    "sg:tags":[
        "meeneem",
        "restaurant"
    ],
    "wof:name":"Pizza Hut",
    "wof:placetype":"venue"
},
  "geometry": {"coordinates":[3.9517929554,50.4544372559],"type":"Point"}
}