{
  "type": "Feature",
  "properties": {
    "iso:country":"BE",
    "sg:address":"Rue Du Bois 41",
    "sg:city":"Braine-le-chateau",
    "sg:orig_category":"Eleveurs de bovins",
    "sg:phone":"+32 2 366 92 32",
    "sg:postcode":"1440",
    "sg:province":"Brabant Wallon",
    "wof:name":"Bertrand Castel",
    "wof:placetype":"venue"
},
  "geometry": {"coordinates":[4.3289551735,50.6846008301],"type":"Point"}
}