{
  "type": "Feature",
  "properties": {
    "iso:country":"BE",
    "sg:address":"Victor Rauterstraat 49",
    "sg:city":"Anderlecht",
    "sg:orig_category":"Elektrische installaties voor woningen",
    "sg:phone":"+32 486 53 43 47",
    "sg:postcode":"1070",
    "sg:province":"Bruxelles-Capitale",
    "wof:name":"Technica-paolillo",
    "wof:placetype":"venue"
},
  "geometry": {"coordinates":[4.3125801086,50.8351707458],"type":"Point"}
}