{
  "type": "Feature",
  "properties": {
    "addr:full":"Hengstenberg 106 Overijse Vlaams-Brabant 3090",
    "addr:housenumber":"106",
    "addr:postcode":"3090",
    "addr:street":"Hengstenberg",
    "iso:country":"BE",
    "sg:address":"Hengstenberg 106",
    "sg:city":"Overijse",
    "sg:classifiers":[
        {
            "category":"Professional",
            "type":"Services"
        }
    ],
    "sg:phone":"+32 2 687 96 28",
    "sg:postcode":"3090",
    "sg:province":"Vlaams-Brabant",
    "sg:tags":[
        "industrial",
        "automation"
    ],
    "wof:name":"Van Del Bvba",
    "wof:placetype":"venue"
},
  "geometry": {"coordinates":[4.5013399124,50.7795715332],"type":"Point"}
}