{
  "type": "Feature",
  "properties": {
    "addr:full":"Rue De L\u00b4egalit\u00c9 223 Soumagne Li\u00e8ge 4630",
    "addr:housenumber":"223",
    "addr:postcode":"4630",
    "addr:street":"Rue De L\u00b4Egalite\u0301",
    "iso:country":"BE",
    "sg:address":"Rue De L\u00b4egalit\u00c9 223",
    "sg:city":"Soumagne",
    "sg:orig_category":"Charpentes and couvertures. Plomberie, chauffage and installations sanitaires",
    "sg:phone":"+32 4 377 26 62",
    "sg:postcode":"4630",
    "sg:province":"Li\u00e8ge",
    "wof:name":"Les Plombiers",
    "wof:placetype":"venue"
},
  "geometry": {"coordinates":[5.7417001724,50.6219100952],"type":"Point"}
}