{
  "type": "Feature",
  "properties": {
    "addr:full":"Voies De Renlies 9 Sivry-rance Hainaut 6470",
    "addr:housenumber":"9",
    "addr:postcode":"6470",
    "addr:street":"Voies;Renlies",
    "iso:country":"BE",
    "sg:address":"Voies De Renlies 9",
    "sg:city":"Sivry-rance",
    "sg:orig_category":"Eleveurs de volaille",
    "sg:phone":"+32 60 45 59 41",
    "sg:postcode":"6470",
    "sg:province":"Hainaut",
    "wof:name":"Poulet Chevrotin",
    "wof:placetype":"venue"
},
  "geometry": {"coordinates":[4.1969251633,50.1734199524],"type":"Point"}
}