{
  "type": "Feature",
  "properties": {
    "iso:country":"BE",
    "sg:address":"Rue Chemin-rue 41",
    "sg:city":"Malmedy",
    "sg:classifiers":[
        {
            "category":"Shopping",
            "subcategory":"Bicycles & Sporting Goods",
            "type":"Retail Goods"
        }
    ],
    "sg:phone":"+32 80 33 93 40",
    "sg:postcode":"4960",
    "sg:province":"Li\u00e8ge",
    "sg:tags":[
        "sport",
        "-"
    ],
    "wof:name":"Solheid Sports",
    "wof:placetype":"venue"
},
  "geometry": {"coordinates":[6.0267300606,50.4254837036],"type":"Point"}
}