{
  "type": "Feature",
  "properties": {
    "addr:full":"Voogdijstraat 2 Mol Antwerpen 2400",
    "addr:housenumber":"2",
    "addr:postcode":"2400",
    "addr:street":"Voogdijstraat",
    "iso:country":"BE",
    "sg:address":"Voogdijstraat 2",
    "sg:city":"Mol",
    "sg:classifiers":[
        {
            "category":"Shopping",
            "subcategory":"Crafts & Fabrics",
            "type":"Retail Goods"
        }
    ],
    "sg:phone":"+32 14 31 17 77",
    "sg:postcode":"2400",
    "sg:province":"Antwerpen",
    "sg:tags":[
        "silk",
        "-"
    ],
    "wof:name":"Rotexco",
    "wof:placetype":"venue"
},
  "geometry": {"coordinates":[5.1198101044,51.1874008179],"type":"Point"}
}