{
  "type": "Feature",
  "properties": {
    "addr:full":"Route Du Condroz 99 Li\u00e8ge 1 (angleur) Li\u00e8ge 4031",
    "addr:housenumber":"99;1",
    "addr:postcode":"4031",
    "addr:street":"Route Du Condroz",
    "iso:country":"BE",
    "sg:address":"Route Du Condroz 99",
    "sg:city":"Li\u00e8ge 1 (angleur)",
    "sg:classifiers":[
        {
            "category":"Arena",
            "subcategory":"Sports Club",
            "type":"Entertainment"
        }
    ],
    "sg:phone":"+32 4 365 14 91",
    "sg:postcode":"4031",
    "sg:province":"Li\u00e8ge",
    "wof:name":"Royal Tennis Club Li\u00e8ge",
    "wof:placetype":"venue"
},
  "geometry": {"coordinates":[5.5870051384,50.6055679321],"type":"Point"}
}