{
  "type": "Feature",
  "properties": {
    "addr:full":"Rue La Reine Elisabeth 2 Estaimpuis Hainaut 7730",
    "addr:housenumber":"2",
    "addr:postcode":"7730",
    "addr:street":"Rue La Reine Elisabeth;Hainaut",
    "iso:country":"BE",
    "sg:address":"Rue La Reine Elisabeth 2",
    "sg:city":"Estaimpuis",
    "sg:classifiers":[
        {
            "category":"Cafe",
            "type":"Food & Drink"
        }
    ],
    "sg:phone":"+32 56 48 90 36",
    "sg:postcode":"7730",
    "sg:province":"Hainaut",
    "sg:tags":[
        "caf\u00e9s"
    ],
    "wof:name":"Caf\u00c9 \u00c0 L'etoile",
    "wof:placetype":"venue"
},
  "geometry": {"coordinates":[3.2587649822,50.6851081848],"type":"Point"}
}