{
  "type": "Feature",
  "properties": {
    "iso:country":"BE",
    "sg:address":"Victor Maloustraat 68",
    "sg:city":"Sint-pieters-leeuw",
    "sg:orig_category":"Eleveurs de bovins",
    "sg:phone":"+32 2 356 55 28",
    "sg:postcode":"1600",
    "sg:province":"Vlaams-Brabant",
    "wof:name":"Georges Van Laethem",
    "wof:placetype":"venue"
},
  "geometry": {"coordinates":[4.2258992195,50.7693481445],"type":"Point"}
}