{
  "type": "Feature",
  "properties": {
    "iso:country":"BE",
    "sg:address":"Rue Libon 34",
    "sg:city":"Verviers",
    "sg:classifiers":[
        {
            "category":"Professional",
            "subcategory":"Accounting & Tax Preparation",
            "type":"Services"
        }
    ],
    "sg:phone":"+32 87 22 19 31",
    "sg:postcode":"4800",
    "sg:province":"Li\u00e8ge",
    "sg:tags":[
        "accountant"
    ],
    "wof:name":"Jacques Rainotte",
    "wof:placetype":"venue"
},
  "geometry": {"coordinates":[5.8630371094,50.5848388672],"type":"Point"}
}