{
  "type": "Feature",
  "properties": {
    "iso:country":"BE",
    "sg:address":"Rue Terre-neuve 26",
    "sg:city":"Brussel/bruxelles",
    "sg:orig_category":"M\u00e9decins and sp\u00e9cialistes",
    "sg:phone":"+32 2 514 13 83",
    "sg:postcode":"1000",
    "sg:province":"Bruxelles-Capitale",
    "wof:name":"Pilade Ferrari",
    "wof:placetype":"venue"
},
  "geometry": {"coordinates":[4.3476791382,50.8425712585],"type":"Point"}
}