{
  "type": "Feature",
  "properties": {
    "iso:country":"BE",
    "sg:address":"Koning Albertlaan 52",
    "sg:city":"Zelzate",
    "sg:orig_category":"Traitements param\u00e9dicaux",
    "sg:phone":"+32 9 344 94 93",
    "sg:postcode":"9060",
    "sg:province":"Oost-Vlaanderen",
    "wof:name":"C. Van Autr\u00c8ve",
    "wof:placetype":"venue"
},
  "geometry": {"coordinates":[3.7969310284,51.2025375366],"type":"Point"}
}