{
  "type": "Feature",
  "properties": {
    "addr:full":"Avenue Du Printemps 25 Namur (belgrade) Namur 5001",
    "addr:housenumber":"25",
    "addr:postcode":"5001",
    "addr:street":"Avenue Du Printemps",
    "iso:country":"BE",
    "sg:address":"Avenue Du Printemps 25",
    "sg:city":"Namur (belgrade)",
    "sg:classifiers":[
        {
            "category":"Travel",
            "subcategory":"Travel Agent",
            "type":"Entertainment"
        }
    ],
    "sg:phone":"+32 81 56 78 78",
    "sg:postcode":"5001",
    "sg:province":"Namur",
    "sg:tags":[
        "agency"
    ],
    "wof:name":"Azimut Sud",
    "wof:placetype":"venue"
},
  "geometry": {"coordinates":[4.8257050514,50.4722557068],"type":"Point"}
}