{
  "type": "Feature",
  "properties": {
    "addr:full":"Haven 1207 Beveren Oost-Vlaanderen 9130",
    "addr:postcode":"1207;9130",
    "addr:street":"Haven",
    "iso:country":"BE",
    "sg:address":"Haven 1207",
    "sg:city":"Beveren",
    "sg:orig_category":"Agences maritimes",
    "sg:phone":"+32 3 570 92 92",
    "sg:postcode":"9130",
    "sg:province":"Oost-Vlaanderen",
    "wof:name":"Transfennica Belgium",
    "wof:placetype":"venue"
},
  "geometry": {"coordinates":[4.175344944,51.2897109985],"type":"Point"}
}