{
  "type": "Feature",
  "properties": {
    "addr:full":"Rue Du Commerce 19 Malmedy/malmedy Li\u00e8ge 4960",
    "addr:housenumber":"19",
    "addr:postcode":"4960",
    "addr:street":"Rue Du Commerce",
    "iso:country":"BE",
    "sg:address":"Rue Du Commerce 19",
    "sg:city":"Malmedy/malmedy",
    "sg:orig_category":"Bagage and lederwaren Verlichting and huishoudartikelen",
    "sg:phone":"+32 80 33 03 39",
    "sg:postcode":"4960",
    "sg:province":"Li\u00e8ge",
    "wof:name":"Siquet A",
    "wof:placetype":"venue"
},
  "geometry": {"coordinates":[6.0551772118,50.37657547],"type":"Point"}
}