{
  "type": "Feature",
  "properties": {
    "iso:country":"BE",
    "sg:address":"Norbert Neeckxlaan 78",
    "sg:city":"Lommel",
    "sg:orig_category":"M\u00e9decins and sp\u00e9cialistes",
    "sg:phone":"+32 11 54 22 15",
    "sg:postcode":"3920",
    "sg:province":"Limburg",
    "wof:name":"Jan Swinnen",
    "wof:placetype":"venue"
},
  "geometry": {"coordinates":[5.3295030594,51.2251625061],"type":"Point"}
}