{
  "type": "Feature",
  "properties": {
    "addr:full":"Route De Huy 77 Lincent Li\u00e8ge 4287",
    "addr:housenumber":"77",
    "addr:postcode":"4287",
    "addr:street":"Route De Huy",
    "iso:country":"BE",
    "sg:address":"Route De Huy 77",
    "sg:city":"Lincent",
    "sg:orig_category":"Studios photographiques",
    "sg:phone":"+32 19 63 23 32",
    "sg:postcode":"4287",
    "sg:province":"Li\u00e8ge",
    "wof:name":"Stephan Vandecan",
    "wof:placetype":"venue"
},
  "geometry": {"coordinates":[5.0357432365,50.7129898071],"type":"Point"}
}