{
  "type": "Feature",
  "properties": {
    "addr:full":"Zi Baileux Hainaut 6464",
    "addr:postcode":"6464",
    "iso:country":"BE",
    "sg:address":"Zi",
    "sg:city":"Baileux",
    "sg:classifiers":[
        {
            "category":"Home & Garden",
            "subcategory":"Furniture",
            "type":"Retail Goods"
        }
    ],
    "sg:phone":"+32 60 21 37 38",
    "sg:postcode":"6464",
    "sg:province":"Hainaut",
    "sg:tags":[
        "wood"
    ],
    "wof:name":"Claberbois Sa",
    "wof:placetype":"venue"
},
  "geometry": {"coordinates":[4.3209447861,50.0234336853],"type":"Point"}
}