{
  "type": "Feature",
  "properties": {
    "addr:full":"Asterdreef 44 Gent (sint-amandsberg) Oost-Vlaanderen 9040",
    "addr:housenumber":"44",
    "addr:postcode":"9040",
    "addr:street":"Asterdreef",
    "iso:country":"BE",
    "sg:address":"Asterdreef 44",
    "sg:city":"Gent (sint-amandsberg)",
    "sg:classifiers":[
        {
            "category":"Professional",
            "subcategory":"Accounting & Tax Preparation",
            "type":"Services"
        }
    ],
    "sg:phone":"+32 9 228 86 66",
    "sg:postcode":"9040",
    "sg:province":"Oost-Vlaanderen",
    "sg:tags":[
        "accountant"
    ],
    "wof:name":"Debuysere R",
    "wof:placetype":"venue"
},
  "geometry": {"coordinates":[3.7585990429,51.0502815247],"type":"Point"}
}