{
  "type": "Feature",
  "properties": {
    "iso:country":"BE",
    "sg:address":"Wijnbergstraat 23",
    "sg:city":"Oud-heverlee",
    "sg:orig_category":"Boekhouders",
    "sg:phone":"+32 16 40 11 18",
    "sg:postcode":"3052",
    "sg:province":"Vlaams-Brabant",
    "wof:name":"Robrechts Peter",
    "wof:placetype":"venue"
},
  "geometry": {"coordinates":[4.7094359398,50.8275642395],"type":"Point"}
}