{
  "type": "Feature",
  "properties": {
    "iso:country":"BE",
    "sg:address":"Slagmanstraat 37",
    "sg:city":"Lochristi",
    "sg:orig_category":"Landmeters",
    "sg:phone":"+32 9 355 63 93",
    "sg:postcode":"9080",
    "sg:province":"Oost-Vlaanderen",
    "wof:name":"Kristof Van Laere",
    "wof:placetype":"venue"
},
  "geometry": {"coordinates":[3.86617589,51.1131210327],"type":"Point"}
}