{
  "type": "Feature",
  "properties": {
    "addr:full":"Echelsven 12 Meerhout Antwerpen 2450",
    "addr:housenumber":"12",
    "addr:postcode":"2450",
    "addr:street":"Echelsven",
    "iso:country":"BE",
    "sg:address":"Echelsven 12",
    "sg:city":"Meerhout",
    "sg:classifiers":[
        {
            "category":"Airport",
            "subcategory":"International",
            "type":"Transportation"
        }
    ],
    "sg:phone":"+32 14 30 17 11",
    "sg:postcode":"2450",
    "sg:province":"Antwerpen",
    "sg:tags":[
        "-",
        "transport"
    ],
    "wof:name":"Cuyvers D",
    "wof:placetype":"venue"
},
  "geometry": {"coordinates":[5.0694332123,51.1319961548],"type":"Point"}
}