{
  "type": "Feature",
  "properties": {
    "iso:country":"BE",
    "sg:address":"Lange Meers 10a",
    "sg:city":"Wervik",
    "sg:orig_category":"Jardinage",
    "sg:phone":"+32 56 51 31 07",
    "sg:postcode":"8940",
    "sg:province":"West-Vlaanderen",
    "wof:name":"Serlet-ghesquiere",
    "wof:placetype":"venue"
},
  "geometry": {"coordinates":[3.082752943,50.804851532],"type":"Point"}
}