{
  "type": "Feature",
  "properties": {
    "addr:full":"Hof Ter Elstlaan 2-a Temse (elversele) Oost-Vlaanderen 9140",
    "addr:housenumber":"2-a",
    "addr:postcode":"9140",
    "addr:street":"Hof Ter Elstlaan",
    "iso:country":"BE",
    "sg:address":"Hof Ter Elstlaan 2-a",
    "sg:city":"Temse (elversele)",
    "sg:classifiers":[
        {
            "category":"Insurance",
            "subcategory":"Insurance Agent",
            "type":"Services"
        }
    ],
    "sg:phone":"+32 52 46 07 22",
    "sg:postcode":"9140",
    "sg:province":"Oost-Vlaanderen",
    "sg:tags":[
        "-",
        "representative"
    ],
    "wof:name":"Elewaut D",
    "wof:placetype":"venue"
},
  "geometry": {"coordinates":[4.1377148628,51.1140327454],"type":"Point"}
}