{
  "type": "Feature",
  "properties": {
    "addr:full":"Boulevard Leopold-iii 29 Schaarbeek/schaerbeek Bruxelles-Capitale 1030",
    "addr:housenumber":"29",
    "addr:postcode":"1030",
    "addr:street":"Boulevard Leopold-Iii",
    "iso:country":"BE",
    "sg:address":"Boulevard Leopold-iii 29",
    "sg:city":"Schaarbeek/schaerbeek",
    "sg:orig_category":"Enseignement maternel and primaire",
    "sg:phone":"+32 2 705 15 49",
    "sg:postcode":"1030",
    "sg:province":"Bruxelles-Capitale",
    "wof:name":"Ecole Fond. Communale",
    "wof:placetype":"venue"
},
  "geometry": {"coordinates":[4.4001731873,50.8597640991],"type":"Point"}
}