{
  "type": "Feature",
  "properties": {
    "addr:full":"Pastoor Blanckestraat 7 Heuvelland West-Vlaanderen 8953",
    "addr:housenumber":"7",
    "addr:postcode":"8953",
    "addr:street":"Pastoor Blanckestraat",
    "iso:country":"BE",
    "sg:address":"Pastoor Blanckestraat 7",
    "sg:city":"Heuvelland",
    "sg:orig_category":"Eleveurs de bovins. Eleveurs and marchands de porcs",
    "sg:phone":"+32 57 44 50 46",
    "sg:postcode":"8953",
    "sg:province":"West-Vlaanderen",
    "wof:name":"Dirk Schoutteten",
    "wof:placetype":"venue"
},
  "geometry": {"coordinates":[2.9269850254,50.7881126404],"type":"Point"}
}