{
  "type": "Feature",
  "properties": {
    "addr:full":"Route De Mons 25 Binche Hainaut 7130",
    "addr:housenumber":"25",
    "addr:postcode":"7130",
    "addr:street":"Route De Mons",
    "iso:country":"BE",
    "sg:address":"Route De Mons 25",
    "sg:city":"Binche",
    "sg:classifiers":[
        {
            "category":"Wholesale",
            "subcategory":"Sporting Goods",
            "type":"Manufacturing & Wholesale Goods"
        }
    ],
    "sg:phone":"+32 64 33 95 18",
    "sg:postcode":"7130",
    "sg:province":"Hainaut",
    "sg:tags":[
        "sport-",
        "kampeermateriaal"
    ],
    "wof:name":"Maison Sport Time",
    "wof:placetype":"venue"
},
  "geometry": {"coordinates":[4.1651821136,50.4129142761],"type":"Point"}
}