{
  "type": "Feature",
  "properties": {
    "addr:full":"Kesselsstraat 68 Schaarbeek/schaerbeek Bruxelles-Capitale 1030",
    "addr:housenumber":"68",
    "addr:postcode":"1030",
    "addr:street":"Kesselsstraat",
    "iso:country":"BE",
    "sg:address":"Kesselsstraat 68",
    "sg:city":"Schaarbeek/schaerbeek",
    "sg:orig_category":"Plaatsen van vloer- and muurbekleding Schilders",
    "sg:phone":"+32 2 241 44 95",
    "sg:postcode":"1030",
    "sg:province":"Bruxelles-Capitale",
    "wof:name":"Pierre Jacob",
    "wof:placetype":"venue"
},
  "geometry": {"coordinates":[4.3774552345,50.8624610901],"type":"Point"}
}