{
  "type": "Feature",
  "properties": {
    "addr:full":"Gemeenteplein 33 Hoeilaart Vlaams-Brabant 1560",
    "addr:housenumber":"33",
    "addr:postcode":"1560",
    "addr:street":"Gemeenteplein",
    "iso:country":"BE",
    "sg:address":"Gemeenteplein 33",
    "sg:city":"Hoeilaart",
    "sg:orig_category":"Herstelling horloges and juwelen Juwelen and horloges",
    "sg:phone":"+32 2 657 63 90",
    "sg:postcode":"1560",
    "sg:province":"Vlaams-Brabant",
    "wof:name":"Dekock",
    "wof:placetype":"venue"
},
  "geometry": {"coordinates":[4.4727401733,50.7684936523],"type":"Point"}
}