{
  "type": "Feature",
  "properties": {
    "addr:full":"Stationsstraat 71 Waarschoot Oost-Vlaanderen 9950",
    "addr:housenumber":"71",
    "addr:postcode":"9950",
    "addr:street":"Stationsstraat",
    "iso:country":"BE",
    "sg:address":"Stationsstraat 71",
    "sg:city":"Waarschoot",
    "sg:classifiers":[
        {
            "category":"Wholesale",
            "subcategory":"Fruits & Vegetables",
            "type":"Manufacturing & Wholesale Goods"
        }
    ],
    "sg:phone":"+32 9 378 41 68",
    "sg:postcode":"9950",
    "sg:province":"Oost-Vlaanderen",
    "sg:tags":[
        "whol",
        "-"
    ],
    "wof:name":"Katy's Groenten En Fruit",
    "wof:placetype":"venue"
},
  "geometry": {"coordinates":[3.6111400127,51.1523475647],"type":"Point"}
}