{
  "type": "Feature",
  "properties": {
    "iso:country":"BE",
    "sg:address":"Oude Baan 121",
    "sg:city":"Bonheiden",
    "sg:classifiers":[
        {
            "category":"Professional",
            "type":"Services"
        }
    ],
    "sg:phone":"+32 15 55 60 81",
    "sg:postcode":"2820",
    "sg:province":"Antwerpen",
    "sg:tags":[
        "packing",
        "-"
    ],
    "wof:name":"International Food Container Organisation",
    "wof:placetype":"venue"
},
  "geometry": {"coordinates":[4.5336608887,51.0340805054],"type":"Point"}
}