{
  "type": "Feature",
  "properties": {
    "addr:full":"Bois De Goesnes 3 Marchin Li\u00e8ge 4570",
    "addr:housenumber":"3",
    "addr:postcode":"4570",
    "addr:street":"Bois De Goesnes",
    "iso:country":"BE",
    "sg:address":"Bois De Goesnes 3",
    "sg:city":"Marchin",
    "sg:classifiers":[
        {
            "category":"Building & Trades",
            "subcategory":"Construction",
            "type":"Services"
        }
    ],
    "sg:phone":"+32 85 23 03 50",
    "sg:postcode":"4570",
    "sg:province":"Li\u00e8ge",
    "sg:tags":[
        "stair"
    ],
    "wof:name":"Scierie Dupont & Fils Sa",
    "wof:placetype":"venue"
},
  "geometry": {"coordinates":[5.2091879845,50.4750823975],"type":"Point"}
}