{
  "type": "Feature",
  "properties": {
    "addr:full":"Sint-salvatorstraat 155 Gent Oost-Vlaanderen 9000",
    "addr:housenumber":"155",
    "addr:postcode":"9000",
    "addr:street":"Oost-Vlaanderen",
    "iso:country":"BE",
    "sg:address":"Sint-salvatorstraat 155",
    "sg:city":"Gent",
    "sg:orig_category":"Slagers",
    "sg:phone":"+32 9 225 65 86",
    "sg:postcode":"9000",
    "sg:province":"Oost-Vlaanderen",
    "wof:name":"Beenhouwerij Adrien",
    "wof:placetype":"venue"
},
  "geometry": {"coordinates":[3.7291040421,51.0672187805],"type":"Point"}
}