{
  "type": "Feature",
  "properties": {
    "addr:full":"Kwakkelstraat 30 Stekene Oost-Vlaanderen 9190",
    "addr:housenumber":"30",
    "addr:postcode":"9190",
    "addr:street":"Kwakkelstraat",
    "iso:country":"BE",
    "sg:address":"Kwakkelstraat 30",
    "sg:city":"Stekene",
    "sg:classifiers":[
        {
            "category":"Professional",
            "subcategory":"Engineering",
            "type":"Services"
        }
    ],
    "sg:phone":"+32 3 779 88 54",
    "sg:postcode":"9190",
    "sg:province":"Oost-Vlaanderen",
    "sg:tags":[
        "-"
    ],
    "wof:name":"S.d.r.",
    "wof:placetype":"venue"
},
  "geometry": {"coordinates":[4.0558757782,51.1959915161],"type":"Point"}
}