{
  "type": "Feature",
  "properties": {
    "addr:full":"Rue De Steppes 7 Li\u00e8ge 1 Li\u00e8ge 4000",
    "addr:housenumber":"7;1",
    "addr:postcode":"4000",
    "addr:street":"Rue De Steppes",
    "iso:country":"BE",
    "sg:address":"Rue De Steppes 7",
    "sg:city":"Li\u00e8ge 1",
    "sg:orig_category":"Solar protection - Inside",
    "sg:postcode":"4000",
    "sg:province":"Li\u00e8ge",
    "wof:name":"Stores Cleaner",
    "wof:placetype":"venue"
},
  "geometry": {"coordinates":[5.5989999771,50.6549453735],"type":"Point"}
}