{
  "type": "Feature",
  "properties": {
    "addr:full":"Rue Baty-de-l'espagnole 10 Fosses-la-ville Namur 5070",
    "addr:housenumber":"10",
    "addr:postcode":"5070",
    "addr:street":"Rue Baty-De-L'Espagnole",
    "iso:country":"BE",
    "sg:address":"Rue Baty-de-l'espagnole 10",
    "sg:city":"Fosses-la-ville",
    "sg:orig_category":"Verhuur voertuigen behalve auto's Voertuigen",
    "sg:phone":"+32 71 71 22 41",
    "sg:postcode":"5070",
    "sg:province":"Namur",
    "wof:name":"Karting Evrard",
    "wof:placetype":"venue"
},
  "geometry": {"coordinates":[4.6991100311,50.3773803711],"type":"Point"}
}