{
  "type": "Feature",
  "properties": {
    "iso:country":"BE",
    "sg:address":"Oekensestraat 146",
    "sg:city":"Roeselare (rumbeke)",
    "sg:classifiers":[
        {
            "category":"Autos & Motor Vehicles",
            "subcategory":"Motorcycle Sales",
            "type":"Retail Goods"
        }
    ],
    "sg:phone":"+32 51 33 30 50",
    "sg:postcode":"8800",
    "sg:province":"West-Vlaanderen",
    "sg:tags":[
        "automobile",
        "brake",
        "-",
        "truck"
    ],
    "wof:name":"I.c.t.",
    "wof:placetype":"venue"
},
  "geometry": {"coordinates":[3.1576108932,50.9232368469],"type":"Point"}
}