{
  "type": "Feature",
  "properties": {
    "addr:full":"Koningin Elisabethlei 58 Turnhout Antwerpen 2300",
    "addr:housenumber":"58",
    "addr:postcode":"2300",
    "addr:street":"Koningin Elisabethlei",
    "iso:country":"BE",
    "sg:address":"Koningin Elisabethlei 58",
    "sg:city":"Turnhout",
    "sg:orig_category":"Metaalbehandeling and -bekleding",
    "sg:phone":"+32 14 41 26 17",
    "sg:postcode":"2300",
    "sg:province":"Antwerpen",
    "wof:name":"Dockx Hans",
    "wof:placetype":"venue"
},
  "geometry": {"coordinates":[4.9482221603,51.3316650391],"type":"Point"}
}