{
  "type": "Feature",
  "properties": {
    "addr:full":"Boshuisweg 1 Zoersel Antwerpen 2980",
    "addr:housenumber":"1",
    "addr:postcode":"2980",
    "addr:street":"Boshuisweg",
    "iso:country":"BE",
    "sg:address":"Boshuisweg 1",
    "sg:city":"Zoersel",
    "sg:orig_category":"RESTAURANTS: CAF\u00c9S",
    "sg:phone":"+32 3 324 11 37",
    "sg:postcode":"2980",
    "sg:province":"Antwerpen",
    "wof:name":"Taverne 't Boshuisje",
    "wof:placetype":"venue"
},
  "geometry": {"coordinates":[4.6764731407,51.2433776855],"type":"Point"}
}