{
  "type": "Feature",
  "properties": {
    "addr:full":"Markt 14 Zele Oost-Vlaanderen 9240",
    "addr:housenumber":"14",
    "addr:postcode":"9240",
    "addr:street":"Markt",
    "iso:country":"BE",
    "sg:address":"Markt 14",
    "sg:city":"Zele",
    "sg:orig_category":"Banken and kredietinstellingen",
    "sg:phone":"+32 52 44 40 39",
    "sg:postcode":"9240",
    "sg:province":"Oost-Vlaanderen",
    "wof:name":"Fortis",
    "wof:placetype":"venue"
},
  "geometry": {"coordinates":[4.0394248962,51.0680427551],"type":"Point"}
}