{
  "type": "Feature",
  "properties": {
    "iso:country":"BE",
    "sg:address":"Meerstraat 1",
    "sg:city":"Hamme",
    "sg:orig_category":"Rundveehouders",
    "sg:phone":"+32 52 47 04 90",
    "sg:postcode":"9220",
    "sg:province":"Oost-Vlaanderen",
    "wof:name":"Bart Bruggeman",
    "wof:placetype":"venue"
},
  "geometry": {"coordinates":[4.1184501648,51.0820198059],"type":"Point"}
}