{
  "type": "Feature",
  "properties": {
    "addr:full":"Bochtenstraat 24 Destelbergen Oost-Vlaanderen 9070",
    "addr:housenumber":"24",
    "addr:postcode":"9070",
    "addr:street":"Bochtenstraat",
    "iso:country":"BE",
    "sg:address":"Bochtenstraat 24",
    "sg:city":"Destelbergen",
    "sg:orig_category":"Artiesten and kunstenaars",
    "sg:phone":"+32 9 355 76 05",
    "sg:postcode":"9070",
    "sg:province":"Oost-Vlaanderen",
    "wof:name":"Helga Demeyere",
    "wof:placetype":"venue"
},
  "geometry": {"coordinates":[3.8323960304,51.0670089722],"type":"Point"}
}