{
  "type": "Feature",
  "properties": {
    "iso:country":"BE",
    "sg:address":"Rue Thier Du Moulin 37",
    "sg:city":"Villers-le-bouillet",
    "sg:orig_category":"Schoonheidssalons",
    "sg:phone":"+32 85 23 47 02",
    "sg:postcode":"4530",
    "sg:province":"Li\u00e8ge",
    "wof:name":"Claudine Van De Broeck",
    "wof:placetype":"venue"
},
  "geometry": {"coordinates":[5.2811088562,50.563205719],"type":"Point"}
}