{
  "type": "Feature",
  "properties": {
    "addr:full":"Brasschaatsebaan 55 Schilde Antwerpen 2970",
    "addr:housenumber":"55",
    "addr:postcode":"2970",
    "addr:street":"Brasschaatsebaan",
    "iso:country":"BE",
    "sg:address":"Brasschaatsebaan 55",
    "sg:city":"Schilde",
    "sg:classifiers":[
        {
            "category":"Building & Trades",
            "subcategory":"Landscaping Services",
            "type":"Services"
        }
    ],
    "sg:phone":"+32 3 383 21 17",
    "sg:postcode":"2970",
    "sg:province":"Antwerpen",
    "sg:tags":[
        "access",
        "pond",
        "laying-out",
        "-"
    ],
    "wof:name":"Beernaert P",
    "wof:placetype":"venue"
},
  "geometry": {"coordinates":[4.5756998062,51.2420578003],"type":"Point"}
}