{
  "type": "Feature",
  "properties": {
    "iso:country":"BE",
    "sg:address":"Van Hammelaan 28",
    "sg:city":"Zedelgem",
    "sg:orig_category":"Instituts de beaut\u00e9",
    "sg:phone":"+32 50 82 57 50",
    "sg:postcode":"8210",
    "sg:province":"West-Vlaanderen",
    "wof:name":"Pedicure Kint",
    "wof:placetype":"venue"
},
  "geometry": {"coordinates":[3.1458399296,51.1376457214],"type":"Point"}
}