{
  "type": "Feature",
  "properties": {
    "addr:full":"Andr\u00e9 Dumontlaan 146 Genk (waterschei) Limburg 3600",
    "addr:housenumber":"146",
    "addr:postcode":"3600",
    "addr:street":"Dumontlaan",
    "iso:country":"BE",
    "sg:address":"Andr\u00e9 Dumontlaan 146",
    "sg:city":"Genk (waterschei)",
    "sg:classifiers":[
        {
            "category":"Retail",
            "subcategory":"Auto Repair",
            "type":"Services"
        }
    ],
    "sg:phone":"+32 89 38 20 88",
    "sg:postcode":"3600",
    "sg:province":"Limburg",
    "sg:tags":[
        "garage"
    ],
    "wof:name":"Willems Nv",
    "wof:placetype":"venue"
},
  "geometry": {"coordinates":[5.5357809067,50.9919242859],"type":"Point"}
}