{
  "type": "Feature",
  "properties": {
    "addr:full":"Mechelseweg 285 Kapelle-op-den-bos Vlaams-Brabant 1880",
    "addr:housenumber":"285",
    "addr:postcode":"1880",
    "addr:street":"Mechelseweg",
    "iso:country":"BE",
    "sg:address":"Mechelseweg 285",
    "sg:city":"Kapelle-op-den-bos",
    "sg:classifiers":[
        {
            "category":"Retail",
            "subcategory":"Storage",
            "type":"Services"
        }
    ],
    "sg:phone":"+32 15 71 10 09",
    "sg:postcode":"1880",
    "sg:province":"Vlaams-Brabant",
    "sg:tags":[
        "access",
        "-",
        "pigeon",
        "fancier"
    ],
    "wof:name":"Noord-brabant Duivenmij.",
    "wof:placetype":"venue"
},
  "geometry": {"coordinates":[4.3638930321,51.0120506287],"type":"Point"}
}