{
  "type": "Feature",
  "properties": {
    "iso:country":"BE",
    "sg:address":"Chauss\u00e9e De Braine Le Comte 82b",
    "sg:city":"Nivelles",
    "sg:classifiers":[
        {
            "category":"Shopping",
            "subcategory":"Computers & Home Electronics",
            "type":"Retail Goods"
        }
    ],
    "sg:phone":"+32 67 21 02 51",
    "sg:postcode":"1400",
    "sg:province":"Brabant Wallon",
    "sg:tags":[
        "sound",
        "equipment",
        "-",
        "system"
    ],
    "wof:name":"Sonority",
    "wof:placetype":"venue"
},
  "geometry": {"coordinates":[4.303358078,50.5992012024],"type":"Point"}
}