{
  "type": "Feature",
  "properties": {
    "addr:full":"Chauss\u00c9e De Tr\u00c9lon 18 Chimay Hainaut 6460",
    "addr:housenumber":"18",
    "addr:postcode":"6460",
    "addr:street":"Chausse\u0301E De Tre\u0301Lon",
    "iso:country":"BE",
    "sg:address":"Chauss\u00c9e De Tr\u00c9lon 18",
    "sg:city":"Chimay",
    "sg:orig_category":"Herstellingen and onderhoud van auto's",
    "sg:phone":"+32 60 21 12 18",
    "sg:postcode":"6460",
    "sg:province":"Hainaut",
    "wof:name":"Garage Durlet",
    "wof:placetype":"venue"
},
  "geometry": {"coordinates":[4.300620079,50.0519943237],"type":"Point"}
}