{
  "type": "Feature",
  "properties": {
    "addr:full":"Chauss\u00e9e De Saint-job 364 Bruxelles (uccle) Bruxelles-Capitale 1180",
    "addr:housenumber":"364",
    "addr:postcode":"1180",
    "addr:street":"Chausse\u0301E De Saint-Job",
    "iso:country":"BE",
    "sg:address":"Chauss\u00e9e De Saint-job 364",
    "sg:city":"Bruxelles (uccle)",
    "sg:classifiers":[
        {
            "category":"Professional",
            "subcategory":"Management & Consulting",
            "type":"Services"
        }
    ],
    "sg:phone":"+32 2 374 01 26",
    "sg:postcode":"1180",
    "sg:province":"Bruxelles-Capitale",
    "sg:tags":[
        "-",
        "processing",
        "data",
        "consultant"
    ],
    "wof:name":"Ad Hoc Consultancy And Solutions Provider",
    "wof:placetype":"venue"
},
  "geometry": {"coordinates":[4.3506069183,50.7920837402],"type":"Point"}
}