{
  "type": "Feature",
  "properties": {
    "iso:country":"BE",
    "sg:address":"Torenstraat 2",
    "sg:city":"Neerpelt",
    "sg:classifiers":[
        {
            "category":"Bars & Pubs",
            "type":"Food & Drink"
        }
    ],
    "sg:phone":"+32 11 66 42 96",
    "sg:postcode":"3910",
    "sg:province":"Limburg",
    "wof:name":"Kesters J",
    "wof:placetype":"venue"
},
  "geometry": {"coordinates":[5.4656920433,51.1984939575],"type":"Point"}
}