{
  "type": "Feature",
  "properties": {
    "addr:full":"Rue Vanderkindere 28 Bruxelles (uccle) Bruxelles-Capitale 1180",
    "addr:housenumber":"28",
    "addr:postcode":"1180",
    "addr:street":"Rue Vanderkindere",
    "iso:country":"BE",
    "sg:address":"Rue Vanderkindere 28",
    "sg:city":"Bruxelles (uccle)",
    "sg:classifiers":[
        {
            "category":"Personal",
            "subcategory":"Beauty Salon",
            "type":"Services"
        }
    ],
    "sg:phone":"+32 2 344 98 70",
    "sg:postcode":"1180",
    "sg:province":"Bruxelles-Capitale",
    "sg:tags":[
        "lady",
        "-",
        "hairdressing"
    ],
    "wof:name":"Bouclette (la)",
    "wof:placetype":"venue"
},
  "geometry": {"coordinates":[4.340118885,50.8137168884],"type":"Point"}
}