{
  "type": "Feature",
  "properties": {
    "iso:country":"BE",
    "sg:address":"Bloemendaalstraat 105",
    "sg:city":"Halen",
    "sg:classifiers":[
        {
            "category":"Arena",
            "subcategory":"Sports Club",
            "type":"Entertainment"
        }
    ],
    "sg:phone":"+32 13 44 26 28",
    "sg:postcode":"3545",
    "sg:province":"Limburg",
    "sg:tags":[
        "de"
    ],
    "wof:name":"Wielervrienden Ertsenrijk",
    "wof:placetype":"venue"
},
  "geometry": {"coordinates":[5.1120381355,50.9371452332],"type":"Point"}
}