{
  "type": "Feature",
  "properties": {
    "addr:full":"Chauss\u00c9e De Wavre 1505 Oudergem/auderghem Bruxelles-Capitale 1160",
    "addr:postcode":"1505;1160",
    "addr:street":"Chausse\u0301E De Wavre",
    "iso:country":"BE",
    "sg:address":"Chauss\u00c9e De Wavre 1505",
    "sg:city":"Oudergem/auderghem",
    "sg:orig_category":"D\u00e9corateurs d'int\u00e9rieur",
    "sg:phone":"+32 2 663 45 81",
    "sg:postcode":"1160",
    "sg:province":"Bruxelles-Capitale",
    "wof:name":"Gamma",
    "wof:placetype":"venue"
},
  "geometry": {"coordinates":[4.4168372154,50.8184051514],"type":"Point"}
}