{
  "type": "Feature",
  "properties": {
    "iso:country":"BE",
    "sg:address":"Rue B\u00e9atam 5",
    "sg:city":"Dour (elouges)",
    "sg:classifiers":[
        {
            "category":"Health Services",
            "subcategory":"Nursing And Care Facility",
            "type":"Services"
        }
    ],
    "sg:phone":"+32 65 65 96 14",
    "sg:postcode":"7370",
    "sg:province":"Hainaut",
    "sg:tags":[
        "home",
        "rest"
    ],
    "wof:name":"Beatam (le) Maison De Repos",
    "wof:placetype":"venue"
},
  "geometry": {"coordinates":[3.7591619492,50.3967781067],"type":"Point"}
}