{
  "type": "Feature",
  "properties": {
    "addr:full":"Houtenweg 9 Maaseik (opoeteren) Limburg 3680",
    "addr:housenumber":"9",
    "addr:postcode":"3680",
    "addr:street":"Houtenweg",
    "iso:country":"BE",
    "sg:address":"Houtenweg 9",
    "sg:city":"Maaseik (opoeteren)",
    "sg:classifiers":[
        {
            "category":"Home & Garden",
            "subcategory":"Carpets & Floor Coverings",
            "type":"Retail Goods"
        }
    ],
    "sg:phone":"+32 89 86 67 21",
    "sg:postcode":"3680",
    "sg:province":"Limburg",
    "sg:tags":[
        "layer",
        "mosaicists"
    ],
    "wof:name":"Daniels R",
    "wof:placetype":"venue"
},
  "geometry": {"coordinates":[5.791285038,51.0954208374],"type":"Point"}
}