{
  "type": "Feature",
  "properties": {
    "addr:full":"Expressweg Rw377 4 Jabbeke (stalhille) West-Vlaanderen 8490",
    "addr:housenumber":"4",
    "addr:postcode":"8490",
    "iso:country":"BE",
    "sg:address":"Expressweg Rw377 4",
    "sg:city":"Jabbeke (stalhille)",
    "sg:classifiers":[
        {
            "category":"Retail",
            "subcategory":"Veterinary Services",
            "type":"Services"
        }
    ],
    "sg:phone":"+32 50 81 32 23",
    "sg:postcode":"8490",
    "sg:province":"West-Vlaanderen",
    "sg:tags":[
        "veterinarian"
    ],
    "wof:name":"Vandeputte S",
    "wof:placetype":"venue"
},
  "geometry": {"coordinates":[3.092564106,51.1942596436],"type":"Point"}
}