{
  "type": "Feature",
  "properties": {
    "addr:full":"Cocquytstraat 1 Eeklo Oost-Vlaanderen 9900",
    "addr:housenumber":"1",
    "addr:postcode":"9900",
    "addr:street":"Cocquytstraat",
    "iso:country":"BE",
    "sg:address":"Cocquytstraat 1",
    "sg:city":"Eeklo",
    "sg:orig_category":"Fantasieartikelen Geschenken and souvenirs Verlichting and huishoudartikelen",
    "sg:phone":"+32 9 377 47 91",
    "sg:postcode":"9900",
    "sg:province":"Oost-Vlaanderen",
    "wof:name":"L Everaert",
    "wof:placetype":"venue"
},
  "geometry": {"coordinates":[3.562869072,51.1850280762],"type":"Point"}
}