{
  "type": "Feature",
  "properties": {
    "iso:country":"BE",
    "sg:address":"Stenaartberg 1",
    "sg:city":"Sint-truiden",
    "sg:orig_category":"M\u00e9decins and sp\u00e9cialistes",
    "sg:phone":"+32 11 68 79 92",
    "sg:postcode":"3800",
    "sg:province":"Limburg",
    "wof:name":"L. Renson",
    "wof:placetype":"venue"
},
  "geometry": {"coordinates":[5.1888279915,50.8178710938],"type":"Point"}
}