{
  "type": "Feature",
  "properties": {
    "addr:full":"Rue Nonfays 12 Soumagne (cerexhe-heuseux) Li\u00e8ge 4632",
    "addr:housenumber":"12",
    "addr:postcode":"4632",
    "addr:street":"Rue Nonfays;Cerexhe-Heuseux",
    "iso:country":"BE",
    "sg:address":"Rue Nonfays 12",
    "sg:city":"Soumagne (cerexhe-heuseux)",
    "sg:classifiers":[
        {
            "category":"Retail",
            "subcategory":"Event Space",
            "type":"Services"
        }
    ],
    "sg:phone":"+32 4 377 03 40",
    "sg:postcode":"4632",
    "sg:province":"Li\u00e8ge",
    "sg:tags":[
        "organisation"
    ],
    "wof:name":"C.o.p.e.",
    "wof:placetype":"venue"
},
  "geometry": {"coordinates":[5.7236428261,50.6535339355],"type":"Point"}
}