{
  "type": "Feature",
  "properties": {
    "addr:full":"Rue De L' Industrie 24 Bruxelles (etterbeek) Bruxelles-Capitale 1040",
    "addr:housenumber":"24",
    "addr:postcode":"1040",
    "addr:street":"Rue De L ' Industrie",
    "iso:country":"BE",
    "sg:address":"Rue De L' Industrie 24",
    "sg:city":"Bruxelles (etterbeek)",
    "sg:classifiers":[
        {
            "category":"Professional",
            "subcategory":"Lawyer & Legal Services",
            "type":"Services"
        }
    ],
    "sg:phone":"+32 2 513 89 55",
    "sg:postcode":"1040",
    "sg:province":"Bruxelles-Capitale",
    "sg:tags":[
        "notary"
    ],
    "wof:name":"Dupont James",
    "wof:placetype":"venue"
},
  "geometry": {"coordinates":[4.3697419167,50.842502594],"type":"Point"}
}