{
  "type": "Feature",
  "properties": {
    "addr:full":"Boshovenstraat 8 Meeuwen-gruitrode Limburg 3670",
    "addr:housenumber":"8",
    "addr:postcode":"3670",
    "addr:street":"Boshovenstraat",
    "iso:country":"BE",
    "sg:address":"Boshovenstraat 8",
    "sg:city":"Meeuwen-gruitrode",
    "sg:orig_category":"Rundveehouders",
    "sg:phone":"+32 89 46 19 17",
    "sg:postcode":"3670",
    "sg:province":"Limburg",
    "wof:name":"Leonardus Kerkhofs",
    "wof:placetype":"venue"
},
  "geometry": {"coordinates":[5.5205497742,51.0963516235],"type":"Point"}
}