{
  "type": "Feature",
  "properties": {
    "addr:full":"Zammelseweg 120 Geel Antwerpen 2440",
    "addr:housenumber":"120",
    "addr:postcode":"2440",
    "addr:street":"Zammelseweg",
    "iso:country":"BE",
    "sg:address":"Zammelseweg 120",
    "sg:city":"Geel",
    "sg:classifiers":[
        {
            "category":"Building & Trades",
            "subcategory":"Landscaping Services",
            "type":"Services"
        }
    ],
    "sg:phone":"+32 14 86 84 14",
    "sg:postcode":"2440",
    "sg:province":"Antwerpen",
    "sg:tags":[
        "gardening",
        "garden",
        "maintenance"
    ],
    "wof:name":"Baeck J & Zonen",
    "wof:placetype":"venue"
},
  "geometry": {"coordinates":[4.960059166,51.1015548706],"type":"Point"}
}