{
  "type": "Feature",
  "properties": {
    "addr:full":"Rue De Marcinelle 16 Charleroi (mont-sur-marchienne) Hainaut 6032",
    "addr:housenumber":"16",
    "addr:postcode":"6032",
    "addr:street":"Rue De Marcinelle",
    "iso:country":"BE",
    "sg:address":"Rue De Marcinelle 16",
    "sg:city":"Charleroi (mont-sur-marchienne)",
    "sg:classifiers":[
        {
            "category":"Retail",
            "subcategory":"Auto Repair",
            "type":"Services"
        }
    ],
    "sg:phone":"+32 71 36 19 38",
    "sg:postcode":"6032",
    "sg:province":"Hainaut",
    "sg:tags":[
        "garage"
    ],
    "wof:name":"Leone R Sa",
    "wof:placetype":"venue"
},
  "geometry": {"coordinates":[4.4207530022,50.3778839111],"type":"Point"}
}