{
  "type": "Feature",
  "properties": {
    "iso:country":"BE",
    "sg:address":"G. Gezellelaan 18",
    "sg:city":"Grobbendonk",
    "sg:orig_category":"Pompes and compresseurs Fab",
    "sg:phone":"+32 14 50 14 71",
    "sg:postcode":"2288",
    "sg:province":"Antwerpen",
    "wof:name":"Seepex",
    "wof:placetype":"venue"
},
  "geometry": {"coordinates":[4.7406787872,51.1686782837],"type":"Point"}
}