{
  "type": "Feature",
  "properties": {
    "iso:country":"BE",
    "sg:address":"Tuinlaan 31",
    "sg:city":"Sint-niklaas",
    "sg:orig_category":"Herstellingen and onderhoud van auto's",
    "sg:phone":"+32 3 776 36 24",
    "sg:postcode":"9111",
    "sg:province":"Oost-Vlaanderen",
    "wof:name":"Carrosserie Vandamme",
    "wof:placetype":"venue"
},
  "geometry": {"coordinates":[4.1071338654,51.1511497498],"type":"Point"}
}