{
  "type": "Feature",
  "properties": {
    "addr:full":"Mezenlaan 35 Oudergem/auderghem Bruxelles-Capitale 1160",
    "addr:housenumber":"35",
    "addr:postcode":"1160",
    "addr:street":"Mezenlaan;/",
    "iso:country":"BE",
    "sg:address":"Mezenlaan 35",
    "sg:city":"Oudergem/auderghem",
    "sg:orig_category":"Architecten Landmeters and schatters",
    "sg:phone":"+32 2 673 49 71",
    "sg:postcode":"1160",
    "sg:province":"Bruxelles-Capitale",
    "wof:name":"Jacques Vander Velde",
    "wof:placetype":"venue"
},
  "geometry": {"coordinates":[4.4246110916,50.8227577209],"type":"Point"}
}