{
  "type": "Feature",
  "properties": {
    "addr:full":"Lichtveld 6 Box 2 Tessenderlo Limburg 3980",
    "addr:housenumber":"6;2",
    "addr:postcode":"3980",
    "addr:street":"Lichtveld;Box",
    "iso:country":"BE",
    "sg:address":"Lichtveld 6 Box 2",
    "sg:city":"Tessenderlo",
    "sg:classifiers":[
        {
            "category":"Professional",
            "subcategory":"Management & Consulting",
            "type":"Services"
        }
    ],
    "sg:phone":"+32 13 67 33 64",
    "sg:postcode":"3980",
    "sg:province":"Limburg",
    "sg:tags":[
        "consultant"
    ],
    "wof:name":"Randor'm Bvba",
    "wof:placetype":"venue"
},
  "geometry": {"coordinates":[5.0891499519,51.0645256042],"type":"Point"}
}