{
  "type": "Feature",
  "properties": {
    "iso:country":"BE",
    "sg:address":"Horizonsq 2",
    "sg:city":"Hamme",
    "sg:classifiers":[
        {
            "category":"Manufacturing",
            "subcategory":"Rubber & Plastics",
            "type":"Manufacturing & Wholesale Goods"
        }
    ],
    "sg:phone":"+32 52 49 91 80",
    "sg:postcode":"9220",
    "sg:province":"Oost-Vlaanderen",
    "wof:name":"Storama Nv",
    "wof:placetype":"venue"
},
  "geometry": {"coordinates":[4.1376290321,51.0983505249],"type":"Point"}
}