{
  "type": "Feature",
  "properties": {
    "addr:full":"Justitiestraat 18 Antwerpen Antwerpen 2018",
    "addr:housenumber":"18",
    "addr:postcode":"2018",
    "addr:street":"Justitiestraat",
    "iso:country":"BE",
    "sg:address":"Justitiestraat 18",
    "sg:city":"Antwerpen",
    "sg:classifiers":[
        {
            "category":"Professional",
            "subcategory":"Lawyer & Legal Services",
            "type":"Services"
        }
    ],
    "sg:phone":"+32 3 248 65 93",
    "sg:postcode":"2018",
    "sg:province":"Antwerpen",
    "wof:name":"Dumez P",
    "wof:placetype":"venue"
},
  "geometry": {"coordinates":[4.4061732292,51.2092094421],"type":"Point"}
}