{
  "type": "Feature",
  "properties": {
    "addr:full":"Steenweg 53 Denderleeuw (welle) Oost-Vlaanderen 9473",
    "addr:housenumber":"53",
    "addr:postcode":"9473",
    "addr:street":"Steenweg",
    "iso:country":"BE",
    "sg:address":"Steenweg 53",
    "sg:city":"Denderleeuw (welle)",
    "sg:orig_category":"Newspapers, magazines, periodicals - Distribution",
    "sg:phone":"+32 53 67 05 91",
    "sg:postcode":"9473",
    "sg:province":"Oost-Vlaanderen",
    "wof:name":"Vonck V Bvba",
    "wof:placetype":"venue"
},
  "geometry": {"coordinates":[4.0554571152,50.9044532776],"type":"Point"}
}