{
  "type": "Feature",
  "properties": {
    "addr:full":"Kleinenbergstraat 148 Zaventem (sint-stevens-woluwe) Vlaams-Brabant 1932",
    "addr:housenumber":"148",
    "addr:postcode":"1932",
    "addr:street":"Kleinenbergstraat",
    "iso:country":"BE",
    "sg:address":"Kleinenbergstraat 148",
    "sg:city":"Zaventem (sint-stevens-woluwe)",
    "sg:classifiers":[
        {
            "category":"Banks & Credit Unions",
            "subcategory":"Investment Brokerage",
            "type":"Services"
        }
    ],
    "sg:phone":"+32 2 305 02 81",
    "sg:postcode":"1932",
    "sg:province":"Vlaams-Brabant",
    "sg:tags":[
        "repair",
        "-",
        "installation",
        "sanitary",
        "article"
    ],
    "wof:name":"Charlier A",
    "wof:placetype":"venue"
},
  "geometry": {"coordinates":[4.4448800087,50.858039856],"type":"Point"}
}