{
  "type": "Feature",
  "properties": {
    "addr:full":"Rue L Th\u00c9odore 28 Jette Bruxelles-Capitale 1090",
    "addr:housenumber":"28",
    "addr:postcode":"1090",
    "addr:street":"Rue L The\u0301Odore",
    "iso:country":"BE",
    "sg:address":"Rue L Th\u00c9odore 28",
    "sg:city":"Jette",
    "sg:orig_category":"Non-foodwinkels",
    "sg:phone":"+32 2 425 45 90",
    "sg:postcode":"1090",
    "sg:province":"Bruxelles-Capitale",
    "wof:name":"Ad Hoc",
    "wof:placetype":"venue"
},
  "geometry": {"coordinates":[4.3260297775,50.874042511],"type":"Point"}
}