{
  "type": "Feature",
  "properties": {
    "iso:country":"BE",
    "sg:address":"Lange Kruisstraat 55",
    "sg:city":"Gent",
    "sg:orig_category":"Postkantoren",
    "sg:phone":"+32 9 269 27 50",
    "sg:postcode":"9000",
    "sg:province":"Oost-Vlaanderen",
    "wof:name":"De Post",
    "wof:placetype":"venue"
},
  "geometry": {"coordinates":[3.725908041,51.0519714355],"type":"Point"}
}