{
  "type": "Feature",
  "properties": {
    "addr:full":"Lenertstraat 5 Sint-truiden Limburg 3800",
    "addr:housenumber":"5",
    "addr:postcode":"3800",
    "addr:street":"Lenertstraat",
    "iso:country":"BE",
    "sg:address":"Lenertstraat 5",
    "sg:city":"Sint-truiden",
    "sg:orig_category":"Sportclubs Sportterreinen and installaties behalve sportcentra",
    "sg:phone":"+32 11 68 15 93",
    "sg:postcode":"3800",
    "sg:province":"Limburg",
    "wof:name":"K. Sportklub Tongeren",
    "wof:placetype":"venue"
},
  "geometry": {"coordinates":[5.222465992,50.8019447327],"type":"Point"}
}