{
  "type": "Feature",
  "properties": {
    "iso:country":"BE",
    "sg:address":"Overbroekstraat 73",
    "sg:city":"Wellen",
    "sg:orig_category":"Woningbouw",
    "sg:phone":"+32 12 74 20 13",
    "sg:postcode":"3830",
    "sg:province":"Limburg",
    "wof:name":"Billen C.",
    "wof:placetype":"venue"
},
  "geometry": {"coordinates":[5.3220610619,50.8279342651],"type":"Point"}
}