{
  "type": "Feature",
  "properties": {
    "addr:full":"Bogaardenstraat 87 Leuven Vlaams-Brabant 3000",
    "addr:housenumber":"87",
    "addr:postcode":"3000",
    "addr:street":"Bogaardenstraat",
    "iso:country":"BE",
    "sg:address":"Bogaardenstraat 87",
    "sg:city":"Leuven",
    "sg:orig_category":"M\u00e9decins and sp\u00e9cialistes",
    "sg:phone":"+32 16 23 79 50",
    "sg:postcode":"3000",
    "sg:province":"Vlaams-Brabant",
    "wof:name":"S. Bogaerts",
    "wof:placetype":"venue"
},
  "geometry": {"coordinates":[4.7112002373,50.87733078],"type":"Point"}
}