{
  "type": "Feature",
  "properties": {
    "addr:full":"Frederik Van Eedenplein 3b28 Antwerpen Antwerpen 2050",
    "addr:housenumber":"3b28",
    "addr:postcode":"2050",
    "addr:street":"Frederik Van Eedenplein",
    "iso:country":"BE",
    "sg:address":"Frederik Van Eedenplein 3b28",
    "sg:city":"Antwerpen",
    "sg:orig_category":"Dierenartsen",
    "sg:phone":"+32 3 219 44 33",
    "sg:postcode":"2050",
    "sg:province":"Antwerpen",
    "wof:name":"Ralph Biront",
    "wof:placetype":"venue"
},
  "geometry": {"coordinates":[4.3870449066,51.2217750549],"type":"Point"}
}