{
  "type": "Feature",
  "properties": {
    "iso:country":"BE",
    "sg:address":"Avenue Reine Astrid 35b15",
    "sg:city":"Spa",
    "sg:orig_category":"Artsen and specialisten",
    "sg:phone":"+32 87 77 48 50",
    "sg:postcode":"4900",
    "sg:province":"Li\u00e8ge",
    "wof:name":"Bernadette Pirotte",
    "wof:placetype":"venue"
},
  "geometry": {"coordinates":[5.8601880074,50.492275238],"type":"Point"}
}