{
  "type": "Feature",
  "properties": {
    "iso:country":"BE",
    "sg:address":"Alfons Pieterslaan 37",
    "sg:city":"Oostende",
    "sg:classifiers":[
        {
            "category":"Bars & Pubs",
            "type":"Food & Drink"
        }
    ],
    "sg:phone":"+32 59 70 76 42",
    "sg:postcode":"8400",
    "sg:province":"West-Vlaanderen",
    "wof:name":"Rodenbach",
    "wof:placetype":"venue"
},
  "geometry": {"coordinates":[2.913599968,51.2260894775],"type":"Point"}
}