{
  "type": "Feature",
  "properties": {
    "addr:full":"Tempelstraat 35 Ieper West-Vlaanderen 8900",
    "addr:housenumber":"35",
    "addr:postcode":"8900",
    "addr:street":"Tempelstraat",
    "iso:country":"BE",
    "sg:address":"Tempelstraat 35",
    "sg:city":"Ieper",
    "sg:orig_category":"Industri\u00eble wasserijen and droogkuis",
    "sg:phone":"+32 57 20 04 40",
    "sg:postcode":"8900",
    "sg:province":"West-Vlaanderen",
    "wof:name":"Wasserij De Zon",
    "wof:placetype":"venue"
},
  "geometry": {"coordinates":[2.8819680214,50.8490447998],"type":"Point"}
}