{
  "type": "Feature",
  "properties": {
    "iso:country":"BE",
    "sg:address":"Kammerstraat 3",
    "sg:city":"Gent",
    "sg:orig_category":"Groenten and fruit Gh",
    "sg:phone":"+32 9 225 91 45",
    "sg:postcode":"9000",
    "sg:province":"Oost-Vlaanderen",
    "wof:name":"Fruitco",
    "wof:placetype":"venue"
},
  "geometry": {"coordinates":[3.726170063,51.0562896729],"type":"Point"}
}