{
  "type": "Feature",
  "properties": {
    "iso:country":"BE",
    "sg:address":"Putkapelstraat 103h",
    "sg:city":"Gent (sint-denijs-westrem - Afsnee)",
    "sg:classifiers":[
        {
            "category":"Health Services",
            "subcategory":"Doctor",
            "type":"Services"
        }
    ],
    "sg:phone":"+32 9 222 42 20",
    "sg:postcode":"9051",
    "sg:province":"Oost-Vlaanderen",
    "sg:tags":[
        "medicinephysicians",
        "surgeon"
    ],
    "wof:name":"Bekaert Stephane",
    "wof:placetype":"venue"
},
  "geometry": {"coordinates":[3.6930129528,51.0229263306],"type":"Point"}
}