{
  "type": "Feature",
  "properties": {
    "iso:country":"BE",
    "sg:address":"Leernsesteenweg 341",
    "sg:city":"Deinze",
    "sg:orig_category":"Eleveurs and marchands de porcs. Eleveurs de bovins",
    "sg:phone":"+32 9 282 33 17",
    "sg:postcode":"9800",
    "sg:province":"Oost-Vlaanderen",
    "wof:name":"Irene Dobbelaere",
    "wof:placetype":"venue"
},
  "geometry": {"coordinates":[3.5957849026,51.0178985596],"type":"Point"}
}