{
  "type": "Feature",
  "properties": {
    "iso:country":"BE",
    "sg:address":"Holt 86",
    "sg:city":"Bilzen (beverst)",
    "sg:classifiers":[
        {
            "category":"Retail",
            "subcategory":"Repair Shop",
            "type":"Services"
        }
    ],
    "sg:phone":"+32 89 50 23 93",
    "sg:postcode":"3740",
    "sg:province":"Limburg",
    "sg:tags":[
        "radio",
        "television",
        "-",
        "maintenance"
    ],
    "wof:name":"Jermei E",
    "wof:placetype":"venue"
},
  "geometry": {"coordinates":[5.4799880981,50.8878631592],"type":"Point"}
}