{
  "type": "Feature",
  "properties": {
    "addr:full":"Strijtemplein 24 Roosdaal Vlaams-Brabant 1760",
    "addr:housenumber":"24",
    "addr:postcode":"1760",
    "addr:street":"Strijtemplein",
    "iso:country":"BE",
    "sg:address":"Strijtemplein 24",
    "sg:city":"Roosdaal",
    "sg:classifiers":[
        {
            "category":"Cafe",
            "type":"Food & Drink"
        }
    ],
    "sg:phone":"+32 54 32 52 08",
    "sg:postcode":"1760",
    "sg:province":"Vlaams-Brabant",
    "sg:tags":[
        "caf\u00e9s"
    ],
    "wof:name":"Caf\u00c9 Bij De Koster",
    "wof:placetype":"venue"
},
  "geometry": {"coordinates":[4.0744271278,50.8435707092],"type":"Point"}
}