{
  "type": "Feature",
  "properties": {
    "iso:country":"BE",
    "sg:address":"Boulevard De Waterloo 30",
    "sg:city":"Brussel/bruxelles",
    "sg:orig_category":"V\u00eatements pour Hommes",
    "sg:phone":"+32 2 511 41 57",
    "sg:postcode":"1000",
    "sg:province":"Bruxelles-Capitale",
    "wof:name":"Maison Mercken",
    "wof:placetype":"venue"
},
  "geometry": {"coordinates":[4.3583469391,50.8375968933],"type":"Point"}
}