{
  "type": "Feature",
  "properties": {
    "addr:full":"Rue Des Tilleuls 18 Anh\u00e9e Namur 5537",
    "addr:housenumber":"18",
    "addr:postcode":"5537",
    "addr:street":"Rue Des Tilleuls",
    "iso:country":"BE",
    "sg:address":"Rue Des Tilleuls 18",
    "sg:city":"Anh\u00e9e",
    "sg:classifiers":[
        {
            "category":"Real Estate",
            "subcategory":"Architect",
            "type":"Services"
        }
    ],
    "sg:phone":"+32 82 61 18 08",
    "sg:postcode":"5537",
    "sg:province":"Namur",
    "wof:name":"Bertholet L-p",
    "wof:placetype":"venue"
},
  "geometry": {"coordinates":[4.8782567978,50.3087463379],"type":"Point"}
}