{
  "type": "Feature",
  "properties": {
    "addr:full":"Karredongen 14 Lille Antwerpen 2275",
    "addr:housenumber":"14",
    "addr:postcode":"2275",
    "addr:street":"Karredongen",
    "iso:country":"BE",
    "sg:address":"Karredongen 14",
    "sg:city":"Lille",
    "sg:classifiers":[
        {
            "category":"Building & Trades",
            "subcategory":"Construction",
            "type":"Services"
        }
    ],
    "sg:phone":"+32 14 88 21 08",
    "sg:postcode":"2275",
    "sg:province":"Antwerpen",
    "sg:tags":[
        "installation",
        "-",
        "central",
        "heating"
    ],
    "wof:name":"Erva",
    "wof:placetype":"venue"
},
  "geometry": {"coordinates":[4.8243088722,51.2658615112],"type":"Point"}
}