{
  "type": "Feature",
  "properties": {
    "addr:full":"Industriepark 3 Nazareth Oost-Vlaanderen 9810",
    "addr:housenumber":"3",
    "addr:postcode":"9810",
    "addr:street":"Industriepark",
    "iso:country":"BE",
    "sg:address":"Industriepark 3",
    "sg:city":"Nazareth",
    "sg:orig_category":"Onderdelen and accessoires voertuigen Gh",
    "sg:phone":"+32 9 385 50 93",
    "sg:postcode":"9810",
    "sg:province":"Oost-Vlaanderen",
    "wof:name":"Rw Wheels",
    "wof:placetype":"venue"
},
  "geometry": {"coordinates":[3.5967800617,50.9596405029],"type":"Point"}
}