{
  "type": "Feature",
  "properties": {
    "iso:country":"BE",
    "sg:address":"Steenhuffeldorp 94",
    "sg:city":"Londerzeel",
    "sg:orig_category":"Boucheries",
    "sg:phone":"+32 52 30 92 99",
    "sg:postcode":"1840",
    "sg:province":"Vlaams-Brabant",
    "wof:name":"Leo En Marleen",
    "wof:placetype":"venue"
},
  "geometry": {"coordinates":[4.2635970116,50.9938316345],"type":"Point"}
}