{
  "type": "Feature",
  "properties": {
    "iso:country":"BE",
    "sg:address":"Alfred Algoetstraat 9",
    "sg:city":"Lennik",
    "sg:orig_category":"Fleurs and plantes",
    "sg:phone":"+32 2 532 24 81",
    "sg:postcode":"1750",
    "sg:province":"Vlaams-Brabant",
    "wof:name":"Reninka",
    "wof:placetype":"venue"
},
  "geometry": {"coordinates":[4.156235218,50.8056602478],"type":"Point"}
}