{
  "type": "Feature",
  "properties": {
    "iso:country":"BE",
    "sg:address":"Rue Basse-wez 132",
    "sg:city":"Li\u00c8ge",
    "sg:orig_category":"Catering and organisation de f\u00eates",
    "sg:phone":"+32 4 343 25 92",
    "sg:postcode":"4020",
    "sg:province":"Li\u00e8ge",
    "wof:name":"Wozny Et Cie",
    "wof:placetype":"venue"
},
  "geometry": {"coordinates":[5.5875749588,50.6338577271],"type":"Point"}
}