{
  "type": "Feature",
  "properties": {
    "addr:full":"Rue Verbist 64 Sint-joost-ten-node/saint-josse-ten-noode Bruxelles-Capitale 1210",
    "addr:housenumber":"64",
    "addr:postcode":"1210",
    "addr:street":"Rue Verbist",
    "iso:country":"BE",
    "sg:address":"Rue Verbist 64",
    "sg:city":"Sint-joost-ten-node/saint-josse-ten-noode",
    "sg:orig_category":"Electrom\u00e9nager, t\u00e9l\u00e9visions and radios. R\u00e9parations d'appareils \u00e9lectrom\u00e9nagers",
    "sg:phone":"+32 2 219 61 17",
    "sg:postcode":"1210",
    "sg:province":"Bruxelles-Capitale",
    "wof:name":"Antoine Labo Tv",
    "wof:placetype":"venue"
},
  "geometry": {"coordinates":[4.3785600662,50.8513641357],"type":"Point"}
}