{
  "type": "Feature",
  "properties": {
    "addr:full":"Parc Industriel 6 Braine-le-ch\u00e2teau (wauthier-braine) Brabant Wallon 1440",
    "addr:housenumber":"6",
    "addr:postcode":"1440",
    "addr:street":"Parc Industriel",
    "iso:country":"BE",
    "sg:address":"Parc Industriel 6",
    "sg:city":"Braine-le-ch\u00e2teau (wauthier-braine)",
    "sg:classifiers":[
        {
            "category":"Banks & Credit Unions",
            "subcategory":"Investment Brokerage",
            "type":"Services"
        }
    ],
    "sg:postcode":"1440",
    "sg:province":"Brabant Wallon",
    "sg:tags":[
        "aid",
        "rehabiliation",
        "apparatus"
    ],
    "wof:name":"Derby Sopal Belgium Sprl",
    "wof:placetype":"venue"
},
  "geometry": {"coordinates":[4.2687120438,50.6824455261],"type":"Point"}
}