{
  "type": "Feature",
  "properties": {
    "iso:country":"BE",
    "sg:address":"Rue De Ninove 120",
    "sg:city":"Renaix",
    "sg:classifiers":[
        {
            "category":"Retail",
            "subcategory":"Auto Repair",
            "type":"Services"
        }
    ],
    "sg:phone":"+32 55 21 30 06",
    "sg:postcode":"9600",
    "sg:province":"Oost-Vlaanderen",
    "sg:tags":[
        "garage"
    ],
    "wof:name":"Capiau-soetens Bvba",
    "wof:placetype":"venue"
},
  "geometry": {"coordinates":[3.619879961,50.7521629333],"type":"Point"}
}