{
  "type": "Feature",
  "properties": {
    "iso:country":"BE",
    "sg:address":"Palingbotterstraat 1",
    "sg:city":"Dendermonde",
    "sg:orig_category":"Verplichte sociale verzekeringen",
    "sg:phone":"+32 52 33 26 59",
    "sg:postcode":"9200",
    "sg:province":"Oost-Vlaanderen",
    "wof:name":"Bond Moyson",
    "wof:placetype":"venue"
},
  "geometry": {"coordinates":[4.0983099937,51.0315208435],"type":"Point"}
}