{
  "type": "Feature",
  "properties": {
    "iso:country":"BE",
    "sg:address":"De Beukelaerlaan 12",
    "sg:city":"Antwerpen (ekeren)",
    "sg:classifiers":[
        {
            "category":"Professional",
            "subcategory":"Art Services",
            "type":"Services"
        }
    ],
    "sg:phone":"+32 3 541 04 59",
    "sg:postcode":"2180",
    "sg:province":"Antwerpen",
    "sg:tags":[
        "-",
        "painter",
        "artist"
    ],
    "wof:name":"De Leeuw Jef",
    "wof:placetype":"venue"
},
  "geometry": {"coordinates":[4.4182572365,51.2778625488],"type":"Point"}
}