{
  "type": "Feature",
  "properties": {
    "addr:full":"Bosstraat 9 Waasmunster Oost-Vlaanderen 9250",
    "addr:housenumber":"9",
    "addr:postcode":"9250",
    "addr:street":"Bosstraat",
    "iso:country":"BE",
    "sg:address":"Bosstraat 9",
    "sg:city":"Waasmunster",
    "sg:orig_category":"Verlichting and huishoudartikelen",
    "sg:phone":"+32 3 772 18 02",
    "sg:postcode":"9250",
    "sg:province":"Oost-Vlaanderen",
    "wof:name":"Ingrid De Brant",
    "wof:placetype":"venue"
},
  "geometry": {"coordinates":[4.1043457985,51.1264038086],"type":"Point"}
}