{
  "type": "Feature",
  "properties": {
    "iso:country":"BE",
    "sg:address":"Kortrijkstraat 87",
    "sg:city":"Wortegem-petegem",
    "sg:orig_category":"Jardinage. Producteurs de fruits",
    "sg:phone":"+32 55 30 25 25",
    "sg:postcode":"9790",
    "sg:province":"Oost-Vlaanderen",
    "wof:name":"Peter Allegaert",
    "wof:placetype":"venue"
},
  "geometry": {"coordinates":[3.5437440872,50.8257522583],"type":"Point"}
}