{
  "type": "Feature",
  "properties": {
    "addr:full":"Rue De La Station 11 Ath Hainaut 7800",
    "addr:housenumber":"11",
    "addr:postcode":"7800",
    "addr:street":"Rue De La Station",
    "iso:country":"BE",
    "sg:address":"Rue De La Station 11",
    "sg:city":"Ath",
    "sg:classifiers":[
        {
            "category":"Bars & Pubs",
            "type":"Food & Drink"
        }
    ],
    "sg:phone":"+32 68 84 29 39",
    "sg:postcode":"7800",
    "sg:province":"Hainaut",
    "wof:name":"Le Trappiste",
    "wof:placetype":"venue"
},
  "geometry": {"coordinates":[3.777410984,50.6274833679],"type":"Point"}
}