{
  "type": "Feature",
  "properties": {
    "addr:full":"Weitmansstraat 4 Knokke-heist West-Vlaanderen 8300",
    "addr:housenumber":"4",
    "addr:postcode":"8300",
    "addr:street":"Weitmansstraat",
    "iso:country":"BE",
    "sg:address":"Weitmansstraat 4",
    "sg:city":"Knokke-heist",
    "sg:orig_category":"Elektrische installaties voor woningen",
    "sg:phone":"+32 50 61 51 66",
    "sg:postcode":"8300",
    "sg:province":"West-Vlaanderen",
    "wof:name":"Dany Willems",
    "wof:placetype":"venue"
},
  "geometry": {"coordinates":[3.287694931,51.3467254639],"type":"Point"}
}