{
  "type": "Feature",
  "properties": {
    "iso:country":"BE",
    "sg:address":"Arendlaan 7",
    "sg:city":"Vilvoorde",
    "sg:orig_category":"Sportclubs Sportterreinen and installaties behalve sportcentra",
    "sg:phone":"+32 2 267 81 95",
    "sg:postcode":"1800",
    "sg:province":"Vlaams-Brabant",
    "wof:name":"R.c.s. Des Transports",
    "wof:placetype":"venue"
},
  "geometry": {"coordinates":[4.3677000999,50.9103393555],"type":"Point"}
}