{
  "type": "Feature",
  "properties": {
    "addr:full":"Nieuwpoortsesteenweg 507 Oostende West-Vlaanderen 8400",
    "addr:housenumber":"507",
    "addr:postcode":"8400",
    "addr:street":"Nieuwpoortsesteenweg",
    "iso:country":"BE",
    "sg:address":"Nieuwpoortsesteenweg 507",
    "sg:city":"Oostende",
    "sg:classifiers":[
        {
            "category":"Professional",
            "subcategory":"Accounting & Tax Preparation",
            "type":"Services"
        }
    ],
    "sg:phone":"+32 59 50 94 73",
    "sg:postcode":"8400",
    "sg:province":"West-Vlaanderen",
    "sg:tags":[
        "accountant"
    ],
    "wof:name":"Claeys G",
    "wof:placetype":"venue"
},
  "geometry": {"coordinates":[2.8883399963,51.2153282166],"type":"Point"}
}