{
  "type": "Feature",
  "properties": {
    "iso:country":"BE",
    "sg:address":"Rue Fernand Ch\u00e8vremont 45",
    "sg:city":"Fl\u00e9ron (retinne)",
    "sg:classifiers":[
        {
            "category":"Health Services",
            "subcategory":"Health Practitioner",
            "type":"Services"
        }
    ],
    "sg:phone":"+32 4 358 28 49",
    "sg:postcode":"4621",
    "sg:province":"Li\u00e8ge",
    "sg:tags":[
        "physiotherapist"
    ],
    "wof:name":"Radelet Kathleen",
    "wof:placetype":"venue"
},
  "geometry": {"coordinates":[5.6996917725,50.6317443848],"type":"Point"}
}