{
  "type": "Feature",
  "properties": {
    "addr:full":"Rue De Menuchamps 18 Paliseul Luxembourg 6856",
    "addr:housenumber":"18",
    "addr:postcode":"6856",
    "addr:street":"Rue De Menuchamps",
    "iso:country":"BE",
    "sg:address":"Rue De Menuchamps 18",
    "sg:city":"Paliseul",
    "sg:orig_category":"Rundveehouders",
    "sg:phone":"+32 61 53 35 47",
    "sg:postcode":"6856",
    "sg:province":"Luxembourg",
    "wof:name":"Gerard Noel",
    "wof:placetype":"venue"
},
  "geometry": {"coordinates":[5.1617321968,49.8693618774],"type":"Point"}
}