{
  "type": "Feature",
  "properties": {
    "addr:full":"Rue F\u00c9lix Delhasse 20 Sint-gillis/saint-gilles Bruxelles-Capitale 1060",
    "addr:housenumber":"20",
    "addr:postcode":"1060",
    "addr:street":"Rue Fe\u0301Lix Delhasse",
    "iso:country":"BE",
    "sg:address":"Rue F\u00c9lix Delhasse 20",
    "sg:city":"Sint-gillis/saint-gilles",
    "sg:orig_category":"Avocats and conseillers juridiques",
    "sg:phone":"+32 2 534 88 80",
    "sg:postcode":"1060",
    "sg:province":"Bruxelles-Capitale",
    "wof:name":"M. Bobrushkin",
    "wof:placetype":"venue"
},
  "geometry": {"coordinates":[4.3512091637,50.8216018677],"type":"Point"}
}