{
  "type": "Feature",
  "properties": {
    "iso:country":"BE",
    "sg:address":"Chemin Naghin 1",
    "sg:city":"Ath",
    "sg:orig_category":"Eleveurs de bovins",
    "sg:phone":"+32 68 55 17 40",
    "sg:postcode":"7823",
    "sg:province":"Hainaut",
    "wof:name":"Albert Develle",
    "wof:placetype":"venue"
},
  "geometry": {"coordinates":[3.8662700653,50.6342849731],"type":"Point"}
}