{
  "type": "Feature",
  "properties": {
    "iso:country":"BE",
    "sg:address":"Molenakkerweg 21",
    "sg:city":"Lommel",
    "sg:classifiers":[
        {
            "category":"Autos & Motor Vehicles",
            "subcategory":"Automobile Sales",
            "type":"Retail Goods"
        }
    ],
    "sg:phone":"+32 11 55 42 23",
    "sg:postcode":"3920",
    "sg:province":"Limburg",
    "sg:tags":[
        "car",
        "used",
        "-"
    ],
    "wof:name":"Van Herk J Cv",
    "wof:placetype":"venue"
},
  "geometry": {"coordinates":[5.3288202286,51.2337303162],"type":"Point"}
}