{
  "type": "Feature",
  "properties": {
    "addr:full":"Weg Naar Zwartberg 2 Opglabbeek Limburg 3660",
    "addr:housenumber":"2",
    "addr:postcode":"3660",
    "addr:street":"Weg Naar Zwartberg",
    "iso:country":"BE",
    "sg:address":"Weg Naar Zwartberg 2",
    "sg:city":"Opglabbeek",
    "sg:orig_category":"Computers and computerapparatuur Diverse informatica-activiteiten Onderhoud van kantoor- and compute",
    "sg:phone":"+32 89 85 32 44",
    "sg:postcode":"3660",
    "sg:province":"Limburg",
    "wof:name":"Vip Soft",
    "wof:placetype":"venue"
},
  "geometry": {"coordinates":[5.582695961,51.0422973633],"type":"Point"}
}