{
  "type": "Feature",
  "properties": {
    "iso:country":"BE",
    "sg:address":"Chauss\u00e9e De Namur 64",
    "sg:city":"Nivelles",
    "sg:classifiers":[
        {
            "category":"Depot",
            "subcategory":"Train",
            "type":"Transportation"
        }
    ],
    "sg:postcode":"1400",
    "sg:province":"Brabant Wallon",
    "sg:tags":[
        "gear",
        "lifting"
    ],
    "wof:name":"Parmentier",
    "wof:placetype":"venue"
},
  "geometry": {"coordinates":[4.3647999763,50.5953292847],"type":"Point"}
}