{
  "type": "Feature",
  "properties": {
    "addr:full":"Ginderoverstr 143 Diepenbeek Limburg 3590",
    "addr:housenumber":"143",
    "addr:postcode":"3590",
    "addr:street":"Diepenbeek Limburg",
    "iso:country":"BE",
    "sg:address":"Ginderoverstr 143",
    "sg:city":"Diepenbeek",
    "sg:classifiers":[
        {
            "category":"Professional",
            "subcategory":"Engineering",
            "type":"Services"
        }
    ],
    "sg:phone":"+32 11 24 74 00",
    "sg:postcode":"3590",
    "sg:province":"Limburg",
    "sg:tags":[
        "good",
        "material",
        "-",
        "machine",
        "equipment",
        "wood",
        "mechanical",
        "handling",
        "furniture"
    ],
    "wof:name":"Bewel Vzw",
    "wof:placetype":"venue"
},
  "geometry": {"coordinates":[5.3973698616,50.9275398254],"type":"Point"}
}