{
  "type": "Feature",
  "properties": {
    "addr:full":"Rijselsestraat 51 Kortrijk West-Vlaanderen 8500",
    "addr:housenumber":"51",
    "addr:postcode":"8500",
    "addr:street":"Rijselsestraat",
    "iso:country":"BE",
    "sg:address":"Rijselsestraat 51",
    "sg:city":"Kortrijk",
    "sg:orig_category":"Kapsalons",
    "sg:phone":"+32 56 21 02 79",
    "sg:postcode":"8500",
    "sg:province":"West-Vlaanderen",
    "wof:name":"Coiffure Patrick Albert",
    "wof:placetype":"venue"
},
  "geometry": {"coordinates":[3.2620930672,50.827167511],"type":"Point"}
}