{
  "type": "Feature",
  "properties": {
    "addr:full":"Robsonplein 12 Turnhout Antwerpen 2300",
    "addr:housenumber":"12",
    "addr:postcode":"2300",
    "addr:street":"Robsonplein",
    "iso:country":"BE",
    "sg:address":"Robsonplein 12",
    "sg:city":"Turnhout",
    "sg:classifiers":[
        {
            "category":"Cafe",
            "type":"Food & Drink"
        }
    ],
    "sg:phone":"+32 14 42 42 25",
    "sg:postcode":"2300",
    "sg:province":"Antwerpen",
    "sg:tags":[
        "snack-bars"
    ],
    "wof:name":"Panino",
    "wof:placetype":"venue"
},
  "geometry": {"coordinates":[4.9286289215,51.3232269287],"type":"Point"}
}