{
  "type": "Feature",
  "properties": {
    "addr:full":"Rue Des Alli\u00e9s 256 Bruxelles (forest) Bruxelles-Capitale 1190",
    "addr:housenumber":"256",
    "addr:postcode":"1190",
    "addr:street":"Rue Des Allie\u0301S",
    "iso:country":"BE",
    "sg:address":"Rue Des Alli\u00e9s 256",
    "sg:city":"Bruxelles (forest)",
    "sg:classifiers":[
        {
            "category":"Professional",
            "subcategory":"Art Services",
            "type":"Services"
        }
    ],
    "sg:phone":"+32 2 343 78 36",
    "sg:postcode":"1190",
    "sg:province":"Bruxelles-Capitale",
    "sg:tags":[
        "graphic",
        "designer"
    ],
    "wof:name":"Smet",
    "wof:placetype":"venue"
},
  "geometry": {"coordinates":[4.327185154,50.821975708],"type":"Point"}
}