{
  "type": "Feature",
  "properties": {
    "addr:full":"Rue Du Petit Village 20 Malmedy Li\u00e8ge 4960",
    "addr:housenumber":"20",
    "addr:postcode":"4960",
    "addr:street":"Rue Du Petit Village",
    "iso:country":"BE",
    "sg:address":"Rue Du Petit Village 20",
    "sg:city":"Malmedy",
    "sg:orig_category":"Architectes",
    "sg:phone":"+32 80 77 05 93",
    "sg:postcode":"4960",
    "sg:province":"Li\u00e8ge",
    "wof:name":"Guy Jamaigne",
    "wof:placetype":"venue"
},
  "geometry": {"coordinates":[6.069674015,50.457069397],"type":"Point"}
}