{
  "type": "Feature",
  "properties": {
    "iso:country":"BE",
    "sg:address":"Tramstraat 7",
    "sg:city":"Zwevezele",
    "sg:classifiers":[
        {
            "category":"Farming",
            "subcategory":"Crops",
            "type":"Manufacturing & Wholesale Goods"
        }
    ],
    "sg:phone":"+32 51 61 10 72",
    "sg:postcode":"8750",
    "sg:province":"West-Vlaanderen",
    "sg:tags":[
        "vegetable",
        "fruit",
        "agriculture",
        "livestock"
    ],
    "wof:name":"Crisper Nv",
    "wof:placetype":"venue"
},
  "geometry": {"coordinates":[3.2153279781,51.0383262634],"type":"Point"}
}