{
  "type": "Feature",
  "properties": {
    "addr:full":"Somm\u00c9straat 49 Antwerpen Antwerpen 2060",
    "addr:housenumber":"49",
    "addr:postcode":"2060",
    "addr:street":"Somme\u0301Straat",
    "iso:country":"BE",
    "sg:address":"Somm\u00c9straat 49",
    "sg:city":"Antwerpen",
    "sg:orig_category":"Woningbouw",
    "sg:phone":"+32 3 236 79 70",
    "sg:postcode":"2060",
    "sg:province":"Antwerpen",
    "wof:name":"B.g.r.",
    "wof:placetype":"venue"
},
  "geometry": {"coordinates":[4.4389929771,51.2224998474],"type":"Point"}
}