{
  "type": "Feature",
  "properties": {
    "iso:country":"BE",
    "sg:address":"Michel Gillemanstraat 2",
    "sg:city":"Zelzate",
    "sg:orig_category":"Dakwerken Loodgieterij, verwarming and sanitaire installaties",
    "sg:phone":"+32 9 345 51 97",
    "sg:postcode":"9060",
    "sg:province":"Oost-Vlaanderen",
    "wof:name":"Van De Voorde",
    "wof:placetype":"venue"
},
  "geometry": {"coordinates":[3.826884985,51.195438385],"type":"Point"}
}