{
  "type": "Feature",
  "properties": {
    "iso:country":"BE",
    "sg:address":"Schoonslaapsterstraat 49b2",
    "sg:city":"Sint-jans-molenbeek/molenbeek-saint-jean",
    "sg:orig_category":"Plaatsen van vloer- and muurbekleding Schilders",
    "sg:phone":"+32 2 411 36 72",
    "sg:postcode":"1080",
    "sg:province":"Bruxelles-Capitale",
    "wof:name":"Jean-pierre Debodt",
    "wof:placetype":"venue"
},
  "geometry": {"coordinates":[4.3033270836,50.8491287231],"type":"Point"}
}