{
  "type": "Feature",
  "properties": {
    "iso:country":"BE",
    "sg:address":"Nijverseelstraat 19",
    "sg:city":"Opwijk",
    "sg:orig_category":"Drukkerijen and copyshops",
    "sg:phone":"+32 52 35 09 56",
    "sg:postcode":"1745",
    "sg:province":"Vlaams-Brabant",
    "wof:name":"Artilettra",
    "wof:placetype":"venue"
},
  "geometry": {"coordinates":[4.1551952362,50.9635658264],"type":"Point"}
}