{
  "type": "Feature",
  "properties": {
    "addr:full":"August Nihoulstraat 16 Scherpenheuvel-zichem Vlaams-Brabant 3270",
    "addr:housenumber":"16",
    "addr:postcode":"3270",
    "addr:street":"Nihoulstraat",
    "iso:country":"BE",
    "sg:address":"August Nihoulstraat 16",
    "sg:city":"Scherpenheuvel-zichem",
    "sg:orig_category":"Schoenen",
    "sg:phone":"+32 13 77 14 93",
    "sg:postcode":"3270",
    "sg:province":"Vlaams-Brabant",
    "wof:name":"Simonne Strackx",
    "wof:placetype":"venue"
},
  "geometry": {"coordinates":[4.9790902138,50.9785232544],"type":"Point"}
}