{
  "type": "Feature",
  "properties": {
    "addr:full":"Elverdingsestraat 8 Ieper West-Vlaanderen 8900",
    "addr:housenumber":"8",
    "addr:postcode":"8900",
    "addr:street":"Elverdingsestraat",
    "iso:country":"BE",
    "sg:address":"Elverdingsestraat 8",
    "sg:city":"Ieper",
    "sg:orig_category":"HERSTELLING ELEKTRISCHE HUISHOUDAPPARATEN Huishoudapparaten, televisies and radio's Telecommunicatie",
    "sg:phone":"+32 57 21 71 97",
    "sg:postcode":"8900",
    "sg:province":"West-Vlaanderen",
    "wof:name":"Eldi",
    "wof:placetype":"venue"
},
  "geometry": {"coordinates":[2.8828759193,50.8523292542],"type":"Point"}
}