{
  "type": "Feature",
  "properties": {
    "iso:country":"BE",
    "sg:address":"Krapstraat 190",
    "sg:city":"Buggenhout",
    "sg:orig_category":"Pain, p\u00e2tisseries and confiseries. Ventes diverses de d\u00e9tail hors magasins",
    "sg:phone":"+32 52 35 03 47",
    "sg:postcode":"9255",
    "sg:province":"Oost-Vlaanderen",
    "wof:name":"Bakkerij Roels-thire",
    "wof:placetype":"venue"
},
  "geometry": {"coordinates":[4.1809902191,51.0031890869],"type":"Point"}
}