{
  "type": "Feature",
  "properties": {
    "addr:full":"Beirstoppellos 18 Wetteren Oost-Vlaanderen 9230",
    "addr:housenumber":"18",
    "addr:postcode":"9230",
    "addr:street":"Beirstoppellos",
    "iso:country":"BE",
    "sg:address":"Beirstoppellos 18",
    "sg:city":"Wetteren",
    "sg:classifiers":[
        {
            "category":"Professional",
            "subcategory":"Accounting & Tax Preparation",
            "type":"Services"
        }
    ],
    "sg:phone":"+32 9 369 08 07",
    "sg:postcode":"9230",
    "sg:province":"Oost-Vlaanderen",
    "sg:tags":[
        "bookkeeper"
    ],
    "wof:name":"Van Caekenberghe & Co Bvba",
    "wof:placetype":"venue"
},
  "geometry": {"coordinates":[3.8725700378,51.0124664307],"type":"Point"}
}