{
  "type": "Feature",
  "properties": {
    "addr:full":"Vossenstraat 20 Kortenberg Vlaams-Brabant 3078",
    "addr:housenumber":"20",
    "addr:postcode":"3078",
    "addr:street":"Vossenstraat;Vlaams-Brabant",
    "iso:country":"BE",
    "sg:address":"Vossenstraat 20",
    "sg:city":"Kortenberg",
    "sg:orig_category":"Kapsalons",
    "sg:phone":"+32 2 759 94 37",
    "sg:postcode":"3078",
    "sg:province":"Vlaams-Brabant",
    "wof:name":"Alfred Cloetens",
    "wof:placetype":"venue"
},
  "geometry": {"coordinates":[4.5331759453,50.871383667],"type":"Point"}
}