{
  "type": "Feature",
  "properties": {
    "iso:country":"BE",
    "sg:address":"Rue Cul\u00c9e 53",
    "sg:city":"Waterloo",
    "sg:orig_category":"Installation \u00e9lectrique r\u00e9sidentielle",
    "sg:phone":"+32 475 51 94 21",
    "sg:postcode":"1410",
    "sg:province":"Brabant Wallon",
    "wof:name":"Evolutel",
    "wof:placetype":"venue"
},
  "geometry": {"coordinates":[4.3997030258,50.6986656189],"type":"Point"}
}