{
  "type": "Feature",
  "properties": {
    "addr:full":"Blankenbergse Steenweg 388 Brugge West-Vlaanderen 8000",
    "addr:housenumber":"388",
    "addr:postcode":"8000",
    "addr:street":"Blankenbergse Steenweg",
    "iso:country":"BE",
    "sg:address":"Blankenbergse Steenweg 388",
    "sg:city":"Brugge",
    "sg:orig_category":"V\u00e9hicules automobiles. Entretien and r\u00e9parations de voitures",
    "sg:phone":"+32 50 31 62 22",
    "sg:postcode":"8000",
    "sg:province":"West-Vlaanderen",
    "wof:name":"Garage Lambrecht",
    "wof:placetype":"venue"
},
  "geometry": {"coordinates":[3.194026947,51.249256134],"type":"Point"}
}