{
  "type": "Feature",
  "properties": {
    "iso:country":"BE",
    "sg:address":"Zonnestraat 33",
    "sg:city":"Aalst",
    "sg:classifiers":[
        {
            "category":"Freight",
            "type":"Transportation"
        }
    ],
    "sg:phone":"+32 53 75 05 81",
    "sg:postcode":"9300",
    "sg:province":"Oost-Vlaanderen",
    "sg:tags":[
        "-",
        "transport"
    ],
    "wof:name":"Peter Ophalffens Bvba",
    "wof:placetype":"venue"
},
  "geometry": {"coordinates":[4.0402722359,50.9343910217],"type":"Point"}
}