{
  "type": "Feature",
  "properties": {
    "addr:full":"Doorniksesteenweg 81a Box 5 Kortrijk West-Vlaanderen 8500",
    "addr:housenumber":"81a box 5",
    "addr:postcode":"8500",
    "addr:street":"Doorniksesteenweg",
    "iso:country":"BE",
    "sg:address":"Doorniksesteenweg 81a Box 5",
    "sg:city":"Kortrijk",
    "sg:classifiers":[
        {
            "category":"Professional",
            "subcategory":"Computer Services",
            "type":"Services"
        }
    ],
    "sg:phone":"+32 56 25 90 99",
    "sg:postcode":"8500",
    "sg:province":"West-Vlaanderen",
    "sg:tags":[
        "-",
        "processing",
        "data",
        "software"
    ],
    "wof:name":"D.i.s.c.",
    "wof:placetype":"venue"
},
  "geometry": {"coordinates":[3.2784368992,50.8091964722],"type":"Point"}
}