{
  "type": "Feature",
  "properties": {
    "addr:full":"Rue Jules Rasquinet 18 Beyne-heusay (queue-du-bois) Li\u00e8ge 4610",
    "addr:housenumber":"18",
    "addr:postcode":"4610",
    "addr:street":"Rue Jules Rasquinet",
    "iso:country":"BE",
    "sg:address":"Rue Jules Rasquinet 18",
    "sg:city":"Beyne-heusay (queue-du-bois)",
    "sg:orig_category":"Non-Classified Establishments",
    "sg:phone":"+32 4 370 16 89",
    "sg:postcode":"4610",
    "sg:province":"Li\u00e8ge",
    "wof:name":"Gillu",
    "wof:placetype":"venue"
},
  "geometry": {"coordinates":[5.6729288101,50.6385765076],"type":"Point"}
}