{
  "type": "Feature",
  "properties": {
    "iso:country":"BE",
    "sg:address":"Gildenstraat 34",
    "sg:city":"Retie",
    "sg:orig_category":"Artsen and specialisten",
    "sg:phone":"+32 14 37 70 29",
    "sg:postcode":"2470",
    "sg:province":"Antwerpen",
    "wof:name":"W. Van Spaendonck",
    "wof:placetype":"venue"
},
  "geometry": {"coordinates":[5.0802798271,51.2640686035],"type":"Point"}
}