{
  "type": "Feature",
  "properties": {
    "iso:country":"BE",
    "sg:address":"Witte Vrouwenlaan 94",
    "sg:city":"Sint-pieters-woluwe/woluwe-saint-pierre",
    "sg:orig_category":"Installatie van houten of kunststof schrijnwerk",
    "sg:phone":"+32 2 779 90 38",
    "sg:postcode":"1150",
    "sg:province":"Bruxelles-Capitale",
    "wof:name":"Philippe Destanberg",
    "wof:placetype":"venue"
},
  "geometry": {"coordinates":[4.464744091,50.827495575],"type":"Point"}
}