{
  "type": "Feature",
  "properties": {
    "addr:full":"Rue Du Moulin 20 Ath Hainaut 7800",
    "addr:housenumber":"20",
    "addr:postcode":"7800",
    "addr:street":"Rue Du Moulin",
    "iso:country":"BE",
    "sg:address":"Rue Du Moulin 20",
    "sg:city":"Ath",
    "sg:orig_category":"Schoenen",
    "sg:phone":"+32 68 28 16 34",
    "sg:postcode":"7800",
    "sg:province":"Hainaut",
    "wof:name":"Shoes In The Box",
    "wof:placetype":"venue"
},
  "geometry": {"coordinates":[3.7776501179,50.6304359436],"type":"Point"}
}