{
  "type": "Feature",
  "properties": {
    "addr:full":"Au Gris Han 13 Tenneville Luxembourg 6970",
    "addr:housenumber":"13",
    "addr:postcode":"6970",
    "addr:street":"Au Gris Han",
    "iso:country":"BE",
    "sg:address":"Au Gris Han 13",
    "sg:city":"Tenneville",
    "sg:orig_category":"Gestion des d\u00e9charges and sites d\u00e9finitifs de stockage",
    "sg:phone":"+32 84 45 60 91",
    "sg:postcode":"6970",
    "sg:province":"Luxembourg",
    "wof:name":"Parcs A Conteneurs Tenneville",
    "wof:placetype":"venue"
},
  "geometry": {"coordinates":[5.5179748535,50.0921669006],"type":"Point"}
}