{
  "type": "Feature",
  "properties": {
    "addr:full":"Torrestraat 16 Lebbeke Oost-Vlaanderen 9280",
    "addr:housenumber":"16",
    "addr:postcode":"9280",
    "addr:street":"Torrestraat",
    "iso:country":"BE",
    "sg:address":"Torrestraat 16",
    "sg:city":"Lebbeke",
    "sg:classifiers":[
        {
            "category":"Food & Beverages",
            "subcategory":"Fruits & Vegetables",
            "type":"Retail Goods"
        }
    ],
    "sg:phone":"+32 52 35 59 13",
    "sg:postcode":"9280",
    "sg:province":"Oost-Vlaanderen",
    "sg:tags":[
        "l\u00e9gumes",
        "gr"
    ],
    "wof:name":"Van Weyenberge",
    "wof:placetype":"venue"
},
  "geometry": {"coordinates":[4.1390881538,50.978351593],"type":"Point"}
}