{
  "type": "Feature",
  "properties": {
    "iso:country":"BE",
    "sg:address":"Rue De Droixhe 16",
    "sg:city":"Li\u00c8ge",
    "sg:orig_category":"Boucheries",
    "sg:phone":"+32 4 223 05 88",
    "sg:postcode":"4020",
    "sg:province":"Li\u00e8ge",
    "wof:name":"Gescovian",
    "wof:placetype":"venue"
},
  "geometry": {"coordinates":[5.6135759354,50.6479225159],"type":"Point"}
}