{
  "type": "Feature",
  "properties": {
    "iso:country":"BE",
    "sg:address":"Fran\u00c7ois-jos. Navezstr. 18b5",
    "sg:city":"Schaarbeek/schaerbeek",
    "sg:orig_category":"Industri\u00eble wasserijen and droogkuis",
    "sg:phone":"+32 2 215 63 67",
    "sg:postcode":"1030",
    "sg:province":"Bruxelles-Capitale",
    "wof:name":"Wasserij Ideal",
    "wof:placetype":"venue"
},
  "geometry": {"coordinates":[4.3716788292,50.8702316284],"type":"Point"}
}