{
  "type": "Feature",
  "properties": {
    "addr:full":"Rue De La Catoire 18 Beloeil (ramegnies) Hainaut 7971",
    "addr:housenumber":"18",
    "addr:postcode":"7971",
    "addr:street":"Rue De La Catoire",
    "iso:country":"BE",
    "sg:address":"Rue De La Catoire 18",
    "sg:city":"Beloeil (ramegnies)",
    "sg:classifiers":[
        {
            "category":"Food & Beverages",
            "subcategory":"Farmers Market",
            "type":"Retail Goods"
        }
    ],
    "sg:phone":"+32 69 57 55 55",
    "sg:postcode":"7971",
    "sg:province":"Hainaut",
    "sg:tags":[
        "fried",
        "van",
        "potato"
    ],
    "wof:name":"Magamobil Sprl",
    "wof:placetype":"venue"
},
  "geometry": {"coordinates":[3.6406540871,50.5427436829],"type":"Point"}
}