{
  "type": "Feature",
  "properties": {
    "addr:full":"Torhoutstraat 7 Houthulst West-Vlaanderen 8650",
    "addr:housenumber":"7",
    "addr:postcode":"8650",
    "addr:street":"Torhoutstraat",
    "iso:country":"BE",
    "sg:address":"Torhoutstraat 7",
    "sg:city":"Houthulst",
    "sg:orig_category":"Eleveurs and marchands de porcs",
    "sg:phone":"+32 51 54 46 00",
    "sg:postcode":"8650",
    "sg:province":"West-Vlaanderen",
    "wof:name":"Georges Vancraeynest",
    "wof:placetype":"venue"
},
  "geometry": {"coordinates":[2.9224419594,50.9837188721],"type":"Point"}
}