{
  "type": "Feature",
  "properties": {
    "addr:full":"Roodebeeksteenweg 300 Sint-lambrechts-woluwe/woluwe-saint-lambert Bruxelles-Capitale 1200",
    "addr:housenumber":"300",
    "addr:postcode":"1200",
    "addr:street":"Roodebeeksteenweg",
    "iso:country":"BE",
    "sg:address":"Roodebeeksteenweg 300",
    "sg:city":"Sint-lambrechts-woluwe/woluwe-saint-lambert",
    "sg:orig_category":"Diverse organisaties and verenigingen",
    "sg:phone":"+32 2 770 53 97",
    "sg:postcode":"1200",
    "sg:province":"Bruxelles-Capitale",
    "wof:name":"M.j. Le Gue",
    "wof:placetype":"venue"
},
  "geometry": {"coordinates":[4.4229650497,50.8491210938],"type":"Point"}
}