{
  "type": "Feature",
  "properties": {
    "addr:full":"Drie Lindenstraat 32 Watermaal-bosvoorde/watermael-boitsfort Bruxelles-Capitale 1170",
    "addr:housenumber":"32",
    "addr:postcode":"1170",
    "addr:street":"Drie Lindenstraat",
    "iso:country":"BE",
    "sg:address":"Drie Lindenstraat 32",
    "sg:city":"Watermaal-bosvoorde/watermael-boitsfort",
    "sg:orig_category":"Openbare bibliotheken and archieven",
    "sg:phone":"+32 2 660 07 94",
    "sg:postcode":"1170",
    "sg:province":"Bruxelles-Capitale",
    "wof:name":"Biblioth\u00c8que Principale",
    "wof:placetype":"venue"
},
  "geometry": {"coordinates":[4.4144911766,50.8016853333],"type":"Point"}
}