{
  "type": "Feature",
  "properties": {
    "addr:full":"Rue De La Morie 5 Gedinne Namur 5575",
    "addr:housenumber":"5",
    "addr:postcode":"5575",
    "addr:street":"Rue De La Morie",
    "iso:country":"BE",
    "sg:address":"Rue De La Morie 5",
    "sg:city":"Gedinne",
    "sg:orig_category":"Protection civile",
    "sg:phone":"+32 61 58 93 39",
    "sg:postcode":"5575",
    "sg:province":"Namur",
    "wof:name":"Corps De Pompiers",
    "wof:placetype":"venue"
},
  "geometry": {"coordinates":[4.9356179237,49.9844322205],"type":"Point"}
}