{
  "type": "Feature",
  "properties": {
    "addr:full":"Chauss\u00c9e De Wavre 1615 Oudergem/auderghem Bruxelles-Capitale 1160",
    "addr:postcode":"1615;1160",
    "addr:street":"Chausse\u0301E De Wavre",
    "iso:country":"BE",
    "sg:address":"Chauss\u00c9e De Wavre 1615",
    "sg:city":"Oudergem/auderghem",
    "sg:classifiers":[
        {
            "category":"Personal",
            "subcategory":"Beauty Salon",
            "type":"Services"
        }
    ],
    "sg:phone":"+32 2 672 90 17",
    "sg:postcode":"1160",
    "sg:province":"Bruxelles-Capitale",
    "sg:tags":[
        "de",
        "coiffure"
    ],
    "wof:name":"Coiffure Lebrun",
    "wof:placetype":"venue"
},
  "geometry": {"coordinates":[4.4211812019,50.8173141479],"type":"Point"}
}