{
  "type": "Feature",
  "properties": {
    "addr:full":"Chauss\u00e9e De Bruxelles 4 Genappe (baisy-thy) Brabant Wallon 1470",
    "addr:housenumber":"4",
    "addr:postcode":"1470",
    "addr:street":"Chausse\u0301E De Bruxelles",
    "iso:country":"BE",
    "sg:address":"Chauss\u00e9e De Bruxelles 4",
    "sg:city":"Genappe (baisy-thy)",
    "sg:classifiers":[
        {
            "category":"Home & Garden",
            "subcategory":"Building Materials",
            "type":"Retail Goods"
        }
    ],
    "sg:phone":"+32 67 33 07 24",
    "sg:postcode":"1470",
    "sg:province":"Brabant Wallon",
    "sg:tags":[
        "bathroom",
        "installation",
        "accessory"
    ],
    "wof:name":"Maison D'orka (la)",
    "wof:placetype":"venue"
},
  "geometry": {"coordinates":[4.4504609108,50.6110496521],"type":"Point"}
}