{
  "type": "Feature",
  "properties": {
    "iso:country":"BE",
    "sg:address":"Hertsbergsestraat 68",
    "sg:city":"Oostkamp",
    "sg:orig_category":"Eleveurs and marchands de porcs. Eleveurs de bovins",
    "sg:phone":"+32 50 82 25 59",
    "sg:postcode":"8020",
    "sg:province":"West-Vlaanderen",
    "wof:name":"Jeannette Verhaeghe",
    "wof:placetype":"venue"
},
  "geometry": {"coordinates":[3.2602200508,51.1319885254],"type":"Point"}
}