{
  "type": "Feature",
  "properties": {
    "addr:full":"Dobbelenbergstraat 12 Machelen Vlaams-Brabant 1830",
    "addr:housenumber":"12",
    "addr:postcode":"1830",
    "addr:street":"Dobbelenbergstraat",
    "iso:country":"BE",
    "sg:address":"Dobbelenbergstraat 12",
    "sg:city":"Machelen",
    "sg:orig_category":"Non-Classified Establishments",
    "sg:phone":"+32 475 70 53 25",
    "sg:postcode":"1830",
    "sg:province":"Vlaams-Brabant",
    "wof:name":"Mega Biscuits Center Vanneste",
    "wof:placetype":"venue"
},
  "geometry": {"coordinates":[4.4184541702,50.9038314819],"type":"Point"}
}