{
  "type": "Feature",
  "properties": {
    "addr:full":"Oelegemsteenweg 69 Wommelgem Antwerpen 2160",
    "addr:housenumber":"69",
    "addr:postcode":"2160",
    "addr:street":"Oelegemsteenweg",
    "iso:country":"BE",
    "sg:address":"Oelegemsteenweg 69",
    "sg:city":"Wommelgem",
    "sg:classifiers":[
        {
            "category":"Bars & Pubs",
            "type":"Food & Drink"
        }
    ],
    "sg:phone":"+32 3 353 98 88",
    "sg:postcode":"2160",
    "sg:province":"Antwerpen",
    "wof:name":"Den Eenhoorn",
    "wof:placetype":"venue"
},
  "geometry": {"coordinates":[4.5436959267,51.2181243896],"type":"Point"}
}