{
  "type": "Feature",
  "properties": {
    "addr:full":"Rue Du Trieu-kaisin 1 Ch\u00c2telet Hainaut 6200",
    "addr:housenumber":"1",
    "addr:postcode":"6200",
    "addr:street":"Rue Du Trieu-Kaisin",
    "iso:country":"BE",
    "sg:address":"Rue Du Trieu-kaisin 1",
    "sg:city":"Ch\u00c2telet",
    "sg:classifiers":[
        {
            "category":"Cinema",
            "subcategory":"Movie Rental",
            "type":"Entertainment"
        }
    ],
    "sg:phone":"+32 71 39 68 95",
    "sg:postcode":"6200",
    "sg:province":"Hainaut",
    "sg:tags":[
        "de",
        "cassette",
        "location",
        "vid\u00e9o",
        "audio"
    ],
    "wof:name":"Vid\u00c9o Futur",
    "wof:placetype":"venue"
},
  "geometry": {"coordinates":[4.4989500046,50.4061737061],"type":"Point"}
}