{
  "type": "Feature",
  "properties": {
    "iso:country":"BE",
    "sg:address":"Rue Sart-lez-moulin",
    "sg:city":"Courcelles",
    "sg:orig_category":"Winkelinrichting and handelsuitrusting Gh",
    "sg:phone":"+32 71 45 51 52",
    "sg:postcode":"6180",
    "sg:province":"Hainaut",
    "wof:name":"Gosset",
    "wof:placetype":"venue"
},
  "geometry": {"coordinates":[4.3584752083,50.4405250549],"type":"Point"}
}