{
  "type": "Feature",
  "properties": {
    "iso:country":"BE",
    "sg:address":"Prins Albertlaan 33a",
    "sg:city":"Sint-truiden",
    "sg:orig_category":"Opticiens",
    "sg:phone":"+32 11 68 83 91",
    "sg:postcode":"3800",
    "sg:province":"Limburg",
    "wof:name":"Cleeren Jan & Co",
    "wof:placetype":"venue"
},
  "geometry": {"coordinates":[5.1800718307,50.8183021545],"type":"Point"}
}