{
  "type": "Feature",
  "properties": {
    "addr:full":"Rue Sainte-henriette Morlanwelz Hainaut 7140",
    "addr:postcode":"7140",
    "addr:street":"Rue Sainte-Henriette;Hainaut",
    "iso:country":"BE",
    "sg:address":"Rue Sainte-henriette",
    "sg:city":"Morlanwelz",
    "sg:classifiers":[
        {
            "category":"Utilities",
            "type":"Services"
        }
    ],
    "sg:phone":"+32 64 44 31 94",
    "sg:postcode":"7140",
    "sg:province":"Hainaut",
    "sg:tags":[
        "raw",
        "energy",
        "material"
    ],
    "wof:name":"Etablissements Socoarc Sa",
    "wof:placetype":"venue"
},
  "geometry": {"coordinates":[4.2632360458,50.4643592834],"type":"Point"}
}