{
  "type": "Feature",
  "properties": {
    "iso:country":"BE",
    "sg:address":"Sint-denijsestraat 97",
    "sg:city":"Kortrijk",
    "sg:orig_category":"Herstellingen and onderhoud van auto's",
    "sg:phone":"+32 56 22 23 99",
    "sg:postcode":"8500",
    "sg:province":"West-Vlaanderen",
    "wof:name":"R. Coppens",
    "wof:placetype":"venue"
},
  "geometry": {"coordinates":[3.2730329037,50.822052002],"type":"Point"}
}