{
  "type": "Feature",
  "properties": {
    "iso:country":"BE",
    "sg:address":"Manhovestraat 27",
    "sg:city":"Herne (sint-pieters-kapelle)",
    "sg:classifiers":[
        {
            "category":"Shopping",
            "subcategory":"Pets & Pet Supplies",
            "type":"Retail Goods"
        }
    ],
    "sg:phone":"+32 2 396 18 58",
    "sg:postcode":"1541",
    "sg:province":"Vlaams-Brabant",
    "sg:tags":[
        "horseriding"
    ],
    "wof:name":"De Manshoeve",
    "wof:placetype":"venue"
},
  "geometry": {"coordinates":[3.9753260612,50.6959648132],"type":"Point"}
}