{
  "type": "Feature",
  "properties": {
    "addr:full":"Waverse Steenweg 1741 Oudergem/auderghem Bruxelles-Capitale 1160",
    "addr:postcode":"1741;1160",
    "addr:street":"Waverse Steenweg",
    "iso:country":"BE",
    "sg:address":"Waverse Steenweg 1741",
    "sg:city":"Oudergem/auderghem",
    "sg:orig_category":"Banken and kredietinstellingen",
    "sg:phone":"+32 2 673 73 12",
    "sg:postcode":"1160",
    "sg:province":"Bruxelles-Capitale",
    "wof:name":"Dexia",
    "wof:placetype":"venue"
},
  "geometry": {"coordinates":[4.4277758598,50.8161659241],"type":"Point"}
}