{
  "type": "Feature",
  "properties": {
    "addr:full":"Diestsebaan 14 Diest Vlaams-Brabant 3290",
    "addr:housenumber":"14",
    "addr:postcode":"3290",
    "addr:street":"Diestsebaan",
    "iso:country":"BE",
    "sg:address":"Diestsebaan 14",
    "sg:city":"Diest",
    "sg:orig_category":"Banques and organismes de cr\u00e9dit",
    "sg:phone":"+32 13 31 29 37",
    "sg:postcode":"3290",
    "sg:province":"Vlaams-Brabant",
    "wof:name":"Citibank",
    "wof:placetype":"venue"
},
  "geometry": {"coordinates":[5.0698041916,50.9952392578],"type":"Point"}
}