{
  "type": "Feature",
  "properties": {
    "iso:country":"BE",
    "sg:address":"R. Rabelais 18",
    "sg:city":"Ottignies-louvain-la-neuve",
    "sg:classifiers":[
        {
            "category":"Restaurant",
            "type":"Food & Drink"
        }
    ],
    "sg:phone":"+32 10 45 42 32",
    "sg:postcode":"1348",
    "sg:province":"Brabant Wallon",
    "wof:name":"La Couscoussi\u00c8re",
    "wof:placetype":"venue"
},
  "geometry": {"coordinates":[4.6129808426,50.669254303],"type":"Point"}
}