{
  "type": "Feature",
  "properties": {
    "addr:full":"Rigessel 147 Rotselaar Vlaams-Brabant 3111",
    "addr:housenumber":"147",
    "addr:postcode":"3111",
    "addr:street":"Rigessel",
    "iso:country":"BE",
    "sg:address":"Rigessel 147",
    "sg:city":"Rotselaar",
    "sg:orig_category":"Persagentschappen Reclamebureaus",
    "sg:phone":"+32 16 58 04 68",
    "sg:postcode":"3111",
    "sg:province":"Vlaams-Brabant",
    "wof:name":"Miet Waes",
    "wof:placetype":"venue"
},
  "geometry": {"coordinates":[4.751513958,50.9443588257],"type":"Point"}
}