{
  "type": "Feature",
  "properties": {
    "addr:full":"Apostelhuizen 26 Gent Oost-Vlaanderen 9000",
    "addr:housenumber":"26",
    "addr:postcode":"9000",
    "addr:street":"Apostelhuizen;Oost-Vlaanderen",
    "iso:country":"BE",
    "sg:address":"Apostelhuizen 26",
    "sg:city":"Gent",
    "sg:classifiers":[
        {
            "category":"Insurance",
            "subcategory":"Insurance Agent",
            "type":"Services"
        }
    ],
    "sg:phone":"+32 9 233 66 89",
    "sg:postcode":"9000",
    "sg:province":"Oost-Vlaanderen",
    "sg:tags":[
        "verzekeringsmakelaars",
        "expert"
    ],
    "wof:name":"T.c.d.",
    "wof:placetype":"venue"
},
  "geometry": {"coordinates":[3.733987093,51.0512962341],"type":"Point"}
}