{
  "type": "Feature",
  "properties": {
    "iso:country":"BE",
    "sg:address":"Hulstersestraat 65",
    "sg:city":"Wielsbeke",
    "sg:orig_category":"Woningbouw",
    "sg:phone":"+32 56 66 78 20",
    "sg:postcode":"8710",
    "sg:province":"West-Vlaanderen",
    "wof:name":"Tony Verhulst",
    "wof:placetype":"venue"
},
  "geometry": {"coordinates":[3.3267951012,50.8946075439],"type":"Point"}
}