{
  "type": "Feature",
  "properties": {
    "iso:country":"BE",
    "sg:address":"Maaseikerlaan 71",
    "sg:city":"Maaseik (neeroeteren)",
    "sg:classifiers":[
        {
            "category":"Health Services",
            "subcategory":"Dentist",
            "type":"Services"
        }
    ],
    "sg:phone":"+32 89 86 33 51",
    "sg:postcode":"3680",
    "sg:province":"Limburg",
    "wof:name":"Hons J",
    "wof:placetype":"venue"
},
  "geometry": {"coordinates":[5.791285038,51.0954208374],"type":"Point"}
}