{
  "type": "Feature",
  "properties": {
    "iso:country":"BE",
    "sg:address":"Dennestraat 24",
    "sg:city":"Sint-katelijne-waver",
    "sg:classifiers":[
        {
            "category":"Home & Garden",
            "subcategory":"Home Furnishings",
            "type":"Retail Goods"
        }
    ],
    "sg:phone":"+32 15 41 32 72",
    "sg:postcode":"2860",
    "sg:province":"Antwerpen",
    "sg:tags":[
        "interior",
        "decoration"
    ],
    "wof:name":"La Marche Bvba",
    "wof:placetype":"venue"
},
  "geometry": {"coordinates":[4.510612011,51.0467643738],"type":"Point"}
}