{
  "type": "Feature",
  "properties": {
    "iso:country":"BE",
    "sg:address":"Rue Masui 73",
    "sg:city":"Bruxelles",
    "sg:classifiers":[
        {
            "category":"Education",
            "subcategory":"School",
            "type":"Public Place"
        }
    ],
    "sg:phone":"+32 2 203 40 07",
    "sg:postcode":"1000",
    "sg:province":"Bruxelles-Capitale",
    "sg:tags":[
        "primary"
    ],
    "wof:name":"All\u00e9e Verte (l')",
    "wof:placetype":"venue"
},
  "geometry": {"coordinates":[4.3603100777,50.8677597046],"type":"Point"}
}