{
  "type": "Feature",
  "properties": {
    "addr:full":"Rue Du 19e-r-i-de-brest 22 Paliseul Luxembourg 6852",
    "addr:housenumber":"22",
    "addr:postcode":"6852",
    "addr:street":"Rue Du 19E-R-I-De-Brest",
    "iso:country":"BE",
    "sg:address":"Rue Du 19e-r-i-de-brest 22",
    "sg:city":"Paliseul",
    "sg:orig_category":"Installation de menuiserie en bois and plastique",
    "sg:phone":"+32 61 65 60 65",
    "sg:postcode":"6852",
    "sg:province":"Luxembourg",
    "wof:name":"Jean Collignon",
    "wof:placetype":"venue"
},
  "geometry": {"coordinates":[5.1785240173,49.9646186829],"type":"Point"}
}