{
  "type": "Feature",
  "properties": {
    "iso:country":"BE",
    "sg:address":"Grootlosestraat 69",
    "sg:city":"Tremelo (baal)",
    "sg:classifiers":[
        {
            "category":"Manufacturing",
            "subcategory":"Metals",
            "type":"Manufacturing & Wholesale Goods"
        }
    ],
    "sg:phone":"+32 16 53 16 71",
    "sg:postcode":"3128",
    "sg:province":"Vlaams-Brabant",
    "sg:tags":[
        "working"
    ],
    "wof:name":"Gebotech",
    "wof:placetype":"venue"
},
  "geometry": {"coordinates":[4.735915184,51.0177497864],"type":"Point"}
}