{
  "type": "Feature",
  "properties": {
    "addr:full":"Rue De L'invasion 25 Limbourg (go\u00e9) Li\u00e8ge 4834",
    "addr:housenumber":"25",
    "addr:postcode":"4834",
    "addr:street":"Rue De L'Invasion",
    "iso:country":"BE",
    "sg:address":"Rue De L'invasion 25",
    "sg:city":"Limbourg (go\u00e9)",
    "sg:classifiers":[
        {
            "category":"Retail",
            "subcategory":"Event Space",
            "type":"Services"
        }
    ],
    "sg:phone":"+32 87 65 69 25",
    "sg:postcode":"4834",
    "sg:province":"Li\u00e8ge",
    "sg:tags":[
        "rental",
        "-",
        "hall"
    ],
    "wof:name":"Auberge (l')",
    "wof:placetype":"venue"
},
  "geometry": {"coordinates":[5.9711289406,50.6024856567],"type":"Point"}
}