{
  "type": "Feature",
  "properties": {
    "iso:country":"BE",
    "sg:address":"Rue Sylvain Panis 1",
    "sg:city":"Crisnee",
    "sg:orig_category":"Toeristische diensten",
    "sg:phone":"+32 19 67 81 63",
    "sg:postcode":"4367",
    "sg:province":"Li\u00e8ge",
    "wof:name":"S.l.p.t.",
    "wof:placetype":"venue"
},
  "geometry": {"coordinates":[5.3965368271,50.714756012],"type":"Point"}
}