{
  "type": "Feature",
  "properties": {
    "addr:full":"Rue Pierre L\u00b4hermite 25 Fontaine-l\u00b4ev\u00caque Hainaut 6140",
    "addr:housenumber":"25",
    "addr:postcode":"6140",
    "addr:street":"Rue Pierre L\u00b4Hermite;Hainaut",
    "iso:country":"BE",
    "sg:address":"Rue Pierre L\u00b4hermite 25",
    "sg:city":"Fontaine-l\u00b4ev\u00caque",
    "sg:classifiers":[
        {
            "category":"Taxi",
            "type":"Transportation"
        }
    ],
    "sg:phone":"+32 71 52 43 08",
    "sg:postcode":"6140",
    "sg:province":"Hainaut",
    "wof:name":"Lavo-tax Robert",
    "wof:placetype":"venue"
},
  "geometry": {"coordinates":[4.3254590034,50.4059867859],"type":"Point"}
}