{
  "type": "Feature",
  "properties": {
    "iso:country":"BE",
    "sg:address":"Paardebloemstraat 15",
    "sg:city":"Gistel",
    "sg:orig_category":"Etalage- and showroomontwerpers",
    "sg:phone":"+32 59 27 69 09",
    "sg:postcode":"8470",
    "sg:province":"West-Vlaanderen",
    "wof:name":"Dominiek Depaepe",
    "wof:placetype":"venue"
},
  "geometry": {"coordinates":[2.9809920788,51.1603889465],"type":"Point"}
}