{
  "type": "Feature",
  "properties": {
    "addr:full":"Rue Gustave Taillard 33 Herve Li\u00e8ge 4650",
    "addr:housenumber":"33",
    "addr:postcode":"4650",
    "addr:street":"Rue Gustave Taillard",
    "iso:country":"BE",
    "sg:address":"Rue Gustave Taillard 33",
    "sg:city":"Herve",
    "sg:orig_category":"D\u00e9taillants en pi\u00e8ces and accessoires de voitures",
    "sg:phone":"+32 87 66 16 76",
    "sg:postcode":"4650",
    "sg:province":"Li\u00e8ge",
    "wof:name":"Maison L'automobile",
    "wof:placetype":"venue"
},
  "geometry": {"coordinates":[5.7924599648,50.6420402527],"type":"Point"}
}