{
  "type": "Feature",
  "properties": {
    "addr:full":"Lisperstraat 68 Lier Antwerpen 2500",
    "addr:housenumber":"68",
    "addr:postcode":"2500",
    "addr:street":"Lisperstraat",
    "iso:country":"BE",
    "sg:address":"Lisperstraat 68",
    "sg:city":"Lier",
    "sg:orig_category":"Artiesten and kunstenaars",
    "sg:phone":"+32 3 480 75 13",
    "sg:postcode":"2500",
    "sg:province":"Antwerpen",
    "wof:name":"Door Van Boeckel",
    "wof:placetype":"venue"
},
  "geometry": {"coordinates":[4.5707402229,51.1332168579],"type":"Point"}
}