{
  "type": "Feature",
  "properties": {
    "iso:country":"BE",
    "sg:address":"Dieregaertstraat 9",
    "sg:city":"Alken",
    "sg:classifiers":[
        {
            "category":"Education",
            "subcategory":"School",
            "type":"Public Place"
        }
    ],
    "sg:phone":"+32 11 72 92 26",
    "sg:postcode":"3570",
    "sg:province":"Limburg",
    "sg:tags":[
        "primary"
    ],
    "wof:name":"'t Schommelbootje Vzw",
    "wof:placetype":"venue"
},
  "geometry": {"coordinates":[5.3032097816,50.8756217957],"type":"Point"}
}