{
  "type": "Feature",
  "properties": {
    "addr:full":"Rijselstraat 174 Menen West-Vlaanderen 8930",
    "addr:housenumber":"174",
    "addr:postcode":"8930",
    "addr:street":"Rijselstraat",
    "iso:country":"BE",
    "sg:address":"Rijselstraat 174",
    "sg:city":"Menen",
    "sg:classifiers":[
        {
            "category":"Restaurant",
            "type":"Food & Drink"
        }
    ],
    "sg:phone":"+32 56 51 22 66",
    "sg:postcode":"8930",
    "sg:province":"West-Vlaanderen",
    "wof:name":"Tearoom Novada",
    "wof:placetype":"venue"
},
  "geometry": {"coordinates":[3.1259729862,50.7899627686],"type":"Point"}
}