{
  "type": "Feature",
  "properties": {
    "iso:country":"BE",
    "sg:address":"Ketelstraat 26",
    "sg:city":"Diest",
    "sg:classifiers":[
        {
            "category":"Shopping",
            "subcategory":"Gifts & Souvenirs",
            "type":"Retail Goods"
        }
    ],
    "sg:phone":"+32 13 31 43 74",
    "sg:postcode":"3290",
    "sg:province":"Vlaams-Brabant",
    "sg:tags":[
        "geschenken"
    ],
    "wof:name":"Krillie",
    "wof:placetype":"venue"
},
  "geometry": {"coordinates":[5.0519719124,50.9842605591],"type":"Point"}
}