{
  "type": "Feature",
  "properties": {
    "iso:country":"BE",
    "sg:address":"Rue De La Grotte 21",
    "sg:city":"Herve",
    "sg:classifiers":[
        {
            "category":"Cafe",
            "type":"Food & Drink"
        }
    ],
    "sg:phone":"+32 87 67 59 77",
    "sg:postcode":"4651",
    "sg:province":"Li\u00e8ge",
    "sg:tags":[
        "caf\u00e9s"
    ],
    "wof:name":"Carl Fohal",
    "wof:placetype":"venue"
},
  "geometry": {"coordinates":[5.8030462265,50.6222648621],"type":"Point"}
}