{
  "type": "Feature",
  "properties": {
    "iso:country":"BE",
    "sg:address":"Rue De Champles 47",
    "sg:city":"Wavre",
    "sg:orig_category":"Installation \u00e9lectrique r\u00e9sidentielle",
    "sg:phone":"+32 10 22 27 81",
    "sg:postcode":"1301",
    "sg:province":"Brabant Wallon",
    "wof:name":"Electricit\u00c9 Voets",
    "wof:placetype":"venue"
},
  "geometry": {"coordinates":[4.5746941566,50.7237243652],"type":"Point"}
}