{
  "type": "Feature",
  "properties": {
    "addr:full":"Rue Belle Vue 26 Villers-le-bouillet Li\u00e8ge 4530",
    "addr:housenumber":"26",
    "addr:postcode":"4530",
    "addr:street":"Rue Belle Vue",
    "iso:country":"BE",
    "sg:address":"Rue Belle Vue 26",
    "sg:city":"Villers-le-bouillet",
    "sg:classifiers":[
        {
            "category":"Utilities",
            "subcategory":"Water",
            "type":"Services"
        }
    ],
    "sg:phone":"+32 85 25 15 10",
    "sg:postcode":"4530",
    "sg:province":"Li\u00e8ge",
    "sg:tags":[
        "purification"
    ],
    "wof:name":"Curvers C",
    "wof:placetype":"venue"
},
  "geometry": {"coordinates":[5.2698349953,50.5618782043],"type":"Point"}
}