{
  "type": "Feature",
  "properties": {
    "addr:full":"Hubert D'ydewallestraat 13ba Beernem West-Vlaanderen 8730",
    "addr:housenumber":"13ba",
    "addr:postcode":"8730",
    "addr:street":"Hubert D'Ydewallestraat",
    "iso:country":"BE",
    "sg:address":"Hubert D'ydewallestraat 13ba",
    "sg:city":"Beernem",
    "sg:classifiers":[
        {
            "category":"Communications",
            "subcategory":"Television Station",
            "type":"Services"
        }
    ],
    "sg:phone":"+32 50 79 12 11",
    "sg:postcode":"8730",
    "sg:province":"West-Vlaanderen",
    "sg:tags":[
        "video",
        "audio",
        "verhuur"
    ],
    "wof:name":"Videoclub Cocoon",
    "wof:placetype":"venue"
},
  "geometry": {"coordinates":[3.3212659359,51.1292686462],"type":"Point"}
}