{
  "type": "Feature",
  "properties": {
    "iso:country":"BE",
    "sg:address":"Antwerpsesteenweg 580",
    "sg:city":"Gent",
    "sg:orig_category":"Kapsalons",
    "sg:phone":"+32 9 228 89 80",
    "sg:postcode":"9040",
    "sg:province":"Oost-Vlaanderen",
    "wof:name":"Coiffure New-men",
    "wof:placetype":"venue"
},
  "geometry": {"coordinates":[3.7552330494,51.0659599304],"type":"Point"}
}