{
  "type": "Feature",
  "properties": {
    "addr:full":"Gentse Steenweg 77 Damme (sijsele) West-Vlaanderen 8340",
    "addr:housenumber":"77",
    "addr:postcode":"8340",
    "addr:street":"Gentse Steenweg",
    "iso:country":"BE",
    "sg:address":"Gentse Steenweg 77",
    "sg:city":"Damme (sijsele)",
    "sg:classifiers":[
        {
            "category":"Building & Trades",
            "subcategory":"Construction",
            "type":"Services"
        }
    ],
    "sg:phone":"+32 50 36 39 79",
    "sg:postcode":"8340",
    "sg:province":"West-Vlaanderen",
    "sg:tags":[
        "asphalt",
        "contractor"
    ],
    "wof:name":"Damme Danny Bvba",
    "wof:placetype":"venue"
},
  "geometry": {"coordinates":[3.362019062,51.2037506104],"type":"Point"}
}