{
  "type": "Feature",
  "properties": {
    "addr:full":"Neerpedestraat 1035 Bruxelles-anderlecht Bruxelles-Capitale 1070",
    "addr:housenumber":"1035",
    "addr:postcode":"1070",
    "addr:street":"Neerpedestraat",
    "iso:country":"BE",
    "sg:address":"Neerpedestraat 1035",
    "sg:city":"Bruxelles-anderlecht",
    "sg:orig_category":"Diensten voor huisdieren Huisdierenkwekers",
    "sg:phone":"+32 2 527 16 75",
    "sg:postcode":"1070",
    "sg:province":"Bruxelles-Capitale",
    "wof:name":"Bouviers Club",
    "wof:placetype":"venue"
},
  "geometry": {"coordinates":[4.2618942261,50.8301429749],"type":"Point"}
}