{
  "type": "Feature",
  "properties": {
    "iso:country":"BE",
    "sg:address":"Rondstraat 13",
    "sg:city":"Kinrooi (molenbeersel)",
    "sg:classifiers":[
        {
            "category":"Wholesale",
            "subcategory":"Beer",
            "type":"Manufacturing & Wholesale Goods"
        }
    ],
    "sg:phone":"+32 89 70 14 83",
    "sg:postcode":"3640",
    "sg:province":"Limburg",
    "sg:tags":[
        "ale",
        "-"
    ],
    "wof:name":"Nies-cox/prik & Tik",
    "wof:placetype":"venue"
},
  "geometry": {"coordinates":[5.741063118,51.168384552],"type":"Point"}
}