{
  "type": "Feature",
  "properties": {
    "addr:full":"Skaldenstraat 129 Gent Oost-Vlaanderen 9042",
    "addr:housenumber":"129",
    "addr:postcode":"9042",
    "addr:street":"Skaldenstraat;Oost-Vlaanderen",
    "iso:country":"BE",
    "sg:address":"Skaldenstraat 129",
    "sg:city":"Gent",
    "sg:orig_category":"Agences d'exp\u00e9dition. Transports routiers de marchandises",
    "sg:phone":"+32 9 255 93 36",
    "sg:postcode":"9042",
    "sg:province":"Oost-Vlaanderen",
    "wof:name":"Ghent Packing & Transport",
    "wof:placetype":"venue"
},
  "geometry": {"coordinates":[3.7816700935,51.1223831177],"type":"Point"}
}