{
  "type": "Feature",
  "properties": {
    "addr:full":"Sneppestraat 35 Kortemark West-Vlaanderen 8610",
    "addr:housenumber":"35",
    "addr:postcode":"8610",
    "addr:street":"Sneppestraat",
    "iso:country":"BE",
    "sg:address":"Sneppestraat 35",
    "sg:city":"Kortemark",
    "sg:classifiers":[
        {
            "category":"Home & Garden",
            "subcategory":"Building Materials",
            "type":"Retail Goods"
        }
    ],
    "sg:phone":"+32 51 56 78 95",
    "sg:postcode":"8610",
    "sg:province":"West-Vlaanderen",
    "sg:tags":[
        "window"
    ],
    "wof:name":"Bruyno Nv",
    "wof:placetype":"venue"
},
  "geometry": {"coordinates":[3.0339119434,51.0327529907],"type":"Point"}
}