{
  "type": "Feature",
  "properties": {
    "iso:country":"BE",
    "sg:address":"Pont A La Faulx 21",
    "sg:city":"Peruwelz",
    "sg:orig_category":"Blanchisseries and teintureries",
    "sg:phone":"+32 69 77 11 68",
    "sg:postcode":"7600",
    "sg:province":"Hainaut",
    "wof:name":"Sainte-barbe Shop",
    "wof:placetype":"venue"
},
  "geometry": {"coordinates":[3.5947089195,50.5108528137],"type":"Point"}
}