{
  "type": "Feature",
  "properties": {
    "iso:country":"BE",
    "sg:address":"Kapelstraat 82",
    "sg:city":"Duffel",
    "sg:classifiers":[
        {
            "category":"Health Services",
            "subcategory":"Health Practitioner",
            "type":"Services"
        }
    ],
    "sg:phone":"+32 15 31 16 30",
    "sg:postcode":"2570",
    "sg:province":"Antwerpen",
    "sg:tags":[
        "physiotherapist"
    ],
    "wof:name":"Verhelst K",
    "wof:placetype":"venue"
},
  "geometry": {"coordinates":[4.5112481117,51.0922966003],"type":"Point"}
}