{
  "type": "Feature",
  "properties": {
    "addr:full":"Breughellaan 2 Moorslede West-Vlaanderen 8890",
    "addr:housenumber":"2",
    "addr:postcode":"8890",
    "addr:street":"Breughellaan",
    "iso:country":"BE",
    "sg:address":"Breughellaan 2",
    "sg:city":"Moorslede",
    "sg:classifiers":[
        {
            "category":"Communications",
            "subcategory":"News Services",
            "type":"Services"
        }
    ],
    "sg:phone":"+32 51 77 01 59",
    "sg:postcode":"8890",
    "sg:province":"West-Vlaanderen",
    "sg:tags":[
        "illustrator"
    ],
    "wof:name":"Cardoen Filip Grafisch Ontwerp",
    "wof:placetype":"venue"
},
  "geometry": {"coordinates":[3.0654649734,50.8858985901],"type":"Point"}
}