{
  "type": "Feature",
  "properties": {
    "addr:full":"Elfde Julistraat 132 Harelbeke West-Vlaanderen 8530",
    "addr:housenumber":"132",
    "addr:postcode":"8530",
    "addr:street":"Julistraat",
    "iso:country":"BE",
    "sg:address":"Elfde Julistraat 132",
    "sg:city":"Harelbeke",
    "sg:orig_category":"Non-Classified Establishments",
    "sg:phone":"+32 56 71 48 53",
    "sg:postcode":"8530",
    "sg:province":"West-Vlaanderen",
    "wof:name":"Christex Nv",
    "wof:placetype":"venue"
},
  "geometry": {"coordinates":[3.2980489731,50.8460159302],"type":"Point"}
}