{
  "type": "Feature",
  "properties": {
    "iso:country":"BE",
    "sg:address":"Rue De Neufch\u00c2tel 36b1",
    "sg:city":"Sint-gillis/saint-gilles",
    "sg:orig_category":"Architectes",
    "sg:phone":"+32 2 537 46 89",
    "sg:postcode":"1060",
    "sg:province":"Bruxelles-Capitale",
    "wof:name":"Jacques Danlee",
    "wof:placetype":"venue"
},
  "geometry": {"coordinates":[4.3535780907,50.8274383545],"type":"Point"}
}