{
  "type": "Feature",
  "properties": {
    "iso:country":"BE",
    "sg:address":"Stelen 33",
    "sg:city":"Geel",
    "sg:classifiers":[
        {
            "category":"Professional",
            "subcategory":"Engineering",
            "type":"Services"
        }
    ],
    "sg:phone":"+32 14 86 78 44",
    "sg:postcode":"2440",
    "sg:province":"Antwerpen",
    "sg:tags":[
        "civil",
        "offices-"
    ],
    "wof:name":"De Krock Herman Bvba",
    "wof:placetype":"venue"
},
  "geometry": {"coordinates":[4.9825677872,51.1509857178],"type":"Point"}
}