{
  "type": "Feature",
  "properties": {
    "addr:full":"Chauss\u00c9e De Louvain 41 Eghezee Namur 5310",
    "addr:housenumber":"41",
    "addr:postcode":"5310",
    "addr:street":"Chausse\u0301E De Louvain;Namur",
    "iso:country":"BE",
    "sg:address":"Chauss\u00c9e De Louvain 41",
    "sg:city":"Eghezee",
    "sg:orig_category":"Advocaten and juridische adviseurs",
    "sg:phone":"+32 81 81 22 98",
    "sg:postcode":"5310",
    "sg:province":"Namur",
    "wof:name":"J.m. Defays",
    "wof:placetype":"venue"
},
  "geometry": {"coordinates":[4.9092059135,50.5945091248],"type":"Point"}
}