{
  "type": "Feature",
  "properties": {
    "addr:full":"Rue Des Vennes 119 Li\u00e8ge 1 (li\u00e8ge 2) Li\u00e8ge 4020",
    "addr:housenumber":"119;1;2",
    "addr:postcode":"4020",
    "addr:street":"Rue Des Vennes",
    "iso:country":"BE",
    "sg:address":"Rue Des Vennes 119",
    "sg:city":"Li\u00e8ge 1 (li\u00e8ge 2)",
    "sg:classifiers":[
        {
            "category":"Health Services",
            "subcategory":"Health Practitioner",
            "type":"Services"
        }
    ],
    "sg:phone":"+32 496 42 40 64",
    "sg:postcode":"4020",
    "sg:province":"Li\u00e8ge",
    "sg:tags":[
        "physiotherapist"
    ],
    "wof:name":"Leonard Christophe",
    "wof:placetype":"venue"
},
  "geometry": {"coordinates":[5.5876507759,50.625202179],"type":"Point"}
}