{
  "type": "Feature",
  "properties": {
    "addr:full":"Bredabaan 1217 Brasschaat Antwerpen 2930",
    "addr:housenumber":"1217",
    "addr:postcode":"2930",
    "addr:street":"Bredabaan",
    "iso:country":"BE",
    "sg:address":"Bredabaan 1217",
    "sg:city":"Brasschaat",
    "sg:classifiers":[
        {
            "category":"Building & Trades",
            "subcategory":"Landscaping Services",
            "type":"Services"
        }
    ],
    "sg:phone":"+32 3 663 34 93",
    "sg:postcode":"2930",
    "sg:province":"Antwerpen",
    "sg:tags":[
        "nurseryman"
    ],
    "wof:name":"Fidiel Nv",
    "wof:placetype":"venue"
},
  "geometry": {"coordinates":[4.5248088837,51.3328781128],"type":"Point"}
}