{
  "type": "Feature",
  "properties": {
    "addr:full":"Moeskroenstraat 876 Menen West-Vlaanderen 8930",
    "addr:housenumber":"876",
    "addr:postcode":"8930",
    "addr:street":"Moeskroenstraat",
    "iso:country":"BE",
    "sg:address":"Moeskroenstraat 876",
    "sg:city":"Menen",
    "sg:orig_category":"Elektrische installaties voor woningen",
    "sg:phone":"+32 56 41 32 07",
    "sg:postcode":"8930",
    "sg:province":"West-Vlaanderen",
    "wof:name":"Saverwel",
    "wof:placetype":"venue"
},
  "geometry": {"coordinates":[3.1548678875,50.7887992859],"type":"Point"}
}