{
  "type": "Feature",
  "properties": {
    "addr:full":"Kerklaan 82 Machelen Vlaams-Brabant 1830",
    "addr:housenumber":"82",
    "addr:postcode":"1830",
    "addr:street":"Kerklaan",
    "iso:country":"BE",
    "sg:address":"Kerklaan 82",
    "sg:city":"Machelen",
    "sg:orig_category":"Entretien and r\u00e9parations de voitures",
    "sg:phone":"+32 2 253 85 50",
    "sg:postcode":"1830",
    "sg:province":"Vlaams-Brabant",
    "wof:name":"Garage Trading",
    "wof:placetype":"venue"
},
  "geometry": {"coordinates":[4.4273371696,50.9135704041],"type":"Point"}
}