{
  "type": "Feature",
  "properties": {
    "iso:country":"BE",
    "sg:address":"Rue Pr\u00c9s. John Kennedy 136",
    "sg:city":"Aiseau-presles",
    "sg:classifiers":[
        {
            "category":"Cafe",
            "type":"Food & Drink"
        }
    ],
    "sg:phone":"+32 71 77 21 22",
    "sg:postcode":"6250",
    "sg:province":"Hainaut",
    "sg:tags":[
        "caf\u00e9s"
    ],
    "wof:name":"Centre Culturel Panama",
    "wof:placetype":"venue"
},
  "geometry": {"coordinates":[4.5863847733,50.40990448],"type":"Point"}
}