{
  "type": "Feature",
  "properties": {
    "iso:country":"BE",
    "sg:address":"Rue Emile Vandervelde 87",
    "sg:city":"Ans",
    "sg:classifiers":[
        {
            "category":"Fast Food",
            "type":"Food & Drink"
        }
    ],
    "sg:phone":"+32 4 247 31 89",
    "sg:postcode":"4431",
    "sg:province":"Li\u00e8ge",
    "sg:tags":[
        "meeneem",
        "restaurant"
    ],
    "wof:name":"Pizza Granita",
    "wof:placetype":"venue"
},
  "geometry": {"coordinates":[5.5051088333,50.6588287354],"type":"Point"}
}