{
  "type": "Feature",
  "properties": {
    "iso:country":"BE",
    "sg:address":"Meuleveld 24",
    "sg:city":"Borsbeek",
    "sg:classifiers":[
        {
            "category":"Professional",
            "subcategory":"Accounting & Tax Preparation",
            "type":"Services"
        }
    ],
    "sg:phone":"+32 3 366 34 34",
    "sg:postcode":"2150",
    "sg:province":"Antwerpen",
    "sg:tags":[
        "accountant"
    ],
    "wof:name":"M. Wouters",
    "wof:placetype":"venue"
},
  "geometry": {"coordinates":[4.4986748695,51.1942596436],"type":"Point"}
}