{
  "type": "Feature",
  "properties": {
    "addr:full":"Rue De Mons 80 Frameries Hainaut 7080",
    "addr:housenumber":"80",
    "addr:postcode":"7080",
    "addr:street":"Rue De Mons",
    "iso:country":"BE",
    "sg:address":"Rue De Mons 80",
    "sg:city":"Frameries",
    "sg:classifiers":[
        {
            "category":"Health Services",
            "subcategory":"Health Practitioner",
            "type":"Services"
        }
    ],
    "sg:phone":"+32 65 51 00 71",
    "sg:postcode":"7080",
    "sg:province":"Hainaut",
    "sg:tags":[
        "physiotherapist"
    ],
    "wof:name":"Lienard Beno\u00eet",
    "wof:placetype":"venue"
},
  "geometry": {"coordinates":[3.9035539627,50.4194412231],"type":"Point"}
}