{
  "type": "Feature",
  "properties": {
    "addr:full":"Vlamingstraat 11 Roeselare West-Vlaanderen 8800",
    "addr:housenumber":"11",
    "addr:postcode":"8800",
    "addr:street":"Vlamingstraat",
    "iso:country":"BE",
    "sg:address":"Vlamingstraat 11",
    "sg:city":"Roeselare",
    "sg:classifiers":[
        {
            "category":"Professional",
            "subcategory":"Lawyer & Legal Services",
            "type":"Services"
        }
    ],
    "sg:phone":"+32 51 20 71 61",
    "sg:postcode":"8800",
    "sg:province":"West-Vlaanderen",
    "wof:name":"Duyck A",
    "wof:placetype":"venue"
},
  "geometry": {"coordinates":[3.1282598972,50.9477882385],"type":"Point"}
}