{
  "type": "Feature",
  "properties": {
    "iso:country":"BE",
    "sg:address":"Heerweg-noord 31",
    "sg:city":"Gent",
    "sg:orig_category":"Pharmaciens",
    "sg:phone":"+32 9 222 80 58",
    "sg:postcode":"9052",
    "sg:province":"Oost-Vlaanderen",
    "wof:name":"Hilde Haems",
    "wof:placetype":"venue"
},
  "geometry": {"coordinates":[3.7080140114,51.0574378967],"type":"Point"}
}