{
  "type": "Feature",
  "properties": {
    "iso:country":"BE",
    "sg:address":"Rogierlaan 377b2",
    "sg:city":"Schaarbeek/schaerbeek",
    "sg:orig_category":"Artiesten and kunstenaars",
    "sg:phone":"+32 2 735 85 29",
    "sg:postcode":"1030",
    "sg:province":"Bruxelles-Capitale",
    "wof:name":"H. Dethier",
    "wof:placetype":"venue"
},
  "geometry": {"coordinates":[4.3941488266,50.8555679321],"type":"Point"}
}