{
  "type": "Feature",
  "properties": {
    "addr:full":"Dorpsstraat 51ba Sint-genesius-rode/rhode-saint-gen\u00c8se Vlaams-Brabant 1640",
    "addr:housenumber":"51ba",
    "addr:postcode":"1640",
    "addr:street":"Dorpsstraat",
    "iso:country":"BE",
    "sg:address":"Dorpsstraat 51ba",
    "sg:city":"Sint-genesius-rode/rhode-saint-gen\u00c8se",
    "sg:orig_category":"Verplichte sociale verzekeringen",
    "sg:phone":"+32 2 381 22 41",
    "sg:postcode":"1640",
    "sg:province":"Vlaams-Brabant",
    "wof:name":"Liberale Mutualiteit",
    "wof:placetype":"venue"
},
  "geometry": {"coordinates":[4.3452339172,50.7458267212],"type":"Point"}
}