{
  "type": "Feature",
  "properties": {
    "addr:full":"Kerkstraat 2 Box 1 Hechtel-eksel (eksel) Limburg 3941",
    "addr:housenumber":"2;1",
    "addr:postcode":"3941",
    "addr:street":"Kerkstraat;Box",
    "iso:country":"BE",
    "sg:address":"Kerkstraat 2 Box 1",
    "sg:city":"Hechtel-eksel (eksel)",
    "sg:classifiers":[
        {
            "category":"Professional",
            "subcategory":"Testing Lab",
            "type":"Services"
        }
    ],
    "sg:phone":"+32 11 73 62 64",
    "sg:postcode":"3941",
    "sg:province":"Limburg",
    "sg:tags":[
        "chemist"
    ],
    "wof:name":"Sneyers Apotheek",
    "wof:placetype":"venue"
},
  "geometry": {"coordinates":[5.3951587677,51.1546020508],"type":"Point"}
}