{
  "type": "Feature",
  "properties": {
    "iso:country":"BE",
    "sg:address":"Gemeentestraat 43a",
    "sg:city":"Lubbeek (linden)",
    "sg:classifiers":[
        {
            "category":"Bakery",
            "type":"Food & Drink"
        }
    ],
    "sg:phone":"+32 16 62 00 06",
    "sg:postcode":"3210",
    "sg:province":"Vlaams-Brabant",
    "sg:tags":[
        "confectioner",
        "baker"
    ],
    "wof:name":"Lindebeke Patisserie",
    "wof:placetype":"venue"
},
  "geometry": {"coordinates":[4.7716469765,50.8942298889],"type":"Point"}
}