{
  "type": "Feature",
  "properties": {
    "iso:country":"BE",
    "sg:address":"Boulevard Sainctelette 63",
    "sg:city":"Mons",
    "sg:classifiers":[
        {
            "category":"Personal",
            "subcategory":"Beauty Salon",
            "type":"Services"
        }
    ],
    "sg:phone":"+32 65 79 22 26",
    "sg:postcode":"7000",
    "sg:province":"Hainaut",
    "wof:name":"Institut Nancy Alvarez",
    "wof:placetype":"venue"
},
  "geometry": {"coordinates":[3.9430999756,50.4475860596],"type":"Point"}
}