{
  "type": "Feature",
  "properties": {
    "addr:full":"Grand Place 17 Momignies Hainaut 6590",
    "addr:housenumber":"17",
    "addr:postcode":"6590",
    "addr:street":"Grand Place;Hainaut",
    "iso:country":"BE",
    "sg:address":"Grand Place 17",
    "sg:city":"Momignies",
    "sg:classifiers":[
        {
            "category":"Bars & Pubs",
            "type":"Food & Drink"
        }
    ],
    "sg:phone":"+32 60 51 10 15",
    "sg:postcode":"6590",
    "sg:province":"Hainaut",
    "wof:name":"St Hilaire",
    "wof:placetype":"venue"
},
  "geometry": {"coordinates":[4.1655030251,50.0292816162],"type":"Point"}
}