{
  "type": "Feature",
  "properties": {
    "iso:country":"BE",
    "sg:address":"Tervuursestw 641",
    "sg:city":"Elewijt",
    "sg:classifiers":[
        {
            "category":"Building & Trades",
            "subcategory":"Construction",
            "type":"Services"
        }
    ],
    "sg:phone":"+32 15 61 36 16",
    "sg:postcode":"1982",
    "sg:province":"Vlaams-Brabant",
    "sg:tags":[
        "stucco",
        "contractor"
    ],
    "wof:name":"De Weerdt Wim",
    "wof:placetype":"venue"
},
  "geometry": {"coordinates":[4.4980278015,50.9583282471],"type":"Point"}
}