{
  "type": "Feature",
  "properties": {
    "iso:country":"BE",
    "sg:address":"Driehoekstraat 86",
    "sg:city":"Brakel",
    "sg:classifiers":[
        {
            "category":"Cafe",
            "type":"Food & Drink"
        }
    ],
    "sg:phone":"+32 55 42 70 20",
    "sg:postcode":"9660",
    "sg:province":"Oost-Vlaanderen",
    "sg:tags":[
        "caf\u00e9s"
    ],
    "wof:name":"C. De Clercq & Co",
    "wof:placetype":"venue"
},
  "geometry": {"coordinates":[3.7666649818,50.8072547913],"type":"Point"}
}