{
  "type": "Feature",
  "properties": {
    "addr:full":"Rue De La Station 24 Ans Li\u00e8ge 4430",
    "addr:housenumber":"24",
    "addr:postcode":"4430",
    "addr:street":"Rue De La Station",
    "iso:country":"BE",
    "sg:address":"Rue De La Station 24",
    "sg:city":"Ans",
    "sg:classifiers":[
        {
            "category":"Cinema",
            "subcategory":"Movie Rental",
            "type":"Entertainment"
        }
    ],
    "sg:phone":"+32 4 239 10 01",
    "sg:postcode":"4430",
    "sg:province":"Li\u00e8ge",
    "sg:tags":[
        "de",
        "cassette",
        "location",
        "vid\u00e9o",
        "audio"
    ],
    "wof:name":"Video Magic",
    "wof:placetype":"venue"
},
  "geometry": {"coordinates":[5.5107398033,50.6632423401],"type":"Point"}
}