{
  "type": "Feature",
  "properties": {
    "addr:full":"Slachthuisstraat 70 Gent Oost-Vlaanderen 9000",
    "addr:housenumber":"70",
    "addr:postcode":"9000",
    "addr:street":"Slachthuisstraat;Oost-Vlaanderen",
    "iso:country":"BE",
    "sg:address":"Slachthuisstraat 70",
    "sg:city":"Gent",
    "sg:classifiers":[
        {
            "category":"Personal",
            "subcategory":"Beauty Salon",
            "type":"Services"
        }
    ],
    "sg:phone":"+32 9 223 88 09",
    "sg:postcode":"9000",
    "sg:province":"Oost-Vlaanderen",
    "sg:tags":[
        "de",
        "coiffure"
    ],
    "wof:name":"Coiffure Elle & Lui",
    "wof:placetype":"venue"
},
  "geometry": {"coordinates":[3.7381188869,51.0527763367],"type":"Point"}
}