{
  "type": "Feature",
  "properties": {
    "addr:full":"Dries 21 Sint-niklaas Oost-Vlaanderen 9112",
    "addr:housenumber":"21",
    "addr:postcode":"9112",
    "addr:street":"Dries",
    "iso:country":"BE",
    "sg:address":"Dries 21",
    "sg:city":"Sint-niklaas",
    "sg:orig_category":"Entretien and r\u00e9parations de machines de bureau and ordinateurs. Location de cassettes vid\u00e9o and aud",
    "sg:phone":"+32 3 772 40 87",
    "sg:postcode":"9112",
    "sg:province":"Oost-Vlaanderen",
    "wof:name":"Dumpy\u00b4s Video & Pc Center",
    "wof:placetype":"venue"
},
  "geometry": {"coordinates":[4.0429940224,51.1564483643],"type":"Point"}
}