{
  "type": "Feature",
  "properties": {
    "addr:full":"Brokelaerestraat 17 Ronse/renaix Oost-Vlaanderen 9600",
    "addr:housenumber":"17",
    "addr:postcode":"9600",
    "addr:street":"Brokelaerestraat",
    "iso:country":"BE",
    "sg:address":"Brokelaerestraat 17",
    "sg:city":"Ronse/renaix",
    "sg:orig_category":"Installatie van metalen schrijnwerk",
    "sg:phone":"+32 55 21 90 57",
    "sg:postcode":"9600",
    "sg:province":"Oost-Vlaanderen",
    "wof:name":"D. Hecq/dominique Hecq",
    "wof:placetype":"venue"
},
  "geometry": {"coordinates":[3.637444973,50.7228240967],"type":"Point"}
}