{
  "type": "Feature",
  "properties": {
    "iso:country":"BE",
    "sg:address":"Overrepenstraat 40",
    "sg:city":"Tongeren",
    "sg:orig_category":"Boekhouders",
    "sg:phone":"+32 12 26 31 22",
    "sg:postcode":"3700",
    "sg:province":"Limburg",
    "wof:name":"Johan Roeffaers",
    "wof:placetype":"venue"
},
  "geometry": {"coordinates":[5.4636240005,50.7807197571],"type":"Point"}
}