{
  "type": "Feature",
  "properties": {
    "addr:full":"Oude R. Pelgrims De Bigardlaan 30 Dilbeek (groot - Bijgaarden) Vlaams-Brabant 1702",
    "addr:housenumber":"30;1702",
    "addr:street":"Oude R. Pelgrims De Bigardlaan;Groot Bijgaarden Vlaams-Brabant",
    "iso:country":"BE",
    "sg:address":"Oude R. Pelgrims De Bigardlaan 30",
    "sg:city":"Dilbeek (groot - Bijgaarden)",
    "sg:classifiers":[
        {
            "category":"Shopping",
            "subcategory":"Florist",
            "type":"Retail Goods"
        }
    ],
    "sg:phone":"+32 2 466 84 99",
    "sg:postcode":"1702",
    "sg:province":"Vlaams-Brabant",
    "wof:name":"Bloemencenter Van Roy Bvba",
    "wof:placetype":"venue"
},
  "geometry": {"coordinates":[4.2628970146,50.8712081909],"type":"Point"}
}