{
  "type": "Feature",
  "properties": {
    "iso:country":"BE",
    "sg:address":"Brugsesteenweg 93",
    "sg:city":"Oudenburg",
    "sg:classifiers":[
        {
            "category":"Building & Trades",
            "subcategory":"Plumbing",
            "type":"Services"
        }
    ],
    "sg:phone":"+32 59 26 85 75",
    "sg:postcode":"8460",
    "sg:province":"West-Vlaanderen",
    "sg:tags":[
        "diver",
        "commerce",
        "gr",
        "pour",
        "equipement"
    ],
    "wof:name":"Roger Demeulemeester",
    "wof:placetype":"venue"
},
  "geometry": {"coordinates":[3.0023450851,51.1840553284],"type":"Point"}
}