{
  "type": "Feature",
  "properties": {
    "addr:full":"Basiliekstraat 108 Halle Vlaams-Brabant 1500",
    "addr:housenumber":"108",
    "addr:postcode":"1500",
    "addr:street":"Basiliekstraat",
    "iso:country":"BE",
    "sg:address":"Basiliekstraat 108",
    "sg:city":"Halle",
    "sg:classifiers":[
        {
            "category":"Shopping",
            "subcategory":"Optician",
            "type":"Retail Goods"
        }
    ],
    "sg:phone":"+32 2 356 76 21",
    "sg:postcode":"1500",
    "sg:province":"Vlaams-Brabant",
    "sg:tags":[
        "-"
    ],
    "wof:name":"Ruth-de Baer Optiek",
    "wof:placetype":"venue"
},
  "geometry": {"coordinates":[4.2363448143,50.7332763672],"type":"Point"}
}