{
  "type": "Feature",
  "properties": {
    "addr:full":"Merksemsebaan 290 Wijnegem Antwerpen 2110",
    "addr:housenumber":"290",
    "addr:postcode":"2110",
    "addr:street":"Merksemsebaan",
    "iso:country":"BE",
    "sg:address":"Merksemsebaan 290",
    "sg:city":"Wijnegem",
    "sg:classifiers":[
        {
            "category":"Wholesale",
            "subcategory":"Machinery & Supplies",
            "type":"Manufacturing & Wholesale Goods"
        }
    ],
    "sg:phone":"+32 3 326 24 00",
    "sg:postcode":"2110",
    "sg:province":"Antwerpen",
    "sg:tags":[
        "food",
        "processing",
        "-",
        "machine",
        "equipment",
        "engineering",
        "mechanical"
    ],
    "wof:name":"Euromat-air Nv",
    "wof:placetype":"venue"
},
  "geometry": {"coordinates":[4.4924502373,51.2357292175],"type":"Point"}
}