{
  "type": "Feature",
  "properties": {
    "addr:full":"Kouterveldstraat 4 Machelen 1931",
    "addr:housenumber":"4",
    "addr:postcode":"1931",
    "addr:street":"Kouterveldstraat",
    "iso:country":"BE",
    "sg:address":"Kouterveldstraat 4",
    "sg:city":"Machelen",
    "sg:orig_category":"Syst\u00e8mes de t\u00e9l\u00e9communications",
    "sg:phone":"+32 2 725 75 34",
    "sg:postcode":"1931",
    "wof:name":"Fax*star",
    "wof:placetype":"venue"
},
  "geometry": {"coordinates":[4.4544901848,50.906539917],"type":"Point"}
}