{
  "type": "Feature",
  "properties": {
    "iso:country":"BE",
    "sg:address":"Slabbaardstraat-noord 69",
    "sg:city":"Izegem",
    "sg:orig_category":"Bouwmaterialen Gh Woningbouw",
    "sg:phone":"+32 51 31 66 89",
    "sg:postcode":"8870",
    "sg:province":"West-Vlaanderen",
    "wof:name":"W.s.b.",
    "wof:placetype":"venue"
},
  "geometry": {"coordinates":[3.2125720978,50.9113845825],"type":"Point"}
}