{
  "type": "Feature",
  "properties": {
    "addr:full":"Dr\u00e8ve Du Moulin 46a Waterloo Brabant Wallon 1410",
    "addr:housenumber":"46a",
    "addr:postcode":"1410",
    "addr:street":"Dre\u0300Ve Du Moulin",
    "iso:country":"BE",
    "sg:address":"Dr\u00e8ve Du Moulin 46a",
    "sg:city":"Waterloo",
    "sg:classifiers":[
        {
            "category":"Banks & Credit Unions",
            "subcategory":"Investment Brokerage",
            "type":"Services"
        }
    ],
    "sg:phone":"+32 2 354 12 12",
    "sg:postcode":"1410",
    "sg:province":"Brabant Wallon",
    "sg:tags":[
        "auditor"
    ],
    "wof:name":"Bastogne J",
    "wof:placetype":"venue"
},
  "geometry": {"coordinates":[4.3917078972,50.7184867859],"type":"Point"}
}