{
  "type": "Feature",
  "properties": {
    "iso:country":"BE",
    "sg:address":"Leuvensesteenweg 247",
    "sg:city":"Tielt-winge (sint-joris-winge)",
    "sg:classifiers":[
        {
            "category":"Building & Trades",
            "subcategory":"Landscaping Services",
            "type":"Services"
        }
    ],
    "sg:phone":"+32 16 25 22 18",
    "sg:postcode":"3390",
    "sg:province":"Vlaams-Brabant",
    "sg:tags":[
        "architect",
        "landscape"
    ],
    "wof:name":"Bernard Briers Bvba",
    "wof:placetype":"venue"
},
  "geometry": {"coordinates":[4.8991470337,50.9160423279],"type":"Point"}
}