{
  "type": "Feature",
  "properties": {
    "addr:full":"Rue Basse Rognac 1 Fl\u00e9malle Li\u00e8ge 4400",
    "addr:housenumber":"1",
    "addr:postcode":"4400",
    "addr:street":"Rue Basse Rognac",
    "iso:country":"BE",
    "sg:address":"Rue Basse Rognac 1",
    "sg:city":"Fl\u00e9malle",
    "sg:classifiers":[
        {
            "category":"Utilities",
            "subcategory":"Fuel Oil & Lpg",
            "type":"Services"
        }
    ],
    "sg:phone":"+32 4 233 72 27",
    "sg:postcode":"4400",
    "sg:province":"Li\u00e8ge",
    "wof:name":"Riga Daniel Sprl",
    "wof:placetype":"venue"
},
  "geometry": {"coordinates":[5.4769201279,50.6158981323],"type":"Point"}
}