{
  "type": "Feature",
  "properties": {
    "addr:full":"Schrovestraat Lebbeke (wieze) Oost-Vlaanderen 9280",
    "addr:postcode":"9280",
    "addr:street":"Schrovestraat;Wieze",
    "iso:country":"BE",
    "sg:address":"Schrovestraat",
    "sg:city":"Lebbeke (wieze)",
    "sg:classifiers":[
        {
            "category":"Fast Food",
            "type":"Food & Drink"
        }
    ],
    "sg:phone":"+32 53 78 13 13",
    "sg:postcode":"9280",
    "sg:province":"Oost-Vlaanderen",
    "sg:tags":[
        "fried",
        "stand",
        "potato"
    ],
    "wof:name":"Nadine",
    "wof:placetype":"venue"
},
  "geometry": {"coordinates":[4.0784502029,50.9759101868],"type":"Point"}
}