{
  "type": "Feature",
  "properties": {
    "addr:full":"Vorkstraat 6 Brugge West-Vlaanderen 8000",
    "addr:housenumber":"6",
    "addr:postcode":"8000",
    "addr:street":"Vorkstraat",
    "iso:country":"BE",
    "sg:address":"Vorkstraat 6",
    "sg:city":"Brugge",
    "sg:classifiers":[
        {
            "category":"Restaurant",
            "type":"Food & Drink"
        }
    ],
    "sg:phone":"+32 50 33 03 19",
    "sg:postcode":"8000",
    "sg:province":"West-Vlaanderen",
    "wof:name":"Dethasse",
    "wof:placetype":"venue"
},
  "geometry": {"coordinates":[3.2263569832,51.2473678589],"type":"Point"}
}