{
  "type": "Feature",
  "properties": {
    "addr:full":"John F. Kennedyplein 8 Zaventem Vlaams-Brabant 1930",
    "addr:housenumber":"8",
    "addr:postcode":"1930",
    "addr:street":"John F. Kennedyplein",
    "iso:country":"BE",
    "sg:address":"John F. Kennedyplein 8",
    "sg:city":"Zaventem",
    "sg:orig_category":"Muziekinstrumenten",
    "sg:phone":"+32 2 712 69 55",
    "sg:postcode":"1930",
    "sg:province":"Vlaams-Brabant",
    "wof:name":"Pianokliniek /clinique Pour Piano's",
    "wof:placetype":"venue"
},
  "geometry": {"coordinates":[4.4840202332,50.8754348755],"type":"Point"}
}