{
  "type": "Feature",
  "properties": {
    "addr:full":"Rue Andr\u00c9 Masquelier 33 Mons Hainaut 7000",
    "addr:housenumber":"33",
    "addr:postcode":"7000",
    "addr:street":"Rue Andre\u0301 Masquelier;Hainaut",
    "iso:country":"BE",
    "sg:address":"Rue Andr\u00c9 Masquelier 33",
    "sg:city":"Mons",
    "sg:orig_category":"M\u00e9decins and sp\u00e9cialistes",
    "sg:phone":"+32 65 35 12 61",
    "sg:postcode":"7000",
    "sg:province":"Hainaut",
    "wof:name":"F. Sasserath",
    "wof:placetype":"venue"
},
  "geometry": {"coordinates":[3.9427649975,50.450958252],"type":"Point"}
}