{
  "type": "Feature",
  "properties": {
    "iso:country":"BE",
    "sg:address":"Meershoven 27",
    "sg:city":"Bilzen",
    "sg:classifiers":[
        {
            "category":"Real Estate",
            "subcategory":"Architect",
            "type":"Services"
        }
    ],
    "sg:phone":"+32 89 41 19 15",
    "sg:postcode":"3740",
    "sg:province":"Limburg",
    "wof:name":"Deltour P",
    "wof:placetype":"venue"
},
  "geometry": {"coordinates":[5.5248498917,50.8739624023],"type":"Point"}
}