{
  "type": "Feature",
  "properties": {
    "addr:full":"Brugse-mettenstraat 5 Brugge West-Vlaanderen 8310",
    "addr:housenumber":"5",
    "addr:postcode":"8310",
    "addr:street":"Brugse-Mettenstraat",
    "iso:country":"BE",
    "sg:address":"Brugse-mettenstraat 5",
    "sg:city":"Brugge",
    "sg:orig_category":"Disquaires",
    "sg:phone":"+32 50 36 11 31",
    "sg:postcode":"8310",
    "sg:province":"West-Vlaanderen",
    "wof:name":"Huis Doctor Vinyl",
    "wof:placetype":"venue"
},
  "geometry": {"coordinates":[3.2434639931,51.2132148743],"type":"Point"}
}