{
  "type": "Feature",
  "properties": {
    "iso:country":"BE",
    "sg:address":"Sint-jobstraat 94",
    "sg:city":"Heusden-zolder (zolder)",
    "sg:classifiers":[
        {
            "category":"Health Services",
            "subcategory":"Dentist",
            "type":"Services"
        }
    ],
    "sg:phone":"+32 11 25 04 15",
    "sg:postcode":"3550",
    "sg:province":"Limburg",
    "wof:name":"Raemaekers C",
    "wof:placetype":"venue"
},
  "geometry": {"coordinates":[5.2754678726,50.986869812],"type":"Point"}
}