{
  "type": "Feature",
  "properties": {
    "addr:full":"Rue Fran\u00c7ois Vekemans 126 Brussel/bruxelles Bruxelles-Capitale 1120",
    "addr:housenumber":"126",
    "addr:postcode":"1120",
    "addr:street":"Rue Franc\u0327Ois Vekemans;/",
    "iso:country":"BE",
    "sg:address":"Rue Fran\u00c7ois Vekemans 126",
    "sg:city":"Brussel/bruxelles",
    "sg:classifiers":[
        {
            "category":"Food & Beverages",
            "subcategory":"Fruits & Vegetables",
            "type":"Retail Goods"
        }
    ],
    "sg:phone":"+32 2 268 25 77",
    "sg:postcode":"1120",
    "sg:province":"Bruxelles-Capitale",
    "sg:tags":[
        "l\u00e9gumes"
    ],
    "wof:name":"Huis De Meester",
    "wof:placetype":"venue"
},
  "geometry": {"coordinates":[4.3870139122,50.895160675],"type":"Point"}
}