{
  "type": "Feature",
  "properties": {
    "iso:country":"BE",
    "sg:address":"Petit Coo 4",
    "sg:city":"Stavelot",
    "sg:orig_category":"Offices du tourisme",
    "sg:phone":"+32 80 68 41 78",
    "sg:postcode":"4970",
    "sg:province":"Li\u00e8ge",
    "wof:name":"Syndicat D\u00b4initiative",
    "wof:placetype":"venue"
},
  "geometry": {"coordinates":[5.8766517639,50.3928642273],"type":"Point"}
}