{
  "type": "Feature",
  "properties": {
    "iso:country":"BE",
    "sg:address":"Blarenberglaan 21-7b",
    "sg:city":"Mechelen",
    "sg:classifiers":[
        {
            "category":"Professional",
            "subcategory":"Printing & Photocopies",
            "type":"Services"
        }
    ],
    "sg:phone":"+32 15 28 15 15",
    "sg:postcode":"2800",
    "sg:province":"Antwerpen",
    "sg:tags":[
        "-",
        "plan",
        "reproduction"
    ],
    "wof:name":"Archi-tech Bvba",
    "wof:placetype":"venue"
},
  "geometry": {"coordinates":[4.4509840012,51.0521621704],"type":"Point"}
}