{
  "type": "Feature",
  "properties": {
    "addr:full":"Muntstraat 11 Tongeren Limburg 3700",
    "addr:housenumber":"11",
    "addr:postcode":"3700",
    "addr:street":"Muntstraat",
    "iso:country":"BE",
    "sg:address":"Muntstraat 11",
    "sg:city":"Tongeren",
    "sg:orig_category":"Advocaten and juridische adviseurs",
    "sg:phone":"+32 12 23 97 41",
    "sg:postcode":"3700",
    "sg:province":"Limburg",
    "wof:name":"F. Duchesne",
    "wof:placetype":"venue"
},
  "geometry": {"coordinates":[5.4627780914,50.7784538269],"type":"Point"}
}