{
  "type": "Feature",
  "properties": {
    "iso:country":"BE",
    "sg:address":"Hoogstraat 4",
    "sg:city":"Bocholt",
    "sg:orig_category":"Sportclubs",
    "sg:phone":"+32 89 46 48 21",
    "sg:postcode":"3950",
    "sg:province":"Limburg",
    "wof:name":"H.c. Achilles Bocholt",
    "wof:placetype":"venue"
},
  "geometry": {"coordinates":[5.582570076,51.1776123047],"type":"Point"}
}