{
  "type": "Feature",
  "properties": {
    "iso:country":"BE",
    "sg:address":"Grote Markt 25bb",
    "sg:city":"Tongeren",
    "sg:orig_category":"Antiek",
    "sg:phone":"+32 12 39 50 37",
    "sg:postcode":"3700",
    "sg:province":"Limburg",
    "wof:name":"Sculptura",
    "wof:placetype":"venue"
},
  "geometry": {"coordinates":[5.4631290436,50.7804527283],"type":"Point"}
}