{
  "type": "Feature",
  "properties": {
    "iso:country":"BE",
    "sg:address":"Groot-bijgaardenstraat 500",
    "sg:city":"Berchem-sainte-agathe",
    "sg:classifiers":[
        {
            "category":"Exhibition Hall",
            "type":"Public Place"
        }
    ],
    "sg:phone":"+32 2 465 01 54",
    "sg:postcode":"1082",
    "sg:province":"Bruxelles-Capitale",
    "sg:tags":[
        "screen",
        "printing",
        "precision"
    ],
    "wof:name":"Otm S.a.",
    "wof:placetype":"venue"
},
  "geometry": {"coordinates":[4.2840738297,50.8655967712],"type":"Point"}
}