{
  "type": "Feature",
  "properties": {
    "iso:country":"BE",
    "sg:address":"Boekenborglei 48",
    "sg:city":"Schoten",
    "sg:orig_category":"Epiceries",
    "sg:phone":"+32 3 645 99 62",
    "sg:postcode":"2900",
    "sg:province":"Antwerpen",
    "wof:name":"Hugo Butaye",
    "wof:placetype":"venue"
},
  "geometry": {"coordinates":[4.459526062,51.2442855835],"type":"Point"}
}