{
  "type": "Feature",
  "properties": {
    "iso:country":"BE",
    "sg:address":"Rue Lion De L'ourthe 2",
    "sg:city":"Rendeux (beffe)",
    "sg:classifiers":[
        {
            "category":"Professional",
            "subcategory":"Lawyer & Legal Services",
            "type":"Services"
        }
    ],
    "sg:phone":"+32 84 47 73 98",
    "sg:postcode":"6987",
    "sg:province":"Luxembourg",
    "wof:name":"Vanwynsberghe Marie-els",
    "wof:placetype":"venue"
},
  "geometry": {"coordinates":[5.514939785,50.246257782],"type":"Point"}
}