{
  "type": "Feature",
  "properties": {
    "iso:country":"BE",
    "sg:address":"Chauss\u00c9e De Louvain 567",
    "sg:city":"Namur",
    "sg:orig_category":"Kapsalons",
    "sg:phone":"+32 81 21 01 17",
    "sg:postcode":"5020",
    "sg:province":"Namur",
    "wof:name":"Coiffure El\u00c9gance",
    "wof:placetype":"venue"
},
  "geometry": {"coordinates":[4.7952418327,50.4352035522],"type":"Point"}
}