{
  "type": "Feature",
  "properties": {
    "addr:full":"Rokerstraat 9a Wingene West-Vlaanderen 8750",
    "addr:housenumber":"9a",
    "addr:postcode":"8750",
    "addr:street":"Rokerstraat",
    "iso:country":"BE",
    "sg:address":"Rokerstraat 9a",
    "sg:city":"Wingene",
    "sg:classifiers":[
        {
            "category":"Shopping",
            "subcategory":"Party Supplies",
            "type":"Retail Goods"
        }
    ],
    "sg:phone":"+32 51 65 78 20",
    "sg:postcode":"8750",
    "sg:province":"West-Vlaanderen",
    "sg:tags":[
        "rental",
        "-"
    ],
    "wof:name":"Verhelst R",
    "wof:placetype":"venue"
},
  "geometry": {"coordinates":[3.2939789295,51.0526542664],"type":"Point"}
}