{
  "type": "Feature",
  "properties": {
    "addr:full":"Dadizeelsestraat 77 Moorslede West-Vlaanderen 8890",
    "addr:housenumber":"77",
    "addr:postcode":"8890",
    "addr:street":"Dadizeelsestraat",
    "iso:country":"BE",
    "sg:address":"Dadizeelsestraat 77",
    "sg:city":"Moorslede",
    "sg:orig_category":"Epiceries",
    "sg:phone":"+32 51 77 81 91",
    "sg:postcode":"8890",
    "sg:province":"West-Vlaanderen",
    "wof:name":"'t Winkelke",
    "wof:placetype":"venue"
},
  "geometry": {"coordinates":[3.0615069866,50.8873252869],"type":"Point"}
}