{
  "type": "Feature",
  "properties": {
    "addr:full":"Quinten Matsijslei 50 Antwerpen Antwerpen 2018",
    "addr:housenumber":"50",
    "addr:postcode":"2018",
    "iso:country":"BE",
    "sg:address":"Quinten Matsijslei 50",
    "sg:city":"Antwerpen",
    "sg:orig_category":"Openbare veiligheid",
    "sg:phone":"+32 3 206 80 11",
    "sg:postcode":"2018",
    "sg:province":"Antwerpen",
    "wof:name":"Federale Politie",
    "wof:placetype":"venue"
},
  "geometry": {"coordinates":[4.4178628922,51.2109642029],"type":"Point"}
}