{
  "type": "Feature",
  "properties": {
    "addr:full":"Nieuwe Gentweg 78 Brugge West-Vlaanderen 8000",
    "addr:housenumber":"78",
    "addr:postcode":"8000",
    "addr:street":"Nieuwe Gentweg",
    "iso:country":"BE",
    "sg:address":"Nieuwe Gentweg 78",
    "sg:city":"Brugge",
    "sg:classifiers":[
        {
            "category":"Travel",
            "subcategory":"Hotels & Motels",
            "type":"Entertainment"
        }
    ],
    "sg:phone":"+32 50 33 11 76",
    "sg:postcode":"8000",
    "sg:province":"West-Vlaanderen",
    "wof:name":"Montanus",
    "wof:placetype":"venue"
},
  "geometry": {"coordinates":[3.2276010513,51.2034759521],"type":"Point"}
}