{
  "type": "Feature",
  "properties": {
    "addr:full":"Avenue Jean-joseph Crocq 10 Bruxelles (jette) Bruxelles-Capitale 1090",
    "addr:housenumber":"10",
    "addr:postcode":"1090",
    "addr:street":"Avenue Jean-Joseph Crocq",
    "iso:country":"BE",
    "sg:address":"Avenue Jean-joseph Crocq 10",
    "sg:city":"Bruxelles (jette)",
    "sg:classifiers":[
        {
            "category":"Education",
            "subcategory":"School",
            "type":"Public Place"
        }
    ],
    "sg:phone":"+32 2 478 24 97",
    "sg:postcode":"1090",
    "sg:province":"Bruxelles-Capitale",
    "sg:tags":[
        "secondary"
    ],
    "wof:name":"Joie De Vivre Ens Sec Prof Special",
    "wof:placetype":"venue"
},
  "geometry": {"coordinates":[4.3272352219,50.8886642456],"type":"Point"}
}