{
  "type": "Feature",
  "properties": {
    "addr:full":"Rigaudrye 7 Ellezelles Hainaut 7890",
    "addr:housenumber":"7",
    "addr:postcode":"7890",
    "addr:street":"Rigaudrye",
    "iso:country":"BE",
    "sg:address":"Rigaudrye 7",
    "sg:city":"Ellezelles",
    "sg:classifiers":[
        {
            "category":"Communications",
            "subcategory":"Television Station",
            "type":"Services"
        }
    ],
    "sg:phone":"+32 68 54 25 17",
    "sg:postcode":"7890",
    "sg:province":"Hainaut",
    "sg:tags":[
        "report",
        "video"
    ],
    "wof:name":"A Kicks Vid\u00e9o Production",
    "wof:placetype":"venue"
},
  "geometry": {"coordinates":[3.6842899323,50.7469596863],"type":"Point"}
}