{
  "type": "Feature",
  "properties": {
    "addr:full":"Sprietstraat 6 Staden (westrozebeke) West-Vlaanderen 8840",
    "addr:housenumber":"6",
    "addr:postcode":"8840",
    "addr:street":"Sprietstraat",
    "iso:country":"BE",
    "sg:address":"Sprietstraat 6",
    "sg:city":"Staden (westrozebeke)",
    "sg:classifiers":[
        {
            "category":"Farming",
            "subcategory":"Livestock Farm",
            "type":"Manufacturing & Wholesale Goods"
        }
    ],
    "sg:phone":"+32 51 77 83 13",
    "sg:postcode":"8840",
    "sg:province":"West-Vlaanderen",
    "sg:tags":[
        "breeding"
    ],
    "wof:name":"Muvarpy Nv",
    "wof:placetype":"venue"
},
  "geometry": {"coordinates":[2.9868938923,50.9315299988],"type":"Point"}
}