{
  "type": "Feature",
  "properties": {
    "addr:full":"Merodecenter 35 Turnhout Antwerpen 2300",
    "addr:housenumber":"35",
    "addr:postcode":"2300",
    "addr:street":"Merodecenter",
    "iso:country":"BE",
    "sg:address":"Merodecenter 35",
    "sg:city":"Turnhout",
    "sg:orig_category":"HERSTELLING ELEKTRISCHE HUISHOUDAPPARATEN Huishoudapparaten, televisies and radio's Telecommunicatie",
    "sg:phone":"+32 14 43 75 18",
    "sg:postcode":"2300",
    "sg:province":"Antwerpen",
    "wof:name":"Eldi",
    "wof:placetype":"venue"
},
  "geometry": {"coordinates":[4.9398899078,51.3222694397],"type":"Point"}
}