{
  "type": "Feature",
  "properties": {
    "iso:country":"BE",
    "sg:address":"Avenue De Vis\u00c9 95",
    "sg:city":"Watermaal-bosvoorde/watermael-boitsfort",
    "sg:orig_category":"V\u00e9t\u00e9rinaires",
    "sg:phone":"+32 2 660 97 16",
    "sg:postcode":"1170",
    "sg:province":"Bruxelles-Capitale",
    "wof:name":"Anne Taton",
    "wof:placetype":"venue"
},
  "geometry": {"coordinates":[4.3939051628,50.8116645813],"type":"Point"}
}