{
  "type": "Feature",
  "properties": {
    "iso:country":"BE",
    "sg:address":"Chauss\u00e9e De Wavre 133",
    "sg:city":"Bruxelles (ixelles)",
    "sg:classifiers":[
        {
            "category":"Community Center",
            "type":"Public Place"
        }
    ],
    "sg:phone":"+32 2 511 20 32",
    "sg:postcode":"1050",
    "sg:province":"Bruxelles-Capitale",
    "sg:tags":[
        "medical"
    ],
    "wof:name":"Centre De M\u00e9decine Sp\u00e9cialis\u00e9e D'ixelles",
    "wof:placetype":"venue"
},
  "geometry": {"coordinates":[4.370267868,50.8354797363],"type":"Point"}
}