{
  "type": "Feature",
  "properties": {
    "addr:full":"Rue Cortil Stiennon 6 H\u00e9ron Li\u00e8ge 4217",
    "addr:housenumber":"6",
    "addr:postcode":"4217",
    "addr:street":"Rue Cortil Stiennon",
    "iso:country":"BE",
    "sg:address":"Rue Cortil Stiennon 6",
    "sg:city":"H\u00e9ron",
    "sg:classifiers":[
        {
            "category":"Professional",
            "subcategory":"Management & Consulting",
            "type":"Services"
        }
    ],
    "sg:phone":"+32 85 71 16 82",
    "sg:postcode":"4217",
    "sg:province":"Li\u00e8ge",
    "sg:tags":[
        "consultant",
        "agency",
        "advertising"
    ],
    "wof:name":"Cool Gray",
    "wof:placetype":"venue"
},
  "geometry": {"coordinates":[5.075717926,50.5361442566],"type":"Point"}
}