{
  "type": "Feature",
  "properties": {
    "addr:full":"Rue De S\u00e9lys 31 Li\u00e8ge 1 Li\u00e8ge 4000",
    "addr:housenumber":"31;1",
    "addr:postcode":"4000",
    "addr:street":"Rue De Se\u0301Lys",
    "iso:country":"BE",
    "sg:address":"Rue De S\u00e9lys 31",
    "sg:city":"Li\u00e8ge 1",
    "sg:classifiers":[
        {
            "category":"Social Services",
            "subcategory":"Child Care",
            "type":"Services"
        }
    ],
    "sg:phone":"+32 4 252 22 53",
    "sg:postcode":"4000",
    "sg:province":"Li\u00e8ge",
    "sg:tags":[
        "home"
    ],
    "wof:name":"Chanmurly",
    "wof:placetype":"venue"
},
  "geometry": {"coordinates":[5.5636239052,50.6301078796],"type":"Point"}
}