{
  "type": "Feature",
  "properties": {
    "addr:full":"Ginderbuiten 97 Mol Antwerpen 2400",
    "addr:housenumber":"97",
    "addr:postcode":"2400",
    "addr:street":"Ginderbuiten",
    "iso:country":"BE",
    "sg:address":"Ginderbuiten 97",
    "sg:city":"Mol",
    "sg:classifiers":[
        {
            "category":"Health Services",
            "subcategory":"Dentist",
            "type":"Services"
        }
    ],
    "sg:phone":"+32 14 31 26 61",
    "sg:postcode":"2400",
    "sg:province":"Antwerpen",
    "wof:name":"Machielsen C",
    "wof:placetype":"venue"
},
  "geometry": {"coordinates":[5.146900177,51.2030792236],"type":"Point"}
}