{
  "type": "Feature",
  "properties": {
    "addr:full":"Meierij 13 Merelbeke Oost-Vlaanderen 9820",
    "addr:housenumber":"13",
    "addr:postcode":"9820",
    "addr:street":"Meierij",
    "iso:country":"BE",
    "sg:address":"Meierij 13",
    "sg:city":"Merelbeke",
    "sg:orig_category":"Installation de menuiserie en bois and plastique. D\u00e9corateurs d'int\u00e9rieur. Organisation de salons, e",
    "sg:phone":"+32 9 362 80 33",
    "sg:postcode":"9820",
    "sg:province":"Oost-Vlaanderen",
    "wof:name":"Design Competence",
    "wof:placetype":"venue"
},
  "geometry": {"coordinates":[3.7251849174,50.9682388306],"type":"Point"}
}