{
  "type": "Feature",
  "properties": {
    "addr:full":"Europalaan 1 Beveren (beveren-waas) Oost-Vlaanderen 9120",
    "addr:housenumber":"1",
    "addr:postcode":"9120",
    "addr:street":"Europalaan;Oost-Vlaanderen",
    "iso:country":"BE",
    "sg:address":"Europalaan 1",
    "sg:city":"Beveren (beveren-waas)",
    "sg:classifiers":[
        {
            "category":"Education",
            "subcategory":"School",
            "type":"Public Place"
        }
    ],
    "sg:phone":"+32 3 750 19 00",
    "sg:postcode":"9120",
    "sg:province":"Oost-Vlaanderen",
    "sg:tags":[
        "secondary"
    ],
    "wof:name":"Gti Beveren",
    "wof:placetype":"venue"
},
  "geometry": {"coordinates":[4.2537741661,51.2192344666],"type":"Point"}
}