{
  "type": "Feature",
  "properties": {
    "addr:full":"Gullegemsesteenweg 139 Kortrijk West-Vlaanderen 8501",
    "addr:housenumber":"139",
    "addr:postcode":"8501",
    "addr:street":"Gullegemsesteenweg",
    "iso:country":"BE",
    "sg:address":"Gullegemsesteenweg 139",
    "sg:city":"Kortrijk",
    "sg:orig_category":"Schoonheidssalons",
    "sg:phone":"+32 56 35 92 21",
    "sg:postcode":"8501",
    "sg:province":"West-Vlaanderen",
    "wof:name":"Instituut Karin",
    "wof:placetype":"venue"
},
  "geometry": {"coordinates":[3.2141499519,50.8329086304],"type":"Point"}
}