{
  "type": "Feature",
  "properties": {
    "iso:country":"BE",
    "sg:address":"Rue Du Lait Beurr\u00c9 97",
    "sg:city":"La Louviere",
    "sg:orig_category":"R\u00e9parations d'appareils \u00e9lectrom\u00e9nagers. Electrom\u00e9nager, t\u00e9l\u00e9visions and radios",
    "sg:phone":"+32 64 21 60 25",
    "sg:postcode":"7110",
    "sg:province":"Hainaut",
    "wof:name":"Francis Moitie",
    "wof:placetype":"venue"
},
  "geometry": {"coordinates":[4.1679029465,50.4966087341],"type":"Point"}
}