{
  "type": "Feature",
  "properties": {
    "iso:country":"BE",
    "sg:address":"Blauwstraat 65",
    "sg:city":"Boom",
    "sg:orig_category":"Boucheries. Alimentation sp\u00e9cialis\u00e9e",
    "sg:phone":"+32 3 888 74 07",
    "sg:postcode":"2850",
    "sg:province":"Antwerpen",
    "wof:name":"De Smulpaap",
    "wof:placetype":"venue"
},
  "geometry": {"coordinates":[4.369284153,51.0868225098],"type":"Point"}
}