{
  "type": "Feature",
  "properties": {
    "iso:country":"BE",
    "sg:address":"Oude Baan 234",
    "sg:city":"Essen",
    "sg:orig_category":"Binnenhuisarchitecten",
    "sg:phone":"+32 3 667 42 56",
    "sg:postcode":"2910",
    "sg:province":"Antwerpen",
    "wof:name":"B. Mennes",
    "wof:placetype":"venue"
},
  "geometry": {"coordinates":[4.4636049271,51.4427986145],"type":"Point"}
}