{
  "type": "Feature",
  "properties": {
    "addr:full":"Akkerstraat 21bc Nijlen Antwerpen 2560",
    "addr:housenumber":"21bc",
    "addr:postcode":"2560",
    "addr:street":"Akkerstraat",
    "iso:country":"BE",
    "sg:address":"Akkerstraat 21bc",
    "sg:city":"Nijlen",
    "sg:orig_category":"D\u00e9taillants en pi\u00e8ces and accessoires de voitures",
    "sg:phone":"+32 3 411 10 85",
    "sg:postcode":"2560",
    "sg:province":"Antwerpen",
    "wof:name":"D.k. Technics",
    "wof:placetype":"venue"
},
  "geometry": {"coordinates":[4.6753602028,51.1552581787],"type":"Point"}
}