{
  "type": "Feature",
  "properties": {
    "iso:country":"BE",
    "sg:address":"Grootloonstraat 25",
    "sg:city":"Borgloon",
    "sg:classifiers":[
        {
            "category":"Communications",
            "subcategory":"Film & Video Production",
            "type":"Services"
        }
    ],
    "sg:phone":"+32 12 74 40 62",
    "sg:postcode":"3840",
    "sg:province":"Limburg",
    "sg:tags":[
        "realisation",
        "-"
    ],
    "wof:name":"P.p. Videoproductions",
    "wof:placetype":"venue"
},
  "geometry": {"coordinates":[5.3579192162,50.7967681885],"type":"Point"}
}