{
  "type": "Feature",
  "properties": {
    "addr:full":"Chauss\u00e9e De Tirlemont 100 Gembloux Namur 5030",
    "addr:housenumber":"100",
    "addr:postcode":"5030",
    "addr:street":"Chausse\u0301E De Tirlemont;Namur",
    "iso:country":"BE",
    "sg:address":"Chauss\u00e9e De Tirlemont 100",
    "sg:city":"Gembloux",
    "sg:orig_category":"Beverage Tubing",
    "sg:phone":"+32 81 62 62 11",
    "sg:postcode":"5030",
    "sg:province":"Namur",
    "wof:name":"Saint-gobain Performance Plastics S.a.",
    "wof:placetype":"venue"
},
  "geometry": {"coordinates":[4.7008938789,50.574672699],"type":"Point"}
}