{
  "type": "Feature",
  "properties": {
    "iso:country":"BE",
    "sg:address":"Rue De Hamoir 5",
    "sg:city":"Ouffet",
    "sg:classifiers":[
        {
            "category":"Professional",
            "subcategory":"Lawyer & Legal Services",
            "type":"Services"
        }
    ],
    "sg:phone":"+32 86 36 62 06",
    "sg:postcode":"4590",
    "sg:province":"Li\u00e8ge",
    "sg:tags":[
        "notary"
    ],
    "wof:name":"Lecomte B",
    "wof:placetype":"venue"
},
  "geometry": {"coordinates":[5.4750227928,50.4378318787],"type":"Point"}
}