{
  "type": "Feature",
  "properties": {
    "addr:full":"Kasteelstraat 49 Asse Vlaams-Brabant 1730",
    "addr:housenumber":"49",
    "addr:postcode":"1730",
    "addr:street":"Kasteelstraat",
    "iso:country":"BE",
    "sg:address":"Kasteelstraat 49",
    "sg:city":"Asse",
    "sg:orig_category":"Enseignement maternel and primaire",
    "sg:phone":"+32 2 452 50 73",
    "sg:postcode":"1730",
    "sg:province":"Vlaams-Brabant",
    "wof:name":"Gemeentel. Lagere School",
    "wof:placetype":"venue"
},
  "geometry": {"coordinates":[4.2253780365,50.9322967529],"type":"Point"}
}