{
  "type": "Feature",
  "properties": {
    "addr:full":"Rue Des D\u00c9port\u00c9s 34 Le Roeulx Hainaut 7070",
    "addr:housenumber":"34",
    "addr:postcode":"7070",
    "addr:street":"Rue Des De\u0301Porte\u0301S",
    "iso:country":"BE",
    "sg:address":"Rue Des D\u00c9port\u00c9s 34",
    "sg:city":"Le Roeulx",
    "sg:orig_category":"Enseignement maternel and primaire",
    "sg:phone":"+32 67 48 51 56",
    "sg:postcode":"7070",
    "sg:province":"Hainaut",
    "wof:name":"Ecole Fondamentale Libre",
    "wof:placetype":"venue"
},
  "geometry": {"coordinates":[4.1492857933,50.5304718018],"type":"Point"}
}