{
  "type": "Feature",
  "properties": {
    "addr:full":"H\u00e9bronval 26 Vielsalm (bihain) Luxembourg 6690",
    "addr:housenumber":"26",
    "addr:postcode":"6690",
    "addr:street":"He\u0301Bronval",
    "iso:country":"BE",
    "sg:address":"H\u00e9bronval 26",
    "sg:city":"Vielsalm (bihain)",
    "sg:classifiers":[
        {
            "category":"Shopping",
            "subcategory":"Bridal",
            "type":"Retail Goods"
        }
    ],
    "sg:phone":"+32 80 41 87 41",
    "sg:postcode":"6690",
    "sg:province":"Luxembourg",
    "sg:tags":[
        "list",
        "-",
        "present",
        "wedding"
    ],
    "wof:name":"Monfort Meubles Sa",
    "wof:placetype":"venue"
},
  "geometry": {"coordinates":[5.8119587898,50.2535476685],"type":"Point"}
}