{
  "type": "Feature",
  "properties": {
    "iso:country":"BE",
    "sg:address":"Knotwilgkant 13",
    "sg:city":"Dilbeek",
    "sg:orig_category":"Voedingsspeciaalzaken",
    "sg:phone":"+32 2 466 04 67",
    "sg:postcode":"1700",
    "sg:province":"Vlaams-Brabant",
    "wof:name":"'t Wilgje",
    "wof:placetype":"venue"
},
  "geometry": {"coordinates":[4.2477211952,50.8596687317],"type":"Point"}
}