{
  "type": "Feature",
  "properties": {
    "iso:country":"BE",
    "sg:address":"Rue Eug\u00c8ne-delvaux 43",
    "sg:city":"Gembloux",
    "sg:orig_category":"Traitements param\u00e9dicaux",
    "sg:phone":"+32 81 61 46 18",
    "sg:postcode":"5030",
    "sg:province":"Namur",
    "wof:name":"De Maesschalck",
    "wof:placetype":"venue"
},
  "geometry": {"coordinates":[4.6743822098,50.5919303894],"type":"Point"}
}