{
  "type": "Feature",
  "properties": {
    "addr:full":"Botermarkt 22 Hasselt Limburg 3500",
    "addr:housenumber":"22",
    "addr:postcode":"3500",
    "addr:street":"Botermarkt",
    "iso:country":"BE",
    "sg:address":"Botermarkt 22",
    "sg:city":"Hasselt",
    "sg:classifiers":[
        {
            "category":"Restaurant",
            "type":"Food & Drink"
        }
    ],
    "sg:phone":"+32 11 22 63 75",
    "sg:postcode":"3500",
    "sg:province":"Limburg",
    "wof:name":"La Sardagna Da Angelo",
    "wof:placetype":"venue"
},
  "geometry": {"coordinates":[5.3387670517,50.9306335449],"type":"Point"}
}