{
  "type": "Feature",
  "properties": {
    "addr:full":"Serpentstraat 8 Oudenaarde Oost-Vlaanderen 9700",
    "addr:housenumber":"8",
    "addr:postcode":"9700",
    "addr:street":"Serpentstraat",
    "iso:country":"BE",
    "sg:address":"Serpentstraat 8",
    "sg:city":"Oudenaarde",
    "sg:classifiers":[
        {
            "category":"Personal",
            "subcategory":"Beauty Salon",
            "type":"Services"
        }
    ],
    "sg:phone":"+32 55 31 12 70",
    "sg:postcode":"9700",
    "sg:province":"Oost-Vlaanderen",
    "wof:name":"Thalomar Bvba",
    "wof:placetype":"venue"
},
  "geometry": {"coordinates":[3.6081850529,50.8716087341],"type":"Point"}
}