{
  "type": "Feature",
  "properties": {
    "iso:country":"BE",
    "sg:address":"Rue Vaudr\u00e9e 206",
    "sg:city":"Li\u00e8ge 1 (angleur)",
    "sg:orig_category":"Ice-cream parlours",
    "sg:phone":"+32 4 365 31 67",
    "sg:postcode":"4031",
    "sg:province":"Li\u00e8ge",
    "wof:name":"Pesce Maison",
    "wof:placetype":"venue"
},
  "geometry": {"coordinates":[5.5841670036,50.6128463745],"type":"Point"}
}