{
  "type": "Feature",
  "properties": {
    "iso:country":"BE",
    "sg:address":"Bettenhoek 17",
    "sg:city":"Geraardsbergen (nieuwenhove)",
    "sg:classifiers":[
        {
            "category":"Professional",
            "subcategory":"Management & Consulting",
            "type":"Services"
        }
    ],
    "sg:phone":"+32 54 30 05 95",
    "sg:postcode":"9506",
    "sg:province":"Oost-Vlaanderen",
    "sg:tags":[
        "consultant"
    ],
    "wof:name":"Van Acker W",
    "wof:placetype":"venue"
},
  "geometry": {"coordinates":[3.9812970161,50.7812805176],"type":"Point"}
}