{
  "type": "Feature",
  "properties": {
    "addr:full":"3090 Overijse Vlaams-Brabant 3090",
    "addr:postcode":"3090;3090",
    "iso:country":"BE",
    "sg:address":"3090",
    "sg:city":"Overijse",
    "sg:orig_category":"Articles de jardin",
    "sg:phone":"+32 2 687 58 76",
    "sg:postcode":"3090",
    "sg:province":"Vlaams-Brabant",
    "wof:name":"Plant Shop",
    "wof:placetype":"venue"
},
  "geometry": {"coordinates":[4.537779808,50.7731971741],"type":"Point"}
}