{
  "type": "Feature",
  "properties": {
    "addr:full":"Kasteeldreef 1 Zedelgem West-Vlaanderen 8210",
    "addr:housenumber":"1",
    "addr:postcode":"8210",
    "addr:street":"Kasteeldreef",
    "iso:country":"BE",
    "sg:address":"Kasteeldreef 1",
    "sg:city":"Zedelgem",
    "sg:orig_category":"Decoratieve kunst and kunstbenodigdheden",
    "sg:phone":"+32 50 38 25 06",
    "sg:postcode":"8210",
    "sg:province":"West-Vlaanderen",
    "wof:name":"Jozef Hoste",
    "wof:placetype":"venue"
},
  "geometry": {"coordinates":[3.1725850105,51.1557998657],"type":"Point"}
}