{
  "type": "Feature",
  "properties": {
    "addr:full":"Schomstraat 4 Antwerpen Antwerpen 2600",
    "addr:housenumber":"4",
    "addr:postcode":"2600",
    "addr:street":"Schomstraat",
    "iso:country":"BE",
    "sg:address":"Schomstraat 4",
    "sg:city":"Antwerpen",
    "sg:orig_category":"Taxis. Taxis services sp\u00e9ciaux. Transports terrestres de voyageurs",
    "sg:phone":"+32 3 239 01 36",
    "sg:postcode":"2600",
    "sg:province":"Antwerpen",
    "wof:name":"Driving Services",
    "wof:placetype":"venue"
},
  "geometry": {"coordinates":[4.4174151421,51.1974411011],"type":"Point"}
}