{
  "type": "Feature",
  "properties": {
    "iso:country":"BE",
    "sg:address":"Geraardsbergse Steenweg 271",
    "sg:city":"Oosterzele",
    "sg:classifiers":[
        {
            "category":"Building & Trades",
            "subcategory":"Landscaping Services",
            "type":"Services"
        }
    ],
    "sg:phone":"+32 9 360 92 67",
    "sg:postcode":"9860",
    "sg:province":"Oost-Vlaanderen",
    "sg:tags":[
        "nurseryman"
    ],
    "wof:name":"De Backer J",
    "wof:placetype":"venue"
},
  "geometry": {"coordinates":[3.814800024,50.9339904785],"type":"Point"}
}