{
  "type": "Feature",
  "properties": {
    "addr:full":"Kloosterstraat 46 Zele Oost-Vlaanderen 9240",
    "addr:housenumber":"46",
    "addr:postcode":"9240",
    "addr:street":"Kloosterstraat",
    "iso:country":"BE",
    "sg:address":"Kloosterstraat 46",
    "sg:city":"Zele",
    "sg:classifiers":[
        {
            "category":"Professional",
            "subcategory":"Lawyer & Legal Services",
            "type":"Services"
        }
    ],
    "sg:phone":"+32 52 44 42 30",
    "sg:postcode":"9240",
    "sg:province":"Oost-Vlaanderen",
    "wof:name":"De Maerschalck Philip",
    "wof:placetype":"venue"
},
  "geometry": {"coordinates":[4.04246521,51.0688591003],"type":"Point"}
}