{
  "type": "Feature",
  "properties": {
    "iso:country":"BE",
    "sg:address":"Bevrijdingslaan 103",
    "sg:city":"Gent",
    "sg:orig_category":"Maroquinerie and articles de voyage",
    "sg:phone":"+32 9 226 23 96",
    "sg:postcode":"9000",
    "sg:province":"Oost-Vlaanderen",
    "wof:name":"Huis Eli",
    "wof:placetype":"venue"
},
  "geometry": {"coordinates":[3.695884943,51.0636558533],"type":"Point"}
}