{
  "type": "Feature",
  "properties": {
    "iso:country":"BE",
    "sg:address":"Place D'amougies 2",
    "sg:city":"Mont-de-l'enclus",
    "sg:classifiers":[
        {
            "category":"Health Services",
            "subcategory":"Nursing And Care Facility",
            "type":"Services"
        }
    ],
    "sg:phone":"+32 69 76 95 52",
    "sg:postcode":"7750",
    "sg:province":"Hainaut",
    "sg:tags":[
        "public"
    ],
    "wof:name":"C.p.a.s.",
    "wof:placetype":"venue"
},
  "geometry": {"coordinates":[3.5024199486,50.745349884],"type":"Point"}
}