{
  "type": "Feature",
  "properties": {
    "addr:full":"Rue De La D\u00c9portation 148 Tubize Brabant Wallon 1480",
    "addr:housenumber":"148",
    "addr:postcode":"1480",
    "addr:street":"Rue De La De\u0301Portation;Wallon",
    "iso:country":"BE",
    "sg:address":"Rue De La D\u00c9portation 148",
    "sg:city":"Tubize",
    "sg:orig_category":"Dakwerken Loodgieterij, verwarming and sanitaire installaties",
    "sg:phone":"+32 2 355 74 06",
    "sg:postcode":"1480",
    "sg:province":"Brabant Wallon",
    "wof:name":"Marcelis Fredy",
    "wof:placetype":"venue"
},
  "geometry": {"coordinates":[4.212100029,50.6907424927],"type":"Point"}
}