{
  "type": "Feature",
  "properties": {
    "addr:full":"Hoogstraat 16 Gistel West-Vlaanderen 8470",
    "addr:housenumber":"16",
    "addr:postcode":"8470",
    "addr:street":"Hoogstraat",
    "iso:country":"BE",
    "sg:address":"Hoogstraat 16",
    "sg:city":"Gistel",
    "sg:orig_category":"Banken and kredietinstellingen",
    "sg:phone":"+32 59 27 73 17",
    "sg:postcode":"8470",
    "sg:province":"West-Vlaanderen",
    "wof:name":"Dexia",
    "wof:placetype":"venue"
},
  "geometry": {"coordinates":[2.9656660557,51.1564979553],"type":"Point"}
}