{
  "type": "Feature",
  "properties": {
    "iso:country":"BE",
    "sg:address":"Rue Du Cardinal 46",
    "sg:city":"Bruxelles",
    "sg:classifiers":[
        {
            "category":"Professional",
            "subcategory":"Lawyer & Legal Services",
            "type":"Services"
        }
    ],
    "sg:phone":"+32 2 235 07 50",
    "sg:postcode":"1000",
    "sg:province":"Bruxelles-Capitale",
    "sg:tags":[
        "notary"
    ],
    "wof:name":"Behets Wydemans Y",
    "wof:placetype":"venue"
},
  "geometry": {"coordinates":[4.3792147636,50.8483123779],"type":"Point"}
}