{
  "type": "Feature",
  "properties": {
    "addr:full":"Muntelbeekstraat 42 Hasselt (sint-lambrechts-herk) Limburg 3500",
    "addr:housenumber":"42",
    "addr:postcode":"3500",
    "addr:street":"Muntelbeekstraat",
    "iso:country":"BE",
    "sg:address":"Muntelbeekstraat 42",
    "sg:city":"Hasselt (sint-lambrechts-herk)",
    "sg:classifiers":[
        {
            "category":"Manufacturing",
            "subcategory":"Electronics",
            "type":"Manufacturing & Wholesale Goods"
        }
    ],
    "sg:phone":"+32 11 27 99 00",
    "sg:postcode":"3500",
    "sg:province":"Limburg",
    "sg:tags":[
        "telecommunication",
        "system"
    ],
    "wof:name":"Tadicom Telecommunication Nv",
    "wof:placetype":"venue"
},
  "geometry": {"coordinates":[5.3423748016,50.8886985779],"type":"Point"}
}