{
  "type": "Feature",
  "properties": {
    "iso:country":"BE",
    "sg:address":"Lievevrouwdreef 23",
    "sg:city":"Maldegem",
    "sg:orig_category":"Goederenvervoer over de weg Verhuisdiensten",
    "sg:phone":"+32 50 71 58 28",
    "sg:postcode":"9990",
    "sg:province":"Oost-Vlaanderen",
    "wof:name":"D.a. Trans",
    "wof:placetype":"venue"
},
  "geometry": {"coordinates":[3.4380099773,51.1790885925],"type":"Point"}
}