{
  "type": "Feature",
  "properties": {
    "addr:full":"Peter Benoitstraat 1 Blankenberge West-Vlaanderen 8370",
    "addr:housenumber":"1",
    "addr:postcode":"8370",
    "addr:street":"Peter Benoitstraat",
    "iso:country":"BE",
    "sg:address":"Peter Benoitstraat 1",
    "sg:city":"Blankenberge",
    "sg:classifiers":[
        {
            "category":"Travel",
            "subcategory":"Hotels & Motels",
            "type":"Entertainment"
        }
    ],
    "sg:phone":"+32 50 42 41 20",
    "sg:postcode":"8370",
    "sg:province":"West-Vlaanderen",
    "wof:name":"Tropicana",
    "wof:placetype":"venue"
},
  "geometry": {"coordinates":[3.1254279613,51.3142204285],"type":"Point"}
}