{
  "type": "Feature",
  "properties": {
    "addr:full":"Reipelveld 22 Kontich Antwerpen 2550",
    "addr:housenumber":"22",
    "addr:postcode":"2550",
    "addr:street":"Reipelveld",
    "iso:country":"BE",
    "sg:address":"Reipelveld 22",
    "sg:city":"Kontich",
    "sg:classifiers":[
        {
            "category":"Arena",
            "subcategory":"Sports Club",
            "type":"Entertainment"
        }
    ],
    "sg:phone":"+32 3 457 27 23",
    "sg:postcode":"2550",
    "sg:province":"Antwerpen",
    "sg:tags":[
        "de"
    ],
    "wof:name":"B.s.c. Kon. Borgerhout",
    "wof:placetype":"venue"
},
  "geometry": {"coordinates":[4.4550709724,51.1139717102],"type":"Point"}
}