{
  "type": "Feature",
  "properties": {
    "addr:full":"Hoogstraat 45 Avelgem West-Vlaanderen 8580",
    "addr:housenumber":"45",
    "addr:postcode":"8580",
    "addr:street":"Hoogstraat",
    "iso:country":"BE",
    "sg:address":"Hoogstraat 45",
    "sg:city":"Avelgem",
    "sg:classifiers":[
        {
            "category":"Insurance",
            "subcategory":"Insurance Agent",
            "type":"Services"
        }
    ],
    "sg:phone":"+32 56 64 40 29",
    "sg:postcode":"8580",
    "sg:province":"West-Vlaanderen",
    "sg:tags":[
        "verzekeringsmakelaars",
        "expert"
    ],
    "wof:name":"Frans Vanrenterghem",
    "wof:placetype":"venue"
},
  "geometry": {"coordinates":[3.4390621185,50.7763557434],"type":"Point"}
}