{
  "type": "Feature",
  "properties": {
    "iso:country":"BE",
    "sg:address":"Rue Bois Bourdon 38",
    "sg:city":"Frameries",
    "sg:classifiers":[
        {
            "category":"Shopping",
            "subcategory":"Crafts & Fabrics",
            "type":"Retail Goods"
        }
    ],
    "sg:phone":"+32 65 51 51 28",
    "sg:postcode":"7080",
    "sg:province":"Hainaut",
    "sg:tags":[
        "plant",
        "flower",
        "artificial"
    ],
    "wof:name":"Neusy Horticulture",
    "wof:placetype":"venue"
},
  "geometry": {"coordinates":[3.9085791111,50.4022903442],"type":"Point"}
}