{
  "type": "Feature",
  "properties": {
    "iso:country":"BE",
    "sg:address":"Heivelden 32",
    "sg:city":"Sint-katelijne-waver",
    "sg:orig_category":"Bloemen and planten Gh Groententeelt",
    "sg:phone":"+32 15 55 18 84",
    "sg:postcode":"2861",
    "sg:province":"Antwerpen",
    "wof:name":"Rudolf Van Rompaye",
    "wof:placetype":"venue"
},
  "geometry": {"coordinates":[4.5492987633,51.0461883545],"type":"Point"}
}