{
  "type": "Feature",
  "properties": {
    "addr:full":"Bld Jean-th\u00c9odore Radoux 49 Li\u00c8ge Li\u00e8ge 4000",
    "addr:housenumber":"49",
    "addr:postcode":"4000",
    "iso:country":"BE",
    "sg:address":"Bld Jean-th\u00c9odore Radoux 49",
    "sg:city":"Li\u00c8ge",
    "sg:orig_category":"M\u00e9decins and sp\u00e9cialistes",
    "sg:phone":"+32 4 224 32 62",
    "sg:postcode":"4000",
    "sg:province":"Li\u00e8ge",
    "wof:name":"Nadine Cielniaszek",
    "wof:placetype":"venue"
},
  "geometry": {"coordinates":[5.5548629761,50.6528930664],"type":"Point"}
}