{
  "type": "Feature",
  "properties": {
    "addr:full":"Maastrichtersteenweg 184 Tongeren Limburg 3700",
    "addr:housenumber":"184",
    "addr:postcode":"3700",
    "addr:street":"Maastrichtersteenweg",
    "iso:country":"BE",
    "sg:address":"Maastrichtersteenweg 184",
    "sg:city":"Tongeren",
    "sg:classifiers":[
        {
            "category":"Insurance",
            "subcategory":"Life Insurance",
            "type":"Services"
        }
    ],
    "sg:phone":"+32 12 23 22 68",
    "sg:postcode":"3700",
    "sg:province":"Limburg",
    "sg:tags":[
        "assurance"
    ],
    "wof:name":"Bureau Philips",
    "wof:placetype":"venue"
},
  "geometry": {"coordinates":[5.470510006,50.7831993103],"type":"Point"}
}