{
  "type": "Feature",
  "properties": {
    "iso:country":"BE",
    "sg:address":"Smoutpot 14",
    "sg:city":"Zwijndrecht",
    "sg:orig_category":"Fruitteelt",
    "sg:phone":"+32 3 252 83 49",
    "sg:postcode":"2070",
    "sg:province":"Antwerpen",
    "wof:name":"Adhemar Ryckaert",
    "wof:placetype":"venue"
},
  "geometry": {"coordinates":[4.3026299477,51.2263717651],"type":"Point"}
}