{
  "type": "Feature",
  "properties": {
    "addr:full":"Ijskelderstraat 38 Sint-gillis/saint-gilles Bruxelles-Capitale 1060",
    "addr:housenumber":"38",
    "addr:postcode":"1060",
    "addr:street":"Ijskelderstraat",
    "iso:country":"BE",
    "sg:address":"Ijskelderstraat 38",
    "sg:city":"Sint-gillis/saint-gilles",
    "sg:orig_category":"Diepvriesproducten Gh",
    "sg:phone":"+32 2 534 40 03",
    "sg:postcode":"1060",
    "sg:province":"Bruxelles-Capitale",
    "wof:name":"La Glaci\u00c8re",
    "wof:placetype":"venue"
},
  "geometry": {"coordinates":[4.3507537842,50.8219871521],"type":"Point"}
}