{
  "type": "Feature",
  "properties": {
    "addr:full":"Stationsstraat 99 Menen West-Vlaanderen 8930",
    "addr:housenumber":"99",
    "addr:postcode":"8930",
    "addr:street":"Stationsstraat",
    "iso:country":"BE",
    "sg:address":"Stationsstraat 99",
    "sg:city":"Menen",
    "sg:classifiers":[
        {
            "category":"Health Services",
            "subcategory":"Doctor",
            "type":"Services"
        }
    ],
    "sg:phone":"+32 56 51 81 40",
    "sg:postcode":"8930",
    "sg:province":"West-Vlaanderen",
    "sg:tags":[
        "medicinephysicians",
        "surgeon"
    ],
    "wof:name":"Lamon K",
    "wof:placetype":"venue"
},
  "geometry": {"coordinates":[3.1151030064,50.7991256714],"type":"Point"}
}