{
  "type": "Feature",
  "properties": {
    "addr:full":"Rue Marcel Gillis 21 Mons (hyon) Hainaut 7022",
    "addr:housenumber":"21",
    "addr:postcode":"7022",
    "addr:street":"Rue Marcel Gillis",
    "iso:country":"BE",
    "sg:address":"Rue Marcel Gillis 21",
    "sg:city":"Mons (hyon)",
    "sg:classifiers":[
        {
            "category":"Health Services",
            "subcategory":"Doctor",
            "type":"Services"
        }
    ],
    "sg:phone":"+32 65 34 00 07",
    "sg:postcode":"7022",
    "sg:province":"Hainaut",
    "sg:tags":[
        "medicinephysicians",
        "surgeon"
    ],
    "wof:name":"Borghgraef J",
    "wof:placetype":"venue"
},
  "geometry": {"coordinates":[4.0181078911,50.4045410156],"type":"Point"}
}