{
  "type": "Feature",
  "properties": {
    "addr:full":"Steenweg Op Mol 116 Oud-turnhout Antwerpen 2360",
    "addr:housenumber":"116",
    "addr:postcode":"2360",
    "addr:street":"Steenweg Op Mol",
    "iso:country":"BE",
    "sg:address":"Steenweg Op Mol 116",
    "sg:city":"Oud-turnhout",
    "sg:orig_category":"Industri\u00eble and commerci\u00eble bouw Woningbouw",
    "sg:phone":"+32 14 45 31 57",
    "sg:postcode":"2360",
    "sg:province":"Antwerpen",
    "wof:name":"D.v.g.",
    "wof:placetype":"venue"
},
  "geometry": {"coordinates":[4.9894099236,51.3142852783],"type":"Point"}
}