{
  "type": "Feature",
  "properties": {
    "iso:country":"BE",
    "sg:address":"Heirweg 53",
    "sg:city":"Zulte",
    "sg:orig_category":"Dakwerken Installatie van houten of kunststof schrijnwerk MEUBELONTWERP AND -INSTALLATIE",
    "sg:phone":"+32 9 388 80 87",
    "sg:postcode":"9870",
    "sg:province":"Oost-Vlaanderen",
    "wof:name":"Schelstraete Luc",
    "wof:placetype":"venue"
},
  "geometry": {"coordinates":[3.4653398991,50.9409217834],"type":"Point"}
}