{
  "type": "Feature",
  "properties": {
    "addr:full":"Square De L'aviation 6-8 Brussels Bruxelles-Capitale 1070",
    "addr:housenumber":"6-8",
    "addr:postcode":"1070",
    "addr:street":"Square De L'Aviation",
    "iso:country":"BE",
    "sg:address":"Square De L'aviation 6-8",
    "sg:city":"Brussels",
    "sg:classifiers":[
        {
            "category":"Travel",
            "subcategory":"Travel Agent",
            "type":"Entertainment"
        }
    ],
    "sg:phone":"+32 65 36 04 64",
    "sg:postcode":"1070",
    "sg:province":"Bruxelles-Capitale",
    "wof:name":"Tourist Board For The Province Of Hainaut",
    "wof:placetype":"venue"
},
  "geometry": {"coordinates":[3.9497220516,50.4533958435],"type":"Point"}
}