{
  "type": "Feature",
  "properties": {
    "addr:full":"Vierselbaan 17 Zandhoven Antwerpen 2240",
    "addr:housenumber":"17",
    "addr:postcode":"2240",
    "addr:street":"Vierselbaan",
    "iso:country":"BE",
    "sg:address":"Vierselbaan 17",
    "sg:city":"Zandhoven",
    "sg:orig_category":"Jeux and jouets. V\u00eatements pour b\u00e9b\u00e9s and enfants",
    "sg:phone":"+32 3 464 00 15",
    "sg:postcode":"2240",
    "sg:province":"Antwerpen",
    "wof:name":"Huis Hupsakee",
    "wof:placetype":"venue"
},
  "geometry": {"coordinates":[4.6575508118,51.2115974426],"type":"Point"}
}