{
  "type": "Feature",
  "properties": {
    "addr:full":"Rue De Landelies 94 Montigny-le-tilleul Hainaut 6110",
    "addr:housenumber":"94",
    "addr:postcode":"6110",
    "addr:street":"Rue De Landelies",
    "iso:country":"BE",
    "sg:address":"Rue De Landelies 94",
    "sg:city":"Montigny-le-tilleul",
    "sg:orig_category":"Sportclubs",
    "sg:phone":"+32 71 51 27 11",
    "sg:postcode":"6110",
    "sg:province":"Hainaut",
    "wof:name":"V.c. Coll\u00c8ge",
    "wof:placetype":"venue"
},
  "geometry": {"coordinates":[4.3758702278,50.3763084412],"type":"Point"}
}