{
  "type": "Feature",
  "properties": {
    "iso:country":"BE",
    "sg:address":"Kleine Waregemsestraat 43",
    "sg:city":"Harelbeke",
    "sg:orig_category":"Charpentes and couvertures",
    "sg:phone":"+32 56 71 14 02",
    "sg:postcode":"8530",
    "sg:province":"West-Vlaanderen",
    "wof:name":"Vanbo",
    "wof:placetype":"venue"
},
  "geometry": {"coordinates":[3.3289198875,50.8592834473],"type":"Point"}
}