{
  "type": "Feature",
  "properties": {
    "iso:country":"BE",
    "sg:address":"Rue Des Groseilliers 34",
    "sg:city":"Dour",
    "sg:orig_category":"Artsen and specialisten",
    "sg:phone":"+32 65 65 11 12",
    "sg:postcode":"7370",
    "sg:province":"Hainaut",
    "wof:name":"Eric Pepin",
    "wof:placetype":"venue"
},
  "geometry": {"coordinates":[3.781717062,50.396812439],"type":"Point"}
}