{
  "type": "Feature",
  "properties": {
    "addr:full":"Chauss\u00c9e De Wavre 1130 Oudergem/auderghem Bruxelles-Capitale 1160",
    "addr:postcode":"1130;1160",
    "addr:street":"Chausse\u0301E De Wavre",
    "iso:country":"BE",
    "sg:address":"Chauss\u00c9e De Wavre 1130",
    "sg:city":"Oudergem/auderghem",
    "sg:orig_category":"V\u00e9hicules automobiles",
    "sg:phone":"+32 475 27 25 44",
    "sg:postcode":"1160",
    "sg:province":"Bruxelles-Capitale",
    "wof:name":"Jean-luc Halon",
    "wof:placetype":"venue"
},
  "geometry": {"coordinates":[4.4036140442,50.8224868774],"type":"Point"}
}