{
  "type": "Feature",
  "properties": {
    "iso:country":"BE",
    "sg:address":"Geo Verbancklaan 1",
    "sg:city":"Gent (sint-denijs-westrem - Afsnee)",
    "sg:classifiers":[
        {
            "category":"Real Estate",
            "subcategory":"Developer",
            "type":"Services"
        }
    ],
    "sg:phone":"+32 9 221 32 56",
    "sg:postcode":"9051",
    "sg:province":"Oost-Vlaanderen",
    "sg:tags":[
        "project"
    ],
    "wof:name":"Albat",
    "wof:placetype":"venue"
},
  "geometry": {"coordinates":[3.67100811,51.0154571533],"type":"Point"}
}