{
  "type": "Feature",
  "properties": {
    "addr:full":"Lilsedijk 3 Beerse Antwerpen 2340",
    "addr:housenumber":"3",
    "addr:postcode":"2340",
    "addr:street":"Lilsedijk",
    "iso:country":"BE",
    "sg:address":"Lilsedijk 3",
    "sg:city":"Beerse",
    "sg:classifiers":[
        {
            "category":"Retail",
            "subcategory":"Auto Repair",
            "type":"Services"
        }
    ],
    "sg:phone":"+32 14 61 53 97",
    "sg:postcode":"2340",
    "sg:province":"Antwerpen",
    "sg:tags":[
        "garage"
    ],
    "wof:name":"Crets G",
    "wof:placetype":"venue"
},
  "geometry": {"coordinates":[4.8409690857,51.3059120178],"type":"Point"}
}