{
  "type": "Feature",
  "properties": {
    "addr:full":"Pontstraat 87 Deerlijk West-Vlaanderen 8540",
    "addr:housenumber":"87",
    "addr:postcode":"8540",
    "addr:street":"Pontstraat",
    "iso:country":"BE",
    "sg:address":"Pontstraat 87",
    "sg:city":"Deerlijk",
    "sg:orig_category":"Autokeuringen",
    "sg:phone":"+32 56 77 55 52",
    "sg:postcode":"8540",
    "sg:province":"West-Vlaanderen",
    "wof:name":"Autokeuring",
    "wof:placetype":"venue"
},
  "geometry": {"coordinates":[3.3600161076,50.8496284485],"type":"Point"}
}