{
  "type": "Feature",
  "properties": {
    "addr:full":"Place Du Centenaire 15 Estinnes (fauroeulx) Hainaut 7120",
    "addr:housenumber":"15",
    "addr:postcode":"7120",
    "addr:street":"Place Du Centenaire",
    "iso:country":"BE",
    "sg:address":"Place Du Centenaire 15",
    "sg:city":"Estinnes (fauroeulx)",
    "sg:classifiers":[
        {
            "category":"Health Services",
            "subcategory":"Doctor",
            "type":"Services"
        }
    ],
    "sg:phone":"+32 64 77 27 15",
    "sg:postcode":"7120",
    "sg:province":"Hainaut",
    "sg:tags":[
        "medicinephysicians",
        "surgeon"
    ],
    "wof:name":"Demoustier C\u00e9cile",
    "wof:placetype":"venue"
},
  "geometry": {"coordinates":[4.1103339195,50.3704299927],"type":"Point"}
}