{
  "type": "Feature",
  "properties": {
    "addr:full":"Egide Belsacklaan 55 Beersel Vlaams-Brabant 1654",
    "addr:housenumber":"55",
    "addr:postcode":"1654",
    "addr:street":"Belsacklaan",
    "iso:country":"BE",
    "sg:address":"Egide Belsacklaan 55",
    "sg:city":"Beersel",
    "sg:orig_category":"Dranken Gh",
    "sg:phone":"+32 2 356 12 66",
    "sg:postcode":"1654",
    "sg:province":"Vlaams-Brabant",
    "wof:name":"Henri De Pauw",
    "wof:placetype":"venue"
},
  "geometry": {"coordinates":[4.2716031075,50.745929718],"type":"Point"}
}