{
  "type": "Feature",
  "properties": {
    "addr:full":"Rue De Marche 58 Nandrin Li\u00e8ge 4550",
    "addr:housenumber":"58",
    "addr:postcode":"4550",
    "addr:street":"Rue De Marche",
    "iso:country":"BE",
    "sg:address":"Rue De Marche 58",
    "sg:city":"Nandrin",
    "sg:classifiers":[
        {
            "category":"Autos & Motor Vehicles",
            "subcategory":"Auto Supplies",
            "type":"Retail Goods"
        }
    ],
    "sg:phone":"+32 85 51 18 23",
    "sg:postcode":"4550",
    "sg:province":"Li\u00e8ge",
    "sg:tags":[
        "access",
        "automobile",
        "part",
        "-"
    ],
    "wof:name":"Rorive Et Halleux Sprl",
    "wof:placetype":"venue"
},
  "geometry": {"coordinates":[5.441010952,50.5418548584],"type":"Point"}
}