{
  "type": "Feature",
  "properties": {
    "iso:country":"BE",
    "sg:address":"Rue Henri Deleers 22",
    "sg:city":"Bruxelles (anderlecht)",
    "sg:orig_category":"Non-Classified Establishments",
    "sg:phone":"+32 2 521 82 34",
    "sg:postcode":"1070",
    "sg:province":"Bruxelles-Capitale",
    "wof:name":"Ateliers Neirynck-stevens Sa",
    "wof:placetype":"venue"
},
  "geometry": {"coordinates":[4.3003878593,50.8256263733],"type":"Point"}
}