{
  "type": "Feature",
  "properties": {
    "iso:country":"BE",
    "sg:address":"Rozebaan 4",
    "sg:city":"Moorsel",
    "sg:orig_category":"Traitements param\u00e9dicaux",
    "sg:phone":"+32 53 78 28 37",
    "sg:postcode":"9310",
    "sg:province":"Oost-Vlaanderen",
    "wof:name":"Van Onacker Gunther",
    "wof:placetype":"venue"
},
  "geometry": {"coordinates":[4.5366868973,50.8444519043],"type":"Point"}
}