{
  "type": "Feature",
  "properties": {
    "addr:full":"Planterijstraat 20 Ruiselede West-Vlaanderen 8755",
    "addr:housenumber":"20",
    "addr:postcode":"8755",
    "addr:street":"Planterijstraat",
    "iso:country":"BE",
    "sg:address":"Planterijstraat 20",
    "sg:city":"Ruiselede",
    "sg:orig_category":"Non-Classified Establishments",
    "sg:phone":"+32 51 65 79 34",
    "sg:postcode":"8755",
    "sg:province":"West-Vlaanderen",
    "wof:name":"Fd Confect",
    "wof:placetype":"venue"
},
  "geometry": {"coordinates":[3.3655750751,51.0826530457],"type":"Point"}
}