{
  "type": "Feature",
  "properties": {
    "addr:full":"Driepaalweg 5 Maaseik (opoeteren) Limburg 3680",
    "addr:housenumber":"5",
    "addr:postcode":"3680",
    "addr:street":"Driepaalweg",
    "iso:country":"BE",
    "sg:address":"Driepaalweg 5",
    "sg:city":"Maaseik (opoeteren)",
    "sg:classifiers":[
        {
            "category":"Home & Garden",
            "subcategory":"Household Appliances",
            "type":"Retail Goods"
        }
    ],
    "sg:phone":"+32 89 86 39 54",
    "sg:postcode":"3680",
    "sg:province":"Limburg",
    "sg:tags":[
        "repair",
        "mainten",
        "-",
        "electric"
    ],
    "wof:name":"Flux/vanhelden",
    "wof:placetype":"venue"
},
  "geometry": {"coordinates":[5.791285038,51.0954208374],"type":"Point"}
}