{
  "type": "Feature",
  "properties": {
    "iso:country":"BE",
    "sg:address":"Rue Fernand Neuray 59",
    "sg:city":"Elsene/ixelles",
    "sg:orig_category":"Messageries",
    "sg:phone":"+32 2 344 14 13",
    "sg:postcode":"1050",
    "sg:province":"Bruxelles-Capitale",
    "wof:name":"Sprint Services",
    "wof:placetype":"venue"
},
  "geometry": {"coordinates":[4.3554382324,50.8195877075],"type":"Point"}
}