{
  "type": "Feature",
  "properties": {
    "iso:country":"BE",
    "sg:address":"Rue Carnot 1 Box 1",
    "sg:city":"Quaregnon",
    "sg:classifiers":[
        {
            "category":"Utilities",
            "subcategory":"Telephone",
            "type":"Services"
        }
    ],
    "sg:phone":"+32 65 75 51 54",
    "sg:postcode":"7390",
    "sg:province":"Hainaut",
    "sg:tags":[
        "-",
        "internet"
    ],
    "wof:name":"Net Club",
    "wof:placetype":"venue"
},
  "geometry": {"coordinates":[3.8664400578,50.4428443909],"type":"Point"}
}