{
  "type": "Feature",
  "properties": {
    "iso:country":"BE",
    "sg:address":"Pitantiestraat 115-2",
    "sg:city":"Waregem (desselgem)",
    "sg:classifiers":[
        {
            "category":"Professional",
            "subcategory":"Employment Agencies",
            "type":"Services"
        }
    ],
    "sg:phone":"+32 800 92 921",
    "sg:postcode":"8792",
    "sg:province":"West-Vlaanderen",
    "sg:tags":[
        "market",
        "research"
    ],
    "wof:name":"Business Phone Bvba",
    "wof:placetype":"venue"
},
  "geometry": {"coordinates":[3.3726201057,50.896812439],"type":"Point"}
}