{
  "type": "Feature",
  "properties": {
    "iso:country":"BE",
    "sg:address":"Chauss\u00c9e De Dinant 29",
    "sg:city":"Profondeville",
    "sg:orig_category":"Juwelen and horloges",
    "sg:phone":"+32 81 41 13 47",
    "sg:postcode":"5170",
    "sg:province":"Namur",
    "wof:name":"L'emeraude",
    "wof:placetype":"venue"
},
  "geometry": {"coordinates":[4.872469902,50.3772163391],"type":"Point"}
}