{
  "type": "Feature",
  "properties": {
    "addr:full":"Gansbeekstraat 12a Bilzen Limburg 3740",
    "addr:housenumber":"12a",
    "addr:postcode":"3740",
    "addr:street":"Gansbeekstraat",
    "iso:country":"BE",
    "sg:address":"Gansbeekstraat 12a",
    "sg:city":"Bilzen",
    "sg:orig_category":"Loodgieterij, verwarming and sanitaire installaties",
    "sg:phone":"+32 89 41 21 76",
    "sg:postcode":"3740",
    "sg:province":"Limburg",
    "wof:name":"Gielkens Marc",
    "wof:placetype":"venue"
},
  "geometry": {"coordinates":[5.5144248009,50.8748054504],"type":"Point"}
}