{
  "type": "Feature",
  "properties": {
    "iso:country":"BE",
    "sg:address":"Brusselsesteenweg 419",
    "sg:city":"Merchtem",
    "sg:classifiers":[
        {
            "category":"Manufacturing",
            "subcategory":"Tools & Machinery",
            "type":"Manufacturing & Wholesale Goods"
        }
    ],
    "sg:phone":"+32 2 460 43 01",
    "sg:postcode":"1785",
    "sg:province":"Vlaams-Brabant",
    "sg:tags":[
        "pneumatic"
    ],
    "wof:name":"Jobe Werktuigen",
    "wof:placetype":"venue"
},
  "geometry": {"coordinates":[4.280561924,50.9215011597],"type":"Point"}
}