{
  "type": "Feature",
  "properties": {
    "addr:full":"Chauss\u00e9e De Charleroi 59 Gembloux-sur-orneau (gembloux) Namur 5030",
    "addr:housenumber":"59",
    "addr:postcode":"5030",
    "addr:street":"Chausse\u0301E De Charleroi;Namur",
    "iso:country":"BE",
    "sg:address":"Chauss\u00e9e De Charleroi 59",
    "sg:city":"Gembloux-sur-orneau (gembloux)",
    "sg:classifiers":[
        {
            "category":"Building & Trades",
            "subcategory":"Pest Control",
            "type":"Services"
        }
    ],
    "sg:phone":"+32 81 61 04 31",
    "sg:postcode":"5030",
    "sg:province":"Namur",
    "sg:tags":[
        "painting",
        "contractor"
    ],
    "wof:name":"C.l. Decor",
    "wof:placetype":"venue"
},
  "geometry": {"coordinates":[4.6895489693,50.5658111572],"type":"Point"}
}