{
  "type": "Feature",
  "properties": {
    "addr:full":"Jozef Wautersstraat 48 Gent Oost-Vlaanderen 9050",
    "addr:housenumber":"48",
    "addr:postcode":"9050",
    "addr:street":"Jozef Wautersstraat;Oost-Vlaanderen",
    "iso:country":"BE",
    "sg:address":"Jozef Wautersstraat 48",
    "sg:city":"Gent",
    "sg:classifiers":[
        {
            "category":"Food & Beverages",
            "subcategory":"Fruits & Vegetables",
            "type":"Retail Goods"
        }
    ],
    "sg:phone":"+32 9 231 34 34",
    "sg:postcode":"9050",
    "sg:province":"Oost-Vlaanderen",
    "sg:tags":[
        "l\u00e9gumes"
    ],
    "wof:name":"In De Primeurhalle",
    "wof:placetype":"venue"
},
  "geometry": {"coordinates":[3.7579369545,51.0390014648],"type":"Point"}
}