{
  "type": "Feature",
  "properties": {
    "iso:country":"BE",
    "sg:address":"Route De Flandre 86",
    "sg:city":"Komen-waasten",
    "sg:orig_category":"Diensten voor huisdieren Diverse organisaties and verenigingen",
    "sg:phone":"+32 56 55 71 02",
    "sg:postcode":"7780",
    "sg:province":"Hainaut",
    "wof:name":"Societ\u00c9 Protectrice Des Animaux Comines-warneton",
    "wof:placetype":"venue"
},
  "geometry": {"coordinates":[3.0023899078,50.7912712097],"type":"Point"}
}