{
  "type": "Feature",
  "properties": {
    "addr:full":"Rue De La Rocaille 17 Florennes Namur 5620",
    "addr:housenumber":"17",
    "addr:postcode":"5620",
    "addr:street":"Rue De La Rocaille",
    "iso:country":"BE",
    "sg:address":"Rue De La Rocaille 17",
    "sg:city":"Florennes",
    "sg:orig_category":"Instituts de beaut\u00e9",
    "sg:phone":"+32 82 68 92 81",
    "sg:postcode":"5620",
    "sg:province":"Namur",
    "wof:name":"Katty Dessomme",
    "wof:placetype":"venue"
},
  "geometry": {"coordinates":[4.721971035,50.2511749268],"type":"Point"}
}