{
  "type": "Feature",
  "properties": {
    "addr:full":"Pater Pellensstraat 3 Neerpelt Limburg 3910",
    "addr:housenumber":"3",
    "addr:postcode":"3910",
    "addr:street":"Pater Pellensstraat",
    "iso:country":"BE",
    "sg:address":"Pater Pellensstraat 3",
    "sg:city":"Neerpelt",
    "sg:classifiers":[
        {
            "category":"Communications",
            "type":"Services"
        }
    ],
    "sg:phone":"+32 11 66 45 96",
    "sg:postcode":"3910",
    "sg:province":"Limburg",
    "sg:tags":[
        "translator"
    ],
    "wof:name":"Chairang A",
    "wof:placetype":"venue"
},
  "geometry": {"coordinates":[5.4644589424,51.2368621826],"type":"Point"}
}