{
  "type": "Feature",
  "properties": {
    "iso:country":"BE",
    "sg:address":"Rue De Sirault 9",
    "sg:city":"Jurbise (herchies)",
    "sg:classifiers":[
        {
            "category":"Shopping",
            "subcategory":"Clothing, Apparel, & Fashions",
            "type":"Retail Goods"
        }
    ],
    "sg:phone":"+32 65 22 53 32",
    "sg:postcode":"7050",
    "sg:province":"Hainaut",
    "sg:tags":[
        "boutique"
    ],
    "wof:name":"Vestissimo",
    "wof:placetype":"venue"
},
  "geometry": {"coordinates":[3.8481030464,50.5288124084],"type":"Point"}
}