{
  "type": "Feature",
  "properties": {
    "addr:full":"Mussepi 39 Sint-katelijne-waver Antwerpen 2860",
    "addr:housenumber":"39",
    "addr:postcode":"2860",
    "addr:street":"Mussepi",
    "iso:country":"BE",
    "sg:address":"Mussepi 39",
    "sg:city":"Sint-katelijne-waver",
    "sg:orig_category":"Groententeelt",
    "sg:phone":"+32 15 55 23 89",
    "sg:postcode":"2860",
    "sg:province":"Antwerpen",
    "wof:name":"Willy Van Den Eynde",
    "wof:placetype":"venue"
},
  "geometry": {"coordinates":[4.5052638054,51.0556411743],"type":"Point"}
}