{
  "type": "Feature",
  "properties": {
    "iso:country":"BE",
    "sg:address":"Van Den Hautelei 107",
    "sg:city":"Deurne",
    "sg:classifiers":[
        {
            "category":"Home & Garden",
            "subcategory":"Furniture",
            "type":"Retail Goods"
        }
    ],
    "sg:phone":"+32 3 321 01 69",
    "sg:postcode":"2100",
    "sg:province":"Antwerpen",
    "sg:tags":[
        "household",
        "wood"
    ],
    "wof:name":"Bussche Bvba",
    "wof:placetype":"venue"
},
  "geometry": {"coordinates":[4.4675931931,51.2036018372],"type":"Point"}
}