{
  "type": "Feature",
  "properties": {
    "addr:full":"Rue Jacquet 55 Rochefort Namur 5580",
    "addr:housenumber":"55",
    "addr:postcode":"5580",
    "addr:street":"Rue Jacquet",
    "iso:country":"BE",
    "sg:address":"Rue Jacquet 55",
    "sg:city":"Rochefort",
    "sg:classifiers":[
        {
            "category":"Arena",
            "subcategory":"Sports Club",
            "type":"Entertainment"
        }
    ],
    "sg:phone":"+32 84 22 10 54",
    "sg:postcode":"5580",
    "sg:province":"Namur",
    "sg:tags":[
        "de"
    ],
    "wof:name":"Clus Solex De Belgique",
    "wof:placetype":"venue"
},
  "geometry": {"coordinates":[5.2223620415,50.1551017761],"type":"Point"}
}