{
  "type": "Feature",
  "properties": {
    "addr:full":"Chauss\u00c9e De La Hulpe 171 Watermaal-bosvoorde/watermael-boitsfort Bruxelles-Capitale 1170",
    "addr:housenumber":"171;/",
    "addr:postcode":"1170",
    "addr:street":"Chausse\u0301E De La Hulpe;Watermaal-Bosvoorde",
    "iso:country":"BE",
    "sg:address":"Chauss\u00c9e De La Hulpe 171",
    "sg:city":"Watermaal-bosvoorde/watermael-boitsfort",
    "sg:orig_category":"Administration d'immeubles",
    "sg:phone":"+32 2 663 60 00",
    "sg:postcode":"1170",
    "sg:province":"Bruxelles-Capitale",
    "wof:name":"Fonc. Carrefour Europe",
    "wof:placetype":"venue"
},
  "geometry": {"coordinates":[4.4016389847,50.7960395813],"type":"Point"}
}