{
  "type": "Feature",
  "properties": {
    "iso:country":"BE",
    "sg:address":"Nijverheidszone 'begijnenmeers' 51",
    "sg:city":"Liedekerke",
    "sg:classifiers":[
        {
            "category":"Landmark",
            "subcategory":"Memorial",
            "type":"Public Place"
        }
    ],
    "sg:phone":"+32 53 68 08 55",
    "sg:postcode":"1770",
    "sg:province":"Vlaams-Brabant",
    "sg:tags":[
        "-",
        "monument"
    ],
    "wof:name":"Van Snick - De Pever",
    "wof:placetype":"venue"
},
  "geometry": {"coordinates":[4.0872688293,50.8854942322],"type":"Point"}
}