{
  "type": "Feature",
  "properties": {
    "iso:country":"BE",
    "sg:address":"Grote Baan 155",
    "sg:city":"Houthalen-helchteren",
    "sg:orig_category":"Benzinestations and brandstoffen",
    "sg:phone":"+32 11 52 53 56",
    "sg:postcode":"3530",
    "sg:province":"Limburg",
    "wof:name":"Fina",
    "wof:placetype":"venue"
},
  "geometry": {"coordinates":[5.3776688576,51.0364341736],"type":"Point"}
}