{
  "type": "Feature",
  "properties": {
    "iso:country":"BE",
    "sg:address":"Bruinbeekstraat 53",
    "sg:city":"Bonheiden",
    "sg:orig_category":"Non-Classified Establishments",
    "sg:phone":"+32 15 55 32 31",
    "sg:postcode":"2820",
    "sg:province":"Antwerpen",
    "wof:name":"Gimalek Nv",
    "wof:placetype":"venue"
},
  "geometry": {"coordinates":[4.5300111771,51.0349235535],"type":"Point"}
}