{
  "type": "Feature",
  "properties": {
    "iso:country":"BE",
    "sg:address":"Avenue Du Centenaire 176",
    "sg:city":"Charleroi (montignies-sur-sambre)",
    "sg:classifiers":[
        {
            "category":"Autos & Motor Vehicles",
            "subcategory":"Automobile Sales",
            "type":"Retail Goods"
        }
    ],
    "sg:phone":"+32 71 70 04 74",
    "sg:postcode":"6061",
    "sg:province":"Hainaut",
    "sg:tags":[
        "delivery",
        "-",
        "used",
        "van",
        "truck"
    ],
    "wof:name":"A.p.c. Sprl",
    "wof:placetype":"venue"
},
  "geometry": {"coordinates":[4.4795150757,50.4009437561],"type":"Point"}
}