{
  "type": "Feature",
  "properties": {
    "addr:full":"Diestersteenweg 213 Hasselt Limburg 3510",
    "addr:housenumber":"213",
    "addr:postcode":"3510",
    "addr:street":"Diestersteenweg",
    "iso:country":"BE",
    "sg:address":"Diestersteenweg 213",
    "sg:city":"Hasselt",
    "sg:orig_category":"Banques and organismes de cr\u00e9dit",
    "sg:phone":"+32 11 85 16 85",
    "sg:postcode":"3510",
    "sg:province":"Limburg",
    "wof:name":"Centea",
    "wof:placetype":"venue"
},
  "geometry": {"coordinates":[5.2359399796,50.947719574],"type":"Point"}
}