{
  "type": "Feature",
  "properties": {
    "addr:full":"Kooldriesstraat 1 Brecht Antwerpen 2960",
    "addr:housenumber":"1",
    "addr:postcode":"2960",
    "addr:street":"Kooldriesstraat",
    "iso:country":"BE",
    "sg:address":"Kooldriesstraat 1",
    "sg:city":"Brecht",
    "sg:orig_category":"Plaatsen van vloer- and muurbekleding Schilders",
    "sg:phone":"+32 3 313 67 49",
    "sg:postcode":"2960",
    "sg:province":"Antwerpen",
    "wof:name":"Ivo Bernard",
    "wof:placetype":"venue"
},
  "geometry": {"coordinates":[4.6509900093,51.3269309998],"type":"Point"}
}