{
  "type": "Feature",
  "properties": {
    "addr:full":"Colonel Silvertopstraat 15 Boom Antwerpen 2850",
    "addr:housenumber":"15",
    "addr:postcode":"2850",
    "addr:street":"Silvertopstraat",
    "iso:country":"BE",
    "sg:address":"Colonel Silvertopstraat 15",
    "sg:city":"Boom",
    "sg:orig_category":"Caf\u00e9s Ruimtes voor conferenties, recepties and feesten",
    "sg:phone":"+32 3 844 64 10",
    "sg:postcode":"2850",
    "sg:province":"Antwerpen",
    "wof:name":"Feestpaleis",
    "wof:placetype":"venue"
},
  "geometry": {"coordinates":[4.3619680405,51.0860977173],"type":"Point"}
}