{
  "type": "Feature",
  "properties": {
    "addr:full":"Sint-bernardsesteenweg 260 Antwerpen Antwerpen 2020",
    "addr:housenumber":"260",
    "addr:postcode":"2020",
    "addr:street":"Sint-Bernardsesteenweg",
    "iso:country":"BE",
    "sg:address":"Sint-bernardsesteenweg 260",
    "sg:city":"Antwerpen",
    "sg:orig_category":"Boekhouders",
    "sg:phone":"+32 3 216 29 25",
    "sg:postcode":"2020",
    "sg:province":"Antwerpen",
    "wof:name":"Georges Vermeiren",
    "wof:placetype":"venue"
},
  "geometry": {"coordinates":[4.3797559738,51.1918716431],"type":"Point"}
}