{
  "type": "Feature",
  "properties": {
    "iso:country":"BE",
    "sg:address":"Boekrakelaan 30",
    "sg:city":"Genk",
    "sg:classifiers":[
        {
            "category":"Community Center",
            "subcategory":"Youth",
            "type":"Public Place"
        }
    ],
    "sg:phone":"+32 89 35 62 20",
    "sg:postcode":"3600",
    "sg:province":"Limburg",
    "sg:tags":[
        "club"
    ],
    "wof:name":"Jeugdherberg De Roerdomp Bokrijk",
    "wof:placetype":"venue"
},
  "geometry": {"coordinates":[5.4201278687,50.973323822],"type":"Point"}
}