{
  "type": "Feature",
  "properties": {
    "addr:full":"Chauss\u00e9e De Bruxelles 261 Charleroi (lodelinsart) Hainaut 6042",
    "addr:housenumber":"261",
    "addr:postcode":"6042",
    "addr:street":"Chausse\u0301E De Bruxelles",
    "iso:country":"BE",
    "sg:address":"Chauss\u00e9e De Bruxelles 261",
    "sg:city":"Charleroi (lodelinsart)",
    "sg:orig_category":"Autombile concessionaires",
    "sg:phone":"+32 71 30 30 60",
    "sg:postcode":"6042",
    "sg:province":"Hainaut",
    "wof:name":"Castus Sa",
    "wof:placetype":"venue"
},
  "geometry": {"coordinates":[4.4361891747,50.4442749023],"type":"Point"}
}