{
  "type": "Feature",
  "properties": {
    "iso:country":"BE",
    "sg:address":"Kerselarenstraat 24",
    "sg:city":"Tongeren",
    "sg:orig_category":"V\u00e9los",
    "sg:phone":"+32 12 23 60 33",
    "sg:postcode":"3700",
    "sg:province":"Limburg",
    "wof:name":"Fe. Francus",
    "wof:placetype":"venue"
},
  "geometry": {"coordinates":[5.4973201752,50.7472114563],"type":"Point"}
}