{
  "type": "Feature",
  "properties": {
    "iso:country":"BE",
    "sg:address":"Moerestraat 18ba",
    "sg:city":"Koekelare",
    "sg:orig_category":"Banques and organismes de cr\u00e9dit",
    "sg:phone":"+32 51 58 88 13",
    "sg:postcode":"8680",
    "sg:province":"West-Vlaanderen",
    "wof:name":"Landbouwkrediet",
    "wof:placetype":"venue"
},
  "geometry": {"coordinates":[2.9794580936,51.0921401978],"type":"Point"}
}