{
  "type": "Feature",
  "properties": {
    "iso:country":"BE",
    "sg:address":"Impedorp 40",
    "sg:city":"Lede",
    "sg:classifiers":[
        {
            "category":"Building & Trades",
            "subcategory":"Plumbing",
            "type":"Services"
        }
    ],
    "sg:phone":"+32 53 80 79 43",
    "sg:postcode":"9340",
    "sg:province":"Oost-Vlaanderen",
    "sg:tags":[
        "contractor"
    ],
    "wof:name":"Lanckman Erwin",
    "wof:placetype":"venue"
},
  "geometry": {"coordinates":[3.9507949352,50.9607810974],"type":"Point"}
}