{
  "type": "Feature",
  "properties": {
    "addr:full":"Smoutakker 85 Stabroek Antwerpen 2940",
    "addr:housenumber":"85",
    "addr:postcode":"2940",
    "addr:street":"Smoutakker",
    "iso:country":"BE",
    "sg:address":"Smoutakker 85",
    "sg:city":"Stabroek",
    "sg:classifiers":[
        {
            "category":"Building & Trades",
            "subcategory":"Electrical",
            "type":"Services"
        }
    ],
    "sg:phone":"+32 3 568 76 74",
    "sg:postcode":"2940",
    "sg:province":"Antwerpen",
    "sg:tags":[
        "electric",
        "-",
        "housewiring",
        "contractor"
    ],
    "wof:name":"Peersman",
    "wof:placetype":"venue"
},
  "geometry": {"coordinates":[4.3706579208,51.3302307129],"type":"Point"}
}