{
  "type": "Feature",
  "properties": {
    "iso:country":"BE",
    "sg:address":"Rue Joseph Wauters 38",
    "sg:city":"Morlanwelz (morlanwelz-mariemont)",
    "sg:classifiers":[
        {
            "category":"Health Services",
            "subcategory":"Health Practitioner",
            "type":"Services"
        }
    ],
    "sg:phone":"+32 64 45 14 77",
    "sg:postcode":"7140",
    "sg:province":"Hainaut",
    "sg:tags":[
        "physiotherapist"
    ],
    "wof:name":"Dept J",
    "wof:placetype":"venue"
},
  "geometry": {"coordinates":[4.2461800575,50.4546813965],"type":"Point"}
}