{
  "type": "Feature",
  "properties": {
    "addr:full":"Grote Steenweg 73 Zulte Oost-Vlaanderen 9870",
    "addr:housenumber":"73",
    "addr:postcode":"9870",
    "addr:street":"Grote Steenweg",
    "iso:country":"BE",
    "sg:address":"Grote Steenweg 73",
    "sg:city":"Zulte",
    "sg:classifiers":[
        {
            "category":"Restaurant",
            "type":"Food & Drink"
        }
    ],
    "sg:phone":"+32 9 388 82 08",
    "sg:postcode":"9870",
    "sg:province":"Oost-Vlaanderen",
    "wof:name":"Restaurant Breugelhof",
    "wof:placetype":"venue"
},
  "geometry": {"coordinates":[3.4674749374,50.9374542236],"type":"Point"}
}