{
  "type": "Feature",
  "properties": {
    "iso:country":"BE",
    "sg:address":"Winterslagstraat 114",
    "sg:city":"Genk",
    "sg:orig_category":"Studios photographiques",
    "sg:phone":"+32 89 35 35 07",
    "sg:postcode":"3600",
    "sg:province":"Limburg",
    "wof:name":"Gelders-schepers",
    "wof:placetype":"venue"
},
  "geometry": {"coordinates":[5.5005431175,50.9702110291],"type":"Point"}
}