{
  "type": "Feature",
  "properties": {
    "addr:full":"Place Madou - Chauss\u00c9e De Louvain 9 Bruxelles Bruxelles-Capitale 1210",
    "addr:housenumber":"9",
    "addr:postcode":"1210",
    "addr:street":"Place Madou Chausse\u0301E De Louvain",
    "iso:country":"BE",
    "sg:address":"Place Madou - Chauss\u00c9e De Louvain 9",
    "sg:city":"Bruxelles",
    "sg:orig_category":"Mat\u00e9riel de T\u00e9l\u00e9communication",
    "sg:phone":"+32 2 219 15 15",
    "sg:postcode":"1210",
    "sg:province":"Bruxelles-Capitale",
    "wof:name":"Gsm Planet",
    "wof:placetype":"venue"
},
  "geometry": {"coordinates":[4.3700709343,50.8492164612],"type":"Point"}
}