{
  "type": "Feature",
  "properties": {
    "addr:full":"Paardenmarkt 38 Antwerpen Antwerpen 2000",
    "addr:housenumber":"38",
    "addr:postcode":"2000",
    "addr:street":"Paardenmarkt",
    "iso:country":"BE",
    "sg:address":"Paardenmarkt 38",
    "sg:city":"Antwerpen",
    "sg:orig_category":"Plaatsen van vloer- and muurbekleding Schilders Textiel Verlichting and huishoudartikelen",
    "sg:phone":"+32 3 233 80 58",
    "sg:postcode":"2000",
    "sg:province":"Antwerpen",
    "wof:name":"Ludo Steppe",
    "wof:placetype":"venue"
},
  "geometry": {"coordinates":[4.409719944,51.2250709534],"type":"Point"}
}