{
  "type": "Feature",
  "properties": {
    "iso:country":"BE",
    "sg:address":"Borrestraat 23",
    "sg:city":"Sint-pieters-leeuw",
    "sg:classifiers":[
        {
            "category":"Professional",
            "subcategory":"Accounting & Tax Preparation",
            "type":"Services"
        }
    ],
    "sg:phone":"+32 2 532 45 97",
    "sg:postcode":"1602",
    "sg:province":"Vlaams-Brabant",
    "sg:tags":[
        "accountant"
    ],
    "wof:name":"Yves Apelmaen",
    "wof:placetype":"venue"
},
  "geometry": {"coordinates":[4.2263770103,50.8044586182],"type":"Point"}
}