{
  "type": "Feature",
  "properties": {
    "addr:full":"Hillestraat 7 Heuvelland (dranouter) West-Vlaanderen 8951",
    "addr:housenumber":"7",
    "addr:postcode":"8951",
    "addr:street":"Hillestraat",
    "iso:country":"BE",
    "sg:address":"Hillestraat 7",
    "sg:city":"Heuvelland (dranouter)",
    "sg:classifiers":[
        {
            "category":"Farming",
            "subcategory":"Farm & Veterinary Services",
            "type":"Manufacturing & Wholesale Goods"
        }
    ],
    "sg:phone":"+32 57 44 45 60",
    "sg:postcode":"8951",
    "sg:province":"West-Vlaanderen",
    "sg:tags":[
        "agricultural",
        "contractor"
    ],
    "wof:name":"Baelde P",
    "wof:placetype":"venue"
},
  "geometry": {"coordinates":[2.7666831017,50.7586174011],"type":"Point"}
}