{
  "type": "Feature",
  "properties": {
    "iso:country":"BE",
    "sg:address":"Weegschede 49",
    "sg:city":"Alveringem",
    "sg:orig_category":"Dakwerken",
    "sg:phone":"+32 58 29 94 68",
    "sg:postcode":"8691",
    "sg:province":"West-Vlaanderen",
    "wof:name":"Fa. Dekindt",
    "wof:placetype":"venue"
},
  "geometry": {"coordinates":[2.67730093,50.9702644348],"type":"Point"}
}