{
  "type": "Feature",
  "properties": {
    "addr:full":"Amandinaweg 175 Herk-de-stad Limburg 3540",
    "addr:housenumber":"175",
    "addr:postcode":"3540",
    "addr:street":"Amandinaweg",
    "iso:country":"BE",
    "sg:address":"Amandinaweg 175",
    "sg:city":"Herk-de-stad",
    "sg:orig_category":"Rundveehouders",
    "sg:phone":"+32 13 55 16 82",
    "sg:postcode":"3540",
    "sg:province":"Limburg",
    "wof:name":"Guillaume Douce",
    "wof:placetype":"venue"
},
  "geometry": {"coordinates":[5.2030220032,50.9054222107],"type":"Point"}
}