{
  "type": "Feature",
  "properties": {
    "iso:country":"BE",
    "sg:address":"Markt 18",
    "sg:city":"Haacht",
    "sg:orig_category":"Pharmaciens",
    "sg:phone":"+32 16 60 23 94",
    "sg:postcode":"3150",
    "sg:province":"Vlaams-Brabant",
    "wof:name":"Apoteek Centrum",
    "wof:placetype":"venue"
},
  "geometry": {"coordinates":[4.6382431984,50.9765510559],"type":"Point"}
}