{
  "type": "Feature",
  "properties": {
    "addr:full":"Rue Du Major Sabbe 44be Pecq Hainaut 7740",
    "addr:housenumber":"44be",
    "addr:postcode":"7740",
    "addr:street":"Rue Du Major Sabbe",
    "iso:country":"BE",
    "sg:address":"Rue Du Major Sabbe 44be",
    "sg:city":"Pecq",
    "sg:classifiers":[
        {
            "category":"Insurance",
            "subcategory":"Life Insurance",
            "type":"Services"
        }
    ],
    "sg:phone":"+32 69 55 79 01",
    "sg:postcode":"7740",
    "sg:province":"Hainaut",
    "sg:tags":[
        "assurance"
    ],
    "wof:name":"Pierre Duthoit",
    "wof:placetype":"venue"
},
  "geometry": {"coordinates":[3.3357610703,50.6823730469],"type":"Point"}
}