{
  "type": "Feature",
  "properties": {
    "iso:country":"BE",
    "sg:address":"Bunderswijk 47",
    "sg:city":"Dentergem",
    "sg:orig_category":"R\u00e9parations de chaussures and articles en cuir",
    "sg:phone":"+32 51 63 55 09",
    "sg:postcode":"8720",
    "sg:province":"West-Vlaanderen",
    "wof:name":"Rudi Vandemaele",
    "wof:placetype":"venue"
},
  "geometry": {"coordinates":[3.4109959602,50.9641647339],"type":"Point"}
}