{
  "type": "Feature",
  "properties": {
    "iso:country":"BE",
    "sg:address":"Rue Des Deux Eglises 36b13",
    "sg:city":"Brussel/bruxelles",
    "sg:orig_category":"G\u00e9om\u00e8tres. Evaluation and estimation de biens immobiliers",
    "sg:phone":"+32 2 217 56 76",
    "sg:postcode":"1000",
    "sg:province":"Bruxelles-Capitale",
    "wof:name":"Bureau Immorex",
    "wof:placetype":"venue"
},
  "geometry": {"coordinates":[4.372633934,50.846622467],"type":"Point"}
}