{
  "type": "Feature",
  "properties": {
    "addr:full":"Veurnestraat 1 Vleteren West-Vlaanderen 8640",
    "addr:housenumber":"1",
    "addr:postcode":"8640",
    "addr:street":"Veurnestraat",
    "iso:country":"BE",
    "sg:address":"Veurnestraat 1",
    "sg:city":"Vleteren",
    "sg:orig_category":"Slagers",
    "sg:phone":"+32 57 40 06 20",
    "sg:postcode":"8640",
    "sg:province":"West-Vlaanderen",
    "wof:name":"Frans Boury",
    "wof:placetype":"venue"
},
  "geometry": {"coordinates":[2.7362840176,50.932434082],"type":"Point"}
}