{
  "type": "Feature",
  "properties": {
    "iso:country":"BE",
    "sg:address":"Staf Larochelaan 27",
    "sg:city":"Brecht",
    "sg:classifiers":[
        {
            "category":"Professional",
            "subcategory":"Engineering",
            "type":"Services"
        }
    ],
    "sg:phone":"+32 3 636 14 24",
    "sg:postcode":"2960",
    "sg:province":"Antwerpen",
    "sg:tags":[
        "-"
    ],
    "wof:name":"Van Bael M",
    "wof:placetype":"venue"
},
  "geometry": {"coordinates":[4.5806908607,51.3027801514],"type":"Point"}
}