{
  "type": "Feature",
  "properties": {
    "iso:country":"BE",
    "sg:address":"Emile Maxlaan 182b11",
    "sg:city":"Schaarbeek/schaerbeek",
    "sg:orig_category":"Boekhouders",
    "sg:phone":"+32 2 735 00 52",
    "sg:postcode":"1030",
    "sg:province":"Bruxelles-Capitale",
    "wof:name":"Yves Fundu-makani",
    "wof:placetype":"venue"
},
  "geometry": {"coordinates":[4.3999857903,50.851890564],"type":"Point"}
}