{
  "type": "Feature",
  "properties": {
    "addr:full":"Chauss\u00e9e De Charleroi 83 Namur Namur 5000",
    "addr:housenumber":"83",
    "addr:postcode":"5000",
    "addr:street":"Chausse\u0301E De Charleroi",
    "iso:country":"BE",
    "sg:address":"Chauss\u00e9e De Charleroi 83",
    "sg:city":"Namur",
    "sg:classifiers":[
        {
            "category":"Organizations",
            "subcategory":"Professional Association",
            "type":"Services"
        }
    ],
    "sg:phone":"+32 81 72 18 88",
    "sg:postcode":"5000",
    "sg:province":"Namur",
    "sg:tags":[
        "trade-union",
        "federation"
    ],
    "wof:name":"Horeca",
    "wof:placetype":"venue"
},
  "geometry": {"coordinates":[4.8409872055,50.4619750977],"type":"Point"}
}