{
  "type": "Feature",
  "properties": {
    "addr:full":"Vijlststraat 3 Merchtem Vlaams-Brabant 1785",
    "addr:housenumber":"3",
    "addr:postcode":"1785",
    "addr:street":"Vijlststraat",
    "iso:country":"BE",
    "sg:address":"Vijlststraat 3",
    "sg:city":"Merchtem",
    "sg:orig_category":"Eleveurs de bovins. Producteurs de l\u00e9gumes",
    "sg:phone":"+32 2 460 22 74",
    "sg:postcode":"1785",
    "sg:province":"Vlaams-Brabant",
    "wof:name":"Karel Van Den Eynde",
    "wof:placetype":"venue"
},
  "geometry": {"coordinates":[4.2317490578,50.9585723877],"type":"Point"}
}