{
  "type": "Feature",
  "properties": {
    "iso:country":"BE",
    "sg:address":"Lambermontlaan 78",
    "sg:city":"Schaarbeek/schaerbeek",
    "sg:orig_category":"Binnenhuisarchitecten Textiel Verlichting and huishoudartikelen",
    "sg:phone":"+32 2 242 91 50",
    "sg:postcode":"1030",
    "sg:province":"Bruxelles-Capitale",
    "wof:name":"Arch Nova",
    "wof:placetype":"venue"
},
  "geometry": {"coordinates":[4.3780832291,50.8733787537],"type":"Point"}
}