{
  "type": "Feature",
  "properties": {
    "iso:country":"BE",
    "sg:address":"Hopstraat 8",
    "sg:city":"Sint-katherina-lombeek",
    "sg:orig_category":"Stained Glass",
    "sg:phone":"+32 474 70 30 83",
    "sg:postcode":"1742",
    "sg:province":"Vlaams-Brabant",
    "wof:name":"Ab\u00e9 Gallery",
    "wof:placetype":"venue"
},
  "geometry": {"coordinates":[4.1107020378,50.8791122437],"type":"Point"}
}