{
  "type": "Feature",
  "properties": {
    "addr:full":"Rue Roosevelt 20 Fl\u00e9ron (roms\u00e9e) Li\u00e8ge 4624",
    "addr:housenumber":"20",
    "addr:postcode":"4624",
    "addr:street":"Rue Roosevelt",
    "iso:country":"BE",
    "sg:address":"Rue Roosevelt 20",
    "sg:city":"Fl\u00e9ron (roms\u00e9e)",
    "sg:classifiers":[
        {
            "category":"Farming",
            "subcategory":"Fish & Marine Products",
            "type":"Manufacturing & Wholesale Goods"
        }
    ],
    "sg:phone":"+32 4 358 79 66",
    "sg:postcode":"4624",
    "sg:province":"Li\u00e8ge",
    "sg:tags":[
        "retail",
        "-",
        "shellfish"
    ],
    "wof:name":"Lagune (la)",
    "wof:placetype":"venue"
},
  "geometry": {"coordinates":[5.663435936,50.6105422974],"type":"Point"}
}