{
  "type": "Feature",
  "properties": {
    "iso:country":"BE",
    "sg:address":"Rue Vanderkindere 318",
    "sg:city":"Bruxelles (uccle)",
    "sg:orig_category":"Newspapers, magazines, periodicals - Distribution",
    "sg:phone":"+32 2 343 44 99",
    "sg:postcode":"1180",
    "sg:province":"Bruxelles-Capitale",
    "wof:name":"Sedip Belgium Sa",
    "wof:placetype":"venue"
},
  "geometry": {"coordinates":[4.3542518616,50.8141937256],"type":"Point"}
}