{
  "type": "Feature",
  "properties": {
    "addr:full":"Rue Jacobs-fontaine 35 Brussel/bruxelles Bruxelles-Capitale 1020",
    "addr:housenumber":"35",
    "addr:postcode":"1020",
    "addr:street":"Rue Jacobs-Fontaine;/",
    "iso:country":"BE",
    "sg:address":"Rue Jacobs-fontaine 35",
    "sg:city":"Brussel/bruxelles",
    "sg:orig_category":"Installation de menuiserie en bois and plastique. Charpentes and couvertures",
    "sg:phone":"+32 2 427 52 22",
    "sg:postcode":"1020",
    "sg:province":"Bruxelles-Capitale",
    "wof:name":"Jean-pierre Wtoreck",
    "wof:placetype":"venue"
},
  "geometry": {"coordinates":[4.3417367935,50.8781471252],"type":"Point"}
}