{
  "type": "Feature",
  "properties": {
    "addr:full":"Brusselsesteenweg 214 Melle Oost-Vlaanderen 9090",
    "addr:housenumber":"214",
    "addr:postcode":"9090",
    "addr:street":"Brusselsesteenweg",
    "iso:country":"BE",
    "sg:address":"Brusselsesteenweg 214",
    "sg:city":"Melle",
    "sg:classifiers":[
        {
            "category":"Shopping",
            "subcategory":"Florist",
            "type":"Retail Goods"
        }
    ],
    "sg:phone":"+32 9 252 16 38",
    "sg:postcode":"9090",
    "sg:province":"Oost-Vlaanderen",
    "wof:name":"Floribel",
    "wof:placetype":"venue"
},
  "geometry": {"coordinates":[3.8010759354,51.0030441284],"type":"Point"}
}