{
  "type": "Feature",
  "properties": {
    "addr:full":"Gullegemsestraat 183 Ledegem (sint-eloois-winkel) West-Vlaanderen 8880",
    "addr:housenumber":"183",
    "addr:postcode":"8880",
    "addr:street":"Gullegemsestraat",
    "iso:country":"BE",
    "sg:address":"Gullegemsestraat 183",
    "sg:city":"Ledegem (sint-eloois-winkel)",
    "sg:classifiers":[
        {
            "category":"Airport",
            "subcategory":"International",
            "type":"Transportation"
        }
    ],
    "sg:phone":"+32 56 50 92 79",
    "sg:postcode":"8880",
    "sg:province":"West-Vlaanderen",
    "sg:tags":[
        "-",
        "transport"
    ],
    "wof:name":"Bruwier Geert Bvba",
    "wof:placetype":"venue"
},
  "geometry": {"coordinates":[3.184180975,50.8637466431],"type":"Point"}
}