{
  "type": "Feature",
  "properties": {
    "addr:full":"Kolveniersvest 12 Lier Antwerpen 2500",
    "addr:housenumber":"12",
    "addr:postcode":"2500",
    "addr:street":"Kolveniersvest",
    "iso:country":"BE",
    "sg:address":"Kolveniersvest 12",
    "sg:city":"Lier",
    "sg:classifiers":[
        {
            "category":"Health Services",
            "subcategory":"Dentist",
            "type":"Services"
        }
    ],
    "sg:phone":"+32 3 480 00 69",
    "sg:postcode":"2500",
    "sg:province":"Antwerpen",
    "wof:name":"Bellens Bieke",
    "wof:placetype":"venue"
},
  "geometry": {"coordinates":[4.5664710999,51.1321258545],"type":"Point"}
}