{
  "type": "Feature",
  "properties": {
    "iso:country":"BE",
    "sg:address":"Het Oud Blok 48",
    "sg:city":"Balen",
    "sg:orig_category":"Serres and speciale beglazing",
    "sg:phone":"+32 14 30 04 98",
    "sg:postcode":"2490",
    "sg:province":"Antwerpen",
    "wof:name":"Rene Engelen",
    "wof:placetype":"venue"
},
  "geometry": {"coordinates":[5.105550766,51.1532897949],"type":"Point"}
}