{
  "type": "Feature",
  "properties": {
    "addr:full":"Impasse Du Blancbou 6 Gesves Namur 5340",
    "addr:housenumber":"6",
    "addr:postcode":"5340",
    "addr:street":"Impasse Du Blancbou",
    "iso:country":"BE",
    "sg:address":"Impasse Du Blancbou 6",
    "sg:city":"Gesves",
    "sg:orig_category":"Messageries",
    "sg:phone":"+32 81 57 05 67",
    "sg:postcode":"5340",
    "sg:province":"Namur",
    "wof:name":"Colis Super Express",
    "wof:placetype":"venue"
},
  "geometry": {"coordinates":[5.0374341011,50.422832489],"type":"Point"}
}