{
  "type": "Feature",
  "properties": {
    "addr:full":"Rue Haute 39 Vis\u00e9 Li\u00e8ge 4600",
    "addr:housenumber":"39",
    "addr:postcode":"4600",
    "addr:street":"Rue Haute",
    "iso:country":"BE",
    "sg:address":"Rue Haute 39",
    "sg:city":"Vis\u00e9",
    "sg:classifiers":[
        {
            "category":"Shopping",
            "subcategory":"Luggage & Leather Goods",
            "type":"Retail Goods"
        }
    ],
    "sg:phone":"+32 4 379 61 33",
    "sg:postcode":"4600",
    "sg:province":"Li\u00e8ge",
    "sg:tags":[
        "-"
    ],
    "wof:name":"Michele M",
    "wof:placetype":"venue"
},
  "geometry": {"coordinates":[5.6963758469,50.7340927124],"type":"Point"}
}