{
  "type": "Feature",
  "properties": {
    "addr:full":"Bld Fr\u00c8re Orban 37 Li\u00c8ge Li\u00e8ge 4000",
    "addr:housenumber":"37",
    "addr:postcode":"4000",
    "addr:street":"Bld Fre\u0300Re Orban",
    "iso:country":"BE",
    "sg:address":"Bld Fr\u00c8re Orban 37",
    "sg:city":"Li\u00c8ge",
    "sg:orig_category":"Artsen and specialisten",
    "sg:phone":"+32 4 252 02 87",
    "sg:postcode":"4000",
    "sg:province":"Li\u00e8ge",
    "wof:name":"J. Mauhin",
    "wof:placetype":"venue"
},
  "geometry": {"coordinates":[5.5721130371,50.6293983459],"type":"Point"}
}