{
  "type": "Feature",
  "properties": {
    "addr:full":"Rue Metsys 73 Brussel/bruxelles Bruxelles-Capitale 1030",
    "addr:housenumber":"73",
    "addr:postcode":"1030",
    "addr:street":"Rue Metsys;/",
    "iso:country":"BE",
    "sg:address":"Rue Metsys 73",
    "sg:city":"Brussel/bruxelles",
    "sg:orig_category":"Journaux. Tabac",
    "sg:phone":"+32 2 216 48 58",
    "sg:postcode":"1030",
    "sg:province":"Bruxelles-Capitale",
    "wof:name":"Maison Bisschot",
    "wof:placetype":"venue"
},
  "geometry": {"coordinates":[4.3766150475,50.8697090149],"type":"Point"}
}