{
  "type": "Feature",
  "properties": {
    "addr:full":"Rue Ferrer 14 Sprimont Li\u00e8ge 4140",
    "addr:housenumber":"14",
    "addr:postcode":"4140",
    "addr:street":"Rue Ferrer",
    "iso:country":"BE",
    "sg:address":"Rue Ferrer 14",
    "sg:city":"Sprimont",
    "sg:orig_category":"Boekhouders",
    "sg:phone":"+32 4 382 32 70",
    "sg:postcode":"4140",
    "sg:province":"Li\u00e8ge",
    "wof:name":"Cogniaux Maurice",
    "wof:placetype":"venue"
},
  "geometry": {"coordinates":[5.6625699997,50.5028495789],"type":"Point"}
}