{
  "type": "Feature",
  "properties": {
    "addr:full":"Rue Des Nations 6 Seraing Li\u00e8ge 4102",
    "addr:housenumber":"6",
    "addr:postcode":"4102",
    "addr:street":"Rue Des Nations",
    "iso:country":"BE",
    "sg:address":"Rue Des Nations 6",
    "sg:city":"Seraing",
    "sg:orig_category":"M\u00e9decines alternatives",
    "sg:phone":"+32 4 365 70 62",
    "sg:postcode":"4102",
    "sg:province":"Li\u00e8ge",
    "wof:name":"Mich\u00c8le Fuger",
    "wof:placetype":"venue"
},
  "geometry": {"coordinates":[5.5415048599,50.5881538391],"type":"Point"}
}