{
  "type": "Feature",
  "properties": {
    "addr:full":"Ijzerenmolenstraat 105 Leuven (groot) Vlaams-Brabant 3001",
    "addr:housenumber":"105",
    "addr:postcode":"3001",
    "addr:street":"Ijzerenmolenstraat;Groot Vlaams-Brabant",
    "iso:country":"BE",
    "sg:address":"Ijzerenmolenstraat 105",
    "sg:city":"Leuven (groot)",
    "sg:orig_category":"Avocats and conseillers juridiques",
    "sg:phone":"+32 16 31 04 20",
    "sg:postcode":"3001",
    "sg:province":"Vlaams-Brabant",
    "wof:name":"Hans-kristof Car\u00came",
    "wof:placetype":"venue"
},
  "geometry": {"coordinates":[4.6817178726,50.8686637878],"type":"Point"}
}