{
  "type": "Feature",
  "properties": {
    "iso:country":"BE",
    "sg:address":"Rue Reine Elisabeth 5",
    "sg:city":"Mettet",
    "sg:orig_category":"Equipement photographique. Studios photographiques",
    "sg:phone":"+32 71 72 72 36",
    "sg:postcode":"5640",
    "sg:province":"Namur",
    "wof:name":"Studio Mottet",
    "wof:placetype":"venue"
},
  "geometry": {"coordinates":[4.6583337784,50.3202819824],"type":"Point"}
}