{
  "type": "Feature",
  "properties": {
    "addr:full":"Sint-servaasstraat 30 Hasselt Limburg 3500",
    "addr:housenumber":"30",
    "addr:postcode":"3500",
    "addr:street":"Sint-Servaasstraat",
    "iso:country":"BE",
    "sg:address":"Sint-servaasstraat 30",
    "sg:city":"Hasselt",
    "sg:orig_category":"Etalage- and showroomontwerpers",
    "sg:phone":"+32 11 27 14 77",
    "sg:postcode":"3500",
    "sg:province":"Limburg",
    "wof:name":"Johan Hermans",
    "wof:placetype":"venue"
},
  "geometry": {"coordinates":[5.314977169,50.9303207397],"type":"Point"}
}