{
  "type": "Feature",
  "properties": {
    "addr:full":"Vecpr\u00e9 4 La Roche-en-ardenne Luxembourg 6980",
    "addr:housenumber":"4",
    "addr:postcode":"6980",
    "addr:street":"Vecpre\u0301",
    "iso:country":"BE",
    "sg:address":"Vecpr\u00e9 4",
    "sg:city":"La Roche-en-ardenne",
    "sg:classifiers":[
        {
            "category":"Recreation",
            "subcategory":"Campground",
            "type":"Entertainment"
        }
    ],
    "sg:phone":"+32 84 41 11 74",
    "sg:postcode":"6980",
    "sg:province":"Luxembourg",
    "sg:tags":[
        "site",
        "camping"
    ],
    "wof:name":"Pouhou(camping)",
    "wof:placetype":"venue"
},
  "geometry": {"coordinates":[5.559158802,50.1822395325],"type":"Point"}
}