{
  "type": "Feature",
  "properties": {
    "addr:full":"Ringlaan 10 Zandhoven Antwerpen 2240",
    "addr:housenumber":"10",
    "addr:postcode":"2240",
    "addr:street":"Ringlaan",
    "iso:country":"BE",
    "sg:address":"Ringlaan 10",
    "sg:city":"Zandhoven",
    "sg:classifiers":[
        {
            "category":"Banks & Credit Unions",
            "subcategory":"Investment Brokerage",
            "type":"Services"
        }
    ],
    "sg:phone":"+32 3 484 59 35",
    "sg:postcode":"2240",
    "sg:province":"Antwerpen",
    "sg:tags":[
        "-",
        "sale",
        "yachts",
        "accessory",
        "pleasure",
        "boat"
    ],
    "wof:name":"Moviboats",
    "wof:placetype":"venue"
},
  "geometry": {"coordinates":[4.6541690826,51.2078208923],"type":"Point"}
}