{
  "type": "Feature",
  "properties": {
    "addr:full":"Avenue Gisseleire Vers\u00e9 23-25 Bruxelles (berchem-sainte-agathe) Bruxelles-Capitale 1082",
    "addr:housenumber":"23-25",
    "addr:postcode":"1082",
    "addr:street":"Avenue Gisseleire Verse\u0301",
    "iso:country":"BE",
    "sg:address":"Avenue Gisseleire Vers\u00e9 23-25",
    "sg:city":"Bruxelles (berchem-sainte-agathe)",
    "sg:classifiers":[
        {
            "category":"Health Services",
            "subcategory":"Nursing And Care Facility",
            "type":"Services"
        }
    ],
    "sg:phone":"+32 2 465 67 15",
    "sg:postcode":"1082",
    "sg:province":"Bruxelles-Capitale",
    "sg:tags":[
        "home",
        "rest"
    ],
    "wof:name":"Nouvelle R\u00e9sidence Le Saule",
    "wof:placetype":"venue"
},
  "geometry": {"coordinates":[4.2995758057,50.86095047],"type":"Point"}
}