{
  "type": "Feature",
  "properties": {
    "iso:country":"BE",
    "sg:address":"Leuvenseweg 40-42",
    "sg:city":"Brussel/bruxelles",
    "sg:orig_category":"Openbare instellingen economische aangelegenheden",
    "sg:phone":"+32 2 552 22 11",
    "sg:postcode":"1000",
    "sg:province":"Bruxelles-Capitale",
    "wof:name":"Staatsblad",
    "wof:placetype":"venue"
},
  "geometry": {"coordinates":[4.364962101,50.8475379944],"type":"Point"}
}