{
  "type": "Feature",
  "properties": {
    "addr:full":"Knippegroen 1 Gent Oost-Vlaanderen 9042",
    "addr:housenumber":"1",
    "addr:postcode":"9042",
    "addr:street":"Knippegroen;Oost-Vlaanderen",
    "iso:country":"BE",
    "sg:address":"Knippegroen 1",
    "sg:city":"Gent",
    "sg:orig_category":"Goederenvervoer over de weg Verhuur bouwmachines",
    "sg:phone":"+32 9 345 98 91",
    "sg:postcode":"9042",
    "sg:province":"Oost-Vlaanderen",
    "wof:name":"Van Seumeren",
    "wof:placetype":"venue"
},
  "geometry": {"coordinates":[3.8020489216,51.1569480896],"type":"Point"}
}