{
  "type": "Feature",
  "properties": {
    "addr:full":"Roodbos 38 Fourons Limburg 3791",
    "addr:housenumber":"38",
    "addr:postcode":"3791",
    "addr:street":"Roodbos",
    "iso:country":"BE",
    "sg:address":"Roodbos 38",
    "sg:city":"Fourons",
    "sg:orig_category":"Tuinen",
    "sg:phone":"+32 4 381 11 82",
    "sg:postcode":"3791",
    "sg:province":"Limburg",
    "wof:name":"Rouland",
    "wof:placetype":"venue"
},
  "geometry": {"coordinates":[5.8665189743,50.7298812866],"type":"Point"}
}