{
  "type": "Feature",
  "properties": {
    "iso:country":"BE",
    "sg:address":"Chauss\u00e9e De Jolimont 130",
    "sg:city":"La Louvi\u00e8re (haine-saint-pierre)",
    "sg:classifiers":[
        {
            "category":"Shopping",
            "subcategory":"Bicycles & Sporting Goods",
            "type":"Retail Goods"
        }
    ],
    "sg:phone":"+32 64 22 57 88",
    "sg:postcode":"7100",
    "sg:province":"Hainaut",
    "sg:tags":[
        "-"
    ],
    "wof:name":"Ets Vansteelant Demil",
    "wof:placetype":"venue"
},
  "geometry": {"coordinates":[4.2180700302,50.4738082886],"type":"Point"}
}