{
  "type": "Feature",
  "properties": {
    "addr:full":"Molenstraat 6 Rumst (reet) Antwerpen 2840",
    "addr:housenumber":"6",
    "addr:postcode":"2840",
    "addr:street":"Molenstraat",
    "iso:country":"BE",
    "sg:address":"Molenstraat 6",
    "sg:city":"Rumst (reet)",
    "sg:classifiers":[
        {
            "category":"Education",
            "subcategory":"School",
            "type":"Public Place"
        }
    ],
    "sg:phone":"+32 3 888 43 02",
    "sg:postcode":"2840",
    "sg:province":"Antwerpen",
    "sg:tags":[
        "primary"
    ],
    "wof:name":"De Wingerd (vrije Basisschool)",
    "wof:placetype":"venue"
},
  "geometry": {"coordinates":[4.4228310585,51.0781745911],"type":"Point"}
}