{
  "type": "Feature",
  "properties": {
    "iso:country":"BE",
    "sg:address":"Oranjelaan 32",
    "sg:city":"Sint-pieters-woluwe/woluwe-saint-pierre",
    "sg:orig_category":"Artsen and specialisten",
    "sg:phone":"+32 2 770 33 79",
    "sg:postcode":"1150",
    "sg:province":"Bruxelles-Capitale",
    "wof:name":"Genevi\u00c8ve Fran\u00c7ois",
    "wof:placetype":"venue"
},
  "geometry": {"coordinates":[4.441699028,50.8298950195],"type":"Point"}
}