{
  "type": "Feature",
  "properties": {
    "addr:full":"Steenweg 125 Alken Limburg 3570",
    "addr:housenumber":"125",
    "addr:postcode":"3570",
    "addr:street":"Steenweg",
    "iso:country":"BE",
    "sg:address":"Steenweg 125",
    "sg:city":"Alken",
    "sg:classifiers":[
        {
            "category":"Autos & Motor Vehicles",
            "subcategory":"Fuel & Gas Station",
            "type":"Retail Goods"
        }
    ],
    "sg:phone":"+32 11 31 43 91",
    "sg:postcode":"3570",
    "sg:province":"Limburg",
    "wof:name":"Shell/ballet-punie",
    "wof:placetype":"venue"
},
  "geometry": {"coordinates":[5.2897629738,50.8886756897],"type":"Point"}
}