{
  "type": "Feature",
  "properties": {
    "iso:country":"BE",
    "sg:address":"Moerasstraat 24",
    "sg:city":"Meulebeke",
    "sg:classifiers":[
        {
            "category":"Professional",
            "subcategory":"Management & Consulting",
            "type":"Services"
        }
    ],
    "sg:phone":"+32 51 48 60 93",
    "sg:postcode":"8760",
    "sg:province":"West-Vlaanderen",
    "sg:tags":[
        "consultant"
    ],
    "wof:name":"Hairdesk",
    "wof:placetype":"venue"
},
  "geometry": {"coordinates":[3.2827029228,50.9613952637],"type":"Point"}
}