{
  "type": "Feature",
  "properties": {
    "addr:full":"Diestsestraat 177 Leuven Vlaams-Brabant 3000",
    "addr:housenumber":"177",
    "addr:postcode":"3000",
    "addr:street":"Diestsestraat",
    "iso:country":"BE",
    "sg:address":"Diestsestraat 177",
    "sg:city":"Leuven",
    "sg:classifiers":[
        {
            "category":"Shopping",
            "subcategory":"Gifts & Souvenirs",
            "type":"Retail Goods"
        }
    ],
    "sg:phone":"+32 16 22 23 19",
    "sg:postcode":"3000",
    "sg:province":"Vlaams-Brabant",
    "sg:tags":[
        "-"
    ],
    "wof:name":"Chadresz Nv",
    "wof:placetype":"venue"
},
  "geometry": {"coordinates":[4.7097978592,50.8815765381],"type":"Point"}
}