{
  "type": "Feature",
  "properties": {
    "iso:country":"BE",
    "sg:address":"Lysbrugstraat 37",
    "sg:city":"Ingelmunster",
    "sg:classifiers":[
        {
            "category":"Building & Trades",
            "subcategory":"Landscaping Services",
            "type":"Services"
        }
    ],
    "sg:phone":"+32 51 30 65 51",
    "sg:postcode":"8770",
    "sg:province":"West-Vlaanderen",
    "sg:tags":[
        "gardening",
        "garden",
        "maintenance"
    ],
    "wof:name":"Messiaen J",
    "wof:placetype":"venue"
},
  "geometry": {"coordinates":[3.2653319836,50.9145507812],"type":"Point"}
}