{
  "type": "Feature",
  "properties": {
    "iso:country":"BE",
    "sg:address":"Puttestraat 10",
    "sg:city":"Balen",
    "sg:orig_category":"Produits chimiques Gr",
    "sg:phone":"+32 14 81 12 81",
    "sg:postcode":"2490",
    "sg:province":"Antwerpen",
    "wof:name":"E.c.p.",
    "wof:placetype":"venue"
},
  "geometry": {"coordinates":[5.1528959274,51.1588287354],"type":"Point"}
}