{
  "type": "Feature",
  "properties": {
    "addr:full":"Assesteenweg 108 Ternat Vlaams-Brabant 1742",
    "addr:housenumber":"108",
    "addr:postcode":"1742",
    "addr:street":"Assesteenweg",
    "iso:country":"BE",
    "sg:address":"Assesteenweg 108",
    "sg:city":"Ternat",
    "sg:orig_category":"Benzinestations and brandstoffen",
    "sg:phone":"+32 2 582 48 57",
    "sg:postcode":"1742",
    "sg:province":"Vlaams-Brabant",
    "wof:name":"Q8",
    "wof:placetype":"venue"
},
  "geometry": {"coordinates":[4.1638979912,50.8766975403],"type":"Point"}
}