{
  "type": "Feature",
  "properties": {
    "iso:country":"BE",
    "sg:address":"Ternatsestraat 131",
    "sg:city":"Affligem",
    "sg:classifiers":[
        {
            "category":"Personal",
            "subcategory":"Beauty Salon",
            "type":"Services"
        }
    ],
    "sg:phone":"+32 2 582 10 51",
    "sg:postcode":"1790",
    "sg:province":"Vlaams-Brabant",
    "sg:tags":[
        "de",
        "coiffure"
    ],
    "wof:name":"Fashion",
    "wof:placetype":"venue"
},
  "geometry": {"coordinates":[4.1408128738,50.8952484131],"type":"Point"}
}