{
  "type": "Feature",
  "properties": {
    "addr:full":"Rue Buisseret 6 Binche Hainaut 7130",
    "addr:housenumber":"6",
    "addr:postcode":"7130",
    "addr:street":"Rue Buisseret",
    "iso:country":"BE",
    "sg:address":"Rue Buisseret 6",
    "sg:city":"Binche",
    "sg:orig_category":"Huisdieren and benodigdheden Royal Canin",
    "sg:phone":"+32 64 33 44 47",
    "sg:postcode":"7130",
    "sg:province":"Hainaut",
    "wof:name":"M Maloteaux",
    "wof:placetype":"venue"
},
  "geometry": {"coordinates":[4.1668491364,50.411441803],"type":"Point"}
}