{
  "type": "Feature",
  "properties": {
    "addr:full":"Iepersestraat 245 Roeselare West-Vlaanderen 8800",
    "addr:housenumber":"245",
    "addr:postcode":"8800",
    "addr:street":"Iepersestraat",
    "iso:country":"BE",
    "sg:address":"Iepersestraat 245",
    "sg:city":"Roeselare",
    "sg:orig_category":"Algemeen secundair onderwijs",
    "sg:phone":"+32 51 20 58 86",
    "sg:postcode":"8800",
    "sg:province":"West-Vlaanderen",
    "wof:name":"Buso Onze Jeugd",
    "wof:placetype":"venue"
},
  "geometry": {"coordinates":[3.1121621132,50.9383926392],"type":"Point"}
}