{
  "type": "Feature",
  "properties": {
    "addr:full":"Marktstraat 46 Maldegem Oost-Vlaanderen 9990",
    "addr:housenumber":"46",
    "addr:postcode":"9990",
    "addr:street":"Marktstraat",
    "iso:country":"BE",
    "sg:address":"Marktstraat 46",
    "sg:city":"Maldegem",
    "sg:classifiers":[
        {
            "category":"Shopping",
            "subcategory":"Clothing, Apparel, & Fashions",
            "type":"Retail Goods"
        }
    ],
    "sg:phone":"+32 50 71 34 35",
    "sg:postcode":"9990",
    "sg:province":"Oost-Vlaanderen",
    "sg:tags":[
        "underwear",
        "lingerie",
        "-"
    ],
    "wof:name":"Sharron",
    "wof:placetype":"venue"
},
  "geometry": {"coordinates":[3.4474430084,51.209022522],"type":"Point"}
}