{
  "type": "Feature",
  "properties": {
    "iso:country":"BE",
    "sg:address":"Driesstraat 34",
    "sg:city":"Heusden-zolder (zolder)",
    "sg:classifiers":[
        {
            "category":"Wholesale",
            "subcategory":"Plants",
            "type":"Manufacturing & Wholesale Goods"
        }
    ],
    "sg:phone":"+32 11 53 70 13",
    "sg:postcode":"3550",
    "sg:province":"Limburg",
    "sg:tags":[
        "whol",
        "flower",
        "-",
        "grower"
    ],
    "wof:name":"Put L",
    "wof:placetype":"venue"
},
  "geometry": {"coordinates":[5.2612738609,51.0096473694],"type":"Point"}
}