{
  "type": "Feature",
  "properties": {
    "iso:country":"BE",
    "sg:address":"Rue Gosuin 17b",
    "sg:city":"Wanze",
    "sg:classifiers":[
        {
            "category":"Building & Trades",
            "subcategory":"Construction",
            "type":"Services"
        }
    ],
    "sg:phone":"+32 85 41 27 46",
    "sg:postcode":"4520",
    "sg:province":"Li\u00e8ge",
    "sg:tags":[
        "stone",
        "cutter"
    ],
    "wof:name":"D.g.j. Pierres",
    "wof:placetype":"venue"
},
  "geometry": {"coordinates":[5.2120299339,50.5320358276],"type":"Point"}
}