{
  "type": "Feature",
  "properties": {
    "iso:country":"BE",
    "sg:address":"Wijngaardstraat 26",
    "sg:city":"Tielt-winge",
    "sg:orig_category":"Diverse bouwafwerking and reiniging Gespecialiseerde residenti\u00eble bouw Pleisterwerk",
    "sg:phone":"+32 16 63 51 37",
    "sg:postcode":"3390",
    "sg:province":"Vlaams-Brabant",
    "wof:name":"Guido Elsen",
    "wof:placetype":"venue"
},
  "geometry": {"coordinates":[4.8675251007,50.9462242126],"type":"Point"}
}