{
  "type": "Feature",
  "properties": {
    "addr:full":"Dendermondse Steenweg 61 Berlare Oost-Vlaanderen 9290",
    "addr:housenumber":"61",
    "addr:postcode":"9290",
    "addr:street":"Steenweg",
    "iso:country":"BE",
    "sg:address":"Dendermondse Steenweg 61",
    "sg:city":"Berlare",
    "sg:orig_category":"Supermarkten",
    "sg:phone":"+32 9 367 93 54",
    "sg:postcode":"9290",
    "sg:province":"Oost-Vlaanderen",
    "wof:name":"Ad Delhaize",
    "wof:placetype":"venue"
},
  "geometry": {"coordinates":[3.9740169048,51.0501174927],"type":"Point"}
}