{
  "type": "Feature",
  "properties": {
    "iso:country":"BE",
    "sg:address":"Leliestraat 30",
    "sg:city":"Geraardsbergen",
    "sg:classifiers":[
        {
            "category":"Cafe",
            "type":"Food & Drink"
        }
    ],
    "sg:phone":"+32 54 41 84 50",
    "sg:postcode":"9500",
    "sg:province":"Oost-Vlaanderen",
    "sg:tags":[
        "caf\u00e9s"
    ],
    "wof:name":"Christiane De Galan",
    "wof:placetype":"venue"
},
  "geometry": {"coordinates":[3.8579659462,50.7670173645],"type":"Point"}
}