{
  "type": "Feature",
  "properties": {
    "addr:full":"Generaal Lemanstraat 20 Menen West-Vlaanderen 8930",
    "addr:housenumber":"20",
    "addr:postcode":"8930",
    "addr:street":"Generaal Lemanstraat",
    "iso:country":"BE",
    "sg:address":"Generaal Lemanstraat 20",
    "sg:city":"Menen",
    "sg:classifiers":[
        {
            "category":"Health Services",
            "subcategory":"Dentist",
            "type":"Services"
        }
    ],
    "sg:phone":"+32 56 51 57 93",
    "sg:postcode":"8930",
    "sg:province":"West-Vlaanderen",
    "wof:name":"Jonnaert P",
    "wof:placetype":"venue"
},
  "geometry": {"coordinates":[3.1087110043,50.7989959717],"type":"Point"}
}