{
  "type": "Feature",
  "properties": {
    "iso:country":"BE",
    "sg:address":"Messidorlaan 122",
    "sg:city":"Ukkel/uccle",
    "sg:orig_category":"Paramedische behandelingen",
    "sg:phone":"+32 2 347 03 86",
    "sg:postcode":"1180",
    "sg:province":"Bruxelles-Capitale",
    "wof:name":"Reyns",
    "wof:placetype":"venue"
},
  "geometry": {"coordinates":[4.3428578377,50.81016922],"type":"Point"}
}