{
  "type": "Feature",
  "properties": {
    "iso:country":"BE",
    "sg:address":"Kerkweg 1",
    "sg:city":"Dilbeek",
    "sg:orig_category":"HUISBRANDOLIE",
    "sg:phone":"+32 2 569 21 61",
    "sg:postcode":"1703",
    "sg:province":"Vlaams-Brabant",
    "wof:name":"Simone Decoster",
    "wof:placetype":"venue"
},
  "geometry": {"coordinates":[4.1901311874,50.8379364014],"type":"Point"}
}