{
  "type": "Feature",
  "properties": {
    "iso:country":"BE",
    "sg:address":"Rue Edith Cavell 45",
    "sg:city":"Bruxelles (uccle)",
    "sg:classifiers":[
        {
            "category":"Education",
            "subcategory":"School",
            "type":"Public Place"
        }
    ],
    "sg:phone":"+32 2 344 24 09",
    "sg:postcode":"1180",
    "sg:province":"Bruxelles-Capitale",
    "sg:tags":[
        "-",
        "private"
    ],
    "wof:name":"E.e.p.p.",
    "wof:placetype":"venue"
},
  "geometry": {"coordinates":[4.3573298454,50.8117141724],"type":"Point"}
}