{
  "type": "Feature",
  "properties": {
    "addr:full":"Sinte-aleidisvoorplein 40 Sint-pieters-woluwe/woluwe-saint-pierre Bruxelles-Capitale 1150",
    "addr:housenumber":"40",
    "addr:postcode":"1150",
    "addr:street":"Sinte-Aleidisvoorplein;/",
    "iso:country":"BE",
    "sg:address":"Sinte-aleidisvoorplein 40",
    "sg:city":"Sint-pieters-woluwe/woluwe-saint-pierre",
    "sg:orig_category":"Baby- and kinderkleding Dameskledingzaken Tweedehandsgoederen",
    "sg:phone":"+32 2 762 48 58",
    "sg:postcode":"1150",
    "sg:province":"Bruxelles-Capitale",
    "wof:name":"Le Tiroir Aux Surprises",
    "wof:placetype":"venue"
},
  "geometry": {"coordinates":[4.4621219635,50.8284721375],"type":"Point"}
}