{
  "type": "Feature",
  "properties": {
    "iso:country":"BE",
    "sg:address":"Voie De Li\u00c8ge 111",
    "sg:city":"Welkenraedt/welkenraedt",
    "sg:orig_category":"Rundveehouders",
    "sg:phone":"+32 87 88 00 23",
    "sg:postcode":"4840",
    "sg:province":"Li\u00e8ge",
    "wof:name":"Martin Pauquet",
    "wof:placetype":"venue"
},
  "geometry": {"coordinates":[5.9796700478,50.6616210938],"type":"Point"}
}