{
  "type": "Feature",
  "properties": {
    "addr:full":"Spaanskwartier 30a Sint-gillis-waas (de Klinge) Oost-Vlaanderen 9170",
    "addr:housenumber":"30a",
    "addr:postcode":"9170",
    "addr:street":"Spaanskwartier;Oost-Vlaanderen",
    "iso:country":"BE",
    "sg:address":"Spaanskwartier 30a",
    "sg:city":"Sint-gillis-waas (de Klinge)",
    "sg:classifiers":[
        {
            "category":"Building & Trades",
            "subcategory":"Electrical",
            "type":"Services"
        }
    ],
    "sg:phone":"+32 3 707 05 36",
    "sg:postcode":"9170",
    "sg:province":"Oost-Vlaanderen",
    "sg:tags":[
        "electric",
        "-",
        "housewiring",
        "contractor"
    ],
    "wof:name":"Schelfhout R",
    "wof:placetype":"venue"
},
  "geometry": {"coordinates":[4.1255750656,51.2189941406],"type":"Point"}
}