{
  "type": "Feature",
  "properties": {
    "iso:country":"BE",
    "sg:address":"Lodistraat 105",
    "sg:city":"Oostkamp",
    "sg:orig_category":"V\u00e9los",
    "sg:phone":"+32 50 82 22 05",
    "sg:postcode":"8020",
    "sg:province":"West-Vlaanderen",
    "wof:name":"Norbert Vangaver",
    "wof:placetype":"venue"
},
  "geometry": {"coordinates":[3.2669548988,51.122467041],"type":"Point"}
}