{
  "type": "Feature",
  "properties": {
    "addr:full":"Dennengaerdelaan 7 As Limburg 3665",
    "addr:housenumber":"as",
    "addr:postcode":"3665",
    "addr:street":"Dennengaerdelaan;Limburg",
    "iso:country":"BE",
    "sg:address":"Dennengaerdelaan 7",
    "sg:city":"As",
    "sg:classifiers":[
        {
            "category":"Arena",
            "subcategory":"Sports Club",
            "type":"Entertainment"
        }
    ],
    "sg:phone":"+32 89 65 77 39",
    "sg:postcode":"3665",
    "sg:province":"Limburg",
    "sg:tags":[
        "de"
    ],
    "wof:name":"W.s.v. De Heikabouters",
    "wof:placetype":"venue"
},
  "geometry": {"coordinates":[5.6118612289,51.0139274597],"type":"Point"}
}