{
  "type": "Feature",
  "properties": {
    "iso:country":"BE",
    "sg:address":"Rue Du Coll\u00c8ge St-michel 55",
    "sg:city":"Sint-pieters-woluwe/woluwe-saint-pierre",
    "sg:orig_category":"Installation de piscines. Plomberie, chauffage and installations sanitaires",
    "sg:phone":"+32 2 733 39 56",
    "sg:postcode":"1150",
    "sg:province":"Bruxelles-Capitale",
    "wof:name":"Abeco-poolcare",
    "wof:placetype":"venue"
},
  "geometry": {"coordinates":[4.4113478661,50.8349571228],"type":"Point"}
}