{
  "type": "Feature",
  "properties": {
    "addr:full":"Hoek 76 Boom Antwerpen 2850",
    "addr:housenumber":"76",
    "addr:postcode":"2850",
    "addr:street":"Hoek",
    "iso:country":"BE",
    "sg:address":"Hoek 76",
    "sg:city":"Boom",
    "sg:classifiers":[
        {
            "category":"Home & Garden",
            "subcategory":"Building Materials",
            "type":"Retail Goods"
        }
    ],
    "sg:phone":"+32 3 830 37 58",
    "sg:postcode":"2850",
    "sg:province":"Antwerpen",
    "sg:tags":[
        "wall",
        "cupboard"
    ],
    "wof:name":"Lumac Id Bvba",
    "wof:placetype":"venue"
},
  "geometry": {"coordinates":[4.3774271011,51.0845031738],"type":"Point"}
}