{
  "type": "Feature",
  "properties": {
    "addr:full":"Rue De La Station 11 La Bruy\u00c8re Namur 5080",
    "addr:housenumber":"11",
    "addr:postcode":"5080",
    "addr:street":"Rue De La Station",
    "iso:country":"BE",
    "sg:address":"Rue De La Station 11",
    "sg:city":"La Bruy\u00c8re",
    "sg:orig_category":"Dakwerken Loodgieterij, verwarming and sanitaire installaties",
    "sg:phone":"+32 81 56 71 37",
    "sg:postcode":"5080",
    "sg:province":"Namur",
    "wof:name":"Rolain Jean-louis",
    "wof:placetype":"venue"
},
  "geometry": {"coordinates":[4.8048710823,50.5030517578],"type":"Point"}
}