{
  "type": "Feature",
  "properties": {
    "addr:full":"Franklin Rooseveltlaan 173 Vilvoorde Vlaams-Brabant 1800",
    "addr:housenumber":"173",
    "addr:postcode":"1800",
    "addr:street":"Franklin Rooseveltlaan",
    "iso:country":"BE",
    "sg:address":"Franklin Rooseveltlaan 173",
    "sg:city":"Vilvoorde",
    "sg:orig_category":"Pharmaciens",
    "sg:phone":"+32 2 251 02 03",
    "sg:postcode":"1800",
    "sg:province":"Vlaams-Brabant",
    "wof:name":"Multipharma",
    "wof:placetype":"venue"
},
  "geometry": {"coordinates":[4.4243950844,50.9304924011],"type":"Point"}
}