{
  "type": "Feature",
  "properties": {
    "addr:full":"Nieuwstraat 1ba Borgloon Limburg 3840",
    "addr:housenumber":"1ba",
    "addr:postcode":"3840",
    "addr:street":"Nieuwstraat",
    "iso:country":"BE",
    "sg:address":"Nieuwstraat 1ba",
    "sg:city":"Borgloon",
    "sg:orig_category":"Banques and organismes de cr\u00e9dit",
    "sg:phone":"+32 12 74 12 03",
    "sg:postcode":"3840",
    "sg:province":"Limburg",
    "wof:name":"Fortis",
    "wof:placetype":"venue"
},
  "geometry": {"coordinates":[5.3404049873,50.8034172058],"type":"Point"}
}