{
  "type": "Feature",
  "properties": {
    "addr:full":"Hovenierslaan 3 Schilde Antwerpen 2970",
    "addr:housenumber":"3",
    "addr:postcode":"2970",
    "addr:street":"Hovenierslaan",
    "iso:country":"BE",
    "sg:address":"Hovenierslaan 3",
    "sg:city":"Schilde",
    "sg:orig_category":"Medische apparatuur, orthopedische artikelen and prothesen Fab",
    "sg:phone":"+32 3 383 36 40",
    "sg:postcode":"2970",
    "sg:province":"Antwerpen",
    "wof:name":"J. Sels",
    "wof:placetype":"venue"
},
  "geometry": {"coordinates":[4.5948472023,51.2343406677],"type":"Point"}
}