{
  "type": "Feature",
  "properties": {
    "iso:country":"BE",
    "sg:address":"Gouden-boomstraat 70",
    "sg:city":"Brugge",
    "sg:orig_category":"Paramedische behandelingen",
    "sg:phone":"+32 50 31 70 92",
    "sg:postcode":"8000",
    "sg:province":"West-Vlaanderen",
    "wof:name":"Inneke Nyssen",
    "wof:placetype":"venue"
},
  "geometry": {"coordinates":[3.2104310989,51.2136497498],"type":"Point"}
}