{
  "type": "Feature",
  "properties": {
    "addr:full":"Place De La Station 4 Kraainem Vlaams-Brabant 1950",
    "addr:housenumber":"4",
    "addr:postcode":"1950",
    "addr:street":"Place De La Station",
    "iso:country":"BE",
    "sg:address":"Place De La Station 4",
    "sg:city":"Kraainem",
    "sg:classifiers":[
        {
            "category":"Fast Food",
            "type":"Food & Drink"
        }
    ],
    "sg:phone":"+32 2 721 47 43",
    "sg:postcode":"1950",
    "sg:province":"Vlaams-Brabant",
    "sg:tags":[
        "fried",
        "stand",
        "potato"
    ],
    "wof:name":"Francine",
    "wof:placetype":"venue"
},
  "geometry": {"coordinates":[4.4529161453,50.8663063049],"type":"Point"}
}