{
  "type": "Feature",
  "properties": {
    "addr:full":"Baalsebaan 289 Tremelo Vlaams-Brabant 3128",
    "addr:housenumber":"289",
    "addr:postcode":"3128",
    "addr:street":"Baalsebaan",
    "iso:country":"BE",
    "sg:address":"Baalsebaan 289",
    "sg:city":"Tremelo",
    "sg:classifiers":[
        {
            "category":"Health Services",
            "subcategory":"Nursing And Care Facility",
            "type":"Services"
        }
    ],
    "sg:phone":"+32 16 53 39 46",
    "sg:postcode":"3128",
    "sg:province":"Vlaams-Brabant",
    "sg:tags":[
        "public"
    ],
    "wof:name":"O.c.m.w.",
    "wof:placetype":"venue"
},
  "geometry": {"coordinates":[4.7498559952,50.9949760437],"type":"Point"}
}