{
  "type": "Feature",
  "properties": {
    "addr:full":"Brugsesteenweg 5-7 Gent Oost-Vlaanderen 9000",
    "addr:housenumber":"5-7",
    "addr:postcode":"9000",
    "addr:street":"Brugsesteenweg;Oost-Vlaanderen",
    "iso:country":"BE",
    "sg:address":"Brugsesteenweg 5-7",
    "sg:city":"Gent",
    "sg:classifiers":[
        {
            "category":"Utilities",
            "subcategory":"Electric",
            "type":"Services"
        }
    ],
    "sg:phone":"+32 9 329 87 00",
    "sg:postcode":"9000",
    "sg:province":"Oost-Vlaanderen",
    "sg:tags":[
        "energy",
        "renewable"
    ],
    "wof:name":"Westenwind",
    "wof:placetype":"venue"
},
  "geometry": {"coordinates":[3.695389986,51.0636711121],"type":"Point"}
}