{
  "type": "Feature",
  "properties": {
    "iso:country":"BE",
    "sg:address":"Torhoutse Steenweg 162",
    "sg:city":"Brugge",
    "sg:orig_category":"Brood, gebak and snoepgoed",
    "sg:phone":"+32 50 39 19 07",
    "sg:postcode":"8200",
    "sg:province":"West-Vlaanderen",
    "wof:name":"Kurt Mersy",
    "wof:placetype":"venue"
},
  "geometry": {"coordinates":[3.2020289898,51.1983299255],"type":"Point"}
}