{
  "type": "Feature",
  "properties": {
    "addr:full":"Boulevard Poincar\u00e9 55 Bruxelles (anderlecht) Bruxelles-Capitale 1070",
    "addr:housenumber":"55",
    "addr:postcode":"1070",
    "addr:street":"Boulevard Poincare\u0301",
    "iso:country":"BE",
    "sg:address":"Boulevard Poincar\u00e9 55",
    "sg:city":"Bruxelles (anderlecht)",
    "sg:classifiers":[
        {
            "category":"Shopping",
            "subcategory":"Clothing, Apparel, & Fashions",
            "type":"Retail Goods"
        }
    ],
    "sg:phone":"+32 2 521 49 22",
    "sg:postcode":"1070",
    "sg:province":"Bruxelles-Capitale",
    "sg:tags":[
        "-",
        "fur"
    ],
    "wof:name":"De Mesmaeker-mertens Sa",
    "wof:placetype":"venue"
},
  "geometry": {"coordinates":[4.3391361237,50.8425331116],"type":"Point"}
}