{
  "type": "Feature",
  "properties": {
    "iso:country":"BE",
    "sg:address":"Vijverslaan 88b6",
    "sg:city":"Wemmel/wemmel",
    "sg:classifiers":[
        {
            "category":"Professional",
            "subcategory":"Accounting & Tax Preparation",
            "type":"Services"
        }
    ],
    "sg:phone":"+32 2 461 14 73",
    "sg:postcode":"1780",
    "sg:province":"Vlaams-Brabant",
    "sg:tags":[
        "accountant"
    ],
    "wof:name":"J-j Hoebanckx/jean-joseph Hoebanckx",
    "wof:placetype":"venue"
},
  "geometry": {"coordinates":[4.3061461449,50.9028892517],"type":"Point"}
}