{
  "type": "Feature",
  "properties": {
    "iso:country":"BE",
    "sg:address":"Stationsstraat 15",
    "sg:city":"Maaseik",
    "sg:classifiers":[
        {
            "category":"Health Services",
            "subcategory":"Doctor",
            "type":"Services"
        }
    ],
    "sg:phone":"+32 89 56 66 75",
    "sg:postcode":"3680",
    "sg:province":"Limburg",
    "sg:tags":[
        "medicinephysicians",
        "surgeon"
    ],
    "wof:name":"Coenen Marilou",
    "wof:placetype":"venue"
},
  "geometry": {"coordinates":[5.7796797752,51.0968894958],"type":"Point"}
}