{
  "type": "Feature",
  "properties": {
    "addr:full":"Rue Du Comptoir 4-6-8 Charleroi Hainaut 6000",
    "addr:housenumber":"4-6-8",
    "addr:postcode":"6000",
    "addr:street":"Rue Du Comptoir;Hainaut",
    "iso:country":"BE",
    "sg:address":"Rue Du Comptoir 4-6-8",
    "sg:city":"Charleroi",
    "sg:classifiers":[
        {
            "category":"Restaurant",
            "type":"Food & Drink"
        }
    ],
    "sg:phone":"+32 71 32 19 02",
    "sg:postcode":"6000",
    "sg:province":"Hainaut",
    "wof:name":"L'hippopotame",
    "wof:placetype":"venue"
},
  "geometry": {"coordinates":[4.4402828217,50.4079971313],"type":"Point"}
}