{
  "type": "Feature",
  "properties": {
    "addr:full":"Baronielaan 56 Izegem West-Vlaanderen 8870",
    "addr:housenumber":"56",
    "addr:postcode":"8870",
    "addr:street":"Baronielaan",
    "iso:country":"BE",
    "sg:address":"Baronielaan 56",
    "sg:city":"Izegem",
    "sg:classifiers":[
        {
            "category":"Health Services",
            "subcategory":"Dentist",
            "type":"Services"
        }
    ],
    "sg:phone":"+32 51 31 47 19",
    "sg:postcode":"8870",
    "sg:province":"West-Vlaanderen",
    "wof:name":"Gyselinck Wouter",
    "wof:placetype":"venue"
},
  "geometry": {"coordinates":[3.2197299004,50.9088973999],"type":"Point"}
}