{
  "type": "Feature",
  "properties": {
    "addr:full":"Klokkestraat 32 Duffel Antwerpen 2570",
    "addr:housenumber":"32",
    "addr:postcode":"2570",
    "addr:street":"Klokkestraat",
    "iso:country":"BE",
    "sg:address":"Klokkestraat 32",
    "sg:city":"Duffel",
    "sg:orig_category":"Groententeelt",
    "sg:phone":"+32 15 31 28 21",
    "sg:postcode":"2570",
    "sg:province":"Antwerpen",
    "wof:name":"Duffelplant",
    "wof:placetype":"venue"
},
  "geometry": {"coordinates":[4.4898929596,51.1099815369],"type":"Point"}
}