{
  "type": "Feature",
  "properties": {
    "addr:full":"Hof Leeuwergem 5 Aalst Oost-Vlaanderen 9300",
    "addr:housenumber":"5",
    "addr:postcode":"9300",
    "addr:street":"Hof Leeuwergem",
    "iso:country":"BE",
    "sg:address":"Hof Leeuwergem 5",
    "sg:city":"Aalst",
    "sg:classifiers":[
        {
            "category":"Professional",
            "subcategory":"Accounting & Tax Preparation",
            "type":"Services"
        }
    ],
    "sg:phone":"+32 53 77 49 52",
    "sg:postcode":"9300",
    "sg:province":"Oost-Vlaanderen",
    "sg:tags":[
        "bookkeeper"
    ],
    "wof:name":"Aaco Cvba",
    "wof:placetype":"venue"
},
  "geometry": {"coordinates":[4.0774831772,50.9302482605],"type":"Point"}
}