{
  "type": "Feature",
  "properties": {
    "iso:country":"BE",
    "sg:address":"Sint-truidersteenweg 472",
    "sg:city":"Borgloon",
    "sg:orig_category":"Fruitteelt",
    "sg:phone":"+32 12 74 73 29",
    "sg:postcode":"3840",
    "sg:province":"Limburg",
    "wof:name":"Albert Bex",
    "wof:placetype":"venue"
},
  "geometry": {"coordinates":[5.2769980431,50.8072814941],"type":"Point"}
}