{
  "type": "Feature",
  "properties": {
    "iso:country":"BE",
    "sg:address":"Hans Memlingstraat 3",
    "sg:city":"Kortrijk (marke)",
    "sg:classifiers":[
        {
            "category":"Shopping",
            "subcategory":"Clothing, Apparel, & Fashions",
            "type":"Retail Goods"
        }
    ],
    "sg:phone":"+32 56 21 24 50",
    "sg:postcode":"8510",
    "sg:province":"West-Vlaanderen",
    "sg:tags":[
        "lady",
        "clothing",
        "-"
    ],
    "wof:name":"Ongenae Dameskleding Bvba",
    "wof:placetype":"venue"
},
  "geometry": {"coordinates":[3.250754118,50.8026428223],"type":"Point"}
}