{
  "type": "Feature",
  "properties": {
    "addr:full":"Rue Du Travail 105 Namur Namur 5000",
    "addr:housenumber":"105",
    "addr:postcode":"5000",
    "addr:street":"Rue Du Travail",
    "iso:country":"BE",
    "sg:address":"Rue Du Travail 105",
    "sg:city":"Namur",
    "sg:orig_category":"M\u00e9decins and sp\u00e9cialistes",
    "sg:phone":"+32 81 73 75 73",
    "sg:postcode":"5000",
    "sg:province":"Namur",
    "wof:name":"Rapha\u00cblle Leroy",
    "wof:placetype":"venue"
},
  "geometry": {"coordinates":[4.8442378044,50.4566574097],"type":"Point"}
}