{
  "type": "Feature",
  "properties": {
    "iso:country":"BE",
    "sg:address":"Rue Nestor Bouillon 7a",
    "sg:city":"Somme-leuze (sinsin)",
    "sg:classifiers":[
        {
            "category":"Health Services",
            "subcategory":"Health Practitioner",
            "type":"Services"
        }
    ],
    "sg:phone":"+32 83 68 90 52",
    "sg:postcode":"5377",
    "sg:province":"Namur",
    "sg:tags":[
        "physiotherapist"
    ],
    "wof:name":"Denis Sabine",
    "wof:placetype":"venue"
},
  "geometry": {"coordinates":[5.2499990463,50.2708511353],"type":"Point"}
}