{
  "type": "Feature",
  "properties": {
    "addr:full":"Rue De Grand'axhe 56bc Waremme Li\u00e8ge 4300",
    "addr:housenumber":"56bc",
    "addr:postcode":"4300",
    "addr:street":"Rue De Grand'Axhe",
    "iso:country":"BE",
    "sg:address":"Rue De Grand'axhe 56bc",
    "sg:city":"Waremme",
    "sg:orig_category":"Installation \u00e9lectrique r\u00e9sidentielle",
    "sg:phone":"+32 19 32 88 08",
    "sg:postcode":"4300",
    "sg:province":"Li\u00e8ge",
    "wof:name":"Fe. Somelec",
    "wof:placetype":"venue"
},
  "geometry": {"coordinates":[5.2289471626,50.6803283691],"type":"Point"}
}