{
  "type": "Feature",
  "properties": {
    "addr:full":"Chauss\u00c9e De Houffalize 14 Bastogne Luxembourg 6600",
    "addr:housenumber":"14",
    "addr:postcode":"6600",
    "addr:street":"Chausse\u0301E De Houffalize",
    "iso:country":"BE",
    "sg:address":"Chauss\u00c9e De Houffalize 14",
    "sg:city":"Bastogne",
    "sg:orig_category":"Advocaten and juridische adviseurs",
    "sg:phone":"+32 61 21 47 12",
    "sg:postcode":"6600",
    "sg:province":"Luxembourg",
    "wof:name":"Jean-benoit Massart",
    "wof:placetype":"venue"
},
  "geometry": {"coordinates":[5.7244839668,50.0142555237],"type":"Point"}
}