{
  "type": "Feature",
  "properties": {
    "addr:full":"Daelvenne 11 Berlare Oost-Vlaanderen 9290",
    "addr:housenumber":"11",
    "addr:postcode":"9290",
    "addr:street":"Daelvenne",
    "iso:country":"BE",
    "sg:address":"Daelvenne 11",
    "sg:city":"Berlare",
    "sg:orig_category":"Charpentes and couvertures",
    "sg:phone":"+32 52 42 41 11",
    "sg:postcode":"9290",
    "sg:province":"Oost-Vlaanderen",
    "wof:name":"Baeyens",
    "wof:placetype":"venue"
},
  "geometry": {"coordinates":[4.0026669502,51.0121116638],"type":"Point"}
}