{
  "type": "Feature",
  "properties": {
    "addr:full":"Chauss\u00c9e De Charleroi 9 Fontaine-l\u00b4ev\u00caque Hainaut 6140",
    "addr:housenumber":"9",
    "addr:postcode":"6140",
    "addr:street":"Chausse\u0301E De Charleroi;Hainaut",
    "iso:country":"BE",
    "sg:address":"Chauss\u00c9e De Charleroi 9",
    "sg:city":"Fontaine-l\u00b4ev\u00caque",
    "sg:orig_category":"Agences de voyages",
    "sg:phone":"+32 71 54 32 20",
    "sg:postcode":"6140",
    "sg:province":"Hainaut",
    "wof:name":"Espace Voyages",
    "wof:placetype":"venue"
},
  "geometry": {"coordinates":[4.3315200806,50.4069099426],"type":"Point"}
}