{
  "type": "Feature",
  "properties": {
    "addr:full":"Wittenonnenstraat 24a Oostende West-Vlaanderen 8400",
    "addr:housenumber":"24a",
    "addr:postcode":"8400",
    "addr:street":"Wittenonnenstraat",
    "iso:country":"BE",
    "sg:address":"Wittenonnenstraat 24a",
    "sg:city":"Oostende",
    "sg:classifiers":[
        {
            "category":"Home & Garden",
            "subcategory":"Home Furnishings",
            "type":"Retail Goods"
        }
    ],
    "sg:phone":"+32 59 50 91 29",
    "sg:postcode":"8400",
    "sg:province":"West-Vlaanderen",
    "sg:tags":[
        "linen",
        "household",
        "-"
    ],
    "wof:name":"Descamps",
    "wof:placetype":"venue"
},
  "geometry": {"coordinates":[2.9178009033,51.2308769226],"type":"Point"}
}