{
  "type": "Feature",
  "properties": {
    "iso:country":"BE",
    "sg:address":"Jan Devischstraat 87",
    "sg:city":"Knokke-heist",
    "sg:orig_category":"Bloemen and planten",
    "sg:phone":"+32 50 62 66 21",
    "sg:postcode":"8300",
    "sg:province":"West-Vlaanderen",
    "wof:name":"Huis Violette",
    "wof:placetype":"venue"
},
  "geometry": {"coordinates":[3.3002951145,51.3378868103],"type":"Point"}
}