{
  "type": "Feature",
  "properties": {
    "iso:country":"BE",
    "sg:address":"Puursesteenweg 329",
    "sg:city":"Bornem",
    "sg:orig_category":"Herstellingen and onderhoud van auto's",
    "sg:phone":"+32 3 889 57 26",
    "sg:postcode":"2880",
    "sg:province":"Antwerpen",
    "wof:name":"Bornem Motors",
    "wof:placetype":"venue"
},
  "geometry": {"coordinates":[4.2591028214,51.0858078003],"type":"Point"}
}