{
  "type": "Feature",
  "properties": {
    "addr:full":"Sint-godfriedstraat 8 Sint-truiden Limburg 3800",
    "addr:housenumber":"8",
    "addr:postcode":"3800",
    "addr:street":"Sint-Godfriedstraat",
    "iso:country":"BE",
    "sg:address":"Sint-godfriedstraat 8",
    "sg:city":"Sint-truiden",
    "sg:classifiers":[
        {
            "category":"Health Services",
            "subcategory":"Doctor",
            "type":"Services"
        }
    ],
    "sg:phone":"+32 11 68 96 84",
    "sg:postcode":"3800",
    "sg:province":"Limburg",
    "sg:tags":[
        "medicinephysicians",
        "surgeon"
    ],
    "wof:name":"Budo Camille",
    "wof:placetype":"venue"
},
  "geometry": {"coordinates":[5.1993780136,50.8308868408],"type":"Point"}
}