{
  "type": "Feature",
  "properties": {
    "iso:country":"BE",
    "sg:address":"David Tenierslaan 42b3",
    "sg:city":"Lier",
    "sg:orig_category":"Schoonheidssalons",
    "sg:phone":"+32 3 480 22 69",
    "sg:postcode":"2500",
    "sg:province":"Antwerpen",
    "wof:name":"Albert Verbiest",
    "wof:placetype":"venue"
},
  "geometry": {"coordinates":[4.5532817841,51.1304779053],"type":"Point"}
}