{
  "type": "Feature",
  "properties": {
    "addr:full":"Rue De La D\u00c9portation 42 La Louviere Hainaut 7100",
    "addr:housenumber":"42",
    "addr:postcode":"7100",
    "addr:street":"Rue De La De\u0301Portation",
    "iso:country":"BE",
    "sg:address":"Rue De La D\u00c9portation 42",
    "sg:city":"La Louviere",
    "sg:orig_category":"Benzinestations and brandstoffen",
    "sg:phone":"+32 64 22 18 99",
    "sg:postcode":"7100",
    "sg:province":"Hainaut",
    "wof:name":"Esso",
    "wof:placetype":"venue"
},
  "geometry": {"coordinates":[4.1998257637,50.4650611877],"type":"Point"}
}