{
  "type": "Feature",
  "properties": {
    "iso:country":"BE",
    "sg:address":"Route De Mons 71",
    "sg:city":"Charleroi",
    "sg:orig_category":"Textiel",
    "sg:phone":"+32 71 32 17 83",
    "sg:postcode":"6020",
    "sg:province":"Hainaut",
    "wof:name":"M. Gouti\u00c8re",
    "wof:placetype":"venue"
},
  "geometry": {"coordinates":[4.429664135,50.4124717712],"type":"Point"}
}