{
  "type": "Feature",
  "properties": {
    "addr:full":"Rechtstraat 2 Lochristi Oost-Vlaanderen 9080",
    "addr:housenumber":"2",
    "addr:postcode":"9080",
    "addr:street":"Rechtstraat",
    "iso:country":"BE",
    "sg:address":"Rechtstraat 2",
    "sg:city":"Lochristi",
    "sg:orig_category":"Pain, p\u00e2tisseries and confiseries",
    "sg:phone":"+32 9 355 65 53",
    "sg:postcode":"9080",
    "sg:province":"Oost-Vlaanderen",
    "wof:name":"Bakkerij De Zwaluw",
    "wof:placetype":"venue"
},
  "geometry": {"coordinates":[3.8544380665,51.1303329468],"type":"Point"}
}