{
  "type": "Feature",
  "properties": {
    "iso:country":"BE",
    "sg:address":"Dorpsstraat 2",
    "sg:city":"Zingem",
    "sg:orig_category":"Instituts de beaut\u00e9",
    "sg:phone":"+32 9 384 55 66",
    "sg:postcode":"9750",
    "sg:province":"Oost-Vlaanderen",
    "wof:name":"Ann Van Parijs",
    "wof:placetype":"venue"
},
  "geometry": {"coordinates":[3.6527769566,50.9043426514],"type":"Point"}
}