{
  "type": "Feature",
  "properties": {
    "iso:country":"BE",
    "sg:address":"Belsenakestraat 1",
    "sg:city":"Herent",
    "sg:classifiers":[
        {
            "category":"Shopping",
            "subcategory":"Pets & Pet Supplies",
            "type":"Retail Goods"
        }
    ],
    "sg:phone":"+32 16 29 12 33",
    "sg:postcode":"3020",
    "sg:province":"Vlaams-Brabant",
    "sg:tags":[
        "shop",
        "-"
    ],
    "wof:name":"Squama",
    "wof:placetype":"venue"
},
  "geometry": {"coordinates":[4.6745867729,50.9114112854],"type":"Point"}
}