{
  "type": "Feature",
  "properties": {
    "iso:country":"BE",
    "sg:address":"Rue Des H\u00e9ros 9",
    "sg:city":"Remicourt (momalle)",
    "sg:classifiers":[
        {
            "category":"Farming",
            "subcategory":"Livestock Farm",
            "type":"Manufacturing & Wholesale Goods"
        }
    ],
    "sg:phone":"+32 4 250 11 52",
    "sg:postcode":"4350",
    "sg:province":"Li\u00e8ge",
    "sg:tags":[
        "buyer"
    ],
    "wof:name":"Volont O",
    "wof:placetype":"venue"
},
  "geometry": {"coordinates":[5.3702578545,50.6844902039],"type":"Point"}
}