{
  "type": "Feature",
  "properties": {
    "iso:country":"BE",
    "sg:address":"Rue De L'eglise 5",
    "sg:city":"Beloeil",
    "sg:orig_category":"Artiesten and kunstenaars",
    "sg:phone":"+32 69 57 50 89",
    "sg:postcode":"7971",
    "sg:province":"Hainaut",
    "wof:name":"Surquin",
    "wof:placetype":"venue"
},
  "geometry": {"coordinates":[3.6467080116,50.5387306213],"type":"Point"}
}