{
  "type": "Feature",
  "properties": {
    "addr:full":"Rue De La Trembloie 12 Meix-devant-virton Luxembourg 6769",
    "addr:housenumber":"12",
    "addr:postcode":"6769",
    "addr:street":"Rue De La Trembloie",
    "iso:country":"BE",
    "sg:address":"Rue De La Trembloie 12",
    "sg:city":"Meix-devant-virton",
    "sg:orig_category":"Artistes ind\u00e9pendants",
    "sg:phone":"+32 63 57 07 18",
    "sg:postcode":"6769",
    "sg:province":"Luxembourg",
    "wof:name":"Nadine Calande",
    "wof:placetype":"venue"
},
  "geometry": {"coordinates":[5.4782829285,49.6070137024],"type":"Point"}
}