{
  "type": "Feature",
  "properties": {
    "addr:full":"Rue Neuve 74 Charleroi Hainaut 6000",
    "addr:housenumber":"74",
    "addr:postcode":"6000",
    "addr:street":"Rue Neuve;Hainaut",
    "iso:country":"BE",
    "sg:address":"Rue Neuve 74",
    "sg:city":"Charleroi",
    "sg:classifiers":[
        {
            "category":"Shopping",
            "subcategory":"Clothing, Apparel, & Fashions",
            "type":"Retail Goods"
        }
    ],
    "sg:phone":"+32 71 31 13 69",
    "sg:postcode":"6000",
    "sg:province":"Hainaut",
    "sg:tags":[
        "boutique"
    ],
    "wof:name":"J F R",
    "wof:placetype":"venue"
},
  "geometry": {"coordinates":[4.4459881783,50.413936615],"type":"Point"}
}