{
  "type": "Feature",
  "properties": {
    "iso:country":"BE",
    "sg:address":"Hulstersestraat 13",
    "sg:city":"Wielsbeke (ooigem)",
    "sg:classifiers":[
        {
            "category":"Manufacturing",
            "subcategory":"Metals",
            "type":"Manufacturing & Wholesale Goods"
        }
    ],
    "sg:phone":"+32 56 66 73 64",
    "sg:postcode":"8710",
    "sg:province":"West-Vlaanderen",
    "sg:tags":[
        "working"
    ],
    "wof:name":"Lampaert B",
    "wof:placetype":"venue"
},
  "geometry": {"coordinates":[3.3316400051,50.8921585083],"type":"Point"}
}