{
  "type": "Feature",
  "properties": {
    "addr:full":"Kiezelstraat 26 Hasselt Limburg 3500",
    "addr:housenumber":"26",
    "addr:postcode":"3500",
    "addr:street":"Kiezelstraat",
    "iso:country":"BE",
    "sg:address":"Kiezelstraat 26",
    "sg:city":"Hasselt",
    "sg:classifiers":[
        {
            "category":"Health Services",
            "subcategory":"Health Practitioner",
            "type":"Services"
        }
    ],
    "sg:phone":"+32 11 23 24 71",
    "sg:postcode":"3500",
    "sg:province":"Limburg",
    "sg:tags":[
        "physiotherapist"
    ],
    "wof:name":"Roeges Bernadette",
    "wof:placetype":"venue"
},
  "geometry": {"coordinates":[5.3722219467,50.9275817871],"type":"Point"}
}