{
  "type": "Feature",
  "properties": {
    "addr:full":"Hoogstraat 52 Oostrozebeke West-Vlaanderen 8780",
    "addr:housenumber":"52",
    "addr:postcode":"8780",
    "addr:street":"Hoogstraat",
    "iso:country":"BE",
    "sg:address":"Hoogstraat 52",
    "sg:city":"Oostrozebeke",
    "sg:classifiers":[
        {
            "category":"Fast Food",
            "type":"Food & Drink"
        }
    ],
    "sg:phone":"+32 56 66 93 28",
    "sg:postcode":"8780",
    "sg:province":"West-Vlaanderen",
    "sg:tags":[
        "\u00c0",
        "restaurants",
        "emporter",
        "restaurant"
    ],
    "wof:name":"Prinsenhof",
    "wof:placetype":"venue"
},
  "geometry": {"coordinates":[3.3309500217,50.9203224182],"type":"Point"}
}