{
  "type": "Feature",
  "properties": {
    "iso:country":"BE",
    "sg:address":"Weggevoerdenstraat 201",
    "sg:city":"Leuven",
    "sg:classifiers":[
        {
            "category":"Personal",
            "subcategory":"Beauty Salon",
            "type":"Services"
        }
    ],
    "sg:phone":"+32 16 44 55 65",
    "sg:postcode":"3012",
    "sg:province":"Vlaams-Brabant",
    "sg:tags":[
        "de",
        "coiffure"
    ],
    "wof:name":"Martine",
    "wof:placetype":"venue"
},
  "geometry": {"coordinates":[4.7076601982,50.9254798889],"type":"Point"}
}