{
  "type": "Feature",
  "properties": {
    "addr:full":"Place De La Gare Quievrain Hainaut 7380",
    "addr:postcode":"7380",
    "addr:street":"Place De La Gare Quievrain Hainaut",
    "iso:country":"BE",
    "sg:address":"Place De La Gare",
    "sg:city":"Quievrain",
    "sg:orig_category":"Transports ferroviaires",
    "sg:phone":"+32 65 45 70 29",
    "sg:postcode":"7380",
    "sg:province":"Hainaut",
    "wof:name":"Gare De Qui\u00c9vrain",
    "wof:placetype":"venue"
},
  "geometry": {"coordinates":[3.6861419678,50.4095878601],"type":"Point"}
}