{
  "type": "Feature",
  "properties": {
    "addr:full":"Martelarenplein 6 Leuven Vlaams-Brabant 3000",
    "addr:housenumber":"6",
    "addr:postcode":"3000",
    "addr:street":"Martelarenplein",
    "iso:country":"BE",
    "sg:address":"Martelarenplein 6",
    "sg:city":"Leuven",
    "sg:classifiers":[
        {
            "category":"Travel",
            "subcategory":"Hotels & Motels",
            "type":"Entertainment"
        }
    ],
    "sg:phone":"+32 16 22 12 52",
    "sg:postcode":"3000",
    "sg:province":"Vlaams-Brabant",
    "wof:name":"La Royale",
    "wof:placetype":"venue"
},
  "geometry": {"coordinates":[4.7140622139,50.8809623718],"type":"Point"}
}