{
  "type": "Feature",
  "properties": {
    "iso:country":"BE",
    "sg:address":"Krekelstraat 57a",
    "sg:city":"Ingelmunster",
    "sg:classifiers":[
        {
            "category":"Farming",
            "subcategory":"Crops",
            "type":"Manufacturing & Wholesale Goods"
        }
    ],
    "sg:phone":"+32 51 48 69 43",
    "sg:postcode":"8770",
    "sg:province":"West-Vlaanderen",
    "sg:tags":[
        "vegetable",
        "fruit",
        "-",
        "grower"
    ],
    "wof:name":"Deceuninck",
    "wof:placetype":"venue"
},
  "geometry": {"coordinates":[3.2765610218,50.9264678955],"type":"Point"}
}