{
  "type": "Feature",
  "properties": {
    "addr:full":"Rue De La Fraternit\u00e9 4 Bruxelles (schaerbeek) Bruxelles-Capitale 1030",
    "addr:housenumber":"4",
    "addr:postcode":"1030",
    "addr:street":"Rue De La Fraternite\u0301",
    "iso:country":"BE",
    "sg:address":"Rue De La Fraternit\u00e9 4",
    "sg:city":"Bruxelles (schaerbeek)",
    "sg:classifiers":[
        {
            "category":"Professional",
            "subcategory":"Accounting & Tax Preparation",
            "type":"Services"
        }
    ],
    "sg:phone":"+32 2 217 44 53",
    "sg:postcode":"1030",
    "sg:province":"Bruxelles-Capitale",
    "sg:tags":[
        "accountant"
    ],
    "wof:name":"Sano L",
    "wof:placetype":"venue"
},
  "geometry": {"coordinates":[4.3635840416,50.8604125977],"type":"Point"}
}