{
  "type": "Feature",
  "properties": {
    "iso:country":"BE",
    "sg:address":"Dorpsstraat 64",
    "sg:city":"Heusden-zolder (zolder)",
    "sg:classifiers":[
        {
            "category":"Home & Garden",
            "subcategory":"Building Materials",
            "type":"Retail Goods"
        }
    ],
    "sg:phone":"+32 11 53 86 96",
    "sg:postcode":"3550",
    "sg:province":"Limburg",
    "sg:tags":[
        "article",
        "-",
        "do-it-yourself"
    ],
    "wof:name":"Handig Handje ('t)",
    "wof:placetype":"venue"
},
  "geometry": {"coordinates":[5.3149580956,51.0231285095],"type":"Point"}
}