{
  "type": "Feature",
  "properties": {
    "iso:country":"BE",
    "sg:address":"Rue Godefroid 35",
    "sg:city":"Namur",
    "sg:orig_category":"Cr\u00e9dits divers",
    "sg:postcode":"5000",
    "sg:province":"Namur",
    "wof:name":"Bancontact-mister Cash",
    "wof:placetype":"venue"
},
  "geometry": {"coordinates":[4.8623270988,50.4675483704],"type":"Point"}
}