{
  "type": "Feature",
  "properties": {
    "addr:full":"Brugstraat 194 Aalter Oost-Vlaanderen 9880",
    "addr:housenumber":"194",
    "addr:postcode":"9880",
    "addr:street":"Brugstraat",
    "iso:country":"BE",
    "sg:address":"Brugstraat 194",
    "sg:city":"Aalter",
    "sg:classifiers":[
        {
            "category":"Retail",
            "subcategory":"Auto Repair",
            "type":"Services"
        }
    ],
    "sg:phone":"+32 9 374 57 89",
    "sg:postcode":"9880",
    "sg:province":"Oost-Vlaanderen",
    "sg:tags":[
        "garage"
    ],
    "wof:name":"Vanhauwere Marc Nv",
    "wof:placetype":"venue"
},
  "geometry": {"coordinates":[3.4357049465,51.1048164368],"type":"Point"}
}