{
  "type": "Feature",
  "properties": {
    "addr:full":"Balgerhoeke 85 Eeklo Oost-Vlaanderen 9900",
    "addr:housenumber":"85",
    "addr:postcode":"9900",
    "addr:street":"Balgerhoeke",
    "iso:country":"BE",
    "sg:address":"Balgerhoeke 85",
    "sg:city":"Eeklo",
    "sg:orig_category":"Magasins sp\u00e9cialis\u00e9s. Rev\u00eatements de sols and murs",
    "sg:phone":"+32 9 377 22 62",
    "sg:postcode":"9900",
    "sg:province":"Oost-Vlaanderen",
    "wof:name":"V.d.braembussche-goossens",
    "wof:placetype":"venue"
},
  "geometry": {"coordinates":[3.5174279213,51.2035331726],"type":"Point"}
}