{
  "type": "Feature",
  "properties": {
    "addr:full":"Burg De Lausnaystraat 38 Berlare Oost-Vlaanderen 9290",
    "addr:housenumber":"38",
    "addr:postcode":"9290",
    "addr:street":"Lausnaystraat",
    "iso:country":"BE",
    "sg:address":"Burg De Lausnaystraat 38",
    "sg:city":"Berlare",
    "sg:orig_category":"Belastingconsulenten Diverse juridische dienstverlening",
    "sg:phone":"+32 9 367 52 95",
    "sg:postcode":"9290",
    "sg:province":"Oost-Vlaanderen",
    "wof:name":"Juracc",
    "wof:placetype":"venue"
},
  "geometry": {"coordinates":[4.005710125,51.0165214539],"type":"Point"}
}