{
  "type": "Feature",
  "properties": {
    "addr:full":"Rue Du Tombu 9 Braives Li\u00e8ge 4260",
    "addr:housenumber":"9",
    "addr:postcode":"4260",
    "addr:street":"Rue Du Tombu",
    "iso:country":"BE",
    "sg:address":"Rue Du Tombu 9",
    "sg:city":"Braives",
    "sg:orig_category":"Plomberie, chauffage and installations sanitaires",
    "sg:phone":"+32 19 69 94 84",
    "sg:postcode":"4260",
    "sg:province":"Li\u00e8ge",
    "wof:name":"Weerts",
    "wof:placetype":"venue"
},
  "geometry": {"coordinates":[5.1354298592,50.6187324524],"type":"Point"}
}