{
  "type": "Feature",
  "properties": {
    "iso:country":"BE",
    "sg:address":"Rue De La Poste 5",
    "sg:city":"Mont-saint-guibert",
    "sg:orig_category":"Elektrische installaties voor woningen",
    "sg:phone":"+32 10 65 77 89",
    "sg:postcode":"1435",
    "sg:province":"Brabant Wallon",
    "wof:name":"Victor Leglise",
    "wof:placetype":"venue"
},
  "geometry": {"coordinates":[4.6105899811,50.6378822327],"type":"Point"}
}