{
  "type": "Feature",
  "properties": {
    "iso:country":"BE",
    "sg:address":"Langestraat 73",
    "sg:city":"Zandhoven",
    "sg:orig_category":"Eleveurs de volaille",
    "sg:phone":"+32 3 484 31 23",
    "sg:postcode":"2240",
    "sg:province":"Antwerpen",
    "wof:name":"August Van Loock",
    "wof:placetype":"venue"
},
  "geometry": {"coordinates":[4.6728138924,51.2233047485],"type":"Point"}
}