{
  "type": "Feature",
  "properties": {
    "addr:full":"Avenue Misonne 23 Chatelet Hainaut 6200",
    "addr:housenumber":"23",
    "addr:postcode":"6200",
    "addr:street":"Avenue Misonne;Hainaut",
    "iso:country":"BE",
    "sg:address":"Avenue Misonne 23",
    "sg:city":"Chatelet",
    "sg:orig_category":"HERSTELLING ELEKTRISCHE HUISHOUDAPPARATEN Herstelling aan huis van elektrische huishoudapparaten",
    "sg:phone":"+32 71 38 40 97",
    "sg:postcode":"6200",
    "sg:province":"Hainaut",
    "wof:name":"Antonino Barattucci",
    "wof:placetype":"venue"
},
  "geometry": {"coordinates":[4.5225338936,50.4150314331],"type":"Point"}
}