{
  "type": "Feature",
  "properties": {
    "addr:full":"Rue De Trazegnies 2 Charleroi Hainaut 6044",
    "addr:housenumber":"2",
    "addr:postcode":"6044",
    "addr:street":"Rue De Trazegnies;Hainaut",
    "iso:country":"BE",
    "sg:address":"Rue De Trazegnies 2",
    "sg:city":"Charleroi",
    "sg:orig_category":"M\u00e9decines alternatives",
    "sg:phone":"+32 71 31 68 07",
    "sg:postcode":"6044",
    "sg:province":"Hainaut",
    "wof:name":"Ost\u00c9opathe Lebailly G.",
    "wof:placetype":"venue"
},
  "geometry": {"coordinates":[4.3657751083,50.435333252],"type":"Point"}
}