{
  "type": "Feature",
  "properties": {
    "addr:full":"Putstraat 28 Tongeren Limburg 3700",
    "addr:housenumber":"28",
    "addr:postcode":"3700",
    "addr:street":"Putstraat",
    "iso:country":"BE",
    "sg:address":"Putstraat 28",
    "sg:city":"Tongeren",
    "sg:orig_category":"Evaluation and estimation de biens immobiliers. Agences immobili\u00e8res",
    "sg:phone":"+32 12 26 37 00",
    "sg:postcode":"3700",
    "sg:province":"Limburg",
    "wof:name":"R. Jongen",
    "wof:placetype":"venue"
},
  "geometry": {"coordinates":[5.461728096,50.7790336609],"type":"Point"}
}