{
  "type": "Feature",
  "properties": {
    "iso:country":"BE",
    "sg:address":"Zwalmlaan 8-1",
    "sg:city":"Zwalm (munkzwalm)",
    "sg:classifiers":[
        {
            "category":"Professional",
            "subcategory":"Lawyer & Legal Services",
            "type":"Services"
        }
    ],
    "sg:phone":"+32 55 49 97 97",
    "sg:postcode":"9630",
    "sg:province":"Oost-Vlaanderen",
    "wof:name":"Eeckhout A",
    "wof:placetype":"venue"
},
  "geometry": {"coordinates":[3.7341029644,50.8764915466],"type":"Point"}
}