{
  "type": "Feature",
  "properties": {
    "addr:full":"Rue Fran\u00e7ois-joseph Navez 91-93 Bruxelles (schaerbeek) Bruxelles-Capitale 1030",
    "addr:housenumber":"91-93",
    "addr:postcode":"1030",
    "addr:street":"Rue Franc\u0327Ois-Joseph Navez",
    "iso:country":"BE",
    "sg:address":"Rue Fran\u00e7ois-joseph Navez 91-93",
    "sg:city":"Bruxelles (schaerbeek)",
    "sg:classifiers":[
        {
            "category":"Military Area",
            "subcategory":"Restricted Area",
            "type":"Public Place"
        }
    ],
    "sg:phone":"+32 2 216 91 00",
    "sg:postcode":"1030",
    "sg:province":"Bruxelles-Capitale",
    "sg:tags":[
        "map",
        "plan"
    ],
    "wof:name":"De Rouck (cartographie)",
    "wof:placetype":"venue"
},
  "geometry": {"coordinates":[4.3732018471,50.8723716736],"type":"Point"}
}