{
  "type": "Feature",
  "properties": {
    "addr:full":"Sint-bernardusstraat 136 Sint-gillis/saint-gilles Bruxelles-Capitale 1060",
    "addr:housenumber":"136",
    "addr:postcode":"1060",
    "addr:street":"Sint-Bernardusstraat",
    "iso:country":"BE",
    "sg:address":"Sint-bernardusstraat 136",
    "sg:city":"Sint-gillis/saint-gilles",
    "sg:orig_category":"Dierenartsen",
    "sg:phone":"+32 2 538 81 63",
    "sg:postcode":"1060",
    "sg:province":"Bruxelles-Capitale",
    "wof:name":"Vincent Charpentier",
    "wof:placetype":"venue"
},
  "geometry": {"coordinates":[4.3509168625,50.8263931274],"type":"Point"}
}