{
  "type": "Feature",
  "properties": {
    "addr:full":"Rue Mayeurmont 26 Ecaussinnes Hainaut 7190",
    "addr:housenumber":"26",
    "addr:postcode":"7190",
    "addr:street":"Rue Mayeurmont;Hainaut",
    "iso:country":"BE",
    "sg:address":"Rue Mayeurmont 26",
    "sg:city":"Ecaussinnes",
    "sg:orig_category":"Drogueries",
    "sg:phone":"+32 67 44 39 98",
    "sg:postcode":"7190",
    "sg:province":"Hainaut",
    "wof:name":"M.l.computer",
    "wof:placetype":"venue"
},
  "geometry": {"coordinates":[4.1688580513,50.565990448],"type":"Point"}
}