{
  "type": "Feature",
  "properties": {
    "addr:full":"Place Reine Astrid 24 Dinant Namur 5500",
    "addr:housenumber":"24",
    "addr:postcode":"5500",
    "addr:street":"Place Reine Astrid",
    "iso:country":"BE",
    "sg:address":"Place Reine Astrid 24",
    "sg:city":"Dinant",
    "sg:classifiers":[
        {
            "category":"Bars & Pubs",
            "type":"Food & Drink"
        }
    ],
    "sg:phone":"+32 82 22 96 81",
    "sg:postcode":"5500",
    "sg:province":"Namur",
    "sg:tags":[
        "tavern"
    ],
    "wof:name":"Bayard (le)",
    "wof:placetype":"venue"
},
  "geometry": {"coordinates":[4.9121999741,50.2605781555],"type":"Point"}
}