{
  "type": "Feature",
  "properties": {
    "addr:full":"Cyriel Buyssestraat 41 Nevele Oost-Vlaanderen 9850",
    "addr:housenumber":"41",
    "addr:postcode":"9850",
    "addr:street":"Cyriel Buyssestraat",
    "iso:country":"BE",
    "sg:address":"Cyriel Buyssestraat 41",
    "sg:city":"Nevele",
    "sg:classifiers":[
        {
            "category":"Professional",
            "subcategory":"Art Services",
            "type":"Services"
        }
    ],
    "sg:phone":"+32 9 371 98 92",
    "sg:postcode":"9850",
    "sg:province":"Oost-Vlaanderen",
    "sg:tags":[
        "-",
        "painter",
        "artist"
    ],
    "wof:name":"Declercq G",
    "wof:placetype":"venue"
},
  "geometry": {"coordinates":[3.5460970402,51.0319290161],"type":"Point"}
}