{
  "type": "Feature",
  "properties": {
    "addr:full":"Rue Du Camp 2 Bouillon Luxembourg 6834",
    "addr:housenumber":"2",
    "addr:postcode":"6834",
    "addr:street":"Rue Du Camp",
    "iso:country":"BE",
    "sg:address":"Rue Du Camp 2",
    "sg:city":"Bouillon",
    "sg:orig_category":"Rundveehouders",
    "sg:phone":"+32 61 46 62 21",
    "sg:postcode":"6834",
    "sg:province":"Luxembourg",
    "wof:name":"Nemery-husson & Nemery P.",
    "wof:placetype":"venue"
},
  "geometry": {"coordinates":[5.1092801094,49.8381462097],"type":"Point"}
}