{
  "type": "Feature",
  "properties": {
    "addr:full":"Rue De La R\u00c9gence 5 Baelen/baelen Li\u00e8ge 4837",
    "addr:housenumber":"5",
    "addr:postcode":"4837",
    "addr:street":"Rue De La Re\u0301Gence",
    "iso:country":"BE",
    "sg:address":"Rue De La R\u00c9gence 5",
    "sg:city":"Baelen/baelen",
    "sg:classifiers":[
        {
            "category":"Fast Food",
            "type":"Food & Drink"
        }
    ],
    "sg:phone":"+32 87 76 46 61",
    "sg:postcode":"4837",
    "sg:province":"Li\u00e8ge",
    "sg:tags":[
        "\u00c0",
        "emporter",
        "restaurants"
    ],
    "wof:name":"Friterie Marguerite",
    "wof:placetype":"venue"
},
  "geometry": {"coordinates":[5.9706897736,50.6305351257],"type":"Point"}
}