{
  "type": "Feature",
  "properties": {
    "addr:full":"Cours Amarante 8 Sint-pieters-woluwe/woluwe-saint-pierre Bruxelles-Capitale 1150",
    "addr:housenumber":"8",
    "addr:postcode":"1150",
    "addr:street":"Cours Amarante;/",
    "iso:country":"BE",
    "sg:address":"Cours Amarante 8",
    "sg:city":"Sint-pieters-woluwe/woluwe-saint-pierre",
    "sg:classifiers":[
        {
            "category":"Personal",
            "subcategory":"Beauty Salon",
            "type":"Services"
        }
    ],
    "sg:phone":"+32 2 770 40 75",
    "sg:postcode":"1150",
    "sg:province":"Bruxelles-Capitale",
    "sg:tags":[
        "de",
        "coiffure"
    ],
    "wof:name":"Serre \u00c0 Boucles (la)",
    "wof:placetype":"venue"
},
  "geometry": {"coordinates":[4.4402451515,50.8334083557],"type":"Point"}
}