{
  "type": "Feature",
  "properties": {
    "addr:full":"Herentalsebaan 645 Box 4 Wommelgem Antwerpen 2160",
    "addr:housenumber":"645;4",
    "addr:postcode":"2160",
    "addr:street":"Herentalsebaan;Box",
    "iso:country":"BE",
    "sg:address":"Herentalsebaan 645 Box 4",
    "sg:city":"Wommelgem",
    "sg:classifiers":[
        {
            "category":"Professional",
            "subcategory":"Accounting & Tax Preparation",
            "type":"Services"
        }
    ],
    "sg:phone":"+32 3 355 50 90",
    "sg:postcode":"2160",
    "sg:province":"Antwerpen",
    "sg:tags":[
        "accountant"
    ],
    "wof:name":"Vmw Accountants Bvba",
    "wof:placetype":"venue"
},
  "geometry": {"coordinates":[4.52059412,51.1975784302],"type":"Point"}
}