{
  "type": "Feature",
  "properties": {
    "iso:country":"BE",
    "sg:address":"Hezewijk 8be",
    "sg:city":"Olen",
    "sg:orig_category":"Epiceries",
    "sg:phone":"+32 14 26 79 86",
    "sg:postcode":"2250",
    "sg:province":"Antwerpen",
    "wof:name":"Walter Caers",
    "wof:placetype":"venue"
},
  "geometry": {"coordinates":[4.8446378708,51.1457557678],"type":"Point"}
}