{
  "type": "Feature",
  "properties": {
    "addr:full":"Smaragdlaan 56b6 Schaarbeek/schaerbeek Bruxelles-Capitale 1030",
    "addr:housenumber":"56b6",
    "addr:postcode":"1030",
    "addr:street":"Smaragdlaan",
    "iso:country":"BE",
    "sg:address":"Smaragdlaan 56b6",
    "sg:city":"Schaarbeek/schaerbeek",
    "sg:orig_category":"Fotografen and fotostudio's",
    "sg:phone":"+32 2 732 32 97",
    "sg:postcode":"1030",
    "sg:province":"Bruxelles-Capitale",
    "wof:name":"Eleonore Lequime",
    "wof:placetype":"venue"
},
  "geometry": {"coordinates":[4.3985328674,50.8528251648],"type":"Point"}
}