{
  "type": "Feature",
  "properties": {
    "addr:full":"Nieuwstraat 1 Brecht Antwerpen 2960",
    "addr:housenumber":"1",
    "addr:postcode":"2960",
    "addr:street":"Nieuwstraat",
    "iso:country":"BE",
    "sg:address":"Nieuwstraat 1",
    "sg:city":"Brecht",
    "sg:orig_category":"Artsen and specialisten",
    "sg:phone":"+32 3 313 83 09",
    "sg:postcode":"2960",
    "sg:province":"Antwerpen",
    "wof:name":"J. Maes",
    "wof:placetype":"venue"
},
  "geometry": {"coordinates":[4.6780161858,51.3465805054],"type":"Point"}
}