{
  "type": "Feature",
  "properties": {
    "addr:full":"Rue Du Ri D'asse 3 Dalhem (mortroux) Li\u00e8ge 4607",
    "addr:housenumber":"3",
    "addr:postcode":"4607",
    "addr:street":"Rue Du Ri D'Asse",
    "iso:country":"BE",
    "sg:address":"Rue Du Ri D'asse 3",
    "sg:city":"Dalhem (mortroux)",
    "sg:classifiers":[
        {
            "category":"Building & Trades",
            "subcategory":"Construction",
            "type":"Services"
        }
    ],
    "sg:phone":"+32 4 376 71 78",
    "sg:postcode":"4607",
    "sg:province":"Li\u00e8ge",
    "sg:tags":[
        "carpenter"
    ],
    "wof:name":"Boussingault P",
    "wof:placetype":"venue"
},
  "geometry": {"coordinates":[5.7506370544,50.7140274048],"type":"Point"}
}