{
  "type": "Feature",
  "properties": {
    "iso:country":"BE",
    "sg:address":"Rue Les Croupets 11",
    "sg:city":"Amay (ombret-rawsa)",
    "sg:classifiers":[
        {
            "category":"Professional",
            "subcategory":"Business Services",
            "type":"Services"
        }
    ],
    "sg:phone":"+32 85 31 43 61",
    "sg:postcode":"4540",
    "sg:province":"Li\u00e8ge",
    "sg:tags":[
        "firm"
    ],
    "wof:name":"Buro Service les Croupets",
    "wof:placetype":"venue"
},
  "geometry": {"coordinates":[5.3373198509,50.5432510376],"type":"Point"}
}