{
  "type": "Feature",
  "properties": {
    "iso:country":"BE",
    "sg:address":"Dorpstraat 158",
    "sg:city":"Stabroek",
    "sg:orig_category":"Huisdieren and benodigdheden Royal Canin",
    "sg:phone":"+32 3 568 63 92",
    "sg:postcode":"2940",
    "sg:province":"Antwerpen",
    "wof:name":"Cassimon-fissers",
    "wof:placetype":"venue"
},
  "geometry": {"coordinates":[4.3723940849,51.334980011],"type":"Point"}
}