{
  "type": "Feature",
  "properties": {
    "iso:country":"BE",
    "sg:address":"Hogeweg 58",
    "sg:city":"Gent",
    "sg:classifiers":[
        {
            "category":"Building & Trades",
            "subcategory":"Plumbing",
            "type":"Services"
        }
    ],
    "sg:phone":"+32 9 251 62 22",
    "sg:postcode":"9000",
    "sg:province":"Oost-Vlaanderen",
    "sg:tags":[
        "repair",
        "mainten",
        "-",
        "central",
        "heating"
    ],
    "wof:name":"Heatcare Warmte & Techniek",
    "wof:placetype":"venue"
},
  "geometry": {"coordinates":[3.7470710278,51.0737876892],"type":"Point"}
}