{
  "type": "Feature",
  "properties": {
    "iso:country":"BE",
    "sg:address":"Rue Du Centre 73",
    "sg:city":"Braives (latinne)",
    "sg:classifiers":[
        {
            "category":"Retail",
            "subcategory":"Event Space",
            "type":"Services"
        }
    ],
    "sg:phone":"+32 496 72 50 57",
    "sg:postcode":"4261",
    "sg:province":"Li\u00e8ge",
    "sg:tags":[
        "rental",
        "-",
        "hall"
    ],
    "wof:name":"Ferme Des Capucines (la)",
    "wof:placetype":"venue"
},
  "geometry": {"coordinates":[5.1635260582,50.6246261597],"type":"Point"}
}