{
  "type": "Feature",
  "properties": {
    "iso:country":"BE",
    "sg:address":"Rue Saint-roch 22",
    "sg:city":"Houyet",
    "sg:orig_category":"Slagers",
    "sg:phone":"+32 82 66 63 58",
    "sg:postcode":"5560",
    "sg:province":"Namur",
    "wof:name":"Emile Stienon",
    "wof:placetype":"venue"
},
  "geometry": {"coordinates":[5.0053391457,50.1878929138],"type":"Point"}
}