{
  "type": "Feature",
  "properties": {
    "addr:full":"Tolstraat 83 Antwerpen Antwerpen 2000",
    "addr:housenumber":"83",
    "addr:postcode":"2000",
    "addr:street":"Tolstraat",
    "iso:country":"BE",
    "sg:address":"Tolstraat 83",
    "sg:city":"Antwerpen",
    "sg:classifiers":[
        {
            "category":"Professional",
            "subcategory":"Lawyer & Legal Services",
            "type":"Services"
        }
    ],
    "sg:phone":"+32 3 237 42 42",
    "sg:postcode":"2000",
    "sg:province":"Antwerpen",
    "wof:name":"Greeve-van Goethem Advocatenassociatie",
    "wof:placetype":"venue"
},
  "geometry": {"coordinates":[4.4015002251,51.2092285156],"type":"Point"}
}