{
  "type": "Feature",
  "properties": {
    "iso:country":"BE",
    "sg:address":"Vlasgaard 7",
    "sg:city":"Zoersel (halle)",
    "sg:classifiers":[
        {
            "category":"Structure",
            "subcategory":"Office Building",
            "type":"Public Place"
        }
    ],
    "sg:phone":"+32 3 385 01 34",
    "sg:postcode":"2980",
    "sg:province":"Antwerpen",
    "sg:tags":[
        "drawing"
    ],
    "wof:name":"Cotap Bvba",
    "wof:placetype":"venue"
},
  "geometry": {"coordinates":[4.6417479515,51.2379264832],"type":"Point"}
}