{
  "type": "Feature",
  "properties": {
    "iso:country":"BE",
    "sg:address":"Leemstraat 11a",
    "sg:city":"Sint-katelijne-waver (onze-lieve-vrouw-waver)",
    "sg:classifiers":[
        {
            "category":"Health Services",
            "subcategory":"Nursing And Care Facility",
            "type":"Services"
        }
    ],
    "sg:phone":"+32 15 76 79 80",
    "sg:postcode":"2861",
    "sg:province":"Antwerpen",
    "sg:tags":[
        "home",
        "rest"
    ],
    "wof:name":"Rusthuis Huyze-de Pauw Vzw",
    "wof:placetype":"venue"
},
  "geometry": {"coordinates":[4.5807881355,51.0613327026],"type":"Point"}
}