{
  "type": "Feature",
  "properties": {
    "addr:full":"Slagmolenstraat 14 Merksplas Antwerpen 2330",
    "addr:housenumber":"14",
    "addr:postcode":"2330",
    "addr:street":"Slagmolenstraat",
    "iso:country":"BE",
    "sg:address":"Slagmolenstraat 14",
    "sg:city":"Merksplas",
    "sg:classifiers":[
        {
            "category":"Professional",
            "subcategory":"Art Services",
            "type":"Services"
        }
    ],
    "sg:phone":"+32 14 63 55 32",
    "sg:postcode":"2330",
    "sg:province":"Antwerpen",
    "sg:tags":[
        "automobile",
        "transit",
        "-",
        "export",
        "import"
    ],
    "wof:name":"Autotransportbedrijf Bvba",
    "wof:placetype":"venue"
},
  "geometry": {"coordinates":[4.8545260429,51.3703422546],"type":"Point"}
}