{
  "type": "Feature",
  "properties": {
    "iso:country":"BE",
    "sg:address":"Statiestraat 80",
    "sg:city":"Hemiksem",
    "sg:classifiers":[
        {
            "category":"Education",
            "subcategory":"Music School",
            "type":"Public Place"
        }
    ],
    "sg:phone":"+32 477 52 74 31",
    "sg:postcode":"2620",
    "sg:province":"Antwerpen",
    "sg:tags":[
        "-",
        "teacher",
        "private"
    ],
    "wof:name":"Fontyn H",
    "wof:placetype":"venue"
},
  "geometry": {"coordinates":[4.3382401466,51.1361503601],"type":"Point"}
}