{
  "type": "Feature",
  "properties": {
    "iso:country":"BE",
    "sg:address":"Chauss\u00e9e De Haecht 1369",
    "sg:city":"Bruxelles",
    "sg:classifiers":[
        {
            "category":"Utilities",
            "subcategory":"Refuse",
            "type":"Services"
        }
    ],
    "sg:phone":"+32 2 215 98 75",
    "sg:postcode":"1130",
    "sg:province":"Bruxelles-Capitale",
    "sg:tags":[
        "removal"
    ],
    "wof:name":"Servaes Henri & Fils",
    "wof:placetype":"venue"
},
  "geometry": {"coordinates":[4.4181041718,50.8825836182],"type":"Point"}
}