{
  "type": "Feature",
  "properties": {
    "addr:full":"Rue Albert 1er 58 Peruwelz Hainaut 7600",
    "addr:housenumber":"58",
    "addr:postcode":"7600",
    "addr:street":"Rue Albert 1Er;Hainaut",
    "iso:country":"BE",
    "sg:address":"Rue Albert 1er 58",
    "sg:city":"Peruwelz",
    "sg:orig_category":"Boucheries",
    "sg:phone":"+32 69 77 26 18",
    "sg:postcode":"7600",
    "sg:province":"Hainaut",
    "wof:name":"Boucherie Bruxelloise",
    "wof:placetype":"venue"
},
  "geometry": {"coordinates":[3.5906410217,50.5079841614],"type":"Point"}
}