{
  "type": "Feature",
  "properties": {
    "addr:full":"Marktstraat 12 Wielsbeke West-Vlaanderen 8710",
    "addr:housenumber":"12",
    "addr:postcode":"8710",
    "addr:street":"Marktstraat;West-Vlaanderen",
    "iso:country":"BE",
    "sg:address":"Marktstraat 12",
    "sg:city":"Wielsbeke",
    "sg:orig_category":"Boucheries",
    "sg:phone":"+32 56 66 64 50",
    "sg:postcode":"8710",
    "sg:province":"West-Vlaanderen",
    "wof:name":"Luc Seyns",
    "wof:placetype":"venue"
},
  "geometry": {"coordinates":[3.3688440323,50.9086952209],"type":"Point"}
}