{
  "type": "Feature",
  "properties": {
    "addr:full":"Sint-jansstraat 124 Herentals Antwerpen 2200",
    "addr:housenumber":"124",
    "addr:postcode":"2200",
    "addr:street":"Sint-Jansstraat",
    "iso:country":"BE",
    "sg:address":"Sint-jansstraat 124",
    "sg:city":"Herentals",
    "sg:classifiers":[
        {
            "category":"Education",
            "subcategory":"School",
            "type":"Public Place"
        }
    ],
    "sg:phone":"+32 14 21 84 85",
    "sg:postcode":"2200",
    "sg:province":"Antwerpen",
    "sg:tags":[
        "primary"
    ],
    "wof:name":"Scheppers",
    "wof:placetype":"venue"
},
  "geometry": {"coordinates":[4.8319778442,51.1733169556],"type":"Point"}
}