{
  "type": "Feature",
  "properties": {
    "iso:country":"BE",
    "sg:address":"Werfweg 15",
    "sg:city":"Holsbeek",
    "sg:orig_category":"Installation \u00e9lectrique r\u00e9sidentielle. Plomberie, chauffage and installations sanitaires",
    "sg:phone":"+32 16 62 25 64",
    "sg:postcode":"3220",
    "sg:province":"Vlaams-Brabant",
    "wof:name":"Van Nerum",
    "wof:placetype":"venue"
},
  "geometry": {"coordinates":[4.82107687,50.9307518005],"type":"Point"}
}