{
  "type": "Feature",
  "properties": {
    "iso:country":"BE",
    "sg:address":"Gentsesteenweg 340",
    "sg:city":"Asse",
    "sg:orig_category":"Sportclubs",
    "sg:phone":"+32 2 452 97 77",
    "sg:postcode":"1730",
    "sg:province":"Vlaams-Brabant",
    "wof:name":"Verenigde Liefhebbers",
    "wof:placetype":"venue"
},
  "geometry": {"coordinates":[4.157889843,50.9189071655],"type":"Point"}
}