{
  "type": "Feature",
  "properties": {
    "addr:full":"Rue Roberts Jones 77 - Brussels Bruxelles-Capitale 1180",
    "addr:housenumber":"77",
    "addr:postcode":"1180",
    "addr:street":"Rue Roberts Jones",
    "iso:country":"BE",
    "sg:address":"Rue Roberts Jones 77 -",
    "sg:city":"Brussels",
    "sg:classifiers":[
        {
            "category":"Professional",
            "subcategory":"Art Services",
            "type":"Services"
        }
    ],
    "sg:phone":"+32 2 343 00 20",
    "sg:postcode":"1180",
    "sg:province":"Bruxelles-Capitale",
    "sg:tags":[
        "export-import"
    ],
    "wof:name":"Cuba Embassy",
    "wof:placetype":"venue"
},
  "geometry": {"coordinates":[4.3524651527,50.806224823],"type":"Point"}
}