{
  "type": "Feature",
  "properties": {
    "iso:country":"BE",
    "sg:address":"Rue De Cond\u00c9 54",
    "sg:city":"Saint-ghislain",
    "sg:orig_category":"Pain, p\u00e2tisseries and confiseries",
    "sg:phone":"+32 65 64 13 68",
    "sg:postcode":"7331",
    "sg:province":"Hainaut",
    "wof:name":"Leclercq Fr\u00c8res",
    "wof:placetype":"venue"
},
  "geometry": {"coordinates":[3.8259539604,50.4804382324],"type":"Point"}
}