{
  "type": "Feature",
  "properties": {
    "iso:country":"BE",
    "sg:address":"Walmersumstraat 1a",
    "sg:city":"Glabbeek (bunsbeek)",
    "sg:classifiers":[
        {
            "category":"Building & Trades",
            "subcategory":"Cleaning & Sanitation",
            "type":"Services"
        }
    ],
    "sg:phone":"+32 16 82 39 10",
    "sg:postcode":"3380",
    "sg:province":"Vlaams-Brabant",
    "sg:tags":[
        "equipment",
        "industrial",
        "maintenance"
    ],
    "wof:name":"Gansow-kestens Reinigingstechniek",
    "wof:placetype":"venue"
},
  "geometry": {"coordinates":[4.9438238144,50.8427238464],"type":"Point"}
}