{
  "type": "Feature",
  "properties": {
    "iso:country":"BE",
    "sg:address":"Heerweg Noord 2",
    "sg:city":"Zwijnaarde",
    "sg:orig_category":"Levering aan huis restaurants Restaurants Ruimtes voor conferenties, recepties and feesten",
    "sg:phone":"+32 9 222 42 31",
    "sg:postcode":"9052",
    "sg:province":"Oost-Vlaanderen",
    "wof:name":"Oud Gemeentehuis",
    "wof:placetype":"venue"
},
  "geometry": {"coordinates":[3.7143130302,51.0030479431],"type":"Point"}
}