{
  "type": "Feature",
  "properties": {
    "addr:full":"Ringlaan 32 Koekelare West-Vlaanderen 8680",
    "addr:housenumber":"32",
    "addr:postcode":"8680",
    "addr:street":"Ringlaan",
    "iso:country":"BE",
    "sg:address":"Ringlaan 32",
    "sg:city":"Koekelare",
    "sg:orig_category":"Entretien and r\u00e9parations de voitures. V\u00e9hicules automobiles",
    "sg:phone":"+32 51 58 06 36",
    "sg:postcode":"8680",
    "sg:province":"West-Vlaanderen",
    "wof:name":"Garage Lauwaert",
    "wof:placetype":"venue"
},
  "geometry": {"coordinates":[2.9772810936,51.0928153992],"type":"Point"}
}