{
  "type": "Feature",
  "properties": {
    "iso:country":"BE",
    "sg:address":"All\u00c9e Du Nondeux 38",
    "sg:city":"Beauraing",
    "sg:orig_category":"Artsen and specialisten",
    "sg:phone":"+32 82 71 17 13",
    "sg:postcode":"5570",
    "sg:province":"Namur",
    "wof:name":"Cath\u00c9rine Aubry",
    "wof:placetype":"venue"
},
  "geometry": {"coordinates":[4.955242157,50.1078681946],"type":"Point"}
}