{
  "type": "Feature",
  "properties": {
    "iso:country":"BE",
    "sg:address":"Rue Albert I 154",
    "sg:city":"Farciennes",
    "sg:classifiers":[
        {
            "category":"Personal",
            "subcategory":"Beauty Salon",
            "type":"Services"
        }
    ],
    "sg:phone":"+32 71 39 25 40",
    "sg:postcode":"6240",
    "sg:province":"Hainaut",
    "sg:tags":[
        "lady",
        "-",
        "hairdressing"
    ],
    "wof:name":"Jacquemin Coiffure",
    "wof:placetype":"venue"
},
  "geometry": {"coordinates":[4.5328249931,50.4235649109],"type":"Point"}
}