{
  "type": "Feature",
  "properties": {
    "iso:country":"BE",
    "sg:address":"Watervalstraat 22ba",
    "sg:city":"Ardooie",
    "sg:orig_category":"Fruits and l\u00e9gumes. Boucheries. Supermarch\u00e9s",
    "sg:phone":"+32 51 74 81 91",
    "sg:postcode":"8850",
    "sg:province":"West-Vlaanderen",
    "wof:name":"Supermarkt Devos",
    "wof:placetype":"venue"
},
  "geometry": {"coordinates":[3.2005310059,50.9837760925],"type":"Point"}
}