{
  "type": "Feature",
  "properties": {
    "addr:full":"Nerenhoek 13 Lochristi Oost-Vlaanderen 9080",
    "addr:housenumber":"13",
    "addr:postcode":"9080",
    "addr:street":"Nerenhoek",
    "iso:country":"BE",
    "sg:address":"Nerenhoek 13",
    "sg:city":"Lochristi",
    "sg:orig_category":"Elektrische installaties voor woningen",
    "sg:phone":"+32 9 355 28 08",
    "sg:postcode":"9080",
    "sg:province":"Oost-Vlaanderen",
    "wof:name":"Filip Mattan",
    "wof:placetype":"venue"
},
  "geometry": {"coordinates":[3.837501049,51.1324043274],"type":"Point"}
}