{
  "type": "Feature",
  "properties": {
    "addr:full":"Rue De Ransbeek 188 Bruxelles Bruxelles-Capitale 1120",
    "addr:housenumber":"188",
    "addr:postcode":"1120",
    "addr:street":"Rue De Ransbeek",
    "iso:country":"BE",
    "sg:address":"Rue De Ransbeek 188",
    "sg:city":"Bruxelles",
    "sg:classifiers":[
        {
            "category":"Bars & Pubs",
            "type":"Food & Drink"
        }
    ],
    "sg:phone":"+32 2 262 21 54",
    "sg:postcode":"1120",
    "sg:province":"Bruxelles-Capitale",
    "sg:tags":[
        "tavern"
    ],
    "wof:name":"Grande Ferme (la)",
    "wof:placetype":"venue"
},
  "geometry": {"coordinates":[4.3980278969,50.8984069824],"type":"Point"}
}