{
  "type": "Feature",
  "properties": {
    "addr:full":"Hufengasse 4 Eupen/eupen Li\u00e8ge 4700",
    "addr:housenumber":"4",
    "addr:postcode":"4700",
    "addr:street":"Hufengasse",
    "iso:country":"BE",
    "sg:address":"Hufengasse 4",
    "sg:city":"Eupen/eupen",
    "sg:orig_category":"Artsen and specialisten",
    "sg:phone":"+32 87 55 64 64",
    "sg:postcode":"4700",
    "sg:province":"Li\u00e8ge",
    "wof:name":"Bernard Kittel",
    "wof:placetype":"venue"
},
  "geometry": {"coordinates":[6.0297698975,50.6291999817],"type":"Point"}
}