{
  "type": "Feature",
  "properties": {
    "iso:country":"BE",
    "sg:address":"K. Deswertlaan 95",
    "sg:city":"Blankenberge",
    "sg:orig_category":"Sportclubs",
    "sg:phone":"+32 50 41 29 89",
    "sg:postcode":"8370",
    "sg:province":"West-Vlaanderen",
    "wof:name":"W.c. Havensportvrienden",
    "wof:placetype":"venue"
},
  "geometry": {"coordinates":[3.1283578873,51.307964325],"type":"Point"}
}