{
  "type": "Feature",
  "properties": {
    "addr:full":"Planetariumweg 19 Genk Limburg 3600",
    "addr:housenumber":"19",
    "addr:postcode":"3600",
    "addr:street":"Planetariumweg",
    "iso:country":"BE",
    "sg:address":"Planetariumweg 19",
    "sg:city":"Genk",
    "sg:orig_category":"Recherche en sciences physiques and naturelles. Mus\u00e9es and patrimoine culturel",
    "sg:phone":"+32 89 30 79 90",
    "sg:postcode":"3600",
    "sg:province":"Limburg",
    "wof:name":"Europlanetarium",
    "wof:placetype":"venue"
},
  "geometry": {"coordinates":[5.5350260735,50.9573173523],"type":"Point"}
}