{
  "type": "Feature",
  "properties": {
    "iso:country":"BE",
    "sg:address":"Rue Emile Vandervelde 14",
    "sg:city":"Charleroi",
    "sg:orig_category":"Tankcleaning",
    "sg:phone":"+32 71 41 06 48",
    "sg:postcode":"6000",
    "sg:province":"Hainaut",
    "wof:name":"Pluie Economique (la)",
    "wof:placetype":"venue"
},
  "geometry": {"coordinates":[4.456785202,50.4230575562],"type":"Point"}
}