{
  "type": "Feature",
  "properties": {
    "addr:full":"Rue Du Transvaal 74 Charleroi (couillet) Hainaut 6010",
    "addr:housenumber":"74",
    "addr:postcode":"6010",
    "addr:street":"Rue Du Transvaal",
    "iso:country":"BE",
    "sg:address":"Rue Du Transvaal 74",
    "sg:city":"Charleroi (couillet)",
    "sg:classifiers":[
        {
            "category":"Parking",
            "subcategory":"Bicycle",
            "type":"Transportation"
        }
    ],
    "sg:phone":"+32 71 21 44 26",
    "sg:postcode":"6010",
    "sg:province":"Hainaut",
    "sg:tags":[
        "chiropodist"
    ],
    "wof:name":"Centre De Soins Annick",
    "wof:placetype":"venue"
},
  "geometry": {"coordinates":[4.4584641457,50.3866691589],"type":"Point"}
}