{
  "type": "Feature",
  "properties": {
    "iso:country":"BE",
    "sg:address":"Av Rusatira 3",
    "sg:city":"Ganshoran",
    "sg:classifiers":[
        {
            "category":"Professional",
            "subcategory":"Advertising",
            "type":"Services"
        }
    ],
    "sg:phone":"+32 2 464 13 11",
    "sg:postcode":"1083",
    "sg:province":"Bruxelles-Capitale",
    "sg:tags":[
        "marketing",
        "medium",
        "communication"
    ],
    "wof:name":"Gfi Sa",
    "wof:placetype":"venue"
},
  "geometry": {"coordinates":[4.2962508202,50.8745574951],"type":"Point"}
}