{
  "type": "Feature",
  "properties": {
    "addr:full":"Dorpsstraat 35 Houthalen-helchteren (houthalen) Limburg 3530",
    "addr:housenumber":"35",
    "addr:postcode":"3530",
    "addr:street":"Dorpsstraat",
    "iso:country":"BE",
    "sg:address":"Dorpsstraat 35",
    "sg:city":"Houthalen-helchteren (houthalen)",
    "sg:classifiers":[
        {
            "category":"Bars & Pubs",
            "type":"Food & Drink"
        }
    ],
    "sg:phone":"+32 11 52 42 73",
    "sg:postcode":"3530",
    "sg:province":"Limburg",
    "wof:name":"Europacentrum",
    "wof:placetype":"venue"
},
  "geometry": {"coordinates":[5.372988224,51.0307655334],"type":"Point"}
}