{
  "type": "Feature",
  "properties": {
    "iso:country":"BE",
    "sg:address":"Nieuwstraat 45",
    "sg:city":"Essen",
    "sg:classifiers":[
        {
            "category":"Shopping",
            "subcategory":"Stationery & Office Supplies",
            "type":"Retail Goods"
        }
    ],
    "sg:phone":"+32 3 667 53 85",
    "sg:postcode":"2910",
    "sg:province":"Antwerpen",
    "wof:name":"Vandekeybus",
    "wof:placetype":"venue"
},
  "geometry": {"coordinates":[4.4684739113,51.4676856995],"type":"Point"}
}