{
  "type": "Feature",
  "properties": {
    "iso:country":"BE",
    "sg:address":"Place Eug\u00e8ne Keym 30a",
    "sg:city":"Bruxelles (watermael-boitsfort)",
    "sg:classifiers":[
        {
            "category":"Shopping",
            "subcategory":"Clothing, Apparel, & Fashions",
            "type":"Retail Goods"
        }
    ],
    "sg:phone":"+32 2 660 13 72",
    "sg:postcode":"1170",
    "sg:province":"Bruxelles-Capitale",
    "sg:tags":[
        "boutique"
    ],
    "wof:name":"Ni-nice",
    "wof:placetype":"venue"
},
  "geometry": {"coordinates":[4.4036831856,50.8093528748],"type":"Point"}
}