{
  "type": "Feature",
  "properties": {
    "addr:full":"Grand Place Pierre Delannoy 32 Enghien Hainaut 7850",
    "addr:housenumber":"32",
    "addr:postcode":"7850",
    "addr:street":"Grand Place Pierre Delannoy",
    "iso:country":"BE",
    "sg:address":"Grand Place Pierre Delannoy 32",
    "sg:city":"Enghien",
    "sg:classifiers":[
        {
            "category":"Restaurant",
            "type":"Food & Drink"
        }
    ],
    "sg:phone":"+32 2 395 47 89",
    "sg:postcode":"7850",
    "sg:province":"Hainaut",
    "wof:name":"Les D\u00c9lices Du Parc",
    "wof:placetype":"venue"
},
  "geometry": {"coordinates":[4.0396199226,50.6931915283],"type":"Point"}
}