{
  "type": "Feature",
  "properties": {
    "iso:country":"BE",
    "sg:address":"Rue Fanchon 187",
    "sg:city":"Sombreffe",
    "sg:orig_category":"HUISBRANDOLIE",
    "sg:phone":"+32 71 88 85 81",
    "sg:postcode":"5140",
    "sg:province":"Namur",
    "wof:name":"Didier Tourneur",
    "wof:placetype":"venue"
},
  "geometry": {"coordinates":[4.6098070145,50.5010452271],"type":"Point"}
}