{
  "type": "Feature",
  "properties": {
    "iso:country":"BE",
    "sg:address":"Avenue Foch 786",
    "sg:city":"Mons (jemappes)",
    "sg:classifiers":[
        {
            "category":"Shopping",
            "subcategory":"Clothing, Apparel, & Fashions",
            "type":"Retail Goods"
        }
    ],
    "sg:phone":"+32 65 82 45 75",
    "sg:postcode":"7012",
    "sg:province":"Hainaut",
    "sg:tags":[
        "-",
        "clothing",
        "child"
    ],
    "wof:name":"Charlotte",
    "wof:placetype":"venue"
},
  "geometry": {"coordinates":[3.8894600868,50.4481964111],"type":"Point"}
}