{
  "type": "Feature",
  "properties": {
    "iso:country":"BE",
    "sg:address":"Avelgemstraat 20",
    "sg:city":"Zwevegem",
    "sg:orig_category":"Etalage- and showroomontwerpers",
    "sg:phone":"+32 56 75 68 66",
    "sg:postcode":"8550",
    "sg:province":"West-Vlaanderen",
    "wof:name":"Linsy Lanssens",
    "wof:placetype":"venue"
},
  "geometry": {"coordinates":[3.3330080509,50.8121604919],"type":"Point"}
}