{
  "type": "Feature",
  "properties": {
    "addr:full":"Vredestraat 12 Tielt West-Vlaanderen 8700",
    "addr:housenumber":"12",
    "addr:postcode":"8700",
    "addr:street":"Vredestraat",
    "iso:country":"BE",
    "sg:address":"Vredestraat 12",
    "sg:city":"Tielt",
    "sg:orig_category":"Dranken",
    "sg:phone":"+32 51 40 34 52",
    "sg:postcode":"8700",
    "sg:province":"West-Vlaanderen",
    "wof:name":"Wijnhuis Douchy",
    "wof:placetype":"venue"
},
  "geometry": {"coordinates":[3.3276839256,50.994808197],"type":"Point"}
}