{
  "type": "Feature",
  "properties": {
    "addr:full":"Ruisbroekdorp 64 Puurs Antwerpen 2870",
    "addr:housenumber":"64",
    "addr:postcode":"2870",
    "addr:street":"Ruisbroekdorp",
    "iso:country":"BE",
    "sg:address":"Ruisbroekdorp 64",
    "sg:city":"Puurs",
    "sg:orig_category":"Epiceries",
    "sg:phone":"+32 3 886 73 47",
    "sg:postcode":"2870",
    "sg:province":"Antwerpen",
    "wof:name":"Shopwell",
    "wof:placetype":"venue"
},
  "geometry": {"coordinates":[4.3293647766,51.0871353149],"type":"Point"}
}