{
  "type": "Feature",
  "properties": {
    "addr:full":"Leedse Vroente 6 Kortenaken (kersbeek-miskom) Vlaams-Brabant 3472",
    "addr:housenumber":"6",
    "addr:postcode":"3472",
    "addr:street":"Leedse Vroente",
    "iso:country":"BE",
    "sg:address":"Leedse Vroente 6",
    "sg:city":"Kortenaken (kersbeek-miskom)",
    "sg:classifiers":[
        {
            "category":"Bakery",
            "type":"Food & Drink"
        }
    ],
    "sg:phone":"+32 16 77 04 76",
    "sg:postcode":"3472",
    "sg:province":"Vlaams-Brabant",
    "sg:tags":[
        "confectioner",
        "baker"
    ],
    "wof:name":"Boerderij De Brabander Vzw",
    "wof:placetype":"venue"
},
  "geometry": {"coordinates":[5.0113358498,50.9024925232],"type":"Point"}
}