{
  "type": "Feature",
  "properties": {
    "addr:full":"Chauss\u00e9e De Tongres 146 Juprelle (lantin) Li\u00e8ge 4450",
    "addr:housenumber":"146",
    "addr:postcode":"4450",
    "addr:street":"Chausse\u0301E De Tongres;Lantin",
    "iso:country":"BE",
    "sg:address":"Chauss\u00e9e De Tongres 146",
    "sg:city":"Juprelle (lantin)",
    "sg:classifiers":[
        {
            "category":"Manufacturing",
            "subcategory":"Furniture",
            "type":"Manufacturing & Wholesale Goods"
        }
    ],
    "sg:phone":"+32 4 263 56 98",
    "sg:postcode":"4450",
    "sg:province":"Li\u00e8ge",
    "sg:tags":[
        "juvenile",
        "-"
    ],
    "wof:name":"Juniorama",
    "wof:placetype":"venue"
},
  "geometry": {"coordinates":[5.5315198898,50.698299408],"type":"Point"}
}