{
  "type": "Feature",
  "properties": {
    "addr:full":"Lt. Dobbelaerestraat 29 Zomergem Oost-Vlaanderen 9930",
    "addr:housenumber":"29",
    "addr:postcode":"9930",
    "addr:street":"Dobbelaerestraat",
    "iso:country":"BE",
    "sg:address":"Lt. Dobbelaerestraat 29",
    "sg:city":"Zomergem",
    "sg:orig_category":"Boekhouders",
    "sg:phone":"+32 9 372 41 86",
    "sg:postcode":"9930",
    "sg:province":"Oost-Vlaanderen",
    "wof:name":"Marc De Kezel",
    "wof:placetype":"venue"
},
  "geometry": {"coordinates":[3.5591619015,51.1206245422],"type":"Point"}
}