{
  "type": "Feature",
  "properties": {
    "addr:full":"Avenue Moli\u00e8re 469 Bruxelles (ixelles) Bruxelles-Capitale 1050",
    "addr:housenumber":"469",
    "addr:postcode":"1050",
    "addr:street":"Avenue Molie\u0300Re",
    "iso:country":"BE",
    "sg:address":"Avenue Moli\u00e8re 469",
    "sg:city":"Bruxelles (ixelles)",
    "sg:classifiers":[
        {
            "category":"Government",
            "subcategory":"Embassy",
            "type":"Public Place"
        }
    ],
    "sg:phone":"+32 2 343 56 49",
    "sg:postcode":"1050",
    "sg:province":"Bruxelles-Capitale",
    "sg:tags":[
        "consulate"
    ],
    "wof:name":"Zambie",
    "wof:placetype":"venue"
},
  "geometry": {"coordinates":[4.363535881,50.8160743713],"type":"Point"}
}