{
  "type": "Feature",
  "properties": {
    "addr:full":"Blauwesteenstraat 15 Destelbergen Oost-Vlaanderen 9070",
    "addr:housenumber":"15",
    "addr:postcode":"9070",
    "addr:street":"Blauwesteenstraat",
    "iso:country":"BE",
    "sg:address":"Blauwesteenstraat 15",
    "sg:city":"Destelbergen",
    "sg:classifiers":[
        {
            "category":"Arena",
            "subcategory":"Sports Club",
            "type":"Entertainment"
        }
    ],
    "sg:phone":"+32 9 230 58 20",
    "sg:postcode":"9070",
    "sg:province":"Oost-Vlaanderen",
    "sg:tags":[
        "de"
    ],
    "wof:name":"De Snelle Reizigers",
    "wof:placetype":"venue"
},
  "geometry": {"coordinates":[3.8062739372,51.040561676],"type":"Point"}
}