{
  "type": "Feature",
  "properties": {
    "addr:full":"Kortrijksepoortstraat 92 Gent Oost-Vlaanderen 9000",
    "addr:housenumber":"92",
    "addr:postcode":"9000",
    "addr:street":"Kortrijksepoortstraat;Oost-Vlaanderen",
    "iso:country":"BE",
    "sg:address":"Kortrijksepoortstraat 92",
    "sg:city":"Gent",
    "sg:classifiers":[
        {
            "category":"Utilities",
            "subcategory":"Telephone",
            "type":"Services"
        }
    ],
    "sg:phone":"+32 9 329 00 24",
    "sg:postcode":"9000",
    "sg:province":"Oost-Vlaanderen",
    "sg:tags":[
        "-",
        "internet"
    ],
    "wof:name":"One2web",
    "wof:placetype":"venue"
},
  "geometry": {"coordinates":[3.7219130993,51.0453109741],"type":"Point"}
}