{
  "type": "Feature",
  "properties": {
    "addr:full":"Itterbeekse Laan 56 Anderlecht Bruxelles-Capitale 1070",
    "addr:housenumber":"56",
    "addr:postcode":"1070",
    "addr:street":"Laan",
    "iso:country":"BE",
    "sg:address":"Itterbeekse Laan 56",
    "sg:city":"Anderlecht",
    "sg:orig_category":"Banken and kredietinstellingen",
    "sg:phone":"+32 2 523 21 02",
    "sg:postcode":"1070",
    "sg:province":"Bruxelles-Capitale",
    "wof:name":"Fortis",
    "wof:placetype":"venue"
},
  "geometry": {"coordinates":[4.2959518433,50.8355178833],"type":"Point"}
}