{
  "type": "Feature",
  "properties": {
    "addr:full":"Delaerestraat 8 Roeselare West-Vlaanderen 8800",
    "addr:housenumber":"8",
    "addr:postcode":"8800",
    "addr:street":"Delaerestraat",
    "iso:country":"BE",
    "sg:address":"Delaerestraat 8",
    "sg:city":"Roeselare",
    "sg:orig_category":"Diverse persoonlijke diensten",
    "sg:phone":"+32 51 22 27 45",
    "sg:postcode":"8800",
    "sg:province":"West-Vlaanderen",
    "wof:name":"Rudy Pattyn",
    "wof:placetype":"venue"
},
  "geometry": {"coordinates":[3.1275498867,50.9465255737],"type":"Point"}
}