{
  "type": "Feature",
  "properties": {
    "addr:full":"Brouwerijstraat 1 Drogenbos/drogenbos Vlaams-Brabant 1620",
    "addr:housenumber":"1",
    "addr:postcode":"1620",
    "addr:street":"Brouwerijstraat",
    "iso:country":"BE",
    "sg:address":"Brouwerijstraat 1",
    "sg:city":"Drogenbos/drogenbos",
    "sg:orig_category":"Banken and kredietinstellingen",
    "sg:phone":"+32 2 378 07 74",
    "sg:postcode":"1620",
    "sg:province":"Vlaams-Brabant",
    "wof:name":"Kbc",
    "wof:placetype":"venue"
},
  "geometry": {"coordinates":[4.3184337616,50.787727356],"type":"Point"}
}