{
  "type": "Feature",
  "properties": {
    "addr:full":"Kontichsesteenweg 36 Aartselaar Antwerpen 2630",
    "addr:housenumber":"36",
    "addr:postcode":"2630",
    "addr:street":"Kontichsesteenweg",
    "iso:country":"BE",
    "sg:address":"Kontichsesteenweg 36",
    "sg:city":"Aartselaar",
    "sg:classifiers":[
        {
            "category":"Shopping",
            "subcategory":"Computers & Home Electronics",
            "type":"Retail Goods"
        }
    ],
    "sg:phone":"+32 3 870 80 00",
    "sg:postcode":"2630",
    "sg:province":"Antwerpen",
    "sg:tags":[
        "siemens",
        "fujitsu",
        "computerapparatuur"
    ],
    "wof:name":"Portable Center Nv",
    "wof:placetype":"venue"
},
  "geometry": {"coordinates":[4.3865962029,51.1432228088],"type":"Point"}
}