{
  "type": "Feature",
  "properties": {
    "addr:full":"Rue De La Carbo 10 B6 Tertre Hainaut 7333",
    "addr:housenumber":"10",
    "addr:postcode":"7333",
    "addr:street":"Rue De La Carbo",
    "iso:country":"BE",
    "sg:address":"Rue De La Carbo 10 B6",
    "sg:city":"Tertre",
    "sg:classifiers":[
        {
            "category":"Science Facility",
            "type":"Public Place"
        }
    ],
    "sg:phone":"+32 65 71 25 16",
    "sg:postcode":"7333",
    "sg:province":"Hainaut",
    "sg:tags":[
        "ammonia"
    ],
    "wof:name":"Kemira Growhow S.a./n.v.",
    "wof:placetype":"venue"
},
  "geometry": {"coordinates":[3.8111400604,50.4655151367],"type":"Point"}
}