{
  "type": "Feature",
  "properties": {
    "iso:country":"BE",
    "sg:address":"Nieuwmoer Dorp 45",
    "sg:city":"Kalmthout",
    "sg:classifiers":[
        {
            "category":"Bars & Pubs",
            "type":"Food & Drink"
        }
    ],
    "sg:phone":"+32 3 667 22 14",
    "sg:postcode":"2920",
    "sg:province":"Antwerpen",
    "sg:tags":[
        "tavern"
    ],
    "wof:name":"Den Engel",
    "wof:placetype":"venue"
},
  "geometry": {"coordinates":[4.4736428261,51.3958930969],"type":"Point"}
}