{
  "type": "Feature",
  "properties": {
    "addr:full":"Place Elie Delferri\u00c8re 24 Charleroi Hainaut 6000",
    "addr:housenumber":"24",
    "addr:postcode":"6000",
    "addr:street":"Place Elie Delferrie\u0300Re;Hainaut",
    "iso:country":"BE",
    "sg:address":"Place Elie Delferri\u00c8re 24",
    "sg:city":"Charleroi",
    "sg:orig_category":"S\u00e9lection de personnel and placement",
    "sg:phone":"+32 71 42 30 20",
    "sg:postcode":"6000",
    "sg:province":"Hainaut",
    "wof:name":"Lsi Consult",
    "wof:placetype":"venue"
},
  "geometry": {"coordinates":[4.4527812004,50.4215660095],"type":"Point"}
}