{
  "type": "Feature",
  "properties": {
    "addr:full":"Arthur Scheirisstraat 31 Zottegem Oost-Vlaanderen 9620",
    "addr:housenumber":"31",
    "addr:postcode":"9620",
    "addr:street":"Scheirisstraat",
    "iso:country":"BE",
    "sg:address":"Arthur Scheirisstraat 31",
    "sg:city":"Zottegem",
    "sg:orig_category":"S\u00e9curit\u00e9 sociale",
    "sg:phone":"+32 9 360 15 80",
    "sg:postcode":"9620",
    "sg:province":"Oost-Vlaanderen",
    "wof:name":"Liberale Mutualiteit",
    "wof:placetype":"venue"
},
  "geometry": {"coordinates":[3.8099679947,50.8697967529],"type":"Point"}
}