{
  "type": "Feature",
  "properties": {
    "addr:full":"Rue Caporal Tr\u00c9signies 13 Rebecq Brabant Wallon 1430",
    "addr:housenumber":"13",
    "addr:postcode":"1430",
    "addr:street":"Rue Caporal Tre\u0301Signies",
    "iso:country":"BE",
    "sg:address":"Rue Caporal Tr\u00c9signies 13",
    "sg:city":"Rebecq",
    "sg:orig_category":"Enseignement maternel and primaire",
    "sg:phone":"+32 2 395 61 67",
    "sg:postcode":"1430",
    "sg:province":"Brabant Wallon",
    "wof:name":"Ecole Fond. Communale",
    "wof:placetype":"venue"
},
  "geometry": {"coordinates":[4.1195502281,50.6956710815],"type":"Point"}
}