{
  "type": "Feature",
  "properties": {
    "iso:country":"BE",
    "sg:address":"Polderken 7",
    "sg:city":"Maldegem (middelburg)",
    "sg:classifiers":[
        {
            "category":"Retail",
            "subcategory":"Veterinary Services",
            "type":"Services"
        }
    ],
    "sg:phone":"+32 475 48 64 50",
    "sg:postcode":"9992",
    "sg:province":"Oost-Vlaanderen",
    "sg:tags":[
        "veterinarian"
    ],
    "wof:name":"Vangheluwe B",
    "wof:placetype":"venue"
},
  "geometry": {"coordinates":[3.4069919586,51.2433624268],"type":"Point"}
}