{
  "type": "Feature",
  "properties": {
    "addr:full":"Rue Jules Tison 34 La Louviere Hainaut 7100",
    "addr:housenumber":"34",
    "addr:postcode":"7100",
    "addr:street":"Rue Jules Tison",
    "iso:country":"BE",
    "sg:address":"Rue Jules Tison 34",
    "sg:city":"La Louviere",
    "sg:orig_category":"M\u00e9decins and sp\u00e9cialistes",
    "sg:phone":"+32 64 22 55 12",
    "sg:postcode":"7100",
    "sg:province":"Hainaut",
    "wof:name":"R. Sabbatini",
    "wof:placetype":"venue"
},
  "geometry": {"coordinates":[4.1832079887,50.4692077637],"type":"Point"}
}