{
  "type": "Feature",
  "properties": {
    "addr:full":"Rosier 32 Antwerpen Antwerpen 2000",
    "addr:housenumber":"32",
    "addr:postcode":"2000",
    "addr:street":"Rosier",
    "iso:country":"BE",
    "sg:address":"Rosier 32",
    "sg:city":"Antwerpen",
    "sg:classifiers":[
        {
            "category":"Shopping",
            "subcategory":"Clothing, Apparel, & Fashions",
            "type":"Retail Goods"
        }
    ],
    "sg:phone":"+32 3 293 74 85",
    "sg:postcode":"2000",
    "sg:province":"Antwerpen",
    "sg:tags":[
        "designer",
        "stylist"
    ],
    "wof:name":"Detlef",
    "wof:placetype":"venue"
},
  "geometry": {"coordinates":[4.4035139084,51.2138252258],"type":"Point"}
}