{
  "type": "Feature",
  "properties": {
    "iso:country":"BE",
    "sg:address":"Bommerstraat 12",
    "sg:city":"Herk-de-stad",
    "sg:orig_category":"Bloemen and planten Gh",
    "sg:phone":"+32 13 55 27 93",
    "sg:postcode":"3540",
    "sg:province":"Limburg",
    "wof:name":"Flora-dora Plantenkwerij",
    "wof:placetype":"venue"
},
  "geometry": {"coordinates":[5.1513409615,50.9287948608],"type":"Point"}
}