{
  "type": "Feature",
  "properties": {
    "iso:country":"BE",
    "sg:address":"Tichelrijstraat 4",
    "sg:city":"Sint-truiden",
    "sg:classifiers":[
        {
            "category":"Health Services",
            "subcategory":"Doctor",
            "type":"Services"
        }
    ],
    "sg:phone":"+32 11 59 23 85",
    "sg:postcode":"3800",
    "sg:province":"Limburg",
    "sg:tags":[
        "medicinephysicians",
        "surgeon"
    ],
    "wof:name":"Malcorps J",
    "wof:placetype":"venue"
},
  "geometry": {"coordinates":[5.1917648315,50.8173942566],"type":"Point"}
}