{
  "type": "Feature",
  "properties": {
    "addr:full":"Droogtestraat 8 Deerlijk West-Vlaanderen 8540",
    "addr:housenumber":"8",
    "addr:postcode":"8540",
    "addr:street":"Droogtestraat",
    "iso:country":"BE",
    "sg:address":"Droogtestraat 8",
    "sg:city":"Deerlijk",
    "sg:classifiers":[
        {
            "category":"Health Services",
            "subcategory":"Nursing And Care Facility",
            "type":"Services"
        }
    ],
    "sg:phone":"+32 56 71 52 15",
    "sg:postcode":"8540",
    "sg:province":"West-Vlaanderen",
    "sg:tags":[
        "home"
    ],
    "wof:name":"Depraetere Ann Bvba",
    "wof:placetype":"venue"
},
  "geometry": {"coordinates":[3.3477330208,50.8538322449],"type":"Point"}
}