{
  "type": "Feature",
  "properties": {
    "iso:country":"BE",
    "sg:address":"Chauss\u00c9e Charlemagne 91",
    "sg:city":"Thimister-clermont",
    "sg:orig_category":"Woningbouw",
    "sg:phone":"+32 87 44 67 09",
    "sg:postcode":"4890",
    "sg:province":"Li\u00e8ge",
    "wof:name":"Christian Pirenne",
    "wof:placetype":"venue"
},
  "geometry": {"coordinates":[5.8786768913,50.6483306885],"type":"Point"}
}