{
  "type": "Feature",
  "properties": {
    "addr:full":"Klaterstraat 45 Rijkevorsel Antwerpen 2310",
    "addr:housenumber":"45",
    "addr:postcode":"2310",
    "addr:street":"Klaterstraat",
    "iso:country":"BE",
    "sg:address":"Klaterstraat 45",
    "sg:city":"Rijkevorsel",
    "sg:orig_category":"Eleveurs de bovins",
    "sg:phone":"+32 3 314 43 34",
    "sg:postcode":"2310",
    "sg:province":"Antwerpen",
    "wof:name":"Johan Renders",
    "wof:placetype":"venue"
},
  "geometry": {"coordinates":[4.7875800133,51.3678665161],"type":"Point"}
}