{
  "type": "Feature",
  "properties": {
    "addr:full":"Avenue Baron Louis Huart 21bb Namur Namur 5000",
    "addr:housenumber":"21bb",
    "addr:postcode":"5000",
    "addr:street":"Avenue Baron Louis Huart",
    "iso:country":"BE",
    "sg:address":"Avenue Baron Louis Huart 21bb",
    "sg:city":"Namur",
    "sg:orig_category":"V\u00e9t\u00e9rinaires",
    "sg:phone":"+32 81 22 21 33",
    "sg:postcode":"5000",
    "sg:province":"Namur",
    "wof:name":"Anina Colin",
    "wof:placetype":"venue"
},
  "geometry": {"coordinates":[4.866394043,50.4596176147],"type":"Point"}
}