{
  "type": "Feature",
  "properties": {
    "addr:full":"Hendrik I Lei 5 Vilvoorde Vlaams-Brabant 1800",
    "addr:housenumber":"5",
    "addr:postcode":"1800",
    "addr:street":"Hendrik I Lei",
    "iso:country":"BE",
    "sg:address":"Hendrik I Lei 5",
    "sg:city":"Vilvoorde",
    "sg:classifiers":[
        {
            "category":"Fast Food",
            "type":"Food & Drink"
        }
    ],
    "sg:phone":"+32 2 305 00 00",
    "sg:postcode":"1800",
    "sg:province":"Vlaams-Brabant",
    "sg:tags":[
        "meeneem",
        "restaurant"
    ],
    "wof:name":"Testa Rossi",
    "wof:placetype":"venue"
},
  "geometry": {"coordinates":[4.4281320572,50.9309921265],"type":"Point"}
}