{
  "type": "Feature",
  "properties": {
    "addr:full":"Blauwe Weg 261haven Antwerpen Antwerpen 2030",
    "addr:housenumber":"261haven",
    "addr:postcode":"2030",
    "addr:street":"Blauwe Weg",
    "iso:country":"BE",
    "sg:address":"Blauwe Weg 261haven",
    "sg:city":"Antwerpen",
    "sg:classifiers":[
        {
            "category":"Utilities",
            "subcategory":"Refuse",
            "type":"Services"
        }
    ],
    "sg:phone":"+32 3 543 59 11",
    "sg:postcode":"2030",
    "sg:province":"Antwerpen",
    "sg:tags":[
        "management",
        "waste"
    ],
    "wof:name":"Marpobel Nv",
    "wof:placetype":"venue"
},
  "geometry": {"coordinates":[4.3814167976,51.2565536499],"type":"Point"}
}