{
  "type": "Feature",
  "properties": {
    "iso:country":"BE",
    "sg:address":"Paalstraat 72",
    "sg:city":"Schoten",
    "sg:orig_category":"Tabac. Maroquinerie and articles de voyage. Fournitures de bureau. Jeux and jouets. Eclairage et \u00e9qu",
    "sg:phone":"+32 3 658 47 36",
    "sg:postcode":"2900",
    "sg:province":"Antwerpen",
    "wof:name":"Pasmans",
    "wof:placetype":"venue"
},
  "geometry": {"coordinates":[4.5011482239,51.2522888184],"type":"Point"}
}