{
  "type": "Feature",
  "properties": {
    "addr:full":"Nieuwstraat 2 Geel Antwerpen 2440",
    "addr:housenumber":"2",
    "addr:postcode":"2440",
    "addr:street":"Nieuwstraat",
    "iso:country":"BE",
    "sg:address":"Nieuwstraat 2",
    "sg:city":"Geel",
    "sg:classifiers":[
        {
            "category":"Shopping",
            "subcategory":"Clothing, Apparel, & Fashions",
            "type":"Retail Goods"
        }
    ],
    "sg:phone":"+32 14 58 58 37",
    "sg:postcode":"2440",
    "sg:province":"Antwerpen",
    "sg:tags":[
        "clothing",
        "-",
        "gentleman"
    ],
    "wof:name":"Adonis Herenkleding Bvba",
    "wof:placetype":"venue"
},
  "geometry": {"coordinates":[4.991133213,51.1627197266],"type":"Point"}
}