{
  "type": "Feature",
  "properties": {
    "iso:country":"BE",
    "sg:address":"Ren\u00c9 Carelsstraat 17",
    "sg:city":"Antwerpen",
    "sg:orig_category":"Dranken",
    "sg:phone":"+32 3 235 20 68",
    "sg:postcode":"2140",
    "sg:province":"Antwerpen",
    "wof:name":"Huis Divino",
    "wof:placetype":"venue"
},
  "geometry": {"coordinates":[4.4332199097,51.2137565613],"type":"Point"}
}