{
  "type": "Feature",
  "properties": {
    "addr:full":"Avenue De La Gare 13 Arlon Luxembourg 6700",
    "addr:housenumber":"13",
    "addr:postcode":"6700",
    "addr:street":"Avenue De La Gare",
    "iso:country":"BE",
    "sg:address":"Avenue De La Gare 13",
    "sg:city":"Arlon",
    "sg:orig_category":"Apotheken",
    "sg:phone":"+32 63 22 46 68",
    "sg:postcode":"6700",
    "sg:province":"Luxembourg",
    "wof:name":"B. Waltzing",
    "wof:placetype":"venue"
},
  "geometry": {"coordinates":[5.8110499382,49.680721283],"type":"Point"}
}