{
  "type": "Feature",
  "properties": {
    "iso:country":"BE",
    "sg:address":"Bredabaan 166b2",
    "sg:city":"Brasschaat",
    "sg:orig_category":"Agences immobili\u00e8res. Services divers aux entreprises",
    "sg:phone":"+32 3 652 19 60",
    "sg:postcode":"2930",
    "sg:province":"Antwerpen",
    "wof:name":"Immo-pascal",
    "wof:placetype":"venue"
},
  "geometry": {"coordinates":[4.4855542183,51.2869567871],"type":"Point"}
}