{
  "type": "Feature",
  "properties": {
    "addr:full":"Esseghemstraat 54 Jette/jette Bruxelles-Capitale 1090",
    "addr:housenumber":"54",
    "addr:postcode":"1090",
    "addr:street":"Esseghemstraat",
    "iso:country":"BE",
    "sg:address":"Esseghemstraat 54",
    "sg:city":"Jette/jette",
    "sg:orig_category":"Krantenwinkels Rookartikelen",
    "sg:phone":"+32 2 425 31 34",
    "sg:postcode":"1090",
    "sg:province":"Bruxelles-Capitale",
    "wof:name":"Alla Kirillova",
    "wof:placetype":"venue"
},
  "geometry": {"coordinates":[4.3361148834,50.8778686523],"type":"Point"}
}