{
  "type": "Feature",
  "properties": {
    "iso:country":"BE",
    "sg:address":"Ieperstraat 214",
    "sg:city":"Poperinge",
    "sg:orig_category":"HUISBRANDOLIE Hout and afgeleiden Gh Houtbewerking and -behandeling IJzerwaren, bouw- and verfmateri",
    "sg:phone":"+32 57 33 37 53",
    "sg:postcode":"8970",
    "sg:province":"West-Vlaanderen",
    "wof:name":"Rony Gekiere",
    "wof:placetype":"venue"
},
  "geometry": {"coordinates":[2.7425720692,50.8551216125],"type":"Point"}
}