{
  "type": "Feature",
  "properties": {
    "iso:country":"BE",
    "sg:address":"Passage Du Centre 29",
    "sg:city":"Mons",
    "sg:classifiers":[
        {
            "category":"Personal",
            "subcategory":"Piercing",
            "type":"Services"
        }
    ],
    "sg:phone":"+32 65 35 40 33",
    "sg:postcode":"7000",
    "sg:province":"Hainaut",
    "sg:tags":[
        "piercings",
        "tatouages"
    ],
    "wof:name":"Ritual-piercing & Tattoo",
    "wof:placetype":"venue"
},
  "geometry": {"coordinates":[3.94876194,50.451461792],"type":"Point"}
}