{
  "type": "Feature",
  "properties": {
    "addr:full":"Rue Docteur Albert Hustin 24 Virton (ethe) Luxembourg 6760",
    "addr:housenumber":"24",
    "addr:postcode":"6760",
    "addr:street":"Rue Docteur Albert Hustin",
    "iso:country":"BE",
    "sg:address":"Rue Docteur Albert Hustin 24",
    "sg:city":"Virton (ethe)",
    "sg:classifiers":[
        {
            "category":"Shopping",
            "subcategory":"Computers & Home Electronics",
            "type":"Retail Goods"
        }
    ],
    "sg:phone":"+32 63 58 19 00",
    "sg:postcode":"6760",
    "sg:province":"Luxembourg",
    "sg:tags":[
        "automobile",
        "-",
        "navigation",
        "system"
    ],
    "wof:name":"Willaime M",
    "wof:placetype":"venue"
},
  "geometry": {"coordinates":[5.5842189789,49.5798377991],"type":"Point"}
}