{
  "type": "Feature",
  "properties": {
    "iso:country":"BE",
    "sg:address":"Rue Adolphe Willemyns 166 Box 7",
    "sg:city":"Bruxelles (anderlecht)",
    "sg:classifiers":[
        {
            "category":"Sports & Exercise",
            "subcategory":"Swimming Pool",
            "type":"Entertainment"
        }
    ],
    "sg:phone":"+32 2 522 94 08",
    "sg:postcode":"1070",
    "sg:province":"Bruxelles-Capitale",
    "sg:tags":[
        "tank",
        "septic"
    ],
    "wof:name":"Vandeput-van Eeckhoudt",
    "wof:placetype":"venue"
},
  "geometry": {"coordinates":[4.2962598801,50.8387107849],"type":"Point"}
}