{
  "type": "Feature",
  "properties": {
    "iso:country":"BE",
    "sg:address":"Beverlosesteenweg 311",
    "sg:city":"Beringen",
    "sg:orig_category":"Non-Classified Establishments",
    "sg:phone":"+32 11 45 55 00",
    "sg:postcode":"3580",
    "sg:province":"Limburg",
    "wof:name":"Kristina Bvba",
    "wof:placetype":"venue"
},
  "geometry": {"coordinates":[5.2100481987,51.070640564],"type":"Point"}
}