{
  "type": "Feature",
  "properties": {
    "iso:country":"BE",
    "sg:address":"Keibergstraat 35",
    "sg:city":"Landen",
    "sg:orig_category":"P\u00e9pini\u00e9ristes. Jardinage",
    "sg:phone":"+32 16 78 89 67",
    "sg:postcode":"3400",
    "sg:province":"Vlaams-Brabant",
    "wof:name":"Hombroux Pierre Tuin- & Vijveraanleg",
    "wof:placetype":"venue"
},
  "geometry": {"coordinates":[5.0547580719,50.766456604],"type":"Point"}
}