{
  "type": "Feature",
  "properties": {
    "addr:full":"Rue Saint-laurent 29 Arlon Luxembourg 6700",
    "addr:housenumber":"29",
    "addr:postcode":"6700",
    "addr:street":"Rue Saint-Laurent",
    "iso:country":"BE",
    "sg:address":"Rue Saint-laurent 29",
    "sg:city":"Arlon",
    "sg:classifiers":[
        {
            "category":"Building & Trades",
            "subcategory":"Construction",
            "type":"Services"
        }
    ],
    "sg:phone":"+32 63 21 70 23",
    "sg:postcode":"6700",
    "sg:province":"Luxembourg",
    "sg:tags":[
        "carpenter"
    ],
    "wof:name":"Klensch M",
    "wof:placetype":"venue"
},
  "geometry": {"coordinates":[5.8188529015,49.6834030151],"type":"Point"}
}