{
  "type": "Feature",
  "properties": {
    "iso:country":"BE",
    "sg:address":"Rue Forgeur 25",
    "sg:city":"Li\u00c8ge",
    "sg:orig_category":"Diverse organisaties and verenigingen Maatschappelijke dienstverlening",
    "sg:phone":"+32 4 222 08 78",
    "sg:postcode":"4000",
    "sg:province":"Li\u00e8ge",
    "wof:name":"S.i.e.p.",
    "wof:placetype":"venue"
},
  "geometry": {"coordinates":[5.5699720383,50.6346893311],"type":"Point"}
}