{
  "type": "Feature",
  "properties": {
    "addr:full":"Rue Trixhe \u00e0 L'arbre 4 Hannut (grand-hallet) Li\u00e8ge 4280",
    "addr:housenumber":"4",
    "addr:postcode":"4280",
    "addr:street":"Rue Trixhe A\u0300 L'Arbre",
    "iso:country":"BE",
    "sg:address":"Rue Trixhe \u00e0 L'arbre 4",
    "sg:city":"Hannut (grand-hallet)",
    "sg:classifiers":[
        {
            "category":"Real Estate",
            "subcategory":"Real Estate Services",
            "type":"Services"
        }
    ],
    "sg:phone":"+32 19 63 46 87",
    "sg:postcode":"4280",
    "sg:province":"Li\u00e8ge",
    "wof:name":"Berger E",
    "wof:placetype":"venue"
},
  "geometry": {"coordinates":[5.0394310951,50.6977424622],"type":"Point"}
}