{
  "type": "Feature",
  "properties": {
    "iso:country":"BE",
    "sg:address":"Zittaard 47",
    "sg:city":"Halen",
    "sg:orig_category":"Ruimtes voor conferenties, recepties and feesten",
    "sg:phone":"+32 13 44 14 00",
    "sg:postcode":"3545",
    "sg:province":"Limburg",
    "wof:name":"Princenhof",
    "wof:placetype":"venue"
},
  "geometry": {"coordinates":[5.1051669121,50.9434165955],"type":"Point"}
}