{
  "type": "Feature",
  "properties": {
    "addr:full":"Battelsesteenweg 27 Mechelen Antwerpen 2800",
    "addr:housenumber":"27",
    "addr:postcode":"2800",
    "addr:street":"Battelsesteenweg",
    "iso:country":"BE",
    "sg:address":"Battelsesteenweg 27",
    "sg:city":"Mechelen",
    "sg:classifiers":[
        {
            "category":"Health Services",
            "subcategory":"Health Practitioner",
            "type":"Services"
        }
    ],
    "sg:phone":"+32 15 26 21 66",
    "sg:postcode":"2800",
    "sg:province":"Antwerpen",
    "sg:tags":[
        "physiotherapist"
    ],
    "wof:name":"De Groote Ph",
    "wof:placetype":"venue"
},
  "geometry": {"coordinates":[4.4690380096,51.0285682678],"type":"Point"}
}