{
  "type": "Feature",
  "properties": {
    "iso:country":"BE",
    "sg:address":"C.c. Porte De Tr\u00caves 1",
    "sg:city":"Bastogne",
    "sg:classifiers":[
        {
            "category":"Cinema",
            "subcategory":"Movie Rental",
            "type":"Entertainment"
        }
    ],
    "sg:phone":"+32 61 21 49 18",
    "sg:postcode":"6600",
    "sg:province":"Luxembourg",
    "sg:tags":[
        "de",
        "cassette",
        "location",
        "vid\u00e9o",
        "audio"
    ],
    "wof:name":"J.r. Video Club",
    "wof:placetype":"venue"
},
  "geometry": {"coordinates":[5.7224497795,50.0050735474],"type":"Point"}
}