{
  "type": "Feature",
  "properties": {
    "addr:full":"Heuvelplein 12 Essen Antwerpen 2910",
    "addr:housenumber":"12",
    "addr:postcode":"2910",
    "addr:street":"Heuvelplein",
    "iso:country":"BE",
    "sg:address":"Heuvelplein 12",
    "sg:city":"Essen",
    "sg:orig_category":"Journaux. Tabac",
    "sg:phone":"+32 3 667 77 15",
    "sg:postcode":"2910",
    "sg:province":"Antwerpen",
    "wof:name":"Huis 't Heuveltje",
    "wof:placetype":"venue"
},
  "geometry": {"coordinates":[4.472700119,51.4650001526],"type":"Point"}
}