{
  "type": "Feature",
  "properties": {
    "addr:full":"Ieperstraat 3 Komen-waasten/comines-warneton Hainaut 7784",
    "addr:housenumber":"3;7784",
    "addr:street":"Ieperstraat",
    "iso:country":"BE",
    "sg:address":"Ieperstraat 3",
    "sg:city":"Komen-waasten/comines-warneton",
    "sg:orig_category":"Brood, gebak and snoepgoed",
    "sg:phone":"+32 56 55 54 94",
    "sg:postcode":"7784",
    "sg:province":"Hainaut",
    "wof:name":"Leonidas",
    "wof:placetype":"venue"
},
  "geometry": {"coordinates":[2.9385099411,50.738319397],"type":"Point"}
}