{
  "type": "Feature",
  "properties": {
    "addr:full":"Luikersteenweg 182 Sint-truiden (brustem) Limburg 3800",
    "addr:housenumber":"182",
    "addr:postcode":"3800",
    "addr:street":"Luikersteenweg",
    "iso:country":"BE",
    "sg:address":"Luikersteenweg 182",
    "sg:city":"Sint-truiden (brustem)",
    "sg:classifiers":[
        {
            "category":"Communications",
            "subcategory":"Film & Video Production",
            "type":"Services"
        }
    ],
    "sg:phone":"+32 11 69 64 54",
    "sg:postcode":"3800",
    "sg:province":"Limburg",
    "sg:tags":[
        "hiring",
        "-"
    ],
    "wof:name":"Sepro",
    "wof:placetype":"venue"
},
  "geometry": {"coordinates":[5.2020549774,50.8044166565],"type":"Point"}
}