{
  "type": "Feature",
  "properties": {
    "addr:full":"Kipdorp 49 Antwerpen Antwerpen 2000",
    "addr:housenumber":"49",
    "addr:postcode":"2000",
    "addr:street":"Kipdorp",
    "iso:country":"BE",
    "sg:address":"Kipdorp 49",
    "sg:city":"Antwerpen",
    "sg:orig_category":"Agences d'exp\u00e9dition. Agences maritimes",
    "sg:phone":"+32 3 222 17 11",
    "sg:postcode":"2000",
    "sg:province":"Antwerpen",
    "wof:name":"Cosco Belgium",
    "wof:placetype":"venue"
},
  "geometry": {"coordinates":[4.409014225,51.220905304],"type":"Point"}
}