{
  "type": "Feature",
  "properties": {
    "iso:country":"BE",
    "sg:address":"Immerseelstraat 27",
    "sg:city":"Wommelgem",
    "sg:classifiers":[
        {
            "category":"Retail",
            "subcategory":"Auto Repair",
            "type":"Services"
        }
    ],
    "sg:phone":"+32 3 354 30 03",
    "sg:postcode":"2160",
    "sg:province":"Antwerpen",
    "sg:tags":[
        "garage"
    ],
    "wof:name":"Duo Motors",
    "wof:placetype":"venue"
},
  "geometry": {"coordinates":[4.4977312088,51.2104682922],"type":"Point"}
}