{
  "type": "Feature",
  "properties": {
    "addr:full":"Rue De Tourcoing 53 Mouscron Hainaut 7700",
    "addr:housenumber":"53",
    "addr:postcode":"7700",
    "addr:street":"Rue De Tourcoing",
    "iso:country":"BE",
    "sg:address":"Rue De Tourcoing 53",
    "sg:city":"Mouscron",
    "sg:classifiers":[
        {
            "category":"Retail",
            "subcategory":"Event Space",
            "type":"Services"
        }
    ],
    "sg:phone":"+32 56 33 24 11",
    "sg:postcode":"7700",
    "sg:province":"Hainaut",
    "sg:tags":[
        "rental",
        "-",
        "hall"
    ],
    "wof:name":"Palais De Chine (le)",
    "wof:placetype":"venue"
},
  "geometry": {"coordinates":[3.2112009525,50.7445602417],"type":"Point"}
}