{
  "type": "Feature",
  "properties": {
    "iso:country":"BE",
    "sg:address":"Kortrijksestraat 72",
    "sg:city":"Oostkamp",
    "sg:classifiers":[
        {
            "category":"Bars & Pubs",
            "type":"Food & Drink"
        }
    ],
    "sg:phone":"+32 50 82 42 10",
    "sg:postcode":"8020",
    "sg:province":"West-Vlaanderen",
    "wof:name":"Shooters",
    "wof:placetype":"venue"
},
  "geometry": {"coordinates":[3.2339780331,51.1515312195],"type":"Point"}
}