{
  "type": "Feature",
  "properties": {
    "iso:country":"BE",
    "sg:address":"Rue Du Manchester 13",
    "sg:city":"Sint-jans-molenbeek/molenbeek-saint-jean",
    "sg:orig_category":"Imprimeries and copyshops",
    "sg:phone":"+32 2 410 07 80",
    "sg:postcode":"1080",
    "sg:province":"Bruxelles-Capitale",
    "wof:name":"Imprimerie G.a.m.",
    "wof:placetype":"venue"
},
  "geometry": {"coordinates":[4.3286690712,50.8478431702],"type":"Point"}
}