{
  "type": "Feature",
  "properties": {
    "addr:full":"Kiewitstraat 196 Diepenbeek Limburg 3590",
    "addr:housenumber":"196",
    "addr:postcode":"3590",
    "addr:street":"Kiewitstraat",
    "iso:country":"BE",
    "sg:address":"Kiewitstraat 196",
    "sg:city":"Diepenbeek",
    "sg:orig_category":"Entretien et r\u00e9parations de v\u00e9hicules \u00e0 domicile. D\u00e9taillants en pi\u00e8ces and accessoires de voitures",
    "sg:phone":"+32 11 22 30 30",
    "sg:postcode":"3590",
    "sg:province":"Limburg",
    "wof:name":"Banden De Cond\u00c9",
    "wof:placetype":"venue"
},
  "geometry": {"coordinates":[5.41918993,50.9083938599],"type":"Point"}
}