{
  "type": "Feature",
  "properties": {
    "iso:country":"BE",
    "sg:address":"Bisschop Calewaertlaan 19",
    "sg:city":"Deinze",
    "sg:classifiers":[
        {
            "category":"Communications",
            "type":"Services"
        }
    ],
    "sg:phone":"+32 9 387 08 08",
    "sg:postcode":"9800",
    "sg:province":"Oost-Vlaanderen",
    "sg:tags":[
        "translator"
    ],
    "wof:name":"De Muynck A",
    "wof:placetype":"venue"
},
  "geometry": {"coordinates":[3.5393869877,50.9838829041],"type":"Point"}
}