{
  "type": "Feature",
  "properties": {
    "addr:full":"Rue De La Lib\u00c9ration 104 Frameries Hainaut 7080",
    "addr:housenumber":"104",
    "addr:postcode":"7080",
    "addr:street":"Rue De La Libe\u0301Ration",
    "iso:country":"BE",
    "sg:address":"Rue De La Lib\u00c9ration 104",
    "sg:city":"Frameries",
    "sg:classifiers":[
        {
            "category":"Cafe",
            "type":"Food & Drink"
        }
    ],
    "sg:phone":"+32 65 67 43 62",
    "sg:postcode":"7080",
    "sg:province":"Hainaut",
    "sg:tags":[
        "caf\u00e9s"
    ],
    "wof:name":"Caf\u00c9 Le Jupiler",
    "wof:placetype":"venue"
},
  "geometry": {"coordinates":[3.9013249874,50.4052352905],"type":"Point"}
}