{
  "type": "Feature",
  "properties": {
    "addr:full":"Place Joseph Dejardin 4 Beyne-heusay Li\u00e8ge 4610",
    "addr:housenumber":"4",
    "addr:postcode":"4610",
    "addr:street":"Place Joseph Dejardin",
    "iso:country":"BE",
    "sg:address":"Place Joseph Dejardin 4",
    "sg:city":"Beyne-heusay",
    "sg:classifiers":[
        {
            "category":"Fast Food",
            "type":"Food & Drink"
        }
    ],
    "sg:phone":"+32 4 365 12 24",
    "sg:postcode":"4610",
    "sg:province":"Li\u00e8ge",
    "sg:tags":[
        "fried",
        "stand",
        "potato"
    ],
    "wof:name":"Frite Dor\u00e9e (la)",
    "wof:placetype":"venue"
},
  "geometry": {"coordinates":[5.6558761597,50.6227531433],"type":"Point"}
}