{
  "type": "Feature",
  "properties": {
    "addr:full":"Helkijnstraat 33 Zwevegem (sint-denijs) West-Vlaanderen 8554",
    "addr:housenumber":"33",
    "addr:postcode":"8554",
    "addr:street":"Helkijnstraat",
    "iso:country":"BE",
    "sg:address":"Helkijnstraat 33",
    "sg:city":"Zwevegem (sint-denijs)",
    "sg:classifiers":[
        {
            "category":"Bakery",
            "type":"Food & Drink"
        }
    ],
    "sg:phone":"+32 56 45 61 70",
    "sg:postcode":"8554",
    "sg:province":"West-Vlaanderen",
    "sg:tags":[
        "confectioner",
        "baker"
    ],
    "wof:name":"Vandeputte L",
    "wof:placetype":"venue"
},
  "geometry": {"coordinates":[3.3706920147,50.7496185303],"type":"Point"}
}