{
  "type": "Feature",
  "properties": {
    "iso:country":"BE",
    "sg:address":"Groot Veld 36",
    "sg:city":"Kontich",
    "sg:orig_category":"Diverse bouwafwerking and reiniging Elektrische installaties voor woningen",
    "sg:phone":"+32 3 457 99 00",
    "sg:postcode":"2550",
    "sg:province":"Antwerpen",
    "wof:name":"Luc Demarest",
    "wof:placetype":"venue"
},
  "geometry": {"coordinates":[4.4553399086,51.1132888794],"type":"Point"}
}