{
  "type": "Feature",
  "properties": {
    "iso:country":"BE",
    "sg:address":"Bois-du-ry 10",
    "sg:city":"Rendeux",
    "sg:orig_category":"Rev\u00eatements de sols and murs. Rev\u00eatements pour sols and murs",
    "sg:phone":"+32 84 47 70 50",
    "sg:postcode":"6987",
    "sg:province":"Luxembourg",
    "wof:name":"Maurice Junius",
    "wof:placetype":"venue"
},
  "geometry": {"coordinates":[5.5352711678,50.2005081177],"type":"Point"}
}