{
  "type": "Feature",
  "properties": {
    "addr:full":"Roeselaarsestraat 41 Ardooie West-Vlaanderen 8850",
    "addr:housenumber":"41",
    "addr:postcode":"8850",
    "addr:street":"Roeselaarsestraat",
    "iso:country":"BE",
    "sg:address":"Roeselaarsestraat 41",
    "sg:city":"Ardooie",
    "sg:classifiers":[
        {
            "category":"Communications",
            "subcategory":"Television Station",
            "type":"Services"
        }
    ],
    "sg:phone":"+32 51 74 83 88",
    "sg:postcode":"8850",
    "sg:province":"West-Vlaanderen",
    "sg:tags":[
        "report",
        "video"
    ],
    "wof:name":"Devriese G",
    "wof:placetype":"venue"
},
  "geometry": {"coordinates":[3.1871960163,50.9686317444],"type":"Point"}
}