{
  "type": "Feature",
  "properties": {
    "addr:full":"Avenue Winston Churchill 8 Ukkel/uccle Bruxelles-Capitale 1180",
    "addr:housenumber":"8",
    "addr:postcode":"1180",
    "addr:street":"Avenue Winston Churchill;/",
    "iso:country":"BE",
    "sg:address":"Avenue Winston Churchill 8",
    "sg:city":"Ukkel/uccle",
    "sg:orig_category":"Agences immobili\u00e8res",
    "sg:phone":"+32 2 347 26 86",
    "sg:postcode":"1180",
    "sg:province":"Bruxelles-Capitale",
    "wof:name":"Espace & Cr\u00c9ation Habitat",
    "wof:placetype":"venue"
},
  "geometry": {"coordinates":[4.3485751152,50.8134727478],"type":"Point"}
}