{
  "type": "Feature",
  "properties": {
    "addr:full":"Schriekstraat 131-1 Heist-op-den-berg (schriek) Antwerpen 2223",
    "addr:postcode":"131-1;2223",
    "addr:street":"Schriekstraat",
    "iso:country":"BE",
    "sg:address":"Schriekstraat 131-1",
    "sg:city":"Heist-op-den-berg (schriek)",
    "sg:classifiers":[
        {
            "category":"Building & Trades",
            "subcategory":"Construction",
            "type":"Services"
        }
    ],
    "sg:phone":"+32 15 73 00 28",
    "sg:postcode":"2223",
    "sg:province":"Antwerpen",
    "sg:tags":[
        "scaffolding"
    ],
    "wof:name":"D.w. Construct",
    "wof:placetype":"venue"
},
  "geometry": {"coordinates":[4.6935648918,51.0282707214],"type":"Point"}
}