{
  "type": "Feature",
  "properties": {
    "iso:country":"BE",
    "sg:address":"Mechelsestraat 203a",
    "sg:city":"Leuven",
    "sg:orig_category":"Boissons",
    "sg:phone":"+32 16 20 20 00",
    "sg:postcode":"3000",
    "sg:province":"Vlaams-Brabant",
    "wof:name":"Terclavers Drankservice",
    "wof:placetype":"venue"
},
  "geometry": {"coordinates":[4.6966061592,50.8864593506],"type":"Point"}
}