{
  "type": "Feature",
  "properties": {
    "addr:full":"Generaal De Wittelaan 17 B30 Mechelen Antwerpen 2800",
    "addr:housenumber":"17 b30",
    "addr:postcode":"2800",
    "addr:street":"Generaal De Wittelaan",
    "iso:country":"BE",
    "sg:address":"Generaal De Wittelaan 17 B30",
    "sg:city":"Mechelen",
    "sg:orig_category":"Messageries. Transports routiers de marchandises",
    "sg:phone":"+32 15 55 55 55",
    "sg:postcode":"2800",
    "sg:province":"Antwerpen",
    "wof:name":"D.h.l. Sprintline",
    "wof:placetype":"venue"
},
  "geometry": {"coordinates":[4.4854397774,51.0289268494],"type":"Point"}
}