{
  "type": "Feature",
  "properties": {
    "addr:full":"Passtraat 258 Sint-niklaas Oost-Vlaanderen 9100",
    "addr:housenumber":"258",
    "addr:postcode":"9100",
    "addr:street":"Passtraat",
    "iso:country":"BE",
    "sg:address":"Passtraat 258",
    "sg:city":"Sint-niklaas",
    "sg:orig_category":"Airconditioning and ventilatie",
    "sg:phone":"+32 3 766 29 02",
    "sg:postcode":"9100",
    "sg:province":"Oost-Vlaanderen",
    "wof:name":"Geja Koeltechniek",
    "wof:placetype":"venue"
},
  "geometry": {"coordinates":[4.1748809814,51.1664199829],"type":"Point"}
}