{
  "type": "Feature",
  "properties": {
    "iso:country":"BE",
    "sg:address":"Rue Du Ch\u00c2teau 54",
    "sg:city":"Anderlues",
    "sg:classifiers":[
        {
            "category":"Insurance",
            "subcategory":"Life Insurance",
            "type":"Services"
        }
    ],
    "sg:phone":"+32 71 54 32 28",
    "sg:postcode":"6150",
    "sg:province":"Hainaut",
    "sg:tags":[
        "assurance"
    ],
    "wof:name":"F. Stievenart",
    "wof:placetype":"venue"
},
  "geometry": {"coordinates":[4.2584609985,50.4028396606],"type":"Point"}
}