{
  "type": "Feature",
  "properties": {
    "addr:full":"Trooststraat 26 Edegem Antwerpen 2650",
    "addr:housenumber":"26",
    "addr:postcode":"2650",
    "addr:street":"Trooststraat",
    "iso:country":"BE",
    "sg:address":"Trooststraat 26",
    "sg:city":"Edegem",
    "sg:classifiers":[
        {
            "category":"Building & Trades",
            "subcategory":"Equipment Rental",
            "type":"Services"
        }
    ],
    "sg:phone":"+32 3 450 94 80",
    "sg:postcode":"2650",
    "sg:province":"Antwerpen",
    "sg:tags":[
        "use",
        "apparatus",
        "tool",
        "-",
        "professional",
        "machines"
    ],
    "wof:name":"Mister Floor",
    "wof:placetype":"venue"
},
  "geometry": {"coordinates":[4.4466071129,51.1549987793],"type":"Point"}
}