{
  "type": "Feature",
  "properties": {
    "iso:country":"BE",
    "sg:address":"Dooren 97",
    "sg:city":"Merchtem",
    "sg:orig_category":"Agences de publicit\u00e9. Bureaux d'\u00e9tudes de march\u00e9",
    "sg:phone":"+32 52 37 50 51",
    "sg:postcode":"1785",
    "sg:province":"Vlaams-Brabant",
    "wof:name":"Mail Partners",
    "wof:placetype":"venue"
},
  "geometry": {"coordinates":[4.2501049042,50.9530029297],"type":"Point"}
}