{
  "type": "Feature",
  "properties": {
    "addr:full":"Vliegenstraat 8 Antwerpen Antwerpen 2060",
    "addr:housenumber":"8",
    "addr:postcode":"2060",
    "addr:street":"Vliegenstraat",
    "iso:country":"BE",
    "sg:address":"Vliegenstraat 8",
    "sg:city":"Antwerpen",
    "sg:orig_category":"Plomberie, chauffage and installations sanitaires",
    "sg:phone":"+32 3 231 73 89",
    "sg:postcode":"2060",
    "sg:province":"Antwerpen",
    "wof:name":"J.o.",
    "wof:placetype":"venue"
},
  "geometry": {"coordinates":[4.4203658104,51.2253265381],"type":"Point"}
}