{
  "type": "Feature",
  "properties": {
    "addr:full":"Place De Moustier 4a Jemeppe-sur-sambre (moustier-sur-sambre) Namur 5190",
    "addr:housenumber":"4a",
    "addr:postcode":"5190",
    "addr:street":"Place De Moustier",
    "iso:country":"BE",
    "sg:address":"Place De Moustier 4a",
    "sg:city":"Jemeppe-sur-sambre (moustier-sur-sambre)",
    "sg:classifiers":[
        {
            "category":"Health Services",
            "subcategory":"Doctor",
            "type":"Services"
        }
    ],
    "sg:phone":"+32 71 78 81 81",
    "sg:postcode":"5190",
    "sg:province":"Namur",
    "sg:tags":[
        "medicinephysicians",
        "surgeon"
    ],
    "wof:name":"Bodarw\u00e9 A-d",
    "wof:placetype":"venue"
},
  "geometry": {"coordinates":[4.6979141235,50.4660491943],"type":"Point"}
}