{
  "type": "Feature",
  "properties": {
    "addr:full":"Chauss\u00e9e De Tervuren 285 Waterloo Brabant Wallon 1410",
    "addr:housenumber":"285",
    "addr:postcode":"1410",
    "addr:street":"Chausse\u0301E De Tervuren",
    "iso:country":"BE",
    "sg:address":"Chauss\u00e9e De Tervuren 285",
    "sg:city":"Waterloo",
    "sg:classifiers":[
        {
            "category":"Home & Garden",
            "subcategory":"Home Furnishings",
            "type":"Retail Goods"
        }
    ],
    "sg:phone":"+32 2 351 61 62",
    "sg:postcode":"1410",
    "sg:province":"Brabant Wallon",
    "sg:tags":[
        "-",
        "bed",
        "mattress"
    ],
    "wof:name":"Espace Loggia",
    "wof:placetype":"venue"
},
  "geometry": {"coordinates":[4.413599968,50.720500946],"type":"Point"}
}