{
  "type": "Feature",
  "properties": {
    "addr:full":"De Parre 2 Rijkevorsel Antwerpen 2310",
    "addr:housenumber":"2",
    "addr:postcode":"2310",
    "addr:street":"Parre",
    "iso:country":"BE",
    "sg:address":"De Parre 2",
    "sg:city":"Rijkevorsel",
    "sg:orig_category":"Groententeelt",
    "sg:phone":"+32 3 312 49 43",
    "sg:postcode":"2310",
    "sg:province":"Antwerpen",
    "wof:name":"Josephus Janssens",
    "wof:placetype":"venue"
},
  "geometry": {"coordinates":[4.7697291374,51.3383674622],"type":"Point"}
}