{
  "type": "Feature",
  "properties": {
    "iso:country":"BE",
    "sg:address":"Moenstraat 37",
    "sg:city":"Zwevegem",
    "sg:classifiers":[
        {
            "category":"Food & Beverages",
            "subcategory":"Fruits & Vegetables",
            "type":"Retail Goods"
        }
    ],
    "sg:phone":"+32 56 45 51 87",
    "sg:postcode":"8554",
    "sg:province":"West-Vlaanderen",
    "sg:tags":[
        "l\u00e9gumes",
        "gr"
    ],
    "wof:name":"Blomme Marcel",
    "wof:placetype":"venue"
},
  "geometry": {"coordinates":[3.3772130013,50.7599601746],"type":"Point"}
}