{
  "type": "Feature",
  "properties": {
    "iso:country":"BE",
    "sg:address":"Vierde Regiment Karabiniersstraat 5",
    "sg:city":"Zonnebeke (passendale)",
    "sg:classifiers":[
        {
            "category":"Professional",
            "subcategory":"Lawyer & Legal Services",
            "type":"Services"
        }
    ],
    "sg:phone":"+32 51 77 70 08",
    "sg:postcode":"8980",
    "sg:province":"West-Vlaanderen",
    "sg:tags":[
        "notary"
    ],
    "wof:name":"Debucquoy L",
    "wof:placetype":"venue"
},
  "geometry": {"coordinates":[2.9872550964,50.8730812073],"type":"Point"}
}