{
  "type": "Feature",
  "properties": {
    "addr:full":"Rue Joseph Dechamps 18 Wavre Brabant Wallon 1300",
    "addr:housenumber":"18;1300",
    "addr:street":"Rue Joseph Dechamps",
    "iso:country":"BE",
    "sg:address":"Rue Joseph Dechamps 18",
    "sg:city":"Wavre",
    "sg:orig_category":"Artsen and specialisten",
    "sg:phone":"+32 10 41 70 70",
    "sg:postcode":"1300",
    "sg:province":"Brabant Wallon",
    "wof:name":"Alain Danhaive",
    "wof:placetype":"venue"
},
  "geometry": {"coordinates":[4.6116552353,50.7134132385],"type":"Point"}
}