{
  "type": "Feature",
  "properties": {
    "addr:full":"Westweg 3 Maldegem Oost-Vlaanderen 9990",
    "addr:housenumber":"3",
    "addr:postcode":"9990",
    "addr:street":"Westweg",
    "iso:country":"BE",
    "sg:address":"Westweg 3",
    "sg:city":"Maldegem",
    "sg:orig_category":"Rundveehouders Varkenskwekers",
    "sg:phone":"+32 50 71 23 63",
    "sg:postcode":"9990",
    "sg:province":"Oost-Vlaanderen",
    "wof:name":"Andre De Clercq",
    "wof:placetype":"venue"
},
  "geometry": {"coordinates":[3.4621069431,51.2347984314],"type":"Point"}
}