{
  "type": "Feature",
  "properties": {
    "addr:full":"Beverlosesteenweg 322 Beringen (paal) Limburg 3583",
    "addr:housenumber":"322",
    "addr:postcode":"3583",
    "addr:street":"Beverlosesteenweg",
    "iso:country":"BE",
    "sg:address":"Beverlosesteenweg 322",
    "sg:city":"Beringen (paal)",
    "sg:classifiers":[
        {
            "category":"Health Services",
            "subcategory":"Health Practitioner",
            "type":"Services"
        }
    ],
    "sg:phone":"+32 11 45 00 11",
    "sg:postcode":"3583",
    "sg:province":"Limburg",
    "sg:tags":[
        "physiotherapist"
    ],
    "wof:name":"Ghys Caroline",
    "wof:placetype":"venue"
},
  "geometry": {"coordinates":[5.2101111412,51.0707054138],"type":"Point"}
}