{
  "type": "Feature",
  "properties": {
    "addr:full":"Bijkhoevelaan 16 Wijnegem Antwerpen 2110",
    "addr:housenumber":"16",
    "addr:postcode":"2110",
    "addr:street":"Bijkhoevelaan",
    "iso:country":"BE",
    "sg:address":"Bijkhoevelaan 16",
    "sg:city":"Wijnegem",
    "sg:classifiers":[
        {
            "category":"Professional",
            "subcategory":"Employment Agencies",
            "type":"Services"
        }
    ],
    "sg:phone":"+32 3 360 61 50",
    "sg:postcode":"2110",
    "sg:province":"Antwerpen",
    "sg:tags":[
        "asbestos",
        "disposal",
        "removal"
    ],
    "wof:name":"Asbestos Removal Nv",
    "wof:placetype":"venue"
},
  "geometry": {"coordinates":[4.4942979813,51.2320480347],"type":"Point"}
}