{
  "type": "Feature",
  "properties": {
    "iso:country":"BE",
    "sg:address":"Liersebaan 20",
    "sg:city":"Zandhoven",
    "sg:classifiers":[
        {
            "category":"Insurance",
            "subcategory":"Insurance Agent",
            "type":"Services"
        }
    ],
    "sg:phone":"+32 3 484 64 07",
    "sg:postcode":"2240",
    "sg:province":"Antwerpen",
    "sg:tags":[
        "verzekeringsmakelaars",
        "expert"
    ],
    "wof:name":"Dieleman Verzekeringen",
    "wof:placetype":"venue"
},
  "geometry": {"coordinates":[4.6589288712,51.2144546509],"type":"Point"}
}