{
  "type": "Feature",
  "properties": {
    "addr:full":"Poedeldreef 37 Brecht Antwerpen 2960",
    "addr:housenumber":"37",
    "addr:postcode":"2960",
    "addr:street":"Poedeldreef",
    "iso:country":"BE",
    "sg:address":"Poedeldreef 37",
    "sg:city":"Brecht",
    "sg:classifiers":[
        {
            "category":"Building & Trades",
            "subcategory":"Electrical",
            "type":"Services"
        }
    ],
    "sg:phone":"+32 3 663 64 31",
    "sg:postcode":"2960",
    "sg:province":"Antwerpen",
    "sg:tags":[
        "electric",
        "-",
        "housewiring",
        "contractor"
    ],
    "wof:name":"Wittevrongel J",
    "wof:placetype":"venue"
},
  "geometry": {"coordinates":[4.561319828,51.3162384033],"type":"Point"}
}