{
  "type": "Feature",
  "properties": {
    "addr:full":"Rue Du Commerce 1 Ciney Namur 5590",
    "addr:housenumber":"1",
    "addr:postcode":"5590",
    "addr:street":"Rue Du Commerce",
    "iso:country":"BE",
    "sg:address":"Rue Du Commerce 1",
    "sg:city":"Ciney",
    "sg:orig_category":"Banken and kredietinstellingen",
    "sg:phone":"+32 83 21 28 09",
    "sg:postcode":"5590",
    "sg:province":"Namur",
    "wof:name":"Bacob",
    "wof:placetype":"venue"
},
  "geometry": {"coordinates":[5.1000227928,50.2952880859],"type":"Point"}
}