{
  "type": "Feature",
  "properties": {
    "iso:country":"BE",
    "sg:address":"Spaanseweg 6",
    "sg:city":"Sint-pieters-leeuw",
    "sg:orig_category":"HUISBRANDOLIE",
    "sg:phone":"+32 2 377 35 48",
    "sg:postcode":"1600",
    "sg:province":"Vlaams-Brabant",
    "wof:name":"Joseph Van Osselaer",
    "wof:placetype":"venue"
},
  "geometry": {"coordinates":[4.2758541107,50.7947463989],"type":"Point"}
}