{
  "type": "Feature",
  "properties": {
    "iso:country":"BE",
    "sg:address":"Nijvelsesteenweg 404",
    "sg:city":"Halle",
    "sg:classifiers":[
        {
            "category":"Communications",
            "subcategory":"Film & Video Production",
            "type":"Services"
        }
    ],
    "sg:phone":"+32 2 361 10 48",
    "sg:postcode":"1500",
    "sg:province":"Vlaams-Brabant",
    "sg:tags":[
        "realisation",
        "-"
    ],
    "wof:name":"Corthals K",
    "wof:placetype":"venue"
},
  "geometry": {"coordinates":[4.2498221397,50.7215957642],"type":"Point"}
}