{
  "type": "Feature",
  "properties": {
    "addr:full":"Rue Leopold Ii 20 Mons Hainaut 7000",
    "addr:housenumber":"20",
    "addr:postcode":"7000",
    "addr:street":"Rue Leopold Ii;Hainaut",
    "iso:country":"BE",
    "sg:address":"Rue Leopold Ii 20",
    "sg:city":"Mons",
    "sg:classifiers":[
        {
            "category":"Travel",
            "subcategory":"Hotels & Motels",
            "type":"Entertainment"
        }
    ],
    "sg:phone":"+32 65 31 46 64",
    "sg:postcode":"7000",
    "sg:province":"Hainaut",
    "wof:name":"Metropole (hotel) Sprl",
    "wof:placetype":"venue"
},
  "geometry": {"coordinates":[3.9436941147,50.4529724121],"type":"Point"}
}