{
  "type": "Feature",
  "properties": {
    "iso:country":"BE",
    "sg:address":"Stationsstraat 125",
    "sg:city":"Hooglede (gits)",
    "sg:classifiers":[
        {
            "category":"Utilities",
            "subcategory":"Natural Gas",
            "type":"Services"
        }
    ],
    "sg:phone":"+32 51 22 69 31",
    "sg:postcode":"8830",
    "sg:province":"West-Vlaanderen",
    "sg:tags":[
        "welding"
    ],
    "wof:name":"Versyck-demeulenaere Bvba",
    "wof:placetype":"venue"
},
  "geometry": {"coordinates":[3.1074120998,50.9981231689],"type":"Point"}
}