{
  "type": "Feature",
  "properties": {
    "iso:country":"BE",
    "sg:address":"Oudstrijdersstraat 11",
    "sg:city":"Asse",
    "sg:orig_category":"Drukkerijen and copyshops",
    "sg:phone":"+32 2 452 90 19",
    "sg:postcode":"1730",
    "sg:province":"Vlaams-Brabant",
    "wof:name":"Drukkerij Demeulemeester",
    "wof:placetype":"venue"
},
  "geometry": {"coordinates":[4.2176527977,50.9328804016],"type":"Point"}
}