{
  "type": "Feature",
  "properties": {
    "addr:full":"Heirstraat 161 Maasmechelen Limburg 3630",
    "addr:housenumber":"161",
    "addr:postcode":"3630",
    "addr:street":"Heirstraat",
    "iso:country":"BE",
    "sg:address":"Heirstraat 161",
    "sg:city":"Maasmechelen",
    "sg:orig_category":"Installatie van houten of kunststof schrijnwerk",
    "sg:phone":"+32 89 76 75 47",
    "sg:postcode":"3630",
    "sg:province":"Limburg",
    "wof:name":"Coenen",
    "wof:placetype":"venue"
},
  "geometry": {"coordinates":[5.6999950409,50.966594696],"type":"Point"}
}