{
  "type": "Feature",
  "properties": {
    "addr:full":"Keizerstraat 20-22 Antwerpen Antwerpen 2000",
    "addr:postcode":"20-22;2000",
    "addr:street":"Keizerstraat",
    "iso:country":"BE",
    "sg:address":"Keizerstraat 20-22",
    "sg:city":"Antwerpen",
    "sg:orig_category":"Zeevrachtagentschappen",
    "sg:phone":"+32 3 231 69 30",
    "sg:postcode":"2000",
    "sg:province":"Antwerpen",
    "wof:name":"Coli Shipping & Transport",
    "wof:placetype":"venue"
},
  "geometry": {"coordinates":[4.406648159,51.2216262817],"type":"Point"}
}