{
  "type": "Feature",
  "properties": {
    "iso:country":"BE",
    "sg:address":"Lincolnstraat 48",
    "sg:city":"Ukkel/uccle",
    "sg:orig_category":"Film-, tv- and videoproductie",
    "sg:phone":"+32 476 41 86 97",
    "sg:postcode":"1180",
    "sg:province":"Bruxelles-Capitale",
    "wof:name":"Y. Opstaele",
    "wof:placetype":"venue"
},
  "geometry": {"coordinates":[4.3635721207,50.8147239685],"type":"Point"}
}