{
  "type": "Feature",
  "properties": {
    "iso:country":"BE",
    "sg:address":"Rue De Bruxelles 121",
    "sg:city":"Tubize",
    "sg:classifiers":[
        {
            "category":"Manufacturing",
            "subcategory":"Jewelry",
            "type":"Manufacturing & Wholesale Goods"
        }
    ],
    "sg:phone":"+32 2 355 79 02",
    "sg:postcode":"1480",
    "sg:province":"Brabant Wallon",
    "sg:tags":[
        "jewellery",
        "fancy"
    ],
    "wof:name":"Van Der Lyn-bury & Fr\u00e8re S.a.",
    "wof:placetype":"venue"
},
  "geometry": {"coordinates":[4.2050738335,50.6975708008],"type":"Point"}
}