{
  "type": "Feature",
  "properties": {
    "addr:full":"Rue De La Paix 9 Aywaille Li\u00e8ge 4920",
    "addr:housenumber":"9",
    "addr:postcode":"4920",
    "addr:street":"Rue De La Paix",
    "iso:country":"BE",
    "sg:address":"Rue De La Paix 9",
    "sg:city":"Aywaille",
    "sg:classifiers":[
        {
            "category":"Professional",
            "type":"Services"
        }
    ],
    "sg:phone":"+32 4 384 54 87",
    "sg:postcode":"4920",
    "sg:province":"Li\u00e8ge",
    "sg:tags":[
        "industrial",
        "automation"
    ],
    "wof:name":"Nils O",
    "wof:placetype":"venue"
},
  "geometry": {"coordinates":[5.6723771095,50.4683151245],"type":"Point"}
}