{
  "type": "Feature",
  "properties": {
    "addr:full":"Antwerpseweg 81a Geel Antwerpen 2440",
    "addr:housenumber":"81a",
    "addr:postcode":"2440",
    "addr:street":"Antwerpseweg",
    "iso:country":"BE",
    "sg:address":"Antwerpseweg 81a",
    "sg:city":"Geel",
    "sg:classifiers":[
        {
            "category":"Manufacturing",
            "subcategory":"Wood Products",
            "type":"Manufacturing & Wholesale Goods"
        }
    ],
    "sg:phone":"+32 14 58 26 19",
    "sg:postcode":"2440",
    "sg:province":"Antwerpen",
    "sg:tags":[
        "solid",
        "door"
    ],
    "wof:name":"De Kegel Interieur Nv",
    "wof:placetype":"venue"
},
  "geometry": {"coordinates":[4.958106041,51.1466331482],"type":"Point"}
}