{
  "type": "Feature",
  "properties": {
    "addr:full":"Eikelstraat 6 Heuvelland West-Vlaanderen 8950",
    "addr:housenumber":"6",
    "addr:postcode":"8950",
    "addr:street":"Eikelstraat",
    "iso:country":"BE",
    "sg:address":"Eikelstraat 6",
    "sg:city":"Heuvelland",
    "sg:orig_category":"Eleveurs and marchands de porcs. Eleveurs de bovins",
    "sg:phone":"+32 57 44 45 10",
    "sg:postcode":"8950",
    "sg:province":"West-Vlaanderen",
    "wof:name":"Dirk Vermeersch",
    "wof:placetype":"venue"
},
  "geometry": {"coordinates":[2.8152329922,50.7360992432],"type":"Point"}
}