{
  "type": "Feature",
  "properties": {
    "iso:country":"BE",
    "sg:address":"Gerhees 82",
    "sg:city":"Ham",
    "sg:orig_category":"Woningbouw",
    "sg:phone":"+32 11 34 29 51",
    "sg:postcode":"3945",
    "sg:province":"Limburg",
    "wof:name":"Woningbouw Van Look",
    "wof:placetype":"venue"
},
  "geometry": {"coordinates":[5.1776199341,51.1046104431],"type":"Point"}
}