{
  "type": "Feature",
  "properties": {
    "iso:country":"BE",
    "sg:address":"Rue De L' Abbaye 8",
    "sg:city":"Assesse",
    "sg:orig_category":"Herstelling horloges and juwelen Juwelen and horloges Verlichting and huishoudartikelen",
    "sg:phone":"+32 83 65 52 69",
    "sg:postcode":"5336",
    "sg:province":"Namur",
    "wof:name":"Leon Pirmez",
    "wof:placetype":"venue"
},
  "geometry": {"coordinates":[4.9962368011,50.3916511536],"type":"Point"}
}