{
  "type": "Feature",
  "properties": {
    "addr:full":"Blancefloerlaan 46 Antwerpen Antwerpen 2050",
    "addr:housenumber":"46",
    "addr:postcode":"2050",
    "addr:street":"Blancefloerlaan",
    "iso:country":"BE",
    "sg:address":"Blancefloerlaan 46",
    "sg:city":"Antwerpen",
    "sg:orig_category":"Solariums",
    "sg:phone":"+32 3 219 72 95",
    "sg:postcode":"2050",
    "sg:province":"Antwerpen",
    "wof:name":"Nicosia",
    "wof:placetype":"venue"
},
  "geometry": {"coordinates":[4.3784651756,51.2206497192],"type":"Point"}
}