{
  "type": "Feature",
  "properties": {
    "addr:full":"Nachtegaalstraat 88 Wevelgem West-Vlaanderen 8560",
    "addr:housenumber":"88",
    "addr:postcode":"8560",
    "addr:street":"Nachtegaalstraat",
    "iso:country":"BE",
    "sg:address":"Nachtegaalstraat 88",
    "sg:city":"Wevelgem",
    "sg:classifiers":[
        {
            "category":"Professional",
            "subcategory":"Management & Consulting",
            "type":"Services"
        }
    ],
    "sg:phone":"+32 56 41 35 04",
    "sg:postcode":"8560",
    "sg:province":"West-Vlaanderen",
    "sg:tags":[
        "tax-consultants"
    ],
    "wof:name":"Taillieu J",
    "wof:placetype":"venue"
},
  "geometry": {"coordinates":[3.1753129959,50.8149299622],"type":"Point"}
}