{
  "type": "Feature",
  "properties": {
    "iso:country":"BE",
    "sg:address":"R De L'esplanade 47",
    "sg:city":"Bammeux-sprimont",
    "sg:classifiers":[
        {
            "category":"Travel",
            "subcategory":"Hotels & Motels",
            "type":"Entertainment"
        }
    ],
    "sg:phone":"+32 4 360 81 25",
    "sg:postcode":"4141",
    "sg:province":"Li\u00e8ge",
    "sg:tags":[
        "hotels",
        "business",
        "restaurant"
    ],
    "wof:name":"Hotel-restaurant-halleux Sprl",
    "wof:placetype":"venue"
},
  "geometry": {"coordinates":[5.7449140549,50.5387840271],"type":"Point"}
}