{
  "type": "Feature",
  "properties": {
    "addr:full":"Burgscheldestraat 40 Oudenaarde Oost-Vlaanderen 9700",
    "addr:housenumber":"40",
    "addr:postcode":"9700",
    "addr:street":"Burgscheldestraat",
    "iso:country":"BE",
    "sg:address":"Burgscheldestraat 40",
    "sg:city":"Oudenaarde",
    "sg:classifiers":[
        {
            "category":"Social Services",
            "type":"Services"
        }
    ],
    "sg:phone":"+32 55 30 04 46",
    "sg:postcode":"9700",
    "sg:province":"Oost-Vlaanderen",
    "wof:name":"Bemiddelingscommissie Bijzondere Jeugd- Bijstand-oudenaarde",
    "wof:placetype":"venue"
},
  "geometry": {"coordinates":[3.6065859795,50.8429718018],"type":"Point"}
}