{
  "type": "Feature",
  "properties": {
    "addr:full":"Tennisstraat 1 Gent (gentbrugge) Oost-Vlaanderen 9050",
    "addr:housenumber":"1",
    "addr:postcode":"9050",
    "addr:street":"Tennisstraat",
    "iso:country":"BE",
    "sg:address":"Tennisstraat 1",
    "sg:city":"Gent (gentbrugge)",
    "sg:classifiers":[
        {
            "category":"Health Services",
            "subcategory":"Doctor",
            "type":"Services"
        }
    ],
    "sg:phone":"+32 9 231 48 48",
    "sg:postcode":"9050",
    "sg:province":"Oost-Vlaanderen",
    "sg:tags":[
        "medicinephysicians",
        "surgeon"
    ],
    "wof:name":"Dr R\u00d6tgens Erik Bvba",
    "wof:placetype":"venue"
},
  "geometry": {"coordinates":[3.765073061,51.0300102234],"type":"Point"}
}