{
  "type": "Feature",
  "properties": {
    "addr:full":"Molenstraat 46 Assenede Oost-Vlaanderen 9960",
    "addr:housenumber":"46",
    "addr:postcode":"9960",
    "addr:street":"Molenstraat",
    "iso:country":"BE",
    "sg:address":"Molenstraat 46",
    "sg:city":"Assenede",
    "sg:classifiers":[
        {
            "category":"Building & Trades",
            "subcategory":"Landscaping Services",
            "type":"Services"
        }
    ],
    "sg:phone":"+32 9 344 32 59",
    "sg:postcode":"9960",
    "sg:province":"Oost-Vlaanderen",
    "sg:tags":[
        "gardening",
        "garden",
        "maintenance"
    ],
    "wof:name":"Van Brussel A",
    "wof:placetype":"venue"
},
  "geometry": {"coordinates":[3.7483661175,51.2249794006],"type":"Point"}
}