{
  "type": "Feature",
  "properties": {
    "addr:full":"Smissestraat 28 Laakdal Antwerpen 2430",
    "addr:housenumber":"28",
    "addr:postcode":"2430",
    "addr:street":"Smissestraat",
    "iso:country":"BE",
    "sg:address":"Smissestraat 28",
    "sg:city":"Laakdal",
    "sg:orig_category":"Postkantoren Verzekeringsmakelaars and experts",
    "sg:phone":"+32 13 66 10 16",
    "sg:postcode":"2430",
    "sg:province":"Antwerpen",
    "wof:name":"De Post",
    "wof:placetype":"venue"
},
  "geometry": {"coordinates":[5.0222611427,51.0795707703],"type":"Point"}
}