{
  "type": "Feature",
  "properties": {
    "iso:country":"BE",
    "sg:address":"Rue De La Station 33",
    "sg:city":"Froidchapelle",
    "sg:orig_category":"Rundveehouders",
    "sg:phone":"+32 60 41 16 95",
    "sg:postcode":"6440",
    "sg:province":"Hainaut",
    "wof:name":"Leon Charneux",
    "wof:placetype":"venue"
},
  "geometry": {"coordinates":[4.3254032135,50.1467132568],"type":"Point"}
}