{
  "type": "Feature",
  "properties": {
    "iso:country":"BE",
    "sg:address":"Parkstraat 5",
    "sg:city":"Menen",
    "sg:orig_category":"Sportclubs",
    "sg:phone":"+32 56 51 42 02",
    "sg:postcode":"8930",
    "sg:province":"West-Vlaanderen",
    "wof:name":"Chin Do Jang Menen",
    "wof:placetype":"venue"
},
  "geometry": {"coordinates":[3.1238501072,50.8000526428],"type":"Point"}
}