{
  "type": "Feature",
  "properties": {
    "iso:country":"BE",
    "sg:address":"Avenue Des Martyrs 274",
    "sg:city":"Fl\u00e9ron",
    "sg:classifiers":[
        {
            "category":"Shopping",
            "subcategory":"Shoes",
            "type":"Retail Goods"
        }
    ],
    "sg:phone":"+32 4 358 37 74",
    "sg:postcode":"4620",
    "sg:province":"Li\u00e8ge",
    "sg:tags":[
        "slipper",
        "-"
    ],
    "wof:name":"Step By Step",
    "wof:placetype":"venue"
},
  "geometry": {"coordinates":[5.6854801178,50.6145248413],"type":"Point"}
}