{
  "type": "Feature",
  "properties": {
    "addr:full":"39-41 Begijnenvest Antwerpen Antwerpen 2000",
    "addr:housenumber":"39-41",
    "addr:postcode":"2000",
    "addr:street":"Begijnenvest",
    "iso:country":"BE",
    "sg:address":"39-41 Begijnenvest",
    "sg:city":"Antwerpen",
    "sg:classifiers":[
        {
            "category":"Manufacturing",
            "subcategory":"Printing",
            "type":"Manufacturing & Wholesale Goods"
        }
    ],
    "sg:phone":"+32 3 231 11 59",
    "sg:postcode":"2000",
    "sg:province":"Antwerpen",
    "sg:tags":[
        "publishing"
    ],
    "wof:name":"Drukkerij A Van Den Bosch-callot Nv",
    "wof:placetype":"venue"
},
  "geometry": {"coordinates":[4.4063849449,51.2119598389],"type":"Point"}
}