{
  "type": "Feature",
  "properties": {
    "iso:country":"BE",
    "sg:address":"Elfnovemberstraat 22",
    "sg:city":"Gent (mariakerke)",
    "sg:classifiers":[
        {
            "category":"Health Services",
            "subcategory":"Doctor",
            "type":"Services"
        }
    ],
    "sg:phone":"+32 9 227 19 00",
    "sg:postcode":"9030",
    "sg:province":"Oost-Vlaanderen",
    "sg:tags":[
        "medicinephysicians",
        "surgeon"
    ],
    "wof:name":"Derave R",
    "wof:placetype":"venue"
},
  "geometry": {"coordinates":[3.6786899567,51.0725898743],"type":"Point"}
}