{
  "type": "Feature",
  "properties": {
    "addr:full":"Maaldestedestraat 137 Ieper West-Vlaanderen 8902",
    "addr:housenumber":"137",
    "addr:postcode":"8902",
    "addr:street":"Maaldestedestraat",
    "iso:country":"BE",
    "sg:address":"Maaldestedestraat 137",
    "sg:city":"Ieper",
    "sg:orig_category":"Producteurs de fruits",
    "sg:phone":"+32 57 20 24 71",
    "sg:postcode":"8902",
    "sg:province":"West-Vlaanderen",
    "wof:name":"Henk Mahieu",
    "wof:placetype":"venue"
},
  "geometry": {"coordinates":[2.9164168835,50.8467178345],"type":"Point"}
}