{
  "type": "Feature",
  "properties": {
    "addr:full":"Pieter Reypenslei 8 Mortsel Antwerpen 2640",
    "addr:housenumber":"8",
    "addr:postcode":"2640",
    "addr:street":"Pieter Reypenslei",
    "iso:country":"BE",
    "sg:address":"Pieter Reypenslei 8",
    "sg:city":"Mortsel",
    "sg:classifiers":[
        {
            "category":"Shopping",
            "subcategory":"Gifts & Souvenirs",
            "type":"Retail Goods"
        }
    ],
    "sg:phone":"+32 3 440 85 88",
    "sg:postcode":"2640",
    "sg:province":"Antwerpen",
    "sg:tags":[
        "-"
    ],
    "wof:name":"Contempo",
    "wof:placetype":"venue"
},
  "geometry": {"coordinates":[4.4531841278,51.1700134277],"type":"Point"}
}