{
  "type": "Feature",
  "properties": {
    "iso:country":"BE",
    "sg:address":"Ardooisesteenweg 6",
    "sg:city":"Roeselare",
    "sg:orig_category":"M\u00e9decins and sp\u00e9cialistes",
    "sg:phone":"+32 51 24 29 45",
    "sg:postcode":"8800",
    "sg:province":"West-Vlaanderen",
    "wof:name":"Johan Bosschaert",
    "wof:placetype":"venue"
},
  "geometry": {"coordinates":[3.1312398911,50.9486236572],"type":"Point"}
}