{
  "type": "Feature",
  "properties": {
    "addr:full":"Esenweg 195 Diksmuide West-Vlaanderen 8600",
    "addr:housenumber":"195",
    "addr:postcode":"8600",
    "iso:country":"BE",
    "sg:address":"Esenweg 195",
    "sg:city":"Diksmuide",
    "sg:orig_category":"Ordinateurs and \u00e9quipement informatique",
    "sg:phone":"+32 51 50 13 72",
    "sg:postcode":"8600",
    "sg:province":"West-Vlaanderen",
    "wof:name":"F.c.s. Service",
    "wof:placetype":"venue"
},
  "geometry": {"coordinates":[2.8822650909,51.0304870605],"type":"Point"}
}