{
  "type": "Feature",
  "properties": {
    "addr:full":"Turnhoutsebaan 209 Diest (molenstede) Vlaams-Brabant 3294",
    "addr:housenumber":"209",
    "addr:postcode":"3294",
    "addr:street":"Turnhoutsebaan",
    "iso:country":"BE",
    "sg:address":"Turnhoutsebaan 209",
    "sg:city":"Diest (molenstede)",
    "sg:classifiers":[
        {
            "category":"Autos & Motor Vehicles",
            "subcategory":"Automobile Sales",
            "type":"Retail Goods"
        }
    ],
    "sg:phone":"+32 13 32 17 48",
    "sg:postcode":"3294",
    "sg:province":"Vlaams-Brabant",
    "sg:tags":[
        "delivery",
        "-",
        "used",
        "van",
        "truck"
    ],
    "wof:name":"J.c.t. Bvba",
    "wof:placetype":"venue"
},
  "geometry": {"coordinates":[5.0229830742,51.0122947693],"type":"Point"}
}