{
  "type": "Feature",
  "properties": {
    "addr:full":"Honingenveldstraat 23 Gooik Vlaams-Brabant 1755",
    "addr:housenumber":"23",
    "addr:postcode":"1755",
    "addr:street":"Honingenveldstraat",
    "iso:country":"BE",
    "sg:address":"Honingenveldstraat 23",
    "sg:city":"Gooik",
    "sg:classifiers":[
        {
            "category":"Freight",
            "type":"Transportation"
        }
    ],
    "sg:phone":"+32 2 532 10 32",
    "sg:postcode":"1755",
    "sg:province":"Vlaams-Brabant",
    "sg:tags":[
        "-",
        "transport"
    ],
    "wof:name":"Svederick Bvba",
    "wof:placetype":"venue"
},
  "geometry": {"coordinates":[4.1325302124,50.7917518616],"type":"Point"}
}