{
  "type": "Feature",
  "properties": {
    "iso:country":"BE",
    "sg:address":"Luingnestraat 270",
    "sg:city":"Kortrijk",
    "sg:orig_category":"Eleveurs de bovins",
    "sg:phone":"+32 56 41 38 24",
    "sg:postcode":"8511",
    "sg:province":"West-Vlaanderen",
    "wof:name":"Ars\u00c8ne Lavaert",
    "wof:placetype":"venue"
},
  "geometry": {"coordinates":[3.2360699177,50.763168335],"type":"Point"}
}