{
  "type": "Feature",
  "properties": {
    "iso:country":"BE",
    "sg:address":"Antwerpsestraat 91bb32",
    "sg:city":"Boom",
    "sg:orig_category":"M\u00e9decins and sp\u00e9cialistes",
    "sg:phone":"+32 3 888 28 72",
    "sg:postcode":"2850",
    "sg:province":"Antwerpen",
    "wof:name":"Diane J.a. De Neubourg",
    "wof:placetype":"venue"
},
  "geometry": {"coordinates":[4.3652057648,51.0882644653],"type":"Point"}
}