{
  "type": "Feature",
  "properties": {
    "addr:full":"Groot-bijgaardenstraat 551 Berchem-sainte-agathe Bruxelles-Capitale 1082",
    "addr:housenumber":"551",
    "addr:postcode":"1082",
    "addr:street":"Groot-Bijgaardenstraat",
    "iso:country":"BE",
    "sg:address":"Groot-bijgaardenstraat 551",
    "sg:city":"Berchem-sainte-agathe",
    "sg:classifiers":[
        {
            "category":"Shopping",
            "subcategory":"Bicycles & Sporting Goods",
            "type":"Retail Goods"
        }
    ],
    "sg:phone":"+32 2 465 48 44",
    "sg:postcode":"1082",
    "sg:province":"Bruxelles-Capitale",
    "sg:tags":[
        "article",
        "de",
        "sport",
        "camping"
    ],
    "wof:name":"Stringing Office",
    "wof:placetype":"venue"
},
  "geometry": {"coordinates":[4.2844672203,50.8657112122],"type":"Point"}
}