{
  "type": "Feature",
  "properties": {
    "addr:full":"Balendijk 222 Lommel Limburg 3920",
    "addr:housenumber":"222",
    "addr:postcode":"3920",
    "iso:country":"BE",
    "sg:address":"Balendijk 222",
    "sg:city":"Lommel",
    "sg:classifiers":[
        {
            "category":"Manufacturing",
            "subcategory":"Metals",
            "type":"Manufacturing & Wholesale Goods"
        }
    ],
    "sg:phone":"+32 11 54 19 81",
    "sg:postcode":"3920",
    "sg:province":"Limburg",
    "sg:tags":[
        "turning"
    ],
    "wof:name":"Bergmans Chris Tools Nv",
    "wof:placetype":"venue"
},
  "geometry": {"coordinates":[5.2757601738,51.2175598145],"type":"Point"}
}