{
  "type": "Feature",
  "properties": {
    "iso:country":"BE",
    "sg:address":"Bosstraat 39",
    "sg:city":"Westerlo (tongerlo)",
    "sg:classifiers":[
        {
            "category":"Ice Cream",
            "type":"Food & Drink"
        }
    ],
    "sg:phone":"+32 14 23 41 07",
    "sg:postcode":"2260",
    "sg:province":"Antwerpen",
    "wof:name":"Ceuppens J",
    "wof:placetype":"venue"
},
  "geometry": {"coordinates":[4.9025650024,51.1187210083],"type":"Point"}
}