{
  "type": "Feature",
  "properties": {
    "iso:country":"BE",
    "sg:address":"Lichtveld 552a",
    "sg:city":"Tessenderlo",
    "sg:classifiers":[
        {
            "category":"Professional",
            "subcategory":"Lawyer & Legal Services",
            "type":"Services"
        }
    ],
    "sg:phone":"+32 13 67 59 08",
    "sg:postcode":"3980",
    "sg:province":"Limburg",
    "wof:name":"Lievesoens Kurt",
    "wof:placetype":"venue"
},
  "geometry": {"coordinates":[5.0945501328,51.0645217896],"type":"Point"}
}