{
  "type": "Feature",
  "properties": {
    "iso:country":"BE",
    "sg:address":"Chauss\u00e9e De Beaumont 192b",
    "sg:city":"Mons (spiennes)",
    "sg:classifiers":[
        {
            "category":"Sports & Exercise",
            "subcategory":"Bowling",
            "type":"Entertainment"
        }
    ],
    "sg:phone":"+32 65 33 56 16",
    "sg:postcode":"7032",
    "sg:province":"Hainaut",
    "sg:tags":[
        "skittle",
        "alley"
    ],
    "wof:name":"Barri\u00e8re Bowling",
    "wof:placetype":"venue"
},
  "geometry": {"coordinates":[3.9869709015,50.4255142212],"type":"Point"}
}