{
  "type": "Feature",
  "properties": {
    "iso:country":"BE",
    "sg:address":"Paul Lebrunstraat 1",
    "sg:city":"Leuven",
    "sg:orig_category":"M\u00e9decins and sp\u00e9cialistes",
    "sg:phone":"+32 16 23 81 74",
    "sg:postcode":"3000",
    "sg:province":"Vlaams-Brabant",
    "wof:name":"Jean-marie Goethals",
    "wof:placetype":"venue"
},
  "geometry": {"coordinates":[4.7025771141,50.8707237244],"type":"Point"}
}