{
  "type": "Feature",
  "properties": {
    "iso:country":"BE",
    "sg:address":"Gemeenteplaats 3",
    "sg:city":"Sint-jans-molenbeek/molenbeek-saint-jean",
    "sg:orig_category":"Slagers",
    "sg:phone":"+32 2 411 30 05",
    "sg:postcode":"1080",
    "sg:province":"Bruxelles-Capitale",
    "wof:name":"Beenhouwerij St.jean",
    "wof:placetype":"venue"
},
  "geometry": {"coordinates":[4.3381700516,50.8544120789],"type":"Point"}
}