{
  "type": "Feature",
  "properties": {
    "addr:full":"Diestsestraat 168 Leuven Vlaams-Brabant 3000",
    "addr:housenumber":"168",
    "addr:postcode":"3000",
    "addr:street":"Diestsestraat",
    "iso:country":"BE",
    "sg:address":"Diestsestraat 168",
    "sg:city":"Leuven",
    "sg:orig_category":"Electrom\u00e9nager, t\u00e9l\u00e9visions and radios",
    "sg:phone":"+32 16 22 43 64",
    "sg:postcode":"3000",
    "sg:province":"Vlaams-Brabant",
    "wof:name":"L.g. Goldstar Center",
    "wof:placetype":"venue"
},
  "geometry": {"coordinates":[4.7101268768,50.8813591003],"type":"Point"}
}