{
  "type": "Feature",
  "properties": {
    "addr:full":"Gte Hemmenweg 149 Zonhoven Limburg 3520",
    "addr:housenumber":"149",
    "addr:postcode":"3520",
    "addr:street":"Gte Hemmenweg",
    "iso:country":"BE",
    "sg:address":"Gte Hemmenweg 149",
    "sg:city":"Zonhoven",
    "sg:orig_category":"Non-Classified Establishments",
    "sg:phone":"+32 11 72 00 90",
    "sg:postcode":"3520",
    "sg:province":"Limburg",
    "wof:name":"Fico Bvba",
    "wof:placetype":"venue"
},
  "geometry": {"coordinates":[5.3974261284,50.9962043762],"type":"Point"}
}