{
  "type": "Feature",
  "properties": {
    "addr:full":"Rue Paul Janson 62 Anderlues Hainaut 6150",
    "addr:housenumber":"62",
    "addr:postcode":"6150",
    "addr:street":"Rue Paul Janson",
    "iso:country":"BE",
    "sg:address":"Rue Paul Janson 62",
    "sg:city":"Anderlues",
    "sg:orig_category":"Bloemen and planten",
    "sg:phone":"+32 71 52 51 88",
    "sg:postcode":"6150",
    "sg:province":"Hainaut",
    "wof:name":"Maison Marie-christine",
    "wof:placetype":"venue"
},
  "geometry": {"coordinates":[4.2752690315,50.4045333862],"type":"Point"}
}