{
  "type": "Feature",
  "properties": {
    "addr:full":"Gasthuisstraat 17 Geraardsbergen Oost-Vlaanderen 9500",
    "addr:housenumber":"17",
    "addr:postcode":"9500",
    "addr:street":"Gasthuisstraat",
    "iso:country":"BE",
    "sg:address":"Gasthuisstraat 17",
    "sg:city":"Geraardsbergen",
    "sg:classifiers":[
        {
            "category":"Health Services",
            "subcategory":"Dentist",
            "type":"Services"
        }
    ],
    "sg:phone":"+32 54 41 75 73",
    "sg:postcode":"9500",
    "sg:province":"Oost-Vlaanderen",
    "wof:name":"Elens Luc",
    "wof:placetype":"venue"
},
  "geometry": {"coordinates":[3.8774759769,50.7715530396],"type":"Point"}
}