{
  "type": "Feature",
  "properties": {
    "addr:full":"Chauss\u00c9e De Wavre 743 Etterbeek/etterbeek Bruxelles-Capitale 1040",
    "addr:housenumber":"743",
    "addr:postcode":"1040",
    "addr:street":"Chausse\u0301E De Wavre",
    "iso:country":"BE",
    "sg:address":"Chauss\u00c9e De Wavre 743",
    "sg:city":"Etterbeek/etterbeek",
    "sg:orig_category":"Magasins de r\u00e9parations d'articles personnels et m\u00e9nagers divers",
    "sg:phone":"+32 2 647 13 07",
    "sg:postcode":"1040",
    "sg:province":"Bruxelles-Capitale",
    "wof:name":"Sevan",
    "wof:placetype":"venue"
},
  "geometry": {"coordinates":[4.3921751976,50.8289833069],"type":"Point"}
}