{
  "type": "Feature",
  "properties": {
    "addr:full":"Meensesteenweg 14 Moorslede West-Vlaanderen 8890",
    "addr:housenumber":"14",
    "addr:postcode":"8890",
    "addr:street":"Meensesteenweg",
    "iso:country":"BE",
    "sg:address":"Meensesteenweg 14",
    "sg:city":"Moorslede",
    "sg:classifiers":[
        {
            "category":"Insurance",
            "subcategory":"Life Insurance",
            "type":"Services"
        }
    ],
    "sg:phone":"+32 56 50 24 03",
    "sg:postcode":"8890",
    "sg:province":"West-Vlaanderen",
    "sg:tags":[
        "assurance"
    ],
    "wof:name":"D. Vandommele",
    "wof:placetype":"venue"
},
  "geometry": {"coordinates":[3.1135869026,50.8897361755],"type":"Point"}
}