{
  "type": "Feature",
  "properties": {
    "addr:full":"Heirweg 3 Geraardsbergen (idegem) Oost-Vlaanderen 9506",
    "addr:housenumber":"3",
    "addr:postcode":"9506",
    "addr:street":"Heirweg",
    "iso:country":"BE",
    "sg:address":"Heirweg 3",
    "sg:city":"Geraardsbergen (idegem)",
    "sg:classifiers":[
        {
            "category":"Retail",
            "subcategory":"Veterinary Services",
            "type":"Services"
        }
    ],
    "sg:phone":"+32 54 51 51 10",
    "sg:postcode":"9506",
    "sg:province":"Oost-Vlaanderen",
    "sg:tags":[
        "veterinarian"
    ],
    "wof:name":"Van Der Schueren G",
    "wof:placetype":"venue"
},
  "geometry": {"coordinates":[3.9350149632,50.8079566956],"type":"Point"}
}