{
  "type": "Feature",
  "properties": {
    "addr:full":"Kalandeberg 8 Gent Oost-Vlaanderen 9000",
    "addr:housenumber":"8",
    "addr:postcode":"9000",
    "addr:street":"Kalandeberg;Oost-Vlaanderen",
    "iso:country":"BE",
    "sg:address":"Kalandeberg 8",
    "sg:city":"Gent",
    "sg:classifiers":[
        {
            "category":"Shopping",
            "subcategory":"Gifts & Souvenirs",
            "type":"Retail Goods"
        }
    ],
    "sg:phone":"+32 9 223 90 51",
    "sg:postcode":"9000",
    "sg:province":"Oost-Vlaanderen",
    "sg:tags":[
        "-"
    ],
    "wof:name":"Mezzo Gent",
    "wof:placetype":"venue"
},
  "geometry": {"coordinates":[3.7251830101,51.051399231],"type":"Point"}
}