{
  "type": "Feature",
  "properties": {
    "addr:full":"Rue Maurice-wilmotte 3 Li\u00c8ge Li\u00e8ge 4020",
    "addr:housenumber":"3",
    "addr:postcode":"4020",
    "addr:street":"Rue Maurice-Wilmotte",
    "iso:country":"BE",
    "sg:address":"Rue Maurice-wilmotte 3",
    "sg:city":"Li\u00c8ge",
    "sg:orig_category":"Brood, gebak and snoepgoed",
    "sg:phone":"+32 4 343 65 66",
    "sg:postcode":"4020",
    "sg:province":"Li\u00e8ge",
    "wof:name":"Boulangerie Desti",
    "wof:placetype":"venue"
},
  "geometry": {"coordinates":[5.6078181267,50.6474075317],"type":"Point"}
}