{
  "type": "Feature",
  "properties": {
    "addr:full":"Rue Des Chartreux 69 Brussel/bruxelles Bruxelles-Capitale 1000",
    "addr:housenumber":"69",
    "addr:postcode":"1000",
    "addr:street":"Rue Des Chartreux;/",
    "iso:country":"BE",
    "sg:address":"Rue Des Chartreux 69",
    "sg:city":"Brussel/bruxelles",
    "sg:orig_category":"M\u00e9decins and sp\u00e9cialistes",
    "sg:phone":"+32 2 512 24 54",
    "sg:postcode":"1000",
    "sg:province":"Bruxelles-Capitale",
    "wof:name":"Polyclinique Des Chartreux",
    "wof:placetype":"venue"
},
  "geometry": {"coordinates":[4.3439221382,50.8484268188],"type":"Point"}
}