{
  "type": "Feature",
  "properties": {
    "iso:country":"BE",
    "sg:address":"Rue Sainfoin 7",
    "sg:city":"Namur",
    "sg:orig_category":"Electrom\u00e9nager, t\u00e9l\u00e9visions and radios",
    "sg:phone":"+32 81 21 28 47",
    "sg:postcode":"5020",
    "sg:province":"Namur",
    "wof:name":"Guy Wanlin",
    "wof:placetype":"venue"
},
  "geometry": {"coordinates":[4.8703641891,50.4833831787],"type":"Point"}
}