{
  "type": "Feature",
  "properties": {
    "addr:full":"Avenue Du Marouset 142 Braine-le-comte Hainaut 7090",
    "addr:housenumber":"142",
    "addr:postcode":"7090",
    "addr:street":"Avenue Du Marouset",
    "iso:country":"BE",
    "sg:address":"Avenue Du Marouset 142",
    "sg:city":"Braine-le-comte",
    "sg:orig_category":"D\u00e9molition d\u00b4immeubles and terrassements",
    "sg:phone":"+32 67 55 65 55",
    "sg:postcode":"7090",
    "sg:province":"Hainaut",
    "wof:name":"Trebor De Backer",
    "wof:placetype":"venue"
},
  "geometry": {"coordinates":[4.1680688858,50.6097221375],"type":"Point"}
}