{
  "type": "Feature",
  "properties": {
    "addr:full":"Nieuwstraat 8 Oostende West-Vlaanderen 8400",
    "addr:housenumber":"8",
    "addr:postcode":"8400",
    "addr:street":"Nieuwstraat",
    "iso:country":"BE",
    "sg:address":"Nieuwstraat 8",
    "sg:city":"Oostende",
    "sg:classifiers":[
        {
            "category":"Restaurant",
            "type":"Food & Drink"
        }
    ],
    "sg:phone":"+32 59 50 47 04",
    "sg:postcode":"8400",
    "sg:province":"West-Vlaanderen",
    "wof:name":"Tearoom 't Krokantje",
    "wof:placetype":"venue"
},
  "geometry": {"coordinates":[2.9210300446,51.2333068848],"type":"Point"}
}