{
  "type": "Feature",
  "properties": {
    "iso:country":"BE",
    "sg:address":"Chauss\u00c9e De Bruxelles 343",
    "sg:city":"Overijse",
    "sg:orig_category":"V\u00e9hicules automobiles",
    "sg:phone":"+32 2 688 38 12",
    "sg:postcode":"3090",
    "sg:province":"Vlaams-Brabant",
    "wof:name":"Garage Aabecar",
    "wof:placetype":"venue"
},
  "geometry": {"coordinates":[4.5086698532,50.7826538086],"type":"Point"}
}