{
  "type": "Feature",
  "properties": {
    "iso:country":"BE",
    "sg:address":"Nieuwstr 86",
    "sg:city":"Diepenbeek",
    "sg:classifiers":[
        {
            "category":"Professional",
            "subcategory":"Computer Services",
            "type":"Services"
        }
    ],
    "sg:phone":"+32 11 35 10 10",
    "sg:postcode":"3590",
    "sg:province":"Limburg",
    "sg:tags":[
        "information",
        "technology",
        "software"
    ],
    "wof:name":"Briljant Software Nv",
    "wof:placetype":"venue"
},
  "geometry": {"coordinates":[5.4435482025,50.9198989868],"type":"Point"}
}