{
  "type": "Feature",
  "properties": {
    "addr:full":"Grand'place 15 Lessines Hainaut 7860",
    "addr:housenumber":"15",
    "addr:postcode":"7860",
    "addr:street":"Grand'Place;Hainaut",
    "iso:country":"BE",
    "sg:address":"Grand'place 15",
    "sg:city":"Lessines",
    "sg:classifiers":[
        {
            "category":"Insurance",
            "subcategory":"Insurance Agent",
            "type":"Services"
        }
    ],
    "sg:phone":"+32 68 33 75 00",
    "sg:postcode":"7860",
    "sg:province":"Hainaut",
    "sg:tags":[
        "broker"
    ],
    "wof:name":"Flament-de Loor",
    "wof:placetype":"venue"
},
  "geometry": {"coordinates":[3.8290889263,50.7124633789],"type":"Point"}
}