{
  "type": "Feature",
  "properties": {
    "iso:country":"BE",
    "sg:address":"Rue De La Grosse Pomme 10",
    "sg:city":"Mons",
    "sg:classifiers":[
        {
            "category":"Real Estate",
            "subcategory":"Architect",
            "type":"Services"
        }
    ],
    "sg:phone":"+32 476 92 62 72",
    "sg:postcode":"7000",
    "sg:province":"Hainaut",
    "wof:name":"Cockenpot O",
    "wof:placetype":"venue"
},
  "geometry": {"coordinates":[3.9460279942,50.4530754089],"type":"Point"}
}