{
  "type": "Feature",
  "properties": {
    "addr:full":"Muisstraat 11 Haaltert Oost-Vlaanderen 9450",
    "addr:housenumber":"11",
    "addr:postcode":"9450",
    "addr:street":"Muisstraat",
    "iso:country":"BE",
    "sg:address":"Muisstraat 11",
    "sg:city":"Haaltert",
    "sg:classifiers":[
        {
            "category":"Building & Trades",
            "subcategory":"Construction",
            "type":"Services"
        }
    ],
    "sg:phone":"+32 53 83 28 07",
    "sg:postcode":"9450",
    "sg:province":"Oost-Vlaanderen",
    "sg:tags":[
        "carpenter"
    ],
    "wof:name":"Luwaert L",
    "wof:placetype":"venue"
},
  "geometry": {"coordinates":[4.0048360825,50.9042930603],"type":"Point"}
}