{
  "type": "Feature",
  "properties": {
    "addr:full":"Meeuwenlaan 4 Blankenberge West-Vlaanderen 8370",
    "addr:housenumber":"4",
    "addr:postcode":"8370",
    "addr:street":"Meeuwenlaan",
    "iso:country":"BE",
    "sg:address":"Meeuwenlaan 4",
    "sg:city":"Blankenberge",
    "sg:orig_category":"Artiesten and kunstenaars",
    "sg:phone":"+32 50 41 41 41",
    "sg:postcode":"8370",
    "sg:province":"West-Vlaanderen",
    "wof:name":"Diana Deprest",
    "wof:placetype":"venue"
},
  "geometry": {"coordinates":[3.1493489742,51.3089790344],"type":"Point"}
}