{
  "type": "Feature",
  "properties": {
    "iso:country":"BE",
    "sg:address":"Kerkplein 4",
    "sg:city":"Baarle-hertog",
    "sg:classifiers":[
        {
            "category":"Restaurant",
            "type":"Food & Drink"
        }
    ],
    "sg:phone":"+32 14 69 99 29",
    "sg:postcode":"2387",
    "sg:province":"Antwerpen",
    "sg:tags":[
        "caf\u00e9s"
    ],
    "wof:name":"Taverne De Twee Leeuwen",
    "wof:placetype":"venue"
},
  "geometry": {"coordinates":[4.9301872253,51.4422607422],"type":"Point"}
}