{
  "type": "Feature",
  "properties": {
    "addr:full":"Stationsstraat 19 Leopoldsburg Limburg 3970",
    "addr:housenumber":"19",
    "addr:postcode":"3970",
    "addr:street":"Stationsstraat",
    "iso:country":"BE",
    "sg:address":"Stationsstraat 19",
    "sg:city":"Leopoldsburg",
    "sg:classifiers":[
        {
            "category":"Bakery",
            "type":"Food & Drink"
        }
    ],
    "sg:phone":"+32 11 40 17 67",
    "sg:postcode":"3970",
    "sg:province":"Limburg",
    "sg:tags":[
        "confectioner",
        "baker"
    ],
    "wof:name":"Geoffroy J",
    "wof:placetype":"venue"
},
  "geometry": {"coordinates":[5.2618041039,51.1179351807],"type":"Point"}
}