{
  "type": "Feature",
  "properties": {
    "addr:full":"Menensteenweg 64 Kortrijk West-Vlaanderen 8500",
    "addr:housenumber":"64",
    "addr:postcode":"8500",
    "addr:street":"Menensteenweg",
    "iso:country":"BE",
    "sg:address":"Menensteenweg 64",
    "sg:city":"Kortrijk",
    "sg:orig_category":"Fleurs and plantes",
    "sg:phone":"+32 2 242 29 64",
    "sg:postcode":"8500",
    "sg:province":"West-Vlaanderen",
    "wof:name":"Floribel",
    "wof:placetype":"venue"
},
  "geometry": {"coordinates":[3.2504711151,50.830291748],"type":"Point"}
}