{
  "type": "Feature",
  "properties": {
    "addr:full":"Gentseweg 35 Beveren Oost-Vlaanderen 9120",
    "addr:housenumber":"35",
    "addr:postcode":"9120",
    "addr:street":"Gentseweg",
    "iso:country":"BE",
    "sg:address":"Gentseweg 35",
    "sg:city":"Beveren",
    "sg:classifiers":[
        {
            "category":"Fast Food",
            "type":"Food & Drink"
        }
    ],
    "sg:phone":"+32 3 755 08 84",
    "sg:postcode":"9120",
    "sg:province":"Oost-Vlaanderen",
    "sg:tags":[
        "\u00c0",
        "emporter",
        "restaurants"
    ],
    "wof:name":"Pitta Service",
    "wof:placetype":"venue"
},
  "geometry": {"coordinates":[4.2411699295,51.2057189941],"type":"Point"}
}