{
  "type": "Feature",
  "properties": {
    "iso:country":"BE",
    "sg:address":"Route D'arlon 34",
    "sg:city":"Neufchateau",
    "sg:orig_category":"Koerierbedrijven Voertuigen",
    "sg:phone":"+32 61 27 91 60",
    "sg:postcode":"6840",
    "sg:province":"Luxembourg",
    "wof:name":"T.m.b.l.",
    "wof:placetype":"venue"
},
  "geometry": {"coordinates":[5.4386768341,49.839641571],"type":"Point"}
}