{
  "type": "Feature",
  "properties": {
    "addr:full":"Minderbroedersstraat 12 Tienen Vlaams-Brabant 3300",
    "addr:housenumber":"12",
    "addr:postcode":"3300",
    "addr:street":"Minderbroedersstraat",
    "iso:country":"BE",
    "sg:address":"Minderbroedersstraat 12",
    "sg:city":"Tienen",
    "sg:classifiers":[
        {
            "category":"Recreation",
            "subcategory":"Fishing",
            "type":"Entertainment"
        }
    ],
    "sg:phone":"+32 16 81 75 65",
    "sg:postcode":"3300",
    "sg:province":"Vlaams-Brabant",
    "sg:tags":[
        "tackle"
    ],
    "wof:name":"Roland",
    "wof:placetype":"venue"
},
  "geometry": {"coordinates":[4.9381737709,50.8056945801],"type":"Point"}
}