{
  "type": "Feature",
  "properties": {
    "iso:country":"BE",
    "sg:address":"Stationsstraat 209",
    "sg:city":"Sint-katelijne-waver",
    "sg:classifiers":[
        {
            "category":"Real Estate",
            "subcategory":"Architect",
            "type":"Services"
        }
    ],
    "sg:phone":"+32 15 31 59 02",
    "sg:postcode":"2860",
    "sg:province":"Antwerpen",
    "wof:name":"Van Hoeck G",
    "wof:placetype":"venue"
},
  "geometry": {"coordinates":[4.5104460716,51.0706596375],"type":"Point"}
}