{
  "type": "Feature",
  "properties": {
    "iso:country":"BE",
    "sg:address":"Berkelei 34",
    "sg:city":"Sint-katelijne-waver",
    "sg:classifiers":[
        {
            "category":"Building & Trades",
            "subcategory":"Electrical",
            "type":"Services"
        }
    ],
    "sg:phone":"+32 15 55 37 47",
    "sg:postcode":"2860",
    "sg:province":"Antwerpen",
    "sg:tags":[
        "-",
        "electric",
        "contractor"
    ],
    "wof:name":"Van Crombruggen E",
    "wof:placetype":"venue"
},
  "geometry": {"coordinates":[4.5034022331,51.0427474976],"type":"Point"}
}