{
  "type": "Feature",
  "properties": {
    "iso:country":"BE",
    "sg:address":"Rue Lognoul 31",
    "sg:city":"Ferri\u00c8res",
    "sg:orig_category":"P\u00e9pini\u00e9ristes",
    "sg:phone":"+32 86 40 06 97",
    "sg:postcode":"4190",
    "sg:province":"Li\u00e8ge",
    "wof:name":"Fleurolex",
    "wof:placetype":"venue"
},
  "geometry": {"coordinates":[5.6145401001,50.4006996155],"type":"Point"}
}