{
  "type": "Feature",
  "properties": {
    "addr:full":"Kruisstraat 67 Diest (molenstede) Vlaams-Brabant 3294",
    "addr:housenumber":"67",
    "addr:postcode":"3294",
    "addr:street":"Kruisstraat",
    "iso:country":"BE",
    "sg:address":"Kruisstraat 67",
    "sg:city":"Diest (molenstede)",
    "sg:classifiers":[
        {
            "category":"Health Services",
            "subcategory":"Doctor",
            "type":"Services"
        }
    ],
    "sg:phone":"+32 13 32 74 30",
    "sg:postcode":"3294",
    "sg:province":"Vlaams-Brabant",
    "sg:tags":[
        "medicinephysicians",
        "surgeon"
    ],
    "wof:name":"Ketelers Knut",
    "wof:placetype":"venue"
},
  "geometry": {"coordinates":[5.0133299828,51.0038795471],"type":"Point"}
}