{
  "type": "Feature",
  "properties": {
    "iso:country":"BE",
    "sg:address":"Av. Village Des Rivi\u00c8res 13",
    "sg:city":"Charleroi",
    "sg:orig_category":"Immobili\u00ebnkantoren Verzekeringsmakelaars and experts",
    "sg:phone":"+32 71 45 13 03",
    "sg:postcode":"6044",
    "sg:province":"Hainaut",
    "wof:name":"Model",
    "wof:placetype":"venue"
},
  "geometry": {"coordinates":[4.3846740723,50.4421615601],"type":"Point"}
}