{
  "type": "Feature",
  "properties": {
    "addr:full":"Sint-onolfsdijk 89 Dendermonde Oost-Vlaanderen 9200",
    "addr:housenumber":"89",
    "addr:postcode":"9200",
    "addr:street":"Sint-Onolfsdijk;Oost-Vlaanderen",
    "iso:country":"BE",
    "sg:address":"Sint-onolfsdijk 89",
    "sg:city":"Dendermonde",
    "sg:classifiers":[
        {
            "category":"Bars & Pubs",
            "type":"Food & Drink"
        }
    ],
    "sg:phone":"+32 52 21 60 13",
    "sg:postcode":"9200",
    "sg:province":"Oost-Vlaanderen",
    "wof:name":"De Rust",
    "wof:placetype":"venue"
},
  "geometry": {"coordinates":[4.0638689995,51.0488739014],"type":"Point"}
}