{
  "type": "Feature",
  "properties": {
    "addr:full":"Lange Leemstraat 52 Antwerpen Antwerpen 2018",
    "addr:housenumber":"52",
    "addr:postcode":"2018",
    "addr:street":"Lange Leemstraat",
    "iso:country":"BE",
    "sg:address":"Lange Leemstraat 52",
    "sg:city":"Antwerpen",
    "sg:classifiers":[
        {
            "category":"Building & Trades",
            "subcategory":"Electrical",
            "type":"Services"
        }
    ],
    "sg:phone":"+32 3 232 47 68",
    "sg:postcode":"2018",
    "sg:province":"Antwerpen",
    "sg:tags":[
        "electric",
        "-",
        "housewiring",
        "contractor"
    ],
    "wof:name":"Meiren Leon Bvba",
    "wof:placetype":"venue"
},
  "geometry": {"coordinates":[4.4109740257,51.2089347839],"type":"Point"}
}