{
  "type": "Feature",
  "properties": {
    "addr:full":"Rue Albert I 5 Les Bons Villers (frasnes-lez-gosselies) Hainaut 6210",
    "addr:housenumber":"5",
    "addr:postcode":"6210",
    "addr:street":"Rue Albert I",
    "iso:country":"BE",
    "sg:address":"Rue Albert I 5",
    "sg:city":"Les Bons Villers (frasnes-lez-gosselies)",
    "sg:classifiers":[
        {
            "category":"Shopping",
            "subcategory":"Computers & Home Electronics",
            "type":"Retail Goods"
        }
    ],
    "sg:phone":"+32 71 85 19 82",
    "sg:postcode":"6210",
    "sg:province":"Hainaut",
    "sg:tags":[
        "spare",
        "part",
        "processing",
        "-",
        "data"
    ],
    "wof:name":"M V Informatique Sprl",
    "wof:placetype":"venue"
},
  "geometry": {"coordinates":[4.4511561394,50.5378227234],"type":"Point"}
}