{
  "type": "Feature",
  "properties": {
    "iso:country":"BE",
    "sg:address":"Rue Du Trixhay",
    "sg:city":"Li\u00e8ge 1 (wandre)",
    "sg:classifiers":[
        {
            "category":"Arena",
            "subcategory":"Sports Club",
            "type":"Entertainment"
        }
    ],
    "sg:phone":"+32 4 362 80 42",
    "sg:postcode":"4020",
    "sg:province":"Li\u00e8ge",
    "wof:name":"Tennis De Wandre",
    "wof:placetype":"venue"
},
  "geometry": {"coordinates":[5.6522049904,50.6652565002],"type":"Point"}
}