{
  "type": "Feature",
  "properties": {
    "addr:full":"Rue Django Reinhardt 18 Pont-\u00c0-celles Hainaut 6238",
    "addr:housenumber":"18",
    "addr:postcode":"6238",
    "addr:street":"Rue Django Reinhardt",
    "iso:country":"BE",
    "sg:address":"Rue Django Reinhardt 18",
    "sg:city":"Pont-\u00c0-celles",
    "sg:orig_category":"Paramedische behandelingen",
    "sg:phone":"+32 71 84 67 13",
    "sg:postcode":"6238",
    "sg:province":"Hainaut",
    "wof:name":"Lorand",
    "wof:placetype":"venue"
},
  "geometry": {"coordinates":[4.393974781,50.5089416504],"type":"Point"}
}