{
  "type": "Feature",
  "properties": {
    "addr:full":"Steenweg Op Turnhout 37 Oud-turnhout Antwerpen 2360",
    "addr:housenumber":"37",
    "addr:postcode":"2360",
    "addr:street":"Steenweg Op Turnhout",
    "iso:country":"BE",
    "sg:address":"Steenweg Op Turnhout 37",
    "sg:city":"Oud-turnhout",
    "sg:orig_category":"Diverse zakelijke dienstverlening Immobili\u00ebnkantoren Projectontwikkelaars",
    "sg:phone":"+32 14 45 12 00",
    "sg:postcode":"2360",
    "sg:province":"Antwerpen",
    "wof:name":"Bureau Vansweevelt",
    "wof:placetype":"venue"
},
  "geometry": {"coordinates":[4.9781107903,51.3193435669],"type":"Point"}
}