{
  "type": "Feature",
  "properties": {
    "addr:full":"Lindenlei 7 Wijnegem Antwerpen 2110",
    "addr:housenumber":"7",
    "addr:postcode":"2110",
    "addr:street":"Lindenlei",
    "iso:country":"BE",
    "sg:address":"Lindenlei 7",
    "sg:city":"Wijnegem",
    "sg:orig_category":"Pi\u00e8ces and accessoires de v\u00e9hicules automobiles Gr",
    "sg:phone":"+32 3 354 35 60",
    "sg:postcode":"2110",
    "sg:province":"Antwerpen",
    "wof:name":"Akemi",
    "wof:placetype":"venue"
},
  "geometry": {"coordinates":[4.5307540894,51.2272033691],"type":"Point"}
}