{
  "type": "Feature",
  "properties": {
    "addr:full":"Bonderstraat 15 Riemst Limburg 3770",
    "addr:housenumber":"15",
    "addr:postcode":"3770",
    "addr:street":"Bonderstraat",
    "iso:country":"BE",
    "sg:address":"Bonderstraat 15",
    "sg:city":"Riemst",
    "sg:orig_category":"Elektrische installaties voor woningen Installatie van metalen schrijnwerk",
    "sg:phone":"+32 12 45 19 51",
    "sg:postcode":"3770",
    "sg:province":"Limburg",
    "wof:name":"E.v.a. Vanheusden",
    "wof:placetype":"venue"
},
  "geometry": {"coordinates":[5.6114301682,50.8302192688],"type":"Point"}
}