{
  "type": "Feature",
  "properties": {
    "addr:full":"Nederdellelaan 24 Overijse Vlaams-Brabant 3090",
    "addr:housenumber":"24",
    "addr:postcode":"3090",
    "addr:street":"Nederdellelaan",
    "iso:country":"BE",
    "sg:address":"Nederdellelaan 24",
    "sg:city":"Overijse",
    "sg:classifiers":[
        {
            "category":"Arena",
            "subcategory":"Sports Club",
            "type":"Entertainment"
        }
    ],
    "sg:phone":"+32 495 63 86 11",
    "sg:postcode":"3090",
    "sg:province":"Vlaams-Brabant",
    "sg:tags":[
        "terrain",
        "hors",
        "de",
        "installation",
        "sportifs"
    ],
    "wof:name":"V.k. Overijse",
    "wof:placetype":"venue"
},
  "geometry": {"coordinates":[4.5287108421,50.7623291016],"type":"Point"}
}