{
  "type": "Feature",
  "properties": {
    "iso:country":"BE",
    "sg:address":"Chauss\u00c9e R Astrid 39",
    "sg:city":"Eigenbrakel",
    "sg:orig_category":"V\u00eatements",
    "sg:phone":"+32 2 387 49 94",
    "sg:postcode":"1420",
    "sg:province":"Brabant Wallon",
    "wof:name":"Ocean Color",
    "wof:placetype":"venue"
},
  "geometry": {"coordinates":[4.3790669441,50.6857910156],"type":"Point"}
}