{
  "type": "Feature",
  "properties": {
    "addr:full":"Schalkhovenstraat 8 Hoeselt (schalkhoven) Limburg 3732",
    "addr:housenumber":"8",
    "addr:postcode":"3732",
    "addr:street":"Schalkhovenstraat",
    "iso:country":"BE",
    "sg:address":"Schalkhovenstraat 8",
    "sg:city":"Hoeselt (schalkhoven)",
    "sg:classifiers":[
        {
            "category":"Manufacturing",
            "subcategory":"Glass & Minerals",
            "type":"Manufacturing & Wholesale Goods"
        }
    ],
    "sg:phone":"+32 12 26 31 67",
    "sg:postcode":"3732",
    "sg:province":"Limburg",
    "sg:tags":[
        "stained",
        "glazier",
        "-"
    ],
    "wof:name":"Smeulders",
    "wof:placetype":"venue"
},
  "geometry": {"coordinates":[5.4510102272,50.8392105103],"type":"Point"}
}