{
  "type": "Feature",
  "properties": {
    "addr:full":"Wellekensstraat 45 Aalst Oost-Vlaanderen 9300",
    "addr:housenumber":"45",
    "addr:postcode":"9300",
    "addr:street":"Wellekensstraat",
    "iso:country":"BE",
    "sg:address":"Wellekensstraat 45",
    "sg:city":"Aalst",
    "sg:classifiers":[
        {
            "category":"Professional",
            "subcategory":"Accounting & Tax Preparation",
            "type":"Services"
        }
    ],
    "sg:phone":"+32 53 73 08 05",
    "sg:postcode":"9300",
    "sg:province":"Oost-Vlaanderen",
    "sg:tags":[
        "accountant"
    ],
    "wof:name":"De Groote R",
    "wof:placetype":"venue"
},
  "geometry": {"coordinates":[4.0309929848,50.9434013367],"type":"Point"}
}