{
  "type": "Feature",
  "properties": {
    "iso:country":"BE",
    "sg:address":"Gevaartsestraat 120",
    "sg:city":"Oostkamp",
    "sg:orig_category":"Fiduciairies",
    "sg:phone":"+32 50 54 88 90",
    "sg:postcode":"8020",
    "sg:province":"West-Vlaanderen",
    "wof:name":"Canhoutte Consulting",
    "wof:placetype":"venue"
},
  "geometry": {"coordinates":[3.2768259048,51.1494483948],"type":"Point"}
}