{
  "type": "Feature",
  "properties": {
    "iso:country":"BE",
    "sg:address":"Ninoofsesteenweg 432",
    "sg:city":"Brussel-anderlecht",
    "sg:orig_category":"Huisdieren and benodigdheden Royal Canin",
    "sg:phone":"+32 2 523 97 29",
    "sg:postcode":"1070",
    "sg:province":"Bruxelles-Capitale",
    "wof:name":"Goldfish Sprl",
    "wof:placetype":"venue"
},
  "geometry": {"coordinates":[4.3093400002,50.8476676941],"type":"Point"}
}