{
  "type": "Feature",
  "properties": {
    "iso:country":"BE",
    "sg:address":"Burg. Jos. Chalmetlaan 93",
    "sg:city":"Zelzate",
    "sg:orig_category":"Rev\u00eatements pour sols and murs. Peinture",
    "sg:phone":"+32 9 345 59 44",
    "sg:postcode":"9060",
    "sg:province":"Oost-Vlaanderen",
    "wof:name":"Alex Laheyne",
    "wof:placetype":"venue"
},
  "geometry": {"coordinates":[3.817718029,51.1967163086],"type":"Point"}
}