{
  "type": "Feature",
  "properties": {
    "addr:full":"Rue Fort Saint-antoine 12 Namur Namur 5000",
    "addr:housenumber":"12",
    "addr:postcode":"5000",
    "addr:street":"Rue Fort Saint-Antoine",
    "iso:country":"BE",
    "sg:address":"Rue Fort Saint-antoine 12",
    "sg:city":"Namur",
    "sg:orig_category":"Artsen and specialisten",
    "sg:phone":"+32 81 26 13 57",
    "sg:postcode":"5000",
    "sg:province":"Namur",
    "wof:name":"Ph. Stasse",
    "wof:placetype":"venue"
},
  "geometry": {"coordinates":[4.8647742271,50.4756851196],"type":"Point"}
}