{
  "type": "Feature",
  "properties": {
    "addr:full":"Lazarijstraat 73 Hasselt Limburg 3500",
    "addr:housenumber":"73",
    "addr:postcode":"3500",
    "addr:street":"Lazarijstraat",
    "iso:country":"BE",
    "sg:address":"Lazarijstraat 73",
    "sg:city":"Hasselt",
    "sg:orig_category":"Artsen and specialisten",
    "sg:phone":"+32 11 25 37 91",
    "sg:postcode":"3500",
    "sg:province":"Limburg",
    "wof:name":"A. Robben",
    "wof:placetype":"venue"
},
  "geometry": {"coordinates":[5.3284950256,50.9342193604],"type":"Point"}
}