{
  "type": "Feature",
  "properties": {
    "iso:country":"BE",
    "sg:address":"Bld Pr\u00c9sident Kennedy 69",
    "sg:city":"Mons",
    "sg:orig_category":"Belastingconsulenten Diverse juridische dienstverlening",
    "sg:phone":"+32 65 36 12 82",
    "sg:postcode":"7000",
    "sg:province":"Hainaut",
    "wof:name":"Fiduc. Compt. Du Hainaut",
    "wof:placetype":"venue"
},
  "geometry": {"coordinates":[3.9598920345,50.4589195251],"type":"Point"}
}