{
  "type": "Feature",
  "properties": {
    "iso:country":"BE",
    "sg:address":"Westpoeselstraat 3",
    "sg:city":"Lo-reninge (noordschote)",
    "sg:classifiers":[
        {
            "category":"Building & Trades",
            "subcategory":"Landscaping Services",
            "type":"Services"
        }
    ],
    "sg:phone":"+32 51 54 47 37",
    "sg:postcode":"8647",
    "sg:province":"West-Vlaanderen",
    "sg:tags":[
        "nurseryman"
    ],
    "wof:name":"Deheegher M",
    "wof:placetype":"venue"
},
  "geometry": {"coordinates":[2.8293159008,50.9501075745],"type":"Point"}
}