{
  "type": "Feature",
  "properties": {
    "iso:country":"BE",
    "sg:address":"Rue D'eben 11",
    "sg:city":"Oupeye (haccourt)",
    "sg:classifiers":[
        {
            "category":"Health Services",
            "subcategory":"Health Practitioner",
            "type":"Services"
        }
    ],
    "sg:phone":"+32 4 379 32 28",
    "sg:postcode":"4684",
    "sg:province":"Li\u00e8ge",
    "sg:tags":[
        "physiotherapist"
    ],
    "wof:name":"Spits Anne-marie",
    "wof:placetype":"venue"
},
  "geometry": {"coordinates":[5.6584239006,50.7435417175],"type":"Point"}
}