{
  "type": "Feature",
  "properties": {
    "addr:full":"Rue Ferdinand Nicolay 213 Ougr\u00e9e Li\u00e8ge 4102",
    "addr:housenumber":"213",
    "addr:postcode":"4102",
    "addr:street":"Rue Ferdinand Nicolay",
    "iso:country":"BE",
    "sg:address":"Rue Ferdinand Nicolay 213",
    "sg:city":"Ougr\u00e9e",
    "sg:classifiers":[
        {
            "category":"Building & Trades",
            "subcategory":"Construction",
            "type":"Services"
        }
    ],
    "sg:phone":"+32 4 338 56 66",
    "sg:postcode":"4102",
    "sg:province":"Li\u00e8ge",
    "sg:tags":[
        "work",
        "public"
    ],
    "wof:name":"Ets De Jaive Sa",
    "wof:placetype":"venue"
},
  "geometry": {"coordinates":[5.5409698486,50.6042289734],"type":"Point"}
}