{
  "type": "Feature",
  "properties": {
    "addr:full":"Rue Defuisseaux 5 Saint-ghislain Hainaut 7333",
    "addr:housenumber":"5",
    "addr:postcode":"7333",
    "addr:street":"Rue Defuisseaux;Hainaut",
    "iso:country":"BE",
    "sg:address":"Rue Defuisseaux 5",
    "sg:city":"Saint-ghislain",
    "sg:classifiers":[
        {
            "category":"Cafe",
            "type":"Food & Drink"
        }
    ],
    "sg:phone":"+32 65 64 44 50",
    "sg:postcode":"7333",
    "sg:province":"Hainaut",
    "sg:tags":[
        "caf\u00e9s"
    ],
    "wof:name":"Caf\u00c9 Washington",
    "wof:placetype":"venue"
},
  "geometry": {"coordinates":[3.8111400604,50.4655151367],"type":"Point"}
}