{
  "type": "Feature",
  "properties": {
    "iso:country":"BE",
    "sg:address":"Schotelven 141",
    "sg:city":"Arendonk",
    "sg:orig_category":"Rundveehouders",
    "sg:phone":"+32 14 67 81 96",
    "sg:postcode":"2370",
    "sg:province":"Antwerpen",
    "wof:name":"Jozef Geudens",
    "wof:placetype":"venue"
},
  "geometry": {"coordinates":[5.04961586,51.312171936],"type":"Point"}
}