{
  "type": "Feature",
  "properties": {
    "addr:full":"Vijfentwintig Augustusgalerij 2 Bruxelles Bruxelles-Capitale 1000",
    "addr:housenumber":"2",
    "addr:postcode":"1000",
    "addr:street":"Augustusgalerij",
    "iso:country":"BE",
    "sg:address":"Vijfentwintig Augustusgalerij 2",
    "sg:city":"Bruxelles",
    "sg:classifiers":[
        {
            "category":"Shopping",
            "subcategory":"Clothing, Apparel, & Fashions",
            "type":"Retail Goods"
        }
    ],
    "sg:phone":"+32 2 218 48 89",
    "sg:postcode":"1000",
    "sg:province":"Bruxelles-Capitale",
    "sg:tags":[
        "clothing",
        "-",
        "gentleman"
    ],
    "wof:name":"Mixage",
    "wof:placetype":"venue"
},
  "geometry": {"coordinates":[4.4127597809,50.8474159241],"type":"Point"}
}