{
  "type": "Feature",
  "properties": {
    "addr:full":"Gustave Gibonstraat 33 Sint-pieters-leeuw Vlaams-Brabant 1600",
    "addr:housenumber":"33",
    "addr:postcode":"1600",
    "addr:street":"Gustave Gibonstraat",
    "iso:country":"BE",
    "sg:address":"Gustave Gibonstraat 33",
    "sg:city":"Sint-pieters-leeuw",
    "sg:classifiers":[
        {
            "category":"Building & Trades",
            "subcategory":"Construction",
            "type":"Services"
        }
    ],
    "sg:phone":"+32 2 377 25 09",
    "sg:postcode":"1600",
    "sg:province":"Vlaams-Brabant",
    "sg:tags":[
        "installation",
        "-",
        "central",
        "heating"
    ],
    "wof:name":"Van Der Smissen F",
    "wof:placetype":"venue"
},
  "geometry": {"coordinates":[4.2815680504,50.8040618896],"type":"Point"}
}