{
  "type": "Feature",
  "properties": {
    "addr:full":"Avenue Emile Vandervelde 21 Chatelet Hainaut 6200",
    "addr:housenumber":"21",
    "addr:postcode":"6200",
    "addr:street":"Avenue Emile Vandervelde;Hainaut",
    "iso:country":"BE",
    "sg:address":"Avenue Emile Vandervelde 21",
    "sg:city":"Chatelet",
    "sg:orig_category":"Kapsalons",
    "sg:phone":"+32 71 38 38 41",
    "sg:postcode":"6200",
    "sg:province":"Hainaut",
    "wof:name":"Michel",
    "wof:placetype":"venue"
},
  "geometry": {"coordinates":[4.5205302238,50.396320343],"type":"Point"}
}