{
  "type": "Feature",
  "properties": {
    "addr:full":"Gustaaf Papestraat 49 Aalst Oost-Vlaanderen 9300",
    "addr:housenumber":"49",
    "addr:postcode":"9300",
    "addr:street":"Gustaaf Papestraat",
    "iso:country":"BE",
    "sg:address":"Gustaaf Papestraat 49",
    "sg:city":"Aalst",
    "sg:classifiers":[
        {
            "category":"Utilities",
            "subcategory":"Refuse",
            "type":"Services"
        }
    ],
    "sg:phone":"+32 53 70 22 13",
    "sg:postcode":"9300",
    "sg:province":"Oost-Vlaanderen",
    "sg:tags":[
        "removal"
    ],
    "wof:name":"Neetens & Co Nv",
    "wof:placetype":"venue"
},
  "geometry": {"coordinates":[4.031935215,50.9339790344],"type":"Point"}
}