{
  "type": "Feature",
  "properties": {
    "addr:full":"Rue D'erquy 31 Oupeye Li\u00e8ge 4680",
    "addr:housenumber":"31",
    "addr:postcode":"4680",
    "addr:street":"Rue D'Erquy",
    "iso:country":"BE",
    "sg:address":"Rue D'erquy 31",
    "sg:city":"Oupeye",
    "sg:classifiers":[
        {
            "category":"Arena",
            "subcategory":"Sports Club",
            "type":"Entertainment"
        }
    ],
    "sg:phone":"+32 4 264 98 01",
    "sg:postcode":"4680",
    "sg:province":"Li\u00e8ge",
    "sg:tags":[
        "installation",
        "sportifs",
        "de",
        "terrain",
        "hors",
        "caf\u00e9s"
    ],
    "wof:name":"La Marmotte",
    "wof:placetype":"venue"
},
  "geometry": {"coordinates":[5.6523871422,50.7097396851],"type":"Point"}
}