{
  "type": "Feature",
  "properties": {
    "iso:country":"BE",
    "sg:address":"Oostjachtpark 5",
    "sg:city":"Sint-niklaas",
    "sg:orig_category":"Disquaires",
    "sg:phone":"+32 3 777 10 96",
    "sg:postcode":"9100",
    "sg:province":"Oost-Vlaanderen",
    "wof:name":"Daniella",
    "wof:placetype":"venue"
},
  "geometry": {"coordinates":[4.1732878685,51.141620636],"type":"Point"}
}