{
  "type": "Feature",
  "properties": {
    "iso:country":"BE",
    "sg:address":"Rue Dartois 17bb",
    "sg:city":"Li\u00c8ge",
    "sg:orig_category":"M\u00e9decins and sp\u00e9cialistes",
    "sg:phone":"+32 4 252 93 36",
    "sg:postcode":"4000",
    "sg:province":"Li\u00e8ge",
    "wof:name":"Khanh Duong-viet",
    "wof:placetype":"venue"
},
  "geometry": {"coordinates":[5.5664148331,50.6283454895],"type":"Point"}
}