{
  "type": "Feature",
  "properties": {
    "iso:country":"BE",
    "sg:address":"Chauss\u00c9e De Namur 45",
    "sg:city":"Incourt",
    "sg:orig_category":"Installatie van houten of kunststof schrijnwerk",
    "sg:phone":"+32 10 88 98 18",
    "sg:postcode":"1315",
    "sg:province":"Brabant Wallon",
    "wof:name":"Michel Rosy",
    "wof:placetype":"venue"
},
  "geometry": {"coordinates":[4.8047719002,50.6936759949],"type":"Point"}
}