{
  "type": "Feature",
  "properties": {
    "iso:country":"BE",
    "sg:address":"Graanmarkt 8",
    "sg:city":"Kortrijk",
    "sg:orig_category":"Telecommunicatieapparaten",
    "sg:phone":"+32 56 20 54 27",
    "sg:postcode":"8500",
    "sg:province":"West-Vlaanderen",
    "wof:name":"T\u00c9l\u00c9com Corner",
    "wof:placetype":"venue"
},
  "geometry": {"coordinates":[3.265362978,50.8271408081],"type":"Point"}
}