{
  "type": "Feature",
  "properties": {
    "addr:full":"Steuren Ambacht 2 Lendelede West-Vlaanderen 8860",
    "addr:housenumber":"2",
    "addr:postcode":"8860",
    "addr:street":"Steuren Ambacht",
    "iso:country":"BE",
    "sg:address":"Steuren Ambacht 2",
    "sg:city":"Lendelede",
    "sg:orig_category":"Sportcentra",
    "sg:phone":"+32 51 30 60 39",
    "sg:postcode":"8860",
    "sg:province":"West-Vlaanderen",
    "wof:name":"Sporthal Steuren Ambacht",
    "wof:placetype":"venue"
},
  "geometry": {"coordinates":[3.2326619625,50.8830986023],"type":"Point"}
}