{
  "type": "Feature",
  "properties": {
    "addr:full":"Lindekouterstraat 2 Gent (mariakerke) Oost-Vlaanderen 9030",
    "addr:housenumber":"2",
    "addr:postcode":"9030",
    "addr:street":"Lindekouterstraat",
    "iso:country":"BE",
    "sg:address":"Lindekouterstraat 2",
    "sg:city":"Gent (mariakerke)",
    "sg:classifiers":[
        {
            "category":"Professional",
            "subcategory":"Testing Lab",
            "type":"Services"
        }
    ],
    "sg:phone":"+32 9 226 33 18",
    "sg:postcode":"9030",
    "sg:province":"Oost-Vlaanderen",
    "sg:tags":[
        "chemist"
    ],
    "wof:name":"Van Overberge W",
    "wof:placetype":"venue"
},
  "geometry": {"coordinates":[3.701654911,51.0777702332],"type":"Point"}
}