{
  "type": "Feature",
  "properties": {
    "iso:country":"BE",
    "sg:address":"Koolzaadstraat 16",
    "sg:city":"Roeselare (rumbeke)",
    "sg:classifiers":[
        {
            "category":"Farming",
            "subcategory":"Livestock Farm",
            "type":"Manufacturing & Wholesale Goods"
        }
    ],
    "sg:phone":"+32 51 20 86 83",
    "sg:postcode":"8800",
    "sg:province":"West-Vlaanderen",
    "sg:tags":[
        "buyer"
    ],
    "wof:name":"Pattyn C",
    "wof:placetype":"venue"
},
  "geometry": {"coordinates":[3.1376640797,50.8993606567],"type":"Point"}
}