{
  "type": "Feature",
  "properties": {
    "addr:full":"Avenue Docteur Zamenhof 10 Box 47 Bruxelles (anderlecht) Bruxelles-Capitale 1070",
    "addr:housenumber":"10 box 47",
    "addr:postcode":"1070",
    "addr:street":"Avenue Docteur Zamenhof",
    "iso:country":"BE",
    "sg:address":"Avenue Docteur Zamenhof 10 Box 47",
    "sg:city":"Bruxelles (anderlecht)",
    "sg:classifiers":[
        {
            "category":"Health Services",
            "subcategory":"Health Practitioner",
            "type":"Services"
        }
    ],
    "sg:phone":"+32 2 520 23 79",
    "sg:postcode":"1070",
    "sg:province":"Bruxelles-Capitale",
    "sg:tags":[
        "physiotherapist"
    ],
    "wof:name":"Despineux M",
    "wof:placetype":"venue"
},
  "geometry": {"coordinates":[4.3076729774,50.8284416199],"type":"Point"}
}