{
  "type": "Feature",
  "properties": {
    "addr:full":"Chauss\u00c9e De Tongres 200 Li\u00c8ge Li\u00e8ge 4000",
    "addr:housenumber":"200",
    "addr:postcode":"4000",
    "addr:street":"Chausse\u0301E De Tongres",
    "iso:country":"BE",
    "sg:address":"Chauss\u00c9e De Tongres 200",
    "sg:city":"Li\u00c8ge",
    "sg:classifiers":[
        {
            "category":"Restaurant",
            "type":"Food & Drink"
        }
    ],
    "sg:phone":"+32 4 226 24 42",
    "sg:postcode":"4000",
    "sg:province":"Li\u00e8ge",
    "wof:name":"Buffalo Grill",
    "wof:placetype":"venue"
},
  "geometry": {"coordinates":[5.5551748276,50.668056488],"type":"Point"}
}