{
  "type": "Feature",
  "properties": {
    "addr:full":"Vredelaan 19 Box 13 Houthalen-helchteren (houthalen) Limburg 3530",
    "addr:housenumber":"19 box 13",
    "addr:postcode":"3530",
    "addr:street":"Vredelaan",
    "iso:country":"BE",
    "sg:address":"Vredelaan 19 Box 13",
    "sg:city":"Houthalen-helchteren (houthalen)",
    "sg:classifiers":[
        {
            "category":"Professional",
            "subcategory":"Art Services",
            "type":"Services"
        }
    ],
    "sg:phone":"+32 11 52 52 18",
    "sg:postcode":"3530",
    "sg:province":"Limburg",
    "sg:tags":[
        "picture",
        "framer"
    ],
    "wof:name":"Handwerkhuis 't Zwarte Schaap",
    "wof:placetype":"venue"
},
  "geometry": {"coordinates":[5.3728470802,51.0319747925],"type":"Point"}
}