{
  "type": "Feature",
  "properties": {
    "iso:country":"BE",
    "sg:address":"Franz Wittoucklaan 11",
    "sg:city":"Zelzate",
    "sg:orig_category":"Installation \u00e9lectrique r\u00e9sidentielle",
    "sg:phone":"+32 9 345 55 53",
    "sg:postcode":"9060",
    "sg:province":"Oost-Vlaanderen",
    "wof:name":"Yves Van Der Linden",
    "wof:placetype":"venue"
},
  "geometry": {"coordinates":[3.8118200302,51.1989593506],"type":"Point"}
}