{
  "type": "Feature",
  "properties": {
    "iso:country":"BE",
    "sg:address":"Pauwstraat 71",
    "sg:city":"Beveren (melsele)",
    "sg:classifiers":[
        {
            "category":"Autos & Motor Vehicles",
            "subcategory":"Automobile Sales",
            "type":"Retail Goods"
        }
    ],
    "sg:phone":"+32 3 775 66 72",
    "sg:postcode":"9120",
    "sg:province":"Oost-Vlaanderen",
    "sg:tags":[
        "ceremony",
        "car"
    ],
    "wof:name":"Robert",
    "wof:placetype":"venue"
},
  "geometry": {"coordinates":[4.2917718887,51.215259552],"type":"Point"}
}