{
  "type": "Feature",
  "properties": {
    "addr:full":"Provincielaan 13 Puurs (breendonk) Antwerpen 2870",
    "addr:housenumber":"13",
    "addr:postcode":"2870",
    "addr:street":"Provincielaan",
    "iso:country":"BE",
    "sg:address":"Provincielaan 13",
    "sg:city":"Puurs (breendonk)",
    "sg:classifiers":[
        {
            "category":"Wholesale",
            "subcategory":"Scrap",
            "type":"Manufacturing & Wholesale Goods"
        }
    ],
    "sg:phone":"+32 3 889 86 96",
    "sg:postcode":"2870",
    "sg:province":"Antwerpen",
    "sg:tags":[
        "metal"
    ],
    "wof:name":"Van Der Plas P",
    "wof:placetype":"venue"
},
  "geometry": {"coordinates":[4.2989201546,51.0507926941],"type":"Point"}
}