{
  "type": "Feature",
  "properties": {
    "addr:full":"Rue Des Fran\u00c7ais 35 Aiseau-presles Hainaut 6250",
    "addr:housenumber":"35",
    "addr:postcode":"6250",
    "addr:street":"Rue Des Franc\u0327Ais;Hainaut",
    "iso:country":"BE",
    "sg:address":"Rue Des Fran\u00c7ais 35",
    "sg:city":"Aiseau-presles",
    "sg:orig_category":"Fleurs and plantes",
    "sg:phone":"+32 71 77 18 94",
    "sg:postcode":"6250",
    "sg:province":"Hainaut",
    "wof:name":"Monique & Jacques",
    "wof:placetype":"venue"
},
  "geometry": {"coordinates":[4.5757761002,50.4267616272],"type":"Point"}
}