{
  "type": "Feature",
  "properties": {
    "addr:full":"Oude Godstraat 4 Heist-op-den-berg Antwerpen 2220",
    "addr:housenumber":"4",
    "addr:postcode":"2220",
    "addr:street":"Oude Godstraat",
    "iso:country":"BE",
    "sg:address":"Oude Godstraat 4",
    "sg:city":"Heist-op-den-berg",
    "sg:classifiers":[
        {
            "category":"Restaurant",
            "type":"Food & Drink"
        }
    ],
    "sg:phone":"+32 15 24 66 68",
    "sg:postcode":"2220",
    "sg:province":"Antwerpen",
    "wof:name":"Den Hosp",
    "wof:placetype":"venue"
},
  "geometry": {"coordinates":[4.7276592255,51.0746459961],"type":"Point"}
}