{
  "type": "Feature",
  "properties": {
    "addr:full":"Waterheidestraat 19 Turnhout Antwerpen 2300",
    "addr:housenumber":"19",
    "addr:postcode":"2300",
    "addr:street":"Waterheidestraat",
    "iso:country":"BE",
    "sg:address":"Waterheidestraat 19",
    "sg:city":"Turnhout",
    "sg:orig_category":"Activit\u00e9s d\u00b4action sociale sans h\u00e9bergement",
    "sg:phone":"+32 14 42 81 35",
    "sg:postcode":"2300",
    "sg:province":"Antwerpen",
    "wof:name":"Vclb-centrum",
    "wof:placetype":"venue"
},
  "geometry": {"coordinates":[4.9552741051,51.3049468994],"type":"Point"}
}