{
  "type": "Feature",
  "properties": {
    "iso:country":"BE",
    "sg:address":"Rue Middelbourg 120",
    "sg:city":"Watermaal-bosvoorde/watermael-",
    "sg:orig_category":"Tabac. Pain, p\u00e2tisseries and confiseries. Biens d'occasion. Fournitures de bureau. Journaux",
    "sg:phone":"+32 2 672 02 03",
    "sg:postcode":"1170",
    "sg:province":"Bruxelles-Capitale",
    "wof:name":"Journal De Nicolas La Photo D\u00b4annick",
    "wof:placetype":"venue"
},
  "geometry": {"coordinates":[4.4186000824,50.7939796448],"type":"Point"}
}