{
  "type": "Feature",
  "properties": {
    "addr:full":"Georges Lobertstraat 54 Oudenaarde Oost-Vlaanderen 9700",
    "addr:housenumber":"54",
    "addr:postcode":"9700",
    "addr:street":"Lobertstraat",
    "iso:country":"BE",
    "sg:address":"Georges Lobertstraat 54",
    "sg:city":"Oudenaarde",
    "sg:orig_category":"Installation de menuiserie en bois and plastique. Installation de menuiserie m\u00e9tallique",
    "sg:phone":"+32 55 31 90 61",
    "sg:postcode":"9700",
    "sg:province":"Oost-Vlaanderen",
    "wof:name":"Deco-alu",
    "wof:placetype":"venue"
},
  "geometry": {"coordinates":[3.5996160507,50.8307189941],"type":"Point"}
}