{
  "type": "Feature",
  "properties": {
    "iso:country":"BE",
    "sg:address":"Rue Charles Quint 114",
    "sg:city":"Bruxelles",
    "sg:classifiers":[
        {
            "category":"Education",
            "subcategory":"School",
            "type":"Public Place"
        }
    ],
    "sg:phone":"+32 2 736 23 71",
    "sg:postcode":"1000",
    "sg:province":"Bruxelles-Capitale",
    "sg:tags":[
        "primary"
    ],
    "wof:name":"Retraite Du Sacr\u00e9-coeur",
    "wof:placetype":"venue"
},
  "geometry": {"coordinates":[4.3877711296,50.8492736816],"type":"Point"}
}