{
  "type": "Feature",
  "properties": {
    "iso:country":"BE",
    "sg:address":"Rue De Jemeppe 19ba",
    "sg:city":"Jemeppe-sur-sambre",
    "sg:orig_category":"Boissons",
    "sg:phone":"+32 71 78 41 97",
    "sg:postcode":"5190",
    "sg:province":"Namur",
    "wof:name":"Le Coude \u00c0 Coude",
    "wof:placetype":"venue"
},
  "geometry": {"coordinates":[4.6924190521,50.4655380249],"type":"Point"}
}