{
  "type": "Feature",
  "properties": {
    "addr:full":"Avenue De Criel 30 Havelange Namur 5370",
    "addr:housenumber":"30",
    "addr:postcode":"5370",
    "addr:street":"Avenue De Criel",
    "iso:country":"BE",
    "sg:address":"Avenue De Criel 30",
    "sg:city":"Havelange",
    "sg:orig_category":"Librairies. Tabac. Journaux",
    "sg:phone":"+32 83 63 45 09",
    "sg:postcode":"5370",
    "sg:province":"Namur",
    "wof:name":"Maison Avant-propos",
    "wof:placetype":"venue"
},
  "geometry": {"coordinates":[5.2379488945,50.3891487122],"type":"Point"}
}