{
  "type": "Feature",
  "properties": {
    "addr:full":"Gistelsesteenweg 1 Oostende West-Vlaanderen 8400",
    "addr:housenumber":"1",
    "addr:postcode":"8400",
    "addr:street":"Gistelsesteenweg",
    "iso:country":"BE",
    "sg:address":"Gistelsesteenweg 1",
    "sg:city":"Oostende",
    "sg:orig_category":"Informaticaconsulenten Onderhoud van kantoor- and computeruitrusting Software ontwikkeling and ontwe",
    "sg:phone":"+32 59 51 00 19",
    "sg:postcode":"8400",
    "sg:province":"West-Vlaanderen",
    "wof:name":"Compufit",
    "wof:placetype":"venue"
},
  "geometry": {"coordinates":[2.9262011051,51.2159461975],"type":"Point"}
}