{
  "type": "Feature",
  "properties": {
    "iso:country":"BE",
    "sg:address":"Rue Haute Saive 7",
    "sg:city":"Blegny",
    "sg:orig_category":"Epiceries",
    "sg:phone":"+32 4 370 00 16",
    "sg:postcode":"4671",
    "sg:province":"Li\u00e8ge",
    "wof:name":"Jean Fontaine",
    "wof:placetype":"venue"
},
  "geometry": {"coordinates":[5.67964077,50.6538543701],"type":"Point"}
}