{
  "type": "Feature",
  "properties": {
    "addr:full":"Pas 307 Geel Antwerpen 2440",
    "addr:housenumber":"307",
    "addr:postcode":"2440",
    "addr:street":"Pas",
    "iso:country":"BE",
    "sg:address":"Pas 307",
    "sg:city":"Geel",
    "sg:orig_category":"V\u00eatements, chaussures and accessoires V\u00eatements. Imprimeries and copyshops. Grossistes divers",
    "sg:phone":"+32 14 58 77 27",
    "sg:postcode":"2440",
    "sg:province":"Antwerpen",
    "wof:name":"Context",
    "wof:placetype":"venue"
},
  "geometry": {"coordinates":[4.9765748978,51.1535301208],"type":"Point"}
}