{
  "type": "Feature",
  "properties": {
    "iso:country":"BE",
    "sg:address":"Rue Clemenceau 17",
    "sg:city":"Ans",
    "sg:classifiers":[
        {
            "category":"Health Services",
            "subcategory":"Health Practitioner",
            "type":"Services"
        }
    ],
    "sg:phone":"+32 4 224 17 80",
    "sg:postcode":"4430",
    "sg:province":"Li\u00e8ge",
    "sg:tags":[
        "physiotherapist"
    ],
    "wof:name":"Brock Didier",
    "wof:placetype":"venue"
},
  "geometry": {"coordinates":[5.539773941,50.653263092],"type":"Point"}
}