{
  "type": "Feature",
  "properties": {
    "addr:full":"Laguitstraat 30 Turnhout Antwerpen 2300",
    "addr:housenumber":"30",
    "addr:postcode":"2300",
    "addr:street":"Laguitstraat",
    "iso:country":"BE",
    "sg:address":"Laguitstraat 30",
    "sg:city":"Turnhout",
    "sg:classifiers":[
        {
            "category":"Sports & Exercise",
            "subcategory":"Stables",
            "type":"Entertainment"
        }
    ],
    "sg:phone":"+32 14 41 42 41",
    "sg:postcode":"2300",
    "sg:province":"Antwerpen",
    "sg:tags":[
        "riding",
        "school"
    ],
    "wof:name":"De Casteleyn Nv",
    "wof:placetype":"venue"
},
  "geometry": {"coordinates":[4.9504508972,51.3443603516],"type":"Point"}
}