{
  "type": "Feature",
  "properties": {
    "iso:country":"BE",
    "sg:address":"Oud-hoflaan 26a",
    "sg:city":"Lochristi",
    "sg:classifiers":[
        {
            "category":"Wholesale",
            "subcategory":"Plants",
            "type":"Manufacturing & Wholesale Goods"
        }
    ],
    "sg:phone":"+32 476 63 39 35",
    "sg:postcode":"9080",
    "sg:province":"Oost-Vlaanderen",
    "sg:tags":[
        "whol",
        "flower",
        "-",
        "grower"
    ],
    "wof:name":"Flor\u00e9 K Bvba",
    "wof:placetype":"venue"
},
  "geometry": {"coordinates":[3.8265020847,51.101474762],"type":"Point"}
}