{
  "type": "Feature",
  "properties": {
    "iso:country":"BE",
    "sg:address":"Kestelstraat 33",
    "sg:city":"Aalter",
    "sg:classifiers":[
        {
            "category":"Personal",
            "type":"Services"
        }
    ],
    "sg:phone":"+32 9 374 15 03",
    "sg:postcode":"9880",
    "sg:province":"Oost-Vlaanderen",
    "sg:tags":[
        "party",
        "planning"
    ],
    "wof:name":"Diner-service",
    "wof:placetype":"venue"
},
  "geometry": {"coordinates":[3.4551510811,51.0834655762],"type":"Point"}
}