{
  "type": "Feature",
  "properties": {
    "addr:full":"Frans Halsvest 92 Mechelen Antwerpen 2800",
    "addr:housenumber":"92",
    "addr:postcode":"2800",
    "addr:street":"Frans Halsvest",
    "iso:country":"BE",
    "sg:address":"Frans Halsvest 92",
    "sg:city":"Mechelen",
    "sg:orig_category":"Epiceries",
    "sg:phone":"+32 15 29 06 07",
    "sg:postcode":"2800",
    "sg:province":"Antwerpen",
    "wof:name":"Huis Steffresh",
    "wof:placetype":"venue"
},
  "geometry": {"coordinates":[4.4886221886,51.0301055908],"type":"Point"}
}