{
  "type": "Feature",
  "properties": {
    "addr:full":"Rozenlaan 6 Sint-katelijne-waver (onze-lieve-vrouw-waver) Antwerpen 2861",
    "addr:housenumber":"6",
    "addr:postcode":"2861",
    "addr:street":"Rozenlaan",
    "iso:country":"BE",
    "sg:address":"Rozenlaan 6",
    "sg:city":"Sint-katelijne-waver (onze-lieve-vrouw-waver)",
    "sg:classifiers":[
        {
            "category":"Professional",
            "subcategory":"Accounting & Tax Preparation",
            "type":"Services"
        }
    ],
    "sg:phone":"+32 15 23 73 89",
    "sg:postcode":"2861",
    "sg:province":"Antwerpen",
    "sg:tags":[
        "bookkeeper"
    ],
    "wof:name":"Fiscaal- En Boekhoudkantoor Hellemans",
    "wof:placetype":"venue"
},
  "geometry": {"coordinates":[4.5425448418,51.0475387573],"type":"Point"}
}