{
  "type": "Feature",
  "properties": {
    "iso:country":"BE",
    "sg:address":"Wareslagestraat 109",
    "sg:city":"Waasmunster",
    "sg:orig_category":"Herstellingen and onderhoud van auto's",
    "sg:phone":"+32 52 46 00 15",
    "sg:postcode":"9250",
    "sg:province":"Oost-Vlaanderen",
    "wof:name":"Johan Mouton",
    "wof:placetype":"venue"
},
  "geometry": {"coordinates":[4.097700119,51.1108016968],"type":"Point"}
}