{
  "type": "Feature",
  "properties": {
    "addr:full":"Sepulkrijnenlaan 73 Hasselt Limburg 3500",
    "addr:housenumber":"73",
    "addr:postcode":"3500",
    "addr:street":"Sepulkrijnenlaan",
    "iso:country":"BE",
    "sg:address":"Sepulkrijnenlaan 73",
    "sg:city":"Hasselt",
    "sg:orig_category":"Agences immobili\u00e8res",
    "sg:phone":"+32 11 27 35 20",
    "sg:postcode":"3500",
    "sg:province":"Limburg",
    "wof:name":"Van Der Veken",
    "wof:placetype":"venue"
},
  "geometry": {"coordinates":[5.3359251022,50.9270362854],"type":"Point"}
}