{
  "type": "Feature",
  "properties": {
    "addr:full":"Binnenkouter 5 Poperinge West-Vlaanderen 8970",
    "addr:housenumber":"5",
    "addr:postcode":"8970",
    "addr:street":"Binnenkouter",
    "iso:country":"BE",
    "sg:address":"Binnenkouter 5",
    "sg:city":"Poperinge",
    "sg:classifiers":[
        {
            "category":"Health Services",
            "subcategory":"Nursing And Care Facility",
            "type":"Services"
        }
    ],
    "sg:phone":"+32 57 33 88 99",
    "sg:postcode":"8970",
    "sg:province":"West-Vlaanderen",
    "sg:tags":[
        "home"
    ],
    "wof:name":"Maes M",
    "wof:placetype":"venue"
},
  "geometry": {"coordinates":[2.7352719307,50.8572845459],"type":"Point"}
}