{
  "type": "Feature",
  "properties": {
    "iso:country":"BE",
    "sg:address":"Chauss\u00c9e D'hannut 141",
    "sg:city":"Jodoigne",
    "sg:orig_category":"Ramassage and traitement des d\u00e9chets m\u00e9nagers",
    "sg:phone":"+32 10 81 29 89",
    "sg:postcode":"1370",
    "sg:province":"Brabant Wallon",
    "wof:name":"Service De La Voirie",
    "wof:placetype":"venue"
},
  "geometry": {"coordinates":[4.8973588943,50.7131004333],"type":"Point"}
}