{
  "type": "Feature",
  "properties": {
    "iso:country":"BE",
    "sg:address":"Hasseltsebaan 131",
    "sg:city":"Hechtel-eksel (hechtel)",
    "sg:classifiers":[
        {
            "category":"Banks & Credit Unions",
            "subcategory":"Investment Brokerage",
            "type":"Services"
        }
    ],
    "sg:phone":"+32 11 73 30 00",
    "sg:postcode":"3940",
    "sg:province":"Limburg",
    "sg:tags":[
        "exchange",
        "stock"
    ],
    "wof:name":"Stijns Rommelmarkt",
    "wof:placetype":"venue"
},
  "geometry": {"coordinates":[5.3750371933,51.0968093872],"type":"Point"}
}