{
  "type": "Feature",
  "properties": {
    "addr:full":"Ronselestraat 21 Zomergem Oost-Vlaanderen 9932",
    "addr:housenumber":"21",
    "addr:postcode":"9932",
    "addr:street":"Ronselestraat",
    "iso:country":"BE",
    "sg:address":"Ronselestraat 21",
    "sg:city":"Zomergem",
    "sg:orig_category":"Varkenskwekers",
    "sg:phone":"+32 9 372 74 83",
    "sg:postcode":"9932",
    "sg:province":"Oost-Vlaanderen",
    "wof:name":"Marc Sierens",
    "wof:placetype":"venue"
},
  "geometry": {"coordinates":[3.5500600338,51.1339912415],"type":"Point"}
}