{
  "type": "Feature",
  "properties": {
    "iso:country":"BE",
    "sg:address":"Rue De L'institut 5 Box 303",
    "sg:city":"Namur (bouge)",
    "sg:classifiers":[
        {
            "category":"Professional",
            "subcategory":"Management & Consulting",
            "type":"Services"
        }
    ],
    "sg:phone":"+32 81 21 21 26",
    "sg:postcode":"5004",
    "sg:province":"Namur",
    "sg:tags":[
        "consultant"
    ],
    "wof:name":"Duvivier & Partners Scs",
    "wof:placetype":"venue"
},
  "geometry": {"coordinates":[4.8855419159,50.4737739563],"type":"Point"}
}