{
  "type": "Feature",
  "properties": {
    "addr:full":"Retiesebaan 3 Kasterlee Antwerpen 2460",
    "addr:housenumber":"3",
    "addr:postcode":"2460",
    "addr:street":"Retiesebaan",
    "iso:country":"BE",
    "sg:address":"Retiesebaan 3",
    "sg:city":"Kasterlee",
    "sg:orig_category":"Boucheries",
    "sg:phone":"+32 14 85 22 88",
    "sg:postcode":"2460",
    "sg:province":"Antwerpen",
    "wof:name":"Slagerij Van Hoof",
    "wof:placetype":"venue"
},
  "geometry": {"coordinates":[4.969078064,51.2407913208],"type":"Point"}
}