{
  "type": "Feature",
  "properties": {
    "addr:full":"Betekomsesteenweg 91 Begijnendijk (groot) Vlaams-Brabant 3130",
    "addr:housenumber":"91",
    "addr:postcode":"3130",
    "addr:street":"Betekomsesteenweg;Groot Vlaams-Brabant",
    "iso:country":"BE",
    "sg:address":"Betekomsesteenweg 91",
    "sg:city":"Begijnendijk (groot)",
    "sg:orig_category":"Elektrische installaties voor woningen",
    "sg:phone":"+32 16 69 74 55",
    "sg:postcode":"3130",
    "sg:province":"Vlaams-Brabant",
    "wof:name":"S.a.s.",
    "wof:placetype":"venue"
},
  "geometry": {"coordinates":[4.7875728607,51.0138626099],"type":"Point"}
}