{
  "type": "Feature",
  "properties": {
    "addr:full":"Avenue Vauban 29 Ath Hainaut 7800",
    "addr:housenumber":"29",
    "addr:postcode":"7800",
    "addr:street":"Avenue Vauban",
    "iso:country":"BE",
    "sg:address":"Avenue Vauban 29",
    "sg:city":"Ath",
    "sg:orig_category":"Activit\u00e9s r\u00e9cr\u00e9atives diverses",
    "sg:phone":"+32 68 28 42 18",
    "sg:postcode":"7800",
    "sg:province":"Hainaut",
    "wof:name":"Union Philat\u00c9lique",
    "wof:placetype":"venue"
},
  "geometry": {"coordinates":[3.7882430553,50.6267318726],"type":"Point"}
}