{
  "type": "Feature",
  "properties": {
    "iso:country":"BE",
    "sg:address":"Heidestraat 22b",
    "sg:city":"Merchtem (hamme)",
    "sg:classifiers":[
        {
            "category":"Professional",
            "subcategory":"Computer Services",
            "type":"Services"
        }
    ],
    "sg:phone":"+32 2 610 67 55",
    "sg:postcode":"1785",
    "sg:province":"Vlaams-Brabant",
    "sg:tags":[
        "webdesign",
        "-",
        "internet"
    ],
    "wof:name":"Netuse",
    "wof:placetype":"venue"
},
  "geometry": {"coordinates":[4.2205629349,50.9841079712],"type":"Point"}
}