{
  "type": "Feature",
  "properties": {
    "addr:full":"Rue De Lantign\u00e9 34 Durbuy (grandhan) Luxembourg 6940",
    "addr:housenumber":"34",
    "addr:postcode":"6940",
    "addr:street":"Rue De Lantigne\u0301",
    "iso:country":"BE",
    "sg:address":"Rue De Lantign\u00e9 34",
    "sg:city":"Durbuy (grandhan)",
    "sg:orig_category":"Solar protection - Outside",
    "sg:phone":"+32 86 21 10 27",
    "sg:postcode":"6940",
    "sg:province":"Luxembourg",
    "wof:name":"M.g. Stores Sprl",
    "wof:placetype":"venue"
},
  "geometry": {"coordinates":[5.4366278648,50.3379402161],"type":"Point"}
}