{
  "type": "Feature",
  "properties": {
    "addr:full":"Gentsesteenweg 255b Aalst Oost-Vlaanderen 9300",
    "addr:housenumber":"255b",
    "addr:postcode":"9300",
    "addr:street":"Gentsesteenweg",
    "iso:country":"BE",
    "sg:address":"Gentsesteenweg 255b",
    "sg:city":"Aalst",
    "sg:orig_category":"Verlichting and huishoudartikelen",
    "sg:phone":"+32 53 70 90 49",
    "sg:postcode":"9300",
    "sg:province":"Oost-Vlaanderen",
    "wof:name":"Happy Memories",
    "wof:placetype":"venue"
},
  "geometry": {"coordinates":[4.0071630478,50.9410514832],"type":"Point"}
}