{
  "type": "Feature",
  "properties": {
    "iso:country":"BE",
    "sg:address":"Oosterveldln. 99",
    "sg:city":"Wilrijk",
    "sg:classifiers":[
        {
            "category":"Utilities",
            "type":"Services"
        }
    ],
    "sg:phone":"+32 3 260 94 70",
    "sg:postcode":"2610",
    "sg:province":"Antwerpen",
    "sg:tags":[
        "raw",
        "energy",
        "material"
    ],
    "wof:name":"Carbomet Sa",
    "wof:placetype":"venue"
},
  "geometry": {"coordinates":[4.422413826,51.1758499146],"type":"Point"}
}