{
  "type": "Feature",
  "properties": {
    "addr:full":"Heuvel 17 Kalmthout Antwerpen 2920",
    "addr:housenumber":"17",
    "addr:postcode":"2920",
    "addr:street":"Heuvel",
    "iso:country":"BE",
    "sg:address":"Heuvel 17",
    "sg:city":"Kalmthout",
    "sg:orig_category":"Epiceries",
    "sg:phone":"+32 3 666 66 68",
    "sg:postcode":"2920",
    "sg:province":"Antwerpen",
    "wof:name":"'t Heuvelken",
    "wof:placetype":"venue"
},
  "geometry": {"coordinates":[4.4648098946,51.3903770447],"type":"Point"}
}