{
  "type": "Feature",
  "properties": {
    "iso:country":"BE",
    "sg:address":"Henisstraat 131",
    "sg:city":"Tongeren",
    "sg:classifiers":[
        {
            "category":"Personal",
            "subcategory":"Beauty Salon",
            "type":"Services"
        }
    ],
    "sg:phone":"+32 12 23 49 72",
    "sg:postcode":"3700",
    "sg:province":"Limburg",
    "sg:tags":[
        "lady",
        "-",
        "hairdressing"
    ],
    "wof:name":"Rolande",
    "wof:placetype":"venue"
},
  "geometry": {"coordinates":[5.4693989754,50.7881774902],"type":"Point"}
}