{
  "type": "Feature",
  "properties": {
    "addr:full":"Dendermondsesteenweg 79 Lebbeke Oost-Vlaanderen 9280",
    "addr:housenumber":"79",
    "addr:postcode":"9280",
    "addr:street":"Dendermondsesteenweg",
    "iso:country":"BE",
    "sg:address":"Dendermondsesteenweg 79",
    "sg:city":"Lebbeke",
    "sg:classifiers":[
        {
            "category":"Restaurant",
            "type":"Food & Drink"
        }
    ],
    "sg:phone":"+32 52 41 43 24",
    "sg:postcode":"9280",
    "sg:province":"Oost-Vlaanderen",
    "sg:tags":[
        "caf\u00e9s"
    ],
    "wof:name":"Taverne Schuttershof",
    "wof:placetype":"venue"
},
  "geometry": {"coordinates":[4.1249518394,51.0041046143],"type":"Point"}
}