{
  "type": "Feature",
  "properties": {
    "iso:country":"BE",
    "sg:address":"Wouwersdreef 14",
    "sg:city":"Schoten",
    "sg:classifiers":[
        {
            "category":"Health Services",
            "subcategory":"Doctor",
            "type":"Services"
        }
    ],
    "sg:phone":"+32 3 658 83 47",
    "sg:postcode":"2900",
    "sg:province":"Antwerpen",
    "sg:tags":[
        "medicinephysicians",
        "surgeon"
    ],
    "wof:name":"De Schepper A",
    "wof:placetype":"venue"
},
  "geometry": {"coordinates":[4.5433740616,51.2677993774],"type":"Point"}
}