{
  "type": "Feature",
  "properties": {
    "addr:full":"Rudyard Kiplinglaan 2 Ieper West-Vlaanderen 8900",
    "addr:housenumber":"2",
    "addr:postcode":"8900",
    "addr:street":"Rudyard Kiplinglaan",
    "iso:country":"BE",
    "sg:address":"Rudyard Kiplinglaan 2",
    "sg:city":"Ieper",
    "sg:orig_category":"Avocats and conseillers juridiques",
    "sg:phone":"+32 57 20 43 74",
    "sg:postcode":"8900",
    "sg:province":"West-Vlaanderen",
    "wof:name":"Marnix Muylle",
    "wof:placetype":"venue"
},
  "geometry": {"coordinates":[2.8919579983,50.8527603149],"type":"Point"}
}