{
  "type": "Feature",
  "properties": {
    "iso:country":"BE",
    "sg:address":"Boulevard G\u00e9n\u00e9ral Wahis 234",
    "sg:city":"Bruxelles (schaerbeek)",
    "sg:classifiers":[
        {
            "category":"Professional",
            "subcategory":"Lawyer & Legal Services",
            "type":"Services"
        }
    ],
    "sg:phone":"+32 2 705 75 70",
    "sg:postcode":"1030",
    "sg:province":"Bruxelles-Capitale",
    "wof:name":"Josseaux Marie-no\u00eblle",
    "wof:placetype":"venue"
},
  "geometry": {"coordinates":[4.3983201981,50.8565864563],"type":"Point"}
}