{
  "type": "Feature",
  "properties": {
    "iso:country":"BE",
    "sg:address":"Liefkenshoekstraat 24",
    "sg:city":"Beveren",
    "sg:orig_category":"Eleveurs de bovins",
    "sg:phone":"+32 3 773 29 89",
    "sg:postcode":"9130",
    "sg:province":"Oost-Vlaanderen",
    "wof:name":"Omer Van Royen",
    "wof:placetype":"venue"
},
  "geometry": {"coordinates":[4.2674012184,51.3077087402],"type":"Point"}
}