{
  "type": "Feature",
  "properties": {
    "addr:full":"Krijgsbaan 183 Temse Oost-Vlaanderen 9140",
    "addr:housenumber":"183",
    "addr:postcode":"9140",
    "addr:street":"Krijgsbaan",
    "iso:country":"BE",
    "sg:address":"Krijgsbaan 183",
    "sg:city":"Temse",
    "sg:classifiers":[
        {
            "category":"Health Services",
            "subcategory":"Doctor",
            "type":"Services"
        }
    ],
    "sg:phone":"+32 3 771 01 19",
    "sg:postcode":"9140",
    "sg:province":"Oost-Vlaanderen",
    "sg:tags":[
        "medicinephysicians",
        "surgeon"
    ],
    "wof:name":"Felix Kristien",
    "wof:placetype":"venue"
},
  "geometry": {"coordinates":[4.2383470535,51.128490448],"type":"Point"}
}