{
  "type": "Feature",
  "properties": {
    "addr:full":"Steenbokstraat 36 Antwerpen Antwerpen 2018",
    "addr:housenumber":"36",
    "addr:postcode":"2018",
    "addr:street":"Steenbokstraat",
    "iso:country":"BE",
    "sg:address":"Steenbokstraat 36",
    "sg:city":"Antwerpen",
    "sg:classifiers":[
        {
            "category":"Arts & Performance",
            "subcategory":"Theater",
            "type":"Entertainment"
        }
    ],
    "sg:phone":"+32 3 239 53 05",
    "sg:postcode":"2018",
    "sg:province":"Antwerpen",
    "sg:tags":[
        "group",
        "theatre"
    ],
    "wof:name":"Figurentheater Ultima Thule",
    "wof:placetype":"venue"
},
  "geometry": {"coordinates":[4.4264149666,51.2067070007],"type":"Point"}
}