{
  "type": "Feature",
  "properties": {
    "addr:full":"Ronsesestraat 227 Brakel Oost-Vlaanderen 9660",
    "addr:housenumber":"227",
    "addr:postcode":"9660",
    "addr:street":"Ronsesestraat",
    "iso:country":"BE",
    "sg:address":"Ronsesestraat 227",
    "sg:city":"Brakel",
    "sg:orig_category":"Installation de menuiserie m\u00e9tallique",
    "sg:phone":"+32 55 42 25 67",
    "sg:postcode":"9660",
    "sg:province":"Oost-Vlaanderen",
    "wof:name":"Etienne Mincke",
    "wof:placetype":"venue"
},
  "geometry": {"coordinates":[3.7257349491,50.7864990234],"type":"Point"}
}