{
  "type": "Feature",
  "properties": {
    "addr:full":"Chauss\u00e9e De Waterloo 735 Bruxelles (uccle) Bruxelles-Capitale 1180",
    "addr:housenumber":"735",
    "addr:postcode":"1180",
    "addr:street":"Chausse\u0301E De Waterloo",
    "iso:country":"BE",
    "sg:address":"Chauss\u00e9e De Waterloo 735",
    "sg:city":"Bruxelles (uccle)",
    "sg:classifiers":[
        {
            "category":"Banks & Credit Unions",
            "subcategory":"Bank",
            "type":"Services"
        }
    ],
    "sg:phone":"+32 2 345 83 86",
    "sg:postcode":"1180",
    "sg:province":"Bruxelles-Capitale",
    "wof:name":"Argenta",
    "wof:placetype":"venue"
},
  "geometry": {"coordinates":[4.3673710823,50.8142623901],"type":"Point"}
}