{
  "type": "Feature",
  "properties": {
    "iso:country":"BE",
    "sg:address":"Chauss\u00c9e Roi Baudouin 19",
    "sg:city":"Mons",
    "sg:classifiers":[
        {
            "category":"Insurance",
            "subcategory":"Insurance Agent",
            "type":"Services"
        }
    ],
    "sg:phone":"+32 65 33 92 70",
    "sg:postcode":"7030",
    "sg:province":"Hainaut",
    "sg:tags":[
        "verzekeringsmakelaars",
        "expert"
    ],
    "wof:name":"C. Flamme",
    "wof:placetype":"venue"
},
  "geometry": {"coordinates":[4.0108299255,50.4393882751],"type":"Point"}
}