{
  "type": "Feature",
  "properties": {
    "iso:country":"BE",
    "sg:address":"Eendenstraat 32",
    "sg:city":"Denderleeuw (welle)",
    "sg:classifiers":[
        {
            "category":"Health Services",
            "subcategory":"Doctor",
            "type":"Services"
        }
    ],
    "sg:phone":"+32 53 68 00 40",
    "sg:postcode":"9473",
    "sg:province":"Oost-Vlaanderen",
    "sg:tags":[
        "medicinephysicians",
        "surgeon"
    ],
    "wof:name":"Bouchez Stefaan",
    "wof:placetype":"venue"
},
  "geometry": {"coordinates":[4.0546879768,50.8973731995],"type":"Point"}
}