{
  "type": "Feature",
  "properties": {
    "addr:full":"Rue Bris\u00e9e 138 Mons (obourg) Hainaut 7034",
    "addr:housenumber":"138",
    "addr:postcode":"7034",
    "addr:street":"Rue Brise\u0301E",
    "iso:country":"BE",
    "sg:address":"Rue Bris\u00e9e 138",
    "sg:city":"Mons (obourg)",
    "sg:classifiers":[
        {
            "category":"Professional",
            "subcategory":"Accounting & Tax Preparation",
            "type":"Services"
        }
    ],
    "sg:phone":"+32 65 73 04 49",
    "sg:postcode":"7034",
    "sg:province":"Hainaut",
    "sg:tags":[
        "accountant"
    ],
    "wof:name":"Cardinal B",
    "wof:placetype":"venue"
},
  "geometry": {"coordinates":[4.0086159706,50.4765396118],"type":"Point"}
}