{
  "type": "Feature",
  "properties": {
    "iso:country":"BE",
    "sg:address":"Avenue Chantecler 5",
    "sg:city":"Braine-l'alleud",
    "sg:orig_category":"Artsen and specialisten",
    "sg:phone":"+32 2 384 88 51",
    "sg:postcode":"1420",
    "sg:province":"Brabant Wallon",
    "wof:name":"Dayaneedee Chellun",
    "wof:placetype":"venue"
},
  "geometry": {"coordinates":[18.6601905823,-33.8623886108],"type":"Point"}
}