{
  "type": "Feature",
  "properties": {
    "addr:full":"Meulestraat 19 Sint-lievens-houtem (bavegem) Oost-Vlaanderen 9520",
    "addr:housenumber":"19",
    "addr:postcode":"9520",
    "addr:street":"Meulestraat;Bavegem",
    "iso:country":"BE",
    "sg:address":"Meulestraat 19",
    "sg:city":"Sint-lievens-houtem (bavegem)",
    "sg:orig_category":"Non-Classified Establishments",
    "sg:phone":"+32 9 363 82 82",
    "sg:postcode":"9520",
    "sg:province":"Oost-Vlaanderen",
    "wof:name":"Inex Nv",
    "wof:placetype":"venue"
},
  "geometry": {"coordinates":[3.8680000305,50.9363517761],"type":"Point"}
}