{
  "type": "Feature",
  "properties": {
    "iso:country":"BE",
    "sg:address":"Rue Du Prince De Li\u00e8ge 9",
    "sg:city":"Gerpinnes (villers-poterie)",
    "sg:classifiers":[
        {
            "category":"Health Services",
            "subcategory":"Nursing And Care Facility",
            "type":"Services"
        }
    ],
    "sg:phone":"+32 71 50 26 76",
    "sg:postcode":"6280",
    "sg:province":"Hainaut",
    "sg:tags":[
        "home"
    ],
    "wof:name":"Evlard N",
    "wof:placetype":"venue"
},
  "geometry": {"coordinates":[4.5508480072,50.3657798767],"type":"Point"}
}