{
  "type": "Feature",
  "properties": {
    "iso:country":"BE",
    "sg:address":"Place De Goegnies 28b",
    "sg:city":"La Louvi\u00e8re (houdeng-goegnies)",
    "sg:classifiers":[
        {
            "category":"Utilities",
            "subcategory":"Mobile Phone",
            "type":"Services"
        }
    ],
    "sg:phone":"+32 64 34 28 32",
    "sg:postcode":"7110",
    "sg:province":"Hainaut",
    "sg:tags":[
        "access",
        "gsm",
        "-",
        "apparatus"
    ],
    "wof:name":"Gsm Point Com",
    "wof:placetype":"venue"
},
  "geometry": {"coordinates":[4.1505050659,50.4826698303],"type":"Point"}
}