{
  "type": "Feature",
  "properties": {
    "iso:country":"BE",
    "sg:address":"Antwerpenstraat 31",
    "sg:city":"Bredene",
    "sg:classifiers":[
        {
            "category":"Building & Trades",
            "subcategory":"Construction",
            "type":"Services"
        }
    ],
    "sg:phone":"+32 59 32 13 57",
    "sg:postcode":"8450",
    "sg:province":"West-Vlaanderen",
    "sg:tags":[
        "carpenter"
    ],
    "wof:name":"Vanholme F",
    "wof:placetype":"venue"
},
  "geometry": {"coordinates":[2.9649169445,51.2476081848],"type":"Point"}
}