{
  "type": "Feature",
  "properties": {
    "iso:country":"BE",
    "sg:address":"Barelstraat 80",
    "sg:city":"Bornem",
    "sg:orig_category":"Loodgieterij, verwarming and sanitaire installaties",
    "sg:phone":"+32 3 889 08 76",
    "sg:postcode":"2880",
    "sg:province":"Antwerpen",
    "wof:name":"Spiessens",
    "wof:placetype":"venue"
},
  "geometry": {"coordinates":[4.2337298393,51.0936050415],"type":"Point"}
}