{
  "type": "Feature",
  "properties": {
    "addr:full":"Gemeenteplein 7 Mortsel Antwerpen 2640",
    "addr:housenumber":"7",
    "addr:postcode":"2640",
    "addr:street":"Gemeenteplein",
    "iso:country":"BE",
    "sg:address":"Gemeenteplein 7",
    "sg:city":"Mortsel",
    "sg:classifiers":[
        {
            "category":"Bars & Pubs",
            "type":"Food & Drink"
        }
    ],
    "sg:phone":"+32 3 440 51 76",
    "sg:postcode":"2640",
    "sg:province":"Antwerpen",
    "wof:name":"Beer (den)",
    "wof:placetype":"venue"
},
  "geometry": {"coordinates":[4.450466156,51.1701202393],"type":"Point"}
}