{
  "type": "Feature",
  "properties": {
    "addr:full":"Blaubergsesteenweg 63ba Herselt Antwerpen 2230",
    "addr:housenumber":"63ba",
    "addr:postcode":"2230",
    "addr:street":"Blaubergsesteenweg",
    "iso:country":"BE",
    "sg:address":"Blaubergsesteenweg 63ba",
    "sg:city":"Herselt",
    "sg:orig_category":"Belastingconsulenten Diverse juridische dienstverlening",
    "sg:phone":"+32 14 54 34 31",
    "sg:postcode":"2230",
    "sg:province":"Antwerpen",
    "wof:name":"Bureau Bofimac",
    "wof:placetype":"venue"
},
  "geometry": {"coordinates":[4.9141659737,51.046131134],"type":"Point"}
}