{
  "type": "Feature",
  "properties": {
    "iso:country":"BE",
    "sg:address":"Beemdenstraat 15",
    "sg:city":"Beerse",
    "sg:orig_category":"Non-Classified Establishments",
    "sg:phone":"+32 14 62 24 60",
    "sg:postcode":"2340",
    "sg:province":"Antwerpen",
    "wof:name":"Emj Lighting Nv",
    "wof:placetype":"venue"
},
  "geometry": {"coordinates":[4.8312358856,51.3012199402],"type":"Point"}
}