{
  "type": "Feature",
  "properties": {
    "iso:country":"BE",
    "sg:address":"Place De Thumaide 18",
    "sg:city":"Beloeil (thumaide)",
    "sg:classifiers":[
        {
            "category":"Health Services",
            "subcategory":"Nursing And Care Facility",
            "type":"Services"
        }
    ],
    "sg:phone":"+32 69 77 45 08",
    "sg:postcode":"7971",
    "sg:province":"Hainaut",
    "sg:tags":[
        "home",
        "rest"
    ],
    "wof:name":"Le Val D'ambroise",
    "wof:placetype":"venue"
},
  "geometry": {"coordinates":[3.6284499168,50.5425491333],"type":"Point"}
}