{
  "type": "Feature",
  "properties": {
    "iso:country":"BE",
    "sg:address":"Place De La Paix 16",
    "sg:city":"Evere",
    "sg:classifiers":[
        {
            "category":"Cinema",
            "subcategory":"Movie Rental",
            "type":"Entertainment"
        }
    ],
    "sg:phone":"+32 2 216 10 69",
    "sg:postcode":"1140",
    "sg:province":"Bruxelles-Capitale",
    "sg:tags":[
        "de",
        "cassette",
        "location",
        "vid\u00e9o",
        "audio"
    ],
    "wof:name":"Cin\u00c9bank Vid\u00c9o 24h/24",
    "wof:placetype":"venue"
},
  "geometry": {"coordinates":[4.4015488625,50.8769989014],"type":"Point"}
}