{
  "type": "Feature",
  "properties": {
    "addr:full":"Rue Berkendael 20 Vorst/forest Bruxelles-Capitale 1190",
    "addr:housenumber":"20",
    "addr:postcode":"1190",
    "addr:street":"Rue Berkendael;/ Forest",
    "iso:country":"BE",
    "sg:address":"Rue Berkendael 20",
    "sg:city":"Vorst/forest",
    "sg:orig_category":"Agences de presse",
    "sg:phone":"+32 2 346 96 40",
    "sg:postcode":"1190",
    "sg:province":"Bruxelles-Capitale",
    "wof:name":"Isabelle Blandiaux",
    "wof:placetype":"venue"
},
  "geometry": {"coordinates":[4.3451719284,50.8187484741],"type":"Point"}
}