{
  "type": "Feature",
  "properties": {
    "iso:country":"BE",
    "sg:address":"Bredabaan 338",
    "sg:city":"Brasschaat",
    "sg:classifiers":[
        {
            "category":"Fast Food",
            "type":"Food & Drink"
        }
    ],
    "sg:phone":"+32 3 651 80 28",
    "sg:postcode":"2930",
    "sg:province":"Antwerpen",
    "sg:tags":[
        "meeneem",
        "restaurant"
    ],
    "wof:name":"Tang\u00b4s Keuken",
    "wof:placetype":"venue"
},
  "geometry": {"coordinates":[4.4938249588,51.292137146],"type":"Point"}
}