{
  "type": "Feature",
  "properties": {
    "iso:country":"BE",
    "sg:address":"Rue Des Goutteaux 3",
    "sg:city":"Charleroi (mont-sur-marchienne)",
    "sg:classifiers":[
        {
            "category":"Shopping",
            "subcategory":"Books",
            "type":"Retail Goods"
        }
    ],
    "sg:phone":"+32 71 36 97 05",
    "sg:postcode":"6032",
    "sg:province":"Hainaut",
    "sg:tags":[
        "bookseller"
    ],
    "wof:name":"Librairie Des Goutteaux",
    "wof:placetype":"venue"
},
  "geometry": {"coordinates":[4.4075961113,50.389957428],"type":"Point"}
}