{
  "type": "Feature",
  "properties": {
    "addr:full":"Bruggesteenweg 44 Hooglede West-Vlaanderen 8830",
    "addr:housenumber":"44",
    "addr:postcode":"8830",
    "addr:street":"Bruggesteenweg",
    "iso:country":"BE",
    "sg:address":"Bruggesteenweg 44",
    "sg:city":"Hooglede",
    "sg:classifiers":[
        {
            "category":"Sports & Exercise",
            "subcategory":"Sports Center",
            "type":"Entertainment"
        }
    ],
    "sg:phone":"+32 51 24 16 09",
    "sg:postcode":"8830",
    "sg:province":"West-Vlaanderen",
    "sg:tags":[
        "terrain",
        "hors",
        "de",
        "installation",
        "sportifs"
    ],
    "wof:name":"Paintball Battlefield",
    "wof:placetype":"venue"
},
  "geometry": {"coordinates":[3.0854070187,50.9791564941],"type":"Point"}
}