{
  "type": "Feature",
  "properties": {
    "iso:country":"BE",
    "sg:address":"Boskant 19",
    "sg:city":"Meise",
    "sg:orig_category":"Rundveehouders",
    "sg:phone":"+32 52 30 91 80",
    "sg:postcode":"1861",
    "sg:province":"Vlaams-Brabant",
    "wof:name":"M Bogemans",
    "wof:placetype":"venue"
},
  "geometry": {"coordinates":[4.3091049194,50.9506645203],"type":"Point"}
}