{
  "type": "Feature",
  "properties": {
    "addr:full":"Munsterenstraat 2 Genk Limburg 3600",
    "addr:housenumber":"2",
    "addr:postcode":"3600",
    "addr:street":"Munsterenstraat",
    "iso:country":"BE",
    "sg:address":"Munsterenstraat 2",
    "sg:city":"Genk",
    "sg:orig_category":"Gases, Technical",
    "sg:phone":"+32 89 62 38 40",
    "sg:postcode":"3600",
    "sg:province":"Limburg",
    "wof:name":"L'air Liquide Belgium Nv",
    "wof:placetype":"venue"
},
  "geometry": {"coordinates":[5.5212578773,50.9265136719],"type":"Point"}
}