{
  "type": "Feature",
  "properties": {
    "iso:country":"BE",
    "sg:address":"Wespelaarsebaan 61",
    "sg:city":"Boortmeerbeek",
    "sg:orig_category":"Loodgieterij, verwarming and sanitaire installaties",
    "sg:phone":"+32 15 51 56 61",
    "sg:postcode":"3190",
    "sg:province":"Vlaams-Brabant",
    "wof:name":"J. Bogaerts",
    "wof:placetype":"venue"
},
  "geometry": {"coordinates":[4.5796189308,50.9782180786],"type":"Point"}
}