{
  "type": "Feature",
  "properties": {
    "iso:country":"BE",
    "sg:address":"Hovestraat 32",
    "sg:city":"Arendonk",
    "sg:orig_category":"Brood, gebak and snoepgoed",
    "sg:phone":"+32 14 67 75 57",
    "sg:postcode":"2370",
    "sg:province":"Antwerpen",
    "wof:name":"Gust Boermans",
    "wof:placetype":"venue"
},
  "geometry": {"coordinates":[5.0906991959,51.3201637268],"type":"Point"}
}