{
  "type": "Feature",
  "properties": {
    "addr:full":"Crapaurue 179 Verviers Li\u00e8ge 4800",
    "addr:housenumber":"179",
    "addr:postcode":"4800",
    "iso:country":"BE",
    "sg:address":"Crapaurue 179",
    "sg:city":"Verviers",
    "sg:classifiers":[
        {
            "category":"Professional",
            "subcategory":"Testing Lab",
            "type":"Services"
        }
    ],
    "sg:phone":"+32 87 33 06 22",
    "sg:postcode":"4800",
    "sg:province":"Li\u00e8ge",
    "sg:tags":[
        "chemist"
    ],
    "wof:name":"Dubois-nortier",
    "wof:placetype":"venue"
},
  "geometry": {"coordinates":[5.8624978065,50.592502594],"type":"Point"}
}