{
  "type": "Feature",
  "properties": {
    "addr:full":"Nati\u00ebnlaan 108-110 Knokke-heist (westkapelle) West-Vlaanderen 8300",
    "addr:housenumber":"108-110",
    "addr:postcode":"8300",
    "addr:street":"Natie\u0308Nlaan",
    "iso:country":"BE",
    "sg:address":"Nati\u00ebnlaan 108-110",
    "sg:city":"Knokke-heist (westkapelle)",
    "sg:orig_category":"Autombile concessionaires",
    "sg:phone":"+32 50 61 44 44",
    "sg:postcode":"8300",
    "sg:province":"West-Vlaanderen",
    "wof:name":"Gar De Zutter",
    "wof:placetype":"venue"
},
  "geometry": {"coordinates":[3.2888998985,51.3360900879],"type":"Point"}
}