{
  "type": "Feature",
  "properties": {
    "iso:country":"BE",
    "sg:address":"Kiefhoekstraat 30ba",
    "sg:city":"Hechtel-eksel",
    "sg:orig_category":"Elektrische installaties voor woningen",
    "sg:phone":"+32 11 34 75 53",
    "sg:postcode":"3941",
    "sg:province":"Limburg",
    "wof:name":"Karel Schoeters",
    "wof:placetype":"venue"
},
  "geometry": {"coordinates":[5.2955679893,51.1602897644],"type":"Point"}
}