{
  "type": "Feature",
  "properties": {
    "iso:country":"BE",
    "sg:address":"Rue De La Gare 5",
    "sg:city":"Eghez\u00c9e",
    "sg:orig_category":"Salles de spectacles",
    "sg:phone":"+32 81 81 20 31",
    "sg:postcode":"5310",
    "sg:province":"Namur",
    "wof:name":"Centre Culturel",
    "wof:placetype":"venue"
},
  "geometry": {"coordinates":[4.9102640152,50.5942230225],"type":"Point"}
}