{
  "type": "Feature",
  "properties": {
    "addr:full":"Rue Orger Meurice Beaumont (leugnies) Hainaut 6500",
    "addr:postcode":"6500",
    "addr:street":"Rue Orger Meurice",
    "iso:country":"BE",
    "sg:address":"Rue Orger Meurice",
    "sg:city":"Beaumont (leugnies)",
    "sg:classifiers":[
        {
            "category":"Health Services",
            "subcategory":"Nursing And Care Facility",
            "type":"Services"
        }
    ],
    "sg:phone":"+32 71 58 92 13",
    "sg:postcode":"6500",
    "sg:province":"Hainaut",
    "sg:tags":[
        "home",
        "rest"
    ],
    "wof:name":"Moulineau (le) Residence",
    "wof:placetype":"venue"
},
  "geometry": {"coordinates":[4.203769207,50.2265853882],"type":"Point"}
}