{
  "type": "Feature",
  "properties": {
    "addr:full":"Bld Alfred De Fontaine 21b14 Charleroi Hainaut 6000",
    "addr:housenumber":"21b14",
    "addr:postcode":"6000",
    "addr:street":"Bld Alfred De Fontaine;Hainaut",
    "iso:country":"BE",
    "sg:address":"Bld Alfred De Fontaine 21b14",
    "sg:city":"Charleroi",
    "sg:orig_category":"Advocaten and juridische adviseurs",
    "sg:phone":"+32 71 32 21 76",
    "sg:postcode":"6000",
    "sg:province":"Hainaut",
    "wof:name":"J.l. Roba",
    "wof:placetype":"venue"
},
  "geometry": {"coordinates":[4.4468569756,50.4107208252],"type":"Point"}
}