{
  "type": "Feature",
  "properties": {
    "addr:full":"Veurs 24 Fourons (fouron-st.-martin) Limburg 3790",
    "addr:housenumber":"24",
    "addr:postcode":"3790",
    "addr:street":"Veurs",
    "iso:country":"BE",
    "sg:address":"Veurs 24",
    "sg:city":"Fourons (fouron-st.-martin)",
    "sg:classifiers":[
        {
            "category":"Manufacturing",
            "subcategory":"Furniture",
            "type":"Manufacturing & Wholesale Goods"
        }
    ],
    "sg:phone":"+32 4 381 02 60",
    "sg:postcode":"3790",
    "sg:province":"Limburg",
    "sg:tags":[
        "made",
        "-",
        "custom"
    ],
    "wof:name":"Droeven J",
    "wof:placetype":"venue"
},
  "geometry": {"coordinates":[5.8579039574,50.7303733826],"type":"Point"}
}