{
  "type": "Feature",
  "properties": {
    "addr:full":"Merenweg 4 Hoogstraten Antwerpen 2321",
    "addr:housenumber":"4",
    "addr:postcode":"2321",
    "addr:street":"Merenweg",
    "iso:country":"BE",
    "sg:address":"Merenweg 4",
    "sg:city":"Hoogstraten",
    "sg:orig_category":"Fruitteelt Plaatsen van vloer- and muurbekleding Rundveehouders Woningbouw",
    "sg:phone":"+32 3 315 73 14",
    "sg:postcode":"2321",
    "sg:province":"Antwerpen",
    "wof:name":"Aernouts",
    "wof:placetype":"venue"
},
  "geometry": {"coordinates":[4.7163977623,51.4463348389],"type":"Point"}
}