{
  "type": "Feature",
  "properties": {
    "addr:full":"Centre Comm. Bay Bonnet 5 Fleron Li\u00e8ge 4620",
    "addr:housenumber":"5",
    "addr:postcode":"4620",
    "addr:street":"Fleron Lie\u0300Ge",
    "iso:country":"BE",
    "sg:address":"Centre Comm. Bay Bonnet 5",
    "sg:city":"Fleron",
    "sg:classifiers":[
        {
            "category":"Restaurant",
            "type":"Food & Drink"
        }
    ],
    "sg:phone":"+32 4 358 19 09",
    "sg:postcode":"4620",
    "sg:province":"Li\u00e8ge",
    "sg:tags":[
        "caf\u00e9s"
    ],
    "wof:name":"Taverne Le Bay Bonnet",
    "wof:placetype":"venue"
},
  "geometry": {"coordinates":[5.6891207695,50.6131019592],"type":"Point"}
}