{
  "type": "Feature",
  "properties": {
    "iso:country":"BE",
    "sg:address":"Notelaarstraat 5",
    "sg:city":"Bonheiden",
    "sg:orig_category":"Studios photographiques",
    "sg:phone":"+32 15 55 37 42",
    "sg:postcode":"2820",
    "sg:province":"Antwerpen",
    "wof:name":"Van Wijk Aerial Survey",
    "wof:placetype":"venue"
},
  "geometry": {"coordinates":[4.5253272057,51.0360488892],"type":"Point"}
}