{
  "type": "Feature",
  "properties": {
    "addr:full":"Rue Defalque 4 Court-saint-etienne Brabant Wallon 1490",
    "addr:housenumber":"4;1490",
    "addr:street":"Rue Defalque",
    "iso:country":"BE",
    "sg:address":"Rue Defalque 4",
    "sg:city":"Court-saint-etienne",
    "sg:orig_category":"Enseignement maternel and primaire",
    "sg:phone":"+32 10 61 40 59",
    "sg:postcode":"1490",
    "sg:province":"Brabant Wallon",
    "wof:name":"Ecole Matern. Communale",
    "wof:placetype":"venue"
},
  "geometry": {"coordinates":[4.5674037933,50.6421394348],"type":"Point"}
}