{
  "type": "Feature",
  "properties": {
    "iso:country":"BE",
    "sg:address":"Scheibeekstraat 15",
    "sg:city":"Herne",
    "sg:classifiers":[
        {
            "category":"Personal",
            "subcategory":"Beauty Salon",
            "type":"Services"
        }
    ],
    "sg:phone":"+32 2 396 17 70",
    "sg:postcode":"1540",
    "sg:province":"Vlaams-Brabant",
    "sg:tags":[
        "de",
        "coiffure"
    ],
    "wof:name":"Hair Service Fr\u00c9",
    "wof:placetype":"venue"
},
  "geometry": {"coordinates":[4.0340118408,50.7348251343],"type":"Point"}
}