{
  "type": "Feature",
  "properties": {
    "iso:country":"BE",
    "sg:address":"Rue Des Haies 67",
    "sg:city":"Ham-sur-heure-nalinnes (nalinnes)",
    "sg:classifiers":[
        {
            "category":"Real Estate",
            "subcategory":"Architect",
            "type":"Services"
        }
    ],
    "sg:phone":"+32 71 21 79 16",
    "sg:postcode":"6120",
    "sg:province":"Hainaut",
    "wof:name":"Crokart P",
    "wof:placetype":"venue"
},
  "geometry": {"coordinates":[4.448472023,50.3462295532],"type":"Point"}
}