{
  "type": "Feature",
  "properties": {
    "addr:full":"Grotestraat 112 Maasmechelen Limburg 3631",
    "addr:housenumber":"112",
    "addr:postcode":"3631",
    "addr:street":"Grotestraat",
    "iso:country":"BE",
    "sg:address":"Grotestraat 112",
    "sg:city":"Maasmechelen",
    "sg:orig_category":"Epiceries. Boucheries",
    "sg:phone":"+32 89 76 46 41",
    "sg:postcode":"3631",
    "sg:province":"Limburg",
    "wof:name":"Michel Milissen",
    "wof:placetype":"venue"
},
  "geometry": {"coordinates":[5.7239232063,50.9423713684],"type":"Point"}
}