{
  "type": "Feature",
  "properties": {
    "addr:full":"Wilgenhoevestraat 65 Antwerpen Antwerpen 2180",
    "addr:housenumber":"65",
    "addr:postcode":"2180",
    "addr:street":"Wilgenhoevestraat",
    "iso:country":"BE",
    "sg:address":"Wilgenhoevestraat 65",
    "sg:city":"Antwerpen",
    "sg:orig_category":"Sportterreinen and installaties behalve sportcentra",
    "sg:phone":"+32 3 541 63 57",
    "sg:postcode":"2180",
    "sg:province":"Antwerpen",
    "wof:name":"Belgian Paintball World",
    "wof:placetype":"venue"
},
  "geometry": {"coordinates":[4.4182572365,51.2778625488],"type":"Point"}
}