{
  "type": "Feature",
  "properties": {
    "iso:country":"BE",
    "sg:address":"Graethemstraat 9",
    "sg:city":"Borgloon",
    "sg:orig_category":"Verlichting and huishoudartikelen",
    "sg:phone":"+32 12 74 20 27",
    "sg:postcode":"3840",
    "sg:province":"Limburg",
    "wof:name":"Kado - Lux Haling",
    "wof:placetype":"venue"
},
  "geometry": {"coordinates":[5.33705616,50.803478241],"type":"Point"}
}