{
  "type": "Feature",
  "properties": {
    "iso:country":"BE",
    "sg:address":"Meulestedekaai 390",
    "sg:city":"Gent",
    "sg:orig_category":"Artsen and specialisten",
    "sg:phone":"+32 9 251 59 99",
    "sg:postcode":"9000",
    "sg:province":"Oost-Vlaanderen",
    "wof:name":"Consultatiebur.jonge Kind",
    "wof:placetype":"venue"
},
  "geometry": {"coordinates":[3.7280759811,51.0828666687],"type":"Point"}
}