{
  "type": "Feature",
  "properties": {
    "addr:full":"Rue J Cornet 61 Mons Hainaut 7000",
    "addr:housenumber":"61",
    "addr:postcode":"7000",
    "addr:street":"Rue J Cornet;Hainaut",
    "iso:country":"BE",
    "sg:address":"Rue J Cornet 61",
    "sg:city":"Mons",
    "sg:orig_category":"Astrologen, grafologen and mediums",
    "sg:phone":"+32 475 61 91 31",
    "sg:postcode":"7000",
    "sg:province":"Hainaut",
    "wof:name":"G\u00c9obiologie Scientifique",
    "wof:placetype":"venue"
},
  "geometry": {"coordinates":[3.9610180855,50.4624176025],"type":"Point"}
}