{
  "type": "Feature",
  "properties": {
    "addr:full":"Chauss\u00c9e De L'europe 39 Couvin Namur 5660",
    "addr:housenumber":"39",
    "addr:postcode":"5660",
    "addr:street":"Chausse\u0301E De L'Europe",
    "iso:country":"BE",
    "sg:address":"Chauss\u00c9e De L'europe 39",
    "sg:city":"Couvin",
    "sg:classifiers":[
        {
            "category":"Autos & Motor Vehicles",
            "subcategory":"Fuel & Gas Station",
            "type":"Retail Goods"
        }
    ],
    "sg:phone":"+32 60 37 81 81",
    "sg:postcode":"5660",
    "sg:province":"Namur",
    "sg:tags":[
        "stations-service",
        "carburants"
    ],
    "wof:name":"Patricia Marechal",
    "wof:placetype":"venue"
},
  "geometry": {"coordinates":[4.4537410736,49.9605827332],"type":"Point"}
}