{
  "type": "Feature",
  "properties": {
    "addr:full":"Eikenlaan 2 Genk Limburg 3600",
    "addr:housenumber":"2",
    "addr:postcode":"3600",
    "addr:street":"Eikenlaan",
    "iso:country":"BE",
    "sg:address":"Eikenlaan 2",
    "sg:city":"Genk",
    "sg:classifiers":[
        {
            "category":"Health Services",
            "subcategory":"Doctor",
            "type":"Services"
        }
    ],
    "sg:phone":"+32 89 35 12 80",
    "sg:postcode":"3600",
    "sg:province":"Limburg",
    "sg:tags":[
        "medicinephysicians",
        "surgeon"
    ],
    "wof:name":"De Marneffe Guy",
    "wof:placetype":"venue"
},
  "geometry": {"coordinates":[5.4893989563,50.9759979248],"type":"Point"}
}