{
  "type": "Feature",
  "properties": {
    "iso:country":"BE",
    "sg:address":"Floris De Cuijperstraat 6",
    "sg:city":"Mortsel",
    "sg:classifiers":[
        {
            "category":"Professional",
            "subcategory":"Management & Consulting",
            "type":"Services"
        }
    ],
    "sg:phone":"+32 3 448 24 35",
    "sg:postcode":"2640",
    "sg:province":"Antwerpen",
    "sg:tags":[
        "-",
        "processing",
        "data",
        "consultant"
    ],
    "wof:name":"Online Bvba",
    "wof:placetype":"venue"
},
  "geometry": {"coordinates":[4.4448919296,51.1743240356],"type":"Point"}
}