{
  "type": "Feature",
  "properties": {
    "iso:country":"BE",
    "sg:address":"Place Du March\u00c9 6",
    "sg:city":"Eupen",
    "sg:orig_category":"Eclairage et \u00e9quipements du foyer",
    "sg:phone":"+32 87 74 25 76",
    "sg:postcode":"4700",
    "sg:province":"Li\u00e8ge",
    "wof:name":"Haus Mertens",
    "wof:placetype":"venue"
},
  "geometry": {"coordinates":[6.0313239098,50.6306152344],"type":"Point"}
}