{
  "type": "Feature",
  "properties": {
    "iso:country":"BE",
    "sg:address":"Broekstraat 55",
    "sg:city":"Sint-gillis-waas",
    "sg:classifiers":[
        {
            "category":"Manufacturing",
            "subcategory":"Wood Products",
            "type":"Manufacturing & Wholesale Goods"
        }
    ],
    "sg:phone":"+32 3 766 40 90",
    "sg:postcode":"9170",
    "sg:province":"Oost-Vlaanderen",
    "sg:tags":[
        "pallet",
        "made"
    ],
    "wof:name":"Van Gaeveren B.v.b.a.",
    "wof:placetype":"venue"
},
  "geometry": {"coordinates":[4.1214399338,51.2261810303],"type":"Point"}
}