{
  "type": "Feature",
  "properties": {
    "iso:country":"BE",
    "sg:address":"J. De Troozlaan 93",
    "sg:city":"Blankenberge",
    "sg:classifiers":[
        {
            "category":"Fast Food",
            "type":"Food & Drink"
        }
    ],
    "sg:phone":"+32 50 41 27 54",
    "sg:postcode":"8370",
    "sg:province":"West-Vlaanderen",
    "sg:tags":[
        "\u00c0",
        "restaurants",
        "emporter",
        "restaurant"
    ],
    "wof:name":"Moeder Lambic",
    "wof:placetype":"venue"
},
  "geometry": {"coordinates":[3.1357169151,51.3168907166],"type":"Point"}
}