{
  "type": "Feature",
  "properties": {
    "iso:country":"BE",
    "sg:address":"Middelkaart 5",
    "sg:city":"Brasschaat",
    "sg:classifiers":[
        {
            "category":"Banks & Credit Unions",
            "subcategory":"Bank",
            "type":"Services"
        }
    ],
    "sg:phone":"+32 3 651 68 62",
    "sg:postcode":"2130",
    "wof:name":"Caisse Nationale De, Cr\u00e9dit Professionnel",
    "wof:placetype":"venue"
},
  "geometry": {"coordinates":[119.9737319946,31.7901992798],"type":"Point"}
}