{
  "type": "Feature",
  "properties": {
    "addr:full":"Leuvensesteenweg 93 Diest Vlaams-Brabant 3290",
    "addr:housenumber":"93",
    "addr:postcode":"3290",
    "addr:street":"Leuvensesteenweg",
    "iso:country":"BE",
    "sg:address":"Leuvensesteenweg 93",
    "sg:city":"Diest",
    "sg:classifiers":[
        {
            "category":"Travel",
            "subcategory":"Hotels & Motels",
            "type":"Entertainment"
        }
    ],
    "sg:phone":"+32 13 31 10 66",
    "sg:postcode":"3290",
    "sg:province":"Vlaams-Brabant",
    "sg:tags":[
        "restaurant"
    ],
    "wof:name":"Restaurant Taverne Hotel Modern",
    "wof:placetype":"venue"
},
  "geometry": {"coordinates":[5.0452709198,50.9785194397],"type":"Point"}
}