{
  "type": "Feature",
  "properties": {
    "iso:country":"BE",
    "sg:address":"Fortem 46",
    "sg:city":"Alveringem",
    "sg:orig_category":"Eleveurs and marchands de porcs",
    "sg:phone":"+32 58 28 80 99",
    "sg:postcode":"8690",
    "sg:province":"West-Vlaanderen",
    "wof:name":"Maurice Boone",
    "wof:placetype":"venue"
},
  "geometry": {"coordinates":[2.7274179459,51.0156326294],"type":"Point"}
}