{
  "type": "Feature",
  "properties": {
    "addr:full":"Avenue De La Belle Voie 25 Wavre Brabant Wallon 1300",
    "addr:housenumber":"25;1300",
    "addr:street":"Avenue De La Belle Voie",
    "iso:country":"BE",
    "sg:address":"Avenue De La Belle Voie 25",
    "sg:city":"Wavre",
    "sg:orig_category":"Sportclubs",
    "sg:phone":"+32 10 24 45 16",
    "sg:postcode":"1300",
    "sg:province":"Brabant Wallon",
    "wof:name":"B.w.y.c.",
    "wof:placetype":"venue"
},
  "geometry": {"coordinates":[4.6181898117,50.7199897766],"type":"Point"}
}