{
  "type": "Feature",
  "properties": {
    "addr:full":"Desguinlei 64 Antwerpen Antwerpen 2018",
    "addr:housenumber":"64",
    "addr:postcode":"2018",
    "addr:street":"Desguinlei",
    "iso:country":"BE",
    "sg:address":"Desguinlei 64",
    "sg:city":"Antwerpen",
    "sg:classifiers":[
        {
            "category":"Professional",
            "subcategory":"Art Services",
            "type":"Services"
        }
    ],
    "sg:phone":"+32 3 237 37 19",
    "sg:postcode":"2018",
    "sg:province":"Antwerpen",
    "sg:tags":[
        "graphic",
        "designer"
    ],
    "wof:name":"Atelier Verbergt Nv",
    "wof:placetype":"venue"
},
  "geometry": {"coordinates":[4.4094247818,51.192741394],"type":"Point"}
}