{
  "type": "Feature",
  "properties": {
    "iso:country":"BE",
    "sg:address":"Centrumstraat 53",
    "sg:city":"Zulte",
    "sg:orig_category":"Meubelzaken, woning- and keukeninrichting",
    "sg:phone":"+32 9 388 91 45",
    "sg:postcode":"9870",
    "sg:province":"Oost-Vlaanderen",
    "wof:name":"St.jozef Meubelgalerij",
    "wof:placetype":"venue"
},
  "geometry": {"coordinates":[3.4681649208,50.9339942932],"type":"Point"}
}