{
  "type": "Feature",
  "properties": {
    "addr:full":"Dichtkunstlaan 17 Anderlecht/anderlecht Bruxelles-Capitale 1070",
    "addr:housenumber":"17",
    "addr:postcode":"1070",
    "addr:street":"Dichtkunstlaan",
    "iso:country":"BE",
    "sg:address":"Dichtkunstlaan 17",
    "sg:city":"Anderlecht/anderlecht",
    "sg:orig_category":"Schoonheidssalons",
    "sg:phone":"+32 2 523 74 52",
    "sg:postcode":"1070",
    "sg:province":"Bruxelles-Capitale",
    "wof:name":"Podologue Stas-desmet",
    "wof:placetype":"venue"
},
  "geometry": {"coordinates":[4.2950539589,50.845954895],"type":"Point"}
}