{
  "type": "Feature",
  "properties": {
    "iso:country":"BE",
    "sg:address":"Harelbeeksestraat 80",
    "sg:city":"Kuurne",
    "sg:classifiers":[
        {
            "category":"Manufacturing",
            "subcategory":"Metals",
            "type":"Manufacturing & Wholesale Goods"
        }
    ],
    "sg:phone":"+32 56 71 61 82",
    "sg:postcode":"8520",
    "sg:province":"West-Vlaanderen",
    "sg:tags":[
        "working"
    ],
    "wof:name":"Dimar Nv",
    "wof:placetype":"venue"
},
  "geometry": {"coordinates":[3.2953019142,50.8507003784],"type":"Point"}
}