{
  "type": "Feature",
  "properties": {
    "iso:country":"BE",
    "sg:address":"Chauss\u00c9e De Mons 29",
    "sg:city":"La Louviere",
    "sg:orig_category":"Pain, p\u00e2tisseries and confiseries",
    "sg:phone":"+32 64 21 48 43",
    "sg:postcode":"7100",
    "sg:province":"Hainaut",
    "wof:name":"Jacques Danis",
    "wof:placetype":"venue"
},
  "geometry": {"coordinates":[4.1995410919,50.4645805359],"type":"Point"}
}