{
  "type": "Feature",
  "properties": {
    "iso:country":"BE",
    "sg:address":"Hof Te Bollebeeklaan 5",
    "sg:city":"Asse",
    "sg:orig_category":"Editeurs de revues and p\u00e9riodiques. Editeurs de journaux",
    "sg:phone":"+32 2 454 15 11",
    "sg:postcode":"1730",
    "sg:province":"Vlaams-Brabant",
    "wof:name":"C.p.c.",
    "wof:placetype":"venue"
},
  "geometry": {"coordinates":[4.2393269539,50.9193191528],"type":"Point"}
}