{
  "type": "Feature",
  "properties": {
    "addr:full":"Deken De Bostraat 61 Waregem West-Vlaanderen 8791",
    "addr:housenumber":"61",
    "addr:postcode":"8791",
    "addr:street":"Deken De Bostraat",
    "iso:country":"BE",
    "sg:address":"Deken De Bostraat 61",
    "sg:city":"Waregem",
    "sg:orig_category":"Boekenuitgeverijen Platenmaatschappijen",
    "sg:phone":"+32 56 71 98 20",
    "sg:postcode":"8791",
    "sg:province":"West-Vlaanderen",
    "wof:name":"Golden River Music",
    "wof:placetype":"venue"
},
  "geometry": {"coordinates":[3.345813036,50.8797340393],"type":"Point"}
}