{
  "type": "Feature",
  "properties": {
    "addr:full":"Peperstraat 37 Herzele Oost-Vlaanderen 9550",
    "addr:housenumber":"37",
    "addr:postcode":"9550",
    "addr:street":"Peperstraat;Oost-Vlaanderen",
    "iso:country":"BE",
    "sg:address":"Peperstraat 37",
    "sg:city":"Herzele",
    "sg:orig_category":"Imprimeries and copyshops",
    "sg:phone":"+32 53 62 25 35",
    "sg:postcode":"9550",
    "sg:province":"Oost-Vlaanderen",
    "wof:name":"Drukkerij De Toren",
    "wof:placetype":"venue"
},
  "geometry": {"coordinates":[3.8953690529,50.88514328],"type":"Point"}
}