{
  "type": "Feature",
  "properties": {
    "addr:full":"Chauss\u00c9e De Charleroi 41 Sombreffe Namur 5140",
    "addr:housenumber":"41",
    "addr:postcode":"5140",
    "addr:street":"Chausse\u0301E De Charleroi",
    "iso:country":"BE",
    "sg:address":"Chauss\u00c9e De Charleroi 41",
    "sg:city":"Sombreffe",
    "sg:orig_category":"Benzinestations and brandstoffen",
    "sg:phone":"+32 71 88 78 76",
    "sg:postcode":"5140",
    "sg:province":"Namur",
    "wof:name":"Manco",
    "wof:placetype":"venue"
},
  "geometry": {"coordinates":[4.6127781868,50.5198554993],"type":"Point"}
}