{
  "type": "Feature",
  "properties": {
    "iso:country":"BE",
    "sg:address":"Hulsterweg 17",
    "sg:city":"Tessenderlo",
    "sg:orig_category":"D\u00e9taillants en pi\u00e8ces and accessoires de voitures",
    "sg:phone":"+32 13 66 84 16",
    "sg:postcode":"3980",
    "sg:province":"Limburg",
    "wof:name":"Looise Bandencentrale",
    "wof:placetype":"venue"
},
  "geometry": {"coordinates":[5.1057071686,51.0666847229],"type":"Point"}
}