{
  "type": "Feature",
  "properties": {
    "addr:full":"Leiestraat 2 Kortrijk West-Vlaanderen 8500",
    "addr:housenumber":"2",
    "addr:postcode":"8500",
    "addr:street":"Leiestraat",
    "iso:country":"BE",
    "sg:address":"Leiestraat 2",
    "sg:city":"Kortrijk",
    "sg:orig_category":"Banques and organismes de cr\u00e9dit",
    "sg:phone":"+32 56 21 09 76",
    "sg:postcode":"8500",
    "sg:province":"West-Vlaanderen",
    "wof:name":"Europabank",
    "wof:placetype":"venue"
},
  "geometry": {"coordinates":[3.2652199268,50.8280944824],"type":"Point"}
}