{
  "type": "Feature",
  "properties": {
    "iso:country":"BE",
    "sg:address":"Vrenenstraat 46",
    "sg:city":"Overpelt",
    "sg:orig_category":"Woningbouw",
    "sg:phone":"+32 11 64 30 10",
    "sg:postcode":"3900",
    "sg:province":"Limburg",
    "wof:name":"Hermans Jos & Co",
    "wof:placetype":"venue"
},
  "geometry": {"coordinates":[5.3950247765,51.1921348572],"type":"Point"}
}