{
  "type": "Feature",
  "properties": {
    "iso:country":"BE",
    "sg:address":"Boskantstraat 107",
    "sg:city":"Beringen",
    "sg:classifiers":[
        {
            "category":"Cafe",
            "type":"Food & Drink"
        }
    ],
    "sg:phone":"+32 11 34 27 86",
    "sg:postcode":"3581",
    "sg:province":"Limburg",
    "sg:tags":[
        "caf\u00e9s"
    ],
    "wof:name":"Nathalie Poelmans",
    "wof:placetype":"venue"
},
  "geometry": {"coordinates":[5.2674670219,51.088470459],"type":"Point"}
}