{
  "type": "Feature",
  "properties": {
    "iso:country":"BE",
    "sg:address":"Albert Van Cotthemstraat 1",
    "sg:city":"Sint-pieters-leeuw",
    "sg:classifiers":[
        {
            "category":"Utilities",
            "subcategory":"Refuse",
            "type":"Services"
        }
    ],
    "sg:phone":"+32 2 569 89 07",
    "sg:postcode":"1600",
    "sg:province":"Vlaams-Brabant",
    "sg:tags":[
        "removal"
    ],
    "wof:name":"A.a. Rocotrans Bvba",
    "wof:placetype":"venue"
},
  "geometry": {"coordinates":[4.2862401009,50.8020210266],"type":"Point"}
}