{
  "type": "Feature",
  "properties": {
    "addr:full":"Brabantdam 33be Gent Oost-Vlaanderen 9000",
    "addr:housenumber":"33be",
    "addr:postcode":"9000",
    "addr:street":"Brabantdam;Oost-Vlaanderen",
    "iso:country":"BE",
    "sg:address":"Brabantdam 33be",
    "sg:city":"Gent",
    "sg:orig_category":"Technische studies and ingenieursactiviteiten",
    "sg:phone":"+32 9 233 00 11",
    "sg:postcode":"9000",
    "sg:province":"Oost-Vlaanderen",
    "wof:name":"Derveaux Ingenieursbureau",
    "wof:placetype":"venue"
},
  "geometry": {"coordinates":[3.7283549309,51.0505561829],"type":"Point"}
}