{
  "type": "Feature",
  "properties": {
    "addr:full":"Spoorweglaan 192 Beveren Oost-Vlaanderen 9120",
    "addr:housenumber":"192",
    "addr:postcode":"9120",
    "addr:street":"Spoorweglaan",
    "iso:country":"BE",
    "sg:address":"Spoorweglaan 192",
    "sg:city":"Beveren",
    "sg:classifiers":[
        {
            "category":"Insurance",
            "subcategory":"Life Insurance",
            "type":"Services"
        }
    ],
    "sg:phone":"+32 3 775 84 93",
    "sg:postcode":"9120",
    "sg:province":"Oost-Vlaanderen",
    "sg:tags":[
        "assurance"
    ],
    "wof:name":"Van Den Camp",
    "wof:placetype":"venue"
},
  "geometry": {"coordinates":[4.2840352058,51.2123947144],"type":"Point"}
}