{
  "type": "Feature",
  "properties": {
    "addr:full":"Mimosasstraat 39 Schaarbeek/schaerbeek Bruxelles-Capitale 1030",
    "addr:housenumber":"39",
    "addr:postcode":"1030",
    "addr:street":"Mimosasstraat",
    "iso:country":"BE",
    "sg:address":"Mimosasstraat 39",
    "sg:city":"Schaarbeek/schaerbeek",
    "sg:orig_category":"Fotografen and fotostudio's",
    "sg:phone":"+32 2 241 11 06",
    "sg:postcode":"1030",
    "sg:province":"Bruxelles-Capitale",
    "wof:name":"P. Carr\u00c9",
    "wof:placetype":"venue"
},
  "geometry": {"coordinates":[4.3874559402,50.8643379211],"type":"Point"}
}