{
  "type": "Feature",
  "properties": {
    "iso:country":"BE",
    "sg:address":"Clos Des Comtes Du Hainaut 4",
    "sg:city":"Ath",
    "sg:classifiers":[
        {
            "category":"Health Services",
            "subcategory":"Health Practitioner",
            "type":"Services"
        }
    ],
    "sg:phone":"+32 68 84 23 45",
    "sg:postcode":"7800",
    "sg:province":"Hainaut",
    "sg:tags":[
        "physiotherapist"
    ],
    "wof:name":"Dumont Stephane",
    "wof:placetype":"venue"
},
  "geometry": {"coordinates":[3.7744879723,50.6174430847],"type":"Point"}
}