{
  "type": "Feature",
  "properties": {
    "iso:country":"BE",
    "sg:address":"Sint-benedictusdreef 19",
    "sg:city":"Schoten",
    "sg:orig_category":"M\u00e9decins and sp\u00e9cialistes",
    "sg:phone":"+32 3 685 18 29",
    "sg:postcode":"2900",
    "sg:province":"Antwerpen",
    "wof:name":"G. Detournay",
    "wof:placetype":"venue"
},
  "geometry": {"coordinates":[4.5301918983,51.2468986511],"type":"Point"}
}