{
  "type": "Feature",
  "properties": {
    "addr:full":"Voorstraat 24 Kortrijk West-Vlaanderen 8500",
    "addr:housenumber":"24",
    "addr:postcode":"8500",
    "addr:street":"Voorstraat",
    "iso:country":"BE",
    "sg:address":"Voorstraat 24",
    "sg:city":"Kortrijk",
    "sg:classifiers":[
        {
            "category":"Shopping",
            "subcategory":"Bridal",
            "type":"Retail Goods"
        }
    ],
    "sg:phone":"+32 56 20 26 73",
    "sg:postcode":"8500",
    "sg:province":"West-Vlaanderen",
    "sg:tags":[
        "list",
        "-",
        "present",
        "wedding"
    ],
    "wof:name":"Villa Palladio",
    "wof:placetype":"venue"
},
  "geometry": {"coordinates":[3.2714750767,50.8277053833],"type":"Point"}
}