{
  "type": "Feature",
  "properties": {
    "addr:full":"Rue Jean Schinler 2 Sprimont Li\u00e8ge 4140",
    "addr:housenumber":"2",
    "addr:postcode":"4140",
    "addr:street":"Rue Jean Schinler",
    "iso:country":"BE",
    "sg:address":"Rue Jean Schinler 2",
    "sg:city":"Sprimont",
    "sg:orig_category":"Artistes ind\u00e9pendants",
    "sg:phone":"+32 4 382 20 35",
    "sg:postcode":"4140",
    "sg:province":"Li\u00e8ge",
    "wof:name":"Damien Laviolette",
    "wof:placetype":"venue"
},
  "geometry": {"coordinates":[5.6656570435,50.5001411438],"type":"Point"}
}