{
  "type": "Feature",
  "properties": {
    "iso:country":"BE",
    "sg:address":"Rooienberg 90",
    "sg:city":"Duffel",
    "sg:classifiers":[
        {
            "category":"Food & Beverages",
            "subcategory":"Fruits & Vegetables",
            "type":"Retail Goods"
        }
    ],
    "sg:phone":"+32 15 31 10 30",
    "sg:postcode":"2570",
    "sg:province":"Antwerpen",
    "sg:tags":[
        "groenten"
    ],
    "wof:name":"De Vos",
    "wof:placetype":"venue"
},
  "geometry": {"coordinates":[4.4864268303,51.0974655151],"type":"Point"}
}