{
  "type": "Feature",
  "properties": {
    "addr:full":"Stadsomvaart 11 Hasselt Limburg 3500",
    "addr:housenumber":"11",
    "addr:postcode":"3500",
    "addr:street":"Stadsomvaart",
    "iso:country":"BE",
    "sg:address":"Stadsomvaart 11",
    "sg:city":"Hasselt",
    "sg:orig_category":"Eclairage et \u00e9quipements du foyer. Tabac. Journaux",
    "sg:phone":"+32 11 30 84 95",
    "sg:postcode":"3500",
    "sg:province":"Limburg",
    "wof:name":"Kadootje",
    "wof:placetype":"venue"
},
  "geometry": {"coordinates":[5.3415780067,50.9264144897],"type":"Point"}
}