{
  "type": "Feature",
  "properties": {
    "addr:full":"Hooistraat 11 Dendermonde Oost-Vlaanderen 9200",
    "addr:housenumber":"11",
    "addr:postcode":"9200",
    "addr:street":"Hooistraat;Oost-Vlaanderen",
    "iso:country":"BE",
    "sg:address":"Hooistraat 11",
    "sg:city":"Dendermonde",
    "sg:orig_category":"Pluimveekwekers Rundveehouders",
    "sg:phone":"+32 52 21 50 58",
    "sg:postcode":"9200",
    "sg:province":"Oost-Vlaanderen",
    "wof:name":"Marcel Mathijs",
    "wof:placetype":"venue"
},
  "geometry": {"coordinates":[4.0983099937,51.0315208435],"type":"Point"}
}