{
  "type": "Feature",
  "properties": {
    "addr:full":"Ch De Jolimont 19 La Louviere Hainaut 7100",
    "addr:housenumber":"19",
    "addr:postcode":"7100",
    "addr:street":"Ch De Jolimont",
    "iso:country":"BE",
    "sg:address":"Ch De Jolimont 19",
    "sg:city":"La Louviere",
    "sg:orig_category":"Jeux de hasard",
    "sg:phone":"+32 64 21 24 20",
    "sg:postcode":"7100",
    "sg:province":"Hainaut",
    "wof:name":"Ladbroke",
    "wof:placetype":"venue"
},
  "geometry": {"coordinates":[4.2157001495,50.4721488953],"type":"Point"}
}