{
  "type": "Feature",
  "properties": {
    "addr:full":"Rue Du Marche Aux Herbes 39 Brussel Bruxelles-Capitale 1000",
    "addr:housenumber":"39",
    "addr:postcode":"1000",
    "addr:street":"Rue Du Marche Aux Herbes",
    "iso:country":"BE",
    "sg:address":"Rue Du Marche Aux Herbes 39",
    "sg:city":"Brussel",
    "sg:orig_category":"Speelgoed",
    "sg:phone":"+32 2 511 96 22",
    "sg:postcode":"1000",
    "sg:province":"Bruxelles-Capitale",
    "wof:name":"Grasshopper",
    "wof:placetype":"venue"
},
  "geometry": {"coordinates":[4.3525600433,50.8475036621],"type":"Point"}
}