{
  "type": "Feature",
  "properties": {
    "addr:full":"Anspachlaan 155 Brussel/bruxelles Bruxelles-Capitale 1000",
    "addr:housenumber":"155",
    "addr:postcode":"1000",
    "addr:street":"Anspachlaan;/",
    "iso:country":"BE",
    "sg:address":"Anspachlaan 155",
    "sg:city":"Brussel/bruxelles",
    "sg:orig_category":"Diverse kredietdiensten",
    "sg:postcode":"1000",
    "sg:province":"Bruxelles-Capitale",
    "wof:name":"Bancontact-mister Cash",
    "wof:placetype":"venue"
},
  "geometry": {"coordinates":[4.3470611572,50.8460617065],"type":"Point"}
}