{
  "type": "Feature",
  "properties": {
    "addr:full":"Avenue Wolvendael 13 Ukkel Bruxelles-Capitale 1180",
    "addr:housenumber":"13",
    "addr:postcode":"1180",
    "addr:street":"Avenue Wolvendael",
    "iso:country":"BE",
    "sg:address":"Avenue Wolvendael 13",
    "sg:city":"Ukkel",
    "sg:orig_category":"Diverse persoonlijke diensten",
    "sg:phone":"+32 2 375 06 09",
    "sg:postcode":"1180",
    "sg:province":"Bruxelles-Capitale",
    "wof:name":"Grimour",
    "wof:placetype":"venue"
},
  "geometry": {"coordinates":[4.3410730362,50.8003082275],"type":"Point"}
}