{
  "type": "Feature",
  "properties": {
    "iso:country":"BE",
    "sg:address":"Rue Du Commerce 2",
    "sg:city":"Aubange",
    "sg:classifiers":[
        {
            "category":"Bars & Pubs",
            "subcategory":"Champagne Bar",
            "type":"Food & Drink"
        }
    ],
    "sg:phone":"+32 63 38 81 75",
    "sg:postcode":"6791",
    "sg:province":"Luxembourg",
    "sg:tags":[
        "c\u00e9r\u00e9ales",
        "animaux",
        "gr",
        "pour",
        "aliment"
    ],
    "wof:name":"Socolaur",
    "wof:placetype":"venue"
},
  "geometry": {"coordinates":[5.8368301392,49.5627288818],"type":"Point"}
}