{
  "type": "Feature",
  "properties": {
    "iso:country":"BE",
    "sg:address":"Zwijnaardsesteenweg 316a Box E",
    "sg:city":"Gent",
    "sg:orig_category":"Non-Classified Establishments",
    "sg:phone":"+32 9 242 96 42",
    "sg:postcode":"9000",
    "sg:province":"Oost-Vlaanderen",
    "wof:name":"Elementis Service Centre Nv",
    "wof:placetype":"venue"
},
  "geometry": {"coordinates":[3.7285690308,51.0556335449],"type":"Point"}
}