{
  "type": "Feature",
  "properties": {
    "addr:full":"Grand'route 468a Braine L'alleud (lillois-witterz\u00e9e) Brabant Wallon 1428",
    "addr:housenumber":"468a",
    "addr:postcode":"1428",
    "addr:street":"Grand'Route",
    "iso:country":"BE",
    "sg:address":"Grand'route 468a",
    "sg:city":"Braine L'alleud (lillois-witterz\u00e9e)",
    "sg:classifiers":[
        {
            "category":"Education",
            "subcategory":"Dance Studio",
            "type":"Public Place"
        }
    ],
    "sg:phone":"+32 2 385 02 53",
    "sg:postcode":"1428",
    "sg:province":"Brabant Wallon",
    "sg:tags":[
        "school",
        "dancing"
    ],
    "wof:name":"Expression Asbl",
    "wof:placetype":"venue"
},
  "geometry": {"coordinates":[-0.6584389806,47.4034957886],"type":"Point"}
}