{
  "type": "Feature",
  "properties": {
    "addr:full":"Pastoor Peetersstraat 10 Bornem Antwerpen 2880",
    "addr:housenumber":"10",
    "addr:postcode":"2880",
    "addr:street":"Pastoor Peetersstraat",
    "iso:country":"BE",
    "sg:address":"Pastoor Peetersstraat 10",
    "sg:city":"Bornem",
    "sg:orig_category":"Enseignement maternel and primaire",
    "sg:phone":"+32 3 889 39 16",
    "sg:postcode":"2880",
    "sg:province":"Antwerpen",
    "wof:name":"Vrije Basisschool",
    "wof:placetype":"venue"
},
  "geometry": {"coordinates":[4.2027788162,51.0808868408],"type":"Point"}
}