{
  "type": "Feature",
  "properties": {
    "iso:country":"BE",
    "sg:address":"Rue Du Ry-des-mines 1",
    "sg:city":"La Bruyere",
    "sg:orig_category":"Woningbouw",
    "sg:phone":"+32 81 56 65 13",
    "sg:postcode":"5080",
    "sg:province":"Namur",
    "wof:name":"Fil-ter-co",
    "wof:placetype":"venue"
},
  "geometry": {"coordinates":[4.7953848839,50.505443573],"type":"Point"}
}