{
  "type": "Feature",
  "properties": {
    "addr:full":"Chauss\u00e9e De Neerstalle 442 Bruxelles (uccle) Bruxelles-Capitale 1180",
    "addr:housenumber":"442",
    "addr:postcode":"1180",
    "addr:street":"Chausse\u0301E De Neerstalle",
    "iso:country":"BE",
    "sg:address":"Chauss\u00e9e De Neerstalle 442",
    "sg:city":"Bruxelles (uccle)",
    "sg:classifiers":[
        {
            "category":"Building & Trades",
            "subcategory":"Construction",
            "type":"Services"
        }
    ],
    "sg:phone":"+32 2 376 55 67",
    "sg:postcode":"1180",
    "sg:province":"Bruxelles-Capitale",
    "sg:tags":[
        "glazier"
    ],
    "wof:name":"Maison Macbeth",
    "wof:placetype":"venue"
},
  "geometry": {"coordinates":[4.3209090233,50.7971305847],"type":"Point"}
}