{
  "type": "Feature",
  "properties": {
    "iso:country":"BE",
    "sg:address":"Korenbloemstraat 18",
    "sg:city":"Meerhout",
    "sg:orig_category":"Herstellingen and onderhoud aan huis voor voertuigen Huisdierenkwekers",
    "sg:phone":"+32 14 30 17 17",
    "sg:postcode":"2450",
    "sg:province":"Antwerpen",
    "wof:name":"Hannes",
    "wof:placetype":"venue"
},
  "geometry": {"coordinates":[5.0686888695,51.1382102966],"type":"Point"}
}