{
  "type": "Feature",
  "properties": {
    "iso:country":"BE",
    "sg:address":"Passage Wellington 44",
    "sg:city":"Waterloo",
    "sg:classifiers":[
        {
            "category":"Shopping",
            "subcategory":"Optician",
            "type":"Retail Goods"
        }
    ],
    "sg:phone":"+32 2 351 01 51",
    "sg:postcode":"1410",
    "sg:province":"Brabant Wallon",
    "sg:tags":[
        "-"
    ],
    "wof:name":"Wellington Optique",
    "wof:placetype":"venue"
},
  "geometry": {"coordinates":[4.4066472054,50.7151145935],"type":"Point"}
}