{
  "type": "Feature",
  "properties": {
    "iso:country":"BE",
    "sg:address":"Tulpenlaan 45",
    "sg:city":"Grimbergen (strombeek-bever)",
    "sg:classifiers":[
        {
            "category":"Health Services",
            "subcategory":"Health Practitioner",
            "type":"Services"
        }
    ],
    "sg:phone":"+32 2 267 12 65",
    "sg:postcode":"1853",
    "sg:province":"Vlaams-Brabant",
    "sg:tags":[
        "psychologist"
    ],
    "wof:name":"Claes A",
    "wof:placetype":"venue"
},
  "geometry": {"coordinates":[4.36398983,50.9094314575],"type":"Point"}
}