{
  "type": "Feature",
  "properties": {
    "iso:country":"BE",
    "sg:address":"Rue Hors-ch\u00c2teau 24",
    "sg:city":"Li\u00c8ge",
    "sg:orig_category":"M\u00e9decins and sp\u00e9cialistes",
    "sg:phone":"+32 4 237 02 07",
    "sg:postcode":"4000",
    "sg:province":"Li\u00e8ge",
    "wof:name":"J.m. Stevenin",
    "wof:placetype":"venue"
},
  "geometry": {"coordinates":[5.5770487785,50.6466522217],"type":"Point"}
}