{
  "type": "Feature",
  "properties": {
    "iso:country":"BE",
    "sg:address":"Spaanse Lindebaan 130",
    "sg:city":"Grimbergen",
    "sg:orig_category":"Fleurs and plantes",
    "sg:phone":"+32 2 270 23 10",
    "sg:postcode":"1850",
    "sg:province":"Vlaams-Brabant",
    "wof:name":"St\u00c9phane Gichumm",
    "wof:placetype":"venue"
},
  "geometry": {"coordinates":[4.3717479706,50.9233131409],"type":"Point"}
}