{
  "type": "Feature",
  "properties": {
    "iso:country":"BE",
    "sg:address":"Chauss\u00c9e Romaine 788",
    "sg:city":"Wemmel",
    "sg:orig_category":"Mat\u00e9riaux de construction Gr",
    "sg:phone":"+32 2 461 35 64",
    "sg:postcode":"1780",
    "sg:province":"Vlaams-Brabant",
    "wof:name":"D.t.e.",
    "wof:placetype":"venue"
},
  "geometry": {"coordinates":[4.3192830086,50.8952407837],"type":"Point"}
}