{
  "type": "Feature",
  "properties": {
    "iso:country":"BE",
    "sg:address":"Molendreef 18",
    "sg:city":"Anzegem",
    "sg:orig_category":"Pain, p\u00e2tisseries and confiseries",
    "sg:phone":"+32 56 77 77 73",
    "sg:postcode":"8570",
    "sg:province":"West-Vlaanderen",
    "wof:name":"Philip Derycke",
    "wof:placetype":"venue"
},
  "geometry": {"coordinates":[3.4019920826,50.8390541077],"type":"Point"}
}