{
  "type": "Feature",
  "properties": {
    "addr:full":"Koning Albertlaan 95 Lochristi Oost-Vlaanderen 9080",
    "addr:housenumber":"95",
    "addr:postcode":"9080",
    "addr:street":"Koning Albertlaan",
    "iso:country":"BE",
    "sg:address":"Koning Albertlaan 95",
    "sg:city":"Lochristi",
    "sg:classifiers":[
        {
            "category":"Home & Garden",
            "subcategory":"Home Furnishings",
            "type":"Retail Goods"
        }
    ],
    "sg:phone":"+32 9 355 74 20",
    "sg:postcode":"9080",
    "sg:province":"Oost-Vlaanderen",
    "sg:tags":[
        "interior",
        "decoration"
    ],
    "wof:name":"Schatteman H",
    "wof:placetype":"venue"
},
  "geometry": {"coordinates":[3.8273620605,51.1028671265],"type":"Point"}
}