{
  "type": "Feature",
  "properties": {
    "addr:full":"Dorpsstraat 22 Heuvelland West-Vlaanderen 8952",
    "addr:housenumber":"22",
    "addr:postcode":"8952",
    "addr:street":"Dorpsstraat",
    "iso:country":"BE",
    "sg:address":"Dorpsstraat 22",
    "sg:city":"Heuvelland",
    "sg:orig_category":"Instellingen voor mindervalide volwassenen",
    "sg:phone":"+32 57 44 56 18",
    "sg:postcode":"8952",
    "sg:province":"West-Vlaanderen",
    "wof:name":"De Pelgrim",
    "wof:placetype":"venue"
},
  "geometry": {"coordinates":[2.8543798923,50.7594032288],"type":"Point"}
}