{
  "type": "Feature",
  "properties": {
    "iso:country":"BE",
    "sg:address":"Impasse Du Spinois 18",
    "sg:city":"Fleurus",
    "sg:orig_category":"Fotografen and fotostudio's",
    "sg:phone":"+32 71 81 51 38",
    "sg:postcode":"6224",
    "sg:province":"Hainaut",
    "wof:name":"Philippe Derousseaux",
    "wof:placetype":"venue"
},
  "geometry": {"coordinates":[4.5681681633,50.4570732117],"type":"Point"}
}