{
  "type": "Feature",
  "properties": {
    "addr:full":"Steenweg Op Dendermonde 130 Aalst Oost-Vlaanderen 9308",
    "addr:housenumber":"130",
    "addr:postcode":"9308",
    "addr:street":"Steenweg Op Dendermonde",
    "iso:country":"BE",
    "sg:address":"Steenweg Op Dendermonde 130",
    "sg:city":"Aalst",
    "sg:orig_category":"Gespecialiseerde niet-residenti\u00eble bouw Industri\u00eble and commerci\u00eble bouw",
    "sg:phone":"+32 53 71 06 09",
    "sg:postcode":"9308",
    "sg:province":"Oost-Vlaanderen",
    "wof:name":"De Ridder",
    "wof:placetype":"venue"
},
  "geometry": {"coordinates":[4.0347590446,50.9603500366],"type":"Point"}
}