{
  "type": "Feature",
  "properties": {
    "addr:full":"Rue Emile Dury 50 Waterloo Brabant Wallon 1410",
    "addr:housenumber":"50",
    "addr:postcode":"1410",
    "addr:street":"Rue Emile Dury",
    "iso:country":"BE",
    "sg:address":"Rue Emile Dury 50",
    "sg:city":"Waterloo",
    "sg:classifiers":[
        {
            "category":"Food & Beverages",
            "subcategory":"Groceries & Convenience Stores",
            "type":"Retail Goods"
        }
    ],
    "sg:phone":"+32 2 354 78 23",
    "sg:postcode":"1410",
    "sg:province":"Brabant Wallon",
    "sg:tags":[
        "grocer"
    ],
    "wof:name":"Caspienne",
    "wof:placetype":"venue"
},
  "geometry": {"coordinates":[4.3795371056,50.7075424194],"type":"Point"}
}