{
  "type": "Feature",
  "properties": {
    "iso:country":"BE",
    "sg:address":"Schierveldestraat 11",
    "sg:city":"Staden",
    "sg:orig_category":"Groententeelt",
    "sg:phone":"+32 51 24 01 32",
    "sg:postcode":"8840",
    "sg:province":"West-Vlaanderen",
    "wof:name":"Maria Moutton",
    "wof:placetype":"venue"
},
  "geometry": {"coordinates":[3.0797109604,50.9518852234],"type":"Point"}
}