{
  "type": "Feature",
  "properties": {
    "iso:country":"BE",
    "sg:address":"Vonckstraat 58",
    "sg:city":"Herenthout",
    "sg:orig_category":"Afvalwaterverwerking and ontstoppingsdiensten Huisvuilophaling and -verwerking",
    "sg:phone":"+32 14 23 07 85",
    "sg:postcode":"2270",
    "sg:province":"Antwerpen",
    "wof:name":"Van Mogh J.",
    "wof:placetype":"venue"
},
  "geometry": {"coordinates":[4.7599549294,51.1386833191],"type":"Point"}
}