{
  "type": "Feature",
  "properties": {
    "addr:full":"Monninxstraat 5 Hasselt Limburg 3510",
    "addr:housenumber":"5",
    "addr:postcode":"3510",
    "addr:street":"Monninxstraat",
    "iso:country":"BE",
    "sg:address":"Monninxstraat 5",
    "sg:city":"Hasselt",
    "sg:orig_category":"Dierenartsen",
    "sg:phone":"+32 11 87 24 12",
    "sg:postcode":"3510",
    "sg:province":"Limburg",
    "wof:name":"Els Minsen",
    "wof:placetype":"venue"
},
  "geometry": {"coordinates":[5.2389001846,50.955909729],"type":"Point"}
}