{
  "type": "Feature",
  "properties": {
    "iso:country":"BE",
    "sg:address":"Rue Des Couteliers 13",
    "sg:city":"Court-saint-etienne",
    "sg:orig_category":"Plaatsen van vloer- and muurbekleding",
    "sg:phone":"+32 475 94 86 61",
    "sg:postcode":"1490",
    "sg:province":"Brabant Wallon",
    "wof:name":"E.g. Entreprises",
    "wof:placetype":"venue"
},
  "geometry": {"coordinates":[4.560863018,50.6167106628],"type":"Point"}
}