{
  "type": "Feature",
  "properties": {
    "addr:full":"Place De L'eglise 6a Cerfontaine Namur 5630",
    "addr:housenumber":"6a",
    "addr:postcode":"5630",
    "addr:street":"Place De L'Eglise",
    "iso:country":"BE",
    "sg:address":"Place De L'eglise 6a",
    "sg:city":"Cerfontaine",
    "sg:classifiers":[
        {
            "category":"Shopping",
            "subcategory":"Pharmacy",
            "type":"Retail Goods"
        }
    ],
    "sg:phone":"+32 71 64 40 79",
    "sg:postcode":"5630",
    "sg:province":"Namur",
    "sg:tags":[
        "store",
        "drug"
    ],
    "wof:name":"Buchet Sprl",
    "wof:placetype":"venue"
},
  "geometry": {"coordinates":[4.410130024,50.1695098877],"type":"Point"}
}