{
  "type": "Feature",
  "properties": {
    "iso:country":"BE",
    "sg:address":"Clos Du Colbie 8",
    "sg:city":"Braine-l'alleud",
    "sg:orig_category":"Studios photographiques",
    "sg:phone":"+32 2 387 34 37",
    "sg:postcode":"1420",
    "sg:province":"Brabant Wallon",
    "wof:name":"Rudy Langlais",
    "wof:placetype":"venue"
},
  "geometry": {"coordinates":[-0.6790779829,47.3779411316],"type":"Point"}
}