{
  "type": "Feature",
  "properties": {
    "addr:full":"Markt 4 Kruishoutem Oost-Vlaanderen 9770",
    "addr:housenumber":"4",
    "addr:postcode":"9770",
    "addr:street":"Markt",
    "iso:country":"BE",
    "sg:address":"Markt 4",
    "sg:city":"Kruishoutem",
    "sg:orig_category":"Banken and kredietinstellingen",
    "sg:phone":"+32 9 383 53 34",
    "sg:postcode":"9770",
    "sg:province":"Oost-Vlaanderen",
    "wof:name":"Fortis",
    "wof:placetype":"venue"
},
  "geometry": {"coordinates":[3.5277609825,50.9045372009],"type":"Point"}
}