{
  "type": "Feature",
  "properties": {
    "iso:country":"BE",
    "sg:address":"Bredabaan 891-893",
    "sg:city":"Antwerpen (merksem)",
    "sg:classifiers":[
        {
            "category":"Shopping",
            "subcategory":"Pets & Pet Supplies",
            "type":"Retail Goods"
        }
    ],
    "sg:phone":"+32 3 645 96 77",
    "sg:postcode":"2170",
    "sg:province":"Antwerpen",
    "sg:tags":[
        "aquarium",
        "accessory"
    ],
    "wof:name":"Petco Dierensuper Bvba",
    "wof:placetype":"venue"
},
  "geometry": {"coordinates":[4.4505147934,51.246723175],"type":"Point"}
}