{
  "type": "Feature",
  "properties": {
    "iso:country":"BE",
    "sg:address":"Cathilleweg 8",
    "sg:city":"Jabbeke",
    "sg:orig_category":"Rev\u00eatements pour sols and murs. Peinture",
    "sg:phone":"+32 50 81 47 21",
    "sg:postcode":"8490",
    "sg:province":"West-Vlaanderen",
    "wof:name":"Paul Baillieu",
    "wof:placetype":"venue"
},
  "geometry": {"coordinates":[3.0814809799,51.2055168152],"type":"Point"}
}