{
  "type": "Feature",
  "properties": {
    "addr:full":"Baliestraat 106 Brugge West-Vlaanderen 8000",
    "addr:housenumber":"106",
    "addr:postcode":"8000",
    "addr:street":"Baliestraat",
    "iso:country":"BE",
    "sg:address":"Baliestraat 106",
    "sg:city":"Brugge",
    "sg:classifiers":[
        {
            "category":"Health Services",
            "subcategory":"Health Practitioner",
            "type":"Services"
        }
    ],
    "sg:phone":"+32 50 33 82 57",
    "sg:postcode":"8000",
    "sg:province":"West-Vlaanderen",
    "sg:tags":[
        "physiotherapist"
    ],
    "wof:name":"Cappelle Johan",
    "wof:placetype":"venue"
},
  "geometry": {"coordinates":[3.2257790565,51.2180099487],"type":"Point"}
}