{
  "type": "Feature",
  "properties": {
    "addr:full":"Klosterstrasse 11-17 Eupen Li\u00e8ge 4700",
    "addr:postcode":"11-17;4700",
    "addr:street":"Klosterstrasse",
    "iso:country":"BE",
    "sg:address":"Klosterstrasse 11-17",
    "sg:city":"Eupen",
    "sg:classifiers":[
        {
            "category":"Shopping",
            "subcategory":"Clothing, Apparel, & Fashions",
            "type":"Retail Goods"
        }
    ],
    "sg:phone":"+32 87 55 24 08",
    "sg:postcode":"4700",
    "sg:province":"Li\u00e8ge",
    "sg:tags":[
        "boutique"
    ],
    "wof:name":"Junge Mode - Sandy's Sprl",
    "wof:placetype":"venue"
},
  "geometry": {"coordinates":[6.0305900574,50.6315460205],"type":"Point"}
}