{
  "type": "Feature",
  "properties": {
    "addr:full":"Petit-audenardestraat 113 Moeskroen/mouscron Hainaut 7712",
    "addr:housenumber":"113 moeskroen;mouscron",
    "addr:postcode":"7712",
    "addr:street":"Hainaut",
    "iso:country":"BE",
    "sg:address":"Petit-audenardestraat 113",
    "sg:city":"Moeskroen/mouscron",
    "sg:orig_category":"Banken and kredietinstellingen",
    "sg:phone":"+32 56 33 04 14",
    "sg:postcode":"7712",
    "sg:province":"Hainaut",
    "wof:name":"Bbl",
    "wof:placetype":"venue"
},
  "geometry": {"coordinates":[3.2535879612,50.714931488],"type":"Point"}
}