{
  "type": "Feature",
  "properties": {
    "addr:full":"Meershoven 84 Bilzen Limburg 3740",
    "addr:housenumber":"84",
    "addr:postcode":"3740",
    "addr:street":"Meershoven",
    "iso:country":"BE",
    "sg:address":"Meershoven 84",
    "sg:city":"Bilzen",
    "sg:classifiers":[
        {
            "category":"Personal",
            "subcategory":"Barber",
            "type":"Services"
        }
    ],
    "sg:phone":"+32 89 49 19 52",
    "sg:postcode":"3740",
    "sg:province":"Limburg",
    "sg:tags":[
        "gentleman",
        "salon",
        "-",
        "hairdressing"
    ],
    "wof:name":"Nasser Atelier",
    "wof:placetype":"venue"
},
  "geometry": {"coordinates":[5.5270829201,50.8774185181],"type":"Point"}
}