{
  "type": "Feature",
  "properties": {
    "addr:full":"Avenue Firmin Lecharlier 150 Bruxelles (jette) Bruxelles-Capitale 1090",
    "addr:housenumber":"150",
    "addr:postcode":"1090",
    "addr:street":"Avenue Firmin Lecharlier",
    "iso:country":"BE",
    "sg:address":"Avenue Firmin Lecharlier 150",
    "sg:city":"Bruxelles (jette)",
    "sg:classifiers":[
        {
            "category":"Real Estate",
            "subcategory":"Architect",
            "type":"Services"
        }
    ],
    "sg:phone":"+32 2 426 29 90",
    "sg:postcode":"1090",
    "sg:province":"Bruxelles-Capitale",
    "wof:name":"Groep Est\u00e9",
    "wof:placetype":"venue"
},
  "geometry": {"coordinates":[4.3348941803,50.8680992126],"type":"Point"}
}