{
  "type": "Feature",
  "properties": {
    "addr:full":"Peperstraat 11 Tienen Vlaams-Brabant 3300",
    "addr:housenumber":"11",
    "addr:postcode":"3300",
    "addr:street":"Peperstraat",
    "iso:country":"BE",
    "sg:address":"Peperstraat 11",
    "sg:city":"Tienen",
    "sg:classifiers":[
        {
            "category":"Fast Food",
            "type":"Food & Drink"
        }
    ],
    "sg:phone":"+32 16 81 55 17",
    "sg:postcode":"3300",
    "sg:province":"Vlaams-Brabant",
    "sg:tags":[
        "\u00c0",
        "restaurants",
        "emporter",
        "restaurant"
    ],
    "wof:name":"Kowloon",
    "wof:placetype":"venue"
},
  "geometry": {"coordinates":[4.9374451637,50.806350708],"type":"Point"}
}