{
  "type": "Feature",
  "properties": {
    "addr:full":"Henri Regastraat 12 Leuven Vlaams-Brabant 3000",
    "addr:housenumber":"12",
    "addr:postcode":"3000",
    "addr:street":"Henri Regastraat",
    "iso:country":"BE",
    "sg:address":"Henri Regastraat 12",
    "sg:city":"Leuven",
    "sg:orig_category":"Activit\u00e9s d\u00b4action sociale sans h\u00e9bergement",
    "sg:phone":"+32 16 22 79 96",
    "sg:postcode":"3000",
    "sg:province":"Vlaams-Brabant",
    "wof:name":"C.l.b.",
    "wof:placetype":"venue"
},
  "geometry": {"coordinates":[4.7094349861,50.8704719543],"type":"Point"}
}