{
  "type": "Feature",
  "properties": {
    "addr:full":"Nerm 82 Hoegaarden Vlaams-Brabant 3320",
    "addr:housenumber":"82",
    "addr:postcode":"3320",
    "addr:street":"Nerm",
    "iso:country":"BE",
    "sg:address":"Nerm 82",
    "sg:city":"Hoegaarden",
    "sg:orig_category":"Tweedehandsgoederen",
    "sg:phone":"+32 16 76 78 20",
    "sg:postcode":"3320",
    "sg:province":"Vlaams-Brabant",
    "wof:name":"All Computer Serv. Acos",
    "wof:placetype":"venue"
},
  "geometry": {"coordinates":[4.8713197708,50.7709960938],"type":"Point"}
}