{
  "type": "Feature",
  "properties": {
    "iso:country":"BE",
    "sg:address":"Rue Cheminet 2",
    "sg:city":"Tournai (esplechin)",
    "sg:classifiers":[
        {
            "category":"Farming",
            "subcategory":"Farm & Veterinary Services",
            "type":"Manufacturing & Wholesale Goods"
        }
    ],
    "sg:phone":"+32 69 64 84 32",
    "sg:postcode":"7502",
    "sg:province":"Hainaut",
    "sg:tags":[
        "agricultural",
        "contractor"
    ],
    "wof:name":"Tricart'her Sprl Sprl",
    "wof:placetype":"venue"
},
  "geometry": {"coordinates":[3.292994976,50.575466156],"type":"Point"}
}