{
  "type": "Feature",
  "properties": {
    "addr:full":"Mottekensstraat 1 Lebbeke (denderbelle) Oost-Vlaanderen 9280",
    "addr:housenumber":"1",
    "addr:postcode":"9280",
    "addr:street":"Mottekensstraat",
    "iso:country":"BE",
    "sg:address":"Mottekensstraat 1",
    "sg:city":"Lebbeke (denderbelle)",
    "sg:classifiers":[
        {
            "category":"Health Services",
            "subcategory":"Health Practitioner",
            "type":"Services"
        }
    ],
    "sg:phone":"+32 52 41 30 05",
    "sg:postcode":"9280",
    "sg:province":"Oost-Vlaanderen",
    "sg:tags":[
        "physiotherapist"
    ],
    "wof:name":"Meert K",
    "wof:placetype":"venue"
},
  "geometry": {"coordinates":[4.0936670303,50.9889602661],"type":"Point"}
}