{
  "type": "Feature",
  "properties": {
    "addr:full":"De Gerlachestraat 2b2 Hasselt Limburg 3500",
    "addr:housenumber":"2b2",
    "addr:postcode":"3500",
    "addr:street":"De Gerlachestraat",
    "iso:country":"BE",
    "sg:address":"De Gerlachestraat 2b2",
    "sg:city":"Hasselt",
    "sg:orig_category":"Artsen and specialisten",
    "sg:phone":"+32 11 22 89 03",
    "sg:postcode":"3500",
    "sg:province":"Limburg",
    "wof:name":"Marc Muyldermans",
    "wof:placetype":"venue"
},
  "geometry": {"coordinates":[5.3415470123,50.9276695251],"type":"Point"}
}