{
  "type": "Feature",
  "properties": {
    "addr:full":"Rue Edouard Huys 3 Merbes-le-ch\u00c2teau Hainaut 6567",
    "addr:housenumber":"3",
    "addr:postcode":"6567",
    "addr:street":"Rue Edouard Huys",
    "iso:country":"BE",
    "sg:address":"Rue Edouard Huys 3",
    "sg:city":"Merbes-le-ch\u00c2teau",
    "sg:orig_category":"Entretien and r\u00e9parations de voitures",
    "sg:phone":"+32 71 55 52 75",
    "sg:postcode":"6567",
    "sg:province":"Hainaut",
    "wof:name":"Garage Desoil",
    "wof:placetype":"venue"
},
  "geometry": {"coordinates":[4.225757122,50.314239502],"type":"Point"}
}