{
  "type": "Feature",
  "properties": {
    "iso:country":"BE",
    "sg:address":"All\u00e9e De L'europe 16",
    "sg:city":"Vis\u00e9",
    "sg:classifiers":[
        {
            "category":"Food & Beverages",
            "subcategory":"Groceries & Convenience Stores",
            "type":"Retail Goods"
        }
    ],
    "sg:phone":"+32 4 379 69 43",
    "sg:postcode":"4600",
    "sg:province":"Li\u00e8ge",
    "sg:tags":[
        "grocer"
    ],
    "wof:name":"4 Saisons (aux)",
    "wof:placetype":"venue"
},
  "geometry": {"coordinates":[5.7044568062,50.7400283813],"type":"Point"}
}