{
  "type": "Feature",
  "properties": {
    "addr:full":"Heirweg 19 Kuurne West-Vlaanderen 8520",
    "addr:housenumber":"19",
    "addr:postcode":"8520",
    "addr:street":"Heirweg",
    "iso:country":"BE",
    "sg:address":"Heirweg 19",
    "sg:city":"Kuurne",
    "sg:orig_category":"Bijouteries and horlogeries",
    "sg:phone":"+32 56 35 70 76",
    "sg:postcode":"8520",
    "sg:province":"West-Vlaanderen",
    "wof:name":"Luc Vierstraete",
    "wof:placetype":"venue"
},
  "geometry": {"coordinates":[3.265100956,50.8546104431],"type":"Point"}
}