{
  "type": "Feature",
  "properties": {
    "addr:full":"Chauss\u00e9e Du Roeulx 262a Mons Hainaut 7000",
    "addr:housenumber":"262a",
    "addr:postcode":"7000",
    "addr:street":"Chausse\u0301E Du Roeulx;Hainaut",
    "iso:country":"BE",
    "sg:address":"Chauss\u00e9e Du Roeulx 262a",
    "sg:city":"Mons",
    "sg:classifiers":[
        {
            "category":"Shopping",
            "subcategory":"Books",
            "type":"Retail Goods"
        }
    ],
    "sg:phone":"+32 65 34 08 35",
    "sg:postcode":"7000",
    "sg:province":"Hainaut",
    "sg:tags":[
        "bookseller"
    ],
    "wof:name":"Sinnaeve M",
    "wof:placetype":"venue"
},
  "geometry": {"coordinates":[3.9813320637,50.4563713074],"type":"Point"}
}