{
  "type": "Feature",
  "properties": {
    "iso:country":"BE",
    "sg:address":"Rue De F\u00c9tinne 13",
    "sg:city":"Li\u00c8ge",
    "sg:orig_category":"Herstelling and restauratie van meubelen",
    "sg:phone":"+32 4 342 71 46",
    "sg:postcode":"4020",
    "sg:province":"Li\u00e8ge",
    "wof:name":"Marc Hermesse",
    "wof:placetype":"venue"
},
  "geometry": {"coordinates":[5.5817451477,50.6277503967],"type":"Point"}
}