{
  "type": "Feature",
  "properties": {
    "iso:country":"BE",
    "sg:address":"Rue De La Vall\u00e9e 18",
    "sg:city":"Celles (viemme)",
    "sg:classifiers":[
        {
            "category":"Personal",
            "subcategory":"Beauty Salon",
            "type":"Services"
        }
    ],
    "sg:phone":"+32 19 32 54 43",
    "sg:postcode":"4317",
    "sg:province":"Li\u00e8ge",
    "sg:tags":[
        "lady",
        "-",
        "hairdressing"
    ],
    "wof:name":"Myriam",
    "wof:placetype":"venue"
},
  "geometry": {"coordinates":[5.2618951797,50.6657218933],"type":"Point"}
}