{
  "type": "Feature",
  "properties": {
    "iso:country":"BE",
    "sg:address":"Chauss\u00e9e De Fleurus 4",
    "sg:city":"Charleroi (gilly)",
    "sg:classifiers":[
        {
            "category":"Wholesale",
            "subcategory":"Medical Equipment & Supplies",
            "type":"Manufacturing & Wholesale Goods"
        }
    ],
    "sg:phone":"+32 71 41 25 16",
    "sg:postcode":"6060",
    "sg:province":"Hainaut",
    "sg:tags":[
        "aid",
        "hearing"
    ],
    "wof:name":"Vision Et Precision Sprl",
    "wof:placetype":"venue"
},
  "geometry": {"coordinates":[4.4721298218,50.4454612732],"type":"Point"}
}