{
  "type": "Feature",
  "properties": {
    "iso:country":"BE",
    "sg:address":"Vredeplein 3",
    "sg:city":"Aalst",
    "sg:orig_category":"Reisbureaus",
    "sg:phone":"+32 53 77 36 00",
    "sg:postcode":"9300",
    "sg:province":"Oost-Vlaanderen",
    "wof:name":"Ticket B.b.l. Travel/huybrechts",
    "wof:placetype":"venue"
},
  "geometry": {"coordinates":[4.034142971,50.9383811951],"type":"Point"}
}