{
  "type": "Feature",
  "properties": {
    "addr:full":"Lekestraat 128 Eeklo Oost-Vlaanderen 9900",
    "addr:housenumber":"128",
    "addr:postcode":"9900",
    "addr:street":"Lekestraat",
    "iso:country":"BE",
    "sg:address":"Lekestraat 128",
    "sg:city":"Eeklo",
    "sg:orig_category":"Boekhouders",
    "sg:phone":"+32 9 377 95 94",
    "sg:postcode":"9900",
    "sg:province":"Oost-Vlaanderen",
    "wof:name":"Van Hulle Marc",
    "wof:placetype":"venue"
},
  "geometry": {"coordinates":[3.5903348923,51.1793365479],"type":"Point"}
}