{
  "type": "Feature",
  "properties": {
    "iso:country":"BE",
    "sg:address":"Heidelaan 17",
    "sg:city":"De Pinte",
    "sg:orig_category":"Artiesten and kunstenaars",
    "sg:phone":"+32 9 282 59 58",
    "sg:postcode":"9840",
    "sg:province":"Oost-Vlaanderen",
    "wof:name":"Sven Op De Beeck",
    "wof:placetype":"venue"
},
  "geometry": {"coordinates":[3.6355860233,50.9957084656],"type":"Point"}
}