{
  "type": "Feature",
  "properties": {
    "iso:country":"BE",
    "sg:address":"Rue De Verviers 38",
    "sg:city":"Eupen/eupen",
    "sg:orig_category":"M\u00e9decins and sp\u00e9cialistes",
    "sg:phone":"+32 87 55 30 78",
    "sg:postcode":"4700",
    "sg:province":"Li\u00e8ge",
    "wof:name":"Guido Pesch",
    "wof:placetype":"venue"
},
  "geometry": {"coordinates":[6.0244259834,50.6316108704],"type":"Point"}
}