{
  "type": "Feature",
  "properties": {
    "iso:country":"BE",
    "sg:address":"Rue Du Vieux Moulin 11",
    "sg:city":"Saint-l\u00e9ger",
    "sg:classifiers":[
        {
            "category":"Real Estate",
            "subcategory":"Architect",
            "type":"Services"
        }
    ],
    "sg:phone":"+32 63 23 94 09",
    "sg:postcode":"6747",
    "sg:province":"Luxembourg",
    "wof:name":"Langlois C",
    "wof:placetype":"venue"
},
  "geometry": {"coordinates":[5.6532897949,49.602230072],"type":"Point"}
}