{
  "type": "Feature",
  "properties": {
    "addr:full":"Rue Du Bilemont 47 Mouscron Hainaut 7700",
    "addr:housenumber":"47",
    "addr:postcode":"7700",
    "addr:street":"Rue Du Bilemont",
    "iso:country":"BE",
    "sg:address":"Rue Du Bilemont 47",
    "sg:city":"Mouscron",
    "sg:classifiers":[
        {
            "category":"Health Services",
            "subcategory":"Doctor",
            "type":"Services"
        }
    ],
    "sg:phone":"+32 56 84 30 98",
    "sg:postcode":"7700",
    "sg:province":"Hainaut",
    "sg:tags":[
        "medicinephysicians",
        "surgeon"
    ],
    "wof:name":"Deceuninck Paul",
    "wof:placetype":"venue"
},
  "geometry": {"coordinates":[3.2124660015,50.7382850647],"type":"Point"}
}