{
  "type": "Feature",
  "properties": {
    "addr:full":"Oude Dendermondse Stweenweg 328 Aalst Oost-Vlaanderen 9300",
    "addr:housenumber":"328",
    "addr:postcode":"9300",
    "addr:street":"Oude;Stweenweg",
    "iso:country":"BE",
    "sg:address":"Oude Dendermondse Stweenweg 328",
    "sg:city":"Aalst",
    "sg:orig_category":"Levering aan huis restaurants",
    "sg:phone":"+32 53 78 25 46",
    "sg:postcode":"9300",
    "sg:province":"Oost-Vlaanderen",
    "wof:name":"De Cock-de Schutter",
    "wof:placetype":"venue"
},
  "geometry": {"coordinates":[4.0559959412,50.9554672241],"type":"Point"}
}