{
  "type": "Feature",
  "properties": {
    "addr:full":"Velmerlaan 192 Sint-truiden (velm) Limburg 3806",
    "addr:housenumber":"192",
    "addr:postcode":"3806",
    "addr:street":"Velmerlaan",
    "iso:country":"BE",
    "sg:address":"Velmerlaan 192",
    "sg:city":"Sint-truiden (velm)",
    "sg:classifiers":[
        {
            "category":"Professional",
            "subcategory":"Testing Lab",
            "type":"Services"
        }
    ],
    "sg:phone":"+32 11 68 74 44",
    "sg:postcode":"3806",
    "sg:province":"Limburg",
    "sg:tags":[
        "chemist"
    ],
    "wof:name":"Van Meensel",
    "wof:placetype":"venue"
},
  "geometry": {"coordinates":[5.1337070465,50.7815284729],"type":"Point"}
}