{
  "type": "Feature",
  "properties": {
    "iso:country":"BE",
    "sg:address":"Geluwestraat 16",
    "sg:city":"Moorslede (dadizele)",
    "sg:classifiers":[
        {
            "category":"Farming",
            "subcategory":"Farm & Veterinary Services",
            "type":"Manufacturing & Wholesale Goods"
        }
    ],
    "sg:phone":"+32 56 50 02 12",
    "sg:postcode":"8890",
    "sg:province":"West-Vlaanderen",
    "sg:tags":[
        "agricultural",
        "contractor"
    ],
    "wof:name":"Vynckier",
    "wof:placetype":"venue"
},
  "geometry": {"coordinates":[3.0637769699,50.891456604],"type":"Point"}
}