{
  "type": "Feature",
  "properties": {
    "addr:full":"Kruisweg 11 Haven 650 Antwerpen Antwerpen 2040",
    "addr:housenumber":"11;650",
    "addr:postcode":"2040",
    "addr:street":"Kruisweg;Haven",
    "iso:country":"BE",
    "sg:address":"Kruisweg 11 Haven 650",
    "sg:city":"Antwerpen",
    "sg:classifiers":[
        {
            "category":"Transit Center",
            "subcategory":"Freight",
            "type":"Transportation"
        }
    ],
    "sg:phone":"+32 3 542 51 20",
    "sg:postcode":"2040",
    "sg:province":"Antwerpen",
    "sg:tags":[
        "ser",
        "business",
        "travel",
        "-",
        "air",
        "transport",
        "sea",
        "road"
    ],
    "wof:name":"Geologistics",
    "wof:placetype":"venue"
},
  "geometry": {"coordinates":[4.3254981041,51.3139648438],"type":"Point"}
}