{
  "type": "Feature",
  "properties": {
    "addr:full":"Magerakkerlaan 2 Lochristi Oost-Vlaanderen 9080",
    "addr:housenumber":"2",
    "addr:postcode":"9080",
    "addr:street":"Magerakkerlaan",
    "iso:country":"BE",
    "sg:address":"Magerakkerlaan 2",
    "sg:city":"Lochristi",
    "sg:orig_category":"Paramedische behandelingen",
    "sg:phone":"+32 9 355 79 02",
    "sg:postcode":"9080",
    "sg:province":"Oost-Vlaanderen",
    "wof:name":"B. Derijcke",
    "wof:placetype":"venue"
},
  "geometry": {"coordinates":[3.8580338955,51.0964698792],"type":"Point"}
}