{
  "type": "Feature",
  "properties": {
    "addr:full":"Rue De Marchovelette 21 Namur Namur 5000",
    "addr:housenumber":"21",
    "addr:postcode":"5000",
    "addr:street":"Rue De Marchovelette",
    "iso:country":"BE",
    "sg:address":"Rue De Marchovelette 21",
    "sg:city":"Namur",
    "sg:classifiers":[
        {
            "category":"Utilities",
            "subcategory":"Mobile Phone",
            "type":"Services"
        }
    ],
    "sg:phone":"+32 81 26 26 26",
    "sg:postcode":"5000",
    "sg:province":"Namur",
    "sg:tags":[
        "-",
        "gsm"
    ],
    "wof:name":"Espace Communication",
    "wof:placetype":"venue"
},
  "geometry": {"coordinates":[4.8668460846,50.4626121521],"type":"Point"}
}