{
  "type": "Feature",
  "properties": {
    "addr:full":"Zwaluwenlaan 2a Kortrijk West-Vlaanderen 8500",
    "addr:housenumber":"2a",
    "addr:postcode":"8500",
    "addr:street":"Zwaluwenlaan",
    "iso:country":"BE",
    "sg:address":"Zwaluwenlaan 2a",
    "sg:city":"Kortrijk",
    "sg:classifiers":[
        {
            "category":"Shopping",
            "subcategory":"Clothing, Apparel, & Fashions",
            "type":"Retail Goods"
        }
    ],
    "sg:phone":"+32 56 20 53 21",
    "sg:postcode":"8500",
    "sg:province":"West-Vlaanderen",
    "sg:tags":[
        "-",
        "clothing",
        "child"
    ],
    "wof:name":"Venise Du Nord",
    "wof:placetype":"venue"
},
  "geometry": {"coordinates":[3.2986791134,50.8160133362],"type":"Point"}
}