{
  "type": "Feature",
  "properties": {
    "iso:country":"BE",
    "sg:address":"Duffelsesteenweg 113",
    "sg:city":"Sint-katelijne-waver",
    "sg:classifiers":[
        {
            "category":"Health Services",
            "subcategory":"Health Practitioner",
            "type":"Services"
        }
    ],
    "sg:phone":"+32 15 31 63 10",
    "sg:postcode":"2860",
    "sg:province":"Antwerpen",
    "sg:tags":[
        "physiotherapist"
    ],
    "wof:name":"Slagmolen Jan",
    "wof:placetype":"venue"
},
  "geometry": {"coordinates":[4.5251398087,51.0806617737],"type":"Point"}
}