{
  "type": "Feature",
  "properties": {
    "addr:full":"Koning-albertlaan 186 Lochristi Oost-Vlaanderen 9080",
    "addr:housenumber":"186",
    "addr:postcode":"9080",
    "iso:country":"BE",
    "sg:address":"Koning-albertlaan 186",
    "sg:city":"Lochristi",
    "sg:orig_category":"Instituts de beaut\u00e9",
    "sg:phone":"+32 9 355 63 30",
    "sg:postcode":"9080",
    "sg:province":"Oost-Vlaanderen",
    "wof:name":"Ivan Lybaert",
    "wof:placetype":"venue"
},
  "geometry": {"coordinates":[3.8176019192,51.1091575623],"type":"Point"}
}