{
  "type": "Feature",
  "properties": {
    "addr:full":"Industrielaan 2 Hoeselt Limburg 3730",
    "addr:housenumber":"2",
    "addr:postcode":"3730",
    "addr:street":"Industrielaan",
    "iso:country":"BE",
    "sg:address":"Industrielaan 2",
    "sg:city":"Hoeselt",
    "sg:classifiers":[
        {
            "category":"Autos & Motor Vehicles",
            "subcategory":"Auto Supplies",
            "type":"Retail Goods"
        }
    ],
    "sg:phone":"+32 89 41 10 41",
    "sg:postcode":"3730",
    "sg:province":"Limburg",
    "sg:tags":[
        "body",
        "car",
        "truck",
        "trailer",
        "superstructure"
    ],
    "wof:name":"Jans Creacar Nv",
    "wof:placetype":"venue"
},
  "geometry": {"coordinates":[5.4953641891,50.8577728271],"type":"Point"}
}