{
  "type": "Feature",
  "properties": {
    "iso:country":"BE",
    "sg:address":"Route De Bavay 1",
    "sg:city":"Frameries",
    "sg:classifiers":[
        {
            "category":"Retail",
            "subcategory":"Auto Repair",
            "type":"Services"
        }
    ],
    "sg:phone":"+32 65 67 33 10",
    "sg:postcode":"7080",
    "sg:province":"Hainaut",
    "sg:tags":[
        "breakdown",
        "automobile",
        "-",
        "recovery"
    ],
    "wof:name":"Occabel",
    "wof:placetype":"venue"
},
  "geometry": {"coordinates":[3.9189360142,50.4040336609],"type":"Point"}
}