{
  "type": "Feature",
  "properties": {
    "iso:country":"BE",
    "sg:address":"Rue Saint Bernard 140",
    "sg:city":"Sint-gillis/saint-gilles",
    "sg:orig_category":"Bloemen and planten",
    "sg:phone":"+32 2 537 96 24",
    "sg:postcode":"1060",
    "sg:province":"Bruxelles-Capitale",
    "wof:name":"Debut - Grimaud",
    "wof:placetype":"venue"
},
  "geometry": {"coordinates":[4.3508667946,50.8262939453],"type":"Point"}
}