{
  "type": "Feature",
  "properties": {
    "addr:full":"Rue D'orbais 22 Jodoigne (jauchelette) Brabant Wallon 1370",
    "addr:housenumber":"22",
    "addr:postcode":"1370",
    "addr:street":"Rue D'Orbais;Wallon",
    "iso:country":"BE",
    "sg:address":"Rue D'orbais 22",
    "sg:city":"Jodoigne (jauchelette)",
    "sg:classifiers":[
        {
            "category":"Health Services",
            "subcategory":"Doctor",
            "type":"Services"
        }
    ],
    "sg:phone":"+32 10 86 76 75",
    "sg:postcode":"1370",
    "sg:province":"Brabant Wallon",
    "sg:tags":[
        "psychotherapist",
        "psychoanalyst"
    ],
    "wof:name":"Sobotik A",
    "wof:placetype":"venue"
},
  "geometry": {"coordinates":[4.845705986,50.6907539368],"type":"Point"}
}