{
  "type": "Feature",
  "properties": {
    "addr:full":"Pontweg 18 Aalst Oost-Vlaanderen 9310",
    "addr:housenumber":"18",
    "addr:postcode":"9310",
    "addr:street":"Pontweg",
    "iso:country":"BE",
    "sg:address":"Pontweg 18",
    "sg:city":"Aalst",
    "sg:orig_category":"Sportclubs",
    "sg:phone":"+32 53 70 37 86",
    "sg:postcode":"9310",
    "sg:province":"Oost-Vlaanderen",
    "wof:name":"V.v.v.de Faluintjesstreek",
    "wof:placetype":"venue"
},
  "geometry": {"coordinates":[4.079791069,50.9642066956],"type":"Point"}
}