{
  "type": "Feature",
  "properties": {
    "addr:full":"Bd. L. Schmidt 22 Etterbeek Bruxelles-Capitale 1040",
    "addr:housenumber":"22",
    "addr:postcode":"1040",
    "addr:street":"Bd. L. Schmidt",
    "iso:country":"BE",
    "sg:address":"Bd. L. Schmidt 22",
    "sg:city":"Etterbeek",
    "sg:orig_category":"Reliure and finition",
    "sg:phone":"+32 2 732 40 25",
    "sg:postcode":"1040",
    "sg:province":"Bruxelles-Capitale",
    "wof:name":"Pro Logika",
    "wof:placetype":"venue"
},
  "geometry": {"coordinates":[4.4003491402,50.8281936646],"type":"Point"}
}