{
  "type": "Feature",
  "properties": {
    "iso:country":"BE",
    "sg:address":"Clos Chantraine 4",
    "sg:city":"Pont-\u00e0-celles",
    "sg:classifiers":[
        {
            "category":"Real Estate",
            "subcategory":"Architect",
            "type":"Services"
        }
    ],
    "sg:phone":"+32 71 84 34 13",
    "sg:postcode":"6230",
    "sg:province":"Hainaut",
    "wof:name":"Burny J",
    "wof:placetype":"venue"
},
  "geometry": {"coordinates":[4.3672170639,50.5050468445],"type":"Point"}
}