{
  "type": "Feature",
  "properties": {
    "addr:full":"Velodroomstraat 263 Boom Antwerpen 2850",
    "addr:housenumber":"263",
    "addr:postcode":"2850",
    "addr:street":"Velodroomstraat",
    "iso:country":"BE",
    "sg:address":"Velodroomstraat 263",
    "sg:city":"Boom",
    "sg:classifiers":[
        {
            "category":"Bakery",
            "type":"Food & Drink"
        }
    ],
    "sg:phone":"+32 3 888 14 13",
    "sg:postcode":"2850",
    "sg:province":"Antwerpen",
    "sg:tags":[
        "confectioner",
        "baker"
    ],
    "wof:name":"Roelandts J",
    "wof:placetype":"venue"
},
  "geometry": {"coordinates":[4.3739509583,51.092502594],"type":"Point"}
}