{
  "type": "Feature",
  "properties": {
    "addr:full":"Rue Stephenson 42 Bruxelles Bruxelles-Capitale 1000",
    "addr:housenumber":"42",
    "addr:postcode":"1000",
    "addr:street":"Rue Stephenson",
    "iso:country":"BE",
    "sg:address":"Rue Stephenson 42",
    "sg:city":"Bruxelles",
    "sg:orig_category":"Non-Classified Establishments",
    "sg:phone":"+32 2 245 33 82",
    "sg:postcode":"1000",
    "sg:province":"Bruxelles-Capitale",
    "wof:name":"Atelier Du Tapis",
    "wof:placetype":"venue"
},
  "geometry": {"coordinates":[4.3710298538,50.8713912964],"type":"Point"}
}