{
  "type": "Feature",
  "properties": {
    "addr:full":"Broodstraat 19 Oudenaarde Oost-Vlaanderen 9700",
    "addr:housenumber":"19",
    "addr:postcode":"9700",
    "addr:street":"Broodstraat",
    "iso:country":"BE",
    "sg:address":"Broodstraat 19",
    "sg:city":"Oudenaarde",
    "sg:orig_category":"V\u00eatements pour Dames. V\u00eatements",
    "sg:phone":"+32 55 31 37 45",
    "sg:postcode":"9700",
    "sg:province":"Oost-Vlaanderen",
    "wof:name":"Dorothy's Shop",
    "wof:placetype":"venue"
},
  "geometry": {"coordinates":[3.605850935,50.8428688049],"type":"Point"}
}