{
  "type": "Feature",
  "properties": {
    "iso:country":"BE",
    "sg:address":"Place Foyer P\u00c9ruwelzien 1",
    "sg:city":"P\u00c9ruwelz",
    "sg:orig_category":"Radioproductie and uitzendingen",
    "sg:phone":"+32 69 78 06 36",
    "sg:postcode":"7600",
    "sg:province":"Hainaut",
    "wof:name":"Radio Hebdo",
    "wof:placetype":"venue"
},
  "geometry": {"coordinates":[3.5909481049,50.5110778809],"type":"Point"}
}