{
  "type": "Feature",
  "properties": {
    "iso:country":"BE",
    "sg:address":"Rue G\u00c9n\u00c9ral Patton 25",
    "sg:city":"Elsene/ixelles",
    "sg:orig_category":"Administration d'immeubles. Architectes",
    "sg:phone":"+32 2 640 14 13",
    "sg:postcode":"1050",
    "sg:province":"Bruxelles-Capitale",
    "wof:name":"Luc Reyns",
    "wof:placetype":"venue"
},
  "geometry": {"coordinates":[4.3683719635,50.816822052],"type":"Point"}
}