{
  "type": "Feature",
  "properties": {
    "addr:full":"Molenstraat 14 Zele Oost-Vlaanderen 9240",
    "addr:housenumber":"14",
    "addr:postcode":"9240",
    "addr:street":"Molenstraat",
    "iso:country":"BE",
    "sg:address":"Molenstraat 14",
    "sg:city":"Zele",
    "sg:orig_category":"Charpentes and couvertures",
    "sg:phone":"+32 52 44 66 09",
    "sg:postcode":"9240",
    "sg:province":"Oost-Vlaanderen",
    "wof:name":"De Palmenaer Andre",
    "wof:placetype":"venue"
},
  "geometry": {"coordinates":[3.986219883,51.0670547485],"type":"Point"}
}