{
  "type": "Feature",
  "properties": {
    "addr:full":"Grote Spekstraat 27a Herent (veltem-beisem) Vlaams-Brabant 3020",
    "addr:housenumber":"27a",
    "addr:postcode":"3020",
    "addr:street":"Grote Spekstraat",
    "iso:country":"BE",
    "sg:address":"Grote Spekstraat 27a",
    "sg:city":"Herent (veltem-beisem)",
    "sg:classifiers":[
        {
            "category":"Home & Garden",
            "subcategory":"Carpets & Floor Coverings",
            "type":"Retail Goods"
        }
    ],
    "sg:phone":"+32 16 60 60 05",
    "sg:postcode":"3020",
    "sg:province":"Vlaams-Brabant",
    "sg:tags":[
        "armoring"
    ],
    "wof:name":"Van Campenhout D",
    "wof:placetype":"venue"
},
  "geometry": {"coordinates":[4.6749200821,50.9079055786],"type":"Point"}
}