{
  "type": "Feature",
  "properties": {
    "iso:country":"BE",
    "sg:address":"Grandheid 18",
    "sg:city":"Lierneux",
    "sg:orig_category":"Eleveurs de bovins",
    "sg:phone":"+32 86 43 31 57",
    "sg:postcode":"4990",
    "sg:province":"Li\u00e8ge",
    "wof:name":"Andre Fourgon",
    "wof:placetype":"venue"
},
  "geometry": {"coordinates":[5.7349362373,50.3586807251],"type":"Point"}
}