{
  "type": "Feature",
  "properties": {
    "iso:country":"BE",
    "sg:address":"Boulevard Paul Janson 46",
    "sg:city":"Charleroi",
    "sg:orig_category":"Avocats and conseillers juridiques",
    "sg:phone":"+32 71 31 32 47",
    "sg:postcode":"6000",
    "sg:province":"Hainaut",
    "wof:name":"Bernard Francq",
    "wof:placetype":"venue"
},
  "geometry": {"coordinates":[4.4477591515,50.4141769409],"type":"Point"}
}