{
  "type": "Feature",
  "properties": {
    "iso:country":"BE",
    "sg:address":"Ressegemstraat 41",
    "sg:city":"Herzele (ressegem)",
    "sg:classifiers":[
        {
            "category":"Parking",
            "subcategory":"Lot",
            "type":"Transportation"
        }
    ],
    "sg:phone":"+32 53 62 84 26",
    "sg:postcode":"9551",
    "sg:province":"Oost-Vlaanderen",
    "sg:tags":[
        "parking-places",
        "laying-out"
    ],
    "wof:name":"Vereeken",
    "wof:placetype":"venue"
},
  "geometry": {"coordinates":[3.9049808979,50.8905029297],"type":"Point"}
}