{
  "type": "Feature",
  "properties": {
    "addr:full":"Tweebruggenstraat 19 Lokeren Oost-Vlaanderen 9160",
    "addr:housenumber":"19",
    "addr:postcode":"9160",
    "addr:street":"Tweebruggenstraat",
    "iso:country":"BE",
    "sg:address":"Tweebruggenstraat 19",
    "sg:city":"Lokeren",
    "sg:classifiers":[
        {
            "category":"Food & Beverages",
            "subcategory":"Groceries & Convenience Stores",
            "type":"Retail Goods"
        }
    ],
    "sg:phone":"+32 9 348 45 50",
    "sg:postcode":"9160",
    "sg:province":"Oost-Vlaanderen",
    "sg:tags":[
        "grocer"
    ],
    "wof:name":"Birdy's",
    "wof:placetype":"venue"
},
  "geometry": {"coordinates":[3.9811990261,51.1107711792],"type":"Point"}
}