{
  "type": "Feature",
  "properties": {
    "iso:country":"BE",
    "sg:address":"Meereigen 164",
    "sg:city":"Antwerpen (merksem)",
    "sg:classifiers":[
        {
            "category":"Home & Garden",
            "subcategory":"Carpets & Floor Coverings",
            "type":"Retail Goods"
        }
    ],
    "sg:phone":"+32 3 647 29 65",
    "sg:postcode":"2170",
    "sg:province":"Antwerpen",
    "sg:tags":[
        "layer",
        "mosaicists"
    ],
    "wof:name":"Van Dyck Theo",
    "wof:placetype":"venue"
},
  "geometry": {"coordinates":[4.4505147934,51.246723175],"type":"Point"}
}