{
  "type": "Feature",
  "properties": {
    "addr:full":"Avenue Des H\u00c9ros Leuzois 38 Leuze-en-hainaut Hainaut 7900",
    "addr:housenumber":"38",
    "addr:postcode":"7900",
    "addr:street":"Avenue Des He\u0301Ros Leuzois",
    "iso:country":"BE",
    "sg:address":"Avenue Des H\u00c9ros Leuzois 38",
    "sg:city":"Leuze-en-hainaut",
    "sg:orig_category":"Biblioth\u00e8ques and archives publiques",
    "sg:phone":"+32 69 66 56 75",
    "sg:postcode":"7900",
    "sg:province":"Hainaut",
    "wof:name":"Biblioth\u00c8que Publique",
    "wof:placetype":"venue"
},
  "geometry": {"coordinates":[3.6301460266,50.6001472473],"type":"Point"}
}