{
  "type": "Feature",
  "properties": {
    "iso:country":"BE",
    "sg:address":"Kerkplein 2",
    "sg:city":"Deerlijk",
    "sg:orig_category":"Banken and kredietinstellingen",
    "sg:phone":"+32 56 71 68 28",
    "sg:postcode":"8540",
    "sg:province":"West-Vlaanderen",
    "wof:name":"Fortis",
    "wof:placetype":"venue"
},
  "geometry": {"coordinates":[3.3547689915,50.8532676697],"type":"Point"}
}