{
  "type": "Feature",
  "properties": {
    "addr:full":"Markt 85 Berlaar Antwerpen 2590",
    "addr:housenumber":"85",
    "addr:postcode":"2590",
    "addr:street":"Markt",
    "iso:country":"BE",
    "sg:address":"Markt 85",
    "sg:city":"Berlaar",
    "sg:orig_category":"Notaires",
    "sg:phone":"+32 3 482 10 40",
    "sg:postcode":"2590",
    "sg:province":"Antwerpen",
    "wof:name":"B. Cuvelier",
    "wof:placetype":"venue"
},
  "geometry": {"coordinates":[4.6576151848,51.1174621582],"type":"Point"}
}