{
  "type": "Feature",
  "properties": {
    "iso:country":"BE",
    "sg:address":"De Cockplein 15",
    "sg:city":"Diegem",
    "sg:classifiers":[
        {
            "category":"Banks & Credit Unions",
            "subcategory":"Bank",
            "type":"Services"
        }
    ],
    "sg:phone":"+32 2 720 00 11",
    "sg:postcode":"1920",
    "wof:name":"Aslk-cger Bank",
    "wof:placetype":"venue"
},
  "geometry": {"coordinates":[4.4359498024,50.8944702148],"type":"Point"}
}