{
  "type": "Feature",
  "properties": {
    "iso:country":"BE",
    "sg:address":"Dorpsstraat 39",
    "sg:city":"Halen",
    "sg:orig_category":"Enseignement maternel and primaire",
    "sg:phone":"+32 13 44 33 63",
    "sg:postcode":"3545",
    "sg:province":"Limburg",
    "wof:name":"Gemeentel. Kleuterschool",
    "wof:placetype":"venue"
},
  "geometry": {"coordinates":[5.1039638519,50.9790763855],"type":"Point"}
}