{
  "type": "Feature",
  "properties": {
    "addr:full":"Rue Du Pont De Pierres 41ba Court-saint-etienne Brabant Wallon 1490",
    "addr:housenumber":"41ba;1490",
    "addr:street":"Rue Du Pont De Pierres",
    "iso:country":"BE",
    "sg:address":"Rue Du Pont De Pierres 41ba",
    "sg:city":"Court-saint-etienne",
    "sg:orig_category":"Woningbouw",
    "sg:phone":"+32 10 61 23 91",
    "sg:postcode":"1490",
    "sg:province":"Brabant Wallon",
    "wof:name":"Michael Rouet",
    "wof:placetype":"venue"
},
  "geometry": {"coordinates":[4.5511841774,50.639541626],"type":"Point"}
}