{
  "type": "Feature",
  "properties": {
    "iso:country":"BE",
    "sg:address":"Rue De Mettet 69",
    "sg:city":"Florennes",
    "sg:classifiers":[
        {
            "category":"Fast Food",
            "type":"Food & Drink"
        }
    ],
    "sg:phone":"+32 71 68 98 88",
    "sg:postcode":"5620",
    "sg:province":"Namur",
    "sg:tags":[
        "\u00c0",
        "restaurants",
        "emporter",
        "restaurant"
    ],
    "wof:name":"New China",
    "wof:placetype":"venue"
},
  "geometry": {"coordinates":[4.6069788933,50.2544746399],"type":"Point"}
}