{
  "type": "Feature",
  "properties": {
    "addr:full":"Kapellestraat 43 Zulte Oost-Vlaanderen 9870",
    "addr:housenumber":"43",
    "addr:postcode":"9870",
    "addr:street":"Kapellestraat",
    "iso:country":"BE",
    "sg:address":"Kapellestraat 43",
    "sg:city":"Zulte",
    "sg:orig_category":"Woningbouw",
    "sg:phone":"+32 9 388 70 81",
    "sg:postcode":"9870",
    "sg:province":"Oost-Vlaanderen",
    "wof:name":"Fa. Snoeck Gebrs",
    "wof:placetype":"venue"
},
  "geometry": {"coordinates":[3.4497020245,50.9157142639],"type":"Point"}
}