{
  "type": "Feature",
  "properties": {
    "iso:country":"BE",
    "sg:address":"Burggravenlaan 63",
    "sg:city":"Evergem",
    "sg:classifiers":[
        {
            "category":"Arts & Performance",
            "subcategory":"Symphony",
            "type":"Entertainment"
        }
    ],
    "sg:phone":"+32 9 253 78 46",
    "sg:postcode":"9940",
    "sg:province":"Oost-Vlaanderen",
    "sg:tags":[
        "orchestra"
    ],
    "wof:name":"Roland De Ridder",
    "wof:placetype":"venue"
},
  "geometry": {"coordinates":[3.7373430729,51.1220588684],"type":"Point"}
}