{
  "type": "Feature",
  "properties": {
    "iso:country":"BE",
    "sg:address":"Guido Gezellestraat 59a",
    "sg:city":"Wielsbeke",
    "sg:orig_category":"Plomberie, chauffage and installations sanitaires",
    "sg:phone":"+32 56 66 85 04",
    "sg:postcode":"8710",
    "sg:province":"West-Vlaanderen",
    "wof:name":"Geert Bouckaert",
    "wof:placetype":"venue"
},
  "geometry": {"coordinates":[3.3314220905,50.8997344971],"type":"Point"}
}