{
  "type": "Feature",
  "properties": {
    "iso:country":"BE",
    "sg:address":"Klinkeshofchen 5",
    "sg:city":"Eupen",
    "sg:classifiers":[
        {
            "category":"Arena",
            "subcategory":"Sports Club",
            "type":"Entertainment"
        }
    ],
    "sg:phone":"+32 87 74 44 22",
    "sg:postcode":"4700",
    "sg:province":"Li\u00e8ge",
    "sg:tags":[
        "de"
    ],
    "wof:name":"Centre Militaire Belge",
    "wof:placetype":"venue"
},
  "geometry": {"coordinates":[6.0271391869,50.6309318542],"type":"Point"}
}