{
  "type": "Feature",
  "properties": {
    "addr:full":"Turnhoutsebaan 131 Mol Antwerpen 2400",
    "addr:housenumber":"131",
    "addr:postcode":"2400",
    "addr:street":"Turnhoutsebaan",
    "iso:country":"BE",
    "sg:address":"Turnhoutsebaan 131",
    "sg:city":"Mol",
    "sg:orig_category":"Benzinestations and brandstoffen",
    "sg:phone":"+32 14 31 62 07",
    "sg:postcode":"2400",
    "sg:province":"Antwerpen",
    "wof:name":"Shell",
    "wof:placetype":"venue"
},
  "geometry": {"coordinates":[5.1151947975,51.205696106],"type":"Point"}
}