{
  "type": "Feature",
  "properties": {
    "iso:country":"BE",
    "sg:address":"Brielken 27",
    "sg:city":"Evergem",
    "sg:orig_category":"HUISBRANDOLIE",
    "sg:phone":"+32 9 253 81 91",
    "sg:postcode":"9940",
    "sg:province":"Oost-Vlaanderen",
    "wof:name":"Vermeire Albert & August",
    "wof:placetype":"venue"
},
  "geometry": {"coordinates":[3.7007699013,51.1109962463],"type":"Point"}
}