{
  "type": "Feature",
  "properties": {
    "addr:full":"Jesserenstraat 114 Borgloon Limburg 3840",
    "addr:housenumber":"114",
    "addr:postcode":"3840",
    "addr:street":"Jesserenstraat",
    "iso:country":"BE",
    "sg:address":"Jesserenstraat 114",
    "sg:city":"Borgloon",
    "sg:orig_category":"Fruitteelt",
    "sg:phone":"+32 12 74 22 61",
    "sg:postcode":"3840",
    "sg:province":"Limburg",
    "wof:name":"Emile Cuvelier",
    "wof:placetype":"venue"
},
  "geometry": {"coordinates":[5.3441700935,50.8012466431],"type":"Point"}
}