{
  "type": "Feature",
  "properties": {
    "addr:full":"Kursaalstraat 38 Knokke-heist (heist-aan-zee) West-Vlaanderen 8301",
    "addr:housenumber":"38",
    "addr:postcode":"8301",
    "addr:street":"Kursaalstraat",
    "iso:country":"BE",
    "sg:address":"Kursaalstraat 38",
    "sg:city":"Knokke-heist (heist-aan-zee)",
    "sg:classifiers":[
        {
            "category":"Banks & Credit Unions",
            "subcategory":"Investment Brokerage",
            "type":"Services"
        }
    ],
    "sg:phone":"+32 50 51 45 27",
    "sg:postcode":"8301",
    "sg:province":"West-Vlaanderen",
    "sg:tags":[
        "jean",
        "casual",
        "wear"
    ],
    "wof:name":"Blouson",
    "wof:placetype":"venue"
},
  "geometry": {"coordinates":[3.2639000416,51.3396911621],"type":"Point"}
}