{
  "type": "Feature",
  "properties": {
    "addr:full":"Rue Des Ti\u00c8nnes 8 Beauraing Namur 5570",
    "addr:housenumber":"8",
    "addr:postcode":"5570",
    "addr:street":"Rue Des Tie\u0300Nnes",
    "iso:country":"BE",
    "sg:address":"Rue Des Ti\u00c8nnes 8",
    "sg:city":"Beauraing",
    "sg:orig_category":"Fitnesscentra",
    "sg:phone":"+32 82 71 24 59",
    "sg:postcode":"5570",
    "sg:province":"Namur",
    "wof:name":"Fitness Centre Belot",
    "wof:placetype":"venue"
},
  "geometry": {"coordinates":[4.9281110764,50.0926513672],"type":"Point"}
}