{
  "type": "Feature",
  "properties": {
    "addr:full":"Stevinstraat 50 Brussel/bruxelles Bruxelles-Capitale 1000",
    "addr:housenumber":"50",
    "addr:postcode":"1000",
    "addr:street":"Stevinstraat;/",
    "iso:country":"BE",
    "sg:address":"Stevinstraat 50",
    "sg:city":"Brussel/bruxelles",
    "sg:orig_category":"Apotheken",
    "sg:phone":"+32 2 230 41 82",
    "sg:postcode":"1000",
    "sg:province":"Bruxelles-Capitale",
    "wof:name":"Esco-farma",
    "wof:placetype":"venue"
},
  "geometry": {"coordinates":[4.3774271011,50.8456306458],"type":"Point"}
}