{
  "type": "Feature",
  "properties": {
    "iso:country":"BE",
    "sg:address":"Maria-christinastraat 150",
    "sg:city":"Brussel/bruxelles",
    "sg:orig_category":"Kapsalons",
    "sg:phone":"+32 2 427 14 62",
    "sg:postcode":"1020",
    "sg:province":"Bruxelles-Capitale",
    "wof:name":"Coiffure Alberto",
    "wof:placetype":"venue"
},
  "geometry": {"coordinates":[4.352367878,50.8757781982],"type":"Point"}
}