{
  "type": "Feature",
  "properties": {
    "addr:full":"Avenue De La D\u00e9livrance 123 Mouscron (dottignies) Hainaut 7711",
    "addr:housenumber":"123",
    "addr:postcode":"7711",
    "addr:street":"Avenue De La De\u0301Livrance",
    "iso:country":"BE",
    "sg:address":"Avenue De La D\u00e9livrance 123",
    "sg:city":"Mouscron (dottignies)",
    "sg:classifiers":[
        {
            "category":"Professional",
            "subcategory":"Accounting & Tax Preparation",
            "type":"Services"
        }
    ],
    "sg:phone":"+32 56 48 75 58",
    "sg:postcode":"7711",
    "sg:province":"Hainaut",
    "sg:tags":[
        "accountant"
    ],
    "wof:name":"Naessens F",
    "wof:placetype":"venue"
},
  "geometry": {"coordinates":[3.3008089066,50.718788147],"type":"Point"}
}