{
  "type": "Feature",
  "properties": {
    "iso:country":"BE",
    "sg:address":"Schoebroekstraat 40",
    "sg:city":"Beringen",
    "sg:classifiers":[
        {
            "category":"Building & Trades",
            "subcategory":"Construction",
            "type":"Services"
        }
    ],
    "sg:phone":"+32 11 45 09 50",
    "sg:postcode":"3583",
    "sg:province":"Limburg",
    "sg:tags":[
        "la",
        "de",
        "\u00e9quipement",
        "pour",
        "machine",
        "location"
    ],
    "wof:name":"Arcomet Verhuur",
    "wof:placetype":"venue"
},
  "geometry": {"coordinates":[5.1706700325,51.0389442444],"type":"Point"}
}