{
  "type": "Feature",
  "properties": {
    "addr:full":"Kleinstraat 35 Rotselaar Vlaams-Brabant 3118",
    "addr:housenumber":"35",
    "addr:postcode":"3118",
    "addr:street":"Kleinstraat",
    "iso:country":"BE",
    "sg:address":"Kleinstraat 35",
    "sg:city":"Rotselaar",
    "sg:classifiers":[
        {
            "category":"Insurance",
            "subcategory":"Insurance Agent",
            "type":"Services"
        }
    ],
    "sg:phone":"+32 16 53 35 14",
    "sg:postcode":"3118",
    "sg:province":"Vlaams-Brabant",
    "sg:tags":[
        "verzekeringsmakelaars",
        "expert"
    ],
    "wof:name":"Interpres",
    "wof:placetype":"venue"
},
  "geometry": {"coordinates":[4.7122101784,50.9756393433],"type":"Point"}
}