{
  "type": "Feature",
  "properties": {
    "addr:full":"Route D'ath 7 Jurbise Hainaut 7050",
    "addr:housenumber":"7",
    "addr:postcode":"7050",
    "addr:street":"Route D'Ath",
    "iso:country":"BE",
    "sg:address":"Route D'ath 7",
    "sg:city":"Jurbise",
    "sg:orig_category":"M\u00e9decins and sp\u00e9cialistes",
    "sg:phone":"+32 65 22 93 03",
    "sg:postcode":"7050",
    "sg:province":"Hainaut",
    "wof:name":"Arielle Nuyts",
    "wof:placetype":"venue"
},
  "geometry": {"coordinates":[3.9327330589,50.5013885498],"type":"Point"}
}