{
  "type": "Feature",
  "properties": {
    "iso:country":"BE",
    "sg:address":"Rue Grand Aaz 36",
    "sg:city":"Oupeye",
    "sg:orig_category":"Fruitteelt",
    "sg:phone":"+32 4 278 52 42",
    "sg:postcode":"4680",
    "sg:province":"Li\u00e8ge",
    "wof:name":"Loly Henri Et Philippe",
    "wof:placetype":"venue"
},
  "geometry": {"coordinates":[5.6106500626,50.7157287598],"type":"Point"}
}