{
  "type": "Feature",
  "properties": {
    "iso:country":"BE",
    "sg:address":"Kerkstraat 3",
    "sg:city":"Gavere",
    "sg:classifiers":[
        {
            "category":"Personal",
            "subcategory":"Beauty Salon",
            "type":"Services"
        }
    ],
    "sg:phone":"+32 9 384 11 98",
    "sg:postcode":"9890",
    "sg:province":"Oost-Vlaanderen",
    "sg:tags":[
        "de",
        "coiffure"
    ],
    "wof:name":"R. Van Lancker",
    "wof:placetype":"venue"
},
  "geometry": {"coordinates":[3.6906321049,50.9179573059],"type":"Point"}
}