{
  "type": "Feature",
  "properties": {
    "addr:full":"Rue Lesbroussart 51 Elsene/ixelles Bruxelles-Capitale 1050",
    "addr:housenumber":"51",
    "addr:postcode":"1050",
    "addr:street":"Rue Lesbroussart",
    "iso:country":"BE",
    "sg:address":"Rue Lesbroussart 51",
    "sg:city":"Elsene/ixelles",
    "sg:orig_category":"M\u00e9decins and sp\u00e9cialistes",
    "sg:phone":"+32 2 640 48 41",
    "sg:postcode":"1050",
    "sg:province":"Bruxelles-Capitale",
    "wof:name":"Jacqueline Coulon",
    "wof:placetype":"venue"
},
  "geometry": {"coordinates":[4.3683972359,50.8278198242],"type":"Point"}
}