{
  "type": "Feature",
  "properties": {
    "addr:full":"Baron De Caterslaan 21 Zoersel Antwerpen 2980",
    "addr:housenumber":"21",
    "addr:postcode":"2980",
    "addr:street":"Baron De Caterslaan",
    "iso:country":"BE",
    "sg:address":"Baron De Caterslaan 21",
    "sg:city":"Zoersel",
    "sg:classifiers":[
        {
            "category":"Fast Food",
            "type":"Food & Drink"
        }
    ],
    "sg:phone":"+32 3 386 61 32",
    "sg:postcode":"2980",
    "sg:province":"Antwerpen",
    "sg:tags":[
        "\u00c0",
        "emporter",
        "restaurants"
    ],
    "wof:name":"Daelemans Bob",
    "wof:placetype":"venue"
},
  "geometry": {"coordinates":[4.6377301216,51.2607002258],"type":"Point"}
}