{
  "type": "Feature",
  "properties": {
    "iso:country":"BE",
    "sg:address":"Doornzele Dries 46ba",
    "sg:city":"Evergem",
    "sg:orig_category":"Apotheken",
    "sg:phone":"+32 9 253 70 33",
    "sg:postcode":"9940",
    "sg:province":"Oost-Vlaanderen",
    "wof:name":"Apotheek Oushoorn",
    "wof:placetype":"venue"
},
  "geometry": {"coordinates":[3.763808012,51.141368866],"type":"Point"}
}