{
  "type": "Feature",
  "properties": {
    "addr:full":"Rue De Magn\u00e9e 110 Beyne-heusay Li\u00e8ge 4610",
    "addr:housenumber":"110",
    "addr:postcode":"4610",
    "addr:street":"Rue De Magne\u0301E",
    "iso:country":"BE",
    "sg:address":"Rue De Magn\u00e9e 110",
    "sg:city":"Beyne-heusay",
    "sg:classifiers":[
        {
            "category":"Manufacturing",
            "subcategory":"Tools & Machinery",
            "type":"Manufacturing & Wholesale Goods"
        }
    ],
    "sg:phone":"+32 4 355 81 81",
    "sg:postcode":"4610",
    "sg:province":"Li\u00e8ge",
    "sg:tags":[
        "equipment",
        "measurement",
        "-",
        "precision",
        "instrument"
    ],
    "wof:name":"Aquacom Nv",
    "wof:placetype":"venue"
},
  "geometry": {"coordinates":[5.6692547798,50.6152114868],"type":"Point"}
}