{
  "type": "Feature",
  "properties": {
    "iso:country":"BE",
    "sg:address":"Rue De Verdun 80",
    "sg:city":"Brussel/bruxelles",
    "sg:orig_category":"Articles de sport, camping and jouets Gr",
    "sg:phone":"+32 2 216 39 36",
    "sg:postcode":"1130",
    "sg:province":"Bruxelles-Capitale",
    "wof:name":"Marcel Delit",
    "wof:placetype":"venue"
},
  "geometry": {"coordinates":[4.4083919525,50.8839263916],"type":"Point"}
}