{
  "type": "Feature",
  "properties": {
    "addr:full":"Antoine Dansaertstraat 16 Brussel Bruxelles-Capitale 1000",
    "addr:housenumber":"16",
    "addr:postcode":"1000",
    "addr:street":"Antoine Dansaertstraat",
    "iso:country":"BE",
    "sg:address":"Antoine Dansaertstraat 16",
    "sg:city":"Brussel",
    "sg:orig_category":"Brood, gebak and snoepgoed Restaurants",
    "sg:phone":"+32 2 502 23 61",
    "sg:postcode":"1000",
    "sg:province":"Bruxelles-Capitale",
    "wof:name":"Le Pain Quotidien",
    "wof:placetype":"venue"
},
  "geometry": {"coordinates":[4.3473858833,50.8491477966],"type":"Point"}
}