{
  "type": "Feature",
  "properties": {
    "iso:country":"BE",
    "sg:address":"Steenweg 16",
    "sg:city":"Mechelen",
    "sg:orig_category":"Schoenen",
    "sg:phone":"+32 15 20 31 30",
    "sg:postcode":"2800",
    "sg:province":"Antwerpen",
    "wof:name":"Junior Guma Styles",
    "wof:placetype":"venue"
},
  "geometry": {"coordinates":[4.4786448479,51.0282478333],"type":"Point"}
}