{
  "type": "Feature",
  "properties": {
    "iso:country":"BE",
    "sg:address":"Rue De Villers 33",
    "sg:city":"Wanze",
    "sg:orig_category":"Dakwerken Diverse bouwafwerking and reiniging Gespecialiseerde residenti\u00eble bouw Isolatiewerk Schild",
    "sg:phone":"+32 85 23 54 53",
    "sg:postcode":"4520",
    "sg:province":"Li\u00e8ge",
    "wof:name":"B.f.c.",
    "wof:placetype":"venue"
},
  "geometry": {"coordinates":[5.2139430046,50.5367546082],"type":"Point"}
}