{
  "type": "Feature",
  "properties": {
    "iso:country":"BE",
    "sg:address":"Rue De Verviers 10",
    "sg:city":"Herve",
    "sg:orig_category":"Banques and organismes de cr\u00e9dit",
    "sg:phone":"+32 87 67 80 93",
    "sg:postcode":"4651",
    "sg:province":"Li\u00e8ge",
    "wof:name":"Fortis",
    "wof:placetype":"venue"
},
  "geometry": {"coordinates":[5.8225131035,50.6474494934],"type":"Point"}
}