{
  "type": "Feature",
  "properties": {
    "addr:full":"Rue Henry Dandoy 63 Namur Namur 5020",
    "addr:housenumber":"63",
    "addr:postcode":"5020",
    "addr:street":"Rue Henry Dandoy",
    "iso:country":"BE",
    "sg:address":"Rue Henry Dandoy 63",
    "sg:city":"Namur",
    "sg:orig_category":"Traitements param\u00e9dicaux",
    "sg:phone":"+32 81 74 06 25",
    "sg:postcode":"5020",
    "sg:province":"Namur",
    "wof:name":"P. Mathieu",
    "wof:placetype":"venue"
},
  "geometry": {"coordinates":[4.7952418327,50.4352035522],"type":"Point"}
}