{
  "type": "Feature",
  "properties": {
    "iso:country":"BE",
    "sg:address":"Gasmeterlaan 194",
    "sg:city":"Gent",
    "sg:classifiers":[
        {
            "category":"Real Estate",
            "subcategory":"Architect",
            "type":"Services"
        }
    ],
    "sg:phone":"+32 9 329 71 99",
    "sg:postcode":"9000",
    "sg:province":"Oost-Vlaanderen",
    "wof:name":"Ch\u00e2tel G",
    "wof:placetype":"venue"
},
  "geometry": {"coordinates":[3.7234349251,51.0673561096],"type":"Point"}
}