{
  "type": "Feature",
  "properties": {
    "iso:country":"BE",
    "sg:address":"Rue Joseph Stiernon 20",
    "sg:city":"Binche (p\u00e9ronnes-lez-binche)",
    "sg:classifiers":[
        {
            "category":"Utilities",
            "subcategory":"Refuse",
            "type":"Services"
        }
    ],
    "sg:phone":"+32 64 34 23 54",
    "sg:postcode":"7134",
    "sg:province":"Hainaut",
    "sg:tags":[
        "management",
        "waste"
    ],
    "wof:name":"Transmosca Sa",
    "wof:placetype":"venue"
},
  "geometry": {"coordinates":[4.2065992355,50.4313354492],"type":"Point"}
}