{
  "type": "Feature",
  "properties": {
    "addr:full":"Rue Major-mouzon 69 Libin Luxembourg 6890",
    "addr:housenumber":"69",
    "addr:postcode":"6890",
    "addr:street":"Rue Major-Mouzon",
    "iso:country":"BE",
    "sg:address":"Rue Major-mouzon 69",
    "sg:city":"Libin",
    "sg:orig_category":"Artsen and specialisten",
    "sg:phone":"+32 61 22 47 44",
    "sg:postcode":"6890",
    "sg:province":"Luxembourg",
    "wof:name":"G. Pirson",
    "wof:placetype":"venue"
},
  "geometry": {"coordinates":[5.2768750191,49.9249076843],"type":"Point"}
}