{
  "type": "Feature",
  "properties": {
    "iso:country":"BE",
    "sg:address":"Val Villers 62",
    "sg:city":"Chaumont-gistoux (corroy-le-grand)",
    "sg:classifiers":[
        {
            "category":"Education",
            "subcategory":"Dance Studio",
            "type":"Public Place"
        }
    ],
    "sg:phone":"+32 10 24 19 96",
    "sg:postcode":"1325",
    "sg:province":"Brabant Wallon",
    "sg:tags":[
        "school",
        "dancing"
    ],
    "wof:name":"Incidanse Asbl - Wavre",
    "wof:placetype":"venue"
},
  "geometry": {"coordinates":[4.6335921288,50.6859893799],"type":"Point"}
}