{
  "type": "Feature",
  "properties": {
    "iso:country":"BE",
    "sg:address":"Sparrenlaan 20",
    "sg:city":"Schoten",
    "sg:orig_category":"Artistes ind\u00e9pendants",
    "sg:phone":"+32 3 658 46 81",
    "sg:postcode":"2900",
    "sg:province":"Antwerpen",
    "wof:name":"Bellemans",
    "wof:placetype":"venue"
},
  "geometry": {"coordinates":[4.5167021751,51.2623138428],"type":"Point"}
}