{
  "type": "Feature",
  "properties": {
    "addr:full":"Rue Gatti De Gamond 251 Ukkel Bruxelles-Capitale 1180",
    "addr:housenumber":"251",
    "addr:postcode":"1180",
    "addr:street":"Rue Gatti De Gamond",
    "iso:country":"BE",
    "sg:address":"Rue Gatti De Gamond 251",
    "sg:city":"Ukkel",
    "sg:orig_category":"Medische and orthopedische apparaten",
    "sg:phone":"+32 2 376 16 88",
    "sg:postcode":"1180",
    "sg:province":"Bruxelles-Capitale",
    "wof:name":"Salman S.",
    "wof:placetype":"venue"
},
  "geometry": {"coordinates":[4.3273038864,50.7988548279],"type":"Point"}
}