{
  "type": "Feature",
  "properties": {
    "iso:country":"BE",
    "sg:address":"Rue Du H\u00c9rou 56",
    "sg:city":"Houffalize",
    "sg:orig_category":"Entretien and r\u00e9parations de voitures",
    "sg:phone":"+32 84 44 45 30",
    "sg:postcode":"6660",
    "sg:province":"Luxembourg",
    "wof:name":"Marc Octave",
    "wof:placetype":"venue"
},
  "geometry": {"coordinates":[5.6683402061,50.1563606262],"type":"Point"}
}