{
  "type": "Feature",
  "properties": {
    "addr:full":"Chauss\u00c9e De Namur 32 Incourt Brabant Wallon 1315",
    "addr:housenumber":"32",
    "addr:postcode":"1315",
    "addr:street":"Chausse\u0301E De Namur",
    "iso:country":"BE",
    "sg:address":"Chauss\u00c9e De Namur 32",
    "sg:city":"Incourt",
    "sg:classifiers":[
        {
            "category":"Autos & Motor Vehicles",
            "subcategory":"Fuel & Gas Station",
            "type":"Retail Goods"
        }
    ],
    "sg:phone":"+32 10 84 28 78",
    "sg:postcode":"1315",
    "sg:province":"Brabant Wallon",
    "sg:tags":[
        "stations-service",
        "carburants"
    ],
    "wof:name":"Autoroyal",
    "wof:placetype":"venue"
},
  "geometry": {"coordinates":[4.8042221069,50.6948051453],"type":"Point"}
}