{
  "type": "Feature",
  "properties": {
    "iso:country":"BE",
    "sg:address":"Avenue D'alost 23",
    "sg:city":"Rochefort",
    "sg:orig_category":"Woningbouw",
    "sg:phone":"+32 84 21 17 75",
    "sg:postcode":"5580",
    "sg:province":"Namur",
    "wof:name":"Stephane Troquet",
    "wof:placetype":"venue"
},
  "geometry": {"coordinates":[5.2198910713,50.1593208313],"type":"Point"}
}