{
  "type": "Feature",
  "properties": {
    "iso:country":"BE",
    "sg:address":"Zandrietpad 2",
    "sg:city":"Brugge",
    "sg:classifiers":[
        {
            "category":"Fast Food",
            "type":"Food & Drink"
        }
    ],
    "sg:phone":"+32 50 54 57 19",
    "sg:postcode":"8380",
    "sg:province":"West-Vlaanderen",
    "sg:tags":[
        "\u00c0",
        "emporter",
        "restaurants"
    ],
    "wof:name":"Frituur Fran\u00c7oise",
    "wof:placetype":"venue"
},
  "geometry": {"coordinates":[3.2288448811,51.2742958069],"type":"Point"}
}