{
  "type": "Feature",
  "properties": {
    "addr:full":"Canadezenlaan 15 Maldegem Oost-Vlaanderen 9991",
    "addr:housenumber":"15",
    "addr:postcode":"9991",
    "addr:street":"Canadezenlaan",
    "iso:country":"BE",
    "sg:address":"Canadezenlaan 15",
    "sg:city":"Maldegem",
    "sg:orig_category":"V\u00eatements sur mesure Fab",
    "sg:phone":"+32 50 71 28 26",
    "sg:postcode":"9991",
    "sg:province":"Oost-Vlaanderen",
    "wof:name":"C Van De Walle",
    "wof:placetype":"venue"
},
  "geometry": {"coordinates":[3.4864239693,51.2059364319],"type":"Point"}
}