{
  "type": "Feature",
  "properties": {
    "addr:full":"Slameuterstraat 1b Putte Antwerpen 2580",
    "addr:housenumber":"1b",
    "addr:postcode":"2580",
    "addr:street":"Slameuterstraat",
    "iso:country":"BE",
    "sg:address":"Slameuterstraat 1b",
    "sg:city":"Putte",
    "sg:classifiers":[
        {
            "category":"Home & Garden",
            "subcategory":"Carpets & Floor Coverings",
            "type":"Retail Goods"
        }
    ],
    "sg:phone":"+32 15 25 38 10",
    "sg:postcode":"2580",
    "sg:province":"Antwerpen",
    "sg:tags":[
        "industrial",
        "-"
    ],
    "wof:name":"Stac Industrial Coatings",
    "wof:placetype":"venue"
},
  "geometry": {"coordinates":[4.5859379768,51.0414886475],"type":"Point"}
}