{
  "type": "Feature",
  "properties": {
    "iso:country":"BE",
    "sg:address":"Sint-maartenstraat 25",
    "sg:city":"Leuven",
    "sg:classifiers":[
        {
            "category":"Retail",
            "subcategory":"Laundry & Dry Cleaning",
            "type":"Services"
        }
    ],
    "sg:phone":"+32 16 22 13 31",
    "sg:postcode":"3000",
    "sg:province":"Vlaams-Brabant",
    "sg:tags":[
        "dyer",
        "cleaner"
    ],
    "wof:name":"Euro-shop",
    "wof:placetype":"venue"
},
  "geometry": {"coordinates":[4.7050919533,50.8816604614],"type":"Point"}
}