{
  "type": "Feature",
  "properties": {
    "iso:country":"BE",
    "sg:address":"Rue De La Barre 42",
    "sg:city":"Chaumont-gistoux",
    "sg:classifiers":[
        {
            "category":"Professional",
            "subcategory":"Management & Consulting",
            "type":"Services"
        }
    ],
    "sg:phone":"+32 10 84 66 03",
    "sg:postcode":"1325",
    "sg:province":"Brabant Wallon",
    "sg:tags":[
        "-",
        "processing",
        "data",
        "consultant"
    ],
    "wof:name":"Agrion",
    "wof:placetype":"venue"
},
  "geometry": {"coordinates":[4.7223548889,50.6729545593],"type":"Point"}
}