{
  "type": "Feature",
  "properties": {
    "iso:country":"BE",
    "sg:address":"Rue De L'orient 23b82",
    "sg:city":"Tournai",
    "sg:orig_category":"Produits surgel\u00e9s Gr",
    "sg:phone":"+32 69 22 66 02",
    "sg:postcode":"7500",
    "sg:province":"Hainaut",
    "wof:name":"Detournay Cyr & Fils",
    "wof:placetype":"venue"
},
  "geometry": {"coordinates":[3.414550066,50.6028327942],"type":"Point"}
}