{
  "type": "Feature",
  "properties": {
    "addr:full":"Alexander Franckstraat 28 Boechout Antwerpen 2530",
    "addr:housenumber":"28",
    "addr:postcode":"2530",
    "addr:street":"Alexander Franckstraat",
    "iso:country":"BE",
    "sg:address":"Alexander Franckstraat 28",
    "sg:city":"Boechout",
    "sg:orig_category":"Fotografen and fotostudio's",
    "sg:phone":"+32 3 454 30 74",
    "sg:postcode":"2530",
    "sg:province":"Antwerpen",
    "wof:name":"Studio 44",
    "wof:placetype":"venue"
},
  "geometry": {"coordinates":[4.4951992035,51.1591529846],"type":"Point"}
}