{
  "type": "Feature",
  "properties": {
    "addr:full":"Schrieksebaan 83 Keerbergen Vlaams-Brabant 3140",
    "addr:housenumber":"83",
    "addr:postcode":"3140",
    "addr:street":"Schrieksebaan",
    "iso:country":"BE",
    "sg:address":"Schrieksebaan 83",
    "sg:city":"Keerbergen",
    "sg:orig_category":"Woningbouw",
    "sg:phone":"+32 15 73 09 66",
    "sg:postcode":"3140",
    "sg:province":"Vlaams-Brabant",
    "wof:name":"Wima",
    "wof:placetype":"venue"
},
  "geometry": {"coordinates":[4.6604881287,51.0108451843],"type":"Point"}
}