{
  "type": "Feature",
  "properties": {
    "addr:full":"Meensestraat 84-86 Kortrijk West-Vlaanderen 8500",
    "addr:postcode":"84-86;8500",
    "addr:street":"Meensestraat",
    "iso:country":"BE",
    "sg:address":"Meensestraat 84-86",
    "sg:city":"Kortrijk",
    "sg:classifiers":[
        {
            "category":"Bars & Pubs",
            "type":"Food & Drink"
        }
    ],
    "sg:phone":"+32 56 37 49 50",
    "sg:postcode":"8500",
    "sg:province":"West-Vlaanderen",
    "wof:name":"Menenpoort (de)",
    "wof:placetype":"venue"
},
  "geometry": {"coordinates":[3.2561600208,50.8327484131],"type":"Point"}
}