{
  "type": "Feature",
  "properties": {
    "addr:full":"Rue De Namur 62 Wavre Brabant Wallon 1300",
    "addr:housenumber":"62;1300",
    "addr:street":"Rue De Namur",
    "iso:country":"BE",
    "sg:address":"Rue De Namur 62",
    "sg:city":"Wavre",
    "sg:orig_category":"Artsen and specialisten",
    "sg:phone":"+32 10 22 75 89",
    "sg:postcode":"1300",
    "sg:province":"Brabant Wallon",
    "wof:name":"G\u00c9rard Lothier",
    "wof:placetype":"venue"
},
  "geometry": {"coordinates":[4.6129112244,50.7121505737],"type":"Point"}
}