{
  "type": "Feature",
  "properties": {
    "iso:country":"BE",
    "sg:address":"Heuvel 23",
    "sg:city":"Kalmthout",
    "sg:classifiers":[
        {
            "category":"Bakery",
            "type":"Food & Drink"
        }
    ],
    "sg:phone":"+32 3 666 41 88",
    "sg:postcode":"2920",
    "sg:province":"Antwerpen",
    "sg:tags":[
        "confectioner",
        "baker"
    ],
    "wof:name":"Neys T",
    "wof:placetype":"venue"
},
  "geometry": {"coordinates":[4.463778019,51.3900222778],"type":"Point"}
}