{
  "type": "Feature",
  "properties": {
    "iso:country":"BE",
    "sg:address":"Boulevard Raymond Poincar\u00e9 75",
    "sg:city":"Li\u00e8ge 1 (li\u00e8ge 2)",
    "sg:classifiers":[
        {
            "category":"Home & Garden",
            "subcategory":"Building Materials",
            "type":"Retail Goods"
        }
    ],
    "sg:phone":"+32 4 343 48 76",
    "sg:postcode":"4020",
    "sg:province":"Li\u00e8ge",
    "sg:tags":[
        "stone",
        "artificial"
    ],
    "wof:name":"Bernardin Ets Sa",
    "wof:placetype":"venue"
},
  "geometry": {"coordinates":[5.5829081535,50.6297912598],"type":"Point"}
}