{
  "type": "Feature",
  "properties": {
    "addr:full":"Albert Servaeslaan 40 Rumst (reet) Antwerpen 2840",
    "addr:housenumber":"40",
    "addr:postcode":"2840",
    "addr:street":"Albert Servaeslaan",
    "iso:country":"BE",
    "sg:address":"Albert Servaeslaan 40",
    "sg:city":"Rumst (reet)",
    "sg:classifiers":[
        {
            "category":"Real Estate",
            "subcategory":"Surveying",
            "type":"Services"
        }
    ],
    "sg:phone":"+32 3 888 82 84",
    "sg:postcode":"2840",
    "sg:province":"Antwerpen",
    "sg:tags":[
        "lettering",
        "letter"
    ],
    "wof:name":"T.c. Design",
    "wof:placetype":"venue"
},
  "geometry": {"coordinates":[4.3663640022,51.107925415],"type":"Point"}
}