{
  "type": "Feature",
  "properties": {
    "addr:full":"Veldweg 6 Zottegem (leeuwergem) Oost-Vlaanderen 9620",
    "addr:housenumber":"6",
    "addr:postcode":"9620",
    "addr:street":"Veldweg",
    "iso:country":"BE",
    "sg:address":"Veldweg 6",
    "sg:city":"Zottegem (leeuwergem)",
    "sg:classifiers":[
        {
            "category":"Retail",
            "subcategory":"Car Wash",
            "type":"Services"
        }
    ],
    "sg:phone":"+32 9 361 28 15",
    "sg:postcode":"9620",
    "sg:province":"Oost-Vlaanderen",
    "sg:tags":[
        "automobile",
        "washing",
        "-",
        "truck"
    ],
    "wof:name":"Sirocco Carwash",
    "wof:placetype":"venue"
},
  "geometry": {"coordinates":[3.8356969357,50.8875961304],"type":"Point"}
}