{
  "type": "Feature",
  "properties": {
    "addr:full":"Koning Leopold I-straat 1b62 Leuven Vlaams-Brabant 3000",
    "addr:housenumber":"1b62",
    "addr:postcode":"3000",
    "addr:street":"Koning Leopold I-Straat",
    "iso:country":"BE",
    "sg:address":"Koning Leopold I-straat 1b62",
    "sg:city":"Leuven",
    "sg:orig_category":"Projectontwikkelaars",
    "sg:phone":"+32 16 23 23 87",
    "sg:postcode":"3000",
    "sg:province":"Vlaams-Brabant",
    "wof:name":"Immo Christophe Promotion",
    "wof:placetype":"venue"
},
  "geometry": {"coordinates":[4.7080302238,50.8788490295],"type":"Point"}
}