{
  "type": "Feature",
  "properties": {
    "addr:full":"Karolingenstraat 13 Mechelen (muizen) Antwerpen 2812",
    "addr:housenumber":"13",
    "addr:postcode":"2812",
    "addr:street":"Karolingenstraat",
    "iso:country":"BE",
    "sg:address":"Karolingenstraat 13",
    "sg:city":"Mechelen (muizen)",
    "sg:classifiers":[
        {
            "category":"Personal",
            "subcategory":"Beauty Salon",
            "type":"Services"
        }
    ],
    "sg:phone":"+32 15 42 22 28",
    "sg:postcode":"2812",
    "sg:province":"Antwerpen",
    "sg:tags":[
        "lady",
        "-",
        "hairdressing"
    ],
    "wof:name":"Sonja",
    "wof:placetype":"venue"
},
  "geometry": {"coordinates":[4.5115661621,51.0104026794],"type":"Point"}
}