{
  "type": "Feature",
  "properties": {
    "addr:full":". Houthalen-helchteren Limburg 3530",
    "addr:postcode":"3530",
    "iso:country":"BE",
    "sg:address":".",
    "sg:city":"Houthalen-helchteren",
    "sg:orig_category":"Apotheken",
    "sg:phone":"+32 900 10 500",
    "sg:postcode":"3530",
    "sg:province":"Limburg",
    "wof:name":"Apothekers Van Wacht",
    "wof:placetype":"venue"
},
  "geometry": {"coordinates":[5.3719201088,51.0310020447],"type":"Point"}
}