{
  "type": "Feature",
  "properties": {
    "iso:country":"BE",
    "sg:address":"Rue Marcel Louis 6",
    "sg:city":"Incourt (pi\u00e8trebais)",
    "sg:classifiers":[
        {
            "category":"Personal",
            "subcategory":"Beauty Salon",
            "type":"Services"
        }
    ],
    "sg:phone":"+32 2 649 13 97",
    "sg:postcode":"1315",
    "sg:province":"Brabant Wallon",
    "sg:tags":[
        "lady",
        "-",
        "hairdressing"
    ],
    "wof:name":"Coiff'mobile",
    "wof:placetype":"venue"
},
  "geometry": {"coordinates":[4.7542209625,50.7299728394],"type":"Point"}
}