{
  "type": "Feature",
  "properties": {
    "iso:country":"BE",
    "sg:address":"Clos Michel Thiry 18",
    "sg:city":"Li\u00e8ge 1 (li\u00e8ge 2)",
    "sg:classifiers":[
        {
            "category":"Arts & Performance",
            "subcategory":"Theater",
            "type":"Entertainment"
        }
    ],
    "sg:postcode":"4020",
    "sg:province":"Li\u00e8ge",
    "sg:tags":[
        "theatrical",
        "agency"
    ],
    "wof:name":"Mh Productions Asbl",
    "wof:placetype":"venue"
},
  "geometry": {"coordinates":[5.584127903,50.6269989014],"type":"Point"}
}