{
  "type": "Feature",
  "properties": {
    "addr:full":"Mail 1 Bruxelles (ganshoren) Bruxelles-Capitale 1083",
    "addr:housenumber":"1",
    "addr:postcode":"1083",
    "addr:street":"Mail",
    "iso:country":"BE",
    "sg:address":"Mail 1",
    "sg:city":"Bruxelles (ganshoren)",
    "sg:classifiers":[
        {
            "category":"Professional",
            "subcategory":"Secretarial Services",
            "type":"Services"
        }
    ],
    "sg:phone":"+32 2 468 51 22",
    "sg:postcode":"1083",
    "sg:province":"Bruxelles-Capitale",
    "sg:tags":[
        "delivery",
        "messenger"
    ],
    "wof:name":"Flm T&t Sprl",
    "wof:placetype":"venue"
},
  "geometry": {"coordinates":[4.3025398254,50.8734397888],"type":"Point"}
}