{
  "type": "Feature",
  "properties": {
    "iso:country":"BE",
    "sg:address":"Marktplein 10",
    "sg:city":"Ternat",
    "sg:orig_category":"Apotheken",
    "sg:phone":"+32 2 582 11 51",
    "sg:postcode":"1740",
    "sg:province":"Vlaams-Brabant",
    "wof:name":"Farmagora",
    "wof:placetype":"venue"
},
  "geometry": {"coordinates":[4.1782608032,50.8713645935],"type":"Point"}
}