{
  "type": "Feature",
  "properties": {
    "iso:country":"BE",
    "sg:address":"Koninkrijk 95",
    "sg:city":"Herentals (morkhoven)",
    "sg:classifiers":[
        {
            "category":"Building & Trades",
            "subcategory":"Landscaping Services",
            "type":"Services"
        }
    ],
    "sg:phone":"+32 14 26 12 55",
    "sg:postcode":"2200",
    "sg:province":"Antwerpen",
    "sg:tags":[
        "gardening",
        "garden",
        "maintenance"
    ],
    "wof:name":"Van Looy Tuinplanning",
    "wof:placetype":"venue"
},
  "geometry": {"coordinates":[4.8293390274,51.1194152832],"type":"Point"}
}