{
  "type": "Feature",
  "properties": {
    "addr:full":"Rue Francois Lef\u00e8bvre 121a Li\u00e8ge 1 (rocourt) Li\u00e8ge 4000",
    "addr:housenumber":"121a;1",
    "addr:postcode":"4000",
    "addr:street":"Rue Francois Lefe\u0300Bvre",
    "iso:country":"BE",
    "sg:address":"Rue Francois Lef\u00e8bvre 121a",
    "sg:city":"Li\u00e8ge 1 (rocourt)",
    "sg:classifiers":[
        {
            "category":"Insurance",
            "subcategory":"Insurance Agent",
            "type":"Services"
        }
    ],
    "sg:phone":"+32 4 239 11 31",
    "sg:postcode":"4000",
    "sg:province":"Li\u00e8ge",
    "sg:tags":[
        "broker"
    ],
    "wof:name":"Vaes G",
    "wof:placetype":"venue"
},
  "geometry": {"coordinates":[5.5482578278,50.6815452576],"type":"Point"}
}