{
  "type": "Feature",
  "properties": {
    "iso:country":"BE",
    "sg:address":"Place Marie -jos\u00c9 8",
    "sg:city":"Elsene/ixelles",
    "sg:orig_category":"Epiceries",
    "sg:phone":"+32 2 648 63 74",
    "sg:postcode":"1050",
    "sg:province":"Bruxelles-Capitale",
    "wof:name":"Socauto Services Fina",
    "wof:placetype":"venue"
},
  "geometry": {"coordinates":[4.3876070976,50.8061676025],"type":"Point"}
}