{
  "type": "Feature",
  "properties": {
    "addr:full":"Galerie Cath\u00e9drale 70 Li\u00e8ge 1 Li\u00e8ge 4000",
    "addr:housenumber":"70;1",
    "addr:postcode":"4000",
    "addr:street":"Lie\u0300Ge",
    "iso:country":"BE",
    "sg:address":"Galerie Cath\u00e9drale 70",
    "sg:city":"Li\u00e8ge 1",
    "sg:classifiers":[
        {
            "category":"Health Services",
            "subcategory":"Optometrist",
            "type":"Services"
        }
    ],
    "sg:phone":"+32 4 221 34 56",
    "sg:postcode":"4000",
    "sg:province":"Li\u00e8ge",
    "wof:name":"Lafont Boutique",
    "wof:placetype":"venue"
},
  "geometry": {"coordinates":[5.5740208626,50.6423606873],"type":"Point"}
}