{
  "type": "Feature",
  "properties": {
    "iso:country":"BE",
    "sg:address":"Kerkstraat 61",
    "sg:city":"Hulshout",
    "sg:orig_category":"Artsen and specialisten",
    "sg:phone":"+32 15 22 21 75",
    "sg:postcode":"2235",
    "sg:province":"Antwerpen",
    "wof:name":"Rita Van Doninck",
    "wof:placetype":"venue"
},
  "geometry": {"coordinates":[4.795129776,51.077381134],"type":"Point"}
}