{
  "type": "Feature",
  "properties": {
    "iso:country":"BE",
    "sg:address":"Omselweg 41",
    "sg:city":"Bree",
    "sg:classifiers":[
        {
            "category":"Cafe",
            "type":"Food & Drink"
        }
    ],
    "sg:phone":"+32 89 86 77 08",
    "sg:postcode":"3960",
    "sg:province":"Limburg",
    "sg:tags":[
        "caf\u00e9s"
    ],
    "wof:name":"Valentina Joosten",
    "wof:placetype":"venue"
},
  "geometry": {"coordinates":[5.5944190025,51.1405677795],"type":"Point"}
}