{
  "type": "Feature",
  "properties": {
    "iso:country":"BE",
    "sg:address":"Rue Georges-simenon 22",
    "sg:city":"Li\u00e8ge 1 (li\u00e8ge 2)",
    "sg:classifiers":[
        {
            "category":"Real Estate",
            "subcategory":"Architect",
            "type":"Services"
        }
    ],
    "sg:phone":"+32 4 342 76 74",
    "sg:postcode":"4020",
    "sg:province":"Li\u00e8ge",
    "wof:name":"Cornet M",
    "wof:placetype":"venue"
},
  "geometry": {"coordinates":[5.5863828659,50.6418266296],"type":"Point"}
}