{
  "type": "Feature",
  "properties": {
    "iso:country":"BE",
    "sg:address":"Stasegemsesteenweg 184",
    "sg:city":"Harelbeke",
    "sg:classifiers":[
        {
            "category":"Home & Garden",
            "subcategory":"Building Materials",
            "type":"Retail Goods"
        }
    ],
    "sg:phone":"+32 56 22 65 34",
    "sg:postcode":"8530",
    "sg:province":"West-Vlaanderen",
    "sg:tags":[
        "window"
    ],
    "wof:name":"Holvoet R Bvba",
    "wof:placetype":"venue"
},
  "geometry": {"coordinates":[3.3112049103,50.837928772],"type":"Point"}
}