{
  "type": "Feature",
  "properties": {
    "addr:full":"Noordmoerstraat 7 Veurne West-Vlaanderen 8630",
    "addr:housenumber":"7",
    "addr:postcode":"8630",
    "addr:street":"Noordmoerstraat",
    "iso:country":"BE",
    "sg:address":"Noordmoerstraat 7",
    "sg:city":"Veurne",
    "sg:orig_category":"Eleveurs and marchands de porcs",
    "sg:phone":"+32 58 31 10 42",
    "sg:postcode":"8630",
    "sg:province":"West-Vlaanderen",
    "wof:name":"Freddy Huyghe",
    "wof:placetype":"venue"
},
  "geometry": {"coordinates":[2.6146850586,51.0472145081],"type":"Point"}
}