{
  "type": "Feature",
  "properties": {
    "addr:full":"Begijnenstraat 60 Box 1 Diest Vlaams-Brabant 3290",
    "addr:housenumber":"60;1",
    "addr:postcode":"3290",
    "addr:street":"Begijnenstraat;Box",
    "iso:country":"BE",
    "sg:address":"Begijnenstraat 60 Box 1",
    "sg:city":"Diest",
    "sg:orig_category":"Non-Classified Establishments",
    "sg:phone":"+32 13 32 78 32",
    "sg:postcode":"3290",
    "sg:province":"Vlaams-Brabant",
    "wof:name":"Daily-trading",
    "wof:placetype":"venue"
},
  "geometry": {"coordinates":[5.0595507622,50.98802948],"type":"Point"}
}