{
  "type": "Feature",
  "properties": {
    "iso:country":"BE",
    "sg:address":"Vredelaan 43",
    "sg:city":"Torhout",
    "sg:classifiers":[
        {
            "category":"Shopping",
            "subcategory":"Antiques",
            "type":"Retail Goods"
        }
    ],
    "sg:phone":"+32 50 22 07 47",
    "sg:postcode":"8820",
    "sg:province":"West-Vlaanderen",
    "wof:name":"Oud Thourout Antiek",
    "wof:placetype":"venue"
},
  "geometry": {"coordinates":[3.0953578949,51.0603218079],"type":"Point"}
}