{
  "type": "Feature",
  "properties": {
    "addr:full":"Gal. Carmes Wavre Brabant Wallon 1300",
    "addr:housenumber":"1300",
    "iso:country":"BE",
    "sg:address":"Gal. Carmes",
    "sg:city":"Wavre",
    "sg:orig_category":"Catalogues de vente par correspondance",
    "sg:phone":"+32 10 24 26 88",
    "sg:postcode":"1300",
    "sg:province":"Brabant Wallon",
    "wof:name":"Belgique Loisirs",
    "wof:placetype":"venue"
},
  "geometry": {"coordinates":[4.6083159447,50.7159461975],"type":"Point"}
}