{
  "type": "Feature",
  "properties": {
    "addr:full":"Chemin De Saint-ghislain 134 Chi\u00e8vres Hainaut 7950",
    "addr:housenumber":"134",
    "addr:postcode":"7950",
    "addr:street":"Chemin De Saint-Ghislain;Hainaut",
    "iso:country":"BE",
    "sg:address":"Chemin De Saint-ghislain 134",
    "sg:city":"Chi\u00e8vres",
    "sg:classifiers":[
        {
            "category":"Shopping",
            "subcategory":"Florist",
            "type":"Retail Goods"
        }
    ],
    "sg:phone":"+32 68 66 59 23",
    "sg:postcode":"7950",
    "sg:province":"Hainaut",
    "wof:name":"Fleurs Des Champs (aux)",
    "wof:placetype":"venue"
},
  "geometry": {"coordinates":[3.806210041,50.5593299866],"type":"Point"}
}