{
  "type": "Feature",
  "properties": {
    "addr:full":"Lege Veldkantlaan 36 Hove Antwerpen 2540",
    "addr:housenumber":"36",
    "addr:postcode":"2540",
    "addr:street":"Lege Veldkantlaan",
    "iso:country":"BE",
    "sg:address":"Lege Veldkantlaan 36",
    "sg:city":"Hove",
    "sg:orig_category":"Artsen and specialisten",
    "sg:phone":"+32 3 454 34 44",
    "sg:postcode":"2540",
    "sg:province":"Antwerpen",
    "wof:name":"Marion Valkenburg",
    "wof:placetype":"venue"
},
  "geometry": {"coordinates":[4.4830851555,51.1420211792],"type":"Point"}
}