{
  "type": "Feature",
  "properties": {
    "addr:full":"Chauss\u00c9e De W\u00c9gimont 76 Soumagne Li\u00e8ge 4630",
    "addr:housenumber":"76",
    "addr:postcode":"4630",
    "addr:street":"Chausse\u0301E De We\u0301Gimont",
    "iso:country":"BE",
    "sg:address":"Chauss\u00c9e De W\u00c9gimont 76",
    "sg:city":"Soumagne",
    "sg:orig_category":"Caf\u00e9s Kampeerterreinen",
    "sg:phone":"+32 4 377 99 02",
    "sg:postcode":"4630",
    "sg:province":"Li\u00e8ge",
    "wof:name":"Camping Du Domaine Provincial W\u00c9gimont",
    "wof:placetype":"venue"
},
  "geometry": {"coordinates":[5.738503933,50.6115951538],"type":"Point"}
}