{
  "type": "Feature",
  "properties": {
    "addr:full":"Spani\u00cbnhof 23 Sint-genesius-rode/rhode-saint-gen\u00c8se Vlaams-Brabant 1640",
    "addr:housenumber":"23",
    "addr:postcode":"1640",
    "addr:street":"Spanie\u0308Nhof",
    "iso:country":"BE",
    "sg:address":"Spani\u00cbnhof 23",
    "sg:city":"Sint-genesius-rode/rhode-saint-gen\u00c8se",
    "sg:orig_category":"Installatie van houten of kunststof schrijnwerk",
    "sg:phone":"+32 2 380 94 02",
    "sg:postcode":"1640",
    "sg:province":"Vlaams-Brabant",
    "wof:name":"Eddy Lamal",
    "wof:placetype":"venue"
},
  "geometry": {"coordinates":[4.3565897942,50.7479095459],"type":"Point"}
}