{
  "type": "Feature",
  "properties": {
    "addr:full":"Koningin Astridlaan 217 Gent Oost-Vlaanderen 9000",
    "addr:housenumber":"217",
    "addr:postcode":"9000",
    "addr:street":"Koningin Astridlaan;Oost-Vlaanderen",
    "iso:country":"BE",
    "sg:address":"Koningin Astridlaan 217",
    "sg:city":"Gent",
    "sg:orig_category":"Apotheken",
    "sg:phone":"+32 9 222 21 99",
    "sg:postcode":"9000",
    "sg:province":"Oost-Vlaanderen",
    "wof:name":"Liliane De Mey",
    "wof:placetype":"venue"
},
  "geometry": {"coordinates":[3.7129130363,51.0362472534],"type":"Point"}
}