{
  "type": "Feature",
  "properties": {
    "addr:full":"Dorp 37 Sint-katelijne-waver Antwerpen 2580",
    "addr:housenumber":"37",
    "addr:postcode":"2580",
    "addr:street":"Dorp",
    "iso:country":"BE",
    "sg:address":"Dorp 37",
    "sg:city":"Sint-katelijne-waver",
    "sg:orig_category":"Drukkerijen and copyshops Kantoormateriaal",
    "sg:phone":"+32 15 75 78 55",
    "sg:postcode":"2580",
    "sg:province":"Antwerpen",
    "wof:name":"Papierhandel Filip Willems",
    "wof:placetype":"venue"
},
  "geometry": {"coordinates":[4.6288099289,51.0548591614],"type":"Point"}
}