{
  "type": "Feature",
  "properties": {
    "addr:full":"Desselgem-dries 127 Waregem West-Vlaanderen 8792",
    "addr:housenumber":"127",
    "addr:postcode":"8792",
    "iso:country":"BE",
    "sg:address":"Desselgem-dries 127",
    "sg:city":"Waregem",
    "sg:orig_category":"Slagers",
    "sg:phone":"+32 56 71 21 84",
    "sg:postcode":"8792",
    "sg:province":"West-Vlaanderen",
    "wof:name":"Fernand Vermoere",
    "wof:placetype":"venue"
},
  "geometry": {"coordinates":[3.3650488853,50.8864898682],"type":"Point"}
}