{
  "type": "Feature",
  "properties": {
    "addr:full":"Engelstraat 47 Ichtegem West-Vlaanderen 8480",
    "addr:housenumber":"47",
    "addr:postcode":"8480",
    "addr:street":"Engelstraat",
    "iso:country":"BE",
    "sg:address":"Engelstraat 47",
    "sg:city":"Ichtegem",
    "sg:orig_category":"Instituts de beaut\u00e9. Centres de relaxation and bien-\u00eatre. Sous-v\u00eatements and lingerie",
    "sg:phone":"+32 51 58 96 16",
    "sg:postcode":"8480",
    "sg:province":"West-Vlaanderen",
    "wof:name":"Nymphaea",
    "wof:placetype":"venue"
},
  "geometry": {"coordinates":[3.0144309998,51.0933380127],"type":"Point"}
}