{
  "type": "Feature",
  "properties": {
    "addr:full":"Statiestraat 18 Kalmthout Antwerpen 2920",
    "addr:housenumber":"18",
    "addr:postcode":"2920",
    "addr:street":"Statiestraat",
    "iso:country":"BE",
    "sg:address":"Statiestraat 18",
    "sg:city":"Kalmthout",
    "sg:orig_category":"V\u00eatements",
    "sg:phone":"+32 3 666 45 88",
    "sg:postcode":"2920",
    "sg:province":"Antwerpen",
    "wof:name":"Jeans Fizz",
    "wof:placetype":"venue"
},
  "geometry": {"coordinates":[4.4731278419,51.3938980103],"type":"Point"}
}