{
  "type": "Feature",
  "properties": {
    "iso:country":"BE",
    "sg:address":"Ieperstraat 4",
    "sg:city":"Langemark-poelkapelle",
    "sg:orig_category":"Eleveurs de bovins",
    "sg:phone":"+32 57 48 85 01",
    "sg:postcode":"8920",
    "sg:province":"West-Vlaanderen",
    "wof:name":"Frans Deraedt",
    "wof:placetype":"venue"
},
  "geometry": {"coordinates":[2.919770956,50.9132423401],"type":"Point"}
}