{
  "type": "Feature",
  "properties": {
    "iso:country":"BE",
    "sg:address":"Ellestraat 119ba",
    "sg:city":"Zwevegem",
    "sg:orig_category":"HUISBRANDOLIE",
    "sg:phone":"+32 56 75 52 35",
    "sg:postcode":"8550",
    "sg:province":"West-Vlaanderen",
    "wof:name":"Roose",
    "wof:placetype":"venue"
},
  "geometry": {"coordinates":[3.3576300144,50.8049583435],"type":"Point"}
}