{
  "type": "Feature",
  "properties": {
    "addr:full":"Bloemenlaan 25 Kluisbergen Oost-Vlaanderen 9690",
    "addr:housenumber":"25",
    "addr:postcode":"9690",
    "addr:street":"Bloemenlaan",
    "iso:country":"BE",
    "sg:address":"Bloemenlaan 25",
    "sg:city":"Kluisbergen",
    "sg:orig_category":"Eleveurs de bovins",
    "sg:phone":"+32 55 38 71 86",
    "sg:postcode":"9690",
    "sg:province":"Oost-Vlaanderen",
    "wof:name":"Herman Verplanken",
    "wof:placetype":"venue"
},
  "geometry": {"coordinates":[3.5123620033,50.789352417],"type":"Point"}
}