{
  "type": "Feature",
  "properties": {
    "iso:country":"BE",
    "sg:address":"Boeur 3",
    "sg:city":"Houffalize",
    "sg:orig_category":"Rundveehouders",
    "sg:phone":"+32 61 28 85 72",
    "sg:postcode":"6662",
    "sg:province":"Luxembourg",
    "wof:name":"Maurice Widart",
    "wof:placetype":"venue"
},
  "geometry": {"coordinates":[5.8389720917,50.0886611938],"type":"Point"}
}