{
  "type": "Feature",
  "properties": {
    "iso:country":"BE",
    "sg:address":"Statiestraat 4a",
    "sg:city":"Mol",
    "sg:orig_category":"Newspapers, magazines, periodicals - Distribution",
    "sg:phone":"+32 14 31 18 94",
    "sg:postcode":"2400",
    "sg:province":"Antwerpen",
    "wof:name":"Press Shop Alg",
    "wof:placetype":"venue"
},
  "geometry": {"coordinates":[5.1182022095,51.1898498535],"type":"Point"}
}