{
  "type": "Feature",
  "properties": {
    "addr:full":"Cloetbergstraat 24 Ardooie West-Vlaanderen 8850",
    "addr:housenumber":"24",
    "addr:postcode":"8850",
    "addr:street":"Cloetbergstraat",
    "iso:country":"BE",
    "sg:address":"Cloetbergstraat 24",
    "sg:city":"Ardooie",
    "sg:orig_category":"Groententeelt",
    "sg:phone":"+32 51 74 49 76",
    "sg:postcode":"8850",
    "sg:province":"West-Vlaanderen",
    "wof:name":"Donald Deprez",
    "wof:placetype":"venue"
},
  "geometry": {"coordinates":[3.1887249947,50.9626197815],"type":"Point"}
}