{
  "type": "Feature",
  "properties": {
    "addr:full":"Verbrande Brugsesteenweg 52 Grimbergen Vlaams-Brabant 1850",
    "addr:housenumber":"52",
    "addr:postcode":"1850",
    "addr:street":"Verbrande Brugsesteenweg",
    "iso:country":"BE",
    "sg:address":"Verbrande Brugsesteenweg 52",
    "sg:city":"Grimbergen",
    "sg:classifiers":[
        {
            "category":"Shopping",
            "subcategory":"Stationery & Office Supplies",
            "type":"Retail Goods"
        }
    ],
    "sg:phone":"+32 2 251 43 57",
    "sg:postcode":"1850",
    "sg:province":"Vlaams-Brabant",
    "sg:tags":[
        "information",
        "technology",
        "telecommunication",
        "equipment"
    ],
    "wof:name":"Kores Nordic Belgium Nv",
    "wof:placetype":"venue"
},
  "geometry": {"coordinates":[4.4079017639,50.9438209534],"type":"Point"}
}