{
  "type": "Feature",
  "properties": {
    "iso:country":"BE",
    "sg:address":"Ringlaan 32",
    "sg:city":"Mol",
    "sg:orig_category":"Non-Classified Establishments",
    "sg:phone":"+32 800 90 761",
    "sg:postcode":"2400",
    "sg:province":"Antwerpen",
    "wof:name":"Loop Eyewear Bvba",
    "wof:placetype":"venue"
},
  "geometry": {"coordinates":[5.2130250931,51.1911354065],"type":"Point"}
}