{
  "type": "Feature",
  "properties": {
    "addr:full":"Langemarkstraat 38 Zonnebeke West-Vlaanderen 8980",
    "addr:housenumber":"38",
    "addr:postcode":"8980",
    "addr:street":"Langemarkstraat",
    "iso:country":"BE",
    "sg:address":"Langemarkstraat 38",
    "sg:city":"Zonnebeke",
    "sg:orig_category":"Rev\u00eatements de sols and murs",
    "sg:phone":"+32 51 77 84 69",
    "sg:postcode":"8980",
    "sg:province":"West-Vlaanderen",
    "wof:name":"Robert Vanwalleghem",
    "wof:placetype":"venue"
},
  "geometry": {"coordinates":[2.9841499329,50.8751564026],"type":"Point"}
}