{
  "type": "Feature",
  "properties": {
    "iso:country":"BE",
    "sg:address":"Kunstlaan 19",
    "sg:city":"Sint-joost-ten-node/saint-josse-ten-noode",
    "sg:orig_category":"Artsen and specialisten",
    "sg:phone":"+32 2 220 56 23",
    "sg:postcode":"1210",
    "sg:province":"Bruxelles-Capitale",
    "wof:name":"Nadine Gabet",
    "wof:placetype":"venue"
},
  "geometry": {"coordinates":[4.369784832,50.8469467163],"type":"Point"}
}