{
  "type": "Feature",
  "properties": {
    "iso:country":"BE",
    "sg:address":"Nederrij 21",
    "sg:city":"Herentals (grand)",
    "sg:classifiers":[
        {
            "category":"Restaurant",
            "type":"Food & Drink"
        }
    ],
    "sg:phone":"+32 14 22 66 77",
    "sg:postcode":"2200",
    "sg:province":"Antwerpen",
    "wof:name":"Pronto",
    "wof:placetype":"venue"
},
  "geometry": {"coordinates":[4.8347969055,51.1825218201],"type":"Point"}
}