{
  "type": "Feature",
  "properties": {
    "iso:country":"BE",
    "sg:address":"Sint-annastraat 9",
    "sg:city":"Overpelt",
    "sg:classifiers":[
        {
            "category":"Personal",
            "subcategory":"Beauty Salon",
            "type":"Services"
        }
    ],
    "sg:phone":"+32 11 64 65 77",
    "sg:postcode":"3900",
    "sg:province":"Limburg",
    "sg:tags":[
        "lady",
        "-",
        "hairdressing"
    ],
    "wof:name":"Myriam",
    "wof:placetype":"venue"
},
  "geometry": {"coordinates":[5.4286270142,51.2032241821],"type":"Point"}
}