{
  "type": "Feature",
  "properties": {
    "iso:country":"BE",
    "sg:address":"Eikenstraat 71",
    "sg:city":"Lubbeek",
    "sg:orig_category":"Telecommunicatiesystemen",
    "sg:phone":"+32 16 62 15 03",
    "sg:postcode":"3210",
    "sg:province":"Vlaams-Brabant",
    "wof:name":"Fax Star Belgium",
    "wof:placetype":"venue"
},
  "geometry": {"coordinates":[4.7846579552,50.9077796936],"type":"Point"}
}