{
  "type": "Feature",
  "properties": {
    "addr:full":"Achterlee 11 Kasterlee (lichtaart) Antwerpen 2460",
    "addr:housenumber":"11",
    "addr:postcode":"2460",
    "addr:street":"Achterlee",
    "iso:country":"BE",
    "sg:address":"Achterlee 11",
    "sg:city":"Kasterlee (lichtaart)",
    "sg:orig_category":"Non-Classified Establishments",
    "sg:phone":"+32 14 55 15 29",
    "sg:postcode":"2460",
    "sg:province":"Antwerpen",
    "wof:name":"Kantklosje ('t)",
    "wof:placetype":"venue"
},
  "geometry": {"coordinates":[4.9671049118,51.2406616211],"type":"Point"}
}