{
  "type": "Feature",
  "properties": {
    "addr:full":"Avenue Paul Deschanel 47 Bruxelles (schaerbeek) Bruxelles-Capitale 1030",
    "addr:housenumber":"47",
    "addr:postcode":"1030",
    "addr:street":"Avenue Paul Deschanel",
    "iso:country":"BE",
    "sg:address":"Avenue Paul Deschanel 47",
    "sg:city":"Bruxelles (schaerbeek)",
    "sg:classifiers":[
        {
            "category":"Building & Trades",
            "subcategory":"Landscaping Services",
            "type":"Services"
        }
    ],
    "sg:phone":"+32 2 241 77 89",
    "sg:postcode":"1030",
    "sg:province":"Bruxelles-Capitale",
    "sg:tags":[
        "gardening",
        "garden",
        "maintenance"
    ],
    "wof:name":"Van Damme J",
    "wof:placetype":"venue"
},
  "geometry": {"coordinates":[4.3796920776,50.8614082336],"type":"Point"}
}