{
  "type": "Feature",
  "properties": {
    "iso:country":"BE",
    "sg:address":"Rue Charles Gantois 35",
    "sg:city":"Estinnes (fauroeulx)",
    "sg:classifiers":[
        {
            "category":"Real Estate",
            "subcategory":"Architect",
            "type":"Services"
        }
    ],
    "sg:phone":"+32 64 77 22 87",
    "sg:postcode":"7120",
    "sg:province":"Hainaut",
    "wof:name":"Amiri H",
    "wof:placetype":"venue"
},
  "geometry": {"coordinates":[4.1168379784,50.3689155579],"type":"Point"}
}