{
  "type": "Feature",
  "properties": {
    "addr:full":"Filips De Goedelaan 14 Landen Vlaams-Brabant 3400",
    "addr:housenumber":"14",
    "addr:postcode":"3400",
    "addr:street":"Filips De Goedelaan",
    "iso:country":"BE",
    "sg:address":"Filips De Goedelaan 14",
    "sg:city":"Landen",
    "sg:classifiers":[
        {
            "category":"Cafe",
            "type":"Food & Drink"
        }
    ],
    "sg:phone":"+32 11 88 24 55",
    "sg:postcode":"3400",
    "sg:province":"Vlaams-Brabant",
    "sg:tags":[
        "caf\u00e9s"
    ],
    "wof:name":"V.c. Sparta Landen",
    "wof:placetype":"venue"
},
  "geometry": {"coordinates":[5.088321209,50.7467460632],"type":"Point"}
}