{
  "type": "Feature",
  "properties": {
    "addr:full":"Cit\u00c9 Du Bois Goulet 9 Verviers Li\u00e8ge 4801",
    "addr:housenumber":"9",
    "addr:postcode":"4801",
    "addr:street":"Cite\u0301 Du Bois Goulet",
    "iso:country":"BE",
    "sg:address":"Cit\u00c9 Du Bois Goulet 9",
    "sg:city":"Verviers",
    "sg:classifiers":[
        {
            "category":"Arena",
            "subcategory":"Sports Club",
            "type":"Entertainment"
        }
    ],
    "sg:phone":"+32 87 22 89 00",
    "sg:postcode":"4801",
    "sg:province":"Li\u00e8ge",
    "sg:tags":[
        "de"
    ],
    "wof:name":"B.c. S.f.x. Verviers",
    "wof:placetype":"venue"
},
  "geometry": {"coordinates":[5.8924832344,50.5811386108],"type":"Point"}
}