{
  "type": "Feature",
  "properties": {
    "addr:full":"Rode-kruisplein 20 Mechelen Antwerpen 2800",
    "addr:housenumber":"20",
    "addr:postcode":"2800",
    "addr:street":"Rode-Kruisplein",
    "iso:country":"BE",
    "sg:address":"Rode-kruisplein 20",
    "sg:city":"Mechelen",
    "sg:classifiers":[
        {
            "category":"Food & Beverages",
            "subcategory":"Groceries & Convenience Stores",
            "type":"Retail Goods"
        }
    ],
    "sg:phone":"+32 15 29 02 66",
    "sg:postcode":"2800",
    "sg:province":"Antwerpen",
    "sg:tags":[
        "product",
        "related"
    ],
    "wof:name":"Walter Marcelo Nv",
    "wof:placetype":"venue"
},
  "geometry": {"coordinates":[4.4708938599,51.0332641602],"type":"Point"}
}