{
  "type": "Feature",
  "properties": {
    "addr:full":"Rue De L'institut 68 Soumagne (cerexhe-heuseux) Li\u00e8ge 4632",
    "addr:housenumber":"68",
    "addr:postcode":"4632",
    "addr:street":"Rue De L'Institut;Cerexhe-Heuseux",
    "iso:country":"BE",
    "sg:address":"Rue De L'institut 68",
    "sg:city":"Soumagne (cerexhe-heuseux)",
    "sg:classifiers":[
        {
            "category":"Retail",
            "subcategory":"Auto Repair",
            "type":"Services"
        }
    ],
    "sg:phone":"+32 4 387 41 33",
    "sg:postcode":"4632",
    "sg:province":"Li\u00e8ge",
    "sg:tags":[
        "garage"
    ],
    "wof:name":"Poumay Jean-marie",
    "wof:placetype":"venue"
},
  "geometry": {"coordinates":[5.7179670334,50.6567726135],"type":"Point"}
}