{
  "type": "Feature",
  "properties": {
    "iso:country":"BE",
    "sg:address":"Taverneux 44",
    "sg:city":"Houffalize (mont)",
    "sg:classifiers":[
        {
            "category":"Food & Beverages",
            "subcategory":"Meat & Fish",
            "type":"Retail Goods"
        }
    ],
    "sg:phone":"+32 61 28 80 43",
    "sg:postcode":"6661",
    "sg:province":"Luxembourg",
    "sg:tags":[
        "-",
        "livestock"
    ],
    "wof:name":"Deumer A",
    "wof:placetype":"venue"
},
  "geometry": {"coordinates":[5.768889904,50.1544418335],"type":"Point"}
}