{
  "type": "Feature",
  "properties": {
    "iso:country":"BE",
    "sg:address":"Delaerestraat 27",
    "sg:city":"Roeselare",
    "sg:classifiers":[
        {
            "category":"Bars & Pubs",
            "type":"Food & Drink"
        }
    ],
    "sg:phone":"+32 51 20 79 40",
    "sg:postcode":"8800",
    "sg:province":"West-Vlaanderen",
    "wof:name":"Bistro Pistache",
    "wof:placetype":"venue"
},
  "geometry": {"coordinates":[3.1282529831,50.9462509155],"type":"Point"}
}