{
  "type": "Feature",
  "properties": {
    "addr:full":"Waversesteenweg 63 Putte Antwerpen 2580",
    "addr:housenumber":"63",
    "addr:postcode":"2580",
    "addr:street":"Waversesteenweg",
    "iso:country":"BE",
    "sg:address":"Waversesteenweg 63",
    "sg:city":"Putte",
    "sg:classifiers":[
        {
            "category":"Retail",
            "subcategory":"Funeral Services",
            "type":"Services"
        }
    ],
    "sg:phone":"+32 15 75 54 25",
    "sg:postcode":"2580",
    "sg:province":"Antwerpen",
    "sg:tags":[
        "director"
    ],
    "wof:name":"Begrafenissen Van Der Hoeven",
    "wof:placetype":"venue"
},
  "geometry": {"coordinates":[4.6206130981,51.0600318909],"type":"Point"}
}