{
  "type": "Feature",
  "properties": {
    "iso:country":"BE",
    "sg:address":"Lage Leemstraat 319",
    "sg:city":"Antwerpen",
    "sg:orig_category":"Agences d'exp\u00e9dition",
    "sg:phone":"+32 3 281 01 78",
    "sg:postcode":"2018",
    "sg:province":"Antwerpen",
    "wof:name":"Morisco",
    "wof:placetype":"venue"
},
  "geometry": {"coordinates":[4.4226360321,51.2042961121],"type":"Point"}
}