{
  "type": "Feature",
  "properties": {
    "iso:country":"BE",
    "sg:address":"Rue Laplace 64",
    "sg:city":"Seraing",
    "sg:classifiers":[
        {
            "category":"Health Services",
            "subcategory":"Nursing And Care Facility",
            "type":"Services"
        }
    ],
    "sg:phone":"+32 4 338 74 90",
    "sg:postcode":"4100",
    "sg:province":"Li\u00e8ge",
    "sg:tags":[
        "home",
        "rest"
    ],
    "wof:name":"A.i.s.h",
    "wof:placetype":"venue"
},
  "geometry": {"coordinates":[5.4904050827,50.5798835754],"type":"Point"}
}