{
  "type": "Feature",
  "properties": {
    "addr:full":"Blauweweg 7 Antwerpen Antwerpen 2030",
    "addr:housenumber":"7",
    "addr:postcode":"2030",
    "addr:street":"Blauweweg",
    "iso:country":"BE",
    "sg:address":"Blauweweg 7",
    "sg:city":"Antwerpen",
    "sg:orig_category":"Huisvuilophaling and -verwerking",
    "sg:phone":"+32 3 542 14 82",
    "sg:postcode":"2030",
    "sg:province":"Antwerpen",
    "wof:name":"Marpobel",
    "wof:placetype":"venue"
},
  "geometry": {"coordinates":[4.3614268303,51.2570419312],"type":"Point"}
}