{
  "type": "Feature",
  "properties": {
    "addr:full":"Vitshoekstraat 1033haven Zwijndrecht Antwerpen 2070",
    "addr:postcode":"2070",
    "addr:street":"Vitshoekstraat 1033Haven",
    "iso:country":"BE",
    "sg:address":"Vitshoekstraat 1033haven",
    "sg:city":"Zwijndrecht",
    "sg:classifiers":[
        {
            "category":"Government",
            "subcategory":"Fire Station",
            "type":"Public Place"
        }
    ],
    "sg:phone":"+32 3 234 95 55",
    "sg:postcode":"2070",
    "sg:province":"Antwerpen",
    "sg:tags":[
        "extinguisher"
    ],
    "wof:name":"Euro Safe",
    "wof:placetype":"venue"
},
  "geometry": {"coordinates":[4.326734066,51.2184944153],"type":"Point"}
}