{
  "type": "Feature",
  "properties": {
    "iso:country":"BE",
    "sg:address":"Rue J. Wauters 44",
    "sg:city":"Waremme",
    "sg:orig_category":"V\u00eatements pour Dames. Articles pour b\u00e9b\u00e9s. V\u00eatements pour b\u00e9b\u00e9s and enfants",
    "sg:phone":"+32 19 32 33 02",
    "sg:postcode":"4300",
    "sg:province":"Li\u00e8ge",
    "wof:name":"Pr\u00c9maman",
    "wof:placetype":"venue"
},
  "geometry": {"coordinates":[5.2531528473,50.6959037781],"type":"Point"}
}