{
  "type": "Feature",
  "properties": {
    "addr:full":"Bekerstraat 3 Kinrooi Limburg 3640",
    "addr:housenumber":"3",
    "addr:postcode":"3640",
    "addr:street":"Bekerstraat",
    "iso:country":"BE",
    "sg:address":"Bekerstraat 3",
    "sg:city":"Kinrooi",
    "sg:classifiers":[
        {
            "category":"Cafe",
            "type":"Food & Drink"
        }
    ],
    "sg:phone":"+32 89 70 12 03",
    "sg:postcode":"3640",
    "sg:province":"Limburg",
    "sg:tags":[
        "caf\u00e9s"
    ],
    "wof:name":"Leonardus Van Mierlo",
    "wof:placetype":"venue"
},
  "geometry": {"coordinates":[5.7692670822,51.1689147949],"type":"Point"}
}