{
  "type": "Feature",
  "properties": {
    "addr:full":"Aalsterse Steenweg 112 Aalst (moorsel) Oost-Vlaanderen 9310",
    "addr:housenumber":"112",
    "addr:postcode":"9310",
    "addr:street":"Steenweg;Moorsel Oost-Vlaanderen",
    "iso:country":"BE",
    "sg:address":"Aalsterse Steenweg 112",
    "sg:city":"Aalst (moorsel)",
    "sg:classifiers":[
        {
            "category":"Personal",
            "subcategory":"Beauty Salon",
            "type":"Services"
        }
    ],
    "sg:phone":"+32 53 21 47 12",
    "sg:postcode":"9310",
    "sg:province":"Oost-Vlaanderen",
    "wof:name":"Betty",
    "wof:placetype":"venue"
},
  "geometry": {"coordinates":[4.098400116,50.9477767944],"type":"Point"}
}