{
  "type": "Feature",
  "properties": {
    "addr:full":"Bois D'olne 22h Olne Li\u00e8ge 4877",
    "addr:postcode":"4877",
    "iso:country":"BE",
    "sg:address":"Bois D'olne 22h",
    "sg:city":"Olne",
    "sg:orig_category":"Non-Classified Establishments",
    "sg:phone":"+32 87 26 78 86",
    "sg:postcode":"4877",
    "sg:province":"Li\u00e8ge",
    "wof:name":"Crosset R",
    "wof:placetype":"venue"
},
  "geometry": {"coordinates":[5.7579078674,50.5803947449],"type":"Point"}
}