{
  "type": "Feature",
  "properties": {
    "addr:full":"Chauss\u00e9e De Bruxelles 163 Braine-le-comte Hainaut 7090",
    "addr:housenumber":"163",
    "addr:postcode":"7090",
    "addr:street":"Chausse\u0301E De Bruxelles",
    "iso:country":"BE",
    "sg:address":"Chauss\u00e9e De Bruxelles 163",
    "sg:city":"Braine-le-comte",
    "sg:classifiers":[
        {
            "category":"Building & Trades",
            "subcategory":"Landscaping Services",
            "type":"Services"
        }
    ],
    "sg:phone":"+32 67 55 20 46",
    "sg:postcode":"7090",
    "sg:province":"Hainaut",
    "sg:tags":[
        "gardening",
        "garden",
        "maintenance"
    ],
    "wof:name":"Linea Hortus Bvba",
    "wof:placetype":"venue"
},
  "geometry": {"coordinates":[4.1472997665,50.6296463013],"type":"Point"}
}