{
  "type": "Feature",
  "properties": {
    "addr:full":"Chauss\u00c9e De Namur 23 Eghezee Namur 5310",
    "addr:housenumber":"23",
    "addr:postcode":"5310",
    "addr:street":"Chausse\u0301E De Namur;Namur",
    "iso:country":"BE",
    "sg:address":"Chauss\u00c9e De Namur 23",
    "sg:city":"Eghezee",
    "sg:orig_category":"Pain, p\u00e2tisseries and confiseries",
    "sg:phone":"+32 81 81 24 08",
    "sg:postcode":"5310",
    "sg:province":"Namur",
    "wof:name":"Leonidas",
    "wof:placetype":"venue"
},
  "geometry": {"coordinates":[4.912571907,50.5894508362],"type":"Point"}
}