{
  "type": "Feature",
  "properties": {
    "iso:country":"BE",
    "sg:address":"Ledebergstraat 1",
    "sg:city":"Gent",
    "sg:classifiers":[
        {
            "category":"Food & Beverages",
            "subcategory":"Fruits & Vegetables",
            "type":"Retail Goods"
        }
    ],
    "sg:phone":"+32 9 231 26 75",
    "sg:postcode":"9050",
    "sg:province":"Oost-Vlaanderen",
    "sg:tags":[
        "l\u00e9gumes"
    ],
    "wof:name":"Huis Chreron",
    "wof:placetype":"venue"
},
  "geometry": {"coordinates":[3.7413160801,51.0368537903],"type":"Point"}
}