{
  "type": "Feature",
  "properties": {
    "addr:full":"Korte Steenstraat 7 Kortrijk West-Vlaanderen 8500",
    "addr:housenumber":"7",
    "addr:postcode":"8500",
    "addr:street":"Korte Steenstraat",
    "iso:country":"BE",
    "sg:address":"Korte Steenstraat 7",
    "sg:city":"Kortrijk",
    "sg:orig_category":"V\u00eatements",
    "sg:phone":"+32 56 22 23 67",
    "sg:postcode":"8500",
    "sg:province":"West-Vlaanderen",
    "wof:name":"Sporthome",
    "wof:placetype":"venue"
},
  "geometry": {"coordinates":[3.2674760818,50.8273353577],"type":"Point"}
}