{
  "type": "Feature",
  "properties": {
    "addr:full":"Rue De La Closi\u00c8re 8 Sambreville Namur 5060",
    "addr:housenumber":"8",
    "addr:postcode":"5060",
    "addr:street":"Rue De La Closie\u0300Re",
    "iso:country":"BE",
    "sg:address":"Rue De La Closi\u00c8re 8",
    "sg:city":"Sambreville",
    "sg:orig_category":"Experts-comptables",
    "sg:phone":"+32 71 76 08 19",
    "sg:postcode":"5060",
    "sg:province":"Namur",
    "wof:name":"Aldo D'alonzo",
    "wof:placetype":"venue"
},
  "geometry": {"coordinates":[4.5863552094,50.4435386658],"type":"Point"}
}