{
  "type": "Feature",
  "properties": {
    "iso:country":"BE",
    "sg:address":"217",
    "sg:city":"Oostrozebekestraat 8770 Ingelmunster",
    "sg:classifiers":[
        {
            "category":"Farming",
            "subcategory":"Fish & Marine Products",
            "type":"Manufacturing & Wholesale Goods"
        }
    ],
    "sg:phone":"+32 51 63 40 90",
    "sg:postcode":"217",
    "sg:tags":[
        "livestock",
        "food",
        "related",
        "fruit",
        "vegetable",
        "agriculture"
    ],
    "wof:name":"Chamdella Bvba",
    "wof:placetype":"venue"
},
  "geometry": {"coordinates":[3.2560250759,50.9203109741],"type":"Point"}
}