{
  "type": "Feature",
  "properties": {
    "iso:country":"BE",
    "sg:address":"Rue Maredret 11",
    "sg:city":"Mettet",
    "sg:classifiers":[
        {
            "category":"Restaurant",
            "type":"Food & Drink"
        }
    ],
    "sg:phone":"+32 71 72 57 89",
    "sg:postcode":"5564",
    "sg:province":"Namur",
    "wof:name":"Le Molign'art",
    "wof:placetype":"venue"
},
  "geometry": {"coordinates":[5.0614261627,50.1595497131],"type":"Point"}
}