{
  "type": "Feature",
  "properties": {
    "addr:full":"Rue Mac Donald 143 Jemappes Hainaut 7012",
    "addr:housenumber":"143",
    "addr:postcode":"7012",
    "addr:street":"Rue Mac Donald;Hainaut",
    "iso:country":"BE",
    "sg:address":"Rue Mac Donald 143",
    "sg:city":"Jemappes",
    "sg:classifiers":[
        {
            "category":"Organizations",
            "subcategory":"Labor Organization",
            "type":"Services"
        }
    ],
    "sg:phone":"+32 65 88 64 64",
    "sg:postcode":"7012",
    "sg:province":"Hainaut",
    "sg:tags":[
        "work",
        "assembling",
        "assembly",
        "contract"
    ],
    "wof:name":"Instrumelec S.a.",
    "wof:placetype":"venue"
},
  "geometry": {"coordinates":[3.8945109844,50.4520606995],"type":"Point"}
}