{
  "type": "Feature",
  "properties": {
    "iso:country":"BE",
    "sg:address":"Rue De Lannoy 44",
    "sg:city":"Pecq",
    "sg:classifiers":[
        {
            "category":"Bakery",
            "type":"Food & Drink"
        }
    ],
    "sg:phone":"+32 69 55 61 87",
    "sg:postcode":"7740",
    "sg:province":"Hainaut",
    "sg:tags":[
        "confectioner",
        "baker"
    ],
    "wof:name":"Bousmar M",
    "wof:placetype":"venue"
},
  "geometry": {"coordinates":[3.3358750343,50.685836792],"type":"Point"}
}