{
  "type": "Feature",
  "properties": {
    "iso:country":"BE",
    "sg:address":"Pannenbakkersstraat 4",
    "sg:city":"Zwevegem",
    "sg:orig_category":"Rev\u00eatements pour sols and murs. Rev\u00eatements de sols and murs",
    "sg:phone":"+32 56 75 91 51",
    "sg:postcode":"8552",
    "wof:name":"Beyaert",
    "wof:placetype":"venue"
},
  "geometry": {"coordinates":[3.3652529716,50.7968101501],"type":"Point"}
}