{
  "type": "Feature",
  "properties": {
    "iso:country":"BE",
    "sg:address":"Holleweg 13",
    "sg:city":"Maldegem",
    "sg:orig_category":"Varkenskwekers",
    "sg:phone":"+32 50 71 30 29",
    "sg:postcode":"9990",
    "sg:province":"Oost-Vlaanderen",
    "wof:name":"Firmin Van De Ginste",
    "wof:placetype":"venue"
},
  "geometry": {"coordinates":[3.4245240688,51.1845474243],"type":"Point"}
}