{
  "type": "Feature",
  "properties": {
    "iso:country":"BE",
    "sg:address":"Kronevoordestraat 44",
    "sg:city":"Kortemark",
    "sg:classifiers":[
        {
            "category":"Personal",
            "subcategory":"Beauty Salon",
            "type":"Services"
        }
    ],
    "sg:phone":"+32 51 56 76 75",
    "sg:postcode":"8610",
    "sg:province":"West-Vlaanderen",
    "sg:tags":[
        "de",
        "coiffure"
    ],
    "wof:name":"Coiffure Christine",
    "wof:placetype":"venue"
},
  "geometry": {"coordinates":[3.0031089783,51.0225868225],"type":"Point"}
}