{
  "type": "Feature",
  "properties": {
    "iso:country":"BE",
    "sg:address":"Rue De Schaerbeek 26",
    "sg:city":"Houffalize",
    "sg:orig_category":"Industri\u00eble and commerci\u00eble bouw Installatie van houten of kunststof schrijnwerk Woningbouw",
    "sg:phone":"+32 61 28 80 95",
    "sg:postcode":"6660",
    "sg:province":"Luxembourg",
    "wof:name":"Sacma",
    "wof:placetype":"venue"
},
  "geometry": {"coordinates":[5.7900681496,50.1312713623],"type":"Point"}
}