{
  "type": "Feature",
  "properties": {
    "iso:country":"BE",
    "sg:address":"Rue Fernand Stilmant 37",
    "sg:city":"Farciennes",
    "sg:orig_category":"M\u00e9decins and sp\u00e9cialistes",
    "sg:phone":"+32 71 38 59 33",
    "sg:postcode":"6240",
    "sg:province":"Hainaut",
    "wof:name":"Michel Toussaint",
    "wof:placetype":"venue"
},
  "geometry": {"coordinates":[4.5320539474,50.4232254028],"type":"Point"}
}