{
  "type": "Feature",
  "properties": {
    "addr:full":"Quai Du Sud 1 Charleroi (marchienne-au-pont) Hainaut 6030",
    "addr:housenumber":"1",
    "addr:postcode":"6030",
    "addr:street":"Quai Du Sud",
    "iso:country":"BE",
    "sg:address":"Quai Du Sud 1",
    "sg:city":"Charleroi (marchienne-au-pont)",
    "sg:classifiers":[
        {
            "category":"Social Services",
            "type":"Services"
        }
    ],
    "sg:phone":"+32 71 51 66 62",
    "sg:postcode":"6030",
    "sg:province":"Hainaut",
    "wof:name":"Bateau Chapelle",
    "wof:placetype":"venue"
},
  "geometry": {"coordinates":[4.3956131935,50.4077453613],"type":"Point"}
}