{
  "type": "Feature",
  "properties": {
    "addr:full":"Rue Remy-himmer 107 Dinant Namur 5500",
    "addr:housenumber":"107",
    "addr:postcode":"5500",
    "addr:street":"Rue Remy-Himmer",
    "iso:country":"BE",
    "sg:address":"Rue Remy-himmer 107",
    "sg:city":"Dinant",
    "sg:orig_category":"Plomberie, chauffage and installations sanitaires",
    "sg:phone":"+32 82 22 63 85",
    "sg:postcode":"5500",
    "sg:province":"Namur",
    "wof:name":"Georges Delcroix",
    "wof:placetype":"venue"
},
  "geometry": {"coordinates":[4.9541101456,50.2747116089],"type":"Point"}
}