{
  "type": "Feature",
  "properties": {
    "iso:country":"BE",
    "sg:address":"Rue Simon 14",
    "sg:city":"Hotton",
    "sg:classifiers":[
        {
            "category":"Education",
            "subcategory":"Library",
            "type":"Public Place"
        }
    ],
    "sg:phone":"+32 84 36 78 42",
    "sg:postcode":"6990",
    "sg:province":"Luxembourg",
    "wof:name":"Bibliotheque-ludotheque",
    "wof:placetype":"venue"
},
  "geometry": {"coordinates":[5.4483909607,50.2665481567],"type":"Point"}
}