{
  "type": "Feature",
  "properties": {
    "addr:full":"Veurnseweg 16 Ieper West-Vlaanderen 8900",
    "addr:housenumber":"16",
    "addr:postcode":"8900",
    "addr:street":"Veurnseweg",
    "iso:country":"BE",
    "sg:address":"Veurnseweg 16",
    "sg:city":"Ieper",
    "sg:classifiers":[
        {
            "category":"Restaurant",
            "type":"Food & Drink"
        }
    ],
    "sg:phone":"+32 57 20 81 05",
    "sg:postcode":"8900",
    "sg:province":"West-Vlaanderen",
    "wof:name":"In De Rustplaats",
    "wof:placetype":"venue"
},
  "geometry": {"coordinates":[2.8621668816,50.8632240295],"type":"Point"}
}