{
  "type": "Feature",
  "properties": {
    "iso:country":"BE",
    "sg:address":"Rue Achille Delattre 47",
    "sg:city":"Boussu",
    "sg:orig_category":"Kapsalons",
    "sg:phone":"+32 65 65 38 89",
    "sg:postcode":"7300",
    "sg:province":"Hainaut",
    "wof:name":"Coiffure Christiane",
    "wof:placetype":"venue"
},
  "geometry": {"coordinates":[3.7915151119,50.4140167236],"type":"Point"}
}