{
  "type": "Feature",
  "properties": {
    "addr:full":"Zeedijk 175 Middelkerke West-Vlaanderen 8430",
    "addr:housenumber":"175",
    "addr:postcode":"8430",
    "addr:street":"Zeedijk",
    "iso:country":"BE",
    "sg:address":"Zeedijk 175",
    "sg:city":"Middelkerke",
    "sg:classifiers":[
        {
            "category":"Tea Room",
            "subcategory":"None",
            "type":"Food & Drink"
        }
    ],
    "sg:phone":"+32 59 30 42 54",
    "sg:postcode":"8430",
    "sg:province":"West-Vlaanderen",
    "wof:name":"Bonbini",
    "wof:placetype":"venue"
},
  "geometry": {"coordinates":[2.8082480431,51.1851997375],"type":"Point"}
}