{
  "type": "Feature",
  "properties": {
    "addr:full":"Bosstraat 17 Bilzen Limburg 3740",
    "addr:housenumber":"17",
    "addr:postcode":"3740",
    "addr:street":"Bosstraat",
    "iso:country":"BE",
    "sg:address":"Bosstraat 17",
    "sg:city":"Bilzen",
    "sg:orig_category":"R\u00e9alisation de programmes and logiciels",
    "sg:phone":"+32 475 29 35 47",
    "sg:postcode":"3740",
    "sg:province":"Limburg",
    "wof:name":"Softpcs",
    "wof:placetype":"venue"
},
  "geometry": {"coordinates":[5.5731368065,50.8438415527],"type":"Point"}
}