{
  "type": "Feature",
  "properties": {
    "iso:country":"BE",
    "sg:address":"Affligemdreef 36",
    "sg:city":"Aalst",
    "sg:classifiers":[
        {
            "category":"Health Services",
            "subcategory":"Health Practitioner",
            "type":"Services"
        }
    ],
    "sg:phone":"+32 53 78 08 07",
    "sg:postcode":"9300",
    "sg:province":"Oost-Vlaanderen",
    "sg:tags":[
        "physiotherapist"
    ],
    "wof:name":"Evenepoel Luc",
    "wof:placetype":"venue"
},
  "geometry": {"coordinates":[4.063021183,50.9335174561],"type":"Point"}
}