{
  "type": "Feature",
  "properties": {
    "addr:full":"Hyacintenlaan 17 Schaarbeek/schaerbeek Bruxelles-Capitale 1030",
    "addr:housenumber":"17",
    "addr:postcode":"1030",
    "addr:street":"Hyacintenlaan",
    "iso:country":"BE",
    "sg:address":"Hyacintenlaan 17",
    "sg:city":"Schaarbeek/schaerbeek",
    "sg:orig_category":"Immobili\u00ebnkantoren",
    "sg:phone":"+32 2 216 06 04",
    "sg:postcode":"1030",
    "sg:province":"Bruxelles-Capitale",
    "wof:name":"Immo Lambermont",
    "wof:placetype":"venue"
},
  "geometry": {"coordinates":[4.3890519142,50.8628959656],"type":"Point"}
}