{
  "type": "Feature",
  "properties": {
    "iso:country":"BE",
    "sg:address":"Avenue De Stalingrad 52",
    "sg:city":"Bruxelles",
    "sg:classifiers":[
        {
            "category":"Social Services",
            "type":"Services"
        }
    ],
    "sg:phone":"+32 2 646 63 74",
    "sg:postcode":"1000",
    "sg:province":"Bruxelles-Capitale",
    "wof:name":"Causes Communes",
    "wof:placetype":"venue"
},
  "geometry": {"coordinates":[4.3441109657,50.8411827087],"type":"Point"}
}