{
  "type": "Feature",
  "properties": {
    "addr:full":"Avenue De Messidor 101 Bruxelles (uccle) Bruxelles-Capitale 1180",
    "addr:housenumber":"101",
    "addr:postcode":"1180",
    "addr:street":"Avenue De Messidor",
    "iso:country":"BE",
    "sg:address":"Avenue De Messidor 101",
    "sg:city":"Bruxelles (uccle)",
    "sg:classifiers":[
        {
            "category":"Health Services",
            "subcategory":"Doctor",
            "type":"Services"
        }
    ],
    "sg:phone":"+32 2 344 54 81",
    "sg:postcode":"1180",
    "sg:province":"Bruxelles-Capitale",
    "sg:tags":[
        "medicinephysicians",
        "surgeon"
    ],
    "wof:name":"Bruyns Jean",
    "wof:placetype":"venue"
},
  "geometry": {"coordinates":[4.3411641121,50.8099746704],"type":"Point"}
}