{
  "type": "Feature",
  "properties": {
    "addr:full":"Place Jules Seeliger 7 Li\u00c8ge Li\u00e8ge 4000",
    "addr:housenumber":"7",
    "addr:postcode":"4000",
    "addr:street":"Place Jules Seeliger",
    "iso:country":"BE",
    "sg:address":"Place Jules Seeliger 7",
    "sg:city":"Li\u00c8ge",
    "sg:classifiers":[
        {
            "category":"Personal",
            "subcategory":"Beauty Salon",
            "type":"Services"
        }
    ],
    "sg:phone":"+32 4 226 45 91",
    "sg:postcode":"4000",
    "sg:province":"Li\u00e8ge",
    "sg:tags":[
        "de",
        "coiffure"
    ],
    "wof:name":"Coiffure Josiane",
    "wof:placetype":"venue"
},
  "geometry": {"coordinates":[5.5614538193,50.6575202942],"type":"Point"}
}