{
  "type": "Feature",
  "properties": {
    "iso:country":"BE",
    "sg:address":"Kleine Tapuitstraat",
    "sg:city":"Deerlijk",
    "sg:orig_category":"Beheer van afvalopslag- and stortplaatsen",
    "sg:phone":"+32 56 77 89 00",
    "sg:postcode":"8540",
    "sg:province":"West-Vlaanderen",
    "wof:name":"Containerpark Deerlijk",
    "wof:placetype":"venue"
},
  "geometry": {"coordinates":[3.3518950939,50.84192276],"type":"Point"}
}