{
  "type": "Feature",
  "properties": {
    "addr:full":"Sint-martensstraat 5 Ronse/renaix Oost-Vlaanderen 9600",
    "addr:housenumber":"5",
    "addr:postcode":"9600",
    "addr:street":"Sint-Martensstraat",
    "iso:country":"BE",
    "sg:address":"Sint-martensstraat 5",
    "sg:city":"Ronse/renaix",
    "sg:orig_category":"Herstelling horloges and juwelen Juwelen and horloges",
    "sg:phone":"+32 55 21 44 78",
    "sg:postcode":"9600",
    "sg:province":"Oost-Vlaanderen",
    "wof:name":"Vandenhoucke Paul",
    "wof:placetype":"venue"
},
  "geometry": {"coordinates":[3.5992999077,50.7470397949],"type":"Point"}
}