{
  "type": "Feature",
  "properties": {
    "addr:full":"Hoek 76 Boom Antwerpen 2850",
    "addr:housenumber":"76",
    "addr:postcode":"2850",
    "addr:street":"Hoek",
    "iso:country":"BE",
    "sg:address":"Hoek 76",
    "sg:city":"Boom",
    "sg:classifiers":[
        {
            "category":"Banks & Credit Unions",
            "subcategory":"Investment Brokerage",
            "type":"Services"
        }
    ],
    "sg:phone":"+32 3 888 54 34",
    "sg:postcode":"2850",
    "sg:province":"Antwerpen",
    "sg:tags":[
        "-",
        "sale",
        "yachts",
        "accessory",
        "pleasure",
        "boat"
    ],
    "wof:name":"Ukiyo Nv",
    "wof:placetype":"venue"
},
  "geometry": {"coordinates":[4.3774271011,51.0845031738],"type":"Point"}
}