{
  "type": "Feature",
  "properties": {
    "addr:full":"Belingstraat 27 Sint-truiden (brustem) Limburg 3800",
    "addr:housenumber":"27",
    "addr:postcode":"3800",
    "addr:street":"Belingstraat",
    "iso:country":"BE",
    "sg:address":"Belingstraat 27",
    "sg:city":"Sint-truiden (brustem)",
    "sg:classifiers":[
        {
            "category":"Retail",
            "subcategory":"Veterinary Services",
            "type":"Services"
        }
    ],
    "sg:phone":"+32 11 68 47 76",
    "sg:postcode":"3800",
    "sg:province":"Limburg",
    "sg:tags":[
        "veterinarian"
    ],
    "wof:name":"Schellis C",
    "wof:placetype":"venue"
},
  "geometry": {"coordinates":[5.2158460617,50.7923583984],"type":"Point"}
}