{
  "type": "Feature",
  "properties": {
    "addr:full":"Kwakstraat 6 Sint-martens-latem Oost-Vlaanderen 9830",
    "addr:housenumber":"6",
    "addr:postcode":"9830",
    "addr:street":"Kwakstraat",
    "iso:country":"BE",
    "sg:address":"Kwakstraat 6",
    "sg:city":"Sint-martens-latem",
    "sg:orig_category":"M\u00e9decins and sp\u00e9cialistes",
    "sg:phone":"+32 9 282 83 09",
    "sg:postcode":"9830",
    "sg:province":"Oost-Vlaanderen",
    "wof:name":"Michel Maere",
    "wof:placetype":"venue"
},
  "geometry": {"coordinates":[3.6322309971,51.0230941772],"type":"Point"}
}