{
  "type": "Feature",
  "properties": {
    "iso:country":"BE",
    "sg:address":"Leopoldstraat 38bb",
    "sg:city":"Zemst",
    "sg:classifiers":[
        {
            "category":"Food & Beverages",
            "subcategory":"Fruits & Vegetables",
            "type":"Retail Goods"
        }
    ],
    "sg:phone":"+32 15 61 25 36",
    "sg:postcode":"1980",
    "sg:province":"Vlaams-Brabant",
    "sg:tags":[
        "l\u00e9gumes"
    ],
    "wof:name":"Wouters W D M",
    "wof:placetype":"venue"
},
  "geometry": {"coordinates":[4.4614300728,50.9835319519],"type":"Point"}
}