{
  "type": "Feature",
  "properties": {
    "iso:country":"BE",
    "sg:address":"Rue Ferrer 150",
    "sg:city":"Charleroi",
    "sg:orig_category":"Restaurants Zuivelproducten",
    "sg:phone":"+32 71 32 60 84",
    "sg:postcode":"6061",
    "sg:province":"Hainaut",
    "wof:name":"Gerard Devilers",
    "wof:placetype":"venue"
},
  "geometry": {"coordinates":[4.4683361053,50.4109420776],"type":"Point"}
}