{
  "type": "Feature",
  "properties": {
    "iso:country":"BE",
    "sg:address":"'t Helleke 1",
    "sg:city":"Kortrijk",
    "sg:orig_category":"Agences immobili\u00e8res",
    "sg:phone":"+32 56 22 76 44",
    "sg:postcode":"8500",
    "sg:province":"West-Vlaanderen",
    "wof:name":"Promibo",
    "wof:placetype":"venue"
},
  "geometry": {"coordinates":[3.2423360348,50.793384552],"type":"Point"}
}