{
  "type": "Feature",
  "properties": {
    "addr:full":"Bergense Steenweg 1023 Anderlecht Bruxelles-Capitale 1070",
    "addr:postcode":"1023;1070",
    "addr:street":"Bergense Steenweg",
    "iso:country":"BE",
    "sg:address":"Bergense Steenweg 1023",
    "sg:city":"Anderlecht",
    "sg:orig_category":"Fotogravure and zetwerk",
    "sg:phone":"+32 2 524 38 12",
    "sg:postcode":"1070",
    "sg:province":"Bruxelles-Capitale",
    "wof:name":"Fe. Ecoprint",
    "wof:placetype":"venue"
},
  "geometry": {"coordinates":[4.2973480225,50.825252533],"type":"Point"}
}