{
  "type": "Feature",
  "properties": {
    "addr:full":"Generaal De Wittelaan 1-2 Mechelen Antwerpen 2800",
    "addr:housenumber":"1-2",
    "addr:postcode":"2800",
    "addr:street":"Generaal De Wittelaan",
    "iso:country":"BE",
    "sg:address":"Generaal De Wittelaan 1-2",
    "sg:city":"Mechelen",
    "sg:classifiers":[
        {
            "category":"Community Center",
            "subcategory":"Youth",
            "type":"Public Place"
        }
    ],
    "sg:phone":"+32 15 44 62 40",
    "sg:postcode":"2800",
    "sg:province":"Antwerpen",
    "sg:tags":[
        "workshop",
        "sheltered"
    ],
    "wof:name":"Beschermde Werkplaats Mechelen Vzw",
    "wof:placetype":"venue"
},
  "geometry": {"coordinates":[4.456152916,51.0585365295],"type":"Point"}
}