{
  "type": "Feature",
  "properties": {
    "iso:country":"BE",
    "sg:address":"Rue Fran\u00c7ois Dorz\u00c9e 28",
    "sg:city":"Boussu",
    "sg:orig_category":"V\u00eatements pour b\u00e9b\u00e9s and enfants",
    "sg:phone":"+32 65 79 44 85",
    "sg:postcode":"7300",
    "sg:province":"Hainaut",
    "wof:name":"Maison Carden Junior",
    "wof:placetype":"venue"
},
  "geometry": {"coordinates":[3.7982809544,50.4335975647],"type":"Point"}
}