{
  "type": "Feature",
  "properties": {
    "addr:full":"Heirweg 5 Maldegem Oost-Vlaanderen 9990",
    "addr:housenumber":"5",
    "addr:postcode":"9990",
    "addr:street":"Heirweg",
    "iso:country":"BE",
    "sg:address":"Heirweg 5",
    "sg:city":"Maldegem",
    "sg:orig_category":"Fiduciairies",
    "sg:phone":"+32 50 71 96 60",
    "sg:postcode":"9990",
    "sg:province":"Oost-Vlaanderen",
    "wof:name":"Herpelinck M",
    "wof:placetype":"venue"
},
  "geometry": {"coordinates":[3.4131710529,51.2092590332],"type":"Point"}
}