{
  "type": "Feature",
  "properties": {
    "addr:full":"Grendelbaan 100 Diepenbeek Limburg 3590",
    "addr:housenumber":"100",
    "addr:postcode":"3590",
    "addr:street":"Grendelbaan",
    "iso:country":"BE",
    "sg:address":"Grendelbaan 100",
    "sg:city":"Diepenbeek",
    "sg:orig_category":"Woningbouw",
    "sg:phone":"+32 11 32 42 94",
    "sg:postcode":"3590",
    "sg:province":"Limburg",
    "wof:name":"Pieter Caubergh",
    "wof:placetype":"venue"
},
  "geometry": {"coordinates":[5.4421100616,50.9009284973],"type":"Point"}
}