{
  "type": "Feature",
  "properties": {
    "iso:country":"BE",
    "sg:address":"Rue Entre Deux-ris 18",
    "sg:city":"Oupeye (haccourt)",
    "sg:classifiers":[
        {
            "category":"Building & Trades",
            "subcategory":"Landscaping Services",
            "type":"Services"
        }
    ],
    "sg:phone":"+32 4 379 73 04",
    "sg:postcode":"4684",
    "sg:province":"Li\u00e8ge",
    "sg:tags":[
        "handicraft"
    ],
    "wof:name":"Graphil Sprl",
    "wof:placetype":"venue"
},
  "geometry": {"coordinates":[5.6733951569,50.7341957092],"type":"Point"}
}