{
  "type": "Feature",
  "properties": {
    "addr:full":"Monnikenredestraat 6 Damme West-Vlaanderen 8340",
    "addr:housenumber":"6",
    "addr:postcode":"8340",
    "addr:street":"Monnikenredestraat",
    "iso:country":"BE",
    "sg:address":"Monnikenredestraat 6",
    "sg:city":"Damme",
    "sg:classifiers":[
        {
            "category":"Restaurant",
            "type":"Food & Drink"
        }
    ],
    "sg:phone":"+32 50 62 51 52",
    "sg:postcode":"8340",
    "sg:province":"West-Vlaanderen",
    "wof:name":"De Krinkeldijk",
    "wof:placetype":"venue"
},
  "geometry": {"coordinates":[3.2815999985,51.2513160706],"type":"Point"}
}