{
  "type": "Feature",
  "properties": {
    "addr:full":"Zonnestraat 180 Ronse/renaix Oost-Vlaanderen 9600",
    "addr:housenumber":"180",
    "addr:postcode":"9600",
    "addr:street":"Zonnestraat",
    "iso:country":"BE",
    "sg:address":"Zonnestraat 180",
    "sg:city":"Ronse/renaix",
    "sg:classifiers":[
        {
            "category":"Cafe",
            "type":"Food & Drink"
        }
    ],
    "sg:phone":"+32 55 20 88 35",
    "sg:postcode":"9600",
    "sg:province":"Oost-Vlaanderen",
    "sg:tags":[
        "caf\u00e9s"
    ],
    "wof:name":"Caf\u00c9 L'oasis",
    "wof:placetype":"venue"
},
  "geometry": {"coordinates":[3.586220026,50.7490844727],"type":"Point"}
}