{
  "type": "Feature",
  "properties": {
    "iso:country":"BE",
    "sg:address":"Avenue Du Baleau 14",
    "sg:city":"Wavre",
    "sg:orig_category":"Plaatsen van vloer- and muurbekleding Schilders Textiel Verlichting and huishoudartikelen Vloer- and",
    "sg:phone":"+32 10 41 12 17",
    "sg:postcode":"1300",
    "sg:province":"Brabant Wallon",
    "wof:name":"Colophil",
    "wof:placetype":"venue"
},
  "geometry": {"coordinates":[4.5492892265,50.6911735535],"type":"Point"}
}