{
  "type": "Feature",
  "properties": {
    "iso:country":"BE",
    "sg:address":"Rue L. Mar\u00c9chal 46",
    "sg:city":"Oreye",
    "sg:orig_category":"HUISBRANDOLIE",
    "sg:phone":"+32 19 67 80 97",
    "sg:postcode":"4360",
    "sg:province":"Li\u00e8ge",
    "wof:name":"Courtoy",
    "wof:placetype":"venue"
},
  "geometry": {"coordinates":[5.3476371765,50.7248840332],"type":"Point"}
}