{
  "type": "Feature",
  "properties": {
    "iso:country":"BE",
    "sg:address":"Chauss\u00c9e De Renaix 140",
    "sg:city":"Lessines",
    "sg:orig_category":"Produits chimiques Gr",
    "sg:phone":"+32 68 33 75 23",
    "sg:postcode":"7860",
    "sg:province":"Hainaut",
    "wof:name":"Help Hygi\u00c8ne",
    "wof:placetype":"venue"
},
  "geometry": {"coordinates":[3.8186299801,50.7134819031],"type":"Point"}
}