{
  "type": "Feature",
  "properties": {
    "iso:country":"BE",
    "sg:address":"Hemmestraat 57",
    "sg:city":"Nieuwpoort (ramskapelle)",
    "sg:classifiers":[
        {
            "category":"Farming",
            "subcategory":"Farm & Veterinary Services",
            "type":"Manufacturing & Wholesale Goods"
        }
    ],
    "sg:phone":"+32 58 23 66 09",
    "sg:postcode":"8620",
    "sg:province":"West-Vlaanderen",
    "sg:tags":[
        "agricultural",
        "contractor"
    ],
    "wof:name":"Focquaert",
    "wof:placetype":"venue"
},
  "geometry": {"coordinates":[2.7823340893,51.1094322205],"type":"Point"}
}