{
  "type": "Feature",
  "properties": {
    "addr:full":"Rue De La Colline 91 Flemalle Li\u00e8ge 4400",
    "addr:housenumber":"91",
    "addr:postcode":"4400",
    "addr:street":"Rue De La Colline",
    "iso:country":"BE",
    "sg:address":"Rue De La Colline 91",
    "sg:city":"Flemalle",
    "sg:orig_category":"Paramedische behandelingen",
    "sg:phone":"+32 4 336 62 51",
    "sg:postcode":"4400",
    "sg:province":"Li\u00e8ge",
    "wof:name":"A. Parent",
    "wof:placetype":"venue"
},
  "geometry": {"coordinates":[5.4576430321,50.5693130493],"type":"Point"}
}