{
  "type": "Feature",
  "properties": {
    "iso:country":"BE",
    "sg:address":"Herentalse Steenweg 34",
    "sg:city":"Grobbendonk",
    "sg:orig_category":"Benzinestations and brandstoffen",
    "sg:phone":"+32 14 51 13 02",
    "sg:postcode":"2280",
    "sg:province":"Antwerpen",
    "wof:name":"Garage Autostrade",
    "wof:placetype":"venue"
},
  "geometry": {"coordinates":[4.754131794,51.1743087769],"type":"Point"}
}