{
  "type": "Feature",
  "properties": {
    "iso:country":"BE",
    "sg:address":"Rijksweg 318",
    "sg:city":"Wielsbeke",
    "sg:classifiers":[
        {
            "category":"Fast Food",
            "type":"Food & Drink"
        }
    ],
    "sg:phone":"+32 56 44 03 41",
    "sg:postcode":"8710",
    "sg:province":"West-Vlaanderen",
    "sg:tags":[
        "fried",
        "stand",
        "potato"
    ],
    "wof:name":"Frituur Evelyne",
    "wof:placetype":"venue"
},
  "geometry": {"coordinates":[3.3723199368,50.9102935791],"type":"Point"}
}