{
  "type": "Feature",
  "properties": {
    "addr:full":"Gentstraat 164 Oudenaarde Oost-Vlaanderen 9700",
    "addr:housenumber":"164",
    "addr:postcode":"9700",
    "addr:street":"Gentstraat",
    "iso:country":"BE",
    "sg:address":"Gentstraat 164",
    "sg:city":"Oudenaarde",
    "sg:orig_category":"Werk and personeelsselectie",
    "sg:phone":"+32 55 30 04 52",
    "sg:postcode":"9700",
    "sg:province":"Oost-Vlaanderen",
    "wof:name":"Kellens Consulting",
    "wof:placetype":"venue"
},
  "geometry": {"coordinates":[3.5994970798,50.8570709229],"type":"Point"}
}