{
  "type": "Feature",
  "properties": {
    "iso:country":"BE",
    "sg:address":"Waversesteenweg 1717",
    "sg:city":"Oudergem/auderghem",
    "sg:orig_category":"Slagers",
    "sg:phone":"+32 2 672 49 37",
    "sg:postcode":"1160",
    "sg:province":"Bruxelles-Capitale",
    "wof:name":"Boucherie Francies",
    "wof:placetype":"venue"
},
  "geometry": {"coordinates":[4.425743103,50.8165245056],"type":"Point"}
}