{
  "type": "Feature",
  "properties": {
    "iso:country":"BE",
    "sg:address":"Rue Des D\u00c9port\u00c9s 1bb",
    "sg:city":"Courcelles",
    "sg:orig_category":"Herstellingen and onderhoud van auto's Voertuigen",
    "sg:phone":"+32 71 46 22 22",
    "sg:postcode":"6180",
    "sg:province":"Hainaut",
    "wof:name":"J.w. Center",
    "wof:placetype":"venue"
},
  "geometry": {"coordinates":[4.3735971451,50.4635162354],"type":"Point"}
}