{
  "type": "Feature",
  "properties": {
    "addr:full":"Beemd 27 Sint-genesius-rode/rhode-saint-genese Vlaams-Brabant 1640",
    "addr:housenumber":"27",
    "addr:postcode":"1640",
    "addr:street":"Beemd",
    "iso:country":"BE",
    "sg:address":"Beemd 27",
    "sg:city":"Sint-genesius-rode/rhode-saint-genese",
    "sg:classifiers":[
        {
            "category":"Cafe",
            "type":"Food & Drink"
        }
    ],
    "sg:phone":"+32 2 380 38 68",
    "sg:postcode":"1640",
    "sg:province":"Vlaams-Brabant",
    "sg:tags":[
        "caf\u00e9s"
    ],
    "wof:name":"Luk Lerminiaux",
    "wof:placetype":"venue"
},
  "geometry": {"coordinates":[4.3317217827,50.7387313843],"type":"Point"}
}