{
  "type": "Feature",
  "properties": {
    "addr:full":"Berkenlaan 29 Harelbeke West-Vlaanderen 8530",
    "addr:housenumber":"29",
    "addr:postcode":"8530",
    "addr:street":"Berkenlaan",
    "iso:country":"BE",
    "sg:address":"Berkenlaan 29",
    "sg:city":"Harelbeke",
    "sg:orig_category":"Woningbouw",
    "sg:phone":"+32 56 70 08 93",
    "sg:postcode":"8530",
    "sg:province":"West-Vlaanderen",
    "wof:name":"Desimpelaere",
    "wof:placetype":"venue"
},
  "geometry": {"coordinates":[3.302642107,50.8440132141],"type":"Point"}
}