{
  "type": "Feature",
  "properties": {
    "addr:full":"Sparrenlaan 14 Brasschaat Antwerpen 2930",
    "addr:housenumber":"14",
    "addr:postcode":"2930",
    "addr:street":"Sparrenlaan",
    "iso:country":"BE",
    "sg:address":"Sparrenlaan 14",
    "sg:city":"Brasschaat",
    "sg:classifiers":[
        {
            "category":"Insurance",
            "subcategory":"Life Insurance",
            "type":"Services"
        }
    ],
    "sg:phone":"+32 3 652 10 15",
    "sg:postcode":"2930",
    "sg:province":"Antwerpen",
    "sg:tags":[
        "assurance"
    ],
    "wof:name":"Andr\u00c9 En Tom Geukens",
    "wof:placetype":"venue"
},
  "geometry": {"coordinates":[4.4586582184,51.2980232239],"type":"Point"}
}