{
  "type": "Feature",
  "properties": {
    "iso:country":"BE",
    "sg:address":"Rue De L'eglise 113",
    "sg:city":"Attert",
    "sg:orig_category":"Eleveurs de bovins",
    "sg:phone":"+32 63 22 68 40",
    "sg:postcode":"6717",
    "sg:province":"Luxembourg",
    "wof:name":"Lucien Schmit",
    "wof:placetype":"venue"
},
  "geometry": {"coordinates":[5.7262148857,49.7570838928],"type":"Point"}
}