{
  "type": "Feature",
  "properties": {
    "addr:full":"Paardenmarkt 92 Antwerpen Antwerpen 2000",
    "addr:housenumber":"92",
    "addr:postcode":"2000",
    "addr:street":"Paardenmarkt",
    "iso:country":"BE",
    "sg:address":"Paardenmarkt 92",
    "sg:city":"Antwerpen",
    "sg:orig_category":"Hoger onderwijs",
    "sg:phone":"+32 3 213 79 10",
    "sg:postcode":"2000",
    "sg:province":"Antwerpen",
    "wof:name":"Hogeschool Antwerpen",
    "wof:placetype":"venue"
},
  "geometry": {"coordinates":[4.413008213,51.2246780396],"type":"Point"}
}