{
  "type": "Feature",
  "properties": {
    "iso:country":"BE",
    "sg:address":"Bruggesteenweg 7",
    "sg:city":"Hooglede",
    "sg:orig_category":"Eleveurs de volaille",
    "sg:phone":"+32 51 72 56 45",
    "sg:postcode":"8830",
    "sg:province":"West-Vlaanderen",
    "wof:name":"Robrecht Casier",
    "wof:placetype":"venue"
},
  "geometry": {"coordinates":[3.0833160877,50.9789924622],"type":"Point"}
}