{
  "type": "Feature",
  "properties": {
    "addr:full":"Rue De La Grande Couture 2 Tournai (blandain - Hertain) Hainaut 7522",
    "addr:housenumber":"2",
    "addr:postcode":"7522",
    "addr:street":"Rue De La Grande Couture;Hainaut",
    "iso:country":"BE",
    "sg:address":"Rue De La Grande Couture 2",
    "sg:city":"Tournai (blandain - Hertain)",
    "sg:classifiers":[
        {
            "category":"Professional",
            "subcategory":"Lawyer & Legal Services",
            "type":"Services"
        }
    ],
    "sg:phone":"+32 69 64 65 00",
    "sg:postcode":"7522",
    "sg:province":"Hainaut",
    "sg:tags":[
        "notary"
    ],
    "wof:name":"Jacmin Edouard Soc Civ \u00e0 Forme De",
    "wof:placetype":"venue"
},
  "geometry": {"coordinates":[3.3004500866,50.6229057312],"type":"Point"}
}