{
  "type": "Feature",
  "properties": {
    "iso:country":"BE",
    "sg:address":"Felix Beernaertsplein 28",
    "sg:city":"Wetteren",
    "sg:orig_category":"Banken and kredietinstellingen",
    "sg:phone":"+32 9 369 38 43",
    "sg:postcode":"9230",
    "sg:province":"Oost-Vlaanderen",
    "wof:name":"Kbc",
    "wof:placetype":"venue"
},
  "geometry": {"coordinates":[3.8795619011,51.0027198792],"type":"Point"}
}