{
  "type": "Feature",
  "properties": {
    "addr:full":"Rue Des Capucins 9 Arlon Luxembourg 6700",
    "addr:housenumber":"9",
    "addr:postcode":"6700",
    "addr:street":"Rue Des Capucins",
    "iso:country":"BE",
    "sg:address":"Rue Des Capucins 9",
    "sg:city":"Arlon",
    "sg:orig_category":"R\u00e9parations de chaussures and articles en cuir. Maroquinerie and articles de voyage",
    "sg:phone":"+32 63 22 68 22",
    "sg:postcode":"6700",
    "sg:province":"Luxembourg",
    "wof:name":"Cordonnerie Du Centre",
    "wof:placetype":"venue"
},
  "geometry": {"coordinates":[5.8140058517,49.6842193604],"type":"Point"}
}