{
  "type": "Feature",
  "properties": {
    "addr:full":"Avenue De La F\u00e9condit\u00e9 76 Bruxelles (anderlecht) Bruxelles-Capitale 1070",
    "addr:housenumber":"76",
    "addr:postcode":"1070",
    "addr:street":"Avenue De La Fe\u0301Condite\u0301",
    "iso:country":"BE",
    "sg:address":"Avenue De La F\u00e9condit\u00e9 76",
    "sg:city":"Bruxelles (anderlecht)",
    "sg:classifiers":[
        {
            "category":"Building & Trades",
            "subcategory":"Pest Control",
            "type":"Services"
        }
    ],
    "sg:phone":"+32 2 521 68 61",
    "sg:postcode":"1070",
    "sg:province":"Bruxelles-Capitale",
    "sg:tags":[
        "painting",
        "contractor"
    ],
    "wof:name":"G.s. Decor",
    "wof:placetype":"venue"
},
  "geometry": {"coordinates":[4.2751321793,50.8380622864],"type":"Point"}
}