{
  "type": "Feature",
  "properties": {
    "iso:country":"BE",
    "sg:address":"Rue Du Gymnase 42",
    "sg:city":"Verviers",
    "sg:classifiers":[
        {
            "category":"Wholesale",
            "subcategory":"Music Publishers",
            "type":"Manufacturing & Wholesale Goods"
        }
    ],
    "sg:phone":"+32 87 33 74 54",
    "sg:postcode":"4800",
    "sg:province":"Li\u00e8ge",
    "wof:name":"Fraipont G",
    "wof:placetype":"venue"
},
  "geometry": {"coordinates":[5.8601279259,50.593875885],"type":"Point"}
}