{
  "type": "Feature",
  "properties": {
    "addr:full":"Rue Jean-martin Mar\u00e9chal 18 Verviers (ensival) Li\u00e8ge 4800",
    "addr:housenumber":"18",
    "addr:postcode":"4800",
    "addr:street":"Rue Jean-Martin Mare\u0301Chal",
    "iso:country":"BE",
    "sg:address":"Rue Jean-martin Mar\u00e9chal 18",
    "sg:city":"Verviers (ensival)",
    "sg:classifiers":[
        {
            "category":"Communications",
            "subcategory":"Film & Video Production",
            "type":"Services"
        }
    ],
    "sg:phone":"+32 87 31 60 54",
    "sg:postcode":"4800",
    "sg:province":"Li\u00e8ge",
    "sg:tags":[
        "hiring",
        "-"
    ],
    "wof:name":"Ensival Vid\u00e9o",
    "wof:placetype":"venue"
},
  "geometry": {"coordinates":[5.8594508171,50.5917663574],"type":"Point"}
}