{
  "type": "Feature",
  "properties": {
    "addr:full":"Zandstraat 207 Heusden-zolder Limburg 3550",
    "addr:housenumber":"207",
    "addr:postcode":"3550",
    "addr:street":"Zandstraat",
    "iso:country":"BE",
    "sg:address":"Zandstraat 207",
    "sg:city":"Heusden-zolder",
    "sg:orig_category":"Artsen and specialisten",
    "sg:phone":"+32 11 25 23 62",
    "sg:postcode":"3550",
    "sg:province":"Limburg",
    "wof:name":"Greet Vandebriel",
    "wof:placetype":"venue"
},
  "geometry": {"coordinates":[5.3025407791,50.9852523804],"type":"Point"}
}