{
  "type": "Feature",
  "properties": {
    "addr:full":"Lierseweg 108 Herentals Antwerpen 2200",
    "addr:housenumber":"108",
    "addr:postcode":"2200",
    "addr:street":"Lierseweg",
    "iso:country":"BE",
    "sg:address":"Lierseweg 108",
    "sg:city":"Herentals",
    "sg:orig_category":"Architecten Binnenhuisarchitecten",
    "sg:phone":"+32 14 22 07 55",
    "sg:postcode":"2200",
    "sg:province":"Antwerpen",
    "wof:name":"Studio Twee",
    "wof:placetype":"venue"
},
  "geometry": {"coordinates":[4.8247981071,51.1757926941],"type":"Point"}
}