{
  "type": "Feature",
  "properties": {
    "addr:full":"Hekkestraat 38 Dendermonde (grembergen) Oost-Vlaanderen 9200",
    "addr:housenumber":"38",
    "addr:postcode":"9200",
    "addr:street":"Hekkestraat",
    "iso:country":"BE",
    "sg:address":"Hekkestraat 38",
    "sg:city":"Dendermonde (grembergen)",
    "sg:classifiers":[
        {
            "category":"Personal",
            "subcategory":"Beauty Salon",
            "type":"Services"
        }
    ],
    "sg:phone":"+32 52 21 34 48",
    "sg:postcode":"9200",
    "sg:province":"Oost-Vlaanderen",
    "sg:tags":[
        "child",
        "-",
        "hairdressing"
    ],
    "wof:name":"Beirnaert N",
    "wof:placetype":"venue"
},
  "geometry": {"coordinates":[4.090323925,51.0554847717],"type":"Point"}
}