{
  "type": "Feature",
  "properties": {
    "addr:full":"Waterloose Steenweg 515 Elsene/ixelles Bruxelles-Capitale 1050",
    "addr:housenumber":"515",
    "addr:postcode":"1050",
    "addr:street":"Waterloose Steenweg",
    "iso:country":"BE",
    "sg:address":"Waterloose Steenweg 515",
    "sg:city":"Elsene/ixelles",
    "sg:orig_category":"Brood, gebak and snoepgoed Restaurants",
    "sg:phone":"+32 2 343 33 59",
    "sg:postcode":"1050",
    "sg:province":"Bruxelles-Capitale",
    "wof:name":"Le Pain Quotidien",
    "wof:placetype":"venue"
},
  "geometry": {"coordinates":[4.3596191406,50.8199806213],"type":"Point"}
}