{
  "type": "Feature",
  "properties": {
    "iso:country":"BE",
    "sg:address":"Rue Des Ch\u00e8vrefeuilles 8",
    "sg:city":"Aywaille",
    "sg:classifiers":[
        {
            "category":"Banks & Credit Unions",
            "subcategory":"Financial Services",
            "type":"Services"
        }
    ],
    "sg:phone":"+32 4 384 47 43",
    "sg:postcode":"4920",
    "sg:province":"Li\u00e8ge",
    "sg:tags":[
        "loan",
        "mortgage"
    ],
    "wof:name":"Bertrand Jules Sprl",
    "wof:placetype":"venue"
},
  "geometry": {"coordinates":[5.6556768417,50.4728851318],"type":"Point"}
}