{
  "type": "Feature",
  "properties": {
    "addr:full":"Damstraat 107 Moerbeke-waas Oost-Vlaanderen 9180",
    "addr:housenumber":"107",
    "addr:postcode":"9180",
    "addr:street":"Damstraat;Oost-Vlaanderen",
    "iso:country":"BE",
    "sg:address":"Damstraat 107",
    "sg:city":"Moerbeke-waas",
    "sg:orig_category":"Installation de menuiserie en bois and plastique",
    "sg:phone":"+32 478 65 72 33",
    "sg:postcode":"9180",
    "sg:province":"Oost-Vlaanderen",
    "wof:name":"Eric Celie",
    "wof:placetype":"venue"
},
  "geometry": {"coordinates":[3.9478878975,51.1724052429],"type":"Point"}
}