{
  "type": "Feature",
  "properties": {
    "addr:full":"Schakelstraat 43 Waregem West-Vlaanderen 8790",
    "addr:housenumber":"43",
    "addr:postcode":"8790",
    "addr:street":"Schakelstraat",
    "iso:country":"BE",
    "sg:address":"Schakelstraat 43",
    "sg:city":"Waregem",
    "sg:orig_category":"Maisons de repos and r\u00e9sidences",
    "sg:phone":"+32 56 62 99 32",
    "sg:postcode":"8790",
    "sg:province":"West-Vlaanderen",
    "wof:name":"Residentie Zonnetijd",
    "wof:placetype":"venue"
},
  "geometry": {"coordinates":[3.4328389168,50.8835525513],"type":"Point"}
}