{
  "type": "Feature",
  "properties": {
    "addr:full":"Stationsstraat 3a Nazareth (eke) Oost-Vlaanderen 9810",
    "addr:housenumber":"3a",
    "addr:postcode":"9810",
    "addr:street":"Stationsstraat",
    "iso:country":"BE",
    "sg:address":"Stationsstraat 3a",
    "sg:city":"Nazareth (eke)",
    "sg:classifiers":[
        {
            "category":"Real Estate",
            "subcategory":"Surveying",
            "type":"Services"
        }
    ],
    "sg:phone":"+32 9 243 81 10",
    "sg:postcode":"9810",
    "sg:province":"Oost-Vlaanderen",
    "sg:tags":[
        "surveyor",
        "land"
    ],
    "wof:name":"Vansteelandt B",
    "wof:placetype":"venue"
},
  "geometry": {"coordinates":[3.6425230503,50.9568214417],"type":"Point"}
}