{
  "type": "Feature",
  "properties": {
    "iso:country":"BE",
    "sg:address":"Beekveldstraat 14",
    "sg:city":"Zemst",
    "sg:orig_category":"Installation \u00e9lectrique r\u00e9sidentielle",
    "sg:phone":"+32 15 61 01 66",
    "sg:postcode":"1980",
    "sg:province":"Vlaams-Brabant",
    "wof:name":"Paulus Fr.-blommaert G.",
    "wof:placetype":"venue"
},
  "geometry": {"coordinates":[4.4365520477,50.9968452454],"type":"Point"}
}