{
  "type": "Feature",
  "properties": {
    "iso:country":"BE",
    "sg:address":"Rue De Nimy 7",
    "sg:city":"Mons",
    "sg:classifiers":[
        {
            "category":"Education",
            "subcategory":"University",
            "type":"Public Place"
        }
    ],
    "sg:phone":"+32 65 34 73 77",
    "sg:postcode":"7000",
    "sg:province":"Hainaut",
    "sg:tags":[
        "higher"
    ],
    "wof:name":"Conservatoire Royal De Musique",
    "wof:placetype":"venue"
},
  "geometry": {"coordinates":[3.9531440735,50.4553833008],"type":"Point"}
}