{
  "type": "Feature",
  "properties": {
    "iso:country":"BE",
    "sg:address":"Papegaaistraat 17",
    "sg:city":"Oostrozebeke",
    "sg:classifiers":[
        {
            "category":"Military Area",
            "subcategory":"Air Force Base",
            "type":"Public Place"
        }
    ],
    "sg:phone":"+32 475 51 99 93",
    "sg:postcode":"8780",
    "sg:province":"West-Vlaanderen",
    "sg:tags":[
        "water",
        "treatment"
    ],
    "wof:name":"Bayard Waterontharders/ De Clercq Patrick",
    "wof:placetype":"venue"
},
  "geometry": {"coordinates":[3.3528358936,50.9290771484],"type":"Point"}
}