{
  "type": "Feature",
  "properties": {
    "iso:country":"BE",
    "sg:address":"Koestraat 114 W",
    "sg:city":"Stekene",
    "sg:orig_category":"Woningbouw",
    "sg:phone":"+32 3 789 18 64",
    "sg:postcode":"9190",
    "sg:province":"Oost-Vlaanderen",
    "wof:name":"Van De Voorde S.",
    "wof:placetype":"venue"
},
  "geometry": {"coordinates":[4.0427942276,51.2077407837],"type":"Point"}
}