{
  "type": "Feature",
  "properties": {
    "iso:country":"BE",
    "sg:address":"Avenue Besme 93",
    "sg:city":"Vorst",
    "sg:orig_category":"Bouwmaterialen Gh",
    "sg:phone":"+32 2 345 39 59",
    "sg:postcode":"1190",
    "sg:province":"Bruxelles-Capitale",
    "wof:name":"Spray Color",
    "wof:placetype":"venue"
},
  "geometry": {"coordinates":[4.3398900032,50.8210945129],"type":"Point"}
}