{
  "type": "Feature",
  "properties": {
    "iso:country":"BE",
    "sg:address":"Andrimont 42",
    "sg:city":"Stoumont (la Gleize)",
    "sg:classifiers":[
        {
            "category":"Retail",
            "subcategory":"Event Space",
            "type":"Services"
        }
    ],
    "sg:phone":"+32 80 51 19 91",
    "sg:postcode":"4987",
    "sg:province":"Li\u00e8ge",
    "sg:tags":[
        "organisation"
    ],
    "wof:name":"Plein G",
    "wof:placetype":"venue"
},
  "geometry": {"coordinates":[5.8098897934,50.4056663513],"type":"Point"}
}