{
  "type": "Feature",
  "properties": {
    "iso:country":"BE",
    "sg:address":"Rue De Namur 37b Box 303",
    "sg:city":"Mont-saint-guibert",
    "sg:classifiers":[
        {
            "category":"Professional",
            "subcategory":"Management & Consulting",
            "type":"Services"
        }
    ],
    "sg:phone":"+32 10 24 23 14",
    "sg:postcode":"1435",
    "sg:province":"Brabant Wallon",
    "sg:tags":[
        "-",
        "processing",
        "data",
        "consultant"
    ],
    "wof:name":"J.s.n. Management & Consulting",
    "wof:placetype":"venue"
},
  "geometry": {"coordinates":[4.6099681854,50.6584434509],"type":"Point"}
}