{
  "type": "Feature",
  "properties": {
    "iso:country":"BE",
    "sg:address":"Rue De Li\u00e8ge 97",
    "sg:city":"Vis\u00e9 (lixhe)",
    "sg:classifiers":[
        {
            "category":"Parking",
            "subcategory":"Lot",
            "type":"Transportation"
        }
    ],
    "sg:phone":"+32 3 355 14 64",
    "sg:postcode":"4600",
    "sg:province":"Li\u00e8ge",
    "sg:tags":[
        "pneumatic",
        "automation"
    ],
    "wof:name":"Smc Pneumatics Nv",
    "wof:placetype":"venue"
},
  "geometry": {"coordinates":[4.9066038132,52.3776397705],"type":"Point"}
}