{
  "type": "Feature",
  "properties": {
    "addr:full":"Beekstraat 6 Ham (kwaadmechelen) Limburg 3945",
    "addr:housenumber":"6",
    "addr:postcode":"kwaadmechelen;3945",
    "addr:street":"Beekstraat",
    "iso:country":"BE",
    "sg:address":"Beekstraat 6",
    "sg:city":"Ham (kwaadmechelen)",
    "sg:classifiers":[
        {
            "category":"Professional",
            "subcategory":"Accounting & Tax Preparation",
            "type":"Services"
        }
    ],
    "sg:phone":"+32 13 67 57 02",
    "sg:postcode":"3945",
    "sg:province":"Limburg",
    "sg:tags":[
        "bookkeeper"
    ],
    "wof:name":"Stevens J & Co Boekhoudkantoor Bvba Bvba",
    "wof:placetype":"venue"
},
  "geometry": {"coordinates":[5.1776199341,51.1046104431],"type":"Point"}
}