{
  "type": "Feature",
  "properties": {
    "iso:country":"BE",
    "sg:address":"Schoolstraat 65",
    "sg:city":"Opwijk",
    "sg:orig_category":"Enseignement maternel and primaire",
    "sg:phone":"+32 52 35 87 22",
    "sg:postcode":"1745",
    "sg:province":"Vlaams-Brabant",
    "wof:name":"Bulo De Karekiet",
    "wof:placetype":"venue"
},
  "geometry": {"coordinates":[4.1825470924,50.9692077637],"type":"Point"}
}