{
  "type": "Feature",
  "properties": {
    "iso:country":"BE",
    "sg:address":"Wijngaardberg 38",
    "sg:city":"Balen",
    "sg:classifiers":[
        {
            "category":"Arena",
            "subcategory":"Sports Club",
            "type":"Entertainment"
        }
    ],
    "sg:phone":"+32 14 30 16 55",
    "sg:postcode":"2491",
    "sg:province":"Antwerpen",
    "sg:tags":[
        "de"
    ],
    "wof:name":"B.c. \u00b4t Fluimke",
    "wof:placetype":"venue"
},
  "geometry": {"coordinates":[5.1621751785,51.1364784241],"type":"Point"}
}