{
  "type": "Feature",
  "properties": {
    "iso:country":"BE",
    "sg:address":"Zwartkeeltjeslaan 5",
    "sg:city":"Oudergem/auderghem",
    "sg:orig_category":"Kinderopvang",
    "sg:phone":"+32 2 660 74 03",
    "sg:postcode":"1160",
    "sg:province":"Bruxelles-Capitale",
    "wof:name":"Cr\u00c8che Comme Dans Un R\u00cave",
    "wof:placetype":"venue"
},
  "geometry": {"coordinates":[4.4145140648,50.8204154968],"type":"Point"}
}