{
  "type": "Feature",
  "properties": {
    "addr:full":"Zandstraat 19 Oostkamp West-Vlaanderen 8020",
    "addr:housenumber":"19",
    "addr:postcode":"8020",
    "addr:street":"Zandstraat",
    "iso:country":"BE",
    "sg:address":"Zandstraat 19",
    "sg:city":"Oostkamp",
    "sg:orig_category":"Winkelinrichting and handelsuitrusting Gh",
    "sg:phone":"+32 50 27 93 97",
    "sg:postcode":"8020",
    "sg:province":"West-Vlaanderen",
    "wof:name":"Fa. Mera",
    "wof:placetype":"venue"
},
  "geometry": {"coordinates":[3.2184040546,51.0971832275],"type":"Point"}
}