{
  "type": "Feature",
  "properties": {
    "iso:country":"BE",
    "sg:address":"Minister Alfred De Taeyestraat 27",
    "sg:city":"Zwevegem",
    "sg:classifiers":[
        {
            "category":"Banks & Credit Unions",
            "subcategory":"Investment Brokerage",
            "type":"Services"
        }
    ],
    "sg:phone":"+32 56 75 60 86",
    "sg:postcode":"8550",
    "sg:province":"West-Vlaanderen",
    "sg:tags":[
        "printing",
        "-"
    ],
    "wof:name":"Van Reckem N",
    "wof:placetype":"venue"
},
  "geometry": {"coordinates":[3.325109005,50.8115081787],"type":"Point"}
}