{
  "type": "Feature",
  "properties": {
    "iso:country":"BE",
    "sg:address":"Valleistraat 15",
    "sg:city":"Heist-op-den-berg",
    "sg:orig_category":"D\u00e9corateurs d'int\u00e9rieur",
    "sg:phone":"+32 14 26 08 95",
    "sg:postcode":"2222",
    "sg:province":"Antwerpen",
    "wof:name":"Paul Lienard",
    "wof:placetype":"venue"
},
  "geometry": {"coordinates":[4.7292399406,51.1032218933],"type":"Point"}
}