{
  "type": "Feature",
  "properties": {
    "iso:country":"BE",
    "sg:address":"Aubettestraat 14",
    "sg:city":"Kortrijk",
    "sg:orig_category":"Diverse bouwafwerking and reiniging Gespecialiseerde residenti\u00eble bouw",
    "sg:phone":"+32 56 21 63 54",
    "sg:postcode":"8510",
    "sg:province":"West-Vlaanderen",
    "wof:name":"Fa. Vanblo",
    "wof:placetype":"venue"
},
  "geometry": {"coordinates":[3.2871589661,50.7885894775],"type":"Point"}
}