{
  "type": "Feature",
  "properties": {
    "addr:full":"Rue Du M\u00e9ridien 32 Bruxelles (saint-josse-ten-noode) Bruxelles-Capitale 1210",
    "addr:housenumber":"32",
    "addr:postcode":"1210",
    "addr:street":"Rue Du Me\u0301Ridien",
    "iso:country":"BE",
    "sg:address":"Rue Du M\u00e9ridien 32",
    "sg:city":"Bruxelles (saint-josse-ten-noode)",
    "sg:classifiers":[
        {
            "category":"Professional",
            "subcategory":"Management & Consulting",
            "type":"Services"
        }
    ],
    "sg:phone":"+32 2 217 48 61",
    "sg:postcode":"1210",
    "sg:province":"Bruxelles-Capitale",
    "sg:tags":[
        "consultant",
        "agency",
        "advertising"
    ],
    "wof:name":"Jordens J Sprl",
    "wof:placetype":"venue"
},
  "geometry": {"coordinates":[4.3691601753,50.8539390564],"type":"Point"}
}