{
  "type": "Feature",
  "properties": {
    "iso:country":"BE",
    "sg:address":"Dorp 14",
    "sg:city":"Waarschoot",
    "sg:classifiers":[
        {
            "category":"Cafe",
            "type":"Food & Drink"
        }
    ],
    "sg:phone":"+32 9 377 58 78",
    "sg:postcode":"9950",
    "sg:province":"Oost-Vlaanderen",
    "sg:tags":[
        "caf\u00e9s"
    ],
    "wof:name":"Caf\u00c9 De Hoop Van Vrede",
    "wof:placetype":"venue"
},
  "geometry": {"coordinates":[3.6059799194,51.1514587402],"type":"Point"}
}