{
  "type": "Feature",
  "properties": {
    "addr:full":"Avenue Des Bouleaux 36 Watermaal-bosvoorde/watermael-boitsfort Bruxelles-Capitale 1170",
    "addr:housenumber":"36",
    "addr:postcode":"1170",
    "addr:street":"Avenue Des Bouleaux",
    "iso:country":"BE",
    "sg:address":"Avenue Des Bouleaux 36",
    "sg:city":"Watermaal-bosvoorde/watermael-boitsfort",
    "sg:orig_category":"Avocats and conseillers juridiques",
    "sg:phone":"+32 2 672 67 79",
    "sg:postcode":"1170",
    "sg:province":"Bruxelles-Capitale",
    "wof:name":"Sabine Delhaye",
    "wof:placetype":"venue"
},
  "geometry": {"coordinates":[4.4076418877,50.804058075],"type":"Point"}
}