{
  "type": "Feature",
  "properties": {
    "addr:full":"Dreve Richelle 161e-f Waterloo Brabant Wallon 1410",
    "addr:postcode":"1410",
    "addr:street":"Dreve;161E-F",
    "iso:country":"BE",
    "sg:address":"Dreve Richelle 161e-f",
    "sg:city":"Waterloo",
    "sg:classifiers":[
        {
            "category":"Communications",
            "subcategory":"Television Station",
            "type":"Services"
        }
    ],
    "sg:phone":"+32 2 352 25 11",
    "sg:postcode":"1410",
    "sg:province":"Brabant Wallon",
    "sg:tags":[
        "colour",
        "scanners",
        "scanner"
    ],
    "wof:name":"Creoscitex Europe S.a.",
    "wof:placetype":"venue"
},
  "geometry": {"coordinates":[4.3980250359,50.7174263],"type":"Point"}
}