{
  "type": "Feature",
  "properties": {
    "iso:country":"BE",
    "sg:address":"Chemin D'havr\u00e9 80",
    "sg:city":"Mons (saint-symphorien)",
    "sg:classifiers":[
        {
            "category":"Building & Trades",
            "subcategory":"Landscaping Services",
            "type":"Services"
        }
    ],
    "sg:phone":"+32 65 87 38 89",
    "sg:postcode":"7030",
    "sg:province":"Hainaut",
    "sg:tags":[
        "access",
        "pond",
        "laying-out",
        "-"
    ],
    "wof:name":"Chouett' Piscines",
    "wof:placetype":"venue"
},
  "geometry": {"coordinates":[4.0224452019,50.4432296753],"type":"Point"}
}