{
  "type": "Feature",
  "properties": {
    "addr:full":"Afsneedorp 1 Gent Oost-Vlaanderen 9051",
    "addr:housenumber":"1",
    "addr:postcode":"9051",
    "addr:street":"Afsneedorp;Oost-Vlaanderen",
    "iso:country":"BE",
    "sg:address":"Afsneedorp 1",
    "sg:city":"Gent",
    "sg:classifiers":[
        {
            "category":"Restaurant",
            "type":"Food & Drink"
        }
    ],
    "sg:phone":"+32 9 220 69 03",
    "sg:postcode":"9051",
    "sg:province":"Oost-Vlaanderen",
    "sg:tags":[
        "caf\u00e9s"
    ],
    "wof:name":"Taverne Sphinx",
    "wof:placetype":"venue"
},
  "geometry": {"coordinates":[3.6683819294,51.020690918],"type":"Point"}
}