{
  "type": "Feature",
  "properties": {
    "addr:full":"Pater Penninckxstraat 32 Zemst (elewijt) Vlaams-Brabant 1982",
    "addr:housenumber":"32",
    "addr:postcode":"1982",
    "addr:street":"Pater Penninckxstraat",
    "iso:country":"BE",
    "sg:address":"Pater Penninckxstraat 32",
    "sg:city":"Zemst (elewijt)",
    "sg:classifiers":[
        {
            "category":"Retail",
            "subcategory":"Event Space",
            "type":"Services"
        }
    ],
    "sg:phone":"+32 15 62 08 69",
    "sg:postcode":"1982",
    "sg:province":"Vlaams-Brabant",
    "sg:tags":[
        "rental",
        "-",
        "hall"
    ],
    "wof:name":"Molenveld",
    "wof:placetype":"venue"
},
  "geometry": {"coordinates":[4.4969110489,50.960308075],"type":"Point"}
}