{
  "type": "Feature",
  "properties": {
    "addr:full":"Hagenlei 31 Schoten Antwerpen 2900",
    "addr:housenumber":"31",
    "addr:postcode":"2900",
    "addr:street":"Hagenlei",
    "iso:country":"BE",
    "sg:address":"Hagenlei 31",
    "sg:city":"Schoten",
    "sg:classifiers":[
        {
            "category":"Communications",
            "subcategory":"Film & Video Production",
            "type":"Services"
        }
    ],
    "sg:phone":"+32 3 658 33 40",
    "sg:postcode":"2900",
    "sg:province":"Antwerpen",
    "sg:tags":[
        "realisation",
        "-"
    ],
    "wof:name":"V.c.r.",
    "wof:placetype":"venue"
},
  "geometry": {"coordinates":[4.5173368454,51.2498817444],"type":"Point"}
}