{
  "type": "Feature",
  "properties": {
    "addr:full":"Rue De Fragn\u00c9e 104 Li\u00c8ge Li\u00e8ge 4000",
    "addr:housenumber":"104",
    "addr:postcode":"4000",
    "addr:street":"Rue De Fragne\u0301E",
    "iso:country":"BE",
    "sg:address":"Rue De Fragn\u00c9e 104",
    "sg:city":"Li\u00c8ge",
    "sg:orig_category":"Dierenartsen",
    "sg:phone":"+32 4 254 24 67",
    "sg:postcode":"4000",
    "sg:province":"Li\u00e8ge",
    "wof:name":"Mathieu Elangue",
    "wof:placetype":"venue"
},
  "geometry": {"coordinates":[5.5726652145,50.6241416931],"type":"Point"}
}