{
  "type": "Feature",
  "properties": {
    "addr:full":"Chauss\u00e9e De Bruxelles 161b Charleroi (jumet) Hainaut 6040",
    "addr:housenumber":"161b",
    "addr:postcode":"6040",
    "addr:street":"Chausse\u0301E De Bruxelles",
    "iso:country":"BE",
    "sg:address":"Chauss\u00e9e De Bruxelles 161b",
    "sg:city":"Charleroi (jumet)",
    "sg:classifiers":[
        {
            "category":"Manufacturing",
            "subcategory":"Motor Vehicles & Parts",
            "type":"Manufacturing & Wholesale Goods"
        }
    ],
    "sg:phone":"+32 71 37 57 09",
    "sg:postcode":"6040",
    "sg:province":"Hainaut",
    "sg:tags":[
        "body",
        "automobile",
        "construction",
        "-"
    ],
    "wof:name":"Camion (le)",
    "wof:placetype":"venue"
},
  "geometry": {"coordinates":[4.4377908707,50.4404296875],"type":"Point"}
}