{
  "type": "Feature",
  "properties": {
    "addr:full":"Carillolei 2 Aartselaar Antwerpen 2630",
    "addr:housenumber":"2",
    "addr:postcode":"2630",
    "addr:street":"Carillolei",
    "iso:country":"BE",
    "sg:address":"Carillolei 2",
    "sg:city":"Aartselaar",
    "sg:orig_category":"Enseignement maternel and primaire",
    "sg:phone":"+32 3 887 49 88",
    "sg:postcode":"2630",
    "sg:province":"Antwerpen",
    "wof:name":"Gemeentel. Lagere School",
    "wof:placetype":"venue"
},
  "geometry": {"coordinates":[4.3869328499,51.1337013245],"type":"Point"}
}