{
  "type": "Feature",
  "properties": {
    "addr:full":"Diksmuidseweg 455 Ieper West-Vlaanderen 8904",
    "addr:housenumber":"455",
    "addr:postcode":"8904",
    "iso:country":"BE",
    "sg:address":"Diksmuidseweg 455",
    "sg:city":"Ieper",
    "sg:orig_category":"Instituts de beaut\u00e9",
    "sg:phone":"+32 57 42 33 25",
    "sg:postcode":"8904",
    "sg:province":"West-Vlaanderen",
    "wof:name":"Mia Vanderjeugt",
    "wof:placetype":"venue"
},
  "geometry": {"coordinates":[2.8521690369,50.8986282349],"type":"Point"}
}