{
  "type": "Feature",
  "properties": {
    "addr:full":"Vijverstraat 1 Zaventem Vlaams-Brabant 1930",
    "addr:housenumber":"1",
    "addr:postcode":"1930",
    "addr:street":"Vijverstraat",
    "iso:country":"BE",
    "sg:address":"Vijverstraat 1",
    "sg:city":"Zaventem",
    "sg:classifiers":[
        {
            "category":"Professional",
            "subcategory":"Art Services",
            "type":"Services"
        }
    ],
    "sg:phone":"+32 2 720 62 96",
    "sg:postcode":"1930",
    "sg:province":"Vlaams-Brabant",
    "sg:tags":[
        "design",
        "packing",
        "-",
        "realization"
    ],
    "wof:name":"Struyf & Partners",
    "wof:placetype":"venue"
},
  "geometry": {"coordinates":[4.4736051559,50.8808403015],"type":"Point"}
}