{
  "type": "Feature",
  "properties": {
    "iso:country":"BE",
    "sg:address":"Elizabetlaan 309",
    "sg:city":"Knokke-heist (heist-aan-zee)",
    "sg:classifiers":[
        {
            "category":"Building & Trades",
            "subcategory":"Construction",
            "type":"Services"
        }
    ],
    "sg:phone":"+32 50 51 12 33",
    "sg:postcode":"8301",
    "sg:province":"West-Vlaanderen",
    "sg:tags":[
        "installation",
        "-",
        "central",
        "heating"
    ],
    "wof:name":"Casteleyn-vandevelde Bvba",
    "wof:placetype":"venue"
},
  "geometry": {"coordinates":[3.2586400509,51.3408622742],"type":"Point"}
}