{
  "type": "Feature",
  "properties": {
    "addr:full":"Rue De L'eglise 28 Kelmis/la Calamine Li\u00e8ge 4720",
    "addr:housenumber":"28",
    "addr:postcode":"4720",
    "addr:street":"Rue De L'Eglise",
    "iso:country":"BE",
    "sg:address":"Rue De L'eglise 28",
    "sg:city":"Kelmis/la Calamine",
    "sg:classifiers":[
        {
            "category":"Manufacturing",
            "subcategory":"Textiles",
            "type":"Manufacturing & Wholesale Goods"
        }
    ],
    "sg:phone":"+32 87 65 22 48",
    "sg:postcode":"4720",
    "sg:province":"Li\u00e8ge",
    "wof:name":"Belle Couture",
    "wof:placetype":"venue"
},
  "geometry": {"coordinates":[6.0143799782,50.7158050537],"type":"Point"}
}