{
  "type": "Feature",
  "properties": {
    "iso:country":"BE",
    "sg:address":"Petunialaan 14",
    "sg:city":"Kapellen",
    "sg:orig_category":"Architectes",
    "sg:phone":"+32 3 664 97 48",
    "sg:postcode":"2950",
    "sg:province":"Antwerpen",
    "wof:name":"Jan Herman",
    "wof:placetype":"venue"
},
  "geometry": {"coordinates":[4.4473290443,51.3127555847],"type":"Point"}
}