{
  "type": "Feature",
  "properties": {
    "addr:full":"Avenue De L'hippodrome 50 Bruxelles (ixelles) Bruxelles-Capitale 1050",
    "addr:housenumber":"50",
    "addr:postcode":"1050",
    "addr:street":"Avenue De L'Hippodrome",
    "iso:country":"BE",
    "sg:address":"Avenue De L'hippodrome 50",
    "sg:city":"Bruxelles (ixelles)",
    "sg:classifiers":[
        {
            "category":"Professional",
            "subcategory":"Lawyer & Legal Services",
            "type":"Services"
        }
    ],
    "sg:phone":"+32 2 626 02 02",
    "sg:postcode":"1050",
    "sg:province":"Bruxelles-Capitale",
    "wof:name":"Magin Rapha\u00ebl",
    "wof:placetype":"venue"
},
  "geometry": {"coordinates":[4.3755588531,50.8223381042],"type":"Point"}
}