{
  "type": "Feature",
  "properties": {
    "addr:full":"Gaaipersstraat 2 Roeselare West-Vlaanderen 8800",
    "addr:housenumber":"2",
    "addr:postcode":"8800",
    "addr:street":"Gaaipersstraat",
    "iso:country":"BE",
    "sg:address":"Gaaipersstraat 2",
    "sg:city":"Roeselare",
    "sg:classifiers":[
        {
            "category":"Community Center",
            "subcategory":"Youth",
            "type":"Public Place"
        }
    ],
    "sg:phone":"+32 51 20 61 11",
    "sg:postcode":"8800",
    "sg:province":"West-Vlaanderen",
    "sg:tags":[
        "club"
    ],
    "wof:name":"Panta Rhei Vzw",
    "wof:placetype":"venue"
},
  "geometry": {"coordinates":[3.1198909283,50.9504508972],"type":"Point"}
}