{
  "type": "Feature",
  "properties": {
    "iso:country":"BE",
    "sg:address":"Rue Elisa Dumonceau 65",
    "sg:city":"Herstal",
    "sg:classifiers":[
        {
            "category":"Building & Trades",
            "subcategory":"Construction",
            "type":"Services"
        }
    ],
    "sg:phone":"+32 4 240 06 97",
    "sg:postcode":"4040",
    "sg:province":"Li\u00e8ge",
    "sg:tags":[
        "surveyor",
        "-"
    ],
    "wof:name":"Del Peso Fernando",
    "wof:placetype":"venue"
},
  "geometry": {"coordinates":[5.6294698715,50.6632728577],"type":"Point"}
}