{
  "type": "Feature",
  "properties": {
    "iso:country":"BE",
    "sg:address":"Molenstraat 67",
    "sg:city":"Herenthout",
    "sg:classifiers":[
        {
            "category":"Cafe",
            "type":"Food & Drink"
        }
    ],
    "sg:phone":"+32 14 51 69 35",
    "sg:postcode":"2270",
    "sg:province":"Antwerpen",
    "sg:tags":[
        "caf\u00e9s"
    ],
    "wof:name":"Caf\u00c9 Tower",
    "wof:placetype":"venue"
},
  "geometry": {"coordinates":[4.7608690262,51.140209198],"type":"Point"}
}