{
  "type": "Feature",
  "properties": {
    "addr:full":"Rue Jean Jaur\u00c8s 47 Saint-nicolas Li\u00e8ge 4420",
    "addr:housenumber":"47",
    "addr:postcode":"4420",
    "addr:street":"Rue Jean Jaure\u0300S",
    "iso:country":"BE",
    "sg:address":"Rue Jean Jaur\u00c8s 47",
    "sg:city":"Saint-nicolas",
    "sg:orig_category":"Bloemen and planten",
    "sg:phone":"+32 4 246 29 02",
    "sg:postcode":"4420",
    "sg:province":"Li\u00e8ge",
    "wof:name":"Cadoflor",
    "wof:placetype":"venue"
},
  "geometry": {"coordinates":[5.5220508575,50.638961792],"type":"Point"}
}