{
  "type": "Feature",
  "properties": {
    "addr:full":"Dirk Martensstraat 14a Brugge (sint-andries) West-Vlaanderen 8200",
    "addr:housenumber":"14a",
    "addr:postcode":"8200",
    "addr:street":"Dirk Martensstraat",
    "iso:country":"BE",
    "sg:address":"Dirk Martensstraat 14a",
    "sg:city":"Brugge (sint-andries)",
    "sg:classifiers":[
        {
            "category":"Real Estate",
            "subcategory":"Real Estate Operator",
            "type":"Services"
        }
    ],
    "sg:phone":"+32 50 31 34 40",
    "sg:postcode":"8200",
    "sg:province":"West-Vlaanderen",
    "sg:tags":[
        "sample",
        "brochure",
        "-",
        "distributors"
    ],
    "wof:name":"Distribrugge Nv",
    "wof:placetype":"venue"
},
  "geometry": {"coordinates":[3.1949470043,51.2104988098],"type":"Point"}
}