{
  "type": "Feature",
  "properties": {
    "iso:country":"BE",
    "sg:address":"Rue D'arquet 4",
    "sg:city":"Namur",
    "sg:classifiers":[
        {
            "category":"Social Services",
            "type":"Services"
        }
    ],
    "sg:phone":"+32 81 22 73 22",
    "sg:postcode":"5000",
    "sg:province":"Namur",
    "wof:name":"Boutique De Droit Du Resto Du Coeur",
    "wof:placetype":"venue"
},
  "geometry": {"coordinates":[4.8664221764,50.4708404541],"type":"Point"}
}