{
  "type": "Feature",
  "properties": {
    "addr:full":"Reepstraat 94 Geraardsbergen Oost-Vlaanderen 9500",
    "addr:housenumber":"94",
    "addr:postcode":"9500",
    "addr:street":"Reepstraat",
    "iso:country":"BE",
    "sg:address":"Reepstraat 94",
    "sg:city":"Geraardsbergen",
    "sg:orig_category":"Sportclubs",
    "sg:phone":"+32 54 41 69 49",
    "sg:postcode":"9500",
    "sg:province":"Oost-Vlaanderen",
    "wof:name":"Rust Roest",
    "wof:placetype":"venue"
},
  "geometry": {"coordinates":[3.8708469868,50.7728881836],"type":"Point"}
}