{
  "type": "Feature",
  "properties": {
    "iso:country":"BE",
    "sg:address":"Fleurbeekstraat 8",
    "sg:city":"Drogenbos/drogenbos",
    "sg:orig_category":"Maatkleding Fab",
    "sg:phone":"+32 2 378 09 63",
    "sg:postcode":"1620",
    "sg:province":"Vlaams-Brabant",
    "wof:name":"Gino Dalla-vecchia",
    "wof:placetype":"venue"
},
  "geometry": {"coordinates":[4.3180990219,50.7914657593],"type":"Point"}
}