{
  "type": "Feature",
  "properties": {
    "addr:full":"Rue De Beauvechain 22 Tourinnes-la-grosse Brabant Wallon 1320",
    "addr:housenumber":"22;1320",
    "addr:street":"Rue De Beauvechain;Brabant Wallon",
    "iso:country":"BE",
    "sg:address":"Rue De Beauvechain 22",
    "sg:city":"Tourinnes-la-grosse",
    "sg:classifiers":[
        {
            "category":"Restaurant",
            "type":"Food & Drink"
        }
    ],
    "sg:phone":"+32 10 86 20 50",
    "sg:postcode":"1320",
    "sg:province":"Brabant Wallon",
    "wof:name":"La Gargouille",
    "wof:placetype":"venue"
},
  "geometry": {"coordinates":[4.7452569008,50.7774848938],"type":"Point"}
}