{
  "type": "Feature",
  "properties": {
    "iso:country":"BE",
    "sg:address":"Bosstraat 55",
    "sg:city":"Maaseik",
    "sg:classifiers":[
        {
            "category":"Shopping",
            "subcategory":"Clothing, Apparel, & Fashions",
            "type":"Retail Goods"
        }
    ],
    "sg:phone":"+32 89 56 39 22",
    "sg:postcode":"3680",
    "sg:province":"Limburg",
    "sg:tags":[
        "v\u00eatements",
        "pour",
        "dame"
    ],
    "wof:name":"Daniella Schmeitz",
    "wof:placetype":"venue"
},
  "geometry": {"coordinates":[5.7875781059,51.0958976746],"type":"Point"}
}