{
  "type": "Feature",
  "properties": {
    "addr:full":"Hogevorst 17 Assenede Oost-Vlaanderen 9968",
    "addr:housenumber":"17",
    "addr:postcode":"9968",
    "addr:street":"Hogevorst",
    "iso:country":"BE",
    "sg:address":"Hogevorst 17",
    "sg:city":"Assenede",
    "sg:orig_category":"Woningbouw",
    "sg:phone":"+32 9 373 83 91",
    "sg:postcode":"9968",
    "sg:province":"Oost-Vlaanderen",
    "wof:name":"Alex De Craemer",
    "wof:placetype":"venue"
},
  "geometry": {"coordinates":[3.6887938976,51.1923027039],"type":"Point"}
}