{
  "type": "Feature",
  "properties": {
    "addr:full":"Lierbaan 61 Putte Antwerpen 2580",
    "addr:housenumber":"61",
    "addr:postcode":"2580",
    "addr:street":"Lierbaan",
    "iso:country":"BE",
    "sg:address":"Lierbaan 61",
    "sg:city":"Putte",
    "sg:orig_category":"Banques and organismes de cr\u00e9dit",
    "sg:phone":"+32 15 75 40 73",
    "sg:postcode":"2580",
    "sg:province":"Antwerpen",
    "wof:name":"Dexia",
    "wof:placetype":"venue"
},
  "geometry": {"coordinates":[4.6288309097,51.0569458008],"type":"Point"}
}