{
  "type": "Feature",
  "properties": {
    "addr:full":"Hagaard 49 Overijse Vlaams-Brabant 3090",
    "addr:housenumber":"49",
    "addr:postcode":"3090",
    "addr:street":"Hagaard",
    "iso:country":"BE",
    "sg:address":"Hagaard 49",
    "sg:city":"Overijse",
    "sg:orig_category":"Caf\u00e9s Woningbouw",
    "sg:phone":"+32 2 688 29 19",
    "sg:postcode":"3090",
    "sg:province":"Vlaams-Brabant",
    "wof:name":"Caf\u00c9 Terminus",
    "wof:placetype":"venue"
},
  "geometry": {"coordinates":[4.5215249062,50.7633514404],"type":"Point"}
}