{
  "type": "Feature",
  "properties": {
    "addr:full":"Rue De La Gare 14ba Bertrix Luxembourg 6880",
    "addr:housenumber":"14ba",
    "addr:postcode":"6880",
    "addr:street":"Rue De La Gare",
    "iso:country":"BE",
    "sg:address":"Rue De La Gare 14ba",
    "sg:city":"Bertrix",
    "sg:orig_category":"Banques and organismes de cr\u00e9dit",
    "sg:phone":"+32 61 41 20 51",
    "sg:postcode":"6880",
    "sg:province":"Luxembourg",
    "wof:name":"Cbc",
    "wof:placetype":"venue"
},
  "geometry": {"coordinates":[5.2543859482,49.8550376892],"type":"Point"}
}