{
  "type": "Feature",
  "properties": {
    "addr:full":"Sint-truidersteenweg 67 Hasselt Limburg 3500",
    "addr:housenumber":"67",
    "addr:postcode":"3500",
    "addr:street":"Sint-Truidersteenweg",
    "iso:country":"BE",
    "sg:address":"Sint-truidersteenweg 67",
    "sg:city":"Hasselt",
    "sg:orig_category":"Rev\u00eatements de sols and murs",
    "sg:phone":"+32 11 27 36 56",
    "sg:postcode":"3500",
    "sg:province":"Limburg",
    "wof:name":"Doultremont M",
    "wof:placetype":"venue"
},
  "geometry": {"coordinates":[5.3089671135,50.8998374939],"type":"Point"}
}