{
  "type": "Feature",
  "properties": {
    "addr:full":"Rue De L'eglise Saint-pierre 54a Bruxelles (jette) Bruxelles-Capitale 1090",
    "addr:housenumber":"54a",
    "addr:postcode":"1090",
    "addr:street":"Rue De L'Eglise Saint-Pierre",
    "iso:country":"BE",
    "sg:address":"Rue De L'eglise Saint-pierre 54a",
    "sg:city":"Bruxelles (jette)",
    "sg:classifiers":[
        {
            "category":"Food & Beverages",
            "subcategory":"Chocolate",
            "type":"Retail Goods"
        }
    ],
    "sg:phone":"+32 2 426 91 51",
    "sg:postcode":"1090",
    "sg:province":"Bruxelles-Capitale",
    "sg:tags":[
        "confectionery",
        "-"
    ],
    "wof:name":"David Chocolatier",
    "wof:placetype":"venue"
},
  "geometry": {"coordinates":[4.3252339363,50.8803787231],"type":"Point"}
}