{
  "type": "Feature",
  "properties": {
    "addr:full":"Rue Raskinroy 8 Vis\u00c9 Li\u00e8ge 4600",
    "addr:housenumber":"8",
    "addr:postcode":"4600",
    "addr:street":"Rue Raskinroy",
    "iso:country":"BE",
    "sg:address":"Rue Raskinroy 8",
    "sg:city":"Vis\u00c9",
    "sg:classifiers":[
        {
            "category":"Restaurant",
            "type":"Food & Drink"
        }
    ],
    "sg:phone":"+32 4 379 09 99",
    "sg:postcode":"4600",
    "sg:province":"Li\u00e8ge",
    "wof:name":"Le Raskin Roy",
    "wof:placetype":"venue"
},
  "geometry": {"coordinates":[5.6958899498,50.7343902588],"type":"Point"}
}