{
  "type": "Feature",
  "properties": {
    "iso:country":"BE",
    "sg:address":"Rue De Dampremy 2",
    "sg:city":"Charleroi",
    "sg:classifiers":[
        {
            "category":"Bars & Pubs",
            "type":"Food & Drink"
        }
    ],
    "sg:phone":"+32 71 31 90 05",
    "sg:postcode":"6000",
    "sg:province":"Hainaut",
    "wof:name":"Pi\u00e9ton (le)",
    "wof:placetype":"venue"
},
  "geometry": {"coordinates":[4.442343235,50.4086303711],"type":"Point"}
}