{
  "type": "Feature",
  "properties": {
    "iso:country":"BE",
    "sg:address":"Steenakker 25",
    "sg:city":"Mortsel",
    "sg:orig_category":"M\u00e9decins and sp\u00e9cialistes",
    "sg:phone":"+32 3 449 37 51",
    "sg:postcode":"2640",
    "sg:province":"Antwerpen",
    "wof:name":"Kathleen Buys",
    "wof:placetype":"venue"
},
  "geometry": {"coordinates":[4.4683599472,51.1713752747],"type":"Point"}
}