{
  "type": "Feature",
  "properties": {
    "iso:country":"BE",
    "sg:address":"Rue Du Plouys 27",
    "sg:city":"Jurbise",
    "sg:orig_category":"Groententeelt",
    "sg:phone":"+32 65 22 90 64",
    "sg:postcode":"7050",
    "sg:province":"Hainaut",
    "wof:name":"Raymond Lievens",
    "wof:placetype":"venue"
},
  "geometry": {"coordinates":[3.8775100708,50.5292510986],"type":"Point"}
}