{
  "type": "Feature",
  "properties": {
    "iso:country":"BE",
    "sg:address":"Excelsiorlaan 49",
    "sg:city":"Zaventem",
    "sg:orig_category":"Farmaceutische bereidingen and geneesmiddelen Fab Technische and wetenschappelijke instrumenten Fab",
    "sg:phone":"+32 2 715 01 70",
    "sg:postcode":"1930",
    "sg:province":"Vlaams-Brabant",
    "wof:name":"Chiron",
    "wof:placetype":"venue"
},
  "geometry": {"coordinates":[4.4543352127,50.8843803406],"type":"Point"}
}