{
  "type": "Feature",
  "properties": {
    "addr:full":"Rattepoelstraat 16 Maarkedal (maarke-kerkem) Oost-Vlaanderen 9680",
    "addr:housenumber":"16",
    "addr:postcode":"9680",
    "addr:street":"Rattepoelstraat",
    "iso:country":"BE",
    "sg:address":"Rattepoelstraat 16",
    "sg:city":"Maarkedal (maarke-kerkem)",
    "sg:classifiers":[
        {
            "category":"Manufacturing",
            "subcategory":"Chemicals & Compounds",
            "type":"Manufacturing & Wholesale Goods"
        }
    ],
    "sg:phone":"+32 55 31 20 55",
    "sg:postcode":"9680",
    "sg:province":"Oost-Vlaanderen",
    "sg:tags":[
        "agricultural"
    ],
    "wof:name":"Cierkens A",
    "wof:placetype":"venue"
},
  "geometry": {"coordinates":[3.6580719948,50.8117599487],"type":"Point"}
}