{
  "type": "Feature",
  "properties": {
    "iso:country":"BE",
    "sg:address":"Parklaan 56",
    "sg:city":"Turnhout",
    "sg:classifiers":[
        {
            "category":"Bars & Pubs",
            "type":"Food & Drink"
        }
    ],
    "sg:phone":"+32 14 43 87 87",
    "sg:postcode":"2300",
    "sg:province":"Antwerpen",
    "wof:name":"Stadspark Brasserie Nv",
    "wof:placetype":"venue"
},
  "geometry": {"coordinates":[4.9383301735,51.3024406433],"type":"Point"}
}