{
  "type": "Feature",
  "properties": {
    "iso:country":"BE",
    "sg:address":"Wijnheuvelenstraat 124",
    "sg:city":"Schaarbeek/schaerbeek",
    "sg:orig_category":"Kapsalons",
    "sg:phone":"+32 2 215 62 32",
    "sg:postcode":"1030",
    "sg:province":"Bruxelles-Capitale",
    "wof:name":"Coiffure Martine",
    "wof:placetype":"venue"
},
  "geometry": {"coordinates":[4.3764801025,50.8579330444],"type":"Point"}
}