{
  "type": "Feature",
  "properties": {
    "addr:full":"L\u00c9opold Peretstraat 48 Jette Bruxelles-Capitale 1090",
    "addr:housenumber":"48",
    "addr:postcode":"1090",
    "addr:street":"Peretstraat",
    "iso:country":"BE",
    "sg:address":"L\u00c9opold Peretstraat 48",
    "sg:city":"Jette",
    "sg:orig_category":"Artsen and specialisten",
    "sg:phone":"+32 2 474 08 76",
    "sg:postcode":"1090",
    "sg:province":"Bruxelles-Capitale",
    "wof:name":"Christina Taki",
    "wof:placetype":"venue"
},
  "geometry": {"coordinates":[4.3372950554,50.8848266602],"type":"Point"}
}