{
  "type": "Feature",
  "properties": {
    "addr:full":"Rue Aim\u00c9 Hoslet 12 Grez-doiceau Brabant Wallon 1390",
    "addr:housenumber":"12",
    "addr:postcode":"1390",
    "addr:street":"Rue Aime\u0301 Hoslet",
    "iso:country":"BE",
    "sg:address":"Rue Aim\u00c9 Hoslet 12",
    "sg:city":"Grez-doiceau",
    "sg:orig_category":"Installatie van houten of kunststof schrijnwerk",
    "sg:phone":"+32 10 84 07 44",
    "sg:postcode":"1390",
    "sg:province":"Brabant Wallon",
    "wof:name":"Hugo Vanmeerbeek",
    "wof:placetype":"venue"
},
  "geometry": {"coordinates":[4.6476788521,50.7700767517],"type":"Point"}
}