{
  "type": "Feature",
  "properties": {
    "addr:full":"Bouwelven 5 Grobbendonk Antwerpen 2280",
    "addr:housenumber":"5",
    "addr:postcode":"2280",
    "addr:street":"Bouwelven",
    "iso:country":"BE",
    "sg:address":"Bouwelven 5",
    "sg:city":"Grobbendonk",
    "sg:orig_category":"Mat\u00e9riaux de construction Gr",
    "sg:phone":"+32 14 23 07 07",
    "sg:postcode":"2280",
    "sg:province":"Antwerpen",
    "wof:name":"Bital",
    "wof:placetype":"venue"
},
  "geometry": {"coordinates":[4.7081608772,51.1736831665],"type":"Point"}
}