{
  "type": "Feature",
  "properties": {
    "addr:full":"Rue Am\u00c9ricaine 100 Elsene/ixelles Bruxelles-Capitale 1050",
    "addr:housenumber":"100",
    "addr:postcode":"1050",
    "addr:street":"Rue Ame\u0301Ricaine",
    "iso:country":"BE",
    "sg:address":"Rue Am\u00c9ricaine 100",
    "sg:city":"Elsene/ixelles",
    "sg:orig_category":"Notarissen",
    "sg:phone":"+32 2 537 93 17",
    "sg:postcode":"1050",
    "sg:province":"Bruxelles-Capitale",
    "wof:name":"Dubuisson O.",
    "wof:placetype":"venue"
},
  "geometry": {"coordinates":[4.3594751358,50.8232536316],"type":"Point"}
}