{
  "type": "Feature",
  "properties": {
    "iso:country":"BE",
    "sg:address":"Nijverheidsstraat 55",
    "sg:city":"Gavere",
    "sg:orig_category":"Kapsalons",
    "sg:phone":"+32 9 384 11 26",
    "sg:postcode":"9890",
    "sg:province":"Oost-Vlaanderen",
    "wof:name":"Anja's Hairclub",
    "wof:placetype":"venue"
},
  "geometry": {"coordinates":[3.6836919785,50.9198036194],"type":"Point"}
}