{
  "type": "Feature",
  "properties": {
    "addr:full":"Leopoldstraat 6 Blankenberge West-Vlaanderen 8370",
    "addr:housenumber":"6",
    "addr:postcode":"8370",
    "addr:street":"Leopoldstraat",
    "iso:country":"BE",
    "sg:address":"Leopoldstraat 6",
    "sg:city":"Blankenberge",
    "sg:classifiers":[
        {
            "category":"Cafe",
            "type":"Food & Drink"
        }
    ],
    "sg:phone":"+32 50 41 21 82",
    "sg:postcode":"8370",
    "sg:province":"West-Vlaanderen",
    "sg:tags":[
        "caf\u00e9s"
    ],
    "wof:name":"Anja Ramaekers",
    "wof:placetype":"venue"
},
  "geometry": {"coordinates":[3.1228070259,51.314453125],"type":"Point"}
}