{
  "type": "Feature",
  "properties": {
    "addr:full":"Rootenstraat 25b15 Genk Limburg 3600",
    "addr:housenumber":"25b15",
    "addr:postcode":"3600",
    "addr:street":"Rootenstraat",
    "iso:country":"BE",
    "sg:address":"Rootenstraat 25b15",
    "sg:city":"Genk",
    "sg:orig_category":"Installatie van metalen schrijnwerk",
    "sg:phone":"+32 89 35 51 98",
    "sg:postcode":"3600",
    "sg:province":"Limburg",
    "wof:name":"B.r.w.",
    "wof:placetype":"venue"
},
  "geometry": {"coordinates":[5.5028338432,50.9652481079],"type":"Point"}
}