{
  "type": "Feature",
  "properties": {
    "iso:country":"BE",
    "sg:address":"Kabinestraat 9",
    "sg:city":"Landen",
    "sg:classifiers":[
        {
            "category":"Arena",
            "subcategory":"Sports Club",
            "type":"Entertainment"
        }
    ],
    "sg:phone":"+32 11 88 28 70",
    "sg:postcode":"3401",
    "sg:province":"Vlaams-Brabant",
    "sg:tags":[
        "terrain",
        "hors",
        "de",
        "installation",
        "sportifs"
    ],
    "wof:name":"R.f.c. Walshoutem",
    "wof:placetype":"venue"
},
  "geometry": {"coordinates":[5.0655550957,50.7247161865],"type":"Point"}
}