{
  "type": "Feature",
  "properties": {
    "addr:full":"Weg Naar Ellikom 53 Meeuwen-gruitrode Limburg 3670",
    "addr:housenumber":"53",
    "addr:postcode":"3670",
    "addr:street":"Weg Naar Ellikom",
    "iso:country":"BE",
    "sg:address":"Weg Naar Ellikom 53",
    "sg:city":"Meeuwen-gruitrode",
    "sg:orig_category":"Banken and kredietinstellingen",
    "sg:phone":"+32 11 79 36 23",
    "sg:postcode":"3670",
    "sg:province":"Limburg",
    "wof:name":"Ippa",
    "wof:placetype":"venue"
},
  "geometry": {"coordinates":[5.517788887,51.1019134521],"type":"Point"}
}