{
  "type": "Feature",
  "properties": {
    "iso:country":"BE",
    "sg:address":"Woestenstraat 17",
    "sg:city":"Vleteren",
    "sg:orig_category":"Entretien and r\u00e9parations de voitures. Stations-service and carburants",
    "sg:phone":"+32 57 40 00 09",
    "sg:postcode":"8640",
    "sg:province":"West-Vlaanderen",
    "wof:name":"Andre Covemaecker",
    "wof:placetype":"venue"
},
  "geometry": {"coordinates":[2.7395699024,50.9298286438],"type":"Point"}
}