{
  "type": "Feature",
  "properties": {
    "addr:full":"Vliegplein 45b Maldegem Oost-Vlaanderen 9990",
    "addr:housenumber":"45b",
    "addr:postcode":"9990",
    "addr:street":"Vliegplein",
    "iso:country":"BE",
    "sg:address":"Vliegplein 45b",
    "sg:city":"Maldegem",
    "sg:orig_category":"Non-Classified Establishments",
    "sg:phone":"+32 50 71 82 36",
    "sg:postcode":"9990",
    "sg:province":"Oost-Vlaanderen",
    "wof:name":"Cobraflex",
    "wof:placetype":"venue"
},
  "geometry": {"coordinates":[3.4711539745,51.199836731],"type":"Point"}
}