{
  "type": "Feature",
  "properties": {
    "iso:country":"BE",
    "sg:address":"Hanenstraat 14",
    "sg:city":"Kortenaken",
    "sg:orig_category":"Fruitteelt",
    "sg:phone":"+32 11 58 74 23",
    "sg:postcode":"3472",
    "sg:province":"Vlaams-Brabant",
    "wof:name":"Gaston Lavers",
    "wof:placetype":"venue"
},
  "geometry": {"coordinates":[5.0220751762,50.8937835693],"type":"Point"}
}