{
  "type": "Feature",
  "properties": {
    "addr:full":"Place P. Beaufaux 30 Wavre Brabant Wallon 1300",
    "addr:housenumber":"30;1300",
    "addr:street":"Place;Beaufaux",
    "iso:country":"BE",
    "sg:address":"Place P. Beaufaux 30",
    "sg:city":"Wavre",
    "sg:orig_category":"Epiceries",
    "sg:phone":"+32 10 22 25 50",
    "sg:postcode":"1300",
    "sg:province":"Brabant Wallon",
    "wof:name":"La Dyle",
    "wof:placetype":"venue"
},
  "geometry": {"coordinates":[4.6246199608,50.7213783264],"type":"Point"}
}