{
  "type": "Feature",
  "properties": {
    "addr:full":"Hektor Casteleinstraat 6 Kortrijk (marke) West-Vlaanderen 8510",
    "addr:housenumber":"6",
    "addr:postcode":"8510",
    "addr:street":"Casteleinstraat",
    "iso:country":"BE",
    "sg:address":"Hektor Casteleinstraat 6",
    "sg:city":"Kortrijk (marke)",
    "sg:classifiers":[
        {
            "category":"Ice Cream",
            "type":"Food & Drink"
        }
    ],
    "sg:phone":"+32 56 21 25 52",
    "sg:postcode":"8510",
    "sg:province":"West-Vlaanderen",
    "wof:name":"Millennium Chocolaterie",
    "wof:placetype":"venue"
},
  "geometry": {"coordinates":[3.2303071022,50.8083496094],"type":"Point"}
}