{
  "type": "Feature",
  "properties": {
    "addr:full":"Avenue Fond Generet 19 Chaumont-gistoux Brabant Wallon 1325",
    "addr:housenumber":"19",
    "addr:postcode":"1325",
    "addr:street":"Avenue Fond Generet",
    "iso:country":"BE",
    "sg:address":"Avenue Fond Generet 19",
    "sg:city":"Chaumont-gistoux",
    "sg:orig_category":"Rusthuizen and serviceflats",
    "sg:phone":"+32 10 22 37 02",
    "sg:postcode":"1325",
    "sg:province":"Brabant Wallon",
    "wof:name":"Home Les Generets",
    "wof:placetype":"venue"
},
  "geometry": {"coordinates":[4.6479568481,50.6963615417],"type":"Point"}
}