{
  "type": "Feature",
  "properties": {
    "iso:country":"BE",
    "sg:address":"Processiestraat 84",
    "sg:city":"Waregem",
    "sg:classifiers":[
        {
            "category":"Professional",
            "subcategory":"Art Services",
            "type":"Services"
        }
    ],
    "sg:phone":"+32 56 71 39 46",
    "sg:postcode":"8790",
    "sg:province":"West-Vlaanderen",
    "sg:tags":[
        "photographer"
    ],
    "wof:name":"Denoulet Ch",
    "wof:placetype":"venue"
},
  "geometry": {"coordinates":[3.4251880646,50.885219574],"type":"Point"}
}