{
  "type": "Feature",
  "properties": {
    "addr:full":"Avenue W\u00c9rihet 53 Li\u00c8ge Li\u00e8ge 4020",
    "addr:housenumber":"53",
    "addr:postcode":"4020",
    "addr:street":"Avenue We\u0301Rihet",
    "iso:country":"BE",
    "sg:address":"Avenue W\u00c9rihet 53",
    "sg:city":"Li\u00c8ge",
    "sg:orig_category":"Agences d'exp\u00e9dition. Constructions r\u00e9sidentielles sp\u00e9cifiques. Construction de maisons",
    "sg:phone":"+32 4 362 57 08",
    "sg:postcode":"4020",
    "sg:province":"Li\u00e8ge",
    "wof:name":"Boma",
    "wof:placetype":"venue"
},
  "geometry": {"coordinates":[5.6346750259,50.6462516785],"type":"Point"}
}