{
  "type": "Feature",
  "properties": {
    "iso:country":"BE",
    "sg:address":"Herenthoutseweg 192",
    "sg:city":"Herentals",
    "sg:orig_category":"Quincailleries",
    "sg:phone":"+32 14 23 19 67",
    "sg:postcode":"2200",
    "sg:province":"Antwerpen",
    "wof:name":"Snap-on-tools",
    "wof:placetype":"venue"
},
  "geometry": {"coordinates":[4.8193101883,51.1600799561],"type":"Point"}
}