{
  "type": "Feature",
  "properties": {
    "iso:country":"BE",
    "sg:address":"Laurier-kersenlaan 14",
    "sg:city":"Kraainem/kraainem",
    "sg:orig_category":"DIVERSE RECREATIEVE ACTIVITEITEN",
    "sg:phone":"+32 2 731 38 26",
    "sg:postcode":"1950",
    "sg:province":"Vlaams-Brabant",
    "wof:name":"Cercle Phil. P. De Smeth",
    "wof:placetype":"venue"
},
  "geometry": {"coordinates":[4.4759130478,50.8366928101],"type":"Point"}
}