{
  "type": "Feature",
  "properties": {
    "addr:full":"Aardseweg 11 Geel Antwerpen 2440",
    "addr:housenumber":"11",
    "addr:postcode":"2440",
    "addr:street":"Aardseweg",
    "iso:country":"BE",
    "sg:address":"Aardseweg 11",
    "sg:city":"Geel",
    "sg:orig_category":"Epiceries",
    "sg:phone":"+32 14 85 25 50",
    "sg:postcode":"2440",
    "sg:province":"Antwerpen",
    "wof:name":"J. Vandoninck",
    "wof:placetype":"venue"
},
  "geometry": {"coordinates":[5.0070700645,51.2123603821],"type":"Point"}
}