{
  "type": "Feature",
  "properties": {
    "iso:country":"BE",
    "sg:address":"Antwerpsesteenweg 64",
    "sg:city":"Kapellen",
    "sg:orig_category":"Entretien and r\u00e9parations de voitures",
    "sg:phone":"+32 3 664 64 39",
    "sg:postcode":"2950",
    "sg:province":"Antwerpen",
    "wof:name":"Herman Robert",
    "wof:placetype":"venue"
},
  "geometry": {"coordinates":[4.4296350479,51.3118858337],"type":"Point"}
}