{
  "type": "Feature",
  "properties": {
    "addr:full":"Liersebaan 54 Zandhoven Antwerpen 2240",
    "addr:housenumber":"54",
    "addr:postcode":"2240",
    "addr:street":"Liersebaan",
    "iso:country":"BE",
    "sg:address":"Liersebaan 54",
    "sg:city":"Zandhoven",
    "sg:classifiers":[
        {
            "category":"Shopping",
            "subcategory":"Shoes",
            "type":"Retail Goods"
        }
    ],
    "sg:phone":"+32 3 484 30 85",
    "sg:postcode":"2240",
    "sg:province":"Antwerpen",
    "sg:tags":[
        "slipper",
        "-"
    ],
    "wof:name":"Copp\u00e9 Bvba",
    "wof:placetype":"venue"
},
  "geometry": {"coordinates":[4.6493902206,51.2051010132],"type":"Point"}
}