{
  "type": "Feature",
  "properties": {
    "addr:full":"Rue Auguste De Boeck 66 Bruxelles (evere) Bruxelles-Capitale 1140",
    "addr:housenumber":"66",
    "addr:postcode":"1140",
    "addr:street":"Rue Auguste De Boeck",
    "iso:country":"BE",
    "sg:address":"Rue Auguste De Boeck 66",
    "sg:city":"Bruxelles (evere)",
    "sg:classifiers":[
        {
            "category":"Airport",
            "subcategory":"International",
            "type":"Transportation"
        }
    ],
    "sg:phone":"+32 2 726 22 22",
    "sg:postcode":"1140",
    "sg:province":"Bruxelles-Capitale",
    "sg:tags":[
        "-",
        "transport"
    ],
    "wof:name":"Paris France Porteur Sprl",
    "wof:placetype":"venue"
},
  "geometry": {"coordinates":[4.400539875,50.8679084778],"type":"Point"}
}