{
  "type": "Feature",
  "properties": {
    "iso:country":"BE",
    "sg:address":"Borgwal 2b83",
    "sg:city":"Brussel/bruxelles",
    "sg:orig_category":"Artsen and specialisten",
    "sg:phone":"+32 2 512 37 33",
    "sg:postcode":"1000",
    "sg:province":"Bruxelles-Capitale",
    "wof:name":"A. Jesuran",
    "wof:placetype":"venue"
},
  "geometry": {"coordinates":[4.3485450745,50.8474197388],"type":"Point"}
}