{
  "type": "Feature",
  "properties": {
    "iso:country":"BE",
    "sg:address":"Rue De Burhaimont 23",
    "sg:city":"Bertrix",
    "sg:orig_category":"Quincailleries",
    "sg:phone":"+32 61 41 12 92",
    "sg:postcode":"6880",
    "sg:province":"Luxembourg",
    "wof:name":"Albert Deruisseaux",
    "wof:placetype":"venue"
},
  "geometry": {"coordinates":[5.2517490387,49.8573608398],"type":"Point"}
}