{
  "type": "Feature",
  "properties": {
    "addr:full":"Avenue De Mai 143 Bruxelles (woluwe-saint-lambert) Bruxelles-Capitale 1200",
    "addr:housenumber":"143",
    "addr:postcode":"1200",
    "addr:street":"Avenue De Mai",
    "iso:country":"BE",
    "sg:address":"Avenue De Mai 143",
    "sg:city":"Bruxelles (woluwe-saint-lambert)",
    "sg:classifiers":[
        {
            "category":"Landmark",
            "subcategory":"Scenic View",
            "type":"Public Place"
        }
    ],
    "sg:phone":"+32 2 770 46 05",
    "sg:postcode":"1200",
    "sg:province":"Bruxelles-Capitale",
    "sg:tags":[
        "setting",
        "photographic"
    ],
    "wof:name":"Objectif Sprl",
    "wof:placetype":"venue"
},
  "geometry": {"coordinates":[4.4174981117,50.8483963013],"type":"Point"}
}