{
  "type": "Feature",
  "properties": {
    "iso:country":"BE",
    "sg:address":"Rue De L'echangeur 99",
    "sg:city":"Namur",
    "sg:orig_category":"Installation de menuiserie m\u00e9tallique",
    "sg:phone":"+32 81 21 53 25",
    "sg:postcode":"5020",
    "sg:province":"Namur",
    "wof:name":"Atelier Laurent Claude",
    "wof:placetype":"venue"
},
  "geometry": {"coordinates":[4.8711528778,50.5153770447],"type":"Point"}
}