{
  "type": "Feature",
  "properties": {
    "iso:country":"BE",
    "sg:address":"Rue Pierre Deno\u00cbl 4",
    "sg:city":"Beyne-heusay",
    "sg:orig_category":"S\u00e9curit\u00e9 sociale",
    "sg:phone":"+32 4 358 73 49",
    "sg:postcode":"4610",
    "sg:province":"Li\u00e8ge",
    "wof:name":"Mutualit\u00c9 Profes. & Libre",
    "wof:placetype":"venue"
},
  "geometry": {"coordinates":[5.6632080078,50.6186828613],"type":"Point"}
}