{
  "type": "Feature",
  "properties": {
    "addr:full":"Schoenmarkt 16-18 Antwerpen Antwerpen 2000",
    "addr:postcode":"16-18;2000",
    "addr:street":"Schoenmarkt",
    "iso:country":"BE",
    "sg:address":"Schoenmarkt 16-18",
    "sg:city":"Antwerpen",
    "sg:classifiers":[
        {
            "category":"Shopping",
            "subcategory":"Clothing, Apparel, & Fashions",
            "type":"Retail Goods"
        }
    ],
    "sg:phone":"+32 3 233 05 98",
    "sg:postcode":"2000",
    "sg:province":"Antwerpen",
    "sg:tags":[
        "boutique"
    ],
    "wof:name":"Hima Herenkleding Nv",
    "wof:placetype":"venue"
},
  "geometry": {"coordinates":[4.4041080475,51.2183036804],"type":"Point"}
}