{
  "type": "Feature",
  "properties": {
    "iso:country":"BE",
    "sg:address":"Irislaan 7",
    "sg:city":"Kampenhout",
    "sg:orig_category":"Plaatsen van vloer- and muurbekleding Schilders",
    "sg:phone":"+32 16 65 17 76",
    "sg:postcode":"1910",
    "sg:province":"Vlaams-Brabant",
    "wof:name":"Jean Vandewyngaerde",
    "wof:placetype":"venue"
},
  "geometry": {"coordinates":[4.5223588943,50.9254760742],"type":"Point"}
}