{
  "type": "Feature",
  "properties": {
    "addr:full":"Rue Saint-gertrude 25 Waterloo Brabant Wallon 1410",
    "addr:housenumber":"25",
    "addr:postcode":"1410",
    "addr:street":"Rue Saint-Gertrude",
    "iso:country":"BE",
    "sg:address":"Rue Saint-gertrude 25",
    "sg:city":"Waterloo",
    "sg:classifiers":[
        {
            "category":"Building & Trades",
            "subcategory":"Pest Control",
            "type":"Services"
        }
    ],
    "sg:phone":"+32 2 354 15 63",
    "sg:postcode":"1410",
    "sg:province":"Brabant Wallon",
    "sg:tags":[
        "painting",
        "contractor"
    ],
    "wof:name":"Barigand Alain Sprl",
    "wof:placetype":"venue"
},
  "geometry": {"coordinates":[4.3617610931,50.712184906],"type":"Point"}
}