{
  "type": "Feature",
  "properties": {
    "addr:full":"Chauss\u00e9e Du Tilleul 199 Box 2 Wavre Brabant Wallon 1300",
    "addr:housenumber":"199;2;1300",
    "addr:street":"Chausse\u0301E Du Tilleul;Box",
    "iso:country":"BE",
    "sg:address":"Chauss\u00e9e Du Tilleul 199 Box 2",
    "sg:city":"Wavre",
    "sg:classifiers":[
        {
            "category":"Personal",
            "subcategory":"Massage",
            "type":"Services"
        }
    ],
    "sg:phone":"+32 10 22 29 99",
    "sg:postcode":"1300",
    "sg:province":"Brabant Wallon",
    "wof:name":"Vicente J C",
    "wof:placetype":"venue"
},
  "geometry": {"coordinates":[4.6166610718,50.7250175476],"type":"Point"}
}