{
  "type": "Feature",
  "properties": {
    "iso:country":"BE",
    "sg:address":"Van Volxemlaan 31",
    "sg:city":"Vorst/forest",
    "sg:orig_category":"Artsen and specialisten",
    "sg:phone":"+32 2 343 16 39",
    "sg:postcode":"1190",
    "sg:province":"Bruxelles-Capitale",
    "wof:name":"Nicole Vanden Bossche",
    "wof:placetype":"venue"
},
  "geometry": {"coordinates":[4.3251051903,50.8141822815],"type":"Point"}
}