{
  "type": "Feature",
  "properties": {
    "addr:full":"Rollebaan 68 Sint-genesius-rode/rhode-saint-gen\u00c8se Vlaams-Brabant 1640",
    "addr:housenumber":"68",
    "addr:postcode":"1640",
    "addr:street":"Rollebaan",
    "iso:country":"BE",
    "sg:address":"Rollebaan 68",
    "sg:city":"Sint-genesius-rode/rhode-saint-gen\u00c8se",
    "sg:orig_category":"Services de Nettoyage and de D\u00e9sinfection",
    "sg:phone":"+32 2 380 80 90",
    "sg:postcode":"1640",
    "sg:province":"Vlaams-Brabant",
    "wof:name":"Thierry",
    "wof:placetype":"venue"
},
  "geometry": {"coordinates":[4.353290081,50.74659729],"type":"Point"}
}