{
  "type": "Feature",
  "properties": {
    "addr:full":"Rue Du Ch\u00e2teau Kieffelt 7 Bruxelles (woluwe-saint-lambert) Bruxelles-Capitale 1200",
    "addr:housenumber":"7",
    "addr:postcode":"1200",
    "addr:street":"Rue Du Cha\u0302Teau Kieffelt",
    "iso:country":"BE",
    "sg:address":"Rue Du Ch\u00e2teau Kieffelt 7",
    "sg:city":"Bruxelles (woluwe-saint-lambert)",
    "sg:classifiers":[
        {
            "category":"Health Services",
            "subcategory":"Dentist",
            "type":"Services"
        }
    ],
    "sg:phone":"+32 2 772 28 98",
    "sg:postcode":"1200",
    "sg:province":"Bruxelles-Capitale",
    "wof:name":"Delmelle Pierre",
    "wof:placetype":"venue"
},
  "geometry": {"coordinates":[4.4431619644,50.8483581543],"type":"Point"}
}