{
  "type": "Feature",
  "properties": {
    "iso:country":"BE",
    "sg:address":"Brackvenn 5",
    "sg:city":"Eupen",
    "sg:orig_category":"D\u00e9chets and d\u00e9bris Gr",
    "sg:phone":"+32 87 74 33 14",
    "sg:postcode":"4700",
    "sg:province":"Li\u00e8ge",
    "wof:name":"Fa. Thonissen M. & D.",
    "wof:placetype":"venue"
},
  "geometry": {"coordinates":[6.0271630287,50.63722229],"type":"Point"}
}