{
  "type": "Feature",
  "properties": {
    "iso:country":"BE",
    "sg:address":"Avenue Jean Jaur\u00e8s 9",
    "sg:city":"Courcelles",
    "sg:classifiers":[
        {
            "category":"Retail",
            "subcategory":"Funeral Services",
            "type":"Services"
        }
    ],
    "sg:phone":"+32 71 45 28 46",
    "sg:postcode":"6180",
    "sg:province":"Hainaut",
    "sg:tags":[
        "director"
    ],
    "wof:name":"Demierbe J",
    "wof:placetype":"venue"
},
  "geometry": {"coordinates":[4.3755121231,50.4573020935],"type":"Point"}
}