{
  "type": "Feature",
  "properties": {
    "iso:country":"BE",
    "sg:address":"Keizersplein 66",
    "sg:city":"Aalst",
    "sg:classifiers":[
        {
            "category":"Professional",
            "subcategory":"Art Services",
            "type":"Services"
        }
    ],
    "sg:phone":"+32 53 78 64 67",
    "sg:postcode":"9300",
    "sg:province":"Oost-Vlaanderen",
    "sg:tags":[
        "photographer"
    ],
    "wof:name":"Studio Photo-line Bvba",
    "wof:placetype":"venue"
},
  "geometry": {"coordinates":[4.0381579399,50.9357185364],"type":"Point"}
}