{
  "type": "Feature",
  "properties": {
    "addr:full":"Rue Pierre Hans 5 Charleroi (monceau-sur-sambre) Hainaut 6031",
    "addr:housenumber":"5",
    "addr:postcode":"6031",
    "addr:street":"Rue Pierre Hans",
    "iso:country":"BE",
    "sg:address":"Rue Pierre Hans 5",
    "sg:city":"Charleroi (monceau-sur-sambre)",
    "sg:classifiers":[
        {
            "category":"Retail",
            "subcategory":"Auto Rental",
            "type":"Services"
        }
    ],
    "sg:phone":"+32 71 20 83 76",
    "sg:postcode":"6031",
    "sg:province":"Hainaut",
    "sg:tags":[
        "automobile",
        "-",
        "car",
        "self-drive"
    ],
    "wof:name":"D.k. Belgium",
    "wof:placetype":"venue"
},
  "geometry": {"coordinates":[4.369533062,50.4171028137],"type":"Point"}
}