{
  "type": "Feature",
  "properties": {
    "iso:country":"BE",
    "sg:address":"Schoterweg 238",
    "sg:city":"Tessenderlo",
    "sg:classifiers":[
        {
            "category":"Utilities",
            "subcategory":"Natural Gas",
            "type":"Services"
        }
    ],
    "sg:phone":"+32 13 66 20 33",
    "sg:postcode":"3980",
    "sg:province":"Limburg",
    "sg:tags":[
        "industrial",
        "-"
    ],
    "wof:name":"Hertenweg J",
    "wof:placetype":"venue"
},
  "geometry": {"coordinates":[5.0565400124,51.0672416687],"type":"Point"}
}