{
  "type": "Feature",
  "properties": {
    "addr:full":"Avenue Paul Terlinden 19 Rixensart Brabant Wallon 1330",
    "addr:housenumber":"19",
    "addr:postcode":"1330",
    "addr:street":"Avenue Paul Terlinden;Wallon",
    "iso:country":"BE",
    "sg:address":"Avenue Paul Terlinden 19",
    "sg:city":"Rixensart",
    "sg:orig_category":"Advocaten and juridische adviseurs",
    "sg:phone":"+32 2 653 76 32",
    "sg:postcode":"1330",
    "sg:province":"Brabant Wallon",
    "wof:name":"J.m. Maguin Vreux",
    "wof:placetype":"venue"
},
  "geometry": {"coordinates":[4.5334191322,50.7128486633],"type":"Point"}
}