{
  "type": "Feature",
  "properties": {
    "iso:country":"BE",
    "sg:address":"Place Albert Ier 8b2",
    "sg:city":"Fleurus",
    "sg:orig_category":"Avocats and conseillers juridiques",
    "sg:phone":"+32 71 81 53 69",
    "sg:postcode":"6220",
    "sg:province":"Hainaut",
    "wof:name":"J. Hordies",
    "wof:placetype":"venue"
},
  "geometry": {"coordinates":[4.5558428764,50.4590873718],"type":"Point"}
}