{
  "type": "Feature",
  "properties": {
    "iso:country":"BE",
    "sg:address":"Rue Jules Destr\u00c9e 105",
    "sg:city":"Courcelles",
    "sg:orig_category":"Tabac. Journaux",
    "sg:phone":"+32 71 45 48 35",
    "sg:postcode":"6183",
    "sg:province":"Hainaut",
    "wof:name":"Au Petit Ecolier",
    "wof:placetype":"venue"
},
  "geometry": {"coordinates":[4.3305897713,50.4651794434],"type":"Point"}
}