{
  "type": "Feature",
  "properties": {
    "iso:country":"BE",
    "sg:address":"Langerodestraat 8",
    "sg:city":"Huldenberg",
    "sg:orig_category":"Artsen and specialisten",
    "sg:phone":"+32 16 47 13 71",
    "sg:postcode":"3040",
    "sg:province":"Vlaams-Brabant",
    "wof:name":"C. Devalck",
    "wof:placetype":"venue"
},
  "geometry": {"coordinates":[4.6341428757,50.8285064697],"type":"Point"}
}