{
  "type": "Feature",
  "properties": {
    "addr:full":"Route De La Sauveni\u00c8re116 Spa Li\u00e8ge 4900",
    "addr:postcode":"4900",
    "addr:street":"Route De La Sauvenie\u0300Re116",
    "iso:country":"BE",
    "sg:address":"Route De La Sauveni\u00c8re116",
    "sg:city":"Spa",
    "sg:classifiers":[
        {
            "category":"Restaurant",
            "type":"Food & Drink"
        }
    ],
    "sg:phone":"+32 87 77 51 68",
    "sg:postcode":"4900",
    "sg:province":"Li\u00e8ge",
    "sg:tags":[
        "organisation",
        "de",
        "f\u00eates",
        "catering"
    ],
    "wof:name":"La Sauveni\u00c8re",
    "wof:placetype":"venue"
},
  "geometry": {"coordinates":[5.8635501862,50.4911689758],"type":"Point"}
}