{
  "type": "Feature",
  "properties": {
    "iso:country":"BE",
    "sg:address":"Hoogbeverenstraat 9",
    "sg:city":"Ardooie",
    "sg:orig_category":"Producteurs de l\u00e9gumes",
    "sg:phone":"+32 51 74 55 29",
    "sg:postcode":"8850",
    "sg:province":"West-Vlaanderen",
    "wof:name":"Antoon Depoortere",
    "wof:placetype":"venue"
},
  "geometry": {"coordinates":[3.1730620861,50.9828720093],"type":"Point"}
}