{
  "type": "Feature",
  "properties": {
    "iso:country":"BE",
    "sg:address":"Stokerijstraat 35",
    "sg:city":"Wijnegem",
    "sg:orig_category":"B\u00e9ton pr\u00eat \u00e0 l'emploi Fab",
    "sg:phone":"+32 3 353 17 35",
    "sg:postcode":"2110",
    "sg:province":"Antwerpen",
    "wof:name":"Readymix",
    "wof:placetype":"venue"
},
  "geometry": {"coordinates":[4.5350279808,51.2266273499],"type":"Point"}
}