{
  "type": "Feature",
  "properties": {
    "addr:full":"Kerkstraat 10 De Haan (wenduine) West-Vlaanderen 8420",
    "addr:housenumber":"10",
    "addr:postcode":"8420",
    "addr:street":"Kerkstraat",
    "iso:country":"BE",
    "sg:address":"Kerkstraat 10",
    "sg:city":"De Haan (wenduine)",
    "sg:classifiers":[
        {
            "category":"Shopping",
            "subcategory":"Clothing, Apparel, & Fashions",
            "type":"Retail Goods"
        }
    ],
    "sg:phone":"+32 50 41 68 41",
    "sg:postcode":"8420",
    "sg:province":"West-Vlaanderen",
    "sg:tags":[
        "boutique"
    ],
    "wof:name":"Brigitte",
    "wof:placetype":"venue"
},
  "geometry": {"coordinates":[3.079736948,51.3008804321],"type":"Point"}
}