{
  "type": "Feature",
  "properties": {
    "iso:country":"BE",
    "sg:address":"Pastorijstraat 56",
    "sg:city":"Tremelo",
    "sg:orig_category":"M\u00e9decins and sp\u00e9cialistes",
    "sg:phone":"+32 16 53 43 51",
    "sg:postcode":"3128",
    "sg:province":"Vlaams-Brabant",
    "wof:name":"Viviane Van Den Bergh",
    "wof:placetype":"venue"
},
  "geometry": {"coordinates":[4.7515950203,50.9983596802],"type":"Point"}
}