{
  "type": "Feature",
  "properties": {
    "addr:full":"Laaglandlei 70 Schoten Antwerpen 2900",
    "addr:housenumber":"70",
    "addr:postcode":"2900",
    "addr:street":"Laaglandlei",
    "iso:country":"BE",
    "sg:address":"Laaglandlei 70",
    "sg:city":"Schoten",
    "sg:orig_category":"Installatie van houten of kunststof schrijnwerk",
    "sg:phone":"+32 3 658 42 92",
    "sg:postcode":"2900",
    "sg:province":"Antwerpen",
    "wof:name":"Em. Verdijck",
    "wof:placetype":"venue"
},
  "geometry": {"coordinates":[4.5130119324,51.2503128052],"type":"Point"}
}