{
  "type": "Feature",
  "properties": {
    "addr:full":"Zuidlaan 32 Zele Oost-Vlaanderen 9240",
    "addr:housenumber":"32",
    "addr:postcode":"9240",
    "addr:street":"Zuidlaan",
    "iso:country":"BE",
    "sg:address":"Zuidlaan 32",
    "sg:city":"Zele",
    "sg:classifiers":[
        {
            "category":"Building & Trades",
            "subcategory":"Construction",
            "type":"Services"
        }
    ],
    "sg:phone":"+32 52 44 61 67",
    "sg:postcode":"9240",
    "sg:province":"Oost-Vlaanderen",
    "sg:tags":[
        "truss-makers"
    ],
    "wof:name":"De Bruyne A",
    "wof:placetype":"venue"
},
  "geometry": {"coordinates":[4.0311360359,51.0645370483],"type":"Point"}
}