{
  "type": "Feature",
  "properties": {
    "iso:country":"BE",
    "sg:address":"Scheidingsstraat 2",
    "sg:city":"Ruiselede",
    "sg:orig_category":"Producteurs de l\u00e9gumes",
    "sg:phone":"+32 51 68 92 07",
    "sg:postcode":"8755",
    "sg:province":"West-Vlaanderen",
    "wof:name":"Marnix De Smet",
    "wof:placetype":"venue"
},
  "geometry": {"coordinates":[3.3452599049,51.0581932068],"type":"Point"}
}