{
  "type": "Feature",
  "properties": {
    "iso:country":"BE",
    "sg:address":"Staatsbaan 25",
    "sg:city":"Maldegem (adegem)",
    "sg:classifiers":[
        {
            "category":"Shopping",
            "subcategory":"Clothing, Apparel, & Fashions",
            "type":"Retail Goods"
        }
    ],
    "sg:phone":"+32 50 71 15 90",
    "sg:postcode":"9991",
    "sg:province":"Oost-Vlaanderen",
    "sg:tags":[
        "clothing",
        "-",
        "gentleman"
    ],
    "wof:name":"Alibi Trends",
    "wof:placetype":"venue"
},
  "geometry": {"coordinates":[3.4786319733,51.2050323486],"type":"Point"}
}