{
  "type": "Feature",
  "properties": {
    "iso:country":"BE",
    "sg:address":"Torhoutsestraat 101",
    "sg:city":"Oostkamp",
    "sg:orig_category":"Woningbouw",
    "sg:phone":"+32 50 27 77 11",
    "sg:postcode":"8020",
    "sg:province":"West-Vlaanderen",
    "wof:name":"Dero-bouw",
    "wof:placetype":"venue"
},
  "geometry": {"coordinates":[3.2020509243,51.0891914368],"type":"Point"}
}