{
  "type": "Feature",
  "properties": {
    "addr:full":"Geraardsbergsestraat 71 Dilbeek (schepdaal) Vlaams-Brabant 1703",
    "addr:housenumber":"71",
    "addr:postcode":"1703",
    "addr:street":"Geraardsbergsestraat",
    "iso:country":"BE",
    "sg:address":"Geraardsbergsestraat 71",
    "sg:city":"Dilbeek (schepdaal)",
    "sg:classifiers":[
        {
            "category":"Health Services",
            "subcategory":"Dentist",
            "type":"Services"
        }
    ],
    "sg:phone":"+32 2 569 68 81",
    "sg:postcode":"1703",
    "sg:province":"Vlaams-Brabant",
    "wof:name":"Ceuterickx Vera",
    "wof:placetype":"venue"
},
  "geometry": {"coordinates":[4.2016158104,50.835609436],"type":"Point"}
}