{
  "type": "Feature",
  "properties": {
    "addr:full":"Wijgmaalsesteenweg 24 Haacht Vlaams-Brabant 3150",
    "addr:housenumber":"24",
    "addr:postcode":"3150",
    "addr:street":"Wijgmaalsesteenweg",
    "iso:country":"BE",
    "sg:address":"Wijgmaalsesteenweg 24",
    "sg:city":"Haacht",
    "sg:orig_category":"G\u00e9om\u00e8tres",
    "sg:phone":"+32 16 60 31 93",
    "sg:postcode":"3150",
    "sg:province":"Vlaams-Brabant",
    "wof:name":"Daniel Vanhoutvinck",
    "wof:placetype":"venue"
},
  "geometry": {"coordinates":[4.6667690277,50.9605064392],"type":"Point"}
}