{
  "type": "Feature",
  "properties": {
    "addr:full":"Rue G\u00e9ron 38 Andenne (seilles) Namur 5300",
    "addr:housenumber":"38",
    "addr:postcode":"5300",
    "addr:street":"Rue Ge\u0301Ron",
    "iso:country":"BE",
    "sg:address":"Rue G\u00e9ron 38",
    "sg:city":"Andenne (seilles)",
    "sg:classifiers":[
        {
            "category":"Food & Beverages",
            "subcategory":"Fruits & Vegetables",
            "type":"Retail Goods"
        }
    ],
    "sg:phone":"+32 85 82 62 02",
    "sg:postcode":"5300",
    "sg:province":"Namur",
    "sg:tags":[
        "-"
    ],
    "wof:name":"Pirotte V",
    "wof:placetype":"venue"
},
  "geometry": {"coordinates":[5.0982642174,50.4863739014],"type":"Point"}
}