{
  "type": "Feature",
  "properties": {
    "addr:full":"Prieelstraat 100 Asse Vlaams-Brabant 1730",
    "addr:housenumber":"100",
    "addr:postcode":"1730",
    "addr:street":"Prieelstraat",
    "iso:country":"BE",
    "sg:address":"Prieelstraat 100",
    "sg:city":"Asse",
    "sg:classifiers":[
        {
            "category":"Real Estate",
            "subcategory":"Architect",
            "type":"Services"
        }
    ],
    "sg:phone":"+32 2 452 88 08",
    "sg:postcode":"1730",
    "sg:province":"Vlaams-Brabant",
    "wof:name":"Van Mulders L",
    "wof:placetype":"venue"
},
  "geometry": {"coordinates":[4.1931371689,50.9186706543],"type":"Point"}
}