{
  "type": "Feature",
  "properties": {
    "addr:full":"Avenue Everard 22 Vorst/forest Bruxelles-Capitale 1190",
    "addr:housenumber":"22",
    "addr:postcode":"1190",
    "addr:street":"Avenue Everard;/ Forest",
    "iso:country":"BE",
    "sg:address":"Avenue Everard 22",
    "sg:city":"Vorst/forest",
    "sg:classifiers":[
        {
            "category":"Personal",
            "subcategory":"Beauty Salon",
            "type":"Services"
        }
    ],
    "sg:phone":"+32 2 344 53 24",
    "sg:postcode":"1190",
    "sg:province":"Bruxelles-Capitale",
    "sg:tags":[
        "de",
        "coiffure"
    ],
    "wof:name":"Pherez Harmonie Capillaire",
    "wof:placetype":"venue"
},
  "geometry": {"coordinates":[4.3384308815,50.8161506653],"type":"Point"}
}