{
  "type": "Feature",
  "properties": {
    "iso:country":"BE",
    "sg:address":"Rue Charles Piron 66",
    "sg:city":"Ghlin",
    "sg:orig_category":"Fitnesscentra",
    "sg:phone":"+32 65 35 17 94",
    "sg:postcode":"7011",
    "sg:province":"Hainaut",
    "wof:name":"Anatomic Center",
    "wof:placetype":"venue"
},
  "geometry": {"coordinates":[3.9181358814,50.4708938599],"type":"Point"}
}