{
  "type": "Feature",
  "properties": {
    "addr:full":"Rue Neuve Du Pont 10 Renaix Oost-Vlaanderen 9600",
    "addr:housenumber":"10",
    "addr:postcode":"9600",
    "addr:street":"Rue Neuve Du Pont",
    "iso:country":"BE",
    "sg:address":"Rue Neuve Du Pont 10",
    "sg:city":"Renaix",
    "sg:classifiers":[
        {
            "category":"Home & Garden",
            "subcategory":"Carpets & Floor Coverings",
            "type":"Retail Goods"
        }
    ],
    "sg:phone":"+32 55 21 06 20",
    "sg:postcode":"9600",
    "sg:province":"Oost-Vlaanderen",
    "sg:tags":[
        "parquet"
    ],
    "wof:name":"Gerko Bvba",
    "wof:placetype":"venue"
},
  "geometry": {"coordinates":[3.5763700008,50.739692688],"type":"Point"}
}