{
  "type": "Feature",
  "properties": {
    "addr:full":"Szamotulystraat 3 Tielt West-Vlaanderen 8700",
    "addr:housenumber":"3",
    "addr:postcode":"8700",
    "addr:street":"Szamotulystraat",
    "iso:country":"BE",
    "sg:address":"Szamotulystraat 3",
    "sg:city":"Tielt",
    "sg:classifiers":[
        {
            "category":"Manufacturing",
            "subcategory":"Rubber & Plastics",
            "type":"Manufacturing & Wholesale Goods"
        }
    ],
    "sg:phone":"+32 51 68 93 77",
    "sg:postcode":"8700",
    "sg:province":"West-Vlaanderen",
    "sg:tags":[
        "pipe",
        "-"
    ],
    "wof:name":"Liberty Trading Nv",
    "wof:placetype":"venue"
},
  "geometry": {"coordinates":[3.3592998981,50.9967002869],"type":"Point"}
}