{
  "type": "Feature",
  "properties": {
    "addr:full":"Rue L\u00e9on Charlier 70 Wanze Li\u00e8ge 4520",
    "addr:housenumber":"70",
    "addr:postcode":"4520",
    "addr:street":"Rue Le\u0301On Charlier",
    "iso:country":"BE",
    "sg:address":"Rue L\u00e9on Charlier 70",
    "sg:city":"Wanze",
    "sg:classifiers":[
        {
            "category":"Health Services",
            "subcategory":"Health Practitioner",
            "type":"Services"
        }
    ],
    "sg:phone":"+32 85 23 23 91",
    "sg:postcode":"4520",
    "sg:province":"Li\u00e8ge",
    "sg:tags":[
        "physiotherapist"
    ],
    "wof:name":"Degotte J-p",
    "wof:placetype":"venue"
},
  "geometry": {"coordinates":[5.2036042213,50.5309104919],"type":"Point"}
}