{
  "type": "Feature",
  "properties": {
    "addr:full":"Jubellaan 80 Mechelen Antwerpen 2800",
    "addr:housenumber":"80",
    "addr:postcode":"2800",
    "addr:street":"Jubellaan",
    "iso:country":"BE",
    "sg:address":"Jubellaan 80",
    "sg:city":"Mechelen",
    "sg:orig_category":"Quincailleries",
    "sg:phone":"+32 15 43 32 12",
    "sg:postcode":"2800",
    "sg:province":"Antwerpen",
    "wof:name":"Van Marcke",
    "wof:placetype":"venue"
},
  "geometry": {"coordinates":[4.4771351814,51.0048065186],"type":"Point"}
}