{
  "type": "Feature",
  "properties": {
    "addr:full":"Berckmansstraat 62 Sint-gillis/saint-gilles Bruxelles-Capitale 1060",
    "addr:housenumber":"62",
    "addr:postcode":"1060",
    "addr:street":"Berckmansstraat",
    "iso:country":"BE",
    "sg:address":"Berckmansstraat 62",
    "sg:city":"Sint-gillis/saint-gilles",
    "sg:classifiers":[
        {
            "category":"Insurance",
            "subcategory":"Insurance Agent",
            "type":"Services"
        }
    ],
    "sg:phone":"+32 2 543 02 50",
    "sg:postcode":"1060",
    "sg:province":"Bruxelles-Capitale",
    "sg:tags":[
        "verzekeringsmakelaars",
        "expert"
    ],
    "wof:name":"Heger O.",
    "wof:placetype":"venue"
},
  "geometry": {"coordinates":[4.3541488647,50.8316612244],"type":"Point"}
}