{
  "type": "Feature",
  "properties": {
    "addr:full":"Avenue Rogier 154 Brussel/bruxelles Bruxelles-Capitale 1030",
    "addr:housenumber":"154",
    "addr:postcode":"1030",
    "addr:street":"Avenue Rogier;/",
    "iso:country":"BE",
    "sg:address":"Avenue Rogier 154",
    "sg:city":"Brussel/bruxelles",
    "sg:orig_category":"Technische and wetenschappelijke instrumenten Fab",
    "sg:phone":"+32 2 216 96 26",
    "sg:postcode":"1030",
    "sg:province":"Bruxelles-Capitale",
    "wof:name":"Pasture Cie",
    "wof:placetype":"venue"
},
  "geometry": {"coordinates":[4.3822999001,50.858543396],"type":"Point"}
}