{
  "type": "Feature",
  "properties": {
    "iso:country":"BE",
    "sg:address":"Wolvertemsesteenweg 74",
    "sg:city":"Grimbergen",
    "sg:orig_category":"Charpentes and couvertures. Construction de maisons",
    "sg:phone":"+32 2 269 63 87",
    "sg:postcode":"1850",
    "sg:province":"Vlaams-Brabant",
    "wof:name":"Eikenblok",
    "wof:placetype":"venue"
},
  "geometry": {"coordinates":[4.3680582047,50.935459137],"type":"Point"}
}