{
  "type": "Feature",
  "properties": {
    "addr:full":"Gemeenteplein 6 Leuven (groot) Vlaams-Brabant 3010",
    "addr:housenumber":"6",
    "addr:postcode":"3010",
    "addr:street":"Gemeenteplein;Groot Vlaams-Brabant",
    "iso:country":"BE",
    "sg:address":"Gemeenteplein 6",
    "sg:city":"Leuven (groot)",
    "sg:orig_category":"Banken and kredietinstellingen",
    "sg:phone":"+32 16 35 91 20",
    "sg:postcode":"3010",
    "sg:province":"Vlaams-Brabant",
    "wof:name":"Dexia",
    "wof:placetype":"venue"
},
  "geometry": {"coordinates":[4.7304501534,50.889755249],"type":"Point"}
}