{
  "type": "Feature",
  "properties": {
    "iso:country":"BE",
    "sg:address":"Gentsesteenweg 190",
    "sg:city":"Zele",
    "sg:orig_category":"Installation de menuiserie en bois and plastique. Articles de sport, camping and jouets Gr",
    "sg:phone":"+32 52 44 52 07",
    "sg:postcode":"9240",
    "sg:province":"Oost-Vlaanderen",
    "wof:name":"Sporta De Waele",
    "wof:placetype":"venue"
},
  "geometry": {"coordinates":[4.0163211823,51.0574111938],"type":"Point"}
}