{
  "type": "Feature",
  "properties": {
    "addr:full":"Kiemerstraat 127 Sint-niklaas Oost-Vlaanderen 9100",
    "addr:housenumber":"127",
    "addr:postcode":"9100",
    "addr:street":"Kiemerstraat",
    "iso:country":"BE",
    "sg:address":"Kiemerstraat 127",
    "sg:city":"Sint-niklaas",
    "sg:orig_category":"Diepvriesproducten Gh Zuivelproducten",
    "sg:phone":"+32 3 776 13 29",
    "sg:postcode":"9100",
    "sg:province":"Oost-Vlaanderen",
    "wof:name":"Francois De Leeuw",
    "wof:placetype":"venue"
},
  "geometry": {"coordinates":[4.1343522072,51.1354637146],"type":"Point"}
}