{
  "type": "Feature",
  "properties": {
    "addr:full":"Rode Kruisstraat 14 Oud-turnhout Antwerpen 2360",
    "addr:housenumber":"14",
    "addr:postcode":"2360",
    "addr:street":"Rode Kruisstraat",
    "iso:country":"BE",
    "sg:address":"Rode Kruisstraat 14",
    "sg:city":"Oud-turnhout",
    "sg:classifiers":[
        {
            "category":"Utilities",
            "subcategory":"Telephone",
            "type":"Services"
        }
    ],
    "sg:phone":"+32 14 72 07 22",
    "sg:postcode":"2360",
    "sg:province":"Antwerpen",
    "sg:tags":[
        "-",
        "internet"
    ],
    "wof:name":"Webline",
    "wof:placetype":"venue"
},
  "geometry": {"coordinates":[4.9804339409,51.3216438293],"type":"Point"}
}