{
  "type": "Feature",
  "properties": {
    "addr:full":"Zavel 7 Lochristi Oost-Vlaanderen 9080",
    "addr:housenumber":"7",
    "addr:postcode":"9080",
    "addr:street":"Zavel",
    "iso:country":"BE",
    "sg:address":"Zavel 7",
    "sg:city":"Lochristi",
    "sg:orig_category":"Gestion des d\u00e9charges and sites d\u00e9finitifs de stockage",
    "sg:phone":"+32 9 355 52 06",
    "sg:postcode":"9080",
    "sg:province":"Oost-Vlaanderen",
    "wof:name":"Containerpark Lochristi",
    "wof:placetype":"venue"
},
  "geometry": {"coordinates":[3.8867409229,51.1081085205],"type":"Point"}
}