{
  "type": "Feature",
  "properties": {
    "addr:full":"Schooldreef 23-5 Mol Antwerpen 2400",
    "addr:housenumber":"23-5",
    "addr:postcode":"2400",
    "addr:street":"Schooldreef",
    "iso:country":"BE",
    "sg:address":"Schooldreef 23-5",
    "sg:city":"Mol",
    "sg:classifiers":[
        {
            "category":"Shopping",
            "subcategory":"Luggage & Leather Goods",
            "type":"Retail Goods"
        }
    ],
    "sg:phone":"+32 14 81 33 40",
    "sg:postcode":"2400",
    "sg:province":"Antwerpen",
    "sg:tags":[
        "luggage-carriers"
    ],
    "wof:name":"Kings",
    "wof:placetype":"venue"
},
  "geometry": {"coordinates":[5.2068858147,51.2094192505],"type":"Point"}
}