{
  "type": "Feature",
  "properties": {
    "iso:country":"BE",
    "sg:address":"Westerlosesteenweg 165",
    "sg:city":"Herselt",
    "sg:classifiers":[
        {
            "category":"Wholesale",
            "subcategory":"Construction Materials",
            "type":"Manufacturing & Wholesale Goods"
        }
    ],
    "sg:phone":"+32 14 54 22 02",
    "sg:postcode":"2230",
    "sg:province":"Antwerpen",
    "sg:tags":[
        "civil",
        "engineering",
        "-"
    ],
    "wof:name":"Qubus Civiele & Waterbouwtechnieken Bvba",
    "wof:placetype":"venue"
},
  "geometry": {"coordinates":[4.8923602104,51.0659103394],"type":"Point"}
}