{
  "type": "Feature",
  "properties": {
    "iso:country":"BE",
    "sg:address":"Naamsesteenweg 218",
    "sg:city":"Sint-truiden",
    "sg:classifiers":[
        {
            "category":"Banks & Credit Unions",
            "subcategory":"Investment Brokerage",
            "type":"Services"
        }
    ],
    "sg:phone":"+32 11 70 55 70",
    "sg:postcode":"3800",
    "sg:province":"Limburg",
    "sg:tags":[
        "development",
        "electronics"
    ],
    "wof:name":"B&a Development B.v.b.a.",
    "wof:placetype":"venue"
},
  "geometry": {"coordinates":[5.1812000275,50.8059883118],"type":"Point"}
}