{
  "type": "Feature",
  "properties": {
    "iso:country":"BE",
    "sg:address":"Gistelsteenweg 541",
    "sg:city":"Jabbeke",
    "sg:classifiers":[
        {
            "category":"Real Estate",
            "subcategory":"Architect",
            "type":"Services"
        }
    ],
    "sg:phone":"+32 50 81 33 75",
    "sg:postcode":"8490",
    "sg:province":"West-Vlaanderen",
    "wof:name":"Moyaert B",
    "wof:placetype":"venue"
},
  "geometry": {"coordinates":[3.0699179173,51.1752281189],"type":"Point"}
}