{
  "type": "Feature",
  "properties": {
    "addr:full":"Sq A Masson 1 Namur Namur 5000",
    "addr:housenumber":"1",
    "addr:postcode":"5000",
    "addr:street":"Sq;Masson",
    "iso:country":"BE",
    "sg:address":"Sq A Masson 1",
    "sg:city":"Namur",
    "sg:classifiers":[
        {
            "category":"Banks & Credit Unions",
            "subcategory":"Bank",
            "type":"Services"
        }
    ],
    "sg:postcode":"5000",
    "sg:province":"Namur",
    "wof:name":"Finest",
    "wof:placetype":"venue"
},
  "geometry": {"coordinates":[4.356523037,50.8498725891],"type":"Point"}
}