{
  "type": "Feature",
  "properties": {
    "iso:country":"BE",
    "sg:address":"Rue Sainte-gertrude 18",
    "sg:city":"Jodoigne",
    "sg:orig_category":"Woningbouw",
    "sg:phone":"+32 10 81 14 74",
    "sg:postcode":"1370",
    "sg:province":"Brabant Wallon",
    "wof:name":"Neerdael-molle Et Fils",
    "wof:placetype":"venue"
},
  "geometry": {"coordinates":[4.9159641266,50.7229881287],"type":"Point"}
}