{
  "type": "Feature",
  "properties": {
    "addr:full":"Sint-bavostraat 6 Wielsbeke West-Vlaanderen 8710",
    "addr:housenumber":"6",
    "addr:postcode":"8710",
    "addr:street":"Sint-Bavostraat;West-Vlaanderen",
    "iso:country":"BE",
    "sg:address":"Sint-bavostraat 6",
    "sg:city":"Wielsbeke",
    "sg:orig_category":"Verplichte sociale verzekeringen",
    "sg:phone":"+32 56 60 10 54",
    "sg:postcode":"8710",
    "sg:province":"West-Vlaanderen",
    "wof:name":"Kristelijk Ziekenfonds",
    "wof:placetype":"venue"
},
  "geometry": {"coordinates":[3.3908069134,50.9097633362],"type":"Point"}
}