{
  "type": "Feature",
  "properties": {
    "addr:full":"Doornstraat 60 Sint-gillis-waas Oost-Vlaanderen 9170",
    "addr:housenumber":"60",
    "addr:postcode":"9170",
    "addr:street":"Doornstraat",
    "iso:country":"BE",
    "sg:address":"Doornstraat 60",
    "sg:city":"Sint-gillis-waas",
    "sg:orig_category":"Producteurs de fruits",
    "sg:phone":"+32 3 770 53 55",
    "sg:postcode":"9170",
    "sg:province":"Oost-Vlaanderen",
    "wof:name":"Luc Tack",
    "wof:placetype":"venue"
},
  "geometry": {"coordinates":[4.1258249283,51.2096977234],"type":"Point"}
}