{
  "type": "Feature",
  "properties": {
    "iso:country":"BE",
    "sg:address":"Diesterstraat 72",
    "sg:city":"Sint-truiden",
    "sg:orig_category":"Pain, p\u00e2tisseries and confiseries",
    "sg:phone":"+32 11 68 71 89",
    "sg:postcode":"3800",
    "sg:province":"Limburg",
    "wof:name":"Jean Brans",
    "wof:placetype":"venue"
},
  "geometry": {"coordinates":[5.1826329231,50.8183097839],"type":"Point"}
}