{
  "type": "Feature",
  "properties": {
    "iso:country":"BE",
    "sg:address":"Marcel Habetslaan 27",
    "sg:city":"Genk",
    "sg:classifiers":[
        {
            "category":"Cafe",
            "type":"Food & Drink"
        }
    ],
    "sg:phone":"+32 89 38 38 42",
    "sg:postcode":"3600",
    "sg:province":"Limburg",
    "sg:tags":[
        "caf\u00e9s"
    ],
    "wof:name":"Coninx-mitskou",
    "wof:placetype":"venue"
},
  "geometry": {"coordinates":[5.4927558899,51.011920929],"type":"Point"}
}