{
  "type": "Feature",
  "properties": {
    "iso:country":"BE",
    "sg:address":"Tuinstraat 4",
    "sg:city":"Kasterlee (lichtaart)",
    "sg:classifiers":[
        {
            "category":"Personal",
            "subcategory":"Nail Salon",
            "type":"Services"
        }
    ],
    "sg:phone":"+32 14 55 42 88",
    "sg:postcode":"2460",
    "sg:province":"Antwerpen",
    "sg:tags":[
        "pedicure"
    ],
    "wof:name":"Gerda",
    "wof:placetype":"venue"
},
  "geometry": {"coordinates":[4.9190211296,51.2256965637],"type":"Point"}
}