{
  "type": "Feature",
  "properties": {
    "addr:full":"Rue De La Perche 1 Dour Hainaut 7370",
    "addr:housenumber":"1",
    "addr:postcode":"7370",
    "addr:street":"Rue De La Perche;Hainaut",
    "iso:country":"BE",
    "sg:address":"Rue De La Perche 1",
    "sg:city":"Dour",
    "sg:orig_category":"Epiceries",
    "sg:phone":"+32 65 65 31 51",
    "sg:postcode":"7370",
    "sg:province":"Hainaut",
    "wof:name":"Maison Schiavone",
    "wof:placetype":"venue"
},
  "geometry": {"coordinates":[3.7785201073,50.39635849],"type":"Point"}
}