{
  "type": "Feature",
  "properties": {
    "addr:full":"Nonnendijk 2 Damme West-Vlaanderen 8340",
    "addr:housenumber":"2",
    "addr:postcode":"8340",
    "addr:street":"Nonnendijk",
    "iso:country":"BE",
    "sg:address":"Nonnendijk 2",
    "sg:city":"Damme",
    "sg:orig_category":"Eleveurs de bovins",
    "sg:phone":"+32 50 50 17 42",
    "sg:postcode":"8340",
    "sg:province":"West-Vlaanderen",
    "wof:name":"Jozef Dendooven",
    "wof:placetype":"venue"
},
  "geometry": {"coordinates":[3.3792541027,51.2669525146],"type":"Point"}
}