{
  "type": "Feature",
  "properties": {
    "iso:country":"BE",
    "sg:address":"Postbaan 146",
    "sg:city":"Diest",
    "sg:orig_category":"Woningbouw",
    "sg:phone":"+32 13 32 71 09",
    "sg:postcode":"3290",
    "sg:province":"Vlaams-Brabant",
    "wof:name":"Wils Frank",
    "wof:placetype":"venue"
},
  "geometry": {"coordinates":[5.0900030136,50.9981651306],"type":"Point"}
}