{
  "type": "Feature",
  "properties": {
    "addr:full":"Brucargo 706 Zaventem Vlaams-Brabant 1930",
    "addr:housenumber":"706",
    "addr:postcode":"1930",
    "addr:street":"Brucargo",
    "iso:country":"BE",
    "sg:address":"Brucargo 706",
    "sg:city":"Zaventem",
    "sg:classifiers":[
        {
            "category":"Banks & Credit Unions",
            "subcategory":"Bank",
            "type":"Services"
        }
    ],
    "sg:phone":"+32 2 751 92 03",
    "sg:postcode":"1930",
    "sg:province":"Vlaams-Brabant",
    "wof:name":"Kredietbank Nv",
    "wof:placetype":"venue"
},
  "geometry": {"coordinates":[4.4741148949,50.8835449219],"type":"Point"}
}