{
  "type": "Feature",
  "properties": {
    "iso:country":"BE",
    "sg:address":"Lindelsebaan 248",
    "sg:city":"Overpelt",
    "sg:classifiers":[
        {
            "category":"Restaurant",
            "type":"Food & Drink"
        }
    ],
    "sg:phone":"+32 11 66 44 59",
    "sg:postcode":"3900",
    "sg:province":"Limburg",
    "sg:tags":[
        "caf\u00e9s"
    ],
    "wof:name":"Taverne Lindelhof",
    "wof:placetype":"venue"
},
  "geometry": {"coordinates":[5.4034051895,51.2007408142],"type":"Point"}
}