{
  "type": "Feature",
  "properties": {
    "iso:country":"BE",
    "sg:address":"Avenue Des Coteaux 171",
    "sg:city":"Li\u00e8ge 1 (grivegn\u00e9e)",
    "sg:classifiers":[
        {
            "category":"Shopping",
            "subcategory":"Stationery & Office Supplies",
            "type":"Retail Goods"
        }
    ],
    "sg:phone":"+32 4 343 05 09",
    "sg:postcode":"4030",
    "sg:province":"Li\u00e8ge",
    "sg:tags":[
        "exchange"
    ],
    "wof:name":"Deschampheleire L Et F Sprl",
    "wof:placetype":"venue"
},
  "geometry": {"coordinates":[5.5996479988,50.6241836548],"type":"Point"}
}