{
  "type": "Feature",
  "properties": {
    "addr:full":"Rue Oscar Roger 33 Tournai (blandain - Hertain) Hainaut 7522",
    "addr:housenumber":"33",
    "addr:postcode":"7522",
    "addr:street":"Rue Oscar Roger;Hainaut",
    "iso:country":"BE",
    "sg:address":"Rue Oscar Roger 33",
    "sg:city":"Tournai (blandain - Hertain)",
    "sg:classifiers":[
        {
            "category":"Professional",
            "subcategory":"Testing Lab",
            "type":"Services"
        }
    ],
    "sg:phone":"+32 69 35 22 15",
    "sg:postcode":"7522",
    "sg:province":"Hainaut",
    "sg:tags":[
        "chemist"
    ],
    "wof:name":"Demuynck",
    "wof:placetype":"venue"
},
  "geometry": {"coordinates":[3.3056230545,50.6270065308],"type":"Point"}
}