{
  "type": "Feature",
  "properties": {
    "iso:country":"BE",
    "sg:address":"Noir Mouton 8",
    "sg:city":"Celles (escanaffles)",
    "sg:orig_category":"Non-Classified Establishments",
    "sg:phone":"+32 69 45 65 52",
    "sg:postcode":"7760",
    "sg:province":"Hainaut",
    "wof:name":"Neuvi\u00e8me Dragon (le)",
    "wof:placetype":"venue"
},
  "geometry": {"coordinates":[3.4733870029,50.7370643616],"type":"Point"}
}