{
  "type": "Feature",
  "properties": {
    "addr:full":"De Pintelaan 185 Gent Oost-Vlaanderen 9000",
    "addr:housenumber":"185",
    "addr:postcode":"9000",
    "addr:street":"Pintelaan;Oost-Vlaanderen",
    "iso:country":"BE",
    "sg:address":"De Pintelaan 185",
    "sg:city":"Gent",
    "sg:classifiers":[
        {
            "category":"Community Center",
            "type":"Public Place"
        }
    ],
    "sg:phone":"+32 9 240 35 72",
    "sg:postcode":"9000",
    "sg:province":"Oost-Vlaanderen",
    "sg:tags":[
        "medical"
    ],
    "wof:name":"Centrum Voor Gehoor- & Spraakrevalidatie",
    "wof:placetype":"venue"
},
  "geometry": {"coordinates":[3.7236289978,51.0276527405],"type":"Point"}
}