{
  "type": "Feature",
  "properties": {
    "iso:country":"BE",
    "sg:address":"Rue Des Fran\u00c7ais 47",
    "sg:city":"Peruwelz",
    "sg:orig_category":"Huisdieren and benodigdheden",
    "sg:phone":"+32 69 77 70 75",
    "sg:postcode":"7600",
    "sg:province":"Hainaut",
    "wof:name":"La Maison Qui Chante",
    "wof:placetype":"venue"
},
  "geometry": {"coordinates":[3.5923700333,50.5132064819],"type":"Point"}
}