{
  "type": "Feature",
  "properties": {
    "addr:full":"Rue D\u00b4assaut 1 Brussel/bruxelles Bruxelles-Capitale 1000",
    "addr:housenumber":"1",
    "addr:postcode":"1000",
    "addr:street":"Rue D\u00b4Assaut;/",
    "iso:country":"BE",
    "sg:address":"Rue D\u00b4assaut 1",
    "sg:city":"Brussel/bruxelles",
    "sg:orig_category":"Imprimeries and copyshops",
    "sg:phone":"+32 2 503 30 43",
    "sg:postcode":"1000",
    "sg:province":"Bruxelles-Capitale",
    "wof:name":"Good Luck Copies",
    "wof:placetype":"venue"
},
  "geometry": {"coordinates":[4.3568048477,50.8487968445],"type":"Point"}
}