{
  "type": "Feature",
  "properties": {
    "addr:full":"Vlaamsekaai 27 Gent Oost-Vlaanderen 9000",
    "addr:housenumber":"27",
    "addr:postcode":"9000",
    "addr:street":"Vlaamsekaai;Oost-Vlaanderen",
    "iso:country":"BE",
    "sg:address":"Vlaamsekaai 27",
    "sg:city":"Gent",
    "sg:classifiers":[
        {
            "category":"Health Services",
            "subcategory":"Dentist",
            "type":"Services"
        }
    ],
    "sg:phone":"+32 9 224 29 26",
    "sg:postcode":"9000",
    "sg:province":"Oost-Vlaanderen",
    "wof:name":"Van Mullem J",
    "wof:placetype":"venue"
},
  "geometry": {"coordinates":[3.7421569824,51.04454422],"type":"Point"}
}