{
  "type": "Feature",
  "properties": {
    "iso:country":"BE",
    "sg:address":"Zandstraat 14",
    "sg:city":"Sint-laureins",
    "sg:orig_category":"Elektrische installaties voor woningen",
    "sg:phone":"+32 9 379 96 13",
    "sg:postcode":"9988",
    "sg:province":"Oost-Vlaanderen",
    "wof:name":"Philippe Van Hevele",
    "wof:placetype":"venue"
},
  "geometry": {"coordinates":[3.5946409702,51.2935028076],"type":"Point"}
}