{
  "type": "Feature",
  "properties": {
    "iso:country":"BE",
    "sg:address":"Ertsenrijkstraat 136",
    "sg:city":"Halen",
    "sg:orig_category":"Diensten voor huisdieren",
    "sg:phone":"+32 13 44 45 21",
    "sg:postcode":"3545",
    "sg:province":"Limburg",
    "wof:name":"Hondenhotel Viking",
    "wof:placetype":"venue"
},
  "geometry": {"coordinates":[5.1238250732,50.9191055298],"type":"Point"}
}