{
  "type": "Feature",
  "properties": {
    "iso:country":"BE",
    "sg:address":"Allaertshuizenstraat 7",
    "sg:city":"Koksijde",
    "sg:orig_category":"Eleveurs de bovins",
    "sg:phone":"+32 58 23 74 90",
    "sg:postcode":"8670",
    "sg:province":"West-Vlaanderen",
    "wof:name":"Andre Vandewoude",
    "wof:placetype":"venue"
},
  "geometry": {"coordinates":[2.7276439667,51.0990486145],"type":"Point"}
}