{
  "type": "Feature",
  "properties": {
    "iso:country":"BE",
    "sg:address":"Berkendaalstraat 189",
    "sg:city":"Elsene/ixelles",
    "sg:orig_category":"Advocaten and juridische adviseurs",
    "sg:phone":"+32 2 345 73 27",
    "sg:postcode":"1050",
    "sg:province":"Bruxelles-Capitale",
    "wof:name":"A. Wijns",
    "wof:placetype":"venue"
},
  "geometry": {"coordinates":[4.3526301384,50.8167610168],"type":"Point"}
}