{
  "type": "Feature",
  "properties": {
    "addr:full":"Eduard Anseelestraat 44 Willebroek Antwerpen 2830",
    "addr:housenumber":"44",
    "addr:postcode":"2830",
    "addr:street":"Eduard Anseelestraat",
    "iso:country":"BE",
    "sg:address":"Eduard Anseelestraat 44",
    "sg:city":"Willebroek",
    "sg:orig_category":"Supermarch\u00e9s",
    "sg:phone":"+32 3 886 92 65",
    "sg:postcode":"2830",
    "sg:province":"Antwerpen",
    "wof:name":"Profi",
    "wof:placetype":"venue"
},
  "geometry": {"coordinates":[4.357670784,51.0638313293],"type":"Point"}
}