{
  "type": "Feature",
  "properties": {
    "iso:country":"BE",
    "sg:address":"Rue Georges-cousot 2",
    "sg:city":"Dinant",
    "sg:classifiers":[
        {
            "category":"Fast Food",
            "type":"Food & Drink"
        }
    ],
    "sg:phone":"+32 82 22 63 65",
    "sg:postcode":"5500",
    "sg:province":"Namur",
    "sg:tags":[
        "\u00c0",
        "emporter",
        "restaurants"
    ],
    "wof:name":"S. Lemoine",
    "wof:placetype":"venue"
},
  "geometry": {"coordinates":[4.915060997,50.2554283142],"type":"Point"}
}