{
  "type": "Feature",
  "properties": {
    "addr:full":"Kleitstraat 11 Zomergem Oost-Vlaanderen 9930",
    "addr:housenumber":"11",
    "addr:postcode":"9930",
    "addr:street":"Kleitstraat",
    "iso:country":"BE",
    "sg:address":"Kleitstraat 11",
    "sg:city":"Zomergem",
    "sg:orig_category":"Artsen and specialisten",
    "sg:phone":"+32 9 372 70 45",
    "sg:postcode":"9930",
    "sg:province":"Oost-Vlaanderen",
    "wof:name":"P. Van Der Haeghen",
    "wof:placetype":"venue"
},
  "geometry": {"coordinates":[3.5588240623,51.1190605164],"type":"Point"}
}