{
  "type": "Feature",
  "properties": {
    "addr:full":"Avenue De L'europe 113 Ans Li\u00e8ge 4430",
    "addr:housenumber":"113",
    "addr:postcode":"4430",
    "addr:street":"Avenue De L'Europe",
    "iso:country":"BE",
    "sg:address":"Avenue De L'europe 113",
    "sg:city":"Ans",
    "sg:classifiers":[
        {
            "category":"Organizations",
            "subcategory":"Professional Association",
            "type":"Services"
        }
    ],
    "sg:phone":"+32 4 263 79 24",
    "sg:postcode":"4430",
    "sg:province":"Li\u00e8ge",
    "sg:tags":[
        "tie",
        "scarf"
    ],
    "wof:name":"B.p.i.-trading Sprl",
    "wof:placetype":"venue"
},
  "geometry": {"coordinates":[5.5236420631,50.6649513245],"type":"Point"}
}