{
  "type": "Feature",
  "properties": {
    "iso:country":"BE",
    "sg:address":"'t Veer 4",
    "sg:city":"Mechelen",
    "sg:classifiers":[
        {
            "category":"Home & Garden",
            "subcategory":"Carpets & Floor Coverings",
            "type":"Retail Goods"
        }
    ],
    "sg:phone":"+32 15 20 47 41",
    "sg:postcode":"2800",
    "sg:province":"Antwerpen",
    "sg:tags":[
        "tile"
    ],
    "wof:name":"Dancaers E",
    "wof:placetype":"venue"
},
  "geometry": {"coordinates":[4.4730520248,51.0294418335],"type":"Point"}
}