{
  "type": "Feature",
  "properties": {
    "addr:full":"Gal Anc.hotel Des Postes 62 Bruxelles Bruxelles-Capitale 1000",
    "addr:housenumber":"62",
    "addr:postcode":"1000",
    "iso:country":"BE",
    "sg:address":"Gal Anc.hotel Des Postes 62",
    "sg:city":"Bruxelles",
    "sg:classifiers":[
        {
            "category":"Bars & Pubs",
            "type":"Food & Drink"
        }
    ],
    "sg:phone":"+32 2 219 69 13",
    "sg:postcode":"1000",
    "sg:province":"Bruxelles-Capitale",
    "wof:name":"Stella Metro",
    "wof:placetype":"venue"
},
  "geometry": {"coordinates":[4.3534507751,50.8516616821],"type":"Point"}
}