{
  "type": "Feature",
  "properties": {
    "iso:country":"BE",
    "sg:address":"Rue T Serstevens 43",
    "sg:city":"Thuin",
    "sg:classifiers":[
        {
            "category":"Banks & Credit Unions",
            "subcategory":"Bank",
            "type":"Services"
        }
    ],
    "sg:phone":"+32 60 59 00 58",
    "sg:postcode":"6530",
    "sg:province":"Hainaut",
    "wof:name":"G\u00e9n\u00e9rale De Banque Sa",
    "wof:placetype":"venue"
},
  "geometry": {"coordinates":[4.2818818092,50.3416290283],"type":"Point"}
}