{
  "type": "Feature",
  "properties": {
    "iso:country":"BE",
    "sg:address":"Hasseltsestraat 38ba",
    "sg:city":"Bilzen",
    "sg:orig_category":"Fleurs and plantes",
    "sg:phone":"+32 89 49 22 73",
    "sg:postcode":"3740",
    "sg:province":"Limburg",
    "wof:name":"Dirk Streignart",
    "wof:placetype":"venue"
},
  "geometry": {"coordinates":[5.5025601387,50.8761291504],"type":"Point"}
}