{
  "type": "Feature",
  "properties": {
    "iso:country":"BE",
    "sg:address":"Brugsesteenweg 379",
    "sg:city":"Kuurne",
    "sg:classifiers":[
        {
            "category":"Travel",
            "subcategory":"Hotels & Motels",
            "type":"Entertainment"
        }
    ],
    "sg:phone":"+32 56 73 91 50",
    "sg:postcode":"8520",
    "sg:province":"West-Vlaanderen",
    "wof:name":"Dorian",
    "wof:placetype":"venue"
},
  "geometry": {"coordinates":[3.2709178925,50.8669662476],"type":"Point"}
}