{
  "type": "Feature",
  "properties": {
    "iso:country":"BE",
    "sg:address":"Mallekotstraat 65",
    "sg:city":"Lier",
    "sg:orig_category":"Gedistilleerde dranken and aperitieven Fab Wijnen Fab",
    "sg:phone":"+32 3 488 19 01",
    "sg:postcode":"2500",
    "sg:province":"Antwerpen",
    "wof:name":"Intervinum",
    "wof:placetype":"venue"
},
  "geometry": {"coordinates":[4.5605950356,51.1465148926],"type":"Point"}
}