{
  "type": "Feature",
  "properties": {
    "iso:country":"BE",
    "sg:address":"Koksijdestraat 24",
    "sg:city":"Veurne",
    "sg:orig_category":"Non-Classified Establishments",
    "sg:phone":"+32 58 31 41 69",
    "sg:postcode":"8630",
    "sg:province":"West-Vlaanderen",
    "wof:name":"Cailliau K",
    "wof:placetype":"venue"
},
  "geometry": {"coordinates":[2.642772913,51.0838661194],"type":"Point"}
}