{
  "type": "Feature",
  "properties": {
    "iso:country":"BE",
    "sg:address":"Molenberg 8",
    "sg:city":"Zwalm",
    "sg:classifiers":[
        {
            "category":"Restaurant",
            "type":"Food & Drink"
        }
    ],
    "sg:phone":"+32 55 49 83 26",
    "sg:postcode":"9630",
    "sg:province":"Oost-Vlaanderen",
    "wof:name":"Lars Vandewiele",
    "wof:placetype":"venue"
},
  "geometry": {"coordinates":[3.7004439831,50.8589057922],"type":"Point"}
}