{
  "type": "Feature",
  "properties": {
    "iso:country":"BE",
    "sg:address":"Vaartstraat 69",
    "sg:city":"Laarne (kalken)",
    "sg:classifiers":[
        {
            "category":"Fast Food",
            "type":"Food & Drink"
        }
    ],
    "sg:phone":"+32 9 366 53 87",
    "sg:postcode":"9270",
    "sg:province":"Oost-Vlaanderen",
    "sg:tags":[
        "fried",
        "stand",
        "potato"
    ],
    "wof:name":"De Vaart",
    "wof:placetype":"venue"
},
  "geometry": {"coordinates":[3.9114589691,51.0336837769],"type":"Point"}
}