{
  "type": "Feature",
  "properties": {
    "addr:full":"Hoogstr 38 Hamme Oost-Vlaanderen 9160",
    "addr:housenumber":"38",
    "addr:postcode":"9160",
    "addr:street":"Hoogstr",
    "iso:country":"BE",
    "sg:address":"Hoogstr 38",
    "sg:city":"Hamme",
    "sg:classifiers":[
        {
            "category":"Banks & Credit Unions",
            "subcategory":"Bank",
            "type":"Services"
        }
    ],
    "sg:phone":"+32 52 47 08 60",
    "sg:postcode":"9160",
    "sg:province":"Oost-Vlaanderen",
    "wof:name":"Krediet Nuverheid",
    "wof:placetype":"venue"
},
  "geometry": {"coordinates":[3.9864850044,51.1047401428],"type":"Point"}
}