{
  "type": "Feature",
  "properties": {
    "iso:country":"BE",
    "sg:address":"Grotestraat 28",
    "sg:city":"Genk",
    "sg:orig_category":"Pain, p\u00e2tisseries and confiseries",
    "sg:phone":"+32 89 35 33 54",
    "sg:postcode":"3600",
    "sg:province":"Limburg",
    "wof:name":"Kamiel Dictus",
    "wof:placetype":"venue"
},
  "geometry": {"coordinates":[5.4963870049,50.9636383057],"type":"Point"}
}