{
  "type": "Feature",
  "properties": {
    "iso:country":"BE",
    "sg:address":"L\u00c9on Vande Woesteynestr. 14",
    "sg:city":"Oudergem/auderghem",
    "sg:classifiers":[
        {
            "category":"Cafe",
            "type":"Food & Drink"
        }
    ],
    "sg:phone":"+32 2 660 82 64",
    "sg:postcode":"1160",
    "sg:province":"Bruxelles-Capitale",
    "sg:tags":[
        "caf\u00e9s"
    ],
    "wof:name":"Maenaut",
    "wof:placetype":"venue"
},
  "geometry": {"coordinates":[4.4381818771,50.8044242859],"type":"Point"}
}