{
  "type": "Feature",
  "properties": {
    "iso:country":"BE",
    "sg:address":"Rue De La Station 16",
    "sg:city":"Waterloo",
    "sg:classifiers":[
        {
            "category":"Organizations",
            "subcategory":"Community Association",
            "type":"Services"
        }
    ],
    "sg:phone":"+32 2 351 21 12",
    "sg:postcode":"1410",
    "sg:province":"Brabant Wallon",
    "sg:tags":[
        "organisation"
    ],
    "wof:name":"Re' Cr\u00c9ation",
    "wof:placetype":"venue"
},
  "geometry": {"coordinates":[4.395512104,50.7177848816],"type":"Point"}
}