{
  "type": "Feature",
  "properties": {
    "iso:country":"BE",
    "sg:address":"Turnhoutsebaan 5 B90",
    "sg:city":"Wijnegem",
    "sg:orig_category":"Boekhandels Microsoft",
    "sg:phone":"+32 3 354 16 13",
    "sg:postcode":"2110",
    "sg:province":"Antwerpen",
    "wof:name":"Standaard Boekhandel Wijnegem",
    "wof:placetype":"venue"
},
  "geometry": {"coordinates":[4.5248470306,51.2279434204],"type":"Point"}
}