{
  "type": "Feature",
  "properties": {
    "iso:country":"BE",
    "sg:address":"Chauss\u00c9e De Drogenbos",
    "sg:city":"Ukkel/uccle",
    "sg:orig_category":"Entreprises de travail adapt\u00e9",
    "sg:phone":"+32 2 332 44 44",
    "sg:postcode":"1180",
    "sg:province":"Bruxelles-Capitale",
    "wof:name":"A.p.a.m.",
    "wof:placetype":"venue"
},
  "geometry": {"coordinates":[4.3207101822,50.7858009338],"type":"Point"}
}