{
  "type": "Feature",
  "properties": {
    "iso:country":"BE",
    "sg:address":"Chauss\u00c9e De Wavre 1603",
    "sg:city":"Oudergem/auderghem",
    "sg:orig_category":"Tabac. Journaux. Librairies",
    "sg:phone":"+32 2 675 01 26",
    "sg:postcode":"1160",
    "sg:province":"Bruxelles-Capitale",
    "wof:name":"Librairie Oliver-kid",
    "wof:placetype":"venue"
},
  "geometry": {"coordinates":[4.4208579063,50.8173789978],"type":"Point"}
}