{
  "type": "Feature",
  "properties": {
    "iso:country":"BE",
    "sg:address":"Waterloosesteenweg 98-100",
    "sg:city":"Sint-gillis/saint-gilles",
    "sg:orig_category":"HERSTELLING ELEKTRISCHE HUISHOUDAPPARATEN Huishoudapparaten, televisies and radio's Telecommunicatie",
    "sg:phone":"+32 2 538 86 17",
    "sg:postcode":"1060",
    "sg:province":"Bruxelles-Capitale",
    "wof:name":"Kr\u00cbfel",
    "wof:placetype":"venue"
},
  "geometry": {"coordinates":[4.3446121216,50.829284668],"type":"Point"}
}