{
  "type": "Feature",
  "properties": {
    "iso:country":"BE",
    "sg:address":"Rue De Li\u00c8ge 15a",
    "sg:city":"Tinlot",
    "sg:orig_category":"Offices du tourisme",
    "sg:phone":"+32 85 51 27 88",
    "sg:postcode":"4557",
    "sg:province":"Li\u00e8ge",
    "wof:name":"Syndicat D'initiative",
    "wof:placetype":"venue"
},
  "geometry": {"coordinates":[5.4142179489,50.4783935547],"type":"Point"}
}