{
  "type": "Feature",
  "properties": {
    "iso:country":"BE",
    "sg:address":"Rue Du Village 2",
    "sg:city":"La Bruyere",
    "sg:orig_category":"Openbare bibliotheken and archieven",
    "sg:phone":"+32 81 56 60 63",
    "sg:postcode":"5081",
    "sg:province":"Namur",
    "wof:name":"Biblioth\u00c8que Publique",
    "wof:placetype":"venue"
},
  "geometry": {"coordinates":[4.8005628586,50.5518264771],"type":"Point"}
}