{
  "type": "Feature",
  "properties": {
    "addr:full":"Dorpsplein 1 Anzegem West-Vlaanderen 8570",
    "addr:housenumber":"1",
    "addr:postcode":"8570",
    "addr:street":"Dorpsplein",
    "iso:country":"BE",
    "sg:address":"Dorpsplein 1",
    "sg:city":"Anzegem",
    "sg:classifiers":[
        {
            "category":"Shopping",
            "subcategory":"Clothing, Apparel, & Fashions",
            "type":"Retail Goods"
        }
    ],
    "sg:phone":"+32 56 68 88 70",
    "sg:postcode":"8570",
    "sg:province":"West-Vlaanderen",
    "sg:tags":[
        "boutique"
    ],
    "wof:name":"Anzie",
    "wof:placetype":"venue"
},
  "geometry": {"coordinates":[3.4787399769,50.8327102661],"type":"Point"}
}