{
  "type": "Feature",
  "properties": {
    "iso:country":"BE",
    "sg:address":"Vlamingstraat 26",
    "sg:city":"Brugge",
    "sg:orig_category":"Eclairage et \u00e9quipements du foyer",
    "sg:phone":"+32 50 33 30 10",
    "sg:postcode":"8000",
    "sg:province":"West-Vlaanderen",
    "wof:name":"Kunsthandel Reynaert",
    "wof:placetype":"venue"
},
  "geometry": {"coordinates":[3.2211899757,51.2160339355],"type":"Point"}
}