{
  "type": "Feature",
  "properties": {
    "addr:full":"Kiliaanstraat 5 Antwerpen Antwerpen 2000",
    "addr:housenumber":"5",
    "addr:postcode":"2000",
    "addr:street":"Kiliaanstraat",
    "iso:country":"BE",
    "sg:address":"Kiliaanstraat 5",
    "sg:city":"Antwerpen",
    "sg:classifiers":[
        {
            "category":"Health Services",
            "subcategory":"Health Practitioner",
            "type":"Services"
        }
    ],
    "sg:phone":"+32 3 232 92 60",
    "sg:postcode":"2000",
    "sg:province":"Antwerpen",
    "sg:tags":[
        "physiotherapist"
    ],
    "wof:name":"Van Hoof E",
    "wof:placetype":"venue"
},
  "geometry": {"coordinates":[4.4067230225,51.2113952637],"type":"Point"}
}