{
  "type": "Feature",
  "properties": {
    "iso:country":"BE",
    "sg:address":"Lippenslaan 149",
    "sg:city":"Knokke-heist",
    "sg:orig_category":"Production and distribution de gaz and combustibles. Production and distribution d'\u00e9lectricit\u00e9. Comp",
    "sg:phone":"+32 78 35 35 35",
    "sg:postcode":"8300",
    "sg:province":"West-Vlaanderen",
    "wof:name":"Electrabel-imewo-tevewest",
    "wof:placetype":"venue"
},
  "geometry": {"coordinates":[3.2880721092,51.3459968567],"type":"Point"}
}