{
  "type": "Feature",
  "properties": {
    "iso:country":"BE",
    "sg:address":"Mechelse Plein 10",
    "sg:city":"Antwerpen",
    "sg:orig_category":"Pain, p\u00e2tisseries and confiseries",
    "sg:phone":"+32 3 232 64 40",
    "sg:postcode":"2000",
    "sg:province":"Antwerpen",
    "wof:name":"Frans Teysen",
    "wof:placetype":"venue"
},
  "geometry": {"coordinates":[4.4046440125,51.2131309509],"type":"Point"}
}