{
  "type": "Feature",
  "properties": {
    "addr:full":"Chauss\u00e9e De Maubeuge 265 Mons (hyon) Hainaut 7022",
    "addr:housenumber":"265",
    "addr:postcode":"7022",
    "addr:street":"Chausse\u0301E De Maubeuge",
    "iso:country":"BE",
    "sg:address":"Chauss\u00e9e De Maubeuge 265",
    "sg:city":"Mons (hyon)",
    "sg:classifiers":[
        {
            "category":"Building & Trades",
            "subcategory":"Plumbing",
            "type":"Services"
        }
    ],
    "sg:phone":"+32 65 33 92 99",
    "sg:postcode":"7022",
    "sg:province":"Hainaut",
    "sg:tags":[
        "repair",
        "mainten",
        "-",
        "central",
        "heating"
    ],
    "wof:name":"Froid Et Chaleur",
    "wof:placetype":"venue"
},
  "geometry": {"coordinates":[3.9476840496,50.4293670654],"type":"Point"}
}