{
  "type": "Feature",
  "properties": {
    "addr:full":"Groenstraat 108 Heverlee Vlaams-Brabant 3001",
    "addr:housenumber":"108",
    "addr:postcode":"3001",
    "addr:street":"Groenstraat",
    "iso:country":"BE",
    "sg:address":"Groenstraat 108",
    "sg:city":"Heverlee",
    "sg:classifiers":[
        {
            "category":"Wholesale",
            "subcategory":"Sporting Goods",
            "type":"Manufacturing & Wholesale Goods"
        }
    ],
    "sg:phone":"+32 16 40 50 10",
    "sg:postcode":"3001",
    "sg:province":"Vlaams-Brabant",
    "sg:tags":[
        "sport-",
        "kampeermateriaal"
    ],
    "wof:name":"Compartners Techniek",
    "wof:placetype":"venue"
},
  "geometry": {"coordinates":[4.6843857765,50.8709640503],"type":"Point"}
}