{
  "type": "Feature",
  "properties": {
    "addr:full":"Rue Des Trois Piliers 116 Namur Namur 5002",
    "addr:housenumber":"116",
    "addr:postcode":"5002",
    "addr:street":"Rue Des Trois Piliers",
    "iso:country":"BE",
    "sg:address":"Rue Des Trois Piliers 116",
    "sg:city":"Namur",
    "sg:orig_category":"Installation de menuiserie en bois and plastique. Fabrication and montage de mobilier. Meubles D\u00e9tai",
    "sg:phone":"+32 81 73 37 44",
    "sg:postcode":"5002",
    "sg:province":"Namur",
    "wof:name":"Hanse Meubles",
    "wof:placetype":"venue"
},
  "geometry": {"coordinates":[4.8462319374,50.4782791138],"type":"Point"}
}