{
  "type": "Feature",
  "properties": {
    "iso:country":"BE",
    "sg:address":"Katelijnestraat 150",
    "sg:city":"Brugge",
    "sg:classifiers":[
        {
            "category":"Real Estate",
            "subcategory":"Real Estate Services",
            "type":"Services"
        }
    ],
    "sg:phone":"+32 50 34 38 48",
    "sg:postcode":"8000",
    "sg:province":"West-Vlaanderen",
    "wof:name":"De Neve & Partners Nv",
    "wof:placetype":"venue"
},
  "geometry": {"coordinates":[3.2288138866,51.2000236511],"type":"Point"}
}