{
  "type": "Feature",
  "properties": {
    "iso:country":"BE",
    "sg:address":"Trapstraat 2a",
    "sg:city":"Geraardsbergen",
    "sg:orig_category":"Procesbesturingssystemen Fab",
    "sg:phone":"+32 54 58 89 81",
    "sg:postcode":"9500",
    "sg:province":"Oost-Vlaanderen",
    "wof:name":"Vp Systems",
    "wof:placetype":"venue"
},
  "geometry": {"coordinates":[3.9128708839,50.7333221436],"type":"Point"}
}