{
  "type": "Feature",
  "properties": {
    "iso:country":"BE",
    "sg:address":"Rue Heyvaert 213",
    "sg:city":"Anderlecht/anderlecht",
    "sg:orig_category":"Boucheries",
    "sg:phone":"+32 2 523 38 23",
    "sg:postcode":"1070",
    "sg:province":"Bruxelles-Capitale",
    "wof:name":"Beenhouwerij Abattoirs",
    "wof:placetype":"venue"
},
  "geometry": {"coordinates":[4.3280701637,50.843711853],"type":"Point"}
}