{
  "type": "Feature",
  "properties": {
    "addr:full":"Ottergemsesteenweg 433 Gent Oost-Vlaanderen 9000",
    "addr:housenumber":"433",
    "addr:postcode":"9000",
    "addr:street":"Ottergemsesteenweg;Oost-Vlaanderen",
    "iso:country":"BE",
    "sg:address":"Ottergemsesteenweg 433",
    "sg:city":"Gent",
    "sg:orig_category":"Agents artistiques",
    "sg:phone":"+32 9 222 34 10",
    "sg:postcode":"9000",
    "sg:province":"Oost-Vlaanderen",
    "wof:name":"Star Entertainment",
    "wof:placetype":"venue"
},
  "geometry": {"coordinates":[3.7334449291,51.0267906189],"type":"Point"}
}