{
  "type": "Feature",
  "properties": {
    "iso:country":"BE",
    "sg:address":"Rue De Ros\u00c9e 8",
    "sg:city":"Florennes",
    "sg:orig_category":"Eleveurs de bovins",
    "sg:phone":"+32 82 68 85 27",
    "sg:postcode":"5620",
    "sg:province":"Namur",
    "wof:name":"Albert Masschelein",
    "wof:placetype":"venue"
},
  "geometry": {"coordinates":[4.6772079468,50.250995636],"type":"Point"}
}