{
  "type": "Feature",
  "properties": {
    "iso:country":"BE",
    "sg:address":"Sint-amandusstraat 55",
    "sg:city":"Oudenaarde",
    "sg:orig_category":"Gespecialiseerde residenti\u00eble bouw Woningbouw",
    "sg:phone":"+32 55 31 71 03",
    "sg:postcode":"9700",
    "sg:province":"Oost-Vlaanderen",
    "wof:name":"Bouwonderneming Bracke",
    "wof:placetype":"venue"
},
  "geometry": {"coordinates":[3.6365470886,50.8882713318],"type":"Point"}
}