{
  "type": "Feature",
  "properties": {
    "addr:full":"Tulpenstraat 84 Houthalen-helchteren Limburg 3530",
    "addr:housenumber":"84",
    "addr:postcode":"3530",
    "addr:street":"Tulpenstraat",
    "iso:country":"BE",
    "sg:address":"Tulpenstraat 84",
    "sg:city":"Houthalen-helchteren",
    "sg:orig_category":"D\u00e9molition d\u00b4immeubles and terrassements. Ramassage and traitement des d\u00e9chets m\u00e9nagers",
    "sg:phone":"+32 89 38 20 23",
    "sg:postcode":"3530",
    "sg:province":"Limburg",
    "wof:name":"Geerkens-meus & Zoon",
    "wof:placetype":"venue"
},
  "geometry": {"coordinates":[5.4718852043,51.0184555054],"type":"Point"}
}