{
  "type": "Feature",
  "properties": {
    "iso:country":"BE",
    "sg:address":"Sint-denijsplein 1",
    "sg:city":"Vorst/forest",
    "sg:orig_category":"Brood, gebak and snoepgoed",
    "sg:phone":"+32 2 376 42 84",
    "sg:postcode":"1190",
    "sg:province":"Bruxelles-Capitale",
    "wof:name":"P\u00c2tisserie Quinaux",
    "wof:placetype":"venue"
},
  "geometry": {"coordinates":[4.3175368309,50.8101615906],"type":"Point"}
}