{
  "type": "Feature",
  "properties": {
    "addr:full":"Zuiddammestraat 5 Beernem West-Vlaanderen 8730",
    "addr:housenumber":"5",
    "addr:postcode":"8730",
    "addr:street":"Zuiddammestraat",
    "iso:country":"BE",
    "sg:address":"Zuiddammestraat 5",
    "sg:city":"Beernem",
    "sg:orig_category":"Rev\u00eatements pour sols and murs. Peinture",
    "sg:phone":"+32 50 79 11 73",
    "sg:postcode":"8730",
    "sg:province":"West-Vlaanderen",
    "wof:name":"Thierry Tierenteyn",
    "wof:placetype":"venue"
},
  "geometry": {"coordinates":[3.3487489223,51.1543464661],"type":"Point"}
}