{
  "type": "Feature",
  "properties": {
    "addr:full":"Egemstraat 105 Pittem West-Vlaanderen 8740",
    "addr:housenumber":"105",
    "addr:postcode":"8740",
    "addr:street":"Egemstraat",
    "iso:country":"BE",
    "sg:address":"Egemstraat 105",
    "sg:city":"Pittem",
    "sg:orig_category":"Varkenskwekers",
    "sg:phone":"+32 51 46 63 53",
    "sg:postcode":"8740",
    "sg:province":"West-Vlaanderen",
    "wof:name":"Gabriel Soenens",
    "wof:placetype":"venue"
},
  "geometry": {"coordinates":[3.2580649853,51.0105705261],"type":"Point"}
}