{
  "type": "Feature",
  "properties": {
    "addr:full":"Stationsstraat 26 Deinze Oost-Vlaanderen 9800",
    "addr:housenumber":"26",
    "addr:postcode":"9800",
    "addr:street":"Stationsstraat",
    "iso:country":"BE",
    "sg:address":"Stationsstraat 26",
    "sg:city":"Deinze",
    "sg:orig_category":"Advocaten and juridische adviseurs Balie van Gent",
    "sg:phone":"+32 9 380 34 39",
    "sg:postcode":"9800",
    "sg:province":"Oost-Vlaanderen",
    "wof:name":"Vermeulen Jan",
    "wof:placetype":"venue"
},
  "geometry": {"coordinates":[3.5323190689,50.9784431458],"type":"Point"}
}