{
  "type": "Feature",
  "properties": {
    "addr:full":"Chauss\u00c9e D'alsemberg Sint-gillis/saint-gilles Bruxelles-Capitale 1060",
    "addr:postcode":"1060",
    "addr:street":"Chausse\u0301E D'Alsemberg",
    "iso:country":"BE",
    "sg:address":"Chauss\u00c9e D'alsemberg",
    "sg:city":"Sint-gillis/saint-gilles",
    "sg:orig_category":"Production de films, t\u00e9l\u00e9films and vid\u00e9os",
    "sg:phone":"+32 2 534 48 69",
    "sg:postcode":"1060",
    "sg:province":"Bruxelles-Capitale",
    "wof:name":"Bureau New Ems",
    "wof:placetype":"venue"
},
  "geometry": {"coordinates":[4.3436179161,50.8256263733],"type":"Point"}
}