{
  "type": "Feature",
  "properties": {
    "iso:country":"BE",
    "sg:address":"Koningin Astridlaan 25",
    "sg:city":"Kontich",
    "sg:orig_category":"Slagers",
    "sg:phone":"+32 3 457 33 45",
    "sg:postcode":"2550",
    "sg:province":"Antwerpen",
    "wof:name":"Alex Smeets",
    "wof:placetype":"venue"
},
  "geometry": {"coordinates":[4.4527978897,51.1270713806],"type":"Point"}
}