{
  "type": "Feature",
  "properties": {
    "addr:full":"Vlierkouter 107 Hamme Oost-Vlaanderen 9220",
    "addr:housenumber":"107",
    "addr:postcode":"9220",
    "iso:country":"BE",
    "sg:address":"Vlierkouter 107",
    "sg:city":"Hamme",
    "sg:orig_category":"Sportclubs Sportterreinen and installaties behalve sportcentra",
    "sg:phone":"+32 52 47 27 59",
    "sg:postcode":"9220",
    "sg:province":"Oost-Vlaanderen",
    "wof:name":"Verenigde Krachten Hamme",
    "wof:placetype":"venue"
},
  "geometry": {"coordinates":[4.1259670258,51.0871276855],"type":"Point"}
}