{
  "type": "Feature",
  "properties": {
    "addr:full":"Vondelpark 165 Tremelo Vlaams-Brabant 3120",
    "addr:housenumber":"165",
    "addr:postcode":"3120",
    "addr:street":"Vondelpark",
    "iso:country":"BE",
    "sg:address":"Vondelpark 165",
    "sg:city":"Tremelo",
    "sg:classifiers":[
        {
            "category":"Autos & Motor Vehicles",
            "subcategory":"Recreational Vehicle Sales",
            "type":"Retail Goods"
        }
    ],
    "sg:phone":"+32 498 53 46 01",
    "sg:postcode":"3120",
    "sg:province":"Vlaams-Brabant",
    "sg:tags":[
        "caravan",
        "accessory"
    ],
    "wof:name":"Benny",
    "wof:placetype":"venue"
},
  "geometry": {"coordinates":[4.7154350281,51.0104675293],"type":"Point"}
}