{
  "type": "Feature",
  "properties": {
    "iso:country":"BE",
    "sg:address":"Rue Ledocte 8",
    "sg:city":"Chastre (chastre-villeroux-blanmont)",
    "sg:classifiers":[
        {
            "category":"Health Services",
            "subcategory":"Dentist",
            "type":"Services"
        }
    ],
    "sg:phone":"+32 10 65 77 04",
    "sg:postcode":"1450",
    "sg:province":"Brabant Wallon",
    "wof:name":"Maes Eliane",
    "wof:placetype":"venue"
},
  "geometry": {"coordinates":[4.6497168541,50.6082496643],"type":"Point"}
}