{
  "type": "Feature",
  "properties": {
    "iso:country":"BE",
    "sg:address":"Albertlaan 26",
    "sg:city":"Vorst/forest",
    "sg:orig_category":"Landmeters and schatters",
    "sg:phone":"+32 2 346 33 08",
    "sg:postcode":"1190",
    "sg:province":"Bruxelles-Capitale",
    "wof:name":"Van Ongevalle Patrick",
    "wof:placetype":"venue"
},
  "geometry": {"coordinates":[4.3440041542,50.8213005066],"type":"Point"}
}