{
  "type": "Feature",
  "properties": {
    "iso:country":"BE",
    "sg:address":"Rue De La Gare 8-1",
    "sg:city":"Fexhe-le-haut-clocher",
    "sg:classifiers":[
        {
            "category":"Health Services",
            "subcategory":"Nursing And Care Facility",
            "type":"Services"
        }
    ],
    "sg:phone":"+32 4 250 47 89",
    "sg:postcode":"4347",
    "sg:province":"Li\u00e8ge",
    "sg:tags":[
        "home",
        "rest"
    ],
    "wof:name":"R\u00e9sidence Edelweiss",
    "wof:placetype":"venue"
},
  "geometry": {"coordinates":[5.4296889305,50.6555671692],"type":"Point"}
}