{
  "type": "Feature",
  "properties": {
    "addr:full":"Abeelplein 4 Borgloon Limburg 3840",
    "addr:housenumber":"4",
    "addr:postcode":"3840",
    "addr:street":"Abeelplein",
    "iso:country":"BE",
    "sg:address":"Abeelplein 4",
    "sg:city":"Borgloon",
    "sg:classifiers":[
        {
            "category":"Real Estate",
            "subcategory":"Architect",
            "type":"Services"
        }
    ],
    "sg:phone":"+32 12 74 19 76",
    "sg:postcode":"3840",
    "sg:province":"Limburg",
    "wof:name":"Vandeplas L",
    "wof:placetype":"venue"
},
  "geometry": {"coordinates":[5.3431549072,50.802646637],"type":"Point"}
}