{
  "type": "Feature",
  "properties": {
    "addr:full":"Rue Des Emmanuel 15 Brunehaut (wez-velvain) Hainaut 7620",
    "addr:housenumber":"15",
    "addr:postcode":"7620",
    "addr:street":"Rue Des Emmanuel;Wez-Velvain Hainaut",
    "iso:country":"BE",
    "sg:address":"Rue Des Emmanuel 15",
    "sg:city":"Brunehaut (wez-velvain)",
    "sg:classifiers":[
        {
            "category":"Food & Beverages",
            "subcategory":"Groceries & Convenience Stores",
            "type":"Retail Goods"
        }
    ],
    "sg:phone":"+32 69 34 47 74",
    "sg:postcode":"7620",
    "sg:province":"Hainaut",
    "sg:tags":[
        "grocer"
    ],
    "wof:name":"Au Superfrais",
    "wof:placetype":"venue"
},
  "geometry": {"coordinates":[3.4210350513,50.5150413513],"type":"Point"}
}