{
  "type": "Feature",
  "properties": {
    "iso:country":"BE",
    "sg:address":"Rue Joseph Muller 11b",
    "sg:city":"Dalhem (warsage)",
    "sg:classifiers":[
        {
            "category":"Retail",
            "subcategory":"Event Space",
            "type":"Services"
        }
    ],
    "sg:phone":"+32 4 376 72 81",
    "sg:postcode":"4608",
    "sg:province":"Li\u00e8ge",
    "sg:tags":[
        "rental",
        "-",
        "hall"
    ],
    "wof:name":"Amon Nos Otes",
    "wof:placetype":"venue"
},
  "geometry": {"coordinates":[5.7665410042,50.7354812622],"type":"Point"}
}