{
  "type": "Feature",
  "properties": {
    "iso:country":"BE",
    "sg:address":"Veldeken 27",
    "sg:city":"Waarschoot",
    "sg:orig_category":"Boomkwekerijen Tuinen",
    "sg:phone":"+32 9 372 82 52",
    "sg:postcode":"9950",
    "sg:province":"Oost-Vlaanderen",
    "wof:name":"Rudy Geniets",
    "wof:placetype":"venue"
},
  "geometry": {"coordinates":[3.6124250889,51.1267776489],"type":"Point"}
}