{
  "type": "Feature",
  "properties": {
    "addr:full":"Rue De Nivelles 39 Ecaussinnes (marche-lez-ecaussines) Hainaut 7190",
    "addr:housenumber":"39",
    "addr:postcode":"7190",
    "addr:street":"Rue De Nivelles;Marche-Lez-Ecaussines Hainaut",
    "iso:country":"BE",
    "sg:address":"Rue De Nivelles 39",
    "sg:city":"Ecaussinnes (marche-lez-ecaussines)",
    "sg:classifiers":[
        {
            "category":"Professional",
            "subcategory":"Engineering",
            "type":"Services"
        }
    ],
    "sg:phone":"+32 67 44 49 01",
    "sg:postcode":"7190",
    "sg:province":"Hainaut",
    "sg:tags":[
        "civil",
        "offices-"
    ],
    "wof:name":"Tahon J",
    "wof:placetype":"venue"
},
  "geometry": {"coordinates":[4.1844501495,50.547870636],"type":"Point"}
}