{
  "type": "Feature",
  "properties": {
    "addr:full":"Vinkestraat 121 Wevelgem West-Vlaanderen 8560",
    "addr:housenumber":"121",
    "addr:postcode":"8560",
    "addr:street":"Vinkestraat",
    "iso:country":"BE",
    "sg:address":"Vinkestraat 121",
    "sg:city":"Wevelgem",
    "sg:classifiers":[
        {
            "category":"Real Estate",
            "subcategory":"Architect",
            "type":"Services"
        }
    ],
    "sg:phone":"+32 56 41 07 68",
    "sg:postcode":"8560",
    "sg:province":"West-Vlaanderen",
    "wof:name":"Corne E",
    "wof:placetype":"venue"
},
  "geometry": {"coordinates":[3.1775560379,50.8230285645],"type":"Point"}
}