{
  "type": "Feature",
  "properties": {
    "iso:country":"BE",
    "sg:address":"Gallaitstraat 149",
    "sg:city":"Schaarbeek/schaerbeek",
    "sg:classifiers":[
        {
            "category":"Food & Beverages",
            "subcategory":"Meat & Fish",
            "type":"Retail Goods"
        }
    ],
    "sg:phone":"+32 2 241 35 32",
    "sg:postcode":"1030",
    "sg:province":"Bruxelles-Capitale",
    "sg:tags":[
        "vi",
        "zeevruchten"
    ],
    "wof:name":"Mohamed Bouassab",
    "wof:placetype":"venue"
},
  "geometry": {"coordinates":[4.3714227676,50.8693885803],"type":"Point"}
}