{
  "type": "Feature",
  "properties": {
    "addr:full":"Groenstraat 2 Rotselaar Vlaams-Brabant 3110",
    "addr:housenumber":"2",
    "addr:postcode":"3110",
    "addr:street":"Groenstraat",
    "iso:country":"BE",
    "sg:address":"Groenstraat 2",
    "sg:city":"Rotselaar",
    "sg:classifiers":[
        {
            "category":"Building & Trades",
            "subcategory":"Construction",
            "type":"Services"
        }
    ],
    "sg:phone":"+32 16 44 56 88",
    "sg:postcode":"3110",
    "sg:province":"Vlaams-Brabant",
    "sg:tags":[
        "carpenter"
    ],
    "wof:name":"Geeraerts Gebroeders",
    "wof:placetype":"venue"
},
  "geometry": {"coordinates":[4.7096271515,50.9519119263],"type":"Point"}
}