{
  "type": "Feature",
  "properties": {
    "iso:country":"BE",
    "sg:address":"Kapelstraat 45",
    "sg:city":"Zwijndrecht",
    "sg:orig_category":"Peinture. Rev\u00eatements pour sols and murs",
    "sg:phone":"+32 3 252 58 12",
    "sg:postcode":"2070",
    "sg:province":"Antwerpen",
    "wof:name":"Ludo Lauwers",
    "wof:placetype":"venue"
},
  "geometry": {"coordinates":[4.3400969505,51.2007827759],"type":"Point"}
}