{
  "type": "Feature",
  "properties": {
    "addr:full":"Wondelgemstraat 111 Gent Oost-Vlaanderen 9000",
    "addr:housenumber":"111",
    "addr:postcode":"9000",
    "addr:street":"Wondelgemstraat;Oost-Vlaanderen",
    "iso:country":"BE",
    "sg:address":"Wondelgemstraat 111",
    "sg:city":"Gent",
    "sg:classifiers":[
        {
            "category":"Banks & Credit Unions",
            "subcategory":"Financial Services",
            "type":"Services"
        }
    ],
    "sg:phone":"+32 9 269 09 99",
    "sg:postcode":"9000",
    "sg:province":"Oost-Vlaanderen",
    "sg:tags":[
        "loan",
        "mortgage"
    ],
    "wof:name":"Bagseven Finans",
    "wof:placetype":"venue"
},
  "geometry": {"coordinates":[3.7098259926,51.0631065369],"type":"Point"}
}