{
  "type": "Feature",
  "properties": {
    "iso:country":"BE",
    "sg:address":"Rue L\u00c9on Duray 15",
    "sg:city":"La Louviere",
    "sg:orig_category":"Brood, gebak and snoepgoed",
    "sg:phone":"+32 64 22 75 48",
    "sg:postcode":"7110",
    "sg:province":"Hainaut",
    "wof:name":"Au Croissant",
    "wof:placetype":"venue"
},
  "geometry": {"coordinates":[4.1562228203,50.486328125],"type":"Point"}
}