{
  "type": "Feature",
  "properties": {
    "iso:country":"BE",
    "sg:address":"Minimenstraat 27",
    "sg:city":"Brussel/bruxelles",
    "sg:orig_category":"Diverse zakelijke dienstverlening",
    "sg:phone":"+32 2 511 75 07",
    "sg:postcode":"1000",
    "sg:province":"Bruxelles-Capitale",
    "wof:name":"Maison Koenig",
    "wof:placetype":"venue"
},
  "geometry": {"coordinates":[4.3532180786,50.8404159546],"type":"Point"}
}