{
  "type": "Feature",
  "properties": {
    "addr:full":"Rue De Frameries 37 Qu\u00e9vy (qu\u00e9vy-le-petit) Hainaut 7040",
    "addr:housenumber":"37",
    "addr:postcode":"7040",
    "addr:street":"Rue De Frameries",
    "iso:country":"BE",
    "sg:address":"Rue De Frameries 37",
    "sg:city":"Qu\u00e9vy (qu\u00e9vy-le-petit)",
    "sg:classifiers":[
        {
            "category":"Health Services",
            "subcategory":"Nursing And Care Facility",
            "type":"Services"
        }
    ],
    "sg:phone":"+32 65 56 03 03",
    "sg:postcode":"7040",
    "sg:province":"Hainaut",
    "sg:tags":[
        "home",
        "rest"
    ],
    "wof:name":"R\u00e9sidence Du P'tit Quevy",
    "wof:placetype":"venue"
},
  "geometry": {"coordinates":[3.9332530499,50.3685684204],"type":"Point"}
}