{
  "type": "Feature",
  "properties": {
    "iso:country":"BE",
    "sg:address":"Avenue De Tervueren 402",
    "sg:city":"Bruxelles (woluwe-saint-pierre)",
    "sg:classifiers":[
        {
            "category":"Professional",
            "subcategory":"Management & Consulting",
            "type":"Services"
        }
    ],
    "sg:phone":"+32 2 761 66 11",
    "sg:postcode":"1150",
    "sg:province":"Bruxelles-Capitale",
    "sg:tags":[
        "consultant",
        "relation",
        "public"
    ],
    "wof:name":"Interel Mari\u00ebn Sa",
    "wof:placetype":"venue"
},
  "geometry": {"coordinates":[4.4438309669,50.8279647827],"type":"Point"}
}