{
  "type": "Feature",
  "properties": {
    "addr:full":"Leuvenstraat 52 Sint-katelijne-waver Antwerpen 2860",
    "addr:housenumber":"52",
    "addr:postcode":"2860",
    "addr:street":"Leuvenstraat",
    "iso:country":"BE",
    "sg:address":"Leuvenstraat 52",
    "sg:city":"Sint-katelijne-waver",
    "sg:orig_category":"Auto-\u00e9coles",
    "sg:phone":"+32 16 31 71 45",
    "sg:postcode":"2860",
    "sg:province":"Antwerpen",
    "wof:name":"Rijschool Vrg",
    "wof:placetype":"venue"
},
  "geometry": {"coordinates":[4.5338730812,51.0684928894],"type":"Point"}
}