{
  "type": "Feature",
  "properties": {
    "addr:full":"Molendreef 4 Willebroek Antwerpen 2830",
    "addr:housenumber":"4",
    "addr:postcode":"2830",
    "addr:street":"Molendreef",
    "iso:country":"BE",
    "sg:address":"Molendreef 4",
    "sg:city":"Willebroek",
    "sg:orig_category":"Centres de relaxation and bien-\u00eatre",
    "sg:phone":"+32 3 886 27 82",
    "sg:postcode":"2830",
    "sg:province":"Antwerpen",
    "wof:name":"Mia Deferme",
    "wof:placetype":"venue"
},
  "geometry": {"coordinates":[4.386423111,51.0512466431],"type":"Point"}
}