{
  "type": "Feature",
  "properties": {
    "iso:country":"BE",
    "sg:address":"Statielei 67",
    "sg:city":"Mortsel",
    "sg:classifiers":[
        {
            "category":"Building & Trades",
            "subcategory":"Locksmith",
            "type":"Services"
        }
    ],
    "sg:phone":"+32 3 324 45 76",
    "sg:postcode":"2640",
    "sg:province":"Antwerpen",
    "sg:tags":[
        "roofing",
        "industrial"
    ],
    "wof:name":"Platteau B.v.b.a.",
    "wof:placetype":"venue"
},
  "geometry": {"coordinates":[4.4663882256,51.2244644165],"type":"Point"}
}