{
  "type": "Feature",
  "properties": {
    "addr:full":"Robsonplein 8 Turnhout Antwerpen 2300",
    "addr:housenumber":"8",
    "addr:postcode":"2300",
    "addr:street":"Robsonplein",
    "iso:country":"BE",
    "sg:address":"Robsonplein 8",
    "sg:city":"Turnhout",
    "sg:classifiers":[
        {
            "category":"Fast Food",
            "type":"Food & Drink"
        }
    ],
    "sg:phone":"+32 14 41 44 10",
    "sg:postcode":"2300",
    "sg:province":"Antwerpen",
    "sg:tags":[
        "fried",
        "stand",
        "potato"
    ],
    "wof:name":"Stardust",
    "wof:placetype":"venue"
},
  "geometry": {"coordinates":[4.9287290573,51.3230743408],"type":"Point"}
}