{
  "type": "Feature",
  "properties": {
    "addr:full":"Biestebroekkaai 110 Anderlecht/anderlecht Bruxelles-Capitale 1070",
    "addr:housenumber":"110",
    "addr:postcode":"1070",
    "addr:street":"Biestebroekkaai",
    "iso:country":"BE",
    "sg:address":"Biestebroekkaai 110",
    "sg:city":"Anderlecht/anderlecht",
    "sg:orig_category":"Herstellingen and onderhoud van auto's",
    "sg:phone":"+32 2 521 79 05",
    "sg:postcode":"1070",
    "sg:province":"Bruxelles-Capitale",
    "wof:name":"Garage Monaco",
    "wof:placetype":"venue"
},
  "geometry": {"coordinates":[4.3141131401,50.8326187134],"type":"Point"}
}