{
  "type": "Feature",
  "properties": {
    "addr:full":"Zandvoordestraat 509 Oostende West-Vlaanderen 8400",
    "addr:housenumber":"509",
    "addr:postcode":"8400",
    "addr:street":"Zandvoordestraat",
    "iso:country":"BE",
    "sg:address":"Zandvoordestraat 509",
    "sg:city":"Oostende",
    "sg:orig_category":"Winkelinrichting and handelsuitrusting Gh",
    "sg:phone":"+32 59 70 17 87",
    "sg:postcode":"8400",
    "sg:province":"West-Vlaanderen",
    "wof:name":"Gruka-saeco",
    "wof:placetype":"venue"
},
  "geometry": {"coordinates":[2.9752159119,51.2070503235],"type":"Point"}
}