{
  "type": "Feature",
  "properties": {
    "iso:country":"BE",
    "sg:address":"Noorderlaan 81",
    "sg:city":"Antwerpen",
    "sg:orig_category":"Elektrische installaties voor woningen Industri\u00eble elektrische installaties Motoren, transformatoren",
    "sg:phone":"+32 3 541 71 40",
    "sg:postcode":"2030",
    "sg:province":"Antwerpen",
    "wof:name":"Asea Brown Boveri",
    "wof:placetype":"venue"
},
  "geometry": {"coordinates":[4.4198851585,51.2550621033],"type":"Point"}
}