{
  "type": "Feature",
  "properties": {
    "iso:country":"BE",
    "sg:address":"Rue Du Vent Val 39ba",
    "sg:city":"Le Roeulx",
    "sg:orig_category":"Eleveurs de bovins. P\u00e9pini\u00e9ristes. Fleurs and plantes",
    "sg:phone":"+32 64 66 20 56",
    "sg:postcode":"7070",
    "sg:province":"Hainaut",
    "wof:name":"Demarbaix",
    "wof:placetype":"venue"
},
  "geometry": {"coordinates":[4.0662231445,50.5035247803],"type":"Point"}
}