{
  "type": "Feature",
  "properties": {
    "iso:country":"BE",
    "sg:address":"Chauss\u00c9e De Bruxelles 299",
    "sg:city":"Waterloo",
    "sg:orig_category":"Foto-uitrusting",
    "sg:phone":"+32 2 353 08 81",
    "sg:postcode":"1410",
    "sg:province":"Brabant Wallon",
    "wof:name":"Minit Colors",
    "wof:placetype":"venue"
},
  "geometry": {"coordinates":[4.401321888,50.7098083496],"type":"Point"}
}