{
  "type": "Feature",
  "properties": {
    "addr:full":"Sint-jansplein 44 Antwerpen Antwerpen 2060",
    "addr:housenumber":"44",
    "addr:postcode":"2060",
    "addr:street":"Sint-Jansplein",
    "iso:country":"BE",
    "sg:address":"Sint-jansplein 44",
    "sg:city":"Antwerpen",
    "sg:classifiers":[
        {
            "category":"Bars & Pubs",
            "type":"Food & Drink"
        }
    ],
    "sg:phone":"+32 3 232 45 42",
    "sg:postcode":"2060",
    "sg:province":"Antwerpen",
    "wof:name":"Monda",
    "wof:placetype":"venue"
},
  "geometry": {"coordinates":[4.4172701836,51.2245788574],"type":"Point"}
}