{
  "type": "Feature",
  "properties": {
    "addr:full":"Lange Beeldekensstraat 118 Antwerpen Antwerpen 2060",
    "addr:housenumber":"118",
    "addr:postcode":"2060",
    "addr:street":"Lange Beeldekensstraat",
    "iso:country":"BE",
    "sg:address":"Lange Beeldekensstraat 118",
    "sg:city":"Antwerpen",
    "sg:classifiers":[
        {
            "category":"Personal",
            "subcategory":"Beauty Salon",
            "type":"Services"
        }
    ],
    "sg:phone":"+32 3 225 01 10",
    "sg:postcode":"2060",
    "sg:province":"Antwerpen",
    "sg:tags":[
        "de",
        "coiffure"
    ],
    "wof:name":"Coiffure Georgette",
    "wof:placetype":"venue"
},
  "geometry": {"coordinates":[4.4266238213,51.2214584351],"type":"Point"}
}