{
  "type": "Feature",
  "properties": {
    "addr:full":"Korenbloemlaan 2-4 Liedekerke Vlaams-Brabant 1770",
    "addr:housenumber":"2-4",
    "addr:postcode":"1770",
    "addr:street":"Korenbloemlaan;Vlaams-Brabant",
    "iso:country":"BE",
    "sg:address":"Korenbloemlaan 2-4",
    "sg:city":"Liedekerke",
    "sg:classifiers":[
        {
            "category":"Professional",
            "subcategory":"Art Services",
            "type":"Services"
        }
    ],
    "sg:phone":"+32 53 66 47 80",
    "sg:postcode":"1770",
    "sg:province":"Vlaams-Brabant",
    "sg:tags":[
        "-",
        "furniture"
    ],
    "wof:name":"Mobilas Meubelen Bvba",
    "wof:placetype":"venue"
},
  "geometry": {"coordinates":[4.1141171455,50.8595542908],"type":"Point"}
}