{
  "type": "Feature",
  "properties": {
    "addr:full":"Chemin Du Nesplier 43 Braine-le-comte Hainaut 7090",
    "addr:housenumber":"43",
    "addr:postcode":"7090",
    "addr:street":"Chemin Du Nesplier",
    "iso:country":"BE",
    "sg:address":"Chemin Du Nesplier 43",
    "sg:city":"Braine-le-comte",
    "sg:orig_category":"M\u00e9decins and sp\u00e9cialistes",
    "sg:phone":"+32 67 55 55 03",
    "sg:postcode":"7090",
    "sg:province":"Hainaut",
    "wof:name":"Jean-marc Bertrand",
    "wof:placetype":"venue"
},
  "geometry": {"coordinates":[4.1510329247,50.5946006775],"type":"Point"}
}