{
  "type": "Feature",
  "properties": {
    "iso:country":"BE",
    "sg:address":"Hernestraat 1",
    "sg:city":"Galmaarden (tollembeek)",
    "sg:classifiers":[
        {
            "category":"Bars & Pubs",
            "type":"Food & Drink"
        }
    ],
    "sg:phone":"+32 54 58 75 83",
    "sg:postcode":"1570",
    "sg:province":"Vlaams-Brabant",
    "wof:name":"Torenhof",
    "wof:placetype":"venue"
},
  "geometry": {"coordinates":[4.0067858696,50.7409439087],"type":"Point"}
}