{
  "type": "Feature",
  "properties": {
    "addr:full":"Wouter Schoutstraat 8 Kortrijk (heule) West-Vlaanderen 8501",
    "addr:housenumber":"8",
    "addr:postcode":"8501",
    "addr:street":"Wouter Schoutstraat",
    "iso:country":"BE",
    "sg:address":"Wouter Schoutstraat 8",
    "sg:city":"Kortrijk (heule)",
    "sg:classifiers":[
        {
            "category":"Building & Trades",
            "subcategory":"Landscaping Services",
            "type":"Services"
        }
    ],
    "sg:phone":"+32 56 35 98 76",
    "sg:postcode":"8501",
    "sg:province":"West-Vlaanderen",
    "sg:tags":[
        "nurseryman"
    ],
    "wof:name":"Devriendt K",
    "wof:placetype":"venue"
},
  "geometry": {"coordinates":[3.2225730419,50.8704833984],"type":"Point"}
}