{
  "type": "Feature",
  "properties": {
    "iso:country":"BE",
    "sg:address":"Frans Beirenslaan 189",
    "sg:city":"Borsbeek",
    "sg:orig_category":"Dakwerken",
    "sg:phone":"+32 3 458 76 82",
    "sg:postcode":"2150",
    "sg:province":"Antwerpen",
    "wof:name":"Verstraeten",
    "wof:placetype":"venue"
},
  "geometry": {"coordinates":[4.4824500084,51.1990280151],"type":"Point"}
}