{
  "type": "Feature",
  "properties": {
    "iso:country":"BE",
    "sg:address":"Baantveld 16ba",
    "sg:city":"Geel",
    "sg:orig_category":"Immobili\u00ebnkantoren Verzekeringsmakelaars and experts",
    "sg:phone":"+32 14 58 26 54",
    "sg:postcode":"2440",
    "sg:province":"Antwerpen",
    "wof:name":"Act-imm",
    "wof:placetype":"venue"
},
  "geometry": {"coordinates":[4.9799351692,51.1609573364],"type":"Point"}
}