{
  "type": "Feature",
  "properties": {
    "addr:full":"Flonkedreef 16 Gent (drongen) Oost-Vlaanderen 9031",
    "addr:housenumber":"16",
    "addr:postcode":"9031",
    "addr:street":"Flonkedreef",
    "iso:country":"BE",
    "sg:address":"Flonkedreef 16",
    "sg:city":"Gent (drongen)",
    "sg:classifiers":[
        {
            "category":"Wholesale",
            "subcategory":"Painting Supplies",
            "type":"Manufacturing & Wholesale Goods"
        }
    ],
    "sg:phone":"+32 9 330 47 74",
    "sg:postcode":"9031",
    "sg:province":"Oost-Vlaanderen",
    "sg:tags":[
        "spray"
    ],
    "wof:name":"Airbrush Marc",
    "wof:placetype":"venue"
},
  "geometry": {"coordinates":[3.6385369301,51.0492706299],"type":"Point"}
}