{
  "type": "Feature",
  "properties": {
    "iso:country":"BE",
    "sg:address":"Grand-rue 51",
    "sg:city":"Leuze-en-hainaut",
    "sg:classifiers":[
        {
            "category":"Fast Food",
            "type":"Food & Drink"
        }
    ],
    "sg:phone":"+32 69 66 16 94",
    "sg:postcode":"7900",
    "sg:province":"Hainaut",
    "sg:tags":[
        "\u00c0",
        "restaurants",
        "emporter",
        "restaurant"
    ],
    "wof:name":"Restaurant Olympos",
    "wof:placetype":"venue"
},
  "geometry": {"coordinates":[3.6186990738,50.5998039246],"type":"Point"}
}