{
  "type": "Feature",
  "properties": {
    "iso:country":"BE",
    "sg:address":"Chauss\u00c9e De Charleroi 325",
    "sg:city":"Gembloux",
    "sg:orig_category":"Boomkwekerijen Tuinen",
    "sg:phone":"+32 475 48 00 09",
    "sg:postcode":"5030",
    "sg:province":"Namur",
    "wof:name":"Dricot Fr\u00c9deric",
    "wof:placetype":"venue"
},
  "geometry": {"coordinates":[4.6829199791,50.5614318848],"type":"Point"}
}