{
  "type": "Feature",
  "properties": {
    "addr:full":"Hanswijkstraat 33 Mechelen Antwerpen 2800",
    "addr:housenumber":"33",
    "addr:postcode":"2800",
    "addr:street":"Hanswijkstraat",
    "iso:country":"BE",
    "sg:address":"Hanswijkstraat 33",
    "sg:city":"Mechelen",
    "sg:orig_category":"Verlichting and huishoudartikelen",
    "sg:phone":"+32 15 41 63 46",
    "sg:postcode":"2800",
    "sg:province":"Antwerpen",
    "wof:name":"Meka",
    "wof:placetype":"venue"
},
  "geometry": {"coordinates":[4.4836220741,51.0224723816],"type":"Point"}
}