{
  "type": "Feature",
  "properties": {
    "addr:full":"Rue D'arlon 220-39 Messancy Luxembourg 6780",
    "addr:postcode":"220-39;6780",
    "addr:street":"Rue D'Arlon",
    "iso:country":"BE",
    "sg:address":"Rue D'arlon 220-39",
    "sg:city":"Messancy",
    "sg:classifiers":[
        {
            "category":"Shopping",
            "subcategory":"Clothing, Apparel, & Fashions",
            "type":"Retail Goods"
        }
    ],
    "sg:phone":"+32 63 38 76 13",
    "sg:postcode":"6780",
    "sg:province":"Luxembourg",
    "sg:tags":[
        "lady",
        "clothing",
        "-"
    ],
    "wof:name":"Pimkie",
    "wof:placetype":"venue"
},
  "geometry": {"coordinates":[5.8126430511,49.5978775024],"type":"Point"}
}