{
  "type": "Feature",
  "properties": {
    "addr:full":"Kapelstraat 9 Temse Oost-Vlaanderen 9140",
    "addr:housenumber":"9",
    "addr:postcode":"9140",
    "addr:street":"Kapelstraat",
    "iso:country":"BE",
    "sg:address":"Kapelstraat 9",
    "sg:city":"Temse",
    "sg:orig_category":"Brood, gebak and snoepgoed",
    "sg:phone":"+32 3 774 38 56",
    "sg:postcode":"9140",
    "sg:province":"Oost-Vlaanderen",
    "wof:name":"Casemir",
    "wof:placetype":"venue"
},
  "geometry": {"coordinates":[4.2492799759,51.1289596558],"type":"Point"}
}