{
  "type": "Feature",
  "properties": {
    "addr:full":"Rue Vis\u00e9-voie 204 Herstal (vottem) Li\u00e8ge 4041",
    "addr:housenumber":"204",
    "addr:postcode":"4041",
    "addr:street":"Rue Vise\u0301-Voie;Vottem",
    "iso:country":"BE",
    "sg:address":"Rue Vis\u00e9-voie 204",
    "sg:city":"Herstal (vottem)",
    "sg:classifiers":[
        {
            "category":"Arena",
            "subcategory":"Sports Club",
            "type":"Entertainment"
        }
    ],
    "sg:phone":"+32 4 227 00 08",
    "sg:postcode":"4041",
    "sg:province":"Li\u00e8ge",
    "wof:name":"Studio Forme Sprl",
    "wof:placetype":"venue"
},
  "geometry": {"coordinates":[5.5749340057,50.6696281433],"type":"Point"}
}