{
  "type": "Feature",
  "properties": {
    "addr:full":"Avenue De L'espoir 40 Boussu Hainaut 7301",
    "addr:housenumber":"40",
    "addr:postcode":"7301",
    "addr:street":"Avenue De L'Espoir",
    "iso:country":"BE",
    "sg:address":"Avenue De L'espoir 40",
    "sg:city":"Boussu",
    "sg:orig_category":"Installation \u00e9lectrique r\u00e9sidentielle. Installation \u00e9lectrique industrielle",
    "sg:phone":"+32 65 76 69 20",
    "sg:postcode":"7301",
    "sg:province":"Hainaut",
    "wof:name":"Montelec",
    "wof:placetype":"venue"
},
  "geometry": {"coordinates":[3.820743084,50.435333252],"type":"Point"}
}