{
  "type": "Feature",
  "properties": {
    "iso:country":"BE",
    "sg:address":"Leopoldplaats 11",
    "sg:city":"Antwerpen",
    "sg:orig_category":"D\u00e9corateurs d'int\u00e9rieur",
    "sg:phone":"+32 3 233 87 15",
    "sg:postcode":"2000",
    "sg:province":"Antwerpen",
    "wof:name":"Gert Voorjans",
    "wof:placetype":"venue"
},
  "geometry": {"coordinates":[4.4069027901,51.2121391296],"type":"Point"}
}