{
  "type": "Feature",
  "properties": {
    "iso:country":"BE",
    "sg:address":"Broekelken 32",
    "sg:city":"Maldegem (adegem)",
    "sg:classifiers":[
        {
            "category":"Communications",
            "subcategory":"News Services",
            "type":"Services"
        }
    ],
    "sg:phone":"+32 50 72 00 45",
    "sg:postcode":"9991",
    "sg:province":"Oost-Vlaanderen",
    "sg:tags":[
        "agency"
    ],
    "wof:name":"Vacas",
    "wof:placetype":"venue"
},
  "geometry": {"coordinates":[3.4889791012,51.2109794617],"type":"Point"}
}