{
  "type": "Feature",
  "properties": {
    "addr:full":"Avenue Ferdinand Nicolay 9 Stavelot Li\u00e8ge 4970",
    "addr:housenumber":"9",
    "addr:postcode":"4970",
    "addr:street":"Avenue Ferdinand Nicolay",
    "iso:country":"BE",
    "sg:address":"Avenue Ferdinand Nicolay 9",
    "sg:city":"Stavelot",
    "sg:classifiers":[
        {
            "category":"Travel",
            "subcategory":"Hotels & Motels",
            "type":"Entertainment"
        }
    ],
    "sg:phone":"+32 80 86 20 44",
    "sg:postcode":"4970",
    "sg:province":"Li\u00e8ge",
    "wof:name":"Auberge St-remacle",
    "wof:placetype":"venue"
},
  "geometry": {"coordinates":[5.9308018684,50.3944396973],"type":"Point"}
}