{
  "type": "Feature",
  "properties": {
    "addr:full":"Rue De Fontenoille 155 Florenville Luxembourg 6820",
    "addr:housenumber":"155",
    "addr:postcode":"6820",
    "addr:street":"Rue De Fontenoille",
    "iso:country":"BE",
    "sg:address":"Rue De Fontenoille 155",
    "sg:city":"Florenville",
    "sg:orig_category":"Rundveehouders",
    "sg:phone":"+32 61 31 22 04",
    "sg:postcode":"6820",
    "sg:province":"Luxembourg",
    "wof:name":"Paulin Guiot",
    "wof:placetype":"venue"
},
  "geometry": {"coordinates":[5.2383871078,49.7241897583],"type":"Point"}
}