{
  "type": "Feature",
  "properties": {
    "addr:full":"Sint-michielstraat 21 Tielt West-Vlaanderen 8700",
    "addr:housenumber":"21",
    "addr:postcode":"8700",
    "addr:street":"Sint-Michielstraat",
    "iso:country":"BE",
    "sg:address":"Sint-michielstraat 21",
    "sg:city":"Tielt",
    "sg:orig_category":"Studios photographiques",
    "sg:phone":"+32 51 40 48 72",
    "sg:postcode":"8700",
    "sg:province":"West-Vlaanderen",
    "wof:name":"Foto Terma",
    "wof:placetype":"venue"
},
  "geometry": {"coordinates":[3.3217248917,50.9976615906],"type":"Point"}
}