{
  "type": "Feature",
  "properties": {
    "iso:country":"BE",
    "sg:address":"Onze Lieve Vrouwlaan 107",
    "sg:city":"Evere",
    "sg:orig_category":"Herstelling horloges and juwelen Juwelen and horloges",
    "sg:phone":"+32 2 215 37 08",
    "sg:postcode":"1140",
    "sg:province":"Bruxelles-Capitale",
    "wof:name":"Maison Van Hoof",
    "wof:placetype":"venue"
},
  "geometry": {"coordinates":[4.400592804,50.8713951111],"type":"Point"}
}