{
  "type": "Feature",
  "properties": {
    "addr:full":"Kapellestraat 54 Oostkamp West-Vlaanderen 8020",
    "addr:housenumber":"54",
    "addr:postcode":"8020",
    "addr:street":"Kapellestraat",
    "iso:country":"BE",
    "sg:address":"Kapellestraat 54",
    "sg:city":"Oostkamp",
    "sg:orig_category":"Elektrische installaties voor woningen Winkelinrichting and handelsuitrusting Gh",
    "sg:phone":"+32 50 82 50 92",
    "sg:postcode":"8020",
    "sg:province":"West-Vlaanderen",
    "wof:name":"Luc Danneels",
    "wof:placetype":"venue"
},
  "geometry": {"coordinates":[3.2388660908,51.1518287659],"type":"Point"}
}