{
  "type": "Feature",
  "properties": {
    "addr:full":"Galgenberg 25 Gent Oost-Vlaanderen 9000",
    "addr:housenumber":"25",
    "addr:postcode":"9000",
    "addr:street":"Galgenberg;Oost-Vlaanderen",
    "iso:country":"BE",
    "sg:address":"Galgenberg 25",
    "sg:city":"Gent",
    "sg:classifiers":[
        {
            "category":"Travel",
            "subcategory":"Hotels & Motels",
            "type":"Entertainment"
        }
    ],
    "sg:phone":"+32 9 233 63 96",
    "sg:postcode":"9000",
    "sg:province":"Oost-Vlaanderen",
    "wof:name":"Hoste Business Flats",
    "wof:placetype":"venue"
},
  "geometry": {"coordinates":[3.7139770985,51.0509567261],"type":"Point"}
}