{
  "type": "Feature",
  "properties": {
    "addr:full":"Rue Al'copette 9 Marche-en-famenne Luxembourg 6900",
    "addr:housenumber":"9",
    "addr:postcode":"6900",
    "addr:street":"Rue Al'Copette",
    "iso:country":"BE",
    "sg:address":"Rue Al'copette 9",
    "sg:city":"Marche-en-famenne",
    "sg:classifiers":[
        {
            "category":"Insurance",
            "subcategory":"Life Insurance",
            "type":"Services"
        }
    ],
    "sg:phone":"+32 84 31 51 28",
    "sg:postcode":"6900",
    "sg:province":"Luxembourg",
    "sg:tags":[
        "assurance"
    ],
    "wof:name":"F. De Ceulaer",
    "wof:placetype":"venue"
},
  "geometry": {"coordinates":[5.3234591484,50.1979446411],"type":"Point"}
}