{
  "type": "Feature",
  "properties": {
    "iso:country":"BE",
    "sg:address":"Blekersdijk 33",
    "sg:city":"Gent",
    "sg:classifiers":[
        {
            "category":"Professional",
            "subcategory":"Engineering",
            "type":"Services"
        }
    ],
    "sg:phone":"+32 9 223 70 05",
    "sg:postcode":"9000",
    "sg:province":"Oost-Vlaanderen",
    "sg:tags":[
        "-"
    ],
    "wof:name":"Atelier 4",
    "wof:placetype":"venue"
},
  "geometry": {"coordinates":[3.7311561108,51.0596389771],"type":"Point"}
}