{
  "type": "Feature",
  "properties": {
    "addr:full":"Kortrijksestraat 32 Oostkamp West-Vlaanderen 8020",
    "addr:housenumber":"32",
    "addr:postcode":"8020",
    "addr:street":"Kortrijksestraat",
    "iso:country":"BE",
    "sg:address":"Kortrijksestraat 32",
    "sg:city":"Oostkamp",
    "sg:classifiers":[
        {
            "category":"Sports & Exercise",
            "subcategory":"Gym",
            "type":"Entertainment"
        }
    ],
    "sg:phone":"+32 50 82 71 76",
    "sg:postcode":"8020",
    "sg:province":"West-Vlaanderen",
    "sg:tags":[
        "access",
        "gymnastics",
        "-",
        "apparatus",
        "fitness"
    ],
    "wof:name":"Sana Care",
    "wof:placetype":"venue"
},
  "geometry": {"coordinates":[3.2347569466,51.1529655457],"type":"Point"}
}