{
  "type": "Feature",
  "properties": {
    "addr:full":"Toekomststraat 31 Kortrijk West-Vlaanderen 8500",
    "addr:housenumber":"31",
    "addr:postcode":"8500",
    "addr:street":"Toekomststraat",
    "iso:country":"BE",
    "sg:address":"Toekomststraat 31",
    "sg:city":"Kortrijk",
    "sg:classifiers":[
        {
            "category":"Real Estate",
            "subcategory":"Architect",
            "type":"Services"
        }
    ],
    "sg:phone":"+32 56 32 04 12",
    "sg:postcode":"8500",
    "sg:province":"West-Vlaanderen",
    "wof:name":"Vandenbulcke L",
    "wof:placetype":"venue"
},
  "geometry": {"coordinates":[3.2708289623,50.8217201233],"type":"Point"}
}