{
  "type": "Feature",
  "properties": {
    "iso:country":"BE",
    "sg:address":"Fonteinstraat 22",
    "sg:city":"Menen",
    "sg:orig_category":"Entretien and r\u00e9parations de voitures",
    "sg:phone":"+32 56 42 48 66",
    "sg:postcode":"8930",
    "sg:province":"West-Vlaanderen",
    "wof:name":"Lieven Denys",
    "wof:placetype":"venue"
},
  "geometry": {"coordinates":[3.1662430763,50.7851104736],"type":"Point"}
}