{
  "type": "Feature",
  "properties": {
    "addr:full":"Heiwijkerweg 36 Zutendaal Limburg 3690",
    "addr:housenumber":"36",
    "addr:postcode":"3690",
    "addr:street":"Heiwijkerweg",
    "iso:country":"BE",
    "sg:address":"Heiwijkerweg 36",
    "sg:city":"Zutendaal",
    "sg:classifiers":[
        {
            "category":"Home & Garden",
            "subcategory":"Hardware",
            "type":"Retail Goods"
        }
    ],
    "sg:phone":"+32 89 61 15 53",
    "sg:postcode":"3690",
    "sg:province":"Limburg",
    "sg:tags":[
        "gate",
        "opener",
        "door",
        "automatic"
    ],
    "wof:name":"Euromatic Bvba",
    "wof:placetype":"venue"
},
  "geometry": {"coordinates":[5.5903339386,50.9390106201],"type":"Point"}
}