{
  "type": "Feature",
  "properties": {
    "addr:full":"Place Des Arsilliers 9 Malmedy Li\u00e8ge 4960",
    "addr:housenumber":"9",
    "addr:postcode":"4960",
    "addr:street":"Place Des Arsilliers",
    "iso:country":"BE",
    "sg:address":"Place Des Arsilliers 9",
    "sg:city":"Malmedy",
    "sg:orig_category":"S\u00e9lection de personnel and placement",
    "sg:phone":"+32 80 79 94 11",
    "sg:postcode":"4960",
    "sg:province":"Li\u00e8ge",
    "wof:name":"F.o.r.e.m.",
    "wof:placetype":"venue"
},
  "geometry": {"coordinates":[6.0247330666,50.4235229492],"type":"Point"}
}