{
  "type": "Feature",
  "properties": {
    "addr:full":"Avenue Paul Pastur 82 Charleroi (marcinelle) Hainaut 6001",
    "addr:housenumber":"82",
    "addr:postcode":"6001",
    "addr:street":"Avenue Paul Pastur",
    "iso:country":"BE",
    "sg:address":"Avenue Paul Pastur 82",
    "sg:city":"Charleroi (marcinelle)",
    "sg:classifiers":[
        {
            "category":"Building & Trades",
            "subcategory":"Pest Control",
            "type":"Services"
        }
    ],
    "sg:phone":"+32 71 36 27 31",
    "sg:postcode":"6001",
    "sg:province":"Hainaut",
    "sg:tags":[
        "machine",
        "vending"
    ],
    "wof:name":"Distriservice Sprl",
    "wof:placetype":"venue"
},
  "geometry": {"coordinates":[4.4297580719,50.4026374817],"type":"Point"}
}