{
  "type": "Feature",
  "properties": {
    "iso:country":"BE",
    "sg:address":"Route De La Hesbaye 369",
    "sg:city":"Eghezee",
    "sg:orig_category":"Landbouwmachines Gh",
    "sg:phone":"+32 81 85 57 54",
    "sg:postcode":"5310",
    "sg:province":"Namur",
    "wof:name":"Michel Grandgagnage",
    "wof:placetype":"venue"
},
  "geometry": {"coordinates":[4.9628119469,50.6269874573],"type":"Point"}
}