{
  "type": "Feature",
  "properties": {
    "addr:full":"Duinenweg 493 Middelkerke West-Vlaanderen 8430",
    "addr:housenumber":"493",
    "addr:postcode":"8430",
    "addr:street":"Duinenweg",
    "iso:country":"BE",
    "sg:address":"Duinenweg 493",
    "sg:city":"Middelkerke",
    "sg:classifiers":[
        {
            "category":"Travel",
            "subcategory":"Resort",
            "type":"Entertainment"
        }
    ],
    "sg:phone":"+32 59 30 53 38",
    "sg:postcode":"8430",
    "sg:province":"West-Vlaanderen",
    "sg:tags":[
        "vacation"
    ],
    "wof:name":"Zeegalm Nv",
    "wof:placetype":"venue"
},
  "geometry": {"coordinates":[2.7916100025,51.1751289368],"type":"Point"}
}