{
  "type": "Feature",
  "properties": {
    "addr:full":"Rue Tout Y Faut 84 La Louvi\u00e8re (houdeng-goegnies) Hainaut 7110",
    "addr:housenumber":"84",
    "addr:postcode":"7110",
    "addr:street":"Rue Tout Y Faut",
    "iso:country":"BE",
    "sg:address":"Rue Tout Y Faut 84",
    "sg:city":"La Louvi\u00e8re (houdeng-goegnies)",
    "sg:classifiers":[
        {
            "category":"Insurance",
            "subcategory":"Insurance Agent",
            "type":"Services"
        }
    ],
    "sg:phone":"+32 64 26 41 11",
    "sg:postcode":"7110",
    "sg:province":"Hainaut",
    "sg:tags":[
        "broker"
    ],
    "wof:name":"S.i.e. Sa",
    "wof:placetype":"venue"
},
  "geometry": {"coordinates":[4.1505050659,50.4826698303],"type":"Point"}
}