{
  "type": "Feature",
  "properties": {
    "addr:full":"Autobaan 12a Zedelgem (loppem) West-Vlaanderen 8210",
    "addr:housenumber":"12a",
    "addr:postcode":"8210",
    "addr:street":"Autobaan",
    "iso:country":"BE",
    "sg:address":"Autobaan 12a",
    "sg:city":"Zedelgem (loppem)",
    "sg:classifiers":[
        {
            "category":"Fast Food",
            "type":"Food & Drink"
        }
    ],
    "sg:phone":"+32 50 84 12 80",
    "sg:postcode":"8210",
    "sg:province":"West-Vlaanderen",
    "sg:tags":[
        "fried",
        "stand",
        "potato"
    ],
    "wof:name":"Exit 7",
    "wof:placetype":"venue"
},
  "geometry": {"coordinates":[3.1458399296,51.1376457214],"type":"Point"}
}