{
  "type": "Feature",
  "properties": {
    "iso:country":"BE",
    "sg:address":"Rue Chantrenne 30",
    "sg:city":"Momignies",
    "sg:orig_category":"D\u00e9taillants en pi\u00e8ces and accessoires de voitures",
    "sg:phone":"+32 60 51 14 86",
    "sg:postcode":"6590",
    "sg:province":"Hainaut",
    "wof:name":"Momignies Pneu Service",
    "wof:placetype":"venue"
},
  "geometry": {"coordinates":[4.1622171402,50.0288467407],"type":"Point"}
}