{
  "type": "Feature",
  "properties": {
    "iso:country":"BE",
    "sg:address":"Rue De Plate 15",
    "sg:city":"Saint-l\u00c9ger",
    "sg:orig_category":"Boekhouders",
    "sg:phone":"+32 63 22 18 98",
    "sg:postcode":"6747",
    "sg:province":"Luxembourg",
    "wof:name":"Guy Collot",
    "wof:placetype":"venue"
},
  "geometry": {"coordinates":[5.6536512375,49.6105690002],"type":"Point"}
}