{
  "type": "Feature",
  "properties": {
    "addr:full":"Feldstraat 58 Butgenbach Li\u00e8ge 4750",
    "addr:housenumber":"58",
    "addr:postcode":"4750",
    "addr:street":"Feldstraat",
    "iso:country":"BE",
    "sg:address":"Feldstraat 58",
    "sg:city":"Butgenbach",
    "sg:orig_category":"Woningbouw",
    "sg:phone":"+32 80 44 01 10",
    "sg:postcode":"4750",
    "sg:province":"Li\u00e8ge",
    "wof:name":"Heck",
    "wof:placetype":"venue"
},
  "geometry": {"coordinates":[6.1707220078,50.4288063049],"type":"Point"}
}