{
  "type": "Feature",
  "properties": {
    "iso:country":"BE",
    "sg:address":"Rue Du Faubourg 5",
    "sg:city":"Leuze-en-hainaut (willaupuis)",
    "sg:classifiers":[
        {
            "category":"Home & Garden",
            "subcategory":"Garden Supply",
            "type":"Retail Goods"
        }
    ],
    "sg:phone":"+32 69 66 12 29",
    "sg:postcode":"7904",
    "sg:province":"Hainaut",
    "sg:tags":[
        "seed",
        "-"
    ],
    "wof:name":"De Vlieger J-p",
    "wof:placetype":"venue"
},
  "geometry": {"coordinates":[3.6111040115,50.5638542175],"type":"Point"}
}