{
  "type": "Feature",
  "properties": {
    "addr:full":"Clos Chapelle-aux-champs 30b39 Sint-lambrechts-woluwe/woluwe-saint-lambert Bruxelles-Capitale 1200",
    "addr:housenumber":"30b39",
    "addr:postcode":"1200",
    "addr:street":"Clos Chapelle-Aux-Champs",
    "iso:country":"BE",
    "sg:address":"Clos Chapelle-aux-champs 30b39",
    "sg:city":"Sint-lambrechts-woluwe/woluwe-saint-lambert",
    "sg:orig_category":"M\u00e9decins and sp\u00e9cialistes",
    "sg:phone":"+32 2 764 30 80",
    "sg:postcode":"1200",
    "sg:province":"Bruxelles-Capitale",
    "wof:name":"Mich\u00c8le Gros Gean",
    "wof:placetype":"venue"
},
  "geometry": {"coordinates":[4.4498109818,50.8496398926],"type":"Point"}
}