{
  "type": "Feature",
  "properties": {
    "addr:full":"Siedlung Europa 11 Kelmis/la Calamine Li\u00e8ge 4720",
    "addr:housenumber":"11",
    "addr:postcode":"4720",
    "addr:street":"Siedlung Europa",
    "iso:country":"BE",
    "sg:address":"Siedlung Europa 11",
    "sg:city":"Kelmis/la Calamine",
    "sg:orig_category":"Rev\u00eatements pour sols and murs",
    "sg:phone":"+32 87 65 70 37",
    "sg:postcode":"4720",
    "sg:province":"Li\u00e8ge",
    "wof:name":"Peter Loup",
    "wof:placetype":"venue"
},
  "geometry": {"coordinates":[6.0123028755,50.7190895081],"type":"Point"}
}