{
  "type": "Feature",
  "properties": {
    "iso:country":"BE",
    "sg:address":"Jachtstraat 10",
    "sg:city":"Bilzen",
    "sg:classifiers":[
        {
            "category":"Health Services",
            "subcategory":"Doctor",
            "type":"Services"
        }
    ],
    "sg:phone":"+32 89 35 31 33",
    "sg:postcode":"3740",
    "sg:province":"Limburg",
    "sg:tags":[
        "psychotherapist",
        "psychoanalyst"
    ],
    "wof:name":"Berta B",
    "wof:placetype":"venue"
},
  "geometry": {"coordinates":[5.4867768288,50.8816146851],"type":"Point"}
}