{
  "type": "Feature",
  "properties": {
    "iso:country":"BE",
    "sg:address":"Route De Philippeville 219",
    "sg:city":"Charleroi (couillet)",
    "sg:classifiers":[
        {
            "category":"Food & Beverages",
            "subcategory":"Groceries & Convenience Stores",
            "type":"Retail Goods"
        }
    ],
    "sg:phone":"+32 71 43 43 85",
    "sg:postcode":"6010",
    "sg:province":"Hainaut",
    "sg:tags":[
        "grocer"
    ],
    "wof:name":"Leader-price Sa",
    "wof:placetype":"venue"
},
  "geometry": {"coordinates":[4.4621329308,50.3870429993],"type":"Point"}
}