{
  "type": "Feature",
  "properties": {
    "addr:full":"Rue Du Moulin 37 Braine-le-comte Hainaut 7090",
    "addr:housenumber":"37",
    "addr:postcode":"7090",
    "addr:street":"Rue Du Moulin",
    "iso:country":"BE",
    "sg:address":"Rue Du Moulin 37",
    "sg:city":"Braine-le-comte",
    "sg:orig_category":"Mat\u00e9riel m\u00e9dical and orthop\u00e9dique and proth\u00e8ses Fab",
    "sg:phone":"+32 67 56 01 61",
    "sg:postcode":"7090",
    "sg:province":"Hainaut",
    "wof:name":"Ecodent",
    "wof:placetype":"venue"
},
  "geometry": {"coordinates":[4.1431288719,50.6102256775],"type":"Point"}
}