{
  "type": "Feature",
  "properties": {
    "iso:country":"BE",
    "sg:address":"Rue Saint-jean 42",
    "sg:city":"Tubize",
    "sg:orig_category":"M\u00e9decines alternatives",
    "sg:phone":"+32 2 355 65 07",
    "sg:postcode":"1480",
    "sg:province":"Brabant Wallon",
    "wof:name":"Robert Latinis",
    "wof:placetype":"venue"
},
  "geometry": {"coordinates":[4.2249350548,50.6904792786],"type":"Point"}
}