{
  "type": "Feature",
  "properties": {
    "iso:country":"BE",
    "sg:address":"Aarschotsesteenweg 165",
    "sg:city":"Lier (groot)",
    "sg:orig_category":"Textiel",
    "sg:phone":"+32 3 482 15 61",
    "sg:postcode":"2500",
    "sg:province":"Antwerpen",
    "wof:name":"Huis Busschots",
    "wof:placetype":"venue"
},
  "geometry": {"coordinates":[4.6134910583,51.100112915],"type":"Point"}
}