{
  "type": "Feature",
  "properties": {
    "iso:country":"BE",
    "sg:address":"Rue Des Acacias 26",
    "sg:city":"Mont-saint-guibert",
    "sg:orig_category":"Sportclubs",
    "sg:phone":"+32 10 65 78 08",
    "sg:postcode":"1435",
    "sg:province":"Brabant Wallon",
    "wof:name":"R.m.c. Pierreux",
    "wof:placetype":"venue"
},
  "geometry": {"coordinates":[4.6087441444,50.6454429626],"type":"Point"}
}