{
  "type": "Feature",
  "properties": {
    "addr:full":"Rue Henri Lemaitre 81 Namur Namur 5000",
    "addr:housenumber":"81",
    "addr:postcode":"5000",
    "addr:street":"Rue Henri Lemaitre",
    "iso:country":"BE",
    "sg:address":"Rue Henri Lemaitre 81",
    "sg:city":"Namur",
    "sg:classifiers":[
        {
            "category":"Insurance",
            "subcategory":"Life Insurance",
            "type":"Services"
        }
    ],
    "sg:phone":"+32 81 74 65 65",
    "sg:postcode":"5000",
    "sg:province":"Namur",
    "sg:tags":[
        "assurance"
    ],
    "wof:name":"Arquin Nicolas",
    "wof:placetype":"venue"
},
  "geometry": {"coordinates":[4.8547949791,50.4633522034],"type":"Point"}
}