{
  "type": "Feature",
  "properties": {
    "addr:full":"Kliniekstraat 26 Gent (gentbrugge) Oost-Vlaanderen 9050",
    "addr:housenumber":"26",
    "addr:postcode":"9050",
    "addr:street":"Kliniekstraat",
    "iso:country":"BE",
    "sg:address":"Kliniekstraat 26",
    "sg:city":"Gent (gentbrugge)",
    "sg:classifiers":[
        {
            "category":"Food & Beverages",
            "subcategory":"Groceries & Convenience Stores",
            "type":"Retail Goods"
        }
    ],
    "sg:phone":"+32 9 230 11 63",
    "sg:postcode":"9050",
    "sg:province":"Oost-Vlaanderen",
    "sg:tags":[
        "grocer"
    ],
    "wof:name":"Devre",
    "wof:placetype":"venue"
},
  "geometry": {"coordinates":[3.7553110123,51.0432281494],"type":"Point"}
}