{
  "type": "Feature",
  "properties": {
    "iso:country":"BE",
    "sg:address":"Bruyneelstraat 3",
    "sg:city":"Steenokkerzeel",
    "sg:orig_category":"M\u00e9decins and sp\u00e9cialistes",
    "sg:phone":"+32 2 759 72 29",
    "sg:postcode":"1820",
    "sg:province":"Vlaams-Brabant",
    "wof:name":"Herwig Van Asch",
    "wof:placetype":"venue"
},
  "geometry": {"coordinates":[4.5133318901,50.9102745056],"type":"Point"}
}