{
  "type": "Feature",
  "properties": {
    "iso:country":"BE",
    "sg:address":"Oplintersesteenweg 578",
    "sg:city":"Tienen",
    "sg:orig_category":"Fleurs and plantes",
    "sg:phone":"+32 16 81 60 64",
    "sg:postcode":"3300",
    "sg:province":"Vlaams-Brabant",
    "wof:name":"Sidon",
    "wof:placetype":"venue"
},
  "geometry": {"coordinates":[4.9496798515,50.8199691772],"type":"Point"}
}