{
  "type": "Feature",
  "properties": {
    "addr:full":"Avenue Louise 423 Elsene/ixelles Bruxelles-Capitale 1050",
    "addr:housenumber":"423",
    "addr:postcode":"1050",
    "addr:street":"Avenue Louise",
    "iso:country":"BE",
    "sg:address":"Avenue Louise 423",
    "sg:city":"Elsene/ixelles",
    "sg:orig_category":"Salles de spectacles",
    "sg:phone":"+32 2 648 60 55",
    "sg:postcode":"1050",
    "sg:province":"Bruxelles-Capitale",
    "wof:name":"Cloots Ch.",
    "wof:placetype":"venue"
},
  "geometry": {"coordinates":[4.355919838,50.8357810974],"type":"Point"}
}