{
  "type": "Feature",
  "properties": {
    "addr:full":"Knutsegemstraat 29bb Zottegem Oost-Vlaanderen 9620",
    "addr:housenumber":"29bb",
    "addr:postcode":"9620",
    "addr:street":"Knutsegemstraat",
    "iso:country":"BE",
    "sg:address":"Knutsegemstraat 29bb",
    "sg:city":"Zottegem",
    "sg:orig_category":"Traitements param\u00e9dicaux",
    "sg:phone":"+32 9 360 93 05",
    "sg:postcode":"9620",
    "sg:province":"Oost-Vlaanderen",
    "wof:name":"M. Hallewaert",
    "wof:placetype":"venue"
},
  "geometry": {"coordinates":[3.8112111092,50.871181488],"type":"Point"}
}