{
  "type": "Feature",
  "properties": {
    "iso:country":"BE",
    "sg:address":"Bergense Steenweg 1048ba",
    "sg:city":"Anderlecht/anderlecht",
    "sg:orig_category":"Slagers Zuivelproducten",
    "sg:phone":"+32 2 521 49 70",
    "sg:postcode":"1070",
    "sg:province":"Bruxelles-Capitale",
    "wof:name":"Albert Mox/a. Mox",
    "wof:placetype":"venue"
},
  "geometry": {"coordinates":[4.2951879501,50.822719574],"type":"Point"}
}