{
  "type": "Feature",
  "properties": {
    "iso:country":"BE",
    "sg:address":"Rue Du Parc 32",
    "sg:city":"Namur",
    "sg:classifiers":[
        {
            "category":"Real Estate",
            "subcategory":"Architect",
            "type":"Services"
        }
    ],
    "sg:phone":"+32 81 22 02 26",
    "sg:postcode":"5000",
    "sg:province":"Namur",
    "wof:name":"Alluin M",
    "wof:placetype":"venue"
},
  "geometry": {"coordinates":[4.8832402229,50.4823303223],"type":"Point"}
}