{
  "type": "Feature",
  "properties": {
    "addr:full":"Rue Emile Vandervelde 22 Charleroi Hainaut 6010",
    "addr:housenumber":"22",
    "addr:postcode":"6010",
    "addr:street":"Rue Emile Vandervelde;Hainaut",
    "iso:country":"BE",
    "sg:address":"Rue Emile Vandervelde 22",
    "sg:city":"Charleroi",
    "sg:orig_category":"Herstelling leer and schoeisel",
    "sg:phone":"+32 71 43 98 29",
    "sg:postcode":"6010",
    "sg:province":"Hainaut",
    "wof:name":"Franco Cavazza",
    "wof:placetype":"venue"
},
  "geometry": {"coordinates":[4.4695301056,50.3911056519],"type":"Point"}
}