{
  "type": "Feature",
  "properties": {
    "addr:full":"Avenue Marcel Cools 62 Fl\u00e9malle Li\u00e8ge 4400",
    "addr:housenumber":"62",
    "addr:postcode":"4400",
    "addr:street":"Avenue Marcel Cools",
    "iso:country":"BE",
    "sg:address":"Avenue Marcel Cools 62",
    "sg:city":"Fl\u00e9malle",
    "sg:classifiers":[
        {
            "category":"Health Services",
            "subcategory":"Health Practitioner",
            "type":"Services"
        }
    ],
    "sg:phone":"+32 4 273 02 19",
    "sg:postcode":"4400",
    "sg:province":"Li\u00e8ge",
    "sg:tags":[
        "physiotherapist"
    ],
    "wof:name":"Houlmont Frank",
    "wof:placetype":"venue"
},
  "geometry": {"coordinates":[5.4618649483,50.6007423401],"type":"Point"}
}