{
  "type": "Feature",
  "properties": {
    "addr:full":"Rue Basse Cornet 36 Couvin (frasnes) Namur 5660",
    "addr:housenumber":"36",
    "addr:postcode":"5660",
    "addr:street":"Rue Basse Cornet",
    "iso:country":"BE",
    "sg:address":"Rue Basse Cornet 36",
    "sg:city":"Couvin (frasnes)",
    "sg:classifiers":[
        {
            "category":"Wholesale",
            "subcategory":"Machinery & Supplies",
            "type":"Manufacturing & Wholesale Goods"
        }
    ],
    "sg:phone":"+32 60 31 26 91",
    "sg:postcode":"5660",
    "sg:province":"Namur",
    "sg:tags":[
        "refrigeration",
        "-",
        "industrial",
        "commercial",
        "equipment"
    ],
    "wof:name":"Sabinot C",
    "wof:placetype":"venue"
},
  "geometry": {"coordinates":[4.5095801353,50.0805168152],"type":"Point"}
}