{
  "type": "Feature",
  "properties": {
    "iso:country":"BE",
    "sg:address":"Brugstraat 81",
    "sg:city":"Aalter",
    "sg:classifiers":[
        {
            "category":"Retail",
            "subcategory":"Veterinary Services",
            "type":"Services"
        }
    ],
    "sg:phone":"+32 9 374 35 86",
    "sg:postcode":"9880",
    "sg:province":"Oost-Vlaanderen",
    "sg:tags":[
        "veterinarian"
    ],
    "wof:name":"Vergauwe L",
    "wof:placetype":"venue"
},
  "geometry": {"coordinates":[3.4417800903,51.0973396301],"type":"Point"}
}