{
  "type": "Feature",
  "properties": {
    "addr:full":"Rue Du Centre 23 Geer Li\u00e8ge 4250",
    "addr:housenumber":"23",
    "addr:postcode":"4250",
    "addr:street":"Rue Du Centre",
    "iso:country":"BE",
    "sg:address":"Rue Du Centre 23",
    "sg:city":"Geer",
    "sg:classifiers":[
        {
            "category":"Personal",
            "subcategory":"Beauty Salon",
            "type":"Services"
        }
    ],
    "sg:phone":"+32 19 32 89 45",
    "sg:postcode":"4250",
    "sg:province":"Li\u00e8ge",
    "sg:tags":[
        "de",
        "coiffure"
    ],
    "wof:name":"Coiffure Diffusion",
    "wof:placetype":"venue"
},
  "geometry": {"coordinates":[5.2110261917,50.6750450134],"type":"Point"}
}