{
  "type": "Feature",
  "properties": {
    "addr:full":"Rue Des Gaulois 9 Ath Hainaut 7800",
    "addr:housenumber":"9",
    "addr:postcode":"7800",
    "addr:street":"Rue Des Gaulois",
    "iso:country":"BE",
    "sg:address":"Rue Des Gaulois 9",
    "sg:city":"Ath",
    "sg:orig_category":"Anti-Burglary Equipment, Mechanical, For Doors, Windows, Roller Shutters , Shafts",
    "sg:phone":"+32 53 83 32 32",
    "sg:postcode":"7800",
    "sg:province":"Hainaut",
    "wof:name":"Somati Nv",
    "wof:placetype":"venue"
},
  "geometry": {"coordinates":[4.0422258377,50.9105186462],"type":"Point"}
}