{
  "type": "Feature",
  "properties": {
    "addr:full":"Rue Louis Vanbeveren 14 Halle Vlaams-Brabant 1500",
    "addr:housenumber":"14",
    "addr:postcode":"1500",
    "addr:street":"Rue Louis Vanbeveren",
    "iso:country":"BE",
    "sg:address":"Rue Louis Vanbeveren 14",
    "sg:city":"Halle",
    "sg:orig_category":"Production and distribution de gaz and combustibles. Production and distribution d'\u00e9lectricit\u00e9. Serv",
    "sg:phone":"+32 78 78 78 78",
    "sg:postcode":"1500",
    "sg:province":"Vlaams-Brabant",
    "wof:name":"Electrabel",
    "wof:placetype":"venue"
},
  "geometry": {"coordinates":[4.2306609154,50.7377738953],"type":"Point"}
}