{
  "type": "Feature",
  "properties": {
    "iso:country":"BE",
    "sg:address":"Oudenaardestraat 22",
    "sg:city":"Zulte (olsene)",
    "sg:classifiers":[
        {
            "category":"Structure",
            "subcategory":"Office Building",
            "type":"Public Place"
        }
    ],
    "sg:phone":"+32 9 388 65 61",
    "sg:postcode":"9870",
    "sg:province":"Oost-Vlaanderen",
    "sg:tags":[
        "drawing"
    ],
    "wof:name":"Doutreligne T",
    "wof:placetype":"venue"
},
  "geometry": {"coordinates":[3.4733350277,50.9291992188],"type":"Point"}
}