{
  "type": "Feature",
  "properties": {
    "iso:country":"BE",
    "sg:address":"Dr.vandeperrestraat 281",
    "sg:city":"Geel",
    "sg:orig_category":"Installation \u00e9lectrique r\u00e9sidentielle. Plomberie, chauffage and installations sanitaires",
    "sg:phone":"+32 14 58 45 39",
    "sg:postcode":"2440",
    "sg:province":"Antwerpen",
    "wof:name":"Theeuwes Bart",
    "wof:placetype":"venue"
},
  "geometry": {"coordinates":[4.9855880737,51.1803321838],"type":"Point"}
}