{
  "type": "Feature",
  "properties": {
    "addr:full":"Hertogendal 163 Oudergem/auderghem Bruxelles-Capitale 1160",
    "addr:housenumber":"163",
    "addr:postcode":"1160",
    "addr:street":"Hertogendal;/",
    "iso:country":"BE",
    "sg:address":"Hertogendal 163",
    "sg:city":"Oudergem/auderghem",
    "sg:orig_category":"Immobili\u00ebnkantoren",
    "sg:phone":"+32 2 675 98 68",
    "sg:postcode":"1160",
    "sg:province":"Bruxelles-Capitale",
    "wof:name":"Z.s. Consult",
    "wof:placetype":"venue"
},
  "geometry": {"coordinates":[4.416164875,50.8194732666],"type":"Point"}
}