{
  "type": "Feature",
  "properties": {
    "iso:country":"BE",
    "sg:address":"Brusselsesteenweg 478",
    "sg:city":"Asse (zellik)",
    "sg:classifiers":[
        {
            "category":"Organizations",
            "subcategory":"Professional Association",
            "type":"Services"
        }
    ],
    "sg:phone":"+32 2 463 19 50",
    "sg:postcode":"1731",
    "sg:province":"Vlaams-Brabant",
    "sg:tags":[
        "trade-union",
        "federation"
    ],
    "wof:name":"F\u00e9d\u00e9ration Belge De L'entretien Du Textile",
    "wof:placetype":"venue"
},
  "geometry": {"coordinates":[4.2603030205,50.8903007507],"type":"Point"}
}