{
  "type": "Feature",
  "properties": {
    "iso:country":"BE",
    "sg:address":"Route De Moustier 0",
    "sg:city":"Frasnes-lez-anvaing",
    "sg:orig_category":"Beheer van afvalopslag- and stortplaatsen",
    "sg:phone":"+32 69 86 84 50",
    "sg:postcode":"7911",
    "sg:province":"Hainaut",
    "wof:name":"Parcs Des Conteneurs Frasnes-les-anvaing",
    "wof:placetype":"venue"
},
  "geometry": {"coordinates":[3.6198570728,50.6563873291],"type":"Point"}
}