{
  "type": "Feature",
  "properties": {
    "iso:country":"BE",
    "sg:address":"Chauss\u00c9e Brunehaut 384",
    "sg:city":"Beloeil",
    "sg:orig_category":"Eleveurs de bovins",
    "sg:phone":"+32 69 68 93 18",
    "sg:postcode":"7972",
    "sg:province":"Hainaut",
    "wof:name":"Leon Delobelle",
    "wof:placetype":"venue"
},
  "geometry": {"coordinates":[3.6905319691,50.5555038452],"type":"Point"}
}