{
  "type": "Feature",
  "properties": {
    "addr:full":"Schoterweg 274 Tessenderlo Limburg 3980",
    "addr:housenumber":"274",
    "addr:postcode":"3980",
    "addr:street":"Schoterweg",
    "iso:country":"BE",
    "sg:address":"Schoterweg 274",
    "sg:city":"Tessenderlo",
    "sg:classifiers":[
        {
            "category":"Food & Beverages",
            "subcategory":"Groceries & Convenience Stores",
            "type":"Retail Goods"
        }
    ],
    "sg:phone":"+32 13 67 18 35",
    "sg:postcode":"3980",
    "sg:province":"Limburg",
    "sg:tags":[
        "grocer"
    ],
    "wof:name":"Kruideniertje ('t)",
    "wof:placetype":"venue"
},
  "geometry": {"coordinates":[5.0284900665,51.0672798157],"type":"Point"}
}