{
  "type": "Feature",
  "properties": {
    "addr:full":"Place De L'esro 63 Libin (redu) Luxembourg 6890",
    "addr:housenumber":"63",
    "addr:postcode":"6890",
    "addr:street":"Place De L'Esro",
    "iso:country":"BE",
    "sg:address":"Place De L'esro 63",
    "sg:city":"Libin (redu)",
    "sg:classifiers":[
        {
            "category":"Government",
            "subcategory":"Office",
            "type":"Public Place"
        }
    ],
    "sg:phone":"+32 61 65 65 16",
    "sg:postcode":"6890",
    "sg:province":"Luxembourg",
    "sg:tags":[
        "-",
        "tourism",
        "federation"
    ],
    "wof:name":"Office Du Tourisme",
    "wof:placetype":"venue"
},
  "geometry": {"coordinates":[5.1602888107,50.0076065063],"type":"Point"}
}