{
  "type": "Feature",
  "properties": {
    "iso:country":"BE",
    "sg:address":"Fort 1",
    "sg:city":"Asse",
    "sg:classifiers":[
        {
            "category":"Communications",
            "subcategory":"Film & Video Production",
            "type":"Services"
        }
    ],
    "sg:phone":"+32 2 453 16 32",
    "sg:postcode":"1730",
    "sg:province":"Vlaams-Brabant",
    "sg:tags":[
        "producer",
        "realizators"
    ],
    "wof:name":"Clerx J",
    "wof:placetype":"venue"
},
  "geometry": {"coordinates":[4.1964550018,50.9232559204],"type":"Point"}
}