{
  "type": "Feature",
  "properties": {
    "iso:country":"BE",
    "sg:address":"Korteweg 14",
    "sg:city":"Linter",
    "sg:orig_category":"Dranken",
    "sg:phone":"+32 11 78 05 31",
    "sg:postcode":"3350",
    "sg:province":"Vlaams-Brabant",
    "wof:name":"Wilfried Mattheus",
    "wof:placetype":"venue"
},
  "geometry": {"coordinates":[5.0565462112,50.8004951477],"type":"Point"}
}