{
  "type": "Feature",
  "properties": {
    "addr:full":"Beatrijslaan 1-9 Antwerpen Antwerpen 2050",
    "addr:housenumber":"1-9",
    "addr:postcode":"2050",
    "addr:street":"Beatrijslaan",
    "iso:country":"BE",
    "sg:address":"Beatrijslaan 1-9",
    "sg:city":"Antwerpen",
    "sg:classifiers":[
        {
            "category":"Personal",
            "type":"Services"
        }
    ],
    "sg:phone":"+32 3 219 32 91",
    "sg:postcode":"2050",
    "sg:province":"Antwerpen",
    "sg:tags":[
        "party",
        "planning"
    ],
    "wof:name":"Scheldezicht",
    "wof:placetype":"venue"
},
  "geometry": {"coordinates":[4.3873000145,51.2202301025],"type":"Point"}
}