{
  "type": "Feature",
  "properties": {
    "iso:country":"BE",
    "sg:address":"Neudorfer Strasse 76",
    "sg:city":"Raeren",
    "sg:classifiers":[
        {
            "category":"Bakery",
            "type":"Food & Drink"
        }
    ],
    "sg:phone":"+32 87 85 14 61",
    "sg:postcode":"4730",
    "sg:province":"Li\u00e8ge",
    "sg:tags":[
        "confectioner",
        "baker"
    ],
    "wof:name":"Rodtheut F",
    "wof:placetype":"venue"
},
  "geometry": {"coordinates":[6.1070017815,50.6679840088],"type":"Point"}
}