{
  "type": "Feature",
  "properties": {
    "addr:full":"Vent 1a Assenede (bassevelde) Oost-Vlaanderen 9968",
    "addr:housenumber":"1a",
    "addr:postcode":"9968",
    "addr:street":"Vent",
    "iso:country":"BE",
    "sg:address":"Vent 1a",
    "sg:city":"Assenede (bassevelde)",
    "sg:classifiers":[
        {
            "category":"Wholesale",
            "subcategory":"Medical Equipment & Supplies",
            "type":"Manufacturing & Wholesale Goods"
        }
    ],
    "sg:phone":"+32 9 373 82 82",
    "sg:postcode":"9968",
    "sg:province":"Oost-Vlaanderen",
    "sg:tags":[
        "instrument",
        "apparatus"
    ],
    "wof:name":"Jeecee International Nv",
    "wof:placetype":"venue"
},
  "geometry": {"coordinates":[3.6887938976,51.1923027039],"type":"Point"}
}