{
  "type": "Feature",
  "properties": {
    "iso:country":"BE",
    "sg:address":"Rue Du Sablon 129",
    "sg:city":"Bastenaken",
    "sg:orig_category":"Banken and kredietinstellingen",
    "sg:phone":"+32 61 21 40 31",
    "sg:postcode":"6600",
    "sg:province":"Luxembourg",
    "wof:name":"C.b.c. Banque Et Assurances",
    "wof:placetype":"venue"
},
  "geometry": {"coordinates":[5.7185339928,50.003326416],"type":"Point"}
}