{
  "type": "Feature",
  "properties": {
    "addr:full":"Koning Boudewijnstraat 226 Kuurne West-Vlaanderen 8520",
    "addr:housenumber":"226",
    "addr:postcode":"8520",
    "addr:street":"Koning Boudewijnstraat",
    "iso:country":"BE",
    "sg:address":"Koning Boudewijnstraat 226",
    "sg:city":"Kuurne",
    "sg:orig_category":"HUISBRANDOLIE",
    "sg:phone":"+32 56 70 12 42",
    "sg:postcode":"8520",
    "sg:province":"West-Vlaanderen",
    "wof:name":"Willy Van Audenaerde",
    "wof:placetype":"venue"
},
  "geometry": {"coordinates":[3.2773220539,50.8673744202],"type":"Point"}
}