{
  "type": "Feature",
  "properties": {
    "addr:full":"A. Rodenbachstraat 43b Box 1 Denderleeuw Oost-Vlaanderen 9470",
    "addr:housenumber":"43b;1",
    "addr:postcode":"9470",
    "addr:street":"A. Rodenbachstraat;Box",
    "iso:country":"BE",
    "sg:address":"A. Rodenbachstraat 43b Box 1",
    "sg:city":"Denderleeuw",
    "sg:classifiers":[
        {
            "category":"Professional",
            "subcategory":"Computer Services",
            "type":"Services"
        }
    ],
    "sg:phone":"+32 53 67 44 64",
    "sg:postcode":"9470",
    "sg:province":"Oost-Vlaanderen",
    "sg:tags":[
        "webdesign",
        "-",
        "internet"
    ],
    "wof:name":"Cq-lin Bvba",
    "wof:placetype":"venue"
},
  "geometry": {"coordinates":[4.0712399483,50.8943252563],"type":"Point"}
}