{
  "type": "Feature",
  "properties": {
    "addr:full":"Lijsterbeslaan 14 Gistel West-Vlaanderen 8470",
    "addr:housenumber":"14",
    "addr:postcode":"8470",
    "addr:street":"Lijsterbeslaan",
    "iso:country":"BE",
    "sg:address":"Lijsterbeslaan 14",
    "sg:city":"Gistel",
    "sg:orig_category":"Sportclubs",
    "sg:phone":"+32 59 27 96 64",
    "sg:postcode":"8470",
    "sg:province":"West-Vlaanderen",
    "wof:name":"Germinal",
    "wof:placetype":"venue"
},
  "geometry": {"coordinates":[2.9592659473,51.1587257385],"type":"Point"}
}