{
  "type": "Feature",
  "properties": {
    "iso:country":"BE",
    "sg:address":"Molenijzer 18",
    "sg:city":"Brugge",
    "sg:orig_category":"Sportclubs Sportterreinen and installaties behalve sportcentra",
    "sg:phone":"+32 50 39 06 81",
    "sg:postcode":"8200",
    "sg:province":"West-Vlaanderen",
    "wof:name":"P.s.v. Brugge",
    "wof:placetype":"venue"
},
  "geometry": {"coordinates":[3.1810400486,51.1874084473],"type":"Point"}
}