{
  "type": "Feature",
  "properties": {
    "addr:full":"Chauss\u00e9e De Louvain 585 Lasne (ohain) Brabant Wallon 1380",
    "addr:housenumber":"585",
    "addr:postcode":"1380",
    "addr:street":"Chausse\u0301E De Louvain;Wallon",
    "iso:country":"BE",
    "sg:address":"Chauss\u00e9e De Louvain 585",
    "sg:city":"Lasne (ohain)",
    "sg:classifiers":[
        {
            "category":"Communications",
            "type":"Services"
        }
    ],
    "sg:phone":"+32 2 644 03 65",
    "sg:postcode":"1380",
    "sg:province":"Brabant Wallon",
    "sg:tags":[
        "telecommunication"
    ],
    "wof:name":"Telli Telecom",
    "wof:placetype":"venue"
},
  "geometry": {"coordinates":[4.483235836,50.6850166321],"type":"Point"}
}