{
  "type": "Feature",
  "properties": {
    "addr:full":"Oosthinderstraat 37 Oostende West-Vlaanderen 8400",
    "addr:housenumber":"37",
    "addr:postcode":"8400",
    "addr:street":"Oosthinderstraat",
    "iso:country":"BE",
    "sg:address":"Oosthinderstraat 37",
    "sg:city":"Oostende",
    "sg:classifiers":[
        {
            "category":"Health Services",
            "subcategory":"Doctor",
            "type":"Services"
        }
    ],
    "sg:phone":"+32 59 51 50 78",
    "sg:postcode":"8400",
    "sg:province":"West-Vlaanderen",
    "sg:tags":[
        "medicinephysicians",
        "surgeon"
    ],
    "wof:name":"Depraetere M",
    "wof:placetype":"venue"
},
  "geometry": {"coordinates":[2.8950738907,51.2169761658],"type":"Point"}
}