{
  "type": "Feature",
  "properties": {
    "iso:country":"BE",
    "sg:address":"Sint-sebastiaanslaan 1",
    "sg:city":"Kortrijk",
    "sg:orig_category":"Boucheries",
    "sg:phone":"+32 56 22 64 84",
    "sg:postcode":"8500",
    "sg:province":"West-Vlaanderen",
    "wof:name":"Buurtslagers",
    "wof:placetype":"venue"
},
  "geometry": {"coordinates":[3.2607369423,50.8231163025],"type":"Point"}
}