{
  "type": "Feature",
  "properties": {
    "addr:full":"Asserweg 5 Zutendaal Limburg 3690",
    "addr:housenumber":"5",
    "addr:postcode":"3690",
    "addr:street":"Asserweg",
    "iso:country":"BE",
    "sg:address":"Asserweg 5",
    "sg:city":"Zutendaal",
    "sg:classifiers":[
        {
            "category":"Food & Beverages",
            "subcategory":"Groceries & Convenience Stores",
            "type":"Retail Goods"
        }
    ],
    "sg:phone":"+32 89 61 16 61",
    "sg:postcode":"3690",
    "sg:province":"Limburg",
    "sg:tags":[
        "grocer"
    ],
    "wof:name":"Full-service Europe",
    "wof:placetype":"venue"
},
  "geometry": {"coordinates":[5.5596208572,50.9532356262],"type":"Point"}
}