{
  "type": "Feature",
  "properties": {
    "addr:full":"Dorp 26 Lennik (sint-martens-lennik) Vlaams-Brabant 1750",
    "addr:housenumber":"26",
    "addr:postcode":"1750",
    "addr:street":"Dorp",
    "iso:country":"BE",
    "sg:address":"Dorp 26",
    "sg:city":"Lennik (sint-martens-lennik)",
    "sg:classifiers":[
        {
            "category":"Wholesale",
            "subcategory":"Beer",
            "type":"Manufacturing & Wholesale Goods"
        }
    ],
    "sg:phone":"+32 2 532 45 63",
    "sg:postcode":"1750",
    "sg:province":"Vlaams-Brabant",
    "sg:tags":[
        "ale",
        "-"
    ],
    "wof:name":"Heymans-drinks Bvba",
    "wof:placetype":"venue"
},
  "geometry": {"coordinates":[4.1680998802,50.8118553162],"type":"Point"}
}