{
  "type": "Feature",
  "properties": {
    "iso:country":"BE",
    "sg:address":"Chemin De Sartiau 8",
    "sg:city":"Ath",
    "sg:orig_category":"Landbouwmachines Gh",
    "sg:phone":"+32 68 64 50 35",
    "sg:postcode":"7804",
    "sg:province":"Hainaut",
    "wof:name":"Lizon Et Fils",
    "wof:placetype":"venue"
},
  "geometry": {"coordinates":[3.7832849026,50.6607551575],"type":"Point"}
}