{
  "type": "Feature",
  "properties": {
    "addr:full":"Rue Deveux 23-25 Li\u00e8ge 1 (li\u00e8ge 2) Li\u00e8ge 4020",
    "addr:housenumber":"2",
    "addr:postcode":"23-25;4020",
    "addr:street":"Rue Deveux;Lie\u0300Ge",
    "iso:country":"BE",
    "sg:address":"Rue Deveux 23-25",
    "sg:city":"Li\u00e8ge 1 (li\u00e8ge 2)",
    "sg:classifiers":[
        {
            "category":"Building & Trades",
            "subcategory":"Construction",
            "type":"Services"
        }
    ],
    "sg:phone":"+32 4 343 97 60",
    "sg:postcode":"4020",
    "sg:province":"Li\u00e8ge",
    "sg:tags":[
        "carpenter"
    ],
    "wof:name":"Schneider F",
    "wof:placetype":"venue"
},
  "geometry": {"coordinates":[5.5830130577,50.6354026794],"type":"Point"}
}