{
  "type": "Feature",
  "properties": {
    "addr:full":"Rue Bonnier Du Ch\u00c8ne 34 Herstal Li\u00e8ge 4041",
    "addr:housenumber":"34",
    "addr:postcode":"4041",
    "addr:street":"Rue Bonnier Du Che\u0300Ne",
    "iso:country":"BE",
    "sg:address":"Rue Bonnier Du Ch\u00c8ne 34",
    "sg:city":"Herstal",
    "sg:orig_category":"Charpentes and couvertures. Quincailleries. R\u00e9parations \u00e0 domicile d'articles divers. Plomberie, cha",
    "sg:phone":"+32 4 227 53 53",
    "sg:postcode":"4041",
    "sg:province":"Li\u00e8ge",
    "wof:name":"Ets. Drion",
    "wof:placetype":"venue"
},
  "geometry": {"coordinates":[5.5849199295,50.6724891663],"type":"Point"}
}