{
  "type": "Feature",
  "properties": {
    "iso:country":"BE",
    "sg:address":"Rue De La Plage 0",
    "sg:city":"Yvoir",
    "sg:orig_category":"Kampeerterreinen",
    "sg:phone":"+32 82 61 12 31",
    "sg:postcode":"5530",
    "sg:province":"Namur",
    "wof:name":"Camping Les Tilleuls",
    "wof:placetype":"venue"
},
  "geometry": {"coordinates":[4.8581309319,50.3493461609],"type":"Point"}
}