{
  "type": "Feature",
  "properties": {
    "addr:full":"Hoogstraatsesteenweg 20 Rijkevorsel Antwerpen 2310",
    "addr:housenumber":"20",
    "addr:postcode":"2310",
    "addr:street":"Hoogstraatsesteenweg",
    "iso:country":"BE",
    "sg:address":"Hoogstraatsesteenweg 20",
    "sg:city":"Rijkevorsel",
    "sg:classifiers":[
        {
            "category":"Restaurant",
            "type":"Food & Drink"
        }
    ],
    "sg:phone":"+32 3 314 13 58",
    "sg:postcode":"2310",
    "sg:province":"Antwerpen",
    "wof:name":"Footsteps",
    "wof:placetype":"venue"
},
  "geometry": {"coordinates":[4.7603502274,51.3514022827],"type":"Point"}
}