{
  "type": "Feature",
  "properties": {
    "iso:country":"BE",
    "sg:address":"Mechelsebaan 29",
    "sg:city":"Duffel",
    "sg:orig_category":"Meubles D\u00e9taillants, Am\u00e9nagement de B\u00e2timents et de Cuisines. Quincailleries. Bois Gr",
    "sg:phone":"+32 15 31 39 35",
    "sg:postcode":"2570",
    "sg:province":"Antwerpen",
    "wof:name":"Serulus",
    "wof:placetype":"venue"
},
  "geometry": {"coordinates":[4.5108180046,51.0896034241],"type":"Point"}
}