{
  "type": "Feature",
  "properties": {
    "addr:full":"Antwerpsesteenweg 547 Gent Oost-Vlaanderen 9040",
    "addr:housenumber":"547",
    "addr:postcode":"9040",
    "addr:street":"Antwerpsesteenweg;Oost-Vlaanderen",
    "iso:country":"BE",
    "sg:address":"Antwerpsesteenweg 547",
    "sg:city":"Gent",
    "sg:orig_category":"Caf\u00e9s. Salles de conf\u00e9rences and de r\u00e9ceptions",
    "sg:phone":"+32 9 228 27 61",
    "sg:postcode":"9040",
    "sg:province":"Oost-Vlaanderen",
    "wof:name":"'t Meuleken",
    "wof:placetype":"venue"
},
  "geometry": {"coordinates":[3.7611279488,51.0678977966],"type":"Point"}
}