{
  "type": "Feature",
  "properties": {
    "addr:full":"Rue Du Baty Des Monts 211 Andenne (vezin) Namur 5300",
    "addr:housenumber":"211",
    "addr:postcode":"5300",
    "addr:street":"Rue Du Baty Des Monts",
    "iso:country":"BE",
    "sg:address":"Rue Du Baty Des Monts 211",
    "sg:city":"Andenne (vezin)",
    "sg:classifiers":[
        {
            "category":"Retail",
            "subcategory":"Veterinary Services",
            "type":"Services"
        }
    ],
    "sg:phone":"+32 81 58 85 78",
    "sg:postcode":"5300",
    "sg:province":"Namur",
    "sg:tags":[
        "veterinarian"
    ],
    "wof:name":"Marlier D",
    "wof:placetype":"venue"
},
  "geometry": {"coordinates":[4.9818968773,50.5069694519],"type":"Point"}
}