{
  "type": "Feature",
  "properties": {
    "iso:country":"BE",
    "sg:address":"Chauss\u00e9e De Beaumont 348",
    "sg:city":"Mons (harmignies)",
    "sg:classifiers":[
        {
            "category":"Farming",
            "subcategory":"Livestock Farm",
            "type":"Manufacturing & Wholesale Goods"
        }
    ],
    "sg:phone":"+32 65 36 24 17",
    "sg:postcode":"7022",
    "sg:province":"Hainaut",
    "sg:tags":[
        "buyer"
    ],
    "wof:name":"Gobert J-c",
    "wof:placetype":"venue"
},
  "geometry": {"coordinates":[4.0181078911,50.4045410156],"type":"Point"}
}