{
  "type": "Feature",
  "properties": {
    "iso:country":"BE",
    "sg:address":"Leopold Ii Laan 44",
    "sg:city":"Sint-jans-molenbeek/molenbeek-saint-jean",
    "sg:orig_category":"Diverse organisaties and verenigingen",
    "sg:phone":"+32 2 413 29 30",
    "sg:postcode":"1080",
    "sg:province":"Bruxelles-Capitale",
    "wof:name":"C.j.e.f.",
    "wof:placetype":"venue"
},
  "geometry": {"coordinates":[4.3350548744,50.8619308472],"type":"Point"}
}