{
  "type": "Feature",
  "properties": {
    "iso:country":"BE",
    "sg:address":"Mandellaan 23",
    "sg:city":"Meulebeke",
    "sg:orig_category":"Magasins sp\u00e9cialis\u00e9s",
    "sg:phone":"+32 51 48 64 69",
    "sg:postcode":"8760",
    "sg:province":"West-Vlaanderen",
    "wof:name":"Nasimo",
    "wof:placetype":"venue"
},
  "geometry": {"coordinates":[3.2924919128,50.940246582],"type":"Point"}
}