{
  "type": "Feature",
  "properties": {
    "addr:full":"Avenue Paul De Merten 71 Bruxelles (jette) Bruxelles-Capitale 1090",
    "addr:housenumber":"71",
    "addr:postcode":"1090",
    "addr:street":"Avenue Paul De Merten",
    "iso:country":"BE",
    "sg:address":"Avenue Paul De Merten 71",
    "sg:city":"Bruxelles (jette)",
    "sg:classifiers":[
        {
            "category":"Building & Trades",
            "subcategory":"Construction",
            "type":"Services"
        }
    ],
    "sg:phone":"+32 2 524 00 33",
    "sg:postcode":"1090",
    "sg:province":"Bruxelles-Capitale",
    "sg:tags":[
        "installation",
        "-",
        "central",
        "heating"
    ],
    "wof:name":"Batissec",
    "wof:placetype":"venue"
},
  "geometry": {"coordinates":[4.3282442093,50.8713989258],"type":"Point"}
}