{
  "type": "Feature",
  "properties": {
    "iso:country":"BE",
    "sg:address":"Zeven Septemberlaan 13",
    "sg:city":"Hasselt",
    "sg:classifiers":[
        {
            "category":"Health Services",
            "subcategory":"Nursing And Care Facility",
            "type":"Services"
        }
    ],
    "sg:phone":"+32 11 30 87 00",
    "sg:postcode":"3500",
    "sg:province":"Limburg",
    "sg:tags":[
        "home",
        "rest"
    ],
    "wof:name":"Zonnestraal",
    "wof:placetype":"venue"
},
  "geometry": {"coordinates":[5.3460421562,50.9230422974],"type":"Point"}
}