{
  "type": "Feature",
  "properties": {
    "addr:full":"Chemin Martin 3 Saint-hubert Luxembourg 6870",
    "addr:housenumber":"3",
    "addr:postcode":"6870",
    "addr:street":"Chemin Martin",
    "iso:country":"BE",
    "sg:address":"Chemin Martin 3",
    "sg:city":"Saint-hubert",
    "sg:classifiers":[
        {
            "category":"Retail",
            "subcategory":"Auto Repair",
            "type":"Services"
        }
    ],
    "sg:phone":"+32 61 27 12 96",
    "sg:postcode":"6870",
    "sg:province":"Luxembourg",
    "sg:tags":[
        "automobile-body"
    ],
    "wof:name":"Laroche Olivier",
    "wof:placetype":"venue"
},
  "geometry": {"coordinates":[5.3674092293,50.0238037109],"type":"Point"}
}