{
  "type": "Feature",
  "properties": {
    "addr:full":"Rue De M\u00e9rode 51 Bruxelles (saint-gilles) Bruxelles-Capitale 1060",
    "addr:housenumber":"51",
    "addr:postcode":"1060",
    "addr:street":"Rue De Me\u0301Rode",
    "iso:country":"BE",
    "sg:address":"Rue De M\u00e9rode 51",
    "sg:city":"Bruxelles (saint-gilles)",
    "sg:classifiers":[
        {
            "category":"Food & Beverages",
            "subcategory":"Groceries & Convenience Stores",
            "type":"Retail Goods"
        }
    ],
    "sg:phone":"+32 2 537 56 79",
    "sg:postcode":"1060",
    "sg:province":"Bruxelles-Capitale",
    "sg:tags":[
        "grocer"
    ],
    "wof:name":"Andr\u00e9 Shopwell",
    "wof:placetype":"venue"
},
  "geometry": {"coordinates":[4.3389787674,50.8352355957],"type":"Point"}
}