{
  "type": "Feature",
  "properties": {
    "addr:full":"Bosstraat 103 Wellen Limburg 3830",
    "addr:housenumber":"103",
    "addr:postcode":"3830",
    "addr:street":"Bosstraat",
    "iso:country":"BE",
    "sg:address":"Bosstraat 103",
    "sg:city":"Wellen",
    "sg:orig_category":"Fruitteelt",
    "sg:phone":"+32 11 37 69 48",
    "sg:postcode":"3830",
    "sg:province":"Limburg",
    "wof:name":"Danny America",
    "wof:placetype":"venue"
},
  "geometry": {"coordinates":[5.3371481895,50.8624954224],"type":"Point"}
}