{
  "type": "Feature",
  "properties": {
    "iso:country":"BE",
    "sg:address":"Chauss\u00c9e Brunehault 253",
    "sg:city":"Estinnes",
    "sg:orig_category":"HUISBRANDOLIE",
    "sg:phone":"+32 64 33 86 07",
    "sg:postcode":"7120",
    "sg:province":"Hainaut",
    "wof:name":"Hacardiaux",
    "wof:placetype":"venue"
},
  "geometry": {"coordinates":[4.0884218216,50.3938407898],"type":"Point"}
}