{
  "type": "Feature",
  "properties": {
    "iso:country":"BE",
    "sg:address":"K. Van De Woestijnestr. 1",
    "sg:city":"Aalst",
    "sg:orig_category":"Plaatsen van vloer- and muurbekleding",
    "sg:phone":"+32 53 70 27 85",
    "sg:postcode":"9300",
    "sg:province":"Oost-Vlaanderen",
    "wof:name":"Johan Van Neck",
    "wof:placetype":"venue"
},
  "geometry": {"coordinates":[4.0289168358,50.9349784851],"type":"Point"}
}