{
  "type": "Feature",
  "properties": {
    "iso:country":"BE",
    "sg:address":"Van Iseghemlaan 147b2",
    "sg:city":"Oostende",
    "sg:orig_category":"Ordinateurs and \u00e9quipement informatique. R\u00e9alisation de programmes and logiciels",
    "sg:phone":"+32 59 70 00 29",
    "sg:postcode":"8400",
    "sg:province":"West-Vlaanderen",
    "wof:name":"A.m.t.",
    "wof:placetype":"venue"
},
  "geometry": {"coordinates":[2.9105160236,51.228553772],"type":"Point"}
}