{
  "type": "Feature",
  "properties": {
    "addr:full":"Rue Des Bataves 17-21 Bruxelles (etterbeek) Bruxelles-Capitale 1040",
    "addr:housenumber":"17-21",
    "addr:postcode":"1040",
    "addr:street":"Rue Des Bataves",
    "iso:country":"BE",
    "sg:address":"Rue Des Bataves 17-21",
    "sg:city":"Bruxelles (etterbeek)",
    "sg:orig_category":"Autombile concessionaires",
    "sg:phone":"+32 2 743 21 11",
    "sg:postcode":"1040",
    "sg:province":"Bruxelles-Capitale",
    "wof:name":"D'ieteren Etterbeek",
    "wof:placetype":"venue"
},
  "geometry": {"coordinates":[4.4019532204,50.8372154236],"type":"Point"}
}