{
  "type": "Feature",
  "properties": {
    "addr:full":"Avenue Albert I 55 Huy Li\u00e8ge 4500",
    "addr:housenumber":"55",
    "addr:postcode":"4500",
    "addr:street":"Avenue Albert I",
    "iso:country":"BE",
    "sg:address":"Avenue Albert I 55",
    "sg:city":"Huy",
    "sg:classifiers":[
        {
            "category":"Retail",
            "subcategory":"Auto Repair",
            "type":"Services"
        }
    ],
    "sg:phone":"+32 85 21 15 49",
    "sg:postcode":"4500",
    "sg:province":"Li\u00e8ge",
    "sg:tags":[
        "automobile-body"
    ],
    "wof:name":"Walch P",
    "wof:placetype":"venue"
},
  "geometry": {"coordinates":[5.234331131,50.5250205994],"type":"Point"}
}