{
  "type": "Feature",
  "properties": {
    "addr:full":"Rue Du Be Paki 4 Herve Li\u00e8ge 4650",
    "addr:housenumber":"4",
    "addr:postcode":"4650",
    "addr:street":"Rue Du Be Paki",
    "iso:country":"BE",
    "sg:address":"Rue Du Be Paki 4",
    "sg:city":"Herve",
    "sg:classifiers":[
        {
            "category":"Personal",
            "subcategory":"Beauty Salon",
            "type":"Services"
        }
    ],
    "sg:phone":"+32 87 67 43 85",
    "sg:postcode":"4650",
    "sg:province":"Li\u00e8ge",
    "sg:tags":[
        "de",
        "coiffure"
    ],
    "wof:name":"Coiffure Llorente",
    "wof:placetype":"venue"
},
  "geometry": {"coordinates":[5.8244371414,50.6425170898],"type":"Point"}
}