{
  "type": "Feature",
  "properties": {
    "addr:full":"Terlostraat 84 Gooik Vlaams-Brabant 1755",
    "addr:housenumber":"84",
    "addr:postcode":"1755",
    "addr:street":"Terlostraat",
    "iso:country":"BE",
    "sg:address":"Terlostraat 84",
    "sg:city":"Gooik",
    "sg:classifiers":[
        {
            "category":"Personal",
            "subcategory":"Beauty Salon",
            "type":"Services"
        }
    ],
    "sg:phone":"+32 54 56 63 04",
    "sg:postcode":"1755",
    "sg:province":"Vlaams-Brabant",
    "sg:tags":[
        "de",
        "coiffure"
    ],
    "wof:name":"Coiffure Irene",
    "wof:placetype":"venue"
},
  "geometry": {"coordinates":[4.0982551575,50.7906761169],"type":"Point"}
}