{
  "type": "Feature",
  "properties": {
    "addr:full":"Kapitein Commandant Vinckestraat 19 Wielsbeke West-Vlaanderen 8710",
    "addr:housenumber":"19",
    "addr:postcode":"8710",
    "addr:street":"Kapitein Commandant Vinckestraat;West-Vlaanderen",
    "iso:country":"BE",
    "sg:address":"Kapitein Commandant Vinckestraat 19",
    "sg:city":"Wielsbeke",
    "sg:orig_category":"Kapsalons",
    "sg:phone":"+32 56 66 32 06",
    "sg:postcode":"8710",
    "sg:province":"West-Vlaanderen",
    "wof:name":"Coiffure Youri",
    "wof:placetype":"venue"
},
  "geometry": {"coordinates":[3.3334209919,50.8923568726],"type":"Point"}
}