{
  "type": "Feature",
  "properties": {
    "iso:country":"BE",
    "sg:address":"Kampveld 32",
    "sg:city":"Sint-truiden",
    "sg:orig_category":"Woningbouw",
    "sg:phone":"+32 11 68 86 92",
    "sg:postcode":"3800",
    "sg:province":"Limburg",
    "wof:name":"Angelo Consentino",
    "wof:placetype":"venue"
},
  "geometry": {"coordinates":[5.2126970291,50.8280792236],"type":"Point"}
}