{
  "type": "Feature",
  "properties": {
    "iso:country":"BE",
    "sg:address":"Lommelsebaan 60",
    "sg:city":"Hechtel-eksel",
    "sg:orig_category":"Medische apparatuur, orthopedische artikelen and prothesen Fab",
    "sg:phone":"+32 11 73 52 73",
    "sg:postcode":"3940",
    "sg:province":"Limburg",
    "wof:name":"Vandenbussel Mia & Co",
    "wof:placetype":"venue"
},
  "geometry": {"coordinates":[5.364795208,51.1255340576],"type":"Point"}
}