{
  "type": "Feature",
  "properties": {
    "iso:country":"BE",
    "sg:address":"Vogelenzang 20",
    "sg:city":"Borsbeek",
    "sg:orig_category":"Woningbouw",
    "sg:phone":"+32 3 321 82 14",
    "sg:postcode":"2150",
    "sg:province":"Antwerpen",
    "wof:name":"Van Den Bosch",
    "wof:placetype":"venue"
},
  "geometry": {"coordinates":[4.496445179,51.1951522827],"type":"Point"}
}