{
  "type": "Feature",
  "properties": {
    "addr:full":"Rue De Neufch\u00c2teau 34 Bastogne Luxembourg 6600",
    "addr:housenumber":"34",
    "addr:postcode":"6600",
    "addr:street":"Rue De Neufcha\u0302Teau",
    "iso:country":"BE",
    "sg:address":"Rue De Neufch\u00c2teau 34",
    "sg:city":"Bastogne",
    "sg:orig_category":"Banken and kredietinstellingen",
    "sg:phone":"+32 61 21 07 10",
    "sg:postcode":"6600",
    "sg:province":"Luxembourg",
    "wof:name":"Bbl",
    "wof:placetype":"venue"
},
  "geometry": {"coordinates":[5.7132949829,49.999004364],"type":"Point"}
}