{
  "type": "Feature",
  "properties": {
    "iso:country":"BE",
    "sg:address":"Rue Des Vergiers 43",
    "sg:city":"Huy",
    "sg:orig_category":"M\u00e9decins and sp\u00e9cialistes",
    "sg:phone":"+32 85 23 14 96",
    "sg:postcode":"4500",
    "sg:province":"Li\u00e8ge",
    "wof:name":"Pierre Dehon",
    "wof:placetype":"venue"
},
  "geometry": {"coordinates":[5.2471938133,50.5287742615],"type":"Point"}
}