{
  "type": "Feature",
  "properties": {
    "iso:country":"BE",
    "sg:address":"Chauss\u00e9e D'alsemberg 737",
    "sg:city":"Bruxelles (uccle)",
    "sg:classifiers":[
        {
            "category":"Shopping",
            "subcategory":"Computers & Home Electronics",
            "type":"Retail Goods"
        }
    ],
    "sg:phone":"+32 2 344 88 22",
    "sg:postcode":"1180",
    "sg:province":"Bruxelles-Capitale",
    "sg:tags":[
        "-",
        "television",
        "radio"
    ],
    "wof:name":"Audio Video Pro",
    "wof:placetype":"venue"
},
  "geometry": {"coordinates":[4.3365440369,50.8041534424],"type":"Point"}
}