{
  "type": "Feature",
  "properties": {
    "addr:full":"Chauss\u00e9e De Bruxelles 347 Charleroi (dampremy) Hainaut 6020",
    "addr:housenumber":"347",
    "addr:postcode":"6020",
    "addr:street":"Chausse\u0301E De Bruxelles",
    "iso:country":"BE",
    "sg:address":"Chauss\u00e9e De Bruxelles 347",
    "sg:city":"Charleroi (dampremy)",
    "sg:classifiers":[
        {
            "category":"Personal",
            "subcategory":"Beauty Salon",
            "type":"Services"
        }
    ],
    "sg:phone":"+32 71 63 45 63",
    "sg:postcode":"6020",
    "sg:province":"Hainaut",
    "sg:tags":[
        "lady",
        "-",
        "hairdressing"
    ],
    "wof:name":"Tudela Nuniz H",
    "wof:placetype":"venue"
},
  "geometry": {"coordinates":[4.4401531219,50.422088623],"type":"Point"}
}