{
  "type": "Feature",
  "properties": {
    "addr:full":"Polberglei 12 Kapellen Antwerpen 2950",
    "addr:housenumber":"12",
    "addr:postcode":"2950",
    "addr:street":"Polberglei",
    "iso:country":"BE",
    "sg:address":"Polberglei 12",
    "sg:city":"Kapellen",
    "sg:classifiers":[
        {
            "category":"Wholesale",
            "subcategory":"Vending Machines",
            "type":"Manufacturing & Wholesale Goods"
        }
    ],
    "sg:phone":"+32 3 666 64 58",
    "sg:postcode":"2950",
    "sg:province":"Antwerpen",
    "sg:tags":[
        "crushing",
        "installation"
    ],
    "wof:name":"Shec Bvba",
    "wof:placetype":"venue"
},
  "geometry": {"coordinates":[4.4662680626,51.3503990173],"type":"Point"}
}