{
  "type": "Feature",
  "properties": {
    "addr:full":"Oude Baan 26-28 Maasmechelen (eisden) Limburg 3630",
    "addr:housenumber":"26-28",
    "addr:postcode":"3630",
    "addr:street":"Oude Baan",
    "iso:country":"BE",
    "sg:address":"Oude Baan 26-28",
    "sg:city":"Maasmechelen (eisden)",
    "sg:classifiers":[
        {
            "category":"Shopping",
            "subcategory":"Clothing, Apparel, & Fashions",
            "type":"Retail Goods"
        }
    ],
    "sg:phone":"+32 89 76 42 75",
    "sg:postcode":"3630",
    "sg:province":"Limburg",
    "sg:tags":[
        "lady",
        "clothing",
        "-"
    ],
    "wof:name":"Jostex",
    "wof:placetype":"venue"
},
  "geometry": {"coordinates":[5.6941361427,50.9876365662],"type":"Point"}
}