{
  "type": "Feature",
  "properties": {
    "addr:full":"Grand Place 36 Paliseul Luxembourg 6850",
    "addr:housenumber":"36",
    "addr:postcode":"6850",
    "addr:street":"Grand Place",
    "iso:country":"BE",
    "sg:address":"Grand Place 36",
    "sg:city":"Paliseul",
    "sg:classifiers":[
        {
            "category":"Professional",
            "subcategory":"Testing Lab",
            "type":"Services"
        }
    ],
    "sg:phone":"+32 61 53 33 91",
    "sg:postcode":"6850",
    "sg:province":"Luxembourg",
    "sg:tags":[
        "laboratory",
        "photographic",
        "film"
    ],
    "wof:name":"Burnonville Sa",
    "wof:placetype":"venue"
},
  "geometry": {"coordinates":[5.1350898743,49.9034004211],"type":"Point"}
}