{
  "type": "Feature",
  "properties": {
    "addr:full":"Hendrikaplein 5 Nieuwpoort West-Vlaanderen 8620",
    "addr:housenumber":"5",
    "addr:postcode":"8620",
    "addr:street":"Hendrikaplein",
    "iso:country":"BE",
    "sg:address":"Hendrikaplein 5",
    "sg:city":"Nieuwpoort",
    "sg:classifiers":[
        {
            "category":"Shopping",
            "subcategory":"Clothing, Apparel, & Fashions",
            "type":"Retail Goods"
        }
    ],
    "sg:phone":"+32 58 23 22 48",
    "sg:postcode":"8620",
    "sg:province":"West-Vlaanderen",
    "sg:tags":[
        "-",
        "clothing",
        "child"
    ],
    "wof:name":"Pum & Pum",
    "wof:placetype":"venue"
},
  "geometry": {"coordinates":[2.7205760479,51.1507759094],"type":"Point"}
}