{
  "type": "Feature",
  "properties": {
    "iso:country":"BE",
    "sg:address":"Klapeksterstraat 1bc",
    "sg:city":"Gent",
    "sg:orig_category":"Architecten",
    "sg:phone":"+32 9 236 26 80",
    "sg:postcode":"9000",
    "sg:province":"Oost-Vlaanderen",
    "wof:name":"Jan Mannaerts",
    "wof:placetype":"venue"
},
  "geometry": {"coordinates":[3.7018399239,51.0611457825],"type":"Point"}
}