{
  "type": "Feature",
  "properties": {
    "iso:country":"BE",
    "sg:address":"Place Cdt. De Block 19",
    "sg:city":"Wemmel",
    "sg:orig_category":"Epiceries",
    "sg:phone":"+32 2 460 52 42",
    "sg:postcode":"1780",
    "sg:province":"Vlaams-Brabant",
    "wof:name":"Van Langenhove - Huygens",
    "wof:placetype":"venue"
},
  "geometry": {"coordinates":[4.3122148514,50.8995819092],"type":"Point"}
}