{
  "type": "Feature",
  "properties": {
    "addr:full":"Muizendijkstraat 8 Bree Limburg 3960",
    "addr:housenumber":"8",
    "addr:postcode":"3960",
    "addr:street":"Muizendijkstraat",
    "iso:country":"BE",
    "sg:address":"Muizendijkstraat 8",
    "sg:city":"Bree",
    "sg:orig_category":"Eleveurs de bovins",
    "sg:phone":"+32 89 46 21 81",
    "sg:postcode":"3960",
    "sg:province":"Limburg",
    "wof:name":"Vrinssen A. & Math. & S.",
    "wof:placetype":"venue"
},
  "geometry": {"coordinates":[5.5902891159,51.1123924255],"type":"Point"}
}