{
  "type": "Feature",
  "properties": {
    "iso:country":"BE",
    "sg:address":"Hoogstraat 27",
    "sg:city":"Puurs",
    "sg:orig_category":"Meubles D\u00e9taillants, Am\u00e9nagement de B\u00e2timents et de Cuisines",
    "sg:phone":"+32 3 889 00 89",
    "sg:postcode":"2870",
    "sg:province":"Antwerpen",
    "wof:name":"Retro Meubel",
    "wof:placetype":"venue"
},
  "geometry": {"coordinates":[4.2773070335,51.0764579773],"type":"Point"}
}