{
  "type": "Feature",
  "properties": {
    "iso:country":"BE",
    "sg:address":"Bd Industriel 92",
    "sg:city":"Mouscron",
    "sg:classifiers":[
        {
            "category":"Manufacturing",
            "subcategory":"Metals",
            "type":"Manufacturing & Wholesale Goods"
        }
    ],
    "sg:phone":"+32 56 33 01 57",
    "sg:postcode":"7700",
    "sg:province":"Hainaut",
    "sg:tags":[
        "metallurgy",
        "metalworking",
        "processing"
    ],
    "wof:name":"Jackson Sa",
    "wof:placetype":"venue"
},
  "geometry": {"coordinates":[3.245413065,50.748260498],"type":"Point"}
}