{
  "type": "Feature",
  "properties": {
    "addr:full":"Route Nationale 4 23 Nassogne (bande) Luxembourg 6951",
    "addr:housenumber":"23",
    "addr:postcode":"6951",
    "addr:street":"Route Nationale 4",
    "iso:country":"BE",
    "sg:address":"Route Nationale 4 23",
    "sg:city":"Nassogne (bande)",
    "sg:classifiers":[
        {
            "category":"Airport",
            "subcategory":"International",
            "type":"Transportation"
        }
    ],
    "sg:phone":"+32 84 34 46 39",
    "sg:postcode":"6951",
    "sg:province":"Luxembourg",
    "sg:tags":[
        "-",
        "transport"
    ],
    "wof:name":"Compagnie De Distribution Sa",
    "wof:placetype":"venue"
},
  "geometry": {"coordinates":[5.4134459496,50.1566886902],"type":"Point"}
}