{
  "type": "Feature",
  "properties": {
    "iso:country":"BE",
    "sg:address":"Heide 32a",
    "sg:city":"Berlare",
    "sg:classifiers":[
        {
            "category":"Sports & Exercise",
            "subcategory":"Gym",
            "type":"Entertainment"
        }
    ],
    "sg:phone":"+32 52 42 47 73",
    "sg:postcode":"9290",
    "sg:province":"Oost-Vlaanderen",
    "sg:tags":[
        "access",
        "gymnastics",
        "-",
        "apparatus",
        "fitness"
    ],
    "wof:name":"Fietspaleis Nv",
    "wof:placetype":"venue"
},
  "geometry": {"coordinates":[4.010281086,51.0201377869],"type":"Point"}
}