{
  "type": "Feature",
  "properties": {
    "iso:country":"BE",
    "sg:address":"Rue Belle-vue 12",
    "sg:city":"Tubize",
    "sg:orig_category":"Beveiligingsdiensten and bewakingsbedrijven",
    "sg:phone":"+32 2 355 45 63",
    "sg:postcode":"1480",
    "sg:province":"Brabant Wallon",
    "wof:name":"Delbauve Jean Bernard",
    "wof:placetype":"venue"
},
  "geometry": {"coordinates":[4.1905660629,50.6940917969],"type":"Point"}
}