{
  "type": "Feature",
  "properties": {
    "addr:full":"Albertlaan 80 Ninove Oost-Vlaanderen 9400",
    "addr:housenumber":"80",
    "addr:postcode":"9400",
    "addr:street":"Albertlaan",
    "iso:country":"BE",
    "sg:address":"Albertlaan 80",
    "sg:city":"Ninove",
    "sg:classifiers":[
        {
            "category":"Restaurant",
            "type":"Food & Drink"
        }
    ],
    "sg:phone":"+32 54 31 16 93",
    "sg:postcode":"9400",
    "sg:province":"Oost-Vlaanderen",
    "wof:name":"Lunch Garden",
    "wof:placetype":"venue"
},
  "geometry": {"coordinates":[4.0100579262,50.8380508423],"type":"Point"}
}