{
  "type": "Feature",
  "properties": {
    "iso:country":"BE",
    "sg:address":"Rue Grande 60",
    "sg:city":"Qui\u00e9vrain",
    "sg:classifiers":[
        {
            "category":"Shopping",
            "subcategory":"Clothing, Apparel, & Fashions",
            "type":"Retail Goods"
        }
    ],
    "sg:phone":"+32 65 45 71 85",
    "sg:postcode":"7380",
    "sg:province":"Hainaut",
    "sg:tags":[
        "lady",
        "clothing",
        "-"
    ],
    "wof:name":"Boulvin Martine (boutique)",
    "wof:placetype":"venue"
},
  "geometry": {"coordinates":[3.6830079556,50.4054336548],"type":"Point"}
}