{
  "type": "Feature",
  "properties": {
    "addr:full":"Houthulstseweg 75ba Langemark-poelkapelle West-Vlaanderen 8920",
    "addr:housenumber":"75ba",
    "addr:postcode":"8920",
    "addr:street":"Houthulstseweg",
    "iso:country":"BE",
    "sg:address":"Houthulstseweg 75ba",
    "sg:city":"Langemark-poelkapelle",
    "sg:orig_category":"Architectes",
    "sg:phone":"+32 57 48 84 69",
    "sg:postcode":"8920",
    "sg:province":"West-Vlaanderen",
    "wof:name":"Alex Moenaert",
    "wof:placetype":"venue"
},
  "geometry": {"coordinates":[2.9419920444,50.9352264404],"type":"Point"}
}