{
  "type": "Feature",
  "properties": {
    "iso:country":"BE",
    "sg:address":"Franz Courtensstraat 12",
    "sg:city":"Dendermonde",
    "sg:orig_category":"Openbare veiligheid",
    "sg:phone":"+32 52 22 08 80",
    "sg:postcode":"9200",
    "sg:province":"Oost-Vlaanderen",
    "wof:name":"Federale Politie",
    "wof:placetype":"venue"
},
  "geometry": {"coordinates":[4.1002187729,51.0321617126],"type":"Point"}
}