{
  "type": "Feature",
  "properties": {
    "addr:full":"Rue Gr\u00c9goire 4 Charleroi Hainaut 6040",
    "addr:housenumber":"4",
    "addr:postcode":"6040",
    "addr:street":"Rue Gre\u0301Goire;Hainaut",
    "iso:country":"BE",
    "sg:address":"Rue Gr\u00c9goire 4",
    "sg:city":"Charleroi",
    "sg:orig_category":"Entretien and r\u00e9parations de voitures",
    "sg:phone":"+32 71 34 07 65",
    "sg:postcode":"6040",
    "sg:province":"Hainaut",
    "wof:name":"Carrosserie Mauro",
    "wof:placetype":"venue"
},
  "geometry": {"coordinates":[4.4091739655,50.4351959229],"type":"Point"}
}