{
  "type": "Feature",
  "properties": {
    "addr:full":"Koning Albertstraat 22 Hasselt Limburg 3500",
    "addr:housenumber":"22",
    "addr:postcode":"3500",
    "addr:street":"Koning Albertstraat",
    "iso:country":"BE",
    "sg:address":"Koning Albertstraat 22",
    "sg:city":"Hasselt",
    "sg:classifiers":[
        {
            "category":"Shopping",
            "subcategory":"Clothing, Apparel, & Fashions",
            "type":"Retail Goods"
        }
    ],
    "sg:phone":"+32 11 22 10 30",
    "sg:postcode":"3500",
    "sg:province":"Limburg",
    "sg:tags":[
        "ondergoed",
        "lingerie"
    ],
    "wof:name":"Lingerie An",
    "wof:placetype":"venue"
},
  "geometry": {"coordinates":[5.3372488022,50.9287643433],"type":"Point"}
}