{
  "type": "Feature",
  "properties": {
    "iso:country":"BE",
    "sg:address":"Rue De Hal 35",
    "sg:city":"Braine-le-ch\u00e2teau",
    "sg:classifiers":[
        {
            "category":"Professional",
            "subcategory":"Art Services",
            "type":"Services"
        }
    ],
    "sg:phone":"+32 2 366 93 04",
    "sg:postcode":"1440",
    "sg:province":"Brabant Wallon",
    "sg:tags":[
        "photographer"
    ],
    "wof:name":"Roucourt B",
    "wof:placetype":"venue"
},
  "geometry": {"coordinates":[4.2693610191,50.6913566589],"type":"Point"}
}