{
  "type": "Feature",
  "properties": {
    "iso:country":"BE",
    "sg:address":"Sq A Masson 1",
    "sg:city":"Namur",
    "sg:classifiers":[
        {
            "category":"Banks & Credit Unions",
            "subcategory":"Bank",
            "type":"Services"
        }
    ],
    "sg:postcode":"5000",
    "sg:province":"Namur",
    "wof:name":"Fastnet Belgium",
    "wof:placetype":"venue"
},
  "geometry": {"coordinates":[5.7148098946,50.0007781982],"type":"Point"}
}