{
  "type": "Feature",
  "properties": {
    "addr:full":"116 Rue De Marche 6600 Bastogne 116",
    "addr:housenumber":"116;116",
    "addr:postcode":"6600",
    "addr:street":"Rue De Marche",
    "iso:country":"BE",
    "sg:address":"116",
    "sg:city":"Rue De Marche 6600 Bastogne",
    "sg:classifiers":[
        {
            "category":"Manufacturing",
            "subcategory":"Tools & Machinery",
            "type":"Manufacturing & Wholesale Goods"
        }
    ],
    "sg:phone":"+32 61 21 48 41",
    "sg:postcode":"116",
    "sg:tags":[
        "metallurgy",
        "metalworking"
    ],
    "wof:name":"Interbrico Sa",
    "wof:placetype":"venue"
},
  "geometry": {"coordinates":[5.6969451904,50.0022964478],"type":"Point"}
}