{
  "type": "Feature",
  "properties": {
    "iso:country":"BE",
    "sg:address":"Durmakker 51",
    "sg:city":"Evergem",
    "sg:orig_category":"IJzerwaren, bouw- and verfmaterialen Installatie van houten of kunststof schrijnwerk MEUBELONTWERP A",
    "sg:phone":"+32 9 253 50 66",
    "sg:postcode":"9940",
    "sg:province":"Oost-Vlaanderen",
    "wof:name":"Interbudget Construct",
    "wof:placetype":"venue"
},
  "geometry": {"coordinates":[3.6782770157,51.0945320129],"type":"Point"}
}