{
  "type": "Feature",
  "properties": {
    "iso:country":"BE",
    "sg:address":"Rue Des Faubourgs 40",
    "sg:city":"Arlon",
    "sg:classifiers":[
        {
            "category":"Cafe",
            "type":"Food & Drink"
        }
    ],
    "sg:phone":"+32 63 21 92 31",
    "sg:postcode":"6700",
    "sg:province":"Luxembourg",
    "sg:tags":[
        "caf\u00e9s"
    ],
    "wof:name":"Caf\u00c9 Le Zenith",
    "wof:placetype":"venue"
},
  "geometry": {"coordinates":[5.8106541634,49.6846656799],"type":"Point"}
}