{
  "type": "Feature",
  "properties": {
    "iso:country":"BE",
    "sg:address":"Nationalestraat 108",
    "sg:city":"Antwerpen",
    "sg:orig_category":"Imprimeries and copyshops",
    "sg:phone":"+32 3 232 16 97",
    "sg:postcode":"2000",
    "sg:province":"Antwerpen",
    "wof:name":"Koppie Kopie",
    "wof:placetype":"venue"
},
  "geometry": {"coordinates":[4.3980650902,51.2143440247],"type":"Point"}
}