{
  "type": "Feature",
  "properties": {
    "iso:country":"BE",
    "sg:address":"Brechtsebaan 28",
    "sg:city":"Schoten",
    "sg:classifiers":[
        {
            "category":"Home & Garden",
            "subcategory":"Home Furnishings",
            "type":"Retail Goods"
        }
    ],
    "sg:phone":"+32 3 685 39 82",
    "sg:postcode":"2900",
    "sg:province":"Antwerpen",
    "sg:tags":[
        "-",
        "furniture"
    ],
    "wof:name":"International Buyers Group Nv",
    "wof:placetype":"venue"
},
  "geometry": {"coordinates":[4.5110669136,51.265296936],"type":"Point"}
}