{
  "type": "Feature",
  "properties": {
    "addr:full":"Grand Route 289a Drogenbos Vlaams-Brabant 1620",
    "addr:postcode":"1620",
    "addr:street":"Grand Route 289A",
    "iso:country":"BE",
    "sg:address":"Grand Route 289a",
    "sg:city":"Drogenbos",
    "sg:classifiers":[
        {
            "category":"Shopping",
            "subcategory":"Florist",
            "type":"Retail Goods"
        }
    ],
    "sg:phone":"+32 2 377 56 65",
    "sg:postcode":"1620",
    "sg:province":"Vlaams-Brabant",
    "wof:name":"Anemone",
    "wof:placetype":"venue"
},
  "geometry": {"coordinates":[4.3176279068,50.7869567871],"type":"Point"}
}