{
  "type": "Feature",
  "properties": {
    "iso:country":"BE",
    "sg:address":"Zoning Industriel 1\u00e8re Rue",
    "sg:city":"Charleroi (jumet)",
    "sg:classifiers":[
        {
            "category":"Wholesale",
            "subcategory":"Construction Materials",
            "type":"Manufacturing & Wholesale Goods"
        }
    ],
    "sg:phone":"+32 71 34 54 18",
    "sg:postcode":"6040",
    "sg:province":"Hainaut",
    "sg:tags":[
        "tubing",
        "industrial"
    ],
    "wof:name":"Sertip Sa",
    "wof:placetype":"venue"
},
  "geometry": {"coordinates":[4.4549150467,50.4562835693],"type":"Point"}
}