{
  "type": "Feature",
  "properties": {
    "addr:full":"Paardenmarkt 31 Antwerpen Antwerpen 2000",
    "addr:housenumber":"31",
    "addr:postcode":"2000",
    "addr:street":"Paardenmarkt",
    "iso:country":"BE",
    "sg:address":"Paardenmarkt 31",
    "sg:city":"Antwerpen",
    "sg:classifiers":[
        {
            "category":"Building & Trades",
            "subcategory":"Pest Control",
            "type":"Services"
        }
    ],
    "sg:phone":"+32 3 226 00 83",
    "sg:postcode":"2000",
    "sg:province":"Antwerpen",
    "sg:tags":[
        "machine",
        "vending"
    ],
    "wof:name":"Van Rickstal-jerotka",
    "wof:placetype":"venue"
},
  "geometry": {"coordinates":[4.4085621834,51.2251968384],"type":"Point"}
}