{
  "type": "Feature",
  "properties": {
    "addr:full":"Hoogpoort 27 Gent Oost-Vlaanderen 9000",
    "addr:housenumber":"27",
    "addr:postcode":"9000",
    "addr:street":"Hoogpoort;Oost-Vlaanderen",
    "iso:country":"BE",
    "sg:address":"Hoogpoort 27",
    "sg:city":"Gent",
    "sg:orig_category":"Artsen and specialisten",
    "sg:phone":"+32 9 223 30 80",
    "sg:postcode":"9000",
    "sg:province":"Oost-Vlaanderen",
    "wof:name":"P. Symons",
    "wof:placetype":"venue"
},
  "geometry": {"coordinates":[3.7237789631,51.0553703308],"type":"Point"}
}