{
  "type": "Feature",
  "properties": {
    "iso:country":"BE",
    "sg:address":"Tremelobaan 204",
    "sg:city":"Keerbergen",
    "sg:classifiers":[
        {
            "category":"Professional",
            "subcategory":"Accounting & Tax Preparation",
            "type":"Services"
        }
    ],
    "sg:phone":"+32 16 53 33 41",
    "sg:postcode":"3140",
    "sg:province":"Vlaams-Brabant",
    "sg:tags":[
        "bookkeeper"
    ],
    "wof:name":"Artois S",
    "wof:placetype":"venue"
},
  "geometry": {"coordinates":[4.6854081154,50.9947013855],"type":"Point"}
}