{
  "type": "Feature",
  "properties": {
    "addr:full":"H. Deweertkaai 1y Oostende West-Vlaanderen 8400",
    "addr:postcode":"8400",
    "iso:country":"BE",
    "sg:address":"H. Deweertkaai 1y",
    "sg:city":"Oostende",
    "sg:orig_category":"Salles de conf\u00e9rences and de r\u00e9ceptions",
    "sg:phone":"+32 59 33 21 16",
    "sg:postcode":"8400",
    "sg:province":"West-Vlaanderen",
    "wof:name":"Cultuurschip Imke-c",
    "wof:placetype":"venue"
},
  "geometry": {"coordinates":[2.943089962,51.2195358276],"type":"Point"}
}