{
  "type": "Feature",
  "properties": {
    "iso:country":"BE",
    "sg:address":"Rue Mattot 86",
    "sg:city":"Waterloo",
    "sg:classifiers":[
        {
            "category":"Arena",
            "subcategory":"Sports Club",
            "type":"Entertainment"
        }
    ],
    "sg:phone":"+32 2 354 92 81",
    "sg:postcode":"1400",
    "sg:province":"Brabant Wallon",
    "sg:tags":[
        "de"
    ],
    "wof:name":"Archers Du Grand Serment De Saint-s\u00c9bastien",
    "wof:placetype":"venue"
},
  "geometry": {"coordinates":[-88.0607299805,34.9151916504],"type":"Point"}
}