{
  "type": "Feature",
  "properties": {
    "iso:country":"BE",
    "sg:address":"Pilkemseweg 23",
    "sg:city":"Ieper",
    "sg:classifiers":[
        {
            "category":"Freight",
            "type":"Transportation"
        }
    ],
    "sg:phone":"+32 57 20 08 01",
    "sg:postcode":"8900",
    "sg:province":"West-Vlaanderen",
    "sg:tags":[
        "-",
        "transport"
    ],
    "wof:name":"Maxitax Bvba",
    "wof:placetype":"venue"
},
  "geometry": {"coordinates":[2.8923740387,50.8621902466],"type":"Point"}
}