{
  "type": "Feature",
  "properties": {
    "addr:full":"Dokter Bruwierlaan 63 Ichtegem West-Vlaanderen 8480",
    "addr:housenumber":"63",
    "addr:postcode":"8480",
    "addr:street":"Dokter Bruwierlaan",
    "iso:country":"BE",
    "sg:address":"Dokter Bruwierlaan 63",
    "sg:city":"Ichtegem",
    "sg:classifiers":[
        {
            "category":"Arena",
            "subcategory":"Sports Club",
            "type":"Entertainment"
        }
    ],
    "sg:phone":"+32 51 58 18 43",
    "sg:postcode":"8480",
    "sg:province":"West-Vlaanderen",
    "sg:tags":[
        "terrain",
        "hors",
        "de",
        "installation",
        "sportifs"
    ],
    "wof:name":"V.c. Ichtegem",
    "wof:placetype":"venue"
},
  "geometry": {"coordinates":[3.0154900551,51.0928192139],"type":"Point"}
}