{
  "type": "Feature",
  "properties": {
    "addr:full":"Deinzesteenweg 177 Kruishoutem Oost-Vlaanderen 9770",
    "addr:housenumber":"177",
    "addr:postcode":"9770",
    "addr:street":"Deinzesteenweg",
    "iso:country":"BE",
    "sg:address":"Deinzesteenweg 177",
    "sg:city":"Kruishoutem",
    "sg:orig_category":"Gespecialiseerde residenti\u00eble bouw Huishoudapparaten, televisies and radio's",
    "sg:phone":"+32 9 386 12 21",
    "sg:postcode":"9770",
    "sg:province":"Oost-Vlaanderen",
    "wof:name":"De Baere Elektro",
    "wof:placetype":"venue"
},
  "geometry": {"coordinates":[3.5372760296,50.9326820374],"type":"Point"}
}