{
  "type": "Feature",
  "properties": {
    "addr:full":"Chauss\u00e9e De Roly 5 Couvin (mariembourg) Namur 5660",
    "addr:housenumber":"5",
    "addr:postcode":"5660",
    "addr:street":"Chausse\u0301E De Roly",
    "iso:country":"BE",
    "sg:address":"Chauss\u00e9e De Roly 5",
    "sg:city":"Couvin (mariembourg)",
    "sg:classifiers":[
        {
            "category":"Education",
            "subcategory":"School",
            "type":"Public Place"
        }
    ],
    "sg:phone":"+32 60 31 15 62",
    "sg:postcode":"5660",
    "sg:province":"Namur",
    "sg:tags":[
        "primary"
    ],
    "wof:name":"Enseignement Sp\u00e9cial De La Communaut\u00e9 Fran\u00e7aise",
    "wof:placetype":"venue"
},
  "geometry": {"coordinates":[4.5289649963,50.1092605591],"type":"Point"}
}