{
  "type": "Feature",
  "properties": {
    "addr:full":"Sint-amandstraat 13 Tielt West-Vlaanderen 8700",
    "addr:housenumber":"13",
    "addr:postcode":"8700",
    "addr:street":"Sint-Amandstraat",
    "iso:country":"BE",
    "sg:address":"Sint-amandstraat 13",
    "sg:city":"Tielt",
    "sg:classifiers":[
        {
            "category":"Farming",
            "subcategory":"Farm & Veterinary Services",
            "type":"Manufacturing & Wholesale Goods"
        }
    ],
    "sg:phone":"+32 51 40 05 87",
    "sg:postcode":"8700",
    "sg:province":"West-Vlaanderen",
    "sg:tags":[
        "agricultural",
        "contractor"
    ],
    "wof:name":"Van Dorpe J",
    "wof:placetype":"venue"
},
  "geometry": {"coordinates":[3.332887888,50.9726982117],"type":"Point"}
}