{
  "type": "Feature",
  "properties": {
    "iso:country":"BE",
    "sg:address":"Leuvensestraat 44-48",
    "sg:city":"Aarschot (groot)",
    "sg:orig_category":"Banken and kredietinstellingen",
    "sg:phone":"+32 16 55 01 70",
    "sg:postcode":"3200",
    "sg:province":"Vlaams-Brabant",
    "wof:name":"Dexia",
    "wof:placetype":"venue"
},
  "geometry": {"coordinates":[4.8322401047,50.9837989807],"type":"Point"}
}