{
  "type": "Feature",
  "properties": {
    "addr:full":"Avenue De La Crois\u00e9e 6 Wavre Brabant Wallon 1300",
    "addr:housenumber":"6;1300",
    "addr:street":"Avenue De La Croise\u0301E",
    "iso:country":"BE",
    "sg:address":"Avenue De La Crois\u00e9e 6",
    "sg:city":"Wavre",
    "sg:classifiers":[
        {
            "category":"Banks & Credit Unions",
            "subcategory":"Financial Services",
            "type":"Services"
        }
    ],
    "sg:phone":"+32 10 24 21 80",
    "sg:postcode":"1300",
    "sg:province":"Brabant Wallon",
    "sg:tags":[
        "debt",
        "recovery"
    ],
    "wof:name":"Servirec Sa",
    "wof:placetype":"venue"
},
  "geometry": {"coordinates":[4.6269359589,50.706817627],"type":"Point"}
}