{
  "type": "Feature",
  "properties": {
    "iso:country":"BE",
    "sg:address":"Fochelstraat 6",
    "sg:city":"Lebbeke",
    "sg:orig_category":"Installatie van metalen schrijnwerk Metaalbehandeling and -bekleding",
    "sg:phone":"+32 52 35 81 45",
    "sg:postcode":"9280",
    "sg:province":"Oost-Vlaanderen",
    "wof:name":"Cooreman",
    "wof:placetype":"venue"
},
  "geometry": {"coordinates":[4.1472420692,50.9887123108],"type":"Point"}
}