{
  "type": "Feature",
  "properties": {
    "iso:country":"BE",
    "sg:address":"Vierwegstraat 96",
    "sg:city":"Roeselare",
    "sg:classifiers":[
        {
            "category":"Cafe",
            "type":"Food & Drink"
        }
    ],
    "sg:phone":"+32 51 20 68 31",
    "sg:postcode":"8800",
    "sg:province":"West-Vlaanderen",
    "sg:tags":[
        "caf\u00e9s"
    ],
    "wof:name":"K Colpaert",
    "wof:placetype":"venue"
},
  "geometry": {"coordinates":[3.1459460258,50.9478988647],"type":"Point"}
}