{
  "type": "Feature",
  "properties": {
    "iso:country":"BE",
    "sg:address":"Nijverheidsstraat 9",
    "sg:city":"Malle (oostmalle)",
    "sg:orig_category":"Non-Classified Establishments",
    "sg:phone":"+32 3 312 35 61",
    "sg:postcode":"2390",
    "sg:province":"Antwerpen",
    "wof:name":"Van Der Vorst M",
    "wof:placetype":"venue"
},
  "geometry": {"coordinates":[4.7125377655,51.2945289612],"type":"Point"}
}