{
  "type": "Feature",
  "properties": {
    "addr:full":"Rue Saint-guidon 81 Bruxelles (anderlecht) Bruxelles-Capitale 1070",
    "addr:housenumber":"81",
    "addr:postcode":"1070",
    "addr:street":"Rue Saint-Guidon",
    "iso:country":"BE",
    "sg:address":"Rue Saint-guidon 81",
    "sg:city":"Bruxelles (anderlecht)",
    "sg:classifiers":[
        {
            "category":"Retail",
            "subcategory":"Auto Repair",
            "type":"Services"
        }
    ],
    "sg:phone":"+32 2 523 79 09",
    "sg:postcode":"1070",
    "sg:province":"Bruxelles-Capitale",
    "sg:tags":[
        "garage"
    ],
    "wof:name":"Pm Motor Sprl",
    "wof:placetype":"venue"
},
  "geometry": {"coordinates":[4.302467823,50.8359718323],"type":"Point"}
}