{
  "type": "Feature",
  "properties": {
    "addr:full":"Henegouwenstraat 47 Gent Oost-Vlaanderen 9000",
    "addr:housenumber":"47",
    "addr:postcode":"9000",
    "addr:street":"Henegouwenstraat;Oost-Vlaanderen",
    "iso:country":"BE",
    "sg:address":"Henegouwenstraat 47",
    "sg:city":"Gent",
    "sg:orig_category":"Artsen and specialisten",
    "sg:phone":"+32 9 223 62 22",
    "sg:postcode":"9000",
    "sg:province":"Oost-Vlaanderen",
    "wof:name":"E. Vereecken",
    "wof:placetype":"venue"
},
  "geometry": {"coordinates":[3.7262260914,51.0522232056],"type":"Point"}
}