{
  "type": "Feature",
  "properties": {
    "addr:full":"Rue Ransy 2 Chaudfontaine (vaux-sous-ch\u00e8vremont) Li\u00e8ge 4051",
    "addr:housenumber":"2",
    "addr:postcode":"4051",
    "addr:street":"Rue Ransy",
    "iso:country":"BE",
    "sg:address":"Rue Ransy 2",
    "sg:city":"Chaudfontaine (vaux-sous-ch\u00e8vremont)",
    "sg:classifiers":[
        {
            "category":"Health Services",
            "subcategory":"Doctor",
            "type":"Services"
        }
    ],
    "sg:phone":"+32 4 367 24 60",
    "sg:postcode":"4051",
    "sg:province":"Li\u00e8ge",
    "sg:tags":[
        "medicinephysicians",
        "surgeon"
    ],
    "wof:name":"Herry L",
    "wof:placetype":"venue"
},
  "geometry": {"coordinates":[5.6291007996,50.6078948975],"type":"Point"}
}