{
  "type": "Feature",
  "properties": {
    "addr:full":"Chauss\u00e9e De Louvain 68 Bruxelles (saint-josse-ten-noode) Bruxelles-Capitale 1210",
    "addr:housenumber":"68",
    "addr:postcode":"1210",
    "addr:street":"Chausse\u0301E De Louvain",
    "iso:country":"BE",
    "sg:address":"Chauss\u00e9e De Louvain 68",
    "sg:city":"Bruxelles (saint-josse-ten-noode)",
    "sg:classifiers":[
        {
            "category":"Retail",
            "subcategory":"Repair Shop",
            "type":"Services"
        }
    ],
    "sg:phone":"+32 2 218 41 45",
    "sg:postcode":"1210",
    "sg:province":"Bruxelles-Capitale",
    "sg:tags":[
        "-",
        "clothing",
        "alteration"
    ],
    "wof:name":"Gabriel (chez)",
    "wof:placetype":"venue"
},
  "geometry": {"coordinates":[4.3724308014,50.8496208191],"type":"Point"}
}