{
  "type": "Feature",
  "properties": {
    "iso:country":"BE",
    "sg:address":"Peulisstraat 21",
    "sg:city":"Putte",
    "sg:orig_category":"Kapsalons",
    "sg:phone":"+32 15 76 10 29",
    "sg:postcode":"2580",
    "sg:province":"Antwerpen",
    "wof:name":"Haarateljee",
    "wof:placetype":"venue"
},
  "geometry": {"coordinates":[4.5887718201,51.0378112793],"type":"Point"}
}