{
  "type": "Feature",
  "properties": {
    "iso:country":"BE",
    "sg:address":"Sint-medardusplein 18",
    "sg:city":"Heuvelland (wijtschate)",
    "sg:classifiers":[
        {
            "category":"Insurance",
            "subcategory":"Insurance Agent",
            "type":"Services"
        }
    ],
    "sg:phone":"+32 57 44 63 93",
    "sg:postcode":"8953",
    "sg:province":"West-Vlaanderen",
    "sg:tags":[
        "broker"
    ],
    "wof:name":"Fonteyne Bernard Bvba",
    "wof:placetype":"venue"
},
  "geometry": {"coordinates":[2.883122921,50.7858085632],"type":"Point"}
}