{
  "type": "Feature",
  "properties": {
    "iso:country":"BE",
    "sg:address":"B\u00c9verc\u00c9 25bv",
    "sg:city":"Malmedy",
    "sg:orig_category":"Medische apparatuur, orthopedische artikelen and prothesen Fab",
    "sg:phone":"+32 80 33 90 50",
    "sg:postcode":"4960",
    "sg:province":"Li\u00e8ge",
    "wof:name":"Jacques Van Herstraeten",
    "wof:placetype":"venue"
},
  "geometry": {"coordinates":[6.0306248665,50.4252433777],"type":"Point"}
}