{
  "type": "Feature",
  "properties": {
    "addr:full":"Rozenstraat 93bb Wevelgem West-Vlaanderen 8560",
    "addr:housenumber":"93bb",
    "addr:postcode":"8560",
    "addr:street":"Rozenstraat",
    "iso:country":"BE",
    "sg:address":"Rozenstraat 93bb",
    "sg:city":"Wevelgem",
    "sg:orig_category":"V\u00eatements",
    "sg:phone":"+32 56 42 00 58",
    "sg:postcode":"8560",
    "sg:province":"West-Vlaanderen",
    "wof:name":"De Geest Breigoederenfab.",
    "wof:placetype":"venue"
},
  "geometry": {"coordinates":[3.1687879562,50.8426742554],"type":"Point"}
}