{
  "type": "Feature",
  "properties": {
    "addr:full":"Rue Des Carm\u00e9lites 54 Bruxelles (uccle) Bruxelles-Capitale 1180",
    "addr:housenumber":"54",
    "addr:postcode":"1180",
    "addr:street":"Rue Des Carme\u0301Lites",
    "iso:country":"BE",
    "sg:address":"Rue Des Carm\u00e9lites 54",
    "sg:city":"Bruxelles (uccle)",
    "sg:classifiers":[
        {
            "category":"Home & Garden",
            "subcategory":"Household Appliances",
            "type":"Retail Goods"
        }
    ],
    "sg:phone":"+32 2 343 38 15",
    "sg:postcode":"1180",
    "sg:province":"Bruxelles-Capitale",
    "sg:tags":[
        "repair",
        "mainten",
        "-",
        "electric"
    ],
    "wof:name":"Technic-home Sc",
    "wof:placetype":"venue"
},
  "geometry": {"coordinates":[4.3408341408,50.8124885559],"type":"Point"}
}