{
  "type": "Feature",
  "properties": {
    "iso:country":"BE",
    "sg:address":"Rue Du Beau Site 27",
    "sg:city":"Grez-doiceau (biez)",
    "sg:classifiers":[
        {
            "category":"Building & Trades",
            "subcategory":"Plumbing",
            "type":"Services"
        }
    ],
    "sg:phone":"+32 10 84 23 58",
    "sg:postcode":"1390",
    "sg:province":"Brabant Wallon",
    "sg:tags":[
        "repair",
        "mainten",
        "-",
        "central",
        "heating"
    ],
    "wof:name":"Nemegeer W",
    "wof:placetype":"venue"
},
  "geometry": {"coordinates":[4.703769207,50.7264137268],"type":"Point"}
}