{
  "type": "Feature",
  "properties": {
    "addr:full":"Boulevard Paul Janson 30 Charleroi Hainaut 6000",
    "addr:housenumber":"30",
    "addr:postcode":"6000",
    "addr:street":"Boulevard Paul Janson;Hainaut",
    "iso:country":"BE",
    "sg:address":"Boulevard Paul Janson 30",
    "sg:city":"Charleroi",
    "sg:orig_category":"Magasins de r\u00e9parations d'articles personnels et m\u00e9nagers divers",
    "sg:phone":"+32 71 30 64 66",
    "sg:postcode":"6000",
    "sg:province":"Hainaut",
    "wof:name":"Maison Samibeltex",
    "wof:placetype":"venue"
},
  "geometry": {"coordinates":[4.446721077,50.4146308899],"type":"Point"}
}