{
  "type": "Feature",
  "properties": {
    "iso:country":"BE",
    "sg:address":"Route De Bouillon 140",
    "sg:city":"Arlon (heinsch)",
    "sg:classifiers":[
        {
            "category":"Real Estate",
            "subcategory":"Architect",
            "type":"Services"
        }
    ],
    "sg:phone":"+32 63 21 76 00",
    "sg:postcode":"6700",
    "sg:province":"Luxembourg",
    "wof:name":"Cornet E",
    "wof:placetype":"venue"
},
  "geometry": {"coordinates":[5.8126749992,49.6823234558],"type":"Point"}
}