{
  "type": "Feature",
  "properties": {
    "addr:full":"Rue Charlemont 39 Chastre Brabant Wallon 1450",
    "addr:housenumber":"39",
    "addr:postcode":"1450",
    "addr:street":"Rue Charlemont",
    "iso:country":"BE",
    "sg:address":"Rue Charlemont 39",
    "sg:city":"Chastre",
    "sg:orig_category":"Artsen and specialisten",
    "sg:phone":"+32 71 87 67 19",
    "sg:postcode":"1450",
    "sg:province":"Brabant Wallon",
    "wof:name":"Genevi\u00c8ve Moreau",
    "wof:placetype":"venue"
},
  "geometry": {"coordinates":[4.636452198,50.6085243225],"type":"Point"}
}