{
  "type": "Feature",
  "properties": {
    "iso:country":"BE",
    "sg:address":"Rue De Gawday 83",
    "sg:city":"Andenne (maizeret)",
    "sg:classifiers":[
        {
            "category":"Professional",
            "subcategory":"Accounting & Tax Preparation",
            "type":"Services"
        }
    ],
    "sg:phone":"+32 81 58 89 01",
    "sg:postcode":"5300",
    "sg:province":"Namur",
    "sg:tags":[
        "accountant"
    ],
    "wof:name":"Houyoux G",
    "wof:placetype":"venue"
},
  "geometry": {"coordinates":[4.9837799072,50.4705886841],"type":"Point"}
}