{
  "type": "Feature",
  "properties": {
    "iso:country":"BE",
    "sg:address":"Steenweg 208",
    "sg:city":"As",
    "sg:orig_category":"Travaux de finition and nettoyage de b\u00e2timents. Peinture. Services de Nettoyage and de D\u00e9sinfection.",
    "sg:phone":"+32 89 65 00 20",
    "sg:postcode":"3665",
    "sg:province":"Limburg",
    "wof:name":"A.s.l.v.",
    "wof:placetype":"venue"
},
  "geometry": {"coordinates":[5.5616898537,50.9983901978],"type":"Point"}
}