{
  "type": "Feature",
  "properties": {
    "addr:full":"Rue L\u00e9opold I 159 Bruxelles Bruxelles-Capitale 1020",
    "addr:housenumber":"159",
    "addr:postcode":"1020",
    "addr:street":"Rue Le\u0301Opold I",
    "iso:country":"BE",
    "sg:address":"Rue L\u00e9opold I 159",
    "sg:city":"Bruxelles",
    "sg:classifiers":[
        {
            "category":"Wholesale",
            "subcategory":"Wine & Distilled Alcoholic Beverages",
            "type":"Manufacturing & Wholesale Goods"
        }
    ],
    "sg:phone":"+32 2 428 32 20",
    "sg:postcode":"1020",
    "sg:province":"Bruxelles-Capitale",
    "sg:tags":[
        "whol",
        "-",
        "spirit",
        "mfg"
    ],
    "wof:name":"Vinos Granada-vanden Bussche",
    "wof:placetype":"venue"
},
  "geometry": {"coordinates":[4.3461780548,50.8775291443],"type":"Point"}
}