{
  "type": "Feature",
  "properties": {
    "iso:country":"BE",
    "sg:address":"Juniorslaan 38",
    "sg:city":"Mechelen",
    "sg:orig_category":"Producteurs de l\u00e9gumes",
    "sg:phone":"+32 15 71 19 73",
    "sg:postcode":"2811",
    "sg:province":"Antwerpen",
    "wof:name":"Verbeeck Dry Froods",
    "wof:placetype":"venue"
},
  "geometry": {"coordinates":[4.4443998337,51.014541626],"type":"Point"}
}