{
  "type": "Feature",
  "properties": {
    "iso:country":"BE",
    "sg:address":"Schaarbeeklei 14",
    "sg:city":"Vilvoorde",
    "sg:classifiers":[
        {
            "category":"Health Services",
            "subcategory":"Health Practitioner",
            "type":"Services"
        }
    ],
    "sg:phone":"+32 2 251 48 67",
    "sg:postcode":"1800",
    "sg:province":"Vlaams-Brabant",
    "sg:tags":[
        "physiotherapist"
    ],
    "wof:name":"Van Den Houte M",
    "wof:placetype":"venue"
},
  "geometry": {"coordinates":[4.4261288643,50.9259033203],"type":"Point"}
}