{
  "type": "Feature",
  "properties": {
    "addr:full":"Monseigneur De Haernelaan 51 Kortrijk West-Vlaanderen 8500",
    "addr:housenumber":"51",
    "addr:postcode":"8500",
    "addr:street":"Monseigneur De Haernelaan",
    "iso:country":"BE",
    "sg:address":"Monseigneur De Haernelaan 51",
    "sg:city":"Kortrijk",
    "sg:orig_category":"Non-Classified Establishments",
    "sg:phone":"+32 56 21 06 99",
    "sg:postcode":"8500",
    "sg:province":"West-Vlaanderen",
    "wof:name":"Bellino Lighting Nv",
    "wof:placetype":"venue"
},
  "geometry": {"coordinates":[3.2609000206,50.8216094971],"type":"Point"}
}