{
  "type": "Feature",
  "properties": {
    "iso:country":"BE",
    "sg:address":"G. Scottlaan 13",
    "sg:city":"Koksijde",
    "sg:orig_category":"Artiesten and kunstenaars",
    "sg:phone":"+32 58 51 50 09",
    "sg:postcode":"8670",
    "sg:province":"West-Vlaanderen",
    "wof:name":"Erik Colpaert",
    "wof:placetype":"venue"
},
  "geometry": {"coordinates":[2.6492800713,51.1061401367],"type":"Point"}
}