{
  "type": "Feature",
  "properties": {
    "iso:country":"BE",
    "sg:address":"Sint-benedictusstraat 13",
    "sg:city":"Mortsel",
    "sg:classifiers":[
        {
            "category":"Fast Food",
            "type":"Food & Drink"
        }
    ],
    "sg:phone":"+32 3 440 67 59",
    "sg:postcode":"2640",
    "sg:province":"Antwerpen",
    "sg:tags":[
        "fried",
        "stand",
        "potato"
    ],
    "wof:name":"Sint-benedictus",
    "wof:placetype":"venue"
},
  "geometry": {"coordinates":[4.4621949196,51.1657409668],"type":"Point"}
}