{
  "type": "Feature",
  "properties": {
    "iso:country":"BE",
    "sg:address":"Nieder-emmels 100ba",
    "sg:city":"Sankt Vith/saint-vith",
    "sg:orig_category":"Diverse bouwafwerking and reiniging Schilders",
    "sg:phone":"+32 80 22 89 30",
    "sg:postcode":"4784",
    "sg:province":"Li\u00e8ge",
    "wof:name":"Berens",
    "wof:placetype":"venue"
},
  "geometry": {"coordinates":[6.091219902,50.3113288879],"type":"Point"}
}