{
  "type": "Feature",
  "properties": {
    "iso:country":"BE",
    "sg:address":"Chauss\u00e9e De Dinant 156",
    "sg:city":"Profondeville",
    "sg:classifiers":[
        {
            "category":"Retail",
            "subcategory":"Auto Repair",
            "type":"Services"
        }
    ],
    "sg:phone":"+32 81 41 10 82",
    "sg:postcode":"5170",
    "sg:province":"Namur",
    "sg:tags":[
        "automobile-body"
    ],
    "wof:name":"Tasseroul (carrosserie)",
    "wof:placetype":"venue"
},
  "geometry": {"coordinates":[4.8709058762,50.359703064],"type":"Point"}
}