{
  "type": "Feature",
  "properties": {
    "addr:full":"Avenue Fernand Desonay 10 Verviers Li\u00e8ge 4801",
    "addr:housenumber":"10",
    "addr:postcode":"4801",
    "addr:street":"Avenue Fernand Desonay",
    "iso:country":"BE",
    "sg:address":"Avenue Fernand Desonay 10",
    "sg:city":"Verviers",
    "sg:orig_category":"Supermarch\u00e9s",
    "sg:phone":"+32 87 22 80 87",
    "sg:postcode":"4801",
    "sg:province":"Li\u00e8ge",
    "wof:name":"Profi",
    "wof:placetype":"venue"
},
  "geometry": {"coordinates":[5.8904800415,50.5901107788],"type":"Point"}
}