{
  "type": "Feature",
  "properties": {
    "iso:country":"BE",
    "sg:address":"Dorpsplein 3",
    "sg:city":"Melle",
    "sg:orig_category":"Boucheries",
    "sg:phone":"+32 9 252 12 93",
    "sg:postcode":"9090",
    "sg:province":"Oost-Vlaanderen",
    "wof:name":"Christian Bocklandt",
    "wof:placetype":"venue"
},
  "geometry": {"coordinates":[3.8018009663,51.0046005249],"type":"Point"}
}