{
  "type": "Feature",
  "properties": {
    "addr:full":"Leeuweriklaan 25 Kapellen Antwerpen 2950",
    "addr:housenumber":"25",
    "addr:postcode":"2950",
    "addr:street":"Leeuweriklaan",
    "iso:country":"BE",
    "sg:address":"Leeuweriklaan 25",
    "sg:city":"Kapellen",
    "sg:orig_category":"Production and transformation de viande",
    "sg:phone":"+32 3 605 34 61",
    "sg:postcode":"2950",
    "sg:province":"Antwerpen",
    "wof:name":"Doux Frais Europe",
    "wof:placetype":"venue"
},
  "geometry": {"coordinates":[4.4442100525,51.3012428284],"type":"Point"}
}