{
  "type": "Feature",
  "properties": {
    "iso:country":"BE",
    "sg:address":"Hufengasse 4-8",
    "sg:city":"Eupen",
    "sg:classifiers":[
        {
            "category":"Health Services",
            "subcategory":"Health Practitioner",
            "type":"Services"
        }
    ],
    "sg:phone":"+32 87 59 96 61",
    "sg:postcode":"4700",
    "sg:province":"Li\u00e8ge",
    "sg:tags":[
        "physiotherapist"
    ],
    "wof:name":"Rehabilitationszentrum Physiotherapie",
    "wof:placetype":"venue"
},
  "geometry": {"coordinates":[6.0297698975,50.6291999817],"type":"Point"}
}