{
  "type": "Feature",
  "properties": {
    "addr:full":"Arnold Van Loonlaan 27 Hasselt Limburg 3500",
    "addr:housenumber":"27",
    "addr:postcode":"3500",
    "addr:street":"Arnold Van Loonlaan",
    "iso:country":"BE",
    "sg:address":"Arnold Van Loonlaan 27",
    "sg:city":"Hasselt",
    "sg:classifiers":[
        {
            "category":"Health Services",
            "subcategory":"Health Practitioner",
            "type":"Services"
        }
    ],
    "sg:phone":"+32 11 27 23 19",
    "sg:postcode":"3500",
    "sg:province":"Limburg",
    "sg:tags":[
        "physiotherapist"
    ],
    "wof:name":"Vanbockrijck C",
    "wof:placetype":"venue"
},
  "geometry": {"coordinates":[5.3418049812,50.9151725769],"type":"Point"}
}