{
  "type": "Feature",
  "properties": {
    "iso:country":"BE",
    "sg:address":"Rue De Virelles 16",
    "sg:city":"Froidchapelle",
    "sg:orig_category":"Woningbouw",
    "sg:phone":"+32 60 41 20 96",
    "sg:postcode":"6440",
    "sg:province":"Hainaut",
    "wof:name":"Cambier Jean-jacques",
    "wof:placetype":"venue"
},
  "geometry": {"coordinates":[4.3273711205,50.1434288025],"type":"Point"}
}