{
  "type": "Feature",
  "properties": {
    "addr:full":"Koning Leopold Iii-laan 39 Kortrijk West-Vlaanderen 8500",
    "addr:housenumber":"39",
    "addr:postcode":"8500",
    "addr:street":"Koning Leopold Iii-Laan",
    "iso:country":"BE",
    "sg:address":"Koning Leopold Iii-laan 39",
    "sg:city":"Kortrijk",
    "sg:orig_category":"Pharmaciens",
    "sg:phone":"+32 56 35 46 41",
    "sg:postcode":"8500",
    "sg:province":"West-Vlaanderen",
    "wof:name":"B. Vermaut",
    "wof:placetype":"venue"
},
  "geometry": {"coordinates":[3.2670099735,50.8403778076],"type":"Point"}
}