{
  "type": "Feature",
  "properties": {
    "addr:full":"Rue P Dupont 167 Evere Bruxelles-Capitale 1140",
    "addr:housenumber":"167",
    "addr:postcode":"1140",
    "addr:street":"Rue P Dupont",
    "iso:country":"BE",
    "sg:address":"Rue P Dupont 167",
    "sg:city":"Evere",
    "sg:orig_category":"Mat\u00e9riaux de construction Quincailleries. Pi\u00e8ces and accessoires de v\u00e9hicules automobiles Gr",
    "sg:phone":"+32 2 726 16 85",
    "sg:postcode":"1140",
    "sg:province":"Bruxelles-Capitale",
    "wof:name":"Sika",
    "wof:placetype":"venue"
},
  "geometry": {"coordinates":[4.4124150276,50.8641777039],"type":"Point"}
}