{
  "type": "Feature",
  "properties": {
    "iso:country":"BE",
    "sg:address":"Molenstraat 82",
    "sg:city":"Schilde",
    "sg:orig_category":"Kapsalons",
    "sg:phone":"+32 3 383 41 87",
    "sg:postcode":"2970",
    "sg:province":"Antwerpen",
    "wof:name":"Marianne Van Camp",
    "wof:placetype":"venue"
},
  "geometry": {"coordinates":[4.5756602287,51.2457618713],"type":"Point"}
}