{
  "type": "Feature",
  "properties": {
    "iso:country":"BE",
    "sg:address":"Boshoek 316",
    "sg:city":"Boechout",
    "sg:classifiers":[
        {
            "category":"Retail",
            "subcategory":"Veterinary Services",
            "type":"Services"
        }
    ],
    "sg:phone":"+32 3 488 58 79",
    "sg:postcode":"2530",
    "sg:province":"Antwerpen",
    "sg:tags":[
        "veterinarian"
    ],
    "wof:name":"Gys L",
    "wof:placetype":"venue"
},
  "geometry": {"coordinates":[4.5216741562,51.1346931458],"type":"Point"}
}