{
  "type": "Feature",
  "properties": {
    "addr:full":"Avenue Des Vaillants 9b12 Sint-lambrechts-woluwe/woluwe-saint-lambert Bruxelles-Capitale 1200",
    "addr:housenumber":"9b12 sint-lambrechts-woluwe",
    "addr:postcode":"1200",
    "addr:street":"Avenue Des Vaillants",
    "iso:country":"BE",
    "sg:address":"Avenue Des Vaillants 9b12",
    "sg:city":"Sint-lambrechts-woluwe/woluwe-saint-lambert",
    "sg:classifiers":[
        {
            "category":"Arena",
            "subcategory":"Sports Club",
            "type":"Entertainment"
        }
    ],
    "sg:phone":"+32 2 771 65 83",
    "sg:postcode":"1200",
    "sg:province":"Bruxelles-Capitale",
    "sg:tags":[
        "de"
    ],
    "wof:name":"B.m.a.",
    "wof:placetype":"venue"
},
  "geometry": {"coordinates":[4.4280619621,50.8442230225],"type":"Point"}
}