{
  "type": "Feature",
  "properties": {
    "iso:country":"BE",
    "sg:address":"Verlorenbroodstraat 19",
    "sg:city":"Merelbeke",
    "sg:orig_category":"Rev\u00eatements pour sols and murs",
    "sg:phone":"+32 9 231 70 53",
    "sg:postcode":"9820",
    "sg:province":"Oost-Vlaanderen",
    "wof:name":"Patrick Lootens",
    "wof:placetype":"venue"
},
  "geometry": {"coordinates":[3.7503819466,51.0152130127],"type":"Point"}
}