{
  "type": "Feature",
  "properties": {
    "addr:full":"1046 Leuerbroek 3640 Kinrooi 1046",
    "addr:housenumber":"1046",
    "addr:postcode":"3640;1046",
    "addr:street":"Leuerbroek",
    "iso:country":"BE",
    "sg:address":"1046",
    "sg:city":"Leuerbroek 3640 Kinrooi",
    "sg:classifiers":[
        {
            "category":"Manufacturing",
            "subcategory":"Metals",
            "type":"Manufacturing & Wholesale Goods"
        }
    ],
    "sg:phone":"+32 89 70 36 63",
    "sg:postcode":"1046",
    "sg:tags":[
        "metallurgy",
        "metalworking",
        "processing"
    ],
    "wof:name":"Thermozink Bvba",
    "wof:placetype":"venue"
},
  "geometry": {"coordinates":[5.7513651848,51.1384811401],"type":"Point"}
}