{
  "type": "Feature",
  "properties": {
    "addr:full":"Val D'heure 24 Ham-sur-heure-nalinnes Hainaut 6120",
    "addr:housenumber":"24",
    "addr:postcode":"6120",
    "addr:street":"Val D'Heure;Hainaut",
    "iso:country":"BE",
    "sg:address":"Val D'heure 24",
    "sg:city":"Ham-sur-heure-nalinnes",
    "sg:orig_category":"Wasserijen, Reiniging and Droogkuis",
    "sg:phone":"+32 71 21 32 22",
    "sg:postcode":"6120",
    "sg:province":"Hainaut",
    "wof:name":"Servinett",
    "wof:placetype":"venue"
},
  "geometry": {"coordinates":[4.4028811455,50.3474502563],"type":"Point"}
}