{
  "type": "Feature",
  "properties": {
    "addr:full":"Bergstraat 7 Grimbergen Vlaams-Brabant 1850",
    "addr:housenumber":"7",
    "addr:postcode":"1850",
    "addr:street":"Bergstraat",
    "iso:country":"BE",
    "sg:address":"Bergstraat 7",
    "sg:city":"Grimbergen",
    "sg:orig_category":"Elektrische installaties voor woningen",
    "sg:phone":"+32 2 252 38 31",
    "sg:postcode":"1850",
    "sg:province":"Vlaams-Brabant",
    "wof:name":"Rudi Poncin",
    "wof:placetype":"venue"
},
  "geometry": {"coordinates":[4.399971962,50.9749031067],"type":"Point"}
}