{
  "type": "Feature",
  "properties": {
    "addr:full":"Rue Du Congr\u00e8s 56 Bruxelles Bruxelles-Capitale 1000",
    "addr:housenumber":"56",
    "addr:postcode":"1000",
    "addr:street":"Rue Du Congre\u0300S",
    "iso:country":"BE",
    "sg:address":"Rue Du Congr\u00e8s 56",
    "sg:city":"Bruxelles",
    "sg:classifiers":[
        {
            "category":"Professional",
            "subcategory":"Testing Lab",
            "type":"Services"
        }
    ],
    "sg:phone":"+32 2 217 32 76",
    "sg:postcode":"1000",
    "sg:province":"Bruxelles-Capitale",
    "sg:tags":[
        "chemist"
    ],
    "wof:name":"Collet N",
    "wof:placetype":"venue"
},
  "geometry": {"coordinates":[4.3678979874,50.8492622375],"type":"Point"}
}