{
  "type": "Feature",
  "properties": {
    "iso:country":"BE",
    "sg:address":"Rue Spinois 43",
    "sg:city":"Charleroi (montignies-sur-sambre)",
    "sg:classifiers":[
        {
            "category":"Personal",
            "subcategory":"Beauty Salon",
            "type":"Services"
        }
    ],
    "sg:phone":"+32 71 31 19 29",
    "sg:postcode":"6061",
    "sg:province":"Hainaut",
    "sg:tags":[
        "lady",
        "-",
        "hairdressing"
    ],
    "wof:name":"Pour Vous Coiffer Sprl",
    "wof:placetype":"venue"
},
  "geometry": {"coordinates":[4.4572620392,50.4144821167],"type":"Point"}
}