{
  "type": "Feature",
  "properties": {
    "iso:country":"BE",
    "sg:address":"Zandberg 59",
    "sg:city":"Westerlo",
    "sg:orig_category":"Herstellingen and onderhoud van auto's",
    "sg:phone":"+32 14 54 49 24",
    "sg:postcode":"2260",
    "sg:province":"Antwerpen",
    "wof:name":"Ennekens",
    "wof:placetype":"venue"
},
  "geometry": {"coordinates":[4.9370989799,51.0946426392],"type":"Point"}
}