{
  "type": "Feature",
  "properties": {
    "iso:country":"BE",
    "sg:address":"Place Roi Baudouin 10",
    "sg:city":"Floreffe",
    "sg:orig_category":"Postkantoren",
    "sg:phone":"+32 81 44 45 23",
    "sg:postcode":"5150",
    "sg:province":"Namur",
    "wof:name":"La Poste",
    "wof:placetype":"venue"
},
  "geometry": {"coordinates":[4.7598891258,50.4357185364],"type":"Point"}
}