{
  "type": "Feature",
  "properties": {
    "addr:full":"Kouterstraat 238 Kortenberg Vlaams-Brabant 3071",
    "addr:housenumber":"238",
    "addr:postcode":"3071",
    "addr:street":"Kouterstraat;Vlaams-Brabant",
    "iso:country":"BE",
    "sg:address":"Kouterstraat 238",
    "sg:city":"Kortenberg",
    "sg:orig_category":"Pain, p\u00e2tisseries and confiseries",
    "sg:phone":"+32 2 759 55 27",
    "sg:postcode":"3071",
    "sg:province":"Vlaams-Brabant",
    "wof:name":"Het Taartenhuizeke",
    "wof:placetype":"venue"
},
  "geometry": {"coordinates":[4.5875868797,50.8936004639],"type":"Point"}
}