{
  "type": "Feature",
  "properties": {
    "addr:full":"Pelgrimsstraat 11 Antwerpen Antwerpen 2000",
    "addr:housenumber":"11",
    "addr:postcode":"2000",
    "addr:street":"Pelgrimsstraat",
    "iso:country":"BE",
    "sg:address":"Pelgrimsstraat 11",
    "sg:city":"Antwerpen",
    "sg:classifiers":[
        {
            "category":"Real Estate",
            "subcategory":"Real Estate Services",
            "type":"Services"
        }
    ],
    "sg:phone":"+32 3 226 46 90",
    "sg:postcode":"2000",
    "sg:province":"Antwerpen",
    "wof:name":"Immo Marvin Nv",
    "wof:placetype":"venue"
},
  "geometry": {"coordinates":[4.39980793,51.2196807861],"type":"Point"}
}