{
  "type": "Feature",
  "properties": {
    "iso:country":"BE",
    "sg:address":"Mispelstraat 1",
    "sg:city":"Sint-niklaas",
    "sg:classifiers":[
        {
            "category":"Bakery",
            "type":"Food & Drink"
        }
    ],
    "sg:phone":"+32 3 776 97 42",
    "sg:postcode":"9100",
    "sg:province":"Oost-Vlaanderen",
    "sg:tags":[
        "confectioner",
        "baker"
    ],
    "wof:name":"Voeding Petra",
    "wof:placetype":"venue"
},
  "geometry": {"coordinates":[4.1198678017,51.1753120422],"type":"Point"}
}