{
  "type": "Feature",
  "properties": {
    "addr:full":"Zegeplein 14 Turnhout Antwerpen 2300",
    "addr:housenumber":"14",
    "addr:postcode":"2300",
    "addr:street":"Zegeplein",
    "iso:country":"BE",
    "sg:address":"Zegeplein 14",
    "sg:city":"Turnhout",
    "sg:classifiers":[
        {
            "category":"Recreation",
            "subcategory":"Dance Hall",
            "type":"Entertainment"
        }
    ],
    "sg:phone":"+32 14 41 27 73",
    "sg:postcode":"2300",
    "sg:province":"Antwerpen",
    "sg:tags":[
        "discotheque"
    ],
    "wof:name":"Pike Club Discotheek",
    "wof:placetype":"venue"
},
  "geometry": {"coordinates":[4.9479780197,51.3236236572],"type":"Point"}
}