{
  "type": "Feature",
  "properties": {
    "addr:full":"Rue D'orl\u00e9ans 12 Colfontaine (p\u00e2turages) Hainaut 7340",
    "addr:housenumber":"12",
    "addr:postcode":"7340",
    "addr:street":"Rue D'Orle \u0301Ans",
    "iso:country":"BE",
    "sg:address":"Rue D'orl\u00e9ans 12",
    "sg:city":"Colfontaine (p\u00e2turages)",
    "sg:classifiers":[
        {
            "category":"Education",
            "subcategory":"School",
            "type":"Public Place"
        }
    ],
    "sg:phone":"+32 65 67 22 13",
    "sg:postcode":"7340",
    "sg:province":"Hainaut",
    "sg:tags":[
        "secondary"
    ],
    "wof:name":"Inst Du Sacr\u00e9-coeur",
    "wof:placetype":"venue"
},
  "geometry": {"coordinates":[3.8636379242,50.4113883972],"type":"Point"}
}