{
  "type": "Feature",
  "properties": {
    "addr:full":"Rue De Launet 3 Saint-hubert (hatrival) Luxembourg 6870",
    "addr:housenumber":"3",
    "addr:postcode":"6870",
    "addr:street":"Rue De Launet",
    "iso:country":"BE",
    "sg:address":"Rue De Launet 3",
    "sg:city":"Saint-hubert (hatrival)",
    "sg:classifiers":[
        {
            "category":"Government",
            "subcategory":"Post Office",
            "type":"Public Place"
        }
    ],
    "sg:phone":"+32 61 61 15 29",
    "sg:postcode":"6870",
    "sg:province":"Luxembourg",
    "sg:tags":[
        "yoga"
    ],
    "wof:name":"Viniyoga",
    "wof:placetype":"venue"
},
  "geometry": {"coordinates":[5.373360157,50.0256156921],"type":"Point"}
}