{
  "type": "Feature",
  "properties": {
    "addr:full":"Maaltebruggestraat 46 Gent Oost-Vlaanderen 9000",
    "addr:housenumber":"46",
    "addr:postcode":"9000",
    "addr:street":"Maaltebruggestraat;Oost-Vlaanderen",
    "iso:country":"BE",
    "sg:address":"Maaltebruggestraat 46",
    "sg:city":"Gent",
    "sg:classifiers":[
        {
            "category":"Professional",
            "subcategory":"Computer Services",
            "type":"Services"
        }
    ],
    "sg:phone":"+32 477 84 03 64",
    "sg:postcode":"9000",
    "sg:province":"Oost-Vlaanderen",
    "sg:tags":[
        "-",
        "processing",
        "data",
        "software"
    ],
    "wof:name":"Open Systems Bvba",
    "wof:placetype":"venue"
},
  "geometry": {"coordinates":[3.7121500969,51.0310707092],"type":"Point"}
}