{
  "type": "Feature",
  "properties": {
    "addr:full":"Boterberg 44 Linkebeek Vlaams-Brabant 1630",
    "addr:housenumber":"44",
    "addr:postcode":"1630",
    "addr:street":"Boterberg",
    "iso:country":"BE",
    "sg:address":"Boterberg 44",
    "sg:city":"Linkebeek",
    "sg:classifiers":[
        {
            "category":"Social Services",
            "subcategory":"Job Training",
            "type":"Services"
        }
    ],
    "sg:phone":"+32 2 377 91 15",
    "sg:postcode":"1630",
    "sg:province":"Vlaams-Brabant",
    "sg:tags":[
        "interpreter"
    ],
    "wof:name":"Slunecko M",
    "wof:placetype":"venue"
},
  "geometry": {"coordinates":[4.3247008324,50.7754402161],"type":"Point"}
}