{
  "type": "Feature",
  "properties": {
    "addr:full":"Rue Du Centre 6 Momignies (macquenoise) Hainaut 6593",
    "addr:housenumber":"6",
    "addr:postcode":"6593",
    "addr:street":"Rue Du Centre",
    "iso:country":"BE",
    "sg:address":"Rue Du Centre 6",
    "sg:city":"Momignies (macquenoise)",
    "sg:classifiers":[
        {
            "category":"Communications",
            "subcategory":"Television Station",
            "type":"Services"
        }
    ],
    "sg:phone":"+32 60 51 29 21",
    "sg:postcode":"6593",
    "sg:province":"Hainaut",
    "sg:tags":[
        "electricity",
        "cabling",
        "wiring",
        "-"
    ],
    "wof:name":"Robin P Ets",
    "wof:placetype":"venue"
},
  "geometry": {"coordinates":[4.1803197861,49.9754104614],"type":"Point"}
}