{
  "type": "Feature",
  "properties": {
    "addr:full":"Eksaarde Dorp 147 Lokeren (eksaarde) Oost-Vlaanderen 9160",
    "addr:housenumber":"147",
    "addr:postcode":"9160",
    "addr:street":"Eksaarde Dorp;Lokeren Eksaarde Oost-Vlaanderen",
    "iso:country":"BE",
    "sg:address":"Eksaarde Dorp 147",
    "sg:city":"Lokeren (eksaarde)",
    "sg:classifiers":[
        {
            "category":"Health Services",
            "subcategory":"Health Practitioner",
            "type":"Services"
        }
    ],
    "sg:phone":"+32 9 346 97 45",
    "sg:postcode":"9160",
    "sg:province":"Oost-Vlaanderen",
    "sg:tags":[
        "physiotherapist"
    ],
    "wof:name":"De Blieck Philippe",
    "wof:placetype":"venue"
},
  "geometry": {"coordinates":[3.962100029,51.1151504517],"type":"Point"}
}