{
  "type": "Feature",
  "properties": {
    "iso:country":"BE",
    "sg:address":"Nijverheidslaan 2",
    "sg:city":"Gullegem",
    "sg:classifiers":[
        {
            "category":"Manufacturing",
            "subcategory":"Metals",
            "type":"Manufacturing & Wholesale Goods"
        }
    ],
    "sg:phone":"+32 56 43 05 11",
    "sg:postcode":"8560",
    "sg:province":"West-Vlaanderen",
    "sg:tags":[
        "machine",
        "sheet",
        "working"
    ],
    "wof:name":"Lvd Company Nv",
    "wof:placetype":"venue"
},
  "geometry": {"coordinates":[3.186248064,50.8446655273],"type":"Point"}
}