{
  "type": "Feature",
  "properties": {
    "iso:country":"BE",
    "sg:address":"Grand 'rue 5",
    "sg:city":"Habay",
    "sg:orig_category":"Binnenhuisarchitecten Verlichting and huishoudartikelen",
    "sg:phone":"+32 63 41 14 52",
    "sg:postcode":"6724",
    "sg:province":"Luxembourg",
    "wof:name":"D' Hoedt Charlier B.",
    "wof:placetype":"venue"
},
  "geometry": {"coordinates":[5.5386037827,49.7265663147],"type":"Point"}
}