{
  "type": "Feature",
  "properties": {
    "iso:country":"BE",
    "sg:address":"Tramstraat 3b4",
    "sg:city":"Tielt",
    "sg:orig_category":"Fotografen and fotostudio's",
    "sg:phone":"+32 51 40 10 48",
    "sg:postcode":"8700",
    "sg:province":"West-Vlaanderen",
    "wof:name":"Ronny Neirinck",
    "wof:placetype":"venue"
},
  "geometry": {"coordinates":[3.3275809288,51.0007400513],"type":"Point"}
}