{
  "type": "Feature",
  "properties": {
    "iso:country":"BE",
    "sg:address":"Molenakker 36",
    "sg:city":"Schilde",
    "sg:orig_category":"D\u00e9corateurs d'int\u00e9rieur",
    "sg:phone":"+32 3 685 58 70",
    "sg:postcode":"2970",
    "sg:province":"Antwerpen",
    "wof:name":"Hans Daemen",
    "wof:placetype":"venue"
},
  "geometry": {"coordinates":[4.5809907913,51.2429275513],"type":"Point"}
}