{
  "type": "Feature",
  "properties": {
    "addr:full":"Doelstraat 155 Ingelmunster West-Vlaanderen 8770",
    "addr:housenumber":"155",
    "addr:postcode":"8770",
    "addr:street":"Doelstraat",
    "iso:country":"BE",
    "sg:address":"Doelstraat 155",
    "sg:city":"Ingelmunster",
    "sg:orig_category":"Eleveurs de bovins. Producteurs de l\u00e9gumes",
    "sg:phone":"+32 51 30 25 08",
    "sg:postcode":"8770",
    "sg:province":"West-Vlaanderen",
    "wof:name":"Roger Kerckhof",
    "wof:placetype":"venue"
},
  "geometry": {"coordinates":[3.2421309948,50.9347648621],"type":"Point"}
}