{
  "type": "Feature",
  "properties": {
    "addr:full":"Jan Van Rijswijcklaan 258 Antwerpen Antwerpen 2020",
    "addr:housenumber":"258",
    "addr:postcode":"2020",
    "addr:street":"Jan Van Rijswijcklaan",
    "iso:country":"BE",
    "sg:address":"Jan Van Rijswijcklaan 258",
    "sg:city":"Antwerpen",
    "sg:orig_category":"Banken and kredietinstellingen",
    "sg:phone":"+32 3 238 40 11",
    "sg:postcode":"2020",
    "sg:province":"Antwerpen",
    "wof:name":"Fortis",
    "wof:placetype":"venue"
},
  "geometry": {"coordinates":[4.3924398422,51.1868400574],"type":"Point"}
}