{
  "type": "Feature",
  "properties": {
    "iso:country":"BE",
    "sg:address":"Korte Torhoutstraat 7",
    "sg:city":"Ieper",
    "sg:classifiers":[
        {
            "category":"Bars & Pubs",
            "type":"Food & Drink"
        }
    ],
    "sg:phone":"+32 57 20 99 30",
    "sg:postcode":"8900",
    "sg:province":"West-Vlaanderen",
    "wof:name":"The Times",
    "wof:placetype":"venue"
},
  "geometry": {"coordinates":[2.8881340027,50.8520812988],"type":"Point"}
}