{
  "type": "Feature",
  "properties": {
    "addr:full":"Stationsstraat 24 Sint-pieters-leeuw Vlaams-Brabant 1601",
    "addr:housenumber":"24",
    "addr:postcode":"1601",
    "addr:street":"Stationsstraat",
    "iso:country":"BE",
    "sg:address":"Stationsstraat 24",
    "sg:city":"Sint-pieters-leeuw",
    "sg:orig_category":"Traitements param\u00e9dicaux",
    "sg:phone":"+32 2 377 83 32",
    "sg:postcode":"1601",
    "sg:province":"Vlaams-Brabant",
    "wof:name":"Christine Stas",
    "wof:placetype":"venue"
},
  "geometry": {"coordinates":[4.2967767715,50.7905654907],"type":"Point"}
}