{
  "type": "Feature",
  "properties": {
    "iso:country":"BE",
    "sg:address":"Lispersteenweg 76",
    "sg:city":"Lier",
    "sg:classifiers":[
        {
            "category":"Professional",
            "subcategory":"Advertising",
            "type":"Services"
        }
    ],
    "sg:phone":"+32 3 488 48 89",
    "sg:postcode":"2500",
    "sg:province":"Antwerpen",
    "sg:tags":[
        "studio"
    ],
    "wof:name":"Verrijsen P",
    "wof:placetype":"venue"
},
  "geometry": {"coordinates":[4.5743460655,51.1407394409],"type":"Point"}
}