{
  "type": "Feature",
  "properties": {
    "addr:full":"De Hulsten 80 Zoersel Antwerpen 2980",
    "addr:housenumber":"80",
    "addr:postcode":"2980",
    "iso:country":"BE",
    "sg:address":"De Hulsten 80",
    "sg:city":"Zoersel",
    "sg:classifiers":[
        {
            "category":"Building & Trades",
            "subcategory":"Cleaning & Sanitation",
            "type":"Services"
        }
    ],
    "sg:phone":"+32 3 385 06 95",
    "sg:postcode":"2980",
    "sg:province":"Antwerpen",
    "sg:tags":[
        "cleaner",
        "window"
    ],
    "wof:name":"Cleaning Services Stefan Van Puymbroeck & Co Vof",
    "wof:placetype":"venue"
},
  "geometry": {"coordinates":[4.6857938766,51.2759971619],"type":"Point"}
}