{
  "type": "Feature",
  "properties": {
    "addr:full":"Dorpsstraat 18 Hasselt Limburg 3500",
    "addr:housenumber":"18",
    "addr:postcode":"3500",
    "addr:street":"Dorpsstraat",
    "iso:country":"BE",
    "sg:address":"Dorpsstraat 18",
    "sg:city":"Hasselt",
    "sg:classifiers":[
        {
            "category":"Shopping",
            "subcategory":"Optician",
            "type":"Retail Goods"
        }
    ],
    "sg:phone":"+32 11 22 76 96",
    "sg:postcode":"3500",
    "sg:province":"Limburg",
    "sg:tags":[
        "-"
    ],
    "wof:name":"Nolens R",
    "wof:placetype":"venue"
},
  "geometry": {"coordinates":[5.3351659775,50.93227005],"type":"Point"}
}