{
  "type": "Feature",
  "properties": {
    "iso:country":"BE",
    "sg:address":"Schaapveld 2",
    "sg:city":"Dendermonde (sint-gillis-bij-dendermonde)",
    "sg:classifiers":[
        {
            "category":"Military Area",
            "subcategory":"Armory",
            "type":"Public Place"
        }
    ],
    "sg:phone":"+32 52 25 88 20",
    "sg:postcode":"9200",
    "sg:province":"Oost-Vlaanderen",
    "sg:tags":[
        "blade",
        "industrial",
        "-",
        "knife"
    ],
    "wof:name":"Ragoform",
    "wof:placetype":"venue"
},
  "geometry": {"coordinates":[4.1409459114,51.0236701965],"type":"Point"}
}