{
  "type": "Feature",
  "properties": {
    "iso:country":"BE",
    "sg:address":"Koppenstraat 2",
    "sg:city":"Heist-op-den-berg",
    "sg:orig_category":"D\u00e9molition d\u00b4immeubles and terrassements. Locations de machines and \u00e9quipement pour la construction.",
    "sg:phone":"+32 15 22 41 88",
    "sg:postcode":"2221",
    "sg:province":"Antwerpen",
    "wof:name":"Herman Michiels",
    "wof:placetype":"venue"
},
  "geometry": {"coordinates":[4.7739758492,51.0512428284],"type":"Point"}
}