{
  "type": "Feature",
  "properties": {
    "addr:full":"Rue Quev\u00c9e 4 Trivieres Hainaut 7100",
    "addr:housenumber":"4",
    "addr:postcode":"7100",
    "addr:street":"Rue Queve\u0301E;Hainaut",
    "iso:country":"BE",
    "sg:address":"Rue Quev\u00c9e 4",
    "sg:city":"Trivieres",
    "sg:orig_category":"Travaux de pl\u00e2trage",
    "sg:phone":"+32 64 84 26 76",
    "sg:postcode":"7100",
    "sg:province":"Hainaut",
    "wof:name":"Greg Plafonnage",
    "wof:placetype":"venue"
},
  "geometry": {"coordinates":[4.1439461708,50.4456596375],"type":"Point"}
}