{
  "type": "Feature",
  "properties": {
    "addr:full":"Liezeledorp 39 Puurs Antwerpen 2870",
    "addr:housenumber":"39",
    "addr:postcode":"2870",
    "addr:street":"Liezeledorp",
    "iso:country":"BE",
    "sg:address":"Liezeledorp 39",
    "sg:city":"Puurs",
    "sg:orig_category":"Herstellingen motorfietsen",
    "sg:phone":"+32 3 889 38 46",
    "sg:postcode":"2870",
    "sg:province":"Antwerpen",
    "wof:name":"Joramo",
    "wof:placetype":"venue"
},
  "geometry": {"coordinates":[4.2799448967,51.0663337708],"type":"Point"}
}