{
  "type": "Feature",
  "properties": {
    "iso:country":"BE",
    "sg:address":"Place 14",
    "sg:city":"Tournai (warchin)",
    "sg:classifiers":[
        {
            "category":"Shopping",
            "subcategory":"Books",
            "type":"Retail Goods"
        }
    ],
    "sg:phone":"+32 69 84 41 11",
    "sg:postcode":"7548",
    "sg:province":"Hainaut",
    "sg:tags":[
        "bookseller"
    ],
    "wof:name":"Philippe (libr.)",
    "wof:placetype":"venue"
},
  "geometry": {"coordinates":[3.4201769829,50.608379364],"type":"Point"}
}