{
  "type": "Feature",
  "properties": {
    "addr:full":"Rodenbachstraat 17 Boortmeerbeek Vlaams-Brabant 3191",
    "addr:housenumber":"17",
    "addr:postcode":"3191",
    "addr:street":"Rodenbachstraat",
    "iso:country":"BE",
    "sg:address":"Rodenbachstraat 17",
    "sg:city":"Boortmeerbeek",
    "sg:orig_category":"V\u00e9los",
    "sg:phone":"+32 15 51 62 84",
    "sg:postcode":"3191",
    "sg:province":"Vlaams-Brabant",
    "wof:name":"Vanderhoeven",
    "wof:placetype":"venue"
},
  "geometry": {"coordinates":[4.5484418869,50.9942855835],"type":"Point"}
}