{
  "type": "Feature",
  "properties": {
    "iso:country":"BE",
    "sg:address":"Rue Sander Pierron 13",
    "sg:city":"Schaarbeek/schaerbeek",
    "sg:orig_category":"Reliure and finition",
    "sg:phone":"+32 2 245 07 89",
    "sg:postcode":"1030",
    "sg:province":"Bruxelles-Capitale",
    "wof:name":"Fe. Vervisch",
    "wof:placetype":"venue"
},
  "geometry": {"coordinates":[4.3890647888,50.8770980835],"type":"Point"}
}