{
  "type": "Feature",
  "properties": {
    "iso:country":"BE",
    "sg:address":"Rue Joseph Van Hove 72",
    "sg:city":"Kraainem",
    "sg:classifiers":[
        {
            "category":"Retail",
            "subcategory":"Event Space",
            "type":"Services"
        }
    ],
    "sg:phone":"+32 2 721 15 15",
    "sg:postcode":"1950",
    "sg:province":"Vlaams-Brabant",
    "sg:tags":[
        "rental",
        "-",
        "hall"
    ],
    "wof:name":"Patatrac",
    "wof:placetype":"venue"
},
  "geometry": {"coordinates":[4.4544157982,50.864440918],"type":"Point"}
}