{
  "type": "Feature",
  "properties": {
    "addr:full":"Zeelaan 148 Koksijde West-Vlaanderen 8670",
    "addr:housenumber":"148",
    "addr:postcode":"8670",
    "addr:street":"Zeelaan",
    "iso:country":"BE",
    "sg:address":"Zeelaan 148",
    "sg:city":"Koksijde",
    "sg:orig_category":"Secr\u00e9tariats sociaux",
    "sg:phone":"+32 58 53 29 29",
    "sg:postcode":"8670",
    "sg:province":"West-Vlaanderen",
    "wof:name":"Soc. Secretariaat Securex",
    "wof:placetype":"venue"
},
  "geometry": {"coordinates":[2.6409249306,51.1137886047],"type":"Point"}
}