{
  "type": "Feature",
  "properties": {
    "addr:full":"Rue Elisabeth 37 Gembloux Namur 5030",
    "addr:housenumber":"37",
    "addr:postcode":"5030",
    "addr:street":"Rue Elisabeth;Namur",
    "iso:country":"BE",
    "sg:address":"Rue Elisabeth 37",
    "sg:city":"Gembloux",
    "sg:orig_category":"Vertalers and tolken",
    "sg:phone":"+32 81 61 07 87",
    "sg:postcode":"5030",
    "sg:province":"Namur",
    "wof:name":"Soree I. Cbtip/bkvtf",
    "wof:placetype":"venue"
},
  "geometry": {"coordinates":[4.6959171295,50.5574989319],"type":"Point"}
}