{
  "type": "Feature",
  "properties": {
    "addr:full":"Frans Courtenslaan 139 Schaarbeek/schaerbeek Bruxelles-Capitale 1030",
    "addr:housenumber":"139",
    "addr:postcode":"1030",
    "addr:street":"Frans Courtenslaan",
    "iso:country":"BE",
    "sg:address":"Frans Courtenslaan 139",
    "sg:city":"Schaarbeek/schaerbeek",
    "sg:orig_category":"Artsen and specialisten",
    "sg:phone":"+32 2 705 14 89",
    "sg:postcode":"1030",
    "sg:province":"Bruxelles-Capitale",
    "wof:name":"Philippe Laurent",
    "wof:placetype":"venue"
},
  "geometry": {"coordinates":[4.4034471512,50.8601799011],"type":"Point"}
}