{
  "type": "Feature",
  "properties": {
    "iso:country":"BE",
    "sg:address":"Rue Des Ecoles 59",
    "sg:city":"Gerpinnes (acoz)",
    "sg:classifiers":[
        {
            "category":"Arts & Performance",
            "subcategory":"Arts Center",
            "type":"Entertainment"
        }
    ],
    "sg:phone":"+32 71 50 45 08",
    "sg:postcode":"6280",
    "sg:province":"Hainaut",
    "sg:tags":[
        "slide"
    ],
    "wof:name":"Cadrages",
    "wof:placetype":"venue"
},
  "geometry": {"coordinates":[4.5276851654,50.3365364075],"type":"Point"}
}