{
  "type": "Feature",
  "properties": {
    "addr:full":"Moorselboslaan 11 Tervuren Vlaams-Brabant 3080",
    "addr:housenumber":"11",
    "addr:postcode":"3080",
    "addr:street":"Moorselboslaan",
    "iso:country":"BE",
    "sg:address":"Moorselboslaan 11",
    "sg:city":"Tervuren",
    "sg:classifiers":[
        {
            "category":"Professional",
            "subcategory":"Management & Consulting",
            "type":"Services"
        }
    ],
    "sg:phone":"+32 2 305 03 92",
    "sg:postcode":"3080",
    "sg:province":"Vlaams-Brabant",
    "sg:tags":[
        "consultant"
    ],
    "wof:name":"Kappa Management",
    "wof:placetype":"venue"
},
  "geometry": {"coordinates":[4.5397310257,50.8463935852],"type":"Point"}
}