{
  "type": "Feature",
  "properties": {
    "iso:country":"BE",
    "sg:address":"Avenue Victor Rousseau 53b7",
    "sg:city":"Vorst/forest",
    "sg:orig_category":"M\u00e9decins and sp\u00e9cialistes",
    "sg:phone":"+32 2 345 63 38",
    "sg:postcode":"1190",
    "sg:province":"Bruxelles-Capitale",
    "wof:name":"Christel Scheers",
    "wof:placetype":"venue"
},
  "geometry": {"coordinates":[4.3341879845,50.8155860901],"type":"Point"}
}