{
  "type": "Feature",
  "properties": {
    "addr:full":"Rue Vanderkindere 34 Ukkel/uccle Bruxelles-Capitale 1180",
    "addr:housenumber":"34",
    "addr:postcode":"1180",
    "addr:street":"Rue Vanderkindere;/",
    "iso:country":"BE",
    "sg:address":"Rue Vanderkindere 34",
    "sg:city":"Ukkel/uccle",
    "sg:orig_category":"Cr\u00e8ches and garderies d'enfants",
    "sg:phone":"+32 2 344 05 58",
    "sg:postcode":"1180",
    "sg:province":"Bruxelles-Capitale",
    "wof:name":"Cr\u00c8che C\u00c9leste",
    "wof:placetype":"venue"
},
  "geometry": {"coordinates":[4.3403348923,50.8137245178],"type":"Point"}
}