{
  "type": "Feature",
  "properties": {
    "addr:full":"P. Benoitstraat 8 Blankenberge West-Vlaanderen 8370",
    "addr:housenumber":"8",
    "addr:postcode":"8370",
    "addr:street":"P. Benoitstraat",
    "iso:country":"BE",
    "sg:address":"P. Benoitstraat 8",
    "sg:city":"Blankenberge",
    "sg:orig_category":"Peinture. Rev\u00eatements pour sols and murs",
    "sg:phone":"+32 50 41 30 99",
    "sg:postcode":"8370",
    "sg:province":"West-Vlaanderen",
    "wof:name":"Louis Jonckheere",
    "wof:placetype":"venue"
},
  "geometry": {"coordinates":[3.1259329319,51.3142204285],"type":"Point"}
}