{
  "type": "Feature",
  "properties": {
    "addr:full":"Sint-denijseweg 62 Kortrijk West-Vlaanderen 8500",
    "addr:housenumber":"62",
    "addr:postcode":"8500",
    "addr:street":"Sint-Denijseweg",
    "iso:country":"BE",
    "sg:address":"Sint-denijseweg 62",
    "sg:city":"Kortrijk",
    "sg:classifiers":[
        {
            "category":"Health Services",
            "subcategory":"Doctor",
            "type":"Services"
        }
    ],
    "sg:phone":"+32 56 22 51 31",
    "sg:postcode":"8500",
    "sg:province":"West-Vlaanderen",
    "sg:tags":[
        "medicinephysicians",
        "surgeon"
    ],
    "wof:name":"Gheysens B",
    "wof:placetype":"venue"
},
  "geometry": {"coordinates":[3.2724618912,50.8233413696],"type":"Point"}
}