{
  "type": "Feature",
  "properties": {
    "iso:country":"BE",
    "sg:address":"Regentiestraat 30",
    "sg:city":"Sint-niklaas",
    "sg:classifiers":[
        {
            "category":"Health Services",
            "subcategory":"Doctor",
            "type":"Services"
        }
    ],
    "sg:phone":"+32 3 776 99 27",
    "sg:postcode":"9100",
    "sg:province":"Oost-Vlaanderen",
    "sg:tags":[
        "medicinephysicians",
        "surgeon"
    ],
    "wof:name":"Ivens L",
    "wof:placetype":"venue"
},
  "geometry": {"coordinates":[4.1425299644,51.1687927246],"type":"Point"}
}