{
  "type": "Feature",
  "properties": {
    "addr:full":"Schans 4 Dessel Antwerpen 2480",
    "addr:housenumber":"4",
    "addr:postcode":"2480",
    "addr:street":"Schans",
    "iso:country":"BE",
    "sg:address":"Schans 4",
    "sg:city":"Dessel",
    "sg:classifiers":[
        {
            "category":"Shopping",
            "subcategory":"Computers & Home Electronics",
            "type":"Retail Goods"
        }
    ],
    "sg:phone":"+32 14 38 93 90",
    "sg:postcode":"2480",
    "sg:province":"Antwerpen",
    "sg:tags":[
        "electromechanical",
        "module"
    ],
    "wof:name":"Adesko Nv",
    "wof:placetype":"venue"
},
  "geometry": {"coordinates":[5.132818222,51.2290382385],"type":"Point"}
}