{
  "type": "Feature",
  "properties": {
    "iso:country":"BE",
    "sg:address":"Avenue De La Couronne 38",
    "sg:city":"Bruxelles (ixelles)",
    "sg:classifiers":[
        {
            "category":"Professional",
            "subcategory":"Accounting & Tax Preparation",
            "type":"Services"
        }
    ],
    "sg:phone":"+32 2 647 21 92",
    "sg:postcode":"1050",
    "sg:province":"Bruxelles-Capitale",
    "sg:tags":[
        "bookkeeper"
    ],
    "wof:name":"Bizac E",
    "wof:placetype":"venue"
},
  "geometry": {"coordinates":[4.3768110275,50.831703186],"type":"Point"}
}