{
  "type": "Feature",
  "properties": {
    "addr:full":"Bethani\u00ebnlei 18 Brecht (sint-job-in-'t Goor) Antwerpen 2960",
    "addr:housenumber":"18",
    "addr:postcode":"2960",
    "addr:street":"Bethanie\u0308Nlei;' T Goor",
    "iso:country":"BE",
    "sg:address":"Bethani\u00ebnlei 18",
    "sg:city":"Brecht (sint-job-in-'t Goor)",
    "sg:classifiers":[
        {
            "category":"Health Services",
            "subcategory":"Doctor",
            "type":"Services"
        }
    ],
    "sg:phone":"+32 3 636 12 18",
    "sg:postcode":"2960",
    "sg:province":"Antwerpen",
    "sg:tags":[
        "medicinephysicians",
        "surgeon"
    ],
    "wof:name":"Delbeke Luc",
    "wof:placetype":"venue"
},
  "geometry": {"coordinates":[4.587706089,51.2914123535],"type":"Point"}
}