{
  "type": "Feature",
  "properties": {
    "iso:country":"BE",
    "sg:address":"De Stappe 35",
    "sg:city":"Mortsel",
    "sg:classifiers":[
        {
            "category":"Social Services",
            "type":"Services"
        }
    ],
    "sg:phone":"+32 3 455 73 73",
    "sg:postcode":"2640",
    "sg:province":"Antwerpen",
    "sg:tags":[
        "handicapped",
        "-"
    ],
    "wof:name":"Stappe (de)",
    "wof:placetype":"venue"
},
  "geometry": {"coordinates":[4.4698619843,51.1633644104],"type":"Point"}
}