{
  "type": "Feature",
  "properties": {
    "addr:full":"Rue De L\u00b4ile 17 Bassenge Li\u00e8ge 4690",
    "addr:housenumber":"17",
    "addr:postcode":"4690",
    "addr:street":"Rue De L\u00b4Ile",
    "iso:country":"BE",
    "sg:address":"Rue De L\u00b4ile 17",
    "sg:city":"Bassenge",
    "sg:orig_category":"Entretien and r\u00e9parations de voitures",
    "sg:phone":"+32 4 286 57 12",
    "sg:postcode":"4690",
    "sg:province":"Li\u00e8ge",
    "wof:name":"Garage Bekaert",
    "wof:placetype":"venue"
},
  "geometry": {"coordinates":[5.5853271484,50.7522277832],"type":"Point"}
}