{
  "type": "Feature",
  "properties": {
    "addr:full":"Place 5 Mesen/messines West-Vlaanderen 8957",
    "addr:housenumber":"5",
    "addr:postcode":"8957",
    "iso:country":"BE",
    "sg:address":"Place 5",
    "sg:city":"Mesen/messines",
    "sg:orig_category":"Epiceries",
    "sg:phone":"+32 57 44 74 12",
    "sg:postcode":"8957",
    "sg:province":"West-Vlaanderen",
    "wof:name":"Marie Gillebert",
    "wof:placetype":"venue"
},
  "geometry": {"coordinates":[2.8986029625,50.7654342651],"type":"Point"}
}