{
  "type": "Feature",
  "properties": {
    "addr:full":"Rue Sainte-anne 12 Bruxelles Bruxelles-Capitale 1000",
    "addr:housenumber":"12",
    "addr:postcode":"1000",
    "addr:street":"Rue Sainte-Anne",
    "iso:country":"BE",
    "sg:address":"Rue Sainte-anne 12",
    "sg:city":"Bruxelles",
    "sg:classifiers":[
        {
            "category":"Personal",
            "subcategory":"Barber",
            "type":"Services"
        }
    ],
    "sg:phone":"+32 2 502 22 52",
    "sg:postcode":"1000",
    "sg:province":"Bruxelles-Capitale",
    "sg:tags":[
        "gentleman",
        "salon",
        "-",
        "hairdressing"
    ],
    "wof:name":"Nathan M",
    "wof:placetype":"venue"
},
  "geometry": {"coordinates":[4.3563752174,50.8415718079],"type":"Point"}
}