{
  "type": "Feature",
  "properties": {
    "addr:full":"Koestraat 10 Stekene Oost-Vlaanderen 9190",
    "addr:housenumber":"10",
    "addr:postcode":"9190",
    "addr:street":"Koestraat",
    "iso:country":"BE",
    "sg:address":"Koestraat 10",
    "sg:city":"Stekene",
    "sg:classifiers":[
        {
            "category":"Restaurant",
            "type":"Food & Drink"
        }
    ],
    "sg:phone":"+32 3 779 67 00",
    "sg:postcode":"9190",
    "sg:province":"Oost-Vlaanderen",
    "wof:name":"De Boshoeve",
    "wof:placetype":"venue"
},
  "geometry": {"coordinates":[4.0748648643,51.233581543],"type":"Point"}
}