{
  "type": "Feature",
  "properties": {
    "addr:full":"Venlaan 20 Bonheiden Antwerpen 2820",
    "addr:housenumber":"20",
    "addr:postcode":"2820",
    "addr:street":"Venlaan",
    "iso:country":"BE",
    "sg:address":"Venlaan 20",
    "sg:city":"Bonheiden",
    "sg:orig_category":"Plaatsen van vloer- and muurbekleding Schilders",
    "sg:phone":"+32 15 51 75 10",
    "sg:postcode":"2820",
    "sg:province":"Antwerpen",
    "wof:name":"Philippe Noeninckx",
    "wof:placetype":"venue"
},
  "geometry": {"coordinates":[4.5680260658,51.0175857544],"type":"Point"}
}