{
  "type": "Feature",
  "properties": {
    "iso:country":"BE",
    "sg:address":"Misstraat 2",
    "sg:city":"Berlaar",
    "sg:orig_category":"Plomberie, chauffage and installations sanitaires",
    "sg:phone":"+32 3 482 13 23",
    "sg:postcode":"2590",
    "sg:province":"Antwerpen",
    "wof:name":"Verdonck",
    "wof:placetype":"venue"
},
  "geometry": {"coordinates":[4.6388578415,51.1130180359],"type":"Point"}
}