{
  "type": "Feature",
  "properties": {
    "addr:full":"Rue Bas Vin\u00c2ve 8 Villers-le-bouillet Li\u00e8ge 4530",
    "addr:housenumber":"8",
    "addr:postcode":"4530",
    "addr:street":"Rue Bas Vina\u0302Ve",
    "iso:country":"BE",
    "sg:address":"Rue Bas Vin\u00c2ve 8",
    "sg:city":"Villers-le-bouillet",
    "sg:orig_category":"Sportclubs",
    "sg:phone":"+32 19 56 67 17",
    "sg:postcode":"4530",
    "sg:province":"Li\u00e8ge",
    "wof:name":"H.c. F\u00c9mina Villers 59",
    "wof:placetype":"venue"
},
  "geometry": {"coordinates":[5.2233490944,50.6123008728],"type":"Point"}
}