{
  "type": "Feature",
  "properties": {
    "addr:full":"Struikstraat 20 Bekkevoort (assent) Vlaams-Brabant 3460",
    "addr:housenumber":"20",
    "addr:postcode":"3460",
    "addr:street":"Struikstraat",
    "iso:country":"BE",
    "sg:address":"Struikstraat 20",
    "sg:city":"Bekkevoort (assent)",
    "sg:classifiers":[
        {
            "category":"Wholesale",
            "subcategory":"Plants",
            "type":"Manufacturing & Wholesale Goods"
        }
    ],
    "sg:phone":"+32 13 33 61 73",
    "sg:postcode":"3460",
    "sg:province":"Vlaams-Brabant",
    "sg:tags":[
        "whol",
        "flower",
        "-",
        "grower"
    ],
    "wof:name":"Somers G",
    "wof:placetype":"venue"
},
  "geometry": {"coordinates":[5.0183978081,50.9384651184],"type":"Point"}
}