{
  "type": "Feature",
  "properties": {
    "iso:country":"BE",
    "sg:address":"Aardebrug 28",
    "sg:city":"Lubbeek",
    "sg:orig_category":"Afbraak- and draineerwerken Bouwmaterialen Gh Huisvuilophaling and -verwerking",
    "sg:phone":"+32 16 73 48 35",
    "sg:postcode":"3210",
    "sg:province":"Vlaams-Brabant",
    "wof:name":"R.s.b.",
    "wof:placetype":"venue"
},
  "geometry": {"coordinates":[4.8122601509,50.8655357361],"type":"Point"}
}