{
  "type": "Feature",
  "properties": {
    "addr:full":"Lommelsegracht 6 Hechtel-eksel Limburg 3941",
    "addr:housenumber":"6",
    "addr:postcode":"3941",
    "addr:street":"Lommelsegracht",
    "iso:country":"BE",
    "sg:address":"Lommelsegracht 6",
    "sg:city":"Hechtel-eksel",
    "sg:orig_category":"Installatie van houten of kunststof schrijnwerk",
    "sg:phone":"+32 11 39 22 37",
    "sg:postcode":"3941",
    "sg:province":"Limburg",
    "wof:name":"Luc Caerts",
    "wof:placetype":"venue"
},
  "geometry": {"coordinates":[5.3011779785,51.1664047241],"type":"Point"}
}