{
  "type": "Feature",
  "properties": {
    "addr:full":"Rue Du Tige 31 Ouffet Li\u00e8ge 4590",
    "addr:housenumber":"31",
    "addr:postcode":"4590",
    "addr:street":"Rue Du Tige",
    "iso:country":"BE",
    "sg:address":"Rue Du Tige 31",
    "sg:city":"Ouffet",
    "sg:classifiers":[
        {
            "category":"Arena",
            "subcategory":"Sports Club",
            "type":"Entertainment"
        }
    ],
    "sg:phone":"+32 86 36 66 57",
    "sg:postcode":"4590",
    "sg:province":"Li\u00e8ge",
    "sg:tags":[
        "de"
    ],
    "wof:name":"J.c. Havelange",
    "wof:placetype":"venue"
},
  "geometry": {"coordinates":[5.4745140076,50.4440422058],"type":"Point"}
}