{
  "type": "Feature",
  "properties": {
    "addr:full":"Rue Ijsmolen 44 Ronse/renaix Oost-Vlaanderen 9600",
    "addr:housenumber":"44",
    "addr:postcode":"9600",
    "addr:street":"Rue Ijsmolen",
    "iso:country":"BE",
    "sg:address":"Rue Ijsmolen 44",
    "sg:city":"Ronse/renaix",
    "sg:orig_category":"Installation de menuiserie en bois and plastique",
    "sg:phone":"+32 55 23 90 86",
    "sg:postcode":"9600",
    "sg:province":"Oost-Vlaanderen",
    "wof:name":"Geert Bellinck",
    "wof:placetype":"venue"
},
  "geometry": {"coordinates":[3.6526119709,50.7569694519],"type":"Point"}
}