{
  "type": "Feature",
  "properties": {
    "iso:country":"BE",
    "sg:address":"Hoeledensebaan 98",
    "sg:city":"Kortenaken (hoeleden)",
    "sg:classifiers":[
        {
            "category":"Personal",
            "subcategory":"Beauty Salon",
            "type":"Services"
        }
    ],
    "sg:phone":"+32 16 77 17 75",
    "sg:postcode":"3471",
    "sg:province":"Vlaams-Brabant",
    "wof:name":"Ilse Schoonheidssalon",
    "wof:placetype":"venue"
},
  "geometry": {"coordinates":[4.987724781,50.8690567017],"type":"Point"}
}