{
  "type": "Feature",
  "properties": {
    "addr:full":"Kerkhofstraat 10 Rotselaar Vlaams-Brabant 3110",
    "addr:housenumber":"10",
    "addr:postcode":"3110",
    "addr:street":"Kerkhofstraat",
    "iso:country":"BE",
    "sg:address":"Kerkhofstraat 10",
    "sg:city":"Rotselaar",
    "sg:classifiers":[
        {
            "category":"Communications",
            "subcategory":"Television Station",
            "type":"Services"
        }
    ],
    "sg:phone":"+32 16 44 69 40",
    "sg:postcode":"3110",
    "sg:province":"Vlaams-Brabant",
    "sg:tags":[
        "report",
        "video"
    ],
    "wof:name":"Take Two",
    "wof:placetype":"venue"
},
  "geometry": {"coordinates":[4.7348351479,50.9622764587],"type":"Point"}
}