{
  "type": "Feature",
  "properties": {
    "iso:country":"BE",
    "sg:address":"Ooievaarsstraat 16 Box 2",
    "sg:city":"Antwerpen",
    "sg:classifiers":[
        {
            "category":"Professional",
            "subcategory":"Management & Consulting",
            "type":"Services"
        }
    ],
    "sg:phone":"+32 3 236 64 16",
    "sg:postcode":"2060",
    "sg:province":"Antwerpen",
    "sg:tags":[
        "consultant"
    ],
    "wof:name":"Smash Consult Bvba",
    "wof:placetype":"venue"
},
  "geometry": {"coordinates":[4.4377970695,51.220123291],"type":"Point"}
}