{
  "type": "Feature",
  "properties": {
    "iso:country":"BE",
    "sg:address":"Chauss\u00c9e De Charleroi 1ba",
    "sg:city":"Sint-gillis/saint-gilles",
    "sg:orig_category":"Maroquinerie and articles de voyage. Chaussures",
    "sg:phone":"+32 2 538 38 97",
    "sg:postcode":"1060",
    "sg:province":"Bruxelles-Capitale",
    "wof:name":"Maison Robert Clergerie",
    "wof:placetype":"venue"
},
  "geometry": {"coordinates":[4.3571047783,50.8336524963],"type":"Point"}
}