{
  "type": "Feature",
  "properties": {
    "addr:full":"Chauss\u00c9e De Tongres 38 Amay Li\u00e8ge 4540",
    "addr:housenumber":"38",
    "addr:postcode":"4540",
    "addr:street":"Chausse\u0301E De Tongres",
    "iso:country":"BE",
    "sg:address":"Chauss\u00c9e De Tongres 38",
    "sg:city":"Amay",
    "sg:orig_category":"Loodgieterij, verwarming and sanitaire installaties",
    "sg:phone":"+32 85 31 41 50",
    "sg:postcode":"4540",
    "sg:province":"Li\u00e8ge",
    "wof:name":"Marcel Philippart",
    "wof:placetype":"venue"
},
  "geometry": {"coordinates":[5.3114581108,50.5467453003],"type":"Point"}
}