{
  "type": "Feature",
  "properties": {
    "addr:full":"Puursesteenweg 329 Bornem Antwerpen 2880",
    "addr:housenumber":"329",
    "addr:postcode":"2880",
    "addr:street":"Puursesteenweg",
    "iso:country":"BE",
    "sg:address":"Puursesteenweg 329",
    "sg:city":"Bornem",
    "sg:classifiers":[
        {
            "category":"Retail",
            "subcategory":"Auto Repair",
            "type":"Services"
        }
    ],
    "sg:phone":"+32 3 889 72 29",
    "sg:postcode":"2880",
    "sg:province":"Antwerpen",
    "sg:tags":[
        "garage"
    ],
    "wof:name":"Bornemmotors",
    "wof:placetype":"venue"
},
  "geometry": {"coordinates":[4.2591028214,51.0858078003],"type":"Point"}
}