{
  "type": "Feature",
  "properties": {
    "iso:country":"BE",
    "sg:address":"Vorstlaan 272",
    "sg:city":"Oudergem/auderghem",
    "sg:classifiers":[
        {
            "category":"Restaurant",
            "type":"Food & Drink"
        }
    ],
    "sg:phone":"+32 2 672 98 30",
    "sg:postcode":"1160",
    "sg:province":"Bruxelles-Capitale",
    "wof:name":"Restaurant Deauville",
    "wof:placetype":"venue"
},
  "geometry": {"coordinates":[4.4260101318,50.8166007996],"type":"Point"}
}