{
  "type": "Feature",
  "properties": {
    "addr:full":"Rue Chemin-rue 49 Malmedy Li\u00e8ge 4960",
    "addr:housenumber":"49",
    "addr:postcode":"4960",
    "addr:street":"Rue Chemin-Rue",
    "iso:country":"BE",
    "sg:address":"Rue Chemin-rue 49",
    "sg:city":"Malmedy",
    "sg:classifiers":[
        {
            "category":"Shopping",
            "subcategory":"Stationery & Office Supplies",
            "type":"Retail Goods"
        }
    ],
    "sg:phone":"+32 80 33 02 03",
    "sg:postcode":"4960",
    "sg:province":"Li\u00e8ge",
    "wof:name":"Cunibert Daumen Sa",
    "wof:placetype":"venue"
},
  "geometry": {"coordinates":[6.0263948441,50.425617218],"type":"Point"}
}