{
  "type": "Feature",
  "properties": {
    "addr:full":"Av L\u00e9opold Iii 18 Waterloo Brabant Wallon 1410",
    "addr:housenumber":"18",
    "addr:postcode":"1410",
    "addr:street":"Av Le\u0301Opold Iii",
    "iso:country":"BE",
    "sg:address":"Av L\u00e9opold Iii 18",
    "sg:city":"Waterloo",
    "sg:classifiers":[
        {
            "category":"Shopping",
            "subcategory":"Gifts & Souvenirs",
            "type":"Retail Goods"
        }
    ],
    "sg:phone":"+32 2 351 09 56",
    "sg:postcode":"1410",
    "sg:province":"Brabant Wallon",
    "sg:tags":[
        "product",
        "miscellaneous"
    ],
    "wof:name":"Black Bird Sa",
    "wof:placetype":"venue"
},
  "geometry": {"coordinates":[4.395067215,50.7229766846],"type":"Point"}
}