{
  "type": "Feature",
  "properties": {
    "addr:full":"Medelaar 86 Zoersel (halle) Antwerpen 2980",
    "addr:housenumber":"86",
    "addr:postcode":"2980",
    "addr:street":"Medelaar",
    "iso:country":"BE",
    "sg:address":"Medelaar 86",
    "sg:city":"Zoersel (halle)",
    "sg:classifiers":[
        {
            "category":"Shopping",
            "subcategory":"Books",
            "type":"Retail Goods"
        }
    ],
    "sg:phone":"+32 3 385 43 95",
    "sg:postcode":"2980",
    "sg:province":"Antwerpen",
    "sg:tags":[
        "bookseller"
    ],
    "wof:name":"Pagadder (de)",
    "wof:placetype":"venue"
},
  "geometry": {"coordinates":[4.6544299126,51.2543907166],"type":"Point"}
}