{
  "type": "Feature",
  "properties": {
    "addr:full":"Sint-truidersteenweg 44 Hasselt Limburg 3500",
    "addr:housenumber":"44",
    "addr:postcode":"3500",
    "addr:street":"Sint-Truidersteenweg",
    "iso:country":"BE",
    "sg:address":"Sint-truidersteenweg 44",
    "sg:city":"Hasselt",
    "sg:orig_category":"Fleurop Interflora. Fleurs and plantes",
    "sg:phone":"+32 11 27 33 33",
    "sg:postcode":"3500",
    "sg:province":"Limburg",
    "wof:name":"Henrioulle",
    "wof:placetype":"venue"
},
  "geometry": {"coordinates":[5.3343310356,50.9255599976],"type":"Point"}
}