{
  "type": "Feature",
  "properties": {
    "iso:country":"BE",
    "sg:address":"Oelegemsesteenweg 43",
    "sg:city":"Ranst",
    "sg:orig_category":"Sportclubs Sportterreinen and installaties behalve sportcentra",
    "sg:phone":"+32 3 475 00 86",
    "sg:postcode":"2520",
    "sg:province":"Antwerpen",
    "wof:name":"V.v.w. Broechem",
    "wof:placetype":"venue"
},
  "geometry": {"coordinates":[4.5982208252,51.199848175],"type":"Point"}
}