{
  "type": "Feature",
  "properties": {
    "addr:full":"Rue De Jeneffe 5 Gr\u00e2ce-hollogne (horion-hoz\u00e9mont) Li\u00e8ge 4460",
    "addr:housenumber":"5",
    "addr:postcode":"4460",
    "addr:street":"Rue De Jeneffe;Horion-Hoze\u0301Mont",
    "iso:country":"BE",
    "sg:address":"Rue De Jeneffe 5",
    "sg:city":"Gr\u00e2ce-hollogne (horion-hoz\u00e9mont)",
    "sg:classifiers":[
        {
            "category":"Farming",
            "subcategory":"Livestock Farm",
            "type":"Manufacturing & Wholesale Goods"
        }
    ],
    "sg:phone":"+32 4 250 12 19",
    "sg:postcode":"4460",
    "sg:province":"Li\u00e8ge",
    "sg:tags":[
        "buyer"
    ],
    "wof:name":"Jaco Sa",
    "wof:placetype":"venue"
},
  "geometry": {"coordinates":[5.3760318756,50.6313667297],"type":"Point"}
}