{
  "type": "Feature",
  "properties": {
    "iso:country":"BE",
    "sg:address":"Provinciestraat 235",
    "sg:city":"Antwerpen",
    "sg:classifiers":[
        {
            "category":"Bars & Pubs",
            "type":"Food & Drink"
        }
    ],
    "sg:phone":"+32 3 226 09 14",
    "sg:postcode":"2018",
    "sg:province":"Antwerpen",
    "wof:name":"Zonnestraal",
    "wof:placetype":"venue"
},
  "geometry": {"coordinates":[4.4258742332,51.2105712891],"type":"Point"}
}