{
  "type": "Feature",
  "properties": {
    "addr:full":"Chauss\u00c9e De Charleroi 164 Sint-gillis Bruxelles-Capitale 1060",
    "addr:housenumber":"164",
    "addr:postcode":"1060",
    "addr:street":"Chausse\u0301E De Charleroi",
    "iso:country":"BE",
    "sg:address":"Chauss\u00c9e De Charleroi 164",
    "sg:city":"Sint-gillis",
    "sg:orig_category":"Rev\u00eatements de sols and murs",
    "sg:phone":"+32 2 537 69 27",
    "sg:postcode":"1060",
    "sg:province":"Bruxelles-Capitale",
    "wof:name":"Mokhberian",
    "wof:placetype":"venue"
},
  "geometry": {"coordinates":[4.3549599648,50.8261146545],"type":"Point"}
}