{
  "type": "Feature",
  "properties": {
    "addr:full":"Lang Ossegoor 36 Malle Antwerpen 2390",
    "addr:housenumber":"36",
    "addr:postcode":"2390",
    "addr:street":"Ossegoor",
    "iso:country":"BE",
    "sg:address":"Lang Ossegoor 36",
    "sg:city":"Malle",
    "sg:orig_category":"Landmeters",
    "sg:phone":"+32 3 311 65 23",
    "sg:postcode":"2390",
    "sg:province":"Antwerpen",
    "wof:name":"J. Schillebeeckx",
    "wof:placetype":"venue"
},
  "geometry": {"coordinates":[4.6748399734,51.2904701233],"type":"Point"}
}