{
  "type": "Feature",
  "properties": {
    "addr:full":"Rue Des Mauvaises-vignes 175 Li\u00e8ge 1 (ch\u00ean\u00e9e) Li\u00e8ge 4032",
    "addr:housenumber":"175;1",
    "addr:postcode":"4032",
    "addr:street":"Rue Des Mauvaises-Vignes",
    "iso:country":"BE",
    "sg:address":"Rue Des Mauvaises-vignes 175",
    "sg:city":"Li\u00e8ge 1 (ch\u00ean\u00e9e)",
    "sg:classifiers":[
        {
            "category":"Shopping",
            "subcategory":"Computers & Home Electronics",
            "type":"Retail Goods"
        }
    ],
    "sg:phone":"+32 4 365 21 91",
    "sg:postcode":"4032",
    "sg:province":"Li\u00e8ge",
    "sg:tags":[
        "-",
        "television",
        "radio"
    ],
    "wof:name":"Joliet Service",
    "wof:placetype":"venue"
},
  "geometry": {"coordinates":[5.6179981232,50.618473053],"type":"Point"}
}