{
  "type": "Feature",
  "properties": {
    "addr:full":"Meensesteenweg 195 Roeselare West-Vlaanderen 8800",
    "addr:housenumber":"195",
    "addr:postcode":"8800",
    "addr:street":"Meensesteenweg",
    "iso:country":"BE",
    "sg:address":"Meensesteenweg 195",
    "sg:city":"Roeselare",
    "sg:orig_category":"Agences d\u00b4interim and personnel temporaire",
    "sg:phone":"+32 51 22 77 30",
    "sg:postcode":"8800",
    "sg:province":"West-Vlaanderen",
    "wof:name":"Konvert Interim",
    "wof:placetype":"venue"
},
  "geometry": {"coordinates":[3.1207830906,50.9343986511],"type":"Point"}
}