{
  "type": "Feature",
  "properties": {
    "iso:country":"BE",
    "sg:address":"Rue Docteur Jeanty 2",
    "sg:city":"Virton",
    "sg:classifiers":[
        {
            "category":"Professional",
            "subcategory":"Testing Lab",
            "type":"Services"
        }
    ],
    "sg:phone":"+32 63 57 70 69",
    "sg:postcode":"6760",
    "sg:province":"Luxembourg",
    "sg:tags":[
        "chemist"
    ],
    "wof:name":"De Seille J-m",
    "wof:placetype":"venue"
},
  "geometry": {"coordinates":[5.5313258171,49.5674133301],"type":"Point"}
}