{
  "type": "Feature",
  "properties": {
    "iso:country":"BE",
    "sg:address":"Rue Joseph Wauters 21ba",
    "sg:city":"Berloz",
    "sg:orig_category":"Installation de menuiserie m\u00e9tallique",
    "sg:phone":"+32 19 32 82 02",
    "sg:postcode":"4257",
    "sg:province":"Li\u00e8ge",
    "wof:name":"Jean-marie Gaspart",
    "wof:placetype":"venue"
},
  "geometry": {"coordinates":[5.1873102188,50.7099494934],"type":"Point"}
}