{
  "type": "Feature",
  "properties": {
    "iso:country":"BE",
    "sg:address":"Tweede Carabinierslaan 145",
    "sg:city":"Veldwezelt",
    "sg:orig_category":"Fa\u00e7ade Bricks",
    "sg:phone":"+32 89 71 51 38",
    "sg:postcode":"3620",
    "sg:province":"Limburg",
    "wof:name":"Heylen Siersteenfabriek Nv",
    "wof:placetype":"venue"
},
  "geometry": {"coordinates":[5.6372299194,50.8596916199],"type":"Point"}
}