{
  "type": "Feature",
  "properties": {
    "addr:full":"Lokerse Baan 94 Sint-niklaas Oost-Vlaanderen 9111",
    "addr:housenumber":"94",
    "addr:postcode":"9111",
    "addr:street":"Lokerse Baan",
    "iso:country":"BE",
    "sg:address":"Lokerse Baan 94",
    "sg:city":"Sint-niklaas",
    "sg:classifiers":[
        {
            "category":"Food & Beverages",
            "subcategory":"Fruits & Vegetables",
            "type":"Retail Goods"
        }
    ],
    "sg:phone":"+32 3 722 09 83",
    "sg:postcode":"9111",
    "sg:province":"Oost-Vlaanderen",
    "sg:tags":[
        "l\u00e9gumes"
    ],
    "wof:name":"De Fruitkorf",
    "wof:placetype":"venue"
},
  "geometry": {"coordinates":[4.0707612038,51.138885498],"type":"Point"}
}