{
  "type": "Feature",
  "properties": {
    "addr:full":"Hendrik Ghijselenstraat 20 Lennik Vlaams-Brabant 1750",
    "addr:housenumber":"20;1750",
    "addr:street":"Ghijselenstraat;Vlaams-Brabant",
    "iso:country":"BE",
    "sg:address":"Hendrik Ghijselenstraat 20",
    "sg:city":"Lennik",
    "sg:orig_category":"Boucheries",
    "sg:phone":"+32 2 532 40 95",
    "sg:postcode":"1750",
    "sg:province":"Vlaams-Brabant",
    "wof:name":"Vanda",
    "wof:placetype":"venue"
},
  "geometry": {"coordinates":[4.1524600983,50.8058433533],"type":"Point"}
}