{
  "type": "Feature",
  "properties": {
    "iso:country":"BE",
    "sg:address":"Mallekotstraat 44",
    "sg:city":"Lier",
    "sg:orig_category":"Dakwerken Loodgieterij, verwarming and sanitaire installaties",
    "sg:phone":"+32 3 485 76 43",
    "sg:postcode":"2500",
    "sg:province":"Antwerpen",
    "wof:name":"Cedico",
    "wof:placetype":"venue"
},
  "geometry": {"coordinates":[4.5706601143,51.1463050842],"type":"Point"}
}