{
  "type": "Feature",
  "properties": {
    "addr:full":"Rue Lamir 8 Box 21 Mons Hainaut 7000",
    "addr:housenumber":"8 box 21",
    "addr:postcode":"7000",
    "addr:street":"Rue Lamir;Hainaut",
    "iso:country":"BE",
    "sg:address":"Rue Lamir 8 Box 21",
    "sg:city":"Mons",
    "sg:classifiers":[
        {
            "category":"Structure",
            "subcategory":"Office Building",
            "type":"Public Place"
        }
    ],
    "sg:phone":"+32 65 84 56 87",
    "sg:postcode":"7000",
    "sg:province":"Hainaut",
    "sg:tags":[
        "drawing"
    ],
    "wof:name":"Cecchin Ch",
    "wof:placetype":"venue"
},
  "geometry": {"coordinates":[3.9483439922,50.449256897],"type":"Point"}
}