{
  "type": "Feature",
  "properties": {
    "iso:country":"BE",
    "sg:address":"Chaussee De Beaumont 401a",
    "sg:city":"Harmignies",
    "sg:classifiers":[
        {
            "category":"Manufacturing",
            "subcategory":"Glass & Minerals",
            "type":"Manufacturing & Wholesale Goods"
        }
    ],
    "sg:phone":"+32 65 58 63 28",
    "sg:postcode":"7022",
    "sg:province":"Hainaut",
    "sg:tags":[
        "chalk"
    ],
    "wof:name":"Cray\u00e8res, Cimenterie & Fours Chaux D'harmignies S.a.",
    "wof:placetype":"venue"
},
  "geometry": {"coordinates":[4.006893158,50.412437439],"type":"Point"}
}