{
  "type": "Feature",
  "properties": {
    "iso:country":"BE",
    "sg:address":"Marlier 1",
    "sg:city":"Asse",
    "sg:orig_category":"Location de machines-outils and de mat\u00e9riel de bricolage. Quincailleries. Bois Gr",
    "sg:phone":"+32 2 452 52 52",
    "sg:postcode":"1730",
    "sg:province":"Vlaams-Brabant",
    "wof:name":"Gamma",
    "wof:placetype":"venue"
},
  "geometry": {"coordinates":[4.1983270645,50.9133834839],"type":"Point"}
}