{
  "type": "Feature",
  "properties": {
    "addr:full":"Rue Fernand Piette 40 Wanze Li\u00e8ge 4520",
    "addr:housenumber":"40",
    "addr:postcode":"4520",
    "addr:street":"Rue Fernand Piette",
    "iso:country":"BE",
    "sg:address":"Rue Fernand Piette 40",
    "sg:city":"Wanze",
    "sg:classifiers":[
        {
            "category":"Arena",
            "subcategory":"Sports Club",
            "type":"Entertainment"
        }
    ],
    "sg:phone":"+32 85 21 75 91",
    "sg:postcode":"4520",
    "sg:province":"Li\u00e8ge",
    "sg:tags":[
        "de"
    ],
    "wof:name":"C. Royal Natation De Huy",
    "wof:placetype":"venue"
},
  "geometry": {"coordinates":[5.195789814,50.5247497559],"type":"Point"}
}