{
  "type": "Feature",
  "properties": {
    "addr:full":"Statiestraat 1b Zulte Oost-Vlaanderen 9870",
    "addr:housenumber":"1b",
    "addr:postcode":"9870",
    "addr:street":"Statiestraat",
    "iso:country":"BE",
    "sg:address":"Statiestraat 1b",
    "sg:city":"Zulte",
    "sg:orig_category":"Agences d'exp\u00e9dition",
    "sg:phone":"+32 9 388 58 95",
    "sg:postcode":"9870",
    "sg:province":"Oost-Vlaanderen",
    "wof:name":"E D Trading",
    "wof:placetype":"venue"
},
  "geometry": {"coordinates":[3.4403829575,50.9192466736],"type":"Point"}
}