{
  "type": "Feature",
  "properties": {
    "addr:full":"Weg Naar Zwartberg 90 Houthalen-helchteren (houthalen) Limburg 3530",
    "addr:housenumber":"90",
    "addr:postcode":"3530",
    "addr:street":"Weg Naar Zwartberg",
    "iso:country":"BE",
    "sg:address":"Weg Naar Zwartberg 90",
    "sg:city":"Houthalen-helchteren (houthalen)",
    "sg:classifiers":[
        {
            "category":"Health Services",
            "subcategory":"Health Practitioner",
            "type":"Services"
        }
    ],
    "sg:phone":"+32 89 38 18 30",
    "sg:postcode":"3530",
    "sg:province":"Limburg",
    "sg:tags":[
        "physiotherapist"
    ],
    "wof:name":"Ceustermans E",
    "wof:placetype":"venue"
},
  "geometry": {"coordinates":[5.4123802185,51.0261192322],"type":"Point"}
}