{
  "type": "Feature",
  "properties": {
    "iso:country":"BE",
    "sg:address":"Place Jean Guyot 45",
    "sg:city":"Chatelet",
    "sg:orig_category":"Maisons de repos and r\u00e9sidences",
    "sg:phone":"+32 71 38 25 81",
    "sg:postcode":"6200",
    "sg:province":"Hainaut",
    "wof:name":"Home N.d. Bonne Esp\u00c9rance",
    "wof:placetype":"venue"
},
  "geometry": {"coordinates":[4.526157856,50.404712677],"type":"Point"}
}