{
  "type": "Feature",
  "properties": {
    "iso:country":"BE",
    "sg:address":"Rue Du Gouvernement 1",
    "sg:city":"Ath",
    "sg:classifiers":[
        {
            "category":"Social Services",
            "type":"Services"
        }
    ],
    "sg:phone":"+32 68 26 99 70",
    "sg:postcode":"7800",
    "sg:province":"Hainaut",
    "wof:name":"Action Jeunesse Info",
    "wof:placetype":"venue"
},
  "geometry": {"coordinates":[3.7766799927,50.6309204102],"type":"Point"}
}