{
  "type": "Feature",
  "properties": {
    "addr:full":"Fransmanstraat 50 Brussel/bruxelles Bruxelles-Capitale 1020",
    "addr:housenumber":"50",
    "addr:postcode":"1020",
    "addr:street":"Fransmanstraat;/",
    "iso:country":"BE",
    "sg:address":"Fransmanstraat 50",
    "sg:city":"Brussel/bruxelles",
    "sg:orig_category":"Slagers",
    "sg:phone":"+32 2 426 76 30",
    "sg:postcode":"1020",
    "sg:province":"Bruxelles-Capitale",
    "wof:name":"Boucherie De Keyser",
    "wof:placetype":"venue"
},
  "geometry": {"coordinates":[4.3454117775,50.8784217834],"type":"Point"}
}