{
  "type": "Feature",
  "properties": {
    "iso:country":"BE",
    "sg:address":"Moeskouterlaan 10",
    "sg:city":"Dendermonde",
    "sg:classifiers":[
        {
            "category":"Cafe",
            "type":"Food & Drink"
        }
    ],
    "sg:phone":"+32 52 22 47 73",
    "sg:postcode":"9200",
    "sg:province":"Oost-Vlaanderen",
    "sg:tags":[
        "caf\u00e9s"
    ],
    "wof:name":"Voetbalclub Fc Lutterzeel",
    "wof:placetype":"venue"
},
  "geometry": {"coordinates":[4.1100258827,51.0129776001],"type":"Point"}
}