{
  "type": "Feature",
  "properties": {
    "addr:full":"Bruy\u00e8res 12 Thimister-clermont (clermont) Li\u00e8ge 4890",
    "addr:housenumber":"12",
    "addr:postcode":"4890",
    "addr:street":"Bruye\u0300Res",
    "iso:country":"BE",
    "sg:address":"Bruy\u00e8res 12",
    "sg:city":"Thimister-clermont (clermont)",
    "sg:classifiers":[
        {
            "category":"Banks & Credit Unions",
            "subcategory":"Investment Brokerage",
            "type":"Services"
        }
    ],
    "sg:phone":"+32 87 68 81 80",
    "sg:postcode":"4890",
    "sg:province":"Li\u00e8ge",
    "sg:tags":[
        "auditor"
    ],
    "wof:name":"Nyssen D",
    "wof:placetype":"venue"
},
  "geometry": {"coordinates":[5.8850159645,50.6857147217],"type":"Point"}
}