{
  "type": "Feature",
  "properties": {
    "addr:full":"Kruisbaan 34 Mechelen Antwerpen 2800",
    "addr:housenumber":"34",
    "addr:postcode":"2800",
    "addr:street":"Kruisbaan",
    "iso:country":"BE",
    "sg:address":"Kruisbaan 34",
    "sg:city":"Mechelen",
    "sg:orig_category":"Non-Classified Establishments",
    "sg:phone":"+32 15 71 09 10",
    "sg:postcode":"2800",
    "sg:province":"Antwerpen",
    "wof:name":"Magic Productions",
    "wof:placetype":"venue"
},
  "geometry": {"coordinates":[4.4720001221,51.0088310242],"type":"Point"}
}