{
  "type": "Feature",
  "properties": {
    "addr:full":"Sint Truidensesteenweg 403 Tienen Vlaams-Brabant 3300",
    "addr:housenumber":"403",
    "addr:postcode":"3300",
    "addr:street":"Truidensesteenweg",
    "iso:country":"BE",
    "sg:address":"Sint Truidensesteenweg 403",
    "sg:city":"Tienen",
    "sg:orig_category":"SMEEDWERK, METAALBEWERKING AND POEDERMETALLURGIE",
    "sg:phone":"+32 16 78 83 68",
    "sg:postcode":"3300",
    "sg:province":"Vlaams-Brabant",
    "wof:name":"Kunstmederij Sciot-deboes",
    "wof:placetype":"venue"
},
  "geometry": {"coordinates":[4.9766449928,50.7986907959],"type":"Point"}
}