{
  "type": "Feature",
  "properties": {
    "iso:country":"BE",
    "sg:address":"Industrialaan 2",
    "sg:city":"Dilbeek (groot - Bijgaarden)",
    "sg:classifiers":[
        {
            "category":"Education",
            "subcategory":"Special Training",
            "type":"Public Place"
        }
    ],
    "sg:phone":"+32 2 453 25 56",
    "sg:postcode":"1702",
    "sg:province":"Vlaams-Brabant",
    "sg:tags":[
        "professional"
    ],
    "wof:name":"Cosman Training Center",
    "wof:placetype":"venue"
},
  "geometry": {"coordinates":[4.2746300697,50.8794250488],"type":"Point"}
}