{
  "type": "Feature",
  "properties": {
    "iso:country":"BE",
    "sg:address":"Rodestraat 69",
    "sg:city":"Zottegem",
    "sg:orig_category":"Experts-comptables",
    "sg:phone":"+32 9 360 65 33",
    "sg:postcode":"9620",
    "sg:province":"Oost-Vlaanderen",
    "wof:name":"Roger Coopman",
    "wof:placetype":"venue"
},
  "geometry": {"coordinates":[3.8337450027,50.8594322205],"type":"Point"}
}