{
  "type": "Feature",
  "properties": {
    "addr:full":"Pas De La Bourse 20 Charleroi Hainaut 6000",
    "addr:housenumber":"20",
    "addr:postcode":"6000",
    "addr:street":"Pas De La Bourse;Hainaut",
    "iso:country":"BE",
    "sg:address":"Pas De La Bourse 20",
    "sg:city":"Charleroi",
    "sg:classifiers":[
        {
            "category":"Restaurant",
            "type":"Food & Drink"
        }
    ],
    "sg:phone":"+32 71 30 59 39",
    "sg:postcode":"6000",
    "sg:province":"Hainaut",
    "wof:name":"L' Argus",
    "wof:placetype":"venue"
},
  "geometry": {"coordinates":[4.4405970573,50.4070167542],"type":"Point"}
}