{
  "type": "Feature",
  "properties": {
    "addr:full":"Rue Large Voie 104 Herstal Li\u00e8ge 4040",
    "addr:housenumber":"104",
    "addr:postcode":"4040",
    "addr:street":"Rue Large Voie",
    "iso:country":"BE",
    "sg:address":"Rue Large Voie 104",
    "sg:city":"Herstal",
    "sg:classifiers":[
        {
            "category":"Professional",
            "subcategory":"Accounting & Tax Preparation",
            "type":"Services"
        }
    ],
    "sg:phone":"+32 4 264 18 61",
    "sg:postcode":"4040",
    "sg:province":"Li\u00e8ge",
    "sg:tags":[
        "accountant"
    ],
    "wof:name":"Bureau Guilleaume Sprl",
    "wof:placetype":"venue"
},
  "geometry": {"coordinates":[5.634718895,50.6669578552],"type":"Point"}
}