{
  "type": "Feature",
  "properties": {
    "addr:full":"Bas Rejet 10 Mont-de-l\u00b4enclus Hainaut 7750",
    "addr:housenumber":"10",
    "addr:postcode":"7750",
    "addr:street":"Bas Rejet;Hainaut",
    "iso:country":"BE",
    "sg:address":"Bas Rejet 10",
    "sg:city":"Mont-de-l\u00b4enclus",
    "sg:classifiers":[
        {
            "category":"Arena",
            "subcategory":"Sports Club",
            "type":"Entertainment"
        }
    ],
    "sg:phone":"+32 69 45 41 82",
    "sg:postcode":"7750",
    "sg:province":"Hainaut",
    "sg:tags":[
        "de"
    ],
    "wof:name":"W.c. Le Rayon De Soleil",
    "wof:placetype":"venue"
},
  "geometry": {"coordinates":[3.4947109222,50.7360305786],"type":"Point"}
}