{
  "type": "Feature",
  "properties": {
    "iso:country":"BE",
    "sg:address":"Achiel Van Ackerplein 2",
    "sg:city":"Brugge",
    "sg:classifiers":[
        {
            "category":"Fast Food",
            "type":"Food & Drink"
        }
    ],
    "sg:phone":"+32 50 33 81 41",
    "sg:postcode":"8000",
    "sg:province":"West-Vlaanderen",
    "sg:tags":[
        "de",
        "restaurant",
        "organisation",
        "\u00c0",
        "catering",
        "emporter",
        "f\u00cates",
        "restaurants"
    ],
    "wof:name":"Restaurant Pottenkijker",
    "wof:placetype":"venue"
},
  "geometry": {"coordinates":[3.2187039852,51.2133865356],"type":"Point"}
}