{
  "type": "Feature",
  "properties": {
    "iso:country":"BE",
    "sg:address":"Deerlijkseweg 240",
    "sg:city":"Waregem",
    "sg:orig_category":"Boucheries",
    "sg:phone":"+32 56 60 17 27",
    "sg:postcode":"8790",
    "sg:province":"West-Vlaanderen",
    "wof:name":"Haerinck",
    "wof:placetype":"venue"
},
  "geometry": {"coordinates":[3.4023430347,50.8688812256],"type":"Point"}
}