{
  "type": "Feature",
  "properties": {
    "iso:country":"BE",
    "sg:address":"Antwerpsestw 107",
    "sg:city":"Oostmalle",
    "sg:classifiers":[
        {
            "category":"Shopping",
            "subcategory":"Computers & Home Electronics",
            "type":"Retail Goods"
        }
    ],
    "sg:phone":"+32 3 312 92 30",
    "sg:postcode":"2390",
    "sg:province":"Antwerpen",
    "sg:tags":[
        "electronic",
        "electrical",
        "equipment"
    ],
    "wof:name":"Get Nv",
    "wof:placetype":"venue"
},
  "geometry": {"coordinates":[4.7325649261,51.3011360168],"type":"Point"}
}