{
  "type": "Feature",
  "properties": {
    "addr:full":"Lamorinierestraat 120 Antwerpen Antwerpen 2018",
    "addr:housenumber":"120",
    "addr:postcode":"2018",
    "addr:street":"Lamorinierestraat",
    "iso:country":"BE",
    "sg:address":"Lamorinierestraat 120",
    "sg:city":"Antwerpen",
    "sg:classifiers":[
        {
            "category":"Banks & Credit Unions",
            "subcategory":"Bank",
            "type":"Services"
        }
    ],
    "sg:phone":"+32 3 230 30 70",
    "sg:postcode":"2018",
    "sg:province":"Antwerpen",
    "sg:tags":[
        "savings-banks"
    ],
    "wof:name":"Focus Verzekeringen Nv",
    "wof:placetype":"venue"
},
  "geometry": {"coordinates":[4.4213857651,51.2048416138],"type":"Point"}
}