{
  "type": "Feature",
  "properties": {
    "addr:full":"Matenstraat 212 Niel Antwerpen 2845",
    "addr:housenumber":"212",
    "addr:postcode":"2845",
    "addr:street":"Matenstraat",
    "iso:country":"BE",
    "sg:address":"Matenstraat 212",
    "sg:city":"Niel",
    "sg:orig_category":"Bouwmaterialen Gh",
    "sg:phone":"+32 3 880 60 60",
    "sg:postcode":"2845",
    "sg:province":"Antwerpen",
    "wof:name":"Reynolds Architectural Systems Belgium Sa-nv",
    "wof:placetype":"venue"
},
  "geometry": {"coordinates":[4.350684166,51.1109886169],"type":"Point"}
}