{
  "type": "Feature",
  "properties": {
    "iso:country":"BE",
    "sg:address":"Alb. Rodenbachplantsoen 100",
    "sg:city":"Turnhout",
    "sg:orig_category":"Dranken",
    "sg:phone":"+32 14 43 02 81",
    "sg:postcode":"2300",
    "sg:province":"Antwerpen",
    "wof:name":"Josephus Dierckx",
    "wof:placetype":"venue"
},
  "geometry": {"coordinates":[4.9388017654,51.303188324],"type":"Point"}
}