{
  "type": "Feature",
  "properties": {
    "iso:country":"BE",
    "sg:address":"Fr. Van Ryhoevelaan 11-15",
    "sg:city":"Gent",
    "sg:orig_category":"Herstelling and restauratie van meubelen Meubelzaken, woning- and keukeninrichting Textiel Verlichti",
    "sg:phone":"+32 9 226 50 39",
    "sg:postcode":"9000",
    "sg:province":"Oost-Vlaanderen",
    "wof:name":"Telstar",
    "wof:placetype":"venue"
},
  "geometry": {"coordinates":[3.708548069,51.0664291382],"type":"Point"}
}