{
  "type": "Feature",
  "properties": {
    "addr:full":"Isabellalei 2 Antwerpen Antwerpen 2018",
    "addr:housenumber":"2",
    "addr:postcode":"2018",
    "addr:street":"Isabellalei",
    "iso:country":"BE",
    "sg:address":"Isabellalei 2",
    "sg:city":"Antwerpen",
    "sg:classifiers":[
        {
            "category":"Professional",
            "subcategory":"Art Services",
            "type":"Services"
        }
    ],
    "sg:phone":"+32 474 48 45 59",
    "sg:postcode":"2018",
    "sg:province":"Antwerpen",
    "sg:tags":[
        "designer",
        "display"
    ],
    "wof:name":"Romonesco H",
    "wof:placetype":"venue"
},
  "geometry": {"coordinates":[4.4147429466,51.2066726685],"type":"Point"}
}