{
  "type": "Feature",
  "properties": {
    "addr:full":"Willem De Croylaan 11b2 Heverlee Vlaams-Brabant 3001",
    "addr:housenumber":"11b2",
    "addr:postcode":"3001",
    "addr:street":"Willem De Croylaan",
    "iso:country":"BE",
    "sg:address":"Willem De Croylaan 11b2",
    "sg:city":"Heverlee",
    "sg:orig_category":"Emission Spectrometers",
    "sg:phone":"+32 16 20 83 54",
    "sg:postcode":"3001",
    "sg:province":"Vlaams-Brabant",
    "wof:name":"Anatec Nv",
    "wof:placetype":"venue"
},
  "geometry": {"coordinates":[4.684899807,50.8606796265],"type":"Point"}
}