{
  "type": "Feature",
  "properties": {
    "iso:country":"BE",
    "sg:address":"Molenstraat 209",
    "sg:city":"Kruibeke",
    "sg:orig_category":"Chaussures",
    "sg:phone":"+32 3 774 43 24",
    "sg:postcode":"9150",
    "sg:province":"Oost-Vlaanderen",
    "wof:name":"Sabine",
    "wof:placetype":"venue"
},
  "geometry": {"coordinates":[4.3038377762,51.1765785217],"type":"Point"}
}