{
  "type": "Feature",
  "properties": {
    "iso:country":"BE",
    "sg:address":"Steenvoordestraat 37",
    "sg:city":"Poperinge",
    "sg:orig_category":"Huishoudapparaten, televisies and radio's Telecommunicatieapparaten",
    "sg:phone":"+32 57 38 86 29",
    "sg:postcode":"8979",
    "wof:name":"Careye",
    "wof:placetype":"venue"
},
  "geometry": {"coordinates":[2.7263898849,50.8555984497],"type":"Point"}
}