{
  "type": "Feature",
  "properties": {
    "iso:country":"BE",
    "sg:address":"Rue Belle Vue 5",
    "sg:city":"Li\u00e8ge 1 (bressoux)",
    "sg:classifiers":[
        {
            "category":"Professional",
            "subcategory":"Business Services",
            "type":"Services"
        }
    ],
    "sg:phone":"+32 4 343 93 26",
    "sg:postcode":"4020",
    "sg:province":"Li\u00e8ge",
    "sg:tags":[
        "automobile",
        "-",
        "assessor"
    ],
    "wof:name":"Georges E",
    "wof:placetype":"venue"
},
  "geometry": {"coordinates":[5.5971961021,50.6373596191],"type":"Point"}
}