{
  "type": "Feature",
  "properties": {
    "addr:full":"Rue Fran\u00c7ois-hittelet 57 Jemeppe-sur-sambre Namur 5190",
    "addr:housenumber":"57",
    "addr:postcode":"5190",
    "addr:street":"Rue Franc\u0327Ois-Hittelet",
    "iso:country":"BE",
    "sg:address":"Rue Fran\u00c7ois-hittelet 57",
    "sg:city":"Jemeppe-sur-sambre",
    "sg:orig_category":"Elektrische installaties voor woningen",
    "sg:phone":"+32 71 78 74 66",
    "sg:postcode":"5190",
    "sg:province":"Namur",
    "wof:name":"Philippe Vandeput",
    "wof:placetype":"venue"
},
  "geometry": {"coordinates":[4.6603617668,50.4548568726],"type":"Point"}
}