{
  "type": "Feature",
  "properties": {
    "addr:full":"Koningin Astridlaan 57 Sint-niklaas Oost-Vlaanderen 9100",
    "addr:housenumber":"57",
    "addr:postcode":"9100",
    "addr:street":"Koningin Astridlaan",
    "iso:country":"BE",
    "sg:address":"Koningin Astridlaan 57",
    "sg:city":"Sint-niklaas",
    "sg:classifiers":[
        {
            "category":"Organizations",
            "subcategory":"Community Association",
            "type":"Services"
        }
    ],
    "sg:phone":"+32 3 778 05 11",
    "sg:postcode":"9100",
    "sg:province":"Oost-Vlaanderen",
    "sg:tags":[
        "de",
        "h\u00d4tels",
        "restaurant",
        "food",
        "organisation",
        "\u00c0",
        "fast",
        "catering",
        "emporter",
        "f\u00cates",
        "restaurants"
    ],
    "wof:name":"Hotel Serwir",
    "wof:placetype":"venue"
},
  "geometry": {"coordinates":[4.1535577774,51.1556472778],"type":"Point"}
}