{
  "type": "Feature",
  "properties": {
    "iso:country":"BE",
    "sg:address":"Avenue Van Volxem 97",
    "sg:city":"Vorst/forest",
    "sg:orig_category":"Entretien and r\u00e9parations de voitures. V\u00e9hicules automobiles",
    "sg:phone":"+32 2 344 05 26",
    "sg:postcode":"1190",
    "sg:province":"Bruxelles-Capitale",
    "wof:name":"Delta Motors",
    "wof:placetype":"venue"
},
  "geometry": {"coordinates":[4.3255209923,50.8164558411],"type":"Point"}
}