{
  "type": "Feature",
  "properties": {
    "iso:country":"BE",
    "sg:address":"Leopold Ii-laan 2",
    "sg:city":"De Haan",
    "sg:classifiers":[
        {
            "category":"Fast Food",
            "type":"Food & Drink"
        }
    ],
    "sg:phone":"+32 50 41 38 87",
    "sg:postcode":"8420",
    "sg:province":"West-Vlaanderen",
    "sg:tags":[
        "meeneem",
        "restaurant"
    ],
    "wof:name":"Restaurant Piccadilly",
    "wof:placetype":"venue"
},
  "geometry": {"coordinates":[3.0777609348,51.3004074097],"type":"Point"}
}