{
  "type": "Feature",
  "properties": {
    "iso:country":"BE",
    "sg:address":"Chauss\u00c9e De Bruxelles 185",
    "sg:city":"Waterloo (grand)",
    "sg:orig_category":"Dameskledingzaken",
    "sg:phone":"+32 2 351 57 98",
    "sg:postcode":"1410",
    "sg:province":"Brabant Wallon",
    "wof:name":"Cassis",
    "wof:placetype":"venue"
},
  "geometry": {"coordinates":[4.398501873,50.7165298462],"type":"Point"}
}