{
  "type": "Feature",
  "properties": {
    "addr:full":"Rue De Trazegnies 500 Charleroi (monceau-sur-sambre) Hainaut 6031",
    "addr:housenumber":"500",
    "addr:postcode":"6031",
    "addr:street":"Rue De Trazegnies",
    "iso:country":"BE",
    "sg:address":"Rue De Trazegnies 500",
    "sg:city":"Charleroi (monceau-sur-sambre)",
    "sg:classifiers":[
        {
            "category":"Home & Garden",
            "subcategory":"Garden Supply",
            "type":"Retail Goods"
        }
    ],
    "sg:postcode":"6031",
    "sg:province":"Hainaut",
    "sg:tags":[
        "equipment",
        "playground"
    ],
    "wof:name":"All Play Trampolines",
    "wof:placetype":"venue"
},
  "geometry": {"coordinates":[5.2323260307,51.3734169006],"type":"Point"}
}