{
  "type": "Feature",
  "properties": {
    "addr:full":"Torhoutsesteenweg 122 Oostende West-Vlaanderen 8400",
    "addr:housenumber":"122",
    "addr:postcode":"8400",
    "addr:street":"Torhoutsesteenweg",
    "iso:country":"BE",
    "sg:address":"Torhoutsesteenweg 122",
    "sg:city":"Oostende",
    "sg:orig_category":"Opticiens",
    "sg:phone":"+32 59 80 20 86",
    "sg:postcode":"8400",
    "sg:province":"West-Vlaanderen",
    "wof:name":"Jan Senave",
    "wof:placetype":"venue"
},
  "geometry": {"coordinates":[2.9086151123,51.2218208313],"type":"Point"}
}