{
  "type": "Feature",
  "properties": {
    "iso:country":"BE",
    "sg:address":"Bosterhoutstraat 9",
    "sg:city":"Meulebeke",
    "sg:orig_category":"Groententeelt",
    "sg:phone":"+32 51 48 89 79",
    "sg:postcode":"8760",
    "sg:province":"West-Vlaanderen",
    "wof:name":"Franky Neirynck",
    "wof:placetype":"venue"
},
  "geometry": {"coordinates":[3.2918429375,50.9681816101],"type":"Point"}
}