{
  "type": "Feature",
  "properties": {
    "addr:full":"Lombardsijdestraat 3 Nieuwpoort West-Vlaanderen 8620",
    "addr:housenumber":"3",
    "addr:postcode":"8620",
    "addr:street":"Lombardsijdestraat",
    "iso:country":"BE",
    "sg:address":"Lombardsijdestraat 3",
    "sg:city":"Nieuwpoort",
    "sg:orig_category":"Antiek",
    "sg:phone":"+32 58 24 34 42",
    "sg:postcode":"8620",
    "sg:province":"West-Vlaanderen",
    "wof:name":"Maru",
    "wof:placetype":"venue"
},
  "geometry": {"coordinates":[2.722151041,51.1511611938],"type":"Point"}
}