{
  "type": "Feature",
  "properties": {
    "iso:country":"BE",
    "sg:address":"Rue Du Chenai 64",
    "sg:city":"Daverdisse",
    "sg:orig_category":"Textiel",
    "sg:phone":"+32 61 51 19 13",
    "sg:postcode":"6929",
    "sg:province":"Luxembourg",
    "wof:name":"Roland-clair-mode",
    "wof:placetype":"venue"
},
  "geometry": {"coordinates":[5.0874562263,49.9772834778],"type":"Point"}
}