{
  "type": "Feature",
  "properties": {
    "addr:full":"Rue D'aremberg 54 Doische Namur 5680",
    "addr:housenumber":"54",
    "addr:postcode":"5680",
    "addr:street":"Rue D'Aremberg",
    "iso:country":"BE",
    "sg:address":"Rue D'aremberg 54",
    "sg:city":"Doische",
    "sg:orig_category":"Dakwerken",
    "sg:phone":"+32 82 67 82 91",
    "sg:postcode":"5680",
    "sg:province":"Namur",
    "wof:name":"J.p. Guislain",
    "wof:placetype":"venue"
},
  "geometry": {"coordinates":[4.7126250267,50.1315727234],"type":"Point"}
}