{
  "type": "Feature",
  "properties": {
    "iso:country":"BE",
    "sg:address":"Chauss\u00e9e De Lodelinsart 208",
    "sg:city":"Charleroi (gilly)",
    "sg:classifiers":[
        {
            "category":"Retail",
            "subcategory":"Repair Shop",
            "type":"Services"
        }
    ],
    "sg:phone":"+32 71 41 43 13",
    "sg:postcode":"6060",
    "sg:province":"Hainaut",
    "sg:tags":[
        "-",
        "clothing",
        "alteration"
    ],
    "wof:name":"De A Recoudre (le)",
    "wof:placetype":"venue"
},
  "geometry": {"coordinates":[4.4880981445,50.4251937866],"type":"Point"}
}