{
  "type": "Feature",
  "properties": {
    "iso:country":"BE",
    "sg:address":"Hoogstraat 1",
    "sg:city":"Balen",
    "sg:orig_category":"Traitements param\u00e9dicaux",
    "sg:phone":"+32 14 30 17 27",
    "sg:postcode":"2491",
    "sg:province":"Antwerpen",
    "wof:name":"K. Wuyts",
    "wof:placetype":"venue"
},
  "geometry": {"coordinates":[5.1495189667,51.1393241882],"type":"Point"}
}