{
  "type": "Feature",
  "properties": {
    "iso:country":"BE",
    "sg:address":"Rue De Nivelles 7",
    "sg:city":"Genappe",
    "sg:orig_category":"Installatie van houten of kunststof schrijnwerk Vloer- and muurbekleding",
    "sg:phone":"+32 67 77 15 93",
    "sg:postcode":"1476",
    "sg:province":"Brabant Wallon",
    "wof:name":"Beauty Home",
    "wof:placetype":"venue"
},
  "geometry": {"coordinates":[4.4143671989,50.5811767578],"type":"Point"}
}