{
  "type": "Feature",
  "properties": {
    "addr:full":"Avenue Du Progr\u00c8s 5 Ans (groot) Li\u00e8ge 4432",
    "addr:housenumber":"5",
    "addr:postcode":"4432",
    "addr:street":"Avenue Du Progre\u0300S;Groot Lie\u0300Ge",
    "iso:country":"BE",
    "sg:address":"Avenue Du Progr\u00c8s 5",
    "sg:city":"Ans (groot)",
    "sg:orig_category":"Quincailleries. Textiles. Rev\u00eatements de sols and murs. Rev\u00eatements pour sols and murs. Peinture. Ec",
    "sg:phone":"+32 4 263 16 62",
    "sg:postcode":"4432",
    "sg:province":"Li\u00e8ge",
    "wof:name":"Heytens",
    "wof:placetype":"venue"
},
  "geometry": {"coordinates":[5.5269970894,50.6727790833],"type":"Point"}
}