{
  "type": "Feature",
  "properties": {
    "addr:full":"Rue Fran\u00c7ois Lorge 54 Namur Namur 5020",
    "addr:housenumber":"54",
    "addr:postcode":"5020",
    "addr:street":"Rue Franc\u0327Ois Lorge",
    "iso:country":"BE",
    "sg:address":"Rue Fran\u00c7ois Lorge 54",
    "sg:city":"Namur",
    "sg:orig_category":"Rusthuizen and serviceflats",
    "sg:phone":"+32 81 21 31 45",
    "sg:postcode":"5020",
    "sg:province":"Namur",
    "wof:name":"Home Les Ombrelles",
    "wof:placetype":"venue"
},
  "geometry": {"coordinates":[4.8691458702,50.481010437],"type":"Point"}
}