{
  "type": "Feature",
  "properties": {
    "iso:country":"BE",
    "sg:address":"Mechelsesteenweg 270",
    "sg:city":"Willebroek",
    "sg:orig_category":"Loodgieterij, verwarming and sanitaire installaties",
    "sg:phone":"+32 3 886 53 69",
    "sg:postcode":"2830",
    "sg:province":"Antwerpen",
    "wof:name":"Aerts",
    "wof:placetype":"venue"
},
  "geometry": {"coordinates":[4.3726520538,51.0504722595],"type":"Point"}
}