{
  "type": "Feature",
  "properties": {
    "iso:country":"BE",
    "sg:address":"Chauss\u00c9e D'ixelles 48",
    "sg:city":"Elsene/ixelles",
    "sg:orig_category":"Pain, p\u00e2tisseries and confiseries",
    "sg:phone":"+32 2 502 74 38",
    "sg:postcode":"1050",
    "sg:province":"Bruxelles-Capitale",
    "wof:name":"Boulangerie & Caf\u00c9 Fran\u00c7ais",
    "wof:placetype":"venue"
},
  "geometry": {"coordinates":[4.3627018929,50.8369293213],"type":"Point"}
}