{
  "type": "Feature",
  "properties": {
    "addr:full":"Stwg. Op Vilvoorde 252 Opwijk Vlaams-Brabant 1745",
    "addr:housenumber":"252",
    "addr:postcode":"1745",
    "addr:street":"Op Vilvoorde",
    "iso:country":"BE",
    "sg:address":"Stwg. Op Vilvoorde 252",
    "sg:city":"Opwijk",
    "sg:classifiers":[
        {
            "category":"Professional",
            "type":"Services"
        }
    ],
    "sg:phone":"+32 52 35 58 46",
    "sg:postcode":"1745",
    "sg:province":"Vlaams-Brabant",
    "sg:tags":[
        "transport"
    ],
    "wof:name":"Plumes B.v.b.a.",
    "wof:placetype":"venue"
},
  "geometry": {"coordinates":[4.1859798431,50.9557113647],"type":"Point"}
}