{
  "type": "Feature",
  "properties": {
    "iso:country":"BE",
    "sg:address":"Rue Hans Pierre 33",
    "sg:city":"Charleroi (jumet)",
    "sg:classifiers":[
        {
            "category":"Communications",
            "subcategory":"Film & Video Production",
            "type":"Services"
        }
    ],
    "sg:phone":"+32 71 35 80 97",
    "sg:postcode":"6040",
    "sg:province":"Hainaut",
    "sg:tags":[
        "sound",
        "recording",
        "studio"
    ],
    "wof:name":"Picarella Claudio",
    "wof:placetype":"venue"
},
  "geometry": {"coordinates":[4.4405322075,50.4366722107],"type":"Point"}
}