{
  "type": "Feature",
  "properties": {
    "iso:country":"BE",
    "sg:address":"Place Prume 6",
    "sg:city":"Stavelot",
    "sg:classifiers":[
        {
            "category":"Insurance",
            "subcategory":"Insurance Agent",
            "type":"Services"
        }
    ],
    "sg:phone":"+32 80 86 24 80",
    "sg:postcode":"4970",
    "sg:province":"Li\u00e8ge",
    "sg:tags":[
        "verzekeringsmakelaars",
        "expert"
    ],
    "wof:name":"Fe. Lejeune-wetz-lemaire",
    "wof:placetype":"venue"
},
  "geometry": {"coordinates":[5.9312992096,50.3950614929],"type":"Point"}
}