{
  "type": "Feature",
  "properties": {
    "iso:country":"BE",
    "sg:address":"Lichtelarestraat 63",
    "sg:city":"Lochristi",
    "sg:orig_category":"Bloemen and planten Gh",
    "sg:phone":"+32 9 355 65 09",
    "sg:postcode":"9080",
    "sg:province":"Oost-Vlaanderen",
    "wof:name":"De Wilde-blomme",
    "wof:placetype":"venue"
},
  "geometry": {"coordinates":[3.8169651031,51.0854148865],"type":"Point"}
}