{
  "type": "Feature",
  "properties": {
    "iso:country":"BE",
    "sg:address":"De Schiervellaan 12ba",
    "sg:city":"Hasselt",
    "sg:orig_category":"M\u00e9decins and sp\u00e9cialistes",
    "sg:phone":"+32 11 22 17 07",
    "sg:postcode":"3500",
    "sg:province":"Limburg",
    "wof:name":"H. Nolens",
    "wof:placetype":"venue"
},
  "geometry": {"coordinates":[5.3322582245,50.9300727844],"type":"Point"}
}