{
  "type": "Feature",
  "properties": {
    "addr:full":"Baron De P\u00e9lichystraat 42 Izegem West-Vlaanderen 8870",
    "addr:housenumber":"42",
    "addr:postcode":"8870",
    "addr:street":"Baron De Pe\u0301Lichystraat",
    "iso:country":"BE",
    "sg:address":"Baron De P\u00e9lichystraat 42",
    "sg:city":"Izegem",
    "sg:classifiers":[
        {
            "category":"Personal",
            "subcategory":"Beauty Salon",
            "type":"Services"
        }
    ],
    "sg:phone":"+32 51 31 45 34",
    "sg:postcode":"8870",
    "sg:province":"West-Vlaanderen",
    "wof:name":"Aphrodite",
    "wof:placetype":"venue"
},
  "geometry": {"coordinates":[3.2120699883,50.9164428711],"type":"Point"}
}