{
  "type": "Feature",
  "properties": {
    "iso:country":"BE",
    "sg:address":"Vekenstraat 9",
    "sg:city":"Genk",
    "sg:orig_category":"Gespecialiseerde residenti\u00eble bouw",
    "sg:phone":"+32 89 38 33 96",
    "sg:postcode":"3600",
    "sg:province":"Limburg",
    "wof:name":"Alfons Creemers",
    "wof:placetype":"venue"
},
  "geometry": {"coordinates":[5.4915699959,51.0099601746],"type":"Point"}
}