{
  "type": "Feature",
  "properties": {
    "addr:full":"Rue Gabrielle 39 Bruxelles (uccle) Bruxelles-Capitale 1180",
    "addr:housenumber":"39",
    "addr:postcode":"1180",
    "addr:street":"Rue Gabrielle",
    "iso:country":"BE",
    "sg:address":"Rue Gabrielle 39",
    "sg:city":"Bruxelles (uccle)",
    "sg:classifiers":[
        {
            "category":"Real Estate",
            "subcategory":"Architect",
            "type":"Services"
        }
    ],
    "sg:phone":"+32 2 346 88 86",
    "sg:postcode":"1180",
    "sg:province":"Bruxelles-Capitale",
    "wof:name":"Melviez G",
    "wof:placetype":"venue"
},
  "geometry": {"coordinates":[4.3593277931,50.8140335083],"type":"Point"}
}