{
  "type": "Feature",
  "properties": {
    "addr:full":"Rue Des Vergers 3a Ottignies-louvain-la-neuve (ottignies) Brabant Wallon 1340",
    "addr:housenumber":"3a",
    "addr:postcode":"1340",
    "addr:street":"Rue Des Vergers",
    "iso:country":"BE",
    "sg:address":"Rue Des Vergers 3a",
    "sg:city":"Ottignies-louvain-la-neuve (ottignies)",
    "sg:classifiers":[
        {
            "category":"Farming",
            "subcategory":"Farm & Veterinary Services",
            "type":"Manufacturing & Wholesale Goods"
        }
    ],
    "sg:phone":"+32 10 41 00 88",
    "sg:postcode":"1340",
    "sg:province":"Brabant Wallon",
    "sg:tags":[
        "agricultural",
        "contractor"
    ],
    "wof:name":"Stiernet P",
    "wof:placetype":"venue"
},
  "geometry": {"coordinates":[4.5426340103,50.6812477112],"type":"Point"}
}