{
  "type": "Feature",
  "properties": {
    "addr:full":"Weg Naar As 168b1 Genk Limburg 3600",
    "addr:housenumber":"168b1",
    "addr:postcode":"3600",
    "addr:street":"Weg Naar As",
    "iso:country":"BE",
    "sg:address":"Weg Naar As 168b1",
    "sg:city":"Genk",
    "sg:orig_category":"Quincailleries. Magasins sp\u00e9cialis\u00e9s. Forge, Moulage and Profilage des M\u00e9taux",
    "sg:phone":"+32 78 71 90 32",
    "sg:postcode":"3600",
    "sg:province":"Limburg",
    "wof:name":"Goris-jans Kachelzaak",
    "wof:placetype":"venue"
},
  "geometry": {"coordinates":[5.5167808533,50.9725761414],"type":"Point"}
}