{
  "type": "Feature",
  "properties": {
    "addr:full":"Veldstraat 91 Houthulst West-Vlaanderen 8650",
    "addr:housenumber":"91",
    "addr:postcode":"8650",
    "addr:street":"Veldstraat",
    "iso:country":"BE",
    "sg:address":"Veldstraat 91",
    "sg:city":"Houthulst",
    "sg:orig_category":"Boucheries",
    "sg:phone":"+32 51 70 39 32",
    "sg:postcode":"8650",
    "sg:province":"West-Vlaanderen",
    "wof:name":"Gilbert Bulcke",
    "wof:placetype":"venue"
},
  "geometry": {"coordinates":[2.9315619469,50.9782981873],"type":"Point"}
}