{
  "type": "Feature",
  "properties": {
    "iso:country":"BE",
    "sg:address":"Rue De La Gare 25",
    "sg:city":"Erquelinnes (solre-sur-sambre)",
    "sg:classifiers":[
        {
            "category":"Health Services",
            "subcategory":"Health Practitioner",
            "type":"Services"
        }
    ],
    "sg:phone":"+32 71 55 80 04",
    "sg:postcode":"6560",
    "sg:province":"Hainaut",
    "sg:tags":[
        "physiotherapist"
    ],
    "wof:name":"Bailly Guy",
    "wof:placetype":"venue"
},
  "geometry": {"coordinates":[4.1577677727,50.3115196228],"type":"Point"}
}