{
  "type": "Feature",
  "properties": {
    "iso:country":"BE",
    "sg:address":"Rue De Luxembourg 44",
    "sg:city":"L\u00e9glise",
    "sg:classifiers":[
        {
            "category":"Bakery",
            "type":"Food & Drink"
        }
    ],
    "sg:phone":"+32 63 43 34 64",
    "sg:postcode":"6860",
    "sg:province":"Luxembourg",
    "sg:tags":[
        "confectioner",
        "baker"
    ],
    "wof:name":"Epi Dor\u00e9 (l')",
    "wof:placetype":"venue"
},
  "geometry": {"coordinates":[5.5343770981,49.7997093201],"type":"Point"}
}