{
  "type": "Feature",
  "properties": {
    "addr:full":"Genits 8 Meeuwen-gruitrode Limburg 3670",
    "addr:housenumber":"8",
    "addr:postcode":"3670",
    "addr:street":"Genits",
    "iso:country":"BE",
    "sg:address":"Genits 8",
    "sg:city":"Meeuwen-gruitrode",
    "sg:orig_category":"Bloemen and planten Huisdieren and benodigdheden Royal Canin Tuinbenodigdheden",
    "sg:phone":"+32 11 79 20 88",
    "sg:postcode":"3670",
    "sg:province":"Limburg",
    "wof:name":"Garden Center. Paesen Indekeu Marc",
    "wof:placetype":"venue"
},
  "geometry": {"coordinates":[5.5253100395,51.0909042358],"type":"Point"}
}