{
  "type": "Feature",
  "properties": {
    "iso:country":"BE",
    "sg:address":"Rue Gr\u00c9goire N\u00c9lis 16",
    "sg:city":"Jodoigne",
    "sg:classifiers":[
        {
            "category":"Insurance",
            "subcategory":"Insurance Agent",
            "type":"Services"
        }
    ],
    "sg:phone":"+32 10 81 40 62",
    "sg:postcode":"1370",
    "sg:province":"Brabant Wallon",
    "sg:tags":[
        "verzekeringsmakelaars",
        "expert"
    ],
    "wof:name":"Bureau Laverdisse",
    "wof:placetype":"venue"
},
  "geometry": {"coordinates":[4.8682160378,50.723526001],"type":"Point"}
}