{
  "type": "Feature",
  "properties": {
    "iso:country":"BE",
    "sg:address":"Withuislaan 40",
    "sg:city":"Dilbeek",
    "sg:orig_category":"Installation \u00e9lectrique r\u00e9sidentielle",
    "sg:phone":"+32 2 466 33 99",
    "sg:postcode":"1700",
    "sg:province":"Vlaams-Brabant",
    "wof:name":"Jacqval",
    "wof:placetype":"venue"
},
  "geometry": {"coordinates":[4.244207859,50.8613014221],"type":"Point"}
}