{
  "type": "Feature",
  "properties": {
    "iso:country":"BE",
    "sg:address":"Bosstraat 24b6",
    "sg:city":"Maaseik",
    "sg:orig_category":"Bijouteries and horlogeries",
    "sg:phone":"+32 89 56 41 21",
    "sg:postcode":"3680",
    "sg:province":"Limburg",
    "wof:name":"Residence",
    "wof:placetype":"venue"
},
  "geometry": {"coordinates":[5.7896099091,51.0950164795],"type":"Point"}
}