{
  "type": "Feature",
  "properties": {
    "addr:full":"Voskenslaan 99 Gent Oost-Vlaanderen 9000",
    "addr:housenumber":"99",
    "addr:postcode":"9000",
    "addr:street":"Voskenslaan;Oost-Vlaanderen",
    "iso:country":"BE",
    "sg:address":"Voskenslaan 99",
    "sg:city":"Gent",
    "sg:orig_category":"M\u00e9decins and sp\u00e9cialistes",
    "sg:phone":"+32 9 222 38 60",
    "sg:postcode":"9000",
    "sg:province":"Oost-Vlaanderen",
    "wof:name":"Jan Poelman",
    "wof:placetype":"venue"
},
  "geometry": {"coordinates":[3.7078680992,51.0324897766],"type":"Point"}
}