{
  "type": "Feature",
  "properties": {
    "addr:full":"Gentsesteenweg 325 Asse Vlaams-Brabant 1730",
    "addr:housenumber":"325",
    "addr:postcode":"1730",
    "addr:street":"Gentsesteenweg",
    "iso:country":"BE",
    "sg:address":"Gentsesteenweg 325",
    "sg:city":"Asse",
    "sg:orig_category":"Installatie van houten of kunststof schrijnwerk",
    "sg:phone":"+32 2 452 92 45",
    "sg:postcode":"1730",
    "sg:province":"Vlaams-Brabant",
    "wof:name":"De Ridder T. & Zn",
    "wof:placetype":"venue"
},
  "geometry": {"coordinates":[4.1570219994,50.9170722961],"type":"Point"}
}