{
  "type": "Feature",
  "properties": {
    "iso:country":"BE",
    "sg:address":"Fonds-de-l'eau 20",
    "sg:city":"Couvin",
    "sg:orig_category":"Boekhouders",
    "sg:phone":"+32 60 34 59 71",
    "sg:postcode":"5660",
    "sg:province":"Namur",
    "wof:name":"J. Paternoster",
    "wof:placetype":"venue"
},
  "geometry": {"coordinates":[4.4941368103,50.0329933167],"type":"Point"}
}