{
  "type": "Feature",
  "properties": {
    "addr:full":"Bogaert 48 Wichelen Oost-Vlaanderen 9260",
    "addr:housenumber":"48",
    "addr:postcode":"9260",
    "addr:street":"Bogaert",
    "iso:country":"BE",
    "sg:address":"Bogaert 48",
    "sg:city":"Wichelen",
    "sg:orig_category":"Rundveehouders",
    "sg:phone":"+32 52 42 27 37",
    "sg:postcode":"9260",
    "sg:province":"Oost-Vlaanderen",
    "wof:name":"Daniel Eeckhaudt",
    "wof:placetype":"venue"
},
  "geometry": {"coordinates":[3.9905049801,50.9974212646],"type":"Point"}
}