{
  "type": "Feature",
  "properties": {
    "iso:country":"BE",
    "sg:address":"Sint-amandsplein 15a",
    "sg:city":"Grimbergen (strombeek-bever)",
    "sg:classifiers":[
        {
            "category":"Food & Beverages",
            "subcategory":"Groceries & Convenience Stores",
            "type":"Retail Goods"
        }
    ],
    "sg:phone":"+32 2 267 49 69",
    "sg:postcode":"1853",
    "sg:province":"Vlaams-Brabant",
    "sg:tags":[
        "grocer"
    ],
    "wof:name":"Dino Dilara Sprl",
    "wof:placetype":"venue"
},
  "geometry": {"coordinates":[4.3549771309,50.910030365],"type":"Point"}
}