{
  "type": "Feature",
  "properties": {
    "iso:country":"BE",
    "sg:address":"Rue De La Sylle 39",
    "sg:city":"Silly",
    "sg:orig_category":"Architecten",
    "sg:phone":"+32 68 55 17 00",
    "sg:postcode":"7830",
    "sg:province":"Hainaut",
    "wof:name":"Olivier Lesage",
    "wof:placetype":"venue"
},
  "geometry": {"coordinates":[3.8952579498,50.6661224365],"type":"Point"}
}