{
  "type": "Feature",
  "properties": {
    "addr:full":"Avenue Edmond Parmentier 20 Bruxelles (woluwe-saint-pierre) Bruxelles-Capitale 1150",
    "addr:housenumber":"20",
    "addr:postcode":"1150",
    "addr:street":"Avenue Edmond Parmentier",
    "iso:country":"BE",
    "sg:address":"Avenue Edmond Parmentier 20",
    "sg:city":"Bruxelles (woluwe-saint-pierre)",
    "sg:classifiers":[
        {
            "category":"Professional",
            "type":"Services"
        }
    ],
    "sg:phone":"+32 2 771 91 41",
    "sg:postcode":"1150",
    "sg:province":"Bruxelles-Capitale",
    "sg:tags":[
        "surveyor",
        "-",
        "valuer"
    ],
    "wof:name":"Braconnier R R",
    "wof:placetype":"venue"
},
  "geometry": {"coordinates":[4.4370040894,50.8315048218],"type":"Point"}
}