{
  "type": "Feature",
  "properties": {
    "addr:full":"Rue Lambert Fortune 75 Wavre Brabant Wallon 1300",
    "addr:housenumber":"75;1300",
    "addr:street":"Rue Lambert Fortune",
    "iso:country":"BE",
    "sg:address":"Rue Lambert Fortune 75",
    "sg:city":"Wavre",
    "sg:classifiers":[
        {
            "category":"Communications",
            "type":"Services"
        }
    ],
    "sg:phone":"+32 10 81 65 86",
    "sg:postcode":"1300",
    "sg:province":"Brabant Wallon",
    "sg:tags":[
        "translator"
    ],
    "wof:name":"Medi-services Sprl",
    "wof:placetype":"venue"
},
  "geometry": {"coordinates":[4.608643055,50.717502594],"type":"Point"}
}