{
  "type": "Feature",
  "properties": {
    "iso:country":"BE",
    "sg:address":"Rue Du Parc Saint-roch 13",
    "sg:city":"Couvin",
    "sg:classifiers":[
        {
            "category":"Home & Garden",
            "subcategory":"Carpets & Floor Coverings",
            "type":"Retail Goods"
        }
    ],
    "sg:phone":"+32 60 34 40 73",
    "sg:postcode":"5660",
    "sg:province":"Namur",
    "sg:tags":[
        "house",
        "prefabricated"
    ],
    "wof:name":"Les Ateliers Hennequin Sprl",
    "wof:placetype":"venue"
},
  "geometry": {"coordinates":[4.4968800545,50.0538597107],"type":"Point"}
}