{
  "type": "Feature",
  "properties": {
    "addr:full":"Kattenbroekstraat 42 Aalst (moorsel) Oost-Vlaanderen 9310",
    "addr:housenumber":"42",
    "addr:postcode":"9310",
    "addr:street":"Kattenbroekstraat;Moorsel Oost-Vlaanderen",
    "iso:country":"BE",
    "sg:address":"Kattenbroekstraat 42",
    "sg:city":"Aalst (moorsel)",
    "sg:classifiers":[
        {
            "category":"Food & Beverages",
            "subcategory":"Meat & Fish",
            "type":"Retail Goods"
        }
    ],
    "sg:phone":"+32 53 21 33 23",
    "sg:postcode":"9310",
    "sg:province":"Oost-Vlaanderen",
    "sg:tags":[
        "poultry",
        "whol",
        "game",
        "-"
    ],
    "wof:name":"Van Den Eede R",
    "wof:placetype":"venue"
},
  "geometry": {"coordinates":[4.0862870216,50.9566116333],"type":"Point"}
}