{
  "type": "Feature",
  "properties": {
    "addr:full":"Kauwplasstraat 39 Halen Limburg 3545",
    "addr:housenumber":"39",
    "addr:postcode":"3545",
    "addr:street":"Kauwplasstraat",
    "iso:country":"BE",
    "sg:address":"Kauwplasstraat 39",
    "sg:city":"Halen",
    "sg:classifiers":[
        {
            "category":"Building & Trades",
            "subcategory":"Cleaning & Sanitation",
            "type":"Services"
        }
    ],
    "sg:phone":"+32 13 44 47 00",
    "sg:postcode":"3545",
    "sg:province":"Limburg",
    "sg:tags":[
        "fa\u00e7ade",
        "maintenance"
    ],
    "wof:name":"Madriema",
    "wof:placetype":"venue"
},
  "geometry": {"coordinates":[5.074382782,50.9404067993],"type":"Point"}
}