{
  "type": "Feature",
  "properties": {
    "addr:full":"Ch De Waterloo 938 Uccle Bruxelles-Capitale 1180",
    "addr:housenumber":"938",
    "addr:postcode":"1180",
    "addr:street":"Ch De Waterloo",
    "iso:country":"BE",
    "sg:address":"Ch De Waterloo 938",
    "sg:city":"Uccle",
    "sg:classifiers":[
        {
            "category":"Professional",
            "subcategory":"Business Services",
            "type":"Services"
        }
    ],
    "sg:phone":"+32 2 374 12 29",
    "sg:postcode":"1180",
    "sg:province":"Bruxelles-Capitale",
    "sg:tags":[
        "training",
        "advice"
    ],
    "wof:name":"P H M Computing Sprl",
    "wof:placetype":"venue"
},
  "geometry": {"coordinates":[4.3729271889,50.8030967712],"type":"Point"}
}