{
  "type": "Feature",
  "properties": {
    "addr:full":"Georges Henrilaan 156 Sint-lambrechts-woluwe/woluwe-saint-lambert Bruxelles-Capitale 1200",
    "addr:housenumber":"156;/",
    "addr:postcode":"1200",
    "addr:street":"Henrilaan;Sint-Lambrechts-Woluwe",
    "iso:country":"BE",
    "sg:address":"Georges Henrilaan 156",
    "sg:city":"Sint-lambrechts-woluwe/woluwe-saint-lambert",
    "sg:orig_category":"Installatie van metalen schrijnwerk Textiel Verlichting and huishoudartikelen",
    "sg:phone":"+32 2 772 00 07",
    "sg:postcode":"1200",
    "sg:province":"Bruxelles-Capitale",
    "wof:name":"L'atelier Du Store",
    "wof:placetype":"venue"
},
  "geometry": {"coordinates":[4.4180459976,50.8456573486],"type":"Point"}
}