{
  "type": "Feature",
  "properties": {
    "addr:full":"Rue Z\u00e9nobe Gramme 2 Waremme Li\u00e8ge 4300",
    "addr:housenumber":"2",
    "addr:postcode":"4300",
    "addr:street":"Rue Ze\u0301Nobe Gramme",
    "iso:country":"BE",
    "sg:address":"Rue Z\u00e9nobe Gramme 2",
    "sg:city":"Waremme",
    "sg:classifiers":[
        {
            "category":"Personal",
            "subcategory":"Beauty Salon",
            "type":"Services"
        }
    ],
    "sg:phone":"+32 19 33 22 28",
    "sg:postcode":"4300",
    "sg:province":"Li\u00e8ge",
    "sg:tags":[
        "lady",
        "-",
        "hairdressing"
    ],
    "wof:name":"New Hair",
    "wof:placetype":"venue"
},
  "geometry": {"coordinates":[5.2526478767,50.6959533691],"type":"Point"}
}