{
  "type": "Feature",
  "properties": {
    "iso:country":"BE",
    "sg:address":"Mijlstraat 238",
    "sg:city":"Duffel",
    "sg:orig_category":"Jardinage. Construction de rev\u00eatements and voies d'acc\u00e8s r\u00e9sidentiels",
    "sg:phone":"+32 15 31 67 34",
    "sg:postcode":"2570",
    "sg:province":"Antwerpen",
    "wof:name":"Wilfried Neutjens",
    "wof:placetype":"venue"
},
  "geometry": {"coordinates":[4.5483150482,51.1037063599],"type":"Point"}
}