{
  "type": "Feature",
  "properties": {
    "iso:country":"BE",
    "sg:address":"Leernsesteenweg 228",
    "sg:city":"Deinze",
    "sg:orig_category":"Imprimeries and copyshops",
    "sg:phone":"+32 9 282 22 86",
    "sg:postcode":"9800",
    "sg:province":"Oost-Vlaanderen",
    "wof:name":"Drukkerij De Meester",
    "wof:placetype":"venue"
},
  "geometry": {"coordinates":[3.5850889683,51.0140266418],"type":"Point"}
}