{
  "type": "Feature",
  "properties": {
    "iso:country":"BE",
    "sg:address":"Satenrozen 8",
    "sg:city":"Kontich",
    "sg:classifiers":[
        {
            "category":"Autos & Motor Vehicles",
            "subcategory":"Motorcycle Sales",
            "type":"Retail Goods"
        }
    ],
    "sg:phone":"+32 3 450 17 11",
    "sg:postcode":"2550",
    "sg:province":"Antwerpen",
    "sg:tags":[
        "motorbike"
    ],
    "wof:name":"Alcopa Two Wheels",
    "wof:placetype":"venue"
},
  "geometry": {"coordinates":[4.4137301445,51.1232795715],"type":"Point"}
}