{
  "type": "Feature",
  "properties": {
    "iso:country":"BE",
    "sg:address":"Past. Boelstraat 14",
    "sg:city":"Temse",
    "sg:orig_category":"V\u00e9hicules automobiles. Entretien and r\u00e9parations de voitures",
    "sg:phone":"+32 3 771 01 22",
    "sg:postcode":"9140",
    "sg:province":"Oost-Vlaanderen",
    "wof:name":"Carrosserie Meeus",
    "wof:placetype":"venue"
},
  "geometry": {"coordinates":[4.2115092278,51.1271820068],"type":"Point"}
}