{
  "type": "Feature",
  "properties": {
    "addr:full":"Place De Plancenoit 21 Lasne Brabant Wallon 1380",
    "addr:housenumber":"21",
    "addr:postcode":"1380",
    "addr:street":"Place De Plancenoit",
    "iso:country":"BE",
    "sg:address":"Place De Plancenoit 21",
    "sg:city":"Lasne",
    "sg:orig_category":"M\u00e9decins and sp\u00e9cialistes",
    "sg:phone":"+32 2 633 27 70",
    "sg:postcode":"1380",
    "sg:province":"Brabant Wallon",
    "wof:name":"V\u00c9ronique Van Bol",
    "wof:placetype":"venue"
},
  "geometry": {"coordinates":[4.4307742119,50.6605453491],"type":"Point"}
}