{
  "type": "Feature",
  "properties": {
    "iso:country":"BE",
    "sg:address":"Hannekensboslaan 21",
    "sg:city":"Overijse",
    "sg:classifiers":[
        {
            "category":"Professional",
            "subcategory":"Accounting & Tax Preparation",
            "type":"Services"
        }
    ],
    "sg:phone":"+32 2 687 42 99",
    "sg:postcode":"3090",
    "sg:province":"Vlaams-Brabant",
    "sg:tags":[
        "bookkeeper"
    ],
    "wof:name":"De Grand Ry B",
    "wof:placetype":"venue"
},
  "geometry": {"coordinates":[4.544962883,50.763458252],"type":"Point"}
}