{
  "type": "Feature",
  "properties": {
    "iso:country":"BE",
    "sg:address":"Grand'rue 80",
    "sg:city":"Mons",
    "sg:orig_category":"Cr\u00e9meries",
    "sg:phone":"+32 65 33 92 27",
    "sg:postcode":"7000",
    "sg:province":"Hainaut",
    "wof:name":"Scouflaire",
    "wof:placetype":"venue"
},
  "geometry": {"coordinates":[3.952878952,50.4551277161],"type":"Point"}
}