{
  "type": "Feature",
  "properties": {
    "iso:country":"BE",
    "sg:address":"Naarstigheidstraat 172",
    "sg:city":"Aalst",
    "sg:orig_category":"Banken and kredietinstellingen",
    "sg:phone":"+32 53 77 21 00",
    "sg:postcode":"9300",
    "sg:province":"Oost-Vlaanderen",
    "wof:name":"Fortis",
    "wof:placetype":"venue"
},
  "geometry": {"coordinates":[4.0175590515,50.9414634705],"type":"Point"}
}