{
  "type": "Feature",
  "properties": {
    "addr:full":"Rue De Lens 44 Soignies Hainaut 7061",
    "addr:housenumber":"44",
    "addr:postcode":"7061",
    "addr:street":"Rue De Lens",
    "iso:country":"BE",
    "sg:address":"Rue De Lens 44",
    "sg:city":"Soignies",
    "sg:classifiers":[
        {
            "category":"Insurance",
            "subcategory":"Insurance Agent",
            "type":"Services"
        }
    ],
    "sg:phone":"+32 65 72 80 32",
    "sg:postcode":"7061",
    "sg:province":"Hainaut",
    "sg:tags":[
        "verzekeringsmakelaars",
        "expert"
    ],
    "wof:name":"A. Dassonville",
    "wof:placetype":"venue"
},
  "geometry": {"coordinates":[4.0002160072,50.5175895691],"type":"Point"}
}