{
  "type": "Feature",
  "properties": {
    "addr:full":"L. Carr\u00c9straat 26 Hallaar Antwerpen 2220",
    "addr:housenumber":"26",
    "addr:postcode":"2220",
    "addr:street":"L. Carre\u0301Straat",
    "iso:country":"BE",
    "sg:address":"L. Carr\u00c9straat 26",
    "sg:city":"Hallaar",
    "sg:orig_category":"Informaticaconsulenten Software ontwikkeling and ontwerp",
    "sg:phone":"+32 475 82 54 66",
    "sg:postcode":"2220",
    "sg:province":"Antwerpen",
    "wof:name":"D.r.-software",
    "wof:placetype":"venue"
},
  "geometry": {"coordinates":[4.7333660126,51.0892524719],"type":"Point"}
}