{
  "type": "Feature",
  "properties": {
    "addr:full":"Rue De Lille 57 Comines-warneton (warneton) Hainaut 7784",
    "addr:housenumber":"57",
    "addr:postcode":"7784",
    "addr:street":"Rue De Lille",
    "iso:country":"BE",
    "sg:address":"Rue De Lille 57",
    "sg:city":"Comines-warneton (warneton)",
    "sg:classifiers":[
        {
            "category":"Farming",
            "subcategory":"Berry Farm",
            "type":"Manufacturing & Wholesale Goods"
        }
    ],
    "sg:phone":"+32 56 58 88 11",
    "sg:postcode":"7784",
    "sg:province":"Hainaut",
    "sg:tags":[
        "horticulture",
        "-",
        "broker",
        "whol",
        "seed",
        "grain",
        "agriculture"
    ],
    "wof:name":"Ollivier Sa",
    "wof:placetype":"venue"
},
  "geometry": {"coordinates":[2.9483098984,50.752620697],"type":"Point"}
}