{
  "type": "Feature",
  "properties": {
    "addr:full":"Korenstraat 7 Genk Limburg 3600",
    "addr:housenumber":"7",
    "addr:postcode":"3600",
    "addr:street":"Korenstraat",
    "iso:country":"BE",
    "sg:address":"Korenstraat 7",
    "sg:city":"Genk",
    "sg:classifiers":[
        {
            "category":"Professional",
            "subcategory":"Engineering",
            "type":"Services"
        }
    ],
    "sg:phone":"+32 89 62 21 12",
    "sg:postcode":"3600",
    "sg:province":"Limburg",
    "sg:tags":[
        "-"
    ],
    "wof:name":"Dime Engineering",
    "wof:placetype":"venue"
},
  "geometry": {"coordinates":[5.5282258987,50.9411811829],"type":"Point"}
}