{
  "type": "Feature",
  "properties": {
    "iso:country":"BE",
    "sg:address":"Postbaan 34",
    "sg:city":"Essen",
    "sg:classifiers":[
        {
            "category":"Building & Trades",
            "subcategory":"Construction",
            "type":"Services"
        }
    ],
    "sg:phone":"+32 3 667 43 38",
    "sg:postcode":"2910",
    "sg:province":"Antwerpen",
    "sg:tags":[
        "installation",
        "-",
        "central",
        "heating"
    ],
    "wof:name":"Lambrechts Bvba",
    "wof:placetype":"venue"
},
  "geometry": {"coordinates":[4.4974031448,51.4621238708],"type":"Point"}
}