{
  "type": "Feature",
  "properties": {
    "addr:full":"Daalstraat 151 Grimbergen (beigem) Vlaams-Brabant 1852",
    "addr:housenumber":"151",
    "addr:postcode":"1852",
    "addr:street":"Daalstraat",
    "iso:country":"BE",
    "sg:address":"Daalstraat 151",
    "sg:city":"Grimbergen (beigem)",
    "sg:classifiers":[
        {
            "category":"Parking",
            "subcategory":"Lot",
            "type":"Transportation"
        }
    ],
    "sg:phone":"+32 2 269 35 95",
    "sg:postcode":"1852",
    "sg:province":"Vlaams-Brabant",
    "sg:tags":[
        "parking-places",
        "laying-out"
    ],
    "wof:name":"Haelwaeters J",
    "wof:placetype":"venue"
},
  "geometry": {"coordinates":[4.3810791969,50.9548797607],"type":"Point"}
}