{
  "type": "Feature",
  "properties": {
    "iso:country":"BE",
    "sg:address":"Place D'italie 5b72",
    "sg:city":"Li\u00c8ge",
    "sg:orig_category":"Artsen and specialisten",
    "sg:phone":"+32 4 342 18 91",
    "sg:postcode":"4020",
    "sg:province":"Li\u00e8ge",
    "wof:name":"Jules Renier",
    "wof:placetype":"venue"
},
  "geometry": {"coordinates":[5.5746598244,50.632434845],"type":"Point"}
}