{
  "type": "Feature",
  "properties": {
    "addr:full":"Enclus Du Haut 49bc Mont-de-l\u00b4enclus Hainaut 7750",
    "addr:postcode":"7750",
    "addr:street":"Hainaut",
    "iso:country":"BE",
    "sg:address":"Enclus Du Haut 49bc",
    "sg:city":"Mont-de-l\u00b4enclus",
    "sg:orig_category":"Belastingconsulenten Diverse juridische dienstverlening",
    "sg:phone":"+32 69 45 56 46",
    "sg:postcode":"7750",
    "sg:province":"Hainaut",
    "wof:name":"Ch. Deglas",
    "wof:placetype":"venue"
},
  "geometry": {"coordinates":[3.4913370609,50.7575149536],"type":"Point"}
}