{
  "type": "Feature",
  "properties": {
    "addr:full":"Avenue De L'hippodrome 64 Elsene/ixelles Bruxelles-Capitale 1050",
    "addr:housenumber":"64",
    "addr:postcode":"1050",
    "addr:street":"Avenue De L'Hippodrome",
    "iso:country":"BE",
    "sg:address":"Avenue De L'hippodrome 64",
    "sg:city":"Elsene/ixelles",
    "sg:orig_category":"Avocats and conseillers juridiques",
    "sg:phone":"+32 2 640 34 18",
    "sg:postcode":"1050",
    "sg:province":"Bruxelles-Capitale",
    "wof:name":"Ph. Van De Velde",
    "wof:placetype":"venue"
},
  "geometry": {"coordinates":[4.3758068085,50.8220672607],"type":"Point"}
}