{
  "type": "Feature",
  "properties": {
    "iso:country":"BE",
    "sg:address":"Heppenbach 99",
    "sg:city":"Amel (heppenbach)",
    "sg:classifiers":[
        {
            "category":"Building & Trades",
            "subcategory":"Electrical",
            "type":"Services"
        }
    ],
    "sg:phone":"+32 80 34 12 18",
    "sg:postcode":"4771",
    "sg:province":"Li\u00e8ge",
    "sg:tags":[
        "industrial",
        "-",
        "electric",
        "contractor"
    ],
    "wof:name":"Nowitec Ag",
    "wof:placetype":"venue"
},
  "geometry": {"coordinates":[6.2186770439,50.3613700867],"type":"Point"}
}