{
  "type": "Feature",
  "properties": {
    "iso:country":"BE",
    "sg:address":"Rue De L'eglise 228",
    "sg:city":"Attert (thiaumont)",
    "sg:classifiers":[
        {
            "category":"Education",
            "subcategory":"Special Training",
            "type":"Public Place"
        }
    ],
    "sg:phone":"+32 63 22 04 62",
    "sg:postcode":"6717",
    "sg:province":"Luxembourg",
    "sg:tags":[
        "school",
        "language"
    ],
    "wof:name":"Pro Linguis",
    "wof:placetype":"venue"
},
  "geometry": {"coordinates":[5.7305431366,49.7167701721],"type":"Point"}
}