{
  "type": "Feature",
  "properties": {
    "addr:full":"Herseltsesteenweg 5 Aarschot Vlaams-Brabant 3200",
    "addr:housenumber":"5",
    "addr:postcode":"3200",
    "addr:street":"Herseltsesteenweg",
    "iso:country":"BE",
    "sg:address":"Herseltsesteenweg 5",
    "sg:city":"Aarschot",
    "sg:classifiers":[
        {
            "category":"Health Services",
            "subcategory":"Doctor",
            "type":"Services"
        }
    ],
    "sg:phone":"+32 16 56 63 36",
    "sg:postcode":"3200",
    "sg:province":"Vlaams-Brabant",
    "sg:tags":[
        "medicinephysicians",
        "surgeon"
    ],
    "wof:name":"Bauwens Maurice",
    "wof:placetype":"venue"
},
  "geometry": {"coordinates":[4.8401741982,50.9922294617],"type":"Point"}
}