{
  "type": "Feature",
  "properties": {
    "iso:country":"BE",
    "sg:address":"Gatti De Gamondstraat 30b11",
    "sg:city":"Ukkel/uccle",
    "sg:orig_category":"Organisatie van beurzen, congressen and tentoonstellingen Reisbureaus",
    "sg:phone":"+32 2 376 51 53",
    "sg:postcode":"1180",
    "sg:province":"Bruxelles-Capitale",
    "wof:name":"Network",
    "wof:placetype":"venue"
},
  "geometry": {"coordinates":[4.3283247948,50.8049468994],"type":"Point"}
}