{
  "type": "Feature",
  "properties": {
    "iso:country":"BE",
    "sg:address":"Avenue Paul Pastur 279",
    "sg:city":"Charleroi",
    "sg:orig_category":"M\u00e9decins and sp\u00e9cialistes",
    "sg:phone":"+32 71 47 23 27",
    "sg:postcode":"6032",
    "sg:province":"Hainaut",
    "wof:name":"Marie-anne Raimondi",
    "wof:placetype":"venue"
},
  "geometry": {"coordinates":[4.4169158936,50.3952293396],"type":"Point"}
}