{
  "type": "Feature",
  "properties": {
    "iso:country":"BE",
    "sg:address":"Oudebaan 246a",
    "sg:city":"Leuven",
    "sg:classifiers":[
        {
            "category":"Wholesale",
            "subcategory":"Books, Periodicals, & Newspapers",
            "type":"Manufacturing & Wholesale Goods"
        }
    ],
    "sg:phone":"+32 16 25 50 43",
    "sg:postcode":"3000",
    "sg:province":"Vlaams-Brabant",
    "sg:tags":[
        "publisher"
    ],
    "wof:name":"Publi-touch",
    "wof:placetype":"venue"
},
  "geometry": {"coordinates":[4.7409992218,50.864490509],"type":"Point"}
}