{
  "type": "Feature",
  "properties": {
    "iso:country":"BE",
    "sg:address":"Stippelberg 28",
    "sg:city":"Herselt",
    "sg:orig_category":"Loodgieterij, verwarming and sanitaire installaties",
    "sg:phone":"+32 14 54 64 32",
    "sg:postcode":"2230",
    "sg:province":"Antwerpen",
    "wof:name":"Yvo Verlinden",
    "wof:placetype":"venue"
},
  "geometry": {"coordinates":[4.8896827698,51.0565986633],"type":"Point"}
}