{
  "type": "Feature",
  "properties": {
    "iso:country":"BE",
    "sg:address":"Rue Pairois 125",
    "sg:city":"Dour",
    "sg:orig_category":"Dameskledingzaken",
    "sg:phone":"+32 65 65 97 87",
    "sg:postcode":"7370",
    "sg:province":"Hainaut",
    "wof:name":"Chlo\u00c9 Couture",
    "wof:placetype":"venue"
},
  "geometry": {"coordinates":[3.7854139805,50.398651123],"type":"Point"}
}