{
  "type": "Feature",
  "properties": {
    "iso:country":"BE",
    "sg:address":"Graanmarkt 11",
    "sg:city":"Kortrijk",
    "sg:classifiers":[
        {
            "category":"Arena",
            "subcategory":"Sports Club",
            "type":"Entertainment"
        }
    ],
    "sg:phone":"+32 56 21 81 80",
    "sg:postcode":"8500",
    "sg:province":"West-Vlaanderen",
    "sg:tags":[
        "de"
    ],
    "wof:name":"Kon. Belg. Liefhebbers Voetbalbond W.-vl.",
    "wof:placetype":"venue"
},
  "geometry": {"coordinates":[3.2652049065,50.8267784119],"type":"Point"}
}