{
  "type": "Feature",
  "properties": {
    "addr:full":"Rijstraat 54 Ninove (denderwindeke) Oost-Vlaanderen 9400",
    "addr:housenumber":"54",
    "addr:postcode":"9400",
    "addr:street":"Rijstraat",
    "iso:country":"BE",
    "sg:address":"Rijstraat 54",
    "sg:city":"Ninove (denderwindeke)",
    "sg:classifiers":[
        {
            "category":"Personal",
            "subcategory":"Beauty Salon",
            "type":"Services"
        }
    ],
    "sg:phone":"+32 54 32 09 37",
    "sg:postcode":"9400",
    "sg:province":"Oost-Vlaanderen",
    "sg:tags":[
        "lady",
        "-",
        "hairdressing"
    ],
    "wof:name":"Cathy",
    "wof:placetype":"venue"
},
  "geometry": {"coordinates":[4.0215239525,50.7857971191],"type":"Point"}
}