{
  "type": "Feature",
  "properties": {
    "iso:country":"BE",
    "sg:address":"Lange Ridderstraat 58",
    "sg:city":"Antwerpen",
    "sg:classifiers":[
        {
            "category":"Organizations",
            "subcategory":"Community Association",
            "type":"Services"
        }
    ],
    "sg:phone":"+32 3 232 06 70",
    "sg:postcode":"2000",
    "sg:province":"Antwerpen",
    "sg:tags":[
        "organisation"
    ],
    "wof:name":"De Waag",
    "wof:placetype":"venue"
},
  "geometry": {"coordinates":[4.3961257935,51.2156143188],"type":"Point"}
}