{
  "type": "Feature",
  "properties": {
    "iso:country":"BE",
    "sg:address":"Europaweg 12",
    "sg:city":"Lummen",
    "sg:classifiers":[
        {
            "category":"Airport",
            "subcategory":"International",
            "type":"Transportation"
        }
    ],
    "sg:phone":"+32 11 43 65 00",
    "sg:postcode":"3560",
    "sg:province":"Limburg",
    "sg:tags":[
        "-",
        "transport"
    ],
    "wof:name":"K M R Transport Nv",
    "wof:placetype":"venue"
},
  "geometry": {"coordinates":[5.2214508057,51.0252609253],"type":"Point"}
}