{
  "type": "Feature",
  "properties": {
    "addr:full":"Avenue Des Croix Du Feu 145 Bruxelles Bruxelles-Capitale 1020",
    "addr:housenumber":"145",
    "addr:postcode":"1020",
    "addr:street":"Avenue Des Croix Du Feu",
    "iso:country":"BE",
    "sg:address":"Avenue Des Croix Du Feu 145",
    "sg:city":"Bruxelles",
    "sg:orig_category":"Assistances juridiques. Conseillers fiscaux",
    "sg:phone":"+32 2 242 06 10",
    "sg:postcode":"1020",
    "sg:province":"Bruxelles-Capitale",
    "wof:name":"Raoul Baele",
    "wof:placetype":"venue"
},
  "geometry": {"coordinates":[4.3690719604,50.8916015625],"type":"Point"}
}