{
  "type": "Feature",
  "properties": {
    "addr:full":"Groenendaalsesteenweg 19a Hoeilaart Vlaams-Brabant 1560",
    "addr:housenumber":"19a",
    "addr:postcode":"1560",
    "addr:street":"Groenendaalsesteenweg",
    "iso:country":"BE",
    "sg:address":"Groenendaalsesteenweg 19a",
    "sg:city":"Hoeilaart",
    "sg:orig_category":"Installation de piscines. Plomberie, chauffage and installations sanitaires",
    "sg:phone":"+32 2 657 38 16",
    "sg:postcode":"1560",
    "sg:province":"Vlaams-Brabant",
    "wof:name":"Marc Vanderlinden",
    "wof:placetype":"venue"
},
  "geometry": {"coordinates":[4.4686098099,50.7682533264],"type":"Point"}
}