{
  "type": "Feature",
  "properties": {
    "iso:country":"BE",
    "sg:address":"Rue Tour L'ev\u00eaque 2",
    "sg:city":"Vis\u00e9",
    "sg:classifiers":[
        {
            "category":"Building & Trades",
            "subcategory":"Construction",
            "type":"Services"
        }
    ],
    "sg:phone":"+32 496 82 79 38",
    "sg:postcode":"4600",
    "sg:province":"Li\u00e8ge",
    "sg:tags":[
        "paper",
        "hanger"
    ],
    "wof:name":"E.g.p",
    "wof:placetype":"venue"
},
  "geometry": {"coordinates":[5.6946401596,50.7382469177],"type":"Point"}
}