{
  "type": "Feature",
  "properties": {
    "addr:full":"Rue Reper Vreven 17 Bruxelles Bruxelles-Capitale 1020",
    "addr:housenumber":"17",
    "addr:postcode":"1020",
    "addr:street":"Rue Reper Vreven",
    "iso:country":"BE",
    "sg:address":"Rue Reper Vreven 17",
    "sg:city":"Bruxelles",
    "sg:classifiers":[
        {
            "category":"Building & Trades",
            "subcategory":"Electrical",
            "type":"Services"
        }
    ],
    "sg:phone":"+32 2 479 11 21",
    "sg:postcode":"1020",
    "sg:province":"Bruxelles-Capitale",
    "sg:tags":[
        "electric",
        "-",
        "housewiring",
        "contractor"
    ],
    "wof:name":"George R (ets) Sprl",
    "wof:placetype":"venue"
},
  "geometry": {"coordinates":[4.3425679207,50.8906440735],"type":"Point"}
}