{
  "type": "Feature",
  "properties": {
    "iso:country":"BE",
    "sg:address":"Chasse De Saint-ghislain 32",
    "sg:city":"Boussu",
    "sg:classifiers":[
        {
            "category":"Personal",
            "subcategory":"Beauty Salon",
            "type":"Services"
        }
    ],
    "sg:phone":"+32 65 78 76 97",
    "sg:postcode":"7300",
    "sg:province":"Hainaut",
    "sg:tags":[
        "lady",
        "-",
        "hairdressing"
    ],
    "wof:name":"Dora",
    "wof:placetype":"venue"
},
  "geometry": {"coordinates":[3.8019719124,50.4363288879],"type":"Point"}
}