{
  "type": "Feature",
  "properties": {
    "iso:country":"BE",
    "sg:address":"Chauss\u00e9e De Charleroi 35",
    "sg:city":"Genappe (baisy-thy)",
    "sg:classifiers":[
        {
            "category":"Home & Garden",
            "subcategory":"Home Furnishings",
            "type":"Retail Goods"
        }
    ],
    "sg:phone":"+32 67 77 25 81",
    "sg:postcode":"1470",
    "sg:province":"Brabant Wallon",
    "sg:tags":[
        "-",
        "furniture"
    ],
    "wof:name":"Galeries Du Meuble (les)",
    "wof:placetype":"venue"
},
  "geometry": {"coordinates":[4.450469017,50.6090545654],"type":"Point"}
}