{
  "type": "Feature",
  "properties": {
    "addr:full":"Zuidkaai 7 Gent Oost-Vlaanderen 9000",
    "addr:housenumber":"7",
    "addr:postcode":"9000",
    "addr:street":"Zuidkaai;Oost-Vlaanderen",
    "iso:country":"BE",
    "sg:address":"Zuidkaai 7",
    "sg:city":"Gent",
    "sg:orig_category":"Huishoudapparaten, televisies and radio's",
    "sg:phone":"+32 9 226 22 50",
    "sg:postcode":"9000",
    "sg:province":"Oost-Vlaanderen",
    "wof:name":"Fa. Vanghesdaele",
    "wof:placetype":"venue"
},
  "geometry": {"coordinates":[3.7065479755,51.05809021],"type":"Point"}
}