{
  "type": "Feature",
  "properties": {
    "addr:full":"Avenue Wielemans Ceuppens 164 Bruxelles (forest) Bruxelles-Capitale 1190",
    "addr:housenumber":"164",
    "addr:postcode":"1190",
    "addr:street":"Avenue Wielemans Ceuppens",
    "iso:country":"BE",
    "sg:address":"Avenue Wielemans Ceuppens 164",
    "sg:city":"Bruxelles (forest)",
    "sg:classifiers":[
        {
            "category":"Professional",
            "subcategory":"Computer Services",
            "type":"Services"
        }
    ],
    "sg:phone":"+32 2 537 00 04",
    "sg:postcode":"1190",
    "sg:province":"Bruxelles-Capitale",
    "sg:tags":[
        "repair",
        "processing",
        "-",
        "maintenance",
        "data"
    ],
    "wof:name":"Centrale Pc",
    "wof:placetype":"venue"
},
  "geometry": {"coordinates":[4.3330922127,50.8244476318],"type":"Point"}
}