{
  "type": "Feature",
  "properties": {
    "iso:country":"BE",
    "sg:address":"Zorgvliet 13",
    "sg:city":"Overijse",
    "sg:classifiers":[
        {
            "category":"Building & Trades",
            "subcategory":"Cleaning & Sanitation",
            "type":"Services"
        }
    ],
    "sg:phone":"+32 2 688 12 44",
    "sg:postcode":"3090",
    "sg:province":"Vlaams-Brabant",
    "sg:tags":[
        "cleaner",
        "window"
    ],
    "wof:name":"Freshclean",
    "wof:placetype":"venue"
},
  "geometry": {"coordinates":[4.5205860138,50.7683792114],"type":"Point"}
}