{
  "type": "Feature",
  "properties": {
    "addr:full":"Rue De Livourne 46 Elsene/ixelles Bruxelles-Capitale 1050",
    "addr:housenumber":"46",
    "addr:postcode":"1050",
    "addr:street":"Rue De Livourne",
    "iso:country":"BE",
    "sg:address":"Rue De Livourne 46",
    "sg:city":"Elsene/ixelles",
    "sg:orig_category":"D\u00e9corateurs d'int\u00e9rieur",
    "sg:phone":"+32 2 537 57 69",
    "sg:postcode":"1050",
    "sg:province":"Bruxelles-Capitale",
    "wof:name":"Avanti -design",
    "wof:placetype":"venue"
},
  "geometry": {"coordinates":[4.3585510254,50.8288383484],"type":"Point"}
}