{
  "type": "Feature",
  "properties": {
    "addr:full":"Korte Dennenlaan 3 Malle Antwerpen 2390",
    "addr:housenumber":"3",
    "addr:postcode":"2390",
    "addr:street":"Korte Dennenlaan",
    "iso:country":"BE",
    "sg:address":"Korte Dennenlaan 3",
    "sg:city":"Malle",
    "sg:classifiers":[
        {
            "category":"Professional",
            "subcategory":"Accounting & Tax Preparation",
            "type":"Services"
        }
    ],
    "sg:phone":"+32 3 311 65 34",
    "sg:postcode":"2390",
    "sg:province":"Antwerpen",
    "sg:tags":[
        "accountant"
    ],
    "wof:name":"Jan Kuypers",
    "wof:placetype":"venue"
},
  "geometry": {"coordinates":[4.6715078354,51.2844772339],"type":"Point"}
}