{
  "type": "Feature",
  "properties": {
    "addr:full":"Rue Ferrer 146-152 Charleroi (montignies-sur-sambre) Hainaut 6061",
    "addr:postcode":"146-152;6061",
    "addr:street":"Rue Ferrer",
    "iso:country":"BE",
    "sg:address":"Rue Ferrer 146-152",
    "sg:city":"Charleroi (montignies-sur-sambre)",
    "sg:classifiers":[
        {
            "category":"Manufacturing",
            "subcategory":"Paper Products",
            "type":"Manufacturing & Wholesale Goods"
        }
    ],
    "sg:phone":"+32 71 32 40 21",
    "sg:postcode":"6061",
    "sg:province":"Hainaut",
    "sg:tags":[
        "bookbinding"
    ],
    "wof:name":"De Vulder",
    "wof:placetype":"venue"
},
  "geometry": {"coordinates":[4.468170166,50.4110565186],"type":"Point"}
}