{
  "type": "Feature",
  "properties": {
    "iso:country":"BE",
    "sg:address":"Rue Du Midi 28",
    "sg:city":"Bruxelles",
    "sg:classifiers":[
        {
            "category":"Shopping",
            "subcategory":"Clothing, Apparel, & Fashions",
            "type":"Retail Goods"
        }
    ],
    "sg:phone":"+32 2 503 37 75",
    "sg:postcode":"1000",
    "sg:province":"Bruxelles-Capitale",
    "sg:tags":[
        "boutique"
    ],
    "wof:name":"Selwyn",
    "wof:placetype":"venue"
},
  "geometry": {"coordinates":[4.3506569862,50.8470878601],"type":"Point"}
}