{
  "type": "Feature",
  "properties": {
    "iso:country":"BE",
    "sg:address":"Vijverstraat 1",
    "sg:city":"Bredene",
    "sg:orig_category":"Poissonniers and \u00e9caillers",
    "sg:phone":"+32 59 33 23 09",
    "sg:postcode":"8450",
    "sg:province":"West-Vlaanderen",
    "wof:name":"Charles Devinck",
    "wof:placetype":"venue"
},
  "geometry": {"coordinates":[2.9628388882,51.2335472107],"type":"Point"}
}