{
  "type": "Feature",
  "properties": {
    "addr:full":"Bouvelostraat 6 Anzegem (gijzelbrechtegem) West-Vlaanderen 8570",
    "addr:housenumber":"6",
    "addr:postcode":"8570",
    "addr:street":"Bouvelostraat",
    "iso:country":"BE",
    "sg:address":"Bouvelostraat 6",
    "sg:city":"Anzegem (gijzelbrechtegem)",
    "sg:classifiers":[
        {
            "category":"Banks & Credit Unions",
            "subcategory":"Bank",
            "type":"Services"
        }
    ],
    "sg:phone":"+32 56 68 85 45",
    "sg:postcode":"8570",
    "sg:province":"West-Vlaanderen",
    "sg:tags":[
        "savings-banks"
    ],
    "wof:name":"Vercaemst J",
    "wof:placetype":"venue"
},
  "geometry": {"coordinates":[3.5057849884,50.829158783],"type":"Point"}
}