{
  "type": "Feature",
  "properties": {
    "iso:country":"BE",
    "sg:address":"Rue D'havr\u00c9 29",
    "sg:city":"Walcourt",
    "sg:orig_category":"Schoonheidssalons",
    "sg:phone":"+32 71 63 40 72",
    "sg:postcode":"5650",
    "sg:province":"Namur",
    "wof:name":"Cath\u00c9rine Colle",
    "wof:placetype":"venue"
},
  "geometry": {"coordinates":[4.4931378365,50.2401885986],"type":"Point"}
}