{
  "type": "Feature",
  "properties": {
    "iso:country":"BE",
    "sg:address":"Rue Fran\u00c7ois Fagnoul 1",
    "sg:city":"Waimes",
    "sg:orig_category":"Charpentes and couvertures",
    "sg:phone":"+32 80 67 92 60",
    "sg:postcode":"4950",
    "sg:province":"Li\u00e8ge",
    "wof:name":"Haddouche Benamar",
    "wof:placetype":"venue"
},
  "geometry": {"coordinates":[6.1161541939,50.4114151001],"type":"Point"}
}