{
  "type": "Feature",
  "properties": {
    "iso:country":"BE",
    "sg:address":"Rue Des Peupliers 23",
    "sg:city":"Neufch\u00c2teau",
    "sg:orig_category":"Belastingconsulenten Boekhouders Diverse juridische dienstverlening",
    "sg:phone":"+32 61 27 13 29",
    "sg:postcode":"6840",
    "sg:province":"Luxembourg",
    "wof:name":"Bureau Halloy P.",
    "wof:placetype":"venue"
},
  "geometry": {"coordinates":[5.4466772079,49.8453598022],"type":"Point"}
}