{
  "type": "Feature",
  "properties": {
    "iso:country":"BE",
    "sg:address":"Lil 49",
    "sg:city":"Meerhout",
    "sg:classifiers":[
        {
            "category":"Retail",
            "subcategory":"Auto Repair",
            "type":"Services"
        }
    ],
    "sg:phone":"+32 14 30 76 20",
    "sg:postcode":"2450",
    "sg:province":"Antwerpen",
    "sg:tags":[
        "automobile-body"
    ],
    "wof:name":"Theeuws Davy",
    "wof:placetype":"venue"
},
  "geometry": {"coordinates":[5.0893988609,51.1404838562],"type":"Point"}
}