{
  "type": "Feature",
  "properties": {
    "iso:country":"BE",
    "sg:address":"Bergendreef 5",
    "sg:city":"Schilde",
    "sg:classifiers":[
        {
            "category":"Professional",
            "subcategory":"Lawyer & Legal Services",
            "type":"Services"
        }
    ],
    "sg:phone":"+32 3 354 06 70",
    "sg:postcode":"2970",
    "sg:province":"Antwerpen",
    "wof:name":"Daems A",
    "wof:placetype":"venue"
},
  "geometry": {"coordinates":[4.5607271194,51.2284965515],"type":"Point"}
}