{
  "type": "Feature",
  "properties": {
    "iso:country":"BE",
    "sg:address":"Kortrijkstraat 103",
    "sg:city":"Tielt",
    "sg:orig_category":"Kapsalons",
    "sg:phone":"+32 51 40 18 04",
    "sg:postcode":"8700",
    "sg:province":"West-Vlaanderen",
    "wof:name":"Roger Vercoutere",
    "wof:placetype":"venue"
},
  "geometry": {"coordinates":[3.3256430626,50.9959449768],"type":"Point"}
}