{
  "type": "Feature",
  "properties": {
    "addr:full":"Rue Saint-eleuth\u00e8re 323 Tournai Hainaut 7500",
    "addr:housenumber":"323",
    "addr:postcode":"7500",
    "addr:street":"Rue Saint-Eleuthe\u0300Re",
    "iso:country":"BE",
    "sg:address":"Rue Saint-eleuth\u00e8re 323",
    "sg:city":"Tournai",
    "sg:classifiers":[
        {
            "category":"Health Services",
            "subcategory":"Doctor",
            "type":"Services"
        }
    ],
    "sg:phone":"+32 69 21 29 62",
    "sg:postcode":"7500",
    "sg:province":"Hainaut",
    "sg:tags":[
        "medicinephysicians",
        "surgeon"
    ],
    "wof:name":"Krings S",
    "wof:placetype":"venue"
},
  "geometry": {"coordinates":[3.3655650616,50.6172065735],"type":"Point"}
}