{
  "type": "Feature",
  "properties": {
    "addr:full":"Torhoutse Steenweg 261 Brugge (sint-michiels) West-Vlaanderen 8200",
    "addr:housenumber":"261",
    "addr:postcode":"8200",
    "addr:street":"Torhoutse Steenweg",
    "iso:country":"BE",
    "sg:address":"Torhoutse Steenweg 261",
    "sg:city":"Brugge (sint-michiels)",
    "sg:classifiers":[
        {
            "category":"Bars & Pubs",
            "type":"Food & Drink"
        }
    ],
    "sg:phone":"+32 50 39 23 58",
    "sg:postcode":"8200",
    "sg:province":"West-Vlaanderen",
    "sg:tags":[
        "tavern"
    ],
    "wof:name":"Farao's (the)",
    "wof:placetype":"venue"
},
  "geometry": {"coordinates":[3.1995139122,51.1951370239],"type":"Point"}
}