{
  "type": "Feature",
  "properties": {
    "addr:full":"Heppensesteenweg 119 Beringen Limburg 3581",
    "addr:housenumber":"119",
    "addr:postcode":"3581",
    "addr:street":"Heppensesteenweg",
    "iso:country":"BE",
    "sg:address":"Heppensesteenweg 119",
    "sg:city":"Beringen",
    "sg:orig_category":"IJzerwaren, bouw- and verfmaterialen Speciaalzaken",
    "sg:phone":"+32 11 34 77 23",
    "sg:postcode":"3581",
    "sg:province":"Limburg",
    "wof:name":"Fa. Das-berrevoets",
    "wof:placetype":"venue"
},
  "geometry": {"coordinates":[5.226006031,51.0974464417],"type":"Point"}
}