{
  "type": "Feature",
  "properties": {
    "iso:country":"BE",
    "sg:address":"Place Saint-martin 6",
    "sg:city":"Sambreville",
    "sg:classifiers":[
        {
            "category":"Cafe",
            "type":"Food & Drink"
        }
    ],
    "sg:phone":"+32 71 77 17 11",
    "sg:postcode":"5060",
    "sg:province":"Namur",
    "sg:tags":[
        "caf\u00e9s"
    ],
    "wof:name":"Caf\u00c9 St-martin",
    "wof:placetype":"venue"
},
  "geometry": {"coordinates":[4.6142997742,50.4313850403],"type":"Point"}
}