{
  "type": "Feature",
  "properties": {
    "addr:full":"Rue Sainte-barbe 25 Ciney Namur 5590",
    "addr:housenumber":"25",
    "addr:postcode":"5590",
    "addr:street":"Rue Sainte-Barbe",
    "iso:country":"BE",
    "sg:address":"Rue Sainte-barbe 25",
    "sg:city":"Ciney",
    "sg:orig_category":"Agences d\u00b4interim and personnel temporaire",
    "sg:phone":"+32 83 22 01 55",
    "sg:postcode":"5590",
    "sg:province":"Namur",
    "wof:name":"T-int\u00c9rim",
    "wof:placetype":"venue"
},
  "geometry": {"coordinates":[5.0961799622,50.2928352356],"type":"Point"}
}