{
  "type": "Feature",
  "properties": {
    "addr:full":"Hoevestraat 25 Zulte Oost-Vlaanderen 9870",
    "addr:housenumber":"25",
    "addr:postcode":"9870",
    "addr:street":"Hoevestraat",
    "iso:country":"BE",
    "sg:address":"Hoevestraat 25",
    "sg:city":"Zulte",
    "sg:orig_category":"Electrom\u00e9nager, t\u00e9l\u00e9visions and radios. R\u00e9parations \u00e0 domicile d'appareils \u00e9lectriques. R\u00e9parations ",
    "sg:phone":"+32 9 386 09 38",
    "sg:postcode":"9870",
    "sg:province":"Oost-Vlaanderen",
    "wof:name":"Electro-koeltechniek Tant",
    "wof:placetype":"venue"
},
  "geometry": {"coordinates":[3.4791879654,50.9560241699],"type":"Point"}
}