{
  "type": "Feature",
  "properties": {
    "addr:full":"Aartrijkestraat 30 Torhout West-Vlaanderen 8820",
    "addr:housenumber":"30",
    "addr:postcode":"8820",
    "addr:street":"Aartrijkestraat",
    "iso:country":"BE",
    "sg:address":"Aartrijkestraat 30",
    "sg:city":"Torhout",
    "sg:classifiers":[
        {
            "category":"Health Services",
            "subcategory":"Dentist",
            "type":"Services"
        }
    ],
    "sg:phone":"+32 50 22 27 00",
    "sg:postcode":"8820",
    "sg:province":"West-Vlaanderen",
    "wof:name":"Billiet Toon",
    "wof:placetype":"venue"
},
  "geometry": {"coordinates":[3.1000249386,51.0693702698],"type":"Point"}
}