{
  "type": "Feature",
  "properties": {
    "iso:country":"BE",
    "sg:address":"Yzerbergstraat 28",
    "sg:city":"Wingene",
    "sg:orig_category":"Eleveurs de bovins. Eleveurs and marchands de porcs. Producteurs de l\u00e9gumes",
    "sg:phone":"+32 51 61 14 18",
    "sg:postcode":"8750",
    "sg:province":"West-Vlaanderen",
    "wof:name":"Roland Vansimaeys",
    "wof:placetype":"venue"
},
  "geometry": {"coordinates":[3.2213599682,51.0507774353],"type":"Point"}
}