{
  "type": "Feature",
  "properties": {
    "addr:full":"Rue De Fer 51 Namur Namur 5000",
    "addr:housenumber":"51",
    "addr:postcode":"5000",
    "addr:street":"Rue De Fer",
    "iso:country":"BE",
    "sg:address":"Rue De Fer 51",
    "sg:city":"Namur",
    "sg:orig_category":"Location de v\u00eatements, chaussures and textiles. V\u00eatements de mariage and c\u00e9r\u00e9monies. V\u00eatements pour ",
    "sg:phone":"+32 81 23 10 78",
    "sg:postcode":"5000",
    "sg:province":"Namur",
    "wof:name":"Maison Charles-antoine",
    "wof:placetype":"venue"
},
  "geometry": {"coordinates":[4.8651380539,50.4658470154],"type":"Point"}
}