{
  "type": "Feature",
  "properties": {
    "addr:full":"Chestruvin 4 Onhaye Namur 5520",
    "addr:housenumber":"4",
    "addr:postcode":"5520",
    "addr:street":"Chestruvin",
    "iso:country":"BE",
    "sg:address":"Chestruvin 4",
    "sg:city":"Onhaye",
    "sg:orig_category":"Rundveehouders",
    "sg:phone":"+32 82 22 24 51",
    "sg:postcode":"5520",
    "sg:province":"Namur",
    "wof:name":"Freddy Verhelle",
    "wof:placetype":"venue"
},
  "geometry": {"coordinates":[4.8516168594,50.2624855042],"type":"Point"}
}