{
  "type": "Feature",
  "properties": {
    "iso:country":"BE",
    "sg:address":"Rue Saint-martin 18",
    "sg:city":"Ohey (jallet)",
    "sg:classifiers":[
        {
            "category":"Farming",
            "subcategory":"Livestock Farm",
            "type":"Manufacturing & Wholesale Goods"
        }
    ],
    "sg:phone":"+32 85 61 61 58",
    "sg:postcode":"5354",
    "sg:province":"Namur",
    "sg:tags":[
        "stud"
    ],
    "wof:name":"Haras St Martin",
    "wof:placetype":"venue"
},
  "geometry": {"coordinates":[5.1922969818,50.4459266663],"type":"Point"}
}