{
  "type": "Feature",
  "properties": {
    "iso:country":"BE",
    "sg:address":"Fonds De Pierreux 4",
    "sg:city":"Hamoir (filot)",
    "sg:classifiers":[
        {
            "category":"Building & Trades",
            "subcategory":"Construction",
            "type":"Services"
        }
    ],
    "sg:phone":"+32 86 38 82 88",
    "sg:postcode":"4181",
    "sg:province":"Li\u00e8ge",
    "sg:tags":[
        "carpenter"
    ],
    "wof:name":"Fagnoul A",
    "wof:placetype":"venue"
},
  "geometry": {"coordinates":[5.5691680908,50.4253540039],"type":"Point"}
}