{
  "type": "Feature",
  "properties": {
    "addr:full":"Route Des Cr\u00cates 68 Profondeville Namur 5170",
    "addr:housenumber":"68",
    "addr:postcode":"5170",
    "addr:street":"Route Des Cre\u0302Tes",
    "iso:country":"BE",
    "sg:address":"Route Des Cr\u00cates 68",
    "sg:city":"Profondeville",
    "sg:orig_category":"Kapsalons",
    "sg:phone":"+32 81 41 32 46",
    "sg:postcode":"5170",
    "sg:province":"Namur",
    "wof:name":"Katy Coiff\u00b4",
    "wof:placetype":"venue"
},
  "geometry": {"coordinates":[4.8586888313,50.3880348206],"type":"Point"}
}