{
  "type": "Feature",
  "properties": {
    "addr:full":"Rue Godin 9 Verviers (ensival) Li\u00e8ge 4800",
    "addr:housenumber":"9",
    "addr:postcode":"4800",
    "addr:street":"Rue Godin",
    "iso:country":"BE",
    "sg:address":"Rue Godin 9",
    "sg:city":"Verviers (ensival)",
    "sg:classifiers":[
        {
            "category":"Personal",
            "subcategory":"Beauty Salon",
            "type":"Services"
        }
    ],
    "sg:phone":"+32 87 33 12 35",
    "sg:postcode":"4800",
    "sg:province":"Li\u00e8ge",
    "sg:tags":[
        "lady",
        "-",
        "hairdressing"
    ],
    "wof:name":"Marinette Studio",
    "wof:placetype":"venue"
},
  "geometry": {"coordinates":[5.8594508171,50.5917663574],"type":"Point"}
}