{
  "type": "Feature",
  "properties": {
    "addr:full":"Klein Ronsestraat 80ba Zwevegem West-Vlaanderen 8553",
    "addr:housenumber":"80ba",
    "addr:postcode":"8553",
    "addr:street":"Klein Ronsestraat",
    "iso:country":"BE",
    "sg:address":"Klein Ronsestraat 80ba",
    "sg:city":"Zwevegem",
    "sg:orig_category":"Kapsalons",
    "sg:phone":"+32 56 77 82 16",
    "sg:postcode":"8553",
    "sg:province":"West-Vlaanderen",
    "wof:name":"Christ Detremmerie",
    "wof:placetype":"venue"
},
  "geometry": {"coordinates":[3.4282970428,50.8064308167],"type":"Point"}
}