{
  "type": "Feature",
  "properties": {
    "addr:full":"Gullegemsestraat 4 Ledegem West-Vlaanderen 8880",
    "addr:housenumber":"4",
    "addr:postcode":"8880",
    "addr:street":"Gullegemsestraat",
    "iso:country":"BE",
    "sg:address":"Gullegemsestraat 4",
    "sg:city":"Ledegem",
    "sg:orig_category":"Diverse bouwafwerking and reiniging Gespecialiseerde residenti\u00eble bouw",
    "sg:phone":"+32 56 50 69 83",
    "sg:postcode":"8880",
    "sg:province":"West-Vlaanderen",
    "wof:name":"Fa. Vandoorne & Zn",
    "wof:placetype":"venue"
},
  "geometry": {"coordinates":[3.1792318821,50.8751335144],"type":"Point"}
}