{
  "type": "Feature",
  "properties": {
    "iso:country":"BE",
    "sg:address":"Keizersplein 40",
    "sg:city":"Aalst",
    "sg:classifiers":[
        {
            "category":"Social Services",
            "type":"Services"
        }
    ],
    "sg:phone":"+32 53 76 87 10",
    "sg:postcode":"9300",
    "sg:province":"Oost-Vlaanderen",
    "wof:name":"Comitee Bijzondere Jeugdzorg",
    "wof:placetype":"venue"
},
  "geometry": {"coordinates":[4.0367431641,50.9366226196],"type":"Point"}
}