{
  "type": "Feature",
  "properties": {
    "addr:full":"Lindedorp 39 Peer Limburg 3990",
    "addr:housenumber":"39",
    "addr:postcode":"3990",
    "addr:street":"Lindedorp",
    "iso:country":"BE",
    "sg:address":"Lindedorp 39",
    "sg:city":"Peer",
    "sg:classifiers":[
        {
            "category":"Fast Food",
            "type":"Food & Drink"
        }
    ],
    "sg:phone":"+32 11 79 27 34",
    "sg:postcode":"3990",
    "sg:province":"Limburg",
    "sg:tags":[
        "fried",
        "stand",
        "potato"
    ],
    "wof:name":"Dorpshuys Bvba",
    "wof:placetype":"venue"
},
  "geometry": {"coordinates":[5.4462528229,51.0964851379],"type":"Point"}
}