{
  "type": "Feature",
  "properties": {
    "addr:full":"Lierseweg 6 Herentals Antwerpen 2200",
    "addr:housenumber":"6",
    "addr:postcode":"2200",
    "addr:street":"Lierseweg",
    "iso:country":"BE",
    "sg:address":"Lierseweg 6",
    "sg:city":"Herentals",
    "sg:classifiers":[
        {
            "category":"Insurance",
            "subcategory":"Insurance Agent",
            "type":"Services"
        }
    ],
    "sg:phone":"+32 14 21 36 64",
    "sg:postcode":"2200",
    "sg:province":"Antwerpen",
    "sg:tags":[
        "broker"
    ],
    "wof:name":"Smans Staf",
    "wof:placetype":"venue"
},
  "geometry": {"coordinates":[4.8296928406,51.1771202087],"type":"Point"}
}