{
  "type": "Feature",
  "properties": {
    "addr:full":"Grote Baan 195 Aalst Oost-Vlaanderen 9310",
    "addr:housenumber":"195",
    "addr:postcode":"9310",
    "addr:street":"Grote Baan",
    "iso:country":"BE",
    "sg:address":"Grote Baan 195",
    "sg:city":"Aalst",
    "sg:orig_category":"Landmeters",
    "sg:phone":"+32 53 21 67 80",
    "sg:postcode":"9310",
    "sg:province":"Oost-Vlaanderen",
    "wof:name":"L. Hutsebaut",
    "wof:placetype":"venue"
},
  "geometry": {"coordinates":[4.0660362244,50.9704284668],"type":"Point"}
}