{
  "type": "Feature",
  "properties": {
    "iso:country":"BE",
    "sg:address":"Schabbestraat 8",
    "sg:city":"Hasselt",
    "sg:orig_category":"Kapsalons",
    "sg:phone":"+32 11 25 18 85",
    "sg:postcode":"3511",
    "sg:province":"Limburg",
    "wof:name":"Carlo Geerts",
    "wof:placetype":"venue"
},
  "geometry": {"coordinates":[5.2819929123,50.9656867981],"type":"Point"}
}