{
  "type": "Feature",
  "properties": {
    "addr:full":"Rozenweg 50 Aalst Oost-Vlaanderen 9300",
    "addr:housenumber":"50",
    "addr:postcode":"9300",
    "addr:street":"Rozenweg",
    "iso:country":"BE",
    "sg:address":"Rozenweg 50",
    "sg:city":"Aalst",
    "sg:classifiers":[
        {
            "category":"Health Services",
            "subcategory":"Health Practitioner",
            "type":"Services"
        }
    ],
    "sg:phone":"+32 53 77 66 29",
    "sg:postcode":"9300",
    "sg:province":"Oost-Vlaanderen",
    "sg:tags":[
        "osteopath"
    ],
    "wof:name":"Phlips S (d.o.)",
    "wof:placetype":"venue"
},
  "geometry": {"coordinates":[4.0538668633,50.9463920593],"type":"Point"}
}