{
  "type": "Feature",
  "properties": {
    "addr:full":"Rue Samain 13 Binche (waudrez) Hainaut 7131",
    "addr:housenumber":"13",
    "addr:postcode":"7131",
    "addr:street":"Rue Samain",
    "iso:country":"BE",
    "sg:address":"Rue Samain 13",
    "sg:city":"Binche (waudrez)",
    "sg:classifiers":[
        {
            "category":"Wholesale",
            "subcategory":"Auto Parts",
            "type":"Manufacturing & Wholesale Goods"
        }
    ],
    "sg:phone":"+32 64 34 27 09",
    "sg:postcode":"7131",
    "sg:province":"Hainaut",
    "sg:tags":[
        "body",
        "automobile",
        "supply",
        "equipment"
    ],
    "wof:name":"Pr Design Car",
    "wof:placetype":"venue"
},
  "geometry": {"coordinates":[4.1536269188,50.4121551514],"type":"Point"}
}