{
  "type": "Feature",
  "properties": {
    "iso:country":"BE",
    "sg:address":"De Gravestraat 10",
    "sg:city":"Sint-niklaas",
    "sg:orig_category":"Non-Classified Establishments",
    "sg:phone":"+32 3 776 36 62",
    "sg:postcode":"9100",
    "sg:province":"Oost-Vlaanderen",
    "wof:name":"Bonneterie Pauwels Nv",
    "wof:placetype":"venue"
},
  "geometry": {"coordinates":[4.1464328766,51.1707992554],"type":"Point"}
}