{
  "type": "Feature",
  "properties": {
    "iso:country":"BE",
    "sg:address":"Antoon Catriestraat 58",
    "sg:city":"Gent (drongen)",
    "sg:classifiers":[
        {
            "category":"Professional",
            "subcategory":"Computer Services",
            "type":"Services"
        }
    ],
    "sg:phone":"+32 9 226 52 83",
    "sg:postcode":"9031",
    "sg:province":"Oost-Vlaanderen",
    "sg:tags":[
        "-",
        "processing",
        "data"
    ],
    "wof:name":"Dhooge C",
    "wof:placetype":"venue"
},
  "geometry": {"coordinates":[3.6488990784,51.0549621582],"type":"Point"}
}