{
  "type": "Feature",
  "properties": {
    "addr:full":"Potegemstraat 3 Zonnebeke West-Vlaanderen 8980",
    "addr:housenumber":"3",
    "addr:postcode":"8980",
    "addr:street":"Potegemstraat",
    "iso:country":"BE",
    "sg:address":"Potegemstraat 3",
    "sg:city":"Zonnebeke",
    "sg:orig_category":"Groententeelt",
    "sg:phone":"+32 51 77 01 34",
    "sg:postcode":"8980",
    "sg:province":"West-Vlaanderen",
    "wof:name":"Ronny Debuf",
    "wof:placetype":"venue"
},
  "geometry": {"coordinates":[2.9872550964,50.8730812073],"type":"Point"}
}