{
  "type": "Feature",
  "properties": {
    "iso:country":"BE",
    "sg:address":"Pater Gillardstraat 15",
    "sg:city":"Gingelom",
    "sg:orig_category":"Pain, p\u00e2tisseries and confiseries",
    "sg:phone":"+32 11 83 16 42",
    "sg:postcode":"3890",
    "sg:province":"Limburg",
    "wof:name":"M-a Schuppen",
    "wof:placetype":"venue"
},
  "geometry": {"coordinates":[5.1356778145,50.7504997253],"type":"Point"}
}