{
  "type": "Feature",
  "properties": {
    "addr:full":"Prins Boudewijnlaan 107 Sint-niklaas Oost-Vlaanderen 9100",
    "addr:housenumber":"107",
    "addr:postcode":"9100",
    "addr:street":"Prins Boudewijnlaan",
    "iso:country":"BE",
    "sg:address":"Prins Boudewijnlaan 107",
    "sg:city":"Sint-niklaas",
    "sg:classifiers":[
        {
            "category":"Communications",
            "subcategory":"Radio Station",
            "type":"Services"
        }
    ],
    "sg:phone":"+32 3 766 38 90",
    "sg:postcode":"9100",
    "sg:province":"Oost-Vlaanderen",
    "sg:tags":[
        "local"
    ],
    "wof:name":"Radio Cbs",
    "wof:placetype":"venue"
},
  "geometry": {"coordinates":[4.1720590591,51.1652793884],"type":"Point"}
}