{
  "type": "Feature",
  "properties": {
    "addr:full":"Vierde Lansierslaan 66 Tienen Vlaams-Brabant 3300",
    "addr:housenumber":"66",
    "addr:postcode":"3300",
    "addr:street":"Vierde Lansierslaan",
    "iso:country":"BE",
    "sg:address":"Vierde Lansierslaan 66",
    "sg:city":"Tienen",
    "sg:classifiers":[
        {
            "category":"Fast Food",
            "type":"Food & Drink"
        }
    ],
    "sg:phone":"+32 16 81 71 97",
    "sg:postcode":"3300",
    "sg:province":"Vlaams-Brabant",
    "sg:tags":[
        "\u00c0",
        "restaurants",
        "emporter",
        "restaurant"
    ],
    "wof:name":"Restaurant Hong-kong",
    "wof:placetype":"venue"
},
  "geometry": {"coordinates":[4.9274001122,50.8084907532],"type":"Point"}
}