{
  "type": "Feature",
  "properties": {
    "addr:full":"Marialei 23 Antwerpen Antwerpen 2018",
    "addr:housenumber":"23",
    "addr:postcode":"2018",
    "addr:street":"Marialei",
    "iso:country":"BE",
    "sg:address":"Marialei 23",
    "sg:city":"Antwerpen",
    "sg:orig_category":"Produits interm\u00e9diaires Gr",
    "sg:phone":"+32 3 239 18 88",
    "sg:postcode":"2018",
    "sg:province":"Antwerpen",
    "wof:name":"Jack Schpektor",
    "wof:placetype":"venue"
},
  "geometry": {"coordinates":[4.4207987785,51.2021255493],"type":"Point"}
}