{
  "type": "Feature",
  "properties": {
    "addr:full":"Visesteenweg 292 Riemst Limburg 3770",
    "addr:housenumber":"292",
    "addr:postcode":"3770",
    "addr:street":"Visesteenweg",
    "iso:country":"BE",
    "sg:address":"Visesteenweg 292",
    "sg:city":"Riemst",
    "sg:orig_category":"Travaux de pl\u00e2trage",
    "sg:phone":"+32 12 45 58 83",
    "sg:postcode":"3770",
    "sg:province":"Limburg",
    "wof:name":"Vanderstichelen",
    "wof:placetype":"venue"
},
  "geometry": {"coordinates":[5.606347084,50.8036117554],"type":"Point"}
}