{
  "type": "Feature",
  "properties": {
    "iso:country":"BE",
    "sg:address":"Jetselaan 57",
    "sg:city":"Koekelberg/koekelberg",
    "sg:orig_category":"Airconditioning and ventilatie Elektrische huishoudapparaten, radio and televisie Gh Huishoudapparat",
    "sg:phone":"+32 2 428 40 35",
    "sg:postcode":"1081",
    "sg:province":"Bruxelles-Capitale",
    "wof:name":"Notec",
    "wof:placetype":"venue"
},
  "geometry": {"coordinates":[4.3269438744,50.8668289185],"type":"Point"}
}