{
  "type": "Feature",
  "properties": {
    "iso:country":"BE",
    "sg:address":"Rue De Ciply 454",
    "sg:city":"Mons (cuesmes)",
    "sg:classifiers":[
        {
            "category":"Building & Trades",
            "subcategory":"Plumbing",
            "type":"Services"
        }
    ],
    "sg:phone":"+32 65 32 88 88",
    "sg:postcode":"7033",
    "sg:province":"Hainaut",
    "sg:tags":[
        "repair",
        "mainten",
        "-",
        "central",
        "heating"
    ],
    "wof:name":"Mar\u00e9chal Service Sa",
    "wof:placetype":"venue"
},
  "geometry": {"coordinates":[3.9253261089,50.4366378784],"type":"Point"}
}