{
  "type": "Feature",
  "properties": {
    "addr:full":"Ramselsesteenweg 85 Hulshout (westmeerbeek) Antwerpen 2235",
    "addr:housenumber":"85",
    "addr:postcode":"2235",
    "addr:street":"Ramselsesteenweg",
    "iso:country":"BE",
    "sg:address":"Ramselsesteenweg 85",
    "sg:city":"Hulshout (westmeerbeek)",
    "sg:classifiers":[
        {
            "category":"Recreation",
            "subcategory":"Amusement Park",
            "type":"Entertainment"
        }
    ],
    "sg:phone":"+32 16 69 68 38",
    "sg:postcode":"2235",
    "sg:province":"Antwerpen",
    "sg:tags":[
        "attraction",
        "-",
        "sale",
        "fair",
        "hiring"
    ],
    "wof:name":"Ceulemans L",
    "wof:placetype":"venue"
},
  "geometry": {"coordinates":[4.8336629868,51.0542793274],"type":"Point"}
}