{
  "type": "Feature",
  "properties": {
    "iso:country":"BE",
    "sg:address":"Diestsesteenweg 443",
    "sg:city":"Leuven",
    "sg:orig_category":"Alternatieve geneeskunde",
    "sg:phone":"+32 16 26 22 20",
    "sg:postcode":"3010",
    "sg:province":"Vlaams-Brabant",
    "wof:name":"L. Mensaert",
    "wof:placetype":"venue"
},
  "geometry": {"coordinates":[4.7304501534,50.889755249],"type":"Point"}
}