{
  "type": "Feature",
  "properties": {
    "addr:full":"Liersesteenweg 205 Berlaar Antwerpen 2590",
    "addr:housenumber":"205",
    "addr:postcode":"2590",
    "addr:street":"Liersesteenweg",
    "iso:country":"BE",
    "sg:address":"Liersesteenweg 205",
    "sg:city":"Berlaar",
    "sg:orig_category":"V\u00e9hicules automobiles. Entretien and r\u00e9parations de voitures",
    "sg:phone":"+32 3 482 25 78",
    "sg:postcode":"2590",
    "sg:province":"Antwerpen",
    "wof:name":"Garage Leemans",
    "wof:placetype":"venue"
},
  "geometry": {"coordinates":[4.632212162,51.1195526123],"type":"Point"}
}