{
  "type": "Feature",
  "properties": {
    "iso:country":"BE",
    "sg:address":"Topaaslaan 38",
    "sg:city":"Schaarbeek/schaerbeek",
    "sg:orig_category":"Sportclubs",
    "sg:phone":"+32 2 734 79 35",
    "sg:postcode":"1030",
    "sg:province":"Bruxelles-Capitale",
    "wof:name":"P.c. Les Jardins",
    "wof:placetype":"venue"
},
  "geometry": {"coordinates":[4.3941979408,50.8530387878],"type":"Point"}
}