{
  "type": "Feature",
  "properties": {
    "addr:full":"Marktstraat 16 Meulebeke West-Vlaanderen 8760",
    "addr:housenumber":"16",
    "addr:postcode":"8760",
    "addr:street":"Marktstraat",
    "iso:country":"BE",
    "sg:address":"Marktstraat 16",
    "sg:city":"Meulebeke",
    "sg:classifiers":[
        {
            "category":"Building & Trades",
            "subcategory":"Pest Control",
            "type":"Services"
        }
    ],
    "sg:phone":"+32 51 48 93 77",
    "sg:postcode":"8760",
    "sg:province":"West-Vlaanderen",
    "sg:tags":[
        "painting",
        "contractor"
    ],
    "wof:name":"Vansteenkiste L",
    "wof:placetype":"venue"
},
  "geometry": {"coordinates":[3.2888269424,50.9499282837],"type":"Point"}
}