{
  "type": "Feature",
  "properties": {
    "addr:full":"Strijlandstraat 101 Gooik Vlaams-Brabant 1755",
    "addr:housenumber":"101",
    "addr:postcode":"1755",
    "addr:street":"Strijlandstraat",
    "iso:country":"BE",
    "sg:address":"Strijlandstraat 101",
    "sg:city":"Gooik",
    "sg:classifiers":[
        {
            "category":"Banks & Credit Unions",
            "subcategory":"Investment Brokerage",
            "type":"Services"
        }
    ],
    "sg:phone":"+32 54 32 89 56",
    "sg:postcode":"1755",
    "sg:province":"Vlaams-Brabant",
    "sg:tags":[
        "ladies'",
        "tailor",
        "tailoresses",
        "-",
        "clothing"
    ],
    "wof:name":"Borremans L",
    "wof:placetype":"venue"
},
  "geometry": {"coordinates":[4.0754499435,50.7937927246],"type":"Point"}
}