{
  "type": "Feature",
  "properties": {
    "addr:full":"Rue Emile Parfonry 46 Hotton Luxembourg 6990",
    "addr:housenumber":"46",
    "addr:postcode":"6990",
    "addr:street":"Rue Emile Parfonry",
    "iso:country":"BE",
    "sg:address":"Rue Emile Parfonry 46",
    "sg:city":"Hotton",
    "sg:classifiers":[
        {
            "category":"Shopping",
            "subcategory":"Shoes",
            "type":"Retail Goods"
        }
    ],
    "sg:phone":"+32 84 46 71 21",
    "sg:postcode":"6990",
    "sg:province":"Luxembourg",
    "sg:tags":[
        "slipper",
        "-"
    ],
    "wof:name":"Godillot (le) Sc",
    "wof:placetype":"venue"
},
  "geometry": {"coordinates":[5.4442420006,50.2669143677],"type":"Point"}
}