{
  "type": "Feature",
  "properties": {
    "addr:full":"Doorniksesteenweg 355 Avelgem (outrijve) West-Vlaanderen 8582",
    "addr:housenumber":"355",
    "addr:postcode":"8582",
    "addr:street":"Doorniksesteenweg",
    "iso:country":"BE",
    "sg:address":"Doorniksesteenweg 355",
    "sg:city":"Avelgem (outrijve)",
    "sg:classifiers":[
        {
            "category":"Organizations",
            "subcategory":"Professional Association",
            "type":"Services"
        }
    ],
    "sg:phone":"+32 56 64 48 10",
    "sg:postcode":"8582",
    "sg:province":"West-Vlaanderen",
    "sg:tags":[
        "organisation",
        "seminar"
    ],
    "wof:name":"Alta Ripa (salons)",
    "wof:placetype":"venue"
},
  "geometry": {"coordinates":[3.4310159683,50.7573699951],"type":"Point"}
}