{
  "type": "Feature",
  "properties": {
    "addr:full":"Stationsstraat 10 Ichtegem (eernegem) West-Vlaanderen 8480",
    "addr:housenumber":"10",
    "addr:postcode":"8480",
    "addr:street":"Stationsstraat",
    "iso:country":"BE",
    "sg:address":"Stationsstraat 10",
    "sg:city":"Ichtegem (eernegem)",
    "sg:classifiers":[
        {
            "category":"Shopping",
            "subcategory":"Clothing, Apparel, & Fashions",
            "type":"Retail Goods"
        }
    ],
    "sg:phone":"+32 59 29 96 49",
    "sg:postcode":"8480",
    "sg:province":"West-Vlaanderen",
    "sg:tags":[
        "boutique"
    ],
    "wof:name":"M.l. Mode",
    "wof:placetype":"venue"
},
  "geometry": {"coordinates":[3.0255150795,51.129611969],"type":"Point"}
}