{
  "type": "Feature",
  "properties": {
    "addr:full":"F\u00e9ronstr\u00e9e 75 Li\u00e8ge 1 Li\u00e8ge 4000",
    "addr:housenumber":"75;1",
    "addr:postcode":"4000",
    "addr:street":"Fe\u0301Ronstre\u0301E",
    "iso:country":"BE",
    "sg:address":"F\u00e9ronstr\u00e9e 75",
    "sg:city":"Li\u00e8ge 1",
    "sg:classifiers":[
        {
            "category":"Food & Beverages",
            "subcategory":"Groceries & Convenience Stores",
            "type":"Retail Goods"
        }
    ],
    "sg:phone":"+32 4 223 08 26",
    "sg:postcode":"4000",
    "sg:province":"Li\u00e8ge",
    "sg:tags":[
        "grocer"
    ],
    "wof:name":"Fernandez M",
    "wof:placetype":"venue"
},
  "geometry": {"coordinates":[5.5790810585,50.6465415955],"type":"Point"}
}