{
  "type": "Feature",
  "properties": {
    "addr:full":"Goetsbloetsstraat 29 Hasselt Limburg 3500",
    "addr:housenumber":"29",
    "addr:postcode":"3500",
    "addr:street":"Goetsbloetsstraat",
    "iso:country":"BE",
    "sg:address":"Goetsbloetsstraat 29",
    "sg:city":"Hasselt",
    "sg:orig_category":"Peinture. Rev\u00eatements pour sols and murs",
    "sg:phone":"+32 11 87 32 78",
    "sg:postcode":"3500",
    "sg:province":"Limburg",
    "wof:name":"Stefan Driesen",
    "wof:placetype":"venue"
},
  "geometry": {"coordinates":[5.3228192329,50.9332351685],"type":"Point"}
}