{
  "type": "Feature",
  "properties": {
    "addr:full":"Hallaaraard 14 Heist-op-den-berg (hallaar) Antwerpen 2220",
    "addr:housenumber":"14",
    "addr:postcode":"2220",
    "addr:street":"Hallaaraard",
    "iso:country":"BE",
    "sg:address":"Hallaaraard 14",
    "sg:city":"Heist-op-den-berg (hallaar)",
    "sg:classifiers":[
        {
            "category":"Shopping",
            "subcategory":"Jewelry",
            "type":"Retail Goods"
        }
    ],
    "sg:phone":"+32 15 24 25 03",
    "sg:postcode":"2220",
    "sg:province":"Antwerpen",
    "sg:tags":[
        "-",
        "imitation"
    ],
    "wof:name":"Wauters",
    "wof:placetype":"venue"
},
  "geometry": {"coordinates":[4.7282481194,51.074672699],"type":"Point"}
}