{
  "type": "Feature",
  "properties": {
    "iso:country":"BE",
    "sg:address":"Nielandtsdam 1",
    "sg:city":"Kruibeke",
    "sg:orig_category":"Eleveurs de bovins",
    "sg:phone":"+32 3 774 19 56",
    "sg:postcode":"9150",
    "sg:province":"Oost-Vlaanderen",
    "wof:name":"Maria Oste",
    "wof:placetype":"venue"
},
  "geometry": {"coordinates":[4.278055191,51.1542663574],"type":"Point"}
}