{
  "type": "Feature",
  "properties": {
    "addr:full":"26 Berg 9860 Oosterzele-balegem 26",
    "addr:housenumber":"26;26",
    "addr:postcode":"9860",
    "addr:street":"Berg;Oosterzele-Balegem",
    "iso:country":"BE",
    "sg:address":"26",
    "sg:city":"Berg 9860 Oosterzele-balegem",
    "sg:classifiers":[
        {
            "category":"Farming",
            "subcategory":"Farm",
            "type":"Manufacturing & Wholesale Goods"
        }
    ],
    "sg:phone":"+32 9 362 63 61",
    "sg:postcode":"26",
    "sg:tags":[
        "horticulture",
        "agriculture",
        "livestock"
    ],
    "wof:name":"Bogaert Bvba",
    "wof:placetype":"venue"
},
  "geometry": {"coordinates":[3.7988049984,50.9225082397],"type":"Point"}
}