{
  "type": "Feature",
  "properties": {
    "iso:country":"BE",
    "sg:address":"Jezus-eiksesteenweg 65",
    "sg:city":"Hoeilaart",
    "sg:orig_category":"Producteurs de fruits",
    "sg:phone":"+32 2 657 28 20",
    "sg:postcode":"1560",
    "sg:province":"Vlaams-Brabant",
    "wof:name":"Jean Mariens",
    "wof:placetype":"venue"
},
  "geometry": {"coordinates":[4.4752750397,50.7754554749],"type":"Point"}
}