{
  "type": "Feature",
  "properties": {
    "iso:country":"BE",
    "sg:address":"Bavikhoofsestraat 26",
    "sg:city":"Kuurne",
    "sg:orig_category":"Drukkerijen and copyshops Secretariaatsdiensten",
    "sg:phone":"+32 56 71 39 77",
    "sg:postcode":"8520",
    "sg:province":"West-Vlaanderen",
    "wof:name":"Drukkerij Sabbe",
    "wof:placetype":"venue"
},
  "geometry": {"coordinates":[3.2886281013,50.8547706604],"type":"Point"}
}