{
  "type": "Feature",
  "properties": {
    "iso:country":"BE",
    "sg:address":"Jozef Buyssestraat 72",
    "sg:city":"Wetteren",
    "sg:orig_category":"R\u00e9alisation de programmes and logiciels",
    "sg:phone":"+32 9 366 17 73",
    "sg:postcode":"9230",
    "sg:province":"Oost-Vlaanderen",
    "wof:name":"Data-m",
    "wof:placetype":"venue"
},
  "geometry": {"coordinates":[3.8866000175,51.0046691895],"type":"Point"}
}