{
  "type": "Feature",
  "properties": {
    "iso:country":"BE",
    "sg:address":"Mauvaise-presle 167ba",
    "sg:city":"Wellin",
    "sg:orig_category":"G\u00e9om\u00e8tres",
    "sg:phone":"+32 84 38 70 80",
    "sg:postcode":"6920",
    "sg:province":"Luxembourg",
    "wof:name":"Pierre Gerday",
    "wof:placetype":"venue"
},
  "geometry": {"coordinates":[5.1054930687,50.0824813843],"type":"Point"}
}