{
  "type": "Feature",
  "properties": {
    "addr:full":"Industrieweg 2b Bocholt (kaulille) Limburg 3950",
    "addr:housenumber":"2b",
    "addr:postcode":"3950",
    "addr:street":"Industrieweg",
    "iso:country":"BE",
    "sg:address":"Industrieweg 2b",
    "sg:city":"Bocholt (kaulille)",
    "sg:classifiers":[
        {
            "category":"Autos & Motor Vehicles",
            "subcategory":"Automobile Sales",
            "type":"Retail Goods"
        }
    ],
    "sg:phone":"+32 11 66 67 74",
    "sg:postcode":"3950",
    "sg:province":"Limburg",
    "sg:tags":[
        "delivery",
        "-",
        "used",
        "van",
        "truck"
    ],
    "wof:name":"B. Service",
    "wof:placetype":"venue"
},
  "geometry": {"coordinates":[5.5218839645,51.2097587585],"type":"Point"}
}