{
  "type": "Feature",
  "properties": {
    "addr:full":"Casseldreef 23 Poperinge West-Vlaanderen 8970",
    "addr:housenumber":"23",
    "addr:postcode":"8970",
    "addr:street":"Casseldreef",
    "iso:country":"BE",
    "sg:address":"Casseldreef 23",
    "sg:city":"Poperinge",
    "sg:orig_category":"Eleveurs and marchands de porcs. Eleveurs de bovins",
    "sg:phone":"+32 57 33 48 16",
    "sg:postcode":"8970",
    "sg:province":"West-Vlaanderen",
    "wof:name":"Noel Dehouck",
    "wof:placetype":"venue"
},
  "geometry": {"coordinates":[2.7218461037,50.8536872864],"type":"Point"}
}