{
  "type": "Feature",
  "properties": {
    "addr:full":"Antwerpsesteenweg 434 Gent Oost-Vlaanderen 9040",
    "addr:housenumber":"434",
    "addr:postcode":"9040",
    "addr:street":"Antwerpsesteenweg;Oost-Vlaanderen",
    "iso:country":"BE",
    "sg:address":"Antwerpsesteenweg 434",
    "sg:city":"Gent",
    "sg:orig_category":"Artsen and specialisten",
    "sg:phone":"+32 9 238 22 20",
    "sg:postcode":"9040",
    "sg:province":"Oost-Vlaanderen",
    "wof:name":"C. Vande Maele",
    "wof:placetype":"venue"
},
  "geometry": {"coordinates":[3.7507660389,51.0628929138],"type":"Point"}
}