{
  "type": "Feature",
  "properties": {
    "addr:full":"Tentoonstellingslaan 426 Jette/jette Bruxelles-Capitale 1090",
    "addr:housenumber":"426",
    "addr:postcode":"1090",
    "addr:street":"Tentoonstellingslaan",
    "iso:country":"BE",
    "sg:address":"Tentoonstellingslaan 426",
    "sg:city":"Jette/jette",
    "sg:orig_category":"Artsen and specialisten",
    "sg:phone":"+32 2 478 38 80",
    "sg:postcode":"1090",
    "sg:province":"Bruxelles-Capitale",
    "wof:name":"Michel Muls",
    "wof:placetype":"venue"
},
  "geometry": {"coordinates":[4.3156228065,50.8905639648],"type":"Point"}
}