{
  "type": "Feature",
  "properties": {
    "iso:country":"BE",
    "sg:address":"Rue Washington 51a",
    "sg:city":"Elsene/ixelles",
    "sg:classifiers":[
        {
            "category":"Shopping",
            "subcategory":"Clothing, Apparel, & Fashions",
            "type":"Retail Goods"
        }
    ],
    "sg:phone":"+32 2 534 91 69",
    "sg:postcode":"1050",
    "sg:province":"Bruxelles-Capitale",
    "sg:tags":[
        "v\u00eatements",
        "pour",
        "dame"
    ],
    "wof:name":"Cashmere House - John Gaby\u00b4s",
    "wof:placetype":"venue"
},
  "geometry": {"coordinates":[4.3631119728,50.8236465454],"type":"Point"}
}