{
  "type": "Feature",
  "properties": {
    "addr:full":"Graanmarkt 3 Diest Vlaams-Brabant 3290",
    "addr:housenumber":"3",
    "addr:postcode":"3290",
    "addr:street":"Graanmarkt",
    "iso:country":"BE",
    "sg:address":"Graanmarkt 3",
    "sg:city":"Diest",
    "sg:orig_category":"Reclamebureaus",
    "sg:phone":"+32 13 32 24 45",
    "sg:postcode":"3290",
    "sg:province":"Vlaams-Brabant",
    "wof:name":"Publi Swa",
    "wof:placetype":"venue"
},
  "geometry": {"coordinates":[5.0545749664,50.9833297729],"type":"Point"}
}