{
  "type": "Feature",
  "properties": {
    "iso:country":"BE",
    "sg:address":"Mollemseweg 51",
    "sg:city":"Asse",
    "sg:orig_category":"Production de films, t\u00e9l\u00e9films and vid\u00e9os",
    "sg:phone":"+32 2 452 52 16",
    "sg:postcode":"1730",
    "sg:province":"Vlaams-Brabant",
    "wof:name":"Artebella",
    "wof:placetype":"venue"
},
  "geometry": {"coordinates":[4.1999177933,50.9190788269],"type":"Point"}
}