{
  "type": "Feature",
  "properties": {
    "addr:full":"Muilenstraat 236 Liedekerke Vlaams-Brabant 1770",
    "addr:housenumber":"236",
    "addr:postcode":"1770",
    "addr:street":"Muilenstraat;Vlaams-Brabant",
    "iso:country":"BE",
    "sg:address":"Muilenstraat 236",
    "sg:city":"Liedekerke",
    "sg:classifiers":[
        {
            "category":"Home & Garden",
            "subcategory":"Building Materials",
            "type":"Retail Goods"
        }
    ],
    "sg:phone":"+32 53 66 35 47",
    "sg:postcode":"1770",
    "sg:province":"Vlaams-Brabant",
    "sg:tags":[
        "veranda"
    ],
    "wof:name":"Ghijsels W",
    "wof:placetype":"venue"
},
  "geometry": {"coordinates":[4.1028680801,50.8796195984],"type":"Point"}
}