{
  "type": "Feature",
  "properties": {
    "addr:full":"Rue Du Berchon 159 Colfontaine Hainaut 7340",
    "addr:housenumber":"159",
    "addr:postcode":"7340",
    "addr:street":"Rue Du Berchon",
    "iso:country":"BE",
    "sg:address":"Rue Du Berchon 159",
    "sg:city":"Colfontaine",
    "sg:orig_category":"Enseignement secondaire g\u00e9n\u00e9ral",
    "sg:phone":"+32 65 78 59 33",
    "sg:postcode":"7340",
    "sg:province":"Hainaut",
    "wof:name":"Ecole La Cord\u00c9e",
    "wof:placetype":"venue"
},
  "geometry": {"coordinates":[3.8172399998,50.4128990173],"type":"Point"}
}