{
  "type": "Feature",
  "properties": {
    "addr:full":"Gullegemsestraat 20 Kortrijk West-Vlaanderen 8501",
    "addr:housenumber":"20",
    "addr:postcode":"8501",
    "addr:street":"Gullegemsestraat",
    "iso:country":"BE",
    "sg:address":"Gullegemsestraat 20",
    "sg:city":"Kortrijk",
    "sg:orig_category":"Boucheries",
    "sg:phone":"+32 56 35 71 85",
    "sg:postcode":"8501",
    "sg:province":"West-Vlaanderen",
    "wof:name":"Renmans",
    "wof:placetype":"venue"
},
  "geometry": {"coordinates":[3.2288239002,50.8444862366],"type":"Point"}
}