{
  "type": "Feature",
  "properties": {
    "addr:full":"Beverenstraat 1a Hooglede West-Vlaanderen 8830",
    "addr:housenumber":"1a",
    "addr:postcode":"8830",
    "addr:street":"Beverenstraat",
    "iso:country":"BE",
    "sg:address":"Beverenstraat 1a",
    "sg:city":"Hooglede",
    "sg:classifiers":[
        {
            "category":"Food & Beverages",
            "subcategory":"Supermarket",
            "type":"Retail Goods"
        }
    ],
    "sg:phone":"+32 51 24 03 65",
    "sg:postcode":"8830",
    "sg:province":"West-Vlaanderen",
    "sg:tags":[
        "department",
        "store"
    ],
    "wof:name":"Gb Contact",
    "wof:placetype":"venue"
},
  "geometry": {"coordinates":[3.0842990875,50.9772872925],"type":"Point"}
}