{
  "type": "Feature",
  "properties": {
    "addr:full":"Wissenstraat 7 Dendermonde Oost-Vlaanderen 9200",
    "addr:housenumber":"7",
    "addr:postcode":"9200",
    "addr:street":"Wissenstraat;Oost-Vlaanderen",
    "iso:country":"BE",
    "sg:address":"Wissenstraat 7",
    "sg:city":"Dendermonde",
    "sg:orig_category":"Poultry, Slaughtered",
    "sg:phone":"+32 52 21 89 97",
    "sg:postcode":"9200",
    "sg:province":"Oost-Vlaanderen",
    "wof:name":"Cooreman Petrus",
    "wof:placetype":"venue"
},
  "geometry": {"coordinates":[4.1423830986,51.0282669067],"type":"Point"}
}