{
  "type": "Feature",
  "properties": {
    "addr:full":"Rue De Rochefort 7 Box 6 Beauraing Namur 5570",
    "addr:housenumber":"7;6",
    "addr:postcode":"5570",
    "addr:street":"Rue De Rochefort;Box",
    "iso:country":"BE",
    "sg:address":"Rue De Rochefort 7 Box 6",
    "sg:city":"Beauraing",
    "sg:classifiers":[
        {
            "category":"Shopping",
            "subcategory":"Clothing, Apparel, & Fashions",
            "type":"Retail Goods"
        }
    ],
    "sg:phone":"+32 82 71 37 67",
    "sg:postcode":"5570",
    "sg:province":"Namur",
    "sg:tags":[
        "boutique"
    ],
    "wof:name":"Tendances",
    "wof:placetype":"venue"
},
  "geometry": {"coordinates":[4.9583392143,50.1086006165],"type":"Point"}
}