{
  "type": "Feature",
  "properties": {
    "addr:full":"Koningin Astridlaan 55 Sint-niklaas Oost-Vlaanderen 9100",
    "addr:housenumber":"55",
    "addr:postcode":"9100",
    "addr:street":"Koningin Astridlaan",
    "iso:country":"BE",
    "sg:address":"Koningin Astridlaan 55",
    "sg:city":"Sint-niklaas",
    "sg:classifiers":[
        {
            "category":"Insurance",
            "subcategory":"Life Insurance",
            "type":"Services"
        }
    ],
    "sg:phone":"+32 3 777 17 75",
    "sg:postcode":"9100",
    "sg:province":"Oost-Vlaanderen",
    "sg:tags":[
        "assurance"
    ],
    "wof:name":"Vero",
    "wof:placetype":"venue"
},
  "geometry": {"coordinates":[4.1551089287,51.1561279297],"type":"Point"}
}