{
  "type": "Feature",
  "properties": {
    "iso:country":"BE",
    "sg:address":"Chauss\u00e9e De Charleroi 226",
    "sg:city":"Sombreffe (ligny)",
    "sg:classifiers":[
        {
            "category":"Health Services",
            "subcategory":"Health Practitioner",
            "type":"Services"
        }
    ],
    "sg:phone":"+32 71 81 30 09",
    "sg:postcode":"5140",
    "sg:province":"Namur",
    "sg:tags":[
        "physiotherapist"
    ],
    "wof:name":"Smal G",
    "wof:placetype":"venue"
},
  "geometry": {"coordinates":[4.5774960518,50.498878479],"type":"Point"}
}