{
  "type": "Feature",
  "properties": {
    "iso:country":"BE",
    "sg:address":"Chauss\u00e9e De Dinant 998",
    "sg:city":"Namur (w\u00e9pion)",
    "sg:classifiers":[
        {
            "category":"Shopping",
            "subcategory":"Optician",
            "type":"Retail Goods"
        }
    ],
    "sg:phone":"+32 81 46 11 59",
    "sg:postcode":"5100",
    "sg:province":"Namur",
    "sg:tags":[
        "-"
    ],
    "wof:name":"Mosseray Optique",
    "wof:placetype":"venue"
},
  "geometry": {"coordinates":[4.8774528503,50.4198913574],"type":"Point"}
}