{
  "type": "Feature",
  "properties": {
    "iso:country":"BE",
    "sg:address":"M. Van Der Borghtstraat 58",
    "sg:city":"Putte",
    "sg:orig_category":"V\u00e9hicules automobiles. Entretien and r\u00e9parations de voitures",
    "sg:phone":"+32 15 23 38 05",
    "sg:postcode":"2580",
    "sg:province":"Antwerpen",
    "wof:name":"Garage Raymond",
    "wof:placetype":"venue"
},
  "geometry": {"coordinates":[4.659318924,51.0366630554],"type":"Point"}
}