{
  "type": "Feature",
  "properties": {
    "addr:full":"Dorpsstraat 26 Hasselt Limburg 3500",
    "addr:housenumber":"26",
    "addr:postcode":"3500",
    "addr:street":"Dorpsstraat",
    "iso:country":"BE",
    "sg:address":"Dorpsstraat 26",
    "sg:city":"Hasselt",
    "sg:classifiers":[
        {
            "category":"Shopping",
            "subcategory":"Books",
            "type":"Retail Goods"
        }
    ],
    "sg:phone":"+32 11 26 27 28",
    "sg:postcode":"3500",
    "sg:province":"Limburg",
    "sg:tags":[
        "antiquarian",
        "trade"
    ],
    "wof:name":"De Lezenaar",
    "wof:placetype":"venue"
},
  "geometry": {"coordinates":[5.335144043,50.9325675964],"type":"Point"}
}