{
  "type": "Feature",
  "properties": {
    "iso:country":"BE",
    "sg:address":"Ernest Ourystraat 42",
    "sg:city":"Hoegaarden",
    "sg:classifiers":[
        {
            "category":"Fast Food",
            "type":"Food & Drink"
        }
    ],
    "sg:phone":"+32 16 76 55 86",
    "sg:postcode":"3320",
    "sg:province":"Vlaams-Brabant",
    "sg:tags":[
        "meeneem",
        "restaurant"
    ],
    "wof:name":"\u00b4t Friet-uurtje",
    "wof:placetype":"venue"
},
  "geometry": {"coordinates":[4.8968491554,50.7740516663],"type":"Point"}
}