{
  "type": "Feature",
  "properties": {
    "iso:country":"BE",
    "sg:address":"Rue De Houffalize 5",
    "sg:city":"Houffalize",
    "sg:classifiers":[
        {
            "category":"Fast Food",
            "type":"Food & Drink"
        }
    ],
    "sg:phone":"+32 84 44 42 19",
    "sg:postcode":"6660",
    "sg:province":"Luxembourg",
    "sg:tags":[
        "\u00c0",
        "emporter",
        "restaurants"
    ],
    "wof:name":"Friterie Gillot",
    "wof:placetype":"venue"
},
  "geometry": {"coordinates":[5.7902050018,50.1322784424],"type":"Point"}
}