{
  "type": "Feature",
  "properties": {
    "iso:country":"BE",
    "sg:address":"Groeningestraat 48",
    "sg:city":"Harelbeke",
    "sg:classifiers":[
        {
            "category":"Real Estate",
            "subcategory":"Architect",
            "type":"Services"
        }
    ],
    "sg:phone":"+32 56 71 66 47",
    "sg:postcode":"8530",
    "sg:province":"West-Vlaanderen",
    "wof:name":"Vlieghe J",
    "wof:placetype":"venue"
},
  "geometry": {"coordinates":[3.3010339737,50.8454055786],"type":"Point"}
}