{
  "type": "Feature",
  "properties": {
    "iso:country":"BE",
    "sg:address":"Rue Br\u00dblarte 6",
    "sg:city":"Quevy",
    "sg:classifiers":[
        {
            "category":"Personal",
            "subcategory":"Beauty Salon",
            "type":"Services"
        }
    ],
    "sg:phone":"+32 65 58 63 73",
    "sg:postcode":"7041",
    "sg:province":"Hainaut",
    "sg:tags":[
        "de",
        "coiffure"
    ],
    "wof:name":"Suzette Masqueiller",
    "wof:placetype":"venue"
},
  "geometry": {"coordinates":[4.0314970016,50.3775863647],"type":"Point"}
}