{
  "type": "Feature",
  "properties": {
    "addr:full":"Rue De La Falaise 3 Couvin Namur 5660",
    "addr:housenumber":"3",
    "addr:postcode":"5660",
    "addr:street":"Rue De La Falaise",
    "iso:country":"BE",
    "sg:address":"Rue De La Falaise 3",
    "sg:city":"Couvin",
    "sg:orig_category":"Toeristische diensten",
    "sg:phone":"+32 60 34 74 63",
    "sg:postcode":"5660",
    "sg:province":"Namur",
    "wof:name":"Syndicat D'initiative",
    "wof:placetype":"venue"
},
  "geometry": {"coordinates":[4.4993672371,50.0481147766],"type":"Point"}
}