{
  "type": "Feature",
  "properties": {
    "iso:country":"BE",
    "sg:address":"Schoonzichtstraat 9",
    "sg:city":"Gent (sint-denijs-westrem - Afsnee)",
    "sg:classifiers":[
        {
            "category":"Tea Room",
            "subcategory":"None",
            "type":"Food & Drink"
        }
    ],
    "sg:phone":"+32 9 222 91 93",
    "sg:postcode":"9051",
    "sg:province":"Oost-Vlaanderen",
    "wof:name":"Sissi",
    "wof:placetype":"venue"
},
  "geometry": {"coordinates":[3.6712958813,51.0176925659],"type":"Point"}
}