{
  "type": "Feature",
  "properties": {
    "addr:full":"Rue De Fromelennes 85 Beauraing Namur 5570",
    "addr:housenumber":"85",
    "addr:postcode":"5570",
    "addr:street":"Rue De Fromelennes",
    "iso:country":"BE",
    "sg:address":"Rue De Fromelennes 85",
    "sg:city":"Beauraing",
    "sg:orig_category":"Enseignement maternel and primaire",
    "sg:phone":"+32 82 71 30 34",
    "sg:postcode":"5570",
    "sg:province":"Namur",
    "wof:name":"Ecole Prim. Communale",
    "wof:placetype":"venue"
},
  "geometry": {"coordinates":[4.8878250122,50.1189537048],"type":"Point"}
}