{
  "type": "Feature",
  "properties": {
    "iso:country":"BE",
    "sg:address":"Rue Du By 116",
    "sg:city":"Binche",
    "sg:orig_category":"Bloemen and planten",
    "sg:phone":"+32 64 34 19 76",
    "sg:postcode":"7134",
    "sg:province":"Hainaut",
    "wof:name":"Floril\u00c8ge",
    "wof:placetype":"venue"
},
  "geometry": {"coordinates":[4.2175779343,50.4159622192],"type":"Point"}
}