{
  "type": "Feature",
  "properties": {
    "addr:full":"Rue D'h\u00c9rinnes 2 Edingen/enghien Hainaut 7850",
    "addr:housenumber":"2",
    "addr:postcode":"7850",
    "addr:street":"Rue D'He \u0301Rinnes",
    "iso:country":"BE",
    "sg:address":"Rue D'h\u00c9rinnes 2",
    "sg:city":"Edingen/enghien",
    "sg:orig_category":"Cr\u00e9meries",
    "sg:phone":"+32 2 395 36 79",
    "sg:postcode":"7850",
    "sg:province":"Hainaut",
    "wof:name":"Maison Claudine",
    "wof:placetype":"venue"
},
  "geometry": {"coordinates":[4.0395159721,50.693687439],"type":"Point"}
}