{
  "type": "Feature",
  "properties": {
    "addr:full":"Kursaalstraat 35 Knokke-heist West-Vlaanderen 8301",
    "addr:housenumber":"35",
    "addr:postcode":"8301",
    "addr:street":"Kursaalstraat",
    "iso:country":"BE",
    "sg:address":"Kursaalstraat 35",
    "sg:city":"Knokke-heist",
    "sg:orig_category":"Brood, gebak and snoepgoed",
    "sg:phone":"+32 50 51 14 71",
    "sg:postcode":"8301",
    "sg:province":"West-Vlaanderen",
    "wof:name":"Bakkerij Michel",
    "wof:placetype":"venue"
},
  "geometry": {"coordinates":[3.2639000416,51.3396911621],"type":"Point"}
}