{
  "type": "Feature",
  "properties": {
    "iso:country":"BE",
    "sg:address":"Quai Godefroid Kurth 12",
    "sg:city":"Li\u00c8ge",
    "sg:orig_category":"Avocats and conseillers juridiques",
    "sg:phone":"+32 4 344 96 31",
    "sg:postcode":"4020",
    "sg:province":"Li\u00e8ge",
    "wof:name":"Dirk Ramboer",
    "wof:placetype":"venue"
},
  "geometry": {"coordinates":[5.5875811577,50.6458511353],"type":"Point"}
}