{
  "type": "Feature",
  "properties": {
    "iso:country":"BE",
    "sg:address":"Maarschalk Plumerlaan 24",
    "sg:city":"Ieper",
    "sg:orig_category":"Enseignement maternel and primaire",
    "sg:phone":"+32 57 20 15 27",
    "sg:postcode":"8900",
    "sg:province":"West-Vlaanderen",
    "wof:name":"Basisschool",
    "wof:placetype":"venue"
},
  "geometry": {"coordinates":[2.8764669895,50.8497772217],"type":"Point"}
}