{
  "type": "Feature",
  "properties": {
    "addr:full":"Steenweg Op Waarloos 35 Rumst (reet) Antwerpen 2840",
    "addr:housenumber":"35",
    "addr:postcode":"2840",
    "addr:street":"Steenweg Op Waarloos",
    "iso:country":"BE",
    "sg:address":"Steenweg Op Waarloos 35",
    "sg:city":"Rumst (reet)",
    "sg:classifiers":[
        {
            "category":"Personal",
            "subcategory":"Beauty Salon",
            "type":"Services"
        }
    ],
    "sg:phone":"+32 3 294 02 51",
    "sg:postcode":"2840",
    "sg:province":"Antwerpen",
    "sg:tags":[
        "product",
        "-",
        "apparatus"
    ],
    "wof:name":"Dermato Cosmetic Science-div.of Nannic Int.",
    "wof:placetype":"venue"
},
  "geometry": {"coordinates":[4.4227218628,51.0800132751],"type":"Point"}
}