{
  "type": "Feature",
  "properties": {
    "addr:full":"Livornostraat 45 Elsene/ixelles Bruxelles-Capitale 1050",
    "addr:housenumber":"45",
    "addr:postcode":"1050",
    "addr:street":"Livornostraat",
    "iso:country":"BE",
    "sg:address":"Livornostraat 45",
    "sg:city":"Elsene/ixelles",
    "sg:orig_category":"Advocaten and juridische adviseurs",
    "sg:phone":"+32 2 539 03 51",
    "sg:postcode":"1050",
    "sg:province":"Bruxelles-Capitale",
    "wof:name":"P. Valvekens",
    "wof:placetype":"venue"
},
  "geometry": {"coordinates":[4.359085083,50.8296737671],"type":"Point"}
}