{
  "type": "Feature",
  "properties": {
    "iso:country":"BE",
    "sg:address":"Weststraat 16",
    "sg:city":"Lichtervelde",
    "sg:classifiers":[
        {
            "category":"Home & Garden",
            "subcategory":"Garden Supply",
            "type":"Retail Goods"
        }
    ],
    "sg:phone":"+32 51 72 57 53",
    "sg:postcode":"8810",
    "sg:province":"West-Vlaanderen",
    "sg:tags":[
        "machine",
        "agricultural",
        "-"
    ],
    "wof:name":"Vallaey Bvba",
    "wof:placetype":"venue"
},
  "geometry": {"coordinates":[3.126265049,51.0262527466],"type":"Point"}
}