{
  "type": "Feature",
  "properties": {
    "iso:country":"BE",
    "sg:address":"Notestraat 64ba",
    "sg:city":"Ternat",
    "sg:orig_category":"M\u00e9decins and sp\u00e9cialistes",
    "sg:phone":"+32 2 582 29 13",
    "sg:postcode":"1742",
    "sg:province":"Vlaams-Brabant",
    "wof:name":"Chantal De Troch",
    "wof:placetype":"venue"
},
  "geometry": {"coordinates":[4.1402549744,50.8730316162],"type":"Point"}
}