{
  "type": "Feature",
  "properties": {
    "iso:country":"BE",
    "sg:address":"Lochtemanweg 122",
    "sg:city":"Heusden-zolder (heusden)",
    "sg:classifiers":[
        {
            "category":"Home & Garden",
            "subcategory":"Hardware",
            "type":"Retail Goods"
        }
    ],
    "sg:phone":"+32 11 43 22 40",
    "sg:postcode":"3550",
    "sg:province":"Limburg",
    "sg:tags":[
        "gate",
        "opener",
        "door",
        "automatic"
    ],
    "wof:name":"Maris Technics",
    "wof:placetype":"venue"
},
  "geometry": {"coordinates":[5.2335782051,51.0299034119],"type":"Point"}
}