{
  "type": "Feature",
  "properties": {
    "iso:country":"BE",
    "sg:address":"Kalverbosstraat 75",
    "sg:city":"Destelbergen (heusden)",
    "sg:classifiers":[
        {
            "category":"Airport",
            "subcategory":"International",
            "type":"Transportation"
        }
    ],
    "sg:phone":"+32 9 211 12 82",
    "sg:postcode":"9070",
    "sg:province":"Oost-Vlaanderen",
    "sg:tags":[
        "-",
        "transport"
    ],
    "wof:name":"C & S Express",
    "wof:placetype":"venue"
},
  "geometry": {"coordinates":[3.801058054,51.0134086609],"type":"Point"}
}