{
  "type": "Feature",
  "properties": {
    "addr:full":"Baljuwstraat 80 Poperinge West-Vlaanderen 8970",
    "addr:housenumber":"80",
    "addr:postcode":"8970",
    "addr:street":"Baljuwstraat",
    "iso:country":"BE",
    "sg:address":"Baljuwstraat 80",
    "sg:city":"Poperinge",
    "sg:orig_category":"Rundveehouders Varkenskwekers",
    "sg:phone":"+32 57 33 46 82",
    "sg:postcode":"8970",
    "sg:province":"West-Vlaanderen",
    "wof:name":"Marc Lagache",
    "wof:placetype":"venue"
},
  "geometry": {"coordinates":[2.7465660572,50.8327941895],"type":"Point"}
}