{
  "type": "Feature",
  "properties": {
    "addr:full":"Boulevard De La Woluwe 200 Brussel Bruxelles-Capitale 1200",
    "addr:housenumber":"200",
    "addr:postcode":"1200",
    "addr:street":"Boulevard De La Woluwe",
    "iso:country":"BE",
    "sg:address":"Boulevard De La Woluwe 200",
    "sg:city":"Brussel",
    "sg:orig_category":"Huishoudapparaten, televisies and radio's Telecommunicatieapparaten",
    "sg:phone":"+32 2 763 01 69",
    "sg:postcode":"1200",
    "sg:province":"Bruxelles-Capitale",
    "wof:name":"Vanden Borre",
    "wof:placetype":"venue"
},
  "geometry": {"coordinates":[4.446269989,50.8563690186],"type":"Point"}
}