{
  "type": "Feature",
  "properties": {
    "addr:full":"Chauss\u00e9e De Charleroi 95 Charleroi (gilly) Hainaut 6060",
    "addr:housenumber":"95",
    "addr:postcode":"6060",
    "addr:street":"Chausse\u0301E De Charleroi",
    "iso:country":"BE",
    "sg:address":"Chauss\u00e9e De Charleroi 95",
    "sg:city":"Charleroi (gilly)",
    "sg:classifiers":[
        {
            "category":"Professional",
            "subcategory":"Computer Services",
            "type":"Services"
        }
    ],
    "sg:phone":"+32 71 28 77 34",
    "sg:postcode":"6060",
    "sg:province":"Hainaut",
    "sg:tags":[
        "-",
        "processing",
        "data",
        "software"
    ],
    "wof:name":"Walsys-dessy Scs",
    "wof:placetype":"venue"
},
  "geometry": {"coordinates":[4.4736452103,50.401638031],"type":"Point"}
}