{
  "type": "Feature",
  "properties": {
    "iso:country":"BE",
    "sg:address":"Vlaschaard 47",
    "sg:city":"Kortrijk (heule)",
    "sg:classifiers":[
        {
            "category":"Building & Trades",
            "subcategory":"Landscaping Services",
            "type":"Services"
        }
    ],
    "sg:phone":"+32 56 35 81 50",
    "sg:postcode":"8501",
    "sg:province":"West-Vlaanderen",
    "sg:tags":[
        "gardening",
        "garden",
        "maintenance"
    ],
    "wof:name":"Wingerd (de)",
    "wof:placetype":"venue"
},
  "geometry": {"coordinates":[3.2505340576,50.8410835266],"type":"Point"}
}