{
  "type": "Feature",
  "properties": {
    "iso:country":"BE",
    "sg:address":"Schupstraat 1-7",
    "sg:city":"Antwerpen",
    "sg:classifiers":[
        {
            "category":"Professional",
            "subcategory":"Detective & Security Services",
            "type":"Services"
        }
    ],
    "sg:phone":"+32 3 231 68 45",
    "sg:postcode":"2018",
    "sg:province":"Antwerpen",
    "sg:tags":[
        "certificates",
        "honorary",
        "certificate"
    ],
    "wof:name":"International Gemmological Institute B.v.b.a.",
    "wof:placetype":"venue"
},
  "geometry": {"coordinates":[4.41873312,51.2144050598],"type":"Point"}
}