{
  "type": "Feature",
  "properties": {
    "iso:country":"BE",
    "sg:address":"Prins Albertlei 20",
    "sg:city":"Kapellen",
    "sg:classifiers":[
        {
            "category":"Retail",
            "subcategory":"Veterinary Services",
            "type":"Services"
        }
    ],
    "sg:phone":"+32 3 666 92 02",
    "sg:postcode":"2950",
    "sg:province":"Antwerpen",
    "sg:tags":[
        "veterinarian"
    ],
    "wof:name":"Van Walle A",
    "wof:placetype":"venue"
},
  "geometry": {"coordinates":[4.4716029167,51.3533744812],"type":"Point"}
}