{
  "type": "Feature",
  "properties": {
    "addr:full":"Hogeweg 25 Zandhoven (massenhoven) Antwerpen 2240",
    "addr:housenumber":"25",
    "addr:postcode":"2240",
    "addr:street":"Hogeweg",
    "iso:country":"BE",
    "sg:address":"Hogeweg 25",
    "sg:city":"Zandhoven (massenhoven)",
    "sg:classifiers":[
        {
            "category":"Health Services",
            "subcategory":"Health Practitioner",
            "type":"Services"
        }
    ],
    "sg:phone":"+32 3 484 42 23",
    "sg:postcode":"2240",
    "sg:province":"Antwerpen",
    "sg:tags":[
        "physiotherapist"
    ],
    "wof:name":"Gorris Gerda",
    "wof:placetype":"venue"
},
  "geometry": {"coordinates":[4.6388888359,51.2008247375],"type":"Point"}
}