{
  "type": "Feature",
  "properties": {
    "iso:country":"BE",
    "sg:address":"Groenstraat 20",
    "sg:city":"Boutersem (roosbeek)",
    "sg:classifiers":[
        {
            "category":"Health Services",
            "subcategory":"Health Practitioner",
            "type":"Services"
        }
    ],
    "sg:phone":"+32 16 72 02 90",
    "sg:postcode":"3370",
    "sg:province":"Vlaams-Brabant",
    "sg:tags":[
        "physiotherapist"
    ],
    "wof:name":"Vansteenvoort G",
    "wof:placetype":"venue"
},
  "geometry": {"coordinates":[4.8598132133,50.8374404907],"type":"Point"}
}