{
  "type": "Feature",
  "properties": {
    "iso:country":"BE",
    "sg:address":"Rue Vivier 2",
    "sg:city":"Welkenraedt (henri-chapelle)",
    "sg:classifiers":[
        {
            "category":"Tea Room",
            "subcategory":"None",
            "type":"Food & Drink"
        }
    ],
    "sg:phone":"+32 87 88 09 00",
    "sg:postcode":"4841",
    "sg:province":"Li\u00e8ge",
    "wof:name":"Le Birdie",
    "wof:placetype":"venue"
},
  "geometry": {"coordinates":[5.9403529167,50.6855163574],"type":"Point"}
}