{
  "type": "Feature",
  "properties": {
    "iso:country":"BE",
    "sg:address":"Rue Saint Fiacre 39",
    "sg:city":"Monceau-sur-sambre",
    "sg:classifiers":[
        {
            "category":"Professional",
            "subcategory":"Art Services",
            "type":"Services"
        }
    ],
    "sg:phone":"+32 71 32 72 22",
    "sg:postcode":"6031",
    "sg:province":"Hainaut",
    "sg:tags":[
        "metalwork"
    ],
    "wof:name":"Ets Patrick Filet",
    "wof:placetype":"venue"
},
  "geometry": {"coordinates":[4.3913240433,50.4113388062],"type":"Point"}
}