{
  "type": "Feature",
  "properties": {
    "iso:country":"BE",
    "sg:address":"Rue Du Charnois 28b",
    "sg:city":"Ottignies-louvain-la-neuve (limelette)",
    "sg:classifiers":[
        {
            "category":"Building & Trades",
            "subcategory":"Construction",
            "type":"Services"
        }
    ],
    "sg:phone":"+32 10 41 01 36",
    "sg:postcode":"1342",
    "sg:province":"Brabant Wallon",
    "sg:tags":[
        "work",
        "waterproofing"
    ],
    "wof:name":"Dromursec Bvba-sprl",
    "wof:placetype":"venue"
},
  "geometry": {"coordinates":[4.5418539047,50.6845092773],"type":"Point"}
}