{
  "type": "Feature",
  "properties": {
    "iso:country":"BE",
    "sg:address":"Grand'place 1",
    "sg:city":"Quaregnon",
    "sg:orig_category":"Enseignement secondaire technique and professionnel. Enseignement secondaire g\u00e9n\u00e9ral",
    "sg:phone":"+32 65 77 72 68",
    "sg:postcode":"7390",
    "sg:province":"Hainaut",
    "wof:name":"Institut Comm. Ens. Sec.",
    "wof:placetype":"venue"
},
  "geometry": {"coordinates":[3.8668880463,50.423248291],"type":"Point"}
}