{
  "type": "Feature",
  "properties": {
    "iso:country":"BE",
    "sg:address":"Toemaathoek 10",
    "sg:city":"Mol",
    "sg:classifiers":[
        {
            "category":"Arena",
            "subcategory":"Sports Club",
            "type":"Entertainment"
        }
    ],
    "sg:phone":"+32 14 31 04 42",
    "sg:postcode":"2400",
    "sg:province":"Antwerpen",
    "sg:tags":[
        "de"
    ],
    "wof:name":"T.c. Field",
    "wof:placetype":"venue"
},
  "geometry": {"coordinates":[5.1444897652,51.1996002197],"type":"Point"}
}