{
  "type": "Feature",
  "properties": {
    "addr:full":"Weg Naar Ellikom 17 Meeuwen-gruitrode Limburg 3670",
    "addr:housenumber":"17",
    "addr:postcode":"3670",
    "addr:street":"Weg Naar Ellikom",
    "iso:country":"BE",
    "sg:address":"Weg Naar Ellikom 17",
    "sg:city":"Meeuwen-gruitrode",
    "sg:orig_category":"M\u00e9decins and sp\u00e9cialistes",
    "sg:phone":"+32 11 79 38 54",
    "sg:postcode":"3670",
    "sg:province":"Limburg",
    "wof:name":"Margaretha Vandyck",
    "wof:placetype":"venue"
},
  "geometry": {"coordinates":[5.5180301666,51.0994338989],"type":"Point"}
}