{
  "type": "Feature",
  "properties": {
    "addr:full":"Kerkstraat 41 Maasmechelen Limburg 3630",
    "addr:housenumber":"41",
    "addr:postcode":"3630",
    "addr:street":"Kerkstraat",
    "iso:country":"BE",
    "sg:address":"Kerkstraat 41",
    "sg:city":"Maasmechelen",
    "sg:classifiers":[
        {
            "category":"Food & Beverages",
            "subcategory":"Fruits & Vegetables",
            "type":"Retail Goods"
        }
    ],
    "sg:phone":"+32 89 77 47 77",
    "sg:postcode":"3630",
    "sg:province":"Limburg",
    "sg:tags":[
        "l\u00e9gumes",
        "gr"
    ],
    "wof:name":"Agrar International",
    "wof:placetype":"venue"
},
  "geometry": {"coordinates":[5.6856198311,50.9394607544],"type":"Point"}
}