{
  "type": "Feature",
  "properties": {
    "addr:full":"Rue Des Cerisiers 11 Grez-doiceau Brabant Wallon 1390",
    "addr:housenumber":"11",
    "addr:postcode":"1390",
    "addr:street":"Rue Des Cerisiers",
    "iso:country":"BE",
    "sg:address":"Rue Des Cerisiers 11",
    "sg:city":"Grez-doiceau",
    "sg:orig_category":"S\u00e9lection de personnel and placement",
    "sg:phone":"+32 10 84 52 22",
    "sg:postcode":"1390",
    "sg:province":"Brabant Wallon",
    "wof:name":"Declercq & Associ\u00c9s",
    "wof:placetype":"venue"
},
  "geometry": {"coordinates":[4.7040848732,50.738407135],"type":"Point"}
}