{
  "type": "Feature",
  "properties": {
    "addr:full":"3960 Bree (groot) Limburg 3960",
    "addr:postcode":"3960;groot;3960",
    "addr:street":"Limburg",
    "iso:country":"BE",
    "sg:address":"3960",
    "sg:city":"Bree (groot)",
    "sg:orig_category":"Pharmaciens",
    "sg:phone":"+32 900 10 500",
    "sg:postcode":"3960",
    "sg:province":"Limburg",
    "wof:name":"Pharmacies De Garde",
    "wof:placetype":"venue"
},
  "geometry": {"coordinates":[5.5944190025,51.1405677795],"type":"Point"}
}