{
  "type": "Feature",
  "properties": {
    "iso:country":"BE",
    "sg:address":"Rue De Senzeilles 27",
    "sg:city":"Cerfontaine",
    "sg:classifiers":[
        {
            "category":"Health Services",
            "subcategory":"Health Practitioner",
            "type":"Services"
        }
    ],
    "sg:phone":"+32 71 64 47 40",
    "sg:postcode":"5630",
    "sg:province":"Namur",
    "sg:tags":[
        "physiotherapist"
    ],
    "wof:name":"Soupart P",
    "wof:placetype":"venue"
},
  "geometry": {"coordinates":[4.4163460732,50.1716804504],"type":"Point"}
}