{
  "type": "Feature",
  "properties": {
    "iso:country":"BE",
    "sg:address":"Zeedijk 232b73",
    "sg:city":"Middelkerke",
    "sg:orig_category":"Meubelen, niet-elektrische huishoudapparaten and vloerbekleding Gh",
    "sg:phone":"+32 59 31 39 16",
    "sg:postcode":"8430",
    "sg:province":"West-Vlaanderen",
    "wof:name":"Eurema",
    "wof:placetype":"venue"
},
  "geometry": {"coordinates":[2.8023500443,51.182674408],"type":"Point"}
}