{
  "type": "Feature",
  "properties": {
    "iso:country":"BE",
    "sg:address":"Bontestraat 10",
    "sg:city":"Lierde (sint-martens-lierde)",
    "sg:classifiers":[
        {
            "category":"Building & Trades",
            "subcategory":"Landscaping Services",
            "type":"Services"
        }
    ],
    "sg:phone":"+32 55 42 07 73",
    "sg:postcode":"9572",
    "sg:province":"Oost-Vlaanderen",
    "sg:tags":[
        "gardening",
        "garden",
        "maintenance"
    ],
    "wof:name":"R.g. Tuinen",
    "wof:placetype":"venue"
},
  "geometry": {"coordinates":[3.7978351116,50.8113174438],"type":"Point"}
}