{
  "type": "Feature",
  "properties": {
    "iso:country":"BE",
    "sg:address":"Groenweg 12",
    "sg:city":"Kortrijk",
    "sg:orig_category":"Kinderopvang",
    "sg:phone":"+32 56 25 52 57",
    "sg:postcode":"8510",
    "sg:province":"West-Vlaanderen",
    "wof:name":"Kribbe 't Sloeberke",
    "wof:placetype":"venue"
},
  "geometry": {"coordinates":[3.2622759342,50.7873802185],"type":"Point"}
}