{
  "type": "Feature",
  "properties": {
    "addr:full":"Avenue G\u00c9n\u00c9ral Bernheim 54 Etterbeek/etterbeek Bruxelles-Capitale 1040",
    "addr:housenumber":"54",
    "addr:postcode":"1040",
    "addr:street":"Avenue Ge\u0301Ne\u0301Ral Bernheim",
    "iso:country":"BE",
    "sg:address":"Avenue G\u00c9n\u00c9ral Bernheim 54",
    "sg:city":"Etterbeek/etterbeek",
    "sg:orig_category":"Tabac. Journaux",
    "sg:phone":"+32 2 647 38 51",
    "sg:postcode":"1040",
    "sg:province":"Bruxelles-Capitale",
    "wof:name":"Too Day",
    "wof:placetype":"venue"
},
  "geometry": {"coordinates":[4.388010025,50.8264427185],"type":"Point"}
}