{
  "type": "Feature",
  "properties": {
    "iso:country":"BE",
    "sg:address":"Rue Des Alli\u00c9s 8",
    "sg:city":"Libramont-chevigny",
    "sg:orig_category":"Installation \u00e9lectrique r\u00e9sidentielle",
    "sg:phone":"+32 61 22 31 50",
    "sg:postcode":"6800",
    "sg:province":"Luxembourg",
    "wof:name":"Joseph Yernaux",
    "wof:placetype":"venue"
},
  "geometry": {"coordinates":[5.3761348724,49.9199943542],"type":"Point"}
}