{
  "type": "Feature",
  "properties": {
    "addr:full":"Stuivenbergbaan 150 Mechelen Antwerpen 2800",
    "addr:housenumber":"150",
    "addr:postcode":"2800",
    "addr:street":"Stuivenbergbaan",
    "iso:country":"BE",
    "sg:address":"Stuivenbergbaan 150",
    "sg:city":"Mechelen",
    "sg:orig_category":"Reclamebureaus",
    "sg:phone":"+32 15 41 85 40",
    "sg:postcode":"2800",
    "sg:province":"Antwerpen",
    "wof:name":"Bureau Vandervelde",
    "wof:placetype":"venue"
},
  "geometry": {"coordinates":[4.4512572289,51.0256004333],"type":"Point"}
}