{
  "type": "Feature",
  "properties": {
    "iso:country":"BE",
    "sg:address":"Vanderkinderestraat 461",
    "sg:city":"Ukkel/uccle",
    "sg:orig_category":"Boekenuitgeverijen",
    "sg:phone":"+32 2 343 57 25",
    "sg:postcode":"1180",
    "sg:province":"Bruxelles-Capitale",
    "wof:name":"Ed.musica Latinoamericana",
    "wof:placetype":"venue"
},
  "geometry": {"coordinates":[4.3644781113,50.8144073486],"type":"Point"}
}