{
  "type": "Feature",
  "properties": {
    "addr:full":"Oude Schrieksebaan 19ba Bonheiden Antwerpen 2820",
    "addr:housenumber":"19ba",
    "addr:postcode":"2820",
    "addr:street":"Oude Schrieksebaan",
    "iso:country":"BE",
    "sg:address":"Oude Schrieksebaan 19ba",
    "sg:city":"Bonheiden",
    "sg:orig_category":"Articles de jardin",
    "sg:phone":"+32 15 52 97 83",
    "sg:postcode":"2820",
    "sg:province":"Antwerpen",
    "wof:name":"Potterie Hulsens",
    "wof:placetype":"venue"
},
  "geometry": {"coordinates":[4.5790739059,51.0174865723],"type":"Point"}
}