{
  "type": "Feature",
  "properties": {
    "addr:full":"Rue De La Praile 129 Ham-sur-heure-nalinnes Hainaut 6120",
    "addr:housenumber":"129",
    "addr:postcode":"6120",
    "addr:street":"Rue De La Praile;Hainaut",
    "iso:country":"BE",
    "sg:address":"Rue De La Praile 129",
    "sg:city":"Ham-sur-heure-nalinnes",
    "sg:orig_category":"Installation \u00e9lectrique r\u00e9sidentielle",
    "sg:phone":"+32 71 21 79 65",
    "sg:postcode":"6120",
    "sg:province":"Hainaut",
    "wof:name":"Lannoy Philippe",
    "wof:placetype":"venue"
},
  "geometry": {"coordinates":[4.4608597755,50.3184814453],"type":"Point"}
}