{
  "type": "Feature",
  "properties": {
    "iso:country":"BE",
    "sg:address":"Gildestraat 82",
    "sg:city":"Beringen (koersel)",
    "sg:classifiers":[
        {
            "category":"Home & Garden",
            "subcategory":"Garden Supply",
            "type":"Retail Goods"
        }
    ],
    "sg:phone":"+32 11 57 21 02",
    "sg:postcode":"3582",
    "sg:province":"Limburg",
    "sg:tags":[
        "lawn",
        "mower"
    ],
    "wof:name":"Lemmens A",
    "wof:placetype":"venue"
},
  "geometry": {"coordinates":[5.2708749771,51.0595359802],"type":"Point"}
}