{
  "type": "Feature",
  "properties": {
    "addr:full":"Ninoofsesteenweg 535 Dilbeek Vlaams-Brabant 1701",
    "addr:housenumber":"535",
    "addr:postcode":"1701",
    "addr:street":"Ninoofsesteenweg",
    "iso:country":"BE",
    "sg:address":"Ninoofsesteenweg 535",
    "sg:city":"Dilbeek",
    "sg:orig_category":"Goederenvervoer over de weg",
    "sg:phone":"+32 2 569 34 51",
    "sg:postcode":"1701",
    "sg:province":"Vlaams-Brabant",
    "wof:name":"De Koninck",
    "wof:placetype":"venue"
},
  "geometry": {"coordinates":[4.2474551201,50.842716217],"type":"Point"}
}