{
  "type": "Feature",
  "properties": {
    "addr:full":"Kalvariestraat 15 Genk Limburg 3600",
    "addr:housenumber":"15",
    "addr:postcode":"3600",
    "addr:street":"Kalvariestraat",
    "iso:country":"BE",
    "sg:address":"Kalvariestraat 15",
    "sg:city":"Genk",
    "sg:orig_category":"Bouwmaterialen Gh HUISBRANDOLIE",
    "sg:phone":"+32 89 35 21 17",
    "sg:postcode":"3600",
    "sg:province":"Limburg",
    "wof:name":"Jean Bergmans",
    "wof:placetype":"venue"
},
  "geometry": {"coordinates":[5.48939991,50.962852478],"type":"Point"}
}