{
  "type": "Feature",
  "properties": {
    "addr:full":"Chauss\u00c9e De Neerstalle 13 Vorst/forest Bruxelles-Capitale 1190",
    "addr:housenumber":"13",
    "addr:postcode":"1190",
    "addr:street":"Chausse\u0301E De Neerstalle;/ Forest",
    "iso:country":"BE",
    "sg:address":"Chauss\u00c9e De Neerstalle 13",
    "sg:city":"Vorst/forest",
    "sg:classifiers":[
        {
            "category":"Personal",
            "subcategory":"Beauty Salon",
            "type":"Services"
        }
    ],
    "sg:phone":"+32 2 376 37 93",
    "sg:postcode":"1190",
    "sg:province":"Bruxelles-Capitale",
    "sg:tags":[
        "de",
        "coiffure"
    ],
    "wof:name":"Coiffure Lady Jo",
    "wof:placetype":"venue"
},
  "geometry": {"coordinates":[4.3174967766,50.8096847534],"type":"Point"}
}