{
  "type": "Feature",
  "properties": {
    "iso:country":"BE",
    "sg:address":"Renderstraat 118",
    "sg:city":"Westerlo",
    "sg:orig_category":"Rundveehouders",
    "sg:phone":"+32 14 26 43 30",
    "sg:postcode":"2260",
    "sg:province":"Antwerpen",
    "wof:name":"Karel Vranckx",
    "wof:placetype":"venue"
},
  "geometry": {"coordinates":[4.859295845,51.0970573425],"type":"Point"}
}