{
  "type": "Feature",
  "properties": {
    "addr:full":"Eggersberg 2 Scherpenheuvel-zichem (scherpenheuvel) Vlaams-Brabant 3270",
    "addr:housenumber":"2",
    "addr:postcode":"3270",
    "addr:street":"Eggersberg",
    "iso:country":"BE",
    "sg:address":"Eggersberg 2",
    "sg:city":"Scherpenheuvel-zichem (scherpenheuvel)",
    "sg:classifiers":[
        {
            "category":"Professional",
            "subcategory":"Lawyer & Legal Services",
            "type":"Services"
        }
    ],
    "sg:phone":"+32 13 78 38 01",
    "sg:postcode":"3270",
    "sg:province":"Vlaams-Brabant",
    "wof:name":"Decat Marc",
    "wof:placetype":"venue"
},
  "geometry": {"coordinates":[4.9749708176,50.9714851379],"type":"Point"}
}