{
  "type": "Feature",
  "properties": {
    "iso:country":"BE",
    "sg:address":"Koningin Astridlaan 54",
    "sg:city":"Turnhout",
    "sg:orig_category":"Secr\u00e9tariats sociaux",
    "sg:phone":"+32 14 41 56 27",
    "sg:postcode":"2300",
    "sg:province":"Antwerpen",
    "wof:name":"Soc. Secretariaat Salar",
    "wof:placetype":"venue"
},
  "geometry": {"coordinates":[4.9229397774,51.3226776123],"type":"Point"}
}