{
  "type": "Feature",
  "properties": {
    "addr:full":"Quai Des P\u00e9niches 22 Bruxelles Bruxelles-Capitale 1000",
    "addr:housenumber":"22",
    "addr:postcode":"1000",
    "addr:street":"Quai Des Pe\u0301Niches",
    "iso:country":"BE",
    "sg:address":"Quai Des P\u00e9niches 22",
    "sg:city":"Bruxelles",
    "sg:classifiers":[
        {
            "category":"Arts & Performance",
            "subcategory":"Theater",
            "type":"Entertainment"
        }
    ],
    "sg:phone":"+32 2 203 03 03",
    "sg:postcode":"1000",
    "sg:province":"Bruxelles-Capitale",
    "sg:tags":[
        "concert-halls",
        "theatre"
    ],
    "wof:name":"Fulmar Asbl",
    "wof:placetype":"venue"
},
  "geometry": {"coordinates":[4.3518052101,50.8643264771],"type":"Point"}
}