{
  "type": "Feature",
  "properties": {
    "addr:full":"Malihoux 14a Havelange Namur 5370",
    "addr:housenumber":"14a",
    "addr:postcode":"5370",
    "addr:street":"Malihoux",
    "iso:country":"BE",
    "sg:address":"Malihoux 14a",
    "sg:city":"Havelange",
    "sg:classifiers":[
        {
            "category":"Building & Trades",
            "subcategory":"Construction",
            "type":"Services"
        }
    ],
    "sg:phone":"+32 83 63 39 93",
    "sg:postcode":"5370",
    "sg:province":"Namur",
    "sg:tags":[
        "stucco",
        "contractor"
    ],
    "wof:name":"A Et E Melot Succ. E.m. Melot Et F Tuttobene Sa",
    "wof:placetype":"venue"
},
  "geometry": {"coordinates":[5.2238540649,50.3924751282],"type":"Point"}
}