{
  "type": "Feature",
  "properties": {
    "addr:full":"Place D' Isnes-les-dames 7 Gembloux Namur 5032",
    "addr:housenumber":"7",
    "addr:postcode":"5032",
    "addr:street":"Place D ' Isnes-Les-Dames;Namur",
    "iso:country":"BE",
    "sg:address":"Place D' Isnes-les-dames 7",
    "sg:city":"Gembloux",
    "sg:orig_category":"R\u00e9parations d'appareils \u00e9lectrom\u00e9nagers. Electrom\u00e9nager, t\u00e9l\u00e9visions and radios",
    "sg:phone":"+32 81 56 85 96",
    "sg:postcode":"5032",
    "sg:province":"Namur",
    "wof:name":"Imre Szonyi",
    "wof:placetype":"venue"
},
  "geometry": {"coordinates":[4.6960802078,50.5266113281],"type":"Point"}
}