{
  "type": "Feature",
  "properties": {
    "addr:full":"Monaville 540 Bertogne Luxembourg 6688",
    "addr:housenumber":"540",
    "addr:postcode":"6688",
    "addr:street":"Monaville",
    "iso:country":"BE",
    "sg:address":"Monaville 540",
    "sg:city":"Bertogne",
    "sg:orig_category":"Boekhouders",
    "sg:phone":"+32 61 21 27 09",
    "sg:postcode":"6688",
    "sg:province":"Luxembourg",
    "wof:name":"Jean-marc Thiry",
    "wof:placetype":"venue"
},
  "geometry": {"coordinates":[5.689948082,50.0525741577],"type":"Point"}
}