{
  "type": "Feature",
  "properties": {
    "iso:country":"BE",
    "sg:address":"Hogevorst 34-36",
    "sg:city":"Assenede (bassevelde)",
    "sg:classifiers":[
        {
            "category":"Social Services",
            "type":"Services"
        }
    ],
    "sg:phone":"+32 9 373 90 67",
    "sg:postcode":"9968",
    "sg:province":"Oost-Vlaanderen",
    "wof:name":"I.w.c.c. International Vzw",
    "wof:placetype":"venue"
},
  "geometry": {"coordinates":[3.6887938976,51.1923027039],"type":"Point"}
}