{
  "type": "Feature",
  "properties": {
    "addr:full":"Wijngaardstraat 48 Haaltert Oost-Vlaanderen 9450",
    "addr:housenumber":"48",
    "addr:postcode":"9450",
    "addr:street":"Wijngaardstraat",
    "iso:country":"BE",
    "sg:address":"Wijngaardstraat 48",
    "sg:city":"Haaltert",
    "sg:classifiers":[
        {
            "category":"Farming",
            "subcategory":"Fish & Marine Products",
            "type":"Manufacturing & Wholesale Goods"
        }
    ],
    "sg:phone":"+32 53 83 52 26",
    "sg:postcode":"9450",
    "sg:province":"Oost-Vlaanderen",
    "sg:tags":[
        "retail",
        "-",
        "shellfish"
    ],
    "wof:name":"De Troyer",
    "wof:placetype":"venue"
},
  "geometry": {"coordinates":[3.9976539612,50.8912162781],"type":"Point"}
}