{
  "type": "Feature",
  "properties": {
    "addr:full":"Place Saint-lambert 16a Bruxelles (woluwe-saint-lambert) Bruxelles-Capitale 1200",
    "addr:housenumber":"16a",
    "addr:postcode":"1200",
    "addr:street":"Place Saint-Lambert",
    "iso:country":"BE",
    "sg:address":"Place Saint-lambert 16a",
    "sg:city":"Bruxelles (woluwe-saint-lambert)",
    "sg:classifiers":[
        {
            "category":"Personal",
            "subcategory":"Beauty Salon",
            "type":"Services"
        }
    ],
    "sg:phone":"+32 2 770 54 20",
    "sg:postcode":"1200",
    "sg:province":"Bruxelles-Capitale",
    "sg:tags":[
        "lady",
        "-",
        "hairdressing"
    ],
    "wof:name":"Canyoning Hair",
    "wof:placetype":"venue"
},
  "geometry": {"coordinates":[4.433716774,50.8413505554],"type":"Point"}
}