{
  "type": "Feature",
  "properties": {
    "addr:full":"Industrieterrein 2-4 Diest Vlaams-Brabant 3290",
    "addr:housenumber":"2-4",
    "addr:postcode":"3290",
    "addr:street":"Industrieterrein",
    "iso:country":"BE",
    "sg:address":"Industrieterrein 2-4",
    "sg:city":"Diest",
    "sg:classifiers":[
        {
            "category":"Banks & Credit Unions",
            "subcategory":"Investment Brokerage",
            "type":"Services"
        }
    ],
    "sg:phone":"+32 13 35 09 09",
    "sg:postcode":"3290",
    "sg:province":"Vlaams-Brabant",
    "sg:tags":[
        "batteries",
        "primary",
        "secondary"
    ],
    "wof:name":"Kempens Heftruckbedrijf Nv",
    "wof:placetype":"venue"
},
  "geometry": {"coordinates":[5.0769262314,50.9648323059],"type":"Point"}
}