{
  "type": "Feature",
  "properties": {
    "addr:full":"Darmstraat 1 Harelbeke (bavikhove) West-Vlaanderen 8531",
    "addr:housenumber":"1",
    "addr:postcode":"8531",
    "addr:street":"Darmstraat",
    "iso:country":"BE",
    "sg:address":"Darmstraat 1",
    "sg:city":"Harelbeke (bavikhove)",
    "sg:classifiers":[
        {
            "category":"Building & Trades",
            "subcategory":"Landscaping Services",
            "type":"Services"
        }
    ],
    "sg:phone":"+32 56 71 77 36",
    "sg:postcode":"8531",
    "sg:province":"West-Vlaanderen",
    "sg:tags":[
        "nurseryman"
    ],
    "wof:name":"Deo Dora",
    "wof:placetype":"venue"
},
  "geometry": {"coordinates":[3.2782649994,50.8735656738],"type":"Point"}
}