{
  "type": "Feature",
  "properties": {
    "iso:country":"BE",
    "sg:address":"Ciamberlanidreef 42",
    "sg:city":"Beveren (beveren-waas)",
    "sg:classifiers":[
        {
            "category":"Health Services",
            "subcategory":"Dentist",
            "type":"Services"
        }
    ],
    "sg:phone":"+32 3 775 75 10",
    "sg:postcode":"9120",
    "sg:province":"Oost-Vlaanderen",
    "wof:name":"Neirinckx Th\u00e9r\u00e8se",
    "wof:placetype":"venue"
},
  "geometry": {"coordinates":[4.2551608086,51.2161636353],"type":"Point"}
}