{
  "type": "Feature",
  "properties": {
    "addr:full":"Priester Poppestraat 20 Temse Oost-Vlaanderen 9140",
    "addr:housenumber":"20",
    "addr:postcode":"9140",
    "addr:street":"Priester Poppestraat",
    "iso:country":"BE",
    "sg:address":"Priester Poppestraat 20",
    "sg:city":"Temse",
    "sg:classifiers":[
        {
            "category":"Insurance",
            "subcategory":"Insurance Agent",
            "type":"Services"
        }
    ],
    "sg:phone":"+32 3 771 02 56",
    "sg:postcode":"9140",
    "sg:province":"Oost-Vlaanderen",
    "sg:tags":[
        "broker"
    ],
    "wof:name":"Govaert S",
    "wof:placetype":"venue"
},
  "geometry": {"coordinates":[4.2159061432,51.1240081787],"type":"Point"}
}