{
  "type": "Feature",
  "properties": {
    "addr:full":"Van Langenhovestraat 262b Dendermonde (sint-gillis-bij-dendermonde) Oost-Vlaanderen 9200",
    "addr:housenumber":"262b",
    "addr:postcode":"9200",
    "addr:street":"Van Langenhovestraat",
    "iso:country":"BE",
    "sg:address":"Van Langenhovestraat 262b",
    "sg:city":"Dendermonde (sint-gillis-bij-dendermonde)",
    "sg:classifiers":[
        {
            "category":"Retail",
            "subcategory":"Repair Shop",
            "type":"Services"
        }
    ],
    "sg:phone":"+32 52 22 30 17",
    "sg:postcode":"9200",
    "sg:province":"Oost-Vlaanderen",
    "sg:tags":[
        "-",
        "clothing",
        "alteration"
    ],
    "wof:name":"Kamikaze",
    "wof:placetype":"venue"
},
  "geometry": {"coordinates":[4.097424984,51.0178794861],"type":"Point"}
}