{
  "type": "Feature",
  "properties": {
    "addr:full":"Valkenbergstraat 2 Brakel Oost-Vlaanderen 9660",
    "addr:housenumber":"2",
    "addr:postcode":"9660",
    "addr:street":"Valkenbergstraat",
    "iso:country":"BE",
    "sg:address":"Valkenbergstraat 2",
    "sg:city":"Brakel",
    "sg:orig_category":"Salles de spectacles",
    "sg:phone":"+32 55 42 01 43",
    "sg:postcode":"9660",
    "sg:province":"Oost-Vlaanderen",
    "wof:name":"Valkenberghoeve",
    "wof:placetype":"venue"
},
  "geometry": {"coordinates":[3.758275032,50.8123626709],"type":"Point"}
}