{
  "type": "Feature",
  "properties": {
    "addr:full":"Lubbeeksestraat 20 Boutersem (roosbeek) Vlaams-Brabant 3370",
    "addr:housenumber":"20",
    "addr:postcode":"3370",
    "addr:street":"Lubbeeksestraat",
    "iso:country":"BE",
    "sg:address":"Lubbeeksestraat 20",
    "sg:city":"Boutersem (roosbeek)",
    "sg:classifiers":[
        {
            "category":"Health Services",
            "subcategory":"Dentist",
            "type":"Services"
        }
    ],
    "sg:phone":"+32 16 73 35 50",
    "sg:postcode":"3370",
    "sg:province":"Vlaams-Brabant",
    "wof:name":"De Mulder Christine",
    "wof:placetype":"venue"
},
  "geometry": {"coordinates":[4.8618211746,50.8329238892],"type":"Point"}
}