{
  "type": "Feature",
  "properties": {
    "iso:country":"BE",
    "sg:address":"Rue De Wangenies 116",
    "sg:city":"Fleurus (groot)",
    "sg:orig_category":"D\u00e9molition d\u00b4immeubles and terrassements",
    "sg:phone":"+32 71 81 87 52",
    "sg:postcode":"6220",
    "sg:province":"Hainaut",
    "wof:name":"Castille Et Cie",
    "wof:placetype":"venue"
},
  "geometry": {"coordinates":[4.5265002251,50.4568710327],"type":"Point"}
}