{
  "type": "Feature",
  "properties": {
    "addr:full":"Jan Helmanstraat 1 Willebroek Antwerpen 2830",
    "addr:housenumber":"1",
    "addr:postcode":"2830",
    "addr:street":"Helmanstraat",
    "iso:country":"BE",
    "sg:address":"Jan Helmanstraat 1",
    "sg:city":"Willebroek",
    "sg:classifiers":[
        {
            "category":"Coffee & Tea",
            "type":"Food & Drink"
        }
    ],
    "sg:phone":"+32 3 235 64 46",
    "sg:postcode":"2830",
    "sg:province":"Antwerpen",
    "sg:tags":[
        "roasted"
    ],
    "wof:name":"A. Vreys B.v.b.a.",
    "wof:placetype":"venue"
},
  "geometry": {"coordinates":[4.4389767647,51.2102012634],"type":"Point"}
}