{
  "type": "Feature",
  "properties": {
    "addr:full":"Mieregemstraat 68 Merchtem Vlaams-Brabant 1785",
    "addr:housenumber":"68",
    "addr:postcode":"1785",
    "addr:street":"Mieregemstraat",
    "iso:country":"BE",
    "sg:address":"Mieregemstraat 68",
    "sg:city":"Merchtem",
    "sg:classifiers":[
        {
            "category":"Shopping",
            "subcategory":"Stationery & Office Supplies",
            "type":"Retail Goods"
        }
    ],
    "sg:phone":"+32 52 37 03 45",
    "sg:postcode":"1785",
    "sg:province":"Vlaams-Brabant",
    "sg:tags":[
        "-"
    ],
    "wof:name":"A.p.r. Bvba",
    "wof:placetype":"venue"
},
  "geometry": {"coordinates":[4.2310099602,50.9556312561],"type":"Point"}
}