{
  "type": "Feature",
  "properties": {
    "iso:country":"BE",
    "sg:address":"Marie-jos\u00c9laan 149",
    "sg:city":"Sint-lambrechts-woluwe/woluwe-saint-lambert",
    "sg:orig_category":"Artsen and specialisten",
    "sg:phone":"+32 2 736 62 39",
    "sg:postcode":"1200",
    "sg:province":"Bruxelles-Capitale",
    "wof:name":"Jean-fran\u00c7ois Mahy",
    "wof:placetype":"venue"
},
  "geometry": {"coordinates":[4.4069042206,50.8439750671],"type":"Point"}
}