{
  "type": "Feature",
  "properties": {
    "addr:full":"Rue Du Pont 1c Incourt (opprebais) Brabant Wallon 1315",
    "addr:housenumber":"1c",
    "addr:postcode":"1315",
    "addr:street":"Rue Du Pont;Wallon",
    "iso:country":"BE",
    "sg:address":"Rue Du Pont 1c",
    "sg:city":"Incourt (opprebais)",
    "sg:classifiers":[
        {
            "category":"Personal",
            "subcategory":"Nail Salon",
            "type":"Services"
        }
    ],
    "sg:phone":"+32 10 88 10 56",
    "sg:postcode":"1315",
    "sg:province":"Brabant Wallon",
    "sg:tags":[
        "pedicure"
    ],
    "wof:name":"Velasco G",
    "wof:placetype":"venue"
},
  "geometry": {"coordinates":[4.7996101379,50.680606842],"type":"Point"}
}