{
  "type": "Feature",
  "properties": {
    "iso:country":"BE",
    "sg:address":"Helenalei 18",
    "sg:city":"Antwerpen",
    "sg:classifiers":[
        {
            "category":"Shopping",
            "subcategory":"Jewelry",
            "type":"Retail Goods"
        }
    ],
    "sg:phone":"+32 3 239 55 78",
    "sg:postcode":"2018",
    "sg:province":"Antwerpen",
    "sg:tags":[
        "fab",
        "bijou"
    ],
    "wof:name":"Maurice Hirschhorn",
    "wof:placetype":"venue"
},
  "geometry": {"coordinates":[4.4213409424,51.2010231018],"type":"Point"}
}