{
  "type": "Feature",
  "properties": {
    "addr:full":"Pitantiestraat 100 Waregem West-Vlaanderen 8792",
    "addr:housenumber":"100",
    "addr:postcode":"8792",
    "addr:street":"Pitantiestraat",
    "iso:country":"BE",
    "sg:address":"Pitantiestraat 100",
    "sg:city":"Waregem",
    "sg:orig_category":"Rev\u00eatements de sols and murs",
    "sg:phone":"+32 56 71 11 60",
    "sg:postcode":"8792",
    "sg:province":"West-Vlaanderen",
    "wof:name":"Vrobeton",
    "wof:placetype":"venue"
},
  "geometry": {"coordinates":[3.3746500015,50.8960494995],"type":"Point"}
}