{
  "type": "Feature",
  "properties": {
    "addr:full":"Stationsstraat 19 Kortessem (wintershoven) Limburg 3722",
    "addr:housenumber":"19",
    "addr:postcode":"3722",
    "addr:street":"Stationsstraat",
    "iso:country":"BE",
    "sg:address":"Stationsstraat 19",
    "sg:city":"Kortessem (wintershoven)",
    "sg:classifiers":[
        {
            "category":"Autos & Motor Vehicles",
            "subcategory":"Motorcycle Sales",
            "type":"Retail Goods"
        }
    ],
    "sg:phone":"+32 11 37 54 07",
    "sg:postcode":"3722",
    "sg:province":"Limburg",
    "sg:tags":[
        "motorbike"
    ],
    "wof:name":"Dam Inox Dempers",
    "wof:placetype":"venue"
},
  "geometry": {"coordinates":[5.4178037643,50.8538246155],"type":"Point"}
}