{
  "type": "Feature",
  "properties": {
    "addr:full":"Kapucijnenstraat 1 Herentals Antwerpen 2200",
    "addr:housenumber":"1",
    "addr:postcode":"2200",
    "addr:street":"Kapucijnenstraat",
    "iso:country":"BE",
    "sg:address":"Kapucijnenstraat 1",
    "sg:city":"Herentals",
    "sg:classifiers":[
        {
            "category":"Bakery",
            "type":"Food & Drink"
        }
    ],
    "sg:phone":"+32 14 21 11 00",
    "sg:postcode":"2200",
    "sg:province":"Antwerpen",
    "sg:tags":[
        "confectioner",
        "baker"
    ],
    "wof:name":"Mens Bvba",
    "wof:placetype":"venue"
},
  "geometry": {"coordinates":[4.8296117783,51.1791763306],"type":"Point"}
}