{
  "type": "Feature",
  "properties": {
    "addr:full":"Rue De Li\u00c8ge 6 Houffalize Luxembourg 6660",
    "addr:housenumber":"6",
    "addr:postcode":"6660",
    "addr:street":"Rue De Lie\u0300Ge",
    "iso:country":"BE",
    "sg:address":"Rue De Li\u00c8ge 6",
    "sg:city":"Houffalize",
    "sg:classifiers":[
        {
            "category":"Fast Food",
            "type":"Food & Drink"
        }
    ],
    "sg:phone":"+32 61 28 97 08",
    "sg:postcode":"6660",
    "sg:province":"Luxembourg",
    "sg:tags":[
        "huis",
        "aan",
        "levering",
        "meeneem",
        "restaurant"
    ],
    "wof:name":"La Pomme Canelle",
    "wof:placetype":"venue"
},
  "geometry": {"coordinates":[5.7909970284,50.1326713562],"type":"Point"}
}