{
  "type": "Feature",
  "properties": {
    "iso:country":"BE",
    "sg:address":"Landmolenstraat 28",
    "sg:city":"Temse",
    "sg:orig_category":"Eleveurs and marchands de porcs",
    "sg:phone":"+32 3 771 12 32",
    "sg:postcode":"9140",
    "sg:province":"Oost-Vlaanderen",
    "wof:name":"Agnes De Bock",
    "wof:placetype":"venue"
},
  "geometry": {"coordinates":[4.2417478561,51.1471481323],"type":"Point"}
}