{
  "type": "Feature",
  "properties": {
    "addr:full":"Chauss\u00e9e De Dinant 988 Namur (w\u00e9pion) Namur 5100",
    "addr:housenumber":"988",
    "addr:postcode":"5100",
    "addr:street":"Chausse\u0301E De Dinant",
    "iso:country":"BE",
    "sg:address":"Chauss\u00e9e De Dinant 988",
    "sg:city":"Namur (w\u00e9pion)",
    "sg:classifiers":[
        {
            "category":"Autos & Motor Vehicles",
            "subcategory":"Motorcycle Sales",
            "type":"Retail Goods"
        }
    ],
    "sg:phone":"+32 81 47 04 37",
    "sg:postcode":"5100",
    "sg:province":"Namur",
    "sg:tags":[
        "motorbike"
    ],
    "wof:name":"Moto Passion Namur",
    "wof:placetype":"venue"
},
  "geometry": {"coordinates":[4.8768959045,50.4209709167],"type":"Point"}
}