{
  "type": "Feature",
  "properties": {
    "addr:full":"Pamelse Klei 9 Roosdaal Vlaams-Brabant 1760",
    "addr:housenumber":"9",
    "addr:postcode":"1760",
    "addr:street":"Klei",
    "iso:country":"BE",
    "sg:address":"Pamelse Klei 9",
    "sg:city":"Roosdaal",
    "sg:classifiers":[
        {
            "category":"Shopping",
            "subcategory":"Shoes",
            "type":"Retail Goods"
        }
    ],
    "sg:phone":"+32 54 32 93 06",
    "sg:postcode":"1760",
    "sg:province":"Vlaams-Brabant",
    "sg:tags":[
        "slipper",
        "-"
    ],
    "wof:name":"Taccino",
    "wof:placetype":"venue"
},
  "geometry": {"coordinates":[4.0744271278,50.8435707092],"type":"Point"}
}