{
  "type": "Feature",
  "properties": {
    "iso:country":"BE",
    "sg:address":"Pothoekstraat 116",
    "sg:city":"Antwerpen",
    "sg:classifiers":[
        {
            "category":"Food & Beverages",
            "subcategory":"Supermarket",
            "type":"Retail Goods"
        }
    ],
    "sg:phone":"+32 3 272 28 41",
    "sg:postcode":"2060",
    "sg:province":"Antwerpen",
    "sg:tags":[
        "department",
        "store"
    ],
    "wof:name":"Gesmabo Enterprise Com V",
    "wof:placetype":"venue"
},
  "geometry": {"coordinates":[4.4368729591,51.224281311],"type":"Point"}
}