{
  "type": "Feature",
  "properties": {
    "iso:country":"BE",
    "sg:address":"Museumstraat 103",
    "sg:city":"Aalter",
    "sg:orig_category":"Mus\u00e9es and patrimoine culturel",
    "sg:phone":"+32 9 374 34 99",
    "sg:postcode":"9881",
    "sg:province":"Oost-Vlaanderen",
    "wof:name":"Het Grammenshuis",
    "wof:placetype":"venue"
},
  "geometry": {"coordinates":[3.4973208904,51.0960388184],"type":"Point"}
}