{
  "type": "Feature",
  "properties": {
    "addr:full":"Rue Houckaye 105 Verviers Li\u00e8ge 4800",
    "addr:housenumber":"105",
    "addr:postcode":"4800",
    "addr:street":"Rue Houckaye",
    "iso:country":"BE",
    "sg:address":"Rue Houckaye 105",
    "sg:city":"Verviers",
    "sg:orig_category":"Traitements param\u00e9dicaux",
    "sg:phone":"+32 87 22 82 37",
    "sg:postcode":"4800",
    "sg:province":"Li\u00e8ge",
    "wof:name":"P. Branle",
    "wof:placetype":"venue"
},
  "geometry": {"coordinates":[5.8594508171,50.5917663574],"type":"Point"}
}