{
  "type": "Feature",
  "properties": {
    "iso:country":"BE",
    "sg:address":"Avenue Des Pl\u00c9iades 71",
    "sg:city":"Sint-lambrechts-woluwe/woluwe-saint-lambert",
    "sg:orig_category":"Syst\u00e8mes de t\u00e9l\u00e9communications",
    "sg:phone":"+32 2 778 42 00",
    "sg:postcode":"1200",
    "sg:province":"Bruxelles-Capitale",
    "wof:name":"Cisco Systems Belgium",
    "wof:placetype":"venue"
},
  "geometry": {"coordinates":[4.4225749969,50.8556022644],"type":"Point"}
}