{
  "type": "Feature",
  "properties": {
    "addr:full":"Achterbroekste Steenweg 16 Kalmthout Antwerpen 2920",
    "addr:housenumber":"16",
    "addr:postcode":"2920",
    "addr:street":"Steenweg",
    "iso:country":"BE",
    "sg:address":"Achterbroekste Steenweg 16",
    "sg:city":"Kalmthout",
    "sg:orig_category":"M\u00e9taux and minerais Gr",
    "sg:phone":"+32 3 666 30 74",
    "sg:postcode":"2920",
    "sg:province":"Antwerpen",
    "wof:name":"V H",
    "wof:placetype":"venue"
},
  "geometry": {"coordinates":[4.4760432243,51.3939628601],"type":"Point"}
}