{
  "type": "Feature",
  "properties": {
    "iso:country":"BE",
    "sg:address":"Werkmanstraat 2",
    "sg:city":"Leuven",
    "sg:orig_category":"Imprimeries and copyshops",
    "sg:phone":"+32 16 29 47 77",
    "sg:postcode":"3000",
    "sg:province":"Vlaams-Brabant",
    "wof:name":"Exemplaar",
    "wof:placetype":"venue"
},
  "geometry": {"coordinates":[4.7024321556,50.8880844116],"type":"Point"}
}