{
  "type": "Feature",
  "properties": {
    "addr:full":"Robijnsstraat 5 Gingelom Limburg 3891",
    "addr:housenumber":"5",
    "addr:postcode":"3891",
    "addr:street":"Robijnsstraat",
    "iso:country":"BE",
    "sg:address":"Robijnsstraat 5",
    "sg:city":"Gingelom",
    "sg:orig_category":"Producteurs de fruits",
    "sg:phone":"+32 11 48 51 63",
    "sg:postcode":"3891",
    "sg:province":"Limburg",
    "wof:name":"Rene Joris",
    "wof:placetype":"venue"
},
  "geometry": {"coordinates":[5.2143130302,50.7547264099],"type":"Point"}
}