{
  "type": "Feature",
  "properties": {
    "iso:country":"BE",
    "sg:address":"Papenkasteelstraat 44b3",
    "sg:city":"Ukkel/uccle",
    "sg:classifiers":[
        {
            "category":"Professional",
            "subcategory":"Accounting & Tax Preparation",
            "type":"Services"
        }
    ],
    "sg:phone":"+32 2 374 88 16",
    "sg:postcode":"1180",
    "sg:province":"Bruxelles-Capitale",
    "sg:tags":[
        "accountant"
    ],
    "wof:name":"Pierre Tel",
    "wof:placetype":"venue"
},
  "geometry": {"coordinates":[4.3397498131,50.7902793884],"type":"Point"}
}