{
  "type": "Feature",
  "properties": {
    "addr:full":"Rue De Oizy 51 Bievre Namur 5555",
    "addr:housenumber":"51",
    "addr:postcode":"5555",
    "addr:street":"Rue De Oizy",
    "iso:country":"BE",
    "sg:address":"Rue De Oizy 51",
    "sg:city":"Bievre",
    "sg:classifiers":[
        {
            "category":"Food & Beverages",
            "subcategory":"Fruits & Vegetables",
            "type":"Retail Goods"
        }
    ],
    "sg:phone":"+32 61 51 11 81",
    "sg:postcode":"5555",
    "sg:province":"Namur",
    "sg:tags":[
        "l\u00e9gumes"
    ],
    "wof:name":"Michel Copine",
    "wof:placetype":"venue"
},
  "geometry": {"coordinates":[4.987180233,49.9049758911],"type":"Point"}
}