{
  "type": "Feature",
  "properties": {
    "iso:country":"BE",
    "sg:address":"Sint-willibrordusplein 4",
    "sg:city":"Heusden-zolder",
    "sg:orig_category":"M\u00e9decins and sp\u00e9cialistes",
    "sg:phone":"+32 11 42 69 16",
    "sg:postcode":"3550",
    "sg:province":"Limburg",
    "wof:name":"Maes",
    "wof:placetype":"venue"
},
  "geometry": {"coordinates":[5.2814188004,51.0338096619],"type":"Point"}
}