{
  "type": "Feature",
  "properties": {
    "iso:country":"BE",
    "sg:address":"August Vermeylenlaan 13b6",
    "sg:city":"Antwerpen",
    "sg:orig_category":"Architectes",
    "sg:phone":"+32 3 219 09 98",
    "sg:postcode":"2050",
    "sg:province":"Antwerpen",
    "wof:name":"Bureau Macken Paul",
    "wof:placetype":"venue"
},
  "geometry": {"coordinates":[4.3786897659,51.2311019897],"type":"Point"}
}