{
  "type": "Feature",
  "properties": {
    "addr:full":"Schrieksesteenweg 65 Putte Antwerpen 2580",
    "addr:housenumber":"65",
    "addr:postcode":"2580",
    "addr:street":"Schrieksesteenweg",
    "iso:country":"BE",
    "sg:address":"Schrieksesteenweg 65",
    "sg:city":"Putte",
    "sg:orig_category":"Transports routiers de marchandises",
    "sg:phone":"+32 15 75 61 21",
    "sg:postcode":"2580",
    "sg:province":"Antwerpen",
    "wof:name":"Fransen Transport",
    "wof:placetype":"venue"
},
  "geometry": {"coordinates":[4.6458659172,51.0417938232],"type":"Point"}
}