{
  "type": "Feature",
  "properties": {
    "iso:country":"BE",
    "sg:address":"Nicolaylaan 15",
    "sg:city":"Leopoldsburg",
    "sg:classifiers":[
        {
            "category":"Insurance",
            "subcategory":"Insurance Agent",
            "type":"Services"
        }
    ],
    "sg:phone":"+32 11 40 19 57",
    "sg:postcode":"3970",
    "sg:province":"Limburg",
    "sg:tags":[
        "verzekeringsmakelaars",
        "expert"
    ],
    "wof:name":"V.k.s.",
    "wof:placetype":"venue"
},
  "geometry": {"coordinates":[5.2586197853,51.1163291931],"type":"Point"}
}