{
  "type": "Feature",
  "properties": {
    "iso:country":"BE",
    "sg:address":"Bertogne 175",
    "sg:city":"Bertogne",
    "sg:classifiers":[
        {
            "category":"Building & Trades",
            "subcategory":"Landscaping Services",
            "type":"Services"
        }
    ],
    "sg:phone":"+32 61 21 31 90",
    "sg:postcode":"6687",
    "sg:province":"Luxembourg",
    "sg:tags":[
        "forestry"
    ],
    "wof:name":"Jacquemart P",
    "wof:placetype":"venue"
},
  "geometry": {"coordinates":[5.6736187935,50.0870018005],"type":"Point"}
}