{
  "type": "Feature",
  "properties": {
    "iso:country":"BE",
    "sg:address":"Schoolsteeg 1 A",
    "sg:city":"Bilzen",
    "sg:orig_category":"Gespecialiseerde residenti\u00eble bouw Woningbouw",
    "sg:phone":"+32 12 45 42 21",
    "sg:postcode":"3740",
    "sg:province":"Limburg",
    "wof:name":"Cuipers P",
    "wof:placetype":"venue"
},
  "geometry": {"coordinates":[5.55311203,50.8311157227],"type":"Point"}
}