{
  "type": "Feature",
  "properties": {
    "iso:country":"BE",
    "sg:address":"Losange 3",
    "sg:city":"Vaux-sur-s\u00fbre (hompr\u00e9)",
    "sg:classifiers":[
        {
            "category":"Building & Trades",
            "subcategory":"Cleaning & Sanitation",
            "type":"Services"
        }
    ],
    "sg:phone":"+32 61 21 10 63",
    "sg:postcode":"6640",
    "sg:province":"Luxembourg",
    "sg:tags":[
        "sweep",
        "chimney"
    ],
    "wof:name":"Choffray D",
    "wof:placetype":"venue"
},
  "geometry": {"coordinates":[5.5671000481,49.91065979],"type":"Point"}
}