{
  "type": "Feature",
  "properties": {
    "addr:full":"Rue De Charleroi 3 Walcourt Namur 5650",
    "addr:housenumber":"3",
    "addr:postcode":"5650",
    "addr:street":"Rue De Charleroi",
    "iso:country":"BE",
    "sg:address":"Rue De Charleroi 3",
    "sg:city":"Walcourt",
    "sg:orig_category":"RESTAURANTS: CATERING AND ORGANISATION DE F\u00caTES. ALIMENTATION SP\u00c9CIALIS\u00c9E",
    "sg:phone":"+32 71 65 52 75",
    "sg:postcode":"5650",
    "sg:province":"Namur",
    "wof:name":"La Botte D'yves",
    "wof:placetype":"venue"
},
  "geometry": {"coordinates":[4.4313349724,50.2514762878],"type":"Point"}
}