{
  "type": "Feature",
  "properties": {
    "addr:full":"Rue De La Fabrique 62ba Jemeppe-sur-sambre Namur 5190",
    "addr:housenumber":"62ba",
    "addr:postcode":"5190",
    "addr:street":"Rue De La Fabrique",
    "iso:country":"BE",
    "sg:address":"Rue De La Fabrique 62ba",
    "sg:city":"Jemeppe-sur-sambre",
    "sg:orig_category":"Artsen and specialisten",
    "sg:phone":"+32 71 78 57 57",
    "sg:postcode":"5190",
    "sg:province":"Namur",
    "wof:name":"Jean Dogot",
    "wof:placetype":"venue"
},
  "geometry": {"coordinates":[4.690882206,50.4551811218],"type":"Point"}
}