{
  "type": "Feature",
  "properties": {
    "addr:full":"Rue Pel\u00c9mont 20 Andenne Namur 5300",
    "addr:housenumber":"20",
    "addr:postcode":"5300",
    "addr:street":"Rue Pele\u0301Mont",
    "iso:country":"BE",
    "sg:address":"Rue Pel\u00c9mont 20",
    "sg:city":"Andenne",
    "sg:orig_category":"Herstellingen and onderhoud van auto's",
    "sg:phone":"+32 85 84 36 07",
    "sg:postcode":"5300",
    "sg:province":"Namur",
    "wof:name":"Philippe Motte",
    "wof:placetype":"venue"
},
  "geometry": {"coordinates":[5.1197299957,50.4919509888],"type":"Point"}
}