{
  "type": "Feature",
  "properties": {
    "iso:country":"BE",
    "sg:address":"Rue De La Chapelle 1a",
    "sg:city":"L\u00e9glise",
    "sg:classifiers":[
        {
            "category":"Building & Trades",
            "subcategory":"Construction",
            "type":"Services"
        }
    ],
    "sg:phone":"+32 63 42 29 66",
    "sg:postcode":"6860",
    "sg:province":"Luxembourg",
    "sg:tags":[
        "stucco",
        "contractor"
    ],
    "wof:name":"Marquis C",
    "wof:placetype":"venue"
},
  "geometry": {"coordinates":[5.5997757912,49.7866516113],"type":"Point"}
}