{
  "type": "Feature",
  "properties": {
    "addr:full":"Amersveldestraat 84 Kortemark West-Vlaanderen 8610",
    "addr:housenumber":"84",
    "addr:postcode":"8610",
    "addr:street":"Amersveldestraat",
    "iso:country":"BE",
    "sg:address":"Amersveldestraat 84",
    "sg:city":"Kortemark",
    "sg:orig_category":"Enseignement maternel and primaire",
    "sg:phone":"+32 51 56 71 03",
    "sg:postcode":"8610",
    "sg:province":"West-Vlaanderen",
    "wof:name":"Vrije Kleuterschool",
    "wof:placetype":"venue"
},
  "geometry": {"coordinates":[3.0287809372,51.016834259],"type":"Point"}
}