{
  "type": "Feature",
  "properties": {
    "addr:full":"Cesar Van Kerckhovenstraat 117 Bornem Antwerpen 2880",
    "addr:housenumber":"117",
    "addr:postcode":"2880",
    "addr:street":"Cesar Van Kerckhovenstraat",
    "iso:country":"BE",
    "sg:address":"Cesar Van Kerckhovenstraat 117",
    "sg:city":"Bornem",
    "sg:classifiers":[
        {
            "category":"Professional",
            "subcategory":"Secretarial Services",
            "type":"Services"
        }
    ],
    "sg:phone":"+32 3 890 36 00",
    "sg:postcode":"2880",
    "sg:province":"Antwerpen",
    "sg:tags":[
        "delivery",
        "messenger"
    ],
    "wof:name":"Alpaerts 2000 Nv",
    "wof:placetype":"venue"
},
  "geometry": {"coordinates":[4.2679548264,51.0948295593],"type":"Point"}
}