{
  "type": "Feature",
  "properties": {
    "addr:full":"Rue Bazin 17d Celles (pottes) Hainaut 7760",
    "addr:housenumber":"17d",
    "addr:postcode":"7760",
    "addr:street":"Rue Bazin",
    "iso:country":"BE",
    "sg:address":"Rue Bazin 17d",
    "sg:city":"Celles (pottes)",
    "sg:classifiers":[
        {
            "category":"Health Services",
            "subcategory":"Health Practitioner",
            "type":"Services"
        }
    ],
    "sg:phone":"+32 69 45 68 09",
    "sg:postcode":"7760",
    "sg:province":"Hainaut",
    "sg:tags":[
        "physiotherapist"
    ],
    "wof:name":"Testaert Jean-marie",
    "wof:placetype":"venue"
},
  "geometry": {"coordinates":[3.4082698822,50.7250137329],"type":"Point"}
}