{
  "type": "Feature",
  "properties": {
    "iso:country":"BE",
    "sg:address":"Rue Des P\u00e2querettes 50",
    "sg:city":"Dison",
    "sg:orig_category":"Non-Classified Establishments",
    "sg:phone":"+32 87 44 66 52",
    "sg:postcode":"4820",
    "sg:province":"Li\u00e8ge",
    "wof:name":"Jusqu'au Lever Du Jour",
    "wof:placetype":"venue"
},
  "geometry": {"coordinates":[5.8602561951,50.6260375977],"type":"Point"}
}