{
  "type": "Feature",
  "properties": {
    "iso:country":"BE",
    "sg:address":"Lindeveldstraat 43",
    "sg:city":"Geraardsbergen (zandbergen)",
    "sg:classifiers":[
        {
            "category":"Freight",
            "type":"Transportation"
        }
    ],
    "sg:phone":"+32 54 33 30 05",
    "sg:postcode":"9506",
    "sg:province":"Oost-Vlaanderen",
    "sg:tags":[
        "-",
        "transport"
    ],
    "wof:name":"Remue G",
    "wof:placetype":"venue"
},
  "geometry": {"coordinates":[3.9601809978,50.791809082],"type":"Point"}
}