{
  "type": "Feature",
  "properties": {
    "addr:full":"Place De Liberchies 106 Pont-\u00e0-celles (luttre) Hainaut 6238",
    "addr:housenumber":"106",
    "addr:postcode":"6238",
    "addr:street":"Place De Liberchies",
    "iso:country":"BE",
    "sg:address":"Place De Liberchies 106",
    "sg:city":"Pont-\u00e0-celles (luttre)",
    "sg:classifiers":[
        {
            "category":"Retail",
            "subcategory":"Auto Repair",
            "type":"Services"
        }
    ],
    "sg:phone":"+32 71 84 21 66",
    "sg:postcode":"6238",
    "sg:province":"Hainaut",
    "sg:tags":[
        "automobile-body"
    ],
    "wof:name":"Ruidant (garage) Sa",
    "wof:placetype":"venue"
},
  "geometry": {"coordinates":[4.404979229,50.513458252],"type":"Point"}
}