{
  "type": "Feature",
  "properties": {
    "iso:country":"BE",
    "sg:address":"Rijselstraat 200",
    "sg:city":"Menen",
    "sg:orig_category":"Alimentation sp\u00e9cialis\u00e9e",
    "sg:phone":"+32 56 51 89 54",
    "sg:postcode":"8930",
    "sg:province":"West-Vlaanderen",
    "wof:name":"Traiteur St.hubert",
    "wof:placetype":"venue"
},
  "geometry": {"coordinates":[3.1264369488,50.7894515991],"type":"Point"}
}