{
  "type": "Feature",
  "properties": {
    "addr:full":"Weegstraat 1 Aarschot (groot) Vlaams-Brabant 3201",
    "addr:housenumber":"1;3201",
    "addr:street":"Weegstraat;Groot Vlaams-Brabant",
    "iso:country":"BE",
    "sg:address":"Weegstraat 1",
    "sg:city":"Aarschot (groot)",
    "sg:orig_category":"Woningbouw",
    "sg:phone":"+32 16 56 92 29",
    "sg:postcode":"3201",
    "sg:province":"Vlaams-Brabant",
    "wof:name":"Gressens Daniel",
    "wof:placetype":"venue"
},
  "geometry": {"coordinates":[4.9100818634,51.0109367371],"type":"Point"}
}