{
  "type": "Feature",
  "properties": {
    "addr:full":"Kortrijksestraat 328 Kortrijk West-Vlaanderen 8501",
    "addr:housenumber":"328",
    "addr:postcode":"8501",
    "addr:street":"Kortrijksestraat",
    "iso:country":"BE",
    "sg:address":"Kortrijksestraat 328",
    "sg:city":"Kortrijk",
    "sg:orig_category":"Medische and orthopedische apparaten",
    "sg:phone":"+32 56 35 08 13",
    "sg:postcode":"8501",
    "sg:province":"West-Vlaanderen",
    "wof:name":"Huis Lastric",
    "wof:placetype":"venue"
},
  "geometry": {"coordinates":[3.2476799488,50.835521698],"type":"Point"}
}