{
  "type": "Feature",
  "properties": {
    "iso:country":"BE",
    "sg:address":"Lindestraat 56",
    "sg:city":"Mechelen",
    "sg:classifiers":[
        {
            "category":"Arena",
            "subcategory":"Sports Club",
            "type":"Entertainment"
        }
    ],
    "sg:phone":"+32 15 41 13 66",
    "sg:postcode":"2800",
    "sg:province":"Antwerpen",
    "sg:tags":[
        "de"
    ],
    "wof:name":"De Toekomst",
    "wof:placetype":"venue"
},
  "geometry": {"coordinates":[4.4786009789,51.0054397583],"type":"Point"}
}