{
  "type": "Feature",
  "properties": {
    "iso:country":"BE",
    "sg:address":"Stationsstraat 18b",
    "sg:city":"Lanaken",
    "sg:classifiers":[
        {
            "category":"Shopping",
            "subcategory":"Jewelry",
            "type":"Retail Goods"
        }
    ],
    "sg:phone":"+32 89 71 14 32",
    "sg:postcode":"3620",
    "sg:province":"Limburg",
    "sg:tags":[
        "purchase",
        "-",
        "sale",
        "gold"
    ],
    "wof:name":"Kraft Edelmetalen",
    "wof:placetype":"venue"
},
  "geometry": {"coordinates":[5.6503710747,50.8887214661],"type":"Point"}
}