{
  "type": "Feature",
  "properties": {
    "addr:full":"Sint-truidersteenweg 459 Hasselt Limburg 3500",
    "addr:housenumber":"459",
    "addr:postcode":"3500",
    "addr:street":"Sint-Truidersteenweg",
    "iso:country":"BE",
    "sg:address":"Sint-truidersteenweg 459",
    "sg:city":"Hasselt",
    "sg:orig_category":"Dierenartsen",
    "sg:phone":"+32 11 27 22 67",
    "sg:postcode":"3500",
    "sg:province":"Limburg",
    "wof:name":"Jan Van Diest",
    "wof:placetype":"venue"
},
  "geometry": {"coordinates":[5.327709198,50.9188766479],"type":"Point"}
}