{
  "type": "Feature",
  "properties": {
    "iso:country":"BE",
    "sg:address":"Westkapellestraat 64",
    "sg:city":"Knokke-heist",
    "sg:orig_category":"Blanchisseries and teintureries",
    "sg:phone":"+32 50 51 34 20",
    "sg:postcode":"8301",
    "sg:province":"West-Vlaanderen",
    "wof:name":"Mibomatic",
    "wof:placetype":"venue"
},
  "geometry": {"coordinates":[3.2547800541,51.3315315247],"type":"Point"}
}