{
  "type": "Feature",
  "properties": {
    "addr:full":"Quai Au Foin 55 Bruxelles Bruxelles-Capitale 1000",
    "addr:housenumber":"55",
    "addr:postcode":"1000",
    "addr:street":"Quai Au Foin",
    "iso:country":"BE",
    "sg:address":"Quai Au Foin 55",
    "sg:city":"Bruxelles",
    "sg:classifiers":[
        {
            "category":"Military Area",
            "subcategory":"Naval Base",
            "type":"Public Place"
        }
    ],
    "sg:phone":"+32 2 218 10 11",
    "sg:postcode":"1000",
    "sg:province":"Bruxelles-Capitale",
    "sg:tags":[
        "tubes",
        "valve",
        "electronic"
    ],
    "wof:name":"Halfin S.a.",
    "wof:placetype":"venue"
},
  "geometry": {"coordinates":[4.3491358757,50.8558197021],"type":"Point"}
}