{
  "type": "Feature",
  "properties": {
    "addr:full":"Chauss\u00c9e D'ixelles 319 Elsene/ixelles Bruxelles-Capitale 1050",
    "addr:housenumber":"319",
    "addr:postcode":"1050",
    "addr:street":"Chausse\u0301E D'Ixelles",
    "iso:country":"BE",
    "sg:address":"Chauss\u00c9e D'ixelles 319",
    "sg:city":"Elsene/ixelles",
    "sg:orig_category":"Salles de spectacles. Librairies. Restaurants",
    "sg:phone":"+32 2 646 97 86",
    "sg:postcode":"1050",
    "sg:province":"Bruxelles-Capitale",
    "wof:name":"Librairie Des Etangs",
    "wof:placetype":"venue"
},
  "geometry": {"coordinates":[4.3701882362,50.8290634155],"type":"Point"}
}