{
  "type": "Feature",
  "properties": {
    "addr:full":"Lauwestraat 67 Menen (rekkem) West-Vlaanderen 8930",
    "addr:housenumber":"67",
    "addr:postcode":"8930",
    "addr:street":"Lauwestraat",
    "iso:country":"BE",
    "sg:address":"Lauwestraat 67",
    "sg:city":"Menen (rekkem)",
    "sg:classifiers":[
        {
            "category":"Professional",
            "subcategory":"Credit Reporting & Collection",
            "type":"Services"
        }
    ],
    "sg:phone":"+32 56 23 52 01",
    "sg:postcode":"8930",
    "sg:province":"West-Vlaanderen",
    "sg:tags":[
        "bailiff"
    ],
    "wof:name":"Indekeu M",
    "wof:placetype":"venue"
},
  "geometry": {"coordinates":[3.1209149361,50.7961845398],"type":"Point"}
}