{
  "type": "Feature",
  "properties": {
    "addr:full":"Izegemstraat 5 Roeselare West-Vlaanderen 8800",
    "addr:housenumber":"5",
    "addr:postcode":"8800",
    "addr:street":"Izegemstraat",
    "iso:country":"BE",
    "sg:address":"Izegemstraat 5",
    "sg:city":"Roeselare",
    "sg:orig_category":"Artsen and specialisten",
    "sg:phone":"+32 51 20 66 85",
    "sg:postcode":"8800",
    "sg:province":"West-Vlaanderen",
    "wof:name":"J. Doornaert",
    "wof:placetype":"venue"
},
  "geometry": {"coordinates":[3.1571249962,50.9325256348],"type":"Point"}
}