{
  "type": "Feature",
  "properties": {
    "addr:full":"Gentsestraat 31 Izegem West-Vlaanderen 8870",
    "addr:housenumber":"31",
    "addr:postcode":"8870",
    "addr:street":"Gentsestraat",
    "iso:country":"BE",
    "sg:address":"Gentsestraat 31",
    "sg:city":"Izegem",
    "sg:orig_category":"Enseignement secondaire technique and professionnel",
    "sg:phone":"+32 51 30 42 25",
    "sg:postcode":"8870",
    "sg:province":"West-Vlaanderen",
    "wof:name":"Inst.de Pelichy Ave Maria",
    "wof:placetype":"venue"
},
  "geometry": {"coordinates":[3.2168700695,50.9173355103],"type":"Point"}
}