{
  "type": "Feature",
  "properties": {
    "iso:country":"BE",
    "sg:address":"Rue De La For\u00eat 1",
    "sg:city":"Tenneville",
    "sg:classifiers":[
        {
            "category":"Building & Trades",
            "subcategory":"Landscaping Services",
            "type":"Services"
        }
    ],
    "sg:phone":"+32 84 45 53 59",
    "sg:postcode":"6970",
    "sg:province":"Luxembourg",
    "sg:tags":[
        "gardening",
        "garden",
        "maintenance"
    ],
    "wof:name":"Louis V",
    "wof:placetype":"venue"
},
  "geometry": {"coordinates":[5.5086598396,50.0911903381],"type":"Point"}
}