{
  "type": "Feature",
  "properties": {
    "iso:country":"BE",
    "sg:address":"Av De L'esp\u00e9rance",
    "sg:city":"Fleurus",
    "sg:classifiers":[
        {
            "category":"Manufacturing",
            "subcategory":"Tools & Machinery",
            "type":"Manufacturing & Wholesale Goods"
        }
    ],
    "sg:phone":"+32 71 81 00 84",
    "sg:postcode":"6220",
    "sg:province":"Hainaut",
    "sg:tags":[
        "environment",
        "equipment",
        "-"
    ],
    "wof:name":"Iba Mediris",
    "wof:placetype":"venue"
},
  "geometry": {"coordinates":[4.5313301086,50.4716911316],"type":"Point"}
}