{
  "type": "Feature",
  "properties": {
    "iso:country":"BE",
    "sg:address":"Geldmuntstraat 48",
    "sg:city":"Brugge",
    "sg:orig_category":"Bagage and lederwaren",
    "sg:phone":"+32 50 33 31 41",
    "sg:postcode":"8000",
    "sg:province":"West-Vlaanderen",
    "wof:name":"Danneels Lederwaren",
    "wof:placetype":"venue"
},
  "geometry": {"coordinates":[3.2211899757,51.2083511353],"type":"Point"}
}