{
  "type": "Feature",
  "properties": {
    "addr:full":"Schuurstraat 7a Hasselt Limburg 3511",
    "addr:housenumber":"7a",
    "addr:postcode":"3511",
    "addr:street":"Schuurstraat",
    "iso:country":"BE",
    "sg:address":"Schuurstraat 7a",
    "sg:city":"Hasselt",
    "sg:orig_category":"Verlichting and huishoudartikelen",
    "sg:phone":"+32 11 25 19 48",
    "sg:postcode":"3511",
    "sg:province":"Limburg",
    "wof:name":"Knevels L",
    "wof:placetype":"venue"
},
  "geometry": {"coordinates":[5.2718071938,50.9744567871],"type":"Point"}
}