{
  "type": "Feature",
  "properties": {
    "addr:full":"Schutterijstraat 13b10 Deinze Oost-Vlaanderen 9800",
    "addr:housenumber":"13b10",
    "addr:postcode":"9800",
    "addr:street":"Schutterijstraat",
    "iso:country":"BE",
    "sg:address":"Schutterijstraat 13b10",
    "sg:city":"Deinze",
    "sg:orig_category":"Recouvrement de factures and \u00e9valuation de solvabilit\u00e9",
    "sg:phone":"+32 9 380 00 67",
    "sg:postcode":"9800",
    "sg:province":"Oost-Vlaanderen",
    "wof:name":"Immo-re",
    "wof:placetype":"venue"
},
  "geometry": {"coordinates":[3.5282230377,50.9851264954],"type":"Point"}
}