{
  "type": "Feature",
  "properties": {
    "iso:country":"BE",
    "sg:address":"Markettestraat 4",
    "sg:city":"Aalter",
    "sg:orig_category":"Eleveurs de bovins. Eleveurs and marchands de porcs",
    "sg:phone":"+32 9 374 26 52",
    "sg:postcode":"9881",
    "sg:province":"Oost-Vlaanderen",
    "wof:name":"Denis Lemey",
    "wof:placetype":"venue"
},
  "geometry": {"coordinates":[3.499448061,51.0708465576],"type":"Point"}
}