{
  "type": "Feature",
  "properties": {
    "addr:full":"Rue Du March\u00e9 Aux Fromages 22 Bruxelles Bruxelles-Capitale 1000",
    "addr:housenumber":"22",
    "addr:postcode":"1000",
    "addr:street":"Rue Du Marche\u0301 Aux Fromages",
    "iso:country":"BE",
    "sg:address":"Rue Du March\u00e9 Aux Fromages 22",
    "sg:city":"Bruxelles",
    "sg:classifiers":[
        {
            "category":"Shopping",
            "subcategory":"Clothing, Apparel, & Fashions",
            "type":"Retail Goods"
        }
    ],
    "sg:phone":"+32 2 514 23 96",
    "sg:postcode":"1000",
    "sg:province":"Bruxelles-Capitale",
    "sg:tags":[
        "clothing",
        "-",
        "gentleman"
    ],
    "wof:name":"Balthazar Sprl",
    "wof:placetype":"venue"
},
  "geometry": {"coordinates":[4.3533182144,50.8456726074],"type":"Point"}
}