{
  "type": "Feature",
  "properties": {
    "addr:full":"8890 Moorslede (groot) West-Vlaanderen 8890",
    "addr:postcode":"8890;8890",
    "addr:street":"West-Vlaanderen",
    "iso:country":"BE",
    "sg:address":"8890",
    "sg:city":"Moorslede (groot)",
    "sg:orig_category":"Pharmaciens",
    "sg:phone":"+32 900 10 500",
    "sg:postcode":"8890",
    "sg:province":"West-Vlaanderen",
    "wof:name":"Pharmacies De Garde",
    "wof:placetype":"venue"
},
  "geometry": {"coordinates":[3.0637769699,50.891456604],"type":"Point"}
}