{
  "type": "Feature",
  "properties": {
    "iso:country":"BE",
    "sg:address":"Marktstraat 29",
    "sg:city":"Harelbeke",
    "sg:orig_category":"Overheidsdiensten",
    "sg:phone":"+32 56 73 33 11",
    "sg:postcode":"8530",
    "sg:province":"West-Vlaanderen",
    "wof:name":"Stadsbestuur",
    "wof:placetype":"venue"
},
  "geometry": {"coordinates":[3.3104441166,50.8563194275],"type":"Point"}
}