{
  "type": "Feature",
  "properties": {
    "iso:country":"BE",
    "sg:address":"Rue Brun 35",
    "sg:city":"Andenne",
    "sg:classifiers":[
        {
            "category":"Shopping",
            "subcategory":"Clothing, Apparel, & Fashions",
            "type":"Retail Goods"
        }
    ],
    "sg:phone":"+32 85 84 39 47",
    "sg:postcode":"5300",
    "sg:province":"Namur",
    "sg:tags":[
        "underwear",
        "lingerie",
        "-"
    ],
    "wof:name":"Amelie Boutique",
    "wof:placetype":"venue"
},
  "geometry": {"coordinates":[5.0977368355,50.4880981445],"type":"Point"}
}