{
  "type": "Feature",
  "properties": {
    "iso:country":"BE",
    "sg:address":"Rue Martinsart 33",
    "sg:city":"Froidchapelle",
    "sg:orig_category":"Elektrische installaties voor woningen Industri\u00eble elektrische installaties",
    "sg:phone":"+32 60 41 20 18",
    "sg:postcode":"6440",
    "sg:province":"Hainaut",
    "wof:name":"Valentin Ets.",
    "wof:placetype":"venue"
},
  "geometry": {"coordinates":[4.3531842232,50.1483573914],"type":"Point"}
}