{
  "type": "Feature",
  "properties": {
    "addr:full":"Groenestraat 535 Roeselare West-Vlaanderen 8800",
    "addr:housenumber":"535",
    "addr:postcode":"8800",
    "addr:street":"Groenestraat",
    "iso:country":"BE",
    "sg:address":"Groenestraat 535",
    "sg:city":"Roeselare",
    "sg:classifiers":[
        {
            "category":"Building & Trades",
            "subcategory":"Landscaping Services",
            "type":"Services"
        }
    ],
    "sg:phone":"+32 51 20 23 45",
    "sg:postcode":"8800",
    "sg:province":"West-Vlaanderen",
    "sg:tags":[
        "gardening",
        "garden",
        "maintenance"
    ],
    "wof:name":"Van Steenkiste Bvba",
    "wof:placetype":"venue"
},
  "geometry": {"coordinates":[3.0824999809,50.9344062805],"type":"Point"}
}