{
  "type": "Feature",
  "properties": {
    "iso:country":"BE",
    "sg:address":"Ancienne Ch\u00c9e De Haecht 35",
    "sg:city":"Brussel/bruxelles",
    "sg:orig_category":"M\u00e9decins and sp\u00e9cialistes",
    "sg:phone":"+32 2 245 87 93",
    "sg:postcode":"1130",
    "sg:province":"Bruxelles-Capitale",
    "wof:name":"Frank De Veirman",
    "wof:placetype":"venue"
},
  "geometry": {"coordinates":[4.4102201462,50.8780593872],"type":"Point"}
}