{
  "type": "Feature",
  "properties": {
    "addr:full":"Overheide 36 Puurs Antwerpen 2870",
    "addr:housenumber":"36",
    "addr:postcode":"2870",
    "addr:street":"Overheide",
    "iso:country":"BE",
    "sg:address":"Overheide 36",
    "sg:city":"Puurs",
    "sg:orig_category":"Eleveurs de bovins. Producteurs de l\u00e9gumes",
    "sg:phone":"+32 3 889 12 17",
    "sg:postcode":"2870",
    "sg:province":"Antwerpen",
    "wof:name":"Stefan Peeters",
    "wof:placetype":"venue"
},
  "geometry": {"coordinates":[4.2712368965,51.0653686523],"type":"Point"}
}