{
  "type": "Feature",
  "properties": {
    "iso:country":"BE",
    "sg:address":"Schansstraat 10",
    "sg:city":"Lommel",
    "sg:orig_category":"Installation \u00e9lectrique r\u00e9sidentielle",
    "sg:phone":"+32 11 54 44 09",
    "sg:postcode":"3920",
    "sg:province":"Limburg",
    "wof:name":"Frank Gerits",
    "wof:placetype":"venue"
},
  "geometry": {"coordinates":[5.3499298096,51.228187561],"type":"Point"}
}