{
  "type": "Feature",
  "properties": {
    "iso:country":"BE",
    "sg:address":"Rue Saint-jacques 350",
    "sg:city":"Dinant",
    "sg:classifiers":[
        {
            "category":"Retail",
            "subcategory":"Event Space",
            "type":"Services"
        }
    ],
    "sg:phone":"+32 82 22 29 38",
    "sg:postcode":"5500",
    "sg:province":"Namur",
    "sg:tags":[
        "telecommunication"
    ],
    "wof:name":"Ciset International S.a.",
    "wof:placetype":"venue"
},
  "geometry": {"coordinates":[4.9363698959,50.2666931152],"type":"Point"}
}