{
  "type": "Feature",
  "properties": {
    "iso:country":"BE",
    "sg:address":"Torenveld 140",
    "sg:city":"Tessenderlo",
    "sg:orig_category":"Ordinateurs and \u00e9quipement informatique",
    "sg:phone":"+32 13 66 74 01",
    "sg:postcode":"3980",
    "sg:province":"Limburg",
    "wof:name":"Computronics Cv",
    "wof:placetype":"venue"
},
  "geometry": {"coordinates":[5.0824809074,51.0558052063],"type":"Point"}
}