{
  "type": "Feature",
  "properties": {
    "iso:country":"BE",
    "sg:address":"Gelmelstraat 30",
    "sg:city":"Hoogstraten",
    "sg:orig_category":"Centres de relaxation and bien-\u00eatre",
    "sg:phone":"+32 3 314 47 66",
    "sg:postcode":"2320",
    "sg:province":"Antwerpen",
    "wof:name":"Solarium Ipatinga",
    "wof:placetype":"venue"
},
  "geometry": {"coordinates":[4.7641458511,51.4019165039],"type":"Point"}
}