{
  "type": "Feature",
  "properties": {
    "addr:full":"Leuvensesteenweg 703 Mechelen Antwerpen 2800",
    "addr:housenumber":"703",
    "addr:postcode":"2800",
    "addr:street":"Leuvensesteenweg",
    "iso:country":"BE",
    "sg:address":"Leuvensesteenweg 703",
    "sg:city":"Mechelen",
    "sg:classifiers":[
        {
            "category":"Bars & Pubs",
            "type":"Food & Drink"
        }
    ],
    "sg:phone":"+32 15 51 51 61",
    "sg:postcode":"2800",
    "sg:province":"Antwerpen",
    "wof:name":"Hoevehof",
    "wof:placetype":"venue"
},
  "geometry": {"coordinates":[4.4995799065,51.0152511597],"type":"Point"}
}