{
  "type": "Feature",
  "properties": {
    "iso:country":"BE",
    "sg:address":"Capucienenlaan 41",
    "sg:city":"Aalst",
    "sg:classifiers":[
        {
            "category":"Professional",
            "subcategory":"Management & Consulting",
            "type":"Services"
        }
    ],
    "sg:phone":"+32 53 78 63 00",
    "sg:postcode":"9300",
    "sg:province":"Oost-Vlaanderen",
    "sg:tags":[
        "consultant",
        "law"
    ],
    "wof:name":"Uyttendaele Zakenkantoor Nv",
    "wof:placetype":"venue"
},
  "geometry": {"coordinates":[4.0285048485,50.9357223511],"type":"Point"}
}