{
  "type": "Feature",
  "properties": {
    "addr:full":"Lange Munt 55 Gent Oost-Vlaanderen 9000",
    "addr:housenumber":"55",
    "addr:postcode":"9000",
    "addr:street":"Lange Munt;Oost-Vlaanderen",
    "iso:country":"BE",
    "sg:address":"Lange Munt 55",
    "sg:city":"Gent",
    "sg:orig_category":"Souvenirs and objets artisanaux. Instituts de beaut\u00e9",
    "sg:phone":"+32 9 225 37 04",
    "sg:postcode":"9000",
    "sg:province":"Oost-Vlaanderen",
    "wof:name":"Lady's Nagelstudio",
    "wof:placetype":"venue"
},
  "geometry": {"coordinates":[3.7237970829,51.0571022034],"type":"Point"}
}