{
  "type": "Feature",
  "properties": {
    "iso:country":"BE",
    "sg:address":"Abeelstraat 15",
    "sg:city":"Waregem",
    "sg:orig_category":"V\u00eatements",
    "sg:phone":"+32 56 60 38 56",
    "sg:postcode":"8793",
    "sg:province":"West-Vlaanderen",
    "wof:name":"De Coninck",
    "wof:placetype":"venue"
},
  "geometry": {"coordinates":[3.4063639641,50.9064826965],"type":"Point"}
}