{
  "type": "Feature",
  "properties": {
    "addr:full":"Schavolliestraat 64 Gooik Vlaams-Brabant 1755",
    "addr:housenumber":"64",
    "addr:postcode":"1755",
    "addr:street":"Schavolliestraat",
    "iso:country":"BE",
    "sg:address":"Schavolliestraat 64",
    "sg:city":"Gooik",
    "sg:orig_category":"Plomberie, chauffage and installations sanitaires. Charpentes and couvertures",
    "sg:phone":"+32 54 56 83 94",
    "sg:postcode":"1755",
    "sg:province":"Vlaams-Brabant",
    "wof:name":"Raf Peeters",
    "wof:placetype":"venue"
},
  "geometry": {"coordinates":[4.049685955,50.763759613],"type":"Point"}
}