{
  "type": "Feature",
  "properties": {
    "iso:country":"BE",
    "sg:address":"Boulevard Du Tivoli 2bb",
    "sg:city":"La Louviere",
    "sg:orig_category":"Enseignement secondaire technique and professionnel. Enseignement secondaire g\u00e9n\u00e9ral",
    "sg:phone":"+32 64 22 65 49",
    "sg:postcode":"7100",
    "sg:province":"Hainaut",
    "wof:name":"Ath\u00c9n\u00c9e Provincial",
    "wof:placetype":"venue"
},
  "geometry": {"coordinates":[4.2004699707,50.4794197083],"type":"Point"}
}