{
  "type": "Feature",
  "properties": {
    "iso:country":"BE",
    "sg:address":"Binnensteenweg 182",
    "sg:city":"Boechout",
    "sg:classifiers":[
        {
            "category":"Arts & Performance",
            "subcategory":"Theater",
            "type":"Entertainment"
        }
    ],
    "sg:phone":"+32 3 454 64 42",
    "sg:postcode":"2530",
    "sg:province":"Antwerpen",
    "sg:tags":[
        "theatrical",
        "agency"
    ],
    "wof:name":"All Set",
    "wof:placetype":"venue"
},
  "geometry": {"coordinates":[4.4914097786,51.1665763855],"type":"Point"}
}