{
  "type": "Feature",
  "properties": {
    "addr:full":"Gaverlandstraat 111 Beveren Oost-Vlaanderen 9120",
    "addr:housenumber":"111",
    "addr:postcode":"9120",
    "addr:street":"Gaverlandstraat",
    "iso:country":"BE",
    "sg:address":"Gaverlandstraat 111",
    "sg:city":"Beveren",
    "sg:orig_category":"Enseignement maternel and primaire",
    "sg:phone":"+32 3 775 69 41",
    "sg:postcode":"9120",
    "sg:province":"Oost-Vlaanderen",
    "wof:name":"Vrije Kleuterschool",
    "wof:placetype":"venue"
},
  "geometry": {"coordinates":[4.257144928,51.2248878479],"type":"Point"}
}