{
  "type": "Feature",
  "properties": {
    "iso:country":"BE",
    "sg:address":"Palingstraat 113",
    "sg:city":"Puurs",
    "sg:classifiers":[
        {
            "category":"Insurance",
            "subcategory":"Life Insurance",
            "type":"Services"
        }
    ],
    "sg:phone":"+32 3 889 00 84",
    "sg:postcode":"2870",
    "sg:province":"Antwerpen",
    "sg:tags":[
        "assurance"
    ],
    "wof:name":"R. Apers",
    "wof:placetype":"venue"
},
  "geometry": {"coordinates":[4.2794060707,51.0718727112],"type":"Point"}
}