{
  "type": "Feature",
  "properties": {
    "addr:full":"Pastoor Coplaan 33 Zwijndrecht Antwerpen 2070",
    "addr:housenumber":"33",
    "addr:postcode":"2070",
    "addr:street":"Pastoor Coplaan",
    "iso:country":"BE",
    "sg:address":"Pastoor Coplaan 33",
    "sg:city":"Zwijndrecht",
    "sg:orig_category":"Enseignement maternel and primaire",
    "sg:phone":"+32 3 252 54 60",
    "sg:postcode":"2070",
    "sg:province":"Antwerpen",
    "wof:name":"Vrije Kleuterschool",
    "wof:placetype":"venue"
},
  "geometry": {"coordinates":[4.3325948715,51.2120780945],"type":"Point"}
}