{
  "type": "Feature",
  "properties": {
    "iso:country":"BE",
    "sg:address":"Mottestraat 20",
    "sg:city":"Aarschot",
    "sg:orig_category":"Travail and traitement du bois. Bois Quincailleries",
    "sg:phone":"+32 16 50 24 38",
    "sg:postcode":"3200",
    "sg:province":"Vlaams-Brabant",
    "wof:name":"De Motte",
    "wof:placetype":"venue"
},
  "geometry": {"coordinates":[4.8643608093,50.9806213379],"type":"Point"}
}