{
  "type": "Feature",
  "properties": {
    "iso:country":"BE",
    "sg:address":"Wayezstraat 140",
    "sg:city":"Anderlecht/anderlecht",
    "sg:orig_category":"Brood, gebak and snoepgoed",
    "sg:phone":"+32 2 522 59 13",
    "sg:postcode":"1070",
    "sg:province":"Bruxelles-Capitale",
    "wof:name":"Leonidas",
    "wof:placetype":"venue"
},
  "geometry": {"coordinates":[4.310336113,50.835308075],"type":"Point"}
}