{
  "type": "Feature",
  "properties": {
    "addr:full":"Rue Solleveld 38 Bruxelles (woluwe-saint-lambert) Bruxelles-Capitale 1200",
    "addr:housenumber":"38",
    "addr:postcode":"1200",
    "addr:street":"Rue Solleveld",
    "iso:country":"BE",
    "sg:address":"Rue Solleveld 38",
    "sg:city":"Bruxelles (woluwe-saint-lambert)",
    "sg:classifiers":[
        {
            "category":"Building & Trades",
            "subcategory":"Electrical",
            "type":"Services"
        }
    ],
    "sg:phone":"+32 2 772 69 89",
    "sg:postcode":"1200",
    "sg:province":"Bruxelles-Capitale",
    "sg:tags":[
        "electric",
        "-",
        "housewiring",
        "contractor"
    ],
    "wof:name":"Ruth M",
    "wof:placetype":"venue"
},
  "geometry": {"coordinates":[4.4287228584,50.8451766968],"type":"Point"}
}