{
  "type": "Feature",
  "properties": {
    "addr:full":"Herman Teirlinckstraat 4 Zele Oost-Vlaanderen 9240",
    "addr:housenumber":"4",
    "addr:postcode":"9240",
    "addr:street":"Herman Teirlinckstraat",
    "iso:country":"BE",
    "sg:address":"Herman Teirlinckstraat 4",
    "sg:city":"Zele",
    "sg:orig_category":"Installation \u00e9lectrique r\u00e9sidentielle. Installation \u00e9lectrique industrielle",
    "sg:phone":"+32 52 44 86 10",
    "sg:postcode":"9240",
    "sg:province":"Oost-Vlaanderen",
    "wof:name":"Van Lokeren Filip",
    "wof:placetype":"venue"
},
  "geometry": {"coordinates":[4.0377178192,51.057926178],"type":"Point"}
}