{
  "type": "Feature",
  "properties": {
    "addr:full":"De Merodedreef 137 Westerlo Antwerpen 2260",
    "addr:housenumber":"137",
    "addr:postcode":"2260",
    "addr:street":"De Merodedreef",
    "iso:country":"BE",
    "sg:address":"De Merodedreef 137",
    "sg:city":"Westerlo",
    "sg:classifiers":[
        {
            "category":"Retail",
            "subcategory":"Repair Shop",
            "type":"Services"
        }
    ],
    "sg:phone":"+32 14 54 91 46",
    "sg:postcode":"2260",
    "sg:province":"Antwerpen",
    "sg:tags":[
        "upholsterer"
    ],
    "wof:name":"Colors Garnierderij Bvba",
    "wof:placetype":"venue"
},
  "geometry": {"coordinates":[4.9236688614,51.0919723511],"type":"Point"}
}