{
  "type": "Feature",
  "properties": {
    "addr:full":"Rue Des Grands Bureaux 2 Binche Hainaut 7134",
    "addr:housenumber":"2",
    "addr:postcode":"7134",
    "addr:street":"Rue Des Grands Bureaux",
    "iso:country":"BE",
    "sg:address":"Rue Des Grands Bureaux 2",
    "sg:city":"Binche",
    "sg:orig_category":"Woningbouw",
    "sg:phone":"+32 64 33 46 57",
    "sg:postcode":"7134",
    "sg:province":"Hainaut",
    "wof:name":"Travimmo",
    "wof:placetype":"venue"
},
  "geometry": {"coordinates":[4.1973471642,50.4144134521],"type":"Point"}
}