{
  "type": "Feature",
  "properties": {
    "iso:country":"BE",
    "sg:address":"Amerikalei 122",
    "sg:city":"Antwerpen",
    "sg:classifiers":[
        {
            "category":"Professional",
            "subcategory":"Employment Agencies",
            "type":"Services"
        }
    ],
    "sg:phone":"+32 9 230 50 30",
    "sg:postcode":"2000",
    "sg:province":"Antwerpen",
    "sg:tags":[
        "consulting",
        "outplacement"
    ],
    "wof:name":"Right Management Consultants Nv",
    "wof:placetype":"venue"
},
  "geometry": {"coordinates":[3.7357590199,51.0347328186],"type":"Point"}
}