{
  "type": "Feature",
  "properties": {
    "iso:country":"BE",
    "sg:address":"Ooststraat 55b",
    "sg:city":"Veurne",
    "sg:classifiers":[
        {
            "category":"Cafe",
            "type":"Food & Drink"
        }
    ],
    "sg:phone":"+32 58 28 73 43",
    "sg:postcode":"8630",
    "sg:province":"West-Vlaanderen",
    "sg:tags":[
        "snack-bars"
    ],
    "wof:name":"Pitta Rappadocia",
    "wof:placetype":"venue"
},
  "geometry": {"coordinates":[2.6670799255,51.0729675293],"type":"Point"}
}