{
  "type": "Feature",
  "properties": {
    "addr:full":"Rue De L\u00b4 Etuve 11 Li\u00c8ge Li\u00e8ge 4000",
    "addr:housenumber":"11",
    "addr:postcode":"4000",
    "addr:street":"Rue De L\u00b4 Etuve",
    "iso:country":"BE",
    "sg:address":"Rue De L\u00b4 Etuve 11",
    "sg:city":"Li\u00c8ge",
    "sg:orig_category":"Ordinateurs and \u00e9quipement informatique",
    "sg:phone":"+32 4 226 38 17",
    "sg:postcode":"4000",
    "sg:province":"Li\u00e8ge",
    "wof:name":"Micro D.p.c.",
    "wof:placetype":"venue"
},
  "geometry": {"coordinates":[5.5749621391,50.642074585],"type":"Point"}
}