{
  "type": "Feature",
  "properties": {
    "addr:full":"Rue Saint-sang 112 Sambreville Namur 5060",
    "addr:housenumber":"112",
    "addr:postcode":"5060",
    "addr:street":"Rue Saint-Sang",
    "iso:country":"BE",
    "sg:address":"Rue Saint-sang 112",
    "sg:city":"Sambreville",
    "sg:orig_category":"Dierenartsen",
    "sg:phone":"+32 71 77 26 84",
    "sg:postcode":"5060",
    "sg:province":"Namur",
    "wof:name":"Fr. Piedboeuf",
    "wof:placetype":"venue"
},
  "geometry": {"coordinates":[4.6312541962,50.4403953552],"type":"Point"}
}