{
  "type": "Feature",
  "properties": {
    "iso:country":"BE",
    "sg:address":"Driesstraat 46",
    "sg:city":"Melle",
    "sg:orig_category":"Sportclubs",
    "sg:phone":"+32 9 252 15 34",
    "sg:postcode":"9090",
    "sg:province":"Oost-Vlaanderen",
    "wof:name":"B.b.c. Melle",
    "wof:placetype":"venue"
},
  "geometry": {"coordinates":[3.7901940346,51.0034828186],"type":"Point"}
}