{
  "type": "Feature",
  "properties": {
    "iso:country":"BE",
    "sg:address":"Noorderlaan 77",
    "sg:city":"Antwerpen",
    "sg:classifiers":[
        {
            "category":"Autos & Motor Vehicles",
            "subcategory":"Auto Supplies",
            "type":"Retail Goods"
        }
    ],
    "sg:phone":"+32 3 544 81 50",
    "sg:postcode":"2030",
    "sg:province":"Antwerpen",
    "sg:tags":[
        "automobile",
        "accessory"
    ],
    "wof:name":"Central Auto Nv",
    "wof:placetype":"venue"
},
  "geometry": {"coordinates":[4.4197978973,51.253704071],"type":"Point"}
}