{
  "type": "Feature",
  "properties": {
    "addr:full":"Pontstraat 100 Sint-martens-latem (deurle) Oost-Vlaanderen 9831",
    "addr:housenumber":"100",
    "addr:postcode":"9831",
    "addr:street":"Pontstraat",
    "iso:country":"BE",
    "sg:address":"Pontstraat 100",
    "sg:city":"Sint-martens-latem (deurle)",
    "sg:classifiers":[
        {
            "category":"Professional",
            "subcategory":"Management & Consulting",
            "type":"Services"
        }
    ],
    "sg:phone":"+32 9 281 23 64",
    "sg:postcode":"9831",
    "sg:province":"Oost-Vlaanderen",
    "sg:tags":[
        "consultant"
    ],
    "wof:name":"Ulysse",
    "wof:placetype":"venue"
},
  "geometry": {"coordinates":[3.5983428955,51.0086326599],"type":"Point"}
}