{
  "type": "Feature",
  "properties": {
    "iso:country":"BE",
    "sg:address":"Terhove 141",
    "sg:city":"Borgloon",
    "sg:orig_category":"Eleveurs and marchands de porcs",
    "sg:phone":"+32 12 23 18 00",
    "sg:postcode":"3840",
    "sg:province":"Limburg",
    "wof:name":"Nicolas De Schaetzen Van Brienen",
    "wof:placetype":"venue"
},
  "geometry": {"coordinates":[5.3441700935,50.8012466431],"type":"Point"}
}