{
  "type": "Feature",
  "properties": {
    "addr:full":"Square Larousse 1 Vorst/forest Bruxelles-Capitale 1190",
    "addr:housenumber":"1",
    "addr:postcode":"1190",
    "addr:street":"Square Larousse;/ Forest",
    "iso:country":"BE",
    "sg:address":"Square Larousse 1",
    "sg:city":"Vorst/forest",
    "sg:classifiers":[
        {
            "category":"Professional",
            "subcategory":"Business Services",
            "type":"Services"
        }
    ],
    "sg:phone":"+32 2 346 90 85",
    "sg:postcode":"1190",
    "sg:province":"Bruxelles-Capitale",
    "sg:tags":[
        "aux",
        "diver",
        "entreprises"
    ],
    "wof:name":"Bureau Bialek & Partners",
    "wof:placetype":"venue"
},
  "geometry": {"coordinates":[4.3504428864,50.8206329346],"type":"Point"}
}