{
  "type": "Feature",
  "properties": {
    "iso:country":"BE",
    "sg:address":"Dennendreef 26",
    "sg:city":"Nevele",
    "sg:orig_category":"Brood, gebak and snoepgoed",
    "sg:phone":"+32 9 371 57 82",
    "sg:postcode":"9850",
    "sg:province":"Oost-Vlaanderen",
    "wof:name":"Jozef De Buck",
    "wof:placetype":"venue"
},
  "geometry": {"coordinates":[3.5763339996,51.0610389709],"type":"Point"}
}