{
  "type": "Feature",
  "properties": {
    "addr:full":"Chauss\u00e9e D'alsemberg 449 Bruxelles (uccle) Bruxelles-Capitale 1180",
    "addr:housenumber":"449",
    "addr:postcode":"1180",
    "addr:street":"Chausse\u0301E D'Alsemberg",
    "iso:country":"BE",
    "sg:address":"Chauss\u00e9e D'alsemberg 449",
    "sg:city":"Bruxelles (uccle)",
    "sg:classifiers":[
        {
            "category":"Retail",
            "subcategory":"Laundry & Dry Cleaning",
            "type":"Services"
        }
    ],
    "sg:phone":"+32 2 347 03 42",
    "sg:postcode":"1180",
    "sg:province":"Bruxelles-Capitale",
    "sg:tags":[
        "self",
        "-"
    ],
    "wof:name":"Friginet",
    "wof:placetype":"venue"
},
  "geometry": {"coordinates":[4.3382611275,50.8124694824],"type":"Point"}
}