{
  "type": "Feature",
  "properties": {
    "iso:country":"BE",
    "sg:address":"Slachthuisstraat 19",
    "sg:city":"Turnhout",
    "sg:classifiers":[
        {
            "category":"Freight",
            "type":"Transportation"
        }
    ],
    "sg:phone":"+32 14 47 14 70",
    "sg:postcode":"2300",
    "sg:province":"Antwerpen",
    "sg:tags":[
        "-",
        "transport"
    ],
    "wof:name":"Transport Radar Bvba",
    "wof:placetype":"venue"
},
  "geometry": {"coordinates":[4.9242968559,51.3043251038],"type":"Point"}
}