{
  "type": "Feature",
  "properties": {
    "iso:country":"BE",
    "sg:address":"Sankt-vitherstrasse 94",
    "sg:city":"Amel/ambleve",
    "sg:orig_category":"Pain, p\u00e2tisseries and confiseries",
    "sg:phone":"+32 80 34 97 55",
    "sg:postcode":"4770",
    "sg:province":"Li\u00e8ge",
    "wof:name":"Marcel Feltes",
    "wof:placetype":"venue"
},
  "geometry": {"coordinates":[6.1162648201,50.331703186],"type":"Point"}
}