{
  "type": "Feature",
  "properties": {
    "addr:full":"Rue J Cerexhe 26-28 Verviers (grand) Li\u00e8ge 4800",
    "addr:postcode":"26-28;4800",
    "addr:street":"Rue J Cerexhe",
    "iso:country":"BE",
    "sg:address":"Rue J Cerexhe 26-28",
    "sg:city":"Verviers (grand)",
    "sg:orig_category":"Instituts de beaut\u00e9",
    "sg:phone":"+32 87 31 72 48",
    "sg:postcode":"4800",
    "sg:province":"Li\u00e8ge",
    "wof:name":"Contours",
    "wof:placetype":"venue"
},
  "geometry": {"coordinates":[5.8594508171,50.5917663574],"type":"Point"}
}