{
  "type": "Feature",
  "properties": {
    "iso:country":"BE",
    "sg:address":"Dourdanstraat 68",
    "sg:city":"Wervik (geluwe)",
    "sg:classifiers":[
        {
            "category":"Retail",
            "subcategory":"Repair Shop",
            "type":"Services"
        }
    ],
    "sg:phone":"+32 56 53 18 12",
    "sg:postcode":"8940",
    "sg:province":"West-Vlaanderen",
    "sg:tags":[
        "-",
        "clothing",
        "alteration"
    ],
    "wof:name":"Heidi Retouches & Maatkleding",
    "wof:placetype":"venue"
},
  "geometry": {"coordinates":[3.0650498867,50.8089485168],"type":"Point"}
}