{
  "type": "Feature",
  "properties": {
    "addr:full":"Rue De Schramberg 30 Charleroi (marcinelle) Hainaut 6001",
    "addr:housenumber":"30",
    "addr:postcode":"6001",
    "addr:street":"Rue De Schramberg",
    "iso:country":"BE",
    "sg:address":"Rue De Schramberg 30",
    "sg:city":"Charleroi (marcinelle)",
    "sg:classifiers":[
        {
            "category":"Personal",
            "subcategory":"Nail Salon",
            "type":"Services"
        }
    ],
    "sg:phone":"+32 71 47 89 73",
    "sg:postcode":"6001",
    "sg:province":"Hainaut",
    "sg:tags":[
        "pedicure"
    ],
    "wof:name":"Fontaine N",
    "wof:placetype":"venue"
},
  "geometry": {"coordinates":[4.4236278534,50.3935585022],"type":"Point"}
}