{
  "type": "Feature",
  "properties": {
    "iso:country":"BE",
    "sg:address":"Molenlaan 13",
    "sg:city":"Lichtervelde",
    "sg:orig_category":"Kapsalons",
    "sg:phone":"+32 51 72 41 38",
    "sg:postcode":"8810",
    "sg:province":"West-Vlaanderen",
    "wof:name":"Coiffure Nadine",
    "wof:placetype":"venue"
},
  "geometry": {"coordinates":[3.1505219936,51.0245933533],"type":"Point"}
}