{
  "type": "Feature",
  "properties": {
    "addr:full":"Lentestraat 3 Ronse Oost-Vlaanderen 9600",
    "addr:housenumber":"3",
    "addr:postcode":"9600",
    "addr:street":"Lentestraat",
    "iso:country":"BE",
    "sg:address":"Lentestraat 3",
    "sg:city":"Ronse",
    "sg:orig_category":"Installatie van houten of kunststof schrijnwerk Woningbouw",
    "sg:phone":"+32 55 21 07 28",
    "sg:postcode":"9600",
    "sg:province":"Oost-Vlaanderen",
    "wof:name":"Vandermeulen",
    "wof:placetype":"venue"
},
  "geometry": {"coordinates":[3.5524699688,50.7533607483],"type":"Point"}
}