{
  "type": "Feature",
  "properties": {
    "iso:country":"BE",
    "sg:address":"Pelserstraat 4",
    "sg:city":"Maaseik",
    "sg:orig_category":"Verlichting and huishoudartikelen",
    "sg:phone":"+32 89 56 44 77",
    "sg:postcode":"3680",
    "sg:province":"Limburg",
    "wof:name":"Decorette Reuskens",
    "wof:placetype":"venue"
},
  "geometry": {"coordinates":[5.7902541161,51.095993042],"type":"Point"}
}