{
  "type": "Feature",
  "properties": {
    "iso:country":"BE",
    "sg:address":"Rue De Marcinelle 81",
    "sg:city":"Ham-sur-heure-nalinnes (nalinnes)",
    "sg:classifiers":[
        {
            "category":"Retail",
            "subcategory":"Veterinary Services",
            "type":"Services"
        }
    ],
    "sg:phone":"+32 71 21 83 23",
    "sg:postcode":"6120",
    "sg:province":"Hainaut",
    "sg:tags":[
        "veterinarian"
    ],
    "wof:name":"Lembourg Jf",
    "wof:placetype":"venue"
},
  "geometry": {"coordinates":[4.4408168793,50.344203949],"type":"Point"}
}