{
  "type": "Feature",
  "properties": {
    "addr:full":"Avenue De Merode 17 Rixensart Brabant Wallon 1330",
    "addr:housenumber":"17",
    "addr:postcode":"1330",
    "addr:street":"Avenue De Merode;Wallon",
    "iso:country":"BE",
    "sg:address":"Avenue De Merode 17",
    "sg:city":"Rixensart",
    "sg:classifiers":[
        {
            "category":"Food & Beverages",
            "subcategory":"Fruits & Vegetables",
            "type":"Retail Goods"
        }
    ],
    "sg:phone":"+32 2 653 15 70",
    "sg:postcode":"1330",
    "sg:province":"Brabant Wallon",
    "sg:tags":[
        "-"
    ],
    "wof:name":"Maraicher (le)",
    "wof:placetype":"venue"
},
  "geometry": {"coordinates":[4.5288472176,50.7125053406],"type":"Point"}
}