{
  "type": "Feature",
  "properties": {
    "addr:full":"Zuidschotestraat 43 Lo-reninge West-Vlaanderen 8647",
    "addr:housenumber":"43",
    "addr:postcode":"8647",
    "addr:street":"Zuidschotestraat",
    "iso:country":"BE",
    "sg:address":"Zuidschotestraat 43",
    "sg:city":"Lo-reninge",
    "sg:orig_category":"Rundveehouders",
    "sg:phone":"+32 57 42 21 12",
    "sg:postcode":"8647",
    "sg:province":"West-Vlaanderen",
    "wof:name":"Jan Segers",
    "wof:placetype":"venue"
},
  "geometry": {"coordinates":[2.8158330917,50.923122406],"type":"Point"}
}