{
  "type": "Feature",
  "properties": {
    "iso:country":"BE",
    "sg:address":"Rue De Namur 24ba",
    "sg:city":"Wavre",
    "sg:orig_category":"Boekhandels",
    "sg:phone":"+32 10 22 76 33",
    "sg:postcode":"1300",
    "sg:province":"Brabant Wallon",
    "wof:name":"Maison Aladin",
    "wof:placetype":"venue"
},
  "geometry": {"coordinates":[4.6118907928,50.7128143311],"type":"Point"}
}