{
  "type": "Feature",
  "properties": {
    "addr:full":"Groenhove 13 Deinze (wontergem) Oost-Vlaanderen 9800",
    "addr:housenumber":"13",
    "addr:postcode":"9800",
    "addr:street":"Groenhove",
    "iso:country":"BE",
    "sg:address":"Groenhove 13",
    "sg:city":"Deinze (wontergem)",
    "sg:classifiers":[
        {
            "category":"Wholesale",
            "subcategory":"Fruits & Vegetables",
            "type":"Manufacturing & Wholesale Goods"
        }
    ],
    "sg:phone":"+32 51 63 58 68",
    "sg:postcode":"9800",
    "sg:province":"Oost-Vlaanderen",
    "sg:tags":[
        "whol",
        "-"
    ],
    "wof:name":"Lukafruit",
    "wof:placetype":"venue"
},
  "geometry": {"coordinates":[3.4392011166,50.9768371582],"type":"Point"}
}