{
  "type": "Feature",
  "properties": {
    "addr:full":"Rue Des Grandes Vall\u00e9es 18 Charleroi (gilly) Hainaut 6060",
    "addr:housenumber":"18",
    "addr:postcode":"6060",
    "addr:street":"Rue Des Grandes Valle\u0301Es",
    "iso:country":"BE",
    "sg:address":"Rue Des Grandes Vall\u00e9es 18",
    "sg:city":"Charleroi (gilly)",
    "sg:classifiers":[
        {
            "category":"Education",
            "subcategory":"School",
            "type":"Public Place"
        }
    ],
    "sg:phone":"+32 71 41 38 58",
    "sg:postcode":"6060",
    "sg:province":"Hainaut",
    "sg:tags":[
        "secondary"
    ],
    "wof:name":"Lyc\u00e9e Fran\u00e7ois De Sales",
    "wof:placetype":"venue"
},
  "geometry": {"coordinates":[4.4880981445,50.4251937866],"type":"Point"}
}