{
  "type": "Feature",
  "properties": {
    "iso:country":"BE",
    "sg:address":"Rue De La Place 1",
    "sg:city":"Gembloux-sur-orneau (grand-leez)",
    "sg:classifiers":[
        {
            "category":"Bars & Pubs",
            "type":"Food & Drink"
        }
    ],
    "sg:phone":"+32 81 64 02 82",
    "sg:postcode":"5031",
    "sg:province":"Namur",
    "wof:name":"Sportifs (aux)",
    "wof:placetype":"venue"
},
  "geometry": {"coordinates":[4.7657661438,50.5822525024],"type":"Point"}
}