{
  "type": "Feature",
  "properties": {
    "addr:full":"Rue G\u00e9n\u00e9raux Cuvelier 11a Florenville Luxembourg 6820",
    "addr:housenumber":"11a",
    "addr:postcode":"6820",
    "addr:street":"Rue Ge\u0301Ne\u0301Raux Cuvelier",
    "iso:country":"BE",
    "sg:address":"Rue G\u00e9n\u00e9raux Cuvelier 11a",
    "sg:city":"Florenville",
    "sg:classifiers":[
        {
            "category":"Banks & Credit Unions",
            "subcategory":"Investment Brokerage",
            "type":"Services"
        }
    ],
    "sg:phone":"+32 61 31 35 52",
    "sg:postcode":"6820",
    "sg:province":"Luxembourg",
    "sg:tags":[
        "printing",
        "-"
    ],
    "wof:name":"Pire",
    "wof:placetype":"venue"
},
  "geometry": {"coordinates":[5.309399128,49.6978912354],"type":"Point"}
}