{
  "type": "Feature",
  "properties": {
    "iso:country":"BE",
    "sg:address":"Rue Ferrer 11",
    "sg:city":"Braine-le-comte",
    "sg:classifiers":[
        {
            "category":"Social Services",
            "type":"Services"
        }
    ],
    "sg:phone":"+32 67 55 05 00",
    "sg:postcode":"7090",
    "sg:province":"Hainaut",
    "wof:name":"Maison De L'emploi Asbl",
    "wof:placetype":"venue"
},
  "geometry": {"coordinates":[4.1366000175,50.6071815491],"type":"Point"}
}