{
  "type": "Feature",
  "properties": {
    "addr:full":"Avenue Bois Du H\u00c9ron 5b2 Rixensart Brabant Wallon 1330",
    "addr:housenumber":"5b2",
    "addr:postcode":"1330",
    "addr:street":"Avenue Bois Du He\u0301Ron;Wallon",
    "iso:country":"BE",
    "sg:address":"Avenue Bois Du H\u00c9ron 5b2",
    "sg:city":"Rixensart",
    "sg:orig_category":"Astrologen, grafologen and mediums",
    "sg:phone":"+32 475 61 53 80",
    "sg:postcode":"1330",
    "sg:province":"Brabant Wallon",
    "wof:name":"Bio City",
    "wof:placetype":"venue"
},
  "geometry": {"coordinates":[4.5244131088,50.7109870911],"type":"Point"}
}