{
  "type": "Feature",
  "properties": {
    "addr:full":"Avenue Des Combattants 21 Jodoigne Brabant Wallon 1370",
    "addr:housenumber":"21",
    "addr:postcode":"1370",
    "addr:street":"Avenue Des Combattants",
    "iso:country":"BE",
    "sg:address":"Avenue Des Combattants 21",
    "sg:city":"Jodoigne",
    "sg:orig_category":"Immobili\u00ebnkantoren",
    "sg:phone":"+32 10 81 43 03",
    "sg:postcode":"1370",
    "sg:province":"Brabant Wallon",
    "wof:name":"Jacques Bonnivers",
    "wof:placetype":"venue"
},
  "geometry": {"coordinates":[4.8698968887,50.7236061096],"type":"Point"}
}