{
  "type": "Feature",
  "properties": {
    "addr:full":"August De Boeckstraat 9g Sint-niklaas Oost-Vlaanderen 9100",
    "addr:housenumber":"9g",
    "addr:postcode":"9100",
    "addr:street":"August De Boeckstraat",
    "iso:country":"BE",
    "sg:address":"August De Boeckstraat 9g",
    "sg:city":"Sint-niklaas",
    "sg:classifiers":[
        {
            "category":"Wholesale",
            "subcategory":"Medical Equipment & Supplies",
            "type":"Manufacturing & Wholesale Goods"
        }
    ],
    "sg:phone":"+32 3 778 87 77",
    "sg:postcode":"9100",
    "sg:province":"Oost-Vlaanderen",
    "sg:tags":[
        "lubricating"
    ],
    "wof:name":"Chp Bvba",
    "wof:placetype":"venue"
},
  "geometry": {"coordinates":[4.1560149193,51.1575469971],"type":"Point"}
}