{
  "type": "Feature",
  "properties": {
    "iso:country":"BE",
    "sg:address":"Rue Blaes 23",
    "sg:city":"Bruxelles",
    "sg:orig_category":"Verlichting and huishoudartikelen",
    "sg:phone":"+32 2 514 07 17",
    "sg:postcode":"1000",
    "sg:province":"Bruxelles-Capitale",
    "wof:name":"Goris",
    "wof:placetype":"venue"
},
  "geometry": {"coordinates":[4.3501610756,50.8406867981],"type":"Point"}
}