{
  "type": "Feature",
  "properties": {
    "addr:full":"Rue D'enghien 87 Braine-le-comte Hainaut 7090",
    "addr:housenumber":"87",
    "addr:postcode":"7090",
    "addr:street":"Rue D'Enghien",
    "iso:country":"BE",
    "sg:address":"Rue D'enghien 87",
    "sg:city":"Braine-le-comte",
    "sg:orig_category":"Eleveurs de bovins",
    "sg:phone":"+32 67 63 62 62",
    "sg:postcode":"7090",
    "sg:province":"Hainaut",
    "wof:name":"Michel Blampain",
    "wof:placetype":"venue"
},
  "geometry": {"coordinates":[4.0905909538,50.6249694824],"type":"Point"}
}