{
  "type": "Feature",
  "properties": {
    "addr:full":"Rue Des Sorbiers 6 Namur Namur 5101",
    "addr:housenumber":"6",
    "addr:postcode":"5101",
    "addr:street":"Rue Des Sorbiers",
    "iso:country":"BE",
    "sg:address":"Rue Des Sorbiers 6",
    "sg:city":"Namur",
    "sg:orig_category":"M\u00e9decines alternatives",
    "sg:phone":"+32 81 30 23 02",
    "sg:postcode":"5101",
    "sg:province":"Namur",
    "wof:name":"J.m. Jaumin",
    "wof:placetype":"venue"
},
  "geometry": {"coordinates":[4.9041581154,50.4550247192],"type":"Point"}
}