{
  "type": "Feature",
  "properties": {
    "iso:country":"BE",
    "sg:address":"Boulevard Adolphe Max 133",
    "sg:city":"Brussel",
    "sg:orig_category":"Seksshops",
    "sg:phone":"+32 2 219 10 97",
    "sg:postcode":"1000",
    "sg:province":"Bruxelles-Capitale",
    "wof:name":"Erotic Discount Centre",
    "wof:placetype":"venue"
},
  "geometry": {"coordinates":[4.3573560715,50.8547821045],"type":"Point"}
}