{
  "type": "Feature",
  "properties": {
    "addr:full":"Rue De Namur 71 Fernelmont (pontillas) Namur 5380",
    "addr:housenumber":"71",
    "addr:postcode":"5380",
    "addr:street":"Rue De Namur",
    "iso:country":"BE",
    "sg:address":"Rue De Namur 71",
    "sg:city":"Fernelmont (pontillas)",
    "sg:classifiers":[
        {
            "category":"Bakery",
            "type":"Food & Drink"
        }
    ],
    "sg:phone":"+32 81 83 31 37",
    "sg:postcode":"5380",
    "sg:province":"Namur",
    "sg:tags":[
        "confectioner",
        "baker"
    ],
    "wof:name":"Pom'canel",
    "wof:placetype":"venue"
},
  "geometry": {"coordinates":[4.9861078262,50.5531463623],"type":"Point"}
}