{
  "type": "Feature",
  "properties": {
    "addr:full":"Delft 9 Lebbeke Oost-Vlaanderen 9280",
    "addr:housenumber":"9",
    "addr:postcode":"9280",
    "addr:street":"Delft",
    "iso:country":"BE",
    "sg:address":"Delft 9",
    "sg:city":"Lebbeke",
    "sg:orig_category":"Koerierbedrijven",
    "sg:phone":"+32 52 41 31 98",
    "sg:postcode":"9280",
    "sg:province":"Oost-Vlaanderen",
    "wof:name":"Van Landuyt D",
    "wof:placetype":"venue"
},
  "geometry": {"coordinates":[4.1281151772,51.0004501343],"type":"Point"}
}