{
  "type": "Feature",
  "properties": {
    "iso:country":"BE",
    "sg:address":"Eiermarkt 23",
    "sg:city":"Antwerpen",
    "sg:classifiers":[
        {
            "category":"Banks & Credit Unions",
            "subcategory":"Investment Brokerage",
            "type":"Services"
        }
    ],
    "sg:phone":"+32 3 227 30 55",
    "sg:postcode":"2000",
    "sg:province":"Antwerpen",
    "sg:tags":[
        "auditor"
    ],
    "wof:name":"Swaelen & Co-bedrijfsrevisoren Bvba",
    "wof:placetype":"venue"
},
  "geometry": {"coordinates":[4.4035577774,51.2193069458],"type":"Point"}
}