{
  "type": "Feature",
  "properties": {
    "iso:country":"BE",
    "sg:address":"Heidestraat 0",
    "sg:city":"Zaventem",
    "sg:classifiers":[
        {
            "category":"Fast Food",
            "type":"Food & Drink"
        }
    ],
    "sg:phone":"+32 2 721 38 90",
    "sg:postcode":"1930",
    "sg:province":"Vlaams-Brabant",
    "sg:tags":[
        "meeneem",
        "restaurant"
    ],
    "wof:name":"\u00b4t Frietpleintje",
    "wof:placetype":"venue"
},
  "geometry": {"coordinates":[4.4745149612,50.8915481567],"type":"Point"}
}