{
  "type": "Feature",
  "properties": {
    "addr:full":"Toekomststraat 72 Deinze Oost-Vlaanderen 9800",
    "addr:housenumber":"72",
    "addr:postcode":"9800",
    "addr:street":"Toekomststraat",
    "iso:country":"BE",
    "sg:address":"Toekomststraat 72",
    "sg:city":"Deinze",
    "sg:orig_category":"Activit\u00e9s r\u00e9cr\u00e9atives diverses",
    "sg:phone":"+32 9 380 15 96",
    "sg:postcode":"9800",
    "sg:province":"Oost-Vlaanderen",
    "wof:name":"B.c. Artevelde",
    "wof:placetype":"venue"
},
  "geometry": {"coordinates":[3.530174017,50.9863166809],"type":"Point"}
}