{
  "type": "Feature",
  "properties": {
    "addr:full":"Kardinaal Mercierlei 31 Berghem Antwerpen 2600",
    "addr:housenumber":"31",
    "addr:postcode":"2600",
    "addr:street":"Kardinaal Mercierlei",
    "iso:country":"BE",
    "sg:address":"Kardinaal Mercierlei 31",
    "sg:city":"Berghem",
    "sg:classifiers":[
        {
            "category":"Manufacturing",
            "subcategory":"Chemicals & Compounds",
            "type":"Manufacturing & Wholesale Goods"
        }
    ],
    "sg:phone":"+32 3 658 76 42",
    "sg:postcode":"2600",
    "sg:province":"Antwerpen",
    "sg:tags":[
        "pharmaceutical",
        "chemistry",
        "-",
        "by-product"
    ],
    "wof:name":"Platteau Bvba",
    "wof:placetype":"venue"
},
  "geometry": {"coordinates":[5.5656099319,51.7742996216],"type":"Point"}
}