{
  "type": "Feature",
  "properties": {
    "iso:country":"BE",
    "sg:address":"Mechelsesteenweg 478",
    "sg:city":"Herent",
    "sg:orig_category":"Opticiens",
    "sg:phone":"+32 16 23 90 02",
    "sg:postcode":"3020",
    "sg:province":"Vlaams-Brabant",
    "wof:name":"De Groeve",
    "wof:placetype":"venue"
},
  "geometry": {"coordinates":[4.668888092,50.9067993164],"type":"Point"}
}