{
  "type": "Feature",
  "properties": {
    "iso:country":"BE",
    "sg:address":"Wijnendalestationsstraat 57",
    "sg:city":"Torhout",
    "sg:classifiers":[
        {
            "category":"Personal",
            "subcategory":"Beauty Salon",
            "type":"Services"
        }
    ],
    "sg:phone":"+32 50 67 69 56",
    "sg:postcode":"8820",
    "sg:province":"West-Vlaanderen",
    "wof:name":"Esthetiek Evelyne Schoonheidsinstituut",
    "wof:placetype":"venue"
},
  "geometry": {"coordinates":[3.0725979805,51.0847015381],"type":"Point"}
}