{
  "type": "Feature",
  "properties": {
    "iso:country":"BE",
    "sg:address":"Naamsesteenweg 43-45",
    "sg:city":"Leuven",
    "sg:orig_category":"Herstelling horloges and juwelen Juwelen and horloges",
    "sg:phone":"+32 16 22 87 79",
    "sg:postcode":"3001",
    "sg:province":"Vlaams-Brabant",
    "wof:name":"Huis Ringel\u00c9",
    "wof:placetype":"venue"
},
  "geometry": {"coordinates":[4.6974492073,50.8670387268],"type":"Point"}
}