{
  "type": "Feature",
  "properties": {
    "iso:country":"BE",
    "sg:address":"Rue Du Centre 50",
    "sg:city":"Verviers",
    "sg:orig_category":"Belastingconsulenten Diverse juridische dienstverlening",
    "sg:phone":"+32 87 22 33 13",
    "sg:postcode":"4800",
    "sg:province":"Li\u00e8ge",
    "wof:name":"Gecofi",
    "wof:placetype":"venue"
},
  "geometry": {"coordinates":[5.8615469933,50.5892677307],"type":"Point"}
}