{
  "type": "Feature",
  "properties": {
    "addr:full":"Veldekensstraat 25 Destelbergen Oost-Vlaanderen 9070",
    "addr:housenumber":"25",
    "addr:postcode":"9070",
    "addr:street":"Veldekensstraat",
    "iso:country":"BE",
    "sg:address":"Veldekensstraat 25",
    "sg:city":"Destelbergen",
    "sg:orig_category":"Dakwerken IJzerwaren, bouw- and verfmaterialen Loodgieterij, verwarming and sanitaire installaties",
    "sg:phone":"+32 9 355 68 90",
    "sg:postcode":"9070",
    "sg:province":"Oost-Vlaanderen",
    "wof:name":"Patrick De Vos",
    "wof:placetype":"venue"
},
  "geometry": {"coordinates":[3.810516119,51.0735931396],"type":"Point"}
}