{
  "type": "Feature",
  "properties": {
    "addr:full":"Engelse Wandeling 2k Kortrijk West-Vlaanderen 8500",
    "addr:housenumber":"2k",
    "addr:postcode":"8500",
    "addr:street":"Engelse Wandeling",
    "iso:country":"BE",
    "sg:address":"Engelse Wandeling 2k",
    "sg:city":"Kortrijk",
    "sg:classifiers":[
        {
            "category":"Communications",
            "subcategory":"Film & Video Production",
            "type":"Services"
        }
    ],
    "sg:phone":"+32 56 45 66 01",
    "sg:postcode":"8500",
    "sg:province":"West-Vlaanderen",
    "sg:tags":[
        "multimedia",
        "-",
        "system"
    ],
    "wof:name":"Telraam Nv",
    "wof:placetype":"venue"
},
  "geometry": {"coordinates":[3.2476019859,50.8158874512],"type":"Point"}
}