{
  "type": "Feature",
  "properties": {
    "iso:country":"BE",
    "sg:address":"Doortstraat 3",
    "sg:city":"Opwijk",
    "sg:orig_category":"Peinture. Rev\u00eatements pour sols and murs",
    "sg:phone":"+32 52 35 69 60",
    "sg:postcode":"1745",
    "sg:province":"Vlaams-Brabant",
    "wof:name":"Claudio Salgado",
    "wof:placetype":"venue"
},
  "geometry": {"coordinates":[4.1930332184,50.9730377197],"type":"Point"}
}