{
  "type": "Feature",
  "properties": {
    "addr:full":"Vorstlaan 121 Oudergem/auderghem Bruxelles-Capitale 1160",
    "addr:housenumber":"121",
    "addr:postcode":"1160",
    "addr:street":"Vorstlaan;/",
    "iso:country":"BE",
    "sg:address":"Vorstlaan 121",
    "sg:city":"Oudergem/auderghem",
    "sg:orig_category":"Technische studies and ingenieursactiviteiten",
    "sg:phone":"+32 2 672 00 93",
    "sg:postcode":"1160",
    "sg:province":"Bruxelles-Capitale",
    "wof:name":"Alain Franck",
    "wof:placetype":"venue"
},
  "geometry": {"coordinates":[4.4265789986,50.8144187927],"type":"Point"}
}