{
  "type": "Feature",
  "properties": {
    "iso:country":"BE",
    "sg:address":"Markt 15",
    "sg:city":"Herenthout",
    "sg:classifiers":[
        {
            "category":"Restaurant",
            "type":"Food & Drink"
        }
    ],
    "sg:phone":"+32 14 50 13 69",
    "sg:postcode":"2270",
    "sg:province":"Antwerpen",
    "wof:name":"Taverne 't Kamereyck",
    "wof:placetype":"venue"
},
  "geometry": {"coordinates":[4.7563581467,51.1392440796],"type":"Point"}
}