{
  "type": "Feature",
  "properties": {
    "iso:country":"BE",
    "sg:address":"Frans Van Ryhovelaan 178",
    "sg:city":"Gent",
    "sg:orig_category":"Artiesten and kunstenaars",
    "sg:phone":"+32 9 226 15 72",
    "sg:postcode":"9000",
    "sg:province":"Oost-Vlaanderen",
    "wof:name":"Van Der Vinck",
    "wof:placetype":"venue"
},
  "geometry": {"coordinates":[3.7086200714,51.0703811646],"type":"Point"}
}