{
  "type": "Feature",
  "properties": {
    "addr:full":"Rue Aug. Dupont 15 Verviers Li\u00e8ge 4800",
    "addr:housenumber":"15",
    "addr:postcode":"4800",
    "addr:street":"Rue Aug. Dupont",
    "iso:country":"BE",
    "sg:address":"Rue Aug. Dupont 15",
    "sg:city":"Verviers",
    "sg:orig_category":"Herstellingen and onderhoud aan huis voor voertuigen Herstellingen and onderhoud van auto's Metaalaf",
    "sg:phone":"+32 87 33 58 60",
    "sg:postcode":"4800",
    "sg:province":"Li\u00e8ge",
    "wof:name":"Fe. Guilmot",
    "wof:placetype":"venue"
},
  "geometry": {"coordinates":[5.8594508171,50.5917663574],"type":"Point"}
}