{
  "type": "Feature",
  "properties": {
    "iso:country":"BE",
    "sg:address":"Kerkstraat 2",
    "sg:city":"Hamme",
    "sg:classifiers":[
        {
            "category":"Food & Beverages",
            "subcategory":"Cheese",
            "type":"Retail Goods"
        }
    ],
    "sg:phone":"+32 52 47 06 74",
    "sg:postcode":"9220",
    "sg:province":"Oost-Vlaanderen",
    "sg:tags":[
        "-"
    ],
    "wof:name":"Delicatessen Seghers Bvba",
    "wof:placetype":"venue"
},
  "geometry": {"coordinates":[4.1369919777,51.0981521606],"type":"Point"}
}