{
  "type": "Feature",
  "properties": {
    "addr:full":"Dokter Vanderhoeydonckstraat 18 Lummen Limburg 3560",
    "addr:housenumber":"18",
    "addr:postcode":"3560",
    "addr:street":"Dokter Vanderhoeydonckstraat",
    "iso:country":"BE",
    "sg:address":"Dokter Vanderhoeydonckstraat 18",
    "sg:city":"Lummen",
    "sg:classifiers":[
        {
            "category":"Personal",
            "subcategory":"Beauty Salon",
            "type":"Services"
        }
    ],
    "sg:phone":"+32 13 52 25 98",
    "sg:postcode":"3560",
    "sg:province":"Limburg",
    "sg:tags":[
        "lady",
        "-",
        "hairdressing"
    ],
    "wof:name":"Renilde",
    "wof:placetype":"venue"
},
  "geometry": {"coordinates":[5.1946492195,50.9893112183],"type":"Point"}
}