{
  "type": "Feature",
  "properties": {
    "iso:country":"BE",
    "sg:address":"Herentalsesteenweg 52",
    "sg:city":"Herselt",
    "sg:orig_category":"Avocats and conseillers juridiques",
    "sg:phone":"+32 14 53 83 83",
    "sg:postcode":"2230",
    "sg:province":"Antwerpen",
    "wof:name":"M. Van Baelen",
    "wof:placetype":"venue"
},
  "geometry": {"coordinates":[4.8791699409,51.0697212219],"type":"Point"}
}