{
  "type": "Feature",
  "properties": {
    "iso:country":"BE",
    "sg:address":"Hoogstraat 27",
    "sg:city":"Roosdaal",
    "sg:orig_category":"Afvalwaterverwerking and ontstoppingsdiensten Dakwerken Loodgieterij, verwarming and sanitaire insta",
    "sg:phone":"+32 477 73 74 77",
    "sg:postcode":"1760",
    "sg:province":"Vlaams-Brabant",
    "wof:name":"Michaux Ren\u00c9",
    "wof:placetype":"venue"
},
  "geometry": {"coordinates":[4.0744271278,50.8435707092],"type":"Point"}
}