{
  "type": "Feature",
  "properties": {
    "iso:country":"BE",
    "sg:address":"Dorpsstraat 33",
    "sg:city":"Hasselt",
    "sg:classifiers":[
        {
            "category":"Personal",
            "subcategory":"Tattoo Parlor",
            "type":"Services"
        }
    ],
    "sg:phone":"+32 11 26 15 26",
    "sg:postcode":"3500",
    "sg:province":"Limburg",
    "sg:tags":[
        "tattooists"
    ],
    "wof:name":"Tatoo Pink",
    "wof:placetype":"venue"
},
  "geometry": {"coordinates":[5.3348941803,50.9323425293],"type":"Point"}
}