{
  "type": "Feature",
  "properties": {
    "iso:country":"BE",
    "sg:address":"Baljuwstraat 93",
    "sg:city":"Elsene/ixelles",
    "sg:orig_category":"Dameskledingzaken Kleding",
    "sg:phone":"+32 2 537 42 69",
    "sg:postcode":"1050",
    "sg:province":"Bruxelles-Capitale",
    "wof:name":"Bonzai",
    "wof:placetype":"venue"
},
  "geometry": {"coordinates":[4.3590421677,50.8255195618],"type":"Point"}
}