{
  "type": "Feature",
  "properties": {
    "addr:full":"Rue Belle Vue 29 Etalle Luxembourg 6740",
    "addr:housenumber":"29",
    "addr:postcode":"6740",
    "addr:street":"Rue Belle Vue",
    "iso:country":"BE",
    "sg:address":"Rue Belle Vue 29",
    "sg:city":"Etalle",
    "sg:classifiers":[
        {
            "category":"Professional",
            "subcategory":"Lawyer & Legal Services",
            "type":"Services"
        }
    ],
    "sg:phone":"+32 63 45 51 14",
    "sg:postcode":"6740",
    "sg:province":"Luxembourg",
    "sg:tags":[
        "notary"
    ],
    "wof:name":"Bechet M",
    "wof:placetype":"venue"
},
  "geometry": {"coordinates":[5.6027379036,49.678817749],"type":"Point"}
}