{
  "type": "Feature",
  "properties": {
    "iso:country":"BE",
    "sg:address":"Grootveldstraat 2",
    "sg:city":"Pittem (egem)",
    "sg:classifiers":[
        {
            "category":"Building & Trades",
            "subcategory":"Landscaping Services",
            "type":"Services"
        }
    ],
    "sg:phone":"+32 51 61 12 78",
    "sg:postcode":"8740",
    "sg:province":"West-Vlaanderen",
    "sg:tags":[
        "architect",
        "landscape"
    ],
    "wof:name":"Vereecke L",
    "wof:placetype":"venue"
},
  "geometry": {"coordinates":[3.2454319,51.026638031],"type":"Point"}
}