{
  "type": "Feature",
  "properties": {
    "addr:full":"Bergestraat 15 Asse Vlaams-Brabant 1730",
    "addr:housenumber":"15",
    "addr:postcode":"1730",
    "addr:street":"Bergestraat",
    "iso:country":"BE",
    "sg:address":"Bergestraat 15",
    "sg:city":"Asse",
    "sg:orig_category":"Meubelzaken, woning- and keukeninrichting",
    "sg:phone":"+32 2 452 45 54",
    "sg:postcode":"1730",
    "sg:province":"Vlaams-Brabant",
    "wof:name":"Roeland Keymolen",
    "wof:placetype":"venue"
},
  "geometry": {"coordinates":[4.2072839737,50.9056854248],"type":"Point"}
}