{
  "type": "Feature",
  "properties": {
    "addr:full":"Grand-rue 37 Aubange Luxembourg 6791",
    "addr:housenumber":"37",
    "addr:postcode":"6791",
    "addr:street":"Grand-Rue",
    "iso:country":"BE",
    "sg:address":"Grand-rue 37",
    "sg:city":"Aubange",
    "sg:classifiers":[
        {
            "category":"Cafe",
            "type":"Food & Drink"
        }
    ],
    "sg:phone":"+32 63 37 15 80",
    "sg:postcode":"6791",
    "sg:province":"Luxembourg",
    "sg:tags":[
        "caf\u00e9s"
    ],
    "wof:name":"Caf\u00c9 La Potion Magique",
    "wof:placetype":"venue"
},
  "geometry": {"coordinates":[5.8368301392,49.5627288818],"type":"Point"}
}