{
  "type": "Feature",
  "properties": {
    "addr:full":"Antwerpsesteenweg 269 Malle (westmalle) Antwerpen 2390",
    "addr:housenumber":"269",
    "addr:postcode":"2390",
    "addr:street":"Antwerpsesteenweg",
    "iso:country":"BE",
    "sg:address":"Antwerpsesteenweg 269",
    "sg:city":"Malle (westmalle)",
    "sg:classifiers":[
        {
            "category":"Banks & Credit Unions",
            "subcategory":"Investment Brokerage",
            "type":"Services"
        }
    ],
    "sg:phone":"+32 3 312 29 86",
    "sg:postcode":"2390",
    "sg:province":"Antwerpen",
    "sg:tags":[
        "jean",
        "casual",
        "wear"
    ],
    "wof:name":"Move In Jeanswear",
    "wof:placetype":"venue"
},
  "geometry": {"coordinates":[4.6920180321,51.2968063354],"type":"Point"}
}