{
  "type": "Feature",
  "properties": {
    "iso:country":"BE",
    "sg:address":"Burgemeester Achiel Heymanstraat 59",
    "sg:city":"Temse (tielrode)",
    "sg:classifiers":[
        {
            "category":"Building & Trades",
            "subcategory":"Construction",
            "type":"Services"
        }
    ],
    "sg:phone":"+32 3 771 29 71",
    "sg:postcode":"9140",
    "sg:province":"Oost-Vlaanderen",
    "sg:tags":[
        "glazier"
    ],
    "wof:name":"De Smet R",
    "wof:placetype":"venue"
},
  "geometry": {"coordinates":[4.1793351173,51.1141662598],"type":"Point"}
}