{
  "type": "Feature",
  "properties": {
    "addr:full":"Koninginnelaan 23 Oostende West-Vlaanderen 8400",
    "addr:housenumber":"23",
    "addr:postcode":"8400",
    "addr:street":"Koninginnelaan",
    "iso:country":"BE",
    "sg:address":"Koninginnelaan 23",
    "sg:city":"Oostende",
    "sg:classifiers":[
        {
            "category":"Health Services",
            "subcategory":"Doctor",
            "type":"Services"
        }
    ],
    "sg:phone":"+32 59 80 33 77",
    "sg:postcode":"8400",
    "sg:province":"West-Vlaanderen",
    "sg:tags":[
        "medicinephysicians",
        "surgeon"
    ],
    "wof:name":"Gyselen M",
    "wof:placetype":"venue"
},
  "geometry": {"coordinates":[2.9064519405,51.2254981995],"type":"Point"}
}