{
  "type": "Feature",
  "properties": {
    "iso:country":"BE",
    "sg:address":"Avenue Du Chalon 39",
    "sg:city":"Chimay",
    "sg:orig_category":"Artsen and specialisten",
    "sg:phone":"+32 60 21 40 03",
    "sg:postcode":"6460",
    "sg:province":"Hainaut",
    "wof:name":"J.j. Hanot Mambres",
    "wof:placetype":"venue"
},
  "geometry": {"coordinates":[4.3236370087,50.0477180481],"type":"Point"}
}