{
  "type": "Feature",
  "properties": {
    "addr:full":"Boondaalse Steenweg 589 Elsene/ixelles Bruxelles-Capitale 1050",
    "addr:housenumber":"589",
    "addr:postcode":"1050",
    "addr:street":"Boondaalse Steenweg",
    "iso:country":"BE",
    "sg:address":"Boondaalse Steenweg 589",
    "sg:city":"Elsene/ixelles",
    "sg:orig_category":"Brood, gebak and snoepgoed",
    "sg:phone":"+32 2 649 42 50",
    "sg:postcode":"1050",
    "sg:province":"Bruxelles-Capitale",
    "wof:name":"Luc Streber",
    "wof:placetype":"venue"
},
  "geometry": {"coordinates":[4.3913369179,50.8117713928],"type":"Point"}
}