{
  "type": "Feature",
  "properties": {
    "addr:full":"Chauss\u00e9e De Vleurgat 184 Bruxelles Bruxelles-Capitale 1000",
    "addr:housenumber":"184",
    "addr:postcode":"1000",
    "addr:street":"Chausse\u0301E De Vleurgat",
    "iso:country":"BE",
    "sg:address":"Chauss\u00e9e De Vleurgat 184",
    "sg:city":"Bruxelles",
    "sg:classifiers":[
        {
            "category":"Travel",
            "subcategory":"Hotels & Motels",
            "type":"Entertainment"
        }
    ],
    "sg:phone":"+32 2 646 82 00",
    "sg:postcode":"1000",
    "sg:province":"Bruxelles-Capitale",
    "sg:tags":[
        "international",
        "hotels",
        "reservation"
    ],
    "wof:name":"Booking Services International Sa",
    "wof:placetype":"venue"
},
  "geometry": {"coordinates":[4.3668231964,50.8219642639],"type":"Point"}
}