{
  "type": "Feature",
  "properties": {
    "iso:country":"BE",
    "sg:address":"Tinstr 42",
    "sg:city":"Putte",
    "sg:classifiers":[
        {
            "category":"Sports & Exercise",
            "subcategory":"Sports Center",
            "type":"Entertainment"
        }
    ],
    "sg:phone":"+32 15 76 76 00",
    "sg:postcode":"2580",
    "sg:province":"Antwerpen",
    "sg:tags":[
        "game"
    ],
    "wof:name":"Imtenor-greenhill Nv",
    "wof:placetype":"venue"
},
  "geometry": {"coordinates":[4.6286678314,51.0405464172],"type":"Point"}
}