{
  "type": "Feature",
  "properties": {
    "iso:country":"BE",
    "sg:address":"Chemin Du Pr\u00e9 Leftay 34",
    "sg:city":"Spa",
    "sg:orig_category":"Ice-cream parlours",
    "sg:phone":"+32 87 77 56 80",
    "sg:postcode":"4900",
    "sg:province":"Li\u00e8ge",
    "wof:name":"Marc Glacier",
    "wof:placetype":"venue"
},
  "geometry": {"coordinates":[5.883038044,50.4978218079],"type":"Point"}
}