{
  "type": "Feature",
  "properties": {
    "iso:country":"BE",
    "sg:address":"Dr. Vanweddingenlaan 10b1",
    "sg:city":"Herk-de-stad",
    "sg:orig_category":"Enseignement maternel and primaire",
    "sg:phone":"+32 13 55 21 06",
    "sg:postcode":"3540",
    "sg:province":"Limburg",
    "wof:name":"B.s.g.o. Hercker Hof",
    "wof:placetype":"venue"
},
  "geometry": {"coordinates":[5.163672924,50.9395332336],"type":"Point"}
}