{
  "type": "Feature",
  "properties": {
    "addr:full":"Rivage De Boubier 15 Chatelet Hainaut 6200",
    "addr:housenumber":"15",
    "addr:postcode":"6200",
    "addr:street":"Rivage;Boubier;Hainaut",
    "iso:country":"BE",
    "sg:address":"Rivage De Boubier 15",
    "sg:city":"Chatelet",
    "sg:orig_category":"Ramassage and traitement des d\u00e9chets m\u00e9nagers",
    "sg:phone":"+32 71 40 25 94",
    "sg:postcode":"6200",
    "sg:province":"Hainaut",
    "wof:name":"Garwig Et Cie",
    "wof:placetype":"venue"
},
  "geometry": {"coordinates":[4.512720108,50.4036216736],"type":"Point"}
}