{
  "type": "Feature",
  "properties": {
    "addr:full":"Koningin Astridlaan 88 Menen West-Vlaanderen 8930",
    "addr:housenumber":"88",
    "addr:postcode":"8930",
    "addr:street":"Koningin Astridlaan",
    "iso:country":"BE",
    "sg:address":"Koningin Astridlaan 88",
    "sg:city":"Menen",
    "sg:orig_category":"Agences immobili\u00e8res. Promoteurs immobiliers",
    "sg:phone":"+32 56 40 19 35",
    "sg:postcode":"8930",
    "sg:province":"West-Vlaanderen",
    "wof:name":"C B M",
    "wof:placetype":"venue"
},
  "geometry": {"coordinates":[3.1209149361,50.7961845398],"type":"Point"}
}