{
  "type": "Feature",
  "properties": {
    "iso:country":"BE",
    "sg:address":"Rue Des Saules 14",
    "sg:city":"Flemalle",
    "sg:classifiers":[
        {
            "category":"Cafe",
            "type":"Food & Drink"
        }
    ],
    "sg:phone":"+32 4 275 18 56",
    "sg:postcode":"4400",
    "sg:province":"Li\u00e8ge",
    "sg:tags":[
        "caf\u00e9s"
    ],
    "wof:name":"Canin De La Rochette",
    "wof:placetype":"venue"
},
  "geometry": {"coordinates":[5.4576430321,50.5693130493],"type":"Point"}
}