{
  "type": "Feature",
  "properties": {
    "addr:full":"Patijntjestraat 58 Gent Oost-Vlaanderen 9000",
    "addr:housenumber":"58",
    "addr:postcode":"9000",
    "addr:street":"Patijntjestraat;Oost-Vlaanderen",
    "iso:country":"BE",
    "sg:address":"Patijntjestraat 58",
    "sg:city":"Gent",
    "sg:classifiers":[
        {
            "category":"Professional",
            "subcategory":"Art Services",
            "type":"Services"
        }
    ],
    "sg:phone":"+32 2 751 81 91",
    "sg:postcode":"9000",
    "sg:province":"Oost-Vlaanderen",
    "sg:tags":[
        "good",
        "-",
        "transport"
    ],
    "wof:name":"Maertens International Nv",
    "wof:placetype":"venue"
},
  "geometry": {"coordinates":[4.4327301979,50.9123344421],"type":"Point"}
}