{
  "type": "Feature",
  "properties": {
    "addr:full":"Matrouwstraat 16 Brakel Oost-Vlaanderen 9661",
    "addr:housenumber":"16",
    "addr:postcode":"9661",
    "addr:street":"Matrouwstraat",
    "iso:country":"BE",
    "sg:address":"Matrouwstraat 16",
    "sg:city":"Brakel",
    "sg:orig_category":"Artsen and specialisten",
    "sg:phone":"+32 55 42 17 75",
    "sg:postcode":"9661",
    "sg:province":"Oost-Vlaanderen",
    "wof:name":"J. Schaill\u00c9e",
    "wof:placetype":"venue"
},
  "geometry": {"coordinates":[3.7968080044,50.7892341614],"type":"Point"}
}