{
  "type": "Feature",
  "properties": {
    "addr:full":"Raamstraat 28 Begijnendijk Vlaams-Brabant 3130",
    "addr:housenumber":"28",
    "addr:postcode":"3130",
    "addr:street":"Raamstraat",
    "iso:country":"BE",
    "sg:address":"Raamstraat 28",
    "sg:city":"Begijnendijk",
    "sg:orig_category":"Catering and organisation de f\u00eates",
    "sg:phone":"+32 16 53 47 37",
    "sg:postcode":"3130",
    "sg:province":"Vlaams-Brabant",
    "wof:name":"Trait. Indemans-berghmans",
    "wof:placetype":"venue"
},
  "geometry": {"coordinates":[4.7901988029,51.0172576904],"type":"Point"}
}