{
  "type": "Feature",
  "properties": {
    "iso:country":"BE",
    "sg:address":"Churchilllaan 89",
    "sg:city":"Waregem",
    "sg:classifiers":[
        {
            "category":"Health Services",
            "subcategory":"Health Practitioner",
            "type":"Services"
        }
    ],
    "sg:phone":"+32 56 60 76 16",
    "sg:postcode":"8790",
    "sg:province":"West-Vlaanderen",
    "sg:tags":[
        "physiotherapist"
    ],
    "wof:name":"Arickx Isabelle",
    "wof:placetype":"venue"
},
  "geometry": {"coordinates":[3.4422230721,50.8902626038],"type":"Point"}
}