{
  "type": "Feature",
  "properties": {
    "addr:full":"Chauss\u00e9e De Mons 110 Chimay Hainaut 6460",
    "addr:housenumber":"110",
    "addr:postcode":"6460",
    "addr:street":"Chausse\u0301E De Mons",
    "iso:country":"BE",
    "sg:address":"Chauss\u00e9e De Mons 110",
    "sg:city":"Chimay",
    "sg:classifiers":[
        {
            "category":"Farming",
            "subcategory":"Farm & Veterinary Services",
            "type":"Manufacturing & Wholesale Goods"
        }
    ],
    "sg:phone":"+32 60 21 25 80",
    "sg:postcode":"6460",
    "sg:province":"Hainaut",
    "sg:tags":[
        "agricultural",
        "contractor"
    ],
    "wof:name":"Gotiaux Sc",
    "wof:placetype":"venue"
},
  "geometry": {"coordinates":[4.2944908142,50.068775177],"type":"Point"}
}