{
  "type": "Feature",
  "properties": {
    "addr:full":"Postlaan 4 Landen Vlaams-Brabant 3400",
    "addr:housenumber":"4",
    "addr:postcode":"3400",
    "addr:street":"Postlaan",
    "iso:country":"BE",
    "sg:address":"Postlaan 4",
    "sg:city":"Landen",
    "sg:classifiers":[
        {
            "category":"Autos & Motor Vehicles",
            "subcategory":"Fuel & Gas Station",
            "type":"Retail Goods"
        }
    ],
    "sg:phone":"+32 11 83 14 01",
    "sg:postcode":"3400",
    "sg:province":"Vlaams-Brabant",
    "sg:tags":[
        "stations-service",
        "carburants"
    ],
    "wof:name":"Esso",
    "wof:placetype":"venue"
},
  "geometry": {"coordinates":[5.0822081566,50.748046875],"type":"Point"}
}