{
  "type": "Feature",
  "properties": {
    "iso:country":"BE",
    "sg:address":"Rue Xhov\u00e9mont 275",
    "sg:city":"Li\u00e8ge 1",
    "sg:classifiers":[
        {
            "category":"Personal",
            "subcategory":"Beauty Salon",
            "type":"Services"
        }
    ],
    "sg:phone":"+32 4 224 19 16",
    "sg:postcode":"4000",
    "sg:province":"Li\u00e8ge",
    "wof:name":"Johanna Esthetique",
    "wof:placetype":"venue"
},
  "geometry": {"coordinates":[5.5616869926,50.6565628052],"type":"Point"}
}