{
  "type": "Feature",
  "properties": {
    "addr:full":"Beling 4 Beersel (dworp) Vlaams-Brabant 1653",
    "addr:housenumber":"4",
    "addr:postcode":"1653",
    "addr:street":"Beling",
    "iso:country":"BE",
    "sg:address":"Beling 4",
    "sg:city":"Beersel (dworp)",
    "sg:classifiers":[
        {
            "category":"Shopping",
            "subcategory":"Bicycles & Sporting Goods",
            "type":"Retail Goods"
        }
    ],
    "sg:phone":"+32 2 380 45 20",
    "sg:postcode":"1653",
    "sg:province":"Vlaams-Brabant",
    "sg:tags":[
        "-"
    ],
    "wof:name":"Vandenbrande Sport",
    "wof:placetype":"venue"
},
  "geometry": {"coordinates":[4.2991251945,50.7301254272],"type":"Point"}
}