{
  "type": "Feature",
  "properties": {
    "addr:full":"L De Boningestraat 20 Edegem Antwerpen 2650",
    "addr:housenumber":"20",
    "addr:postcode":"2650",
    "addr:street":"L De Boningestraat",
    "iso:country":"BE",
    "sg:address":"L De Boningestraat 20",
    "sg:city":"Edegem",
    "sg:orig_category":"Eleveurs d'\u00e9quid\u00e9s",
    "sg:phone":"+32 3 457 79 55",
    "sg:postcode":"2650",
    "sg:province":"Antwerpen",
    "wof:name":"Vinkenveld",
    "wof:placetype":"venue"
},
  "geometry": {"coordinates":[4.4257798195,51.1525115967],"type":"Point"}
}