{
  "type": "Feature",
  "properties": {
    "addr:full":"Rue De Hamme-mille 165 Grez-doiceau Brabant Wallon 1390",
    "addr:housenumber":"165",
    "addr:postcode":"1390",
    "addr:street":"Rue De Hamme-Mille",
    "iso:country":"BE",
    "sg:address":"Rue De Hamme-mille 165",
    "sg:city":"Grez-doiceau",
    "sg:classifiers":[
        {
            "category":"Cafe",
            "type":"Food & Drink"
        }
    ],
    "sg:phone":"+32 10 86 64 18",
    "sg:postcode":"1390",
    "sg:province":"Brabant Wallon",
    "sg:tags":[
        "caf\u00e9s"
    ],
    "wof:name":"Jeanne Peeters",
    "wof:placetype":"venue"
},
  "geometry": {"coordinates":[4.6893410683,50.782245636],"type":"Point"}
}