{
  "type": "Feature",
  "properties": {
    "iso:country":"BE",
    "sg:address":"Rue Victor Nonet 1",
    "sg:city":"Namur",
    "sg:orig_category":"Textiel",
    "sg:phone":"+32 81 30 32 24",
    "sg:postcode":"5100",
    "sg:province":"Namur",
    "wof:name":"Textild\u00c9cor",
    "wof:placetype":"venue"
},
  "geometry": {"coordinates":[4.8713750839,50.4566345215],"type":"Point"}
}