{
  "type": "Feature",
  "properties": {
    "iso:country":"BE",
    "sg:address":"Rue Albert Ier 32",
    "sg:city":"Beloeil",
    "sg:orig_category":"Huishoudapparaten, televisies and radio's",
    "sg:phone":"+32 69 57 54 69",
    "sg:postcode":"7973",
    "sg:province":"Hainaut",
    "wof:name":"Robert Bonte",
    "wof:placetype":"venue"
},
  "geometry": {"coordinates":[3.7188699245,50.5087738037],"type":"Point"}
}