{
  "type": "Feature",
  "properties": {
    "addr:full":"Itterbeeksebaan 260 Dilbeek Vlaams-Brabant 1700",
    "addr:housenumber":"260",
    "addr:postcode":"1700",
    "iso:country":"BE",
    "sg:address":"Itterbeeksebaan 260",
    "sg:city":"Dilbeek",
    "sg:orig_category":"Pain, p\u00e2tisseries and confiseries",
    "sg:phone":"+32 2 569 00 98",
    "sg:postcode":"1700",
    "sg:province":"Vlaams-Brabant",
    "wof:name":"Bakkerij Plas R. & J.",
    "wof:placetype":"venue"
},
  "geometry": {"coordinates":[4.2608299255,50.8358917236],"type":"Point"}
}