{
  "type": "Feature",
  "properties": {
    "iso:country":"BE",
    "sg:address":"Veeboslaan 7",
    "sg:city":"Zaventem",
    "sg:orig_category":"Architecten",
    "sg:phone":"+32 2 720 09 28",
    "sg:postcode":"1933",
    "sg:province":"Vlaams-Brabant",
    "wof:name":"Jadoul Marcel",
    "wof:placetype":"venue"
},
  "geometry": {"coordinates":[4.4733247757,50.865398407],"type":"Point"}
}