{
  "type": "Feature",
  "properties": {
    "iso:country":"BE",
    "sg:address":"Rue De Nimy 82",
    "sg:city":"Mons",
    "sg:orig_category":"Epiceries",
    "sg:phone":"+32 65 31 38 03",
    "sg:postcode":"7000",
    "sg:province":"Hainaut",
    "wof:name":"Gilbert Leroy",
    "wof:placetype":"venue"
},
  "geometry": {"coordinates":[3.9555659294,50.4577980042],"type":"Point"}
}