{
  "type": "Feature",
  "properties": {
    "addr:full":"Rue De L'ornia 1 Hamois Namur 5361",
    "addr:housenumber":"1",
    "addr:postcode":"5361",
    "addr:street":"Rue De L'Ornia",
    "iso:country":"BE",
    "sg:address":"Rue De L'ornia 1",
    "sg:city":"Hamois",
    "sg:orig_category":"Installatie van houten of kunststof schrijnwerk",
    "sg:phone":"+32 83 61 16 23",
    "sg:postcode":"5361",
    "sg:province":"Namur",
    "wof:name":"Albert Meunier",
    "wof:placetype":"venue"
},
  "geometry": {"coordinates":[5.182071209,50.32006073],"type":"Point"}
}