{
  "type": "Feature",
  "properties": {
    "addr:full":"Chauss\u00c9e D'alsemberg 210 Ukkel/uccle Bruxelles-Capitale 1180",
    "addr:housenumber":"210",
    "addr:postcode":"1180",
    "addr:street":"Chausse\u0301E D'Alsemberg;/",
    "iso:country":"BE",
    "sg:address":"Chauss\u00c9e D'alsemberg 210",
    "sg:city":"Ukkel/uccle",
    "sg:orig_category":"Kapsalons",
    "sg:phone":"+32 2 345 23 46",
    "sg:postcode":"1180",
    "sg:province":"Bruxelles-Capitale",
    "wof:name":"Rg",
    "wof:placetype":"venue"
},
  "geometry": {"coordinates":[4.3354640007,50.7960548401],"type":"Point"}
}