{
  "type": "Feature",
  "properties": {
    "iso:country":"BE",
    "sg:address":"Clos Des Elfes 4",
    "sg:city":"Waterloo",
    "sg:orig_category":"R\u00e9alisation de programmes and logiciels",
    "sg:phone":"+32 2 354 51 39",
    "sg:postcode":"1410",
    "sg:province":"Brabant Wallon",
    "wof:name":"Barbara Rumynskij",
    "wof:placetype":"venue"
},
  "geometry": {"coordinates":[4.4241437912,50.7052993774],"type":"Point"}
}