{
  "type": "Feature",
  "properties": {
    "addr:full":"Rue Royale 2 Chapelle-lez-herlaimont Hainaut 7160",
    "addr:housenumber":"2",
    "addr:postcode":"7160",
    "addr:street":"Rue Royale;Hainaut",
    "iso:country":"BE",
    "sg:address":"Rue Royale 2",
    "sg:city":"Chapelle-lez-herlaimont",
    "sg:classifiers":[
        {
            "category":"Arena",
            "subcategory":"Sports Club",
            "type":"Entertainment"
        }
    ],
    "sg:phone":"+32 64 33 49 17",
    "sg:postcode":"7160",
    "sg:province":"Hainaut",
    "sg:tags":[
        "de"
    ],
    "wof:name":"Moto Club Ressaix",
    "wof:placetype":"venue"
},
  "geometry": {"coordinates":[4.2712011337,50.4800071716],"type":"Point"}
}