{
  "type": "Feature",
  "properties": {
    "addr:full":"Crendal (14) Bureau 10-4 Luxembourg 9743",
    "addr:housenumber":"14",
    "addr:postcode":"9743",
    "addr:street":"Crendal;Bureau 10-4",
    "iso:country":"BE",
    "sg:address":"Crendal (14) Bureau 10-4",
    "sg:city":"Luxembourg",
    "sg:classifiers":[
        {
            "category":"Wholesale",
            "subcategory":"Construction Materials",
            "type":"Manufacturing & Wholesale Goods"
        }
    ],
    "sg:postcode":"9743",
    "sg:tags":[
        "elevator"
    ],
    "wof:name":"Piklift",
    "wof:placetype":"venue"
},
  "geometry": {"coordinates":[5.8951401711,50.0566482544],"type":"Point"}
}