{
  "type": "Feature",
  "properties": {
    "iso:country":"BE",
    "sg:address":"Rue Saint -nicolas 536a",
    "sg:city":"Li\u00c8ge",
    "sg:classifiers":[
        {
            "category":"Fast Food",
            "type":"Food & Drink"
        }
    ],
    "sg:phone":"+32 4 226 05 10",
    "sg:postcode":"4000",
    "sg:province":"Li\u00e8ge",
    "sg:tags":[
        "\u00c0",
        "emporter",
        "restaurants"
    ],
    "wof:name":"Pitta Esp\u00c9rance",
    "wof:placetype":"venue"
},
  "geometry": {"coordinates":[5.5355200768,50.6403884888],"type":"Point"}
}