{
  "type": "Feature",
  "properties": {
    "iso:country":"BE",
    "sg:address":"Dr\u00e8ve Du Proph\u00e8te 16",
    "sg:city":"Mons",
    "sg:classifiers":[
        {
            "category":"Building & Trades",
            "subcategory":"Landscaping Services",
            "type":"Services"
        }
    ],
    "sg:phone":"+32 65 35 21 19",
    "sg:postcode":"7000",
    "sg:province":"Hainaut",
    "sg:tags":[
        "gardening",
        "garden",
        "maintenance"
    ],
    "wof:name":"Genard T",
    "wof:placetype":"venue"
},
  "geometry": {"coordinates":[3.9778990746,50.4637718201],"type":"Point"}
}