{
  "type": "Feature",
  "properties": {
    "addr:full":"Kerkstraat 3 Hoeselt Limburg 3730",
    "addr:housenumber":"3",
    "addr:postcode":"3730",
    "addr:street":"Kerkstraat",
    "iso:country":"BE",
    "sg:address":"Kerkstraat 3",
    "sg:city":"Hoeselt",
    "sg:orig_category":"Banques and organismes de cr\u00e9dit",
    "sg:phone":"+32 89 41 35 06",
    "sg:postcode":"3730",
    "sg:province":"Limburg",
    "wof:name":"Kbc",
    "wof:placetype":"venue"
},
  "geometry": {"coordinates":[5.4889349937,50.8501052856],"type":"Point"}
}