{
  "type": "Feature",
  "properties": {
    "addr:full":"Rooigemlaan 482 Gent Oost-Vlaanderen 9000",
    "addr:housenumber":"482",
    "addr:postcode":"9000",
    "addr:street":"Rooigemlaan;Oost-Vlaanderen",
    "iso:country":"BE",
    "sg:address":"Rooigemlaan 482",
    "sg:city":"Gent",
    "sg:classifiers":[
        {
            "category":"Professional",
            "subcategory":"Management & Consulting",
            "type":"Services"
        }
    ],
    "sg:phone":"+32 9 227 55 91",
    "sg:postcode":"9000",
    "sg:province":"Oost-Vlaanderen",
    "sg:tags":[
        "consultant",
        "agency",
        "advertising"
    ],
    "wof:name":"Pma",
    "wof:placetype":"venue"
},
  "geometry": {"coordinates":[3.695884943,51.0639152527],"type":"Point"}
}