{
  "type": "Feature",
  "properties": {
    "addr:full":"Moutstraat 132 Gent Oost-Vlaanderen 9000",
    "addr:housenumber":"132",
    "addr:postcode":"9000",
    "addr:street":"Moutstraat;Oost-Vlaanderen",
    "iso:country":"BE",
    "sg:address":"Moutstraat 132",
    "sg:city":"Gent",
    "sg:classifiers":[
        {
            "category":"Shopping",
            "subcategory":"Computers & Home Electronics",
            "type":"Retail Goods"
        }
    ],
    "sg:phone":"+32 9 244 88 11",
    "sg:postcode":"9000",
    "sg:province":"Oost-Vlaanderen",
    "sg:tags":[
        "automobile",
        "-",
        "navigation",
        "system"
    ],
    "wof:name":"Tele Atlas Data Gent Bv",
    "wof:placetype":"venue"
},
  "geometry": {"coordinates":[3.7372570038,51.0300521851],"type":"Point"}
}