{
  "type": "Feature",
  "properties": {
    "addr:full":"Dr\u00c8ve Olympique 13 Anderlecht Bruxelles-Capitale 1070",
    "addr:housenumber":"13",
    "addr:postcode":"1070",
    "addr:street":"Dre\u0300Ve Olympique",
    "iso:country":"BE",
    "sg:address":"Dr\u00c8ve Olympique 13",
    "sg:city":"Anderlecht",
    "sg:classifiers":[
        {
            "category":"Shopping",
            "subcategory":"Clothing, Apparel, & Fashions",
            "type":"Retail Goods"
        }
    ],
    "sg:phone":"+32 2 524 54 00",
    "sg:postcode":"1070",
    "sg:province":"Bruxelles-Capitale",
    "sg:tags":[
        "v\u00eatements",
        "pour",
        "dame"
    ],
    "wof:name":"Poly-mod",
    "wof:placetype":"venue"
},
  "geometry": {"coordinates":[4.2757501602,50.8211784363],"type":"Point"}
}