{
  "type": "Feature",
  "properties": {
    "addr:full":"Route De Ch\u00f4des 38 Malmedy Li\u00e8ge 4960",
    "addr:housenumber":"38",
    "addr:postcode":"4960",
    "addr:street":"Route De Cho\u0302Des",
    "iso:country":"BE",
    "sg:address":"Route De Ch\u00f4des 38",
    "sg:city":"Malmedy",
    "sg:classifiers":[
        {
            "category":"Shopping",
            "subcategory":"Bicycles & Sporting Goods",
            "type":"Retail Goods"
        }
    ],
    "sg:phone":"+32 80 33 77 19",
    "sg:postcode":"4960",
    "sg:province":"Li\u00e8ge",
    "sg:tags":[
        "-"
    ],
    "wof:name":"Fagnes Evasion",
    "wof:placetype":"venue"
},
  "geometry": {"coordinates":[6.039203167,50.4236068726],"type":"Point"}
}