{
  "type": "Feature",
  "properties": {
    "iso:country":"BE",
    "sg:address":"Dikkebusstraat 23",
    "sg:city":"Heuvelland (de Klijte)",
    "sg:classifiers":[
        {
            "category":"Autos & Motor Vehicles",
            "subcategory":"Fuel & Gas Station",
            "type":"Retail Goods"
        }
    ],
    "sg:phone":"+32 57 44 73 70",
    "sg:postcode":"8954",
    "sg:province":"West-Vlaanderen",
    "wof:name":"Verclyte Bvba",
    "wof:placetype":"venue"
},
  "geometry": {"coordinates":[2.7856349945,50.7974319458],"type":"Point"}
}