{
  "type": "Feature",
  "properties": {
    "iso:country":"BE",
    "sg:address":"Le Haumont 32",
    "sg:city":"Herve",
    "sg:orig_category":"Woningbouw",
    "sg:phone":"+32 87 31 69 39",
    "sg:postcode":"4650",
    "sg:province":"Li\u00e8ge",
    "wof:name":"Henri Darchambeau",
    "wof:placetype":"venue"
},
  "geometry": {"coordinates":[5.8063421249,50.6049308777],"type":"Point"}
}