{
  "type": "Feature",
  "properties": {
    "iso:country":"BE",
    "sg:address":"Zavelstraat 137",
    "sg:city":"Kortenberg (erps-kwerps)",
    "sg:classifiers":[
        {
            "category":"Banks & Credit Unions",
            "subcategory":"Investment Brokerage",
            "type":"Services"
        }
    ],
    "sg:phone":"+32 2 759 73 07",
    "sg:postcode":"3071",
    "sg:province":"Vlaams-Brabant",
    "sg:tags":[
        "printing",
        "-"
    ],
    "wof:name":"Van Erps Drukkerij",
    "wof:placetype":"venue"
},
  "geometry": {"coordinates":[4.5688757896,50.89320755],"type":"Point"}
}