{
  "type": "Feature",
  "properties": {
    "iso:country":"BE",
    "sg:address":"Zwart Goor 1",
    "sg:city":"Merksplas",
    "sg:classifiers":[
        {
            "category":"Social Services",
            "type":"Services"
        }
    ],
    "sg:phone":"+32 14 63 62 11",
    "sg:postcode":"2330",
    "sg:province":"Antwerpen",
    "sg:tags":[
        "handicapped",
        "-"
    ],
    "wof:name":"Zwart Goor ('t) Dienstverleningscentrum",
    "wof:placetype":"venue"
},
  "geometry": {"coordinates":[4.8891801834,51.3852233887],"type":"Point"}
}