{
  "type": "Feature",
  "properties": {
    "addr:full":"Tarantellastraat 7 Anderlecht/anderlecht Bruxelles-Capitale 1070",
    "addr:housenumber":"7",
    "addr:postcode":"1070",
    "addr:street":"Tarantellastraat",
    "iso:country":"BE",
    "sg:address":"Tarantellastraat 7",
    "sg:city":"Anderlecht/anderlecht",
    "sg:orig_category":"Groenten and fruit Gh",
    "sg:phone":"+32 2 411 41 34",
    "sg:postcode":"1070",
    "sg:province":"Bruxelles-Capitale",
    "wof:name":"Estelle Berriere",
    "wof:placetype":"venue"
},
  "geometry": {"coordinates":[4.2944478989,50.8471641541],"type":"Point"}
}