{
  "type": "Feature",
  "properties": {
    "iso:country":"BE",
    "sg:address":"Avenue Du Derby 7 Box 1",
    "sg:city":"Bruxelles (ixelles)",
    "sg:classifiers":[
        {
            "category":"Health Services",
            "subcategory":"Dentist",
            "type":"Services"
        }
    ],
    "sg:phone":"+32 2 640 53 72",
    "sg:postcode":"1050",
    "sg:province":"Bruxelles-Capitale",
    "wof:name":"Adams Philippe",
    "wof:placetype":"venue"
},
  "geometry": {"coordinates":[4.3878779411,50.8054008484],"type":"Point"}
}