{
  "type": "Feature",
  "properties": {
    "iso:country":"BE",
    "sg:address":"Rue Des Hautes Voies 20",
    "sg:city":"Bertrix (auby-sur-semois)",
    "sg:classifiers":[
        {
            "category":"Health Services",
            "subcategory":"Health Practitioner",
            "type":"Services"
        }
    ],
    "sg:phone":"+32 61 41 36 10",
    "sg:postcode":"6880",
    "sg:province":"Luxembourg",
    "sg:tags":[
        "therapist",
        "speech"
    ],
    "wof:name":"Parmentier-fettweis",
    "wof:placetype":"venue"
},
  "geometry": {"coordinates":[5.1880779266,49.8166275024],"type":"Point"}
}