{
  "type": "Feature",
  "properties": {
    "addr:full":"Onafhankelijkheidsstraat 129 Edegem Antwerpen 2650",
    "addr:housenumber":"129",
    "addr:postcode":"2650",
    "addr:street":"Onafhankelijkheidsstraat",
    "iso:country":"BE",
    "sg:address":"Onafhankelijkheidsstraat 129",
    "sg:city":"Edegem",
    "sg:classifiers":[
        {
            "category":"Building & Trades",
            "subcategory":"Cleaning & Sanitation",
            "type":"Services"
        }
    ],
    "sg:phone":"+32 3 288 51 67",
    "sg:postcode":"2650",
    "sg:province":"Antwerpen",
    "sg:tags":[
        "-",
        "rug",
        "carpet"
    ],
    "wof:name":"Home Cleaning Services",
    "wof:placetype":"venue"
},
  "geometry": {"coordinates":[4.4458432198,51.1600952148],"type":"Point"}
}