{
  "type": "Feature",
  "properties": {
    "addr:full":"Rue Du Mail 73 Elsene/ixelles Bruxelles-Capitale 1050",
    "addr:housenumber":"73",
    "addr:postcode":"1050",
    "addr:street":"Rue Du Mail",
    "iso:country":"BE",
    "sg:address":"Rue Du Mail 73",
    "sg:city":"Elsene/ixelles",
    "sg:orig_category":"D\u00e9corateurs d'int\u00e9rieur",
    "sg:phone":"+32 2 534 68 83",
    "sg:postcode":"1050",
    "sg:province":"Bruxelles-Capitale",
    "wof:name":"O.h.",
    "wof:placetype":"venue"
},
  "geometry": {"coordinates":[4.3591918945,50.8219871521],"type":"Point"}
}