{
  "type": "Feature",
  "properties": {
    "addr:full":"Avenue De Spa 111 Heusy Li\u00e8ge 4802",
    "addr:housenumber":"111",
    "addr:postcode":"4802",
    "addr:street":"Avenue De Spa",
    "iso:country":"BE",
    "sg:address":"Avenue De Spa 111",
    "sg:city":"Heusy",
    "sg:orig_category":"Schoenen",
    "sg:phone":"+32 87 22 25 85",
    "sg:postcode":"4802",
    "sg:province":"Li\u00e8ge",
    "wof:name":"Traces De Pas",
    "wof:placetype":"venue"
},
  "geometry": {"coordinates":[5.8652210236,50.5795783997],"type":"Point"}
}