{
  "type": "Feature",
  "properties": {
    "iso:country":"BE",
    "sg:address":"Rue De Thoricourt 21",
    "sg:city":"Silly",
    "sg:orig_category":"Rundveehouders",
    "sg:phone":"+32 67 45 83 03",
    "sg:postcode":"7830",
    "sg:province":"Hainaut",
    "wof:name":"Hugo Tresnie",
    "wof:placetype":"venue"
},
  "geometry": {"coordinates":[3.9305300713,50.6185340881],"type":"Point"}
}