{
  "type": "Feature",
  "properties": {
    "iso:country":"BE",
    "sg:address":"Avenue Louise 179",
    "sg:city":"Bruxelles (ixelles)",
    "sg:classifiers":[
        {
            "category":"Insurance",
            "subcategory":"Insurance Agent",
            "type":"Services"
        }
    ],
    "sg:phone":"+32 2 642 94 84",
    "sg:postcode":"1050",
    "sg:province":"Bruxelles-Capitale",
    "sg:tags":[
        "factoring"
    ],
    "wof:name":"Commercial Finance Group Nv",
    "wof:placetype":"venue"
},
  "geometry": {"coordinates":[4.3628511429,50.8276786804],"type":"Point"}
}