{
  "type": "Feature",
  "properties": {
    "iso:country":"BE",
    "sg:address":"Kerkstraat 21",
    "sg:city":"Stekene",
    "sg:classifiers":[
        {
            "category":"Personal",
            "subcategory":"Shoe Repair & Shine",
            "type":"Services"
        }
    ],
    "sg:phone":"+32 3 779 82 81",
    "sg:postcode":"9190",
    "sg:province":"Oost-Vlaanderen",
    "sg:tags":[
        "shoemaker"
    ],
    "wof:name":"Klompje (het)",
    "wof:placetype":"venue"
},
  "geometry": {"coordinates":[4.0397930145,51.2068824768],"type":"Point"}
}