{
  "type": "Feature",
  "properties": {
    "addr:full":"Avenue Fabiola 43 Edingen/enghien Hainaut 7850",
    "addr:housenumber":"43",
    "addr:postcode":"7850",
    "addr:street":"Avenue Fabiola",
    "iso:country":"BE",
    "sg:address":"Avenue Fabiola 43",
    "sg:city":"Edingen/enghien",
    "sg:orig_category":"Timbres, monnaies and troph\u00e9es",
    "sg:phone":"+32 2 395 69 73",
    "sg:postcode":"7850",
    "sg:province":"Hainaut",
    "wof:name":"Richard Kosnicki",
    "wof:placetype":"venue"
},
  "geometry": {"coordinates":[4.0491552353,50.6983985901],"type":"Point"}
}