{
  "type": "Feature",
  "properties": {
    "addr:full":"Handelslei 33 Sint-job-in-'t Goor Antwerpen 2960",
    "addr:housenumber":"33",
    "addr:postcode":"2960",
    "addr:street":"Handelslei;' T Goor",
    "iso:country":"BE",
    "sg:address":"Handelslei 33",
    "sg:city":"Sint-job-in-'t Goor",
    "sg:orig_category":"Huisdieren and benodigdheden Royal Canin",
    "sg:phone":"+32 3 663 37 46",
    "sg:postcode":"2960",
    "sg:province":"Antwerpen",
    "wof:name":"Vroman",
    "wof:placetype":"venue"
},
  "geometry": {"coordinates":[6.5870299339,52.2344093323],"type":"Point"}
}