{
  "type": "Feature",
  "properties": {
    "addr:full":"Stoofstraat 6 Boechout Antwerpen 2530",
    "addr:housenumber":"6",
    "addr:postcode":"2530",
    "addr:street":"Stoofstraat",
    "iso:country":"BE",
    "sg:address":"Stoofstraat 6",
    "sg:city":"Boechout",
    "sg:orig_category":"Producteurs de l\u00e9gumes",
    "sg:phone":"+32 3 455 68 67",
    "sg:postcode":"2530",
    "sg:province":"Antwerpen",
    "wof:name":"Walter Hendrickx",
    "wof:placetype":"venue"
},
  "geometry": {"coordinates":[4.5240921974,51.1598777771],"type":"Point"}
}