{
  "type": "Feature",
  "properties": {
    "addr:full":"Tervuursestraat 17b3b Leuven Vlaams-Brabant 3000",
    "addr:housenumber":"17b3b",
    "addr:postcode":"3000",
    "addr:street":"Tervuursestraat",
    "iso:country":"BE",
    "sg:address":"Tervuursestraat 17b3b",
    "sg:city":"Leuven",
    "sg:orig_category":"Paramedische behandelingen",
    "sg:phone":"+32 16 29 31 68",
    "sg:postcode":"3000",
    "sg:province":"Vlaams-Brabant",
    "wof:name":"M. Ceyssens",
    "wof:placetype":"venue"
},
  "geometry": {"coordinates":[4.6892471313,50.879196167],"type":"Point"}
}