{
  "type": "Feature",
  "properties": {
    "addr:full":"Hekstraat 54 Beringen Limburg 3580",
    "addr:housenumber":"54",
    "addr:postcode":"3580",
    "addr:street":"Hekstraat",
    "iso:country":"BE",
    "sg:address":"Hekstraat 54",
    "sg:city":"Beringen",
    "sg:classifiers":[
        {
            "category":"Professional",
            "subcategory":"Accounting & Tax Preparation",
            "type":"Services"
        }
    ],
    "sg:phone":"+32 11 42 60 05",
    "sg:postcode":"3580",
    "sg:province":"Limburg",
    "sg:tags":[
        "bookkeeper"
    ],
    "wof:name":"Belien Ch",
    "wof:placetype":"venue"
},
  "geometry": {"coordinates":[5.2113361359,51.0420227051],"type":"Point"}
}