{
  "type": "Feature",
  "properties": {
    "iso:country":"BE",
    "sg:address":"Rue De Hornes 1",
    "sg:city":"Charleroi",
    "sg:orig_category":"Biens d'occasion. Journaux",
    "sg:phone":"+32 71 34 32 17",
    "sg:postcode":"6040",
    "sg:province":"Hainaut",
    "wof:name":"Librairie Lambillotte",
    "wof:placetype":"venue"
},
  "geometry": {"coordinates":[4.4490599632,50.4409065247],"type":"Point"}
}