{
  "type": "Feature",
  "properties": {
    "addr:full":"Doelstraat 176 Ingelmunster West-Vlaanderen 8770",
    "addr:housenumber":"176",
    "addr:postcode":"8770",
    "addr:street":"Doelstraat",
    "iso:country":"BE",
    "sg:address":"Doelstraat 176",
    "sg:city":"Ingelmunster",
    "sg:orig_category":"Slagers",
    "sg:phone":"+32 51 30 10 15",
    "sg:postcode":"8770",
    "sg:province":"West-Vlaanderen",
    "wof:name":"Bart Defour",
    "wof:placetype":"venue"
},
  "geometry": {"coordinates":[3.237169981,50.9355125427],"type":"Point"}
}