{
  "type": "Feature",
  "properties": {
    "addr:full":"Adegemstraat 151 Mechelen Antwerpen 2800",
    "addr:housenumber":"151",
    "addr:postcode":"2800",
    "addr:street":"Adegemstraat",
    "iso:country":"BE",
    "sg:address":"Adegemstraat 151",
    "sg:city":"Mechelen",
    "sg:orig_category":"Kapsalons",
    "sg:phone":"+32 15 26 11 10",
    "sg:postcode":"2800",
    "sg:province":"Antwerpen",
    "wof:name":"Hair Atelier Chantal",
    "wof:placetype":"venue"
},
  "geometry": {"coordinates":[4.4709010124,51.0275802612],"type":"Point"}
}