{
  "type": "Feature",
  "properties": {
    "addr:full":"Aalbeeksesteenweg 42 Kortrijk West-Vlaanderen 8500",
    "addr:housenumber":"42",
    "addr:postcode":"8500",
    "addr:street":"Aalbeeksesteenweg",
    "iso:country":"BE",
    "sg:address":"Aalbeeksesteenweg 42",
    "sg:city":"Kortrijk",
    "sg:classifiers":[
        {
            "category":"Bakery",
            "type":"Food & Drink"
        }
    ],
    "sg:phone":"+32 56 22 72 76",
    "sg:postcode":"8500",
    "sg:province":"West-Vlaanderen",
    "sg:tags":[
        "confectioner",
        "baker"
    ],
    "wof:name":"Bagettje ('t)",
    "wof:placetype":"venue"
},
  "geometry": {"coordinates":[3.2583580017,50.8222084045],"type":"Point"}
}