{
  "type": "Feature",
  "properties": {
    "addr:full":"Fr\u00e4iheetswee 147 Attert Luxembourg 6717",
    "addr:housenumber":"147",
    "addr:postcode":"6717",
    "addr:street":"Fraeiheetswee",
    "iso:country":"BE",
    "sg:address":"Fr\u00e4iheetswee 147",
    "sg:city":"Attert",
    "sg:classifiers":[
        {
            "category":"Health Services",
            "subcategory":"Health Practitioner",
            "type":"Services"
        }
    ],
    "sg:phone":"+32 63 23 56 65",
    "sg:postcode":"6717",
    "sg:province":"Luxembourg",
    "sg:tags":[
        "physiotherapist"
    ],
    "wof:name":"Tassigny Fran\u00e7oise",
    "wof:placetype":"venue"
},
  "geometry": {"coordinates":[5.7888741493,49.7506217957],"type":"Point"}
}