{
  "type": "Feature",
  "properties": {
    "addr:full":"Duinkerkekeiweg 1 De Panne West-Vlaanderen 8660",
    "addr:housenumber":"1",
    "addr:postcode":"8660",
    "addr:street":"Duinkerkekeiweg",
    "iso:country":"BE",
    "sg:address":"Duinkerkekeiweg 1",
    "sg:city":"De Panne",
    "sg:orig_category":"Stations-service and carburants. V\u00e9hicules automobiles. Tabac",
    "sg:phone":"+32 58 41 19 81",
    "sg:postcode":"8660",
    "sg:province":"West-Vlaanderen",
    "wof:name":"Adicar",
    "wof:placetype":"venue"
},
  "geometry": {"coordinates":[2.5955309868,51.0732765198],"type":"Point"}
}