{
  "type": "Feature",
  "properties": {
    "addr:full":"Heislagsebaan 7 Brasschaat Antwerpen 2930",
    "addr:housenumber":"7",
    "addr:postcode":"2930",
    "addr:street":"Heislagsebaan",
    "iso:country":"BE",
    "sg:address":"Heislagsebaan 7",
    "sg:city":"Brasschaat",
    "sg:orig_category":"Loodgieterij, verwarming and sanitaire installaties",
    "sg:phone":"+32 3 653 48 84",
    "sg:postcode":"2930",
    "sg:province":"Antwerpen",
    "wof:name":"Badboetiek Hellemans",
    "wof:placetype":"venue"
},
  "geometry": {"coordinates":[4.4995999336,51.2980270386],"type":"Point"}
}