{
  "type": "Feature",
  "properties": {
    "iso:country":"BE",
    "sg:address":"Hopmarkt 43",
    "sg:city":"Aalst",
    "sg:orig_category":"Kapsalons Speciaalzaken",
    "sg:phone":"+32 53 21 21 20",
    "sg:postcode":"9300",
    "sg:province":"Oost-Vlaanderen",
    "wof:name":"Marcel Troupin",
    "wof:placetype":"venue"
},
  "geometry": {"coordinates":[4.0369148254,50.937877655],"type":"Point"}
}