{
  "type": "Feature",
  "properties": {
    "iso:country":"BE",
    "sg:address":"Kouterweg 25",
    "sg:city":"Dentergem",
    "sg:orig_category":"Eleveurs de bovins. Eleveurs and marchands de porcs",
    "sg:phone":"+32 51 63 38 09",
    "sg:postcode":"8720",
    "sg:province":"West-Vlaanderen",
    "wof:name":"Johan Vanderheeren",
    "wof:placetype":"venue"
},
  "geometry": {"coordinates":[3.4147629738,50.952003479],"type":"Point"}
}