{
  "type": "Feature",
  "properties": {
    "iso:country":"BE",
    "sg:address":"Lodewijk Coiseaukaai 46",
    "sg:city":"Brugge",
    "sg:classifiers":[
        {
            "category":"Community Center",
            "subcategory":"Youth",
            "type":"Public Place"
        }
    ],
    "sg:phone":"+32 50 59 93 21",
    "sg:postcode":"8000",
    "sg:province":"West-Vlaanderen",
    "sg:tags":[
        "club"
    ],
    "wof:name":"Vlaamse Jeugdherberg herdersbrug",
    "wof:placetype":"venue"
},
  "geometry": {"coordinates":[3.2261660099,51.2305412292],"type":"Point"}
}