{
  "type": "Feature",
  "properties": {
    "addr:full":"Achterstraatje 5 Wuustwezel Antwerpen 2990",
    "addr:housenumber":"5",
    "addr:postcode":"2990",
    "addr:street":"Achterstraatje",
    "iso:country":"BE",
    "sg:address":"Achterstraatje 5",
    "sg:city":"Wuustwezel",
    "sg:classifiers":[
        {
            "category":"Home & Garden",
            "subcategory":"Carpets & Floor Coverings",
            "type":"Retail Goods"
        }
    ],
    "sg:phone":"+32 3 669 54 07",
    "sg:postcode":"2990",
    "sg:province":"Antwerpen",
    "sg:tags":[
        "armoring"
    ],
    "wof:name":"Algemene Bouwwerken Looyen",
    "wof:placetype":"venue"
},
  "geometry": {"coordinates":[4.602640152,51.3860206604],"type":"Point"}
}