{
  "type": "Feature",
  "properties": {
    "iso:country":"BE",
    "sg:address":"Jachtweg 1",
    "sg:city":"Buggenhout",
    "sg:orig_category":"Sportclubs",
    "sg:phone":"+32 52 35 41 78",
    "sg:postcode":"9255",
    "sg:province":"Oost-Vlaanderen",
    "wof:name":"Zaal Nikolaas",
    "wof:placetype":"venue"
},
  "geometry": {"coordinates":[4.1991009712,51.0141983032],"type":"Point"}
}