{
  "type": "Feature",
  "properties": {
    "iso:country":"BE",
    "sg:address":"Avenue Lavoisier 25",
    "sg:city":"Wavre",
    "sg:classifiers":[
        {
            "category":"Utilities",
            "subcategory":"Natural Gas",
            "type":"Services"
        }
    ],
    "sg:phone":"+32 10 24 35 30",
    "sg:postcode":"1300",
    "sg:province":"Brabant Wallon",
    "sg:tags":[
        "filter",
        "-",
        "liquid"
    ],
    "wof:name":"Apr\u00e9 Sprl",
    "wof:placetype":"venue"
},
  "geometry": {"coordinates":[4.5894970894,50.7348899841],"type":"Point"}
}