{
  "type": "Feature",
  "properties": {
    "addr:full":"Place Jean Jaur\u00c8s 39 Herstal Li\u00e8ge 4040",
    "addr:housenumber":"39",
    "addr:postcode":"4040",
    "addr:street":"Place Jean Jaure\u0300S",
    "iso:country":"BE",
    "sg:address":"Place Jean Jaur\u00c8s 39",
    "sg:city":"Herstal",
    "sg:orig_category":"Pain, p\u00e2tisseries and confiseries",
    "sg:phone":"+32 4 240 25 83",
    "sg:postcode":"4040",
    "sg:province":"Li\u00e8ge",
    "wof:name":"Point Chaud",
    "wof:placetype":"venue"
},
  "geometry": {"coordinates":[5.6310310364,50.6655845642],"type":"Point"}
}