{
  "type": "Feature",
  "properties": {
    "addr:full":"Rue De Jeumont 8 Courcelles Hainaut 6181",
    "addr:housenumber":"8",
    "addr:postcode":"6181",
    "addr:street":"Rue De Jeumont",
    "iso:country":"BE",
    "sg:address":"Rue De Jeumont 8",
    "sg:city":"Courcelles",
    "sg:orig_category":"Rundveehouders",
    "sg:phone":"+32 71 84 48 12",
    "sg:postcode":"6181",
    "sg:province":"Hainaut",
    "wof:name":"Pol Ballieux",
    "wof:placetype":"venue"
},
  "geometry": {"coordinates":[4.3141288757,50.4859046936],"type":"Point"}
}