{
  "type": "Feature",
  "properties": {
    "addr:full":"Zuidstraat 10 Ingelmunster West-Vlaanderen 8770",
    "addr:housenumber":"10",
    "addr:postcode":"8770",
    "addr:street":"Zuidstraat",
    "iso:country":"BE",
    "sg:address":"Zuidstraat 10",
    "sg:city":"Ingelmunster",
    "sg:orig_category":"Producteurs de l\u00e9gumes",
    "sg:phone":"+32 56 66 63 40",
    "sg:postcode":"8770",
    "sg:province":"West-Vlaanderen",
    "wof:name":"Vanrobays Gebrs",
    "wof:placetype":"venue"
},
  "geometry": {"coordinates":[3.2847011089,50.9096221924],"type":"Point"}
}