{
  "type": "Feature",
  "properties": {
    "addr:full":"A. Bosmanslaan 70 Begijnendijk (betekom) Vlaams-Brabant 3130",
    "addr:housenumber":"70",
    "addr:postcode":"3130",
    "addr:street":"A. Bosmanslaan",
    "iso:country":"BE",
    "sg:address":"A. Bosmanslaan 70",
    "sg:city":"Begijnendijk (betekom)",
    "sg:classifiers":[
        {
            "category":"Health Services",
            "subcategory":"Nursing And Care Facility",
            "type":"Services"
        }
    ],
    "sg:phone":"+32 16 20 42 55",
    "sg:postcode":"3130",
    "sg:province":"Vlaams-Brabant",
    "sg:tags":[
        "home"
    ],
    "wof:name":"Coninx J",
    "wof:placetype":"venue"
},
  "geometry": {"coordinates":[4.7859082222,50.9902801514],"type":"Point"}
}