{
  "type": "Feature",
  "properties": {
    "addr:full":"Rue Jean Volders 48 Sint-gillis/saint-gilles Bruxelles-Capitale 1060",
    "addr:housenumber":"48",
    "addr:postcode":"1060",
    "addr:street":"Rue Jean Volders",
    "iso:country":"BE",
    "sg:address":"Rue Jean Volders 48",
    "sg:city":"Sint-gillis/saint-gilles",
    "sg:classifiers":[
        {
            "category":"Restaurant",
            "type":"Food & Drink"
        }
    ],
    "sg:phone":"+32 2 538 53 54",
    "sg:postcode":"1060",
    "sg:province":"Bruxelles-Capitale",
    "wof:name":"La Porteuse D'eau",
    "wof:placetype":"venue"
},
  "geometry": {"coordinates":[4.3435778618,50.8316612244],"type":"Point"}
}