{
  "type": "Feature",
  "properties": {
    "iso:country":"BE",
    "sg:address":"Kartuizersvest 115",
    "sg:city":"Lier",
    "sg:orig_category":"Advocaten and juridische adviseurs",
    "sg:phone":"+32 3 480 58 03",
    "sg:postcode":"2500",
    "sg:province":"Antwerpen",
    "wof:name":"Magteld Leys",
    "wof:placetype":"venue"
},
  "geometry": {"coordinates":[4.5710711479,51.1349372864],"type":"Point"}
}