{
  "type": "Feature",
  "properties": {
    "iso:country":"BE",
    "sg:address":"Molenstraat 22",
    "sg:city":"Zingem",
    "sg:orig_category":"Agences d'exp\u00e9dition",
    "sg:phone":"+32 9 383 72 87",
    "sg:postcode":"9750",
    "sg:province":"Oost-Vlaanderen",
    "wof:name":"N. Schepens",
    "wof:placetype":"venue"
},
  "geometry": {"coordinates":[3.5881719589,50.9018630981],"type":"Point"}
}