{
  "type": "Feature",
  "properties": {
    "iso:country":"BE",
    "sg:address":"Impasse De La Cense Gain",
    "sg:city":"Mons",
    "sg:classifiers":[
        {
            "category":"Health Services",
            "subcategory":"Doctor",
            "type":"Services"
        }
    ],
    "sg:phone":"+32 65 36 13 88",
    "sg:postcode":"7000",
    "sg:province":"Hainaut",
    "sg:tags":[
        "medicinephysicians",
        "surgeon"
    ],
    "wof:name":"Droissart C",
    "wof:placetype":"venue"
},
  "geometry": {"coordinates":[3.9887430668,50.4518470764],"type":"Point"}
}