{
  "type": "Feature",
  "properties": {
    "addr:full":"Ham 18 Esneux Li\u00e8ge 4130",
    "addr:housenumber":"18",
    "addr:postcode":"4130",
    "addr:street":"Ham",
    "iso:country":"BE",
    "sg:address":"Ham 18",
    "sg:city":"Esneux",
    "sg:classifiers":[
        {
            "category":"Real Estate",
            "subcategory":"Architect",
            "type":"Services"
        }
    ],
    "sg:phone":"+32 4 380 23 41",
    "sg:postcode":"4130",
    "sg:province":"Li\u00e8ge",
    "wof:name":"Salmon V",
    "wof:placetype":"venue"
},
  "geometry": {"coordinates":[5.5594348907,50.5416145325],"type":"Point"}
}