{
  "type": "Feature",
  "properties": {
    "addr:full":"Rue Des Sangliers 10 Bruxelles (watermael-boitsfort) Bruxelles-Capitale 1170",
    "addr:housenumber":"10",
    "addr:postcode":"1170",
    "addr:street":"Rue Des Sangliers",
    "iso:country":"BE",
    "sg:address":"Rue Des Sangliers 10",
    "sg:city":"Bruxelles (watermael-boitsfort)",
    "sg:classifiers":[
        {
            "category":"Shopping",
            "subcategory":"Musical Instruments",
            "type":"Retail Goods"
        }
    ],
    "sg:phone":"+32 2 662 13 93",
    "sg:postcode":"1170",
    "sg:province":"Bruxelles-Capitale",
    "sg:tags":[
        "optical"
    ],
    "wof:name":"Lambda-x Sprl",
    "wof:placetype":"venue"
},
  "geometry": {"coordinates":[4.4094538689,50.7976570129],"type":"Point"}
}