{
  "type": "Feature",
  "properties": {
    "iso:country":"BE",
    "sg:address":"Torkonjestraat 21d",
    "sg:city":"Kortrijk",
    "sg:orig_category":"Dakwerken Loodgieterij, verwarming and sanitaire installaties",
    "sg:phone":"+32 56 21 52 52",
    "sg:postcode":"8510",
    "sg:province":"West-Vlaanderen",
    "wof:name":"Dejonckheere",
    "wof:placetype":"venue"
},
  "geometry": {"coordinates":[3.2410149574,50.795501709],"type":"Point"}
}