{
  "type": "Feature",
  "properties": {
    "addr:full":"Rue Du Centre 46 Mettet Namur 5640",
    "addr:housenumber":"46",
    "addr:postcode":"5640",
    "addr:street":"Rue Du Centre",
    "iso:country":"BE",
    "sg:address":"Rue Du Centre 46",
    "sg:city":"Mettet",
    "sg:orig_category":"V\u00e9t\u00e9rinaires",
    "sg:phone":"+32 71 72 97 80",
    "sg:postcode":"5640",
    "sg:province":"Namur",
    "wof:name":"Pierre Bodranghien",
    "wof:placetype":"venue"
},
  "geometry": {"coordinates":[4.6578397751,50.3198051453],"type":"Point"}
}