{
  "type": "Feature",
  "properties": {
    "iso:country":"BE",
    "sg:address":"Rue De L'institut 1",
    "sg:city":"Namur (bouge)",
    "sg:classifiers":[
        {
            "category":"Banks & Credit Unions",
            "subcategory":"Financial Services",
            "type":"Services"
        }
    ],
    "sg:phone":"+32 81 20 03 20",
    "sg:postcode":"5004",
    "sg:province":"Namur",
    "sg:tags":[
        "financing"
    ],
    "wof:name":"Comptoir D'escompte De Namur-dinant-marche",
    "wof:placetype":"venue"
},
  "geometry": {"coordinates":[4.8853721619,50.4740180969],"type":"Point"}
}