{
  "type": "Feature",
  "properties": {
    "addr:full":"Kapelseweg 101 Mechelen Antwerpen 2811",
    "addr:housenumber":"101",
    "addr:postcode":"2811",
    "addr:street":"Kapelseweg",
    "iso:country":"BE",
    "sg:address":"Kapelseweg 101",
    "sg:city":"Mechelen",
    "sg:orig_category":"Ordinateurs and \u00e9quipement informatique",
    "sg:phone":"+32 15 42 13 98",
    "sg:postcode":"2811",
    "sg:province":"Antwerpen",
    "wof:name":"Kleisz Informatika",
    "wof:placetype":"venue"
},
  "geometry": {"coordinates":[4.4212641716,51.0178604126],"type":"Point"}
}