{
  "type": "Feature",
  "properties": {
    "iso:country":"BE",
    "sg:address":"Gouwelozestraat 76ba2",
    "sg:city":"Oostende",
    "sg:orig_category":"Boucheries",
    "sg:phone":"+32 59 70 20 77",
    "sg:postcode":"8400",
    "sg:province":"West-Vlaanderen",
    "wof:name":"J. Vandekerckhove",
    "wof:placetype":"venue"
},
  "geometry": {"coordinates":[2.9326560497,51.2179946899],"type":"Point"}
}