{
  "type": "Feature",
  "properties": {
    "iso:country":"BE",
    "sg:address":"Dr\u00c8ve Des Marguerites 38",
    "sg:city":"Edingen/enghien",
    "sg:orig_category":"Architectes",
    "sg:phone":"+32 2 395 35 95",
    "sg:postcode":"7850",
    "sg:province":"Hainaut",
    "wof:name":"Dani\u00cbl Soumillion",
    "wof:placetype":"venue"
},
  "geometry": {"coordinates":[4.1080431938,50.706741333],"type":"Point"}
}