{
  "type": "Feature",
  "properties": {
    "iso:country":"BE",
    "sg:address":"Avenue Reine Astrid 160",
    "sg:city":"Verviers",
    "sg:orig_category":"Banken and kredietinstellingen",
    "sg:phone":"+32 87 22 50 85",
    "sg:postcode":"4802",
    "sg:province":"Li\u00e8ge",
    "wof:name":"Dexia",
    "wof:placetype":"venue"
},
  "geometry": {"coordinates":[5.88377285,50.5843353271],"type":"Point"}
}