{
  "type": "Feature",
  "properties": {
    "addr:full":"Rue Bois-eloi 32 Lasne Brabant Wallon 1380",
    "addr:housenumber":"32",
    "addr:postcode":"1380",
    "addr:street":"Rue Bois-Eloi",
    "iso:country":"BE",
    "sg:address":"Rue Bois-eloi 32",
    "sg:city":"Lasne",
    "sg:orig_category":"M\u00e9decins and sp\u00e9cialistes",
    "sg:phone":"+32 2 633 17 56",
    "sg:postcode":"1380",
    "sg:province":"Brabant Wallon",
    "wof:name":"Roland Kempinaire",
    "wof:placetype":"venue"
},
  "geometry": {"coordinates":[4.4647078514,50.6763191223],"type":"Point"}
}