{
  "type": "Feature",
  "properties": {
    "addr:full":"Rue Sans Souci 51 Elsene/ixelles Bruxelles-Capitale 1050",
    "addr:housenumber":"51",
    "addr:postcode":"1050",
    "addr:street":"Rue Sans Souci",
    "iso:country":"BE",
    "sg:address":"Rue Sans Souci 51",
    "sg:city":"Elsene/ixelles",
    "sg:classifiers":[
        {
            "category":"Sports & Exercise",
            "subcategory":"Sports Center",
            "type":"Entertainment"
        }
    ],
    "sg:phone":"+32 2 512 45 18",
    "sg:postcode":"1050",
    "sg:province":"Bruxelles-Capitale",
    "sg:tags":[
        "de",
        "fitness"
    ],
    "wof:name":"Reebok - Team",
    "wof:placetype":"venue"
},
  "geometry": {"coordinates":[4.3698019981,50.8337860107],"type":"Point"}
}