{
  "type": "Feature",
  "properties": {
    "iso:country":"BE",
    "sg:address":"Chemin Des Sapins 1a",
    "sg:city":"Chaumont-gistoux",
    "sg:classifiers":[
        {
            "category":"Professional",
            "subcategory":"Engineering",
            "type":"Services"
        }
    ],
    "sg:phone":"+32 10 68 02 34",
    "sg:postcode":"1325",
    "sg:province":"Brabant Wallon",
    "sg:tags":[
        "-"
    ],
    "wof:name":"Bureau D'etudes J.renier Sprl",
    "wof:placetype":"venue"
},
  "geometry": {"coordinates":[4.6907157898,50.694316864],"type":"Point"}
}