{
  "type": "Feature",
  "properties": {
    "iso:country":"BE",
    "sg:address":"M. Van Torhoutstraat 42",
    "sg:city":"Oudenaarde",
    "sg:classifiers":[
        {
            "category":"Insurance",
            "subcategory":"Life Insurance",
            "type":"Services"
        }
    ],
    "sg:phone":"+32 55 31 00 77",
    "sg:postcode":"9700",
    "sg:province":"Oost-Vlaanderen",
    "sg:tags":[
        "assurance"
    ],
    "wof:name":"Assurfin D.v.f.",
    "wof:placetype":"venue"
},
  "geometry": {"coordinates":[3.6225800514,50.848613739],"type":"Point"}
}