{
  "type": "Feature",
  "properties": {
    "iso:country":"BE",
    "sg:address":"Voie De La Ferme Mal\u00e8ve 6",
    "sg:city":"Chaumont-gistoux (dion-valmont)",
    "sg:classifiers":[
        {
            "category":"Health Services",
            "subcategory":"Health Practitioner",
            "type":"Services"
        }
    ],
    "sg:phone":"+32 10 24 89 38",
    "sg:postcode":"1325",
    "sg:province":"Brabant Wallon",
    "sg:tags":[
        "physiotherapist"
    ],
    "wof:name":"Stiernet Laurent",
    "wof:placetype":"venue"
},
  "geometry": {"coordinates":[4.6412892342,50.6984443665],"type":"Point"}
}