{
  "type": "Feature",
  "properties": {
    "addr:full":"Ruiseledesteenweg 9ba Wingene West-Vlaanderen 8750",
    "addr:postcode":"8750",
    "addr:street":"Ruiseledesteenweg",
    "iso:country":"BE",
    "sg:address":"Ruiseledesteenweg 9ba",
    "sg:city":"Wingene",
    "sg:orig_category":"Paramedische behandelingen",
    "sg:phone":"+32 51 65 59 49",
    "sg:postcode":"8750",
    "sg:province":"West-Vlaanderen",
    "wof:name":"A. Huys",
    "wof:placetype":"venue"
},
  "geometry": {"coordinates":[3.2961349487,51.0559310913],"type":"Point"}
}