{
  "type": "Feature",
  "properties": {
    "addr:full":"Rue Col Montegnie 116 Rixensart Brabant Wallon 1332",
    "addr:housenumber":"116",
    "addr:postcode":"1332",
    "addr:street":"Rue Col Montegnie;Wallon",
    "iso:country":"BE",
    "sg:address":"Rue Col Montegnie 116",
    "sg:city":"Rixensart",
    "sg:orig_category":"Jeux and jouets",
    "sg:phone":"+32 2 653 52 75",
    "sg:postcode":"1332",
    "sg:province":"Brabant Wallon",
    "wof:name":"Brassine",
    "wof:placetype":"venue"
},
  "geometry": {"coordinates":[4.4802222252,50.7211494446],"type":"Point"}
}