{
  "type": "Feature",
  "properties": {
    "addr:full":"Torhoutse Baan 170 Gistel West-Vlaanderen 8470",
    "addr:housenumber":"170",
    "addr:postcode":"8470",
    "addr:street":"Torhoutse Baan",
    "iso:country":"BE",
    "sg:address":"Torhoutse Baan 170",
    "sg:city":"Gistel",
    "sg:classifiers":[
        {
            "category":"Restaurant",
            "type":"Food & Drink"
        }
    ],
    "sg:phone":"+32 59 27 88 23",
    "sg:postcode":"8470",
    "sg:province":"West-Vlaanderen",
    "sg:tags":[
        "dancing",
        "nachtclubs"
    ],
    "wof:name":"De Kallebasse",
    "wof:placetype":"venue"
},
  "geometry": {"coordinates":[2.9630980492,51.1440582275],"type":"Point"}
}