{
  "type": "Feature",
  "properties": {
    "addr:full":"Nolimpark 4016 Overpelt Limburg 3900",
    "addr:postcode":"4016 overpelt;3900",
    "addr:street":"Nolimpark",
    "iso:country":"BE",
    "sg:address":"Nolimpark 4016",
    "sg:city":"Overpelt",
    "sg:orig_category":"Quincailleries",
    "sg:phone":"+32 11 80 96 00",
    "sg:postcode":"3900",
    "sg:province":"Limburg",
    "wof:name":"Brabantia Home Steel",
    "wof:placetype":"venue"
},
  "geometry": {"coordinates":[5.4235649109,51.2117614746],"type":"Point"}
}