{
  "type": "Feature",
  "properties": {
    "addr:full":"Vaartstraat 155f Ranst Antwerpen 2520",
    "addr:housenumber":"155f",
    "addr:postcode":"2520",
    "addr:street":"Vaartstraat",
    "iso:country":"BE",
    "sg:address":"Vaartstraat 155f",
    "sg:city":"Ranst",
    "sg:classifiers":[
        {
            "category":"Food & Beverages",
            "subcategory":"Supermarket",
            "type":"Retail Goods"
        }
    ],
    "sg:phone":"+32 3 475 12 12",
    "sg:postcode":"2520",
    "sg:province":"Antwerpen",
    "sg:tags":[
        "frozen",
        "-"
    ],
    "wof:name":"Gerona Nv",
    "wof:placetype":"venue"
},
  "geometry": {"coordinates":[4.5882501602,51.2062492371],"type":"Point"}
}