{
  "type": "Feature",
  "properties": {
    "iso:country":"BE",
    "sg:address":"Westrozebekestraat 25a",
    "sg:city":"Zonnebeke (passendale)",
    "sg:classifiers":[
        {
            "category":"Retail",
            "subcategory":"Funeral Services",
            "type":"Services"
        }
    ],
    "sg:phone":"+32 51 77 07 59",
    "sg:postcode":"8980",
    "sg:province":"West-Vlaanderen",
    "sg:tags":[
        "director"
    ],
    "wof:name":"Vandecandelaere-spruytte Bvba",
    "wof:placetype":"venue"
},
  "geometry": {"coordinates":[2.9872550964,50.8730812073],"type":"Point"}
}