{
  "type": "Feature",
  "properties": {
    "addr:full":"Rennevoortstraat 1 Ledegem (rollegem Kapelle) West-Vlaanderen 8880",
    "addr:housenumber":"1",
    "addr:postcode":"8880",
    "addr:street":"Rennevoortstraat",
    "iso:country":"BE",
    "sg:address":"Rennevoortstraat 1",
    "sg:city":"Ledegem (rollegem Kapelle)",
    "sg:classifiers":[
        {
            "category":"Farming",
            "subcategory":"Livestock Farm",
            "type":"Manufacturing & Wholesale Goods"
        }
    ],
    "sg:phone":"+32 56 50 16 81",
    "sg:postcode":"8880",
    "sg:province":"West-Vlaanderen",
    "sg:tags":[
        "buyer"
    ],
    "wof:name":"Degroote Frans Bvba",
    "wof:placetype":"venue"
},
  "geometry": {"coordinates":[3.1559801102,50.8729743958],"type":"Point"}
}