{
  "type": "Feature",
  "properties": {
    "addr:full":"Chauss\u00c9e De Gilly 63 Charleroi Hainaut 6040",
    "addr:housenumber":"63",
    "addr:postcode":"6040",
    "addr:street":"Chausse\u0301E De Gilly;Hainaut",
    "iso:country":"BE",
    "sg:address":"Chauss\u00c9e De Gilly 63",
    "sg:city":"Charleroi",
    "sg:orig_category":"Advocaten and juridische adviseurs",
    "sg:phone":"+32 71 35 11 65",
    "sg:postcode":"6040",
    "sg:province":"Hainaut",
    "wof:name":"Christian Boudelet",
    "wof:placetype":"venue"
},
  "geometry": {"coordinates":[4.4435811043,50.4418945312],"type":"Point"}
}