{
  "type": "Feature",
  "properties": {
    "addr:full":"Rue Des Lavandi\u00e8res 31 Tintigny Luxembourg 6730",
    "addr:housenumber":"31",
    "addr:postcode":"6730",
    "addr:street":"Rue Des Lavandie\u0300Res",
    "iso:country":"BE",
    "sg:address":"Rue Des Lavandi\u00e8res 31",
    "sg:city":"Tintigny",
    "sg:classifiers":[
        {
            "category":"Farming",
            "subcategory":"Farm & Veterinary Services",
            "type":"Manufacturing & Wholesale Goods"
        }
    ],
    "sg:phone":"+32 63 44 41 26",
    "sg:postcode":"6730",
    "sg:province":"Luxembourg",
    "sg:tags":[
        "agricultural",
        "contractor"
    ],
    "wof:name":"Lockman A",
    "wof:placetype":"venue"
},
  "geometry": {"coordinates":[5.5356521606,49.6714630127],"type":"Point"}
}