{
  "type": "Feature",
  "properties": {
    "addr:full":"Rue Trihette 28b Engis Li\u00e8ge 4480",
    "addr:housenumber":"28b",
    "addr:postcode":"4480",
    "addr:street":"Rue Trihette",
    "iso:country":"BE",
    "sg:address":"Rue Trihette 28b",
    "sg:city":"Engis",
    "sg:orig_category":"Plantes and fleurs Gr",
    "sg:phone":"+32 85 31 52 61",
    "sg:postcode":"4480",
    "sg:province":"Li\u00e8ge",
    "wof:name":"Fleurs Michel",
    "wof:placetype":"venue"
},
  "geometry": {"coordinates":[5.3620119095,50.5516014099],"type":"Point"}
}