{
  "type": "Feature",
  "properties": {
    "addr:full":"Kouterstraat 55 Herzele Oost-Vlaanderen 9550",
    "addr:housenumber":"55",
    "addr:postcode":"9550",
    "addr:street":"Kouterstraat;Oost-Vlaanderen",
    "iso:country":"BE",
    "sg:address":"Kouterstraat 55",
    "sg:city":"Herzele",
    "sg:classifiers":[
        {
            "category":"Home & Garden",
            "subcategory":"Carpets & Floor Coverings",
            "type":"Retail Goods"
        }
    ],
    "sg:phone":"+32 53 62 62 12",
    "sg:postcode":"9550",
    "sg:province":"Oost-Vlaanderen",
    "sg:tags":[
        "tile"
    ],
    "wof:name":"De Clippel E",
    "wof:placetype":"venue"
},
  "geometry": {"coordinates":[3.8832859993,50.8894081116],"type":"Point"}
}