{
  "type": "Feature",
  "properties": {
    "addr:full":"Place Albert-ier 13 Dinant Namur 5500",
    "addr:housenumber":"13",
    "addr:postcode":"5500",
    "addr:street":"Place Albert-Ier",
    "iso:country":"BE",
    "sg:address":"Place Albert-ier 13",
    "sg:city":"Dinant",
    "sg:classifiers":[
        {
            "category":"Restaurant",
            "type":"Food & Drink"
        }
    ],
    "sg:phone":"+32 82 22 35 07",
    "sg:postcode":"5500",
    "sg:province":"Namur",
    "sg:tags":[
        "caf\u00e9s"
    ],
    "wof:name":"Taverne Le Mambo",
    "wof:placetype":"venue"
},
  "geometry": {"coordinates":[4.9119329453,50.2604866028],"type":"Point"}
}