{
  "type": "Feature",
  "properties": {
    "addr:full":"Hellestraat 10 Deinze Oost-Vlaanderen 9800",
    "addr:housenumber":"10",
    "addr:postcode":"9800",
    "addr:street":"Hellestraat",
    "iso:country":"BE",
    "sg:address":"Hellestraat 10",
    "sg:city":"Deinze",
    "sg:classifiers":[
        {
            "category":"Arena",
            "subcategory":"Sports Club",
            "type":"Entertainment"
        }
    ],
    "sg:phone":"+32 9 386 21 87",
    "sg:postcode":"9800",
    "sg:province":"Oost-Vlaanderen",
    "sg:tags":[
        "de"
    ],
    "wof:name":"Deinse Kajakclub",
    "wof:placetype":"venue"
},
  "geometry": {"coordinates":[3.530174017,50.9863166809],"type":"Point"}
}