{
  "type": "Feature",
  "properties": {
    "addr:full":"Chauss\u00e9e De Lille 288 Mouscron Hainaut 7700",
    "addr:housenumber":"288",
    "addr:postcode":"7700",
    "addr:street":"Chausse\u0301E De Lille",
    "iso:country":"BE",
    "sg:address":"Chauss\u00e9e De Lille 288",
    "sg:city":"Mouscron",
    "sg:classifiers":[
        {
            "category":"Bakery",
            "type":"Food & Drink"
        }
    ],
    "sg:phone":"+32 56 84 25 15",
    "sg:postcode":"7700",
    "sg:province":"Hainaut",
    "sg:tags":[
        "confectioner",
        "baker"
    ],
    "wof:name":"Hexagone (l')",
    "wof:placetype":"venue"
},
  "geometry": {"coordinates":[3.1850268841,50.7505874634],"type":"Point"}
}