{
  "type": "Feature",
  "properties": {
    "iso:country":"BE",
    "sg:address":"Alfons De Vlamyncklaan 2",
    "sg:city":"Tielt",
    "sg:classifiers":[
        {
            "category":"Retail",
            "subcategory":"Animal Services",
            "type":"Services"
        }
    ],
    "sg:phone":"+32 51 40 58 49",
    "sg:postcode":"8700",
    "sg:province":"West-Vlaanderen",
    "sg:tags":[
        "grooming",
        "-",
        "dog"
    ],
    "wof:name":"Kwispel Trimsalon",
    "wof:placetype":"venue"
},
  "geometry": {"coordinates":[3.3407590389,50.9938583374],"type":"Point"}
}