{
  "type": "Feature",
  "properties": {
    "iso:country":"BE",
    "sg:address":"Laar 126",
    "sg:city":"Geel",
    "sg:orig_category":"Sportclubs Sportterreinen and installaties behalve sportcentra",
    "sg:phone":"+32 14 58 36 30",
    "sg:postcode":"2440",
    "sg:province":"Antwerpen",
    "wof:name":"S.a.v. St.-dymphna Geel",
    "wof:placetype":"venue"
},
  "geometry": {"coordinates":[5.0112128258,51.1578865051],"type":"Point"}
}