{
  "type": "Feature",
  "properties": {
    "addr:full":"Rue Des Champs Elys\u00e9es 75 Bruxelles (ixelles) Bruxelles-Capitale 1050",
    "addr:housenumber":"75",
    "addr:postcode":"1050",
    "addr:street":"Rue Des Champs Elyse\u0301Es",
    "iso:country":"BE",
    "sg:address":"Rue Des Champs Elys\u00e9es 75",
    "sg:city":"Bruxelles (ixelles)",
    "sg:classifiers":[
        {
            "category":"Shopping",
            "subcategory":"Antiques",
            "type":"Retail Goods"
        }
    ],
    "sg:phone":"+32 2 648 81 53",
    "sg:postcode":"1050",
    "sg:province":"Bruxelles-Capitale",
    "sg:tags":[
        "restoration"
    ],
    "wof:name":"Mordant Roann Sprl",
    "wof:placetype":"venue"
},
  "geometry": {"coordinates":[4.3687419891,50.8288955688],"type":"Point"}
}