{
  "type": "Feature",
  "properties": {
    "addr:full":"Place Louis Focan 3 Assesse Namur 5330",
    "addr:housenumber":"3",
    "addr:postcode":"5330",
    "addr:street":"Place Louis Focan",
    "iso:country":"BE",
    "sg:address":"Place Louis Focan 3",
    "sg:city":"Assesse",
    "sg:classifiers":[
        {
            "category":"Shopping",
            "subcategory":"Antiques",
            "type":"Retail Goods"
        }
    ],
    "sg:phone":"+32 475 48 58 37",
    "sg:postcode":"5330",
    "sg:province":"Namur",
    "wof:name":"Demin Jean-pierre",
    "wof:placetype":"venue"
},
  "geometry": {"coordinates":[5.0232830048,50.368144989],"type":"Point"}
}