{
  "type": "Feature",
  "properties": {
    "iso:country":"BE",
    "sg:address":"Industrieweg Noord 1149",
    "sg:city":"Opglabbeek",
    "sg:classifiers":[
        {
            "category":"Home & Garden",
            "subcategory":"Building Materials",
            "type":"Retail Goods"
        }
    ],
    "sg:phone":"+32 89 61 12 66",
    "sg:postcode":"3660",
    "sg:province":"Limburg",
    "sg:tags":[
        "granite",
        "stone",
        "natural",
        "marble"
    ],
    "wof:name":"Sten Steen Beeldenatelier",
    "wof:placetype":"venue"
},
  "geometry": {"coordinates":[5.5484099388,51.0391807556],"type":"Point"}
}