{
  "type": "Feature",
  "properties": {
    "addr:full":"Velddreef 18 Wingene West-Vlaanderen 8750",
    "addr:housenumber":"18",
    "addr:postcode":"8750",
    "addr:street":"Velddreef",
    "iso:country":"BE",
    "sg:address":"Velddreef 18",
    "sg:city":"Wingene",
    "sg:orig_category":"Eleveurs de bovins. Eleveurs and marchands de porcs",
    "sg:phone":"+32 51 61 16 42",
    "sg:postcode":"8750",
    "sg:province":"West-Vlaanderen",
    "wof:name":"Roger Depre",
    "wof:placetype":"venue"
},
  "geometry": {"coordinates":[3.1678640842,51.0521888733],"type":"Point"}
}