{
  "type": "Feature",
  "properties": {
    "iso:country":"BE",
    "sg:address":"Herenbergstraat 9 Box 201",
    "sg:city":"Holsbeek",
    "sg:classifiers":[
        {
            "category":"Professional",
            "subcategory":"Accounting & Tax Preparation",
            "type":"Services"
        }
    ],
    "sg:phone":"+32 16 35 30 11",
    "sg:postcode":"3220",
    "sg:province":"Vlaams-Brabant",
    "sg:tags":[
        "accountant"
    ],
    "wof:name":"Verboomen K",
    "wof:placetype":"venue"
},
  "geometry": {"coordinates":[4.7277817726,50.9095916748],"type":"Point"}
}