{
  "type": "Feature",
  "properties": {
    "iso:country":"BE",
    "sg:address":"Rue Couture 44",
    "sg:city":"Ham-sur-heure-nalinnes",
    "sg:orig_category":"M\u00e9decins and sp\u00e9cialistes",
    "sg:phone":"+32 71 21 59 00",
    "sg:postcode":"6120",
    "sg:province":"Hainaut",
    "wof:name":"Dominique Bouilliez",
    "wof:placetype":"venue"
},
  "geometry": {"coordinates":[4.4498381615,50.3267784119],"type":"Point"}
}