{
  "type": "Feature",
  "properties": {
    "addr:full":"Rue Des Conceptionnistes 3 Nivelles Brabant Wallon 1400",
    "addr:housenumber":"3",
    "addr:postcode":"1400",
    "addr:street":"Rue Des Conceptionnistes",
    "iso:country":"BE",
    "sg:address":"Rue Des Conceptionnistes 3",
    "sg:city":"Nivelles",
    "sg:orig_category":"Cliniques and h\u00f4pitaux",
    "sg:phone":"+32 67 84 06 92",
    "sg:postcode":"1400",
    "sg:province":"Brabant Wallon",
    "wof:name":"Polyclinique Universitaire U.l.b-erasme-nivelles",
    "wof:placetype":"venue"
},
  "geometry": {"coordinates":[4.3262372017,50.5979995728],"type":"Point"}
}