{
  "type": "Feature",
  "properties": {
    "addr:full":"Tiensebaan 91 Bekkevoort Vlaams-Brabant 3461",
    "addr:housenumber":"91",
    "addr:postcode":"3461",
    "addr:street":"Tiensebaan",
    "iso:country":"BE",
    "sg:address":"Tiensebaan 91",
    "sg:city":"Bekkevoort",
    "sg:orig_category":"Woningbouw",
    "sg:phone":"+32 16 77 72 12",
    "sg:postcode":"3461",
    "sg:province":"Vlaams-Brabant",
    "wof:name":"De Ruyter A",
    "wof:placetype":"venue"
},
  "geometry": {"coordinates":[4.9447908401,50.9067268372],"type":"Point"}
}