{
  "type": "Feature",
  "properties": {
    "iso:country":"BE",
    "sg:address":"Oosthoekstraat 19",
    "sg:city":"Tielt",
    "sg:classifiers":[
        {
            "category":"Insurance",
            "subcategory":"Insurance Agent",
            "type":"Services"
        }
    ],
    "sg:phone":"+32 51 68 80 93",
    "sg:postcode":"8700",
    "sg:province":"West-Vlaanderen",
    "sg:tags":[
        "verzekeringsmakelaars",
        "expert"
    ],
    "wof:name":"R. Billiet",
    "wof:placetype":"venue"
},
  "geometry": {"coordinates":[3.4064979553,51.014541626],"type":"Point"}
}