{
  "type": "Feature",
  "properties": {
    "addr:full":"Square Cr\u00e9pin 16 Rochefort Namur 5580",
    "addr:housenumber":"16",
    "addr:postcode":"5580",
    "addr:street":"Square Cre\u0301Pin",
    "iso:country":"BE",
    "sg:address":"Square Cr\u00e9pin 16",
    "sg:city":"Rochefort",
    "sg:classifiers":[
        {
            "category":"Professional",
            "subcategory":"Lawyer & Legal Services",
            "type":"Services"
        }
    ],
    "sg:phone":"+32 84 21 11 83",
    "sg:postcode":"5580",
    "sg:province":"Namur",
    "wof:name":"Letecheur B\u00e9n\u00e9dicte",
    "wof:placetype":"venue"
},
  "geometry": {"coordinates":[5.2203731537,50.1578712463],"type":"Point"}
}