{
  "type": "Feature",
  "properties": {
    "addr:full":"Rue Du Try Bara 25 Lasne (ohain) Brabant Wallon 1380",
    "addr:housenumber":"25",
    "addr:postcode":"1380",
    "addr:street":"Rue Du Try Bara;Wallon",
    "iso:country":"BE",
    "sg:address":"Rue Du Try Bara 25",
    "sg:city":"Lasne (ohain)",
    "sg:classifiers":[
        {
            "category":"Shopping",
            "subcategory":"Florist",
            "type":"Retail Goods"
        }
    ],
    "sg:phone":"+32 2 375 54 74",
    "sg:postcode":"1380",
    "sg:province":"Brabant Wallon",
    "wof:name":"Tri Fleuri (le)",
    "wof:placetype":"venue"
},
  "geometry": {"coordinates":[4.4683442116,50.6996650696],"type":"Point"}
}