{
  "type": "Feature",
  "properties": {
    "addr:full":". Beyne-heusay (groot) Li\u00e8ge 4610",
    "addr:postcode":"4610",
    "addr:street":"Groot Lie\u0300Ge",
    "iso:country":"BE",
    "sg:address":".",
    "sg:city":"Beyne-heusay (groot)",
    "sg:orig_category":"Apotheken",
    "sg:phone":"+32 900 10 500",
    "sg:postcode":"4610",
    "sg:province":"Li\u00e8ge",
    "wof:name":"Apothekers Van Wacht",
    "wof:placetype":"venue"
},
  "geometry": {"coordinates":[5.6611189842,50.6181983948],"type":"Point"}
}