{
  "type": "Feature",
  "properties": {
    "addr:full":"Molendries 17 Box 2 Aalst Oost-Vlaanderen 9300",
    "addr:housenumber":"17;2",
    "addr:postcode":"9300",
    "addr:street":"Molendries;Box",
    "iso:country":"BE",
    "sg:address":"Molendries 17 Box 2",
    "sg:city":"Aalst",
    "sg:classifiers":[
        {
            "category":"Sports & Exercise",
            "subcategory":"Sports Center",
            "type":"Entertainment"
        }
    ],
    "sg:phone":"+32 53 41 96 23",
    "sg:postcode":"9300",
    "sg:province":"Oost-Vlaanderen",
    "sg:tags":[
        "holiday",
        "language"
    ],
    "wof:name":"Milagros",
    "wof:placetype":"venue"
},
  "geometry": {"coordinates":[4.0444850922,50.9414634705],"type":"Point"}
}