{
  "type": "Feature",
  "properties": {
    "addr:full":"Rue Francesco Ferrer 34 Charleroi Hainaut 6042",
    "addr:housenumber":"34",
    "addr:postcode":"6042",
    "addr:street":"Rue Francesco Ferrer;Hainaut",
    "iso:country":"BE",
    "sg:address":"Rue Francesco Ferrer 34",
    "sg:city":"Charleroi",
    "sg:orig_category":"Diverse organisaties and verenigingen",
    "sg:phone":"+32 71 31 87 43",
    "sg:postcode":"6042",
    "sg:province":"Hainaut",
    "wof:name":"Centre Rouge Brique",
    "wof:placetype":"venue"
},
  "geometry": {"coordinates":[4.4485869408,50.4319496155],"type":"Point"}
}