{
  "type": "Feature",
  "properties": {
    "addr:full":"Rue Croix-maron 98 Philippeville Namur 5600",
    "addr:housenumber":"98",
    "addr:postcode":"5600",
    "addr:street":"Rue Croix-Maron",
    "iso:country":"BE",
    "sg:address":"Rue Croix-maron 98",
    "sg:city":"Philippeville",
    "sg:orig_category":"Artsen and specialisten",
    "sg:phone":"+32 82 67 71 75",
    "sg:postcode":"5600",
    "sg:province":"Namur",
    "wof:name":"Magda Geerinck",
    "wof:placetype":"venue"
},
  "geometry": {"coordinates":[4.6916890144,50.1826438904],"type":"Point"}
}