{
  "type": "Feature",
  "properties": {
    "iso:country":"BE",
    "sg:address":"Rue Du Textile 18",
    "sg:city":"Komen-waasten/comines-warneton",
    "sg:orig_category":"Installation de menuiserie en bois and plastique",
    "sg:phone":"+32 56 55 69 60",
    "sg:postcode":"7780",
    "sg:province":"Hainaut",
    "wof:name":"Frandan Plastics Ateliers/frandan Plastics",
    "wof:placetype":"venue"
},
  "geometry": {"coordinates":[3.0195250511,50.7782669067],"type":"Point"}
}