{
  "type": "Feature",
  "properties": {
    "addr:full":"Rue De Li\u00c8ge 81ba Vis\u00c9 Li\u00e8ge 4600",
    "addr:housenumber":"81ba",
    "addr:postcode":"4600",
    "addr:street":"Rue De Lie\u0300Ge",
    "iso:country":"BE",
    "sg:address":"Rue De Li\u00c8ge 81ba",
    "sg:city":"Vis\u00c9",
    "sg:orig_category":"Travaux de pl\u00e2trage",
    "sg:phone":"+32 4 379 72 50",
    "sg:postcode":"4600",
    "sg:province":"Li\u00e8ge",
    "wof:name":"Oscar Lehenerz",
    "wof:placetype":"venue"
},
  "geometry": {"coordinates":[5.6952648163,50.7378158569],"type":"Point"}
}