{
  "type": "Feature",
  "properties": {
    "iso:country":"BE",
    "sg:address":"Chauss\u00c9e De Gand 567",
    "sg:city":"Molenbeek-saint-jean (bruxelles)",
    "sg:orig_category":"Ordinateurs and \u00e9quipement informatique. Fournitures de bureau",
    "sg:phone":"+32 2 468 23 59",
    "sg:postcode":"1080",
    "sg:province":"Bruxelles-Capitale",
    "wof:name":"Gwenpat",
    "wof:placetype":"venue"
},
  "geometry": {"coordinates":[4.3081521988,50.8599662781],"type":"Point"}
}