{
  "type": "Feature",
  "properties": {
    "addr:full":"Chauss\u00c9e D\u00b4alsemberg 156bb Braine-l\u00b4alleud Brabant Wallon 1420",
    "addr:housenumber":"156bb",
    "addr:postcode":"1420",
    "addr:street":"Chausse\u0301E D\u00b4Alsemberg;Brabant Wallon",
    "iso:country":"BE",
    "sg:address":"Chauss\u00c9e D\u00b4alsemberg 156bb",
    "sg:city":"Braine-l\u00b4alleud",
    "sg:orig_category":"Pharmaciens",
    "sg:phone":"+32 2 384 18 90",
    "sg:postcode":"1420",
    "sg:province":"Brabant Wallon",
    "wof:name":"O. Parvais",
    "wof:placetype":"venue"
},
  "geometry": {"coordinates":[4.3686280251,50.6889076233],"type":"Point"}
}