{
  "type": "Feature",
  "properties": {
    "addr:full":"Leon Bekaertlaan 7 Aalter Oost-Vlaanderen 9880",
    "addr:housenumber":"7",
    "addr:postcode":"9880",
    "addr:street":"Leon Bekaertlaan",
    "iso:country":"BE",
    "sg:address":"Leon Bekaertlaan 7",
    "sg:city":"Aalter",
    "sg:classifiers":[
        {
            "category":"Home & Garden",
            "subcategory":"Kitchen Supply",
            "type":"Retail Goods"
        }
    ],
    "sg:phone":"+32 9 375 03 39",
    "sg:postcode":"9880",
    "sg:province":"Oost-Vlaanderen",
    "sg:tags":[
        "installation"
    ],
    "wof:name":"Van De Walle Interieur Bvba",
    "wof:placetype":"venue"
},
  "geometry": {"coordinates":[3.4555220604,51.1025161743],"type":"Point"}
}