{
  "type": "Feature",
  "properties": {
    "iso:country":"BE",
    "sg:address":"Churchilllaan 254",
    "sg:city":"Schoten",
    "sg:classifiers":[
        {
            "category":"Banks & Credit Unions",
            "subcategory":"Investment Brokerage",
            "type":"Services"
        }
    ],
    "sg:phone":"+32 3 658 76 42",
    "sg:postcode":"2900",
    "sg:province":"Antwerpen",
    "sg:tags":[
        "printing",
        "ink"
    ],
    "wof:name":"Platteau Em Bvba",
    "wof:placetype":"venue"
},
  "geometry": {"coordinates":[4.4844818115,51.249912262],"type":"Point"}
}