{
  "type": "Feature",
  "properties": {
    "addr:full":"Rue De La Gare 30 Tournai (froyennes) Hainaut 7503",
    "addr:housenumber":"30",
    "addr:postcode":"7503",
    "addr:street":"Rue De La Gare",
    "iso:country":"BE",
    "sg:address":"Rue De La Gare 30",
    "sg:city":"Tournai (froyennes)",
    "sg:classifiers":[
        {
            "category":"Bars & Pubs",
            "type":"Food & Drink"
        }
    ],
    "sg:phone":"+32 69 22 39 26",
    "sg:postcode":"7503",
    "sg:province":"Hainaut",
    "wof:name":"Cafe De La Gare",
    "wof:placetype":"venue"
},
  "geometry": {"coordinates":[3.3562428951,50.6193199158],"type":"Point"}
}