{
  "type": "Feature",
  "properties": {
    "iso:country":"BE",
    "sg:address":"Rue Des Ateliers 2",
    "sg:city":"Morlanwelz",
    "sg:orig_category":"Advocaten and juridische adviseurs",
    "sg:phone":"+32 64 44 45 49",
    "sg:postcode":"7140",
    "sg:province":"Hainaut",
    "wof:name":"B. Nootebaert",
    "wof:placetype":"venue"
},
  "geometry": {"coordinates":[4.2599802017,50.4666481018],"type":"Point"}
}