{
  "type": "Feature",
  "properties": {
    "iso:country":"BE",
    "sg:address":"Leopold Ii-laan 30",
    "sg:city":"Oostende",
    "sg:orig_category":"V\u00eatements pour b\u00e9b\u00e9s and enfants",
    "sg:phone":"+32 59 80 31 30",
    "sg:postcode":"8400",
    "sg:province":"West-Vlaanderen",
    "wof:name":"Huis Minimorel",
    "wof:placetype":"venue"
},
  "geometry": {"coordinates":[2.9127409458,51.2307929993],"type":"Point"}
}