{
  "type": "Feature",
  "properties": {
    "iso:country":"BE",
    "sg:address":"Rodenbachstraat 11a",
    "sg:city":"Zwevegem",
    "sg:orig_category":"Diverse bedrijfsbeheeradviesbureaus",
    "sg:phone":"+32 56 75 88 55",
    "sg:postcode":"8550",
    "sg:province":"West-Vlaanderen",
    "wof:name":"Vandevijvere M.",
    "wof:placetype":"venue"
},
  "geometry": {"coordinates":[3.3430891037,50.811126709],"type":"Point"}
}