{
  "type": "Feature",
  "properties": {
    "iso:country":"BE",
    "sg:address":"Speteveld 13",
    "sg:city":"Herzele",
    "sg:orig_category":"Diverse producten Gh Sport- and kampeermateriaal",
    "sg:phone":"+32 53 62 11 61",
    "sg:postcode":"9550",
    "sg:province":"Oost-Vlaanderen",
    "wof:name":"De Jaeger",
    "wof:placetype":"venue"
},
  "geometry": {"coordinates":[3.8704481125,50.8994064331],"type":"Point"}
}