{
  "type": "Feature",
  "properties": {
    "iso:country":"BE",
    "sg:address":"Anjerstraat 7",
    "sg:city":"Neerpelt",
    "sg:orig_category":"Installatie van houten of kunststof schrijnwerk",
    "sg:phone":"+32 11 64 99 21",
    "sg:postcode":"3910",
    "sg:province":"Limburg",
    "wof:name":"Michel Meurs",
    "wof:placetype":"venue"
},
  "geometry": {"coordinates":[5.4547309875,51.224861145],"type":"Point"}
}