{
  "type": "Feature",
  "properties": {
    "addr:full":"Rue Du Gu\u00c9 59 Blegny Li\u00e8ge 4670",
    "addr:housenumber":"59",
    "addr:postcode":"4670",
    "addr:street":"Rue Du Gue\u0301",
    "iso:country":"BE",
    "sg:address":"Rue Du Gu\u00c9 59",
    "sg:city":"Blegny",
    "sg:orig_category":"Paramedische behandelingen",
    "sg:phone":"+32 4 387 43 19",
    "sg:postcode":"4670",
    "sg:province":"Li\u00e8ge",
    "wof:name":"L. Petit",
    "wof:placetype":"venue"
},
  "geometry": {"coordinates":[5.7325267792,50.6864242554],"type":"Point"}
}