{
  "type": "Feature",
  "properties": {
    "addr:full":"Marktstraat 46 Kortrijk (marke) West-Vlaanderen 8510",
    "addr:housenumber":"46",
    "addr:postcode":"8510",
    "addr:street":"Marktstraat",
    "iso:country":"BE",
    "sg:address":"Marktstraat 46",
    "sg:city":"Kortrijk (marke)",
    "sg:classifiers":[
        {
            "category":"Communications",
            "type":"Services"
        }
    ],
    "sg:phone":"+32 56 20 04 51",
    "sg:postcode":"8510",
    "sg:province":"West-Vlaanderen",
    "sg:tags":[
        "data"
    ],
    "wof:name":"Stouten Y",
    "wof:placetype":"venue"
},
  "geometry": {"coordinates":[3.234926939,50.8092956543],"type":"Point"}
}