{
  "type": "Feature",
  "properties": {
    "addr:full":"Droogtestraat 14 Deerlijk West-Vlaanderen 8540",
    "addr:housenumber":"14",
    "addr:postcode":"8540",
    "addr:street":"Droogtestraat",
    "iso:country":"BE",
    "sg:address":"Droogtestraat 14",
    "sg:city":"Deerlijk",
    "sg:orig_category":"Producteurs de l\u00e9gumes",
    "sg:phone":"+32 56 70 26 19",
    "sg:postcode":"8540",
    "sg:province":"West-Vlaanderen",
    "wof:name":"Eddy Caveye",
    "wof:placetype":"venue"
},
  "geometry": {"coordinates":[3.3480889797,50.8541564941],"type":"Point"}
}