{
  "type": "Feature",
  "properties": {
    "addr:full":"Kerkstraat 20 Knokke-heist West-Vlaanderen 8301",
    "addr:housenumber":"20",
    "addr:postcode":"8301",
    "addr:street":"Kerkstraat",
    "iso:country":"BE",
    "sg:address":"Kerkstraat 20",
    "sg:city":"Knokke-heist",
    "sg:orig_category":"Epiceries",
    "sg:phone":"+32 50 51 12 67",
    "sg:postcode":"8301",
    "sg:province":"West-Vlaanderen",
    "wof:name":"Yolande Van Crombrugge",
    "wof:placetype":"venue"
},
  "geometry": {"coordinates":[3.2639000416,51.3396911621],"type":"Point"}
}