{
  "type": "Feature",
  "properties": {
    "addr:full":"Beekstraat 9 Evergem Oost-Vlaanderen 9940",
    "addr:housenumber":"9",
    "addr:postcode":"9940",
    "addr:street":"Beekstraat;Oost-Vlaanderen",
    "iso:country":"BE",
    "sg:address":"Beekstraat 9",
    "sg:city":"Evergem",
    "sg:classifiers":[
        {
            "category":"Cafe",
            "type":"Food & Drink"
        }
    ],
    "sg:phone":"+32 9 357 75 08",
    "sg:postcode":"9940",
    "sg:province":"Oost-Vlaanderen",
    "sg:tags":[
        "caf\u00e9s"
    ],
    "wof:name":"Voetbalv. Wippelgem Sport",
    "wof:placetype":"venue"
},
  "geometry": {"coordinates":[3.7329359055,51.1401977539],"type":"Point"}
}