{
  "type": "Feature",
  "properties": {
    "addr:full":"Rue Godefroid 51 Namur Namur 5000",
    "addr:housenumber":"51",
    "addr:postcode":"5000",
    "addr:street":"Rue Godefroid",
    "iso:country":"BE",
    "sg:address":"Rue Godefroid 51",
    "sg:city":"Namur",
    "sg:classifiers":[
        {
            "category":"Fast Food",
            "type":"Food & Drink"
        }
    ],
    "sg:phone":"+32 81 22 55 37",
    "sg:postcode":"5000",
    "sg:province":"Namur",
    "sg:tags":[
        "\u00c0",
        "restaurants",
        "emporter",
        "restaurant"
    ],
    "wof:name":"Le Roi Des Moules",
    "wof:placetype":"venue"
},
  "geometry": {"coordinates":[4.8622617722,50.4679336548],"type":"Point"}
}