{
  "type": "Feature",
  "properties": {
    "iso:country":"BE",
    "sg:address":"Boslaan 51",
    "sg:city":"Knokke-heist (knokke)",
    "sg:classifiers":[
        {
            "category":"Arts & Performance",
            "subcategory":"Art Gallery",
            "type":"Entertainment"
        }
    ],
    "sg:phone":"+32 50 60 42 20",
    "sg:postcode":"8300",
    "sg:province":"West-Vlaanderen",
    "wof:name":"Imelda Art Gallery Nv",
    "wof:placetype":"venue"
},
  "geometry": {"coordinates":[3.315005064,51.3417053223],"type":"Point"}
}