{
  "type": "Feature",
  "properties": {
    "iso:country":"BE",
    "sg:address":"Den Bremt 45",
    "sg:city":"Herent",
    "sg:orig_category":"Binnenhuisarchitecten Installatie van houten of kunststof schrijnwerk Verlichting and huishoudartike",
    "sg:phone":"+32 16 22 98 42",
    "sg:postcode":"3020",
    "sg:province":"Vlaams-Brabant",
    "wof:name":"Maria Vanden Bosch",
    "wof:placetype":"venue"
},
  "geometry": {"coordinates":[4.6619830132,50.9040679932],"type":"Point"}
}