{
  "type": "Feature",
  "properties": {
    "addr:full":"Stationstraat 21 Oostrozebeke West-Vlaanderen 8780",
    "addr:housenumber":"21",
    "addr:postcode":"8780",
    "addr:street":"Stationstraat",
    "iso:country":"BE",
    "sg:address":"Stationstraat 21",
    "sg:city":"Oostrozebeke",
    "sg:orig_category":"Banken and kredietinstellingen",
    "sg:phone":"+32 56 67 62 60",
    "sg:postcode":"8780",
    "sg:province":"West-Vlaanderen",
    "wof:name":"Kbc",
    "wof:placetype":"venue"
},
  "geometry": {"coordinates":[3.3350510597,50.9190673828],"type":"Point"}
}