{
  "type": "Feature",
  "properties": {
    "iso:country":"BE",
    "sg:address":"Maalstraat 5",
    "sg:city":"Wevelgem",
    "sg:orig_category":"Brood, gebak and snoepgoed",
    "sg:phone":"+32 56 50 31 35",
    "sg:postcode":"8560",
    "sg:province":"West-Vlaanderen",
    "wof:name":"Jose Paret",
    "wof:placetype":"venue"
},
  "geometry": {"coordinates":[3.1567919254,50.8548431396],"type":"Point"}
}