{
  "type": "Feature",
  "properties": {
    "addr:full":"Grote Steenweg 119d Zulte (olsene) Oost-Vlaanderen 9870",
    "addr:housenumber":"119d",
    "addr:postcode":"9870",
    "addr:street":"Grote Steenweg",
    "iso:country":"BE",
    "sg:address":"Grote Steenweg 119d",
    "sg:city":"Zulte (olsene)",
    "sg:classifiers":[
        {
            "category":"Cafe",
            "type":"Food & Drink"
        }
    ],
    "sg:phone":"+32 9 388 66 59",
    "sg:postcode":"9870",
    "sg:province":"Oost-Vlaanderen",
    "sg:tags":[
        "snack-bars"
    ],
    "wof:name":"Canteclaer",
    "wof:placetype":"venue"
},
  "geometry": {"coordinates":[3.4629778862,50.9343681335],"type":"Point"}
}