{
  "type": "Feature",
  "properties": {
    "iso:country":"BE",
    "sg:address":"Nieuwstraat 5",
    "sg:city":"Westerlo",
    "sg:classifiers":[
        {
            "category":"Professional",
            "subcategory":"Lawyer & Legal Services",
            "type":"Services"
        }
    ],
    "sg:phone":"+32 14 54 13 24",
    "sg:postcode":"2260",
    "sg:province":"Antwerpen",
    "wof:name":"Van Hove W",
    "wof:placetype":"venue"
},
  "geometry": {"coordinates":[4.9153442383,51.0863609314],"type":"Point"}
}