{
  "type": "Feature",
  "properties": {
    "addr:full":"Kantienberg 9b Gent Oost-Vlaanderen 9000",
    "addr:housenumber":"9b",
    "addr:postcode":"9000",
    "addr:street":"Kantienberg;Oost-Vlaanderen",
    "iso:country":"BE",
    "sg:address":"Kantienberg 9b",
    "sg:city":"Gent",
    "sg:classifiers":[
        {
            "category":"Social Services",
            "type":"Services"
        }
    ],
    "sg:phone":"+32 9 222 30 73",
    "sg:postcode":"9000",
    "sg:province":"Oost-Vlaanderen",
    "wof:name":"Cocon (de)",
    "wof:placetype":"venue"
},
  "geometry": {"coordinates":[3.7292780876,51.0414886475],"type":"Point"}
}