{
  "type": "Feature",
  "properties": {
    "iso:country":"BE",
    "sg:address":"Les Mini\u00e8res 2",
    "sg:city":"Bouillon (sensenruth)",
    "sg:classifiers":[
        {
            "category":"Wholesale",
            "subcategory":"Beer",
            "type":"Manufacturing & Wholesale Goods"
        }
    ],
    "sg:phone":"+32 61 46 66 24",
    "sg:postcode":"6832",
    "sg:province":"Luxembourg",
    "sg:tags":[
        "ale",
        "-"
    ],
    "wof:name":"Brasserie Du Grand Enclos Sprl",
    "wof:placetype":"venue"
},
  "geometry": {"coordinates":[5.0727958679,49.8251419067],"type":"Point"}
}