{
  "type": "Feature",
  "properties": {
    "addr:full":"Rozenkranslaan 7 Genk Limburg 3600",
    "addr:housenumber":"7",
    "addr:postcode":"3600",
    "addr:street":"Rozenkranslaan",
    "iso:country":"BE",
    "sg:address":"Rozenkranslaan 7",
    "sg:city":"Genk",
    "sg:classifiers":[
        {
            "category":"Building & Trades",
            "subcategory":"Construction",
            "type":"Services"
        }
    ],
    "sg:phone":"+32 89 24 74 75",
    "sg:postcode":"3600",
    "sg:province":"Limburg",
    "sg:tags":[
        "paper",
        "hanger"
    ],
    "wof:name":"De Puydt D",
    "wof:placetype":"venue"
},
  "geometry": {"coordinates":[5.4881081581,50.9631233215],"type":"Point"}
}