{
  "type": "Feature",
  "properties": {
    "iso:country":"BE",
    "sg:address":"Rue Florent Joann\u00e8s 120",
    "sg:city":"Montegn\u00e9e",
    "sg:classifiers":[
        {
            "category":"Military Area",
            "subcategory":"Air Force Base",
            "type":"Public Place"
        }
    ],
    "sg:phone":"+32 4 233 86 52",
    "sg:postcode":"4420",
    "sg:province":"Li\u00e8ge",
    "sg:tags":[
        "prime",
        "contractor",
        "contractors"
    ],
    "wof:name":"Ets Hubert Jacobs S.p.r.l.",
    "wof:placetype":"venue"
},
  "geometry": {"coordinates":[5.5179271698,50.6265716553],"type":"Point"}
}