{
  "type": "Feature",
  "properties": {
    "addr:full":"Rue Des Hauchies 10 Gilly Hainaut 6060",
    "addr:housenumber":"10",
    "addr:postcode":"6060",
    "addr:street":"Rue Des Hauchies",
    "iso:country":"BE",
    "sg:address":"Rue Des Hauchies 10",
    "sg:city":"Gilly",
    "sg:orig_category":"Tweedehandsgoederen",
    "sg:phone":"+32 71 41 06 53",
    "sg:postcode":"6060",
    "sg:province":"Hainaut",
    "wof:name":"D\u00c9p\u00d4t Occasions",
    "wof:placetype":"venue"
},
  "geometry": {"coordinates":[4.4665288925,50.4302177429],"type":"Point"}
}