{
  "type": "Feature",
  "properties": {
    "iso:country":"BE",
    "sg:address":"Rue Des Arbal\u00e9triers 18",
    "sg:city":"Boussu",
    "sg:classifiers":[
        {
            "category":"Education",
            "subcategory":"School",
            "type":"Public Place"
        }
    ],
    "sg:phone":"+32 65 79 15 89",
    "sg:postcode":"7300",
    "sg:province":"Hainaut",
    "sg:tags":[
        "primary"
    ],
    "wof:name":"Commun. Scol.ecoles Libres",
    "wof:placetype":"venue"
},
  "geometry": {"coordinates":[3.8000700474,50.4339523315],"type":"Point"}
}