{
  "type": "Feature",
  "properties": {
    "addr:full":"Rue Du March\u00c9 1 Durbuy Luxembourg 6941",
    "addr:housenumber":"1",
    "addr:postcode":"6941",
    "addr:street":"Rue Du Marche\u0301",
    "iso:country":"BE",
    "sg:address":"Rue Du March\u00c9 1",
    "sg:city":"Durbuy",
    "sg:classifiers":[
        {
            "category":"Cafe",
            "type":"Food & Drink"
        }
    ],
    "sg:phone":"+32 86 21 00 90",
    "sg:postcode":"6941",
    "sg:province":"Luxembourg",
    "sg:tags":[
        "caf\u00e9s"
    ],
    "wof:name":"Caf\u00c9 L'escale",
    "wof:placetype":"venue"
},
  "geometry": {"coordinates":[5.524184227,50.3770332336],"type":"Point"}
}