{
  "type": "Feature",
  "properties": {
    "iso:country":"BE",
    "sg:address":"Kapellensteenweg 527",
    "sg:city":"Kalmthout",
    "sg:orig_category":"Tuinbenodigdheden",
    "sg:phone":"+32 3 666 90 38",
    "sg:postcode":"2920",
    "sg:province":"Antwerpen",
    "wof:name":"Zimmer Non Food",
    "wof:placetype":"venue"
},
  "geometry": {"coordinates":[4.4628000259,51.3590812683],"type":"Point"}
}