{
  "type": "Feature",
  "properties": {
    "iso:country":"BE",
    "sg:address":"Cuytelgem 22",
    "sg:city":"Buggenhout",
    "sg:orig_category":"Enseignement maternel and primaire",
    "sg:phone":"+32 52 33 45 64",
    "sg:postcode":"9255",
    "sg:province":"Oost-Vlaanderen",
    "wof:name":"Vrije Kleuterschool",
    "wof:placetype":"venue"
},
  "geometry": {"coordinates":[4.1930680275,51.0321655273],"type":"Point"}
}