{
  "type": "Feature",
  "properties": {
    "addr:full":"Rue Melsens 15 Bruxelles Bruxelles-Capitale 1000",
    "addr:housenumber":"15",
    "addr:postcode":"1000",
    "addr:street":"Rue Melsens",
    "iso:country":"BE",
    "sg:address":"Rue Melsens 15",
    "sg:city":"Bruxelles",
    "sg:classifiers":[
        {
            "category":"Recreation",
            "subcategory":"Dance Hall",
            "type":"Entertainment"
        }
    ],
    "sg:phone":"+32 2 513 48 64",
    "sg:postcode":"1000",
    "sg:province":"Bruxelles-Capitale",
    "sg:tags":[
        "discotheque"
    ],
    "wof:name":"Henry'bar",
    "wof:placetype":"venue"
},
  "geometry": {"coordinates":[4.3484640121,50.850566864],"type":"Point"}
}