{
  "type": "Feature",
  "properties": {
    "addr:full":"Boulevard De La Sauveniere 153 Liege Li\u00e8ge 4000",
    "addr:housenumber":"153",
    "addr:postcode":"4000",
    "addr:street":"Boulevard De La Sauveniere",
    "iso:country":"BE",
    "sg:address":"Boulevard De La Sauveniere 153",
    "sg:city":"Liege",
    "sg:orig_category":"Salles de conf\u00e9rences and de r\u00e9ceptions",
    "sg:phone":"+32 4 222 23 93",
    "sg:postcode":"4000",
    "sg:province":"Li\u00e8ge",
    "wof:name":"Caf\u00c9-restaurant L'elysee",
    "wof:placetype":"venue"
},
  "geometry": {"coordinates":[5.5688858032,50.6403808594],"type":"Point"}
}