{
  "type": "Feature",
  "properties": {
    "addr:full":"Rue Des Mini\u00c8res 3 Verviers Li\u00e8ge 4800",
    "addr:housenumber":"3",
    "addr:postcode":"4800",
    "addr:street":"Rue Des Minie\u0300Res",
    "iso:country":"BE",
    "sg:address":"Rue Des Mini\u00c8res 3",
    "sg:city":"Verviers",
    "sg:orig_category":"M\u00e9decins and sp\u00e9cialistes",
    "sg:phone":"+32 87 22 50 56",
    "sg:postcode":"4800",
    "sg:province":"Li\u00e8ge",
    "wof:name":"Jean-louis Arnould",
    "wof:placetype":"venue"
},
  "geometry": {"coordinates":[5.8582248688,50.5891952515],"type":"Point"}
}