{
  "type": "Feature",
  "properties": {
    "iso:country":"BE",
    "sg:address":"Nieuwpoortsteenweg 107",
    "sg:city":"Koksijde",
    "sg:orig_category":"Epiceries",
    "sg:phone":"+32 58 23 22 52",
    "sg:postcode":"8670",
    "sg:province":"West-Vlaanderen",
    "wof:name":"Armand Van Den Berghe",
    "wof:placetype":"venue"
},
  "geometry": {"coordinates":[2.7017390728,51.1202354431],"type":"Point"}
}