{
  "type": "Feature",
  "properties": {
    "iso:country":"BE",
    "sg:address":"Olsensesteenweg 36",
    "sg:city":"Kruishoutem",
    "sg:orig_category":"Bouwmaterialen Gh Vloer- and muurbekleding",
    "sg:phone":"+32 9 383 72 15",
    "sg:postcode":"9770",
    "sg:province":"Oost-Vlaanderen",
    "wof:name":"Superdal",
    "wof:placetype":"venue"
},
  "geometry": {"coordinates":[3.5159790516,50.9075584412],"type":"Point"}
}