{
  "type": "Feature",
  "properties": {
    "iso:country":"BE",
    "sg:address":"Bellestr 55",
    "sg:city":"Heuvelland",
    "sg:classifiers":[
        {
            "category":"Shopping",
            "subcategory":"Hobbies, Toys, & Games",
            "type":"Retail Goods"
        }
    ],
    "sg:phone":"+32 57 44 51 66",
    "sg:postcode":"8954",
    "sg:province":"West-Vlaanderen",
    "sg:tags":[
        "product",
        "miscellaneous",
        "entertainment"
    ],
    "wof:name":"Domino Nv",
    "wof:placetype":"venue"
},
  "geometry": {"coordinates":[2.743858099,50.7841796875],"type":"Point"}
}