{
  "type": "Feature",
  "properties": {
    "iso:country":"BE",
    "sg:address":"Stokrooiestraat 14",
    "sg:city":"Lummen",
    "sg:classifiers":[
        {
            "category":"Wholesale",
            "subcategory":"Chemicals & Plastics",
            "type":"Manufacturing & Wholesale Goods"
        }
    ],
    "sg:phone":"+32 13 53 14 88",
    "sg:postcode":"3560",
    "sg:province":"Limburg",
    "sg:tags":[
        "packing"
    ],
    "wof:name":"P.t.m.c. Polyplast Bvba",
    "wof:placetype":"venue"
},
  "geometry": {"coordinates":[5.2346701622,50.9704589844],"type":"Point"}
}