{
  "type": "Feature",
  "properties": {
    "addr:full":"Industriestraat 4 Eupen Li\u00e8ge 4700",
    "addr:housenumber":"4",
    "addr:postcode":"4700",
    "addr:street":"Industriestraat",
    "iso:country":"BE",
    "sg:address":"Industriestraat 4",
    "sg:city":"Eupen",
    "sg:orig_category":"Diverse bedrijfsbeheeradviesbureaus",
    "sg:phone":"+32 87 59 31 00",
    "sg:postcode":"4700",
    "sg:province":"Li\u00e8ge",
    "wof:name":"Rr Services For Office",
    "wof:placetype":"venue"
},
  "geometry": {"coordinates":[6.0098409653,50.6420211792],"type":"Point"}
}