{
  "type": "Feature",
  "properties": {
    "addr:full":"Tientjesstraat 12 Harelbeke West-Vlaanderen 8530",
    "addr:housenumber":"12",
    "addr:postcode":"8530",
    "addr:street":"Tientjesstraat",
    "iso:country":"BE",
    "sg:address":"Tientjesstraat 12",
    "sg:city":"Harelbeke",
    "sg:classifiers":[
        {
            "category":"Shopping",
            "subcategory":"Clothing, Apparel, & Fashions",
            "type":"Retail Goods"
        }
    ],
    "sg:phone":"+32 56 71 05 98",
    "sg:postcode":"8530",
    "sg:province":"West-Vlaanderen",
    "sg:tags":[
        "ondergoed",
        "lingerie"
    ],
    "wof:name":"Boetiek Cecelia",
    "wof:placetype":"venue"
},
  "geometry": {"coordinates":[3.3117990494,50.8498954773],"type":"Point"}
}