{
  "type": "Feature",
  "properties": {
    "addr:full":"Rue Fernand S\u00e9verin 49 Bruxelles (schaerbeek) Bruxelles-Capitale 1030",
    "addr:housenumber":"49",
    "addr:postcode":"1030",
    "addr:street":"Rue Fernand Se\u0301Verin",
    "iso:country":"BE",
    "sg:address":"Rue Fernand S\u00e9verin 49",
    "sg:city":"Bruxelles (schaerbeek)",
    "sg:classifiers":[
        {
            "category":"Building & Trades",
            "subcategory":"Plumbing",
            "type":"Services"
        }
    ],
    "sg:phone":"+32 2 216 54 03",
    "sg:postcode":"1030",
    "sg:province":"Bruxelles-Capitale",
    "sg:tags":[
        "contractor"
    ],
    "wof:name":"Brussels Delta Business Sprl",
    "wof:placetype":"venue"
},
  "geometry": {"coordinates":[4.3886961937,50.8757514954],"type":"Point"}
}