{
  "type": "Feature",
  "properties": {
    "iso:country":"BE",
    "sg:address":"Wagenbrugstraat 119",
    "sg:city":"Wevelgem",
    "sg:orig_category":"Installation \u00e9lectrique r\u00e9sidentielle",
    "sg:phone":"+32 56 42 42 09",
    "sg:postcode":"8560",
    "sg:province":"West-Vlaanderen",
    "wof:name":"Thierry Vanassche",
    "wof:placetype":"venue"
},
  "geometry": {"coordinates":[3.1657419205,50.847984314],"type":"Point"}
}