{
  "type": "Feature",
  "properties": {
    "addr:full":"Korenmarkt 23 Izegem West-Vlaanderen 8870",
    "addr:housenumber":"23",
    "addr:postcode":"8870",
    "addr:street":"Korenmarkt",
    "iso:country":"BE",
    "sg:address":"Korenmarkt 23",
    "sg:city":"Izegem",
    "sg:classifiers":[
        {
            "category":"Bars & Pubs",
            "type":"Food & Drink"
        }
    ],
    "sg:phone":"+32 51 30 05 75",
    "sg:postcode":"8870",
    "sg:province":"West-Vlaanderen",
    "wof:name":"Rodenbach",
    "wof:placetype":"venue"
},
  "geometry": {"coordinates":[3.2148048878,50.9199142456],"type":"Point"}
}