{
  "type": "Feature",
  "properties": {
    "iso:country":"BE",
    "sg:address":"Drieluikstraat 35",
    "sg:city":"Beernem",
    "sg:orig_category":"Paramedische behandelingen",
    "sg:phone":"+32 50 36 29 91",
    "sg:postcode":"8730",
    "sg:province":"West-Vlaanderen",
    "wof:name":"G. Louwyck",
    "wof:placetype":"venue"
},
  "geometry": {"coordinates":[3.2886469364,51.188785553],"type":"Point"}
}