{
  "type": "Feature",
  "properties": {
    "addr:full":"Avenue Victor Hugo 37ba Li\u00c8ge Li\u00e8ge 4000",
    "addr:housenumber":"37ba",
    "addr:postcode":"4000",
    "addr:street":"Avenue Victor Hugo",
    "iso:country":"BE",
    "sg:address":"Avenue Victor Hugo 37ba",
    "sg:city":"Li\u00c8ge",
    "sg:orig_category":"Artsen and specialisten",
    "sg:phone":"+32 4 226 48 27",
    "sg:postcode":"4000",
    "sg:province":"Li\u00e8ge",
    "wof:name":"Marc Thoreau",
    "wof:placetype":"venue"
},
  "geometry": {"coordinates":[5.566546917,50.6577186584],"type":"Point"}
}