{
  "type": "Feature",
  "properties": {
    "iso:country":"BE",
    "sg:address":"Hez\u00c9e 176",
    "sg:city":"Pepinster",
    "sg:orig_category":"Rundveehouders",
    "sg:phone":"+32 87 46 95 77",
    "sg:postcode":"4861",
    "sg:province":"Li\u00e8ge",
    "wof:name":"Marie-jeanne Toussaint",
    "wof:placetype":"venue"
},
  "geometry": {"coordinates":[5.7980499268,50.5916137695],"type":"Point"}
}