{
  "type": "Feature",
  "properties": {
    "addr:full":"Kasteelstraat 34-36 Willebroek (groot) Antwerpen 2830",
    "addr:housenumber":"34-36",
    "addr:postcode":"2830",
    "addr:street":"Kasteelstraat;Groot Antwerpen",
    "iso:country":"BE",
    "sg:address":"Kasteelstraat 34-36",
    "sg:city":"Willebroek (groot)",
    "sg:orig_category":"Industri\u00eble wasserijen and droogkuis",
    "sg:phone":"+32 3 886 69 11",
    "sg:postcode":"2830",
    "sg:province":"Antwerpen",
    "wof:name":"Extra",
    "wof:placetype":"venue"
},
  "geometry": {"coordinates":[4.3429718018,51.0508918762],"type":"Point"}
}