{
  "type": "Feature",
  "properties": {
    "addr:full":"Berkelaar 6 Merksplas Antwerpen 2330",
    "addr:housenumber":"6",
    "addr:postcode":"2330",
    "addr:street":"Berkelaar",
    "iso:country":"BE",
    "sg:address":"Berkelaar 6",
    "sg:city":"Merksplas",
    "sg:orig_category":"Eleveurs de bovins. Producteurs de fruits",
    "sg:phone":"+32 14 63 32 34",
    "sg:postcode":"2330",
    "sg:province":"Antwerpen",
    "wof:name":"Alfons Severeyns",
    "wof:placetype":"venue"
},
  "geometry": {"coordinates":[4.8885412216,51.3742713928],"type":"Point"}
}