{
  "type": "Feature",
  "properties": {
    "addr:full":"Rue De Bruxelles 143 Awans Li\u00e8ge 4340",
    "addr:housenumber":"143",
    "addr:postcode":"4340",
    "addr:street":"Rue De Bruxelles",
    "iso:country":"BE",
    "sg:address":"Rue De Bruxelles 143",
    "sg:city":"Awans",
    "sg:orig_category":"Rev\u00eatements de sols and murs",
    "sg:phone":"+32 4 246 39 47",
    "sg:postcode":"4340",
    "sg:province":"Li\u00e8ge",
    "wof:name":"Planet D\u00c9cor",
    "wof:placetype":"venue"
},
  "geometry": {"coordinates":[5.4821147919,50.6756210327],"type":"Point"}
}