{
  "type": "Feature",
  "properties": {
    "iso:country":"BE",
    "sg:address":"Torhoutse Steenweg 239",
    "sg:city":"Brugge (sint-andries)",
    "sg:classifiers":[
        {
            "category":"Wholesale",
            "subcategory":"Vending Machines",
            "type":"Manufacturing & Wholesale Goods"
        }
    ],
    "sg:phone":"+32 50 38 76 10",
    "sg:postcode":"8200",
    "sg:province":"West-Vlaanderen",
    "sg:tags":[
        "labeling"
    ],
    "wof:name":"Luteijn Johan",
    "wof:placetype":"venue"
},
  "geometry": {"coordinates":[3.199960947,51.1956138611],"type":"Point"}
}