{
  "type": "Feature",
  "properties": {
    "addr:full":"Avenue Des Peupliers 15 Chaudfontaine Li\u00e8ge 4053",
    "addr:housenumber":"15",
    "addr:postcode":"4053",
    "addr:street":"Avenue Des Peupliers",
    "iso:country":"BE",
    "sg:address":"Avenue Des Peupliers 15",
    "sg:city":"Chaudfontaine",
    "sg:orig_category":"Industri\u00eble and commerci\u00eble bouw Woningbouw",
    "sg:phone":"+32 4 366 11 26",
    "sg:postcode":"4053",
    "sg:province":"Li\u00e8ge",
    "wof:name":"Bel Maison",
    "wof:placetype":"venue"
},
  "geometry": {"coordinates":[5.6045970917,50.5855751038],"type":"Point"}
}