{
  "type": "Feature",
  "properties": {
    "iso:country":"BE",
    "sg:address":"Schlierbach 13",
    "sg:city":"Sankt Vith/saint-vith",
    "sg:orig_category":"Rev\u00eatements pour sols and murs. Peinture",
    "sg:phone":"+32 80 22 65 54",
    "sg:postcode":"4783",
    "sg:province":"Li\u00e8ge",
    "wof:name":"Rudi Schroeder",
    "wof:placetype":"venue"
},
  "geometry": {"coordinates":[6.1624388695,50.2378196716],"type":"Point"}
}