{
  "type": "Feature",
  "properties": {
    "iso:country":"BE",
    "sg:address":"Rue De L'argentine 140",
    "sg:city":"La Hulpe",
    "sg:orig_category":"Installatie van houten of kunststof schrijnwerk Installatie van metalen schrijnwerk Verlichting and ",
    "sg:phone":"+32 2 653 68 54",
    "sg:postcode":"1310",
    "sg:province":"Brabant Wallon",
    "wof:name":"Anc Coosemans",
    "wof:placetype":"venue"
},
  "geometry": {"coordinates":[4.4819598198,50.7310218811],"type":"Point"}
}