{
  "type": "Feature",
  "properties": {
    "addr:full":"Koninginnelaan 22 Middelkerke West-Vlaanderen 8430",
    "addr:housenumber":"22",
    "addr:postcode":"8430",
    "addr:street":"Koninginnelaan",
    "iso:country":"BE",
    "sg:address":"Koninginnelaan 22",
    "sg:city":"Middelkerke",
    "sg:classifiers":[
        {
            "category":"Health Services",
            "subcategory":"Dentist",
            "type":"Services"
        }
    ],
    "sg:phone":"+32 59 30 49 61",
    "sg:postcode":"8430",
    "sg:province":"West-Vlaanderen",
    "wof:name":"Landuyt Lieve",
    "wof:placetype":"venue"
},
  "geometry": {"coordinates":[2.8170039654,51.1872062683],"type":"Point"}
}