{
  "type": "Feature",
  "properties": {
    "iso:country":"BE",
    "sg:address":"1 Bld Anspach Place De Brouck\u00e9replein 2",
    "sg:city":"Brussels",
    "sg:classifiers":[
        {
            "category":"Banks & Credit Unions",
            "subcategory":"Bank",
            "type":"Services"
        }
    ],
    "sg:phone":"+32 2 250 17 06",
    "sg:postcode":"1000",
    "sg:province":"Bruxelles-Capitale",
    "wof:name":"Cetelem Belgium",
    "wof:placetype":"venue"
},
  "geometry": {"coordinates":[4.3522801399,50.8510665894],"type":"Point"}
}