{
  "type": "Feature",
  "properties": {
    "iso:country":"BE",
    "sg:address":"Rue De Mons 115",
    "sg:city":"Mons (ghlin)",
    "sg:classifiers":[
        {
            "category":"Health Services",
            "subcategory":"Nursing And Care Facility",
            "type":"Services"
        }
    ],
    "sg:phone":"+32 65 31 99 10",
    "sg:postcode":"7011",
    "sg:province":"Hainaut",
    "sg:tags":[
        "home"
    ],
    "wof:name":"Buys C",
    "wof:placetype":"venue"
},
  "geometry": {"coordinates":[3.8567180634,50.4755744934],"type":"Point"}
}