{
  "type": "Feature",
  "properties": {
    "addr:full":"Rue De Barisart 203 Spa Li\u00e8ge 4900",
    "addr:housenumber":"203",
    "addr:postcode":"4900",
    "addr:street":"Rue De Barisart",
    "iso:country":"BE",
    "sg:address":"Rue De Barisart 203",
    "sg:city":"Spa",
    "sg:orig_category":"Sportclubs",
    "sg:phone":"+32 87 77 50 05",
    "sg:postcode":"4900",
    "sg:province":"Li\u00e8ge",
    "wof:name":"Loups Banneux-louveign\u00c9",
    "wof:placetype":"venue"
},
  "geometry": {"coordinates":[5.8599238396,50.4853820801],"type":"Point"}
}