{
  "type": "Feature",
  "properties": {
    "iso:country":"BE",
    "sg:address":"Kleine Dries 19",
    "sg:city":"Diksmuide",
    "sg:classifiers":[
        {
            "category":"Wholesale",
            "subcategory":"Vending Machines",
            "type":"Manufacturing & Wholesale Goods"
        }
    ],
    "sg:phone":"+32 51 51 94 51",
    "sg:postcode":"8600",
    "sg:province":"West-Vlaanderen",
    "sg:tags":[
        "material",
        "-",
        "strapping"
    ],
    "wof:name":"Pacmatec",
    "wof:placetype":"venue"
},
  "geometry": {"coordinates":[2.8580789566,51.018283844],"type":"Point"}
}