{
  "type": "Feature",
  "properties": {
    "iso:country":"BE",
    "sg:address":"Antoon Catriestraat 14",
    "sg:city":"Gent",
    "sg:orig_category":"Fabrication and montage de mobilier. Installation de menuiserie en bois and plastique",
    "sg:phone":"+32 9 236 36 25",
    "sg:postcode":"9031",
    "sg:province":"Oost-Vlaanderen",
    "wof:name":"Keukeninterieur Claeys",
    "wof:placetype":"venue"
},
  "geometry": {"coordinates":[3.6630249023,51.0503692627],"type":"Point"}
}