{
  "type": "Feature",
  "properties": {
    "iso:country":"BE",
    "sg:address":"Aaishove 19",
    "sg:city":"Knokke-heist (ramskapelle)",
    "sg:classifiers":[
        {
            "category":"Freight",
            "type":"Transportation"
        }
    ],
    "sg:phone":"+32 50 51 02 95",
    "sg:postcode":"8301",
    "sg:province":"West-Vlaanderen",
    "sg:tags":[
        "-",
        "transport"
    ],
    "wof:name":"Turbotrans Bvba",
    "wof:placetype":"venue"
},
  "geometry": {"coordinates":[3.2504529953,51.3111000061],"type":"Point"}
}