{
  "type": "Feature",
  "properties": {
    "addr:full":"Rue Du Haut Donjon 2 A Leuze-en-hainaut Hainaut 7904",
    "addr:housenumber":"2 a",
    "addr:postcode":"7904",
    "addr:street":"Rue Du Haut Donjon",
    "iso:country":"BE",
    "sg:address":"Rue Du Haut Donjon 2 A",
    "sg:city":"Leuze-en-hainaut",
    "sg:orig_category":"Herstellingen and onderhoud van auto's",
    "sg:phone":"+32 65 76 76 66",
    "sg:postcode":"7904",
    "sg:province":"Hainaut",
    "wof:name":"Moulin E",
    "wof:placetype":"venue"
},
  "geometry": {"coordinates":[3.5868830681,50.5813331604],"type":"Point"}
}