{
  "type": "Feature",
  "properties": {
    "addr:full":"Rue Du Temple 57 Courcelles Hainaut 6180",
    "addr:housenumber":"57",
    "addr:postcode":"6180",
    "addr:street":"Rue Du Temple",
    "iso:country":"BE",
    "sg:address":"Rue Du Temple 57",
    "sg:city":"Courcelles",
    "sg:orig_category":"Enseignement maternel and primaire",
    "sg:phone":"+32 71 45 49 80",
    "sg:postcode":"6180",
    "sg:province":"Hainaut",
    "wof:name":"Ecole Fondamentale Libre",
    "wof:placetype":"venue"
},
  "geometry": {"coordinates":[4.3802428246,50.4560050964],"type":"Point"}
}