{
  "type": "Feature",
  "properties": {
    "addr:full":"Rue Croix Rouget 11 Aubange Luxembourg 6792",
    "addr:housenumber":"11",
    "addr:postcode":"6792",
    "addr:street":"Rue Croix Rouget",
    "iso:country":"BE",
    "sg:address":"Rue Croix Rouget 11",
    "sg:city":"Aubange",
    "sg:orig_category":"Installatie van houten of kunststof schrijnwerk",
    "sg:phone":"+32 63 38 76 77",
    "sg:postcode":"6792",
    "sg:province":"Luxembourg",
    "wof:name":"Andre Friob",
    "wof:placetype":"venue"
},
  "geometry": {"coordinates":[5.7581338882,49.5642242432],"type":"Point"}
}