{
  "type": "Feature",
  "properties": {
    "iso:country":"BE",
    "sg:address":"Rue Saint-boniface 28",
    "sg:city":"Elsene/ixelles",
    "sg:classifiers":[
        {
            "category":"Restaurant",
            "type":"Food & Drink"
        }
    ],
    "sg:phone":"+32 2 513 52 93",
    "sg:postcode":"1050",
    "sg:province":"Bruxelles-Capitale",
    "wof:name":"L'ile De Gor\u00c9e",
    "wof:placetype":"venue"
},
  "geometry": {"coordinates":[4.3639988899,50.8361206055],"type":"Point"}
}