{
  "type": "Feature",
  "properties": {
    "iso:country":"BE",
    "sg:address":"Avenue Du Parc 84",
    "sg:city":"Chaudfontaine",
    "sg:orig_category":"Software ontwikkeling and ontwerp",
    "sg:phone":"+32 4 365 02 25",
    "sg:postcode":"4053",
    "sg:province":"Li\u00e8ge",
    "wof:name":"A.t.i.l.",
    "wof:placetype":"venue"
},
  "geometry": {"coordinates":[5.6017189026,50.5857429504],"type":"Point"}
}