{
  "type": "Feature",
  "properties": {
    "iso:country":"BE",
    "sg:address":"Avenue Guy-stinglhamber 13",
    "sg:city":"Hastiere",
    "sg:classifiers":[
        {
            "category":"Personal",
            "subcategory":"Beauty Salon",
            "type":"Services"
        }
    ],
    "sg:phone":"+32 82 64 47 44",
    "sg:postcode":"5540",
    "sg:province":"Namur",
    "sg:tags":[
        "de",
        "coiffure"
    ],
    "wof:name":"Louise Borgnet",
    "wof:placetype":"venue"
},
  "geometry": {"coordinates":[4.8220701218,50.2127304077],"type":"Point"}
}