{
  "type": "Feature",
  "properties": {
    "iso:country":"BE",
    "sg:address":"Rue Henri-busch 25",
    "sg:city":"Arlon",
    "sg:orig_category":"Kunstonderwijs",
    "sg:phone":"+32 63 21 79 53",
    "sg:postcode":"6700",
    "sg:province":"Luxembourg",
    "wof:name":"Acad\u00c9mie Des Beaux-arts",
    "wof:placetype":"venue"
},
  "geometry": {"coordinates":[5.8223509789,49.6864280701],"type":"Point"}
}