{
  "type": "Feature",
  "properties": {
    "addr:full":"Rue Barth\u00c9l\u00c9my Frison 13b544 Tournai Hainaut 7500",
    "addr:housenumber":"13b544",
    "addr:postcode":"7500",
    "addr:street":"Rue Barthe\u0301Le\u0301My Frison",
    "iso:country":"BE",
    "sg:address":"Rue Barth\u00c9l\u00c9my Frison 13b544",
    "sg:city":"Tournai",
    "sg:orig_category":"Boekbinderijen and afwerking Drukkerijen and copyshops",
    "sg:phone":"+32 69 22 61 01",
    "sg:postcode":"7500",
    "sg:province":"Hainaut",
    "wof:name":"Campin 2000",
    "wof:placetype":"venue"
},
  "geometry": {"coordinates":[3.3753409386,50.6029319763],"type":"Point"}
}