{
  "type": "Feature",
  "properties": {
    "addr:full":"Steenweg 13 Asse Vlaams-Brabant 1730",
    "addr:housenumber":"13",
    "addr:postcode":"1730",
    "addr:street":"Steenweg",
    "iso:country":"BE",
    "sg:address":"Steenweg 13",
    "sg:city":"Asse",
    "sg:orig_category":"Parfumeries. Drogueries",
    "sg:phone":"+32 2 453 11 10",
    "sg:postcode":"1730",
    "sg:province":"Vlaams-Brabant",
    "wof:name":"Kruidvat",
    "wof:placetype":"venue"
},
  "geometry": {"coordinates":[4.1983752251,50.9107818604],"type":"Point"}
}