{
  "type": "Feature",
  "properties": {
    "iso:country":"BE",
    "sg:address":"Steenweg 13",
    "sg:city":"Asse",
    "sg:orig_category":"Parfumeries. Drogueries",
    "sg:phone":"+32 2 453 11 10",
    "sg:postcode":"1730",
    "sg:province":"Vlaams-Brabant",
    "wof:name":"Kruidvat",
    "wof:placetype":"venue"
},
  "geometry": {"coordinates":[4.1983752251,50.9107818604],"type":"Point"}
}