{
  "type": "Feature",
  "properties": {
    "iso:country":"BE",
    "sg:address":"Chauss\u00e9e De Ruisbroek 18",
    "sg:city":"Bruxelles (uccle)",
    "sg:classifiers":[
        {
            "category":"Arena",
            "subcategory":"Sports Club",
            "type":"Entertainment"
        }
    ],
    "sg:phone":"+32 2 376 37 79",
    "sg:postcode":"1180",
    "sg:province":"Bruxelles-Capitale",
    "wof:name":"Royal Uccle Sport Hockey-tennis",
    "wof:placetype":"venue"
},
  "geometry": {"coordinates":[4.3155708313,50.7991943359],"type":"Point"}
}