{
  "type": "Feature",
  "properties": {
    "addr:full":"Hazeputstraat 10 Lubbeek Vlaams-Brabant 3210",
    "addr:housenumber":"10",
    "addr:postcode":"3210",
    "addr:street":"Hazeputstraat",
    "iso:country":"BE",
    "sg:address":"Hazeputstraat 10",
    "sg:city":"Lubbeek",
    "sg:orig_category":"Animations diverses",
    "sg:phone":"+32 477 95 49 81",
    "sg:postcode":"3210",
    "sg:province":"Vlaams-Brabant",
    "wof:name":"Party D.j. Wim",
    "wof:placetype":"venue"
},
  "geometry": {"coordinates":[4.8399372101,50.8784179688],"type":"Point"}
}