{
  "type": "Feature",
  "properties": {
    "iso:country":"BE",
    "sg:address":"Leuvensestweg 327",
    "sg:city":"Zaventem",
    "sg:orig_category":"Herstellingen and onderhoud van auto's",
    "sg:phone":"+32 2 711 20 60",
    "sg:postcode":"1930",
    "sg:province":"Vlaams-Brabant",
    "wof:name":"Hessing Brussel",
    "wof:placetype":"venue"
},
  "geometry": {"coordinates":[4.4686098099,50.8718490601],"type":"Point"}
}