{
  "type": "Feature",
  "properties": {
    "addr:full":"Rue Devant Les Religieuses 23 Malmedy Li\u00e8ge 4960",
    "addr:housenumber":"23",
    "addr:postcode":"4960",
    "addr:street":"Rue Devant Les Religieuses",
    "iso:country":"BE",
    "sg:address":"Rue Devant Les Religieuses 23",
    "sg:city":"Malmedy",
    "sg:classifiers":[
        {
            "category":"Professional",
            "subcategory":"Testing Lab",
            "type":"Services"
        }
    ],
    "sg:phone":"+32 80 33 92 92",
    "sg:postcode":"4960",
    "sg:province":"Li\u00e8ge",
    "sg:tags":[
        "chemist"
    ],
    "wof:name":"Leriche M",
    "wof:placetype":"venue"
},
  "geometry": {"coordinates":[6.024766922,50.4256210327],"type":"Point"}
}