{
  "type": "Feature",
  "properties": {
    "addr:full":"Chauss\u00e9e D'alsemberg 740 Bruxelles (uccle) Bruxelles-Capitale 1180",
    "addr:housenumber":"740",
    "addr:postcode":"1180",
    "addr:street":"Chausse\u0301E D'Alsemberg",
    "iso:country":"BE",
    "sg:address":"Chauss\u00e9e D'alsemberg 740",
    "sg:city":"Bruxelles (uccle)",
    "sg:classifiers":[
        {
            "category":"Home & Garden",
            "subcategory":"Home Furnishings",
            "type":"Retail Goods"
        }
    ],
    "sg:phone":"+32 2 344 43 34",
    "sg:postcode":"1180",
    "sg:province":"Bruxelles-Capitale",
    "sg:tags":[
        "-",
        "bed",
        "mattress"
    ],
    "wof:name":"Tapiclub Interieur Nv",
    "wof:placetype":"venue"
},
  "geometry": {"coordinates":[4.3368020058,50.801158905],"type":"Point"}
}