{
  "type": "Feature",
  "properties": {
    "addr:full":"Dr\u00c8ve Pittoresque 64 Sint-genesius-rode/rhode-saint-genese Vlaams-Brabant 1640",
    "addr:housenumber":"64",
    "addr:postcode":"1640",
    "addr:street":"Dre\u0300Ve Pittoresque",
    "iso:country":"BE",
    "sg:address":"Dr\u00c8ve Pittoresque 64",
    "sg:city":"Sint-genesius-rode/rhode-saint-genese",
    "sg:orig_category":"M\u00e9decins and sp\u00e9cialistes",
    "sg:phone":"+32 2 358 53 73",
    "sg:postcode":"1640",
    "sg:province":"Vlaams-Brabant",
    "wof:name":"Anne Vanderborght",
    "wof:placetype":"venue"
},
  "geometry": {"coordinates":[4.3756380081,50.7703895569],"type":"Point"}
}