{
  "type": "Feature",
  "properties": {
    "iso:country":"BE",
    "sg:address":"Dr\u00c8ve Aleyde De Brabant 1",
    "sg:city":"Sint-pieters-woluwe/woluwe-saint-pierre",
    "sg:classifiers":[
        {
            "category":"Banks & Credit Unions",
            "subcategory":"Investment Brokerage",
            "type":"Services"
        }
    ],
    "sg:phone":"+32 2 771 98 52",
    "sg:postcode":"1150",
    "sg:province":"Bruxelles-Capitale",
    "sg:tags":[
        "diver",
        "juridiques",
        "assistance",
        "entreprises",
        "aux"
    ],
    "wof:name":"Philips-arthes/arthes",
    "wof:placetype":"venue"
},
  "geometry": {"coordinates":[4.4390969276,50.8247108459],"type":"Point"}
}