{
  "type": "Feature",
  "properties": {
    "addr:full":"Dorp-west 19 Lochristi Oost-Vlaanderen 9080",
    "addr:housenumber":"19",
    "addr:postcode":"9080",
    "addr:street":"Dorp-West",
    "iso:country":"BE",
    "sg:address":"Dorp-west 19",
    "sg:city":"Lochristi",
    "sg:classifiers":[
        {
            "category":"Restaurant",
            "type":"Food & Drink"
        }
    ],
    "sg:phone":"+32 9 356 68 88",
    "sg:postcode":"9080",
    "sg:province":"Oost-Vlaanderen",
    "wof:name":"Restaurant Mekong",
    "wof:placetype":"venue"
},
  "geometry": {"coordinates":[3.8321349621,51.0958786011],"type":"Point"}
}