{
  "type": "Feature",
  "properties": {
    "iso:country":"BE",
    "sg:address":"Draaiboom 19",
    "sg:city":"Oud-turnhout",
    "sg:classifiers":[
        {
            "category":"Arena",
            "subcategory":"Sports Club",
            "type":"Entertainment"
        }
    ],
    "sg:phone":"+32 14 45 31 89",
    "sg:postcode":"2360",
    "sg:province":"Antwerpen",
    "sg:tags":[
        "federation"
    ],
    "wof:name":"Koninklijke Belgische Basketball Bond Vzw",
    "wof:placetype":"venue"
},
  "geometry": {"coordinates":[4.9871058464,51.3220748901],"type":"Point"}
}