{
  "type": "Feature",
  "properties": {
    "iso:country":"BE",
    "sg:address":"Maarschalk Fochplein 16",
    "sg:city":"Leuven",
    "sg:orig_category":"Apotheken",
    "sg:phone":"+32 16 22 11 76",
    "sg:postcode":"3000",
    "sg:province":"Vlaams-Brabant",
    "wof:name":"Apoteek Van Derheyden",
    "wof:placetype":"venue"
},
  "geometry": {"coordinates":[4.7028150558,50.8790664673],"type":"Point"}
}