{
  "type": "Feature",
  "properties": {
    "addr:full":"Kerkhofstraat 50 Bocholt Limburg 3950",
    "addr:housenumber":"50",
    "addr:postcode":"3950",
    "addr:street":"Kerkhofstraat",
    "iso:country":"BE",
    "sg:address":"Kerkhofstraat 50",
    "sg:city":"Bocholt",
    "sg:orig_category":"Loodgieterij, verwarming and sanitaire installaties",
    "sg:phone":"+32 89 46 21 08",
    "sg:postcode":"3950",
    "sg:province":"Limburg",
    "wof:name":"Voortmans",
    "wof:placetype":"venue"
},
  "geometry": {"coordinates":[5.5853772163,51.1736335754],"type":"Point"}
}