{
  "type": "Feature",
  "properties": {
    "addr:full":"Roze Hoevelaan 7b16 Ukkel/uccle Bruxelles-Capitale 1180",
    "addr:housenumber":"7b16",
    "addr:postcode":"1180",
    "addr:street":"Roze Hoevelaan;/",
    "iso:country":"BE",
    "sg:address":"Roze Hoevelaan 7b16",
    "sg:city":"Ukkel/uccle",
    "sg:orig_category":"Advocaten and juridische adviseurs",
    "sg:phone":"+32 2 344 47 89",
    "sg:postcode":"1180",
    "sg:province":"Bruxelles-Capitale",
    "wof:name":"F. De Raedt",
    "wof:placetype":"venue"
},
  "geometry": {"coordinates":[4.359044075,50.8052406311],"type":"Point"}
}