{
  "type": "Feature",
  "properties": {
    "addr:full":"Rue Du M\u00c9tal 1 Sint-gillis/saint-gilles Bruxelles-Capitale 1060",
    "addr:housenumber":"1",
    "addr:postcode":"1060",
    "addr:street":"Rue Du Me\u0301Tal",
    "iso:country":"BE",
    "sg:address":"Rue Du M\u00c9tal 1",
    "sg:city":"Sint-gillis/saint-gilles",
    "sg:orig_category":"Epiceries",
    "sg:phone":"+32 2 538 59 66",
    "sg:postcode":"1060",
    "sg:province":"Bruxelles-Capitale",
    "wof:name":"Sky Line",
    "wof:placetype":"venue"
},
  "geometry": {"coordinates":[4.3483519554,50.8304405212],"type":"Point"}
}