{
  "type": "Feature",
  "properties": {
    "addr:full":"Molenstraat 24 Aalst Oost-Vlaanderen 9300",
    "addr:housenumber":"24",
    "addr:postcode":"9300",
    "addr:street":"Molenstraat",
    "iso:country":"BE",
    "sg:address":"Molenstraat 24",
    "sg:city":"Aalst",
    "sg:orig_category":"Brood, gebak and snoepgoed",
    "sg:phone":"+32 53 77 60 98",
    "sg:postcode":"9300",
    "sg:province":"Oost-Vlaanderen",
    "wof:name":"Neuhaus",
    "wof:placetype":"venue"
},
  "geometry": {"coordinates":[4.0405378342,50.9390945435],"type":"Point"}
}