{
  "type": "Feature",
  "properties": {
    "addr:full":"Oude Godstraat 110 Edegem Antwerpen 2650",
    "addr:housenumber":"110",
    "addr:postcode":"2650",
    "addr:street":"Oude Godstraat",
    "iso:country":"BE",
    "sg:address":"Oude Godstraat 110",
    "sg:city":"Edegem",
    "sg:classifiers":[
        {
            "category":"Health Services",
            "subcategory":"Nursing And Care Facility",
            "type":"Services"
        }
    ],
    "sg:phone":"+32 3 450 84 00",
    "sg:postcode":"2650",
    "sg:province":"Antwerpen",
    "sg:tags":[
        "home",
        "rest"
    ],
    "wof:name":"Immaculata (o.c.m.w.)",
    "wof:placetype":"venue"
},
  "geometry": {"coordinates":[4.4446430206,51.1617851257],"type":"Point"}
}