{
  "type": "Feature",
  "properties": {
    "addr:full":"Dongelstraat 44 Nijlen Antwerpen 2560",
    "addr:housenumber":"44",
    "addr:postcode":"2560",
    "addr:street":"Dongelstraat",
    "iso:country":"BE",
    "sg:address":"Dongelstraat 44",
    "sg:city":"Nijlen",
    "sg:orig_category":"Entretien and r\u00e9parations de voitures",
    "sg:phone":"+32 3 480 75 01",
    "sg:postcode":"2560",
    "sg:province":"Antwerpen",
    "wof:name":"Patrick Van Rossum",
    "wof:placetype":"venue"
},
  "geometry": {"coordinates":[4.6254858971,51.1366043091],"type":"Point"}
}