{
  "type": "Feature",
  "properties": {
    "iso:country":"BE",
    "sg:address":"Rue De Goz\u00c9e 706",
    "sg:city":"Montigny-le-tilleul",
    "sg:orig_category":"Maisons de repos and r\u00e9sidences",
    "sg:phone":"+32 71 29 60 13",
    "sg:postcode":"6110",
    "sg:province":"Hainaut",
    "wof:name":"Home Qui\u00c9tude",
    "wof:placetype":"venue"
},
  "geometry": {"coordinates":[4.3695549965,50.3596229553],"type":"Point"}
}