{
  "type": "Feature",
  "properties": {
    "addr:full":"Industriestraat 28 Ichtegem West-Vlaanderen 8480",
    "addr:housenumber":"28",
    "addr:postcode":"8480",
    "addr:street":"Industriestraat",
    "iso:country":"BE",
    "sg:address":"Industriestraat 28",
    "sg:city":"Ichtegem",
    "sg:classifiers":[
        {
            "category":"Professional",
            "subcategory":"Engineering",
            "type":"Services"
        }
    ],
    "sg:phone":"+32 51 58 14 91",
    "sg:postcode":"8480",
    "sg:province":"West-Vlaanderen",
    "sg:tags":[
        "workshop"
    ],
    "wof:name":"Deprez Construct Nv",
    "wof:placetype":"venue"
},
  "geometry": {"coordinates":[3.024034977,51.0988807678],"type":"Point"}
}