{
  "type": "Feature",
  "properties": {
    "addr:full":"Th. De Beckerstraat 32 Aarschot Vlaams-Brabant 3200",
    "addr:housenumber":"32",
    "addr:postcode":"3200",
    "addr:street":"Th. De Beckerstraat",
    "iso:country":"BE",
    "sg:address":"Th. De Beckerstraat 32",
    "sg:city":"Aarschot",
    "sg:classifiers":[
        {
            "category":"Shopping",
            "subcategory":"Clothing, Apparel, & Fashions",
            "type":"Retail Goods"
        }
    ],
    "sg:phone":"+32 16 56 63 75",
    "sg:postcode":"3200",
    "sg:province":"Vlaams-Brabant",
    "sg:tags":[
        "lingerie",
        "sous-v\u00eatements"
    ],
    "wof:name":"Lingerie De Winter",
    "wof:placetype":"venue"
},
  "geometry": {"coordinates":[4.8371710777,50.9852714539],"type":"Point"}
}