{
  "type": "Feature",
  "properties": {
    "iso:country":"BE",
    "sg:address":"Battelsesteenweg 449-451",
    "sg:city":"Mechelen",
    "sg:orig_category":"Non-Classified Establishments",
    "sg:phone":"+32 15 29 45 60",
    "sg:postcode":"2800",
    "sg:province":"Antwerpen",
    "wof:name":"Piscaer Nv",
    "wof:placetype":"venue"
},
  "geometry": {"coordinates":[4.4526181221,51.0363349915],"type":"Point"}
}