{
  "type": "Feature",
  "properties": {
    "addr:full":"Groeneweg 3 Zulte (olsene) Oost-Vlaanderen 9870",
    "addr:housenumber":"3",
    "addr:postcode":"9870",
    "addr:street":"Groeneweg",
    "iso:country":"BE",
    "sg:address":"Groeneweg 3",
    "sg:city":"Zulte (olsene)",
    "sg:classifiers":[
        {
            "category":"Building & Trades",
            "subcategory":"Pest Control",
            "type":"Services"
        }
    ],
    "sg:phone":"+32 9 388 52 84",
    "sg:postcode":"9870",
    "sg:province":"Oost-Vlaanderen",
    "sg:tags":[
        "painting",
        "contractor"
    ],
    "wof:name":"Delbo Schilderbedrijf Nv",
    "wof:placetype":"venue"
},
  "geometry": {"coordinates":[3.4627780914,50.9281349182],"type":"Point"}
}