{
  "type": "Feature",
  "properties": {
    "iso:country":"BE",
    "sg:address":"Rue Chauss\u00c9e 39",
    "sg:city":"Awans",
    "sg:orig_category":"Projectontwikkelaars Woningbouw",
    "sg:phone":"+32 4 257 77 77",
    "sg:postcode":"4342",
    "sg:province":"Li\u00e8ge",
    "wof:name":"Isovilla",
    "wof:placetype":"venue"
},
  "geometry": {"coordinates":[5.462220192,50.6834106445],"type":"Point"}
}