{
  "type": "Feature",
  "properties": {
    "addr:full":"Meulebeeksestraat 8 Ardooie West-Vlaanderen 8850",
    "addr:housenumber":"8",
    "addr:postcode":"8850",
    "addr:street":"Meulebeeksestraat",
    "iso:country":"BE",
    "sg:address":"Meulebeeksestraat 8",
    "sg:city":"Ardooie",
    "sg:classifiers":[
        {
            "category":"Insurance",
            "subcategory":"Insurance Agent",
            "type":"Services"
        }
    ],
    "sg:phone":"+32 51 74 70 80",
    "sg:postcode":"8850",
    "sg:province":"West-Vlaanderen",
    "sg:tags":[
        "verzekeringsmakelaars",
        "expert"
    ],
    "wof:name":"Bureau Roels",
    "wof:placetype":"venue"
},
  "geometry": {"coordinates":[3.2063798904,50.9754600525],"type":"Point"}
}