{
  "type": "Feature",
  "properties": {
    "addr:full":"Dutskouter 4 Geraardsbergen Oost-Vlaanderen 9500",
    "addr:housenumber":"4",
    "addr:postcode":"9500",
    "addr:street":"Dutskouter",
    "iso:country":"BE",
    "sg:address":"Dutskouter 4",
    "sg:city":"Geraardsbergen",
    "sg:orig_category":"Loodgieterij, verwarming and sanitaire installaties",
    "sg:phone":"+32 54 41 69 59",
    "sg:postcode":"9500",
    "sg:province":"Oost-Vlaanderen",
    "wof:name":"Maes-van Mieghem",
    "wof:placetype":"venue"
},
  "geometry": {"coordinates":[3.8843801022,50.7716445923],"type":"Point"}
}