{
  "type": "Feature",
  "properties": {
    "addr:full":"Avenue Des M\u00c9l\u00c8zes 10 Neupre Li\u00e8ge 4121",
    "addr:housenumber":"10",
    "addr:postcode":"4121",
    "addr:street":"Avenue Des Me\u0301Le\u0300Zes",
    "iso:country":"BE",
    "sg:address":"Avenue Des M\u00c9l\u00c8zes 10",
    "sg:city":"Neupre",
    "sg:orig_category":"Artsen and specialisten",
    "sg:phone":"+32 4 371 50 96",
    "sg:postcode":"4121",
    "sg:province":"Li\u00e8ge",
    "wof:name":"Olivier Gach",
    "wof:placetype":"venue"
},
  "geometry": {"coordinates":[5.4748191833,50.5462265015],"type":"Point"}
}