{
  "type": "Feature",
  "properties": {
    "addr:full":"Kouterstraat 35 Kuurne West-Vlaanderen 8520",
    "addr:housenumber":"35",
    "addr:postcode":"8520",
    "addr:street":"Kouterstraat",
    "iso:country":"BE",
    "sg:address":"Kouterstraat 35",
    "sg:city":"Kuurne",
    "sg:orig_category":"Plaatsen van vloer- and muurbekleding Schilders",
    "sg:phone":"+32 56 71 60 52",
    "sg:postcode":"8520",
    "sg:province":"West-Vlaanderen",
    "wof:name":"Johan Desnyder",
    "wof:placetype":"venue"
},
  "geometry": {"coordinates":[3.2834620476,50.8521728516],"type":"Point"}
}