{
  "type": "Feature",
  "properties": {
    "iso:country":"BE",
    "sg:address":"'t Heiken 10",
    "sg:city":"Beersel",
    "sg:orig_category":"Sportclubs",
    "sg:phone":"+32 2 380 58 53",
    "sg:postcode":"1652",
    "sg:province":"Vlaams-Brabant",
    "wof:name":"T.c. Drogenbos",
    "wof:placetype":"venue"
},
  "geometry": {"coordinates":[4.3290410042,50.7401618958],"type":"Point"}
}