{
  "type": "Feature",
  "properties": {
    "addr:full":"Industriezone 7 Borgloon 3480",
    "addr:housenumber":"7",
    "addr:postcode":"3480",
    "addr:street":"Industriezone",
    "iso:country":"BE",
    "sg:address":"Industriezone 7",
    "sg:city":"Borgloon",
    "sg:orig_category":"Travail and traitement du bois",
    "sg:phone":"+32 12 74 10 88",
    "sg:postcode":"3480",
    "wof:name":"Jamart",
    "wof:placetype":"venue"
},
  "geometry": {"coordinates":[5.3441700935,50.8012390137],"type":"Point"}
}