{
  "type": "Feature",
  "properties": {
    "iso:country":"BE",
    "sg:address":"Rue Hector Denis 30",
    "sg:city":"Charleroi (mont-sur-marchienne)",
    "sg:classifiers":[
        {
            "category":"Arts & Performance",
            "subcategory":"Music",
            "type":"Entertainment"
        }
    ],
    "sg:phone":"+32 71 43 52 40",
    "sg:postcode":"6032",
    "sg:province":"Hainaut",
    "sg:tags":[
        "freelance",
        "musician"
    ],
    "wof:name":"Kerremans L",
    "wof:placetype":"venue"
},
  "geometry": {"coordinates":[4.4071297646,50.387550354],"type":"Point"}
}