{
  "type": "Feature",
  "properties": {
    "iso:country":"BE",
    "sg:address":"Dr\u00e8ve De L'arc-en-ciel 98",
    "sg:city":"Arlon",
    "sg:classifiers":[
        {
            "category":"Park",
            "subcategory":"Municipal",
            "type":"Public Place"
        }
    ],
    "sg:phone":"+32 3 646 21 12",
    "sg:postcode":"6700",
    "sg:province":"Luxembourg",
    "sg:tags":[
        "waste-water",
        "industrial",
        "treatment"
    ],
    "wof:name":"O.c.s. Ocean Combustion Service Nv",
    "wof:placetype":"venue"
},
  "geometry": {"coordinates":[4.4406142235,51.2434616089],"type":"Point"}
}