{
  "type": "Feature",
  "properties": {
    "iso:country":"BE",
    "sg:address":"Beselarestraat 43-55",
    "sg:city":"Wervik (geluwe)",
    "sg:classifiers":[
        {
            "category":"Retail",
            "subcategory":"Auto Repair",
            "type":"Services"
        }
    ],
    "sg:phone":"+32 56 51 27 26",
    "sg:postcode":"8940",
    "sg:province":"West-Vlaanderen",
    "sg:tags":[
        "automobile-body"
    ],
    "wof:name":"Declercq H",
    "wof:placetype":"venue"
},
  "geometry": {"coordinates":[3.0440559387,50.7855262756],"type":"Point"}
}