{
  "type": "Feature",
  "properties": {
    "iso:country":"BE",
    "sg:address":"Rassel 50",
    "sg:city":"Wemmel",
    "sg:classifiers":[
        {
            "category":"Taxi",
            "type":"Transportation"
        }
    ],
    "sg:phone":"+32 2 461 25 65",
    "sg:postcode":"1780",
    "sg:province":"Vlaams-Brabant",
    "sg:tags":[
        "sp\u00e9ciaux",
        "taxis"
    ],
    "wof:name":"Limousine Michel",
    "wof:placetype":"venue"
},
  "geometry": {"coordinates":[4.2978382111,50.9094200134],"type":"Point"}
}