{
  "type": "Feature",
  "properties": {
    "iso:country":"BE",
    "sg:address":"Groenstraat 8ba",
    "sg:city":"Kortenaken",
    "sg:orig_category":"Fruitteelt",
    "sg:phone":"+32 11 58 96 88",
    "sg:postcode":"3470",
    "sg:province":"Vlaams-Brabant",
    "wof:name":"Polydoor Bullens",
    "wof:placetype":"venue"
},
  "geometry": {"coordinates":[5.0484929085,50.9095649719],"type":"Point"}
}