{
  "type": "Feature",
  "properties": {
    "addr:full":"Grote Markt 36 Lier Antwerpen 2500",
    "addr:housenumber":"36",
    "addr:postcode":"2500",
    "addr:street":"Grote Markt",
    "iso:country":"BE",
    "sg:address":"Grote Markt 36",
    "sg:city":"Lier",
    "sg:orig_category":"Banques and organismes de cr\u00e9dit",
    "sg:phone":"+32 3 480 43 53",
    "sg:postcode":"2500",
    "sg:province":"Antwerpen",
    "wof:name":"Artesia",
    "wof:placetype":"venue"
},
  "geometry": {"coordinates":[4.5686922073,51.1312522888],"type":"Point"}
}