{
  "type": "Feature",
  "properties": {
    "addr:full":"Avenue Albert Elisabeth 62 Bruxelles (woluwe-saint-lambert) Bruxelles-Capitale 1200",
    "addr:housenumber":"62",
    "addr:postcode":"1200",
    "addr:street":"Avenue Albert Elisabeth",
    "iso:country":"BE",
    "sg:address":"Avenue Albert Elisabeth 62",
    "sg:city":"Bruxelles (woluwe-saint-lambert)",
    "sg:classifiers":[
        {
            "category":"Parking",
            "subcategory":"Garage",
            "type":"Transportation"
        }
    ],
    "sg:phone":"+32 2 736 40 37",
    "sg:postcode":"1200",
    "sg:province":"Bruxelles-Capitale",
    "wof:name":"Vertige",
    "wof:placetype":"venue"
},
  "geometry": {"coordinates":[4.4030637741,50.8405036926],"type":"Point"}
}