{
  "type": "Feature",
  "properties": {
    "addr:full":"Stationsstraat 55 Waasmunster Oost-Vlaanderen 9250",
    "addr:housenumber":"55",
    "addr:postcode":"9250",
    "addr:street":"Stationsstraat",
    "iso:country":"BE",
    "sg:address":"Stationsstraat 55",
    "sg:city":"Waasmunster",
    "sg:classifiers":[
        {
            "category":"Personal",
            "subcategory":"Beauty Salon",
            "type":"Services"
        }
    ],
    "sg:phone":"+32 52 46 20 46",
    "sg:postcode":"9250",
    "sg:province":"Oost-Vlaanderen",
    "sg:tags":[
        "lady",
        "-",
        "hairdressing"
    ],
    "wof:name":"Caresse",
    "wof:placetype":"venue"
},
  "geometry": {"coordinates":[4.0966048241,51.1131286621],"type":"Point"}
}