{
  "type": "Feature",
  "properties": {
    "iso:country":"BE",
    "sg:address":"Diksmuidse Heerweg 305",
    "sg:city":"Brugge",
    "sg:orig_category":"Architectes",
    "sg:phone":"+32 50 39 48 54",
    "sg:postcode":"8200",
    "sg:province":"West-Vlaanderen",
    "wof:name":"Els Vanhaerents",
    "wof:placetype":"venue"
},
  "geometry": {"coordinates":[3.1981649399,51.1982803345],"type":"Point"}
}