{
  "type": "Feature",
  "properties": {
    "addr:full":"Rue Adolphe Rectem 100 Courcelles Hainaut 6183",
    "addr:housenumber":"100",
    "addr:postcode":"6183",
    "addr:street":"Rue Adolphe Rectem",
    "iso:country":"BE",
    "sg:address":"Rue Adolphe Rectem 100",
    "sg:city":"Courcelles",
    "sg:classifiers":[
        {
            "category":"Personal",
            "subcategory":"Beauty Salon",
            "type":"Services"
        }
    ],
    "sg:phone":"+32 71 45 07 86",
    "sg:postcode":"6183",
    "sg:province":"Hainaut",
    "sg:tags":[
        "de",
        "coiffure"
    ],
    "wof:name":"Fa. Salvaggio Nuzina",
    "wof:placetype":"venue"
},
  "geometry": {"coordinates":[4.3305897713,50.4651794434],"type":"Point"}
}