{
  "type": "Feature",
  "properties": {
    "addr:full":"Steenweg 122 Nazareth (eke) Oost-Vlaanderen 9810",
    "addr:housenumber":"122",
    "addr:postcode":"9810",
    "addr:street":"Steenweg",
    "iso:country":"BE",
    "sg:address":"Steenweg 122",
    "sg:city":"Nazareth (eke)",
    "sg:orig_category":"Non-Classified Establishments",
    "sg:phone":"+32 9 385 68 05",
    "sg:postcode":"9810",
    "sg:province":"Oost-Vlaanderen",
    "wof:name":"Topolino Kids",
    "wof:placetype":"venue"
},
  "geometry": {"coordinates":[3.6427249908,50.9593963623],"type":"Point"}
}