{
  "type": "Feature",
  "properties": {
    "addr:full":"Torhoutse Steenweg 360 Brugge West-Vlaanderen 8200",
    "addr:housenumber":"360",
    "addr:postcode":"8200",
    "addr:street":"Torhoutse Steenweg",
    "iso:country":"BE",
    "sg:address":"Torhoutse Steenweg 360",
    "sg:city":"Brugge",
    "sg:orig_category":"Avocats and conseillers juridiques",
    "sg:phone":"+32 50 39 68 82",
    "sg:postcode":"8200",
    "sg:province":"West-Vlaanderen",
    "wof:name":"Koenraad Stubbe",
    "wof:placetype":"venue"
},
  "geometry": {"coordinates":[3.1787500381,51.1733894348],"type":"Point"}
}