{
  "type": "Feature",
  "properties": {
    "iso:country":"BE",
    "sg:address":"Eenbeekstraat 44",
    "sg:city":"Destelbergen",
    "sg:classifiers":[
        {
            "category":"Communications",
            "subcategory":"Television Station",
            "type":"Services"
        }
    ],
    "sg:phone":"+32 9 229 25 45",
    "sg:postcode":"9070",
    "sg:province":"Oost-Vlaanderen",
    "sg:tags":[
        "switching",
        "panel"
    ],
    "wof:name":"Mecatex Nv",
    "wof:placetype":"venue"
},
  "geometry": {"coordinates":[3.7831940651,51.0577507019],"type":"Point"}
}