{
  "type": "Feature",
  "properties": {
    "iso:country":"BE",
    "sg:address":"Ezelstraat 120",
    "sg:city":"Brugge",
    "sg:classifiers":[
        {
            "category":"Shopping",
            "subcategory":"Clothing, Apparel, & Fashions",
            "type":"Retail Goods"
        }
    ],
    "sg:phone":"+32 50 33 75 63",
    "sg:postcode":"8000",
    "sg:province":"West-Vlaanderen",
    "sg:tags":[
        "milliner"
    ],
    "wof:name":"Baeckelandt Chapellerie",
    "wof:placetype":"venue"
},
  "geometry": {"coordinates":[3.2164781094,51.2150993347],"type":"Point"}
}