{
  "type": "Feature",
  "properties": {
    "addr:full":"Chauss\u00c9e De Mons 394 Tubize Brabant Wallon 1480",
    "addr:housenumber":"394",
    "addr:postcode":"1480",
    "addr:street":"Chausse\u0301E De Mons;Wallon",
    "iso:country":"BE",
    "sg:address":"Chauss\u00c9e De Mons 394",
    "sg:city":"Tubize",
    "sg:orig_category":"Cr\u00e9meries",
    "sg:phone":"+32 2 355 42 59",
    "sg:postcode":"1480",
    "sg:province":"Brabant Wallon",
    "wof:name":"Marcolac",
    "wof:placetype":"venue"
},
  "geometry": {"coordinates":[4.1917109489,50.6797676086],"type":"Point"}
}