{
  "type": "Feature",
  "properties": {
    "iso:country":"BE",
    "sg:address":"Molenwijk 34",
    "sg:city":"Westerlo",
    "sg:orig_category":"Entretien and r\u00e9parations de voitures",
    "sg:phone":"+32 14 54 48 26",
    "sg:postcode":"2260",
    "sg:province":"Antwerpen",
    "wof:name":"L. Daems",
    "wof:placetype":"venue"
},
  "geometry": {"coordinates":[4.9218392372,51.104637146],"type":"Point"}
}