{
  "type": "Feature",
  "properties": {
    "addr:full":"Grote Markt 34 Belgium West-Vlaanderen 8900",
    "addr:housenumber":"34",
    "addr:postcode":"8900",
    "addr:street":"Grote Markt",
    "iso:country":"BE",
    "sg:address":"Grote Markt 34",
    "sg:city":"Belgium",
    "sg:classifiers":[
        {
            "category":"Travel",
            "subcategory":"Travel Agent",
            "type":"Entertainment"
        }
    ],
    "sg:postcode":"8900",
    "sg:province":"West-Vlaanderen",
    "wof:name":"Ypres Tourist Office - In Flanders Fields",
    "wof:placetype":"venue"
},
  "geometry": {"coordinates":[2.8872299194,50.8515586853],"type":"Point"}
}