{
  "type": "Feature",
  "properties": {
    "addr:full":"Ch. De Wavre 1543 Oudergem/auderghem Bruxelles-Capitale 1160",
    "addr:postcode":"1543;1160",
    "addr:street":"Ch. De Wavre",
    "iso:country":"BE",
    "sg:address":"Ch. De Wavre 1543",
    "sg:city":"Oudergem/auderghem",
    "sg:orig_category":"Ordinateurs and \u00e9quipement informatique",
    "sg:phone":"+32 2 662 22 00",
    "sg:postcode":"1160",
    "sg:province":"Bruxelles-Capitale",
    "wof:name":"Tang",
    "wof:placetype":"venue"
},
  "geometry": {"coordinates":[4.4182009697,50.8180084229],"type":"Point"}
}