{
  "type": "Feature",
  "properties": {
    "addr:full":"Gasthuisstraat 31 Aarschot Vlaams-Brabant 3200",
    "addr:housenumber":"31",
    "addr:postcode":"3200",
    "addr:street":"Gasthuisstraat",
    "iso:country":"BE",
    "sg:address":"Gasthuisstraat 31",
    "sg:city":"Aarschot",
    "sg:orig_category":"Apotheken",
    "sg:phone":"+32 16 56 60 98",
    "sg:postcode":"3200",
    "sg:province":"Vlaams-Brabant",
    "wof:name":"Peeters",
    "wof:placetype":"venue"
},
  "geometry": {"coordinates":[4.8398518562,50.9876708984],"type":"Point"}
}