{
  "type": "Feature",
  "properties": {
    "addr:full":"Rue Gr\u00e9goire Wincqz 201 Soignies Hainaut 7060",
    "addr:housenumber":"201",
    "addr:postcode":"7060",
    "addr:street":"Rue Gre\u0301Goire Wincqz",
    "iso:country":"BE",
    "sg:address":"Rue Gr\u00e9goire Wincqz 201",
    "sg:city":"Soignies",
    "sg:classifiers":[
        {
            "category":"Professional",
            "subcategory":"Testing Lab",
            "type":"Services"
        }
    ],
    "sg:phone":"+32 67 33 24 12",
    "sg:postcode":"7060",
    "sg:province":"Hainaut",
    "sg:tags":[
        "chemist"
    ],
    "wof:name":"Matton N",
    "wof:placetype":"venue"
},
  "geometry": {"coordinates":[4.0772042274,50.5719909668],"type":"Point"}
}