{
  "type": "Feature",
  "properties": {
    "iso:country":"BE",
    "sg:address":"Rue Franklin 4",
    "sg:city":"Bruxelles",
    "sg:classifiers":[
        {
            "category":"Food & Beverages",
            "subcategory":"Groceries & Convenience Stores",
            "type":"Retail Goods"
        }
    ],
    "sg:phone":"+32 2 733 28 86",
    "sg:postcode":"1000",
    "sg:province":"Bruxelles-Capitale",
    "sg:tags":[
        "grocer"
    ],
    "wof:name":"Euro City Shop",
    "wof:placetype":"venue"
},
  "geometry": {"coordinates":[4.3839988708,50.8443603516],"type":"Point"}
}