{
  "type": "Feature",
  "properties": {
    "iso:country":"BE",
    "sg:address":"Stationsstraat 115",
    "sg:city":"Geel",
    "sg:classifiers":[
        {
            "category":"Fast Food",
            "type":"Food & Drink"
        }
    ],
    "sg:phone":"+32 14 59 08 90",
    "sg:postcode":"2440",
    "sg:province":"Antwerpen",
    "sg:tags":[
        "fried",
        "stand",
        "potato"
    ],
    "wof:name":"Jean (bij Tony & An)",
    "wof:placetype":"venue"
},
  "geometry": {"coordinates":[4.9892091751,51.166595459],"type":"Point"}
}