{
  "type": "Feature",
  "properties": {
    "iso:country":"BE",
    "sg:address":"Vlaschaard 38",
    "sg:city":"Kortrijk",
    "sg:orig_category":"Elektrische installaties voor woningen",
    "sg:phone":"+32 56 35 81 65",
    "sg:postcode":"8501",
    "sg:province":"West-Vlaanderen",
    "wof:name":"Marcel Delaere",
    "wof:placetype":"venue"
},
  "geometry": {"coordinates":[3.2509610653,50.8409500122],"type":"Point"}
}