{
  "type": "Feature",
  "properties": {
    "iso:country":"BE",
    "sg:address":"Rue Walth\u00e8re Jamar 279",
    "sg:city":"Ans",
    "sg:classifiers":[
        {
            "category":"Utilities",
            "subcategory":"Mobile Phone",
            "type":"Services"
        }
    ],
    "sg:phone":"+32 4 224 70 01",
    "sg:postcode":"4430",
    "sg:province":"Li\u00e8ge",
    "sg:tags":[
        "access",
        "gsm",
        "-",
        "apparatus"
    ],
    "wof:name":"Bureautique S P G",
    "wof:placetype":"venue"
},
  "geometry": {"coordinates":[5.5341300964,50.6545143127],"type":"Point"}
}