{
  "type": "Feature",
  "properties": {
    "iso:country":"BE",
    "sg:address":"Riemsterweg 409",
    "sg:city":"Bilzen",
    "sg:orig_category":"Installatie van houten of kunststof schrijnwerk",
    "sg:phone":"+32 12 45 73 87",
    "sg:postcode":"3740",
    "sg:province":"Limburg",
    "wof:name":"Ferdinand Vrancken",
    "wof:placetype":"venue"
},
  "geometry": {"coordinates":[5.5292901993,50.8601989746],"type":"Point"}
}