{
  "type": "Feature",
  "properties": {
    "addr:full":"Schoterweg 263 Tessenderlo Limburg 3980",
    "addr:housenumber":"263",
    "addr:postcode":"3980",
    "addr:street":"Schoterweg",
    "iso:country":"BE",
    "sg:address":"Schoterweg 263",
    "sg:city":"Tessenderlo",
    "sg:orig_category":"Rundveehouders",
    "sg:phone":"+32 13 66 44 51",
    "sg:postcode":"3980",
    "sg:province":"Limburg",
    "wof:name":"Eric Geypens",
    "wof:placetype":"venue"
},
  "geometry": {"coordinates":[5.0284900665,51.0672798157],"type":"Point"}
}