{
  "type": "Feature",
  "properties": {
    "iso:country":"BE",
    "sg:address":"Krekelberg 29",
    "sg:city":"Stabroek",
    "sg:orig_category":"Rundveehouders",
    "sg:phone":"+32 3 664 15 91",
    "sg:postcode":"2940",
    "sg:province":"Antwerpen",
    "wof:name":"Theofiel Gabriels",
    "wof:placetype":"venue"
},
  "geometry": {"coordinates":[4.3907198906,51.3125686646],"type":"Point"}
}