{
  "type": "Feature",
  "properties": {
    "iso:country":"BE",
    "sg:address":"Industrieweg 399haven",
    "sg:city":"Antwerpen",
    "sg:classifiers":[
        {
            "category":"Bars & Pubs",
            "subcategory":"Oxygen Bar",
            "type":"Food & Drink"
        }
    ],
    "sg:phone":"+32 3 545 73 00",
    "sg:postcode":"2030",
    "sg:province":"Antwerpen",
    "sg:tags":[
        "warehouse",
        "-",
        "liquid"
    ],
    "wof:name":"Vopak Chemicals Logistics Belgium Nv",
    "wof:placetype":"venue"
},
  "geometry": {"coordinates":[4.357489109,51.2505760193],"type":"Point"}
}