{
  "type": "Feature",
  "properties": {
    "addr:full":"Rue Fraichamps 108 Li\u00c8ge Li\u00e8ge 4030",
    "addr:housenumber":"108",
    "addr:postcode":"4030",
    "addr:street":"Rue Fraichamps",
    "iso:country":"BE",
    "sg:address":"Rue Fraichamps 108",
    "sg:city":"Li\u00c8ge",
    "sg:orig_category":"Banques and organismes de cr\u00e9dit",
    "sg:phone":"+32 4 342 10 58",
    "sg:postcode":"4030",
    "sg:province":"Li\u00e8ge",
    "wof:name":"Bbl",
    "wof:placetype":"venue"
},
  "geometry": {"coordinates":[5.6046648026,50.6188240051],"type":"Point"}
}