{
  "type": "Feature",
  "properties": {
    "addr:full":"Eugeen Zetternamstraat 42 Gent Oost-Vlaanderen 9050",
    "addr:housenumber":"42",
    "addr:postcode":"9050",
    "addr:street":"Eugeen Zetternamstraat;Oost-Vlaanderen",
    "iso:country":"BE",
    "sg:address":"Eugeen Zetternamstraat 42",
    "sg:city":"Gent",
    "sg:orig_category":"Decoratieve kunst and kunstbenodigdheden",
    "sg:phone":"+32 9 230 51 85",
    "sg:postcode":"9050",
    "sg:province":"Oost-Vlaanderen",
    "wof:name":"D. Van De Meersschaut",
    "wof:placetype":"venue"
},
  "geometry": {"coordinates":[3.7518539429,51.0275039673],"type":"Point"}
}