{
  "type": "Feature",
  "properties": {
    "iso:country":"BE",
    "sg:address":"Chemin De La Guenette 6",
    "sg:city":"Nivelles",
    "sg:orig_category":"Eleveurs and marchands de porcs",
    "sg:phone":"+32 67 21 32 60",
    "sg:postcode":"1400",
    "sg:province":"Brabant Wallon",
    "wof:name":"Michel Obin",
    "wof:placetype":"venue"
},
  "geometry": {"coordinates":[4.3145341873,50.5757255554],"type":"Point"}
}