{
  "type": "Feature",
  "properties": {
    "iso:country":"BE",
    "sg:address":"Poelvoorde 1",
    "sg:city":"Wingene",
    "sg:orig_category":"Eleveurs de bovins. Eleveurs and marchands de porcs",
    "sg:phone":"+32 51 65 70 83",
    "sg:postcode":"8750",
    "sg:province":"West-Vlaanderen",
    "wof:name":"Marnix Hoorne",
    "wof:placetype":"venue"
},
  "geometry": {"coordinates":[3.3082299232,51.0497627258],"type":"Point"}
}