{
  "type": "Feature",
  "properties": {
    "iso:country":"BE",
    "sg:address":"Kortrijksestraat 159",
    "sg:city":"Kuurne",
    "sg:orig_category":"Gases, Medical",
    "sg:phone":"+32 2 257 08 11",
    "sg:postcode":"8520",
    "sg:province":"West-Vlaanderen",
    "wof:name":"Messer Belgium S.a.",
    "wof:placetype":"venue"
},
  "geometry": {"coordinates":[4.4375739098,50.9180488586],"type":"Point"}
}