{
  "type": "Feature",
  "properties": {
    "iso:country":"BE",
    "sg:address":"Spoorweglaan 49",
    "sg:city":"Oudenaarde",
    "sg:classifiers":[
        {
            "category":"Freight",
            "type":"Transportation"
        }
    ],
    "sg:phone":"+32 55 31 12 09",
    "sg:postcode":"9700",
    "sg:province":"Oost-Vlaanderen",
    "sg:tags":[
        "-",
        "transport"
    ],
    "wof:name":"Defraeye W Nv",
    "wof:placetype":"venue"
},
  "geometry": {"coordinates":[3.6102950573,50.827583313],"type":"Point"}
}