{
  "type": "Feature",
  "properties": {
    "addr:full":"Hovestraat 6 Edegem Antwerpen 2650",
    "addr:housenumber":"6",
    "addr:postcode":"2650",
    "addr:street":"Hovestraat",
    "iso:country":"BE",
    "sg:address":"Hovestraat 6",
    "sg:city":"Edegem",
    "sg:orig_category":"Banken and kredietinstellingen",
    "sg:phone":"+32 3 451 07 10",
    "sg:postcode":"2650",
    "sg:province":"Antwerpen",
    "wof:name":"Kbc",
    "wof:placetype":"venue"
},
  "geometry": {"coordinates":[4.445702076,51.1556167603],"type":"Point"}
}