{
  "type": "Feature",
  "properties": {
    "iso:country":"BE",
    "sg:address":"Industrielaan 27",
    "sg:city":"Torhout",
    "sg:orig_category":"Installatie van metalen schrijnwerk",
    "sg:phone":"+32 50 21 29 55",
    "sg:postcode":"8820",
    "sg:province":"West-Vlaanderen",
    "wof:name":"Tormeco",
    "wof:placetype":"venue"
},
  "geometry": {"coordinates":[3.1040360928,51.072933197],"type":"Point"}
}