{
  "type": "Feature",
  "properties": {
    "addr:full":"Eeklostraat 132b Kaprijke (lembeke) Oost-Vlaanderen 9971",
    "addr:housenumber":"132b",
    "addr:postcode":"9971",
    "addr:street":"Eeklostraat",
    "iso:country":"BE",
    "sg:address":"Eeklostraat 132b",
    "sg:city":"Kaprijke (lembeke)",
    "sg:classifiers":[
        {
            "category":"Professional",
            "subcategory":"Art Services",
            "type":"Services"
        }
    ],
    "sg:phone":"+32 9 378 00 01",
    "sg:postcode":"9971",
    "sg:province":"Oost-Vlaanderen",
    "sg:tags":[
        "interior",
        "designer"
    ],
    "wof:name":"Van Oost P",
    "wof:placetype":"venue"
},
  "geometry": {"coordinates":[3.610640049,51.1848831177],"type":"Point"}
}