{
  "type": "Feature",
  "properties": {
    "iso:country":"BE",
    "sg:address":"Koninginnelaan 75",
    "sg:city":"Oostende",
    "sg:classifiers":[
        {
            "category":"Restaurant",
            "type":"Food & Drink"
        }
    ],
    "sg:phone":"+32 59 70 32 85",
    "sg:postcode":"8400",
    "sg:province":"West-Vlaanderen",
    "sg:tags":[
        "caf\u00e9s"
    ],
    "wof:name":"Taverne Lautrec",
    "wof:placetype":"venue"
},
  "geometry": {"coordinates":[2.9086620808,51.2243041992],"type":"Point"}
}