{
  "type": "Feature",
  "properties": {
    "iso:country":"BE",
    "sg:address":"Rue De La Vausalle 3",
    "sg:city":"Angleur",
    "sg:orig_category":"Cuisines and Equipements de Cuisines. Fabrication and montage de mobilier. Meubles D\u00e9taillants, Am\u00e9n",
    "sg:phone":"+32 4 365 10 83",
    "sg:postcode":"4031",
    "sg:province":"Li\u00e8ge",
    "wof:name":"Maison Gillet-riga Sprl",
    "wof:placetype":"venue"
},
  "geometry": {"coordinates":[5.6009712219,50.6120681763],"type":"Point"}
}