{
  "type": "Feature",
  "properties": {
    "iso:country":"BE",
    "sg:address":"Avenue H. Gobert 16",
    "sg:city":"Auderghem",
    "sg:orig_category":"Diverse bedrijfsbeheeradviesbureaus",
    "sg:phone":"+32 2 660 52 87",
    "sg:postcode":"1160",
    "sg:province":"Bruxelles-Capitale",
    "wof:name":"Van Ypersele Consulting",
    "wof:placetype":"venue"
},
  "geometry": {"coordinates":[4.4299430847,50.8196601868],"type":"Point"}
}