{
  "type": "Feature",
  "properties": {
    "addr:full":"Avenue De Broqueville 92 Bruxelles (woluwe-saint-lambert) Bruxelles-Capitale 1200",
    "addr:housenumber":"92",
    "addr:postcode":"1200",
    "addr:street":"Avenue De Broqueville",
    "iso:country":"BE",
    "sg:address":"Avenue De Broqueville 92",
    "sg:city":"Bruxelles (woluwe-saint-lambert)",
    "sg:classifiers":[
        {
            "category":"Social Services",
            "subcategory":"Job Training",
            "type":"Services"
        }
    ],
    "sg:phone":"+32 2 771 02 77",
    "sg:postcode":"1200",
    "sg:province":"Bruxelles-Capitale",
    "sg:tags":[
        "interpreter"
    ],
    "wof:name":"Baudet K",
    "wof:placetype":"venue"
},
  "geometry": {"coordinates":[4.4137020111,50.8399810791],"type":"Point"}
}