{
  "type": "Feature",
  "properties": {
    "iso:country":"BE",
    "sg:address":"Avenue De Burlet 19",
    "sg:city":"Nivelles",
    "sg:orig_category":"Bloemen and planten",
    "sg:phone":"+32 67 21 54 54",
    "sg:postcode":"1400",
    "sg:province":"Brabant Wallon",
    "wof:name":"Butterfly",
    "wof:placetype":"venue"
},
  "geometry": {"coordinates":[4.3342618942,50.600227356],"type":"Point"}
}