{
  "type": "Feature",
  "properties": {
    "addr:full":"Rue Du Bosquet 7 Louvain-la-neuve Brabant Wallon 1348",
    "addr:housenumber":"7",
    "addr:postcode":"1348",
    "addr:street":"Rue Du Bosquet",
    "iso:country":"BE",
    "sg:address":"Rue Du Bosquet 7",
    "sg:city":"Louvain-la-neuve",
    "sg:classifiers":[
        {
            "category":"Landmark",
            "subcategory":"Square",
            "type":"Public Place"
        }
    ],
    "sg:phone":"+32 10 45 49 04",
    "sg:postcode":"1348",
    "sg:province":"Brabant Wallon",
    "sg:tags":[
        "ic",
        "integrated",
        "circuit"
    ],
    "wof:name":"Barco Silex S.a.",
    "wof:placetype":"venue"
},
  "geometry": {"coordinates":[4.6325969696,50.6606445312],"type":"Point"}
}