{
  "type": "Feature",
  "properties": {
    "addr:full":"Rue Des Hiercheuses 28 Charleroi Hainaut 6001",
    "addr:housenumber":"28",
    "addr:postcode":"6001",
    "addr:street":"Rue Des Hiercheuses;Hainaut",
    "iso:country":"BE",
    "sg:address":"Rue Des Hiercheuses 28",
    "sg:city":"Charleroi",
    "sg:orig_category":"Elektrische and elektronische apparatuur Gh Telecommunicatieapparaten Verlichting and huishoudartike",
    "sg:phone":"+32 71 60 06 00",
    "sg:postcode":"6001",
    "sg:province":"Hainaut",
    "wof:name":"Stylesspace",
    "wof:placetype":"venue"
},
  "geometry": {"coordinates":[4.4388999939,50.39453125],"type":"Point"}
}