{
  "type": "Feature",
  "properties": {
    "addr:full":"Nieuwpoortsesteenweg 32-34 Oostende West-Vlaanderen 8400",
    "addr:housenumber":"32-34",
    "addr:postcode":"8400",
    "addr:street":"Nieuwpoortsesteenweg",
    "iso:country":"BE",
    "sg:address":"Nieuwpoortsesteenweg 32-34",
    "sg:city":"Oostende",
    "sg:classifiers":[
        {
            "category":"Home & Garden",
            "subcategory":"Home Furnishings",
            "type":"Retail Goods"
        }
    ],
    "sg:phone":"+32 59 50 03 95",
    "sg:postcode":"8400",
    "sg:province":"West-Vlaanderen",
    "sg:tags":[
        "curtain",
        "-",
        "fixture"
    ],
    "wof:name":"Serabent Disco-luxe Bvba",
    "wof:placetype":"venue"
},
  "geometry": {"coordinates":[2.9071679115,51.2239074707],"type":"Point"}
}