{
  "type": "Feature",
  "properties": {
    "addr:full":"Rue Neuve 66 Pepinster Li\u00e8ge 4860",
    "addr:housenumber":"66",
    "addr:postcode":"4860",
    "addr:street":"Rue Neuve",
    "iso:country":"BE",
    "sg:address":"Rue Neuve 66",
    "sg:city":"Pepinster",
    "sg:classifiers":[
        {
            "category":"Retail",
            "subcategory":"Auto Repair",
            "type":"Services"
        }
    ],
    "sg:phone":"+32 87 46 02 22",
    "sg:postcode":"4860",
    "sg:province":"Li\u00e8ge",
    "sg:tags":[
        "garage"
    ],
    "wof:name":"Hubin Garage",
    "wof:placetype":"venue"
},
  "geometry": {"coordinates":[5.8036150932,50.5663795471],"type":"Point"}
}