{
  "type": "Feature",
  "properties": {
    "addr:full":"Baljuwstraat 65 Elsene/ixelles Bruxelles-Capitale 1050",
    "addr:housenumber":"65",
    "addr:postcode":"1050",
    "addr:street":"Baljuwstraat",
    "iso:country":"BE",
    "sg:address":"Baljuwstraat 65",
    "sg:city":"Elsene/ixelles",
    "sg:orig_category":"Apotheken",
    "sg:phone":"+32 2 537 03 84",
    "sg:postcode":"1050",
    "sg:province":"Bruxelles-Capitale",
    "wof:name":"Multipharma",
    "wof:placetype":"venue"
},
  "geometry": {"coordinates":[4.3603830338,50.8260726929],"type":"Point"}
}