{
  "type": "Feature",
  "properties": {
    "iso:country":"BE",
    "sg:address":"Chauss\u00e9e D'aelbeke 159",
    "sg:city":"Mouscron",
    "sg:classifiers":[
        {
            "category":"Health Services",
            "subcategory":"Health Practitioner",
            "type":"Services"
        }
    ],
    "sg:phone":"+32 56 33 46 86",
    "sg:postcode":"7700",
    "sg:province":"Hainaut",
    "sg:tags":[
        "physiotherapist"
    ],
    "wof:name":"Sturbaut Olivier",
    "wof:placetype":"venue"
},
  "geometry": {"coordinates":[3.2219181061,50.755405426],"type":"Point"}
}