{
  "type": "Feature",
  "properties": {
    "iso:country":"BE",
    "sg:address":"Route De Tamines 210",
    "sg:city":"Fosses-la-ville",
    "sg:orig_category":"Entretien and r\u00e9parations de voitures",
    "sg:phone":"+32 71 71 22 54",
    "sg:postcode":"5070",
    "sg:province":"Namur",
    "wof:name":"Garage Raymaker",
    "wof:placetype":"venue"
},
  "geometry": {"coordinates":[4.6931128502,50.4020271301],"type":"Point"}
}