{
  "type": "Feature",
  "properties": {
    "addr:full":"Rodenberg 48 Tessenderlo Limburg 3980",
    "addr:housenumber":"48",
    "addr:postcode":"3980",
    "addr:street":"Rodenberg",
    "iso:country":"BE",
    "sg:address":"Rodenberg 48",
    "sg:city":"Tessenderlo",
    "sg:orig_category":"Rundveehouders",
    "sg:phone":"+32 13 66 54 63",
    "sg:postcode":"3980",
    "sg:province":"Limburg",
    "wof:name":"Franciscus Ackx",
    "wof:placetype":"venue"
},
  "geometry": {"coordinates":[5.0758590698,51.0457763672],"type":"Point"}
}