{
  "type": "Feature",
  "properties": {
    "addr:full":"Zeelaan 21 Koksijde West-Vlaanderen 8670",
    "addr:housenumber":"21",
    "addr:postcode":"8670",
    "addr:street":"Zeelaan",
    "iso:country":"BE",
    "sg:address":"Zeelaan 21",
    "sg:city":"Koksijde",
    "sg:classifiers":[
        {
            "category":"Cafe",
            "type":"Food & Drink"
        }
    ],
    "sg:phone":"+32 58 51 17 72",
    "sg:postcode":"8670",
    "sg:province":"West-Vlaanderen",
    "sg:tags":[
        "caf\u00e9s"
    ],
    "wof:name":"Caf\u00c9 Prins Albert",
    "wof:placetype":"venue"
},
  "geometry": {"coordinates":[2.6497631073,51.1054725647],"type":"Point"}
}