{
  "type": "Feature",
  "properties": {
    "addr:full":"Muizelaarstraat 23b Pittem West-Vlaanderen 8740",
    "addr:housenumber":"23b",
    "addr:postcode":"8740",
    "addr:street":"Muizelaarstraat",
    "iso:country":"BE",
    "sg:address":"Muizelaarstraat 23b",
    "sg:city":"Pittem",
    "sg:classifiers":[
        {
            "category":"Farming",
            "subcategory":"Crops",
            "type":"Manufacturing & Wholesale Goods"
        }
    ],
    "sg:phone":"+32 51 46 65 44",
    "sg:postcode":"8740",
    "sg:province":"West-Vlaanderen",
    "sg:tags":[
        "vegetable",
        "fruit",
        "-",
        "grower"
    ],
    "wof:name":"Biesbrouck F",
    "wof:placetype":"venue"
},
  "geometry": {"coordinates":[3.2504239082,50.9735336304],"type":"Point"}
}