{
  "type": "Feature",
  "properties": {
    "addr:full":"Achterstenhoek 7 Lille (groot) Antwerpen 2275",
    "addr:housenumber":"7",
    "addr:postcode":"2275",
    "addr:street":"Achterstenhoek;Groot Antwerpen",
    "iso:country":"BE",
    "sg:address":"Achterstenhoek 7",
    "sg:city":"Lille (groot)",
    "sg:orig_category":"Elektrische installaties voor woningen",
    "sg:phone":"+32 14 88 11 98",
    "sg:postcode":"2275",
    "sg:province":"Antwerpen",
    "wof:name":"Laene K",
    "wof:placetype":"venue"
},
  "geometry": {"coordinates":[4.8126368523,51.2484474182],"type":"Point"}
}