{
  "type": "Feature",
  "properties": {
    "addr:full":"Zoning Industriel 40 Jemeppe-sur-sambre (moustier-sur-sambre) Namur 5190",
    "addr:housenumber":"40",
    "addr:postcode":"5190",
    "addr:street":"Zoning Industriel;Moustier-Sur-Sambre",
    "iso:country":"BE",
    "sg:address":"Zoning Industriel 40",
    "sg:city":"Jemeppe-sur-sambre (moustier-sur-sambre)",
    "sg:classifiers":[
        {
            "category":"Building & Trades",
            "subcategory":"Locksmith",
            "type":"Services"
        }
    ],
    "sg:phone":"+32 71 75 02 70",
    "sg:postcode":"5190",
    "sg:province":"Namur",
    "sg:tags":[
        "material",
        "road"
    ],
    "wof:name":"Remalux Sa",
    "wof:placetype":"venue"
},
  "geometry": {"coordinates":[4.6703448296,50.4645042419],"type":"Point"}
}