{
  "type": "Feature",
  "properties": {
    "iso:country":"BE",
    "sg:address":"Burgemeester Deschodtlaan 2",
    "sg:city":"Poperinge",
    "sg:classifiers":[
        {
            "category":"Health Services",
            "subcategory":"Dentist",
            "type":"Services"
        }
    ],
    "sg:phone":"+32 57 33 63 16",
    "sg:postcode":"8970",
    "sg:province":"West-Vlaanderen",
    "wof:name":"Naessens Chantal",
    "wof:placetype":"venue"
},
  "geometry": {"coordinates":[2.7416229248,50.8551292419],"type":"Point"}
}