{
  "type": "Feature",
  "properties": {
    "addr:full":"Verbindingsstraat 1c Wielsbeke West-Vlaanderen 8710",
    "addr:housenumber":"1c",
    "addr:postcode":"8710",
    "addr:street":"Verbindingsstraat",
    "iso:country":"BE",
    "sg:address":"Verbindingsstraat 1c",
    "sg:city":"Wielsbeke",
    "sg:classifiers":[
        {
            "category":"Building & Trades",
            "subcategory":"Construction",
            "type":"Services"
        }
    ],
    "sg:phone":"+32 56 66 88 10",
    "sg:postcode":"8710",
    "sg:province":"West-Vlaanderen",
    "sg:tags":[
        "installation",
        "-",
        "central",
        "heating"
    ],
    "wof:name":"Coussens Joost Bvba",
    "wof:placetype":"venue"
},
  "geometry": {"coordinates":[3.3275549412,50.9096755981],"type":"Point"}
}