{
  "type": "Feature",
  "properties": {
    "addr:full":"Moeskroensestw 53 Kortrijk West-Vlaanderen 8511",
    "addr:housenumber":"53",
    "addr:postcode":"8511",
    "addr:street":"Moeskroensestw",
    "iso:country":"BE",
    "sg:address":"Moeskroensestw 53",
    "sg:city":"Kortrijk",
    "sg:orig_category":"Medische and orthopedische apparaten",
    "sg:phone":"+32 56 41 44 99",
    "sg:postcode":"8511",
    "sg:province":"West-Vlaanderen",
    "wof:name":"La Couronnd",
    "wof:placetype":"venue"
},
  "geometry": {"coordinates":[3.2302849293,50.7784767151],"type":"Point"}
}