{
  "type": "Feature",
  "properties": {
    "iso:country":"BE",
    "sg:address":"Steenweg 176",
    "sg:city":"Denderleeuw (welle)",
    "sg:classifiers":[
        {
            "category":"Bars & Pubs",
            "type":"Food & Drink"
        }
    ],
    "sg:phone":"+32 53 68 36 26",
    "sg:postcode":"9473",
    "sg:province":"Oost-Vlaanderen",
    "sg:tags":[
        "tavern"
    ],
    "wof:name":"Arjac",
    "wof:placetype":"venue"
},
  "geometry": {"coordinates":[4.0561599731,50.8993530273],"type":"Point"}
}