{
  "type": "Feature",
  "properties": {
    "addr:full":"Ijzerenleen 22 Mechelen Antwerpen 2800",
    "addr:housenumber":"22",
    "addr:postcode":"2800",
    "addr:street":"Ijzerenleen",
    "iso:country":"BE",
    "sg:address":"Ijzerenleen 22",
    "sg:city":"Mechelen",
    "sg:orig_category":"Opticiens",
    "sg:phone":"+32 15 21 67 15",
    "sg:postcode":"2800",
    "sg:province":"Antwerpen",
    "wof:name":"Optiek De Volksmacht",
    "wof:placetype":"venue"
},
  "geometry": {"coordinates":[4.478454113,51.0270729065],"type":"Point"}
}