{
  "type": "Feature",
  "properties": {
    "iso:country":"BE",
    "sg:address":"Ronseweg 81",
    "sg:city":"Oudenaarde",
    "sg:classifiers":[
        {
            "category":"Retail",
            "subcategory":"Auto Repair",
            "type":"Services"
        }
    ],
    "sg:phone":"+32 55 31 15 22",
    "sg:postcode":"9700",
    "sg:province":"Oost-Vlaanderen",
    "sg:tags":[
        "garage"
    ],
    "wof:name":"Thomaes Bvba",
    "wof:placetype":"venue"
},
  "geometry": {"coordinates":[3.5994939804,50.8089752197],"type":"Point"}
}