{
  "type": "Feature",
  "properties": {
    "iso:country":"BE",
    "sg:address":"Staatsbaan 167",
    "sg:city":"Zulte",
    "sg:classifiers":[
        {
            "category":"Bars & Pubs",
            "type":"Food & Drink"
        }
    ],
    "sg:phone":"+32 9 388 90 10",
    "sg:postcode":"9870",
    "sg:province":"Oost-Vlaanderen",
    "wof:name":"Twins (taverne)",
    "wof:placetype":"venue"
},
  "geometry": {"coordinates":[3.4424519539,50.9206962585],"type":"Point"}
}