{
  "type": "Feature",
  "properties": {
    "addr:full":"Hogeweg 240 Stabroek Antwerpen 2940",
    "addr:housenumber":"240",
    "addr:postcode":"2940",
    "addr:street":"Hogeweg",
    "iso:country":"BE",
    "sg:address":"Hogeweg 240",
    "sg:city":"Stabroek",
    "sg:orig_category":"Kapsalons",
    "sg:phone":"+32 3 605 28 56",
    "sg:postcode":"2940",
    "sg:province":"Antwerpen",
    "wof:name":"Haar'fyn Mita",
    "wof:placetype":"venue"
},
  "geometry": {"coordinates":[4.3649148941,51.331943512],"type":"Point"}
}