{
  "type": "Feature",
  "properties": {
    "addr:full":"E 3 Plein 35 Gent (ledeberg) Oost-Vlaanderen 9050",
    "addr:housenumber":"35",
    "addr:postcode":"9050",
    "addr:street":"E 3 Plein",
    "iso:country":"BE",
    "sg:address":"E 3 Plein 35",
    "sg:city":"Gent (ledeberg)",
    "sg:classifiers":[
        {
            "category":"Insurance",
            "subcategory":"Insurance Agent",
            "type":"Services"
        }
    ],
    "sg:phone":"+32 9 231 31 44",
    "sg:postcode":"9050",
    "sg:province":"Oost-Vlaanderen",
    "sg:tags":[
        "-",
        "representative"
    ],
    "wof:name":"Dekoning E",
    "wof:placetype":"venue"
},
  "geometry": {"coordinates":[3.7589480877,51.0448532104],"type":"Point"}
}