{
  "type": "Feature",
  "properties": {
    "addr:full":"Lesbroussartstraat 121 Elsene/ixelles Bruxelles-Capitale 1050",
    "addr:housenumber":"121",
    "addr:postcode":"1050",
    "addr:street":"Lesbroussartstraat",
    "iso:country":"BE",
    "sg:address":"Lesbroussartstraat 121",
    "sg:city":"Elsene/ixelles",
    "sg:orig_category":"Kruideniers Levering aan huis restaurants",
    "sg:phone":"+32 2 647 02 79",
    "sg:postcode":"1050",
    "sg:province":"Bruxelles-Capitale",
    "wof:name":"De Nieuwe Fruithal",
    "wof:placetype":"venue"
},
  "geometry": {"coordinates":[4.3648881912,50.8276901245],"type":"Point"}
}