{
  "type": "Feature",
  "properties": {
    "addr:full":"R\u00e9sidence Marcel Carbonnelle 75 Tournai Hainaut 7500",
    "addr:housenumber":"75",
    "addr:postcode":"7500",
    "addr:street":"Carbonnelle",
    "iso:country":"BE",
    "sg:address":"R\u00e9sidence Marcel Carbonnelle 75",
    "sg:city":"Tournai",
    "sg:classifiers":[
        {
            "category":"Food & Beverages",
            "subcategory":"Groceries & Convenience Stores",
            "type":"Retail Goods"
        }
    ],
    "sg:phone":"+32 69 22 68 57",
    "sg:postcode":"7500",
    "sg:province":"Hainaut",
    "sg:tags":[
        "grocer"
    ],
    "wof:name":"Superette Carbonnelle",
    "wof:placetype":"venue"
},
  "geometry": {"coordinates":[3.3938601017,50.6131210327],"type":"Point"}
}