{
  "type": "Feature",
  "properties": {
    "addr:full":"Windmolenstraat 9 Sint-truiden (brustem) Limburg 3800",
    "addr:housenumber":"9",
    "addr:postcode":"3800",
    "addr:street":"Windmolenstraat",
    "iso:country":"BE",
    "sg:address":"Windmolenstraat 9",
    "sg:city":"Sint-truiden (brustem)",
    "sg:classifiers":[
        {
            "category":"Building & Trades",
            "subcategory":"Pest Control",
            "type":"Services"
        }
    ],
    "sg:phone":"+32 11 68 65 93",
    "sg:postcode":"3800",
    "sg:province":"Limburg",
    "sg:tags":[
        "painting",
        "contractor"
    ],
    "wof:name":"Tuts J",
    "wof:placetype":"venue"
},
  "geometry": {"coordinates":[5.2120351791,50.8033180237],"type":"Point"}
}