{
  "type": "Feature",
  "properties": {
    "addr:full":"Ringboomstraat 9 Riemst (millen) Limburg 3770",
    "addr:housenumber":"9",
    "addr:postcode":"3770",
    "addr:street":"Ringboomstraat",
    "iso:country":"BE",
    "sg:address":"Ringboomstraat 9",
    "sg:city":"Riemst (millen)",
    "sg:classifiers":[
        {
            "category":"Real Estate",
            "subcategory":"Architect",
            "type":"Services"
        }
    ],
    "sg:phone":"+32 12 23 42 41",
    "sg:postcode":"3770",
    "sg:province":"Limburg",
    "wof:name":"Coenegrachts B",
    "wof:placetype":"venue"
},
  "geometry": {"coordinates":[5.5562939644,50.7848014832],"type":"Point"}
}