{
  "type": "Feature",
  "properties": {
    "addr:full":"Arsenaalstraat 20-35 Nieuwpoort West-Vlaanderen 8620",
    "addr:housenumber":"20-35",
    "addr:postcode":"8620",
    "addr:street":"Arsenaalstraat",
    "iso:country":"BE",
    "sg:address":"Arsenaalstraat 20-35",
    "sg:city":"Nieuwpoort",
    "sg:classifiers":[
        {
            "category":"Education",
            "subcategory":"School",
            "type":"Public Place"
        }
    ],
    "sg:phone":"+32 58 23 30 19",
    "sg:postcode":"8620",
    "sg:province":"West-Vlaanderen",
    "sg:tags":[
        "secondary"
    ],
    "wof:name":"Gemeenschapsonderwijs",
    "wof:placetype":"venue"
},
  "geometry": {"coordinates":[2.7547090054,51.1312904358],"type":"Point"}
}