{
  "type": "Feature",
  "properties": {
    "addr:full":"Oudebaan 106 Korbeek-lo Vlaams-Brabant 3360",
    "addr:housenumber":"106",
    "addr:postcode":"3360",
    "addr:street":"Oudebaan",
    "iso:country":"BE",
    "sg:address":"Oudebaan 106",
    "sg:city":"Korbeek-lo",
    "sg:orig_category":"Maisons de repos and r\u00e9sidences",
    "sg:phone":"+32 16 46 39 25",
    "sg:postcode":"3360",
    "sg:province":"Vlaams-Brabant",
    "wof:name":"Ter Korbeke",
    "wof:placetype":"venue"
},
  "geometry": {"coordinates":[4.7549672127,50.8613433838],"type":"Point"}
}