{
  "type": "Feature",
  "properties": {
    "iso:country":"BE",
    "sg:address":"Marktstraat 1",
    "sg:city":"Maldegem",
    "sg:classifiers":[
        {
            "category":"Cafe",
            "type":"Food & Drink"
        }
    ],
    "sg:phone":"+32 50 71 64 45",
    "sg:postcode":"9990",
    "sg:province":"Oost-Vlaanderen",
    "sg:tags":[
        "snack-bars"
    ],
    "wof:name":"Boterhammetje ('t)",
    "wof:placetype":"venue"
},
  "geometry": {"coordinates":[3.4445559978,51.2091293335],"type":"Point"}
}