{
  "type": "Feature",
  "properties": {
    "iso:country":"BE",
    "sg:address":"Chauss\u00e9e Des Collines 102",
    "sg:city":"Wavre",
    "sg:classifiers":[
        {
            "category":"Home & Garden",
            "subcategory":"Home Furnishings",
            "type":"Retail Goods"
        }
    ],
    "sg:phone":"+32 10 24 39 11",
    "sg:postcode":"1300",
    "sg:province":"Brabant Wallon",
    "sg:tags":[
        "interior",
        "decoration"
    ],
    "wof:name":"Sc\u00e8nes D'int\u00e9rieur",
    "wof:placetype":"venue"
},
  "geometry": {"coordinates":[4.5863599777,50.7314186096],"type":"Point"}
}