{
  "type": "Feature",
  "properties": {
    "iso:country":"BE",
    "sg:address":"Charleroise Steenweg 43",
    "sg:city":"Sint-gillis/saint-gilles",
    "sg:orig_category":"Dranken",
    "sg:phone":"+32 2 534 77 03",
    "sg:postcode":"1060",
    "sg:province":"Bruxelles-Capitale",
    "wof:name":"Mig\u00b4s Wine World",
    "wof:placetype":"venue"
},
  "geometry": {"coordinates":[4.3564162254,50.8320426941],"type":"Point"}
}