{
  "type": "Feature",
  "properties": {
    "iso:country":"BE",
    "sg:address":"Verkortingstraat 17",
    "sg:city":"Gent (sint-amandsberg)",
    "sg:classifiers":[
        {
            "category":"Health Services",
            "subcategory":"Health Practitioner",
            "type":"Services"
        }
    ],
    "sg:phone":"+32 9 238 25 05",
    "sg:postcode":"9040",
    "sg:province":"Oost-Vlaanderen",
    "sg:tags":[
        "physiotherapist"
    ],
    "wof:name":"Van Trimpont Rika",
    "wof:placetype":"venue"
},
  "geometry": {"coordinates":[3.7503509521,51.0641365051],"type":"Point"}
}