{
  "type": "Feature",
  "properties": {
    "addr:full":"Galerie Des Halles 13 Ottignies-louvain-la-neuve Brabant Wallon 1348",
    "addr:housenumber":"13",
    "addr:postcode":"1348",
    "addr:street":"Galerie;Ottignies-Louvain-La-Neuve Brabant",
    "iso:country":"BE",
    "sg:address":"Galerie Des Halles 13",
    "sg:city":"Ottignies-louvain-la-neuve",
    "sg:orig_category":"Bloemen and planten",
    "sg:phone":"+32 10 45 42 55",
    "sg:postcode":"1348",
    "sg:province":"Brabant Wallon",
    "wof:name":"Le Vert Tige",
    "wof:placetype":"venue"
},
  "geometry": {"coordinates":[4.567553997,50.6661262512],"type":"Point"}
}