{
  "type": "Feature",
  "properties": {
    "iso:country":"BE",
    "sg:address":"Heuntjesstraat 43",
    "sg:city":"Anzegem",
    "sg:classifiers":[
        {
            "category":"Train Station",
            "subcategory":"Rail",
            "type":"Transportation"
        }
    ],
    "sg:phone":"+32 56 68 81 83",
    "sg:postcode":"8570",
    "sg:province":"West-Vlaanderen",
    "sg:tags":[
        "bulk",
        "good",
        "-",
        "transport"
    ],
    "wof:name":"Breyne W Bvba",
    "wof:placetype":"venue"
},
  "geometry": {"coordinates":[3.4748430252,50.8466415405],"type":"Point"}
}