{
  "type": "Feature",
  "properties": {
    "addr:full":"Markt 38 Wemmel Vlaams-Brabant 1780",
    "addr:housenumber":"38",
    "addr:postcode":"1780",
    "addr:street":"Markt;Vlaams-Brabant",
    "iso:country":"BE",
    "sg:address":"Markt 38",
    "sg:city":"Wemmel",
    "sg:classifiers":[
        {
            "category":"Shopping",
            "subcategory":"Clothing, Apparel, & Fashions",
            "type":"Retail Goods"
        }
    ],
    "sg:phone":"+32 2 460 83 80",
    "sg:postcode":"1780",
    "sg:province":"Vlaams-Brabant",
    "sg:tags":[
        "boutique"
    ],
    "wof:name":"Arrogance Boutique",
    "wof:placetype":"venue"
},
  "geometry": {"coordinates":[4.306579113,50.9103355408],"type":"Point"}
}