{
  "type": "Feature",
  "properties": {
    "iso:country":"BE",
    "sg:address":"Zuidstraat 1",
    "sg:city":"Veurne",
    "sg:classifiers":[
        {
            "category":"Restaurant",
            "type":"Food & Drink"
        }
    ],
    "sg:phone":"+32 58 31 31 10",
    "sg:postcode":"8630",
    "sg:province":"West-Vlaanderen",
    "wof:name":"De Vette Os",
    "wof:placetype":"venue"
},
  "geometry": {"coordinates":[2.6615359783,51.07188797],"type":"Point"}
}