{
  "type": "Feature",
  "properties": {
    "addr:full":"Impasse De La Pompe 1 Gembloux-sur-orneau (mazy) Namur 5032",
    "addr:housenumber":"1",
    "addr:postcode":"5032",
    "addr:street":"Impasse De La Pompe;Mazy",
    "iso:country":"BE",
    "sg:address":"Impasse De La Pompe 1",
    "sg:city":"Gembloux-sur-orneau (mazy)",
    "sg:classifiers":[
        {
            "category":"Professional",
            "subcategory":"Engineering",
            "type":"Services"
        }
    ],
    "sg:phone":"+32 81 40 39 71",
    "sg:postcode":"5032",
    "sg:province":"Namur",
    "sg:tags":[
        "-"
    ],
    "wof:name":"Gu\u00e9rin O",
    "wof:placetype":"venue"
},
  "geometry": {"coordinates":[4.6770501137,50.5190391541],"type":"Point"}
}