{
  "type": "Feature",
  "properties": {
    "addr:full":"Avenue Franklin Roosevelt 32 Box 20 Bruxelles (ixelles) Bruxelles-Capitale 1050",
    "addr:housenumber":"32 box 20",
    "addr:postcode":"1050",
    "addr:street":"Avenue Franklin Roosevelt",
    "iso:country":"BE",
    "sg:address":"Avenue Franklin Roosevelt 32 Box 20",
    "sg:city":"Bruxelles (ixelles)",
    "sg:classifiers":[
        {
            "category":"Real Estate",
            "subcategory":"Architect",
            "type":"Services"
        }
    ],
    "sg:phone":"+32 2 648 82 74",
    "sg:postcode":"1050",
    "sg:province":"Bruxelles-Capitale",
    "wof:name":"Philippe E",
    "wof:placetype":"venue"
},
  "geometry": {"coordinates":[4.3780522346,50.8138389587],"type":"Point"}
}