{
  "type": "Feature",
  "properties": {
    "addr:full":"Abdijstraat 23 Aalst (meldert) Oost-Vlaanderen 9310",
    "addr:housenumber":"23",
    "addr:postcode":"9310",
    "addr:street":"Abdijstraat",
    "iso:country":"BE",
    "sg:address":"Abdijstraat 23",
    "sg:city":"Aalst (meldert)",
    "sg:classifiers":[
        {
            "category":"Building & Trades",
            "subcategory":"Construction",
            "type":"Services"
        }
    ],
    "sg:phone":"+32 2 582 67 36",
    "sg:postcode":"9310",
    "sg:province":"Oost-Vlaanderen",
    "sg:tags":[
        "stucco",
        "contractor"
    ],
    "wof:name":"Coppens L",
    "wof:placetype":"venue"
},
  "geometry": {"coordinates":[4.1363568306,50.9209518433],"type":"Point"}
}