{
  "type": "Feature",
  "properties": {
    "iso:country":"BE",
    "sg:address":"Rue Gaston Gr\u00c9goire 49",
    "sg:city":"Amay",
    "sg:orig_category":"Architectes",
    "sg:phone":"+32 85 31 34 34",
    "sg:postcode":"4540",
    "sg:province":"Li\u00e8ge",
    "wof:name":"Houbar Paul",
    "wof:placetype":"venue"
},
  "geometry": {"coordinates":[5.3170762062,50.5496711731],"type":"Point"}
}