{
  "type": "Feature",
  "properties": {
    "iso:country":"BE",
    "sg:address":"Zeedijk 238",
    "sg:city":"Blankenberge",
    "sg:classifiers":[
        {
            "category":"Cafe",
            "type":"Food & Drink"
        }
    ],
    "sg:phone":"+32 50 42 76 09",
    "sg:postcode":"8370",
    "sg:province":"West-Vlaanderen",
    "sg:tags":[
        "snack-bars"
    ],
    "wof:name":"Hello",
    "wof:placetype":"venue"
},
  "geometry": {"coordinates":[3.140198946,51.3190727234],"type":"Point"}
}