{
  "type": "Feature",
  "properties": {
    "iso:country":"BE",
    "sg:address":"Colemontstraat 6",
    "sg:city":"Hasselt",
    "sg:orig_category":"Installation de menuiserie en bois and plastique",
    "sg:phone":"+32 11 87 20 27",
    "sg:postcode":"3511",
    "sg:province":"Limburg",
    "wof:name":"Dcsi",
    "wof:placetype":"venue"
},
  "geometry": {"coordinates":[5.2769670486,50.9738006592],"type":"Point"}
}