{
  "type": "Feature",
  "properties": {
    "addr:full":"Veertien Septemberlaan 6 Genk (waterschei) Limburg 3600",
    "addr:housenumber":"6",
    "addr:postcode":"3600",
    "addr:street":"Veertien Septemberlaan",
    "iso:country":"BE",
    "sg:address":"Veertien Septemberlaan 6",
    "sg:city":"Genk (waterschei)",
    "sg:classifiers":[
        {
            "category":"Arena",
            "subcategory":"Sports Club",
            "type":"Entertainment"
        }
    ],
    "sg:phone":"+32 89 38 55 80",
    "sg:postcode":"3600",
    "sg:province":"Limburg",
    "wof:name":"Paintball Arena Cv",
    "wof:placetype":"venue"
},
  "geometry": {"coordinates":[5.5131449699,50.9970016479],"type":"Point"}
}