{
  "type": "Feature",
  "properties": {
    "iso:country":"BE",
    "sg:address":"Antwerpsestraat 92",
    "sg:city":"Niel",
    "sg:classifiers":[
        {
            "category":"Personal",
            "subcategory":"Beauty Salon",
            "type":"Services"
        }
    ],
    "sg:phone":"+32 3 844 64 84",
    "sg:postcode":"2845",
    "sg:province":"Antwerpen",
    "wof:name":"Elegance Instituut",
    "wof:placetype":"venue"
},
  "geometry": {"coordinates":[4.3317680359,51.109828949],"type":"Point"}
}