{
  "type": "Feature",
  "properties": {
    "addr:full":"Vleminckveld 42 Antwerpen Antwerpen 2000",
    "addr:housenumber":"42",
    "addr:postcode":"2000",
    "addr:street":"Vleminckveld",
    "iso:country":"BE",
    "sg:address":"Vleminckveld 42",
    "sg:city":"Antwerpen",
    "sg:classifiers":[
        {
            "category":"Retail",
            "subcategory":"Auto Repair",
            "type":"Services"
        }
    ],
    "sg:phone":"+32 3 231 90 88",
    "sg:postcode":"2000",
    "sg:province":"Antwerpen",
    "sg:tags":[
        "garage"
    ],
    "wof:name":"Vleminckveld-ital Auto",
    "wof:placetype":"venue"
},
  "geometry": {"coordinates":[4.4033899307,51.2143325806],"type":"Point"}
}