{
  "type": "Feature",
  "properties": {
    "addr:full":"Neerwegstraat 25 Herzele Oost-Vlaanderen 9550",
    "addr:housenumber":"25",
    "addr:postcode":"9550",
    "addr:street":"Neerwegstraat;Oost-Vlaanderen",
    "iso:country":"BE",
    "sg:address":"Neerwegstraat 25",
    "sg:city":"Herzele",
    "sg:orig_category":"Woningbouw",
    "sg:phone":"+32 53 62 84 50",
    "sg:postcode":"9550",
    "sg:province":"Oost-Vlaanderen",
    "wof:name":"Lievens Bouwbedrijf",
    "wof:placetype":"venue"
},
  "geometry": {"coordinates":[3.9220340252,50.8713951111],"type":"Point"}
}