{
  "type": "Feature",
  "properties": {
    "iso:country":"BE",
    "sg:address":"Leeuwerikstraat 78",
    "sg:city":"Lokeren",
    "sg:orig_category":"Installatie van houten of kunststof schrijnwerk",
    "sg:phone":"+32 9 348 63 32",
    "sg:postcode":"9160",
    "sg:province":"Oost-Vlaanderen",
    "wof:name":"Daniel Hubrecht",
    "wof:placetype":"venue"
},
  "geometry": {"coordinates":[4.012029171,51.1119232178],"type":"Point"}
}