{
  "type": "Feature",
  "properties": {
    "addr:full":"Brugstraat 35 Wichelen Oost-Vlaanderen 9260",
    "addr:housenumber":"35",
    "addr:postcode":"9260",
    "addr:street":"Brugstraat",
    "iso:country":"BE",
    "sg:address":"Brugstraat 35",
    "sg:city":"Wichelen",
    "sg:classifiers":[
        {
            "category":"Shopping",
            "subcategory":"Bicycles & Sporting Goods",
            "type":"Retail Goods"
        }
    ],
    "sg:phone":"+32 52 42 67 64",
    "sg:postcode":"9260",
    "sg:province":"Oost-Vlaanderen",
    "sg:tags":[
        "-"
    ],
    "wof:name":"Groene 2-wieler Cie (de)",
    "wof:placetype":"venue"
},
  "geometry": {"coordinates":[3.9659590721,51.0100593567],"type":"Point"}
}