{
  "type": "Feature",
  "properties": {
    "iso:country":"BE",
    "sg:address":"Dam 1",
    "sg:city":"Ninove",
    "sg:orig_category":"Non-Classified Establishments",
    "sg:phone":"+32 54 34 19 30",
    "sg:postcode":"9400",
    "sg:province":"Oost-Vlaanderen",
    "wof:name":"Importex Belgium",
    "wof:placetype":"venue"
},
  "geometry": {"coordinates":[4.0200839043,50.8375892639],"type":"Point"}
}