{
  "type": "Feature",
  "properties": {
    "iso:country":"BE",
    "sg:address":"Rue Du Pont \u00e0 La Cambe 51",
    "sg:city":"Jodoigne (jodoigne-souveraine)",
    "sg:classifiers":[
        {
            "category":"Health Services",
            "subcategory":"Doctor",
            "type":"Services"
        }
    ],
    "sg:phone":"+32 10 81 60 49",
    "sg:postcode":"1370",
    "sg:province":"Brabant Wallon",
    "sg:tags":[
        "medicinephysicians",
        "surgeon"
    ],
    "wof:name":"Bafort Dominique",
    "wof:placetype":"venue"
},
  "geometry": {"coordinates":[4.8679351807,50.7248001099],"type":"Point"}
}