{
  "type": "Feature",
  "properties": {
    "iso:country":"BE",
    "sg:address":"Emiel Hullebroecklaan 11",
    "sg:city":"Aartselaar",
    "sg:orig_category":"Non-Classified Establishments",
    "sg:phone":"+32 3 844 30 00",
    "sg:postcode":"2630",
    "sg:province":"Antwerpen",
    "wof:name":"Indis Nv",
    "wof:placetype":"venue"
},
  "geometry": {"coordinates":[4.3638501167,51.1125297546],"type":"Point"}
}