{
  "type": "Feature",
  "properties": {
    "iso:country":"BE",
    "sg:address":"Tuinweg 21",
    "sg:city":"Zandhoven",
    "sg:orig_category":"Transports routiers de marchandises",
    "sg:phone":"+32 3 484 36 55",
    "sg:postcode":"2242",
    "sg:province":"Antwerpen",
    "wof:name":"De Cnodder",
    "wof:placetype":"venue"
},
  "geometry": {"coordinates":[4.6957421303,51.2151527405],"type":"Point"}
}