{
  "type": "Feature",
  "properties": {
    "addr:full":"Herbesthaler Strasse 1a Eupen Li\u00e8ge 4700",
    "addr:housenumber":"1a",
    "addr:postcode":"4700",
    "addr:street":"Herbesthaler Strasse",
    "iso:country":"BE",
    "sg:address":"Herbesthaler Strasse 1a",
    "sg:city":"Eupen",
    "sg:classifiers":[
        {
            "category":"Government",
            "subcategory":"Office",
            "type":"Public Place"
        }
    ],
    "sg:phone":"+32 87 55 59 63",
    "sg:postcode":"4700",
    "sg:province":"Li\u00e8ge",
    "sg:tags":[
        "chamber",
        "industry",
        "commerce"
    ],
    "wof:name":"Ihk",
    "wof:placetype":"venue"
},
  "geometry": {"coordinates":[6.0261268616,50.6329727173],"type":"Point"}
}