{
  "type": "Feature",
  "properties": {
    "iso:country":"BE",
    "sg:address":"Lascheid 38",
    "sg:city":"Burg-reuland",
    "sg:orig_category":"Rundveehouders",
    "sg:phone":"+32 80 32 92 43",
    "sg:postcode":"4790",
    "sg:province":"Li\u00e8ge",
    "wof:name":"Martin Schmitz",
    "wof:placetype":"venue"
},
  "geometry": {"coordinates":[6.1315770149,50.1943702698],"type":"Point"}
}