{
  "type": "Feature",
  "properties": {
    "iso:country":"BE",
    "sg:address":"Westrozebekestraat 31",
    "sg:city":"Staden",
    "sg:orig_category":"Kantoormateriaal",
    "sg:phone":"+32 51 21 19 95",
    "sg:postcode":"8840",
    "sg:province":"West-Vlaanderen",
    "wof:name":"Marie-jose Verhalleman",
    "wof:placetype":"venue"
},
  "geometry": {"coordinates":[3.0527250767,50.9425621033],"type":"Point"}
}