{
  "type": "Feature",
  "properties": {
    "addr:full":"Broekstraat 71 Lubbeek Vlaams-Brabant 3210",
    "addr:housenumber":"71",
    "addr:postcode":"3210",
    "addr:street":"Broekstraat",
    "iso:country":"BE",
    "sg:address":"Broekstraat 71",
    "sg:city":"Lubbeek",
    "sg:orig_category":"Messageries",
    "sg:phone":"+32 16 63 26 26",
    "sg:postcode":"3210",
    "sg:province":"Vlaams-Brabant",
    "wof:name":"J.p.l. Express",
    "wof:placetype":"venue"
},
  "geometry": {"coordinates":[4.8404550552,50.8879318237],"type":"Point"}
}