{
  "type": "Feature",
  "properties": {
    "addr:full":"Luchthavenstraat 1b12 Wevelgem West-Vlaanderen 8560",
    "addr:housenumber":"1b12",
    "addr:postcode":"8560",
    "addr:street":"Luchthavenstraat",
    "iso:country":"BE",
    "sg:address":"Luchthavenstraat 1b12",
    "sg:city":"Wevelgem",
    "sg:orig_category":"Ecoles de pilotage de bateaux and d\u00b4avions",
    "sg:phone":"+32 56 37 34 34",
    "sg:postcode":"8560",
    "sg:province":"West-Vlaanderen",
    "wof:name":"L.v.c. Helicopters",
    "wof:placetype":"venue"
},
  "geometry": {"coordinates":[3.2182369232,50.8190460205],"type":"Point"}
}