{
  "type": "Feature",
  "properties": {
    "addr:full":"Rue Des Briqueteries 84 Seraing Li\u00e8ge 4100",
    "addr:housenumber":"84",
    "addr:postcode":"4100",
    "addr:street":"Rue Des Briqueteries",
    "iso:country":"BE",
    "sg:address":"Rue Des Briqueteries 84",
    "sg:city":"Seraing",
    "sg:classifiers":[
        {
            "category":"Real Estate",
            "subcategory":"Architect",
            "type":"Services"
        }
    ],
    "sg:phone":"+32 4 336 53 25",
    "sg:postcode":"4100",
    "sg:province":"Li\u00e8ge",
    "wof:name":"Ghilain P",
    "wof:placetype":"venue"
},
  "geometry": {"coordinates":[5.4996738434,50.5824813843],"type":"Point"}
}