{
  "type": "Feature",
  "properties": {
    "addr:full":"Kiewitstraat 235 Hasselt Limburg 3500",
    "addr:housenumber":"235",
    "addr:postcode":"3500",
    "addr:street":"Kiewitstraat",
    "iso:country":"BE",
    "sg:address":"Kiewitstraat 235",
    "sg:city":"Hasselt",
    "sg:orig_category":"Jardinage. Assurances",
    "sg:phone":"+32 11 21 26 55",
    "sg:postcode":"3500",
    "sg:province":"Limburg",
    "wof:name":"Bureau Janssens",
    "wof:placetype":"venue"
},
  "geometry": {"coordinates":[5.3690128326,50.9566268921],"type":"Point"}
}