{
  "type": "Feature",
  "properties": {
    "addr:full":"Rue Neuve 13-15 Pepinster Li\u00e8ge 4860",
    "addr:postcode":"13-15;4860",
    "addr:street":"Rue Neuve",
    "iso:country":"BE",
    "sg:address":"Rue Neuve 13-15",
    "sg:city":"Pepinster",
    "sg:orig_category":"Boucheries. Alimentation sp\u00e9cialis\u00e9e",
    "sg:phone":"+32 87 46 15 71",
    "sg:postcode":"4860",
    "sg:province":"Li\u00e8ge",
    "wof:name":"La Boucherie",
    "wof:placetype":"venue"
},
  "geometry": {"coordinates":[5.8031411171,50.5677947998],"type":"Point"}
}