{
  "type": "Feature",
  "properties": {
    "iso:country":"BE",
    "sg:address":"Rue De Rempache 13",
    "sg:city":"Hamois",
    "sg:orig_category":"Eleveurs de bovins",
    "sg:phone":"+32 83 61 17 06",
    "sg:postcode":"5364",
    "sg:province":"Namur",
    "wof:name":"Raymond Willem",
    "wof:placetype":"venue"
},
  "geometry": {"coordinates":[5.1289258003,50.3663825989],"type":"Point"}
}