{
  "type": "Feature",
  "properties": {
    "iso:country":"BE",
    "sg:address":"Achterstehoek 3",
    "sg:city":"Lille",
    "sg:orig_category":"Bouwmaterialen Gh Dakwerken",
    "sg:phone":"+32 14 88 31 31",
    "sg:postcode":"2275",
    "sg:province":"Antwerpen",
    "wof:name":"Dakwerken Van Mechelen",
    "wof:placetype":"venue"
},
  "geometry": {"coordinates":[4.8126368523,51.2484474182],"type":"Point"}
}