{
  "type": "Feature",
  "properties": {
    "iso:country":"BE",
    "sg:address":"Zonnelaan 17",
    "sg:city":"Overijse",
    "sg:classifiers":[
        {
            "category":"Wholesale",
            "subcategory":"Medical Equipment & Supplies",
            "type":"Manufacturing & Wholesale Goods"
        }
    ],
    "sg:phone":"+32 2 687 38 68",
    "sg:postcode":"3090",
    "sg:province":"Vlaams-Brabant",
    "sg:tags":[
        "instrument",
        "apparatus"
    ],
    "wof:name":"Pm Trading & Consultancy",
    "wof:placetype":"venue"
},
  "geometry": {"coordinates":[4.5056400299,50.7474784851],"type":"Point"}
}