{
  "type": "Feature",
  "properties": {
    "addr:full":"Rue Emile Vandervelde 352 Li\u00e8ge 1 (glain) Li\u00e8ge 4000",
    "addr:housenumber":"352;1",
    "addr:postcode":"4000",
    "addr:street":"Rue Emile Vandervelde",
    "iso:country":"BE",
    "sg:address":"Rue Emile Vandervelde 352",
    "sg:city":"Li\u00e8ge 1 (glain)",
    "sg:classifiers":[
        {
            "category":"Utilities",
            "subcategory":"Recycling",
            "type":"Services"
        }
    ],
    "sg:phone":"+32 4 384 42 14",
    "sg:postcode":"4000",
    "sg:province":"Li\u00e8ge",
    "wof:name":"Recytec",
    "wof:placetype":"venue"
},
  "geometry": {"coordinates":[5.549683094,50.6481132507],"type":"Point"}
}