{
  "type": "Feature",
  "properties": {
    "addr:full":"Avenue Des Chasseurs 7 Kraainem/kraainem Vlaams-Brabant 1950",
    "addr:housenumber":"7",
    "addr:postcode":"1950",
    "addr:street":"Avenue Des Chasseurs",
    "iso:country":"BE",
    "sg:address":"Avenue Des Chasseurs 7",
    "sg:city":"Kraainem/kraainem",
    "sg:orig_category":"M\u00e9decins and sp\u00e9cialistes",
    "sg:phone":"+32 2 767 35 18",
    "sg:postcode":"1950",
    "sg:province":"Vlaams-Brabant",
    "wof:name":"Marc De Vylder",
    "wof:placetype":"venue"
},
  "geometry": {"coordinates":[4.4793667793,50.8219299316],"type":"Point"}
}