{
  "type": "Feature",
  "properties": {
    "iso:country":"BE",
    "sg:address":"Hoogstraat 108bb",
    "sg:city":"Denderleeuw",
    "sg:orig_category":"Zuivelproducten",
    "sg:phone":"+32 53 67 21 90",
    "sg:postcode":"9472",
    "sg:province":"Oost-Vlaanderen",
    "wof:name":"Eddy Kiekens",
    "wof:placetype":"venue"
},
  "geometry": {"coordinates":[4.0456581116,50.8760032654],"type":"Point"}
}