{
  "type": "Feature",
  "properties": {
    "iso:country":"BE",
    "sg:address":"Lekkerbeetstraat 5-7",
    "sg:city":"Kortrijk",
    "sg:classifiers":[
        {
            "category":"Banks & Credit Unions",
            "subcategory":"Financial Services",
            "type":"Services"
        }
    ],
    "sg:phone":"+32 56 24 02 11",
    "sg:postcode":"8500",
    "sg:province":"West-Vlaanderen",
    "sg:tags":[
        "banking",
        "finance",
        "insurance"
    ],
    "wof:name":"De Kortrijkse Verzekering Nv",
    "wof:placetype":"venue"
},
  "geometry": {"coordinates":[3.2682979107,50.8263778687],"type":"Point"}
}