{
  "type": "Feature",
  "properties": {
    "addr:full":"Motstraat 36 Alken Limburg 3570",
    "addr:housenumber":"36",
    "addr:postcode":"3570",
    "addr:street":"Motstraat",
    "iso:country":"BE",
    "sg:address":"Motstraat 36",
    "sg:city":"Alken",
    "sg:classifiers":[
        {
            "category":"Real Estate",
            "subcategory":"Developer",
            "type":"Services"
        }
    ],
    "sg:phone":"+32 11 31 22 97",
    "sg:postcode":"3570",
    "sg:province":"Limburg",
    "sg:tags":[
        "project"
    ],
    "wof:name":"Stulens Immo Bvba",
    "wof:placetype":"venue"
},
  "geometry": {"coordinates":[5.3086180687,50.8707580566],"type":"Point"}
}