{
  "type": "Feature",
  "properties": {
    "iso:country":"BE",
    "sg:address":"Rue Dansaert 230",
    "sg:city":"Dilbeek",
    "sg:orig_category":"Alimentation sp\u00e9cialis\u00e9e",
    "sg:phone":"+32 2 466 39 33",
    "sg:postcode":"1700",
    "sg:province":"Vlaams-Brabant",
    "wof:name":"Makady",
    "wof:placetype":"venue"
},
  "geometry": {"coordinates":[4.2624697685,50.8459358215],"type":"Point"}
}