{
  "type": "Feature",
  "properties": {
    "addr:full":"De Burburestraat 20 Antwerpen Antwerpen 2000",
    "addr:housenumber":"20",
    "addr:postcode":"2000",
    "addr:street":"Burburestraat",
    "iso:country":"BE",
    "sg:address":"De Burburestraat 20",
    "sg:city":"Antwerpen",
    "sg:orig_category":"Studios photographiques",
    "sg:phone":"+32 3 237 20 25",
    "sg:postcode":"2000",
    "sg:province":"Antwerpen",
    "wof:name":"Photo & Graphic Factory",
    "wof:placetype":"venue"
},
  "geometry": {"coordinates":[4.3917179108,51.2089691162],"type":"Point"}
}