{
  "type": "Feature",
  "properties": {
    "iso:country":"BE",
    "sg:address":"Rue Des Bruy\u00c8res 102a",
    "sg:city":"Eghezee",
    "sg:orig_category":"Installation de menuiserie m\u00e9tallique. Installation de menuiserie en bois and plastique",
    "sg:phone":"+32 81 51 28 38",
    "sg:postcode":"5310",
    "sg:province":"Namur",
    "wof:name":"F.r.a.m.e.",
    "wof:placetype":"venue"
},
  "geometry": {"coordinates":[4.9022130966,50.5505599976],"type":"Point"}
}