{
  "type": "Feature",
  "properties": {
    "addr:full":"Oostrozebekestraat 241a Ingelmunster West-Vlaanderen 8770",
    "addr:housenumber":"241a",
    "addr:postcode":"8770",
    "addr:street":"Oostrozebekestraat",
    "iso:country":"BE",
    "sg:address":"Oostrozebekestraat 241a",
    "sg:city":"Ingelmunster",
    "sg:classifiers":[
        {
            "category":"Government",
            "subcategory":"Fire Station",
            "type":"Public Place"
        }
    ],
    "sg:phone":"+32 51 31 75 10",
    "sg:postcode":"8770",
    "sg:province":"West-Vlaanderen",
    "sg:tags":[
        "installation",
        "-",
        "air conditioning"
    ],
    "wof:name":"Vanluchene I",
    "wof:placetype":"venue"
},
  "geometry": {"coordinates":[3.2737851143,50.9182014465],"type":"Point"}
}