{
  "type": "Feature",
  "properties": {
    "addr:full":"Bisschopstraat 21 Antwerpen Antwerpen 2060",
    "addr:housenumber":"21",
    "addr:postcode":"2060",
    "addr:street":"Bisschopstraat",
    "iso:country":"BE",
    "sg:address":"Bisschopstraat 21",
    "sg:city":"Antwerpen",
    "sg:orig_category":"Verplichte sociale verzekeringen",
    "sg:phone":"+32 3 234 36 71",
    "sg:postcode":"2060",
    "sg:province":"Antwerpen",
    "wof:name":"Liberale Mutualiteit",
    "wof:placetype":"venue"
},
  "geometry": {"coordinates":[4.4245939255,51.2189865112],"type":"Point"}
}