{
  "type": "Feature",
  "properties": {
    "addr:full":"Zeelaan 32 Koksijde West-Vlaanderen 8670",
    "addr:housenumber":"32",
    "addr:postcode":"8670",
    "addr:street":"Zeelaan",
    "iso:country":"BE",
    "sg:address":"Zeelaan 32",
    "sg:city":"Koksijde",
    "sg:classifiers":[
        {
            "category":"Personal",
            "subcategory":"Beauty Salon",
            "type":"Services"
        }
    ],
    "sg:phone":"+32 58 51 29 00",
    "sg:postcode":"8670",
    "sg:province":"West-Vlaanderen",
    "sg:tags":[
        "lady",
        "-",
        "hairdressing"
    ],
    "wof:name":"Knapp",
    "wof:placetype":"venue"
},
  "geometry": {"coordinates":[2.6498410702,51.1058731079],"type":"Point"}
}