{
  "type": "Feature",
  "properties": {
    "addr:full":"Rue Joseph War\u00e8gne 93 Namur (flawinne) Namur 5020",
    "addr:housenumber":"93",
    "addr:postcode":"5020",
    "addr:street":"Rue Joseph Ware\u0300Gne",
    "iso:country":"BE",
    "sg:address":"Rue Joseph War\u00e8gne 93",
    "sg:city":"Namur (flawinne)",
    "sg:classifiers":[
        {
            "category":"Insurance",
            "subcategory":"Insurance Agent",
            "type":"Services"
        }
    ],
    "sg:phone":"+32 81 74 01 13",
    "sg:postcode":"5020",
    "sg:province":"Namur",
    "sg:tags":[
        "broker"
    ],
    "wof:name":"Lemoine (bureau) Sa",
    "wof:placetype":"venue"
},
  "geometry": {"coordinates":[4.8791050911,50.4842414856],"type":"Point"}
}