{
  "type": "Feature",
  "properties": {
    "addr:full":"Rue Saint-roch 5 Mettet Namur 5640",
    "addr:housenumber":"5",
    "addr:postcode":"5640",
    "addr:street":"Rue Saint-Roch",
    "iso:country":"BE",
    "sg:address":"Rue Saint-roch 5",
    "sg:city":"Mettet",
    "sg:orig_category":"Traitements param\u00e9dicaux",
    "sg:phone":"+32 71 72 74 14",
    "sg:postcode":"5640",
    "sg:province":"Namur",
    "wof:name":"H. Defoy",
    "wof:placetype":"venue"
},
  "geometry": {"coordinates":[4.612071991,50.3335647583],"type":"Point"}
}