{
  "type": "Feature",
  "properties": {
    "addr:full":"Herrebeekstraat 17a Kortenaken (hoeleden) Vlaams-Brabant 3471",
    "addr:housenumber":"17a",
    "addr:postcode":"3471",
    "addr:street":"Herrebeekstraat",
    "iso:country":"BE",
    "sg:address":"Herrebeekstraat 17a",
    "sg:city":"Kortenaken (hoeleden)",
    "sg:classifiers":[
        {
            "category":"Sports & Exercise",
            "subcategory":"Skate Park",
            "type":"Entertainment"
        }
    ],
    "sg:phone":"+32 16 77 03 76",
    "sg:postcode":"3471",
    "sg:province":"Vlaams-Brabant",
    "sg:tags":[
        "mushroom"
    ],
    "wof:name":"Champignonkwekerij Kempeneers Eddy Bvba",
    "wof:placetype":"venue"
},
  "geometry": {"coordinates":[5.000026226,50.858581543],"type":"Point"}
}