{
  "type": "Feature",
  "properties": {
    "addr:full":"Postweg 2 Sint-pieters-leeuw Vlaams-Brabant 1602",
    "addr:housenumber":"2",
    "addr:postcode":"1602",
    "addr:street":"Postweg",
    "iso:country":"BE",
    "sg:address":"Postweg 2",
    "sg:city":"Sint-pieters-leeuw",
    "sg:orig_category":"Alimentation sp\u00e9cialis\u00e9e. Grossistes divers. Pain, p\u00e2tisseries and confiseries",
    "sg:phone":"+32 2 568 22 60",
    "sg:postcode":"1602",
    "sg:province":"Vlaams-Brabant",
    "wof:name":"Neuhaus",
    "wof:placetype":"venue"
},
  "geometry": {"coordinates":[4.2587618828,50.8138389587],"type":"Point"}
}