{
  "type": "Feature",
  "properties": {
    "addr:full":"Grondwetlaan 81 Gent Oost-Vlaanderen 9040",
    "addr:housenumber":"81",
    "addr:postcode":"9040",
    "addr:street":"Grondwetlaan;Oost-Vlaanderen",
    "iso:country":"BE",
    "sg:address":"Grondwetlaan 81",
    "sg:city":"Gent",
    "sg:orig_category":"HERSTELLING ELEKTRISCHE HUISHOUDAPPARATEN Huishoudapparaten, televisies and radio's IJzerwaren, bouw",
    "sg:phone":"+32 9 251 49 99",
    "sg:postcode":"9040",
    "sg:province":"Oost-Vlaanderen",
    "wof:name":"Huis Adek",
    "wof:placetype":"venue"
},
  "geometry": {"coordinates":[3.7505099773,51.0674591064],"type":"Point"}
}