{
  "type": "Feature",
  "properties": {
    "iso:country":"BE",
    "sg:address":"Koning Albertstraat 13",
    "sg:city":"Kortrijk",
    "sg:classifiers":[
        {
            "category":"Restaurant",
            "type":"Food & Drink"
        }
    ],
    "sg:phone":"+32 56 20 02 92",
    "sg:postcode":"8500",
    "sg:province":"West-Vlaanderen",
    "wof:name":"Mamma Mia",
    "wof:placetype":"venue"
},
  "geometry": {"coordinates":[3.2636489868,50.8250961304],"type":"Point"}
}