{
  "type": "Feature",
  "properties": {
    "addr:full":"Parklaan 124 Turnhout Antwerpen 2300",
    "addr:housenumber":"124",
    "addr:postcode":"2300",
    "addr:street":"Parklaan",
    "iso:country":"BE",
    "sg:address":"Parklaan 124",
    "sg:city":"Turnhout",
    "sg:classifiers":[
        {
            "category":"Banks & Credit Unions",
            "subcategory":"Bank",
            "type":"Services"
        }
    ],
    "sg:phone":"+32 14 42 49 11",
    "sg:postcode":"2300",
    "sg:province":"Antwerpen",
    "wof:name":"Kredietbank Nv",
    "wof:placetype":"venue"
},
  "geometry": {"coordinates":[4.9665288925,51.3192024231],"type":"Point"}
}