{
  "type": "Feature",
  "properties": {
    "addr:full":"Stokkelse Steenweg 28 Sint-lambrechts-woluwe/woluwe-saint-lambert Bruxelles-Capitale 1200",
    "addr:housenumber":"28",
    "addr:postcode":"1200",
    "addr:street":"Stokkelse Steenweg",
    "iso:country":"BE",
    "sg:address":"Stokkelse Steenweg 28",
    "sg:city":"Sint-lambrechts-woluwe/woluwe-saint-lambert",
    "sg:orig_category":"Technisch and beroeps secundair onderwijs",
    "sg:phone":"+32 2 771 57 81",
    "sg:postcode":"1200",
    "sg:province":"Bruxelles-Capitale",
    "wof:name":"Institut De La Providence",
    "wof:placetype":"venue"
},
  "geometry": {"coordinates":[4.4386019707,50.8402099609],"type":"Point"}
}