{
  "type": "Feature",
  "properties": {
    "addr:full":"Molenheidestraat 9ba Aarschot Vlaams-Brabant 3201",
    "addr:postcode":"3201",
    "addr:street":"Molenheidestraat;Vlaams-Brabant",
    "iso:country":"BE",
    "sg:address":"Molenheidestraat 9ba",
    "sg:city":"Aarschot",
    "sg:orig_category":"Sportclubs",
    "sg:phone":"+32 16 56 28 78",
    "sg:postcode":"3201",
    "sg:province":"Vlaams-Brabant",
    "wof:name":"W.c. Forestbikers",
    "wof:placetype":"venue"
},
  "geometry": {"coordinates":[4.8997879028,51.0126037598],"type":"Point"}
}