{
  "type": "Feature",
  "properties": {
    "iso:country":"BE",
    "sg:address":"Steenovenstraat 26",
    "sg:city":"Tielt",
    "sg:classifiers":[
        {
            "category":"Banks & Credit Unions",
            "subcategory":"Financial Services",
            "type":"Services"
        }
    ],
    "sg:phone":"+32 51 40 02 07",
    "sg:postcode":"8700",
    "sg:province":"West-Vlaanderen",
    "sg:tags":[
        "made",
        "door",
        "plastic"
    ],
    "wof:name":"H. & L. Neirinck B.v.b.a.",
    "wof:placetype":"venue"
},
  "geometry": {"coordinates":[3.3187420368,50.9953155518],"type":"Point"}
}