{
  "type": "Feature",
  "properties": {
    "iso:country":"BE",
    "sg:address":"Moortselestraat 39",
    "sg:city":"Oosterzele",
    "sg:orig_category":"Herstellingen and onderhoud van auto's",
    "sg:phone":"+32 9 362 98 23",
    "sg:postcode":"9860",
    "sg:province":"Oost-Vlaanderen",
    "wof:name":"Gerard Pauwels",
    "wof:placetype":"venue"
},
  "geometry": {"coordinates":[3.7795450687,50.9560089111],"type":"Point"}
}