{
  "type": "Feature",
  "properties": {
    "iso:country":"BE",
    "sg:address":"Rue De L'ev\u00caque 3",
    "sg:city":"Brussel/bruxelles",
    "sg:orig_category":"Telecommunicatieapparaten",
    "sg:phone":"+32 2 218 05 18",
    "sg:postcode":"1000",
    "sg:province":"Bruxelles-Capitale",
    "wof:name":"Abelesco",
    "wof:placetype":"venue"
},
  "geometry": {"coordinates":[4.3510508537,50.8504943848],"type":"Point"}
}