{
  "type": "Feature",
  "properties": {
    "addr:full":"Wittemolenstraat 106 Brugge (sint-michiels) West-Vlaanderen 8200",
    "addr:housenumber":"106",
    "addr:postcode":"8200",
    "addr:street":"Wittemolenstraat",
    "iso:country":"BE",
    "sg:address":"Wittemolenstraat 106",
    "sg:city":"Brugge (sint-michiels)",
    "sg:classifiers":[
        {
            "category":"Insurance",
            "subcategory":"Insurance Agent",
            "type":"Services"
        }
    ],
    "sg:phone":"+32 50 38 22 98",
    "sg:postcode":"8200",
    "sg:province":"West-Vlaanderen",
    "sg:tags":[
        "broker"
    ],
    "wof:name":"Le Fevere De Ten Hove J",
    "wof:placetype":"venue"
},
  "geometry": {"coordinates":[3.1904699802,51.1992111206],"type":"Point"}
}