{
  "type": "Feature",
  "properties": {
    "addr:full":"Place De L'eglise 15 Houffalize Luxembourg 6660",
    "addr:housenumber":"15",
    "addr:postcode":"6660",
    "addr:street":"Place De L'Eglise",
    "iso:country":"BE",
    "sg:address":"Place De L'eglise 15",
    "sg:city":"Houffalize",
    "sg:orig_category":"Pain, p\u00e2tisseries and confiseries",
    "sg:phone":"+32 61 28 92 86",
    "sg:postcode":"6660",
    "sg:province":"Luxembourg",
    "wof:name":"Boulangerie La Paneti\u00c8re",
    "wof:placetype":"venue"
},
  "geometry": {"coordinates":[5.6804599762,50.1528587341],"type":"Point"}
}