{
  "type": "Feature",
  "properties": {
    "iso:country":"BE",
    "sg:address":"Drijhoek 12",
    "sg:city":"Geel",
    "sg:classifiers":[
        {
            "category":"Health Services",
            "subcategory":"Dentist",
            "type":"Services"
        }
    ],
    "sg:phone":"+32 14 58 41 86",
    "sg:postcode":"2440",
    "sg:province":"Antwerpen",
    "wof:name":"Andries Erna",
    "wof:placetype":"venue"
},
  "geometry": {"coordinates":[4.9733901024,51.1599235535],"type":"Point"}
}