{
  "type": "Feature",
  "properties": {
    "addr:full":"Begonialaan 12 Lochristi Oost-Vlaanderen 9080",
    "addr:housenumber":"12",
    "addr:postcode":"9080",
    "addr:street":"Begonialaan",
    "iso:country":"BE",
    "sg:address":"Begonialaan 12",
    "sg:city":"Lochristi",
    "sg:classifiers":[
        {
            "category":"Cafe",
            "type":"Food & Drink"
        }
    ],
    "sg:phone":"+32 9 355 78 18",
    "sg:postcode":"9080",
    "sg:province":"Oost-Vlaanderen",
    "sg:tags":[
        "caf\u00e9s"
    ],
    "wof:name":"Ann Vermeersch",
    "wof:placetype":"venue"
},
  "geometry": {"coordinates":[3.8172829151,51.0931434631],"type":"Point"}
}