{
  "type": "Feature",
  "properties": {
    "addr:full":"Markt 1 Vorselaar Antwerpen 2290",
    "addr:housenumber":"1",
    "addr:postcode":"2290",
    "addr:street":"Markt",
    "iso:country":"BE",
    "sg:address":"Markt 1",
    "sg:city":"Vorselaar",
    "sg:orig_category":"Banques and organismes de cr\u00e9dit",
    "sg:phone":"+32 14 51 47 98",
    "sg:postcode":"2290",
    "sg:province":"Antwerpen",
    "wof:name":"Fortis",
    "wof:placetype":"venue"
},
  "geometry": {"coordinates":[4.7729301453,51.202495575],"type":"Point"}
}