{
  "type": "Feature",
  "properties": {
    "iso:country":"BE",
    "sg:address":"Avenue Neptune 45b1",
    "sg:city":"Vorst/forest",
    "sg:orig_category":"Administration d'immeubles",
    "sg:phone":"+32 2 344 13 03",
    "sg:postcode":"1190",
    "sg:province":"Bruxelles-Capitale",
    "wof:name":"Ch. Schriewer",
    "wof:placetype":"venue"
},
  "geometry": {"coordinates":[4.3341579437,50.8133926392],"type":"Point"}
}