{
  "type": "Feature",
  "properties": {
    "addr:full":"Chemin Du Chevauchoire De Binche 17 Braine-le-comte Hainaut 7090",
    "addr:housenumber":"17",
    "addr:postcode":"7090",
    "addr:street":"Chemin Du Chevauchoire De Binche",
    "iso:country":"BE",
    "sg:address":"Chemin Du Chevauchoire De Binche 17",
    "sg:city":"Braine-le-comte",
    "sg:classifiers":[
        {
            "category":"Home & Garden",
            "subcategory":"Carpets & Floor Coverings",
            "type":"Retail Goods"
        }
    ],
    "sg:phone":"+32 67 55 47 27",
    "sg:postcode":"7090",
    "sg:province":"Hainaut",
    "sg:tags":[
        "layer",
        "mosaicists"
    ],
    "wof:name":"Walem M",
    "wof:placetype":"venue"
},
  "geometry": {"coordinates":[4.1408801079,50.5990791321],"type":"Point"}
}