{
  "type": "Feature",
  "properties": {
    "iso:country":"BE",
    "sg:address":"Tierstraat 67",
    "sg:city":"Diepenbeek",
    "sg:classifiers":[
        {
            "category":"Building & Trades",
            "subcategory":"Construction",
            "type":"Services"
        }
    ],
    "sg:phone":"+32 11 32 15 71",
    "sg:postcode":"3590",
    "sg:province":"Limburg",
    "sg:tags":[
        "carpenter"
    ],
    "wof:name":"Geuns G Bvba",
    "wof:placetype":"venue"
},
  "geometry": {"coordinates":[5.3952069283,50.8894309998],"type":"Point"}
}