{
  "type": "Feature",
  "properties": {
    "iso:country":"BE",
    "sg:address":"Gentsesteenweg 25",
    "sg:city":"Zingem (huise)",
    "sg:classifiers":[
        {
            "category":"Food & Beverages",
            "subcategory":"Fruits & Vegetables",
            "type":"Retail Goods"
        }
    ],
    "sg:phone":"+32 9 384 88 73",
    "sg:postcode":"9750",
    "sg:province":"Oost-Vlaanderen",
    "sg:tags":[
        "-"
    ],
    "wof:name":"Fruitmeester (de)",
    "wof:placetype":"venue"
},
  "geometry": {"coordinates":[3.6519870758,50.9060554504],"type":"Point"}
}