{
  "type": "Feature",
  "properties": {
    "addr:full":"Rue Henri Bl\u00e8s 188 Namur Namur 5000",
    "addr:housenumber":"188",
    "addr:postcode":"5000",
    "addr:street":"Rue Henri Ble\u0300S",
    "iso:country":"BE",
    "sg:address":"Rue Henri Bl\u00e8s 188",
    "sg:city":"Namur",
    "sg:classifiers":[
        {
            "category":"Education",
            "subcategory":"University",
            "type":"Public Place"
        }
    ],
    "sg:phone":"+32 81 72 97 40",
    "sg:postcode":"5000",
    "sg:province":"Namur",
    "sg:tags":[
        "adult"
    ],
    "wof:name":"Ecole Provinciale De Cadres",
    "wof:placetype":"venue"
},
  "geometry": {"coordinates":[4.8390498161,50.4653396606],"type":"Point"}
}