{
  "type": "Feature",
  "properties": {
    "addr:full":"Vosdellestraat 23 Hoeilaart Vlaams-Brabant 1560",
    "addr:housenumber":"23",
    "addr:postcode":"1560",
    "addr:street":"Vosdellestraat",
    "iso:country":"BE",
    "sg:address":"Vosdellestraat 23",
    "sg:city":"Hoeilaart",
    "sg:classifiers":[
        {
            "category":"Cafe",
            "type":"Food & Drink"
        }
    ],
    "sg:phone":"+32 2 657 29 53",
    "sg:postcode":"1560",
    "sg:province":"Vlaams-Brabant",
    "sg:tags":[
        "caf\u00e9s"
    ],
    "wof:name":"Dimitri Erkens",
    "wof:placetype":"venue"
},
  "geometry": {"coordinates":[4.4669141769,50.7611312866],"type":"Point"}
}