{
  "type": "Feature",
  "properties": {
    "iso:country":"BE",
    "sg:address":"Rue Saint-monon 14",
    "sg:city":"Nassogne (groot)",
    "sg:orig_category":"Banques and organismes de cr\u00e9dit",
    "sg:phone":"+32 84 21 08 94",
    "sg:postcode":"6950",
    "sg:province":"Luxembourg",
    "wof:name":"Bily-quirynen",
    "wof:placetype":"venue"
},
  "geometry": {"coordinates":[5.3439588547,50.1301727295],"type":"Point"}
}