{
  "type": "Feature",
  "properties": {
    "addr:full":"Bosdreef 5ba Lochristi Oost-Vlaanderen 9080",
    "addr:housenumber":"5ba",
    "addr:postcode":"9080",
    "addr:street":"Bosdreef",
    "iso:country":"BE",
    "sg:address":"Bosdreef 5ba",
    "sg:city":"Lochristi",
    "sg:classifiers":[
        {
            "category":"Health Services",
            "subcategory":"Nursing And Care Facility",
            "type":"Services"
        }
    ],
    "sg:phone":"+32 9 355 93 09",
    "sg:postcode":"9080",
    "sg:province":"Oost-Vlaanderen",
    "sg:tags":[
        "public"
    ],
    "wof:name":"O.c.m.w.",
    "wof:placetype":"venue"
},
  "geometry": {"coordinates":[3.8389360905,51.0962371826],"type":"Point"}
}