{
  "type": "Feature",
  "properties": {
    "addr:full":"Hospitaalstraat 46 Ieper West-Vlaanderen 8906",
    "addr:housenumber":"46",
    "addr:postcode":"8906",
    "addr:street":"Hospitaalstraat",
    "iso:country":"BE",
    "sg:address":"Hospitaalstraat 46",
    "sg:city":"Ieper",
    "sg:orig_category":"Rundveehouders Varkenskwekers",
    "sg:phone":"+32 57 42 21 41",
    "sg:postcode":"8906",
    "sg:province":"West-Vlaanderen",
    "wof:name":"Noel Hoorelbeke",
    "wof:placetype":"venue"
},
  "geometry": {"coordinates":[2.8054409027,50.8749008179],"type":"Point"}
}