{
  "type": "Feature",
  "properties": {
    "addr:full":"Avenue De L'exposition 257 Jette Bruxelles-Capitale 1090",
    "addr:housenumber":"257",
    "addr:postcode":"1090",
    "addr:street":"Avenue De L'Exposition",
    "iso:country":"BE",
    "sg:address":"Avenue De L'exposition 257",
    "sg:city":"Jette",
    "sg:classifiers":[
        {
            "category":"Arena",
            "subcategory":"Sports Club",
            "type":"Entertainment"
        }
    ],
    "sg:phone":"+32 2 476 11 81",
    "sg:postcode":"1090",
    "sg:province":"Bruxelles-Capitale",
    "sg:tags":[
        "terrain",
        "hors",
        "de",
        "installation",
        "sportifs"
    ],
    "wof:name":"Royal Scup De Jette",
    "wof:placetype":"venue"
},
  "geometry": {"coordinates":[4.3160719872,50.8823165894],"type":"Point"}
}