{
  "type": "Feature",
  "properties": {
    "addr:full":"Kongostraat 47 Bruges West-Vlaanderen 8310",
    "addr:housenumber":"47",
    "addr:postcode":"8310",
    "addr:street":"Kongostraat",
    "iso:country":"BE",
    "sg:address":"Kongostraat 47",
    "sg:city":"Bruges",
    "sg:orig_category":"Appareils de pulv\u00e9risation Fab",
    "sg:phone":"+32 50 36 15 93",
    "sg:postcode":"8310",
    "sg:province":"West-Vlaanderen",
    "wof:name":"A.c. Service",
    "wof:placetype":"venue"
},
  "geometry": {"coordinates":[3.2382490635,51.1896705627],"type":"Point"}
}