{
  "type": "Feature",
  "properties": {
    "iso:country":"BE",
    "sg:address":"Rue Du Chardon 10",
    "sg:city":"Braives",
    "sg:orig_category":"Catering and organisatie van feesten Restaurants Ruimtes voor conferenties, recepties and feesten",
    "sg:phone":"+32 19 69 94 12",
    "sg:postcode":"4260",
    "sg:province":"Li\u00e8ge",
    "wof:name":"Le Chardon",
    "wof:placetype":"venue"
},
  "geometry": {"coordinates":[5.1711058617,50.6098556519],"type":"Point"}
}