{
  "type": "Feature",
  "properties": {
    "iso:country":"BE",
    "sg:address":"Veeweg 2",
    "sg:city":"Evergem",
    "sg:classifiers":[
        {
            "category":"Health Services",
            "subcategory":"Health Practitioner",
            "type":"Services"
        }
    ],
    "sg:phone":"+32 9 253 96 07",
    "sg:postcode":"9940",
    "sg:province":"Oost-Vlaanderen",
    "sg:tags":[
        "therapist",
        "speech"
    ],
    "wof:name":"Lebeer Anne",
    "wof:placetype":"venue"
},
  "geometry": {"coordinates":[3.7187049389,51.1137390137],"type":"Point"}
}