{
  "type": "Feature",
  "properties": {
    "addr:full":"Guido Gezellestraat 104 Denderleeuw Oost-Vlaanderen 9470",
    "addr:housenumber":"104",
    "addr:postcode":"9470",
    "addr:street":"Guido Gezellestraat",
    "iso:country":"BE",
    "sg:address":"Guido Gezellestraat 104",
    "sg:city":"Denderleeuw",
    "sg:orig_category":"Imprimeries and copyshops",
    "sg:phone":"+32 53 67 24 12",
    "sg:postcode":"9470",
    "sg:province":"Oost-Vlaanderen",
    "wof:name":"Drukkerij Rigo",
    "wof:placetype":"venue"
},
  "geometry": {"coordinates":[4.0763788223,50.8883666992],"type":"Point"}
}