{
  "type": "Feature",
  "properties": {
    "iso:country":"BE",
    "sg:address":"Lange Ridderstraat 36",
    "sg:city":"Mechelen",
    "sg:orig_category":"Hoger onderwijs",
    "sg:phone":"+32 15 21 98 72",
    "sg:postcode":"2800",
    "sg:province":"Antwerpen",
    "wof:name":"K.h.m.-'t Leerhuys",
    "wof:placetype":"venue"
},
  "geometry": {"coordinates":[4.4844498634,51.0251693726],"type":"Point"}
}