{
  "type": "Feature",
  "properties": {
    "iso:country":"BE",
    "sg:address":"Porte Des B\u00e2tisseurs 20",
    "sg:city":"Estaimpuis",
    "sg:classifiers":[
        {
            "category":"Professional",
            "subcategory":"Accounting & Tax Preparation",
            "type":"Services"
        }
    ],
    "sg:phone":"+32 56 48 20 76",
    "sg:postcode":"7730",
    "sg:province":"Hainaut",
    "sg:tags":[
        "accountant"
    ],
    "wof:name":"Figescom Sprl",
    "wof:placetype":"venue"
},
  "geometry": {"coordinates":[3.2555201054,50.7073898315],"type":"Point"}
}