{
  "type": "Feature",
  "properties": {
    "addr:full":"Koolmijnlaan 198 Beringen Limburg 3582",
    "addr:housenumber":"198",
    "addr:postcode":"3582",
    "addr:street":"Koolmijnlaan",
    "iso:country":"BE",
    "sg:address":"Koolmijnlaan 198",
    "sg:city":"Beringen",
    "sg:classifiers":[
        {
            "category":"Personal",
            "subcategory":"Beauty Salon",
            "type":"Services"
        }
    ],
    "sg:phone":"+32 11 43 48 23",
    "sg:postcode":"3582",
    "sg:province":"Limburg",
    "sg:tags":[
        "de",
        "coiffure"
    ],
    "wof:name":"Coiffure Patricia",
    "wof:placetype":"venue"
},
  "geometry": {"coordinates":[5.2206659317,51.0688438416],"type":"Point"}
}