{
  "type": "Feature",
  "properties": {
    "iso:country":"BE",
    "sg:address":"Rue De Repeumont 22",
    "sg:city":"Gembloux",
    "sg:orig_category":"Artistes ind\u00e9pendants",
    "sg:phone":"+32 81 61 02 77",
    "sg:postcode":"5031",
    "sg:province":"Namur",
    "wof:name":"Jean-marie Mathot",
    "wof:placetype":"venue"
},
  "geometry": {"coordinates":[4.7349162102,50.5789985657],"type":"Point"}
}