{
  "type": "Feature",
  "properties": {
    "iso:country":"BE",
    "sg:address":"Gaverstraat 6",
    "sg:city":"Zwalm",
    "sg:orig_category":"Woningbouw",
    "sg:phone":"+32 55 49 97 73",
    "sg:postcode":"9630",
    "sg:province":"Oost-Vlaanderen",
    "wof:name":"Maurice De Winne",
    "wof:placetype":"venue"
},
  "geometry": {"coordinates":[3.7156209946,50.9064292908],"type":"Point"}
}