{
  "type": "Feature",
  "properties": {
    "iso:country":"BE",
    "sg:address":"Tildonksesteenweg 172",
    "sg:city":"Herent",
    "sg:orig_category":"Entretien and r\u00e9parations de voitures. Stations-service and carburants",
    "sg:phone":"+32 16 23 83 92",
    "sg:postcode":"3020",
    "sg:province":"Vlaams-Brabant",
    "wof:name":"William Van Hove",
    "wof:placetype":"venue"
},
  "geometry": {"coordinates":[4.6653528214,50.9192008972],"type":"Point"}
}