{
  "type": "Feature",
  "properties": {
    "addr:full":"Kiezelweg 96 Herk-de-stad Limburg 3540",
    "addr:housenumber":"96",
    "addr:postcode":"3540",
    "addr:street":"Kiezelweg",
    "iso:country":"BE",
    "sg:address":"Kiezelweg 96",
    "sg:city":"Herk-de-stad",
    "sg:orig_category":"M\u00e9decins and sp\u00e9cialistes",
    "sg:phone":"+32 13 55 17 60",
    "sg:postcode":"3540",
    "sg:province":"Limburg",
    "wof:name":"Johan Stevens",
    "wof:placetype":"venue"
},
  "geometry": {"coordinates":[5.1763319969,50.9576148987],"type":"Point"}
}