{
  "type": "Feature",
  "properties": {
    "iso:country":"BE",
    "sg:address":"Rue J.-b. Vanpetegem 1bb",
    "sg:city":"Charleroi",
    "sg:orig_category":"Meubelzaken, woning- and keukeninrichting",
    "sg:phone":"+32 71 52 23 94",
    "sg:postcode":"6030",
    "sg:province":"Hainaut",
    "wof:name":"Franco Basso-valentina",
    "wof:placetype":"venue"
},
  "geometry": {"coordinates":[4.3949289322,50.4065132141],"type":"Point"}
}