{
  "type": "Feature",
  "properties": {
    "iso:country":"BE",
    "sg:address":"Servaes Daemsstraat 102",
    "sg:city":"Herentals",
    "sg:orig_category":"Afbraak- and draineerwerken Huisvuilophaling and -verwerking",
    "sg:phone":"+32 14 26 18 83",
    "sg:postcode":"2200",
    "sg:province":"Antwerpen",
    "wof:name":"Van Den Bulck",
    "wof:placetype":"venue"
},
  "geometry": {"coordinates":[4.8235659599,51.1486167908],"type":"Point"}
}