{
  "type": "Feature",
  "properties": {
    "iso:country":"BE",
    "sg:address":"Mont 13",
    "sg:city":"Houffalize",
    "sg:orig_category":"Installatie van houten of kunststof schrijnwerk Plaatsen van vloer- and muurbekleding Woningbouw",
    "sg:phone":"+32 61 28 91 95",
    "sg:postcode":"6661",
    "sg:province":"Luxembourg",
    "wof:name":"Ets. Dislaire D.",
    "wof:placetype":"venue"
},
  "geometry": {"coordinates":[5.7684588432,50.1475448608],"type":"Point"}
}