{
  "type": "Feature",
  "properties": {
    "iso:country":"BE",
    "sg:address":"Zwaluwstraat 77",
    "sg:city":"Londerzeel (malderen)",
    "sg:classifiers":[
        {
            "category":"Banks & Credit Unions",
            "subcategory":"Investment Brokerage",
            "type":"Services"
        }
    ],
    "sg:phone":"+32 52 33 80 12",
    "sg:postcode":"1840",
    "sg:province":"Vlaams-Brabant",
    "sg:tags":[
        "auditor"
    ],
    "wof:name":"Callaert L",
    "wof:placetype":"venue"
},
  "geometry": {"coordinates":[4.2346410751,51.0120849609],"type":"Point"}
}