{
  "type": "Feature",
  "properties": {
    "iso:country":"BE",
    "sg:address":"Beho 57",
    "sg:city":"Gouvy",
    "sg:orig_category":"Rundveehouders",
    "sg:phone":"+32 80 51 72 84",
    "sg:postcode":"6672",
    "sg:province":"Luxembourg",
    "wof:name":"Jean Noll",
    "wof:placetype":"venue"
},
  "geometry": {"coordinates":[5.9970340729,50.2193603516],"type":"Point"}
}