{
  "type": "Feature",
  "properties": {
    "addr:full":"Meerlestraat 4ba Lummen Limburg 3560",
    "addr:postcode":"3560",
    "addr:street":"Meerlestraat",
    "iso:country":"BE",
    "sg:address":"Meerlestraat 4ba",
    "sg:city":"Lummen",
    "sg:orig_category":"Cr\u00e8ches and garderies d'enfants",
    "sg:phone":"+32 13 53 11 30",
    "sg:postcode":"3560",
    "sg:province":"Limburg",
    "wof:name":"Kribbe 't Sjamajeeke",
    "wof:placetype":"venue"
},
  "geometry": {"coordinates":[5.1867427826,50.9855270386],"type":"Point"}
}