{
  "type": "Feature",
  "properties": {
    "addr:full":"Meulebekestraat 3 Ingelmunster West-Vlaanderen 8770",
    "addr:housenumber":"3",
    "addr:postcode":"8770",
    "addr:street":"Meulebekestraat",
    "iso:country":"BE",
    "sg:address":"Meulebekestraat 3",
    "sg:city":"Ingelmunster",
    "sg:classifiers":[
        {
            "category":"Professional",
            "subcategory":"Lawyer & Legal Services",
            "type":"Services"
        }
    ],
    "sg:phone":"+32 51 31 89 01",
    "sg:postcode":"8770",
    "sg:province":"West-Vlaanderen",
    "sg:tags":[
        "notary"
    ],
    "wof:name":"Vlegels F",
    "wof:placetype":"venue"
},
  "geometry": {"coordinates":[3.2552669048,50.9242172241],"type":"Point"}
}