{
  "type": "Feature",
  "properties": {
    "addr:full":"Chauss\u00c9e De Wavre 455 Etterbeek Bruxelles-Capitale 1040",
    "addr:housenumber":"455",
    "addr:postcode":"1040",
    "addr:street":"Chausse\u0301E De Wavre",
    "iso:country":"BE",
    "sg:address":"Chauss\u00c9e De Wavre 455",
    "sg:city":"Etterbeek",
    "sg:classifiers":[
        {
            "category":"Restaurant",
            "type":"Food & Drink"
        }
    ],
    "sg:phone":"+32 2 649 80 61",
    "sg:postcode":"1040",
    "sg:province":"Bruxelles-Capitale",
    "sg:tags":[
        "caf\u00e9s"
    ],
    "wof:name":"Chez Nicky",
    "wof:placetype":"venue"
},
  "geometry": {"coordinates":[4.3839058876,50.8343734741],"type":"Point"}
}