{
  "type": "Feature",
  "properties": {
    "iso:country":"BE",
    "sg:address":"Vieux Chemin De Braine-le-comte 6",
    "sg:city":"Nivelles",
    "sg:orig_category":"Metaalbehandeling and -bekleding",
    "sg:phone":"+32 67 21 15 39",
    "sg:postcode":"1400",
    "sg:province":"Brabant Wallon",
    "wof:name":"Depreter",
    "wof:placetype":"venue"
},
  "geometry": {"coordinates":[4.3140039444,50.6018943787],"type":"Point"}
}