{
  "type": "Feature",
  "properties": {
    "iso:country":"BE",
    "sg:address":"Avenue De La Fauconnerie 60",
    "sg:city":"Bruxelles (watermael-boitsfort)",
    "sg:classifiers":[
        {
            "category":"Communications",
            "subcategory":"Film & Video Production",
            "type":"Services"
        }
    ],
    "sg:phone":"+32 2 660 54 68",
    "sg:postcode":"1170",
    "sg:province":"Bruxelles-Capitale",
    "sg:tags":[
        "multimedia",
        "-",
        "system"
    ],
    "wof:name":"Computerware Sa",
    "wof:placetype":"venue"
},
  "geometry": {"coordinates":[4.4185538292,50.8028678894],"type":"Point"}
}