{
  "type": "Feature",
  "properties": {
    "addr:full":"Square Jos\u00e9phine-charlotte 21 Bruxelles (woluwe-saint-lambert) Bruxelles-Capitale 1200",
    "addr:housenumber":"21",
    "addr:postcode":"1200",
    "addr:street":"Square Jose\u0301Phine-Charlotte",
    "iso:country":"BE",
    "sg:address":"Square Jos\u00e9phine-charlotte 21",
    "sg:city":"Bruxelles (woluwe-saint-lambert)",
    "sg:classifiers":[
        {
            "category":"Health Services",
            "subcategory":"Doctor",
            "type":"Services"
        }
    ],
    "sg:phone":"+32 2 770 77 69",
    "sg:postcode":"1200",
    "sg:province":"Bruxelles-Capitale",
    "sg:tags":[
        "medicinephysicians",
        "surgeon"
    ],
    "wof:name":"Gillet J M",
    "wof:placetype":"venue"
},
  "geometry": {"coordinates":[4.4134049416,50.8404579163],"type":"Point"}
}