{
  "type": "Feature",
  "properties": {
    "addr:full":"Bosstraat 53 Anzegem (vichte) West-Vlaanderen 8570",
    "addr:housenumber":"53",
    "addr:postcode":"8570",
    "addr:street":"Bosstraat",
    "iso:country":"BE",
    "sg:address":"Bosstraat 53",
    "sg:city":"Anzegem (vichte)",
    "sg:classifiers":[
        {
            "category":"Shopping",
            "subcategory":"Pets & Pet Supplies",
            "type":"Retail Goods"
        }
    ],
    "sg:phone":"+32 56 77 48 77",
    "sg:postcode":"8570",
    "sg:province":"West-Vlaanderen",
    "sg:tags":[
        "shop",
        "-"
    ],
    "wof:name":"Stock Debo Bvba",
    "wof:placetype":"venue"
},
  "geometry": {"coordinates":[3.4123239517,50.8358917236],"type":"Point"}
}