{
  "type": "Feature",
  "properties": {
    "addr:full":"Ijzerenmolenstraat 24 Leuven (heverlee) Vlaams-Brabant 3001",
    "addr:housenumber":"24",
    "addr:postcode":"3001",
    "addr:street":"Ijzerenmolenstraat",
    "iso:country":"BE",
    "sg:address":"Ijzerenmolenstraat 24",
    "sg:city":"Leuven (heverlee)",
    "sg:classifiers":[
        {
            "category":"Bars & Pubs",
            "type":"Food & Drink"
        }
    ],
    "sg:phone":"+32 16 29 62 60",
    "sg:postcode":"3001",
    "sg:province":"Vlaams-Brabant",
    "wof:name":"Ad Libidum",
    "wof:placetype":"venue"
},
  "geometry": {"coordinates":[4.6872930527,50.8721542358],"type":"Point"}
}