{
  "type": "Feature",
  "properties": {
    "iso:country":"BE",
    "sg:address":"Watermanlaan 7",
    "sg:city":"Sint-lambrechts-woluwe/woluwe-saint-lambert",
    "sg:orig_category":"Boekenuitgeverijen",
    "sg:phone":"+32 2 770 93 39",
    "sg:postcode":"1200",
    "sg:province":"Bruxelles-Capitale",
    "wof:name":"Editions Musicales Maurer",
    "wof:placetype":"venue"
},
  "geometry": {"coordinates":[4.4188070297,50.8501014709],"type":"Point"}
}