{
  "type": "Feature",
  "properties": {
    "addr:full":"Koning Albertlaan 20a Neerpelt Limburg 3910",
    "addr:housenumber":"20a",
    "addr:postcode":"3910",
    "addr:street":"Koning Albertlaan",
    "iso:country":"BE",
    "sg:address":"Koning Albertlaan 20a",
    "sg:city":"Neerpelt",
    "sg:classifiers":[
        {
            "category":"Cafe",
            "type":"Food & Drink"
        }
    ],
    "sg:phone":"+32 11 80 25 90",
    "sg:postcode":"3910",
    "sg:province":"Limburg",
    "sg:tags":[
        "snack-bars"
    ],
    "wof:name":"Ali Baba",
    "wof:placetype":"venue"
},
  "geometry": {"coordinates":[5.4308800697,51.2263183594],"type":"Point"}
}