{
  "type": "Feature",
  "properties": {
    "addr:full":"Kartuizersvest 17 B1 Lier Antwerpen 2500",
    "addr:housenumber":"17 b1",
    "addr:postcode":"2500",
    "addr:street":"Kartuizersvest",
    "iso:country":"BE",
    "sg:address":"Kartuizersvest 17 B1",
    "sg:city":"Lier",
    "sg:classifiers":[
        {
            "category":"Restaurant",
            "type":"Food & Drink"
        }
    ],
    "sg:phone":"+32 3 480 77 36",
    "sg:postcode":"2500",
    "sg:province":"Antwerpen",
    "wof:name":"Taverne Den Bezem",
    "wof:placetype":"venue"
},
  "geometry": {"coordinates":[4.5707178116,51.1302833557],"type":"Point"}
}