{
  "type": "Feature",
  "properties": {
    "addr:full":"Rue De Martinsart 8 Sivry-rance Hainaut 6470",
    "addr:housenumber":"8",
    "addr:postcode":"6470",
    "addr:street":"Rue De Martinsart",
    "iso:country":"BE",
    "sg:address":"Rue De Martinsart 8",
    "sg:city":"Sivry-rance",
    "sg:orig_category":"Sportclubs",
    "sg:phone":"+32 60 45 51 62",
    "sg:postcode":"6470",
    "sg:province":"Hainaut",
    "wof:name":"Messager A\u00c9riens +",
    "wof:placetype":"venue"
},
  "geometry": {"coordinates":[4.1946592331,50.1698188782],"type":"Point"}
}