{
  "type": "Feature",
  "properties": {
    "iso:country":"BE",
    "sg:address":"Schupstraat 13",
    "sg:city":"Antwerpen",
    "sg:classifiers":[
        {
            "category":"Insurance",
            "subcategory":"Insurance Agent",
            "type":"Services"
        }
    ],
    "sg:phone":"+32 3 231 48 00",
    "sg:postcode":"2018",
    "sg:province":"Antwerpen",
    "sg:tags":[
        "verzekeringsmakelaars",
        "expert"
    ],
    "wof:name":"Bureau Steinbach",
    "wof:placetype":"venue"
},
  "geometry": {"coordinates":[4.4181981087,51.2143363953],"type":"Point"}
}