{
  "type": "Feature",
  "properties": {
    "iso:country":"BE",
    "sg:address":"Nederzwalmsesteenweg 117",
    "sg:city":"Zingem",
    "sg:classifiers":[
        {
            "category":"Retail",
            "subcategory":"Auto Repair",
            "type":"Services"
        }
    ],
    "sg:phone":"+32 9 384 15 68",
    "sg:postcode":"9750",
    "sg:province":"Oost-Vlaanderen",
    "sg:tags":[
        "garage"
    ],
    "wof:name":"Ghysels Adelin Nv",
    "wof:placetype":"venue"
},
  "geometry": {"coordinates":[3.6633460522,50.8998832703],"type":"Point"}
}