{
  "type": "Feature",
  "properties": {
    "iso:country":"BE",
    "sg:address":"Koolmijnlaan 118",
    "sg:city":"Heusden-zolder (heusden)",
    "sg:classifiers":[
        {
            "category":"Personal",
            "subcategory":"Beauty Salon",
            "type":"Services"
        }
    ],
    "sg:phone":"+32 11 81 15 23",
    "sg:postcode":"3550",
    "sg:province":"Limburg",
    "sg:tags":[
        "lady",
        "-",
        "hairdressing"
    ],
    "wof:name":"Vain's Hairstyling Bvba",
    "wof:placetype":"venue"
},
  "geometry": {"coordinates":[5.3022260666,51.0399398804],"type":"Point"}
}