{
  "type": "Feature",
  "properties": {
    "addr:full":"Rue Elmer 15 Modave (str\u00e9e-lez-huy) Li\u00e8ge 4577",
    "addr:housenumber":"15",
    "addr:postcode":"4577",
    "addr:street":"Rue Elmer;Stre\u0301E-Lez-Huy",
    "iso:country":"BE",
    "sg:address":"Rue Elmer 15",
    "sg:city":"Modave (str\u00e9e-lez-huy)",
    "sg:classifiers":[
        {
            "category":"Health Services",
            "subcategory":"Doctor",
            "type":"Services"
        }
    ],
    "sg:phone":"+32 85 51 33 21",
    "sg:postcode":"4577",
    "sg:province":"Li\u00e8ge",
    "sg:tags":[
        "medicinephysicians",
        "surgeon"
    ],
    "wof:name":"Gillard Christian-victor",
    "wof:placetype":"venue"
},
  "geometry": {"coordinates":[5.2979922295,50.4443855286],"type":"Point"}
}