{
  "type": "Feature",
  "properties": {
    "addr:full":"Kastelein 93 Turnhout Antwerpen 2300",
    "addr:housenumber":"93",
    "addr:postcode":"2300",
    "addr:street":"Kastelein",
    "iso:country":"BE",
    "sg:address":"Kastelein 93",
    "sg:city":"Turnhout",
    "sg:classifiers":[
        {
            "category":"Cafe",
            "type":"Food & Drink"
        }
    ],
    "sg:phone":"+32 14 41 41 91",
    "sg:postcode":"2300",
    "sg:province":"Antwerpen",
    "sg:tags":[
        "caf\u00e9s"
    ],
    "wof:name":"Caf\u00c9 De Paai",
    "wof:placetype":"venue"
},
  "geometry": {"coordinates":[4.9436011314,51.343536377],"type":"Point"}
}