{
  "type": "Feature",
  "properties": {
    "addr:full":"Aannemersstraat 100 Gent Oost-Vlaanderen 9040",
    "addr:housenumber":"100",
    "addr:postcode":"9040",
    "addr:street":"Aannemersstraat;Oost-Vlaanderen",
    "iso:country":"BE",
    "sg:address":"Aannemersstraat 100",
    "sg:city":"Gent",
    "sg:orig_category":"Artsen and specialisten",
    "sg:phone":"+32 9 228 36 50",
    "sg:postcode":"9040",
    "sg:province":"Oost-Vlaanderen",
    "wof:name":"C. De Mild",
    "wof:placetype":"venue"
},
  "geometry": {"coordinates":[3.7487440109,51.0493812561],"type":"Point"}
}