{
  "type": "Feature",
  "properties": {
    "iso:country":"BE",
    "sg:address":"Vierschaar 15",
    "sg:city":"Waasmunster",
    "sg:classifiers":[
        {
            "category":"Banks & Credit Unions",
            "subcategory":"Bank",
            "type":"Services"
        }
    ],
    "sg:phone":"+32 52 46 11 08",
    "sg:postcode":"9170",
    "sg:province":"Oost-Vlaanderen",
    "wof:name":"G\u00e9n\u00e9rale De Banque Sa",
    "wof:placetype":"venue"
},
  "geometry": {"coordinates":[4.0962967873,51.1920547485],"type":"Point"}
}