{
  "type": "Feature",
  "properties": {
    "addr:full":"Westendelaan 317 Middelkerke (westende) West-Vlaanderen 8434",
    "addr:housenumber":"317",
    "addr:postcode":"8434",
    "addr:street":"Westendelaan",
    "iso:country":"BE",
    "sg:address":"Westendelaan 317",
    "sg:city":"Middelkerke (westende)",
    "sg:classifiers":[
        {
            "category":"Shopping",
            "subcategory":"Bicycles & Sporting Goods",
            "type":"Retail Goods"
        }
    ],
    "sg:phone":"+32 58 23 78 65",
    "sg:postcode":"8434",
    "sg:province":"West-Vlaanderen",
    "sg:tags":[
        "-"
    ],
    "wof:name":"Jacobs Bvba",
    "wof:placetype":"venue"
},
  "geometry": {"coordinates":[2.7558889389,51.1391983032],"type":"Point"}
}