{
  "type": "Feature",
  "properties": {
    "addr:full":"Bentincklaan 7 Sint-truiden Limburg 3800",
    "addr:housenumber":"7",
    "addr:postcode":"3800",
    "addr:street":"Bentincklaan",
    "iso:country":"BE",
    "sg:address":"Bentincklaan 7",
    "sg:city":"Sint-truiden",
    "sg:orig_category":"Epiceries",
    "sg:phone":"+32 11 67 37 91",
    "sg:postcode":"3800",
    "sg:province":"Limburg",
    "wof:name":"Philippe Medats",
    "wof:placetype":"venue"
},
  "geometry": {"coordinates":[5.1863641739,50.8153343201],"type":"Point"}
}