{
  "type": "Feature",
  "properties": {
    "iso:country":"BE",
    "sg:address":"Meikloklaan 32",
    "sg:city":"Lille",
    "sg:classifiers":[
        {
            "category":"Shopping",
            "subcategory":"Bicycles & Sporting Goods",
            "type":"Retail Goods"
        }
    ],
    "sg:phone":"+32 14 55 70 36",
    "sg:postcode":"2275",
    "sg:province":"Antwerpen",
    "sg:tags":[
        "article",
        "de",
        "sport",
        "camping"
    ],
    "wof:name":"Blue Vision",
    "wof:placetype":"venue"
},
  "geometry": {"coordinates":[4.8699579239,51.2753562927],"type":"Point"}
}