{
  "type": "Feature",
  "properties": {
    "iso:country":"BE",
    "sg:address":"Malmedyer Strasse 8",
    "sg:city":"B\u00fctgenbach",
    "sg:classifiers":[
        {
            "category":"Retail",
            "subcategory":"Funeral Services",
            "type":"Services"
        }
    ],
    "sg:phone":"+32 80 44 61 44",
    "sg:postcode":"4750",
    "sg:province":"Li\u00e8ge",
    "sg:tags":[
        "director"
    ],
    "wof:name":"Radermacher F-j",
    "wof:placetype":"venue"
},
  "geometry": {"coordinates":[6.2036881447,50.4252090454],"type":"Point"}
}