{
  "type": "Feature",
  "properties": {
    "addr:full":"De Wandstraat 116 Brussel/bruxelles Bruxelles-Capitale 1020",
    "addr:housenumber":"116",
    "addr:postcode":"1020",
    "addr:street":"De Wandstraat;/",
    "iso:country":"BE",
    "sg:address":"De Wandstraat 116",
    "sg:city":"Brussel/bruxelles",
    "sg:orig_category":"Kapsalons",
    "sg:phone":"+32 2 262 39 97",
    "sg:postcode":"1020",
    "sg:province":"Bruxelles-Capitale",
    "wof:name":"Coiffure Bellini",
    "wof:placetype":"venue"
},
  "geometry": {"coordinates":[4.3600621223,50.8997917175],"type":"Point"}
}