{
  "type": "Feature",
  "properties": {
    "iso:country":"BE",
    "sg:address":"Kleinveldweg 3b",
    "sg:city":"Schilde",
    "sg:classifiers":[
        {
            "category":"Banks & Credit Unions",
            "subcategory":"Investment Brokerage",
            "type":"Services"
        }
    ],
    "sg:phone":"+32 3 384 36 83",
    "sg:postcode":"2970",
    "sg:province":"Antwerpen",
    "sg:tags":[
        "repair",
        "-",
        "installation",
        "sanitary",
        "article"
    ],
    "wof:name":"Van Echelpoel L",
    "wof:placetype":"venue"
},
  "geometry": {"coordinates":[4.5839128494,51.2381629944],"type":"Point"}
}