{
  "type": "Feature",
  "properties": {
    "addr:full":"Mechelsesteenweg 136-140 Dendermonde Oost-Vlaanderen 9200",
    "addr:housenumber":"136-140",
    "addr:postcode":"9200",
    "addr:street":"Mechelsesteenweg;Oost-Vlaanderen",
    "iso:country":"BE",
    "sg:address":"Mechelsesteenweg 136-140",
    "sg:city":"Dendermonde",
    "sg:classifiers":[
        {
            "category":"Home & Garden",
            "subcategory":"Furniture",
            "type":"Retail Goods"
        }
    ],
    "sg:phone":"+32 52 22 64 49",
    "sg:postcode":"9200",
    "sg:province":"Oost-Vlaanderen",
    "sg:tags":[
        "small",
        "item",
        "-"
    ],
    "wof:name":"Leen Bakker",
    "wof:placetype":"venue"
},
  "geometry": {"coordinates":[4.1168560982,51.0353431702],"type":"Point"}
}