{
  "type": "Feature",
  "properties": {
    "addr:full":"Oude Holstraat 9 Gent Oost-Vlaanderen 9041",
    "addr:housenumber":"9",
    "addr:postcode":"9041",
    "addr:street":"Oude Holstraat;Oost-Vlaanderen",
    "iso:country":"BE",
    "sg:address":"Oude Holstraat 9",
    "sg:city":"Gent",
    "sg:orig_category":"Salles de conf\u00e9rences and de r\u00e9ceptions",
    "sg:phone":"+32 9 251 39 05",
    "sg:postcode":"9041",
    "sg:province":"Oost-Vlaanderen",
    "wof:name":"Bourgeois",
    "wof:placetype":"venue"
},
  "geometry": {"coordinates":[3.7607729435,51.1016311646],"type":"Point"}
}