{
  "type": "Feature",
  "properties": {
    "addr:full":"Rue Morchamps 99 Seraing Li\u00e8ge 4100",
    "addr:housenumber":"99",
    "addr:postcode":"4100",
    "addr:street":"Rue Morchamps",
    "iso:country":"BE",
    "sg:address":"Rue Morchamps 99",
    "sg:city":"Seraing",
    "sg:classifiers":[
        {
            "category":"Home & Garden",
            "subcategory":"Building Materials",
            "type":"Retail Goods"
        }
    ],
    "sg:phone":"+32 4 233 36 66",
    "sg:postcode":"4100",
    "sg:province":"Li\u00e8ge",
    "sg:tags":[
        "window"
    ],
    "wof:name":"Belgo-ch\u00e2ssis",
    "wof:placetype":"venue"
},
  "geometry": {"coordinates":[5.514854908,50.6024436951],"type":"Point"}
}