{
  "type": "Feature",
  "properties": {
    "iso:country":"BE",
    "sg:address":"Zeebruggelaan 169",
    "sg:city":"Blankenberge",
    "sg:orig_category":"Rundveehouders Varkenskwekers",
    "sg:phone":"+32 50 54 42 47",
    "sg:postcode":"8370",
    "sg:province":"West-Vlaanderen",
    "wof:name":"Herman Fevery",
    "wof:placetype":"venue"
},
  "geometry": {"coordinates":[3.1515600681,51.3109893799],"type":"Point"}
}