{
  "type": "Feature",
  "properties": {
    "iso:country":"BE",
    "sg:address":"Ingooigemstraaat 39",
    "sg:city":"Otegem",
    "sg:orig_category":"Installation de menuiserie en bois and plastique",
    "sg:phone":"+32 56 77 72 40",
    "sg:postcode":"8553",
    "sg:province":"West-Vlaanderen",
    "wof:name":"Vuylsteke",
    "wof:placetype":"venue"
},
  "geometry": {"coordinates":[3.4343800545,50.8101806641],"type":"Point"}
}