{
  "type": "Feature",
  "properties": {
    "iso:country":"BE",
    "sg:address":"Rue De Bomer\u00c9e 107",
    "sg:city":"Charleroi",
    "sg:orig_category":"Artsen and specialisten",
    "sg:phone":"+32 71 47 76 60",
    "sg:postcode":"6032",
    "sg:province":"Hainaut",
    "wof:name":"L. Mallet",
    "wof:placetype":"venue"
},
  "geometry": {"coordinates":[4.3992547989,50.3727836609],"type":"Point"}
}