{
  "type": "Feature",
  "properties": {
    "iso:country":"BE",
    "sg:address":"Knaptandstraat 46",
    "sg:city":"Sint-niklaas",
    "sg:orig_category":"Instituts pour adultes moins valides",
    "sg:phone":"+32 3 776 03 86",
    "sg:postcode":"9100",
    "sg:province":"Oost-Vlaanderen",
    "wof:name":"Dagcentrum St.niklaas",
    "wof:placetype":"venue"
},
  "geometry": {"coordinates":[4.1437768936,51.1597442627],"type":"Point"}
}