{
  "type": "Feature",
  "properties": {
    "iso:country":"BE",
    "sg:address":"De Pretlaan 1",
    "sg:city":"Nevele",
    "sg:orig_category":"Instituts de beaut\u00e9",
    "sg:phone":"+32 9 371 57 72",
    "sg:postcode":"9850",
    "sg:province":"Oost-Vlaanderen",
    "wof:name":"Veronique Ally",
    "wof:placetype":"venue"
},
  "geometry": {"coordinates":[3.5573630333,51.0266685486],"type":"Point"}
}