{
  "type": "Feature",
  "properties": {
    "addr:full":"A. De Coninckstraat 13 Kortenberg Vlaams-Brabant 3070",
    "addr:housenumber":"13",
    "addr:postcode":"3070",
    "addr:street":"A. De Coninckstraat;Vlaams-Brabant",
    "iso:country":"BE",
    "sg:address":"A. De Coninckstraat 13",
    "sg:city":"Kortenberg",
    "sg:classifiers":[
        {
            "category":"Banks & Credit Unions",
            "subcategory":"Financial Services",
            "type":"Services"
        }
    ],
    "sg:phone":"+32 2 756 07 56",
    "sg:postcode":"3070",
    "sg:province":"Vlaams-Brabant",
    "sg:tags":[
        "equipment",
        "blood"
    ],
    "wof:name":"Biotest Seralco Benelux Nv",
    "wof:placetype":"venue"
},
  "geometry": {"coordinates":[4.5202178955,50.885799408],"type":"Point"}
}