{
  "type": "Feature",
  "properties": {
    "iso:country":"BE",
    "sg:address":"Waregemsesteenweg 9",
    "sg:city":"Kruishoutem",
    "sg:classifiers":[
        {
            "category":"Professional",
            "subcategory":"Lawyer & Legal Services",
            "type":"Services"
        }
    ],
    "sg:phone":"+32 9 383 50 80",
    "sg:postcode":"9770",
    "sg:province":"Oost-Vlaanderen",
    "sg:tags":[
        "notary"
    ],
    "wof:name":"Van Caenegem J",
    "wof:placetype":"venue"
},
  "geometry": {"coordinates":[3.5232019424,50.9024772644],"type":"Point"}
}