{
  "type": "Feature",
  "properties": {
    "iso:country":"BE",
    "sg:address":"Ijselaars 12",
    "sg:city":"Nazareth",
    "sg:orig_category":"M\u00e9decins and sp\u00e9cialistes",
    "sg:phone":"+32 9 385 84 44",
    "sg:postcode":"9810",
    "sg:province":"Oost-Vlaanderen",
    "wof:name":"P. Lamoral",
    "wof:placetype":"venue"
},
  "geometry": {"coordinates":[3.6636559963,50.9751052856],"type":"Point"}
}