{
  "type": "Feature",
  "properties": {
    "addr:full":"Rue Z\u00e9phirin Fontaine 111 Binche Hainaut 7130",
    "addr:housenumber":"111",
    "addr:postcode":"7130",
    "addr:street":"Rue Ze\u0301Phirin Fontaine",
    "iso:country":"BE",
    "sg:address":"Rue Z\u00e9phirin Fontaine 111",
    "sg:city":"Binche",
    "sg:classifiers":[
        {
            "category":"Travel",
            "subcategory":"Travel Agent",
            "type":"Entertainment"
        }
    ],
    "sg:phone":"+32 64 31 06 66",
    "sg:postcode":"7130",
    "sg:province":"Hainaut",
    "sg:tags":[
        "agency"
    ],
    "wof:name":"Binche Tourisme-b.t. Tours",
    "wof:placetype":"venue"
},
  "geometry": {"coordinates":[4.1660728455,50.412311554],"type":"Point"}
}