{
  "type": "Feature",
  "properties": {
    "addr:full":"Antwerpsesteenweg 263 Mechelen Antwerpen 2800",
    "addr:housenumber":"263",
    "addr:postcode":"2800",
    "addr:street":"Antwerpsesteenweg",
    "iso:country":"BE",
    "sg:address":"Antwerpsesteenweg 263",
    "sg:city":"Mechelen",
    "sg:classifiers":[
        {
            "category":"Health Services",
            "subcategory":"Doctor",
            "type":"Services"
        }
    ],
    "sg:phone":"+32 3 889 08 35",
    "sg:postcode":"2800",
    "sg:province":"Antwerpen",
    "sg:tags":[
        "orthopedist"
    ],
    "wof:name":"Orthopedie Cuyt Cv",
    "wof:placetype":"venue"
},
  "geometry": {"coordinates":[4.4603271484,51.0583648682],"type":"Point"}
}