{
  "type": "Feature",
  "properties": {
    "iso:country":"BE",
    "sg:address":"Rue Masuy 102",
    "sg:city":"Herstal",
    "sg:orig_category":"Fruitteelt",
    "sg:phone":"+32 4 278 55 70",
    "sg:postcode":"4041",
    "sg:province":"Li\u00e8ge",
    "wof:name":"Louis Tasset",
    "wof:placetype":"venue"
},
  "geometry": {"coordinates":[5.5969791412,50.6878395081],"type":"Point"}
}