{
  "type": "Feature",
  "properties": {
    "addr:full":"Willem Elchotstraat 8 Vilvoorde Vlaams-Brabant 1800",
    "addr:housenumber":"8",
    "addr:postcode":"1800",
    "addr:street":"Willem Elchotstraat",
    "iso:country":"BE",
    "sg:address":"Willem Elchotstraat 8",
    "sg:city":"Vilvoorde",
    "sg:orig_category":"Gestion des d\u00e9charges and sites d\u00e9finitifs de stockage",
    "sg:phone":"+32 2 253 41 29",
    "sg:postcode":"1800",
    "sg:province":"Vlaams-Brabant",
    "wof:name":"Containerpark Vilvoorde",
    "wof:placetype":"venue"
},
  "geometry": {"coordinates":[4.4258608818,50.9269294739],"type":"Point"}
}