{
  "type": "Feature",
  "properties": {
    "addr:full":"Rue Neuve 0 Boussu Hainaut 7300",
    "addr:housenumber":"0",
    "addr:postcode":"7300",
    "addr:street":"Rue Neuve",
    "iso:country":"BE",
    "sg:address":"Rue Neuve 0",
    "sg:city":"Boussu",
    "sg:orig_category":"Meubles D\u00e9taillants, Am\u00e9nagement de B\u00e2timents et de Cuisines",
    "sg:phone":"+32 65 80 38 82",
    "sg:postcode":"7300",
    "sg:province":"Hainaut",
    "wof:name":"Distri Meubles",
    "wof:placetype":"venue"
},
  "geometry": {"coordinates":[3.7952940464,50.4333724976],"type":"Point"}
}