{
  "type": "Feature",
  "properties": {
    "iso:country":"BE",
    "sg:address":"Lepelstraat 81b",
    "sg:city":"Temse (steendorp)",
    "sg:classifiers":[
        {
            "category":"Shopping",
            "subcategory":"Clothing, Apparel, & Fashions",
            "type":"Retail Goods"
        }
    ],
    "sg:phone":"+32 3 744 29 01",
    "sg:postcode":"9140",
    "sg:province":"Oost-Vlaanderen",
    "sg:tags":[
        "supply",
        "material",
        "-",
        "access",
        "ready-made",
        "clothing"
    ],
    "wof:name":"Tex World Bvba",
    "wof:placetype":"venue"
},
  "geometry": {"coordinates":[4.282189846,51.1255912781],"type":"Point"}
}