{
  "type": "Feature",
  "properties": {
    "iso:country":"BE",
    "sg:address":"Burgstraat 41",
    "sg:city":"Destelbergen",
    "sg:classifiers":[
        {
            "category":"Wholesale",
            "subcategory":"Poultry",
            "type":"Manufacturing & Wholesale Goods"
        }
    ],
    "sg:phone":"+32 9 355 55 83",
    "sg:postcode":"9070",
    "sg:province":"Oost-Vlaanderen",
    "sg:tags":[
        "whol",
        "-",
        "egg"
    ],
    "wof:name":"Geiregat Julien",
    "wof:placetype":"venue"
},
  "geometry": {"coordinates":[3.8350229263,51.077293396],"type":"Point"}
}