{
  "type": "Feature",
  "properties": {
    "addr:full":"Stationsstraat 23 Gistel West-Vlaanderen 8470",
    "addr:housenumber":"23",
    "addr:postcode":"8470",
    "addr:street":"Stationsstraat",
    "iso:country":"BE",
    "sg:address":"Stationsstraat 23",
    "sg:city":"Gistel",
    "sg:classifiers":[
        {
            "category":"Manufacturing",
            "subcategory":"Textiles",
            "type":"Manufacturing & Wholesale Goods"
        }
    ],
    "sg:phone":"+32 59 27 80 67",
    "sg:postcode":"8470",
    "sg:province":"West-Vlaanderen",
    "sg:tags":[
        "textiles",
        "v\u00eatements",
        "pour",
        "dame"
    ],
    "wof:name":"Landgraaf Kledingpaleis",
    "wof:placetype":"venue"
},
  "geometry": {"coordinates":[2.9654269218,51.1556167603],"type":"Point"}
}