{
  "type": "Feature",
  "properties": {
    "iso:country":"BE",
    "sg:address":"Rue De Harz\u00e9",
    "sg:city":"La Roche-en-ardenne",
    "sg:classifiers":[
        {
            "category":"Arena",
            "subcategory":"Sports Club",
            "type":"Entertainment"
        }
    ],
    "sg:phone":"+32 84 41 20 19",
    "sg:postcode":"6980",
    "sg:province":"Luxembourg",
    "wof:name":"C.t Laroche",
    "wof:placetype":"venue"
},
  "geometry": {"coordinates":[5.5769147873,50.1882781982],"type":"Point"}
}