{
  "type": "Feature",
  "properties": {
    "addr:full":"Meenseheirweg 163 Roeselare West-Vlaanderen 8800",
    "addr:housenumber":"163",
    "addr:postcode":"8800",
    "addr:street":"Meenseheirweg",
    "iso:country":"BE",
    "sg:address":"Meenseheirweg 163",
    "sg:city":"Roeselare",
    "sg:orig_category":"M\u00e9decins and sp\u00e9cialistes",
    "sg:phone":"+32 51 22 66 99",
    "sg:postcode":"8800",
    "sg:province":"West-Vlaanderen",
    "wof:name":"Th. Decancq",
    "wof:placetype":"venue"
},
  "geometry": {"coordinates":[3.123883009,50.9330024719],"type":"Point"}
}