{
  "type": "Feature",
  "properties": {
    "iso:country":"BE",
    "sg:address":"Beverestraat 3",
    "sg:city":"Oudenaarde",
    "sg:classifiers":[
        {
            "category":"Professional",
            "subcategory":"Art Services",
            "type":"Services"
        }
    ],
    "sg:phone":"+32 55 31 28 55",
    "sg:postcode":"9700",
    "sg:province":"Oost-Vlaanderen",
    "sg:tags":[
        "designer",
        "ontwerpers"
    ],
    "wof:name":"Viviane Lamon",
    "wof:placetype":"venue"
},
  "geometry": {"coordinates":[3.6004550457,50.84815979],"type":"Point"}
}