{
  "type": "Feature",
  "properties": {
    "iso:country":"BE",
    "sg:address":"Poreel 10a",
    "sg:city":"Bi\u00e9v\u00e8ne",
    "sg:classifiers":[
        {
            "category":"Travel",
            "subcategory":"Resort",
            "type":"Entertainment"
        }
    ],
    "sg:phone":"+32 54 58 68 20",
    "sg:postcode":"1547",
    "sg:province":"Vlaams-Brabant",
    "sg:tags":[
        "vacation"
    ],
    "wof:name":"Rosario Bvba",
    "wof:placetype":"venue"
},
  "geometry": {"coordinates":[3.9383170605,50.7172927856],"type":"Point"}
}