{
  "type": "Feature",
  "properties": {
    "iso:country":"BE",
    "sg:address":"Avenue Reine Astrid 128",
    "sg:city":"Verviers (heusy)",
    "sg:classifiers":[
        {
            "category":"Government",
            "subcategory":"Office",
            "type":"Public Place"
        }
    ],
    "sg:phone":"+32 87 23 17 77",
    "sg:postcode":"4802",
    "sg:province":"Li\u00e8ge",
    "sg:tags":[
        "-",
        "tourism",
        "federation"
    ],
    "wof:name":"C.d.f.w.",
    "wof:placetype":"venue"
},
  "geometry": {"coordinates":[5.883038044,50.584564209],"type":"Point"}
}