{
  "type": "Feature",
  "properties": {
    "addr:full":"Goormansdijk 68bb Dessel Antwerpen 2480",
    "addr:housenumber":"68bb",
    "addr:postcode":"2480",
    "addr:street":"Goormansdijk",
    "iso:country":"BE",
    "sg:address":"Goormansdijk 68bb",
    "sg:city":"Dessel",
    "sg:orig_category":"Sportclubs",
    "sg:phone":"+32 14 38 95 70",
    "sg:postcode":"2480",
    "sg:province":"Antwerpen",
    "wof:name":"T.c. De Ridder",
    "wof:placetype":"venue"
},
  "geometry": {"coordinates":[5.1267528534,51.228679657],"type":"Point"}
}