{
  "type": "Feature",
  "properties": {
    "iso:country":"BE",
    "sg:address":"Rue De La Dr\u00c8ve 41",
    "sg:city":"Namur",
    "sg:orig_category":"Boekhouders",
    "sg:phone":"+32 81 74 15 75",
    "sg:postcode":"5003",
    "sg:province":"Namur",
    "wof:name":"Yvonne Bassinne",
    "wof:placetype":"venue"
},
  "geometry": {"coordinates":[4.8473348618,50.4915008545],"type":"Point"}
}