{
  "type": "Feature",
  "properties": {
    "addr:full":"Rue Du Magistrat 49 Bruxelles (ixelles) Bruxelles-Capitale 1050",
    "addr:housenumber":"49",
    "addr:postcode":"1050",
    "addr:street":"Rue Du Magistrat",
    "iso:country":"BE",
    "sg:address":"Rue Du Magistrat 49",
    "sg:city":"Bruxelles (ixelles)",
    "sg:classifiers":[
        {
            "category":"Shopping",
            "subcategory":"Florist",
            "type":"Retail Goods"
        }
    ],
    "sg:phone":"+32 2 649 39 49",
    "sg:postcode":"1050",
    "sg:province":"Bruxelles-Capitale",
    "wof:name":"Boutemy T",
    "wof:placetype":"venue"
},
  "geometry": {"coordinates":[4.3635220528,50.8239707947],"type":"Point"}
}