{
  "type": "Feature",
  "properties": {
    "addr:full":"Klipveldstraat 24 Ukkel/uccle Bruxelles-Capitale 1180",
    "addr:housenumber":"24",
    "addr:postcode":"1180",
    "addr:street":"Klipveldstraat;/",
    "iso:country":"BE",
    "sg:address":"Klipveldstraat 24",
    "sg:city":"Ukkel/uccle",
    "sg:orig_category":"Diverse grafische activiteiten",
    "sg:phone":"+32 2 375 42 28",
    "sg:postcode":"1180",
    "sg:province":"Bruxelles-Capitale",
    "wof:name":"Geminii Graphics",
    "wof:placetype":"venue"
},
  "geometry": {"coordinates":[4.3391270638,50.7984695435],"type":"Point"}
}