{
  "type": "Feature",
  "properties": {
    "iso:country":"BE",
    "sg:address":"Puttestraat 139",
    "sg:city":"Begijnendijk",
    "sg:classifiers":[
        {
            "category":"Manufacturing",
            "subcategory":"Textiles",
            "type":"Manufacturing & Wholesale Goods"
        }
    ],
    "sg:phone":"+32 16 56 16 00",
    "sg:postcode":"3130",
    "sg:province":"Vlaams-Brabant",
    "wof:name":"Luc Verduyckt",
    "wof:placetype":"venue"
},
  "geometry": {"coordinates":[4.7982721329,51.0158729553],"type":"Point"}
}