{
  "type": "Feature",
  "properties": {
    "addr:full":"Rue Des Arzi\u00c8res 24 Froidchapelle Hainaut 6440",
    "addr:housenumber":"24",
    "addr:postcode":"6440",
    "addr:street":"Rue Des Arzie\u0300Res",
    "iso:country":"BE",
    "sg:address":"Rue Des Arzi\u00c8res 24",
    "sg:city":"Froidchapelle",
    "sg:orig_category":"Enseignement maternel and primaire",
    "sg:phone":"+32 60 41 10 54",
    "sg:postcode":"6440",
    "sg:province":"Hainaut",
    "wof:name":"Ecole Fond. Communale",
    "wof:placetype":"venue"
},
  "geometry": {"coordinates":[4.32791996,50.1528816223],"type":"Point"}
}