{
  "type": "Feature",
  "properties": {
    "iso:country":"BE",
    "sg:address":"Rue De L'egalit\u00c9 465",
    "sg:city":"Soumagne",
    "sg:orig_category":"Installation \u00e9lectrique r\u00e9sidentielle",
    "sg:phone":"+32 4 377 43 60",
    "sg:postcode":"4630",
    "sg:province":"Li\u00e8ge",
    "wof:name":"Yves Servais",
    "wof:placetype":"venue"
},
  "geometry": {"coordinates":[5.7469520569,50.6142082214],"type":"Point"}
}