{
  "type": "Feature",
  "properties": {
    "addr:full":"Zevekotestraat 32 Izegem West-Vlaanderen 8870",
    "addr:housenumber":"32",
    "addr:postcode":"8870",
    "addr:street":"Zevekotestraat",
    "iso:country":"BE",
    "sg:address":"Zevekotestraat 32",
    "sg:city":"Izegem",
    "sg:classifiers":[
        {
            "category":"Manufacturing",
            "subcategory":"Textiles",
            "type":"Manufacturing & Wholesale Goods"
        }
    ],
    "sg:phone":"+32 51 30 32 65",
    "sg:postcode":"8870",
    "sg:province":"West-Vlaanderen",
    "wof:name":"Rene Timperman",
    "wof:placetype":"venue"
},
  "geometry": {"coordinates":[3.2293300629,50.9154205322],"type":"Point"}
}