{
  "type": "Feature",
  "properties": {
    "addr:full":"Bedevaartstraat 65 Tielt West-Vlaanderen 8700",
    "addr:housenumber":"65",
    "addr:postcode":"8700",
    "addr:street":"Bedevaartstraat",
    "iso:country":"BE",
    "sg:address":"Bedevaartstraat 65",
    "sg:city":"Tielt",
    "sg:orig_category":"V\u00e9t\u00e9rinaires",
    "sg:phone":"+32 51 40 86 68",
    "sg:postcode":"8700",
    "sg:province":"West-Vlaanderen",
    "wof:name":"B. Vande Vijvere",
    "wof:placetype":"venue"
},
  "geometry": {"coordinates":[3.3327300549,50.9872779846],"type":"Point"}
}