{
  "type": "Feature",
  "properties": {
    "addr:full":"Steenweg Op Turnhout 3 Oud Antwerpen 2360",
    "addr:housenumber":"3",
    "addr:postcode":"2360",
    "addr:street":"Steenweg Op Turnhout",
    "iso:country":"BE",
    "sg:address":"Steenweg Op Turnhout 3",
    "sg:city":"Oud",
    "sg:classifiers":[
        {
            "category":"Banks & Credit Unions",
            "subcategory":"Bank",
            "type":"Services"
        }
    ],
    "sg:phone":"+32 14 42 15 28",
    "sg:postcode":"2360",
    "sg:province":"Antwerpen",
    "wof:name":"Aslk-cger Bank",
    "wof:placetype":"venue"
},
  "geometry": {"coordinates":[4.9804720879,51.3184509277],"type":"Point"}
}