{
  "type": "Feature",
  "properties": {
    "addr:full":"Rue Joseph Scohy 63 Fleurus (brye) Hainaut 6222",
    "addr:housenumber":"63",
    "addr:postcode":"6222",
    "addr:street":"Rue Joseph Scohy",
    "iso:country":"BE",
    "sg:address":"Rue Joseph Scohy 63",
    "sg:city":"Fleurus (brye)",
    "sg:classifiers":[
        {
            "category":"Food & Beverages",
            "subcategory":"Liquor & Beverages",
            "type":"Retail Goods"
        }
    ],
    "sg:phone":"+32 71 81 40 17",
    "sg:postcode":"6222",
    "sg:province":"Hainaut",
    "sg:tags":[
        "-",
        "spirit",
        "wine"
    ],
    "wof:name":"Caves Le Pr\u00e9-clos Sa",
    "wof:placetype":"venue"
},
  "geometry": {"coordinates":[4.5563821793,50.5242080688],"type":"Point"}
}