{
  "type": "Feature",
  "properties": {
    "addr:full":"Roeselarestraat 239z Moorslede West-Vlaanderen 8890",
    "addr:housenumber":"239z",
    "addr:postcode":"8890",
    "addr:street":"Roeselarestraat",
    "iso:country":"BE",
    "sg:address":"Roeselarestraat 239z",
    "sg:city":"Moorslede",
    "sg:orig_category":"V\u00e9hicules automobiles. D\u00e9taillants en pi\u00e8ces and accessoires de voitures",
    "sg:phone":"+32 51 77 25 11",
    "sg:postcode":"8890",
    "sg:province":"West-Vlaanderen",
    "wof:name":"Diesel Bernard",
    "wof:placetype":"venue"
},
  "geometry": {"coordinates":[3.0851690769,50.9219970703],"type":"Point"}
}