{
  "type": "Feature",
  "properties": {
    "iso:country":"BE",
    "sg:address":"Rue Ravenstein 11",
    "sg:city":"Bruxelles-centre",
    "sg:orig_category":"Librairies",
    "sg:phone":"+32 2 511 27 75",
    "sg:postcode":"1000",
    "sg:province":"Bruxelles-Capitale",
    "wof:name":"Peuples Et Continents",
    "wof:placetype":"venue"
},
  "geometry": {"coordinates":[4.3592271805,50.8440284729],"type":"Point"}
}