{
  "type": "Feature",
  "properties": {
    "addr:full":"Louizalaan 250 Brussel/bruxelles Bruxelles-Capitale 1050",
    "addr:housenumber":"250",
    "addr:postcode":"1050",
    "addr:street":"Louizalaan;/",
    "iso:country":"BE",
    "sg:address":"Louizalaan 250",
    "sg:city":"Brussel/bruxelles",
    "sg:orig_category":"Tijdelijke werkgelegenheid and uitzendkantoren",
    "sg:phone":"+32 2 646 30 30",
    "sg:postcode":"1050",
    "sg:province":"Bruxelles-Capitale",
    "wof:name":"R.h.i.-managem. Resources",
    "wof:placetype":"venue"
},
  "geometry": {"coordinates":[4.356962204,50.8341941833],"type":"Point"}
}