{
  "type": "Feature",
  "properties": {
    "addr:full":"Maria Van Hongarijelaan 141 Ganshoren Bruxelles-Capitale 1083",
    "addr:housenumber":"141",
    "addr:postcode":"1083",
    "addr:street":"Maria Van Hongarijelaan",
    "iso:country":"BE",
    "sg:address":"Maria Van Hongarijelaan 141",
    "sg:city":"Ganshoren",
    "sg:orig_category":"Rusthuizen and serviceflats",
    "sg:phone":"+32 2 465 19 31",
    "sg:postcode":"1083",
    "sg:province":"Bruxelles-Capitale",
    "wof:name":"R\u00c9sidence Granvelle",
    "wof:placetype":"venue"
},
  "geometry": {"coordinates":[4.2973132133,50.8725204468],"type":"Point"}
}