{
  "type": "Feature",
  "properties": {
    "iso:country":"BE",
    "sg:address":"E Beernaertstraat 52 B2",
    "sg:city":"Ostende",
    "sg:orig_category":"Loodgieterij, verwarming and sanitaire installaties",
    "sg:phone":"+32 59 43 31 09",
    "sg:postcode":"8400",
    "sg:province":"West-Vlaanderen",
    "wof:name":"New Constructa",
    "wof:placetype":"venue"
},
  "geometry": {"coordinates":[2.9126999378,51.2312583923],"type":"Point"}
}