{
  "type": "Feature",
  "properties": {
    "iso:country":"BE",
    "sg:address":"Rue De Trazegnies 42",
    "sg:city":"Chapelle-lez-herlaimont",
    "sg:orig_category":"Brood, gebak and snoepgoed",
    "sg:phone":"+32 64 44 37 12",
    "sg:postcode":"7160",
    "sg:province":"Hainaut",
    "wof:name":"P\u00c2tisserie Le Dessert",
    "wof:placetype":"venue"
},
  "geometry": {"coordinates":[4.2873039246,50.4670028687],"type":"Point"}
}