{
  "type": "Feature",
  "properties": {
    "addr:full":"Rode Kruislaan 142a Bilzen (grote-spouwen) Limburg 3740",
    "addr:housenumber":"142a",
    "addr:postcode":"3740",
    "addr:street":"Rode Kruislaan",
    "iso:country":"BE",
    "sg:address":"Rode Kruislaan 142a",
    "sg:city":"Bilzen (grote-spouwen)",
    "sg:classifiers":[
        {
            "category":"Professional",
            "subcategory":"Lawyer & Legal Services",
            "type":"Services"
        }
    ],
    "sg:phone":"+32 12 45 39 79",
    "sg:postcode":"3740",
    "sg:province":"Limburg",
    "wof:name":"Deuss Marie-jos\u00e9",
    "wof:placetype":"venue"
},
  "geometry": {"coordinates":[5.5520801544,50.8363609314],"type":"Point"}
}