{
  "type": "Feature",
  "properties": {
    "addr:full":"Rue De Forz\u00e9e 72 Beauraing (feschaux) Namur 5570",
    "addr:housenumber":"72",
    "addr:postcode":"5570",
    "addr:street":"Rue De Forze\u0301E",
    "iso:country":"BE",
    "sg:address":"Rue De Forz\u00e9e 72",
    "sg:city":"Beauraing (feschaux)",
    "sg:classifiers":[
        {
            "category":"Personal",
            "subcategory":"Nail Salon",
            "type":"Services"
        }
    ],
    "sg:phone":"+32 82 74 52 71",
    "sg:postcode":"5570",
    "sg:province":"Namur",
    "sg:tags":[
        "pedicure"
    ],
    "wof:name":"Delay C",
    "wof:placetype":"venue"
},
  "geometry": {"coordinates":[4.9081459045,50.147567749],"type":"Point"}
}