{
  "type": "Feature",
  "properties": {
    "iso:country":"BE",
    "sg:address":"Boulevard Leopold Iii 108",
    "sg:city":"P\u00e9ruwelz",
    "sg:orig_category":"Non-Classified Establishments",
    "sg:phone":"+32 69 77 13 68",
    "sg:postcode":"7600",
    "sg:province":"Hainaut",
    "wof:name":"Delbourg",
    "wof:placetype":"venue"
},
  "geometry": {"coordinates":[3.5971319675,50.5036125183],"type":"Point"}
}