{
  "type": "Feature",
  "properties": {
    "addr:full":"Waaienburgstraat 8 Alveringem West-Vlaanderen 8691",
    "addr:housenumber":"8",
    "addr:postcode":"8691",
    "addr:street":"Waaienburgstraat",
    "iso:country":"BE",
    "sg:address":"Waaienburgstraat 8",
    "sg:city":"Alveringem",
    "sg:orig_category":"Gespecialiseerde residenti\u00eble bouw",
    "sg:phone":"+32 57 30 16 17",
    "sg:postcode":"8691",
    "sg:province":"West-Vlaanderen",
    "wof:name":"Frankie Boury",
    "wof:placetype":"venue"
},
  "geometry": {"coordinates":[2.6589989662,50.9163475037],"type":"Point"}
}