{
  "type": "Feature",
  "properties": {
    "iso:country":"BE",
    "sg:address":"Rue Sur-les-dos 43",
    "sg:city":"Anhee",
    "sg:classifiers":[
        {
            "category":"Professional",
            "subcategory":"Accounting & Tax Preparation",
            "type":"Services"
        }
    ],
    "sg:phone":"+32 71 79 93 44",
    "sg:postcode":"5537",
    "sg:province":"Namur",
    "sg:tags":[
        "accountant"
    ],
    "wof:name":"Georges Pozzi",
    "wof:placetype":"venue"
},
  "geometry": {"coordinates":[4.8107647896,50.343296051],"type":"Point"}
}