{
  "type": "Feature",
  "properties": {
    "addr:full":"Avenue Du Roi 39 Bruxelles (saint-gilles) Bruxelles-Capitale 1060",
    "addr:housenumber":"39",
    "addr:postcode":"1060",
    "addr:street":"Avenue Du Roi",
    "iso:country":"BE",
    "sg:address":"Avenue Du Roi 39",
    "sg:city":"Bruxelles (saint-gilles)",
    "sg:classifiers":[
        {
            "category":"Health Services",
            "subcategory":"Doctor",
            "type":"Services"
        }
    ],
    "sg:phone":"+32 2 538 10 72",
    "sg:postcode":"1060",
    "sg:province":"Bruxelles-Capitale",
    "sg:tags":[
        "medicinephysicians",
        "surgeon"
    ],
    "wof:name":"Clausse M",
    "wof:placetype":"venue"
},
  "geometry": {"coordinates":[4.3333330154,50.8297233582],"type":"Point"}
}