{
  "type": "Feature",
  "properties": {
    "addr:full":"R Pont De Tournay 27 Neuch\u00e2teau Luxembourg 6840",
    "addr:housenumber":"27",
    "addr:postcode":"6840",
    "addr:street":"R Pont De Tournay",
    "iso:country":"BE",
    "sg:address":"R Pont De Tournay 27",
    "sg:city":"Neuch\u00e2teau",
    "sg:classifiers":[
        {
            "category":"Shopping",
            "subcategory":"Hobbies, Toys, & Games",
            "type":"Retail Goods"
        }
    ],
    "sg:phone":"+32 71 35 33 93",
    "sg:postcode":"6840",
    "sg:province":"Luxembourg",
    "sg:tags":[
        "product",
        "miscellaneous",
        "entertainment"
    ],
    "wof:name":"Agepa Sprl",
    "wof:placetype":"venue"
},
  "geometry": {"coordinates":[5.4346451759,49.8411598206],"type":"Point"}
}