{
  "type": "Feature",
  "properties": {
    "addr:full":"Pontweg 57 Gavere (asper) Oost-Vlaanderen 9890",
    "addr:housenumber":"57",
    "addr:postcode":"9890",
    "addr:street":"Pontweg",
    "iso:country":"BE",
    "sg:address":"Pontweg 57",
    "sg:city":"Gavere (asper)",
    "sg:classifiers":[
        {
            "category":"Building & Trades",
            "subcategory":"Plumbing",
            "type":"Services"
        }
    ],
    "sg:phone":"+32 9 384 35 63",
    "sg:postcode":"9890",
    "sg:province":"Oost-Vlaanderen",
    "sg:tags":[
        "repair",
        "mainten",
        "-",
        "central",
        "heating"
    ],
    "wof:name":"Van De Steene J",
    "wof:placetype":"venue"
},
  "geometry": {"coordinates":[3.6394300461,50.9316101074],"type":"Point"}
}