{
  "type": "Feature",
  "properties": {
    "iso:country":"BE",
    "sg:address":"Rue Du G\u00c9n\u00c9ral De Gaulle 118",
    "sg:city":"Courcelles",
    "sg:orig_category":"D\u00e9taillants en pi\u00e8ces and accessoires de voitures",
    "sg:phone":"+32 71 45 66 77",
    "sg:postcode":"6180",
    "sg:province":"Hainaut",
    "wof:name":"Auto Parts Plombier",
    "wof:placetype":"venue"
},
  "geometry": {"coordinates":[4.380795002,50.4566383362],"type":"Point"}
}