{
  "type": "Feature",
  "properties": {
    "addr:full":"80 Halfstraat 2627 Schelle 80",
    "addr:housenumber":"80;80",
    "addr:postcode":"2627",
    "addr:street":"Halfstraat",
    "iso:country":"BE",
    "sg:address":"80",
    "sg:city":"Halfstraat 2627 Schelle",
    "sg:classifiers":[
        {
            "category":"Professional",
            "subcategory":"Advertising",
            "type":"Services"
        }
    ],
    "sg:phone":"+32 3 877 60 35",
    "sg:postcode":"80",
    "sg:tags":[
        "information",
        "medium",
        "communication"
    ],
    "wof:name":"Studio 100 Nv",
    "wof:placetype":"venue"
},
  "geometry": {"coordinates":[4.3753609657,51.1189231873],"type":"Point"}
}