{
  "type": "Feature",
  "properties": {
    "addr:full":"Nati\u00ebnlaan 9 Damme (moerkerke) West-Vlaanderen 8340",
    "addr:housenumber":"9",
    "addr:postcode":"8340",
    "addr:street":"Natie\u0308Nlaan",
    "iso:country":"BE",
    "sg:address":"Nati\u00ebnlaan 9",
    "sg:city":"Damme (moerkerke)",
    "sg:classifiers":[
        {
            "category":"Retail",
            "subcategory":"Auto Rental",
            "type":"Services"
        }
    ],
    "sg:phone":"+32 50 50 10 37",
    "sg:postcode":"8340",
    "sg:province":"West-Vlaanderen",
    "sg:tags":[
        "automobile",
        "-",
        "car",
        "self-drive"
    ],
    "wof:name":"Meerschaert D",
    "wof:placetype":"venue"
},
  "geometry": {"coordinates":[3.3705480099,51.2686576843],"type":"Point"}
}