{
  "type": "Feature",
  "properties": {
    "addr:full":"Langesthal 149 Eupen Li\u00e8ge 4700",
    "addr:housenumber":"149",
    "addr:postcode":"4700",
    "addr:street":"Langesthal",
    "iso:country":"BE",
    "sg:address":"Langesthal 149",
    "sg:city":"Eupen",
    "sg:orig_category":"Elektrische installaties voor woningen",
    "sg:phone":"+32 87 59 16 68",
    "sg:postcode":"4700",
    "sg:province":"Li\u00e8ge",
    "wof:name":"Elektro Schlembach",
    "wof:placetype":"venue"
},
  "geometry": {"coordinates":[6.088039875,50.6166610718],"type":"Point"}
}