{
  "type": "Feature",
  "properties": {
    "iso:country":"BE",
    "sg:address":"Beekhoek 2b",
    "sg:city":"Geel",
    "sg:classifiers":[
        {
            "category":"Health Services",
            "subcategory":"Nursing And Care Facility",
            "type":"Services"
        }
    ],
    "sg:phone":"+32 14 85 90 66",
    "sg:postcode":"2440",
    "sg:province":"Antwerpen",
    "sg:tags":[
        "home"
    ],
    "wof:name":"Vansant K",
    "wof:placetype":"venue"
},
  "geometry": {"coordinates":[4.9905319214,51.2034225464],"type":"Point"}
}