{
  "type": "Feature",
  "properties": {
    "iso:country":"BE",
    "sg:address":"Steenaardestraat 18",
    "sg:city":"Gent (sint-denijs-westrem - Afsnee)",
    "sg:classifiers":[
        {
            "category":"Health Services",
            "subcategory":"Doctor",
            "type":"Services"
        }
    ],
    "sg:phone":"+32 9 280 03 21",
    "sg:postcode":"9051",
    "sg:province":"Oost-Vlaanderen",
    "sg:tags":[
        "medicinephysicians",
        "surgeon"
    ],
    "wof:name":"Dopchie Myriam",
    "wof:placetype":"venue"
},
  "geometry": {"coordinates":[3.6693210602,51.0286102295],"type":"Point"}
}