{
  "type": "Feature",
  "properties": {
    "addr:full":"Rue Du Ch\u00c2teau 3 Andenne Namur 5300",
    "addr:housenumber":"3",
    "addr:postcode":"5300",
    "addr:street":"Rue Du Cha\u0302Teau",
    "iso:country":"BE",
    "sg:address":"Rue Du Ch\u00c2teau 3",
    "sg:city":"Andenne",
    "sg:orig_category":"Kapsalons",
    "sg:phone":"+32 85 82 58 41",
    "sg:postcode":"5300",
    "sg:province":"Namur",
    "wof:name":"Coiffure Sonia",
    "wof:placetype":"venue"
},
  "geometry": {"coordinates":[5.0982642174,50.4863739014],"type":"Point"}
}