{
  "type": "Feature",
  "properties": {
    "addr:full":"Rue Edith Cavell 23 Bruxelles (uccle) Bruxelles-Capitale 1180",
    "addr:housenumber":"23",
    "addr:postcode":"1180",
    "addr:street":"Rue Edith Cavell",
    "iso:country":"BE",
    "sg:address":"Rue Edith Cavell 23",
    "sg:city":"Bruxelles (uccle)",
    "sg:classifiers":[
        {
            "category":"Health Services",
            "subcategory":"Health Practitioner",
            "type":"Services"
        }
    ],
    "sg:phone":"+32 2 344 69 68",
    "sg:postcode":"1180",
    "sg:province":"Bruxelles-Capitale",
    "sg:tags":[
        "physiotherapist"
    ],
    "wof:name":"Moens M",
    "wof:placetype":"venue"
},
  "geometry": {"coordinates":[4.3565402031,50.813205719],"type":"Point"}
}