{
  "type": "Feature",
  "properties": {
    "addr:full":"Cit\u00e9 Lallemand 62 Bastogne Luxembourg 6600",
    "addr:housenumber":"62",
    "addr:postcode":"6600",
    "addr:street":"Cite\u0301 Lallemand",
    "iso:country":"BE",
    "sg:address":"Cit\u00e9 Lallemand 62",
    "sg:city":"Bastogne",
    "sg:classifiers":[
        {
            "category":"Wholesale",
            "subcategory":"Scrap",
            "type":"Manufacturing & Wholesale Goods"
        }
    ],
    "sg:phone":"+32 61 21 26 45",
    "sg:postcode":"6600",
    "sg:province":"Luxembourg",
    "sg:tags":[
        "metal"
    ],
    "wof:name":"Monsieur Roger Vandendyck",
    "wof:placetype":"venue"
},
  "geometry": {"coordinates":[5.7143440247,50.0068092346],"type":"Point"}
}