{
  "type": "Feature",
  "properties": {
    "addr:full":"Kachtemsestraat 1 Izegem West-Vlaanderen 8870",
    "addr:housenumber":"1",
    "addr:postcode":"8870",
    "addr:street":"Kachtemsestraat",
    "iso:country":"BE",
    "sg:address":"Kachtemsestraat 1",
    "sg:city":"Izegem",
    "sg:orig_category":"Enseignement maternel and primaire",
    "sg:phone":"+32 51 30 51 97",
    "sg:postcode":"8870",
    "sg:province":"West-Vlaanderen",
    "wof:name":"Vrije Kleuterschool",
    "wof:placetype":"venue"
},
  "geometry": {"coordinates":[3.2135870457,50.9275512695],"type":"Point"}
}