{
  "type": "Feature",
  "properties": {
    "addr:full":"Dokter Carlierlaan 13 Aalst (erembodegem) Oost-Vlaanderen 9320",
    "addr:housenumber":"13",
    "addr:postcode":"9320",
    "addr:street":"Dokter Carlierlaan",
    "iso:country":"BE",
    "sg:address":"Dokter Carlierlaan 13",
    "sg:city":"Aalst (erembodegem)",
    "sg:classifiers":[
        {
            "category":"Food & Beverages",
            "subcategory":"Dairy",
            "type":"Retail Goods"
        }
    ],
    "sg:phone":"+32 53 77 20 78",
    "sg:postcode":"9320",
    "sg:province":"Oost-Vlaanderen",
    "sg:tags":[
        "product",
        "-"
    ],
    "wof:name":"Ledegen M",
    "wof:placetype":"venue"
},
  "geometry": {"coordinates":[4.0553851128,50.9209976196],"type":"Point"}
}