{
  "type": "Feature",
  "properties": {
    "addr:full":"Karel Keymolenstraat 35 Lennik (sint-kwintens-lennik) Vlaams-Brabant 1750",
    "addr:housenumber":"35",
    "addr:postcode":"1750",
    "addr:street":"Karel Keymolenstraat",
    "iso:country":"BE",
    "sg:address":"Karel Keymolenstraat 35",
    "sg:city":"Lennik (sint-kwintens-lennik)",
    "sg:classifiers":[
        {
            "category":"Education",
            "subcategory":"School",
            "type":"Public Place"
        }
    ],
    "sg:phone":"+32 2 532 45 18",
    "sg:postcode":"1750",
    "sg:province":"Vlaams-Brabant",
    "sg:tags":[
        "secondary"
    ],
    "wof:name":"Middenschool Sigo Van Het Gemeenschapsonderwijs Lennik St-pieters-leeuw",
    "wof:placetype":"venue"
},
  "geometry": {"coordinates":[4.1516680717,50.8077201843],"type":"Point"}
}