{
  "type": "Feature",
  "properties": {
    "iso:country":"BE",
    "sg:address":"Chemin De La Valli\u00c8re 16",
    "sg:city":"Mons",
    "sg:orig_category":"M\u00e9decins and sp\u00e9cialistes",
    "sg:phone":"+32 65 35 38 67",
    "sg:postcode":"7000",
    "sg:province":"Hainaut",
    "wof:name":"P. Cauchies",
    "wof:placetype":"venue"
},
  "geometry": {"coordinates":[3.9476230145,50.442024231],"type":"Point"}
}