{
  "type": "Feature",
  "properties": {
    "addr:full":"Avenue Du Centenaire 14 Chaudfontaine Li\u00e8ge 4053",
    "addr:housenumber":"14",
    "addr:postcode":"4053",
    "addr:street":"Avenue Du Centenaire",
    "iso:country":"BE",
    "sg:address":"Avenue Du Centenaire 14",
    "sg:city":"Chaudfontaine",
    "sg:classifiers":[
        {
            "category":"Health Services",
            "subcategory":"Nursing And Care Facility",
            "type":"Services"
        }
    ],
    "sg:phone":"+32 4 361 54 11",
    "sg:postcode":"4053",
    "sg:province":"Li\u00e8ge",
    "sg:tags":[
        "public"
    ],
    "wof:name":"Administration Communale",
    "wof:placetype":"venue"
},
  "geometry": {"coordinates":[5.6116127968,50.5931091309],"type":"Point"}
}