{
  "type": "Feature",
  "properties": {
    "iso:country":"BE",
    "sg:address":"Grand'rue 75",
    "sg:city":"Chi\u00e8vres",
    "sg:classifiers":[
        {
            "category":"Bars & Pubs",
            "type":"Food & Drink"
        }
    ],
    "sg:phone":"+32 68 65 91 10",
    "sg:postcode":"7950",
    "sg:province":"Hainaut",
    "wof:name":"Arlequin (l')",
    "wof:placetype":"venue"
},
  "geometry": {"coordinates":[3.8079679012,50.587223053],"type":"Point"}
}