{
  "type": "Feature",
  "properties": {
    "addr:full":"Rue E. Banning 130 Elsene/ixelles Bruxelles-Capitale 1050",
    "addr:housenumber":"130",
    "addr:postcode":"1050",
    "addr:street":"Rue E. Banning",
    "iso:country":"BE",
    "sg:address":"Rue E. Banning 130",
    "sg:city":"Elsene/ixelles",
    "sg:orig_category":"Antiquit\u00e9s",
    "sg:phone":"+32 2 648 09 35",
    "sg:postcode":"1050",
    "sg:province":"Bruxelles-Capitale",
    "wof:name":"Klinger",
    "wof:placetype":"venue"
},
  "geometry": {"coordinates":[4.381125927,50.8178825378],"type":"Point"}
}