{
  "type": "Feature",
  "properties": {
    "iso:country":"BE",
    "sg:address":"Reigerstraat 7",
    "sg:city":"Lommel",
    "sg:orig_category":"Activit\u00e9s d\u00b4action sociale sans h\u00e9bergement",
    "sg:phone":"+32 11 54 36 75",
    "sg:postcode":"3920",
    "sg:province":"Limburg",
    "wof:name":"Rode Kruis Lommel",
    "wof:placetype":"venue"
},
  "geometry": {"coordinates":[5.2968449593,51.2259483337],"type":"Point"}
}