{
  "type": "Feature",
  "properties": {
    "addr:full":"Rue Haute Claire 12c Herstal Li\u00e8ge 4040",
    "addr:housenumber":"12c",
    "addr:postcode":"4040",
    "addr:street":"Rue Haute Claire",
    "iso:country":"BE",
    "sg:address":"Rue Haute Claire 12c",
    "sg:city":"Herstal",
    "sg:classifiers":[
        {
            "category":"Social Services",
            "subcategory":"Job Training",
            "type":"Services"
        }
    ],
    "sg:phone":"+32 4 278 11 75",
    "sg:postcode":"4040",
    "sg:province":"Li\u00e8ge",
    "sg:tags":[
        "condiment",
        "spice"
    ],
    "wof:name":"Li\u00e9geoise (conserverie La)",
    "wof:placetype":"venue"
},
  "geometry": {"coordinates":[5.6249542236,50.6575317383],"type":"Point"}
}