{
  "type": "Feature",
  "properties": {
    "addr:full":"Kastanjelaan 1 Nijlen Antwerpen 2560",
    "addr:housenumber":"1",
    "addr:postcode":"2560",
    "addr:street":"Kastanjelaan",
    "iso:country":"BE",
    "sg:address":"Kastanjelaan 1",
    "sg:city":"Nijlen",
    "sg:classifiers":[
        {
            "category":"Autos & Motor Vehicles",
            "subcategory":"Fuel & Gas Station",
            "type":"Retail Goods"
        }
    ],
    "sg:phone":"+32 3 480 70 46",
    "sg:postcode":"2560",
    "sg:province":"Antwerpen",
    "sg:tags":[
        "stations-service",
        "carburants"
    ],
    "wof:name":"Eduard Vercammen",
    "wof:placetype":"venue"
},
  "geometry": {"coordinates":[4.6072430611,51.1477394104],"type":"Point"}
}