{
  "type": "Feature",
  "properties": {
    "addr:full":"Rue Albert Poup\u00e9 17 Ramillies (geest-g\u00e9rompont-petit-rosi\u00e8re) Brabant Wallon 1367",
    "addr:housenumber":"17",
    "addr:postcode":"1367",
    "addr:street":"Rue Albert Poupe\u0301;Wallon",
    "iso:country":"BE",
    "sg:address":"Rue Albert Poup\u00e9 17",
    "sg:city":"Ramillies (geest-g\u00e9rompont-petit-rosi\u00e8re)",
    "sg:classifiers":[
        {
            "category":"Airport",
            "subcategory":"International",
            "type":"Transportation"
        }
    ],
    "sg:phone":"+32 81 74 85 85",
    "sg:postcode":"1367",
    "sg:province":"Brabant Wallon",
    "sg:tags":[
        "-",
        "transport"
    ],
    "wof:name":"Alain Debrux Transports Sprl",
    "wof:placetype":"venue"
},
  "geometry": {"coordinates":[4.8935709,50.6546401978],"type":"Point"}
}