{
  "type": "Feature",
  "properties": {
    "addr:full":"Blauwstraat 66 Boom Antwerpen 2850",
    "addr:housenumber":"66",
    "addr:postcode":"2850",
    "addr:street":"Blauwstraat",
    "iso:country":"BE",
    "sg:address":"Blauwstraat 66",
    "sg:city":"Boom",
    "sg:orig_category":"Plomberie, chauffage and installations sanitaires",
    "sg:phone":"+32 3 888 40 05",
    "sg:postcode":"2850",
    "sg:province":"Antwerpen",
    "wof:name":"Jan Van Houwenis",
    "wof:placetype":"venue"
},
  "geometry": {"coordinates":[4.3685150146,51.0865402222],"type":"Point"}
}