{
  "type": "Feature",
  "properties": {
    "addr:full":"Gevaertlaan 180 Westerlo Antwerpen 2260",
    "addr:housenumber":"180",
    "addr:postcode":"2260",
    "addr:street":"Gevaertlaan",
    "iso:country":"BE",
    "sg:address":"Gevaertlaan 180",
    "sg:city":"Westerlo",
    "sg:orig_category":"M\u00e9decins and sp\u00e9cialistes",
    "sg:phone":"+32 16 69 80 82",
    "sg:postcode":"2260",
    "sg:province":"Antwerpen",
    "wof:name":"Ludo Draulans",
    "wof:placetype":"venue"
},
  "geometry": {"coordinates":[4.8500199318,51.0872497559],"type":"Point"}
}