{
  "type": "Feature",
  "properties": {
    "addr:full":"Boulevard Emile Bockstael 169 Bruxelles Bruxelles-Capitale 1020",
    "addr:housenumber":"169",
    "addr:postcode":"1020",
    "addr:street":"Boulevard Emile Bockstael",
    "iso:country":"BE",
    "sg:address":"Boulevard Emile Bockstael 169",
    "sg:city":"Bruxelles",
    "sg:classifiers":[
        {
            "category":"Professional",
            "subcategory":"Testing Lab",
            "type":"Services"
        }
    ],
    "sg:phone":"+32 2 426 47 22",
    "sg:postcode":"1020",
    "sg:province":"Bruxelles-Capitale",
    "sg:tags":[
        "chemist"
    ],
    "wof:name":"Schartz C",
    "wof:placetype":"venue"
},
  "geometry": {"coordinates":[4.3480958939,50.8751678467],"type":"Point"}
}