{
  "type": "Feature",
  "properties": {
    "iso:country":"BE",
    "sg:address":"Jozef Cardijnstraat 11",
    "sg:city":"Pittem",
    "sg:orig_category":"Gespecialiseerde residenti\u00eble bouw Installatie van metalen schrijnwerk",
    "sg:phone":"+32 51 46 78 12",
    "sg:postcode":"8740",
    "sg:province":"West-Vlaanderen",
    "wof:name":"Herman Descheemaeker",
    "wof:placetype":"venue"
},
  "geometry": {"coordinates":[3.2561080456,50.9949836731],"type":"Point"}
}