{
  "type": "Feature",
  "properties": {
    "addr:full":"Knaptandstraat 9-11 Lokeren Oost-Vlaanderen 9160",
    "addr:housenumber":"9-11",
    "addr:postcode":"9160",
    "addr:street":"Knaptandstraat",
    "iso:country":"BE",
    "sg:address":"Knaptandstraat 9-11",
    "sg:city":"Lokeren",
    "sg:classifiers":[
        {
            "category":"Health Services",
            "subcategory":"Doctor",
            "type":"Services"
        }
    ],
    "sg:phone":"+32 9 348 61 31",
    "sg:postcode":"9160",
    "sg:province":"Oost-Vlaanderen",
    "sg:tags":[
        "medicinephysicians",
        "surgeon"
    ],
    "wof:name":"De Clercq Dirk",
    "wof:placetype":"venue"
},
  "geometry": {"coordinates":[3.9841170311,51.1009635925],"type":"Point"}
}