{
  "type": "Feature",
  "properties": {
    "iso:country":"BE",
    "sg:address":"Nieuwstraat 35",
    "sg:city":"Geel",
    "sg:orig_category":"Schoenen",
    "sg:phone":"+32 14 58 84 33",
    "sg:postcode":"2440",
    "sg:province":"Antwerpen",
    "wof:name":"Shoes In The Box",
    "wof:placetype":"venue"
},
  "geometry": {"coordinates":[4.9928388596,51.1628303528],"type":"Point"}
}