{
  "type": "Feature",
  "properties": {
    "iso:country":"BE",
    "sg:address":"Schrieksebaan 66",
    "sg:city":"Keerbergen",
    "sg:classifiers":[
        {
            "category":"Shopping",
            "subcategory":"Bicycles & Sporting Goods",
            "type":"Retail Goods"
        }
    ],
    "sg:phone":"+32 15 23 53 24",
    "sg:postcode":"3140",
    "sg:province":"Vlaams-Brabant",
    "sg:tags":[
        "article",
        "de",
        "sport",
        "camping"
    ],
    "wof:name":"Willy Vanbegin",
    "wof:placetype":"venue"
},
  "geometry": {"coordinates":[4.6542048454,51.0096664429],"type":"Point"}
}