{
  "type": "Feature",
  "properties": {
    "addr:full":"Leuvensebaan 472 Tienen Vlaams-Brabant 3300",
    "addr:housenumber":"472",
    "addr:postcode":"3300",
    "addr:street":"Leuvensebaan",
    "iso:country":"BE",
    "sg:address":"Leuvensebaan 472",
    "sg:city":"Tienen",
    "sg:orig_category":"Sportterreinen and installaties behalve sportcentra",
    "sg:phone":"+32 16 82 46 46",
    "sg:postcode":"3300",
    "sg:province":"Vlaams-Brabant",
    "wof:name":"Acro",
    "wof:placetype":"venue"
},
  "geometry": {"coordinates":[4.9067468643,50.8170204163],"type":"Point"}
}