{
  "type": "Feature",
  "properties": {
    "addr:full":"Stationlaan 53 Bilzen Limburg 3740",
    "addr:housenumber":"53",
    "addr:postcode":"3740",
    "addr:street":"Stationlaan",
    "iso:country":"BE",
    "sg:address":"Stationlaan 53",
    "sg:city":"Bilzen",
    "sg:classifiers":[
        {
            "category":"Shopping",
            "subcategory":"Clothing, Apparel, & Fashions",
            "type":"Retail Goods"
        }
    ],
    "sg:phone":"+32 89 51 19 03",
    "sg:postcode":"3740",
    "sg:province":"Limburg",
    "sg:tags":[
        "boutique"
    ],
    "wof:name":"Spiegelmode Dames Bvba",
    "wof:placetype":"venue"
},
  "geometry": {"coordinates":[5.5104250908,50.8687934875],"type":"Point"}
}