{
  "type": "Feature",
  "properties": {
    "addr:full":"Hulleken 10 A Evergem Oost-Vlaanderen 9940",
    "addr:housenumber":"10 a",
    "addr:postcode":"9940",
    "addr:street":"Hulleken;Oost-Vlaanderen",
    "iso:country":"BE",
    "sg:address":"Hulleken 10 A",
    "sg:city":"Evergem",
    "sg:orig_category":"HERSTELLING ELEKTRISCHE HUISHOUDAPPARATEN Telecommunicatiesystemen",
    "sg:phone":"+32 9 253 81 95",
    "sg:postcode":"9940",
    "sg:province":"Oost-Vlaanderen",
    "wof:name":"Ames Tracking",
    "wof:placetype":"venue"
},
  "geometry": {"coordinates":[3.6819419861,51.1195335388],"type":"Point"}
}