{
  "type": "Feature",
  "properties": {
    "addr:full":"Schoenerstraat 7 Gent Oost-Vlaanderen 9000",
    "addr:housenumber":"7",
    "addr:postcode":"9000",
    "addr:street":"Schoenerstraat;Oost-Vlaanderen",
    "iso:country":"BE",
    "sg:address":"Schoenerstraat 7",
    "sg:city":"Gent",
    "sg:orig_category":"Dakwerken",
    "sg:phone":"+32 9 253 88 02",
    "sg:postcode":"9000",
    "sg:province":"Oost-Vlaanderen",
    "wof:name":"Eddy De Vliegher",
    "wof:placetype":"venue"
},
  "geometry": {"coordinates":[3.7217020988,51.0891914368],"type":"Point"}
}