{
  "type": "Feature",
  "properties": {
    "iso:country":"BE",
    "sg:address":"Rue Marie-th\u00c9r\u00c8se 53",
    "sg:city":"Sint-joost-ten-node/saint-josse-ten-noode",
    "sg:orig_category":"Mat\u00e9riel m\u00e9dical and orthop\u00e9dique and proth\u00e8ses Fab",
    "sg:phone":"+32 2 230 39 68",
    "sg:postcode":"1210",
    "sg:province":"Bruxelles-Capitale",
    "wof:name":"Labo Van Dijck Fr\u00c8res",
    "wof:placetype":"venue"
},
  "geometry": {"coordinates":[4.3727121353,50.8478851318],"type":"Point"}
}