{
  "type": "Feature",
  "properties": {
    "addr:full":"Vierhekkenstraat 19 Gent Oost-Vlaanderen 9031",
    "addr:housenumber":"19",
    "addr:postcode":"9031",
    "addr:street":"Vierhekkenstraat;Oost-Vlaanderen",
    "iso:country":"BE",
    "sg:address":"Vierhekkenstraat 19",
    "sg:city":"Gent",
    "sg:orig_category":"Sportclubs",
    "sg:phone":"+32 9 226 75 43",
    "sg:postcode":"9031",
    "sg:province":"Oost-Vlaanderen",
    "wof:name":"Veloclub Drongen Centrum",
    "wof:placetype":"venue"
},
  "geometry": {"coordinates":[3.6626720428,51.0511627197],"type":"Point"}
}