{
  "type": "Feature",
  "properties": {
    "iso:country":"BE",
    "sg:address":"Rue Du Sacr\u00c9-coeur 7ba",
    "sg:city":"Ciney",
    "sg:orig_category":"Bouwwerktuigen Gh",
    "sg:phone":"+32 83 21 51 62",
    "sg:postcode":"5590",
    "sg:province":"Namur",
    "wof:name":"Leignon-travaux",
    "wof:placetype":"venue"
},
  "geometry": {"coordinates":[5.1232829094,50.2803497314],"type":"Point"}
}