{
  "type": "Feature",
  "properties": {
    "addr:full":"Brugsesteenweg 153 Gent Oost-Vlaanderen 9000",
    "addr:housenumber":"153",
    "addr:postcode":"9000",
    "addr:street":"Brugsesteenweg;Oost-Vlaanderen",
    "iso:country":"BE",
    "sg:address":"Brugsesteenweg 153",
    "sg:city":"Gent",
    "sg:classifiers":[
        {
            "category":"Bars & Pubs",
            "type":"Food & Drink"
        }
    ],
    "sg:phone":"+32 9 227 81 26",
    "sg:postcode":"9000",
    "sg:province":"Oost-Vlaanderen",
    "wof:name":"De Paardekop",
    "wof:placetype":"venue"
},
  "geometry": {"coordinates":[3.6919870377,51.0644683838],"type":"Point"}
}