{
  "type": "Feature",
  "properties": {
    "addr:full":"Langendijk 37 Heist-op-den-berg Antwerpen 2222",
    "addr:housenumber":"37",
    "addr:postcode":"2222",
    "addr:street":"Langendijk",
    "iso:country":"BE",
    "sg:address":"Langendijk 37",
    "sg:city":"Heist-op-den-berg",
    "sg:orig_category":"V\u00eatements pour b\u00e9b\u00e9s and enfants",
    "sg:phone":"+32 15 24 76 95",
    "sg:postcode":"2222",
    "sg:province":"Antwerpen",
    "wof:name":"Horemans",
    "wof:placetype":"venue"
},
  "geometry": {"coordinates":[4.7292399406,51.1032218933],"type":"Point"}
}