{
  "type": "Feature",
  "properties": {
    "iso:country":"BE",
    "sg:address":"Rue Jules Des Essarts 103",
    "sg:city":"Chatelet",
    "sg:classifiers":[
        {
            "category":"Restaurant",
            "type":"Food & Drink"
        }
    ],
    "sg:phone":"+32 71 38 01 17",
    "sg:postcode":"6200",
    "sg:province":"Hainaut",
    "sg:tags":[
        "caf\u00e9s"
    ],
    "wof:name":"Taverne Le Golden Mike",
    "wof:placetype":"venue"
},
  "geometry": {"coordinates":[4.5188889503,50.4170875549],"type":"Point"}
}