{
  "type": "Feature",
  "properties": {
    "addr:full":"Rue Henri Bl\u00e8s 118 Namur Namur 5000",
    "addr:housenumber":"118",
    "addr:postcode":"5000",
    "addr:street":"Rue Henri Ble\u0300S",
    "iso:country":"BE",
    "sg:address":"Rue Henri Bl\u00e8s 118",
    "sg:city":"Namur",
    "sg:classifiers":[
        {
            "category":"Health Services",
            "subcategory":"Doctor",
            "type":"Services"
        }
    ],
    "sg:phone":"+32 81 73 63 65",
    "sg:postcode":"5000",
    "sg:province":"Namur",
    "sg:tags":[
        "medicinephysicians",
        "surgeon"
    ],
    "wof:name":"Manil G",
    "wof:placetype":"venue"
},
  "geometry": {"coordinates":[4.8422999382,50.4653358459],"type":"Point"}
}