{
  "type": "Feature",
  "properties": {
    "iso:country":"BE",
    "sg:address":"Lindeweg 20",
    "sg:city":"Zoutleeuw",
    "sg:orig_category":"Woningbouw",
    "sg:phone":"+32 11 78 29 97",
    "sg:postcode":"3440",
    "sg:province":"Vlaams-Brabant",
    "wof:name":"Biobouw",
    "wof:placetype":"venue"
},
  "geometry": {"coordinates":[5.1344881058,50.8490829468],"type":"Point"}
}