{
  "type": "Feature",
  "properties": {
    "addr:full":"Nieuwstraat 36 Vorselaar Antwerpen 2290",
    "addr:housenumber":"36",
    "addr:postcode":"2290",
    "addr:street":"Nieuwstraat",
    "iso:country":"BE",
    "sg:address":"Nieuwstraat 36",
    "sg:city":"Vorselaar",
    "sg:classifiers":[
        {
            "category":"Sports & Exercise",
            "subcategory":"Gym",
            "type":"Entertainment"
        }
    ],
    "sg:phone":"+32 14 50 24 78",
    "sg:postcode":"2290",
    "sg:province":"Antwerpen",
    "sg:tags":[
        "fitness"
    ],
    "wof:name":"Sportmedische Studio Olympia Bvba",
    "wof:placetype":"venue"
},
  "geometry": {"coordinates":[4.7780079842,51.2020378113],"type":"Point"}
}