{
  "type": "Feature",
  "properties": {
    "iso:country":"BE",
    "sg:address":"Wegvoeringstraat 31",
    "sg:city":"Wetteren",
    "sg:orig_category":"Non-Classified Establishments",
    "sg:phone":"+32 9 369 88 92",
    "sg:postcode":"9230",
    "sg:province":"Oost-Vlaanderen",
    "wof:name":"Bretex Bvba",
    "wof:placetype":"venue"
},
  "geometry": {"coordinates":[3.8881471157,51.00756073],"type":"Point"}
}