{
  "type": "Feature",
  "properties": {
    "addr:full":"Chaussee De Waterloo 1222 Uccle Bruxelles-Capitale 1180",
    "addr:housenumber":"1222",
    "addr:postcode":"1180",
    "addr:street":"Chaussee De Waterloo",
    "iso:country":"BE",
    "sg:address":"Chaussee De Waterloo 1222",
    "sg:city":"Uccle",
    "sg:orig_category":"Royal Canin",
    "sg:phone":"+32 2 375 16 53",
    "sg:postcode":"1180",
    "sg:province":"Bruxelles-Capitale",
    "wof:name":"M.navez",
    "wof:placetype":"venue"
},
  "geometry": {"coordinates":[4.3739352226,50.7943572998],"type":"Point"}
}