{
  "type": "Feature",
  "properties": {
    "iso:country":"BE",
    "sg:address":"Ter Meerenlaan 3",
    "sg:city":"Destelbergen",
    "sg:classifiers":[
        {
            "category":"Arena",
            "subcategory":"Sports Club",
            "type":"Entertainment"
        }
    ],
    "sg:phone":"+32 9 228 27 01",
    "sg:postcode":"9070",
    "sg:province":"Oost-Vlaanderen",
    "sg:tags":[
        "terrain",
        "hors",
        "de",
        "installation",
        "sportifs"
    ],
    "wof:name":"S.k. Verbr. Oostakker",
    "wof:placetype":"venue"
},
  "geometry": {"coordinates":[3.7786200047,51.0554733276],"type":"Point"}
}