{
  "type": "Feature",
  "properties": {
    "iso:country":"BE",
    "sg:address":"Leynseelstraat 96",
    "sg:city":"Avelgem",
    "sg:classifiers":[
        {
            "category":"Building & Trades",
            "subcategory":"Equipment Rental",
            "type":"Services"
        }
    ],
    "sg:phone":"+32 56 64 84 44",
    "sg:postcode":"8580",
    "sg:province":"West-Vlaanderen",
    "sg:tags":[
        "sound",
        "-",
        "system"
    ],
    "wof:name":"Joy Events",
    "wof:placetype":"venue"
},
  "geometry": {"coordinates":[3.4286460876,50.7766342163],"type":"Point"}
}