{
  "type": "Feature",
  "properties": {
    "addr:full":"Avenue De Spa 19 Verviers Li\u00e8ge 4800",
    "addr:housenumber":"19",
    "addr:postcode":"4800",
    "addr:street":"Avenue De Spa",
    "iso:country":"BE",
    "sg:address":"Avenue De Spa 19",
    "sg:city":"Verviers",
    "sg:orig_category":"Belastingconsulenten Diverse juridische dienstverlening",
    "sg:phone":"+32 87 22 25 48",
    "sg:postcode":"4800",
    "sg:province":"Li\u00e8ge",
    "wof:name":"Lince J.",
    "wof:placetype":"venue"
},
  "geometry": {"coordinates":[5.8632698059,50.5830230713],"type":"Point"}
}