{
  "type": "Feature",
  "properties": {
    "addr:full":"Burgemeester Heymansplein 13 Beringen (beverlo) Limburg 3581",
    "addr:housenumber":"13",
    "addr:postcode":"3581",
    "addr:street":"Burgemeester Heymansplein",
    "iso:country":"BE",
    "sg:address":"Burgemeester Heymansplein 13",
    "sg:city":"Beringen (beverlo)",
    "sg:classifiers":[
        {
            "category":"Professional",
            "subcategory":"Testing Lab",
            "type":"Services"
        }
    ],
    "sg:phone":"+32 11 34 01 10",
    "sg:postcode":"3581",
    "sg:province":"Limburg",
    "sg:tags":[
        "chemist"
    ],
    "wof:name":"Balis H",
    "wof:placetype":"venue"
},
  "geometry": {"coordinates":[5.2228298187,51.0881996155],"type":"Point"}
}