{
  "type": "Feature",
  "properties": {
    "iso:country":"BE",
    "sg:address":"Godefriduskaai 28 Box 28",
    "sg:city":"Antwerpen",
    "sg:classifiers":[
        {
            "category":"Professional",
            "subcategory":"Accounting & Tax Preparation",
            "type":"Services"
        }
    ],
    "sg:phone":"+32 3 226 67 80",
    "sg:postcode":"2000",
    "sg:province":"Antwerpen",
    "sg:tags":[
        "accountant"
    ],
    "wof:name":"Accountantskantoor W Soons",
    "wof:placetype":"venue"
},
  "geometry": {"coordinates":[4.4081878662,51.227848053],"type":"Point"}
}