{
  "type": "Feature",
  "properties": {
    "addr:full":"Rue Du Pouly 76 Philippeville Namur 5600",
    "addr:housenumber":"76",
    "addr:postcode":"5600",
    "addr:street":"Rue Du Pouly",
    "iso:country":"BE",
    "sg:address":"Rue Du Pouly 76",
    "sg:city":"Philippeville",
    "sg:orig_category":"Rundveehouders",
    "sg:phone":"+32 71 66 65 68",
    "sg:postcode":"5600",
    "sg:province":"Namur",
    "wof:name":"Joseph Chermanne",
    "wof:placetype":"venue"
},
  "geometry": {"coordinates":[4.5290441513,50.2162666321],"type":"Point"}
}