{
  "type": "Feature",
  "properties": {
    "iso:country":"BE",
    "sg:address":"Rue Des Chalets 1",
    "sg:city":"Sint-agatha-berchem/berchem-sa",
    "sg:orig_category":"Installations and terrains de sport hors centres sportifs. Clubs de sport. Centres sportifs. Cours d",
    "sg:phone":"+32 2 465 83 46",
    "sg:postcode":"1082",
    "sg:province":"Bruxelles-Capitale",
    "wof:name":"Centre Sportif",
    "wof:placetype":"venue"
},
  "geometry": {"coordinates":[4.2954311371,50.8645133972],"type":"Point"}
}