{
  "type": "Feature",
  "properties": {
    "addr:full":"Bld Anciens-combattants 2 Ronse/renaix Oost-Vlaanderen 9600",
    "addr:housenumber":"2",
    "addr:postcode":"9600",
    "addr:street":"Bld Anciens-Combattants",
    "iso:country":"BE",
    "sg:address":"Bld Anciens-combattants 2",
    "sg:city":"Ronse/renaix",
    "sg:classifiers":[
        {
            "category":"Autos & Motor Vehicles",
            "subcategory":"Fuel & Gas Station",
            "type":"Retail Goods"
        }
    ],
    "sg:phone":"+32 55 21 41 17",
    "sg:postcode":"9600",
    "sg:province":"Oost-Vlaanderen",
    "sg:tags":[
        "stations-service",
        "carburants"
    ],
    "wof:name":"Q8",
    "wof:placetype":"venue"
},
  "geometry": {"coordinates":[3.5975370407,50.7413291931],"type":"Point"}
}