{
  "type": "Feature",
  "properties": {
    "addr:full":"Europaplein 7 De Pinte Oost-Vlaanderen 9840",
    "addr:housenumber":"7",
    "addr:postcode":"9840",
    "addr:street":"Europaplein",
    "iso:country":"BE",
    "sg:address":"Europaplein 7",
    "sg:city":"De Pinte",
    "sg:classifiers":[
        {
            "category":"Shopping",
            "subcategory":"Clothing, Apparel, & Fashions",
            "type":"Retail Goods"
        }
    ],
    "sg:phone":"+32 9 324 38 52",
    "sg:postcode":"9840",
    "sg:province":"Oost-Vlaanderen",
    "sg:tags":[
        "boutique"
    ],
    "wof:name":"Dress Store",
    "wof:placetype":"venue"
},
  "geometry": {"coordinates":[3.6542899609,50.9905281067],"type":"Point"}
}