{
  "type": "Feature",
  "properties": {
    "iso:country":"BE",
    "sg:address":"Meire 3b1",
    "sg:city":"Zottegem",
    "sg:orig_category":"Advocaten and juridische adviseurs",
    "sg:phone":"+32 9 360 45 97",
    "sg:postcode":"9620",
    "sg:province":"Oost-Vlaanderen",
    "wof:name":"Guy Van Gansbeke",
    "wof:placetype":"venue"
},
  "geometry": {"coordinates":[3.8079099655,50.8673286438],"type":"Point"}
}