{
  "type": "Feature",
  "properties": {
    "addr:full":"Oude Heirweg 9 Lichtervelde West-Vlaanderen 8810",
    "addr:housenumber":"9",
    "addr:postcode":"8810",
    "addr:street":"Oude Heirweg",
    "iso:country":"BE",
    "sg:address":"Oude Heirweg 9",
    "sg:city":"Lichtervelde",
    "sg:orig_category":"Rundveehouders Varkenskwekers",
    "sg:phone":"+32 51 74 45 72",
    "sg:postcode":"8810",
    "sg:province":"West-Vlaanderen",
    "wof:name":"Daniel Tommeleyn",
    "wof:placetype":"venue"
},
  "geometry": {"coordinates":[3.1746730804,51.004108429],"type":"Point"}
}