{
  "type": "Feature",
  "properties": {
    "iso:country":"BE",
    "sg:address":"Kortrijksepoortstraat 23",
    "sg:city":"Gent",
    "sg:orig_category":"S\u00e9curit\u00e9 sociale",
    "sg:phone":"+32 9 233 39 07",
    "sg:postcode":"9000",
    "sg:province":"Oost-Vlaanderen",
    "wof:name":"Unie Mutualiteit",
    "wof:placetype":"venue"
},
  "geometry": {"coordinates":[3.7223310471,51.0457992554],"type":"Point"}
}