{
  "type": "Feature",
  "properties": {
    "iso:country":"BE",
    "sg:address":"Chauss\u00c9e De Wavre 3h",
    "sg:city":"Perwez",
    "sg:orig_category":"Agences de voyages",
    "sg:phone":"+32 81 65 95 80",
    "sg:postcode":"1360",
    "sg:province":"Brabant Wallon",
    "wof:name":"Voyages Horizon Bleu",
    "wof:placetype":"venue"
},
  "geometry": {"coordinates":[4.8102040291,50.6256942749],"type":"Point"}
}