{
  "type": "Feature",
  "properties": {
    "iso:country":"BE",
    "sg:address":"Lage Kaart 499",
    "sg:city":"Brasschaat",
    "sg:orig_category":"Non-Classified Establishments",
    "sg:phone":"+32 3 653 56 47",
    "sg:postcode":"2930",
    "sg:province":"Antwerpen",
    "wof:name":"Munich Sport",
    "wof:placetype":"venue"
},
  "geometry": {"coordinates":[4.4963521957,51.3104667664],"type":"Point"}
}