{
  "type": "Feature",
  "properties": {
    "iso:country":"BE",
    "sg:address":"Lombaardstraat 22",
    "sg:city":"Brussel",
    "sg:orig_category":"Kapsalons Speciaalzaken",
    "sg:phone":"+32 2 513 82 42",
    "sg:postcode":"1000",
    "sg:province":"Bruxelles-Capitale",
    "wof:name":"All Hair Haarspecialisten",
    "wof:placetype":"venue"
},
  "geometry": {"coordinates":[4.3503751755,50.8458976746],"type":"Point"}
}