{
  "type": "Feature",
  "properties": {
    "addr:full":"Tivolistraat 13 Brussel/bruxelles Bruxelles-Capitale 1020",
    "addr:housenumber":"13",
    "addr:postcode":"1020",
    "addr:street":"Tivolistraat;/",
    "iso:country":"BE",
    "sg:address":"Tivolistraat 13",
    "sg:city":"Brussel/bruxelles",
    "sg:orig_category":"Kinderopvang",
    "sg:phone":"+32 2 425 73 41",
    "sg:postcode":"1020",
    "sg:province":"Bruxelles-Capitale",
    "wof:name":"Cr\u00c8che Commun. Bruxelles",
    "wof:placetype":"venue"
},
  "geometry": {"coordinates":[4.3545269966,50.8721389771],"type":"Point"}
}