{
  "type": "Feature",
  "properties": {
    "iso:country":"BE",
    "sg:address":"Rijkmakerlaan 15",
    "sg:city":"Essen",
    "sg:classifiers":[
        {
            "category":"Shopping",
            "subcategory":"Pets & Pet Supplies",
            "type":"Retail Goods"
        }
    ],
    "sg:phone":"+32 3 677 02 10",
    "sg:postcode":"2910",
    "sg:province":"Antwerpen",
    "sg:tags":[
        "aquarium",
        "accessory"
    ],
    "wof:name":"M B F Bvba",
    "wof:placetype":"venue"
},
  "geometry": {"coordinates":[4.499229908,51.4457626343],"type":"Point"}
}