{
  "type": "Feature",
  "properties": {
    "addr:full":"Rue Sous Le Ch\u00c2teau 128 Dison Li\u00e8ge 4821",
    "addr:housenumber":"128",
    "addr:postcode":"4821",
    "addr:street":"Rue Sous Le Cha\u0302Teau",
    "iso:country":"BE",
    "sg:address":"Rue Sous Le Ch\u00c2teau 128",
    "sg:city":"Dison",
    "sg:orig_category":"Rundveehouders",
    "sg:phone":"+32 87 33 59 89",
    "sg:postcode":"4821",
    "sg:province":"Li\u00e8ge",
    "wof:name":"Scholzen Joseph & Rene",
    "wof:placetype":"venue"
},
  "geometry": {"coordinates":[5.866645813,50.6097602844],"type":"Point"}
}