{
  "type": "Feature",
  "properties": {
    "iso:country":"BE",
    "sg:address":"Rue Neuve 81",
    "sg:city":"Ellezelles (wodecq)",
    "sg:classifiers":[
        {
            "category":"Bars & Pubs",
            "type":"Food & Drink"
        }
    ],
    "sg:phone":"+32 68 54 25 73",
    "sg:postcode":"7890",
    "sg:province":"Hainaut",
    "wof:name":"Local Colombophil",
    "wof:placetype":"venue"
},
  "geometry": {"coordinates":[3.7436599731,50.7171592712],"type":"Point"}
}