{
  "type": "Feature",
  "properties": {
    "addr:full":"Willem Geetsstraat 36 Mechelen Antwerpen 2800",
    "addr:housenumber":"36",
    "addr:postcode":"2800",
    "addr:street":"Willem Geetsstraat",
    "iso:country":"BE",
    "sg:address":"Willem Geetsstraat 36",
    "sg:city":"Mechelen",
    "sg:orig_category":"Dansscholen Kapsalons",
    "sg:phone":"+32 15 34 00 97",
    "sg:postcode":"2800",
    "sg:province":"Antwerpen",
    "wof:name":"Elite",
    "wof:placetype":"venue"
},
  "geometry": {"coordinates":[4.4782681465,51.0183448792],"type":"Point"}
}