{
  "type": "Feature",
  "properties": {
    "addr:full":"Rue Du Tir 15 La Louviere Hainaut 7100",
    "addr:housenumber":"15",
    "addr:postcode":"7100",
    "addr:street":"Rue Du Tir",
    "iso:country":"BE",
    "sg:address":"Rue Du Tir 15",
    "sg:city":"La Louviere",
    "sg:classifiers":[
        {
            "category":"Insurance",
            "subcategory":"Insurance Agent",
            "type":"Services"
        }
    ],
    "sg:phone":"+32 64 22 70 76",
    "sg:postcode":"7100",
    "sg:province":"Hainaut",
    "sg:tags":[
        "verzekeringsmakelaars",
        "expert"
    ],
    "wof:name":"S. Iacobucci",
    "wof:placetype":"venue"
},
  "geometry": {"coordinates":[4.1688637733,50.4773139954],"type":"Point"}
}