{
  "type": "Feature",
  "properties": {
    "addr:full":"Maarschalk Neylaan 92 Ukkel/uccle Bruxelles-Capitale 1180",
    "addr:housenumber":"92",
    "addr:postcode":"1180",
    "addr:street":"Maarschalk Neylaan;/",
    "iso:country":"BE",
    "sg:address":"Maarschalk Neylaan 92",
    "sg:city":"Ukkel/uccle",
    "sg:orig_category":"Artsen and specialisten",
    "sg:phone":"+32 2 374 52 23",
    "sg:postcode":"1180",
    "sg:province":"Bruxelles-Capitale",
    "wof:name":"Christine Oth",
    "wof:placetype":"venue"
},
  "geometry": {"coordinates":[4.3603768349,50.7787399292],"type":"Point"}
}