{
  "type": "Feature",
  "properties": {
    "addr:full":"Gitsbergstraat 93 Hooglede West-Vlaanderen 8830",
    "addr:housenumber":"93",
    "addr:postcode":"8830",
    "addr:street":"Gitsbergstraat",
    "iso:country":"BE",
    "sg:address":"Gitsbergstraat 93",
    "sg:city":"Hooglede",
    "sg:orig_category":"Loodgieterij, verwarming and sanitaire installaties",
    "sg:phone":"+32 51 22 08 11",
    "sg:postcode":"8830",
    "sg:province":"West-Vlaanderen",
    "wof:name":"Haelewyn Lieven",
    "wof:placetype":"venue"
},
  "geometry": {"coordinates":[3.1047990322,50.9904785156],"type":"Point"}
}