{
  "type": "Feature",
  "properties": {
    "iso:country":"BE",
    "sg:address":"Gentse Steenweg 233",
    "sg:city":"Lokeren",
    "sg:classifiers":[
        {
            "category":"Home & Garden",
            "subcategory":"Carpets & Floor Coverings",
            "type":"Retail Goods"
        }
    ],
    "sg:phone":"+32 9 348 16 30",
    "sg:postcode":"9160",
    "sg:province":"Oost-Vlaanderen",
    "sg:tags":[
        "tile"
    ],
    "wof:name":"Van Peteghem Bvba",
    "wof:placetype":"venue"
},
  "geometry": {"coordinates":[3.9251759052,51.1118049622],"type":"Point"}
}