{
  "type": "Feature",
  "properties": {
    "iso:country":"BE",
    "sg:address":"Korenmarkt 18-19",
    "sg:city":"Izegem",
    "sg:classifiers":[
        {
            "category":"Shopping",
            "subcategory":"Stationery & Office Supplies",
            "type":"Retail Goods"
        }
    ],
    "sg:phone":"+32 51 30 09 93",
    "sg:postcode":"8870",
    "sg:province":"West-Vlaanderen",
    "wof:name":"Nonkel",
    "wof:placetype":"venue"
},
  "geometry": {"coordinates":[3.2146260738,50.9196014404],"type":"Point"}
}