{
  "type": "Feature",
  "properties": {
    "iso:country":"BE",
    "sg:address":"Kruisheide 8",
    "sg:city":"Londerzeel",
    "sg:orig_category":"Eleveurs de bovins",
    "sg:phone":"+32 52 33 67 32",
    "sg:postcode":"1840",
    "sg:province":"Vlaams-Brabant",
    "wof:name":"Georges Goossens",
    "wof:placetype":"venue"
},
  "geometry": {"coordinates":[4.2884988785,51.0105667114],"type":"Point"}
}