{
  "type": "Feature",
  "properties": {
    "addr:full":"Rue Neuve 11 Charleroi Hainaut 6000",
    "addr:housenumber":"11",
    "addr:postcode":"6000",
    "addr:street":"Rue Neuve;Hainaut",
    "iso:country":"BE",
    "sg:address":"Rue Neuve 11",
    "sg:city":"Charleroi",
    "sg:classifiers":[
        {
            "category":"Shopping",
            "subcategory":"Clothing, Apparel, & Fashions",
            "type":"Retail Goods"
        }
    ],
    "sg:phone":"+32 71 32 21 26",
    "sg:postcode":"6000",
    "sg:province":"Hainaut",
    "sg:tags":[
        "boutique"
    ],
    "wof:name":"Turbulence",
    "wof:placetype":"venue"
},
  "geometry": {"coordinates":[4.4446687698,50.4123497009],"type":"Point"}
}