{
  "type": "Feature",
  "properties": {
    "addr:full":"Place Verte Li\u00c8ge Li\u00e8ge 4000",
    "addr:postcode":"4000",
    "addr:street":"Place Verte",
    "iso:country":"BE",
    "sg:address":"Place Verte",
    "sg:city":"Li\u00c8ge",
    "sg:classifiers":[
        {
            "category":"Fast Food",
            "type":"Food & Drink"
        }
    ],
    "sg:phone":"+32 4 250 09 50",
    "sg:postcode":"4000",
    "sg:province":"Li\u00e8ge",
    "sg:tags":[
        "meeneem",
        "restaurant"
    ],
    "wof:name":"Roi Ferr\u00c9",
    "wof:placetype":"venue"
},
  "geometry": {"coordinates":[5.5707697868,50.6441345215],"type":"Point"}
}