{
  "type": "Feature",
  "properties": {
    "addr:full":"Wilgenstraat 10 Gavere Oost-Vlaanderen 9890",
    "addr:housenumber":"10",
    "addr:postcode":"9890",
    "addr:street":"Wilgenstraat",
    "iso:country":"BE",
    "sg:address":"Wilgenstraat 10",
    "sg:city":"Gavere",
    "sg:orig_category":"Rundveehouders",
    "sg:phone":"+32 9 384 18 21",
    "sg:postcode":"9890",
    "sg:province":"Oost-Vlaanderen",
    "wof:name":"Christiaan De Roose",
    "wof:placetype":"venue"
},
  "geometry": {"coordinates":[3.6588599682,50.9283752441],"type":"Point"}
}