{
  "type": "Feature",
  "properties": {
    "iso:country":"BE",
    "sg:address":"Rue Louis De Brouck\u00c8re 62",
    "sg:city":"Saint-nicolas",
    "sg:orig_category":"Imprimeries and copyshops",
    "sg:phone":"+32 4 263 10 82",
    "sg:postcode":"4420",
    "sg:province":"Li\u00e8ge",
    "wof:name":"Imprimerie Andre Robert",
    "wof:placetype":"venue"
},
  "geometry": {"coordinates":[5.5219168663,50.6360931396],"type":"Point"}
}