{
  "type": "Feature",
  "properties": {
    "iso:country":"BE",
    "sg:address":"Rue Du Ch\u00e2teau D'eau 8",
    "sg:city":"Momignies (seloignes)",
    "sg:classifiers":[
        {
            "category":"Health Services",
            "subcategory":"Nursing And Care Facility",
            "type":"Services"
        }
    ],
    "sg:phone":"+32 60 51 25 79",
    "sg:postcode":"6596",
    "sg:province":"Hainaut",
    "sg:tags":[
        "home",
        "rest"
    ],
    "wof:name":"R\u00e9sidence Le Liberty Sprl",
    "wof:placetype":"venue"
},
  "geometry": {"coordinates":[4.2404360771,50.0094299316],"type":"Point"}
}