{
  "type": "Feature",
  "properties": {
    "iso:country":"BE",
    "sg:address":"Lange Koepoortstraat 70-72",
    "sg:city":"Antwerpen",
    "sg:orig_category":"Drogueries. Quincailleries. Combustibles. C\u00e9r\u00e9ales and aliments pour animaux Produits chimiques Mat\u00e9",
    "sg:phone":"+32 3 233 21 57",
    "sg:postcode":"2000",
    "sg:province":"Antwerpen",
    "wof:name":"Van Der Stuyf J.",
    "wof:placetype":"venue"
},
  "geometry": {"coordinates":[4.4021859169,51.2218132019],"type":"Point"}
}