{
  "type": "Feature",
  "properties": {
    "addr:full":"Iddergemsesteenweg 6 Haaltert (denderhoutem) Oost-Vlaanderen 9450",
    "addr:housenumber":"6",
    "addr:postcode":"9450",
    "addr:street":"Iddergemsesteenweg",
    "iso:country":"BE",
    "sg:address":"Iddergemsesteenweg 6",
    "sg:city":"Haaltert (denderhoutem)",
    "sg:classifiers":[
        {
            "category":"Health Services",
            "subcategory":"Dentist",
            "type":"Services"
        }
    ],
    "sg:phone":"+32 54 33 01 87",
    "sg:postcode":"9450",
    "sg:province":"Oost-Vlaanderen",
    "wof:name":"Noe C",
    "wof:placetype":"venue"
},
  "geometry": {"coordinates":[4.0220570564,50.8757629395],"type":"Point"}
}