{
  "type": "Feature",
  "properties": {
    "iso:country":"BE",
    "sg:address":"Het Oud Blok 31",
    "sg:city":"Balen",
    "sg:orig_category":"Installation de menuiserie en bois and plastique",
    "sg:phone":"+32 14 30 07 78",
    "sg:postcode":"2490",
    "sg:province":"Antwerpen",
    "wof:name":"Immob. Vermeulen",
    "wof:placetype":"venue"
},
  "geometry": {"coordinates":[5.1117582321,51.1510810852],"type":"Point"}
}