{
  "type": "Feature",
  "properties": {
    "iso:country":"BE",
    "sg:address":"Rue De La Vall\u00e9e 51",
    "sg:city":"Ch\u00e2telet (ch\u00e2telineau)",
    "sg:classifiers":[
        {
            "category":"Professional",
            "subcategory":"Lawyer & Legal Services",
            "type":"Services"
        }
    ],
    "sg:phone":"+32 71 38 00 14",
    "sg:postcode":"6200",
    "sg:province":"Hainaut",
    "sg:tags":[
        "notary"
    ],
    "wof:name":"De Thier H",
    "wof:placetype":"venue"
},
  "geometry": {"coordinates":[4.5189390182,50.4130744934],"type":"Point"}
}