{
  "type": "Feature",
  "properties": {
    "addr:full":"Chauss\u00e9e De Maubeuge 97 Mons (hyon) Hainaut 7022",
    "addr:housenumber":"97",
    "addr:postcode":"7022",
    "addr:street":"Chausse\u0301E De Maubeuge",
    "iso:country":"BE",
    "sg:address":"Chauss\u00e9e De Maubeuge 97",
    "sg:city":"Mons (hyon)",
    "sg:classifiers":[
        {
            "category":"Building & Trades",
            "subcategory":"Cleaning & Sanitation",
            "type":"Services"
        }
    ],
    "sg:phone":"+32 65 34 72 44",
    "sg:postcode":"7022",
    "sg:province":"Hainaut",
    "sg:tags":[
        "janitor"
    ],
    "wof:name":"Vitro Service Sa",
    "wof:placetype":"venue"
},
  "geometry": {"coordinates":[3.9479110241,50.4350242615],"type":"Point"}
}