{
  "type": "Feature",
  "properties": {
    "iso:country":"BE",
    "sg:address":"Rue Eug\u00c8ne Castaigne 11ba",
    "sg:city":"La Hulpe",
    "sg:orig_category":"Installation de menuiserie en bois and plastique. Charpentes and couvertures",
    "sg:phone":"+32 2 653 71 59",
    "sg:postcode":"1310",
    "sg:province":"Brabant Wallon",
    "wof:name":"Dekeyser Guy",
    "wof:placetype":"venue"
},
  "geometry": {"coordinates":[4.4876971245,50.7324523926],"type":"Point"}
}