{
  "type": "Feature",
  "properties": {
    "addr:full":"Nieuwstraat 15 Denderleeuw Oost-Vlaanderen 9470",
    "addr:housenumber":"15",
    "addr:postcode":"9470",
    "addr:street":"Nieuwstraat",
    "iso:country":"BE",
    "sg:address":"Nieuwstraat 15",
    "sg:city":"Denderleeuw",
    "sg:orig_category":"Newspapers, magazines, periodicals - Distribution",
    "sg:phone":"+32 53 66 71 95",
    "sg:postcode":"9470",
    "sg:province":"Oost-Vlaanderen",
    "wof:name":"Crisma Bookshop",
    "wof:placetype":"venue"
},
  "geometry": {"coordinates":[4.0741810799,50.8805122375],"type":"Point"}
}