{
  "type": "Feature",
  "properties": {
    "iso:country":"BE",
    "sg:address":"Scav\u00e9e Du Bi\u00e9reau 3",
    "sg:city":"Ottignies-louvain-la-neuve (louvain-la-neuve)",
    "sg:classifiers":[
        {
            "category":"Arts & Performance",
            "subcategory":"Theater",
            "type":"Entertainment"
        }
    ],
    "sg:postcode":"1348",
    "sg:province":"Brabant Wallon",
    "sg:tags":[
        "concert-halls",
        "theatre"
    ],
    "wof:name":"Ferme Du Diereau",
    "wof:placetype":"venue"
},
  "geometry": {"coordinates":[4.6174359322,50.665561676],"type":"Point"}
}