{
  "type": "Feature",
  "properties": {
    "iso:country":"BE",
    "sg:address":"Rue De Sesselich 122",
    "sg:city":"Arlon",
    "sg:orig_category":"Dansscholen",
    "sg:phone":"+32 63 21 70 11",
    "sg:postcode":"6700",
    "sg:province":"Luxembourg",
    "wof:name":"Nicole Aimont",
    "wof:placetype":"venue"
},
  "geometry": {"coordinates":[5.8101968765,49.6736183167],"type":"Point"}
}