{
  "type": "Feature",
  "properties": {
    "addr:full":"Brouwerijdreef 36 Mol Antwerpen 2400",
    "addr:housenumber":"36",
    "addr:postcode":"2400",
    "addr:street":"Brouwerijdreef",
    "iso:country":"BE",
    "sg:address":"Brouwerijdreef 36",
    "sg:city":"Mol",
    "sg:orig_category":"Sportclubs",
    "sg:phone":"+32 14 81 02 29",
    "sg:postcode":"2400",
    "sg:province":"Antwerpen",
    "wof:name":"Wielersport. Mol Wezel 61",
    "wof:placetype":"venue"
},
  "geometry": {"coordinates":[5.2084522247,51.1898994446],"type":"Point"}
}