{
  "type": "Feature",
  "properties": {
    "iso:country":"BE",
    "sg:address":"Place Verte 13bbis",
    "sg:city":"Soignies",
    "sg:classifiers":[
        {
            "category":"Cafe",
            "type":"Food & Drink"
        }
    ],
    "sg:phone":"+32 67 33 55 11",
    "sg:postcode":"7060",
    "sg:province":"Hainaut",
    "sg:tags":[
        "caf\u00e9s"
    ],
    "wof:name":"Caf\u00c9 L'europe",
    "wof:placetype":"venue"
},
  "geometry": {"coordinates":[4.0681037903,50.5789375305],"type":"Point"}
}