{
  "type": "Feature",
  "properties": {
    "iso:country":"BE",
    "sg:address":"Zandstraat 20",
    "sg:city":"Zemst (hofstade)",
    "sg:classifiers":[
        {
            "category":"Health Services",
            "subcategory":"Doctor",
            "type":"Services"
        }
    ],
    "sg:phone":"+32 15 61 62 62",
    "sg:postcode":"1981",
    "sg:province":"Vlaams-Brabant",
    "sg:tags":[
        "medicinephysicians",
        "surgeon"
    ],
    "wof:name":"Crols R",
    "wof:placetype":"venue"
},
  "geometry": {"coordinates":[4.4960098267,50.9868888855],"type":"Point"}
}