{
  "type": "Feature",
  "properties": {
    "iso:country":"BE",
    "sg:address":"Grote Markt 24",
    "sg:city":"Diest",
    "sg:classifiers":[
        {
            "category":"Cafe",
            "type":"Food & Drink"
        }
    ],
    "sg:phone":"+32 13 32 73 75",
    "sg:postcode":"3290",
    "sg:province":"Vlaams-Brabant",
    "sg:tags":[
        "caf\u00e9s"
    ],
    "wof:name":"Caf\u00c9 Leffe",
    "wof:placetype":"venue"
},
  "geometry": {"coordinates":[5.0507202148,50.9840316772],"type":"Point"}
}