{
  "type": "Feature",
  "properties": {
    "iso:country":"BE",
    "sg:address":"Maarschalk Haiglaan 3",
    "sg:city":"Ieper",
    "sg:classifiers":[
        {
            "category":"Bars & Pubs",
            "type":"Food & Drink"
        }
    ],
    "sg:phone":"+32 57 20 90 28",
    "sg:postcode":"8900",
    "sg:province":"West-Vlaanderen",
    "wof:name":"Du Boulevard",
    "wof:placetype":"venue"
},
  "geometry": {"coordinates":[2.8760530949,50.8513755798],"type":"Point"}
}