{
  "type": "Feature",
  "properties": {
    "iso:country":"BE",
    "sg:address":"Lenniksebaan 1383",
    "sg:city":"Sint-pieters-leeuw",
    "sg:classifiers":[
        {
            "category":"Professional",
            "subcategory":"Accounting & Tax Preparation",
            "type":"Services"
        }
    ],
    "sg:phone":"+32 2 569 00 12",
    "sg:postcode":"1602",
    "sg:province":"Vlaams-Brabant",
    "sg:tags":[
        "accountant"
    ],
    "wof:name":"Norbert Geirnaert",
    "wof:placetype":"venue"
},
  "geometry": {"coordinates":[4.2114977837,50.8145484924],"type":"Point"}
}