{
  "type": "Feature",
  "properties": {
    "iso:country":"BE",
    "sg:address":"Beukendreef 9",
    "sg:city":"Aalst",
    "sg:orig_category":"Traducteurs and interpr\u00e8tes",
    "sg:phone":"+32 53 78 82 56",
    "sg:postcode":"9300",
    "sg:province":"Oost-Vlaanderen",
    "wof:name":"De Rouck M. Cbtip/bkvtf",
    "wof:placetype":"venue"
},
  "geometry": {"coordinates":[4.0582442284,50.9327926636],"type":"Point"}
}