{
  "type": "Feature",
  "properties": {
    "addr:full":"Brugsestw 347 Roeselare West-Vlaanderen 8800",
    "addr:housenumber":"347",
    "addr:postcode":"8800",
    "iso:country":"BE",
    "sg:address":"Brugsestw 347",
    "sg:city":"Roeselare",
    "sg:classifiers":[
        {
            "category":"Home & Garden",
            "subcategory":"Furniture",
            "type":"Retail Goods"
        }
    ],
    "sg:phone":"+32 51 26 04 10",
    "sg:postcode":"8800",
    "sg:province":"West-Vlaanderen",
    "sg:tags":[
        "household",
        "wood"
    ],
    "wof:name":"Keukens Dovy Nv",
    "wof:placetype":"venue"
},
  "geometry": {"coordinates":[3.1203548908,50.9647521973],"type":"Point"}
}