{
  "type": "Feature",
  "properties": {
    "addr:full":"Kirchstrasse 28 Kelmis Li\u00e8ge 4720",
    "addr:housenumber":"28",
    "addr:postcode":"4720",
    "addr:street":"Kirchstrasse",
    "iso:country":"BE",
    "sg:address":"Kirchstrasse 28",
    "sg:city":"Kelmis",
    "sg:classifiers":[
        {
            "category":"Communications",
            "subcategory":"Radio Station",
            "type":"Services"
        }
    ],
    "sg:phone":"+32 87 65 88 07",
    "sg:postcode":"4720",
    "sg:province":"Li\u00e8ge",
    "sg:tags":[
        "local"
    ],
    "wof:name":"Radio Studio Kelmis",
    "wof:placetype":"venue"
},
  "geometry": {"coordinates":[6.0133728981,50.7161102295],"type":"Point"}
}