{
  "type": "Feature",
  "properties": {
    "iso:country":"BE",
    "sg:address":"Rue Trieu Malonne 11",
    "sg:city":"Sambreville",
    "sg:orig_category":"Produits \u00e0 base de pommes de terre Fruits and l\u00e9gumes Gr",
    "sg:phone":"+32 71 77 12 43",
    "sg:postcode":"5060",
    "sg:province":"Namur",
    "wof:name":"Joel Sabbe",
    "wof:placetype":"venue"
},
  "geometry": {"coordinates":[4.6285200119,50.4448738098],"type":"Point"}
}