{
  "type": "Feature",
  "properties": {
    "iso:country":"BE",
    "sg:address":"Chauss\u00c9e De Wavre 26",
    "sg:city":"Perwez",
    "sg:orig_category":"Herstellingen and onderhoud van auto's",
    "sg:phone":"+32 81 65 58 39",
    "sg:postcode":"1360",
    "sg:province":"Brabant Wallon",
    "wof:name":"Yves Martiny",
    "wof:placetype":"venue"
},
  "geometry": {"coordinates":[4.8069009781,50.6270675659],"type":"Point"}
}