{
  "type": "Feature",
  "properties": {
    "addr:full":"Rue Margot 38 Walhain (nil-saint-vincent-saint-martin) Brabant Wallon 1457",
    "addr:housenumber":"38",
    "addr:postcode":"1457",
    "addr:street":"Rue Margot;Wallon",
    "iso:country":"BE",
    "sg:address":"Rue Margot 38",
    "sg:city":"Walhain (nil-saint-vincent-saint-martin)",
    "sg:classifiers":[
        {
            "category":"Sports & Exercise",
            "subcategory":"Sports Center",
            "type":"Entertainment"
        }
    ],
    "sg:phone":"+32 10 65 59 95",
    "sg:postcode":"1457",
    "sg:province":"Brabant Wallon",
    "sg:tags":[
        "holiday",
        "language"
    ],
    "wof:name":"European Students",
    "wof:placetype":"venue"
},
  "geometry": {"coordinates":[4.6540670395,50.6364517212],"type":"Point"}
}