{
  "type": "Feature",
  "properties": {
    "iso:country":"BE",
    "sg:address":"Rue Du Chatelet 62",
    "sg:city":"Villers-la-ville",
    "sg:classifiers":[
        {
            "category":"Sports & Exercise",
            "subcategory":"Sports Center",
            "type":"Entertainment"
        }
    ],
    "sg:phone":"+32 71 87 77 65",
    "sg:postcode":"1495",
    "sg:province":"Brabant Wallon",
    "sg:tags":[
        "club",
        "article",
        "de",
        "camping"
    ],
    "wof:name":"Golfclub De Rigen\u00c9e",
    "wof:placetype":"venue"
},
  "geometry": {"coordinates":[4.530477047,50.5786132812],"type":"Point"}
}