{
  "type": "Feature",
  "properties": {
    "addr:full":"Nijverheidslaan 11 Vichte West-Vlaanderen 8570",
    "addr:housenumber":"11",
    "addr:postcode":"8570",
    "addr:street":"Nijverheidslaan;West-Vlaanderen",
    "iso:country":"BE",
    "sg:address":"Nijverheidslaan 11",
    "sg:city":"Vichte",
    "sg:classifiers":[
        {
            "category":"Shopping",
            "subcategory":"Crafts & Fabrics",
            "type":"Retail Goods"
        }
    ],
    "sg:phone":"+32 56 77 73 80",
    "sg:postcode":"8570",
    "sg:province":"West-Vlaanderen",
    "sg:tags":[
        "textile",
        "linen",
        "clothing"
    ],
    "wof:name":"Vandeginste M Nv",
    "wof:placetype":"venue"
},
  "geometry": {"coordinates":[3.478826046,50.8326339722],"type":"Point"}
}