{
  "type": "Feature",
  "properties": {
    "addr:full":"Chemin Des P\u00e8lerins 12 Mont-saint-aubert Hainaut 7542",
    "addr:housenumber":"12",
    "addr:postcode":"7542",
    "addr:street":"Chemin Des Pe\u0300Lerins",
    "iso:country":"BE",
    "sg:address":"Chemin Des P\u00e8lerins 12",
    "sg:city":"Mont-saint-aubert",
    "sg:classifiers":[
        {
            "category":"Building & Trades",
            "subcategory":"Construction",
            "type":"Services"
        }
    ],
    "sg:phone":"+32 69 23 29 82",
    "sg:postcode":"7542",
    "sg:province":"Hainaut",
    "sg:tags":[
        "industrial",
        "design"
    ],
    "wof:name":"Susini International Design S.p.r.l.",
    "wof:placetype":"venue"
},
  "geometry": {"coordinates":[3.3998579979,50.6472358704],"type":"Point"}
}