{
  "type": "Feature",
  "properties": {
    "iso:country":"BE",
    "sg:address":"Nieuwendorpe",
    "sg:city":"Eeklo",
    "sg:classifiers":[
        {
            "category":"Utilities",
            "subcategory":"Recycling",
            "type":"Services"
        }
    ],
    "sg:phone":"+32 9 378 19 96",
    "sg:postcode":"9900",
    "sg:province":"Oost-Vlaanderen",
    "wof:name":"Van Hecke Gebr",
    "wof:placetype":"venue"
},
  "geometry": {"coordinates":[3.5425350666,51.1788139343],"type":"Point"}
}