{
  "type": "Feature",
  "properties": {
    "iso:country":"BE",
    "sg:address":"2050",
    "sg:city":"Antwerpen",
    "sg:orig_category":"Graphologues, astrologues, voyants and radiesth\u00e9sistes",
    "sg:phone":"+32 496 15 45 33",
    "sg:postcode":"2050",
    "sg:province":"Antwerpen",
    "wof:name":"Anaii",
    "wof:placetype":"venue"
},
  "geometry": {"coordinates":[4.3689899445,51.2226295471],"type":"Point"}
}