{
  "type": "Feature",
  "properties": {
    "iso:country":"BE",
    "sg:address":"Gitsbergstraat 43bb",
    "sg:city":"Hooglede",
    "sg:orig_category":"V\u00e9hicules automobiles",
    "sg:phone":"+32 51 24 09 53",
    "sg:postcode":"8830",
    "sg:province":"West-Vlaanderen",
    "wof:name":"C.a. Internat. Trucks",
    "wof:placetype":"venue"
},
  "geometry": {"coordinates":[3.0947480202,50.9926185608],"type":"Point"}
}