{
  "type": "Feature",
  "properties": {
    "addr:full":"Rue D'arenberg 44b32 Brussel/bruxelles Bruxelles-Capitale 1000",
    "addr:housenumber":"44b32",
    "addr:postcode":"1000",
    "addr:street":"Rue D'Arenberg;/",
    "iso:country":"BE",
    "sg:address":"Rue D'arenberg 44b32",
    "sg:city":"Brussel/bruxelles",
    "sg:orig_category":"Avocats and conseillers juridiques",
    "sg:phone":"+32 2 511 72 77",
    "sg:postcode":"1000",
    "sg:province":"Bruxelles-Capitale",
    "wof:name":"Fl. Van Meer",
    "wof:placetype":"venue"
},
  "geometry": {"coordinates":[4.3568410873,50.8481941223],"type":"Point"}
}