{
  "type": "Feature",
  "properties": {
    "iso:country":"BE",
    "sg:address":"Schaarbeeklei 686",
    "sg:city":"Vilvoorde",
    "sg:orig_category":"Diverse metaalwaren Fab Onderdelen and accessoires voertuigen Gh Werk- and beschermkleding Fab",
    "sg:phone":"+32 2 253 23 80",
    "sg:postcode":"1800",
    "sg:province":"Vlaams-Brabant",
    "wof:name":"Abc Automotive",
    "wof:placetype":"venue"
},
  "geometry": {"coordinates":[4.4144392014,50.9086303711],"type":"Point"}
}