{
  "type": "Feature",
  "properties": {
    "iso:country":"BE",
    "sg:address":"Rue De L'infante 232",
    "sg:city":"Waterloo",
    "sg:classifiers":[
        {
            "category":"Real Estate",
            "subcategory":"Real Estate Services",
            "type":"Services"
        }
    ],
    "sg:phone":"+32 2 351 08 29",
    "sg:postcode":"1410",
    "sg:province":"Brabant Wallon",
    "wof:name":"Renneboog C",
    "wof:placetype":"venue"
},
  "geometry": {"coordinates":[4.3843111992,50.7071456909],"type":"Point"}
}