{
  "type": "Feature",
  "properties": {
    "addr:full":"Guido Gezellelaan 64 Puurs Antwerpen 2870",
    "addr:housenumber":"64",
    "addr:postcode":"2870",
    "addr:street":"Guido Gezellelaan",
    "iso:country":"BE",
    "sg:address":"Guido Gezellelaan 64",
    "sg:city":"Puurs",
    "sg:classifiers":[
        {
            "category":"Health Services",
            "subcategory":"Dentist",
            "type":"Services"
        }
    ],
    "sg:phone":"+32 3 889 44 11",
    "sg:postcode":"2870",
    "sg:province":"Antwerpen",
    "wof:name":"Mignolet W",
    "wof:placetype":"venue"
},
  "geometry": {"coordinates":[4.2871727943,51.0753440857],"type":"Point"}
}