{
  "type": "Feature",
  "properties": {
    "iso:country":"BE",
    "sg:address":"Chauss\u00c9e De Mons 29",
    "sg:city":"Nivelles",
    "sg:orig_category":"Cabinets d\u00b4huissiers",
    "sg:phone":"+32 67 21 99 00",
    "sg:postcode":"1400",
    "sg:province":"Brabant Wallon",
    "wof:name":"Pierre Vranckx",
    "wof:placetype":"venue"
},
  "geometry": {"coordinates":[4.3104419708,50.5867958069],"type":"Point"}
}