{
  "type": "Feature",
  "properties": {
    "addr:full":"Route De Fourquepire 28 Ellezelles Hainaut 7890",
    "addr:housenumber":"28",
    "addr:postcode":"7890",
    "addr:street":"Route De Fourquepire",
    "iso:country":"BE",
    "sg:address":"Route De Fourquepire 28",
    "sg:city":"Ellezelles",
    "sg:orig_category":"Catering and organisatie van feesten Ruimtes voor conferenties, recepties and feesten",
    "sg:phone":"+32 68 54 22 07",
    "sg:postcode":"7890",
    "sg:province":"Hainaut",
    "wof:name":"Ferme De Fourquepire",
    "wof:placetype":"venue"
},
  "geometry": {"coordinates":[3.6846311092,50.7268676758],"type":"Point"}
}