{
  "type": "Feature",
  "properties": {
    "iso:country":"BE",
    "sg:address":"Koksijdestraat 20",
    "sg:city":"Veurne",
    "sg:orig_category":"R\u00e9parations d'appareils \u00e9lectrom\u00e9nagers. Electrom\u00e9nager, t\u00e9l\u00e9visions and radios",
    "sg:phone":"+32 58 31 19 58",
    "sg:postcode":"8630",
    "sg:province":"West-Vlaanderen",
    "wof:name":"Dewilde",
    "wof:placetype":"venue"
},
  "geometry": {"coordinates":[2.6421370506,51.0834236145],"type":"Point"}
}