{
  "type": "Feature",
  "properties": {
    "addr:full":"Rue De La Closi\u00c8re 48 Fleurus Hainaut 6224",
    "addr:housenumber":"48",
    "addr:postcode":"6224",
    "addr:street":"Rue De La Closie\u0300Re",
    "iso:country":"BE",
    "sg:address":"Rue De La Closi\u00c8re 48",
    "sg:city":"Fleurus",
    "sg:orig_category":"Enseignement maternel and primaire",
    "sg:phone":"+32 71 81 61 61",
    "sg:postcode":"6224",
    "sg:province":"Hainaut",
    "wof:name":"E.f.l. St.pierre",
    "wof:placetype":"venue"
},
  "geometry": {"coordinates":[4.58770895,50.4717788696],"type":"Point"}
}