{
  "type": "Feature",
  "properties": {
    "addr:full":"Avenue De Fr\u00e9 66 Bruxelles (uccle) Bruxelles-Capitale 1180",
    "addr:housenumber":"66",
    "addr:postcode":"1180",
    "addr:street":"Avenue De Fre\u0301",
    "iso:country":"BE",
    "sg:address":"Avenue De Fr\u00e9 66",
    "sg:city":"Bruxelles (uccle)",
    "sg:classifiers":[
        {
            "category":"Government",
            "subcategory":"Embassy",
            "type":"Public Place"
        }
    ],
    "sg:phone":"+32 2 374 34 00",
    "sg:postcode":"1180",
    "sg:province":"Bruxelles-Capitale",
    "sg:tags":[
        "consulate"
    ],
    "wof:name":"Russische Federatie (ambassade)",
    "wof:placetype":"venue"
},
  "geometry": {"coordinates":[4.3531417847,50.8043937683],"type":"Point"}
}