{
  "type": "Feature",
  "properties": {
    "addr:full":"Omselweg 4 Bree Limburg 3960",
    "addr:housenumber":"4",
    "addr:postcode":"3960",
    "addr:street":"Omselweg",
    "iso:country":"BE",
    "sg:address":"Omselweg 4",
    "sg:city":"Bree",
    "sg:orig_category":"Banken and kredietinstellingen",
    "sg:phone":"+32 89 86 30 57",
    "sg:postcode":"3960",
    "sg:province":"Limburg",
    "wof:name":"Fortis",
    "wof:placetype":"venue"
},
  "geometry": {"coordinates":[5.5944190025,51.1405677795],"type":"Point"}
}