{
  "type": "Feature",
  "properties": {
    "addr:full":"Bohemen 103a Wichelen Oost-Vlaanderen 9260",
    "addr:housenumber":"103a",
    "addr:postcode":"9260",
    "addr:street":"Bohemen",
    "iso:country":"BE",
    "sg:address":"Bohemen 103a",
    "sg:city":"Wichelen",
    "sg:classifiers":[
        {
            "category":"Home & Garden",
            "subcategory":"Kitchen Supply",
            "type":"Retail Goods"
        }
    ],
    "sg:phone":"+32 52 42 50 43",
    "sg:postcode":"9260",
    "sg:province":"Oost-Vlaanderen",
    "sg:tags":[
        "installation"
    ],
    "wof:name":"De Geyter Interieur",
    "wof:placetype":"venue"
},
  "geometry": {"coordinates":[3.9925830364,51.0020141602],"type":"Point"}
}