{
  "type": "Feature",
  "properties": {
    "iso:country":"BE",
    "sg:address":"Rue Du G\u00c9n\u00c9ral-molitor 6",
    "sg:city":"Arlon",
    "sg:orig_category":"Notaires",
    "sg:phone":"+32 63 22 02 28",
    "sg:postcode":"6700",
    "sg:province":"Luxembourg",
    "wof:name":"Bosseler H.",
    "wof:placetype":"venue"
},
  "geometry": {"coordinates":[5.8122391701,49.6818809509],"type":"Point"}
}