{
  "type": "Feature",
  "properties": {
    "iso:country":"BE",
    "sg:address":"Rue Bois Du Sart 7",
    "sg:city":"Chaumont-gistoux",
    "sg:orig_category":"Entretien and r\u00e9parations de voitures",
    "sg:phone":"+32 10 68 99 78",
    "sg:postcode":"1325",
    "sg:province":"Brabant Wallon",
    "wof:name":"Thierry Desmet",
    "wof:placetype":"venue"
},
  "geometry": {"coordinates":[4.7212347984,50.6867675781],"type":"Point"}
}