{
  "type": "Feature",
  "properties": {
    "addr:full":"Peulisbaan 74 Bonheiden (rijmenam) Antwerpen 2820",
    "addr:housenumber":"74",
    "addr:postcode":"2820",
    "addr:street":"Peulisbaan",
    "iso:country":"BE",
    "sg:address":"Peulisbaan 74",
    "sg:city":"Bonheiden (rijmenam)",
    "sg:classifiers":[
        {
            "category":"Professional",
            "subcategory":"Management & Consulting",
            "type":"Services"
        }
    ],
    "sg:phone":"+32 15 33 14 31",
    "sg:postcode":"2820",
    "sg:province":"Antwerpen",
    "sg:tags":[
        "-",
        "processing",
        "data",
        "consultant"
    ],
    "wof:name":"Marbel Consulting Bvba",
    "wof:placetype":"venue"
},
  "geometry": {"coordinates":[4.5815119743,51.0267715454],"type":"Point"}
}