{
  "type": "Feature",
  "properties": {
    "addr:full":"Brugsestraat 233 Zedelgem West-Vlaanderen 8210",
    "addr:housenumber":"233",
    "addr:postcode":"8210",
    "addr:street":"Brugsestraat",
    "iso:country":"BE",
    "sg:address":"Brugsestraat 233",
    "sg:city":"Zedelgem",
    "sg:orig_category":"Voertuigen",
    "sg:phone":"+32 50 20 99 86",
    "sg:postcode":"8210",
    "sg:province":"West-Vlaanderen",
    "wof:name":"Paul Devriendt",
    "wof:placetype":"venue"
},
  "geometry": {"coordinates":[3.1457929611,51.1280822754],"type":"Point"}
}