{
  "type": "Feature",
  "properties": {
    "iso:country":"BE",
    "sg:address":"Dirk Martensstraat 10a",
    "sg:city":"Brugge (sint-andries)",
    "sg:classifiers":[
        {
            "category":"Professional",
            "subcategory":"Detective & Security Services",
            "type":"Services"
        }
    ],
    "sg:phone":"+32 2 731 36 10",
    "sg:postcode":"8200",
    "sg:province":"West-Vlaanderen",
    "sg:tags":[
        "-",
        "system",
        "apparatus",
        "surveillance"
    ],
    "wof:name":"A & E Security",
    "wof:placetype":"venue"
},
  "geometry": {"coordinates":[3.1964130402,51.2103042603],"type":"Point"}
}