{
  "type": "Feature",
  "properties": {
    "iso:country":"BE",
    "sg:address":"20",
    "sg:city":"Rue Robert Ledecq 1440 Braine-le-chateau",
    "sg:classifiers":[
        {
            "category":"Professional",
            "type":"Services"
        }
    ],
    "sg:phone":"+32 2 366 36 66",
    "sg:postcode":"20",
    "sg:tags":[
        "transport",
        "road"
    ],
    "wof:name":"Tds",
    "wof:placetype":"venue"
},
  "geometry": {"coordinates":[4.3197598457,50.6859931946],"type":"Point"}
}