{
  "type": "Feature",
  "properties": {
    "addr:full":"Damstraat 57 Deinze (sint-martens-leerne) Oost-Vlaanderen 9800",
    "addr:housenumber":"57",
    "addr:postcode":"9800",
    "addr:street":"Damstraat",
    "iso:country":"BE",
    "sg:address":"Damstraat 57",
    "sg:city":"Deinze (sint-martens-leerne)",
    "sg:classifiers":[
        {
            "category":"Military Area",
            "subcategory":"Air Force Base",
            "type":"Public Place"
        }
    ],
    "sg:phone":"+32 9 282 65 93",
    "sg:postcode":"9800",
    "sg:province":"Oost-Vlaanderen",
    "sg:tags":[
        "balustrade"
    ],
    "wof:name":"Nv Lootens Line Nv",
    "wof:placetype":"venue"
},
  "geometry": {"coordinates":[3.5755569935,51.0184593201],"type":"Point"}
}