{
  "type": "Feature",
  "properties": {
    "iso:country":"BE",
    "sg:address":"Rue Du Chevalet 11",
    "sg:city":"Ottignies-louvain-la-neuve",
    "sg:orig_category":"Traitements param\u00e9dicaux",
    "sg:phone":"+32 10 45 64 05",
    "sg:postcode":"1348",
    "sg:province":"Brabant Wallon",
    "wof:name":"D. Guisset",
    "wof:placetype":"venue"
},
  "geometry": {"coordinates":[4.6068558693,50.6657562256],"type":"Point"}
}