{
  "type": "Feature",
  "properties": {
    "addr:full":"Groenweg 47 Kortrijk (bellegem) West-Vlaanderen 8510",
    "addr:housenumber":"47",
    "addr:postcode":"8510",
    "addr:street":"Groenweg",
    "iso:country":"BE",
    "sg:address":"Groenweg 47",
    "sg:city":"Kortrijk (bellegem)",
    "sg:classifiers":[
        {
            "category":"Building & Trades",
            "subcategory":"Landscaping Services",
            "type":"Services"
        }
    ],
    "sg:phone":"+32 56 21 63 55",
    "sg:postcode":"8510",
    "sg:province":"West-Vlaanderen",
    "sg:tags":[
        "gardening",
        "garden",
        "maintenance"
    ],
    "wof:name":"Vanden Bussche Bvba",
    "wof:placetype":"venue"
},
  "geometry": {"coordinates":[3.292550087,50.7742042542],"type":"Point"}
}