{
  "type": "Feature",
  "properties": {
    "addr:full":"Rue Du Centre 46 Gouvy Luxembourg 6670",
    "addr:housenumber":"46",
    "addr:postcode":"6670",
    "addr:street":"Rue Du Centre",
    "iso:country":"BE",
    "sg:address":"Rue Du Centre 46",
    "sg:city":"Gouvy",
    "sg:orig_category":"Epiceries",
    "sg:phone":"+32 80 21 66 89",
    "sg:postcode":"6670",
    "sg:province":"Luxembourg",
    "wof:name":"A. Bock",
    "wof:placetype":"venue"
},
  "geometry": {"coordinates":[5.9395232201,50.1854057312],"type":"Point"}
}