{
  "type": "Feature",
  "properties": {
    "addr:full":"Grand'route 136 Crisn\u00e9e Li\u00e8ge 4367",
    "addr:housenumber":"136",
    "addr:postcode":"4367",
    "addr:street":"Grand'Route",
    "iso:country":"BE",
    "sg:address":"Grand'route 136",
    "sg:city":"Crisn\u00e9e",
    "sg:classifiers":[
        {
            "category":"Freight",
            "type":"Transportation"
        }
    ],
    "sg:phone":"+32 19 67 71 77",
    "sg:postcode":"4367",
    "sg:province":"Li\u00e8ge",
    "sg:tags":[
        "-",
        "transport"
    ],
    "wof:name":"Vervoir Ets Sprl",
    "wof:placetype":"venue"
},
  "geometry": {"coordinates":[5.3976302147,50.7166290283],"type":"Point"}
}