{
  "type": "Feature",
  "properties": {
    "addr:full":"Ooststraat 47 Roeselare West-Vlaanderen 8800",
    "addr:housenumber":"47",
    "addr:postcode":"8800",
    "addr:street":"Ooststraat",
    "iso:country":"BE",
    "sg:address":"Ooststraat 47",
    "sg:city":"Roeselare",
    "sg:orig_category":"Banques and organismes de cr\u00e9dit",
    "sg:phone":"+32 51 20 88 34",
    "sg:postcode":"8800",
    "sg:province":"West-Vlaanderen",
    "wof:name":"Citibank",
    "wof:placetype":"venue"
},
  "geometry": {"coordinates":[3.1262950897,50.9465866089],"type":"Point"}
}