{
  "type": "Feature",
  "properties": {
    "addr:full":"Place Emile Vandervelde 4 Ciney Namur 5590",
    "addr:housenumber":"4",
    "addr:postcode":"5590",
    "addr:street":"Place Emile Vandervelde",
    "iso:country":"BE",
    "sg:address":"Place Emile Vandervelde 4",
    "sg:city":"Ciney",
    "sg:classifiers":[
        {
            "category":"Restaurant",
            "type":"Food & Drink"
        }
    ],
    "sg:phone":"+32 83 21 67 09",
    "sg:postcode":"5590",
    "sg:province":"Namur",
    "wof:name":"Le Provencal",
    "wof:placetype":"venue"
},
  "geometry": {"coordinates":[5.091989994,50.2914085388],"type":"Point"}
}