{
  "type": "Feature",
  "properties": {
    "addr:full":"Nieuwburgstraat 50 Sint-gillis/saint-gilles Bruxelles-Capitale 1060",
    "addr:housenumber":"50",
    "addr:postcode":"1060",
    "addr:street":"Nieuwburgstraat",
    "iso:country":"BE",
    "sg:address":"Nieuwburgstraat 50",
    "sg:city":"Sint-gillis/saint-gilles",
    "sg:orig_category":"Elektrische installaties voor woningen Loodgieterij, verwarming and sanitaire installaties",
    "sg:phone":"+32 2 534 91 46",
    "sg:postcode":"1060",
    "sg:province":"Bruxelles-Capitale",
    "wof:name":"Cap'assistance",
    "wof:placetype":"venue"
},
  "geometry": {"coordinates":[4.3531727791,50.8276786804],"type":"Point"}
}