{
  "type": "Feature",
  "properties": {
    "addr:full":"Baty De Branchon 21 Eghez\u00e9e (branchon) Namur 5310",
    "addr:housenumber":"21",
    "addr:postcode":"5310",
    "addr:street":"Baty;Branchon;Branchon",
    "iso:country":"BE",
    "sg:address":"Baty De Branchon 21",
    "sg:city":"Eghez\u00e9e (branchon)",
    "sg:classifiers":[
        {
            "category":"Home & Garden",
            "subcategory":"Carpets & Floor Coverings",
            "type":"Retail Goods"
        }
    ],
    "sg:phone":"+32 81 46 19 16",
    "sg:postcode":"5310",
    "sg:province":"Namur",
    "sg:tags":[
        "parquet"
    ],
    "wof:name":"Euro-parquets",
    "wof:placetype":"venue"
},
  "geometry": {"coordinates":[4.9676837921,50.6305465698],"type":"Point"}
}