{
  "type": "Feature",
  "properties": {
    "addr:full":"Henisstraat 73 Tongeren Limburg 3700",
    "addr:housenumber":"73",
    "addr:postcode":"3700",
    "addr:street":"Henisstraat",
    "iso:country":"BE",
    "sg:address":"Henisstraat 73",
    "sg:city":"Tongeren",
    "sg:classifiers":[
        {
            "category":"Health Services",
            "subcategory":"Health Practitioner",
            "type":"Services"
        }
    ],
    "sg:phone":"+32 12 23 71 76",
    "sg:postcode":"3700",
    "sg:province":"Limburg",
    "sg:tags":[
        "physiotherapist"
    ],
    "wof:name":"Gielen Daniel",
    "wof:placetype":"venue"
},
  "geometry": {"coordinates":[5.4700050354,50.7863540649],"type":"Point"}
}