{
  "type": "Feature",
  "properties": {
    "addr:full":"Rue Saint-roch 35 Houyet Namur 5560",
    "addr:housenumber":"35",
    "addr:postcode":"5560",
    "addr:street":"Rue Saint-Roch",
    "iso:country":"BE",
    "sg:address":"Rue Saint-roch 35",
    "sg:city":"Houyet",
    "sg:orig_category":"Entretien and r\u00e9parations de voitures",
    "sg:phone":"+32 82 66 67 87",
    "sg:postcode":"5560",
    "sg:province":"Namur",
    "wof:name":"M.s. Export",
    "wof:placetype":"venue"
},
  "geometry": {"coordinates":[5.00578022,50.1879425049],"type":"Point"}
}