{
  "type": "Feature",
  "properties": {
    "addr:full":"Rue Jean Lenoir 10 Louvain-la-neuve Brabant Wallon 1348",
    "addr:housenumber":"10",
    "addr:postcode":"1348",
    "addr:street":"Rue Jean Lenoir",
    "iso:country":"BE",
    "sg:address":"Rue Jean Lenoir 10",
    "sg:city":"Louvain-la-neuve",
    "sg:classifiers":[
        {
            "category":"Utilities",
            "subcategory":"Telephone",
            "type":"Services"
        }
    ],
    "sg:phone":"+32 10 48 56 00",
    "sg:postcode":"1348",
    "sg:province":"Brabant Wallon",
    "sg:tags":[
        "telecommunication"
    ],
    "wof:name":"Gt & T Sa",
    "wof:placetype":"venue"
},
  "geometry": {"coordinates":[4.6268630028,50.6639862061],"type":"Point"}
}