{
  "type": "Feature",
  "properties": {
    "addr:full":"Pastoor De Vosstraat 1 Oosterzele Oost-Vlaanderen 9860",
    "addr:housenumber":"1",
    "addr:postcode":"9860",
    "addr:street":"Pastoor De Vosstraat;Oost-Vlaanderen",
    "iso:country":"BE",
    "sg:address":"Pastoor De Vosstraat 1",
    "sg:city":"Oosterzele",
    "sg:classifiers":[
        {
            "category":"Cafe",
            "type":"Food & Drink"
        }
    ],
    "sg:phone":"+32 9 362 53 08",
    "sg:postcode":"9860",
    "sg:province":"Oost-Vlaanderen",
    "sg:tags":[
        "caf\u00e9s"
    ],
    "wof:name":"Paroch.werk.scheldewind.",
    "wof:placetype":"venue"
},
  "geometry": {"coordinates":[3.7859449387,50.9382209778],"type":"Point"}
}