{
  "type": "Feature",
  "properties": {
    "addr:full":"Zeelaan 167 De Panne West-Vlaanderen 8660",
    "addr:housenumber":"167",
    "addr:postcode":"8660",
    "addr:street":"Zeelaan",
    "iso:country":"BE",
    "sg:address":"Zeelaan 167",
    "sg:city":"De Panne",
    "sg:classifiers":[
        {
            "category":"Tea Room",
            "subcategory":"None",
            "type":"Food & Drink"
        }
    ],
    "sg:phone":"+32 58 42 19 76",
    "sg:postcode":"8660",
    "sg:province":"West-Vlaanderen",
    "wof:name":"Cordial(au)",
    "wof:placetype":"venue"
},
  "geometry": {"coordinates":[2.5905890465,51.1026611328],"type":"Point"}
}