{
  "type": "Feature",
  "properties": {
    "iso:country":"BE",
    "sg:address":"Industrieweg 28",
    "sg:city":"Borgloon",
    "sg:classifiers":[
        {
            "category":"Retail",
            "subcategory":"Auto Repair",
            "type":"Services"
        }
    ],
    "sg:phone":"+32 12 67 21 00",
    "sg:postcode":"3840",
    "sg:province":"Limburg",
    "sg:tags":[
        "garage"
    ],
    "wof:name":"Vanheers Wim Nv",
    "wof:placetype":"venue"
},
  "geometry": {"coordinates":[5.3427891731,50.8157958984],"type":"Point"}
}