{
  "type": "Feature",
  "properties": {
    "iso:country":"BE",
    "sg:address":"Eugeen Dierckxlaan 20",
    "sg:city":"Schilde",
    "sg:classifiers":[
        {
            "category":"Professional",
            "subcategory":"Management & Consulting",
            "type":"Services"
        }
    ],
    "sg:phone":"+32 3 385 22 12",
    "sg:postcode":"2970",
    "sg:province":"Antwerpen",
    "sg:tags":[
        "consultant"
    ],
    "wof:name":"Koch J",
    "wof:placetype":"venue"
},
  "geometry": {"coordinates":[4.5803070068,51.2376213074],"type":"Point"}
}