{
  "type": "Feature",
  "properties": {
    "iso:country":"BE",
    "sg:address":"Familiestraat 68",
    "sg:city":"Antwerpen",
    "sg:classifiers":[
        {
            "category":"Insurance",
            "subcategory":"Life Insurance",
            "type":"Services"
        }
    ],
    "sg:phone":"+32 3 272 12 80",
    "sg:postcode":"2060",
    "sg:province":"Antwerpen",
    "sg:tags":[
        "assurance"
    ],
    "wof:name":"Dap Consulting",
    "wof:placetype":"venue"
},
  "geometry": {"coordinates":[4.4347271919,51.2252120972],"type":"Point"}
}