{
  "type": "Feature",
  "properties": {
    "iso:country":"BE",
    "sg:address":"Bergensesteenweg 37",
    "sg:city":"Halle",
    "sg:orig_category":"Architectes",
    "sg:phone":"+32 2 356 22 77",
    "sg:postcode":"1500",
    "sg:province":"Vlaams-Brabant",
    "wof:name":"Bichara Michel",
    "wof:placetype":"venue"
},
  "geometry": {"coordinates":[4.2341008186,50.733921051],"type":"Point"}
}