{
  "type": "Feature",
  "properties": {
    "iso:country":"BE",
    "sg:address":"127F rue de Percke",
    "sg:city":"Bruxelles",
    "sg:classifiers":[
        {
            "category":"Professional",
            "subcategory":"Computer Services",
            "type":"Services"
        }
    ],
    "sg:postcode":"1180",
    "sg:tags":[
        "communities",
        "social",
        "android",
        "iphone"
    ],
    "sg:website":"http://www.kiboo.net",
    "wof:name":"Kiboo",
    "wof:placetype":"venue"
},
  "geometry": {"coordinates":[4.3601497,50.7741726],"type":"Point"}
}