{
  "type": "Feature",
  "properties": {
    "iso:country":"BE",
    "sg:address":"Rue Du Plavitout 168",
    "sg:city":"Mouscron",
    "sg:classifiers":[
        {
            "category":"Utilities",
            "subcategory":"Natural Gas",
            "type":"Services"
        }
    ],
    "sg:phone":"+32 56 33 06 45",
    "sg:postcode":"7700",
    "sg:province":"Hainaut",
    "sg:tags":[
        "hide",
        "skin"
    ],
    "wof:name":"Joye & Fils",
    "wof:placetype":"venue"
},
  "geometry": {"coordinates":[3.2404789925,50.7561721802],"type":"Point"}
}