{
  "type": "Feature",
  "properties": {
    "addr:full":"Openveldstraat 111 Lede Oost-Vlaanderen 9340",
    "addr:housenumber":"111",
    "addr:postcode":"9340",
    "addr:street":"Openveldstraat",
    "iso:country":"BE",
    "sg:address":"Openveldstraat 111",
    "sg:city":"Lede",
    "sg:orig_category":"Epiceries",
    "sg:phone":"+32 53 80 53 78",
    "sg:postcode":"9340",
    "sg:province":"Oost-Vlaanderen",
    "wof:name":"Spar",
    "wof:placetype":"venue"
},
  "geometry": {"coordinates":[3.974050045,50.9703102112],"type":"Point"}
}