{
  "type": "Feature",
  "properties": {
    "iso:country":"BE",
    "sg:address":"Adolphe Lacombl\u00c9laan 17b1",
    "sg:city":"Schaarbeek/schaerbeek",
    "sg:orig_category":"Artsen and specialisten",
    "sg:phone":"+32 2 734 49 19",
    "sg:postcode":"1030",
    "sg:province":"Bruxelles-Capitale",
    "wof:name":"J. Degrooff",
    "wof:placetype":"venue"
},
  "geometry": {"coordinates":[4.400812149,50.849937439],"type":"Point"}
}