{
  "type": "Feature",
  "properties": {
    "addr:full":"Werfstraat 91 Brugge West-Vlaanderen 8000",
    "addr:housenumber":"91",
    "addr:postcode":"8000",
    "addr:street":"Werfstraat",
    "iso:country":"BE",
    "sg:address":"Werfstraat 91",
    "sg:city":"Brugge",
    "sg:classifiers":[
        {
            "category":"Sports & Exercise",
            "subcategory":"Gym",
            "type":"Entertainment"
        }
    ],
    "sg:phone":"+32 50 34 36 60",
    "sg:postcode":"8000",
    "sg:province":"West-Vlaanderen",
    "sg:tags":[
        "fitness"
    ],
    "wof:name":"Body Balance",
    "wof:placetype":"venue"
},
  "geometry": {"coordinates":[3.2190179825,51.2186203003],"type":"Point"}
}