{
  "type": "Feature",
  "properties": {
    "iso:country":"BE",
    "sg:address":"Gr\u00c9trystraat 64",
    "sg:city":"Brussel/bruxelles",
    "sg:classifiers":[
        {
            "category":"Fast Food",
            "type":"Food & Drink"
        }
    ],
    "sg:phone":"+32 2 219 52 27",
    "sg:postcode":"1000",
    "sg:province":"Bruxelles-Capitale",
    "sg:tags":[
        "meeneem",
        "restaurant"
    ],
    "wof:name":"Restaurant Cathay",
    "wof:placetype":"venue"
},
  "geometry": {"coordinates":[4.3533377647,50.848613739],"type":"Point"}
}