{
  "type": "Feature",
  "properties": {
    "addr:full":"Rue Lug\u00c9a 100 Alleur Li\u00e8ge 4432",
    "addr:housenumber":"100",
    "addr:postcode":"4432",
    "addr:street":"Rue Luge\u0301A",
    "iso:country":"BE",
    "sg:address":"Rue Lug\u00c9a 100",
    "sg:city":"Alleur",
    "sg:classifiers":[
        {
            "category":"Shopping",
            "subcategory":"Bicycles & Sporting Goods",
            "type":"Retail Goods"
        }
    ],
    "sg:phone":"+32 4 263 10 38",
    "sg:postcode":"4432",
    "sg:province":"Li\u00e8ge",
    "sg:tags":[
        "article",
        "de",
        "sport",
        "camping"
    ],
    "wof:name":"Espace Ping",
    "wof:placetype":"venue"
},
  "geometry": {"coordinates":[5.5199289322,50.6751441956],"type":"Point"}
}