{
  "type": "Feature",
  "properties": {
    "addr:full":"Eekstraat 31 Zele Oost-Vlaanderen 9240",
    "addr:housenumber":"31",
    "addr:postcode":"9240",
    "addr:street":"Eekstraat",
    "iso:country":"BE",
    "sg:address":"Eekstraat 31",
    "sg:city":"Zele",
    "sg:classifiers":[
        {
            "category":"Building & Trades",
            "subcategory":"Locksmith",
            "type":"Services"
        }
    ],
    "sg:phone":"+32 52 44 88 57",
    "sg:postcode":"9240",
    "sg:province":"Oost-Vlaanderen",
    "sg:tags":[
        "material",
        "road"
    ],
    "wof:name":"Heirman Bvba",
    "wof:placetype":"venue"
},
  "geometry": {"coordinates":[4.0176987648,51.0624427795],"type":"Point"}
}