{
  "type": "Feature",
  "properties": {
    "addr:full":"Chemin Du Bois Du Roi 12 Dalhem (warsage) Li\u00e8ge 4608",
    "addr:housenumber":"12",
    "addr:postcode":"4608",
    "addr:street":"Chemin Du Bois Du Roi",
    "iso:country":"BE",
    "sg:address":"Chemin Du Bois Du Roi 12",
    "sg:city":"Dalhem (warsage)",
    "sg:classifiers":[
        {
            "category":"Banks & Credit Unions",
            "subcategory":"Financial Services",
            "type":"Services"
        }
    ],
    "sg:phone":"+32 4 376 73 82",
    "sg:postcode":"4608",
    "sg:province":"Li\u00e8ge",
    "sg:tags":[
        "financing"
    ],
    "wof:name":"Flash Finance Sprl",
    "wof:placetype":"venue"
},
  "geometry": {"coordinates":[5.7849230766,50.7407798767],"type":"Point"}
}