{
  "type": "Feature",
  "properties": {
    "addr:full":"Rue Grande-champlon 44 Tenneville Luxembourg 6971",
    "addr:housenumber":"44",
    "addr:postcode":"6971",
    "addr:street":"Rue Grande-Champlon",
    "iso:country":"BE",
    "sg:address":"Rue Grande-champlon 44",
    "sg:city":"Tenneville",
    "sg:orig_category":"Banques and organismes de cr\u00e9dit",
    "sg:phone":"+32 84 45 62 05",
    "sg:postcode":"6971",
    "sg:province":"Luxembourg",
    "wof:name":"Anhyp",
    "wof:placetype":"venue"
},
  "geometry": {"coordinates":[5.4967360497,50.1085281372],"type":"Point"}
}