{
  "type": "Feature",
  "properties": {
    "addr:full":"Rue De La Station 12 Seraing Li\u00e8ge 4101",
    "addr:housenumber":"12",
    "addr:postcode":"4101",
    "addr:street":"Rue De La Station",
    "iso:country":"BE",
    "sg:address":"Rue De La Station 12",
    "sg:city":"Seraing",
    "sg:orig_category":"Articles de camping and de sport. Chaussures",
    "sg:phone":"+32 4 231 16 09",
    "sg:postcode":"4101",
    "sg:province":"Li\u00e8ge",
    "wof:name":"Bruno Sports",
    "wof:placetype":"venue"
},
  "geometry": {"coordinates":[5.4984021187,50.6174354553],"type":"Point"}
}