{
  "type": "Feature",
  "properties": {
    "addr:full":"Rue Longue 163 Ch\u00c2telet Hainaut 6200",
    "addr:housenumber":"163",
    "addr:postcode":"6200",
    "addr:street":"Rue Longue",
    "iso:country":"BE",
    "sg:address":"Rue Longue 163",
    "sg:city":"Ch\u00c2telet",
    "sg:orig_category":"Enseignement maternel and primaire",
    "sg:phone":"+32 71 50 41 21",
    "sg:postcode":"6200",
    "sg:province":"Hainaut",
    "wof:name":"Ecole Matern. Communale",
    "wof:placetype":"venue"
},
  "geometry": {"coordinates":[4.495059967,50.374786377],"type":"Point"}
}