{
  "type": "Feature",
  "properties": {
    "iso:country":"BE",
    "sg:address":"Nieuwpoortsteenweg 14",
    "sg:city":"Koksijde",
    "sg:classifiers":[
        {
            "category":"Arena",
            "subcategory":"Sports Club",
            "type":"Entertainment"
        }
    ],
    "sg:phone":"+32 58 51 25 28",
    "sg:postcode":"8670",
    "sg:province":"West-Vlaanderen",
    "sg:tags":[
        "terrain",
        "hors",
        "de",
        "installation",
        "sportifs"
    ],
    "wof:name":"K.v.v. Oostduinkerke",
    "wof:placetype":"venue"
},
  "geometry": {"coordinates":[2.6880469322,51.1168327332],"type":"Point"}
}