{
  "type": "Feature",
  "properties": {
    "addr:full":"Dorpsstraat 18 Kapellen Antwerpen 2950",
    "addr:housenumber":"18",
    "addr:postcode":"2950",
    "addr:street":"Dorpsstraat",
    "iso:country":"BE",
    "sg:address":"Dorpsstraat 18",
    "sg:city":"Kapellen",
    "sg:classifiers":[
        {
            "category":"Shopping",
            "subcategory":"Jewelry",
            "type":"Retail Goods"
        }
    ],
    "sg:phone":"+32 3 297 23 83",
    "sg:postcode":"2950",
    "sg:province":"Antwerpen",
    "sg:tags":[
        "jeweller",
        "-"
    ],
    "wof:name":"B\u00f6hrer",
    "wof:placetype":"venue"
},
  "geometry": {"coordinates":[4.4291391373,51.3156166077],"type":"Point"}
}