{
  "type": "Feature",
  "properties": {
    "addr:full":"Slijpesteenweg 11 Middelkerke West-Vlaanderen 8432",
    "addr:housenumber":"11",
    "addr:postcode":"8432",
    "addr:street":"Slijpesteenweg",
    "iso:country":"BE",
    "sg:address":"Slijpesteenweg 11",
    "sg:city":"Middelkerke",
    "sg:orig_category":"D\u00e9taillants en pi\u00e8ces and accessoires de voitures. Entretien and r\u00e9parations de voitures",
    "sg:phone":"+32 59 30 53 18",
    "sg:postcode":"8432",
    "sg:province":"West-Vlaanderen",
    "wof:name":"Martin Beernaert",
    "wof:placetype":"venue"
},
  "geometry": {"coordinates":[2.8791849613,51.1716537476],"type":"Point"}
}