{
  "type": "Feature",
  "properties": {
    "iso:country":"BE",
    "sg:address":"Bellevoorde 1",
    "sg:city":"Wetteren",
    "sg:classifiers":[
        {
            "category":"Wholesale",
            "subcategory":"Machinery & Supplies",
            "type":"Manufacturing & Wholesale Goods"
        }
    ],
    "sg:phone":"+32 9 252 52 28",
    "sg:postcode":"9230",
    "sg:province":"Oost-Vlaanderen",
    "sg:tags":[
        "water",
        "pump",
        "-"
    ],
    "wof:name":"Devaplus Regenwaterputten",
    "wof:placetype":"venue"
},
  "geometry": {"coordinates":[3.8445599079,51.0144309998],"type":"Point"}
}