{
  "type": "Feature",
  "properties": {
    "addr:full":"Industrieterrein 1555 Opglabbeek Limburg 3660",
    "addr:postcode":"1555 opglabbeek;3660",
    "addr:street":"Industrieterrein",
    "iso:country":"BE",
    "sg:address":"Industrieterrein 1555",
    "sg:city":"Opglabbeek",
    "sg:orig_category":"Installation de menuiserie m\u00e9tallique",
    "sg:phone":"+32 89 85 60 47",
    "sg:postcode":"3660",
    "sg:province":"Limburg",
    "wof:name":"Goossens Metaalbouw",
    "wof:placetype":"venue"
},
  "geometry": {"coordinates":[5.5838198662,51.0429496765],"type":"Point"}
}