{
  "type": "Feature",
  "properties": {
    "addr:full":"Lindelei 174 Hemiksem Antwerpen 2620",
    "addr:housenumber":"174",
    "addr:postcode":"2620",
    "addr:street":"Lindelei",
    "iso:country":"BE",
    "sg:address":"Lindelei 174",
    "sg:city":"Hemiksem",
    "sg:orig_category":"V\u00e9los",
    "sg:phone":"+32 3 887 12 23",
    "sg:postcode":"2620",
    "sg:province":"Antwerpen",
    "wof:name":"David Vermeiren",
    "wof:placetype":"venue"
},
  "geometry": {"coordinates":[4.3440771103,51.145236969],"type":"Point"}
}