{
  "type": "Feature",
  "properties": {
    "addr:full":"Rue Du Corbeau 104 Bruxelles (schaerbeek) Bruxelles-Capitale 1030",
    "addr:housenumber":"104",
    "addr:postcode":"1030",
    "addr:street":"Rue Du Corbeau",
    "iso:country":"BE",
    "sg:address":"Rue Du Corbeau 104",
    "sg:city":"Bruxelles (schaerbeek)",
    "sg:classifiers":[
        {
            "category":"Home & Garden",
            "subcategory":"Building Materials",
            "type":"Retail Goods"
        }
    ],
    "sg:phone":"+32 2 242 28 63",
    "sg:postcode":"1030",
    "sg:province":"Bruxelles-Capitale",
    "sg:tags":[
        "shutter"
    ],
    "wof:name":"Serruvitre Sa",
    "wof:placetype":"venue"
},
  "geometry": {"coordinates":[4.3932142258,50.8732528687],"type":"Point"}
}