{
  "type": "Feature",
  "properties": {
    "iso:country":"BE",
    "sg:address":"Rue Saint-pierre 30",
    "sg:city":"Mouscron",
    "sg:orig_category":"Fleurs and plantes",
    "sg:phone":"+32 56 34 61 06",
    "sg:postcode":"7700",
    "sg:province":"Hainaut",
    "wof:name":"Julie",
    "wof:placetype":"venue"
},
  "geometry": {"coordinates":[3.2149291039,50.7421607971],"type":"Point"}
}