{
  "type": "Feature",
  "properties": {
    "addr:full":"P. Delvauxlaan 6 Koksijde West-Vlaanderen 8670",
    "addr:housenumber":"6",
    "addr:postcode":"8670",
    "addr:street":"P. Delvauxlaan",
    "iso:country":"BE",
    "sg:address":"P. Delvauxlaan 6",
    "sg:city":"Koksijde",
    "sg:classifiers":[
        {
            "category":"Professional",
            "subcategory":"Accounting & Tax Preparation",
            "type":"Services"
        }
    ],
    "sg:phone":"+32 58 51 40 80",
    "sg:postcode":"8670",
    "sg:province":"West-Vlaanderen",
    "sg:tags":[
        "accountant"
    ],
    "wof:name":"J. Scailquin",
    "wof:placetype":"venue"
},
  "geometry": {"coordinates":[2.6492800713,51.1061401367],"type":"Point"}
}