{
  "type": "Feature",
  "properties": {
    "addr:full":"Noordzandstraat 76 Brugge West-Vlaanderen 8000",
    "addr:housenumber":"76",
    "addr:postcode":"8000",
    "addr:street":"Noordzandstraat",
    "iso:country":"BE",
    "sg:address":"Noordzandstraat 76",
    "sg:city":"Brugge",
    "sg:classifiers":[
        {
            "category":"Education",
            "subcategory":"School",
            "type":"Public Place"
        }
    ],
    "sg:phone":"+32 50 47 17 17",
    "sg:postcode":"8000",
    "sg:province":"West-Vlaanderen",
    "sg:tags":[
        "secondary"
    ],
    "wof:name":"Sint-jozef Humaniora",
    "wof:placetype":"venue"
},
  "geometry": {"coordinates":[3.2186100483,51.2065811157],"type":"Point"}
}