{
  "type": "Feature",
  "properties": {
    "addr:full":"Rue Valduc 307-309 Bruxelles-auderghem Bruxelles-Capitale 1160",
    "addr:postcode":"307-309;1160",
    "addr:street":"Rue Valduc",
    "iso:country":"BE",
    "sg:address":"Rue Valduc 307-309",
    "sg:city":"Bruxelles-auderghem",
    "sg:orig_category":"Motos. R\u00e9parations and entretien de motos. V\u00e9hicules automobiles",
    "sg:phone":"+32 2 673 19 93",
    "sg:postcode":"1160",
    "sg:province":"Bruxelles-Capitale",
    "wof:name":"Src 2000",
    "wof:placetype":"venue"
},
  "geometry": {"coordinates":[4.4115381241,50.8208732605],"type":"Point"}
}