{
  "type": "Feature",
  "properties": {
    "addr:full":"Avenue De Broqueville 40 Bruxelles (woluwe-saint-lambert) Bruxelles-Capitale 1200",
    "addr:housenumber":"40",
    "addr:postcode":"1200",
    "addr:street":"Avenue De Broqueville",
    "iso:country":"BE",
    "sg:address":"Avenue De Broqueville 40",
    "sg:city":"Bruxelles (woluwe-saint-lambert)",
    "sg:classifiers":[
        {
            "category":"Social Services",
            "subcategory":"Job Training",
            "type":"Services"
        }
    ],
    "sg:phone":"+32 2 763 35 51",
    "sg:postcode":"1200",
    "sg:province":"Bruxelles-Capitale",
    "sg:tags":[
        "personnel",
        "-selection",
        "recruitment"
    ],
    "wof:name":"Sidus",
    "wof:placetype":"venue"
},
  "geometry": {"coordinates":[4.410695076,50.8384094238],"type":"Point"}
}