{
  "type": "Feature",
  "properties": {
    "iso:country":"BE",
    "sg:address":"Beersebaan 38",
    "sg:city":"Lille (gierle)",
    "sg:classifiers":[
        {
            "category":"Building & Trades",
            "subcategory":"Construction",
            "type":"Services"
        }
    ],
    "sg:phone":"+32 14 55 48 65",
    "sg:postcode":"2275",
    "sg:province":"Antwerpen",
    "sg:tags":[
        "carpenter"
    ],
    "wof:name":"Vervoort Bvba",
    "wof:placetype":"venue"
},
  "geometry": {"coordinates":[4.8667759895,51.2714424133],"type":"Point"}
}