{
  "type": "Feature",
  "properties": {
    "iso:country":"BE",
    "sg:address":"Rue Du Calvaire 11",
    "sg:city":"Tournai",
    "sg:orig_category":"Eleveurs de bovins",
    "sg:phone":"+32 69 84 61 89",
    "sg:postcode":"7522",
    "sg:province":"Hainaut",
    "wof:name":"Bernard Lampe",
    "wof:placetype":"venue"
},
  "geometry": {"coordinates":[3.3004500866,50.6229057312],"type":"Point"}
}