{
  "type": "Feature",
  "properties": {
    "addr:full":"Rue De Mons 34 Beloeil Hainaut 7970",
    "addr:housenumber":"34",
    "addr:postcode":"7970",
    "addr:street":"Rue De Mons",
    "iso:country":"BE",
    "sg:address":"Rue De Mons 34",
    "sg:city":"Beloeil",
    "sg:orig_category":"Eclairage et \u00e9quipements du foyer",
    "sg:phone":"+32 69 68 91 30",
    "sg:postcode":"7970",
    "sg:province":"Hainaut",
    "wof:name":"Maison Huart",
    "wof:placetype":"venue"
},
  "geometry": {"coordinates":[3.7359359264,50.5474205017],"type":"Point"}
}