{
  "type": "Feature",
  "properties": {
    "iso:country":"BE",
    "sg:address":"Rue De Saint-ethon 35",
    "sg:city":"Seneffe (feluy)",
    "sg:classifiers":[
        {
            "category":"Professional",
            "subcategory":"Art Services",
            "type":"Services"
        }
    ],
    "sg:phone":"+32 67 87 70 14",
    "sg:postcode":"7181",
    "sg:province":"Hainaut",
    "sg:tags":[
        "graphic",
        "designer"
    ],
    "wof:name":"Mirabel Graphic Design",
    "wof:placetype":"venue"
},
  "geometry": {"coordinates":[4.2554302216,50.5584106445],"type":"Point"}
}