{
  "type": "Feature",
  "properties": {
    "iso:country":"BE",
    "sg:address":"Rue De Robermont 115",
    "sg:city":"Li\u00e8ge 1 (li\u00e8ge 2)",
    "sg:classifiers":[
        {
            "category":"Food & Beverages",
            "subcategory":"Liquor & Beverages",
            "type":"Retail Goods"
        }
    ],
    "sg:phone":"+32 495 51 76 94",
    "sg:postcode":"4020",
    "sg:province":"Li\u00e8ge",
    "sg:tags":[
        "-",
        "spirit",
        "wine"
    ],
    "wof:name":"Oenotria",
    "wof:placetype":"venue"
},
  "geometry": {"coordinates":[5.5963602066,50.6376190186],"type":"Point"}
}