{
  "type": "Feature",
  "properties": {
    "iso:country":"BE",
    "sg:address":"Mechelsesteenweg 198",
    "sg:city":"Lier",
    "sg:classifiers":[
        {
            "category":"Restaurant",
            "type":"Food & Drink"
        }
    ],
    "sg:phone":"+32 3 480 98 87",
    "sg:postcode":"2500",
    "sg:province":"Antwerpen",
    "wof:name":"De Smissche",
    "wof:placetype":"venue"
},
  "geometry": {"coordinates":[4.5646901131,51.1314315796],"type":"Point"}
}