{
  "type": "Feature",
  "properties": {
    "addr:full":"Kruiwagenstraat 33 Geraardsbergen Oost-Vlaanderen 9500",
    "addr:housenumber":"33",
    "addr:postcode":"9500",
    "addr:street":"Kruiwagenstraat",
    "iso:country":"BE",
    "sg:address":"Kruiwagenstraat 33",
    "sg:city":"Geraardsbergen",
    "sg:orig_category":"Huisdieren and benodigdheden",
    "sg:phone":"+32 54 42 24 20",
    "sg:postcode":"9500",
    "sg:province":"Oost-Vlaanderen",
    "wof:name":"Van Den Berghe Gino",
    "wof:placetype":"venue"
},
  "geometry": {"coordinates":[3.9183320999,50.7658843994],"type":"Point"}
}