{
  "type": "Feature",
  "properties": {
    "iso:country":"BE",
    "sg:address":"Sint-martinuskerkstraat 105",
    "sg:city":"Ganshoren/ganshoren",
    "sg:orig_category":"Slagers Voedingsspeciaalzaken Zuivelproducten",
    "sg:phone":"+32 2 427 57 57",
    "sg:postcode":"1083",
    "sg:province":"Bruxelles-Capitale",
    "wof:name":"Deca",
    "wof:placetype":"venue"
},
  "geometry": {"coordinates":[4.3134698868,50.8735694885],"type":"Point"}
}