{
  "type": "Feature",
  "properties": {
    "addr:full":"Rue Basse 13 Vise Li\u00e8ge 4600",
    "addr:housenumber":"13",
    "addr:postcode":"4600",
    "addr:street":"Rue Basse",
    "iso:country":"BE",
    "sg:address":"Rue Basse 13",
    "sg:city":"Vise",
    "sg:classifiers":[
        {
            "category":"Arena",
            "subcategory":"Sports Club",
            "type":"Entertainment"
        }
    ],
    "sg:phone":"+32 4 379 42 60",
    "sg:postcode":"4600",
    "sg:province":"Li\u00e8ge",
    "sg:tags":[
        "de"
    ],
    "wof:name":"La Roue Libre",
    "wof:placetype":"venue"
},
  "geometry": {"coordinates":[5.6940908432,50.7345542908],"type":"Point"}
}