{
  "type": "Feature",
  "properties": {
    "addr:full":"Avenue Des Arts 58 Brussel/bruxelles Bruxelles-Capitale 1000",
    "addr:housenumber":"58",
    "addr:postcode":"1000",
    "addr:street":"Avenue Des Arts;/",
    "iso:country":"BE",
    "sg:address":"Avenue Des Arts 58",
    "sg:city":"Brussel/bruxelles",
    "sg:classifiers":[
        {
            "category":"Insurance",
            "subcategory":"Life Insurance",
            "type":"Services"
        }
    ],
    "sg:phone":"+32 2 514 10 99",
    "sg:postcode":"1000",
    "sg:province":"Bruxelles-Capitale",
    "sg:tags":[
        "assurance"
    ],
    "wof:name":"Assurances Albingia",
    "wof:placetype":"venue"
},
  "geometry": {"coordinates":[4.366309166,50.8406295776],"type":"Point"}
}