{
  "type": "Feature",
  "properties": {
    "addr:full":"Botermarkt 10 Hasselt Limburg 3500",
    "addr:housenumber":"10",
    "addr:postcode":"3500",
    "addr:street":"Botermarkt",
    "iso:country":"BE",
    "sg:address":"Botermarkt 10",
    "sg:city":"Hasselt",
    "sg:classifiers":[
        {
            "category":"Shopping",
            "subcategory":"Clothing, Apparel, & Fashions",
            "type":"Retail Goods"
        }
    ],
    "sg:phone":"+32 11 87 45 35",
    "sg:postcode":"3500",
    "sg:province":"Limburg",
    "sg:tags":[
        "lady",
        "clothing",
        "-"
    ],
    "wof:name":"Intini",
    "wof:placetype":"venue"
},
  "geometry": {"coordinates":[5.338312149,50.9306869507],"type":"Point"}
}