{
  "type": "Feature",
  "properties": {
    "addr:full":"Rue D'austravant 8 Chimay Hainaut 6460",
    "addr:housenumber":"8",
    "addr:postcode":"6460",
    "addr:street":"Rue D'Austravant",
    "iso:country":"BE",
    "sg:address":"Rue D'austravant 8",
    "sg:city":"Chimay",
    "sg:orig_category":"Boucheries",
    "sg:phone":"+32 60 21 12 31",
    "sg:postcode":"6460",
    "sg:province":"Hainaut",
    "wof:name":"Andre Demaret",
    "wof:placetype":"venue"
},
  "geometry": {"coordinates":[4.3142571449,50.0481987],"type":"Point"}
}