{
  "type": "Feature",
  "properties": {
    "addr:full":"Knesselarestraat 120 Beernem West-Vlaanderen 8730",
    "addr:housenumber":"120",
    "addr:postcode":"8730",
    "addr:street":"Knesselarestraat",
    "iso:country":"BE",
    "sg:address":"Knesselarestraat 120",
    "sg:city":"Beernem",
    "sg:orig_category":"Rundveehouders",
    "sg:phone":"+32 50 78 93 13",
    "sg:postcode":"8730",
    "sg:province":"West-Vlaanderen",
    "wof:name":"Eric Hallaert",
    "wof:placetype":"venue"
},
  "geometry": {"coordinates":[3.3767299652,51.1543388367],"type":"Point"}
}