{
  "type": "Feature",
  "properties": {
    "addr:full":"Rue Du Coquelet 26b Namur Namur 5000",
    "addr:housenumber":"26b",
    "addr:postcode":"5000",
    "addr:street":"Rue Du Coquelet",
    "iso:country":"BE",
    "sg:address":"Rue Du Coquelet 26b",
    "sg:city":"Namur",
    "sg:classifiers":[
        {
            "category":"Sports & Exercise",
            "subcategory":"Playing Field",
            "type":"Entertainment"
        }
    ],
    "sg:phone":"+32 81 74 27 08",
    "sg:postcode":"5000",
    "sg:province":"Namur",
    "sg:tags":[
        "application",
        "programming"
    ],
    "wof:name":"Automation Vincent Marin",
    "wof:placetype":"venue"
},
  "geometry": {"coordinates":[4.8766207695,50.4690284729],"type":"Point"}
}