{
  "type": "Feature",
  "properties": {
    "addr:full":"Edestraat 0 Erpe-mere Oost-Vlaanderen 9420",
    "addr:housenumber":"0",
    "addr:postcode":"9420",
    "addr:street":"Edestraat",
    "iso:country":"BE",
    "sg:address":"Edestraat 0",
    "sg:city":"Erpe-mere",
    "sg:orig_category":"Traitements param\u00e9dicaux",
    "sg:phone":"+32 53 83 68 19",
    "sg:postcode":"9420",
    "sg:province":"Oost-Vlaanderen",
    "wof:name":"D. Van Den Bossche",
    "wof:placetype":"venue"
},
  "geometry": {"coordinates":[3.978579998,50.9128341675],"type":"Point"}
}