{
  "type": "Feature",
  "properties": {
    "addr:full":"Rue Arthur Roelandt 1 Moeskroen/mouscron Hainaut 7711",
    "addr:housenumber":"1",
    "addr:postcode":"7711",
    "addr:street":"Rue Arthur Roelandt",
    "iso:country":"BE",
    "sg:address":"Rue Arthur Roelandt 1",
    "sg:city":"Moeskroen/mouscron",
    "sg:orig_category":"Banques and organismes de cr\u00e9dit",
    "sg:phone":"+32 56 48 70 79",
    "sg:postcode":"7711",
    "sg:province":"Hainaut",
    "wof:name":"Bacob",
    "wof:placetype":"venue"
},
  "geometry": {"coordinates":[3.3047759533,50.7279853821],"type":"Point"}
}