{
  "type": "Feature",
  "properties": {
    "iso:country":"BE",
    "sg:address":"Manderfeld 71a",
    "sg:city":"B\u00fcllingen (manderfeld)",
    "sg:classifiers":[
        {
            "category":"Professional",
            "subcategory":"Testing Lab",
            "type":"Services"
        }
    ],
    "sg:phone":"+32 80 54 86 05",
    "sg:postcode":"4760",
    "sg:province":"Li\u00e8ge",
    "sg:tags":[
        "chemist"
    ],
    "wof:name":"Schalandryn R",
    "wof:placetype":"venue"
},
  "geometry": {"coordinates":[6.3412599564,50.3308792114],"type":"Point"}
}