{
  "type": "Feature",
  "properties": {
    "iso:country":"BE",
    "sg:address":"Van Schoorstraat 27",
    "sg:city":"Schaarbeek/schaerbeek",
    "sg:orig_category":"Elektrische installaties voor woningen",
    "sg:phone":"+32 2 245 40 51",
    "sg:postcode":"1030",
    "sg:province":"Bruxelles-Capitale",
    "wof:name":"Stefanos Mitoussis",
    "wof:placetype":"venue"
},
  "geometry": {"coordinates":[4.366522789,50.8684654236],"type":"Point"}
}