{
  "type": "Feature",
  "properties": {
    "addr:full":"Grevenbroekstraat 9 Hamont-achel Limburg 3930",
    "addr:housenumber":"9",
    "addr:postcode":"3930",
    "addr:street":"Grevenbroekstraat",
    "iso:country":"BE",
    "sg:address":"Grevenbroekstraat 9",
    "sg:city":"Hamont-achel",
    "sg:orig_category":"Enseignement maternel and primaire",
    "sg:phone":"+32 11 64 21 94",
    "sg:postcode":"3930",
    "sg:province":"Limburg",
    "wof:name":"Vrije Basisschool",
    "wof:placetype":"venue"
},
  "geometry": {"coordinates":[5.4822101593,51.2571105957],"type":"Point"}
}