{
  "type": "Feature",
  "properties": {
    "addr:full":"Molenweg 71bb Riemst Limburg 3770",
    "addr:housenumber":"71bb",
    "addr:postcode":"3770",
    "addr:street":"Molenweg",
    "iso:country":"BE",
    "sg:address":"Molenweg 71bb",
    "sg:city":"Riemst",
    "sg:orig_category":"Supermarkten Warenhuizen",
    "sg:phone":"+32 12 45 14 52",
    "sg:postcode":"3770",
    "sg:province":"Limburg",
    "wof:name":"Gb Contact",
    "wof:placetype":"venue"
},
  "geometry": {"coordinates":[5.5827379227,50.8337097168],"type":"Point"}
}