{
  "type": "Feature",
  "properties": {
    "addr:full":"De Maurissensstraat 23 Wielsbeke West-Vlaanderen 8710",
    "addr:housenumber":"23",
    "addr:postcode":"8710",
    "addr:street":"Maurissensstraat;West-Vlaanderen",
    "iso:country":"BE",
    "sg:address":"De Maurissensstraat 23",
    "sg:city":"Wielsbeke",
    "sg:classifiers":[
        {
            "category":"Professional",
            "subcategory":"Engineering",
            "type":"Services"
        }
    ],
    "sg:phone":"+32 56 66 61 83",
    "sg:postcode":"8710",
    "sg:province":"West-Vlaanderen",
    "sg:tags":[
        "-"
    ],
    "wof:name":"H.t.b. Bvba",
    "wof:placetype":"venue"
},
  "geometry": {"coordinates":[3.3663830757,50.9071502686],"type":"Point"}
}