{
  "type": "Feature",
  "properties": {
    "addr:full":"Rue J.van Volsem 71 Elsene/ixelles Bruxelles-Capitale 1050",
    "addr:housenumber":"71",
    "addr:postcode":"1050",
    "addr:street":"Rue J.Van Volsem",
    "iso:country":"BE",
    "sg:address":"Rue J.van Volsem 71",
    "sg:city":"Elsene/ixelles",
    "sg:orig_category":"Mus\u00e9es and patrimoine culturel",
    "sg:phone":"+32 2 511 90 84",
    "sg:postcode":"1050",
    "sg:province":"Bruxelles-Capitale",
    "wof:name":"Mus\u00c9e Communal D'ixelles",
    "wof:placetype":"venue"
},
  "geometry": {"coordinates":[4.3724842072,50.831615448],"type":"Point"}
}