{
  "type": "Feature",
  "properties": {
    "addr:full":"Rue Des Kessales 87 Seraing (jemeppe-sur-meuse) Li\u00e8ge 4101",
    "addr:housenumber":"87",
    "addr:postcode":"4101",
    "addr:street":"Rue Des Kessales;Jemeppe-Sur-Meuse",
    "iso:country":"BE",
    "sg:address":"Rue Des Kessales 87",
    "sg:city":"Seraing (jemeppe-sur-meuse)",
    "sg:classifiers":[
        {
            "category":"Health Services",
            "subcategory":"Doctor",
            "type":"Services"
        }
    ],
    "sg:phone":"+32 4 233 26 06",
    "sg:postcode":"4101",
    "sg:province":"Li\u00e8ge",
    "sg:tags":[
        "medicinephysicians",
        "surgeon"
    ],
    "wof:name":"Laenen W",
    "wof:placetype":"venue"
},
  "geometry": {"coordinates":[5.4905538559,50.6153297424],"type":"Point"}
}