{
  "type": "Feature",
  "properties": {
    "iso:country":"BE",
    "sg:address":"Hazelaarsdreef 18",
    "sg:city":"Brecht (sint-job-in-'t Goor)",
    "sg:classifiers":[
        {
            "category":"Health Services",
            "subcategory":"Health Practitioner",
            "type":"Services"
        }
    ],
    "sg:phone":"+32 3 633 07 07",
    "sg:postcode":"2960",
    "sg:province":"Antwerpen",
    "sg:tags":[
        "physiotherapist"
    ],
    "wof:name":"Verdyck Nathalie",
    "wof:placetype":"venue"
},
  "geometry": {"coordinates":[4.5575218201,51.3059387207],"type":"Point"}
}