{
  "type": "Feature",
  "properties": {
    "iso:country":"BE",
    "sg:address":"Rue De Thy Le Baudouin 14",
    "sg:city":"Laneffe",
    "sg:orig_category":"Beveiligingsdiensten and bewakingsbedrijven",
    "sg:phone":"+32 71 65 07 70",
    "sg:postcode":"5651",
    "sg:province":"Namur",
    "wof:name":"Anubis Security Guarding",
    "wof:placetype":"venue"
},
  "geometry": {"coordinates":[4.5006918907,50.2769813538],"type":"Point"}
}