{
  "type": "Feature",
  "properties": {
    "addr:full":"Eksaardserijweg 210 Gent Oost-Vlaanderen 9041",
    "addr:housenumber":"210",
    "addr:postcode":"9041",
    "addr:street":"Oost-Vlaanderen",
    "iso:country":"BE",
    "sg:address":"Eksaardserijweg 210",
    "sg:city":"Gent",
    "sg:orig_category":"Artiesten and kunstenaars",
    "sg:phone":"+32 9 251 30 18",
    "sg:postcode":"9041",
    "sg:province":"Oost-Vlaanderen",
    "wof:name":"Gudrun Van De Voorde",
    "wof:placetype":"venue"
},
  "geometry": {"coordinates":[3.7738120556,51.0907020569],"type":"Point"}
}