{
  "type": "Feature",
  "properties": {
    "addr:full":"Luithagen Haven Antwerpen Antwerpen 2030",
    "addr:postcode":"2030",
    "addr:street":"Luithagen",
    "iso:country":"BE",
    "sg:address":"Luithagen Haven",
    "sg:city":"Antwerpen",
    "sg:classifiers":[
        {
            "category":"Transit Center",
            "subcategory":"Freight",
            "type":"Transportation"
        }
    ],
    "sg:phone":"+32 3 544 71 19",
    "sg:postcode":"2030",
    "sg:province":"Antwerpen",
    "sg:tags":[
        "import",
        "export",
        "-"
    ],
    "wof:name":"Alberto Trading Nv",
    "wof:placetype":"venue"
},
  "geometry": {"coordinates":[4.3273148537,51.2739982605],"type":"Point"}
}