{
  "type": "Feature",
  "properties": {
    "iso:country":"BE",
    "sg:address":"Stationstraat 22",
    "sg:city":"Tielt",
    "sg:orig_category":"Enseignement maternel and primaire. Enseignement secondaire g\u00e9n\u00e9ral",
    "sg:phone":"+32 51 40 62 63",
    "sg:postcode":"8700",
    "sg:province":"West-Vlaanderen",
    "wof:name":"Vrije Basisschool",
    "wof:placetype":"venue"
},
  "geometry": {"coordinates":[3.3267960548,50.9933624268],"type":"Point"}
}