{
  "type": "Feature",
  "properties": {
    "addr:full":"Broekstraat 82 Dilbeek Vlaams-Brabant 1700",
    "addr:housenumber":"82",
    "addr:postcode":"1700",
    "addr:street":"Broekstraat",
    "iso:country":"BE",
    "sg:address":"Broekstraat 82",
    "sg:city":"Dilbeek",
    "sg:classifiers":[
        {
            "category":"Building & Trades",
            "subcategory":"Pest Control",
            "type":"Services"
        }
    ],
    "sg:phone":"+32 2 366 13 53",
    "sg:postcode":"1700",
    "sg:province":"Vlaams-Brabant",
    "sg:tags":[
        "machine",
        "vending"
    ],
    "wof:name":"Marbin",
    "wof:placetype":"venue"
},
  "geometry": {"coordinates":[4.2687540054,50.8399238586],"type":"Point"}
}