{
  "type": "Feature",
  "properties": {
    "addr:full":"Egelantierlaan 27 De Panne West-Vlaanderen 8660",
    "addr:housenumber":"27",
    "addr:postcode":"8660",
    "addr:street":"Egelantierlaan",
    "iso:country":"BE",
    "sg:address":"Egelantierlaan 27",
    "sg:city":"De Panne",
    "sg:orig_category":"Diverse juridische dienstverlening",
    "sg:phone":"+32 58 41 07 44",
    "sg:postcode":"8660",
    "sg:province":"West-Vlaanderen",
    "wof:name":"Windsor",
    "wof:placetype":"venue"
},
  "geometry": {"coordinates":[2.5771598816,51.0941696167],"type":"Point"}
}