{
  "type": "Feature",
  "properties": {
    "addr:full":"Mechelsestraat 10 Vilvoorde Vlaams-Brabant 1800",
    "addr:housenumber":"10",
    "addr:postcode":"1800",
    "addr:street":"Mechelsestraat",
    "iso:country":"BE",
    "sg:address":"Mechelsestraat 10",
    "sg:city":"Vilvoorde",
    "sg:classifiers":[
        {
            "category":"Social Services",
            "type":"Services"
        }
    ],
    "sg:phone":"+32 2 251 58 59",
    "sg:postcode":"1800",
    "sg:province":"Vlaams-Brabant",
    "wof:name":"Casa Blanca",
    "wof:placetype":"venue"
},
  "geometry": {"coordinates":[4.4221959114,50.929813385],"type":"Point"}
}