{
  "type": "Feature",
  "properties": {
    "iso:country":"BE",
    "sg:address":"Rue Henri Van Zuylen 78",
    "sg:city":"Bruxelles (uccle)",
    "sg:classifiers":[
        {
            "category":"Arts & Performance",
            "subcategory":"Symphony",
            "type":"Entertainment"
        }
    ],
    "sg:phone":"+32 2 374 77 59",
    "sg:postcode":"1180",
    "sg:province":"Bruxelles-Capitale",
    "sg:tags":[
        "orchestra"
    ],
    "wof:name":"A. Alex Scorier-karine Barella",
    "wof:placetype":"venue"
},
  "geometry": {"coordinates":[4.3415541649,50.7975654602],"type":"Point"}
}