{
  "type": "Feature",
  "properties": {
    "addr:full":"Route D\u00b4herbesthal 317 Eupen Li\u00e8ge 4700",
    "addr:housenumber":"317",
    "addr:postcode":"4700",
    "addr:street":"Route D\u00b4Herbesthal",
    "iso:country":"BE",
    "sg:address":"Route D\u00b4herbesthal 317",
    "sg:city":"Eupen",
    "sg:classifiers":[
        {
            "category":"Autos & Motor Vehicles",
            "subcategory":"Fuel & Gas Station",
            "type":"Retail Goods"
        }
    ],
    "sg:phone":"+32 87 88 09 51",
    "sg:postcode":"4700",
    "sg:province":"Li\u00e8ge",
    "sg:tags":[
        "stations-service",
        "carburants"
    ],
    "wof:name":"Jet",
    "wof:placetype":"venue"
},
  "geometry": {"coordinates":[6.0110998154,50.6427307129],"type":"Point"}
}