{
  "type": "Feature",
  "properties": {
    "addr:full":"Rue De Valenciennes 106 Qui\u00e9vrain Hainaut 7380",
    "addr:housenumber":"106",
    "addr:postcode":"7380",
    "addr:street":"Rue De Valenciennes",
    "iso:country":"BE",
    "sg:address":"Rue De Valenciennes 106",
    "sg:city":"Qui\u00e9vrain",
    "sg:orig_category":"Non-Classified Establishments",
    "sg:phone":"+32 65 43 07 02",
    "sg:postcode":"7380",
    "sg:province":"Hainaut",
    "wof:name":"Ovidias Pralines",
    "wof:placetype":"venue"
},
  "geometry": {"coordinates":[3.6762170792,50.4039764404],"type":"Point"}
}