{
  "type": "Feature",
  "properties": {
    "iso:country":"BE",
    "sg:address":"Chauss\u00c9e De Wavre 187",
    "sg:city":"Wanze",
    "sg:orig_category":"Jardinage. P\u00e9pini\u00e9ristes",
    "sg:phone":"+32 85 23 07 38",
    "sg:postcode":"4520",
    "sg:province":"Li\u00e8ge",
    "wof:name":"P\u00c9pini\u00c8res De Champia",
    "wof:placetype":"venue"
},
  "geometry": {"coordinates":[5.1992840767,50.5374412537],"type":"Point"}
}