{
  "type": "Feature",
  "properties": {
    "iso:country":"BE",
    "sg:address":"Holleweggaarde 6ba",
    "sg:city":"Schaarbeek/schaerbeek",
    "sg:orig_category":"Rusthuizen and serviceflats",
    "sg:phone":"+32 2 215 89 34",
    "sg:postcode":"1030",
    "sg:province":"Bruxelles-Capitale",
    "wof:name":"Les Jardins De Terdelt",
    "wof:placetype":"venue"
},
  "geometry": {"coordinates":[4.3932051659,50.8647575378],"type":"Point"}
}