{
  "type": "Feature",
  "properties": {
    "addr:full":"Grotenbergestraat 78 Zottegem Oost-Vlaanderen 9620",
    "addr:housenumber":"78",
    "addr:postcode":"9620",
    "addr:street":"Grotenbergestraat",
    "iso:country":"BE",
    "sg:address":"Grotenbergestraat 78",
    "sg:city":"Zottegem",
    "sg:orig_category":"Pleisterwerk",
    "sg:phone":"+32 9 360 60 33",
    "sg:postcode":"9620",
    "sg:province":"Oost-Vlaanderen",
    "wof:name":"Holderbeke",
    "wof:placetype":"venue"
},
  "geometry": {"coordinates":[3.820882082,50.8724441528],"type":"Point"}
}