{
  "type": "Feature",
  "properties": {
    "iso:country":"BE",
    "sg:address":"Jamin\u00c9straat 44",
    "sg:city":"Tongeren",
    "sg:orig_category":"Bagage and lederwaren Schoenen",
    "sg:phone":"+32 12 26 24 68",
    "sg:postcode":"3700",
    "sg:province":"Limburg",
    "wof:name":"Mara",
    "wof:placetype":"venue"
},
  "geometry": {"coordinates":[5.4730548859,50.7831306458],"type":"Point"}
}