{
  "type": "Feature",
  "properties": {
    "addr:full":"Schellekensberg 24 Diest (schaffen) Vlaams-Brabant 3290",
    "addr:housenumber":"24",
    "addr:postcode":"3290",
    "addr:street":"Schellekensberg",
    "iso:country":"BE",
    "sg:address":"Schellekensberg 24",
    "sg:city":"Diest (schaffen)",
    "sg:classifiers":[
        {
            "category":"Building & Trades",
            "subcategory":"Landscaping Services",
            "type":"Services"
        }
    ],
    "sg:phone":"+32 13 31 28 06",
    "sg:postcode":"3290",
    "sg:province":"Vlaams-Brabant",
    "sg:tags":[
        "soil",
        "analysis"
    ],
    "wof:name":"Vande Voorde Bvba",
    "wof:placetype":"venue"
},
  "geometry": {"coordinates":[5.1070680618,51.0186157227],"type":"Point"}
}