{
  "type": "Feature",
  "properties": {
    "addr:full":"Chemin De Mos\u00c9e 4 Ciney Namur 5590",
    "addr:housenumber":"4",
    "addr:postcode":"5590",
    "addr:street":"Chemin De Mose\u0301E",
    "iso:country":"BE",
    "sg:address":"Chemin De Mos\u00c9e 4",
    "sg:city":"Ciney",
    "sg:orig_category":"Landbouwmachines Gh",
    "sg:phone":"+32 83 21 15 78",
    "sg:postcode":"5590",
    "sg:province":"Namur",
    "wof:name":"M.d.m.",
    "wof:placetype":"venue"
},
  "geometry": {"coordinates":[5.0878119469,50.2958183289],"type":"Point"}
}