{
  "type": "Feature",
  "properties": {
    "addr:full":"Q. Aux Pierres De Taille 23 Brussel/bruxelles Bruxelles-Capitale 1000",
    "addr:housenumber":"23",
    "addr:postcode":"1000",
    "addr:street":"Q. Aux Pierres De Taille;/",
    "iso:country":"BE",
    "sg:address":"Q. Aux Pierres De Taille 23",
    "sg:city":"Brussel/bruxelles",
    "sg:orig_category":"Biblioth\u00e8ques and archives publiques",
    "sg:phone":"+32 2 219 05 38",
    "sg:postcode":"1000",
    "sg:province":"Bruxelles-Capitale",
    "wof:name":"Biblioth\u00c8que Publique",
    "wof:placetype":"venue"
},
  "geometry": {"coordinates":[4.3499059677,50.8552474976],"type":"Point"}
}