{
  "type": "Feature",
  "properties": {
    "iso:country":"BE",
    "sg:address":"Rue Des Rossignols 27",
    "sg:city":"Marche-en-famenne",
    "sg:classifiers":[
        {
            "category":"Insurance",
            "subcategory":"Insurance Agent",
            "type":"Services"
        }
    ],
    "sg:phone":"+32 84 31 12 72",
    "sg:postcode":"6900",
    "sg:province":"Luxembourg",
    "sg:tags":[
        "broker"
    ],
    "wof:name":"Galoy A",
    "wof:placetype":"venue"
},
  "geometry": {"coordinates":[5.3747200966,50.2356987],"type":"Point"}
}