{
  "type": "Feature",
  "properties": {
    "iso:country":"BE",
    "sg:address":"Boeregemstraat 30",
    "sg:city":"Wortegem-petegem",
    "sg:orig_category":"Rundveehouders",
    "sg:phone":"+32 56 68 86 65",
    "sg:postcode":"9790",
    "sg:province":"Oost-Vlaanderen",
    "wof:name":"Alain Depestele",
    "wof:placetype":"venue"
},
  "geometry": {"coordinates":[3.5111711025,50.8687705994],"type":"Point"}
}