{
  "type": "Feature",
  "properties": {
    "addr:full":"Rue De Tilleur 1b Li\u00e8ge 1 Li\u00e8ge 4000",
    "addr:housenumber":"1b;1",
    "addr:postcode":"4000",
    "addr:street":"Rue De Tilleur",
    "iso:country":"BE",
    "sg:address":"Rue De Tilleur 1b",
    "sg:city":"Li\u00e8ge 1",
    "sg:classifiers":[
        {
            "category":"Real Estate",
            "subcategory":"Real Estate Services",
            "type":"Services"
        }
    ],
    "sg:phone":"+32 4 254 04 14",
    "sg:postcode":"4000",
    "sg:province":"Li\u00e8ge",
    "wof:name":"Immobili\u00e8re (l') Sprl",
    "wof:placetype":"venue"
},
  "geometry": {"coordinates":[5.5470328331,50.6324195862],"type":"Point"}
}