{
  "type": "Feature",
  "properties": {
    "addr:full":"Chauss\u00e9e De Huy 346 Chaumont-gistoux Brabant Wallon 1325",
    "addr:housenumber":"346",
    "addr:postcode":"1325",
    "addr:street":"Chausse\u0301E De Huy",
    "iso:country":"BE",
    "sg:address":"Chauss\u00e9e De Huy 346",
    "sg:city":"Chaumont-gistoux",
    "sg:classifiers":[
        {
            "category":"Professional",
            "subcategory":"Engineering",
            "type":"Services"
        }
    ],
    "sg:phone":"+32 10 68 00 67",
    "sg:postcode":"1325",
    "sg:province":"Brabant Wallon",
    "sg:tags":[
        "environmental",
        "technique",
        "-"
    ],
    "wof:name":"Astero Sprl",
    "wof:placetype":"venue"
},
  "geometry": {"coordinates":[4.7281661034,50.6682739258],"type":"Point"}
}