{
  "type": "Feature",
  "properties": {
    "iso:country":"BE",
    "sg:address":"Rue G\u00c9n\u00c9ral-jacques 5",
    "sg:city":"Vielsalm",
    "sg:orig_category":"Slagers",
    "sg:phone":"+32 80 21 61 08",
    "sg:postcode":"6690",
    "sg:province":"Luxembourg",
    "wof:name":"Boucherie Lebrun",
    "wof:placetype":"venue"
},
  "geometry": {"coordinates":[5.9165849686,50.2868614197],"type":"Point"}
}