{
  "type": "Feature",
  "properties": {
    "iso:country":"BE",
    "sg:address":"Melanedreef 6",
    "sg:city":"Houthulst",
    "sg:orig_category":"Non-Classified Establishments",
    "sg:phone":"+32 51 70 11 47",
    "sg:postcode":"8650",
    "sg:province":"West-Vlaanderen",
    "wof:name":"Bara Nv",
    "wof:placetype":"venue"
},
  "geometry": {"coordinates":[2.9509100914,50.971321106],"type":"Point"}
}