{
  "type": "Feature",
  "properties": {
    "iso:country":"BE",
    "sg:address":"Paleizenstraat 316",
    "sg:city":"Brussel/bruxelles",
    "sg:orig_category":"Dranken",
    "sg:phone":"+32 2 203 42 19",
    "sg:postcode":"1000",
    "sg:province":"Bruxelles-Capitale",
    "wof:name":"Bibendum",
    "wof:placetype":"venue"
},
  "geometry": {"coordinates":[4.3634409904,50.8714599609],"type":"Point"}
}