{
  "type": "Feature",
  "properties": {
    "iso:country":"BE",
    "sg:address":"Rue Joseph Wauters 12",
    "sg:city":"Villers-le-bouillet",
    "sg:orig_category":"V\u00e9t\u00e9rinaires",
    "sg:phone":"+32 19 56 61 11",
    "sg:postcode":"4530",
    "sg:province":"Li\u00e8ge",
    "wof:name":"Joel Gustin",
    "wof:placetype":"venue"
},
  "geometry": {"coordinates":[5.2604899406,50.5760765076],"type":"Point"}
}