{
  "type": "Feature",
  "properties": {
    "iso:country":"BE",
    "sg:address":"Sint-michielsstraat 17",
    "sg:city":"Gent",
    "sg:classifiers":[
        {
            "category":"Shopping",
            "subcategory":"Musical Instruments",
            "type":"Retail Goods"
        }
    ],
    "sg:phone":"+32 9 225 92 75",
    "sg:postcode":"9000",
    "sg:province":"Oost-Vlaanderen",
    "sg:tags":[
        "-"
    ],
    "wof:name":"Antares Belgium",
    "wof:placetype":"venue"
},
  "geometry": {"coordinates":[3.7177948952,51.0538902283],"type":"Point"}
}