{
  "type": "Feature",
  "properties": {
    "iso:country":"BE",
    "sg:address":"Voie De L'ardenne 158",
    "sg:city":"Chaudfontaine (embourg)",
    "sg:classifiers":[
        {
            "category":"Building & Trades",
            "subcategory":"Electrical",
            "type":"Services"
        }
    ],
    "sg:phone":"+32 4 367 09 15",
    "sg:postcode":"4053",
    "sg:province":"Li\u00e8ge",
    "sg:tags":[
        "tool",
        "electric"
    ],
    "wof:name":"Kova Outils Sa",
    "wof:placetype":"venue"
},
  "geometry": {"coordinates":[5.6124000549,50.5863113403],"type":"Point"}
}