{
  "type": "Feature",
  "properties": {
    "iso:country":"BE",
    "sg:address":"Avenue Albert-elisabeth 13",
    "sg:city":"Mons",
    "sg:orig_category":"Artsen and specialisten",
    "sg:phone":"+32 65 31 14 77",
    "sg:postcode":"7030",
    "sg:province":"Hainaut",
    "wof:name":"J.l. Delveaux",
    "wof:placetype":"venue"
},
  "geometry": {"coordinates":[3.9541730881,50.4477653503],"type":"Point"}
}