{
  "type": "Feature",
  "properties": {
    "addr:full":"Baron Straat 118 Izegem West-Vlaanderen 8870",
    "addr:housenumber":"118",
    "addr:postcode":"8870",
    "addr:street":"Baron Straat",
    "iso:country":"BE",
    "sg:address":"Baron Straat 118",
    "sg:city":"Izegem",
    "sg:classifiers":[
        {
            "category":"Professional",
            "subcategory":"Engineering",
            "type":"Services"
        }
    ],
    "sg:phone":"+32 51 30 13 58",
    "sg:postcode":"8870",
    "sg:province":"West-Vlaanderen",
    "sg:tags":[
        "-",
        "metal",
        "precision",
        "machine",
        "equipment",
        "machinery",
        "mechanical"
    ],
    "wof:name":"Cerdi Bvba",
    "wof:placetype":"venue"
},
  "geometry": {"coordinates":[3.2197990417,50.9269142151],"type":"Point"}
}