{
  "type": "Feature",
  "properties": {
    "addr:full":"Langstraat 7 Glabbeek Vlaams-Brabant 3384",
    "addr:housenumber":"7",
    "addr:postcode":"3384",
    "addr:street":"Langstraat",
    "iso:country":"BE",
    "sg:address":"Langstraat 7",
    "sg:city":"Glabbeek",
    "sg:orig_category":"Medische apparatuur, orthopedische artikelen and prothesen Fab",
    "sg:phone":"+32 16 77 99 32",
    "sg:postcode":"3384",
    "sg:province":"Vlaams-Brabant",
    "wof:name":"Didier Debuisson",
    "wof:placetype":"venue"
},
  "geometry": {"coordinates":[4.9215230942,50.875328064],"type":"Point"}
}