{
  "type": "Feature",
  "properties": {
    "addr:full":"Chauss\u00e9e De Mons 15 Bruxelles (anderlecht) Bruxelles-Capitale 1070",
    "addr:housenumber":"15",
    "addr:postcode":"1070",
    "addr:street":"Chausse\u0301E De Mons",
    "iso:country":"BE",
    "sg:address":"Chauss\u00e9e De Mons 15",
    "sg:city":"Bruxelles (anderlecht)",
    "sg:classifiers":[
        {
            "category":"Community Center",
            "type":"Public Place"
        }
    ],
    "sg:phone":"+32 2 524 03 03",
    "sg:postcode":"1070",
    "sg:province":"Bruxelles-Capitale",
    "sg:tags":[
        "medical"
    ],
    "wof:name":"Medisud",
    "wof:placetype":"venue"
},
  "geometry": {"coordinates":[4.3377671242,50.8446617126],"type":"Point"}
}