{
  "type": "Feature",
  "properties": {
    "addr:full":"Noordstraat 5 Damme (sijsele) West-Vlaanderen 8340",
    "addr:housenumber":"5",
    "addr:postcode":"8340",
    "addr:street":"Noordstraat",
    "iso:country":"BE",
    "sg:address":"Noordstraat 5",
    "sg:city":"Damme (sijsele)",
    "sg:classifiers":[
        {
            "category":"Recreation",
            "subcategory":"Amusement Park",
            "type":"Entertainment"
        }
    ],
    "sg:phone":"+32 50 35 60 40",
    "sg:postcode":"8340",
    "sg:province":"West-Vlaanderen",
    "sg:tags":[
        "attraction",
        "-",
        "sale",
        "fair",
        "hiring"
    ],
    "wof:name":"Janssens Verhuur",
    "wof:placetype":"venue"
},
  "geometry": {"coordinates":[3.3203909397,51.2042236328],"type":"Point"}
}