{
  "type": "Feature",
  "properties": {
    "addr:full":"A. Mervilliestraat 15 Zedelgem (aartrijke) West-Vlaanderen 8211",
    "addr:housenumber":"15",
    "addr:postcode":"8211",
    "addr:street":"Mervilliestraat",
    "iso:country":"BE",
    "sg:address":"A. Mervilliestraat 15",
    "sg:city":"Zedelgem (aartrijke)",
    "sg:classifiers":[
        {
            "category":"Food & Beverages",
            "subcategory":"Fruits & Vegetables",
            "type":"Retail Goods"
        }
    ],
    "sg:phone":"+32 50 20 94 79",
    "sg:postcode":"8211",
    "sg:province":"West-Vlaanderen",
    "sg:tags":[
        "-"
    ],
    "wof:name":"Tanghe D",
    "wof:placetype":"venue"
},
  "geometry": {"coordinates":[3.0889649391,51.1200408936],"type":"Point"}
}