{
  "type": "Feature",
  "properties": {
    "addr:full":"R.d.weert-saint-georges 43 Grez-doiceau Brabant Wallon 1390",
    "addr:housenumber":"43",
    "addr:postcode":"1390",
    "addr:street":"R.D.Weert-Saint-Georges",
    "iso:country":"BE",
    "sg:address":"R.d.weert-saint-georges 43",
    "sg:city":"Grez-doiceau",
    "sg:orig_category":"Tuinen",
    "sg:phone":"+32 10 86 81 18",
    "sg:postcode":"1390",
    "sg:province":"Brabant Wallon",
    "wof:name":"Uni-vert",
    "wof:placetype":"venue"
},
  "geometry": {"coordinates":[4.6700229645,50.7887496948],"type":"Point"}
}