{
  "type": "Feature",
  "properties": {
    "iso:country":"BE",
    "sg:address":"Rue L\u00e9opold I 360b",
    "sg:city":"Bruxelles (jette)",
    "sg:classifiers":[
        {
            "category":"Autos & Motor Vehicles",
            "subcategory":"Boat Sales",
            "type":"Retail Goods"
        }
    ],
    "sg:phone":"+32 2 425 00 25",
    "sg:postcode":"1090",
    "sg:province":"Bruxelles-Capitale",
    "sg:tags":[
        "automobile",
        "sunroof",
        "-",
        "roof"
    ],
    "wof:name":"Audity",
    "wof:placetype":"venue"
},
  "geometry": {"coordinates":[4.3321948051,50.874294281],"type":"Point"}
}