{
  "type": "Feature",
  "properties": {
    "addr:full":"Chauss\u00e9e De Charleroi 4 Nivelles Brabant Wallon 1400",
    "addr:housenumber":"4",
    "addr:postcode":"1400",
    "addr:street":"Chausse\u0301E De Charleroi",
    "iso:country":"BE",
    "sg:address":"Chauss\u00e9e De Charleroi 4",
    "sg:city":"Nivelles",
    "sg:classifiers":[
        {
            "category":"Wholesale",
            "subcategory":"Books, Periodicals, & Newspapers",
            "type":"Manufacturing & Wholesale Goods"
        }
    ],
    "sg:phone":"+32 67 21 85 49",
    "sg:postcode":"1400",
    "sg:province":"Brabant Wallon",
    "sg:tags":[
        "banner"
    ],
    "wof:name":"Seridel",
    "wof:placetype":"venue"
},
  "geometry": {"coordinates":[4.3316469193,50.5884246826],"type":"Point"}
}