{
  "type": "Feature",
  "properties": {
    "addr:full":"Pauwengraaf 98 Eisden Limburg 3640",
    "addr:housenumber":"98",
    "addr:postcode":"3640",
    "addr:street":"Pauwengraaf",
    "iso:country":"BE",
    "sg:address":"Pauwengraaf 98",
    "sg:city":"Eisden",
    "sg:classifiers":[
        {
            "category":"Banks & Credit Unions",
            "subcategory":"Bank",
            "type":"Services"
        }
    ],
    "sg:phone":"+32 11 76 46 50",
    "sg:postcode":"3640",
    "sg:province":"Limburg",
    "wof:name":"Aslk-cger Bank",
    "wof:placetype":"venue"
},
  "geometry": {"coordinates":[5.69252491,50.9886817932],"type":"Point"}
}