{
  "type": "Feature",
  "properties": {
    "addr:full":"Dorpsstraat 24 Diest Vlaams-Brabant 3294",
    "addr:housenumber":"24",
    "addr:postcode":"3294",
    "addr:street":"Dorpsstraat",
    "iso:country":"BE",
    "sg:address":"Dorpsstraat 24",
    "sg:city":"Diest",
    "sg:orig_category":"Banken and kredietinstellingen",
    "sg:phone":"+32 13 35 15 60",
    "sg:postcode":"3294",
    "sg:province":"Vlaams-Brabant",
    "wof:name":"Kbc",
    "wof:placetype":"venue"
},
  "geometry": {"coordinates":[5.0160470009,51.0033454895],"type":"Point"}
}