{
  "type": "Feature",
  "properties": {
    "addr:full":"Pauwelslei 115 Brasschaat Antwerpen 2930",
    "addr:housenumber":"115",
    "addr:postcode":"2930",
    "addr:street":"Pauwelslei",
    "iso:country":"BE",
    "sg:address":"Pauwelslei 115",
    "sg:city":"Brasschaat",
    "sg:classifiers":[
        {
            "category":"Building & Trades",
            "subcategory":"Construction",
            "type":"Services"
        }
    ],
    "sg:phone":"+32 3 651 78 02",
    "sg:postcode":"2930",
    "sg:province":"Antwerpen",
    "sg:tags":[
        "paper",
        "hanger"
    ],
    "wof:name":"Boyens Danny Cvba",
    "wof:placetype":"venue"
},
  "geometry": {"coordinates":[4.5138130188,51.3021202087],"type":"Point"}
}