{
  "type": "Feature",
  "properties": {
    "addr:full":"Achterdiedonken 9 Bonheiden Antwerpen 2820",
    "addr:housenumber":"9",
    "addr:postcode":"2820",
    "addr:street":"Achterdiedonken",
    "iso:country":"BE",
    "sg:address":"Achterdiedonken 9",
    "sg:city":"Bonheiden",
    "sg:classifiers":[
        {
            "category":"Professional",
            "subcategory":"Management & Consulting",
            "type":"Services"
        }
    ],
    "sg:phone":"+32 15 55 77 80",
    "sg:postcode":"2820",
    "sg:province":"Antwerpen",
    "sg:tags":[
        "-",
        "processing",
        "data",
        "consultant"
    ],
    "wof:name":"Willemot A",
    "wof:placetype":"venue"
},
  "geometry": {"coordinates":[4.5400910378,51.0433921814],"type":"Point"}
}