{
  "type": "Feature",
  "properties": {
    "iso:country":"BE",
    "sg:address":"Rue Du Vert Coron 103",
    "sg:city":"Peruwelz",
    "sg:orig_category":"Travaux de finition and nettoyage de b\u00e2timents. Charpentes and couvertures",
    "sg:phone":"+32 69 77 35 00",
    "sg:postcode":"7600",
    "sg:province":"Hainaut",
    "wof:name":"Robert Procureur",
    "wof:placetype":"venue"
},
  "geometry": {"coordinates":[3.6068489552,50.5053672791],"type":"Point"}
}