{
  "type": "Feature",
  "properties": {
    "iso:country":"BE",
    "sg:address":"Beversluisweg 3",
    "sg:city":"Putte",
    "sg:classifiers":[
        {
            "category":"Wholesale",
            "subcategory":"Fruits & Vegetables",
            "type":"Manufacturing & Wholesale Goods"
        }
    ],
    "sg:postcode":"2580",
    "sg:province":"Antwerpen",
    "sg:tags":[
        "whol",
        "-"
    ],
    "wof:name":"Van Looy J",
    "wof:placetype":"venue"
},
  "geometry": {"coordinates":[4.6571340561,51.0230064392],"type":"Point"}
}