{
  "type": "Feature",
  "properties": {
    "addr:full":"Rue L\u00c9on-fr\u00c9d\u00c9ricq 28 Li\u00c8ge Li\u00e8ge 4020",
    "addr:housenumber":"28",
    "addr:postcode":"4020",
    "addr:street":"Rue Le\u0301On-Fre\u0301De\u0301Ricq",
    "iso:country":"BE",
    "sg:address":"Rue L\u00c9on-fr\u00c9d\u00c9ricq 28",
    "sg:city":"Li\u00c8ge",
    "sg:orig_category":"Boekhouders",
    "sg:phone":"+32 4 342 01 15",
    "sg:postcode":"4020",
    "sg:province":"Li\u00e8ge",
    "wof:name":"Andre Vanloo",
    "wof:placetype":"venue"
},
  "geometry": {"coordinates":[5.5756578445,50.6338539124],"type":"Point"}
}