{
  "type": "Feature",
  "properties": {
    "addr:full":"Rue Des Guillemins 76 Li\u00c8ge Li\u00e8ge 4000",
    "addr:housenumber":"76",
    "addr:postcode":"4000",
    "addr:street":"Rue Des Guillemins",
    "iso:country":"BE",
    "sg:address":"Rue Des Guillemins 76",
    "sg:city":"Li\u00c8ge",
    "sg:orig_category":"Beautyfarms, relaxatie and lichamelijk welzijn Dameskledingzaken Lingerie and ondergoed Schoonheidss",
    "sg:phone":"+32 4 253 26 66",
    "sg:postcode":"4000",
    "sg:province":"Li\u00e8ge",
    "wof:name":"Institut Cybelle",
    "wof:placetype":"venue"
},
  "geometry": {"coordinates":[5.5667901039,50.6277275085],"type":"Point"}
}