{
  "type": "Feature",
  "properties": {
    "iso:country":"BE",
    "sg:address":"Beukenlaan 34",
    "sg:city":"Alken",
    "sg:classifiers":[
        {
            "category":"Professional",
            "subcategory":"Engineering",
            "type":"Services"
        }
    ],
    "sg:phone":"+32 11 59 29 01",
    "sg:postcode":"3570",
    "sg:province":"Limburg",
    "sg:tags":[
        "-"
    ],
    "wof:name":"Jefferson",
    "wof:placetype":"venue"
},
  "geometry": {"coordinates":[5.2803320885,50.8984336853],"type":"Point"}
}