{
  "type": "Feature",
  "properties": {
    "addr:full":"Rue Eikenbos 35a Rhode-saint-gen\u00e8se Vlaams-Brabant 1640",
    "addr:housenumber":"35a",
    "addr:postcode":"1640",
    "addr:street":"Rue Eikenbos",
    "iso:country":"BE",
    "sg:address":"Rue Eikenbos 35a",
    "sg:city":"Rhode-saint-gen\u00e8se",
    "sg:classifiers":[
        {
            "category":"Social Services",
            "type":"Services"
        }
    ],
    "sg:phone":"+32 2 380 66 79",
    "sg:postcode":"1640",
    "sg:province":"Vlaams-Brabant",
    "wof:name":"Le Levain pour Les Pauvres Vzw",
    "wof:placetype":"venue"
},
  "geometry": {"coordinates":[4.3603811264,50.7362251282],"type":"Point"}
}