{
  "type": "Feature",
  "properties": {
    "iso:country":"BE",
    "sg:address":"Rue Emile Tumelaire 65",
    "sg:city":"Charleroi",
    "sg:classifiers":[
        {
            "category":"Professional",
            "subcategory":"Lawyer & Legal Services",
            "type":"Services"
        }
    ],
    "sg:phone":"+32 71 32 48 08",
    "sg:postcode":"6000",
    "sg:province":"Hainaut",
    "wof:name":"Mayence J-ph",
    "wof:placetype":"venue"
},
  "geometry": {"coordinates":[4.4501919746,50.4096794128],"type":"Point"}
}