{
  "type": "Feature",
  "properties": {
    "iso:country":"BE",
    "sg:address":"Prins-regentstraat 17ba",
    "sg:city":"Menen",
    "sg:orig_category":"Herstellingen and onderhoud aan huis voor voertuigen Herstellingen and onderhoud van auto's Metaalaf",
    "sg:phone":"+32 56 41 26 85",
    "sg:postcode":"8930",
    "sg:province":"West-Vlaanderen",
    "wof:name":"Rudy Coeman",
    "wof:placetype":"venue"
},
  "geometry": {"coordinates":[3.1209149361,50.7961845398],"type":"Point"}
}