{
  "type": "Feature",
  "properties": {
    "iso:country":"BE",
    "sg:address":"Koning Leopoldlaan 81bb",
    "sg:city":"Maldegem",
    "sg:orig_category":"Installation de menuiserie m\u00e9tallique",
    "sg:phone":"+32 50 71 18 93",
    "sg:postcode":"9990",
    "sg:province":"Oost-Vlaanderen",
    "wof:name":"Van Hyfte",
    "wof:placetype":"venue"
},
  "geometry": {"coordinates":[3.4647979736,51.2040176392],"type":"Point"}
}