{
  "type": "Feature",
  "properties": {
    "addr:full":"Gentseweg 588 Waregem West-Vlaanderen 8793",
    "addr:housenumber":"588",
    "addr:postcode":"8793",
    "addr:street":"Gentseweg",
    "iso:country":"BE",
    "sg:address":"Gentseweg 588",
    "sg:city":"Waregem",
    "sg:orig_category":"Catering and organisatie van feesten",
    "sg:phone":"+32 56 60 17 63",
    "sg:postcode":"8793",
    "sg:province":"West-Vlaanderen",
    "wof:name":"Lisabeth Mazereel",
    "wof:placetype":"venue"
},
  "geometry": {"coordinates":[3.4084649086,50.9025650024],"type":"Point"}
}