{
  "type": "Feature",
  "properties": {
    "iso:country":"BE",
    "sg:address":"Koning Albertstraat 8",
    "sg:city":"Mechelen",
    "sg:orig_category":"Electrom\u00e9nager, t\u00e9l\u00e9visions and radios",
    "sg:phone":"+32 15 20 42 50",
    "sg:postcode":"2800",
    "sg:province":"Antwerpen",
    "wof:name":"Nestor Van Riet",
    "wof:placetype":"venue"
},
  "geometry": {"coordinates":[4.4787521362,51.020324707],"type":"Point"}
}