{
  "type": "Feature",
  "properties": {
    "iso:country":"BE",
    "sg:address":"Smissestraat 44",
    "sg:city":"Ledegem (sint-eloois-winkel)",
    "sg:classifiers":[
        {
            "category":"Personal",
            "subcategory":"Beauty Salon",
            "type":"Services"
        }
    ],
    "sg:phone":"+32 56 50 01 43",
    "sg:postcode":"8880",
    "sg:province":"West-Vlaanderen",
    "wof:name":"Lagae L",
    "wof:placetype":"venue"
},
  "geometry": {"coordinates":[3.1826329231,50.8742599487],"type":"Point"}
}