{
  "type": "Feature",
  "properties": {
    "addr:full":"Schildhovenstraat 24 Kampenhout Vlaams-Brabant 1910",
    "addr:housenumber":"24",
    "addr:postcode":"1910",
    "addr:street":"Schildhovenstraat",
    "iso:country":"BE",
    "sg:address":"Schildhovenstraat 24",
    "sg:city":"Kampenhout",
    "sg:orig_category":"Boekhouders",
    "sg:phone":"+32 16 65 72 82",
    "sg:postcode":"1910",
    "sg:province":"Vlaams-Brabant",
    "wof:name":"Mireille Budts",
    "wof:placetype":"venue"
},
  "geometry": {"coordinates":[4.5728449821,50.9455795288],"type":"Point"}
}