{
  "type": "Feature",
  "properties": {
    "addr:full":"Diestse 430 Aarschot Vlaams-Brabant 3200",
    "addr:housenumber":"430",
    "addr:postcode":"3200",
    "addr:street":"Diestse",
    "iso:country":"BE",
    "sg:address":"Diestse 430",
    "sg:city":"Aarschot",
    "sg:classifiers":[
        {
            "category":"Banks & Credit Unions",
            "subcategory":"Bank",
            "type":"Services"
        }
    ],
    "sg:phone":"+32 16 50 26 31",
    "sg:postcode":"3200",
    "sg:province":"Vlaams-Brabant",
    "wof:name":"G\u00e9n\u00e9rale De Banque Sa",
    "wof:placetype":"venue"
},
  "geometry": {"coordinates":[4.8655099869,50.9781112671],"type":"Point"}
}