{
  "type": "Feature",
  "properties": {
    "addr:full":"Rue De Lustin 22 Assesse Namur 5330",
    "addr:housenumber":"22",
    "addr:postcode":"5330",
    "addr:street":"Rue De Lustin",
    "iso:country":"BE",
    "sg:address":"Rue De Lustin 22",
    "sg:city":"Assesse",
    "sg:orig_category":"Slagers",
    "sg:phone":"+32 83 65 52 58",
    "sg:postcode":"5330",
    "sg:province":"Namur",
    "wof:name":"Francis Genette",
    "wof:placetype":"venue"
},
  "geometry": {"coordinates":[4.9710087776,50.3783187866],"type":"Point"}
}