{
  "type": "Feature",
  "properties": {
    "addr:full":"Baarstraat 53 Oudenaarde Oost-Vlaanderen 9700",
    "addr:housenumber":"53",
    "addr:postcode":"9700",
    "addr:street":"Baarstraat",
    "iso:country":"BE",
    "sg:address":"Baarstraat 53",
    "sg:city":"Oudenaarde",
    "sg:orig_category":"M\u00e9decins and sp\u00e9cialistes",
    "sg:phone":"+32 55 31 18 23",
    "sg:postcode":"9700",
    "sg:province":"Oost-Vlaanderen",
    "wof:name":"V. De Wolf",
    "wof:placetype":"venue"
},
  "geometry": {"coordinates":[3.607544899,50.8393096924],"type":"Point"}
}