{
  "type": "Feature",
  "properties": {
    "addr:full":"Leuvensestraat 134 Tienen Vlaams-Brabant 3300",
    "addr:housenumber":"134",
    "addr:postcode":"3300",
    "addr:street":"Leuvensestraat",
    "iso:country":"BE",
    "sg:address":"Leuvensestraat 134",
    "sg:city":"Tienen",
    "sg:classifiers":[
        {
            "category":"Shopping",
            "subcategory":"Party Supplies",
            "type":"Retail Goods"
        }
    ],
    "sg:phone":"+32 16 81 45 81",
    "sg:postcode":"3300",
    "sg:province":"Vlaams-Brabant",
    "sg:tags":[
        "hunting"
    ],
    "wof:name":"Hero",
    "wof:placetype":"venue"
},
  "geometry": {"coordinates":[4.9242811203,50.8113059998],"type":"Point"}
}