{
  "type": "Feature",
  "properties": {
    "addr:full":"Bevrijdingsln 155 Gent Oost-Vlaanderen 9000",
    "addr:housenumber":"155",
    "addr:postcode":"9000",
    "addr:street":"Oost-Vlaanderen",
    "iso:country":"BE",
    "sg:address":"Bevrijdingsln 155",
    "sg:city":"Gent",
    "sg:classifiers":[
        {
            "category":"Banks & Credit Unions",
            "subcategory":"Bank",
            "type":"Services"
        }
    ],
    "sg:phone":"+32 9 226 77 05",
    "sg:postcode":"9000",
    "sg:province":"Oost-Vlaanderen",
    "wof:name":"Banque Bruxelles Lambert Sa",
    "wof:placetype":"venue"
},
  "geometry": {"coordinates":[3.6986429691,51.0624275208],"type":"Point"}
}