{
  "type": "Feature",
  "properties": {
    "iso:country":"BE",
    "sg:address":"Meersenierstraat 12",
    "sg:city":"Gent",
    "sg:orig_category":"V\u00eatements. V\u00eatements pour Hommes. Chaussures",
    "sg:phone":"+32 9 233 82 69",
    "sg:postcode":"9000",
    "sg:province":"Oost-Vlaanderen",
    "wof:name":"Obius",
    "wof:placetype":"venue"
},
  "geometry": {"coordinates":[3.7243850231,51.057559967],"type":"Point"}
}