{
  "type": "Feature",
  "properties": {
    "addr:full":"Hammestraat 45 Aalst Oost-Vlaanderen 9300",
    "addr:housenumber":"45",
    "addr:postcode":"9300",
    "addr:street":"Hammestraat",
    "iso:country":"BE",
    "sg:address":"Hammestraat 45",
    "sg:city":"Aalst",
    "sg:classifiers":[
        {
            "category":"Building & Trades",
            "subcategory":"Landscaping Services",
            "type":"Services"
        }
    ],
    "sg:phone":"+32 53 70 58 09",
    "sg:postcode":"9300",
    "sg:province":"Oost-Vlaanderen",
    "sg:tags":[
        "access",
        "pond",
        "laying-out",
        "-"
    ],
    "wof:name":"Aep",
    "wof:placetype":"venue"
},
  "geometry": {"coordinates":[4.0476508141,50.9631843567],"type":"Point"}
}