{
  "type": "Feature",
  "properties": {
    "iso:country":"BE",
    "sg:address":"Rue De La Station 115",
    "sg:city":"Walcourt",
    "sg:classifiers":[
        {
            "category":"Real Estate",
            "subcategory":"Architect",
            "type":"Services"
        }
    ],
    "sg:phone":"+32 71 61 42 66",
    "sg:postcode":"5650",
    "sg:province":"Namur",
    "wof:name":"Donceel Ph",
    "wof:placetype":"venue"
},
  "geometry": {"coordinates":[4.437584877,50.2582359314],"type":"Point"}
}