{
  "type": "Feature",
  "properties": {
    "iso:country":"BE",
    "sg:address":"Bergense Steenweg 69",
    "sg:city":"Anderlecht/anderlecht",
    "sg:orig_category":"Voertuigen",
    "sg:phone":"+32 2 521 75 44",
    "sg:postcode":"1070",
    "sg:province":"Bruxelles-Capitale",
    "wof:name":"Solibex",
    "wof:placetype":"venue"
},
  "geometry": {"coordinates":[4.3349089622,50.843875885],"type":"Point"}
}