{
  "type": "Feature",
  "properties": {
    "iso:country":"BE",
    "sg:address":"Schepsveld 17",
    "sg:city":"Balen",
    "sg:classifiers":[
        {
            "category":"Professional",
            "subcategory":"Printing & Photocopies",
            "type":"Services"
        }
    ],
    "sg:phone":"+32 14 81 33 23",
    "sg:postcode":"2490",
    "sg:province":"Antwerpen",
    "sg:tags":[
        "-",
        "publishing",
        "desktop"
    ],
    "wof:name":"Montana",
    "wof:placetype":"venue"
},
  "geometry": {"coordinates":[5.1752710342,51.1594772339],"type":"Point"}
}