{
  "type": "Feature",
  "properties": {
    "iso:country":"BE",
    "sg:address":"Industriepark Noord",
    "sg:city":"Mechelen",
    "sg:classifiers":[
        {
            "category":"Professional",
            "subcategory":"Art Services",
            "type":"Services"
        }
    ],
    "sg:phone":"+32 15 28 73 00",
    "sg:postcode":"2800",
    "sg:province":"Antwerpen",
    "sg:tags":[
        "realization",
        "audio-visual"
    ],
    "wof:name":"Option Facilities Nv",
    "wof:placetype":"venue"
},
  "geometry": {"coordinates":[4.4854397774,51.0289268494],"type":"Point"}
}