{
  "type": "Feature",
  "properties": {
    "addr:full":"Tielensteenweg 96 Kasterlee Antwerpen 2460",
    "addr:housenumber":"96",
    "addr:postcode":"2460",
    "addr:street":"Tielensteenweg",
    "iso:country":"BE",
    "sg:address":"Tielensteenweg 96",
    "sg:city":"Kasterlee",
    "sg:orig_category":"Opticiens",
    "sg:phone":"+32 14 55 64 79",
    "sg:postcode":"2460",
    "sg:province":"Antwerpen",
    "wof:name":"Trioptic",
    "wof:placetype":"venue"
},
  "geometry": {"coordinates":[4.900949955,51.239238739],"type":"Point"}
}