{
  "type": "Feature",
  "properties": {
    "addr:full":"Wildetijmstraat 22 Genk (waterschei) Limburg 3600",
    "addr:housenumber":"22",
    "addr:postcode":"3600",
    "addr:street":"Wildetijmstraat",
    "iso:country":"BE",
    "sg:address":"Wildetijmstraat 22",
    "sg:city":"Genk (waterschei)",
    "sg:orig_category":"Fairs, shows, exhibitions",
    "sg:phone":"+32 89 84 53 57",
    "sg:postcode":"3600",
    "sg:province":"Limburg",
    "wof:name":"Tuinbeurs-hobbybeurs Hasselt Bvba",
    "wof:placetype":"venue"
},
  "geometry": {"coordinates":[5.5120520592,50.9946289062],"type":"Point"}
}