{
  "type": "Feature",
  "properties": {
    "addr:full":"Avenue Mar\u00c9chal Foch 902 Mons Hainaut 7012",
    "addr:housenumber":"902",
    "addr:postcode":"7012",
    "addr:street":"Avenue Mare\u0301Chal Foch;Hainaut",
    "iso:country":"BE",
    "sg:address":"Avenue Mar\u00c9chal Foch 902",
    "sg:city":"Mons",
    "sg:orig_category":"R\u00e9parations d'appareils \u00e9lectrom\u00e9nagers. Electrom\u00e9nager, t\u00e9l\u00e9visions and radios",
    "sg:phone":"+32 65 88 46 24",
    "sg:postcode":"7012",
    "sg:province":"Hainaut",
    "wof:name":"Maison Kit-tec",
    "wof:placetype":"venue"
},
  "geometry": {"coordinates":[3.8894600868,50.4481964111],"type":"Point"}
}