{
  "type": "Feature",
  "properties": {
    "iso:country":"BE",
    "sg:address":"Rue De Looz 9",
    "sg:city":"Ans",
    "sg:orig_category":"Eleveurs and marchands de porcs",
    "sg:phone":"+32 4 257 42 43",
    "sg:postcode":"4432",
    "sg:province":"Li\u00e8ge",
    "wof:name":"Joseph Servais",
    "wof:placetype":"venue"
},
  "geometry": {"coordinates":[5.4823908806,50.705280304],"type":"Point"}
}