{
  "type": "Feature",
  "properties": {
    "addr:full":"Domaine Provincial Genk Limburg 3600",
    "addr:postcode":"3600",
    "addr:street":"Limburg",
    "iso:country":"BE",
    "sg:address":"Domaine Provincial",
    "sg:city":"Genk",
    "sg:orig_category":"Luna-parks and parcs de r\u00e9cr\u00e9ation. Mus\u00e9es and patrimoine culturel. Restaurants",
    "sg:phone":"+32 11 26 53 00",
    "sg:postcode":"3600",
    "sg:province":"Limburg",
    "wof:name":"Domein Bokrijk",
    "wof:placetype":"venue"
},
  "geometry": {"coordinates":[5.4990148544,50.9635848999],"type":"Point"}
}