{
  "type": "Feature",
  "properties": {
    "addr:full":"Luikstraat 4 Anvers (grand) Antwerpen 2000",
    "addr:housenumber":"4",
    "addr:postcode":"2000",
    "addr:street":"Luikstraat;Grand Antwerpen",
    "iso:country":"BE",
    "sg:address":"Luikstraat 4",
    "sg:city":"Anvers (grand)",
    "sg:classifiers":[
        {
            "category":"Restaurant",
            "type":"Food & Drink"
        }
    ],
    "sg:phone":"+32 3 294 02 93",
    "sg:postcode":"2000",
    "sg:province":"Antwerpen",
    "wof:name":"Little Budha",
    "wof:placetype":"venue"
},
  "geometry": {"coordinates":[4.3887929916,51.2105484009],"type":"Point"}
}