{
  "type": "Feature",
  "properties": {
    "addr:full":"Nijverheidslaan 31 Deerlijk West-Vlaanderen 8540",
    "addr:housenumber":"31",
    "addr:postcode":"8540",
    "addr:street":"Nijverheidslaan",
    "iso:country":"BE",
    "sg:address":"Nijverheidslaan 31",
    "sg:city":"Deerlijk",
    "sg:classifiers":[
        {
            "category":"Utilities",
            "subcategory":"Telephone",
            "type":"Services"
        }
    ],
    "sg:phone":"+32 3 380 10 80",
    "sg:postcode":"8540",
    "sg:province":"West-Vlaanderen",
    "sg:tags":[
        "system"
    ],
    "wof:name":"Optitecht Telecom",
    "wof:placetype":"venue"
},
  "geometry": {"coordinates":[4.4737257957,51.2215270996],"type":"Point"}
}