{
  "type": "Feature",
  "properties": {
    "addr:full":"Ninoofse Steenweg 58 Gooik Vlaams-Brabant 1755",
    "addr:housenumber":"58",
    "addr:postcode":"1755",
    "addr:street":"Ninoofse Steenweg",
    "iso:country":"BE",
    "sg:address":"Ninoofse Steenweg 58",
    "sg:city":"Gooik",
    "sg:classifiers":[
        {
            "category":"Social Services",
            "subcategory":"Job Training",
            "type":"Services"
        }
    ],
    "sg:phone":"+32 54 56 60 28",
    "sg:postcode":"1755",
    "sg:province":"Vlaams-Brabant",
    "sg:tags":[
        "condiment",
        "spice"
    ],
    "wof:name":"De Loecker Bvba",
    "wof:placetype":"venue"
},
  "geometry": {"coordinates":[4.0935058594,50.7799072266],"type":"Point"}
}