{
  "type": "Feature",
  "properties": {
    "addr:full":"Zwevegemstraat 97a Zwevegem (otegem) West-Vlaanderen 8553",
    "addr:housenumber":"97a",
    "addr:postcode":"8553",
    "addr:street":"Zwevegemstraat",
    "iso:country":"BE",
    "sg:address":"Zwevegemstraat 97a",
    "sg:city":"Zwevegem (otegem)",
    "sg:classifiers":[
        {
            "category":"Personal",
            "subcategory":"Psychics & Astrologers",
            "type":"Services"
        }
    ],
    "sg:phone":"+32 56 77 10 90",
    "sg:postcode":"8553",
    "sg:province":"West-Vlaanderen",
    "sg:tags":[
        "astrology"
    ],
    "wof:name":"Vandemaele K",
    "wof:placetype":"venue"
},
  "geometry": {"coordinates":[3.4085550308,50.8128128052],"type":"Point"}
}