{
  "type": "Feature",
  "properties": {
    "addr:full":"Chauss\u00e9e De Dinant 10 Yvoir (spontin) Namur 5530",
    "addr:housenumber":"10",
    "addr:postcode":"5530",
    "addr:street":"Chausse\u0301E De Dinant",
    "iso:country":"BE",
    "sg:address":"Chauss\u00e9e De Dinant 10",
    "sg:city":"Yvoir (spontin)",
    "sg:classifiers":[
        {
            "category":"Travel",
            "subcategory":"Hotels & Motels",
            "type":"Entertainment"
        }
    ],
    "sg:phone":"+32 83 69 01 54",
    "sg:postcode":"5530",
    "sg:province":"Namur",
    "wof:name":"Hostellerie Du Bocq",
    "wof:placetype":"venue"
},
  "geometry": {"coordinates":[5.0079679489,50.322052002],"type":"Point"}
}