{
  "type": "Feature",
  "properties": {
    "addr:full":"Koning Albertstraat 41 Diest Vlaams-Brabant 3290",
    "addr:housenumber":"41",
    "addr:postcode":"3290",
    "addr:street":"Koning Albertstraat",
    "iso:country":"BE",
    "sg:address":"Koning Albertstraat 41",
    "sg:city":"Diest",
    "sg:classifiers":[
        {
            "category":"Taxi",
            "type":"Transportation"
        }
    ],
    "sg:phone":"+32 495 25 07 50",
    "sg:postcode":"3290",
    "sg:province":"Vlaams-Brabant",
    "sg:tags":[
        "taxicab"
    ],
    "wof:name":"Taxi Dienst Vbl Bvba",
    "wof:placetype":"venue"
},
  "geometry": {"coordinates":[5.0532917976,50.9860839844],"type":"Point"}
}