{
  "type": "Feature",
  "properties": {
    "iso:country":"BE",
    "sg:address":"Kasteelstraat 14",
    "sg:city":"Kortessem (guigoven)",
    "sg:classifiers":[
        {
            "category":"Retail",
            "subcategory":"Repair Shop",
            "type":"Services"
        }
    ],
    "sg:phone":"+32 11 37 68 64",
    "sg:postcode":"3723",
    "sg:province":"Limburg",
    "sg:tags":[
        "upholsterer"
    ],
    "wof:name":"Vanelderen R",
    "wof:placetype":"venue"
},
  "geometry": {"coordinates":[5.4003949165,50.8377609253],"type":"Point"}
}