{
  "type": "Feature",
  "properties": {
    "iso:country":"BE",
    "sg:address":"Kruittorenwal 17",
    "sg:city":"Bree",
    "sg:classifiers":[
        {
            "category":"Education",
            "subcategory":"School",
            "type":"Public Place"
        }
    ],
    "sg:phone":"+32 89 46 75 85",
    "sg:postcode":"3960",
    "sg:province":"Limburg",
    "sg:tags":[
        "-",
        "private"
    ],
    "wof:name":"Helmie's Beauty Concept",
    "wof:placetype":"venue"
},
  "geometry": {"coordinates":[5.5949940681,51.1410675049],"type":"Point"}
}