{
  "type": "Feature",
  "properties": {
    "addr:full":"Groenstraat 6 Ingelmunster West-Vlaanderen 8770",
    "addr:housenumber":"6",
    "addr:postcode":"8770",
    "addr:street":"Groenstraat",
    "iso:country":"BE",
    "sg:address":"Groenstraat 6",
    "sg:city":"Ingelmunster",
    "sg:orig_category":"Producteurs de l\u00e9gumes",
    "sg:phone":"+32 51 30 31 37",
    "sg:postcode":"8770",
    "sg:province":"West-Vlaanderen",
    "wof:name":"Marcel Tack",
    "wof:placetype":"venue"
},
  "geometry": {"coordinates":[3.2496480942,50.9295272827],"type":"Point"}
}