{
  "type": "Feature",
  "properties": {
    "iso:country":"BE",
    "sg:address":"Assesteenweg 136",
    "sg:city":"Edingen",
    "sg:classifiers":[
        {
            "category":"Building & Trades",
            "subcategory":"Construction",
            "type":"Services"
        }
    ],
    "sg:phone":"+32 2 395 85 00",
    "sg:postcode":"7850",
    "sg:province":"Hainaut",
    "sg:tags":[
        "industry",
        "air-conditioning",
        "system"
    ],
    "wof:name":"Limko N.v.-s.a.",
    "wof:placetype":"venue"
},
  "geometry": {"coordinates":[4.053647995,50.6995048523],"type":"Point"}
}