{
  "type": "Feature",
  "properties": {
    "iso:country":"BE",
    "sg:address":"Rue Plein-vent 22",
    "sg:city":"Baelen/baelen",
    "sg:orig_category":"Installation de menuiserie en bois and plastique",
    "sg:phone":"+32 87 76 37 68",
    "sg:postcode":"4837",
    "sg:province":"Li\u00e8ge",
    "wof:name":"Straet Et Corman",
    "wof:placetype":"venue"
},
  "geometry": {"coordinates":[5.9705529213,50.6364402771],"type":"Point"}
}