{
  "type": "Feature",
  "properties": {
    "iso:country":"BE",
    "sg:address":"Bergstraat 2ba",
    "sg:city":"Koekelare",
    "sg:classifiers":[
        {
            "category":"Arena",
            "subcategory":"Sports Club",
            "type":"Entertainment"
        }
    ],
    "sg:phone":"+32 51 58 98 50",
    "sg:postcode":"8680",
    "sg:province":"West-Vlaanderen",
    "sg:tags":[
        "de"
    ],
    "wof:name":"D & W Koekelare",
    "wof:placetype":"venue"
},
  "geometry": {"coordinates":[2.9952290058,51.0904197693],"type":"Point"}
}