{
  "type": "Feature",
  "properties": {
    "addr:full":"Gommerijnstraat 12a Heist-op-den-berg Antwerpen 2220",
    "addr:housenumber":"12a",
    "addr:postcode":"2220",
    "addr:street":"Gommerijnstraat",
    "iso:country":"BE",
    "sg:address":"Gommerijnstraat 12a",
    "sg:city":"Heist-op-den-berg",
    "sg:classifiers":[
        {
            "category":"Personal",
            "subcategory":"Beauty Salon",
            "type":"Services"
        }
    ],
    "sg:phone":"+32 15 23 62 76",
    "sg:postcode":"2220",
    "sg:province":"Antwerpen",
    "sg:tags":[
        "lady",
        "-",
        "hairdressing"
    ],
    "wof:name":"Sylvia",
    "wof:placetype":"venue"
},
  "geometry": {"coordinates":[4.7161898613,51.0391693115],"type":"Point"}
}