{
  "type": "Feature",
  "properties": {
    "addr:full":"Rue Marechal Foch 35 Chatelet Hainaut 6200",
    "addr:housenumber":"35",
    "addr:postcode":"6200",
    "addr:street":"Rue Marechal Foch;Hainaut",
    "iso:country":"BE",
    "sg:address":"Rue Marechal Foch 35",
    "sg:city":"Chatelet",
    "sg:orig_category":"Blanchisseries and teintureries",
    "sg:phone":"+32 71 39 51 87",
    "sg:postcode":"6200",
    "sg:province":"Hainaut",
    "wof:name":"As Du Sec",
    "wof:placetype":"venue"
},
  "geometry": {"coordinates":[4.518389225,50.4100532532],"type":"Point"}
}