{
  "type": "Feature",
  "properties": {
    "addr:full":"Rue De La Place 12 Walcourt Namur 5650",
    "addr:housenumber":"12",
    "addr:postcode":"5650",
    "addr:street":"Rue De La Place",
    "iso:country":"BE",
    "sg:address":"Rue De La Place 12",
    "sg:city":"Walcourt",
    "sg:orig_category":"Dakwerken",
    "sg:phone":"+32 476 72 78 31",
    "sg:postcode":"5650",
    "sg:province":"Namur",
    "wof:name":"Fe. Bykans",
    "wof:placetype":"venue"
},
  "geometry": {"coordinates":[4.4316239357,50.2521972656],"type":"Point"}
}