{
  "type": "Feature",
  "properties": {
    "iso:country":"BE",
    "sg:address":"Prins Leopoldsquare 34",
    "sg:city":"Brussel/bruxelles",
    "sg:orig_category":"Pleisterwerk",
    "sg:phone":"+32 2 478 39 13",
    "sg:postcode":"1020",
    "sg:province":"Bruxelles-Capitale",
    "wof:name":"Jacques Dekeuleneer",
    "wof:placetype":"venue"
},
  "geometry": {"coordinates":[4.3400359154,50.884185791],"type":"Point"}
}