{
  "type": "Feature",
  "properties": {
    "iso:country":"BE",
    "sg:address":"Avenue E Demolder 134",
    "sg:city":"Brussel",
    "sg:orig_category":"Ruimtes voor conferenties, recepties and feesten",
    "sg:phone":"+32 2 216 73 05",
    "sg:postcode":"1030",
    "sg:province":"Bruxelles-Capitale",
    "wof:name":"Respel",
    "wof:placetype":"venue"
},
  "geometry": {"coordinates":[4.3827681541,50.8733444214],"type":"Point"}
}