{
  "type": "Feature",
  "properties": {
    "iso:country":"BE",
    "sg:address":"Rue Des Canadiens 16",
    "sg:city":"Mons",
    "sg:orig_category":"Enseignement maternel and primaire",
    "sg:phone":"+32 65 35 49 73",
    "sg:postcode":"7022",
    "sg:province":"Hainaut",
    "wof:name":"Ecole Maternelle Libre",
    "wof:placetype":"venue"
},
  "geometry": {"coordinates":[3.9597499371,50.4379806519],"type":"Point"}
}