{
  "type": "Feature",
  "properties": {
    "addr:full":"Prosper De Troyerstraat 32 Mechelen Antwerpen 2800",
    "addr:housenumber":"32",
    "addr:postcode":"2800",
    "addr:street":"Prosper De Troyerstraat",
    "iso:country":"BE",
    "sg:address":"Prosper De Troyerstraat 32",
    "sg:city":"Mechelen",
    "sg:orig_category":"Diverse grafische activiteiten",
    "sg:phone":"+32 15 26 04 74",
    "sg:postcode":"2800",
    "sg:province":"Antwerpen",
    "wof:name":"Graphic Commun. Intern.",
    "wof:placetype":"venue"
},
  "geometry": {"coordinates":[4.4643101692,51.0331993103],"type":"Point"}
}