{
  "type": "Feature",
  "properties": {
    "addr:full":"Handelskaai 1f Box 61 Kortrijk West-Vlaanderen 8500",
    "addr:housenumber":"1f box 61",
    "addr:postcode":"8500",
    "addr:street":"Handelskaai",
    "iso:country":"BE",
    "sg:address":"Handelskaai 1f Box 61",
    "sg:city":"Kortrijk",
    "sg:classifiers":[
        {
            "category":"Real Estate",
            "subcategory":"Architect",
            "type":"Services"
        }
    ],
    "sg:phone":"+32 56 22 31 40",
    "sg:postcode":"8500",
    "sg:province":"West-Vlaanderen",
    "wof:name":"Baert H",
    "wof:placetype":"venue"
},
  "geometry": {"coordinates":[3.2582530975,50.8291664124],"type":"Point"}
}