{
  "type": "Feature",
  "properties": {
    "iso:country":"BE",
    "sg:address":"Rue De Mangombroux 253",
    "sg:city":"Verviers",
    "sg:orig_category":"Herstellingen and onderhoud van auto's",
    "sg:phone":"+32 87 33 39 59",
    "sg:postcode":"4800",
    "sg:province":"Li\u00e8ge",
    "wof:name":"Carrosserie De Spa",
    "wof:placetype":"venue"
},
  "geometry": {"coordinates":[5.8751368523,50.5862464905],"type":"Point"}
}