{
  "type": "Feature",
  "properties": {
    "iso:country":"BE",
    "sg:address":"Miksebaan 45",
    "sg:city":"Brasschaat",
    "sg:classifiers":[
        {
            "category":"Fast Food",
            "type":"Food & Drink"
        }
    ],
    "sg:phone":"+32 3 651 41 85",
    "sg:postcode":"2930",
    "sg:province":"Antwerpen",
    "sg:tags":[
        "\u00c0",
        "restaurants",
        "emporter",
        "restaurant"
    ],
    "wof:name":"Sam's Snackbar",
    "wof:placetype":"venue"
},
  "geometry": {"coordinates":[4.4962291718,51.290019989],"type":"Point"}
}