{
  "type": "Feature",
  "properties": {
    "addr:full":"Zevendagwand 4 Dendermonde (sint-gillis-bij-dendermonde) Oost-Vlaanderen 9200",
    "addr:housenumber":"4",
    "addr:postcode":"9200",
    "addr:street":"Zevendagwand",
    "iso:country":"BE",
    "sg:address":"Zevendagwand 4",
    "sg:city":"Dendermonde (sint-gillis-bij-dendermonde)",
    "sg:classifiers":[
        {
            "category":"Professional",
            "subcategory":"Accounting & Tax Preparation",
            "type":"Services"
        }
    ],
    "sg:phone":"+32 52 22 11 68",
    "sg:postcode":"9200",
    "sg:province":"Oost-Vlaanderen",
    "sg:tags":[
        "bookkeeper"
    ],
    "wof:name":"Pieters A",
    "wof:placetype":"venue"
},
  "geometry": {"coordinates":[4.1214151382,51.0243186951],"type":"Point"}
}