{
  "type": "Feature",
  "properties": {
    "addr:full":"Rue Georges C\u00c9sar 80 Waremme Li\u00e8ge 4300",
    "addr:housenumber":"80",
    "addr:postcode":"4300",
    "addr:street":"Rue Georges Ce\u0301Sar",
    "iso:country":"BE",
    "sg:address":"Rue Georges C\u00c9sar 80",
    "sg:city":"Waremme",
    "sg:orig_category":"M\u00e9decines alternatives",
    "sg:phone":"+32 19 32 83 23",
    "sg:postcode":"4300",
    "sg:province":"Li\u00e8ge",
    "wof:name":"G. Clausse",
    "wof:placetype":"venue"
},
  "geometry": {"coordinates":[5.2305259705,50.673286438],"type":"Point"}
}