{
  "type": "Feature",
  "properties": {
    "addr:full":"Rue De Tubize 2 Ittre Brabant Wallon 1460",
    "addr:housenumber":"2;1460",
    "addr:street":"Rue De Tubize",
    "iso:country":"BE",
    "sg:address":"Rue De Tubize 2",
    "sg:city":"Ittre",
    "sg:orig_category":"Rundveehouders",
    "sg:phone":"+32 67 64 63 76",
    "sg:postcode":"1460",
    "sg:province":"Brabant Wallon",
    "wof:name":"Decausemacker & Goethals",
    "wof:placetype":"venue"
},
  "geometry": {"coordinates":[4.2196598053,50.6496086121],"type":"Point"}
}