{
  "type": "Feature",
  "properties": {
    "addr:full":"Rue Ravenstein 62 Brussel/bruxelles Bruxelles-Capitale 1000",
    "addr:housenumber":"62",
    "addr:postcode":"1000",
    "addr:street":"Rue Ravenstein;/",
    "iso:country":"BE",
    "sg:address":"Rue Ravenstein 62",
    "sg:city":"Brussel/bruxelles",
    "sg:orig_category":"Transports a\u00e9riens r\u00e9guliers",
    "sg:phone":"+32 2 512 00 72",
    "sg:postcode":"1000",
    "sg:province":"Bruxelles-Capitale",
    "wof:name":"Balkan Airlines",
    "wof:placetype":"venue"
},
  "geometry": {"coordinates":[4.3589901924,50.84557724],"type":"Point"}
}