{
  "type": "Feature",
  "properties": {
    "addr:full":"Chauss\u00e9e De Vleurgat 217 Bruxelles (ixelles) Bruxelles-Capitale 1050",
    "addr:housenumber":"217",
    "addr:postcode":"1050",
    "addr:street":"Chausse\u0301E De Vleurgat",
    "iso:country":"BE",
    "sg:address":"Chauss\u00e9e De Vleurgat 217",
    "sg:city":"Bruxelles (ixelles)",
    "sg:classifiers":[
        {
            "category":"Government",
            "subcategory":"Embassy",
            "type":"Public Place"
        }
    ],
    "sg:phone":"+32 2 640 91 40",
    "sg:postcode":"1050",
    "sg:province":"Bruxelles-Capitale",
    "sg:tags":[
        "consulate"
    ],
    "wof:name":"Inde-india",
    "wof:placetype":"venue"
},
  "geometry": {"coordinates":[4.3660650253,50.8199577332],"type":"Point"}
}