{
  "type": "Feature",
  "properties": {
    "addr:full":"Eikenlaan 94-96 Waregem West-Vlaanderen 8790",
    "addr:housenumber":"94-96",
    "addr:postcode":"8790",
    "addr:street":"Eikenlaan",
    "iso:country":"BE",
    "sg:address":"Eikenlaan 94-96",
    "sg:city":"Waregem",
    "sg:classifiers":[
        {
            "category":"Home & Garden",
            "subcategory":"Carpets & Floor Coverings",
            "type":"Retail Goods"
        }
    ],
    "sg:phone":"+32 56 60 00 49",
    "sg:postcode":"8790",
    "sg:province":"West-Vlaanderen",
    "sg:tags":[
        "parquet"
    ],
    "wof:name":"Zarbia Bvba",
    "wof:placetype":"venue"
},
  "geometry": {"coordinates":[3.4121499062,50.8942718506],"type":"Point"}
}