{
  "type": "Feature",
  "properties": {
    "iso:country":"BE",
    "sg:address":"Koningslaan 144b11",
    "sg:city":"Vorst/forest",
    "sg:orig_category":"Artsen and specialisten",
    "sg:phone":"+32 2 538 16 75",
    "sg:postcode":"1190",
    "sg:province":"Bruxelles-Capitale",
    "wof:name":"Urbain Reynaert",
    "wof:placetype":"venue"
},
  "geometry": {"coordinates":[4.3345279694,50.8268203735],"type":"Point"}
}