{
  "type": "Feature",
  "properties": {
    "iso:country":"BE",
    "sg:address":"Demerwal 16",
    "sg:city":"Bilzen",
    "sg:orig_category":"Herstellingswinkels voor diverse persoonlijke and huishoudartikelen",
    "sg:phone":"+32 89 51 12 31",
    "sg:postcode":"3740",
    "sg:province":"Limburg",
    "wof:name":"Agata\u00b4s Atelier",
    "wof:placetype":"venue"
},
  "geometry": {"coordinates":[5.515048027,50.868812561],"type":"Point"}
}