{
  "type": "Feature",
  "properties": {
    "addr:full":"Idegemplein 20 Geraardsbergen Oost-Vlaanderen 9506",
    "addr:housenumber":"20",
    "addr:postcode":"9506",
    "addr:street":"Idegemplein",
    "iso:country":"BE",
    "sg:address":"Idegemplein 20",
    "sg:city":"Geraardsbergen",
    "sg:orig_category":"Instituts de beaut\u00e9",
    "sg:phone":"+32 54 50 27 16",
    "sg:postcode":"9506",
    "sg:province":"Oost-Vlaanderen",
    "wof:name":"Brig",
    "wof:placetype":"venue"
},
  "geometry": {"coordinates":[3.8985300064,50.7987060547],"type":"Point"}
}