{
  "type": "Feature",
  "properties": {
    "iso:country":"BE",
    "sg:address":"Rue De La Vall\u00e9e 10",
    "sg:city":"Remicourt (pousset)",
    "sg:classifiers":[
        {
            "category":"Communications",
            "type":"Services"
        }
    ],
    "sg:phone":"+32 19 54 63 39",
    "sg:postcode":"4350",
    "sg:province":"Li\u00e8ge",
    "sg:tags":[
        "translator"
    ],
    "wof:name":"Morph\u00e8me",
    "wof:placetype":"venue"
},
  "geometry": {"coordinates":[5.3068637848,50.6938438416],"type":"Point"}
}