{
  "type": "Feature",
  "properties": {
    "addr:full":"Voie De La Petite Reine 1 Ottignies-louvain-la-neuve (louvain-la-neuve) Brabant Wallon 1348",
    "addr:housenumber":"1",
    "addr:postcode":"1348",
    "addr:street":"Voie De La Petite Reine",
    "iso:country":"BE",
    "sg:address":"Voie De La Petite Reine 1",
    "sg:city":"Ottignies-louvain-la-neuve (louvain-la-neuve)",
    "sg:classifiers":[
        {
            "category":"Health Services",
            "subcategory":"Health Practitioner",
            "type":"Services"
        }
    ],
    "sg:phone":"+32 10 45 12 03",
    "sg:postcode":"1348",
    "sg:province":"Brabant Wallon",
    "sg:tags":[
        "physiotherapist"
    ],
    "wof:name":"Hanon Jean-fran\u00e7ois",
    "wof:placetype":"venue"
},
  "geometry": {"coordinates":[4.6006717682,50.6692504883],"type":"Point"}
}