{
  "type": "Feature",
  "properties": {
    "addr:full":"Olmenlaan 48 Lennik (sint-martens-lennik) Vlaams-Brabant 1750",
    "addr:housenumber":"48",
    "addr:postcode":"1750",
    "addr:street":"Olmenlaan",
    "iso:country":"BE",
    "sg:address":"Olmenlaan 48",
    "sg:city":"Lennik (sint-martens-lennik)",
    "sg:classifiers":[
        {
            "category":"Wholesale",
            "subcategory":"Medical Equipment & Supplies",
            "type":"Manufacturing & Wholesale Goods"
        }
    ],
    "sg:phone":"+32 2 532 47 63",
    "sg:postcode":"1750",
    "sg:province":"Vlaams-Brabant",
    "sg:tags":[
        "instrument",
        "apparatus"
    ],
    "wof:name":"Reynders Medical Supplies Bvba",
    "wof:placetype":"venue"
},
  "geometry": {"coordinates":[4.175757885,50.8188438416],"type":"Point"}
}