{
  "type": "Feature",
  "properties": {
    "iso:country":"BE",
    "sg:address":"Turnhoutsebaan 594",
    "sg:city":"Wijnegem",
    "sg:classifiers":[
        {
            "category":"Home & Garden",
            "subcategory":"Building Materials",
            "type":"Retail Goods"
        }
    ],
    "sg:phone":"+32 3 755 83 32",
    "sg:postcode":"2110",
    "sg:province":"Antwerpen",
    "sg:tags":[
        "veranda"
    ],
    "wof:name":"Finewood",
    "wof:placetype":"venue"
},
  "geometry": {"coordinates":[4.5416879654,51.2282218933],"type":"Point"}
}