{
  "type": "Feature",
  "properties": {
    "addr:full":"Kerkhoflaan 65 Zaventem Vlaams-Brabant 1930",
    "addr:housenumber":"65",
    "addr:postcode":"1930",
    "addr:street":"Kerkhoflaan",
    "iso:country":"BE",
    "sg:address":"Kerkhoflaan 65",
    "sg:city":"Zaventem",
    "sg:orig_category":"Producteurs de l\u00e9gumes",
    "sg:phone":"+32 2 720 35 76",
    "sg:postcode":"1930",
    "sg:province":"Vlaams-Brabant",
    "wof:name":"Emile Hermans",
    "wof:placetype":"venue"
},
  "geometry": {"coordinates":[4.4842119217,50.8854446411],"type":"Point"}
}