{
  "type": "Feature",
  "properties": {
    "addr:full":"Zandstraat 180 Turnhout Antwerpen 2300",
    "addr:housenumber":"180",
    "addr:postcode":"2300",
    "addr:street":"Zandstraat",
    "iso:country":"BE",
    "sg:address":"Zandstraat 180",
    "sg:city":"Turnhout",
    "sg:classifiers":[
        {
            "category":"Personal",
            "subcategory":"Beauty Salon",
            "type":"Services"
        }
    ],
    "sg:phone":"+32 14 42 66 96",
    "sg:postcode":"2300",
    "sg:province":"Antwerpen",
    "sg:tags":[
        "lady",
        "-",
        "hairdressing"
    ],
    "wof:name":"Christel",
    "wof:placetype":"venue"
},
  "geometry": {"coordinates":[4.9275751114,51.3194694519],"type":"Point"}
}