{
  "type": "Feature",
  "properties": {
    "addr:full":"Oude Zeedijk 38 Diksmuide West-Vlaanderen 8600",
    "addr:housenumber":"38",
    "addr:postcode":"8600",
    "addr:street":"Oude Zeedijk",
    "iso:country":"BE",
    "sg:address":"Oude Zeedijk 38",
    "sg:city":"Diksmuide",
    "sg:orig_category":"Eleveurs de bovins. Eleveurs and marchands de porcs",
    "sg:phone":"+32 51 50 39 46",
    "sg:postcode":"8600",
    "sg:province":"West-Vlaanderen",
    "wof:name":"Martin Obin",
    "wof:placetype":"venue"
},
  "geometry": {"coordinates":[2.7985498905,51.022857666],"type":"Point"}
}