{
  "type": "Feature",
  "properties": {
    "addr:full":"Route De Harsin 27 Nassogne Luxembourg 6953",
    "addr:housenumber":"27",
    "addr:postcode":"6953",
    "addr:street":"Route De Harsin",
    "iso:country":"BE",
    "sg:address":"Route De Harsin 27",
    "sg:city":"Nassogne",
    "sg:orig_category":"Rundveehouders",
    "sg:phone":"+32 84 21 37 63",
    "sg:postcode":"6953",
    "sg:province":"Luxembourg",
    "wof:name":"Orban",
    "wof:placetype":"venue"
},
  "geometry": {"coordinates":[5.2774748802,50.1315689087],"type":"Point"}
}