{
  "type": "Feature",
  "properties": {
    "iso:country":"BE",
    "sg:address":"Schoolstraat 22",
    "sg:city":"Edingen/enghien",
    "sg:orig_category":"Openbare veiligheid",
    "sg:phone":"+32 2 395 40 40",
    "sg:postcode":"7850",
    "sg:province":"Hainaut",
    "wof:name":"Police F\u00c9d\u00c9rale/federale Politie",
    "wof:placetype":"venue"
},
  "geometry": {"coordinates":[4.0413708687,50.695640564],"type":"Point"}
}