{
  "type": "Feature",
  "properties": {
    "iso:country":"BE",
    "sg:address":"Grote Markt 16",
    "sg:city":"Herentals",
    "sg:classifiers":[
        {
            "category":"Bars & Pubs",
            "type":"Food & Drink"
        }
    ],
    "sg:phone":"+32 14 22 15 12",
    "sg:postcode":"2200",
    "sg:province":"Antwerpen",
    "sg:tags":[
        "tavern"
    ],
    "wof:name":"Brigand (den)",
    "wof:placetype":"venue"
},
  "geometry": {"coordinates":[4.8367118835,51.176486969],"type":"Point"}
}