{
  "type": "Feature",
  "properties": {
    "addr:full":"Haringrodestraat 61 Antwerpen Antwerpen 2018",
    "addr:housenumber":"61",
    "addr:postcode":"2018",
    "addr:street":"Haringrodestraat",
    "iso:country":"BE",
    "sg:address":"Haringrodestraat 61",
    "sg:city":"Antwerpen",
    "sg:orig_category":"Artsen and specialisten Medische and orthopedische apparaten",
    "sg:phone":"+32 3 218 40 82",
    "sg:postcode":"2018",
    "sg:province":"Antwerpen",
    "wof:name":"Laerenbergh - Dandoy",
    "wof:placetype":"venue"
},
  "geometry": {"coordinates":[4.4156899452,51.2017364502],"type":"Point"}
}