{
  "type": "Feature",
  "properties": {
    "iso:country":"BE",
    "sg:address":"Rue De La Station 2",
    "sg:city":"Fleurus",
    "sg:orig_category":"Randstad",
    "sg:phone":"+32 71 82 71 71",
    "sg:postcode":"6220",
    "sg:province":"Hainaut",
    "wof:name":"Randstad",
    "wof:placetype":"venue"
},
  "geometry": {"coordinates":[4.5493159294,50.4824295044],"type":"Point"}
}