{
  "type": "Feature",
  "properties": {
    "addr:full":"Rue De Charleroi 131 Fontaine-l'ev\u00eaque Hainaut 6140",
    "addr:housenumber":"131",
    "addr:postcode":"6140",
    "addr:street":"Rue De Charleroi;\u0302Que Hainaut",
    "iso:country":"BE",
    "sg:address":"Rue De Charleroi 131",
    "sg:city":"Fontaine-l'ev\u00eaque",
    "sg:classifiers":[
        {
            "category":"Home & Garden",
            "subcategory":"Building Materials",
            "type":"Retail Goods"
        }
    ],
    "sg:phone":"+32 71 54 87 00",
    "sg:postcode":"6140",
    "sg:province":"Hainaut",
    "sg:tags":[
        "article",
        "-",
        "do-it-yourself"
    ],
    "wof:name":"Brico Depot",
    "wof:placetype":"venue"
},
  "geometry": {"coordinates":[4.3309459686,50.4070205688],"type":"Point"}
}