{
  "type": "Feature",
  "properties": {
    "addr:full":"Limesweg 5 Tongeren (berg) Limburg 3700",
    "addr:housenumber":"5",
    "addr:postcode":"3700",
    "addr:street":"Limesweg",
    "iso:country":"BE",
    "sg:address":"Limesweg 5",
    "sg:city":"Tongeren (berg)",
    "sg:classifiers":[
        {
            "category":"Building & Trades",
            "subcategory":"Construction",
            "type":"Services"
        }
    ],
    "sg:phone":"+32 12 26 23 60",
    "sg:postcode":"3700",
    "sg:province":"Limburg",
    "sg:tags":[
        "roofing",
        "material",
        "-"
    ],
    "wof:name":"Defrancq Sa",
    "wof:placetype":"venue"
},
  "geometry": {"coordinates":[5.5228571892,50.7887840271],"type":"Point"}
}