{
  "type": "Feature",
  "properties": {
    "iso:country":"BE",
    "sg:address":"Rue Jules Destr\u00c9e 15",
    "sg:city":"Charleroi",
    "sg:orig_category":"Mat\u00e9riel m\u00e9dical and orthop\u00e9dique and proth\u00e8ses Fab",
    "sg:phone":"+32 71 47 33 81",
    "sg:postcode":"6032",
    "sg:province":"Hainaut",
    "wof:name":"Esthetico Ceram",
    "wof:placetype":"venue"
},
  "geometry": {"coordinates":[4.4103012085,50.3924102783],"type":"Point"}
}