{
  "type": "Feature",
  "properties": {
    "iso:country":"BE",
    "sg:address":"Ren\u00e9 De Clercqstraat 7",
    "sg:city":"Deerlijk",
    "sg:classifiers":[
        {
            "category":"Health Services",
            "subcategory":"Dentist",
            "type":"Services"
        }
    ],
    "sg:phone":"+32 56 71 51 74",
    "sg:postcode":"8540",
    "sg:province":"West-Vlaanderen",
    "wof:name":"Vanneste Sofie",
    "wof:placetype":"venue"
},
  "geometry": {"coordinates":[3.3554298878,50.8523368835],"type":"Point"}
}