{
  "type": "Feature",
  "properties": {
    "addr:full":"Ruisbroek-dorp 57 Puurs Antwerpen 2870",
    "addr:housenumber":"57",
    "addr:postcode":"2870",
    "addr:street":"Ruisbroek-Dorp",
    "iso:country":"BE",
    "sg:address":"Ruisbroek-dorp 57",
    "sg:city":"Puurs",
    "sg:orig_category":"Imprimeries and copyshops",
    "sg:phone":"+32 3 886 70 26",
    "sg:postcode":"2870",
    "sg:province":"Antwerpen",
    "wof:name":"Verstraeten-mareels",
    "wof:placetype":"venue"
},
  "geometry": {"coordinates":[4.3308157921,51.0877609253],"type":"Point"}
}