{
  "type": "Feature",
  "properties": {
    "addr:full":"Adriaanstraat 26a Overijse Vlaams-Brabant 3090",
    "addr:housenumber":"26a",
    "addr:postcode":"3090",
    "addr:street":"Adriaanstraat",
    "iso:country":"BE",
    "sg:address":"Adriaanstraat 26a",
    "sg:city":"Overijse",
    "sg:orig_category":"Ordinateurs and \u00e9quipement informatique",
    "sg:phone":"+32 2 688 07 29",
    "sg:postcode":"3090",
    "sg:province":"Vlaams-Brabant",
    "wof:name":"Dcom Computer Services",
    "wof:placetype":"venue"
},
  "geometry": {"coordinates":[4.5485877991,50.7703933716],"type":"Point"}
}