{
  "type": "Feature",
  "properties": {
    "iso:country":"BE",
    "sg:address":"Dolfijnkaai 4",
    "sg:city":"Kortrijk",
    "sg:orig_category":"Fleurs and plantes",
    "sg:phone":"+32 56 22 06 76",
    "sg:postcode":"8500",
    "sg:province":"West-Vlaanderen",
    "wof:name":"Marie-claire Vanlandeghem",
    "wof:placetype":"venue"
},
  "geometry": {"coordinates":[3.2640590668,50.8293304443],"type":"Point"}
}