{
  "type": "Feature",
  "properties": {
    "iso:country":"BE",
    "sg:address":"Rue De La Gare 22",
    "sg:city":"Eghez\u00e9e",
    "sg:classifiers":[
        {
            "category":"Banks & Credit Unions",
            "subcategory":"Bank",
            "type":"Services"
        }
    ],
    "sg:postcode":"5310",
    "sg:province":"Namur",
    "wof:name":"Alpha Card Scrl",
    "wof:placetype":"venue"
},
  "geometry": {"coordinates":[4.3496799469,50.8483810425],"type":"Point"}
}