{
  "type": "Feature",
  "properties": {
    "addr:full":"Elshoven 4 Bocholt Limburg 3950",
    "addr:housenumber":"4",
    "addr:postcode":"3950",
    "addr:street":"Elshoven",
    "iso:country":"BE",
    "sg:address":"Elshoven 4",
    "sg:city":"Bocholt",
    "sg:orig_category":"Eleveurs de bovins",
    "sg:phone":"+32 11 44 10 76",
    "sg:postcode":"3950",
    "sg:province":"Limburg",
    "wof:name":"Theo Keppens",
    "wof:placetype":"venue"
},
  "geometry": {"coordinates":[5.4954528809,51.1861495972],"type":"Point"}
}