{
  "type": "Feature",
  "properties": {
    "addr:full":"Alfred Algoetstraat 8 Lennik Vlaams-Brabant 1750",
    "addr:housenumber":"8;1750",
    "addr:street":"Algoetstraat;Vlaams-Brabant",
    "iso:country":"BE",
    "sg:address":"Alfred Algoetstraat 8",
    "sg:city":"Lennik",
    "sg:orig_category":"Pain, p\u00e2tisseries and confiseries",
    "sg:phone":"+32 2 532 11 30",
    "sg:postcode":"1750",
    "sg:province":"Vlaams-Brabant",
    "wof:name":"Roger Borguinon",
    "wof:placetype":"venue"
},
  "geometry": {"coordinates":[4.1560959816,50.8059196472],"type":"Point"}
}