{
  "type": "Feature",
  "properties": {
    "iso:country":"BE",
    "sg:address":"Belzele Dorp 43",
    "sg:city":"Evergem",
    "sg:classifiers":[
        {
            "category":"Home & Garden",
            "subcategory":"Household Appliances",
            "type":"Retail Goods"
        }
    ],
    "sg:phone":"+32 9 253 06 68",
    "sg:postcode":"9940",
    "sg:province":"Oost-Vlaanderen",
    "sg:tags":[
        "heating",
        "apparatus"
    ],
    "wof:name":"Van Poucke R",
    "wof:placetype":"venue"
},
  "geometry": {"coordinates":[3.6629970074,51.1014862061],"type":"Point"}
}