{
  "type": "Feature",
  "properties": {
    "iso:country":"BE",
    "sg:address":"Stokstraat 15",
    "sg:city":"Halen",
    "sg:orig_category":"HUISBRANDOLIE",
    "sg:phone":"+32 13 44 13 32",
    "sg:postcode":"3545",
    "sg:province":"Limburg",
    "wof:name":"Marcel Van Thienen",
    "wof:placetype":"venue"
},
  "geometry": {"coordinates":[5.0605602264,50.9274406433],"type":"Point"}
}