{
  "type": "Feature",
  "properties": {
    "iso:country":"BE",
    "sg:address":"Avenue Nouvelle 76 Box 6",
    "sg:city":"Bruxelles (etterbeek)",
    "sg:classifiers":[
        {
            "category":"Professional",
            "subcategory":"Accounting & Tax Preparation",
            "type":"Services"
        }
    ],
    "sg:phone":"+32 2 643 43 43",
    "sg:postcode":"1040",
    "sg:province":"Bruxelles-Capitale",
    "sg:tags":[
        "accountant"
    ],
    "wof:name":"Fiduciaire Conseil Expertise Fiscal Sprl Cef",
    "wof:placetype":"venue"
},
  "geometry": {"coordinates":[4.3846259117,50.827205658],"type":"Point"}
}