{
  "type": "Feature",
  "properties": {
    "addr:full":"Rue Ferdinand Nicolay 693 Saint-nicolas Li\u00e8ge 4420",
    "addr:housenumber":"693",
    "addr:postcode":"4420",
    "addr:street":"Rue Ferdinand Nicolay;Saint-Nicolas Lie\u0300Ge",
    "iso:country":"BE",
    "sg:address":"Rue Ferdinand Nicolay 693",
    "sg:city":"Saint-nicolas",
    "sg:orig_category":"Slagers",
    "sg:phone":"+32 4 233 85 10",
    "sg:postcode":"4420",
    "sg:province":"Li\u00e8ge",
    "wof:name":"Boucherie Van Houdt",
    "wof:placetype":"venue"
},
  "geometry": {"coordinates":[5.5313000679,50.6251296997],"type":"Point"}
}