{
  "type": "Feature",
  "properties": {
    "addr:full":"Toekomststraat 15-17 Sint-truiden Limburg 3800",
    "addr:postcode":"15-17;3800",
    "addr:street":"Toekomststraat",
    "iso:country":"BE",
    "sg:address":"Toekomststraat 15-17",
    "sg:city":"Sint-truiden",
    "sg:classifiers":[
        {
            "category":"Personal",
            "subcategory":"Beauty Salon",
            "type":"Services"
        }
    ],
    "sg:phone":"+32 11 69 19 92",
    "sg:postcode":"3800",
    "sg:province":"Limburg",
    "sg:tags":[
        "lady",
        "-",
        "hairdressing"
    ],
    "wof:name":"Michelangelo (atelier)",
    "wof:placetype":"venue"
},
  "geometry": {"coordinates":[5.1803841591,50.8179206848],"type":"Point"}
}