{
  "type": "Feature",
  "properties": {
    "addr:full":"Soetebeek 71 Meeuwen-gruitrode Limburg 3670",
    "addr:housenumber":"71",
    "addr:postcode":"3670",
    "addr:street":"Soetebeek",
    "iso:country":"BE",
    "sg:address":"Soetebeek 71",
    "sg:city":"Meeuwen-gruitrode",
    "sg:classifiers":[
        {
            "category":"Cafe",
            "type":"Food & Drink"
        }
    ],
    "sg:phone":"+32 89 46 12 72",
    "sg:postcode":"3670",
    "sg:province":"Limburg",
    "sg:tags":[
        "caf\u00e9s"
    ],
    "wof:name":"Jeanine Voortmans",
    "wof:placetype":"venue"
},
  "geometry": {"coordinates":[5.5528430939,51.1184577942],"type":"Point"}
}