{
  "type": "Feature",
  "properties": {
    "addr:full":"Boulevard Bara 28 Tournai Hainaut 7500",
    "addr:housenumber":"28",
    "addr:postcode":"7500",
    "addr:street":"Boulevard Bara",
    "iso:country":"BE",
    "sg:address":"Boulevard Bara 28",
    "sg:city":"Tournai",
    "sg:classifiers":[
        {
            "category":"Professional",
            "subcategory":"Lawyer & Legal Services",
            "type":"Services"
        }
    ],
    "sg:phone":"+32 69 23 38 60",
    "sg:postcode":"7500",
    "sg:province":"Hainaut",
    "wof:name":"Creteur Pascale",
    "wof:placetype":"venue"
},
  "geometry": {"coordinates":[3.3830699921,50.6041603088],"type":"Point"}
}