{
  "type": "Feature",
  "properties": {
    "addr:full":"Rue De Valenciennes 121 Bernissart Hainaut 7320",
    "addr:housenumber":"121",
    "addr:postcode":"7320",
    "addr:street":"Rue De Valenciennes",
    "iso:country":"BE",
    "sg:address":"Rue De Valenciennes 121",
    "sg:city":"Bernissart",
    "sg:classifiers":[
        {
            "category":"Insurance",
            "subcategory":"Insurance Agent",
            "type":"Services"
        }
    ],
    "sg:phone":"+32 69 59 01 11",
    "sg:postcode":"7320",
    "sg:province":"Hainaut",
    "sg:tags":[
        "broker"
    ],
    "wof:name":"Actis Sprl",
    "wof:placetype":"venue"
},
  "geometry": {"coordinates":[3.647069931,50.4798812866],"type":"Point"}
}