{
  "type": "Feature",
  "properties": {
    "addr:full":"Schoolstraat 7 Gingelom Limburg 3890",
    "addr:housenumber":"7",
    "addr:postcode":"3890",
    "addr:street":"Schoolstraat",
    "iso:country":"BE",
    "sg:address":"Schoolstraat 7",
    "sg:city":"Gingelom",
    "sg:orig_category":"Fruitteelt",
    "sg:phone":"+32 11 88 36 76",
    "sg:postcode":"3890",
    "sg:province":"Limburg",
    "wof:name":"Gerda Nicolai",
    "wof:placetype":"venue"
},
  "geometry": {"coordinates":[5.1510281563,50.7058258057],"type":"Point"}
}