{
  "type": "Feature",
  "properties": {
    "iso:country":"BE",
    "sg:address":"Adolf Papeleustraat 112",
    "sg:city":"Wetteren",
    "sg:orig_category":"Afbraak- and draineerwerken Tuinen",
    "sg:phone":"+32 9 369 10 50",
    "sg:postcode":"9230",
    "sg:province":"Oost-Vlaanderen",
    "wof:name":"Temmerman E",
    "wof:placetype":"venue"
},
  "geometry": {"coordinates":[3.9122979641,50.9923439026],"type":"Point"}
}