{
  "type": "Feature",
  "properties": {
    "iso:country":"BE",
    "sg:address":"Chauss\u00e9e De Wavre 221",
    "sg:city":"Grez-doiceau",
    "sg:classifiers":[
        {
            "category":"Retail",
            "subcategory":"Animal Services",
            "type":"Services"
        }
    ],
    "sg:phone":"+32 10 84 24 21",
    "sg:postcode":"1390",
    "sg:province":"Brabant Wallon",
    "sg:tags":[
        "grooming",
        "-",
        "dog"
    ],
    "wof:name":"Canino",
    "wof:placetype":"venue"
},
  "geometry": {"coordinates":[4.6744318008,50.7418556213],"type":"Point"}
}