{
  "type": "Feature",
  "properties": {
    "iso:country":"BE",
    "sg:address":"Rue Des Fripiers 24b",
    "sg:city":"Bruxelles-centre",
    "sg:classifiers":[
        {
            "category":"Utilities",
            "subcategory":"Mobile Phone",
            "type":"Services"
        }
    ],
    "sg:phone":"+32 2 250 36 00",
    "sg:postcode":"1000",
    "sg:province":"Bruxelles-Capitale",
    "sg:tags":[
        "house",
        "mat\u00e9riel",
        "de",
        "t\u00e9l\u00e9communication"
    ],
    "wof:name":"The Phone House",
    "wof:placetype":"venue"
},
  "geometry": {"coordinates":[4.3523879051,50.8489341736],"type":"Point"}
}