{
  "type": "Feature",
  "properties": {
    "iso:country":"BE",
    "sg:address":"Ren\u00c9 Willemestraat 39",
    "sg:city":"Kalmthout",
    "sg:orig_category":"Studios photographiques",
    "sg:phone":"+32 3 666 59 24",
    "sg:postcode":"2920",
    "sg:province":"Antwerpen",
    "wof:name":"Marc Van Loon",
    "wof:placetype":"venue"
},
  "geometry": {"coordinates":[4.4626407623,51.4012260437],"type":"Point"}
}