{
  "type": "Feature",
  "properties": {
    "iso:country":"BE",
    "sg:address":"Hogestraat 32",
    "sg:city":"Kortemark",
    "sg:orig_category":"Installation de menuiserie en bois and plastique",
    "sg:phone":"+32 51 56 94 33",
    "sg:postcode":"8610",
    "sg:province":"West-Vlaanderen",
    "wof:name":"Johan Deseure",
    "wof:placetype":"venue"
},
  "geometry": {"coordinates":[3.0078439713,51.0482139587],"type":"Point"}
}