{
  "type": "Feature",
  "properties": {
    "addr:full":"Claerhoutstraat 15 Tielt West-Vlaanderen 8700",
    "addr:housenumber":"15",
    "addr:postcode":"8700",
    "addr:street":"Claerhoutstraat",
    "iso:country":"BE",
    "sg:address":"Claerhoutstraat 15",
    "sg:city":"Tielt",
    "sg:orig_category":"Produits chimiques Gr",
    "sg:phone":"+32 475 68 74 93",
    "sg:postcode":"8700",
    "sg:province":"West-Vlaanderen",
    "wof:name":"Patti-nova",
    "wof:placetype":"venue"
},
  "geometry": {"coordinates":[3.3086650372,50.9947776794],"type":"Point"}
}