{
  "type": "Feature",
  "properties": {
    "addr:full":"Unescolaan 8 Gent Oost-Vlaanderen 9030",
    "addr:housenumber":"8",
    "addr:postcode":"9030",
    "addr:street":"Unescolaan;Oost-Vlaanderen",
    "iso:country":"BE",
    "sg:address":"Unescolaan 8",
    "sg:city":"Gent",
    "sg:orig_category":"Sportclubs",
    "sg:phone":"+32 9 329 84 45",
    "sg:postcode":"9030",
    "sg:province":"Oost-Vlaanderen",
    "wof:name":"B.c. Latem",
    "wof:placetype":"venue"
},
  "geometry": {"coordinates":[3.6884829998,51.0784416199],"type":"Point"}
}