{
  "type": "Feature",
  "properties": {
    "addr:full":"Rue Basse Vaux 33a Sombreffe Namur 5140",
    "addr:housenumber":"33a",
    "addr:postcode":"5140",
    "addr:street":"Rue Basse Vaux",
    "iso:country":"BE",
    "sg:address":"Rue Basse Vaux 33a",
    "sg:city":"Sombreffe",
    "sg:classifiers":[
        {
            "category":"Real Estate",
            "subcategory":"Architect",
            "type":"Services"
        }
    ],
    "sg:phone":"+32 71 88 64 41",
    "sg:postcode":"5140",
    "sg:province":"Namur",
    "wof:name":"Baudart J-y",
    "wof:placetype":"venue"
},
  "geometry": {"coordinates":[4.5897231102,50.5314865112],"type":"Point"}
}