{
  "type": "Feature",
  "properties": {
    "addr:full":"Ahornelaan 5 Aartselaar Antwerpen 2630",
    "addr:housenumber":"5",
    "addr:postcode":"2630",
    "addr:street":"Ahornelaan",
    "iso:country":"BE",
    "sg:address":"Ahornelaan 5",
    "sg:city":"Aartselaar",
    "sg:classifiers":[
        {
            "category":"Banks & Credit Unions",
            "subcategory":"Investment Brokerage",
            "type":"Services"
        }
    ],
    "sg:phone":"+32 3 877 00 69",
    "sg:postcode":"2630",
    "sg:province":"Antwerpen",
    "sg:tags":[
        "machine",
        "mat\u00e9riel",
        "de",
        "bureau",
        "gr"
    ],
    "wof:name":"G.t.r.",
    "wof:placetype":"venue"
},
  "geometry": {"coordinates":[4.3766751289,51.1413536072],"type":"Point"}
}