{
  "type": "Feature",
  "properties": {
    "iso:country":"BE",
    "sg:address":"Parvis Sainte-alix 53",
    "sg:city":"Sint-pieters-woluwe/woluwe-saint-pierre",
    "sg:orig_category":"M\u00e9decins and sp\u00e9cialistes",
    "sg:phone":"+32 2 779 96 28",
    "sg:postcode":"1150",
    "sg:province":"Bruxelles-Capitale",
    "wof:name":"Patrick Vanhoorne",
    "wof:placetype":"venue"
},
  "geometry": {"coordinates":[4.4631409645,50.8283119202],"type":"Point"}
}