{
  "type": "Feature",
  "properties": {
    "addr:full":"Rue Croix Thomas 13 Ottignies-louvain-la-neuve (c\u00e9roux-mousty) Brabant Wallon 1341",
    "addr:housenumber":"13",
    "addr:postcode":"1341",
    "addr:street":"Rue Croix Thomas;Ce\u0301Roux-Mousty;Wallon",
    "iso:country":"BE",
    "sg:address":"Rue Croix Thomas 13",
    "sg:city":"Ottignies-louvain-la-neuve (c\u00e9roux-mousty)",
    "sg:classifiers":[
        {
            "category":"Health Services",
            "subcategory":"Health Practitioner",
            "type":"Services"
        }
    ],
    "sg:phone":"+32 10 61 50 05",
    "sg:postcode":"1341",
    "sg:province":"Brabant Wallon",
    "sg:tags":[
        "physiotherapist"
    ],
    "wof:name":"Coenen Muriel",
    "wof:placetype":"venue"
},
  "geometry": {"coordinates":[4.5627598763,50.6583099365],"type":"Point"}
}