{
  "type": "Feature",
  "properties": {
    "addr:full":"Kerkstraat 1 Vosselaar Antwerpen 2350",
    "addr:housenumber":"1",
    "addr:postcode":"2350",
    "addr:street":"Kerkstraat",
    "iso:country":"BE",
    "sg:address":"Kerkstraat 1",
    "sg:city":"Vosselaar",
    "sg:orig_category":"M\u00e9decins and sp\u00e9cialistes",
    "sg:phone":"+32 14 61 12 69",
    "sg:postcode":"2350",
    "sg:province":"Antwerpen",
    "wof:name":"Pol Colpaert",
    "wof:placetype":"venue"
},
  "geometry": {"coordinates":[4.8886289597,51.3133125305],"type":"Point"}
}