{
  "type": "Feature",
  "properties": {
    "iso:country":"BE",
    "sg:address":"Albert Panisstraat 36",
    "sg:city":"Beveren",
    "sg:orig_category":"Loodgieterij, verwarming and sanitaire installaties",
    "sg:phone":"+32 3 755 06 43",
    "sg:postcode":"9120",
    "sg:province":"Oost-Vlaanderen",
    "wof:name":"Van Esbroeck Willy & Zn",
    "wof:placetype":"venue"
},
  "geometry": {"coordinates":[4.248374939,51.2093696594],"type":"Point"}
}