{
  "type": "Feature",
  "properties": {
    "addr:full":"Peperstraat 100 Wetteren Oost-Vlaanderen 9230",
    "addr:housenumber":"100",
    "addr:postcode":"9230",
    "addr:street":"Peperstraat",
    "iso:country":"BE",
    "sg:address":"Peperstraat 100",
    "sg:city":"Wetteren",
    "sg:orig_category":"Dakwerken",
    "sg:phone":"+32 9 366 11 16",
    "sg:postcode":"9230",
    "sg:province":"Oost-Vlaanderen",
    "wof:name":"Baeyens",
    "wof:placetype":"venue"
},
  "geometry": {"coordinates":[3.8720118999,51.007610321],"type":"Point"}
}