{
  "type": "Feature",
  "properties": {
    "addr:full":"Alsembergsesteenweg 731 Ukkel Bruxelles-Capitale 1180",
    "addr:housenumber":"731",
    "addr:postcode":"1180",
    "addr:street":"Alsembergsesteenweg",
    "iso:country":"BE",
    "sg:address":"Alsembergsesteenweg 731",
    "sg:city":"Ukkel",
    "sg:orig_category":"Tijdelijke werkgelegenheid and uitzendkantoren Vedior",
    "sg:phone":"+32 2 346 22 25",
    "sg:postcode":"1180",
    "sg:province":"Bruxelles-Capitale",
    "wof:name":"Vedior Interim",
    "wof:placetype":"venue"
},
  "geometry": {"coordinates":[4.3365588188,50.804359436],"type":"Point"}
}