{
  "type": "Feature",
  "properties": {
    "addr:full":"Chauss\u00c9e De Renaix 80 Tournai Hainaut 7500",
    "addr:housenumber":"80",
    "addr:postcode":"7500",
    "addr:street":"Chausse\u0301E De Renaix",
    "iso:country":"BE",
    "sg:address":"Chauss\u00c9e De Renaix 80",
    "sg:city":"Tournai",
    "sg:orig_category":"Fleurs and plantes",
    "sg:phone":"+32 69 23 63 31",
    "sg:postcode":"7500",
    "sg:province":"Hainaut",
    "wof:name":"Le Vent Dans Les Saules",
    "wof:placetype":"venue"
},
  "geometry": {"coordinates":[3.4065630436,50.6140823364],"type":"Point"}
}