{
  "type": "Feature",
  "properties": {
    "iso:country":"BE",
    "sg:address":"Turnhoutsebaan 105",
    "sg:city":"Dessel",
    "sg:classifiers":[
        {
            "category":"Professional",
            "subcategory":"Art Services",
            "type":"Services"
        }
    ],
    "sg:phone":"+32 14 37 17 50",
    "sg:postcode":"2480",
    "sg:province":"Antwerpen",
    "sg:tags":[
        "picture",
        "framer"
    ],
    "wof:name":"Euro-frame Bvba",
    "wof:placetype":"venue"
},
  "geometry": {"coordinates":[5.1096668243,51.2461891174],"type":"Point"}
}