{
  "type": "Feature",
  "properties": {
    "addr:full":"Rue Oborne 6 Bassenge (glons) Li\u00e8ge 4690",
    "addr:housenumber":"6",
    "addr:postcode":"4690",
    "addr:street":"Rue Oborne;Glons",
    "iso:country":"BE",
    "sg:address":"Rue Oborne 6",
    "sg:city":"Bassenge (glons)",
    "sg:classifiers":[
        {
            "category":"Retail",
            "subcategory":"Animal Services",
            "type":"Services"
        }
    ],
    "sg:phone":"+32 477 45 18 52",
    "sg:postcode":"4690",
    "sg:province":"Li\u00e8ge",
    "sg:tags":[
        "farrier"
    ],
    "wof:name":"Keppenne J-l",
    "wof:placetype":"venue"
},
  "geometry": {"coordinates":[5.5363020897,50.7532157898],"type":"Point"}
}