{
  "type": "Feature",
  "properties": {
    "iso:country":"BE",
    "sg:address":"Van Notenstraat 69",
    "sg:city":"Antwerpen",
    "sg:orig_category":"Instellingen voor probleemkinderen Kindertehuizen",
    "sg:phone":"+32 3 366 37 74",
    "sg:postcode":"2100",
    "sg:province":"Antwerpen",
    "wof:name":"Dagcentrum Taimoem",
    "wof:placetype":"venue"
},
  "geometry": {"coordinates":[4.4586100578,51.2203941345],"type":"Point"}
}