{
  "type": "Feature",
  "properties": {
    "addr:full":"All\u00c9e Du Grand Cheniat 3 Gerpinnes Hainaut 6280",
    "addr:housenumber":"3",
    "addr:postcode":"6280",
    "addr:street":"Alle\u0301E Du Grand Cheniat;Hainaut",
    "iso:country":"BE",
    "sg:address":"All\u00c9e Du Grand Cheniat 3",
    "sg:city":"Gerpinnes",
    "sg:orig_category":"Zand and grindontginning",
    "sg:phone":"+32 71 47 28 13",
    "sg:postcode":"6280",
    "sg:province":"Hainaut",
    "wof:name":"Sabli\u00c8res De Freyr",
    "wof:placetype":"venue"
},
  "geometry": {"coordinates":[4.4656591415,50.3745422363],"type":"Point"}
}