{
  "type": "Feature",
  "properties": {
    "addr:full":"Rue De Jaunay-clan 41 Peruwelz Hainaut 7600",
    "addr:housenumber":"41",
    "addr:postcode":"7600",
    "addr:street":"Rue De Jaunay-Clan;Hainaut",
    "iso:country":"BE",
    "sg:address":"Rue De Jaunay-clan 41",
    "sg:city":"Peruwelz",
    "sg:orig_category":"Sportclubs",
    "sg:phone":"+32 69 77 62 06",
    "sg:postcode":"7600",
    "sg:province":"Hainaut",
    "wof:name":"Star Center Pipaix",
    "wof:placetype":"venue"
},
  "geometry": {"coordinates":[3.5852279663,50.5170402527],"type":"Point"}
}