{
  "type": "Feature",
  "properties": {
    "iso:country":"BE",
    "sg:address":"St. Annastraat 127a",
    "sg:city":"Hamme",
    "sg:orig_category":"Erotische Etablissementen",
    "sg:phone":"+32 52 47 94 93",
    "sg:postcode":"9220",
    "sg:province":"Oost-Vlaanderen",
    "wof:name":"New Riddershof",
    "wof:placetype":"venue"
},
  "geometry": {"coordinates":[4.0646767616,51.0904846191],"type":"Point"}
}