{
  "type": "Feature",
  "properties": {
    "addr:full":"Kausdelle 12 Huldenberg Vlaams-Brabant 3040",
    "addr:housenumber":"12",
    "addr:postcode":"3040",
    "addr:street":"Kausdelle",
    "iso:country":"BE",
    "sg:address":"Kausdelle 12",
    "sg:city":"Huldenberg",
    "sg:orig_category":"Entretien and r\u00e9parations de voitures",
    "sg:phone":"+32 2 687 46 13",
    "sg:postcode":"3040",
    "sg:province":"Vlaams-Brabant",
    "wof:name":"Andre Stas",
    "wof:placetype":"venue"
},
  "geometry": {"coordinates":[4.5824432373,50.7858085632],"type":"Point"}
}