{
  "type": "Feature",
  "properties": {
    "iso:country":"BE",
    "sg:address":"Bergstraat 4",
    "sg:city":"Gingelom (borlo)",
    "sg:classifiers":[
        {
            "category":"Airport",
            "subcategory":"International",
            "type":"Transportation"
        }
    ],
    "sg:phone":"+32 11 59 79 60",
    "sg:postcode":"3891",
    "sg:province":"Limburg",
    "sg:tags":[
        "-",
        "transport"
    ],
    "wof:name":"Tmp International",
    "wof:placetype":"venue"
},
  "geometry": {"coordinates":[5.1800508499,50.7416915894],"type":"Point"}
}