{
  "type": "Feature",
  "properties": {
    "addr:full":"Route De Wallonie 168 Saint-ghislain Hainaut 7331",
    "addr:housenumber":"168",
    "addr:postcode":"7331",
    "addr:street":"Route De Wallonie;Hainaut",
    "iso:country":"BE",
    "sg:address":"Route De Wallonie 168",
    "sg:city":"Saint-ghislain",
    "sg:orig_category":"Diverse grafische activiteiten Film-, tv- and videoproductie Marketingbureaus Marktonderzoekbureaus ",
    "sg:phone":"+32 65 64 26 19",
    "sg:postcode":"7331",
    "sg:province":"Hainaut",
    "wof:name":"Bureau Orange Bleu",
    "wof:placetype":"venue"
},
  "geometry": {"coordinates":[3.8393619061,50.4777030945],"type":"Point"}
}