{
  "type": "Feature",
  "properties": {
    "iso:country":"BE",
    "sg:address":"Grand'place 14",
    "sg:city":"Dour",
    "sg:orig_category":"Advocaten and juridische adviseurs",
    "sg:phone":"+32 65 65 55 55",
    "sg:postcode":"7370",
    "sg:province":"Hainaut",
    "wof:name":"Yvette Mazy",
    "wof:placetype":"venue"
},
  "geometry": {"coordinates":[3.7798650265,50.3962402344],"type":"Point"}
}