{
  "type": "Feature",
  "properties": {
    "addr:full":"Schilsweg 4 Eupen/eupen Li\u00e8ge 4700",
    "addr:housenumber":"4",
    "addr:postcode":"4700",
    "addr:street":"Schilsweg",
    "iso:country":"BE",
    "sg:address":"Schilsweg 4",
    "sg:city":"Eupen/eupen",
    "sg:orig_category":"Banques and organismes de cr\u00e9dit",
    "sg:phone":"+32 87 74 06 28",
    "sg:postcode":"4700",
    "sg:province":"Li\u00e8ge",
    "wof:name":"Centea",
    "wof:placetype":"venue"
},
  "geometry": {"coordinates":[6.0403738022,50.6218185425],"type":"Point"}
}