{
  "type": "Feature",
  "properties": {
    "addr:full":"Rue Du Peuple 85 Colfontaine Hainaut 7340",
    "addr:housenumber":"85",
    "addr:postcode":"7340",
    "addr:street":"Rue Du Peuple",
    "iso:country":"BE",
    "sg:address":"Rue Du Peuple 85",
    "sg:city":"Colfontaine",
    "sg:orig_category":"Chaussures",
    "sg:phone":"+32 65 67 29 45",
    "sg:postcode":"7340",
    "sg:province":"Hainaut",
    "wof:name":"Robert Caufriez",
    "wof:placetype":"venue"
},
  "geometry": {"coordinates":[3.8620989323,50.4086837769],"type":"Point"}
}