{
  "type": "Feature",
  "properties": {
    "addr:full":"Steenweg Op Blaasveld 113 Mechelen (heffen) Antwerpen 2801",
    "addr:housenumber":"113",
    "addr:postcode":"2801",
    "addr:street":"Steenweg Op Blaasveld",
    "iso:country":"BE",
    "sg:address":"Steenweg Op Blaasveld 113",
    "sg:city":"Mechelen (heffen)",
    "sg:classifiers":[
        {
            "category":"Building & Trades",
            "subcategory":"Electrical",
            "type":"Services"
        }
    ],
    "sg:phone":"+32 3 886 19 52",
    "sg:postcode":"2801",
    "sg:province":"Antwerpen",
    "sg:tags":[
        "electric",
        "-",
        "housewiring",
        "contractor"
    ],
    "wof:name":"De Vleeschouwer S",
    "wof:placetype":"venue"
},
  "geometry": {"coordinates":[4.4020619392,51.0469665527],"type":"Point"}
}