{
  "type": "Feature",
  "properties": {
    "addr:full":"Chauss\u00e9e De Wavre 8 Wanze Li\u00e8ge 4520",
    "addr:housenumber":"8",
    "addr:postcode":"4520",
    "addr:street":"Chausse\u0301E De Wavre",
    "iso:country":"BE",
    "sg:address":"Chauss\u00e9e De Wavre 8",
    "sg:city":"Wanze",
    "sg:classifiers":[
        {
            "category":"Shopping",
            "subcategory":"Bridal",
            "type":"Retail Goods"
        }
    ],
    "sg:phone":"+32 85 21 14 15",
    "sg:postcode":"4520",
    "sg:province":"Li\u00e8ge",
    "sg:tags":[
        "list",
        "-",
        "present",
        "wedding"
    ],
    "wof:name":"Resimont-id",
    "wof:placetype":"venue"
},
  "geometry": {"coordinates":[5.2173647881,50.5355186462],"type":"Point"}
}