{
  "type": "Feature",
  "properties": {
    "addr:full":"Ramskapellestraat 10 Nieuwpoort West-Vlaanderen 8620",
    "addr:housenumber":"10",
    "addr:postcode":"8620",
    "addr:street":"Ramskapellestraat",
    "iso:country":"BE",
    "sg:address":"Ramskapellestraat 10",
    "sg:city":"Nieuwpoort",
    "sg:orig_category":"Rundveehouders Varkenskwekers",
    "sg:phone":"+32 58 23 41 78",
    "sg:postcode":"8620",
    "sg:province":"West-Vlaanderen",
    "wof:name":"Ivan Monballiu",
    "wof:placetype":"venue"
},
  "geometry": {"coordinates":[2.7669389248,51.1247177124],"type":"Point"}
}