{
  "type": "Feature",
  "properties": {
    "addr:full":"Werviksesteenweg 309 Komen-waasten/comines-warneton Hainaut 7780",
    "addr:housenumber":"309;7780",
    "addr:street":"Werviksesteenweg",
    "iso:country":"BE",
    "sg:address":"Werviksesteenweg 309",
    "sg:city":"Komen-waasten/comines-warneton",
    "sg:orig_category":"Kapsalons",
    "sg:phone":"+32 56 55 88 75",
    "sg:postcode":"7780",
    "sg:province":"Hainaut",
    "wof:name":"Coiffure La Griffe",
    "wof:placetype":"venue"
},
  "geometry": {"coordinates":[2.9984300137,50.7863311768],"type":"Point"}
}