{
  "type": "Feature",
  "properties": {
    "iso:country":"BE",
    "sg:address":"Sint-rochuslaan 1",
    "sg:city":"Borgloon",
    "sg:classifiers":[
        {
            "category":"Wholesale",
            "subcategory":"Meat",
            "type":"Manufacturing & Wholesale Goods"
        }
    ],
    "sg:phone":"+32 12 74 11 11",
    "sg:postcode":"3840",
    "sg:province":"Limburg",
    "sg:tags":[
        "whol",
        "-"
    ],
    "wof:name":"Ory Vleeshandel Nv",
    "wof:placetype":"venue"
},
  "geometry": {"coordinates":[5.3514280319,50.8019866943],"type":"Point"}
}