{
  "type": "Feature",
  "properties": {
    "iso:country":"BE",
    "sg:address":"Rue Du Saiwiat 18",
    "sg:city":"Eghez\u00e9e",
    "sg:classifiers":[
        {
            "category":"Shopping",
            "subcategory":"Antiques",
            "type":"Retail Goods"
        }
    ],
    "sg:phone":"+32 81 85 69 90",
    "sg:postcode":"5310",
    "sg:province":"Namur",
    "wof:name":"Euro-troc",
    "wof:placetype":"venue"
},
  "geometry": {"coordinates":[4.9073719978,50.5948448181],"type":"Point"}
}