{
  "type": "Feature",
  "properties": {
    "iso:country":"BE",
    "sg:address":"Vossenbergstraat 10b6",
    "sg:city":"Maaseik",
    "sg:orig_category":"Binnenhuisarchitecten",
    "sg:phone":"+32 89 56 10 49",
    "sg:postcode":"3680",
    "sg:province":"Limburg",
    "wof:name":"Bert Quadvlieg",
    "wof:placetype":"venue"
},
  "geometry": {"coordinates":[5.7900252342,51.0944671631],"type":"Point"}
}