{
  "type": "Feature",
  "properties": {
    "iso:country":"BE",
    "sg:address":"Avenue Adolphe Demeur 15",
    "sg:city":"Sint-gillis/saint-gilles",
    "sg:orig_category":"M\u00e9decins and sp\u00e9cialistes",
    "sg:phone":"+32 2 537 61 66",
    "sg:postcode":"1060",
    "sg:province":"Bruxelles-Capitale",
    "wof:name":"Michel Dewinter",
    "wof:placetype":"venue"
},
  "geometry": {"coordinates":[4.3461999893,50.8255691528],"type":"Point"}
}