{
  "type": "Feature",
  "properties": {
    "addr:full":"23 Rue Osseghem 1080 Bruxelles 23",
    "addr:housenumber":"23",
    "addr:postcode":"1080;23",
    "addr:street":"Rue Osseghem",
    "iso:country":"BE",
    "sg:address":"23",
    "sg:city":"Rue Osseghem 1080 Bruxelles",
    "sg:classifiers":[
        {
            "category":"Shopping",
            "subcategory":"Computers & Home Electronics",
            "type":"Retail Goods"
        }
    ],
    "sg:phone":"+32 2 410 82 24",
    "sg:postcode":"23",
    "sg:tags":[
        "household",
        "appliance",
        "telecommunication",
        "audio-visual"
    ],
    "wof:name":"Emji Sprl",
    "wof:placetype":"venue"
},
  "geometry": {"coordinates":[4.3093128204,50.8519248962],"type":"Point"}
}