{
  "type": "Feature",
  "properties": {
    "iso:country":"BE",
    "sg:address":"Bruggestraat 1",
    "sg:city":"Beernem",
    "sg:orig_category":"Sportclubs",
    "sg:phone":"+32 50 78 09 43",
    "sg:postcode":"8730",
    "sg:province":"West-Vlaanderen",
    "wof:name":"Calypso",
    "wof:placetype":"venue"
},
  "geometry": {"coordinates":[3.3383619785,51.1685218811],"type":"Point"}
}