{
  "type": "Feature",
  "properties": {
    "iso:country":"BE",
    "sg:address":"Kruindersweg 34",
    "sg:city":"Maasmechelen",
    "sg:orig_category":"Woningbouw",
    "sg:phone":"+32 89 76 04 05",
    "sg:postcode":"3630",
    "sg:province":"Limburg",
    "wof:name":"Vincenzo De Martino",
    "wof:placetype":"venue"
},
  "geometry": {"coordinates":[5.6961350441,50.963848114],"type":"Point"}
}