{
  "type": "Feature",
  "properties": {
    "iso:country":"BE",
    "sg:address":"De Pintelaan 347ba",
    "sg:city":"Gent",
    "sg:orig_category":"Activit\u00e9s diverses d'imprimerie. Agences de publicit\u00e9. R\u00e9alisation de programmes and logiciels",
    "sg:phone":"+32 9 243 81 81",
    "sg:postcode":"9000",
    "sg:province":"Oost-Vlaanderen",
    "wof:name":"Living Stone",
    "wof:placetype":"venue"
},
  "geometry": {"coordinates":[3.7124190331,51.0229187012],"type":"Point"}
}