{
  "type": "Feature",
  "properties": {
    "addr:full":"Lindenstraat 73 Oostkamp West-Vlaanderen 8020",
    "addr:housenumber":"73",
    "addr:postcode":"8020",
    "addr:street":"Lindenstraat",
    "iso:country":"BE",
    "sg:address":"Lindenstraat 73",
    "sg:city":"Oostkamp",
    "sg:classifiers":[
        {
            "category":"Health Services",
            "subcategory":"Doctor",
            "type":"Services"
        }
    ],
    "sg:phone":"+32 50 35 80 57",
    "sg:postcode":"8020",
    "sg:province":"West-Vlaanderen",
    "sg:tags":[
        "medicinephysicians",
        "surgeon"
    ],
    "wof:name":"Callewaert E",
    "wof:placetype":"venue"
},
  "geometry": {"coordinates":[3.2422749996,51.1807174683],"type":"Point"}
}