{
  "type": "Feature",
  "properties": {
    "addr:full":"Bliekstraat 29 Deinze (astene) Oost-Vlaanderen 9800",
    "addr:housenumber":"29",
    "addr:postcode":"9800",
    "addr:street":"Bliekstraat",
    "iso:country":"BE",
    "sg:address":"Bliekstraat 29",
    "sg:city":"Deinze (astene)",
    "sg:classifiers":[
        {
            "category":"Retail",
            "subcategory":"Car Wash",
            "type":"Services"
        }
    ],
    "sg:phone":"+32 9 386 12 04",
    "sg:postcode":"9800",
    "sg:province":"Oost-Vlaanderen",
    "sg:tags":[
        "automobile",
        "washing",
        "-",
        "truck"
    ],
    "wof:name":"Car Cleaning Systems Bvba",
    "wof:placetype":"venue"
},
  "geometry": {"coordinates":[3.530174017,50.9863166809],"type":"Point"}
}