{
  "type": "Feature",
  "properties": {
    "addr:full":"Berkemei 82 Zoersel Antwerpen 2980",
    "addr:housenumber":"82",
    "addr:postcode":"2980",
    "addr:street":"Berkemei",
    "iso:country":"BE",
    "sg:address":"Berkemei 82",
    "sg:city":"Zoersel",
    "sg:orig_category":"Services pour animaux domestiques",
    "sg:phone":"+32 3 383 35 46",
    "sg:postcode":"2980",
    "sg:province":"Antwerpen",
    "wof:name":"Hondenkapsalon Gabber",
    "wof:placetype":"venue"
},
  "geometry": {"coordinates":[4.6570568085,51.2458839417],"type":"Point"}
}