{
  "type": "Feature",
  "properties": {
    "iso:country":"BE",
    "sg:address":"Dorp 2",
    "sg:city":"Lennik (sint-martens-lennik)",
    "sg:orig_category":"Fiduciairies",
    "sg:phone":"+32 2 532 44 45",
    "sg:postcode":"1750",
    "sg:province":"Vlaams-Brabant",
    "wof:name":"Van Der Voorde & Co Bvba",
    "wof:placetype":"venue"
},
  "geometry": {"coordinates":[4.1653652191,50.8122520447],"type":"Point"}
}