{
  "type": "Feature",
  "properties": {
    "iso:country":"BE",
    "sg:address":"Bosstr 83",
    "sg:city":"Halen",
    "sg:classifiers":[
        {
            "category":"Farming",
            "subcategory":"Livestock Farm",
            "type":"Manufacturing & Wholesale Goods"
        }
    ],
    "sg:phone":"+32 13 44 19 66",
    "sg:postcode":"3545",
    "sg:province":"Limburg",
    "sg:tags":[
        "horticulture",
        "vegetable",
        "fruit",
        "agriculture"
    ],
    "wof:name":"Morren & Jorofru Nv",
    "wof:placetype":"venue"
},
  "geometry": {"coordinates":[5.10998106,50.9203300476],"type":"Point"}
}