{
  "type": "Feature",
  "properties": {
    "addr:full":"Champs 814 Bertogne (longchamps) Luxembourg 6688",
    "addr:housenumber":"814",
    "addr:postcode":"6688",
    "iso:country":"BE",
    "sg:address":"Champs 814",
    "sg:city":"Bertogne (longchamps)",
    "sg:classifiers":[
        {
            "category":"Retail",
            "subcategory":"Animal Services",
            "type":"Services"
        }
    ],
    "sg:phone":"+32 61 21 67 59",
    "sg:postcode":"6688",
    "sg:province":"Luxembourg",
    "sg:tags":[
        "farrier"
    ],
    "wof:name":"Leduc S",
    "wof:placetype":"venue"
},
  "geometry": {"coordinates":[5.6678438187,50.041179657],"type":"Point"}
}