{
  "type": "Feature",
  "properties": {
    "addr:full":"Rue Groeselenberg 37a Box 2 Bruxelles (uccle) Bruxelles-Capitale 1180",
    "addr:housenumber":"37a box 2",
    "addr:postcode":"1180",
    "addr:street":"Rue Groeselenberg",
    "iso:country":"BE",
    "sg:address":"Rue Groeselenberg 37a Box 2",
    "sg:city":"Bruxelles (uccle)",
    "sg:classifiers":[
        {
            "category":"Real Estate",
            "subcategory":"Architect",
            "type":"Services"
        }
    ],
    "sg:phone":"+32 2 374 38 61",
    "sg:postcode":"1180",
    "sg:province":"Bruxelles-Capitale",
    "wof:name":"Casse A",
    "wof:placetype":"venue"
},
  "geometry": {"coordinates":[4.3518371582,50.8025512695],"type":"Point"}
}