{
  "type": "Feature",
  "properties": {
    "addr:full":"Gentstraat 43 Beveren Oost-Vlaanderen 9120",
    "addr:housenumber":"43",
    "addr:postcode":"9120",
    "addr:street":"Gentstraat",
    "iso:country":"BE",
    "sg:address":"Gentstraat 43",
    "sg:city":"Beveren",
    "sg:orig_category":"Eleveurs de bovins",
    "sg:phone":"+32 3 775 42 26",
    "sg:postcode":"9120",
    "sg:province":"Oost-Vlaanderen",
    "wof:name":"Rudolf Vyt",
    "wof:placetype":"venue"
},
  "geometry": {"coordinates":[4.2715802193,51.2082252502],"type":"Point"}
}