{
  "type": "Feature",
  "properties": {
    "iso:country":"BE",
    "sg:address":"Grote Markt 9",
    "sg:city":"Tongeren",
    "sg:classifiers":[
        {
            "category":"Restaurant",
            "type":"Food & Drink"
        }
    ],
    "sg:phone":"+32 12 23 51 58",
    "sg:postcode":"3700",
    "sg:province":"Limburg",
    "wof:name":"Tearoom Chopin",
    "wof:placetype":"venue"
},
  "geometry": {"coordinates":[5.463198185,50.7808303833],"type":"Point"}
}