{
  "type": "Feature",
  "properties": {
    "iso:country":"BE",
    "sg:address":"Route D'ath 37-39",
    "sg:city":"Jurbise",
    "sg:classifiers":[
        {
            "category":"Autos & Motor Vehicles",
            "subcategory":"Automobile Sales",
            "type":"Retail Goods"
        }
    ],
    "sg:phone":"+32 65 22 71 82",
    "sg:postcode":"7050",
    "sg:province":"Hainaut",
    "sg:tags":[
        "car",
        "used",
        "-"
    ],
    "wof:name":"Star Import Export",
    "wof:placetype":"venue"
},
  "geometry": {"coordinates":[3.9308259487,50.5038566589],"type":"Point"}
}