{
  "type": "Feature",
  "properties": {
    "iso:country":"BE",
    "sg:address":"Avenue Mascaut 594",
    "sg:city":"Marcinelle",
    "sg:orig_category":"Dakwerken",
    "sg:phone":"+32 71 36 76 33",
    "sg:postcode":"6001",
    "sg:province":"Hainaut",
    "wof:name":"Entreprise Girardi",
    "wof:placetype":"venue"
},
  "geometry": {"coordinates":[4.4308490753,50.3850860596],"type":"Point"}
}