{
  "type": "Feature",
  "properties": {
    "addr:full":"R.du Foyer Schaerbeekois 23 Schaarbeek/schaerbeek Bruxelles-Capitale 1030",
    "addr:housenumber":"23",
    "addr:postcode":"1030",
    "addr:street":"Schaerbeekois",
    "iso:country":"BE",
    "sg:address":"R.du Foyer Schaerbeekois 23",
    "sg:city":"Schaarbeek/schaerbeek",
    "sg:orig_category":"Instituts de beaut\u00e9. Traitements param\u00e9dicaux",
    "sg:phone":"+32 2 216 33 97",
    "sg:postcode":"1030",
    "sg:province":"Bruxelles-Capitale",
    "wof:name":"Brichart",
    "wof:placetype":"venue"
},
  "geometry": {"coordinates":[4.3864898682,50.8713989258],"type":"Point"}
}