{
  "type": "Feature",
  "properties": {
    "addr:full":"Voorzienigheidstraat 7 Oostende West-Vlaanderen 8400",
    "addr:housenumber":"7",
    "addr:postcode":"8400",
    "addr:street":"Voorzienigheidstraat",
    "iso:country":"BE",
    "sg:address":"Voorzienigheidstraat 7",
    "sg:city":"Oostende",
    "sg:orig_category":"Sportclubs Sportterreinen and installaties behalve sportcentra",
    "sg:phone":"+32 59 51 11 43",
    "sg:postcode":"8400",
    "sg:province":"West-Vlaanderen",
    "wof:name":"K.s.k. Stadspersoneel",
    "wof:placetype":"venue"
},
  "geometry": {"coordinates":[2.8944311142,51.2159767151],"type":"Point"}
}