{
  "type": "Feature",
  "properties": {
    "addr:full":"Rue Louverex Li\u00c8ge Li\u00e8ge 4000",
    "addr:postcode":"4000",
    "addr:street":"Rue Louverex",
    "iso:country":"BE",
    "sg:address":"Rue Louverex",
    "sg:city":"Li\u00c8ge",
    "sg:orig_category":"Dierentuinen, botanische tuinen, sterrenwachten and natuurreservaten",
    "sg:phone":"+32 4 252 40 71",
    "sg:postcode":"4000",
    "sg:province":"Li\u00e8ge",
    "wof:name":"Serres & Jardin Botanique",
    "wof:placetype":"venue"
},
  "geometry": {"coordinates":[5.5644497871,50.6332397461],"type":"Point"}
}