{
  "type": "Feature",
  "properties": {
    "iso:country":"BE",
    "sg:address":"Fran\u00c7ois Bossaertsstraat 18",
    "sg:city":"Schaarbeek/schaerbeek",
    "sg:orig_category":"Kapsalons",
    "sg:phone":"+32 2 733 31 52",
    "sg:postcode":"1030",
    "sg:province":"Bruxelles-Capitale",
    "wof:name":"Nadia Hamdan",
    "wof:placetype":"venue"
},
  "geometry": {"coordinates":[4.3841347694,50.8543205261],"type":"Point"}
}