{
  "type": "Feature",
  "properties": {
    "addr:full":"Waterloosesteenweg 23 Sint-gillis/saint-gilles Bruxelles-Capitale 1060",
    "addr:housenumber":"23",
    "addr:postcode":"1060",
    "addr:street":"Waterloosesteenweg",
    "iso:country":"BE",
    "sg:address":"Waterloosesteenweg 23",
    "sg:city":"Sint-gillis/saint-gilles",
    "sg:orig_category":"Voedingsspeciaalzaken",
    "sg:phone":"+32 2 538 71 36",
    "sg:postcode":"1060",
    "sg:province":"Bruxelles-Capitale",
    "wof:name":"Casa Tella",
    "wof:placetype":"venue"
},
  "geometry": {"coordinates":[4.3445291519,50.8316078186],"type":"Point"}
}