{
  "type": "Feature",
  "properties": {
    "iso:country":"BE",
    "sg:address":"Rue Cazerie 1",
    "sg:city":"Celles",
    "sg:orig_category":"Pain, p\u00e2tisseries and confiseries",
    "sg:phone":"+32 69 45 41 21",
    "sg:postcode":"7760",
    "sg:province":"Hainaut",
    "wof:name":"Andre Roland",
    "wof:placetype":"venue"
},
  "geometry": {"coordinates":[3.4565119743,50.7120819092],"type":"Point"}
}