{
  "type": "Feature",
  "properties": {
    "addr:full":"Rue Alphonse Poullet 34 Mouscron (dottignies) Hainaut 7711",
    "addr:housenumber":"34",
    "addr:postcode":"7711",
    "addr:street":"Rue Alphonse Poullet",
    "iso:country":"BE",
    "sg:address":"Rue Alphonse Poullet 34",
    "sg:city":"Mouscron (dottignies)",
    "sg:orig_category":"Non-Classified Establishments",
    "sg:phone":"+32 56 48 56 76",
    "sg:postcode":"7711",
    "sg:province":"Hainaut",
    "wof:name":"G.f.i. Services Sprl",
    "wof:placetype":"venue"
},
  "geometry": {"coordinates":[3.3048028946,50.7296257019],"type":"Point"}
}