{
  "type": "Feature",
  "properties": {
    "iso:country":"BE",
    "sg:address":"Chemin Des Grands Pr\u00c9s 441",
    "sg:city":"Mons",
    "sg:orig_category":"Services pour animaux domestiques",
    "sg:phone":"+32 65 31 71 80",
    "sg:postcode":"7000",
    "sg:province":"Hainaut",
    "wof:name":"Pension Du Pont Canal",
    "wof:placetype":"venue"
},
  "geometry": {"coordinates":[3.9229640961,50.4544296265],"type":"Point"}
}