{
  "type": "Feature",
  "properties": {
    "iso:country":"BE",
    "sg:address":"Massemsesteenweg 255",
    "sg:city":"Wetteren",
    "sg:classifiers":[
        {
            "category":"Cafe",
            "type":"Food & Drink"
        }
    ],
    "sg:phone":"+32 9 368 07 40",
    "sg:postcode":"9230",
    "sg:province":"Oost-Vlaanderen",
    "sg:tags":[
        "caf\u00e9s"
    ],
    "wof:name":"Hans Jacobs",
    "wof:placetype":"venue"
},
  "geometry": {"coordinates":[3.8790500164,50.9921302795],"type":"Point"}
}