{
  "type": "Feature",
  "properties": {
    "iso:country":"BE",
    "sg:address":"Plaats-vondel 3",
    "sg:city":"Scherpenheuvel-zichem",
    "sg:orig_category":"Installatie van houten of kunststof schrijnwerk",
    "sg:phone":"+32 13 77 31 04",
    "sg:postcode":"3272",
    "sg:province":"Vlaams-Brabant",
    "wof:name":"Deckers Jos & Rene",
    "wof:placetype":"venue"
},
  "geometry": {"coordinates":[4.9551720619,51.0159645081],"type":"Point"}
}