{
  "type": "Feature",
  "properties": {
    "addr:full":"Rue De Virelles 9 Cerfontaine Namur 5630",
    "addr:housenumber":"9",
    "addr:postcode":"5630",
    "addr:street":"Rue De Virelles",
    "iso:country":"BE",
    "sg:address":"Rue De Virelles 9",
    "sg:city":"Cerfontaine",
    "sg:classifiers":[
        {
            "category":"Personal",
            "subcategory":"Beauty Salon",
            "type":"Services"
        }
    ],
    "sg:phone":"+32 71 64 40 93",
    "sg:postcode":"5630",
    "sg:province":"Namur",
    "sg:tags":[
        "lady",
        "-",
        "hairdressing"
    ],
    "wof:name":"Fran\u00e7ois M",
    "wof:placetype":"venue"
},
  "geometry": {"coordinates":[4.4030599594,50.1677284241],"type":"Point"}
}