{
  "type": "Feature",
  "properties": {
    "iso:country":"BE",
    "sg:address":"Zeedijk 98b231",
    "sg:city":"Oostende",
    "sg:orig_category":"Artsen and specialisten",
    "sg:phone":"+32 59 80 67 28",
    "sg:postcode":"8400",
    "sg:province":"West-Vlaanderen",
    "wof:name":"Michel Hanssens",
    "wof:placetype":"venue"
},
  "geometry": {"coordinates":[2.896559,51.2243499756],"type":"Point"}
}