{
  "type": "Feature",
  "properties": {
    "iso:country":"BE",
    "sg:address":"Rollegemstraat 191",
    "sg:city":"Ledegem",
    "sg:classifiers":[
        {
            "category":"Cafe",
            "type":"Food & Drink"
        }
    ],
    "sg:phone":"+32 56 50 91 29",
    "sg:postcode":"8880",
    "sg:province":"West-Vlaanderen",
    "sg:tags":[
        "caf\u00e9s"
    ],
    "wof:name":"Lia Deltour",
    "wof:placetype":"venue"
},
  "geometry": {"coordinates":[3.1366300583,50.8625335693],"type":"Point"}
}