{
  "type": "Feature",
  "properties": {
    "iso:country":"BE",
    "sg:address":"Castelsebaan 85",
    "sg:city":"Mol",
    "sg:classifiers":[
        {
            "category":"Health Services",
            "subcategory":"Nursing And Care Facility",
            "type":"Services"
        }
    ],
    "sg:phone":"+32 14 32 28 82",
    "sg:postcode":"2400",
    "sg:province":"Antwerpen",
    "sg:tags":[
        "home"
    ],
    "wof:name":"Vanhoof-paepen K",
    "wof:placetype":"venue"
},
  "geometry": {"coordinates":[5.0623340607,51.1984977722],"type":"Point"}
}