{
  "type": "Feature",
  "properties": {
    "iso:country":"BE",
    "sg:address":"Rue Turenne 30",
    "sg:city":"Charleroi",
    "sg:classifiers":[
        {
            "category":"Personal",
            "subcategory":"Psychics & Astrologers",
            "type":"Services"
        }
    ],
    "sg:phone":"+32 479 53 11 97",
    "sg:postcode":"6000",
    "sg:province":"Hainaut",
    "sg:tags":[
        "astrology"
    ],
    "wof:name":"Prof Emill",
    "wof:placetype":"venue"
},
  "geometry": {"coordinates":[4.4411659241,50.4116172791],"type":"Point"}
}