{
  "type": "Feature",
  "properties": {
    "iso:country":"BE",
    "sg:address":"Rue De Namur 15-17",
    "sg:city":"Wavre",
    "sg:classifiers":[
        {
            "category":"Home & Garden",
            "subcategory":"Home Furnishings",
            "type":"Retail Goods"
        }
    ],
    "sg:phone":"+32 10 24 32 10",
    "sg:postcode":"1300",
    "sg:province":"Brabant Wallon",
    "sg:tags":[
        "-",
        "furniture"
    ],
    "wof:name":"Maison & Objets",
    "wof:placetype":"venue"
},
  "geometry": {"coordinates":[4.6113181114,50.7128562927],"type":"Point"}
}