{
  "type": "Feature",
  "properties": {
    "iso:country":"BE",
    "sg:address":"Rue E Martin 7ba",
    "sg:city":"Tournai",
    "sg:orig_category":"Metaalbehandeling and -bekleding",
    "sg:phone":"+32 69 35 26 86",
    "sg:postcode":"7520",
    "sg:province":"Hainaut",
    "wof:name":"Wilfart St",
    "wof:placetype":"venue"
},
  "geometry": {"coordinates":[3.2830650806,50.6447639465],"type":"Point"}
}