{
  "type": "Feature",
  "properties": {
    "addr:full":"Rue De Colard Trouillet 18 Seraing Li\u00e8ge 4100",
    "addr:housenumber":"18",
    "addr:postcode":"4100",
    "addr:street":"Rue De Colard Trouillet",
    "iso:country":"BE",
    "sg:address":"Rue De Colard Trouillet 18",
    "sg:city":"Seraing",
    "sg:classifiers":[
        {
            "category":"Cafe",
            "type":"Food & Drink"
        }
    ],
    "sg:phone":"+32 4 337 11 04",
    "sg:postcode":"4100",
    "sg:province":"Li\u00e8ge",
    "sg:tags":[
        "snack-bars"
    ],
    "wof:name":"Cafet'18 (la)",
    "wof:placetype":"venue"
},
  "geometry": {"coordinates":[5.5098910332,50.6148910522],"type":"Point"}
}