{
  "type": "Feature",
  "properties": {
    "addr:full":"Lentestraat 1 Hasselt Limburg 3500",
    "addr:housenumber":"1",
    "addr:postcode":"3500",
    "addr:street":"Lentestraat",
    "iso:country":"BE",
    "sg:address":"Lentestraat 1",
    "sg:city":"Hasselt",
    "sg:classifiers":[
        {
            "category":"Health Services",
            "subcategory":"Dentist",
            "type":"Services"
        }
    ],
    "sg:phone":"+32 11 27 18 31",
    "sg:postcode":"3500",
    "sg:province":"Limburg",
    "wof:name":"Werck M",
    "wof:placetype":"venue"
},
  "geometry": {"coordinates":[5.3453559875,50.9197998047],"type":"Point"}
}