{
  "type": "Feature",
  "properties": {
    "iso:country":"BE",
    "sg:address":"Onze Lieve Vrouwlaan 125",
    "sg:city":"Evere",
    "sg:orig_category":"Immobili\u00ebnkantoren",
    "sg:phone":"+32 2 242 93 99",
    "sg:postcode":"1140",
    "sg:province":"Bruxelles-Capitale",
    "wof:name":"Assistance Service Immobilier",
    "wof:placetype":"venue"
},
  "geometry": {"coordinates":[4.4012727737,50.871547699],"type":"Point"}
}