{
  "type": "Feature",
  "properties": {
    "iso:country":"BE",
    "sg:address":"Grote Markt 66",
    "sg:city":"Sint-truiden",
    "sg:orig_category":"Bloemen and planten",
    "sg:phone":"+32 11 68 32 22",
    "sg:postcode":"3800",
    "sg:province":"Limburg",
    "wof:name":"Bloemen Koopmans",
    "wof:placetype":"venue"
},
  "geometry": {"coordinates":[5.187046051,50.8158874512],"type":"Point"}
}