{
  "type": "Feature",
  "properties": {
    "addr:full":"Veldstr 31 Denderleeuw (groot) Oost-Vlaanderen 9470",
    "addr:housenumber":"31",
    "addr:postcode":"9470",
    "addr:street":"Veldstr;Groot Oost-Vlaanderen",
    "iso:country":"BE",
    "sg:address":"Veldstr 31",
    "sg:city":"Denderleeuw (groot)",
    "sg:orig_category":"Kapsalons",
    "sg:phone":"+32 53 66 66 45",
    "sg:postcode":"9470",
    "sg:province":"Oost-Vlaanderen",
    "wof:name":"De Neve",
    "wof:placetype":"venue"
},
  "geometry": {"coordinates":[4.0720028877,50.8851127625],"type":"Point"}
}