{
  "type": "Feature",
  "properties": {
    "addr:full":"Vlasstraat 1 Deerlijk West-Vlaanderen 8540",
    "addr:housenumber":"1",
    "addr:postcode":"8540",
    "addr:street":"Vlasstraat",
    "iso:country":"BE",
    "sg:address":"Vlasstraat 1",
    "sg:city":"Deerlijk",
    "sg:orig_category":"Rev\u00eatements de sols and murs",
    "sg:phone":"+32 56 70 17 72",
    "sg:postcode":"8540",
    "sg:province":"West-Vlaanderen",
    "wof:name":"Geert Debaere",
    "wof:placetype":"venue"
},
  "geometry": {"coordinates":[3.3433389664,50.8514251709],"type":"Point"}
}