{
  "type": "Feature",
  "properties": {
    "addr:full":"Place Fr\u00e8re Orban 7 Fontaine-l'ev\u00eaque Hainaut 6140",
    "addr:housenumber":"7",
    "addr:postcode":"6140",
    "addr:street":"Place Fre\u0300Re Orban;\u0302Que Hainaut",
    "iso:country":"BE",
    "sg:address":"Place Fr\u00e8re Orban 7",
    "sg:city":"Fontaine-l'ev\u00eaque",
    "sg:classifiers":[
        {
            "category":"Personal",
            "subcategory":"Beauty Salon",
            "type":"Services"
        }
    ],
    "sg:phone":"+32 71 54 42 54",
    "sg:postcode":"6140",
    "sg:province":"Hainaut",
    "wof:name":"Institut Perle D'\u00d4",
    "wof:placetype":"venue"
},
  "geometry": {"coordinates":[-111.9644622803,46.2507972717],"type":"Point"}
}