{
  "type": "Feature",
  "properties": {
    "addr:full":"Richard Caluwaertsstraat 6 Bornem (hingene) Antwerpen 2880",
    "addr:housenumber":"6",
    "addr:postcode":"2880",
    "addr:street":"Caluwaertsstraat",
    "iso:country":"BE",
    "sg:address":"Richard Caluwaertsstraat 6",
    "sg:city":"Bornem (hingene)",
    "sg:classifiers":[
        {
            "category":"Health Services",
            "subcategory":"Health Practitioner",
            "type":"Services"
        }
    ],
    "sg:phone":"+32 3 899 17 44",
    "sg:postcode":"2880",
    "sg:province":"Antwerpen",
    "sg:tags":[
        "physiotherapist"
    ],
    "wof:name":"De Pooter Annemie",
    "wof:placetype":"venue"
},
  "geometry": {"coordinates":[4.242205143,51.0998497009],"type":"Point"}
}