{
  "type": "Feature",
  "properties": {
    "addr:full":"Letterkouter 8 Zottegem (velzeke-ruddershove) Oost-Vlaanderen 9620",
    "addr:housenumber":"8",
    "addr:postcode":"9620",
    "addr:street":"Letterkouter",
    "iso:country":"BE",
    "sg:address":"Letterkouter 8",
    "sg:city":"Zottegem (velzeke-ruddershove)",
    "sg:classifiers":[
        {
            "category":"Community Center",
            "subcategory":"Youth",
            "type":"Public Place"
        }
    ],
    "sg:phone":"+32 9 360 16 34",
    "sg:postcode":"9620",
    "sg:province":"Oost-Vlaanderen",
    "sg:tags":[
        "club"
    ],
    "wof:name":"Jeugdheem De Populier",
    "wof:placetype":"venue"
},
  "geometry": {"coordinates":[3.8112111092,50.871181488],"type":"Point"}
}