{
  "type": "Feature",
  "properties": {
    "addr:full":"Brugse Steenweg 131 Veurne West-Vlaanderen 8630",
    "addr:housenumber":"131",
    "addr:postcode":"8630",
    "addr:street":"Brugse Steenweg",
    "iso:country":"BE",
    "sg:address":"Brugse Steenweg 131",
    "sg:city":"Veurne",
    "sg:orig_category":"Epiceries",
    "sg:phone":"+32 58 31 20 01",
    "sg:postcode":"8630",
    "sg:province":"West-Vlaanderen",
    "wof:name":"Ronny Dendooven",
    "wof:placetype":"venue"
},
  "geometry": {"coordinates":[2.6796190739,51.0751266479],"type":"Point"}
}