{
  "type": "Feature",
  "properties": {
    "addr:full":"Rue Louis Taburiaux 25 B8 Genappe Brabant Wallon 1472",
    "addr:housenumber":"25 b8",
    "addr:postcode":"1472",
    "addr:street":"Rue Louis Taburiaux;Wallon",
    "iso:country":"BE",
    "sg:address":"Rue Louis Taburiaux 25 B8",
    "sg:city":"Genappe",
    "sg:orig_category":"S\u00e9lection de personnel and placement",
    "sg:phone":"+32 67 79 05 90",
    "sg:postcode":"1472",
    "sg:province":"Brabant Wallon",
    "wof:name":"S.l.a.i.e. Genappe",
    "wof:placetype":"venue"
},
  "geometry": {"coordinates":[4.438849926,50.6078643799],"type":"Point"}
}