{
  "type": "Feature",
  "properties": {
    "iso:country":"BE",
    "sg:address":"Geneesheerstraat 5",
    "sg:city":"Hoeilaart",
    "sg:classifiers":[
        {
            "category":"Communications",
            "type":"Services"
        }
    ],
    "sg:phone":"+32 2 657 53 03",
    "sg:postcode":"1560",
    "sg:province":"Vlaams-Brabant",
    "sg:tags":[
        "translator"
    ],
    "wof:name":"Archiscan",
    "wof:placetype":"venue"
},
  "geometry": {"coordinates":[4.4793000221,50.7642631531],"type":"Point"}
}