{
  "type": "Feature",
  "properties": {
    "addr:full":"Rue Royale 97 Bruxelles Bruxelles-Capitale 1000",
    "addr:housenumber":"97",
    "addr:postcode":"1000",
    "addr:street":"Rue Royale",
    "iso:country":"BE",
    "sg:address":"Rue Royale 97",
    "sg:city":"Bruxelles",
    "sg:classifiers":[
        {
            "category":"Building & Trades",
            "subcategory":"Construction",
            "type":"Services"
        }
    ],
    "sg:phone":"+32 3 324 44 53",
    "sg:postcode":"1000",
    "sg:province":"Bruxelles-Capitale",
    "sg:tags":[
        "track"
    ],
    "wof:name":"Chabot Nv",
    "wof:placetype":"venue"
},
  "geometry": {"coordinates":[4.4500141144,51.2343101501],"type":"Point"}
}