{
  "type": "Feature",
  "properties": {
    "iso:country":"BE",
    "sg:address":"Place Du Beau Site 11",
    "sg:city":"Rixensart",
    "sg:classifiers":[
        {
            "category":"Retail",
            "subcategory":"Veterinary Services",
            "type":"Services"
        }
    ],
    "sg:phone":"+32 2 653 27 28",
    "sg:postcode":"1330",
    "sg:province":"Brabant Wallon",
    "sg:tags":[
        "veterinarian"
    ],
    "wof:name":"Berge H",
    "wof:placetype":"venue"
},
  "geometry": {"coordinates":[4.5464081764,50.7122306824],"type":"Point"}
}