{
  "type": "Feature",
  "properties": {
    "iso:country":"BE",
    "sg:address":"Weertersteenweg 383",
    "sg:city":"Kinrooi",
    "sg:classifiers":[
        {
            "category":"Shopping Center",
            "type":"Public Place"
        }
    ],
    "sg:phone":"+32 89 70 16 20",
    "sg:postcode":"3640",
    "sg:province":"Limburg",
    "sg:tags":[
        "furniture"
    ],
    "wof:name":"Spereco Bvba",
    "wof:placetype":"venue"
},
  "geometry": {"coordinates":[5.7421097755,51.1599807739],"type":"Point"}
}