{
  "type": "Feature",
  "properties": {
    "addr:full":"Beukendreef 4 Lanaken Limburg 3620",
    "addr:housenumber":"4",
    "addr:postcode":"3620",
    "addr:street":"Beukendreef",
    "iso:country":"BE",
    "sg:address":"Beukendreef 4",
    "sg:city":"Lanaken",
    "sg:orig_category":"S\u00e9lection de personnel and placement",
    "sg:phone":"+32 89 72 15 87",
    "sg:postcode":"3620",
    "sg:province":"Limburg",
    "wof:name":"K.m.c.",
    "wof:placetype":"venue"
},
  "geometry": {"coordinates":[5.6717047691,50.9015083313],"type":"Point"}
}