{
  "type": "Feature",
  "properties": {
    "iso:country":"BE",
    "sg:address":"Hof Te Fiennesstraat 18",
    "sg:city":"Maarkedal",
    "sg:classifiers":[
        {
            "category":"Cafe",
            "type":"Food & Drink"
        }
    ],
    "sg:phone":"+32 55 21 50 31",
    "sg:postcode":"9680",
    "sg:province":"Oost-Vlaanderen",
    "sg:tags":[
        "caf\u00e9s"
    ],
    "wof:name":"Ksv Maarkedal",
    "wof:placetype":"venue"
},
  "geometry": {"coordinates":[3.6343889236,50.7795143127],"type":"Point"}
}