{
  "type": "Feature",
  "properties": {
    "iso:country":"BE",
    "sg:address":"Kopkapelstraat 43",
    "sg:city":"Lokeren",
    "sg:orig_category":"Rev\u00eatements pour sols and murs. Peinture",
    "sg:phone":"+32 9 348 66 65",
    "sg:postcode":"9160",
    "sg:province":"Oost-Vlaanderen",
    "wof:name":"Danny De Vriendt",
    "wof:placetype":"venue"
},
  "geometry": {"coordinates":[4.0019412041,51.117275238],"type":"Point"}
}