{
  "type": "Feature",
  "properties": {
    "iso:country":"BE",
    "sg:address":"Steenweg Van Grembergen 8",
    "sg:city":"Dendermonde",
    "sg:orig_category":"Viessmann. Plomberie, chauffage and installations sanitaires",
    "sg:phone":"+32 52 22 32 02",
    "sg:postcode":"9200",
    "sg:province":"Oost-Vlaanderen",
    "wof:name":"Fierens Hans",
    "wof:placetype":"venue"
},
  "geometry": {"coordinates":[4.1014909744,51.035446167],"type":"Point"}
}