{
  "type": "Feature",
  "properties": {
    "iso:country":"BE",
    "sg:address":"Groenln 1b2",
    "sg:city":"Zelzate",
    "sg:classifiers":[
        {
            "category":"Personal",
            "subcategory":"Beauty Salon",
            "type":"Services"
        }
    ],
    "sg:phone":"+32 9 343 06 67",
    "sg:postcode":"9060",
    "sg:province":"Oost-Vlaanderen",
    "sg:tags":[
        "de",
        "coiffure"
    ],
    "wof:name":"Natacha's Hairstudio",
    "wof:placetype":"venue"
},
  "geometry": {"coordinates":[3.8146300316,51.1975364685],"type":"Point"}
}