{
  "type": "Feature",
  "properties": {
    "iso:country":"BE",
    "sg:address":"Oostereindestraat 32",
    "sg:city":"Lummen",
    "sg:orig_category":"Pain, p\u00e2tisseries and confiseries",
    "sg:phone":"+32 13 52 13 08",
    "sg:postcode":"3560",
    "sg:province":"Limburg",
    "wof:name":"Bakkerij Coenen J.",
    "wof:placetype":"venue"
},
  "geometry": {"coordinates":[5.1988921165,50.9883613586],"type":"Point"}
}