{
  "type": "Feature",
  "properties": {
    "iso:country":"BE",
    "sg:address":"Watertorenlaan 28",
    "sg:city":"Zaventem",
    "sg:classifiers":[
        {
            "category":"Wholesale",
            "subcategory":"Computers",
            "type":"Manufacturing & Wholesale Goods"
        }
    ],
    "sg:phone":"+32 2 721 31 75",
    "sg:postcode":"1930",
    "sg:province":"Vlaams-Brabant",
    "sg:tags":[
        "cabling",
        "processing",
        "-",
        "data"
    ],
    "wof:name":"Vhl Cabling Solution",
    "wof:placetype":"venue"
},
  "geometry": {"coordinates":[4.4723272324,50.8859481812],"type":"Point"}
}