{
  "type": "Feature",
  "properties": {
    "iso:country":"BE",
    "sg:address":"Rue De La Ronce 28",
    "sg:city":"Gembloux",
    "sg:orig_category":"Installation de menuiserie en bois and plastique",
    "sg:phone":"+32 81 63 44 92",
    "sg:postcode":"5032",
    "sg:province":"Namur",
    "wof:name":"Jean Zabus",
    "wof:placetype":"venue"
},
  "geometry": {"coordinates":[4.6528058052,50.5230712891],"type":"Point"}
}