{
  "type": "Feature",
  "properties": {
    "iso:country":"BE",
    "sg:address":"Rue Des H\u00c9ros 68",
    "sg:city":"Liege",
    "sg:classifiers":[
        {
            "category":"Bars & Pubs",
            "subcategory":"Nightclub",
            "type":"Food & Drink"
        }
    ],
    "sg:phone":"+32 4 247 12 30",
    "sg:postcode":"4000",
    "sg:province":"Li\u00e8ge",
    "sg:tags":[
        "nachtclubs",
        "dancing"
    ],
    "wof:name":"Romantic Alhambra",
    "wof:placetype":"venue"
},
  "geometry": {"coordinates":[5.5529370308,50.6830482483],"type":"Point"}
}