{
  "type": "Feature",
  "properties": {
    "iso:country":"BE",
    "sg:address":"Rue Alfred Defruisseaux 26",
    "sg:city":"Soumagne",
    "sg:orig_category":"Alternatieve geneeskunde",
    "sg:phone":"+32 4 377 60 08",
    "sg:postcode":"4630",
    "sg:province":"Li\u00e8ge",
    "wof:name":"Fran\u00c7oise Remy",
    "wof:placetype":"venue"
},
  "geometry": {"coordinates":[5.747262001,50.6083984375],"type":"Point"}
}