{
  "type": "Feature",
  "properties": {
    "addr:full":"Bredabaan 161b2 Brasschaat Antwerpen 2930",
    "addr:housenumber":"161b2",
    "addr:postcode":"2930",
    "addr:street":"Bredabaan",
    "iso:country":"BE",
    "sg:address":"Bredabaan 161b2",
    "sg:city":"Brasschaat",
    "sg:orig_category":"Avocats and conseillers juridiques",
    "sg:phone":"+32 3 653 00 27",
    "sg:postcode":"2930",
    "sg:province":"Antwerpen",
    "wof:name":"Gabri\u00cblle Van Bussel",
    "wof:placetype":"venue"
},
  "geometry": {"coordinates":[4.4844250679,51.2855606079],"type":"Point"}
}