{
  "type": "Feature",
  "properties": {
    "addr:full":"Quai Des Anglais 44 Nimy Hainaut 7020",
    "addr:housenumber":"44",
    "addr:postcode":"7020",
    "addr:street":"Quai Des Anglais",
    "iso:country":"BE",
    "sg:address":"Quai Des Anglais 44",
    "sg:city":"Nimy",
    "sg:classifiers":[
        {
            "category":"Military Area",
            "subcategory":"Air Force Base",
            "type":"Public Place"
        }
    ],
    "sg:phone":"+32 65 34 64 57",
    "sg:postcode":"7020",
    "sg:province":"Hainaut",
    "sg:tags":[
        "prime",
        "contractor",
        "contractors"
    ],
    "wof:name":"Abatir S.a.",
    "wof:placetype":"venue"
},
  "geometry": {"coordinates":[3.9454898834,50.4753608704],"type":"Point"}
}