{
  "type": "Feature",
  "properties": {
    "iso:country":"BE",
    "sg:address":"Faubourg De Bruxelles 5",
    "sg:city":"Nivelles",
    "sg:orig_category":"Schoonmaakbedrijven and ongediertebestrijding Tuinen",
    "sg:phone":"+32 67 21 51 93",
    "sg:postcode":"1400",
    "sg:province":"Brabant Wallon",
    "wof:name":"D.d. Marin",
    "wof:placetype":"venue"
},
  "geometry": {"coordinates":[4.3263969421,50.6006889343],"type":"Point"}
}