{
  "type": "Feature",
  "properties": {
    "iso:country":"BE",
    "sg:address":"Noorderlaan 133",
    "sg:city":"Antwerpen",
    "sg:classifiers":[
        {
            "category":"Manufacturing",
            "subcategory":"Chemicals & Compounds",
            "type":"Manufacturing & Wholesale Goods"
        }
    ],
    "sg:phone":"+32 3 541 42 69",
    "sg:postcode":"2030",
    "sg:province":"Antwerpen",
    "sg:tags":[
        "pharmaceutical",
        "chemistry"
    ],
    "wof:name":"Necarbo Bv",
    "wof:placetype":"venue"
},
  "geometry": {"coordinates":[4.402130127,51.2644462585],"type":"Point"}
}