{
  "type": "Feature",
  "properties": {
    "addr:full":"Rue Henin 79 Farciennes Hainaut 6240",
    "addr:housenumber":"79",
    "addr:postcode":"6240",
    "addr:street":"Rue Henin",
    "iso:country":"BE",
    "sg:address":"Rue Henin 79",
    "sg:city":"Farciennes",
    "sg:classifiers":[
        {
            "category":"Personal",
            "subcategory":"Beauty Salon",
            "type":"Services"
        }
    ],
    "sg:phone":"+32 71 38 79 67",
    "sg:postcode":"6240",
    "sg:province":"Hainaut",
    "sg:tags":[
        "de",
        "coiffure"
    ],
    "wof:name":"Francoise Dellisse",
    "wof:placetype":"venue"
},
  "geometry": {"coordinates":[4.5450577736,50.4274559021],"type":"Point"}
}