{
  "type": "Feature",
  "properties": {
    "iso:country":"BE",
    "sg:address":"Drongenstationstraat 61",
    "sg:city":"Drongen",
    "sg:classifiers":[
        {
            "category":"Manufacturing",
            "subcategory":"Printing",
            "type":"Manufacturing & Wholesale Goods"
        }
    ],
    "sg:phone":"+32 9 226 60 29",
    "sg:postcode":"9031",
    "sg:province":"Oost-Vlaanderen",
    "sg:tags":[
        "cd-rom",
        "duplication"
    ],
    "wof:name":"Meyriade Nv",
    "wof:placetype":"venue"
},
  "geometry": {"coordinates":[3.6560840607,51.047492981],"type":"Point"}
}