{
  "type": "Feature",
  "properties": {
    "iso:country":"BE",
    "sg:address":"Molenwegel 4",
    "sg:city":"Ardooie (koolskamp)",
    "sg:classifiers":[
        {
            "category":"Health Services",
            "subcategory":"Doctor",
            "type":"Services"
        }
    ],
    "sg:phone":"+32 51 74 68 67",
    "sg:postcode":"8851",
    "sg:province":"West-Vlaanderen",
    "sg:tags":[
        "medicinephysicians",
        "surgeon"
    ],
    "wof:name":"Deckers Luc",
    "wof:placetype":"venue"
},
  "geometry": {"coordinates":[3.2127399445,51.0020942688],"type":"Point"}
}