{
  "type": "Feature",
  "properties": {
    "iso:country":"BE",
    "sg:address":"Antwerpsesteenweg 48",
    "sg:city":"Essen",
    "sg:orig_category":"Eleveurs de bovins. Eleveurs and marchands de porcs",
    "sg:phone":"+32 3 667 27 25",
    "sg:postcode":"2910",
    "sg:province":"Antwerpen",
    "wof:name":"Jozef Peeters",
    "wof:placetype":"venue"
},
  "geometry": {"coordinates":[4.4821329117,51.4302940369],"type":"Point"}
}