{
  "type": "Feature",
  "properties": {
    "iso:country":"BE",
    "sg:address":"Rue S. Deloye 30",
    "sg:city":"Seraing (ougr\u00e9e)",
    "sg:classifiers":[
        {
            "category":"Professional",
            "subcategory":"Accounting & Tax Preparation",
            "type":"Services"
        }
    ],
    "sg:phone":"+32 4 337 47 43",
    "sg:postcode":"4102",
    "sg:province":"Li\u00e8ge",
    "sg:tags":[
        "bookkeeper"
    ],
    "wof:name":"Nguyen H-h",
    "wof:placetype":"venue"
},
  "geometry": {"coordinates":[5.5415048599,50.5881538391],"type":"Point"}
}