{
  "type": "Feature",
  "properties": {
    "iso:country":"BE",
    "sg:address":"Parc Du Peterbos 5 Box 24",
    "sg:city":"Bruxelles (anderlecht)",
    "sg:classifiers":[
        {
            "category":"Professional",
            "subcategory":"Art Services",
            "type":"Services"
        }
    ],
    "sg:phone":"+32 2 523 54 85",
    "sg:postcode":"1070",
    "sg:province":"Bruxelles-Capitale",
    "sg:tags":[
        "sculptor"
    ],
    "wof:name":"Devaert A",
    "wof:placetype":"venue"
},
  "geometry": {"coordinates":[4.2952270508,50.8428382874],"type":"Point"}
}