{
  "type": "Feature",
  "properties": {
    "addr:full":"Nieuwe Bevelsesteenweg 70 Nijlen (kessel) Antwerpen 2560",
    "addr:housenumber":"70",
    "addr:postcode":"2560",
    "addr:street":"Nieuwe Bevelsesteenweg",
    "iso:country":"BE",
    "sg:address":"Nieuwe Bevelsesteenweg 70",
    "sg:city":"Nijlen (kessel)",
    "sg:classifiers":[
        {
            "category":"Shopping",
            "subcategory":"Jewelry",
            "type":"Retail Goods"
        }
    ],
    "sg:phone":"+32 3 481 89 95",
    "sg:postcode":"2560",
    "sg:province":"Antwerpen",
    "sg:tags":[
        "jeweller",
        "-"
    ],
    "wof:name":"Verlinden Bvba",
    "wof:placetype":"venue"
},
  "geometry": {"coordinates":[4.6733560562,51.1552124023],"type":"Point"}
}