{
  "type": "Feature",
  "properties": {
    "addr:full":"Boulevard Anspach 65 Bruxelles Bruxelles-Capitale 1000",
    "addr:housenumber":"65",
    "addr:postcode":"1000",
    "addr:street":"Boulevard Anspach",
    "iso:country":"BE",
    "sg:address":"Boulevard Anspach 65",
    "sg:city":"Bruxelles",
    "sg:classifiers":[
        {
            "category":"Professional",
            "subcategory":"Employment Agencies",
            "type":"Services"
        }
    ],
    "sg:phone":"+32 2 505 14 11",
    "sg:postcode":"1000",
    "sg:province":"Bruxelles-Capitale",
    "wof:name":"Bgda",
    "wof:placetype":"venue"
},
  "geometry": {"coordinates":[4.3499851227,50.8489074707],"type":"Point"}
}