{
  "type": "Feature",
  "properties": {
    "addr:full":"Lubbeeksestraat 106 Boutersem (roosbeek) Vlaams-Brabant 3370",
    "addr:housenumber":"106",
    "addr:postcode":"3370",
    "addr:street":"Lubbeeksestraat",
    "iso:country":"BE",
    "sg:address":"Lubbeeksestraat 106",
    "sg:city":"Boutersem (roosbeek)",
    "sg:classifiers":[
        {
            "category":"Building & Trades",
            "subcategory":"Construction",
            "type":"Services"
        }
    ],
    "sg:phone":"+32 16 72 02 79",
    "sg:postcode":"3370",
    "sg:province":"Vlaams-Brabant",
    "sg:tags":[
        "installation",
        "-",
        "central",
        "heating"
    ],
    "wof:name":"Weygaerts J",
    "wof:placetype":"venue"
},
  "geometry": {"coordinates":[4.8628821373,50.8372001648],"type":"Point"}
}