{
  "type": "Feature",
  "properties": {
    "iso:country":"BE",
    "sg:address":"Place Alphonse Bosch 18",
    "sg:city":"Waver (groot)",
    "sg:orig_category":"S\u00e9curit\u00e9 sociale. Secr\u00e9tariats sociaux",
    "sg:phone":"+32 10 23 57 50",
    "sg:postcode":"1300",
    "sg:province":"Brabant Wallon",
    "wof:name":"Partena",
    "wof:placetype":"venue"
},
  "geometry": {"coordinates":[4.6119117737,50.7138252258],"type":"Point"}
}