{
  "type": "Feature",
  "properties": {
    "iso:country":"BE",
    "sg:address":"Kalmthoutse Steenweg 117",
    "sg:city":"Wuustwezel",
    "sg:orig_category":"M\u00e9decins and sp\u00e9cialistes",
    "sg:phone":"+32 3 669 85 55",
    "sg:postcode":"2990",
    "sg:province":"Antwerpen",
    "wof:name":"Gert Huysmans",
    "wof:placetype":"venue"
},
  "geometry": {"coordinates":[4.5790848732,51.3902206421],"type":"Point"}
}