{
  "type": "Feature",
  "properties": {
    "addr:full":"Doelstokstraat 4 Ardooie West-Vlaanderen 8850",
    "addr:housenumber":"4",
    "addr:postcode":"8850",
    "addr:street":"Doelstokstraat",
    "iso:country":"BE",
    "sg:address":"Doelstokstraat 4",
    "sg:city":"Ardooie",
    "sg:orig_category":"Installation de menuiserie en bois and plastique",
    "sg:phone":"+32 51 74 67 46",
    "sg:postcode":"8850",
    "sg:province":"West-Vlaanderen",
    "wof:name":"Bertin Van Maele",
    "wof:placetype":"venue"
},
  "geometry": {"coordinates":[3.209608078,50.9756698608],"type":"Point"}
}