{
  "type": "Feature",
  "properties": {
    "iso:country":"BE",
    "sg:address":"Tiensesteenweg 158a",
    "sg:city":"Bierbeek",
    "sg:orig_category":"Kapsalons",
    "sg:phone":"+32 16 46 22 70",
    "sg:postcode":"3360",
    "sg:province":"Vlaams-Brabant",
    "wof:name":"Bart Vancauwenbergh",
    "wof:placetype":"venue"
},
  "geometry": {"coordinates":[4.766245842,50.8614959717],"type":"Point"}
}