{
  "type": "Feature",
  "properties": {
    "addr:full":". Mons Hainaut 7000",
    "addr:postcode":"7000",
    "addr:street":"Hainaut",
    "iso:country":"BE",
    "sg:address":".",
    "sg:city":"Mons",
    "sg:orig_category":"Glaszetten and glaswerk Herstelling aan huis van huishoudartikelen Loodgieterij, verwarming and sani",
    "sg:phone":"+32 65 36 00 34",
    "sg:postcode":"7000",
    "sg:province":"Hainaut",
    "wof:name":"A. Antoine",
    "wof:placetype":"venue"
},
  "geometry": {"coordinates":[3.9522509575,50.4547271729],"type":"Point"}
}