{
  "type": "Feature",
  "properties": {
    "addr:full":"Basilieklaan 79a Scherpenheuvel-zichem (scherpenheuvel) Vlaams-Brabant 3270",
    "addr:housenumber":"79a",
    "addr:postcode":"3270",
    "addr:street":"Basilieklaan",
    "iso:country":"BE",
    "sg:address":"Basilieklaan 79a",
    "sg:city":"Scherpenheuvel-zichem (scherpenheuvel)",
    "sg:classifiers":[
        {
            "category":"Military Area",
            "subcategory":"Air Force Base",
            "type":"Public Place"
        }
    ],
    "sg:phone":"+32 13 77 72 90",
    "sg:postcode":"3270",
    "sg:province":"Vlaams-Brabant",
    "sg:tags":[
        "-",
        "lighting",
        "neon",
        "fluorescent"
    ],
    "wof:name":"Luna Lights Bvba",
    "wof:placetype":"venue"
},
  "geometry": {"coordinates":[4.9696159363,50.9798545837],"type":"Point"}
}