{
  "type": "Feature",
  "properties": {
    "iso:country":"BE",
    "sg:address":"Rue \u00c0 Paniers 64be",
    "sg:city":"Colfontaine",
    "sg:orig_category":"Entretien and r\u00e9parations de voitures",
    "sg:phone":"+32 65 66 32 73",
    "sg:postcode":"7340",
    "sg:province":"Hainaut",
    "wof:name":"Roland Vertenoeil",
    "wof:placetype":"venue"
},
  "geometry": {"coordinates":[3.8398931026,50.4094734192],"type":"Point"}
}