{
  "type": "Feature",
  "properties": {
    "iso:country":"BE",
    "sg:address":"Krijgslaan 186",
    "sg:city":"Gent",
    "sg:classifiers":[
        {
            "category":"Health Services",
            "subcategory":"Doctor",
            "type":"Services"
        }
    ],
    "sg:phone":"+32 9 222 91 01",
    "sg:postcode":"9000",
    "sg:province":"Oost-Vlaanderen",
    "sg:tags":[
        "medicinephysicians",
        "surgeon"
    ],
    "wof:name":"Boeykens Jean",
    "wof:placetype":"venue"
},
  "geometry": {"coordinates":[3.7159559727,51.0277175903],"type":"Point"}
}