{
  "type": "Feature",
  "properties": {
    "addr:full":"Wandellaan 26 Wielsbeke West-Vlaanderen 8710",
    "addr:housenumber":"26",
    "addr:postcode":"8710",
    "addr:street":"Wandellaan;West-Vlaanderen",
    "iso:country":"BE",
    "sg:address":"Wandellaan 26",
    "sg:city":"Wielsbeke",
    "sg:orig_category":"Beautyfarms, relaxatie and lichamelijk welzijn Schoonheidssalons",
    "sg:phone":"+32 56 66 79 44",
    "sg:postcode":"8710",
    "sg:province":"West-Vlaanderen",
    "wof:name":"Marijke Cafmeyer",
    "wof:placetype":"venue"
},
  "geometry": {"coordinates":[3.3783619404,50.9108924866],"type":"Point"}
}