{
  "type": "Feature",
  "properties": {
    "addr:full":"Ieperstraat 15 Lo-reninge (reninge) West-Vlaanderen 8647",
    "addr:housenumber":"15",
    "addr:postcode":"8647",
    "addr:street":"Ieperstraat",
    "iso:country":"BE",
    "sg:address":"Ieperstraat 15",
    "sg:city":"Lo-reninge (reninge)",
    "sg:classifiers":[
        {
            "category":"Bakery",
            "type":"Food & Drink"
        }
    ],
    "sg:phone":"+32 57 40 02 13",
    "sg:postcode":"8647",
    "sg:province":"West-Vlaanderen",
    "sg:tags":[
        "confectioner",
        "baker"
    ],
    "wof:name":"Lemahieu H",
    "wof:placetype":"venue"
},
  "geometry": {"coordinates":[2.7901170254,50.9449272156],"type":"Point"}
}