{
  "type": "Feature",
  "properties": {
    "addr:full":"Terveldestraat 3 Kortessem Limburg 3720",
    "addr:housenumber":"3",
    "addr:postcode":"3720",
    "addr:street":"Terveldestraat",
    "iso:country":"BE",
    "sg:address":"Terveldestraat 3",
    "sg:city":"Kortessem",
    "sg:orig_category":"Advocaten and juridische adviseurs",
    "sg:phone":"+32 11 37 15 11",
    "sg:postcode":"3720",
    "sg:province":"Limburg",
    "wof:name":"Erwin Govarts",
    "wof:placetype":"venue"
},
  "geometry": {"coordinates":[5.3826007843,50.864315033],"type":"Point"}
}