{
  "type": "Feature",
  "properties": {
    "addr:full":"Heibrikstraat 50 Hoeselt Limburg 3730",
    "addr:housenumber":"50",
    "addr:postcode":"3730",
    "addr:street":"Heibrikstraat",
    "iso:country":"BE",
    "sg:address":"Heibrikstraat 50",
    "sg:city":"Hoeselt",
    "sg:classifiers":[
        {
            "category":"Communications",
            "subcategory":"Film & Video Production",
            "type":"Services"
        }
    ],
    "sg:phone":"+32 89 51 43 21",
    "sg:postcode":"3730",
    "sg:province":"Limburg",
    "sg:tags":[
        "sound",
        "recording",
        "studio"
    ],
    "wof:name":"Soundhouse",
    "wof:placetype":"venue"
},
  "geometry": {"coordinates":[5.4780569077,50.8548431396],"type":"Point"}
}