{
  "type": "Feature",
  "properties": {
    "iso:country":"BE",
    "sg:address":"Rue Chevaufosse 70",
    "sg:city":"Li\u00c8ge",
    "sg:orig_category":"Instellingen voor probleemkinderen Kindertehuizen",
    "sg:phone":"+32 4 223 72 56",
    "sg:postcode":"4000",
    "sg:province":"Li\u00e8ge",
    "wof:name":"Institut Michotte",
    "wof:placetype":"venue"
},
  "geometry": {"coordinates":[5.5567917824,50.638671875],"type":"Point"}
}