{
  "type": "Feature",
  "properties": {
    "iso:country":"BE",
    "sg:address":"Pastorijstraat 2",
    "sg:city":"Boortmeerbeek",
    "sg:orig_category":"Overheidsdiensten Werk and personeelsselectie",
    "sg:phone":"+32 15 51 82 04",
    "sg:postcode":"3190",
    "sg:province":"Vlaams-Brabant",
    "wof:name":"Pwa Boortmeerbeek",
    "wof:placetype":"venue"
},
  "geometry": {"coordinates":[4.572054863,50.9818534851],"type":"Point"}
}