{
  "type": "Feature",
  "properties": {
    "addr:full":"Rue Auguste Blariaux 11a Erquelinnes (solre-sur-sambre) Hainaut 6560",
    "addr:housenumber":"11a",
    "addr:postcode":"6560",
    "addr:street":"Rue Auguste Blariaux",
    "iso:country":"BE",
    "sg:address":"Rue Auguste Blariaux 11a",
    "sg:city":"Erquelinnes (solre-sur-sambre)",
    "sg:classifiers":[
        {
            "category":"Building & Trades",
            "subcategory":"Plumbing",
            "type":"Services"
        }
    ],
    "sg:phone":"+32 71 55 68 49",
    "sg:postcode":"6560",
    "sg:province":"Hainaut",
    "sg:tags":[
        "contractor"
    ],
    "wof:name":"Pr\u00e9vost R Sprl",
    "wof:placetype":"venue"
},
  "geometry": {"coordinates":[4.1522808075,50.3098335266],"type":"Point"}
}