{
  "type": "Feature",
  "properties": {
    "iso:country":"BE",
    "sg:address":"Ommegangstraat 73",
    "sg:city":"Zele",
    "sg:classifiers":[
        {
            "category":"Wholesale",
            "subcategory":"Medical Equipment & Supplies",
            "type":"Manufacturing & Wholesale Goods"
        }
    ],
    "sg:phone":"+32 52 45 29 63",
    "sg:postcode":"9240",
    "sg:province":"Oost-Vlaanderen",
    "sg:tags":[
        "lubricating"
    ],
    "wof:name":"Smeertechniek Van Damme Bvba",
    "wof:placetype":"venue"
},
  "geometry": {"coordinates":[4.0420517921,51.0630149841],"type":"Point"}
}