{
  "type": "Feature",
  "properties": {
    "addr:full":"Herkenrodesingel 10 Hasselt Limburg 3500",
    "addr:housenumber":"10",
    "addr:postcode":"3500",
    "addr:street":"Herkenrodesingel",
    "iso:country":"BE",
    "sg:address":"Herkenrodesingel 10",
    "sg:city":"Hasselt",
    "sg:orig_category":"Newspapers, magazines, periodicals - Publishers",
    "sg:phone":"+32 11 87 81 11",
    "sg:postcode":"3500",
    "sg:province":"Limburg",
    "wof:name":"Regionale Uitgeversgroep",
    "wof:placetype":"venue"
},
  "geometry": {"coordinates":[5.3260068893,50.9430122375],"type":"Point"}
}