{
  "type": "Feature",
  "properties": {
    "addr:full":"1170 Watermael-boitsfort (bruxelles) Bruxelles-Capitale 1170",
    "addr:housenumber":"1170",
    "addr:postcode":"1170",
    "addr:street":"Watermael-Boitsfort",
    "iso:country":"BE",
    "sg:address":"1170",
    "sg:city":"Watermael-boitsfort (bruxelles)",
    "sg:orig_category":"Pharmaciens",
    "sg:phone":"+32 900 10 500",
    "sg:postcode":"1170",
    "sg:province":"Bruxelles-Capitale",
    "wof:name":"Pharmacies De Garde",
    "wof:placetype":"venue"
},
  "geometry": {"coordinates":[4.4041399956,50.8091392517],"type":"Point"}
}