{
  "type": "Feature",
  "properties": {
    "addr:full":"Steenweg Op Blaasveld 72 Mechelen (heffen) Antwerpen 2801",
    "addr:housenumber":"72",
    "addr:postcode":"2801",
    "addr:street":"Steenweg Op Blaasveld",
    "iso:country":"BE",
    "sg:address":"Steenweg Op Blaasveld 72",
    "sg:city":"Mechelen (heffen)",
    "sg:classifiers":[
        {
            "category":"Utilities",
            "subcategory":"Water",
            "type":"Services"
        }
    ],
    "sg:phone":"+32 3 860 77 77",
    "sg:postcode":"2801",
    "sg:province":"Antwerpen",
    "sg:tags":[
        "softener"
    ],
    "wof:name":"Aqua-claro Nv",
    "wof:placetype":"venue"
},
  "geometry": {"coordinates":[4.4079771042,51.0472412109],"type":"Point"}
}