{
  "type": "Feature",
  "properties": {
    "iso:country":"BE",
    "sg:address":"Weg Nr. Ellikom 159",
    "sg:city":"Meeuwen",
    "sg:classifiers":[
        {
            "category":"Real Estate",
            "subcategory":"Surveying",
            "type":"Services"
        }
    ],
    "sg:phone":"+32 11 63 40 26",
    "sg:postcode":"3670",
    "sg:province":"Limburg",
    "sg:tags":[
        "lettering",
        "letter"
    ],
    "wof:name":"Boonen Jan Publi",
    "wof:placetype":"venue"
},
  "geometry": {"coordinates":[5.5210309029,51.1165313721],"type":"Point"}
}