{
  "type": "Feature",
  "properties": {
    "iso:country":"BE",
    "sg:address":"Rue Du Sart 28",
    "sg:city":"Ans (alleur)",
    "sg:orig_category":"Ergotherapists",
    "sg:phone":"+32 4 263 56 90",
    "sg:postcode":"4432",
    "sg:province":"Li\u00e8ge",
    "wof:name":"Baccus M",
    "wof:placetype":"venue"
},
  "geometry": {"coordinates":[5.5100369453,50.6676292419],"type":"Point"}
}