{
  "type": "Feature",
  "properties": {
    "addr:full":"Rue Potaarde 76b1 Sint-agatha-berchem/berchem-sainte-agathe Bruxelles-Capitale 1082",
    "addr:housenumber":"76b1",
    "addr:postcode":"1082",
    "addr:street":"Rue Potaarde;/",
    "iso:country":"BE",
    "sg:address":"Rue Potaarde 76b1",
    "sg:city":"Sint-agatha-berchem/berchem-sainte-agathe",
    "sg:orig_category":"Administration d'immeubles. G\u00e9om\u00e8tres",
    "sg:phone":"+32 2 460 11 35",
    "sg:postcode":"1082",
    "sg:province":"Bruxelles-Capitale",
    "wof:name":"A4i",
    "wof:placetype":"venue"
},
  "geometry": {"coordinates":[4.2824158669,50.8648605347],"type":"Point"}
}