{
  "type": "Feature",
  "properties": {
    "addr:full":"Kasteelstraat 27 Dilbeek Vlaams-Brabant 1700",
    "addr:housenumber":"27",
    "addr:postcode":"1700",
    "addr:street":"Kasteelstraat",
    "iso:country":"BE",
    "sg:address":"Kasteelstraat 27",
    "sg:city":"Dilbeek",
    "sg:classifiers":[
        {
            "category":"Home & Garden",
            "subcategory":"Home Furnishings",
            "type":"Retail Goods"
        }
    ],
    "sg:phone":"+32 2 460 86 55",
    "sg:postcode":"1700",
    "sg:province":"Vlaams-Brabant",
    "sg:tags":[
        "interior",
        "decoration"
    ],
    "wof:name":"Interno Idee",
    "wof:placetype":"venue"
},
  "geometry": {"coordinates":[4.2633218765,50.845615387],"type":"Point"}
}