{
  "type": "Feature",
  "properties": {
    "iso:country":"BE",
    "sg:address":"Bilksken 34",
    "sg:city":"Lovendegem",
    "sg:classifiers":[
        {
            "category":"Professional",
            "subcategory":"Printing & Photocopies",
            "type":"Services"
        }
    ],
    "sg:phone":"+32 9 344 51 25",
    "sg:postcode":"9920",
    "sg:province":"Oost-Vlaanderen",
    "sg:tags":[
        "-",
        "offset"
    ],
    "wof:name":"Vermeulen Printing Bvba",
    "wof:placetype":"venue"
},
  "geometry": {"coordinates":[3.6374700069,51.0945091248],"type":"Point"}
}