{
  "type": "Feature",
  "properties": {
    "addr:full":"Rue Des Tombes 30 Box 5 Wanze (antheit) Li\u00e8ge 4520",
    "addr:housenumber":"30;5",
    "addr:postcode":"4520",
    "addr:street":"Rue Des Tombes;Box",
    "iso:country":"BE",
    "sg:address":"Rue Des Tombes 30 Box 5",
    "sg:city":"Wanze (antheit)",
    "sg:classifiers":[
        {
            "category":"Social Services",
            "subcategory":"Job Training",
            "type":"Services"
        }
    ],
    "sg:phone":"+32 496 25 19 26",
    "sg:postcode":"4520",
    "sg:province":"Li\u00e8ge",
    "sg:tags":[
        "personnel"
    ],
    "wof:name":"Trait D'union Asbl",
    "wof:placetype":"venue"
},
  "geometry": {"coordinates":[5.2279500961,50.5519790649],"type":"Point"}
}