{
  "type": "Feature",
  "properties": {
    "addr:full":"Chemin Du Four 40 Namur (malonne) Namur 5020",
    "addr:housenumber":"40",
    "addr:postcode":"5020",
    "addr:street":"Chemin Du Four",
    "iso:country":"BE",
    "sg:address":"Chemin Du Four 40",
    "sg:city":"Namur (malonne)",
    "sg:classifiers":[
        {
            "category":"Airport",
            "subcategory":"International",
            "type":"Transportation"
        }
    ],
    "sg:phone":"+32 81 44 02 73",
    "sg:postcode":"5020",
    "sg:province":"Namur",
    "sg:tags":[
        "-",
        "transport"
    ],
    "wof:name":"Pajena",
    "wof:placetype":"venue"
},
  "geometry": {"coordinates":[4.7952418327,50.4352035522],"type":"Point"}
}