{
  "type": "Feature",
  "properties": {
    "addr:full":"Rue De La Fontaine 3 Saint-hubert Luxembourg 6870",
    "addr:housenumber":"3",
    "addr:postcode":"6870",
    "addr:street":"Rue De La Fontaine",
    "iso:country":"BE",
    "sg:address":"Rue De La Fontaine 3",
    "sg:city":"Saint-hubert",
    "sg:classifiers":[
        {
            "category":"Bakery",
            "type":"Food & Drink"
        }
    ],
    "sg:phone":"+32 61 61 14 66",
    "sg:postcode":"6870",
    "sg:province":"Luxembourg",
    "sg:tags":[
        "confectioner",
        "baker"
    ],
    "wof:name":"Evrard C",
    "wof:placetype":"venue"
},
  "geometry": {"coordinates":[5.3730587959,50.0261268616],"type":"Point"}
}