{
  "type": "Feature",
  "properties": {
    "iso:country":"BE",
    "sg:address":"Ieperstraat 11",
    "sg:city":"Poperinge",
    "sg:orig_category":"Chaussures",
    "sg:phone":"+32 57 33 33 72",
    "sg:postcode":"8970",
    "sg:province":"West-Vlaanderen",
    "wof:name":"Sidon's",
    "wof:placetype":"venue"
},
  "geometry": {"coordinates":[2.7275350094,50.8547363281],"type":"Point"}
}