{
  "type": "Feature",
  "properties": {
    "iso:country":"BE",
    "sg:address":"Torhoutsesteenweg 338",
    "sg:city":"Oostende",
    "sg:orig_category":"Boucheries",
    "sg:phone":"+32 59 70 16 18",
    "sg:postcode":"8400",
    "sg:province":"West-Vlaanderen",
    "wof:name":"Wilfried Dhondt",
    "wof:placetype":"venue"
},
  "geometry": {"coordinates":[2.9064500332,51.2150154114],"type":"Point"}
}