{
  "type": "Feature",
  "properties": {
    "iso:country":"BE",
    "sg:address":"Minister Liebaertlaan 31",
    "sg:city":"Kortrijk",
    "sg:orig_category":"Landmeters Landmeters and schatters",
    "sg:phone":"+32 56 20 38 78",
    "sg:postcode":"8500",
    "sg:province":"West-Vlaanderen",
    "wof:name":"Luc Callens",
    "wof:placetype":"venue"
},
  "geometry": {"coordinates":[3.2729010582,50.8324623108],"type":"Point"}
}