{
  "type": "Feature",
  "properties": {
    "iso:country":"BE",
    "sg:address":"Krombekestraat 89a",
    "sg:city":"Alveringem (stavele)",
    "sg:classifiers":[
        {
            "category":"Retail",
            "subcategory":"Veterinary Services",
            "type":"Services"
        }
    ],
    "sg:phone":"+32 57 30 02 40",
    "sg:postcode":"8691",
    "sg:province":"West-Vlaanderen",
    "sg:tags":[
        "veterinarian"
    ],
    "wof:name":"Debruyne J",
    "wof:placetype":"venue"
},
  "geometry": {"coordinates":[2.6714770794,50.9355659485],"type":"Point"}
}