{
  "type": "Feature",
  "properties": {
    "iso:country":"BE",
    "sg:address":"Ganzenstraat 34",
    "sg:city":"Brugge",
    "sg:classifiers":[
        {
            "category":"Professional",
            "subcategory":"Accounting & Tax Preparation",
            "type":"Services"
        }
    ],
    "sg:phone":"+32 50 33 57 65",
    "sg:postcode":"8000",
    "sg:province":"West-Vlaanderen",
    "sg:tags":[
        "accountant"
    ],
    "wof:name":"Wolters A",
    "wof:placetype":"venue"
},
  "geometry": {"coordinates":[3.2348759174,51.2088127136],"type":"Point"}
}