{
  "type": "Feature",
  "properties": {
    "iso:country":"BE",
    "sg:address":"Roth 45",
    "sg:city":"Aarschot",
    "sg:orig_category":"Groententeelt",
    "sg:phone":"+32 16 50 20 59",
    "sg:postcode":"3202",
    "sg:province":"Vlaams-Brabant",
    "wof:name":"Raymond Tuerlinckx",
    "wof:placetype":"venue"
},
  "geometry": {"coordinates":[4.8867950439,50.9807167053],"type":"Point"}
}