{
  "type": "Feature",
  "properties": {
    "iso:country":"BE",
    "sg:address":"Rue Lambert Crickx 9a",
    "sg:city":"Bruxelles (anderlecht)",
    "sg:orig_category":"Non-Classified Establishments",
    "sg:phone":"+32 2 520 20 34",
    "sg:postcode":"1070",
    "sg:province":"Bruxelles-Capitale",
    "wof:name":"Union Jack",
    "wof:placetype":"venue"
},
  "geometry": {"coordinates":[4.3380041122,50.8409500122],"type":"Point"}
}