{
  "type": "Feature",
  "properties": {
    "addr:full":"Chauss\u00e9e De La Hulpe 181 Bruxelles (watermael-boitsfort) Bruxelles-Capitale 1170",
    "addr:housenumber":"181",
    "addr:postcode":"1170",
    "addr:street":"Chausse\u0301E De La Hulpe",
    "iso:country":"BE",
    "sg:address":"Chauss\u00e9e De La Hulpe 181",
    "sg:city":"Bruxelles (watermael-boitsfort)",
    "sg:classifiers":[
        {
            "category":"Restaurant",
            "type":"Food & Drink"
        }
    ],
    "sg:phone":"+32 2 663 13 30",
    "sg:postcode":"1170",
    "sg:province":"Bruxelles-Capitale",
    "sg:tags":[
        "industrial",
        "kitchen",
        "catering"
    ],
    "wof:name":"Del Monte Brands Ne",
    "wof:placetype":"venue"
},
  "geometry": {"coordinates":[4.4043002129,50.7956581116],"type":"Point"}
}