{
  "type": "Feature",
  "properties": {
    "addr:full":"Steenstraat 43 Ieper West-Vlaanderen 8904",
    "addr:housenumber":"43",
    "addr:postcode":"8904",
    "addr:street":"Steenstraat",
    "iso:country":"BE",
    "sg:address":"Steenstraat 43",
    "sg:city":"Ieper",
    "sg:orig_category":"Eleveurs de bovins",
    "sg:phone":"+32 57 42 21 54",
    "sg:postcode":"8904",
    "sg:province":"West-Vlaanderen",
    "wof:name":"Dirk Decorte",
    "wof:placetype":"venue"
},
  "geometry": {"coordinates":[2.8185141087,50.9054031372],"type":"Point"}
}