{
  "type": "Feature",
  "properties": {
    "iso:country":"BE",
    "sg:address":"Avenue De Scailmont 28",
    "sg:city":"Manage",
    "sg:orig_category":"Artsen and specialisten",
    "sg:phone":"+32 64 54 11 71",
    "sg:postcode":"7170",
    "sg:province":"Hainaut",
    "wof:name":"Fran\u00c7ois Pilette",
    "wof:placetype":"venue"
},
  "geometry": {"coordinates":[4.2369699478,50.5021018982],"type":"Point"}
}