{
  "type": "Feature",
  "properties": {
    "addr:full":"Chauss\u00c9e De Lodelinsart 186 Charleroi Hainaut 6060",
    "addr:housenumber":"186",
    "addr:postcode":"6060",
    "addr:street":"Chausse\u0301E De Lodelinsart;Hainaut",
    "iso:country":"BE",
    "sg:address":"Chauss\u00c9e De Lodelinsart 186",
    "sg:city":"Charleroi",
    "sg:orig_category":"Banken and kredietinstellingen",
    "sg:phone":"+32 71 41 90 47",
    "sg:postcode":"6060",
    "sg:province":"Hainaut",
    "wof:name":"Fortis",
    "wof:placetype":"venue"
},
  "geometry": {"coordinates":[4.4496979713,50.424079895],"type":"Point"}
}