{
  "type": "Feature",
  "properties": {
    "iso:country":"BE",
    "sg:address":"Hoogstraat 10",
    "sg:city":"Meise",
    "sg:orig_category":"Apotheken",
    "sg:phone":"+32 2 269 12 27",
    "sg:postcode":"1861",
    "sg:province":"Vlaams-Brabant",
    "wof:name":"Hubert Cauwenbergh",
    "wof:placetype":"venue"
},
  "geometry": {"coordinates":[4.3095870018,50.9515342712],"type":"Point"}
}