{
  "type": "Feature",
  "properties": {
    "addr:full":"Rue De L'harmonie 15 Herve Li\u00e8ge 4650",
    "addr:housenumber":"15",
    "addr:postcode":"4650",
    "addr:street":"Rue De L'Harmonie",
    "iso:country":"BE",
    "sg:address":"Rue De L'harmonie 15",
    "sg:city":"Herve",
    "sg:classifiers":[
        {
            "category":"Health Services",
            "subcategory":"Doctor",
            "type":"Services"
        }
    ],
    "sg:phone":"+32 87 66 09 00",
    "sg:postcode":"4650",
    "sg:province":"Li\u00e8ge",
    "sg:tags":[
        "medicinephysicians",
        "surgeon"
    ],
    "wof:name":"Chanteux A",
    "wof:placetype":"venue"
},
  "geometry": {"coordinates":[5.7965011597,50.638885498],"type":"Point"}
}