{
  "type": "Feature",
  "properties": {
    "iso:country":"BE",
    "sg:address":"Holstraat 13",
    "sg:city":"Evergem",
    "sg:orig_category":"Quincailleries",
    "sg:phone":"+32 9 344 67 86",
    "sg:postcode":"9940",
    "sg:province":"Oost-Vlaanderen",
    "wof:name":"W. Buysse",
    "wof:placetype":"venue"
},
  "geometry": {"coordinates":[3.7456300259,51.1808319092],"type":"Point"}
}