{
  "type": "Feature",
  "properties": {
    "iso:country":"BE",
    "sg:address":"Kauter 1",
    "sg:city":"Beernem",
    "sg:orig_category":"MEUBELONTWERP AND -INSTALLATIE",
    "sg:phone":"+32 50 78 01 31",
    "sg:postcode":"8730",
    "sg:province":"West-Vlaanderen",
    "wof:name":"Thysebaert",
    "wof:placetype":"venue"
},
  "geometry": {"coordinates":[3.3783299923,51.1277160645],"type":"Point"}
}