{
  "type": "Feature",
  "properties": {
    "addr:full":"Jan Vanderstraetenstraat 77 Sint-pieters-leeuw Vlaams-Brabant 1600",
    "addr:housenumber":"77",
    "addr:postcode":"1600",
    "addr:street":"Jan Vanderstraetenstraat",
    "iso:country":"BE",
    "sg:address":"Jan Vanderstraetenstraat 77",
    "sg:city":"Sint-pieters-leeuw",
    "sg:orig_category":"M\u00e9decins and sp\u00e9cialistes",
    "sg:phone":"+32 2 331 12 66",
    "sg:postcode":"1600",
    "sg:province":"Vlaams-Brabant",
    "wof:name":"Marie Christine Lacroix",
    "wof:placetype":"venue"
},
  "geometry": {"coordinates":[4.2804808617,50.7945518494],"type":"Point"}
}