{
  "type": "Feature",
  "properties": {
    "iso:country":"BE",
    "sg:address":"Oscar Van Kesbeeckstraat 65",
    "sg:city":"Mechelen",
    "sg:classifiers":[
        {
            "category":"Personal",
            "subcategory":"Barber",
            "type":"Services"
        }
    ],
    "sg:phone":"+32 15 21 29 09",
    "sg:postcode":"2800",
    "sg:province":"Antwerpen",
    "sg:tags":[
        "gentleman",
        "salon",
        "-",
        "hairdressing"
    ],
    "wof:name":"Steffens R",
    "wof:placetype":"venue"
},
  "geometry": {"coordinates":[4.4720630646,51.039691925],"type":"Point"}
}