{
  "type": "Feature",
  "properties": {
    "iso:country":"BE",
    "sg:address":"Mechelsesteenweg 414",
    "sg:city":"Zaventem (nossegem)",
    "sg:classifiers":[
        {
            "category":"Real Estate",
            "subcategory":"Real Estate Operator",
            "type":"Services"
        }
    ],
    "sg:phone":"+32 2 759 59 40",
    "sg:postcode":"1930",
    "sg:province":"Vlaams-Brabant",
    "sg:tags":[
        "sample",
        "brochure",
        "-",
        "distributors"
    ],
    "wof:name":"Belgische Distributiedienst",
    "wof:placetype":"venue"
},
  "geometry": {"coordinates":[4.5092248917,50.8732032776],"type":"Point"}
}