{
  "type": "Feature",
  "properties": {
    "iso:country":"BE",
    "sg:address":"Lindendreef 30",
    "sg:city":"Veurne",
    "sg:classifiers":[
        {
            "category":"Restaurant",
            "type":"Food & Drink"
        }
    ],
    "sg:phone":"+32 58 31 36 00",
    "sg:postcode":"8630",
    "sg:province":"West-Vlaanderen",
    "wof:name":"De Dreve",
    "wof:placetype":"venue"
},
  "geometry": {"coordinates":[2.6631379128,51.0694541931],"type":"Point"}
}