{
  "type": "Feature",
  "properties": {
    "addr:full":"Suikerrui 4 Antwerpen-centrum Antwerpen 2000",
    "addr:housenumber":"4",
    "addr:postcode":"2000",
    "addr:street":"Suikerrui",
    "iso:country":"BE",
    "sg:address":"Suikerrui 4",
    "sg:city":"Antwerpen-centrum",
    "sg:classifiers":[
        {
            "category":"Restaurant",
            "type":"Food & Drink"
        }
    ],
    "sg:phone":"+32 3 233 07 58",
    "sg:postcode":"2000",
    "sg:province":"Antwerpen",
    "wof:name":"Maritime",
    "wof:placetype":"venue"
},
  "geometry": {"coordinates":[4.39727211,51.2211036682],"type":"Point"}
}