{
  "type": "Feature",
  "properties": {
    "addr:full":"Rue Des Bayards 49 Li\u00e8ge 1 Li\u00e8ge 4000",
    "addr:housenumber":"49;1",
    "addr:postcode":"4000",
    "addr:street":"Rue Des Bayards",
    "iso:country":"BE",
    "sg:address":"Rue Des Bayards 49",
    "sg:city":"Li\u00e8ge 1",
    "sg:orig_category":"Accumulators",
    "sg:phone":"+32 4 227 02 95",
    "sg:postcode":"4000",
    "sg:province":"Li\u00e8ge",
    "wof:name":"Auto Service Luigi",
    "wof:placetype":"venue"
},
  "geometry": {"coordinates":[5.6004648209,50.6525001526],"type":"Point"}
}