{
  "type": "Feature",
  "properties": {
    "addr:full":"Kolmenstraat 184 Hasselt Limburg 3512",
    "addr:housenumber":"184",
    "addr:postcode":"3512",
    "addr:street":"Kolmenstraat",
    "iso:country":"BE",
    "sg:address":"Kolmenstraat 184",
    "sg:city":"Hasselt",
    "sg:orig_category":"Entretien and r\u00e9parations de voitures",
    "sg:phone":"+32 11 31 23 67",
    "sg:postcode":"3512",
    "sg:province":"Limburg",
    "wof:name":"Carrosserie Vesters",
    "wof:placetype":"venue"
},
  "geometry": {"coordinates":[5.2270441055,50.9212837219],"type":"Point"}
}