{
  "type": "Feature",
  "properties": {
    "addr:full":"Rue Des Combattant 55 Florennes Namur 5621",
    "addr:housenumber":"55",
    "addr:postcode":"5621",
    "addr:street":"Rue Des Combattant",
    "iso:country":"BE",
    "sg:address":"Rue Des Combattant 55",
    "sg:city":"Florennes",
    "sg:orig_category":"Rev\u00eatements pour sols and murs. Peinture",
    "sg:phone":"+32 71 50 17 14",
    "sg:postcode":"5621",
    "sg:province":"Namur",
    "wof:name":"Hallet D\u00c9cor",
    "wof:placetype":"venue"
},
  "geometry": {"coordinates":[4.5450720787,50.3113822937],"type":"Point"}
}