{
  "type": "Feature",
  "properties": {
    "iso:country":"BE",
    "sg:address":"Maastrichterstraat 17",
    "sg:city":"Tongeren",
    "sg:orig_category":"Mobistar Centres",
    "sg:phone":"+32 12 24 17 11",
    "sg:postcode":"3700",
    "sg:province":"Limburg",
    "wof:name":"Mobistar Center Allcom Service",
    "wof:placetype":"venue"
},
  "geometry": {"coordinates":[5.4646968842,50.7815704346],"type":"Point"}
}