{
  "type": "Feature",
  "properties": {
    "addr:full":"Rue Des Criquets 1 Rochefort (wavreille) Namur 5580",
    "addr:housenumber":"1",
    "addr:postcode":"5580",
    "addr:street":"Rue Des Criquets",
    "iso:country":"BE",
    "sg:address":"Rue Des Criquets 1",
    "sg:city":"Rochefort (wavreille)",
    "sg:classifiers":[
        {
            "category":"Bars & Pubs",
            "type":"Food & Drink"
        }
    ],
    "sg:phone":"+32 84 21 37 01",
    "sg:postcode":"5580",
    "sg:province":"Namur",
    "sg:tags":[
        "tavern"
    ],
    "wof:name":"Ocean Blue (l') Sc",
    "wof:placetype":"venue"
},
  "geometry": {"coordinates":[5.2572212219,50.1187057495],"type":"Point"}
}