{
  "type": "Feature",
  "properties": {
    "iso:country":"BE",
    "sg:address":"Chemin Saint-landry 35",
    "sg:city":"Soignies",
    "sg:classifiers":[
        {
            "category":"Professional",
            "subcategory":"Testing Lab",
            "type":"Services"
        }
    ],
    "sg:phone":"+32 67 33 32 87",
    "sg:postcode":"7060",
    "sg:province":"Hainaut",
    "sg:tags":[
        "laboratory",
        "-"
    ],
    "wof:name":"Agri-qualit\u00e9",
    "wof:placetype":"venue"
},
  "geometry": {"coordinates":[4.0787568092,50.5851211548],"type":"Point"}
}