{
  "type": "Feature",
  "properties": {
    "iso:country":"BE",
    "sg:address":"Bredabaan 222bb",
    "sg:city":"Wuustwezel",
    "sg:classifiers":[
        {
            "category":"Fast Food",
            "type":"Food & Drink"
        }
    ],
    "sg:phone":"+32 3 669 95 67",
    "sg:postcode":"2990",
    "sg:province":"Antwerpen",
    "sg:tags":[
        "\u00c0",
        "emporter",
        "restaurants"
    ],
    "wof:name":"China Garden",
    "wof:placetype":"venue"
},
  "geometry": {"coordinates":[4.6038799286,51.4000701904],"type":"Point"}
}