{
  "type": "Feature",
  "properties": {
    "addr:full":"Rue Des Eperonniers 33 Bruxelles Bruxelles-Capitale 1000",
    "addr:housenumber":"33",
    "addr:postcode":"1000",
    "addr:street":"Rue Des Eperonniers",
    "iso:country":"BE",
    "sg:address":"Rue Des Eperonniers 33",
    "sg:city":"Bruxelles",
    "sg:classifiers":[
        {
            "category":"Shopping",
            "subcategory":"Clothing, Apparel, & Fashions",
            "type":"Retail Goods"
        }
    ],
    "sg:phone":"+32 2 512 62 76",
    "sg:postcode":"1000",
    "sg:province":"Bruxelles-Capitale",
    "sg:tags":[
        "boutique"
    ],
    "wof:name":"Try-me",
    "wof:placetype":"venue"
},
  "geometry": {"coordinates":[4.3536300659,50.8456535339],"type":"Point"}
}