{
  "type": "Feature",
  "properties": {
    "iso:country":"BE",
    "sg:address":"Kardinaal Cardijnplein 8",
    "sg:city":"Bornem",
    "sg:orig_category":"Non-Classified Establishments",
    "sg:phone":"+32 3 899 13 01",
    "sg:postcode":"2880",
    "sg:province":"Antwerpen",
    "wof:name":"Sigma-aldrich Nv",
    "wof:placetype":"venue"
},
  "geometry": {"coordinates":[4.2348828316,51.0993728638],"type":"Point"}
}