{
  "type": "Feature",
  "properties": {
    "addr:full":"Montenakenweg 127 Sint-truiden Limburg 3800",
    "addr:housenumber":"127",
    "addr:postcode":"3800",
    "addr:street":"Montenakenweg",
    "iso:country":"BE",
    "sg:address":"Montenakenweg 127",
    "sg:city":"Sint-truiden",
    "sg:classifiers":[
        {
            "category":"Cafe",
            "type":"Food & Drink"
        }
    ],
    "sg:phone":"+32 11 67 25 75",
    "sg:postcode":"3800",
    "sg:province":"Limburg",
    "sg:tags":[
        "caf\u00e9s"
    ],
    "wof:name":"Lidia Geysenberghs",
    "wof:placetype":"venue"
},
  "geometry": {"coordinates":[5.1759119034,50.8073616028],"type":"Point"}
}