{
  "type": "Feature",
  "properties": {
    "addr:full":"Bd Du Gal Wahis 16e Bruxelles Bruxelles-Capitale 1030",
    "addr:housenumber":"16e",
    "addr:postcode":"1030",
    "addr:street":"Bd Du Gal Wahis",
    "iso:country":"BE",
    "sg:address":"Bd Du Gal Wahis 16e",
    "sg:city":"Bruxelles",
    "sg:classifiers":[
        {
            "category":"Shopping",
            "subcategory":"Hobbies, Toys, & Games",
            "type":"Retail Goods"
        }
    ],
    "sg:phone":"+32 2 705 43 53",
    "sg:postcode":"1030",
    "sg:province":"Bruxelles-Capitale",
    "sg:tags":[
        "household",
        "wood",
        "furniture",
        "entertainment"
    ],
    "wof:name":"Leisure & Business Events Equipments Sa",
    "wof:placetype":"venue"
},
  "geometry": {"coordinates":[4.394411087,50.8601799011],"type":"Point"}
}