{
  "type": "Feature",
  "properties": {
    "iso:country":"BE",
    "sg:address":"Rue Du Crucifix 41",
    "sg:city":"Herstal",
    "sg:orig_category":"Epiceries. Boucheries",
    "sg:phone":"+32 4 264 77 42",
    "sg:postcode":"4040",
    "sg:province":"Li\u00e8ge",
    "wof:name":"La Communaut\u00c9",
    "wof:placetype":"venue"
},
  "geometry": {"coordinates":[5.6395001411,50.6750717163],"type":"Point"}
}