{
  "type": "Feature",
  "properties": {
    "addr:full":"Rue Achille Masset 13 Awans Li\u00e8ge 4340",
    "addr:housenumber":"13",
    "addr:postcode":"4340",
    "addr:street":"Rue Achille Masset",
    "iso:country":"BE",
    "sg:address":"Rue Achille Masset 13",
    "sg:city":"Awans",
    "sg:orig_category":"Forge, Moulage and Profilage des M\u00e9taux",
    "sg:phone":"+32 4 250 52 65",
    "sg:postcode":"4340",
    "sg:province":"Li\u00e8ge",
    "wof:name":"Radoux Philippe",
    "wof:placetype":"venue"
},
  "geometry": {"coordinates":[5.4346489906,50.6756477356],"type":"Point"}
}