{
  "type": "Feature",
  "properties": {
    "addr:full":"Bassevillestraat 81 Middelkerke West-Vlaanderen 8434",
    "addr:housenumber":"81",
    "addr:postcode":"8434",
    "addr:street":"Bassevillestraat",
    "iso:country":"BE",
    "sg:address":"Bassevillestraat 81",
    "sg:city":"Middelkerke",
    "sg:classifiers":[
        {
            "category":"Restaurant",
            "type":"Food & Drink"
        }
    ],
    "sg:phone":"+32 58 23 73 44",
    "sg:postcode":"8434",
    "sg:province":"West-Vlaanderen",
    "wof:name":"De Automobiel",
    "wof:placetype":"venue"
},
  "geometry": {"coordinates":[2.7568869591,51.1495056152],"type":"Point"}
}