{
  "type": "Feature",
  "properties": {
    "iso:country":"BE",
    "sg:address":"Groenplaats 16",
    "sg:city":"Antwerpen",
    "sg:orig_category":"Decoratieve kunst and kunstbenodigdheden Verlichting and huishoudartikelen",
    "sg:phone":"+32 3 232 29 08",
    "sg:postcode":"2000",
    "sg:province":"Antwerpen",
    "wof:name":"Marc Van Der Wee",
    "wof:placetype":"venue"
},
  "geometry": {"coordinates":[4.401154995,51.2198143005],"type":"Point"}
}