{
  "type": "Feature",
  "properties": {
    "addr:full":"Rue Puits Connette 4 Assesse Namur 5330",
    "addr:housenumber":"4",
    "addr:postcode":"5330",
    "addr:street":"Rue Puits Connette",
    "iso:country":"BE",
    "sg:address":"Rue Puits Connette 4",
    "sg:city":"Assesse",
    "sg:orig_category":"Jardinage",
    "sg:phone":"+32 83 66 01 96",
    "sg:postcode":"5330",
    "sg:province":"Namur",
    "wof:name":"Christophe Thibaut",
    "wof:placetype":"venue"
},
  "geometry": {"coordinates":[4.969892025,50.3771018982],"type":"Point"}
}