{
  "type": "Feature",
  "properties": {
    "iso:country":"BE",
    "sg:address":"Bloemluststraat 19",
    "sg:city":"Wetteren",
    "sg:classifiers":[
        {
            "category":"Shopping",
            "subcategory":"Clothing, Apparel, & Fashions",
            "type":"Retail Goods"
        }
    ],
    "sg:phone":"+32 9 369 01 89",
    "sg:postcode":"9230",
    "sg:province":"Oost-Vlaanderen",
    "sg:tags":[
        "ondergoed",
        "lingerie"
    ],
    "wof:name":"Huis Schepens-braeckman",
    "wof:placetype":"venue"
},
  "geometry": {"coordinates":[3.8742530346,50.9983215332],"type":"Point"}
}