{
  "type": "Feature",
  "properties": {
    "iso:country":"BE",
    "sg:address":"Egenhovenstraat 100",
    "sg:city":"Bertem",
    "sg:orig_category":"Dierenartsen",
    "sg:phone":"+32 16 48 95 77",
    "sg:postcode":"3060",
    "sg:province":"Vlaams-Brabant",
    "wof:name":"Edgard Putseys",
    "wof:placetype":"venue"
},
  "geometry": {"coordinates":[4.6412777901,50.8623695374],"type":"Point"}
}