{
  "type": "Feature",
  "properties": {
    "iso:country":"BE",
    "sg:address":"Rue Des Archers 95",
    "sg:city":"Binche",
    "sg:classifiers":[
        {
            "category":"Health Services",
            "subcategory":"Nursing And Care Facility",
            "type":"Services"
        }
    ],
    "sg:phone":"+32 64 33 63 20",
    "sg:postcode":"7130",
    "sg:province":"Hainaut",
    "sg:tags":[
        "home"
    ],
    "wof:name":"Cornart Y",
    "wof:placetype":"venue"
},
  "geometry": {"coordinates":[4.1641068459,50.4143371582],"type":"Point"}
}