{
  "type": "Feature",
  "properties": {
    "addr:full":"Chemin Du Prince 247 Jurbeke Hainaut 7050",
    "addr:housenumber":"247",
    "addr:postcode":"7050",
    "addr:street":"Chemin Du Prince;Hainaut",
    "iso:country":"BE",
    "sg:address":"Chemin Du Prince 247",
    "sg:city":"Jurbeke",
    "sg:orig_category":"Jardinage",
    "sg:phone":"+32 65 22 72 94",
    "sg:postcode":"7050",
    "sg:province":"Hainaut",
    "wof:name":"Berdal Ch",
    "wof:placetype":"venue"
},
  "geometry": {"coordinates":[3.9394049644,50.5095787048],"type":"Point"}
}