{
  "type": "Feature",
  "properties": {
    "iso:country":"BE",
    "sg:address":"Av Des N\u00e9nuphars 19 Bp 15",
    "sg:city":"Bruxelles",
    "sg:classifiers":[
        {
            "category":"Utilities",
            "subcategory":"Electric",
            "type":"Services"
        }
    ],
    "sg:phone":"+32 2 673 27 30",
    "sg:postcode":"1160",
    "sg:province":"Bruxelles-Capitale",
    "sg:tags":[
        "electricity",
        "electronic",
        "electrical",
        "equipment"
    ],
    "wof:name":"Drb Batterie",
    "wof:placetype":"venue"
},
  "geometry": {"coordinates":[4.4304947853,50.8215141296],"type":"Point"}
}