{
  "type": "Feature",
  "properties": {
    "addr:full":"Rue De L'eglise 15 Gerpinnes (villers-poterie) Hainaut 6280",
    "addr:housenumber":"15",
    "addr:postcode":"6280",
    "addr:street":"Rue De L'Eglise",
    "iso:country":"BE",
    "sg:address":"Rue De L'eglise 15",
    "sg:city":"Gerpinnes (villers-poterie)",
    "sg:classifiers":[
        {
            "category":"Home & Garden",
            "subcategory":"Carpets & Floor Coverings",
            "type":"Retail Goods"
        }
    ],
    "sg:phone":"+32 71 50 54 91",
    "sg:postcode":"6280",
    "sg:province":"Hainaut",
    "sg:tags":[
        "-"
    ],
    "wof:name":"Vanespen R",
    "wof:placetype":"venue"
},
  "geometry": {"coordinates":[4.5474648476,50.3508415222],"type":"Point"}
}