{
  "type": "Feature",
  "properties": {
    "iso:country":"BE",
    "sg:address":"Heerdreef 1",
    "sg:city":"Kaprijke (lembeke)",
    "sg:classifiers":[
        {
            "category":"Health Services",
            "subcategory":"Doctor",
            "type":"Services"
        }
    ],
    "sg:phone":"+32 9 377 45 79",
    "sg:postcode":"9971",
    "sg:province":"Oost-Vlaanderen",
    "sg:tags":[
        "medicinephysicians",
        "surgeon"
    ],
    "wof:name":"Ingelaere H",
    "wof:placetype":"venue"
},
  "geometry": {"coordinates":[3.6258630753,51.1787796021],"type":"Point"}
}