{
  "type": "Feature",
  "properties": {
    "addr:full":"Rue Des Tanneurs 36 Estaimpuis Hainaut 7730",
    "addr:housenumber":"36",
    "addr:postcode":"7730",
    "addr:street":"Rue Des Tanneurs;Hainaut",
    "iso:country":"BE",
    "sg:address":"Rue Des Tanneurs 36",
    "sg:city":"Estaimpuis",
    "sg:orig_category":"Artsen and specialisten",
    "sg:phone":"+32 69 55 62 01",
    "sg:postcode":"7730",
    "sg:province":"Hainaut",
    "wof:name":"Ghislain Dubar",
    "wof:placetype":"venue"
},
  "geometry": {"coordinates":[3.3102250099,50.6771278381],"type":"Point"}
}