{
  "type": "Feature",
  "properties": {
    "iso:country":"BE",
    "sg:address":"Heidestraat 18",
    "sg:city":"Overpelt",
    "sg:orig_category":"Rundveehouders",
    "sg:phone":"+32 11 64 35 79",
    "sg:postcode":"3900",
    "sg:province":"Limburg",
    "wof:name":"Joannes Dilissen",
    "wof:placetype":"venue"
},
  "geometry": {"coordinates":[5.4053459167,51.2063980103],"type":"Point"}
}