{
  "type": "Feature",
  "properties": {
    "iso:country":"BE",
    "sg:address":"Hundelgemsesteenweg 143",
    "sg:city":"Merelbeke",
    "sg:orig_category":"Brood, gebak and snoepgoed",
    "sg:phone":"+32 9 230 30 18",
    "sg:postcode":"9820",
    "sg:province":"Oost-Vlaanderen",
    "wof:name":"Patisserie Herman",
    "wof:placetype":"venue"
},
  "geometry": {"coordinates":[3.7520110607,51.0033226013],"type":"Point"}
}