{
  "type": "Feature",
  "properties": {
    "addr:full":"Opperstraat 118 Liedekerke Vlaams-Brabant 1770",
    "addr:housenumber":"118",
    "addr:postcode":"1770",
    "addr:street":"Opperstraat;Vlaams-Brabant",
    "iso:country":"BE",
    "sg:address":"Opperstraat 118",
    "sg:city":"Liedekerke",
    "sg:orig_category":"Lampes and appareils \u00e9lectriques Fab. Travaux d\u00b4installation divers",
    "sg:phone":"+32 53 66 68 71",
    "sg:postcode":"1770",
    "sg:province":"Vlaams-Brabant",
    "wof:name":"Fa. Deneve Security",
    "wof:placetype":"venue"
},
  "geometry": {"coordinates":[4.0893039703,50.8691482544],"type":"Point"}
}