{
  "type": "Feature",
  "properties": {
    "iso:country":"BE",
    "sg:address":"Klein Molenstraat 14",
    "sg:city":"Vilvoorde",
    "sg:classifiers":[
        {
            "category":"Bars & Pubs",
            "type":"Food & Drink"
        }
    ],
    "sg:phone":"+32 2 253 43 80",
    "sg:postcode":"1800",
    "sg:province":"Vlaams-Brabant",
    "sg:tags":[
        "tavern"
    ],
    "wof:name":"The New Cambrinus",
    "wof:placetype":"venue"
},
  "geometry": {"coordinates":[4.4242811203,50.9275970459],"type":"Point"}
}