{
  "type": "Feature",
  "properties": {
    "addr:full":"27 Rue De Sartiau 6532 Thuin 27",
    "addr:housenumber":"27;27",
    "addr:postcode":"6532",
    "addr:street":"Rue De Sartiau",
    "iso:country":"BE",
    "sg:address":"27",
    "sg:city":"Rue De Sartiau 6532 Thuin",
    "sg:classifiers":[
        {
            "category":"Building & Trades",
            "subcategory":"Construction",
            "type":"Services"
        }
    ],
    "sg:phone":"+32 71 59 00 41",
    "sg:postcode":"27",
    "sg:tags":[
        "work",
        "public"
    ],
    "wof:name":"Travexploit Sa",
    "wof:placetype":"venue"
},
  "geometry": {"coordinates":[4.25629282,50.3186531067],"type":"Point"}
}