{
  "type": "Feature",
  "properties": {
    "addr:full":"Kerkstraat 6a Dilsen-stokkem (elen) Limburg 3650",
    "addr:housenumber":"6a",
    "addr:postcode":"3650",
    "addr:street":"Kerkstraat;Elen Limburg",
    "iso:country":"BE",
    "sg:address":"Kerkstraat 6a",
    "sg:city":"Dilsen-stokkem (elen)",
    "sg:classifiers":[
        {
            "category":"Professional",
            "subcategory":"Accounting & Tax Preparation",
            "type":"Services"
        }
    ],
    "sg:phone":"+32 89 56 75 81",
    "sg:postcode":"3650",
    "sg:province":"Limburg",
    "sg:tags":[
        "accountant"
    ],
    "wof:name":"Detrez L",
    "wof:placetype":"venue"
},
  "geometry": {"coordinates":[5.727396965,51.0364189148],"type":"Point"}
}