{
  "type": "Feature",
  "properties": {
    "iso:country":"BE",
    "sg:address":"Koningin Elisabethlaan 92",
    "sg:city":"Brugge",
    "sg:orig_category":"M\u00e9decins and sp\u00e9cialistes",
    "sg:phone":"+32 50 33 69 70",
    "sg:postcode":"8000",
    "sg:province":"West-Vlaanderen",
    "wof:name":"Centrum Geboorteregeling",
    "wof:placetype":"venue"
},
  "geometry": {"coordinates":[3.2200961113,51.2177772522],"type":"Point"}
}