{
  "type": "Feature",
  "properties": {
    "addr:full":"Rue Saint-bernard 46 Bruxelles (saint-gilles) Bruxelles-Capitale 1060",
    "addr:housenumber":"46",
    "addr:postcode":"1060",
    "addr:street":"Rue Saint-Bernard",
    "iso:country":"BE",
    "sg:address":"Rue Saint-bernard 46",
    "sg:city":"Bruxelles (saint-gilles)",
    "sg:classifiers":[
        {
            "category":"Wholesale",
            "subcategory":"Tobacco Products",
            "type":"Manufacturing & Wholesale Goods"
        }
    ],
    "sg:phone":"+32 2 542 87 50",
    "sg:postcode":"1060",
    "sg:province":"Bruxelles-Capitale",
    "sg:tags":[
        "import",
        "wood",
        "-"
    ],
    "wof:name":"Compagnie Internationale Des Bois Sa",
    "wof:placetype":"venue"
},
  "geometry": {"coordinates":[4.3542571068,50.8286705017],"type":"Point"}
}