{
  "type": "Feature",
  "properties": {
    "iso:country":"BE",
    "sg:address":"Wideuxdreef 3",
    "sg:city":"Hasselt (sint-lambrechts-herk)",
    "sg:classifiers":[
        {
            "category":"Freight",
            "type":"Transportation"
        }
    ],
    "sg:phone":"+32 11 31 21 42",
    "sg:postcode":"3500",
    "sg:province":"Limburg",
    "sg:tags":[
        "-",
        "transport"
    ],
    "wof:name":"Cosemans",
    "wof:placetype":"venue"
},
  "geometry": {"coordinates":[5.2865538597,50.9109458923],"type":"Point"}
}