{
  "type": "Feature",
  "properties": {
    "addr:full":"Meensesteenweg 167 Kortrijk West-Vlaanderen 8501",
    "addr:housenumber":"167",
    "addr:postcode":"8501",
    "addr:street":"Meensesteenweg",
    "iso:country":"BE",
    "sg:address":"Meensesteenweg 167",
    "sg:city":"Kortrijk",
    "sg:orig_category":"V\u00e9hicules automobiles",
    "sg:phone":"+32 56 35 13 41",
    "sg:postcode":"8501",
    "sg:province":"West-Vlaanderen",
    "wof:name":"Carrosserie Vantomme",
    "wof:placetype":"venue"
},
  "geometry": {"coordinates":[3.2420489788,50.8269233704],"type":"Point"}
}