{
  "type": "Feature",
  "properties": {
    "addr:full":"Avenue De La Tendraie 36 Braine-l'alleud Brabant Wallon 1421",
    "addr:housenumber":"36",
    "addr:postcode":"1421",
    "addr:street":"Avenue De La Tendraie",
    "iso:country":"BE",
    "sg:address":"Avenue De La Tendraie 36",
    "sg:city":"Braine-l'alleud",
    "sg:orig_category":"M\u00e9decins and sp\u00e9cialistes",
    "sg:phone":"+32 2 384 20 24",
    "sg:postcode":"1421",
    "sg:province":"Brabant Wallon",
    "wof:name":"M. Thiriar",
    "wof:placetype":"venue"
},
  "geometry": {"coordinates":[-0.7004899979,47.369140625],"type":"Point"}
}