{
  "type": "Feature",
  "properties": {
    "addr:full":"Peerdskerkhof 1 Mol Antwerpen 2400",
    "addr:housenumber":"1",
    "addr:postcode":"2400",
    "addr:street":"Peerdskerkhof",
    "iso:country":"BE",
    "sg:address":"Peerdskerkhof 1",
    "sg:city":"Mol",
    "sg:orig_category":"Boekhouders",
    "sg:phone":"+32 14 31 98 39",
    "sg:postcode":"2400",
    "sg:province":"Antwerpen",
    "wof:name":"Alfons Cosemans",
    "wof:placetype":"venue"
},
  "geometry": {"coordinates":[5.1050391197,51.1826019287],"type":"Point"}
}