{
  "type": "Feature",
  "properties": {
    "addr:full":"Waversebaan 120 Oud-heverlee Vlaams-Brabant 3050",
    "addr:housenumber":"120",
    "addr:postcode":"3050",
    "addr:street":"Waversebaan",
    "iso:country":"BE",
    "sg:address":"Waversebaan 120",
    "sg:city":"Oud-heverlee",
    "sg:classifiers":[
        {
            "category":"Communications",
            "subcategory":"Television Station",
            "type":"Services"
        }
    ],
    "sg:phone":"+32 16 40 51 95",
    "sg:postcode":"3050",
    "sg:province":"Vlaams-Brabant",
    "sg:tags":[
        "report",
        "video"
    ],
    "wof:name":"Ap Producties",
    "wof:placetype":"venue"
},
  "geometry": {"coordinates":[4.6671938896,50.8402099609],"type":"Point"}
}