{
  "type": "Feature",
  "properties": {
    "addr:full":"Rue Gilot 7 Hannut Li\u00e8ge 4280",
    "addr:housenumber":"7",
    "addr:postcode":"4280",
    "addr:street":"Rue Gilot",
    "iso:country":"BE",
    "sg:address":"Rue Gilot 7",
    "sg:city":"Hannut",
    "sg:orig_category":"Epiceries",
    "sg:phone":"+32 19 51 46 17",
    "sg:postcode":"4280",
    "sg:province":"Li\u00e8ge",
    "wof:name":"Chez Maguy",
    "wof:placetype":"venue"
},
  "geometry": {"coordinates":[5.1248040199,50.6555137634],"type":"Point"}
}