{
  "type": "Feature",
  "properties": {
    "iso:country":"BE",
    "sg:address":"Duffelsesteenweg",
    "sg:city":"Kontich",
    "sg:orig_category":"Sportclubs Sportterreinen and installaties behalve sportcentra",
    "sg:phone":"+32 3 457 80 36",
    "sg:postcode":"2550",
    "sg:province":"Antwerpen",
    "wof:name":"Kwb Sint-martinus",
    "wof:placetype":"venue"
},
  "geometry": {"coordinates":[4.4515609741,51.1289710999],"type":"Point"}
}