{
  "type": "Feature",
  "properties": {
    "iso:country":"BE",
    "sg:address":"Testeltsesteenweg 83",
    "sg:city":"Aarschot",
    "sg:orig_category":"Epiceries",
    "sg:phone":"+32 16 56 51 40",
    "sg:postcode":"3201",
    "sg:province":"Vlaams-Brabant",
    "wof:name":"Charline Verhaegen",
    "wof:placetype":"venue"
},
  "geometry": {"coordinates":[4.8794531822,50.9985198975],"type":"Point"}
}