{
  "type": "Feature",
  "properties": {
    "iso:country":"BE",
    "sg:address":"Ch De Marche 548",
    "sg:city":"Namur",
    "sg:classifiers":[
        {
            "category":"Bakery",
            "type":"Food & Drink"
        }
    ],
    "sg:phone":"+32 81 31 20 72",
    "sg:postcode":"5101",
    "sg:province":"Namur",
    "sg:tags":[
        "cake",
        "product",
        "related",
        "bread"
    ],
    "wof:name":"Patisserie Dumont Sa",
    "wof:placetype":"venue"
},
  "geometry": {"coordinates":[4.9033799171,50.4430084229],"type":"Point"}
}