{
  "type": "Feature",
  "properties": {
    "iso:country":"BE",
    "sg:address":"Kerkstraat 88",
    "sg:city":"Affligem",
    "sg:orig_category":"Entretien and r\u00e9parations de voitures",
    "sg:phone":"+32 53 67 22 17",
    "sg:postcode":"1790",
    "sg:province":"Vlaams-Brabant",
    "wof:name":"Willy Beelen",
    "wof:placetype":"venue"
},
  "geometry": {"coordinates":[4.1080870628,50.9081115723],"type":"Point"}
}