{
  "type": "Feature",
  "properties": {
    "iso:country":"BE",
    "sg:address":"Keizerstraat 33",
    "sg:city":"Kortrijk",
    "sg:orig_category":"Artistes ind\u00e9pendants",
    "sg:phone":"+32 56 21 56 95",
    "sg:postcode":"8510",
    "sg:province":"West-Vlaanderen",
    "wof:name":"B. Van Dorpe",
    "wof:placetype":"venue"
},
  "geometry": {"coordinates":[3.238615036,50.7971763611],"type":"Point"}
}