{
  "type": "Feature",
  "properties": {
    "iso:country":"BE",
    "sg:address":"Borggravenvijversstraat 17",
    "sg:city":"Hasselt",
    "sg:orig_category":"Syst\u00e8mes de t\u00e9l\u00e9communications",
    "sg:phone":"+32 11 21 29 73",
    "sg:postcode":"3500",
    "sg:province":"Limburg",
    "wof:name":"Vic Electronics",
    "wof:placetype":"venue"
},
  "geometry": {"coordinates":[5.3658781052,50.9511604309],"type":"Point"}
}