{
  "type": "Feature",
  "properties": {
    "iso:country":"BE",
    "sg:address":"Rue De La Fayencerie 10-12",
    "sg:city":"Quaregnon",
    "sg:classifiers":[
        {
            "category":"Manufacturing",
            "subcategory":"Printing",
            "type":"Manufacturing & Wholesale Goods"
        }
    ],
    "sg:phone":"+32 65 78 30 35",
    "sg:postcode":"7390",
    "sg:province":"Hainaut",
    "sg:tags":[
        "publishing"
    ],
    "wof:name":"Anc Cocu Et Mairesse Sprl",
    "wof:placetype":"venue"
},
  "geometry": {"coordinates":[3.8640799522,50.4308815002],"type":"Point"}
}