{
  "type": "Feature",
  "properties": {
    "addr:full":"Dommelstraat 58 Waasmunster Oost-Vlaanderen 9250",
    "addr:housenumber":"58",
    "addr:postcode":"9250",
    "addr:street":"Dommelstraat",
    "iso:country":"BE",
    "sg:address":"Dommelstraat 58",
    "sg:city":"Waasmunster",
    "sg:orig_category":"Woningbouw",
    "sg:phone":"+32 52 46 08 43",
    "sg:postcode":"9250",
    "sg:province":"Oost-Vlaanderen",
    "wof:name":"Goossens",
    "wof:placetype":"venue"
},
  "geometry": {"coordinates":[4.1092791557,51.1143074036],"type":"Point"}
}