{
  "type": "Feature",
  "properties": {
    "addr:full":"Guido Gezellestraat 66 Zele Oost-Vlaanderen 9240",
    "addr:housenumber":"66",
    "addr:postcode":"9240",
    "addr:street":"Guido Gezellestraat",
    "iso:country":"BE",
    "sg:address":"Guido Gezellestraat 66",
    "sg:city":"Zele",
    "sg:orig_category":"Slagers",
    "sg:phone":"+32 52 44 91 71",
    "sg:postcode":"9240",
    "sg:province":"Oost-Vlaanderen",
    "wof:name":"Robert Roels",
    "wof:placetype":"venue"
},
  "geometry": {"coordinates":[4.0376610756,51.0563201904],"type":"Point"}
}