{
  "type": "Feature",
  "properties": {
    "addr:full":"Rue Ludger Lapoulle 20 Chi\u00e8vres (huissignies) Hainaut 7950",
    "addr:housenumber":"20",
    "addr:postcode":"7950",
    "addr:street":"Rue Ludger Lapoulle",
    "iso:country":"BE",
    "sg:address":"Rue Ludger Lapoulle 20",
    "sg:city":"Chi\u00e8vres (huissignies)",
    "sg:classifiers":[
        {
            "category":"Home & Garden",
            "subcategory":"Kitchen Supply",
            "type":"Retail Goods"
        }
    ],
    "sg:phone":"+32 69 76 64 04",
    "sg:postcode":"7950",
    "sg:province":"Hainaut",
    "sg:tags":[
        "installation"
    ],
    "wof:name":"H S Cuisines Sprl",
    "wof:placetype":"venue"
},
  "geometry": {"coordinates":[3.7454040051,50.5679588318],"type":"Point"}
}