{
  "type": "Feature",
  "properties": {
    "iso:country":"BE",
    "sg:address":"Dudzeelse Steenweg 92",
    "sg:city":"Brugge",
    "sg:orig_category":"Installatie van houten of kunststof schrijnwerk Installatie van metalen schrijnwerk Verlichting and ",
    "sg:phone":"+32 50 34 56 85",
    "sg:postcode":"8000",
    "sg:province":"West-Vlaanderen",
    "wof:name":"Van Belle",
    "wof:placetype":"venue"
},
  "geometry": {"coordinates":[3.2280910015,51.2275810242],"type":"Point"}
}