{
  "type": "Feature",
  "properties": {
    "iso:country":"BE",
    "sg:address":"Hazaarddam 2",
    "sg:city":"Beveren",
    "sg:classifiers":[
        {
            "category":"Cafe",
            "type":"Food & Drink"
        }
    ],
    "sg:phone":"+32 3 775 66 73",
    "sg:postcode":"9120",
    "sg:province":"Oost-Vlaanderen",
    "sg:tags":[
        "caf\u00e9s"
    ],
    "wof:name":"Caf\u00c9 Beveren",
    "wof:placetype":"venue"
},
  "geometry": {"coordinates":[4.2818098068,51.2204322815],"type":"Point"}
}