{
  "type": "Feature",
  "properties": {
    "iso:country":"BE",
    "sg:address":"Rue Haie Mayet 16",
    "sg:city":"Mettet",
    "sg:classifiers":[
        {
            "category":"Food & Beverages",
            "subcategory":"Fruits & Vegetables",
            "type":"Retail Goods"
        }
    ],
    "sg:phone":"+32 71 79 81 50",
    "sg:postcode":"5640",
    "sg:province":"Namur",
    "sg:tags":[
        "groenten"
    ],
    "wof:name":"P.h.s. Primeurs",
    "wof:placetype":"venue"
},
  "geometry": {"coordinates":[4.7053899765,50.3673782349],"type":"Point"}
}