{
  "type": "Feature",
  "properties": {
    "addr:full":"Leopold Ii-laan 14 De Haan West-Vlaanderen 8420",
    "addr:housenumber":"14",
    "addr:postcode":"8420",
    "addr:street":"Leopold Ii-Laan",
    "iso:country":"BE",
    "sg:address":"Leopold Ii-laan 14",
    "sg:city":"De Haan",
    "sg:orig_category":"M\u00e9decins and sp\u00e9cialistes",
    "sg:phone":"+32 50 41 46 07",
    "sg:postcode":"8420",
    "sg:province":"West-Vlaanderen",
    "wof:name":"Roland Tavernier",
    "wof:placetype":"venue"
},
  "geometry": {"coordinates":[3.0771870613,51.2975006104],"type":"Point"}
}