{
  "type": "Feature",
  "properties": {
    "addr:full":"Keerbergsesteenweg 4 Haacht Vlaams-Brabant 3150",
    "addr:housenumber":"4",
    "addr:postcode":"3150",
    "addr:street":"Keerbergsesteenweg",
    "iso:country":"BE",
    "sg:address":"Keerbergsesteenweg 4",
    "sg:city":"Haacht",
    "sg:classifiers":[
        {
            "category":"Personal",
            "subcategory":"Barber",
            "type":"Services"
        }
    ],
    "sg:phone":"+32 16 60 04 61",
    "sg:postcode":"3150",
    "sg:province":"Vlaams-Brabant",
    "sg:tags":[
        "gentleman",
        "salon",
        "-",
        "hairdressing"
    ],
    "wof:name":"Simon",
    "wof:placetype":"venue"
},
  "geometry": {"coordinates":[4.638376236,50.9778213501],"type":"Point"}
}