{
  "type": "Feature",
  "properties": {
    "addr:full":"Meershoven 125 Bilzen Limburg 3740",
    "addr:housenumber":"125",
    "addr:postcode":"3740",
    "addr:street":"Meershoven",
    "iso:country":"BE",
    "sg:address":"Meershoven 125",
    "sg:city":"Bilzen",
    "sg:orig_category":"Woningbouw",
    "sg:phone":"+32 89 41 48 66",
    "sg:postcode":"3740",
    "sg:province":"Limburg",
    "wof:name":"Lindelauf J. & H.",
    "wof:placetype":"venue"
},
  "geometry": {"coordinates":[5.5277061462,50.8789215088],"type":"Point"}
}