{
  "type": "Feature",
  "properties": {
    "addr:full":"Ringlaan-zuid 97 De Haan West-Vlaanderen 8420",
    "addr:housenumber":"97",
    "addr:postcode":"8420",
    "addr:street":"Ringlaan-Zuid",
    "iso:country":"BE",
    "sg:address":"Ringlaan-zuid 97",
    "sg:city":"De Haan",
    "sg:orig_category":"Catering and organisation de f\u00eates",
    "sg:phone":"+32 59 23 52 56",
    "sg:postcode":"8420",
    "sg:province":"West-Vlaanderen",
    "wof:name":"Traiteur Don Pedro",
    "wof:placetype":"venue"
},
  "geometry": {"coordinates":[3.0184841156,51.2643852234],"type":"Point"}
}