{
  "type": "Feature",
  "properties": {
    "addr:full":"Wippelgem Eindeken 33a Evergem Oost-Vlaanderen 9940",
    "addr:housenumber":"33a",
    "addr:postcode":"9940",
    "addr:street":"Eindeken;Oost-Vlaanderen",
    "iso:country":"BE",
    "sg:address":"Wippelgem Eindeken 33a",
    "sg:city":"Evergem",
    "sg:classifiers":[
        {
            "category":"Freight",
            "type":"Transportation"
        }
    ],
    "sg:phone":"+32 9 357 45 51",
    "sg:postcode":"9940",
    "sg:province":"Oost-Vlaanderen",
    "sg:tags":[
        "-",
        "transport"
    ],
    "wof:name":"Rc Transport Bvba",
    "wof:placetype":"venue"
},
  "geometry": {"coordinates":[3.7096180916,51.1067390442],"type":"Point"}
}