{
  "type": "Feature",
  "properties": {
    "iso:country":"BE",
    "sg:address":"Brikstraat 33",
    "sg:city":"Herne",
    "sg:orig_category":"Eleveurs and marchands de porcs",
    "sg:phone":"+32 2 396 16 94",
    "sg:postcode":"1541",
    "sg:province":"Vlaams-Brabant",
    "wof:name":"Adelin Faucq",
    "wof:placetype":"venue"
},
  "geometry": {"coordinates":[4.0044088364,50.7133255005],"type":"Point"}
}