{
  "type": "Feature",
  "properties": {
    "addr:full":"Westlaan 49-51 Roeselare West-Vlaanderen 8800",
    "addr:housenumber":"49-51",
    "addr:postcode":"8800",
    "addr:street":"Westlaan",
    "iso:country":"BE",
    "sg:address":"Westlaan 49-51",
    "sg:city":"Roeselare",
    "sg:classifiers":[
        {
            "category":"Home & Garden",
            "subcategory":"Home Furnishings",
            "type":"Retail Goods"
        }
    ],
    "sg:phone":"+32 51 20 19 12",
    "sg:postcode":"8800",
    "sg:province":"West-Vlaanderen",
    "sg:tags":[
        "curtain",
        "-",
        "fixture"
    ],
    "wof:name":"'t Garnierdershuis Huyghe Bvba",
    "wof:placetype":"venue"
},
  "geometry": {"coordinates":[3.1188879013,50.9370384216],"type":"Point"}
}