{
  "type": "Feature",
  "properties": {
    "iso:country":"BE",
    "sg:address":"Rogierlaan 4",
    "sg:city":"Blankenberge",
    "sg:classifiers":[
        {
            "category":"Restaurant",
            "type":"Food & Drink"
        }
    ],
    "sg:phone":"+32 50 41 11 51",
    "sg:postcode":"8370",
    "sg:province":"West-Vlaanderen",
    "wof:name":"Hotel Lucullus",
    "wof:placetype":"venue"
},
  "geometry": {"coordinates":[3.1322519779,51.3161659241],"type":"Point"}
}