{
  "type": "Feature",
  "properties": {
    "addr:full":"Rue D'autre Eglise 49 Ramillies (huppaye) Brabant Wallon 1367",
    "addr:housenumber":"49",
    "addr:postcode":"1367",
    "addr:street":"Rue D'Autre Eglise;Wallon",
    "iso:country":"BE",
    "sg:address":"Rue D'autre Eglise 49",
    "sg:city":"Ramillies (huppaye)",
    "sg:classifiers":[
        {
            "category":"Retail",
            "subcategory":"Veterinary Services",
            "type":"Services"
        }
    ],
    "sg:phone":"+32 10 81 62 55",
    "sg:postcode":"1367",
    "sg:province":"Brabant Wallon",
    "sg:tags":[
        "veterinarian"
    ],
    "wof:name":"Merlevede I",
    "wof:placetype":"venue"
},
  "geometry": {"coordinates":[4.923169136,50.6655654907],"type":"Point"}
}