{
  "type": "Feature",
  "properties": {
    "addr:full":"Roeselaarsestraat 70 Kortrijk (heule) West-Vlaanderen 8501",
    "addr:housenumber":"70",
    "addr:postcode":"8501",
    "addr:street":"Roeselaarsestraat",
    "iso:country":"BE",
    "sg:address":"Roeselaarsestraat 70",
    "sg:city":"Kortrijk (heule)",
    "sg:classifiers":[
        {
            "category":"Home & Garden",
            "subcategory":"Building Materials",
            "type":"Retail Goods"
        }
    ],
    "sg:phone":"+32 56 37 26 62",
    "sg:postcode":"8501",
    "sg:province":"West-Vlaanderen",
    "sg:tags":[
        "window"
    ],
    "wof:name":"Denys Nv",
    "wof:placetype":"venue"
},
  "geometry": {"coordinates":[3.2217280865,50.8479804993],"type":"Point"}
}