{
  "type": "Feature",
  "properties": {
    "iso:country":"BE",
    "sg:address":"Beselarestraat 141",
    "sg:city":"Wervik",
    "sg:orig_category":"Varkenskwekers",
    "sg:phone":"+32 56 51 31 46",
    "sg:postcode":"8940",
    "sg:province":"West-Vlaanderen",
    "wof:name":"Etienne Nollet",
    "wof:placetype":"venue"
},
  "geometry": {"coordinates":[3.0456318855,50.7897338867],"type":"Point"}
}