{
  "type": "Feature",
  "properties": {
    "iso:country":"BE",
    "sg:address":"Rue Neuve 29",
    "sg:city":"Beloeil (ellignies-sainte-anne)",
    "sg:classifiers":[
        {
            "category":"Health Services",
            "subcategory":"Health Practitioner",
            "type":"Services"
        }
    ],
    "sg:phone":"+32 69 58 12 98",
    "sg:postcode":"7972",
    "sg:province":"Hainaut",
    "sg:tags":[
        "therapist",
        "speech"
    ],
    "wof:name":"Quequin M",
    "wof:placetype":"venue"
},
  "geometry": {"coordinates":[3.6783509254,50.5624809265],"type":"Point"}
}