{
  "type": "Feature",
  "properties": {
    "addr:full":"Vermeulenstraat 59 Lokeren Oost-Vlaanderen 9160",
    "addr:housenumber":"59",
    "addr:postcode":"9160",
    "addr:street":"Vermeulenstraat",
    "iso:country":"BE",
    "sg:address":"Vermeulenstraat 59",
    "sg:city":"Lokeren",
    "sg:orig_category":"M\u00e9decines alternatives",
    "sg:phone":"+32 9 348 14 94",
    "sg:postcode":"9160",
    "sg:province":"Oost-Vlaanderen",
    "wof:name":"Elly Van Chaze",
    "wof:placetype":"venue"
},
  "geometry": {"coordinates":[3.9948940277,51.1003494263],"type":"Point"}
}