{
  "type": "Feature",
  "properties": {
    "addr:full":"Rozendreef 140 Aalst Oost-Vlaanderen 9300",
    "addr:housenumber":"140",
    "addr:postcode":"9300",
    "addr:street":"Rozendreef",
    "iso:country":"BE",
    "sg:address":"Rozendreef 140",
    "sg:city":"Aalst",
    "sg:orig_category":"Installation de menuiserie m\u00e9tallique",
    "sg:phone":"+32 53 78 23 25",
    "sg:postcode":"9300",
    "sg:province":"Oost-Vlaanderen",
    "wof:name":"All Plafond",
    "wof:placetype":"venue"
},
  "geometry": {"coordinates":[4.0604982376,50.9492797852],"type":"Point"}
}