{
  "type": "Feature",
  "properties": {
    "iso:country":"BE",
    "sg:address":"Hestreux 12a",
    "sg:city":"Anthisnes",
    "sg:classifiers":[
        {
            "category":"Retail",
            "subcategory":"Auto Repair",
            "type":"Services"
        }
    ],
    "sg:phone":"+32 4 383 78 58",
    "sg:postcode":"4160",
    "sg:province":"Li\u00e8ge",
    "sg:tags":[
        "garage"
    ],
    "wof:name":"Simon & Simon Automobiles",
    "wof:placetype":"venue"
},
  "geometry": {"coordinates":[5.5060458183,50.5050544739],"type":"Point"}
}