{
  "type": "Feature",
  "properties": {
    "addr:full":"Rue Cheval-godet 6b5 Nivelles Brabant Wallon 1400",
    "addr:housenumber":"6b5",
    "addr:postcode":"1400",
    "addr:street":"Rue Cheval-Godet",
    "iso:country":"BE",
    "sg:address":"Rue Cheval-godet 6b5",
    "sg:city":"Nivelles",
    "sg:orig_category":"M\u00e9decins and sp\u00e9cialistes",
    "sg:phone":"+32 67 22 05 66",
    "sg:postcode":"1400",
    "sg:province":"Brabant Wallon",
    "wof:name":"Bernard Candi",
    "wof:placetype":"venue"
},
  "geometry": {"coordinates":[4.3241038322,50.6038551331],"type":"Point"}
}