{
  "type": "Feature",
  "properties": {
    "iso:country":"BE",
    "sg:address":"Chauss\u00c9e D'ellezelles 65",
    "sg:city":"Ronse/renaix",
    "sg:orig_category":"Meubles D\u00e9taillants, Am\u00e9nagement de B\u00e2timents et de Cuisines. Installation de menuiserie en bois and",
    "sg:phone":"+32 55 23 90 86",
    "sg:postcode":"9600",
    "sg:province":"Oost-Vlaanderen",
    "wof:name":"Jose Bellinck",
    "wof:placetype":"venue"
},
  "geometry": {"coordinates":[3.6135261059,50.7430648804],"type":"Point"}
}