{
  "type": "Feature",
  "properties": {
    "iso:country":"BE",
    "sg:address":"Route De Champion 37",
    "sg:city":"Eghez\u00e9e (hanret)",
    "sg:classifiers":[
        {
            "category":"Building & Trades",
            "subcategory":"Landscaping Services",
            "type":"Services"
        }
    ],
    "sg:phone":"+32 81 81 17 71",
    "sg:postcode":"5310",
    "sg:province":"Namur",
    "sg:tags":[
        "-",
        "lopping",
        "work",
        "tree",
        "felling"
    ],
    "wof:name":"Gillot Ets-woodlight Garden",
    "wof:placetype":"venue"
},
  "geometry": {"coordinates":[4.9465098381,50.5818367004],"type":"Point"}
}