{
  "type": "Feature",
  "properties": {
    "iso:country":"BE",
    "sg:address":"Brugbemdenstraat 1",
    "sg:city":"Hasselt",
    "sg:classifiers":[
        {
            "category":"Social Services",
            "type":"Services"
        }
    ],
    "sg:phone":"+32 11 27 84 20",
    "sg:postcode":"3500",
    "sg:province":"Limburg",
    "wof:name":"Bezinningscentrum Godsheide",
    "wof:placetype":"venue"
},
  "geometry": {"coordinates":[5.3754010201,50.9375534058],"type":"Point"}
}