{
  "type": "Feature",
  "properties": {
    "addr:full":"Volkegemberg 13 Oudenaarde Oost-Vlaanderen 9700",
    "addr:housenumber":"13",
    "addr:postcode":"9700",
    "addr:street":"Volkegemberg",
    "iso:country":"BE",
    "sg:address":"Volkegemberg 13",
    "sg:city":"Oudenaarde",
    "sg:classifiers":[
        {
            "category":"Cafe",
            "type":"Food & Drink"
        }
    ],
    "sg:phone":"+32 55 31 82 56",
    "sg:postcode":"9700",
    "sg:province":"Oost-Vlaanderen",
    "sg:tags":[
        "caf\u00e9s"
    ],
    "wof:name":"Caf\u00c9 Au Petit Pont",
    "wof:placetype":"venue"
},
  "geometry": {"coordinates":[3.6369359493,50.8404502869],"type":"Point"}
}