{
  "type": "Feature",
  "properties": {
    "iso:country":"BE",
    "sg:address":"Avenue D'itterbeek 402",
    "sg:city":"Bruxelles (anderlecht)",
    "sg:classifiers":[
        {
            "category":"Professional",
            "subcategory":"Testing Lab",
            "type":"Services"
        }
    ],
    "sg:phone":"+32 2 522 85 59",
    "sg:postcode":"1070",
    "sg:province":"Bruxelles-Capitale",
    "sg:tags":[
        "chemist"
    ],
    "wof:name":"Bon Air (pharmacie Du)",
    "wof:placetype":"venue"
},
  "geometry": {"coordinates":[4.2776098251,50.8352355957],"type":"Point"}
}