{
  "type": "Feature",
  "properties": {
    "addr:full":"Chauss\u00c9e De Wavre 218-220 Elsene/ixelles Bruxelles-Capitale 1050",
    "addr:postcode":"218-220;1050",
    "addr:street":"Chausse\u0301E De Wavre",
    "iso:country":"BE",
    "sg:address":"Chauss\u00c9e De Wavre 218-220",
    "sg:city":"Elsene/ixelles",
    "sg:orig_category":"Disquaires. Librairies",
    "sg:phone":"+32 2 648 96 89",
    "sg:postcode":"1050",
    "sg:province":"Bruxelles-Capitale",
    "wof:name":"Librairie U.o.p.c.",
    "wof:placetype":"venue"
},
  "geometry": {"coordinates":[4.3727560043,50.836101532],"type":"Point"}
}