{
  "type": "Feature",
  "properties": {
    "iso:country":"BE",
    "sg:address":"Grote Baan 16",
    "sg:city":"Waasmunster",
    "sg:classifiers":[
        {
            "category":"Professional",
            "type":"Services"
        }
    ],
    "sg:phone":"+32 3 772 10 91",
    "sg:postcode":"9250",
    "sg:province":"Oost-Vlaanderen",
    "sg:tags":[
        "aux",
        "diver",
        "personnes"
    ],
    "wof:name":"Stuer D.",
    "wof:placetype":"venue"
},
  "geometry": {"coordinates":[4.0678210258,51.1377296448],"type":"Point"}
}