{
  "type": "Feature",
  "properties": {
    "iso:country":"BE",
    "sg:address":"Dorpsstraat 23",
    "sg:city":"Kortessem",
    "sg:orig_category":"Artistes ind\u00e9pendants",
    "sg:phone":"+32 11 37 63 60",
    "sg:postcode":"3720",
    "sg:province":"Limburg",
    "wof:name":"Christel Van Schoonwinkel",
    "wof:placetype":"venue"
},
  "geometry": {"coordinates":[5.3878149986,50.8581428528],"type":"Point"}
}