{
  "type": "Feature",
  "properties": {
    "iso:country":"BE",
    "sg:address":"Zaventemsesteenweg 154-162",
    "sg:city":"Machelen",
    "sg:orig_category":"IJzerwaren, bouw- and verfmaterialen MEUBELONTWERP AND -INSTALLATIE Meubelzaken, woning- and keukeni",
    "sg:phone":"+32 2 720 49 20",
    "sg:postcode":"1831",
    "sg:province":"Vlaams-Brabant",
    "wof:name":"Reno",
    "wof:placetype":"venue"
},
  "geometry": {"coordinates":[4.442920208,50.8960800171],"type":"Point"}
}