{
  "type": "Feature",
  "properties": {
    "addr:full":"Rue Des Forgerons 6 Charleroi (marcinelle) Hainaut 6001",
    "addr:housenumber":"6",
    "addr:postcode":"6001",
    "addr:street":"Rue Des Forgerons",
    "iso:country":"BE",
    "sg:address":"Rue Des Forgerons 6",
    "sg:city":"Charleroi (marcinelle)",
    "sg:classifiers":[
        {
            "category":"Real Estate",
            "subcategory":"Architect",
            "type":"Services"
        }
    ],
    "sg:phone":"+32 71 36 29 87",
    "sg:postcode":"6001",
    "sg:province":"Hainaut",
    "wof:name":"Delmotte P",
    "wof:placetype":"venue"
},
  "geometry": {"coordinates":[4.4486107826,50.3927726746],"type":"Point"}
}