{
  "type": "Feature",
  "properties": {
    "iso:country":"BE",
    "sg:address":"Chauss\u00e9e De Huy 224",
    "sg:city":"Chaumont-gistoux",
    "sg:classifiers":[
        {
            "category":"Personal",
            "subcategory":"Beauty Salon",
            "type":"Services"
        }
    ],
    "sg:phone":"+32 10 68 05 23",
    "sg:postcode":"1325",
    "sg:province":"Brabant Wallon",
    "sg:tags":[
        "lady",
        "-",
        "hairdressing"
    ],
    "wof:name":"Art & Cheveux",
    "wof:placetype":"venue"
},
  "geometry": {"coordinates":[4.6941437721,50.6843528748],"type":"Point"}
}