{
  "type": "Feature",
  "properties": {
    "iso:country":"BE",
    "sg:address":"Matenstraat 125",
    "sg:city":"Niel",
    "sg:classifiers":[
        {
            "category":"Building & Trades",
            "subcategory":"Landscaping Services",
            "type":"Services"
        }
    ],
    "sg:phone":"+32 3 888 85 61",
    "sg:postcode":"2845",
    "sg:province":"Antwerpen",
    "sg:tags":[
        "gardening",
        "garden",
        "maintenance"
    ],
    "wof:name":"Van Der Sanden M",
    "wof:placetype":"venue"
},
  "geometry": {"coordinates":[4.3442912102,51.1116409302],"type":"Point"}
}