{
  "type": "Feature",
  "properties": {
    "iso:country":"BE",
    "sg:address":"Rue De L'eglise 98a",
    "sg:city":"Bruxelles (woluwe-saint-pierre)",
    "sg:classifiers":[
        {
            "category":"Food & Beverages",
            "subcategory":"Liquor & Beverages",
            "type":"Retail Goods"
        }
    ],
    "sg:phone":"+32 2 772 77 06",
    "sg:postcode":"1150",
    "sg:province":"Bruxelles-Capitale",
    "sg:tags":[
        "-",
        "spirit",
        "wine"
    ],
    "wof:name":"Eurowines",
    "wof:placetype":"venue"
},
  "geometry": {"coordinates":[4.4640240669,50.8407058716],"type":"Point"}
}