{
  "type": "Feature",
  "properties": {
    "addr:full":"Rijksweg 160 Zulte (machelen) Oost-Vlaanderen 9870",
    "addr:housenumber":"160",
    "addr:postcode":"9870",
    "addr:street":"Rijksweg",
    "iso:country":"BE",
    "sg:address":"Rijksweg 160",
    "sg:city":"Zulte (machelen)",
    "sg:classifiers":[
        {
            "category":"Bars & Pubs",
            "type":"Food & Drink"
        }
    ],
    "sg:phone":"+32 9 388 79 68",
    "sg:postcode":"9870",
    "sg:province":"Oost-Vlaanderen",
    "sg:tags":[
        "tavern"
    ],
    "wof:name":"Napoleon",
    "wof:placetype":"venue"
},
  "geometry": {"coordinates":[3.476788044,50.9442558289],"type":"Point"}
}