{
  "type": "Feature",
  "properties": {
    "iso:country":"BE",
    "sg:address":"Rue L\u00e9on Defuisseaux 47",
    "sg:city":"Frameries",
    "sg:classifiers":[
        {
            "category":"Health Services",
            "subcategory":"Nursing And Care Facility",
            "type":"Services"
        }
    ],
    "sg:phone":"+32 65 66 05 96",
    "sg:postcode":"7080",
    "sg:province":"Hainaut",
    "sg:tags":[
        "home"
    ],
    "wof:name":"Toubeau C",
    "wof:placetype":"venue"
},
  "geometry": {"coordinates":[3.895637989,50.4063301086],"type":"Point"}
}