{
  "type": "Feature",
  "properties": {
    "addr:full":"Rijselstraat 131 Menen West-Vlaanderen 8930",
    "addr:housenumber":"131",
    "addr:postcode":"8930",
    "addr:street":"Rijselstraat",
    "iso:country":"BE",
    "sg:address":"Rijselstraat 131",
    "sg:city":"Menen",
    "sg:classifiers":[
        {
            "category":"Shopping",
            "subcategory":"Crafts & Fabrics",
            "type":"Retail Goods"
        }
    ],
    "sg:phone":"+32 56 51 18 77",
    "sg:postcode":"8930",
    "sg:province":"West-Vlaanderen",
    "sg:tags":[
        "silk",
        "-"
    ],
    "wof:name":"P\u00e9n\u00e9lope",
    "wof:placetype":"venue"
},
  "geometry": {"coordinates":[3.1245679855,50.7910385132],"type":"Point"}
}