{
  "type": "Feature",
  "properties": {
    "iso:country":"BE",
    "sg:address":"Steenstraat 50",
    "sg:city":"Brugge",
    "sg:orig_category":"Verlichting and huishoudartikelen",
    "sg:phone":"+32 50 33 03 95",
    "sg:postcode":"8000",
    "sg:province":"West-Vlaanderen",
    "wof:name":"Pop Art",
    "wof:placetype":"venue"
},
  "geometry": {"coordinates":[3.2225248814,51.2070388794],"type":"Point"}
}