{
  "type": "Feature",
  "properties": {
    "addr:full":"Avenue De Hony 43 Esneux Li\u00e8ge 4130",
    "addr:housenumber":"43",
    "addr:postcode":"4130",
    "addr:street":"Avenue De Hony",
    "iso:country":"BE",
    "sg:address":"Avenue De Hony 43",
    "sg:city":"Esneux",
    "sg:classifiers":[
        {
            "category":"Real Estate",
            "subcategory":"Surveying",
            "type":"Services"
        }
    ],
    "sg:phone":"+32 4 388 26 25",
    "sg:postcode":"4130",
    "sg:province":"Li\u00e8ge",
    "sg:tags":[
        "surveyor",
        "land"
    ],
    "wof:name":"Cofa Sa",
    "wof:placetype":"venue"
},
  "geometry": {"coordinates":[5.5829091072,50.5447273254],"type":"Point"}
}