{
  "type": "Feature",
  "properties": {
    "addr:full":"Rue De La Montagne 74 Charleroi Hainaut 6000",
    "addr:housenumber":"74",
    "addr:postcode":"6000",
    "addr:street":"Rue De La Montagne;Hainaut",
    "iso:country":"BE",
    "sg:address":"Rue De La Montagne 74",
    "sg:city":"Charleroi",
    "sg:classifiers":[
        {
            "category":"Shopping",
            "subcategory":"Clothing, Apparel, & Fashions",
            "type":"Retail Goods"
        }
    ],
    "sg:phone":"+32 71 32 62 45",
    "sg:postcode":"6000",
    "sg:province":"Hainaut",
    "sg:tags":[
        "clothing",
        "-",
        "gentleman"
    ],
    "wof:name":"Charvet Henri Sprl",
    "wof:placetype":"venue"
},
  "geometry": {"coordinates":[4.4436659813,50.411075592],"type":"Point"}
}