{
  "type": "Feature",
  "properties": {
    "iso:country":"BE",
    "sg:address":"Rue De La Semence 29b4",
    "sg:city":"Sint-jans-molenbeek/molenbeek-",
    "sg:orig_category":"Messageries. Agences de marketing",
    "sg:phone":"+32 2 415 99 21",
    "sg:postcode":"1080",
    "sg:province":"Bruxelles-Capitale",
    "wof:name":"Strat Up Communication",
    "wof:placetype":"venue"
},
  "geometry": {"coordinates":[4.3135948181,50.8503684998],"type":"Point"}
}