{
  "type": "Feature",
  "properties": {
    "addr:full":"Mechelsesteenweg 26 Lier Antwerpen 2500",
    "addr:housenumber":"26",
    "addr:postcode":"2500",
    "addr:street":"Mechelsesteenweg",
    "iso:country":"BE",
    "sg:address":"Mechelsesteenweg 26",
    "sg:city":"Lier",
    "sg:orig_category":"Dancings and nachtclubs Ruimtes voor conferenties, recepties and feesten",
    "sg:phone":"+32 3 644 18 17",
    "sg:postcode":"2500",
    "sg:province":"Antwerpen",
    "wof:name":"New Zazou",
    "wof:placetype":"venue"
},
  "geometry": {"coordinates":[4.5611371994,51.1303253174],"type":"Point"}
}