{
  "type": "Feature",
  "properties": {
    "iso:country":"BE",
    "sg:address":"Ring 71",
    "sg:city":"Herentals (noorderwijk)",
    "sg:classifiers":[
        {
            "category":"Professional",
            "subcategory":"Management & Consulting",
            "type":"Services"
        }
    ],
    "sg:phone":"+32 14 27 75 70",
    "sg:postcode":"2200",
    "sg:province":"Antwerpen",
    "sg:tags":[
        "marketing",
        "-",
        "consultant"
    ],
    "wof:name":"Avivos Bvba",
    "wof:placetype":"venue"
},
  "geometry": {"coordinates":[4.8364129066,51.1365585327],"type":"Point"}
}