{
  "type": "Feature",
  "properties": {
    "addr:full":"Gaarveldstraat 40 Box 1 Hasselt Limburg 3500",
    "addr:housenumber":"40;1",
    "addr:postcode":"3500",
    "addr:street":"Gaarveldstraat;Box",
    "iso:country":"BE",
    "sg:address":"Gaarveldstraat 40 Box 1",
    "sg:city":"Hasselt",
    "sg:classifiers":[
        {
            "category":"Organizations",
            "subcategory":"Professional Association",
            "type":"Services"
        }
    ],
    "sg:phone":"+32 11 35 23 79",
    "sg:postcode":"3500",
    "sg:province":"Limburg",
    "sg:tags":[
        "trade-union",
        "federation"
    ],
    "wof:name":"Federatie Van Invoerders En Producenten Van Hulpstoffen",
    "wof:placetype":"venue"
},
  "geometry": {"coordinates":[5.3297781944,50.9265327454],"type":"Point"}
}