{
  "type": "Feature",
  "properties": {
    "addr:full":"Stenenmuurstraat 58 Sint-niklaas Oost-Vlaanderen 9112",
    "addr:housenumber":"58",
    "addr:postcode":"9112",
    "addr:street":"Stenenmuurstraat",
    "iso:country":"BE",
    "sg:address":"Stenenmuurstraat 58",
    "sg:city":"Sint-niklaas",
    "sg:orig_category":"Rundveehouders",
    "sg:phone":"+32 3 722 02 09",
    "sg:postcode":"9112",
    "sg:province":"Oost-Vlaanderen",
    "wof:name":"De Block",
    "wof:placetype":"venue"
},
  "geometry": {"coordinates":[4.0486869812,51.1703529358],"type":"Point"}
}