{
  "type": "Feature",
  "properties": {
    "addr:full":"Steenweg Op Zondereigen 2 Turnhout Antwerpen 2300",
    "addr:housenumber":"2",
    "addr:postcode":"2300",
    "addr:street":"Steenweg Op Zondereigen",
    "iso:country":"BE",
    "sg:address":"Steenweg Op Zondereigen 2",
    "sg:city":"Turnhout",
    "sg:classifiers":[
        {
            "category":"Cafe",
            "type":"Food & Drink"
        }
    ],
    "sg:phone":"+32 14 65 85 09",
    "sg:postcode":"2300",
    "sg:province":"Antwerpen",
    "sg:tags":[
        "caf\u00e9s"
    ],
    "wof:name":"Caf\u00c9 Het Hoefijzer",
    "wof:placetype":"venue"
},
  "geometry": {"coordinates":[4.9232001305,51.3897094727],"type":"Point"}
}