{
  "type": "Feature",
  "properties": {
    "iso:country":"BE",
    "sg:address":"Dries 59",
    "sg:city":"Bruxelles (watermael-boitsfort)",
    "sg:classifiers":[
        {
            "category":"Food & Beverages",
            "subcategory":"Groceries & Convenience Stores",
            "type":"Retail Goods"
        }
    ],
    "sg:phone":"+32 2 672 76 11",
    "sg:postcode":"1170",
    "sg:province":"Bruxelles-Capitale",
    "sg:tags":[
        "grocer"
    ],
    "wof:name":"Pamir",
    "wof:placetype":"venue"
},
  "geometry": {"coordinates":[4.3990511894,50.8032646179],"type":"Point"}
}