{
  "type": "Feature",
  "properties": {
    "addr:full":"Rue D'eghez\u00c9e 45 Fernelmont Namur 5380",
    "addr:housenumber":"45",
    "addr:postcode":"5380",
    "addr:street":"Rue D'Egheze \u0301E",
    "iso:country":"BE",
    "sg:address":"Rue D'eghez\u00c9e 45",
    "sg:city":"Fernelmont",
    "sg:orig_category":"Banques and organismes de cr\u00e9dit",
    "sg:phone":"+32 81 83 34 52",
    "sg:postcode":"5380",
    "sg:province":"Namur",
    "wof:name":"Fortis",
    "wof:placetype":"venue"
},
  "geometry": {"coordinates":[5.0000309944,50.5738296509],"type":"Point"}
}