{
  "type": "Feature",
  "properties": {
    "addr:full":"E Blondieaustraat 16 Vilvoorde Vlaams-Brabant 1800",
    "addr:housenumber":"16",
    "addr:postcode":"1800",
    "addr:street":"Blondieaustraat",
    "iso:country":"BE",
    "sg:address":"E Blondieaustraat 16",
    "sg:city":"Vilvoorde",
    "sg:orig_category":"Imprimeries and copyshops",
    "sg:phone":"+32 2 253 99 19",
    "sg:postcode":"1800",
    "sg:province":"Vlaams-Brabant",
    "wof:name":"Blue Dog",
    "wof:placetype":"venue"
},
  "geometry": {"coordinates":[4.4320611954,50.9260063171],"type":"Point"}
}