{
  "type": "Feature",
  "properties": {
    "iso:country":"BE",
    "sg:address":"Vlaktedreef 0",
    "sg:city":"Tervuren",
    "sg:orig_category":"Dierentuinen, botanische tuinen, sterrenwachten and natuurreservaten",
    "sg:phone":"+32 2 769 20 81",
    "sg:postcode":"3080",
    "sg:province":"Vlaams-Brabant",
    "wof:name":"Arboretum",
    "wof:placetype":"venue"
},
  "geometry": {"coordinates":[4.4947471619,50.8089447021],"type":"Point"}
}