{
  "type": "Feature",
  "properties": {
    "iso:country":"BE",
    "sg:address":"Sint-geertruistraat 78",
    "sg:city":"Tongeren",
    "sg:orig_category":"Mat\u00e9riel m\u00e9dical and orthop\u00e9dique and proth\u00e8ses Fab",
    "sg:phone":"+32 12 23 48 34",
    "sg:postcode":"3700",
    "sg:province":"Limburg",
    "wof:name":"Simons Marcel",
    "wof:placetype":"venue"
},
  "geometry": {"coordinates":[5.4532599449,50.8100891113],"type":"Point"}
}