{
  "type": "Feature",
  "properties": {
    "iso:country":"BE",
    "sg:address":"Kastanjelaan 35",
    "sg:city":"Diepenbeek",
    "sg:orig_category":"Installation de menuiserie m\u00e9tallique",
    "sg:phone":"+32 11 32 36 89",
    "sg:postcode":"3590",
    "sg:province":"Limburg",
    "wof:name":"Roland Briers",
    "wof:placetype":"venue"
},
  "geometry": {"coordinates":[5.4003667831,50.9087791443],"type":"Point"}
}