{
  "type": "Feature",
  "properties": {
    "addr:full":"Avenue Brillat Savarin 80 Bruxelles (ixelles) Bruxelles-Capitale 1050",
    "addr:housenumber":"80",
    "addr:postcode":"1050",
    "addr:street":"Avenue Brillat Savarin",
    "iso:country":"BE",
    "sg:address":"Avenue Brillat Savarin 80",
    "sg:city":"Bruxelles (ixelles)",
    "sg:classifiers":[
        {
            "category":"Health Services",
            "subcategory":"Health Practitioner",
            "type":"Services"
        }
    ],
    "sg:phone":"+32 2 649 83 57",
    "sg:postcode":"1050",
    "sg:province":"Bruxelles-Capitale",
    "sg:tags":[
        "physiotherapist"
    ],
    "wof:name":"Lefebvre C",
    "wof:placetype":"venue"
},
  "geometry": {"coordinates":[4.3847799301,50.8159790039],"type":"Point"}
}