{
  "type": "Feature",
  "properties": {
    "addr:full":"Lange Venstraat 4 Tremelo (baal) Vlaams-Brabant 3128",
    "addr:housenumber":"4",
    "addr:postcode":"3128",
    "addr:street":"Lange Venstraat",
    "iso:country":"BE",
    "sg:address":"Lange Venstraat 4",
    "sg:city":"Tremelo (baal)",
    "sg:classifiers":[
        {
            "category":"Organizations",
            "subcategory":"Community Association",
            "type":"Services"
        }
    ],
    "sg:phone":"+32 496 72 19 16",
    "sg:postcode":"3128",
    "sg:province":"Vlaams-Brabant",
    "sg:tags":[
        "badge"
    ],
    "wof:name":"W & G Atelier",
    "wof:placetype":"venue"
},
  "geometry": {"coordinates":[4.7462830544,51.0127296448],"type":"Point"}
}