{
  "type": "Feature",
  "properties": {
    "addr:full":"G. Demeurslaan 110 Beersel Vlaams-Brabant 1654",
    "addr:housenumber":"110",
    "addr:postcode":"1654",
    "addr:street":"Demeurslaan",
    "iso:country":"BE",
    "sg:address":"G. Demeurslaan 110",
    "sg:city":"Beersel",
    "sg:orig_category":"Entretien and r\u00e9parations de machines de bureau and ordinateurs",
    "sg:phone":"+32 2 536 41 76",
    "sg:postcode":"1654",
    "sg:province":"Vlaams-Brabant",
    "wof:name":"Cosmo",
    "wof:placetype":"venue"
},
  "geometry": {"coordinates":[4.2651357651,50.7567329407],"type":"Point"}
}