{
  "type": "Feature",
  "properties": {
    "iso:country":"BE",
    "sg:address":"Brugsesteenweg 62",
    "sg:city":"Kuurne",
    "sg:orig_category":"Plaatsen van vloer- and muurbekleding Schilders",
    "sg:phone":"+32 56 35 02 14",
    "sg:postcode":"8520",
    "sg:province":"West-Vlaanderen",
    "wof:name":"Jacky Maes",
    "wof:placetype":"venue"
},
  "geometry": {"coordinates":[3.2697548866,50.8478240967],"type":"Point"}
}