{
  "type": "Feature",
  "properties": {
    "iso:country":"BE",
    "sg:address":"Brezendedreef 1",
    "sg:city":"Maldegem",
    "sg:classifiers":[
        {
            "category":"Personal",
            "subcategory":"Beauty Salon",
            "type":"Services"
        }
    ],
    "sg:phone":"+32 50 71 14 67",
    "sg:postcode":"9990",
    "sg:province":"Oost-Vlaanderen",
    "sg:tags":[
        "de",
        "coiffure"
    ],
    "wof:name":"Coiffure Annie",
    "wof:placetype":"venue"
},
  "geometry": {"coordinates":[3.382117033,51.2218360901],"type":"Point"}
}