{
  "type": "Feature",
  "properties": {
    "addr:full":". Rebecq Brabant Wallon 1430",
    "addr:postcode":"1430",
    "iso:country":"BE",
    "sg:address":".",
    "sg:city":"Rebecq",
    "sg:orig_category":"Apotheken",
    "sg:phone":"+32 900 10 500",
    "sg:postcode":"1430",
    "sg:province":"Brabant Wallon",
    "wof:name":"Apothekers Van Wacht",
    "wof:placetype":"venue"
},
  "geometry": {"coordinates":[4.1317100525,50.6643714905],"type":"Point"}
}