{
  "type": "Feature",
  "properties": {
    "iso:country":"BE",
    "sg:address":"Rue De L'h\u00f4tel De Ville 16",
    "sg:city":"Vielsalm",
    "sg:classifiers":[
        {
            "category":"Real Estate",
            "subcategory":"Architect",
            "type":"Services"
        }
    ],
    "sg:phone":"+32 80 21 78 11",
    "sg:postcode":"6690",
    "sg:province":"Luxembourg",
    "wof:name":"David P",
    "wof:placetype":"venue"
},
  "geometry": {"coordinates":[5.9159607887,50.2850151062],"type":"Point"}
}