{
  "type": "Feature",
  "properties": {
    "iso:country":"BE",
    "sg:address":"Hector Denisstraat 6",
    "sg:city":"Ronse",
    "sg:orig_category":"Pain, p\u00e2tisseries and confiseries",
    "sg:phone":"+32 475 96 25 64",
    "sg:postcode":"9600",
    "sg:province":"Oost-Vlaanderen",
    "wof:name":"Mathu",
    "wof:placetype":"venue"
},
  "geometry": {"coordinates":[3.6052610874,50.7357978821],"type":"Point"}
}