{
  "type": "Feature",
  "properties": {
    "addr:full":"Bruggestraat 11 Ruiselede West-Vlaanderen 8755",
    "addr:housenumber":"11",
    "addr:postcode":"8755",
    "addr:street":"Bruggestraat",
    "iso:country":"BE",
    "sg:address":"Bruggestraat 11",
    "sg:city":"Ruiselede",
    "sg:orig_category":"Artsen and specialisten",
    "sg:phone":"+32 51 68 72 99",
    "sg:postcode":"8755",
    "sg:province":"West-Vlaanderen",
    "wof:name":"Marie-christine De Jaeger",
    "wof:placetype":"venue"
},
  "geometry": {"coordinates":[3.3957231045,51.0416908264],"type":"Point"}
}