{
  "type": "Feature",
  "properties": {
    "addr:full":"Grand Place 18 Frasnes-lez-anvaing Hainaut 7911",
    "addr:housenumber":"18",
    "addr:postcode":"7911",
    "addr:street":"Grand Place",
    "iso:country":"BE",
    "sg:address":"Grand Place 18",
    "sg:city":"Frasnes-lez-anvaing",
    "sg:classifiers":[
        {
            "category":"Cafe",
            "type":"Food & Drink"
        }
    ],
    "sg:phone":"+32 69 86 86 79",
    "sg:postcode":"7911",
    "sg:province":"Hainaut",
    "sg:tags":[
        "caf\u00e9s"
    ],
    "wof:name":"Le Sympa",
    "wof:placetype":"venue"
},
  "geometry": {"coordinates":[3.6210598946,50.66796875],"type":"Point"}
}