{
  "type": "Feature",
  "properties": {
    "addr:full":"Rue Hubert Denis 5 Plombi\u00e8res (montzen) Li\u00e8ge 4850",
    "addr:housenumber":"5",
    "addr:postcode":"4850",
    "addr:street":"Rue Hubert Denis",
    "iso:country":"BE",
    "sg:address":"Rue Hubert Denis 5",
    "sg:city":"Plombi\u00e8res (montzen)",
    "sg:classifiers":[
        {
            "category":"Freight",
            "type":"Transportation"
        }
    ],
    "sg:phone":"+32 87 78 82 20",
    "sg:postcode":"4850",
    "sg:province":"Li\u00e8ge",
    "sg:tags":[
        "express",
        "transport"
    ],
    "wof:name":"Transhoubben Sa",
    "wof:placetype":"venue"
},
  "geometry": {"coordinates":[5.9577741623,50.707572937],"type":"Point"}
}