{
  "type": "Feature",
  "properties": {
    "addr:full":"Rue Du Mail 109 Bruxelles (ixelles) Bruxelles-Capitale 1050",
    "addr:housenumber":"109",
    "addr:postcode":"1050",
    "addr:street":"Rue Du Mail",
    "iso:country":"BE",
    "sg:address":"Rue Du Mail 109",
    "sg:city":"Bruxelles (ixelles)",
    "sg:classifiers":[
        {
            "category":"Health Services",
            "subcategory":"Health Practitioner",
            "type":"Services"
        }
    ],
    "sg:phone":"+32 2 534 95 75",
    "sg:postcode":"1050",
    "sg:province":"Bruxelles-Capitale",
    "sg:tags":[
        "physiotherapist"
    ],
    "wof:name":"Bauweleers Sophie",
    "wof:placetype":"venue"
},
  "geometry": {"coordinates":[4.3581690788,50.8210945129],"type":"Point"}
}