{
  "type": "Feature",
  "properties": {
    "addr:full":"Molenberglei 42 Schelle Antwerpen 2627",
    "addr:housenumber":"42",
    "addr:postcode":"2627",
    "addr:street":"Molenberglei",
    "iso:country":"BE",
    "sg:address":"Molenberglei 42",
    "sg:city":"Schelle",
    "sg:classifiers":[
        {
            "category":"Professional",
            "subcategory":"Engineering",
            "type":"Services"
        }
    ],
    "sg:phone":"+32 3 354 45 70",
    "sg:postcode":"2627",
    "sg:province":"Antwerpen",
    "sg:tags":[
        "industrial",
        "-",
        "automation"
    ],
    "wof:name":"Cardoen Technology Nv Nv",
    "wof:placetype":"venue"
},
  "geometry": {"coordinates":[4.3683099747,51.1193618774],"type":"Point"}
}