{
  "type": "Feature",
  "properties": {
    "addr:full":"Rue Joseph-jean Merlot 59 Chaudfontaine (vaux-sous-ch\u00e8vremont) Li\u00e8ge 4051",
    "addr:housenumber":"59",
    "addr:postcode":"4051",
    "addr:street":"Rue Joseph-Jean Merlot",
    "iso:country":"BE",
    "sg:address":"Rue Joseph-jean Merlot 59",
    "sg:city":"Chaudfontaine (vaux-sous-ch\u00e8vremont)",
    "sg:classifiers":[
        {
            "category":"Building & Trades",
            "subcategory":"Cleaning & Sanitation",
            "type":"Services"
        }
    ],
    "sg:phone":"+32 4 367 20 83",
    "sg:postcode":"4051",
    "sg:province":"Li\u00e8ge",
    "sg:tags":[
        "blast"
    ],
    "wof:name":"Li\u00e9geois B",
    "wof:placetype":"venue"
},
  "geometry": {"coordinates":[5.629650116,50.6044692993],"type":"Point"}
}