{
  "type": "Feature",
  "properties": {
    "addr:full":"Handzamestraat 139 Kortemark (handzame) West-Vlaanderen 8610",
    "addr:housenumber":"139",
    "addr:postcode":"8610",
    "addr:street":"Handzamestraat",
    "iso:country":"BE",
    "sg:address":"Handzamestraat 139",
    "sg:city":"Kortemark (handzame)",
    "sg:classifiers":[
        {
            "category":"Bars & Pubs",
            "type":"Food & Drink"
        }
    ],
    "sg:phone":"+32 51 56 77 61",
    "sg:postcode":"8610",
    "sg:province":"West-Vlaanderen",
    "wof:name":"Delirium",
    "wof:placetype":"venue"
},
  "geometry": {"coordinates":[3.0237998962,51.0284194946],"type":"Point"}
}