{
  "type": "Feature",
  "properties": {
    "addr:full":"Sprietestraat 172 Waregem West-Vlaanderen 8792",
    "addr:housenumber":"172",
    "addr:postcode":"8792",
    "addr:street":"Sprietestraat",
    "iso:country":"BE",
    "sg:address":"Sprietestraat 172",
    "sg:city":"Waregem",
    "sg:orig_category":"V\u00e9hicules automobiles",
    "sg:phone":"+32 56 71 52 17",
    "sg:postcode":"8792",
    "sg:province":"West-Vlaanderen",
    "wof:name":"Garage Debruyne",
    "wof:placetype":"venue"
},
  "geometry": {"coordinates":[3.3665568829,50.8740997314],"type":"Point"}
}