{
  "type": "Feature",
  "properties": {
    "addr:full":"Rue Charles W\u00c9rotte 82 Namur Namur 5000",
    "addr:housenumber":"82",
    "addr:postcode":"5000",
    "addr:street":"Rue Charles We\u0301Rotte",
    "iso:country":"BE",
    "sg:address":"Rue Charles W\u00c9rotte 82",
    "sg:city":"Namur",
    "sg:orig_category":"Artsen and specialisten",
    "sg:phone":"+32 81 74 79 24",
    "sg:postcode":"5000",
    "sg:province":"Namur",
    "wof:name":"Christine Etienne",
    "wof:placetype":"venue"
},
  "geometry": {"coordinates":[4.8482370377,50.4625511169],"type":"Point"}
}