{
  "type": "Feature",
  "properties": {
    "addr:full":"Avenue Odon Warland 212 Jette/jette Bruxelles-Capitale 1090",
    "addr:housenumber":"212",
    "addr:postcode":"1090",
    "addr:street":"Avenue Odon Warland",
    "iso:country":"BE",
    "sg:address":"Avenue Odon Warland 212",
    "sg:city":"Jette/jette",
    "sg:orig_category":"Antiquit\u00e9s",
    "sg:phone":"+32 2 426 61 94",
    "sg:postcode":"1090",
    "sg:province":"Bruxelles-Capitale",
    "wof:name":"Yann Patou",
    "wof:placetype":"venue"
},
  "geometry": {"coordinates":[4.3384070396,50.8724060059],"type":"Point"}
}