{
  "type": "Feature",
  "properties": {
    "addr:full":"Brabantstraat 19 Nieuwpoort West-Vlaanderen 8620",
    "addr:housenumber":"19",
    "addr:postcode":"8620",
    "addr:street":"Brabantstraat",
    "iso:country":"BE",
    "sg:address":"Brabantstraat 19",
    "sg:city":"Nieuwpoort",
    "sg:classifiers":[
        {
            "category":"Utilities",
            "subcategory":"Telephone",
            "type":"Services"
        }
    ],
    "sg:phone":"+32 58 23 02 06",
    "sg:postcode":"8620",
    "sg:province":"West-Vlaanderen",
    "sg:tags":[
        "-",
        "internet"
    ],
    "wof:name":"Wk Virtual Productions Vof",
    "wof:placetype":"venue"
},
  "geometry": {"coordinates":[2.7123498917,51.1461868286],"type":"Point"}
}