{
  "type": "Feature",
  "properties": {
    "iso:country":"BE",
    "sg:address":"Bd Emile Jacqmain 53",
    "sg:city":"Bruxelles",
    "sg:classifiers":[
        {
            "category":"Banks & Credit Unions",
            "subcategory":"Financial Services",
            "type":"Services"
        }
    ],
    "sg:phone":"+32 2 220 81 11",
    "sg:postcode":"1000",
    "sg:province":"Bruxelles-Capitale",
    "sg:tags":[
        "banking",
        "finance",
        "insurance"
    ],
    "wof:name":"Fortis Assurances Nv",
    "wof:placetype":"venue"
},
  "geometry": {"coordinates":[4.3540110588,50.8533439636],"type":"Point"}
}