{
  "type": "Feature",
  "properties": {
    "iso:country":"BE",
    "sg:address":"Baillet Latourlei 114",
    "sg:city":"Brasschaat",
    "sg:classifiers":[
        {
            "category":"Professional",
            "subcategory":"Management & Consulting",
            "type":"Services"
        }
    ],
    "sg:phone":"+32 3 651 52 87",
    "sg:postcode":"2930",
    "sg:province":"Antwerpen",
    "sg:tags":[
        "consultant"
    ],
    "wof:name":"Leysen L",
    "wof:placetype":"venue"
},
  "geometry": {"coordinates":[4.4650378227,51.2868614197],"type":"Point"}
}