{
  "type": "Feature",
  "properties": {
    "iso:country":"BE",
    "sg:address":"Anemonenstraat 3",
    "sg:city":"Merelbeke",
    "sg:classifiers":[
        {
            "category":"Health Services",
            "subcategory":"Health Practitioner",
            "type":"Services"
        }
    ],
    "sg:phone":"+32 9 232 26 86",
    "sg:postcode":"9820",
    "sg:province":"Oost-Vlaanderen",
    "sg:tags":[
        "physiotherapist"
    ],
    "wof:name":"Volckaert Hilde",
    "wof:placetype":"venue"
},
  "geometry": {"coordinates":[3.76719594,51.0090408325],"type":"Point"}
}