{
  "type": "Feature",
  "properties": {
    "iso:country":"BE",
    "sg:address":"Blandenstraat 77b2",
    "sg:city":"Oud-heverlee",
    "sg:orig_category":"Brood, gebak and snoepgoed",
    "sg:phone":"+32 16 40 37 79",
    "sg:postcode":"3053",
    "sg:province":"Vlaams-Brabant",
    "wof:name":"Filip Natens",
    "wof:placetype":"venue"
},
  "geometry": {"coordinates":[4.7283530235,50.8339767456],"type":"Point"}
}