{
  "type": "Feature",
  "properties": {
    "iso:country":"BE",
    "sg:address":"Steenstraat 21",
    "sg:city":"Geetbets",
    "sg:orig_category":"Gestion des d\u00e9charges and sites d\u00e9finitifs de stockage",
    "sg:phone":"+32 11 58 61 08",
    "sg:postcode":"3450",
    "sg:province":"Vlaams-Brabant",
    "wof:name":"Containerpark Geetbets",
    "wof:placetype":"venue"
},
  "geometry": {"coordinates":[5.1130490303,50.8935012817],"type":"Point"}
}