{
  "type": "Feature",
  "properties": {
    "iso:country":"BE",
    "sg:address":"Nereth 1",
    "sg:city":"Baelen",
    "sg:classifiers":[
        {
            "category":"Professional",
            "subcategory":"Accounting & Tax Preparation",
            "type":"Services"
        }
    ],
    "sg:phone":"+32 87 89 06 30",
    "sg:postcode":"4837",
    "sg:province":"Li\u00e8ge",
    "sg:tags":[
        "bookkeeper"
    ],
    "wof:name":"Jecofi Scprl Sa",
    "wof:placetype":"venue"
},
  "geometry": {"coordinates":[5.9869298935,50.6403884888],"type":"Point"}
}