{
  "type": "Feature",
  "properties": {
    "iso:country":"BE",
    "sg:address":"D. Martenslaan 7",
    "sg:city":"Izegem",
    "sg:orig_category":"Centres de relaxation and bien-\u00eatre. Instituts de beaut\u00e9",
    "sg:phone":"+32 51 31 35 67",
    "sg:postcode":"8870",
    "sg:province":"West-Vlaanderen",
    "wof:name":"Beautystudio Silke",
    "wof:placetype":"venue"
},
  "geometry": {"coordinates":[3.2180249691,50.9207038879],"type":"Point"}
}