{
  "type": "Feature",
  "properties": {
    "iso:country":"BE",
    "sg:address":"Krommestraat 45",
    "sg:city":"Herzele (steenhuize-wijnhuize)",
    "sg:classifiers":[
        {
            "category":"Freight",
            "type":"Transportation"
        }
    ],
    "sg:phone":"+32 54 32 84 55",
    "sg:postcode":"9550",
    "sg:province":"Oost-Vlaanderen",
    "sg:tags":[
        "-",
        "transport"
    ],
    "wof:name":"Diependaele T.m.d.",
    "wof:placetype":"venue"
},
  "geometry": {"coordinates":[3.8847110271,50.8349723816],"type":"Point"}
}