{
  "type": "Feature",
  "properties": {
    "iso:country":"BE",
    "sg:address":"Lampertheimlaan 14",
    "sg:city":"Maldegem",
    "sg:orig_category":"Technische studies and ingenieursactiviteiten",
    "sg:phone":"+32 50 71 79 42",
    "sg:postcode":"9990",
    "sg:province":"Oost-Vlaanderen",
    "wof:name":"Termote",
    "wof:placetype":"venue"
},
  "geometry": {"coordinates":[3.438270092,51.2157745361],"type":"Point"}
}