{
  "type": "Feature",
  "properties": {
    "iso:country":"BE",
    "sg:address":"Chopinstraat 23",
    "sg:city":"Anderlecht",
    "sg:orig_category":"Kapsalons",
    "sg:phone":"+32 2 523 49 82",
    "sg:postcode":"1070",
    "sg:province":"Bruxelles-Capitale",
    "wof:name":"Jean",
    "wof:placetype":"venue"
},
  "geometry": {"coordinates":[4.2953248024,50.828868866],"type":"Point"}
}