{
  "type": "Feature",
  "properties": {
    "iso:country":"BE",
    "sg:address":"Meelbesdreef 35",
    "sg:city":"Kortrijk",
    "sg:orig_category":"Artsen and specialisten",
    "sg:phone":"+32 56 35 40 54",
    "sg:postcode":"8501",
    "sg:province":"West-Vlaanderen",
    "wof:name":"Akasha-center",
    "wof:placetype":"venue"
},
  "geometry": {"coordinates":[3.2492239475,50.8485679626],"type":"Point"}
}