{
  "type": "Feature",
  "properties": {
    "addr:full":"Avenue Charles-quint 560 Sint-agatha-berchem/berchem-sainte-agathe Bruxelles-Capitale 1082",
    "addr:housenumber":"560",
    "addr:postcode":"1082",
    "addr:street":"Avenue Charles-Quint;/",
    "iso:country":"BE",
    "sg:address":"Avenue Charles-quint 560",
    "sg:city":"Sint-agatha-berchem/berchem-sainte-agathe",
    "sg:orig_category":"Assurances. Bureaux de poste",
    "sg:phone":"+32 2 465 72 72",
    "sg:postcode":"1082",
    "sg:province":"Bruxelles-Capitale",
    "wof:name":"La Poste",
    "wof:placetype":"venue"
},
  "geometry": {"coordinates":[4.2913331985,50.8709526062],"type":"Point"}
}