{
  "type": "Feature",
  "properties": {
    "iso:country":"BE",
    "sg:address":"Schoolstraat 35",
    "sg:city":"Zwalm",
    "sg:orig_category":"HUISBRANDOLIE",
    "sg:phone":"+32 55 49 94 17",
    "sg:postcode":"9636",
    "sg:province":"Oost-Vlaanderen",
    "wof:name":"Van Lancker",
    "wof:placetype":"venue"
},
  "geometry": {"coordinates":[3.6865370274,50.8861198425],"type":"Point"}
}