{
  "type": "Feature",
  "properties": {
    "addr:full":"Rue L\u00e9anne 102 Namur Namur 5000",
    "addr:housenumber":"102",
    "addr:postcode":"5000",
    "addr:street":"Rue Le\u0301Anne",
    "iso:country":"BE",
    "sg:address":"Rue L\u00e9anne 102",
    "sg:city":"Namur",
    "sg:classifiers":[
        {
            "category":"Building & Trades",
            "subcategory":"Construction",
            "type":"Services"
        }
    ],
    "sg:phone":"+32 81 22 19 09",
    "sg:postcode":"5000",
    "sg:province":"Namur",
    "sg:tags":[
        "surveyor",
        "-"
    ],
    "wof:name":"Merveille G",
    "wof:placetype":"venue"
},
  "geometry": {"coordinates":[4.8723192215,50.4718742371],"type":"Point"}
}