{
  "type": "Feature",
  "properties": {
    "addr:full":"Rue De Neufch\u00e2teau 14 Bastogne Luxembourg 6600",
    "addr:housenumber":"14",
    "addr:postcode":"6600",
    "addr:street":"Rue De Neufcha\u0302Teau",
    "iso:country":"BE",
    "sg:address":"Rue De Neufch\u00e2teau 14",
    "sg:city":"Bastogne",
    "sg:classifiers":[
        {
            "category":"Professional",
            "subcategory":"Art Services",
            "type":"Services"
        }
    ],
    "sg:phone":"+32 61 26 78 00",
    "sg:postcode":"6600",
    "sg:province":"Luxembourg",
    "sg:tags":[
        "model",
        "manufacturer"
    ],
    "wof:name":"Kit Ou Double",
    "wof:placetype":"venue"
},
  "geometry": {"coordinates":[5.7143278122,49.9996337891],"type":"Point"}
}