{
  "type": "Feature",
  "properties": {
    "iso:country":"BE",
    "sg:address":"Hasseltsesteenweg 103 Box 1",
    "sg:city":"Sint-truiden",
    "sg:classifiers":[
        {
            "category":"Arena",
            "subcategory":"Sports Club",
            "type":"Entertainment"
        }
    ],
    "sg:phone":"+32 11 69 68 23",
    "sg:postcode":"3800",
    "sg:province":"Limburg",
    "wof:name":"Stichting Omnisport Sint Joris Vzw",
    "wof:placetype":"venue"
},
  "geometry": {"coordinates":[5.2018060684,50.8288002014],"type":"Point"}
}