{
  "type": "Feature",
  "properties": {
    "iso:country":"BE",
    "sg:address":"Wijngaardstraat 12",
    "sg:city":"Kortrijk",
    "sg:orig_category":"Bloemen and planten",
    "sg:phone":"+32 56 21 05 44",
    "sg:postcode":"8500",
    "sg:province":"West-Vlaanderen",
    "wof:name":"Huis Elle\u00b4sig",
    "wof:placetype":"venue"
},
  "geometry": {"coordinates":[3.2691290379,50.825717926],"type":"Point"}
}