{
  "type": "Feature",
  "properties": {
    "iso:country":"BE",
    "sg:address":"Sint-catharinaplein 28",
    "sg:city":"Oostende",
    "sg:classifiers":[
        {
            "category":"Cafe",
            "type":"Food & Drink"
        }
    ],
    "sg:phone":"+32 59 50 72 14",
    "sg:postcode":"8400",
    "sg:province":"West-Vlaanderen",
    "sg:tags":[
        "caf\u00e9s"
    ],
    "wof:name":"Norbert Vanhoye",
    "wof:placetype":"venue"
},
  "geometry": {"coordinates":[2.9043679237,51.2168235779],"type":"Point"}
}