{
  "type": "Feature",
  "properties": {
    "iso:country":"BE",
    "sg:address":"Leopold Ii-laan 19",
    "sg:city":"Sint-niklaas",
    "sg:orig_category":"Bakstenen and dakpannen Fab Bouwmaterialen Gh",
    "sg:phone":"+32 3 777 61 11",
    "sg:postcode":"9100",
    "sg:province":"Oost-Vlaanderen",
    "wof:name":"Scheerders-van Kerchove Handelmaatschappij",
    "wof:placetype":"venue"
},
  "geometry": {"coordinates":[4.1457619667,51.1712760925],"type":"Point"}
}