{
  "type": "Feature",
  "properties": {
    "addr:full":"Chauss\u00e9e De Roodebeek 153 Bruxelles (woluwe-saint-lambert) Bruxelles-Capitale 1200",
    "addr:housenumber":"153",
    "addr:postcode":"1200",
    "addr:street":"Chausse\u0301E De Roodebeek",
    "iso:country":"BE",
    "sg:address":"Chauss\u00e9e De Roodebeek 153",
    "sg:city":"Bruxelles (woluwe-saint-lambert)",
    "sg:classifiers":[
        {
            "category":"Retail",
            "subcategory":"Laundry & Dry Cleaning",
            "type":"Services"
        }
    ],
    "sg:phone":"+32 2 771 02 27",
    "sg:postcode":"1200",
    "sg:province":"Bruxelles-Capitale",
    "wof:name":"Apere Blanchisserie",
    "wof:placetype":"venue"
},
  "geometry": {"coordinates":[4.4302568436,50.8487548828],"type":"Point"}
}