{
  "type": "Feature",
  "properties": {
    "iso:country":"BE",
    "sg:address":"Rue Des Awirs 209",
    "sg:city":"Flemalle",
    "sg:orig_category":"Maisons de repos and r\u00e9sidences",
    "sg:phone":"+32 4 275 72 96",
    "sg:postcode":"4400",
    "sg:province":"Li\u00e8ge",
    "wof:name":"Home La Rotonde",
    "wof:placetype":"venue"
},
  "geometry": {"coordinates":[5.3892731667,50.6146774292],"type":"Point"}
}