{
  "type": "Feature",
  "properties": {
    "iso:country":"BE",
    "sg:address":"Rue G\u00c9ol. Maurice Robert 10",
    "sg:city":"Beloeil",
    "sg:orig_category":"Paramedische behandelingen",
    "sg:phone":"+32 69 57 72 49",
    "sg:postcode":"7973",
    "sg:province":"Hainaut",
    "wof:name":"P. Conversano",
    "wof:placetype":"venue"
},
  "geometry": {"coordinates":[3.7236459255,50.5079841614],"type":"Point"}
}