{
  "type": "Feature",
  "properties": {
    "addr:full":"Moenaardestraat 78 Poperinge West-Vlaanderen 8972",
    "addr:housenumber":"78",
    "addr:postcode":"8972",
    "addr:street":"Moenaardestraat",
    "iso:country":"BE",
    "sg:address":"Moenaardestraat 78",
    "sg:city":"Poperinge",
    "sg:orig_category":"Banques and organismes de cr\u00e9dit",
    "sg:phone":"+32 57 30 10 01",
    "sg:postcode":"8972",
    "sg:province":"West-Vlaanderen",
    "wof:name":"Westkrediet",
    "wof:placetype":"venue"
},
  "geometry": {"coordinates":[2.6227750778,50.8971328735],"type":"Point"}
}