{
  "type": "Feature",
  "properties": {
    "addr:full":"Chauss\u00c9e De Mons 2 Ath Hainaut 7800",
    "addr:housenumber":"2",
    "addr:postcode":"7800",
    "addr:street":"Chausse\u0301E De Mons",
    "iso:country":"BE",
    "sg:address":"Chauss\u00c9e De Mons 2",
    "sg:city":"Ath",
    "sg:orig_category":"Dansscholen",
    "sg:phone":"+32 69 56 23 56",
    "sg:postcode":"7800",
    "sg:province":"Hainaut",
    "wof:name":"Diverty Dance Club",
    "wof:placetype":"venue"
},
  "geometry": {"coordinates":[3.7694530487,50.630695343],"type":"Point"}
}