{
  "type": "Feature",
  "properties": {
    "iso:country":"BE",
    "sg:address":"Zijstraat 3b3",
    "sg:city":"Roeselare",
    "sg:orig_category":"Paramedische behandelingen",
    "sg:phone":"+32 51 25 18 60",
    "sg:postcode":"8800",
    "sg:province":"West-Vlaanderen",
    "wof:name":"E. Devisch",
    "wof:placetype":"venue"
},
  "geometry": {"coordinates":[3.1273438931,50.9541625977],"type":"Point"}
}