{
  "type": "Feature",
  "properties": {
    "addr:full":"Langestraat 107 Nieuwpoort West-Vlaanderen 8620",
    "addr:housenumber":"107",
    "addr:postcode":"8620",
    "addr:street":"Langestraat",
    "iso:country":"BE",
    "sg:address":"Langestraat 107",
    "sg:city":"Nieuwpoort",
    "sg:orig_category":"Textiles. Eclairage et \u00e9quipements du foyer",
    "sg:phone":"+32 58 23 36 18",
    "sg:postcode":"8620",
    "sg:province":"West-Vlaanderen",
    "wof:name":"H. Hennebert",
    "wof:placetype":"venue"
},
  "geometry": {"coordinates":[2.7509260178,51.1323051453],"type":"Point"}
}