{
  "type": "Feature",
  "properties": {
    "iso:country":"BE",
    "sg:address":"Kloosterstraat 5",
    "sg:city":"Lede",
    "sg:classifiers":[
        {
            "category":"Health Services",
            "subcategory":"Nursing And Care Facility",
            "type":"Services"
        }
    ],
    "sg:phone":"+32 53 80 75 37",
    "sg:postcode":"9340",
    "sg:province":"Oost-Vlaanderen",
    "sg:tags":[
        "home"
    ],
    "wof:name":"Van Der Straeten C",
    "wof:placetype":"venue"
},
  "geometry": {"coordinates":[3.971613884,50.9725494385],"type":"Point"}
}