{
  "type": "Feature",
  "properties": {
    "addr:full":"Lindestraat 164ba Alken Limburg 3570",
    "addr:housenumber":"164ba",
    "addr:postcode":"3570",
    "addr:street":"Lindestraat",
    "iso:country":"BE",
    "sg:address":"Lindestraat 164ba",
    "sg:city":"Alken",
    "sg:orig_category":"Fruitteelt",
    "sg:phone":"+32 11 31 23 17",
    "sg:postcode":"3570",
    "sg:province":"Limburg",
    "wof:name":"Rita Gelade",
    "wof:placetype":"venue"
},
  "geometry": {"coordinates":[5.262966156,50.8973007202],"type":"Point"}
}