{
  "type": "Feature",
  "properties": {
    "iso:country":"BE",
    "sg:address":"Rue De L'avoine 10",
    "sg:city":"Namur",
    "sg:orig_category":"Plomberie, chauffage and installations sanitaires. Charpentes and couvertures",
    "sg:phone":"+32 81 22 17 37",
    "sg:postcode":"5100",
    "sg:province":"Namur",
    "wof:name":"Ets. Sottiaux Pierre",
    "wof:placetype":"venue"
},
  "geometry": {"coordinates":[4.8852720261,50.4491043091],"type":"Point"}
}