{
  "type": "Feature",
  "properties": {
    "addr:full":"Abdijstraat 6 Affligem Vlaams-Brabant 1790",
    "addr:housenumber":"6",
    "addr:postcode":"1790",
    "addr:street":"Abdijstraat",
    "iso:country":"BE",
    "sg:address":"Abdijstraat 6",
    "sg:city":"Affligem",
    "sg:orig_category":"Salles de spectacles",
    "sg:phone":"+32 53 66 70 25",
    "sg:postcode":"1790",
    "sg:province":"Vlaams-Brabant",
    "wof:name":"Cultureel Centrum",
    "wof:placetype":"venue"
},
  "geometry": {"coordinates":[4.1132040024,50.9245223999],"type":"Point"}
}