{
  "type": "Feature",
  "properties": {
    "iso:country":"BE",
    "sg:address":"Opeindestraat 72",
    "sg:city":"Kortessem",
    "sg:orig_category":"Producteurs de fruits",
    "sg:phone":"+32 11 37 66 23",
    "sg:postcode":"3720",
    "sg:province":"Limburg",
    "wof:name":"Gustaaf Maquoi",
    "wof:placetype":"venue"
},
  "geometry": {"coordinates":[5.3810429573,50.8532142639],"type":"Point"}
}