{
  "type": "Feature",
  "properties": {
    "iso:country":"BE",
    "sg:address":"Heimolenstraat 79",
    "sg:city":"Sint-niklaas",
    "sg:classifiers":[
        {
            "category":"Building & Trades",
            "subcategory":"Equipment Rental",
            "type":"Services"
        }
    ],
    "sg:phone":"+32 3 776 12 18",
    "sg:postcode":"9100",
    "sg:province":"Oost-Vlaanderen",
    "sg:tags":[
        "safety",
        "collective",
        "individual",
        "-"
    ],
    "wof:name":"Loquet Bvba",
    "wof:placetype":"venue"
},
  "geometry": {"coordinates":[4.1330299377,51.1424713135],"type":"Point"}
}