{
  "type": "Feature",
  "properties": {
    "addr:full":"Avenue Louis Lepoutre 55 Bruxelles (ixelles) Bruxelles-Capitale 1050",
    "addr:housenumber":"55",
    "addr:postcode":"1050",
    "addr:street":"Avenue Louis Lepoutre",
    "iso:country":"BE",
    "sg:address":"Avenue Louis Lepoutre 55",
    "sg:city":"Bruxelles (ixelles)",
    "sg:classifiers":[
        {
            "category":"Professional",
            "subcategory":"Art Services",
            "type":"Services"
        }
    ],
    "sg:phone":"+32 2 346 69 79",
    "sg:postcode":"1050",
    "sg:province":"Bruxelles-Capitale",
    "sg:tags":[
        "interior",
        "designer"
    ],
    "wof:name":"M.b.o.",
    "wof:placetype":"venue"
},
  "geometry": {"coordinates":[4.3571920395,50.8190498352],"type":"Point"}
}