{
  "type": "Feature",
  "properties": {
    "iso:country":"BE",
    "sg:address":"Sint-ermelindisstraat 14",
    "sg:city":"Hoegaarden",
    "sg:orig_category":"Salles de conf\u00e9rences and de r\u00e9ceptions. Caf\u00e9s",
    "sg:phone":"+32 16 76 61 71",
    "sg:postcode":"3320",
    "sg:province":"Vlaams-Brabant",
    "wof:name":"Sint-ermelindis Feestzaal",
    "wof:placetype":"venue"
},
  "geometry": {"coordinates":[4.8375668526,50.7882270813],"type":"Point"}
}