{
  "type": "Feature",
  "properties": {
    "iso:country":"BE",
    "sg:address":"Jezusstraat 15",
    "sg:city":"Antwerpen",
    "sg:classifiers":[
        {
            "category":"Home & Garden",
            "subcategory":"Household Appliances",
            "type":"Retail Goods"
        }
    ],
    "sg:phone":"+32 3 232 78 10",
    "sg:postcode":"2000",
    "sg:province":"Antwerpen",
    "sg:tags":[
        "housewares",
        "-"
    ],
    "wof:name":"Mathot-vanhoffelen",
    "wof:placetype":"venue"
},
  "geometry": {"coordinates":[4.4134249687,51.2190513611],"type":"Point"}
}