{
  "type": "Feature",
  "properties": {
    "iso:country":"BE",
    "sg:address":"Rue Saint-norbert 38-42",
    "sg:city":"Bruxelles (jette)",
    "sg:classifiers":[
        {
            "category":"Professional",
            "subcategory":"Printing & Photocopies",
            "type":"Services"
        }
    ],
    "sg:phone":"+32 2 478 78 81",
    "sg:postcode":"1090",
    "sg:province":"Bruxelles-Capitale",
    "sg:tags":[
        "digital"
    ],
    "wof:name":"This Sign Sa",
    "wof:placetype":"venue"
},
  "geometry": {"coordinates":[4.3373498917,50.8821144104],"type":"Point"}
}