{
  "type": "Feature",
  "properties": {
    "addr:full":"Vondel 17 Brecht Antwerpen 2960",
    "addr:housenumber":"17",
    "addr:postcode":"2960",
    "addr:street":"Vondel",
    "iso:country":"BE",
    "sg:address":"Vondel 17",
    "sg:city":"Brecht",
    "sg:orig_category":"Artiesten and kunstenaars",
    "sg:phone":"+32 3 289 80 81",
    "sg:postcode":"2960",
    "sg:province":"Antwerpen",
    "wof:name":"Josephus Van Britsom",
    "wof:placetype":"venue"
},
  "geometry": {"coordinates":[4.6415200233,51.3512115479],"type":"Point"}
}