{
  "type": "Feature",
  "properties": {
    "iso:country":"BE",
    "sg:address":"Avenue De La Pr\u00c9voyance 14",
    "sg:city":"Charleroi",
    "sg:orig_category":"Installation \u00e9lectrique r\u00e9sidentielle",
    "sg:phone":"+32 71 36 69 00",
    "sg:postcode":"6001",
    "sg:province":"Hainaut",
    "wof:name":"Iovino Rene",
    "wof:placetype":"venue"
},
  "geometry": {"coordinates":[4.4563322067,50.3804473877],"type":"Point"}
}