{
  "type": "Feature",
  "properties": {
    "iso:country":"BE",
    "sg:address":"Grand'rue Du Double Ecot 30c",
    "sg:city":"Lasne",
    "sg:orig_category":"Informaticaconsulenten",
    "sg:phone":"+32 2 633 65 77",
    "sg:postcode":"1380",
    "sg:province":"Brabant Wallon",
    "wof:name":"Vanderwilt Ph C.r.i.g.",
    "wof:placetype":"venue"
},
  "geometry": {"coordinates":[4.4784808159,50.6561355591],"type":"Point"}
}