{
  "type": "Feature",
  "properties": {
    "addr:full":"Rue Fond-des-roppes 1 Somme-leuze Namur 5377",
    "addr:housenumber":"1",
    "addr:postcode":"5377",
    "addr:street":"Rue Fond-Des-Roppes",
    "iso:country":"BE",
    "sg:address":"Rue Fond-des-roppes 1",
    "sg:city":"Somme-leuze",
    "sg:orig_category":"Installatie van houten of kunststof schrijnwerk",
    "sg:phone":"+32 83 68 85 52",
    "sg:postcode":"5377",
    "sg:province":"Namur",
    "wof:name":"Daniel Lissoir",
    "wof:placetype":"venue"
},
  "geometry": {"coordinates":[5.2549819946,50.2713890076],"type":"Point"}
}