{
  "type": "Feature",
  "properties": {
    "iso:country":"BE",
    "sg:address":"Avenue Jean Sobieski 44 Box 5",
    "sg:city":"Bruxelles",
    "sg:classifiers":[
        {
            "category":"Insurance",
            "subcategory":"Insurance Agent",
            "type":"Services"
        }
    ],
    "sg:phone":"+32 2 479 17 77",
    "sg:postcode":"1020",
    "sg:province":"Bruxelles-Capitale",
    "sg:tags":[
        "broker"
    ],
    "wof:name":"Reynaers Marc Nv",
    "wof:placetype":"venue"
},
  "geometry": {"coordinates":[4.3444271088,50.8888092041],"type":"Point"}
}