{
  "type": "Feature",
  "properties": {
    "iso:country":"BE",
    "sg:address":"Chauss\u00c9e De Wavre 48",
    "sg:city":"Wanze",
    "sg:orig_category":"Schoonheidssalons",
    "sg:phone":"+32 85 25 58 98",
    "sg:postcode":"4520",
    "sg:province":"Li\u00e8ge",
    "wof:name":"Institut Nath\u00c9a",
    "wof:placetype":"venue"
},
  "geometry": {"coordinates":[5.2151827812,50.536781311],"type":"Point"}
}