{
  "type": "Feature",
  "properties": {
    "iso:country":"BE",
    "sg:address":"Rue G\u00e9rard Dubois 44",
    "sg:city":"Ath",
    "sg:classifiers":[
        {
            "category":"Banks & Credit Unions",
            "subcategory":"Investment Brokerage",
            "type":"Services"
        }
    ],
    "sg:phone":"+32 68 84 08 39",
    "sg:postcode":"7800",
    "sg:province":"Hainaut",
    "sg:tags":[
        "ladies'",
        "tailor",
        "tailoresses",
        "-",
        "clothing"
    ],
    "wof:name":"Deloy R",
    "wof:placetype":"venue"
},
  "geometry": {"coordinates":[3.7733669281,50.6334495544],"type":"Point"}
}