{
  "type": "Feature",
  "properties": {
    "iso:country":"BE",
    "sg:address":"Kerkplein 5",
    "sg:city":"Lanaken",
    "sg:orig_category":"Telecommunicatiesystemen",
    "sg:phone":"+32 89 73 15 59",
    "sg:postcode":"3620",
    "sg:province":"Limburg",
    "wof:name":"Allcom Service",
    "wof:placetype":"venue"
},
  "geometry": {"coordinates":[5.6336631775,50.8638496399],"type":"Point"}
}