{
  "type": "Feature",
  "properties": {
    "addr:full":"Grasmarkt 11 Brussel/bruxelles Bruxelles-Capitale 1000",
    "addr:housenumber":"11",
    "addr:postcode":"1000",
    "addr:street":"Grasmarkt;/",
    "iso:country":"BE",
    "sg:address":"Grasmarkt 11",
    "sg:city":"Brussel/bruxelles",
    "sg:orig_category":"Herenkledingzaken",
    "sg:phone":"+32 2 503 24 74",
    "sg:postcode":"1000",
    "sg:province":"Bruxelles-Capitale",
    "wof:name":"Maison Coton",
    "wof:placetype":"venue"
},
  "geometry": {"coordinates":[4.3522539139,50.8479766846],"type":"Point"}
}