{
  "type": "Feature",
  "properties": {
    "iso:country":"BE",
    "sg:address":"Voskensstraat 50",
    "sg:city":"Geraardsbergen",
    "sg:orig_category":"Jardinage",
    "sg:phone":"+32 54 41 61 19",
    "sg:postcode":"9500",
    "sg:province":"Oost-Vlaanderen",
    "wof:name":"Van Der Linden Tuinbouw",
    "wof:placetype":"venue"
},
  "geometry": {"coordinates":[3.8776700497,50.7622299194],"type":"Point"}
}