{
  "type": "Feature",
  "properties": {
    "addr:full":"Avenue De Merode 4 Wavre Brabant Wallon 1300",
    "addr:housenumber":"4;1300",
    "addr:street":"Avenue De Merode",
    "iso:country":"BE",
    "sg:address":"Avenue De Merode 4",
    "sg:city":"Wavre",
    "sg:orig_category":"Alimentation sp\u00e9cialis\u00e9e. Supermarch\u00e9s",
    "sg:phone":"+32 10 41 03 16",
    "sg:postcode":"1300",
    "sg:province":"Brabant Wallon",
    "wof:name":"Louis Delhaize",
    "wof:placetype":"venue"
},
  "geometry": {"coordinates":[4.6116552353,50.7134132385],"type":"Point"}
}