{
  "type": "Feature",
  "properties": {
    "iso:country":"BE",
    "sg:address":"Kruiningestraat 14-16",
    "sg:city":"Antwerpen (deurne)",
    "sg:classifiers":[
        {
            "category":"Autos & Motor Vehicles",
            "subcategory":"Automobile Sales",
            "type":"Retail Goods"
        }
    ],
    "sg:phone":"+32 3 324 58 17",
    "sg:postcode":"2100",
    "sg:province":"Antwerpen",
    "sg:tags":[
        "car",
        "used",
        "-"
    ],
    "wof:name":"Nijsmans Carrosserie Nv",
    "wof:placetype":"venue"
},
  "geometry": {"coordinates":[4.4586100578,51.2203941345],"type":"Point"}
}