{
  "type": "Feature",
  "properties": {
    "addr:full":"Kleine Hellekensstraat 48d Box 4 Zonhoven Limburg 3520",
    "addr:housenumber":"48d",
    "addr:postcode":"3520",
    "addr:street":"Hellekensstraat;Box 4",
    "iso:country":"BE",
    "sg:address":"Kleine Hellekensstraat 48d Box 4",
    "sg:city":"Zonhoven",
    "sg:classifiers":[
        {
            "category":"Building & Trades",
            "subcategory":"Plumbing",
            "type":"Services"
        }
    ],
    "sg:phone":"+32 11 82 37 90",
    "sg:postcode":"3520",
    "sg:province":"Limburg",
    "sg:tags":[
        "repair",
        "mainten",
        "-",
        "central",
        "heating"
    ],
    "wof:name":"Broux J",
    "wof:placetype":"venue"
},
  "geometry": {"coordinates":[5.3614449501,50.9823417664],"type":"Point"}
}