{
  "type": "Feature",
  "properties": {
    "iso:country":"BE",
    "sg:address":"Avenue D'andrimont 3",
    "sg:city":"Bruxelles (uccle)",
    "sg:classifiers":[
        {
            "category":"Education",
            "subcategory":"School",
            "type":"Public Place"
        }
    ],
    "sg:phone":"+32 2 374 52 60",
    "sg:postcode":"1180",
    "sg:province":"Bruxelles-Capitale",
    "sg:tags":[
        "-",
        "private"
    ],
    "wof:name":"Centre De Mise Au Point & Aide Scolaire",
    "wof:placetype":"venue"
},
  "geometry": {"coordinates":[4.365377903,50.789691925],"type":"Point"}
}