{
  "type": "Feature",
  "properties": {
    "addr:full":"Rue Horloz 18 Saint-nicolas Li\u00e8ge 4420",
    "addr:housenumber":"18",
    "addr:postcode":"4420",
    "addr:street":"Rue Horloz",
    "iso:country":"BE",
    "sg:address":"Rue Horloz 18",
    "sg:city":"Saint-nicolas",
    "sg:classifiers":[
        {
            "category":"Restaurant",
            "type":"Food & Drink"
        }
    ],
    "sg:phone":"+32 4 234 01 49",
    "sg:postcode":"4420",
    "sg:province":"Li\u00e8ge",
    "sg:tags":[
        "caf\u00e9s"
    ],
    "wof:name":"Taverne Du Horloz",
    "wof:placetype":"venue"
},
  "geometry": {"coordinates":[5.5314331055,50.6289787292],"type":"Point"}
}