{
  "type": "Feature",
  "properties": {
    "addr:full":"Yzerhand 9 Beveren (beveren-waas) Oost-Vlaanderen 9120",
    "addr:housenumber":"9",
    "addr:postcode":"9120",
    "addr:street":"Yzerhand;Oost-Vlaanderen",
    "iso:country":"BE",
    "sg:address":"Yzerhand 9",
    "sg:city":"Beveren (beveren-waas)",
    "sg:classifiers":[
        {
            "category":"Travel",
            "subcategory":"Travel Agent",
            "type":"Entertainment"
        }
    ],
    "sg:phone":"+32 3 755 01 74",
    "sg:postcode":"9120",
    "sg:province":"Oost-Vlaanderen",
    "sg:tags":[
        "agency"
    ],
    "wof:name":"Joly Travel",
    "wof:placetype":"venue"
},
  "geometry": {"coordinates":[4.2523560524,51.215133667],"type":"Point"}
}