{
  "type": "Feature",
  "properties": {
    "addr:full":"Rue Moraifosse 12 Verviers Li\u00e8ge 4802",
    "addr:housenumber":"12",
    "addr:postcode":"4802",
    "addr:street":"Rue Moraifosse",
    "iso:country":"BE",
    "sg:address":"Rue Moraifosse 12",
    "sg:city":"Verviers",
    "sg:orig_category":"V\u00e9t\u00e9rinaires",
    "sg:phone":"+32 87 22 93 55",
    "sg:postcode":"4802",
    "sg:province":"Li\u00e8ge",
    "wof:name":"Micheline Nielsen",
    "wof:placetype":"venue"
},
  "geometry": {"coordinates":[5.8671250343,50.5714111328],"type":"Point"}
}