{
  "type": "Feature",
  "properties": {
    "addr:full":"Linkebeeksedreef 43 Sint-genesius-rode/rhode-saint-genese Vlaams-Brabant 1640",
    "addr:housenumber":"43",
    "addr:postcode":"1640",
    "addr:street":"Linkebeeksedreef",
    "iso:country":"BE",
    "sg:address":"Linkebeeksedreef 43",
    "sg:city":"Sint-genesius-rode/rhode-saint-genese",
    "sg:orig_category":"Landmeters",
    "sg:phone":"+32 2 358 18 82",
    "sg:postcode":"1640",
    "sg:province":"Vlaams-Brabant",
    "wof:name":"Patrice Wirtz/patrick Wirtz",
    "wof:placetype":"venue"
},
  "geometry": {"coordinates":[4.3730578423,50.7597770691],"type":"Point"}
}