{
  "type": "Feature",
  "properties": {
    "iso:country":"BE",
    "sg:address":"Ratelingestraat 18",
    "sg:city":"Wingene",
    "sg:orig_category":"Eleveurs and marchands de porcs. Eleveurs de bovins",
    "sg:phone":"+32 51 65 59 48",
    "sg:postcode":"8750",
    "sg:province":"West-Vlaanderen",
    "wof:name":"Lionel Danneels",
    "wof:placetype":"venue"
},
  "geometry": {"coordinates":[3.2745831013,51.0384674072],"type":"Point"}
}