{
  "type": "Feature",
  "properties": {
    "iso:country":"BE",
    "sg:address":"Oude Bruggeweg 33",
    "sg:city":"Lichtervelde",
    "sg:orig_category":"Non-Classified Establishments",
    "sg:phone":"+32 51 72 25 68",
    "sg:postcode":"8810",
    "sg:province":"West-Vlaanderen",
    "wof:name":"Colpaert N",
    "wof:placetype":"venue"
},
  "geometry": {"coordinates":[3.1483631134,51.0408782959],"type":"Point"}
}