{
  "type": "Feature",
  "properties": {
    "addr:full":"Rue Albert De Latour 19 Bruxelles (schaerbeek) Bruxelles-Capitale 1030",
    "addr:housenumber":"19",
    "addr:postcode":"1030",
    "addr:street":"Rue Albert De Latour",
    "iso:country":"BE",
    "sg:address":"Rue Albert De Latour 19",
    "sg:city":"Bruxelles (schaerbeek)",
    "sg:classifiers":[
        {
            "category":"Health Services",
            "subcategory":"Health Practitioner",
            "type":"Services"
        }
    ],
    "sg:phone":"+32 2 245 03 16",
    "sg:postcode":"1030",
    "sg:province":"Bruxelles-Capitale",
    "sg:tags":[
        "physiotherapist"
    ],
    "wof:name":"Guislain B\u00e9n\u00e9dicte",
    "wof:placetype":"venue"
},
  "geometry": {"coordinates":[4.3806180954,50.8549461365],"type":"Point"}
}