{
  "type": "Feature",
  "properties": {
    "addr:full":"Rue De Bellevue 3 Sivry-rance Hainaut 6470",
    "addr:housenumber":"3",
    "addr:postcode":"6470",
    "addr:street":"Rue De Bellevue",
    "iso:country":"BE",
    "sg:address":"Rue De Bellevue 3",
    "sg:city":"Sivry-rance",
    "sg:orig_category":"Eleveurs de bovins",
    "sg:phone":"+32 60 45 53 36",
    "sg:postcode":"6470",
    "sg:province":"Hainaut",
    "wof:name":"Marie Buchet",
    "wof:placetype":"venue"
},
  "geometry": {"coordinates":[4.2078847885,50.2032737732],"type":"Point"}
}