{
  "type": "Feature",
  "properties": {
    "iso:country":"BE",
    "sg:address":"Rue Lambert Dewonck 205",
    "sg:city":"Ans",
    "sg:orig_category":"Cr\u00e9dits divers",
    "sg:postcode":"4432",
    "sg:province":"Li\u00e8ge",
    "wof:name":"Bancontact-mister Cash",
    "wof:placetype":"venue"
},
  "geometry": {"coordinates":[5.5124988556,50.6646499634],"type":"Point"}
}