{
  "type": "Feature",
  "properties": {
    "iso:country":"BE",
    "sg:address":"Ingberthoeveweg 6",
    "sg:city":"Aartselaar",
    "sg:classifiers":[
        {
            "category":"Professional",
            "type":"Services"
        }
    ],
    "sg:phone":"+32 3 450 18 18",
    "sg:postcode":"2630",
    "sg:province":"Antwerpen",
    "sg:tags":[
        "leasing"
    ],
    "wof:name":"Ing Car Lease Belgium Nv",
    "wof:placetype":"venue"
},
  "geometry": {"coordinates":[4.3966560364,51.1490440369],"type":"Point"}
}