{
  "type": "Feature",
  "properties": {
    "addr:full":"Turnhoutsebaan 550b Wijnegem Antwerpen 2110",
    "addr:housenumber":"550b",
    "addr:postcode":"2110",
    "addr:street":"Turnhoutsebaan",
    "iso:country":"BE",
    "sg:address":"Turnhoutsebaan 550b",
    "sg:city":"Wijnegem",
    "sg:classifiers":[
        {
            "category":"Manufacturing",
            "subcategory":"Signs",
            "type":"Manufacturing & Wholesale Goods"
        }
    ],
    "sg:phone":"+32 3 354 02 35",
    "sg:postcode":"2110",
    "sg:province":"Antwerpen",
    "sg:tags":[
        "-",
        "illuminated"
    ],
    "wof:name":"Neon Gilsi",
    "wof:placetype":"venue"
},
  "geometry": {"coordinates":[4.5392642021,51.2282524109],"type":"Point"}
}