{
  "type": "Feature",
  "properties": {
    "iso:country":"BE",
    "sg:address":"Tolstraat 10",
    "sg:city":"Kortrijk",
    "sg:classifiers":[
        {
            "category":"Cafe",
            "type":"Food & Drink"
        }
    ],
    "sg:phone":"+32 56 22 17 27",
    "sg:postcode":"8500",
    "sg:province":"West-Vlaanderen",
    "sg:tags":[
        "caf\u00e9s"
    ],
    "wof:name":"Sportpaleis",
    "wof:placetype":"venue"
},
  "geometry": {"coordinates":[3.2626779079,50.8249282837],"type":"Point"}
}