{
  "type": "Feature",
  "properties": {
    "iso:country":"BE",
    "sg:address":"Elf Novemberlaan 3",
    "sg:city":"Lochristi",
    "sg:classifiers":[
        {
            "category":"Health Services",
            "subcategory":"Health Practitioner",
            "type":"Services"
        }
    ],
    "sg:phone":"+32 9 355 75 53",
    "sg:postcode":"9080",
    "sg:province":"Oost-Vlaanderen",
    "sg:tags":[
        "physiotherapist"
    ],
    "wof:name":"Van Hoecke M",
    "wof:placetype":"venue"
},
  "geometry": {"coordinates":[3.832201004,51.1028709412],"type":"Point"}
}