{
  "type": "Feature",
  "properties": {
    "addr:full":"Tolpoortstraat 82 Deinze Oost-Vlaanderen 9800",
    "addr:housenumber":"82",
    "addr:postcode":"9800",
    "addr:street":"Tolpoortstraat",
    "iso:country":"BE",
    "sg:address":"Tolpoortstraat 82",
    "sg:city":"Deinze",
    "sg:orig_category":"V\u00eatements",
    "sg:phone":"+32 9 386 37 78",
    "sg:postcode":"9800",
    "sg:province":"Oost-Vlaanderen",
    "wof:name":"Ly's Fashion",
    "wof:placetype":"venue"
},
  "geometry": {"coordinates":[3.5302259922,50.9800415039],"type":"Point"}
}