{
  "type": "Feature",
  "properties": {
    "addr:full":"Haachtsebaan 27 Keerbergen Vlaams-Brabant 3140",
    "addr:housenumber":"27",
    "addr:postcode":"3140",
    "addr:street":"Haachtsebaan",
    "iso:country":"BE",
    "sg:address":"Haachtsebaan 27",
    "sg:city":"Keerbergen",
    "sg:classifiers":[
        {
            "category":"Personal",
            "subcategory":"Beauty Salon",
            "type":"Services"
        }
    ],
    "sg:phone":"+32 15 51 28 33",
    "sg:postcode":"3140",
    "sg:province":"Vlaams-Brabant",
    "sg:tags":[
        "lady",
        "-",
        "hairdressing"
    ],
    "wof:name":"Kreatos",
    "wof:placetype":"venue"
},
  "geometry": {"coordinates":[4.6307191849,51.0040969849],"type":"Point"}
}