{
  "type": "Feature",
  "properties": {
    "iso:country":"BE",
    "sg:address":"Grand'place 12",
    "sg:city":"Binche",
    "sg:classifiers":[
        {
            "category":"Fast Food",
            "type":"Food & Drink"
        }
    ],
    "sg:phone":"+32 64 33 72 22",
    "sg:postcode":"7130",
    "sg:province":"Hainaut",
    "sg:tags":[
        "\u00c0",
        "restaurants",
        "emporter",
        "restaurant"
    ],
    "wof:name":"China Town",
    "wof:placetype":"venue"
},
  "geometry": {"coordinates":[4.1649107933,50.4107818604],"type":"Point"}
}