{
  "type": "Feature",
  "properties": {
    "iso:country":"BE",
    "sg:address":"Kleine Hemmenweg 36",
    "sg:city":"Zonhoven",
    "sg:classifiers":[
        {
            "category":"Government",
            "subcategory":"Fire Station",
            "type":"Public Place"
        }
    ],
    "sg:phone":"+32 11 81 35 54",
    "sg:postcode":"3520",
    "sg:province":"Limburg",
    "sg:tags":[
        "installation",
        "-",
        "air conditioning"
    ],
    "wof:name":"Misaya Bogaerts",
    "wof:placetype":"venue"
},
  "geometry": {"coordinates":[5.3763542175,50.9974937439],"type":"Point"}
}