{
  "type": "Feature",
  "properties": {
    "iso:country":"BE",
    "sg:address":"Aachenerstraat",
    "sg:city":"Raeren",
    "sg:orig_category":"Meubles Fab",
    "sg:phone":"+32 87 65 34 68",
    "sg:postcode":"4730",
    "sg:province":"Li\u00e8ge",
    "wof:name":"Eicher Belgium",
    "wof:placetype":"venue"
},
  "geometry": {"coordinates":[6.0674948692,50.6674995422],"type":"Point"}
}