{
  "type": "Feature",
  "properties": {
    "addr:full":"Maria-christinastraat 182 Brussel/bruxelles Bruxelles-Capitale 1020",
    "addr:housenumber":"182",
    "addr:postcode":"1020",
    "addr:street":"Maria-Christinastraat;/",
    "iso:country":"BE",
    "sg:address":"Maria-christinastraat 182",
    "sg:city":"Brussel/bruxelles",
    "sg:classifiers":[
        {
            "category":"Shopping",
            "subcategory":"Clothing, Apparel, & Fashions",
            "type":"Retail Goods"
        }
    ],
    "sg:phone":"+32 2 425 83 69",
    "sg:postcode":"1020",
    "sg:province":"Bruxelles-Capitale",
    "sg:tags":[
        "ondergoed",
        "lingerie"
    ],
    "wof:name":"Damart",
    "wof:placetype":"venue"
},
  "geometry": {"coordinates":[4.3509907722,50.8762397766],"type":"Point"}
}