{
  "type": "Feature",
  "properties": {
    "addr:full":"Stationsstraat 4 Ninove Oost-Vlaanderen 9400",
    "addr:housenumber":"4",
    "addr:postcode":"9400",
    "addr:street":"Stationsstraat",
    "iso:country":"BE",
    "sg:address":"Stationsstraat 4",
    "sg:city":"Ninove",
    "sg:orig_category":"V\u00eatements",
    "sg:phone":"+32 54 33 42 36",
    "sg:postcode":"9400",
    "sg:province":"Oost-Vlaanderen",
    "wof:name":"Pelzen",
    "wof:placetype":"venue"
},
  "geometry": {"coordinates":[4.0228819847,50.8376197815],"type":"Point"}
}