{
  "type": "Feature",
  "properties": {
    "addr:full":"Rue L\u00c9on-mathieu 54 Gedinne Namur 5575",
    "addr:housenumber":"54",
    "addr:postcode":"5575",
    "addr:street":"Rue Le\u0301On-Mathieu",
    "iso:country":"BE",
    "sg:address":"Rue L\u00c9on-mathieu 54",
    "sg:city":"Gedinne",
    "sg:orig_category":"Artsen and specialisten",
    "sg:phone":"+32 61 58 71 60",
    "sg:postcode":"5575",
    "sg:province":"Namur",
    "wof:name":"M. Keyaert",
    "wof:placetype":"venue"
},
  "geometry": {"coordinates":[4.882598877,49.9893455505],"type":"Point"}
}