{
  "type": "Feature",
  "properties": {
    "addr:full":"Chaussee De Wavre 362 Grez-doiceau Brabant Wallon 1390",
    "addr:housenumber":"362",
    "addr:postcode":"1390",
    "addr:street":"Chaussee De Wavre",
    "iso:country":"BE",
    "sg:address":"Chaussee De Wavre 362",
    "sg:city":"Grez-doiceau",
    "sg:classifiers":[
        {
            "category":"Organizations",
            "subcategory":"Labor Organization",
            "type":"Services"
        }
    ],
    "sg:phone":"+32 10 84 47 85",
    "sg:postcode":"1390",
    "sg:province":"Brabant Wallon",
    "sg:tags":[
        "on-site",
        "waste-water",
        "treatment",
        "system"
    ],
    "wof:name":"Technox-equipement S.a.",
    "wof:placetype":"venue"
},
  "geometry": {"coordinates":[4.6538910866,50.7361907959],"type":"Point"}
}