{
  "type": "Feature",
  "properties": {
    "addr:full":"Koninklijke Baan 186 Koksijde West-Vlaanderen 8670",
    "addr:housenumber":"186",
    "addr:postcode":"8670",
    "addr:street":"Koninklijke Baan",
    "iso:country":"BE",
    "sg:address":"Koninklijke Baan 186",
    "sg:city":"Koksijde",
    "sg:orig_category":"S\u00e9curit\u00e9 sociale",
    "sg:phone":"+32 58 51 62 40",
    "sg:postcode":"8670",
    "sg:province":"West-Vlaanderen",
    "wof:name":"Westvl. Liberaal Ziekenf.",
    "wof:placetype":"venue"
},
  "geometry": {"coordinates":[2.6319880486,51.1190605164],"type":"Point"}
}