{
  "type": "Feature",
  "properties": {
    "iso:country":"BE",
    "sg:address":"Bovenrij 30",
    "sg:city":"Herentals",
    "sg:classifiers":[
        {
            "category":"Education",
            "subcategory":"School",
            "type":"Public Place"
        }
    ],
    "sg:phone":"+32 14 25 95 30",
    "sg:postcode":"2200",
    "sg:province":"Antwerpen",
    "sg:tags":[
        "secondary"
    ],
    "wof:name":"Francesco Paviljoen",
    "wof:placetype":"venue"
},
  "geometry": {"coordinates":[4.8379597664,51.1745986938],"type":"Point"}
}