{
  "type": "Feature",
  "properties": {
    "addr:full":"Rue De Waroux 23b Li\u00e8ge 1 Li\u00e8ge 4000",
    "addr:housenumber":"23b;1",
    "addr:postcode":"4000",
    "addr:street":"Rue De Waroux",
    "iso:country":"BE",
    "sg:address":"Rue De Waroux 23b",
    "sg:city":"Li\u00e8ge 1",
    "sg:classifiers":[
        {
            "category":"Shopping",
            "subcategory":"Stationery & Office Supplies",
            "type":"Retail Goods"
        }
    ],
    "sg:phone":"+32 4 224 53 53",
    "sg:postcode":"4000",
    "sg:province":"Li\u00e8ge",
    "sg:tags":[
        "partition"
    ],
    "wof:name":"Europlex Sa",
    "wof:placetype":"venue"
},
  "geometry": {"coordinates":[5.555975914,50.6437606812],"type":"Point"}
}