{
  "type": "Feature",
  "properties": {
    "addr:full":"Blekerijstraat 120 Izegem West-Vlaanderen 8870",
    "addr:housenumber":"120",
    "addr:postcode":"8870",
    "addr:street":"Blekerijstraat",
    "iso:country":"BE",
    "sg:address":"Blekerijstraat 120",
    "sg:city":"Izegem",
    "sg:orig_category":"Slagers",
    "sg:phone":"+32 51 30 26 61",
    "sg:postcode":"8870",
    "sg:province":"West-Vlaanderen",
    "wof:name":"Roger Witdouck",
    "wof:placetype":"venue"
},
  "geometry": {"coordinates":[3.1997909546,50.9021759033],"type":"Point"}
}