{
  "type": "Feature",
  "properties": {
    "addr:full":"Ring 2 Pepingen Vlaams-Brabant 1670",
    "addr:housenumber":"2",
    "addr:postcode":"1670",
    "addr:street":"Ring",
    "iso:country":"BE",
    "sg:address":"Ring 2",
    "sg:city":"Pepingen",
    "sg:orig_category":"Avocats and conseillers juridiques",
    "sg:phone":"+32 2 361 37 02",
    "sg:postcode":"1670",
    "sg:province":"Vlaams-Brabant",
    "wof:name":"P. De Jonghe",
    "wof:placetype":"venue"
},
  "geometry": {"coordinates":[4.136370182,50.7397346497],"type":"Point"}
}