{
  "type": "Feature",
  "properties": {
    "addr:full":"Brusselsestraat 11 Dendermonde Oost-Vlaanderen 9200",
    "addr:housenumber":"11",
    "addr:postcode":"9200",
    "addr:street":"Brusselsestraat;Oost-Vlaanderen",
    "iso:country":"BE",
    "sg:address":"Brusselsestraat 11",
    "sg:city":"Dendermonde",
    "sg:orig_category":"Boekhandels",
    "sg:phone":"+32 52 21 56 38",
    "sg:postcode":"9200",
    "sg:province":"Oost-Vlaanderen",
    "wof:name":"Boekhandel Reinaert",
    "wof:placetype":"venue"
},
  "geometry": {"coordinates":[4.0989699364,51.0286865234],"type":"Point"}
}