{
  "type": "Feature",
  "properties": {
    "addr:full":"Tongersestraat 11 Borgloon Limburg 3840",
    "addr:housenumber":"11",
    "addr:postcode":"3840",
    "addr:street":"Tongersestraat",
    "iso:country":"BE",
    "sg:address":"Tongersestraat 11",
    "sg:city":"Borgloon",
    "sg:classifiers":[
        {
            "category":"Bars & Pubs",
            "type":"Food & Drink"
        }
    ],
    "sg:phone":"+32 12 74 72 43",
    "sg:postcode":"3840",
    "sg:province":"Limburg",
    "sg:tags":[
        "tavern"
    ],
    "wof:name":"Konak Taverne",
    "wof:placetype":"venue"
},
  "geometry": {"coordinates":[5.3469219208,50.8021850586],"type":"Point"}
}