{
  "type": "Feature",
  "properties": {
    "iso:country":"BE",
    "sg:address":"Zwaluwneststraat 8",
    "sg:city":"Zedelgem",
    "sg:orig_category":"Sportclubs",
    "sg:phone":"+32 50 24 03 32",
    "sg:postcode":"8210",
    "sg:province":"West-Vlaanderen",
    "wof:name":"Basket West-vlaanderen",
    "wof:placetype":"venue"
},
  "geometry": {"coordinates":[3.1426808834,51.1345024109],"type":"Point"}
}