{
  "type": "Feature",
  "properties": {
    "iso:country":"BE",
    "sg:address":"Rue Neuve 57",
    "sg:city":"Chiny (jamoigne)",
    "sg:classifiers":[
        {
            "category":"Health Services",
            "subcategory":"Doctor",
            "type":"Services"
        }
    ],
    "sg:phone":"+32 61 32 93 86",
    "sg:postcode":"6810",
    "sg:province":"Luxembourg",
    "sg:tags":[
        "medicinephysicians",
        "surgeon"
    ],
    "wof:name":"Jacquemart Pascaline",
    "wof:placetype":"venue"
},
  "geometry": {"coordinates":[5.3405580521,49.7382736206],"type":"Point"}
}