{
  "type": "Feature",
  "properties": {
    "iso:country":"BE",
    "sg:address":"Rue Trixhelette 18",
    "sg:city":"Verlaine",
    "sg:orig_category":"Paramedische behandelingen",
    "sg:phone":"+32 4 259 50 17",
    "sg:postcode":"4537",
    "sg:province":"Li\u00e8ge",
    "wof:name":"M. Hermann",
    "wof:placetype":"venue"
},
  "geometry": {"coordinates":[5.298101902,50.5867118835],"type":"Point"}
}