{
  "type": "Feature",
  "properties": {
    "iso:country":"BE",
    "sg:address":"Landbouwstraat 2",
    "sg:city":"Niel",
    "sg:classifiers":[
        {
            "category":"Education",
            "subcategory":"University",
            "type":"Public Place"
        }
    ],
    "sg:phone":"+32 3 844 02 16",
    "sg:postcode":"2845",
    "sg:province":"Antwerpen",
    "sg:tags":[
        "adult"
    ],
    "wof:name":"Kunstacademie Niel",
    "wof:placetype":"venue"
},
  "geometry": {"coordinates":[4.3304381371,51.1071014404],"type":"Point"}
}