{
  "type": "Feature",
  "properties": {
    "addr:full":"Chauss\u00c9e De Tongres 532 Li\u00c8ge Li\u00e8ge 4000",
    "addr:housenumber":"532",
    "addr:postcode":"4000",
    "addr:street":"Chausse\u0301E De Tongres",
    "iso:country":"BE",
    "sg:address":"Chauss\u00c9e De Tongres 532",
    "sg:city":"Li\u00c8ge",
    "sg:classifiers":[
        {
            "category":"Banks & Credit Unions",
            "subcategory":"Investment Brokerage",
            "type":"Services"
        }
    ],
    "sg:phone":"+32 4 247 57 70",
    "sg:postcode":"4000",
    "sg:province":"Li\u00e8ge",
    "sg:tags":[
        "de",
        "restaurant",
        "food",
        "organisation",
        "\u00c0",
        "fast",
        "catering",
        "emporter",
        "salles",
        "restaurants",
        "f\u00cates",
        "con"
    ],
    "wof:name":"La Petite Brasserie",
    "wof:placetype":"venue"
},
  "geometry": {"coordinates":[5.5616159439,50.66381073],"type":"Point"}
}