{
  "type": "Feature",
  "properties": {
    "addr:full":"Mechelbaan 667 Putte Antwerpen 2580",
    "addr:housenumber":"667",
    "addr:postcode":"2580",
    "addr:street":"Mechelbaan",
    "iso:country":"BE",
    "sg:address":"Mechelbaan 667",
    "sg:city":"Putte",
    "sg:classifiers":[
        {
            "category":"Home & Garden",
            "subcategory":"Kitchen Supply",
            "type":"Retail Goods"
        }
    ],
    "sg:phone":"+32 15 75 63 11",
    "sg:postcode":"2580",
    "sg:province":"Antwerpen",
    "sg:tags":[
        "fitted"
    ],
    "wof:name":"Vertommen Nv",
    "wof:placetype":"venue"
},
  "geometry": {"coordinates":[4.6095142365,51.0480461121],"type":"Point"}
}