{
  "type": "Feature",
  "properties": {
    "addr:full":"Koetsweg 260 Leuven Vlaams-Brabant 3010",
    "addr:housenumber":"260",
    "addr:postcode":"3010",
    "addr:street":"Koetsweg",
    "iso:country":"BE",
    "sg:address":"Koetsweg 260",
    "sg:city":"Leuven",
    "sg:orig_category":"Sportclubs",
    "sg:phone":"+32 16 25 08 42",
    "sg:postcode":"3010",
    "sg:province":"Vlaams-Brabant",
    "wof:name":"T.s.c. Heidepark",
    "wof:placetype":"venue"
},
  "geometry": {"coordinates":[4.7304501534,50.889755249],"type":"Point"}
}