{
  "type": "Feature",
  "properties": {
    "addr:full":"Vosken 41 Lubbeek Vlaams-Brabant 3210",
    "addr:housenumber":"41",
    "addr:postcode":"3210",
    "addr:street":"Vosken",
    "iso:country":"BE",
    "sg:address":"Vosken 41",
    "sg:city":"Lubbeek",
    "sg:orig_category":"Boekhouders",
    "sg:phone":"+32 16 62 21 89",
    "sg:postcode":"3210",
    "sg:province":"Vlaams-Brabant",
    "wof:name":"Michel Van Cauwenbergh",
    "wof:placetype":"venue"
},
  "geometry": {"coordinates":[4.8427481651,50.9041557312],"type":"Point"}
}