{
  "type": "Feature",
  "properties": {
    "iso:country":"BE",
    "sg:address":"Ottergemdorp 47",
    "sg:city":"Erpe-mere (ottergem)",
    "sg:classifiers":[
        {
            "category":"Building & Trades",
            "subcategory":"Construction",
            "type":"Services"
        }
    ],
    "sg:phone":"+32 53 80 11 24",
    "sg:postcode":"9420",
    "sg:province":"Oost-Vlaanderen",
    "sg:tags":[
        "surveyor",
        "-"
    ],
    "wof:name":"Coolens Dirk",
    "wof:placetype":"venue"
},
  "geometry": {"coordinates":[3.9517478943,50.9364547729],"type":"Point"}
}