{
  "type": "Feature",
  "properties": {
    "addr:full":"Koeisteerthofdreef 34 Mortsel Antwerpen 2640",
    "addr:housenumber":"34",
    "addr:postcode":"2640",
    "addr:street":"Koeisteerthofdreef",
    "iso:country":"BE",
    "sg:address":"Koeisteerthofdreef 34",
    "sg:city":"Mortsel",
    "sg:orig_category":"Newspapers, magazines, periodicals - Distribution",
    "sg:phone":"+32 3 455 39 63",
    "sg:postcode":"2640",
    "sg:province":"Antwerpen",
    "wof:name":"Yannouk",
    "wof:placetype":"venue"
},
  "geometry": {"coordinates":[4.4734048843,51.170589447],"type":"Point"}
}