{
  "type": "Feature",
  "properties": {
    "iso:country":"BE",
    "sg:address":"Rue Ren\u00c9 Dubois 80",
    "sg:city":"Huy",
    "sg:orig_category":"Motos. V\u00e9los",
    "sg:phone":"+32 85 21 39 98",
    "sg:postcode":"4500",
    "sg:province":"Li\u00e8ge",
    "wof:name":"Cycles Ebroin",
    "wof:placetype":"venue"
},
  "geometry": {"coordinates":[5.2194399834,50.5307388306],"type":"Point"}
}