{
  "type": "Feature",
  "properties": {
    "addr:full":"Avenue Des Lis 3 Kraainem Vlaams-Brabant 1950",
    "addr:housenumber":"3",
    "addr:postcode":"1950",
    "addr:street":"Avenue Des Lis",
    "iso:country":"BE",
    "sg:address":"Avenue Des Lis 3",
    "sg:city":"Kraainem",
    "sg:classifiers":[
        {
            "category":"Professional",
            "subcategory":"Management & Consulting",
            "type":"Services"
        }
    ],
    "sg:phone":"+32 2 736 88 60",
    "sg:postcode":"1950",
    "sg:province":"Vlaams-Brabant",
    "sg:tags":[
        "consultant"
    ],
    "wof:name":"Coffeedis Sprl",
    "wof:placetype":"venue"
},
  "geometry": {"coordinates":[4.467757225,50.8526420593],"type":"Point"}
}