{
  "type": "Feature",
  "properties": {
    "iso:country":"BE",
    "sg:address":"Rue Brigade Piron 276",
    "sg:city":"Charleroi (montignies-sur-sambre)",
    "sg:classifiers":[
        {
            "category":"Health Services",
            "subcategory":"Health Practitioner",
            "type":"Services"
        }
    ],
    "sg:phone":"+32 71 31 41 93",
    "sg:postcode":"6061",
    "sg:province":"Hainaut",
    "sg:tags":[
        "physiotherapist"
    ],
    "wof:name":"Stroobants Eric",
    "wof:placetype":"venue"
},
  "geometry": {"coordinates":[4.4553980827,50.4081268311],"type":"Point"}
}