{
  "type": "Feature",
  "properties": {
    "iso:country":"BE",
    "sg:address":"Lentaekkerstraat 46",
    "sg:city":"Ingelmunster",
    "sg:orig_category":"D\u00e9molition d\u00b4immeubles and terrassements. Construction industrielle and commerciale",
    "sg:phone":"+32 51 31 17 24",
    "sg:postcode":"8770",
    "sg:province":"West-Vlaanderen",
    "wof:name":"Debackere Eric",
    "wof:placetype":"venue"
},
  "geometry": {"coordinates":[3.2692770958,50.9284133911],"type":"Point"}
}