{
  "type": "Feature",
  "properties": {
    "addr:full":"Rue De Chapelle 209 Courcelles Hainaut 6183",
    "addr:housenumber":"209",
    "addr:postcode":"6183",
    "addr:street":"Rue De Chapelle",
    "iso:country":"BE",
    "sg:address":"Rue De Chapelle 209",
    "sg:city":"Courcelles",
    "sg:orig_category":"Bouwmaterialen Gh",
    "sg:phone":"+32 71 45 47 14",
    "sg:postcode":"6183",
    "sg:province":"Hainaut",
    "wof:name":"M. Bendetti",
    "wof:placetype":"venue"
},
  "geometry": {"coordinates":[4.3168067932,50.4658088684],"type":"Point"}
}