{
  "type": "Feature",
  "properties": {
    "iso:country":"BE",
    "sg:address":"Verlorenkost 64",
    "sg:city":"Maaseik",
    "sg:orig_category":"Plomberie, chauffage and installations sanitaires",
    "sg:phone":"+32 89 56 23 74",
    "sg:postcode":"3680",
    "sg:province":"Limburg",
    "wof:name":"Gilbert Goyens",
    "wof:placetype":"venue"
},
  "geometry": {"coordinates":[5.7755970955,51.1004753113],"type":"Point"}
}