{
  "type": "Feature",
  "properties": {
    "addr:full":"Rue De L'ath\u00c9n\u00c9e 10 Tournai Hainaut 7500",
    "addr:housenumber":"10",
    "addr:postcode":"7500",
    "addr:street":"Rue De L'Athe \u0301Ne\u0301E",
    "iso:country":"BE",
    "sg:address":"Rue De L'ath\u00c9n\u00c9e 10",
    "sg:city":"Tournai",
    "sg:orig_category":"Avocats and conseillers juridiques",
    "sg:phone":"+32 69 23 37 33",
    "sg:postcode":"7500",
    "sg:province":"Hainaut",
    "wof:name":"Jean-philippe Pochart",
    "wof:placetype":"venue"
},
  "geometry": {"coordinates":[3.395234108,50.6088905334],"type":"Point"}
}