{
  "type": "Feature",
  "properties": {
    "addr:full":"Maria-aalterstraat 8 Ruiselede West-Vlaanderen 8755",
    "addr:housenumber":"8",
    "addr:postcode":"8755",
    "addr:street":"Maria-Aalterstraat",
    "iso:country":"BE",
    "sg:address":"Maria-aalterstraat 8",
    "sg:city":"Ruiselede",
    "sg:orig_category":"Jardinage",
    "sg:phone":"+32 51 72 64 05",
    "sg:postcode":"8755",
    "sg:province":"West-Vlaanderen",
    "wof:name":"Tuinaanleg Reinhard Dauwe",
    "wof:placetype":"venue"
},
  "geometry": {"coordinates":[3.3989710808,51.0425987244],"type":"Point"}
}