{
  "type": "Feature",
  "properties": {
    "addr:full":"Visserskaai 43 Oostende West-Vlaanderen 8400",
    "addr:housenumber":"43",
    "addr:postcode":"8400",
    "addr:street":"Visserskaai",
    "iso:country":"BE",
    "sg:address":"Visserskaai 43",
    "sg:city":"Oostende",
    "sg:classifiers":[
        {
            "category":"Restaurant",
            "type":"Food & Drink"
        }
    ],
    "sg:phone":"+32 59 80 51 84",
    "sg:postcode":"8400",
    "sg:province":"West-Vlaanderen",
    "wof:name":"Flandria",
    "wof:placetype":"venue"
},
  "geometry": {"coordinates":[2.9214630127,51.2340240479],"type":"Point"}
}