{
  "type": "Feature",
  "properties": {
    "iso:country":"BE",
    "sg:address":"Lisseweegs Upperhof 4a",
    "sg:city":"Lissewege",
    "sg:orig_category":"Installatie van houten of kunststof schrijnwerk Installatie van metalen schrijnwerk",
    "sg:phone":"+32 475 55 22 45",
    "sg:postcode":"8380",
    "sg:province":"West-Vlaanderen",
    "wof:name":"Ronny Delannoye",
    "wof:placetype":"venue"
},
  "geometry": {"coordinates":[3.1939160824,51.2954063416],"type":"Point"}
}