{
  "type": "Feature",
  "properties": {
    "iso:country":"BE",
    "sg:address":"Rue F Nicolay",
    "sg:city":"Tilleur",
    "sg:classifiers":[
        {
            "category":"Banks & Credit Unions",
            "subcategory":"Bank",
            "type":"Services"
        }
    ],
    "sg:phone":"+32 41332476",
    "sg:postcode":"4210",
    "sg:province":"Li\u00e8ge",
    "wof:name":"Aslk-cger Bank",
    "wof:placetype":"venue"
},
  "geometry": {"coordinates":[112.6226196289,26.8980007172],"type":"Point"}
}