{
  "type": "Feature",
  "properties": {
    "iso:country":"BE",
    "sg:address":"Route De Ch\u00e2telet 130",
    "sg:city":"Charleroi (couillet)",
    "sg:classifiers":[
        {
            "category":"Shopping",
            "subcategory":"Computers & Home Electronics",
            "type":"Retail Goods"
        }
    ],
    "sg:phone":"+32 71 43 65 94",
    "sg:postcode":"6010",
    "sg:province":"Hainaut",
    "sg:tags":[
        "-",
        "television",
        "radio"
    ],
    "wof:name":"Hennequart (ets)",
    "wof:placetype":"venue"
},
  "geometry": {"coordinates":[4.4610757828,50.3916778564],"type":"Point"}
}