{
  "type": "Feature",
  "properties": {
    "iso:country":"BE",
    "sg:address":"Rue Alnoir 50",
    "sg:city":"Jemeppe-sur-sambre",
    "sg:orig_category":"Loodgieterij, verwarming and sanitaire installaties Schoonmaakbedrijven and ongediertebestrijding",
    "sg:phone":"+32 71 78 78 82",
    "sg:postcode":"5190",
    "sg:province":"Namur",
    "wof:name":"Entr.de Chauffage Deltenre",
    "wof:placetype":"venue"
},
  "geometry": {"coordinates":[4.6541500092,50.4727172852],"type":"Point"}
}