{
  "type": "Feature",
  "properties": {
    "addr:full":"Wilsonstraat 36 Sint-katelijne-waver Antwerpen 2860",
    "addr:housenumber":"36",
    "addr:postcode":"2860",
    "addr:street":"Wilsonstraat",
    "iso:country":"BE",
    "sg:address":"Wilsonstraat 36",
    "sg:city":"Sint-katelijne-waver",
    "sg:orig_category":"V\u00eatements pour Hommes",
    "sg:phone":"+32 15 31 72 92",
    "sg:postcode":"2860",
    "sg:province":"Antwerpen",
    "wof:name":"Kristina Stuer",
    "wof:placetype":"venue"
},
  "geometry": {"coordinates":[4.5349788666,51.0735626221],"type":"Point"}
}