{
  "type": "Feature",
  "properties": {
    "iso:country":"BE",
    "sg:address":"Rue Du Castillon 214",
    "sg:city":"Quaregnon",
    "sg:orig_category":"Herstelling leer and schoeisel",
    "sg:phone":"+32 65 79 23 33",
    "sg:postcode":"7390",
    "sg:province":"Hainaut",
    "wof:name":"A.r.s.",
    "wof:placetype":"venue"
},
  "geometry": {"coordinates":[3.8759739399,50.4290046692],"type":"Point"}
}