{
  "type": "Feature",
  "properties": {
    "addr:full":"Patattenstraat 12 Geraardsbergen Oost-Vlaanderen 9500",
    "addr:housenumber":"12",
    "addr:postcode":"9500",
    "addr:street":"Patattenstraat",
    "iso:country":"BE",
    "sg:address":"Patattenstraat 12",
    "sg:city":"Geraardsbergen",
    "sg:orig_category":"Kapsalons",
    "sg:phone":"+32 54 50 17 63",
    "sg:postcode":"9500",
    "sg:province":"Oost-Vlaanderen",
    "wof:name":"Coiffure Sabine",
    "wof:placetype":"venue"
},
  "geometry": {"coordinates":[3.8837440014,50.8215141296],"type":"Point"}
}