{
  "type": "Feature",
  "properties": {
    "iso:country":"BE",
    "sg:address":"Asserendries 130",
    "sg:city":"Aalst",
    "sg:orig_category":"Solariums",
    "sg:phone":"+32 53 41 54 98",
    "sg:postcode":"9300",
    "sg:province":"Oost-Vlaanderen",
    "wof:name":"Malu Sun",
    "wof:placetype":"venue"
},
  "geometry": {"coordinates":[4.0224199295,50.9442710876],"type":"Point"}
}