{
  "type": "Feature",
  "properties": {
    "addr:full":"Rue Du Pacifique 28 Bruxelles (uccle) Bruxelles-Capitale 1180",
    "addr:housenumber":"28",
    "addr:postcode":"1180",
    "addr:street":"Rue Du Pacifique",
    "iso:country":"BE",
    "sg:address":"Rue Du Pacifique 28",
    "sg:city":"Bruxelles (uccle)",
    "sg:classifiers":[
        {
            "category":"Utilities",
            "subcategory":"Telephone",
            "type":"Services"
        }
    ],
    "sg:phone":"+32 2 345 25 88",
    "sg:postcode":"1180",
    "sg:province":"Bruxelles-Capitale",
    "sg:tags":[
        "-",
        "internet"
    ],
    "wof:name":"Platinum Services Europe",
    "wof:placetype":"venue"
},
  "geometry": {"coordinates":[4.3552780151,50.8134536743],"type":"Point"}
}