{
  "type": "Feature",
  "properties": {
    "iso:country":"BE",
    "sg:address":"Zuidstraat 105",
    "sg:city":"Ichtegem",
    "sg:classifiers":[
        {
            "category":"Utilities",
            "subcategory":"Water",
            "type":"Services"
        }
    ],
    "sg:phone":"+32 51 58 80 12",
    "sg:postcode":"8480",
    "sg:province":"West-Vlaanderen",
    "sg:tags":[
        "purification"
    ],
    "wof:name":"Tanghe Nv",
    "wof:placetype":"venue"
},
  "geometry": {"coordinates":[3.0374350548,51.1068382263],"type":"Point"}
}