{
  "type": "Feature",
  "properties": {
    "addr:full":"Deken De Bolaan 37 Poperinge West-Vlaanderen 8970",
    "addr:housenumber":"37",
    "addr:postcode":"8970",
    "addr:street":"Deken De Bolaan",
    "iso:country":"BE",
    "sg:address":"Deken De Bolaan 37",
    "sg:city":"Poperinge",
    "sg:orig_category":"V\u00e9t\u00e9rinaires",
    "sg:phone":"+32 57 33 61 47",
    "sg:postcode":"8970",
    "sg:province":"West-Vlaanderen",
    "wof:name":"Paul Verstraete",
    "wof:placetype":"venue"
},
  "geometry": {"coordinates":[2.7282269001,50.8509178162],"type":"Point"}
}