{
  "type": "Feature",
  "properties": {
    "addr:full":"Otto Veniusstraat 31 Antwerpen Antwerpen 2000",
    "addr:housenumber":"31",
    "addr:postcode":"2000",
    "addr:street":"Otto Veniusstraat",
    "iso:country":"BE",
    "sg:address":"Otto Veniusstraat 31",
    "sg:city":"Antwerpen",
    "sg:classifiers":[
        {
            "category":"Personal",
            "subcategory":"Beauty Salon",
            "type":"Services"
        }
    ],
    "sg:phone":"+32 3 233 72 91",
    "sg:postcode":"2000",
    "sg:province":"Antwerpen",
    "sg:tags":[
        "de",
        "coiffure"
    ],
    "wof:name":"Coiffure Fredd",
    "wof:placetype":"venue"
},
  "geometry": {"coordinates":[4.4126729965,51.2168655396],"type":"Point"}
}