{
  "type": "Feature",
  "properties": {
    "iso:country":"BE",
    "sg:address":"Rue Muzet 87",
    "sg:city":"Namur (saint-servais)",
    "sg:classifiers":[
        {
            "category":"Arena",
            "subcategory":"Sports Club",
            "type":"Entertainment"
        }
    ],
    "sg:phone":"+32 81 73 04 80",
    "sg:postcode":"5002",
    "sg:province":"Namur",
    "sg:tags":[
        "federation"
    ],
    "wof:name":"Enseignement De La Communaut\u00e9 Fran\u00e7aise (f\u00e9d\u00e9ration Sportive D')",
    "wof:placetype":"venue"
},
  "geometry": {"coordinates":[4.8560619354,50.4723968506],"type":"Point"}
}