{
  "type": "Feature",
  "properties": {
    "addr:full":"Assesteenweg 27 Ternat Vlaams-Brabant 1740",
    "addr:housenumber":"27",
    "addr:postcode":"1740",
    "addr:street":"Assesteenweg",
    "iso:country":"BE",
    "sg:address":"Assesteenweg 27",
    "sg:city":"Ternat",
    "sg:orig_category":"Cad/Cam systems",
    "sg:phone":"+32 2 583 16 00",
    "sg:postcode":"1740",
    "sg:province":"Vlaams-Brabant",
    "wof:name":"Man And Machine Benelux Nv",
    "wof:placetype":"venue"
},
  "geometry": {"coordinates":[4.1683149338,50.8852424622],"type":"Point"}
}