{
  "type": "Feature",
  "properties": {
    "addr:full":"Leopoldstraat 18 Zemst Vlaams-Brabant 1980",
    "addr:housenumber":"18",
    "addr:postcode":"1980",
    "addr:street":"Leopoldstraat;Vlaams-Brabant",
    "iso:country":"BE",
    "sg:address":"Leopoldstraat 18",
    "sg:city":"Zemst",
    "sg:classifiers":[
        {
            "category":"Food & Beverages",
            "subcategory":"Supermarket",
            "type":"Retail Goods"
        }
    ],
    "sg:phone":"+32 15 61 12 77",
    "sg:postcode":"1980",
    "sg:province":"Vlaams-Brabant",
    "sg:tags":[
        "department",
        "store"
    ],
    "wof:name":"De Coninck Bvba",
    "wof:placetype":"venue"
},
  "geometry": {"coordinates":[4.4620018005,50.9838294983],"type":"Point"}
}