{
  "type": "Feature",
  "properties": {
    "addr:full":"Rue G\u00c9n\u00c9ral Lotz 33 Ukkel/uccle Bruxelles-Capitale 1180",
    "addr:housenumber":"33",
    "addr:postcode":"1180",
    "addr:street":"Rue Ge\u0301Ne\u0301Ral Lotz;/",
    "iso:country":"BE",
    "sg:address":"Rue G\u00c9n\u00c9ral Lotz 33",
    "sg:city":"Ukkel/uccle",
    "sg:classifiers":[
        {
            "category":"Personal",
            "subcategory":"Beauty Salon",
            "type":"Services"
        }
    ],
    "sg:phone":"+32 2 343 10 51",
    "sg:postcode":"1180",
    "sg:province":"Bruxelles-Capitale",
    "sg:tags":[
        "de",
        "coiffure"
    ],
    "wof:name":"Foty-fr\u00c8re",
    "wof:placetype":"venue"
},
  "geometry": {"coordinates":[4.3577871323,50.8143882751],"type":"Point"}
}