{
  "type": "Feature",
  "properties": {
    "addr:full":"Avenue Du Haut-pays 14 Honnelles Hainaut 7387",
    "addr:housenumber":"14",
    "addr:postcode":"7387",
    "addr:street":"Avenue Du Haut-Pays;Hainaut",
    "iso:country":"BE",
    "sg:address":"Avenue Du Haut-pays 14",
    "sg:city":"Honnelles",
    "sg:classifiers":[
        {
            "category":"Military Area",
            "subcategory":"Air Force Base",
            "type":"Public Place"
        }
    ],
    "sg:phone":"+32 65 88 67 53",
    "sg:postcode":"7387",
    "sg:province":"Hainaut",
    "sg:tags":[
        "commerce",
        "gr",
        "equipement",
        "de",
        "\u00e9v\u00e9nements",
        "pour",
        "diver",
        "mat\u00e9riel",
        "location",
        "banquet"
    ],
    "wof:name":"Ets. Colot",
    "wof:placetype":"venue"
},
  "geometry": {"coordinates":[3.7649419308,50.3557739258],"type":"Point"}
}