{
  "type": "Feature",
  "properties": {
    "addr:full":"Avenue Eug\u00e8ne Mascaux 118 Charleroi (marcinelle) Hainaut 6001",
    "addr:housenumber":"118",
    "addr:postcode":"6001",
    "addr:street":"Avenue Euge\u0300Ne Mascaux",
    "iso:country":"BE",
    "sg:address":"Avenue Eug\u00e8ne Mascaux 118",
    "sg:city":"Charleroi (marcinelle)",
    "sg:classifiers":[
        {
            "category":"Retail",
            "subcategory":"Veterinary Services",
            "type":"Services"
        }
    ],
    "sg:phone":"+32 71 36 26 76",
    "sg:postcode":"6001",
    "sg:province":"Hainaut",
    "sg:tags":[
        "veterinarian"
    ],
    "wof:name":"Philippe J L",
    "wof:placetype":"venue"
},
  "geometry": {"coordinates":[4.4442191124,50.3969955444],"type":"Point"}
}