{
  "type": "Feature",
  "properties": {
    "addr:full":"Neerveld 4 Kontich Antwerpen 2550",
    "addr:housenumber":"4",
    "addr:postcode":"2550",
    "addr:street":"Neerveld",
    "iso:country":"BE",
    "sg:address":"Neerveld 4",
    "sg:city":"Kontich",
    "sg:orig_category":"Onderdelen and accessoires voor auto's Telecommunicatieapparaten",
    "sg:phone":"+32 3 458 76 93",
    "sg:postcode":"2550",
    "sg:province":"Antwerpen",
    "wof:name":"A.p.c.",
    "wof:placetype":"venue"
},
  "geometry": {"coordinates":[4.4547801018,51.1220664978],"type":"Point"}
}