{
  "type": "Feature",
  "properties": {
    "addr:full":"Langenbend 20 Raeren Li\u00e8ge 4730",
    "addr:housenumber":"20",
    "addr:postcode":"4730",
    "addr:street":"Langenbend",
    "iso:country":"BE",
    "sg:address":"Langenbend 20",
    "sg:city":"Raeren",
    "sg:classifiers":[
        {
            "category":"Quarry",
            "type":"Physical Feature"
        }
    ],
    "sg:phone":"+32 87 85 01 43",
    "sg:postcode":"4730",
    "sg:province":"Li\u00e8ge",
    "sg:tags":[
        "granite",
        "work",
        "marble"
    ],
    "wof:name":"Marmorwerk Raeren Sprlu",
    "wof:placetype":"venue"
},
  "geometry": {"coordinates":[6.1266098022,50.6645507812],"type":"Point"}
}