{
  "type": "Feature",
  "properties": {
    "addr:full":"2480 Dessel Antwerpen 2480",
    "addr:postcode":"2480;2480",
    "iso:country":"BE",
    "sg:address":"2480",
    "sg:city":"Dessel",
    "sg:orig_category":"Pharmaciens",
    "sg:phone":"+32 900 10 500",
    "sg:postcode":"2480",
    "sg:province":"Antwerpen",
    "wof:name":"Pharmacies De Garde",
    "wof:placetype":"venue"
},
  "geometry": {"coordinates":[5.1127700806,51.2395935059],"type":"Point"}
}