{
  "type": "Feature",
  "properties": {
    "addr:full":"Sportstraat 3 Wommelgem Antwerpen 2160",
    "addr:housenumber":"3",
    "addr:postcode":"2160",
    "addr:street":"Sportstraat",
    "iso:country":"BE",
    "sg:address":"Sportstraat 3",
    "sg:city":"Wommelgem",
    "sg:orig_category":"Fietsen",
    "sg:phone":"+32 3 353 10 38",
    "sg:postcode":"2160",
    "sg:province":"Antwerpen",
    "wof:name":"Omer Detienne",
    "wof:placetype":"venue"
},
  "geometry": {"coordinates":[4.5186772346,51.2055931091],"type":"Point"}
}