{
  "type": "Feature",
  "properties": {
    "addr:full":"All\u00e9e Verte 1 Philippeville Namur 5600",
    "addr:housenumber":"1",
    "addr:postcode":"5600",
    "addr:street":"Alle\u0301E Verte",
    "iso:country":"BE",
    "sg:address":"All\u00e9e Verte 1",
    "sg:city":"Philippeville",
    "sg:classifiers":[
        {
            "category":"Health Services",
            "subcategory":"Health Practitioner",
            "type":"Services"
        }
    ],
    "sg:phone":"+32 71 66 62 76",
    "sg:postcode":"5600",
    "sg:province":"Namur",
    "sg:tags":[
        "physiotherapist"
    ],
    "wof:name":"Boreux Jean-claude",
    "wof:placetype":"venue"
},
  "geometry": {"coordinates":[4.5384411812,50.196056366],"type":"Point"}
}