{
  "type": "Feature",
  "properties": {
    "addr:full":"Bargiekaai 1 Gent Oost-Vlaanderen 9000",
    "addr:housenumber":"1",
    "addr:postcode":"9000",
    "addr:street":"Bargiekaai;Oost-Vlaanderen",
    "iso:country":"BE",
    "sg:address":"Bargiekaai 1",
    "sg:city":"Gent",
    "sg:orig_category":"Formation permanente",
    "sg:phone":"+32 9 225 68 05",
    "sg:postcode":"9000",
    "sg:province":"Oost-Vlaanderen",
    "wof:name":"Handels-& Taalleergangen",
    "wof:placetype":"venue"
},
  "geometry": {"coordinates":[3.7080368996,51.0578117371],"type":"Point"}
}