{
  "type": "Feature",
  "properties": {
    "iso:country":"BE",
    "sg:address":"Muggenboskenstraat 10",
    "sg:city":"Nieuwerkerken",
    "sg:classifiers":[
        {
            "category":"Professional",
            "subcategory":"Accounting & Tax Preparation",
            "type":"Services"
        }
    ],
    "sg:phone":"+32 11 69 14 05",
    "sg:postcode":"3850",
    "sg:province":"Limburg",
    "sg:tags":[
        "accountant"
    ],
    "wof:name":"Catherine Bosmans",
    "wof:placetype":"venue"
},
  "geometry": {"coordinates":[5.2013030052,50.86561203],"type":"Point"}
}