{
  "type": "Feature",
  "properties": {
    "iso:country":"BE",
    "sg:address":"Bosstraat 49",
    "sg:city":"Nazareth",
    "sg:classifiers":[
        {
            "category":"Professional",
            "subcategory":"Art Services",
            "type":"Services"
        }
    ],
    "sg:phone":"+32 9 385 84 39",
    "sg:postcode":"9810",
    "sg:province":"Oost-Vlaanderen",
    "sg:tags":[
        "children's",
        "animation"
    ],
    "wof:name":"Whitty Clown",
    "wof:placetype":"venue"
},
  "geometry": {"coordinates":[3.6428980827,50.9691352844],"type":"Point"}
}