{
  "type": "Feature",
  "properties": {
    "iso:country":"BE",
    "sg:address":"Chauss\u00c9e De Haecht 216",
    "sg:city":"Brussel",
    "sg:orig_category":"Agences d'exp\u00e9dition",
    "sg:phone":"+32 2 216 67 42",
    "sg:postcode":"1030",
    "sg:province":"Bruxelles-Capitale",
    "wof:name":"Chinter Belgium",
    "wof:placetype":"venue"
},
  "geometry": {"coordinates":[4.3721590042,50.8616371155],"type":"Point"}
}