{
  "type": "Feature",
  "properties": {
    "addr:full":"Berthoutstraat 51 Boechout Antwerpen 2531",
    "addr:housenumber":"51",
    "addr:postcode":"2531",
    "addr:street":"Berthoutstraat",
    "iso:country":"BE",
    "sg:address":"Berthoutstraat 51",
    "sg:city":"Boechout",
    "sg:orig_category":"Isolatiewerk Woningbouw",
    "sg:phone":"+32 3 455 20 04",
    "sg:postcode":"2531",
    "sg:province":"Antwerpen",
    "wof:name":"Grandry",
    "wof:placetype":"venue"
},
  "geometry": {"coordinates":[4.5236349106,51.1750640869],"type":"Point"}
}