{
  "type": "Feature",
  "properties": {
    "addr:full":"Rue De Marbais 5 Villers-la-ville Brabant Wallon 1495",
    "addr:housenumber":"5",
    "addr:postcode":"1495",
    "addr:street":"Rue De Marbais",
    "iso:country":"BE",
    "sg:address":"Rue De Marbais 5",
    "sg:city":"Villers-la-ville",
    "sg:classifiers":[
        {
            "category":"Personal",
            "subcategory":"Beauty Salon",
            "type":"Services"
        }
    ],
    "sg:phone":"+32 71 87 81 98",
    "sg:postcode":"1495",
    "sg:province":"Brabant Wallon",
    "sg:tags":[
        "lady",
        "-",
        "hairdressing"
    ],
    "wof:name":"Coiffure Rizzeri",
    "wof:placetype":"venue"
},
  "geometry": {"coordinates":[4.5310139656,50.5766296387],"type":"Point"}
}