{
  "type": "Feature",
  "properties": {
    "iso:country":"BE",
    "sg:address":"Wolvenstraat 16",
    "sg:city":"Sint-katelijne-waver (onze-lieve-vrouw-waver)",
    "sg:classifiers":[
        {
            "category":"Home & Garden",
            "subcategory":"Building Materials",
            "type":"Retail Goods"
        }
    ],
    "sg:phone":"+32 15 76 02 55",
    "sg:postcode":"2861",
    "sg:province":"Antwerpen",
    "sg:tags":[
        "granite",
        "stone",
        "natural",
        "marble"
    ],
    "wof:name":"Verschueren-moernaut Nv",
    "wof:placetype":"venue"
},
  "geometry": {"coordinates":[4.5803399086,51.0623168945],"type":"Point"}
}