{
  "type": "Feature",
  "properties": {
    "iso:country":"BE",
    "sg:address":"Rue Du Menuisier 109",
    "sg:city":"Sint-lambrechts-woluwe/woluwe-saint-lambert",
    "sg:orig_category":"Epiceries. Location de cassettes vid\u00e9o and audio",
    "sg:phone":"+32 2 772 53 04",
    "sg:postcode":"1200",
    "sg:province":"Bruxelles-Capitale",
    "wof:name":"Western Night",
    "wof:placetype":"venue"
},
  "geometry": {"coordinates":[4.4154109955,50.8442077637],"type":"Point"}
}