{
  "type": "Feature",
  "properties": {
    "addr:full":"Konterdijk 2 Veurne West-Vlaanderen 8630",
    "addr:housenumber":"2",
    "addr:postcode":"8630",
    "addr:street":"Konterdijk",
    "iso:country":"BE",
    "sg:address":"Konterdijk 2",
    "sg:city":"Veurne",
    "sg:classifiers":[
        {
            "category":"Shopping",
            "subcategory":"Florist",
            "type":"Retail Goods"
        }
    ],
    "sg:phone":"+32 58 31 46 78",
    "sg:postcode":"8630",
    "sg:province":"West-Vlaanderen",
    "wof:name":"Decoster Cactussen",
    "wof:placetype":"venue"
},
  "geometry": {"coordinates":[2.669490099,51.0798110962],"type":"Point"}
}