{
  "type": "Feature",
  "properties": {
    "addr:full":"Rue Cl\u00c9ment Grenier 9 Saint-ghislain Hainaut 7331",
    "addr:housenumber":"9",
    "addr:postcode":"7331",
    "addr:street":"Rue Cle\u0301Ment Grenier;Hainaut",
    "iso:country":"BE",
    "sg:address":"Rue Cl\u00c9ment Grenier 9",
    "sg:city":"Saint-ghislain",
    "sg:orig_category":"M\u00e9decins and sp\u00e9cialistes",
    "sg:phone":"+32 65 64 39 17",
    "sg:postcode":"7331",
    "sg:province":"Hainaut",
    "wof:name":"D. Debbaut",
    "wof:placetype":"venue"
},
  "geometry": {"coordinates":[3.8343689442,50.4857063293],"type":"Point"}
}