{
  "type": "Feature",
  "properties": {
    "addr:full":"Koningsvarenweg 41 Gent Oost-Vlaanderen 9031",
    "addr:housenumber":"41",
    "addr:postcode":"9031",
    "addr:street":"Koningsvarenweg;Oost-Vlaanderen",
    "iso:country":"BE",
    "sg:address":"Koningsvarenweg 41",
    "sg:city":"Gent",
    "sg:orig_category":"Installation de menuiserie en bois and plastique",
    "sg:phone":"+32 9 226 02 89",
    "sg:postcode":"9031",
    "sg:province":"Oost-Vlaanderen",
    "wof:name":"Davy De Vrieze",
    "wof:placetype":"venue"
},
  "geometry": {"coordinates":[3.6409900188,51.0465164185],"type":"Point"}
}