{
  "type": "Feature",
  "properties": {
    "addr:full":"Place Du Commerce 1 Malmedy Li\u00e8ge 4960",
    "addr:housenumber":"1",
    "addr:postcode":"4960",
    "addr:street":"Place Du Commerce",
    "iso:country":"BE",
    "sg:address":"Place Du Commerce 1",
    "sg:city":"Malmedy",
    "sg:orig_category":"Pain, p\u00e2tisseries and confiseries. Fruits and l\u00e9gumes",
    "sg:phone":"+32 80 33 02 80",
    "sg:postcode":"4960",
    "sg:province":"Li\u00e8ge",
    "wof:name":"Marc Bodet",
    "wof:placetype":"venue"
},
  "geometry": {"coordinates":[6.0310149193,50.4251861572],"type":"Point"}
}