{
  "type": "Feature",
  "properties": {
    "iso:country":"BE",
    "sg:address":"Hundelgemsesteenweg 177",
    "sg:city":"Merelbeke",
    "sg:orig_category":"Pain, p\u00e2tisseries and confiseries",
    "sg:phone":"+32 9 232 16 19",
    "sg:postcode":"9820",
    "sg:province":"Oost-Vlaanderen",
    "wof:name":"M Van Malderghem",
    "wof:placetype":"venue"
},
  "geometry": {"coordinates":[3.7515089512,51.0012779236],"type":"Point"}
}