{
  "type": "Feature",
  "properties": {
    "iso:country":"BE",
    "sg:address":"Rue De Heuseux 49",
    "sg:city":"Bl\u00e9gny (barchon)",
    "sg:classifiers":[
        {
            "category":"Health Services",
            "subcategory":"Health Practitioner",
            "type":"Services"
        }
    ],
    "sg:phone":"+32 4 387 82 36",
    "sg:postcode":"4671",
    "sg:province":"Li\u00e8ge",
    "sg:tags":[
        "physiotherapist"
    ],
    "wof:name":"Thiry Fabienne",
    "wof:placetype":"venue"
},
  "geometry": {"coordinates":[5.7013912201,50.6647109985],"type":"Point"}
}