{
  "type": "Feature",
  "properties": {
    "addr:full":"Grand-place 14 Ham-sur-heure-nalinnes Hainaut 6120",
    "addr:housenumber":"14",
    "addr:postcode":"6120",
    "addr:street":"Grand-Place;Hainaut",
    "iso:country":"BE",
    "sg:address":"Grand-place 14",
    "sg:city":"Ham-sur-heure-nalinnes",
    "sg:classifiers":[
        {
            "category":"Cafe",
            "type":"Food & Drink"
        }
    ],
    "sg:phone":"+32 71 21 53 56",
    "sg:postcode":"6120",
    "sg:province":"Hainaut",
    "sg:tags":[
        "caf\u00e9s"
    ],
    "wof:name":"Caf\u00c9 Le Touriste",
    "wof:placetype":"venue"
},
  "geometry": {"coordinates":[4.3872900009,50.3219146729],"type":"Point"}
}