{
  "type": "Feature",
  "properties": {
    "addr:full":"Bistweg 84 Broechem Antwerpen 2520",
    "addr:housenumber":"84",
    "addr:postcode":"2520",
    "addr:street":"Bistweg",
    "iso:country":"BE",
    "sg:address":"Bistweg 84",
    "sg:city":"Broechem",
    "sg:classifiers":[
        {
            "category":"Building & Trades",
            "subcategory":"Construction",
            "type":"Services"
        }
    ],
    "sg:phone":"+32 3 235 00 28",
    "sg:postcode":"2520",
    "sg:province":"Antwerpen",
    "sg:tags":[
        "roofing"
    ],
    "wof:name":"Keteleer Nv",
    "wof:placetype":"venue"
},
  "geometry": {"coordinates":[4.4484329224,51.2093315125],"type":"Point"}
}