{
  "type": "Feature",
  "properties": {
    "addr:full":"Drieslaan 10 Moorsele West-Vlaanderen 8560",
    "addr:housenumber":"10",
    "addr:postcode":"8560",
    "addr:street":"Drieslaan",
    "iso:country":"BE",
    "sg:address":"Drieslaan 10",
    "sg:city":"Moorsele",
    "sg:classifiers":[
        {
            "category":"Professional",
            "subcategory":"Engineering",
            "type":"Services"
        }
    ],
    "sg:phone":"+32 56 41 95 93",
    "sg:postcode":"8560",
    "sg:province":"West-Vlaanderen",
    "sg:tags":[
        "machine",
        "-",
        "mechanical"
    ],
    "wof:name":"Frigro Nv",
    "wof:placetype":"venue"
},
  "geometry": {"coordinates":[3.1803300381,50.847618103],"type":"Point"}
}