{
  "type": "Feature",
  "properties": {
    "iso:country":"BE",
    "sg:address":"Ertveldesteenweg 107",
    "sg:city":"Assenede (oosteeklo)",
    "sg:classifiers":[
        {
            "category":"Health Services",
            "subcategory":"Doctor",
            "type":"Services"
        }
    ],
    "sg:phone":"+32 9 373 76 51",
    "sg:postcode":"9968",
    "sg:province":"Oost-Vlaanderen",
    "sg:tags":[
        "medicinephysicians",
        "surgeon"
    ],
    "wof:name":"Baekelandt J",
    "wof:placetype":"venue"
},
  "geometry": {"coordinates":[3.6976079941,51.1901931763],"type":"Point"}
}