{
  "type": "Feature",
  "properties": {
    "addr:full":"Henri Dunantlaan Gent Oost-Vlaanderen 9000",
    "addr:postcode":"9000",
    "addr:street":"Henri Dunantlaan",
    "iso:country":"BE",
    "sg:address":"Henri Dunantlaan",
    "sg:city":"Gent",
    "sg:classifiers":[
        {
            "category":"Health Services",
            "subcategory":"Doctor",
            "type":"Services"
        }
    ],
    "sg:phone":"+32 9 224 85 76",
    "sg:postcode":"9000",
    "sg:province":"Oost-Vlaanderen",
    "sg:tags":[
        "medicinephysicians",
        "surgeon"
    ],
    "wof:name":"Derycke Anne",
    "wof:placetype":"venue"
},
  "geometry": {"coordinates":[3.7031950951,51.04895401],"type":"Point"}
}