{
  "type": "Feature",
  "properties": {
    "addr:full":"Broelstraat 80 Harelbeke West-Vlaanderen 8530",
    "addr:housenumber":"80",
    "addr:postcode":"8530",
    "addr:street":"Broelstraat",
    "iso:country":"BE",
    "sg:address":"Broelstraat 80",
    "sg:city":"Harelbeke",
    "sg:orig_category":"Boekhouders",
    "sg:phone":"+32 56 70 32 04",
    "sg:postcode":"8530",
    "sg:province":"West-Vlaanderen",
    "wof:name":"Martine Meurisse",
    "wof:placetype":"venue"
},
  "geometry": {"coordinates":[3.3099370003,50.8620185852],"type":"Point"}
}