{
  "type": "Feature",
  "properties": {
    "iso:country":"BE",
    "sg:address":"Rue Middelbourg 64a",
    "sg:city":"Bruxelles (watermael-boitsfort)",
    "sg:orig_category":"Non-Classified Establishments",
    "sg:phone":"+32 2 663 05 00",
    "sg:postcode":"1170",
    "sg:province":"Bruxelles-Capitale",
    "wof:name":"Crumble Sprl",
    "wof:placetype":"venue"
},
  "geometry": {"coordinates":[4.4180498123,50.7956809998],"type":"Point"}
}