{
  "type": "Feature",
  "properties": {
    "addr:full":"Gieterijstr 92 Gent Limburg 3600",
    "addr:housenumber":"92",
    "addr:postcode":"gent;3600",
    "addr:street":"Gieterijstr",
    "iso:country":"BE",
    "sg:address":"Gieterijstr 92",
    "sg:city":"Gent",
    "sg:classifiers":[
        {
            "category":"Home & Garden",
            "subcategory":"Furniture",
            "type":"Retail Goods"
        }
    ],
    "sg:phone":"+32 89 84 84 44",
    "sg:postcode":"3600",
    "sg:province":"Limburg",
    "sg:tags":[
        "wood"
    ],
    "wof:name":"Genk Hout Nv",
    "wof:placetype":"venue"
},
  "geometry": {"coordinates":[5.4879322052,51.0034980774],"type":"Point"}
}