{
  "type": "Feature",
  "properties": {
    "iso:country":"BE",
    "sg:address":"Kanunnik Triestlaan 104",
    "sg:city":"Lovendegem",
    "sg:classifiers":[
        {
            "category":"Arena",
            "subcategory":"Sports Club",
            "type":"Entertainment"
        }
    ],
    "sg:phone":"+32 9 372 63 36",
    "sg:postcode":"9920",
    "sg:province":"Oost-Vlaanderen",
    "sg:tags":[
        "de"
    ],
    "wof:name":"B.c. Gentse Leeuwen",
    "wof:placetype":"venue"
},
  "geometry": {"coordinates":[3.6144471169,51.0992240906],"type":"Point"}
}