{
  "type": "Feature",
  "properties": {
    "iso:country":"BE",
    "sg:address":"Klingedorp 93",
    "sg:city":"Sint-gillis-waas",
    "sg:orig_category":"Banken and kredietinstellingen",
    "sg:phone":"+32 3 770 69 34",
    "sg:postcode":"9170",
    "sg:province":"Oost-Vlaanderen",
    "wof:name":"Anhyp",
    "wof:placetype":"venue"
},
  "geometry": {"coordinates":[4.0911102295,51.2592391968],"type":"Point"}
}