{
  "type": "Feature",
  "properties": {
    "iso:country":"BE",
    "sg:address":"Voie Am\u00c9riciane 9",
    "sg:city":"Mons",
    "sg:orig_category":"Boekhouders",
    "sg:phone":"+32 65 36 27 67",
    "sg:postcode":"7022",
    "sg:province":"Hainaut",
    "wof:name":"Delelienne Michel",
    "wof:placetype":"venue"
},
  "geometry": {"coordinates":[3.9596738815,50.426071167],"type":"Point"}
}