{
  "type": "Feature",
  "properties": {
    "addr:full":"Oorsprongstraat 9 Borgloon Limburg 3840",
    "addr:housenumber":"9",
    "addr:postcode":"3840",
    "addr:street":"Oorsprongstraat",
    "iso:country":"BE",
    "sg:address":"Oorsprongstraat 9",
    "sg:city":"Borgloon",
    "sg:orig_category":"Rev\u00eatements pour sols and murs. Peinture",
    "sg:phone":"+32 12 74 23 26",
    "sg:postcode":"3840",
    "sg:province":"Limburg",
    "wof:name":"Velkeniers Claesen",
    "wof:placetype":"venue"
},
  "geometry": {"coordinates":[5.3441700935,50.8012466431],"type":"Point"}
}