{
  "type": "Feature",
  "properties": {
    "iso:country":"BE",
    "sg:address":"Vijverstraat 17",
    "sg:city":"Tielt",
    "sg:classifiers":[
        {
            "category":"Building & Trades",
            "subcategory":"Construction",
            "type":"Services"
        }
    ],
    "sg:phone":"+32 51 40 30 52",
    "sg:postcode":"8700",
    "sg:province":"West-Vlaanderen",
    "sg:tags":[
        "stucco",
        "contractor"
    ],
    "wof:name":"Bekaert Freddy Plakwerken Bvba",
    "wof:placetype":"venue"
},
  "geometry": {"coordinates":[3.3292980194,50.9989089966],"type":"Point"}
}