{
  "type": "Feature",
  "properties": {
    "addr:full":"Torhoutse Steenweg 68 Brugge West-Vlaanderen 8200",
    "addr:housenumber":"68",
    "addr:postcode":"8200",
    "addr:street":"Torhoutse Steenweg",
    "iso:country":"BE",
    "sg:address":"Torhoutse Steenweg 68",
    "sg:city":"Brugge",
    "sg:orig_category":"Diverse kredietdiensten",
    "sg:postcode":"8200",
    "sg:province":"West-Vlaanderen",
    "wof:name":"Bancontact-mister Cash",
    "wof:placetype":"venue"
},
  "geometry": {"coordinates":[3.2048909664,51.2013130188],"type":"Point"}
}