{
  "type": "Feature",
  "properties": {
    "iso:country":"BE",
    "sg:address":"Vlietestraat 75",
    "sg:city":"Harelbeke",
    "sg:orig_category":"Schoonheidssalons",
    "sg:phone":"+32 56 71 59 84",
    "sg:postcode":"8531",
    "sg:province":"West-Vlaanderen",
    "wof:name":"Liliane Desplenter",
    "wof:placetype":"venue"
},
  "geometry": {"coordinates":[3.3063750267,50.8812141418],"type":"Point"}
}