{
  "type": "Feature",
  "properties": {
    "addr:full":"Vilvoordse Baan 20 Herent Vlaams-Brabant 3020",
    "addr:housenumber":"20",
    "addr:postcode":"3020",
    "addr:street":"Vilvoordse Baan",
    "iso:country":"BE",
    "sg:address":"Vilvoordse Baan 20",
    "sg:city":"Herent",
    "sg:orig_category":"Producteurs de l\u00e9gumes",
    "sg:phone":"+32 16 48 09 06",
    "sg:postcode":"3020",
    "sg:province":"Vlaams-Brabant",
    "wof:name":"Oscar Denies",
    "wof:placetype":"venue"
},
  "geometry": {"coordinates":[4.6749200821,50.9079055786],"type":"Point"}
}