{
  "type": "Feature",
  "properties": {
    "iso:country":"BE",
    "sg:address":"Pontweg 3",
    "sg:city":"Nazareth",
    "sg:orig_category":"Fleurs and plantes",
    "sg:phone":"+32 9 384 30 66",
    "sg:postcode":"9810",
    "sg:province":"Oost-Vlaanderen",
    "wof:name":"Arlette Van Schelstraete",
    "wof:placetype":"venue"
},
  "geometry": {"coordinates":[3.6436140537,50.9466133118],"type":"Point"}
}