{
  "type": "Feature",
  "properties": {
    "iso:country":"BE",
    "sg:address":"Rue Notre Dame 57",
    "sg:city":"Mons",
    "sg:orig_category":"Architectes",
    "sg:phone":"+32 65 84 27 14",
    "sg:postcode":"7000",
    "sg:province":"Hainaut",
    "wof:name":"Angelo Dore",
    "wof:placetype":"venue"
},
  "geometry": {"coordinates":[3.9509019852,50.4505691528],"type":"Point"}
}