{
  "type": "Feature",
  "properties": {
    "addr:full":"Chauss\u00e9e De Mons 82 Bruxelles (anderlecht) Bruxelles-Capitale 1070",
    "addr:housenumber":"82",
    "addr:postcode":"1070",
    "addr:street":"Chausse\u0301E De Mons",
    "iso:country":"BE",
    "sg:address":"Chauss\u00e9e De Mons 82",
    "sg:city":"Bruxelles (anderlecht)",
    "sg:classifiers":[
        {
            "category":"Shopping",
            "subcategory":"Books",
            "type":"Retail Goods"
        }
    ],
    "sg:phone":"+32 2 524 05 30",
    "sg:postcode":"1070",
    "sg:province":"Bruxelles-Capitale",
    "sg:tags":[
        "bookseller"
    ],
    "wof:name":"Carrefour Presse",
    "wof:placetype":"venue"
},
  "geometry": {"coordinates":[4.3344111443,50.8434524536],"type":"Point"}
}