{
  "type": "Feature",
  "properties": {
    "addr:full":"Lange Leemstraat 201 Antwerpen Antwerpen 2018",
    "addr:housenumber":"201",
    "addr:postcode":"2018",
    "addr:street":"Lange Leemstraat",
    "iso:country":"BE",
    "sg:address":"Lange Leemstraat 201",
    "sg:city":"Antwerpen",
    "sg:classifiers":[
        {
            "category":"Fast Food",
            "type":"Food & Drink"
        }
    ],
    "sg:phone":"+32 3 239 02 26",
    "sg:postcode":"2018",
    "sg:province":"Antwerpen",
    "sg:tags":[
        "meeneem",
        "restaurant"
    ],
    "wof:name":"Happy Garden",
    "wof:placetype":"venue"
},
  "geometry": {"coordinates":[4.4170641899,51.2062835693],"type":"Point"}
}