{
  "type": "Feature",
  "properties": {
    "addr:full":"Eeuwfeestlaan 25 De Pinte Oost-Vlaanderen 9840",
    "addr:housenumber":"25",
    "addr:postcode":"9840",
    "addr:street":"Eeuwfeestlaan",
    "iso:country":"BE",
    "sg:address":"Eeuwfeestlaan 25",
    "sg:city":"De Pinte",
    "sg:classifiers":[
        {
            "category":"Professional",
            "subcategory":"Management & Consulting",
            "type":"Services"
        }
    ],
    "sg:phone":"+32 9 280 03 17",
    "sg:postcode":"9840",
    "sg:province":"Oost-Vlaanderen",
    "sg:tags":[
        "consultant"
    ],
    "wof:name":"Balcaen Consult Ez",
    "wof:placetype":"venue"
},
  "geometry": {"coordinates":[3.6488850117,50.9887161255],"type":"Point"}
}