{
  "type": "Feature",
  "properties": {
    "iso:country":"BE",
    "sg:address":"Reepkaai 4",
    "sg:city":"Kortrijk",
    "sg:orig_category":"Rusthuizen and serviceflats Ziekenhuizen and zorginstellingen Ziekenvervoer",
    "sg:phone":"+32 56 30 51 11",
    "sg:postcode":"8500",
    "sg:province":"West-Vlaanderen",
    "wof:name":"Onze-lieve-vrouwehospitaal Kortrijk",
    "wof:placetype":"venue"
},
  "geometry": {"coordinates":[3.262873888,50.8299331665],"type":"Point"}
}