{
  "type": "Feature",
  "properties": {
    "addr:full":"Perrestraat 20 Herzele Oost-Vlaanderen 9550",
    "addr:housenumber":"20",
    "addr:postcode":"9550",
    "addr:street":"Perrestraat;Oost-Vlaanderen",
    "iso:country":"BE",
    "sg:address":"Perrestraat 20",
    "sg:city":"Herzele",
    "sg:orig_category":"Enseignement maternel and primaire",
    "sg:phone":"+32 9 360 17 44",
    "sg:postcode":"9550",
    "sg:province":"Oost-Vlaanderen",
    "wof:name":"Gemeentelijke Basisschool",
    "wof:placetype":"venue"
},
  "geometry": {"coordinates":[3.855148077,50.8941383362],"type":"Point"}
}