{
  "type": "Feature",
  "properties": {
    "addr:full":"Alphonse Poulletstraat 35 Moeskroen/mouscron Hainaut 7711",
    "addr:housenumber":"35",
    "addr:postcode":"7711",
    "addr:street":"Poulletstraat",
    "iso:country":"BE",
    "sg:address":"Alphonse Poulletstraat 35",
    "sg:city":"Moeskroen/mouscron",
    "sg:orig_category":"Landmeters Landmeters and schatters",
    "sg:phone":"+32 56 48 82 76",
    "sg:postcode":"7711",
    "sg:province":"Hainaut",
    "wof:name":"Guy Moulin",
    "wof:placetype":"venue"
},
  "geometry": {"coordinates":[3.30428195,50.7291755676],"type":"Point"}
}