{
  "type": "Feature",
  "properties": {
    "iso:country":"BE",
    "sg:address":"Lepelstraat 125",
    "sg:city":"Lommel",
    "sg:classifiers":[
        {
            "category":"Professional",
            "subcategory":"Lawyer & Legal Services",
            "type":"Services"
        }
    ],
    "sg:phone":"+32 11 54 08 08",
    "sg:postcode":"3920",
    "sg:province":"Limburg",
    "wof:name":"Vanvelthoven Peter",
    "wof:placetype":"venue"
},
  "geometry": {"coordinates":[5.3085598946,51.2342185974],"type":"Point"}
}