{
  "type": "Feature",
  "properties": {
    "iso:country":"BE",
    "sg:address":"Vrijheid 63",
    "sg:city":"Hoogstraten",
    "sg:classifiers":[
        {
            "category":"Food & Beverages",
            "subcategory":"Chocolate",
            "type":"Retail Goods"
        }
    ],
    "sg:phone":"+32 3 314 21 24",
    "sg:postcode":"2320",
    "sg:province":"Antwerpen",
    "sg:tags":[
        "confectionery",
        "-"
    ],
    "wof:name":"Chocoladehuis (het)",
    "wof:placetype":"venue"
},
  "geometry": {"coordinates":[4.7631568909,51.4052467346],"type":"Point"}
}