{
  "type": "Feature",
  "properties": {
    "addr:full":"Pastorijstraat 4b4 Grimbergen Vlaams-Brabant 1853",
    "addr:housenumber":"4b4",
    "addr:postcode":"1853",
    "addr:street":"Pastorijstraat",
    "iso:country":"BE",
    "sg:address":"Pastorijstraat 4b4",
    "sg:city":"Grimbergen",
    "sg:orig_category":"Beheer onroerend goed",
    "sg:phone":"+32 2 252 40 87",
    "sg:postcode":"1853",
    "sg:province":"Vlaams-Brabant",
    "wof:name":"Beheerkant. Van Strombeek",
    "wof:placetype":"venue"
},
  "geometry": {"coordinates":[4.354924202,50.9092559814],"type":"Point"}
}