{
  "type": "Feature",
  "properties": {
    "addr:full":"Koolbroek 2 Anzegem West-Vlaanderen 8572",
    "addr:housenumber":"2",
    "addr:postcode":"8572",
    "addr:street":"Koolbroek",
    "iso:country":"BE",
    "sg:address":"Koolbroek 2",
    "sg:city":"Anzegem",
    "sg:orig_category":"Rundveehouders",
    "sg:phone":"+32 56 68 87 18",
    "sg:postcode":"8572",
    "sg:province":"West-Vlaanderen",
    "wof:name":"Achiel Avet",
    "wof:placetype":"venue"
},
  "geometry": {"coordinates":[3.4944291115,50.8026161194],"type":"Point"}
}