{
  "type": "Feature",
  "properties": {
    "addr:full":"Kwadeweg 175 Evergem Oost-Vlaanderen 9940",
    "addr:housenumber":"175",
    "addr:postcode":"9940",
    "addr:street":"Kwadeweg;Oost-Vlaanderen",
    "iso:country":"BE",
    "sg:address":"Kwadeweg 175",
    "sg:city":"Evergem",
    "sg:classifiers":[
        {
            "category":"Food & Beverages",
            "subcategory":"Fruits & Vegetables",
            "type":"Retail Goods"
        }
    ],
    "sg:phone":"+32 9 357 54 10",
    "sg:postcode":"9940",
    "sg:province":"Oost-Vlaanderen",
    "sg:tags":[
        "groenten"
    ],
    "wof:name":"Julien Vanhoet",
    "wof:placetype":"venue"
},
  "geometry": {"coordinates":[3.6912600994,51.1144218445],"type":"Point"}
}