{
  "type": "Feature",
  "properties": {
    "iso:country":"BE",
    "sg:address":"Grote Baan 362",
    "sg:city":"Houthalen-helchteren",
    "sg:orig_category":"Woningbouw",
    "sg:phone":"+32 11 74 00 45",
    "sg:postcode":"3530",
    "sg:province":"Limburg",
    "wof:name":"Bdvs",
    "wof:placetype":"venue"
},
  "geometry": {"coordinates":[5.3802499771,51.0446510315],"type":"Point"}
}