{
  "type": "Feature",
  "properties": {
    "iso:country":"BE",
    "sg:address":"7110",
    "sg:city":"La Louviere",
    "sg:orig_category":"Eleveurs d'animaux domestiques",
    "sg:phone":"+32 64 55 72 76",
    "sg:postcode":"7110",
    "sg:province":"Hainaut",
    "wof:name":"Des Pres De Couri\u00c8re",
    "wof:placetype":"venue"
},
  "geometry": {"coordinates":[4.1340098381,50.4762802124],"type":"Point"}
}