{
  "type": "Feature",
  "properties": {
    "addr:full":"Kleine Monnikenwerve 9 Brugge West-Vlaanderen 8000",
    "addr:housenumber":"9",
    "addr:postcode":"8000",
    "addr:street":"Kleine Monnikenwerve",
    "iso:country":"BE",
    "sg:address":"Kleine Monnikenwerve 9",
    "sg:city":"Brugge",
    "sg:classifiers":[
        {
            "category":"Wholesale",
            "subcategory":"Machinery & Supplies",
            "type":"Manufacturing & Wholesale Goods"
        }
    ],
    "sg:phone":"+32 50 31 89 01",
    "sg:postcode":"8000",
    "sg:province":"West-Vlaanderen",
    "sg:tags":[
        "packing"
    ],
    "wof:name":"Alliance Engineering Services Europe Bvba",
    "wof:placetype":"venue"
},
  "geometry": {"coordinates":[3.2025969028,51.2446212769],"type":"Point"}
}