{
  "type": "Feature",
  "properties": {
    "addr:full":"Rue Du Rond-point 302 Charleroi Hainaut 6060",
    "addr:housenumber":"302",
    "addr:postcode":"6060",
    "addr:street":"Rue Du Rond-Point;Hainaut",
    "iso:country":"BE",
    "sg:address":"Rue Du Rond-point 302",
    "sg:city":"Charleroi",
    "sg:orig_category":"Services fun\u00e9raires. Traitement and fa\u00e7onnage de la pierre",
    "sg:phone":"+32 71 41 50 55",
    "sg:postcode":"6060",
    "sg:province":"Hainaut",
    "wof:name":"Hennau Pompes Funebres",
    "wof:placetype":"venue"
},
  "geometry": {"coordinates":[4.4917521477,50.4390335083],"type":"Point"}
}