{
  "type": "Feature",
  "properties": {
    "addr:full":"Hoekvijverslaan 15 Hasselt Limburg 3500",
    "addr:housenumber":"15",
    "addr:postcode":"3500",
    "addr:street":"Hoekvijverslaan",
    "iso:country":"BE",
    "sg:address":"Hoekvijverslaan 15",
    "sg:city":"Hasselt",
    "sg:classifiers":[
        {
            "category":"Professional",
            "subcategory":"Printing & Photocopies",
            "type":"Services"
        }
    ],
    "sg:phone":"+32 11 24 24 39",
    "sg:postcode":"3500",
    "sg:province":"Limburg",
    "sg:tags":[
        "machine",
        "equipment"
    ],
    "wof:name":"Zadikon",
    "wof:placetype":"venue"
},
  "geometry": {"coordinates":[5.3715209961,50.946647644],"type":"Point"}
}