{
  "type": "Feature",
  "properties": {
    "addr:full":"Rue Etienne Soubre 33 Li\u00c8ge Li\u00e8ge 4000",
    "addr:housenumber":"33",
    "addr:postcode":"4000",
    "addr:street":"Rue Etienne Soubre",
    "iso:country":"BE",
    "sg:address":"Rue Etienne Soubre 33",
    "sg:city":"Li\u00c8ge",
    "sg:orig_category":"Architecten",
    "sg:phone":"+32 4 222 24 51",
    "sg:postcode":"4000",
    "sg:province":"Li\u00e8ge",
    "wof:name":"Didier Vonneche",
    "wof:placetype":"venue"
},
  "geometry": {"coordinates":[5.559032917,50.6381149292],"type":"Point"}
}