{
  "type": "Feature",
  "properties": {
    "iso:country":"BE",
    "sg:address":"Schemeringlaan 14ba",
    "sg:city":"Overijse",
    "sg:orig_category":"Boekhouders",
    "sg:phone":"+32 2 687 69 28",
    "sg:postcode":"3090",
    "sg:province":"Vlaams-Brabant",
    "wof:name":"Marie-p. Christophe",
    "wof:placetype":"venue"
},
  "geometry": {"coordinates":[4.5182747841,50.7745132446],"type":"Point"}
}