{
  "type": "Feature",
  "properties": {
    "addr:full":"Rue Du Rabiseau Fleurus Hainaut 6220",
    "addr:postcode":"6220",
    "addr:street":"Rue Du Rabiseau;Hainaut",
    "iso:country":"BE",
    "sg:address":"Rue Du Rabiseau",
    "sg:city":"Fleurus",
    "sg:classifiers":[
        {
            "category":"Home & Garden",
            "subcategory":"Home Furnishings",
            "type":"Retail Goods"
        }
    ],
    "sg:phone":"+32 71 87 60 01",
    "sg:postcode":"6220",
    "sg:province":"Hainaut",
    "sg:tags":[
        "illumination"
    ],
    "wof:name":"Netolite Sa",
    "wof:placetype":"venue"
},
  "geometry": {"coordinates":[4.5496749878,50.4825363159],"type":"Point"}
}