{
  "type": "Feature",
  "properties": {
    "addr:full":"Place St-lambert 16 Liege Li\u00e8ge 4000",
    "addr:housenumber":"16",
    "addr:postcode":"4000",
    "addr:street":"Place St-Lambert",
    "iso:country":"BE",
    "sg:address":"Place St-lambert 16",
    "sg:city":"Liege",
    "sg:orig_category":"Warenhuizen",
    "sg:phone":"+32 4 220 70 10",
    "sg:postcode":"4000",
    "sg:province":"Li\u00e8ge",
    "wof:name":"Hema",
    "wof:placetype":"venue"
},
  "geometry": {"coordinates":[5.5742330551,50.6455764771],"type":"Point"}
}