{
  "type": "Feature",
  "properties": {
    "iso:country":"BE",
    "sg:address":"Rue De Gaumi\u00e9mont 90",
    "sg:city":"Etalle",
    "sg:classifiers":[
        {
            "category":"Building & Trades",
            "subcategory":"Landscaping Services",
            "type":"Services"
        }
    ],
    "sg:phone":"+32 63 45 64 34",
    "sg:postcode":"6740",
    "sg:province":"Luxembourg",
    "sg:tags":[
        "forestry"
    ],
    "wof:name":"Dejana Thierry Sc",
    "wof:placetype":"venue"
},
  "geometry": {"coordinates":[5.6019248962,49.6724891663],"type":"Point"}
}