{
  "type": "Feature",
  "properties": {
    "addr:full":"Blekte 66 Lede (oordegem) Oost-Vlaanderen 9340",
    "addr:housenumber":"66",
    "addr:postcode":"9340",
    "addr:street":"Blekte",
    "iso:country":"BE",
    "sg:address":"Blekte 66",
    "sg:city":"Lede (oordegem)",
    "sg:classifiers":[
        {
            "category":"Wholesale",
            "subcategory":"Beer",
            "type":"Manufacturing & Wholesale Goods"
        }
    ],
    "sg:phone":"+32 9 369 88 70",
    "sg:postcode":"9340",
    "sg:province":"Oost-Vlaanderen",
    "sg:tags":[
        "ale",
        "-"
    ],
    "wof:name":"De Winter F",
    "wof:placetype":"venue"
},
  "geometry": {"coordinates":[3.9101800919,50.969455719],"type":"Point"}
}