{
  "type": "Feature",
  "properties": {
    "addr:full":"Bornstrasse 23 Bntgenbach/bntgenbach Li\u00e8ge 4750",
    "addr:housenumber":"23",
    "addr:postcode":"4750",
    "addr:street":"Bornstrasse",
    "iso:country":"BE",
    "sg:address":"Bornstrasse 23",
    "sg:city":"Bntgenbach/bntgenbach",
    "sg:orig_category":"Rundveehouders",
    "sg:phone":"+32 80 44 68 09",
    "sg:postcode":"4750",
    "sg:province":"Li\u00e8ge",
    "wof:name":"Hermann Heinen",
    "wof:placetype":"venue"
},
  "geometry": {"coordinates":[6.2205519676,50.4354972839],"type":"Point"}
}