{
  "type": "Feature",
  "properties": {
    "iso:country":"BE",
    "sg:address":"Rue Du Mont Des Carliers 22",
    "sg:city":"Tournai (blandain - Hertain)",
    "sg:classifiers":[
        {
            "category":"Professional",
            "subcategory":"Art Services",
            "type":"Services"
        }
    ],
    "sg:phone":"+32 69 88 84 66",
    "sg:postcode":"7522",
    "sg:province":"Hainaut",
    "sg:tags":[
        "-",
        "mailing",
        "lettershops",
        "direct",
        "mail"
    ],
    "wof:name":"Cermas Routage Europ\u00e9en Sa",
    "wof:placetype":"venue"
},
  "geometry": {"coordinates":[3.3198549747,50.6235809326],"type":"Point"}
}