{
  "type": "Feature",
  "properties": {
    "addr:full":"Pladutse 5 Oudenaarde Oost-Vlaanderen 9700",
    "addr:housenumber":"5",
    "addr:postcode":"9700",
    "addr:street":"Pladutse",
    "iso:country":"BE",
    "sg:address":"Pladutse 5",
    "sg:city":"Oudenaarde",
    "sg:orig_category":"Eleveurs de bovins",
    "sg:phone":"+32 55 38 84 99",
    "sg:postcode":"9700",
    "sg:province":"Oost-Vlaanderen",
    "wof:name":"Georges Blommaert",
    "wof:placetype":"venue"
},
  "geometry": {"coordinates":[3.5725109577,50.7986335754],"type":"Point"}
}