{
  "type": "Feature",
  "properties": {
    "iso:country":"BE",
    "sg:address":"Singel 22",
    "sg:city":"Gent",
    "sg:classifiers":[
        {
            "category":"Manufacturing",
            "subcategory":"Textiles",
            "type":"Manufacturing & Wholesale Goods"
        }
    ],
    "sg:phone":"+32 9 255 92 92",
    "sg:postcode":"9000",
    "sg:province":"Oost-Vlaanderen",
    "sg:tags":[
        "spinning",
        "weaving",
        "mill"
    ],
    "wof:name":"Lys-lieve Nv",
    "wof:placetype":"venue"
},
  "geometry": {"coordinates":[3.7486150265,51.0831985474],"type":"Point"}
}