{
  "type": "Feature",
  "properties": {
    "iso:country":"BE",
    "sg:address":"Golvenstraat 10b6",
    "sg:city":"Oostende",
    "sg:orig_category":"Eclairage et \u00e9quipements du foyer",
    "sg:phone":"+32 59 70 67 75",
    "sg:postcode":"8400",
    "sg:province":"West-Vlaanderen",
    "wof:name":"Claudine Bonte",
    "wof:placetype":"venue"
},
  "geometry": {"coordinates":[2.8982870579,51.214756012],"type":"Point"}
}