{
  "type": "Feature",
  "properties": {
    "iso:country":"BE",
    "sg:address":"Grote Zavel 21",
    "sg:city":"Brussel/bruxelles",
    "sg:orig_category":"Artiesten and kunstenaars",
    "sg:phone":"+32 2 512 34 99",
    "sg:postcode":"1000",
    "sg:province":"Bruxelles-Capitale",
    "wof:name":"Nicole Jacquemin",
    "wof:placetype":"venue"
},
  "geometry": {"coordinates":[4.3554801941,50.8409385681],"type":"Point"}
}