{
  "type": "Feature",
  "properties": {
    "addr:full":"Bronstraat 44 Oudenaarde (mater) Oost-Vlaanderen 9700",
    "addr:housenumber":"44",
    "addr:postcode":"9700",
    "addr:street":"Bronstraat;Mater Oost-Vlaanderen",
    "iso:country":"BE",
    "sg:address":"Bronstraat 44",
    "sg:city":"Oudenaarde (mater)",
    "sg:classifiers":[
        {
            "category":"Professional",
            "subcategory":"Management & Consulting",
            "type":"Services"
        }
    ],
    "sg:phone":"+32 55 45 50 02",
    "sg:postcode":"9700",
    "sg:province":"Oost-Vlaanderen",
    "sg:tags":[
        "consultant"
    ],
    "wof:name":"Dynac Nv",
    "wof:placetype":"venue"
},
  "geometry": {"coordinates":[3.6619470119,50.8517150879],"type":"Point"}
}