{
  "type": "Feature",
  "properties": {
    "addr:full":"Bevelsesteenweg 135 Nijlen Antwerpen 2560",
    "addr:housenumber":"135",
    "addr:postcode":"2560",
    "addr:street":"Bevelsesteenweg",
    "iso:country":"BE",
    "sg:address":"Bevelsesteenweg 135",
    "sg:city":"Nijlen",
    "sg:orig_category":"Groententeelt",
    "sg:phone":"+32 3 481 71 28",
    "sg:postcode":"2560",
    "sg:province":"Antwerpen",
    "wof:name":"Franciscus Vets",
    "wof:placetype":"venue"
},
  "geometry": {"coordinates":[4.673789978,51.1535186768],"type":"Point"}
}