{
  "type": "Feature",
  "properties": {
    "addr:full":"Stationstraat 37 Ardooie West-Vlaanderen 8850",
    "addr:housenumber":"37",
    "addr:postcode":"8850",
    "addr:street":"Stationstraat",
    "iso:country":"BE",
    "sg:address":"Stationstraat 37",
    "sg:city":"Ardooie",
    "sg:orig_category":"Banken and kredietinstellingen",
    "sg:phone":"+32 51 74 06 50",
    "sg:postcode":"8850",
    "sg:province":"West-Vlaanderen",
    "wof:name":"Kbc",
    "wof:placetype":"venue"
},
  "geometry": {"coordinates":[3.1991140842,50.980091095],"type":"Point"}
}