{
  "type": "Feature",
  "properties": {
    "addr:full":"Breidelstraat 8 Oostende West-Vlaanderen 8400",
    "addr:housenumber":"8",
    "addr:postcode":"8400",
    "addr:street":"Breidelstraat",
    "iso:country":"BE",
    "sg:address":"Breidelstraat 8",
    "sg:city":"Oostende",
    "sg:orig_category":"Reisbureaus",
    "sg:phone":"+32 59 70 83 61",
    "sg:postcode":"8400",
    "sg:province":"West-Vlaanderen",
    "wof:name":"Vtb-vab",
    "wof:placetype":"venue"
},
  "geometry": {"coordinates":[2.9188220501,51.2322235107],"type":"Point"}
}