{
  "type": "Feature",
  "properties": {
    "iso:country":"BE",
    "sg:address":"Quartier Du Pont 22",
    "sg:city":"La Louviere",
    "sg:classifiers":[
        {
            "category":"Insurance",
            "subcategory":"Life Insurance",
            "type":"Services"
        }
    ],
    "sg:phone":"+32 64 28 19 12",
    "sg:postcode":"7100",
    "sg:province":"Hainaut",
    "sg:tags":[
        "assurance"
    ],
    "wof:name":"Michel Duby",
    "wof:placetype":"venue"
},
  "geometry": {"coordinates":[4.2150301933,50.4732322693],"type":"Point"}
}