{
  "type": "Feature",
  "properties": {
    "iso:country":"BE",
    "sg:address":"Rijselseweg 164",
    "sg:city":"Ieper",
    "sg:orig_category":"Landbouwmachines Gh",
    "sg:phone":"+32 57 20 11 47",
    "sg:postcode":"8902",
    "sg:province":"West-Vlaanderen",
    "wof:name":"Jan Lemahieu",
    "wof:placetype":"venue"
},
  "geometry": {"coordinates":[2.8898620605,50.8459777832],"type":"Point"}
}