{
  "type": "Feature",
  "properties": {
    "iso:country":"BE",
    "sg:address":"Frans Gasthuislaan 42",
    "sg:city":"Sint-agatha-berchem/berchem-sainte-agathe",
    "sg:orig_category":"Brood, gebak and snoepgoed",
    "sg:phone":"+32 2 420 05 53",
    "sg:postcode":"1082",
    "sg:province":"Bruxelles-Capitale",
    "wof:name":"P\u00c2tisserie Chris-soft",
    "wof:placetype":"venue"
},
  "geometry": {"coordinates":[4.3128361702,50.8671684265],"type":"Point"}
}