{
  "type": "Feature",
  "properties": {
    "iso:country":"BE",
    "sg:address":"Rue Englebert Lescrenier 45",
    "sg:city":"Awans (oth\u00e9e)",
    "sg:classifiers":[
        {
            "category":"Health Services",
            "subcategory":"Dentist",
            "type":"Services"
        }
    ],
    "sg:phone":"+32 4 257 54 04",
    "sg:postcode":"4340",
    "sg:province":"Li\u00e8ge",
    "wof:name":"Poncelet Christine",
    "wof:placetype":"venue"
},
  "geometry": {"coordinates":[5.4704189301,50.7085838318],"type":"Point"}
}