{
  "type": "Feature",
  "properties": {
    "iso:country":"BE",
    "sg:address":"Haagdoornstraat 28",
    "sg:city":"Neerpelt",
    "sg:classifiers":[
        {
            "category":"Health Services",
            "subcategory":"Health Practitioner",
            "type":"Services"
        }
    ],
    "sg:phone":"+32 11 66 18 58",
    "sg:postcode":"3910",
    "sg:province":"Limburg",
    "sg:tags":[
        "therapist",
        "speech"
    ],
    "wof:name":"Put L",
    "wof:placetype":"venue"
},
  "geometry": {"coordinates":[5.4190411568,51.2300186157],"type":"Point"}
}