{
  "type": "Feature",
  "properties": {
    "addr:full":"Steenweg Op Antwerpen 35 Turnhout Antwerpen 2300",
    "addr:housenumber":"35",
    "addr:postcode":"2300",
    "addr:street":"Steenweg Op Antwerpen",
    "iso:country":"BE",
    "sg:address":"Steenweg Op Antwerpen 35",
    "sg:city":"Turnhout",
    "sg:classifiers":[
        {
            "category":"Health Services",
            "subcategory":"Doctor",
            "type":"Services"
        }
    ],
    "sg:phone":"+32 14 41 23 33",
    "sg:postcode":"2300",
    "sg:province":"Antwerpen",
    "sg:tags":[
        "medicinephysicians",
        "surgeon"
    ],
    "wof:name":"Gillis Ren\u00e9",
    "wof:placetype":"venue"
},
  "geometry": {"coordinates":[4.9229221344,51.319480896],"type":"Point"}
}