{
  "type": "Feature",
  "properties": {
    "iso:country":"BE",
    "sg:address":"Rue Dourlet 103",
    "sg:city":"Charleroi",
    "sg:classifiers":[
        {
            "category":"Taxi",
            "type":"Transportation"
        }
    ],
    "sg:phone":"+32 71 48 82 00",
    "sg:postcode":"6000",
    "sg:province":"Hainaut",
    "sg:tags":[
        "taxi's"
    ],
    "wof:name":"Confort Tax",
    "wof:placetype":"venue"
},
  "geometry": {"coordinates":[4.45480299,50.4200325012],"type":"Point"}
}