{
  "type": "Feature",
  "properties": {
    "addr:full":"Stationsstraat 106-108 Gavere Oost-Vlaanderen 9890",
    "addr:housenumber":"106-108",
    "addr:postcode":"9890",
    "addr:street":"Stationsstraat",
    "iso:country":"BE",
    "sg:address":"Stationsstraat 106-108",
    "sg:city":"Gavere",
    "sg:orig_category":"Non-Classified Establishments",
    "sg:phone":"+32 9 384 69 39",
    "sg:postcode":"9890",
    "sg:province":"Oost-Vlaanderen",
    "wof:name":"E.v.d. Mode",
    "wof:placetype":"venue"
},
  "geometry": {"coordinates":[3.6481471062,50.9294776917],"type":"Point"}
}