{
  "type": "Feature",
  "properties": {
    "iso:country":"BE",
    "sg:address":"Dubbeekstraat 192",
    "sg:city":"Aarschot",
    "sg:orig_category":"Producteurs de l\u00e9gumes. Producteurs de fruits",
    "sg:phone":"+32 16 56 11 90",
    "sg:postcode":"3200",
    "sg:province":"Vlaams-Brabant",
    "wof:name":"Gustaaf Janssens",
    "wof:placetype":"venue"
},
  "geometry": {"coordinates":[4.8405418396,50.9635925293],"type":"Point"}
}