{
  "type": "Feature",
  "properties": {
    "iso:country":"BE",
    "sg:address":"Beukenlei 58",
    "sg:city":"Brecht",
    "sg:orig_category":"Traitements param\u00e9dicaux",
    "sg:phone":"+32 3 636 43 46",
    "sg:postcode":"2960",
    "sg:province":"Antwerpen",
    "wof:name":"Wendy Steurs",
    "wof:placetype":"venue"
},
  "geometry": {"coordinates":[4.5634908676,51.3066062927],"type":"Point"}
}