{
  "type": "Feature",
  "properties": {
    "iso:country":"BE",
    "sg:address":"Chauss\u00e9e De Louvain 387",
    "sg:city":"Wavre",
    "sg:classifiers":[
        {
            "category":"Building & Trades",
            "subcategory":"Construction",
            "type":"Services"
        }
    ],
    "sg:phone":"+32 10 22 32 49",
    "sg:postcode":"1300",
    "sg:province":"Brabant Wallon",
    "sg:tags":[
        "stucco",
        "contractor"
    ],
    "wof:name":"Reno Sud",
    "wof:placetype":"venue"
},
  "geometry": {"coordinates":[4.6253399849,50.7220458984],"type":"Point"}
}