{
  "type": "Feature",
  "properties": {
    "addr:full":"Drogentop 3 Ninove Oost-Vlaanderen 9400",
    "addr:housenumber":"3",
    "addr:postcode":"9400",
    "addr:street":"Drogentop",
    "iso:country":"BE",
    "sg:address":"Drogentop 3",
    "sg:city":"Ninove",
    "sg:orig_category":"Installation \u00e9lectrique r\u00e9sidentielle",
    "sg:phone":"+32 54 33 46 94",
    "sg:postcode":"9400",
    "sg:province":"Oost-Vlaanderen",
    "wof:name":"Koen De Vidts",
    "wof:placetype":"venue"
},
  "geometry": {"coordinates":[4.0232000351,50.8349113464],"type":"Point"}
}