{
  "type": "Feature",
  "properties": {
    "addr:full":"Rue Eug\u00e8ne Gilles 6 Les Bons Villers (frasnes-lez-gosselies) Hainaut 6210",
    "addr:housenumber":"6",
    "addr:postcode":"6210",
    "addr:street":"Rue Euge\u0300Ne Gilles",
    "iso:country":"BE",
    "sg:address":"Rue Eug\u00e8ne Gilles 6",
    "sg:city":"Les Bons Villers (frasnes-lez-gosselies)",
    "sg:classifiers":[
        {
            "category":"Shopping",
            "subcategory":"Books",
            "type":"Retail Goods"
        }
    ],
    "sg:phone":"+32 71 85 46 42",
    "sg:postcode":"6210",
    "sg:province":"Hainaut",
    "sg:tags":[
        "bookseller"
    ],
    "wof:name":"Duvipress Le Marais",
    "wof:placetype":"venue"
},
  "geometry": {"coordinates":[4.4511561394,50.5378227234],"type":"Point"}
}