{
  "type": "Feature",
  "properties": {
    "iso:country":"BE",
    "sg:address":"Ernest Masoinlaan 89",
    "sg:city":"Brussel/bruxelles",
    "sg:orig_category":"Artsen and specialisten",
    "sg:phone":"+32 2 479 05 35",
    "sg:postcode":"1020",
    "sg:province":"Bruxelles-Capitale",
    "wof:name":"S. Loomans",
    "wof:placetype":"venue"
},
  "geometry": {"coordinates":[4.3352279663,50.8869400024],"type":"Point"}
}