{
  "type": "Feature",
  "properties": {
    "iso:country":"BE",
    "sg:address":"Casinoplein 10",
    "sg:city":"Kortrijk",
    "sg:classifiers":[
        {
            "category":"Shopping Center",
            "type":"Public Place"
        }
    ],
    "sg:phone":"+32 56 22 73 51",
    "sg:postcode":"8500",
    "sg:province":"West-Vlaanderen",
    "sg:tags":[
        "enseignement",
        "formation"
    ],
    "wof:name":"B.l.c.c. Taaltrainingen",
    "wof:placetype":"venue"
},
  "geometry": {"coordinates":[3.2620210648,50.8257102966],"type":"Point"}
}