{
  "type": "Feature",
  "properties": {
    "addr:full":"Veldonkstraat 9 Tremelo Vlaams-Brabant 3120",
    "addr:housenumber":"9",
    "addr:postcode":"3120",
    "addr:street":"Veldonkstraat",
    "iso:country":"BE",
    "sg:address":"Veldonkstraat 9",
    "sg:city":"Tremelo",
    "sg:orig_category":"Supermarkten",
    "sg:phone":"+32 16 53 13 71",
    "sg:postcode":"3120",
    "sg:province":"Vlaams-Brabant",
    "wof:name":"Unic",
    "wof:placetype":"venue"
},
  "geometry": {"coordinates":[4.7061300278,50.9896202087],"type":"Point"}
}