{
  "type": "Feature",
  "properties": {
    "iso:country":"BE",
    "sg:address":"Rue Des Charrettes 28",
    "sg:city":"Paliseul",
    "sg:orig_category":"Tabac. Imprimeries and copyshops",
    "sg:phone":"+32 61 53 53 47",
    "sg:postcode":"6850",
    "sg:province":"Luxembourg",
    "wof:name":"Imprimerie Barras",
    "wof:placetype":"venue"
},
  "geometry": {"coordinates":[5.1395001411,49.9090919495],"type":"Point"}
}