{
  "type": "Feature",
  "properties": {
    "addr:full":"Avenue Du Monoplan 41 Sint-pieters-woluwe/woluwe-saint-pierre Bruxelles-Capitale 1150",
    "addr:housenumber":"41",
    "addr:postcode":"1150",
    "addr:street":"Avenue Du Monoplan;/",
    "iso:country":"BE",
    "sg:address":"Avenue Du Monoplan 41",
    "sg:city":"Sint-pieters-woluwe/woluwe-saint-pierre",
    "sg:orig_category":"Agences immobili\u00e8res",
    "sg:phone":"+32 2 772 32 78",
    "sg:postcode":"1150",
    "sg:province":"Bruxelles-Capitale",
    "wof:name":"Immo J.m.c.",
    "wof:placetype":"venue"
},
  "geometry": {"coordinates":[4.4515328407,50.8325119019],"type":"Point"}
}