{
  "type": "Feature",
  "properties": {
    "iso:country":"BE",
    "sg:address":"Watervoort 77",
    "sg:city":"Herentals",
    "sg:orig_category":"Eleveurs de bovins",
    "sg:phone":"+32 14 21 20 83",
    "sg:postcode":"2200",
    "sg:province":"Antwerpen",
    "wof:name":"Frans Nuyts",
    "wof:placetype":"venue"
},
  "geometry": {"coordinates":[4.8266358376,51.1987876892],"type":"Point"}
}