{
  "type": "Feature",
  "properties": {
    "addr:full":"Courtil 110 Gouvy (bovigny) Luxembourg 6671",
    "addr:housenumber":"110",
    "addr:postcode":"6671",
    "addr:street":"Courtil",
    "iso:country":"BE",
    "sg:address":"Courtil 110",
    "sg:city":"Gouvy (bovigny)",
    "sg:classifiers":[
        {
            "category":"Professional",
            "subcategory":"Advertising",
            "type":"Services"
        }
    ],
    "sg:phone":"+32 80 21 54 62",
    "sg:postcode":"6671",
    "sg:province":"Luxembourg",
    "sg:tags":[
        "clothes"
    ],
    "wof:name":"Graphiset Belgium Sc",
    "wof:placetype":"venue"
},
  "geometry": {"coordinates":[5.9153008461,50.2131004333],"type":"Point"}
}