{
  "type": "Feature",
  "properties": {
    "iso:country":"BE",
    "sg:address":"Place 12",
    "sg:city":"Rumes",
    "sg:orig_category":"Installation \u00e9lectrique r\u00e9sidentielle",
    "sg:phone":"+32 69 64 75 90",
    "sg:postcode":"7618",
    "sg:province":"Hainaut",
    "wof:name":"Jean-michel Desmedt",
    "wof:placetype":"venue"
},
  "geometry": {"coordinates":[3.303841114,50.5545730591],"type":"Point"}
}