{
  "type": "Feature",
  "properties": {
    "iso:country":"BE",
    "sg:address":"Middenstraat 51",
    "sg:city":"Essen",
    "sg:classifiers":[
        {
            "category":"Freight",
            "type":"Transportation"
        }
    ],
    "sg:phone":"+32 3 677 24 09",
    "sg:postcode":"2910",
    "sg:province":"Antwerpen",
    "sg:tags":[
        "-",
        "transport"
    ],
    "wof:name":"Dribeth Bvba",
    "wof:placetype":"venue"
},
  "geometry": {"coordinates":[4.4670958519,51.4233169556],"type":"Point"}
}