{
  "type": "Feature",
  "properties": {
    "addr:full":"Schaapsdreef 48 Kortrijk West-Vlaanderen 8500",
    "addr:housenumber":"48",
    "addr:postcode":"8500",
    "addr:street":"Schaapsdreef",
    "iso:country":"BE",
    "sg:address":"Schaapsdreef 48",
    "sg:city":"Kortrijk",
    "sg:orig_category":"Dierenartsen",
    "sg:phone":"+32 56 25 93 27",
    "sg:postcode":"8500",
    "sg:province":"West-Vlaanderen",
    "wof:name":"Guy Gadeyne",
    "wof:placetype":"venue"
},
  "geometry": {"coordinates":[3.291686058,50.8012504578],"type":"Point"}
}