{
  "type": "Feature",
  "properties": {
    "addr:full":"Oostdreef 62 Dentergem (wakken) West-Vlaanderen 8720",
    "addr:housenumber":"62",
    "addr:postcode":"8720",
    "addr:street":"Oostdreef",
    "iso:country":"BE",
    "sg:address":"Oostdreef 62",
    "sg:city":"Dentergem (wakken)",
    "sg:classifiers":[
        {
            "category":"Retail",
            "subcategory":"Laundry & Dry Cleaning",
            "type":"Services"
        }
    ],
    "sg:phone":"+32 56 60 23 60",
    "sg:postcode":"8720",
    "sg:province":"West-Vlaanderen",
    "wof:name":"Edelweiss Wakken Bvba",
    "wof:placetype":"venue"
},
  "geometry": {"coordinates":[3.400963068,50.9330406189],"type":"Point"}
}