{
  "type": "Feature",
  "properties": {
    "addr:full":"Rue De Dinant 5 Eigenbrakel Brabant Wallon 1421",
    "addr:housenumber":"5;1421",
    "addr:street":"Rue De Dinant;Brabant Wallon",
    "iso:country":"BE",
    "sg:address":"Rue De Dinant 5",
    "sg:city":"Eigenbrakel",
    "sg:orig_category":"Forge, Moulage and Profilage des M\u00e9taux",
    "sg:phone":"+32 2 387 18 26",
    "sg:postcode":"1421",
    "sg:province":"Brabant Wallon",
    "wof:name":"Deridder E",
    "wof:placetype":"venue"
},
  "geometry": {"coordinates":[4.3447260857,50.6623802185],"type":"Point"}
}