{
  "type": "Feature",
  "properties": {
    "iso:country":"BE",
    "sg:address":"Steenstraat 67",
    "sg:city":"Kortemark",
    "sg:orig_category":"Eleveurs de bovins. Producteurs de l\u00e9gumes",
    "sg:phone":"+32 51 56 64 87",
    "sg:postcode":"8610",
    "sg:province":"West-Vlaanderen",
    "wof:name":"Pierre Maertens",
    "wof:placetype":"venue"
},
  "geometry": {"coordinates":[2.9722800255,51.0405769348],"type":"Point"}
}