{
  "type": "Feature",
  "properties": {
    "addr:full":"Brechtsebaan 114ba Schoten Antwerpen 2900",
    "addr:housenumber":"114ba",
    "addr:postcode":"2900",
    "addr:street":"Brechtsebaan",
    "iso:country":"BE",
    "sg:address":"Brechtsebaan 114ba",
    "sg:city":"Schoten",
    "sg:orig_category":"Bouwmaterialen Gh",
    "sg:phone":"+32 3 658 69 96",
    "sg:postcode":"2900",
    "sg:province":"Antwerpen",
    "wof:name":"Pirobouw",
    "wof:placetype":"venue"
},
  "geometry": {"coordinates":[4.5120401382,51.2662391663],"type":"Point"}
}