{
  "type": "Feature",
  "properties": {
    "addr:full":"Weidestraat 28 Roeselare West-Vlaanderen 8800",
    "addr:housenumber":"28",
    "addr:postcode":"8800",
    "addr:street":"Weidestraat",
    "iso:country":"BE",
    "sg:address":"Weidestraat 28",
    "sg:city":"Roeselare",
    "sg:classifiers":[
        {
            "category":"Professional",
            "subcategory":"Art Services",
            "type":"Services"
        }
    ],
    "sg:phone":"+32 51 24 26 71",
    "sg:postcode":"8800",
    "sg:province":"West-Vlaanderen",
    "sg:tags":[
        "photographer"
    ],
    "wof:name":"Goddeeris A",
    "wof:placetype":"venue"
},
  "geometry": {"coordinates":[3.106069088,50.9626617432],"type":"Point"}
}