{
  "type": "Feature",
  "properties": {
    "iso:country":"BE",
    "sg:address":"Avenue De L'agriculture 66",
    "sg:city":"Li\u00c8ge",
    "sg:orig_category":"Apotheken",
    "sg:phone":"+32 4 342 50 51",
    "sg:postcode":"4030",
    "sg:province":"Li\u00e8ge",
    "wof:name":"J. Danthine",
    "wof:placetype":"venue"
},
  "geometry": {"coordinates":[5.6082239151,50.6281356812],"type":"Point"}
}