{
  "type": "Feature",
  "properties": {
    "addr:full":"Hooiwege 45 Evergem Oost-Vlaanderen 9940",
    "addr:housenumber":"45",
    "addr:postcode":"9940",
    "addr:street":"Hooiwege;Oost-Vlaanderen",
    "iso:country":"BE",
    "sg:address":"Hooiwege 45",
    "sg:city":"Evergem",
    "sg:classifiers":[
        {
            "category":"Food & Beverages",
            "subcategory":"Fruits & Vegetables",
            "type":"Retail Goods"
        }
    ],
    "sg:phone":"+32 9 357 75 36",
    "sg:postcode":"9940",
    "sg:province":"Oost-Vlaanderen",
    "sg:tags":[
        "l\u00e9gumes"
    ],
    "wof:name":"Nico De Zutter",
    "wof:placetype":"venue"
},
  "geometry": {"coordinates":[3.675301075,51.1412620544],"type":"Point"}
}