{
  "type": "Feature",
  "properties": {
    "addr:full":"Wijerstraat 26 Herk-de-stad Limburg 3540",
    "addr:housenumber":"26",
    "addr:postcode":"3540",
    "addr:street":"Wijerstraat",
    "iso:country":"BE",
    "sg:address":"Wijerstraat 26",
    "sg:city":"Herk-de-stad",
    "sg:classifiers":[
        {
            "category":"Farming",
            "subcategory":"Crops",
            "type":"Manufacturing & Wholesale Goods"
        }
    ],
    "sg:phone":"+32 11 31 30 56",
    "sg:postcode":"3540",
    "sg:province":"Limburg",
    "sg:tags":[
        "vegetable",
        "fruit",
        "-",
        "grower"
    ],
    "wof:name":"Hermans S",
    "wof:placetype":"venue"
},
  "geometry": {"coordinates":[5.222823143,50.9146728516],"type":"Point"}
}