{
  "type": "Feature",
  "properties": {
    "iso:country":"BE",
    "sg:address":"Sasstraat 36",
    "sg:city":"Kapelle-op-den-bos",
    "sg:orig_category":"Herstelling horloges and juwelen Juwelen and horloges",
    "sg:phone":"+32 15 71 31 59",
    "sg:postcode":"1880",
    "sg:province":"Vlaams-Brabant",
    "wof:name":"Wilfried De Smedt",
    "wof:placetype":"venue"
},
  "geometry": {"coordinates":[4.3693180084,51.0094680786],"type":"Point"}
}