{
  "type": "Feature",
  "properties": {
    "addr:full":"Rue Du Bourrelier 61 Jurbise Hainaut 7050",
    "addr:housenumber":"61",
    "addr:postcode":"7050",
    "addr:street":"Rue Du Bourrelier",
    "iso:country":"BE",
    "sg:address":"Rue Du Bourrelier 61",
    "sg:city":"Jurbise",
    "sg:classifiers":[
        {
            "category":"Banks & Credit Unions",
            "subcategory":"Financial Services",
            "type":"Services"
        }
    ],
    "sg:phone":"+32 65 22 58 56",
    "sg:postcode":"7050",
    "sg:province":"Hainaut",
    "sg:tags":[
        "loan",
        "mortgage"
    ],
    "wof:name":"Conreurassur",
    "wof:placetype":"venue"
},
  "geometry": {"coordinates":[3.9256999493,50.5348434448],"type":"Point"}
}