{
  "type": "Feature",
  "properties": {
    "iso:country":"BE",
    "sg:address":"Toekomststraat 24",
    "sg:city":"Hasselt",
    "sg:classifiers":[
        {
            "category":"Professional",
            "subcategory":"Lawyer & Legal Services",
            "type":"Services"
        }
    ],
    "sg:phone":"+32 11 22 24 25",
    "sg:postcode":"3500",
    "sg:province":"Limburg",
    "wof:name":"Warnants Henri",
    "wof:placetype":"venue"
},
  "geometry": {"coordinates":[5.3391571045,50.9263305664],"type":"Point"}
}