{
  "type": "Feature",
  "properties": {
    "addr:full":"Europark 1078 Houthalen-helchteren (houthalen) Limburg 3530",
    "addr:housenumber":"1078",
    "addr:postcode":"3530",
    "addr:street":"Europark",
    "iso:country":"BE",
    "sg:address":"Europark 1078",
    "sg:city":"Houthalen-helchteren (houthalen)",
    "sg:classifiers":[
        {
            "category":"Home & Garden",
            "subcategory":"Building Materials",
            "type":"Retail Goods"
        }
    ],
    "sg:phone":"+32 11 52 42 53",
    "sg:postcode":"3530",
    "sg:province":"Limburg",
    "sg:tags":[
        "window"
    ],
    "wof:name":"Winco",
    "wof:placetype":"venue"
},
  "geometry": {"coordinates":[5.4051451683,51.0454139709],"type":"Point"}
}