{
  "type": "Feature",
  "properties": {
    "iso:country":"BE",
    "sg:address":"Rue Albert 3",
    "sg:city":"Gembloux",
    "sg:orig_category":"Maatschappelijke dienstverlening",
    "sg:phone":"+32 81 61 03 61",
    "sg:postcode":"5030",
    "sg:province":"Namur",
    "wof:name":"Centre P.m.s.",
    "wof:placetype":"venue"
},
  "geometry": {"coordinates":[4.6958041191,50.5598297119],"type":"Point"}
}