{
  "type": "Feature",
  "properties": {
    "iso:country":"BE",
    "sg:address":"Zwartschaapstraat 19",
    "sg:city":"Gooik",
    "sg:classifiers":[
        {
            "category":"Social Services",
            "subcategory":"Job Training",
            "type":"Services"
        }
    ],
    "sg:phone":"+32 54 34 28 56",
    "sg:postcode":"1755",
    "sg:province":"Vlaams-Brabant",
    "sg:tags":[
        "coordinator",
        "safety"
    ],
    "wof:name":"De Pelsmaeker W",
    "wof:placetype":"venue"
},
  "geometry": {"coordinates":[4.0917010307,50.7832946777],"type":"Point"}
}