{
  "type": "Feature",
  "properties": {
    "iso:country":"BE",
    "sg:address":"Hellestraat 30",
    "sg:city":"Ardooie",
    "sg:orig_category":"Eleveurs and marchands de porcs",
    "sg:phone":"+32 51 74 43 56",
    "sg:postcode":"8850",
    "sg:province":"West-Vlaanderen",
    "wof:name":"Georges Demuynck",
    "wof:placetype":"venue"
},
  "geometry": {"coordinates":[3.1793599129,50.9810028076],"type":"Point"}
}