{
  "type": "Feature",
  "properties": {
    "iso:country":"BE",
    "sg:address":"Blommekens 33",
    "sg:city":"Eeklo",
    "sg:orig_category":"Kapsalons",
    "sg:phone":"+32 9 377 61 79",
    "sg:postcode":"9900",
    "sg:province":"Oost-Vlaanderen",
    "wof:name":"Coiffure Francine",
    "wof:placetype":"venue"
},
  "geometry": {"coordinates":[3.5696709156,51.190536499],"type":"Point"}
}