{
  "type": "Feature",
  "properties": {
    "addr:full":"Dorpslaan 19 Destelbergen Oost-Vlaanderen 9070",
    "addr:housenumber":"19",
    "addr:postcode":"9070",
    "addr:street":"Dorpslaan",
    "iso:country":"BE",
    "sg:address":"Dorpslaan 19",
    "sg:city":"Destelbergen",
    "sg:orig_category":"V\u00e9t\u00e9rinaires",
    "sg:phone":"+32 9 230 47 52",
    "sg:postcode":"9070",
    "sg:province":"Oost-Vlaanderen",
    "wof:name":"Martin Schepens",
    "wof:placetype":"venue"
},
  "geometry": {"coordinates":[3.7968919277,51.0559501648],"type":"Point"}
}