{
  "type": "Feature",
  "properties": {
    "addr:full":"Oudenaardsesteenweg 81 Kortrijk West-Vlaanderen 8500",
    "addr:housenumber":"81",
    "addr:postcode":"8500",
    "addr:street":"Oudenaardsesteenweg",
    "iso:country":"BE",
    "sg:address":"Oudenaardsesteenweg 81",
    "sg:city":"Kortrijk",
    "sg:orig_category":"Epiceries",
    "sg:phone":"+32 56 22 78 40",
    "sg:postcode":"8500",
    "sg:province":"West-Vlaanderen",
    "wof:name":"Rita Depraetere",
    "wof:placetype":"venue"
},
  "geometry": {"coordinates":[3.2807030678,50.8213882446],"type":"Point"}
}