{
  "type": "Feature",
  "properties": {
    "addr:full":"Hermans-lybaertstraat 42 Knokke-heist (heist-aan-zee) West-Vlaanderen 8301",
    "addr:housenumber":"42",
    "addr:postcode":"8301",
    "addr:street":"Hermans-Lybaertstraat",
    "iso:country":"BE",
    "sg:address":"Hermans-lybaertstraat 42",
    "sg:city":"Knokke-heist (heist-aan-zee)",
    "sg:classifiers":[
        {
            "category":"Bars & Pubs",
            "type":"Food & Drink"
        }
    ],
    "sg:phone":"+32 50 51 59 36",
    "sg:postcode":"8301",
    "sg:province":"West-Vlaanderen",
    "wof:name":"Golfbreker (de)",
    "wof:placetype":"venue"
},
  "geometry": {"coordinates":[3.2639000416,51.3396911621],"type":"Point"}
}