{
  "type": "Feature",
  "properties": {
    "addr:full":"Av. Chevaliers De Malte 3 Waterloo Brabant Wallon 1410",
    "addr:housenumber":"3",
    "addr:postcode":"1410",
    "addr:street":"Av. Chevaliers De Malte",
    "iso:country":"BE",
    "sg:address":"Av. Chevaliers De Malte 3",
    "sg:city":"Waterloo",
    "sg:orig_category":"Artistes ind\u00e9pendants",
    "sg:phone":"+32 2 384 15 08",
    "sg:postcode":"1410",
    "sg:province":"Brabant Wallon",
    "wof:name":"Ren\u00c9e Fonck",
    "wof:placetype":"venue"
},
  "geometry": {"coordinates":[4.4010391235,50.6964187622],"type":"Point"}
}