{
  "type": "Feature",
  "properties": {
    "addr:full":"Rue De Hollogne 215 Seraing (jemeppe-sur-meuse) Li\u00e8ge 4101",
    "addr:housenumber":"215",
    "addr:postcode":"4101",
    "addr:street":"Rue De Hollogne;Jemeppe-Sur-Meuse",
    "iso:country":"BE",
    "sg:address":"Rue De Hollogne 215",
    "sg:city":"Seraing (jemeppe-sur-meuse)",
    "sg:classifiers":[
        {
            "category":"Food & Beverages",
            "subcategory":"Meat & Fish",
            "type":"Retail Goods"
        }
    ],
    "sg:phone":"+32 4 225 97 40",
    "sg:postcode":"4101",
    "sg:province":"Li\u00e8ge",
    "sg:tags":[
        "poultry",
        "whol",
        "game",
        "-"
    ],
    "wof:name":"Volailles Hubert Leboutte Sprl",
    "wof:placetype":"venue"
},
  "geometry": {"coordinates":[5.4892392159,50.6248245239],"type":"Point"}
}