{
  "type": "Feature",
  "properties": {
    "addr:full":"Duinkerkestraat 31 Poperinge West-Vlaanderen 8970",
    "addr:housenumber":"31",
    "addr:postcode":"8970",
    "addr:street":"Duinkerkestraat",
    "iso:country":"BE",
    "sg:address":"Duinkerkestraat 31",
    "sg:city":"Poperinge",
    "sg:classifiers":[
        {
            "category":"Insurance",
            "subcategory":"Life Insurance",
            "type":"Services"
        }
    ],
    "sg:phone":"+32 57 33 46 06",
    "sg:postcode":"8970",
    "sg:province":"West-Vlaanderen",
    "sg:tags":[
        "assurance"
    ],
    "wof:name":"Hans Vanhoutte",
    "wof:placetype":"venue"
},
  "geometry": {"coordinates":[2.7207810879,50.8550338745],"type":"Point"}
}