{
  "type": "Feature",
  "properties": {
    "addr:full":"Prins Boudewijnlaan 18 Antwerpen (berchem) Antwerpen 2600",
    "addr:housenumber":"18",
    "addr:postcode":"2600",
    "addr:street":"Prins Boudewijnlaan;Antwerpen",
    "iso:country":"BE",
    "sg:address":"Prins Boudewijnlaan 18",
    "sg:city":"Antwerpen (berchem)",
    "sg:classifiers":[
        {
            "category":"Health Services",
            "subcategory":"Dentist",
            "type":"Services"
        }
    ],
    "sg:phone":"+32 3 239 02 92",
    "sg:postcode":"2600",
    "sg:province":"Antwerpen",
    "wof:name":"Speelman D",
    "wof:placetype":"venue"
},
  "geometry": {"coordinates":[4.4233798981,51.1806526184],"type":"Point"}
}