{
  "type": "Feature",
  "properties": {
    "iso:country":"BE",
    "sg:address":"Toekomststraat 13",
    "sg:city":"Mechelen",
    "sg:orig_category":"Artiesten and kunstenaars",
    "sg:phone":"+32 15 41 69 45",
    "sg:postcode":"2812",
    "sg:province":"Antwerpen",
    "wof:name":"De Greve",
    "wof:placetype":"venue"
},
  "geometry": {"coordinates":[4.5038371086,51.0118942261],"type":"Point"}
}