{
  "type": "Feature",
  "properties": {
    "iso:country":"BE",
    "sg:address":"Het Einde 5",
    "sg:city":"Arendonk",
    "sg:classifiers":[
        {
            "category":"Home & Garden",
            "subcategory":"Kitchen Supply",
            "type":"Retail Goods"
        }
    ],
    "sg:phone":"+32 14 67 87 24",
    "sg:postcode":"2370",
    "sg:province":"Antwerpen",
    "sg:tags":[
        "installation"
    ],
    "wof:name":"Huybrechts P",
    "wof:placetype":"venue"
},
  "geometry": {"coordinates":[5.0631890297,51.3145103455],"type":"Point"}
}