{
  "type": "Feature",
  "properties": {
    "iso:country":"BE",
    "sg:address":"Heekskestraat 1",
    "sg:city":"Peer",
    "sg:orig_category":"Production and transformation de viande",
    "sg:phone":"+32 11 79 34 30",
    "sg:postcode":"3990",
    "sg:province":"Limburg",
    "wof:name":"Gielen",
    "wof:placetype":"venue"
},
  "geometry": {"coordinates":[5.4336872101,51.0954284668],"type":"Point"}
}