{
  "type": "Feature",
  "properties": {
    "addr:full":"Elzenstraat 6 Dilbeek Vlaams-Brabant 1702",
    "addr:housenumber":"6",
    "addr:postcode":"1702",
    "addr:street":"Elzenstraat",
    "iso:country":"BE",
    "sg:address":"Elzenstraat 6",
    "sg:city":"Dilbeek",
    "sg:orig_category":"Elektrische installaties voor woningen Industri\u00eble elektrische installaties",
    "sg:phone":"+32 2 466 99 46",
    "sg:postcode":"1702",
    "sg:province":"Vlaams-Brabant",
    "wof:name":"L.d.w. Security",
    "wof:placetype":"venue"
},
  "geometry": {"coordinates":[4.2612719536,50.8667221069],"type":"Point"}
}