{
  "type": "Feature",
  "properties": {
    "addr:full":"Werkhuizenstraat 24 Vilvoorde Vlaams-Brabant 1800",
    "addr:housenumber":"24",
    "addr:postcode":"1800",
    "addr:street":"Werkhuizenstraat",
    "iso:country":"BE",
    "sg:address":"Werkhuizenstraat 24",
    "sg:city":"Vilvoorde",
    "sg:classifiers":[
        {
            "category":"Taxi",
            "type":"Transportation"
        }
    ],
    "sg:phone":"+32 2 253 02 18",
    "sg:postcode":"1800",
    "sg:province":"Vlaams-Brabant",
    "sg:tags":[
        "taxicab"
    ],
    "wof:name":"Van Gucht J",
    "wof:placetype":"venue"
},
  "geometry": {"coordinates":[4.421628952,50.9339637756],"type":"Point"}
}