{
  "type": "Feature",
  "properties": {
    "addr:full":"Leuvensebaan 5 Rotselaar Vlaams-Brabant 3110",
    "addr:housenumber":"5",
    "addr:postcode":"3110",
    "addr:street":"Leuvensebaan",
    "iso:country":"BE",
    "sg:address":"Leuvensebaan 5",
    "sg:city":"Rotselaar",
    "sg:orig_category":"Traitements param\u00e9dicaux",
    "sg:phone":"+32 16 44 06 20",
    "sg:postcode":"3110",
    "sg:province":"Vlaams-Brabant",
    "wof:name":"Vancraesbeek",
    "wof:placetype":"venue"
},
  "geometry": {"coordinates":[4.7123999596,50.9503593445],"type":"Point"}
}