{
  "type": "Feature",
  "properties": {
    "iso:country":"BE",
    "sg:address":"D'hoef 4",
    "sg:city":"Brecht",
    "sg:orig_category":"Organisation de salons, expositions and bourses",
    "sg:phone":"+32 3 313 52 09",
    "sg:postcode":"2960",
    "sg:province":"Antwerpen",
    "wof:name":"Alline Systems",
    "wof:placetype":"venue"
},
  "geometry": {"coordinates":[4.6755781174,51.3407440186],"type":"Point"}
}