{
  "type": "Feature",
  "properties": {
    "addr:full":"Merksplassesteenweg 104 Rijkevorsel Antwerpen 2310",
    "addr:housenumber":"104",
    "addr:postcode":"2310",
    "addr:street":"Merksplassesteenweg",
    "iso:country":"BE",
    "sg:address":"Merksplassesteenweg 104",
    "sg:city":"Rijkevorsel",
    "sg:classifiers":[
        {
            "category":"Home & Garden",
            "subcategory":"Home Furnishings",
            "type":"Retail Goods"
        }
    ],
    "sg:phone":"+32 3 340 04 66",
    "sg:postcode":"2310",
    "sg:province":"Antwerpen",
    "sg:tags":[
        "-",
        "furniture"
    ],
    "wof:name":"Take & Pay",
    "wof:placetype":"venue"
},
  "geometry": {"coordinates":[4.7773098946,51.3453598022],"type":"Point"}
}