{
  "type": "Feature",
  "properties": {
    "iso:country":"BE",
    "sg:address":"Rue Grande 125",
    "sg:city":"Beloeil",
    "sg:orig_category":"Eclairage et \u00e9quipements du foyer",
    "sg:phone":"+32 69 57 81 91",
    "sg:postcode":"7971",
    "sg:province":"Hainaut",
    "wof:name":"Maison Les Oliviades",
    "wof:placetype":"venue"
},
  "geometry": {"coordinates":[3.6538441181,50.5237350464],"type":"Point"}
}