{
  "type": "Feature",
  "properties": {
    "iso:country":"BE",
    "sg:address":"Vlamingenlaan 1",
    "sg:city":"Heusden-zolder (zolder)",
    "sg:classifiers":[
        {
            "category":"Retail",
            "subcategory":"Animal Services",
            "type":"Services"
        }
    ],
    "sg:phone":"+32 11 53 73 83",
    "sg:postcode":"3550",
    "sg:province":"Limburg",
    "sg:tags":[
        "grooming",
        "-",
        "dog"
    ],
    "wof:name":"Trimsalon Shimmy's",
    "wof:placetype":"venue"
},
  "geometry": {"coordinates":[5.2889881134,51.0101470947],"type":"Point"}
}