{
  "type": "Feature",
  "properties": {
    "addr:full":"Boomse Steenweg 320 Antwerpen Antwerpen 2020",
    "addr:housenumber":"320",
    "addr:postcode":"2020",
    "addr:street":"Steenweg",
    "iso:country":"BE",
    "sg:address":"Boomse Steenweg 320",
    "sg:city":"Antwerpen",
    "sg:classifiers":[
        {
            "category":"Bars & Pubs",
            "type":"Food & Drink"
        }
    ],
    "sg:phone":"+32 3 233 11 96",
    "sg:postcode":"2020",
    "sg:province":"Antwerpen",
    "wof:name":"Lafayette",
    "wof:placetype":"venue"
},
  "geometry": {"coordinates":[4.3872690201,51.1882972717],"type":"Point"}
}