{
  "type": "Feature",
  "properties": {
    "addr:full":"Ch De Battice 5 Dalhem Li\u00e8ge 4607",
    "addr:housenumber":"5",
    "addr:postcode":"4607",
    "addr:street":"Ch De Battice",
    "iso:country":"BE",
    "sg:address":"Ch De Battice 5",
    "sg:city":"Dalhem",
    "sg:orig_category":"Kapsalons",
    "sg:phone":"+32 4 379 38 66",
    "sg:postcode":"4607",
    "sg:province":"Li\u00e8ge",
    "wof:name":"Coiffure Chantal",
    "wof:placetype":"venue"
},
  "geometry": {"coordinates":[5.7234959602,50.713634491],"type":"Point"}
}