{
  "type": "Feature",
  "properties": {
    "addr:full":"Notelarenweg 17 Herent Vlaams-Brabant 3020",
    "addr:housenumber":"17",
    "addr:postcode":"3020",
    "addr:street":"Notelarenweg",
    "iso:country":"BE",
    "sg:address":"Notelarenweg 17",
    "sg:city":"Herent",
    "sg:classifiers":[
        {
            "category":"Professional",
            "subcategory":"Art Services",
            "type":"Services"
        }
    ],
    "sg:phone":"+32 16 23 44 27",
    "sg:postcode":"3020",
    "sg:province":"Vlaams-Brabant",
    "sg:tags":[
        "interior",
        "designer"
    ],
    "wof:name":"Busseniers H",
    "wof:placetype":"venue"
},
  "geometry": {"coordinates":[4.6754741669,50.9092254639],"type":"Point"}
}