{
  "type": "Feature",
  "properties": {
    "iso:country":"BE",
    "sg:address":"Chaussee De Gand 696",
    "sg:city":"Bruxelles",
    "sg:classifiers":[
        {
            "category":"Professional",
            "subcategory":"Printing & Photocopies",
            "type":"Services"
        }
    ],
    "sg:phone":"+32 2 465 77 17",
    "sg:postcode":"1080",
    "sg:province":"Bruxelles-Capitale",
    "sg:tags":[
        "offset"
    ],
    "wof:name":"Litho Offset De Jonghe S.a.",
    "wof:placetype":"venue"
},
  "geometry": {"coordinates":[4.3075652122,50.8598556519],"type":"Point"}
}