{
  "type": "Feature",
  "properties": {
    "addr:full":"Rue Gaston Barla 6 Theux Li\u00e8ge 4910",
    "addr:housenumber":"6",
    "addr:postcode":"4910",
    "addr:street":"Rue Gaston Barla",
    "iso:country":"BE",
    "sg:address":"Rue Gaston Barla 6",
    "sg:city":"Theux",
    "sg:classifiers":[
        {
            "category":"Manufacturing",
            "subcategory":"Textiles",
            "type":"Manufacturing & Wholesale Goods"
        }
    ],
    "sg:phone":"+32 56 71 61 36",
    "sg:postcode":"4910",
    "sg:province":"Li\u00e8ge",
    "sg:tags":[
        "used",
        "machines"
    ],
    "wof:name":"Maebe Luc Nv",
    "wof:placetype":"venue"
},
  "geometry": {"coordinates":[3.3383469582,50.8790283203],"type":"Point"}
}