{
  "type": "Feature",
  "properties": {
    "addr:full":"Frans Beirenslaan 61 Borsbeek Antwerpen 2150",
    "addr:housenumber":"61",
    "addr:postcode":"2150",
    "addr:street":"Frans Beirenslaan",
    "iso:country":"BE",
    "sg:address":"Frans Beirenslaan 61",
    "sg:city":"Borsbeek",
    "sg:classifiers":[
        {
            "category":"Cafe",
            "type":"Food & Drink"
        }
    ],
    "sg:phone":"+32 3 321 04 14",
    "sg:postcode":"2150",
    "sg:province":"Antwerpen",
    "sg:tags":[
        "caf\u00e9s"
    ],
    "wof:name":"Caf\u00c9 The Corner",
    "wof:placetype":"venue"
},
  "geometry": {"coordinates":[4.4791231155,51.1948471069],"type":"Point"}
}