{
  "type": "Feature",
  "properties": {
    "iso:country":"BE",
    "sg:address":"Kirchstrasse 15",
    "sg:city":"Eupen",
    "sg:classifiers":[
        {
            "category":"Cinema",
            "subcategory":"Movie Theater",
            "type":"Entertainment"
        }
    ],
    "sg:phone":"+32 87 74 00 28",
    "sg:postcode":"4700",
    "sg:province":"Li\u00e8ge",
    "wof:name":"Comit\u00e9 Culturel De La Ville D'eupen Asbl",
    "wof:placetype":"venue"
},
  "geometry": {"coordinates":[6.0322871208,50.6302909851],"type":"Point"}
}