{
  "type": "Feature",
  "properties": {
    "addr:full":"Rue De La Fr\u00cate 21 Orp-jauche Brabant Wallon 1350",
    "addr:housenumber":"21",
    "addr:postcode":"1350",
    "addr:street":"Rue De La Fre\u0302Te",
    "iso:country":"BE",
    "sg:address":"Rue De La Fr\u00cate 21",
    "sg:city":"Orp-jauche",
    "sg:orig_category":"Installation de menuiserie en bois and plastique",
    "sg:phone":"+32 81 87 83 44",
    "sg:postcode":"1350",
    "sg:province":"Brabant Wallon",
    "wof:name":"Jacques Depoortere",
    "wof:placetype":"venue"
},
  "geometry": {"coordinates":[4.97920084,50.6738891602],"type":"Point"}
}