{
  "type": "Feature",
  "properties": {
    "addr:full":"Gospertstrasse 93 Eupen Li\u00e8ge 4700",
    "addr:housenumber":"93",
    "addr:postcode":"4700",
    "addr:street":"Gospertstrasse",
    "iso:country":"BE",
    "sg:address":"Gospertstrasse 93",
    "sg:city":"Eupen",
    "sg:classifiers":[
        {
            "category":"Bakery",
            "type":"Food & Drink"
        }
    ],
    "sg:phone":"+32 87 74 24 31",
    "sg:postcode":"4700",
    "sg:province":"Li\u00e8ge",
    "sg:tags":[
        "confectioner",
        "baker"
    ],
    "wof:name":"Mattar Konditorei",
    "wof:placetype":"venue"
},
  "geometry": {"coordinates":[6.0370059013,50.6324768066],"type":"Point"}
}