{
  "type": "Feature",
  "properties": {
    "addr:full":"Rue Du Fayais 4 Weismes Li\u00e8ge 4950",
    "addr:housenumber":"4",
    "addr:postcode":"4950",
    "addr:street":"Rue Du Fayais",
    "iso:country":"BE",
    "sg:address":"Rue Du Fayais 4",
    "sg:city":"Weismes",
    "sg:classifiers":[
        {
            "category":"Building & Trades",
            "subcategory":"Electrical",
            "type":"Services"
        }
    ],
    "sg:phone":"+32 80 67 01 70",
    "sg:postcode":"4950",
    "sg:province":"Li\u00e8ge",
    "sg:tags":[
        "industrial",
        "-",
        "electric",
        "contractor"
    ],
    "wof:name":"Mr Lemaire A",
    "wof:placetype":"venue"
},
  "geometry": {"coordinates":[6.1104631424,50.4205741882],"type":"Point"}
}