{
  "type": "Feature",
  "properties": {
    "addr:full":"Nijverheidszone 'begijnenmeers' 75a Liedekerke Vlaams-Brabant 1770",
    "addr:housenumber":"75a",
    "addr:postcode":"1770",
    "addr:street":"Vlaams-Brabant",
    "iso:country":"BE",
    "sg:address":"Nijverheidszone 'begijnenmeers' 75a",
    "sg:city":"Liedekerke",
    "sg:orig_category":"Non-Classified Establishments",
    "sg:phone":"+32 53 64 87 97",
    "sg:postcode":"1770",
    "sg:province":"Vlaams-Brabant",
    "wof:name":"I.s.p.d. Singer Nv-sa",
    "wof:placetype":"venue"
},
  "geometry": {"coordinates":[4.0872688293,50.8854942322],"type":"Point"}
}