{
  "type": "Feature",
  "properties": {
    "iso:country":"BE",
    "sg:address":"Rue De Li\u00c8ge 12",
    "sg:city":"Somme-leuze",
    "sg:orig_category":"Herstellingen and onderhoud van auto's Voertuigen",
    "sg:phone":"+32 86 32 20 71",
    "sg:postcode":"5377",
    "sg:province":"Namur",
    "wof:name":"Garage Jamagne",
    "wof:placetype":"venue"
},
  "geometry": {"coordinates":[5.3727869987,50.34375],"type":"Point"}
}