{
  "type": "Feature",
  "properties": {
    "addr:full":"Pottelberg 181 Kortrijk (marke) West-Vlaanderen 8510",
    "addr:housenumber":"181",
    "addr:postcode":"8510",
    "addr:street":"Pottelberg",
    "iso:country":"BE",
    "sg:address":"Pottelberg 181",
    "sg:city":"Kortrijk (marke)",
    "sg:classifiers":[
        {
            "category":"Airline",
            "type":"Transportation"
        }
    ],
    "sg:phone":"+32 56 43 10 64",
    "sg:postcode":"8510",
    "sg:province":"West-Vlaanderen",
    "wof:name":"Kronos",
    "wof:placetype":"venue"
},
  "geometry": {"coordinates":[3.244658947,50.8041229248],"type":"Point"}
}