{
  "type": "Feature",
  "properties": {
    "addr:full":"Dworpsestraat 188 Beersel Vlaams-Brabant 1651",
    "addr:housenumber":"188",
    "addr:postcode":"1651",
    "addr:street":"Dworpsestraat",
    "iso:country":"BE",
    "sg:address":"Dworpsestraat 188",
    "sg:city":"Beersel",
    "sg:classifiers":[
        {
            "category":"Personal",
            "subcategory":"Beauty Salon",
            "type":"Services"
        }
    ],
    "sg:phone":"+32 2 377 83 60",
    "sg:postcode":"1651",
    "sg:province":"Vlaams-Brabant",
    "sg:tags":[
        "de",
        "coiffure"
    ],
    "wof:name":"Josiane Bellemans",
    "wof:placetype":"venue"
},
  "geometry": {"coordinates":[4.2724809647,50.761013031],"type":"Point"}
}