{
  "type": "Feature",
  "properties": {
    "iso:country":"BE",
    "sg:address":"Brusselsesteenweg 449",
    "sg:city":"Melle",
    "sg:orig_category":"Installatie van houten of kunststof schrijnwerk",
    "sg:phone":"+32 9 252 41 33",
    "sg:postcode":"9090",
    "sg:province":"Oost-Vlaanderen",
    "wof:name":"Andre De Vloed",
    "wof:placetype":"venue"
},
  "geometry": {"coordinates":[3.8088018894,50.9992904663],"type":"Point"}
}