{
  "type": "Feature",
  "properties": {
    "iso:country":"BE",
    "sg:address":"Rue Paul Lauters 1",
    "sg:city":"Bruxelles",
    "sg:orig_category":"Newspapers, magazines, periodicals - Publishers",
    "sg:phone":"+32 2 646 43 02",
    "sg:postcode":"1000",
    "sg:province":"Bruxelles-Capitale",
    "wof:name":"Editions Geo-money (les) Sa",
    "wof:placetype":"venue"
},
  "geometry": {"coordinates":[4.3711309433,50.8175544739],"type":"Point"}
}