{
  "type": "Feature",
  "properties": {
    "iso:country":"BE",
    "sg:address":"Maastrichterstraat 68",
    "sg:city":"Tongeren",
    "sg:classifiers":[
        {
            "category":"Food & Beverages",
            "subcategory":"Meat & Fish",
            "type":"Retail Goods"
        }
    ],
    "sg:phone":"+32 12 23 13 79",
    "sg:postcode":"3700",
    "sg:province":"Limburg",
    "sg:tags":[
        "poultry",
        "whol",
        "game",
        "-"
    ],
    "wof:name":"Lysens",
    "wof:placetype":"venue"
},
  "geometry": {"coordinates":[5.4666018486,50.7824172974],"type":"Point"}
}