{
  "type": "Feature",
  "properties": {
    "iso:country":"BE",
    "sg:address":"Bosstraat 1",
    "sg:city":"Merelbeke",
    "sg:classifiers":[
        {
            "category":"Restaurant",
            "type":"Food & Drink"
        }
    ],
    "sg:phone":"+32 9 362 73 00",
    "sg:postcode":"9820",
    "sg:province":"Oost-Vlaanderen",
    "sg:tags":[
        "caf\u00e9s"
    ],
    "wof:name":"Taverne De Zoete Zonde",
    "wof:placetype":"venue"
},
  "geometry": {"coordinates":[3.7324819565,50.9492721558],"type":"Point"}
}