{
  "type": "Feature",
  "properties": {
    "addr:full":"Rue De L'eglise Saint-gilles 73 Bruxelles (saint-gilles) Bruxelles-Capitale 1060",
    "addr:housenumber":"73",
    "addr:postcode":"1060",
    "addr:street":"Rue De L'Eglise Saint-Gilles",
    "iso:country":"BE",
    "sg:address":"Rue De L'eglise Saint-gilles 73",
    "sg:city":"Bruxelles (saint-gilles)",
    "sg:classifiers":[
        {
            "category":"Professional",
            "subcategory":"Testing Lab",
            "type":"Services"
        }
    ],
    "sg:phone":"+32 2 537 31 80",
    "sg:postcode":"1060",
    "sg:province":"Bruxelles-Capitale",
    "sg:tags":[
        "laboratory",
        "-"
    ],
    "wof:name":"Bruvitro",
    "wof:placetype":"venue"
},
  "geometry": {"coordinates":[4.3433680534,50.8302307129],"type":"Point"}
}