{
  "type": "Feature",
  "properties": {
    "addr:full":"Rue Du Menuisier Bruxelles Bruxelles-Capitale 1000",
    "addr:postcode":"1000",
    "addr:street":"Rue Du Menuisier",
    "iso:country":"BE",
    "sg:address":"Rue Du Menuisier",
    "sg:city":"Bruxelles",
    "sg:orig_category":"Telecommunicatieapparaten",
    "sg:phone":"+32 2 771 44 49",
    "sg:postcode":"1000",
    "sg:province":"Bruxelles-Capitale",
    "wof:name":"Aidel(georges Henri)",
    "wof:placetype":"venue"
},
  "geometry": {"coordinates":[4.4153399467,50.8442192078],"type":"Point"}
}