{
  "type": "Feature",
  "properties": {
    "iso:country":"BE",
    "sg:address":"Frankenweg 29",
    "sg:city":"Lier",
    "sg:orig_category":"Woningbouw",
    "sg:phone":"+32 3 488 02 27",
    "sg:postcode":"2500",
    "sg:province":"Antwerpen",
    "wof:name":"Arras F.",
    "wof:placetype":"venue"
},
  "geometry": {"coordinates":[4.5737719536,51.1483840942],"type":"Point"}
}