{
  "type": "Feature",
  "properties": {
    "addr:full":"Chemin Des Espagnols 244 Arlon Luxembourg 6700",
    "addr:housenumber":"244",
    "addr:postcode":"6700",
    "addr:street":"Chemin Des Espagnols",
    "iso:country":"BE",
    "sg:address":"Chemin Des Espagnols 244",
    "sg:city":"Arlon",
    "sg:orig_category":"Sportclubs",
    "sg:phone":"+32 63 23 35 20",
    "sg:postcode":"6700",
    "sg:province":"Luxembourg",
    "wof:name":"B.c. Asperule Arlon",
    "wof:placetype":"venue"
},
  "geometry": {"coordinates":[5.8263711929,49.6819610596],"type":"Point"}
}