{
  "type": "Feature",
  "properties": {
    "addr:full":"Oudleikestraat 12 Ruiselede West-Vlaanderen 8755",
    "addr:housenumber":"12",
    "addr:postcode":"8755",
    "addr:street":"Oudleikestraat",
    "iso:country":"BE",
    "sg:address":"Oudleikestraat 12",
    "sg:city":"Ruiselede",
    "sg:orig_category":"Rundveehouders Varkenskwekers",
    "sg:phone":"+32 51 68 71 30",
    "sg:postcode":"8755",
    "sg:province":"West-Vlaanderen",
    "wof:name":"Bernard Van De Walle",
    "wof:placetype":"venue"
},
  "geometry": {"coordinates":[3.4165380001,51.0594558716],"type":"Point"}
}