{
  "type": "Feature",
  "properties": {
    "addr:full":"Reimond Stijnsstraat 85 Sint-jans-molenbeek/molenbeek-saint-jean Bruxelles-Capitale 1080",
    "addr:housenumber":"85",
    "addr:postcode":"1080",
    "addr:street":"Reimond Stijnsstraat",
    "iso:country":"BE",
    "sg:address":"Reimond Stijnsstraat 85",
    "sg:city":"Sint-jans-molenbeek/molenbeek-saint-jean",
    "sg:orig_category":"Boekbinderijen and afwerking Mailing- and besteldiensten",
    "sg:phone":"+32 2 414 56 58",
    "sg:postcode":"1080",
    "sg:province":"Bruxelles-Capitale",
    "wof:name":"D.m.s.",
    "wof:placetype":"venue"
},
  "geometry": {"coordinates":[4.3152990341,50.8564796448],"type":"Point"}
}