{
  "type": "Feature",
  "properties": {
    "addr:full":"Antwerpsesteenweg 99 Mechelen Antwerpen 2800",
    "addr:housenumber":"99",
    "addr:postcode":"2800",
    "addr:street":"Antwerpsesteenweg",
    "iso:country":"BE",
    "sg:address":"Antwerpsesteenweg 99",
    "sg:city":"Mechelen",
    "sg:orig_category":"Advocaten and juridische adviseurs",
    "sg:phone":"+32 15 20 48 46",
    "sg:postcode":"2800",
    "sg:province":"Antwerpen",
    "wof:name":"Cl. De Bie",
    "wof:placetype":"venue"
},
  "geometry": {"coordinates":[4.4709558487,51.0415267944],"type":"Point"}
}