{
  "type": "Feature",
  "properties": {
    "iso:country":"BE",
    "sg:address":"Matersplein 15",
    "sg:city":"Oudenaarde",
    "sg:orig_category":"Enseignement maternel and primaire",
    "sg:phone":"+32 55 45 56 26",
    "sg:postcode":"9700",
    "sg:province":"Oost-Vlaanderen",
    "wof:name":"Vrije Basisschool",
    "wof:placetype":"venue"
},
  "geometry": {"coordinates":[3.6629800797,50.8427467346],"type":"Point"}
}