{
  "type": "Feature",
  "properties": {
    "addr:full":"Michiel Jansplein 28b Lommel Limburg 3920",
    "addr:housenumber":"28b",
    "addr:postcode":"3920",
    "addr:street":"Michiel Jansplein",
    "iso:country":"BE",
    "sg:address":"Michiel Jansplein 28b",
    "sg:city":"Lommel",
    "sg:classifiers":[
        {
            "category":"Autos & Motor Vehicles",
            "subcategory":"Boat Sales",
            "type":"Retail Goods"
        }
    ],
    "sg:phone":"+32 11 55 31 55",
    "sg:postcode":"3920",
    "sg:province":"Limburg",
    "sg:tags":[
        "balloon"
    ],
    "wof:name":"United Telecom",
    "wof:placetype":"venue"
},
  "geometry": {"coordinates":[5.3150777817,51.2290153503],"type":"Point"}
}