{
  "type": "Feature",
  "properties": {
    "addr:full":"Grand\u00b4place 26 Chimay Hainaut 6460",
    "addr:housenumber":"26",
    "addr:postcode":"6460",
    "addr:street":"Grand\u00b4Place",
    "iso:country":"BE",
    "sg:address":"Grand\u00b4place 26",
    "sg:city":"Chimay",
    "sg:orig_category":"Maroquinerie and articles de voyage. Chaussures",
    "sg:phone":"+32 60 21 10 34",
    "sg:postcode":"6460",
    "sg:province":"Hainaut",
    "wof:name":"Chaussures Boulet",
    "wof:placetype":"venue"
},
  "geometry": {"coordinates":[4.3148198128,50.0489082336],"type":"Point"}
}