{
  "type": "Feature",
  "properties": {
    "addr:full":"Bukenstraat 5 Haacht (tildonk) Vlaams-Brabant 3150",
    "addr:housenumber":"5",
    "addr:postcode":"3150",
    "addr:street":"Bukenstraat",
    "iso:country":"BE",
    "sg:address":"Bukenstraat 5",
    "sg:city":"Haacht (tildonk)",
    "sg:classifiers":[
        {
            "category":"Building & Trades",
            "subcategory":"Plumbing",
            "type":"Services"
        }
    ],
    "sg:phone":"+32 16 60 12 35",
    "sg:postcode":"3150",
    "sg:province":"Vlaams-Brabant",
    "sg:tags":[
        "pipe",
        "drain",
        "unblocking"
    ],
    "wof:name":"Van Brusselen J",
    "wof:placetype":"venue"
},
  "geometry": {"coordinates":[4.6418628693,50.9435272217],"type":"Point"}
}