{
  "type": "Feature",
  "properties": {
    "addr:full":"Rue Justin Sauvenier 38 Bl\u00c9gny Li\u00e8ge 4671",
    "addr:housenumber":"38",
    "addr:postcode":"4671",
    "addr:street":"Rue Justin Sauvenier",
    "iso:country":"BE",
    "sg:address":"Rue Justin Sauvenier 38",
    "sg:city":"Bl\u00c9gny",
    "sg:orig_category":"V\u00e9t\u00e9rinaires",
    "sg:phone":"+32 4 387 72 00",
    "sg:postcode":"4671",
    "sg:province":"Li\u00e8ge",
    "wof:name":"S. Lievens",
    "wof:placetype":"venue"
},
  "geometry": {"coordinates":[5.7016220093,50.668636322],"type":"Point"}
}