{
  "type": "Feature",
  "properties": {
    "addr:full":"Mulslaan 5 Steenokkerzeel Vlaams-Brabant 1820",
    "addr:housenumber":"5",
    "addr:postcode":"1820",
    "addr:street":"Mulslaan",
    "iso:country":"BE",
    "sg:address":"Mulslaan 5",
    "sg:city":"Steenokkerzeel",
    "sg:orig_category":"Boucheries",
    "sg:phone":"+32 2 759 64 33",
    "sg:postcode":"1820",
    "sg:province":"Vlaams-Brabant",
    "wof:name":"Martin Pinceel",
    "wof:placetype":"venue"
},
  "geometry": {"coordinates":[4.5129380226,50.9086914062],"type":"Point"}
}