{
  "type": "Feature",
  "properties": {
    "addr:full":"Beekstraat 22 Haaltert (kerksken) Oost-Vlaanderen 9451",
    "addr:housenumber":"22",
    "addr:postcode":"9451",
    "addr:street":"Beekstraat",
    "iso:country":"BE",
    "sg:address":"Beekstraat 22",
    "sg:city":"Haaltert (kerksken)",
    "sg:classifiers":[
        {
            "category":"Health Services",
            "subcategory":"Health Practitioner",
            "type":"Services"
        }
    ],
    "sg:phone":"+32 53 83 41 22",
    "sg:postcode":"9451",
    "sg:province":"Oost-Vlaanderen",
    "sg:tags":[
        "physiotherapist"
    ],
    "wof:name":"Van Driessche G",
    "wof:placetype":"venue"
},
  "geometry": {"coordinates":[3.9924418926,50.8867988586],"type":"Point"}
}