{
  "type": "Feature",
  "properties": {
    "iso:country":"BE",
    "sg:address":"Rue Bouhouille 17",
    "sg:city":"Blegny",
    "sg:orig_category":"HERSTELLING ELEKTRISCHE HUISHOUDAPPARATEN Huishoudapparaten, televisies and radio's",
    "sg:phone":"+32 4 387 61 01",
    "sg:postcode":"4671",
    "sg:province":"Li\u00e8ge",
    "wof:name":"Ets.andr\u00c9 L\u00c9on",
    "wof:placetype":"venue"
},
  "geometry": {"coordinates":[5.7081742287,50.6838150024],"type":"Point"}
}