{
  "type": "Feature",
  "properties": {
    "addr:full":"Sint-truidersteenweg 217 Hasselt Limburg 3500",
    "addr:housenumber":"217",
    "addr:postcode":"3500",
    "addr:street":"Sint-Truidersteenweg",
    "iso:country":"BE",
    "sg:address":"Sint-truidersteenweg 217",
    "sg:city":"Hasselt",
    "sg:orig_category":"Baby- and kinderkleding Dameskledingzaken Herenkledingzaken",
    "sg:phone":"+32 11 27 15 91",
    "sg:postcode":"3500",
    "sg:province":"Limburg",
    "wof:name":"Croes Kleding",
    "wof:placetype":"venue"
},
  "geometry": {"coordinates":[5.3293280602,50.9203567505],"type":"Point"}
}