{
  "type": "Feature",
  "properties": {
    "addr:full":"Korte Mooiaardstraat 2 Heuvelland West-Vlaanderen 8950",
    "addr:housenumber":"2",
    "addr:postcode":"8950",
    "addr:street":"Korte Mooiaardstraat",
    "iso:country":"BE",
    "sg:address":"Korte Mooiaardstraat 2",
    "sg:city":"Heuvelland",
    "sg:orig_category":"Eleveurs and marchands de porcs",
    "sg:phone":"+32 57 44 41 88",
    "sg:postcode":"8950",
    "sg:province":"West-Vlaanderen",
    "wof:name":"Gerardine Depuydt",
    "wof:placetype":"venue"
},
  "geometry": {"coordinates":[2.8155519962,50.7455825806],"type":"Point"}
}