{
  "type": "Feature",
  "properties": {
    "iso:country":"BE",
    "sg:address":"Boskapellaan 49",
    "sg:city":"Lochristi",
    "sg:classifiers":[
        {
            "category":"Professional",
            "subcategory":"Management & Consulting",
            "type":"Services"
        }
    ],
    "sg:phone":"+32 9 355 79 85",
    "sg:postcode":"9080",
    "sg:province":"Oost-Vlaanderen",
    "sg:tags":[
        "-",
        "processing",
        "data",
        "consultant"
    ],
    "wof:name":"International Systems Management Consultants Bvba",
    "wof:placetype":"venue"
},
  "geometry": {"coordinates":[3.849916935,51.087688446],"type":"Point"}
}