{
  "type": "Feature",
  "properties": {
    "iso:country":"BE",
    "sg:address":"Drie Eikenstraat 510",
    "sg:city":"Edegem",
    "sg:classifiers":[
        {
            "category":"Arena",
            "subcategory":"Sports Club",
            "type":"Entertainment"
        }
    ],
    "sg:phone":"+32 3 288 51 10",
    "sg:postcode":"2650",
    "sg:province":"Antwerpen",
    "sg:tags":[
        "de"
    ],
    "wof:name":"Edegemse Golf Club",
    "wof:placetype":"venue"
},
  "geometry": {"coordinates":[4.4171080589,51.1553611755],"type":"Point"}
}