{
  "type": "Feature",
  "properties": {
    "addr:full":"Leenwegel 1 Landegem Oost-Vlaanderen 9850",
    "addr:housenumber":"1",
    "addr:postcode":"9850",
    "addr:street":"Leenwegel;Oost-Vlaanderen",
    "iso:country":"BE",
    "sg:address":"Leenwegel 1",
    "sg:city":"Landegem",
    "sg:orig_category":"Entretien and r\u00e9parations de machines de bureau and ordinateurs. Ordinateurs and \u00e9quipement informat",
    "sg:phone":"+32 9 371 96 16",
    "sg:postcode":"9850",
    "sg:province":"Oost-Vlaanderen",
    "wof:name":"Hspa",
    "wof:placetype":"venue"
},
  "geometry": {"coordinates":[3.5494019985,51.0329589844],"type":"Point"}
}