{
  "type": "Feature",
  "properties": {
    "addr:full":"Voie De Li\u00e8ge 133 Chaudfontaine (embourg) Li\u00e8ge 4053",
    "addr:housenumber":"133",
    "addr:postcode":"4053",
    "addr:street":"Voie De Lie\u0300Ge",
    "iso:country":"BE",
    "sg:address":"Voie De Li\u00e8ge 133",
    "sg:city":"Chaudfontaine (embourg)",
    "sg:classifiers":[
        {
            "category":"Autos & Motor Vehicles",
            "subcategory":"Motorcycle Sales",
            "type":"Retail Goods"
        }
    ],
    "sg:phone":"+32 4 369 40 78",
    "sg:postcode":"4053",
    "sg:province":"Li\u00e8ge",
    "sg:tags":[
        "motorbike"
    ],
    "wof:name":"Herzet F",
    "wof:placetype":"venue"
},
  "geometry": {"coordinates":[5.6186637878,50.5877799988],"type":"Point"}
}