{
  "type": "Feature",
  "properties": {
    "iso:country":"BE",
    "sg:address":"Rue De La Gare 15",
    "sg:city":"Eghezee",
    "sg:orig_category":"Entretien and r\u00e9parations de voitures",
    "sg:phone":"+32 81 81 13 98",
    "sg:postcode":"5310",
    "sg:province":"Namur",
    "wof:name":"Garage Simonet C.",
    "wof:placetype":"venue"
},
  "geometry": {"coordinates":[4.9110479355,50.5968513489],"type":"Point"}
}