{
  "type": "Feature",
  "properties": {
    "addr:full":"Schorvoortberg 43 Turnhout Antwerpen 2300",
    "addr:housenumber":"43",
    "addr:postcode":"2300",
    "addr:street":"Schorvoortberg",
    "iso:country":"BE",
    "sg:address":"Schorvoortberg 43",
    "sg:city":"Turnhout",
    "sg:classifiers":[
        {
            "category":"Building & Trades",
            "subcategory":"Landscaping Services",
            "type":"Services"
        }
    ],
    "sg:phone":"+32 14 43 89 39",
    "sg:postcode":"2300",
    "sg:province":"Antwerpen",
    "sg:tags":[
        "-",
        "lopping",
        "work",
        "tree",
        "felling"
    ],
    "wof:name":"Arboklim Bvba",
    "wof:placetype":"venue"
},
  "geometry": {"coordinates":[4.9588871002,51.3094978333],"type":"Point"}
}