{
  "type": "Feature",
  "properties": {
    "addr:full":"Antwerpsestw 386 Lier Antwerpen 2500",
    "addr:housenumber":"386",
    "addr:postcode":"2500",
    "iso:country":"BE",
    "sg:address":"Antwerpsestw 386",
    "sg:city":"Lier",
    "sg:classifiers":[
        {
            "category":"Professional",
            "subcategory":"Printing & Photocopies",
            "type":"Services"
        }
    ],
    "sg:phone":"+32 3 490 47 11",
    "sg:postcode":"2500",
    "sg:province":"Antwerpen",
    "sg:tags":[
        "publishing"
    ],
    "wof:name":"Drukkerij Monti Nv",
    "wof:placetype":"venue"
},
  "geometry": {"coordinates":[4.5330138206,51.1499061584],"type":"Point"}
}