{
  "type": "Feature",
  "properties": {
    "addr:full":"Rue Bour\u00e9 3 Bruxelles (ixelles) Bruxelles-Capitale 1050",
    "addr:housenumber":"3",
    "addr:postcode":"1050",
    "addr:street":"Rue Boure\u0301",
    "iso:country":"BE",
    "sg:address":"Rue Bour\u00e9 3",
    "sg:city":"Bruxelles (ixelles)",
    "sg:classifiers":[
        {
            "category":"Health Services",
            "subcategory":"Dentist",
            "type":"Services"
        }
    ],
    "sg:phone":"+32 2 512 06 30",
    "sg:postcode":"1050",
    "sg:province":"Bruxelles-Capitale",
    "wof:name":"Charbel R",
    "wof:placetype":"venue"
},
  "geometry": {"coordinates":[4.3660259247,50.8356513977],"type":"Point"}
}