{
  "type": "Feature",
  "properties": {
    "iso:country":"BE",
    "sg:address":"Olympiadelaan Z/n",
    "sg:city":"Herentals",
    "sg:classifiers":[
        {
            "category":"Arena",
            "subcategory":"Sports Club",
            "type":"Entertainment"
        }
    ],
    "sg:phone":"+32 14 22 53 45",
    "sg:postcode":"2200",
    "sg:province":"Antwerpen",
    "sg:tags":[
        "terrain",
        "hors",
        "de",
        "installation",
        "sportifs"
    ],
    "wof:name":"Sefa Sport",
    "wof:placetype":"venue"
},
  "geometry": {"coordinates":[4.8360338211,51.1774635315],"type":"Point"}
}