{
  "type": "Feature",
  "properties": {
    "addr:full":"Rue Des Bruy\u00c8res 172 Eghezee Namur 5310",
    "addr:housenumber":"172",
    "addr:postcode":"5310",
    "addr:street":"Rue Des Bruye\u0300Res;Namur",
    "iso:country":"BE",
    "sg:address":"Rue Des Bruy\u00c8res 172",
    "sg:city":"Eghezee",
    "sg:orig_category":"Bijouteries and horlogeries",
    "sg:phone":"+32 81 51 19 45",
    "sg:postcode":"5310",
    "sg:province":"Namur",
    "wof:name":"Jacques Gengoux",
    "wof:placetype":"venue"
},
  "geometry": {"coordinates":[4.8963980675,50.5429077148],"type":"Point"}
}