{
  "type": "Feature",
  "properties": {
    "addr:full":"Boterhoek 12 Zottegem (sint-maria-oudenhove) Oost-Vlaanderen 9620",
    "addr:housenumber":"12",
    "addr:postcode":"9620",
    "addr:street":"Boterhoek",
    "iso:country":"BE",
    "sg:address":"Boterhoek 12",
    "sg:city":"Zottegem (sint-maria-oudenhove)",
    "sg:classifiers":[
        {
            "category":"Health Services",
            "subcategory":"Health Practitioner",
            "type":"Services"
        }
    ],
    "sg:phone":"+32 9 360 52 43",
    "sg:postcode":"9620",
    "sg:province":"Oost-Vlaanderen",
    "sg:tags":[
        "physiotherapist"
    ],
    "wof:name":"Plovier D",
    "wof:placetype":"venue"
},
  "geometry": {"coordinates":[3.7709739208,50.8415908813],"type":"Point"}
}