{
  "type": "Feature",
  "properties": {
    "iso:country":"BE",
    "sg:address":"Doornstraat 252",
    "sg:city":"Temse",
    "sg:classifiers":[
        {
            "category":"Restaurant",
            "type":"Food & Drink"
        }
    ],
    "sg:phone":"+32 3 711 07 63",
    "sg:postcode":"9140",
    "sg:province":"Oost-Vlaanderen",
    "wof:name":"La Provence",
    "wof:placetype":"venue"
},
  "geometry": {"coordinates":[4.2020897865,51.1537628174],"type":"Point"}
}