{
  "type": "Feature",
  "properties": {
    "addr:full":"Larendries 49 Sint-amands Antwerpen 2890",
    "addr:housenumber":"49",
    "addr:postcode":"2890",
    "addr:street":"Larendries",
    "iso:country":"BE",
    "sg:address":"Larendries 49",
    "sg:city":"Sint-amands",
    "sg:orig_category":"Vins Fab. Distilleries",
    "sg:phone":"+32 52 33 26 89",
    "sg:postcode":"2890",
    "sg:province":"Antwerpen",
    "wof:name":"Petrus Hallez",
    "wof:placetype":"venue"
},
  "geometry": {"coordinates":[4.2123680115,51.0435752869],"type":"Point"}
}