{
  "type": "Feature",
  "properties": {
    "iso:country":"BE",
    "sg:address":"Walenstr 92",
    "sg:city":"Hasselt",
    "sg:classifiers":[
        {
            "category":"Professional",
            "subcategory":"Advertising",
            "type":"Services"
        }
    ],
    "sg:phone":"+32 11 21 10 15",
    "sg:postcode":"3500",
    "sg:province":"Limburg",
    "sg:tags":[
        "information",
        "medium",
        "communication"
    ],
    "wof:name":"Studio Truyens Bvba",
    "wof:placetype":"venue"
},
  "geometry": {"coordinates":[5.3601198196,50.9536895752],"type":"Point"}
}