{
  "type": "Feature",
  "properties": {
    "addr:full":"Markt 18 Lennik Vlaams-Brabant 1750",
    "addr:housenumber":"18;1750",
    "addr:street":"Markt;Vlaams-Brabant",
    "iso:country":"BE",
    "sg:address":"Markt 18",
    "sg:city":"Lennik",
    "sg:orig_category":"Overheidsdiensten",
    "sg:phone":"+32 2 532 41 15",
    "sg:postcode":"1750",
    "sg:province":"Vlaams-Brabant",
    "wof:name":"Gemeentebestuur",
    "wof:placetype":"venue"
},
  "geometry": {"coordinates":[4.1546258926,50.8059387207],"type":"Point"}
}