{
  "type": "Feature",
  "properties": {
    "addr:full":"Rozendalestraat 64 Wingene West-Vlaanderen 8750",
    "addr:housenumber":"64",
    "addr:postcode":"8750",
    "addr:street":"Rozendalestraat",
    "iso:country":"BE",
    "sg:address":"Rozendalestraat 64",
    "sg:city":"Wingene",
    "sg:orig_category":"Location de mat\u00e9riel pour banquets and \u00e9v\u00e9nements. Eleveurs and marchands de porcs. Eleveurs de bovi",
    "sg:phone":"+32 51 65 56 81",
    "sg:postcode":"8750",
    "sg:province":"West-Vlaanderen",
    "wof:name":"Ketelaere",
    "wof:placetype":"venue"
},
  "geometry": {"coordinates":[3.2624890804,51.0641593933],"type":"Point"}
}