{
  "type": "Feature",
  "properties": {
    "iso:country":"BE",
    "sg:address":"Minderbroedersstraat 17",
    "sg:city":"Antwerpen",
    "sg:classifiers":[
        {
            "category":"Bars & Pubs",
            "type":"Food & Drink"
        }
    ],
    "sg:phone":"+32 3 231 11 73",
    "sg:postcode":"2000",
    "sg:province":"Antwerpen",
    "wof:name":"Berenbak",
    "wof:placetype":"venue"
},
  "geometry": {"coordinates":[4.4047341347,51.2225837708],"type":"Point"}
}