{
  "type": "Feature",
  "properties": {
    "addr:full":"8 Terheidenboslaan 1730 Asse 8",
    "addr:housenumber":"8",
    "addr:postcode":"1730",
    "addr:street":"Terheidenboslaan",
    "iso:country":"BE",
    "sg:address":"8",
    "sg:city":"Terheidenboslaan 1730 Asse",
    "sg:classifiers":[
        {
            "category":"Manufacturing",
            "subcategory":"Rubber & Plastics",
            "type":"Manufacturing & Wholesale Goods"
        }
    ],
    "sg:phone":"+32 2 452 33 93",
    "sg:postcode":"8",
    "wof:name":"Carpanel Nv",
    "wof:placetype":"venue"
},
  "geometry": {"coordinates":[4.2250151634,50.9121742249],"type":"Point"}
}