{
  "type": "Feature",
  "properties": {
    "addr:full":"Rue Du Bercet 23 Couvin Namur 5660",
    "addr:housenumber":"23",
    "addr:postcode":"5660",
    "addr:street":"Rue Du Bercet",
    "iso:country":"BE",
    "sg:address":"Rue Du Bercet 23",
    "sg:city":"Couvin",
    "sg:classifiers":[
        {
            "category":"Bars & Pubs",
            "type":"Food & Drink"
        }
    ],
    "sg:phone":"+32 60 34 66 95",
    "sg:postcode":"5660",
    "sg:province":"Namur",
    "sg:tags":[
        "tavern"
    ],
    "wof:name":"Marie-florence (chez)",
    "wof:placetype":"venue"
},
  "geometry": {"coordinates":[4.4939751625,50.0525093079],"type":"Point"}
}