{
  "type": "Feature",
  "properties": {
    "addr:full":"Spilstraat 27 Neeroeteren Limburg 3680",
    "addr:housenumber":"27",
    "addr:postcode":"3680",
    "addr:street":"Spilstraat",
    "iso:country":"BE",
    "sg:address":"Spilstraat 27",
    "sg:city":"Neeroeteren",
    "sg:orig_category":"Verlichting and huishoudartikelen",
    "sg:phone":"+32 89 86 49 28",
    "sg:postcode":"3680",
    "sg:province":"Limburg",
    "wof:name":"Geschenken Bussels",
    "wof:placetype":"venue"
},
  "geometry": {"coordinates":[5.701444149,51.0918922424],"type":"Point"}
}