{
  "type": "Feature",
  "properties": {
    "iso:country":"BE",
    "sg:address":"Burgemeester Lionel Pussemierstraat 153",
    "sg:city":"Eeklo",
    "sg:classifiers":[
        {
            "category":"Shopping",
            "subcategory":"Bicycles & Sporting Goods",
            "type":"Retail Goods"
        }
    ],
    "sg:phone":"+32 9 377 27 25",
    "sg:postcode":"9900",
    "sg:province":"Oost-Vlaanderen",
    "sg:tags":[
        "-"
    ],
    "wof:name":"De Muynck S",
    "wof:placetype":"venue"
},
  "geometry": {"coordinates":[3.5770580769,51.1855010986],"type":"Point"}
}