{
  "type": "Feature",
  "properties": {
    "iso:country":"BE",
    "sg:address":"Albert Rowiesstraat 4b",
    "sg:city":"Hoeilaart",
    "sg:classifiers":[
        {
            "category":"Professional",
            "subcategory":"Art Services",
            "type":"Services"
        }
    ],
    "sg:phone":"+32 2 657 30 76",
    "sg:postcode":"1560",
    "sg:province":"Vlaams-Brabant",
    "sg:tags":[
        "sculptor"
    ],
    "wof:name":"Strebelle V",
    "wof:placetype":"venue"
},
  "geometry": {"coordinates":[4.4720392227,50.7619171143],"type":"Point"}
}