{
  "type": "Feature",
  "properties": {
    "iso:country":"BE",
    "sg:address":"Etienne Balcaenstraat 43",
    "sg:city":"Avelgem",
    "sg:orig_category":"Eleveurs and marchands de porcs",
    "sg:phone":"+32 56 64 44 73",
    "sg:postcode":"8580",
    "sg:province":"West-Vlaanderen",
    "wof:name":"Ghislaine Verhiest",
    "wof:placetype":"venue"
},
  "geometry": {"coordinates":[3.4413640499,50.7626876831],"type":"Point"}
}