{
  "type": "Feature",
  "properties": {
    "iso:country":"BE",
    "sg:address":"Rue De Gembloux 189",
    "sg:city":"Namur",
    "sg:orig_category":"Verplichte sociale verzekeringen",
    "sg:phone":"+32 81 73 29 33",
    "sg:postcode":"5002",
    "sg:province":"Namur",
    "wof:name":"Office R\u00c9gional",
    "wof:placetype":"venue"
},
  "geometry": {"coordinates":[4.8462319374,50.4782791138],"type":"Point"}
}