{
  "type": "Feature",
  "properties": {
    "iso:country":"BE",
    "sg:address":"Vervierser Strasse 29",
    "sg:city":"Eupen",
    "sg:classifiers":[
        {
            "category":"Health Services",
            "subcategory":"Dentist",
            "type":"Services"
        }
    ],
    "sg:phone":"+32 87 55 54 01",
    "sg:postcode":"4700",
    "sg:province":"Li\u00e8ge",
    "wof:name":"Baguette H",
    "wof:placetype":"venue"
},
  "geometry": {"coordinates":[6.0249500275,50.6318473816],"type":"Point"}
}