{
  "type": "Feature",
  "properties": {
    "addr:full":"Botermarkt 16 Hasselt Limburg 3500",
    "addr:housenumber":"16",
    "addr:postcode":"3500",
    "addr:street":"Botermarkt",
    "iso:country":"BE",
    "sg:address":"Botermarkt 16",
    "sg:city":"Hasselt",
    "sg:classifiers":[
        {
            "category":"Retail",
            "subcategory":"Repair Shop",
            "type":"Services"
        }
    ],
    "sg:phone":"+32 11 22 24 21",
    "sg:postcode":"3500",
    "sg:province":"Limburg",
    "sg:tags":[
        "-",
        "mainten",
        "watch",
        "clock"
    ],
    "wof:name":"Depooter",
    "wof:placetype":"venue"
},
  "geometry": {"coordinates":[5.3385639191,50.9306793213],"type":"Point"}
}