{
  "type": "Feature",
  "properties": {
    "iso:country":"BE",
    "sg:address":"Rue De L'auripette 1",
    "sg:city":"Gembloux",
    "sg:orig_category":"Diverse bouwafwerking and reiniging",
    "sg:phone":"+32 81 63 49 20",
    "sg:postcode":"5032",
    "sg:province":"Namur",
    "wof:name":"Paulo De Oliveira",
    "wof:placetype":"venue"
},
  "geometry": {"coordinates":[4.6985421181,50.5215644836],"type":"Point"}
}