{
  "type": "Feature",
  "properties": {
    "addr:full":"Gentsesteenweg 97 Wetteren Oost-Vlaanderen 9230",
    "addr:housenumber":"97",
    "addr:postcode":"9230",
    "addr:street":"Gentsesteenweg",
    "iso:country":"BE",
    "sg:address":"Gentsesteenweg 97",
    "sg:city":"Wetteren",
    "sg:classifiers":[
        {
            "category":"Home & Garden",
            "subcategory":"Building Materials",
            "type":"Retail Goods"
        }
    ],
    "sg:phone":"+32 9 369 47 47",
    "sg:postcode":"9230",
    "sg:province":"Oost-Vlaanderen",
    "sg:tags":[
        "article",
        "-",
        "do-it-yourself"
    ],
    "wof:name":"Luwaert Interieur Bvba",
    "wof:placetype":"venue"
},
  "geometry": {"coordinates":[3.8717200756,51.0002746582],"type":"Point"}
}