{
  "type": "Feature",
  "properties": {
    "addr:full":"Stationsstraat 33 Izegem West-Vlaanderen 8870",
    "addr:housenumber":"33",
    "addr:postcode":"8870",
    "addr:street":"Stationsstraat",
    "iso:country":"BE",
    "sg:address":"Stationsstraat 33",
    "sg:city":"Izegem",
    "sg:classifiers":[
        {
            "category":"Professional",
            "subcategory":"Art Services",
            "type":"Services"
        }
    ],
    "sg:phone":"+32 51 30 00 24",
    "sg:postcode":"8870",
    "sg:province":"West-Vlaanderen",
    "sg:tags":[
        "photographer"
    ],
    "wof:name":"Wenerdroom",
    "wof:placetype":"venue"
},
  "geometry": {"coordinates":[3.2125930786,50.9204902649],"type":"Point"}
}