{
  "type": "Feature",
  "properties": {
    "addr:full":"Chemin De Catomoreau 20 Waterloo Brabant Wallon 1410",
    "addr:housenumber":"20",
    "addr:postcode":"1410",
    "addr:street":"Chemin De Catomoreau",
    "iso:country":"BE",
    "sg:address":"Chemin De Catomoreau 20",
    "sg:city":"Waterloo",
    "sg:orig_category":"M\u00e9decins and sp\u00e9cialistes",
    "sg:phone":"+32 2 384 08 59",
    "sg:postcode":"1410",
    "sg:province":"Brabant Wallon",
    "wof:name":"Nathalie Biebuyck",
    "wof:placetype":"venue"
},
  "geometry": {"coordinates":[4.416891098,50.6927452087],"type":"Point"}
}