{
  "type": "Feature",
  "properties": {
    "addr:full":"Nieuwstraat 28 Laakdal (forest) Antwerpen 2430",
    "addr:housenumber":"28",
    "addr:postcode":"2430",
    "addr:street":"Nieuwstraat",
    "iso:country":"BE",
    "sg:address":"Nieuwstraat 28",
    "sg:city":"Laakdal (forest)",
    "sg:orig_category":"Leisure articles",
    "sg:phone":"+32 13 66 18 58",
    "sg:postcode":"2430",
    "sg:province":"Antwerpen",
    "wof:name":"Theys S",
    "wof:placetype":"venue"
},
  "geometry": {"coordinates":[5.0718708038,51.0905685425],"type":"Point"}
}