{
  "type": "Feature",
  "properties": {
    "addr:full":"Luikersteenweg 145 Heers Limburg 3870",
    "addr:housenumber":"145",
    "addr:postcode":"3870",
    "addr:street":"Luikersteenweg",
    "iso:country":"BE",
    "sg:address":"Luikersteenweg 145",
    "sg:city":"Heers",
    "sg:orig_category":"Blanchisseries and teintureries",
    "sg:phone":"+32 11 48 50 45",
    "sg:postcode":"3870",
    "sg:province":"Limburg",
    "wof:name":"Joseph Vansimsen",
    "wof:placetype":"venue"
},
  "geometry": {"coordinates":[5.3017759323,50.752746582],"type":"Point"}
}