{
  "type": "Feature",
  "properties": {
    "iso:country":"BE",
    "sg:address":"Bouteille 34",
    "sg:city":"Olne",
    "sg:orig_category":"Eleveurs de bovins",
    "sg:phone":"+32 87 26 74 07",
    "sg:postcode":"4877",
    "sg:province":"Li\u00e8ge",
    "wof:name":"Philippe Jortay",
    "wof:placetype":"venue"
},
  "geometry": {"coordinates":[5.7654919624,50.5986328125],"type":"Point"}
}