{
  "type": "Feature",
  "properties": {
    "addr:full":"Dorpstraat 120 Wichelen Oost-Vlaanderen 9260",
    "addr:housenumber":"120",
    "addr:postcode":"9260",
    "addr:street":"Dorpstraat",
    "iso:country":"BE",
    "sg:address":"Dorpstraat 120",
    "sg:city":"Wichelen",
    "sg:orig_category":"Slagers",
    "sg:phone":"+32 9 369 20 49",
    "sg:postcode":"9260",
    "sg:province":"Oost-Vlaanderen",
    "wof:name":"Gilbert Corthals",
    "wof:placetype":"venue"
},
  "geometry": {"coordinates":[3.9233739376,50.9904556274],"type":"Point"}
}