{
  "type": "Feature",
  "properties": {
    "addr:full":"Rue Arthur Warocqu\u00c9 47 La Louvi\u00c8re Hainaut 7100",
    "addr:housenumber":"47",
    "addr:postcode":"7100",
    "addr:street":"Rue Arthur Warocque\u0301",
    "iso:country":"BE",
    "sg:address":"Rue Arthur Warocqu\u00c9 47",
    "sg:city":"La Louvi\u00c8re",
    "sg:orig_category":"Artsen and specialisten",
    "sg:phone":"+32 64 84 91 22",
    "sg:postcode":"7100",
    "sg:province":"Hainaut",
    "wof:name":"Jean-louis Pestiaux",
    "wof:placetype":"venue"
},
  "geometry": {"coordinates":[4.1920499802,50.4772605896],"type":"Point"}
}