{
  "type": "Feature",
  "properties": {
    "iso:country":"BE",
    "sg:address":"Avenue D' Esneux 236",
    "sg:city":"Esneux",
    "sg:orig_category":"Journaux. Tabac",
    "sg:phone":"+32 4 388 27 74",
    "sg:postcode":"4130",
    "sg:province":"Li\u00e8ge",
    "wof:name":"Librairie Nicole",
    "wof:placetype":"venue"
},
  "geometry": {"coordinates":[5.5899729729,50.5484542847],"type":"Point"}
}