{
  "type": "Feature",
  "properties": {
    "iso:country":"BE",
    "sg:address":"Avenue Des Saisons 22",
    "sg:city":"Elsene/ixelles",
    "sg:orig_category":"Pharmaciens",
    "sg:phone":"+32 2 648 51 53",
    "sg:postcode":"1050",
    "sg:province":"Bruxelles-Capitale",
    "wof:name":"Nicole Fontaine",
    "wof:placetype":"venue"
},
  "geometry": {"coordinates":[4.3861980438,50.8199310303],"type":"Point"}
}