{
  "type": "Feature",
  "properties": {
    "iso:country":"BE",
    "sg:address":"Avenue De Marlagne 2",
    "sg:city":"Namur",
    "sg:orig_category":"Apotheken",
    "sg:phone":"+32 81 73 63 13",
    "sg:postcode":"5000",
    "sg:province":"Namur",
    "wof:name":"Francoise Gilmard",
    "wof:placetype":"venue"
},
  "geometry": {"coordinates":[4.8428611755,50.459980011],"type":"Point"}
}