{
  "type": "Feature",
  "properties": {
    "iso:country":"BE",
    "sg:address":"Fr\u00c8re-orbanstraat 9",
    "sg:city":"Oostende",
    "sg:orig_category":"Artsen and specialisten",
    "sg:phone":"+32 59 70 33 67",
    "sg:postcode":"8400",
    "sg:province":"West-Vlaanderen",
    "wof:name":"Pieter Caenen",
    "wof:placetype":"venue"
},
  "geometry": {"coordinates":[2.9086680412,51.221282959],"type":"Point"}
}