{
  "type": "Feature",
  "properties": {
    "addr:full":"Westkerkestraat 49 Ichtegem (eernegem) West-Vlaanderen 8480",
    "addr:housenumber":"49",
    "addr:postcode":"8480",
    "addr:street":"Westkerkestraat",
    "iso:country":"BE",
    "sg:address":"Westkerkestraat 49",
    "sg:city":"Ichtegem (eernegem)",
    "sg:classifiers":[
        {
            "category":"Banks & Credit Unions",
            "subcategory":"Investment Brokerage",
            "type":"Services"
        }
    ],
    "sg:phone":"+32 59 29 83 29",
    "sg:postcode":"8480",
    "sg:province":"West-Vlaanderen",
    "sg:tags":[
        "printing",
        "-"
    ],
    "wof:name":"Drukhuis Debeer Bvba",
    "wof:placetype":"venue"
},
  "geometry": {"coordinates":[3.0267341137,51.1327056885],"type":"Point"}
}