{
  "type": "Feature",
  "properties": {
    "iso:country":"BE",
    "sg:address":"Ijzerwegstraat 16",
    "sg:city":"Oostende",
    "sg:orig_category":"V\u00e9los",
    "sg:phone":"+32 59 70 68 01",
    "sg:postcode":"8400",
    "sg:province":"West-Vlaanderen",
    "wof:name":"Huis Van Iseghem",
    "wof:placetype":"venue"
},
  "geometry": {"coordinates":[2.9362308979,51.2174835205],"type":"Point"}
}