{
  "type": "Feature",
  "properties": {
    "iso:country":"BE",
    "sg:address":"Hauseter-strasse 6-7",
    "sg:city":"Kelmis/la Calamine",
    "sg:orig_category":"Bloemen and planten Boomkwekerijen Tuinbenodigdheden Tuinen",
    "sg:phone":"+32 87 65 96 37",
    "sg:postcode":"4728",
    "sg:province":"Li\u00e8ge",
    "wof:name":"Ren\u00c9 Dodemont",
    "wof:placetype":"venue"
},
  "geometry": {"coordinates":[6.0302791595,50.7077445984],"type":"Point"}
}