{
  "type": "Feature",
  "properties": {
    "iso:country":"BE",
    "sg:address":"Sluisstraat 4",
    "sg:city":"Brugge",
    "sg:orig_category":"Voertuigen",
    "sg:phone":"+32 50 59 83 00",
    "sg:postcode":"8000",
    "sg:province":"West-Vlaanderen",
    "wof:name":"Garage Combitech",
    "wof:placetype":"venue"
},
  "geometry": {"coordinates":[3.2269730568,51.2240562439],"type":"Point"}
}