{
  "type": "Feature",
  "properties": {
    "addr:full":"Hollestraat 7 Opwijk Vlaams-Brabant 1745",
    "addr:housenumber":"7",
    "addr:postcode":"1745",
    "addr:street":"Hollestraat",
    "iso:country":"BE",
    "sg:address":"Hollestraat 7",
    "sg:city":"Opwijk",
    "sg:classifiers":[
        {
            "category":"Retail",
            "subcategory":"Repair Shop",
            "type":"Services"
        }
    ],
    "sg:phone":"+32 52 35 99 57",
    "sg:postcode":"1745",
    "sg:province":"Vlaams-Brabant",
    "sg:tags":[
        "upholsterer"
    ],
    "wof:name":"Sanders M",
    "wof:placetype":"venue"
},
  "geometry": {"coordinates":[4.1987109184,50.9668769836],"type":"Point"}
}