{
  "type": "Feature",
  "properties": {
    "addr:full":"Stationsplein 2 Kasterlee Antwerpen 2460",
    "addr:housenumber":"2",
    "addr:postcode":"2460",
    "addr:street":"Stationsplein",
    "iso:country":"BE",
    "sg:address":"Stationsplein 2",
    "sg:city":"Kasterlee",
    "sg:orig_category":"Alimentation sp\u00e9cialis\u00e9e. Catering and organisation de f\u00eates. Restauration pour collectivit\u00e9s. Resta",
    "sg:phone":"+32 14 55 74 47",
    "sg:postcode":"2460",
    "sg:province":"Antwerpen",
    "wof:name":"\u00b4t Meuleke",
    "wof:placetype":"venue"
},
  "geometry": {"coordinates":[4.9671049118,51.2406616211],"type":"Point"}
}