{
  "type": "Feature",
  "properties": {
    "iso:country":"BE",
    "sg:address":"Avenue Comte De Smet De Nayer 2 Box 28",
    "sg:city":"Namur",
    "sg:orig_category":"Fairs, shows, exhibitions",
    "sg:phone":"+32 81 22 81 23",
    "sg:postcode":"5000",
    "sg:province":"Namur",
    "wof:name":"Best Environnement",
    "wof:placetype":"venue"
},
  "geometry": {"coordinates":[4.8741641045,50.4639282227],"type":"Point"}
}