{
  "type": "Feature",
  "properties": {
    "addr:full":"Arbespine 50 Jalhay Li\u00e8ge 4845",
    "addr:housenumber":"50",
    "addr:postcode":"4845",
    "addr:street":"Arbespine",
    "iso:country":"BE",
    "sg:address":"Arbespine 50",
    "sg:city":"Jalhay",
    "sg:orig_category":"Paramedische behandelingen",
    "sg:phone":"+32 87 47 53 80",
    "sg:postcode":"4845",
    "sg:province":"Li\u00e8ge",
    "wof:name":"P. Vermeiren",
    "wof:placetype":"venue"
},
  "geometry": {"coordinates":[5.9044141769,50.5175704956],"type":"Point"}
}