{
  "type": "Feature",
  "properties": {
    "iso:country":"BE",
    "sg:address":"Koeistraat 59",
    "sg:city":"Arendonk",
    "sg:orig_category":"Artsen and specialisten",
    "sg:phone":"+32 14 67 06 61",
    "sg:postcode":"2370",
    "sg:province":"Antwerpen",
    "wof:name":"Johan Lambrechts",
    "wof:placetype":"venue"
},
  "geometry": {"coordinates":[5.0872302055,51.3176612854],"type":"Point"}
}