{
  "type": "Feature",
  "properties": {
    "iso:country":"BE",
    "sg:address":"Hendrik Consciencestraat 8",
    "sg:city":"Kortrijk",
    "sg:classifiers":[
        {
            "category":"Shopping",
            "subcategory":"Beauty & Cosmetics",
            "type":"Retail Goods"
        }
    ],
    "sg:phone":"+32 56 22 31 08",
    "sg:postcode":"8500",
    "sg:province":"West-Vlaanderen",
    "sg:tags":[
        "-",
        "perfumery"
    ],
    "wof:name":"D.p. Line",
    "wof:placetype":"venue"
},
  "geometry": {"coordinates":[3.2597260475,50.8266448975],"type":"Point"}
}