{
  "type": "Feature",
  "properties": {
    "iso:country":"BE",
    "sg:address":"Rue De Nazareth 2",
    "sg:city":"Ath",
    "sg:orig_category":"Mus\u00e9es and patrimoine culturel",
    "sg:phone":"+32 68 26 92 33",
    "sg:postcode":"7800",
    "sg:province":"Hainaut",
    "wof:name":"Mus\u00c9e Espace Gallo-romain",
    "wof:placetype":"venue"
},
  "geometry": {"coordinates":[3.778539896,50.6302185059],"type":"Point"}
}