{
  "type": "Feature",
  "properties": {
    "addr:full":"Rue Franz Merjay 1 Bruxelles (ixelles) Bruxelles-Capitale 1050",
    "addr:housenumber":"1",
    "addr:postcode":"1050",
    "addr:street":"Rue Franz Merjay",
    "iso:country":"BE",
    "sg:address":"Rue Franz Merjay 1",
    "sg:city":"Bruxelles (ixelles)",
    "sg:classifiers":[
        {
            "category":"Real Estate",
            "subcategory":"Real Estate Services",
            "type":"Services"
        }
    ],
    "sg:phone":"+32 2 346 80 46",
    "sg:postcode":"1050",
    "sg:province":"Bruxelles-Capitale",
    "wof:name":"Sogemi Immobilier",
    "wof:placetype":"venue"
},
  "geometry": {"coordinates":[4.3549690247,50.8219451904],"type":"Point"}
}