{
  "type": "Feature",
  "properties": {
    "iso:country":"BE",
    "sg:address":"Rue Louis Van Beethoven 60",
    "sg:city":"Bruxelles (anderlecht)",
    "sg:classifiers":[
        {
            "category":"Building & Trades",
            "subcategory":"Cleaning & Sanitation",
            "type":"Services"
        }
    ],
    "sg:phone":"+32 2 521 03 24",
    "sg:postcode":"1070",
    "sg:province":"Bruxelles-Capitale",
    "sg:tags":[
        "janitor"
    ],
    "wof:name":"Star Net Cris",
    "wof:placetype":"venue"
},
  "geometry": {"coordinates":[4.2967300415,50.8290863037],"type":"Point"}
}