{
  "type": "Feature",
  "properties": {
    "iso:country":"BE",
    "sg:address":"Rue De La Malle-poste 12",
    "sg:city":"Watermaal-bosvoorde/watermael-boitsfort",
    "sg:orig_category":"Studios photographiques",
    "sg:phone":"+32 2 675 57 13",
    "sg:postcode":"1170",
    "sg:province":"Bruxelles-Capitale",
    "wof:name":"Michel Gelinne",
    "wof:placetype":"venue"
},
  "geometry": {"coordinates":[4.4020338058,50.8076438904],"type":"Point"}
}