{
  "type": "Feature",
  "properties": {
    "iso:country":"BE",
    "sg:address":"Brusselsestraat 240",
    "sg:city":"Leuven",
    "sg:classifiers":[
        {
            "category":"Real Estate",
            "subcategory":"Architect",
            "type":"Services"
        }
    ],
    "sg:phone":"+32 16 23 41 25",
    "sg:postcode":"3000",
    "sg:province":"Vlaams-Brabant",
    "wof:name":"Moors M",
    "wof:placetype":"venue"
},
  "geometry": {"coordinates":[4.6889429092,50.8819274902],"type":"Point"}
}