{
  "type": "Feature",
  "properties": {
    "iso:country":"BE",
    "sg:address":"Domaine Vincent Van Gogh 40-41",
    "sg:city":"Boussu (hornu)",
    "sg:classifiers":[
        {
            "category":"Social Services",
            "type":"Services"
        }
    ],
    "sg:phone":"+32 65 77 85 96",
    "sg:postcode":"7301",
    "sg:province":"Hainaut",
    "wof:name":"S.o.s Alcool",
    "wof:placetype":"venue"
},
  "geometry": {"coordinates":[3.8270859718,50.4235076904],"type":"Point"}
}