{
  "type": "Feature",
  "properties": {
    "addr:full":"Churchilllaan 194 Schoten Antwerpen 2900",
    "addr:housenumber":"194",
    "addr:postcode":"2900",
    "addr:street":"Churchilllaan",
    "iso:country":"BE",
    "sg:address":"Churchilllaan 194",
    "sg:city":"Schoten",
    "sg:orig_category":"Diverse bouwafwerking and reiniging",
    "sg:phone":"+32 3 685 15 28",
    "sg:postcode":"2900",
    "sg:province":"Antwerpen",
    "wof:name":"Beto-clean",
    "wof:placetype":"venue"
},
  "geometry": {"coordinates":[4.4871940613,51.2500686646],"type":"Point"}
}