{
  "type": "Feature",
  "properties": {
    "addr:full":"Rue De La Loi 107 Bruxelles Bruxelles-Capitale 1040",
    "addr:housenumber":"107",
    "addr:postcode":"1040",
    "addr:street":"Rue De La Loi",
    "iso:country":"BE",
    "sg:address":"Rue De La Loi 107",
    "sg:city":"Bruxelles",
    "sg:classifiers":[
        {
            "category":"Travel",
            "subcategory":"Hotels & Motels",
            "type":"Entertainment"
        }
    ],
    "sg:phone":"+32 2 230 13 33",
    "sg:postcode":"1040",
    "sg:province":"Bruxelles-Capitale",
    "sg:tags":[
        "hotels",
        "business",
        "restaurant"
    ],
    "wof:name":"Crowne Plaza Brussels Europa",
    "wof:placetype":"venue"
},
  "geometry": {"coordinates":[4.3779392242,50.8435821533],"type":"Point"}
}