{
  "type": "Feature",
  "properties": {
    "iso:country":"BE",
    "sg:address":"Molenaarstraat 39",
    "sg:city":"Beringen",
    "sg:orig_category":"Epiceries",
    "sg:phone":"+32 11 34 15 12",
    "sg:postcode":"3581",
    "sg:province":"Limburg",
    "wof:name":"L. Theunis",
    "wof:placetype":"venue"
},
  "geometry": {"coordinates":[5.2285552025,51.0906677246],"type":"Point"}
}