{
  "type": "Feature",
  "properties": {
    "addr:full":"Tusvoort 100 Tessenderlo Limburg 3980",
    "addr:housenumber":"100",
    "addr:postcode":"3980",
    "addr:street":"Tessenderlo Limburg",
    "iso:country":"BE",
    "sg:address":"Tusvoort 100",
    "sg:city":"Tessenderlo",
    "sg:orig_category":"Diensten voor huisdieren",
    "sg:phone":"+32 13 66 61 03",
    "sg:postcode":"3980",
    "sg:province":"Limburg",
    "wof:name":"Pluto",
    "wof:placetype":"venue"
},
  "geometry": {"coordinates":[5.1402101517,51.0714683533],"type":"Point"}
}