{
  "type": "Feature",
  "properties": {
    "addr:full":"Oorlogsvrijwilligsstraat 13 Moeskroen/mouscron Hainaut 7711",
    "addr:housenumber":"13",
    "addr:postcode":"7711",
    "addr:street":"Oorlogsvrijwilligsstraat",
    "iso:country":"BE",
    "sg:address":"Oorlogsvrijwilligsstraat 13",
    "sg:city":"Moeskroen/mouscron",
    "sg:orig_category":"Plaatsen van vloer- and muurbekleding Schilders",
    "sg:phone":"+32 56 48 52 77",
    "sg:postcode":"7711",
    "sg:province":"Hainaut",
    "wof:name":"Indigo",
    "wof:placetype":"venue"
},
  "geometry": {"coordinates":[3.3073959351,50.7293014526],"type":"Point"}
}