{
  "type": "Feature",
  "properties": {
    "addr:full":"Berkenlaan 18 Steenokkerzeel (melsbroek) Vlaams-Brabant 1820",
    "addr:housenumber":"18",
    "addr:postcode":"1820",
    "addr:street":"Berkenlaan",
    "iso:country":"BE",
    "sg:address":"Berkenlaan 18",
    "sg:city":"Steenokkerzeel (melsbroek)",
    "sg:classifiers":[
        {
            "category":"Community Center",
            "subcategory":"Social",
            "type":"Public Place"
        }
    ],
    "sg:phone":"+32 2 751 84 85",
    "sg:postcode":"1820",
    "sg:province":"Vlaams-Brabant",
    "sg:tags":[
        "-",
        "haute",
        "clothing",
        "couture"
    ],
    "wof:name":"Gino V",
    "wof:placetype":"venue"
},
  "geometry": {"coordinates":[4.492582798,50.9247436523],"type":"Point"}
}