{
  "type": "Feature",
  "properties": {
    "iso:country":"BE",
    "sg:address":"Weidepenningstraat 26",
    "sg:city":"Damme (sijsele)",
    "sg:classifiers":[
        {
            "category":"Real Estate",
            "subcategory":"Surveying",
            "type":"Services"
        }
    ],
    "sg:phone":"+32 50 37 29 06",
    "sg:postcode":"8340",
    "sg:province":"West-Vlaanderen",
    "sg:tags":[
        "surveyor",
        "land"
    ],
    "wof:name":"Henneco L",
    "wof:placetype":"venue"
},
  "geometry": {"coordinates":[3.3110840321,51.2078590393],"type":"Point"}
}