{
  "type": "Feature",
  "properties": {
    "iso:country":"BE",
    "sg:address":"Rue De Tournai 192",
    "sg:city":"Beloeil (stambruges)",
    "sg:classifiers":[
        {
            "category":"Building & Trades",
            "subcategory":"Construction",
            "type":"Services"
        }
    ],
    "sg:phone":"+32 69 56 02 26",
    "sg:postcode":"7973",
    "sg:province":"Hainaut",
    "sg:tags":[
        "scaffolding"
    ],
    "wof:name":"Atlas Copco/ Six Equipment",
    "wof:placetype":"venue"
},
  "geometry": {"coordinates":[3.6951210499,50.5047492981],"type":"Point"}
}