{
  "type": "Feature",
  "properties": {
    "addr:full":"Bergensesteenweg 398 Sint-pieters-leeuw Vlaams-Brabant 1600",
    "addr:housenumber":"398",
    "addr:postcode":"1600",
    "addr:street":"Bergensesteenweg",
    "iso:country":"BE",
    "sg:address":"Bergensesteenweg 398",
    "sg:city":"Sint-pieters-leeuw",
    "sg:orig_category":"Installatie van houten of kunststof schrijnwerk",
    "sg:phone":"+32 2 378 31 02",
    "sg:postcode":"1600",
    "sg:province":"Vlaams-Brabant",
    "wof:name":"Vandervoorde",
    "wof:placetype":"venue"
},
  "geometry": {"coordinates":[4.2767248154,50.7855377197],"type":"Point"}
}