{
  "type": "Feature",
  "properties": {
    "iso:country":"BE",
    "sg:address":"Genkerbaan 54",
    "sg:city":"Zonhoven",
    "sg:classifiers":[
        {
            "category":"Shopping",
            "subcategory":"Gifts & Souvenirs",
            "type":"Retail Goods"
        }
    ],
    "sg:phone":"+32 11 82 16 74",
    "sg:postcode":"3520",
    "sg:province":"Limburg",
    "sg:tags":[
        "-"
    ],
    "wof:name":"Koopjesstock",
    "wof:placetype":"venue"
},
  "geometry": {"coordinates":[5.3735880852,50.9913978577],"type":"Point"}
}