{
  "type": "Feature",
  "properties": {
    "iso:country":"BE",
    "sg:address":"Place Aux Foires 21",
    "sg:city":"Marche-en-famenne",
    "sg:orig_category":"Banken and kredietinstellingen Verzekeringsmakelaars and experts",
    "sg:phone":"+32 84 31 17 84",
    "sg:postcode":"6900",
    "sg:province":"Luxembourg",
    "wof:name":"Bacob",
    "wof:placetype":"venue"
},
  "geometry": {"coordinates":[5.3451480865,50.2257728577],"type":"Point"}
}