{
  "type": "Feature",
  "properties": {
    "iso:country":"BE",
    "sg:address":"Oelegembaan 13a",
    "sg:city":"Zandhoven",
    "sg:orig_category":"Herstellingen and onderhoud van auto's",
    "sg:phone":"+32 3 484 50 26",
    "sg:postcode":"2243",
    "sg:province":"Antwerpen",
    "wof:name":"Soetewey",
    "wof:placetype":"venue"
},
  "geometry": {"coordinates":[4.6551170349,51.2133636475],"type":"Point"}
}