{
  "type": "Feature",
  "properties": {
    "addr:full":"Doregem 91 Bornem Antwerpen 2880",
    "addr:housenumber":"91",
    "addr:postcode":"2880",
    "addr:street":"Doregem",
    "iso:country":"BE",
    "sg:address":"Doregem 91",
    "sg:city":"Bornem",
    "sg:classifiers":[
        {
            "category":"Health Services",
            "subcategory":"Nursing And Care Facility",
            "type":"Services"
        }
    ],
    "sg:phone":"+32 3 889 60 68",
    "sg:postcode":"2880",
    "sg:province":"Antwerpen",
    "sg:tags":[
        "home"
    ],
    "wof:name":"Van Hamme & Cie",
    "wof:placetype":"venue"
},
  "geometry": {"coordinates":[4.2501401901,51.0864944458],"type":"Point"}
}