{
  "type": "Feature",
  "properties": {
    "addr:full":"Wolfseind 14 Arendonk Antwerpen 2370",
    "addr:housenumber":"14",
    "addr:postcode":"2370",
    "addr:street":"Wolfseind",
    "iso:country":"BE",
    "sg:address":"Wolfseind 14",
    "sg:city":"Arendonk",
    "sg:orig_category":"Woningbouw",
    "sg:phone":"+32 14 67 85 05",
    "sg:postcode":"2370",
    "sg:province":"Antwerpen",
    "wof:name":"Hubert Van Steenbergen",
    "wof:placetype":"venue"
},
  "geometry": {"coordinates":[5.0960388184,51.3220214844],"type":"Point"}
}