{
  "type": "Feature",
  "properties": {
    "iso:country":"BE",
    "sg:address":"Processieweg 46",
    "sg:city":"Lichtervelde",
    "sg:orig_category":"Bouwmaterialen Gh",
    "sg:phone":"+32 51 72 43 22",
    "sg:postcode":"8810",
    "sg:province":"West-Vlaanderen",
    "wof:name":"Fa. De Meulenaere",
    "wof:placetype":"venue"
},
  "geometry": {"coordinates":[3.1477220058,51.0214614868],"type":"Point"}
}