{
  "type": "Feature",
  "properties": {
    "iso:country":"BE",
    "sg:address":"Rue Georges Bodard 71ba",
    "sg:city":"Musson",
    "sg:orig_category":"Imprimeries and copyshops",
    "sg:phone":"+32 63 67 55 76",
    "sg:postcode":"6750",
    "sg:province":"Luxembourg",
    "wof:name":"Bruno Roels",
    "wof:placetype":"venue"
},
  "geometry": {"coordinates":[5.7190599442,49.5588417053],"type":"Point"}
}