{
  "type": "Feature",
  "properties": {
    "iso:country":"BE",
    "sg:address":"Stationsstraat 8ba",
    "sg:city":"Aalst",
    "sg:orig_category":"Pain, p\u00e2tisseries and confiseries",
    "sg:phone":"+32 53 77 89 27",
    "sg:postcode":"9308",
    "sg:province":"Oost-Vlaanderen",
    "wof:name":"Patisserie Napoleon",
    "wof:placetype":"venue"
},
  "geometry": {"coordinates":[4.0371479988,50.9416923523],"type":"Point"}
}