{
  "type": "Feature",
  "properties": {
    "addr:full":"Europark 1511 Houthalen-helchteren Limburg 3530",
    "addr:housenumber":"1511",
    "addr:postcode":"3530",
    "addr:street":"Europark",
    "iso:country":"BE",
    "sg:address":"Europark 1511",
    "sg:city":"Houthalen-helchteren",
    "sg:orig_category":"Woningbouw",
    "sg:phone":"+32 11 52 51 61",
    "sg:postcode":"3530",
    "sg:province":"Limburg",
    "wof:name":"Gabri\u00cbls-schr\u00d6der",
    "wof:placetype":"venue"
},
  "geometry": {"coordinates":[5.4041419029,51.0400619507],"type":"Point"}
}