{
  "type": "Feature",
  "properties": {
    "iso:country":"BE",
    "sg:address":"Rue Du Champ De L'eglise 2",
    "sg:city":"Bruxelles",
    "sg:orig_category":"Sportclubs",
    "sg:phone":"+32 475 75 65 56",
    "sg:postcode":"1020",
    "sg:province":"Bruxelles-Capitale",
    "wof:name":"Racing Jet De Bruxelles",
    "wof:placetype":"venue"
},
  "geometry": {"coordinates":[4.3548259735,50.8777275085],"type":"Point"}
}