{
  "type": "Feature",
  "properties": {
    "iso:country":"BE",
    "sg:address":"Rue De Marchovelette 35",
    "sg:city":"Namur",
    "sg:classifiers":[
        {
            "category":"Shopping",
            "subcategory":"Bicycles & Sporting Goods",
            "type":"Retail Goods"
        }
    ],
    "sg:phone":"+32 81 46 13 03",
    "sg:postcode":"5000",
    "sg:province":"Namur",
    "sg:tags":[
        "article",
        "de",
        "sport",
        "camping"
    ],
    "wof:name":"R.b. Industrie Et Marine",
    "wof:placetype":"venue"
},
  "geometry": {"coordinates":[4.8663988113,50.462677002],"type":"Point"}
}