{
  "type": "Feature",
  "properties": {
    "iso:country":"BE",
    "sg:address":"Rue Albert 1er 5",
    "sg:city":"Les Bons Villers",
    "sg:orig_category":"Ordinateurs and \u00e9quipement informatique. Entretien and r\u00e9parations de machines de bureau and ordinat",
    "sg:phone":"+32 71 85 19 82",
    "sg:postcode":"6210",
    "sg:province":"Hainaut",
    "wof:name":"M.v. Informatique",
    "wof:placetype":"venue"
},
  "geometry": {"coordinates":[4.4481739998,50.5360374451],"type":"Point"}
}