{
  "type": "Feature",
  "properties": {
    "addr:full":"Sint-jansweg 3 Beveren (verrebroek) Oost-Vlaanderen 9130",
    "addr:housenumber":"3",
    "addr:postcode":"9130",
    "addr:street":"Sint-Jansweg",
    "iso:country":"BE",
    "sg:address":"Sint-jansweg 3",
    "sg:city":"Beveren (verrebroek)",
    "sg:classifiers":[
        {
            "category":"Transit Center",
            "subcategory":"Freight",
            "type":"Transportation"
        }
    ],
    "sg:phone":"+32 3 575 05 50",
    "sg:postcode":"9130",
    "sg:province":"Oost-Vlaanderen",
    "sg:tags":[
        "tanker",
        "-",
        "transport"
    ],
    "wof:name":"De Jongh Transport Nv",
    "wof:placetype":"venue"
},
  "geometry": {"coordinates":[4.2616200447,51.2697944641],"type":"Point"}
}