{
  "type": "Feature",
  "properties": {
    "addr:full":"Roodebeeksteenweg 243 Brussel/bruxelles Bruxelles-Capitale 1200",
    "addr:housenumber":"243",
    "addr:postcode":"1200",
    "addr:street":"Roodebeeksteenweg;/",
    "iso:country":"BE",
    "sg:address":"Roodebeeksteenweg 243",
    "sg:city":"Brussel/bruxelles",
    "sg:orig_category":"Banken and kredietinstellingen",
    "sg:phone":"+32 2 762 84 48",
    "sg:postcode":"1200",
    "sg:province":"Bruxelles-Capitale",
    "wof:name":"Fortis",
    "wof:placetype":"venue"
},
  "geometry": {"coordinates":[4.4263048172,50.8480758667],"type":"Point"}
}