{
  "type": "Feature",
  "properties": {
    "addr:full":"Lange Lobroekstraat 65 Antwerpen Antwerpen 2060",
    "addr:housenumber":"65",
    "addr:postcode":"2060",
    "addr:street":"Lange Lobroekstraat",
    "iso:country":"BE",
    "sg:address":"Lange Lobroekstraat 65",
    "sg:city":"Antwerpen",
    "sg:classifiers":[
        {
            "category":"Restaurant",
            "type":"Food & Drink"
        }
    ],
    "sg:phone":"+32 3 271 08 71",
    "sg:postcode":"2060",
    "sg:province":"Antwerpen",
    "wof:name":"Den Abboitoir",
    "wof:placetype":"venue"
},
  "geometry": {"coordinates":[4.4322462082,51.229259491],"type":"Point"}
}