{
  "type": "Feature",
  "properties": {
    "iso:country":"BE",
    "sg:address":"Rue De La Magr\u00c9e 26",
    "sg:city":"Anthisnes",
    "sg:orig_category":"Artsen and specialisten",
    "sg:phone":"+32 4 383 66 38",
    "sg:postcode":"4163",
    "sg:province":"Li\u00e8ge",
    "wof:name":"L. Erpicum",
    "wof:placetype":"venue"
},
  "geometry": {"coordinates":[5.4701499939,50.4961433411],"type":"Point"}
}