{
  "type": "Feature",
  "properties": {
    "addr:full":"Tongersesteenweg 298 Kortessem Limburg 3724",
    "addr:housenumber":"298",
    "addr:postcode":"3724",
    "addr:street":"Tongersesteenweg",
    "iso:country":"BE",
    "sg:address":"Tongersesteenweg 298",
    "sg:city":"Kortessem",
    "sg:orig_category":"Rundveehouders",
    "sg:phone":"+32 12 23 71 61",
    "sg:postcode":"3724",
    "sg:province":"Limburg",
    "wof:name":"Erik Wilmots",
    "wof:placetype":"venue"
},
  "geometry": {"coordinates":[5.4130301476,50.8234024048],"type":"Point"}
}