{
  "type": "Feature",
  "properties": {
    "iso:country":"BE",
    "sg:address":"Oude Kortrijkstraat 15",
    "sg:city":"Zonnebeke (beselare)",
    "sg:classifiers":[
        {
            "category":"Shopping",
            "subcategory":"Florist",
            "type":"Retail Goods"
        }
    ],
    "sg:phone":"+32 57 46 69 87",
    "sg:postcode":"8980",
    "sg:province":"West-Vlaanderen",
    "wof:name":"Mylle G",
    "wof:placetype":"venue"
},
  "geometry": {"coordinates":[3.0200579166,50.8511734009],"type":"Point"}
}