{
  "type": "Feature",
  "properties": {
    "addr:full":"Gorsemweg 10 Sint-truiden Limburg 3800",
    "addr:housenumber":"10",
    "addr:postcode":"3800",
    "addr:street":"Gorsemweg",
    "iso:country":"BE",
    "sg:address":"Gorsemweg 10",
    "sg:city":"Sint-truiden",
    "sg:orig_category":"Architectes",
    "sg:phone":"+32 11 68 38 54",
    "sg:postcode":"3800",
    "sg:province":"Limburg",
    "wof:name":"Pierre Reynaerts En Zonen",
    "wof:placetype":"venue"
},
  "geometry": {"coordinates":[5.1811571121,50.819065094],"type":"Point"}
}