{
  "type": "Feature",
  "properties": {
    "addr:full":"Rue Docteur Andr\u00e9 52 Ellezelles Hainaut 7890",
    "addr:housenumber":"52",
    "addr:postcode":"7890",
    "addr:street":"Rue Docteur Andre\u0301",
    "iso:country":"BE",
    "sg:address":"Rue Docteur Andr\u00e9 52",
    "sg:city":"Ellezelles",
    "sg:classifiers":[
        {
            "category":"Health Services",
            "subcategory":"Health Practitioner",
            "type":"Services"
        }
    ],
    "sg:phone":"+32 68 54 22 44",
    "sg:postcode":"7890",
    "sg:province":"Hainaut",
    "sg:tags":[
        "physiotherapist"
    ],
    "wof:name":"Hermant Jean-pierre",
    "wof:placetype":"venue"
},
  "geometry": {"coordinates":[3.6809930801,50.7367897034],"type":"Point"}
}