{
  "type": "Feature",
  "properties": {
    "addr:full":"Grand Place 35 Mouscron Hainaut 7700",
    "addr:housenumber":"35",
    "addr:postcode":"7700",
    "addr:street":"Grand Place",
    "iso:country":"BE",
    "sg:address":"Grand Place 35",
    "sg:city":"Mouscron",
    "sg:classifiers":[
        {
            "category":"Bars & Pubs",
            "type":"Food & Drink"
        }
    ],
    "sg:phone":"+32 56 34 46 85",
    "sg:postcode":"7700",
    "sg:province":"Hainaut",
    "wof:name":"Paix (la)",
    "wof:placetype":"venue"
},
  "geometry": {"coordinates":[3.2150170803,50.7436141968],"type":"Point"}
}