{
  "type": "Feature",
  "properties": {
    "addr:full":"Rue Basse Hollande 1 Jodoigne Brabant Wallon 1370",
    "addr:housenumber":"1",
    "addr:postcode":"1370",
    "addr:street":"Rue Basse Hollande",
    "iso:country":"BE",
    "sg:address":"Rue Basse Hollande 1",
    "sg:city":"Jodoigne",
    "sg:classifiers":[
        {
            "category":"Professional",
            "subcategory":"Management & Consulting",
            "type":"Services"
        }
    ],
    "sg:phone":"+32 10 81 31 85",
    "sg:postcode":"1370",
    "sg:province":"Brabant Wallon",
    "sg:tags":[
        "-",
        "processing",
        "data",
        "consultant"
    ],
    "wof:name":"Carlot M",
    "wof:placetype":"venue"
},
  "geometry": {"coordinates":[4.8600158691,50.7460708618],"type":"Point"}
}