{
  "type": "Feature",
  "properties": {
    "addr:full":"Marais D'acren 30 Lessines Hainaut 7864",
    "addr:housenumber":"30",
    "addr:postcode":"7864",
    "addr:street":"Hainaut",
    "iso:country":"BE",
    "sg:address":"Marais D'acren 30",
    "sg:city":"Lessines",
    "sg:orig_category":"Artistes ind\u00e9pendants",
    "sg:phone":"+32 68 33 81 79",
    "sg:postcode":"7864",
    "sg:province":"Hainaut",
    "wof:name":"Bernard Payen",
    "wof:placetype":"venue"
},
  "geometry": {"coordinates":[3.8720219135,50.7253494263],"type":"Point"}
}