{
  "type": "Feature",
  "properties": {
    "addr:full":"Schuttersvest 19 Mechelen Antwerpen 2800",
    "addr:housenumber":"19",
    "addr:postcode":"2800",
    "addr:street":"Schuttersvest",
    "iso:country":"BE",
    "sg:address":"Schuttersvest 19",
    "sg:city":"Mechelen",
    "sg:classifiers":[
        {
            "category":"Health Services",
            "subcategory":"Dentist",
            "type":"Services"
        }
    ],
    "sg:phone":"+32 15 41 40 27",
    "sg:postcode":"2800",
    "sg:province":"Antwerpen",
    "wof:name":"Cornez Christa",
    "wof:placetype":"venue"
},
  "geometry": {"coordinates":[4.4783101082,51.0210647583],"type":"Point"}
}