{
  "type": "Feature",
  "properties": {
    "iso:country":"BE",
    "sg:address":"Rue De La Station 154",
    "sg:city":"Havelange",
    "sg:classifiers":[
        {
            "category":"Shopping",
            "subcategory":"Antiques",
            "type":"Retail Goods"
        }
    ],
    "sg:phone":"+32 478 32 52 78",
    "sg:postcode":"5370",
    "sg:province":"Namur",
    "sg:tags":[
        "restoration"
    ],
    "wof:name":"Wilmotte B",
    "wof:placetype":"venue"
},
  "geometry": {"coordinates":[5.2522439957,50.3819274902],"type":"Point"}
}