{
  "type": "Feature",
  "properties": {
    "addr:full":"Jonkershovestraat 49 Houthulst West-Vlaanderen 8650",
    "addr:housenumber":"49",
    "addr:postcode":"8650",
    "addr:street":"Jonkershovestraat",
    "iso:country":"BE",
    "sg:address":"Jonkershovestraat 49",
    "sg:city":"Houthulst",
    "sg:classifiers":[
        {
            "category":"Personal",
            "subcategory":"Beauty Salon",
            "type":"Services"
        }
    ],
    "sg:phone":"+32 51 70 55 00",
    "sg:postcode":"8650",
    "sg:province":"West-Vlaanderen",
    "sg:tags":[
        "lady",
        "-",
        "hairdressing"
    ],
    "wof:name":"J.d.-hairdesign",
    "wof:placetype":"venue"
},
  "geometry": {"coordinates":[2.9424209595,50.9760093689],"type":"Point"}
}