{
  "type": "Feature",
  "properties": {
    "addr:full":"Torenstraat 40 Arendonk Antwerpen 2370",
    "addr:housenumber":"40",
    "addr:postcode":"2370",
    "addr:street":"Torenstraat",
    "iso:country":"BE",
    "sg:address":"Torenstraat 40",
    "sg:city":"Arendonk",
    "sg:orig_category":"Dansscholen",
    "sg:phone":"+32 14 67 09 60",
    "sg:postcode":"2370",
    "sg:province":"Antwerpen",
    "wof:name":"Dansliga Sportfederatie",
    "wof:placetype":"venue"
},
  "geometry": {"coordinates":[5.0828509331,51.3194274902],"type":"Point"}
}