{
  "type": "Feature",
  "properties": {
    "iso:country":"BE",
    "sg:address":"Centrum Zuid 2415",
    "sg:city":"Houthalen-helchteren (houthalen)",
    "sg:orig_category":"Non-Classified Establishments",
    "sg:phone":"+32 11 82 26 82",
    "sg:postcode":"3530",
    "sg:province":"Limburg",
    "wof:name":"Van Oirschot Nv",
    "wof:placetype":"venue"
},
  "geometry": {"coordinates":[5.3518128395,51.0194778442],"type":"Point"}
}