{
  "type": "Feature",
  "properties": {
    "iso:country":"BE",
    "sg:address":"Moorselbaan 262",
    "sg:city":"Aalst",
    "sg:orig_category":"Rev\u00eatements pour sols and murs. Peinture",
    "sg:phone":"+32 53 77 89 56",
    "sg:postcode":"9300",
    "sg:province":"Oost-Vlaanderen",
    "wof:name":"Hugo Hobbels",
    "wof:placetype":"venue"
},
  "geometry": {"coordinates":[4.060585022,50.9437828064],"type":"Point"}
}