{
  "type": "Feature",
  "properties": {
    "iso:country":"BE",
    "sg:address":"Herentalseweg 34",
    "sg:city":"Olen",
    "sg:classifiers":[
        {
            "category":"Recreation",
            "subcategory":"Amusement Park",
            "type":"Entertainment"
        }
    ],
    "sg:phone":"+32 14 26 33 10",
    "sg:postcode":"2250",
    "sg:province":"Antwerpen",
    "sg:tags":[
        "attraction",
        "-",
        "sale",
        "fair",
        "hiring"
    ],
    "wof:name":"Promo Rent",
    "wof:placetype":"venue"
},
  "geometry": {"coordinates":[4.8547868729,51.1458778381],"type":"Point"}
}