{
  "type": "Feature",
  "properties": {
    "addr:full":"Maaseikersteenweg 40b Lanaken Limburg 3620",
    "addr:housenumber":"40b",
    "addr:postcode":"3620",
    "addr:street":"Maaseikersteenweg",
    "iso:country":"BE",
    "sg:address":"Maaseikersteenweg 40b",
    "sg:city":"Lanaken",
    "sg:orig_category":"Eclairage et \u00e9quipements du foyer. Fabrication and montage de mobilier. Plomberie, chauffage and ins",
    "sg:phone":"+32 89 71 45 34",
    "sg:postcode":"3620",
    "sg:province":"Limburg",
    "wof:name":"Sanhebec",
    "wof:placetype":"venue"
},
  "geometry": {"coordinates":[5.6734991074,50.8825187683],"type":"Point"}
}