{
  "type": "Feature",
  "properties": {
    "addr:full":"Kastanjelaan 45 Herentals Antwerpen 2200",
    "addr:housenumber":"45",
    "addr:postcode":"2200",
    "addr:street":"Kastanjelaan",
    "iso:country":"BE",
    "sg:address":"Kastanjelaan 45",
    "sg:city":"Herentals",
    "sg:orig_category":"Geluidsopnames",
    "sg:phone":"+32 14 21 12 45",
    "sg:postcode":"2200",
    "sg:province":"Antwerpen",
    "wof:name":"Geert Verbeeck",
    "wof:placetype":"venue"
},
  "geometry": {"coordinates":[4.8250918388,51.1608161926],"type":"Point"}
}