{
  "type": "Feature",
  "properties": {
    "addr:full":"Place Des Combattants 2 Mettet (biesmer\u00e9e) Namur 5640",
    "addr:housenumber":"2",
    "addr:postcode":"5640",
    "addr:street":"Place Des Combattants;Biesmere\u0301E",
    "iso:country":"BE",
    "sg:address":"Place Des Combattants 2",
    "sg:city":"Mettet (biesmer\u00e9e)",
    "sg:classifiers":[
        {
            "category":"Professional",
            "subcategory":"Art Services",
            "type":"Services"
        }
    ],
    "sg:phone":"+32 71 72 89 31",
    "sg:postcode":"5640",
    "sg:province":"Namur",
    "sg:tags":[
        "sculptor"
    ],
    "wof:name":"Artefact Sprl",
    "wof:placetype":"venue"
},
  "geometry": {"coordinates":[4.6800289154,50.2971801758],"type":"Point"}
}