{
  "type": "Feature",
  "properties": {
    "iso:country":"BE",
    "sg:address":"Oude Liersebaan 35",
    "sg:city":"Duffel",
    "sg:orig_category":"Opticiens",
    "sg:phone":"+32 15 32 03 52",
    "sg:postcode":"2570",
    "sg:province":"Antwerpen",
    "wof:name":"Fabrik Optik",
    "wof:placetype":"venue"
},
  "geometry": {"coordinates":[4.5177969933,51.0965995789],"type":"Point"}
}