{
  "type": "Feature",
  "properties": {
    "addr:full":"Rue De La Station 28 Anderlues Hainaut 6150",
    "addr:housenumber":"28",
    "addr:postcode":"6150",
    "addr:street":"Rue De La Station",
    "iso:country":"BE",
    "sg:address":"Rue De La Station 28",
    "sg:city":"Anderlues",
    "sg:classifiers":[
        {
            "category":"Health Services",
            "subcategory":"Doctor",
            "type":"Services"
        }
    ],
    "sg:phone":"+32 71 52 67 67",
    "sg:postcode":"6150",
    "sg:province":"Hainaut",
    "sg:tags":[
        "medicinephysicians",
        "surgeon"
    ],
    "wof:name":"Herman Y",
    "wof:placetype":"venue"
},
  "geometry": {"coordinates":[4.2812957764,50.4003715515],"type":"Point"}
}