{
  "type": "Feature",
  "properties": {
    "iso:country":"BE",
    "sg:address":"Tramlaan 117",
    "sg:city":"Zaventem",
    "sg:orig_category":"Astrologen, grafologen and mediums",
    "sg:phone":"+32 2 731 40 53",
    "sg:postcode":"1933",
    "sg:province":"Vlaams-Brabant",
    "wof:name":"Van Bever",
    "wof:placetype":"venue"
},
  "geometry": {"coordinates":[4.5073409081,50.8632087708],"type":"Point"}
}