{
  "type": "Feature",
  "properties": {
    "addr:full":"Dijk 99b1 Sint-katelijne-waver Antwerpen 2861",
    "addr:housenumber":"99b1",
    "addr:postcode":"2861",
    "addr:street":"Dijk",
    "iso:country":"BE",
    "sg:address":"Dijk 99b1",
    "sg:city":"Sint-katelijne-waver",
    "sg:classifiers":[
        {
            "category":"Insurance",
            "subcategory":"Life Insurance",
            "type":"Services"
        }
    ],
    "sg:phone":"+32 15 76 01 11",
    "sg:postcode":"2861",
    "sg:province":"Antwerpen",
    "sg:tags":[
        "assurance"
    ],
    "wof:name":"Fa. Hellemans",
    "wof:placetype":"venue"
},
  "geometry": {"coordinates":[4.5730400085,51.0555686951],"type":"Point"}
}