{
  "type": "Feature",
  "properties": {
    "iso:country":"BE",
    "sg:address":"Strandlaan 260",
    "sg:city":"Koksijde",
    "sg:classifiers":[
        {
            "category":"Health Services",
            "subcategory":"Health Practitioner",
            "type":"Services"
        }
    ],
    "sg:phone":"+32 58 52 06 86",
    "sg:postcode":"8670",
    "sg:province":"West-Vlaanderen",
    "sg:tags":[
        "physiotherapist"
    ],
    "wof:name":"Suber Sofie",
    "wof:placetype":"venue"
},
  "geometry": {"coordinates":[2.6128969193,51.1091766357],"type":"Point"}
}