{
  "type": "Feature",
  "properties": {
    "addr:full":"Bornstraat 1 Genk Limburg 3600",
    "addr:housenumber":"1",
    "addr:postcode":"3600",
    "addr:street":"Bornstraat",
    "iso:country":"BE",
    "sg:address":"Bornstraat 1",
    "sg:city":"Genk",
    "sg:classifiers":[
        {
            "category":"Restaurant",
            "type":"Food & Drink"
        }
    ],
    "sg:phone":"+32 89 84 53 70",
    "sg:postcode":"3600",
    "sg:province":"Limburg",
    "wof:name":"Erdal",
    "wof:placetype":"venue"
},
  "geometry": {"coordinates":[5.4893817902,51.0126800537],"type":"Point"}
}