{
  "type": "Feature",
  "properties": {
    "iso:country":"BE",
    "sg:address":"Haneveldlaan 42",
    "sg:city":"Grimbergen",
    "sg:orig_category":"Artsen and specialisten",
    "sg:phone":"+32 2 267 76 77",
    "sg:postcode":"1850",
    "sg:province":"Vlaams-Brabant",
    "wof:name":"P. Kocheleff",
    "wof:placetype":"venue"
},
  "geometry": {"coordinates":[4.3626232147,50.9149284363],"type":"Point"}
}