{
  "type": "Feature",
  "properties": {
    "addr:full":"Leuvensesteenweg 453 Kortenberg Vlaams-Brabant 3070",
    "addr:housenumber":"453",
    "addr:postcode":"3070",
    "addr:street":"Leuvensesteenweg;Vlaams-Brabant",
    "iso:country":"BE",
    "sg:address":"Leuvensesteenweg 453",
    "sg:city":"Kortenberg",
    "sg:orig_category":"Pain, p\u00e2tisseries and confiseries",
    "sg:phone":"+32 2 759 94 01",
    "sg:postcode":"3070",
    "sg:province":"Vlaams-Brabant",
    "wof:name":"Woontip Doopsuiker",
    "wof:placetype":"venue"
},
  "geometry": {"coordinates":[4.5449209213,50.8887672424],"type":"Point"}
}