{
  "type": "Feature",
  "properties": {
    "addr:full":"Zuidstationstraat 34-36 Gent Oost-Vlaanderen 9000",
    "addr:housenumber":"34-36",
    "addr:postcode":"9000",
    "addr:street":"Zuidstationstraat;Oost-Vlaanderen",
    "iso:country":"BE",
    "sg:address":"Zuidstationstraat 34-36",
    "sg:city":"Gent",
    "sg:classifiers":[
        {
            "category":"Insurance",
            "subcategory":"Insurance Agent",
            "type":"Services"
        }
    ],
    "sg:phone":"+32 9 233 22 11",
    "sg:postcode":"9000",
    "sg:province":"Oost-Vlaanderen",
    "sg:tags":[
        "broker"
    ],
    "wof:name":"Intereuropean Nv Esteco Group",
    "wof:placetype":"venue"
},
  "geometry": {"coordinates":[3.732542038,51.0489807129],"type":"Point"}
}