{
  "type": "Feature",
  "properties": {
    "iso:country":"BE",
    "sg:address":"Rue De La Fontaine 7",
    "sg:city":"Yvoir",
    "sg:orig_category":"Instituts de beaut\u00e9",
    "sg:phone":"+32 83 69 92 66",
    "sg:postcode":"5530",
    "sg:province":"Namur",
    "wof:name":"Joseph Lottin",
    "wof:placetype":"venue"
},
  "geometry": {"coordinates":[4.9717330933,50.313911438],"type":"Point"}
}