{
  "type": "Feature",
  "properties": {
    "addr:full":"Acht Gemetendreef 2 Oostkamp (hertsberge) West-Vlaanderen 8020",
    "addr:housenumber":"2",
    "addr:postcode":"8020",
    "iso:country":"BE",
    "sg:address":"Acht Gemetendreef 2",
    "sg:city":"Oostkamp (hertsberge)",
    "sg:classifiers":[
        {
            "category":"Building & Trades",
            "subcategory":"Cleaning & Sanitation",
            "type":"Services"
        }
    ],
    "sg:phone":"+32 50 28 05 05",
    "sg:postcode":"8020",
    "sg:province":"West-Vlaanderen",
    "sg:tags":[
        "cleaner",
        "window"
    ],
    "wof:name":"Ruitenwasserij Philippe",
    "wof:placetype":"venue"
},
  "geometry": {"coordinates":[3.293587923,51.0994949341],"type":"Point"}
}