{
  "type": "Feature",
  "properties": {
    "addr:full":"Maastrichtersteenweg 119 Box 2 Hasselt Limburg 3500",
    "addr:housenumber":"119;2",
    "addr:postcode":"3500",
    "addr:street":"Maastrichtersteenweg;Box",
    "iso:country":"BE",
    "sg:address":"Maastrichtersteenweg 119 Box 2",
    "sg:city":"Hasselt",
    "sg:classifiers":[
        {
            "category":"Fast Food",
            "type":"Food & Drink"
        }
    ],
    "sg:phone":"+32 11 74 01 80",
    "sg:postcode":"3500",
    "sg:province":"Limburg",
    "sg:tags":[
        "fried",
        "stand",
        "potato"
    ],
    "wof:name":"Lekker Stuk ('t)",
    "wof:placetype":"venue"
},
  "geometry": {"coordinates":[5.3515601158,50.9292182922],"type":"Point"}
}