{
  "type": "Feature",
  "properties": {
    "iso:country":"BE",
    "sg:address":"Vliegweg 22",
    "sg:city":"Oostkamp",
    "sg:orig_category":"Producteurs de l\u00e9gumes",
    "sg:phone":"+32 50 82 24 52",
    "sg:postcode":"8020",
    "sg:province":"West-Vlaanderen",
    "wof:name":"Kris De Guffroy",
    "wof:placetype":"venue"
},
  "geometry": {"coordinates":[3.2135910988,51.1483230591],"type":"Point"}
}