{
  "type": "Feature",
  "properties": {
    "iso:country":"BE",
    "sg:address":"Rue Centrale 53",
    "sg:city":"Weismes (robertville)",
    "sg:classifiers":[
        {
            "category":"Government",
            "subcategory":"Office",
            "type":"Public Place"
        }
    ],
    "sg:phone":"+32 80 44 64 75",
    "sg:postcode":"4950",
    "sg:province":"Li\u00e8ge",
    "sg:tags":[
        "-",
        "tourism",
        "federation"
    ],
    "wof:name":"Syndicat D'initiative De Robertville",
    "wof:placetype":"venue"
},
  "geometry": {"coordinates":[6.1225662231,50.4549064636],"type":"Point"}
}