{
  "type": "Feature",
  "properties": {
    "addr:full":"Vissenakenstraat 410 Tienen Vlaams-Brabant 3300",
    "addr:housenumber":"410",
    "addr:postcode":"3300",
    "addr:street":"Vissenakenstraat",
    "iso:country":"BE",
    "sg:address":"Vissenakenstraat 410",
    "sg:city":"Tienen",
    "sg:orig_category":"V\u00e9hicules automobiles. Entretien and r\u00e9parations de voitures",
    "sg:phone":"+32 16 81 64 48",
    "sg:postcode":"3300",
    "sg:province":"Vlaams-Brabant",
    "wof:name":"Garage Vanrijckegem",
    "wof:placetype":"venue"
},
  "geometry": {"coordinates":[4.9337100983,50.8235015869],"type":"Point"}
}