{
  "type": "Feature",
  "properties": {
    "iso:country":"BE",
    "sg:address":"Aux Rochettes 1",
    "sg:city":"Gesves (haltinne)",
    "sg:classifiers":[
        {
            "category":"Building & Trades",
            "subcategory":"Cleaning & Sanitation",
            "type":"Services"
        }
    ],
    "sg:phone":"+32 85 84 68 86",
    "sg:postcode":"5340",
    "sg:province":"Namur",
    "wof:name":"Alkemade E",
    "wof:placetype":"venue"
},
  "geometry": {"coordinates":[5.0755457878,50.4024353027],"type":"Point"}
}