{
  "type": "Feature",
  "properties": {
    "addr:full":"Dorpsstraat 101 Sint-laureins Oost-Vlaanderen 9980",
    "addr:housenumber":"101",
    "addr:postcode":"9980",
    "addr:street":"Dorpsstraat",
    "iso:country":"BE",
    "sg:address":"Dorpsstraat 101",
    "sg:city":"Sint-laureins",
    "sg:orig_category":"Epiceries",
    "sg:phone":"+32 9 379 85 66",
    "sg:postcode":"9980",
    "sg:province":"Oost-Vlaanderen",
    "wof:name":"Carla Hermie",
    "wof:placetype":"venue"
},
  "geometry": {"coordinates":[3.5254399776,51.241519928],"type":"Point"}
}