{
  "type": "Feature",
  "properties": {
    "iso:country":"BE",
    "sg:address":"Rue Du Roi Albert 1",
    "sg:city":"Colfontaine",
    "sg:orig_category":"Enseignement maternel and primaire",
    "sg:phone":"+32 65 66 72 49",
    "sg:postcode":"7340",
    "sg:province":"Hainaut",
    "wof:name":"Ecole Fond. Communale",
    "wof:placetype":"venue"
},
  "geometry": {"coordinates":[3.8376700878,50.4083099365],"type":"Point"}
}