{
  "type": "Feature",
  "properties": {
    "iso:country":"BE",
    "sg:address":"Avenue Reine Astrid 390",
    "sg:city":"Kraainem",
    "sg:classifiers":[
        {
            "category":"Insurance",
            "subcategory":"Life Insurance",
            "type":"Services"
        }
    ],
    "sg:phone":"+32 2 784 32 00",
    "sg:postcode":"1950",
    "sg:province":"Vlaams-Brabant",
    "sg:tags":[
        "assurance"
    ],
    "wof:name":"Stappaerts Benoit",
    "wof:placetype":"venue"
},
  "geometry": {"coordinates":[4.4689998627,50.8415756226],"type":"Point"}
}