{
  "type": "Feature",
  "properties": {
    "iso:country":"BE",
    "sg:address":"Vestje 7",
    "sg:city":"Brussel/bruxelles",
    "sg:orig_category":"Onderdelen and accessoires voor auto's",
    "sg:phone":"+32 2 513 06 70",
    "sg:postcode":"1000",
    "sg:province":"Bruxelles-Capitale",
    "wof:name":"Minguet",
    "wof:placetype":"venue"
},
  "geometry": {"coordinates":[4.3396968842,50.8455238342],"type":"Point"}
}