{
  "type": "Feature",
  "properties": {
    "addr:full":"Dr\u00c8ve Olympique 11 Anderlecht Bruxelles-Capitale 1070",
    "addr:housenumber":"11",
    "addr:postcode":"1070",
    "addr:street":"Dre\u0300Ve Olympique",
    "iso:country":"BE",
    "sg:address":"Dr\u00c8ve Olympique 11",
    "sg:city":"Anderlecht",
    "sg:classifiers":[
        {
            "category":"Fast Food",
            "type":"Food & Drink"
        }
    ],
    "sg:phone":"+32 2 523 54 71",
    "sg:postcode":"1070",
    "sg:province":"Bruxelles-Capitale",
    "sg:tags":[
        "\u00c0",
        "emporter",
        "restaurants"
    ],
    "wof:name":"Quick",
    "wof:placetype":"venue"
},
  "geometry": {"coordinates":[4.2753558159,50.8217391968],"type":"Point"}
}