{
  "type": "Feature",
  "properties": {
    "addr:full":"Centrumstraat 6a Lebbeke Oost-Vlaanderen 9280",
    "addr:housenumber":"6a",
    "addr:postcode":"9280",
    "addr:street":"Centrumstraat",
    "iso:country":"BE",
    "sg:address":"Centrumstraat 6a",
    "sg:city":"Lebbeke",
    "sg:classifiers":[
        {
            "category":"Professional",
            "subcategory":"Business Services",
            "type":"Services"
        }
    ],
    "sg:phone":"+32 52 41 05 50",
    "sg:postcode":"9280",
    "sg:province":"Oost-Vlaanderen",
    "sg:tags":[
        "automobile",
        "-",
        "assessor"
    ],
    "wof:name":"Rogge E",
    "wof:placetype":"venue"
},
  "geometry": {"coordinates":[4.1331410408,51.0011024475],"type":"Point"}
}