{
  "type": "Feature",
  "properties": {
    "iso:country":"BE",
    "sg:address":"Randoux 3",
    "sg:city":"Houffalize",
    "sg:orig_category":"H\u00f4tels. Restaurants",
    "sg:phone":"+32 61 28 80 44",
    "sg:postcode":"6663",
    "sg:province":"Luxembourg",
    "wof:name":"Auberge La Cl\u00c9 Des Champs",
    "wof:placetype":"venue"
},
  "geometry": {"coordinates":[5.7398071289,50.0987205505],"type":"Point"}
}