{
  "type": "Feature",
  "properties": {
    "addr:full":"Rodendijk 60 Zoersel Antwerpen 2980",
    "addr:housenumber":"60",
    "addr:postcode":"2980",
    "addr:street":"Rodendijk",
    "iso:country":"BE",
    "sg:address":"Rodendijk 60",
    "sg:city":"Zoersel",
    "sg:orig_category":"MEUBELONTWERP AND -INSTALLATIE Meubelzaken, woning- and keukeninrichting",
    "sg:phone":"+32 3 311 77 33",
    "sg:postcode":"2980",
    "sg:province":"Antwerpen",
    "wof:name":"Meubelen Frako",
    "wof:placetype":"venue"
},
  "geometry": {"coordinates":[4.7041211128,51.2472610474],"type":"Point"}
}