{
  "type": "Feature",
  "properties": {
    "addr:full":"Rue Du Calvaire 16 Charleroi (gosselies) Hainaut 6041",
    "addr:housenumber":"16",
    "addr:postcode":"6041",
    "addr:street":"Rue Du Calvaire",
    "iso:country":"BE",
    "sg:address":"Rue Du Calvaire 16",
    "sg:city":"Charleroi (gosselies)",
    "sg:classifiers":[
        {
            "category":"Utilities",
            "subcategory":"Mobile Phone",
            "type":"Services"
        }
    ],
    "sg:phone":"+32 71 37 01 29",
    "sg:postcode":"6041",
    "sg:province":"Hainaut",
    "sg:tags":[
        "access",
        "gsm",
        "-",
        "apparatus"
    ],
    "wof:name":"Multi Phone",
    "wof:placetype":"venue"
},
  "geometry": {"coordinates":[4.4816207886,50.4015769958],"type":"Point"}
}