{
  "type": "Feature",
  "properties": {
    "addr:full":"Bergstraat 37 Grimbergen Vlaams-Brabant 1850",
    "addr:housenumber":"37",
    "addr:postcode":"1850",
    "addr:street":"Bergstraat",
    "iso:country":"BE",
    "sg:address":"Bergstraat 37",
    "sg:city":"Grimbergen",
    "sg:classifiers":[
        {
            "category":"Farming",
            "subcategory":"Crops",
            "type":"Manufacturing & Wholesale Goods"
        }
    ],
    "sg:phone":"+32 2 251 14 97",
    "sg:postcode":"1850",
    "sg:province":"Vlaams-Brabant",
    "sg:tags":[
        "vegetable",
        "fruit",
        "-",
        "grower"
    ],
    "wof:name":"Doms J",
    "wof:placetype":"venue"
},
  "geometry": {"coordinates":[4.4032711983,50.9765853882],"type":"Point"}
}