{
  "type": "Feature",
  "properties": {
    "addr:full":"Kasteelstraat 50 Zottegem Oost-Vlaanderen 9620",
    "addr:housenumber":"50",
    "addr:postcode":"9620",
    "addr:street":"Kasteelstraat",
    "iso:country":"BE",
    "sg:address":"Kasteelstraat 50",
    "sg:city":"Zottegem",
    "sg:orig_category":"Artsen and specialisten",
    "sg:phone":"+32 9 360 07 36",
    "sg:postcode":"9620",
    "sg:province":"Oost-Vlaanderen",
    "wof:name":"Ina De Vis",
    "wof:placetype":"venue"
},
  "geometry": {"coordinates":[3.8076519966,50.8706245422],"type":"Point"}
}