{
  "type": "Feature",
  "properties": {
    "iso:country":"BE",
    "sg:address":"Rue Du Centre 2b",
    "sg:city":"H\u00e9l\u00e9cine (linsmeau)",
    "sg:classifiers":[
        {
            "category":"Real Estate",
            "subcategory":"Architect",
            "type":"Services"
        }
    ],
    "sg:phone":"+32 19 65 59 30",
    "sg:postcode":"1357",
    "sg:province":"Brabant Wallon",
    "wof:name":"Quintin I",
    "wof:placetype":"venue"
},
  "geometry": {"coordinates":[4.9954471588,50.7368202209],"type":"Point"}
}