{
  "type": "Feature",
  "properties": {
    "iso:country":"BE",
    "sg:address":"Rozenlaan 19",
    "sg:city":"Belsele",
    "sg:orig_category":"Huisdieren and benodigdheden Royal Canin",
    "sg:phone":"+32 3 722 01 79",
    "sg:postcode":"9111",
    "sg:province":"Oost-Vlaanderen",
    "wof:name":"Mariman Geert",
    "wof:placetype":"venue"
},
  "geometry": {"coordinates":[4.1008238792,51.147102356],"type":"Point"}
}