{
  "type": "Feature",
  "properties": {
    "addr:full":"Groenestraat 21 Kortrijk West-Vlaanderen 8501",
    "addr:housenumber":"21",
    "addr:postcode":"8501",
    "addr:street":"Groenestraat",
    "iso:country":"BE",
    "sg:address":"Groenestraat 21",
    "sg:city":"Kortrijk",
    "sg:orig_category":"Sportclubs",
    "sg:phone":"+32 56 35 52 59",
    "sg:postcode":"8501",
    "sg:province":"West-Vlaanderen",
    "wof:name":"V.c. Jong Kuurne",
    "wof:placetype":"venue"
},
  "geometry": {"coordinates":[3.2426700592,50.8566665649],"type":"Point"}
}