{
  "type": "Feature",
  "properties": {
    "addr:full":"Gompelbaan 165 Mol Antwerpen 2400",
    "addr:housenumber":"165",
    "addr:postcode":"2400",
    "addr:street":"Gompelbaan",
    "iso:country":"BE",
    "sg:address":"Gompelbaan 165",
    "sg:city":"Mol",
    "sg:orig_category":"Sportclubs",
    "sg:phone":"+32 14 31 75 23",
    "sg:postcode":"2400",
    "sg:province":"Antwerpen",
    "wof:name":"T.k. Zilverzand",
    "wof:placetype":"venue"
},
  "geometry": {"coordinates":[5.1486377716,51.1937866211],"type":"Point"}
}