{
  "type": "Feature",
  "properties": {
    "addr:full":"Industrieweg 5f Borgloon Limburg 3840",
    "addr:housenumber":"5f",
    "addr:postcode":"3840",
    "addr:street":"Industrieweg",
    "iso:country":"BE",
    "sg:address":"Industrieweg 5f",
    "sg:city":"Borgloon",
    "sg:classifiers":[
        {
            "category":"Shopping",
            "subcategory":"Antiques",
            "type":"Retail Goods"
        }
    ],
    "sg:phone":"+32 12 45 84 55",
    "sg:postcode":"3840",
    "sg:province":"Limburg",
    "sg:tags":[
        "restoration"
    ],
    "wof:name":"Roosen Mario - Morial",
    "wof:placetype":"venue"
},
  "geometry": {"coordinates":[5.3436970711,50.8130531311],"type":"Point"}
}