{
  "type": "Feature",
  "properties": {
    "iso:country":"BE",
    "sg:address":"Oosterhoven 16",
    "sg:city":"Herenthout",
    "sg:orig_category":"Eleveurs and marchands de porcs",
    "sg:phone":"+32 14 21 31 19",
    "sg:postcode":"2270",
    "sg:province":"Antwerpen",
    "wof:name":"Alfons Gios",
    "wof:placetype":"venue"
},
  "geometry": {"coordinates":[4.7912921906,51.1458435059],"type":"Point"}
}