{
  "type": "Feature",
  "properties": {
    "iso:country":"BE",
    "sg:address":"Avenue De Bouillon",
    "sg:city":"Libramont",
    "sg:orig_category":"RESTAURANTS: PENSIONS DE FAMILLE",
    "sg:phone":"+32 61 22 25 61",
    "sg:postcode":"6800",
    "sg:province":"Luxembourg",
    "wof:name":"Le Bon Vieux Temps",
    "wof:placetype":"venue"
},
  "geometry": {"coordinates":[5.36774683,49.9166412354],"type":"Point"}
}