{
  "type": "Feature",
  "properties": {
    "addr:full":"Turnhoutsebaan 278a Schilde Antwerpen 2970",
    "addr:housenumber":"278a",
    "addr:postcode":"2970",
    "addr:street":"Turnhoutsebaan",
    "iso:country":"BE",
    "sg:address":"Turnhoutsebaan 278a",
    "sg:city":"Schilde",
    "sg:classifiers":[
        {
            "category":"Health Services",
            "subcategory":"Nursing And Care Facility",
            "type":"Services"
        }
    ],
    "sg:phone":"+32 3 384 39 23",
    "sg:postcode":"2970",
    "sg:province":"Antwerpen",
    "sg:tags":[
        "safe"
    ],
    "wof:name":"Safe House Peeters",
    "wof:placetype":"venue"
},
  "geometry": {"coordinates":[4.5818901062,51.2400970459],"type":"Point"}
}