{
  "type": "Feature",
  "properties": {
    "addr:full":"Het Hazepad 12 Aarschot (langdorp) Vlaams-Brabant 3201",
    "addr:housenumber":"12",
    "addr:postcode":"3201",
    "addr:street":"Het Hazepad",
    "iso:country":"BE",
    "sg:address":"Het Hazepad 12",
    "sg:city":"Aarschot (langdorp)",
    "sg:classifiers":[
        {
            "category":"Building & Trades",
            "subcategory":"Landscaping Services",
            "type":"Services"
        }
    ],
    "sg:phone":"+32 16 57 39 66",
    "sg:postcode":"3201",
    "sg:province":"Vlaams-Brabant",
    "sg:tags":[
        "gardening",
        "garden",
        "maintenance"
    ],
    "wof:name":"Vercalsteren P",
    "wof:placetype":"venue"
},
  "geometry": {"coordinates":[4.8670291901,51.0037498474],"type":"Point"}
}