{
  "type": "Feature",
  "properties": {
    "addr:full":"Roterijstraat 101 Waregem West-Vlaanderen 8790",
    "addr:housenumber":"101",
    "addr:postcode":"8790",
    "addr:street":"Roterijstraat",
    "iso:country":"BE",
    "sg:address":"Roterijstraat 101",
    "sg:city":"Waregem",
    "sg:classifiers":[
        {
            "category":"Airport",
            "subcategory":"International",
            "type":"Transportation"
        }
    ],
    "sg:phone":"+32 56 61 35 08",
    "sg:postcode":"8790",
    "sg:province":"West-Vlaanderen",
    "sg:tags":[
        "-",
        "transport"
    ],
    "wof:name":"Waelkens M",
    "wof:placetype":"venue"
},
  "geometry": {"coordinates":[3.406555891,50.8931045532],"type":"Point"}
}