{
  "type": "Feature",
  "properties": {
    "iso:country":"BE",
    "sg:address":"Chauss\u00e9e D'audenarde 83",
    "sg:city":"Tournai",
    "sg:classifiers":[
        {
            "category":"Building & Trades",
            "subcategory":"Landscaping Services",
            "type":"Services"
        }
    ],
    "sg:phone":"+32 496 65 79 82",
    "sg:postcode":"7500",
    "sg:province":"Hainaut",
    "sg:tags":[
        "gardening",
        "garden",
        "maintenance"
    ],
    "wof:name":"Mathieu T",
    "wof:placetype":"venue"
},
  "geometry": {"coordinates":[3.3864629269,50.6184005737],"type":"Point"}
}