{
  "type": "Feature",
  "properties": {
    "iso:country":"BE",
    "sg:address":"Molenstraat 100",
    "sg:city":"Temse",
    "sg:orig_category":"Rundveehouders Varkenskwekers",
    "sg:phone":"+32 3 776 80 14",
    "sg:postcode":"9140",
    "sg:province":"Oost-Vlaanderen",
    "wof:name":"Joseph Beck",
    "wof:placetype":"venue"
},
  "geometry": {"coordinates":[4.1726827621,51.1352081299],"type":"Point"}
}