{
  "type": "Feature",
  "properties": {
    "addr:full":"Slingerweg 62 Genk Limburg 3600",
    "addr:housenumber":"62",
    "addr:postcode":"3600",
    "addr:street":"Slingerweg",
    "iso:country":"BE",
    "sg:address":"Slingerweg 62",
    "sg:city":"Genk",
    "sg:classifiers":[
        {
            "category":"Manufacturing",
            "subcategory":"Wood Products",
            "type":"Manufacturing & Wholesale Goods"
        }
    ],
    "sg:phone":"+32 89 49 20 40",
    "sg:postcode":"3600",
    "sg:province":"Limburg",
    "sg:tags":[
        "derived",
        "timber",
        "component",
        "furniture"
    ],
    "wof:name":"Fikszo Belgium B.v.b.a.",
    "wof:placetype":"venue"
},
  "geometry": {"coordinates":[5.4915599823,50.9230308533],"type":"Point"}
}