{
  "type": "Feature",
  "properties": {
    "iso:country":"BE",
    "sg:address":"Slypsstraat 4",
    "sg:city":"Ledegem",
    "sg:orig_category":"Non-Classified Establishments",
    "sg:phone":"+32 56 50 01 91",
    "sg:postcode":"8880",
    "sg:province":"West-Vlaanderen",
    "wof:name":"Juventa Nv",
    "wof:placetype":"venue"
},
  "geometry": {"coordinates":[3.1060550213,50.8648719788],"type":"Point"}
}