{
  "type": "Feature",
  "properties": {
    "iso:country":"BE",
    "sg:address":"Steenweg Op Heindonk 103",
    "sg:city":"Mechelen (heffen)",
    "sg:classifiers":[
        {
            "category":"Social Services",
            "subcategory":"Child Care",
            "type":"Services"
        }
    ],
    "sg:phone":"+32 3 886 33 89",
    "sg:postcode":"2801",
    "sg:province":"Antwerpen",
    "sg:tags":[
        "home"
    ],
    "wof:name":"Hefboom (de)",
    "wof:placetype":"venue"
},
  "geometry": {"coordinates":[4.4223451614,51.0472068787],"type":"Point"}
}