{
  "type": "Feature",
  "properties": {
    "addr:full":"Jozef Van Gorpstraat 5 Ravels Antwerpen 2380",
    "addr:housenumber":"5",
    "addr:postcode":"2380",
    "addr:street":"Jozef Van Gorpstraat",
    "iso:country":"BE",
    "sg:address":"Jozef Van Gorpstraat 5",
    "sg:city":"Ravels",
    "sg:orig_category":"Banken and kredietinstellingen",
    "sg:phone":"+32 14 65 77 33",
    "sg:postcode":"2380",
    "sg:province":"Antwerpen",
    "wof:name":"Ippa",
    "wof:placetype":"venue"
},
  "geometry": {"coordinates":[4.9919300079,51.3723907471],"type":"Point"}
}