{
  "type": "Feature",
  "properties": {
    "addr:full":"Galerie De La Toison D\u00b4or 409 Bruxelles-ixelles Bruxelles-Capitale 1050",
    "addr:housenumber":"409",
    "addr:postcode":"1050",
    "addr:street":"Galerie De La Toison D\u00b4Or",
    "iso:country":"BE",
    "sg:address":"Galerie De La Toison D\u00b4or 409",
    "sg:city":"Bruxelles-ixelles",
    "sg:classifiers":[
        {
            "category":"Shopping",
            "subcategory":"Bicycles & Sporting Goods",
            "type":"Retail Goods"
        }
    ],
    "sg:phone":"+32 2 514 53 88",
    "sg:postcode":"1050",
    "sg:province":"Bruxelles-Capitale",
    "sg:tags":[
        "article",
        "de",
        "sport",
        "camping"
    ],
    "wof:name":"Trans Canada",
    "wof:placetype":"venue"
},
  "geometry": {"coordinates":[4.3667850494,50.8326339722],"type":"Point"}
}