{
  "type": "Feature",
  "properties": {
    "addr:full":"Biesmuiterlaan 2 Overijse Vlaams-Brabant 3090",
    "addr:housenumber":"2",
    "addr:postcode":"3090",
    "addr:street":"Biesmuiterlaan",
    "iso:country":"BE",
    "sg:address":"Biesmuiterlaan 2",
    "sg:city":"Overijse",
    "sg:classifiers":[
        {
            "category":"Building & Trades",
            "subcategory":"Construction",
            "type":"Services"
        }
    ],
    "sg:phone":"+32 2 687 86 95",
    "sg:postcode":"3090",
    "sg:province":"Vlaams-Brabant",
    "sg:tags":[
        "installation",
        "-",
        "central",
        "heating"
    ],
    "wof:name":"Demol Raymond Bvba",
    "wof:placetype":"venue"
},
  "geometry": {"coordinates":[4.5348558426,50.7807693481],"type":"Point"}
}