{
  "type": "Feature",
  "properties": {
    "addr:full":"Rue De Malmedy 24 St. Vith Li\u00e8ge 4780",
    "addr:housenumber":"24",
    "addr:postcode":"4780",
    "addr:street":"Rue De Malmedy",
    "iso:country":"BE",
    "sg:address":"Rue De Malmedy 24",
    "sg:city":"St. Vith",
    "sg:classifiers":[
        {
            "category":"Banks & Credit Unions",
            "subcategory":"Bank",
            "type":"Services"
        }
    ],
    "sg:phone":"+32 80 22 82 75",
    "sg:postcode":"4780",
    "sg:province":"Li\u00e8ge",
    "wof:name":"Banque Nagelmackers",
    "wof:placetype":"venue"
},
  "geometry": {"coordinates":[6.1233048439,50.2837371826],"type":"Point"}
}