{
  "type": "Feature",
  "properties": {
    "addr:full":"Begonialaan 64 Affligem (teralfene) Vlaams-Brabant 1790",
    "addr:housenumber":"64",
    "addr:postcode":"1790",
    "addr:street":"Begonialaan",
    "iso:country":"BE",
    "sg:address":"Begonialaan 64",
    "sg:city":"Affligem (teralfene)",
    "sg:classifiers":[
        {
            "category":"Freight",
            "type":"Transportation"
        }
    ],
    "sg:phone":"+32 53 66 89 64",
    "sg:postcode":"1790",
    "sg:province":"Vlaams-Brabant",
    "sg:tags":[
        "-",
        "transport"
    ],
    "wof:name":"Vbe Trans",
    "wof:placetype":"venue"
},
  "geometry": {"coordinates":[4.0951099396,50.8909416199],"type":"Point"}
}