{
  "type": "Feature",
  "properties": {
    "addr:full":"Rue Du Calvaire 2 Pont-\u00e0-celles (obaix) Hainaut 6230",
    "addr:housenumber":"2",
    "addr:postcode":"6230",
    "addr:street":"Rue Du Calvaire;Obaix Hainaut",
    "iso:country":"BE",
    "sg:address":"Rue Du Calvaire 2",
    "sg:city":"Pont-\u00e0-celles (obaix)",
    "sg:classifiers":[
        {
            "category":"Home & Garden",
            "subcategory":"Building Materials",
            "type":"Retail Goods"
        }
    ],
    "sg:phone":"+32 476 72 54 17",
    "sg:postcode":"6230",
    "sg:province":"Hainaut",
    "sg:tags":[
        "house"
    ],
    "wof:name":"Atelier Lacroix",
    "wof:placetype":"venue"
},
  "geometry": {"coordinates":[4.3622570038,50.5265083313],"type":"Point"}
}