{
  "type": "Feature",
  "properties": {
    "iso:country":"BE",
    "sg:address":"Hunckevlietstraat 1",
    "sg:city":"Middelkerke",
    "sg:orig_category":"Produits c\u00e9r\u00e9aliers Fab",
    "sg:phone":"+32 51 55 52 00",
    "sg:postcode":"8433",
    "sg:province":"West-Vlaanderen",
    "wof:name":"Simoens",
    "wof:placetype":"venue"
},
  "geometry": {"coordinates":[2.8506441116,51.1164855957],"type":"Point"}
}