{
  "type": "Feature",
  "properties": {
    "iso:country":"BE",
    "sg:address":"Tomberg 257",
    "sg:city":"Bruxelles (woluwe-saint-lambert)",
    "sg:classifiers":[
        {
            "category":"Retail",
            "subcategory":"Laundry & Dry Cleaning",
            "type":"Services"
        }
    ],
    "sg:phone":"+32 2 770 41 00",
    "sg:postcode":"1200",
    "sg:province":"Bruxelles-Capitale",
    "sg:tags":[
        "dyer",
        "cleaner"
    ],
    "wof:name":"Triangle Cleaners Sprl",
    "wof:placetype":"venue"
},
  "geometry": {"coordinates":[4.4207248688,50.8441543579],"type":"Point"}
}