{
  "type": "Feature",
  "properties": {
    "addr:full":"Casinostraat 7 Sint-truiden Limburg 3800",
    "addr:housenumber":"7",
    "addr:postcode":"3800",
    "addr:street":"Casinostraat",
    "iso:country":"BE",
    "sg:address":"Casinostraat 7",
    "sg:city":"Sint-truiden",
    "sg:classifiers":[
        {
            "category":"Cinema",
            "subcategory":"Movie Rental",
            "type":"Entertainment"
        }
    ],
    "sg:phone":"+32 11 68 86 09",
    "sg:postcode":"3800",
    "sg:province":"Limburg",
    "sg:tags":[
        "de",
        "cassette",
        "location",
        "vid\u00e9o",
        "audio"
    ],
    "wof:name":"Circle",
    "wof:placetype":"venue"
},
  "geometry": {"coordinates":[5.1899847984,50.8125801086],"type":"Point"}
}