{
  "type": "Feature",
  "properties": {
    "addr:full":"Dorp 18ba Sint-martens-latem Oost-Vlaanderen 9830",
    "addr:housenumber":"18ba",
    "addr:postcode":"9830",
    "addr:street":"Dorp",
    "iso:country":"BE",
    "sg:address":"Dorp 18ba",
    "sg:city":"Sint-martens-latem",
    "sg:orig_category":"Zalen voor culturele evenementen",
    "sg:phone":"+32 9 282 01 10",
    "sg:postcode":"9830",
    "sg:province":"Oost-Vlaanderen",
    "wof:name":"Galerij Grusenmeyer",
    "wof:placetype":"venue"
},
  "geometry": {"coordinates":[3.6403269768,51.0201034546],"type":"Point"}
}