{
  "type": "Feature",
  "properties": {
    "iso:country":"BE",
    "sg:address":"Vennestraat 25",
    "sg:city":"Wetteren",
    "sg:orig_category":"Rundveehouders",
    "sg:phone":"+32 9 369 32 43",
    "sg:postcode":"9230",
    "sg:province":"Oost-Vlaanderen",
    "wof:name":"Marcel Verhoeve",
    "wof:placetype":"venue"
},
  "geometry": {"coordinates":[3.8722860813,51.0098800659],"type":"Point"}
}