{
  "type": "Feature",
  "properties": {
    "addr:full":"Kwaplasstraat 5 Torhout West-Vlaanderen 8820",
    "addr:housenumber":"5",
    "addr:postcode":"8820",
    "addr:street":"Kwaplasstraat",
    "iso:country":"BE",
    "sg:address":"Kwaplasstraat 5",
    "sg:city":"Torhout",
    "sg:orig_category":"Installation \u00e9lectrique r\u00e9sidentielle",
    "sg:phone":"+32 50 21 15 28",
    "sg:postcode":"8820",
    "sg:province":"West-Vlaanderen",
    "wof:name":"Filip Sap",
    "wof:placetype":"venue"
},
  "geometry": {"coordinates":[3.1167280674,51.0562744141],"type":"Point"}
}