{
  "type": "Feature",
  "properties": {
    "iso:country":"BE",
    "sg:address":"Mgr. Simenonlaan 38",
    "sg:city":"Riemst",
    "sg:orig_category":"Installation \u00e9lectrique r\u00e9sidentielle",
    "sg:phone":"+32 12 45 56 59",
    "sg:postcode":"3770",
    "sg:province":"Limburg",
    "wof:name":"Electro Rouflart",
    "wof:placetype":"venue"
},
  "geometry": {"coordinates":[5.5969901085,50.8109016418],"type":"Point"}
}