{
  "type": "Feature",
  "properties": {
    "addr:full":"Bisdom 6 Overijse Vlaams-Brabant 3090",
    "addr:housenumber":"6",
    "addr:postcode":"3090",
    "addr:street":"Bisdom",
    "iso:country":"BE",
    "sg:address":"Bisdom 6",
    "sg:city":"Overijse",
    "sg:classifiers":[
        {
            "category":"Building & Trades",
            "subcategory":"Locksmith",
            "type":"Services"
        }
    ],
    "sg:phone":"+32 2 687 32 83",
    "sg:postcode":"3090",
    "sg:province":"Vlaams-Brabant",
    "sg:tags":[
        "lock",
        "key"
    ],
    "wof:name":"Vandevijver",
    "wof:placetype":"venue"
},
  "geometry": {"coordinates":[4.5511231422,50.7725830078],"type":"Point"}
}