{
  "type": "Feature",
  "properties": {
    "addr:full":"Bruggestraat 290 Ingelmunster West-Vlaanderen 8770",
    "addr:housenumber":"290",
    "addr:postcode":"8770",
    "addr:street":"Bruggestraat",
    "iso:country":"BE",
    "sg:address":"Bruggestraat 290",
    "sg:city":"Ingelmunster",
    "sg:orig_category":"Elektrische installaties voor woningen IJzerwaren, bouw- and verfmaterialen Loodgieterij, verwarming",
    "sg:phone":"+32 51 48 57 32",
    "sg:postcode":"8770",
    "sg:province":"West-Vlaanderen",
    "wof:name":"Divepco",
    "wof:placetype":"venue"
},
  "geometry": {"coordinates":[3.2487299442,50.9421348572],"type":"Point"}
}