{
  "type": "Feature",
  "properties": {
    "addr:full":"Deinsesteenweg 29a-29 Tielt West-Vlaanderen 8700",
    "addr:housenumber":"29a-29",
    "addr:postcode":"8700",
    "addr:street":"Deinsesteenweg",
    "iso:country":"BE",
    "sg:address":"Deinsesteenweg 29a-29",
    "sg:city":"Tielt",
    "sg:classifiers":[
        {
            "category":"Building & Trades",
            "subcategory":"Equipment Rental",
            "type":"Services"
        }
    ],
    "sg:phone":"+32 89 77 22 00",
    "sg:postcode":"8700",
    "sg:province":"West-Vlaanderen",
    "sg:tags":[
        "use",
        "apparatus",
        "tool",
        "-",
        "professional",
        "machines"
    ],
    "wof:name":"Meyer-hwk Bvba",
    "wof:placetype":"venue"
},
  "geometry": {"coordinates":[4.9512782097,52.3041000366],"type":"Point"}
}