{
  "type": "Feature",
  "properties": {
    "addr:full":"Nachtegaallaan 25 Grimbergen Vlaams-Brabant 1851",
    "addr:housenumber":"25",
    "addr:postcode":"1851",
    "addr:street":"Nachtegaallaan",
    "iso:country":"BE",
    "sg:address":"Nachtegaallaan 25",
    "sg:city":"Grimbergen",
    "sg:classifiers":[
        {
            "category":"Cafe",
            "type":"Food & Drink"
        }
    ],
    "sg:phone":"+32 2 269 03 50",
    "sg:postcode":"1851",
    "sg:province":"Vlaams-Brabant",
    "sg:tags":[
        "caf\u00e9s"
    ],
    "wof:name":"Humbeekse Lijnvissers",
    "wof:placetype":"venue"
},
  "geometry": {"coordinates":[4.3869600296,50.9707984924],"type":"Point"}
}