{
  "type": "Feature",
  "properties": {
    "iso:country":"BE",
    "sg:address":"Vlamingstraat 10",
    "sg:city":"Brugge",
    "sg:classifiers":[
        {
            "category":"Shopping",
            "subcategory":"Clothing, Apparel, & Fashions",
            "type":"Retail Goods"
        }
    ],
    "sg:phone":"+32 50 34 13 47",
    "sg:postcode":"8000",
    "sg:province":"West-Vlaanderen",
    "sg:tags":[
        "clothing",
        "-",
        "gentleman"
    ],
    "wof:name":"L\u00e9onardo",
    "wof:placetype":"venue"
},
  "geometry": {"coordinates":[3.2213408947,51.2154388428],"type":"Point"}
}