{
  "type": "Feature",
  "properties": {
    "addr:full":"Rue Victor Corne 64 Mouscron Hainaut 7700",
    "addr:housenumber":"64",
    "addr:postcode":"7700",
    "addr:street":"Rue Victor Corne",
    "iso:country":"BE",
    "sg:address":"Rue Victor Corne 64",
    "sg:city":"Mouscron",
    "sg:classifiers":[
        {
            "category":"Shopping",
            "subcategory":"Clothing, Apparel, & Fashions",
            "type":"Retail Goods"
        }
    ],
    "sg:phone":"+32 56 84 03 03",
    "sg:postcode":"7700",
    "sg:province":"Hainaut",
    "sg:tags":[
        "textile",
        "clothing",
        "clothes"
    ],
    "wof:name":"Cyrillus Benelux Sa",
    "wof:placetype":"venue"
},
  "geometry": {"coordinates":[3.2178959846,50.7482528687],"type":"Point"}
}