{
  "type": "Feature",
  "properties": {
    "iso:country":"BE",
    "sg:address":"Vosstraat 9b",
    "sg:city":"Wervik",
    "sg:orig_category":"Salles de conf\u00e9rences and de r\u00e9ceptions",
    "sg:phone":"+32 56 31 40 77",
    "sg:postcode":"8940",
    "sg:province":"West-Vlaanderen",
    "wof:name":"Feestzaal De Fonteyne",
    "wof:placetype":"venue"
},
  "geometry": {"coordinates":[3.0438868999,50.8109283447],"type":"Point"}
}