{
  "type": "Feature",
  "properties": {
    "addr:full":"Herbiester 4 Jalhay Li\u00e8ge 4845",
    "addr:housenumber":"4",
    "addr:postcode":"4845",
    "addr:street":"Herbiester",
    "iso:country":"BE",
    "sg:address":"Herbiester 4",
    "sg:city":"Jalhay",
    "sg:classifiers":[
        {
            "category":"Building & Trades",
            "subcategory":"Pest Control",
            "type":"Services"
        }
    ],
    "sg:phone":"+32 87 64 74 38",
    "sg:postcode":"4845",
    "sg:province":"Li\u00e8ge",
    "sg:tags":[
        "painting",
        "contractor"
    ],
    "wof:name":"Bourdon J-m Et Fils",
    "wof:placetype":"venue"
},
  "geometry": {"coordinates":[5.9728660583,50.557849884],"type":"Point"}
}