{
  "type": "Feature",
  "properties": {
    "addr:full":"Oosthoek 12 Assenede (oosteeklo) Oost-Vlaanderen 9968",
    "addr:housenumber":"12",
    "addr:postcode":"9968",
    "addr:street":"Oosthoek",
    "iso:country":"BE",
    "sg:address":"Oosthoek 12",
    "sg:city":"Assenede (oosteeklo)",
    "sg:classifiers":[
        {
            "category":"Personal",
            "subcategory":"Beauty Salon",
            "type":"Services"
        }
    ],
    "sg:phone":"+32 9 373 88 10",
    "sg:postcode":"9968",
    "sg:province":"Oost-Vlaanderen",
    "sg:tags":[
        "lady",
        "-",
        "hairdressing"
    ],
    "wof:name":"Annick",
    "wof:placetype":"venue"
},
  "geometry": {"coordinates":[3.6972138882,51.1959114075],"type":"Point"}
}