{
  "type": "Feature",
  "properties": {
    "iso:country":"BE",
    "sg:address":"Winterslagstraat 5",
    "sg:city":"Genk",
    "sg:orig_category":"Cr\u00e9dits divers",
    "sg:postcode":"3600",
    "sg:province":"Limburg",
    "wof:name":"Bancontact-mister Cash",
    "wof:placetype":"venue"
},
  "geometry": {"coordinates":[5.4983139038,50.963848114],"type":"Point"}
}