{
  "type": "Feature",
  "properties": {
    "addr:full":"Kuurstraat 15 Genk Limburg 3600",
    "addr:housenumber":"15",
    "addr:postcode":"3600",
    "addr:street":"Kuurstraat",
    "iso:country":"BE",
    "sg:address":"Kuurstraat 15",
    "sg:city":"Genk",
    "sg:orig_category":"Artsen and specialisten",
    "sg:phone":"+32 11 22 36 06",
    "sg:postcode":"3600",
    "sg:province":"Limburg",
    "wof:name":"M. Bouts",
    "wof:placetype":"venue"
},
  "geometry": {"coordinates":[5.4211568832,50.9539337158],"type":"Point"}
}