{
  "type": "Feature",
  "properties": {
    "addr:full":"Vindictivelaan 21 Oostende West-Vlaanderen 8400",
    "addr:housenumber":"21",
    "addr:postcode":"8400",
    "addr:street":"Vindictivelaan",
    "iso:country":"BE",
    "sg:address":"Vindictivelaan 21",
    "sg:city":"Oostende",
    "sg:classifiers":[
        {
            "category":"Fast Food",
            "type":"Food & Drink"
        }
    ],
    "sg:phone":"+32 59 51 27 80",
    "sg:postcode":"8400",
    "sg:province":"West-Vlaanderen",
    "sg:tags":[
        "\u00c0",
        "restaurants",
        "emporter",
        "restaurant"
    ],
    "wof:name":"China Crystal Palace",
    "wof:placetype":"venue"
},
  "geometry": {"coordinates":[2.9223411083,51.2283859253],"type":"Point"}
}