{
  "type": "Feature",
  "properties": {
    "addr:full":"Legeweg 116 Oostkamp West-Vlaanderen 8020",
    "addr:housenumber":"116",
    "addr:postcode":"8020",
    "addr:street":"Legeweg",
    "iso:country":"BE",
    "sg:address":"Legeweg 116",
    "sg:city":"Oostkamp",
    "sg:orig_category":"Rundveehouders Varkenskwekers",
    "sg:phone":"+32 50 82 25 08",
    "sg:postcode":"8020",
    "sg:province":"West-Vlaanderen",
    "wof:name":"Erik Keereman",
    "wof:placetype":"venue"
},
  "geometry": {"coordinates":[3.2527699471,51.1708717346],"type":"Point"}
}