{
  "type": "Feature",
  "properties": {
    "addr:full":"Damputstraat 67 Hamme Oost-Vlaanderen 9220",
    "addr:housenumber":"67",
    "addr:postcode":"9220",
    "addr:street":"Damputstraat",
    "iso:country":"BE",
    "sg:address":"Damputstraat 67",
    "sg:city":"Hamme",
    "sg:orig_category":"Brood, gebak and snoepgoed",
    "sg:phone":"+32 52 47 71 97",
    "sg:postcode":"9220",
    "sg:province":"Oost-Vlaanderen",
    "wof:name":"Bakkerij Mariman",
    "wof:placetype":"venue"
},
  "geometry": {"coordinates":[4.1419701576,51.0935974121],"type":"Point"}
}