{
  "type": "Feature",
  "properties": {
    "addr:full":"Centrumlaan 11 Ninove Oost-Vlaanderen 9400",
    "addr:housenumber":"11",
    "addr:postcode":"9400",
    "addr:street":"Centrumlaan",
    "iso:country":"BE",
    "sg:address":"Centrumlaan 11",
    "sg:city":"Ninove",
    "sg:orig_category":"Randstad",
    "sg:phone":"+32 54 31 78 30",
    "sg:postcode":"9400",
    "sg:province":"Oost-Vlaanderen",
    "wof:name":"Randstad",
    "wof:placetype":"venue"
},
  "geometry": {"coordinates":[4.0216550827,50.8347473145],"type":"Point"}
}