{
  "type": "Feature",
  "properties": {
    "iso:country":"BE",
    "sg:address":"Scheldestraat 38",
    "sg:city":"Zele",
    "sg:orig_category":"Installation de menuiserie en bois and plastique",
    "sg:phone":"+32 52 44 56 17",
    "sg:postcode":"9240",
    "sg:province":"Oost-Vlaanderen",
    "wof:name":"Michiels Etienne",
    "wof:placetype":"venue"
},
  "geometry": {"coordinates":[4.0379948616,51.0523109436],"type":"Point"}
}