{
  "type": "Feature",
  "properties": {
    "iso:country":"BE",
    "sg:address":"Blankenbergse Steenweg 25",
    "sg:city":"Brugge",
    "sg:orig_category":"Herstelling and restauratie van meubelen Textiel Verlichting and huishoudartikelen",
    "sg:phone":"+32 50 31 85 25",
    "sg:postcode":"8000",
    "sg:province":"West-Vlaanderen",
    "wof:name":"Fa. Wijdo",
    "wof:placetype":"venue"
},
  "geometry": {"coordinates":[3.2234170437,51.2077293396],"type":"Point"}
}