{
  "type": "Feature",
  "properties": {
    "iso:country":"BE",
    "sg:address":"Driekoningenstraat 120",
    "sg:city":"Antwerpen",
    "sg:orig_category":"Kleding Lingerie and ondergoed",
    "sg:phone":"+32 3 281 10 91",
    "sg:postcode":"2600",
    "sg:province":"Antwerpen",
    "wof:name":"Huis L & G",
    "wof:placetype":"venue"
},
  "geometry": {"coordinates":[4.4174151421,51.1974411011],"type":"Point"}
}