{
  "type": "Feature",
  "properties": {
    "iso:country":"BE",
    "sg:address":"Kaphaanlei 18",
    "sg:city":"Mortsel",
    "sg:classifiers":[
        {
            "category":"Education",
            "subcategory":"Dance Studio",
            "type":"Public Place"
        }
    ],
    "sg:phone":"+32 3 454 52 55",
    "sg:postcode":"2640",
    "sg:province":"Antwerpen",
    "sg:tags":[
        "school",
        "dancing"
    ],
    "wof:name":"Dansschool An Slootmaekers Vzw",
    "wof:placetype":"venue"
},
  "geometry": {"coordinates":[4.473069191,51.1676216125],"type":"Point"}
}