{
  "type": "Feature",
  "properties": {
    "iso:country":"BE",
    "sg:address":"Elzenlaan 22",
    "sg:city":"Diepenbeek",
    "sg:classifiers":[
        {
            "category":"Professional",
            "type":"Services"
        }
    ],
    "sg:phone":"+32 11 32 26 79",
    "sg:postcode":"3590",
    "sg:province":"Limburg",
    "sg:tags":[
        "entertainer"
    ],
    "wof:name":"De Kriebelkuil Willy Jorissen Vzw",
    "wof:placetype":"venue"
},
  "geometry": {"coordinates":[5.4329628944,50.9341392517],"type":"Point"}
}