{
  "type": "Feature",
  "properties": {
    "addr:full":"Molenstraat 41 Merelbeke (schelderode) Oost-Vlaanderen 9820",
    "addr:housenumber":"41",
    "addr:postcode":"9820",
    "addr:street":"Molenstraat",
    "iso:country":"BE",
    "sg:address":"Molenstraat 41",
    "sg:city":"Merelbeke (schelderode)",
    "sg:classifiers":[
        {
            "category":"Building & Trades",
            "subcategory":"Plumbing",
            "type":"Services"
        }
    ],
    "sg:phone":"+32 9 362 95 89",
    "sg:postcode":"9820",
    "sg:province":"Oost-Vlaanderen",
    "sg:tags":[
        "repair",
        "mainten",
        "-",
        "central",
        "heating"
    ],
    "wof:name":"De Torck P",
    "wof:placetype":"venue"
},
  "geometry": {"coordinates":[3.7302680016,50.9673461914],"type":"Point"}
}