{
  "type": "Feature",
  "properties": {
    "iso:country":"BE",
    "sg:address":"Rue De La Chauss\u00e9e 45",
    "sg:city":"Mons",
    "sg:classifiers":[
        {
            "category":"Shopping",
            "subcategory":"Clothing, Apparel, & Fashions",
            "type":"Retail Goods"
        }
    ],
    "sg:phone":"+32 65 35 28 32",
    "sg:postcode":"7000",
    "sg:province":"Hainaut",
    "sg:tags":[
        "boutique"
    ],
    "wof:name":"Paris Style Sa",
    "wof:placetype":"venue"
},
  "geometry": {"coordinates":[3.9509301186,50.4526977539],"type":"Point"}
}