{
  "type": "Feature",
  "properties": {
    "addr:full":"Goswin De Stassartstraat 56 Mechelen Antwerpen 2800",
    "addr:housenumber":"56",
    "addr:postcode":"2800",
    "addr:street":"Goswin De Stassartstraat",
    "iso:country":"BE",
    "sg:address":"Goswin De Stassartstraat 56",
    "sg:city":"Mechelen",
    "sg:orig_category":"D\u00e9taillants en pi\u00e8ces and accessoires de voitures. Mat\u00e9riel de T\u00e9l\u00e9communication",
    "sg:phone":"+32 15 21 20 23",
    "sg:postcode":"2800",
    "sg:province":"Antwerpen",
    "wof:name":"Acrijo",
    "wof:placetype":"venue"
},
  "geometry": {"coordinates":[4.4800081253,51.0324554443],"type":"Point"}
}