{
  "type": "Feature",
  "properties": {
    "iso:country":"BE",
    "sg:address":"Milostraat 14",
    "sg:city":"Mol",
    "sg:classifiers":[
        {
            "category":"Professional",
            "subcategory":"Testing Lab",
            "type":"Services"
        }
    ],
    "sg:phone":"+32 14 31 35 04",
    "sg:postcode":"2400",
    "sg:province":"Antwerpen",
    "sg:tags":[
        "chemist"
    ],
    "wof:name":"Smolders G",
    "wof:placetype":"venue"
},
  "geometry": {"coordinates":[5.0757369995,51.189666748],"type":"Point"}
}