{
  "type": "Feature",
  "properties": {
    "addr:full":"Pont Du Christ 14 Wavre Brabant Wallon 1300",
    "addr:housenumber":"14;1300",
    "addr:street":"Pont Du Christ",
    "iso:country":"BE",
    "sg:address":"Pont Du Christ 14",
    "sg:city":"Wavre",
    "sg:classifiers":[
        {
            "category":"Shopping",
            "subcategory":"Music",
            "type":"Retail Goods"
        }
    ],
    "sg:phone":"+32 10 22 86 88",
    "sg:postcode":"1300",
    "sg:province":"Brabant Wallon",
    "sg:tags":[
        "-",
        "cd's",
        "recorded",
        "cassette"
    ],
    "wof:name":"Melodisc",
    "wof:placetype":"venue"
},
  "geometry": {"coordinates":[4.6102151871,50.7151184082],"type":"Point"}
}