{
  "type": "Feature",
  "properties": {
    "addr:full":"Rue Grande 82a Saint-ghislain Hainaut 7330",
    "addr:housenumber":"82a",
    "addr:postcode":"7330",
    "addr:street":"Rue Grande;Hainaut",
    "iso:country":"BE",
    "sg:address":"Rue Grande 82a",
    "sg:city":"Saint-ghislain",
    "sg:classifiers":[
        {
            "category":"Shopping",
            "subcategory":"Clothing, Apparel, & Fashions",
            "type":"Retail Goods"
        }
    ],
    "sg:phone":"+32 65 52 16 21",
    "sg:postcode":"7330",
    "sg:province":"Hainaut",
    "sg:tags":[
        "lady",
        "clothing",
        "-"
    ],
    "wof:name":"Attitude",
    "wof:placetype":"venue"
},
  "geometry": {"coordinates":[3.8204259872,50.4445800781],"type":"Point"}
}