{
  "type": "Feature",
  "properties": {
    "addr:full":"Veldstraat 14 Pittem West-Vlaanderen 8740",
    "addr:housenumber":"14",
    "addr:postcode":"8740",
    "addr:street":"Veldstraat",
    "iso:country":"BE",
    "sg:address":"Veldstraat 14",
    "sg:city":"Pittem",
    "sg:orig_category":"Groententeelt",
    "sg:phone":"+32 51 46 63 22",
    "sg:postcode":"8740",
    "sg:province":"West-Vlaanderen",
    "wof:name":"Dirk Mingneau",
    "wof:placetype":"venue"
},
  "geometry": {"coordinates":[3.2574400902,50.9804649353],"type":"Point"}
}