{
  "type": "Feature",
  "properties": {
    "iso:country":"BE",
    "sg:address":"Avenue D'auderghem 137",
    "sg:city":"Etterbeek",
    "sg:orig_category":"Agences d'exp\u00e9dition",
    "sg:phone":"+32 2 640 50 12",
    "sg:postcode":"1040",
    "sg:province":"Bruxelles-Capitale",
    "wof:name":"General Steel International",
    "wof:placetype":"venue"
},
  "geometry": {"coordinates":[4.3871941566,50.8358154297],"type":"Point"}
}