{
  "type": "Feature",
  "properties": {
    "addr:full":"Beverlaai 4 Kortrijk West-Vlaanderen 8500",
    "addr:housenumber":"4",
    "addr:postcode":"8500",
    "addr:street":"Beverlaai",
    "iso:country":"BE",
    "sg:address":"Beverlaai 4",
    "sg:city":"Kortrijk",
    "sg:orig_category":"Advocaten and juridische adviseurs",
    "sg:phone":"+32 56 22 65 46",
    "sg:postcode":"8500",
    "sg:province":"West-Vlaanderen",
    "wof:name":"Kris Gheysen",
    "wof:placetype":"venue"
},
  "geometry": {"coordinates":[3.2663350105,50.8224525452],"type":"Point"}
}