{
  "type": "Feature",
  "properties": {
    "iso:country":"BE",
    "sg:address":"Rue Montgom\u00e9ry 17",
    "sg:city":"Enghien",
    "sg:classifiers":[
        {
            "category":"Professional",
            "subcategory":"Art Services",
            "type":"Services"
        }
    ],
    "sg:phone":"+32 2 395 32 55",
    "sg:postcode":"7850",
    "sg:province":"Hainaut",
    "sg:tags":[
        "photographer"
    ],
    "wof:name":"Berger (studio)",
    "wof:placetype":"venue"
},
  "geometry": {"coordinates":[4.0377621651,50.6932601929],"type":"Point"}
}