{
  "type": "Feature",
  "properties": {
    "addr:full":"Place Buisset Charleroi Hainaut 6000",
    "addr:postcode":"6000",
    "addr:street":"Place Buisset;Hainaut",
    "iso:country":"BE",
    "sg:address":"Place Buisset",
    "sg:city":"Charleroi",
    "sg:classifiers":[
        {
            "category":"Restaurant",
            "type":"Food & Drink"
        }
    ],
    "sg:phone":"+32 71 70 37 04",
    "sg:postcode":"6000",
    "sg:province":"Hainaut",
    "wof:name":"Aux Sans Fa\u00c7ons",
    "wof:placetype":"venue"
},
  "geometry": {"coordinates":[4.4389328957,50.4063682556],"type":"Point"}
}