{
  "type": "Feature",
  "properties": {
    "addr:full":"Rue De La Perche 44 Colfontaine Hainaut 7340",
    "addr:housenumber":"44",
    "addr:postcode":"7340",
    "addr:street":"Rue De La Perche",
    "iso:country":"BE",
    "sg:address":"Rue De La Perche 44",
    "sg:city":"Colfontaine",
    "sg:orig_category":"Boucheries",
    "sg:phone":"+32 65 67 92 50",
    "sg:postcode":"7340",
    "sg:province":"Hainaut",
    "wof:name":"Boucherie A.b.c.",
    "wof:placetype":"venue"
},
  "geometry": {"coordinates":[3.8589880466,50.4087677002],"type":"Point"}
}