{
  "type": "Feature",
  "properties": {
    "iso:country":"BE",
    "sg:address":"Rue De La Calamine 32",
    "sg:city":"Philippeville",
    "sg:classifiers":[
        {
            "category":"Education",
            "subcategory":"School",
            "type":"Public Place"
        }
    ],
    "sg:phone":"+32 71 66 75 37",
    "sg:postcode":"5600",
    "sg:province":"Namur",
    "sg:tags":[
        "secondary"
    ],
    "wof:name":"Ets D'ens Sec Sp\u00e9c De La Com. Fr.",
    "wof:placetype":"venue"
},
  "geometry": {"coordinates":[4.5607948303,50.178855896],"type":"Point"}
}