{
  "type": "Feature",
  "properties": {
    "iso:country":"BE",
    "sg:address":"Rue Docteur Colson 12",
    "sg:city":"Rebecq",
    "sg:classifiers":[
        {
            "category":"Fast Food",
            "type":"Food & Drink"
        }
    ],
    "sg:phone":"+32 67 67 08 68",
    "sg:postcode":"1430",
    "sg:province":"Brabant Wallon",
    "sg:tags":[
        "\u00c0",
        "restaurants",
        "emporter",
        "restaurant"
    ],
    "wof:name":"Oasis D\u00b4aremberg",
    "wof:placetype":"venue"
},
  "geometry": {"coordinates":[4.1322507858,50.6638679504],"type":"Point"}
}