{
  "type": "Feature",
  "properties": {
    "addr:full":"Basiliekstr 136 Halle Vlaams-Brabant 1500",
    "addr:housenumber":"136",
    "addr:postcode":"1500",
    "iso:country":"BE",
    "sg:address":"Basiliekstr 136",
    "sg:city":"Halle",
    "sg:classifiers":[
        {
            "category":"Travel",
            "subcategory":"Hotels & Motels",
            "type":"Entertainment"
        }
    ],
    "sg:phone":"+32 2 361 13 40",
    "sg:postcode":"1500",
    "sg:province":"Vlaams-Brabant",
    "sg:tags":[
        "hotels",
        "business",
        "restaurant"
    ],
    "wof:name":"Hotel Les Eleveurs",
    "wof:placetype":"venue"
},
  "geometry": {"coordinates":[4.23706007,50.7325744629],"type":"Point"}
}