{
  "type": "Feature",
  "properties": {
    "addr:full":"Kwadeveldenstraat 86 Antwerpen Antwerpen 2170",
    "addr:housenumber":"86",
    "addr:postcode":"2170",
    "addr:street":"Kwadeveldenstraat",
    "iso:country":"BE",
    "sg:address":"Kwadeveldenstraat 86",
    "sg:city":"Antwerpen",
    "sg:orig_category":"M\u00e9decins and sp\u00e9cialistes",
    "sg:phone":"+32 3 647 32 44",
    "sg:postcode":"2170",
    "sg:province":"Antwerpen",
    "wof:name":"Carl Vanderheyden",
    "wof:placetype":"venue"
},
  "geometry": {"coordinates":[4.4505147934,51.246723175],"type":"Point"}
}