{
  "type": "Feature",
  "properties": {
    "addr:full":"Kuhlmannkaai 1 Gent Oost-Vlaanderen 9042",
    "addr:housenumber":"1",
    "addr:postcode":"9042",
    "addr:street":"Kuhlmannkaai;Oost-Vlaanderen",
    "iso:country":"BE",
    "sg:address":"Kuhlmannkaai 1",
    "sg:city":"Gent",
    "sg:orig_category":"Produits chimiques Gr",
    "sg:phone":"+32 9 341 14 11",
    "sg:postcode":"9042",
    "sg:province":"Oost-Vlaanderen",
    "wof:name":"Arco Chemical Products Europe",
    "wof:placetype":"venue"
},
  "geometry": {"coordinates":[3.7974219322,51.1826171875],"type":"Point"}
}