{
  "type": "Feature",
  "properties": {
    "addr:full":"Sint -jan Nepomucenusstraat 20 Brussel/bruxelles Bruxelles-Capitale 1000",
    "addr:housenumber":"20",
    "addr:postcode":"1000",
    "addr:street":"Sint Jan Nepomucenusstraat;/",
    "iso:country":"BE",
    "sg:address":"Sint -jan Nepomucenusstraat 20",
    "sg:city":"Brussel/bruxelles",
    "sg:orig_category":"Reisbureaus",
    "sg:phone":"+32 2 217 76 75",
    "sg:postcode":"1000",
    "sg:province":"Bruxelles-Capitale",
    "wof:name":"Magellan Tours",
    "wof:placetype":"venue"
},
  "geometry": {"coordinates":[4.353869915,50.85572052],"type":"Point"}
}