{
  "type": "Feature",
  "properties": {
    "iso:country":"BE",
    "sg:address":"Meulebrouckstraat 2",
    "sg:city":"Moorslede",
    "sg:classifiers":[
        {
            "category":"Building & Trades",
            "subcategory":"Landscaping Services",
            "type":"Services"
        }
    ],
    "sg:phone":"+32 51 78 06 67",
    "sg:postcode":"8890",
    "sg:province":"West-Vlaanderen",
    "sg:tags":[
        "gardening",
        "garden",
        "maintenance"
    ],
    "wof:name":"Tuinen Clift",
    "wof:placetype":"venue"
},
  "geometry": {"coordinates":[3.0518870354,50.882068634],"type":"Point"}
}