{
  "type": "Feature",
  "properties": {
    "iso:country":"BE",
    "sg:address":"Rue Du Centre 21",
    "sg:city":"Modave",
    "sg:classifiers":[
        {
            "category":"Bars & Pubs",
            "type":"Food & Drink"
        }
    ],
    "sg:phone":"+32 85 41 15 84",
    "sg:postcode":"4577",
    "sg:province":"Li\u00e8ge",
    "wof:name":"Baratin (le)",
    "wof:placetype":"venue"
},
  "geometry": {"coordinates":[5.3006892204,50.4431762695],"type":"Point"}
}