{
  "type": "Feature",
  "properties": {
    "iso:country":"BE",
    "sg:address":"Groenstraat 15",
    "sg:city":"Brakel (michelbeke)",
    "sg:classifiers":[
        {
            "category":"Education",
            "subcategory":"School",
            "type":"Public Place"
        }
    ],
    "sg:phone":"+32 55 42 30 67",
    "sg:postcode":"9660",
    "sg:province":"Oost-Vlaanderen",
    "sg:tags":[
        "secondary"
    ],
    "wof:name":"Instituut Stella Matutina",
    "wof:placetype":"venue"
},
  "geometry": {"coordinates":[3.7642250061,50.8031082153],"type":"Point"}
}