{
  "type": "Feature",
  "properties": {
    "iso:country":"BE",
    "sg:address":"Rue Des Commonnettes 2",
    "sg:city":"Havelange (m\u00e9an)",
    "sg:classifiers":[
        {
            "category":"Banks & Credit Unions",
            "subcategory":"Bank",
            "type":"Services"
        }
    ],
    "sg:phone":"+32 86 32 23 52",
    "sg:postcode":"5372",
    "sg:province":"Namur",
    "sg:tags":[
        "savings-banks"
    ],
    "wof:name":"Paquay M",
    "wof:placetype":"venue"
},
  "geometry": {"coordinates":[5.3332271576,50.3610115051],"type":"Point"}
}