{
  "type": "Feature",
  "properties": {
    "addr:full":"Chauss\u00e9e De Dinant 28 Yvoir (spontin) Namur 5530",
    "addr:housenumber":"28",
    "addr:postcode":"5530",
    "addr:street":"Chausse\u0301E De Dinant",
    "iso:country":"BE",
    "sg:address":"Chauss\u00e9e De Dinant 28",
    "sg:city":"Yvoir (spontin)",
    "sg:classifiers":[
        {
            "category":"Shopping",
            "subcategory":"Books",
            "type":"Retail Goods"
        }
    ],
    "sg:phone":"+32 83 69 98 12",
    "sg:postcode":"5530",
    "sg:province":"Namur",
    "sg:tags":[
        "bookseller"
    ],
    "wof:name":"Etienne K",
    "wof:placetype":"venue"
},
  "geometry": {"coordinates":[5.0051751137,50.3223190308],"type":"Point"}
}