{
  "type": "Feature",
  "properties": {
    "iso:country":"BE",
    "sg:address":"Cadixstraat 2",
    "sg:city":"Antwerpen",
    "sg:orig_category":"Technisch and beroeps secundair onderwijs",
    "sg:phone":"+32 3 206 00 60",
    "sg:postcode":"2000",
    "sg:province":"Antwerpen",
    "wof:name":"Inst. Sierk. & Ambachten",
    "wof:placetype":"venue"
},
  "geometry": {"coordinates":[4.4119448662,51.2331047058],"type":"Point"}
}