{
  "type": "Feature",
  "properties": {
    "addr:full":"Rue Des Aulniats 254 Charleroi Hainaut 6042",
    "addr:housenumber":"254",
    "addr:postcode":"6042",
    "addr:street":"Rue Des Aulniats;Hainaut",
    "iso:country":"BE",
    "sg:address":"Rue Des Aulniats 254",
    "sg:city":"Charleroi",
    "sg:orig_category":"Woningbouw",
    "sg:phone":"+32 71 30 78 60",
    "sg:postcode":"6042",
    "sg:province":"Hainaut",
    "wof:name":"Befahy B",
    "wof:placetype":"venue"
},
  "geometry": {"coordinates":[4.4490199089,50.4293518066],"type":"Point"}
}