{
  "type": "Feature",
  "properties": {
    "addr:full":"Boulevard Pierre Mayence 5 Charleroi Hainaut 6000",
    "addr:housenumber":"5",
    "addr:postcode":"6000",
    "addr:street":"Boulevard Pierre Mayence;Hainaut",
    "iso:country":"BE",
    "sg:address":"Boulevard Pierre Mayence 5",
    "sg:city":"Charleroi",
    "sg:classifiers":[
        {
            "category":"Health Services",
            "subcategory":"Doctor",
            "type":"Services"
        }
    ],
    "sg:phone":"+32 71 30 78 39",
    "sg:postcode":"6000",
    "sg:province":"Hainaut",
    "sg:tags":[
        "medicinephysicians",
        "surgeon"
    ],
    "wof:name":"Jabry S",
    "wof:placetype":"venue"
},
  "geometry": {"coordinates":[4.4519958496,50.408115387],"type":"Point"}
}