{
  "type": "Feature",
  "properties": {
    "addr:full":"Rue C\u00e9lestin Demblon 190 Herstal Li\u00e8ge 4040",
    "addr:housenumber":"190",
    "addr:postcode":"4040",
    "addr:street":"Rue Ce\u0301Lestin Demblon",
    "iso:country":"BE",
    "sg:address":"Rue C\u00e9lestin Demblon 190",
    "sg:city":"Herstal",
    "sg:classifiers":[
        {
            "category":"Health Services",
            "subcategory":"Doctor",
            "type":"Services"
        }
    ],
    "sg:phone":"+32 4 240 42 22",
    "sg:postcode":"4040",
    "sg:province":"Li\u00e8ge",
    "sg:tags":[
        "medicinephysicians",
        "surgeon"
    ],
    "wof:name":"Gadomski Bernard",
    "wof:placetype":"venue"
},
  "geometry": {"coordinates":[5.6330480576,50.6765708923],"type":"Point"}
}