{
  "type": "Feature",
  "properties": {
    "addr:full":"Quai De La Boverie 97 Li\u00c8ge Li\u00e8ge 4020",
    "addr:housenumber":"97",
    "addr:postcode":"4020",
    "addr:street":"Quai De La Boverie",
    "iso:country":"BE",
    "sg:address":"Quai De La Boverie 97",
    "sg:city":"Li\u00c8ge",
    "sg:orig_category":"Boekhouders",
    "sg:phone":"+32 4 342 75 15",
    "sg:postcode":"4020",
    "sg:province":"Li\u00e8ge",
    "wof:name":"Didier Lambermont",
    "wof:placetype":"venue"
},
  "geometry": {"coordinates":[5.5772719383,50.6307029724],"type":"Point"}
}