{
  "type": "Feature",
  "properties": {
    "iso:country":"BE",
    "sg:address":"Parkstraat 7",
    "sg:city":"Alken",
    "sg:classifiers":[
        {
            "category":"Tea Room",
            "subcategory":"None",
            "type":"Food & Drink"
        }
    ],
    "sg:phone":"+32 11 31 11 31",
    "sg:postcode":"3570",
    "sg:province":"Limburg",
    "wof:name":"Ter Coost Bvba",
    "wof:placetype":"venue"
},
  "geometry": {"coordinates":[5.2749609947,50.8975982666],"type":"Point"}
}