{
  "type": "Feature",
  "properties": {
    "iso:country":"BE",
    "sg:address":"V-dagstraat 5",
    "sg:city":"Zwevegem",
    "sg:classifiers":[
        {
            "category":"Shopping",
            "subcategory":"Computers & Home Electronics",
            "type":"Retail Goods"
        }
    ],
    "sg:phone":"+32 56 64 55 01",
    "sg:postcode":"8550",
    "sg:province":"West-Vlaanderen",
    "sg:tags":[
        "system",
        "automation"
    ],
    "wof:name":"Vercoutere Jacques B.v.b.a.",
    "wof:placetype":"venue"
},
  "geometry": {"coordinates":[3.3329548836,50.8128356934],"type":"Point"}
}