{
  "type": "Feature",
  "properties": {
    "addr:full":"Rue De Montigny 32 Charleroi Hainaut 6000",
    "addr:housenumber":"32",
    "addr:postcode":"6000",
    "addr:street":"Rue De Montigny;Hainaut",
    "iso:country":"BE",
    "sg:address":"Rue De Montigny 32",
    "sg:city":"Charleroi",
    "sg:classifiers":[
        {
            "category":"Personal",
            "subcategory":"Beauty Salon",
            "type":"Services"
        }
    ],
    "sg:phone":"+32 71 50 02 84",
    "sg:postcode":"6000",
    "sg:province":"Hainaut",
    "sg:tags":[
        "lady",
        "-",
        "hairdressing"
    ],
    "wof:name":"Angel's Coiffure",
    "wof:placetype":"venue"
},
  "geometry": {"coordinates":[4.4443850517,50.4085273743],"type":"Point"}
}