{
  "type": "Feature",
  "properties": {
    "addr:full":"Rue Humer\u00c9e 46 Sombreffe Namur 5140",
    "addr:housenumber":"46",
    "addr:postcode":"5140",
    "addr:street":"Rue Humere\u0301E",
    "iso:country":"BE",
    "sg:address":"Rue Humer\u00c9e 46",
    "sg:city":"Sombreffe",
    "sg:orig_category":"Gespecialiseerde residenti\u00eble bouw",
    "sg:phone":"+32 71 88 92 47",
    "sg:postcode":"5140",
    "sg:province":"Namur",
    "wof:name":"Stephane Winand",
    "wof:placetype":"venue"
},
  "geometry": {"coordinates":[4.6212420464,50.531578064],"type":"Point"}
}