{
  "type": "Feature",
  "properties": {
    "addr:full":"Churchilllaan 20 Schoten Antwerpen 2900",
    "addr:housenumber":"20",
    "addr:postcode":"2900",
    "addr:street":"Churchilllaan",
    "iso:country":"BE",
    "sg:address":"Churchilllaan 20",
    "sg:city":"Schoten",
    "sg:orig_category":"Services fun\u00e9raires",
    "sg:phone":"+32 3 658 45 61",
    "sg:postcode":"2900",
    "sg:province":"Antwerpen",
    "wof:name":"Daems",
    "wof:placetype":"venue"
},
  "geometry": {"coordinates":[4.4962639809,51.2507781982],"type":"Point"}
}