{
  "type": "Feature",
  "properties": {
    "addr:full":"Gezondheidslei 29 Brasschaat Antwerpen 2930",
    "addr:housenumber":"29",
    "addr:postcode":"2930",
    "addr:street":"Gezondheidslei",
    "iso:country":"BE",
    "sg:address":"Gezondheidslei 29",
    "sg:city":"Brasschaat",
    "sg:classifiers":[
        {
            "category":"Building & Trades",
            "subcategory":"Pest Control",
            "type":"Services"
        }
    ],
    "sg:phone":"+32 3 665 23 43",
    "sg:postcode":"2930",
    "sg:province":"Antwerpen",
    "sg:tags":[
        "painting",
        "contractor"
    ],
    "wof:name":"Van Meervelde M",
    "wof:placetype":"venue"
},
  "geometry": {"coordinates":[4.4447550774,51.2941741943],"type":"Point"}
}