{
  "type": "Feature",
  "properties": {
    "addr:full":"Diksmuidseweg 150 Ieper West-Vlaanderen 8900",
    "addr:housenumber":"150",
    "addr:postcode":"8900",
    "iso:country":"BE",
    "sg:address":"Diksmuidseweg 150",
    "sg:city":"Ieper",
    "sg:orig_category":"Non-Classified Establishments",
    "sg:phone":"+32 57 21 73 50",
    "sg:postcode":"8900",
    "sg:province":"West-Vlaanderen",
    "wof:name":"Lakebos Nv",
    "wof:placetype":"venue"
},
  "geometry": {"coordinates":[2.8722400665,50.8719177246],"type":"Point"}
}