{
  "type": "Feature",
  "properties": {
    "addr:full":"Nijverheidslaan 124 Waasmunster Oost-Vlaanderen 9250",
    "addr:housenumber":"124",
    "addr:postcode":"9250",
    "addr:street":"Nijverheidslaan",
    "iso:country":"BE",
    "sg:address":"Nijverheidslaan 124",
    "sg:city":"Waasmunster",
    "sg:classifiers":[
        {
            "category":"Cafe",
            "type":"Food & Drink"
        }
    ],
    "sg:phone":"+32 52 46 33 54",
    "sg:postcode":"9250",
    "sg:province":"Oost-Vlaanderen",
    "sg:tags":[
        "caf\u00e9s"
    ],
    "wof:name":"I Verschelden",
    "wof:placetype":"venue"
},
  "geometry": {"coordinates":[4.1146950722,51.1236381531],"type":"Point"}
}