{
  "type": "Feature",
  "properties": {
    "iso:country":"BE",
    "sg:address":"Rue Des D\u00c8gues 16",
    "sg:city":"Braine-le-chateau",
    "sg:orig_category":"Elektrische installaties voor woningen",
    "sg:phone":"+32 2 366 44 87",
    "sg:postcode":"1440",
    "sg:province":"Brabant Wallon",
    "wof:name":"Serge Baudoux",
    "wof:placetype":"venue"
},
  "geometry": {"coordinates":[4.2749209404,50.6635551453],"type":"Point"}
}