{
  "type": "Feature",
  "properties": {
    "addr:full":"Minderhoutsestraat 19 Hoogstraten Antwerpen 2320",
    "addr:housenumber":"19",
    "addr:postcode":"2320",
    "addr:street":"Minderhoutsestraat",
    "iso:country":"BE",
    "sg:address":"Minderhoutsestraat 19",
    "sg:city":"Hoogstraten",
    "sg:classifiers":[
        {
            "category":"Building & Trades",
            "subcategory":"Electrical",
            "type":"Services"
        }
    ],
    "sg:phone":"+32 3 314 37 67",
    "sg:postcode":"2320",
    "sg:province":"Antwerpen",
    "sg:tags":[
        "electric",
        "-",
        "housewiring",
        "contractor"
    ],
    "wof:name":"Van Hemelen H",
    "wof:placetype":"venue"
},
  "geometry": {"coordinates":[4.7620720863,51.408996582],"type":"Point"}
}