{
  "type": "Feature",
  "properties": {
    "addr:full":"Dhoorestraat 17 Brugge West-Vlaanderen 8310",
    "addr:housenumber":"17",
    "addr:postcode":"8310",
    "addr:street":"Dhoorestraat",
    "iso:country":"BE",
    "sg:address":"Dhoorestraat 17",
    "sg:city":"Brugge",
    "sg:orig_category":"Advocaten and juridische adviseurs",
    "sg:phone":"+32 50 37 27 25",
    "sg:postcode":"8310",
    "sg:province":"West-Vlaanderen",
    "wof:name":"Dirk Plancke",
    "wof:placetype":"venue"
},
  "geometry": {"coordinates":[3.2421090603,51.2002563477],"type":"Point"}
}