{
  "type": "Feature",
  "properties": {
    "iso:country":"BE",
    "sg:address":"Achttiende Oogstwal 7 Box 2_",
    "sg:city":"Tongeren",
    "sg:orig_category":"Ice-cream parlours",
    "sg:phone":"+32 12 23 03 38",
    "sg:postcode":"3700",
    "sg:province":"Limburg",
    "wof:name":"Butterfly (the)",
    "wof:placetype":"venue"
},
  "geometry": {"coordinates":[5.4705457687,50.7836265564],"type":"Point"}
}