{
  "type": "Feature",
  "properties": {
    "addr:full":"Sint-hubrechtsstraat 43 Roeselare West-Vlaanderen 8800",
    "addr:housenumber":"43",
    "addr:postcode":"8800",
    "addr:street":"Sint-Hubrechtsstraat",
    "iso:country":"BE",
    "sg:address":"Sint-hubrechtsstraat 43",
    "sg:city":"Roeselare",
    "sg:classifiers":[
        {
            "category":"Bars & Pubs",
            "type":"Food & Drink"
        }
    ],
    "sg:phone":"+32 51 24 47 87",
    "sg:postcode":"8800",
    "sg:province":"West-Vlaanderen",
    "wof:name":"D'hert M",
    "wof:placetype":"venue"
},
  "geometry": {"coordinates":[3.1334779263,50.94739151],"type":"Point"}
}