{
  "type": "Feature",
  "properties": {
    "addr:full":"Weldonkstraat 327 Tremelo Vlaams-Brabant 3128",
    "addr:housenumber":"327",
    "addr:postcode":"3128",
    "addr:street":"Weldonkstraat",
    "iso:country":"BE",
    "sg:address":"Weldonkstraat 327",
    "sg:city":"Tremelo",
    "sg:orig_category":"Woningbouw",
    "sg:phone":"+32 16 53 40 33",
    "sg:postcode":"3128",
    "sg:province":"Vlaams-Brabant",
    "wof:name":"G. Van Den Bergh",
    "wof:placetype":"venue"
},
  "geometry": {"coordinates":[4.7541508675,50.9949302673],"type":"Point"}
}