{
  "type": "Feature",
  "properties": {
    "iso:country":"BE",
    "sg:address":"Vleminckstr 18",
    "sg:city":"Antwerpen",
    "sg:classifiers":[
        {
            "category":"Professional",
            "subcategory":"Printing & Photocopies",
            "type":"Services"
        }
    ],
    "sg:phone":"+32 3 234 05 50",
    "sg:postcode":"2000",
    "sg:province":"Antwerpen",
    "sg:tags":[
        "publishing"
    ],
    "wof:name":"De Lloyd Nv",
    "wof:placetype":"venue"
},
  "geometry": {"coordinates":[4.4040222168,51.2196884155],"type":"Point"}
}