{
  "type": "Feature",
  "properties": {
    "addr:full":"Chauss\u00e9e De Tongres 269 Li\u00e8ge 1 (rocourt) Li\u00e8ge 4000",
    "addr:housenumber":"269;1",
    "addr:postcode":"4000",
    "addr:street":"Chausse\u0301E De Tongres",
    "iso:country":"BE",
    "sg:address":"Chauss\u00e9e De Tongres 269",
    "sg:city":"Li\u00e8ge 1 (rocourt)",
    "sg:orig_category":"Accumulators",
    "sg:phone":"+32 4 263 92 85",
    "sg:postcode":"4000",
    "sg:province":"Li\u00e8ge",
    "wof:name":"Auto Centre Cora Lambermont",
    "wof:placetype":"venue"
},
  "geometry": {"coordinates":[5.5499391556,50.6700019836],"type":"Point"}
}