{
  "type": "Feature",
  "properties": {
    "addr:full":"Molenhuisstraat 46 Deinze Oost-Vlaanderen 9800",
    "addr:housenumber":"46",
    "addr:postcode":"9800",
    "addr:street":"Molenhuisstraat",
    "iso:country":"BE",
    "sg:address":"Molenhuisstraat 46",
    "sg:city":"Deinze",
    "sg:classifiers":[
        {
            "category":"Professional",
            "subcategory":"Art Services",
            "type":"Services"
        }
    ],
    "sg:phone":"+32 9 371 91 18",
    "sg:postcode":"9800",
    "sg:province":"Oost-Vlaanderen",
    "sg:tags":[
        "designer",
        "ontwerpers"
    ],
    "wof:name":"Pecceu B.",
    "wof:placetype":"venue"
},
  "geometry": {"coordinates":[3.5728619099,51.0179634094],"type":"Point"}
}