{
  "type": "Feature",
  "properties": {
    "addr:full":"Rue De Fer 7 Namur Namur 5000",
    "addr:housenumber":"7",
    "addr:postcode":"5000",
    "addr:street":"Rue De Fer",
    "iso:country":"BE",
    "sg:address":"Rue De Fer 7",
    "sg:city":"Namur",
    "sg:orig_category":"V\u00eatements",
    "sg:phone":"+32 81 22 73 07",
    "sg:postcode":"5000",
    "sg:province":"Namur",
    "wof:name":"Levi's",
    "wof:placetype":"venue"
},
  "geometry": {"coordinates":[4.8648061752,50.4651565552],"type":"Point"}
}