{
  "type": "Feature",
  "properties": {
    "iso:country":"BE",
    "sg:address":"Avenue De Berchem Sainte-agathe 38",
    "sg:city":"Bruxelles (koekelberg)",
    "sg:orig_category":"Non-Classified Establishments",
    "sg:phone":"+32 2 411 89 59",
    "sg:postcode":"1081",
    "sg:province":"Bruxelles-Capitale",
    "wof:name":"Rodon Watch Sprl",
    "wof:placetype":"venue"
},
  "geometry": {"coordinates":[4.3160219193,50.8649024963],"type":"Point"}
}