{
  "type": "Feature",
  "properties": {
    "iso:country":"BE",
    "sg:address":"Verbrand-hofstraat 20",
    "sg:city":"Wuustwezel (loenhout)",
    "sg:classifiers":[
        {
            "category":"Building & Trades",
            "subcategory":"Construction",
            "type":"Services"
        }
    ],
    "sg:phone":"+32 3 690 02 02",
    "sg:postcode":"2990",
    "sg:province":"Antwerpen",
    "sg:tags":[
        "stucco",
        "contractor"
    ],
    "wof:name":"Jochems F Bvba",
    "wof:placetype":"venue"
},
  "geometry": {"coordinates":[4.6022458076,51.3900947571],"type":"Point"}
}