{
  "type": "Feature",
  "properties": {
    "iso:country":"BE",
    "sg:address":"Pandhoevestraat 83",
    "sg:city":"Begijnendijk",
    "sg:classifiers":[
        {
            "category":"Professional",
            "type":"Services"
        }
    ],
    "sg:phone":"+32 50 55 96 00",
    "sg:postcode":"3130",
    "sg:province":"Vlaams-Brabant",
    "sg:tags":[
        "transport"
    ],
    "wof:name":"North Sea Express Nv",
    "wof:placetype":"venue"
},
  "geometry": {"coordinates":[3.184869051,51.3204421997],"type":"Point"}
}