{
  "type": "Feature",
  "properties": {
    "iso:country":"BE",
    "sg:address":"Rue De La Cath\u00e9drale 79",
    "sg:city":"Li\u00e8ge 1",
    "sg:classifiers":[
        {
            "category":"Shopping",
            "subcategory":"Clothing, Apparel, & Fashions",
            "type":"Retail Goods"
        }
    ],
    "sg:phone":"+32 4 232 05 50",
    "sg:postcode":"4000",
    "sg:province":"Li\u00e8ge",
    "sg:tags":[
        "lady",
        "clothing",
        "-"
    ],
    "wof:name":"H\u00e9t\u00e9roclite",
    "wof:placetype":"venue"
},
  "geometry": {"coordinates":[5.5735049248,50.6418647766],"type":"Point"}
}