{
  "type": "Feature",
  "properties": {
    "iso:country":"BE",
    "sg:address":"Nijverheidslaan 21",
    "sg:city":"Dilsen-stokkem (dilsen)",
    "sg:classifiers":[
        {
            "category":"Communications",
            "subcategory":"Film & Video Production",
            "type":"Services"
        }
    ],
    "sg:phone":"+32 89 75 53 22",
    "sg:postcode":"3650",
    "sg:province":"Limburg",
    "sg:tags":[
        "equipment",
        "-",
        "sale",
        "supply"
    ],
    "wof:name":"Leco Nv",
    "wof:placetype":"venue"
},
  "geometry": {"coordinates":[5.7082481384,51.019443512],"type":"Point"}
}