{
  "type": "Feature",
  "properties": {
    "addr:full":"Schoonzichtstraat 31 Gent (sint-denijs-westrem - Afsnee) Oost-Vlaanderen 9051",
    "addr:housenumber":"31",
    "addr:postcode":"9051",
    "addr:street":"Schoonzichtstraat;Oost-Vlaanderen",
    "iso:country":"BE",
    "sg:address":"Schoonzichtstraat 31",
    "sg:city":"Gent (sint-denijs-westrem - Afsnee)",
    "sg:classifiers":[
        {
            "category":"Personal",
            "subcategory":"Beauty Salon",
            "type":"Services"
        }
    ],
    "sg:phone":"+32 9 221 80 60",
    "sg:postcode":"9051",
    "sg:province":"Oost-Vlaanderen",
    "sg:tags":[
        "lady",
        "-",
        "hairdressing"
    ],
    "wof:name":"Rapid Hair",
    "wof:placetype":"venue"
},
  "geometry": {"coordinates":[3.6713089943,51.0169639587],"type":"Point"}
}