{
  "type": "Feature",
  "properties": {
    "addr:full":"Rue Ferdinand Lenoir 70 Jette Bruxelles-Capitale 1090",
    "addr:housenumber":"70",
    "addr:postcode":"1090",
    "addr:street":"Rue Ferdinand Lenoir",
    "iso:country":"BE",
    "sg:address":"Rue Ferdinand Lenoir 70",
    "sg:city":"Jette",
    "sg:orig_category":"Imprimeries and copyshops",
    "sg:phone":"+32 2 425 34 13",
    "sg:postcode":"1090",
    "sg:province":"Bruxelles-Capitale",
    "wof:name":"Maison Pap. Dachy",
    "wof:placetype":"venue"
},
  "geometry": {"coordinates":[4.331099987,50.8755493164],"type":"Point"}
}