{
  "type": "Feature",
  "properties": {
    "addr:full":"Poperingseweg 172 Ieper West-Vlaanderen 8908",
    "addr:housenumber":"172",
    "addr:postcode":"8908",
    "addr:street":"Poperingseweg",
    "iso:country":"BE",
    "sg:address":"Poperingseweg 172",
    "sg:city":"Ieper",
    "sg:orig_category":"Loodgieterij, verwarming and sanitaire installaties",
    "sg:phone":"+32 57 20 51 43",
    "sg:postcode":"8908",
    "sg:province":"West-Vlaanderen",
    "wof:name":"Bernard Declerck",
    "wof:placetype":"venue"
},
  "geometry": {"coordinates":[2.8273348808,50.8532981873],"type":"Point"}
}