{
  "type": "Feature",
  "properties": {
    "addr:full":"Dorpstraat 46 Moeskroen/mouscron Hainaut 7700",
    "addr:housenumber":"46",
    "addr:postcode":"7700",
    "addr:street":"Dorpstraat",
    "iso:country":"BE",
    "sg:address":"Dorpstraat 46",
    "sg:city":"Moeskroen/mouscron",
    "sg:orig_category":"Paramedische behandelingen",
    "sg:phone":"+32 56 34 55 17",
    "sg:postcode":"7700",
    "sg:province":"Hainaut",
    "wof:name":"C. Selosse",
    "wof:placetype":"venue"
},
  "geometry": {"coordinates":[3.2323200703,50.7400932312],"type":"Point"}
}