{
  "type": "Feature",
  "properties": {
    "addr:full":"Monterreystraat 16 Gent Oost-Vlaanderen 9000",
    "addr:housenumber":"16",
    "addr:postcode":"9000",
    "addr:street":"Monterreystraat;Oost-Vlaanderen",
    "iso:country":"BE",
    "sg:address":"Monterreystraat 16",
    "sg:city":"Gent",
    "sg:orig_category":"Avocats and conseillers juridiques",
    "sg:phone":"+32 9 222 42 98",
    "sg:postcode":"9000",
    "sg:province":"Oost-Vlaanderen",
    "wof:name":"Ren\u00c9 Verstringhe",
    "wof:placetype":"venue"
},
  "geometry": {"coordinates":[3.7205660343,51.0347099304],"type":"Point"}
}