{
  "type": "Feature",
  "properties": {
    "iso:country":"BE",
    "sg:address":"Meerweg 275",
    "sg:city":"Sint-pieters-leeuw (ruisbroek)",
    "sg:classifiers":[
        {
            "category":"Exhibition Hall",
            "type":"Public Place"
        }
    ],
    "sg:phone":"+32 2 378 29 19",
    "sg:postcode":"1601",
    "sg:province":"Vlaams-Brabant",
    "sg:tags":[
        "stand"
    ],
    "wof:name":"Traits Essentiels",
    "wof:placetype":"venue"
},
  "geometry": {"coordinates":[4.2789640427,50.7797927856],"type":"Point"}
}