{
  "type": "Feature",
  "properties": {
    "addr:full":"Baron August De Becker Remyplein 40 Leuven (kessel-lo) Vlaams-Brabant 3010",
    "addr:housenumber":"40",
    "addr:postcode":"3010",
    "addr:street":"Baron August De Becker Remyplein",
    "iso:country":"BE",
    "sg:address":"Baron August De Becker Remyplein 40",
    "sg:city":"Leuven (kessel-lo)",
    "sg:classifiers":[
        {
            "category":"Food & Beverages",
            "subcategory":"Chocolate",
            "type":"Retail Goods"
        }
    ],
    "sg:phone":"+32 16 35 38 78",
    "sg:postcode":"3010",
    "sg:province":"Vlaams-Brabant",
    "sg:tags":[
        "confectionery",
        "-"
    ],
    "wof:name":"Engeltje-bengeltje",
    "wof:placetype":"venue"
},
  "geometry": {"coordinates":[4.7304501534,50.889755249],"type":"Point"}
}