{
  "type": "Feature",
  "properties": {
    "addr:full":"Vlaanderenstraat 1 Oostende West-Vlaanderen 8400",
    "addr:housenumber":"1",
    "addr:postcode":"8400",
    "addr:street":"Vlaanderenstraat",
    "iso:country":"BE",
    "sg:address":"Vlaanderenstraat 1",
    "sg:city":"Oostende",
    "sg:orig_category":"Bijouteries and horlogeries. Bijoux Fab. R\u00e9parations d'horloges, montres and bijoux",
    "sg:phone":"+32 59 70 49 72",
    "sg:postcode":"8400",
    "sg:province":"West-Vlaanderen",
    "wof:name":"Bourgois",
    "wof:placetype":"venue"
},
  "geometry": {"coordinates":[2.9170360565,51.2321586609],"type":"Point"}
}