{
  "type": "Feature",
  "properties": {
    "addr:full":"Rue Des Colonies 62 Bruxelles Bruxelles-Capitale 1000",
    "addr:housenumber":"62",
    "addr:postcode":"1000",
    "addr:street":"Rue Des Colonies",
    "iso:country":"BE",
    "sg:address":"Rue Des Colonies 62",
    "sg:city":"Bruxelles",
    "sg:classifiers":[
        {
            "category":"Professional",
            "type":"Services"
        }
    ],
    "sg:phone":"+32 2 506 02 11",
    "sg:postcode":"1000",
    "sg:province":"Bruxelles-Capitale",
    "sg:tags":[
        "leasing"
    ],
    "wof:name":"Fortis Lease",
    "wof:placetype":"venue"
},
  "geometry": {"coordinates":[4.3615398407,50.8468742371],"type":"Point"}
}