{
  "type": "Feature",
  "properties": {
    "iso:country":"BE",
    "sg:address":"Sint-denijsstraat 155",
    "sg:city":"Vorst/forest",
    "sg:orig_category":"Meubles D\u00e9taillants, Am\u00e9nagement de B\u00e2timents et de Cuisines. Installation de menuiserie m\u00e9tallique",
    "sg:phone":"+32 2 340 10 80",
    "sg:postcode":"1190",
    "sg:province":"Bruxelles-Capitale",
    "wof:name":"Kardex",
    "wof:placetype":"venue"
},
  "geometry": {"coordinates":[4.317609787,50.8097991943],"type":"Point"}
}