{
  "type": "Feature",
  "properties": {
    "addr:full":"De Geneffestraat 18 Sint-jans-molenbeek/molenbeek-saint-jean Bruxelles-Capitale 1080",
    "addr:housenumber":"18",
    "addr:postcode":"1080",
    "addr:street":"De Geneffestraat",
    "iso:country":"BE",
    "sg:address":"De Geneffestraat 18",
    "sg:city":"Sint-jans-molenbeek/molenbeek-saint-jean",
    "sg:orig_category":"Openbare bibliotheken and archieven",
    "sg:phone":"+32 2 425 06 19",
    "sg:postcode":"1080",
    "sg:province":"Bruxelles-Capitale",
    "wof:name":"Ludoth\u00c8que De Molenbeek",
    "wof:placetype":"venue"
},
  "geometry": {"coordinates":[4.3367462158,50.8558921814],"type":"Point"}
}