{
  "type": "Feature",
  "properties": {
    "addr:full":"Avenue De Bouillon 94a Libramont-chevigny Luxembourg 6800",
    "addr:housenumber":"94a",
    "addr:postcode":"6800",
    "addr:street":"Avenue De Bouillon",
    "iso:country":"BE",
    "sg:address":"Avenue De Bouillon 94a",
    "sg:city":"Libramont-chevigny",
    "sg:orig_category":"Mat\u00e9riel de T\u00e9l\u00e9communication. R\u00e9parations d'appareils \u00e9lectrom\u00e9nagers",
    "sg:phone":"+32 61 23 21 88",
    "sg:postcode":"6800",
    "sg:province":"Luxembourg",
    "wof:name":"Euro Center",
    "wof:placetype":"venue"
},
  "geometry": {"coordinates":[5.3593502045,49.9141998291],"type":"Point"}
}