{
  "type": "Feature",
  "properties": {
    "addr:full":"Dolfijnstraat 51 Antwerpen Antwerpen 2018",
    "addr:housenumber":"51",
    "addr:postcode":"2018",
    "addr:street":"Dolfijnstraat",
    "iso:country":"BE",
    "sg:address":"Dolfijnstraat 51",
    "sg:city":"Antwerpen",
    "sg:classifiers":[
        {
            "category":"Insurance",
            "subcategory":"Insurance Agent",
            "type":"Services"
        }
    ],
    "sg:phone":"+32 3 236 84 13",
    "sg:postcode":"2018",
    "sg:province":"Antwerpen",
    "sg:tags":[
        "broker"
    ],
    "wof:name":"Reimers J",
    "wof:placetype":"venue"
},
  "geometry": {"coordinates":[4.4340538979,51.208026886],"type":"Point"}
}