{
  "type": "Feature",
  "properties": {
    "addr:full":"Rue Du Vieux March\u00e9 3 Vielsalm Luxembourg 6690",
    "addr:housenumber":"3",
    "addr:postcode":"6690",
    "addr:street":"Rue Du Vieux Marche\u0301",
    "iso:country":"BE",
    "sg:address":"Rue Du Vieux March\u00e9 3",
    "sg:city":"Vielsalm",
    "sg:classifiers":[
        {
            "category":"Utilities",
            "subcategory":"Mobile Phone",
            "type":"Services"
        }
    ],
    "sg:phone":"+32 80 21 62 16",
    "sg:postcode":"6690",
    "sg:province":"Luxembourg",
    "sg:tags":[
        "access",
        "gsm",
        "-",
        "apparatus"
    ],
    "wof:name":"Gustin P",
    "wof:placetype":"venue"
},
  "geometry": {"coordinates":[5.9154238701,50.2867698669],"type":"Point"}
}