{
  "type": "Feature",
  "properties": {
    "addr:full":"Boulevard G\u00e9n\u00e9ral Jacques 200 Bruxelles (ixelles) Bruxelles-Capitale 1050",
    "addr:housenumber":"200",
    "addr:postcode":"1050",
    "addr:street":"Boulevard Ge\u0301Ne\u0301Ral Jacques",
    "iso:country":"BE",
    "sg:address":"Boulevard G\u00e9n\u00e9ral Jacques 200",
    "sg:city":"Bruxelles (ixelles)",
    "sg:classifiers":[
        {
            "category":"Social Services",
            "subcategory":"Retirement Home",
            "type":"Services"
        }
    ],
    "sg:phone":"+32 2 648 32 25",
    "sg:postcode":"1050",
    "sg:province":"Bruxelles-Capitale",
    "sg:tags":[
        "residence"
    ],
    "wof:name":"R\u00e9sidence 200 Sprl",
    "wof:placetype":"venue"
},
  "geometry": {"coordinates":[4.386054039,50.8211555481],"type":"Point"}
}