{
  "type": "Feature",
  "properties": {
    "addr:full":"Resesastraat 23 Lovendegem Oost-Vlaanderen 9920",
    "addr:housenumber":"23",
    "addr:postcode":"9920",
    "addr:street":"Resesastraat",
    "iso:country":"BE",
    "sg:address":"Resesastraat 23",
    "sg:city":"Lovendegem",
    "sg:orig_category":"Instituts de beaut\u00e9",
    "sg:phone":"+32 9 372 67 11",
    "sg:postcode":"9920",
    "sg:province":"Oost-Vlaanderen",
    "wof:name":"Ter Bronnen",
    "wof:placetype":"venue"
},
  "geometry": {"coordinates":[3.6097290516,51.0944099426],"type":"Point"}
}