{
  "type": "Feature",
  "properties": {
    "iso:country":"BE",
    "sg:address":"Heilig-hartlaan 55",
    "sg:city":"Jette",
    "sg:orig_category":"Bouwmaterialen Gh Plaatsen van vloer- and muurbekleding",
    "sg:phone":"+32 2 478 95 50",
    "sg:postcode":"1090",
    "sg:province":"Bruxelles-Capitale",
    "wof:name":"Ben Thiers",
    "wof:placetype":"venue"
},
  "geometry": {"coordinates":[4.3310370445,50.8836212158],"type":"Point"}
}