{
  "type": "Feature",
  "properties": {
    "iso:country":"BE",
    "sg:address":"Mooi Uitzichtlaan 34",
    "sg:city":"Bilzen",
    "sg:classifiers":[
        {
            "category":"Building & Trades",
            "subcategory":"Construction",
            "type":"Services"
        }
    ],
    "sg:phone":"+32 89 41 58 75",
    "sg:postcode":"3740",
    "sg:province":"Limburg",
    "sg:tags":[
        "stucco",
        "contractor"
    ],
    "wof:name":"Winten N",
    "wof:placetype":"venue"
},
  "geometry": {"coordinates":[5.5230760574,50.8676986694],"type":"Point"}
}