{
  "type": "Feature",
  "properties": {
    "iso:country":"BE",
    "sg:address":"Rue Du Chaffour 61",
    "sg:city":"Paliseul",
    "sg:classifiers":[
        {
            "category":"Professional",
            "subcategory":"Accounting & Tax Preparation",
            "type":"Services"
        }
    ],
    "sg:phone":"+32 61 53 36 50",
    "sg:postcode":"6850",
    "sg:province":"Luxembourg",
    "sg:tags":[
        "accountant"
    ],
    "wof:name":"Lucien Renauld",
    "wof:placetype":"venue"
},
  "geometry": {"coordinates":[5.1263480186,49.9028091431],"type":"Point"}
}