{
  "type": "Feature",
  "properties": {
    "iso:country":"BE",
    "sg:address":"Pollarestraat 126",
    "sg:city":"Ninove",
    "sg:classifiers":[
        {
            "category":"Cafe",
            "type":"Food & Drink"
        }
    ],
    "sg:phone":"+32 54 32 35 31",
    "sg:postcode":"9400",
    "sg:province":"Oost-Vlaanderen",
    "sg:tags":[
        "caf\u00e9s"
    ],
    "wof:name":"George Burkitt",
    "wof:placetype":"venue"
},
  "geometry": {"coordinates":[4.0205512047,50.8275146484],"type":"Point"}
}