{
  "type": "Feature",
  "properties": {
    "addr:full":"Statielei 73 Mortsel Antwerpen 2640",
    "addr:housenumber":"73",
    "addr:postcode":"2640",
    "addr:street":"Statielei",
    "iso:country":"BE",
    "sg:address":"Statielei 73",
    "sg:city":"Mortsel",
    "sg:classifiers":[
        {
            "category":"Shopping",
            "subcategory":"Clothing, Apparel, & Fashions",
            "type":"Retail Goods"
        }
    ],
    "sg:phone":"+32 3 449 36 52",
    "sg:postcode":"2640",
    "sg:province":"Antwerpen",
    "sg:tags":[
        "v\u00eatements",
        "pour",
        "dame"
    ],
    "wof:name":"M&s Mode",
    "wof:placetype":"venue"
},
  "geometry": {"coordinates":[4.4526510239,51.1706466675],"type":"Point"}
}