{
  "type": "Feature",
  "properties": {
    "addr:full":"Avenue Du Parc 9 Wavre Brabant Wallon 1300",
    "addr:housenumber":"9;1300",
    "addr:street":"Avenue Du Parc",
    "iso:country":"BE",
    "sg:address":"Avenue Du Parc 9",
    "sg:city":"Wavre",
    "sg:classifiers":[
        {
            "category":"Communications",
            "subcategory":"News Services",
            "type":"Services"
        }
    ],
    "sg:phone":"+32 10 22 76 65",
    "sg:postcode":"1300",
    "sg:province":"Brabant Wallon",
    "sg:tags":[
        "illustrator"
    ],
    "wof:name":"Creations Roger Leloup Sa",
    "wof:placetype":"venue"
},
  "geometry": {"coordinates":[4.6187090874,50.7108230591],"type":"Point"}
}