{
  "type": "Feature",
  "properties": {
    "addr:full":"Langestraat 6 Gent (ledeberg) Oost-Vlaanderen 9050",
    "addr:housenumber":"6",
    "addr:postcode":"9050",
    "addr:street":"Langestraat",
    "iso:country":"BE",
    "sg:address":"Langestraat 6",
    "sg:city":"Gent (ledeberg)",
    "sg:classifiers":[
        {
            "category":"Food & Beverages",
            "subcategory":"Specialty",
            "type":"Retail Goods"
        }
    ],
    "sg:phone":"+32 9 385 32 23",
    "sg:postcode":"9050",
    "sg:province":"Oost-Vlaanderen",
    "sg:tags":[
        "health",
        "dietary",
        "-",
        "biological"
    ],
    "wof:name":"De Vier Seizoenen",
    "wof:placetype":"venue"
},
  "geometry": {"coordinates":[3.7449090481,51.0393333435],"type":"Point"}
}