{
  "type": "Feature",
  "properties": {
    "addr:full":"Prof.o.rubbrechtstraat 68b Poperinge West-Vlaanderen 8972",
    "addr:housenumber":"68b",
    "addr:postcode":"8972",
    "addr:street":"Prof.O.Rubbrechtstraat",
    "iso:country":"BE",
    "sg:address":"Prof.o.rubbrechtstraat 68b",
    "sg:city":"Poperinge",
    "sg:orig_category":"Banken and kredietinstellingen",
    "sg:phone":"+32 57 30 02 70",
    "sg:postcode":"8972",
    "sg:province":"West-Vlaanderen",
    "wof:name":"Landbouwkrediet",
    "wof:placetype":"venue"
},
  "geometry": {"coordinates":[2.6271851063,50.9170532227],"type":"Point"}
}