{
  "type": "Feature",
  "properties": {
    "iso:country":"BE",
    "sg:address":"Industrieweg 40",
    "sg:city":"Roeselare",
    "sg:orig_category":"HUISBRANDOLIE",
    "sg:phone":"+32 51 22 06 72",
    "sg:postcode":"8800",
    "sg:province":"West-Vlaanderen",
    "wof:name":"Vervoer R Haelewyn",
    "wof:placetype":"venue"
},
  "geometry": {"coordinates":[3.1306250095,50.9754943848],"type":"Point"}
}