{
  "type": "Feature",
  "properties": {
    "iso:country":"BE",
    "sg:address":"10",
    "sg:city":"Bouwelven 2280 Grobbendonk",
    "sg:classifiers":[
        {
            "category":"Manufacturing",
            "subcategory":"Textiles",
            "type":"Manufacturing & Wholesale Goods"
        }
    ],
    "sg:phone":"+32 14 25 80 60",
    "sg:postcode":"10",
    "sg:tags":[
        "linen",
        "clothing",
        "fabric"
    ],
    "wof:name":"Veneta Nv",
    "wof:placetype":"venue"
},
  "geometry": {"coordinates":[4.7798848152,51.1661109924],"type":"Point"}
}