{
  "type": "Feature",
  "properties": {
    "iso:country":"BE",
    "sg:address":"Borstekouterstraat 43",
    "sg:city":"Zwalm",
    "sg:orig_category":"RESTAURANTS: LIVRAISON \u00c0 DOMICILE. RESTAURANTS",
    "sg:phone":"+32 55 49 78 43",
    "sg:postcode":"9630",
    "sg:province":"Oost-Vlaanderen",
    "wof:name":"Restaurant Roborsthoeve",
    "wof:placetype":"venue"
},
  "geometry": {"coordinates":[3.74635005,50.8635292053],"type":"Point"}
}