{
  "type": "Feature",
  "properties": {
    "iso:country":"BE",
    "sg:address":"Rue De La Vigne 21",
    "sg:city":"Bruxelles (anderlecht)",
    "sg:classifiers":[
        {
            "category":"Retail",
            "subcategory":"Laundry & Dry Cleaning",
            "type":"Services"
        }
    ],
    "sg:phone":"+32 2 527 84 52",
    "sg:postcode":"1070",
    "sg:province":"Bruxelles-Capitale",
    "sg:tags":[
        "self",
        "-"
    ],
    "wof:name":"Lavoir La Vigne",
    "wof:placetype":"venue"
},
  "geometry": {"coordinates":[4.2853970528,50.8289985657],"type":"Point"}
}