{
  "type": "Feature",
  "properties": {
    "iso:country":"BE",
    "sg:address":"Pruimelaarstraat 18",
    "sg:city":"Evergem",
    "sg:orig_category":"Installatie van houten of kunststof schrijnwerk",
    "sg:phone":"+32 9 357 23 91",
    "sg:postcode":"9940",
    "sg:province":"Oost-Vlaanderen",
    "wof:name":"Carette",
    "wof:placetype":"venue"
},
  "geometry": {"coordinates":[3.6725900173,51.1321144104],"type":"Point"}
}