{
  "type": "Feature",
  "properties": {
    "addr:full":"Rue De Beckerich 27 Arlon Luxembourg 6704",
    "addr:housenumber":"27",
    "addr:postcode":"6704",
    "addr:street":"Rue De Beckerich",
    "iso:country":"BE",
    "sg:address":"Rue De Beckerich 27",
    "sg:city":"Arlon",
    "sg:orig_category":"M\u00e9decins and sp\u00e9cialistes",
    "sg:phone":"+32 63 22 01 95",
    "sg:postcode":"6704",
    "sg:province":"Luxembourg",
    "wof:name":"Mitri Ramal Fahd",
    "wof:placetype":"venue"
},
  "geometry": {"coordinates":[5.8503890038,49.7173995972],"type":"Point"}
}