{
  "type": "Feature",
  "properties": {
    "addr:full":"Muzementen 1 Hoogstraten Antwerpen 2320",
    "addr:housenumber":"1",
    "addr:postcode":"2320",
    "addr:street":"Muzementen",
    "iso:country":"BE",
    "sg:address":"Muzementen 1",
    "sg:city":"Hoogstraten",
    "sg:orig_category":"Eleveurs and marchands de porcs. Eleveurs de bovins",
    "sg:phone":"+32 3 314 59 42",
    "sg:postcode":"2320",
    "sg:province":"Antwerpen",
    "wof:name":"Jozef Govaerts",
    "wof:placetype":"venue"
},
  "geometry": {"coordinates":[4.739346981,51.4064254761],"type":"Point"}
}