{
  "type": "Feature",
  "properties": {
    "addr:full":"Wingepark 29 Rotselaar Vlaams-Brabant 3110",
    "addr:housenumber":"29",
    "addr:postcode":"3110",
    "addr:street":"Wingepark",
    "iso:country":"BE",
    "sg:address":"Wingepark 29",
    "sg:city":"Rotselaar",
    "sg:classifiers":[
        {
            "category":"Manufacturing",
            "subcategory":"Tools & Machinery",
            "type":"Manufacturing & Wholesale Goods"
        }
    ],
    "sg:phone":"+32 15 52 09 97",
    "sg:postcode":"3110",
    "sg:province":"Vlaams-Brabant",
    "sg:tags":[
        "-"
    ],
    "wof:name":"Alto-longin Services",
    "wof:placetype":"venue"
},
  "geometry": {"coordinates":[4.7457470894,50.9406967163],"type":"Point"}
}