{
  "type": "Feature",
  "properties": {
    "addr:full":"Rue De Belle-vue 188 La Louviere Hainaut 7100",
    "addr:housenumber":"188",
    "addr:postcode":"7100",
    "addr:street":"Rue De Belle-Vue",
    "iso:country":"BE",
    "sg:address":"Rue De Belle-vue 188",
    "sg:city":"La Louviere",
    "sg:orig_category":"Huishoudapparaten, televisies and radio's",
    "sg:phone":"+32 64 22 44 91",
    "sg:postcode":"7100",
    "sg:province":"Hainaut",
    "wof:name":"Maison Zanoni",
    "wof:placetype":"venue"
},
  "geometry": {"coordinates":[4.1904420853,50.4704208374],"type":"Point"}
}