{
  "type": "Feature",
  "properties": {
    "addr:full":"Vrijheidsstraat 27 Gistel (snaaskerke) West-Vlaanderen 8470",
    "addr:housenumber":"27",
    "addr:postcode":"8470",
    "addr:street":"Vrijheidsstraat",
    "iso:country":"BE",
    "sg:address":"Vrijheidsstraat 27",
    "sg:city":"Gistel (snaaskerke)",
    "sg:classifiers":[
        {
            "category":"Shopping",
            "type":"Retail Goods"
        }
    ],
    "sg:phone":"+32 59 27 64 66",
    "sg:postcode":"8470",
    "sg:province":"West-Vlaanderen",
    "sg:tags":[
        "product",
        "cleaning",
        "maintenance"
    ],
    "wof:name":"D B S - Products",
    "wof:placetype":"venue"
},
  "geometry": {"coordinates":[2.9384820461,51.1730575562],"type":"Point"}
}