{
  "type": "Feature",
  "properties": {
    "addr:full":"Grote Markt 12 Tienen Vlaams-Brabant 3300",
    "addr:housenumber":"12",
    "addr:postcode":"3300",
    "addr:street":"Grote Markt",
    "iso:country":"BE",
    "sg:address":"Grote Markt 12",
    "sg:city":"Tienen",
    "sg:orig_category":"Foto-uitrusting Telecommunicatieapparaten",
    "sg:phone":"+32 16 80 59 80",
    "sg:postcode":"3300",
    "sg:province":"Vlaams-Brabant",
    "wof:name":"Foto Video Leyssens Action Shop",
    "wof:placetype":"venue"
},
  "geometry": {"coordinates":[4.9375982285,50.808429718],"type":"Point"}
}