{
  "type": "Feature",
  "properties": {
    "addr:full":"L. Van Boeckelstraat 21b52 Evere Bruxelles-Capitale 1140",
    "addr:housenumber":"21b52",
    "addr:postcode":"1140",
    "addr:street":"L. Van Boeckelstraat",
    "iso:country":"BE",
    "sg:address":"L. Van Boeckelstraat 21b52",
    "sg:city":"Evere",
    "sg:orig_category":"Boekenuitgeverijen",
    "sg:phone":"+32 2 241 08 21",
    "sg:postcode":"1140",
    "sg:province":"Bruxelles-Capitale",
    "wof:name":"Editions Memeurop",
    "wof:placetype":"venue"
},
  "geometry": {"coordinates":[4.4002327919,50.875919342],"type":"Point"}
}