{
  "type": "Feature",
  "properties": {
    "addr:full":"Chauss\u00e9e De Charleroi 115 Beaumont (str\u00e9e) Hainaut 6511",
    "addr:housenumber":"115",
    "addr:postcode":"6511",
    "addr:street":"Chausse\u0301E De Charleroi",
    "iso:country":"BE",
    "sg:address":"Chauss\u00e9e De Charleroi 115",
    "sg:city":"Beaumont (str\u00e9e)",
    "sg:classifiers":[
        {
            "category":"Banks & Credit Unions",
            "subcategory":"Investment Brokerage",
            "type":"Services"
        }
    ],
    "sg:phone":"+32 71 58 82 23",
    "sg:postcode":"6511",
    "sg:province":"Hainaut",
    "sg:tags":[
        "printing",
        "-"
    ],
    "wof:name":"Imprimeries Beaumontoises Lebrun Sprl",
    "wof:placetype":"venue"
},
  "geometry": {"coordinates":[4.2843699455,50.270980835],"type":"Point"}
}