{
  "type": "Feature",
  "properties": {
    "iso:country":"BE",
    "sg:address":"Rue Clovis Poullet 9",
    "sg:city":"Estaimpuis (estaimbourg)",
    "sg:classifiers":[
        {
            "category":"Food & Beverages",
            "subcategory":"Groceries & Convenience Stores",
            "type":"Retail Goods"
        }
    ],
    "sg:phone":"+32 69 45 69 56",
    "sg:postcode":"7730",
    "sg:province":"Hainaut",
    "sg:tags":[
        "grocer"
    ],
    "wof:name":"Au P'tit Boutiq'",
    "wof:placetype":"venue"
},
  "geometry": {"coordinates":[3.3169019222,50.6821517944],"type":"Point"}
}