{
  "type": "Feature",
  "properties": {
    "iso:country":"BE",
    "sg:address":"Heiderfeld 43",
    "sg:city":"Amel/ambleve",
    "sg:orig_category":"Rundveehouders",
    "sg:phone":"+32 80 34 98 65",
    "sg:postcode":"4770",
    "sg:province":"Li\u00e8ge",
    "wof:name":"Irmgard Mertes",
    "wof:placetype":"venue"
},
  "geometry": {"coordinates":[6.1876211166,50.3251914978],"type":"Point"}
}