{
  "type": "Feature",
  "properties": {
    "iso:country":"BE",
    "sg:address":"Bergsebaan 35",
    "sg:city":"Essen",
    "sg:orig_category":"Producteurs de l\u00e9gumes",
    "sg:phone":"+32 3 677 33 46",
    "sg:postcode":"2910",
    "sg:province":"Antwerpen",
    "wof:name":"Adrianus Van Aert",
    "wof:placetype":"venue"
},
  "geometry": {"coordinates":[4.3962378502,51.448589325],"type":"Point"}
}