{
  "type": "Feature",
  "properties": {
    "iso:country":"BE",
    "sg:address":"Koningin Fabiolastraat 6",
    "sg:city":"Wevelgem",
    "sg:orig_category":"Banken and kredietinstellingen",
    "sg:phone":"+32 56 41 13 14",
    "sg:postcode":"8560",
    "sg:province":"West-Vlaanderen",
    "wof:name":"Bbl",
    "wof:placetype":"venue"
},
  "geometry": {"coordinates":[3.2038199902,50.8425331116],"type":"Point"}
}