{
  "type": "Feature",
  "properties": {
    "addr:full":"Bormansstraat 75 Landen Vlaams-Brabant 3401",
    "addr:housenumber":"75",
    "addr:postcode":"3401",
    "addr:street":"Bormansstraat",
    "iso:country":"BE",
    "sg:address":"Bormansstraat 75",
    "sg:city":"Landen",
    "sg:orig_category":"Artsen and specialisten",
    "sg:phone":"+32 11 88 32 44",
    "sg:postcode":"3401",
    "sg:province":"Vlaams-Brabant",
    "wof:name":"P. Maes",
    "wof:placetype":"venue"
},
  "geometry": {"coordinates":[5.0927901268,50.7192802429],"type":"Point"}
}