{
  "type": "Feature",
  "properties": {
    "addr:full":"Kuurnsesteenweg 103 Kortrijk West-Vlaanderen 8500",
    "addr:housenumber":"103",
    "addr:postcode":"8500",
    "addr:street":"Kuurnsesteenweg",
    "iso:country":"BE",
    "sg:address":"Kuurnsesteenweg 103",
    "sg:city":"Kortrijk",
    "sg:classifiers":[
        {
            "category":"Health Services",
            "subcategory":"Medical Lab",
            "type":"Services"
        }
    ],
    "sg:phone":"+32 56 36 53 46",
    "sg:postcode":"8500",
    "sg:province":"West-Vlaanderen",
    "sg:tags":[
        "laboratory",
        "dental"
    ],
    "wof:name":"Vanderbeken Dental Labo",
    "wof:placetype":"venue"
},
  "geometry": {"coordinates":[3.2705740929,50.8430595398],"type":"Point"}
}