{
  "type": "Feature",
  "properties": {
    "addr:full":"Lispersteenweg 367 Lier Antwerpen 2500",
    "addr:housenumber":"367",
    "addr:postcode":"2500",
    "addr:street":"Lispersteenweg",
    "iso:country":"BE",
    "sg:address":"Lispersteenweg 367",
    "sg:city":"Lier",
    "sg:orig_category":"Herstelling leer and schoeisel",
    "sg:phone":"+32 3 290 78 24",
    "sg:postcode":"2500",
    "sg:province":"Antwerpen",
    "wof:name":"Schoenmakerij Grijp",
    "wof:placetype":"venue"
},
  "geometry": {"coordinates":[4.575925827,51.1473236084],"type":"Point"}
}