{
  "type": "Feature",
  "properties": {
    "addr:full":"Kleiveld 24 Linkebeek Vlaams-Brabant 1630",
    "addr:housenumber":"24",
    "addr:postcode":"1630",
    "addr:street":"Kleiveld",
    "iso:country":"BE",
    "sg:address":"Kleiveld 24",
    "sg:city":"Linkebeek",
    "sg:classifiers":[
        {
            "category":"Home & Garden",
            "subcategory":"Carpets & Floor Coverings",
            "type":"Retail Goods"
        }
    ],
    "sg:phone":"+32 2 381 24 15",
    "sg:postcode":"1630",
    "sg:province":"Vlaams-Brabant",
    "sg:tags":[
        "parquet"
    ],
    "wof:name":"Tout Parquet Fils",
    "wof:placetype":"venue"
},
  "geometry": {"coordinates":[4.3447208405,50.7710113525],"type":"Point"}
}