{
  "type": "Feature",
  "properties": {
    "addr:full":"Hoge Mauw 64 Arendonk Antwerpen 2370",
    "addr:housenumber":"64",
    "addr:postcode":"2370",
    "addr:street":"Hoge Mauw",
    "iso:country":"BE",
    "sg:address":"Hoge Mauw 64",
    "sg:city":"Arendonk",
    "sg:classifiers":[
        {
            "category":"Utilities",
            "subcategory":"Natural Gas",
            "type":"Services"
        }
    ],
    "sg:phone":"+32 14 67 89 21",
    "sg:postcode":"2370",
    "sg:province":"Antwerpen",
    "sg:tags":[
        "welding"
    ],
    "wof:name":"Verwaest Fr",
    "wof:placetype":"venue"
},
  "geometry": {"coordinates":[5.1088500023,51.2997703552],"type":"Point"}
}