{
  "type": "Feature",
  "properties": {
    "addr:full":"Collegelaan 48 Bornem Antwerpen 2880",
    "addr:housenumber":"48",
    "addr:postcode":"2880",
    "addr:street":"Collegelaan",
    "iso:country":"BE",
    "sg:address":"Collegelaan 48",
    "sg:city":"Bornem",
    "sg:orig_category":"Woningbouw",
    "sg:phone":"+32 3 889 51 84",
    "sg:postcode":"2880",
    "sg:province":"Antwerpen",
    "wof:name":"Dirk Vercruyssen",
    "wof:placetype":"venue"
},
  "geometry": {"coordinates":[4.2258338928,51.09009552],"type":"Point"}
}