{
  "type": "Feature",
  "properties": {
    "addr:full":"Chauss\u00e9e D'ixelles 257 Bruxelles (ixelles) Bruxelles-Capitale 1050",
    "addr:housenumber":"257",
    "addr:postcode":"1050",
    "addr:street":"Chausse\u0301E D'Ixelles",
    "iso:country":"BE",
    "sg:address":"Chauss\u00e9e D'ixelles 257",
    "sg:city":"Bruxelles (ixelles)",
    "sg:classifiers":[
        {
            "category":"Shopping",
            "subcategory":"Books",
            "type":"Retail Goods"
        }
    ],
    "sg:phone":"+32 2 648 01 94",
    "sg:postcode":"1050",
    "sg:province":"Bruxelles-Capitale",
    "sg:tags":[
        "bookseller"
    ],
    "wof:name":"Polar & Co",
    "wof:placetype":"venue"
},
  "geometry": {"coordinates":[4.3687357903,50.8306922913],"type":"Point"}
}