{
  "type": "Feature",
  "properties": {
    "addr:full":"Rue Du Docteur Harvengt 10 Qu\u00e9vy (genly) Hainaut 7040",
    "addr:housenumber":"10",
    "addr:postcode":"7040",
    "addr:street":"Rue Du Docteur Harvengt;Hainaut",
    "iso:country":"BE",
    "sg:address":"Rue Du Docteur Harvengt 10",
    "sg:city":"Qu\u00e9vy (genly)",
    "sg:classifiers":[
        {
            "category":"Health Services",
            "subcategory":"Nursing And Care Facility",
            "type":"Services"
        }
    ],
    "sg:phone":"+32 65 56 86 30",
    "sg:postcode":"7040",
    "sg:province":"Hainaut",
    "sg:tags":[
        "home"
    ],
    "wof:name":"Genique Christine",
    "wof:placetype":"venue"
},
  "geometry": {"coordinates":[3.9196400642,50.3959617615],"type":"Point"}
}