{
  "type": "Feature",
  "properties": {
    "iso:country":"BE",
    "sg:address":"Stokrooiestraat 59",
    "sg:city":"Lummen",
    "sg:orig_category":"Airconditioning and ventilatie Loodgieterij, verwarming and sanitaire installaties",
    "sg:phone":"+32 13 52 34 10",
    "sg:postcode":"3560",
    "sg:province":"Limburg",
    "wof:name":"Motmans Eric",
    "wof:placetype":"venue"
},
  "geometry": {"coordinates":[5.2371511459,50.9699897766],"type":"Point"}
}