{
  "type": "Feature",
  "properties": {
    "addr:full":"Miksebeekstraat 63 Brasschaat Antwerpen 2930",
    "addr:housenumber":"63",
    "addr:postcode":"2930",
    "addr:street":"Miksebeekstraat",
    "iso:country":"BE",
    "sg:address":"Miksebeekstraat 63",
    "sg:city":"Brasschaat",
    "sg:orig_category":"Slagers",
    "sg:phone":"+32 3 651 86 56",
    "sg:postcode":"2930",
    "sg:province":"Antwerpen",
    "wof:name":"Robert Franckaerts",
    "wof:placetype":"venue"
},
  "geometry": {"coordinates":[4.5079698563,51.2953567505],"type":"Point"}
}