{
  "type": "Feature",
  "properties": {
    "iso:country":"BE",
    "sg:address":"Nijverheidsln 33",
    "sg:city":"Diest",
    "sg:classifiers":[
        {
            "category":"Home & Garden",
            "subcategory":"Furniture",
            "type":"Retail Goods"
        }
    ],
    "sg:phone":"+32 13 35 10 60",
    "sg:postcode":"3290",
    "sg:province":"Vlaams-Brabant",
    "sg:tags":[
        "household",
        "wood"
    ],
    "wof:name":"Jasaco Nv",
    "wof:placetype":"venue"
},
  "geometry": {"coordinates":[5.0374999046,50.987991333],"type":"Point"}
}