{
  "type": "Feature",
  "properties": {
    "iso:country":"BE",
    "sg:address":"Rue Pierre Hap Lemaitre 26",
    "sg:city":"Etterbeek/etterbeek",
    "sg:orig_category":"Plomberie, chauffage and installations sanitaires",
    "sg:phone":"+32 2 649 08 29",
    "sg:postcode":"1040",
    "sg:province":"Bruxelles-Capitale",
    "wof:name":"Michel Trovato",
    "wof:placetype":"venue"
},
  "geometry": {"coordinates":[4.3864388466,50.8266181946],"type":"Point"}
}