{
  "type": "Feature",
  "properties": {
    "iso:country":"BE",
    "sg:address":"Urselweg 20",
    "sg:city":"Aalter",
    "sg:classifiers":[
        {
            "category":"Wholesale",
            "subcategory":"Farm Supplies",
            "type":"Manufacturing & Wholesale Goods"
        }
    ],
    "sg:phone":"+32 9 374 25 09",
    "sg:postcode":"9880",
    "sg:province":"Oost-Vlaanderen",
    "sg:tags":[
        "machine",
        "agricoles",
        "mat\u00e9riel",
        "gr"
    ],
    "wof:name":"Achiel Vermeire",
    "wof:placetype":"venue"
},
  "geometry": {"coordinates":[3.4474480152,51.1154136658],"type":"Point"}
}