{
  "type": "Feature",
  "properties": {
    "iso:country":"BE",
    "sg:address":"Josaphatstraat 56",
    "sg:city":"Schaarbeek/schaerbeek",
    "sg:orig_category":"Installatie van houten of kunststof schrijnwerk",
    "sg:phone":"+32 2 201 57 65",
    "sg:postcode":"1030",
    "sg:province":"Bruxelles-Capitale",
    "wof:name":"Ab Team Windows Firatpen",
    "wof:placetype":"venue"
},
  "geometry": {"coordinates":[4.3731760979,50.8570365906],"type":"Point"}
}