{
  "type": "Feature",
  "properties": {
    "iso:country":"BE",
    "sg:address":"Boulevard Piercot 33",
    "sg:city":"Li\u00c8ge",
    "sg:orig_category":"Avocats and conseillers juridiques",
    "sg:phone":"+32 4 221 39 66",
    "sg:postcode":"4000",
    "sg:province":"Li\u00e8ge",
    "wof:name":"Thierry Dessard",
    "wof:placetype":"venue"
},
  "geometry": {"coordinates":[5.569876194,50.6352653503],"type":"Point"}
}