{
  "type": "Feature",
  "properties": {
    "addr:full":"Rue Du W\u00e9rihet 22 Chaudfontaine (beaufays) Li\u00e8ge 4052",
    "addr:housenumber":"22",
    "addr:postcode":"4052",
    "addr:street":"Rue Du We\u0301Rihet;Beaufays",
    "iso:country":"BE",
    "sg:address":"Rue Du W\u00e9rihet 22",
    "sg:city":"Chaudfontaine (beaufays)",
    "sg:classifiers":[
        {
            "category":"Building & Trades",
            "subcategory":"Plumbing",
            "type":"Services"
        }
    ],
    "sg:phone":"+32 4 368 53 56",
    "sg:postcode":"4052",
    "sg:province":"Li\u00e8ge",
    "sg:tags":[
        "pipe",
        "drain",
        "unblocking"
    ],
    "wof:name":"Fisenne J-n",
    "wof:placetype":"venue"
},
  "geometry": {"coordinates":[5.6392202377,50.5586051941],"type":"Point"}
}