{
  "type": "Feature",
  "properties": {
    "iso:country":"BE",
    "sg:address":"Rijksweg 284",
    "sg:city":"Wielsbeke",
    "sg:orig_category":"Textiel",
    "sg:phone":"+32 56 66 77 75",
    "sg:postcode":"8710",
    "sg:province":"West-Vlaanderen",
    "wof:name":"Huis Ladies",
    "wof:placetype":"venue"
},
  "geometry": {"coordinates":[3.375041008,50.9082717896],"type":"Point"}
}