{
  "type": "Feature",
  "properties": {
    "addr:full":"Louis Van Kerckhovenstraat 20 Heist-op-den-berg Antwerpen 2220",
    "addr:housenumber":"20",
    "addr:postcode":"2220",
    "addr:street":"Louis Van Kerckhovenstraat",
    "iso:country":"BE",
    "sg:address":"Louis Van Kerckhovenstraat 20",
    "sg:city":"Heist-op-den-berg",
    "sg:classifiers":[
        {
            "category":"Manufacturing",
            "subcategory":"Electronics",
            "type":"Manufacturing & Wholesale Goods"
        }
    ],
    "sg:phone":"+32 15 25 12 73",
    "sg:postcode":"2220",
    "sg:province":"Antwerpen",
    "sg:tags":[
        "oven",
        "microwave"
    ],
    "wof:name":"Van Weert Service Bvba",
    "wof:placetype":"venue"
},
  "geometry": {"coordinates":[4.7002778053,51.0752372742],"type":"Point"}
}