{
  "type": "Feature",
  "properties": {
    "addr:full":"Rue Winston Churchill 286 Courcelles Hainaut 6180",
    "addr:housenumber":"286",
    "addr:postcode":"6180",
    "addr:street":"Rue Winston Churchill",
    "iso:country":"BE",
    "sg:address":"Rue Winston Churchill 286",
    "sg:city":"Courcelles",
    "sg:classifiers":[
        {
            "category":"Manufacturing",
            "subcategory":"Motor Vehicles & Parts",
            "type":"Manufacturing & Wholesale Goods"
        }
    ],
    "sg:phone":"+32 71 46 24 90",
    "sg:postcode":"6180",
    "sg:province":"Hainaut",
    "sg:tags":[
        "exhaust",
        "system"
    ],
    "wof:name":"Racing Sport Churchill",
    "wof:placetype":"venue"
},
  "geometry": {"coordinates":[4.3943171501,50.4630393982],"type":"Point"}
}