{
  "type": "Feature",
  "properties": {
    "iso:country":"BE",
    "sg:address":"Gastelstraat 20",
    "sg:city":"Waarschoot",
    "sg:orig_category":"Rundveehouders",
    "sg:phone":"+32 9 377 30 18",
    "sg:postcode":"9950",
    "sg:province":"Oost-Vlaanderen",
    "wof:name":"Daniel De Kesel",
    "wof:placetype":"venue"
},
  "geometry": {"coordinates":[3.6117610931,51.146774292],"type":"Point"}
}