{
  "type": "Feature",
  "properties": {
    "addr:full":"Chauss\u00c9e De Vleurgat 73 Elsene/ixelles Bruxelles-Capitale 1050",
    "addr:housenumber":"73",
    "addr:postcode":"1050",
    "addr:street":"Chausse\u0301E De Vleurgat",
    "iso:country":"BE",
    "sg:address":"Chauss\u00c9e De Vleurgat 73",
    "sg:city":"Elsene/ixelles",
    "sg:orig_category":"V\u00e9hicules automobiles. Entretien and r\u00e9parations de voitures",
    "sg:phone":"+32 2 640 91 30",
    "sg:postcode":"1050",
    "sg:province":"Bruxelles-Capitale",
    "wof:name":"Carrosserie Belgica",
    "wof:placetype":"venue"
},
  "geometry": {"coordinates":[4.3691740036,50.8254776001],"type":"Point"}
}