{
  "type": "Feature",
  "properties": {
    "iso:country":"BE",
    "sg:address":"Rue Provinciale 66",
    "sg:city":"Herstal",
    "sg:orig_category":"Artsen and specialisten",
    "sg:phone":"+32 4 278 66 51",
    "sg:postcode":"4042",
    "sg:province":"Li\u00e8ge",
    "wof:name":"Alain Wilmont",
    "wof:placetype":"venue"
},
  "geometry": {"coordinates":[5.5649881363,50.6940727234],"type":"Point"}
}