{
  "type": "Feature",
  "properties": {
    "addr:full":"Rue Principale 19 Fexhe-le-haut-clocher Li\u00e8ge 4347",
    "addr:housenumber":"19",
    "addr:postcode":"4347",
    "addr:street":"Rue Principale",
    "iso:country":"BE",
    "sg:address":"Rue Principale 19",
    "sg:city":"Fexhe-le-haut-clocher",
    "sg:classifiers":[
        {
            "category":"Arena",
            "subcategory":"Sports Club",
            "type":"Entertainment"
        }
    ],
    "sg:phone":"+32 4 250 22 24",
    "sg:postcode":"4347",
    "sg:province":"Li\u00e8ge",
    "sg:tags":[
        "de"
    ],
    "wof:name":"Y.s.c.f.",
    "wof:placetype":"venue"
},
  "geometry": {"coordinates":[5.3842658997,50.6623306274],"type":"Point"}
}