{
  "type": "Feature",
  "properties": {
    "addr:full":"Tramstraat 8 Destelbergen Oost-Vlaanderen 9070",
    "addr:housenumber":"8",
    "addr:postcode":"9070",
    "addr:street":"Tramstraat",
    "iso:country":"BE",
    "sg:address":"Tramstraat 8",
    "sg:city":"Destelbergen",
    "sg:orig_category":"Installation \u00e9lectrique r\u00e9sidentielle. Electrom\u00e9nager, t\u00e9l\u00e9visions and radios",
    "sg:phone":"+32 9 230 80 10",
    "sg:postcode":"9070",
    "sg:province":"Oost-Vlaanderen",
    "wof:name":"A. Van Der Straeten",
    "wof:placetype":"venue"
},
  "geometry": {"coordinates":[3.8011610508,51.0294570923],"type":"Point"}
}