{
  "type": "Feature",
  "properties": {
    "addr:full":"Grand\u00b4place 16 Chimay Hainaut 6460",
    "addr:housenumber":"16",
    "addr:postcode":"6460",
    "addr:street":"Grand\u00b4Place",
    "iso:country":"BE",
    "sg:address":"Grand\u00b4place 16",
    "sg:city":"Chimay",
    "sg:classifiers":[
        {
            "category":"Restaurant",
            "type":"Food & Drink"
        }
    ],
    "sg:phone":"+32 60 21 55 66",
    "sg:postcode":"6460",
    "sg:province":"Hainaut",
    "wof:name":"La Vache Gourmande",
    "wof:placetype":"venue"
},
  "geometry": {"coordinates":[4.3148198128,50.0489082336],"type":"Point"}
}