{
  "type": "Feature",
  "properties": {
    "addr:full":"Aarlenstraat 92 Bruxelles (etterbeek) Bruxelles-Capitale 1040",
    "addr:housenumber":"92",
    "addr:postcode":"1040",
    "addr:street":"Aarlenstraat",
    "iso:country":"BE",
    "sg:address":"Aarlenstraat 92",
    "sg:city":"Bruxelles (etterbeek)",
    "sg:classifiers":[
        {
            "category":"Professional",
            "subcategory":"Lawyer & Legal Services",
            "type":"Services"
        }
    ],
    "sg:phone":"+32 2 282 00 60",
    "sg:postcode":"1040",
    "sg:province":"Bruxelles-Capitale",
    "wof:name":"Cornet Ivan",
    "wof:placetype":"venue"
},
  "geometry": {"coordinates":[4.3736791611,50.8426628113],"type":"Point"}
}