{
  "type": "Feature",
  "properties": {
    "iso:country":"BE",
    "sg:address":"Gippershovenstraat 87",
    "sg:city":"Sint-truiden",
    "sg:orig_category":"Diensten voor huisdieren",
    "sg:phone":"+32 12 74 49 42",
    "sg:postcode":"3800",
    "sg:province":"Limburg",
    "wof:name":"Hondenkapsalon Diane",
    "wof:placetype":"venue"
},
  "geometry": {"coordinates":[5.2787299156,50.8391189575],"type":"Point"}
}