{
  "type": "Feature",
  "properties": {
    "addr:full":"Mechelse Steenweg 34-7 Antwerpen Antwerpen 2018",
    "addr:housenumber":"34-7",
    "addr:postcode":"2018",
    "addr:street":"Steenweg",
    "iso:country":"BE",
    "sg:address":"Mechelse Steenweg 34-7",
    "sg:city":"Antwerpen",
    "sg:classifiers":[
        {
            "category":"Social Services",
            "subcategory":"Job Training",
            "type":"Services"
        }
    ],
    "sg:phone":"+32 3 242 84 84",
    "sg:postcode":"2018",
    "sg:province":"Antwerpen",
    "sg:tags":[
        "personnel",
        "-selection",
        "recruitment"
    ],
    "wof:name":"Officeteam Select",
    "wof:placetype":"venue"
},
  "geometry": {"coordinates":[4.4077467918,51.2100524902],"type":"Point"}
}