{
  "type": "Feature",
  "properties": {
    "addr:full":"Zeedijk 150 Blankenberge West-Vlaanderen 8370",
    "addr:housenumber":"150",
    "addr:postcode":"8370",
    "addr:street":"Zeedijk",
    "iso:country":"BE",
    "sg:address":"Zeedijk 150",
    "sg:city":"Blankenberge",
    "sg:orig_category":"Kansspelen Restaurants",
    "sg:phone":"+32 50 43 20 20",
    "sg:postcode":"8370",
    "sg:province":"West-Vlaanderen",
    "wof:name":"Casino Blankenberge",
    "wof:placetype":"venue"
},
  "geometry": {"coordinates":[3.1295349598,51.3166618347],"type":"Point"}
}