{
  "type": "Feature",
  "properties": {
    "addr:full":"Tervurenlaan 133 Oudergem/auderghem Bruxelles-Capitale 1160",
    "addr:housenumber":"133",
    "addr:postcode":"1160",
    "addr:street":"Tervurenlaan;/",
    "iso:country":"BE",
    "sg:address":"Tervurenlaan 133",
    "sg:city":"Oudergem/auderghem",
    "sg:orig_category":"Diverse bedrijfsbeheeradviesbureaus",
    "sg:phone":"+32 2 675 39 42",
    "sg:postcode":"1160",
    "sg:province":"Bruxelles-Capitale",
    "wof:name":"C D L Strategy",
    "wof:placetype":"venue"
},
  "geometry": {"coordinates":[4.4365749359,50.8164863586],"type":"Point"}
}