{
  "type": "Feature",
  "properties": {
    "iso:country":"BE",
    "sg:address":"Rue De La Duve 1",
    "sg:city":"Sambreville",
    "sg:orig_category":"Dakwerken",
    "sg:phone":"+32 71 77 42 60",
    "sg:postcode":"5060",
    "sg:province":"Namur",
    "wof:name":"Pol Revillod",
    "wof:placetype":"venue"
},
  "geometry": {"coordinates":[4.6285200119,50.4448738098],"type":"Point"}
}