{
  "type": "Feature",
  "properties": {
    "iso:country":"BE",
    "sg:address":"Jozef De Bomstraat 63",
    "sg:city":"Antwerpen",
    "sg:orig_category":"Mat\u00e9riaux de construction Gr",
    "sg:phone":"+32 3 237 71 71",
    "sg:postcode":"2018",
    "sg:province":"Antwerpen",
    "wof:name":"Delta Associates",
    "wof:placetype":"venue"
},
  "geometry": {"coordinates":[4.4065799713,51.2062110901],"type":"Point"}
}