{
  "type": "Feature",
  "properties": {
    "addr:full":"Rue Du Chalet 1 Havelange (barvaux-condroz) Namur 5370",
    "addr:housenumber":"1",
    "addr:postcode":"5370",
    "addr:street":"Rue Du Chalet",
    "iso:country":"BE",
    "sg:address":"Rue Du Chalet 1",
    "sg:city":"Havelange (barvaux-condroz)",
    "sg:classifiers":[
        {
            "category":"Professional",
            "subcategory":"Lawyer & Legal Services",
            "type":"Services"
        }
    ],
    "sg:phone":"+32 83 61 33 87",
    "sg:postcode":"5370",
    "sg:province":"Namur",
    "wof:name":"Delloye Bernard",
    "wof:placetype":"venue"
},
  "geometry": {"coordinates":[5.284142971,50.3346672058],"type":"Point"}
}