{
  "type": "Feature",
  "properties": {
    "addr:full":"Chauss\u00c9e De Vleurgat 182 Brussel/bruxelles Bruxelles-Capitale 1000",
    "addr:housenumber":"182",
    "addr:postcode":"1000",
    "addr:street":"Chausse\u0301E De Vleurgat;/",
    "iso:country":"BE",
    "sg:address":"Chauss\u00c9e De Vleurgat 182",
    "sg:city":"Brussel/bruxelles",
    "sg:orig_category":"Enregistrements sonores",
    "sg:phone":"+32 2 644 18 88",
    "sg:postcode":"1000",
    "sg:province":"Bruxelles-Capitale",
    "wof:name":"On Air",
    "wof:placetype":"venue"
},
  "geometry": {"coordinates":[4.3667769432,50.8220062256],"type":"Point"}
}