{
  "type": "Feature",
  "properties": {
    "iso:country":"BE",
    "sg:address":"Bredabaan 626",
    "sg:city":"Brasschaat",
    "sg:classifiers":[
        {
            "category":"Retail",
            "subcategory":"Car Wash",
            "type":"Services"
        }
    ],
    "sg:phone":"+32 3 633 24 24",
    "sg:postcode":"2930",
    "sg:province":"Antwerpen",
    "sg:tags":[
        "automobile",
        "washing",
        "-",
        "truck"
    ],
    "wof:name":"American Soft Car Wash-felix Car Service",
    "wof:placetype":"venue"
},
  "geometry": {"coordinates":[4.5091300011,51.309753418],"type":"Point"}
}