{
  "type": "Feature",
  "properties": {
    "addr:full":"Sint-damiaanstraat 141 Wommelgem Antwerpen 2160",
    "addr:housenumber":"141",
    "addr:postcode":"2160",
    "addr:street":"Sint-Damiaanstraat",
    "iso:country":"BE",
    "sg:address":"Sint-damiaanstraat 141",
    "sg:city":"Wommelgem",
    "sg:orig_category":"Verplichte sociale verzekeringen",
    "sg:phone":"+32 3 354 19 82",
    "sg:postcode":"2160",
    "sg:province":"Antwerpen",
    "wof:name":"Vlaams Neutraal Ziekenf.",
    "wof:placetype":"venue"
},
  "geometry": {"coordinates":[4.5179028511,51.1990127563],"type":"Point"}
}