{
  "type": "Feature",
  "properties": {
    "addr:full":"Kloosterstraat 62 Antwerpen Antwerpen 2000",
    "addr:housenumber":"62",
    "addr:postcode":"2000",
    "addr:street":"Kloosterstraat",
    "iso:country":"BE",
    "sg:address":"Kloosterstraat 62",
    "sg:city":"Antwerpen",
    "sg:classifiers":[
        {
            "category":"Shopping",
            "subcategory":"Discount & Variety Stores",
            "type":"Retail Goods"
        }
    ],
    "sg:phone":"+32 3 248 33 42",
    "sg:postcode":"2000",
    "sg:province":"Antwerpen",
    "sg:tags":[
        "shop",
        "clearers",
        "curiosity",
        "furniture"
    ],
    "wof:name":"De Laere P",
    "wof:placetype":"venue"
},
  "geometry": {"coordinates":[4.3945951462,51.2156677246],"type":"Point"}
}