{
  "type": "Feature",
  "properties": {
    "iso:country":"BE",
    "sg:address":"Monnikenwerve 194",
    "sg:city":"Brugge",
    "sg:orig_category":"Non-Classified Establishments",
    "sg:phone":"+32 50 31 20 04",
    "sg:postcode":"8000",
    "sg:province":"West-Vlaanderen",
    "wof:name":"Joka Bvba",
    "wof:placetype":"venue"
},
  "geometry": {"coordinates":[3.2046151161,51.2450294495],"type":"Point"}
}