{
  "type": "Feature",
  "properties": {
    "addr:full":"Toekomstlaan 28 Herentals Antwerpen 2200",
    "addr:housenumber":"28",
    "addr:postcode":"2200",
    "addr:street":"Toekomstlaan",
    "iso:country":"BE",
    "sg:address":"Toekomstlaan 28",
    "sg:city":"Herentals",
    "sg:orig_category":"Transports routiers de marchandises",
    "sg:phone":"+32 14 21 22 68",
    "sg:postcode":"2200",
    "sg:province":"Antwerpen",
    "wof:name":"T.l.h.",
    "wof:placetype":"venue"
},
  "geometry": {"coordinates":[4.8052191734,51.1624183655],"type":"Point"}
}