{
  "type": "Feature",
  "properties": {
    "addr:full":"Monnikendreef 21 Zoersel Antwerpen 2980",
    "addr:housenumber":"21",
    "addr:postcode":"2980",
    "addr:street":"Monnikendreef",
    "iso:country":"BE",
    "sg:address":"Monnikendreef 21",
    "sg:city":"Zoersel",
    "sg:orig_category":"Woningbouw",
    "sg:phone":"+32 3 384 28 09",
    "sg:postcode":"2980",
    "sg:province":"Antwerpen",
    "wof:name":"Alfino",
    "wof:placetype":"venue"
},
  "geometry": {"coordinates":[4.6936597824,51.2629394531],"type":"Point"}
}