{
  "type": "Feature",
  "properties": {
    "iso:country":"BE",
    "sg:address":"Arthur Roelandtstraat 11",
    "sg:city":"Moeskroen/mouscron",
    "sg:orig_category":"Fietsen",
    "sg:phone":"+32 56 48 90 09",
    "sg:postcode":"7711",
    "sg:province":"Hainaut",
    "wof:name":"Cycles Decruynaere",
    "wof:placetype":"venue"
},
  "geometry": {"coordinates":[3.3043079376,50.7277984619],"type":"Point"}
}