{
  "type": "Feature",
  "properties": {
    "iso:country":"BE",
    "sg:address":"Toekomststraat 67",
    "sg:city":"Machelen",
    "sg:classifiers":[
        {
            "category":"Arena",
            "subcategory":"Sports Club",
            "type":"Entertainment"
        }
    ],
    "sg:phone":"+32 2 251 20 51",
    "sg:postcode":"1830",
    "sg:province":"Vlaams-Brabant",
    "sg:tags":[
        "de"
    ],
    "wof:name":"T.c. Machelen-diegem",
    "wof:placetype":"venue"
},
  "geometry": {"coordinates":[4.4392800331,50.9103546143],"type":"Point"}
}