{
  "type": "Feature",
  "properties": {
    "iso:country":"BE",
    "sg:address":"Donystraat 10",
    "sg:city":"Tienen",
    "sg:orig_category":"Diverse organisaties and verenigingen",
    "sg:phone":"+32 16 82 38 64",
    "sg:postcode":"3300",
    "sg:province":"Vlaams-Brabant",
    "wof:name":"Jeugdhuis De Bleek",
    "wof:placetype":"venue"
},
  "geometry": {"coordinates":[4.9429101944,50.8063430786],"type":"Point"}
}