{
  "type": "Feature",
  "properties": {
    "addr:full":"Groenpl 5 Zelzate Oost-Vlaanderen 9060",
    "addr:housenumber":"5",
    "addr:postcode":"9060",
    "addr:street":"Groenpl",
    "iso:country":"BE",
    "sg:address":"Groenpl 5",
    "sg:city":"Zelzate",
    "sg:classifiers":[
        {
            "category":"Banks & Credit Unions",
            "subcategory":"Bank",
            "type":"Services"
        }
    ],
    "sg:phone":"+32 9 343 07 88",
    "sg:postcode":"9060",
    "sg:province":"Oost-Vlaanderen",
    "wof:name":"Banque Bruxelles Lambert Sa",
    "wof:placetype":"venue"
},
  "geometry": {"coordinates":[3.7943940163,51.1965026855],"type":"Point"}
}