{
  "type": "Feature",
  "properties": {
    "addr:full":"Romershovenstraat 87 Hoeselt Limburg 3730",
    "addr:housenumber":"87",
    "addr:postcode":"3730",
    "addr:street":"Romershovenstraat",
    "iso:country":"BE",
    "sg:address":"Romershovenstraat 87",
    "sg:city":"Hoeselt",
    "sg:orig_category":"V\u00eatements pour Hommes. Location de v\u00eatements, chaussures and textiles",
    "sg:phone":"+32 89 51 41 10",
    "sg:postcode":"3730",
    "sg:province":"Limburg",
    "wof:name":"Kleding Baer",
    "wof:placetype":"venue"
},
  "geometry": {"coordinates":[5.4615898132,50.8511390686],"type":"Point"}
}