{
  "type": "Feature",
  "properties": {
    "iso:country":"BE",
    "sg:address":"Sloepstraat 1",
    "sg:city":"Gent",
    "sg:classifiers":[
        {
            "category":"Utilities",
            "subcategory":"Refuse",
            "type":"Services"
        }
    ],
    "sg:phone":"+32 9 253 87 15",
    "sg:postcode":"9000",
    "sg:province":"Oost-Vlaanderen",
    "sg:tags":[
        "boiler",
        "-",
        "heating",
        "steam"
    ],
    "wof:name":"Ateliers Mahy Fr\u00e8res",
    "wof:placetype":"venue"
},
  "geometry": {"coordinates":[3.7211999893,51.0883216858],"type":"Point"}
}