{
  "type": "Feature",
  "properties": {
    "addr:full":"Rue Auguste Hainaut 34 Jette Bruxelles-Capitale 1090",
    "addr:housenumber":"34",
    "addr:postcode":"1090",
    "addr:street":"Rue Auguste Hainaut",
    "iso:country":"BE",
    "sg:address":"Rue Auguste Hainaut 34",
    "sg:city":"Jette",
    "sg:orig_category":"Salons de coiffure. Centres de relaxation and bien-\u00eatre",
    "sg:phone":"+32 2 425 45 54",
    "sg:postcode":"1090",
    "sg:province":"Bruxelles-Capitale",
    "wof:name":"Jacques Meurisse Coiffure",
    "wof:placetype":"venue"
},
  "geometry": {"coordinates":[4.3356399536,50.8684158325],"type":"Point"}
}