{
  "type": "Feature",
  "properties": {
    "iso:country":"BE",
    "sg:address":"Rue De Gosselies 62",
    "sg:city":"Courcelles",
    "sg:orig_category":"V\u00eatements",
    "sg:phone":"+32 71 45 35 15",
    "sg:postcode":"6183",
    "sg:province":"Hainaut",
    "wof:name":"Atelier De Marie-claire",
    "wof:placetype":"venue"
},
  "geometry": {"coordinates":[4.3397731781,50.4629402161],"type":"Point"}
}