{
  "type": "Feature",
  "properties": {
    "iso:country":"BE",
    "sg:address":"De Gheeststraat 1a",
    "sg:city":"Aalst",
    "sg:classifiers":[
        {
            "category":"Home & Garden",
            "subcategory":"Home Furnishings",
            "type":"Retail Goods"
        }
    ],
    "sg:phone":"+32 53 78 15 85",
    "sg:postcode":"9300",
    "sg:province":"Oost-Vlaanderen",
    "sg:tags":[
        "-",
        "furniture"
    ],
    "wof:name":"Meganck Way Of Living",
    "wof:placetype":"venue"
},
  "geometry": {"coordinates":[4.0458278656,50.9346580505],"type":"Point"}
}