{
  "type": "Feature",
  "properties": {
    "addr:full":"Mechelsestraat 88 Londerzeel Vlaams-Brabant 1840",
    "addr:housenumber":"88",
    "addr:postcode":"1840",
    "addr:street":"Mechelsestraat",
    "iso:country":"BE",
    "sg:address":"Mechelsestraat 88",
    "sg:city":"Londerzeel",
    "sg:orig_category":"M\u00e9decins and sp\u00e9cialistes",
    "sg:phone":"+32 52 30 27 92",
    "sg:postcode":"1840",
    "sg:province":"Vlaams-Brabant",
    "wof:name":"Daniella Van Derheyden",
    "wof:placetype":"venue"
},
  "geometry": {"coordinates":[4.3078169823,51.0047225952],"type":"Point"}
}