{
  "type": "Feature",
  "properties": {
    "addr:full":"Van Aelbrouckstraat 15 Zottegem Oost-Vlaanderen 9620",
    "addr:housenumber":"15",
    "addr:postcode":"9620",
    "addr:street":"Aelbrouckstraat",
    "iso:country":"BE",
    "sg:address":"Van Aelbrouckstraat 15",
    "sg:city":"Zottegem",
    "sg:classifiers":[
        {
            "category":"Cafe",
            "type":"Food & Drink"
        }
    ],
    "sg:phone":"+32 9 360 60 28",
    "sg:postcode":"9620",
    "sg:province":"Oost-Vlaanderen",
    "sg:tags":[
        "snack-bars"
    ],
    "wof:name":"Cheers",
    "wof:placetype":"venue"
},
  "geometry": {"coordinates":[3.8135418892,50.8676719666],"type":"Point"}
}