{
  "type": "Feature",
  "properties": {
    "addr:full":"Steenvoordestraat 56 Poperinge West-Vlaanderen 8978",
    "addr:housenumber":"56",
    "addr:postcode":"8978",
    "addr:street":"Steenvoordestraat",
    "iso:country":"BE",
    "sg:address":"Steenvoordestraat 56",
    "sg:city":"Poperinge",
    "sg:orig_category":"Traitements param\u00e9dicaux",
    "sg:phone":"+32 57 38 87 35",
    "sg:postcode":"8978",
    "sg:province":"West-Vlaanderen",
    "wof:name":"Anne Vuylsteke",
    "wof:placetype":"venue"
},
  "geometry": {"coordinates":[2.6206049919,50.8592453003],"type":"Point"}
}