{
  "type": "Feature",
  "properties": {
    "iso:country":"BE",
    "sg:address":"Zomerstraat-oost 2",
    "sg:city":"Beernem",
    "sg:orig_category":"Installatie van houten of kunststof schrijnwerk",
    "sg:phone":"+32 50 36 00 23",
    "sg:postcode":"8730",
    "sg:province":"West-Vlaanderen",
    "wof:name":"Eric Roels",
    "wof:placetype":"venue"
},
  "geometry": {"coordinates":[3.3310859203,51.1941604614],"type":"Point"}
}