{
  "type": "Feature",
  "properties": {
    "addr:full":"Sint-pieterssteenweg 193 Etterbeek/etterbeek Bruxelles-Capitale 1040",
    "addr:housenumber":"193",
    "addr:postcode":"1040",
    "addr:street":"Sint-Pieterssteenweg",
    "iso:country":"BE",
    "sg:address":"Sint-pieterssteenweg 193",
    "sg:city":"Etterbeek/etterbeek",
    "sg:orig_category":"Openbare bibliotheken and archieven",
    "sg:phone":"+32 2 735 05 86",
    "sg:postcode":"1040",
    "sg:province":"Bruxelles-Capitale",
    "wof:name":"Biblioth\u00c8que Publique",
    "wof:placetype":"venue"
},
  "geometry": {"coordinates":[4.389485836,50.8362503052],"type":"Point"}
}