{
  "type": "Feature",
  "properties": {
    "addr:full":"Gasstraat 21 Geel Antwerpen 2440",
    "addr:housenumber":"21",
    "addr:postcode":"2440",
    "addr:street":"Gasstraat",
    "iso:country":"BE",
    "sg:address":"Gasstraat 21",
    "sg:city":"Geel",
    "sg:classifiers":[
        {
            "category":"Transit Center",
            "subcategory":"Freight",
            "type":"Transportation"
        }
    ],
    "sg:phone":"+32 14 58 78 43",
    "sg:postcode":"2440",
    "sg:province":"Antwerpen",
    "sg:tags":[
        "-",
        "tape",
        "adhesive"
    ],
    "wof:name":"Vromans Industrie Bvba",
    "wof:placetype":"venue"
},
  "geometry": {"coordinates":[4.9829421043,51.1777687073],"type":"Point"}
}