{
  "type": "Feature",
  "properties": {
    "iso:country":"BE",
    "sg:address":"Ijzerstraat 57",
    "sg:city":"Tervuren (duisburg)",
    "sg:classifiers":[
        {
            "category":"Wholesale",
            "subcategory":"Fruits & Vegetables",
            "type":"Manufacturing & Wholesale Goods"
        }
    ],
    "sg:phone":"+32 2 687 72 64",
    "sg:postcode":"3080",
    "sg:province":"Vlaams-Brabant",
    "sg:tags":[
        "whol",
        "-"
    ],
    "wof:name":"G T R",
    "wof:placetype":"venue"
},
  "geometry": {"coordinates":[4.5448770523,50.8036575317],"type":"Point"}
}