{
  "type": "Feature",
  "properties": {
    "addr:full":"Boulevard De La Sauveniere 94 Li\u00e8ge Li\u00e8ge 4000",
    "addr:housenumber":"94",
    "addr:postcode":"4000",
    "addr:street":"Boulevard De La Sauveniere",
    "iso:country":"BE",
    "sg:address":"Boulevard De La Sauveniere 94",
    "sg:city":"Li\u00e8ge",
    "sg:classifiers":[
        {
            "category":"Professional",
            "subcategory":"Employment Agencies",
            "type":"Services"
        }
    ],
    "sg:phone":"+32 4 223 25 35",
    "sg:postcode":"4000",
    "sg:province":"Li\u00e8ge",
    "sg:tags":[
        "personnel",
        "temporary"
    ],
    "wof:name":"Sicom Interim S.a.",
    "wof:placetype":"venue"
},
  "geometry": {"coordinates":[5.5655431747,50.6430435181],"type":"Point"}
}