{
  "type": "Feature",
  "properties": {
    "iso:country":"BE",
    "sg:address":"Watering 12",
    "sg:city":"Arendonk",
    "sg:orig_category":"Eleveurs de bovins. Eleveurs and marchands de porcs",
    "sg:phone":"+32 14 67 84 12",
    "sg:postcode":"2370",
    "sg:province":"Antwerpen",
    "wof:name":"Marcel Laurijssen",
    "wof:placetype":"venue"
},
  "geometry": {"coordinates":[5.1253418922,51.3118782043],"type":"Point"}
}