{
  "type": "Feature",
  "properties": {
    "addr:full":"Gendarmeriestraat 63 Vilvoorde Vlaams-Brabant 1800",
    "addr:housenumber":"63",
    "addr:postcode":"1800",
    "addr:street":"Gendarmeriestraat",
    "iso:country":"BE",
    "sg:address":"Gendarmeriestraat 63",
    "sg:city":"Vilvoorde",
    "sg:orig_category":"M\u00e9decins and sp\u00e9cialistes",
    "sg:phone":"+32 2 251 68 60",
    "sg:postcode":"1800",
    "sg:province":"Vlaams-Brabant",
    "wof:name":"Consultatiebur.jonge Kind",
    "wof:placetype":"venue"
},
  "geometry": {"coordinates":[4.4177699089,50.9285812378],"type":"Point"}
}