{
  "type": "Feature",
  "properties": {
    "addr:full":"\u00b4s Gravenstraat 197i Nazareth Oost-Vlaanderen 9810",
    "addr:housenumber":"197i",
    "addr:postcode":"9810",
    "addr:street":"Gravenstraat",
    "iso:country":"BE",
    "sg:address":"\u00b4s Gravenstraat 197i",
    "sg:city":"Nazareth",
    "sg:orig_category":"Installation \u00e9lectrique r\u00e9sidentielle",
    "sg:phone":"+32 9 385 69 54",
    "sg:postcode":"9810",
    "sg:province":"Oost-Vlaanderen",
    "wof:name":"Delagrense Johny",
    "wof:placetype":"venue"
},
  "geometry": {"coordinates":[3.593118906,50.9481430054],"type":"Point"}
}