{
  "type": "Feature",
  "properties": {
    "iso:country":"BE",
    "sg:address":"President Kennedypark 37",
    "sg:city":"Kortrijk",
    "sg:orig_category":"Advocaten and juridische adviseurs",
    "sg:phone":"+32 56 23 51 11",
    "sg:postcode":"8500",
    "sg:province":"West-Vlaanderen",
    "wof:name":"Bart Vanschoebeke",
    "wof:placetype":"venue"
},
  "geometry": {"coordinates":[3.2745509148,50.7990951538],"type":"Point"}
}