{
  "type": "Feature",
  "properties": {
    "iso:country":"BE",
    "sg:address":"Moli\u00c8relaan 264",
    "sg:city":"Ukkel/uccle",
    "sg:orig_category":"Artsen and specialisten",
    "sg:phone":"+32 2 344 25 35",
    "sg:postcode":"1180",
    "sg:province":"Bruxelles-Capitale",
    "wof:name":"Philippe Van De Kerckhove",
    "wof:placetype":"venue"
},
  "geometry": {"coordinates":[4.3584618568,50.8155975342],"type":"Point"}
}