{
  "type": "Feature",
  "properties": {
    "addr:full":"Rue Du Finist\u00e8re 24 Bruxelles Bruxelles-Capitale 1000",
    "addr:housenumber":"24",
    "addr:postcode":"1000",
    "addr:street":"Rue Du Finiste\u0300Re",
    "iso:country":"BE",
    "sg:address":"Rue Du Finist\u00e8re 24",
    "sg:city":"Bruxelles",
    "sg:classifiers":[
        {
            "category":"Professional",
            "subcategory":"Testing Lab",
            "type":"Services"
        }
    ],
    "sg:phone":"+32 2 218 59 76",
    "sg:postcode":"1000",
    "sg:province":"Bruxelles-Capitale",
    "sg:tags":[
        "chemist"
    ],
    "wof:name":"Finistere (du)",
    "wof:placetype":"venue"
},
  "geometry": {"coordinates":[4.3555111885,50.8528251648],"type":"Point"}
}