{
  "type": "Feature",
  "properties": {
    "iso:country":"BE",
    "sg:address":"Heuvenstraat 17",
    "sg:city":"Zonhoven",
    "sg:classifiers":[
        {
            "category":"Bakery",
            "type":"Food & Drink"
        }
    ],
    "sg:phone":"+32 11 81 68 10",
    "sg:postcode":"3520",
    "sg:province":"Limburg",
    "sg:tags":[
        "confectioner",
        "baker"
    ],
    "wof:name":"Schoofs L",
    "wof:placetype":"venue"
},
  "geometry": {"coordinates":[5.3676671982,50.9898948669],"type":"Point"}
}