{
  "type": "Feature",
  "properties": {
    "addr:full":"Plaats 22ba Menen West-Vlaanderen 8930",
    "addr:housenumber":"22ba",
    "addr:postcode":"8930",
    "addr:street":"Plaats",
    "iso:country":"BE",
    "sg:address":"Plaats 22ba",
    "sg:city":"Menen",
    "sg:orig_category":"M\u00e9decins and sp\u00e9cialistes",
    "sg:phone":"+32 56 42 46 76",
    "sg:postcode":"8930",
    "sg:province":"West-Vlaanderen",
    "wof:name":"Nikolaas Vuylsteke",
    "wof:placetype":"venue"
},
  "geometry": {"coordinates":[3.164634943,50.7829704285],"type":"Point"}
}