{
  "type": "Feature",
  "properties": {
    "addr:full":"Chauss\u00e9e De Bruxelles 684a Waterloo Brabant Wallon 1410",
    "addr:housenumber":"684a",
    "addr:postcode":"1410",
    "addr:street":"Chausse\u0301E De Bruxelles",
    "iso:country":"BE",
    "sg:address":"Chauss\u00e9e De Bruxelles 684a",
    "sg:city":"Waterloo",
    "sg:classifiers":[
        {
            "category":"Home & Garden",
            "subcategory":"Hardware",
            "type":"Retail Goods"
        }
    ],
    "sg:phone":"+32 2 384 99 71",
    "sg:postcode":"1410",
    "sg:province":"Brabant Wallon",
    "sg:tags":[
        "garage",
        "supply",
        "-",
        "equipment"
    ],
    "wof:name":"Devillers Autodistribution",
    "wof:placetype":"venue"
},
  "geometry": {"coordinates":[4.4035840034,50.6943054199],"type":"Point"}
}