{
  "type": "Feature",
  "properties": {
    "addr:full":"Dorpsstraat 5 Zonhoven Limburg 3520",
    "addr:housenumber":"5",
    "addr:postcode":"3520",
    "addr:street":"Dorpsstraat",
    "iso:country":"BE",
    "sg:address":"Dorpsstraat 5",
    "sg:city":"Zonhoven",
    "sg:classifiers":[
        {
            "category":"Manufacturing",
            "subcategory":"Textiles",
            "type":"Manufacturing & Wholesale Goods"
        }
    ],
    "sg:phone":"+32 11 82 22 98",
    "sg:postcode":"3520",
    "sg:province":"Limburg",
    "sg:tags":[
        "retail",
        "-"
    ],
    "wof:name":"Zeeman Textiel Supers",
    "wof:placetype":"venue"
},
  "geometry": {"coordinates":[5.3684921265,50.9913787842],"type":"Point"}
}