{
  "type": "Feature",
  "properties": {
    "iso:country":"BE",
    "sg:address":"Rue De La Fontaine 5",
    "sg:city":"Rhode-saint-gen\u00e8se",
    "sg:classifiers":[
        {
            "category":"Banks & Credit Unions",
            "subcategory":"Bank",
            "type":"Services"
        }
    ],
    "sg:phone":"+32 2 380 08 35",
    "sg:postcode":"1640",
    "sg:province":"Vlaams-Brabant",
    "sg:tags":[
        "savings-banks"
    ],
    "wof:name":"Centea-p & M Mosselmans",
    "wof:placetype":"venue"
},
  "geometry": {"coordinates":[4.3460640907,50.7445068359],"type":"Point"}
}