{
  "type": "Feature",
  "properties": {
    "addr:full":"Rue De L'h\u00f4pital 77 Charleroi (marchienne-au-pont) Hainaut 6030",
    "addr:housenumber":"77",
    "addr:postcode":"6030",
    "addr:street":"Rue De L'Ho \u0302Pital",
    "iso:country":"BE",
    "sg:address":"Rue De L'h\u00f4pital 77",
    "sg:city":"Charleroi (marchienne-au-pont)",
    "sg:classifiers":[
        {
            "category":"Health Services",
            "subcategory":"Nursing And Care Facility",
            "type":"Services"
        }
    ],
    "sg:phone":"+32 71 29 31 00",
    "sg:postcode":"6030",
    "sg:province":"Hainaut",
    "sg:tags":[
        "home",
        "rest"
    ],
    "wof:name":"Jardins (residence Les)",
    "wof:placetype":"venue"
},
  "geometry": {"coordinates":[4.4308400154,50.4648895264],"type":"Point"}
}