{
  "type": "Feature",
  "properties": {
    "iso:country":"BE",
    "sg:address":"Eglantierlaan 5",
    "sg:city":"Anvers",
    "sg:orig_category":"Diverse bedrijfsbeheeradviesbureaus",
    "sg:phone":"+32 3 828 65 11",
    "sg:postcode":"2020",
    "sg:province":"Antwerpen",
    "wof:name":"Pattern Institute Of Mind And Management",
    "wof:placetype":"venue"
},
  "geometry": {"coordinates":[4.4035601616,51.1859169006],"type":"Point"}
}