{
  "type": "Feature",
  "properties": {
    "iso:country":"BE",
    "sg:address":"Klingedorp 13",
    "sg:city":"Sint-gillis-waas (de Klinge)",
    "sg:classifiers":[
        {
            "category":"Shopping",
            "subcategory":"Clothing, Apparel, & Fashions",
            "type":"Retail Goods"
        }
    ],
    "sg:phone":"+32 3 770 53 32",
    "sg:postcode":"9170",
    "sg:province":"Oost-Vlaanderen",
    "sg:tags":[
        "clothing",
        "-",
        "gentleman"
    ],
    "wof:name":"Ivens Kleding",
    "wof:placetype":"venue"
},
  "geometry": {"coordinates":[4.0904560089,51.2566452026],"type":"Point"}
}