{
  "type": "Feature",
  "properties": {
    "iso:country":"BE",
    "sg:address":"Route De Valenciennes \u00e0 Mons 411",
    "sg:city":"Quaregnon (wasmuel)",
    "sg:classifiers":[
        {
            "category":"Home & Garden",
            "subcategory":"Home Furnishings",
            "type":"Retail Goods"
        }
    ],
    "sg:phone":"+32 65 79 24 64",
    "sg:postcode":"7390",
    "sg:province":"Hainaut",
    "sg:tags":[
        "-",
        "furniture"
    ],
    "wof:name":"Literie N\u00b01",
    "wof:placetype":"venue"
},
  "geometry": {"coordinates":[3.8651049137,50.4428939819],"type":"Point"}
}