{
  "type": "Feature",
  "properties": {
    "iso:country":"BE",
    "sg:address":"Herbesthaler Str.46-48",
    "sg:city":"Eupen",
    "sg:orig_category":"Fabrication and montage de mobilier. Meubles D\u00e9taillants, Am\u00e9nagement de B\u00e2timents et de Cuisines. F",
    "sg:phone":"+32 87 59 16 20",
    "sg:postcode":"4700",
    "sg:province":"Li\u00e8ge",
    "wof:name":"Cremer S.a.",
    "wof:placetype":"venue"
},
  "geometry": {"coordinates":[6.0219597816,50.6356697083],"type":"Point"}
}