{
  "type": "Feature",
  "properties": {
    "addr:full":"Rue De La Station 25 Waterloo Brabant Wallon 1410",
    "addr:housenumber":"25",
    "addr:postcode":"1410",
    "addr:street":"Rue De La Station",
    "iso:country":"BE",
    "sg:address":"Rue De La Station 25",
    "sg:city":"Waterloo",
    "sg:orig_category":"Herstelling leer and schoeisel",
    "sg:phone":"+32 2 353 28 33",
    "sg:postcode":"1410",
    "sg:province":"Brabant Wallon",
    "wof:name":"Serge Cabu",
    "wof:placetype":"venue"
},
  "geometry": {"coordinates":[4.39168787,50.7165336609],"type":"Point"}
}