{
  "type": "Feature",
  "properties": {
    "addr:full":"Avenue Ducp\u00e9tiaux 108 Bruxelles (saint-gilles) Bruxelles-Capitale 1060",
    "addr:housenumber":"108",
    "addr:postcode":"1060",
    "addr:street":"Avenue Ducpe\u0301Tiaux",
    "iso:country":"BE",
    "sg:address":"Avenue Ducp\u00e9tiaux 108",
    "sg:city":"Bruxelles (saint-gilles)",
    "sg:classifiers":[
        {
            "category":"Health Services",
            "subcategory":"Health Practitioner",
            "type":"Services"
        }
    ],
    "sg:phone":"+32 2 346 49 34",
    "sg:postcode":"1060",
    "sg:province":"Bruxelles-Capitale",
    "sg:tags":[
        "physiotherapist"
    ],
    "wof:name":"Meskens Anne",
    "wof:placetype":"venue"
},
  "geometry": {"coordinates":[4.3460898399,50.8221931458],"type":"Point"}
}