{
  "type": "Feature",
  "properties": {
    "addr:full":"Tervuursevest 11b2 Leuven Vlaams-Brabant 3001",
    "addr:housenumber":"11b2",
    "addr:postcode":"3001",
    "addr:street":"Tervuursevest",
    "iso:country":"BE",
    "sg:address":"Tervuursevest 11b2",
    "sg:city":"Leuven",
    "sg:classifiers":[
        {
            "category":"Shopping",
            "subcategory":"Clothing, Apparel, & Fashions",
            "type":"Retail Goods"
        }
    ],
    "sg:phone":"+32 16 22 45 78",
    "sg:postcode":"3001",
    "sg:province":"Vlaams-Brabant",
    "sg:tags":[
        "ondergoed",
        "lingerie"
    ],
    "wof:name":"Huis Thalia",
    "wof:placetype":"venue"
},
  "geometry": {"coordinates":[4.6827630997,50.8766021729],"type":"Point"}
}