{
  "type": "Feature",
  "properties": {
    "iso:country":"BE",
    "sg:address":"Sint-katelijnestraat 34",
    "sg:city":"Gent",
    "sg:orig_category":"V\u00eatements",
    "sg:phone":"+32 9 228 75 54",
    "sg:postcode":"9000",
    "sg:province":"Oost-Vlaanderen",
    "wof:name":"Alg. Gents Confectiebedr.",
    "wof:placetype":"venue"
},
  "geometry": {"coordinates":[3.7278330326,51.0592842102],"type":"Point"}
}