{
  "type": "Feature",
  "properties": {
    "addr:full":"Waterloose Steenweg 1348 Ukkel/uccle Bruxelles-Capitale 1180",
    "addr:postcode":"1348;1180",
    "addr:street":"Waterloose Steenweg",
    "iso:country":"BE",
    "sg:address":"Waterloose Steenweg 1348",
    "sg:city":"Ukkel/uccle",
    "sg:classifiers":[
        {
            "category":"Shopping",
            "subcategory":"Clothing, Apparel, & Fashions",
            "type":"Retail Goods"
        }
    ],
    "sg:phone":"+32 2 374 14 61",
    "sg:postcode":"1180",
    "sg:province":"Bruxelles-Capitale",
    "sg:tags":[
        "ondergoed",
        "lingerie"
    ],
    "wof:name":"Les Secrets Sherwood",
    "wof:placetype":"venue"
},
  "geometry": {"coordinates":[4.3751068115,50.7896614075],"type":"Point"}
}