{
  "type": "Feature",
  "properties": {
    "iso:country":"BE",
    "sg:address":"Watermolenstraat 18bc",
    "sg:city":"Ternat",
    "sg:orig_category":"M\u00e9decins and sp\u00e9cialistes",
    "sg:phone":"+32 2 582 70 72",
    "sg:postcode":"1742",
    "sg:province":"Vlaams-Brabant",
    "wof:name":"Patricia Stockman",
    "wof:placetype":"venue"
},
  "geometry": {"coordinates":[4.1494951248,50.8700904846],"type":"Point"}
}