{
  "type": "Feature",
  "properties": {
    "iso:country":"BE",
    "sg:address":"Rue Grande Champlon 114",
    "sg:city":"Tenneville (champlon)",
    "sg:classifiers":[
        {
            "category":"Building & Trades",
            "subcategory":"Construction",
            "type":"Services"
        }
    ],
    "sg:phone":"+32 84 45 58 14",
    "sg:postcode":"6971",
    "sg:province":"Luxembourg",
    "sg:tags":[
        "carpenter"
    ],
    "wof:name":"Poncin Sprl",
    "wof:placetype":"venue"
},
  "geometry": {"coordinates":[5.4775600433,50.1069793701],"type":"Point"}
}