{
  "type": "Feature",
  "properties": {
    "iso:country":"BE",
    "sg:address":"Rue De La Neuville 91",
    "sg:city":"Seraing",
    "sg:classifiers":[
        {
            "category":"Arena",
            "subcategory":"Sports Club",
            "type":"Entertainment"
        }
    ],
    "sg:phone":"+32 4 336 29 35",
    "sg:postcode":"4100",
    "sg:province":"Li\u00e8ge",
    "sg:tags":[
        "de"
    ],
    "wof:name":"Club Motor. Ourthe Tilff",
    "wof:placetype":"venue"
},
  "geometry": {"coordinates":[5.5015912056,50.5854148865],"type":"Point"}
}