{
  "type": "Feature",
  "properties": {
    "addr:full":"Rue Ville-basse 34 Houffalize Luxembourg 6660",
    "addr:housenumber":"34",
    "addr:postcode":"6660",
    "addr:street":"Rue Ville-Basse",
    "iso:country":"BE",
    "sg:address":"Rue Ville-basse 34",
    "sg:city":"Houffalize",
    "sg:classifiers":[
        {
            "category":"Fast Food",
            "type":"Food & Drink"
        }
    ],
    "sg:phone":"+32 61 28 89 11",
    "sg:postcode":"6660",
    "sg:province":"Luxembourg",
    "sg:tags":[
        "meeneem",
        "restaurant"
    ],
    "wof:name":"Friterie Eric",
    "wof:placetype":"venue"
},
  "geometry": {"coordinates":[5.7909660339,50.1305351257],"type":"Point"}
}