{
  "type": "Feature",
  "properties": {
    "iso:country":"BE",
    "sg:address":"Velm 33b",
    "sg:city":"Asse",
    "sg:orig_category":"Plomberie, chauffage and installations sanitaires. Charpentes and couvertures",
    "sg:phone":"+32 2 452 79 38",
    "sg:postcode":"1730",
    "sg:province":"Vlaams-Brabant",
    "wof:name":"Felix Van Belle",
    "wof:placetype":"venue"
},
  "geometry": {"coordinates":[4.2312121391,50.9265937805],"type":"Point"}
}