{
  "type": "Feature",
  "properties": {
    "addr:full":"Place Albert Ier 1 Wavre Brabant Wallon 1300",
    "addr:housenumber":"1;1300",
    "addr:street":"Place Albert Ier",
    "iso:country":"BE",
    "sg:address":"Place Albert Ier 1",
    "sg:city":"Wavre",
    "sg:orig_category":"Enseignement maternel and primaire",
    "sg:phone":"+32 10 41 55 70",
    "sg:postcode":"1300",
    "sg:province":"Brabant Wallon",
    "wof:name":"E.f.l. Gai Savoir",
    "wof:placetype":"venue"
},
  "geometry": {"coordinates":[4.6116552353,50.7134132385],"type":"Point"}
}