{
  "type": "Feature",
  "properties": {
    "addr:full":"Rue G\u00e9rard Delvoye 1 Welkenraedt Li\u00e8ge 4840",
    "addr:housenumber":"1",
    "addr:postcode":"4840",
    "addr:street":"Rue Ge\u0301Rard Delvoye",
    "iso:country":"BE",
    "sg:address":"Rue G\u00e9rard Delvoye 1",
    "sg:city":"Welkenraedt",
    "sg:classifiers":[
        {
            "category":"Community Center",
            "type":"Public Place"
        }
    ],
    "sg:phone":"+32 87 88 00 33",
    "sg:postcode":"4840",
    "sg:province":"Li\u00e8ge",
    "sg:tags":[
        "medical"
    ],
    "wof:name":"Centre M\u00e9dical",
    "wof:placetype":"venue"
},
  "geometry": {"coordinates":[5.9710798264,50.6629981995],"type":"Point"}
}