{
  "type": "Feature",
  "properties": {
    "addr:full":"Nieuwstraat 20 Aalst Oost-Vlaanderen 9300",
    "addr:housenumber":"20",
    "addr:postcode":"9300",
    "addr:street":"Nieuwstraat",
    "iso:country":"BE",
    "sg:address":"Nieuwstraat 20",
    "sg:city":"Aalst",
    "sg:orig_category":"Cr\u00e9dits divers",
    "sg:postcode":"9300",
    "sg:province":"Oost-Vlaanderen",
    "wof:name":"Bancontact-mister Cash",
    "wof:placetype":"venue"
},
  "geometry": {"coordinates":[4.0360779762,50.9383087158],"type":"Point"}
}