{
  "type": "Feature",
  "properties": {
    "iso:country":"BE",
    "sg:address":"Simon Stevinstraat 35",
    "sg:city":"Kortrijk",
    "sg:classifiers":[
        {
            "category":"Autos & Motor Vehicles",
            "subcategory":"Motorcycle Sales",
            "type":"Retail Goods"
        }
    ],
    "sg:phone":"+32 56 35 22 62",
    "sg:postcode":"8500",
    "sg:province":"West-Vlaanderen",
    "sg:tags":[
        "motorbike"
    ],
    "wof:name":"Mertens A",
    "wof:placetype":"venue"
},
  "geometry": {"coordinates":[3.2668790817,50.8363838196],"type":"Point"}
}