{
  "type": "Feature",
  "properties": {
    "addr:full":"Leopold Ii-laan 15 Oostende West-Vlaanderen 8400",
    "addr:housenumber":"15",
    "addr:postcode":"8400",
    "addr:street":"Leopold Ii-Laan",
    "iso:country":"BE",
    "sg:address":"Leopold Ii-laan 15",
    "sg:city":"Oostende",
    "sg:classifiers":[
        {
            "category":"Personal",
            "subcategory":"Beauty Salon",
            "type":"Services"
        }
    ],
    "sg:phone":"+32 59 70 20 41",
    "sg:postcode":"8400",
    "sg:province":"West-Vlaanderen",
    "sg:tags":[
        "lady",
        "-",
        "hairdressing"
    ],
    "wof:name":"Jean-pierre",
    "wof:placetype":"venue"
},
  "geometry": {"coordinates":[2.9143109322,51.230266571],"type":"Point"}
}