{
  "type": "Feature",
  "properties": {
    "iso:country":"BE",
    "sg:address":"Rue De Noailles 2",
    "sg:city":"Chimay",
    "sg:orig_category":"Banques and organismes de cr\u00e9dit",
    "sg:phone":"+32 60 21 32 84",
    "sg:postcode":"6460",
    "sg:province":"Hainaut",
    "wof:name":"Banque Patriotique",
    "wof:placetype":"venue"
},
  "geometry": {"coordinates":[4.3171429634,50.0493812561],"type":"Point"}
}