{
  "type": "Feature",
  "properties": {
    "addr:full":"Rue Des Viaducs 318 Mons Hainaut 7020",
    "addr:housenumber":"318",
    "addr:postcode":"7020",
    "addr:street":"Rue Des Viaducs;Hainaut",
    "iso:country":"BE",
    "sg:address":"Rue Des Viaducs 318",
    "sg:city":"Mons",
    "sg:orig_category":"Onderdelen and accessoires voor auto's",
    "sg:phone":"+32 65 36 30 31",
    "sg:postcode":"7020",
    "sg:province":"Hainaut",
    "wof:name":"Speedy Belgium",
    "wof:placetype":"venue"
},
  "geometry": {"coordinates":[3.9553449154,50.4761772156],"type":"Point"}
}