{
  "type": "Feature",
  "properties": {
    "addr:full":"Chauss\u00e9e De Gand 92 Bruxelles (molenbeek-saint-jean) Bruxelles-Capitale 1080",
    "addr:housenumber":"92",
    "addr:postcode":"1080",
    "addr:street":"Chausse\u0301E De Gand",
    "iso:country":"BE",
    "sg:address":"Chauss\u00e9e De Gand 92",
    "sg:city":"Bruxelles (molenbeek-saint-jean)",
    "sg:classifiers":[
        {
            "category":"Shopping",
            "subcategory":"Gifts & Souvenirs",
            "type":"Retail Goods"
        }
    ],
    "sg:phone":"+32 2 411 40 71",
    "sg:postcode":"1080",
    "sg:province":"Bruxelles-Capitale",
    "sg:tags":[
        "-"
    ],
    "wof:name":"Cadeau-center",
    "wof:placetype":"venue"
},
  "geometry": {"coordinates":[4.3362488747,50.854347229],"type":"Point"}
}