{
  "type": "Feature",
  "properties": {
    "addr:full":"Ridders Menten Hornepln 7ba Sint-truiden Limburg 3800",
    "addr:postcode":"3800",
    "addr:street":"Hornepln",
    "iso:country":"BE",
    "sg:address":"Ridders Menten Hornepln 7ba",
    "sg:city":"Sint-truiden",
    "sg:orig_category":"RESTAURANTS: CAF\u00c9S",
    "sg:phone":"+32 11 69 29 44",
    "sg:postcode":"3800",
    "sg:province":"Limburg",
    "wof:name":"Taverne De Horne",
    "wof:placetype":"venue"
},
  "geometry": {"coordinates":[5.1816101074,50.8187408447],"type":"Point"}
}