{
  "type": "Feature",
  "properties": {
    "iso:country":"BE",
    "sg:address":"Fabriekstraat 1",
    "sg:city":"Ardooie",
    "sg:classifiers":[
        {
            "category":"Home & Garden",
            "subcategory":"Hardware",
            "type":"Retail Goods"
        }
    ],
    "sg:phone":"+32 51 74 43 82",
    "sg:postcode":"8850",
    "sg:province":"West-Vlaanderen",
    "sg:tags":[
        "equipment"
    ],
    "wof:name":"De Pypere Bvba",
    "wof:placetype":"venue"
},
  "geometry": {"coordinates":[3.2027289867,50.988193512],"type":"Point"}
}