{
  "type": "Feature",
  "properties": {
    "iso:country":"BE",
    "sg:address":"Rue Des Combattants 36",
    "sg:city":"Oreye",
    "sg:classifiers":[
        {
            "category":"Wholesale",
            "subcategory":"Fruits & Vegetables",
            "type":"Manufacturing & Wholesale Goods"
        }
    ],
    "sg:phone":"+32 19 67 76 90",
    "sg:postcode":"4360",
    "sg:province":"Li\u00e8ge",
    "sg:tags":[
        "whol",
        "-"
    ],
    "wof:name":"Albert H",
    "wof:placetype":"venue"
},
  "geometry": {"coordinates":[5.3571047783,50.7285575867],"type":"Point"}
}