{
  "type": "Feature",
  "properties": {
    "addr:full":"Negenoord Dilsen-stokkem (stokkem) Limburg 3650",
    "addr:postcode":"3650",
    "iso:country":"BE",
    "sg:address":"Negenoord",
    "sg:city":"Dilsen-stokkem (stokkem)",
    "sg:classifiers":[
        {
            "category":"Museum",
            "type":"Entertainment"
        }
    ],
    "sg:phone":"+32 89 75 21 71",
    "sg:postcode":"3650",
    "sg:province":"Limburg",
    "wof:name":"De Wissen",
    "wof:placetype":"venue"
},
  "geometry": {"coordinates":[5.727396965,51.0364189148],"type":"Point"}
}