{
  "type": "Feature",
  "properties": {
    "iso:country":"BE",
    "sg:address":"Rue Des Roses Tremieres 26",
    "sg:city":"Namur",
    "sg:orig_category":"Travaux de pl\u00e2trage",
    "sg:phone":"+32 81 21 57 99",
    "sg:postcode":"5020",
    "sg:province":"Namur",
    "wof:name":"Robert Paris",
    "wof:placetype":"venue"
},
  "geometry": {"coordinates":[4.7952418327,50.4352035522],"type":"Point"}
}