{
  "type": "Feature",
  "properties": {
    "addr:full":"Avenue Gomar Vandewiele 12 Renaix Oost-Vlaanderen 9600",
    "addr:housenumber":"12",
    "addr:postcode":"9600",
    "addr:street":"Avenue Gomar Vandewiele",
    "iso:country":"BE",
    "sg:address":"Avenue Gomar Vandewiele 12",
    "sg:city":"Renaix",
    "sg:classifiers":[
        {
            "category":"Health Services",
            "subcategory":"Health Practitioner",
            "type":"Services"
        }
    ],
    "sg:phone":"+32 55 21 45 16",
    "sg:postcode":"9600",
    "sg:province":"Oost-Vlaanderen",
    "sg:tags":[
        "physiotherapist"
    ],
    "wof:name":"De Rudder Marc",
    "wof:placetype":"venue"
},
  "geometry": {"coordinates":[3.5944569111,50.742225647],"type":"Point"}
}