{
  "type": "Feature",
  "properties": {
    "iso:country":"BE",
    "sg:address":"Smaragdlaan 12",
    "sg:city":"Schaarbeek/schaerbeek",
    "sg:orig_category":"Technisch and beroeps secundair onderwijs",
    "sg:phone":"+32 2 734 38 85",
    "sg:postcode":"1030",
    "sg:province":"Bruxelles-Capitale",
    "wof:name":"Coll\u00c8ge Roi Baudouin",
    "wof:placetype":"venue"
},
  "geometry": {"coordinates":[4.3961129189,50.8529090881],"type":"Point"}
}