{
  "type": "Feature",
  "properties": {
    "addr:full":"Chauss\u00e9e De Jolimont 205 La Louvi\u00e8re (haine-saint-pierre) Hainaut 7100",
    "addr:housenumber":"205",
    "addr:postcode":"7100",
    "addr:street":"Chausse\u0301E De Jolimont",
    "iso:country":"BE",
    "sg:address":"Chauss\u00e9e De Jolimont 205",
    "sg:city":"La Louvi\u00e8re (haine-saint-pierre)",
    "sg:orig_category":"Non-Classified Establishments",
    "sg:phone":"+32 64 28 45 97",
    "sg:postcode":"7100",
    "sg:province":"Hainaut",
    "wof:name":"Benedetto A",
    "wof:placetype":"venue"
},
  "geometry": {"coordinates":[4.2153959274,50.4720954895],"type":"Point"}
}