{
  "type": "Feature",
  "properties": {
    "addr:full":"Boulevard Joseph Tirou 177 Charleroi Hainaut 6000",
    "addr:housenumber":"177",
    "addr:postcode":"6000",
    "addr:street":"Boulevard Joseph Tirou;Hainaut",
    "iso:country":"BE",
    "sg:address":"Boulevard Joseph Tirou 177",
    "sg:city":"Charleroi",
    "sg:orig_category":"Timbres, monnaies and troph\u00e9es",
    "sg:phone":"+32 71 33 19 59",
    "sg:postcode":"6000",
    "sg:province":"Hainaut",
    "wof:name":"Fe. Mainghain",
    "wof:placetype":"venue"
},
  "geometry": {"coordinates":[4.4457669258,50.4071464539],"type":"Point"}
}