{
  "type": "Feature",
  "properties": {
    "iso:country":"BE",
    "sg:address":"Rue Try Des Rudes 27",
    "sg:city":"Chastre (cortil-noirmont)",
    "sg:classifiers":[
        {
            "category":"Building & Trades",
            "subcategory":"Electrical",
            "type":"Services"
        }
    ],
    "sg:phone":"+32 81 61 18 41",
    "sg:postcode":"1450",
    "sg:province":"Brabant Wallon",
    "sg:tags":[
        "-",
        "electric",
        "contractor"
    ],
    "wof:name":"Steens R",
    "wof:placetype":"venue"
},
  "geometry": {"coordinates":[4.6508760452,50.5724906921],"type":"Point"}
}