{
  "type": "Feature",
  "properties": {
    "addr:full":"Offerandestraat 34 Antwerpen Antwerpen 2060",
    "addr:housenumber":"34",
    "addr:postcode":"2060",
    "addr:street":"Offerandestraat",
    "iso:country":"BE",
    "sg:address":"Offerandestraat 34",
    "sg:city":"Antwerpen",
    "sg:orig_category":"Dameskledingzaken",
    "sg:phone":"+32 3 233 37 71",
    "sg:postcode":"2060",
    "sg:province":"Antwerpen",
    "wof:name":"Huis Seasons",
    "wof:placetype":"venue"
},
  "geometry": {"coordinates":[4.424973011,51.2199821472],"type":"Point"}
}