{
  "type": "Feature",
  "properties": {
    "addr:full":"Veldweg 14 Kortessem Limburg 3720",
    "addr:housenumber":"14",
    "addr:postcode":"3720",
    "addr:street":"Veldweg;Limburg",
    "iso:country":"BE",
    "sg:address":"Veldweg 14",
    "sg:city":"Kortessem",
    "sg:orig_category":"Banques and organismes de cr\u00e9dit",
    "sg:phone":"+32 11 37 60 92",
    "sg:postcode":"3720",
    "sg:province":"Limburg",
    "wof:name":"Ippa",
    "wof:placetype":"venue"
},
  "geometry": {"coordinates":[5.3785200119,50.8615951538],"type":"Point"}
}