{
  "type": "Feature",
  "properties": {
    "addr:full":"Rue Du Tombeux 55 Verviers (stembert) Li\u00e8ge 4801",
    "addr:housenumber":"55",
    "addr:postcode":"4801",
    "addr:street":"Rue Du Tombeux",
    "iso:country":"BE",
    "sg:address":"Rue Du Tombeux 55",
    "sg:city":"Verviers (stembert)",
    "sg:classifiers":[
        {
            "category":"Shopping",
            "subcategory":"Beauty & Cosmetics",
            "type":"Retail Goods"
        }
    ],
    "sg:phone":"+32 87 34 00 63",
    "sg:postcode":"4801",
    "sg:province":"Li\u00e8ge",
    "sg:tags":[
        "-",
        "perfumery"
    ],
    "wof:name":"Defawe L",
    "wof:placetype":"venue"
},
  "geometry": {"coordinates":[5.8930549622,50.5922393799],"type":"Point"}
}