{
  "type": "Feature",
  "properties": {
    "iso:country":"BE",
    "sg:address":"Rue Fran\u00c7ois Bovesse 54",
    "sg:city":"Gembloux",
    "sg:orig_category":"Sportclubs",
    "sg:phone":"+32 81 61 33 35",
    "sg:postcode":"5030",
    "sg:province":"Namur",
    "wof:name":"Les Petanquis D'djibloux",
    "wof:placetype":"venue"
},
  "geometry": {"coordinates":[4.6812448502,50.5703887939],"type":"Point"}
}