{
  "type": "Feature",
  "properties": {
    "addr:full":"Rue Des Pierres \u00c0 Fusil 3 Jurbise Hainaut 7050",
    "addr:housenumber":"3",
    "addr:postcode":"7050",
    "addr:street":"Rue Des Pierres A\u0300 Fusil",
    "iso:country":"BE",
    "sg:address":"Rue Des Pierres \u00c0 Fusil 3",
    "sg:city":"Jurbise",
    "sg:orig_category":"Pain, p\u00e2tisseries and confiseries",
    "sg:phone":"+32 65 22 90 09",
    "sg:postcode":"7050",
    "sg:province":"Hainaut",
    "wof:name":"Pains Beck",
    "wof:placetype":"venue"
},
  "geometry": {"coordinates":[3.9314661026,50.5037765503],"type":"Point"}
}