{
  "type": "Feature",
  "properties": {
    "addr:full":"Withuisstraat 167-168 Fourons Limburg 3790",
    "addr:housenumber":"167-168",
    "addr:postcode":"3790",
    "addr:street":"Withuisstraat",
    "iso:country":"BE",
    "sg:address":"Withuisstraat 167-168",
    "sg:city":"Fourons",
    "sg:orig_category":"Diverse bouwafwerking and reiniging Gespecialiseerde residenti\u00eble bouw Woningbouw",
    "sg:phone":"+32 4 381 08 55",
    "sg:postcode":"3790",
    "sg:province":"Limburg",
    "wof:name":"Smeets",
    "wof:placetype":"venue"
},
  "geometry": {"coordinates":[5.721350193,50.763999939],"type":"Point"}
}