{
  "type": "Feature",
  "properties": {
    "iso:country":"BE",
    "sg:address":"Rue De Longwy 3",
    "sg:city":"Aubange",
    "sg:classifiers":[
        {
            "category":"Manufacturing",
            "subcategory":"Motor Vehicles & Parts",
            "type":"Manufacturing & Wholesale Goods"
        }
    ],
    "sg:phone":"+32 63 37 10 35",
    "sg:postcode":"6790",
    "sg:province":"Luxembourg",
    "sg:tags":[
        "exhaust",
        "system"
    ],
    "wof:name":"Autos Pi\u00e8ces & Industries Sa",
    "wof:placetype":"venue"
},
  "geometry": {"coordinates":[5.7980999947,49.5634689331],"type":"Point"}
}