{
  "type": "Feature",
  "properties": {
    "iso:country":"BE",
    "sg:address":"Kipdorpvest 24",
    "sg:city":"Antwerpen",
    "sg:orig_category":"Formation permanente",
    "sg:phone":"+32 3 233 37 90",
    "sg:postcode":"2000",
    "sg:province":"Antwerpen",
    "wof:name":"Sted. Techn. Leergangen",
    "wof:placetype":"venue"
},
  "geometry": {"coordinates":[4.4144740105,51.2187004089],"type":"Point"}
}