{
  "type": "Feature",
  "properties": {
    "addr:full":"Rue De Tervaete 62 Etterbeek Bruxelles-Capitale 1040",
    "addr:housenumber":"62",
    "addr:postcode":"1040",
    "addr:street":"Rue De Tervaete",
    "iso:country":"BE",
    "sg:address":"Rue De Tervaete 62",
    "sg:city":"Etterbeek",
    "sg:orig_category":"M\u00e9decins and sp\u00e9cialistes",
    "sg:phone":"+32 2 733 32 80",
    "sg:postcode":"1040",
    "sg:province":"Bruxelles-Capitale",
    "wof:name":"Michel Amand",
    "wof:placetype":"venue"
},
  "geometry": {"coordinates":[4.401116848,50.8301391602],"type":"Point"}
}