{
  "type": "Feature",
  "properties": {
    "iso:country":"BE",
    "sg:address":"Xhos 5",
    "sg:city":"Anthisnes",
    "sg:orig_category":"Eleveurs de bovins",
    "sg:phone":"+32 4 383 61 74",
    "sg:postcode":"4163",
    "sg:province":"Li\u00e8ge",
    "wof:name":"Bernard Deflandre",
    "wof:placetype":"venue"
},
  "geometry": {"coordinates":[5.4695720673,50.4952926636],"type":"Point"}
}