{
  "type": "Feature",
  "properties": {
    "addr:full":"Rue Faignart 47 La Louvi\u00c8re Hainaut 7100",
    "addr:housenumber":"47",
    "addr:postcode":"7100",
    "addr:street":"Rue Faignart",
    "iso:country":"BE",
    "sg:address":"Rue Faignart 47",
    "sg:city":"La Louvi\u00c8re",
    "sg:orig_category":"Boekhouders",
    "sg:phone":"+32 64 22 83 61",
    "sg:postcode":"7100",
    "sg:province":"Hainaut",
    "wof:name":"Fran\u00c7oise Duriau",
    "wof:placetype":"venue"
},
  "geometry": {"coordinates":[4.1798300743,50.4701690674],"type":"Point"}
}