{
  "type": "Feature",
  "properties": {
    "iso:country":"BE",
    "sg:address":"Bergstraat 18",
    "sg:city":"Grobbendonk",
    "sg:classifiers":[
        {
            "category":"Professional",
            "subcategory":"Computer Services",
            "type":"Services"
        }
    ],
    "sg:phone":"+32 14 50 16 64",
    "sg:postcode":"2280",
    "sg:province":"Antwerpen",
    "sg:tags":[
        "-",
        "processing",
        "data",
        "software"
    ],
    "wof:name":"Silvester Systems & Software",
    "wof:placetype":"venue"
},
  "geometry": {"coordinates":[4.736623764,51.1940612793],"type":"Point"}
}