{
  "type": "Feature",
  "properties": {
    "addr:full":"Nijverheidsstraat 114 Vilvoorde Vlaams-Brabant 1800",
    "addr:housenumber":"114",
    "addr:postcode":"1800",
    "addr:street":"Nijverheidsstraat",
    "iso:country":"BE",
    "sg:address":"Nijverheidsstraat 114",
    "sg:city":"Vilvoorde",
    "sg:orig_category":"Dansscholen",
    "sg:phone":"+32 2 251 62 81",
    "sg:postcode":"1800",
    "sg:province":"Vlaams-Brabant",
    "wof:name":"Modern Dance Studio",
    "wof:placetype":"venue"
},
  "geometry": {"coordinates":[4.4373688698,50.9326057434],"type":"Point"}
}