{
  "type": "Feature",
  "properties": {
    "iso:country":"BE",
    "sg:address":"Sportlaan 23",
    "sg:city":"Ham",
    "sg:orig_category":"Maatschappelijke dienstverlening",
    "sg:phone":"+32 13 67 14 76",
    "sg:postcode":"3945",
    "sg:province":"Limburg",
    "wof:name":"Rode Kruis Ham",
    "wof:placetype":"venue"
},
  "geometry": {"coordinates":[5.1776199341,51.1046104431],"type":"Point"}
}