{
  "type": "Feature",
  "properties": {
    "addr:full":"Schawijkstraat 51 Ranst (groot) Antwerpen 2520",
    "addr:housenumber":"51",
    "addr:postcode":"2520",
    "addr:street":"Schawijkstraat;Groot Antwerpen",
    "iso:country":"BE",
    "sg:address":"Schawijkstraat 51",
    "sg:city":"Ranst (groot)",
    "sg:orig_category":"Diverse bedrijfsbeheeradviesbureaus",
    "sg:phone":"+32 3 877 55 03",
    "sg:postcode":"2520",
    "sg:province":"Antwerpen",
    "wof:name":"Hetano",
    "wof:placetype":"venue"
},
  "geometry": {"coordinates":[4.544629097,51.1964759827],"type":"Point"}
}