{
  "type": "Feature",
  "properties": {
    "iso:country":"BE",
    "sg:address":"Maastrichterstraat 96",
    "sg:city":"Hasselt",
    "sg:orig_category":"Hoger onderwijs",
    "sg:phone":"+32 11 30 04 90",
    "sg:postcode":"3500",
    "sg:province":"Limburg",
    "wof:name":"Katholieke Hogeschool",
    "wof:placetype":"venue"
},
  "geometry": {"coordinates":[5.3410930634,50.930103302],"type":"Point"}
}