{
  "type": "Feature",
  "properties": {
    "iso:country":"BE",
    "sg:address":"Dhoye 19",
    "sg:city":"Deinze",
    "sg:orig_category":"Rundveehouders",
    "sg:phone":"+32 9 386 73 14",
    "sg:postcode":"9800",
    "sg:province":"Oost-Vlaanderen",
    "wof:name":"Luc De Keukeleire",
    "wof:placetype":"venue"
},
  "geometry": {"coordinates":[3.5082230568,50.986995697],"type":"Point"}
}