{
  "type": "Feature",
  "properties": {
    "addr:full":"Avenue De La Floride 63 Bruxelles (uccle) Bruxelles-Capitale 1180",
    "addr:housenumber":"63",
    "addr:postcode":"1180",
    "addr:street":"Avenue De La Floride",
    "iso:country":"BE",
    "sg:address":"Avenue De La Floride 63",
    "sg:city":"Bruxelles (uccle)",
    "sg:classifiers":[
        {
            "category":"Professional",
            "subcategory":"Art Services",
            "type":"Services"
        }
    ],
    "sg:phone":"+32 2 372 36 47",
    "sg:postcode":"1180",
    "sg:province":"Bruxelles-Capitale",
    "sg:tags":[
        "interior",
        "designer"
    ],
    "wof:name":"Salza G",
    "wof:placetype":"venue"
},
  "geometry": {"coordinates":[4.3659410477,50.8071136475],"type":"Point"}
}