{
  "type": "Feature",
  "properties": {
    "addr:full":"Rue Edouard Colson 314 Ans (loncin) Li\u00e8ge 4431",
    "addr:housenumber":"314",
    "addr:postcode":"4431",
    "addr:street":"Rue Edouard Colson",
    "iso:country":"BE",
    "sg:address":"Rue Edouard Colson 314",
    "sg:city":"Ans (loncin)",
    "sg:classifiers":[
        {
            "category":"Retail",
            "subcategory":"Repair Shop",
            "type":"Services"
        }
    ],
    "sg:phone":"+32 4 247 16 36",
    "sg:postcode":"4431",
    "sg:province":"Li\u00e8ge",
    "sg:tags":[
        "radio",
        "television",
        "-",
        "maintenance"
    ],
    "wof:name":"Arta Audio-tvc-video-henoumont Andre",
    "wof:placetype":"venue"
},
  "geometry": {"coordinates":[5.490735054,50.6720466614],"type":"Point"}
}