{
  "type": "Feature",
  "properties": {
    "iso:country":"BE",
    "sg:address":"Givry 1190a",
    "sg:city":"Bertogne",
    "sg:orig_category":"Installatie van houten of kunststof schrijnwerk Meubelzaken, woning- and keukeninrichting",
    "sg:phone":"+32 61 21 41 56",
    "sg:postcode":"6686",
    "sg:province":"Luxembourg",
    "wof:name":"Philippe Ghys",
    "wof:placetype":"venue"
},
  "geometry": {"coordinates":[5.6022458076,50.0324134827],"type":"Point"}
}