{
  "type": "Feature",
  "properties": {
    "iso:country":"BE",
    "sg:address":"Rue Ta\u00efenne 45",
    "sg:city":"Aiseau-presles (presles)",
    "sg:classifiers":[
        {
            "category":"Real Estate",
            "subcategory":"Architect",
            "type":"Services"
        }
    ],
    "sg:phone":"+32 71 39 72 20",
    "sg:postcode":"6250",
    "sg:province":"Hainaut",
    "wof:name":"Watillon L",
    "wof:placetype":"venue"
},
  "geometry": {"coordinates":[4.5863847733,50.40990448],"type":"Point"}
}