{
  "type": "Feature",
  "properties": {
    "addr:full":"Eeklostraat 108 Gent Oost-Vlaanderen 9030",
    "addr:housenumber":"108",
    "addr:postcode":"9030",
    "addr:street":"Eeklostraat;Oost-Vlaanderen",
    "iso:country":"BE",
    "sg:address":"Eeklostraat 108",
    "sg:city":"Gent",
    "sg:orig_category":"Plaatsen van vloer- and muurbekleding Schilders",
    "sg:phone":"+32 9 226 16 55",
    "sg:postcode":"9030",
    "sg:province":"Oost-Vlaanderen",
    "wof:name":"Jo Myncke",
    "wof:placetype":"venue"
},
  "geometry": {"coordinates":[3.6949419975,51.0734443665],"type":"Point"}
}