{
  "type": "Feature",
  "properties": {
    "addr:full":"Rue Des Deux Bonniers 2 Lens Hainaut 7870",
    "addr:housenumber":"2",
    "addr:postcode":"7870",
    "addr:street":"Rue Des Deux Bonniers",
    "iso:country":"BE",
    "sg:address":"Rue Des Deux Bonniers 2",
    "sg:city":"Lens",
    "sg:orig_category":"Rundveehouders",
    "sg:phone":"+32 68 45 41 91",
    "sg:postcode":"7870",
    "sg:province":"Hainaut",
    "wof:name":"Etienne Fauvarque",
    "wof:placetype":"venue"
},
  "geometry": {"coordinates":[3.901911974,50.587978363],"type":"Point"}
}