{
  "type": "Feature",
  "properties": {
    "iso:country":"BE",
    "sg:address":"Vismarkt 10b",
    "sg:city":"Leuven",
    "sg:classifiers":[
        {
            "category":"Home & Garden",
            "subcategory":"Home Furnishings",
            "type":"Retail Goods"
        }
    ],
    "sg:phone":"+32 16 23 45 23",
    "sg:postcode":"3000",
    "sg:province":"Vlaams-Brabant",
    "sg:tags":[
        "interior",
        "decoration"
    ],
    "wof:name":"Abacuse",
    "wof:placetype":"venue"
},
  "geometry": {"coordinates":[4.7003622055,50.8815040588],"type":"Point"}
}