{
  "type": "Feature",
  "properties": {
    "addr:full":"Grande Carri\u00e8re 17 Ath (ormeignies) Hainaut 7802",
    "addr:housenumber":"17",
    "addr:postcode":"7802",
    "addr:street":"Grande Carrie\u0300Re",
    "iso:country":"BE",
    "sg:address":"Grande Carri\u00e8re 17",
    "sg:city":"Ath (ormeignies)",
    "sg:classifiers":[
        {
            "category":"Manufacturing",
            "subcategory":"Tools & Machinery",
            "type":"Manufacturing & Wholesale Goods"
        }
    ],
    "sg:phone":"+32 68 28 23 05",
    "sg:postcode":"7802",
    "sg:province":"Hainaut",
    "sg:tags":[
        "scale"
    ],
    "wof:name":"Selvais",
    "wof:placetype":"venue"
},
  "geometry": {"coordinates":[3.7445349693,50.601146698],"type":"Point"}
}