{
  "type": "Feature",
  "properties": {
    "addr:full":"Rue Du Centre 3 Mettet Namur 5640",
    "addr:housenumber":"3",
    "addr:postcode":"5640",
    "addr:street":"Rue Du Centre",
    "iso:country":"BE",
    "sg:address":"Rue Du Centre 3",
    "sg:city":"Mettet",
    "sg:orig_category":"Instruments de musique",
    "sg:phone":"+32 71 72 98 87",
    "sg:postcode":"5640",
    "sg:province":"Namur",
    "wof:name":"Maison Namur Musique",
    "wof:placetype":"venue"
},
  "geometry": {"coordinates":[4.6574788094,50.3192405701],"type":"Point"}
}