{
  "type": "Feature",
  "properties": {
    "iso:country":"BE",
    "sg:address":"Grootzand 158",
    "sg:city":"Dendermonde",
    "sg:orig_category":"Peinture. Rev\u00eatements pour sols and murs",
    "sg:phone":"+32 52 21 84 07",
    "sg:postcode":"9200",
    "sg:province":"Oost-Vlaanderen",
    "wof:name":"Vanvaerenbergh Fr.",
    "wof:placetype":"venue"
},
  "geometry": {"coordinates":[4.1040449142,51.0425758362],"type":"Point"}
}