{
  "type": "Feature",
  "properties": {
    "addr:full":"Grote Noordstraat 62 Hooglede West-Vlaanderen 8830",
    "addr:housenumber":"62",
    "addr:postcode":"8830",
    "addr:street":"Grote Noordstraat",
    "iso:country":"BE",
    "sg:address":"Grote Noordstraat 62",
    "sg:city":"Hooglede",
    "sg:classifiers":[
        {
            "category":"Retail",
            "subcategory":"Veterinary Services",
            "type":"Services"
        }
    ],
    "sg:phone":"+32 51 22 52 77",
    "sg:postcode":"8830",
    "sg:province":"West-Vlaanderen",
    "sg:tags":[
        "veterinarian"
    ],
    "wof:name":"Callens L",
    "wof:placetype":"venue"
},
  "geometry": {"coordinates":[3.0742878914,50.9934654236],"type":"Point"}
}