{
  "type": "Feature",
  "properties": {
    "iso:country":"BE",
    "sg:address":"Neerstraat 45",
    "sg:city":"Waregem",
    "sg:orig_category":"Travaux de finition and nettoyage de b\u00e2timents. Constructions r\u00e9sidentielles sp\u00e9cifiques",
    "sg:phone":"+32 56 60 83 75",
    "sg:postcode":"8793",
    "sg:province":"West-Vlaanderen",
    "wof:name":"Neirynck Gino",
    "wof:placetype":"venue"
},
  "geometry": {"coordinates":[3.412801981,50.9059448242],"type":"Point"}
}