{
  "type": "Feature",
  "properties": {
    "addr:full":"Sint-truidersteenweg 161 Tongeren Limburg 3700",
    "addr:housenumber":"161",
    "addr:postcode":"3700",
    "addr:street":"Sint-Truidersteenweg",
    "iso:country":"BE",
    "sg:address":"Sint-truidersteenweg 161",
    "sg:city":"Tongeren",
    "sg:classifiers":[
        {
            "category":"Home & Garden",
            "subcategory":"Building Materials",
            "type":"Retail Goods"
        }
    ],
    "sg:phone":"+32 12 45 85 01",
    "sg:postcode":"3700",
    "sg:province":"Limburg",
    "sg:tags":[
        "granite",
        "stone",
        "natural",
        "marble"
    ],
    "wof:name":"De Tegelconsulent",
    "wof:placetype":"venue"
},
  "geometry": {"coordinates":[5.4488420486,50.7778930664],"type":"Point"}
}