{
  "type": "Feature",
  "properties": {
    "iso:country":"BE",
    "sg:address":"Elsense Steenweg 227bb",
    "sg:city":"Elsene/ixelles",
    "sg:orig_category":"Film-, tv- and videoproductie Geluidsopnames",
    "sg:phone":"+32 2 640 77 31",
    "sg:postcode":"1050",
    "sg:province":"Bruxelles-Capitale",
    "wof:name":"Polygone",
    "wof:placetype":"venue"
},
  "geometry": {"coordinates":[4.3680410385,50.8314971924],"type":"Point"}
}