{
  "type": "Feature",
  "properties": {
    "addr:full":"Schaluin 91 Aarschot Vlaams-Brabant 3200",
    "addr:housenumber":"91",
    "addr:postcode":"3200",
    "addr:street":"Schaluin",
    "iso:country":"BE",
    "sg:address":"Schaluin 91",
    "sg:city":"Aarschot",
    "sg:orig_category":"Banken and kredietinstellingen",
    "sg:phone":"+32 16 56 51 52",
    "sg:postcode":"3200",
    "sg:province":"Vlaams-Brabant",
    "wof:name":"Bacob",
    "wof:placetype":"venue"
},
  "geometry": {"coordinates":[4.8410100937,50.990486145],"type":"Point"}
}