{
  "type": "Feature",
  "properties": {
    "addr:full":"Schrijberg 243 Sint-niklaas Oost-Vlaanderen 9111",
    "addr:housenumber":"243",
    "addr:postcode":"9111",
    "addr:street":"Schrijberg",
    "iso:country":"BE",
    "sg:address":"Schrijberg 243",
    "sg:city":"Sint-niklaas",
    "sg:orig_category":"Boucheries",
    "sg:phone":"+32 3 772 37 87",
    "sg:postcode":"9111",
    "sg:province":"Oost-Vlaanderen",
    "wof:name":"Gilbert De Sutter",
    "wof:placetype":"venue"
},
  "geometry": {"coordinates":[4.0764989853,51.1345367432],"type":"Point"}
}