{
  "type": "Feature",
  "properties": {
    "addr:full":"Liniestraat 56 Halen Limburg 3545",
    "addr:housenumber":"56",
    "addr:postcode":"3545",
    "addr:street":"Liniestraat",
    "iso:country":"BE",
    "sg:address":"Liniestraat 56",
    "sg:city":"Halen",
    "sg:classifiers":[
        {
            "category":"Cafe",
            "type":"Food & Drink"
        }
    ],
    "sg:phone":"+32 13 44 12 12",
    "sg:postcode":"3545",
    "sg:province":"Limburg",
    "sg:tags":[
        "caf\u00e9s"
    ],
    "wof:name":"Anna Gakens",
    "wof:placetype":"venue"
},
  "geometry": {"coordinates":[5.0996828079,50.9367637634],"type":"Point"}
}