{
  "type": "Feature",
  "properties": {
    "addr:full":"Leuvenseweg 38 Herent Vlaams-Brabant 3020",
    "addr:housenumber":"38",
    "addr:postcode":"3020",
    "addr:street":"Leuvenseweg",
    "iso:country":"BE",
    "sg:address":"Leuvenseweg 38",
    "sg:city":"Herent",
    "sg:classifiers":[
        {
            "category":"Health Services",
            "subcategory":"Dentist",
            "type":"Services"
        }
    ],
    "sg:phone":"+32 16 22 08 96",
    "sg:postcode":"3020",
    "sg:province":"Vlaams-Brabant",
    "wof:name":"Lefevre Monique",
    "wof:placetype":"venue"
},
  "geometry": {"coordinates":[4.6751899719,50.9037132263],"type":"Point"}
}