{
  "type": "Feature",
  "properties": {
    "addr:full":"Avenue Louise 534 Bruxelles 1051",
    "addr:housenumber":"534",
    "addr:postcode":"1051",
    "addr:street":"Avenue Louise",
    "iso:country":"BE",
    "sg:address":"Avenue Louise 534",
    "sg:city":"Bruxelles",
    "sg:classifiers":[
        {
            "category":"Shopping",
            "subcategory":"Stationery & Office Supplies",
            "type":"Retail Goods"
        }
    ],
    "sg:phone":"+32 15 61 34 40",
    "sg:postcode":"1051",
    "sg:tags":[
        "chemical",
        "plant",
        "planning"
    ],
    "wof:name":"V.d.b. Petit Nv",
    "wof:placetype":"venue"
},
  "geometry": {"coordinates":[4.5156068802,50.9960784912],"type":"Point"}
}