{
  "type": "Feature",
  "properties": {
    "iso:country":"BE",
    "sg:address":"Sint-michielsplein 14",
    "sg:city":"Roeselare",
    "sg:orig_category":"Dameskledingzaken",
    "sg:phone":"+32 51 20 51 10",
    "sg:postcode":"8800",
    "sg:province":"West-Vlaanderen",
    "wof:name":"V.s.b.",
    "wof:placetype":"venue"
},
  "geometry": {"coordinates":[3.1231620312,50.9439163208],"type":"Point"}
}