{
  "type": "Feature",
  "properties": {
    "addr:full":"Parklaan 80 Turnhout Antwerpen 2300",
    "addr:housenumber":"80",
    "addr:postcode":"2300",
    "addr:street":"Parklaan",
    "iso:country":"BE",
    "sg:address":"Parklaan 80",
    "sg:city":"Turnhout",
    "sg:classifiers":[
        {
            "category":"Shopping",
            "subcategory":"Crafts & Fabrics",
            "type":"Retail Goods"
        }
    ],
    "sg:phone":"+32 14 42 18 82",
    "sg:postcode":"2300",
    "sg:province":"Antwerpen",
    "sg:tags":[
        "silk",
        "-"
    ],
    "wof:name":"Limbutex Stoffen",
    "wof:placetype":"venue"
},
  "geometry": {"coordinates":[4.9464230537,51.3122634888],"type":"Point"}
}