{
  "type": "Feature",
  "properties": {
    "addr:full":". Oudergem (brussel) Bruxelles-Capitale 1160",
    "addr:postcode":"1160",
    "addr:street":"Oudergem",
    "iso:country":"BE",
    "sg:address":".",
    "sg:city":"Oudergem (brussel)",
    "sg:orig_category":"Apotheken",
    "sg:phone":"+32 900 10 500",
    "sg:postcode":"1160",
    "sg:province":"Bruxelles-Capitale",
    "wof:name":"Apothekers Van Wacht",
    "wof:placetype":"venue"
},
  "geometry": {"coordinates":[4.4251499176,50.8167381287],"type":"Point"}
}