{
  "type": "Feature",
  "properties": {
    "iso:country":"BE",
    "sg:address":"Heistraat 53",
    "sg:city":"Wilrijk",
    "sg:orig_category":"Tijdelijke werkgelegenheid and uitzendkantoren Vedior",
    "sg:phone":"+32 3 825 43 65",
    "sg:postcode":"2610",
    "sg:province":"Antwerpen",
    "wof:name":"Vedior Interim",
    "wof:placetype":"venue"
},
  "geometry": {"coordinates":[4.3939890862,51.1720046997],"type":"Point"}
}