{
  "type": "Feature",
  "properties": {
    "addr:full":"Rue Du Delta 23 Mons Hainaut 7000",
    "addr:housenumber":"23",
    "addr:postcode":"7000",
    "addr:street":"Rue Du Delta;Hainaut",
    "iso:country":"BE",
    "sg:address":"Rue Du Delta 23",
    "sg:city":"Mons",
    "sg:classifiers":[
        {
            "category":"Structure",
            "subcategory":"Building",
            "type":"Public Place"
        }
    ],
    "sg:phone":"+32 65 33 77 86",
    "sg:postcode":"7000",
    "sg:province":"Hainaut",
    "sg:tags":[
        "door"
    ],
    "wof:name":"Comebloc Sprl",
    "wof:placetype":"venue"
},
  "geometry": {"coordinates":[3.9380369186,50.4482345581],"type":"Point"}
}