{
  "type": "Feature",
  "properties": {
    "iso:country":"BE",
    "sg:address":"Chauss\u00c9e D'alsemberg 945",
    "sg:city":"Ukkel/uccle",
    "sg:orig_category":"Magasins de r\u00e9parations d'articles personnels et m\u00e9nagers divers",
    "sg:phone":"+32 2 332 24 51",
    "sg:postcode":"1180",
    "sg:province":"Bruxelles-Capitale",
    "wof:name":"Couture Sabine",
    "wof:placetype":"venue"
},
  "geometry": {"coordinates":[4.3359460831,50.797454834],"type":"Point"}
}