{
  "type": "Feature",
  "properties": {
    "iso:country":"BE",
    "sg:address":"Kuildamstraat 73",
    "sg:city":"Sint-niklaas",
    "sg:classifiers":[
        {
            "category":"Real Estate",
            "subcategory":"Architect",
            "type":"Services"
        }
    ],
    "sg:phone":"+32 3 778 09 34",
    "sg:postcode":"9100",
    "sg:province":"Oost-Vlaanderen",
    "wof:name":"Vandecappelle P",
    "wof:placetype":"venue"
},
  "geometry": {"coordinates":[4.1293921471,51.1800689697],"type":"Point"}
}