{
  "type": "Feature",
  "properties": {
    "iso:country":"BE",
    "sg:address":"Bouwelsesteenweg 293",
    "sg:city":"Nijlen",
    "sg:classifiers":[
        {
            "category":"Real Estate",
            "subcategory":"Architect",
            "type":"Services"
        }
    ],
    "sg:phone":"+32 3 411 01 69",
    "sg:postcode":"2560",
    "sg:province":"Antwerpen",
    "wof:name":"Docx F",
    "wof:placetype":"venue"
},
  "geometry": {"coordinates":[4.7037482262,51.1637535095],"type":"Point"}
}