{
  "type": "Feature",
  "properties": {
    "iso:country":"BE",
    "sg:address":"Rue De La Gaume 188",
    "sg:city":"Tintigny",
    "sg:orig_category":"Installatie van houten of kunststof schrijnwerk",
    "sg:phone":"+32 63 44 43 15",
    "sg:postcode":"6730",
    "sg:province":"Luxembourg",
    "wof:name":"Andre Flamion",
    "wof:placetype":"venue"
},
  "geometry": {"coordinates":[5.4957580566,49.6641120911],"type":"Point"}
}