{
  "type": "Feature",
  "properties": {
    "iso:country":"BE",
    "sg:address":"Heirebaan 355",
    "sg:city":"Ninove (denderwindeke)",
    "sg:classifiers":[
        {
            "category":"Food & Beverages",
            "subcategory":"Dairy",
            "type":"Retail Goods"
        }
    ],
    "sg:phone":"+32 54 33 04 10",
    "sg:postcode":"9400",
    "sg:province":"Oost-Vlaanderen",
    "sg:tags":[
        "product",
        "-"
    ],
    "wof:name":"Sijmoens B",
    "wof:placetype":"venue"
},
  "geometry": {"coordinates":[3.9940600395,50.7946395874],"type":"Point"}
}