{
  "type": "Feature",
  "properties": {
    "iso:country":"BE",
    "sg:address":"Mellestraat 28",
    "sg:city":"Gent (ledeberg)",
    "sg:classifiers":[
        {
            "category":"Professional",
            "type":"Services"
        }
    ],
    "sg:phone":"+32 9 231 12 71",
    "sg:postcode":"9050",
    "sg:province":"Oost-Vlaanderen",
    "sg:tags":[
        "entertainer"
    ],
    "wof:name":"Clown Loki",
    "wof:placetype":"venue"
},
  "geometry": {"coordinates":[3.7574350834,51.0231781006],"type":"Point"}
}