{
  "type": "Feature",
  "properties": {
    "addr:full":"Weg Naar As 50 Genk Limburg 3600",
    "addr:housenumber":"50",
    "addr:postcode":"3600",
    "addr:street":"Weg Naar As",
    "iso:country":"BE",
    "sg:address":"Weg Naar As 50",
    "sg:city":"Genk",
    "sg:orig_category":"Enseignement sup\u00e9rieur",
    "sg:phone":"+32 89 30 08 50",
    "sg:postcode":"3600",
    "sg:province":"Limburg",
    "wof:name":"Katholieke Hogeschool",
    "wof:placetype":"venue"
},
  "geometry": {"coordinates":[5.5082249641,50.9684944153],"type":"Point"}
}