{
  "type": "Feature",
  "properties": {
    "iso:country":"BE",
    "sg:address":"Nedergemlaan 1980",
    "sg:city":"Zemst",
    "sg:orig_category":"Tuinen",
    "sg:phone":"+32 15 62 38 38",
    "sg:postcode":"1980",
    "sg:province":"Vlaams-Brabant",
    "wof:name":"Hilderson",
    "wof:placetype":"venue"
},
  "geometry": {"coordinates":[4.4579200745,50.9658584595],"type":"Point"}
}