{
  "type": "Feature",
  "properties": {
    "iso:country":"BE",
    "sg:address":"Chemin De La Bardane 18",
    "sg:city":"Ottignies-louvain-la-neuve",
    "sg:orig_category":"Administration d'immeubles. Agences immobili\u00e8res",
    "sg:phone":"+32 10 45 11 45",
    "sg:postcode":"1348",
    "sg:province":"Brabant Wallon",
    "wof:name":"Agence Eckelmans",
    "wof:placetype":"venue"
},
  "geometry": {"coordinates":[4.6112890244,50.6715202332],"type":"Point"}
}