{
  "type": "Feature",
  "properties": {
    "iso:country":"BE",
    "sg:address":"Krekelstraat 17",
    "sg:city":"Ingelmunster",
    "sg:classifiers":[
        {
            "category":"Freight",
            "type":"Transportation"
        }
    ],
    "sg:phone":"+32 51 48 70 00",
    "sg:postcode":"8770",
    "sg:province":"West-Vlaanderen",
    "sg:tags":[
        "-",
        "transport"
    ],
    "wof:name":"Transluca",
    "wof:placetype":"venue"
},
  "geometry": {"coordinates":[3.2801139355,50.9186058044],"type":"Point"}
}