{
  "type": "Feature",
  "properties": {
    "addr:full":"Rue Des Wallons 4 Ottignies-louvain-la-neuve Brabant Wallon 1348",
    "addr:housenumber":"4",
    "addr:postcode":"1348",
    "addr:street":"Rue Des Wallons",
    "iso:country":"BE",
    "sg:address":"Rue Des Wallons 4",
    "sg:city":"Ottignies-louvain-la-neuve",
    "sg:classifiers":[
        {
            "category":"Restaurant",
            "type":"Food & Drink"
        }
    ],
    "sg:phone":"+32 10 45 27 85",
    "sg:postcode":"1348",
    "sg:province":"Brabant Wallon",
    "wof:name":"Snack Bar Panibel",
    "wof:placetype":"venue"
},
  "geometry": {"coordinates":[4.6151990891,50.66954422],"type":"Point"}
}