{
  "type": "Feature",
  "properties": {
    "iso:country":"BE",
    "sg:address":"Vosveld 19",
    "sg:city":"Wijnegem",
    "sg:classifiers":[
        {
            "category":"Food & Beverages",
            "subcategory":"Groceries & Convenience Stores",
            "type":"Retail Goods"
        }
    ],
    "sg:phone":"+32 3 326 26 11",
    "sg:postcode":"2110",
    "sg:province":"Antwerpen",
    "sg:tags":[
        "product",
        "related"
    ],
    "wof:name":"Vagro Nv",
    "wof:placetype":"venue"
},
  "geometry": {"coordinates":[4.4957489967,51.2315979004],"type":"Point"}
}