{
  "type": "Feature",
  "properties": {
    "iso:country":"BE",
    "sg:address":"Kerselaarlaan 26",
    "sg:city":"Boom",
    "sg:orig_category":"Epiceries",
    "sg:phone":"+32 3 888 18 04",
    "sg:postcode":"2850",
    "sg:province":"Antwerpen",
    "wof:name":"Huis Sonja",
    "wof:placetype":"venue"
},
  "geometry": {"coordinates":[4.3702349663,51.1030158997],"type":"Point"}
}