{
  "type": "Feature",
  "properties": {
    "addr:full":"Rue Conrad-d'argenteau 8 Sombreffe Namur 5140",
    "addr:housenumber":"8",
    "addr:postcode":"5140",
    "addr:street":"Rue Conrad-D'Argenteau",
    "iso:country":"BE",
    "sg:address":"Rue Conrad-d'argenteau 8",
    "sg:city":"Sombreffe",
    "sg:orig_category":"M\u00e9decins and sp\u00e9cialistes",
    "sg:phone":"+32 71 88 99 26",
    "sg:postcode":"5140",
    "sg:province":"Namur",
    "wof:name":"E. Coquelet",
    "wof:placetype":"venue"
},
  "geometry": {"coordinates":[4.57523489,50.5163650513],"type":"Point"}
}