{
  "type": "Feature",
  "properties": {
    "iso:country":"BE",
    "sg:address":"Rue Grisar 44",
    "sg:city":"Bruxelles (anderlecht)",
    "sg:orig_category":"Non-Classified Establishments",
    "sg:phone":"+32 2 522 16 46",
    "sg:postcode":"1070",
    "sg:province":"Bruxelles-Capitale",
    "wof:name":"Elite",
    "wof:placetype":"venue"
},
  "geometry": {"coordinates":[4.3331007957,50.8379898071],"type":"Point"}
}