{
  "type": "Feature",
  "properties": {
    "iso:country":"BE",
    "sg:address":"Rue Nestor-bouillon 2",
    "sg:city":"Somme-leuze",
    "sg:orig_category":"Rundveehouders",
    "sg:phone":"+32 83 68 84 79",
    "sg:postcode":"5377",
    "sg:province":"Namur",
    "wof:name":"Christian Baudoin",
    "wof:placetype":"venue"
},
  "geometry": {"coordinates":[5.248857975,50.2690124512],"type":"Point"}
}