{
  "type": "Feature",
  "properties": {
    "addr:full":"Chauss\u00c9e De Fleurus 49bb Charleroi Hainaut 6041",
    "addr:housenumber":"49bb",
    "addr:postcode":"6041",
    "addr:street":"Chausse\u0301E De Fleurus;Hainaut",
    "iso:country":"BE",
    "sg:address":"Chauss\u00c9e De Fleurus 49bb",
    "sg:city":"Charleroi",
    "sg:orig_category":"Dakwerken",
    "sg:phone":"+32 71 37 05 89",
    "sg:postcode":"6041",
    "sg:province":"Hainaut",
    "wof:name":"G\u00c9n\u00c9ral B\u00c2timent",
    "wof:placetype":"venue"
},
  "geometry": {"coordinates":[4.4729399681,50.441242218],"type":"Point"}
}