{
  "type": "Feature",
  "properties": {
    "addr:full":"Bergstraat 104 Kortrijk (marke) West-Vlaanderen 8510",
    "addr:housenumber":"104",
    "addr:postcode":"8510",
    "addr:street":"Bergstraat",
    "iso:country":"BE",
    "sg:address":"Bergstraat 104",
    "sg:city":"Kortrijk (marke)",
    "sg:orig_category":"Rainwear",
    "sg:phone":"+32 56 41 37 75",
    "sg:postcode":"8510",
    "sg:province":"West-Vlaanderen",
    "wof:name":"Montaine",
    "wof:placetype":"venue"
},
  "geometry": {"coordinates":[3.2388119698,50.775680542],"type":"Point"}
}