{
  "type": "Feature",
  "properties": {
    "iso:country":"BE",
    "sg:address":"Natendries 55",
    "sg:city":"Oudenaarde",
    "sg:classifiers":[
        {
            "category":"Arena",
            "subcategory":"Sports Club",
            "type":"Entertainment"
        }
    ],
    "sg:phone":"+32 55 31 17 40",
    "sg:postcode":"9700",
    "sg:province":"Oost-Vlaanderen",
    "sg:tags":[
        "terrain",
        "hors",
        "de",
        "installation",
        "sportifs"
    ],
    "wof:name":"Ladies Oudenaarde",
    "wof:placetype":"venue"
},
  "geometry": {"coordinates":[3.6448779106,50.8439102173],"type":"Point"}
}