{
  "type": "Feature",
  "properties": {
    "iso:country":"BE",
    "sg:address":"Sterrewachtlaan 2",
    "sg:city":"Ukkel/uccle",
    "sg:orig_category":"Beheer onroerend goed",
    "sg:phone":"+32 2 375 55 08",
    "sg:postcode":"1180",
    "sg:province":"Bruxelles-Capitale",
    "wof:name":"Gifico",
    "wof:placetype":"venue"
},
  "geometry": {"coordinates":[4.3721752167,50.8050384521],"type":"Point"}
}