{
  "type": "Feature",
  "properties": {
    "addr:full":"Middelmolenlaan 121 Antwerpen Antwerpen 2100",
    "addr:housenumber":"121",
    "addr:postcode":"2100",
    "addr:street":"Middelmolenlaan",
    "iso:country":"BE",
    "sg:address":"Middelmolenlaan 121",
    "sg:city":"Antwerpen",
    "sg:orig_category":"Drukkerijen and copyshops",
    "sg:phone":"+32 3 360 80 80",
    "sg:postcode":"2100",
    "sg:province":"Antwerpen",
    "wof:name":"Universitas",
    "wof:placetype":"venue"
},
  "geometry": {"coordinates":[4.4586100578,51.2203941345],"type":"Point"}
}