{
  "type": "Feature",
  "properties": {
    "addr:full":"Mooremandestraat 3 Tielt West-Vlaanderen 8700",
    "addr:housenumber":"3",
    "addr:postcode":"8700",
    "addr:street":"Mooremandestraat",
    "iso:country":"BE",
    "sg:address":"Mooremandestraat 3",
    "sg:city":"Tielt",
    "sg:orig_category":"Rundveehouders Varkenskwekers",
    "sg:phone":"+32 51 68 89 57",
    "sg:postcode":"8700",
    "sg:province":"West-Vlaanderen",
    "wof:name":"Gentiel Bollaert",
    "wof:placetype":"venue"
},
  "geometry": {"coordinates":[3.4251570702,51.0228843689],"type":"Point"}
}