{
  "type": "Feature",
  "properties": {
    "iso:country":"BE",
    "sg:address":"Heerbaan 44",
    "sg:city":"Harelbeke",
    "sg:orig_category":"Imprimeries and copyshops. Agences de publicit\u00e9",
    "sg:phone":"+32 56 71 62 20",
    "sg:postcode":"8530",
    "sg:province":"West-Vlaanderen",
    "wof:name":"Publideba",
    "wof:placetype":"venue"
},
  "geometry": {"coordinates":[3.31229496,50.8474502563],"type":"Point"}
}