{
  "type": "Feature",
  "properties": {
    "iso:country":"BE",
    "sg:address":"Rue Cit\u00e9 Du Chestia 3",
    "sg:city":"Profondeville (bois-de-villers)",
    "sg:classifiers":[
        {
            "category":"Home & Garden",
            "subcategory":"Carpets & Floor Coverings",
            "type":"Retail Goods"
        }
    ],
    "sg:phone":"+32 81 43 39 49",
    "sg:postcode":"5170",
    "sg:province":"Namur",
    "sg:tags":[
        "layer",
        "mosaicists"
    ],
    "wof:name":"Blanchy J",
    "wof:placetype":"venue"
},
  "geometry": {"coordinates":[4.8674049377,50.3786392212],"type":"Point"}
}