{
  "type": "Feature",
  "properties": {
    "iso:country":"BE",
    "sg:address":"Rue De Fragn\u00c9e 182",
    "sg:city":"Liege",
    "sg:classifiers":[
        {
            "category":"Restaurant",
            "type":"Food & Drink"
        }
    ],
    "sg:phone":"+32 4 253 58 54",
    "sg:postcode":"4000",
    "sg:province":"Li\u00e8ge",
    "wof:name":"Song-long",
    "wof:placetype":"venue"
},
  "geometry": {"coordinates":[5.5731010437,50.6215744019],"type":"Point"}
}