{
  "type": "Feature",
  "properties": {
    "addr:full":"Misstraat 109 Lier (koningshooikt) Antwerpen 2500",
    "addr:housenumber":"109",
    "addr:postcode":"2500",
    "addr:street":"Misstraat",
    "iso:country":"BE",
    "sg:address":"Misstraat 109",
    "sg:city":"Lier (koningshooikt)",
    "sg:classifiers":[
        {
            "category":"Retail",
            "subcategory":"Auto Repair",
            "type":"Services"
        }
    ],
    "sg:phone":"+32 3 482 13 47",
    "sg:postcode":"2500",
    "sg:province":"Antwerpen",
    "sg:tags":[
        "garage"
    ],
    "wof:name":"Garage Nauwelaerts Eddy Bvba",
    "wof:placetype":"venue"
},
  "geometry": {"coordinates":[4.6156458855,51.1004104614],"type":"Point"}
}