{
  "type": "Feature",
  "properties": {
    "iso:country":"BE",
    "sg:address":"Stationsstraat 14",
    "sg:city":"Asse",
    "sg:orig_category":"Bloemen and planten",
    "sg:phone":"+32 2 453 03 92",
    "sg:postcode":"1730",
    "sg:province":"Vlaams-Brabant",
    "wof:name":"Laurus",
    "wof:placetype":"venue"
},
  "geometry": {"coordinates":[4.2047319412,50.907787323],"type":"Point"}
}