{
  "type": "Feature",
  "properties": {
    "iso:country":"BE",
    "sg:address":"Grand'rue 49",
    "sg:city":"Clavier (ocquier)",
    "sg:classifiers":[
        {
            "category":"Building & Trades",
            "subcategory":"Pest Control",
            "type":"Services"
        }
    ],
    "sg:phone":"+32 86 34 44 26",
    "sg:postcode":"4560",
    "sg:province":"Li\u00e8ge",
    "sg:tags":[
        "painting",
        "contractor"
    ],
    "wof:name":"Michotte J Sprl",
    "wof:placetype":"venue"
},
  "geometry": {"coordinates":[5.3246378899,50.4303741455],"type":"Point"}
}