{
  "type": "Feature",
  "properties": {
    "iso:country":"BE",
    "sg:address":"Rue Falleur Et Schmidt 32",
    "sg:city":"Charleroi",
    "sg:orig_category":"P\u00e9pini\u00e9ristes",
    "sg:phone":"+32 71 43 16 50",
    "sg:postcode":"6001",
    "sg:province":"Hainaut",
    "wof:name":"Arbres De Noel",
    "wof:placetype":"venue"
},
  "geometry": {"coordinates":[4.431912899,50.3992195129],"type":"Point"}
}