{
  "type": "Feature",
  "properties": {
    "iso:country":"BE",
    "sg:address":"Grand-route 174",
    "sg:city":"Bassenge",
    "sg:orig_category":"Rev\u00eatements pour sols and murs",
    "sg:phone":"+32 4 286 24 77",
    "sg:postcode":"4690",
    "sg:province":"Li\u00e8ge",
    "wof:name":"Jean Trioux",
    "wof:placetype":"venue"
},
  "geometry": {"coordinates":[5.6412301064,50.768913269],"type":"Point"}
}