{
  "type": "Feature",
  "properties": {
    "iso:country":"BE",
    "sg:address":"Galgeneinde 73",
    "sg:city":"Heusden-zolder (zolder)",
    "sg:classifiers":[
        {
            "category":"Wholesale",
            "subcategory":"Meat",
            "type":"Manufacturing & Wholesale Goods"
        }
    ],
    "sg:phone":"+32 11 25 05 05",
    "sg:postcode":"3550",
    "sg:province":"Limburg",
    "sg:tags":[
        "whol",
        "-"
    ],
    "wof:name":"Bubo Bvba",
    "wof:placetype":"venue"
},
  "geometry": {"coordinates":[5.2662820816,50.9854011536],"type":"Point"}
}