{
  "type": "Feature",
  "properties": {
    "iso:country":"BE",
    "sg:address":"Rue Des Ecoles 121",
    "sg:city":"Comblain-au-pont (poulseur)",
    "sg:classifiers":[
        {
            "category":"Home & Garden",
            "subcategory":"Building Materials",
            "type":"Retail Goods"
        }
    ],
    "sg:phone":"+32 4 380 37 00",
    "sg:postcode":"4171",
    "sg:province":"Li\u00e8ge",
    "sg:tags":[
        "granite",
        "stone",
        "natural",
        "marble"
    ],
    "wof:name":"Mathy Sprl",
    "wof:placetype":"venue"
},
  "geometry": {"coordinates":[5.5891900063,50.5086631775],"type":"Point"}
}