{
  "type": "Feature",
  "properties": {
    "addr:full":"Rue Du Vicinal 26 Hamoir Li\u00e8ge 4180",
    "addr:housenumber":"26",
    "addr:postcode":"4180",
    "addr:street":"Rue Du Vicinal",
    "iso:country":"BE",
    "sg:address":"Rue Du Vicinal 26",
    "sg:city":"Hamoir",
    "sg:orig_category":"Installation de menuiserie en bois and plastique",
    "sg:phone":"+32 4 369 25 62",
    "sg:postcode":"4180",
    "sg:province":"Li\u00e8ge",
    "wof:name":"Laurent Levert",
    "wof:placetype":"venue"
},
  "geometry": {"coordinates":[5.5677847862,50.4594573975],"type":"Point"}
}