{
  "type": "Feature",
  "properties": {
    "addr:full":"Rue Chamelot 1 Esneux Li\u00e8ge 4130",
    "addr:housenumber":"1",
    "addr:postcode":"4130",
    "addr:street":"Rue Chamelot",
    "iso:country":"BE",
    "sg:address":"Rue Chamelot 1",
    "sg:city":"Esneux",
    "sg:classifiers":[
        {
            "category":"Health Services",
            "subcategory":"Dentist",
            "type":"Services"
        }
    ],
    "sg:phone":"+32 4 380 32 61",
    "sg:postcode":"4130",
    "sg:province":"Li\u00e8ge",
    "wof:name":"Goffart Fran\u00e7ois",
    "wof:placetype":"venue"
},
  "geometry": {"coordinates":[5.5683441162,50.5342597961],"type":"Point"}
}