{
  "type": "Feature",
  "properties": {
    "iso:country":"BE",
    "sg:address":"Herentalse Steenweg 28",
    "sg:city":"Herenthout",
    "sg:classifiers":[
        {
            "category":"Home & Garden",
            "subcategory":"Kitchen Supply",
            "type":"Retail Goods"
        }
    ],
    "sg:phone":"+32 14 51 30 16",
    "sg:postcode":"2270",
    "sg:province":"Antwerpen",
    "sg:tags":[
        "installation"
    ],
    "wof:name":"Cambre Roger",
    "wof:placetype":"venue"
},
  "geometry": {"coordinates":[4.7755441666,51.1412887573],"type":"Point"}
}