{
  "type": "Feature",
  "properties": {
    "addr:full":"Winkelomstraat 54 Bilzen Limburg 3740",
    "addr:housenumber":"54",
    "addr:postcode":"3740",
    "addr:street":"Winkelomstraat",
    "iso:country":"BE",
    "sg:address":"Winkelomstraat 54",
    "sg:city":"Bilzen",
    "sg:orig_category":"Rundveehouders",
    "sg:phone":"+32 89 41 32 90",
    "sg:postcode":"3740",
    "sg:province":"Limburg",
    "wof:name":"Guido Jans",
    "wof:placetype":"venue"
},
  "geometry": {"coordinates":[5.5856451988,50.8739509583],"type":"Point"}
}