{
  "type": "Feature",
  "properties": {
    "iso:country":"BE",
    "sg:address":"Titecastraat 80a",
    "sg:city":"Brugge (sint-michiels)",
    "sg:classifiers":[
        {
            "category":"Education",
            "subcategory":"Dance Studio",
            "type":"Public Place"
        }
    ],
    "sg:phone":"+32 50 39 03 56",
    "sg:postcode":"8200",
    "sg:province":"West-Vlaanderen",
    "sg:tags":[
        "school",
        "dancing"
    ],
    "wof:name":"Het Danshuis Tamara Jackson",
    "wof:placetype":"venue"
},
  "geometry": {"coordinates":[3.2034699917,51.1934318542],"type":"Point"}
}