{
  "type": "Feature",
  "properties": {
    "iso:country":"BE",
    "sg:address":"Noordmoerstraat 12",
    "sg:city":"Veurne",
    "sg:orig_category":"Fruits and l\u00e9gumes Eleveurs and marchands de porcs",
    "sg:phone":"+32 58 29 91 46",
    "sg:postcode":"8630",
    "sg:province":"West-Vlaanderen",
    "wof:name":"Albert Mergaert",
    "wof:placetype":"venue"
},
  "geometry": {"coordinates":[2.6146850586,51.0472145081],"type":"Point"}
}