{
  "type": "Feature",
  "properties": {
    "iso:country":"BE",
    "sg:address":"Stationsstraat 51b2",
    "sg:city":"Neerpelt",
    "sg:orig_category":"Kapsalons",
    "sg:phone":"+32 11 80 62 12",
    "sg:postcode":"3910",
    "sg:province":"Limburg",
    "wof:name":"Coiffure Schrijvers",
    "wof:placetype":"venue"
},
  "geometry": {"coordinates":[5.4374790192,51.2248878479],"type":"Point"}
}