{
  "type": "Feature",
  "properties": {
    "addr:full":"Rue Rogier 28 Tournai Hainaut 7500",
    "addr:housenumber":"28",
    "addr:postcode":"7500",
    "addr:street":"Rue Rogier",
    "iso:country":"BE",
    "sg:address":"Rue Rogier 28",
    "sg:city":"Tournai",
    "sg:classifiers":[
        {
            "category":"Health Services",
            "subcategory":"Health Practitioner",
            "type":"Services"
        }
    ],
    "sg:phone":"+32 69 23 47 72",
    "sg:postcode":"7500",
    "sg:province":"Hainaut",
    "sg:tags":[
        "physiotherapist"
    ],
    "wof:name":"D'odorico J-p",
    "wof:placetype":"venue"
},
  "geometry": {"coordinates":[3.3894710541,50.6010971069],"type":"Point"}
}