{
  "type": "Feature",
  "properties": {
    "iso:country":"BE",
    "sg:address":"Nationalestraat 114ba",
    "sg:city":"Antwerpen",
    "sg:classifiers":[
        {
            "category":"Restaurant",
            "type":"Food & Drink"
        }
    ],
    "sg:phone":"+32 3 237 55 97",
    "sg:postcode":"2000",
    "sg:province":"Antwerpen",
    "wof:name":"Centre Ville",
    "wof:placetype":"venue"
},
  "geometry": {"coordinates":[4.3981041908,51.2141685486],"type":"Point"}
}