{
  "type": "Feature",
  "properties": {
    "iso:country":"BE",
    "sg:address":"Wijngaardstraat 10",
    "sg:city":"Bilzen",
    "sg:orig_category":"Bijouteries and horlogeries",
    "sg:phone":"+32 89 41 86 20",
    "sg:postcode":"3740",
    "sg:province":"Limburg",
    "wof:name":"Marcel Fransen",
    "wof:placetype":"venue"
},
  "geometry": {"coordinates":[5.5254101753,50.8879699707],"type":"Point"}
}