{
  "type": "Feature",
  "properties": {
    "iso:country":"BE",
    "sg:address":"Torhoutsesteenweg 222ba",
    "sg:city":"Zedelgem",
    "sg:orig_category":"Installatie van houten of kunststof schrijnwerk",
    "sg:phone":"+32 50 24 02 36",
    "sg:postcode":"8210",
    "sg:province":"West-Vlaanderen",
    "wof:name":"Vercaemst",
    "wof:placetype":"venue"
},
  "geometry": {"coordinates":[3.1576468945,51.1365127563],"type":"Point"}
}