{
  "type": "Feature",
  "properties": {
    "addr:full":"Grote Baan 124 Aalst (herdersem) Oost-Vlaanderen 9310",
    "addr:housenumber":"124",
    "addr:postcode":"9310",
    "addr:street":"Grote Baan",
    "iso:country":"BE",
    "sg:address":"Grote Baan 124",
    "sg:city":"Aalst (herdersem)",
    "sg:classifiers":[
        {
            "category":"Freight",
            "type":"Transportation"
        }
    ],
    "sg:phone":"+32 53 70 46 66",
    "sg:postcode":"9310",
    "sg:province":"Oost-Vlaanderen",
    "sg:tags":[
        "-",
        "transport"
    ],
    "wof:name":"De Smet",
    "wof:placetype":"venue"
},
  "geometry": {"coordinates":[4.0634942055,50.9670639038],"type":"Point"}
}