{
  "type": "Feature",
  "properties": {
    "addr:full":"Rue De Bitremont 71 Antoing Hainaut 7640",
    "addr:housenumber":"71",
    "addr:postcode":"7640",
    "addr:street":"Rue De Bitremont",
    "iso:country":"BE",
    "sg:address":"Rue De Bitremont 71",
    "sg:city":"Antoing",
    "sg:orig_category":"Activit\u00e9s r\u00e9cr\u00e9atives diverses",
    "sg:phone":"+32 69 84 21 02",
    "sg:postcode":"7640",
    "sg:province":"Hainaut",
    "wof:name":"Les Fun Flyers",
    "wof:placetype":"venue"
},
  "geometry": {"coordinates":[3.4519898891,50.565738678],"type":"Point"}
}