{
  "type": "Feature",
  "properties": {
    "iso:country":"BE",
    "sg:address":"Spiegelstraat 23",
    "sg:city":"Sint-truiden",
    "sg:classifiers":[
        {
            "category":"Professional",
            "subcategory":"Accounting & Tax Preparation",
            "type":"Services"
        }
    ],
    "sg:phone":"+32 495 52 20 55",
    "sg:postcode":"3800",
    "sg:province":"Limburg",
    "sg:tags":[
        "bookkeeper"
    ],
    "wof:name":"Janssen D",
    "wof:placetype":"venue"
},
  "geometry": {"coordinates":[5.1857790947,50.8117980957],"type":"Point"}
}