{
  "type": "Feature",
  "properties": {
    "iso:country":"BE",
    "sg:address":"Turnhoutsebaan 413",
    "sg:city":"Schilde",
    "sg:orig_category":"Herstellingen and onderhoud van auto's",
    "sg:phone":"+32 3 385 89 09",
    "sg:postcode":"2970",
    "sg:province":"Antwerpen",
    "wof:name":"Soft & Shine",
    "wof:placetype":"venue"
},
  "geometry": {"coordinates":[4.6071572304,51.2504234314],"type":"Point"}
}