{
  "type": "Feature",
  "properties": {
    "iso:country":"BE",
    "sg:address":"Place 12",
    "sg:city":"Tournai (esplechin)",
    "sg:classifiers":[
        {
            "category":"Personal",
            "subcategory":"Beauty Salon",
            "type":"Services"
        }
    ],
    "sg:phone":"+32 69 64 07 88",
    "sg:postcode":"7502",
    "sg:province":"Hainaut",
    "sg:tags":[
        "lady",
        "-",
        "hairdressing"
    ],
    "wof:name":"Duquesne B",
    "wof:placetype":"venue"
},
  "geometry": {"coordinates":[3.3065268993,50.5743675232],"type":"Point"}
}