{
  "type": "Feature",
  "properties": {
    "addr:full":"Koning Maria Hendrikaplein 2 Melle Oost-Vlaanderen 9090",
    "addr:housenumber":"2",
    "addr:postcode":"9090",
    "addr:street":"Koning Maria Hendrikaplein",
    "iso:country":"BE",
    "sg:address":"Koning Maria Hendrikaplein 2",
    "sg:city":"Melle",
    "sg:orig_category":"Treinen and spoorwegen",
    "sg:phone":"+32 9 241 36 35",
    "sg:postcode":"9090",
    "sg:province":"Oost-Vlaanderen",
    "wof:name":"Station Melle",
    "wof:placetype":"venue"
},
  "geometry": {"coordinates":[3.8026149273,51.0023956299],"type":"Point"}
}