{
  "type": "Feature",
  "properties": {
    "addr:full":"Dorpstraat 332 Bertem Vlaams-Brabant 3061",
    "addr:housenumber":"332",
    "addr:postcode":"3061",
    "addr:street":"Dorpstraat",
    "iso:country":"BE",
    "sg:address":"Dorpstraat 332",
    "sg:city":"Bertem",
    "sg:orig_category":"Plomberie, chauffage and installations sanitaires",
    "sg:phone":"+32 16 48 01 68",
    "sg:postcode":"3061",
    "sg:province":"Vlaams-Brabant",
    "wof:name":"Huyberechts Gebroeders",
    "wof:placetype":"venue"
},
  "geometry": {"coordinates":[4.6039161682,50.8535270691],"type":"Point"}
}