{
  "type": "Feature",
  "properties": {
    "iso:country":"BE",
    "sg:address":"Rue Des Chardons 44 Box 6",
    "sg:city":"Bruxelles (schaerbeek)",
    "sg:classifiers":[
        {
            "category":"Professional",
            "subcategory":"Secretarial Services",
            "type":"Services"
        }
    ],
    "sg:phone":"+32 476 44 35 72",
    "sg:postcode":"1030",
    "sg:province":"Bruxelles-Capitale",
    "sg:tags":[
        "firm"
    ],
    "wof:name":"Gecoplan",
    "wof:placetype":"venue"
},
  "geometry": {"coordinates":[4.3926057816,50.8582038879],"type":"Point"}
}