{
  "type": "Feature",
  "properties": {
    "addr:full":"Schoonaerde 20 Diest Vlaams-Brabant 3290",
    "addr:housenumber":"20",
    "addr:postcode":"3290",
    "addr:street":"Schoonaerde",
    "iso:country":"BE",
    "sg:address":"Schoonaerde 20",
    "sg:city":"Diest",
    "sg:classifiers":[
        {
            "category":"Personal",
            "subcategory":"Beauty Salon",
            "type":"Services"
        }
    ],
    "sg:phone":"+32 13 33 57 84",
    "sg:postcode":"3290",
    "sg:province":"Vlaams-Brabant",
    "sg:tags":[
        "de",
        "coiffure"
    ],
    "wof:name":"Coiffure Pascale",
    "wof:placetype":"venue"
},
  "geometry": {"coordinates":[5.0694208145,50.9949417114],"type":"Point"}
}