{
  "type": "Feature",
  "properties": {
    "iso:country":"BE",
    "sg:address":"Schapestraat 59",
    "sg:city":"Merelbeke",
    "sg:orig_category":"Plantes and fleurs Gr",
    "sg:phone":"+32 9 252 16 93",
    "sg:postcode":"9820",
    "sg:province":"Oost-Vlaanderen",
    "wof:name":"De Bosscher",
    "wof:placetype":"venue"
},
  "geometry": {"coordinates":[3.7592918873,50.9830131531],"type":"Point"}
}