{
  "type": "Feature",
  "properties": {
    "addr:full":"Hoogstraat 21 Roeselare West-Vlaanderen 8800",
    "addr:housenumber":"21",
    "addr:postcode":"8800",
    "addr:street":"Hoogstraat",
    "iso:country":"BE",
    "sg:address":"Hoogstraat 21",
    "sg:city":"Roeselare",
    "sg:orig_category":"Woningbouw",
    "sg:phone":"+32 51 20 52 18",
    "sg:postcode":"8800",
    "sg:province":"West-Vlaanderen",
    "wof:name":"Heli Corneillie",
    "wof:placetype":"venue"
},
  "geometry": {"coordinates":[3.1463499069,50.9309806824],"type":"Point"}
}