{
  "type": "Feature",
  "properties": {
    "addr:full":"Marktstraat 40 Box 3 Opwijk Vlaams-Brabant 1745",
    "addr:housenumber":"40;3",
    "addr:postcode":"1745",
    "addr:street":"Marktstraat;Box",
    "iso:country":"BE",
    "sg:address":"Marktstraat 40 Box 3",
    "sg:city":"Opwijk",
    "sg:classifiers":[
        {
            "category":"Professional",
            "subcategory":"Art Services",
            "type":"Services"
        }
    ],
    "sg:phone":"+32 52 35 21 83",
    "sg:postcode":"1745",
    "sg:province":"Vlaams-Brabant",
    "sg:tags":[
        "graphic",
        "designer"
    ],
    "wof:name":"Drv Visual Marketing",
    "wof:placetype":"venue"
},
  "geometry": {"coordinates":[4.189743042,50.9694023132],"type":"Point"}
}