{
  "type": "Feature",
  "properties": {
    "addr:full":"Toekomstlaan 14 Lokeren Oost-Vlaanderen 9160",
    "addr:housenumber":"14",
    "addr:postcode":"9160",
    "addr:street":"Toekomstlaan",
    "iso:country":"BE",
    "sg:address":"Toekomstlaan 14",
    "sg:city":"Lokeren",
    "sg:orig_category":"Herstellingen and onderhoud aan huis voor voertuigen Metaalafval, schrootrecyclage and sloperijen",
    "sg:phone":"+32 9 349 61 48",
    "sg:postcode":"9160",
    "sg:province":"Oost-Vlaanderen",
    "wof:name":"J. Meiresonne",
    "wof:placetype":"venue"
},
  "geometry": {"coordinates":[4.0143399239,51.1176490784],"type":"Point"}
}