{
  "type": "Feature",
  "properties": {
    "addr:full":"Dendermondesteenweg 475 Destelbergen Oost-Vlaanderen 9070",
    "addr:housenumber":"475",
    "addr:postcode":"9070",
    "addr:street":"Dendermondesteenweg",
    "iso:country":"BE",
    "sg:address":"Dendermondesteenweg 475",
    "sg:city":"Destelbergen",
    "sg:orig_category":"Verplichte sociale verzekeringen",
    "sg:phone":"+32 9 229 28 76",
    "sg:postcode":"9070",
    "sg:province":"Oost-Vlaanderen",
    "wof:name":"Christelijke Mutualiteit",
    "wof:placetype":"venue"
},
  "geometry": {"coordinates":[3.7988250256,51.0561714172],"type":"Point"}
}