{
  "type": "Feature",
  "properties": {
    "addr:full":"Olmense Markt 19 Balen Antwerpen 2491",
    "addr:housenumber":"19",
    "addr:postcode":"2491",
    "addr:street":"Olmense Markt",
    "iso:country":"BE",
    "sg:address":"Olmense Markt 19",
    "sg:city":"Balen",
    "sg:orig_category":"Banken and kredietinstellingen",
    "sg:phone":"+32 14 30 06 28",
    "sg:postcode":"2491",
    "sg:province":"Antwerpen",
    "wof:name":"Bacob",
    "wof:placetype":"venue"
},
  "geometry": {"coordinates":[5.1493639946,51.1420631409],"type":"Point"}
}