{
  "type": "Feature",
  "properties": {
    "iso:country":"BE",
    "sg:address":"Rue De Hotton 1",
    "sg:city":"Durbuy",
    "sg:orig_category":"Eleveurs de bovins",
    "sg:phone":"+32 86 21 18 17",
    "sg:postcode":"6940",
    "sg:province":"Luxembourg",
    "wof:name":"Isabelle Dujardin",
    "wof:placetype":"venue"
},
  "geometry": {"coordinates":[5.4543361664,50.3515777588],"type":"Point"}
}