{
  "type": "Feature",
  "properties": {
    "iso:country":"BE",
    "sg:address":"Pilootlaan 9",
    "sg:city":"Sint-pieters-woluwe",
    "sg:orig_category":"Woningbouw",
    "sg:phone":"+32 2 770 96 70",
    "sg:postcode":"1150",
    "sg:province":"Bruxelles-Capitale",
    "wof:name":"Ricci",
    "wof:placetype":"venue"
},
  "geometry": {"coordinates":[4.4456291199,50.8344078064],"type":"Point"}
}