{
  "type": "Feature",
  "properties": {
    "addr:full":"Rue Morchamps 133 Seraing Li\u00e8ge 4100",
    "addr:housenumber":"133",
    "addr:postcode":"4100",
    "addr:street":"Rue Morchamps",
    "iso:country":"BE",
    "sg:address":"Rue Morchamps 133",
    "sg:city":"Seraing",
    "sg:classifiers":[
        {
            "category":"Food & Beverages",
            "subcategory":"Groceries & Convenience Stores",
            "type":"Retail Goods"
        }
    ],
    "sg:phone":"+32 4 336 85 05",
    "sg:postcode":"4100",
    "sg:province":"Li\u00e8ge",
    "sg:tags":[
        "grocer"
    ],
    "wof:name":"Mariani E",
    "wof:placetype":"venue"
},
  "geometry": {"coordinates":[5.5138921738,50.6019058228],"type":"Point"}
}