{
  "type": "Feature",
  "properties": {
    "addr:full":"Destelbergenstraat 131 Gent (sint-amandsberg) Oost-Vlaanderen 9040",
    "addr:housenumber":"131",
    "addr:postcode":"9040",
    "addr:street":"Destelbergenstraat",
    "iso:country":"BE",
    "sg:address":"Destelbergenstraat 131",
    "sg:city":"Gent (sint-amandsberg)",
    "sg:classifiers":[
        {
            "category":"Banks & Credit Unions",
            "subcategory":"Investment Brokerage",
            "type":"Services"
        }
    ],
    "sg:phone":"+32 9 228 54 63",
    "sg:postcode":"9040",
    "sg:province":"Oost-Vlaanderen",
    "sg:tags":[
        "distributor",
        "-",
        "distributors",
        "physical"
    ],
    "wof:name":"Van Veirdeghem P",
    "wof:placetype":"venue"
},
  "geometry": {"coordinates":[3.7573349476,51.0516166687],"type":"Point"}
}