{
  "type": "Feature",
  "properties": {
    "addr:full":"Van Der Meerschenlaan 3 Sint-pieters-woluwe/woluwe-saint-pierre Bruxelles-Capitale 1150",
    "addr:housenumber":"3",
    "addr:postcode":"1150",
    "addr:street":"Van Der Meerschenlaan;/",
    "iso:country":"BE",
    "sg:address":"Van Der Meerschenlaan 3",
    "sg:city":"Sint-pieters-woluwe/woluwe-saint-pierre",
    "sg:orig_category":"Artsen and specialisten",
    "sg:phone":"+32 2 772 76 38",
    "sg:postcode":"1150",
    "sg:province":"Bruxelles-Capitale",
    "wof:name":"Christiane Hodje",
    "wof:placetype":"venue"
},
  "geometry": {"coordinates":[4.4572620392,50.8257369995],"type":"Point"}
}