{
  "type": "Feature",
  "properties": {
    "addr:full":"Atlantische Oceaanlaan 122 Sint-pieters-woluwe/woluwe-sai Bruxelles-Capitale 1150",
    "addr:housenumber":"122",
    "addr:postcode":"1150",
    "addr:street":"Atlantische Oceaanlaan",
    "iso:country":"BE",
    "sg:address":"Atlantische Oceaanlaan 122",
    "sg:city":"Sint-pieters-woluwe/woluwe-sai",
    "sg:orig_category":"Organisatie van beurzen, congressen and tentoonstellingen",
    "sg:phone":"+32 2 779 39 39",
    "sg:postcode":"1150",
    "sg:province":"Bruxelles-Capitale",
    "wof:name":"Resotel",
    "wof:placetype":"venue"
},
  "geometry": {"coordinates":[4.4186458588,50.8281097412],"type":"Point"}
}