{
  "type": "Feature",
  "properties": {
    "addr:full":"Rue Des P\u00c9pini\u00c8res 23 Soumagne Li\u00e8ge 4632",
    "addr:housenumber":"23",
    "addr:postcode":"4632",
    "addr:street":"Rue Des Pe\u0301Pinie\u0300Res",
    "iso:country":"BE",
    "sg:address":"Rue Des P\u00c9pini\u00c8res 23",
    "sg:city":"Soumagne",
    "sg:orig_category":"Herstellingen and onderhoud van auto's",
    "sg:phone":"+32 4 387 79 43",
    "sg:postcode":"4632",
    "sg:province":"Li\u00e8ge",
    "wof:name":"Louis Picili",
    "wof:placetype":"venue"
},
  "geometry": {"coordinates":[5.7155652046,50.6556129456],"type":"Point"}
}