{
  "type": "Feature",
  "properties": {
    "iso:country":"BE",
    "sg:address":"Rue Alfred Smeets 22",
    "sg:city":"Seraing",
    "sg:orig_category":"Boucheries",
    "sg:phone":"+32 4 337 26 09",
    "sg:postcode":"4100",
    "sg:province":"Li\u00e8ge",
    "wof:name":"Andre Gaspar",
    "wof:placetype":"venue"
},
  "geometry": {"coordinates":[5.5151529312,50.6051063538],"type":"Point"}
}