{
  "type": "Feature",
  "properties": {
    "iso:country":"BE",
    "sg:address":"De Vosdellestraat 15",
    "sg:city":"Houthalen-helchteren",
    "sg:orig_category":"Travaux de finition and nettoyage de b\u00e2timents",
    "sg:phone":"+32 11 52 46 93",
    "sg:postcode":"3530",
    "sg:province":"Limburg",
    "wof:name":"Diritec",
    "wof:placetype":"venue"
},
  "geometry": {"coordinates":[5.3639149666,51.0380897522],"type":"Point"}
}