{
  "type": "Feature",
  "properties": {
    "addr:full":"Meerlaan 25 Zottegem Oost-Vlaanderen 9620",
    "addr:housenumber":"25",
    "addr:postcode":"9620",
    "addr:street":"Meerlaan",
    "iso:country":"BE",
    "sg:address":"Meerlaan 25",
    "sg:city":"Zottegem",
    "sg:classifiers":[
        {
            "category":"Education",
            "subcategory":"School",
            "type":"Public Place"
        }
    ],
    "sg:phone":"+32 9 360 05 69",
    "sg:postcode":"9620",
    "sg:province":"Oost-Vlaanderen",
    "sg:tags":[
        "secondary"
    ],
    "wof:name":"Koninklijk Atheneum",
    "wof:placetype":"venue"
},
  "geometry": {"coordinates":[3.8101921082,50.8652191162],"type":"Point"}
}