{
  "type": "Feature",
  "properties": {
    "iso:country":"BE",
    "sg:address":"6\u00e8me Avenue 28",
    "sg:city":"Charleroi (marcinelle)",
    "sg:classifiers":[
        {
            "category":"Transit Center",
            "subcategory":"Freight",
            "type":"Transportation"
        }
    ],
    "sg:phone":"+32 71 36 22 98",
    "sg:postcode":"6001",
    "sg:province":"Hainaut",
    "sg:tags":[
        "import",
        "export",
        "-"
    ],
    "wof:name":"B.b. International Sprl",
    "wof:placetype":"venue"
},
  "geometry": {"coordinates":[4.4358391762,50.3542175293],"type":"Point"}
}