{
  "type": "Feature",
  "properties": {
    "addr:full":"Kastanjelaan 10 Overpelt Limburg 3900",
    "addr:housenumber":"10",
    "addr:postcode":"3900",
    "addr:street":"Kastanjelaan",
    "iso:country":"BE",
    "sg:address":"Kastanjelaan 10",
    "sg:city":"Overpelt",
    "sg:orig_category":"Kapsalons Mobiele kappers",
    "sg:phone":"+32 11 64 51 40",
    "sg:postcode":"3900",
    "sg:province":"Limburg",
    "wof:name":"Kapsalon Marcel",
    "wof:placetype":"venue"
},
  "geometry": {"coordinates":[5.4056210518,51.1988945007],"type":"Point"}
}