{
  "type": "Feature",
  "properties": {
    "iso:country":"BE",
    "sg:address":"Rondehuisjesdreef 30",
    "sg:city":"Gent",
    "sg:orig_category":"Studios photographiques",
    "sg:phone":"+32 9 236 57 74",
    "sg:postcode":"9031",
    "sg:province":"Oost-Vlaanderen",
    "wof:name":"Filmstudio Scala",
    "wof:placetype":"venue"
},
  "geometry": {"coordinates":[3.6597630978,51.0522422791],"type":"Point"}
}