{
  "type": "Feature",
  "properties": {
    "iso:country":"BE",
    "sg:address":"Koninklijke Baan 105",
    "sg:city":"Koksijde",
    "sg:classifiers":[
        {
            "category":"Restaurant",
            "type":"Food & Drink"
        }
    ],
    "sg:phone":"+32 58 51 12 81",
    "sg:postcode":"8670",
    "sg:province":"West-Vlaanderen",
    "wof:name":"Echo De La Mer",
    "wof:placetype":"venue"
},
  "geometry": {"coordinates":[2.6360270977,51.120639801],"type":"Point"}
}