{
  "type": "Feature",
  "properties": {
    "iso:country":"BE",
    "sg:address":"Sint-jan-berchmansstraat 23",
    "sg:city":"Mechelen",
    "sg:orig_category":"Reclamebureaus",
    "sg:phone":"+32 15 41 74 48",
    "sg:postcode":"2800",
    "sg:province":"Antwerpen",
    "wof:name":"Erik Dams Copywriting",
    "wof:placetype":"venue"
},
  "geometry": {"coordinates":[4.4746499062,51.0176582336],"type":"Point"}
}