{
  "type": "Feature",
  "properties": {
    "iso:country":"BE",
    "sg:address":"Hochstrasse 36",
    "sg:city":"Lontzen/lontzen",
    "sg:orig_category":"Herstellingen and onderhoud van auto's",
    "sg:phone":"+32 87 65 25 84",
    "sg:postcode":"4711",
    "sg:province":"Li\u00e8ge",
    "wof:name":"Guido Britz",
    "wof:placetype":"venue"
},
  "geometry": {"coordinates":[6.0337781906,50.6930236816],"type":"Point"}
}