{
  "type": "Feature",
  "properties": {
    "addr:full":"Chauss\u00e9e De Wavre 613 Bruxelles (etterbeek) Bruxelles-Capitale 1040",
    "addr:housenumber":"613",
    "addr:postcode":"1040",
    "addr:street":"Chausse\u0301E De Wavre",
    "iso:country":"BE",
    "sg:address":"Chauss\u00e9e De Wavre 613",
    "sg:city":"Bruxelles (etterbeek)",
    "sg:classifiers":[
        {
            "category":"Building & Trades",
            "subcategory":"Landscaping Services",
            "type":"Services"
        }
    ],
    "sg:phone":"+32 2 374 68 98",
    "sg:postcode":"1040",
    "sg:province":"Bruxelles-Capitale",
    "sg:tags":[
        "architect",
        "landscape"
    ],
    "wof:name":"Chevolet V",
    "wof:placetype":"venue"
},
  "geometry": {"coordinates":[4.3884649277,50.8313293457],"type":"Point"}
}