{
  "type": "Feature",
  "properties": {
    "iso:country":"BE",
    "sg:address":"Chevauchoire De Viane 170",
    "sg:city":"Lessines (deux-acren)",
    "sg:classifiers":[
        {
            "category":"Professional",
            "subcategory":"Business Services",
            "type":"Services"
        }
    ],
    "sg:postcode":"7864",
    "sg:province":"Hainaut",
    "sg:tags":[
        "firm"
    ],
    "wof:name":"Intermail",
    "wof:placetype":"venue"
},
  "geometry": {"coordinates":[3.8561370373,50.7231369019],"type":"Point"}
}