{
  "type": "Feature",
  "properties": {
    "iso:country":"BE",
    "sg:address":"Avenue Duc Henri De Brabant 31",
    "sg:city":"Wavre",
    "sg:classifiers":[
        {
            "category":"Health Services",
            "subcategory":"Dentist",
            "type":"Services"
        }
    ],
    "sg:phone":"+32 475 26 08 36",
    "sg:postcode":"1300",
    "sg:province":"Brabant Wallon",
    "wof:name":"Vankriekinge P",
    "wof:placetype":"venue"
},
  "geometry": {"coordinates":[4.6282849312,50.7133979797],"type":"Point"}
}