{
  "type": "Feature",
  "properties": {
    "addr:full":"Boomstraat 49 Bornem Antwerpen 2880",
    "addr:housenumber":"49",
    "addr:postcode":"2880",
    "addr:street":"Boomstraat",
    "iso:country":"BE",
    "sg:address":"Boomstraat 49",
    "sg:city":"Bornem",
    "sg:orig_category":"Apotheken",
    "sg:phone":"+32 3 889 10 57",
    "sg:postcode":"2880",
    "sg:province":"Antwerpen",
    "wof:name":"De Volksmacht",
    "wof:placetype":"venue"
},
  "geometry": {"coordinates":[4.2334890366,51.0973777771],"type":"Point"}
}