{
  "type": "Feature",
  "properties": {
    "addr:full":"Industriepark-drongen 2bab Gent Oost-Vlaanderen 9031",
    "addr:postcode":"9031",
    "addr:street":"Oost-Vlaanderen",
    "iso:country":"BE",
    "sg:address":"Industriepark-drongen 2bab",
    "sg:city":"Gent",
    "sg:orig_category":"Syst\u00e8mes de t\u00e9l\u00e9communications",
    "sg:phone":"+32 9 281 15 51",
    "sg:postcode":"9031",
    "sg:province":"Oost-Vlaanderen",
    "wof:name":"European Telecom",
    "wof:placetype":"venue"
},
  "geometry": {"coordinates":[3.5996029377,51.0436286926],"type":"Point"}
}