{
  "type": "Feature",
  "properties": {
    "iso:country":"BE",
    "sg:address":"Grote Steenweg 65",
    "sg:city":"Zoutleeuw",
    "sg:orig_category":"Art and fournitures artistiques. Antiquit\u00e9s",
    "sg:phone":"+32 11 78 09 67",
    "sg:postcode":"3440",
    "sg:province":"Vlaams-Brabant",
    "wof:name":"T Molenhof",
    "wof:placetype":"venue"
},
  "geometry": {"coordinates":[5.1017780304,50.807674408],"type":"Point"}
}