{
  "type": "Feature",
  "properties": {
    "iso:country":"BE",
    "sg:address":"Chauss\u00e9e De Tirlemont 139",
    "sg:city":"Gembloux-sur-orneau (gembloux)",
    "sg:classifiers":[
        {
            "category":"Manufacturing",
            "subcategory":"Metals",
            "type":"Manufacturing & Wholesale Goods"
        }
    ],
    "sg:phone":"+32 81 60 05 33",
    "sg:postcode":"5030",
    "sg:province":"Namur",
    "sg:tags":[
        "ironwork"
    ],
    "wof:name":"Ferronnerie Tassoul",
    "wof:placetype":"venue"
},
  "geometry": {"coordinates":[4.7131018639,50.5846672058],"type":"Point"}
}