{
  "type": "Feature",
  "properties": {
    "iso:country":"BE",
    "sg:address":"Rue De La Gare 75b",
    "sg:city":"Erquelinnes (solre-sur-sambre)",
    "sg:classifiers":[
        {
            "category":"Autos & Motor Vehicles",
            "subcategory":"Motorcycle Sales",
            "type":"Retail Goods"
        }
    ],
    "sg:phone":"+32 71 55 59 90",
    "sg:postcode":"6560",
    "sg:province":"Hainaut",
    "sg:tags":[
        "motorbike"
    ],
    "wof:name":"Nouvelles Evasions",
    "wof:placetype":"venue"
},
  "geometry": {"coordinates":[4.1594491005,50.3184814453],"type":"Point"}
}