{
  "type": "Feature",
  "properties": {
    "addr:full":"Dorp 18 Rijkevorsel Antwerpen 2310",
    "addr:housenumber":"18",
    "addr:postcode":"2310",
    "addr:street":"Dorp",
    "iso:country":"BE",
    "sg:address":"Dorp 18",
    "sg:city":"Rijkevorsel",
    "sg:orig_category":"Banques and organismes de cr\u00e9dit",
    "sg:phone":"+32 3 314 62 88",
    "sg:postcode":"2310",
    "sg:province":"Antwerpen",
    "wof:name":"Fortis",
    "wof:placetype":"venue"
},
  "geometry": {"coordinates":[4.7595419884,51.3500099182],"type":"Point"}
}