{
  "type": "Feature",
  "properties": {
    "addr:full":"Avenue Des Gaulois 10 Bruxelles (etterbeek) Bruxelles-Capitale 1040",
    "addr:housenumber":"10",
    "addr:postcode":"1040",
    "addr:street":"Avenue Des Gaulois",
    "iso:country":"BE",
    "sg:address":"Avenue Des Gaulois 10",
    "sg:city":"Bruxelles (etterbeek)",
    "sg:classifiers":[
        {
            "category":"Professional",
            "subcategory":"Management & Consulting",
            "type":"Services"
        }
    ],
    "sg:phone":"+32 2 736 72 94",
    "sg:postcode":"1040",
    "sg:province":"Bruxelles-Capitale",
    "sg:tags":[
        "consultant",
        "agency",
        "advertising"
    ],
    "wof:name":"Gambis Communications Sprl",
    "wof:placetype":"venue"
},
  "geometry": {"coordinates":[4.3945569992,50.8382911682],"type":"Point"}
}