{
  "type": "Feature",
  "properties": {
    "iso:country":"BE",
    "sg:address":"Grande Rue 1",
    "sg:city":"Librament",
    "sg:classifiers":[
        {
            "category":"Professional",
            "subcategory":"Business Services",
            "type":"Services"
        }
    ],
    "sg:phone":"+32 61 29 30 40",
    "sg:postcode":"6800",
    "sg:province":"Luxembourg",
    "sg:tags":[
        "body",
        "advice"
    ],
    "wof:name":"Chambre De Comm Et D'indust Du Luxemburg Belge",
    "wof:placetype":"venue"
},
  "geometry": {"coordinates":[5.4534888268,49.9753837585],"type":"Point"}
}