{
  "type": "Feature",
  "properties": {
    "addr:full":"Oude Baan 332 Maasmechelen Limburg 3630",
    "addr:housenumber":"332",
    "addr:postcode":"3630",
    "addr:street":"Oude Baan",
    "iso:country":"BE",
    "sg:address":"Oude Baan 332",
    "sg:city":"Maasmechelen",
    "sg:classifiers":[
        {
            "category":"Food & Beverages",
            "subcategory":"Groceries & Convenience Stores",
            "type":"Retail Goods"
        }
    ],
    "sg:phone":"+32 89 70 30 32",
    "sg:postcode":"3630",
    "sg:province":"Limburg",
    "sg:tags":[
        "grocer"
    ],
    "wof:name":"Amici (d')",
    "wof:placetype":"venue"
},
  "geometry": {"coordinates":[5.6846179962,50.9714736938],"type":"Point"}
}