{
  "type": "Feature",
  "properties": {
    "addr:full":"Rue Strivay 2 Neupr\u00e9 (plainevaux) Li\u00e8ge 4122",
    "addr:housenumber":"2",
    "addr:postcode":"4122",
    "addr:street":"Rue Strivay;Plainevaux",
    "iso:country":"BE",
    "sg:address":"Rue Strivay 2",
    "sg:city":"Neupr\u00e9 (plainevaux)",
    "sg:classifiers":[
        {
            "category":"Health Services",
            "subcategory":"Doctor",
            "type":"Services"
        }
    ],
    "sg:phone":"+32 4 380 51 15",
    "sg:postcode":"4122",
    "sg:province":"Li\u00e8ge",
    "sg:tags":[
        "medicinephysicians",
        "surgeon"
    ],
    "wof:name":"Jacquerie Fran\u00e7oise",
    "wof:placetype":"venue"
},
  "geometry": {"coordinates":[5.5311841965,50.5405540466],"type":"Point"}
}