{
  "type": "Feature",
  "properties": {
    "iso:country":"BE",
    "sg:address":"Karenveldstraat 10",
    "sg:city":"Opwijk",
    "sg:classifiers":[
        {
            "category":"Health Services",
            "subcategory":"Health Practitioner",
            "type":"Services"
        }
    ],
    "sg:phone":"+32 52 35 04 21",
    "sg:postcode":"1745",
    "sg:province":"Vlaams-Brabant",
    "sg:tags":[
        "physiotherapist"
    ],
    "wof:name":"De Proost M",
    "wof:placetype":"venue"
},
  "geometry": {"coordinates":[4.1801800728,50.9683074951],"type":"Point"}
}