{
  "type": "Feature",
  "properties": {
    "addr:full":"Nieuwstraat 33 Wetteren Oost-Vlaanderen 9230",
    "addr:housenumber":"33",
    "addr:postcode":"9230",
    "addr:street":"Nieuwstraat",
    "iso:country":"BE",
    "sg:address":"Nieuwstraat 33",
    "sg:city":"Wetteren",
    "sg:orig_category":"Agences de publicit\u00e9",
    "sg:phone":"+32 9 369 57 65",
    "sg:postcode":"9230",
    "sg:province":"Oost-Vlaanderen",
    "wof:name":"Copyteam",
    "wof:placetype":"venue"
},
  "geometry": {"coordinates":[3.8807170391,51.0025100708],"type":"Point"}
}