{
  "type": "Feature",
  "properties": {
    "iso:country":"BE",
    "sg:address":"Kerkhofstraat 37",
    "sg:city":"Houthalen-helchteren (houthalen)",
    "sg:classifiers":[
        {
            "category":"Building & Trades",
            "subcategory":"Cleaning & Sanitation",
            "type":"Services"
        }
    ],
    "sg:phone":"+32 11 52 21 58",
    "sg:postcode":"3530",
    "sg:province":"Limburg",
    "sg:tags":[
        "janitor"
    ],
    "wof:name":"Bell Clean Bvba",
    "wof:placetype":"venue"
},
  "geometry": {"coordinates":[5.3847398758,51.0386276245],"type":"Point"}
}