{
  "type": "Feature",
  "properties": {
    "addr:full":"Ave Des Arts 27 Bte 4 Bruxelles Bruxelles-Capitale 1040",
    "addr:housenumber":"27 bte 4",
    "addr:postcode":"1040",
    "addr:street":"Ave Des Arts",
    "iso:country":"BE",
    "sg:address":"Ave Des Arts 27 Bte 4",
    "sg:city":"Bruxelles",
    "sg:classifiers":[
        {
            "category":"Banks & Credit Unions",
            "subcategory":"Bank",
            "type":"Services"
        }
    ],
    "sg:phone":"+32 2 230 81 00",
    "sg:postcode":"1040",
    "sg:province":"Bruxelles-Capitale",
    "wof:name":"Asahi Bank Sa",
    "wof:placetype":"venue"
},
  "geometry": {"coordinates":[4.3687877655,50.8451957703],"type":"Point"}
}