{
  "type": "Feature",
  "properties": {
    "iso:country":"BE",
    "sg:address":"Rue Sainte Jozef 7a",
    "sg:city":"Incourt",
    "sg:orig_category":"Plomberie, chauffage and installations sanitaires",
    "sg:phone":"+32 495 20 33 33",
    "sg:postcode":"1315",
    "sg:province":"Brabant Wallon",
    "wof:name":"Carlier",
    "wof:placetype":"venue"
},
  "geometry": {"coordinates":[4.8145899773,50.6942405701],"type":"Point"}
}