{
  "type": "Feature",
  "properties": {
    "iso:country":"BE",
    "sg:address":"Stationsstraat 90",
    "sg:city":"Aalter",
    "sg:orig_category":"Apotheken",
    "sg:phone":"+32 9 374 15 17",
    "sg:postcode":"9880",
    "sg:province":"Oost-Vlaanderen",
    "wof:name":"A. Delhuvenne",
    "wof:placetype":"venue"
},
  "geometry": {"coordinates":[3.4482300282,51.0874290466],"type":"Point"}
}