{
  "type": "Feature",
  "properties": {
    "addr:full":"Baron Robert De Vironlaan 1 Dilbeek Vlaams-Brabant 1700",
    "addr:housenumber":"1",
    "addr:postcode":"1700",
    "addr:street":"Baron Robert De Vironlaan",
    "iso:country":"BE",
    "sg:address":"Baron Robert De Vironlaan 1",
    "sg:city":"Dilbeek",
    "sg:classifiers":[
        {
            "category":"Utilities",
            "subcategory":"Refuse",
            "type":"Services"
        }
    ],
    "sg:phone":"+32 2 461 19 92",
    "sg:postcode":"1700",
    "sg:province":"Vlaams-Brabant",
    "sg:tags":[
        "removal"
    ],
    "wof:name":"Dilmove",
    "wof:placetype":"venue"
},
  "geometry": {"coordinates":[4.2658290863,50.8477706909],"type":"Point"}
}