{
  "type": "Feature",
  "properties": {
    "addr:full":"Lindestraat 22 Aalter Oost-Vlaanderen 9880",
    "addr:housenumber":"22",
    "addr:postcode":"9880",
    "addr:street":"Lindestraat",
    "iso:country":"BE",
    "sg:address":"Lindestraat 22",
    "sg:city":"Aalter",
    "sg:classifiers":[
        {
            "category":"Communications",
            "subcategory":"Radio Station",
            "type":"Services"
        }
    ],
    "sg:phone":"+32 9 325 80 58",
    "sg:postcode":"9880",
    "sg:province":"Oost-Vlaanderen",
    "sg:tags":[
        "local"
    ],
    "wof:name":"Top Radio Aalter",
    "wof:placetype":"venue"
},
  "geometry": {"coordinates":[3.4375460148,51.0823097229],"type":"Point"}
}