{
  "type": "Feature",
  "properties": {
    "iso:country":"BE",
    "sg:address":"Brusselse Steenweg 334",
    "sg:city":"Vorst/forest",
    "sg:orig_category":"Artsen and specialisten",
    "sg:phone":"+32 2 346 62 37",
    "sg:postcode":"1190",
    "sg:province":"Bruxelles-Capitale",
    "wof:name":"Pierre Fossion",
    "wof:placetype":"venue"
},
  "geometry": {"coordinates":[4.329788208,50.8194541931],"type":"Point"}
}