{
  "type": "Feature",
  "properties": {
    "addr:full":"Otterstraat 48 Turnhout Antwerpen 2300",
    "addr:housenumber":"48",
    "addr:postcode":"2300",
    "addr:street":"Otterstraat",
    "iso:country":"BE",
    "sg:address":"Otterstraat 48",
    "sg:city":"Turnhout",
    "sg:orig_category":"Plomberie, chauffage and installations sanitaires",
    "sg:phone":"+32 14 41 28 13",
    "sg:postcode":"2300",
    "sg:province":"Antwerpen",
    "wof:name":"J. Van Herck",
    "wof:placetype":"venue"
},
  "geometry": {"coordinates":[4.9527897835,51.322063446],"type":"Point"}
}