{
  "type": "Feature",
  "properties": {
    "addr:full":"Foreststraat 4 Zonnebeke West-Vlaanderen 8980",
    "addr:housenumber":"4",
    "addr:postcode":"8980",
    "addr:street":"Foreststraat",
    "iso:country":"BE",
    "sg:address":"Foreststraat 4",
    "sg:city":"Zonnebeke",
    "sg:classifiers":[
        {
            "category":"Transit Center",
            "subcategory":"Freight",
            "type":"Transportation"
        }
    ],
    "sg:phone":"+32 51 54 57 34",
    "sg:postcode":"8980",
    "sg:province":"West-Vlaanderen",
    "sg:tags":[
        "import",
        "export",
        "-"
    ],
    "wof:name":"Soenen",
    "wof:placetype":"venue"
},
  "geometry": {"coordinates":[2.9909760952,50.8731040955],"type":"Point"}
}