{
  "type": "Feature",
  "properties": {
    "iso:country":"BE",
    "sg:address":"Rue Emile Bouilliot 2",
    "sg:city":"Elsene/ixelles",
    "sg:orig_category":"M\u00e9decins and sp\u00e9cialistes",
    "sg:phone":"+32 2 347 35 92",
    "sg:postcode":"1050",
    "sg:province":"Bruxelles-Capitale",
    "wof:name":"N. Vander Elst",
    "wof:placetype":"venue"
},
  "geometry": {"coordinates":[4.3541030884,50.8197517395],"type":"Point"}
}