{
  "type": "Feature",
  "properties": {
    "addr:full":"Haachtsesteenweg 1157 Evere Bruxelles-Capitale 1140",
    "addr:housenumber":"1157",
    "addr:postcode":"1140",
    "addr:street":"Haachtsesteenweg",
    "iso:country":"BE",
    "sg:address":"Haachtsesteenweg 1157",
    "sg:city":"Evere",
    "sg:classifiers":[
        {
            "category":"Restaurant",
            "type":"Food & Drink"
        }
    ],
    "sg:phone":"+32 2 245 27 72",
    "sg:postcode":"1140",
    "sg:province":"Bruxelles-Capitale",
    "wof:name":"Restaurant Europa",
    "wof:placetype":"venue"
},
  "geometry": {"coordinates":[4.4092950821,50.8777122498],"type":"Point"}
}