{
  "type": "Feature",
  "properties": {
    "iso:country":"BE",
    "sg:address":"Stanislas Legrellestraat 70",
    "sg:city":"Jette/jette",
    "sg:orig_category":"Artsen and specialisten",
    "sg:phone":"+32 2 428 09 81",
    "sg:postcode":"1090",
    "sg:province":"Bruxelles-Capitale",
    "wof:name":"F. Pochet/fabienne Pochet",
    "wof:placetype":"venue"
},
  "geometry": {"coordinates":[4.3214039803,50.8754272461],"type":"Point"}
}