{
  "type": "Feature",
  "properties": {
    "iso:country":"BE",
    "sg:address":"Heldenlaan 16",
    "sg:city":"Zottegem",
    "sg:orig_category":"Geschenken and souvenirs Huishoudapparaten, televisies and radio's Speelgoed Verlichting and huishou",
    "sg:phone":"+32 9 361 22 77",
    "sg:postcode":"9620",
    "sg:province":"Oost-Vlaanderen",
    "wof:name":"Blokker",
    "wof:placetype":"venue"
},
  "geometry": {"coordinates":[3.8098220825,50.8702278137],"type":"Point"}
}