{
  "type": "Feature",
  "properties": {
    "iso:country":"BE",
    "sg:address":"Turnhoutsebaan 625",
    "sg:city":"Wijnegem",
    "sg:orig_category":"Salles de conf\u00e9rences and de r\u00e9ceptions",
    "sg:phone":"+32 3 353 64 98",
    "sg:postcode":"2110",
    "sg:province":"Antwerpen",
    "wof:name":"Salons Weilandshof",
    "wof:placetype":"venue"
},
  "geometry": {"coordinates":[4.5502290726,51.2304801941],"type":"Point"}
}