{
  "type": "Feature",
  "properties": {
    "addr:full":"Galerie Du Roi 1 Bruxelles Bruxelles-Capitale 1000",
    "addr:housenumber":"1",
    "addr:postcode":"1000",
    "addr:street":"Galerie Du Roi",
    "iso:country":"BE",
    "sg:address":"Galerie Du Roi 1",
    "sg:city":"Bruxelles",
    "sg:classifiers":[
        {
            "category":"Shopping",
            "subcategory":"Clothing, Apparel, & Fashions",
            "type":"Retail Goods"
        }
    ],
    "sg:phone":"+32 2 511 02 80",
    "sg:postcode":"1000",
    "sg:province":"Bruxelles-Capitale",
    "sg:tags":[
        "boutique"
    ],
    "wof:name":"Van Schelle",
    "wof:placetype":"venue"
},
  "geometry": {"coordinates":[4.3330521584,50.8317909241],"type":"Point"}
}