{
  "type": "Feature",
  "properties": {
    "addr:full":"Lostraat 36 Aalter Oost-Vlaanderen 9880",
    "addr:housenumber":"36",
    "addr:postcode":"9880",
    "addr:street":"Lostraat",
    "iso:country":"BE",
    "sg:address":"Lostraat 36",
    "sg:city":"Aalter",
    "sg:orig_category":"Bloemen and planten",
    "sg:phone":"+32 9 374 78 92",
    "sg:postcode":"9880",
    "sg:province":"Oost-Vlaanderen",
    "wof:name":"Curiosa",
    "wof:placetype":"venue"
},
  "geometry": {"coordinates":[3.4505009651,51.080493927],"type":"Point"}
}