{
  "type": "Feature",
  "properties": {
    "addr:full":"Rodolf Callewaertstraat 1 Hooglede West-Vlaanderen 8830",
    "addr:housenumber":"1",
    "addr:postcode":"8830",
    "addr:street":"Callewaertstraat",
    "iso:country":"BE",
    "sg:address":"Rodolf Callewaertstraat 1",
    "sg:city":"Hooglede",
    "sg:classifiers":[
        {
            "category":"Insurance",
            "subcategory":"Insurance Agent",
            "type":"Services"
        }
    ],
    "sg:phone":"+32 51 22 00 05",
    "sg:postcode":"8830",
    "sg:province":"West-Vlaanderen",
    "sg:tags":[
        "verzekeringsmakelaars",
        "expert"
    ],
    "wof:name":"W. Vansteelant",
    "wof:placetype":"venue"
},
  "geometry": {"coordinates":[3.1012721062,50.9958305359],"type":"Point"}
}