{
  "type": "Feature",
  "properties": {
    "addr:full":"Koningin Astridstraat 13 Box 3 Tremelo Vlaams-Brabant 3120",
    "addr:housenumber":"13;3",
    "addr:postcode":"3120",
    "addr:street":"Koningin Astridstraat;Box",
    "iso:country":"BE",
    "sg:address":"Koningin Astridstraat 13 Box 3",
    "sg:city":"Tremelo",
    "sg:classifiers":[
        {
            "category":"Landmark",
            "subcategory":"City Walls",
            "type":"Public Place"
        }
    ],
    "sg:phone":"+32 16 52 03 23",
    "sg:postcode":"3120",
    "sg:province":"Vlaams-Brabant",
    "sg:tags":[
        "plywood"
    ],
    "wof:name":"I.w.p Nv",
    "wof:placetype":"venue"
},
  "geometry": {"coordinates":[4.7069368362,50.9914245605],"type":"Point"}
}