{
  "type": "Feature",
  "properties": {
    "iso:country":"BE",
    "sg:address":"Dorp 33",
    "sg:city":"Berlare",
    "sg:orig_category":"Verhuur cateringmateriaal and evenementuitrusting",
    "sg:phone":"+32 52 42 28 51",
    "sg:postcode":"9290",
    "sg:province":"Oost-Vlaanderen",
    "wof:name":"Tentenverhuur Fran\u00c7ois",
    "wof:placetype":"venue"
},
  "geometry": {"coordinates":[4.0037899017,51.025138855],"type":"Point"}
}