{
  "type": "Feature",
  "properties": {
    "addr:full":"A.c. De Terbekenlaan 50 Gent Oost-Vlaanderen 9030",
    "addr:housenumber":"50",
    "addr:postcode":"9030",
    "addr:street":"Terbekenlaan;Oost-Vlaanderen",
    "iso:country":"BE",
    "sg:address":"A.c. De Terbekenlaan 50",
    "sg:city":"Gent",
    "sg:orig_category":"Traitements param\u00e9dicaux",
    "sg:phone":"+32 9 227 68 83",
    "sg:postcode":"9030",
    "sg:province":"Oost-Vlaanderen",
    "wof:name":"Goeminne Marijke",
    "wof:placetype":"venue"
},
  "geometry": {"coordinates":[3.6745951176,51.072933197],"type":"Point"}
}