{
  "type": "Feature",
  "properties": {
    "iso:country":"BE",
    "sg:address":"Melaan 16",
    "sg:city":"Mechelen",
    "sg:classifiers":[
        {
            "category":"Education",
            "subcategory":"School",
            "type":"Public Place"
        }
    ],
    "sg:phone":"+32 15 28 79 10",
    "sg:postcode":"2800",
    "sg:province":"Antwerpen",
    "sg:tags":[
        "secondary"
    ],
    "wof:name":"Scheppers Instituut",
    "wof:placetype":"venue"
},
  "geometry": {"coordinates":[4.4752497673,51.0284576416],"type":"Point"}
}