{
  "type": "Feature",
  "properties": {
    "addr:full":"Laarstraat 110 Bilzen (beverst) Limburg 3740",
    "addr:housenumber":"110",
    "addr:postcode":"3740",
    "addr:street":"Laarstraat",
    "iso:country":"BE",
    "sg:address":"Laarstraat 110",
    "sg:city":"Bilzen (beverst)",
    "sg:classifiers":[
        {
            "category":"Building & Trades",
            "subcategory":"Construction",
            "type":"Services"
        }
    ],
    "sg:phone":"+32 89 41 78 31",
    "sg:postcode":"3740",
    "sg:province":"Limburg",
    "sg:tags":[
        "stair"
    ],
    "wof:name":"Moors J",
    "wof:placetype":"venue"
},
  "geometry": {"coordinates":[5.4940891266,50.8899650574],"type":"Point"}
}