{
  "type": "Feature",
  "properties": {
    "addr:full":"Hoevenstraat 35 Wommelgem Antwerpen 2160",
    "addr:housenumber":"35",
    "addr:postcode":"2160",
    "addr:street":"Hoevenstraat",
    "iso:country":"BE",
    "sg:address":"Hoevenstraat 35",
    "sg:city":"Wommelgem",
    "sg:classifiers":[
        {
            "category":"Social Services",
            "subcategory":"Job Training",
            "type":"Services"
        }
    ],
    "sg:phone":"+32 3 353 19 44",
    "sg:postcode":"2160",
    "sg:province":"Antwerpen",
    "sg:tags":[
        "coordinator",
        "safety"
    ],
    "wof:name":"Bumaco Bvba",
    "wof:placetype":"venue"
},
  "geometry": {"coordinates":[4.5172610283,51.2041625977],"type":"Point"}
}