{
  "type": "Feature",
  "properties": {
    "addr:full":"Gen. Baron Jacquesstraat 43 Diksmuide West-Vlaanderen 8600",
    "addr:housenumber":"43",
    "addr:postcode":"8600",
    "addr:street":"Gen. Baron Jacquesstraat",
    "iso:country":"BE",
    "sg:address":"Gen. Baron Jacquesstraat 43",
    "sg:city":"Diksmuide",
    "sg:orig_category":"Pain, p\u00e2tisseries and confiseries",
    "sg:phone":"+32 51 50 29 82",
    "sg:postcode":"8600",
    "sg:province":"West-Vlaanderen",
    "wof:name":"'t Croissantje",
    "wof:placetype":"venue"
},
  "geometry": {"coordinates":[2.8613870144,51.0335617065],"type":"Point"}
}