{
  "type": "Feature",
  "properties": {
    "addr:full":"Wayenborgstraat 8 Mechelen Antwerpen 2800",
    "addr:housenumber":"8",
    "addr:postcode":"2800",
    "addr:street":"Wayenborgstraat",
    "iso:country":"BE",
    "sg:address":"Wayenborgstraat 8",
    "sg:city":"Mechelen",
    "sg:orig_category":"Kunststofrecipi\u00ebnten and -verpakkingen Fab",
    "sg:phone":"+32 15 21 27 01",
    "sg:postcode":"2800",
    "sg:province":"Antwerpen",
    "wof:name":"Dispack Industriele & Promotionele Verpakking",
    "wof:placetype":"venue"
},
  "geometry": {"coordinates":[4.4426760674,51.0497131348],"type":"Point"}
}