{
  "type": "Feature",
  "properties": {
    "iso:country":"BE",
    "sg:address":"Populierenlaan 40",
    "sg:city":"Rumst",
    "sg:orig_category":"Woningbouw",
    "sg:phone":"+32 3 888 48 64",
    "sg:postcode":"2840",
    "sg:province":"Antwerpen",
    "wof:name":"Meva",
    "wof:placetype":"venue"
},
  "geometry": {"coordinates":[4.3965997696,51.0768470764],"type":"Point"}
}