{
  "type": "Feature",
  "properties": {
    "addr:full":"Venelle Des Acers 4 Wavre Brabant Wallon 1300",
    "addr:housenumber":"4;1300",
    "addr:street":"Venelle Des Acers",
    "iso:country":"BE",
    "sg:address":"Venelle Des Acers 4",
    "sg:city":"Wavre",
    "sg:orig_category":"Services de Nettoyage and de D\u00e9sinfection",
    "sg:phone":"+32 10 22 35 87",
    "sg:postcode":"1300",
    "sg:province":"Brabant Wallon",
    "wof:name":"Philippe Bernard",
    "wof:placetype":"venue"
},
  "geometry": {"coordinates":[4.6185760498,50.7078170776],"type":"Point"}
}