{
  "type": "Feature",
  "properties": {
    "iso:country":"BE",
    "sg:address":"Clos Des Vergers 4",
    "sg:city":"Dison",
    "sg:orig_category":"V\u00eatements, chaussures and accessoires Gr",
    "sg:phone":"+32 87 33 78 25",
    "sg:postcode":"4821",
    "sg:province":"Li\u00e8ge",
    "wof:name":"A & J B T",
    "wof:placetype":"venue"
},
  "geometry": {"coordinates":[5.8685870171,50.6067657471],"type":"Point"}
}