{
  "type": "Feature",
  "properties": {
    "addr:full":"Rue Hoyoux 159 Herstal Li\u00e8ge 4040",
    "addr:housenumber":"159",
    "addr:postcode":"4040",
    "addr:street":"Rue Hoyoux",
    "iso:country":"BE",
    "sg:address":"Rue Hoyoux 159",
    "sg:city":"Herstal",
    "sg:orig_category":"Kansspelen",
    "sg:phone":"+32 4 264 61 71",
    "sg:postcode":"4040",
    "sg:province":"Li\u00e8ge",
    "wof:name":"Tierc\u00c9 Franco Belge",
    "wof:placetype":"venue"
},
  "geometry": {"coordinates":[5.6249542236,50.6603546143],"type":"Point"}
}