{
  "type": "Feature",
  "properties": {
    "iso:country":"BE",
    "sg:address":"Chauss\u00c9e De Bascoup 9",
    "sg:city":"Morlanwelz",
    "sg:orig_category":"Slagers",
    "sg:phone":"+32 64 44 15 89",
    "sg:postcode":"7140",
    "sg:province":"Hainaut",
    "wof:name":"Renmans",
    "wof:placetype":"venue"
},
  "geometry": {"coordinates":[4.2657299042,50.465511322],"type":"Point"}
}