{
  "type": "Feature",
  "properties": {
    "addr:full":"Karel Van Doorslaerlaan 8 Bornem Antwerpen 2880",
    "addr:housenumber":"8",
    "addr:postcode":"2880",
    "addr:street":"Karel Van Doorslaerlaan",
    "iso:country":"BE",
    "sg:address":"Karel Van Doorslaerlaan 8",
    "sg:city":"Bornem",
    "sg:orig_category":"Artsen and specialisten",
    "sg:phone":"+32 52 34 21 11",
    "sg:postcode":"2880",
    "sg:province":"Antwerpen",
    "wof:name":"Luc Slootmaeckers",
    "wof:placetype":"venue"
},
  "geometry": {"coordinates":[4.1932940483,51.0627174377],"type":"Point"}
}