{
  "type": "Feature",
  "properties": {
    "addr:full":"Nieuw Begijnhof 1 Niel Antwerpen 2845",
    "addr:housenumber":"1",
    "addr:postcode":"2845",
    "addr:street":"Nieuw Begijnhof",
    "iso:country":"BE",
    "sg:address":"Nieuw Begijnhof 1",
    "sg:city":"Niel",
    "sg:classifiers":[
        {
            "category":"Real Estate",
            "subcategory":"Developer",
            "type":"Services"
        }
    ],
    "sg:phone":"+32 3 888 30 07",
    "sg:postcode":"2845",
    "sg:province":"Antwerpen",
    "sg:tags":[
        "project"
    ],
    "wof:name":"Maximus Bvba",
    "wof:placetype":"venue"
},
  "geometry": {"coordinates":[4.3254637718,51.1073951721],"type":"Point"}
}