{
  "type": "Feature",
  "properties": {
    "addr:full":"Baclain 25 Gouvy (montleban) Luxembourg 6674",
    "addr:housenumber":"25",
    "addr:postcode":"6674",
    "addr:street":"Baclain",
    "iso:country":"BE",
    "sg:address":"Baclain 25",
    "sg:city":"Gouvy (montleban)",
    "sg:classifiers":[
        {
            "category":"Professional",
            "subcategory":"Accounting & Tax Preparation",
            "type":"Services"
        }
    ],
    "sg:phone":"+32 80 51 00 44",
    "sg:postcode":"6674",
    "sg:province":"Luxembourg",
    "sg:tags":[
        "bookkeeper"
    ],
    "wof:name":"Infogestion Brion Ch Sprl",
    "wof:placetype":"venue"
},
  "geometry": {"coordinates":[5.8657917976,50.1953620911],"type":"Point"}
}