{
  "type": "Feature",
  "properties": {
    "addr:full":"Grenadiersstraat 6 Ieper West-Vlaanderen 8904",
    "addr:housenumber":"6",
    "addr:postcode":"8904",
    "addr:street":"Grenadiersstraat",
    "iso:country":"BE",
    "sg:address":"Grenadiersstraat 6",
    "sg:city":"Ieper",
    "sg:orig_category":"Electrom\u00e9nager, t\u00e9l\u00e9visions and radios",
    "sg:phone":"+32 51 54 58 58",
    "sg:postcode":"8904",
    "sg:province":"West-Vlaanderen",
    "wof:name":"Digimatic",
    "wof:placetype":"venue"
},
  "geometry": {"coordinates":[2.8318760395,50.9221687317],"type":"Point"}
}