{
  "type": "Feature",
  "properties": {
    "iso:country":"BE",
    "sg:address":"J. De Ter Beerstlaan 44",
    "sg:city":"Pittem",
    "sg:orig_category":"Tuinen",
    "sg:phone":"+32 51 46 63 93",
    "sg:postcode":"8740",
    "sg:province":"West-Vlaanderen",
    "wof:name":"De Volder K.",
    "wof:placetype":"venue"
},
  "geometry": {"coordinates":[3.2523469925,50.9936065674],"type":"Point"}
}