{
  "type": "Feature",
  "properties": {
    "addr:full":"Dorpsstraat 16 Bocholt Limburg 3950",
    "addr:housenumber":"16",
    "addr:postcode":"3950",
    "addr:street":"Dorpsstraat",
    "iso:country":"BE",
    "sg:address":"Dorpsstraat 16",
    "sg:city":"Bocholt",
    "sg:classifiers":[
        {
            "category":"Government",
            "subcategory":"Police Station",
            "type":"Public Place"
        }
    ],
    "sg:phone":"+32 89 46 04 80",
    "sg:postcode":"3950",
    "sg:province":"Limburg",
    "sg:tags":[
        "gendarmerie"
    ],
    "wof:name":"Federale Politie",
    "wof:placetype":"venue"
},
  "geometry": {"coordinates":[5.5791511536,51.1735649109],"type":"Point"}
}