{
  "type": "Feature",
  "properties": {
    "iso:country":"BE",
    "sg:address":"Rue Alexandre 39",
    "sg:city":"Charleroi (marcinelle)",
    "sg:classifiers":[
        {
            "category":"Health Services",
            "subcategory":"Health Practitioner",
            "type":"Services"
        }
    ],
    "sg:phone":"+32 71 43 76 61",
    "sg:postcode":"6001",
    "sg:province":"Hainaut",
    "sg:tags":[
        "physiotherapist"
    ],
    "wof:name":"Gillardin P",
    "wof:placetype":"venue"
},
  "geometry": {"coordinates":[4.4443497658,50.3723716736],"type":"Point"}
}