{
  "type": "Feature",
  "properties": {
    "iso:country":"BE",
    "sg:address":"Hemelrijkweg 37",
    "sg:city":"Essen",
    "sg:classifiers":[
        {
            "category":"Building & Trades",
            "subcategory":"Construction",
            "type":"Services"
        }
    ],
    "sg:phone":"+32 3 667 57 57",
    "sg:postcode":"2910",
    "sg:province":"Antwerpen",
    "sg:tags":[
        "stucco",
        "contractor"
    ],
    "wof:name":"Van Dorst M",
    "wof:placetype":"venue"
},
  "geometry": {"coordinates":[4.457816124,51.4678497314],"type":"Point"}
}