{
  "type": "Feature",
  "properties": {
    "iso:country":"BE",
    "sg:address":"Dorpsstraat 50",
    "sg:city":"Kampenhout",
    "sg:orig_category":"Paardenfokkers",
    "sg:phone":"+32 16 65 50 84",
    "sg:postcode":"1910",
    "sg:province":"Vlaams-Brabant",
    "wof:name":"Stoeterij \u00b4t Molenvondel",
    "wof:placetype":"venue"
},
  "geometry": {"coordinates":[4.5516400337,50.9425506592],"type":"Point"}
}