{
  "type": "Feature",
  "properties": {
    "iso:country":"BE",
    "sg:address":"Hendrik Ghijselenstraat 7",
    "sg:city":"Lennik",
    "sg:orig_category":"Loodgieterij, verwarming and sanitaire installaties",
    "sg:phone":"+32 2 532 55 14",
    "sg:postcode":"1750",
    "sg:province":"Vlaams-Brabant",
    "wof:name":"Bascour",
    "wof:placetype":"venue"
},
  "geometry": {"coordinates":[4.1523628235,50.8061065674],"type":"Point"}
}