{
  "type": "Feature",
  "properties": {
    "addr:full":"Park Ter Heide 7 Scherpenheuvel-zichem Vlaams-Brabant 3271",
    "addr:housenumber":"7",
    "addr:postcode":"3271",
    "addr:street":"Park Ter Heide",
    "iso:country":"BE",
    "sg:address":"Park Ter Heide 7",
    "sg:city":"Scherpenheuvel-zichem",
    "sg:orig_category":"Activit\u00e9s diverses d'imprimerie",
    "sg:phone":"+32 13 77 65 44",
    "sg:postcode":"3271",
    "sg:province":"Vlaams-Brabant",
    "wof:name":"Stijn Claes",
    "wof:placetype":"venue"
},
  "geometry": {"coordinates":[4.9920740128,51.0229148865],"type":"Point"}
}