{
  "type": "Feature",
  "properties": {
    "iso:country":"BE",
    "sg:address":"Halstraat 65",
    "sg:city":"Heusden-zolder (heusden)",
    "sg:classifiers":[
        {
            "category":"Professional",
            "subcategory":"Computer Services",
            "type":"Services"
        }
    ],
    "sg:phone":"+32 11 57 45 70",
    "sg:postcode":"3550",
    "sg:province":"Limburg",
    "sg:tags":[
        "-",
        "processing",
        "data",
        "software"
    ],
    "wof:name":"Sitech Software Services Bvba",
    "wof:placetype":"venue"
},
  "geometry": {"coordinates":[5.3050718307,51.048324585],"type":"Point"}
}