{
  "type": "Feature",
  "properties": {
    "iso:country":"BE",
    "sg:address":"Rue De Maire 15",
    "sg:city":"Tournai (froyennes)",
    "sg:classifiers":[
        {
            "category":"Utilities",
            "subcategory":"Refuse",
            "type":"Services"
        }
    ],
    "sg:phone":"+32 69 21 41 21",
    "sg:postcode":"7503",
    "sg:province":"Hainaut",
    "sg:tags":[
        "boiler",
        "-",
        "heating",
        "steam"
    ],
    "wof:name":"Sanidep Sa",
    "wof:placetype":"venue"
},
  "geometry": {"coordinates":[3.3562428951,50.6193199158],"type":"Point"}
}