{
  "type": "Feature",
  "properties": {
    "iso:country":"BE",
    "sg:address":"Rue De La Libert\u00c9 16",
    "sg:city":"Farciennes",
    "sg:orig_category":"Sociale huisvestingsmaatschappijen",
    "sg:phone":"+32 71 38 33 72",
    "sg:postcode":"6240",
    "sg:province":"Hainaut",
    "wof:name":"La Cit\u00c9 Farciennoise",
    "wof:placetype":"venue"
},
  "geometry": {"coordinates":[4.547647953,50.4315910339],"type":"Point"}
}