{
  "type": "Feature",
  "properties": {
    "addr:full":"Rue L. Vangrootenbruel 11 Ronse/renaix Oost-Vlaanderen 9600",
    "addr:housenumber":"11",
    "addr:postcode":"9600",
    "addr:street":"Rue L. Vangrootenbruel",
    "iso:country":"BE",
    "sg:address":"Rue L. Vangrootenbruel 11",
    "sg:city":"Ronse/renaix",
    "sg:classifiers":[
        {
            "category":"Arena",
            "subcategory":"Sports Club",
            "type":"Entertainment"
        }
    ],
    "sg:phone":"+32 55 21 58 16",
    "sg:postcode":"9600",
    "sg:province":"Oost-Vlaanderen",
    "sg:tags":[
        "de"
    ],
    "wof:name":"W.t.c. Jong Van Hart",
    "wof:placetype":"venue"
},
  "geometry": {"coordinates":[3.5915420055,50.7427215576],"type":"Point"}
}