{
  "type": "Feature",
  "properties": {
    "iso:country":"BE",
    "sg:address":"Dirk Boutslaan 3",
    "sg:city":"Leuven",
    "sg:orig_category":"Bruids- and ceremoniekledij Kleding",
    "sg:phone":"+32 16 23 22 83",
    "sg:postcode":"3000",
    "sg:province":"Vlaams-Brabant",
    "wof:name":"E. Celen",
    "wof:placetype":"venue"
},
  "geometry": {"coordinates":[4.6996388435,50.8800735474],"type":"Point"}
}