{
  "type": "Feature",
  "properties": {
    "addr:full":"Teniersstraat 17 Vilvoorde Vlaams-Brabant 1800",
    "addr:housenumber":"17",
    "addr:postcode":"1800",
    "addr:street":"Teniersstraat",
    "iso:country":"BE",
    "sg:address":"Teniersstraat 17",
    "sg:city":"Vilvoorde",
    "sg:classifiers":[
        {
            "category":"Professional",
            "subcategory":"Art Services",
            "type":"Services"
        }
    ],
    "sg:phone":"+32 2 252 65 30",
    "sg:postcode":"1800",
    "sg:province":"Vlaams-Brabant",
    "sg:tags":[
        "realization",
        "audio-visual"
    ],
    "wof:name":"2bmedia",
    "wof:placetype":"venue"
},
  "geometry": {"coordinates":[4.415435791,50.9244194031],"type":"Point"}
}