{
  "type": "Feature",
  "properties": {
    "iso:country":"BE",
    "sg:address":"Ter Boelhage 14",
    "sg:city":"Leuven",
    "sg:orig_category":"Boekhandels",
    "sg:phone":"+32 16 29 43 89",
    "sg:postcode":"3000",
    "sg:province":"Vlaams-Brabant",
    "wof:name":"Grint",
    "wof:placetype":"venue"
},
  "geometry": {"coordinates":[4.6912899017,50.8838882446],"type":"Point"}
}