{
  "type": "Feature",
  "properties": {
    "addr:full":"Oude Pittemstraat 34 Meulebeke West-Vlaanderen 8760",
    "addr:housenumber":"34",
    "addr:postcode":"8760",
    "addr:street":"Oude Pittemstraat",
    "iso:country":"BE",
    "sg:address":"Oude Pittemstraat 34",
    "sg:city":"Meulebeke",
    "sg:orig_category":"Antiek",
    "sg:phone":"+32 51 48 54 10",
    "sg:postcode":"8760",
    "sg:province":"West-Vlaanderen",
    "wof:name":"Joka",
    "wof:placetype":"venue"
},
  "geometry": {"coordinates":[3.2842309475,50.9617538452],"type":"Point"}
}