{
  "type": "Feature",
  "properties": {
    "iso:country":"BE",
    "sg:address":"Antoon Van Dyckstraat 22",
    "sg:city":"Antwerpen",
    "sg:classifiers":[
        {
            "category":"Organizations",
            "subcategory":"Professional Association",
            "type":"Services"
        }
    ],
    "sg:phone":"+32 3 288 59 58",
    "sg:postcode":"2018",
    "sg:province":"Antwerpen",
    "sg:tags":[
        "trade-union",
        "federation"
    ],
    "wof:name":"Unie Van Zelfstandige Kinesitherapeuten, Verenigd In Kringen Vzw, Uzk-antwerpen",
    "wof:placetype":"venue"
},
  "geometry": {"coordinates":[4.4153380394,51.2095832825],"type":"Point"}
}