{
  "type": "Feature",
  "properties": {
    "iso:country":"BE",
    "sg:address":"Spetstraatje 3",
    "sg:city":"Haacht (wespelaar)",
    "sg:classifiers":[
        {
            "category":"Health Services",
            "subcategory":"Doctor",
            "type":"Services"
        }
    ],
    "sg:phone":"+32 16 60 82 65",
    "sg:postcode":"3150",
    "sg:province":"Vlaams-Brabant",
    "sg:tags":[
        "medicinephysicians",
        "surgeon"
    ],
    "wof:name":"Ferroudji Mohamed",
    "wof:placetype":"venue"
},
  "geometry": {"coordinates":[4.6197180748,50.9632034302],"type":"Point"}
}