{
  "type": "Feature",
  "properties": {
    "addr:full":"Kronenhoekstraat 40 Sint-gillis-waas Oost-Vlaanderen 9170",
    "addr:housenumber":"40",
    "addr:postcode":"9170",
    "addr:street":"Kronenhoekstraat",
    "iso:country":"BE",
    "sg:address":"Kronenhoekstraat 40",
    "sg:city":"Sint-gillis-waas",
    "sg:orig_category":"Medische and orthopedische apparaten Opticiens",
    "sg:phone":"+32 3 770 81 07",
    "sg:postcode":"9170",
    "sg:province":"Oost-Vlaanderen",
    "wof:name":"Optiek Decoster-robeyns",
    "wof:placetype":"venue"
},
  "geometry": {"coordinates":[4.123401165,51.2210273743],"type":"Point"}
}