{
  "type": "Feature",
  "properties": {
    "addr:full":"Rue De La Sauveni\u00e8re 36 Rochefort Namur 5580",
    "addr:housenumber":"36",
    "addr:postcode":"5580",
    "addr:street":"Rue De La Sauvenie\u0300Re",
    "iso:country":"BE",
    "sg:address":"Rue De La Sauveni\u00e8re 36",
    "sg:city":"Rochefort",
    "sg:classifiers":[
        {
            "category":"Health Services",
            "subcategory":"Doctor",
            "type":"Services"
        }
    ],
    "sg:postcode":"5580",
    "sg:province":"Namur",
    "sg:tags":[
        "medicinephysicians",
        "surgeon"
    ],
    "wof:name":"Hebrant Alain",
    "wof:placetype":"venue"
},
  "geometry": {"coordinates":[5.2211680412,50.1590423584],"type":"Point"}
}