{
  "type": "Feature",
  "properties": {
    "iso:country":"BE",
    "sg:address":"Blancefloerlaan 165",
    "sg:city":"Antwerpen",
    "sg:classifiers":[
        {
            "category":"Shopping",
            "subcategory":"Bicycles & Sporting Goods",
            "type":"Retail Goods"
        }
    ],
    "sg:phone":"+32 3 219 43 20",
    "sg:postcode":"2050",
    "sg:province":"Antwerpen",
    "sg:tags":[
        "-"
    ],
    "wof:name":"Gloriant Fiets",
    "wof:placetype":"venue"
},
  "geometry": {"coordinates":[4.3754692078,51.2198104858],"type":"Point"}
}