{
  "type": "Feature",
  "properties": {
    "addr:full":"Tervuursesteenweg 104 Steenokkerzeel Vlaams-Brabant 1820",
    "addr:housenumber":"104",
    "addr:postcode":"1820",
    "addr:street":"Tervuursesteenweg",
    "iso:country":"BE",
    "sg:address":"Tervuursesteenweg 104",
    "sg:city":"Steenokkerzeel",
    "sg:classifiers":[
        {
            "category":"Personal",
            "subcategory":"Beauty Salon",
            "type":"Services"
        }
    ],
    "sg:phone":"+32 2 751 88 34",
    "sg:postcode":"1820",
    "sg:province":"Vlaams-Brabant",
    "sg:tags":[
        "lady",
        "-",
        "hairdressing"
    ],
    "wof:name":"Anny",
    "wof:placetype":"venue"
},
  "geometry": {"coordinates":[4.4991898537,50.9219589233],"type":"Point"}
}