{
  "type": "Feature",
  "properties": {
    "iso:country":"BE",
    "sg:address":"Merodestraat 1",
    "sg:city":"Duffel",
    "sg:classifiers":[
        {
            "category":"Shopping",
            "subcategory":"Clothing, Apparel, & Fashions",
            "type":"Retail Goods"
        }
    ],
    "sg:phone":"+32 15 31 71 57",
    "sg:postcode":"2570",
    "sg:province":"Antwerpen",
    "sg:tags":[
        "boutique"
    ],
    "wof:name":"F For Fashion",
    "wof:placetype":"venue"
},
  "geometry": {"coordinates":[4.5028691292,51.0966262817],"type":"Point"}
}