{
  "type": "Feature",
  "properties": {
    "addr:full":"Place Verte 19 Celles Hainaut 7760",
    "addr:housenumber":"19",
    "addr:postcode":"7760",
    "addr:street":"Place Verte",
    "iso:country":"BE",
    "sg:address":"Place Verte 19",
    "sg:city":"Celles",
    "sg:orig_category":"Kapsalons",
    "sg:phone":"+32 69 45 59 42",
    "sg:postcode":"7760",
    "sg:province":"Hainaut",
    "wof:name":"Coiffure Aurelie",
    "wof:placetype":"venue"
},
  "geometry": {"coordinates":[3.4558930397,50.7124824524],"type":"Point"}
}