{
  "type": "Feature",
  "properties": {
    "iso:country":"BE",
    "sg:address":"Beversesteenweg 55b12",
    "sg:city":"Roeselare",
    "sg:orig_category":"Jardinage. Services de Nettoyage and de D\u00e9sinfection",
    "sg:phone":"+32 51 26 05 62",
    "sg:postcode":"8800",
    "sg:province":"West-Vlaanderen",
    "wof:name":"All Works",
    "wof:placetype":"venue"
},
  "geometry": {"coordinates":[3.1337099075,50.9615402222],"type":"Point"}
}