{
  "type": "Feature",
  "properties": {
    "addr:full":"Avenue De La Joyeuse Entr\u00e9e 43 Mons Hainaut 7000",
    "addr:housenumber":"43",
    "addr:postcode":"7000",
    "addr:street":"Avenue De La Joyeuse Entre\u0301E;Hainaut",
    "iso:country":"BE",
    "sg:address":"Avenue De La Joyeuse Entr\u00e9e 43",
    "sg:city":"Mons",
    "sg:classifiers":[
        {
            "category":"Insurance",
            "subcategory":"Insurance Agent",
            "type":"Services"
        }
    ],
    "sg:phone":"+32 65 31 18 17",
    "sg:postcode":"7000",
    "sg:province":"Hainaut",
    "sg:tags":[
        "broker"
    ],
    "wof:name":"Petit R",
    "wof:placetype":"venue"
},
  "geometry": {"coordinates":[3.9522509575,50.4547271729],"type":"Point"}
}