{
  "type": "Feature",
  "properties": {
    "iso:country":"BE",
    "sg:address":"Brugstraat 24b3",
    "sg:city":"Beringen",
    "sg:orig_category":"Studios photographiques",
    "sg:phone":"+32 11 43 38 18",
    "sg:postcode":"3580",
    "sg:province":"Limburg",
    "wof:name":"Wilhelmina Dalemans",
    "wof:placetype":"venue"
},
  "geometry": {"coordinates":[5.2182559967,51.0478820801],"type":"Point"}
}