{
  "type": "Feature",
  "properties": {
    "iso:country":"BE",
    "sg:address":"L. De Baerdemaekerstr. 103",
    "sg:city":"Bornem",
    "sg:orig_category":"Herstellingen and onderhoud van auto's",
    "sg:phone":"+32 3 889 19 64",
    "sg:postcode":"2880",
    "sg:province":"Antwerpen",
    "wof:name":"Garage Van Boom",
    "wof:placetype":"venue"
},
  "geometry": {"coordinates":[4.242205143,51.0998497009],"type":"Point"}
}