{
  "type": "Feature",
  "properties": {
    "addr:full":"Astridplein 9 Box 1 Grobbendonk Antwerpen 2280",
    "addr:housenumber":"9;1",
    "addr:postcode":"2280",
    "addr:street":"Astridplein;Box",
    "iso:country":"BE",
    "sg:address":"Astridplein 9 Box 1",
    "sg:city":"Grobbendonk",
    "sg:classifiers":[
        {
            "category":"Personal",
            "subcategory":"Nail Salon",
            "type":"Services"
        }
    ],
    "sg:phone":"+32 14 51 22 95",
    "sg:postcode":"2280",
    "sg:province":"Antwerpen",
    "sg:tags":[
        "pedicure"
    ],
    "wof:name":"Sempels M",
    "wof:placetype":"venue"
},
  "geometry": {"coordinates":[4.7395200729,51.1921081543],"type":"Point"}
}