{
  "type": "Feature",
  "properties": {
    "iso:country":"BE",
    "sg:address":"Tweebruggenstraat 16",
    "sg:city":"Lokeren",
    "sg:orig_category":"R\u00e9parations de chaussures and articles en cuir",
    "sg:phone":"+32 9 348 01 55",
    "sg:postcode":"9160",
    "sg:province":"Oost-Vlaanderen",
    "wof:name":"Dirk Saey",
    "wof:placetype":"venue"
},
  "geometry": {"coordinates":[3.9736840725,51.1096038818],"type":"Point"}
}