{
  "type": "Feature",
  "properties": {
    "iso:country":"BE",
    "sg:address":"Zilvervosdreef 28",
    "sg:city":"Schoten",
    "sg:classifiers":[
        {
            "category":"Professional",
            "type":"Services"
        }
    ],
    "sg:phone":"+32 3 685 26 28",
    "sg:postcode":"2900",
    "sg:province":"Antwerpen",
    "sg:tags":[
        "industrial",
        "work",
        "-",
        "maintenance"
    ],
    "wof:name":"Allaeys",
    "wof:placetype":"venue"
},
  "geometry": {"coordinates":[4.5026650429,51.2724304199],"type":"Point"}
}