{
  "type": "Feature",
  "properties": {
    "iso:country":"BE",
    "sg:address":"Eendrachtstraat 54",
    "sg:city":"Elsene/ixelles",
    "sg:orig_category":"Artiesten and kunstenaars",
    "sg:phone":"+32 2 511 15 45",
    "sg:postcode":"1050",
    "sg:province":"Bruxelles-Capitale",
    "wof:name":"Gregory",
    "wof:placetype":"venue"
},
  "geometry": {"coordinates":[4.3604278564,50.8325691223],"type":"Point"}
}