{
  "type": "Feature",
  "properties": {
    "addr:full":"Rue Francois-lefebvre 173 Li\u00c8ge Li\u00e8ge 4000",
    "addr:housenumber":"173",
    "addr:postcode":"4000",
    "addr:street":"Rue Francois-Lefebvre",
    "iso:country":"BE",
    "sg:address":"Rue Francois-lefebvre 173",
    "sg:city":"Li\u00c8ge",
    "sg:orig_category":"Installation de menuiserie en bois and plastique",
    "sg:phone":"+32 4 246 43 23",
    "sg:postcode":"4000",
    "sg:province":"Li\u00e8ge",
    "wof:name":"Alfred Mativa",
    "wof:placetype":"venue"
},
  "geometry": {"coordinates":[5.5512690544,50.6856269836],"type":"Point"}
}