{
  "type": "Feature",
  "properties": {
    "iso:country":"BE",
    "sg:address":"Eindhovensebaan 70",
    "sg:city":"Hechtel-eksel",
    "sg:classifiers":[
        {
            "category":"Cafe",
            "type":"Food & Drink"
        }
    ],
    "sg:phone":"+32 11 73 16 25",
    "sg:postcode":"3941",
    "sg:province":"Limburg",
    "sg:tags":[
        "caf\u00e9s"
    ],
    "wof:name":"Caf\u00c9 Si\u00cbsta",
    "wof:placetype":"venue"
},
  "geometry": {"coordinates":[5.3647141457,51.1634559631],"type":"Point"}
}