{
  "type": "Feature",
  "properties": {
    "iso:country":"BE",
    "sg:address":"Deinzesteenweg 230",
    "sg:city":"Kruishoutem",
    "sg:orig_category":"Kapsalons",
    "sg:phone":"+32 9 386 36 98",
    "sg:postcode":"9770",
    "sg:province":"Oost-Vlaanderen",
    "wof:name":"Lutgarde Crabbe",
    "wof:placetype":"venue"
},
  "geometry": {"coordinates":[3.5390319824,50.9360733032],"type":"Point"}
}