{
  "type": "Feature",
  "properties": {
    "addr:full":"Windchensweg 14 B\u00fctgenbach (elsenborn) Li\u00e8ge 4750",
    "addr:housenumber":"14",
    "addr:postcode":"4750",
    "addr:street":"Windchensweg",
    "iso:country":"BE",
    "sg:address":"Windchensweg 14",
    "sg:city":"B\u00fctgenbach (elsenborn)",
    "sg:classifiers":[
        {
            "category":"Retail",
            "subcategory":"Repair Shop",
            "type":"Services"
        }
    ],
    "sg:phone":"+32 80 44 54 77",
    "sg:postcode":"4750",
    "sg:province":"Li\u00e8ge",
    "wof:name":"Multi Services",
    "wof:placetype":"venue"
},
  "geometry": {"coordinates":[6.2043948174,50.4263038635],"type":"Point"}
}