{
  "type": "Feature",
  "properties": {
    "addr:full":"Verbindingsstraat 24 Dendermonde Oost-Vlaanderen 9200",
    "addr:housenumber":"24",
    "addr:postcode":"9200",
    "addr:street":"Verbindingsstraat;Oost-Vlaanderen",
    "iso:country":"BE",
    "sg:address":"Verbindingsstraat 24",
    "sg:city":"Dendermonde",
    "sg:orig_category":"Enseignement maternel and primaire",
    "sg:phone":"+32 52 21 34 23",
    "sg:postcode":"9200",
    "sg:province":"Oost-Vlaanderen",
    "wof:name":"Basisschool",
    "wof:placetype":"venue"
},
  "geometry": {"coordinates":[4.1041259766,51.0480575562],"type":"Point"}
}