{
  "type": "Feature",
  "properties": {
    "iso:country":"BE",
    "sg:address":"Verbindingsstraat 24",
    "sg:city":"Dendermonde",
    "sg:orig_category":"Enseignement maternel and primaire",
    "sg:phone":"+32 52 21 34 23",
    "sg:postcode":"9200",
    "sg:province":"Oost-Vlaanderen",
    "wof:name":"Basisschool",
    "wof:placetype":"venue"
},
  "geometry": {"coordinates":[4.1041259766,51.0480575562],"type":"Point"}
}