{
  "type": "Feature",
  "properties": {
    "iso:country":"BE",
    "sg:address":"Chauss\u00c9e De Dinant 1104",
    "sg:city":"Namur",
    "sg:orig_category":"Kinderopvang",
    "sg:phone":"+32 81 46 08 00",
    "sg:postcode":"5100",
    "sg:province":"Namur",
    "wof:name":"L\u00b4heure Bleue",
    "wof:placetype":"venue"
},
  "geometry": {"coordinates":[4.8801860809,50.4151573181],"type":"Point"}
}