{
  "type": "Feature",
  "properties": {
    "addr:full":"Nijverheidstraat 10 Weelde Antwerpen 2381",
    "addr:housenumber":"10",
    "addr:postcode":"2381",
    "addr:street":"Nijverheidstraat",
    "iso:country":"BE",
    "sg:address":"Nijverheidstraat 10",
    "sg:city":"Weelde",
    "sg:classifiers":[
        {
            "category":"Manufacturing",
            "subcategory":"Furniture",
            "type":"Manufacturing & Wholesale Goods"
        }
    ],
    "sg:phone":"+32 14 65 59 76",
    "sg:postcode":"2381",
    "sg:province":"Antwerpen",
    "sg:tags":[
        "bedroom"
    ],
    "wof:name":"Wilboorts & Zoon Nv",
    "wof:placetype":"venue"
},
  "geometry": {"coordinates":[4.9539880753,51.4039115906],"type":"Point"}
}