{
  "type": "Feature",
  "properties": {
    "iso:country":"BE",
    "sg:address":"Onze Lieve Vrouwstraat 26",
    "sg:city":"Bilzen",
    "sg:classifiers":[
        {
            "category":"Shopping",
            "subcategory":"Bicycles & Sporting Goods",
            "type":"Retail Goods"
        }
    ],
    "sg:phone":"+32 89 41 75 53",
    "sg:postcode":"3740",
    "sg:province":"Limburg",
    "sg:tags":[
        "article",
        "de",
        "sport",
        "camping"
    ],
    "wof:name":"Berto Nijst Sport",
    "wof:placetype":"venue"
},
  "geometry": {"coordinates":[5.5154399872,50.8709182739],"type":"Point"}
}