{
  "type": "Feature",
  "properties": {
    "addr:full":"Sur Le Ch\u00cane 56 Libramont-chevigny Luxembourg 6800",
    "addr:housenumber":"56",
    "addr:postcode":"6800",
    "addr:street":"Che\u0302Ne",
    "iso:country":"BE",
    "sg:address":"Sur Le Ch\u00cane 56",
    "sg:city":"Libramont-chevigny",
    "sg:orig_category":"Medische apparatuur, orthopedische artikelen and prothesen Fab",
    "sg:phone":"+32 61 22 47 48",
    "sg:postcode":"6800",
    "sg:province":"Luxembourg",
    "wof:name":"Etienne Hartman",
    "wof:placetype":"venue"
},
  "geometry": {"coordinates":[5.3682398796,49.9125785828],"type":"Point"}
}