{
  "type": "Feature",
  "properties": {
    "addr:full":"Jan Breydellaan 29 Brugge West-Vlaanderen 8200",
    "addr:housenumber":"29",
    "addr:postcode":"8200",
    "addr:street":"Jan Breydellaan",
    "iso:country":"BE",
    "sg:address":"Jan Breydellaan 29",
    "sg:city":"Brugge",
    "sg:orig_category":"Reliure and finition",
    "sg:phone":"+32 50 31 47 95",
    "sg:postcode":"8200",
    "sg:province":"West-Vlaanderen",
    "wof:name":"Johan Van Houcke",
    "wof:placetype":"venue"
},
  "geometry": {"coordinates":[3.2088210583,51.2068977356],"type":"Point"}
}