{
  "type": "Feature",
  "properties": {
    "iso:country":"BE",
    "sg:address":"All\u00c9e Du Bois 46",
    "sg:city":"Neupre",
    "sg:orig_category":"M\u00e9decins and sp\u00e9cialistes",
    "sg:phone":"+32 4 371 57 47",
    "sg:postcode":"4120",
    "sg:province":"Li\u00e8ge",
    "wof:name":"B\u00c9n\u00c9dicte Locht",
    "wof:placetype":"venue"
},
  "geometry": {"coordinates":[5.4998250008,50.5372695923],"type":"Point"}
}