{
  "type": "Feature",
  "properties": {
    "iso:country":"BE",
    "sg:address":"Rue De Vis\u00e9 141",
    "sg:city":"Vis\u00e9 (cheratte)",
    "sg:classifiers":[
        {
            "category":"Arena",
            "subcategory":"Sports Club",
            "type":"Entertainment"
        }
    ],
    "sg:phone":"+32 4 370 90 95",
    "sg:postcode":"4602",
    "sg:province":"Li\u00e8ge",
    "wof:name":"Camlica",
    "wof:placetype":"venue"
},
  "geometry": {"coordinates":[5.6704268456,50.6835098267],"type":"Point"}
}