{
  "type": "Feature",
  "properties": {
    "addr:full":"Stationsstraat 33 Rotselaar Vlaams-Brabant 3110",
    "addr:housenumber":"33",
    "addr:postcode":"3110",
    "addr:street":"Stationsstraat",
    "iso:country":"BE",
    "sg:address":"Stationsstraat 33",
    "sg:city":"Rotselaar",
    "sg:orig_category":"Newspapers, magazines, periodicals - Distribution",
    "sg:phone":"+32 16 44 77 42",
    "sg:postcode":"3110",
    "sg:province":"Vlaams-Brabant",
    "wof:name":"Bloempotteke",
    "wof:placetype":"venue"
},
  "geometry": {"coordinates":[4.7151041031,50.9490814209],"type":"Point"}
}