{
  "type": "Feature",
  "properties": {
    "addr:full":"Mosdijk 1 Lier Antwerpen 2500",
    "addr:housenumber":"1",
    "addr:postcode":"2500",
    "addr:street":"Mosdijk",
    "iso:country":"BE",
    "sg:address":"Mosdijk 1",
    "sg:city":"Lier",
    "sg:orig_category":"Voedingsspeciaalzaken",
    "sg:phone":"+32 3 491 08 20",
    "sg:postcode":"2500",
    "sg:province":"Antwerpen",
    "wof:name":"Sibemol",
    "wof:placetype":"venue"
},
  "geometry": {"coordinates":[4.5730090141,51.1314430237],"type":"Point"}
}