{
  "type": "Feature",
  "properties": {
    "addr:full":"Avenue De La Chasse 96a Bruxelles (etterbeek) Bruxelles-Capitale 1040",
    "addr:housenumber":"96a",
    "addr:postcode":"1040",
    "addr:street":"Avenue De La Chasse",
    "iso:country":"BE",
    "sg:address":"Avenue De La Chasse 96a",
    "sg:city":"Bruxelles (etterbeek)",
    "sg:classifiers":[
        {
            "category":"Shopping",
            "subcategory":"Optician",
            "type":"Retail Goods"
        }
    ],
    "sg:phone":"+32 2 734 10 36",
    "sg:postcode":"1040",
    "sg:province":"Bruxelles-Capitale",
    "sg:tags":[
        "-"
    ],
    "wof:name":"Jadoul Bernard Optique Sprl",
    "wof:placetype":"venue"
},
  "geometry": {"coordinates":[4.3927598,50.8338813782],"type":"Point"}
}