{
  "type": "Feature",
  "properties": {
    "addr:full":"Leerhoeklaan 68 Antwerpen Antwerpen 2180",
    "addr:housenumber":"68",
    "addr:postcode":"2180",
    "addr:street":"Leerhoeklaan",
    "iso:country":"BE",
    "sg:address":"Leerhoeklaan 68",
    "sg:city":"Antwerpen",
    "sg:orig_category":"Studios photographiques",
    "sg:phone":"+32 3 542 67 87",
    "sg:postcode":"2180",
    "sg:province":"Antwerpen",
    "wof:name":"Fa. Coolens Ren\u00c9",
    "wof:placetype":"venue"
},
  "geometry": {"coordinates":[4.4182572365,51.2778625488],"type":"Point"}
}