{
  "type": "Feature",
  "properties": {
    "addr:full":"Hulstsestraat 183 Kuurne West-Vlaanderen 8520",
    "addr:housenumber":"183",
    "addr:postcode":"8520",
    "addr:street":"Hulstsestraat",
    "iso:country":"BE",
    "sg:address":"Hulstsestraat 183",
    "sg:city":"Kuurne",
    "sg:orig_category":"Dierentuinen, botanische tuinen, sterrenwachten and natuurreservaten",
    "sg:phone":"+32 56 70 25 62",
    "sg:postcode":"8520",
    "sg:province":"West-Vlaanderen",
    "wof:name":"Oude Leiearm",
    "wof:placetype":"venue"
},
  "geometry": {"coordinates":[3.291877985,50.8618049622],"type":"Point"}
}