{
  "type": "Feature",
  "properties": {
    "addr:full":"Rue De La Faloise 25 Neufch\u00c2teau Luxembourg 6840",
    "addr:housenumber":"25",
    "addr:postcode":"6840",
    "addr:street":"Rue De La Faloise",
    "iso:country":"BE",
    "sg:address":"Rue De La Faloise 25",
    "sg:city":"Neufch\u00c2teau",
    "sg:classifiers":[
        {
            "category":"Arena",
            "subcategory":"Sports Club",
            "type":"Entertainment"
        }
    ],
    "sg:phone":"+32 61 27 76 72",
    "sg:postcode":"6840",
    "sg:province":"Luxembourg",
    "sg:tags":[
        "terrain",
        "hors",
        "de",
        "installation",
        "sportifs"
    ],
    "wof:name":"R.u.s. Chestrolaise",
    "wof:placetype":"venue"
},
  "geometry": {"coordinates":[5.4252591133,49.8388938904],"type":"Point"}
}