{
  "type": "Feature",
  "properties": {
    "iso:country":"BE",
    "sg:address":"Avenue Facult\u00c9 D'agronomie 9",
    "sg:city":"Gembloux",
    "sg:orig_category":"Notaires",
    "sg:phone":"+32 81 61 02 60",
    "sg:postcode":"5030",
    "sg:province":"Namur",
    "wof:name":"Pierre Proesmans",
    "wof:placetype":"venue"
},
  "geometry": {"coordinates":[4.6980800629,50.5625991821],"type":"Point"}
}