{
  "type": "Feature",
  "properties": {
    "iso:country":"BE",
    "sg:address":"Veldstraat 55",
    "sg:city":"Wijnegem",
    "sg:classifiers":[
        {
            "category":"Insurance",
            "subcategory":"Insurance Agent",
            "type":"Services"
        }
    ],
    "sg:phone":"+32 3 353 32 49",
    "sg:postcode":"2110",
    "sg:province":"Antwerpen",
    "sg:tags":[
        "verzekeringsmakelaars",
        "expert"
    ],
    "wof:name":"Verzekeringen Segers Rudi",
    "wof:placetype":"venue"
},
  "geometry": {"coordinates":[4.5169639587,51.2319526672],"type":"Point"}
}