{
  "type": "Feature",
  "properties": {
    "addr:full":"Chemin Du Frise 21 Blegny Li\u00e8ge 4671",
    "addr:housenumber":"21",
    "addr:postcode":"4671",
    "addr:street":"Chemin Du Frise",
    "iso:country":"BE",
    "sg:address":"Chemin Du Frise 21",
    "sg:city":"Blegny",
    "sg:classifiers":[
        {
            "category":"Personal",
            "subcategory":"Beauty Salon",
            "type":"Services"
        }
    ],
    "sg:phone":"+32 4 362 40 05",
    "sg:postcode":"4671",
    "sg:province":"Li\u00e8ge",
    "sg:tags":[
        "de",
        "coiffure"
    ],
    "wof:name":"Coiffure Jeannine",
    "wof:placetype":"venue"
},
  "geometry": {"coordinates":[5.6820588112,50.6480712891],"type":"Point"}
}