{
  "type": "Feature",
  "properties": {
    "iso:country":"BE",
    "sg:address":"Lange Koepoortstraat 30",
    "sg:city":"Antwerpen",
    "sg:orig_category":"Fast food and meeneem restaurants Kruideniers Restaurants Voedingsspeciaalzaken",
    "sg:phone":"+32 3 231 82 93",
    "sg:postcode":"2000",
    "sg:province":"Antwerpen",
    "wof:name":"Italia Snack",
    "wof:placetype":"venue"
},
  "geometry": {"coordinates":[4.4022707939,51.2229118347],"type":"Point"}
}