{
  "type": "Feature",
  "properties": {
    "iso:country":"BE",
    "sg:address":"Chemin Des Pr\u00c9s 7",
    "sg:city":"Eghezee",
    "sg:orig_category":"Plaatsen van vloer- and muurbekleding Schilders",
    "sg:phone":"+32 81 51 23 27",
    "sg:postcode":"5310",
    "sg:province":"Namur",
    "wof:name":"Christian Mandelaire",
    "wof:placetype":"venue"
},
  "geometry": {"coordinates":[4.8935699463,50.5486602783],"type":"Point"}
}