{
  "type": "Feature",
  "properties": {
    "iso:country":"BE",
    "sg:address":"Koninklijke Baan 160",
    "sg:city":"Westende",
    "sg:classifiers":[
        {
            "category":"Social Services",
            "subcategory":"Job Training",
            "type":"Services"
        }
    ],
    "sg:phone":"+32 58 23 39 63",
    "sg:postcode":"8434",
    "sg:province":"West-Vlaanderen",
    "sg:tags":[
        "de",
        "terrain",
        "camping"
    ],
    "wof:name":"Camping Albatros",
    "wof:placetype":"venue"
},
  "geometry": {"coordinates":[2.7665100098,51.157749176],"type":"Point"}
}