{
  "type": "Feature",
  "properties": {
    "addr:full":"Avenue D'esneux 72 Esneux (tilff) Li\u00e8ge 4130",
    "addr:housenumber":"72",
    "addr:postcode":"4130",
    "addr:street":"Avenue D'Esneux",
    "iso:country":"BE",
    "sg:address":"Avenue D'esneux 72",
    "sg:city":"Esneux (tilff)",
    "sg:classifiers":[
        {
            "category":"Utilities",
            "subcategory":"Telephone",
            "type":"Services"
        }
    ],
    "sg:phone":"+32 4 388 38 04",
    "sg:postcode":"4130",
    "sg:province":"Li\u00e8ge",
    "sg:tags":[
        "installation"
    ],
    "wof:name":"Sagi Sa",
    "wof:placetype":"venue"
},
  "geometry": {"coordinates":[5.584444046,50.5538368225],"type":"Point"}
}