{
  "type": "Feature",
  "properties": {
    "iso:country":"BE",
    "sg:address":"Wesselbend 71-73",
    "sg:city":"Raeren",
    "sg:classifiers":[
        {
            "category":"Travel",
            "subcategory":"Hotels & Motels",
            "type":"Entertainment"
        }
    ],
    "sg:phone":"+32 87 65 86 49",
    "sg:postcode":"4731",
    "sg:province":"Li\u00e8ge",
    "sg:tags":[
        "restaurant"
    ],
    "wof:name":"H\u00d4tel Comme Chez Soi",
    "wof:placetype":"venue"
},
  "geometry": {"coordinates":[6.1027598381,50.7107925415],"type":"Point"}
}