{
  "type": "Feature",
  "properties": {
    "addr:full":"Woestijnstraat 25 Bornem Antwerpen 2880",
    "addr:housenumber":"25",
    "addr:postcode":"2880",
    "addr:street":"Woestijnstraat",
    "iso:country":"BE",
    "sg:address":"Woestijnstraat 25",
    "sg:city":"Bornem",
    "sg:classifiers":[
        {
            "category":"Real Estate",
            "subcategory":"Developer",
            "type":"Services"
        }
    ],
    "sg:phone":"+32 3 889 25 40",
    "sg:postcode":"2880",
    "sg:province":"Antwerpen",
    "sg:tags":[
        "project"
    ],
    "wof:name":"Greenmanor Nv Nv",
    "wof:placetype":"venue"
},
  "geometry": {"coordinates":[4.2711930275,51.0936889648],"type":"Point"}
}