{
  "type": "Feature",
  "properties": {
    "addr:full":"Heideweg 53 Tongeren (overrepen) Limburg 3700",
    "addr:housenumber":"53",
    "addr:postcode":"3700",
    "addr:street":"Heideweg",
    "iso:country":"BE",
    "sg:address":"Heideweg 53",
    "sg:city":"Tongeren (overrepen)",
    "sg:classifiers":[
        {
            "category":"Real Estate",
            "subcategory":"Architect",
            "type":"Services"
        }
    ],
    "sg:phone":"+32 12 26 40 88",
    "sg:postcode":"3700",
    "sg:province":"Limburg",
    "wof:name":"Vandeputte B",
    "wof:placetype":"venue"
},
  "geometry": {"coordinates":[5.4636240005,50.7807197571],"type":"Point"}
}