{
  "type": "Feature",
  "properties": {
    "iso:country":"BE",
    "sg:address":"Anemonenlaan 1",
    "sg:city":"Knokke-heist (heist-aan-zee)",
    "sg:classifiers":[
        {
            "category":"Tea Room",
            "subcategory":"None",
            "type":"Food & Drink"
        }
    ],
    "sg:phone":"+32 50 51 05 34",
    "sg:postcode":"8301",
    "sg:province":"West-Vlaanderen",
    "wof:name":"Cap Horn",
    "wof:placetype":"venue"
},
  "geometry": {"coordinates":[3.2573599815,51.341468811],"type":"Point"}
}