{
  "type": "Feature",
  "properties": {
    "iso:country":"BE",
    "sg:address":"Av. Gloires Nationales 39",
    "sg:city":"Ganshoren/ganshoren",
    "sg:orig_category":"M\u00e9decins and sp\u00e9cialistes",
    "sg:phone":"+32 2 425 15 27",
    "sg:postcode":"1083",
    "sg:province":"Bruxelles-Capitale",
    "wof:name":"Jan Trouerbach",
    "wof:placetype":"venue"
},
  "geometry": {"coordinates":[4.3235168457,50.8663787842],"type":"Point"}
}