{
  "type": "Feature",
  "properties": {
    "iso:country":"BE",
    "sg:address":"Ideaallaan 7b4721",
    "sg:city":"Sint-lambrechts-woluwe/woluwe-saint-lambert",
    "sg:orig_category":"Artsen and specialisten",
    "sg:phone":"+32 2 772 89 48",
    "sg:postcode":"1200",
    "sg:province":"Bruxelles-Capitale",
    "wof:name":"Alexandre Manga",
    "wof:placetype":"venue"
},
  "geometry": {"coordinates":[4.4549779892,50.8495750427],"type":"Point"}
}