{
  "type": "Feature",
  "properties": {
    "addr:full":"Albrecht Rodenbachlaan 41 Box 21 Kortrijk (heule) West-Vlaanderen 8501",
    "addr:housenumber":"41 box 21",
    "addr:postcode":"8501",
    "addr:street":"Albrecht Rodenbachlaan",
    "iso:country":"BE",
    "sg:address":"Albrecht Rodenbachlaan 41 Box 21",
    "sg:city":"Kortrijk (heule)",
    "sg:classifiers":[
        {
            "category":"Communications",
            "type":"Services"
        }
    ],
    "sg:phone":"+32 56 36 03 97",
    "sg:postcode":"8501",
    "sg:province":"West-Vlaanderen",
    "sg:tags":[
        "translator"
    ],
    "wof:name":"Sdt Translations",
    "wof:placetype":"venue"
},
  "geometry": {"coordinates":[3.2340159416,50.8387336731],"type":"Point"}
}