{
  "type": "Feature",
  "properties": {
    "addr:full":"Place De Belle-maison 3 Marchin Li\u00e8ge 4570",
    "addr:housenumber":"3",
    "addr:postcode":"4570",
    "addr:street":"Place De Belle-Maison",
    "iso:country":"BE",
    "sg:address":"Place De Belle-maison 3",
    "sg:city":"Marchin",
    "sg:orig_category":"Banques and organismes de cr\u00e9dit",
    "sg:phone":"+32 85 21 52 12",
    "sg:postcode":"4570",
    "sg:province":"Li\u00e8ge",
    "wof:name":"Bbl",
    "wof:placetype":"venue"
},
  "geometry": {"coordinates":[5.2255811691,50.4803314209],"type":"Point"}
}