{
  "type": "Feature",
  "properties": {
    "iso:country":"BE",
    "sg:address":"Grand'rue 72",
    "sg:city":"Aubange (grand)",
    "sg:orig_category":"Banken and kredietinstellingen",
    "sg:postcode":"6791",
    "sg:province":"Luxembourg",
    "wof:name":"Bbl",
    "wof:placetype":"venue"
},
  "geometry": {"coordinates":[5.8356189728,49.5628623962],"type":"Point"}
}