{
  "type": "Feature",
  "properties": {
    "iso:country":"BE",
    "sg:address":"Rue De La For\u00eat 14",
    "sg:city":"Tenneville",
    "sg:orig_category":"Fiduciairies",
    "sg:phone":"+32 84 45 55 88",
    "sg:postcode":"6970",
    "sg:province":"Luxembourg",
    "wof:name":"Sas Computing Company",
    "wof:placetype":"venue"
},
  "geometry": {"coordinates":[5.5055880547,50.0897674561],"type":"Point"}
}