{
  "type": "Feature",
  "properties": {
    "iso:country":"BE",
    "sg:address":"Nieuwpoortsesteenweg 35",
    "sg:city":"Oostende",
    "sg:orig_category":"Banques and organismes de cr\u00e9dit",
    "sg:phone":"+32 59 70 72 09",
    "sg:postcode":"8400",
    "sg:province":"West-Vlaanderen",
    "wof:name":"Anhyp",
    "wof:placetype":"venue"
},
  "geometry": {"coordinates":[2.9070100784,51.2236061096],"type":"Point"}
}