{
  "type": "Feature",
  "properties": {
    "addr:full":"Rue Provinciale 813 Andenne Li\u00e8ge 4450",
    "addr:housenumber":"813",
    "addr:postcode":"4450",
    "addr:street":"Rue Provinciale",
    "iso:country":"BE",
    "sg:address":"Rue Provinciale 813",
    "sg:city":"Andenne",
    "sg:orig_category":"Forge, Moulage and Profilage des M\u00e9taux",
    "sg:phone":"+32 474 78 64 56",
    "sg:postcode":"4450",
    "sg:province":"Li\u00e8ge",
    "wof:name":"Fran\u00c7ois Sciorre",
    "wof:placetype":"venue"
},
  "geometry": {"coordinates":[5.527659893,50.7088737488],"type":"Point"}
}