{
  "type": "Feature",
  "properties": {
    "iso:country":"BE",
    "sg:address":"Grensstraat 22",
    "sg:city":"Beersel (lot)",
    "sg:classifiers":[
        {
            "category":"Professional",
            "subcategory":"Management & Consulting",
            "type":"Services"
        }
    ],
    "sg:phone":"+32 2 466 46 61",
    "sg:postcode":"1651",
    "sg:province":"Vlaams-Brabant",
    "sg:tags":[
        "-",
        "processing",
        "data",
        "consultant"
    ],
    "wof:name":"E.c.n.s.",
    "wof:placetype":"venue"
},
  "geometry": {"coordinates":[4.2724809647,50.761013031],"type":"Point"}
}