{
  "type": "Feature",
  "properties": {
    "iso:country":"BE",
    "sg:address":"Rotemerlaan 30",
    "sg:city":"Maaseik (neeroeteren)",
    "sg:classifiers":[
        {
            "category":"Real Estate",
            "subcategory":"Architect",
            "type":"Services"
        }
    ],
    "sg:phone":"+32 89 86 59 10",
    "sg:postcode":"3680",
    "sg:province":"Limburg",
    "wof:name":"Tindemans M",
    "wof:placetype":"venue"
},
  "geometry": {"coordinates":[5.791285038,51.0954208374],"type":"Point"}
}