{
  "type": "Feature",
  "properties": {
    "addr:full":"Antwerpsedreef 121 Zoersel Antwerpen 2980",
    "addr:housenumber":"121",
    "addr:postcode":"2980",
    "iso:country":"BE",
    "sg:address":"Antwerpsedreef 121",
    "sg:city":"Zoersel",
    "sg:classifiers":[
        {
            "category":"Manufacturing",
            "subcategory":"Tools & Machinery",
            "type":"Manufacturing & Wholesale Goods"
        }
    ],
    "sg:phone":"+32 3 383 05 06",
    "sg:postcode":"2980",
    "sg:province":"Antwerpen",
    "sg:tags":[
        "diamond"
    ],
    "wof:name":"Prodito Nv",
    "wof:placetype":"venue"
},
  "geometry": {"coordinates":[4.6742777824,51.2618713379],"type":"Point"}
}