{
  "type": "Feature",
  "properties": {
    "iso:country":"BE",
    "sg:address":"Klinkkouterstraat 15",
    "sg:city":"Gent",
    "sg:classifiers":[
        {
            "category":"Building & Trades",
            "subcategory":"Construction",
            "type":"Services"
        }
    ],
    "sg:phone":"+32 9 238 12 08",
    "sg:postcode":"9040",
    "sg:province":"Oost-Vlaanderen",
    "sg:tags":[
        "la",
        "de",
        "\u00e9quipement",
        "pour",
        "machine",
        "location"
    ],
    "wof:name":"Bonne Trading",
    "wof:placetype":"venue"
},
  "geometry": {"coordinates":[3.7488570213,51.0516586304],"type":"Point"}
}