{
  "type": "Feature",
  "properties": {
    "iso:country":"BE",
    "sg:address":"Rue Des C\u00f4teaux 130",
    "sg:city":"Bruxelles",
    "sg:classifiers":[
        {
            "category":"Professional",
            "subcategory":"Engineering",
            "type":"Services"
        }
    ],
    "sg:phone":"+32 2 216 55 19",
    "sg:postcode":"1030",
    "sg:province":"Bruxelles-Capitale",
    "sg:tags":[
        "machine",
        "-",
        "mechanical"
    ],
    "wof:name":"Chauffage Georges Janssens Sa",
    "wof:placetype":"venue"
},
  "geometry": {"coordinates":[4.3765678406,50.8580474854],"type":"Point"}
}