{
  "type": "Feature",
  "properties": {
    "iso:country":"BE",
    "sg:address":"Hoogpoort 45",
    "sg:city":"Gent",
    "sg:orig_category":"Binnenhuisarchitecten Meubelzaken, woning- and keukeninrichting",
    "sg:phone":"+32 9 225 71 66",
    "sg:postcode":"9000",
    "sg:province":"Oost-Vlaanderen",
    "wof:name":"'t Aksent",
    "wof:placetype":"venue"
},
  "geometry": {"coordinates":[3.7135529518,51.0546379089],"type":"Point"}
}