{
  "type": "Feature",
  "properties": {
    "addr:full":"Rue Des Amandiers 10 La Louvi\u00c8re Hainaut 7100",
    "addr:housenumber":"10",
    "addr:postcode":"7100",
    "addr:street":"Rue Des Amandiers",
    "iso:country":"BE",
    "sg:address":"Rue Des Amandiers 10",
    "sg:city":"La Louvi\u00c8re",
    "sg:orig_category":"Installatie van metalen schrijnwerk",
    "sg:phone":"+32 64 28 12 68",
    "sg:postcode":"7100",
    "sg:province":"Hainaut",
    "wof:name":"D.b.f.",
    "wof:placetype":"venue"
},
  "geometry": {"coordinates":[4.1709918976,50.4620857239],"type":"Point"}
}