{
  "type": "Feature",
  "properties": {
    "iso:country":"BE",
    "sg:address":"Rue De Ny 4",
    "sg:city":"Hotton",
    "sg:orig_category":"Bouwmaterialen Gh",
    "sg:phone":"+32 84 46 60 61",
    "sg:postcode":"6990",
    "sg:province":"Luxembourg",
    "wof:name":"Entrepots De La Famenne",
    "wof:placetype":"venue"
},
  "geometry": {"coordinates":[5.4411530495,50.282787323],"type":"Point"}
}