{
  "type": "Feature",
  "properties": {
    "addr:full":"Brugsevaart 40 Gent Oost-Vlaanderen 9030",
    "addr:housenumber":"40",
    "addr:postcode":"9030",
    "addr:street":"Brugsevaart;Oost-Vlaanderen",
    "iso:country":"BE",
    "sg:address":"Brugsevaart 40",
    "sg:city":"Gent",
    "sg:orig_category":"Plaatsen van vloer- and muurbekleding Schilders",
    "sg:phone":"+32 9 226 93 28",
    "sg:postcode":"9030",
    "sg:province":"Oost-Vlaanderen",
    "wof:name":"Peeters Gebrs",
    "wof:placetype":"venue"
},
  "geometry": {"coordinates":[3.6812551022,51.0765647888],"type":"Point"}
}