{
  "type": "Feature",
  "properties": {
    "iso:country":"BE",
    "sg:address":"Hollebeekstraat 2",
    "sg:city":"Izegem",
    "sg:classifiers":[
        {
            "category":"Home & Garden",
            "subcategory":"Home Furnishings",
            "type":"Retail Goods"
        }
    ],
    "sg:phone":"+32 475 76 01 04",
    "sg:postcode":"8870",
    "sg:province":"West-Vlaanderen",
    "sg:tags":[
        "interior",
        "decoration"
    ],
    "wof:name":"Viza Trading",
    "wof:placetype":"venue"
},
  "geometry": {"coordinates":[3.1890230179,50.9094696045],"type":"Point"}
}