{
  "type": "Feature",
  "properties": {
    "iso:country":"BE",
    "sg:address":"Leon Dumortierstraat 164",
    "sg:city":"Hove",
    "sg:classifiers":[
        {
            "category":"Real Estate",
            "subcategory":"Architect",
            "type":"Services"
        }
    ],
    "sg:phone":"+32 3 455 82 18",
    "sg:postcode":"2540",
    "sg:province":"Antwerpen",
    "wof:name":"Lenders E",
    "wof:placetype":"venue"
},
  "geometry": {"coordinates":[4.4712228775,51.1498832703],"type":"Point"}
}