{
  "type": "Feature",
  "properties": {
    "iso:country":"BE",
    "sg:address":"Rue De Borlon 14",
    "sg:city":"Somme-leuze",
    "sg:classifiers":[
        {
            "category":"Insurance",
            "subcategory":"Insurance Agent",
            "type":"Services"
        }
    ],
    "sg:phone":"+32 86 34 42 09",
    "sg:postcode":"5377",
    "sg:province":"Namur",
    "sg:tags":[
        "verzekeringsmakelaars",
        "expert"
    ],
    "wof:name":"Willeme Assure",
    "wof:placetype":"venue"
},
  "geometry": {"coordinates":[5.3698949814,50.3404350281],"type":"Point"}
}