{
  "type": "Feature",
  "properties": {
    "iso:country":"BE",
    "sg:address":"Avenue De La For\u00eat 184",
    "sg:city":"Bruxelles",
    "sg:classifiers":[
        {
            "category":"Transit Center",
            "subcategory":"Freight",
            "type":"Transportation"
        }
    ],
    "sg:phone":"+32 2 672 97 00",
    "sg:postcode":"1000",
    "sg:province":"Bruxelles-Capitale",
    "sg:tags":[
        "import",
        "export",
        "-"
    ],
    "wof:name":"Sucotrade Sa",
    "wof:placetype":"venue"
},
  "geometry": {"coordinates":[4.3957967758,50.7982406616],"type":"Point"}
}