{
  "type": "Feature",
  "properties": {
    "iso:country":"BE",
    "sg:address":"Le Petit Clos 15",
    "sg:city":"Verviers (heusy)",
    "sg:classifiers":[
        {
            "category":"Professional",
            "subcategory":"Art Services",
            "type":"Services"
        }
    ],
    "sg:phone":"+32 87 22 79 83",
    "sg:postcode":"4802",
    "sg:province":"Li\u00e8ge",
    "sg:tags":[
        "technical",
        "photographer",
        "industrial",
        "-"
    ],
    "wof:name":"Breuer Jacques Sprl",
    "wof:placetype":"venue"
},
  "geometry": {"coordinates":[5.8600077629,50.5733757019],"type":"Point"}
}