{
  "type": "Feature",
  "properties": {
    "addr:full":"Guldenroedestraat31 Gent Oost-Vlaanderen 9030",
    "addr:postcode":"9030",
    "addr:street":"Oost-Vlaanderen",
    "iso:country":"BE",
    "sg:address":"Guldenroedestraat31",
    "sg:city":"Gent",
    "sg:classifiers":[
        {
            "category":"Taxi",
            "type":"Transportation"
        }
    ],
    "sg:phone":"+32 75250799",
    "sg:postcode":"9030",
    "sg:province":"Oost-Vlaanderen",
    "sg:tags":[
        "taxi's"
    ],
    "wof:name":"Taxi Cuypers",
    "wof:placetype":"venue"
},
  "geometry": {"coordinates":[3.6745951176,51.072933197],"type":"Point"}
}