{
  "type": "Feature",
  "properties": {
    "addr:full":"Vorstsesteenweg 166 Sint-pieters-leeuw (ruisbroek) Vlaams-Brabant 1601",
    "addr:housenumber":"166",
    "addr:postcode":"1601",
    "addr:street":"Vorstsesteenweg",
    "iso:country":"BE",
    "sg:address":"Vorstsesteenweg 166",
    "sg:city":"Sint-pieters-leeuw (ruisbroek)",
    "sg:classifiers":[
        {
            "category":"Wholesale",
            "subcategory":"Chemicals & Plastics",
            "type":"Manufacturing & Wholesale Goods"
        }
    ],
    "sg:phone":"+32 2 377 69 15",
    "sg:postcode":"1601",
    "sg:province":"Vlaams-Brabant",
    "sg:tags":[
        "dyestuff"
    ],
    "wof:name":"Stiernon Robert (ets) Sa",
    "wof:placetype":"venue"
},
  "geometry": {"coordinates":[4.3008317947,50.7944717407],"type":"Point"}
}