{
  "type": "Feature",
  "properties": {
    "addr:full":"Sint-crispijnstraat 49 Izegem West-Vlaanderen 8870",
    "addr:housenumber":"49",
    "addr:postcode":"8870",
    "addr:street":"Sint-Crispijnstraat",
    "iso:country":"BE",
    "sg:address":"Sint-crispijnstraat 49",
    "sg:city":"Izegem",
    "sg:classifiers":[
        {
            "category":"Health Services",
            "subcategory":"Health Practitioner",
            "type":"Services"
        }
    ],
    "sg:phone":"+32 51 30 00 25",
    "sg:postcode":"8870",
    "sg:province":"West-Vlaanderen",
    "sg:tags":[
        "physiotherapist"
    ],
    "wof:name":"Parmentier F",
    "wof:placetype":"venue"
},
  "geometry": {"coordinates":[3.2074410915,50.9178237915],"type":"Point"}
}