{
  "type": "Feature",
  "properties": {
    "iso:country":"BE",
    "sg:address":"Rue D'houdremont 33",
    "sg:city":"Vresse-sur-semois (nafraiture)",
    "sg:classifiers":[
        {
            "category":"Landmark",
            "subcategory":"Tourist Attraction",
            "type":"Public Place"
        }
    ],
    "sg:phone":"+32 61 50 11 33",
    "sg:postcode":"5550",
    "sg:province":"Namur",
    "sg:tags":[
        "-",
        "tourism",
        "interest",
        "sight"
    ],
    "wof:name":"Chiquetterie (la)",
    "wof:placetype":"venue"
},
  "geometry": {"coordinates":[4.9198732376,49.925994873],"type":"Point"}
}