{
  "type": "Feature",
  "properties": {
    "iso:country":"BE",
    "sg:address":"Oudenburgsesteenweg 90",
    "sg:city":"Oostende",
    "sg:orig_category":"Polyurethane Reaction Injection Mouldings Rim",
    "sg:phone":"+32 59 80 32 52",
    "sg:postcode":"8400",
    "sg:province":"West-Vlaanderen",
    "wof:name":"Orac Nv",
    "wof:placetype":"venue"
},
  "geometry": {"coordinates":[2.9684050083,51.217590332],"type":"Point"}
}