{
  "type": "Feature",
  "properties": {
    "iso:country":"BE",
    "sg:address":"Margrietstraat 96",
    "sg:city":"Sint-gillis-waas",
    "sg:orig_category":"Tuinen",
    "sg:phone":"+32 3 773 39 68",
    "sg:postcode":"9170",
    "sg:province":"Oost-Vlaanderen",
    "wof:name":"Aben G.",
    "wof:placetype":"venue"
},
  "geometry": {"coordinates":[4.154943943,51.2511787415],"type":"Point"}
}