{
  "type": "Feature",
  "properties": {
    "addr:full":"Rue Roua 63 Amay Li\u00e8ge 4540",
    "addr:housenumber":"63",
    "addr:postcode":"4540",
    "addr:street":"Rue Roua",
    "iso:country":"BE",
    "sg:address":"Rue Roua 63",
    "sg:city":"Amay",
    "sg:classifiers":[
        {
            "category":"Building & Trades",
            "subcategory":"Plumbing",
            "type":"Services"
        }
    ],
    "sg:phone":"+32 475 73 28 54",
    "sg:postcode":"4540",
    "sg:province":"Li\u00e8ge",
    "sg:tags":[
        "repair",
        "mainten",
        "-",
        "central",
        "heating"
    ],
    "wof:name":"Cordonnier P",
    "wof:placetype":"venue"
},
  "geometry": {"coordinates":[5.3137850761,50.5520706177],"type":"Point"}
}