{
  "type": "Feature",
  "properties": {
    "addr:full":"Rode 26ba Glabbeek Vlaams-Brabant 3380",
    "addr:housenumber":"26ba",
    "addr:postcode":"3380",
    "addr:street":"Rode",
    "iso:country":"BE",
    "sg:address":"Rode 26ba",
    "sg:city":"Glabbeek",
    "sg:orig_category":"Producteurs de fruits. Producteurs de l\u00e9gumes",
    "sg:phone":"+32 16 77 91 87",
    "sg:postcode":"3380",
    "sg:province":"Vlaams-Brabant",
    "wof:name":"Paul Janssens",
    "wof:placetype":"venue"
},
  "geometry": {"coordinates":[4.9375939369,50.8827667236],"type":"Point"}
}