{
  "type": "Feature",
  "properties": {
    "iso:country":"BE",
    "sg:address":"Rue De L'arm\u00e9e Secr\u00e8te 20",
    "sg:city":"Verviers (stembert)",
    "sg:classifiers":[
        {
            "category":"Education",
            "subcategory":"Dance Studio",
            "type":"Public Place"
        }
    ],
    "sg:phone":"+32 87 47 55 33",
    "sg:postcode":"4801",
    "sg:province":"Li\u00e8ge",
    "sg:tags":[
        "school",
        "dancing"
    ],
    "wof:name":"Sart Swing Asbl",
    "wof:placetype":"venue"
},
  "geometry": {"coordinates":[5.9036531448,50.5893058777],"type":"Point"}
}