{
  "type": "Feature",
  "properties": {
    "addr:full":"Brasschaatsesteenweg 180 Kalmthout Antwerpen 2920",
    "addr:housenumber":"180",
    "addr:postcode":"2920",
    "addr:street":"Brasschaatsesteenweg",
    "iso:country":"BE",
    "sg:address":"Brasschaatsesteenweg 180",
    "sg:city":"Kalmthout",
    "sg:orig_category":"Woningbouw",
    "sg:phone":"+32 3 666 82 39",
    "sg:postcode":"2920",
    "sg:province":"Antwerpen",
    "wof:name":"Lobon",
    "wof:placetype":"venue"
},
  "geometry": {"coordinates":[4.5049448013,51.379322052],"type":"Point"}
}