{
  "type": "Feature",
  "properties": {
    "addr:full":"Dweersstraat 10 Brugge West-Vlaanderen 8000",
    "addr:housenumber":"10",
    "addr:postcode":"8000",
    "addr:street":"Dweersstraat",
    "iso:country":"BE",
    "sg:address":"Dweersstraat 10",
    "sg:city":"Brugge",
    "sg:classifiers":[
        {
            "category":"Restaurant",
            "type":"Food & Drink"
        }
    ],
    "sg:phone":"+32 50 34 13 27",
    "sg:postcode":"8000",
    "sg:province":"West-Vlaanderen",
    "sg:tags":[
        "caf\u00e9s"
    ],
    "wof:name":"Taverne Le Bon Vivant",
    "wof:placetype":"venue"
},
  "geometry": {"coordinates":[3.2191109657,51.2062988281],"type":"Point"}
}