{
  "type": "Feature",
  "properties": {
    "addr:full":"Grimaldilaan 75 Stabroek Antwerpen 2940",
    "addr:housenumber":"75",
    "addr:postcode":"2940",
    "addr:street":"Grimaldilaan",
    "iso:country":"BE",
    "sg:address":"Grimaldilaan 75",
    "sg:city":"Stabroek",
    "sg:orig_category":"Schoonheidssalons",
    "sg:phone":"+32 3 568 84 00",
    "sg:postcode":"2940",
    "sg:province":"Antwerpen",
    "wof:name":"Erna Claes",
    "wof:placetype":"venue"
},
  "geometry": {"coordinates":[4.3796458244,51.3317604065],"type":"Point"}
}