{
  "type": "Feature",
  "properties": {
    "iso:country":"BE",
    "sg:address":"Burgstraat 32",
    "sg:city":"Gent",
    "sg:classifiers":[
        {
            "category":"Food & Beverages",
            "subcategory":"Specialty",
            "type":"Retail Goods"
        }
    ],
    "sg:phone":"+32 9 223 62 92",
    "sg:postcode":"9000",
    "sg:province":"Oost-Vlaanderen",
    "sg:tags":[
        "health",
        "dietary",
        "-",
        "biological"
    ],
    "wof:name":"Gravensteen Revogan Nv",
    "wof:placetype":"venue"
},
  "geometry": {"coordinates":[3.7182509899,51.0565414429],"type":"Point"}
}