{
  "type": "Feature",
  "properties": {
    "iso:country":"BE",
    "sg:address":"Bodemstraat 12",
    "sg:city":"Wellen",
    "sg:classifiers":[
        {
            "category":"Professional",
            "subcategory":"Printing & Photocopies",
            "type":"Services"
        }
    ],
    "sg:phone":"+32 11 37 03 11",
    "sg:postcode":"3830",
    "sg:province":"Limburg",
    "sg:tags":[
        "cd-r"
    ],
    "wof:name":"Sentinel Nv",
    "wof:placetype":"venue"
},
  "geometry": {"coordinates":[5.3309259415,50.8591690063],"type":"Point"}
}