{
  "type": "Feature",
  "properties": {
    "iso:country":"BE",
    "sg:address":"Smissestraat 71",
    "sg:city":"Oudenaarde",
    "sg:orig_category":"Installatie van houten of kunststof schrijnwerk Vloer- and muurbekleding",
    "sg:phone":"+32 55 30 08 84",
    "sg:postcode":"9700",
    "sg:province":"Oost-Vlaanderen",
    "wof:name":"Werner Wardenier",
    "wof:placetype":"venue"
},
  "geometry": {"coordinates":[3.6246740818,50.8399124146],"type":"Point"}
}