{
  "type": "Feature",
  "properties": {
    "addr:full":"Rue De Virelles 75 Chimay Hainaut 6460",
    "addr:housenumber":"75",
    "addr:postcode":"6460",
    "addr:street":"Rue De Virelles",
    "iso:country":"BE",
    "sg:address":"Rue De Virelles 75",
    "sg:city":"Chimay",
    "sg:orig_category":"Installations and terrains de sport hors centres sportifs. Centres sportifs",
    "sg:phone":"+32 60 21 27 73",
    "sg:postcode":"6460",
    "sg:province":"Hainaut",
    "wof:name":"Centre Sportif",
    "wof:placetype":"venue"
},
  "geometry": {"coordinates":[4.3236498833,50.0504455566],"type":"Point"}
}