{
  "type": "Feature",
  "properties": {
    "iso:country":"BE",
    "sg:address":"Rue Des Champs Elys\u00e9es 18",
    "sg:city":"Ciney",
    "sg:classifiers":[
        {
            "category":"Education",
            "subcategory":"School",
            "type":"Public Place"
        }
    ],
    "sg:phone":"+32 83 21 57 95",
    "sg:postcode":"5590",
    "sg:province":"Namur",
    "sg:tags":[
        "breeding",
        "livestock",
        "cattle"
    ],
    "wof:name":"Linalux A.e.d.b. S.c.r.l.",
    "wof:placetype":"venue"
},
  "geometry": {"coordinates":[5.0996251106,50.3148384094],"type":"Point"}
}