{
  "type": "Feature",
  "properties": {
    "addr:full":"Diestsesteenweg 355 Aarschot Vlaams-Brabant 3202",
    "addr:housenumber":"355",
    "addr:postcode":"3202",
    "addr:street":"Diestsesteenweg",
    "iso:country":"BE",
    "sg:address":"Diestsesteenweg 355",
    "sg:city":"Aarschot",
    "sg:orig_category":"Verlichting and huishoudartikelen",
    "sg:phone":"+32 16 50 01 20",
    "sg:postcode":"3202",
    "sg:province":"Vlaams-Brabant",
    "wof:name":"Bernar",
    "wof:placetype":"venue"
},
  "geometry": {"coordinates":[4.8970079422,50.9740333557],"type":"Point"}
}