{
  "type": "Feature",
  "properties": {
    "addr:full":"Vlietestraat 166 Harelbeke West-Vlaanderen 8531",
    "addr:housenumber":"166",
    "addr:postcode":"8531",
    "addr:street":"Vlietestraat",
    "iso:country":"BE",
    "sg:address":"Vlietestraat 166",
    "sg:city":"Harelbeke",
    "sg:orig_category":"Jeux de hasard",
    "sg:phone":"+32 56 71 76 12",
    "sg:postcode":"8531",
    "sg:province":"West-Vlaanderen",
    "wof:name":"Pmu",
    "wof:placetype":"venue"
},
  "geometry": {"coordinates":[3.2986299992,50.8817405701],"type":"Point"}
}