{
  "type": "Feature",
  "properties": {
    "addr:full":"Westkantstraat 52 Oostkamp (ruddervoorde) West-Vlaanderen 8020",
    "addr:housenumber":"52",
    "addr:postcode":"8020",
    "addr:street":"Westkantstraat",
    "iso:country":"BE",
    "sg:address":"Westkantstraat 52",
    "sg:city":"Oostkamp (ruddervoorde)",
    "sg:classifiers":[
        {
            "category":"Building & Trades",
            "subcategory":"Landscaping Services",
            "type":"Services"
        }
    ],
    "sg:phone":"+32 50 27 82 11",
    "sg:postcode":"8020",
    "sg:province":"West-Vlaanderen",
    "sg:tags":[
        "nurseryman"
    ],
    "wof:name":"Aurea Boomkwekerij",
    "wof:placetype":"venue"
},
  "geometry": {"coordinates":[3.1867959499,51.0680236816],"type":"Point"}
}