{
  "type": "Feature",
  "properties": {
    "addr:full":"Dorpsstraat 4 Londerzeel Vlaams-Brabant 1840",
    "addr:housenumber":"4",
    "addr:postcode":"1840",
    "addr:street":"Dorpsstraat",
    "iso:country":"BE",
    "sg:address":"Dorpsstraat 4",
    "sg:city":"Londerzeel",
    "sg:classifiers":[
        {
            "category":"Professional",
            "subcategory":"Testing Lab",
            "type":"Services"
        }
    ],
    "sg:phone":"+32 52 30 91 01",
    "sg:postcode":"1840",
    "sg:province":"Vlaams-Brabant",
    "sg:tags":[
        "chemist"
    ],
    "wof:name":"Lion R",
    "wof:placetype":"venue"
},
  "geometry": {"coordinates":[4.3021521568,51.0036392212],"type":"Point"}
}