{
  "type": "Feature",
  "properties": {
    "iso:country":"BE",
    "sg:address":"Kammerstraat 22",
    "sg:city":"Gent",
    "sg:orig_category":"Activit\u00e9s d\u00b4action sociale sans h\u00e9bergement",
    "sg:phone":"+32 9 238 26 26",
    "sg:postcode":"9000",
    "sg:province":"Oost-Vlaanderen",
    "wof:name":"Holebifoon",
    "wof:placetype":"venue"
},
  "geometry": {"coordinates":[3.7270750999,51.0557174683],"type":"Point"}
}