{
  "type": "Feature",
  "properties": {
    "addr:full":"Antwerpsesteenweg 37 Kapellen Antwerpen 2950",
    "addr:housenumber":"37",
    "addr:postcode":"2950",
    "addr:street":"Antwerpsesteenweg",
    "iso:country":"BE",
    "sg:address":"Antwerpsesteenweg 37",
    "sg:city":"Kapellen",
    "sg:orig_category":"Shopping-centres",
    "sg:phone":"+32 3 605 60 00",
    "sg:postcode":"2950",
    "sg:province":"Antwerpen",
    "wof:name":"Promenade",
    "wof:placetype":"venue"
},
  "geometry": {"coordinates":[4.4290380478,51.3132019043],"type":"Point"}
}