{
  "type": "Feature",
  "properties": {
    "addr:full":"Rue D'herbeumont 13 Florenville Luxembourg 6820",
    "addr:housenumber":"13",
    "addr:postcode":"6820",
    "addr:street":"Rue D'Herbeumont",
    "iso:country":"BE",
    "sg:address":"Rue D'herbeumont 13",
    "sg:city":"Florenville",
    "sg:orig_category":"Transports routiers de marchandises",
    "sg:phone":"+32 61 31 23 40",
    "sg:postcode":"6820",
    "sg:province":"Luxembourg",
    "wof:name":"Verger P",
    "wof:placetype":"venue"
},
  "geometry": {"coordinates":[5.2426939011,49.7322044373],"type":"Point"}
}