{
  "type": "Feature",
  "properties": {
    "iso:country":"BE",
    "sg:address":"Victor Olivierlaan 6",
    "sg:city":"Anderlecht",
    "sg:orig_category":"Artsen and specialisten",
    "sg:phone":"+32 2 520 59 95",
    "sg:postcode":"1070",
    "sg:province":"Bruxelles-Capitale",
    "wof:name":"St\u00c9phane Muller",
    "wof:placetype":"venue"
},
  "geometry": {"coordinates":[4.3138861656,50.8343505859],"type":"Point"}
}