{
  "type": "Feature",
  "properties": {
    "iso:country":"BE",
    "sg:address":"Rue Des Carri\u00c8res 5",
    "sg:city":"Seneffe",
    "sg:classifiers":[
        {
            "category":"Cafe",
            "type":"Food & Drink"
        }
    ],
    "sg:phone":"+32 67 87 77 04",
    "sg:postcode":"7181",
    "sg:province":"Hainaut",
    "sg:tags":[
        "caf\u00e9s"
    ],
    "wof:name":"Marie-claire Keppens",
    "wof:placetype":"venue"
},
  "geometry": {"coordinates":[4.2739701271,50.5661697388],"type":"Point"}
}