{
  "type": "Feature",
  "properties": {
    "iso:country":"BE",
    "sg:address":"Rood-kruisstraat",
    "sg:city":"Gingelom",
    "sg:classifiers":[
        {
            "category":"Arena",
            "subcategory":"Sports Club",
            "type":"Entertainment"
        }
    ],
    "sg:phone":"+32 11 83 15 37",
    "sg:postcode":"3890",
    "sg:province":"Limburg",
    "wof:name":"K.v.e. Gingelom",
    "wof:placetype":"venue"
},
  "geometry": {"coordinates":[5.1329078674,50.7547225952],"type":"Point"}
}