{
  "type": "Feature",
  "properties": {
    "addr:full":"Chemin Preuscamp 8 Ath Hainaut 7822",
    "addr:housenumber":"8",
    "addr:postcode":"7822",
    "addr:street":"Chemin Preuscamp",
    "iso:country":"BE",
    "sg:address":"Chemin Preuscamp 8",
    "sg:city":"Ath",
    "sg:classifiers":[
        {
            "category":"Autos & Motor Vehicles",
            "subcategory":"Fuel & Gas Station",
            "type":"Retail Goods"
        }
    ],
    "sg:phone":"+32 68 25 03 11",
    "sg:postcode":"7822",
    "sg:province":"Hainaut",
    "sg:tags":[
        "stations-service",
        "carburants"
    ],
    "wof:name":"Gasotec",
    "wof:placetype":"venue"
},
  "geometry": {"coordinates":[3.8554110527,50.6509056091],"type":"Point"}
}