{
  "type": "Feature",
  "properties": {
    "addr:full":"Baalsesteenweg 34 Begijnendijk Vlaams-Brabant 3130",
    "addr:housenumber":"34",
    "addr:postcode":"3130",
    "addr:street":"Baalsesteenweg",
    "iso:country":"BE",
    "sg:address":"Baalsesteenweg 34",
    "sg:city":"Begijnendijk",
    "sg:classifiers":[
        {
            "category":"Autos & Motor Vehicles",
            "subcategory":"Motorcycle Sales",
            "type":"Retail Goods"
        }
    ],
    "sg:phone":"+32 16 53 53 68",
    "sg:postcode":"3130",
    "sg:province":"Vlaams-Brabant",
    "sg:tags":[
        "motorbike"
    ],
    "wof:name":"Harley Buell Service",
    "wof:placetype":"venue"
},
  "geometry": {"coordinates":[4.7800412178,51.0177192688],"type":"Point"}
}