{
  "type": "Feature",
  "properties": {
    "addr:full":"Jan Devischstraat 148 Knokke-heist West-Vlaanderen 8300",
    "addr:housenumber":"148",
    "addr:postcode":"8300",
    "addr:street":"Devischstraat",
    "iso:country":"BE",
    "sg:address":"Jan Devischstraat 148",
    "sg:city":"Knokke-heist",
    "sg:orig_category":"Rev\u00eatements pour sols and murs. Peinture",
    "sg:phone":"+32 50 60 01 68",
    "sg:postcode":"8300",
    "sg:province":"West-Vlaanderen",
    "wof:name":"Van Raefelgem",
    "wof:placetype":"venue"
},
  "geometry": {"coordinates":[3.3028020859,51.3384284973],"type":"Point"}
}