{
  "type": "Feature",
  "properties": {
    "iso:country":"BE",
    "sg:address":"Hertstraat 19",
    "sg:city":"Hoeselt",
    "sg:orig_category":"Charpentes and couvertures. Plomberie, chauffage and installations sanitaires. Installation de menui",
    "sg:phone":"+32 12 23 73 49",
    "sg:postcode":"3732",
    "sg:province":"Limburg",
    "wof:name":"E.p.s.",
    "wof:placetype":"venue"
},
  "geometry": {"coordinates":[5.4484348297,50.8401260376],"type":"Point"}
}