{
  "type": "Feature",
  "properties": {
    "iso:country":"BE",
    "sg:address":"Klein Laarstraat 26",
    "sg:city":"Heist-op-den-berg",
    "sg:classifiers":[
        {
            "category":"Personal",
            "subcategory":"Beauty Salon",
            "type":"Services"
        }
    ],
    "sg:phone":"+32 15 73 08 58",
    "sg:postcode":"2220",
    "sg:province":"Antwerpen",
    "sg:tags":[
        "lady",
        "-",
        "hairdressing"
    ],
    "wof:name":"Haarmode Sas",
    "wof:placetype":"venue"
},
  "geometry": {"coordinates":[4.7481098175,51.0676651001],"type":"Point"}
}