{
  "type": "Feature",
  "properties": {
    "iso:country":"BE",
    "sg:address":"De Ridderstraat 7",
    "sg:city":"Aalst",
    "sg:classifiers":[
        {
            "category":"Fast Food",
            "type":"Food & Drink"
        }
    ],
    "sg:phone":"+32 53 78 91 06",
    "sg:postcode":"9300",
    "sg:province":"Oost-Vlaanderen",
    "sg:tags":[
        "meeneem",
        "restaurant"
    ],
    "wof:name":"Restaurant Naxos",
    "wof:placetype":"venue"
},
  "geometry": {"coordinates":[4.0364699364,50.9398231506],"type":"Point"}
}