{
  "type": "Feature",
  "properties": {
    "iso:country":"BE",
    "sg:address":"Gerhagen 1",
    "sg:city":"Olen",
    "sg:orig_category":"Fa\u00e7ade Construction, Fa\u00e7ade Lining Services",
    "sg:phone":"+32 14 22 20 40",
    "sg:postcode":"2250",
    "sg:province":"Antwerpen",
    "wof:name":"Idg Industri\u00eble Dak & Gevelwerken Nv",
    "wof:placetype":"venue"
},
  "geometry": {"coordinates":[4.9124798775,51.1634407043],"type":"Point"}
}