{
  "type": "Feature",
  "properties": {
    "addr:full":"Fontaine \u00c0 Louche Straat 96ba Edingen/enghien Hainaut 7850",
    "addr:housenumber":"96ba",
    "addr:postcode":"7850",
    "addr:street":"Louche Straat",
    "iso:country":"BE",
    "sg:address":"Fontaine \u00c0 Louche Straat 96ba",
    "sg:city":"Edingen/enghien",
    "sg:orig_category":"Verbruikerskredietinstellingen",
    "sg:phone":"+32 2 395 81 22",
    "sg:postcode":"7850",
    "sg:province":"Hainaut",
    "wof:name":"A. Delguste",
    "wof:placetype":"venue"
},
  "geometry": {"coordinates":[4.0334601402,50.6914787292],"type":"Point"}
}