{
  "type": "Feature",
  "properties": {
    "iso:country":"BE",
    "sg:address":"Rue Mandenne 23",
    "sg:city":"Momignies",
    "sg:orig_category":"Epiceries",
    "sg:phone":"+32 60 51 11 59",
    "sg:postcode":"6590",
    "sg:province":"Hainaut",
    "wof:name":"Marianne Macq",
    "wof:placetype":"venue"
},
  "geometry": {"coordinates":[4.1535010338,50.0276184082],"type":"Point"}
}