{
  "type": "Feature",
  "properties": {
    "iso:country":"BE",
    "sg:address":"Rue L\u00c9on Bernus 26",
    "sg:city":"Charleroi",
    "sg:orig_category":"Artsen and specialisten",
    "sg:phone":"+32 71 31 21 73",
    "sg:postcode":"6000",
    "sg:province":"Hainaut",
    "wof:name":"J. Stein",
    "wof:placetype":"venue"
},
  "geometry": {"coordinates":[4.4493122101,50.4145317078],"type":"Point"}
}