{
  "type": "Feature",
  "properties": {
    "addr:full":"Rue De Launoy 15 Paliseul Luxembourg 6850",
    "addr:housenumber":"15",
    "addr:postcode":"6850",
    "addr:street":"Rue De Launoy",
    "iso:country":"BE",
    "sg:address":"Rue De Launoy 15",
    "sg:city":"Paliseul",
    "sg:orig_category":"Entretien and r\u00e9parations de voitures",
    "sg:phone":"+32 61 53 36 58",
    "sg:postcode":"6850",
    "sg:province":"Luxembourg",
    "wof:name":"Robert Noel",
    "wof:placetype":"venue"
},
  "geometry": {"coordinates":[5.1429238319,49.879486084],"type":"Point"}
}