{
  "type": "Feature",
  "properties": {
    "iso:country":"BE",
    "sg:address":"Rue De L'escrime 1",
    "sg:city":"Bruxelles (forest)",
    "sg:classifiers":[
        {
            "category":"Communications",
            "type":"Services"
        }
    ],
    "sg:postcode":"1190",
    "sg:province":"Bruxelles-Capitale",
    "sg:tags":[
        "translator"
    ],
    "wof:name":"Prumont Genevi\u00e8ve",
    "wof:placetype":"venue"
},
  "geometry": {"coordinates":[4.3363637924,50.8171348572],"type":"Point"}
}