{
  "type": "Feature",
  "properties": {
    "addr:full":"Chauss\u00e9e De Charleroi 115 Jodoigne Brabant Wallon 1370",
    "addr:housenumber":"115",
    "addr:postcode":"1370",
    "addr:street":"Chausse\u0301E De Charleroi",
    "iso:country":"BE",
    "sg:address":"Chauss\u00e9e De Charleroi 115",
    "sg:city":"Jodoigne",
    "sg:classifiers":[
        {
            "category":"Shopping",
            "subcategory":"Books",
            "type":"Retail Goods"
        }
    ],
    "sg:phone":"+32 10 81 97 30",
    "sg:postcode":"1370",
    "sg:province":"Brabant Wallon",
    "sg:tags":[
        "bookseller"
    ],
    "wof:name":"Co\u00f6perative Des Papetiers Sc",
    "wof:placetype":"venue"
},
  "geometry": {"coordinates":[4.8596720695,50.7134742737],"type":"Point"}
}