{
  "type": "Feature",
  "properties": {
    "addr:full":"Rue Du Pont Margot 40 Habay (habay-la-neuve) Luxembourg 6720",
    "addr:housenumber":"40",
    "addr:postcode":"6720",
    "addr:street":"Rue Du Pont Margot",
    "iso:country":"BE",
    "sg:address":"Rue Du Pont Margot 40",
    "sg:city":"Habay (habay-la-neuve)",
    "sg:classifiers":[
        {
            "category":"Building & Trades",
            "subcategory":"Plumbing",
            "type":"Services"
        }
    ],
    "sg:phone":"+32 63 42 24 22",
    "sg:postcode":"6720",
    "sg:province":"Luxembourg",
    "sg:tags":[
        "repair",
        "mainten",
        "-",
        "central",
        "heating"
    ],
    "wof:name":"Martin Ets",
    "wof:placetype":"venue"
},
  "geometry": {"coordinates":[5.6468100548,49.7278633118],"type":"Point"}
}