{
  "type": "Feature",
  "properties": {
    "addr:full":"Diesterstraat 22 Hasselt Limburg 3500",
    "addr:housenumber":"22",
    "addr:postcode":"3500",
    "addr:street":"Diesterstraat",
    "iso:country":"BE",
    "sg:address":"Diesterstraat 22",
    "sg:city":"Hasselt",
    "sg:classifiers":[
        {
            "category":"Retail",
            "subcategory":"Laundry & Dry Cleaning",
            "type":"Services"
        }
    ],
    "sg:phone":"+32 11 22 94 55",
    "sg:postcode":"3500",
    "sg:province":"Limburg",
    "sg:tags":[
        "dyer",
        "cleaner"
    ],
    "wof:name":"Prima Pressing",
    "wof:placetype":"venue"
},
  "geometry": {"coordinates":[5.3328437805,50.9303588867],"type":"Point"}
}