{
  "type": "Feature",
  "properties": {
    "addr:full":"Rue De La Ferme D'en Haut 20 Profondeville Namur 5170",
    "addr:housenumber":"20",
    "addr:postcode":"5170",
    "addr:street":"Rue De La Ferme D'En Haut",
    "iso:country":"BE",
    "sg:address":"Rue De La Ferme D'en Haut 20",
    "sg:city":"Profondeville",
    "sg:classifiers":[
        {
            "category":"Health Services",
            "subcategory":"Doctor",
            "type":"Services"
        }
    ],
    "sg:phone":"+32 81 41 18 13",
    "sg:postcode":"5170",
    "sg:province":"Namur",
    "sg:tags":[
        "medicinephysicians",
        "surgeon"
    ],
    "wof:name":"Baily Jean-pierre",
    "wof:placetype":"venue"
},
  "geometry": {"coordinates":[4.8664879799,50.3491973877],"type":"Point"}
}