{
  "type": "Feature",
  "properties": {
    "iso:country":"BE",
    "sg:address":"Chauss\u00e9e De La Lib\u00e9ration 36",
    "sg:city":"Grez-doiceau",
    "sg:classifiers":[
        {
            "category":"Building & Trades",
            "subcategory":"Electrical",
            "type":"Services"
        }
    ],
    "sg:phone":"+32 10 84 32 19",
    "sg:postcode":"1390",
    "sg:province":"Brabant Wallon",
    "sg:tags":[
        "electric",
        "-",
        "housewiring",
        "contractor"
    ],
    "wof:name":"Madoe R",
    "wof:placetype":"venue"
},
  "geometry": {"coordinates":[4.6919460297,50.7398338318],"type":"Point"}
}