{
  "type": "Feature",
  "properties": {
    "iso:country":"BE",
    "sg:address":"Kapelstraat 5",
    "sg:city":"Bilzen",
    "sg:orig_category":"Kapsalons",
    "sg:phone":"+32 89 41 31 59",
    "sg:postcode":"3740",
    "sg:province":"Limburg",
    "wof:name":"Coiffure Gilberte",
    "wof:placetype":"venue"
},
  "geometry": {"coordinates":[5.5095582008,50.8738708496],"type":"Point"}
}