{
  "type": "Feature",
  "properties": {
    "addr:full":"Place De L'h\u00f4tel De Ville 24 Ch\u00e2telet Hainaut 6200",
    "addr:housenumber":"24",
    "addr:postcode":"6200",
    "addr:street":"Place De L'Ho \u0302Tel De Ville",
    "iso:country":"BE",
    "sg:address":"Place De L'h\u00f4tel De Ville 24",
    "sg:city":"Ch\u00e2telet",
    "sg:classifiers":[
        {
            "category":"Insurance",
            "subcategory":"Insurance Agent",
            "type":"Services"
        }
    ],
    "sg:phone":"+32 71 39 58 85",
    "sg:postcode":"6200",
    "sg:province":"Hainaut",
    "sg:tags":[
        "broker"
    ],
    "wof:name":"Vaes J P",
    "wof:placetype":"venue"
},
  "geometry": {"coordinates":[7.2359681129,48.3391647339],"type":"Point"}
}