{
  "type": "Feature",
  "properties": {
    "addr:full":"Wissenstraat 9 Dendermonde (sint-gillis-bij-dendermonde) Oost-Vlaanderen 9200",
    "addr:housenumber":"9",
    "addr:postcode":"9200",
    "addr:street":"Wissenstraat",
    "iso:country":"BE",
    "sg:address":"Wissenstraat 9",
    "sg:city":"Dendermonde (sint-gillis-bij-dendermonde)",
    "sg:classifiers":[
        {
            "category":"Airport",
            "subcategory":"International",
            "type":"Transportation"
        }
    ],
    "sg:phone":"+32 52 25 00 52",
    "sg:postcode":"9200",
    "sg:province":"Oost-Vlaanderen",
    "sg:tags":[
        "-",
        "transport"
    ],
    "wof:name":"Van Lokeren Transport Nv",
    "wof:placetype":"venue"
},
  "geometry": {"coordinates":[4.1449790001,51.0286560059],"type":"Point"}
}