{
  "type": "Feature",
  "properties": {
    "addr:full":"Bp 9 Arlon Luxembourg 6700",
    "addr:housenumber":"9",
    "addr:postcode":"6700",
    "iso:country":"BE",
    "sg:address":"Bp 9",
    "sg:city":"Arlon",
    "sg:orig_category":"Diverse organisaties and verenigingen",
    "sg:phone":"+32 61 31 48 72",
    "sg:postcode":"6700",
    "sg:province":"Luxembourg",
    "wof:name":"Agc - Naturlux",
    "wof:placetype":"venue"
},
  "geometry": {"coordinates":[5.8126749992,49.6823234558],"type":"Point"}
}