{
  "type": "Feature",
  "properties": {
    "iso:country":"BE",
    "sg:address":"Kastanjestraat 13",
    "sg:city":"Westerlo",
    "sg:classifiers":[
        {
            "category":"Food & Beverages",
            "subcategory":"Fruits & Vegetables",
            "type":"Retail Goods"
        }
    ],
    "sg:phone":"+32 14 26 47 83",
    "sg:postcode":"2260",
    "sg:province":"Antwerpen",
    "sg:tags":[
        "groenten"
    ],
    "wof:name":"De Gele Citroen",
    "wof:placetype":"venue"
},
  "geometry": {"coordinates":[4.9112768173,51.0883636475],"type":"Point"}
}