{
  "type": "Feature",
  "properties": {
    "iso:country":"BE",
    "sg:address":"Molenbergstraat 19",
    "sg:city":"Rumst",
    "sg:orig_category":"Pharmaciens",
    "sg:phone":"+32 3 844 20 07",
    "sg:postcode":"2840",
    "sg:province":"Antwerpen",
    "wof:name":"Fa. Tobback",
    "wof:placetype":"venue"
},
  "geometry": {"coordinates":[4.4232602119,51.0781402588],"type":"Point"}
}