{
  "type": "Feature",
  "properties": {
    "iso:country":"BE",
    "sg:address":"Rue Dr. Coff\u00c9 0",
    "sg:city":"La Louvi\u00c8re",
    "sg:orig_category":"Cr\u00e8ches and garderies d'enfants",
    "sg:phone":"+32 64 66 55 13",
    "sg:postcode":"7110",
    "sg:province":"Hainaut",
    "wof:name":"Cr\u00c8che Communale",
    "wof:placetype":"venue"
},
  "geometry": {"coordinates":[4.1505050659,50.4826698303],"type":"Point"}
}