{
  "type": "Feature",
  "properties": {
    "addr:full":"Rue De Dinant 36 Beauraing Namur 5570",
    "addr:housenumber":"36",
    "addr:postcode":"5570",
    "addr:street":"Rue De Dinant",
    "iso:country":"BE",
    "sg:address":"Rue De Dinant 36",
    "sg:city":"Beauraing",
    "sg:classifiers":[
        {
            "category":"Cafe",
            "type":"Food & Drink"
        }
    ],
    "sg:phone":"+32 82 71 13 84",
    "sg:postcode":"5570",
    "sg:province":"Namur",
    "sg:tags":[
        "caf\u00e9s"
    ],
    "wof:name":"Jean-luc Linaer",
    "wof:placetype":"venue"
},
  "geometry": {"coordinates":[4.9555630684,50.1120414734],"type":"Point"}
}