{
  "type": "Feature",
  "properties": {
    "addr:full":"Rue J F Kennedy 28 Welkenraedt Li\u00e8ge 4840",
    "addr:housenumber":"28",
    "addr:postcode":"4840",
    "addr:street":"Rue J F Kennedy",
    "iso:country":"BE",
    "sg:address":"Rue J F Kennedy 28",
    "sg:city":"Welkenraedt",
    "sg:orig_category":"Transports routiers de marchandises",
    "sg:phone":"+32 87 88 28 38",
    "sg:postcode":"4840",
    "sg:province":"Li\u00e8ge",
    "wof:name":"Steinbeck A Transports",
    "wof:placetype":"venue"
},
  "geometry": {"coordinates":[5.9641008377,50.6625099182],"type":"Point"}
}