{
  "type": "Feature",
  "properties": {
    "iso:country":"BE",
    "sg:address":"Rue De Ho\u00fbssoi 302e",
    "sg:city":"Andenne (vezin)",
    "sg:classifiers":[
        {
            "category":"Home & Garden",
            "subcategory":"Carpets & Floor Coverings",
            "type":"Retail Goods"
        }
    ],
    "sg:phone":"+32 81 58 08 34",
    "sg:postcode":"5300",
    "sg:province":"Namur",
    "sg:tags":[
        "armoring"
    ],
    "wof:name":"Braggion & Fils Sprl",
    "wof:placetype":"venue"
},
  "geometry": {"coordinates":[5.0982642174,50.4863739014],"type":"Point"}
}