{
  "type": "Feature",
  "properties": {
    "addr:full":"Bree\u00ebrsteenweg 324 Kinrooi Limburg 3640",
    "addr:housenumber":"324",
    "addr:postcode":"3640",
    "addr:street":"Breee\u0308Rsteenweg",
    "iso:country":"BE",
    "sg:address":"Bree\u00ebrsteenweg 324",
    "sg:city":"Kinrooi",
    "sg:classifiers":[
        {
            "category":"Building & Trades",
            "subcategory":"Pest Control",
            "type":"Services"
        }
    ],
    "sg:phone":"+32 89 70 22 72",
    "sg:postcode":"3640",
    "sg:province":"Limburg",
    "sg:tags":[
        "painting",
        "contractor"
    ],
    "wof:name":"Peerlings S",
    "wof:placetype":"venue"
},
  "geometry": {"coordinates":[5.7346968651,51.1457519531],"type":"Point"}
}