{
  "type": "Feature",
  "properties": {
    "iso:country":"BE",
    "sg:address":"Blekenberg 95",
    "sg:city":"Wuustwezel",
    "sg:classifiers":[
        {
            "category":"Parking",
            "subcategory":"Lot",
            "type":"Transportation"
        }
    ],
    "sg:phone":"+32 3 669 68 25",
    "sg:postcode":"2990",
    "sg:province":"Antwerpen",
    "sg:tags":[
        "armoured",
        "door",
        "fireproof"
    ],
    "wof:name":"Mattheeusen",
    "wof:placetype":"venue"
},
  "geometry": {"coordinates":[4.5624518394,51.3846092224],"type":"Point"}
}