{
  "type": "Feature",
  "properties": {
    "addr:full":"Rozenberg 149 Mol Antwerpen 2400",
    "addr:housenumber":"149",
    "addr:postcode":"2400",
    "addr:street":"Rozenberg",
    "iso:country":"BE",
    "sg:address":"Rozenberg 149",
    "sg:city":"Mol",
    "sg:orig_category":"M\u00e9decins and sp\u00e9cialistes",
    "sg:phone":"+32 14 31 99 41",
    "sg:postcode":"2400",
    "sg:province":"Antwerpen",
    "wof:name":"Marc Smets",
    "wof:placetype":"venue"
},
  "geometry": {"coordinates":[5.1209959984,51.1885528564],"type":"Point"}
}