{
  "type": "Feature",
  "properties": {
    "addr:full":"Leopold 3 Laan 126 Brugge (groot) West-Vlaanderen 8200",
    "addr:housenumber":"126",
    "addr:postcode":"8200",
    "addr:street":"Leopold 3 Laan;Groot West-Vlaanderen",
    "iso:country":"BE",
    "sg:address":"Leopold 3 Laan 126",
    "sg:city":"Brugge (groot)",
    "sg:orig_category":"V\u00eatements, chaussures and accessoires Imprimeries and copyshops. V\u00eatements",
    "sg:phone":"+32 50 38 87 86",
    "sg:postcode":"8200",
    "sg:province":"West-Vlaanderen",
    "wof:name":"Valskin",
    "wof:placetype":"venue"
},
  "geometry": {"coordinates":[3.1883189678,51.1889648438],"type":"Point"}
}