{
  "type": "Feature",
  "properties": {
    "addr:full":"Begijnhofstraat 20 Deinze Oost-Vlaanderen 9800",
    "addr:housenumber":"20",
    "addr:postcode":"9800",
    "addr:street":"Begijnhofstraat",
    "iso:country":"BE",
    "sg:address":"Begijnhofstraat 20",
    "sg:city":"Deinze",
    "sg:orig_category":"Diverse opleidingen and onderwijs",
    "sg:phone":"+32 9 380 36 04",
    "sg:postcode":"9800",
    "sg:province":"Oost-Vlaanderen",
    "wof:name":"Fa. Dolphin Systems",
    "wof:placetype":"venue"
},
  "geometry": {"coordinates":[3.530174017,50.9863166809],"type":"Point"}
}