{
  "type": "Feature",
  "properties": {
    "addr:full":"Hondsstraat 6 Olen Antwerpen 2250",
    "addr:housenumber":"6",
    "addr:postcode":"2250",
    "addr:street":"Hondsstraat",
    "iso:country":"BE",
    "sg:address":"Hondsstraat 6",
    "sg:city":"Olen",
    "sg:classifiers":[
        {
            "category":"Building & Trades",
            "subcategory":"Construction",
            "type":"Services"
        }
    ],
    "sg:phone":"+32 14 21 92 27",
    "sg:postcode":"2250",
    "sg:province":"Antwerpen",
    "sg:tags":[
        "carpenter"
    ],
    "wof:name":"Van Geel L",
    "wof:placetype":"venue"
},
  "geometry": {"coordinates":[4.9003667831,51.173915863],"type":"Point"}
}