{
  "type": "Feature",
  "properties": {
    "addr:full":"Roeselarestraat 156 Ledegem (rollegem Kapelle) West-Vlaanderen 8880",
    "addr:housenumber":"156",
    "addr:postcode":"8880",
    "addr:street":"Roeselarestraat",
    "iso:country":"BE",
    "sg:address":"Roeselarestraat 156",
    "sg:city":"Ledegem (rollegem Kapelle)",
    "sg:classifiers":[
        {
            "category":"Retail",
            "subcategory":"Animal Services",
            "type":"Services"
        }
    ],
    "sg:phone":"+32 56 50 05 84",
    "sg:postcode":"8880",
    "sg:province":"West-Vlaanderen",
    "sg:tags":[
        "breeding",
        "selling",
        "-",
        "dog"
    ],
    "wof:name":"De Berkenhoeve/ Cokelaere Eric",
    "wof:placetype":"venue"
},
  "geometry": {"coordinates":[3.1496589184,50.8859863281],"type":"Point"}
}