{
  "type": "Feature",
  "properties": {
    "iso:country":"BE",
    "sg:address":"Wijnveld 290",
    "sg:city":"Sint-niklaas",
    "sg:orig_category":"Slagers",
    "sg:phone":"+32 3 772 12 35",
    "sg:postcode":"9112",
    "sg:province":"Oost-Vlaanderen",
    "wof:name":"Gilbert Fonteyne",
    "wof:placetype":"venue"
},
  "geometry": {"coordinates":[4.065513134,51.1437225342],"type":"Point"}
}