{
  "type": "Feature",
  "properties": {
    "iso:country":"BE",
    "sg:address":"Chauss\u00e9e De Waterloo 1324",
    "sg:city":"Bruxelles (uccle)",
    "sg:classifiers":[
        {
            "category":"Retail",
            "subcategory":"Event Space",
            "type":"Services"
        }
    ],
    "sg:phone":"+32 2 375 25 31",
    "sg:postcode":"1180",
    "sg:province":"Bruxelles-Capitale",
    "sg:tags":[
        "dinner",
        "set",
        "-",
        "cutlery"
    ],
    "wof:name":"Buss",
    "wof:placetype":"venue"
},
  "geometry": {"coordinates":[4.3750710487,50.7906455994],"type":"Point"}
}