{
  "type": "Feature",
  "properties": {
    "iso:country":"BE",
    "sg:address":"Kleitkalseidestraat 4b",
    "sg:city":"Maldegem",
    "sg:orig_category":"Beautyfarms, relaxatie and lichamelijk welzijn Schoonheidssalons",
    "sg:phone":"+32 50 71 49 42",
    "sg:postcode":"9990",
    "sg:province":"Oost-Vlaanderen",
    "wof:name":"Instituut Mieke",
    "wof:placetype":"venue"
},
  "geometry": {"coordinates":[3.4541919231,51.1928291321],"type":"Point"}
}