{
  "type": "Feature",
  "properties": {
    "addr:full":"Hoogveld 62 Dendermonde (sint-gillis-bij-dendermonde) Oost-Vlaanderen 9200",
    "addr:housenumber":"62",
    "addr:postcode":"9200",
    "addr:street":"Hoogveld",
    "iso:country":"BE",
    "sg:address":"Hoogveld 62",
    "sg:city":"Dendermonde (sint-gillis-bij-dendermonde)",
    "sg:classifiers":[
        {
            "category":"Retail",
            "subcategory":"Auto Repair",
            "type":"Services"
        }
    ],
    "sg:phone":"+32 52 21 23 72",
    "sg:postcode":"9200",
    "sg:province":"Oost-Vlaanderen",
    "sg:tags":[
        "garage"
    ],
    "wof:name":"Modern Trucks Nv",
    "wof:placetype":"venue"
},
  "geometry": {"coordinates":[4.1433010101,51.0239677429],"type":"Point"}
}