{
  "type": "Feature",
  "properties": {
    "iso:country":"BE",
    "sg:address":"Rostijne 9",
    "sg:city":"Zelzate",
    "sg:orig_category":"V\u00e9hicules automobiles. Entretien and r\u00e9parations de voitures",
    "sg:phone":"+32 9 342 97 77",
    "sg:postcode":"9060",
    "sg:province":"Oost-Vlaanderen",
    "wof:name":"Garage Baele",
    "wof:placetype":"venue"
},
  "geometry": {"coordinates":[3.8146300316,51.1975364685],"type":"Point"}
}