{
  "type": "Feature",
  "properties": {
    "iso:country":"BE",
    "sg:address":"Rue Restaumont 0",
    "sg:city":"Ecaussinnes",
    "sg:orig_category":"Rev\u00eatements de sols and murs",
    "sg:phone":"+32 67 44 30 40",
    "sg:postcode":"7190",
    "sg:province":"Hainaut",
    "wof:name":"Fayt Fr\u00c8res",
    "wof:placetype":"venue"
},
  "geometry": {"coordinates":[4.1424689293,50.5620117188],"type":"Point"}
}