{
  "type": "Feature",
  "properties": {
    "addr:full":"Sint-antoniusstraat 56 Anzegem West-Vlaanderen 8570",
    "addr:housenumber":"56",
    "addr:postcode":"8570",
    "addr:street":"Sint-Antoniusstraat",
    "iso:country":"BE",
    "sg:address":"Sint-antoniusstraat 56",
    "sg:city":"Anzegem",
    "sg:orig_category":"Kinderopvang",
    "sg:phone":"+32 56 77 81 14",
    "sg:postcode":"8570",
    "sg:province":"West-Vlaanderen",
    "wof:name":"M. Heyse",
    "wof:placetype":"venue"
},
  "geometry": {"coordinates":[3.4355170727,50.8209838867],"type":"Point"}
}