{
  "type": "Feature",
  "properties": {
    "addr:full":"Onderwijslaan 4 Diepenbeek Limburg 3590",
    "addr:housenumber":"4",
    "addr:postcode":"3590",
    "addr:street":"Onderwijslaan",
    "iso:country":"BE",
    "sg:address":"Onderwijslaan 4",
    "sg:city":"Diepenbeek",
    "sg:orig_category":"Jardinage. Construction de rev\u00eatements and voies d'acc\u00e8s r\u00e9sidentiels",
    "sg:phone":"+32 11 32 15 53",
    "sg:postcode":"3590",
    "sg:province":"Limburg",
    "wof:name":"Jan Bynens",
    "wof:placetype":"venue"
},
  "geometry": {"coordinates":[5.4502739906,50.9220809937],"type":"Point"}
}