{
  "type": "Feature",
  "properties": {
    "addr:full":"Universiteitslaan 0 Diepenbeek Limburg 3590",
    "addr:housenumber":"0",
    "addr:postcode":"3590",
    "addr:street":"Universiteitslaan",
    "iso:country":"BE",
    "sg:address":"Universiteitslaan 0",
    "sg:city":"Diepenbeek",
    "sg:orig_category":"Microsoft. Librairies. Fournitures de bureau",
    "sg:phone":"+32 11 23 36 03",
    "sg:postcode":"3590",
    "sg:province":"Limburg",
    "wof:name":"Standaard Boekhandel Diepenbeek",
    "wof:placetype":"venue"
},
  "geometry": {"coordinates":[5.3945360184,50.9326133728],"type":"Point"}
}