{
  "type": "Feature",
  "properties": {
    "addr:full":"Molenstraat 65 Keerbergen Vlaams-Brabant 3140",
    "addr:housenumber":"65",
    "addr:postcode":"3140",
    "addr:street":"Molenstraat",
    "iso:country":"BE",
    "sg:address":"Molenstraat 65",
    "sg:city":"Keerbergen",
    "sg:orig_category":"Produits surgel\u00e9s Gr",
    "sg:phone":"+32 15 52 91 66",
    "sg:postcode":"3140",
    "sg:province":"Vlaams-Brabant",
    "wof:name":"Verbiest A.-storm D.",
    "wof:placetype":"venue"
},
  "geometry": {"coordinates":[4.6454639435,51.0082778931],"type":"Point"}
}