{
  "type": "Feature",
  "properties": {
    "addr:full":"Rue Tout Y Faut 24 La Louvi\u00e8re (houdeng-goegnies) Hainaut 7110",
    "addr:housenumber":"24",
    "addr:postcode":"7110",
    "addr:street":"Rue Tout Y Faut",
    "iso:country":"BE",
    "sg:address":"Rue Tout Y Faut 24",
    "sg:city":"La Louvi\u00e8re (houdeng-goegnies)",
    "sg:classifiers":[
        {
            "category":"Personal",
            "subcategory":"Psychics & Astrologers",
            "type":"Services"
        }
    ],
    "sg:phone":"+32 64 21 10 92",
    "sg:postcode":"7110",
    "sg:province":"Hainaut",
    "sg:tags":[
        "astrology"
    ],
    "wof:name":"Du\u00e7au",
    "wof:placetype":"venue"
},
  "geometry": {"coordinates":[4.1505050659,50.4826698303],"type":"Point"}
}