{
  "type": "Feature",
  "properties": {
    "addr:full":"Bredabaan 282 Brasschaat Antwerpen 2930",
    "addr:housenumber":"282",
    "addr:postcode":"2930",
    "addr:street":"Bredabaan",
    "iso:country":"BE",
    "sg:address":"Bredabaan 282",
    "sg:city":"Brasschaat",
    "sg:orig_category":"Banken and kredietinstellingen",
    "sg:phone":"+32 3 651 80 96",
    "sg:postcode":"2930",
    "sg:province":"Antwerpen",
    "wof:name":"Nuyens-seghers",
    "wof:placetype":"venue"
},
  "geometry": {"coordinates":[4.4921240807,51.2906188965],"type":"Point"}
}