{
  "type": "Feature",
  "properties": {
    "iso:country":"BE",
    "sg:address":"Van Ertbornstraat 8",
    "sg:city":"Antwerpen",
    "sg:classifiers":[
        {
            "category":"Arts & Performance",
            "subcategory":"Theater",
            "type":"Entertainment"
        }
    ],
    "sg:phone":"+32 3 202 10 11",
    "sg:postcode":"2018",
    "sg:province":"Antwerpen",
    "sg:tags":[
        "concert-halls",
        "theatre"
    ],
    "wof:name":"Vlaamse Opera (de)",
    "wof:placetype":"venue"
},
  "geometry": {"coordinates":[4.4167919159,51.2184333801],"type":"Point"}
}