{
  "type": "Feature",
  "properties": {
    "addr:full":"Chauss\u00c9e De Brunehault 475 Herstal Li\u00e8ge 4041",
    "addr:housenumber":"475",
    "addr:postcode":"4041",
    "addr:street":"Chausse\u0301E De Brunehault",
    "iso:country":"BE",
    "sg:address":"Chauss\u00c9e De Brunehault 475",
    "sg:city":"Herstal",
    "sg:orig_category":"Rusthuizen and serviceflats",
    "sg:phone":"+32 4 227 82 16",
    "sg:postcode":"4041",
    "sg:province":"Li\u00e8ge",
    "wof:name":"Domaine Des Aliz\u00c9s",
    "wof:placetype":"venue"
},
  "geometry": {"coordinates":[5.5828299522,50.6791114807],"type":"Point"}
}