{
  "type": "Feature",
  "properties": {
    "addr:full":"Sint-maurusweg 37 Tienen Vlaams-Brabant 3300",
    "addr:housenumber":"37",
    "addr:postcode":"3300",
    "addr:street":"Sint-Maurusweg",
    "iso:country":"BE",
    "sg:address":"Sint-maurusweg 37",
    "sg:city":"Tienen",
    "sg:orig_category":"Diepvriesproducten Gh",
    "sg:phone":"+32 16 76 67 45",
    "sg:postcode":"3300",
    "sg:province":"Vlaams-Brabant",
    "wof:name":"Supefra",
    "wof:placetype":"venue"
},
  "geometry": {"coordinates":[4.9567818642,50.7958831787],"type":"Point"}
}