{
  "type": "Feature",
  "properties": {
    "addr:full":"Corceliusstraat 7b4 Beringen Limburg 3582",
    "addr:housenumber":"7b4",
    "addr:postcode":"3582",
    "addr:street":"Corceliusstraat",
    "iso:country":"BE",
    "sg:address":"Corceliusstraat 7b4",
    "sg:city":"Beringen",
    "sg:orig_category":"Installation \u00e9lectrique r\u00e9sidentielle",
    "sg:phone":"+32 11 42 98 19",
    "sg:postcode":"3582",
    "sg:province":"Limburg",
    "wof:name":"Andre Demulder",
    "wof:placetype":"venue"
},
  "geometry": {"coordinates":[5.2708749771,51.0595359802],"type":"Point"}
}