{
  "type": "Feature",
  "properties": {
    "addr:full":"Schutterijstraat 19 Box 3 Deinze Oost-Vlaanderen 9800",
    "addr:housenumber":"19;3",
    "addr:postcode":"9800",
    "addr:street":"Schutterijstraat;Box",
    "iso:country":"BE",
    "sg:address":"Schutterijstraat 19 Box 3",
    "sg:city":"Deinze",
    "sg:classifiers":[
        {
            "category":"Food & Beverages",
            "subcategory":"Candy",
            "type":"Retail Goods"
        }
    ],
    "sg:phone":"+32 9 386 08 90",
    "sg:postcode":"9800",
    "sg:province":"Oost-Vlaanderen",
    "wof:name":"Aphrodite",
    "wof:placetype":"venue"
},
  "geometry": {"coordinates":[3.5291171074,50.9867668152],"type":"Point"}
}