{
  "type": "Feature",
  "properties": {
    "iso:country":"BE",
    "sg:address":"Weg Naar As 90",
    "sg:city":"Genk",
    "sg:classifiers":[
        {
            "category":"Health Services",
            "subcategory":"Dentist",
            "type":"Services"
        }
    ],
    "sg:phone":"+32 89 36 24 14",
    "sg:postcode":"3600",
    "sg:province":"Limburg",
    "wof:name":"Janssen M",
    "wof:placetype":"venue"
},
  "geometry": {"coordinates":[5.5114941597,50.9696502686],"type":"Point"}
}