{
  "type": "Feature",
  "properties": {
    "addr:full":"Rue Du Wainage 100 Fleurus (lambusart) Hainaut 6220",
    "addr:housenumber":"100",
    "addr:postcode":"6220",
    "addr:street":"Rue Du Wainage",
    "iso:country":"BE",
    "sg:address":"Rue Du Wainage 100",
    "sg:city":"Fleurus (lambusart)",
    "sg:classifiers":[
        {
            "category":"Health Services",
            "subcategory":"Health Practitioner",
            "type":"Services"
        }
    ],
    "sg:phone":"+32 71 81 46 04",
    "sg:postcode":"6220",
    "sg:province":"Hainaut",
    "sg:tags":[
        "physiotherapist"
    ],
    "wof:name":"Moreau J",
    "wof:placetype":"venue"
},
  "geometry": {"coordinates":[4.5510110855,50.4533462524],"type":"Point"}
}