{
  "type": "Feature",
  "properties": {
    "addr:full":"Rue De L'oiseau Du Bois 6 Modave Li\u00e8ge 4577",
    "addr:housenumber":"6",
    "addr:postcode":"4577",
    "addr:street":"Rue De L'Oiseau Du Bois",
    "iso:country":"BE",
    "sg:address":"Rue De L'oiseau Du Bois 6",
    "sg:city":"Modave",
    "sg:orig_category":"Landmeters",
    "sg:phone":"+32 85 51 25 27",
    "sg:postcode":"4577",
    "sg:province":"Li\u00e8ge",
    "wof:name":"Emile Detaille",
    "wof:placetype":"venue"
},
  "geometry": {"coordinates":[5.2999367714,50.4951477051],"type":"Point"}
}