{
  "type": "Feature",
  "properties": {
    "iso:country":"BE",
    "sg:address":"Rue De La Fontaine Des Gattes 33",
    "sg:city":"Genappe (bousval)",
    "sg:classifiers":[
        {
            "category":"Home & Garden",
            "subcategory":"Home Furnishings",
            "type":"Retail Goods"
        }
    ],
    "sg:phone":"+32 10 61 28 33",
    "sg:postcode":"1470",
    "sg:province":"Brabant Wallon",
    "sg:tags":[
        "interior",
        "decoration"
    ],
    "wof:name":"Moerenhout M",
    "wof:placetype":"venue"
},
  "geometry": {"coordinates":[4.5279941559,50.6338043213],"type":"Point"}
}