{
  "type": "Feature",
  "properties": {
    "addr:full":"Nachtegalenlaan 28 Kortenberg Vlaams-Brabant 3078",
    "addr:housenumber":"28",
    "addr:postcode":"3078",
    "addr:street":"Nachtegalenlaan;Vlaams-Brabant",
    "iso:country":"BE",
    "sg:address":"Nachtegalenlaan 28",
    "sg:city":"Kortenberg",
    "sg:orig_category":"M\u00e9decins and sp\u00e9cialistes",
    "sg:phone":"+32 2 759 42 11",
    "sg:postcode":"3078",
    "sg:province":"Vlaams-Brabant",
    "wof:name":"K. Sabouni",
    "wof:placetype":"venue"
},
  "geometry": {"coordinates":[4.53937006,50.8719825745],"type":"Point"}
}