{
  "type": "Feature",
  "properties": {
    "iso:country":"BE",
    "sg:address":"J. Bryndonckxstr 18",
    "sg:city":"Wemmel",
    "sg:classifiers":[
        {
            "category":"Professional",
            "subcategory":"Engineering",
            "type":"Services"
        }
    ],
    "sg:phone":"+32 2 460 33 18",
    "sg:postcode":"1780",
    "sg:province":"Vlaams-Brabant",
    "sg:tags":[
        "machine",
        "-",
        "mechanical"
    ],
    "wof:name":"Edouard Defrance Sprl",
    "wof:placetype":"venue"
},
  "geometry": {"coordinates":[4.3003411293,50.9068717957],"type":"Point"}
}