{
  "type": "Feature",
  "properties": {
    "iso:country":"BE",
    "sg:address":"Wegvoeringsstr 111",
    "sg:city":"St-niklaas",
    "sg:classifiers":[
        {
            "category":"Manufacturing",
            "subcategory":"Textiles",
            "type":"Manufacturing & Wholesale Goods"
        }
    ],
    "sg:phone":"+32 3 777 29 47",
    "sg:postcode":"9100",
    "sg:province":"Oost-Vlaanderen",
    "sg:tags":[
        "clothing",
        "accessory"
    ],
    "wof:name":"Textiel Troch Nv",
    "wof:placetype":"venue"
},
  "geometry": {"coordinates":[4.1299161911,51.1729049683],"type":"Point"}
}