{
  "type": "Feature",
  "properties": {
    "iso:country":"BE",
    "sg:address":"Rue De Roubaix 3",
    "sg:city":"Tournai",
    "sg:orig_category":"Banken and kredietinstellingen",
    "sg:phone":"+32 69 35 22 86",
    "sg:postcode":"7520",
    "sg:province":"Hainaut",
    "wof:name":"Bbl",
    "wof:placetype":"venue"
},
  "geometry": {"coordinates":[3.2826490402,50.6445846558],"type":"Point"}
}