{
  "type": "Feature",
  "properties": {
    "addr:full":"Maastrichterstraat 48 Bilzen Limburg 3740",
    "addr:housenumber":"48",
    "addr:postcode":"3740",
    "addr:street":"Maastrichterstraat",
    "iso:country":"BE",
    "sg:address":"Maastrichterstraat 48",
    "sg:city":"Bilzen",
    "sg:orig_category":"Installation \u00e9lectrique r\u00e9sidentielle. Eclairage et \u00e9quipements du foyer. Jardinage",
    "sg:phone":"+32 89 51 01 11",
    "sg:postcode":"3740",
    "sg:province":"Limburg",
    "wof:name":"Vangronsveld",
    "wof:placetype":"venue"
},
  "geometry": {"coordinates":[5.5304141045,50.8644180298],"type":"Point"}
}