{
  "type": "Feature",
  "properties": {
    "addr:full":"Grand'rue 21 Cerfontaine (daussois) Namur 5630",
    "addr:housenumber":"21",
    "addr:postcode":"5630",
    "addr:street":"Grand'Rue",
    "iso:country":"BE",
    "sg:address":"Grand'rue 21",
    "sg:city":"Cerfontaine (daussois)",
    "sg:classifiers":[
        {
            "category":"Health Services",
            "subcategory":"Nursing And Care Facility",
            "type":"Services"
        }
    ],
    "sg:phone":"+32 71 61 38 50",
    "sg:postcode":"5630",
    "sg:province":"Namur",
    "sg:tags":[
        "home"
    ],
    "wof:name":"Burton C",
    "wof:placetype":"venue"
},
  "geometry": {"coordinates":[4.4817800522,50.1895446777],"type":"Point"}
}