{
  "type": "Feature",
  "properties": {
    "iso:country":"BE",
    "sg:address":"Spilstraat 1",
    "sg:city":"Maaseik",
    "sg:orig_category":"Equipement photographique. Studios photographiques",
    "sg:phone":"+32 89 86 41 93",
    "sg:postcode":"3680",
    "sg:province":"Limburg",
    "wof:name":"Eric Vliegen",
    "wof:placetype":"venue"
},
  "geometry": {"coordinates":[5.791285038,51.0954208374],"type":"Point"}
}