{
  "type": "Feature",
  "properties": {
    "addr:full":"Kapelstraat 10 Bus38 Opglabbeek Limburg 3660",
    "addr:housenumber":"10",
    "addr:postcode":"3660",
    "addr:street":"Kapelstraat",
    "iso:country":"BE",
    "sg:address":"Kapelstraat 10 Bus38",
    "sg:city":"Opglabbeek",
    "sg:orig_category":"Biblioth\u00e8ques and archives publiques",
    "sg:phone":"+32 89 81 01 32",
    "sg:postcode":"3660",
    "sg:province":"Limburg",
    "wof:name":"Openbare Bibliotheek",
    "wof:placetype":"venue"
},
  "geometry": {"coordinates":[5.5838198662,51.0429496765],"type":"Point"}
}