{
  "type": "Feature",
  "properties": {
    "addr:full":"Rue Des Moulins 9-11 Awans (hognoul) Li\u00e8ge 4342",
    "addr:housenumber":"9-11",
    "addr:postcode":"4342",
    "addr:street":"Rue Des Moulins",
    "iso:country":"BE",
    "sg:address":"Rue Des Moulins 9-11",
    "sg:city":"Awans (hognoul)",
    "sg:classifiers":[
        {
            "category":"Bars & Pubs",
            "type":"Food & Drink"
        }
    ],
    "sg:phone":"+32 4 257 57 21",
    "sg:postcode":"4342",
    "sg:province":"Li\u00e8ge",
    "sg:tags":[
        "tavern"
    ],
    "wof:name":"Hognoul I",
    "wof:placetype":"venue"
},
  "geometry": {"coordinates":[5.4653577805,50.6832389832],"type":"Point"}
}