{
  "type": "Feature",
  "properties": {
    "iso:country":"BE",
    "sg:address":"Kolkstraat 64",
    "sg:city":"Sint-niklaas (nieuwkerken-waas)",
    "sg:classifiers":[
        {
            "category":"Home & Garden",
            "subcategory":"Kitchen Supply",
            "type":"Retail Goods"
        }
    ],
    "sg:phone":"+32 3 766 10 81",
    "sg:postcode":"9100",
    "sg:province":"Oost-Vlaanderen",
    "sg:tags":[
        "installation"
    ],
    "wof:name":"De Maere Interieurinrichting",
    "wof:placetype":"venue"
},
  "geometry": {"coordinates":[4.1838831902,51.2016334534],"type":"Point"}
}