{
  "type": "Feature",
  "properties": {
    "addr:full":"Grand Place 11 Hannut Li\u00e8ge 4280",
    "addr:housenumber":"11",
    "addr:postcode":"4280",
    "addr:street":"Grand Place",
    "iso:country":"BE",
    "sg:address":"Grand Place 11",
    "sg:city":"Hannut",
    "sg:classifiers":[
        {
            "category":"Insurance",
            "subcategory":"Insurance Agent",
            "type":"Services"
        }
    ],
    "sg:phone":"+32 19 51 21 89",
    "sg:postcode":"4280",
    "sg:province":"Li\u00e8ge",
    "sg:tags":[
        "broker"
    ],
    "wof:name":"Houpresse Robert & Fils Sprl",
    "wof:placetype":"venue"
},
  "geometry": {"coordinates":[5.0776138306,50.6727142334],"type":"Point"}
}