{
  "type": "Feature",
  "properties": {
    "addr:full":"Sint-elooistraat 26 Lokeren Oost-Vlaanderen 9160",
    "addr:housenumber":"26",
    "addr:postcode":"9160",
    "addr:street":"Sint-Elooistraat",
    "iso:country":"BE",
    "sg:address":"Sint-elooistraat 26",
    "sg:city":"Lokeren",
    "sg:classifiers":[
        {
            "category":"Retail",
            "subcategory":"Auto Repair",
            "type":"Services"
        }
    ],
    "sg:phone":"+32 9 348 87 27",
    "sg:postcode":"9160",
    "sg:province":"Oost-Vlaanderen",
    "sg:tags":[
        "garage"
    ],
    "wof:name":"Serge (garage)",
    "wof:placetype":"venue"
},
  "geometry": {"coordinates":[4.0104498863,51.0896110535],"type":"Point"}
}