{
  "type": "Feature",
  "properties": {
    "addr:full":"Rue Sainte-walburge 63 Li\u00c8ge Li\u00e8ge 4000",
    "addr:housenumber":"63",
    "addr:postcode":"4000",
    "addr:street":"Rue Sainte-Walburge",
    "iso:country":"BE",
    "sg:address":"Rue Sainte-walburge 63",
    "sg:city":"Li\u00c8ge",
    "sg:classifiers":[
        {
            "category":"Food & Beverages",
            "subcategory":"Meat & Fish",
            "type":"Retail Goods"
        }
    ],
    "sg:phone":"+32 4 226 44 95",
    "sg:postcode":"4000",
    "sg:province":"Li\u00e8ge",
    "sg:tags":[
        "vi",
        "zeevruchten"
    ],
    "wof:name":"Chez Blanche",
    "wof:placetype":"venue"
},
  "geometry": {"coordinates":[5.5715532303,50.6557807922],"type":"Point"}
}