{
  "type": "Feature",
  "properties": {
    "iso:country":"BE",
    "sg:address":"Mechelbaan 119",
    "sg:city":"Lier (koningshooikt)",
    "sg:classifiers":[
        {
            "category":"Wholesale",
            "subcategory":"Machinery & Supplies",
            "type":"Manufacturing & Wholesale Goods"
        }
    ],
    "sg:phone":"+32 3 482 23 48",
    "sg:postcode":"2500",
    "sg:province":"Antwerpen",
    "sg:tags":[
        "refrigeration",
        "-",
        "industrial",
        "commercial",
        "equipment"
    ],
    "wof:name":"Clima Comfort",
    "wof:placetype":"venue"
},
  "geometry": {"coordinates":[4.6067810059,51.0884361267],"type":"Point"}
}