{
  "type": "Feature",
  "properties": {
    "iso:country":"BE",
    "sg:address":"Hamelendreef 70",
    "sg:city":"Tienen",
    "sg:classifiers":[
        {
            "category":"Train Station",
            "subcategory":"Rail",
            "type":"Transportation"
        }
    ],
    "sg:phone":"+32 16 82 36 09",
    "sg:postcode":"3300",
    "sg:province":"Vlaams-Brabant",
    "sg:tags":[
        "bulk",
        "good",
        "-",
        "transport"
    ],
    "wof:name":"Transport Saelens Bvba",
    "wof:placetype":"venue"
},
  "geometry": {"coordinates":[4.9541091919,50.807964325],"type":"Point"}
}