{
  "type": "Feature",
  "properties": {
    "addr:full":"Corthoutslaan 14 Lubbeek Vlaams-Brabant 3212",
    "addr:housenumber":"14",
    "addr:postcode":"3212",
    "addr:street":"Corthoutslaan",
    "iso:country":"BE",
    "sg:address":"Corthoutslaan 14",
    "sg:city":"Lubbeek",
    "sg:orig_category":"Dierentuinen, botanische tuinen, sterrenwachten and natuurreservaten",
    "sg:phone":"+32 16 46 27 87",
    "sg:postcode":"3212",
    "sg:province":"Vlaams-Brabant",
    "wof:name":"Spicht (lubbeek)",
    "wof:placetype":"venue"
},
  "geometry": {"coordinates":[4.7884898186,50.8745727539],"type":"Point"}
}