{
  "type": "Feature",
  "properties": {
    "iso:country":"BE",
    "sg:address":"Parijsstraat 6",
    "sg:city":"Leuven",
    "sg:orig_category":"Chaussures",
    "sg:phone":"+32 16 23 26 83",
    "sg:postcode":"3000",
    "sg:province":"Vlaams-Brabant",
    "wof:name":"Huis Gollem",
    "wof:placetype":"venue"
},
  "geometry": {"coordinates":[4.6994590759,50.8792152405],"type":"Point"}
}