{
  "type": "Feature",
  "properties": {
    "iso:country":"BE",
    "sg:address":"Schelkenshof 22",
    "sg:city":"Ranst",
    "sg:orig_category":"Travaux de pl\u00e2trage",
    "sg:phone":"+32 3 475 09 72",
    "sg:postcode":"2520",
    "sg:province":"Antwerpen",
    "wof:name":"Filip De Kock",
    "wof:placetype":"venue"
},
  "geometry": {"coordinates":[4.5980229378,51.1804122925],"type":"Point"}
}