{
  "type": "Feature",
  "properties": {
    "addr:full":"Kerkstraat 13 Destelbergen Oost-Vlaanderen 9070",
    "addr:housenumber":"13",
    "addr:postcode":"9070",
    "addr:street":"Kerkstraat",
    "iso:country":"BE",
    "sg:address":"Kerkstraat 13",
    "sg:city":"Destelbergen",
    "sg:classifiers":[
        {
            "category":"Professional",
            "subcategory":"Management & Consulting",
            "type":"Services"
        }
    ],
    "sg:phone":"+32 9 328 78 81",
    "sg:postcode":"9070",
    "sg:province":"Oost-Vlaanderen",
    "sg:tags":[
        "consultant"
    ],
    "wof:name":"Cemac",
    "wof:placetype":"venue"
},
  "geometry": {"coordinates":[3.7984509468,51.0566101074],"type":"Point"}
}