{
  "type": "Feature",
  "properties": {
    "addr:full":"Waverse Steenweg 633 Etterbeek/etterbeek Bruxelles-Capitale 1040",
    "addr:housenumber":"633",
    "addr:postcode":"1040",
    "addr:street":"Waverse Steenweg",
    "iso:country":"BE",
    "sg:address":"Waverse Steenweg 633",
    "sg:city":"Etterbeek/etterbeek",
    "sg:orig_category":"Zalen voor culturele evenementen",
    "sg:phone":"+32 2 646 96 93",
    "sg:postcode":"1040",
    "sg:province":"Bruxelles-Capitale",
    "wof:name":"Zirk Th\u00c9\u00c2tre",
    "wof:placetype":"venue"
},
  "geometry": {"coordinates":[4.3951997757,50.8335914612],"type":"Point"}
}