{
  "type": "Feature",
  "properties": {
    "iso:country":"BE",
    "sg:address":"Heiststeenweg 4",
    "sg:city":"Putte",
    "sg:orig_category":"Slagers",
    "sg:phone":"+32 15 75 51 15",
    "sg:postcode":"2580",
    "sg:province":"Antwerpen",
    "wof:name":"Slagerij Raf",
    "wof:placetype":"venue"
},
  "geometry": {"coordinates":[4.672524929,51.0574874878],"type":"Point"}
}