{
  "type": "Feature",
  "properties": {
    "addr:full":"Rue App\u00c2a 29 Colfontaine Hainaut 7340",
    "addr:housenumber":"29",
    "addr:postcode":"7340",
    "addr:street":"Rue Appa\u0302A",
    "iso:country":"BE",
    "sg:address":"Rue App\u00c2a 29",
    "sg:city":"Colfontaine",
    "sg:orig_category":"Traitements param\u00e9dicaux",
    "sg:phone":"+32 65 67 67 56",
    "sg:postcode":"7340",
    "sg:province":"Hainaut",
    "wof:name":"F. Cavenaile",
    "wof:placetype":"venue"
},
  "geometry": {"coordinates":[3.8467431068,50.4162025452],"type":"Point"}
}