{
  "type": "Feature",
  "properties": {
    "iso:country":"BE",
    "sg:address":"Rue De La Noblesse 7",
    "sg:city":"Rendeux",
    "sg:orig_category":"Installation de menuiserie en bois and plastique",
    "sg:phone":"+32 84 47 71 54",
    "sg:postcode":"6987",
    "sg:province":"Luxembourg",
    "wof:name":"Philippe Pierret",
    "wof:placetype":"venue"
},
  "geometry": {"coordinates":[5.4574961662,50.2098197937],"type":"Point"}
}