{
  "type": "Feature",
  "properties": {
    "iso:country":"BE",
    "sg:address":"Nijverh. Begijnenmeers 22",
    "sg:city":"Liedekerke",
    "sg:orig_category":"Diepvriesproducten Gh",
    "sg:phone":"+32 53 66 81 72",
    "sg:postcode":"1770",
    "sg:province":"Vlaams-Brabant",
    "wof:name":"Snacks Bosteels",
    "wof:placetype":"venue"
},
  "geometry": {"coordinates":[4.0881090164,50.8857574463],"type":"Point"}
}