{
  "type": "Feature",
  "properties": {
    "iso:country":"BE",
    "sg:address":"Otegemstraat 47",
    "sg:city":"Zwevegem",
    "sg:orig_category":"Pain, p\u00e2tisseries and confiseries",
    "sg:phone":"+32 56 75 55 05",
    "sg:postcode":"8550",
    "sg:province":"West-Vlaanderen",
    "wof:name":"Doopsuiker Dheygere",
    "wof:placetype":"venue"
},
  "geometry": {"coordinates":[3.3371009827,50.8130149841],"type":"Point"}
}