{
  "type": "Feature",
  "properties": {
    "addr:full":"Rue Saint-brice 21-26 Tournai Hainaut 7500",
    "addr:housenumber":"21-26",
    "addr:postcode":"7500",
    "addr:street":"Rue Saint-Brice",
    "iso:country":"BE",
    "sg:address":"Rue Saint-brice 21-26",
    "sg:city":"Tournai",
    "sg:classifiers":[
        {
            "category":"Building & Trades",
            "subcategory":"Locksmith",
            "type":"Services"
        }
    ],
    "sg:phone":"+32 475 34 17 66",
    "sg:postcode":"7500",
    "sg:province":"Hainaut",
    "sg:tags":[
        "lock",
        "key"
    ],
    "wof:name":"Bob Depannage Partout",
    "wof:placetype":"venue"
},
  "geometry": {"coordinates":[3.3916730881,50.6082954407],"type":"Point"}
}