{
  "type": "Feature",
  "properties": {
    "addr:full":"Chemin Des Espagnols 231 Arlon Luxembourg 6700",
    "addr:housenumber":"231",
    "addr:postcode":"6700",
    "addr:street":"Chemin Des Espagnols",
    "iso:country":"BE",
    "sg:address":"Chemin Des Espagnols 231",
    "sg:city":"Arlon",
    "sg:classifiers":[
        {
            "category":"Health Services",
            "subcategory":"Medical Lab",
            "type":"Services"
        }
    ],
    "sg:phone":"+32 63 22 33 22",
    "sg:postcode":"6700",
    "sg:province":"Luxembourg",
    "sg:tags":[
        "laboratory",
        "dental"
    ],
    "wof:name":"Protarl Sprl",
    "wof:placetype":"venue"
},
  "geometry": {"coordinates":[5.8257899284,49.6836242676],"type":"Point"}
}