{
  "type": "Feature",
  "properties": {
    "iso:country":"BE",
    "sg:address":"Avenue Moli\u00c8re 49",
    "sg:city":"Vorst/forest",
    "sg:orig_category":"Architectes",
    "sg:phone":"+32 2 345 18 17",
    "sg:postcode":"1190",
    "sg:province":"Bruxelles-Capitale",
    "wof:name":"Doog'm Design",
    "wof:placetype":"venue"
},
  "geometry": {"coordinates":[4.3417592049,50.8150024414],"type":"Point"}
}