{
  "type": "Feature",
  "properties": {
    "iso:country":"BE",
    "sg:address":"Rue Joseph-pirotte 47",
    "sg:city":"Li\u00e8ge 1 (rocourt)",
    "sg:classifiers":[
        {
            "category":"Home & Garden",
            "subcategory":"Carpets & Floor Coverings",
            "type":"Retail Goods"
        }
    ],
    "sg:phone":"+32 4 247 47 40",
    "sg:postcode":"4000",
    "sg:province":"Li\u00e8ge",
    "sg:tags":[
        "heating"
    ],
    "wof:name":"Dechesne M",
    "wof:placetype":"venue"
},
  "geometry": {"coordinates":[5.5476908684,50.6724319458],"type":"Point"}
}