{
  "type": "Feature",
  "properties": {
    "addr:full":"Rue Du Vieux-march\u00c9 31 Vielsalm Luxembourg 6690",
    "addr:housenumber":"31",
    "addr:postcode":"6690",
    "addr:street":"Rue Du Vieux-Marche\u0301",
    "iso:country":"BE",
    "sg:address":"Rue Du Vieux-march\u00c9 31",
    "sg:city":"Vielsalm",
    "sg:orig_category":"RESTAURANTS: LIVRAISON \u00c0 DOMICILE. CATERING AND ORGANISATION DE F\u00caTES. RESTAURANTS. ALIMENTATION SP\u00c9",
    "sg:phone":"+32 80 21 45 50",
    "sg:postcode":"6690",
    "sg:province":"Luxembourg",
    "wof:name":"Snack-bar-traiteur Chez Bobo",
    "wof:placetype":"venue"
},
  "geometry": {"coordinates":[5.9149899483,50.2844657898],"type":"Point"}
}