{
  "type": "Feature",
  "properties": {
    "iso:country":"BE",
    "sg:address":"Kerkwegel 39",
    "sg:city":"Wetteren",
    "sg:classifiers":[
        {
            "category":"Home & Garden",
            "subcategory":"Garden Supply",
            "type":"Retail Goods"
        }
    ],
    "sg:phone":"+32 9 369 13 81",
    "sg:postcode":"9230",
    "sg:province":"Oost-Vlaanderen",
    "sg:tags":[
        "machine",
        "agricultural",
        "-"
    ],
    "wof:name":"Bollaert P",
    "wof:placetype":"venue"
},
  "geometry": {"coordinates":[3.8860080242,51.0064659119],"type":"Point"}
}