{
  "type": "Feature",
  "properties": {
    "addr:full":"Julien Mulliestraat 2 Moeskroen/mouscron Hainaut 7711",
    "addr:housenumber":"2",
    "addr:postcode":"7711",
    "addr:street":"Mulliestraat",
    "iso:country":"BE",
    "sg:address":"Julien Mulliestraat 2",
    "sg:city":"Moeskroen/mouscron",
    "sg:orig_category":"Loodgieterij and centrale verwarming Gh",
    "sg:phone":"+32 56 48 58 88",
    "sg:postcode":"7711",
    "sg:province":"Hainaut",
    "wof:name":"Aqua & Sani Center",
    "wof:placetype":"venue"
},
  "geometry": {"coordinates":[3.3034780025,50.7291564941],"type":"Point"}
}