{
  "type": "Feature",
  "properties": {
    "addr:full":"Mechelseweg 347 Kapelle-op-den-bos Vlaams-Brabant 1880",
    "addr:housenumber":"347",
    "addr:postcode":"1880",
    "addr:street":"Mechelseweg",
    "iso:country":"BE",
    "sg:address":"Mechelseweg 347",
    "sg:city":"Kapelle-op-den-bos",
    "sg:orig_category":"Enseignement maternel and primaire",
    "sg:phone":"+32 15 71 31 76",
    "sg:postcode":"1880",
    "sg:province":"Vlaams-Brabant",
    "wof:name":"Vrije Basisschool",
    "wof:placetype":"venue"
},
  "geometry": {"coordinates":[4.3693051338,51.0121421814],"type":"Point"}
}