{
  "type": "Feature",
  "properties": {
    "addr:full":"Rue Mayelle 27 Jette Bruxelles-Capitale 1090",
    "addr:housenumber":"27",
    "addr:postcode":"1090",
    "addr:street":"Rue Mayelle",
    "iso:country":"BE",
    "sg:address":"Rue Mayelle 27",
    "sg:city":"Jette",
    "sg:orig_category":"Sportclubs",
    "sg:phone":"+32 2 425 88 48",
    "sg:postcode":"1090",
    "sg:province":"Bruxelles-Capitale",
    "wof:name":"Centre D'activit\u00c9s Sous Marine",
    "wof:placetype":"venue"
},
  "geometry": {"coordinates":[4.3376832008,50.872756958],"type":"Point"}
}