{
  "type": "Feature",
  "properties": {
    "addr:full":"Route De Wavre 120 Hannut Li\u00e8ge 4280",
    "addr:housenumber":"120",
    "addr:postcode":"4280",
    "addr:street":"Route De Wavre",
    "iso:country":"BE",
    "sg:address":"Route De Wavre 120",
    "sg:city":"Hannut",
    "sg:orig_category":"Fleurs and plantes",
    "sg:phone":"+32 19 51 24 52",
    "sg:postcode":"4280",
    "sg:province":"Li\u00e8ge",
    "wof:name":"Christifleur",
    "wof:placetype":"venue"
},
  "geometry": {"coordinates":[5.0443530083,50.6702766418],"type":"Point"}
}