{
  "type": "Feature",
  "properties": {
    "addr:full":"Rue Saint-jacques 4 Tournai Hainaut 7500",
    "addr:housenumber":"4",
    "addr:postcode":"7500",
    "addr:street":"Rue Saint-Jacques",
    "iso:country":"BE",
    "sg:address":"Rue Saint-jacques 4",
    "sg:city":"Tournai",
    "sg:classifiers":[
        {
            "category":"Shopping",
            "subcategory":"Books",
            "type":"Retail Goods"
        }
    ],
    "sg:phone":"+32 69 22 16 09",
    "sg:postcode":"7500",
    "sg:province":"Hainaut",
    "sg:tags":[
        "bookseller"
    ],
    "wof:name":"St Jacques (librairie)",
    "wof:placetype":"venue"
},
  "geometry": {"coordinates":[3.3843100071,50.6091423035],"type":"Point"}
}