{
  "type": "Feature",
  "properties": {
    "iso:country":"BE",
    "sg:address":"Lostraat 2",
    "sg:city":"Mol",
    "sg:classifiers":[
        {
            "category":"Bars & Pubs",
            "type":"Food & Drink"
        }
    ],
    "sg:phone":"+32 14 81 08 10",
    "sg:postcode":"2400",
    "sg:province":"Antwerpen",
    "wof:name":"Parochiehuis St-jozef",
    "wof:placetype":"venue"
},
  "geometry": {"coordinates":[5.2207078934,51.1964225769],"type":"Point"}
}