{
  "type": "Feature",
  "properties": {
    "addr:full":"Elizabetlaan 217 Knokke-heist (knokke) West-Vlaanderen 8300",
    "addr:housenumber":"217",
    "addr:postcode":"8300",
    "addr:street":"Elizabetlaan",
    "iso:country":"BE",
    "sg:address":"Elizabetlaan 217",
    "sg:city":"Knokke-heist (knokke)",
    "sg:orig_category":"Non-Classified Establishments",
    "sg:phone":"+32 50 59 82 95",
    "sg:postcode":"8300",
    "sg:province":"West-Vlaanderen",
    "wof:name":"V & D",
    "wof:placetype":"venue"
},
  "geometry": {"coordinates":[3.2898099422,51.3468093872],"type":"Point"}
}