{
  "type": "Feature",
  "properties": {
    "addr:full":"Hasseltsebaan 127 Diest Vlaams-Brabant 3290",
    "addr:housenumber":"127",
    "addr:postcode":"3290",
    "addr:street":"Hasseltsebaan",
    "iso:country":"BE",
    "sg:address":"Hasseltsebaan 127",
    "sg:city":"Diest",
    "sg:classifiers":[
        {
            "category":"Landmark",
            "subcategory":"Marketplace",
            "type":"Public Place"
        }
    ],
    "sg:phone":"+32 13 66 20 16",
    "sg:postcode":"3290",
    "sg:province":"Vlaams-Brabant",
    "sg:tags":[
        "commerce",
        "gr",
        "equipement",
        "de",
        "pour",
        "divers",
        "biens",
        "location",
        "diver"
    ],
    "wof:name":"Fun = Fair",
    "wof:placetype":"venue"
},
  "geometry": {"coordinates":[5.0917282104,51.0472831726],"type":"Point"}
}