{
  "type": "Feature",
  "properties": {
    "iso:country":"BE",
    "sg:address":"Rue De La Loi 33",
    "sg:city":"La Louvi\u00e8re",
    "sg:classifiers":[
        {
            "category":"Shopping",
            "subcategory":"Clothing, Apparel, & Fashions",
            "type":"Retail Goods"
        }
    ],
    "sg:phone":"+32 64 44 19 19",
    "sg:postcode":"7100",
    "sg:province":"Hainaut",
    "sg:tags":[
        "-",
        "clothing",
        "child"
    ],
    "wof:name":"Lora'less",
    "wof:placetype":"venue"
},
  "geometry": {"coordinates":[4.1862659454,50.4771003723],"type":"Point"}
}