{
  "type": "Feature",
  "properties": {
    "iso:country":"BE",
    "sg:address":"Rue De L'eglise 2",
    "sg:city":"Merbes-le-ch\u00e2teau (fontaine-valmont)",
    "sg:classifiers":[
        {
            "category":"Food & Beverages",
            "subcategory":"Groceries & Convenience Stores",
            "type":"Retail Goods"
        }
    ],
    "sg:phone":"+32 71 55 41 35",
    "sg:postcode":"6567",
    "sg:province":"Hainaut",
    "sg:tags":[
        "grocer"
    ],
    "wof:name":"Superette (la)",
    "wof:placetype":"venue"
},
  "geometry": {"coordinates":[4.213763237,50.3219108582],"type":"Point"}
}