{
  "type": "Feature",
  "properties": {
    "addr:full":"Rootenstraat 11 Box 6 Genk Limburg 3600",
    "addr:housenumber":"11;6",
    "addr:postcode":"3600",
    "addr:street":"Rootenstraat;Box",
    "iso:country":"BE",
    "sg:address":"Rootenstraat 11 Box 6",
    "sg:city":"Genk",
    "sg:classifiers":[
        {
            "category":"Shopping",
            "subcategory":"Clothing, Apparel, & Fashions",
            "type":"Retail Goods"
        }
    ],
    "sg:phone":"+32 89 35 82 17",
    "sg:postcode":"3600",
    "sg:province":"Limburg",
    "sg:tags":[
        "boutique"
    ],
    "wof:name":"Escorpion",
    "wof:placetype":"venue"
},
  "geometry": {"coordinates":[5.5028338432,50.9652481079],"type":"Point"}
}