{
  "type": "Feature",
  "properties": {
    "addr:full":"Rue De Str\u00c9e 33 Walcourt Namur 5650",
    "addr:housenumber":"33",
    "addr:postcode":"5650",
    "addr:street":"Rue De Stre\u0301E",
    "iso:country":"BE",
    "sg:address":"Rue De Str\u00c9e 33",
    "sg:city":"Walcourt",
    "sg:orig_category":"Eleveurs de bovins",
    "sg:phone":"+32 71 53 32 16",
    "sg:postcode":"5650",
    "sg:province":"Namur",
    "wof:name":"Rene Fontaine",
    "wof:placetype":"venue"
},
  "geometry": {"coordinates":[4.4313349724,50.2514762878],"type":"Point"}
}