{
  "type": "Feature",
  "properties": {
    "addr:full":"Van Frachenlaan 16 Steenokkerzeel Vlaams-Brabant 1820",
    "addr:housenumber":"16",
    "addr:postcode":"1820",
    "addr:street":"Van Frachenlaan",
    "iso:country":"BE",
    "sg:address":"Van Frachenlaan 16",
    "sg:city":"Steenokkerzeel",
    "sg:orig_category":"Cr\u00e9dits divers",
    "sg:postcode":"1820",
    "sg:province":"Vlaams-Brabant",
    "wof:name":"Bancontact-mister Cash",
    "wof:placetype":"venue"
},
  "geometry": {"coordinates":[4.5117921829,50.9112586975],"type":"Point"}
}