{
  "type": "Feature",
  "properties": {
    "iso:country":"BE",
    "sg:address":"F. Benardstraat 82",
    "sg:city":"Gent",
    "sg:orig_category":"Agences de voyages",
    "sg:phone":"+32 9 223 66 97",
    "sg:postcode":"9000",
    "sg:province":"Oost-Vlaanderen",
    "wof:name":"Linguamed Institute",
    "wof:placetype":"venue"
},
  "geometry": {"coordinates":[3.7316699028,51.0418739319],"type":"Point"}
}