{
  "type": "Feature",
  "properties": {
    "addr:full":"Brandekensweg 15 Schelle Antwerpen 2627",
    "addr:housenumber":"15",
    "addr:postcode":"2627",
    "addr:street":"Brandekensweg",
    "iso:country":"BE",
    "sg:address":"Brandekensweg 15",
    "sg:city":"Schelle",
    "sg:classifiers":[
        {
            "category":"Shopping",
            "subcategory":"Stationery & Office Supplies",
            "type":"Retail Goods"
        }
    ],
    "sg:phone":"+32 3 888 68 31",
    "sg:postcode":"2627",
    "sg:province":"Antwerpen",
    "sg:tags":[
        "cardboard"
    ],
    "wof:name":"Cartoline Nv",
    "wof:placetype":"venue"
},
  "geometry": {"coordinates":[4.3669409752,51.1148490906],"type":"Point"}
}