{
  "type": "Feature",
  "properties": {
    "iso:country":"BE",
    "sg:address":"Wauwerken 20",
    "sg:city":"Mol",
    "sg:orig_category":"Traitements param\u00e9dicaux",
    "sg:phone":"+32 14 31 72 61",
    "sg:postcode":"2400",
    "sg:province":"Antwerpen",
    "wof:name":"D. Verschueren",
    "wof:placetype":"venue"
},
  "geometry": {"coordinates":[5.1266078949,51.2101020813],"type":"Point"}
}