{
  "type": "Feature",
  "properties": {
    "addr:full":"Sprietestraat 130 Waregem (desselgem) West-Vlaanderen 8792",
    "addr:housenumber":"130",
    "addr:postcode":"8792",
    "addr:street":"Sprietestraat",
    "iso:country":"BE",
    "sg:address":"Sprietestraat 130",
    "sg:city":"Waregem (desselgem)",
    "sg:classifiers":[
        {
            "category":"Building & Trades",
            "subcategory":"Construction",
            "type":"Services"
        }
    ],
    "sg:phone":"+32 56 72 67 59",
    "sg:postcode":"8792",
    "sg:province":"West-Vlaanderen",
    "sg:tags":[
        "installation",
        "-",
        "central",
        "heating"
    ],
    "wof:name":"Delabie Bvba",
    "wof:placetype":"venue"
},
  "geometry": {"coordinates":[3.3654150963,50.8746833801],"type":"Point"}
}