{
  "type": "Feature",
  "properties": {
    "addr:full":"Woumenweg 284 Diksmuide West-Vlaanderen 8600",
    "addr:housenumber":"284",
    "addr:postcode":"8600",
    "addr:street":"Woumenweg",
    "iso:country":"BE",
    "sg:address":"Woumenweg 284",
    "sg:city":"Diksmuide",
    "sg:orig_category":"Bloemen and planten Rundveehouders",
    "sg:phone":"+32 51 50 36 63",
    "sg:postcode":"8600",
    "sg:province":"West-Vlaanderen",
    "wof:name":"Geert Masschelein",
    "wof:placetype":"venue"
},
  "geometry": {"coordinates":[2.8679099083,51.0131607056],"type":"Point"}
}