{
  "type": "Feature",
  "properties": {
    "addr:full":"Ninoofsesteenweg 1036 Dilbeek (schepdaal) Vlaams-Brabant 1703",
    "addr:housenumber":"1036",
    "addr:postcode":"1703",
    "addr:street":"Ninoofsesteenweg",
    "iso:country":"BE",
    "sg:address":"Ninoofsesteenweg 1036",
    "sg:city":"Dilbeek (schepdaal)",
    "sg:classifiers":[
        {
            "category":"Home & Garden",
            "subcategory":"Home Furnishings",
            "type":"Retail Goods"
        }
    ],
    "sg:phone":"+32 2 569 13 05",
    "sg:postcode":"1703",
    "sg:province":"Vlaams-Brabant",
    "sg:tags":[
        "-",
        "furniture"
    ],
    "wof:name":"Heremans Meubelen",
    "wof:placetype":"venue"
},
  "geometry": {"coordinates":[4.190223217,50.8376808167],"type":"Point"}
}