{
  "type": "Feature",
  "properties": {
    "iso:country":"BE",
    "sg:address":"Franz Merjaystraat 71",
    "sg:city":"Elsene/ixelles",
    "sg:orig_category":"Advocaten and juridische adviseurs",
    "sg:phone":"+32 2 344 12 62",
    "sg:postcode":"1050",
    "sg:province":"Bruxelles-Capitale",
    "wof:name":"Thierry Frankin",
    "wof:placetype":"venue"
},
  "geometry": {"coordinates":[4.3539347649,50.8199195862],"type":"Point"}
}