{
  "type": "Feature",
  "properties": {
    "addr:full":"Eedverbondkaai 283 Gent Oost-Vlaanderen 9000",
    "addr:housenumber":"283",
    "addr:postcode":"9000",
    "addr:street":"Oost-Vlaanderen",
    "iso:country":"BE",
    "sg:address":"Eedverbondkaai 283",
    "sg:city":"Gent",
    "sg:orig_category":"Alternatieve geneeskunde",
    "sg:phone":"+32 9 221 38 12",
    "sg:postcode":"9000",
    "sg:province":"Oost-Vlaanderen",
    "wof:name":"Laurence Van Eecke",
    "wof:placetype":"venue"
},
  "geometry": {"coordinates":[3.7111449242,51.0422325134],"type":"Point"}
}