{
  "type": "Feature",
  "properties": {
    "addr:full":"Leuvensesteenweg 759 Kortenberg Vlaams-Brabant 3071",
    "addr:housenumber":"759",
    "addr:postcode":"3071",
    "addr:street":"Leuvensesteenweg;Vlaams-Brabant",
    "iso:country":"BE",
    "sg:address":"Leuvensesteenweg 759",
    "sg:city":"Kortenberg",
    "sg:orig_category":"Benzinestations and brandstoffen Herstellingen and onderhoud van auto's",
    "sg:phone":"+32 2 759 63 37",
    "sg:postcode":"3071",
    "sg:province":"Vlaams-Brabant",
    "wof:name":"Deputter W",
    "wof:placetype":"venue"
},
  "geometry": {"coordinates":[4.5762500763,50.8922691345],"type":"Point"}
}