{
  "type": "Feature",
  "properties": {
    "addr:full":"Moleneind 53 Lille Antwerpen 2275",
    "addr:housenumber":"53",
    "addr:postcode":"2275",
    "addr:street":"Moleneind",
    "iso:country":"BE",
    "sg:address":"Moleneind 53",
    "sg:city":"Lille",
    "sg:classifiers":[
        {
            "category":"Arena",
            "subcategory":"Sports Club",
            "type":"Entertainment"
        }
    ],
    "sg:phone":"+32 14 88 16 91",
    "sg:postcode":"2275",
    "sg:province":"Antwerpen",
    "sg:tags":[
        "de"
    ],
    "wof:name":"Bart En Geert Wellens",
    "wof:placetype":"venue"
},
  "geometry": {"coordinates":[4.8271107674,51.2314491272],"type":"Point"}
}