{
  "type": "Feature",
  "properties": {
    "addr:full":"Square De Boondael 1 Box 40 Bruxelles (ixelles) Bruxelles-Capitale 1050",
    "addr:housenumber":"1 box 40",
    "addr:postcode":"1050",
    "addr:street":"Square De Boondael",
    "iso:country":"BE",
    "sg:address":"Square De Boondael 1 Box 40",
    "sg:city":"Bruxelles (ixelles)",
    "sg:classifiers":[
        {
            "category":"Professional",
            "subcategory":"Management & Consulting",
            "type":"Services"
        }
    ],
    "sg:phone":"+32 2 673 08 90",
    "sg:postcode":"1050",
    "sg:province":"Bruxelles-Capitale",
    "sg:tags":[
        "consultant"
    ],
    "wof:name":"Descamps J",
    "wof:placetype":"venue"
},
  "geometry": {"coordinates":[4.3929038048,50.8093948364],"type":"Point"}
}