{
  "type": "Feature",
  "properties": {
    "addr:full":"Rue Catherine Seret 6 Saint-georges-sur-meuse Li\u00e8ge 4470",
    "addr:housenumber":"6",
    "addr:postcode":"4470",
    "addr:street":"Rue Catherine Seret",
    "iso:country":"BE",
    "sg:address":"Rue Catherine Seret 6",
    "sg:city":"Saint-georges-sur-meuse",
    "sg:classifiers":[
        {
            "category":"Structure",
            "subcategory":"Office Building",
            "type":"Public Place"
        }
    ],
    "sg:phone":"+32 4 275 12 83",
    "sg:postcode":"4470",
    "sg:province":"Li\u00e8ge",
    "sg:tags":[
        "equipment",
        "alarm",
        "installation",
        "system"
    ],
    "wof:name":"Pedoux S.p.r.l.",
    "wof:placetype":"venue"
},
  "geometry": {"coordinates":[5.3833899498,50.598575592],"type":"Point"}
}