{
  "type": "Feature",
  "properties": {
    "iso:country":"BE",
    "sg:address":"Dokter Dhaenenslaan 60",
    "sg:city":"Merelbeke",
    "sg:classifiers":[
        {
            "category":"Personal",
            "subcategory":"Nail Salon",
            "type":"Services"
        }
    ],
    "sg:phone":"+32 9 230 40 99",
    "sg:postcode":"9820",
    "sg:province":"Oost-Vlaanderen",
    "sg:tags":[
        "pedicure"
    ],
    "wof:name":"Mathijs",
    "wof:placetype":"venue"
},
  "geometry": {"coordinates":[3.7570800781,51.0098609924],"type":"Point"}
}