{
  "type": "Feature",
  "properties": {
    "addr:full":"Rue Saint-vincent 35 Walhain (nil-saint-vincent-saint-martin) Brabant Wallon 1457",
    "addr:housenumber":"35",
    "addr:postcode":"1457",
    "addr:street":"Rue Saint-Vincent;Wallon",
    "iso:country":"BE",
    "sg:address":"Rue Saint-vincent 35",
    "sg:city":"Walhain (nil-saint-vincent-saint-martin)",
    "sg:classifiers":[
        {
            "category":"Government",
            "subcategory":"Office",
            "type":"Public Place"
        }
    ],
    "sg:phone":"+32 10 65 11 73",
    "sg:postcode":"1457",
    "sg:province":"Brabant Wallon",
    "sg:tags":[
        "-",
        "tourism",
        "federation"
    ],
    "wof:name":"Sites & Detente A.i.s.b.l.",
    "wof:placetype":"venue"
},
  "geometry": {"coordinates":[4.6699080467,50.6383628845],"type":"Point"}
}