{
  "type": "Feature",
  "properties": {
    "iso:country":"BE",
    "sg:address":"Haantjesstraat 14",
    "sg:city":"Kuurne",
    "sg:orig_category":"Hout and afgeleiden Gh IJzerwaren, bouw- and verfmaterialen",
    "sg:phone":"+32 56 70 41 92",
    "sg:postcode":"8520",
    "sg:province":"West-Vlaanderen",
    "wof:name":"Arcade",
    "wof:placetype":"venue"
},
  "geometry": {"coordinates":[3.2665030956,50.8731193542],"type":"Point"}
}