{
  "type": "Feature",
  "properties": {
    "addr:full":"Rue Ropaix 16 Dour Hainaut 7370",
    "addr:housenumber":"16",
    "addr:postcode":"7370",
    "addr:street":"Rue Ropaix;Hainaut",
    "iso:country":"BE",
    "sg:address":"Rue Ropaix 16",
    "sg:city":"Dour",
    "sg:classifiers":[
        {
            "category":"Health Services",
            "subcategory":"Nursing And Care Facility",
            "type":"Services"
        }
    ],
    "sg:phone":"+32 65 63 21 98",
    "sg:postcode":"7370",
    "sg:province":"Hainaut",
    "sg:tags":[
        "home",
        "rest"
    ],
    "wof:name":"Jours Heureux (les)",
    "wof:placetype":"venue"
},
  "geometry": {"coordinates":[3.8091790676,50.3794631958],"type":"Point"}
}