{
  "type": "Feature",
  "properties": {
    "addr:full":"Gezellestraat 45 Ninove (appelterre-eichem) Oost-Vlaanderen 9400",
    "addr:housenumber":"45",
    "addr:postcode":"9400",
    "addr:street":"Gezellestraat",
    "iso:country":"BE",
    "sg:address":"Gezellestraat 45",
    "sg:city":"Ninove (appelterre-eichem)",
    "sg:classifiers":[
        {
            "category":"Wholesale",
            "subcategory":"Plants",
            "type":"Manufacturing & Wholesale Goods"
        }
    ],
    "sg:phone":"+32 54 34 19 36",
    "sg:postcode":"9400",
    "sg:province":"Oost-Vlaanderen",
    "sg:tags":[
        "whol",
        "flower",
        "-",
        "grower"
    ],
    "wof:name":"Godyvan",
    "wof:placetype":"venue"
},
  "geometry": {"coordinates":[4.0232000351,50.8349113464],"type":"Point"}
}