{
  "type": "Feature",
  "properties": {
    "iso:country":"BE",
    "sg:address":"Posterijlaan 35",
    "sg:city":"Pittem",
    "sg:classifiers":[
        {
            "category":"Arena",
            "subcategory":"Sports Club",
            "type":"Entertainment"
        }
    ],
    "sg:phone":"+32 51 46 70 25",
    "sg:postcode":"8740",
    "sg:province":"West-Vlaanderen",
    "sg:tags":[
        "de"
    ],
    "wof:name":"Deinze Bc Fv",
    "wof:placetype":"venue"
},
  "geometry": {"coordinates":[3.250590086,50.9905357361],"type":"Point"}
}