{
  "type": "Feature",
  "properties": {
    "iso:country":"BE",
    "sg:address":"Place Joseph Wauters 23",
    "sg:city":"Andenne",
    "sg:orig_category":"Advocaten and juridische adviseurs",
    "sg:phone":"+32 85 82 62 30",
    "sg:postcode":"5300",
    "sg:province":"Namur",
    "wof:name":"J.b. Kefer",
    "wof:placetype":"venue"
},
  "geometry": {"coordinates":[5.0923528671,50.4902000427],"type":"Point"}
}