{
  "type": "Feature",
  "properties": {
    "addr:full":"Regentstraat 16 Antwerpen Antwerpen 2060",
    "addr:housenumber":"16",
    "addr:postcode":"2060",
    "addr:street":"Regentstraat",
    "iso:country":"BE",
    "sg:address":"Regentstraat 16",
    "sg:city":"Antwerpen",
    "sg:orig_category":"Experts-comptables",
    "sg:phone":"+32 3 236 24 18",
    "sg:postcode":"2060",
    "sg:province":"Antwerpen",
    "wof:name":"Girard G",
    "wof:placetype":"venue"
},
  "geometry": {"coordinates":[4.4282879829,51.2198143005],"type":"Point"}
}