{
  "type": "Feature",
  "properties": {
    "addr:full":"Grasmuslaan 10 Sint-genesius-rode/rhode-saint-genese Vlaams-Brabant 1640",
    "addr:housenumber":"10",
    "addr:postcode":"1640",
    "addr:street":"Grasmuslaan",
    "iso:country":"BE",
    "sg:address":"Grasmuslaan 10",
    "sg:city":"Sint-genesius-rode/rhode-saint-genese",
    "sg:orig_category":"Artsen and specialisten",
    "sg:phone":"+32 2 358 47 71",
    "sg:postcode":"1640",
    "sg:province":"Vlaams-Brabant",
    "wof:name":"Paul Vanden Weghe",
    "wof:placetype":"venue"
},
  "geometry": {"coordinates":[4.3965058327,50.7458610535],"type":"Point"}
}