{
  "type": "Feature",
  "properties": {
    "iso:country":"BE",
    "sg:address":"Grand-rue 86",
    "sg:city":"Aubange",
    "sg:classifiers":[
        {
            "category":"Cafe",
            "type":"Food & Drink"
        }
    ],
    "sg:phone":"+32 63 38 97 28",
    "sg:postcode":"6791",
    "sg:province":"Luxembourg",
    "sg:tags":[
        "caf\u00e9s"
    ],
    "wof:name":"Le Tropic",
    "wof:placetype":"venue"
},
  "geometry": {"coordinates":[5.8368549347,49.5628395081],"type":"Point"}
}