{
  "type": "Feature",
  "properties": {
    "addr:full":"De Colfmaekerstraat 6 Zottegem Oost-Vlaanderen 9620",
    "addr:housenumber":"6",
    "addr:postcode":"9620",
    "addr:street":"Colfmaekerstraat",
    "iso:country":"BE",
    "sg:address":"De Colfmaekerstraat 6",
    "sg:city":"Zottegem",
    "sg:classifiers":[
        {
            "category":"Health Services",
            "subcategory":"Nursing And Care Facility",
            "type":"Services"
        }
    ],
    "sg:phone":"+32 9 360 69 78",
    "sg:postcode":"9620",
    "sg:province":"Oost-Vlaanderen",
    "sg:tags":[
        "home",
        "rest"
    ],
    "wof:name":"Colfmaecker",
    "wof:placetype":"venue"
},
  "geometry": {"coordinates":[3.8154799938,50.8649330139],"type":"Point"}
}