{
  "type": "Feature",
  "properties": {
    "addr:full":"Steenweg Op Sint-joris Winge 23 Aarschot Vlaams-Brabant 3200",
    "addr:housenumber":"23",
    "addr:postcode":"3200",
    "addr:street":"Steenweg Op Sint-Joris Winge",
    "iso:country":"BE",
    "sg:address":"Steenweg Op Sint-joris Winge 23",
    "sg:city":"Aarschot",
    "sg:classifiers":[
        {
            "category":"Retail",
            "subcategory":"Driving School",
            "type":"Services"
        }
    ],
    "sg:phone":"+32 16 56 76 55",
    "sg:postcode":"3200",
    "sg:province":"Vlaams-Brabant",
    "sg:tags":[
        "automobile",
        "officially",
        "-",
        "recognized"
    ],
    "wof:name":"De Demer Auto- & Motorrijschool",
    "wof:placetype":"venue"
},
  "geometry": {"coordinates":[4.8244609833,50.9798355103],"type":"Point"}
}