{
  "type": "Feature",
  "properties": {
    "addr:full":"Bronlaan 1 Dilbeek (sint-ulriks-kapelle) Vlaams-Brabant 1700",
    "addr:housenumber":"1",
    "addr:postcode":"1700",
    "addr:street":"Bronlaan",
    "iso:country":"BE",
    "sg:address":"Bronlaan 1",
    "sg:city":"Dilbeek (sint-ulriks-kapelle)",
    "sg:classifiers":[
        {
            "category":"Health Services",
            "subcategory":"Doctor",
            "type":"Services"
        }
    ],
    "sg:phone":"+32 2 466 62 86",
    "sg:postcode":"1700",
    "sg:province":"Vlaams-Brabant",
    "sg:tags":[
        "medicinephysicians",
        "surgeon"
    ],
    "wof:name":"Ewalenko P",
    "wof:placetype":"venue"
},
  "geometry": {"coordinates":[4.2622699738,50.8393211365],"type":"Point"}
}