{
  "type": "Feature",
  "properties": {
    "iso:country":"BE",
    "sg:address":"Rue Emile-parfonry 25",
    "sg:city":"Hotton",
    "sg:orig_category":"Assurances. Cr\u00e9dit \u00e0 la consommation",
    "sg:phone":"+32 84 46 68 63",
    "sg:postcode":"6990",
    "sg:province":"Luxembourg",
    "wof:name":"W. Pecheur",
    "wof:placetype":"venue"
},
  "geometry": {"coordinates":[5.4455919266,50.2670707703],"type":"Point"}
}