{
  "type": "Feature",
  "properties": {
    "addr:full":"Stationsstraat 56 Boutersem Vlaams-Brabant 3370",
    "addr:housenumber":"56",
    "addr:postcode":"3370",
    "addr:street":"Stationsstraat",
    "iso:country":"BE",
    "sg:address":"Stationsstraat 56",
    "sg:city":"Boutersem",
    "sg:orig_category":"Banques and organismes de cr\u00e9dit",
    "sg:phone":"+32 16 73 31 68",
    "sg:postcode":"3370",
    "sg:province":"Vlaams-Brabant",
    "wof:name":"Fortis",
    "wof:placetype":"venue"
},
  "geometry": {"coordinates":[4.8395719528,50.8370552063],"type":"Point"}
}