{
  "type": "Feature",
  "properties": {
    "iso:country":"BE",
    "sg:address":"Nieuwstraat 88b",
    "sg:city":"Geel",
    "sg:classifiers":[
        {
            "category":"Professional",
            "subcategory":"Lawyer & Legal Services",
            "type":"Services"
        }
    ],
    "sg:phone":"+32 14 58 02 40",
    "sg:postcode":"2440",
    "sg:province":"Antwerpen",
    "wof:name":"Matheussen Lieve",
    "wof:placetype":"venue"
},
  "geometry": {"coordinates":[4.9943118095,51.1633758545],"type":"Point"}
}