{
  "type": "Feature",
  "properties": {
    "iso:country":"BE",
    "sg:address":"Chemin Dupireux 33",
    "sg:city":"Li\u00e8ge",
    "sg:classifiers":[
        {
            "category":"Banks & Credit Unions",
            "subcategory":"Bureau De Change",
            "type":"Services"
        }
    ],
    "sg:phone":"+32 4 239 98 98",
    "sg:postcode":"4000",
    "sg:province":"Li\u00e8ge",
    "sg:tags":[
        "units",
        "heating",
        "radiator"
    ],
    "wof:name":"Manaut Europe S.a.",
    "wof:placetype":"venue"
},
  "geometry": {"coordinates":[5.5451540947,50.6802482605],"type":"Point"}
}