{
  "type": "Feature",
  "properties": {
    "addr:full":"Boomgaardstraat 18 Ieper West-Vlaanderen 8900",
    "addr:housenumber":"18",
    "addr:postcode":"8900",
    "addr:street":"Boomgaardstraat",
    "iso:country":"BE",
    "sg:address":"Boomgaardstraat 18",
    "sg:city":"Ieper",
    "sg:orig_category":"Banken and kredietinstellingen",
    "sg:phone":"+32 57 21 69 94",
    "sg:postcode":"8900",
    "sg:province":"West-Vlaanderen",
    "wof:name":"Groep Argenta",
    "wof:placetype":"venue"
},
  "geometry": {"coordinates":[2.8845660686,50.8499755859],"type":"Point"}
}