{
  "type": "Feature",
  "properties": {
    "iso:country":"BE",
    "sg:address":"Attenhovenstraat 54b3",
    "sg:city":"Landen",
    "sg:orig_category":"Imprimeries and copyshops",
    "sg:phone":"+32 11 83 12 35",
    "sg:postcode":"3400",
    "sg:province":"Vlaams-Brabant",
    "wof:name":"Bert Vanwelkenhuyzen",
    "wof:placetype":"venue"
},
  "geometry": {"coordinates":[5.0836458206,50.7578773499],"type":"Point"}
}