{
  "type": "Feature",
  "properties": {
    "iso:country":"BE",
    "sg:address":"Rue Du Pont De Bois 9",
    "sg:city":"Thuin (bierc\u00e9e)",
    "sg:classifiers":[
        {
            "category":"Health Services",
            "subcategory":"Doctor",
            "type":"Services"
        }
    ],
    "sg:phone":"+32 71 59 25 25",
    "sg:postcode":"6533",
    "sg:province":"Hainaut",
    "sg:tags":[
        "medicinephysicians",
        "surgeon"
    ],
    "wof:name":"Clamot J",
    "wof:placetype":"venue"
},
  "geometry": {"coordinates":[4.2548418045,50.3264465332],"type":"Point"}
}