{
  "type": "Feature",
  "properties": {
    "iso:country":"BE",
    "sg:address":"Bloemistenstraat 6",
    "sg:city":"Kortrijk",
    "sg:classifiers":[
        {
            "category":"Manufacturing",
            "subcategory":"Jewelry",
            "type":"Manufacturing & Wholesale Goods"
        }
    ],
    "sg:phone":"+32 56 25 80 78",
    "sg:postcode":"8500",
    "sg:province":"West-Vlaanderen",
    "sg:tags":[
        "jewel"
    ],
    "wof:name":"Beheyt Nv",
    "wof:placetype":"venue"
},
  "geometry": {"coordinates":[3.2633070946,50.823097229],"type":"Point"}
}