{
  "type": "Feature",
  "properties": {
    "iso:country":"BE",
    "sg:address":"Zandberg 9",
    "sg:city":"Gent",
    "sg:classifiers":[
        {
            "category":"Professional",
            "subcategory":"Art Services",
            "type":"Services"
        }
    ],
    "sg:phone":"+32 9 223 64 93",
    "sg:postcode":"9000",
    "sg:province":"Oost-Vlaanderen",
    "sg:tags":[
        "photographer"
    ],
    "wof:name":"Press Voyager-yvan Deweerdt",
    "wof:placetype":"venue"
},
  "geometry": {"coordinates":[3.7271399498,51.0548591614],"type":"Point"}
}