{
  "type": "Feature",
  "properties": {
    "iso:country":"BE",
    "sg:address":"Hoogstraat 46",
    "sg:city":"Meeuwen-gruitrode (meeuwen)",
    "sg:classifiers":[
        {
            "category":"Food & Beverages",
            "subcategory":"Chocolate",
            "type":"Retail Goods"
        }
    ],
    "sg:phone":"+32 11 79 28 95",
    "sg:postcode":"3670",
    "sg:province":"Limburg",
    "sg:tags":[
        "confectionery",
        "-"
    ],
    "wof:name":"D'abonie",
    "wof:placetype":"venue"
},
  "geometry": {"coordinates":[5.5228872299,51.0932502747],"type":"Point"}
}