{
  "type": "Feature",
  "properties": {
    "addr:full":"Kellengeerstraat 6 Maaseik Limburg 3680",
    "addr:housenumber":"6",
    "addr:postcode":"3680",
    "addr:street":"Kellengeerstraat",
    "iso:country":"BE",
    "sg:address":"Kellengeerstraat 6",
    "sg:city":"Maaseik",
    "sg:orig_category":"Rev\u00eatements de sols and murs",
    "sg:phone":"+32 89 86 48 33",
    "sg:postcode":"3680",
    "sg:province":"Limburg",
    "wof:name":"Vandewinkel",
    "wof:placetype":"venue"
},
  "geometry": {"coordinates":[5.791285038,51.0954208374],"type":"Point"}
}