{
  "type": "Feature",
  "properties": {
    "iso:country":"BE",
    "sg:address":"Ancien Chemin Wellin 96",
    "sg:city":"Daverdisse",
    "sg:orig_category":"Offices du tourisme. Installations and terrains de sport hors centres sportifs. Mus\u00e9es and patrimoin",
    "sg:phone":"+32 61 58 95 51",
    "sg:postcode":"6929",
    "sg:province":"Luxembourg",
    "wof:name":"Syndicat D'initaitive-piste les Scottons",
    "wof:placetype":"venue"
},
  "geometry": {"coordinates":[5.020678997,50.0019989014],"type":"Point"}
}