{
  "type": "Feature",
  "properties": {
    "addr:full":"Mariastraat 22 Roeselare West-Vlaanderen 8800",
    "addr:housenumber":"22",
    "addr:postcode":"8800",
    "addr:street":"Mariastraat",
    "iso:country":"BE",
    "sg:address":"Mariastraat 22",
    "sg:city":"Roeselare",
    "sg:classifiers":[
        {
            "category":"Building & Trades",
            "subcategory":"Pest Control",
            "type":"Services"
        }
    ],
    "sg:phone":"+32 51 20 06 02",
    "sg:postcode":"8800",
    "sg:province":"West-Vlaanderen",
    "sg:tags":[
        "drive",
        "chain"
    ],
    "wof:name":"Aandrijvingen Gallon Nv",
    "wof:placetype":"venue"
},
  "geometry": {"coordinates":[3.1318860054,50.9506225586],"type":"Point"}
}