{
  "type": "Feature",
  "properties": {
    "addr:full":"Hoog-lachenen 62 Lier Antwerpen 2500",
    "addr:housenumber":"62",
    "addr:postcode":"2500",
    "addr:street":"Hoog-Lachenen",
    "iso:country":"BE",
    "sg:address":"Hoog-lachenen 62",
    "sg:city":"Lier",
    "sg:orig_category":"Reclamebureaus",
    "sg:phone":"+32 3 480 71 36",
    "sg:postcode":"2500",
    "sg:province":"Antwerpen",
    "wof:name":"Fa. Marien Design",
    "wof:placetype":"venue"
},
  "geometry": {"coordinates":[4.5182571411,51.1176567078],"type":"Point"}
}