{
  "type": "Feature",
  "properties": {
    "iso:country":"BE",
    "sg:address":"S. Dupuislaan 239b11",
    "sg:city":"Anderlecht",
    "sg:orig_category":"Diverse bedrijfsbeheeradviesbureaus",
    "sg:phone":"+32 2 520 74 30",
    "sg:postcode":"1070",
    "sg:province":"Bruxelles-Capitale",
    "wof:name":"Boik International",
    "wof:placetype":"venue"
},
  "geometry": {"coordinates":[4.2907910347,50.8376312256],"type":"Point"}
}