{
  "type": "Feature",
  "properties": {
    "iso:country":"BE",
    "sg:address":"Koeistraat 42-2",
    "sg:city":"Arendonk",
    "sg:classifiers":[
        {
            "category":"Insurance",
            "subcategory":"Insurance Agent",
            "type":"Services"
        }
    ],
    "sg:phone":"+32 14 67 12 40",
    "sg:postcode":"2370",
    "sg:province":"Antwerpen",
    "sg:tags":[
        "broker"
    ],
    "wof:name":"Kbc Verzekeringen Maris & Rosier",
    "wof:placetype":"venue"
},
  "geometry": {"coordinates":[5.0868330002,51.3181037903],"type":"Point"}
}