{
  "type": "Feature",
  "properties": {
    "iso:country":"BE",
    "sg:address":"Hoogstraat 10",
    "sg:city":"Beersel",
    "sg:classifiers":[
        {
            "category":"Retail",
            "subcategory":"Event Space",
            "type":"Services"
        }
    ],
    "sg:phone":"+32 2 331 24 46",
    "sg:postcode":"1650",
    "sg:province":"Vlaams-Brabant",
    "sg:tags":[
        "rental",
        "-",
        "hall"
    ],
    "wof:name":"Cafe-feestzaal",
    "wof:placetype":"venue"
},
  "geometry": {"coordinates":[4.3087711334,50.7664375305],"type":"Point"}
}