{
  "type": "Feature",
  "properties": {
    "iso:country":"BE",
    "sg:address":"Rue De La Coop\u00c9ration 111",
    "sg:city":"Saint-nicolas",
    "sg:orig_category":"Catering and organisatie van feesten Fast food and meeneem restaurants Restaurants",
    "sg:phone":"+32 4 226 06 29",
    "sg:postcode":"4420",
    "sg:province":"Li\u00e8ge",
    "wof:name":"Les Jardins De Coralie",
    "wof:placetype":"venue"
},
  "geometry": {"coordinates":[5.5352129936,50.6386489868],"type":"Point"}
}