{
  "type": "Feature",
  "properties": {
    "addr:full":"Esplanade De L'europe 2b220 Lifge Li\u00e8ge 4020",
    "addr:housenumber":"2b220",
    "addr:postcode":"4020",
    "addr:street":"Esplanade De L'Europe",
    "iso:country":"BE",
    "sg:address":"Esplanade De L'europe 2b220",
    "sg:city":"Lifge",
    "sg:orig_category":"Agences de mannequins and h\u00f4tesses",
    "sg:phone":"+32 4 344 00 36",
    "sg:postcode":"4020",
    "sg:province":"Li\u00e8ge",
    "wof:name":"Luxotess",
    "wof:placetype":"venue"
},
  "geometry": {"coordinates":[7.8578400612,52.9761810303],"type":"Point"}
}