{
  "type": "Feature",
  "properties": {
    "addr:full":"Peperhofstraat 103 Genk (waterschei) Limburg 3600",
    "addr:housenumber":"103",
    "addr:postcode":"3600",
    "addr:street":"Peperhofstraat",
    "iso:country":"BE",
    "sg:address":"Peperhofstraat 103",
    "sg:city":"Genk (waterschei)",
    "sg:classifiers":[
        {
            "category":"Government",
            "subcategory":"Fire Station",
            "type":"Public Place"
        }
    ],
    "sg:phone":"+32 89 38 39 71",
    "sg:postcode":"3600",
    "sg:province":"Limburg",
    "sg:tags":[
        "installation",
        "-",
        "air conditioning"
    ],
    "wof:name":"E.k.v.",
    "wof:placetype":"venue"
},
  "geometry": {"coordinates":[5.486823082,50.9978599548],"type":"Point"}
}