{
  "type": "Feature",
  "properties": {
    "addr:full":"Avenue De Spa 17 Verviers Li\u00e8ge 4800",
    "addr:housenumber":"17",
    "addr:postcode":"4800",
    "addr:street":"Avenue De Spa",
    "iso:country":"BE",
    "sg:address":"Avenue De Spa 17",
    "sg:city":"Verviers",
    "sg:orig_category":"Avocats and conseillers juridiques",
    "sg:phone":"+32 87 23 07 70",
    "sg:postcode":"4800",
    "sg:province":"Li\u00e8ge",
    "wof:name":"Yves Wynants",
    "wof:placetype":"venue"
},
  "geometry": {"coordinates":[5.8630571365,50.5834083557],"type":"Point"}
}