{
  "type": "Feature",
  "properties": {
    "addr:full":"Stationsstraat V. Woluwe 54 Sint-lambrechts-woluwe/woluwe-saint-lambert Bruxelles-Capitale 1200",
    "addr:housenumber":"54",
    "addr:postcode":"1200",
    "addr:street":"Stationsstraat V. Woluwe",
    "iso:country":"BE",
    "sg:address":"Stationsstraat V. Woluwe 54",
    "sg:city":"Sint-lambrechts-woluwe/woluwe-saint-lambert",
    "sg:orig_category":"Huisdieren and benodigdheden",
    "sg:phone":"+32 2 763 32 42",
    "sg:postcode":"1200",
    "sg:province":"Bruxelles-Capitale",
    "wof:name":"Exocet Aquarium",
    "wof:placetype":"venue"
},
  "geometry": {"coordinates":[4.4360799789,50.8401603699],"type":"Point"}
}