{
  "type": "Feature",
  "properties": {
    "iso:country":"BE",
    "sg:address":"Place Matt\u00e9oti 1a",
    "sg:city":"Charleroi (jumet)",
    "sg:classifiers":[
        {
            "category":"Professional",
            "subcategory":"Testing Lab",
            "type":"Services"
        }
    ],
    "sg:phone":"+32 71 35 28 69",
    "sg:postcode":"6040",
    "sg:province":"Hainaut",
    "sg:tags":[
        "chemist"
    ],
    "wof:name":"Maes Sprl",
    "wof:placetype":"venue"
},
  "geometry": {"coordinates":[4.4505472183,50.4418067932],"type":"Point"}
}