{
  "type": "Feature",
  "properties": {
    "addr:full":"'t Angereelstraat 51 Ninove (appelterre-eichem) Oost-Vlaanderen 9400",
    "addr:housenumber":"51",
    "addr:postcode":"9400",
    "addr:street":"';Angereelstraat",
    "iso:country":"BE",
    "sg:address":"'t Angereelstraat 51",
    "sg:city":"Ninove (appelterre-eichem)",
    "sg:classifiers":[
        {
            "category":"Building & Trades",
            "subcategory":"Construction",
            "type":"Services"
        }
    ],
    "sg:phone":"+32 54 33 45 62",
    "sg:postcode":"9400",
    "sg:province":"Oost-Vlaanderen",
    "sg:tags":[
        "stucco",
        "contractor"
    ],
    "wof:name":"Caenepenne P & Zn",
    "wof:placetype":"venue"
},
  "geometry": {"coordinates":[3.9698960781,50.816444397],"type":"Point"}
}