{
  "type": "Feature",
  "properties": {
    "iso:country":"BE",
    "sg:address":"Senonchamps 66",
    "sg:city":"Bastogne",
    "sg:orig_category":"Installation de menuiserie m\u00e9tallique. Quincailleries. Bois Gr",
    "sg:phone":"+32 61 21 61 78",
    "sg:postcode":"6600",
    "sg:province":"Luxembourg",
    "wof:name":"Michel Colla",
    "wof:placetype":"venue"
},
  "geometry": {"coordinates":[5.664150238,50.000869751],"type":"Point"}
}