{
  "type": "Feature",
  "properties": {
    "addr:full":"Rue De Jemeppe 37 Ans Li\u00e8ge 4431",
    "addr:housenumber":"37",
    "addr:postcode":"4431",
    "addr:street":"Rue De Jemeppe",
    "iso:country":"BE",
    "sg:address":"Rue De Jemeppe 37",
    "sg:city":"Ans",
    "sg:classifiers":[
        {
            "category":"Fast Food",
            "type":"Food & Drink"
        }
    ],
    "sg:phone":"+32 4 263 46 55",
    "sg:postcode":"4431",
    "sg:province":"Li\u00e8ge",
    "sg:tags":[
        "\u00c0",
        "emporter",
        "restaurants"
    ],
    "wof:name":"Loncin",
    "wof:placetype":"venue"
},
  "geometry": {"coordinates":[5.5034589767,50.665096283],"type":"Point"}
}