{
  "type": "Feature",
  "properties": {
    "addr:full":"Groenstraat 1a Box 4 Aalst (erembodegem) Oost-Vlaanderen 9320",
    "addr:housenumber":"1a box 4",
    "addr:postcode":"9320",
    "addr:street":"Groenstraat",
    "iso:country":"BE",
    "sg:address":"Groenstraat 1a Box 4",
    "sg:city":"Aalst (erembodegem)",
    "sg:classifiers":[
        {
            "category":"Health Services",
            "subcategory":"Health Practitioner",
            "type":"Services"
        }
    ],
    "sg:phone":"+32 477 19 59 49",
    "sg:postcode":"9320",
    "sg:province":"Oost-Vlaanderen",
    "sg:tags":[
        "therapist",
        "speech"
    ],
    "wof:name":"Everaert E",
    "wof:placetype":"venue"
},
  "geometry": {"coordinates":[4.0553851128,50.9209976196],"type":"Point"}
}