{
  "type": "Feature",
  "properties": {
    "addr:full":"Rue Eug\u00e8ne Verheggen 24-26 Bruxelles (saint-gilles) Bruxelles-Capitale 1060",
    "addr:housenumber":"24-26",
    "addr:postcode":"1060",
    "addr:street":"Rue Euge\u0300Ne Verheggen",
    "iso:country":"BE",
    "sg:address":"Rue Eug\u00e8ne Verheggen 24-26",
    "sg:city":"Bruxelles (saint-gilles)",
    "sg:classifiers":[
        {
            "category":"Retail",
            "subcategory":"Auto Repair",
            "type":"Services"
        }
    ],
    "sg:phone":"+32 2 346 22 68",
    "sg:postcode":"1060",
    "sg:province":"Bruxelles-Capitale",
    "sg:tags":[
        "automobile-body"
    ],
    "wof:name":"Nickel Car Sa",
    "wof:placetype":"venue"
},
  "geometry": {"coordinates":[4.3447270393,50.8213500977],"type":"Point"}
}