{
  "type": "Feature",
  "properties": {
    "addr:full":"Rijvisschestraat 118 Box 5 Gent (zwijnaarde) Oost-Vlaanderen 9052",
    "addr:housenumber":"118;5",
    "addr:postcode":"9052",
    "addr:street":"Rijvisschestraat;Box",
    "iso:country":"BE",
    "sg:address":"Rijvisschestraat 118 Box 5",
    "sg:city":"Gent (zwijnaarde)",
    "sg:classifiers":[
        {
            "category":"Farming",
            "subcategory":"Berry Farm",
            "type":"Manufacturing & Wholesale Goods"
        }
    ],
    "sg:phone":"+32 9 243 98 50",
    "sg:postcode":"9052",
    "sg:province":"Oost-Vlaanderen",
    "sg:tags":[
        "horticulture",
        "-",
        "broker",
        "whol",
        "seed",
        "grain",
        "agriculture"
    ],
    "wof:name":"Syngenta Seeds Nv",
    "wof:placetype":"venue"
},
  "geometry": {"coordinates":[3.7167270184,51.0002937317],"type":"Point"}
}