{
  "type": "Feature",
  "properties": {
    "iso:country":"BE",
    "sg:address":"Mechelsesteenweg 152",
    "sg:city":"Edegem",
    "sg:orig_category":"Bagage and lederwaren Fab Bagage and lederwaren Gh",
    "sg:phone":"+32 3 281 69 90",
    "sg:postcode":"2650",
    "sg:province":"Antwerpen",
    "wof:name":"Eastpak",
    "wof:placetype":"venue"
},
  "geometry": {"coordinates":[4.4631900787,51.1497154236],"type":"Point"}
}