{
  "type": "Feature",
  "properties": {
    "iso:country":"BE",
    "sg:address":"Bondgenotenlaan 122",
    "sg:city":"Leuven",
    "sg:orig_category":"Speelgoed",
    "sg:phone":"+32 16 89 80 82",
    "sg:postcode":"3000",
    "sg:province":"Vlaams-Brabant",
    "wof:name":"Christiaensen",
    "wof:placetype":"venue"
},
  "geometry": {"coordinates":[4.7122387886,50.8806495667],"type":"Point"}
}