{
  "type": "Feature",
  "properties": {
    "addr:full":"Kroonlaan 484 Elsene/ixelles Bruxelles-Capitale 1050",
    "addr:housenumber":"484",
    "addr:postcode":"1050",
    "addr:street":"Kroonlaan",
    "iso:country":"BE",
    "sg:address":"Kroonlaan 484",
    "sg:city":"Elsene/ixelles",
    "sg:orig_category":"Onderdelen and accessoires voor auto's",
    "sg:phone":"+32 2 644 08 75",
    "sg:postcode":"1050",
    "sg:province":"Bruxelles-Capitale",
    "wof:name":"New Ideal Pneus",
    "wof:placetype":"venue"
},
  "geometry": {"coordinates":[4.3911681175,50.819896698],"type":"Point"}
}