{
  "type": "Feature",
  "properties": {
    "iso:country":"BE",
    "sg:address":"Rue De L'orjo 83",
    "sg:city":"Namur (jambes)",
    "sg:classifiers":[
        {
            "category":"Building & Trades",
            "subcategory":"Construction",
            "type":"Services"
        }
    ],
    "sg:phone":"+32 81 30 70 73",
    "sg:postcode":"5100",
    "sg:province":"Namur",
    "sg:tags":[
        "installation",
        "-",
        "central",
        "heating"
    ],
    "wof:name":"Pega Sc",
    "wof:placetype":"venue"
},
  "geometry": {"coordinates":[4.8848409653,50.4597930908],"type":"Point"}
}