{
  "type": "Feature",
  "properties": {
    "addr:full":"Avenue Des Saules 26 Waterloo Brabant Wallon 1410",
    "addr:housenumber":"26",
    "addr:postcode":"1410",
    "addr:street":"Avenue Des Saules",
    "iso:country":"BE",
    "sg:address":"Avenue Des Saules 26",
    "sg:city":"Waterloo",
    "sg:classifiers":[
        {
            "category":"Professional",
            "subcategory":"Management & Consulting",
            "type":"Services"
        }
    ],
    "sg:phone":"+32 2 354 43 77",
    "sg:postcode":"1410",
    "sg:province":"Brabant Wallon",
    "sg:tags":[
        "consultant"
    ],
    "wof:name":"Abc Consult",
    "wof:placetype":"venue"
},
  "geometry": {"coordinates":[4.390639782,50.7150344849],"type":"Point"}
}