{
  "type": "Feature",
  "properties": {
    "addr:full":"Avenue Wanderpepen 42 Binche Hainaut 7130",
    "addr:housenumber":"42",
    "addr:postcode":"7130",
    "addr:street":"Avenue Wanderpepen",
    "iso:country":"BE",
    "sg:address":"Avenue Wanderpepen 42",
    "sg:city":"Binche",
    "sg:orig_category":"Eclairage et \u00e9quipements du foyer",
    "sg:phone":"+32 64 36 86 31",
    "sg:postcode":"7130",
    "sg:province":"Hainaut",
    "wof:name":"Chevalier Decoration",
    "wof:placetype":"venue"
},
  "geometry": {"coordinates":[4.1696982384,50.4121322632],"type":"Point"}
}