{
  "type": "Feature",
  "properties": {
    "iso:country":"BE",
    "sg:address":"Admiraal Ronarchstraat 10",
    "sg:city":"Diksmuide",
    "sg:classifiers":[
        {
            "category":"Insurance",
            "subcategory":"Insurance Agent",
            "type":"Services"
        }
    ],
    "sg:phone":"+32 51 50 25 17",
    "sg:postcode":"8600",
    "sg:province":"West-Vlaanderen",
    "sg:tags":[
        "broker"
    ],
    "wof:name":"Loeters L",
    "wof:placetype":"venue"
},
  "geometry": {"coordinates":[2.8662230968,51.032913208],"type":"Point"}
}