{
  "type": "Feature",
  "properties": {
    "iso:country":"BE",
    "sg:address":"Sint-willibrordusplein 23b2",
    "sg:city":"Heusden-zolder",
    "sg:orig_category":"Plaatsen van vloer- and muurbekleding Schilders",
    "sg:phone":"+32 11 42 64 87",
    "sg:postcode":"3550",
    "sg:province":"Limburg",
    "wof:name":"Josephus Truyers",
    "wof:placetype":"venue"
},
  "geometry": {"coordinates":[5.2815589905,51.0331573486],"type":"Point"}
}