{
  "type": "Feature",
  "properties": {
    "addr:full":"Landbouwstraat 88 Antwerpen Antwerpen 2020",
    "addr:housenumber":"88",
    "addr:postcode":"2020",
    "addr:street":"Landbouwstraat",
    "iso:country":"BE",
    "sg:address":"Landbouwstraat 88",
    "sg:city":"Antwerpen",
    "sg:orig_category":"Medische and orthopedische apparaten",
    "sg:phone":"+32 3 238 60 44",
    "sg:postcode":"2020",
    "sg:province":"Antwerpen",
    "wof:name":"De Medische Akoestiek",
    "wof:placetype":"venue"
},
  "geometry": {"coordinates":[4.3846850395,51.1872749329],"type":"Point"}
}