{
  "type": "Feature",
  "properties": {
    "iso:country":"BE",
    "sg:address":"Grand'place 19",
    "sg:city":"P\u00e9ruwelz",
    "sg:classifiers":[
        {
            "category":"Shopping",
            "subcategory":"Optician",
            "type":"Retail Goods"
        }
    ],
    "sg:phone":"+32 69 77 45 21",
    "sg:postcode":"7600",
    "sg:province":"Hainaut",
    "sg:tags":[
        "-"
    ],
    "wof:name":"Dits Centre Optique",
    "wof:placetype":"venue"
},
  "geometry": {"coordinates":[3.5923399925,50.5101509094],"type":"Point"}
}