{
  "type": "Feature",
  "properties": {
    "addr:full":"Hoekstraat 40bb Denderleeuw Oost-Vlaanderen 9472",
    "addr:housenumber":"40bb",
    "addr:postcode":"9472",
    "addr:street":"Hoekstraat",
    "iso:country":"BE",
    "sg:address":"Hoekstraat 40bb",
    "sg:city":"Denderleeuw",
    "sg:orig_category":"Woningbouw",
    "sg:phone":"+32 53 66 94 29",
    "sg:postcode":"9472",
    "sg:province":"Oost-Vlaanderen",
    "wof:name":"Fa. Bisback",
    "wof:placetype":"venue"
},
  "geometry": {"coordinates":[4.0444059372,50.8733558655],"type":"Point"}
}