{
  "type": "Feature",
  "properties": {
    "iso:country":"BE",
    "sg:address":"Hasseltsesteenweg 63",
    "sg:city":"Sint-truiden",
    "sg:orig_category":"V\u00eatements. Chaussures",
    "sg:phone":"+32 11 69 88 39",
    "sg:postcode":"3800",
    "sg:province":"Limburg",
    "wof:name":"Berca",
    "wof:placetype":"venue"
},
  "geometry": {"coordinates":[5.2014269829,50.8281288147],"type":"Point"}
}