{
  "type": "Feature",
  "properties": {
    "iso:country":"BE",
    "sg:address":"Avenue De L'or\u00c9e 25ba2",
    "sg:city":"Elsene/ixelles",
    "sg:orig_category":"Administration d'immeubles",
    "sg:phone":"+32 2 648 62 93",
    "sg:postcode":"1050",
    "sg:province":"Bruxelles-Capitale",
    "wof:name":"B. Karadzas",
    "wof:placetype":"venue"
},
  "geometry": {"coordinates":[4.3856711388,50.8100814819],"type":"Point"}
}