{
  "type": "Feature",
  "properties": {
    "addr:full":"Faubourg De Mignault 23 Le Roeulx Hainaut 7070",
    "addr:housenumber":"23",
    "addr:postcode":"7070",
    "addr:street":"Faubourg De Mignault",
    "iso:country":"BE",
    "sg:address":"Faubourg De Mignault 23",
    "sg:city":"Le Roeulx",
    "sg:orig_category":"Projectontwikkelaars Woningbouw",
    "sg:phone":"+32 64 67 55 86",
    "sg:postcode":"7070",
    "sg:province":"Hainaut",
    "wof:name":"Promotions Y.w.",
    "wof:placetype":"venue"
},
  "geometry": {"coordinates":[4.1205301285,50.5089111328],"type":"Point"}
}