{
  "type": "Feature",
  "properties": {
    "addr:full":"Rue De La Fl\u00c9ch\u00c8re 0 Courcelles Hainaut 6181",
    "addr:housenumber":"0",
    "addr:postcode":"6181",
    "addr:street":"Rue De La Fle\u0301Che\u0300Re",
    "iso:country":"BE",
    "sg:address":"Rue De La Fl\u00c9ch\u00c8re 0",
    "sg:city":"Courcelles",
    "sg:orig_category":"Openbare bibliotheken and archieven",
    "sg:phone":"+32 71 45 75 40",
    "sg:postcode":"6181",
    "sg:province":"Hainaut",
    "wof:name":"Ludoth\u00c8que De La Fl\u00cach\u00c8re",
    "wof:placetype":"venue"
},
  "geometry": {"coordinates":[4.3226828575,50.4973754883],"type":"Point"}
}