{
  "type": "Feature",
  "properties": {
    "addr:full":"Markiesakker 13 Destelbergen Oost-Vlaanderen 9070",
    "addr:housenumber":"13",
    "addr:postcode":"9070",
    "addr:street":"Markiesakker",
    "iso:country":"BE",
    "sg:address":"Markiesakker 13",
    "sg:city":"Destelbergen",
    "sg:classifiers":[
        {
            "category":"Building & Trades",
            "subcategory":"Construction",
            "type":"Services"
        }
    ],
    "sg:phone":"+32 9 228 63 47",
    "sg:postcode":"9070",
    "sg:province":"Oost-Vlaanderen",
    "sg:tags":[
        "installation",
        "-",
        "central",
        "heating"
    ],
    "wof:name":"Lesage P Bvba",
    "wof:placetype":"venue"
},
  "geometry": {"coordinates":[3.7674770355,51.0567779541],"type":"Point"}
}