{
  "type": "Feature",
  "properties": {
    "iso:country":"BE",
    "sg:address":"Prins Boudewijnlaan 314",
    "sg:city":"Edegem",
    "sg:orig_category":"Pharmaciens",
    "sg:phone":"+32 3 449 99 06",
    "sg:postcode":"2650",
    "sg:province":"Antwerpen",
    "wof:name":"K. Van Speybroeck",
    "wof:placetype":"venue"
},
  "geometry": {"coordinates":[4.4273757935,51.1635246277],"type":"Point"}
}