{
  "type": "Feature",
  "properties": {
    "addr:full":"Polderstraat 6 Hamme Oost-Vlaanderen 9220",
    "addr:housenumber":"6",
    "addr:postcode":"9220",
    "addr:street":"Polderstraat",
    "iso:country":"BE",
    "sg:address":"Polderstraat 6",
    "sg:city":"Hamme",
    "sg:classifiers":[
        {
            "category":"Food & Beverages",
            "subcategory":"Fruits & Vegetables",
            "type":"Retail Goods"
        }
    ],
    "sg:phone":"+32 52 47 67 31",
    "sg:postcode":"9220",
    "sg:province":"Oost-Vlaanderen",
    "sg:tags":[
        "l\u00e9gumes"
    ],
    "wof:name":"Lionel Willaert",
    "wof:placetype":"venue"
},
  "geometry": {"coordinates":[4.1616311073,51.0985565186],"type":"Point"}
}