{
  "type": "Feature",
  "properties": {
    "addr:full":"Turnhoutsebaan 97 Schilde Antwerpen 2970",
    "addr:housenumber":"97",
    "addr:postcode":"2970",
    "addr:street":"Turnhoutsebaan",
    "iso:country":"BE",
    "sg:address":"Turnhoutsebaan 97",
    "sg:city":"Schilde",
    "sg:orig_category":"Disneyland Parijs Reisbureaus",
    "sg:phone":"+32 3 383 64 64",
    "sg:postcode":"2970",
    "sg:province":"Antwerpen",
    "wof:name":"Schoeters Autocars Reizen",
    "wof:placetype":"venue"
},
  "geometry": {"coordinates":[4.57751894,51.2386436462],"type":"Point"}
}