{
  "type": "Feature",
  "properties": {
    "addr:full":"Avenue Gustave Latinis 136-138 Brussel/bruxelles Bruxelles-Capitale 1030",
    "addr:postcode":"136-138;/ bruxelles;1030",
    "addr:street":"Avenue Gustave Latinis",
    "iso:country":"BE",
    "sg:address":"Avenue Gustave Latinis 136-138",
    "sg:city":"Brussel/bruxelles",
    "sg:orig_category":"Dakwerken Woningbouw",
    "sg:phone":"+32 2 216 37 37",
    "sg:postcode":"1030",
    "sg:province":"Bruxelles-Capitale",
    "wof:name":"Toiture Express",
    "wof:placetype":"venue"
},
  "geometry": {"coordinates":[4.3920879364,50.8627128601],"type":"Point"}
}