{
  "type": "Feature",
  "properties": {
    "addr:full":"Rue De L'eglise 8 Les Bons Villers (r\u00eaves) Hainaut 6210",
    "addr:housenumber":"8",
    "addr:postcode":"6210",
    "addr:street":"Rue De L'Eglise",
    "iso:country":"BE",
    "sg:address":"Rue De L'eglise 8",
    "sg:city":"Les Bons Villers (r\u00eaves)",
    "sg:classifiers":[
        {
            "category":"Organizations",
            "subcategory":"Professional Association",
            "type":"Services"
        }
    ],
    "sg:phone":"+32 71 85 15 78",
    "sg:postcode":"6210",
    "sg:province":"Hainaut",
    "sg:tags":[
        "organisation",
        "seminar"
    ],
    "wof:name":"Enclume (l')",
    "wof:placetype":"venue"
},
  "geometry": {"coordinates":[4.4162359238,50.5379676819],"type":"Point"}
}