{
  "type": "Feature",
  "properties": {
    "addr:full":"Rue Laurent 1c Saint-ghislain Hainaut 7333",
    "addr:housenumber":"1c",
    "addr:postcode":"7333",
    "addr:street":"Rue Laurent;Hainaut",
    "iso:country":"BE",
    "sg:address":"Rue Laurent 1c",
    "sg:city":"Saint-ghislain",
    "sg:orig_category":"Bloemen and planten",
    "sg:phone":"+32 65 64 47 80",
    "sg:postcode":"7333",
    "sg:province":"Hainaut",
    "wof:name":"Fleurs Cr\u00c9ation",
    "wof:placetype":"venue"
},
  "geometry": {"coordinates":[3.8111400604,50.4655151367],"type":"Point"}
}