{
  "type": "Feature",
  "properties": {
    "iso:country":"BE",
    "sg:address":"Leemkuilstraat 12",
    "sg:city":"Maasmechelen (opgrimbie)",
    "sg:classifiers":[
        {
            "category":"Professional",
            "type":"Services"
        }
    ],
    "sg:phone":"+32 89 77 88 11",
    "sg:postcode":"3630",
    "sg:province":"Limburg",
    "sg:tags":[
        "industrial",
        "work",
        "-",
        "maintenance"
    ],
    "wof:name":"T. R. Engineering Nv",
    "wof:placetype":"venue"
},
  "geometry": {"coordinates":[5.6961350441,50.963848114],"type":"Point"}
}