{
  "type": "Feature",
  "properties": {
    "iso:country":"BE",
    "sg:address":"Leopold Ii Laan 232-238",
    "sg:city":"Koksijde (oostduinkerke)",
    "sg:classifiers":[
        {
            "category":"Real Estate",
            "subcategory":"Developer",
            "type":"Services"
        }
    ],
    "sg:phone":"+32 58 51 06 06",
    "sg:postcode":"8670",
    "sg:province":"West-Vlaanderen",
    "sg:tags":[
        "project"
    ],
    "wof:name":"Coast Construction Nv",
    "wof:placetype":"venue"
},
  "geometry": {"coordinates":[2.6735379696,51.1297607422],"type":"Point"}
}