{
  "type": "Feature",
  "properties": {
    "addr:full":"Jezus Eiklaan 86 Tervuren Vlaams-Brabant 3080",
    "addr:housenumber":"86",
    "addr:postcode":"3080",
    "addr:street":"Eiklaan",
    "iso:country":"BE",
    "sg:address":"Jezus Eiklaan 86",
    "sg:city":"Tervuren",
    "sg:classifiers":[
        {
            "category":"Insurance",
            "subcategory":"Insurance Agent",
            "type":"Services"
        }
    ],
    "sg:phone":"+32 2 767 49 50",
    "sg:postcode":"3080",
    "sg:province":"Vlaams-Brabant",
    "sg:tags":[
        "broker"
    ],
    "wof:name":"Veredan Bvba",
    "wof:placetype":"venue"
},
  "geometry": {"coordinates":[4.5007238388,50.816783905],"type":"Point"}
}