{
  "type": "Feature",
  "properties": {
    "addr:full":"Waterleidingsstraat 3b Heusden-zolder Limburg 3550",
    "addr:housenumber":"3b",
    "addr:postcode":"3550",
    "addr:street":"Waterleidingsstraat",
    "iso:country":"BE",
    "sg:address":"Waterleidingsstraat 3b",
    "sg:city":"Heusden-zolder",
    "sg:classifiers":[
        {
            "category":"Personal",
            "subcategory":"Beauty Salon",
            "type":"Services"
        }
    ],
    "sg:phone":"+32 11 57 19 73",
    "sg:postcode":"3550",
    "sg:province":"Limburg",
    "sg:tags":[
        "de",
        "coiffure"
    ],
    "wof:name":"Hairmode R.c.",
    "wof:placetype":"venue"
},
  "geometry": {"coordinates":[5.3021807671,51.0395812988],"type":"Point"}
}