{
  "type": "Feature",
  "properties": {
    "iso:country":"BE",
    "sg:address":"9200",
    "sg:city":"Dendermonde",
    "sg:orig_category":"Sleepy. Sleepy. Meubles D\u00e9taillants, Am\u00e9nagement de B\u00e2timents et de Cuisines",
    "sg:phone":"+32 52 21 45 51",
    "sg:postcode":"9200",
    "sg:province":"Oost-Vlaanderen",
    "wof:name":"Sleepy Dendermonde",
    "wof:placetype":"venue"
},
  "geometry": {"coordinates":[4.0983099937,51.0315208435],"type":"Point"}
}