{
  "type": "Feature",
  "properties": {
    "addr:full":"Boulevard D'avroy 63 Li\u00c8ge Li\u00e8ge 4000",
    "addr:housenumber":"63",
    "addr:postcode":"4000",
    "addr:street":"Boulevard D'Avroy",
    "iso:country":"BE",
    "sg:address":"Boulevard D'avroy 63",
    "sg:city":"Li\u00c8ge",
    "sg:classifiers":[
        {
            "category":"Insurance",
            "subcategory":"Life Insurance",
            "type":"Services"
        }
    ],
    "sg:phone":"+32 4 221 71 11",
    "sg:postcode":"4000",
    "sg:province":"Li\u00e8ge",
    "sg:tags":[
        "assurance"
    ],
    "wof:name":"P&v",
    "wof:placetype":"venue"
},
  "geometry": {"coordinates":[5.5686597824,50.6368408203],"type":"Point"}
}