{
  "type": "Feature",
  "properties": {
    "addr:full":"Assenois 1 Vaux-sur-s\u00fbre (hompr\u00e9) Luxembourg 6640",
    "addr:housenumber":"1",
    "addr:postcode":"6640",
    "addr:street":"Assenois",
    "iso:country":"BE",
    "sg:address":"Assenois 1",
    "sg:city":"Vaux-sur-s\u00fbre (hompr\u00e9)",
    "sg:classifiers":[
        {
            "category":"Parking",
            "subcategory":"Lot",
            "type":"Transportation"
        }
    ],
    "sg:phone":"+32 61 26 64 27",
    "sg:postcode":"6640",
    "sg:province":"Luxembourg",
    "sg:tags":[
        "parking-places",
        "laying-out"
    ],
    "wof:name":"Guissard B",
    "wof:placetype":"venue"
},
  "geometry": {"coordinates":[5.5671000481,49.91065979],"type":"Point"}
}