{
  "type": "Feature",
  "properties": {
    "iso:country":"BE",
    "sg:address":"Rue F Nicolay 180",
    "sg:city":"Saint-nicolas",
    "sg:orig_category":"Informaticaconsulenten",
    "sg:phone":"+32 4 254 31 31",
    "sg:postcode":"4420",
    "sg:province":"Li\u00e8ge",
    "wof:name":"Darchambleau P",
    "wof:placetype":"venue"
},
  "geometry": {"coordinates":[5.5399169922,50.6307029724],"type":"Point"}
}