{
  "type": "Feature",
  "properties": {
    "addr:full":"Alfons Smetsplein 11 Leuven Vlaams-Brabant 3000",
    "addr:housenumber":"11",
    "addr:postcode":"3000",
    "addr:street":"Alfons Smetsplein",
    "iso:country":"BE",
    "sg:address":"Alfons Smetsplein 11",
    "sg:city":"Leuven",
    "sg:classifiers":[
        {
            "category":"Restaurant",
            "type":"Food & Drink"
        }
    ],
    "sg:phone":"+32 16 29 79 17",
    "sg:postcode":"3000",
    "sg:province":"Vlaams-Brabant",
    "wof:name":"De Rode Kreeft",
    "wof:placetype":"venue"
},
  "geometry": {"coordinates":[4.7041230202,50.8772201538],"type":"Point"}
}