{
  "type": "Feature",
  "properties": {
    "addr:full":"Chemin De Saint-ghislain 234 Chi\u00e8vres Hainaut 7950",
    "addr:housenumber":"234",
    "addr:postcode":"7950",
    "addr:street":"Chemin De Saint-Ghislain;Hainaut",
    "iso:country":"BE",
    "sg:address":"Chemin De Saint-ghislain 234",
    "sg:city":"Chi\u00e8vres",
    "sg:classifiers":[
        {
            "category":"Personal",
            "subcategory":"Beauty Salon",
            "type":"Services"
        }
    ],
    "sg:phone":"+32 68 65 73 54",
    "sg:postcode":"7950",
    "sg:province":"Hainaut",
    "sg:tags":[
        "lady",
        "-",
        "hairdressing"
    ],
    "wof:name":"Jacqueline",
    "wof:placetype":"venue"
},
  "geometry": {"coordinates":[3.806210041,50.5593299866],"type":"Point"}
}