{
  "type": "Feature",
  "properties": {
    "addr:full":"Zebrastraat 222 Gent Oost-Vlaanderen 9000",
    "addr:housenumber":"222",
    "addr:postcode":"9000",
    "addr:street":"Zebrastraat;Oost-Vlaanderen",
    "iso:country":"BE",
    "sg:address":"Zebrastraat 222",
    "sg:city":"Gent",
    "sg:classifiers":[
        {
            "category":"Professional",
            "type":"Services"
        }
    ],
    "sg:phone":"+32 9 233 21 07",
    "sg:postcode":"9000",
    "sg:province":"Oost-Vlaanderen",
    "sg:tags":[
        "surveyor",
        "-",
        "valuer"
    ],
    "wof:name":"Bureau Delforche Bvba",
    "wof:placetype":"venue"
},
  "geometry": {"coordinates":[3.7345559597,51.0402336121],"type":"Point"}
}