{
  "type": "Feature",
  "properties": {
    "iso:country":"BE",
    "sg:address":"Rue Ferrer 119",
    "sg:city":"Mons (cuesmes)",
    "sg:classifiers":[
        {
            "category":"Building & Trades",
            "subcategory":"Equipment Rental",
            "type":"Services"
        }
    ],
    "sg:phone":"+32 65 35 44 23",
    "sg:postcode":"7033",
    "sg:province":"Hainaut",
    "sg:tags":[
        "tableware",
        "-"
    ],
    "wof:name":"Sautois",
    "wof:placetype":"venue"
},
  "geometry": {"coordinates":[3.9253261089,50.4366378784],"type":"Point"}
}