{
  "type": "Feature",
  "properties": {
    "iso:country":"BE",
    "sg:address":"Hoge Heirweg 30",
    "sg:city":"Sint-martens-latem",
    "sg:classifiers":[
        {
            "category":"Professional",
            "type":"Services"
        }
    ],
    "sg:phone":"+32 9 281 00 83",
    "sg:postcode":"9830",
    "sg:province":"Oost-Vlaanderen",
    "sg:tags":[
        "forestry",
        "agriculture",
        "-",
        "auctioneer"
    ],
    "wof:name":"Experflora Bvba",
    "wof:placetype":"venue"
},
  "geometry": {"coordinates":[3.6348860264,51.01304245],"type":"Point"}
}