{
  "type": "Feature",
  "properties": {
    "addr:full":"Hoevensebaan 137 Kapellen Antwerpen 2950",
    "addr:housenumber":"137",
    "addr:postcode":"2950",
    "addr:street":"Hoevensebaan",
    "iso:country":"BE",
    "sg:address":"Hoevensebaan 137",
    "sg:city":"Kapellen",
    "sg:classifiers":[
        {
            "category":"Building & Trades",
            "subcategory":"Pest Control",
            "type":"Services"
        }
    ],
    "sg:phone":"+32 3 295 70 63",
    "sg:postcode":"2950",
    "sg:province":"Antwerpen",
    "sg:tags":[
        "painting",
        "contractor"
    ],
    "wof:name":"Effekt",
    "wof:placetype":"venue"
},
  "geometry": {"coordinates":[4.4234580994,51.3124885559],"type":"Point"}
}