{
  "type": "Feature",
  "properties": {
    "iso:country":"BE",
    "sg:address":"Bovenbosstraat 59",
    "sg:city":"Oud-heverlee",
    "sg:orig_category":"Avocats and conseillers juridiques",
    "sg:phone":"+32 16 40 31 95",
    "sg:postcode":"3053",
    "sg:province":"Vlaams-Brabant",
    "wof:name":"A.m. Huygens",
    "wof:placetype":"venue"
},
  "geometry": {"coordinates":[4.7132511139,50.8333854675],"type":"Point"}
}