{
  "type": "Feature",
  "properties": {
    "iso:country":"BE",
    "sg:address":"Heiplasstraat 24",
    "sg:city":"Lede",
    "sg:classifiers":[
        {
            "category":"Building & Trades",
            "subcategory":"Construction",
            "type":"Services"
        }
    ],
    "sg:phone":"+32 53 80 82 49",
    "sg:postcode":"9340",
    "sg:province":"Oost-Vlaanderen",
    "sg:tags":[
        "carpenter"
    ],
    "wof:name":"Gudi Bvba",
    "wof:placetype":"venue"
},
  "geometry": {"coordinates":[3.9769890308,50.9804496765],"type":"Point"}
}