{
  "type": "Feature",
  "properties": {
    "iso:country":"BE",
    "sg:address":"Koesteertweg 6",
    "sg:city":"Aalst (moorsel)",
    "sg:classifiers":[
        {
            "category":"Parking",
            "subcategory":"Lot",
            "type":"Transportation"
        }
    ],
    "sg:phone":"+32 53 77 03 69",
    "sg:postcode":"9310",
    "sg:province":"Oost-Vlaanderen",
    "sg:tags":[
        "parking-places",
        "laying-out"
    ],
    "wof:name":"De Petter J",
    "wof:placetype":"venue"
},
  "geometry": {"coordinates":[4.1113729477,50.9477539062],"type":"Point"}
}