{
  "type": "Feature",
  "properties": {
    "addr:full":"Kleemstraat 73 Roosdaal Vlaams-Brabant 1760",
    "addr:housenumber":"73",
    "addr:postcode":"1760",
    "addr:street":"Kleemstraat",
    "iso:country":"BE",
    "sg:address":"Kleemstraat 73",
    "sg:city":"Roosdaal",
    "sg:orig_category":"Fruitteelt",
    "sg:phone":"+32 54 33 69 57",
    "sg:postcode":"1760",
    "sg:province":"Vlaams-Brabant",
    "wof:name":"Gilbert Evenepoel",
    "wof:placetype":"venue"
},
  "geometry": {"coordinates":[4.0744271278,50.8435707092],"type":"Point"}
}