{
  "type": "Feature",
  "properties": {
    "addr:full":"Dorpsstraat 29 As Limburg 3665",
    "addr:housenumber":"29",
    "addr:postcode":"3665",
    "addr:street":"Dorpsstraat",
    "iso:country":"BE",
    "sg:address":"Dorpsstraat 29",
    "sg:city":"As",
    "sg:classifiers":[
        {
            "category":"Shopping",
            "subcategory":"Clothing, Apparel, & Fashions",
            "type":"Retail Goods"
        }
    ],
    "sg:phone":"+32 89 65 70 40",
    "sg:postcode":"3665",
    "sg:province":"Limburg",
    "sg:tags":[
        "clothing",
        "-",
        "motorbike",
        "equipment"
    ],
    "wof:name":"Berger T",
    "wof:placetype":"venue"
},
  "geometry": {"coordinates":[5.5861330032,51.0075111389],"type":"Point"}
}