{
  "type": "Feature",
  "properties": {
    "addr:full":"Bentstraat 60 Diepenbeek Limburg 3590",
    "addr:housenumber":"60",
    "addr:postcode":"3590",
    "addr:street":"Bentstraat",
    "iso:country":"BE",
    "sg:address":"Bentstraat 60",
    "sg:city":"Diepenbeek",
    "sg:classifiers":[
        {
            "category":"Autos & Motor Vehicles",
            "subcategory":"Automobile Sales",
            "type":"Retail Goods"
        }
    ],
    "sg:phone":"+32 11 33 38 88",
    "sg:postcode":"3590",
    "sg:province":"Limburg",
    "sg:tags":[
        "car",
        "used",
        "-"
    ],
    "wof:name":"Garage Surinx Geert",
    "wof:placetype":"venue"
},
  "geometry": {"coordinates":[5.4510788918,50.9044723511],"type":"Point"}
}