{
  "type": "Feature",
  "properties": {
    "addr:full":"Rue G\u00c9n\u00c9ral Lotz 103b7 Ukkel/uccle Bruxelles-Capitale 1180",
    "addr:housenumber":"103b7",
    "addr:postcode":"1180",
    "addr:street":"Rue Ge\u0301Ne\u0301Ral Lotz;/",
    "iso:country":"BE",
    "sg:address":"Rue G\u00c9n\u00c9ral Lotz 103b7",
    "sg:city":"Ukkel/uccle",
    "sg:orig_category":"M\u00e9decins and sp\u00e9cialistes",
    "sg:phone":"+32 2 344 77 79",
    "sg:postcode":"1180",
    "sg:province":"Bruxelles-Capitale",
    "wof:name":"E. Littemann",
    "wof:placetype":"venue"
},
  "geometry": {"coordinates":[4.3586797714,50.8116950989],"type":"Point"}
}