{
  "type": "Feature",
  "properties": {
    "addr:full":"Kloosterstraat 1 Bocholt Limburg 3950",
    "addr:housenumber":"1",
    "addr:postcode":"3950",
    "addr:street":"Kloosterstraat",
    "iso:country":"BE",
    "sg:address":"Kloosterstraat 1",
    "sg:city":"Bocholt",
    "sg:orig_category":"Enseignement maternel and primaire",
    "sg:phone":"+32 89 46 28 32",
    "sg:postcode":"3950",
    "sg:province":"Limburg",
    "wof:name":"Vrije Basisschool",
    "wof:placetype":"venue"
},
  "geometry": {"coordinates":[5.5824952126,51.1731567383],"type":"Point"}
}