{
  "type": "Feature",
  "properties": {
    "iso:country":"BE",
    "sg:address":"Boulevard Du Souverain 348 Box 54",
    "sg:city":"Bruxelles (auderghem)",
    "sg:classifiers":[
        {
            "category":"Professional",
            "subcategory":"Management & Consulting",
            "type":"Services"
        }
    ],
    "sg:phone":"+32 2 675 56 00",
    "sg:postcode":"1160",
    "sg:province":"Bruxelles-Capitale",
    "sg:tags":[
        "consultant",
        "relation",
        "public"
    ],
    "wof:name":"Ecopublic Sprl",
    "wof:placetype":"venue"
},
  "geometry": {"coordinates":[4.4299402237,50.820640564],"type":"Point"}
}