{
  "type": "Feature",
  "properties": {
    "iso:country":"BE",
    "sg:address":"Meerstraat 47",
    "sg:city":"Londerzeel",
    "sg:classifiers":[
        {
            "category":"Health Services",
            "subcategory":"Dentist",
            "type":"Services"
        }
    ],
    "sg:phone":"+32 52 30 95 20",
    "sg:postcode":"1840",
    "sg:province":"Vlaams-Brabant",
    "wof:name":"Steenackers Walter",
    "wof:placetype":"venue"
},
  "geometry": {"coordinates":[4.3054280281,51.0058631897],"type":"Point"}
}