{
  "type": "Feature",
  "properties": {
    "addr:full":"Rue D'aulne 2 Ottignies-louvain-la-neuve (louvain-la-neuve) Brabant Wallon 1348",
    "addr:housenumber":"2",
    "addr:postcode":"1348",
    "addr:street":"Rue D'Aulne",
    "iso:country":"BE",
    "sg:address":"Rue D'aulne 2",
    "sg:city":"Ottignies-louvain-la-neuve (louvain-la-neuve)",
    "sg:classifiers":[
        {
            "category":"Health Services",
            "subcategory":"Health Practitioner",
            "type":"Services"
        }
    ],
    "sg:phone":"+32 479 59 58 83",
    "sg:postcode":"1348",
    "sg:province":"Brabant Wallon",
    "sg:tags":[
        "physiotherapist"
    ],
    "wof:name":"Carlier Kristel",
    "wof:placetype":"venue"
},
  "geometry": {"coordinates":[4.6140341759,50.6741027832],"type":"Point"}
}