{
  "type": "Feature",
  "properties": {
    "addr:full":"Rue Du Moh\u00c9ry 39 Hannut Li\u00e8ge 4280",
    "addr:housenumber":"39",
    "addr:postcode":"4280",
    "addr:street":"Rue Du Mohe\u0301Ry",
    "iso:country":"BE",
    "sg:address":"Rue Du Moh\u00c9ry 39",
    "sg:city":"Hannut",
    "sg:classifiers":[
        {
            "category":"Cafe",
            "type":"Food & Drink"
        }
    ],
    "sg:phone":"+32 19 69 72 27",
    "sg:postcode":"4280",
    "sg:province":"Li\u00e8ge",
    "sg:tags":[
        "caf\u00e9s"
    ],
    "wof:name":"Nelly Biname",
    "wof:placetype":"venue"
},
  "geometry": {"coordinates":[5.0688581467,50.6209602356],"type":"Point"}
}