{
  "type": "Feature",
  "properties": {
    "addr:full":"Solhofdreef 27 Aartselaar Antwerpen 2630",
    "addr:housenumber":"27",
    "addr:postcode":"2630",
    "addr:street":"Solhofdreef",
    "iso:country":"BE",
    "sg:address":"Solhofdreef 27",
    "sg:city":"Aartselaar",
    "sg:classifiers":[
        {
            "category":"Shopping",
            "subcategory":"Clothing, Apparel, & Fashions",
            "type":"Retail Goods"
        }
    ],
    "sg:phone":"+32 3 877 39 79",
    "sg:postcode":"2630",
    "sg:province":"Antwerpen",
    "sg:tags":[
        "v\u00eatements",
        "pour",
        "dame"
    ],
    "wof:name":"Scarlet",
    "wof:placetype":"venue"
},
  "geometry": {"coordinates":[4.3969559669,51.134929657],"type":"Point"}
}