{
  "type": "Feature",
  "properties": {
    "addr:full":"Lessensestraat 137 Geraardsbergen Oost-Vlaanderen 9500",
    "addr:housenumber":"137",
    "addr:postcode":"9500",
    "addr:street":"Lessensestraat",
    "iso:country":"BE",
    "sg:address":"Lessensestraat 137",
    "sg:city":"Geraardsbergen",
    "sg:orig_category":"Tabac. Journaux",
    "sg:phone":"+32 54 41 15 75",
    "sg:postcode":"9500",
    "sg:province":"Oost-Vlaanderen",
    "wof:name":"Huis Matthys",
    "wof:placetype":"venue"
},
  "geometry": {"coordinates":[3.872729063,50.7685127258],"type":"Point"}
}