{
  "type": "Feature",
  "properties": {
    "iso:country":"BE",
    "sg:address":"Ripipiabergstraat 22",
    "sg:city":"Hamme (moerzeke)",
    "sg:classifiers":[
        {
            "category":"Freight",
            "type":"Transportation"
        }
    ],
    "sg:phone":"+32 52 48 32 00",
    "sg:postcode":"9220",
    "sg:province":"Oost-Vlaanderen",
    "sg:tags":[
        "-",
        "transport"
    ],
    "wof:name":"De Prez-de Prins L",
    "wof:placetype":"venue"
},
  "geometry": {"coordinates":[4.1376290321,51.0983505249],"type":"Point"}
}