{
  "type": "Feature",
  "properties": {
    "iso:country":"BE",
    "sg:address":"Rue Ruisseau Des Forges 48",
    "sg:city":"Florennes",
    "sg:classifiers":[
        {
            "category":"Health Services",
            "subcategory":"Health Practitioner",
            "type":"Services"
        }
    ],
    "sg:phone":"+32 71 68 85 41",
    "sg:postcode":"5620",
    "sg:province":"Namur",
    "sg:tags":[
        "physiotherapist"
    ],
    "wof:name":"Lasseaux M",
    "wof:placetype":"venue"
},
  "geometry": {"coordinates":[4.6022620201,50.252494812],"type":"Point"}
}