{
  "type": "Feature",
  "properties": {
    "addr:full":"Rue Fransman 8 Bruxelles Bruxelles-Capitale 1020",
    "addr:housenumber":"8",
    "addr:postcode":"1020",
    "addr:street":"Rue Fransman",
    "iso:country":"BE",
    "sg:address":"Rue Fransman 8",
    "sg:city":"Bruxelles",
    "sg:classifiers":[
        {
            "category":"Shopping",
            "subcategory":"Clothing, Apparel, & Fashions",
            "type":"Retail Goods"
        }
    ],
    "sg:phone":"+32 2 428 66 89",
    "sg:postcode":"1020",
    "sg:province":"Bruxelles-Capitale",
    "sg:tags":[
        "boutique"
    ],
    "wof:name":"Chris (boutique)",
    "wof:placetype":"venue"
},
  "geometry": {"coordinates":[4.3463392258,50.8776855469],"type":"Point"}
}