{
  "type": "Feature",
  "properties": {
    "iso:country":"BE",
    "sg:address":"Bruggestraat 20",
    "sg:city":"Ruiselede",
    "sg:classifiers":[
        {
            "category":"Shopping",
            "subcategory":"Shoes",
            "type":"Retail Goods"
        }
    ],
    "sg:phone":"+32 51 68 85 19",
    "sg:postcode":"8755",
    "sg:province":"West-Vlaanderen",
    "sg:tags":[
        "slipper",
        "-"
    ],
    "wof:name":"Nicque Schoenen",
    "wof:placetype":"venue"
},
  "geometry": {"coordinates":[3.3951079845,51.0422325134],"type":"Point"}
}