{
  "type": "Feature",
  "properties": {
    "addr:full":"Rue Omer Lef\u00c8vre 18 La Louviere Hainaut 7100",
    "addr:housenumber":"18",
    "addr:postcode":"7100",
    "addr:street":"Rue Omer Lefe\u0300Vre",
    "iso:country":"BE",
    "sg:address":"Rue Omer Lef\u00c8vre 18",
    "sg:city":"La Louviere",
    "sg:orig_category":"M\u00e9decins and sp\u00e9cialistes",
    "sg:phone":"+32 64 22 53 89",
    "sg:postcode":"7100",
    "sg:province":"Hainaut",
    "wof:name":"Ph. Andrien",
    "wof:placetype":"venue"
},
  "geometry": {"coordinates":[4.1937999725,50.4754257202],"type":"Point"}
}