{
  "type": "Feature",
  "properties": {
    "iso:country":"BE",
    "sg:address":"Rue De Gosselies 175",
    "sg:city":"Courcelles",
    "sg:orig_category":"Maisons de repos and r\u00e9sidences. Traitements param\u00e9dicaux",
    "sg:phone":"+32 71 45 11 42",
    "sg:postcode":"6183",
    "sg:province":"Hainaut",
    "wof:name":"Home Du Parc",
    "wof:placetype":"venue"
},
  "geometry": {"coordinates":[4.3439102173,50.4629707336],"type":"Point"}
}