{
  "type": "Feature",
  "properties": {
    "addr:full":"Grauwe Broedersstraat 38 Diksmuide West-Vlaanderen 8600",
    "addr:housenumber":"38",
    "addr:postcode":"8600",
    "addr:street":"Grauwe Broedersstraat",
    "iso:country":"BE",
    "sg:address":"Grauwe Broedersstraat 38",
    "sg:city":"Diksmuide",
    "sg:orig_category":"Journaux. Epiceries",
    "sg:phone":"+32 51 50 26 85",
    "sg:postcode":"8600",
    "sg:province":"West-Vlaanderen",
    "wof:name":"Spar",
    "wof:placetype":"venue"
},
  "geometry": {"coordinates":[2.8687698841,51.0368041992],"type":"Point"}
}