{
  "type": "Feature",
  "properties": {
    "addr:full":"Provinciale Stw 131 Hemiksem Antwerpen 2620",
    "addr:housenumber":"131",
    "addr:postcode":"2620",
    "addr:street":"Provinciale Stw",
    "iso:country":"BE",
    "sg:address":"Provinciale Stw 131",
    "sg:city":"Hemiksem",
    "sg:orig_category":"Kapsalons",
    "sg:phone":"+32 3 289 00 02",
    "sg:postcode":"2620",
    "sg:province":"Antwerpen",
    "wof:name":"L&n Hairstyling",
    "wof:placetype":"venue"
},
  "geometry": {"coordinates":[4.3382577896,51.1414794922],"type":"Point"}
}