{
  "type": "Feature",
  "properties": {
    "iso:country":"BE",
    "sg:address":"Poel 18",
    "sg:city":"Gent",
    "sg:orig_category":"Eclairage et \u00e9quipements du foyer. Bijouteries and horlogeries",
    "sg:phone":"+32 9 224 09 76",
    "sg:postcode":"9000",
    "sg:province":"Oost-Vlaanderen",
    "wof:name":"Huis Avalon",
    "wof:placetype":"venue"
},
  "geometry": {"coordinates":[3.7116398811,51.0340957642],"type":"Point"}
}