{
  "type": "Feature",
  "properties": {
    "addr:full":"Herentalsebaan 62 Wommelgem Antwerpen 2160",
    "addr:housenumber":"62",
    "addr:postcode":"2160",
    "addr:street":"Herentalsebaan",
    "iso:country":"BE",
    "sg:address":"Herentalsebaan 62",
    "sg:city":"Wommelgem",
    "sg:classifiers":[
        {
            "category":"Fast Food",
            "type":"Food & Drink"
        }
    ],
    "sg:phone":"+32 3 322 63 08",
    "sg:postcode":"2160",
    "sg:province":"Antwerpen",
    "sg:tags":[
        "fried",
        "stand",
        "potato"
    ],
    "wof:name":"Kruispunt",
    "wof:placetype":"venue"
},
  "geometry": {"coordinates":[4.5027999878,51.1958312988],"type":"Point"}
}