{
  "type": "Feature",
  "properties": {
    "iso:country":"BE",
    "sg:address":"Mechelsesteenweg 22",
    "sg:city":"Kampenhout",
    "sg:orig_category":"Voertuigen",
    "sg:phone":"+32 16 60 29 21",
    "sg:postcode":"1910",
    "sg:province":"Vlaams-Brabant",
    "wof:name":"Junior Cars",
    "wof:placetype":"venue"
},
  "geometry": {"coordinates":[4.5892038345,50.9584197998],"type":"Point"}
}