{
  "type": "Feature",
  "properties": {
    "iso:country":"BE",
    "sg:address":"Place Roi Baudouin 11ba",
    "sg:city":"Floreffe",
    "sg:classifiers":[
        {
            "category":"Fast Food",
            "type":"Food & Drink"
        }
    ],
    "sg:phone":"+32 81 45 05 55",
    "sg:postcode":"5150",
    "sg:province":"Namur",
    "sg:tags":[
        "\u00c0",
        "emporter",
        "restaurants"
    ],
    "wof:name":"Pizzeria De La Place",
    "wof:placetype":"venue"
},
  "geometry": {"coordinates":[4.7598891258,50.4357185364],"type":"Point"}
}