{
  "type": "Feature",
  "properties": {
    "addr:full":"Voldersstraat 203 Geraardsbergen Oost-Vlaanderen 9500",
    "addr:housenumber":"203",
    "addr:postcode":"9500",
    "addr:street":"Voldersstraat",
    "iso:country":"BE",
    "sg:address":"Voldersstraat 203",
    "sg:city":"Geraardsbergen",
    "sg:orig_category":"Boekhouders Verlichting and huishoudartikelen",
    "sg:phone":"+32 54 41 52 83",
    "sg:postcode":"9500",
    "sg:province":"Oost-Vlaanderen",
    "wof:name":"'t Kleipotje",
    "wof:placetype":"venue"
},
  "geometry": {"coordinates":[3.8828001022,50.7776184082],"type":"Point"}
}