{
  "type": "Feature",
  "properties": {
    "addr:full":"Onze-lieve-vrouwstraat 163 Heusden-zolder Limburg 3550",
    "addr:housenumber":"163",
    "addr:postcode":"3550",
    "addr:street":"Onze-Lieve-Vrouwstraat",
    "iso:country":"BE",
    "sg:address":"Onze-lieve-vrouwstraat 163",
    "sg:city":"Heusden-zolder",
    "sg:orig_category":"Elektrische installaties voor woningen Huishoudapparaten, televisies and radio's Industri\u00eble elektri",
    "sg:phone":"+32 11 53 84 49",
    "sg:postcode":"3550",
    "sg:province":"Limburg",
    "wof:name":"Jurgen Hetzheim",
    "wof:placetype":"venue"
},
  "geometry": {"coordinates":[5.2711777687,51.0114898682],"type":"Point"}
}