{
  "type": "Feature",
  "properties": {
    "iso:country":"BE",
    "sg:address":"Clos Du Grand Feu 3",
    "sg:city":"Ottignies-louvain-la-neuve",
    "sg:orig_category":"Boekenuitgeverijen",
    "sg:phone":"+32 10 41 17 46",
    "sg:postcode":"1340",
    "sg:province":"Brabant Wallon",
    "wof:name":"Production",
    "wof:placetype":"venue"
},
  "geometry": {"coordinates":[4.5872559547,50.6638755798],"type":"Point"}
}