{
  "type": "Feature",
  "properties": {
    "addr:full":"Groeshoeve 18 Nijlen Antwerpen 2560",
    "addr:housenumber":"18",
    "addr:postcode":"2560",
    "addr:street":"Groeshoeve",
    "iso:country":"BE",
    "sg:address":"Groeshoeve 18",
    "sg:city":"Nijlen",
    "sg:orig_category":"Elektrische installaties voor woningen",
    "sg:phone":"+32 3 480 61 29",
    "sg:postcode":"2560",
    "sg:province":"Antwerpen",
    "wof:name":"Coppens Electro",
    "wof:placetype":"venue"
},
  "geometry": {"coordinates":[4.6255087852,51.1530418396],"type":"Point"}
}