{
  "type": "Feature",
  "properties": {
    "addr:full":"Rue Child\u00c9ric 23 Tournai Hainaut 7500",
    "addr:housenumber":"23",
    "addr:postcode":"7500",
    "addr:street":"Rue Childe\u0301Ric",
    "iso:country":"BE",
    "sg:address":"Rue Child\u00c9ric 23",
    "sg:city":"Tournai",
    "sg:orig_category":"M\u00e9decins and sp\u00e9cialistes",
    "sg:phone":"+32 69 22 42 07",
    "sg:postcode":"7500",
    "sg:province":"Hainaut",
    "wof:name":"A.m. Vandevelde",
    "wof:placetype":"venue"
},
  "geometry": {"coordinates":[3.3948121071,50.6098861694],"type":"Point"}
}