{
  "type": "Feature",
  "properties": {
    "addr:full":"Rue Henri Van Hamme 1a Bruxelles (evere) Bruxelles-Capitale 1140",
    "addr:housenumber":"1a",
    "addr:postcode":"1140",
    "addr:street":"Rue Henri Van Hamme",
    "iso:country":"BE",
    "sg:address":"Rue Henri Van Hamme 1a",
    "sg:city":"Bruxelles (evere)",
    "sg:classifiers":[
        {
            "category":"Shopping",
            "subcategory":"Computers & Home Electronics",
            "type":"Retail Goods"
        }
    ],
    "sg:phone":"+32 2 242 65 23",
    "sg:postcode":"1140",
    "sg:province":"Bruxelles-Capitale",
    "sg:tags":[
        "telephone",
        "apparatus",
        "accessory"
    ],
    "wof:name":"Evere Phone",
    "wof:placetype":"venue"
},
  "geometry": {"coordinates":[4.392824173,50.8759689331],"type":"Point"}
}