{
  "type": "Feature",
  "properties": {
    "iso:country":"BE",
    "sg:address":"Rue Du Midi 90",
    "sg:city":"Brussel/bruxelles",
    "sg:orig_category":"Fleurs and plantes",
    "sg:phone":"+32 2 513 99 96",
    "sg:postcode":"1000",
    "sg:province":"Bruxelles-Capitale",
    "wof:name":"Caloggero Fiori",
    "wof:placetype":"venue"
},
  "geometry": {"coordinates":[4.3491430283,50.8453788757],"type":"Point"}
}