{
  "type": "Feature",
  "properties": {
    "iso:country":"BE",
    "sg:address":"Professor Scharp\u00e9laan 236",
    "sg:city":"Begijnendijk (betekom)",
    "sg:classifiers":[
        {
            "category":"Building & Trades",
            "subcategory":"Construction",
            "type":"Services"
        }
    ],
    "sg:phone":"+32 16 53 61 22",
    "sg:postcode":"3130",
    "sg:province":"Vlaams-Brabant",
    "sg:tags":[
        "carpenter"
    ],
    "wof:name":"Luyten P",
    "wof:placetype":"venue"
},
  "geometry": {"coordinates":[4.7884349823,51.0049324036],"type":"Point"}
}