{
  "type": "Feature",
  "properties": {
    "addr:full":"Debruynehoek 16 Koekelare West-Vlaanderen 8680",
    "addr:housenumber":"16",
    "addr:postcode":"8680",
    "addr:street":"Debruynehoek",
    "iso:country":"BE",
    "sg:address":"Debruynehoek 16",
    "sg:city":"Koekelare",
    "sg:orig_category":"Traitements param\u00e9dicaux",
    "sg:phone":"+32 51 58 32 72",
    "sg:postcode":"8680",
    "sg:province":"West-Vlaanderen",
    "wof:name":"M. Devreker",
    "wof:placetype":"venue"
},
  "geometry": {"coordinates":[2.9540109634,51.0624008179],"type":"Point"}
}