{
  "type": "Feature",
  "properties": {
    "iso:country":"BE",
    "sg:address":"Gangelberg 4",
    "sg:city":"Lier",
    "sg:orig_category":"Rundveehouders",
    "sg:phone":"+32 3 482 43 51",
    "sg:postcode":"2500",
    "sg:province":"Antwerpen",
    "wof:name":"Lodewijk Aerts",
    "wof:placetype":"venue"
},
  "geometry": {"coordinates":[4.632630825,51.0851478577],"type":"Point"}
}