{
  "type": "Feature",
  "properties": {
    "addr:full":"Isschot 11bc Kasterlee Antwerpen 2460",
    "addr:housenumber":"11bc",
    "addr:postcode":"2460",
    "addr:street":"Isschot",
    "iso:country":"BE",
    "sg:address":"Isschot 11bc",
    "sg:city":"Kasterlee",
    "sg:orig_category":"Varkenskwekers",
    "sg:phone":"+32 14 85 15 85",
    "sg:postcode":"2460",
    "sg:province":"Antwerpen",
    "wof:name":"Jozef Van Laer",
    "wof:placetype":"venue"
},
  "geometry": {"coordinates":[4.9846692085,51.2510871887],"type":"Point"}
}