{
  "type": "Feature",
  "properties": {
    "addr:full":"Rue Douffet 36 Li\u00e8ge 1 (li\u00e8ge 2) Li\u00e8ge 4020",
    "addr:housenumber":"36;1;2",
    "addr:postcode":"4020",
    "addr:street":"Rue Douffet",
    "iso:country":"BE",
    "sg:address":"Rue Douffet 36",
    "sg:city":"Li\u00e8ge 1 (li\u00e8ge 2)",
    "sg:classifiers":[
        {
            "category":"Travel",
            "subcategory":"Travel Agent",
            "type":"Entertainment"
        }
    ],
    "sg:phone":"+32 4 341 63 70",
    "sg:postcode":"4020",
    "sg:province":"Li\u00e8ge",
    "sg:tags":[
        "agency"
    ],
    "wof:name":"Amplitours",
    "wof:placetype":"venue"
},
  "geometry": {"coordinates":[5.5846610069,50.636051178],"type":"Point"}
}