{
  "type": "Feature",
  "properties": {
    "addr:full":"Pachtgoedstraat 4bb Hamme Oost-Vlaanderen 9220",
    "addr:housenumber":"4bb",
    "addr:postcode":"9220",
    "addr:street":"Pachtgoedstraat",
    "iso:country":"BE",
    "sg:address":"Pachtgoedstraat 4bb",
    "sg:city":"Hamme",
    "sg:orig_category":"Eleveurs and marchands de porcs. Eleveurs de bovins",
    "sg:phone":"+32 52 47 67 65",
    "sg:postcode":"9220",
    "sg:province":"Oost-Vlaanderen",
    "wof:name":"August Claessens",
    "wof:placetype":"venue"
},
  "geometry": {"coordinates":[4.1398539543,51.063129425],"type":"Point"}
}