{
  "type": "Feature",
  "properties": {
    "addr:full":"Paulatemstraat 11 Zwalm Oost-Vlaanderen 9630",
    "addr:housenumber":"11",
    "addr:postcode":"9630",
    "addr:street":"Paulatemstraat;Oost-Vlaanderen",
    "iso:country":"BE",
    "sg:address":"Paulatemstraat 11",
    "sg:city":"Zwalm",
    "sg:orig_category":"Installatie van metalen schrijnwerk",
    "sg:phone":"+32 55 49 70 49",
    "sg:postcode":"9630",
    "sg:province":"Oost-Vlaanderen",
    "wof:name":"Dirk Van De Velde",
    "wof:placetype":"venue"
},
  "geometry": {"coordinates":[3.707406044,50.8911705017],"type":"Point"}
}