{
  "type": "Feature",
  "properties": {
    "addr:full":"Rue Arthur Decoux 167 Charleroi (dampremy) Hainaut 6020",
    "addr:housenumber":"167",
    "addr:postcode":"6020",
    "addr:street":"Rue Arthur Decoux",
    "iso:country":"BE",
    "sg:address":"Rue Arthur Decoux 167",
    "sg:city":"Charleroi (dampremy)",
    "sg:classifiers":[
        {
            "category":"Home & Garden",
            "subcategory":"Home Furnishings",
            "type":"Retail Goods"
        }
    ],
    "sg:phone":"+32 71 50 69 69",
    "sg:postcode":"6020",
    "sg:province":"Hainaut",
    "sg:tags":[
        "-",
        "furniture"
    ],
    "wof:name":"New Land Meubles Sprl",
    "wof:placetype":"venue"
},
  "geometry": {"coordinates":[4.4374628067,50.4188575745],"type":"Point"}
}