{
  "type": "Feature",
  "properties": {
    "iso:country":"BE",
    "sg:address":"Steenweg Op Asse 14",
    "sg:city":"Merchtem (brussegem)",
    "sg:classifiers":[
        {
            "category":"Health Services",
            "subcategory":"Dentist",
            "type":"Services"
        }
    ],
    "sg:phone":"+32 2 460 52 12",
    "sg:postcode":"1785",
    "sg:province":"Vlaams-Brabant",
    "wof:name":"Meysman P",
    "wof:placetype":"venue"
},
  "geometry": {"coordinates":[4.2621159554,50.927444458],"type":"Point"}
}