{
  "type": "Feature",
  "properties": {
    "addr:full":"Rue Ernest Solvay 20 Li\u00c8ge Li\u00e8ge 4000",
    "addr:housenumber":"20",
    "addr:postcode":"4000",
    "addr:street":"Rue Ernest Solvay",
    "iso:country":"BE",
    "sg:address":"Rue Ernest Solvay 20",
    "sg:city":"Li\u00c8ge",
    "sg:classifiers":[
        {
            "category":"Cafe",
            "type":"Food & Drink"
        }
    ],
    "sg:phone":"+32 4 252 58 95",
    "sg:postcode":"4000",
    "sg:province":"Li\u00e8ge",
    "sg:tags":[
        "caf\u00e9s"
    ],
    "wof:name":"Caf\u00c9 Au Stella",
    "wof:placetype":"venue"
},
  "geometry": {"coordinates":[5.5601878166,50.6096496582],"type":"Point"}
}