{
  "type": "Feature",
  "properties": {
    "addr:full":"Geldenaaksevest 64 Leuven Vlaams-Brabant 3000",
    "addr:housenumber":"64",
    "addr:postcode":"3000",
    "addr:street":"Geldenaaksevest",
    "iso:country":"BE",
    "sg:address":"Geldenaaksevest 64",
    "sg:city":"Leuven",
    "sg:orig_category":"M\u00e9decins and sp\u00e9cialistes",
    "sg:phone":"+32 16 23 69 21",
    "sg:postcode":"3000",
    "sg:province":"Vlaams-Brabant",
    "wof:name":"Myriam Jennes",
    "wof:placetype":"venue"
},
  "geometry": {"coordinates":[4.7114601135,50.8715019226],"type":"Point"}
}