{
  "type": "Feature",
  "properties": {
    "addr:full":"Chauss\u00e9e De Malines 108 Wezembeek-oppem Vlaams-Brabant 1970",
    "addr:housenumber":"108",
    "addr:postcode":"1970",
    "addr:street":"Chausse\u0301E De Malines",
    "iso:country":"BE",
    "sg:address":"Chauss\u00e9e De Malines 108",
    "sg:city":"Wezembeek-oppem",
    "sg:classifiers":[
        {
            "category":"Personal",
            "subcategory":"Beauty Salon",
            "type":"Services"
        }
    ],
    "sg:phone":"+32 2 731 33 57",
    "sg:postcode":"1970",
    "sg:province":"Vlaams-Brabant",
    "sg:tags":[
        "lady",
        "-",
        "hairdressing"
    ],
    "wof:name":"Coiffure Jean-paul Bvba",
    "wof:placetype":"venue"
},
  "geometry": {"coordinates":[4.4945912361,50.8404083252],"type":"Point"}
}