{
  "type": "Feature",
  "properties": {
    "addr:full":"Schorestraat 27 Diksmuide West-Vlaanderen 8600",
    "addr:housenumber":"27",
    "addr:postcode":"8600",
    "addr:street":"Schorestraat",
    "iso:country":"BE",
    "sg:address":"Schorestraat 27",
    "sg:city":"Diksmuide",
    "sg:orig_category":"Eleveurs and marchands de porcs",
    "sg:phone":"+32 51 50 11 43",
    "sg:postcode":"8600",
    "sg:province":"West-Vlaanderen",
    "wof:name":"Etienne Loobuyck",
    "wof:placetype":"venue"
},
  "geometry": {"coordinates":[2.8661940098,51.1051330566],"type":"Point"}
}