{
  "type": "Feature",
  "properties": {
    "iso:country":"BE",
    "sg:address":"Groentemarkt 11",
    "sg:city":"Lokeren",
    "sg:orig_category":"Produits surgel\u00e9s Gr",
    "sg:phone":"+32 9 348 08 04",
    "sg:postcode":"9160",
    "sg:province":"Oost-Vlaanderen",
    "wof:name":"Givana",
    "wof:placetype":"venue"
},
  "geometry": {"coordinates":[3.9883449078,51.1037597656],"type":"Point"}
}