{
  "type": "Feature",
  "properties": {
    "addr:full":"Roeselaarsestraat 101 Box 1 Izegem West-Vlaanderen 8870",
    "addr:housenumber":"101;1",
    "addr:postcode":"8870",
    "addr:street":"Roeselaarsestraat;Box",
    "iso:country":"BE",
    "sg:address":"Roeselaarsestraat 101 Box 1",
    "sg:city":"Izegem",
    "sg:classifiers":[
        {
            "category":"Professional",
            "subcategory":"Advertising",
            "type":"Services"
        }
    ],
    "sg:phone":"+32 51 30 18 59",
    "sg:postcode":"8870",
    "sg:province":"West-Vlaanderen",
    "sg:tags":[
        "photography"
    ],
    "wof:name":"Decock K",
    "wof:placetype":"venue"
},
  "geometry": {"coordinates":[3.2069809437,50.9197616577],"type":"Point"}
}