{
  "type": "Feature",
  "properties": {
    "addr:full":"Kerkstraat 4 Vorselaar Antwerpen 2290",
    "addr:housenumber":"4",
    "addr:postcode":"2290",
    "addr:street":"Kerkstraat",
    "iso:country":"BE",
    "sg:address":"Kerkstraat 4",
    "sg:city":"Vorselaar",
    "sg:classifiers":[
        {
            "category":"Cafe",
            "type":"Food & Drink"
        }
    ],
    "sg:phone":"+32 14 51 55 27",
    "sg:postcode":"2290",
    "sg:province":"Antwerpen",
    "sg:tags":[
        "caf\u00e9s"
    ],
    "wof:name":"Het Bierhuis",
    "wof:placetype":"venue"
},
  "geometry": {"coordinates":[4.7710299492,51.2028465271],"type":"Point"}
}