{
  "type": "Feature",
  "properties": {
    "addr:full":"Chauss\u00c9e De Maubeuge 121 Mons Hainaut 7022",
    "addr:housenumber":"121",
    "addr:postcode":"7022",
    "addr:street":"Chausse\u0301E De Maubeuge;Hainaut",
    "iso:country":"BE",
    "sg:address":"Chauss\u00c9e De Maubeuge 121",
    "sg:city":"Mons",
    "sg:classifiers":[
        {
            "category":"Cafe",
            "type":"Food & Drink"
        }
    ],
    "sg:phone":"+32 65 35 12 19",
    "sg:postcode":"7022",
    "sg:province":"Hainaut",
    "sg:tags":[
        "caf\u00e9s"
    ],
    "wof:name":"Hoyas Rene Et Stephane",
    "wof:placetype":"venue"
},
  "geometry": {"coordinates":[3.9475119114,50.4338874817],"type":"Point"}
}