{
  "type": "Feature",
  "properties": {
    "addr:full":"Kerkhovensesteenweg 359 Lommel Limburg 3920",
    "addr:housenumber":"359",
    "addr:postcode":"3920",
    "addr:street":"Kerkhovensesteenweg",
    "iso:country":"BE",
    "sg:address":"Kerkhovensesteenweg 359",
    "sg:city":"Lommel",
    "sg:classifiers":[
        {
            "category":"Health Services",
            "subcategory":"Health Practitioner",
            "type":"Services"
        }
    ],
    "sg:phone":"+32 11 39 19 26",
    "sg:postcode":"3920",
    "sg:province":"Limburg",
    "sg:tags":[
        "physiotherapist"
    ],
    "wof:name":"Willekens Daisy",
    "wof:placetype":"venue"
},
  "geometry": {"coordinates":[5.2995147705,51.1884803772],"type":"Point"}
}