{
  "type": "Feature",
  "properties": {
    "addr:full":"Sint-jansstraat 3 Brugge West-Vlaanderen 8000",
    "addr:housenumber":"3",
    "addr:postcode":"8000",
    "addr:street":"Sint-Jansstraat",
    "iso:country":"BE",
    "sg:address":"Sint-jansstraat 3",
    "sg:city":"Brugge",
    "sg:orig_category":"Dancings and bo\u00eetes de nuit. Restaurants",
    "sg:phone":"+32 50 33 47 42",
    "sg:postcode":"8000",
    "sg:province":"West-Vlaanderen",
    "wof:name":"Taverne Passe-partout",
    "wof:placetype":"venue"
},
  "geometry": {"coordinates":[3.2254459858,51.2106933594],"type":"Point"}
}