{
  "type": "Feature",
  "properties": {
    "iso:country":"BE",
    "sg:address":"Grande Rue Au Bois 44",
    "sg:city":"Bruxelles (schaerbeek)",
    "sg:classifiers":[
        {
            "category":"Exhibition Hall",
            "type":"Public Place"
        }
    ],
    "sg:phone":"+32 475 28 27 80",
    "sg:postcode":"1030",
    "sg:province":"Bruxelles-Capitale",
    "sg:tags":[
        "stand"
    ],
    "wof:name":"Art & Co Sprl",
    "wof:placetype":"venue"
},
  "geometry": {"coordinates":[4.3858098984,50.8564834595],"type":"Point"}
}