{
  "type": "Feature",
  "properties": {
    "addr:full":"Chemin De La Haze 16 Esneux Li\u00e8ge 4130",
    "addr:housenumber":"16",
    "addr:postcode":"4130",
    "addr:street":"Chemin De La Haze",
    "iso:country":"BE",
    "sg:address":"Chemin De La Haze 16",
    "sg:city":"Esneux",
    "sg:orig_category":"Enseignement maternel and primaire",
    "sg:phone":"+32 4 380 34 28",
    "sg:postcode":"4130",
    "sg:province":"Li\u00e8ge",
    "wof:name":"Ecole Prim. Communale",
    "wof:placetype":"venue"
},
  "geometry": {"coordinates":[5.6019058228,50.5207328796],"type":"Point"}
}