{
  "type": "Feature",
  "properties": {
    "addr:full":"Rue Du Roi Albert 127 Oupeye Li\u00e8ge 4680",
    "addr:housenumber":"127",
    "addr:postcode":"4680",
    "addr:street":"Rue Du Roi Albert",
    "iso:country":"BE",
    "sg:address":"Rue Du Roi Albert 127",
    "sg:city":"Oupeye",
    "sg:orig_category":"Caf\u00e9s Diverse bedrijfsbeheeradviesbureaus",
    "sg:phone":"+32 4 264 58 00",
    "sg:postcode":"4680",
    "sg:province":"Li\u00e8ge",
    "wof:name":"Ch\u00c2teau D'oupeye",
    "wof:placetype":"venue"
},
  "geometry": {"coordinates":[5.6495599747,50.7069702148],"type":"Point"}
}