{
  "type": "Feature",
  "properties": {
    "addr:full":"Rue Gillebertus 11 Bruxelles (jette) Bruxelles-Capitale 1090",
    "addr:housenumber":"11",
    "addr:postcode":"1090",
    "addr:street":"Rue Gillebertus",
    "iso:country":"BE",
    "sg:address":"Rue Gillebertus 11",
    "sg:city":"Bruxelles (jette)",
    "sg:orig_category":"Non-Classified Establishments",
    "sg:phone":"+32 2 428 97 05",
    "sg:postcode":"1090",
    "sg:province":"Bruxelles-Capitale",
    "wof:name":"Demolder J Bvba",
    "wof:placetype":"venue"
},
  "geometry": {"coordinates":[4.3247570992,50.8768196106],"type":"Point"}
}