{
  "type": "Feature",
  "properties": {
    "addr:full":"Stationsstraat 101 Aalter Oost-Vlaanderen 9880",
    "addr:housenumber":"101",
    "addr:postcode":"9880",
    "addr:street":"Stationsstraat",
    "iso:country":"BE",
    "sg:address":"Stationsstraat 101",
    "sg:city":"Aalter",
    "sg:classifiers":[
        {
            "category":"Communications",
            "type":"Services"
        }
    ],
    "sg:phone":"+32 9 325 02 99",
    "sg:postcode":"9880",
    "sg:province":"Oost-Vlaanderen",
    "sg:tags":[
        "telecommunication"
    ],
    "wof:name":"Telecom Aalter",
    "wof:placetype":"venue"
},
  "geometry": {"coordinates":[3.447384119,51.089099884],"type":"Point"}
}