{
  "type": "Feature",
  "properties": {
    "addr:full":"Dorp 16 Horebeke Oost-Vlaanderen 9667",
    "addr:housenumber":"16",
    "addr:postcode":"9667",
    "addr:street":"Dorp",
    "iso:country":"BE",
    "sg:address":"Dorp 16",
    "sg:city":"Horebeke",
    "sg:orig_category":"Groenten and fruit Gh",
    "sg:phone":"+32 55 45 57 64",
    "sg:postcode":"9667",
    "sg:province":"Oost-Vlaanderen",
    "wof:name":"Romain De Martelare",
    "wof:placetype":"venue"
},
  "geometry": {"coordinates":[3.6893000603,50.8390426636],"type":"Point"}
}