{
  "type": "Feature",
  "properties": {
    "iso:country":"BE",
    "sg:address":"Place L. Servais 40",
    "sg:city":"Olne",
    "sg:orig_category":"Overheidsdiensten",
    "sg:phone":"+32 87 26 78 89",
    "sg:postcode":"4877",
    "sg:province":"Li\u00e8ge",
    "wof:name":"C.p.a.s.",
    "wof:placetype":"venue"
},
  "geometry": {"coordinates":[5.7493209839,50.5908203125],"type":"Point"}
}