{
  "type": "Feature",
  "properties": {
    "addr:full":"Harmoniestraat 2 Beringen Limburg 3580",
    "addr:housenumber":"2",
    "addr:postcode":"3580",
    "addr:street":"Harmoniestraat",
    "iso:country":"BE",
    "sg:address":"Harmoniestraat 2",
    "sg:city":"Beringen",
    "sg:orig_category":"Notaires",
    "sg:phone":"+32 11 42 25 76",
    "sg:postcode":"3580",
    "sg:province":"Limburg",
    "wof:name":"Andr\u00c9 Hendrickx",
    "wof:placetype":"venue"
},
  "geometry": {"coordinates":[5.2281470299,51.0469398499],"type":"Point"}
}