{
  "type": "Feature",
  "properties": {
    "addr:full":"Steenweg 45 Asse Vlaams-Brabant 1730",
    "addr:housenumber":"45",
    "addr:postcode":"1730",
    "addr:street":"Steenweg",
    "iso:country":"BE",
    "sg:address":"Steenweg 45",
    "sg:city":"Asse",
    "sg:orig_category":"Tweedehandsgoederen Verlichting and huishoudartikelen",
    "sg:phone":"+32 2 453 07 87",
    "sg:postcode":"1730",
    "sg:province":"Vlaams-Brabant",
    "wof:name":"Oxfam Wereldwinkel",
    "wof:placetype":"venue"
},
  "geometry": {"coordinates":[4.2224397659,50.9028511047],"type":"Point"}
}