{
  "type": "Feature",
  "properties": {
    "iso:country":"BE",
    "sg:address":"Rue Britannique 11",
    "sg:city":"Braine-le-comte",
    "sg:classifiers":[
        {
            "category":"Personal",
            "subcategory":"Beauty Salon",
            "type":"Services"
        }
    ],
    "sg:phone":"+32 67 55 67 18",
    "sg:postcode":"7090",
    "sg:province":"Hainaut",
    "sg:tags":[
        "de",
        "coiffure"
    ],
    "wof:name":"Euro-coiffure",
    "wof:placetype":"venue"
},
  "geometry": {"coordinates":[4.1344060898,50.6074714661],"type":"Point"}
}