{
  "type": "Feature",
  "properties": {
    "addr:full":"Rue Des Praules 0 Gembloux Namur 5030",
    "addr:housenumber":"0",
    "addr:postcode":"5030",
    "addr:street":"Rue Des Praules;Namur",
    "iso:country":"BE",
    "sg:address":"Rue Des Praules 0",
    "sg:city":"Gembloux",
    "sg:orig_category":"Entretien and r\u00e9parations de voitures",
    "sg:phone":"+32 81 64 06 51",
    "sg:postcode":"5030",
    "sg:province":"Namur",
    "wof:name":"Michel Simon",
    "wof:placetype":"venue"
},
  "geometry": {"coordinates":[4.71185112,50.5778160095],"type":"Point"}
}