{
  "type": "Feature",
  "properties": {
    "iso:country":"BE",
    "sg:address":"Grote Vond 5",
    "sg:city":"Ravels",
    "sg:orig_category":"Varkenskwekers",
    "sg:phone":"+32 14 65 61 29",
    "sg:postcode":"2382",
    "sg:province":"Antwerpen",
    "wof:name":"Jan Franken",
    "wof:placetype":"venue"
},
  "geometry": {"coordinates":[5.0302700996,51.4404296875],"type":"Point"}
}