{
  "type": "Feature",
  "properties": {
    "addr:full":"Rue Henri Bl\u00e8s 192 Namur Namur 5000",
    "addr:housenumber":"192",
    "addr:postcode":"5000",
    "addr:street":"Rue Henri Ble\u0300S",
    "iso:country":"BE",
    "sg:address":"Rue Henri Bl\u00e8s 192",
    "sg:city":"Namur",
    "sg:classifiers":[
        {
            "category":"Arena",
            "subcategory":"Sports Club",
            "type":"Entertainment"
        }
    ],
    "sg:phone":"+32 81 44 12 30",
    "sg:postcode":"5000",
    "sg:province":"Namur",
    "wof:name":"Gaillarde (la)",
    "wof:placetype":"venue"
},
  "geometry": {"coordinates":[4.8390498161,50.4653396606],"type":"Point"}
}