{
  "type": "Feature",
  "properties": {
    "addr:full":"Avenue W. Churchill 2 Ukkel/uccle Bruxelles-Capitale 1180",
    "addr:housenumber":"2",
    "addr:postcode":"1180",
    "addr:street":"Avenue W. Churchill;/",
    "iso:country":"BE",
    "sg:address":"Avenue W. Churchill 2",
    "sg:city":"Ukkel/uccle",
    "sg:orig_category":"Decoratieve kunst and kunstbenodigdheden Foto-uitrusting Fotolaboratoria",
    "sg:phone":"+32 2 346 58 75",
    "sg:postcode":"1180",
    "sg:province":"Bruxelles-Capitale",
    "wof:name":"Positif Photo Express G.s.",
    "wof:placetype":"venue"
},
  "geometry": {"coordinates":[4.3483381271,50.8135528564],"type":"Point"}
}