{
  "type": "Feature",
  "properties": {
    "addr:full":"Chauss\u00e9e De Wavre 48 Wanze Li\u00e8ge 4520",
    "addr:housenumber":"48",
    "addr:postcode":"4520",
    "addr:street":"Chausse\u0301E De Wavre",
    "iso:country":"BE",
    "sg:address":"Chauss\u00e9e De Wavre 48",
    "sg:city":"Wanze",
    "sg:classifiers":[
        {
            "category":"Shopping",
            "subcategory":"Optician",
            "type":"Retail Goods"
        }
    ],
    "sg:phone":"+32 85 23 47 15",
    "sg:postcode":"4520",
    "sg:province":"Li\u00e8ge",
    "sg:tags":[
        "-"
    ],
    "wof:name":"Piton Optique",
    "wof:placetype":"venue"
},
  "geometry": {"coordinates":[5.2151827812,50.536781311],"type":"Point"}
}