{
  "type": "Feature",
  "properties": {
    "addr:full":"Groenplaats 2-3 Antwerpen Antwerpen 2000",
    "addr:housenumber":"2-3",
    "addr:postcode":"2000",
    "addr:street":"Groenplaats",
    "iso:country":"BE",
    "sg:address":"Groenplaats 2-3",
    "sg:city":"Antwerpen",
    "sg:classifiers":[
        {
            "category":"Manufacturing",
            "subcategory":"Furniture",
            "type":"Manufacturing & Wholesale Goods"
        }
    ],
    "sg:phone":"+32 3 232 77 49",
    "sg:postcode":"2000",
    "sg:province":"Antwerpen",
    "sg:tags":[
        "armchair",
        "-"
    ],
    "wof:name":"Burodep-gispen",
    "wof:placetype":"venue"
},
  "geometry": {"coordinates":[4.400867939,51.2189750671],"type":"Point"}
}