{
  "type": "Feature",
  "properties": {
    "iso:country":"BE",
    "sg:address":"Ruitersweg 1",
    "sg:city":"Kortrijk",
    "sg:orig_category":"Artsen and specialisten",
    "sg:phone":"+32 56 21 61 90",
    "sg:postcode":"8500",
    "sg:province":"West-Vlaanderen",
    "wof:name":"Andr\u00c9 Van Caster",
    "wof:placetype":"venue"
},
  "geometry": {"coordinates":[3.2752580643,50.8340301514],"type":"Point"}
}