{
  "type": "Feature",
  "properties": {
    "addr:full":"Place Albert I 20 Charleroi (monceau-sur-sambre) Hainaut 6031",
    "addr:housenumber":"20",
    "addr:postcode":"6031",
    "addr:street":"Place Albert I",
    "iso:country":"BE",
    "sg:address":"Place Albert I 20",
    "sg:city":"Charleroi (monceau-sur-sambre)",
    "sg:classifiers":[
        {
            "category":"Professional",
            "subcategory":"Accounting & Tax Preparation",
            "type":"Services"
        }
    ],
    "sg:phone":"+32 71 32 51 95",
    "sg:postcode":"6031",
    "sg:province":"Hainaut",
    "sg:tags":[
        "bookkeeper"
    ],
    "wof:name":"Van Nuffel B",
    "wof:placetype":"venue"
},
  "geometry": {"coordinates":[4.38022995,50.4121742249],"type":"Point"}
}