{
  "type": "Feature",
  "properties": {
    "iso:country":"BE",
    "sg:address":"Snepdreef 35",
    "sg:city":"Evergem",
    "sg:orig_category":"M\u00e9decins and sp\u00e9cialistes",
    "sg:phone":"+32 9 344 80 93",
    "sg:postcode":"9940",
    "sg:province":"Oost-Vlaanderen",
    "wof:name":"Petra Scheir",
    "wof:placetype":"venue"
},
  "geometry": {"coordinates":[3.698266983,51.1740226746],"type":"Point"}
}