{
  "type": "Feature",
  "properties": {
    "iso:country":"BE",
    "sg:address":"Ambachtsweg 8",
    "sg:city":"Rijkevorsel",
    "sg:classifiers":[
        {
            "category":"Food & Beverages",
            "subcategory":"Supermarket",
            "type":"Retail Goods"
        }
    ],
    "sg:phone":"+32 3 340 05 11",
    "sg:postcode":"2310",
    "sg:province":"Antwerpen",
    "sg:tags":[
        "department",
        "store"
    ],
    "wof:name":"Aldi Nv",
    "wof:placetype":"venue"
},
  "geometry": {"coordinates":[4.7840080261,51.3463973999],"type":"Point"}
}