{
  "type": "Feature",
  "properties": {
    "addr:full":"Rue De Namur 404 Ch\u00c2telet Hainaut 6200",
    "addr:housenumber":"404",
    "addr:postcode":"6200",
    "addr:street":"Rue De Namur",
    "iso:country":"BE",
    "sg:address":"Rue De Namur 404",
    "sg:city":"Ch\u00c2telet",
    "sg:orig_category":"M\u00e9decins and sp\u00e9cialistes",
    "sg:phone":"+32 71 40 03 62",
    "sg:postcode":"6200",
    "sg:province":"Hainaut",
    "wof:name":"A. Decourt",
    "wof:placetype":"venue"
},
  "geometry": {"coordinates":[4.5411710739,50.3965110779],"type":"Point"}
}