{
  "type": "Feature",
  "properties": {
    "iso:country":"BE",
    "sg:address":"Rue De La Hamaide 5",
    "sg:city":"Leuze-en-hainaut",
    "sg:orig_category":"Fruits and l\u00e9gumes. Fruits and l\u00e9gumes Produits \u00e0 base de pommes de terre Gr",
    "sg:phone":"+32 69 66 51 69",
    "sg:postcode":"7901",
    "sg:province":"Hainaut",
    "wof:name":"Fe. Fran\u00c7ois",
    "wof:placetype":"venue"
},
  "geometry": {"coordinates":[3.5820600986,50.6142730713],"type":"Point"}
}