{
  "type": "Feature",
  "properties": {
    "iso:country":"BE",
    "sg:address":"De Ham 12",
    "sg:city":"Gooik (kester)",
    "sg:classifiers":[
        {
            "category":"Insurance",
            "subcategory":"Insurance Agent",
            "type":"Services"
        }
    ],
    "sg:phone":"+32 54 56 79 78",
    "sg:postcode":"1755",
    "sg:province":"Vlaams-Brabant",
    "sg:tags":[
        "broker"
    ],
    "wof:name":"Dedoncker I",
    "wof:placetype":"venue"
},
  "geometry": {"coordinates":[4.116186142,50.7635803223],"type":"Point"}
}