{
  "type": "Feature",
  "properties": {
    "addr:full":"Markt 2 Sint-katelijne-waver Antwerpen 2860",
    "addr:housenumber":"2",
    "addr:postcode":"2860",
    "addr:street":"Markt",
    "iso:country":"BE",
    "sg:address":"Markt 2",
    "sg:city":"Sint-katelijne-waver",
    "sg:orig_category":"Kapsalons",
    "sg:phone":"+32 15 31 18 63",
    "sg:postcode":"2860",
    "sg:province":"Antwerpen",
    "wof:name":"Coiffure Freddy",
    "wof:placetype":"venue"
},
  "geometry": {"coordinates":[4.5338730812,51.0684928894],"type":"Point"}
}