{
  "type": "Feature",
  "properties": {
    "addr:full":"Chauss\u00e9e De Namur 248 Wavre Brabant Wallon 1300",
    "addr:housenumber":"248;1300",
    "addr:street":"Chausse\u0301E De Namur",
    "iso:country":"BE",
    "sg:address":"Chauss\u00e9e De Namur 248",
    "sg:city":"Wavre",
    "sg:classifiers":[
        {
            "category":"Home & Garden",
            "subcategory":"Kitchen Supply",
            "type":"Retail Goods"
        }
    ],
    "sg:phone":"+32 10 45 27 25",
    "sg:postcode":"1300",
    "sg:province":"Brabant Wallon",
    "sg:tags":[
        "installation"
    ],
    "wof:name":"Mi-bois Sa",
    "wof:placetype":"venue"
},
  "geometry": {"coordinates":[4.6158699989,50.6923713684],"type":"Point"}
}