{
  "type": "Feature",
  "properties": {
    "iso:country":"BE",
    "sg:address":"Grote Steenweg 30b1",
    "sg:city":"Kontich",
    "sg:orig_category":"Landmeters",
    "sg:phone":"+32 15 32 05 29",
    "sg:postcode":"2550",
    "sg:province":"Antwerpen",
    "wof:name":"David Ibens",
    "wof:placetype":"venue"
},
  "geometry": {"coordinates":[4.4506931305,51.1059951782],"type":"Point"}
}