{
  "type": "Feature",
  "properties": {
    "iso:country":"BE",
    "sg:address":"Place Emile Vandervelde 37",
    "sg:city":"Charleroi",
    "sg:orig_category":"Openbare bibliotheken and archieven",
    "sg:phone":"+32 71 31 34 95",
    "sg:postcode":"6043",
    "sg:province":"Hainaut",
    "wof:name":"Biblioth\u00c8que Publique",
    "wof:placetype":"venue"
},
  "geometry": {"coordinates":[4.4550609589,50.4224853516],"type":"Point"}
}