{
  "type": "Feature",
  "properties": {
    "iso:country":"BE",
    "sg:address":"Meersblomme 29",
    "sg:city":"Waregem",
    "sg:orig_category":"Goederenvervoer over de weg",
    "sg:phone":"+32 56 60 30 09",
    "sg:postcode":"8790",
    "sg:province":"West-Vlaanderen",
    "wof:name":"Transport Ballegeer",
    "wof:placetype":"venue"
},
  "geometry": {"coordinates":[3.4459300041,50.8877220154],"type":"Point"}
}