{
  "type": "Feature",
  "properties": {
    "iso:country":"BE",
    "sg:address":"Avenue Bel Air 37",
    "sg:city":"Rixensart",
    "sg:classifiers":[
        {
            "category":"Building & Trades",
            "subcategory":"Construction",
            "type":"Services"
        }
    ],
    "sg:phone":"+32 2 653 41 15",
    "sg:postcode":"1330",
    "sg:province":"Brabant Wallon",
    "sg:tags":[
        "installation",
        "-",
        "central",
        "heating"
    ],
    "wof:name":"Sani-technic-confort-anc. Ets",
    "wof:placetype":"venue"
},
  "geometry": {"coordinates":[4.5273628235,50.698802948],"type":"Point"}
}