{
  "type": "Feature",
  "properties": {
    "addr:full":"Rue D'evegn\u00e9e 46 Bl\u00e9gny (saive) Li\u00e8ge 4671",
    "addr:housenumber":"46",
    "addr:postcode":"4671",
    "addr:street":"Rue D'Evegne \u0301E",
    "iso:country":"BE",
    "sg:address":"Rue D'evegn\u00e9e 46",
    "sg:city":"Bl\u00e9gny (saive)",
    "sg:classifiers":[
        {
            "category":"Personal",
            "type":"Services"
        }
    ],
    "sg:phone":"+32 475 48 64 16",
    "sg:postcode":"4671",
    "sg:province":"Li\u00e8ge",
    "sg:tags":[
        "party",
        "planning"
    ],
    "wof:name":"Bader A",
    "wof:placetype":"venue"
},
  "geometry": {"coordinates":[5.6921920776,50.6494598389],"type":"Point"}
}