{
  "type": "Feature",
  "properties": {
    "addr:full":"Menenstraat 121 Wevelgem West-Vlaanderen 8560",
    "addr:housenumber":"121",
    "addr:postcode":"8560",
    "addr:street":"Menenstraat",
    "iso:country":"BE",
    "sg:address":"Menenstraat 121",
    "sg:city":"Wevelgem",
    "sg:classifiers":[
        {
            "category":"Bars & Pubs",
            "type":"Food & Drink"
        }
    ],
    "sg:phone":"+32 56 40 06 98",
    "sg:postcode":"8560",
    "sg:province":"West-Vlaanderen",
    "wof:name":"Cameo",
    "wof:placetype":"venue"
},
  "geometry": {"coordinates":[3.173484087,50.8064155579],"type":"Point"}
}