{
  "type": "Feature",
  "properties": {
    "iso:country":"BE",
    "sg:address":"Vrankrijkstraat 66",
    "sg:city":"Dendermonde (schoonaarde)",
    "sg:classifiers":[
        {
            "category":"Shopping",
            "subcategory":"Clothing, Apparel, & Fashions",
            "type":"Retail Goods"
        }
    ],
    "sg:phone":"+32 52 42 76 97",
    "sg:postcode":"9200",
    "sg:province":"Oost-Vlaanderen",
    "sg:tags":[
        "clothing",
        "-",
        "motorbike",
        "equipment"
    ],
    "wof:name":"V O F & Co",
    "wof:placetype":"venue"
},
  "geometry": {"coordinates":[4.0205860138,50.9971351624],"type":"Point"}
}