{
  "type": "Feature",
  "properties": {
    "iso:country":"BE",
    "sg:address":"Quai De Flandre 2",
    "sg:city":"Charleroi",
    "sg:classifiers":[
        {
            "category":"Professional",
            "subcategory":"Advertising",
            "type":"Services"
        }
    ],
    "sg:phone":"+32 71 27 64 11",
    "sg:postcode":"6000",
    "sg:province":"Hainaut",
    "sg:tags":[
        "information",
        "medium",
        "publishing",
        "pu",
        "communication",
        "printing"
    ],
    "wof:name":"Societe Anonyme De Presse & Deditions Sa",
    "wof:placetype":"venue"
},
  "geometry": {"coordinates":[4.4376912117,50.4064483643],"type":"Point"}
}