{
  "type": "Feature",
  "properties": {
    "addr:full":"Rue De La Porte Rouge 26 Brussel/bruxelles Bruxelles-Capitale 1000",
    "addr:housenumber":"26",
    "addr:postcode":"1000",
    "addr:street":"Rue De La Porte Rouge;/",
    "iso:country":"BE",
    "sg:address":"Rue De La Porte Rouge 26",
    "sg:city":"Brussel/bruxelles",
    "sg:orig_category":"Artistes ind\u00e9pendants",
    "sg:phone":"+32 2 219 53 45",
    "sg:postcode":"1000",
    "sg:province":"Bruxelles-Capitale",
    "wof:name":"Chedly Landoulsi",
    "wof:placetype":"venue"
},
  "geometry": {"coordinates":[4.3518967628,50.8389053345],"type":"Point"}
}