{
  "type": "Feature",
  "properties": {
    "addr:full":"Koolkappersstraat 46b3 Kortrijk West-Vlaanderen 8500",
    "addr:housenumber":"46b3",
    "addr:postcode":"8500",
    "addr:street":"Koolkappersstraat",
    "iso:country":"BE",
    "sg:address":"Koolkappersstraat 46b3",
    "sg:city":"Kortrijk",
    "sg:orig_category":"Agences d'exp\u00e9dition",
    "sg:phone":"+32 56 37 33 05",
    "sg:postcode":"8500",
    "sg:province":"West-Vlaanderen",
    "wof:name":"Deikras",
    "wof:placetype":"venue"
},
  "geometry": {"coordinates":[3.2737660408,50.8407897949],"type":"Point"}
}