{
  "type": "Feature",
  "properties": {
    "addr:full":"Kruishillestraat 14 Zedelgem West-Vlaanderen 8211",
    "addr:housenumber":"14",
    "addr:postcode":"8211",
    "addr:street":"Kruishillestraat",
    "iso:country":"BE",
    "sg:address":"Kruishillestraat 14",
    "sg:city":"Zedelgem",
    "sg:orig_category":"Afbraak- and draineerwerken Woningbouw",
    "sg:phone":"+32 50 24 01 24",
    "sg:postcode":"8211",
    "sg:province":"West-Vlaanderen",
    "wof:name":"Portier",
    "wof:placetype":"venue"
},
  "geometry": {"coordinates":[3.0889649391,51.1200408936],"type":"Point"}
}