{
  "type": "Feature",
  "properties": {
    "addr:full":"Margote 111 Wichelen Oost-Vlaanderen 9260",
    "addr:housenumber":"111",
    "addr:postcode":"9260",
    "addr:street":"Margote",
    "iso:country":"BE",
    "sg:address":"Margote 111",
    "sg:city":"Wichelen",
    "sg:classifiers":[
        {
            "category":"Home & Garden",
            "subcategory":"Household Appliances",
            "type":"Retail Goods"
        }
    ],
    "sg:phone":"+32 52 42 35 27",
    "sg:postcode":"9260",
    "sg:province":"Oost-Vlaanderen",
    "sg:tags":[
        "repair",
        "mainten",
        "-",
        "electric"
    ],
    "wof:name":"Redant Eric Bvba",
    "wof:placetype":"venue"
},
  "geometry": {"coordinates":[3.9756400585,51.0060997009],"type":"Point"}
}