{
  "type": "Feature",
  "properties": {
    "addr:full":"Rubensstraat 96 Vilvoorde Vlaams-Brabant 1800",
    "addr:housenumber":"96",
    "addr:postcode":"1800",
    "addr:street":"Rubensstraat",
    "iso:country":"BE",
    "sg:address":"Rubensstraat 96",
    "sg:city":"Vilvoorde",
    "sg:classifiers":[
        {
            "category":"Building & Trades",
            "subcategory":"Locksmith",
            "type":"Services"
        }
    ],
    "sg:phone":"+32 2 251 18 38",
    "sg:postcode":"1800",
    "sg:province":"Vlaams-Brabant",
    "sg:tags":[
        "lock",
        "key"
    ],
    "wof:name":"Theys & Zn Bvba",
    "wof:placetype":"venue"
},
  "geometry": {"coordinates":[4.408577919,50.9238815308],"type":"Point"}
}