{
  "type": "Feature",
  "properties": {
    "addr:full":"Joseph Ravoetstraat 5 Leuven (wilsele) Vlaams-Brabant 3012",
    "addr:housenumber":"5",
    "addr:postcode":"3012",
    "addr:street":"Joseph Ravoetstraat",
    "iso:country":"BE",
    "sg:address":"Joseph Ravoetstraat 5",
    "sg:city":"Leuven (wilsele)",
    "sg:classifiers":[
        {
            "category":"Health Services",
            "subcategory":"Hospital",
            "type":"Services"
        }
    ],
    "sg:phone":"+32 16 44 37 63",
    "sg:postcode":"3012",
    "sg:province":"Vlaams-Brabant",
    "wof:name":"Crystapharm",
    "wof:placetype":"venue"
},
  "geometry": {"coordinates":[4.7172231674,50.915977478],"type":"Point"}
}