{
  "type": "Feature",
  "properties": {
    "addr:full":"Rue Hermant Andr\u00c9 1 Gedinne Namur 5575",
    "addr:housenumber":"1",
    "addr:postcode":"5575",
    "addr:street":"Rue Hermant Andre\u0301",
    "iso:country":"BE",
    "sg:address":"Rue Hermant Andr\u00c9 1",
    "sg:city":"Gedinne",
    "sg:orig_category":"Instituts de beaut\u00e9. Centres de relaxation and bien-\u00eatre",
    "sg:phone":"+32 61 58 88 06",
    "sg:postcode":"5575",
    "sg:province":"Namur",
    "wof:name":"Centre Remise Forme Spin\u00c9e",
    "wof:placetype":"venue"
},
  "geometry": {"coordinates":[4.9395799637,49.9797210693],"type":"Point"}
}