{
  "type": "Feature",
  "properties": {
    "addr:full":"Rodonkstraat 30 Gent Oost-Vlaanderen 9030",
    "addr:housenumber":"30",
    "addr:postcode":"9030",
    "addr:street":"Rodonkstraat;Oost-Vlaanderen",
    "iso:country":"BE",
    "sg:address":"Rodonkstraat 30",
    "sg:city":"Gent",
    "sg:orig_category":"Bloemen and planten",
    "sg:phone":"+32 9 227 20 97",
    "sg:postcode":"9030",
    "sg:province":"Oost-Vlaanderen",
    "wof:name":"Ter Blomme",
    "wof:placetype":"venue"
},
  "geometry": {"coordinates":[3.6683089733,51.0772666931],"type":"Point"}
}