{
  "type": "Feature",
  "properties": {
    "addr:full":"Turnhoutseweg 26b1 Ravels Antwerpen 2381",
    "addr:housenumber":"26b1",
    "addr:postcode":"2381",
    "addr:street":"Turnhoutseweg",
    "iso:country":"BE",
    "sg:address":"Turnhoutseweg 26b1",
    "sg:city":"Ravels",
    "sg:orig_category":"Avocats and conseillers juridiques",
    "sg:phone":"+32 14 42 26 63",
    "sg:postcode":"2381",
    "sg:province":"Antwerpen",
    "wof:name":"Carine Couwenberg",
    "wof:placetype":"venue"
},
  "geometry": {"coordinates":[5.006374836,51.4099845886],"type":"Point"}
}