{
  "type": "Feature",
  "properties": {
    "iso:country":"BE",
    "sg:address":"Grootakker 1",
    "sg:city":"Malle",
    "sg:orig_category":"Sportclubs",
    "sg:phone":"+32 3 309 95 34",
    "sg:postcode":"2390",
    "sg:province":"Antwerpen",
    "wof:name":"T.c. De Tijdrijders Westmalle",
    "wof:placetype":"venue"
},
  "geometry": {"coordinates":[4.6902098656,51.3019714355],"type":"Point"}
}