{
  "type": "Feature",
  "properties": {
    "iso:country":"BE",
    "sg:address":"Millesteenstraat 93",
    "sg:city":"Moorslede",
    "sg:orig_category":"Maroquinerie Fab",
    "sg:phone":"+32 56 50 08 85",
    "sg:postcode":"8890",
    "sg:province":"West-Vlaanderen",
    "wof:name":"Agemy",
    "wof:placetype":"venue"
},
  "geometry": {"coordinates":[3.1098060608,50.8429603577],"type":"Point"}
}