{
  "type": "Feature",
  "properties": {
    "iso:country":"BE",
    "sg:address":"Rucaplein 115",
    "sg:city":"Antwerpen",
    "sg:orig_category":"M\u00e9decins and sp\u00e9cialistes",
    "sg:phone":"+32 3 230 42 00",
    "sg:postcode":"2610",
    "sg:province":"Antwerpen",
    "wof:name":"Gemma Dom",
    "wof:placetype":"venue"
},
  "geometry": {"coordinates":[4.4221029282,51.178943634],"type":"Point"}
}