{
  "type": "Feature",
  "properties": {
    "iso:country":"BE",
    "sg:address":"Rue Grande 58",
    "sg:city":"Quevy",
    "sg:orig_category":"Brood, gebak and snoepgoed",
    "sg:phone":"+32 65 56 87 20",
    "sg:postcode":"7040",
    "sg:province":"Hainaut",
    "wof:name":"Au P'tit Pierre",
    "wof:placetype":"venue"
},
  "geometry": {"coordinates":[3.9133300781,50.3905181885],"type":"Point"}
}