{
  "type": "Feature",
  "properties": {
    "addr:full":"Kerkstraat 34 Vorselaar Antwerpen 2290",
    "addr:housenumber":"34",
    "addr:postcode":"2290",
    "addr:street":"Kerkstraat",
    "iso:country":"BE",
    "sg:address":"Kerkstraat 34",
    "sg:city":"Vorselaar",
    "sg:classifiers":[
        {
            "category":"Food & Beverages",
            "subcategory":"Fruits & Vegetables",
            "type":"Retail Goods"
        }
    ],
    "sg:phone":"+32 14 50 29 14",
    "sg:postcode":"2290",
    "sg:province":"Antwerpen",
    "sg:tags":[
        "-"
    ],
    "wof:name":"Poelmans W",
    "wof:placetype":"venue"
},
  "geometry": {"coordinates":[4.7688398361,51.2029914856],"type":"Point"}
}