{
  "type": "Feature",
  "properties": {
    "iso:country":"BE",
    "sg:address":"Shopping Cora",
    "sg:city":"Chatelet",
    "sg:classifiers":[
        {
            "category":"Personal",
            "subcategory":"Beauty Salon",
            "type":"Services"
        }
    ],
    "sg:phone":"+32 71 39 09 97",
    "sg:postcode":"6200",
    "sg:province":"Hainaut",
    "sg:tags":[
        "de",
        "coiffure"
    ],
    "wof:name":"Hair Coif",
    "wof:placetype":"venue"
},
  "geometry": {"coordinates":[4.5236740112,50.4041366577],"type":"Point"}
}