{
  "type": "Feature",
  "properties": {
    "addr:full":"Avelgemstraat 12 Kluisbergen Oost-Vlaanderen 9690",
    "addr:housenumber":"12",
    "addr:postcode":"9690",
    "addr:street":"Avelgemstraat",
    "iso:country":"BE",
    "sg:address":"Avelgemstraat 12",
    "sg:city":"Kluisbergen",
    "sg:orig_category":"Entretien and r\u00e9parations de voitures. V\u00e9hicules automobiles",
    "sg:phone":"+32 55 38 84 58",
    "sg:postcode":"9690",
    "sg:province":"Oost-Vlaanderen",
    "wof:name":"Garage Baert",
    "wof:placetype":"venue"
},
  "geometry": {"coordinates":[3.4770450592,50.7747879028],"type":"Point"}
}