{
  "type": "Feature",
  "properties": {
    "addr:full":"Lutticher Strasse 27 Kelmis/la Calamine Li\u00e8ge 4721",
    "addr:housenumber":"27",
    "addr:postcode":"4721",
    "addr:street":"Lutticher Strasse",
    "iso:country":"BE",
    "sg:address":"Lutticher Strasse 27",
    "sg:city":"Kelmis/la Calamine",
    "sg:classifiers":[
        {
            "category":"Cafe",
            "type":"Food & Drink"
        }
    ],
    "sg:phone":"+32 87 65 91 57",
    "sg:postcode":"4721",
    "sg:province":"Li\u00e8ge",
    "sg:tags":[
        "caf\u00e9s"
    ],
    "wof:name":"J. Pohlen",
    "wof:placetype":"venue"
},
  "geometry": {"coordinates":[6.0300579071,50.7240219116],"type":"Point"}
}