{
  "type": "Feature",
  "properties": {
    "iso:country":"BE",
    "sg:address":"St. Amandsesteenweg 225-1",
    "sg:city":"Bornem",
    "sg:classifiers":[
        {
            "category":"Arena",
            "subcategory":"Sports Club",
            "type":"Entertainment"
        }
    ],
    "sg:phone":"+32 3 889 73 95",
    "sg:postcode":"2880",
    "sg:province":"Antwerpen",
    "sg:tags":[
        "de"
    ],
    "wof:name":"Samoerai",
    "wof:placetype":"venue"
},
  "geometry": {"coordinates":[4.2232899666,51.0857315063],"type":"Point"}
}