{
  "type": "Feature",
  "properties": {
    "addr:full":"Diksmuidsesteenweg 388 Roeselare West-Vlaanderen 8800",
    "addr:housenumber":"388",
    "addr:postcode":"8800",
    "addr:street":"Diksmuidsesteenweg",
    "iso:country":"BE",
    "sg:address":"Diksmuidsesteenweg 388",
    "sg:city":"Roeselare",
    "sg:orig_category":"Drukkerijen and copyshops Film-, tv- and videoproductie Fotografen and fotostudio's Kantoor- and win",
    "sg:phone":"+32 51 22 77 74",
    "sg:postcode":"8800",
    "sg:province":"West-Vlaanderen",
    "wof:name":"Crea",
    "wof:placetype":"venue"
},
  "geometry": {"coordinates":[3.1034119129,50.9501342773],"type":"Point"}
}