{
  "type": "Feature",
  "properties": {
    "iso:country":"BE",
    "sg:address":"Rue Du Moulin 4",
    "sg:city":"Courcelles (gouy-lez-pi\u00e9ton)",
    "sg:classifiers":[
        {
            "category":"Building & Trades",
            "subcategory":"Landscaping Services",
            "type":"Services"
        }
    ],
    "sg:phone":"+32 71 84 69 48",
    "sg:postcode":"6181",
    "sg:province":"Hainaut",
    "sg:tags":[
        "architect",
        "landscape"
    ],
    "wof:name":"Andr\u00e9 O",
    "wof:placetype":"venue"
},
  "geometry": {"coordinates":[4.32878685,50.4905128479],"type":"Point"}
}