{
  "type": "Feature",
  "properties": {
    "addr:full":"Grote Baan 45 Lovendegem Oost-Vlaanderen 9920",
    "addr:housenumber":"45",
    "addr:postcode":"9920",
    "addr:street":"Grote Baan",
    "iso:country":"BE",
    "sg:address":"Grote Baan 45",
    "sg:city":"Lovendegem",
    "sg:classifiers":[
        {
            "category":"Building & Trades",
            "subcategory":"Electrical",
            "type":"Services"
        }
    ],
    "sg:phone":"+32 9 372 72 72",
    "sg:postcode":"9920",
    "sg:province":"Oost-Vlaanderen",
    "sg:tags":[
        "electric",
        "-",
        "housewiring",
        "contractor"
    ],
    "wof:name":"Ingels D",
    "wof:placetype":"venue"
},
  "geometry": {"coordinates":[3.6399331093,51.0962142944],"type":"Point"}
}