{
  "type": "Feature",
  "properties": {
    "iso:country":"BE",
    "sg:address":"Adolf Buylstraat 36",
    "sg:city":"Oostende",
    "sg:orig_category":"Sous-v\u00eatements and lingerie. V\u00eatements pour Hommes. V\u00eatements pour Dames",
    "sg:phone":"+32 59 70 17 36",
    "sg:postcode":"8400",
    "sg:province":"West-Vlaanderen",
    "wof:name":"M. Vandaele",
    "wof:placetype":"venue"
},
  "geometry": {"coordinates":[2.9156029224,51.2312927246],"type":"Point"}
}