{
  "type": "Feature",
  "properties": {
    "iso:country":"BE",
    "sg:address":"Polderstraat 27",
    "sg:city":"Londerzeel",
    "sg:orig_category":"Installation \u00e9lectrique r\u00e9sidentielle",
    "sg:phone":"+32 52 30 97 06",
    "sg:postcode":"1840",
    "sg:province":"Vlaams-Brabant",
    "wof:name":"Danny Bosman",
    "wof:placetype":"venue"
},
  "geometry": {"coordinates":[4.2969250679,51.0009880066],"type":"Point"}
}