{
  "type": "Feature",
  "properties": {
    "addr:full":"Kapellelaan 350 Meise Vlaams-Brabant 1860",
    "addr:housenumber":"350",
    "addr:postcode":"1860",
    "addr:street":"Kapellelaan",
    "iso:country":"BE",
    "sg:address":"Kapellelaan 350",
    "sg:city":"Meise",
    "sg:classifiers":[
        {
            "category":"Personal",
            "subcategory":"Barber",
            "type":"Services"
        }
    ],
    "sg:phone":"+32 2 269 66 21",
    "sg:postcode":"1860",
    "sg:province":"Vlaams-Brabant",
    "sg:tags":[
        "gentleman",
        "salon",
        "-",
        "hairdressing"
    ],
    "wof:name":"Studio Nadia",
    "wof:placetype":"venue"
},
  "geometry": {"coordinates":[4.3434300423,50.9589614868],"type":"Point"}
}