{
  "type": "Feature",
  "properties": {
    "addr:full":"Waide Des Dames 9 Li\u00e8ge 1 (grivegn\u00e9e) Li\u00e8ge 4030",
    "addr:housenumber":"9;1",
    "addr:postcode":"4030",
    "addr:street":"Waide Des Dames",
    "iso:country":"BE",
    "sg:address":"Waide Des Dames 9",
    "sg:city":"Li\u00e8ge 1 (grivegn\u00e9e)",
    "sg:classifiers":[
        {
            "category":"Arena",
            "subcategory":"Sports Club",
            "type":"Entertainment"
        }
    ],
    "sg:phone":"+32 4 343 27 53",
    "sg:postcode":"4030",
    "sg:province":"Li\u00e8ge",
    "wof:name":"A.t.s.",
    "wof:placetype":"venue"
},
  "geometry": {"coordinates":[5.6054449081,50.6280860901],"type":"Point"}
}