{
  "type": "Feature",
  "properties": {
    "iso:country":"BE",
    "sg:address":"Avenue Milcamps 154",
    "sg:city":"Bruxelles (schaerbeek)",
    "sg:classifiers":[
        {
            "category":"Farming",
            "subcategory":"Fish & Marine Products",
            "type":"Manufacturing & Wholesale Goods"
        }
    ],
    "sg:phone":"+32 2 742 16 65",
    "sg:postcode":"1030",
    "sg:province":"Bruxelles-Capitale",
    "sg:tags":[
        "retail",
        "-",
        "shellfish"
    ],
    "wof:name":"Au Cadre Noir Sprl Sprl",
    "wof:placetype":"venue"
},
  "geometry": {"coordinates":[4.3950400352,50.8525772095],"type":"Point"}
}