{
  "type": "Feature",
  "properties": {
    "addr:full":"Hoogstraatseweg 62 Wuustwezel (loenhout) Antwerpen 2990",
    "addr:housenumber":"62",
    "addr:postcode":"2990",
    "addr:street":"Hoogstraatseweg",
    "iso:country":"BE",
    "sg:address":"Hoogstraatseweg 62",
    "sg:city":"Wuustwezel (loenhout)",
    "sg:orig_category":"Auctions - Greens, fruits, etc",
    "sg:phone":"+32 3 340 02 38",
    "sg:postcode":"2990",
    "sg:province":"Antwerpen",
    "wof:name":"Van Hooydonck Evita Bvba",
    "wof:placetype":"venue"
},
  "geometry": {"coordinates":[4.6525058746,51.4024009705],"type":"Point"}
}