{
  "type": "Feature",
  "properties": {
    "iso:country":"BE",
    "sg:address":"Koolmijnlaan 384",
    "sg:city":"Beverlo",
    "sg:orig_category":"Rijscholen",
    "sg:phone":"+32 11 45 38 34",
    "sg:postcode":"3581",
    "sg:province":"Limburg",
    "wof:name":"Rijschool De Schepper",
    "wof:placetype":"venue"
},
  "geometry": {"coordinates":[5.2189798355,51.0791625977],"type":"Point"}
}