{
  "type": "Feature",
  "properties": {
    "iso:country":"BE",
    "sg:address":"Place De La Station 20",
    "sg:city":"Namur",
    "sg:classifiers":[
        {
            "category":"Bars & Pubs",
            "type":"Food & Drink"
        }
    ],
    "sg:phone":"+32 81 23 13 30",
    "sg:postcode":"5000",
    "sg:province":"Namur",
    "wof:name":"Bon Vieux-temps (au)",
    "wof:placetype":"venue"
},
  "geometry": {"coordinates":[4.862364769,50.4682617188],"type":"Point"}
}