{
  "type": "Feature",
  "properties": {
    "iso:country":"BE",
    "sg:address":"Rue Des Frontaliers 65",
    "sg:city":"Mouscron (herseaux)",
    "sg:classifiers":[
        {
            "category":"Personal",
            "subcategory":"Beauty Salon",
            "type":"Services"
        }
    ],
    "sg:phone":"+32 56 34 65 56",
    "sg:postcode":"7712",
    "sg:province":"Hainaut",
    "sg:tags":[
        "lady",
        "-",
        "hairdressing"
    ],
    "wof:name":"Anne-francoise",
    "wof:placetype":"venue"
},
  "geometry": {"coordinates":[3.2290248871,50.72397995],"type":"Point"}
}