{
  "type": "Feature",
  "properties": {
    "iso:country":"BE",
    "sg:address":"Oude Vest 52",
    "sg:city":"Dendermonde",
    "sg:orig_category":"Maroquinerie and articles de voyage",
    "sg:phone":"+32 52 21 00 59",
    "sg:postcode":"9200",
    "sg:province":"Oost-Vlaanderen",
    "wof:name":"Huis Janique",
    "wof:placetype":"venue"
},
  "geometry": {"coordinates":[4.1012420654,51.0288124084],"type":"Point"}
}