{
  "type": "Feature",
  "properties": {
    "addr:full":"Rue De Jos\u00c9 56 Herve Li\u00e8ge 4651",
    "addr:housenumber":"56",
    "addr:postcode":"4651",
    "addr:street":"Rue De Jose\u0301",
    "iso:country":"BE",
    "sg:address":"Rue De Jos\u00c9 56",
    "sg:city":"Herve",
    "sg:orig_category":"Pain, p\u00e2tisseries and confiseries",
    "sg:phone":"+32 87 66 29 87",
    "sg:postcode":"4651",
    "sg:province":"Li\u00e8ge",
    "wof:name":"Maison La Manon",
    "wof:placetype":"venue"
},
  "geometry": {"coordinates":[5.7733812332,50.6316604614],"type":"Point"}
}