{
  "type": "Feature",
  "properties": {
    "iso:country":"BE",
    "sg:address":"Hemeldonk 8",
    "sg:city":"Lille (gierle)",
    "sg:classifiers":[
        {
            "category":"Utilities",
            "subcategory":"Natural Gas",
            "type":"Services"
        }
    ],
    "sg:phone":"+32 14 55 17 06",
    "sg:postcode":"2275",
    "sg:province":"Antwerpen",
    "sg:tags":[
        "welding"
    ],
    "wof:name":"Rombouts",
    "wof:placetype":"venue"
},
  "geometry": {"coordinates":[4.8551630974,51.2720870972],"type":"Point"}
}