{
  "type": "Feature",
  "properties": {
    "iso:country":"BE",
    "sg:address":"Rue Vertbreucq 36",
    "sg:city":"Mont-de-l\u00b4enclus",
    "sg:orig_category":"Paramedische behandelingen",
    "sg:phone":"+32 69 45 40 33",
    "sg:postcode":"7750",
    "sg:province":"Hainaut",
    "wof:name":"C. Busine",
    "wof:placetype":"venue"
},
  "geometry": {"coordinates":[3.4877998829,50.7450561523],"type":"Point"}
}