{
  "type": "Feature",
  "properties": {
    "addr:full":"Rue Des Croquets 25 Manage Hainaut 7170",
    "addr:housenumber":"25",
    "addr:postcode":"7170",
    "addr:street":"Rue Des Croquets",
    "iso:country":"BE",
    "sg:address":"Rue Des Croquets 25",
    "sg:city":"Manage",
    "sg:orig_category":"Kapsalons",
    "sg:phone":"+32 64 21 22 28",
    "sg:postcode":"7170",
    "sg:province":"Hainaut",
    "wof:name":"Jean Chapuis",
    "wof:placetype":"venue"
},
  "geometry": {"coordinates":[4.2364988327,50.4776763916],"type":"Point"}
}