{
  "type": "Feature",
  "properties": {
    "addr:full":"Hundelgemsesteenweg 124 Merelbeke Oost-Vlaanderen 9820",
    "addr:housenumber":"124",
    "addr:postcode":"9820",
    "addr:street":"Hundelgemsesteenweg",
    "iso:country":"BE",
    "sg:address":"Hundelgemsesteenweg 124",
    "sg:city":"Merelbeke",
    "sg:classifiers":[
        {
            "category":"Personal",
            "subcategory":"Barber",
            "type":"Services"
        }
    ],
    "sg:phone":"+32 9 230 84 80",
    "sg:postcode":"9820",
    "sg:province":"Oost-Vlaanderen",
    "sg:tags":[
        "gentleman",
        "salon",
        "-",
        "hairdressing"
    ],
    "wof:name":"Ornaro",
    "wof:placetype":"venue"
},
  "geometry": {"coordinates":[3.7517058849,51.0105514526],"type":"Point"}
}