{
  "type": "Feature",
  "properties": {
    "iso:country":"BE",
    "sg:address":"Rue Delatte 8",
    "sg:city":"La Louvi\u00c8re",
    "sg:classifiers":[
        {
            "category":"Cafe",
            "type":"Food & Drink"
        }
    ],
    "sg:phone":"+32 64 67 52 74",
    "sg:postcode":"7110",
    "sg:province":"Hainaut",
    "sg:tags":[
        "caf\u00e9s"
    ],
    "wof:name":"Brameco",
    "wof:placetype":"venue"
},
  "geometry": {"coordinates":[4.1505050659,50.4826698303],"type":"Point"}
}