{
  "type": "Feature",
  "properties": {
    "addr:full":"Stationstr. 84 Lendelede West-Vlaanderen 8860",
    "addr:housenumber":"84",
    "addr:postcode":"8860",
    "addr:street":"Stationstr.",
    "iso:country":"BE",
    "sg:address":"Stationstr. 84",
    "sg:city":"Lendelede",
    "sg:classifiers":[
        {
            "category":"Shopping",
            "subcategory":"Crafts & Fabrics",
            "type":"Retail Goods"
        }
    ],
    "sg:phone":"+32 51 33 38 88",
    "sg:postcode":"8860",
    "sg:province":"West-Vlaanderen",
    "sg:tags":[
        "textile",
        "clothing"
    ],
    "wof:name":"Neirynck-holvoet Nv",
    "wof:placetype":"venue"
},
  "geometry": {"coordinates":[3.2497799397,50.8854598999],"type":"Point"}
}