{
  "type": "Feature",
  "properties": {
    "addr:full":"Rue Du Trou 2 Silly Hainaut 7830",
    "addr:housenumber":"2",
    "addr:postcode":"7830",
    "addr:street":"Rue Du Trou",
    "iso:country":"BE",
    "sg:address":"Rue Du Trou 2",
    "sg:city":"Silly",
    "sg:orig_category":"Eleveurs de bovins",
    "sg:phone":"+32 2 395 85 46",
    "sg:postcode":"7830",
    "sg:province":"Hainaut",
    "wof:name":"Duret Leon & Eric",
    "wof:placetype":"venue"
},
  "geometry": {"coordinates":[4.041613102,50.6432151794],"type":"Point"}
}