{
  "type": "Feature",
  "properties": {
    "iso:country":"BE",
    "sg:address":"Rue De Charleroi 21",
    "sg:city":"Genappe",
    "sg:classifiers":[
        {
            "category":"Shopping",
            "subcategory":"Bicycles & Sporting Goods",
            "type":"Retail Goods"
        }
    ],
    "sg:phone":"+32 67 77 24 57",
    "sg:postcode":"1470",
    "sg:province":"Brabant Wallon",
    "sg:tags":[
        "sport",
        "-"
    ],
    "wof:name":"Genasports",
    "wof:placetype":"venue"
},
  "geometry": {"coordinates":[4.4509539604,50.6097640991],"type":"Point"}
}