{
  "type": "Feature",
  "properties": {
    "iso:country":"BE",
    "sg:address":"Avenue Du Saphir 9",
    "sg:city":"Braine-l\u00b4alleud",
    "sg:orig_category":"M\u00e9decins and sp\u00e9cialistes",
    "sg:phone":"+32 2 354 87 53",
    "sg:postcode":"1420",
    "sg:province":"Brabant Wallon",
    "wof:name":"Sophie Matagne",
    "wof:placetype":"venue"
},
  "geometry": {"coordinates":[4.3340711594,50.73387146],"type":"Point"}
}