{
  "type": "Feature",
  "properties": {
    "addr:full":"Kapelstraat 109 Sint-niklaas Oost-Vlaanderen 9100",
    "addr:housenumber":"109",
    "addr:postcode":"9100",
    "addr:street":"Kapelstraat",
    "iso:country":"BE",
    "sg:address":"Kapelstraat 109",
    "sg:city":"Sint-niklaas",
    "sg:classifiers":[
        {
            "category":"Autos & Motor Vehicles",
            "subcategory":"Motorcycle Sales",
            "type":"Retail Goods"
        }
    ],
    "sg:phone":"+32 3 766 14 44",
    "sg:postcode":"9100",
    "sg:province":"Oost-Vlaanderen",
    "sg:tags":[
        "motorbike"
    ],
    "wof:name":"Bakens Benelux Service Bvba",
    "wof:placetype":"venue"
},
  "geometry": {"coordinates":[4.1552147865,51.1510124207],"type":"Point"}
}