{
  "type": "Feature",
  "properties": {
    "addr:full":"Avenue Van Cutsem 17 Tournai Hainaut 7500",
    "addr:housenumber":"17",
    "addr:postcode":"7500",
    "addr:street":"Avenue Van Cutsem",
    "iso:country":"BE",
    "sg:address":"Avenue Van Cutsem 17",
    "sg:city":"Tournai",
    "sg:orig_category":"M\u00e9decins and sp\u00e9cialistes",
    "sg:phone":"+32 69 21 34 22",
    "sg:postcode":"7500",
    "sg:province":"Hainaut",
    "wof:name":"Arthur Chapelle",
    "wof:placetype":"venue"
},
  "geometry": {"coordinates":[3.3981490135,50.6112060547],"type":"Point"}
}