{
  "type": "Feature",
  "properties": {
    "addr:full":"Rue Albert Goossens 6 Ramillies Brabant Wallon 1367",
    "addr:housenumber":"6",
    "addr:postcode":"1367",
    "addr:street":"Rue Albert Goossens",
    "iso:country":"BE",
    "sg:address":"Rue Albert Goossens 6",
    "sg:city":"Ramillies",
    "sg:orig_category":"Rundveehouders",
    "sg:phone":"+32 81 87 71 62",
    "sg:postcode":"1367",
    "sg:province":"Brabant Wallon",
    "wof:name":"Masson E. & Pierard S.",
    "wof:placetype":"venue"
},
  "geometry": {"coordinates":[4.9146900177,50.636631012],"type":"Point"}
}