{
  "type": "Feature",
  "properties": {
    "iso:country":"BE",
    "sg:address":"Bredestraat 8",
    "sg:city":"Antwerpen",
    "sg:classifiers":[
        {
            "category":"Home & Garden",
            "subcategory":"Home Furnishings",
            "type":"Retail Goods"
        }
    ],
    "sg:phone":"+32 3 232 70 18",
    "sg:postcode":"2000",
    "sg:province":"Antwerpen",
    "sg:tags":[
        "curtain",
        "-",
        "fixture"
    ],
    "wof:name":"Verbeeck Christine & Valerie Decoratie",
    "wof:placetype":"venue"
},
  "geometry": {"coordinates":[4.4019980431,51.2150421143],"type":"Point"}
}