{
  "type": "Feature",
  "properties": {
    "addr:full":"Boomstraat 1 Dikkelvenne Oost-Vlaanderen 9890",
    "addr:housenumber":"1",
    "addr:postcode":"9890",
    "addr:street":"Boomstraat;Oost-Vlaanderen",
    "iso:country":"BE",
    "sg:address":"Boomstraat 1",
    "sg:city":"Dikkelvenne",
    "sg:orig_category":"Vakantiehuizen",
    "sg:phone":"+32 498 91 85 40",
    "sg:postcode":"9890",
    "sg:province":"Oost-Vlaanderen",
    "wof:name":"Tichelhoeve",
    "wof:placetype":"venue"
},
  "geometry": {"coordinates":[3.7206408978,50.9199867249],"type":"Point"}
}