{
  "type": "Feature",
  "properties": {
    "iso:country":"BE",
    "sg:address":"3640",
    "sg:city":"Kinrooi (groot)",
    "sg:orig_category":"Pharmaciens",
    "sg:phone":"+32 900 10 500",
    "sg:postcode":"3640",
    "sg:province":"Limburg",
    "wof:name":"Pharmacies De Garde",
    "wof:placetype":"venue"
},
  "geometry": {"coordinates":[5.7422151566,51.1452484131],"type":"Point"}
}