{
  "type": "Feature",
  "properties": {
    "addr:full":"Baliestraat 2 Kortrijk West-Vlaanderen 8510",
    "addr:housenumber":"2",
    "addr:postcode":"8510",
    "addr:street":"Baliestraat",
    "iso:country":"BE",
    "sg:address":"Baliestraat 2",
    "sg:city":"Kortrijk",
    "sg:orig_category":"Eclairage et \u00e9quipements du foyer. Installation \u00e9lectrique r\u00e9sidentielle",
    "sg:phone":"+32 56 20 21 53",
    "sg:postcode":"8510",
    "sg:province":"West-Vlaanderen",
    "wof:name":"Sammy Nolf",
    "wof:placetype":"venue"
},
  "geometry": {"coordinates":[3.2440190315,50.8061904907],"type":"Point"}
}