{
  "type": "Feature",
  "properties": {
    "addr:full":"Avenue D'auderghem 4 Bruxelles (etterbeek) Bruxelles-Capitale 1040",
    "addr:housenumber":"4",
    "addr:postcode":"1040",
    "addr:street":"Avenue D'Auderghem",
    "iso:country":"BE",
    "sg:address":"Avenue D'auderghem 4",
    "sg:city":"Bruxelles (etterbeek)",
    "sg:classifiers":[
        {
            "category":"Bars & Pubs",
            "type":"Food & Drink"
        }
    ],
    "sg:phone":"+32 2 280 28 77",
    "sg:postcode":"1040",
    "sg:province":"Bruxelles-Capitale",
    "sg:tags":[
        "tavern"
    ],
    "wof:name":"1898 (le) Brasserie",
    "wof:placetype":"venue"
},
  "geometry": {"coordinates":[4.3843522072,50.8419685364],"type":"Point"}
}