{
  "type": "Feature",
  "properties": {
    "iso:country":"BE",
    "sg:address":"Vijfseweg 49",
    "sg:city":"Waregem",
    "sg:orig_category":"Decoratieve kunst and kunstbenodigdheden",
    "sg:phone":"+32 56 60 21 29",
    "sg:postcode":"8790",
    "sg:province":"West-Vlaanderen",
    "wof:name":"Luc Van Robaeys",
    "wof:placetype":"venue"
},
  "geometry": {"coordinates":[3.4215409756,50.896938324],"type":"Point"}
}