{
  "type": "Feature",
  "properties": {
    "iso:country":"BE",
    "sg:address":"Rue Mattot 106ba",
    "sg:city":"Waterloo",
    "sg:orig_category":"Boekhouders",
    "sg:phone":"+32 2 354 09 67",
    "sg:postcode":"1410",
    "sg:province":"Brabant Wallon",
    "wof:name":"Laurent Paulus",
    "wof:placetype":"venue"
},
  "geometry": {"coordinates":[4.3786230087,50.7114524841],"type":"Point"}
}