{
  "type": "Feature",
  "properties": {
    "iso:country":"BE",
    "sg:address":"Rue Hack 9-11",
    "sg:city":"Plombi\u00e8res (hombourg)",
    "sg:classifiers":[
        {
            "category":"Bakery",
            "type":"Food & Drink"
        }
    ],
    "sg:phone":"+32 87 78 54 53",
    "sg:postcode":"4852",
    "sg:province":"Li\u00e8ge",
    "sg:tags":[
        "confectioner",
        "baker"
    ],
    "wof:name":"Born E",
    "wof:placetype":"venue"
},
  "geometry": {"coordinates":[5.9598479271,50.7376213074],"type":"Point"}
}