{
  "type": "Feature",
  "properties": {
    "addr:full":"Markt 33 Deinze Oost-Vlaanderen 9800",
    "addr:housenumber":"33",
    "addr:postcode":"9800",
    "addr:street":"Markt",
    "iso:country":"BE",
    "sg:address":"Markt 33",
    "sg:city":"Deinze",
    "sg:orig_category":"Agences d\u00b4interim and personnel temporaire",
    "sg:phone":"+32 9 380 80 32",
    "sg:postcode":"9800",
    "sg:province":"Oost-Vlaanderen",
    "wof:name":"Adecco",
    "wof:placetype":"venue"
},
  "geometry": {"coordinates":[3.5268349648,50.984752655],"type":"Point"}
}