{
  "type": "Feature",
  "properties": {
    "iso:country":"BE",
    "sg:address":"Avenue Joseph Wauters 19",
    "sg:city":"Virton (saint-mard)",
    "sg:classifiers":[
        {
            "category":"Retail",
            "subcategory":"Veterinary Services",
            "type":"Services"
        }
    ],
    "sg:phone":"+32 63 57 88 81",
    "sg:postcode":"6762",
    "sg:province":"Luxembourg",
    "sg:tags":[
        "veterinarian"
    ],
    "wof:name":"Kasaby M",
    "wof:placetype":"venue"
},
  "geometry": {"coordinates":[5.5332231522,49.5546951294],"type":"Point"}
}