{
  "type": "Feature",
  "properties": {
    "addr:full":"Ieperstraat 15a Oostende West-Vlaanderen 8400",
    "addr:housenumber":"15a",
    "addr:postcode":"8400",
    "addr:street":"Ieperstraat",
    "iso:country":"BE",
    "sg:address":"Ieperstraat 15a",
    "sg:city":"Oostende",
    "sg:classifiers":[
        {
            "category":"Shopping",
            "subcategory":"Clothing, Apparel, & Fashions",
            "type":"Retail Goods"
        }
    ],
    "sg:phone":"+32 59 51 95 00",
    "sg:postcode":"8400",
    "sg:province":"West-Vlaanderen",
    "sg:tags":[
        "purchase",
        "clothing",
        "-",
        "sale",
        "second-hand"
    ],
    "wof:name":"De Vlinder",
    "wof:placetype":"venue"
},
  "geometry": {"coordinates":[2.9152851105,51.2262306213],"type":"Point"}
}