{
  "type": "Feature",
  "properties": {
    "addr:full":"Bergveld 69 Westerlo Antwerpen 2260",
    "addr:housenumber":"69",
    "addr:postcode":"2260",
    "addr:street":"Bergveld",
    "iso:country":"BE",
    "sg:address":"Bergveld 69",
    "sg:city":"Westerlo",
    "sg:orig_category":"Loodgieterij, verwarming and sanitaire installaties",
    "sg:phone":"+32 14 54 66 60",
    "sg:postcode":"2260",
    "sg:province":"Antwerpen",
    "wof:name":"Van Eepoel Marc",
    "wof:placetype":"venue"
},
  "geometry": {"coordinates":[4.8754181862,51.0815658569],"type":"Point"}
}