{
  "type": "Feature",
  "properties": {
    "iso:country":"BE",
    "sg:address":"Mechelseweg 43",
    "sg:city":"Kapelle-op-den-bos",
    "sg:classifiers":[
        {
            "category":"Home & Garden",
            "subcategory":"Building Materials",
            "type":"Retail Goods"
        }
    ],
    "sg:phone":"+32 15 71 02 71",
    "sg:postcode":"1880",
    "sg:province":"Vlaams-Brabant",
    "sg:tags":[
        "bathroom",
        "installation",
        "accessory"
    ],
    "wof:name":"De Decker M Bvba",
    "wof:placetype":"venue"
},
  "geometry": {"coordinates":[4.3724999428,51.0122146606],"type":"Point"}
}