{
  "type": "Feature",
  "properties": {
    "iso:country":"BE",
    "sg:address":"Chauss\u00c9e De Mons 66",
    "sg:city":"Soignies",
    "sg:orig_category":"Editeurs de revues and p\u00e9riodiques. Editeurs de journaux",
    "sg:phone":"+32 67 33 35 35",
    "sg:postcode":"7060",
    "sg:province":"Hainaut",
    "wof:name":"Cayoteu",
    "wof:placetype":"venue"
},
  "geometry": {"coordinates":[4.0651102066,50.5692062378],"type":"Point"}
}