{
  "type": "Feature",
  "properties": {
    "addr:full":"Collegelaan 5 Genk Limburg 3600",
    "addr:housenumber":"5",
    "addr:postcode":"3600",
    "addr:street":"Collegelaan",
    "iso:country":"BE",
    "sg:address":"Collegelaan 5",
    "sg:city":"Genk",
    "sg:orig_category":"Enseignement maternel and primaire",
    "sg:phone":"+32 89 35 64 44",
    "sg:postcode":"3600",
    "sg:province":"Limburg",
    "wof:name":"Vrije Lagere School",
    "wof:placetype":"venue"
},
  "geometry": {"coordinates":[5.5184941292,50.9765090942],"type":"Point"}
}