{
  "type": "Feature",
  "properties": {
    "iso:country":"BE",
    "sg:address":"Rue De Tournai 141b4",
    "sg:city":"Pecq",
    "sg:orig_category":"Maisons de repos and r\u00e9sidences",
    "sg:phone":"+32 69 55 89 35",
    "sg:postcode":"7740",
    "sg:province":"Hainaut",
    "wof:name":"R\u00c9sidence Edelweiss",
    "wof:placetype":"venue"
},
  "geometry": {"coordinates":[3.3393139839,50.6786193848],"type":"Point"}
}