{
  "type": "Feature",
  "properties": {
    "iso:country":"BE",
    "sg:address":"Rogery 11",
    "sg:city":"Gouvy (bovigny)",
    "sg:classifiers":[
        {
            "category":"Manufacturing",
            "subcategory":"Metals",
            "type":"Manufacturing & Wholesale Goods"
        }
    ],
    "sg:phone":"+32 80 21 55 35",
    "sg:postcode":"6671",
    "sg:province":"Luxembourg",
    "sg:tags":[
        "ironwork"
    ],
    "wof:name":"Hurdebise J",
    "wof:placetype":"venue"
},
  "geometry": {"coordinates":[5.9485387802,50.2421951294],"type":"Point"}
}