{
  "type": "Feature",
  "properties": {
    "iso:country":"BE",
    "sg:address":"Tiensestraat 224",
    "sg:city":"Leuven",
    "sg:orig_category":"Elektrische installaties voor woningen Industri\u00eble elektrische installaties",
    "sg:phone":"+32 16 23 71 71",
    "sg:postcode":"3000",
    "sg:province":"Vlaams-Brabant",
    "wof:name":"D-tect",
    "wof:placetype":"venue"
},
  "geometry": {"coordinates":[4.7119231224,50.8742027283],"type":"Point"}
}