{
  "type": "Feature",
  "properties": {
    "iso:country":"BE",
    "sg:address":"Place Communale 1",
    "sg:city":"Jemeppe-sur-sambre",
    "sg:classifiers":[
        {
            "category":"Communications",
            "subcategory":"Film & Video Production",
            "type":"Services"
        }
    ],
    "sg:phone":"+32 71 78 08 55",
    "sg:postcode":"5190",
    "sg:province":"Namur",
    "sg:tags":[
        "equipment",
        "-",
        "sale",
        "supply"
    ],
    "wof:name":"Jungle Video",
    "wof:placetype":"venue"
},
  "geometry": {"coordinates":[4.6684741974,50.4658355713],"type":"Point"}
}