{
  "type": "Feature",
  "properties": {
    "addr:full":"Nederenamestraat 336 Oudenaarde Oost-Vlaanderen 9700",
    "addr:housenumber":"336",
    "addr:postcode":"9700",
    "addr:street":"Nederenamestraat",
    "iso:country":"BE",
    "sg:address":"Nederenamestraat 336",
    "sg:city":"Oudenaarde",
    "sg:classifiers":[
        {
            "category":"Retail",
            "subcategory":"Auto Repair",
            "type":"Services"
        }
    ],
    "sg:phone":"+32 55 49 86 41",
    "sg:postcode":"9700",
    "sg:province":"Oost-Vlaanderen",
    "sg:tags":[
        "garage"
    ],
    "wof:name":"Barb\u00e9 D",
    "wof:placetype":"venue"
},
  "geometry": {"coordinates":[3.6548631191,50.8695220947],"type":"Point"}
}