{
  "type": "Feature",
  "properties": {
    "addr:full":"Suikerrui 5 Box 3 Antwerpen Antwerpen 2000",
    "addr:housenumber":"5;3",
    "addr:postcode":"2000",
    "addr:street":"Suikerrui;Box",
    "iso:country":"BE",
    "sg:address":"Suikerrui 5 Box 3",
    "sg:city":"Antwerpen",
    "sg:classifiers":[
        {
            "category":"Manufacturing",
            "subcategory":"Metals",
            "type":"Manufacturing & Wholesale Goods"
        }
    ],
    "sg:phone":"+32 3 232 40 98",
    "sg:postcode":"2000",
    "sg:province":"Antwerpen",
    "sg:tags":[
        "alloy",
        "aluminium"
    ],
    "wof:name":"A J Supplies",
    "wof:placetype":"venue"
},
  "geometry": {"coordinates":[4.3974537849,51.2213058472],"type":"Point"}
}