{
  "type": "Feature",
  "properties": {
    "iso:country":"BE",
    "sg:address":"Pastoor Mensaertstraat 26",
    "sg:city":"Beerse",
    "sg:orig_category":"Woningbouw",
    "sg:phone":"+32 3 325 94 04",
    "sg:postcode":"2340",
    "sg:province":"Antwerpen",
    "wof:name":"Albobo",
    "wof:placetype":"venue"
},
  "geometry": {"coordinates":[4.832444191,51.3204269409],"type":"Point"}
}