{
  "type": "Feature",
  "properties": {
    "addr:full":"Rue Alphonse Minique 65a Chastre (saint-g\u00e9ry) Brabant Wallon 1450",
    "addr:housenumber":"65a",
    "addr:postcode":"1450",
    "addr:street":"Rue Alphonse Minique",
    "iso:country":"BE",
    "sg:address":"Rue Alphonse Minique 65a",
    "sg:city":"Chastre (saint-g\u00e9ry)",
    "sg:classifiers":[
        {
            "category":"Real Estate",
            "subcategory":"Surveying",
            "type":"Services"
        }
    ],
    "sg:phone":"+32 71 87 91 19",
    "sg:postcode":"1450",
    "sg:province":"Brabant Wallon",
    "sg:tags":[
        "surveyor",
        "land"
    ],
    "wof:name":"Deneuter B",
    "wof:placetype":"venue"
},
  "geometry": {"coordinates":[4.636452198,50.6085243225],"type":"Point"}
}