{
  "type": "Feature",
  "properties": {
    "addr:full":"Weststraat 7 Kaprijke Oost-Vlaanderen 9971",
    "addr:housenumber":"7",
    "addr:postcode":"9971",
    "addr:street":"Weststraat",
    "iso:country":"BE",
    "sg:address":"Weststraat 7",
    "sg:city":"Kaprijke",
    "sg:orig_category":"Woningbouw",
    "sg:phone":"+32 9 377 12 35",
    "sg:postcode":"9971",
    "sg:province":"Oost-Vlaanderen",
    "wof:name":"A De Buck",
    "wof:placetype":"venue"
},
  "geometry": {"coordinates":[3.6603190899,51.1892089844],"type":"Point"}
}