{
  "type": "Feature",
  "properties": {
    "addr:full":"Roeselaarsestraat 61 Izegem West-Vlaanderen 8870",
    "addr:housenumber":"61",
    "addr:postcode":"8870",
    "addr:street":"Roeselaarsestraat",
    "iso:country":"BE",
    "sg:address":"Roeselaarsestraat 61",
    "sg:city":"Izegem",
    "sg:orig_category":"Banques and organismes de cr\u00e9dit. Assurances",
    "sg:phone":"+32 51 30 04 25",
    "sg:postcode":"8870",
    "sg:province":"West-Vlaanderen",
    "wof:name":"Denys Roland",
    "wof:placetype":"venue"
},
  "geometry": {"coordinates":[3.2097430229,50.9189720154],"type":"Point"}
}