{
  "type": "Feature",
  "properties": {
    "addr:full":"Rue Notre Dame Des Champs 22 Chi\u00e8vres (huissignies) Hainaut 7950",
    "addr:housenumber":"22",
    "addr:postcode":"7950",
    "addr:street":"Rue Notre Dame Des Champs",
    "iso:country":"BE",
    "sg:address":"Rue Notre Dame Des Champs 22",
    "sg:city":"Chi\u00e8vres (huissignies)",
    "sg:classifiers":[
        {
            "category":"Utilities",
            "subcategory":"Telephone",
            "type":"Services"
        }
    ],
    "sg:phone":"+32 69 68 99 17",
    "sg:postcode":"7950",
    "sg:province":"Hainaut",
    "sg:tags":[
        "-",
        "internet"
    ],
    "wof:name":"Labie B",
    "wof:placetype":"venue"
},
  "geometry": {"coordinates":[3.7429680824,50.5649757385],"type":"Point"}
}