{
  "type": "Feature",
  "properties": {
    "addr:full":"Georges Wittouckstraat 159 Sint-pieters-leeuw Vlaams-Brabant 1600",
    "addr:housenumber":"159",
    "addr:postcode":"1600",
    "addr:street":"Georges Wittouckstraat",
    "iso:country":"BE",
    "sg:address":"Georges Wittouckstraat 159",
    "sg:city":"Sint-pieters-leeuw",
    "sg:orig_category":"Kapsalons",
    "sg:phone":"+32 2 377 24 04",
    "sg:postcode":"1600",
    "sg:province":"Vlaams-Brabant",
    "wof:name":"Marc Declerck",
    "wof:placetype":"venue"
},
  "geometry": {"coordinates":[4.2758321762,50.7892608643],"type":"Point"}
}