{
  "type": "Feature",
  "properties": {
    "addr:full":"Kouter 108 Mechelen Antwerpen 2811",
    "addr:housenumber":"108",
    "addr:postcode":"2811",
    "addr:street":"Kouter",
    "iso:country":"BE",
    "sg:address":"Kouter 108",
    "sg:city":"Mechelen",
    "sg:orig_category":"V\u00e9t\u00e9rinaires",
    "sg:phone":"+32 15 41 13 51",
    "sg:postcode":"2811",
    "sg:province":"Antwerpen",
    "wof:name":"Hilde De Rooster",
    "wof:placetype":"venue"
},
  "geometry": {"coordinates":[4.4273309708,51.0234031677],"type":"Point"}
}