{
  "type": "Feature",
  "properties": {
    "addr:full":"Rue Des Faubourgs 1 Arlon Luxembourg 6700",
    "addr:housenumber":"1",
    "addr:postcode":"6700",
    "addr:street":"Rue Des Faubourgs",
    "iso:country":"BE",
    "sg:address":"Rue Des Faubourgs 1",
    "sg:city":"Arlon",
    "sg:classifiers":[
        {
            "category":"Banks & Credit Unions",
            "subcategory":"Bank",
            "type":"Services"
        }
    ],
    "sg:phone":"+32 63 21 21 03",
    "sg:postcode":"6700",
    "sg:province":"Luxembourg",
    "wof:name":"Banque Bruxelles Lambert Sa",
    "wof:placetype":"venue"
},
  "geometry": {"coordinates":[5.8122301102,49.683921814],"type":"Point"}
}