{
  "type": "Feature",
  "properties": {
    "addr:full":"Kerkhofstraat 89 Londerzeel Vlaams-Brabant 1840",
    "addr:housenumber":"89",
    "addr:postcode":"1840",
    "addr:street":"Kerkhofstraat",
    "iso:country":"BE",
    "sg:address":"Kerkhofstraat 89",
    "sg:city":"Londerzeel",
    "sg:orig_category":"Etalage- and showroomontwerpers Plaatsen van vloer- and muurbekleding Schilders",
    "sg:phone":"+32 52 30 10 72",
    "sg:postcode":"1840",
    "sg:province":"Vlaams-Brabant",
    "wof:name":"Tibor Horvath",
    "wof:placetype":"venue"
},
  "geometry": {"coordinates":[4.3104491234,51.0004234314],"type":"Point"}
}