{
  "type": "Feature",
  "properties": {
    "iso:country":"BE",
    "sg:address":"Kasteleinsplein 24",
    "sg:city":"Elsene/ixelles",
    "sg:orig_category":"Opsporingsdiensten and detectivebureaus",
    "sg:phone":"+32 2 366 00 81",
    "sg:postcode":"1050",
    "sg:province":"Bruxelles-Capitale",
    "wof:name":"Douglas D\u00c9tective",
    "wof:placetype":"venue"
},
  "geometry": {"coordinates":[4.3597950935,50.8245010376],"type":"Point"}
}