{
  "type": "Feature",
  "properties": {
    "iso:country":"BE",
    "sg:address":"Rue De La Rochelle 24",
    "sg:city":"Charleroi (roux)",
    "sg:classifiers":[
        {
            "category":"Health Services",
            "subcategory":"Health Practitioner",
            "type":"Services"
        }
    ],
    "sg:phone":"+32 71 45 54 50",
    "sg:postcode":"6044",
    "sg:province":"Hainaut",
    "sg:tags":[
        "physiotherapist"
    ],
    "wof:name":"Michels Ph",
    "wof:placetype":"venue"
},
  "geometry": {"coordinates":[4.3953089714,50.4414176941],"type":"Point"}
}