{
  "type": "Feature",
  "properties": {
    "addr:full":"Brusselsesteenweg 21 Herent (winksele) Vlaams-Brabant 3020",
    "addr:housenumber":"21",
    "addr:postcode":"3020",
    "addr:street":"Brusselsesteenweg",
    "iso:country":"BE",
    "sg:address":"Brusselsesteenweg 21",
    "sg:city":"Herent (winksele)",
    "sg:classifiers":[
        {
            "category":"Retail",
            "subcategory":"Auto Repair",
            "type":"Services"
        }
    ],
    "sg:phone":"+32 16 22 81 34",
    "sg:postcode":"3020",
    "sg:province":"Vlaams-Brabant",
    "sg:tags":[
        "garage"
    ],
    "wof:name":"Charly",
    "wof:placetype":"venue"
},
  "geometry": {"coordinates":[4.6681170464,50.8866729736],"type":"Point"}
}