{
  "type": "Feature",
  "properties": {
    "iso:country":"BE",
    "sg:address":"Nieuwe Steenweg 122",
    "sg:city":"Tongeren",
    "sg:orig_category":"Pain, p\u00e2tisseries and confiseries",
    "sg:phone":"+32 12 26 11 74",
    "sg:postcode":"3700",
    "sg:province":"Limburg",
    "wof:name":"Davy De Wreede",
    "wof:placetype":"venue"
},
  "geometry": {"coordinates":[5.4504909515,50.7980728149],"type":"Point"}
}