{
  "type": "Feature",
  "properties": {
    "addr:full":"Markt 50 Zele Oost-Vlaanderen 9240",
    "addr:housenumber":"50",
    "addr:postcode":"9240",
    "addr:street":"Markt",
    "iso:country":"BE",
    "sg:address":"Markt 50",
    "sg:city":"Zele",
    "sg:classifiers":[
        {
            "category":"Government",
            "subcategory":"Police Station",
            "type":"Public Place"
        }
    ],
    "sg:phone":"+32 52 45 98 45",
    "sg:postcode":"9240",
    "sg:province":"Oost-Vlaanderen",
    "sg:tags":[
        "gendarmerie"
    ],
    "wof:name":"Federale Politie",
    "wof:placetype":"venue"
},
  "geometry": {"coordinates":[4.0371999741,51.0689811707],"type":"Point"}
}