{
  "type": "Feature",
  "properties": {
    "addr:full":"Rue Du Carrefour 165 Seraing (jemeppe-sur-meuse) Li\u00e8ge 4101",
    "addr:housenumber":"165",
    "addr:postcode":"4101",
    "addr:street":"Rue Du Carrefour;Jemeppe-Sur-Meuse",
    "iso:country":"BE",
    "sg:address":"Rue Du Carrefour 165",
    "sg:city":"Seraing (jemeppe-sur-meuse)",
    "sg:classifiers":[
        {
            "category":"Building & Trades",
            "subcategory":"Electrical",
            "type":"Services"
        }
    ],
    "sg:phone":"+32 4 231 20 04",
    "sg:postcode":"4101",
    "sg:province":"Li\u00e8ge",
    "sg:tags":[
        "-",
        "electric",
        "contractor"
    ],
    "wof:name":"G Cab",
    "wof:placetype":"venue"
},
  "geometry": {"coordinates":[5.503921032,50.6160850525],"type":"Point"}
}