{
  "type": "Feature",
  "properties": {
    "addr:full":"Dr. Van De Perrestraat 102 Geel Antwerpen 2440",
    "addr:housenumber":"102",
    "addr:postcode":"2440",
    "addr:street":"Dr. Van De Perrestraat",
    "iso:country":"BE",
    "sg:address":"Dr. Van De Perrestraat 102",
    "sg:city":"Geel",
    "sg:classifiers":[
        {
            "category":"Building & Trades",
            "subcategory":"Construction",
            "type":"Services"
        }
    ],
    "sg:phone":"+32 14 59 25 69",
    "sg:postcode":"2440",
    "sg:province":"Antwerpen",
    "sg:tags":[
        "carpenter"
    ],
    "wof:name":"Wils J Bvba",
    "wof:placetype":"venue"
},
  "geometry": {"coordinates":[4.9870729446,51.1727333069],"type":"Point"}
}