{
  "type": "Feature",
  "properties": {
    "addr:full":"Bruggesteenweg 144ba Hooglede West-Vlaanderen 8830",
    "addr:postcode":"8830",
    "addr:street":"Bruggesteenweg",
    "iso:country":"BE",
    "sg:address":"Bruggesteenweg 144ba",
    "sg:city":"Hooglede",
    "sg:classifiers":[
        {
            "category":"Arena",
            "subcategory":"Sports Club",
            "type":"Entertainment"
        }
    ],
    "sg:phone":"+32 51 22 60 85",
    "sg:postcode":"8830",
    "sg:province":"West-Vlaanderen",
    "sg:tags":[
        "de"
    ],
    "wof:name":"W.c. Voetje Voor Voetje",
    "wof:placetype":"venue"
},
  "geometry": {"coordinates":[3.1185429096,50.9801216125],"type":"Point"}
}