{
  "type": "Feature",
  "properties": {
    "addr:full":"Place De La Victoire 6 Braine-le-comte Hainaut 7090",
    "addr:housenumber":"6",
    "addr:postcode":"7090",
    "addr:street":"Place De La Victoire",
    "iso:country":"BE",
    "sg:address":"Place De La Victoire 6",
    "sg:city":"Braine-le-comte",
    "sg:orig_category":"M\u00e9decins and sp\u00e9cialistes",
    "sg:phone":"+32 67 55 49 35",
    "sg:postcode":"7090",
    "sg:province":"Hainaut",
    "wof:name":"Christian Roobaert",
    "wof:placetype":"venue"
},
  "geometry": {"coordinates":[4.1332941055,50.6053924561],"type":"Point"}
}