{
  "type": "Feature",
  "properties": {
    "addr:full":"Nazarethsestraat 7 Kruishoutem Oost-Vlaanderen 9770",
    "addr:housenumber":"7",
    "addr:postcode":"9770",
    "addr:street":"Nazarethsestraat",
    "iso:country":"BE",
    "sg:address":"Nazarethsestraat 7",
    "sg:city":"Kruishoutem",
    "sg:orig_category":"Eleveurs de bovins. Eleveurs and marchands de porcs",
    "sg:phone":"+32 9 386 17 50",
    "sg:postcode":"9770",
    "sg:province":"Oost-Vlaanderen",
    "wof:name":"Hugo Van Der Meeren",
    "wof:placetype":"venue"
},
  "geometry": {"coordinates":[3.5419969559,50.9397850037],"type":"Point"}
}