{
  "type": "Feature",
  "properties": {
    "addr:full":"Route Provinciale 2 Incourt Brabant Wallon 1315",
    "addr:housenumber":"2",
    "addr:postcode":"1315",
    "addr:street":"Route Provinciale",
    "iso:country":"BE",
    "sg:address":"Route Provinciale 2",
    "sg:city":"Incourt",
    "sg:orig_category":"Diensten voor huisdieren",
    "sg:phone":"+32 10 81 14 96",
    "sg:postcode":"1315",
    "sg:province":"Brabant Wallon",
    "wof:name":"Special Friends",
    "wof:placetype":"venue"
},
  "geometry": {"coordinates":[4.799115181,50.6915283203],"type":"Point"}
}