{
  "type": "Feature",
  "properties": {
    "iso:country":"BE",
    "sg:address":"Boulevard Du Rectorat 5",
    "sg:city":"Li\u00e8ge 1",
    "sg:classifiers":[
        {
            "category":"Education",
            "subcategory":"University",
            "type":"Public Place"
        }
    ],
    "sg:phone":"+32 4 366 20 72",
    "sg:postcode":"4000",
    "sg:province":"Li\u00e8ge",
    "sg:tags":[
        "higher"
    ],
    "wof:name":"Service De Technologie De L'education S.t.e.-universit\u00e9 De Li\u00e8ge",
    "wof:placetype":"venue"
},
  "geometry": {"coordinates":[5.5679688454,50.5851974487],"type":"Point"}
}