{
  "type": "Feature",
  "properties": {
    "iso:country":"BE",
    "sg:address":"Gal. Carmes",
    "sg:city":"Wavre",
    "sg:orig_category":"Brood, gebak and snoepgoed",
    "sg:phone":"+32 10 24 52 81",
    "sg:postcode":"1300",
    "sg:province":"Brabant Wallon",
    "wof:name":"Myst\u00c8re & Boule De Gomme",
    "wof:placetype":"venue"
},
  "geometry": {"coordinates":[4.607585907,50.7150001526],"type":"Point"}
}