{
  "type": "Feature",
  "properties": {
    "addr:full":"Ninoofsesteenweg 498 Halle Vlaams-Brabant 1500",
    "addr:housenumber":"498",
    "addr:postcode":"1500",
    "addr:street":"Ninoofsesteenweg",
    "iso:country":"BE",
    "sg:address":"Ninoofsesteenweg 498",
    "sg:city":"Halle",
    "sg:orig_category":"R\u00e9parations d'appareils \u00e9lectrom\u00e9nagers. Electrom\u00e9nager, t\u00e9l\u00e9visions and radios",
    "sg:phone":"+32 2 356 04 95",
    "sg:postcode":"1500",
    "sg:province":"Vlaams-Brabant",
    "wof:name":"Electro Paul",
    "wof:placetype":"venue"
},
  "geometry": {"coordinates":[4.2130961418,50.7436752319],"type":"Point"}
}