{
  "type": "Feature",
  "properties": {
    "addr:full":"Drapstraat 88b Hamme Oost-Vlaanderen 9220",
    "addr:housenumber":"88b",
    "addr:postcode":"9220",
    "addr:street":"Drapstraat",
    "iso:country":"BE",
    "sg:address":"Drapstraat 88b",
    "sg:city":"Hamme",
    "sg:classifiers":[
        {
            "category":"Autos & Motor Vehicles",
            "subcategory":"Motorcycle Sales",
            "type":"Retail Goods"
        }
    ],
    "sg:phone":"+32 52 47 68 06",
    "sg:postcode":"9220",
    "sg:province":"Oost-Vlaanderen",
    "sg:tags":[
        "motorbike"
    ],
    "wof:name":"Dragon-wing Bvba",
    "wof:placetype":"venue"
},
  "geometry": {"coordinates":[4.1434931755,51.0990638733],"type":"Point"}
}