{
  "type": "Feature",
  "properties": {
    "iso:country":"BE",
    "sg:address":"Lievevrouwestraat 34",
    "sg:city":"Ranst",
    "sg:orig_category":"Pharmaciens",
    "sg:phone":"+32 3 485 52 76",
    "sg:postcode":"2520",
    "sg:province":"Antwerpen",
    "wof:name":"Apoteek Jacobs",
    "wof:placetype":"venue"
},
  "geometry": {"coordinates":[4.5624442101,51.1892623901],"type":"Point"}
}