{
  "type": "Feature",
  "properties": {
    "addr:full":"Sint-truidensesteenweg 47 Zoutleeuw Vlaams-Brabant 3440",
    "addr:housenumber":"47",
    "addr:postcode":"3440",
    "addr:street":"Sint-Truidensesteenweg;Vlaams-Brabant",
    "iso:country":"BE",
    "sg:address":"Sint-truidensesteenweg 47",
    "sg:city":"Zoutleeuw",
    "sg:classifiers":[
        {
            "category":"Shopping",
            "subcategory":"Florist",
            "type":"Retail Goods"
        }
    ],
    "sg:phone":"+32 11 78 00 41",
    "sg:postcode":"3440",
    "sg:province":"Vlaams-Brabant",
    "wof:name":"Peeters Tuincentrum Nv",
    "wof:placetype":"venue"
},
  "geometry": {"coordinates":[5.1146268845,50.8292503357],"type":"Point"}
}