{
  "type": "Feature",
  "properties": {
    "iso:country":"BE",
    "sg:address":"Rue Hardu\u00c9mont 8",
    "sg:city":"Donceel",
    "sg:orig_category":"Alimentation sp\u00e9cialis\u00e9e",
    "sg:phone":"+32 4 259 61 38",
    "sg:postcode":"4357",
    "sg:province":"Li\u00e8ge",
    "wof:name":"Guy Wauters",
    "wof:placetype":"venue"
},
  "geometry": {"coordinates":[5.3266439438,50.6311569214],"type":"Point"}
}