{
  "type": "Feature",
  "properties": {
    "iso:country":"BE",
    "sg:address":"Eikerstraat 20",
    "sg:city":"Maaseik",
    "sg:orig_category":"R\u00e9parations d'horloges, montres and bijoux. Bijouteries and horlogeries",
    "sg:phone":"+32 89 56 41 04",
    "sg:postcode":"3680",
    "sg:province":"Limburg",
    "wof:name":"Claessens Juwelier",
    "wof:placetype":"venue"
},
  "geometry": {"coordinates":[5.7922358513,51.0955505371],"type":"Point"}
}