{
  "type": "Feature",
  "properties": {
    "iso:country":"BE",
    "sg:address":"Dorpsplein 2",
    "sg:city":"Wellen",
    "sg:classifiers":[
        {
            "category":"Cafe",
            "type":"Food & Drink"
        }
    ],
    "sg:phone":"+32 12 67 24 43",
    "sg:postcode":"3830",
    "sg:province":"Limburg",
    "sg:tags":[
        "snack-bars"
    ],
    "wof:name":"Schorpioentje ('t)",
    "wof:placetype":"venue"
},
  "geometry": {"coordinates":[5.3369650841,50.8411331177],"type":"Point"}
}