{
  "type": "Feature",
  "properties": {
    "addr:full":"Rue Du Page 64 Elsene/ixelles Bruxelles-Capitale 1050",
    "addr:housenumber":"64",
    "addr:postcode":"1050",
    "addr:street":"Rue Du Page",
    "iso:country":"BE",
    "sg:address":"Rue Du Page 64",
    "sg:city":"Elsene/ixelles",
    "sg:orig_category":"Binnenhuisarchitecten",
    "sg:phone":"+32 2 534 44 78",
    "sg:postcode":"1050",
    "sg:province":"Bruxelles-Capitale",
    "wof:name":"Teuwen A.",
    "wof:placetype":"venue"
},
  "geometry": {"coordinates":[4.3581328392,50.8225479126],"type":"Point"}
}