{
  "type": "Feature",
  "properties": {
    "addr:full":"Sint-ferdinandstraat 1 Lummen Limburg 3560",
    "addr:housenumber":"1",
    "addr:postcode":"3560",
    "addr:street":"Sint-Ferdinandstraat",
    "iso:country":"BE",
    "sg:address":"Sint-ferdinandstraat 1",
    "sg:city":"Lummen",
    "sg:orig_category":"Sportcentra",
    "sg:phone":"+32 13 53 06 00",
    "sg:postcode":"3560",
    "sg:province":"Limburg",
    "wof:name":"Sportzaal St.ferdinand",
    "wof:placetype":"venue"
},
  "geometry": {"coordinates":[5.1855821609,50.9986495972],"type":"Point"}
}