{
  "type": "Feature",
  "properties": {
    "iso:country":"BE",
    "sg:address":"Herenthoutsesteenweg 88",
    "sg:city":"Nijlen",
    "sg:orig_category":"Supermarch\u00e9s",
    "sg:phone":"+32 3 481 86 22",
    "sg:postcode":"2560",
    "sg:province":"Antwerpen",
    "wof:name":"Veravo",
    "wof:placetype":"venue"
},
  "geometry": {"coordinates":[4.6848950386,51.1538467407],"type":"Point"}
}