{
  "type": "Feature",
  "properties": {
    "addr:full":"Cecile Cautermanstraat 56 Gent Oost-Vlaanderen 9040",
    "addr:housenumber":"56",
    "addr:postcode":"9040",
    "addr:street":"Cautermanstraat;Oost-Vlaanderen",
    "iso:country":"BE",
    "sg:address":"Cecile Cautermanstraat 56",
    "sg:city":"Gent",
    "sg:classifiers":[
        {
            "category":"Building & Trades",
            "subcategory":"Construction",
            "type":"Services"
        }
    ],
    "sg:phone":"+32 9 228 05 73",
    "sg:postcode":"9040",
    "sg:province":"Oost-Vlaanderen",
    "sg:tags":[
        "la",
        "de",
        "\u00e9quipement",
        "pour",
        "machine",
        "location"
    ],
    "wof:name":"Ekvador",
    "wof:placetype":"venue"
},
  "geometry": {"coordinates":[3.7531518936,51.050693512],"type":"Point"}
}