{
  "type": "Feature",
  "properties": {
    "addr:full":"Rue De La Chauss\u00e9e 22 Mons Hainaut 7000",
    "addr:housenumber":"22",
    "addr:postcode":"7000",
    "addr:street":"Rue De La Chausse\u0301E;Hainaut",
    "iso:country":"BE",
    "sg:address":"Rue De La Chauss\u00e9e 22",
    "sg:city":"Mons",
    "sg:classifiers":[
        {
            "category":"Shopping",
            "subcategory":"Clothing, Apparel, & Fashions",
            "type":"Retail Goods"
        }
    ],
    "sg:phone":"+32 65 84 21 69",
    "sg:postcode":"7000",
    "sg:province":"Hainaut",
    "sg:tags":[
        "-",
        "clothing",
        "child"
    ],
    "wof:name":"Cool Concept",
    "wof:placetype":"venue"
},
  "geometry": {"coordinates":[3.9515199661,50.4534416199],"type":"Point"}
}