{
  "type": "Feature",
  "properties": {
    "iso:country":"BE",
    "sg:address":"Jozef Van Herbruggenstraat 20",
    "sg:city":"Bornem (hingene)",
    "sg:classifiers":[
        {
            "category":"Personal",
            "type":"Services"
        }
    ],
    "sg:phone":"+32 3 899 29 51",
    "sg:postcode":"2880",
    "sg:province":"Antwerpen",
    "sg:tags":[
        "party",
        "planning"
    ],
    "wof:name":"Meyers Promotions Bvba",
    "wof:placetype":"venue"
},
  "geometry": {"coordinates":[4.3014779091,51.1073875427],"type":"Point"}
}