{
  "type": "Feature",
  "properties": {
    "addr:full":"Rue D'orl\u00c9ans 25 Charleroi Hainaut 6000",
    "addr:housenumber":"25",
    "addr:postcode":"6000",
    "addr:street":"Rue D'Orle \u0301Ans;Hainaut",
    "iso:country":"BE",
    "sg:address":"Rue D'orl\u00c9ans 25",
    "sg:city":"Charleroi",
    "sg:classifiers":[
        {
            "category":"Cafe",
            "type":"Food & Drink"
        }
    ],
    "sg:phone":"+32 71 32 65 55",
    "sg:postcode":"6000",
    "sg:province":"Hainaut",
    "sg:tags":[
        "caf\u00e9s"
    ],
    "wof:name":"Marc Ons",
    "wof:placetype":"venue"
},
  "geometry": {"coordinates":[4.4442768097,50.4165420532],"type":"Point"}
}