{
  "type": "Feature",
  "properties": {
    "addr:full":"Hoog Heibos 18 Lint Antwerpen 2547",
    "addr:housenumber":"18",
    "addr:postcode":"2547",
    "addr:street":"Hoog Heibos",
    "iso:country":"BE",
    "sg:address":"Hoog Heibos 18",
    "sg:city":"Lint",
    "sg:orig_category":"Huishoudapparaten, televisies and radio's",
    "sg:phone":"+32 3 455 58 29",
    "sg:postcode":"2547",
    "sg:province":"Antwerpen",
    "wof:name":"Alfons Janssens",
    "wof:placetype":"venue"
},
  "geometry": {"coordinates":[4.4887180328,51.1206169128],"type":"Point"}
}