{
  "type": "Feature",
  "properties": {
    "addr:full":"Sint-laurentiusstraat 4 Veurne (steenkerke) West-Vlaanderen 8630",
    "addr:housenumber":"4",
    "addr:postcode":"8630",
    "addr:street":"Sint-Laurentiusstraat",
    "iso:country":"BE",
    "sg:address":"Sint-laurentiusstraat 4",
    "sg:city":"Veurne (steenkerke)",
    "sg:classifiers":[
        {
            "category":"Insurance",
            "subcategory":"Insurance Agent",
            "type":"Services"
        }
    ],
    "sg:phone":"+32 58 31 32 81",
    "sg:postcode":"8630",
    "sg:province":"West-Vlaanderen",
    "sg:tags":[
        "broker"
    ],
    "wof:name":"Vanquaethem Jean-marie",
    "wof:placetype":"venue"
},
  "geometry": {"coordinates":[2.6904230118,51.0568580627],"type":"Point"}
}