{
  "type": "Feature",
  "properties": {
    "addr:full":"Diestsestraat 173 Leuven Vlaams-Brabant 3000",
    "addr:housenumber":"173",
    "addr:postcode":"3000",
    "addr:street":"Diestsestraat",
    "iso:country":"BE",
    "sg:address":"Diestsestraat 173",
    "sg:city":"Leuven",
    "sg:classifiers":[
        {
            "category":"Professional",
            "subcategory":"Art Services",
            "type":"Services"
        }
    ],
    "sg:phone":"+32 16 29 37 61",
    "sg:postcode":"3000",
    "sg:province":"Vlaams-Brabant",
    "sg:tags":[
        "model",
        "manufacturer"
    ],
    "wof:name":"Model Shop",
    "wof:placetype":"venue"
},
  "geometry": {"coordinates":[4.7096409798,50.8815460205],"type":"Point"}
}