{
  "type": "Feature",
  "properties": {
    "addr:full":"Leuvensesteenweg 610/640 Schaarbeek Bruxelles-Capitale 1030",
    "addr:housenumber":"610 / 640",
    "addr:postcode":"1030",
    "addr:street":"Leuvensesteenweg",
    "iso:country":"BE",
    "sg:address":"Leuvensesteenweg 610/640",
    "sg:city":"Schaarbeek",
    "sg:orig_category":"HERSTELLING ELEKTRISCHE HUISHOUDAPPARATEN Huishoudapparaten, televisies and radio's Packard Bell Nec",
    "sg:phone":"+32 2 705 71 44",
    "sg:postcode":"1030",
    "sg:province":"Bruxelles-Capitale",
    "wof:name":"Vanden Borre",
    "wof:placetype":"venue"
},
  "geometry": {"coordinates":[4.3996710777,50.8552589417],"type":"Point"}
}