{
  "type": "Feature",
  "properties": {
    "iso:country":"BE",
    "sg:address":"Massemsesteenweg 48",
    "sg:city":"Wetteren",
    "sg:classifiers":[
        {
            "category":"Retail",
            "subcategory":"Event Space",
            "type":"Services"
        }
    ],
    "sg:phone":"+32 9 369 30 87",
    "sg:postcode":"9230",
    "sg:province":"Oost-Vlaanderen",
    "sg:tags":[
        "rental",
        "-",
        "hall"
    ],
    "wof:name":"Tonneke",
    "wof:placetype":"venue"
},
  "geometry": {"coordinates":[3.8786690235,50.9958229065],"type":"Point"}
}