{
  "type": "Feature",
  "properties": {
    "addr:full":"Hombeeksesteenweg 214 Mechelen Antwerpen 2800",
    "addr:housenumber":"214",
    "addr:postcode":"2800",
    "addr:street":"Hombeeksesteenweg",
    "iso:country":"BE",
    "sg:address":"Hombeeksesteenweg 214",
    "sg:city":"Mechelen",
    "sg:orig_category":"Newspapers, magazines, periodicals - Distribution",
    "sg:phone":"+32 15 41 47 45",
    "sg:postcode":"2800",
    "sg:province":"Antwerpen",
    "wof:name":"Linda",
    "wof:placetype":"venue"
},
  "geometry": {"coordinates":[4.4662570953,51.0169639587],"type":"Point"}
}