{
  "type": "Feature",
  "properties": {
    "addr:full":"Mechelsesteenweg 1013 Herent Vlaams-Brabant 3020",
    "addr:housenumber":"1013",
    "addr:postcode":"3020",
    "addr:street":"Mechelsesteenweg",
    "iso:country":"BE",
    "sg:address":"Mechelsesteenweg 1013",
    "sg:city":"Herent",
    "sg:classifiers":[
        {
            "category":"Retail",
            "subcategory":"Auto Repair",
            "type":"Services"
        }
    ],
    "sg:phone":"+32 16 49 06 16",
    "sg:postcode":"3020",
    "sg:province":"Vlaams-Brabant",
    "sg:tags":[
        "automobile-body"
    ],
    "wof:name":"Cloet Bvba",
    "wof:placetype":"venue"
},
  "geometry": {"coordinates":[4.64812994,50.9203414917],"type":"Point"}
}