{
  "type": "Feature",
  "properties": {
    "iso:country":"BE",
    "sg:address":"Antwerpsestraat 147",
    "sg:city":"Lier",
    "sg:classifiers":[
        {
            "category":"Banks & Credit Unions",
            "subcategory":"Bank",
            "type":"Services"
        }
    ],
    "sg:phone":"+32 3 480 38 16",
    "sg:postcode":"2500",
    "sg:province":"Antwerpen",
    "sg:tags":[
        "savings-banks"
    ],
    "wof:name":"Zakenkantoor Op De Beeck-van Mieghem Bvba",
    "wof:placetype":"venue"
},
  "geometry": {"coordinates":[4.5650119781,51.1347465515],"type":"Point"}
}