{
  "type": "Feature",
  "properties": {
    "addr:full":"Rue De L'ancien Bourg 18 Braine L'alleud (braine-l'alleud) Brabant Wallon 1420",
    "addr:housenumber":"18",
    "addr:postcode":"1420",
    "addr:street":"Rue De L'Ancien Bourg",
    "iso:country":"BE",
    "sg:address":"Rue De L'ancien Bourg 18",
    "sg:city":"Braine L'alleud (braine-l'alleud)",
    "sg:classifiers":[
        {
            "category":"Personal",
            "subcategory":"Beauty Salon",
            "type":"Services"
        }
    ],
    "sg:phone":"+32 2 384 22 88",
    "sg:postcode":"1420",
    "sg:province":"Brabant Wallon",
    "sg:tags":[
        "lady",
        "-",
        "hairdressing"
    ],
    "wof:name":"Coiffure Prestance",
    "wof:placetype":"venue"
},
  "geometry": {"coordinates":[5.2456002235,46.191444397],"type":"Point"}
}