{
  "type": "Feature",
  "properties": {
    "addr:full":"Rue Grande 52 Qui\u00e9vrain Hainaut 7380",
    "addr:housenumber":"52",
    "addr:postcode":"7380",
    "addr:street":"Rue Grande",
    "iso:country":"BE",
    "sg:address":"Rue Grande 52",
    "sg:city":"Qui\u00e9vrain",
    "sg:classifiers":[
        {
            "category":"Shopping",
            "subcategory":"Optician",
            "type":"Retail Goods"
        }
    ],
    "sg:phone":"+32 65 45 70 58",
    "sg:postcode":"7380",
    "sg:province":"Hainaut",
    "sg:tags":[
        "-"
    ],
    "wof:name":"Rabaux M",
    "wof:placetype":"venue"
},
  "geometry": {"coordinates":[3.6826310158,50.4060249329],"type":"Point"}
}