{
  "type": "Feature",
  "properties": {
    "iso:country":"BE",
    "sg:address":"Rue Puits-en-sock 94",
    "sg:city":"Li\u00c8ge",
    "sg:orig_category":"Dameskledingzaken",
    "sg:phone":"+32 4 344 44 47",
    "sg:postcode":"4020",
    "sg:province":"Li\u00e8ge",
    "wof:name":"Tant Qu'il Y Aura Femmes",
    "wof:placetype":"venue"
},
  "geometry": {"coordinates":[5.5843801498,50.6395111084],"type":"Point"}
}