{
  "type": "Feature",
  "properties": {
    "addr:full":"Rue De La Station 71 Waterloo Brabant Wallon 1410",
    "addr:housenumber":"71",
    "addr:postcode":"1410",
    "addr:street":"Rue De La Station",
    "iso:country":"BE",
    "sg:address":"Rue De La Station 71",
    "sg:city":"Waterloo",
    "sg:classifiers":[
        {
            "category":"Building & Trades",
            "subcategory":"Construction",
            "type":"Services"
        }
    ],
    "sg:phone":"+32 2 354 01 56",
    "sg:postcode":"1410",
    "sg:province":"Brabant Wallon",
    "sg:tags":[
        "installation",
        "-",
        "central",
        "heating"
    ],
    "wof:name":"Saniplomb Sprl",
    "wof:placetype":"venue"
},
  "geometry": {"coordinates":[4.3880190849,50.7154693604],"type":"Point"}
}