{
  "type": "Feature",
  "properties": {
    "iso:country":"BE",
    "sg:address":"Dorpsstraat 31",
    "sg:city":"Middelkerke (leffinge)",
    "sg:classifiers":[
        {
            "category":"Bars & Pubs",
            "type":"Food & Drink"
        }
    ],
    "sg:phone":"+32 59 31 35 64",
    "sg:postcode":"8432",
    "sg:province":"West-Vlaanderen",
    "wof:name":"Centrum",
    "wof:placetype":"venue"
},
  "geometry": {"coordinates":[2.8768401146,51.1755104065],"type":"Point"}
}