{
  "type": "Feature",
  "properties": {
    "iso:country":"BE",
    "sg:address":"Sint-bernardusstraat 25",
    "sg:city":"Hechtel-eksel",
    "sg:orig_category":"Rundveehouders",
    "sg:phone":"+32 11 73 44 12",
    "sg:postcode":"3941",
    "sg:province":"Limburg",
    "wof:name":"Dominique Hulsbosch",
    "wof:placetype":"venue"
},
  "geometry": {"coordinates":[5.3691830635,51.1429328918],"type":"Point"}
}