{
  "type": "Feature",
  "properties": {
    "iso:country":"BE",
    "sg:address":"Edingensesteenweg 871",
    "sg:city":"Halle",
    "sg:orig_category":"Installatie van houten of kunststof schrijnwerk",
    "sg:phone":"+32 2 360 13 96",
    "sg:postcode":"1502",
    "sg:province":"Vlaams-Brabant",
    "wof:name":"Jean De Vos",
    "wof:placetype":"venue"
},
  "geometry": {"coordinates":[4.1946659088,50.7190170288],"type":"Point"}
}