{
  "type": "Feature",
  "properties": {
    "addr:full":"Eedverbondkaai 36 Gent Oost-Vlaanderen 9000",
    "addr:housenumber":"36",
    "addr:postcode":"9000",
    "addr:street":"Eedverbondkaai;Oost-Vlaanderen",
    "iso:country":"BE",
    "sg:address":"Eedverbondkaai 36",
    "sg:city":"Gent",
    "sg:classifiers":[
        {
            "category":"Sports & Exercise",
            "subcategory":"Sports Center",
            "type":"Entertainment"
        }
    ],
    "sg:phone":"+32 9 245 13 36",
    "sg:postcode":"9000",
    "sg:province":"Oost-Vlaanderen",
    "sg:tags":[
        "holiday",
        "language"
    ],
    "wof:name":"E.l.s. Cvba",
    "wof:placetype":"venue"
},
  "geometry": {"coordinates":[3.7170031071,51.0420761108],"type":"Point"}
}