{
  "type": "Feature",
  "properties": {
    "iso:country":"BE",
    "sg:address":"Groenendijkstraat 17",
    "sg:city":"Assenede",
    "sg:classifiers":[
        {
            "category":"Personal",
            "subcategory":"Beauty Salon",
            "type":"Services"
        }
    ],
    "sg:phone":"+32 9 344 59 01",
    "sg:postcode":"9960",
    "sg:province":"Oost-Vlaanderen",
    "sg:tags":[
        "de",
        "coiffure"
    ],
    "wof:name":"Andre Scheir",
    "wof:placetype":"venue"
},
  "geometry": {"coordinates":[3.7606739998,51.2307662964],"type":"Point"}
}