{
  "type": "Feature",
  "properties": {
    "addr:full":"Bruggestraat 94 Beernem West-Vlaanderen 8730",
    "addr:housenumber":"94",
    "addr:postcode":"8730",
    "addr:street":"Bruggestraat",
    "iso:country":"BE",
    "sg:address":"Bruggestraat 94",
    "sg:city":"Beernem",
    "sg:orig_category":"Banques and organismes de cr\u00e9dit",
    "sg:phone":"+32 50 78 90 71",
    "sg:postcode":"8730",
    "sg:province":"West-Vlaanderen",
    "wof:name":"Centea",
    "wof:placetype":"venue"
},
  "geometry": {"coordinates":[3.3272418976,51.1723976135],"type":"Point"}
}