{
  "type": "Feature",
  "properties": {
    "addr:full":"Klein Turkije 16 A Gent Oost-Vlaanderen 9000",
    "addr:housenumber":"16 a",
    "addr:postcode":"9000",
    "addr:street":"Klein Turkije;Oost-Vlaanderen",
    "iso:country":"BE",
    "sg:address":"Klein Turkije 16 A",
    "sg:city":"Gent",
    "sg:classifiers":[
        {
            "category":"Bars & Pubs",
            "type":"Food & Drink"
        }
    ],
    "sg:phone":"+32 476 24 61 92",
    "sg:postcode":"9000",
    "sg:province":"Oost-Vlaanderen",
    "sg:tags":[
        "caf\u00e9s"
    ],
    "wof:name":"'t Kelderken Swingcaf\u00c9",
    "wof:placetype":"venue"
},
  "geometry": {"coordinates":[3.7224450111,51.0543937683],"type":"Point"}
}