{
  "type": "Feature",
  "properties": {
    "addr:full":"Chauss\u00c9e De Bruxelles 198 Tournai Hainaut 7500",
    "addr:housenumber":"198",
    "addr:postcode":"7500",
    "addr:street":"Chausse\u0301E De Bruxelles",
    "iso:country":"BE",
    "sg:address":"Chauss\u00c9e De Bruxelles 198",
    "sg:city":"Tournai",
    "sg:orig_category":"Boekhouders",
    "sg:phone":"+32 69 23 51 67",
    "sg:postcode":"7500",
    "sg:province":"Hainaut",
    "wof:name":"Brigitte Borowiak",
    "wof:placetype":"venue"
},
  "geometry": {"coordinates":[3.4402389526,50.6003799438],"type":"Point"}
}