{
  "type": "Feature",
  "properties": {
    "addr:full":"Ch De Louvain 269 Namur Namur 5004",
    "addr:housenumber":"269",
    "addr:postcode":"5004",
    "addr:street":"Ch De Louvain",
    "iso:country":"BE",
    "sg:address":"Ch De Louvain 269",
    "sg:city":"Namur",
    "sg:classifiers":[
        {
            "category":"Shopping",
            "type":"Retail Goods"
        }
    ],
    "sg:phone":"+32 81 21 27 02",
    "sg:postcode":"5004",
    "sg:province":"Namur",
    "sg:tags":[
        "metallurgy",
        "finished",
        "-",
        "metalworking",
        "metallic"
    ],
    "wof:name":"Gabriel Danneels Sa",
    "wof:placetype":"venue"
},
  "geometry": {"coordinates":[4.8755102158,50.4760665894],"type":"Point"}
}