{
  "type": "Feature",
  "properties": {
    "iso:country":"BE",
    "sg:address":"Avenue Des Combattants 90",
    "sg:city":"Genappe",
    "sg:orig_category":"Artsen and specialisten",
    "sg:phone":"+32 67 77 33 58",
    "sg:postcode":"1470",
    "sg:province":"Brabant Wallon",
    "wof:name":"G. Taelman",
    "wof:placetype":"venue"
},
  "geometry": {"coordinates":[4.5107240677,50.6164474487],"type":"Point"}
}