{
  "type": "Feature",
  "properties": {
    "addr:full":"Rue Cardinal Mercier 1 Soumagne (melen) Li\u00e8ge 4633",
    "addr:housenumber":"1",
    "addr:postcode":"4633",
    "addr:street":"Rue Cardinal Mercier;Melen",
    "iso:country":"BE",
    "sg:address":"Rue Cardinal Mercier 1",
    "sg:city":"Soumagne (melen)",
    "sg:classifiers":[
        {
            "category":"Structure",
            "subcategory":"Office Building",
            "type":"Public Place"
        }
    ],
    "sg:phone":"+32 4 377 39 53",
    "sg:postcode":"4633",
    "sg:province":"Li\u00e8ge",
    "sg:tags":[
        "drawing"
    ],
    "wof:name":"Yilmaz N",
    "wof:placetype":"venue"
},
  "geometry": {"coordinates":[5.7343978882,50.6351013184],"type":"Point"}
}