{
  "type": "Feature",
  "properties": {
    "addr:full":"Rue Ferme Bordeaux 8 Genappe Brabant Wallon 1470",
    "addr:housenumber":"8",
    "addr:postcode":"1470",
    "addr:street":"Rue Ferme Bordeaux;Wallon",
    "iso:country":"BE",
    "sg:address":"Rue Ferme Bordeaux 8",
    "sg:city":"Genappe",
    "sg:orig_category":"Diverse persoonlijke diensten",
    "sg:phone":"+32 10 61 58 28",
    "sg:postcode":"1470",
    "sg:province":"Brabant Wallon",
    "wof:name":"Eddy Clavie",
    "wof:placetype":"venue"
},
  "geometry": {"coordinates":[4.5153799057,50.6417770386],"type":"Point"}
}