{
  "type": "Feature",
  "properties": {
    "addr:full":"Zuidmolendreef 31 Roeselare West-Vlaanderen 8800",
    "addr:housenumber":"31",
    "addr:postcode":"8800",
    "addr:street":"Zuidmolendreef",
    "iso:country":"BE",
    "sg:address":"Zuidmolendreef 31",
    "sg:city":"Roeselare",
    "sg:classifiers":[
        {
            "category":"Real Estate",
            "subcategory":"Real Estate Services",
            "type":"Services"
        }
    ],
    "sg:phone":"+32 51 22 69 65",
    "sg:postcode":"8800",
    "sg:province":"West-Vlaanderen",
    "wof:name":"Derieuw J.p.",
    "wof:placetype":"venue"
},
  "geometry": {"coordinates":[3.1262779236,50.9349327087],"type":"Point"}
}