{
  "type": "Feature",
  "properties": {
    "iso:country":"BE",
    "sg:address":"Hamoirlaan 26",
    "sg:city":"Ukkel/uccle",
    "sg:orig_category":"Huishoudtextiel and -linnen Fab Textiel",
    "sg:phone":"+32 2 374 59 50",
    "sg:postcode":"1180",
    "sg:province":"Bruxelles-Capitale",
    "wof:name":"Faretex-tassier",
    "wof:placetype":"venue"
},
  "geometry": {"coordinates":[4.366147995,50.7974014282],"type":"Point"}
}