{
  "type": "Feature",
  "properties": {
    "addr:full":"Avenue Jules Henin 12 Charleroi Hainaut 6000",
    "addr:housenumber":"12",
    "addr:postcode":"6000",
    "addr:street":"Avenue Jules Henin;Hainaut",
    "iso:country":"BE",
    "sg:address":"Avenue Jules Henin 12",
    "sg:city":"Charleroi",
    "sg:classifiers":[
        {
            "category":"Home & Garden",
            "subcategory":"Kitchen Supply",
            "type":"Retail Goods"
        }
    ],
    "sg:phone":"+32 71 32 50 87",
    "sg:postcode":"6000",
    "sg:province":"Hainaut",
    "sg:tags":[
        "equipment",
        "baker",
        "-"
    ],
    "wof:name":"Darchambeau-pilois Sprl",
    "wof:placetype":"venue"
},
  "geometry": {"coordinates":[4.4494037628,50.4164161682],"type":"Point"}
}