{
  "type": "Feature",
  "properties": {
    "addr:full":"Hynderickstraat 4 Ieper West-Vlaanderen 8904",
    "addr:housenumber":"4",
    "addr:postcode":"8904",
    "addr:street":"Hynderickstraat",
    "iso:country":"BE",
    "sg:address":"Hynderickstraat 4",
    "sg:city":"Ieper",
    "sg:orig_category":"Eleveurs de bovins",
    "sg:phone":"+32 57 42 22 83",
    "sg:postcode":"8904",
    "sg:province":"West-Vlaanderen",
    "wof:name":"Daniel Goderis",
    "wof:placetype":"venue"
},
  "geometry": {"coordinates":[2.8510940075,50.8886184692],"type":"Point"}
}