{
  "type": "Feature",
  "properties": {
    "iso:country":"BE",
    "sg:address":"Spiedamstraat 27",
    "sg:city":"Evergem (ertvelde)",
    "sg:classifiers":[
        {
            "category":"Professional",
            "subcategory":"Detective & Security Services",
            "type":"Services"
        }
    ],
    "sg:phone":"+32 9 343 04 30",
    "sg:postcode":"9940",
    "sg:province":"Oost-Vlaanderen",
    "sg:tags":[
        "installation",
        "alarm",
        "-",
        "system"
    ],
    "wof:name":"Asvd-van Damme & Zoon",
    "wof:placetype":"venue"
},
  "geometry": {"coordinates":[3.7683689594,51.1708526611],"type":"Point"}
}