{
  "type": "Feature",
  "properties": {
    "addr:full":"Zeelaan 114 De Panne West-Vlaanderen 8660",
    "addr:housenumber":"114",
    "addr:postcode":"8660",
    "addr:street":"Zeelaan",
    "iso:country":"BE",
    "sg:address":"Zeelaan 114",
    "sg:city":"De Panne",
    "sg:classifiers":[
        {
            "category":"Tea Room",
            "subcategory":"None",
            "type":"Food & Drink"
        }
    ],
    "sg:phone":"+32 58 41 11 79",
    "sg:postcode":"8660",
    "sg:province":"West-Vlaanderen",
    "wof:name":"Ferme (a La)",
    "wof:placetype":"venue"
},
  "geometry": {"coordinates":[2.5924990177,51.1003570557],"type":"Point"}
}