{
  "type": "Feature",
  "properties": {
    "iso:country":"BE",
    "sg:address":"Dorpsstraat 14",
    "sg:city":"Kortessem",
    "sg:classifiers":[
        {
            "category":"Shopping",
            "subcategory":"Clothing, Apparel, & Fashions",
            "type":"Retail Goods"
        }
    ],
    "sg:phone":"+32 11 37 51 63",
    "sg:postcode":"3720",
    "sg:province":"Limburg",
    "sg:tags":[
        "lingerie",
        "sous-v\u00eatements"
    ],
    "wof:name":"Curtres",
    "wof:placetype":"venue"
},
  "geometry": {"coordinates":[5.3882441521,50.8580360413],"type":"Point"}
}