{
  "type": "Feature",
  "properties": {
    "addr:full":"Kerkstraat 46 Oud-turnhout Antwerpen 2360",
    "addr:housenumber":"46",
    "addr:postcode":"2360",
    "addr:street":"Kerkstraat",
    "iso:country":"BE",
    "sg:address":"Kerkstraat 46",
    "sg:city":"Oud-turnhout",
    "sg:orig_category":"Offices du tourisme",
    "sg:phone":"+32 14 47 94 94",
    "sg:postcode":"2360",
    "sg:province":"Antwerpen",
    "wof:name":"Dienst Voor Toerisme",
    "wof:placetype":"venue"
},
  "geometry": {"coordinates":[4.9821190834,51.3212623596],"type":"Point"}
}