{
  "type": "Feature",
  "properties": {
    "addr:full":"Rue De Hesbaye 100 Li\u00c8ge Li\u00e8ge 4000",
    "addr:housenumber":"100",
    "addr:postcode":"4000",
    "addr:street":"Rue De Hesbaye",
    "iso:country":"BE",
    "sg:address":"Rue De Hesbaye 100",
    "sg:city":"Li\u00c8ge",
    "sg:orig_category":"Brood, gebak and snoepgoed",
    "sg:phone":"+32 4 226 22 40",
    "sg:postcode":"4000",
    "sg:province":"Li\u00e8ge",
    "wof:name":"Au Panier Gourmand",
    "wof:placetype":"venue"
},
  "geometry": {"coordinates":[5.5555047989,50.6484909058],"type":"Point"}
}