{
  "type": "Feature",
  "properties": {
    "iso:country":"BE",
    "sg:address":"Prof. Scharpelaan 170",
    "sg:city":"Begijnendijk",
    "sg:classifiers":[
        {
            "category":"Professional",
            "subcategory":"Accounting & Tax Preparation",
            "type":"Services"
        }
    ],
    "sg:phone":"+32 16 56 09 68",
    "sg:postcode":"3130",
    "sg:province":"Vlaams-Brabant",
    "sg:tags":[
        "accountant"
    ],
    "wof:name":"Willem Van Calster",
    "wof:placetype":"venue"
},
  "geometry": {"coordinates":[4.7888641357,50.9991836548],"type":"Point"}
}