{
  "type": "Feature",
  "properties": {
    "addr:full":"Maurits Sabbestraat 24 Mechelen Antwerpen 2800",
    "addr:housenumber":"24",
    "addr:postcode":"2800",
    "addr:street":"Maurits Sabbestraat",
    "iso:country":"BE",
    "sg:address":"Maurits Sabbestraat 24",
    "sg:city":"Mechelen",
    "sg:classifiers":[
        {
            "category":"Health Services",
            "subcategory":"Doctor",
            "type":"Services"
        }
    ],
    "sg:phone":"+32 15 55 05 05",
    "sg:postcode":"2800",
    "sg:province":"Antwerpen",
    "sg:tags":[
        "medicinephysicians",
        "surgeon"
    ],
    "wof:name":"Kiekens M",
    "wof:placetype":"venue"
},
  "geometry": {"coordinates":[4.4758582115,51.0351867676],"type":"Point"}
}