{
  "type": "Feature",
  "properties": {
    "addr:full":"Place L\u00e9opold 10 Namur Namur 5000",
    "addr:housenumber":"10",
    "addr:postcode":"5000",
    "addr:street":"Place Le\u0301Opold",
    "iso:country":"BE",
    "sg:address":"Place L\u00e9opold 10",
    "sg:city":"Namur",
    "sg:classifiers":[
        {
            "category":"Home & Garden",
            "subcategory":"Carpets & Floor Coverings",
            "type":"Retail Goods"
        }
    ],
    "sg:phone":"+32 81 23 06 30",
    "sg:postcode":"5000",
    "sg:province":"Namur",
    "sg:tags":[
        "oriental"
    ],
    "wof:name":"Mengal Orient",
    "wof:placetype":"venue"
},
  "geometry": {"coordinates":[4.8683800697,50.4685935974],"type":"Point"}
}