{
  "type": "Feature",
  "properties": {
    "iso:country":"BE",
    "sg:address":"Terbeekseweg 51",
    "sg:city":"Wuustwezel (loenhout)",
    "sg:classifiers":[
        {
            "category":"Travel",
            "subcategory":"Resort",
            "type":"Entertainment"
        }
    ],
    "sg:phone":"+32 3 669 80 31",
    "sg:postcode":"2990",
    "sg:province":"Antwerpen",
    "sg:tags":[
        "health"
    ],
    "wof:name":"Beauty Culture",
    "wof:placetype":"venue"
},
  "geometry": {"coordinates":[4.6694951057,51.4017105103],"type":"Point"}
}