{
  "type": "Feature",
  "properties": {
    "iso:country":"BE",
    "sg:address":"Professor Scharp\u00e9laan 175",
    "sg:city":"Begijnendijk (betekom)",
    "sg:classifiers":[
        {
            "category":"Transit Center",
            "subcategory":"Freight",
            "type":"Transportation"
        }
    ],
    "sg:phone":"+32 16 56 18 96",
    "sg:postcode":"3130",
    "sg:province":"Vlaams-Brabant",
    "sg:tags":[
        "dangerous",
        "material",
        "transport"
    ],
    "wof:name":"Transport Noma Bvba",
    "wof:placetype":"venue"
},
  "geometry": {"coordinates":[4.7891459465,51.0003547668],"type":"Point"}
}