{
  "type": "Feature",
  "properties": {
    "addr:full":"Bergstraat 1 Galmaarden Vlaams-Brabant 1570",
    "addr:housenumber":"1",
    "addr:postcode":"1570",
    "addr:street":"Bergstraat",
    "iso:country":"BE",
    "sg:address":"Bergstraat 1",
    "sg:city":"Galmaarden",
    "sg:orig_category":"Verplichte sociale verzekeringen",
    "sg:phone":"+32 54 58 65 55",
    "sg:postcode":"1570",
    "sg:province":"Vlaams-Brabant",
    "wof:name":"Liberale Mutualiteit",
    "wof:placetype":"venue"
},
  "geometry": {"coordinates":[3.9704499245,50.7526283264],"type":"Point"}
}