{
  "type": "Feature",
  "properties": {
    "addr:full":"Avenue Du Monument 7 Marche-en-famenne Luxembourg 6900",
    "addr:housenumber":"7",
    "addr:postcode":"6900",
    "addr:street":"Avenue Du Monument",
    "iso:country":"BE",
    "sg:address":"Avenue Du Monument 7",
    "sg:city":"Marche-en-famenne",
    "sg:classifiers":[
        {
            "category":"Professional",
            "subcategory":"Lawyer & Legal Services",
            "type":"Services"
        }
    ],
    "sg:phone":"+32 84 31 18 65",
    "sg:postcode":"6900",
    "sg:province":"Luxembourg",
    "wof:name":"Hanin Charles",
    "wof:placetype":"venue"
},
  "geometry": {"coordinates":[5.3428239822,50.2248764038],"type":"Point"}
}