{
  "type": "Feature",
  "properties": {
    "addr:full":"Herenstraat 9 Sint-gillis-waas Oost-Vlaanderen 9170",
    "addr:housenumber":"9",
    "addr:postcode":"9170",
    "addr:street":"Herenstraat",
    "iso:country":"BE",
    "sg:address":"Herenstraat 9",
    "sg:city":"Sint-gillis-waas",
    "sg:classifiers":[
        {
            "category":"Social Services",
            "subcategory":"Job Training",
            "type":"Services"
        }
    ],
    "sg:phone":"+32 3 707 09 25",
    "sg:postcode":"9170",
    "sg:province":"Oost-Vlaanderen",
    "sg:tags":[
        "coordinator",
        "safety"
    ],
    "wof:name":"Cotebo",
    "wof:placetype":"venue"
},
  "geometry": {"coordinates":[4.1223931313,51.22240448],"type":"Point"}
}