{
  "type": "Feature",
  "properties": {
    "addr:full":"Oorlogskruisenlaan 1 Brussel/bruxelles Bruxelles-Capitale 1120",
    "addr:housenumber":"1",
    "addr:postcode":"1120",
    "addr:street":"Oorlogskruisenlaan;/",
    "iso:country":"BE",
    "sg:address":"Oorlogskruisenlaan 1",
    "sg:city":"Brussel/bruxelles",
    "sg:orig_category":"Fleurs and plantes",
    "sg:phone":"+32 2 216 82 70",
    "sg:postcode":"1120",
    "sg:province":"Bruxelles-Capitale",
    "wof:name":"De Mooij Pieter",
    "wof:placetype":"venue"
},
  "geometry": {"coordinates":[4.3815197945,50.8900794983],"type":"Point"}
}