{
  "type": "Feature",
  "properties": {
    "addr:full":"Av Paul Pastur 52 Marcinelle Hainaut 6001",
    "addr:housenumber":"52",
    "addr:postcode":"6001",
    "addr:street":"Av Paul Pastur",
    "iso:country":"BE",
    "sg:address":"Av Paul Pastur 52",
    "sg:city":"Marcinelle",
    "sg:classifiers":[
        {
            "category":"Professional",
            "subcategory":"Business Services",
            "type":"Services"
        }
    ],
    "sg:phone":"+32 71 44 88 00",
    "sg:postcode":"6001",
    "sg:province":"Hainaut",
    "sg:tags":[
        "body",
        "advice"
    ],
    "wof:name":"Union Pharmaceutique De Charleroi",
    "wof:placetype":"venue"
},
  "geometry": {"coordinates":[4.431101799,50.4033432007],"type":"Point"}
}