{
  "type": "Feature",
  "properties": {
    "addr:full":"Bracht 10 Burg-reuland/burg-reuland Li\u00e8ge 4790",
    "addr:housenumber":"10",
    "addr:postcode":"4790",
    "addr:street":"Bracht",
    "iso:country":"BE",
    "sg:address":"Bracht 10",
    "sg:city":"Burg-reuland/burg-reuland",
    "sg:orig_category":"Rundveehouders",
    "sg:phone":"+32 80 32 96 42",
    "sg:postcode":"4790",
    "sg:province":"Li\u00e8ge",
    "wof:name":"Erich Oly",
    "wof:placetype":"venue"
},
  "geometry": {"coordinates":[6.1444439888,50.2075576782],"type":"Point"}
}