{
  "type": "Feature",
  "properties": {
    "addr:full":"Onze-lieve-vrouwstraat 31 Westerlo (oevel) Antwerpen 2260",
    "addr:housenumber":"31",
    "addr:postcode":"2260",
    "addr:street":"Onze-Lieve-Vrouwstraat",
    "iso:country":"BE",
    "sg:address":"Onze-lieve-vrouwstraat 31",
    "sg:city":"Westerlo (oevel)",
    "sg:classifiers":[
        {
            "category":"Bars & Pubs",
            "type":"Food & Drink"
        }
    ],
    "sg:phone":"+32 14 22 31 45",
    "sg:postcode":"2260",
    "sg:province":"Antwerpen",
    "sg:tags":[
        "tavern"
    ],
    "wof:name":"Boerenhof Bvba",
    "wof:placetype":"venue"
},
  "geometry": {"coordinates":[4.916656971,51.1392936707],"type":"Point"}
}