{
  "type": "Feature",
  "properties": {
    "iso:country":"BE",
    "sg:address":"Rue Try Des Marais 514",
    "sg:city":"Walcourt (tarcienne)",
    "sg:classifiers":[
        {
            "category":"Government",
            "subcategory":"Fire Station",
            "type":"Public Place"
        }
    ],
    "sg:phone":"+32 71 22 85 74",
    "sg:postcode":"5651",
    "sg:province":"Namur",
    "sg:tags":[
        "installation",
        "-",
        "air conditioning"
    ],
    "wof:name":"B\u00f6hm S",
    "wof:placetype":"venue"
},
  "geometry": {"coordinates":[4.4781098366,50.3188285828],"type":"Point"}
}