{
  "type": "Feature",
  "properties": {
    "iso:country":"BE",
    "sg:address":"Chauss\u00e9e De Bruxelles 436",
    "sg:city":"Ath (ghislenghien)",
    "sg:classifiers":[
        {
            "category":"Farming",
            "subcategory":"Livestock Farm",
            "type":"Manufacturing & Wholesale Goods"
        }
    ],
    "sg:phone":"+32 68 55 15 45",
    "sg:postcode":"7822",
    "sg:province":"Hainaut",
    "sg:tags":[
        "breeding"
    ],
    "wof:name":"Van Wynendaele",
    "wof:placetype":"venue"
},
  "geometry": {"coordinates":[3.8858850002,50.6560249329],"type":"Point"}
}