{
  "type": "Feature",
  "properties": {
    "iso:country":"BE",
    "sg:address":"Rue De La Cambre 336b6",
    "sg:city":"Sint-lambrechts-woluwe/woluwe-saint-lambert",
    "sg:orig_category":"Avocats and conseillers juridiques",
    "sg:phone":"+32 2 770 97 69",
    "sg:postcode":"1200",
    "sg:province":"Bruxelles-Capitale",
    "wof:name":"Marguerite Bastien",
    "wof:placetype":"venue"
},
  "geometry": {"coordinates":[4.4114341736,50.838344574],"type":"Point"}
}