{
  "type": "Feature",
  "properties": {
    "addr:full":"Rue Goette 11 Yvoir (purnode) Namur 5530",
    "addr:housenumber":"11",
    "addr:postcode":"5530",
    "addr:street":"Rue Goette",
    "iso:country":"BE",
    "sg:address":"Rue Goette 11",
    "sg:city":"Yvoir (purnode)",
    "sg:classifiers":[
        {
            "category":"Shopping",
            "subcategory":"Optician",
            "type":"Retail Goods"
        }
    ],
    "sg:phone":"+32 82 61 18 55",
    "sg:postcode":"5530",
    "sg:province":"Namur",
    "sg:tags":[
        "-"
    ],
    "wof:name":"Francois G",
    "wof:placetype":"venue"
},
  "geometry": {"coordinates":[4.9459671974,50.3123435974],"type":"Point"}
}