{
  "type": "Feature",
  "properties": {
    "iso:country":"BE",
    "sg:address":"K. De Backerstraat 14",
    "sg:city":"Hemiksem",
    "sg:orig_category":"Slagers",
    "sg:phone":"+32 3 887 43 54",
    "sg:postcode":"2620",
    "sg:province":"Antwerpen",
    "wof:name":"Van Eggermond",
    "wof:placetype":"venue"
},
  "geometry": {"coordinates":[4.3420791626,51.145614624],"type":"Point"}
}