{
  "type": "Feature",
  "properties": {
    "iso:country":"BE",
    "sg:address":"Chauss\u00c9e De Wavre 1545",
    "sg:city":"Oudergem/auderghem",
    "sg:orig_category":"M\u00e9decins and sp\u00e9cialistes",
    "sg:phone":"+32 2 660 83 85",
    "sg:postcode":"1160",
    "sg:province":"Bruxelles-Capitale",
    "wof:name":"Claude Van Bree",
    "wof:placetype":"venue"
},
  "geometry": {"coordinates":[4.4182620049,50.8179931641],"type":"Point"}
}