{
  "type": "Feature",
  "properties": {
    "iso:country":"BE",
    "sg:address":"Dagobertstraat 14",
    "sg:city":"Leuven",
    "sg:classifiers":[
        {
            "category":"Retail",
            "subcategory":"Repair Shop",
            "type":"Services"
        }
    ],
    "sg:phone":"+32 16 23 54 70",
    "sg:postcode":"3000",
    "sg:province":"Vlaams-Brabant",
    "sg:tags":[
        "denture"
    ],
    "wof:name":"Bastin P",
    "wof:placetype":"venue"
},
  "geometry": {"coordinates":[4.7127947807,50.8762321472],"type":"Point"}
}