{
  "type": "Feature",
  "properties": {
    "addr:full":"Helplasweg Lede Oost-Vlaanderen 9340",
    "addr:postcode":"9340",
    "addr:street":"Oost-Vlaanderen",
    "iso:country":"BE",
    "sg:address":"Helplasweg",
    "sg:city":"Lede",
    "sg:orig_category":"Gestion des d\u00e9charges and sites d\u00e9finitifs de stockage",
    "sg:phone":"+32 53 80 60 71",
    "sg:postcode":"9340",
    "sg:province":"Oost-Vlaanderen",
    "wof:name":"Containerpark Lede",
    "wof:placetype":"venue"
},
  "geometry": {"coordinates":[3.9773280621,50.9667625427],"type":"Point"}
}