{
  "type": "Feature",
  "properties": {
    "iso:country":"BE",
    "sg:address":"Sint-apolloniastraat 23",
    "sg:city":"Brakel",
    "sg:classifiers":[
        {
            "category":"Cafe",
            "type":"Food & Drink"
        }
    ],
    "sg:phone":"+32 55 42 74 83",
    "sg:postcode":"9660",
    "sg:province":"Oost-Vlaanderen",
    "sg:tags":[
        "caf\u00e9s"
    ],
    "wof:name":"Edith Brouckaert",
    "wof:placetype":"venue"
},
  "geometry": {"coordinates":[3.7384989262,50.8304023743],"type":"Point"}
}