{
  "type": "Feature",
  "properties": {
    "iso:country":"BE",
    "sg:address":"Rue Papenkasteel 0",
    "sg:city":"Ukkel",
    "sg:orig_category":"Gestion des d\u00e9charges and sites d\u00e9finitifs de stockage",
    "sg:phone":"+32 2 374 96 74",
    "sg:postcode":"1180",
    "sg:province":"Bruxelles-Capitale",
    "wof:name":"Parcs \u00c0 Conteneurs Uccle",
    "wof:placetype":"venue"
},
  "geometry": {"coordinates":[4.3385448456,50.7913894653],"type":"Point"}
}