{
  "type": "Feature",
  "properties": {
    "iso:country":"BE",
    "sg:address":"Rue De Genville 71",
    "sg:city":"Orp-jauche (jandrain-jandrenouille)",
    "sg:classifiers":[
        {
            "category":"Retail",
            "subcategory":"Animal Services",
            "type":"Services"
        }
    ],
    "sg:phone":"+32 19 63 52 09",
    "sg:postcode":"1350",
    "sg:province":"Brabant Wallon",
    "sg:tags":[
        "breeding",
        "selling",
        "-",
        "dog"
    ],
    "wof:name":"Von Teufel Schelten",
    "wof:placetype":"venue"
},
  "geometry": {"coordinates":[4.9813990593,50.6833534241],"type":"Point"}
}