{
  "type": "Feature",
  "properties": {
    "iso:country":"BE",
    "sg:address":"Rue Basse Chauss\u00e9e 135",
    "sg:city":"Namur (cognel\u00e9e)",
    "sg:classifiers":[
        {
            "category":"Professional",
            "subcategory":"Accounting & Tax Preparation",
            "type":"Services"
        }
    ],
    "sg:phone":"+32 81 21 57 63",
    "sg:postcode":"5022",
    "sg:province":"Namur",
    "sg:tags":[
        "accountant"
    ],
    "wof:name":"Fidunam Sa",
    "wof:placetype":"venue"
},
  "geometry": {"coordinates":[4.902985096,50.513671875],"type":"Point"}
}