{
  "type": "Feature",
  "properties": {
    "addr:full":"Chauss\u00c9e De Boitsfort 120 Watermaal-bosvoorde/watermael-boitsfort Bruxelles-Capitale 1170",
    "addr:housenumber":"120;/",
    "addr:postcode":"1170",
    "addr:street":"Chausse\u0301E De Boitsfort;Watermaal-Bosvoorde",
    "iso:country":"BE",
    "sg:address":"Chauss\u00c9e De Boitsfort 120",
    "sg:city":"Watermaal-bosvoorde/watermael-boitsfort",
    "sg:orig_category":"Artistes ind\u00e9pendants",
    "sg:phone":"+32 2 672 71 54",
    "sg:postcode":"1170",
    "sg:province":"Bruxelles-Capitale",
    "wof:name":"Henri Billen",
    "wof:placetype":"venue"
},
  "geometry": {"coordinates":[4.3990907669,50.7998390198],"type":"Point"}
}