{
  "type": "Feature",
  "properties": {
    "addr:full":"Moerstraat 22a Sint-laureins (sint-jan-in-eremo) Oost-Vlaanderen 9982",
    "addr:housenumber":"22a",
    "addr:postcode":"9982",
    "addr:street":"Moerstraat",
    "iso:country":"BE",
    "sg:address":"Moerstraat 22a",
    "sg:city":"Sint-laureins (sint-jan-in-eremo)",
    "sg:classifiers":[
        {
            "category":"Retail",
            "subcategory":"Event Space",
            "type":"Services"
        }
    ],
    "sg:phone":"+32 9 328 65 44",
    "sg:postcode":"9982",
    "sg:province":"Oost-Vlaanderen",
    "sg:tags":[
        "organisation"
    ],
    "wof:name":"Fest-i-vent Cvoa",
    "wof:placetype":"venue"
},
  "geometry": {"coordinates":[3.5839569569,51.2263031006],"type":"Point"}
}