{
  "type": "Feature",
  "properties": {
    "addr:full":"Rue De La Maillebotte 35 Nivelles Brabant Wallon 1400",
    "addr:housenumber":"35",
    "addr:postcode":"1400",
    "addr:street":"Rue De La Maillebotte",
    "iso:country":"BE",
    "sg:address":"Rue De La Maillebotte 35",
    "sg:city":"Nivelles",
    "sg:classifiers":[
        {
            "category":"Professional",
            "subcategory":"Management & Consulting",
            "type":"Services"
        }
    ],
    "sg:phone":"+32 67 21 48 70",
    "sg:postcode":"1400",
    "sg:province":"Brabant Wallon",
    "sg:tags":[
        "consultant",
        "agency",
        "advertising"
    ],
    "wof:name":"Fable O",
    "wof:placetype":"venue"
},
  "geometry": {"coordinates":[4.3394041061,50.6047363281],"type":"Point"}
}