{
  "type": "Feature",
  "properties": {
    "iso:country":"BE",
    "sg:address":"Noordstraat 1",
    "sg:city":"Veurne",
    "sg:orig_category":"Beheer onroerend goed Verzekeringsmakelaars and experts",
    "sg:phone":"+32 58 31 25 98",
    "sg:postcode":"8630",
    "sg:province":"West-Vlaanderen",
    "wof:name":"Pinson Vanheule & Co",
    "wof:placetype":"venue"
},
  "geometry": {"coordinates":[2.6626870632,51.0728683472],"type":"Point"}
}