{
  "type": "Feature",
  "properties": {
    "addr:full":"Rue Des Bons Enfants 125 Huy Li\u00e8ge 4500",
    "addr:housenumber":"125",
    "addr:postcode":"4500",
    "addr:street":"Rue Des Bons Enfants",
    "iso:country":"BE",
    "sg:address":"Rue Des Bons Enfants 125",
    "sg:city":"Huy",
    "sg:classifiers":[
        {
            "category":"Retail",
            "subcategory":"Veterinary Services",
            "type":"Services"
        }
    ],
    "sg:phone":"+32 85 21 17 63",
    "sg:postcode":"4500",
    "sg:province":"Li\u00e8ge",
    "sg:tags":[
        "veterinarian"
    ],
    "wof:name":"Comblin J",
    "wof:placetype":"venue"
},
  "geometry": {"coordinates":[5.2501969337,50.5281219482],"type":"Point"}
}