{
  "type": "Feature",
  "properties": {
    "iso:country":"BE",
    "sg:address":"Rue G Kurth 25",
    "sg:city":"Evere",
    "sg:orig_category":"D\u00e9taillants en pi\u00e8ces and accessoires de voitures",
    "sg:phone":"+32 2 241 30 57",
    "sg:postcode":"1140",
    "sg:province":"Bruxelles-Capitale",
    "wof:name":"Emmery",
    "wof:placetype":"venue"
},
  "geometry": {"coordinates":[4.3971729279,50.8691368103],"type":"Point"}
}