{
  "type": "Feature",
  "properties": {
    "addr:full":"Rue Des Roses 16 Gembloux-sur-orneau (gembloux) Namur 5030",
    "addr:housenumber":"16",
    "addr:postcode":"5030",
    "addr:street":"Rue Des Roses;Namur",
    "iso:country":"BE",
    "sg:address":"Rue Des Roses 16",
    "sg:city":"Gembloux-sur-orneau (gembloux)",
    "sg:classifiers":[
        {
            "category":"Arts & Performance",
            "subcategory":"Music",
            "type":"Entertainment"
        }
    ],
    "sg:phone":"+32 81 61 45 53",
    "sg:postcode":"5030",
    "sg:province":"Namur",
    "sg:tags":[
        "freelance",
        "musician"
    ],
    "wof:name":"Smets T",
    "wof:placetype":"venue"
},
  "geometry": {"coordinates":[4.684387207,50.5695762634],"type":"Point"}
}