{
  "type": "Feature",
  "properties": {
    "iso:country":"BE",
    "sg:address":"Mageleinstraat 41",
    "sg:city":"Gent",
    "sg:orig_category":"Bijouteries and horlogeries. Antiquit\u00e9s",
    "sg:phone":"+32 9 224 33 20",
    "sg:postcode":"9000",
    "sg:province":"Oost-Vlaanderen",
    "wof:name":"Nachtergaele",
    "wof:placetype":"venue"
},
  "geometry": {"coordinates":[3.7249450684,51.0525779724],"type":"Point"}
}