{
  "type": "Feature",
  "properties": {
    "iso:country":"BE",
    "sg:address":"Hooggeleedstraat 4",
    "sg:city":"Oostende",
    "sg:orig_category":"Installatie van metalen schrijnwerk",
    "sg:phone":"+32 59 70 21 11",
    "sg:postcode":"8400",
    "sg:province":"West-Vlaanderen",
    "wof:name":"Freddy Depecker",
    "wof:placetype":"venue"
},
  "geometry": {"coordinates":[2.9571180344,51.2134284973],"type":"Point"}
}