{
  "type": "Feature",
  "properties": {
    "addr:full":"Wagenstraat 1ba Bilzen Limburg 3740",
    "addr:housenumber":"1ba",
    "addr:postcode":"3740",
    "addr:street":"Wagenstraat",
    "iso:country":"BE",
    "sg:address":"Wagenstraat 1ba",
    "sg:city":"Bilzen",
    "sg:orig_category":"Diverse bouwafwerking and reiniging Gespecialiseerde residenti\u00eble bouw",
    "sg:phone":"+32 89 41 43 05",
    "sg:postcode":"3740",
    "sg:province":"Limburg",
    "wof:name":"Fa. Bollen",
    "wof:placetype":"venue"
},
  "geometry": {"coordinates":[5.4977297783,50.8684082031],"type":"Point"}
}