{
  "type": "Feature",
  "properties": {
    "iso:country":"BE",
    "sg:address":"Laaglandlei 38",
    "sg:city":"Schoten",
    "sg:orig_category":"Herstellingen and onderhoud van auto's",
    "sg:phone":"+32 3 685 41 74",
    "sg:postcode":"2900",
    "sg:province":"Antwerpen",
    "wof:name":"Mcc Wagenreiniging Ter Plaatse",
    "wof:placetype":"venue"
},
  "geometry": {"coordinates":[4.5127391815,51.2510566711],"type":"Point"}
}