{
  "type": "Feature",
  "properties": {
    "iso:country":"BE",
    "sg:address":"Vaart-zuid 1ba",
    "sg:city":"Aalter",
    "sg:orig_category":"Installation de menuiserie m\u00e9tallique",
    "sg:phone":"+32 9 374 34 00",
    "sg:postcode":"9881",
    "sg:province":"Oost-Vlaanderen",
    "wof:name":"Allcon",
    "wof:placetype":"venue"
},
  "geometry": {"coordinates":[3.4993538857,51.0957832336],"type":"Point"}
}