{
  "type": "Feature",
  "properties": {
    "iso:country":"BE",
    "sg:address":"Rue De La Croix Cailloux 10",
    "sg:city":"Saint-ghislain",
    "sg:orig_category":"Installatie van metalen schrijnwerk",
    "sg:phone":"+32 65 62 23 65",
    "sg:postcode":"7334",
    "sg:province":"Hainaut",
    "wof:name":"A B C Plafond",
    "wof:placetype":"venue"
},
  "geometry": {"coordinates":[3.7644500732,50.479675293],"type":"Point"}
}