{
  "type": "Feature",
  "properties": {
    "iso:country":"BE",
    "sg:address":"Hoberg 12",
    "sg:city":"Vosselaar",
    "sg:orig_category":"Artsen and specialisten",
    "sg:phone":"+32 14 61 21 50",
    "sg:postcode":"2350",
    "sg:province":"Antwerpen",
    "wof:name":"Koenraad L.m. Amery",
    "wof:placetype":"venue"
},
  "geometry": {"coordinates":[4.8584132195,51.3028030396],"type":"Point"}
}