{
  "type": "Feature",
  "properties": {
    "addr:full":"Kiewitstraat 19 Hasselt Limburg 3500",
    "addr:housenumber":"19",
    "addr:postcode":"3500",
    "addr:street":"Kiewitstraat",
    "iso:country":"BE",
    "sg:address":"Kiewitstraat 19",
    "sg:city":"Hasselt",
    "sg:orig_category":"Dakwerken",
    "sg:phone":"+32 11 23 39 40",
    "sg:postcode":"3500",
    "sg:province":"Limburg",
    "wof:name":"Fa. Aldak",
    "wof:placetype":"venue"
},
  "geometry": {"coordinates":[5.3798680305,50.9598197937],"type":"Point"}
}