{
  "type": "Feature",
  "properties": {
    "addr:full":"O. Lt. Catoirestraat 19 Moeskroen/mouscron Hainaut 7711",
    "addr:housenumber":"19",
    "addr:postcode":"7711",
    "addr:street":"O.;Catoirestraat",
    "iso:country":"BE",
    "sg:address":"O. Lt. Catoirestraat 19",
    "sg:city":"Moeskroen/mouscron",
    "sg:orig_category":"Plaatsen van vloer- and muurbekleding Schilders",
    "sg:phone":"+32 56 48 76 03",
    "sg:postcode":"7711",
    "sg:province":"Hainaut",
    "wof:name":"Vanmeenen",
    "wof:placetype":"venue"
},
  "geometry": {"coordinates":[3.3126978874,50.7229728699],"type":"Point"}
}