{
  "type": "Feature",
  "properties": {
    "iso:country":"BE",
    "sg:address":"Rue De La Pecherie 15",
    "sg:city":"Marchin",
    "sg:orig_category":"Eleveurs de bovins",
    "sg:phone":"+32 85 41 11 43",
    "sg:postcode":"4570",
    "sg:province":"Li\u00e8ge",
    "wof:name":"Therese Rigot",
    "wof:placetype":"venue"
},
  "geometry": {"coordinates":[5.2676877975,50.4526023865],"type":"Point"}
}