{
  "type": "Feature",
  "properties": {
    "iso:country":"BE",
    "sg:address":"Klapeksterstraat 1a",
    "sg:city":"Gent",
    "sg:classifiers":[
        {
            "category":"Manufacturing",
            "subcategory":"Furniture",
            "type":"Manufacturing & Wholesale Goods"
        }
    ],
    "sg:phone":"+32 9 227 46 00",
    "sg:postcode":"9000",
    "sg:province":"Oost-Vlaanderen",
    "sg:tags":[
        "made",
        "-",
        "custom"
    ],
    "wof:name":"Christiaens",
    "wof:placetype":"venue"
},
  "geometry": {"coordinates":[3.7018399239,51.0611457825],"type":"Point"}
}