{
  "type": "Feature",
  "properties": {
    "iso:country":"BE",
    "sg:address":"Rue De Bruxelles 52",
    "sg:city":"Esneux",
    "sg:orig_category":"Boucheries",
    "sg:phone":"+32 4 380 35 64",
    "sg:postcode":"4130",
    "sg:province":"Li\u00e8ge",
    "wof:name":"J. Lafut",
    "wof:placetype":"venue"
},
  "geometry": {"coordinates":[5.5662732124,50.5302810669],"type":"Point"}
}