{
  "type": "Feature",
  "properties": {
    "iso:country":"BE",
    "sg:address":"Rue Octave Battaille 51",
    "sg:city":"Beloeil",
    "sg:orig_category":"Catering and organisatie van feesten Fast food and meeneem restaurants Levering aan huis restaurants",
    "sg:phone":"+32 69 56 29 69",
    "sg:postcode":"7971",
    "sg:province":"Hainaut",
    "wof:name":"A La Pom D'adam",
    "wof:placetype":"venue"
},
  "geometry": {"coordinates":[3.643335104,50.5278587341],"type":"Point"}
}