{
  "type": "Feature",
  "properties": {
    "iso:country":"BE",
    "sg:address":"Rue Charles Rittw\u00c9ger 233",
    "sg:city":"Theux",
    "sg:orig_category":"Stations-service and carburants. V\u00e9hicules automobiles",
    "sg:phone":"+32 87 53 90 90",
    "sg:postcode":"4910",
    "sg:province":"Li\u00e8ge",
    "wof:name":"Garage Hotte & Fils",
    "wof:placetype":"venue"
},
  "geometry": {"coordinates":[5.8128199577,50.5394210815],"type":"Point"}
}