{
  "type": "Feature",
  "properties": {
    "iso:country":"BE",
    "sg:address":"Nationalestraat 6",
    "sg:city":"Antwerpen (groot)",
    "sg:classifiers":[
        {
            "category":"Restaurant",
            "type":"Food & Drink"
        }
    ],
    "sg:phone":"+32 3 231 37 28",
    "sg:postcode":"2000",
    "sg:province":"Antwerpen",
    "wof:name":"Combos",
    "wof:placetype":"venue"
},
  "geometry": {"coordinates":[4.4005451202,51.2184104919],"type":"Point"}
}