{
  "type": "Feature",
  "properties": {
    "iso:country":"BE",
    "sg:address":"Avenue Fond Jean Rosy 19",
    "sg:city":"Rixensart",
    "sg:orig_category":"Sportclubs",
    "sg:phone":"+32 2 653 03 51",
    "sg:postcode":"1330",
    "sg:province":"Brabant Wallon",
    "wof:name":"Jeune Et Gym",
    "wof:placetype":"venue"
},
  "geometry": {"coordinates":[4.5115170479,50.7128944397],"type":"Point"}
}