{
  "type": "Feature",
  "properties": {
    "iso:country":"BE",
    "sg:address":"Sint-rochusstraat 9a",
    "sg:city":"Kortessem",
    "sg:orig_category":"Animations diverses",
    "sg:phone":"+32 11 37 57 91",
    "sg:postcode":"3720",
    "sg:province":"Limburg",
    "wof:name":"Disco Olympia",
    "wof:placetype":"venue"
},
  "geometry": {"coordinates":[5.3652949333,50.8783149719],"type":"Point"}
}