{
  "type": "Feature",
  "properties": {
    "iso:country":"BE",
    "sg:address":"Holstraat 56",
    "sg:city":"Waregem",
    "sg:classifiers":[
        {
            "category":"Manufacturing",
            "subcategory":"Tools & Machinery",
            "type":"Manufacturing & Wholesale Goods"
        }
    ],
    "sg:phone":"+32 56 60 14 19",
    "sg:postcode":"8790",
    "sg:province":"West-Vlaanderen",
    "sg:tags":[
        "-"
    ],
    "wof:name":"Amerikaanse Stock Duyck",
    "wof:placetype":"venue"
},
  "geometry": {"coordinates":[3.4369769096,50.8840332031],"type":"Point"}
}