{
  "type": "Feature",
  "properties": {
    "addr:full":"Rue Des Comtes De Salm 29 Vielsalm Luxembourg 6690",
    "addr:housenumber":"29",
    "addr:postcode":"6690",
    "addr:street":"Rue Des Comtes De Salm",
    "iso:country":"BE",
    "sg:address":"Rue Des Comtes De Salm 29",
    "sg:city":"Vielsalm",
    "sg:orig_category":"Epiceries",
    "sg:phone":"+32 80 21 63 08",
    "sg:postcode":"6690",
    "sg:province":"Luxembourg",
    "wof:name":"Louis Delhaize",
    "wof:placetype":"venue"
},
  "geometry": {"coordinates":[5.8893389702,50.2683677673],"type":"Point"}
}