{
  "type": "Feature",
  "properties": {
    "iso:country":"BE",
    "sg:address":"Biststraat 1",
    "sg:city":"Kampenhout (nederokkerzeel)",
    "sg:classifiers":[
        {
            "category":"Professional",
            "subcategory":"Management & Consulting",
            "type":"Services"
        }
    ],
    "sg:phone":"+32 16 65 14 75",
    "sg:postcode":"1910",
    "sg:province":"Vlaams-Brabant",
    "sg:tags":[
        "consultant",
        "agency",
        "advertising"
    ],
    "wof:name":"Rush Com Bvba",
    "wof:placetype":"venue"
},
  "geometry": {"coordinates":[4.559677124,50.9201583862],"type":"Point"}
}