{
  "type": "Feature",
  "properties": {
    "iso:country":"BE",
    "sg:address":"Bergbosstraat 151",
    "sg:city":"Merelbeke",
    "sg:orig_category":"M\u00e9decins and sp\u00e9cialistes",
    "sg:phone":"+32 9 230 62 69",
    "sg:postcode":"9820",
    "sg:province":"Oost-Vlaanderen",
    "wof:name":"Frans Van Leuven",
    "wof:placetype":"venue"
},
  "geometry": {"coordinates":[3.7339959145,50.9812736511],"type":"Point"}
}