{
  "type": "Feature",
  "properties": {
    "addr:full":"Chemin Des Deux Maisons 179 Box 66 Bruxelles (woluwe-saint-lambert) Bruxelles-Capitale 1200",
    "addr:housenumber":"179 box 66",
    "addr:postcode":"1200",
    "addr:street":"Chemin Des Deux Maisons",
    "iso:country":"BE",
    "sg:address":"Chemin Des Deux Maisons 179 Box 66",
    "sg:city":"Bruxelles (woluwe-saint-lambert)",
    "sg:classifiers":[
        {
            "category":"Professional",
            "subcategory":"Accounting & Tax Preparation",
            "type":"Services"
        }
    ],
    "sg:phone":"+32 2 762 29 50",
    "sg:postcode":"1200",
    "sg:province":"Bruxelles-Capitale",
    "sg:tags":[
        "bookkeeper"
    ],
    "wof:name":"Euraccount Sprl",
    "wof:placetype":"venue"
},
  "geometry": {"coordinates":[4.424284935,50.8551216125],"type":"Point"}
}