{
  "type": "Feature",
  "properties": {
    "addr:full":"Brusselsesteenweg 81 Tervuren Vlaams-Brabant 3080",
    "addr:housenumber":"81",
    "addr:postcode":"3080",
    "addr:street":"Brusselsesteenweg",
    "iso:country":"BE",
    "sg:address":"Brusselsesteenweg 81",
    "sg:city":"Tervuren",
    "sg:orig_category":"Kapsalons",
    "sg:phone":"+32 2 767 82 58",
    "sg:postcode":"3080",
    "sg:province":"Vlaams-Brabant",
    "wof:name":"Deborah",
    "wof:placetype":"venue"
},
  "geometry": {"coordinates":[4.5077967644,50.8241004944],"type":"Point"}
}