{
  "type": "Feature",
  "properties": {
    "addr:full":"Hoevestraat 3 Pepingen Vlaams-Brabant 1670",
    "addr:housenumber":"3",
    "addr:postcode":"1670",
    "addr:street":"Hoevestraat",
    "iso:country":"BE",
    "sg:address":"Hoevestraat 3",
    "sg:city":"Pepingen",
    "sg:classifiers":[
        {
            "category":"Building & Trades",
            "subcategory":"Landscaping Services",
            "type":"Services"
        }
    ],
    "sg:phone":"+32 2 360 11 84",
    "sg:postcode":"1670",
    "sg:province":"Vlaams-Brabant",
    "sg:tags":[
        "-",
        "lopping",
        "work",
        "tree",
        "felling"
    ],
    "wof:name":"Tuinen Roosens Bvba",
    "wof:placetype":"venue"
},
  "geometry": {"coordinates":[4.1721577644,50.7410202026],"type":"Point"}
}