{
  "type": "Feature",
  "properties": {
    "iso:country":"BE",
    "sg:address":"Rue Jean Koch 4",
    "sg:city":"Lambermont",
    "sg:classifiers":[
        {
            "category":"Shopping",
            "subcategory":"Crafts & Fabrics",
            "type":"Retail Goods"
        }
    ],
    "sg:phone":"+32 87 31 09 06",
    "sg:postcode":"4800",
    "sg:province":"Li\u00e8ge",
    "sg:tags":[
        "band",
        "knife"
    ],
    "wof:name":"Bks S.a.",
    "wof:placetype":"venue"
},
  "geometry": {"coordinates":[5.8345651627,50.581161499],"type":"Point"}
}