{
  "type": "Feature",
  "properties": {
    "addr:full":"Heldenlaan 24 Zottegem Oost-Vlaanderen 9620",
    "addr:housenumber":"24",
    "addr:postcode":"9620",
    "addr:street":"Heldenlaan",
    "iso:country":"BE",
    "sg:address":"Heldenlaan 24",
    "sg:city":"Zottegem",
    "sg:orig_category":"Agences d\u00b4interim and personnel temporaire",
    "sg:phone":"+32 78 16 92 87",
    "sg:postcode":"9620",
    "sg:province":"Oost-Vlaanderen",
    "wof:name":"Randstad",
    "wof:placetype":"venue"
},
  "geometry": {"coordinates":[3.8097519875,50.8704414368],"type":"Point"}
}