{
  "type": "Feature",
  "properties": {
    "addr:full":"Chemin Du Vert Buisson 2 Ath Hainaut 7802",
    "addr:housenumber":"2",
    "addr:postcode":"7802",
    "addr:street":"Chemin Du Vert Buisson",
    "iso:country":"BE",
    "sg:address":"Chemin Du Vert Buisson 2",
    "sg:city":"Ath",
    "sg:orig_category":"M\u00e9decines alternatives",
    "sg:phone":"+32 68 28 22 98",
    "sg:postcode":"7802",
    "sg:province":"Hainaut",
    "wof:name":"Harmegnies Berengere",
    "wof:placetype":"venue"
},
  "geometry": {"coordinates":[3.7527279854,50.5938110352],"type":"Point"}
}