{
  "type": "Feature",
  "properties": {
    "iso:country":"BE",
    "sg:address":"Avenue Charles Deli\u00c8ge 11",
    "sg:city":"Binche",
    "sg:orig_category":"Speelgoed",
    "sg:phone":"+32 64 33 20 34",
    "sg:postcode":"7130",
    "sg:province":"Hainaut",
    "wof:name":"Le R\u00cave Des Petits",
    "wof:placetype":"venue"
},
  "geometry": {"coordinates":[4.167714119,50.414932251],"type":"Point"}
}