{
  "type": "Feature",
  "properties": {
    "iso:country":"BE",
    "sg:address":"Rue De Void 16",
    "sg:city":"Braives",
    "sg:orig_category":"Woningbouw",
    "sg:phone":"+32 19 69 81 48",
    "sg:postcode":"4260",
    "sg:province":"Li\u00e8ge",
    "wof:name":"Constant Willems",
    "wof:placetype":"venue"
},
  "geometry": {"coordinates":[5.0946230888,50.6172027588],"type":"Point"}
}