{
  "type": "Feature",
  "properties": {
    "addr:full":"Rue De Ave 97g Wellin Luxembourg 6920",
    "addr:housenumber":"97g",
    "addr:postcode":"6920",
    "addr:street":"Rue De Ave",
    "iso:country":"BE",
    "sg:address":"Rue De Ave 97g",
    "sg:city":"Wellin",
    "sg:classifiers":[
        {
            "category":"Animal Shelter",
            "type":"Public Place"
        }
    ],
    "sg:phone":"+32 84 38 84 85",
    "sg:postcode":"6920",
    "sg:province":"Luxembourg",
    "sg:tags":[
        "nutrition",
        "husbandry"
    ],
    "wof:name":"Carri\u00e8res Des Limites S.a.",
    "wof:placetype":"venue"
},
  "geometry": {"coordinates":[5.1139631271,50.0823478699],"type":"Point"}
}