{
  "type": "Feature",
  "properties": {
    "iso:country":"BE",
    "sg:address":"Pradostraat 8",
    "sg:city":"Sint-jans-molenbeek/molenbeek-saint-jean",
    "sg:orig_category":"Verlichting and huishoudartikelen",
    "sg:phone":"+32 2 411 58 59",
    "sg:postcode":"1080",
    "sg:province":"Bruxelles-Capitale",
    "wof:name":"Big-shop",
    "wof:placetype":"venue"
},
  "geometry": {"coordinates":[4.3375301361,50.8539657593],"type":"Point"}
}