{
  "type": "Feature",
  "properties": {
    "addr:full":"Tentoonstellingslaan 15 Gent Oost-Vlaanderen 9000",
    "addr:housenumber":"15",
    "addr:postcode":"9000",
    "addr:street":"Tentoonstellingslaan;Oost-Vlaanderen",
    "iso:country":"BE",
    "sg:address":"Tentoonstellingslaan 15",
    "sg:city":"Gent",
    "sg:orig_category":"Advocaten and juridische adviseurs Balie van Gent",
    "sg:phone":"+32 9 233 31 55",
    "sg:postcode":"9000",
    "sg:province":"Oost-Vlaanderen",
    "wof:name":"Deurbroeck Peter",
    "wof:placetype":"venue"
},
  "geometry": {"coordinates":[3.7331960201,51.0420150757],"type":"Point"}
}