{
  "type": "Feature",
  "properties": {
    "iso:country":"BE",
    "sg:address":"Leuvensesteenweg 30",
    "sg:city":"Boortmeerbeek",
    "sg:orig_category":"Immobili\u00ebnkantoren",
    "sg:phone":"+32 15 51 80 90",
    "sg:postcode":"3191",
    "sg:province":"Vlaams-Brabant",
    "wof:name":"Immobilienkantoor De Woning",
    "wof:placetype":"venue"
},
  "geometry": {"coordinates":[4.5342898369,50.9929618835],"type":"Point"}
}