{
  "type": "Feature",
  "properties": {
    "addr:full":"Venneweg 3 Hoogstraten Antwerpen 2321",
    "addr:housenumber":"3",
    "addr:postcode":"2321",
    "addr:street":"Venneweg",
    "iso:country":"BE",
    "sg:address":"Venneweg 3",
    "sg:city":"Hoogstraten",
    "sg:orig_category":"Eleveurs de bovins",
    "sg:phone":"+32 3 315 85 66",
    "sg:postcode":"2321",
    "sg:province":"Antwerpen",
    "wof:name":"Marcel Quirijnen",
    "wof:placetype":"venue"
},
  "geometry": {"coordinates":[4.7397289276,51.4306755066],"type":"Point"}
}