{
  "type": "Feature",
  "properties": {
    "iso:country":"BE",
    "sg:address":"Schotensteenweg 31",
    "sg:city":"Brecht",
    "sg:classifiers":[
        {
            "category":"Building & Trades",
            "subcategory":"Construction",
            "type":"Services"
        }
    ],
    "sg:phone":"+32 3 313 62 83",
    "sg:postcode":"2960",
    "sg:province":"Antwerpen",
    "sg:tags":[
        "stucco",
        "contractor"
    ],
    "wof:name":"Anthonissen D",
    "wof:placetype":"venue"
},
  "geometry": {"coordinates":[4.6143651009,51.3354797363],"type":"Point"}
}