{
  "type": "Feature",
  "properties": {
    "addr:full":"Oostveldstraat 184 Eeklo Oost-Vlaanderen 9900",
    "addr:housenumber":"184",
    "addr:postcode":"9900",
    "addr:street":"Oostveldstraat",
    "iso:country":"BE",
    "sg:address":"Oostveldstraat 184",
    "sg:city":"Eeklo",
    "sg:orig_category":"Meubles D\u00e9taillants, Am\u00e9nagement de B\u00e2timents et de Cuisines. Meubles Fab",
    "sg:phone":"+32 9 377 20 52",
    "sg:postcode":"9900",
    "sg:province":"Oost-Vlaanderen",
    "wof:name":"Codam",
    "wof:placetype":"venue"
},
  "geometry": {"coordinates":[3.5853099823,51.1809692383],"type":"Point"}
}