{
  "type": "Feature",
  "properties": {
    "iso:country":"BE",
    "sg:address":"Diestse Baan 62",
    "sg:city":"Laakdal",
    "sg:orig_category":"Boekbinderijen and afwerking",
    "sg:phone":"+32 14 84 11 38",
    "sg:postcode":"2431",
    "sg:province":"Antwerpen",
    "wof:name":"Zusters Norbertinessen",
    "wof:placetype":"venue"
},
  "geometry": {"coordinates":[4.9917879105,51.0634002686],"type":"Point"}
}