{
  "type": "Feature",
  "properties": {
    "iso:country":"BE",
    "sg:address":"Hasseltsestraat 9",
    "sg:city":"Herk-de-stad",
    "sg:orig_category":"M\u00e9decins and sp\u00e9cialistes",
    "sg:phone":"+32 13 55 15 68",
    "sg:postcode":"3540",
    "sg:province":"Limburg",
    "wof:name":"An Nolmans",
    "wof:placetype":"venue"
},
  "geometry": {"coordinates":[5.1676921844,50.9409980774],"type":"Point"}
}