{
  "type": "Feature",
  "properties": {
    "iso:country":"BE",
    "sg:address":"Lindendreef 16",
    "sg:city":"Beerse",
    "sg:orig_category":"Epiceries. Articles non-alimentaires",
    "sg:phone":"+32 14 61 55 01",
    "sg:postcode":"2340",
    "sg:province":"Antwerpen",
    "wof:name":"Concor",
    "wof:placetype":"venue"
},
  "geometry": {"coordinates":[4.8544211388,51.310546875],"type":"Point"}
}