{
  "type": "Feature",
  "properties": {
    "iso:country":"BE",
    "sg:address":"Sint Jacobsmarkt 76b1",
    "sg:city":"Antwerpen",
    "sg:orig_category":"Editeurs de livres",
    "sg:phone":"+32 3 226 77 19",
    "sg:postcode":"2000",
    "sg:province":"Antwerpen",
    "wof:name":"Inside Records",
    "wof:placetype":"venue"
},
  "geometry": {"coordinates":[4.4139971733,51.2199249268],"type":"Point"}
}