{
  "type": "Feature",
  "properties": {
    "addr:full":"Avenue Blonden 4 Li\u00e8ge 1 Li\u00e8ge 4000",
    "addr:housenumber":"4;1",
    "addr:postcode":"4000",
    "addr:street":"Avenue Blonden",
    "iso:country":"BE",
    "sg:address":"Avenue Blonden 4",
    "sg:city":"Li\u00e8ge 1",
    "sg:classifiers":[
        {
            "category":"Organizations",
            "subcategory":"Professional Association",
            "type":"Services"
        }
    ],
    "sg:phone":"+32 4 253 03 05",
    "sg:postcode":"4000",
    "sg:province":"Li\u00e8ge",
    "sg:tags":[
        "trade-union",
        "federation"
    ],
    "wof:name":"Ital-vil Patronato",
    "wof:placetype":"venue"
},
  "geometry": {"coordinates":[5.5696239471,50.6291923523],"type":"Point"}
}