{
  "type": "Feature",
  "properties": {
    "addr:full":"Moerstraat 49 Wetteren Oost-Vlaanderen 9230",
    "addr:housenumber":"49",
    "addr:postcode":"9230",
    "addr:street":"Moerstraat",
    "iso:country":"BE",
    "sg:address":"Moerstraat 49",
    "sg:city":"Wetteren",
    "sg:orig_category":"Motos. V\u00e9los",
    "sg:phone":"+32 9 369 11 87",
    "sg:postcode":"9230",
    "sg:province":"Oost-Vlaanderen",
    "wof:name":"Ronny",
    "wof:placetype":"venue"
},
  "geometry": {"coordinates":[3.8812160492,51.0053100586],"type":"Point"}
}