{
  "type": "Feature",
  "properties": {
    "iso:country":"BE",
    "sg:address":"Stationsplein 30a",
    "sg:city":"Herentals",
    "sg:classifiers":[
        {
            "category":"Taxi",
            "type":"Transportation"
        }
    ],
    "sg:phone":"+32 14 23 07 53",
    "sg:postcode":"2200",
    "sg:province":"Antwerpen",
    "sg:tags":[
        "taxicab"
    ],
    "wof:name":"Mini-taxi-herentals-l.b.s. Nv",
    "wof:placetype":"venue"
},
  "geometry": {"coordinates":[4.8300938606,51.1810684204],"type":"Point"}
}