{
  "type": "Feature",
  "properties": {
    "iso:country":"BE",
    "sg:address":"Rue Sergent Delisse 5",
    "sg:city":"Namur (bouge)",
    "sg:classifiers":[
        {
            "category":"Communications",
            "subcategory":"Film & Video Production",
            "type":"Services"
        }
    ],
    "sg:phone":"+32 81 21 50 28",
    "sg:postcode":"5004",
    "sg:province":"Namur",
    "sg:tags":[
        "realisation",
        "-"
    ],
    "wof:name":"Class Video Productions",
    "wof:placetype":"venue"
},
  "geometry": {"coordinates":[4.8878769875,50.4854011536],"type":"Point"}
}