{
  "type": "Feature",
  "properties": {
    "iso:country":"BE",
    "sg:address":"Diamantstraat 9",
    "sg:city":"Diksmuide",
    "sg:classifiers":[
        {
            "category":"Restaurant",
            "type":"Food & Drink"
        }
    ],
    "sg:phone":"+32 51 50 18 95",
    "sg:postcode":"8600",
    "sg:province":"West-Vlaanderen",
    "sg:tags":[
        "industrial",
        "kitchen",
        "catering"
    ],
    "wof:name":"Seys-gitsels Zuivelhandel",
    "wof:placetype":"venue"
},
  "geometry": {"coordinates":[2.858438015,51.0278282166],"type":"Point"}
}