{
  "type": "Feature",
  "properties": {
    "addr:full":"Vismijnlaan 141 Oostende West-Vlaanderen 8400",
    "addr:housenumber":"141",
    "addr:postcode":"8400",
    "addr:street":"Vismijnlaan",
    "iso:country":"BE",
    "sg:address":"Vismijnlaan 141",
    "sg:city":"Oostende",
    "sg:classifiers":[
        {
            "category":"Restaurant",
            "type":"Food & Drink"
        }
    ],
    "sg:phone":"+32 59 32 22 86",
    "sg:postcode":"8400",
    "sg:province":"West-Vlaanderen",
    "sg:tags":[
        "industrial",
        "kitchen",
        "catering"
    ],
    "wof:name":"Bonnet Viswaren Nv",
    "wof:placetype":"venue"
},
  "geometry": {"coordinates":[2.9373478889,51.2288475037],"type":"Point"}
}