{
  "type": "Feature",
  "properties": {
    "iso:country":"BE",
    "sg:address":"Burchtlaan 8",
    "sg:city":"Lubbeek",
    "sg:orig_category":"Plomberie, chauffage and installations sanitaires",
    "sg:phone":"+32 16 25 32 58",
    "sg:postcode":"3210",
    "sg:province":"Vlaams-Brabant",
    "wof:name":"G. Siebens",
    "wof:placetype":"venue"
},
  "geometry": {"coordinates":[4.7652950287,50.9037437439],"type":"Point"}
}