{
  "type": "Feature",
  "properties": {
    "addr:full":"Stationstraat 302 Moorslede West-Vlaanderen 8890",
    "addr:housenumber":"302",
    "addr:postcode":"8890",
    "addr:street":"Stationstraat",
    "iso:country":"BE",
    "sg:address":"Stationstraat 302",
    "sg:city":"Moorslede",
    "sg:classifiers":[
        {
            "category":"Wholesale",
            "subcategory":"Sporting Goods",
            "type":"Manufacturing & Wholesale Goods"
        }
    ],
    "sg:phone":"+32 51 77 96 89",
    "sg:postcode":"8890",
    "sg:province":"West-Vlaanderen",
    "sg:tags":[
        "sport-",
        "kampeermateriaal"
    ],
    "wof:name":"Sportorama",
    "wof:placetype":"venue"
},
  "geometry": {"coordinates":[3.0368170738,50.8952598572],"type":"Point"}
}