{
  "type": "Feature",
  "properties": {
    "addr:full":"Edgard Tinellaan 2b Mechelen Antwerpen 2800",
    "addr:housenumber":"2b",
    "addr:postcode":"2800",
    "addr:street":"Edgard Tinellaan",
    "iso:country":"BE",
    "sg:address":"Edgard Tinellaan 2b",
    "sg:city":"Mechelen",
    "sg:classifiers":[
        {
            "category":"Social Services",
            "type":"Services"
        }
    ],
    "sg:phone":"+32 3 866 57 89",
    "sg:postcode":"2800",
    "sg:province":"Antwerpen",
    "wof:name":"C K G Betlehem",
    "wof:placetype":"venue"
},
  "geometry": {"coordinates":[4.4752030373,51.0339851379],"type":"Point"}
}