{
  "type": "Feature",
  "properties": {
    "iso:country":"BE",
    "sg:address":"Winterslagstraat 101",
    "sg:city":"Genk",
    "sg:classifiers":[
        {
            "category":"Professional",
            "subcategory":"Lawyer & Legal Services",
            "type":"Services"
        }
    ],
    "sg:phone":"+32 89 30 49 47",
    "sg:postcode":"3600",
    "sg:province":"Limburg",
    "wof:name":"Maleux Kristien",
    "wof:placetype":"venue"
},
  "geometry": {"coordinates":[5.499961853,50.9696807861],"type":"Point"}
}