{
  "type": "Feature",
  "properties": {
    "addr:full":"Grande Rue 18 Durbuy Luxembourg 6940",
    "addr:housenumber":"18",
    "addr:postcode":"6940",
    "addr:street":"Grande Rue",
    "iso:country":"BE",
    "sg:address":"Grande Rue 18",
    "sg:city":"Durbuy",
    "sg:orig_category":"Elektrische installaties voor woningen Huishoudapparaten, televisies and radio's",
    "sg:phone":"+32 86 21 15 62",
    "sg:postcode":"6940",
    "sg:province":"Luxembourg",
    "wof:name":"Antoine Marc Et Serge",
    "wof:placetype":"venue"
},
  "geometry": {"coordinates":[5.4952149391,50.3505516052],"type":"Point"}
}