{
  "type": "Feature",
  "properties": {
    "addr:full":"Maaseikerlaan 86 Maaseik Limburg 3680",
    "addr:housenumber":"86",
    "addr:postcode":"3680",
    "addr:street":"Maaseikerlaan",
    "iso:country":"BE",
    "sg:address":"Maaseikerlaan 86",
    "sg:city":"Maaseik",
    "sg:orig_category":"Installation \u00e9lectrique r\u00e9sidentielle",
    "sg:phone":"+32 89 86 84 18",
    "sg:postcode":"3680",
    "sg:province":"Limburg",
    "wof:name":"Tegro",
    "wof:placetype":"venue"
},
  "geometry": {"coordinates":[5.791285038,51.0954208374],"type":"Point"}
}