{
  "type": "Feature",
  "properties": {
    "iso:country":"BE",
    "sg:address":"Moerkantsebaan 285",
    "sg:city":"Essen",
    "sg:orig_category":"Enseignement maternel and primaire",
    "sg:phone":"+32 3 667 33 94",
    "sg:postcode":"2910",
    "sg:province":"Antwerpen",
    "wof:name":"Vrije Kleuterschool",
    "wof:placetype":"venue"
},
  "geometry": {"coordinates":[4.4125609398,51.4462776184],"type":"Point"}
}