{
  "type": "Feature",
  "properties": {
    "addr:full":"Place Paul Pastur 13 Anderlues Hainaut 6150",
    "addr:housenumber":"13",
    "addr:postcode":"6150",
    "addr:street":"Place Paul Pastur",
    "iso:country":"BE",
    "sg:address":"Place Paul Pastur 13",
    "sg:city":"Anderlues",
    "sg:orig_category":"Paramedische behandelingen",
    "sg:phone":"+32 71 54 26 29",
    "sg:postcode":"6150",
    "sg:province":"Hainaut",
    "wof:name":"A. Hins",
    "wof:placetype":"venue"
},
  "geometry": {"coordinates":[4.2698287964,50.4082565308],"type":"Point"}
}