{
  "type": "Feature",
  "properties": {
    "addr:full":"Rue Des Trois Soeurs 26 Amay Li\u00e8ge 4540",
    "addr:housenumber":"26",
    "addr:postcode":"4540",
    "addr:street":"Rue Des Trois Soeurs",
    "iso:country":"BE",
    "sg:address":"Rue Des Trois Soeurs 26",
    "sg:city":"Amay",
    "sg:orig_category":"Gespecialiseerde residenti\u00eble bouw Woningbouw",
    "sg:phone":"+32 85 31 39 76",
    "sg:postcode":"4540",
    "sg:province":"Li\u00e8ge",
    "wof:name":"Desire Cornet",
    "wof:placetype":"venue"
},
  "geometry": {"coordinates":[5.3079838753,50.5601959229],"type":"Point"}
}