{
  "type": "Feature",
  "properties": {
    "iso:country":"BE",
    "sg:address":"Eggestraat 54",
    "sg:city":"Beringen",
    "sg:classifiers":[
        {
            "category":"Cafe",
            "type":"Food & Drink"
        }
    ],
    "sg:phone":"+32 11 34 34 02",
    "sg:postcode":"3581",
    "sg:province":"Limburg",
    "sg:tags":[
        "caf\u00e9s"
    ],
    "wof:name":"Play More Music",
    "wof:placetype":"venue"
},
  "geometry": {"coordinates":[5.2228298187,51.0881996155],"type":"Point"}
}