{
  "type": "Feature",
  "properties": {
    "iso:country":"BE",
    "sg:address":"Rue De L'ange 29",
    "sg:city":"Charleroi",
    "sg:orig_category":"Dameskledingzaken",
    "sg:phone":"+32 71 36 27 19",
    "sg:postcode":"6001",
    "sg:province":"Hainaut",
    "wof:name":"Maison Cristaline",
    "wof:placetype":"venue"
},
  "geometry": {"coordinates":[4.4506602287,50.3992881775],"type":"Point"}
}