{
  "type": "Feature",
  "properties": {
    "iso:country":"BE",
    "sg:address":"Stokerijstraat 35",
    "sg:city":"Wijnegem",
    "sg:classifiers":[
        {
            "category":"Building & Trades",
            "subcategory":"Pest Control",
            "type":"Services"
        }
    ],
    "sg:phone":"+32 3 353 26 89",
    "sg:postcode":"2110",
    "sg:province":"Antwerpen",
    "sg:tags":[
        "work",
        "material",
        "equipment",
        "construction",
        "transport",
        "vehicle",
        "public",
        "boat"
    ],
    "wof:name":"Blommaert Scheepsluiken Bvba",
    "wof:placetype":"venue"
},
  "geometry": {"coordinates":[4.5350279808,51.2266273499],"type":"Point"}
}