{
  "type": "Feature",
  "properties": {
    "addr:full":". Perwez Brabant Wallon 1360",
    "addr:housenumber":"1360",
    "iso:country":"BE",
    "sg:address":".",
    "sg:city":"Perwez",
    "sg:orig_category":"Bagage and lederwaren Schoenen",
    "sg:phone":"+32 81 65 81 03",
    "sg:postcode":"1360",
    "sg:province":"Brabant Wallon",
    "wof:name":"Gallipette",
    "wof:placetype":"venue"
},
  "geometry": {"coordinates":[4.8146052361,50.6239395142],"type":"Point"}
}