{
  "type": "Feature",
  "properties": {
    "addr:full":"Boulevard Du Souverain 117bb Oudergem/auderghem Bruxelles-Capitale 1160",
    "addr:housenumber":"117bb",
    "addr:postcode":"1160",
    "addr:street":"Boulevard Du Souverain;/",
    "iso:country":"BE",
    "sg:address":"Boulevard Du Souverain 117bb",
    "sg:city":"Oudergem/auderghem",
    "sg:orig_category":"Location de cassettes vid\u00e9o and audio. Tabac. Journaux",
    "sg:phone":"+32 2 672 75 71",
    "sg:postcode":"1160",
    "sg:province":"Bruxelles-Capitale",
    "wof:name":"Maison Multinight",
    "wof:placetype":"venue"
},
  "geometry": {"coordinates":[4.426735878,50.8141288757],"type":"Point"}
}