{
  "type": "Feature",
  "properties": {
    "iso:country":"BE",
    "sg:address":"Lange Ridderstraat 17",
    "sg:city":"Mechelen",
    "sg:classifiers":[
        {
            "category":"Cafe",
            "type":"Food & Drink"
        }
    ],
    "sg:phone":"+32 15 21 74 35",
    "sg:postcode":"2800",
    "sg:province":"Antwerpen",
    "sg:tags":[
        "snack-bars"
    ],
    "wof:name":"Kotmadam (de)",
    "wof:placetype":"venue"
},
  "geometry": {"coordinates":[4.4837379456,51.0251312256],"type":"Point"}
}