{
  "type": "Feature",
  "properties": {
    "addr:full":"Stationstraat 16 Genk Limburg 3600",
    "addr:housenumber":"16",
    "addr:postcode":"3600",
    "addr:street":"Stationstraat",
    "iso:country":"BE",
    "sg:address":"Stationstraat 16",
    "sg:city":"Genk",
    "sg:orig_category":"Boekhandels Krantenwinkels Microsoft",
    "sg:phone":"+32 89 30 68 32",
    "sg:postcode":"3600",
    "sg:province":"Limburg",
    "wof:name":"Standaard Boekhandel Genk",
    "wof:placetype":"venue"
},
  "geometry": {"coordinates":[5.500852108,50.9647636414],"type":"Point"}
}