{
  "type": "Feature",
  "properties": {
    "iso:country":"BE",
    "sg:address":"Rue De La Vall\u00c9e 44",
    "sg:city":"Chatelet",
    "sg:orig_category":"Alternatieve geneeskunde Artsen and specialisten",
    "sg:phone":"+32 71 38 17 96",
    "sg:postcode":"6200",
    "sg:province":"Hainaut",
    "wof:name":"N\u00d9ria Gomez Ladevesa",
    "wof:placetype":"venue"
},
  "geometry": {"coordinates":[4.5178260803,50.4126548767],"type":"Point"}
}