{
  "type": "Feature",
  "properties": {
    "addr:full":"Lindenlaan 57 Beerse Antwerpen 2340",
    "addr:housenumber":"57",
    "addr:postcode":"2340",
    "addr:street":"Lindenlaan",
    "iso:country":"BE",
    "sg:address":"Lindenlaan 57",
    "sg:city":"Beerse",
    "sg:orig_category":"Slagers",
    "sg:phone":"+32 14 61 12 15",
    "sg:postcode":"2340",
    "sg:province":"Antwerpen",
    "wof:name":"Leo Driesen",
    "wof:placetype":"venue"
},
  "geometry": {"coordinates":[4.8512501717,51.3189582825],"type":"Point"}
}