{
  "type": "Feature",
  "properties": {
    "addr:full":"Kapucinessenstraat 17 Antwerpen Antwerpen 2000",
    "addr:housenumber":"17",
    "addr:postcode":"2000",
    "addr:street":"Kapucinessenstraat",
    "iso:country":"BE",
    "sg:address":"Kapucinessenstraat 17",
    "sg:city":"Antwerpen",
    "sg:classifiers":[
        {
            "category":"Community Center",
            "subcategory":"Youth",
            "type":"Public Place"
        }
    ],
    "sg:phone":"+32 3 234 09 31",
    "sg:postcode":"2000",
    "sg:province":"Antwerpen",
    "sg:tags":[
        "club"
    ],
    "wof:name":"Scouts Vzw",
    "wof:placetype":"venue"
},
  "geometry": {"coordinates":[4.4041361809,51.211391449],"type":"Point"}
}