{
  "type": "Feature",
  "properties": {
    "addr:full":"Avou\u00c9straat 1 Aalst Oost-Vlaanderen 9310",
    "addr:housenumber":"1",
    "addr:postcode":"9310",
    "addr:street":"Avoue\u0301Straat",
    "iso:country":"BE",
    "sg:address":"Avou\u00c9straat 1",
    "sg:city":"Aalst",
    "sg:orig_category":"Location d'appareils audio-visuels",
    "sg:phone":"+32 53 70 47 20",
    "sg:postcode":"9310",
    "sg:province":"Oost-Vlaanderen",
    "wof:name":"Tokkie Sound-light Syst.",
    "wof:placetype":"venue"
},
  "geometry": {"coordinates":[4.0882911682,50.9505271912],"type":"Point"}
}