{
  "type": "Feature",
  "properties": {
    "addr:full":"Chemin De La Dime 18 Chaumont-gistoux Brabant Wallon 1325",
    "addr:housenumber":"18",
    "addr:postcode":"1325",
    "addr:street":"Chemin De La Dime",
    "iso:country":"BE",
    "sg:address":"Chemin De La Dime 18",
    "sg:city":"Chaumont-gistoux",
    "sg:orig_category":"Administration d'immeubles",
    "sg:phone":"+32 10 68 84 62",
    "sg:postcode":"1325",
    "sg:province":"Brabant Wallon",
    "wof:name":"Majela",
    "wof:placetype":"venue"
},
  "geometry": {"coordinates":[4.6726589203,50.6603622437],"type":"Point"}
}