{
  "type": "Feature",
  "properties": {
    "iso:country":"BE",
    "sg:address":"Dorpstraat 49",
    "sg:city":"Zwijndrecht (burcht)",
    "sg:classifiers":[
        {
            "category":"Banks & Credit Unions",
            "subcategory":"Investment Brokerage",
            "type":"Services"
        }
    ],
    "sg:phone":"+32 3 252 51 43",
    "sg:postcode":"2070",
    "sg:province":"Antwerpen",
    "sg:tags":[
        "auditor"
    ],
    "wof:name":"Cloostermans H-j & Co",
    "wof:placetype":"venue"
},
  "geometry": {"coordinates":[4.3457269669,51.2017326355],"type":"Point"}
}