{
  "type": "Feature",
  "properties": {
    "addr:full":"Hendrik Beyaertstraat 2 Kortrijk West-Vlaanderen 8500",
    "addr:housenumber":"2",
    "addr:postcode":"8500",
    "addr:street":"Hendrik Beyaertstraat",
    "iso:country":"BE",
    "sg:address":"Hendrik Beyaertstraat 2",
    "sg:city":"Kortrijk",
    "sg:classifiers":[
        {
            "category":"Organizations",
            "subcategory":"Professional Association",
            "type":"Services"
        }
    ],
    "sg:phone":"+32 56 21 05 08",
    "sg:postcode":"8500",
    "sg:province":"West-Vlaanderen",
    "sg:tags":[
        "trade-union",
        "federation"
    ],
    "wof:name":"Vl. Artsen Synd. Afd O.vl & W.vlaanderen",
    "wof:placetype":"venue"
},
  "geometry": {"coordinates":[3.2586810589,50.8288040161],"type":"Point"}
}