{
  "type": "Feature",
  "properties": {
    "addr:full":"Tieltsesteenweg 2b2 Eeklo Oost-Vlaanderen 9900",
    "addr:housenumber":"2b2",
    "addr:postcode":"9900",
    "addr:street":"Tieltsesteenweg",
    "iso:country":"BE",
    "sg:address":"Tieltsesteenweg 2b2",
    "sg:city":"Eeklo",
    "sg:orig_category":"Diverse producten Gh",
    "sg:phone":"+32 9 378 28 24",
    "sg:postcode":"9900",
    "sg:province":"Oost-Vlaanderen",
    "wof:name":"Cis Trading",
    "wof:placetype":"venue"
},
  "geometry": {"coordinates":[3.5578789711,51.1859779358],"type":"Point"}
}