{
  "type": "Feature",
  "properties": {
    "addr:full":"Heide 32 Hulshout (westmeerbeek) Antwerpen 2235",
    "addr:housenumber":"32",
    "addr:postcode":"2235",
    "addr:street":"Heide",
    "iso:country":"BE",
    "sg:address":"Heide 32",
    "sg:city":"Hulshout (westmeerbeek)",
    "sg:classifiers":[
        {
            "category":"Building & Trades",
            "subcategory":"Landscaping Services",
            "type":"Services"
        }
    ],
    "sg:phone":"+32 16 69 88 98",
    "sg:postcode":"2235",
    "sg:province":"Antwerpen",
    "sg:tags":[
        "architect",
        "landscape"
    ],
    "wof:name":"Greenline Tuincreatie",
    "wof:placetype":"venue"
},
  "geometry": {"coordinates":[4.8423390388,51.06275177],"type":"Point"}
}