{
  "type": "Feature",
  "properties": {
    "iso:country":"BE",
    "sg:address":"Avenue Guillaume Van Nerom 15b70",
    "sg:city":"Oudergem/auderghem",
    "sg:orig_category":"Services de Nettoyage and de D\u00e9sinfection. Travaux de finition and nettoyage de b\u00e2timents",
    "sg:phone":"+32 2 673 35 93",
    "sg:postcode":"1160",
    "sg:province":"Bruxelles-Capitale",
    "wof:name":"Marcel Bekkers",
    "wof:placetype":"venue"
},
  "geometry": {"coordinates":[4.4316601753,50.8066749573],"type":"Point"}
}