{
  "type": "Feature",
  "properties": {
    "addr:full":"Smishoekstraat 8 Sint-gillis-waas (meerdonk) Oost-Vlaanderen 9170",
    "addr:housenumber":"8",
    "addr:postcode":"9170",
    "addr:street":"Smishoekstraat",
    "iso:country":"BE",
    "sg:address":"Smishoekstraat 8",
    "sg:city":"Sint-gillis-waas (meerdonk)",
    "sg:classifiers":[
        {
            "category":"Retail",
            "subcategory":"Auto Repair",
            "type":"Services"
        }
    ],
    "sg:phone":"+32 3 773 49 72",
    "sg:postcode":"9170",
    "sg:province":"Oost-Vlaanderen",
    "sg:tags":[
        "garage"
    ],
    "wof:name":"Geerts E",
    "wof:placetype":"venue"
},
  "geometry": {"coordinates":[4.1538572311,51.2578010559],"type":"Point"}
}