{
  "type": "Feature",
  "properties": {
    "iso:country":"BE",
    "sg:address":"Rue De Longsart 22",
    "sg:city":"Manage",
    "sg:classifiers":[
        {
            "category":"Health Services",
            "subcategory":"Doctor",
            "type":"Services"
        }
    ],
    "sg:phone":"+32 64 55 80 03",
    "sg:postcode":"7170",
    "sg:province":"Hainaut",
    "sg:tags":[
        "medicinephysicians",
        "surgeon"
    ],
    "wof:name":"Joris Marc",
    "wof:placetype":"venue"
},
  "geometry": {"coordinates":[4.2487168312,50.4995155334],"type":"Point"}
}