{
  "type": "Feature",
  "properties": {
    "addr:full":"Rue Andr\u00c9 Renard 3b2 Oupeye Li\u00e8ge 4680",
    "addr:housenumber":"3b2",
    "addr:postcode":"4680",
    "addr:street":"Rue Andre\u0301 Renard",
    "iso:country":"BE",
    "sg:address":"Rue Andr\u00c9 Renard 3b2",
    "sg:city":"Oupeye",
    "sg:orig_category":"Elektrische installaties voor woningen Informaticaconsulenten",
    "sg:phone":"+32 4 239 07 89",
    "sg:postcode":"4680",
    "sg:province":"Li\u00e8ge",
    "wof:name":"Service Partner",
    "wof:placetype":"venue"
},
  "geometry": {"coordinates":[5.6495079994,50.702747345],"type":"Point"}
}