{
  "type": "Feature",
  "properties": {
    "iso:country":"BE",
    "sg:address":"Gilliotstraat 60bg",
    "sg:city":"Hemiksem",
    "sg:orig_category":"Produits chimiques Gr",
    "sg:phone":"+32 3 877 22 33",
    "sg:postcode":"2620",
    "sg:province":"Antwerpen",
    "wof:name":"Proviron Industries",
    "wof:placetype":"venue"
},
  "geometry": {"coordinates":[4.3447341919,51.1450805664],"type":"Point"}
}