{
  "type": "Feature",
  "properties": {
    "addr:full":"Rijmenamseweg 180 Bonheiden Antwerpen 2820",
    "addr:housenumber":"180",
    "addr:postcode":"2820",
    "addr:street":"Rijmenamseweg",
    "iso:country":"BE",
    "sg:address":"Rijmenamseweg 180",
    "sg:city":"Bonheiden",
    "sg:classifiers":[
        {
            "category":"Bars & Pubs",
            "type":"Food & Drink"
        }
    ],
    "sg:phone":"+32 15 51 77 13",
    "sg:postcode":"2820",
    "sg:province":"Antwerpen",
    "sg:tags":[
        "tavern"
    ],
    "wof:name":"Tots (den)",
    "wof:placetype":"venue"
},
  "geometry": {"coordinates":[4.5751800537,51.0174942017],"type":"Point"}
}