{
  "type": "Feature",
  "properties": {
    "iso:country":"BE",
    "sg:address":"Kampagnestraat 4",
    "sg:city":"Balen",
    "sg:classifiers":[
        {
            "category":"Professional",
            "subcategory":"Art Services",
            "type":"Services"
        }
    ],
    "sg:phone":"+32 11 34 56 85",
    "sg:postcode":"2490",
    "sg:province":"Antwerpen",
    "sg:tags":[
        "interior",
        "designer"
    ],
    "wof:name":"Centaur Project-interieurs",
    "wof:placetype":"venue"
},
  "geometry": {"coordinates":[5.2548589706,51.1454162598],"type":"Point"}
}