{
  "type": "Feature",
  "properties": {
    "iso:country":"BE",
    "sg:address":"Ninoofsesteenweg 574",
    "sg:city":"Brussel",
    "sg:orig_category":"Epiceries",
    "sg:phone":"+32 2 521 70 63",
    "sg:postcode":"1070",
    "sg:province":"Bruxelles-Capitale",
    "wof:name":"Superette R\u00c9gine",
    "wof:placetype":"venue"
},
  "geometry": {"coordinates":[4.3035931587,50.8471908569],"type":"Point"}
}