{
  "type": "Feature",
  "properties": {
    "iso:country":"BE",
    "sg:address":"Dorpskring 3",
    "sg:city":"Lubbeek",
    "sg:orig_category":"M\u00e9decins and sp\u00e9cialistes",
    "sg:phone":"+32 16 63 21 90",
    "sg:postcode":"3210",
    "sg:province":"Vlaams-Brabant",
    "wof:name":"G. Vangilbergen",
    "wof:placetype":"venue"
},
  "geometry": {"coordinates":[4.8422498703,50.8806495667],"type":"Point"}
}