{
  "type": "Feature",
  "properties": {
    "addr:full":"Rue De Mons-lez-li\u00c8ge 290 Flemalle Li\u00e8ge 4400",
    "addr:housenumber":"290",
    "addr:postcode":"4400",
    "addr:street":"Rue De Mons-Lez-Lie\u0300Ge",
    "iso:country":"BE",
    "sg:address":"Rue De Mons-lez-li\u00c8ge 290",
    "sg:city":"Flemalle",
    "sg:classifiers":[
        {
            "category":"Insurance",
            "subcategory":"Insurance Agent",
            "type":"Services"
        }
    ],
    "sg:phone":"+32 4 231 35 32",
    "sg:postcode":"4400",
    "sg:province":"Li\u00e8ge",
    "sg:tags":[
        "verzekeringsmakelaars",
        "expert"
    ],
    "wof:name":"Bertrand Huskin",
    "wof:placetype":"venue"
},
  "geometry": {"coordinates":[5.4534039497,50.6216583252],"type":"Point"}
}