{
  "type": "Feature",
  "properties": {
    "iso:country":"BE",
    "sg:address":"Rue De Taillis Pr\u00e9 319",
    "sg:city":"Ch\u00e2telet (ch\u00e2telineau)",
    "sg:classifiers":[
        {
            "category":"Manufacturing",
            "subcategory":"Metals",
            "type":"Manufacturing & Wholesale Goods"
        }
    ],
    "sg:phone":"+32 71 39 45 81",
    "sg:postcode":"6200",
    "sg:province":"Hainaut",
    "sg:tags":[
        "ornamental",
        "work",
        "-"
    ],
    "wof:name":"Vermeulen P",
    "wof:placetype":"venue"
},
  "geometry": {"coordinates":[4.5123729706,50.4394569397],"type":"Point"}
}