{
  "type": "Feature",
  "properties": {
    "addr:full":"Rue De Glimes 1 Ramillies Brabant Wallon 1367",
    "addr:housenumber":"1",
    "addr:postcode":"1367",
    "addr:street":"Rue De Glimes",
    "iso:country":"BE",
    "sg:address":"Rue De Glimes 1",
    "sg:city":"Ramillies",
    "sg:orig_category":"Immobili\u00ebnkantoren",
    "sg:phone":"+32 10 81 36 78",
    "sg:postcode":"1367",
    "sg:province":"Brabant Wallon",
    "wof:name":"I.f.a.p.",
    "wof:placetype":"venue"
},
  "geometry": {"coordinates":[4.9146900177,50.636631012],"type":"Point"}
}