{
  "type": "Feature",
  "properties": {
    "iso:country":"BE",
    "sg:address":"Rue De Liberchies 248",
    "sg:city":"Tournai",
    "sg:classifiers":[
        {
            "category":"Wholesale",
            "subcategory":"Farm Supplies",
            "type":"Manufacturing & Wholesale Goods"
        }
    ],
    "sg:phone":"+32 69 54 65 57",
    "sg:postcode":"7532",
    "sg:province":"Hainaut",
    "sg:tags":[
        "machine",
        "agricoles",
        "mat\u00e9riel",
        "gr"
    ],
    "wof:name":"Bernard Moulin",
    "wof:placetype":"venue"
},
  "geometry": {"coordinates":[3.5248959064,50.6112670898],"type":"Point"}
}