{
  "type": "Feature",
  "properties": {
    "addr:full":"Vonderstraat 11 Nijlen Antwerpen 2560",
    "addr:housenumber":"11",
    "addr:postcode":"2560",
    "addr:street":"Vonderstraat",
    "iso:country":"BE",
    "sg:address":"Vonderstraat 11",
    "sg:city":"Nijlen",
    "sg:orig_category":"Elektrische installaties voor woningen",
    "sg:phone":"+32 3 481 98 41",
    "sg:postcode":"2560",
    "sg:province":"Antwerpen",
    "wof:name":"Evap-vanaken",
    "wof:placetype":"venue"
},
  "geometry": {"coordinates":[4.6889400482,51.1669540405],"type":"Point"}
}