{
  "type": "Feature",
  "properties": {
    "addr:full":"Rembertstraat 80 Zedelgem West-Vlaanderen 8210",
    "addr:housenumber":"80",
    "addr:postcode":"8210",
    "addr:street":"Rembertstraat",
    "iso:country":"BE",
    "sg:address":"Rembertstraat 80",
    "sg:city":"Zedelgem",
    "sg:orig_category":"Kapsalons",
    "sg:phone":"+32 50 28 16 26",
    "sg:postcode":"8210",
    "sg:province":"West-Vlaanderen",
    "wof:name":"Coiffure Trend",
    "wof:placetype":"venue"
},
  "geometry": {"coordinates":[3.1458399296,51.1376457214],"type":"Point"}
}