{
  "type": "Feature",
  "properties": {
    "addr:full":"Kerkstraat 60 Lochristi Oost-Vlaanderen 9080",
    "addr:housenumber":"60",
    "addr:postcode":"9080",
    "addr:street":"Kerkstraat",
    "iso:country":"BE",
    "sg:address":"Kerkstraat 60",
    "sg:city":"Lochristi",
    "sg:orig_category":"M\u00e9decins and sp\u00e9cialistes",
    "sg:phone":"+32 9 355 26 11",
    "sg:postcode":"9080",
    "sg:province":"Oost-Vlaanderen",
    "wof:name":"F. Mabilde",
    "wof:placetype":"venue"
},
  "geometry": {"coordinates":[3.865737915,51.1256217957],"type":"Point"}
}