{
  "type": "Feature",
  "properties": {
    "iso:country":"BE",
    "sg:address":"Avenue Montjoie 81",
    "sg:city":"Ukkel/uccle",
    "sg:orig_category":"R\u00e9alisation de programmes and logiciels",
    "sg:phone":"+32 2 347 32 62",
    "sg:postcode":"1180",
    "sg:province":"Bruxelles-Capitale",
    "wof:name":"Procolor - Espritweb",
    "wof:placetype":"venue"
},
  "geometry": {"coordinates":[4.3657708168,50.8103065491],"type":"Point"}
}