{
  "type": "Feature",
  "properties": {
    "iso:country":"BE",
    "sg:address":"Rue Le Corr\u00e8ge 93",
    "sg:city":"Bruxelles",
    "sg:classifiers":[
        {
            "category":"Professional",
            "subcategory":"Lawyer & Legal Services",
            "type":"Services"
        }
    ],
    "sg:phone":"+32 2 732 54 74",
    "sg:postcode":"1000",
    "sg:province":"Bruxelles-Capitale",
    "wof:name":"Iturriagagoitia J-r",
    "wof:placetype":"venue"
},
  "geometry": {"coordinates":[4.3878698349,50.8444099426],"type":"Point"}
}