{
  "type": "Feature",
  "properties": {
    "addr:full":"Retieseweg 122 Geel Antwerpen 2440",
    "addr:housenumber":"122",
    "addr:postcode":"2440",
    "addr:street":"Retieseweg",
    "iso:country":"BE",
    "sg:address":"Retieseweg 122",
    "sg:city":"Geel",
    "sg:classifiers":[
        {
            "category":"Farming",
            "subcategory":"Livestock Farm",
            "type":"Manufacturing & Wholesale Goods"
        }
    ],
    "sg:phone":"+32 14 58 71 71",
    "sg:postcode":"2440",
    "sg:province":"Antwerpen",
    "sg:tags":[
        "buyer"
    ],
    "wof:name":"Vanberghen A",
    "wof:placetype":"venue"
},
  "geometry": {"coordinates":[5.0301837921,51.1986351013],"type":"Point"}
}