{
  "type": "Feature",
  "properties": {
    "addr:full":"Rue Saint-pierre 27 Antoing Hainaut 7640",
    "addr:housenumber":"27",
    "addr:postcode":"7640",
    "addr:street":"Rue Saint-Pierre",
    "iso:country":"BE",
    "sg:address":"Rue Saint-pierre 27",
    "sg:city":"Antoing",
    "sg:orig_category":"Artiesten and kunstenaars",
    "sg:phone":"+32 69 44 11 08",
    "sg:postcode":"7640",
    "sg:province":"Hainaut",
    "wof:name":"Georges Leclercq",
    "wof:placetype":"venue"
},
  "geometry": {"coordinates":[3.4478299618,50.5623855591],"type":"Point"}
}