{
  "type": "Feature",
  "properties": {
    "iso:country":"BE",
    "sg:address":"Rue De Clavia 10",
    "sg:city":"Ciney (sovet)",
    "sg:classifiers":[
        {
            "category":"Health Services",
            "subcategory":"Doctor",
            "type":"Services"
        }
    ],
    "sg:phone":"+32 83 21 41 26",
    "sg:postcode":"5590",
    "sg:province":"Namur",
    "sg:tags":[
        "medicinephysicians",
        "surgeon"
    ],
    "wof:name":"Ferri\u00e8re Gerard",
    "wof:placetype":"venue"
},
  "geometry": {"coordinates":[5.1022520065,50.297088623],"type":"Point"}
}