{
  "type": "Feature",
  "properties": {
    "iso:country":"BE",
    "sg:address":"Luikersteenweg 158",
    "sg:city":"Tongeren",
    "sg:orig_category":"Herstellingen and onderhoud van auto's",
    "sg:phone":"+32 12 23 03 73",
    "sg:postcode":"3700",
    "sg:province":"Limburg",
    "wof:name":"Garage Smeysters",
    "wof:placetype":"venue"
},
  "geometry": {"coordinates":[5.4652490616,50.7692565918],"type":"Point"}
}