{
  "type": "Feature",
  "properties": {
    "iso:country":"BE",
    "sg:address":"Rue De L'hospice 7a",
    "sg:city":"Jemeppe-sur-sambre (spy)",
    "sg:classifiers":[
        {
            "category":"Building & Trades",
            "subcategory":"Electrical",
            "type":"Services"
        }
    ],
    "sg:phone":"+32 71 78 14 78",
    "sg:postcode":"5190",
    "sg:province":"Namur",
    "sg:tags":[
        "electric",
        "-",
        "housewiring",
        "contractor"
    ],
    "wof:name":"Morelec",
    "wof:placetype":"venue"
},
  "geometry": {"coordinates":[4.7019519806,50.4832496643],"type":"Point"}
}