{
  "type": "Feature",
  "properties": {
    "iso:country":"BE",
    "sg:address":"Wouwendonkstraat 87",
    "sg:city":"Duffel",
    "sg:classifiers":[
        {
            "category":"Real Estate",
            "subcategory":"Architect",
            "type":"Services"
        }
    ],
    "sg:phone":"+32 15 32 24 64",
    "sg:postcode":"2570",
    "sg:province":"Antwerpen",
    "wof:name":"Vervaele B",
    "wof:placetype":"venue"
},
  "geometry": {"coordinates":[4.4988059998,51.0979270935],"type":"Point"}
}