{
  "type": "Feature",
  "properties": {
    "iso:country":"BE",
    "sg:address":"Noordzandstraat 53",
    "sg:city":"Brugge",
    "sg:orig_category":"Pharmaciens",
    "sg:phone":"+32 50 33 28 91",
    "sg:postcode":"8000",
    "sg:province":"West-Vlaanderen",
    "wof:name":"Apotheek Priem",
    "wof:placetype":"venue"
},
  "geometry": {"coordinates":[3.2200539112,51.2071533203],"type":"Point"}
}