{
  "type": "Feature",
  "properties": {
    "iso:country":"BE",
    "sg:address":"Avenue Des Martyrs 206",
    "sg:city":"Fl\u00c9ron",
    "sg:classifiers":[
        {
            "category":"Fast Food",
            "type":"Food & Drink"
        }
    ],
    "sg:phone":"+32 4 358 03 00",
    "sg:postcode":"4620",
    "sg:province":"Li\u00e8ge",
    "sg:tags":[
        "\u00c0",
        "emporter",
        "restaurants"
    ],
    "wof:name":"La Maison D\u00b4antalya",
    "wof:placetype":"venue"
},
  "geometry": {"coordinates":[5.6803731918,50.6144943237],"type":"Point"}
}