{
  "type": "Feature",
  "properties": {
    "addr:full":"Rue De Soudromont 2 Manage Hainaut 7170",
    "addr:housenumber":"2",
    "addr:postcode":"7170",
    "addr:street":"Rue De Soudromont",
    "iso:country":"BE",
    "sg:address":"Rue De Soudromont 2",
    "sg:city":"Manage",
    "sg:orig_category":"Enseignement maternel and primaire",
    "sg:phone":"+32 64 54 97 32",
    "sg:postcode":"7170",
    "sg:province":"Hainaut",
    "wof:name":"Ecole Fondamentale Libre",
    "wof:placetype":"venue"
},
  "geometry": {"coordinates":[4.2581372261,50.4982337952],"type":"Point"}
}