{
  "type": "Feature",
  "properties": {
    "iso:country":"BE",
    "sg:address":"Bunderstraat 3",
    "sg:city":"Roeselare",
    "sg:classifiers":[
        {
            "category":"Travel",
            "subcategory":"Hotels & Motels",
            "type":"Entertainment"
        }
    ],
    "sg:phone":"+32 51 22 96 84",
    "sg:postcode":"8800",
    "sg:province":"West-Vlaanderen",
    "wof:name":"Grovak",
    "wof:placetype":"venue"
},
  "geometry": {"coordinates":[3.1055269241,50.9311637878],"type":"Point"}
}