{
  "type": "Feature",
  "properties": {
    "iso:country":"BE",
    "sg:address":"Invalidenstraat 71",
    "sg:city":"Brugge (sint-kruis)",
    "sg:classifiers":[
        {
            "category":"Retail",
            "subcategory":"Animal Services",
            "type":"Services"
        }
    ],
    "sg:phone":"+32 50 35 95 19",
    "sg:postcode":"8310",
    "sg:province":"West-Vlaanderen",
    "sg:tags":[
        "farrier"
    ],
    "wof:name":"Degrijse D",
    "wof:placetype":"venue"
},
  "geometry": {"coordinates":[3.24928689,51.2079658508],"type":"Point"}
}