{
  "type": "Feature",
  "properties": {
    "iso:country":"BE",
    "sg:address":"Rue Devant La Ville 35",
    "sg:city":"Oupeye",
    "sg:orig_category":"Gespecialiseerde niet-residenti\u00eble bouw",
    "sg:phone":"+32 4 278 55 22",
    "sg:postcode":"4680",
    "sg:province":"Li\u00e8ge",
    "wof:name":"Metamil",
    "wof:placetype":"venue"
},
  "geometry": {"coordinates":[5.6444120407,50.7089729309],"type":"Point"}
}