{
  "type": "Feature",
  "properties": {
    "addr:full":"Victor Van Sandelaan 17 Wetteren Oost-Vlaanderen 9230",
    "addr:housenumber":"17",
    "addr:postcode":"9230",
    "addr:street":"Victor Van Sandelaan",
    "iso:country":"BE",
    "sg:address":"Victor Van Sandelaan 17",
    "sg:city":"Wetteren",
    "sg:classifiers":[
        {
            "category":"Real Estate",
            "subcategory":"Architect",
            "type":"Services"
        }
    ],
    "sg:phone":"+32 9 369 04 91",
    "sg:postcode":"9230",
    "sg:province":"Oost-Vlaanderen",
    "wof:name":"Baudewijn A",
    "wof:placetype":"venue"
},
  "geometry": {"coordinates":[3.8866930008,51.0020256042],"type":"Point"}
}