{
  "type": "Feature",
  "properties": {
    "iso:country":"BE",
    "sg:address":"Bruggestraat 14",
    "sg:city":"Ruiselede",
    "sg:classifiers":[
        {
            "category":"Shopping",
            "subcategory":"Music",
            "type":"Retail Goods"
        }
    ],
    "sg:phone":"+32 51 68 80 67",
    "sg:postcode":"8755",
    "sg:province":"West-Vlaanderen",
    "sg:tags":[
        "-",
        "cd's",
        "recorded",
        "cassette"
    ],
    "wof:name":"Banana Peel Records Cv",
    "wof:placetype":"venue"
},
  "geometry": {"coordinates":[3.3957459927,51.0419998169],"type":"Point"}
}