{
  "type": "Feature",
  "properties": {
    "addr:full":"Rue De La Grotte 14 Namur (suarl\u00e9e) Namur 5020",
    "addr:housenumber":"14",
    "addr:postcode":"5020",
    "addr:street":"Rue De La Grotte",
    "iso:country":"BE",
    "sg:address":"Rue De La Grotte 14",
    "sg:city":"Namur (suarl\u00e9e)",
    "sg:classifiers":[
        {
            "category":"Freight",
            "type":"Transportation"
        }
    ],
    "sg:phone":"+32 81 56 73 57",
    "sg:postcode":"5020",
    "sg:province":"Namur",
    "sg:tags":[
        "-",
        "transport"
    ],
    "wof:name":"Massart Transport Sprl",
    "wof:placetype":"venue"
},
  "geometry": {"coordinates":[4.7952418327,50.4352035522],"type":"Point"}
}