{
  "type": "Feature",
  "properties": {
    "addr:full":"Chauss\u00c9e De Gembloux 64 Sombreffe Namur 5140",
    "addr:housenumber":"64",
    "addr:postcode":"5140",
    "addr:street":"Chausse\u0301E De Gembloux",
    "iso:country":"BE",
    "sg:address":"Chauss\u00c9e De Gembloux 64",
    "sg:city":"Sombreffe",
    "sg:classifiers":[
        {
            "category":"Restaurant",
            "type":"Food & Drink"
        }
    ],
    "sg:phone":"+32 71 88 54 74",
    "sg:postcode":"5140",
    "sg:province":"Namur",
    "wof:name":"La Ferme D\u00b4abondance",
    "wof:placetype":"venue"
},
  "geometry": {"coordinates":[4.6290841103,50.5295639038],"type":"Point"}
}