{
  "type": "Feature",
  "properties": {
    "addr:full":"Rue De L'escasse 71 Charleroi (gosselies) Hainaut 6041",
    "addr:housenumber":"71",
    "addr:postcode":"6041",
    "addr:street":"Rue De L'Escasse",
    "iso:country":"BE",
    "sg:address":"Rue De L'escasse 71",
    "sg:city":"Charleroi (gosselies)",
    "sg:classifiers":[
        {
            "category":"Retail",
            "subcategory":"Animal Services",
            "type":"Services"
        }
    ],
    "sg:phone":"+32 71 35 95 37",
    "sg:postcode":"6041",
    "sg:province":"Hainaut",
    "sg:tags":[
        "grooming",
        "-",
        "dog"
    ],
    "wof:name":"Alexandre C",
    "wof:placetype":"venue"
},
  "geometry": {"coordinates":[4.4450640678,50.469959259],"type":"Point"}
}