{
  "type": "Feature",
  "properties": {
    "iso:country":"BE",
    "sg:address":"Quai Des Anglais 2",
    "sg:city":"Mons (nimy)",
    "sg:orig_category":"Non-Classified Establishments",
    "sg:phone":"+32 65 35 36 52",
    "sg:postcode":"7020",
    "sg:province":"Hainaut",
    "wof:name":"Fontaine",
    "wof:placetype":"venue"
},
  "geometry": {"coordinates":[3.9553449154,50.4761772156],"type":"Point"}
}