{
  "type": "Feature",
  "properties": {
    "iso:country":"BE",
    "sg:address":"Vinkendal 44",
    "sg:city":"Gent",
    "sg:orig_category":"Instituts de beaut\u00e9",
    "sg:phone":"+32 9 226 16 03",
    "sg:postcode":"9031",
    "sg:province":"Oost-Vlaanderen",
    "wof:name":"Aline Deschryver",
    "wof:placetype":"venue"
},
  "geometry": {"coordinates":[3.6386899948,51.0621604919],"type":"Point"}
}