{
  "type": "Feature",
  "properties": {
    "iso:country":"BE",
    "sg:address":"Hundelgemsesteenweg 235",
    "sg:city":"Ledeberg",
    "sg:orig_category":"Travaux de finition and nettoyage de b\u00e2timents. Construction de maisons. Collecte and \u00e9puration des ",
    "sg:phone":"+32 50 34 22 79",
    "sg:postcode":"9050",
    "sg:province":"Oost-Vlaanderen",
    "wof:name":"Ultra Moderne Ontstoppingsdienst",
    "wof:placetype":"venue"
},
  "geometry": {"coordinates":[3.743491888,51.0317115784],"type":"Point"}
}