{
  "type": "Feature",
  "properties": {
    "addr:full":"Avenue Leburton 146 Waremme Li\u00e8ge 4300",
    "addr:housenumber":"146",
    "addr:postcode":"4300",
    "addr:street":"Avenue Leburton",
    "iso:country":"BE",
    "sg:address":"Avenue Leburton 146",
    "sg:city":"Waremme",
    "sg:classifiers":[
        {
            "category":"Manufacturing",
            "subcategory":"Rubber & Plastics",
            "type":"Manufacturing & Wholesale Goods"
        }
    ],
    "sg:phone":"+32 19 32 59 73",
    "sg:postcode":"4300",
    "sg:province":"Li\u00e8ge",
    "sg:tags":[
        "part",
        "industrial",
        "made"
    ],
    "wof:name":"Sobelco Impex S.p.r.l.",
    "wof:placetype":"venue"
},
  "geometry": {"coordinates":[5.2678041458,50.699092865],"type":"Point"}
}