{
  "type": "Feature",
  "properties": {
    "iso:country":"BE",
    "sg:address":"Grote Baan 101",
    "sg:city":"Lovendegem",
    "sg:orig_category":"Herstellingen and onderhoud van auto's Voertuigen",
    "sg:phone":"+32 9 372 01 13",
    "sg:postcode":"9920",
    "sg:province":"Oost-Vlaanderen",
    "wof:name":"Garage Ryco Cars",
    "wof:placetype":"venue"
},
  "geometry": {"coordinates":[3.6325550079,51.1016273499],"type":"Point"}
}