{
  "type": "Feature",
  "properties": {
    "addr:full":"Moerstraat 27 Sint-laureins Oost-Vlaanderen 9982",
    "addr:housenumber":"27",
    "addr:postcode":"9982",
    "addr:street":"Moerstraat",
    "iso:country":"BE",
    "sg:address":"Moerstraat 27",
    "sg:city":"Sint-laureins",
    "sg:orig_category":"Rundveehouders Varkenskwekers",
    "sg:phone":"+32 9 379 89 59",
    "sg:postcode":"9982",
    "sg:province":"Oost-Vlaanderen",
    "wof:name":"Van Damme Gabriel & Geert",
    "wof:placetype":"venue"
},
  "geometry": {"coordinates":[3.5981318951,51.2426261902],"type":"Point"}
}