{
  "type": "Feature",
  "properties": {
    "addr:full":"Rue De La Cambre 180-184 Bruxelles (woluwe-saint-lambert) Bruxelles-Capitale 1200",
    "addr:postcode":"180-184;1200",
    "addr:street":"Rue De La Cambre",
    "iso:country":"BE",
    "sg:address":"Rue De La Cambre 180-184",
    "sg:city":"Bruxelles (woluwe-saint-lambert)",
    "sg:classifiers":[
        {
            "category":"Autos & Motor Vehicles",
            "subcategory":"Automobile Sales",
            "type":"Retail Goods"
        }
    ],
    "sg:phone":"+32 2 762 34 84",
    "sg:postcode":"1200",
    "sg:province":"Bruxelles-Capitale",
    "sg:tags":[
        "car",
        "used",
        "-"
    ],
    "wof:name":"Damseaux Pierre Sa",
    "wof:placetype":"venue"
},
  "geometry": {"coordinates":[4.4169101715,50.8386001587],"type":"Point"}
}