{
  "type": "Feature",
  "properties": {
    "iso:country":"BE",
    "sg:address":"Niemandshoek 52",
    "sg:city":"Vorselaar",
    "sg:orig_category":"Transports routiers de marchandises",
    "sg:phone":"+32 14 51 24 51",
    "sg:postcode":"2290",
    "sg:province":"Antwerpen",
    "wof:name":"Wovetrans",
    "wof:placetype":"venue"
},
  "geometry": {"coordinates":[4.7596502304,51.2161216736],"type":"Point"}
}