{
  "type": "Feature",
  "properties": {
    "iso:country":"BE",
    "sg:address":"Rue De La Vall\u00c9e 40",
    "sg:city":"Elsene/ixelles",
    "sg:orig_category":"R\u00e9paration and restauration de meubles",
    "sg:phone":"+32 2 640 10 30",
    "sg:postcode":"1050",
    "sg:province":"Bruxelles-Capitale",
    "wof:name":"Thierry De Borman",
    "wof:placetype":"venue"
},
  "geometry": {"coordinates":[4.3710899353,50.8249092102],"type":"Point"}
}