{
  "type": "Feature",
  "properties": {
    "addr:full":"Diestseweg 28 Geel Antwerpen 2440",
    "addr:housenumber":"28",
    "addr:postcode":"2440",
    "addr:street":"Diestseweg",
    "iso:country":"BE",
    "sg:address":"Diestseweg 28",
    "sg:city":"Geel",
    "sg:orig_category":"Etablissements Erotiques",
    "sg:phone":"+32 14 58 95 78",
    "sg:postcode":"2440",
    "sg:province":"Antwerpen",
    "wof:name":"Euro-disc",
    "wof:placetype":"venue"
},
  "geometry": {"coordinates":[4.9920520782,51.1599884033],"type":"Point"}
}