{
  "type": "Feature",
  "properties": {
    "iso:country":"BE",
    "sg:address":"Rue Elveau 31",
    "sg:city":"Sombreffe",
    "sg:orig_category":"Woningbouw",
    "sg:phone":"+32 71 88 77 82",
    "sg:postcode":"5140",
    "sg:province":"Namur",
    "wof:name":"L'abbate Vito",
    "wof:placetype":"venue"
},
  "geometry": {"coordinates":[4.5913920403,50.5293731689],"type":"Point"}
}