{
  "type": "Feature",
  "properties": {
    "iso:country":"BE",
    "sg:address":"Mechelsesteenweg 244",
    "sg:city":"Vilvoorde",
    "sg:classifiers":[
        {
            "category":"Professional",
            "subcategory":"Detective & Security Services",
            "type":"Services"
        }
    ],
    "sg:phone":"+32 2 253 13 37",
    "sg:postcode":"1800",
    "sg:province":"Vlaams-Brabant",
    "sg:tags":[
        "-",
        "system",
        "apparatus",
        "surveillance"
    ],
    "wof:name":"Cnc Benelux Bvba",
    "wof:placetype":"venue"
},
  "geometry": {"coordinates":[4.4287090302,50.9355773926],"type":"Point"}
}