{
  "type": "Feature",
  "properties": {
    "addr:full":"Hoveniersstraat 31 Kortrijk West-Vlaanderen 8500",
    "addr:housenumber":"31",
    "addr:postcode":"8500",
    "addr:street":"Hoveniersstraat",
    "iso:country":"BE",
    "sg:address":"Hoveniersstraat 31",
    "sg:city":"Kortrijk",
    "sg:orig_category":"Overheidsdiensten",
    "sg:phone":"+32 56 26 49 71",
    "sg:postcode":"8500",
    "sg:province":"West-Vlaanderen",
    "wof:name":"Admin. Directe Belast.",
    "wof:placetype":"venue"
},
  "geometry": {"coordinates":[3.2646479607,50.8221969604],"type":"Point"}
}