{
  "type": "Feature",
  "properties": {
    "iso:country":"BE",
    "sg:address":"Coenraedt Keynslaan 31b1",
    "sg:city":"Herent",
    "sg:classifiers":[
        {
            "category":"Personal",
            "subcategory":"Beauty Salon",
            "type":"Services"
        }
    ],
    "sg:phone":"+32 16 23 24 14",
    "sg:postcode":"3020",
    "sg:province":"Vlaams-Brabant",
    "sg:tags":[
        "de",
        "coiffure"
    ],
    "wof:name":"Marc Verhelst",
    "wof:placetype":"venue"
},
  "geometry": {"coordinates":[4.6611337662,50.8854179382],"type":"Point"}
}