{
  "type": "Feature",
  "properties": {
    "iso:country":"BE",
    "sg:address":"Markt 11",
    "sg:city":"Kruishoutem",
    "sg:classifiers":[
        {
            "category":"Shopping",
            "subcategory":"Jewelry",
            "type":"Retail Goods"
        }
    ],
    "sg:phone":"+32 9 383 57 28",
    "sg:postcode":"9770",
    "sg:province":"Oost-Vlaanderen",
    "sg:tags":[
        "jeweller",
        "-"
    ],
    "wof:name":"Dumoulin Vof",
    "wof:placetype":"venue"
},
  "geometry": {"coordinates":[3.5280380249,50.9042739868],"type":"Point"}
}