{
  "type": "Feature",
  "properties": {
    "iso:country":"BE",
    "sg:address":"Avenue Maurice Destenay 13",
    "sg:city":"Li\u00e8ge 1",
    "sg:classifiers":[
        {
            "category":"Banks & Credit Unions",
            "subcategory":"Investment Brokerage",
            "type":"Services"
        }
    ],
    "sg:phone":"+32 4 221 99 63",
    "sg:postcode":"4000",
    "sg:province":"Li\u00e8ge",
    "wof:name":"Sowalfin-(soci\u00e9t\u00e9 Wallonne De Financement Et De Garantie Des P.m.e.)",
    "wof:placetype":"venue"
},
  "geometry": {"coordinates":[5.5691590309,50.6379890442],"type":"Point"}
}