{
  "type": "Feature",
  "properties": {
    "iso:country":"BE",
    "sg:address":"Grand-rue 130",
    "sg:city":"Tintigny",
    "sg:orig_category":"V\u00e9t\u00e9rinaires",
    "sg:phone":"+32 63 44 48 77",
    "sg:postcode":"6730",
    "sg:province":"Luxembourg",
    "wof:name":"Andre Maitrejean",
    "wof:placetype":"venue"
},
  "geometry": {"coordinates":[5.5028948784,49.6858978271],"type":"Point"}
}