{
  "type": "Feature",
  "properties": {
    "addr:full":"Stationsstraat 95 Brussel/bruxelles Bruxelles-Capitale 1200",
    "addr:housenumber":"95",
    "addr:postcode":"1200",
    "addr:street":"Stationsstraat;/",
    "iso:country":"BE",
    "sg:address":"Stationsstraat 95",
    "sg:city":"Brussel/bruxelles",
    "sg:classifiers":[
        {
            "category":"Restaurant",
            "type":"Food & Drink"
        }
    ],
    "sg:phone":"+32 2 762 74 70",
    "sg:postcode":"1200",
    "sg:province":"Bruxelles-Capitale",
    "wof:name":"Caf\u00c9 De La Gare",
    "wof:placetype":"venue"
},
  "geometry": {"coordinates":[4.4381041527,50.8367233276],"type":"Point"}
}