{
  "type": "Feature",
  "properties": {
    "iso:country":"BE",
    "sg:address":"Boulevard Chapman 1",
    "sg:city":"Spa",
    "sg:orig_category":"G\u00e9om\u00e8tres",
    "sg:phone":"+32 87 77 11 91",
    "sg:postcode":"4900",
    "sg:province":"Li\u00e8ge",
    "wof:name":"Henri Donneaux",
    "wof:placetype":"venue"
},
  "geometry": {"coordinates":[5.8670611382,50.4889526367],"type":"Point"}
}