{
  "type": "Feature",
  "properties": {
    "iso:country":"BE",
    "sg:address":"Sint-maartenskerkhof 5ba",
    "sg:city":"Kortrijk",
    "sg:orig_category":"Traitements param\u00e9dicaux",
    "sg:phone":"+32 56 22 99 19",
    "sg:postcode":"8500",
    "sg:province":"West-Vlaanderen",
    "wof:name":"Ann Debrouwere",
    "wof:placetype":"venue"
},
  "geometry": {"coordinates":[3.2673809528,50.8275184631],"type":"Point"}
}