{
  "type": "Feature",
  "properties": {
    "addr:full":"Erasmuln 30 Cargovil-brussel 1804",
    "addr:housenumber":"30",
    "addr:postcode":"1804",
    "addr:street":"Erasmuln",
    "iso:country":"BE",
    "sg:address":"Erasmuln 30",
    "sg:city":"Cargovil-brussel",
    "sg:classifiers":[
        {
            "category":"Professional",
            "type":"Services"
        }
    ],
    "sg:phone":"+32 2 721 40 40",
    "sg:postcode":"1804",
    "sg:tags":[
        "transport",
        "road"
    ],
    "wof:name":"Putters International Nv",
    "wof:placetype":"venue"
},
  "geometry": {"coordinates":[4.4343738556,50.9463691711],"type":"Point"}
}