{
  "type": "Feature",
  "properties": {
    "iso:country":"BE",
    "sg:address":"Vierwindenstraat 0",
    "sg:city":"Geraardsbergen",
    "sg:orig_category":"Services pour animaux domestiques",
    "sg:phone":"+32 54 42 23 67",
    "sg:postcode":"9500",
    "sg:province":"Oost-Vlaanderen",
    "wof:name":"Herleving Geraardsbergen",
    "wof:placetype":"venue"
},
  "geometry": {"coordinates":[3.8890430927,50.7678222656],"type":"Point"}
}