{
  "type": "Feature",
  "properties": {
    "addr:full":"Avenue De La Renaissance 1 Bruxelles Bruxelles-Capitale 1000",
    "addr:housenumber":"1",
    "addr:postcode":"1000",
    "addr:street":"Avenue De La Renaissance",
    "iso:country":"BE",
    "sg:address":"Avenue De La Renaissance 1",
    "sg:city":"Bruxelles",
    "sg:classifiers":[
        {
            "category":"Professional",
            "subcategory":"Accounting & Tax Preparation",
            "type":"Services"
        }
    ],
    "sg:phone":"+32 2 736 67 35",
    "sg:postcode":"1000",
    "sg:province":"Bruxelles-Capitale",
    "sg:tags":[
        "bookkeeper"
    ],
    "wof:name":"Grupp W",
    "wof:placetype":"venue"
},
  "geometry": {"coordinates":[4.3879098892,50.8439903259],"type":"Point"}
}