{
  "type": "Feature",
  "properties": {
    "iso:country":"BE",
    "sg:address":"Vichteplaats 34",
    "sg:city":"Anzegem (vichte)",
    "sg:classifiers":[
        {
            "category":"Bars & Pubs",
            "type":"Food & Drink"
        }
    ],
    "sg:phone":"+32 56 77 99 39",
    "sg:postcode":"8570",
    "sg:province":"West-Vlaanderen",
    "wof:name":"Breughel",
    "wof:placetype":"venue"
},
  "geometry": {"coordinates":[3.403439045,50.8357925415],"type":"Point"}
}