{
  "type": "Feature",
  "properties": {
    "iso:country":"BE",
    "sg:address":"Hogestraat 38",
    "sg:city":"Izegem (kachtem)",
    "sg:classifiers":[
        {
            "category":"Personal",
            "subcategory":"Beauty Salon",
            "type":"Services"
        }
    ],
    "sg:phone":"+32 51 31 86 77",
    "sg:postcode":"8870",
    "sg:province":"West-Vlaanderen",
    "sg:tags":[
        "lady",
        "-",
        "hairdressing"
    ],
    "wof:name":"Jeannick",
    "wof:placetype":"venue"
},
  "geometry": {"coordinates":[3.1894130707,50.9350700378],"type":"Point"}
}