{
  "type": "Feature",
  "properties": {
    "iso:country":"BE",
    "sg:address":"Avenue D\u00c9mosth\u00c8ne Poplimont 70b1",
    "sg:city":"Jette/jette",
    "sg:orig_category":"Bijoux Fab. Bijouteries and horlogeries",
    "sg:phone":"+32 2 428 64 72",
    "sg:postcode":"1090",
    "sg:province":"Bruxelles-Capitale",
    "wof:name":"Maison Wildior",
    "wof:placetype":"venue"
},
  "geometry": {"coordinates":[4.3210229874,50.8720016479],"type":"Point"}
}