{
  "type": "Feature",
  "properties": {
    "iso:country":"BE",
    "sg:address":"Anneessensstraat 11a",
    "sg:city":"Antwerpen",
    "sg:classifiers":[
        {
            "category":"Bars & Pubs",
            "type":"Food & Drink"
        }
    ],
    "sg:phone":"+32 3 232 19 36",
    "sg:postcode":"2018",
    "sg:province":"Antwerpen",
    "wof:name":"New Way",
    "wof:placetype":"venue"
},
  "geometry": {"coordinates":[4.4183301926,51.2186203003],"type":"Point"}
}