{
  "type": "Feature",
  "properties": {
    "iso:country":"BE",
    "sg:address":"Hoevensebaan 94",
    "sg:city":"Kapellen",
    "sg:orig_category":"Industri\u00eble wasserijen and droogkuis",
    "sg:phone":"+32 3 664 26 45",
    "sg:postcode":"2950",
    "sg:province":"Antwerpen",
    "wof:name":"Gomoli",
    "wof:placetype":"venue"
},
  "geometry": {"coordinates":[4.4245691299,51.3132743835],"type":"Point"}
}