{
  "type": "Feature",
  "properties": {
    "addr:full":"Rue T Sterstevens 66 Thuin Hainaut 6530",
    "addr:housenumber":"66",
    "addr:postcode":"6530",
    "addr:street":"Rue T Sterstevens",
    "iso:country":"BE",
    "sg:address":"Rue T Sterstevens 66",
    "sg:city":"Thuin",
    "sg:orig_category":"Textiel",
    "sg:phone":"+32 71 59 54 66",
    "sg:postcode":"6530",
    "sg:province":"Hainaut",
    "wof:name":"Phildar",
    "wof:placetype":"venue"
},
  "geometry": {"coordinates":[4.2859711647,50.3395843506],"type":"Point"}
}