{
  "type": "Feature",
  "properties": {
    "iso:country":"BE",
    "sg:address":"Rue De La Brasserie 12",
    "sg:city":"Brunehaut",
    "sg:classifiers":[
        {
            "category":"Cafe",
            "type":"Food & Drink"
        }
    ],
    "sg:phone":"+32 69 64 85 67",
    "sg:postcode":"7620",
    "sg:province":"Hainaut",
    "sg:tags":[
        "caf\u00e9s"
    ],
    "wof:name":"Caf\u00c9 Desombre",
    "wof:placetype":"venue"
},
  "geometry": {"coordinates":[3.3725280762,50.5482063293],"type":"Point"}
}