{
  "type": "Feature",
  "properties": {
    "addr:full":"Pieter Coeckestraat 4 Aalst Oost-Vlaanderen 9300",
    "addr:housenumber":"4",
    "addr:postcode":"9300",
    "addr:street":"Pieter Coeckestraat",
    "iso:country":"BE",
    "sg:address":"Pieter Coeckestraat 4",
    "sg:city":"Aalst",
    "sg:orig_category":"Epiceries. Fruits and l\u00e9gumes",
    "sg:phone":"+32 53 78 79 16",
    "sg:postcode":"9300",
    "sg:province":"Oost-Vlaanderen",
    "wof:name":"De Fruithoek",
    "wof:placetype":"venue"
},
  "geometry": {"coordinates":[4.0346579552,50.942527771],"type":"Point"}
}