{
  "type": "Feature",
  "properties": {
    "addr:full":"Route De Trois-ponts 36 Stavelot Li\u00e8ge 4970",
    "addr:housenumber":"36",
    "addr:postcode":"4970",
    "addr:street":"Route De Trois-Ponts",
    "iso:country":"BE",
    "sg:address":"Route De Trois-ponts 36",
    "sg:city":"Stavelot",
    "sg:orig_category":"Epiceries",
    "sg:phone":"+32 80 86 27 89",
    "sg:postcode":"4970",
    "sg:province":"Li\u00e8ge",
    "wof:name":"Joelle Louys",
    "wof:placetype":"venue"
},
  "geometry": {"coordinates":[5.9110507965,50.3846244812],"type":"Point"}
}