{
  "type": "Feature",
  "properties": {
    "iso:country":"BE",
    "sg:address":"Rue Heyvaert 138",
    "sg:city":"Sint-jans-molenbeek/molenbeek-saint-jean",
    "sg:orig_category":"V\u00e9hicules automobiles",
    "sg:phone":"+32 2 521 92 19",
    "sg:postcode":"1080",
    "sg:province":"Bruxelles-Capitale",
    "wof:name":"Garage Fadi Export",
    "wof:placetype":"venue"
},
  "geometry": {"coordinates":[4.3302989006,50.8456382751],"type":"Point"}
}