{
  "type": "Feature",
  "properties": {
    "addr:full":"Wetstraat 81a Meise Vlaams-Brabant 1860",
    "addr:housenumber":"81a",
    "addr:postcode":"1860",
    "addr:street":"Wetstraat",
    "iso:country":"BE",
    "sg:address":"Wetstraat 81a",
    "sg:city":"Meise",
    "sg:orig_category":"Boekenuitgeverijen Werk and personeelsselectie",
    "sg:phone":"+32 2 269 80 09",
    "sg:postcode":"1860",
    "sg:province":"Vlaams-Brabant",
    "wof:name":"Human Management Advice",
    "wof:placetype":"venue"
},
  "geometry": {"coordinates":[4.3299398422,50.9351844788],"type":"Point"}
}