{
  "type": "Feature",
  "properties": {
    "iso:country":"BE",
    "sg:address":"Rue Saint Quentin 36",
    "sg:city":"Brussel/bruxelles",
    "sg:orig_category":"Herstellingen and onderhoud van auto's",
    "sg:phone":"+32 2 230 65 02",
    "sg:postcode":"1000",
    "sg:province":"Bruxelles-Capitale",
    "wof:name":"Garage Saint-quentin",
    "wof:placetype":"venue"
},
  "geometry": {"coordinates":[4.3809242249,50.8453330994],"type":"Point"}
}