{
  "type": "Feature",
  "properties": {
    "addr:full":"Kleine Pieter Potstraat 21 Antwerpen Antwerpen 2000",
    "addr:housenumber":"21",
    "addr:postcode":"2000",
    "addr:street":"Kleine Pieter Potstraat",
    "iso:country":"BE",
    "sg:address":"Kleine Pieter Potstraat 21",
    "sg:city":"Antwerpen",
    "sg:classifiers":[
        {
            "category":"Real Estate",
            "subcategory":"Architect",
            "type":"Services"
        }
    ],
    "sg:phone":"+32 3 225 26 40",
    "sg:postcode":"2000",
    "sg:province":"Antwerpen",
    "wof:name":"Architectenbur Steenmeijer & Baksteen",
    "wof:placetype":"venue"
},
  "geometry": {"coordinates":[4.3983831406,51.2201004028],"type":"Point"}
}