{
  "type": "Feature",
  "properties": {
    "iso:country":"BE",
    "sg:address":"Rue Pige Au Croly 146",
    "sg:city":"Charleroi",
    "sg:classifiers":[
        {
            "category":"Professional",
            "subcategory":"Testing Lab",
            "type":"Services"
        }
    ],
    "sg:phone":"+32 71 31 29 32",
    "sg:postcode":"6000",
    "sg:province":"Hainaut",
    "sg:tags":[
        "chemist"
    ],
    "wof:name":"Godfraind C",
    "wof:placetype":"venue"
},
  "geometry": {"coordinates":[4.4459261894,50.4210357666],"type":"Point"}
}