{
  "type": "Feature",
  "properties": {
    "addr:full":"Hofstraat 37 Sint-niklaas Oost-Vlaanderen 9100",
    "addr:housenumber":"37",
    "addr:postcode":"9100",
    "addr:street":"Hofstraat",
    "iso:country":"BE",
    "sg:address":"Hofstraat 37",
    "sg:city":"Sint-niklaas",
    "sg:orig_category":"Non-Classified Establishments",
    "sg:phone":"+32 3 776 16 21",
    "sg:postcode":"9100",
    "sg:province":"Oost-Vlaanderen",
    "wof:name":"De Wael A",
    "wof:placetype":"venue"
},
  "geometry": {"coordinates":[4.138628006,51.1686553955],"type":"Point"}
}