{
  "type": "Feature",
  "properties": {
    "iso:country":"BE",
    "sg:address":"Hoogstraat 33",
    "sg:city":"Meise",
    "sg:orig_category":"Pain, p\u00e2tisseries and confiseries",
    "sg:phone":"+32 2 269 19 63",
    "sg:postcode":"1861",
    "sg:province":"Vlaams-Brabant",
    "wof:name":"Luc Pauwels",
    "wof:placetype":"venue"
},
  "geometry": {"coordinates":[4.3108701706,50.9522819519],"type":"Point"}
}