{
  "type": "Feature",
  "properties": {
    "iso:country":"BE",
    "sg:address":"Amelbergastraat 45",
    "sg:city":"Zandhoven",
    "sg:classifiers":[
        {
            "category":"Bakery",
            "type":"Food & Drink"
        }
    ],
    "sg:phone":"+32 3 484 35 59",
    "sg:postcode":"2240",
    "sg:province":"Antwerpen",
    "sg:tags":[
        "confectioner",
        "baker"
    ],
    "wof:name":"Cop\u00e9-lenaerts",
    "wof:placetype":"venue"
},
  "geometry": {"coordinates":[4.6633791924,51.2171287537],"type":"Point"}
}