{
  "type": "Feature",
  "properties": {
    "iso:country":"BE",
    "sg:address":"Sint-bernardsesteenweg 89",
    "sg:city":"Hemiksem",
    "sg:classifiers":[
        {
            "category":"Shopping",
            "subcategory":"Clothing, Apparel, & Fashions",
            "type":"Retail Goods"
        }
    ],
    "sg:phone":"+32 3 887 17 95",
    "sg:postcode":"2620",
    "sg:province":"Antwerpen",
    "sg:tags":[
        "ondergoed",
        "lingerie"
    ],
    "wof:name":"Huis Lucie",
    "wof:placetype":"venue"
},
  "geometry": {"coordinates":[4.3356199265,51.1317062378],"type":"Point"}
}