{
  "type": "Feature",
  "properties": {
    "iso:country":"BE",
    "sg:address":"Brugsesteenweg 8",
    "sg:city":"Pittem",
    "sg:orig_category":"Elektrische installaties voor woningen Telecommunicatieapparaten",
    "sg:phone":"+32 51 48 57 30",
    "sg:postcode":"8740",
    "sg:province":"West-Vlaanderen",
    "wof:name":"Verheust Electrics",
    "wof:placetype":"venue"
},
  "geometry": {"coordinates":[3.2355899811,51.0062103271],"type":"Point"}
}