{
  "type": "Feature",
  "properties": {
    "iso:country":"BE",
    "sg:address":"Rue De Tongres 2",
    "sg:city":"Awans (oth\u00e9e)",
    "sg:classifiers":[
        {
            "category":"Shopping",
            "subcategory":"Crafts & Fabrics",
            "type":"Retail Goods"
        }
    ],
    "sg:phone":"+32 4 257 62 03",
    "sg:postcode":"4340",
    "sg:province":"Li\u00e8ge",
    "sg:tags":[
        "ceramic"
    ],
    "wof:name":"Argika",
    "wof:placetype":"venue"
},
  "geometry": {"coordinates":[5.4725699425,50.7200317383],"type":"Point"}
}