{
  "type": "Feature",
  "properties": {
    "addr:full":"Koning Albertlaan 21 Maaseik Limburg 3680",
    "addr:housenumber":"21",
    "addr:postcode":"3680",
    "addr:street":"Koning Albertlaan",
    "iso:country":"BE",
    "sg:address":"Koning Albertlaan 21",
    "sg:city":"Maaseik",
    "sg:classifiers":[
        {
            "category":"Communications",
            "subcategory":"Radio Station",
            "type":"Services"
        }
    ],
    "sg:phone":"+32 89 56 75 58",
    "sg:postcode":"3680",
    "sg:province":"Limburg",
    "sg:tags":[
        "diffusion",
        "production",
        "de",
        "programme"
    ],
    "wof:name":"Lokale Radio Maaseik",
    "wof:placetype":"venue"
},
  "geometry": {"coordinates":[5.7842378616,51.0965232849],"type":"Point"}
}