{
  "type": "Feature",
  "properties": {
    "iso:country":"BE",
    "sg:address":"Rue Lutiau 10",
    "sg:city":"Beaumont",
    "sg:orig_category":"Kapsalons",
    "sg:phone":"+32 60 45 63 95",
    "sg:postcode":"6500",
    "sg:province":"Hainaut",
    "wof:name":"Sylvie Bortels",
    "wof:placetype":"venue"
},
  "geometry": {"coordinates":[4.2595791817,50.1885719299],"type":"Point"}
}