{
  "type": "Feature",
  "properties": {
    "addr:full":"Rue Du Jardin-botanique 38 Li\u00e8ge 1 Li\u00e8ge 4000",
    "addr:housenumber":"38;1",
    "addr:postcode":"4000",
    "addr:street":"Rue Du Jardin-Botanique",
    "iso:country":"BE",
    "sg:address":"Rue Du Jardin-botanique 38",
    "sg:city":"Li\u00e8ge 1",
    "sg:classifiers":[
        {
            "category":"Health Services",
            "subcategory":"Doctor",
            "type":"Services"
        }
    ],
    "sg:phone":"+32 4 223 59 26",
    "sg:postcode":"4000",
    "sg:province":"Li\u00e8ge",
    "sg:tags":[
        "medicinephysicians",
        "surgeon"
    ],
    "wof:name":"Bailly M",
    "wof:placetype":"venue"
},
  "geometry": {"coordinates":[5.5648531914,50.6345558167],"type":"Point"}
}