{
  "type": "Feature",
  "properties": {
    "iso:country":"BE",
    "sg:address":"Rue Leon Roger 43",
    "sg:city":"Le Roeulx",
    "sg:orig_category":"Tuinen",
    "sg:phone":"+32 67 44 49 23",
    "sg:postcode":"7070",
    "sg:province":"Hainaut",
    "wof:name":"Finet M",
    "wof:placetype":"venue"
},
  "geometry": {"coordinates":[4.1330060959,50.5420455933],"type":"Point"}
}