{
  "type": "Feature",
  "properties": {
    "addr:full":"Rue De La Goulette 2 Chiny Luxembourg 6810",
    "addr:housenumber":"2",
    "addr:postcode":"6810",
    "addr:street":"Rue De La",
    "iso:country":"BE",
    "sg:address":"Rue De La Goulette 2",
    "sg:city":"Chiny",
    "sg:classifiers":[
        {
            "category":"Food & Beverages",
            "subcategory":"Meat & Fish",
            "type":"Retail Goods"
        }
    ],
    "sg:phone":"+32 61 31 17 50",
    "sg:postcode":"6810",
    "sg:province":"Luxembourg",
    "sg:tags":[
        "poultry",
        "whol",
        "game",
        "-"
    ],
    "wof:name":"Protin Maison Sprl",
    "wof:placetype":"venue"
},
  "geometry": {"coordinates":[5.3431820869,49.7405929565],"type":"Point"}
}