{
  "type": "Feature",
  "properties": {
    "addr:full":"Leffingestraat 2 Oostende West-Vlaanderen 8400",
    "addr:housenumber":"2",
    "addr:postcode":"8400",
    "addr:street":"Leffingestraat",
    "iso:country":"BE",
    "sg:address":"Leffingestraat 2",
    "sg:city":"Oostende",
    "sg:classifiers":[
        {
            "category":"Arena",
            "subcategory":"Sports Club",
            "type":"Entertainment"
        }
    ],
    "sg:phone":"+32 59 70 36 01",
    "sg:postcode":"8400",
    "sg:province":"West-Vlaanderen",
    "wof:name":"Koninklijk Hoofdgild St Sebastiaan",
    "wof:placetype":"venue"
},
  "geometry": {"coordinates":[2.9158809185,51.2213516235],"type":"Point"}
}