{
  "type": "Feature",
  "properties": {
    "addr:full":"Charles Hanssensstraat 10 Brussel/bruxelles Bruxelles-Capitale 1000",
    "addr:housenumber":"10",
    "addr:postcode":"1000",
    "addr:street":"Hanssensstraat;/",
    "iso:country":"BE",
    "sg:address":"Charles Hanssensstraat 10",
    "sg:city":"Brussel/bruxelles",
    "sg:orig_category":"Zalen voor culturele evenementen",
    "sg:phone":"+32 2 514 79 90",
    "sg:postcode":"1000",
    "sg:province":"Bruxelles-Capitale",
    "wof:name":"K Gallery",
    "wof:placetype":"venue"
},
  "geometry": {"coordinates":[4.3528580666,50.8393211365],"type":"Point"}
}