{
  "type": "Feature",
  "properties": {
    "addr:full":"Mopertingenstraat 31b Bilzen (mopertingen) Limburg 3740",
    "addr:housenumber":"31b",
    "addr:postcode":"3740",
    "addr:street":"Mopertingenstraat",
    "iso:country":"BE",
    "sg:address":"Mopertingenstraat 31b",
    "sg:city":"Bilzen (mopertingen)",
    "sg:classifiers":[
        {
            "category":"Bakery",
            "type":"Food & Drink"
        }
    ],
    "sg:phone":"+32 89 41 25 50",
    "sg:postcode":"3740",
    "sg:province":"Limburg",
    "sg:tags":[
        "confectioner",
        "baker"
    ],
    "wof:name":"Meyers M",
    "wof:placetype":"venue"
},
  "geometry": {"coordinates":[5.5758662224,50.8637657166],"type":"Point"}
}