{
  "type": "Feature",
  "properties": {
    "addr:full":"Comognes De Suarl\u00e9e 1 Namur (suarl\u00e9e) Namur 5020",
    "addr:housenumber":"1",
    "addr:postcode":"5020",
    "addr:street":"Suarle\u0301E",
    "iso:country":"BE",
    "sg:address":"Comognes De Suarl\u00e9e 1",
    "sg:city":"Namur (suarl\u00e9e)",
    "sg:classifiers":[
        {
            "category":"Health Services",
            "subcategory":"Doctor",
            "type":"Services"
        }
    ],
    "sg:phone":"+32 81 56 07 23",
    "sg:postcode":"5020",
    "sg:province":"Namur",
    "sg:tags":[
        "medicinephysicians",
        "surgeon"
    ],
    "wof:name":"Gojceta L",
    "wof:placetype":"venue"
},
  "geometry": {"coordinates":[4.807489872,50.4918899536],"type":"Point"}
}