{
  "type": "Feature",
  "properties": {
    "addr:full":"Rue De Borfilet 12b1 Charleroi Hainaut 6040",
    "addr:housenumber":"12b1",
    "addr:postcode":"6040",
    "addr:street":"Rue De Borfilet;Hainaut",
    "iso:country":"BE",
    "sg:address":"Rue De Borfilet 12b1",
    "sg:city":"Charleroi",
    "sg:orig_category":"Kapsalons",
    "sg:phone":"+32 71 35 27 73",
    "sg:postcode":"6040",
    "sg:province":"Hainaut",
    "wof:name":"Rosa Saggese",
    "wof:placetype":"venue"
},
  "geometry": {"coordinates":[4.4268388748,50.4477157593],"type":"Point"}
}