{
  "type": "Feature",
  "properties": {
    "addr:full":"Rue Sainte-anne 1 Florenville Luxembourg 6820",
    "addr:housenumber":"1",
    "addr:postcode":"6820",
    "addr:street":"Rue Sainte-Anne",
    "iso:country":"BE",
    "sg:address":"Rue Sainte-anne 1",
    "sg:city":"Florenville",
    "sg:orig_category":"Herstelling leer and schoeisel",
    "sg:phone":"+32 61 31 40 54",
    "sg:postcode":"6820",
    "sg:province":"Luxembourg",
    "wof:name":"Albert Jacob",
    "wof:placetype":"venue"
},
  "geometry": {"coordinates":[5.3118338585,49.6994781494],"type":"Point"}
}