{
  "type": "Feature",
  "properties": {
    "addr:full":"Waversesteenweg 126 Bierbeek (honsem) Vlaams-Brabant 3360",
    "addr:housenumber":"126",
    "addr:postcode":"3360",
    "addr:street":"Waversesteenweg",
    "iso:country":"BE",
    "sg:address":"Waversesteenweg 126",
    "sg:city":"Bierbeek (honsem)",
    "sg:classifiers":[
        {
            "category":"Professional",
            "subcategory":"Management & Consulting",
            "type":"Services"
        }
    ],
    "sg:phone":"+32 16 73 38 57",
    "sg:postcode":"3360",
    "sg:province":"Vlaams-Brabant",
    "sg:tags":[
        "tax-consultants"
    ],
    "wof:name":"Libotte R",
    "wof:placetype":"venue"
},
  "geometry": {"coordinates":[4.7951440811,50.8145256042],"type":"Point"}
}