{
  "type": "Feature",
  "properties": {
    "iso:country":"BE",
    "sg:address":"Chauss\u00e9e De Lille 10",
    "sg:city":"Tournai (blandain - Hertain)",
    "sg:classifiers":[
        {
            "category":"Real Estate",
            "subcategory":"Architect",
            "type":"Services"
        }
    ],
    "sg:phone":"+32 69 22 19 82",
    "sg:postcode":"7522",
    "sg:province":"Hainaut",
    "wof:name":"Dubois B",
    "wof:placetype":"venue"
},
  "geometry": {"coordinates":[3.3750009537,50.6050262451],"type":"Point"}
}