{
  "type": "Feature",
  "properties": {
    "addr:full":"Lierseweg 204 Herentals Antwerpen 2200",
    "addr:housenumber":"204",
    "addr:postcode":"2200",
    "addr:street":"Lierseweg",
    "iso:country":"BE",
    "sg:address":"Lierseweg 204",
    "sg:city":"Herentals",
    "sg:classifiers":[
        {
            "category":"Shopping",
            "subcategory":"Bicycles & Sporting Goods",
            "type":"Retail Goods"
        }
    ],
    "sg:phone":"+32 14 21 88 46",
    "sg:postcode":"2200",
    "sg:province":"Antwerpen",
    "sg:tags":[
        "article",
        "de",
        "sport",
        "camping"
    ],
    "wof:name":"Huis Bentisport",
    "wof:placetype":"venue"
},
  "geometry": {"coordinates":[4.8183817863,51.1749191284],"type":"Point"}
}