{
  "type": "Feature",
  "properties": {
    "iso:country":"BE",
    "sg:address":"Heikensstraat 23a",
    "sg:city":"Zonhoven",
    "sg:classifiers":[
        {
            "category":"Professional",
            "subcategory":"Management & Consulting",
            "type":"Services"
        }
    ],
    "sg:phone":"+32 11 72 62 58",
    "sg:postcode":"3520",
    "sg:province":"Limburg",
    "sg:tags":[
        "consultant"
    ],
    "wof:name":"Advizo Consulting",
    "wof:placetype":"venue"
},
  "geometry": {"coordinates":[5.3401842117,50.9936828613],"type":"Point"}
}