{
  "type": "Feature",
  "properties": {
    "iso:country":"BE",
    "sg:address":"Geraardsbergseseenweg 101",
    "sg:city":"Oosterzele",
    "sg:orig_category":"Gespecialiseerde residenti\u00eble bouw",
    "sg:phone":"+32 9 363 04 13",
    "sg:postcode":"9860",
    "sg:province":"Oost-Vlaanderen",
    "wof:name":"De Clerck D",
    "wof:placetype":"venue"
},
  "geometry": {"coordinates":[3.8142371178,50.9477157593],"type":"Point"}
}