{
  "type": "Feature",
  "properties": {
    "iso:country":"BE",
    "sg:address":"Chauss\u00c9e De Beaumont 192b",
    "sg:city":"Mons",
    "sg:orig_category":"Sportterreinen and installaties behalve sportcentra",
    "sg:phone":"+32 65 33 56 16",
    "sg:postcode":"7032",
    "sg:province":"Hainaut",
    "wof:name":"Barri\u00c8re Bowling",
    "wof:placetype":"venue"
},
  "geometry": {"coordinates":[3.9869709015,50.4255142212],"type":"Point"}
}