{
  "type": "Feature",
  "properties": {
    "addr:full":"Charles Lemairestraat 10 Oudergem/auderghem Bruxelles-Capitale 1160",
    "addr:housenumber":"10",
    "addr:postcode":"1160",
    "addr:street":"Charles Lemairestraat;/",
    "iso:country":"BE",
    "sg:address":"Charles Lemairestraat 10",
    "sg:city":"Oudergem/auderghem",
    "sg:orig_category":"Artsen and specialisten",
    "sg:phone":"+32 2 660 97 11",
    "sg:postcode":"1160",
    "sg:province":"Bruxelles-Capitale",
    "wof:name":"Thierry Wauters",
    "wof:placetype":"venue"
},
  "geometry": {"coordinates":[4.4286208153,50.8107833862],"type":"Point"}
}