{
  "type": "Feature",
  "properties": {
    "addr:full":"Albertplein 24 Knokke-heist (knokke) West-Vlaanderen 8300",
    "addr:housenumber":"24",
    "addr:postcode":"8300",
    "addr:street":"Albertplein",
    "iso:country":"BE",
    "sg:address":"Albertplein 24",
    "sg:city":"Knokke-heist (knokke)",
    "sg:classifiers":[
        {
            "category":"Personal",
            "subcategory":"Barber",
            "type":"Services"
        }
    ],
    "sg:phone":"+32 50 61 54 55",
    "sg:postcode":"8300",
    "sg:province":"West-Vlaanderen",
    "sg:tags":[
        "gentleman",
        "salon",
        "-",
        "hairdressing"
    ],
    "wof:name":"Coiffure Ans",
    "wof:placetype":"venue"
},
  "geometry": {"coordinates":[3.2899050713,51.3419456482],"type":"Point"}
}