{
  "type": "Feature",
  "properties": {
    "addr:full":"Jan Van Puyenbroecklaan 91 Schoten Antwerpen 2900",
    "addr:housenumber":"91",
    "addr:postcode":"2900",
    "addr:street":"Jan Van Puyenbroecklaan",
    "iso:country":"BE",
    "sg:address":"Jan Van Puyenbroecklaan 91",
    "sg:city":"Schoten",
    "sg:classifiers":[
        {
            "category":"Real Estate",
            "subcategory":"Real Estate Services",
            "type":"Services"
        }
    ],
    "sg:phone":"+32 3 640 39 00",
    "sg:postcode":"2900",
    "sg:province":"Antwerpen",
    "wof:name":"Delta Data Bvba",
    "wof:placetype":"venue"
},
  "geometry": {"coordinates":[4.4685997963,51.2623977661],"type":"Point"}
}