{
  "type": "Feature",
  "properties": {
    "addr:full":"Chaussee De Verviers 91 Theux Li\u00e8ge 4910",
    "addr:housenumber":"91",
    "addr:postcode":"4910",
    "addr:street":"Chaussee De Verviers",
    "iso:country":"BE",
    "sg:address":"Chaussee De Verviers 91",
    "sg:city":"Theux",
    "sg:classifiers":[
        {
            "category":"Professional",
            "subcategory":"Accounting & Tax Preparation",
            "type":"Services"
        }
    ],
    "sg:phone":"+32 3 248 66 77",
    "sg:postcode":"4910",
    "sg:province":"Li\u00e8ge",
    "sg:tags":[
        "bookkeeping"
    ],
    "wof:name":"Intersoft Belgium Nv",
    "wof:placetype":"venue"
},
  "geometry": {"coordinates":[4.4436798096,51.1831512451],"type":"Point"}
}