{
  "type": "Feature",
  "properties": {
    "iso:country":"BE",
    "sg:address":"Eikelstraat 16",
    "sg:city":"Zelzate",
    "sg:classifiers":[
        {
            "category":"Utilities",
            "subcategory":"Natural Gas",
            "type":"Services"
        }
    ],
    "sg:phone":"+32 9 344 66 63",
    "sg:postcode":"9060",
    "sg:province":"Oost-Vlaanderen",
    "sg:tags":[
        "welding"
    ],
    "wof:name":"Hamerlinck T",
    "wof:placetype":"venue"
},
  "geometry": {"coordinates":[3.7842869759,51.2012290955],"type":"Point"}
}