{
  "type": "Feature",
  "properties": {
    "iso:country":"BE",
    "sg:address":"Meldenstraat 58",
    "sg:city":"Oudenaarde (melden)",
    "sg:classifiers":[
        {
            "category":"Banks & Credit Unions",
            "subcategory":"Investment Brokerage",
            "type":"Services"
        }
    ],
    "sg:phone":"+32 55 30 39 61",
    "sg:postcode":"9700",
    "sg:province":"Oost-Vlaanderen",
    "sg:tags":[
        "repair",
        "-",
        "installation",
        "sanitary",
        "article"
    ],
    "wof:name":"De Bouver-de Naeyer Cvba",
    "wof:placetype":"venue"
},
  "geometry": {"coordinates":[3.57385993,50.8169593811],"type":"Point"}
}