{
  "type": "Feature",
  "properties": {
    "iso:country":"BE",
    "sg:address":"Rue Des Prairies 48-50",
    "sg:city":"Soumagne",
    "sg:classifiers":[
        {
            "category":"Food & Beverages",
            "subcategory":"Liquor & Beverages",
            "type":"Retail Goods"
        }
    ],
    "sg:phone":"+32 4 377 20 06",
    "sg:postcode":"4630",
    "sg:province":"Li\u00e8ge",
    "sg:tags":[
        "-",
        "spirit",
        "wine"
    ],
    "wof:name":"Vini France",
    "wof:placetype":"venue"
},
  "geometry": {"coordinates":[5.734913826,50.6303672791],"type":"Point"}
}