{
  "type": "Feature",
  "properties": {
    "addr:full":"Rue De La Station 82 Walcourt Namur 5650",
    "addr:housenumber":"82",
    "addr:postcode":"5650",
    "addr:street":"Rue De La Station",
    "iso:country":"BE",
    "sg:address":"Rue De La Station 82",
    "sg:city":"Walcourt",
    "sg:orig_category":"Cr\u00e9dits divers",
    "sg:postcode":"5650",
    "sg:province":"Namur",
    "wof:name":"Bancontact-mister Cash",
    "wof:placetype":"venue"
},
  "geometry": {"coordinates":[4.4374938011,50.2572555542],"type":"Point"}
}