{
  "type": "Feature",
  "properties": {
    "iso:country":"BE",
    "sg:address":"Welvaartstraat 6",
    "sg:city":"Herentals (noorderwijk)",
    "sg:classifiers":[
        {
            "category":"Airport",
            "subcategory":"International",
            "type":"Transportation"
        }
    ],
    "sg:phone":"+32 14 23 57 55",
    "sg:postcode":"2200",
    "sg:province":"Antwerpen",
    "sg:tags":[
        "-",
        "transport"
    ],
    "wof:name":"T P & H",
    "wof:placetype":"venue"
},
  "geometry": {"coordinates":[4.7998099327,51.1599960327],"type":"Point"}
}