{
  "type": "Feature",
  "properties": {
    "iso:country":"BE",
    "sg:address":"Rue De Ch\u00e2telet 7",
    "sg:city":"Philippeville (villers-le-gambon)",
    "sg:classifiers":[
        {
            "category":"Personal",
            "subcategory":"Barber",
            "type":"Services"
        }
    ],
    "sg:phone":"+32 71 61 55 61",
    "sg:postcode":"5600",
    "sg:province":"Namur",
    "sg:tags":[
        "gentleman",
        "salon",
        "-",
        "hairdressing"
    ],
    "wof:name":"Imagin'hair",
    "wof:placetype":"venue"
},
  "geometry": {"coordinates":[4.6067438126,50.1924972534],"type":"Point"}
}