{
  "type": "Feature",
  "properties": {
    "iso:country":"BE",
    "sg:address":"Hoevedreef 21",
    "sg:city":"Aarschot",
    "sg:orig_category":"Rundveehouders Varkenskwekers",
    "sg:phone":"+32 16 50 01 69",
    "sg:postcode":"3202",
    "sg:province":"Vlaams-Brabant",
    "wof:name":"Stephan Verbist",
    "wof:placetype":"venue"
},
  "geometry": {"coordinates":[4.8903942108,50.9778671265],"type":"Point"}
}