{
  "type": "Feature",
  "properties": {
    "addr:full":"Riksingenstraat 60 Tongeren (riksingen) Limburg 3700",
    "addr:housenumber":"60",
    "addr:postcode":"3700",
    "addr:street":"Riksingenstraat",
    "iso:country":"BE",
    "sg:address":"Riksingenstraat 60",
    "sg:city":"Tongeren (riksingen)",
    "sg:classifiers":[
        {
            "category":"Health Services",
            "subcategory":"Doctor",
            "type":"Services"
        }
    ],
    "sg:phone":"+32 12 26 15 76",
    "sg:postcode":"3700",
    "sg:province":"Limburg",
    "sg:tags":[
        "medicinephysicians",
        "surgeon"
    ],
    "wof:name":"Hendrickx E",
    "wof:placetype":"venue"
},
  "geometry": {"coordinates":[5.4636240005,50.7807197571],"type":"Point"}
}