{
  "type": "Feature",
  "properties": {
    "addr:full":"Rue Du Tilleul 373 Bruxelles (evere) Bruxelles-Capitale 1140",
    "addr:housenumber":"373",
    "addr:postcode":"1140",
    "addr:street":"Rue Du Tilleul",
    "iso:country":"BE",
    "sg:address":"Rue Du Tilleul 373",
    "sg:city":"Bruxelles (evere)",
    "sg:classifiers":[
        {
            "category":"Food & Beverages",
            "subcategory":"Groceries & Convenience Stores",
            "type":"Retail Goods"
        }
    ],
    "sg:phone":"+32 2 241 28 51",
    "sg:postcode":"1140",
    "sg:province":"Bruxelles-Capitale",
    "sg:tags":[
        "grocer"
    ],
    "wof:name":"Sonia",
    "wof:placetype":"venue"
},
  "geometry": {"coordinates":[4.3967108727,50.8679199219],"type":"Point"}
}