{
  "type": "Feature",
  "properties": {
    "addr:full":"Rue Croix Claire 5 Nandrin Li\u00e8ge 4550",
    "addr:housenumber":"5",
    "addr:postcode":"4550",
    "addr:street":"Rue Croix Claire",
    "iso:country":"BE",
    "sg:address":"Rue Croix Claire 5",
    "sg:city":"Nandrin",
    "sg:classifiers":[
        {
            "category":"Health Services",
            "subcategory":"Nursing And Care Facility",
            "type":"Services"
        }
    ],
    "sg:phone":"+32 85 51 32 82",
    "sg:postcode":"4550",
    "sg:province":"Li\u00e8ge",
    "sg:tags":[
        "home"
    ],
    "wof:name":"Syrros C",
    "wof:placetype":"venue"
},
  "geometry": {"coordinates":[5.4390997887,50.5209388733],"type":"Point"}
}