{
  "type": "Feature",
  "properties": {
    "addr:full":"Chauss\u00e9e De Montigny 115 Charleroi Hainaut 6000",
    "addr:housenumber":"115",
    "addr:postcode":"6000",
    "addr:street":"Chausse\u0301E De Montigny;Hainaut",
    "iso:country":"BE",
    "sg:address":"Chauss\u00e9e De Montigny 115",
    "sg:city":"Charleroi",
    "sg:classifiers":[
        {
            "category":"Shopping",
            "subcategory":"Shoes",
            "type":"Retail Goods"
        }
    ],
    "sg:phone":"+32 71 31 67 39",
    "sg:postcode":"6000",
    "sg:province":"Hainaut",
    "sg:tags":[
        "work",
        "discharge",
        "protected",
        "electrostatic",
        "esd"
    ],
    "wof:name":"New Ever Best S.p.r.l.",
    "wof:placetype":"venue"
},
  "geometry": {"coordinates":[4.4534368515,50.40442276],"type":"Point"}
}