{
  "type": "Feature",
  "properties": {
    "iso:country":"BE",
    "sg:address":"Malendriesstraat 78",
    "sg:city":"Boutersem",
    "sg:orig_category":"Rundveehouders Varkenskwekers",
    "sg:phone":"+32 16 73 36 79",
    "sg:postcode":"3370",
    "sg:province":"Vlaams-Brabant",
    "wof:name":"Karel Roelants",
    "wof:placetype":"venue"
},
  "geometry": {"coordinates":[4.8664259911,50.8576202393],"type":"Point"}
}