{
  "type": "Feature",
  "properties": {
    "addr:full":"Minister Delbekelaan 70-72 Antwerpen (merksem) Antwerpen 2170",
    "addr:postcode":"70-72;2170",
    "addr:street":"Minister Delbekelaan",
    "iso:country":"BE",
    "sg:address":"Minister Delbekelaan 70-72",
    "sg:city":"Antwerpen (merksem)",
    "sg:classifiers":[
        {
            "category":"Home & Garden",
            "subcategory":"Home Furnishings",
            "type":"Retail Goods"
        }
    ],
    "sg:phone":"+32 3 647 12 10",
    "sg:postcode":"2170",
    "sg:province":"Antwerpen",
    "sg:tags":[
        "interior",
        "decoration"
    ],
    "wof:name":"Ila Benelux Bvba",
    "wof:placetype":"venue"
},
  "geometry": {"coordinates":[4.4505147934,51.246723175],"type":"Point"}
}