{
  "type": "Feature",
  "properties": {
    "iso:country":"BE",
    "sg:address":"Rue De Luna 20",
    "sg:city":"Estaimpuis (estaimbourg)",
    "sg:classifiers":[
        {
            "category":"Health Services",
            "subcategory":"Health Practitioner",
            "type":"Services"
        }
    ],
    "sg:phone":"+32 69 55 78 74",
    "sg:postcode":"7730",
    "sg:province":"Hainaut",
    "sg:tags":[
        "physiotherapist"
    ],
    "wof:name":"Dekoster Ph",
    "wof:placetype":"venue"
},
  "geometry": {"coordinates":[3.2932929993,50.6866226196],"type":"Point"}
}