{
  "type": "Feature",
  "properties": {
    "addr:full":"Rietstraat 27 Oostende West-Vlaanderen 8400",
    "addr:housenumber":"27",
    "addr:postcode":"8400",
    "addr:street":"Rietstraat",
    "iso:country":"BE",
    "sg:address":"Rietstraat 27",
    "sg:city":"Oostende",
    "sg:orig_category":"Traitements param\u00e9dicaux",
    "sg:phone":"+32 59 80 69 75",
    "sg:postcode":"8400",
    "sg:province":"West-Vlaanderen",
    "wof:name":"Heidi Vandecasteele",
    "wof:placetype":"venue"
},
  "geometry": {"coordinates":[2.9118499756,51.218460083],"type":"Point"}
}