{
  "type": "Feature",
  "properties": {
    "iso:country":"BE",
    "sg:address":"Place E. Des Gr\u00c9es Du Bois 15",
    "sg:city":"Tubeke",
    "sg:orig_category":"Diverse opleidingen and onderwijs",
    "sg:phone":"+32 2 355 92 00",
    "sg:postcode":"1480",
    "sg:province":"Brabant Wallon",
    "wof:name":"Syst\u00c8me Service",
    "wof:placetype":"venue"
},
  "geometry": {"coordinates":[4.2332539558,50.6668663025],"type":"Point"}
}