{
  "type": "Feature",
  "properties": {
    "addr:full":"Maldersesteenweg 25 Londerzeel Vlaams-Brabant 1840",
    "addr:housenumber":"25",
    "addr:postcode":"1840",
    "addr:street":"Maldersesteenweg",
    "iso:country":"BE",
    "sg:address":"Maldersesteenweg 25",
    "sg:city":"Londerzeel",
    "sg:orig_category":"Boekhouders",
    "sg:phone":"+32 52 30 07 53",
    "sg:postcode":"1840",
    "sg:province":"Vlaams-Brabant",
    "wof:name":"Pierre Tassenon",
    "wof:placetype":"venue"
},
  "geometry": {"coordinates":[4.2810602188,51.0308074951],"type":"Point"}
}