{
  "type": "Feature",
  "properties": {
    "iso:country":"BE",
    "sg:address":"Atletiekplein 6a",
    "sg:city":"Gent",
    "sg:classifiers":[
        {
            "category":"Health Services",
            "subcategory":"Health Practitioner",
            "type":"Services"
        }
    ],
    "sg:phone":"+32 9 222 30 98",
    "sg:postcode":"9000",
    "sg:province":"Oost-Vlaanderen",
    "sg:tags":[
        "physiotherapist"
    ],
    "wof:name":"Baert P",
    "wof:placetype":"venue"
},
  "geometry": {"coordinates":[3.6990630627,51.0418434143],"type":"Point"}
}