{
  "type": "Feature",
  "properties": {
    "addr:full":"Katteboomstraat 85 Izegem West-Vlaanderen 8870",
    "addr:housenumber":"85",
    "addr:postcode":"8870",
    "addr:street":"Katteboomstraat",
    "iso:country":"BE",
    "sg:address":"Katteboomstraat 85",
    "sg:city":"Izegem",
    "sg:orig_category":"Woningbouw",
    "sg:phone":"+32 51 30 83 69",
    "sg:postcode":"8870",
    "sg:province":"West-Vlaanderen",
    "wof:name":"Marcel Vandecasteele",
    "wof:placetype":"venue"
},
  "geometry": {"coordinates":[3.2308349609,50.9010391235],"type":"Point"}
}