{
  "type": "Feature",
  "properties": {
    "addr:full":"Alex Feldheimstraat 40 Zaventem Vlaams-Brabant 1930",
    "addr:housenumber":"40",
    "addr:postcode":"1930",
    "addr:street":"Alex Feldheimstraat",
    "iso:country":"BE",
    "sg:address":"Alex Feldheimstraat 40",
    "sg:city":"Zaventem",
    "sg:orig_category":"Artsen and specialisten",
    "sg:phone":"+32 2 720 13 52",
    "sg:postcode":"1930",
    "sg:province":"Vlaams-Brabant",
    "wof:name":"Rapha\u00cbl De Graeve",
    "wof:placetype":"venue"
},
  "geometry": {"coordinates":[4.4667930603,50.8892250061],"type":"Point"}
}