{
  "type": "Feature",
  "properties": {
    "addr:full":"Avenue Des Flandres 31 Leuze-en-hainaut Hainaut 7900",
    "addr:housenumber":"31",
    "addr:postcode":"7900",
    "addr:street":"Avenue Des Flandres",
    "iso:country":"BE",
    "sg:address":"Avenue Des Flandres 31",
    "sg:city":"Leuze-en-hainaut",
    "sg:classifiers":[
        {
            "category":"Professional",
            "subcategory":"Accounting & Tax Preparation",
            "type":"Services"
        }
    ],
    "sg:phone":"+32 69 66 44 02",
    "sg:postcode":"7900",
    "sg:province":"Hainaut",
    "sg:tags":[
        "accountant"
    ],
    "wof:name":"Van Wijmeersch G",
    "wof:placetype":"venue"
},
  "geometry": {"coordinates":[3.6158978939,50.6097984314],"type":"Point"}
}