{
  "type": "Feature",
  "properties": {
    "iso:country":"BE",
    "sg:address":"Kattestraat 3",
    "sg:city":"Asse",
    "sg:classifiers":[
        {
            "category":"Real Estate",
            "subcategory":"Real Estate Services",
            "type":"Services"
        }
    ],
    "sg:phone":"+32 2 452 92 52",
    "sg:postcode":"1730",
    "sg:province":"Vlaams-Brabant",
    "wof:name":"Immo Assim Nv",
    "wof:placetype":"venue"
},
  "geometry": {"coordinates":[4.1990809441,50.9102325439],"type":"Point"}
}