{
  "type": "Feature",
  "properties": {
    "addr:full":"Rue Neuve 49 Beloeil Hainaut 7972",
    "addr:housenumber":"49",
    "addr:postcode":"7972",
    "addr:street":"Rue Neuve",
    "iso:country":"BE",
    "sg:address":"Rue Neuve 49",
    "sg:city":"Beloeil",
    "sg:orig_category":"Rundveehouders",
    "sg:phone":"+32 69 68 92 63",
    "sg:postcode":"7972",
    "sg:province":"Hainaut",
    "wof:name":"Jose Verbrigghe",
    "wof:placetype":"venue"
},
  "geometry": {"coordinates":[3.6808900833,50.5615882874],"type":"Point"}
}