{
  "type": "Feature",
  "properties": {
    "iso:country":"BE",
    "sg:address":"Tongersesteenweg 22",
    "sg:city":"Riemst",
    "sg:orig_category":"Antiquit\u00e9s",
    "sg:phone":"+32 12 45 21 07",
    "sg:postcode":"3770",
    "sg:province":"Limburg",
    "wof:name":"Joseph Vanseer",
    "wof:placetype":"venue"
},
  "geometry": {"coordinates":[5.5916981697,50.8106155396],"type":"Point"}
}