{
  "type": "Feature",
  "properties": {
    "addr:full":"Rue De L'avenir 61 Gr\u00e2ce-hollogne (gr\u00e2ce-berleur) Li\u00e8ge 4460",
    "addr:housenumber":"61",
    "addr:postcode":"4460",
    "addr:street":"Rue De L'Avenir;Gra\u0302Ce-Berleur",
    "iso:country":"BE",
    "sg:address":"Rue De L'avenir 61",
    "sg:city":"Gr\u00e2ce-hollogne (gr\u00e2ce-berleur)",
    "sg:orig_category":"Electric transformers, rectifiers, converters",
    "sg:postcode":"4460",
    "sg:province":"Li\u00e8ge",
    "wof:name":"Euro-diesel Seghersbetter Technology Group",
    "wof:placetype":"venue"
},
  "geometry": {"coordinates":[5.4939060211,50.6540794373],"type":"Point"}
}