{
  "type": "Feature",
  "properties": {
    "addr:full":"Avenue Des P\u00e2querettes 4a Rixensart Brabant Wallon 1330",
    "addr:housenumber":"4a",
    "addr:postcode":"1330",
    "addr:street":"Avenue Des Pa\u0302Querettes;Wallon",
    "iso:country":"BE",
    "sg:address":"Avenue Des P\u00e2querettes 4a",
    "sg:city":"Rixensart",
    "sg:classifiers":[
        {
            "category":"Building & Trades",
            "subcategory":"Landscaping Services",
            "type":"Services"
        }
    ],
    "sg:phone":"+32 2 652 16 73",
    "sg:postcode":"1330",
    "sg:province":"Brabant Wallon",
    "sg:tags":[
        "gardening",
        "garden",
        "maintenance"
    ],
    "wof:name":"Stassin S",
    "wof:placetype":"venue"
},
  "geometry": {"coordinates":[4.5260682106,50.7127571106],"type":"Point"}
}