{
  "type": "Feature",
  "properties": {
    "iso:country":"BE",
    "sg:address":"Rue Barri\u00c8re Moye 24",
    "sg:city":"Wavre",
    "sg:orig_category":"Timbres, monnaies and troph\u00e9es",
    "sg:phone":"+32 10 24 50 87",
    "sg:postcode":"1300",
    "sg:province":"Brabant Wallon",
    "wof:name":"Jean-louis Dechesne",
    "wof:placetype":"venue"
},
  "geometry": {"coordinates":[4.6151051521,50.7061042786],"type":"Point"}
}