{
  "type": "Feature",
  "properties": {
    "iso:country":"BE",
    "sg:address":"Rue Saint-joseph 31",
    "sg:city":"Saint-hubert (arville)",
    "sg:classifiers":[
        {
            "category":"Utilities",
            "subcategory":"Refuse",
            "type":"Services"
        }
    ],
    "sg:phone":"+32 61 61 34 59",
    "sg:postcode":"6870",
    "sg:province":"Luxembourg",
    "sg:tags":[
        "removal"
    ],
    "wof:name":"Wathelet A",
    "wof:placetype":"venue"
},
  "geometry": {"coordinates":[5.3082561493,50.031162262],"type":"Point"}
}