{
  "type": "Feature",
  "properties": {
    "iso:country":"BE",
    "sg:address":"Rue De Gouy 15",
    "sg:city":"Chapelle-lez-herlaimont",
    "sg:classifiers":[
        {
            "category":"Bakery",
            "type":"Food & Drink"
        }
    ],
    "sg:phone":"+32 64 44 49 48",
    "sg:postcode":"7160",
    "sg:province":"Hainaut",
    "sg:tags":[
        "confectioner",
        "baker"
    ],
    "wof:name":"Croissant (au)",
    "wof:placetype":"venue"
},
  "geometry": {"coordinates":[4.2840099335,50.4709854126],"type":"Point"}
}