{
  "type": "Feature",
  "properties": {
    "addr:full":"O.l. Vrouwziekenhuis Briekenstraat 1 Ieper West-Vlaanderen 8900",
    "addr:housenumber":"1",
    "addr:postcode":"8900",
    "addr:street":"O.L. Vrouwziekenhuis Briekenstraat",
    "iso:country":"BE",
    "sg:address":"O.l. Vrouwziekenhuis Briekenstraat 1",
    "sg:city":"Ieper",
    "sg:orig_category":"M\u00e9decins and sp\u00e9cialistes",
    "sg:phone":"+32 57 21 57 58",
    "sg:postcode":"8900",
    "sg:province":"West-Vlaanderen",
    "wof:name":"Sercu E.",
    "wof:placetype":"venue"
},
  "geometry": {"coordinates":[2.8878269196,50.8513641357],"type":"Point"}
}