{
  "type": "Feature",
  "properties": {
    "addr:full":"Stevennekens 59 Rijkevorsel Antwerpen 2310",
    "addr:housenumber":"59",
    "addr:postcode":"2310",
    "addr:street":"Stevennekens",
    "iso:country":"BE",
    "sg:address":"Stevennekens 59",
    "sg:city":"Rijkevorsel",
    "sg:orig_category":"Databeheer and gegevensverwerking",
    "sg:phone":"+32 3 309 37 49",
    "sg:postcode":"2310",
    "sg:province":"Antwerpen",
    "wof:name":"Dcc It - Services",
    "wof:placetype":"venue"
},
  "geometry": {"coordinates":[4.7701501846,51.3403816223],"type":"Point"}
}