{
  "type": "Feature",
  "properties": {
    "iso:country":"BE",
    "sg:address":"Grote Branderstraat 41",
    "sg:city":"Ieper",
    "sg:orig_category":"Eleveurs de bovins. Eleveurs and marchands de porcs",
    "sg:phone":"+32 57 33 38 62",
    "sg:postcode":"8908",
    "sg:province":"West-Vlaanderen",
    "wof:name":"Rik Vermeersch",
    "wof:placetype":"venue"
},
  "geometry": {"coordinates":[2.8029949665,50.8403015137],"type":"Point"}
}