{
  "type": "Feature",
  "properties": {
    "iso:country":"BE",
    "sg:address":"Gentse Steenweg 16",
    "sg:city":"Damme",
    "sg:orig_category":"D\u00e9corateurs d'int\u00e9rieur",
    "sg:phone":"+32 50 35 13 22",
    "sg:postcode":"8340",
    "sg:province":"West-Vlaanderen",
    "wof:name":"Barbara Vanhollebeke",
    "wof:placetype":"venue"
},
  "geometry": {"coordinates":[3.3378329277,51.2024116516],"type":"Point"}
}