{
  "type": "Feature",
  "properties": {
    "iso:country":"BE",
    "sg:address":"Rue Des D\u00e9port\u00e9s 51",
    "sg:city":"Braine-le-comte",
    "sg:classifiers":[
        {
            "category":"Shopping",
            "subcategory":"Florist",
            "type":"Retail Goods"
        }
    ],
    "sg:phone":"+32 67 55 31 84",
    "sg:postcode":"7090",
    "sg:province":"Hainaut",
    "wof:name":"Flor'anouck",
    "wof:placetype":"venue"
},
  "geometry": {"coordinates":[4.127573967,50.6067581177],"type":"Point"}
}