{
  "type": "Feature",
  "properties": {
    "addr:full":"Chemin Des T\u00c8rmas 8 Weismes/waimes Li\u00e8ge 4950",
    "addr:housenumber":"8",
    "addr:postcode":"4950",
    "addr:street":"Chemin Des Te\u0300Rmas",
    "iso:country":"BE",
    "sg:address":"Chemin Des T\u00c8rmas 8",
    "sg:city":"Weismes/waimes",
    "sg:orig_category":"M\u00e9decines alternatives",
    "sg:phone":"+32 80 44 66 67",
    "sg:postcode":"4950",
    "sg:province":"Li\u00e8ge",
    "wof:name":"Chantal Wey",
    "wof:placetype":"venue"
},
  "geometry": {"coordinates":[6.1406908035,50.4036178589],"type":"Point"}
}