{
  "type": "Feature",
  "properties": {
    "iso:country":"BE",
    "sg:address":"Langeheidestraat 14",
    "sg:city":"Huldenberg (ottenburg)",
    "sg:classifiers":[
        {
            "category":"Professional",
            "type":"Services"
        }
    ],
    "sg:phone":"+32 16 47 05 40",
    "sg:postcode":"3040",
    "sg:province":"Vlaams-Brabant",
    "sg:tags":[
        "surveyor",
        "-",
        "valuer"
    ],
    "wof:name":"Bury Hans Bvba",
    "wof:placetype":"venue"
},
  "geometry": {"coordinates":[4.6268987656,50.7496528625],"type":"Point"}
}