{
  "type": "Feature",
  "properties": {
    "addr:full":"Square Levie 3 Brussel/bruxelles Bruxelles-Capitale 1200",
    "addr:housenumber":"3",
    "addr:postcode":"1200",
    "addr:street":"Square Levie;/",
    "iso:country":"BE",
    "sg:address":"Square Levie 3",
    "sg:city":"Brussel/bruxelles",
    "sg:orig_category":"Bloemen and planten",
    "sg:phone":"+32 2 733 71 84",
    "sg:postcode":"1200",
    "sg:province":"Bruxelles-Capitale",
    "wof:name":"Fleurs De Lalieu",
    "wof:placetype":"venue"
},
  "geometry": {"coordinates":[4.4090228081,50.8481216431],"type":"Point"}
}