{
  "type": "Feature",
  "properties": {
    "iso:country":"BE",
    "sg:address":"Boomgaardstraat 6",
    "sg:city":"Turnhout",
    "sg:orig_category":"Artsen and specialisten",
    "sg:phone":"+32 14 41 29 45",
    "sg:postcode":"2300",
    "sg:province":"Antwerpen",
    "wof:name":"T. Grietens",
    "wof:placetype":"venue"
},
  "geometry": {"coordinates":[4.9590988159,51.3218231201],"type":"Point"}
}