{
  "type": "Feature",
  "properties": {
    "iso:country":"BE",
    "sg:address":"Tichelrijstraat 51",
    "sg:city":"Sint-truiden",
    "sg:orig_category":"Installatie van houten of kunststof schrijnwerk",
    "sg:phone":"+32 11 68 35 45",
    "sg:postcode":"3800",
    "sg:province":"Limburg",
    "wof:name":"Paul Vancattendyck",
    "wof:placetype":"venue"
},
  "geometry": {"coordinates":[5.1934938431,50.8162841797],"type":"Point"}
}