{
  "type": "Feature",
  "properties": {
    "addr:full":"Hannuitsesteenweg 159 Landen Vlaams-Brabant 3400",
    "addr:housenumber":"159",
    "addr:postcode":"3400",
    "addr:street":"Hannuitsesteenweg",
    "iso:country":"BE",
    "sg:address":"Hannuitsesteenweg 159",
    "sg:city":"Landen",
    "sg:classifiers":[
        {
            "category":"Real Estate",
            "subcategory":"Surveying",
            "type":"Services"
        }
    ],
    "sg:phone":"+32 11 88 46 53",
    "sg:postcode":"3400",
    "sg:province":"Vlaams-Brabant",
    "sg:tags":[
        "surveyor",
        "land"
    ],
    "wof:name":"Bex D",
    "wof:placetype":"venue"
},
  "geometry": {"coordinates":[5.0810799599,50.7411499023],"type":"Point"}
}