{
  "type": "Feature",
  "properties": {
    "addr:full":"Thomas Vanloostraat 38 Oostende West-Vlaanderen 8400",
    "addr:housenumber":"38",
    "addr:postcode":"8400",
    "addr:street":"Vanloostraat",
    "iso:country":"BE",
    "sg:address":"Thomas Vanloostraat 38",
    "sg:city":"Oostende",
    "sg:classifiers":[
        {
            "category":"Personal",
            "subcategory":"Beauty Salon",
            "type":"Services"
        }
    ],
    "sg:phone":"+32 59 32 62 29",
    "sg:postcode":"8400",
    "sg:province":"West-Vlaanderen",
    "sg:tags":[
        "de",
        "coiffure"
    ],
    "wof:name":"Barbara Hair",
    "wof:placetype":"venue"
},
  "geometry": {"coordinates":[2.9126999378,51.2312583923],"type":"Point"}
}