{
  "type": "Feature",
  "properties": {
    "addr:full":"Commijn 10 Bi\u00e9v\u00e8ne Vlaams-Brabant 1547",
    "addr:housenumber":"10;1547",
    "addr:street":"Commijn;Vlaams-Brabant",
    "iso:country":"BE",
    "sg:address":"Commijn 10",
    "sg:city":"Bi\u00e9v\u00e8ne",
    "sg:classifiers":[
        {
            "category":"Health Services",
            "subcategory":"Health Practitioner",
            "type":"Services"
        }
    ],
    "sg:phone":"+32 54 58 01 80",
    "sg:postcode":"1547",
    "sg:province":"Vlaams-Brabant",
    "sg:tags":[
        "physiotherapist"
    ],
    "wof:name":"Desmecht Marthe",
    "wof:placetype":"venue"
},
  "geometry": {"coordinates":[3.9310050011,50.7062301636],"type":"Point"}
}