{
  "type": "Feature",
  "properties": {
    "addr:full":"Chauss\u00e9e De Bruxelles 139a Waterloo Brabant Wallon 1410",
    "addr:housenumber":"139a",
    "addr:postcode":"1410",
    "addr:street":"Chausse\u0301E De Bruxelles",
    "iso:country":"BE",
    "sg:address":"Chauss\u00e9e De Bruxelles 139a",
    "sg:city":"Waterloo",
    "sg:classifiers":[
        {
            "category":"Bakery",
            "type":"Food & Drink"
        }
    ],
    "sg:phone":"+32 2 354 59 90",
    "sg:postcode":"1410",
    "sg:province":"Brabant Wallon",
    "sg:tags":[
        "confectioner",
        "baker"
    ],
    "wof:name":"Pain Quotidien (le)",
    "wof:placetype":"venue"
},
  "geometry": {"coordinates":[4.3981099129,50.7180595398],"type":"Point"}
}