{
  "type": "Feature",
  "properties": {
    "iso:country":"BE",
    "sg:address":"Steegstraat 11",
    "sg:city":"Balen",
    "sg:classifiers":[
        {
            "category":"Banks & Credit Unions",
            "subcategory":"Bank",
            "type":"Services"
        }
    ],
    "sg:phone":"+32 14 81 24 09",
    "sg:postcode":"2490",
    "sg:province":"Antwerpen",
    "wof:name":"Aslk-cger Bank",
    "wof:placetype":"venue"
},
  "geometry": {"coordinates":[5.1686339378,51.1699943542],"type":"Point"}
}