{
  "type": "Feature",
  "properties": {
    "addr:full":"Recognitiestraat 19 Wommelgem Antwerpen 2160",
    "addr:housenumber":"19",
    "addr:postcode":"2160",
    "addr:street":"Recognitiestraat",
    "iso:country":"BE",
    "sg:address":"Recognitiestraat 19",
    "sg:city":"Wommelgem",
    "sg:orig_category":"Sportclubs",
    "sg:phone":"+32 3 353 84 41",
    "sg:postcode":"2160",
    "sg:province":"Antwerpen",
    "wof:name":"K.c. Sparta Ranst",
    "wof:placetype":"venue"
},
  "geometry": {"coordinates":[4.5351691246,51.1954040527],"type":"Point"}
}