{
  "type": "Feature",
  "properties": {
    "addr:full":"Avenue Victor-tesch 5 Arlon Luxembourg 6700",
    "addr:housenumber":"5",
    "addr:postcode":"6700",
    "addr:street":"Avenue Victor-Tesch",
    "iso:country":"BE",
    "sg:address":"Avenue Victor-tesch 5",
    "sg:city":"Arlon",
    "sg:orig_category":"Advocaten and juridische adviseurs",
    "sg:phone":"+32 63 22 47 44",
    "sg:postcode":"6700",
    "sg:province":"Luxembourg",
    "wof:name":"Nathalie Crochet",
    "wof:placetype":"venue"
},
  "geometry": {"coordinates":[5.8004441261,49.6867637634],"type":"Point"}
}