{
  "type": "Feature",
  "properties": {
    "addr:full":"Rue De Mettet 9 Florennes Namur 5620",
    "addr:housenumber":"9",
    "addr:postcode":"5620",
    "addr:street":"Rue De Mettet",
    "iso:country":"BE",
    "sg:address":"Rue De Mettet 9",
    "sg:city":"Florennes",
    "sg:classifiers":[
        {
            "category":"Cafe",
            "type":"Food & Drink"
        }
    ],
    "sg:phone":"+32 71 68 75 84",
    "sg:postcode":"5620",
    "sg:province":"Namur",
    "sg:tags":[
        "caf\u00e9s"
    ],
    "wof:name":"Caf\u00c9 Le Manhattan",
    "wof:placetype":"venue"
},
  "geometry": {"coordinates":[4.604888916,50.2510643005],"type":"Point"}
}