{
  "type": "Feature",
  "properties": {
    "addr:full":"Botermarkt 30 Roeselare West-Vlaanderen 8800",
    "addr:housenumber":"30",
    "addr:postcode":"8800",
    "addr:street":"Botermarkt",
    "iso:country":"BE",
    "sg:address":"Botermarkt 30",
    "sg:city":"Roeselare",
    "sg:orig_category":"Location de logements sociaux. Construction de maisons",
    "sg:phone":"+32 51 20 12 83",
    "sg:postcode":"8800",
    "sg:province":"West-Vlaanderen",
    "wof:name":"De Mandel",
    "wof:placetype":"venue"
},
  "geometry": {"coordinates":[3.1256990433,50.9437713623],"type":"Point"}
}