{
  "type": "Feature",
  "properties": {
    "addr:full":"Treurwilgenstraat 9 Gent (mariakerke) Oost-Vlaanderen 9030",
    "addr:housenumber":"9",
    "addr:postcode":"9030",
    "addr:street":"Treurwilgenstraat",
    "iso:country":"BE",
    "sg:address":"Treurwilgenstraat 9",
    "sg:city":"Gent (mariakerke)",
    "sg:classifiers":[
        {
            "category":"Health Services",
            "subcategory":"Health Practitioner",
            "type":"Services"
        }
    ],
    "sg:phone":"+32 9 226 10 43",
    "sg:postcode":"9030",
    "sg:province":"Oost-Vlaanderen",
    "sg:tags":[
        "physiotherapist"
    ],
    "wof:name":"Soens M",
    "wof:placetype":"venue"
},
  "geometry": {"coordinates":[3.7008469105,51.0763053894],"type":"Point"}
}