{
  "type": "Feature",
  "properties": {
    "addr:full":"Rue De L'abondance 2-4 Bruxelles (saint-josse-ten-noode) Bruxelles-Capitale 1210",
    "addr:housenumber":"2-4",
    "addr:postcode":"1210",
    "addr:street":"Rue De L'Abondance",
    "iso:country":"BE",
    "sg:address":"Rue De L'abondance 2-4",
    "sg:city":"Bruxelles (saint-josse-ten-noode)",
    "sg:classifiers":[
        {
            "category":"Shopping",
            "subcategory":"Clothing, Apparel, & Fashions",
            "type":"Retail Goods"
        }
    ],
    "sg:phone":"+32 2 218 75 77",
    "sg:postcode":"1210",
    "sg:province":"Bruxelles-Capitale",
    "sg:tags":[
        "-",
        "clothing",
        "child"
    ],
    "wof:name":"Papadopoulou Eudoxia",
    "wof:placetype":"venue"
},
  "geometry": {"coordinates":[4.3695449829,50.8529968262],"type":"Point"}
}