{
  "type": "Feature",
  "properties": {
    "iso:country":"BE",
    "sg:address":"Gouden-rivierlaan 73",
    "sg:city":"Kortrijk",
    "sg:orig_category":"Sportclubs",
    "sg:phone":"+32 56 35 11 04",
    "sg:postcode":"8500",
    "sg:province":"West-Vlaanderen",
    "wof:name":"Volley Team Kortrijk",
    "wof:placetype":"venue"
},
  "geometry": {"coordinates":[3.2719678879,50.8399124146],"type":"Point"}
}