{
  "type": "Feature",
  "properties": {
    "addr:full":"Beverensestraat 61 Ardooie West-Vlaanderen 8850",
    "addr:housenumber":"61",
    "addr:postcode":"8850",
    "addr:street":"Beverensestraat",
    "iso:country":"BE",
    "sg:address":"Beverensestraat 61",
    "sg:city":"Ardooie",
    "sg:orig_category":"Elektrische installaties voor woningen Loodgieterij, verwarming and sanitaire installaties",
    "sg:phone":"+32 51 74 46 83",
    "sg:postcode":"8850",
    "sg:province":"West-Vlaanderen",
    "wof:name":"Gabriel Gruyaert",
    "wof:placetype":"venue"
},
  "geometry": {"coordinates":[3.1819159985,50.9774703979],"type":"Point"}
}