{
  "type": "Feature",
  "properties": {
    "addr:full":"Rue Commandant Tilot 39 Namen (groot) Namur 5100",
    "addr:housenumber":"39",
    "addr:postcode":"5100",
    "addr:street":"Rue Commandant Tilot;Groot Namur",
    "iso:country":"BE",
    "sg:address":"Rue Commandant Tilot 39",
    "sg:city":"Namen (groot)",
    "sg:orig_category":"Supermarkten",
    "sg:phone":"+32 81 30 19 45",
    "sg:postcode":"5100",
    "sg:province":"Namur",
    "wof:name":"Colruyt",
    "wof:placetype":"venue"
},
  "geometry": {"coordinates":[4.8713750839,50.4566345215],"type":"Point"}
}