{
  "type": "Feature",
  "properties": {
    "addr:full":"Rue Du Moulin A Vent 11 Walcourt Namur 5650",
    "addr:housenumber":"11",
    "addr:postcode":"5650",
    "addr:street":"Rue Du Moulin A Vent",
    "iso:country":"BE",
    "sg:address":"Rue Du Moulin A Vent 11",
    "sg:city":"Walcourt",
    "sg:orig_category":"Woningbouw",
    "sg:phone":"+32 71 65 07 90",
    "sg:postcode":"5650",
    "sg:province":"Namur",
    "wof:name":"Baras",
    "wof:placetype":"venue"
},
  "geometry": {"coordinates":[4.4313349724,50.2514762878],"type":"Point"}
}