{
  "type": "Feature",
  "properties": {
    "addr:full":"Helvetiastraat 47 Koksijde West-Vlaanderen 8670",
    "addr:housenumber":"47",
    "addr:postcode":"8670",
    "addr:street":"Helvetiastraat",
    "iso:country":"BE",
    "sg:address":"Helvetiastraat 47",
    "sg:city":"Koksijde",
    "sg:classifiers":[
        {
            "category":"Government",
            "subcategory":"Office",
            "type":"Public Place"
        }
    ],
    "sg:phone":"+32 58 51 05 16",
    "sg:postcode":"8670",
    "sg:province":"West-Vlaanderen",
    "sg:tags":[
        "-",
        "tourism",
        "federation"
    ],
    "wof:name":"Meteo West-vlaanderen",
    "wof:placetype":"venue"
},
  "geometry": {"coordinates":[2.6413710117,51.106300354],"type":"Point"}
}