{
  "type": "Feature",
  "properties": {
    "iso:country":"BE",
    "sg:address":"Rue G\u00c9n\u00c9ral Borlon 9",
    "sg:city":"Erez\u00c9e",
    "sg:orig_category":"Pain, p\u00e2tisseries and confiseries",
    "sg:phone":"+32 86 47 71 02",
    "sg:postcode":"6997",
    "sg:province":"Luxembourg",
    "wof:name":"Maison Gosset-l\u00b4estinale",
    "wof:placetype":"venue"
},
  "geometry": {"coordinates":[5.5590190887,50.2914886475],"type":"Point"}
}