{
  "type": "Feature",
  "properties": {
    "addr:full":"Weerterweg 62 Bocholt Limburg 3950",
    "addr:housenumber":"62",
    "addr:postcode":"3950",
    "addr:street":"Weerterweg",
    "iso:country":"BE",
    "sg:address":"Weerterweg 62",
    "sg:city":"Bocholt",
    "sg:classifiers":[
        {
            "category":"Building & Trades",
            "subcategory":"Locksmith",
            "type":"Services"
        }
    ],
    "sg:phone":"+32 89 70 47 66",
    "sg:postcode":"3950",
    "sg:province":"Limburg",
    "sg:tags":[
        "material",
        "road"
    ],
    "wof:name":"Van Den Hurk R",
    "wof:placetype":"venue"
},
  "geometry": {"coordinates":[5.5961060524,51.1839408875],"type":"Point"}
}