{
  "type": "Feature",
  "properties": {
    "addr:full":"Kloosterstraat 28 Neerpelt Limburg 3910",
    "addr:housenumber":"28",
    "addr:postcode":"3910",
    "addr:street":"Kloosterstraat",
    "iso:country":"BE",
    "sg:address":"Kloosterstraat 28",
    "sg:city":"Neerpelt",
    "sg:classifiers":[
        {
            "category":"Restaurant",
            "type":"Food & Drink"
        }
    ],
    "sg:phone":"+32 11 80 38 83",
    "sg:postcode":"3910",
    "sg:province":"Limburg",
    "wof:name":"Tisi",
    "wof:placetype":"venue"
},
  "geometry": {"coordinates":[5.4339270592,51.2299118042],"type":"Point"}
}