{
  "type": "Feature",
  "properties": {
    "addr:full":"Rue G\u00c9rard 2 Soignies Hainaut 7061",
    "addr:housenumber":"2",
    "addr:postcode":"7061",
    "addr:street":"Rue Ge\u0301Rard",
    "iso:country":"BE",
    "sg:address":"Rue G\u00c9rard 2",
    "sg:city":"Soignies",
    "sg:orig_category":"Eleveurs de bovins",
    "sg:phone":"+32 65 72 81 02",
    "sg:postcode":"7061",
    "sg:province":"Hainaut",
    "wof:name":"J. Vanderhoudelingen",
    "wof:placetype":"venue"
},
  "geometry": {"coordinates":[4.0613861084,50.5264129639],"type":"Point"}
}