{
  "type": "Feature",
  "properties": {
    "iso:country":"BE",
    "sg:address":"Heurnestraat 241",
    "sg:city":"Oudenaarde",
    "sg:orig_category":"Landmeters",
    "sg:phone":"+32 55 31 20 99",
    "sg:postcode":"9700",
    "sg:province":"Oost-Vlaanderen",
    "wof:name":"Lucien De Temmerman",
    "wof:placetype":"venue"
},
  "geometry": {"coordinates":[3.6290121078,50.8836975098],"type":"Point"}
}