{
  "type": "Feature",
  "properties": {
    "addr:full":"Uylenbroekstraat 4 Sint-pieters-leeuw Vlaams-Brabant 1600",
    "addr:housenumber":"4",
    "addr:postcode":"1600",
    "addr:street":"Uylenbroekstraat",
    "iso:country":"BE",
    "sg:address":"Uylenbroekstraat 4",
    "sg:city":"Sint-pieters-leeuw",
    "sg:classifiers":[
        {
            "category":"Home & Garden",
            "subcategory":"Home Furnishings",
            "type":"Retail Goods"
        }
    ],
    "sg:phone":"+32 2 344 58 05",
    "sg:postcode":"1600",
    "sg:province":"Vlaams-Brabant",
    "sg:tags":[
        "decorative",
        "lighting",
        "system"
    ],
    "wof:name":"Moonlight Design S.a.",
    "wof:placetype":"venue"
},
  "geometry": {"coordinates":[4.2521910667,50.763343811],"type":"Point"}
}