{
  "type": "Feature",
  "properties": {
    "addr:full":"Gasstraat 22 Roeselare West-Vlaanderen 8800",
    "addr:housenumber":"22",
    "addr:postcode":"8800",
    "addr:street":"Gasstraat",
    "iso:country":"BE",
    "sg:address":"Gasstraat 22",
    "sg:city":"Roeselare",
    "sg:orig_category":"Animations diverses",
    "sg:phone":"+32 51 22 02 29",
    "sg:postcode":"8800",
    "sg:province":"West-Vlaanderen",
    "wof:name":"Piet Depovere",
    "wof:placetype":"venue"
},
  "geometry": {"coordinates":[3.1307389736,50.9465370178],"type":"Point"}
}