{
  "type": "Feature",
  "properties": {
    "addr:full":"Chauss\u00c9e De Bruxelles 64 Charleroi Hainaut 6020",
    "addr:housenumber":"64",
    "addr:postcode":"6020",
    "addr:street":"Chausse\u0301E De Bruxelles;Hainaut",
    "iso:country":"BE",
    "sg:address":"Chauss\u00c9e De Bruxelles 64",
    "sg:city":"Charleroi",
    "sg:orig_category":"Services de s\u00e9curit\u00e9 and entreprises de gardiennage. Installation \u00e9lectrique industrielle",
    "sg:phone":"+32 71 33 45 00",
    "sg:postcode":"6020",
    "sg:province":"Hainaut",
    "wof:name":"Alarmtronic",
    "wof:placetype":"venue"
},
  "geometry": {"coordinates":[4.4378871918,50.4149703979],"type":"Point"}
}