{
  "type": "Feature",
  "properties": {
    "iso:country":"BE",
    "sg:address":"Heiligenbornstraat 59",
    "sg:city":"Nieuwerkerken",
    "sg:orig_category":"Producteurs de fruits",
    "sg:phone":"+32 11 31 22 36",
    "sg:postcode":"3850",
    "sg:province":"Limburg",
    "wof:name":"Maurice Robben",
    "wof:placetype":"venue"
},
  "geometry": {"coordinates":[5.2479090691,50.8750152588],"type":"Point"}
}