{
  "type": "Feature",
  "properties": {
    "iso:country":"BE",
    "sg:address":"Korte Kopstraat 42",
    "sg:city":"Schoten",
    "sg:orig_category":"Vertalers and tolken",
    "sg:phone":"+32 475 70 18 85",
    "sg:postcode":"2900",
    "sg:province":"Antwerpen",
    "wof:name":"De Busschere W. Cbtip/bkvtf",
    "wof:placetype":"venue"
},
  "geometry": {"coordinates":[4.4937019348,51.2563514709],"type":"Point"}
}