{
  "type": "Feature",
  "properties": {
    "iso:country":"BE",
    "sg:address":"De Zippe 19",
    "sg:city":"Merchtem",
    "sg:classifiers":[
        {
            "category":"Professional",
            "subcategory":"Accounting & Tax Preparation",
            "type":"Services"
        }
    ],
    "sg:phone":"+32 52 37 26 09",
    "sg:postcode":"1785",
    "sg:province":"Vlaams-Brabant",
    "sg:tags":[
        "bookkeeper"
    ],
    "wof:name":"Bogaerts R",
    "wof:placetype":"venue"
},
  "geometry": {"coordinates":[4.2324180603,50.9528694153],"type":"Point"}
}