{
  "type": "Feature",
  "properties": {
    "iso:country":"BE",
    "sg:address":"Grote Markt 1",
    "sg:city":"Veurne",
    "sg:orig_category":"Biblioth\u00e8ques and archives publiques",
    "sg:phone":"+32 58 33 05 81",
    "sg:postcode":"8630",
    "sg:province":"West-Vlaanderen",
    "wof:name":"Gemeentelijke P.o.b.",
    "wof:placetype":"venue"
},
  "geometry": {"coordinates":[2.6626210213,51.0726280212],"type":"Point"}
}