{
  "type": "Feature",
  "properties": {
    "addr:full":"Rue Camille Busschaert 40 Mouscron Hainaut 7700",
    "addr:housenumber":"40",
    "addr:postcode":"7700",
    "addr:street":"Rue Camille Busschaert",
    "iso:country":"BE",
    "sg:address":"Rue Camille Busschaert 40",
    "sg:city":"Mouscron",
    "sg:classifiers":[
        {
            "category":"Health Services",
            "subcategory":"Doctor",
            "type":"Services"
        }
    ],
    "sg:phone":"+32 56 34 71 05",
    "sg:postcode":"7700",
    "sg:province":"Hainaut",
    "sg:tags":[
        "medicinephysicians",
        "surgeon"
    ],
    "wof:name":"Debruycker J",
    "wof:placetype":"venue"
},
  "geometry": {"coordinates":[3.2188789845,50.7441978455],"type":"Point"}
}