{
  "type": "Feature",
  "properties": {
    "addr:full":"Chemin Du Pic Au Vent 25 Ath Hainaut 7822",
    "addr:housenumber":"25",
    "addr:postcode":"7822",
    "addr:street":"Chemin Du Pic Au Vent",
    "iso:country":"BE",
    "sg:address":"Chemin Du Pic Au Vent 25",
    "sg:city":"Ath",
    "sg:orig_category":"V\u00e9hicules automobiles. Entretien and r\u00e9parations de voitures",
    "sg:phone":"+32 68 28 11 01",
    "sg:postcode":"7822",
    "sg:province":"Hainaut",
    "wof:name":"O B Internationale",
    "wof:placetype":"venue"
},
  "geometry": {"coordinates":[3.8452620506,50.6482391357],"type":"Point"}
}