{
  "type": "Feature",
  "properties": {
    "iso:country":"BE",
    "sg:address":"Centrumlaan 42",
    "sg:city":"Ninove",
    "sg:classifiers":[
        {
            "category":"Shopping",
            "subcategory":"Music",
            "type":"Retail Goods"
        }
    ],
    "sg:phone":"+32 54 32 62 59",
    "sg:postcode":"9400",
    "sg:province":"Oost-Vlaanderen",
    "sg:tags":[
        "-",
        "cd's",
        "recorded",
        "cassette"
    ],
    "wof:name":"La Folie Du Vinyl",
    "wof:placetype":"venue"
},
  "geometry": {"coordinates":[4.0213398933,50.8344306946],"type":"Point"}
}