{
  "type": "Feature",
  "properties": {
    "addr:full":"Stationsstraat 15 Aalst Oost-Vlaanderen 9300",
    "addr:housenumber":"15",
    "addr:postcode":"9300",
    "addr:street":"Stationsstraat",
    "iso:country":"BE",
    "sg:address":"Stationsstraat 15",
    "sg:city":"Aalst",
    "sg:classifiers":[
        {
            "category":"Health Services",
            "subcategory":"Doctor",
            "type":"Services"
        }
    ],
    "sg:phone":"+32 53 21 20 44",
    "sg:postcode":"9300",
    "sg:province":"Oost-Vlaanderen",
    "sg:tags":[
        "medicinephysicians",
        "surgeon"
    ],
    "wof:name":"Bamelis Mia",
    "wof:placetype":"venue"
},
  "geometry": {"coordinates":[4.0376520157,50.9416160583],"type":"Point"}
}