{
  "type": "Feature",
  "properties": {
    "addr:full":"Meerdaalweg 2 Oud-heverlee Vlaams-Brabant 3050",
    "addr:housenumber":"2",
    "addr:postcode":"3050",
    "addr:street":"Meerdaalweg",
    "iso:country":"BE",
    "sg:address":"Meerdaalweg 2",
    "sg:city":"Oud-heverlee",
    "sg:classifiers":[
        {
            "category":"Sports & Exercise",
            "subcategory":"Sports Center",
            "type":"Entertainment"
        }
    ],
    "sg:phone":"+32 16 47 75 96",
    "sg:postcode":"3050",
    "sg:province":"Vlaams-Brabant",
    "sg:tags":[
        "terrain",
        "hors",
        "de",
        "installation",
        "sportifs"
    ],
    "wof:name":"Meerdaalhof",
    "wof:placetype":"venue"
},
  "geometry": {"coordinates":[4.6673808098,50.8225669861],"type":"Point"}
}