{
  "type": "Feature",
  "properties": {
    "addr:full":"Schrieksebaan 41 Tremelo Vlaams-Brabant 3120",
    "addr:housenumber":"41",
    "addr:postcode":"3120",
    "addr:street":"Schrieksebaan",
    "iso:country":"BE",
    "sg:address":"Schrieksebaan 41",
    "sg:city":"Tremelo",
    "sg:orig_category":"Instituts de beaut\u00e9",
    "sg:phone":"+32 16 53 09 31",
    "sg:postcode":"3120",
    "sg:province":"Vlaams-Brabant",
    "wof:name":"Prestige",
    "wof:placetype":"venue"
},
  "geometry": {"coordinates":[4.705742836,50.9925308228],"type":"Point"}
}