{
  "type": "Feature",
  "properties": {
    "addr:full":"Rue Kelle 121 Bruxelles (woluwe-saint-pierre) Bruxelles-Capitale 1150",
    "addr:housenumber":"121",
    "addr:postcode":"1150",
    "addr:street":"Rue Kelle",
    "iso:country":"BE",
    "sg:address":"Rue Kelle 121",
    "sg:city":"Bruxelles (woluwe-saint-pierre)",
    "sg:classifiers":[
        {
            "category":"Building & Trades",
            "subcategory":"Landscaping Services",
            "type":"Services"
        }
    ],
    "sg:phone":"+32 2 762 80 73",
    "sg:postcode":"1150",
    "sg:province":"Bruxelles-Capitale",
    "sg:tags":[
        "gardening",
        "garden",
        "maintenance"
    ],
    "wof:name":"Serre Outil (la)",
    "wof:placetype":"venue"
},
  "geometry": {"coordinates":[4.4371991158,50.8319244385],"type":"Point"}
}