{
  "type": "Feature",
  "properties": {
    "addr:full":"All\u00e9e Des Coquelicots 13 Vis\u00e9 Li\u00e8ge 4600",
    "addr:housenumber":"13",
    "addr:postcode":"4600",
    "addr:street":"Alle\u0301E Des Coquelicots",
    "iso:country":"BE",
    "sg:address":"All\u00e9e Des Coquelicots 13",
    "sg:city":"Vis\u00e9",
    "sg:classifiers":[
        {
            "category":"Building & Trades",
            "subcategory":"Electrical",
            "type":"Services"
        }
    ],
    "sg:phone":"+32 4 379 76 54",
    "sg:postcode":"4600",
    "sg:province":"Li\u00e8ge",
    "sg:tags":[
        "electric",
        "-",
        "housewiring",
        "contractor"
    ],
    "wof:name":"Tock Ch",
    "wof:placetype":"venue"
},
  "geometry": {"coordinates":[5.7041549683,50.7335548401],"type":"Point"}
}