{
  "type": "Feature",
  "properties": {
    "addr:full":"Rue Du Vieux H\u00catre 15 Waimes Li\u00e8ge 4950",
    "addr:housenumber":"15",
    "addr:postcode":"4950",
    "addr:street":"Rue Du Vieux He\u0302Tre",
    "iso:country":"BE",
    "sg:address":"Rue Du Vieux H\u00catre 15",
    "sg:city":"Waimes",
    "sg:orig_category":"Woningbouw",
    "sg:phone":"+32 80 44 43 08",
    "sg:postcode":"4950",
    "sg:province":"Li\u00e8ge",
    "wof:name":"Patrick Peiffer",
    "wof:placetype":"venue"
},
  "geometry": {"coordinates":[6.1233820915,50.4672889709],"type":"Point"}
}