{
  "type": "Feature",
  "properties": {
    "addr:full":"Pauwelslei 166 Brasschaat Antwerpen 2930",
    "addr:housenumber":"166",
    "addr:postcode":"2930",
    "addr:street":"Pauwelslei",
    "iso:country":"BE",
    "sg:address":"Pauwelslei 166",
    "sg:city":"Brasschaat",
    "sg:classifiers":[
        {
            "category":"Manufacturing",
            "subcategory":"Furniture",
            "type":"Manufacturing & Wholesale Goods"
        }
    ],
    "sg:phone":"+32 3 651 57 22",
    "sg:postcode":"2930",
    "sg:province":"Antwerpen",
    "sg:tags":[
        "armchair",
        "-"
    ],
    "wof:name":"Van Minnebruggen & Meyvis Bvba",
    "wof:placetype":"venue"
},
  "geometry": {"coordinates":[4.515335083,51.2995491028],"type":"Point"}
}