{
  "type": "Feature",
  "properties": {
    "addr:full":"Heilig-hartlaan 25 Oostende West-Vlaanderen 8400",
    "addr:housenumber":"25",
    "addr:postcode":"8400",
    "addr:street":"Heilig-Hartlaan",
    "iso:country":"BE",
    "sg:address":"Heilig-hartlaan 25",
    "sg:city":"Oostende",
    "sg:orig_category":"Pharmaciens",
    "sg:phone":"+32 59 70 13 38",
    "sg:postcode":"8400",
    "sg:province":"West-Vlaanderen",
    "wof:name":"Apotheek Tampere",
    "wof:placetype":"venue"
},
  "geometry": {"coordinates":[2.9048190117,51.221698761],"type":"Point"}
}