{
  "type": "Feature",
  "properties": {
    "addr:full":"Verboekt 71 Herenthout Antwerpen 2270",
    "addr:housenumber":"71",
    "addr:postcode":"2270",
    "addr:street":"Verboekt",
    "iso:country":"BE",
    "sg:address":"Verboekt 71",
    "sg:city":"Herenthout",
    "sg:orig_category":"Travaux de finition and nettoyage de b\u00e2timents. Rev\u00eatements pour sols and murs. Charpentes and couve",
    "sg:phone":"+32 14 48 94 10",
    "sg:postcode":"2270",
    "sg:province":"Antwerpen",
    "wof:name":"Aldyma",
    "wof:placetype":"venue"
},
  "geometry": {"coordinates":[4.7550439835,51.1406288147],"type":"Point"}
}