{
  "type": "Feature",
  "properties": {
    "iso:country":"BE",
    "sg:address":"Luikersteenweg 197",
    "sg:city":"Hasselt",
    "sg:classifiers":[
        {
            "category":"Insurance",
            "subcategory":"Insurance Agent",
            "type":"Services"
        }
    ],
    "sg:phone":"+32 11 28 46 66",
    "sg:postcode":"3500",
    "sg:province":"Limburg",
    "sg:tags":[
        "broker"
    ],
    "wof:name":"Hamaver Nv",
    "wof:placetype":"venue"
},
  "geometry": {"coordinates":[5.3466200829,50.9167633057],"type":"Point"}
}