{
  "type": "Feature",
  "properties": {
    "addr:full":"Kattestraat 3 Zedelgem (loppem) West-Vlaanderen 8210",
    "addr:housenumber":"3",
    "addr:postcode":"8210",
    "addr:street":"Kattestraat",
    "iso:country":"BE",
    "sg:address":"Kattestraat 3",
    "sg:city":"Zedelgem (loppem)",
    "sg:classifiers":[
        {
            "category":"Home & Garden",
            "subcategory":"Furniture",
            "type":"Retail Goods"
        }
    ],
    "sg:phone":"+32 50 82 74 04",
    "sg:postcode":"8210",
    "sg:province":"West-Vlaanderen",
    "sg:tags":[
        "used",
        "-"
    ],
    "wof:name":"De Brocanteling",
    "wof:placetype":"venue"
},
  "geometry": {"coordinates":[3.1458399296,51.1376457214],"type":"Point"}
}