{
  "type": "Feature",
  "properties": {
    "iso:country":"BE",
    "sg:address":"Molenstraat 34",
    "sg:city":"Sint-katelijne-waver",
    "sg:orig_category":"Producteurs de l\u00e9gumes",
    "sg:phone":"+32 15 75 56 18",
    "sg:postcode":"2861",
    "sg:province":"Antwerpen",
    "wof:name":"Gabrielle Vertommen",
    "wof:placetype":"venue"
},
  "geometry": {"coordinates":[4.5840229988,51.0629119873],"type":"Point"}
}