{
  "type": "Feature",
  "properties": {
    "iso:country":"BE",
    "sg:address":"Guido Gezellestraat 65",
    "sg:city":"Boom",
    "sg:orig_category":"Bijouteries and horlogeries",
    "sg:phone":"+32 3 844 26 56",
    "sg:postcode":"2850",
    "sg:province":"Antwerpen",
    "wof:name":"Michele Lariviere",
    "wof:placetype":"venue"
},
  "geometry": {"coordinates":[4.3727669716,51.096786499],"type":"Point"}
}