{
  "type": "Feature",
  "properties": {
    "addr:full":"Rue Du Polich\u00e8ne 10 Morlanwelz (morlanwelz-mariemont) Hainaut 7140",
    "addr:housenumber":"10",
    "addr:postcode":"7140",
    "addr:street":"Rue Du Poliche\u0300Ne",
    "iso:country":"BE",
    "sg:address":"Rue Du Polich\u00e8ne 10",
    "sg:city":"Morlanwelz (morlanwelz-mariemont)",
    "sg:classifiers":[
        {
            "category":"Health Services",
            "subcategory":"Doctor",
            "type":"Services"
        }
    ],
    "sg:phone":"+32 64 44 69 80",
    "sg:postcode":"7140",
    "sg:province":"Hainaut",
    "sg:tags":[
        "medicinephysicians",
        "surgeon"
    ],
    "wof:name":"De Bodt G\u00e9raud",
    "wof:placetype":"venue"
},
  "geometry": {"coordinates":[4.243678093,50.4543075562],"type":"Point"}
}