{
  "type": "Feature",
  "properties": {
    "iso:country":"BE",
    "sg:address":"Chauss\u00e9e De Bracquegnies 123",
    "sg:city":"La Louvi\u00e8re (houdeng-aimeries)",
    "sg:classifiers":[
        {
            "category":"Autos & Motor Vehicles",
            "subcategory":"Auto Supplies",
            "type":"Retail Goods"
        }
    ],
    "sg:phone":"+32 64 67 75 80",
    "sg:postcode":"7110",
    "sg:province":"Hainaut",
    "sg:tags":[
        "automobile",
        "alarm",
        "-",
        "system"
    ],
    "wof:name":"Install'alarm",
    "wof:placetype":"venue"
},
  "geometry": {"coordinates":[4.1505050659,50.4826698303],"type":"Point"}
}