{
  "type": "Feature",
  "properties": {
    "iso:country":"BE",
    "sg:address":"Rue De L'universit\u00c9 45",
    "sg:city":"Li\u00c8ge",
    "sg:orig_category":"Art and fournitures artistiques",
    "sg:phone":"+32 4 223 52 87",
    "sg:postcode":"4000",
    "sg:province":"Li\u00e8ge",
    "wof:name":"La Palette D'art",
    "wof:placetype":"venue"
},
  "geometry": {"coordinates":[5.5746068954,50.641330719],"type":"Point"}
}