{
  "type": "Feature",
  "properties": {
    "iso:country":"BE",
    "sg:address":"Place De Baisieux 154",
    "sg:city":"Qui\u00e9vrain (baisieux)",
    "sg:classifiers":[
        {
            "category":"Health Services",
            "subcategory":"Doctor",
            "type":"Services"
        }
    ],
    "sg:phone":"+32 65 43 15 25",
    "sg:postcode":"7380",
    "sg:province":"Hainaut",
    "sg:tags":[
        "medicinephysicians",
        "surgeon"
    ],
    "wof:name":"Dhenin M",
    "wof:placetype":"venue"
},
  "geometry": {"coordinates":[3.6963839531,50.3874778748],"type":"Point"}
}