{
  "type": "Feature",
  "properties": {
    "iso:country":"BE",
    "sg:address":"Iers-kruisstraat 65",
    "sg:city":"Riemst",
    "sg:orig_category":"Chemicali\u00ebn Gh Drogisterijen",
    "sg:phone":"+32 12 45 50 86",
    "sg:postcode":"3770",
    "sg:province":"Limburg",
    "wof:name":"Jansen",
    "wof:placetype":"venue"
},
  "geometry": {"coordinates":[5.6171159744,50.8290367126],"type":"Point"}
}