{
  "type": "Feature",
  "properties": {
    "addr:full":"Groenstraat 16 Hechtel-eksel Limburg 3941",
    "addr:housenumber":"16",
    "addr:postcode":"3941",
    "addr:street":"Groenstraat",
    "iso:country":"BE",
    "sg:address":"Groenstraat 16",
    "sg:city":"Hechtel-eksel",
    "sg:orig_category":"Advocaten and juridische adviseurs",
    "sg:phone":"+32 11 73 48 54",
    "sg:postcode":"3941",
    "sg:province":"Limburg",
    "wof:name":"Marion Treunen",
    "wof:placetype":"venue"
},
  "geometry": {"coordinates":[5.3922519684,51.1559562683],"type":"Point"}
}