{
  "type": "Feature",
  "properties": {
    "iso:country":"BE",
    "sg:address":"Rue De Pontisse 51",
    "sg:city":"Oupeye",
    "sg:classifiers":[
        {
            "category":"Personal",
            "subcategory":"Beauty Salon",
            "type":"Services"
        }
    ],
    "sg:phone":"+32 4 240 34 74",
    "sg:postcode":"4683",
    "sg:province":"Li\u00e8ge",
    "sg:tags":[
        "de",
        "coiffure"
    ],
    "wof:name":"Valerie Coupe Tif- Mobile",
    "wof:placetype":"venue"
},
  "geometry": {"coordinates":[5.6495499611,50.6958198547],"type":"Point"}
}