{
  "type": "Feature",
  "properties": {
    "addr:full":"Huart Hamoirlaan 111 Schaarbeek/schaerbeek Bruxelles-Capitale 1030",
    "addr:housenumber":"111",
    "addr:postcode":"1030",
    "addr:street":"Huart Hamoirlaan",
    "iso:country":"BE",
    "sg:address":"Huart Hamoirlaan 111",
    "sg:city":"Schaarbeek/schaerbeek",
    "sg:orig_category":"Diverse grafische activiteiten",
    "sg:phone":"+32 2 216 07 14",
    "sg:postcode":"1030",
    "sg:province":"Bruxelles-Capitale",
    "wof:name":"Bureau Co And Co",
    "wof:placetype":"venue"
},
  "geometry": {"coordinates":[4.3846149445,50.8746795654],"type":"Point"}
}