{
  "type": "Feature",
  "properties": {
    "iso:country":"BE",
    "sg:address":"Route De L'eau Rouge 2b",
    "sg:city":"Stavelot",
    "sg:classifiers":[
        {
            "category":"Retail",
            "subcategory":"Auto Repair",
            "type":"Services"
        }
    ],
    "sg:phone":"+32 80 86 28 35",
    "sg:postcode":"4970",
    "sg:province":"Li\u00e8ge",
    "sg:tags":[
        "garage"
    ],
    "wof:name":"Balci F Garage",
    "wof:placetype":"venue"
},
  "geometry": {"coordinates":[6.0294508934,50.4262580872],"type":"Point"}
}