{
  "type": "Feature",
  "properties": {
    "iso:country":"BE",
    "sg:address":"Rue De Lodelinsart 129",
    "sg:city":"Charleroi (jumet)",
    "sg:classifiers":[
        {
            "category":"Personal",
            "subcategory":"Beauty Salon",
            "type":"Services"
        }
    ],
    "sg:phone":"+32 71 35 40 16",
    "sg:postcode":"6040",
    "sg:province":"Hainaut",
    "sg:tags":[
        "lady",
        "-",
        "hairdressing"
    ],
    "wof:name":"Imagina'tifs",
    "wof:placetype":"venue"
},
  "geometry": {"coordinates":[4.450220108,50.4385299683],"type":"Point"}
}