{
  "type": "Feature",
  "properties": {
    "iso:country":"BE",
    "sg:address":"Everweg 13",
    "sg:city":"Vosselaar",
    "sg:classifiers":[
        {
            "category":"Arena",
            "subcategory":"Sports Club",
            "type":"Entertainment"
        }
    ],
    "sg:phone":"+32 14 61 36 53",
    "sg:postcode":"2350",
    "sg:province":"Antwerpen",
    "sg:tags":[
        "de"
    ],
    "wof:name":"W.s.c. De Linde",
    "wof:placetype":"venue"
},
  "geometry": {"coordinates":[4.8713212013,51.3047370911],"type":"Point"}
}