{
  "type": "Feature",
  "properties": {
    "addr:full":"Schaluin 30 Aarschot Vlaams-Brabant 3200",
    "addr:housenumber":"30",
    "addr:postcode":"3200",
    "addr:street":"Schaluin",
    "iso:country":"BE",
    "sg:address":"Schaluin 30",
    "sg:city":"Aarschot",
    "sg:classifiers":[
        {
            "category":"Cafe",
            "type":"Food & Drink"
        }
    ],
    "sg:phone":"+32 16 69 48 68",
    "sg:postcode":"3200",
    "sg:province":"Vlaams-Brabant",
    "sg:tags":[
        "snack-bars"
    ],
    "wof:name":"De Knabbel",
    "wof:placetype":"venue"
},
  "geometry": {"coordinates":[4.8405981064,50.9896736145],"type":"Point"}
}