{
  "type": "Feature",
  "properties": {
    "iso:country":"BE",
    "sg:address":"Rue De Marchienne 115",
    "sg:city":"Thuin",
    "sg:classifiers":[
        {
            "category":"Personal",
            "subcategory":"Beauty Salon",
            "type":"Services"
        }
    ],
    "sg:phone":"+32 71 43 65 13",
    "sg:postcode":"6534",
    "sg:province":"Hainaut",
    "sg:tags":[
        "de",
        "coiffure"
    ],
    "wof:name":"Camila Da Silva",
    "wof:placetype":"venue"
},
  "geometry": {"coordinates":[4.3602190018,50.3435249329],"type":"Point"}
}