{
  "type": "Feature",
  "properties": {
    "iso:country":"BE",
    "sg:address":"Westzavelland 41",
    "sg:city":"Willebroek",
    "sg:classifiers":[
        {
            "category":"Professional",
            "subcategory":"Art Services",
            "type":"Services"
        }
    ],
    "sg:phone":"+32 3 866 03 99",
    "sg:postcode":"2830",
    "sg:province":"Antwerpen",
    "sg:tags":[
        "photographer"
    ],
    "wof:name":"Merckx S",
    "wof:placetype":"venue"
},
  "geometry": {"coordinates":[4.3604412079,51.0545806885],"type":"Point"}
}