{
  "type": "Feature",
  "properties": {
    "iso:country":"BE",
    "sg:address":"Rue Neuve 30",
    "sg:city":"Stavelot",
    "sg:classifiers":[
        {
            "category":"Health Services",
            "subcategory":"Nursing And Care Facility",
            "type":"Services"
        }
    ],
    "sg:phone":"+32 80 88 08 80",
    "sg:postcode":"4970",
    "sg:province":"Li\u00e8ge",
    "sg:tags":[
        "home"
    ],
    "wof:name":"Sacodo",
    "wof:placetype":"venue"
},
  "geometry": {"coordinates":[5.9273619652,50.3932151794],"type":"Point"}
}