{
  "type": "Feature",
  "properties": {
    "addr:full":"Rue La Roche 6 Lens Hainaut 7870",
    "addr:housenumber":"6",
    "addr:postcode":"7870",
    "addr:street":"Rue La Roche",
    "iso:country":"BE",
    "sg:address":"Rue La Roche 6",
    "sg:city":"Lens",
    "sg:orig_category":"Eleveurs de bovins",
    "sg:phone":"+32 65 22 97 49",
    "sg:postcode":"7870",
    "sg:province":"Hainaut",
    "wof:name":"Vercruysse",
    "wof:placetype":"venue"
},
  "geometry": {"coordinates":[3.927421093,50.577419281],"type":"Point"}
}