{
  "type": "Feature",
  "properties": {
    "iso:country":"BE",
    "sg:address":"Bloemendalestraat 42",
    "sg:city":"Beernem",
    "sg:classifiers":[
        {
            "category":"Real Estate",
            "subcategory":"Real Estate Services",
            "type":"Services"
        }
    ],
    "sg:phone":"+32 50 79 05 88",
    "sg:postcode":"8730",
    "sg:province":"West-Vlaanderen",
    "wof:name":"Kantoor Vermeyen Bvba",
    "wof:placetype":"venue"
},
  "geometry": {"coordinates":[3.338850975,51.1411361694],"type":"Point"}
}