{
  "type": "Feature",
  "properties": {
    "addr:full":"Avenue De Roodebeek 80 Schaarbeek/schaerbeek Bruxelles-Capitale 1030",
    "addr:housenumber":"80",
    "addr:postcode":"1030",
    "addr:street":"Avenue De Roodebeek",
    "iso:country":"BE",
    "sg:address":"Avenue De Roodebeek 80",
    "sg:city":"Schaarbeek/schaerbeek",
    "sg:orig_category":"Instituts de beaut\u00e9",
    "sg:phone":"+32 2 733 83 86",
    "sg:postcode":"1030",
    "sg:province":"Bruxelles-Capitale",
    "wof:name":"Institut Nina",
    "wof:placetype":"venue"
},
  "geometry": {"coordinates":[4.4003429413,50.8484840393],"type":"Point"}
}