{
  "type": "Feature",
  "properties": {
    "addr:full":"Rue Saint-antoine 1 Soignies Hainaut 7061",
    "addr:housenumber":"1",
    "addr:postcode":"7061",
    "addr:street":"Rue Saint-Antoine",
    "iso:country":"BE",
    "sg:address":"Rue Saint-antoine 1",
    "sg:city":"Soignies",
    "sg:classifiers":[
        {
            "category":"Personal",
            "subcategory":"Beauty Salon",
            "type":"Services"
        }
    ],
    "sg:phone":"+32 65 72 36 12",
    "sg:postcode":"7061",
    "sg:province":"Hainaut",
    "sg:tags":[
        "de",
        "coiffure"
    ],
    "wof:name":"Coiffure Liliane",
    "wof:placetype":"venue"
},
  "geometry": {"coordinates":[4.0098509789,50.5140571594],"type":"Point"}
}