{
  "type": "Feature",
  "properties": {
    "addr:full":"Rue Soiron-centre 81 Pepinster (soiron) Li\u00e8ge 4861",
    "addr:housenumber":"81",
    "addr:postcode":"4861",
    "addr:street":"Rue Soiron-Centre;Soiron",
    "iso:country":"BE",
    "sg:address":"Rue Soiron-centre 81",
    "sg:city":"Pepinster (soiron)",
    "sg:classifiers":[
        {
            "category":"Professional",
            "subcategory":"Accounting & Tax Preparation",
            "type":"Services"
        }
    ],
    "sg:phone":"+32 87 46 93 38",
    "sg:postcode":"4861",
    "sg:province":"Li\u00e8ge",
    "sg:tags":[
        "accountant"
    ],
    "wof:name":"Bertrand J",
    "wof:placetype":"venue"
},
  "geometry": {"coordinates":[5.7904658318,50.5915985107],"type":"Point"}
}