{
  "type": "Feature",
  "properties": {
    "iso:country":"BE",
    "sg:address":"Emblemsesteenweg 50",
    "sg:city":"Nijlen",
    "sg:orig_category":"Epiceries",
    "sg:phone":"+32 3 480 12 53",
    "sg:postcode":"2560",
    "sg:province":"Antwerpen",
    "wof:name":"\u00b4t Bakkertje",
    "wof:placetype":"venue"
},
  "geometry": {"coordinates":[4.615363121,51.1536026001],"type":"Point"}
}