{
  "type": "Feature",
  "properties": {
    "addr:full":"Rue Fran\u00c7ois Dewiest 11 Charleroi Hainaut 6040",
    "addr:housenumber":"11",
    "addr:postcode":"6040",
    "addr:street":"Rue Franc\u0327Ois Dewiest;Hainaut",
    "iso:country":"BE",
    "sg:address":"Rue Fran\u00c7ois Dewiest 11",
    "sg:city":"Charleroi",
    "sg:orig_category":"Boekhouders",
    "sg:phone":"+32 71 35 82 13",
    "sg:postcode":"6040",
    "sg:province":"Hainaut",
    "wof:name":"Claude Leclercq",
    "wof:placetype":"venue"
},
  "geometry": {"coordinates":[4.4200220108,50.4387931824],"type":"Point"}
}