{
  "type": "Feature",
  "properties": {
    "addr:full":"Goossensvest 11 Tienen Vlaams-Brabant 3300",
    "addr:housenumber":"11",
    "addr:postcode":"3300",
    "addr:street":"Goossensvest",
    "iso:country":"BE",
    "sg:address":"Goossensvest 11",
    "sg:city":"Tienen",
    "sg:orig_category":"Overheidsdiensten",
    "sg:phone":"+32 16 80 05 16",
    "sg:postcode":"3300",
    "sg:province":"Vlaams-Brabant",
    "wof:name":"Admin. Directe Belast.",
    "wof:placetype":"venue"
},
  "geometry": {"coordinates":[4.9338698387,50.8044700623],"type":"Point"}
}