{
  "type": "Feature",
  "properties": {
    "addr:full":"Rue D'offagne 48 Paliseul Luxembourg 6850",
    "addr:housenumber":"48",
    "addr:postcode":"6850",
    "addr:street":"Rue D'Offagne",
    "iso:country":"BE",
    "sg:address":"Rue D'offagne 48",
    "sg:city":"Paliseul",
    "sg:classifiers":[
        {
            "category":"Professional",
            "subcategory":"Accounting & Tax Preparation",
            "type":"Services"
        }
    ],
    "sg:phone":"+32 61 53 36 33",
    "sg:postcode":"6850",
    "sg:province":"Luxembourg",
    "sg:tags":[
        "bookkeeper"
    ],
    "wof:name":"Lagalis J-p",
    "wof:placetype":"venue"
},
  "geometry": {"coordinates":[5.1488571167,49.8997268677],"type":"Point"}
}