{
  "type": "Feature",
  "properties": {
    "addr:full":"Evert Larockstraat 2 Antwerpen Antwerpen 2020",
    "addr:housenumber":"2",
    "addr:postcode":"2020",
    "addr:street":"Evert Larockstraat",
    "iso:country":"BE",
    "sg:address":"Evert Larockstraat 2",
    "sg:city":"Antwerpen",
    "sg:classifiers":[
        {
            "category":"Professional",
            "subcategory":"Testing Lab",
            "type":"Services"
        }
    ],
    "sg:phone":"+32 3 238 26 30",
    "sg:postcode":"2020",
    "sg:province":"Antwerpen",
    "sg:tags":[
        "chemist"
    ],
    "wof:name":"Apotheek Larockstraat Bvba",
    "wof:placetype":"venue"
},
  "geometry": {"coordinates":[4.3747181892,51.1929702759],"type":"Point"}
}