{
  "type": "Feature",
  "properties": {
    "addr:full":"Dronkaertstraat Menen (lauwe) West-Vlaanderen 8930",
    "addr:postcode":"8930",
    "addr:street":"Dronkaertstraat",
    "iso:country":"BE",
    "sg:address":"Dronkaertstraat",
    "sg:city":"Menen (lauwe)",
    "sg:classifiers":[
        {
            "category":"Retail",
            "subcategory":"Animal Services",
            "type":"Services"
        }
    ],
    "sg:phone":"+32 56 41 45 71",
    "sg:postcode":"8930",
    "sg:province":"West-Vlaanderen",
    "sg:tags":[
        "training",
        "dog"
    ],
    "wof:name":"De Trouwe Hond",
    "wof:placetype":"venue"
},
  "geometry": {"coordinates":[3.1636819839,50.7693557739],"type":"Point"}
}