{
  "type": "Feature",
  "properties": {
    "addr:full":"Oude Burg 2f Brugge West-Vlaanderen 8000",
    "addr:housenumber":"2f",
    "addr:postcode":"8000",
    "addr:street":"Oude Burg",
    "iso:country":"BE",
    "sg:address":"Oude Burg 2f",
    "sg:city":"Brugge",
    "sg:orig_category":"Non-Classified Establishments",
    "sg:phone":"+32 50 34 57 70",
    "sg:postcode":"8000",
    "sg:province":"West-Vlaanderen",
    "wof:name":"Pickery",
    "wof:placetype":"venue"
},
  "geometry": {"coordinates":[3.2252418995,51.2077522278],"type":"Point"}
}