{
  "type": "Feature",
  "properties": {
    "addr:full":"Passage Lemonnier 46 Li\u00c8ge Li\u00e8ge 4000",
    "addr:housenumber":"46",
    "addr:postcode":"4000",
    "addr:street":"Passage Lemonnier",
    "iso:country":"BE",
    "sg:address":"Passage Lemonnier 46",
    "sg:city":"Li\u00c8ge",
    "sg:classifiers":[
        {
            "category":"Communications",
            "subcategory":"Film & Video Production",
            "type":"Services"
        }
    ],
    "sg:phone":"+32 4 223 54 70",
    "sg:postcode":"4000",
    "sg:province":"Li\u00e8ge",
    "sg:tags":[
        "platen",
        "cassette",
        "cd's"
    ],
    "wof:name":"Etincel-musiques",
    "wof:placetype":"venue"
},
  "geometry": {"coordinates":[5.571313858,50.641872406],"type":"Point"}
}