{
  "type": "Feature",
  "properties": {
    "addr:full":"Oosthoekplein 1 Knokke-heist West-Vlaanderen 8300",
    "addr:housenumber":"1",
    "addr:postcode":"8300",
    "addr:street":"Oosthoekplein",
    "iso:country":"BE",
    "sg:address":"Oosthoekplein 1",
    "sg:city":"Knokke-heist",
    "sg:classifiers":[
        {
            "category":"Restaurant",
            "type":"Food & Drink"
        }
    ],
    "sg:phone":"+32 50 60 20 08",
    "sg:postcode":"8300",
    "sg:province":"West-Vlaanderen",
    "wof:name":"Tearoom Siska Kinders",
    "wof:placetype":"venue"
},
  "geometry": {"coordinates":[3.3271360397,51.3488578796],"type":"Point"}
}