{
  "type": "Feature",
  "properties": {
    "addr:full":"Parklaan 51b4 Turnhout Antwerpen 2300",
    "addr:housenumber":"51b4",
    "addr:postcode":"2300",
    "addr:street":"Parklaan",
    "iso:country":"BE",
    "sg:address":"Parklaan 51b4",
    "sg:city":"Turnhout",
    "sg:orig_category":"Location de voitures",
    "sg:phone":"+32 14 43 50 30",
    "sg:postcode":"2300",
    "sg:province":"Antwerpen",
    "wof:name":"Auto Lease Turnhout",
    "wof:placetype":"venue"
},
  "geometry": {"coordinates":[4.949365139,51.312702179],"type":"Point"}
}