{
  "type": "Feature",
  "properties": {
    "addr:full":"Chauss\u00e9e De Boondael 315-317 Bruxelles (ixelles) Bruxelles-Capitale 1050",
    "addr:postcode":"315-317;1050",
    "addr:street":"Chausse\u0301E De Boondael",
    "iso:country":"BE",
    "sg:address":"Chauss\u00e9e De Boondael 315-317",
    "sg:city":"Bruxelles (ixelles)",
    "sg:classifiers":[
        {
            "category":"Retail",
            "subcategory":"Auto Repair",
            "type":"Services"
        }
    ],
    "sg:phone":"+32 2 648 17 96",
    "sg:postcode":"1050",
    "sg:province":"Bruxelles-Capitale",
    "sg:tags":[
        "garage"
    ],
    "wof:name":"Peugeot-boondael Motors",
    "wof:placetype":"venue"
},
  "geometry": {"coordinates":[4.3826150894,50.819393158],"type":"Point"}
}