{
  "type": "Feature",
  "properties": {
    "addr:full":"Rue Massart 48 Fernelmont Namur 5380",
    "addr:housenumber":"48",
    "addr:postcode":"5380",
    "addr:street":"Rue Massart",
    "iso:country":"BE",
    "sg:address":"Rue Massart 48",
    "sg:city":"Fernelmont",
    "sg:orig_category":"Verplichte sociale verzekeringen",
    "sg:phone":"+32 81 83 45 23",
    "sg:postcode":"5380",
    "sg:province":"Namur",
    "wof:name":"Euromut Fernellemont",
    "wof:placetype":"venue"
},
  "geometry": {"coordinates":[4.9861078262,50.5531463623],"type":"Point"}
}