{
  "type": "Feature",
  "properties": {
    "addr:full":"Van Peborghlei 75 Mortsel Antwerpen 2640",
    "addr:housenumber":"75",
    "addr:postcode":"2640",
    "iso:country":"BE",
    "sg:address":"Van Peborghlei 75",
    "sg:city":"Mortsel",
    "sg:classifiers":[
        {
            "category":"Health Services",
            "subcategory":"Hospital",
            "type":"Services"
        }
    ],
    "sg:phone":"+32 3 449 28 09",
    "sg:postcode":"2640",
    "sg:province":"Antwerpen",
    "sg:tags":[
        "rinsing",
        "bedpan",
        "sink",
        "apparatus"
    ],
    "wof:name":"Etablissementen G. Stuyck Nv",
    "wof:placetype":"venue"
},
  "geometry": {"coordinates":[4.4427990913,51.1707572937],"type":"Point"}
}