{
  "type": "Feature",
  "properties": {
    "iso:country":"BE",
    "sg:address":"Gen. De Wittelaan 7",
    "sg:city":"Mechelen",
    "sg:orig_category":"Informaticaconsulenten",
    "sg:phone":"+32 15 29 29 29",
    "sg:postcode":"2800",
    "sg:province":"Antwerpen",
    "wof:name":"Microtron",
    "wof:placetype":"venue"
},
  "geometry": {"coordinates":[4.4511489868,51.0562438965],"type":"Point"}
}