{
  "type": "Feature",
  "properties": {
    "addr:full":"Technische-schoolstraat 41 Geel Antwerpen 2440",
    "addr:housenumber":"41",
    "addr:postcode":"2440",
    "addr:street":"Technische-Schoolstraat",
    "iso:country":"BE",
    "sg:address":"Technische-schoolstraat 41",
    "sg:city":"Geel",
    "sg:orig_category":"H\u00f4tels. Restaurants",
    "sg:phone":"+32 14 58 64 78",
    "sg:postcode":"2440",
    "sg:province":"Antwerpen",
    "wof:name":"Restaurant De Postiljon",
    "wof:placetype":"venue"
},
  "geometry": {"coordinates":[4.9845981598,51.1665802002],"type":"Point"}
}