{
  "type": "Feature",
  "properties": {
    "addr:full":"Anspachlaan 2 Brussel/bruxelles Bruxelles-Capitale 1000",
    "addr:housenumber":"2",
    "addr:postcode":"1000",
    "addr:street":"Anspachlaan;/",
    "iso:country":"BE",
    "sg:address":"Anspachlaan 2",
    "sg:city":"Brussel/bruxelles",
    "sg:orig_category":"Banken and kredietinstellingen",
    "sg:phone":"+32 2 226 35 40",
    "sg:postcode":"1000",
    "sg:province":"Bruxelles-Capitale",
    "wof:name":"Bbl",
    "wof:placetype":"venue"
},
  "geometry": {"coordinates":[4.352394104,50.8507728577],"type":"Point"}
}