{
  "type": "Feature",
  "properties": {
    "addr:full":"Sq Ambiorix 18 Bruxelles Bruxelles-Capitale 1000",
    "addr:housenumber":"18",
    "addr:postcode":"1000",
    "addr:street":"Sq Ambiorix",
    "iso:country":"BE",
    "sg:address":"Sq Ambiorix 18",
    "sg:city":"Bruxelles",
    "sg:classifiers":[
        {
            "category":"Professional",
            "subcategory":"Advertising",
            "type":"Services"
        }
    ],
    "sg:phone":"+32 2 736 37 57",
    "sg:postcode":"1000",
    "sg:province":"Bruxelles-Capitale",
    "sg:tags":[
        "communication",
        "medium"
    ],
    "wof:name":"Brumagne Publicite",
    "wof:placetype":"venue"
},
  "geometry": {"coordinates":[4.3847489357,50.847530365],"type":"Point"}
}