{
  "type": "Feature",
  "properties": {
    "iso:country":"BE",
    "sg:address":"Sint-katelijnestraat 84-88",
    "sg:city":"Mechelen",
    "sg:classifiers":[
        {
            "category":"Shopping",
            "subcategory":"Baby Store",
            "type":"Retail Goods"
        }
    ],
    "sg:phone":"+32 15 20 19 08",
    "sg:postcode":"2800",
    "sg:province":"Antwerpen",
    "sg:tags":[
        "-",
        "accessory"
    ],
    "wof:name":"Diana Baby & Junior Bvba",
    "wof:placetype":"venue"
},
  "geometry": {"coordinates":[4.4755759239,51.0323638916],"type":"Point"}
}