{
  "type": "Feature",
  "properties": {
    "iso:country":"BE",
    "sg:address":"Lion D'orweg",
    "sg:city":"Aalst",
    "sg:orig_category":"Mayonnaise - Mfg.& Whol",
    "sg:phone":"+32 53 78 60 48",
    "sg:postcode":"9300",
    "sg:province":"Oost-Vlaanderen",
    "wof:name":"Bocqu\u00e9-lenssens Bvba",
    "wof:placetype":"venue"
},
  "geometry": {"coordinates":[4.0400590897,50.953212738],"type":"Point"}
}