{
  "type": "Feature",
  "properties": {
    "iso:country":"BE",
    "sg:address":"Oude Weg 81",
    "sg:city":"Zulte",
    "sg:classifiers":[
        {
            "category":"Health Services",
            "subcategory":"Health Practitioner",
            "type":"Services"
        }
    ],
    "sg:phone":"+32 56 60 62 21",
    "sg:postcode":"9870",
    "sg:province":"Oost-Vlaanderen",
    "sg:tags":[
        "physiotherapist"
    ],
    "wof:name":"De Clercq F",
    "wof:placetype":"venue"
},
  "geometry": {"coordinates":[3.4375889301,50.9152107239],"type":"Point"}
}