{
  "type": "Feature",
  "properties": {
    "iso:country":"BE",
    "sg:address":"Brugse Heirweg 2",
    "sg:city":"Koekelare",
    "sg:orig_category":"Rundveehouders",
    "sg:phone":"+32 51 58 15 45",
    "sg:postcode":"8680",
    "sg:province":"West-Vlaanderen",
    "wof:name":"Valeer Masschaele",
    "wof:placetype":"venue"
},
  "geometry": {"coordinates":[2.9620780945,51.0843772888],"type":"Point"}
}