{
  "type": "Feature",
  "properties": {
    "iso:country":"BE",
    "sg:address":"Rue Du Marquis 5",
    "sg:city":"Fleurus",
    "sg:classifiers":[
        {
            "category":"Structure",
            "subcategory":"Office Building",
            "type":"Public Place"
        }
    ],
    "sg:phone":"+32 71 42 18 08",
    "sg:postcode":"6220",
    "sg:province":"Hainaut",
    "sg:tags":[
        "-",
        "type",
        "door",
        "sliding",
        "overhead"
    ],
    "wof:name":"Halloin M",
    "wof:placetype":"venue"
},
  "geometry": {"coordinates":[4.5300951004,50.4583282471],"type":"Point"}
}