{
  "type": "Feature",
  "properties": {
    "addr:full":"Royerplein 1 Meeuwen-gruitrode Limburg 3670",
    "addr:housenumber":"1",
    "addr:postcode":"3670",
    "addr:street":"Royerplein",
    "iso:country":"BE",
    "sg:address":"Royerplein 1",
    "sg:city":"Meeuwen-gruitrode",
    "sg:orig_category":"Salles de spectacles",
    "sg:phone":"+32 89 85 59 46",
    "sg:postcode":"3670",
    "sg:province":"Limburg",
    "wof:name":"Kultureel Centrum",
    "wof:placetype":"venue"
},
  "geometry": {"coordinates":[5.5205497742,51.0963516235],"type":"Point"}
}