{
  "type": "Feature",
  "properties": {
    "iso:country":"BE",
    "sg:address":"Casinostraat 7",
    "sg:city":"Blankenberge",
    "sg:classifiers":[
        {
            "category":"Bars & Pubs",
            "type":"Food & Drink"
        }
    ],
    "sg:phone":"+32 50 42 72 77",
    "sg:postcode":"8370",
    "sg:province":"West-Vlaanderen",
    "wof:name":"Zanzibar",
    "wof:placetype":"venue"
},
  "geometry": {"coordinates":[3.1298151016,51.3157997131],"type":"Point"}
}