{
  "type": "Feature",
  "properties": {
    "iso:country":"BE",
    "sg:address":"Galjoenstraat 2",
    "sg:city":"Antwerpen",
    "sg:orig_category":"Algemeen secundair onderwijs Kleuter- en basisonderwijs",
    "sg:phone":"+32 3 541 32 64",
    "sg:postcode":"2030",
    "sg:province":"Antwerpen",
    "wof:name":"Bubao St.jozefinstituut",
    "wof:placetype":"venue"
},
  "geometry": {"coordinates":[4.4223790169,51.2432060242],"type":"Point"}
}