{
  "type": "Feature",
  "properties": {
    "iso:country":"BE",
    "sg:address":"Raamstraat 67",
    "sg:city":"Brugge",
    "sg:orig_category":"Art and fournitures artistiques",
    "sg:phone":"+32 50 33 05 40",
    "sg:postcode":"8000",
    "sg:province":"West-Vlaanderen",
    "wof:name":"Fa. Pollentier-mar\u00c9chal",
    "wof:placetype":"venue"
},
  "geometry": {"coordinates":[3.2177410126,51.2126846313],"type":"Point"}
}