{
  "type": "Feature",
  "properties": {
    "iso:country":"BE",
    "sg:address":"Rue Taille Aux Chevaux 27",
    "sg:city":"Lobbes",
    "sg:classifiers":[
        {
            "category":"Professional",
            "type":"Services"
        }
    ],
    "sg:phone":"+32 71 59 55 67",
    "sg:postcode":"6540",
    "sg:province":"Hainaut",
    "sg:tags":[
        "industrial",
        "automation"
    ],
    "wof:name":"Eltec",
    "wof:placetype":"venue"
},
  "geometry": {"coordinates":[4.2732601166,50.3760414124],"type":"Point"}
}