{
  "type": "Feature",
  "properties": {
    "addr:full":"Oude Staatsbaan 139ba Maldegem Oost-Vlaanderen 9991",
    "addr:postcode":"9991",
    "addr:street":"Oude Staatsbaan 139Ba",
    "iso:country":"BE",
    "sg:address":"Oude Staatsbaan 139ba",
    "sg:city":"Maldegem",
    "sg:orig_category":"Plomberie, chauffage and installations sanitaires. Installation \u00e9lectrique r\u00e9sidentielle",
    "sg:phone":"+32 9 378 09 06",
    "sg:postcode":"9991",
    "sg:province":"Oost-Vlaanderen",
    "wof:name":"Gino Van Den Abeele",
    "wof:placetype":"venue"
},
  "geometry": {"coordinates":[3.5059940815,51.2061691284],"type":"Point"}
}