{
  "type": "Feature",
  "properties": {
    "addr:full":"Heuvelgoor 4 Geel Antwerpen 2440",
    "addr:housenumber":"4",
    "addr:postcode":"2440",
    "addr:street":"Heuvelgoor",
    "iso:country":"BE",
    "sg:address":"Heuvelgoor 4",
    "sg:city":"Geel",
    "sg:classifiers":[
        {
            "category":"Building & Trades",
            "subcategory":"Plumbing",
            "type":"Services"
        }
    ],
    "sg:phone":"+32 14 58 61 95",
    "sg:postcode":"2440",
    "sg:province":"Antwerpen",
    "sg:tags":[
        "repair",
        "mainten",
        "-",
        "central",
        "heating"
    ],
    "wof:name":"Theo Mens Bvba",
    "wof:placetype":"venue"
},
  "geometry": {"coordinates":[4.9902229309,51.17603302],"type":"Point"}
}