{
  "type": "Feature",
  "properties": {
    "addr:full":"Maria-christinastraat 27 Brussel/bruxelles Bruxelles-Capitale 1020",
    "addr:housenumber":"27",
    "addr:postcode":"1020",
    "addr:street":"Maria-Christinastraat;/",
    "iso:country":"BE",
    "sg:address":"Maria-christinastraat 27",
    "sg:city":"Brussel/bruxelles",
    "sg:orig_category":"Rookartikelen",
    "sg:phone":"+32 2 428 67 53",
    "sg:postcode":"1020",
    "sg:province":"Bruxelles-Capitale",
    "wof:name":"Martha Polissiou",
    "wof:placetype":"venue"
},
  "geometry": {"coordinates":[4.3575348854,50.8741569519],"type":"Point"}
}