{
  "type": "Feature",
  "properties": {
    "iso:country":"BE",
    "sg:address":"Antwerpsesteenweg 16",
    "sg:city":"Vosselaar",
    "sg:classifiers":[
        {
            "category":"Professional",
            "type":"Services"
        }
    ],
    "sg:phone":"+32 14 69 80 61",
    "sg:postcode":"2350",
    "sg:province":"Antwerpen",
    "sg:tags":[
        "entertainer"
    ],
    "wof:name":"Lisa Del Bo",
    "wof:placetype":"venue"
},
  "geometry": {"coordinates":[4.9025030136,51.3169174194],"type":"Point"}
}