{
  "type": "Feature",
  "properties": {
    "iso:country":"BE",
    "sg:address":"Ledigheis 51",
    "sg:city":"Lubbeek",
    "sg:orig_category":"Meubles Fab",
    "sg:phone":"+32 16 62 35 43",
    "sg:postcode":"3210",
    "sg:province":"Vlaams-Brabant",
    "wof:name":"Timmermans E",
    "wof:placetype":"venue"
},
  "geometry": {"coordinates":[4.8101701736,50.8913002014],"type":"Point"}
}