{
  "type": "Feature",
  "properties": {
    "addr:full":"Elstrekenweg 102 Zonhoven Limburg 3520",
    "addr:housenumber":"102",
    "addr:postcode":"3520",
    "addr:street":"Zonhoven Limburg",
    "iso:country":"BE",
    "sg:address":"Elstrekenweg 102",
    "sg:city":"Zonhoven",
    "sg:orig_category":"Installation de menuiserie en bois and plastique",
    "sg:phone":"+32 11 81 71 33",
    "sg:postcode":"3520",
    "sg:province":"Limburg",
    "wof:name":"Luc Bijnens",
    "wof:placetype":"venue"
},
  "geometry": {"coordinates":[5.4073867798,50.9784164429],"type":"Point"}
}