{
  "type": "Feature",
  "properties": {
    "addr:full":"Rue Du Dix-neuvi\u00e8me R\u00e9giment D'infanteri 3 Paliseul (maissin) Luxembourg 6852",
    "addr:housenumber":"3",
    "addr:postcode":"6852",
    "addr:street":"Rue Du Dix-Neuvie\u0300Me Re\u0301Giment D'Infanteri",
    "iso:country":"BE",
    "sg:address":"Rue Du Dix-neuvi\u00e8me R\u00e9giment D'infanteri 3",
    "sg:city":"Paliseul (maissin)",
    "sg:classifiers":[
        {
            "category":"Health Services",
            "subcategory":"Dentist",
            "type":"Services"
        }
    ],
    "sg:phone":"+32 61 65 59 88",
    "sg:postcode":"6852",
    "sg:province":"Luxembourg",
    "wof:name":"Strycek Vaclav",
    "wof:placetype":"venue"
},
  "geometry": {"coordinates":[5.1471800804,49.9572715759],"type":"Point"}
}