{
  "type": "Feature",
  "properties": {
    "iso:country":"BE",
    "sg:address":"Dorpsstraat 86",
    "sg:city":"Begijnendijk",
    "sg:classifiers":[
        {
            "category":"Recreation",
            "subcategory":"Campground",
            "type":"Entertainment"
        }
    ],
    "sg:phone":"+32 16 53 36 75",
    "sg:postcode":"3130",
    "sg:province":"Vlaams-Brabant",
    "sg:tags":[
        "site",
        "camping"
    ],
    "wof:name":"Meren (de)",
    "wof:placetype":"venue"
},
  "geometry": {"coordinates":[4.7724599838,51.0234794617],"type":"Point"}
}