{
  "type": "Feature",
  "properties": {
    "iso:country":"BE",
    "sg:address":"Markebekestraat 68",
    "sg:city":"Kortrijk",
    "sg:orig_category":"Installation \u00e9lectrique r\u00e9sidentielle",
    "sg:phone":"+32 56 21 47 23",
    "sg:postcode":"8510",
    "sg:province":"West-Vlaanderen",
    "wof:name":"Labarque & Vanlerberghe",
    "wof:placetype":"venue"
},
  "geometry": {"coordinates":[3.2412528992,50.8168754578],"type":"Point"}
}