{
  "type": "Feature",
  "properties": {
    "addr:full":"Malmedyerstrasse 36 B\u00dctgenbach Li\u00e8ge 4750",
    "addr:housenumber":"36",
    "addr:postcode":"4750",
    "addr:street":"Malmedyerstrasse",
    "iso:country":"BE",
    "sg:address":"Malmedyerstrasse 36",
    "sg:city":"B\u00dctgenbach",
    "sg:orig_category":"Kapsalons",
    "sg:phone":"+32 80 44 41 94",
    "sg:postcode":"4750",
    "sg:province":"Li\u00e8ge",
    "wof:name":"Virtuose Coiffure",
    "wof:placetype":"venue"
},
  "geometry": {"coordinates":[6.1995201111,50.4251098633],"type":"Point"}
}