{
  "type": "Feature",
  "properties": {
    "iso:country":"BE",
    "sg:address":"Sparrenhof 4",
    "sg:city":"Diest",
    "sg:orig_category":"Bagage and lederwaren",
    "sg:phone":"+32 13 31 39 22",
    "sg:postcode":"3290",
    "sg:province":"Vlaams-Brabant",
    "wof:name":"Carinne Geboes",
    "wof:placetype":"venue"
},
  "geometry": {"coordinates":[5.0460000038,50.9884910583],"type":"Point"}
}