{
  "type": "Feature",
  "properties": {
    "addr:full":"Appelmansstraat 26 Box 1 Antwerpen Antwerpen 2018",
    "addr:housenumber":"26;1",
    "addr:postcode":"2018",
    "addr:street":"Appelmansstraat;Box",
    "iso:country":"BE",
    "sg:address":"Appelmansstraat 26 Box 1",
    "sg:city":"Antwerpen",
    "sg:classifiers":[
        {
            "category":"Professional",
            "subcategory":"Accounting & Tax Preparation",
            "type":"Services"
        }
    ],
    "sg:phone":"+32 3 232 07 19",
    "sg:postcode":"2018",
    "sg:province":"Antwerpen",
    "sg:tags":[
        "accountant"
    ],
    "wof:name":"Accountantskantoor Timmermans R Bvba",
    "wof:placetype":"venue"
},
  "geometry": {"coordinates":[4.4171228409,51.2166061401],"type":"Point"}
}