{
  "type": "Feature",
  "properties": {
    "iso:country":"BE",
    "sg:address":"Rue Du Lavoir 4",
    "sg:city":"Bouillon",
    "sg:orig_category":"Slagers Voedingsspeciaalzaken",
    "sg:phone":"+32 61 46 00 37",
    "sg:postcode":"6830",
    "sg:province":"Luxembourg",
    "wof:name":"Le Coin Gourmand",
    "wof:placetype":"venue"
},
  "geometry": {"coordinates":[5.0697097778,49.7955360413],"type":"Point"}
}