{
  "type": "Feature",
  "properties": {
    "iso:country":"BE",
    "sg:address":"Rue De Virginal 195",
    "sg:city":"Tubize",
    "sg:orig_category":"HUISBRANDOLIE",
    "sg:phone":"+32 2 355 67 74",
    "sg:postcode":"1480",
    "sg:province":"Brabant Wallon",
    "wof:name":"Henri Debraekeleer",
    "wof:placetype":"venue"
},
  "geometry": {"coordinates":[4.2059087753,50.6715278625],"type":"Point"}
}