{
  "type": "Feature",
  "properties": {
    "iso:country":"BE",
    "sg:address":"Rue De Florent 3bb",
    "sg:city":"Rumes",
    "sg:orig_category":"Airconditioning and ventilatie Loodgieterij, verwarming and sanitaire installaties",
    "sg:phone":"+32 69 64 87 61",
    "sg:postcode":"7618",
    "sg:province":"Hainaut",
    "wof:name":"Bauvez",
    "wof:placetype":"venue"
},
  "geometry": {"coordinates":[3.3411400318,50.5502166748],"type":"Point"}
}