{
  "type": "Feature",
  "properties": {
    "addr:full":"De Theuxstraat 97 Elsene/ixelles Bruxelles-Capitale 1050",
    "addr:housenumber":"97",
    "addr:postcode":"1050",
    "addr:street":"De Theuxstraat",
    "iso:country":"BE",
    "sg:address":"De Theuxstraat 97",
    "sg:city":"Elsene/ixelles",
    "sg:orig_category":"Fotografen and fotostudio's",
    "sg:phone":"+32 2 649 45 27",
    "sg:postcode":"1050",
    "sg:province":"Bruxelles-Capitale",
    "wof:name":"Thibaut Donck",
    "wof:placetype":"venue"
},
  "geometry": {"coordinates":[4.3813948631,50.8320159912],"type":"Point"}
}