{
  "type": "Feature",
  "properties": {
    "addr:full":"Baty Du Rond C\u00c9risier 6b2 Walhain Brabant Wallon 1457",
    "addr:housenumber":"6b2;1457",
    "addr:street":"Baty Du Rond Ce\u0301Risier",
    "iso:country":"BE",
    "sg:address":"Baty Du Rond C\u00c9risier 6b2",
    "sg:city":"Walhain",
    "sg:orig_category":"Tuinen",
    "sg:phone":"+32 10 65 78 26",
    "sg:postcode":"1457",
    "sg:province":"Brabant Wallon",
    "wof:name":"Luc Bero",
    "wof:placetype":"venue"
},
  "geometry": {"coordinates":[4.7200012207,50.6122589111],"type":"Point"}
}