{
  "type": "Feature",
  "properties": {
    "addr:full":"Donkstraat 87 Haacht Vlaams-Brabant 3150",
    "addr:housenumber":"87",
    "addr:postcode":"3150",
    "addr:street":"Donkstraat",
    "iso:country":"BE",
    "sg:address":"Donkstraat 87",
    "sg:city":"Haacht",
    "sg:orig_category":"Gespecialiseerde residenti\u00eble bouw",
    "sg:phone":"+32 16 60 14 93",
    "sg:postcode":"3150",
    "sg:province":"Vlaams-Brabant",
    "wof:name":"Fa. Gijsemans",
    "wof:placetype":"venue"
},
  "geometry": {"coordinates":[4.6189098358,50.9625434875],"type":"Point"}
}