{
  "type": "Feature",
  "properties": {
    "addr:full":"Rue Du Tchet 37 Farciennes Hainaut 6240",
    "addr:housenumber":"37",
    "addr:postcode":"6240",
    "addr:street":"Rue Du Tchet",
    "iso:country":"BE",
    "sg:address":"Rue Du Tchet 37",
    "sg:city":"Farciennes",
    "sg:classifiers":[
        {
            "category":"Personal",
            "subcategory":"Barber",
            "type":"Services"
        }
    ],
    "sg:phone":"+32 71 39 30 58",
    "sg:postcode":"6240",
    "sg:province":"Hainaut",
    "sg:tags":[
        "gentleman",
        "salon",
        "-",
        "hairdressing"
    ],
    "wof:name":"Bruno Coiffure",
    "wof:placetype":"venue"
},
  "geometry": {"coordinates":[4.5514369011,50.4266014099],"type":"Point"}
}