{
  "type": "Feature",
  "properties": {
    "iso:country":"BE",
    "sg:address":"Marktplein 52",
    "sg:city":"Wemmel",
    "sg:orig_category":"Schoenen",
    "sg:phone":"+32 2 461 39 68",
    "sg:postcode":"1780",
    "sg:province":"Vlaams-Brabant",
    "wof:name":"Caroline L.",
    "wof:placetype":"venue"
},
  "geometry": {"coordinates":[4.3072137833,50.909412384],"type":"Point"}
}