{
  "type": "Feature",
  "properties": {
    "addr:full":"Rue Lamarck 80-84 Liege Li\u00e8ge 4000",
    "addr:housenumber":"80-84",
    "addr:postcode":"4000",
    "addr:street":"Rue Lamarck",
    "iso:country":"BE",
    "sg:address":"Rue Lamarck 80-84",
    "sg:city":"Liege",
    "sg:orig_category":"Kunststofrecipi\u00ebnten and -verpakkingen Fab Papier- and kartonverpakkingen Fab",
    "sg:phone":"+32 4 227 33 65",
    "sg:postcode":"4000",
    "sg:province":"Li\u00e8ge",
    "wof:name":"Eurosac",
    "wof:placetype":"venue"
},
  "geometry": {"coordinates":[5.5936970711,50.6519851685],"type":"Point"}
}