{
  "type": "Feature",
  "properties": {
    "addr:full":"Nicolaylaan 29 Leopoldsburg Limburg 3970",
    "addr:housenumber":"29",
    "addr:postcode":"3970",
    "addr:street":"Nicolaylaan",
    "iso:country":"BE",
    "sg:address":"Nicolaylaan 29",
    "sg:city":"Leopoldsburg",
    "sg:classifiers":[
        {
            "category":"Bars & Pubs",
            "type":"Food & Drink"
        }
    ],
    "sg:phone":"+32 11 34 86 70",
    "sg:postcode":"3970",
    "sg:province":"Limburg",
    "sg:tags":[
        "tavern"
    ],
    "wof:name":"Tunnel",
    "wof:placetype":"venue"
},
  "geometry": {"coordinates":[5.2587590218,51.116481781],"type":"Point"}
}