{
  "type": "Feature",
  "properties": {
    "addr:full":"Rue Ort\u00e9lius 6 Bruxelles Bruxelles-Capitale 1000",
    "addr:housenumber":"6",
    "addr:postcode":"1000",
    "addr:street":"Rue Orte\u0301Lius",
    "iso:country":"BE",
    "sg:address":"Rue Ort\u00e9lius 6",
    "sg:city":"Bruxelles",
    "sg:classifiers":[
        {
            "category":"Health Services",
            "subcategory":"Health Practitioner",
            "type":"Services"
        }
    ],
    "sg:phone":"+32 2 280 06 38",
    "sg:postcode":"1000",
    "sg:province":"Bruxelles-Capitale",
    "sg:tags":[
        "physiotherapist"
    ],
    "wof:name":"Fontaine Bernard",
    "wof:placetype":"venue"
},
  "geometry": {"coordinates":[4.376098156,50.8468551636],"type":"Point"}
}