{
  "type": "Feature",
  "properties": {
    "addr:full":"Rue Longue 162 Drogenbos Vlaams-Brabant 1620",
    "addr:housenumber":"162",
    "addr:postcode":"1620",
    "addr:street":"Rue Longue",
    "iso:country":"BE",
    "sg:address":"Rue Longue 162",
    "sg:city":"Drogenbos",
    "sg:orig_category":"Jeux and jouets",
    "sg:phone":"+32 2 377 45 65",
    "sg:postcode":"1620",
    "sg:province":"Vlaams-Brabant",
    "wof:name":"Maxi-toys",
    "wof:placetype":"venue"
},
  "geometry": {"coordinates":[4.3146457672,50.794216156],"type":"Point"}
}