{
  "type": "Feature",
  "properties": {
    "iso:country":"BE",
    "sg:address":"Avenue Emile Zola 8",
    "sg:city":"Bruxelles (schaerbeek)",
    "sg:classifiers":[
        {
            "category":"Retail",
            "subcategory":"Laundry & Dry Cleaning",
            "type":"Services"
        }
    ],
    "sg:phone":"+32 2 241 34 79",
    "sg:postcode":"1030",
    "sg:province":"Bruxelles-Capitale",
    "wof:name":"Les Lavoirs Reunis Sc",
    "wof:placetype":"venue"
},
  "geometry": {"coordinates":[4.3800411224,50.8769226074],"type":"Point"}
}