{
  "type": "Feature",
  "properties": {
    "addr:full":"Rue Du Ch\u00eane 21 Bruxelles Bruxelles-Capitale 1000",
    "addr:housenumber":"21",
    "addr:postcode":"1000",
    "addr:street":"Rue Du Che\u0302Ne",
    "iso:country":"BE",
    "sg:address":"Rue Du Ch\u00eane 21",
    "sg:city":"Bruxelles",
    "sg:classifiers":[
        {
            "category":"Shopping",
            "subcategory":"Books",
            "type":"Retail Goods"
        }
    ],
    "sg:phone":"+32 2 513 05 25",
    "sg:postcode":"1000",
    "sg:province":"Bruxelles-Capitale",
    "sg:tags":[
        "antiquarian",
        "trade"
    ],
    "wof:name":"Librairie Fl. Tulkens",
    "wof:placetype":"venue"
},
  "geometry": {"coordinates":[4.3511199951,50.8440895081],"type":"Point"}
}