{
  "type": "Feature",
  "properties": {
    "addr:full":"Graethempoort 2 Borgloon Limburg 3840",
    "addr:housenumber":"2",
    "addr:postcode":"3840",
    "addr:street":"Graethempoort",
    "iso:country":"BE",
    "sg:address":"Graethempoort 2",
    "sg:city":"Borgloon",
    "sg:orig_category":"Boucheries",
    "sg:phone":"+32 12 74 11 57",
    "sg:postcode":"3840",
    "sg:province":"Limburg",
    "wof:name":"Beenhouwerij Koll",
    "wof:placetype":"venue"
},
  "geometry": {"coordinates":[5.3337078094,50.8038063049],"type":"Point"}
}