{
  "type": "Feature",
  "properties": {
    "addr:full":"Rue De La Chauss\u00c9e 10 Beloeil Hainaut 7971",
    "addr:housenumber":"10",
    "addr:postcode":"7971",
    "addr:street":"Rue De La Chausse\u0301E",
    "iso:country":"BE",
    "sg:address":"Rue De La Chauss\u00c9e 10",
    "sg:city":"Beloeil",
    "sg:orig_category":"Pain, p\u00e2tisseries and confiseries",
    "sg:phone":"+32 69 78 05 73",
    "sg:postcode":"7971",
    "sg:province":"Hainaut",
    "wof:name":"Stephane Coduti",
    "wof:placetype":"venue"
},
  "geometry": {"coordinates":[3.6324710846,50.5434951782],"type":"Point"}
}