{
  "type": "Feature",
  "properties": {
    "addr:full":"Route De Clervaux 18 Bastogne Luxembourg 6600",
    "addr:housenumber":"18",
    "addr:postcode":"6600",
    "addr:street":"Route De Clervaux",
    "iso:country":"BE",
    "sg:address":"Route De Clervaux 18",
    "sg:city":"Bastogne",
    "sg:orig_category":"Boekhouders",
    "sg:postcode":"6600",
    "sg:province":"Luxembourg",
    "wof:name":"Andr\u00c9 Maquet",
    "wof:placetype":"venue"
},
  "geometry": {"coordinates":[5.7148199081,50.0007820129],"type":"Point"}
}