{
  "type": "Feature",
  "properties": {
    "addr:full":"Oude Houtlei 125 Gent Oost-Vlaanderen 9000",
    "addr:housenumber":"125",
    "addr:postcode":"9000",
    "addr:street":"Oude Houtlei;Oost-Vlaanderen",
    "iso:country":"BE",
    "sg:address":"Oude Houtlei 125",
    "sg:city":"Gent",
    "sg:classifiers":[
        {
            "category":"Professional",
            "subcategory":"Advertising",
            "type":"Services"
        }
    ],
    "sg:phone":"+32 9 225 73 65",
    "sg:postcode":"9000",
    "sg:province":"Oost-Vlaanderen",
    "sg:tags":[
        "telemarketing"
    ],
    "wof:name":"Telebel",
    "wof:placetype":"venue"
},
  "geometry": {"coordinates":[3.7172369957,51.0505371094],"type":"Point"}
}