{
  "type": "Feature",
  "properties": {
    "iso:country":"BE",
    "sg:address":"H. Van Veldekesingel 84",
    "sg:city":"Hasselt",
    "sg:classifiers":[
        {
            "category":"Insurance",
            "subcategory":"Insurance Agent",
            "type":"Services"
        }
    ],
    "sg:phone":"+32 11 27 55 35",
    "sg:postcode":"3500",
    "sg:province":"Limburg",
    "sg:tags":[
        "verzekeringsmakelaars",
        "expert"
    ],
    "wof:name":"W.v.i.",
    "wof:placetype":"venue"
},
  "geometry": {"coordinates":[5.3130578995,50.9299316406],"type":"Point"}
}