{
  "type": "Feature",
  "properties": {
    "addr:full":"Boulevard Auguste Reyers 52 Schaarbeek/schaerbeek 1044",
    "addr:housenumber":"52",
    "addr:postcode":"1044",
    "addr:street":"Boulevard Auguste Reyers",
    "iso:country":"BE",
    "sg:address":"Boulevard Auguste Reyers 52",
    "sg:city":"Schaarbeek/schaerbeek",
    "sg:orig_category":"Mus\u00e9es and patrimoine culturel",
    "sg:phone":"+32 2 737 21 69",
    "sg:postcode":"1044",
    "wof:name":"Musee Radio & T\u00c9l\u00c9vision",
    "wof:placetype":"venue"
},
  "geometry": {"coordinates":[4.4045200348,50.8526916504],"type":"Point"}
}