{
  "type": "Feature",
  "properties": {
    "addr:full":"Rue Sinnich 23 Voeren/fourons Limburg 3793",
    "addr:housenumber":"23",
    "addr:postcode":"3793",
    "addr:street":"Rue Sinnich",
    "iso:country":"BE",
    "sg:address":"Rue Sinnich 23",
    "sg:city":"Voeren/fourons",
    "sg:orig_category":"Charpentes and couvertures",
    "sg:phone":"+32 4 381 08 57",
    "sg:postcode":"3793",
    "sg:province":"Limburg",
    "wof:name":"Michel Jaminon",
    "wof:placetype":"venue"
},
  "geometry": {"coordinates":[5.8723402023,50.7526893616],"type":"Point"}
}