{
  "type": "Feature",
  "properties": {
    "iso:country":"BE",
    "sg:address":"Kaai 28",
    "sg:city":"Boom",
    "sg:orig_category":"Betonnen bouwelementen Fab Bouwmaterialen Gh",
    "sg:phone":"+32 3 888 01 10",
    "sg:postcode":"2850",
    "sg:province":"Antwerpen",
    "wof:name":"Lauwers",
    "wof:placetype":"venue"
},
  "geometry": {"coordinates":[4.3655319214,51.0844116211],"type":"Point"}
}