{
  "type": "Feature",
  "properties": {
    "iso:country":"BE",
    "sg:address":"Avenue Jan Verdoodt 4",
    "sg:city":"Bruxelles (jette)",
    "sg:classifiers":[
        {
            "category":"Health Services",
            "subcategory":"Health Practitioner",
            "type":"Services"
        }
    ],
    "sg:phone":"+32 478 97 15 43",
    "sg:postcode":"1090",
    "sg:province":"Bruxelles-Capitale",
    "sg:tags":[
        "physiotherapist"
    ],
    "wof:name":"Reybroeck-verhulst Jo\u00eblle",
    "wof:placetype":"venue"
},
  "geometry": {"coordinates":[4.3123030663,50.8884925842],"type":"Point"}
}