{
  "type": "Feature",
  "properties": {
    "addr:full":"Avenue Du G\u00c9n\u00c9ral-patton 101 Arlon Luxembourg 6700",
    "addr:housenumber":"101",
    "addr:postcode":"6700",
    "addr:street":"Avenue Du Ge\u0301Ne\u0301Ral-Patton",
    "iso:country":"BE",
    "sg:address":"Avenue Du G\u00c9n\u00c9ral-patton 101",
    "sg:city":"Arlon",
    "sg:orig_category":"Rev\u00eatements pour sols and murs",
    "sg:phone":"+32 63 21 72 87",
    "sg:postcode":"6700",
    "sg:province":"Luxembourg",
    "wof:name":"Thierry Bion",
    "wof:placetype":"venue"
},
  "geometry": {"coordinates":[5.813644886,49.6746826172],"type":"Point"}
}