{
  "type": "Feature",
  "properties": {
    "iso:country":"BE",
    "sg:address":"Rue Du Centre 17",
    "sg:city":"Profondeville",
    "sg:orig_category":"Installatie van metalen schrijnwerk Pleisterwerk",
    "sg:phone":"+32 81 43 47 21",
    "sg:postcode":"5170",
    "sg:province":"Namur",
    "wof:name":"Christophe Seleck",
    "wof:placetype":"venue"
},
  "geometry": {"coordinates":[4.8674049377,50.3786392212],"type":"Point"}
}