{
  "type": "Feature",
  "properties": {
    "addr:full":"Avenue Roi Albert 271 Andenne Namur 5300",
    "addr:housenumber":"271",
    "addr:postcode":"5300",
    "addr:street":"Avenue Roi Albert",
    "iso:country":"BE",
    "sg:address":"Avenue Roi Albert 271",
    "sg:city":"Andenne",
    "sg:orig_category":"Voertuigen",
    "sg:phone":"+32 85 84 29 45",
    "sg:postcode":"5300",
    "sg:province":"Namur",
    "wof:name":"Tannier",
    "wof:placetype":"venue"
},
  "geometry": {"coordinates":[5.1061091423,50.4935951233],"type":"Point"}
}