{
  "type": "Feature",
  "properties": {
    "addr:full":"Chauss\u00c9e De Boondael 391 Elsene/ixelles Bruxelles-Capitale 1050",
    "addr:housenumber":"391",
    "addr:postcode":"1050",
    "addr:street":"Chausse\u0301E De Boondael",
    "iso:country":"BE",
    "sg:address":"Chauss\u00c9e De Boondael 391",
    "sg:city":"Elsene/ixelles",
    "sg:classifiers":[
        {
            "category":"Personal",
            "subcategory":"Beauty Salon",
            "type":"Services"
        }
    ],
    "sg:phone":"+32 2 649 57 27",
    "sg:postcode":"1050",
    "sg:province":"Bruxelles-Capitale",
    "sg:tags":[
        "de",
        "coiffure"
    ],
    "wof:name":"Coiffure Josiane",
    "wof:placetype":"venue"
},
  "geometry": {"coordinates":[4.3876008987,50.8174705505],"type":"Point"}
}