{
  "type": "Feature",
  "properties": {
    "addr:full":"Ouwegemsesteenweg 2 Zingem (ouwegem) Oost-Vlaanderen 9750",
    "addr:housenumber":"2",
    "addr:postcode":"9750",
    "addr:street":"Ouwegemsesteenweg;Ouwegem",
    "iso:country":"BE",
    "sg:address":"Ouwegemsesteenweg 2",
    "sg:city":"Zingem (ouwegem)",
    "sg:classifiers":[
        {
            "category":"Manufacturing",
            "subcategory":"Printing",
            "type":"Manufacturing & Wholesale Goods"
        }
    ],
    "sg:phone":"+32 9 384 77 97",
    "sg:postcode":"9750",
    "sg:province":"Oost-Vlaanderen",
    "sg:tags":[
        "textile",
        "-"
    ],
    "wof:name":"Joe",
    "wof:placetype":"venue"
},
  "geometry": {"coordinates":[3.6146240234,50.9098739624],"type":"Point"}
}