{
  "type": "Feature",
  "properties": {
    "iso:country":"BE",
    "sg:address":"Jean Not\u00c9straat 40",
    "sg:city":"Anderlecht/anderlecht",
    "sg:orig_category":"Fitnesscentra",
    "sg:phone":"+32 2 523 05 70",
    "sg:postcode":"1070",
    "sg:province":"Bruxelles-Capitale",
    "wof:name":"Centre Olympia Gym",
    "wof:placetype":"venue"
},
  "geometry": {"coordinates":[4.2945427895,50.8261985779],"type":"Point"}
}