{
  "type": "Feature",
  "properties": {
    "iso:country":"BE",
    "sg:address":"Rue G\u00e9n\u00e9ral Freyberg 11c",
    "sg:city":"Lessines",
    "sg:classifiers":[
        {
            "category":"Professional",
            "subcategory":"Printing & Photocopies",
            "type":"Services"
        }
    ],
    "sg:phone":"+32 68 33 34 13",
    "sg:postcode":"7860",
    "sg:province":"Hainaut",
    "sg:tags":[
        "-",
        "offset"
    ],
    "wof:name":"Van Nieuwenhove G",
    "wof:placetype":"venue"
},
  "geometry": {"coordinates":[3.8335990906,50.7118988037],"type":"Point"}
}