{
  "type": "Feature",
  "properties": {
    "addr:full":"Ertveldesteenweg 151 Assenede Oost-Vlaanderen 9968",
    "addr:housenumber":"151",
    "addr:postcode":"9968",
    "addr:street":"Ertveldesteenweg",
    "iso:country":"BE",
    "sg:address":"Ertveldesteenweg 151",
    "sg:city":"Assenede",
    "sg:orig_category":"Installatie van houten of kunststof schrijnwerk",
    "sg:phone":"+32 9 344 09 75",
    "sg:postcode":"9968",
    "sg:province":"Oost-Vlaanderen",
    "wof:name":"Danny Claeye",
    "wof:placetype":"venue"
},
  "geometry": {"coordinates":[3.7201480865,51.1858139038],"type":"Point"}
}