{
  "type": "Feature",
  "properties": {
    "addr:full":"Chauss\u00e9e De Saint-job 524 Bruxelles (uccle) Bruxelles-Capitale 1180",
    "addr:housenumber":"524",
    "addr:postcode":"1180",
    "addr:street":"Chausse\u0301E De Saint-Job",
    "iso:country":"BE",
    "sg:address":"Chauss\u00e9e De Saint-job 524",
    "sg:city":"Bruxelles (uccle)",
    "sg:classifiers":[
        {
            "category":"Communications",
            "subcategory":"Film & Video Production",
            "type":"Services"
        }
    ],
    "sg:phone":"+32 2 375 33 06",
    "sg:postcode":"1180",
    "sg:province":"Bruxelles-Capitale",
    "sg:tags":[
        "movie",
        "maker"
    ],
    "wof:name":"Fran\u00e7ois C",
    "wof:placetype":"venue"
},
  "geometry": {"coordinates":[4.3592371941,50.7924232483],"type":"Point"}
}