{
  "type": "Feature",
  "properties": {
    "addr:full":"Veldstraat 1 Lochristi Oost-Vlaanderen 9080",
    "addr:housenumber":"1",
    "addr:postcode":"9080",
    "addr:street":"Veldstraat",
    "iso:country":"BE",
    "sg:address":"Veldstraat 1",
    "sg:city":"Lochristi",
    "sg:classifiers":[
        {
            "category":"Restaurant",
            "type":"Food & Drink"
        }
    ],
    "sg:phone":"+32 9 355 91 93",
    "sg:postcode":"9080",
    "sg:province":"Oost-Vlaanderen",
    "wof:name":"Hijftegoed",
    "wof:placetype":"venue"
},
  "geometry": {"coordinates":[3.8072988987,51.1082763672],"type":"Point"}
}