{
  "type": "Feature",
  "properties": {
    "iso:country":"BE",
    "sg:address":"Jonkershovestraat 52c",
    "sg:city":"Houthulst",
    "sg:classifiers":[
        {
            "category":"Retail",
            "subcategory":"Veterinary Services",
            "type":"Services"
        }
    ],
    "sg:phone":"+32 51 70 06 72",
    "sg:postcode":"8650",
    "sg:province":"West-Vlaanderen",
    "sg:tags":[
        "veterinarian"
    ],
    "wof:name":"Dejager A R",
    "wof:placetype":"venue"
},
  "geometry": {"coordinates":[2.9399049282,50.9753341675],"type":"Point"}
}