{
  "type": "Feature",
  "properties": {
    "addr:full":"Brugsestraat 70 Zedelgem (aartrijke) West-Vlaanderen 8211",
    "addr:housenumber":"70",
    "addr:postcode":"8211",
    "addr:street":"Brugsestraat",
    "iso:country":"BE",
    "sg:address":"Brugsestraat 70",
    "sg:city":"Zedelgem (aartrijke)",
    "sg:classifiers":[
        {
            "category":"Shopping",
            "subcategory":"Shoes",
            "type":"Retail Goods"
        }
    ],
    "sg:phone":"+32 50 24 04 70",
    "sg:postcode":"8211",
    "sg:province":"West-Vlaanderen",
    "sg:tags":[
        "slipper",
        "-"
    ],
    "wof:name":"Viruss Bvba",
    "wof:placetype":"venue"
},
  "geometry": {"coordinates":[3.0889649391,51.1200408936],"type":"Point"}
}