{
  "type": "Feature",
  "properties": {
    "iso:country":"BE",
    "sg:address":"Liersebaan 42",
    "sg:city":"Zandhoven",
    "sg:classifiers":[
        {
            "category":"Shopping",
            "subcategory":"Jewelry",
            "type":"Retail Goods"
        }
    ],
    "sg:phone":"+32 3 484 37 71",
    "sg:postcode":"2240",
    "sg:province":"Antwerpen",
    "sg:tags":[
        "jeweller",
        "-"
    ],
    "wof:name":"Soetewey Y",
    "wof:placetype":"venue"
},
  "geometry": {"coordinates":[4.657544136,51.2139854431],"type":"Point"}
}