{
  "type": "Feature",
  "properties": {
    "addr:full":"Rue Du Man\u00c8ge 1ba Moeskroen/mouscron Hainaut 7700",
    "addr:housenumber":"1ba",
    "addr:postcode":"7700",
    "addr:street":"Rue Du Mane\u0300Ge",
    "iso:country":"BE",
    "sg:address":"Rue Du Man\u00c8ge 1ba",
    "sg:city":"Moeskroen/mouscron",
    "sg:orig_category":"Activit\u00e9s d\u00b4action sociale sans h\u00e9bergement. Ambulances",
    "sg:phone":"+32 56 33 66 98",
    "sg:postcode":"7700",
    "sg:province":"Hainaut",
    "wof:name":"Croix Rouge De Belgique",
    "wof:placetype":"venue"
},
  "geometry": {"coordinates":[3.2323200703,50.7400932312],"type":"Point"}
}