{
  "type": "Feature",
  "properties": {
    "iso:country":"BE",
    "sg:address":"Driftweg 49",
    "sg:city":"Bredene",
    "sg:orig_category":"Sociale secretariaten",
    "sg:phone":"+32 59 32 52 63",
    "sg:postcode":"8450",
    "sg:province":"West-Vlaanderen",
    "wof:name":"Sociaal Kantoor Smets",
    "wof:placetype":"venue"
},
  "geometry": {"coordinates":[2.9481060505,51.2430763245],"type":"Point"}
}