{
  "type": "Feature",
  "properties": {
    "iso:country":"BE",
    "sg:address":"Rue Des Preys 114",
    "sg:city":"Charleroi (montignies-sur-sambre)",
    "sg:classifiers":[
        {
            "category":"Professional",
            "subcategory":"Accounting & Tax Preparation",
            "type":"Services"
        }
    ],
    "sg:phone":"+32 71 30 05 30",
    "sg:postcode":"6061",
    "sg:province":"Hainaut",
    "sg:tags":[
        "bookkeeper"
    ],
    "wof:name":"Honor\u00e9 H",
    "wof:placetype":"venue"
},
  "geometry": {"coordinates":[4.4845690727,50.4019241333],"type":"Point"}
}