{
  "type": "Feature",
  "properties": {
    "addr:full":"Avenue Henri Conscience 154 Evere Bruxelles-Capitale 1140",
    "addr:housenumber":"154",
    "addr:postcode":"1140",
    "addr:street":"Avenue Henri Conscience",
    "iso:country":"BE",
    "sg:address":"Avenue Henri Conscience 154",
    "sg:city":"Evere",
    "sg:orig_category":"Opticiens",
    "sg:phone":"+32 2 215 86 07",
    "sg:postcode":"1140",
    "sg:province":"Bruxelles-Capitale",
    "wof:name":"Evere Optic",
    "wof:placetype":"venue"
},
  "geometry": {"coordinates":[4.4003148079,50.8708648682],"type":"Point"}
}