{
  "type": "Feature",
  "properties": {
    "addr:full":"Grote Markt 30 Menen West-Vlaanderen 8930",
    "addr:housenumber":"30",
    "addr:postcode":"8930",
    "addr:street":"Grote Markt",
    "iso:country":"BE",
    "sg:address":"Grote Markt 30",
    "sg:city":"Menen",
    "sg:orig_category":"H\u00f4tels. Restaurants",
    "sg:phone":"+32 56 51 12 73",
    "sg:postcode":"8930",
    "sg:province":"West-Vlaanderen",
    "wof:name":"De Sterre",
    "wof:placetype":"venue"
},
  "geometry": {"coordinates":[3.1206378937,50.7962684631],"type":"Point"}
}