{
  "type": "Feature",
  "properties": {
    "addr:full":"Larbois 3 Dalhem (neufch\u00e2teau (lez-vis\u00e9)) Li\u00e8ge 4608",
    "addr:housenumber":"3",
    "addr:postcode":"4608",
    "addr:street":"Larbois;Lez-Vise\u0301",
    "iso:country":"BE",
    "sg:address":"Larbois 3",
    "sg:city":"Dalhem (neufch\u00e2teau (lez-vis\u00e9))",
    "sg:classifiers":[
        {
            "category":"Health Services",
            "subcategory":"Health Practitioner",
            "type":"Services"
        }
    ],
    "sg:phone":"+32 4 376 71 65",
    "sg:postcode":"4608",
    "sg:province":"Li\u00e8ge",
    "sg:tags":[
        "physiotherapist"
    ],
    "wof:name":"Kloos J",
    "wof:placetype":"venue"
},
  "geometry": {"coordinates":[5.7779669762,50.7188148499],"type":"Point"}
}