{
  "type": "Feature",
  "properties": {
    "iso:country":"BE",
    "sg:address":"Van Aerdtstraat 10",
    "sg:city":"Antwerpen",
    "sg:classifiers":[
        {
            "category":"Professional",
            "subcategory":"Accounting & Tax Preparation",
            "type":"Services"
        }
    ],
    "sg:phone":"+32 3 238 59 84",
    "sg:postcode":"2060",
    "sg:province":"Antwerpen",
    "sg:tags":[
        "accountant"
    ],
    "wof:name":"Studiecentrum Voor Fiskaliteit En Boekhouding Nv",
    "wof:placetype":"venue"
},
  "geometry": {"coordinates":[4.415186882,51.2274398804],"type":"Point"}
}