{
  "type": "Feature",
  "properties": {
    "iso:country":"BE",
    "sg:address":"P.i. Des Hauts-sarts",
    "sg:city":"Herstal",
    "sg:classifiers":[
        {
            "category":"Autos & Motor Vehicles",
            "subcategory":"Automobile Sales",
            "type":"Retail Goods"
        }
    ],
    "sg:phone":"+32 4 248 50 40",
    "sg:postcode":"4040",
    "sg:province":"Li\u00e8ge",
    "sg:tags":[
        "equipment",
        "industrial",
        "transport"
    ],
    "wof:name":"Scantec Sa",
    "wof:placetype":"venue"
},
  "geometry": {"coordinates":[5.6277627945,50.6893463135],"type":"Point"}
}