{
  "type": "Feature",
  "properties": {
    "addr:full":"Rue Des Ecoles 39 Le Roeulx Hainaut 7070",
    "addr:housenumber":"39",
    "addr:postcode":"7070",
    "addr:street":"Rue Des Ecoles",
    "iso:country":"BE",
    "sg:address":"Rue Des Ecoles 39",
    "sg:city":"Le Roeulx",
    "sg:orig_category":"Enseignement maternel and primaire",
    "sg:phone":"+32 64 67 55 59",
    "sg:postcode":"7070",
    "sg:province":"Hainaut",
    "wof:name":"Ecole Prim. Communale",
    "wof:placetype":"venue"
},
  "geometry": {"coordinates":[4.0913748741,50.4759025574],"type":"Point"}
}