{
  "type": "Feature",
  "properties": {
    "iso:country":"BE",
    "sg:address":"Stationsstraat 33",
    "sg:city":"Ledegem",
    "sg:classifiers":[
        {
            "category":"Bars & Pubs",
            "type":"Food & Drink"
        }
    ],
    "sg:phone":"+32 56 50 24 11",
    "sg:postcode":"8880",
    "sg:province":"West-Vlaanderen",
    "wof:name":"P\u00e9p\u00e9's",
    "wof:placetype":"venue"
},
  "geometry": {"coordinates":[3.1248219013,50.8557815552],"type":"Point"}
}