{
  "type": "Feature",
  "properties": {
    "addr:full":"Dokter Dekemelelaan 5 Ieper West-Vlaanderen 8904",
    "addr:housenumber":"5",
    "addr:postcode":"8904",
    "addr:street":"Dokter Dekemelelaan",
    "iso:country":"BE",
    "sg:address":"Dokter Dekemelelaan 5",
    "sg:city":"Ieper",
    "sg:classifiers":[
        {
            "category":"Sports & Exercise",
            "subcategory":"Sports Center",
            "type":"Entertainment"
        }
    ],
    "sg:phone":"+32 57 42 24 82",
    "sg:postcode":"8904",
    "sg:province":"West-Vlaanderen",
    "sg:tags":[
        "terrain",
        "hors",
        "de",
        "installation",
        "sportifs"
    ],
    "wof:name":"Hydra",
    "wof:placetype":"venue"
},
  "geometry": {"coordinates":[2.8575899601,50.8964576721],"type":"Point"}
}