{
  "type": "Feature",
  "properties": {
    "iso:country":"BE",
    "sg:address":"Sint-truidensesteenweg 3 Box 2",
    "sg:city":"Zoutleeuw",
    "sg:classifiers":[
        {
            "category":"Shopping",
            "subcategory":"Clothing, Apparel, & Fashions",
            "type":"Retail Goods"
        }
    ],
    "sg:phone":"+32 11 78 52 47",
    "sg:postcode":"3440",
    "sg:province":"Vlaams-Brabant",
    "sg:tags":[
        "boutique"
    ],
    "wof:name":"Vive",
    "wof:placetype":"venue"
},
  "geometry": {"coordinates":[5.1066198349,50.8317298889],"type":"Point"}
}