{
  "type": "Feature",
  "properties": {
    "iso:country":"BE",
    "sg:address":"Ambachtenlaan 13ba",
    "sg:city":"Leuven",
    "sg:orig_category":"Beheer onroerend goed Vrachtvervoer",
    "sg:phone":"+32 16 40 43 69",
    "sg:postcode":"3001",
    "sg:province":"Vlaams-Brabant",
    "wof:name":"Apollo Development",
    "wof:placetype":"venue"
},
  "geometry": {"coordinates":[4.7162518501,50.8483467102],"type":"Point"}
}