{
  "type": "Feature",
  "properties": {
    "addr:full":"Dam 52 Lokeren Oost-Vlaanderen 9160",
    "addr:housenumber":"52",
    "addr:postcode":"9160",
    "addr:street":"Dam",
    "iso:country":"BE",
    "sg:address":"Dam 52",
    "sg:city":"Lokeren",
    "sg:classifiers":[
        {
            "category":"Insurance",
            "subcategory":"Insurance Agent",
            "type":"Services"
        }
    ],
    "sg:phone":"+32 9 346 95 01",
    "sg:postcode":"9160",
    "sg:province":"Oost-Vlaanderen",
    "sg:tags":[
        "verzekeringsmakelaars",
        "expert"
    ],
    "wof:name":"I. De Vos",
    "wof:placetype":"venue"
},
  "geometry": {"coordinates":[3.9492731094,51.1505813599],"type":"Point"}
}