{
  "type": "Feature",
  "properties": {
    "addr:full":"Ooststraat 15 Veurne West-Vlaanderen 8630",
    "addr:housenumber":"15",
    "addr:postcode":"8630",
    "addr:street":"Ooststraat",
    "iso:country":"BE",
    "sg:address":"Ooststraat 15",
    "sg:city":"Veurne",
    "sg:orig_category":"Bagage and lederwaren Kledingaccessoires",
    "sg:phone":"+32 58 31 17 05",
    "sg:postcode":"8630",
    "sg:province":"West-Vlaanderen",
    "wof:name":"Madex",
    "wof:placetype":"venue"
},
  "geometry": {"coordinates":[2.6635670662,51.0726051331],"type":"Point"}
}