{
  "type": "Feature",
  "properties": {
    "iso:country":"BE",
    "sg:address":"Sleepstraat 229",
    "sg:city":"Gent",
    "sg:classifiers":[
        {
            "category":"Bars & Pubs",
            "type":"Food & Drink"
        }
    ],
    "sg:phone":"+32 9 224 20 03",
    "sg:postcode":"9000",
    "sg:province":"Oost-Vlaanderen",
    "wof:name":"Titanic",
    "wof:placetype":"venue"
},
  "geometry": {"coordinates":[3.7291100025,51.0640602112],"type":"Point"}
}