{
  "type": "Feature",
  "properties": {
    "iso:country":"BE",
    "sg:address":"Rue Lintermans 22",
    "sg:city":"Seneffe",
    "sg:orig_category":"Boucheries",
    "sg:phone":"+32 64 54 13 03",
    "sg:postcode":"7180",
    "sg:province":"Hainaut",
    "wof:name":"Jacques Andr\u00c9",
    "wof:placetype":"venue"
},
  "geometry": {"coordinates":[4.2572288513,50.5298500061],"type":"Point"}
}