{
  "type": "Feature",
  "properties": {
    "addr:full":"Chemin Haute Franchise 37 Rebecq (rebecq-rognon) Brabant Wallon 1430",
    "addr:housenumber":"37",
    "addr:postcode":"1430",
    "addr:street":"Chemin Haute Franchise;Wallon",
    "iso:country":"BE",
    "sg:address":"Chemin Haute Franchise 37",
    "sg:city":"Rebecq (rebecq-rognon)",
    "sg:classifiers":[
        {
            "category":"Retail",
            "subcategory":"Auto Repair",
            "type":"Services"
        }
    ],
    "sg:phone":"+32 67 63 78 28",
    "sg:postcode":"1430",
    "sg:province":"Brabant Wallon",
    "sg:tags":[
        "automobile-body"
    ],
    "wof:name":"Gilmont",
    "wof:placetype":"venue"
},
  "geometry": {"coordinates":[4.097340107,50.6541595459],"type":"Point"}
}