{
  "type": "Feature",
  "properties": {
    "addr:full":"Robert Molsstraat 49 Antwerpen Antwerpen 2018",
    "addr:housenumber":"49",
    "addr:postcode":"2018",
    "addr:street":"Molsstraat",
    "iso:country":"BE",
    "sg:address":"Robert Molsstraat 49",
    "sg:city":"Antwerpen",
    "sg:classifiers":[
        {
            "category":"Communications",
            "type":"Services"
        }
    ],
    "sg:phone":"+32 3 238 03 19",
    "sg:postcode":"2018",
    "sg:province":"Antwerpen",
    "sg:tags":[
        "translation"
    ],
    "wof:name":"All Trans B.v.b.a.",
    "wof:placetype":"venue"
},
  "geometry": {"coordinates":[4.4017858505,51.1996650696],"type":"Point"}
}