{
  "type": "Feature",
  "properties": {
    "iso:country":"BE",
    "sg:address":"Kruisken 26",
    "sg:city":"Maldegem",
    "sg:classifiers":[
        {
            "category":"Cafe",
            "type":"Food & Drink"
        }
    ],
    "sg:phone":"+32 50 71 65 94",
    "sg:postcode":"9991",
    "sg:province":"Oost-Vlaanderen",
    "sg:tags":[
        "caf\u00e9s"
    ],
    "wof:name":"Rita Lagage",
    "wof:placetype":"venue"
},
  "geometry": {"coordinates":[3.4957499504,51.1886405945],"type":"Point"}
}