{
  "type": "Feature",
  "properties": {
    "addr:full":"Statiestraat 96 Zulte Oost-Vlaanderen 9870",
    "addr:housenumber":"96",
    "addr:postcode":"9870",
    "addr:street":"Statiestraat",
    "iso:country":"BE",
    "sg:address":"Statiestraat 96",
    "sg:city":"Zulte",
    "sg:classifiers":[
        {
            "category":"Health Services",
            "subcategory":"Health Practitioner",
            "type":"Services"
        }
    ],
    "sg:phone":"+32 9 388 92 39",
    "sg:postcode":"9870",
    "sg:province":"Oost-Vlaanderen",
    "sg:tags":[
        "physiotherapist"
    ],
    "wof:name":"Desmet Donald",
    "wof:placetype":"venue"
},
  "geometry": {"coordinates":[3.4448020458,50.9163093567],"type":"Point"}
}