{
  "type": "Feature",
  "properties": {
    "iso:country":"BE",
    "sg:address":"Rue Joseph Stevens 38",
    "sg:city":"Bruxelles",
    "sg:classifiers":[
        {
            "category":"Manufacturing",
            "subcategory":"Furniture",
            "type":"Manufacturing & Wholesale Goods"
        }
    ],
    "sg:phone":"+32 2 512 87 24",
    "sg:postcode":"1000",
    "sg:province":"Bruxelles-Capitale",
    "sg:tags":[
        "armchair",
        "-"
    ],
    "wof:name":"Duchesse Bris\u00e9e (la)",
    "wof:placetype":"venue"
},
  "geometry": {"coordinates":[4.3535351753,50.8415641785],"type":"Point"}
}