{
  "type": "Feature",
  "properties": {
    "addr:full":"Rue D'orleans 53 Comines Hainaut 7780",
    "addr:housenumber":"53",
    "addr:postcode":"7780",
    "addr:street":"Rue D'Orleans",
    "iso:country":"BE",
    "sg:address":"Rue D'orleans 53",
    "sg:city":"Comines",
    "sg:classifiers":[
        {
            "category":"Banks & Credit Unions",
            "subcategory":"Investment Brokerage",
            "type":"Services"
        }
    ],
    "sg:phone":"+32 56 55 51 32",
    "sg:postcode":"7780",
    "sg:province":"Hainaut",
    "sg:tags":[
        "canteen",
        "seating",
        "furnishings"
    ],
    "wof:name":"Declercq Fr\u00e8res S.p.r.l.",
    "wof:placetype":"venue"
},
  "geometry": {"coordinates":[3.0029940605,50.7715606689],"type":"Point"}
}