{
  "type": "Feature",
  "properties": {
    "iso:country":"BE",
    "sg:address":"Rue Du Tige 192",
    "sg:city":"Juprelle",
    "sg:classifiers":[
        {
            "category":"Health Services",
            "subcategory":"Health Practitioner",
            "type":"Services"
        }
    ],
    "sg:phone":"+32 4 278 00 80",
    "sg:postcode":"4450",
    "sg:province":"Li\u00e8ge",
    "sg:tags":[
        "physiotherapist"
    ],
    "wof:name":"Smeets J-m",
    "wof:placetype":"venue"
},
  "geometry": {"coordinates":[5.525454998,50.7086524963],"type":"Point"}
}