{
  "type": "Feature",
  "properties": {
    "iso:country":"BE",
    "sg:address":"Rue Eug\u00c8ne-ysaye 11",
    "sg:city":"Yvoir",
    "sg:orig_category":"Fabrication and montage de mobilier. Mat\u00e9riaux de construction Gr",
    "sg:phone":"+32 82 61 26 57",
    "sg:postcode":"5530",
    "sg:province":"Namur",
    "wof:name":"Namur Carrelages",
    "wof:placetype":"venue"
},
  "geometry": {"coordinates":[4.8746399879,50.3489875793],"type":"Point"}
}