{
  "type": "Feature",
  "properties": {
    "addr:full":"Bollebergen 2a Gent (zwijnaarde) Oost-Vlaanderen 9052",
    "addr:housenumber":"2a",
    "addr:postcode":"9052",
    "addr:street":"Bollebergen",
    "iso:country":"BE",
    "sg:address":"Bollebergen 2a",
    "sg:city":"Gent (zwijnaarde)",
    "sg:classifiers":[
        {
            "category":"Real Estate",
            "subcategory":"Surveying",
            "type":"Services"
        }
    ],
    "sg:phone":"+32 9 375 13 00",
    "sg:postcode":"9052",
    "sg:province":"Oost-Vlaanderen",
    "sg:tags":[
        "raw",
        "material",
        "-",
        "plastic"
    ],
    "wof:name":"Belucon Nv",
    "wof:placetype":"venue"
},
  "geometry": {"coordinates":[3.7167270184,51.0002937317],"type":"Point"}
}