{
  "type": "Feature",
  "properties": {
    "addr:full":"Rue Hector Delanois 189 Mons Hainaut 7033",
    "addr:housenumber":"189",
    "addr:postcode":"7033",
    "addr:street":"Rue Hector Delanois;Hainaut",
    "iso:country":"BE",
    "sg:address":"Rue Hector Delanois 189",
    "sg:city":"Mons",
    "sg:orig_category":"Installation de menuiserie m\u00e9tallique. Installation de menuiserie en bois and plastique",
    "sg:phone":"+32 65 36 13 78",
    "sg:postcode":"7033",
    "sg:province":"Hainaut",
    "wof:name":"Ghilain",
    "wof:placetype":"venue"
},
  "geometry": {"coordinates":[3.9253261089,50.4366378784],"type":"Point"}
}