{
  "type": "Feature",
  "properties": {
    "iso:country":"BE",
    "sg:address":"Ooststraat 17",
    "sg:city":"Lo-reninge",
    "sg:orig_category":"Banken and kredietinstellingen",
    "sg:phone":"+32 58 28 80 49",
    "sg:postcode":"8647",
    "sg:province":"West-Vlaanderen",
    "wof:name":"Dexia",
    "wof:placetype":"venue"
},
  "geometry": {"coordinates":[2.7503240108,50.9809532166],"type":"Point"}
}