{
  "type": "Feature",
  "properties": {
    "addr:full":"Rue Des Pommiers 12 Oupeye Li\u00e8ge 4680",
    "addr:housenumber":"12",
    "addr:postcode":"4680",
    "addr:street":"Rue Des Pommiers",
    "iso:country":"BE",
    "sg:address":"Rue Des Pommiers 12",
    "sg:city":"Oupeye",
    "sg:orig_category":"Diverse bedrijfsbeheeradviesbureaus",
    "sg:phone":"+32 4 278 10 08",
    "sg:postcode":"4680",
    "sg:province":"Li\u00e8ge",
    "wof:name":"Iter",
    "wof:placetype":"venue"
},
  "geometry": {"coordinates":[5.6319828033,50.7122993469],"type":"Point"}
}