{
  "type": "Feature",
  "properties": {
    "addr:full":"E. Van Notenlaan 88 Brecht Antwerpen 2960",
    "addr:housenumber":"88",
    "addr:postcode":"2960",
    "addr:street":"E. Van Notenlaan",
    "iso:country":"BE",
    "sg:address":"E. Van Notenlaan 88",
    "sg:city":"Brecht",
    "sg:classifiers":[
        {
            "category":"Arena",
            "subcategory":"Sports Club",
            "type":"Entertainment"
        }
    ],
    "sg:phone":"+32 3 313 56 50",
    "sg:postcode":"2960",
    "sg:province":"Antwerpen",
    "sg:tags":[
        "de"
    ],
    "wof:name":"W.s.c. Oostmalle",
    "wof:placetype":"venue"
},
  "geometry": {"coordinates":[4.6747670174,51.3524589539],"type":"Point"}
}