{
  "type": "Feature",
  "properties": {
    "iso:country":"BE",
    "sg:address":"Chauss\u00c9e De Waterloo 1599",
    "sg:city":"Ukkel/uccle",
    "sg:orig_category":"Location de voitures. V\u00e9hicules automobiles",
    "sg:phone":"+32 2 375 66 00",
    "sg:postcode":"1180",
    "sg:province":"Bruxelles-Capitale",
    "wof:name":"Belgian Trade Group",
    "wof:placetype":"venue"
},
  "geometry": {"coordinates":[4.3824501038,50.7706794739],"type":"Point"}
}