{
  "type": "Feature",
  "properties": {
    "addr:full":"Place De Ch\u00c9zy 4 Aywaille Li\u00e8ge 4920",
    "addr:housenumber":"4",
    "addr:postcode":"4920",
    "addr:street":"Place De Che\u0301Zy",
    "iso:country":"BE",
    "sg:address":"Place De Ch\u00c9zy 4",
    "sg:city":"Aywaille",
    "sg:classifiers":[
        {
            "category":"Cafe",
            "type":"Food & Drink"
        }
    ],
    "sg:phone":"+32 4 384 44 47",
    "sg:postcode":"4920",
    "sg:province":"Li\u00e8ge",
    "sg:tags":[
        "caf\u00e9s"
    ],
    "wof:name":"Maurille Lespagnard",
    "wof:placetype":"venue"
},
  "geometry": {"coordinates":[5.6782069206,50.4738540649],"type":"Point"}
}