{
  "type": "Feature",
  "properties": {
    "iso:country":"BE",
    "sg:address":"Keizerstraat 27",
    "sg:city":"Beveren (haasdonk)",
    "sg:classifiers":[
        {
            "category":"Real Estate",
            "subcategory":"Architect",
            "type":"Services"
        }
    ],
    "sg:phone":"+32 3 775 40 62",
    "sg:postcode":"9120",
    "sg:province":"Oost-Vlaanderen",
    "wof:name":"De Preter R",
    "wof:placetype":"venue"
},
  "geometry": {"coordinates":[4.2423028946,51.1818351746],"type":"Point"}
}