{
  "type": "Feature",
  "properties": {
    "addr:full":"Heidestraat 76-80 Ternat (sint-katherina-lombeek) Vlaams-Brabant 1742",
    "addr:postcode":"76-80;1742",
    "addr:street":"Heidestraat",
    "iso:country":"BE",
    "sg:address":"Heidestraat 76-80",
    "sg:city":"Ternat (sint-katherina-lombeek)",
    "sg:classifiers":[
        {
            "category":"Parking",
            "subcategory":"Lot",
            "type":"Transportation"
        }
    ],
    "sg:phone":"+32 2 582 15 47",
    "sg:postcode":"1742",
    "sg:province":"Vlaams-Brabant",
    "sg:tags":[
        "parking-places",
        "laying-out"
    ],
    "wof:name":"Van Overstraeten Webo Nv",
    "wof:placetype":"venue"
},
  "geometry": {"coordinates":[4.1424307823,50.8696365356],"type":"Point"}
}