{
  "type": "Feature",
  "properties": {
    "addr:full":"Avenue F. Roosevelt 103 Elsene/ixelles Bruxelles-Capitale 1050",
    "addr:housenumber":"103",
    "addr:postcode":"1050",
    "addr:street":"Avenue F. Roosevelt",
    "iso:country":"BE",
    "sg:address":"Avenue F. Roosevelt 103",
    "sg:city":"Elsene/ixelles",
    "sg:orig_category":"Vertalers and tolken",
    "sg:phone":"+32 2 660 29 42",
    "sg:postcode":"1050",
    "sg:province":"Bruxelles-Capitale",
    "wof:name":"Ioltaa",
    "wof:placetype":"venue"
},
  "geometry": {"coordinates":[4.3798799515,50.8206710815],"type":"Point"}
}