{
  "type": "Feature",
  "properties": {
    "iso:country":"BE",
    "sg:address":"Hooistraat 7",
    "sg:city":"Torhout",
    "sg:classifiers":[
        {
            "category":"Building & Trades",
            "subcategory":"Landscaping Services",
            "type":"Services"
        }
    ],
    "sg:phone":"+32 477 56 42 34",
    "sg:postcode":"8820",
    "sg:province":"West-Vlaanderen",
    "sg:tags":[
        "gardening",
        "garden",
        "maintenance"
    ],
    "wof:name":"Sinnaeve B",
    "wof:placetype":"venue"
},
  "geometry": {"coordinates":[3.0980849266,51.0869750977],"type":"Point"}
}