{
  "type": "Feature",
  "properties": {
    "addr:full":"Voskenslaan 145 Gent Oost-Vlaanderen 9000",
    "addr:housenumber":"145",
    "addr:postcode":"9000",
    "addr:street":"Voskenslaan;Oost-Vlaanderen",
    "iso:country":"BE",
    "sg:address":"Voskenslaan 145",
    "sg:city":"Gent",
    "sg:orig_category":"Maatschappelijke dienstverlening",
    "sg:phone":"+32 9 221 23 22",
    "sg:postcode":"9000",
    "sg:province":"Oost-Vlaanderen",
    "wof:name":"Vclb-centrum",
    "wof:placetype":"venue"
},
  "geometry": {"coordinates":[3.7068579197,51.0312194824],"type":"Point"}
}