{
  "type": "Feature",
  "properties": {
    "addr:full":"Wayezstraat 8 Anderlecht/anderlecht Bruxelles-Capitale 1070",
    "addr:housenumber":"8",
    "addr:postcode":"1070",
    "addr:street":"Wayezstraat",
    "iso:country":"BE",
    "sg:address":"Wayezstraat 8",
    "sg:city":"Anderlecht/anderlecht",
    "sg:orig_category":"Kapsalons",
    "sg:phone":"+32 2 522 38 62",
    "sg:postcode":"1070",
    "sg:province":"Bruxelles-Capitale",
    "wof:name":"Vogue",
    "wof:placetype":"venue"
},
  "geometry": {"coordinates":[4.3168888092,50.8363838196],"type":"Point"}
}