{
  "type": "Feature",
  "properties": {
    "addr:full":"Hopmarkt 26-27 Aalst (groot) Oost-Vlaanderen 9300",
    "addr:housenumber":"26-27",
    "addr:postcode":"9300",
    "addr:street":"Groot Oost-Vlaanderen",
    "iso:country":"BE",
    "sg:address":"Hopmarkt 26-27",
    "sg:city":"Aalst (groot)",
    "sg:classifiers":[
        {
            "category":"Restaurant",
            "type":"Food & Drink"
        }
    ],
    "sg:phone":"+32 53 41 40 01",
    "sg:postcode":"9300",
    "sg:province":"Oost-Vlaanderen",
    "wof:name":"Pizza Hut",
    "wof:placetype":"venue"
},
  "geometry": {"coordinates":[4.0371589661,50.9370002747],"type":"Point"}
}