{
  "type": "Feature",
  "properties": {
    "iso:country":"BE",
    "sg:address":"Rue Du Village 77",
    "sg:city":"Fl\u00c9malle",
    "sg:orig_category":"Avocats and conseillers juridiques",
    "sg:phone":"+32 4 233 43 66",
    "sg:postcode":"4400",
    "sg:province":"Li\u00e8ge",
    "wof:name":"N. Gobin",
    "wof:placetype":"venue"
},
  "geometry": {"coordinates":[5.4651298523,50.5998916626],"type":"Point"}
}