{
  "type": "Feature",
  "properties": {
    "addr:full":"Ter Voort 132 Westerlo Antwerpen 2260",
    "addr:housenumber":"132",
    "addr:postcode":"2260",
    "addr:street":"Ter Voort",
    "iso:country":"BE",
    "sg:address":"Ter Voort 132",
    "sg:city":"Westerlo",
    "sg:classifiers":[
        {
            "category":"Insurance",
            "subcategory":"Life Insurance",
            "type":"Services"
        }
    ],
    "sg:phone":"+32 14 26 77 88",
    "sg:postcode":"2260",
    "sg:province":"Antwerpen",
    "sg:tags":[
        "assurance"
    ],
    "wof:name":"Van Den Bruel",
    "wof:placetype":"venue"
},
  "geometry": {"coordinates":[4.8447461128,51.1206817627],"type":"Point"}
}