{
  "type": "Feature",
  "properties": {
    "addr:full":"Turnhoutsebaan 194 Schilde Antwerpen 2970",
    "addr:housenumber":"194",
    "addr:postcode":"2970",
    "addr:street":"Turnhoutsebaan",
    "iso:country":"BE",
    "sg:address":"Turnhoutsebaan 194",
    "sg:city":"Schilde",
    "sg:orig_category":"Solar protection - Outside",
    "sg:phone":"+32 3 385 83 95",
    "sg:postcode":"2970",
    "sg:province":"Antwerpen",
    "wof:name":"A A A Michaels Nv",
    "wof:placetype":"venue"
},
  "geometry": {"coordinates":[4.5767421722,51.2381401062],"type":"Point"}
}