{
  "type": "Feature",
  "properties": {
    "iso:country":"BE",
    "sg:address":"Colonel Chaltinstraat 85",
    "sg:city":"Ukkel/uccle",
    "sg:orig_category":"Algemeen secundair onderwijs Technisch and beroeps secundair onderwijs",
    "sg:phone":"+32 2 538 28 43",
    "sg:postcode":"1180",
    "sg:province":"Bruxelles-Capitale",
    "wof:name":"Centre Scol. Ma Campagne",
    "wof:placetype":"venue"
},
  "geometry": {"coordinates":[4.3427190781,50.7969322205],"type":"Point"}
}