{
  "type": "Feature",
  "properties": {
    "addr:full":"James Ensorlaan 17 Aartselaar Antwerpen 2630",
    "addr:housenumber":"17",
    "addr:postcode":"2630",
    "addr:street":"James Ensorlaan",
    "iso:country":"BE",
    "sg:address":"James Ensorlaan 17",
    "sg:city":"Aartselaar",
    "sg:orig_category":"Artsen and specialisten",
    "sg:phone":"+32 3 887 97 83",
    "sg:postcode":"2630",
    "sg:province":"Antwerpen",
    "wof:name":"Indra Laureys",
    "wof:placetype":"venue"
},
  "geometry": {"coordinates":[4.3800420761,51.1403656006],"type":"Point"}
}