{
  "type": "Feature",
  "properties": {
    "addr:full":"Guido Gezellestraat 5 Beersel Vlaams-Brabant 1654",
    "addr:housenumber":"5",
    "addr:postcode":"1654",
    "addr:street":"Guido Gezellestraat",
    "iso:country":"BE",
    "sg:address":"Guido Gezellestraat 5",
    "sg:city":"Beersel",
    "sg:classifiers":[
        {
            "category":"Cafe",
            "type":"Food & Drink"
        }
    ],
    "sg:phone":"+32 2 356 28 41",
    "sg:postcode":"1654",
    "sg:province":"Vlaams-Brabant",
    "sg:tags":[
        "caf\u00e9s"
    ],
    "wof:name":"Roger Godau",
    "wof:placetype":"venue"
},
  "geometry": {"coordinates":[4.2638559341,50.749961853],"type":"Point"}
}