{
  "type": "Feature",
  "properties": {
    "addr:full":"Godefriduskaai 22 Box 71 Antwerpen Antwerpen 2000",
    "addr:housenumber":"22 box 71",
    "addr:postcode":"2000",
    "addr:street":"Godefriduskaai",
    "iso:country":"BE",
    "sg:address":"Godefriduskaai 22 Box 71",
    "sg:city":"Antwerpen",
    "sg:classifiers":[
        {
            "category":"Real Estate",
            "subcategory":"Architect",
            "type":"Services"
        }
    ],
    "sg:phone":"+32 3 213 50 70",
    "sg:postcode":"2000",
    "sg:province":"Antwerpen",
    "wof:name":"Poulissen & Partners Architectenbureau Cvba",
    "wof:placetype":"venue"
},
  "geometry": {"coordinates":[4.4076561928,51.2278404236],"type":"Point"}
}