{
  "type": "Feature",
  "properties": {
    "iso:country":"BE",
    "sg:address":"Boneveldstraat 10",
    "sg:city":"Kapelle-op-den-bos",
    "sg:orig_category":"Installation de menuiserie en bois and plastique. Installation de menuiserie m\u00e9tallique",
    "sg:phone":"+32 15 71 27 74",
    "sg:postcode":"1880",
    "sg:province":"Vlaams-Brabant",
    "wof:name":"Geudens Hugo",
    "wof:placetype":"venue"
},
  "geometry": {"coordinates":[4.3525490761,51.0161094666],"type":"Point"}
}