{
  "type": "Feature",
  "properties": {
    "iso:country":"BE",
    "sg:address":"Rue P\u00e8re Maron 34",
    "sg:city":"Esneux",
    "sg:classifiers":[
        {
            "category":"Professional",
            "subcategory":"Management & Consulting",
            "type":"Services"
        }
    ],
    "sg:phone":"+32 4 380 22 84",
    "sg:postcode":"4130",
    "sg:province":"Li\u00e8ge",
    "sg:tags":[
        "consultant"
    ],
    "wof:name":"Europ\u00e9enne De Conseils Sa",
    "wof:placetype":"venue"
},
  "geometry": {"coordinates":[5.5974740982,50.5215606689],"type":"Point"}
}