{
  "type": "Feature",
  "properties": {
    "addr:full":"Chee De Charleroi 116 Bruxelles Bruxelles-Capitale 1060",
    "addr:housenumber":"116",
    "addr:postcode":"1060",
    "addr:street":"Chee",
    "iso:country":"BE",
    "sg:address":"Chee De Charleroi 116",
    "sg:city":"Bruxelles",
    "sg:classifiers":[
        {
            "category":"Banks & Credit Unions",
            "subcategory":"Bank",
            "type":"Services"
        }
    ],
    "sg:postcode":"1060",
    "sg:province":"Bruxelles-Capitale",
    "wof:name":"Infotrade Nv",
    "wof:placetype":"venue"
},
  "geometry": {"coordinates":[4.2628898621,50.8712081909],"type":"Point"}
}