{
  "type": "Feature",
  "properties": {
    "addr:full":"Weg Naar As 48 Genk Limburg 3600",
    "addr:housenumber":"48",
    "addr:postcode":"3600",
    "addr:street":"Weg Naar As",
    "iso:country":"BE",
    "sg:address":"Weg Naar As 48",
    "sg:city":"Genk",
    "sg:orig_category":"Artsen and specialisten",
    "sg:phone":"+32 89 35 41 41",
    "sg:postcode":"3600",
    "sg:province":"Limburg",
    "wof:name":"Louis Van Dijck",
    "wof:placetype":"venue"
},
  "geometry": {"coordinates":[5.5076150894,50.9681510925],"type":"Point"}
}