{
  "type": "Feature",
  "properties": {
    "addr:full":"Rue Saint-michel 28 Bruxelles Bruxelles-Capitale 1000",
    "addr:housenumber":"28",
    "addr:postcode":"1000",
    "addr:street":"Rue Saint-Michel",
    "iso:country":"BE",
    "sg:address":"Rue Saint-michel 28",
    "sg:city":"Bruxelles",
    "sg:classifiers":[
        {
            "category":"Shopping",
            "subcategory":"Clothing, Apparel, & Fashions",
            "type":"Retail Goods"
        }
    ],
    "sg:phone":"+32 2 219 99 02",
    "sg:postcode":"1000",
    "sg:province":"Bruxelles-Capitale",
    "sg:tags":[
        "clothing",
        "-",
        "gentleman"
    ],
    "wof:name":"Laurent Cerrer Belgium",
    "wof:placetype":"venue"
},
  "geometry": {"coordinates":[4.3552441597,50.8522262573],"type":"Point"}
}