{
  "type": "Feature",
  "properties": {
    "addr:full":"Bruggesteenweg 155bb Hooglede West-Vlaanderen 8830",
    "addr:housenumber":"155bb",
    "addr:postcode":"8830",
    "addr:street":"Bruggesteenweg",
    "iso:country":"BE",
    "sg:address":"Bruggesteenweg 155bb",
    "sg:city":"Hooglede",
    "sg:orig_category":"Mat\u00e9riel de T\u00e9l\u00e9communication. D\u00e9taillants en pi\u00e8ces and accessoires de voitures",
    "sg:phone":"+32 51 20 32 64",
    "sg:postcode":"8830",
    "sg:province":"West-Vlaanderen",
    "wof:name":"Fa. Caro",
    "wof:placetype":"venue"
},
  "geometry": {"coordinates":[3.1184489727,50.9829063416],"type":"Point"}
}