{
  "type": "Feature",
  "properties": {
    "addr:full":"Chauss\u00e9e De Wavre 71 Rixensart Brabant Wallon 1330",
    "addr:housenumber":"71",
    "addr:postcode":"1330",
    "addr:street":"Chausse\u0301E De Wavre;Wallon",
    "iso:country":"BE",
    "sg:address":"Chauss\u00e9e De Wavre 71",
    "sg:city":"Rixensart",
    "sg:classifiers":[
        {
            "category":"Building & Trades",
            "subcategory":"Landscaping Services",
            "type":"Services"
        }
    ],
    "sg:phone":"+32 2 652 07 48",
    "sg:postcode":"1330",
    "sg:province":"Brabant Wallon",
    "sg:tags":[
        "-",
        "lopping",
        "work",
        "tree",
        "felling"
    ],
    "wof:name":"Coppens Elagage",
    "wof:placetype":"venue"
},
  "geometry": {"coordinates":[4.5164780617,50.7054405212],"type":"Point"}
}