{
  "type": "Feature",
  "properties": {
    "addr:full":"Wijgmaalsesteenweg 12 Leuven (wilsele) Vlaams-Brabant 3012",
    "addr:housenumber":"12",
    "addr:postcode":"3012",
    "addr:street":"Wijgmaalsesteenweg",
    "iso:country":"BE",
    "sg:address":"Wijgmaalsesteenweg 12",
    "sg:city":"Leuven (wilsele)",
    "sg:classifiers":[
        {
            "category":"Retail",
            "subcategory":"Auto Repair",
            "type":"Services"
        }
    ],
    "sg:phone":"+32 16 29 69 20",
    "sg:postcode":"3012",
    "sg:province":"Vlaams-Brabant",
    "sg:tags":[
        "automobile",
        "-",
        "wrecking"
    ],
    "wof:name":"Autostock Van Den Eynde Bvba",
    "wof:placetype":"venue"
},
  "geometry": {"coordinates":[4.7073612213,50.9046173096],"type":"Point"}
}