{
  "type": "Feature",
  "properties": {
    "iso:country":"BE",
    "sg:address":"Hogewinkelstraat 6",
    "sg:city":"Oud-heverlee",
    "sg:classifiers":[
        {
            "category":"Professional",
            "subcategory":"Accounting & Tax Preparation",
            "type":"Services"
        }
    ],
    "sg:phone":"+32 16 40 32 32",
    "sg:postcode":"3053",
    "sg:province":"Vlaams-Brabant",
    "sg:tags":[
        "accountant"
    ],
    "wof:name":"Marc Casselman",
    "wof:placetype":"venue"
},
  "geometry": {"coordinates":[4.7205781937,50.8338470459],"type":"Point"}
}