{
  "type": "Feature",
  "properties": {
    "iso:country":"BE",
    "sg:address":"Komenstraat 36b",
    "sg:city":"Wervik",
    "sg:orig_category":"Supermarkten",
    "sg:postcode":"8940",
    "sg:province":"West-Vlaanderen",
    "wof:name":"Aldi",
    "wof:placetype":"venue"
},
  "geometry": {"coordinates":[3.0363669395,50.7808570862],"type":"Point"}
}