{
  "type": "Feature",
  "properties": {
    "addr:full":"Torhoutsesteenweg 109 Oostende West-Vlaanderen 8400",
    "addr:housenumber":"109",
    "addr:postcode":"8400",
    "addr:street":"Torhoutsesteenweg",
    "iso:country":"BE",
    "sg:address":"Torhoutsesteenweg 109",
    "sg:city":"Oostende",
    "sg:classifiers":[
        {
            "category":"Personal",
            "subcategory":"Beauty Salon",
            "type":"Services"
        }
    ],
    "sg:phone":"+32 59 50 04 44",
    "sg:postcode":"8400",
    "sg:province":"West-Vlaanderen",
    "sg:tags":[
        "lady",
        "-",
        "hairdressing"
    ],
    "wof:name":"Contrast Coiffure",
    "wof:placetype":"venue"
},
  "geometry": {"coordinates":[2.9084210396,51.2225074768],"type":"Point"}
}