{
  "type": "Feature",
  "properties": {
    "iso:country":"BE",
    "sg:address":"Callemansputtewegel 45a",
    "sg:city":"Evergem (ertvelde)",
    "sg:classifiers":[
        {
            "category":"Retail",
            "subcategory":"Auto Repair",
            "type":"Services"
        }
    ],
    "sg:phone":"+32 9 344 82 08",
    "sg:postcode":"9940",
    "sg:province":"Oost-Vlaanderen",
    "sg:tags":[
        "garage"
    ],
    "wof:name":"Daewoo - Neyt D",
    "wof:placetype":"venue"
},
  "geometry": {"coordinates":[3.7696249485,51.1822853088],"type":"Point"}
}