{
  "type": "Feature",
  "properties": {
    "iso:country":"BE",
    "sg:address":"Limburgerweg 26",
    "sg:city":"Eupen",
    "sg:orig_category":"Sportclubs",
    "sg:phone":"+32 87 74 05 19",
    "sg:postcode":"4700",
    "sg:province":"Li\u00e8ge",
    "wof:name":"Badminton Club Eupen",
    "wof:placetype":"venue"
},
  "geometry": {"coordinates":[6.0269451141,50.6219596863],"type":"Point"}
}