{
  "type": "Feature",
  "properties": {
    "iso:country":"BE",
    "sg:address":"Sint-lucasstraat 41",
    "sg:city":"Lommel",
    "sg:orig_category":"Artsen and specialisten",
    "sg:phone":"+32 11 66 17 41",
    "sg:postcode":"3920",
    "sg:province":"Limburg",
    "wof:name":"Lieve Van Buel",
    "wof:placetype":"venue"
},
  "geometry": {"coordinates":[5.3705759048,51.2380065918],"type":"Point"}
}