{
  "type": "Feature",
  "properties": {
    "iso:country":"BE",
    "sg:address":"Hertogenlaan 13",
    "sg:city":"Lubbeek",
    "sg:orig_category":"Rev\u00eatements de sols and murs",
    "sg:phone":"+32 16 25 53 48",
    "sg:postcode":"3210",
    "sg:province":"Vlaams-Brabant",
    "wof:name":"Jansbergh",
    "wof:placetype":"venue"
},
  "geometry": {"coordinates":[4.7656559944,50.9055633545],"type":"Point"}
}