{
  "type": "Feature",
  "properties": {
    "addr:full":"Tallaart 50 Lier Antwerpen 2500",
    "addr:housenumber":"50",
    "addr:postcode":"2500",
    "addr:street":"Tallaart",
    "iso:country":"BE",
    "sg:address":"Tallaart 50",
    "sg:city":"Lier",
    "sg:orig_category":"Woningbouw",
    "sg:phone":"+32 3 489 26 33",
    "sg:postcode":"2500",
    "sg:province":"Antwerpen",
    "wof:name":"Marc Verrept",
    "wof:placetype":"venue"
},
  "geometry": {"coordinates":[4.5800051689,51.1010017395],"type":"Point"}
}