{
  "type": "Feature",
  "properties": {
    "addr:full":"Chauss\u00e9e De Wervicq 474 Comines-warneton (comines) Hainaut 7780",
    "addr:housenumber":"474",
    "addr:postcode":"7780",
    "addr:street":"Chausse\u0301E De Wervicq",
    "iso:country":"BE",
    "sg:address":"Chauss\u00e9e De Wervicq 474",
    "sg:city":"Comines-warneton (comines)",
    "sg:classifiers":[
        {
            "category":"Health Services",
            "subcategory":"Health Practitioner",
            "type":"Services"
        }
    ],
    "sg:phone":"+32 56 55 74 35",
    "sg:postcode":"7780",
    "sg:province":"Hainaut",
    "sg:tags":[
        "physiotherapist"
    ],
    "wof:name":"Goudeseune S",
    "wof:placetype":"venue"
},
  "geometry": {"coordinates":[3.0177650452,50.7766265869],"type":"Point"}
}