{
  "type": "Feature",
  "properties": {
    "addr:full":"Avenue G. Van Leeuw 81 Bruxelles Bruxelles-Capitale 1140",
    "addr:housenumber":"81",
    "addr:postcode":"1140",
    "addr:street":"Avenue G. Van Leeuw",
    "iso:country":"BE",
    "sg:address":"Avenue G. Van Leeuw 81",
    "sg:city":"Bruxelles",
    "sg:classifiers":[
        {
            "category":"Professional",
            "subcategory":"Business Services",
            "type":"Services"
        }
    ],
    "sg:phone":"+32 2 242 48 32",
    "sg:postcode":"1140",
    "sg:province":"Bruxelles-Capitale",
    "sg:tags":[
        "data"
    ],
    "wof:name":"Multimed S.c.",
    "wof:placetype":"venue"
},
  "geometry": {"coordinates":[4.4061288834,50.8779373169],"type":"Point"}
}