{
  "type": "Feature",
  "properties": {
    "addr:full":"Bokterstraat 13 Peer Limburg 3990",
    "addr:housenumber":"13",
    "addr:postcode":"3990",
    "addr:street":"Bokterstraat",
    "iso:country":"BE",
    "sg:address":"Bokterstraat 13",
    "sg:city":"Peer",
    "sg:classifiers":[
        {
            "category":"Health Services",
            "subcategory":"Health Practitioner",
            "type":"Services"
        }
    ],
    "sg:phone":"+32 11 63 48 69",
    "sg:postcode":"3990",
    "sg:province":"Limburg",
    "sg:tags":[
        "psychologist"
    ],
    "wof:name":"Webers Petra",
    "wof:placetype":"venue"
},
  "geometry": {"coordinates":[5.4514679909,51.1351623535],"type":"Point"}
}