{
  "type": "Feature",
  "properties": {
    "iso:country":"BE",
    "sg:address":"Rue Des Ecoles 5",
    "sg:city":"Neufchateau",
    "sg:orig_category":"Traitements param\u00e9dicaux",
    "sg:phone":"+32 61 27 96 68",
    "sg:postcode":"6840",
    "sg:province":"Luxembourg",
    "wof:name":"G. Rijs",
    "wof:placetype":"venue"
},
  "geometry": {"coordinates":[5.4367141724,49.8435668945],"type":"Point"}
}