{
  "type": "Feature",
  "properties": {
    "iso:country":"BE",
    "sg:address":"Paul Lautersstraat 25",
    "sg:city":"Elsene/ixelles",
    "sg:orig_category":"Groenten and fruit Gh",
    "sg:phone":"+32 2 646 82 19",
    "sg:postcode":"1050",
    "sg:province":"Bruxelles-Capitale",
    "wof:name":"Avimex",
    "wof:placetype":"venue"
},
  "geometry": {"coordinates":[4.3696489334,50.8177146912],"type":"Point"}
}