{
  "type": "Feature",
  "properties": {
    "iso:country":"BE",
    "sg:address":"Hooiwege 47a",
    "sg:city":"Evergem (sleidinge)",
    "sg:classifiers":[
        {
            "category":"Building & Trades",
            "subcategory":"Landscaping Services",
            "type":"Services"
        }
    ],
    "sg:phone":"+32 9 357 66 61",
    "sg:postcode":"9940",
    "sg:province":"Oost-Vlaanderen",
    "sg:tags":[
        "nurseryman"
    ],
    "wof:name":"Bultinck Michel Bvba",
    "wof:placetype":"venue"
},
  "geometry": {"coordinates":[3.6753849983,51.1411628723],"type":"Point"}
}