{
  "type": "Feature",
  "properties": {
    "iso:country":"BE",
    "sg:address":"Rue De Bosquet 20",
    "sg:city":"Saint-gilles (bruxelles)",
    "sg:orig_category":"Pensions de famille",
    "sg:phone":"+32 2 543 74 00",
    "sg:postcode":"1060",
    "sg:province":"Bruxelles-Capitale",
    "wof:name":"Studiotel Le Bosquet",
    "wof:placetype":"venue"
},
  "geometry": {"coordinates":[4.3553800583,50.833114624],"type":"Point"}
}