{
  "type": "Feature",
  "properties": {
    "iso:country":"BE",
    "sg:address":"Hoge Akker 22",
    "sg:city":"Wevelgem",
    "sg:orig_category":"Gespecialiseerde residenti\u00eble bouw",
    "sg:phone":"+32 56 42 29 84",
    "sg:postcode":"8560",
    "sg:province":"West-Vlaanderen",
    "wof:name":"Stefan Eerebout",
    "wof:placetype":"venue"
},
  "geometry": {"coordinates":[3.1825840473,50.81615448],"type":"Point"}
}