{
  "type": "Feature",
  "properties": {
    "iso:country":"BE",
    "sg:address":"Rue Jean Hubin 29",
    "sg:city":"Oupeye",
    "sg:classifiers":[
        {
            "category":"Professional",
            "subcategory":"Secretarial Services",
            "type":"Services"
        }
    ],
    "sg:phone":"+32 4 264 15 39",
    "sg:postcode":"4680",
    "sg:province":"Li\u00e8ge",
    "sg:tags":[
        "firm"
    ],
    "wof:name":"Spits I",
    "wof:placetype":"venue"
},
  "geometry": {"coordinates":[5.6472039223,50.7058601379],"type":"Point"}
}