{
  "type": "Feature",
  "properties": {
    "iso:country":"BE",
    "sg:address":"Rue Des Ormeaux 5",
    "sg:city":"Chimay",
    "sg:orig_category":"Bloemen and planten",
    "sg:phone":"+32 60 21 14 14",
    "sg:postcode":"6460",
    "sg:province":"Hainaut",
    "wof:name":"Cornet",
    "wof:placetype":"venue"
},
  "geometry": {"coordinates":[4.3153457642,50.0478134155],"type":"Point"}
}