{
  "type": "Feature",
  "properties": {
    "addr:full":"Chee.d'alsemberg 849 Ukkel / Uccle Bruxelles-Capitale 1180",
    "addr:housenumber":"849",
    "addr:postcode":"1180",
    "addr:street":"Chee.D'Alsemberg;/",
    "iso:country":"BE",
    "sg:address":"Chee.d'alsemberg 849",
    "sg:city":"Ukkel / Uccle",
    "sg:orig_category":"Agences d\u00b4interim and personnel temporaire",
    "sg:phone":"+32 2 332 00 20",
    "sg:postcode":"1180",
    "sg:province":"Bruxelles-Capitale",
    "wof:name":"Randstad",
    "wof:placetype":"venue"
},
  "geometry": {"coordinates":[4.3627800941,50.7902793884],"type":"Point"}
}