{
  "type": "Feature",
  "properties": {
    "iso:country":"BE",
    "sg:address":"Av. Charles De Li\u00c8ge 33",
    "sg:city":"Binche",
    "sg:orig_category":"Packard Bell Nec. Ordinateurs and \u00e9quipement informatique. Conseils en syst\u00e8mes informatiques. Entre",
    "sg:phone":"+32 64 34 05 03",
    "sg:postcode":"7130",
    "sg:province":"Hainaut",
    "wof:name":"Microcomputer Group",
    "wof:placetype":"venue"
},
  "geometry": {"coordinates":[4.1662912369,50.4124679565],"type":"Point"}
}