{
  "type": "Feature",
  "properties": {
    "addr:full":"Rue Du Muturnia 3 Fleurus Hainaut 6220",
    "addr:housenumber":"3",
    "addr:postcode":"6220",
    "addr:street":"Rue Du Muturnia",
    "iso:country":"BE",
    "sg:address":"Rue Du Muturnia 3",
    "sg:city":"Fleurus",
    "sg:orig_category":"Enseignement maternel and primaire",
    "sg:phone":"+32 71 85 25 95",
    "sg:postcode":"6220",
    "sg:province":"Hainaut",
    "wof:name":"Ecole Fond. Communale",
    "wof:placetype":"venue"
},
  "geometry": {"coordinates":[4.4939870834,50.4809837341],"type":"Point"}
}