{
  "type": "Feature",
  "properties": {
    "addr:full":"Blauwbossen 22 Hoogstraten Antwerpen 2322",
    "addr:housenumber":"22",
    "addr:postcode":"2322",
    "addr:street":"Blauwbossen",
    "iso:country":"BE",
    "sg:address":"Blauwbossen 22",
    "sg:city":"Hoogstraten",
    "sg:orig_category":"Fruitteelt Pluimveekwekers Rundveehouders",
    "sg:phone":"+32 3 315 92 57",
    "sg:postcode":"2322",
    "sg:province":"Antwerpen",
    "wof:name":"Jan Bolckmans",
    "wof:placetype":"venue"
},
  "geometry": {"coordinates":[4.763384819,51.4160041809],"type":"Point"}
}