{
  "type": "Feature",
  "properties": {
    "iso:country":"BE",
    "sg:address":"Henri Dunantlaan 16 Box 2",
    "sg:city":"Hasselt",
    "sg:classifiers":[
        {
            "category":"Real Estate",
            "subcategory":"Architect",
            "type":"Services"
        }
    ],
    "sg:phone":"+32 11 21 03 28",
    "sg:postcode":"3500",
    "sg:province":"Limburg",
    "wof:name":"Ceux G",
    "wof:placetype":"venue"
},
  "geometry": {"coordinates":[5.3447737694,50.9573097229],"type":"Point"}
}