{
  "type": "Feature",
  "properties": {
    "addr:full":"Rue Du Noyer 102 Box 2 Bruxelles (schaerbeek) Bruxelles-Capitale 1030",
    "addr:housenumber":"102;2",
    "addr:postcode":"1030",
    "addr:street":"Rue Du Noyer;Box",
    "iso:country":"BE",
    "sg:address":"Rue Du Noyer 102 Box 2",
    "sg:city":"Bruxelles (schaerbeek)",
    "sg:classifiers":[
        {
            "category":"Health Services",
            "subcategory":"Health Practitioner",
            "type":"Services"
        }
    ],
    "sg:phone":"+32 2 733 68 33",
    "sg:postcode":"1030",
    "sg:province":"Bruxelles-Capitale",
    "sg:tags":[
        "physiotherapist"
    ],
    "wof:name":"Legu\u00e9 Dimitri",
    "wof:placetype":"venue"
},
  "geometry": {"coordinates":[4.3887958527,50.8498725891],"type":"Point"}
}