{
  "type": "Feature",
  "properties": {
    "addr:full":"Cheneux 8 Stoumont Li\u00e8ge 4987",
    "addr:housenumber":"8",
    "addr:postcode":"4987",
    "addr:street":"Cheneux",
    "iso:country":"BE",
    "sg:address":"Cheneux 8",
    "sg:city":"Stoumont",
    "sg:orig_category":"V\u00e9t\u00e9rinaires",
    "sg:phone":"+32 80 78 50 39",
    "sg:postcode":"4987",
    "sg:province":"Li\u00e8ge",
    "wof:name":"Martine Hustin",
    "wof:placetype":"venue"
},
  "geometry": {"coordinates":[5.8163089752,50.3973808289],"type":"Point"}
}