{
  "type": "Feature",
  "properties": {
    "addr:full":"Rue Voie De Messe 44 Beyne-heusay Li\u00e8ge 4610",
    "addr:housenumber":"44",
    "addr:postcode":"4610",
    "addr:street":"Rue Voie De Messe",
    "iso:country":"BE",
    "sg:address":"Rue Voie De Messe 44",
    "sg:city":"Beyne-heusay",
    "sg:orig_category":"Elektrische installaties voor woningen",
    "sg:phone":"+32 4 362 59 78",
    "sg:postcode":"4610",
    "sg:province":"Li\u00e8ge",
    "wof:name":"Olivier Graindor",
    "wof:placetype":"venue"
},
  "geometry": {"coordinates":[5.6712141037,50.6419258118],"type":"Point"}
}