{
  "type": "Feature",
  "properties": {
    "iso:country":"BE",
    "sg:address":"Rodenbachlaan 7",
    "sg:city":"Overpelt",
    "sg:classifiers":[
        {
            "category":"Communications",
            "type":"Services"
        }
    ],
    "sg:phone":"+32 11 80 37 04",
    "sg:postcode":"3900",
    "sg:province":"Limburg",
    "sg:tags":[
        "translator"
    ],
    "wof:name":"Halford Translations Bvba",
    "wof:placetype":"venue"
},
  "geometry": {"coordinates":[5.4257621765,51.2126502991],"type":"Point"}
}