{
  "type": "Feature",
  "properties": {
    "iso:country":"BE",
    "sg:address":"Heulegoedstraat 2",
    "sg:city":"Houthulst (merkem)",
    "sg:classifiers":[
        {
            "category":"Parking",
            "subcategory":"Bicycle",
            "type":"Transportation"
        }
    ],
    "sg:phone":"+32 51 54 52 57",
    "sg:postcode":"8650",
    "sg:province":"West-Vlaanderen",
    "sg:tags":[
        "chiropodist"
    ],
    "wof:name":"Vandevelde H",
    "wof:placetype":"venue"
},
  "geometry": {"coordinates":[2.9509439468,50.9778862],"type":"Point"}
}