{
  "type": "Feature",
  "properties": {
    "iso:country":"BE",
    "sg:address":"Friedensstrasse 6-10",
    "sg:city":"Saint-vith",
    "sg:classifiers":[
        {
            "category":"Communications",
            "subcategory":"Film & Video Production",
            "type":"Services"
        }
    ],
    "sg:phone":"+32 80 28 01 80",
    "sg:postcode":"4780",
    "sg:province":"Li\u00e8ge",
    "sg:tags":[
        "workshop",
        "graphic"
    ],
    "wof:name":"Pro D&p A.g.-s.a.",
    "wof:placetype":"venue"
},
  "geometry": {"coordinates":[6.1237602234,50.2851715088],"type":"Point"}
}