{
  "type": "Feature",
  "properties": {
    "addr:full":"Torekenshoefstraat 25 Ranst Antwerpen 2520",
    "addr:housenumber":"25",
    "addr:postcode":"2520",
    "addr:street":"Torekenshoefstraat",
    "iso:country":"BE",
    "sg:address":"Torekenshoefstraat 25",
    "sg:city":"Ranst",
    "sg:orig_category":"Ordinateurs Fab",
    "sg:phone":"+32 3 485 78 63",
    "sg:postcode":"2520",
    "sg:province":"Antwerpen",
    "wof:name":"L.v. International",
    "wof:placetype":"venue"
},
  "geometry": {"coordinates":[4.5943479538,51.1715126038],"type":"Point"}
}