{
  "type": "Feature",
  "properties": {
    "iso:country":"BE",
    "sg:address":"Chemin Du Gibet 15",
    "sg:city":"Rebecq",
    "sg:orig_category":"Fotografen and fotostudio's",
    "sg:phone":"+32 67 63 80 39",
    "sg:postcode":"1430",
    "sg:province":"Brabant Wallon",
    "wof:name":"Luc Vausort",
    "wof:placetype":"venue"
},
  "geometry": {"coordinates":[4.1300721169,50.6502914429],"type":"Point"}
}