{
  "type": "Feature",
  "properties": {
    "addr:full":"Avenue De Longwy 164 Arlon Luxembourg 6700",
    "addr:housenumber":"164",
    "addr:postcode":"6700",
    "addr:street":"Avenue De Longwy",
    "iso:country":"BE",
    "sg:address":"Avenue De Longwy 164",
    "sg:city":"Arlon",
    "sg:orig_category":"M\u00e9decines alternatives. M\u00e9decins and sp\u00e9cialistes",
    "sg:phone":"+32 63 23 46 20",
    "sg:postcode":"6700",
    "sg:province":"Luxembourg",
    "wof:name":"Docteur Coolens Willy",
    "wof:placetype":"venue"
},
  "geometry": {"coordinates":[5.8243551254,49.6818084717],"type":"Point"}
}