{
  "type": "Feature",
  "properties": {
    "iso:country":"BE",
    "sg:address":"Hoekskensstraat 12",
    "sg:city":"Lochristi",
    "sg:classifiers":[
        {
            "category":"Professional",
            "subcategory":"Art Services",
            "type":"Services"
        }
    ],
    "sg:phone":"+32 9 355 19 77",
    "sg:postcode":"9080",
    "sg:province":"Oost-Vlaanderen",
    "sg:tags":[
        "photographer"
    ],
    "wof:name":"Dtj-art Fotografie",
    "wof:placetype":"venue"
},
  "geometry": {"coordinates":[3.8441329002,51.0999946594],"type":"Point"}
}