{
  "type": "Feature",
  "properties": {
    "iso:country":"BE",
    "sg:address":"Grote Markt 1",
    "sg:city":"Wevelgem",
    "sg:orig_category":"Verplichte sociale verzekeringen",
    "sg:phone":"+32 56 42 35 57",
    "sg:postcode":"8560",
    "sg:province":"West-Vlaanderen",
    "wof:name":"Christelijke Mutualiteit",
    "wof:placetype":"venue"
},
  "geometry": {"coordinates":[3.1845419407,50.8091506958],"type":"Point"}
}