{
  "type": "Feature",
  "properties": {
    "iso:country":"BE",
    "sg:address":"Burgemeester Gillonlaan 39",
    "sg:city":"Kortrijk",
    "sg:classifiers":[
        {
            "category":"Insurance",
            "subcategory":"Life Insurance",
            "type":"Services"
        }
    ],
    "sg:phone":"+32 56 22 30 55",
    "sg:postcode":"8500",
    "sg:province":"West-Vlaanderen",
    "sg:tags":[
        "assurance"
    ],
    "wof:name":"Kortex",
    "wof:placetype":"venue"
},
  "geometry": {"coordinates":[3.2795391083,50.8148727417],"type":"Point"}
}