{
  "type": "Feature",
  "properties": {
    "iso:country":"BE",
    "sg:address":"Molenbaan 48",
    "sg:city":"Merchtem",
    "sg:classifiers":[
        {
            "category":"Cafe",
            "type":"Food & Drink"
        }
    ],
    "sg:phone":"+32 52 37 08 83",
    "sg:postcode":"1785",
    "sg:province":"Vlaams-Brabant",
    "sg:tags":[
        "caf\u00e9s"
    ],
    "wof:name":"Schelkens Luc",
    "wof:placetype":"venue"
},
  "geometry": {"coordinates":[4.2331299782,50.9830055237],"type":"Point"}
}