{
  "type": "Feature",
  "properties": {
    "addr:full":"Kruiskruidlaan 10 Overijse Vlaams-Brabant 3090",
    "addr:housenumber":"10",
    "addr:postcode":"3090",
    "addr:street":"Kruiskruidlaan",
    "iso:country":"BE",
    "sg:address":"Kruiskruidlaan 10",
    "sg:city":"Overijse",
    "sg:classifiers":[
        {
            "category":"Social Services",
            "subcategory":"Job Training",
            "type":"Services"
        }
    ],
    "sg:phone":"+32 2 657 78 10",
    "sg:postcode":"3090",
    "sg:province":"Vlaams-Brabant",
    "sg:tags":[
        "interpreter"
    ],
    "wof:name":"De Cock M-a",
    "wof:placetype":"venue"
},
  "geometry": {"coordinates":[4.494740963,50.774471283],"type":"Point"}
}