{
  "type": "Feature",
  "properties": {
    "addr:full":"Rue Joseph Lescrenier 28 Awans Li\u00e8ge 4340",
    "addr:housenumber":"28",
    "addr:postcode":"4340",
    "addr:street":"Rue Joseph Lescrenier",
    "iso:country":"BE",
    "sg:address":"Rue Joseph Lescrenier 28",
    "sg:city":"Awans",
    "sg:orig_category":"Traitements param\u00e9dicaux",
    "sg:phone":"+32 4 257 42 73",
    "sg:postcode":"4340",
    "sg:province":"Li\u00e8ge",
    "wof:name":"Bemelmans",
    "wof:placetype":"venue"
},
  "geometry": {"coordinates":[5.4704051018,50.7177963257],"type":"Point"}
}