{
  "type": "Feature",
  "properties": {
    "iso:country":"BE",
    "sg:address":"Rue Des Lauriers 3",
    "sg:city":"Li\u00e8ge 1",
    "sg:classifiers":[
        {
            "category":"Shopping",
            "subcategory":"Adult",
            "type":"Retail Goods"
        }
    ],
    "sg:phone":"+32 497 40 97 89",
    "sg:postcode":"4000",
    "sg:province":"Li\u00e8ge",
    "sg:tags":[
        "graphologist"
    ],
    "wof:name":"Troitsky A",
    "wof:placetype":"venue"
},
  "geometry": {"coordinates":[5.5566720963,50.6228561401],"type":"Point"}
}