{
  "type": "Feature",
  "properties": {
    "iso:country":"BE",
    "sg:address":"Chauss\u00e9e De Fleurus 48",
    "sg:city":"Charleroi (gosselies)",
    "sg:classifiers":[
        {
            "category":"Health Services",
            "subcategory":"Dentist",
            "type":"Services"
        }
    ],
    "sg:phone":"+32 71 34 67 47",
    "sg:postcode":"6041",
    "sg:province":"Hainaut",
    "wof:name":"Michel Anne",
    "wof:placetype":"venue"
},
  "geometry": {"coordinates":[4.4720139503,50.4427642822],"type":"Point"}
}