{
  "type": "Feature",
  "properties": {
    "iso:country":"BE",
    "sg:address":"Hulhoek 10",
    "sg:city":"Knesselare",
    "sg:classifiers":[
        {
            "category":"Restaurant",
            "type":"Food & Drink"
        }
    ],
    "sg:phone":"+32 9 374 68 57",
    "sg:postcode":"9910",
    "sg:province":"Oost-Vlaanderen",
    "sg:tags":[
        "caf\u00e9s"
    ],
    "wof:name":"Taverne Kimberly",
    "wof:placetype":"venue"
},
  "geometry": {"coordinates":[3.4264979362,51.1232795715],"type":"Point"}
}