{
  "type": "Feature",
  "properties": {
    "iso:country":"BE",
    "sg:address":"Ingelmunstersteenweg 162",
    "sg:city":"Oostrozebeke",
    "sg:orig_category":"Rev\u00eatements de sols and murs",
    "sg:phone":"+32 56 66 89 24",
    "sg:postcode":"8780",
    "sg:province":"West-Vlaanderen",
    "wof:name":"Martex",
    "wof:placetype":"venue"
},
  "geometry": {"coordinates":[3.3047599792,50.9171829224],"type":"Point"}
}