{
  "type": "Feature",
  "properties": {
    "iso:country":"BE",
    "sg:address":"Schwarzenbeklaan 17",
    "sg:city":"Zelzate",
    "sg:classifiers":[
        {
            "category":"Arena",
            "subcategory":"Sports Club",
            "type":"Entertainment"
        }
    ],
    "sg:phone":"+32 9 345 53 30",
    "sg:postcode":"9060",
    "sg:province":"Oost-Vlaanderen",
    "sg:tags":[
        "terrain",
        "hors",
        "de",
        "installation",
        "sportifs"
    ],
    "wof:name":"F.c. Zelzate",
    "wof:placetype":"venue"
},
  "geometry": {"coordinates":[3.8124148846,51.1947822571],"type":"Point"}
}