{
  "type": "Feature",
  "properties": {
    "iso:country":"BE",
    "sg:address":"Meerweg 162",
    "sg:city":"Sint-pieters-leeuw",
    "sg:orig_category":"Parfumeries",
    "sg:phone":"+32 2 377 39 70",
    "sg:postcode":"1600",
    "sg:province":"Vlaams-Brabant",
    "wof:name":"Dominique Wilkin",
    "wof:placetype":"venue"
},
  "geometry": {"coordinates":[4.2832369804,50.783416748],"type":"Point"}
}