{
  "type": "Feature",
  "properties": {
    "addr:full":"Grand'rue 64 Gembloux-sur-orneau (gembloux) Namur 5030",
    "addr:housenumber":"64",
    "addr:postcode":"5030",
    "addr:street":"Grand'Rue;Namur",
    "iso:country":"BE",
    "sg:address":"Grand'rue 64",
    "sg:city":"Gembloux-sur-orneau (gembloux)",
    "sg:classifiers":[
        {
            "category":"Wholesale",
            "subcategory":"Machinery & Supplies",
            "type":"Manufacturing & Wholesale Goods"
        }
    ],
    "sg:phone":"+32 81 61 10 88",
    "sg:postcode":"5030",
    "sg:province":"Namur",
    "sg:tags":[
        "retail",
        "-",
        "electric"
    ],
    "wof:name":"Cuvelier J-p",
    "wof:placetype":"venue"
},
  "geometry": {"coordinates":[4.6945400238,50.5666313171],"type":"Point"}
}