{
  "type": "Feature",
  "properties": {
    "iso:country":"BE",
    "sg:address":"Rue De Biese 2",
    "sg:city":"Ronse/renaix",
    "sg:orig_category":"Offices du tourisme",
    "sg:phone":"+32 55 23 28 16",
    "sg:postcode":"9600",
    "sg:province":"Oost-Vlaanderen",
    "wof:name":"G.v.v.v. Vlaamse Ardennen",
    "wof:placetype":"venue"
},
  "geometry": {"coordinates":[3.6021440029,50.749080658],"type":"Point"}
}