{
  "type": "Feature",
  "properties": {
    "addr:full":"Rue Hov\u00e9mont 137 Theux Li\u00e8ge 4910",
    "addr:housenumber":"137",
    "addr:postcode":"4910",
    "addr:street":"Rue Hove\u0301Mont",
    "iso:country":"BE",
    "sg:address":"Rue Hov\u00e9mont 137",
    "sg:city":"Theux",
    "sg:classifiers":[
        {
            "category":"Retail",
            "subcategory":"Veterinary Services",
            "type":"Services"
        }
    ],
    "sg:phone":"+32 87 44 86 86",
    "sg:postcode":"4910",
    "sg:province":"Li\u00e8ge",
    "sg:tags":[
        "veterinarian"
    ],
    "wof:name":"Masure S",
    "wof:placetype":"venue"
},
  "geometry": {"coordinates":[5.8151898384,50.5320892334],"type":"Point"}
}