{
  "type": "Feature",
  "properties": {
    "addr:full":"Rue De L'azeille 24 Philippeville Namur 5600",
    "addr:housenumber":"24",
    "addr:postcode":"5600",
    "addr:street":"Rue De L'Azeille",
    "iso:country":"BE",
    "sg:address":"Rue De L'azeille 24",
    "sg:city":"Philippeville",
    "sg:classifiers":[
        {
            "category":"Communications",
            "subcategory":"Film & Video Production",
            "type":"Services"
        }
    ],
    "sg:phone":"+32 60 31 17 49",
    "sg:postcode":"5600",
    "sg:province":"Namur",
    "sg:tags":[
        "commerce",
        "electrom\u00e9nager",
        "t\u00e9l\u00e9visions",
        "equipement",
        "pour",
        "radio",
        "diver"
    ],
    "wof:name":"Frigo-service",
    "wof:placetype":"venue"
},
  "geometry": {"coordinates":[4.5423660278,50.1357002258],"type":"Point"}
}