{
  "type": "Feature",
  "properties": {
    "addr:full":"Rue Du Ch\u00c2telain 36 Elsene Bruxelles-Capitale 1050",
    "addr:housenumber":"36",
    "addr:postcode":"1050",
    "addr:street":"Rue Du Cha\u0302Telain",
    "iso:country":"BE",
    "sg:address":"Rue Du Ch\u00c2telain 36",
    "sg:city":"Elsene",
    "sg:orig_category":"Gespecialiseerde residenti\u00eble bouw",
    "sg:phone":"+32 2 646 00 12",
    "sg:postcode":"1050",
    "sg:province":"Bruxelles-Capitale",
    "wof:name":"Fontec",
    "wof:placetype":"venue"
},
  "geometry": {"coordinates":[4.3620629311,50.8253707886],"type":"Point"}
}