{
  "type": "Feature",
  "properties": {
    "addr:full":"Tavigny 51 Houffalize Luxembourg 6662",
    "addr:housenumber":"51",
    "addr:postcode":"6662",
    "addr:street":"Tavigny",
    "iso:country":"BE",
    "sg:address":"Tavigny 51",
    "sg:city":"Houffalize",
    "sg:orig_category":"Maisons de vacances",
    "sg:phone":"+32 61 28 94 33",
    "sg:postcode":"6662",
    "sg:province":"Luxembourg",
    "wof:name":"Piron Olivier",
    "wof:placetype":"venue"
},
  "geometry": {"coordinates":[5.8380899429,50.108253479],"type":"Point"}
}