{
  "type": "Feature",
  "properties": {
    "iso:country":"BE",
    "sg:address":"Stratem 56",
    "sg:city":"Aalter",
    "sg:classifiers":[
        {
            "category":"Building & Trades",
            "subcategory":"Cleaning & Sanitation",
            "type":"Services"
        }
    ],
    "sg:phone":"+32 9 374 75 55",
    "sg:postcode":"9880",
    "sg:province":"Oost-Vlaanderen",
    "sg:tags":[
        "fa\u00e7ade",
        "maintenance"
    ],
    "wof:name":"Botterman B",
    "wof:placetype":"venue"
},
  "geometry": {"coordinates":[3.4260520935,51.086555481],"type":"Point"}
}