{
  "type": "Feature",
  "properties": {
    "addr:full":"Tervuursesteenweg 161 Kortenberg Vlaams-Brabant 3078",
    "addr:housenumber":"161",
    "addr:postcode":"3078",
    "addr:street":"Tervuursesteenweg;Vlaams-Brabant",
    "iso:country":"BE",
    "sg:address":"Tervuursesteenweg 161",
    "sg:city":"Kortenberg",
    "sg:orig_category":"Tuinen",
    "sg:phone":"+32 2 757 17 72",
    "sg:postcode":"3078",
    "sg:province":"Vlaams-Brabant",
    "wof:name":"G. Verheecke",
    "wof:placetype":"venue"
},
  "geometry": {"coordinates":[4.5541000366,50.8589897156],"type":"Point"}
}