{
  "type": "Feature",
  "properties": {
    "iso:country":"BE",
    "sg:address":"Kouterbaan 10",
    "sg:city":"Denderleeuw",
    "sg:classifiers":[
        {
            "category":"Professional",
            "subcategory":"Testing Lab",
            "type":"Services"
        }
    ],
    "sg:phone":"+32 53 66 75 18",
    "sg:postcode":"9470",
    "sg:province":"Oost-Vlaanderen",
    "sg:tags":[
        "chemist"
    ],
    "wof:name":"Van Den Neucker",
    "wof:placetype":"venue"
},
  "geometry": {"coordinates":[4.0722222328,50.8873634338],"type":"Point"}
}