{
  "type": "Feature",
  "properties": {
    "addr:full":"Rue Des Pommiers 10 Charleroi Hainaut 6001",
    "addr:housenumber":"10",
    "addr:postcode":"6001",
    "addr:street":"Rue Des Pommiers;Hainaut",
    "iso:country":"BE",
    "sg:address":"Rue Des Pommiers 10",
    "sg:city":"Charleroi",
    "sg:classifiers":[
        {
            "category":"Personal",
            "subcategory":"Beauty Salon",
            "type":"Services"
        }
    ],
    "sg:phone":"+32 71 36 44 25",
    "sg:postcode":"6001",
    "sg:province":"Hainaut",
    "sg:tags":[
        "de",
        "coiffure"
    ],
    "wof:name":"Coiffure Nicole",
    "wof:placetype":"venue"
},
  "geometry": {"coordinates":[4.4439849854,50.3858299255],"type":"Point"}
}