{
  "type": "Feature",
  "properties": {
    "iso:country":"BE",
    "sg:address":"Rue Lemaire 52",
    "sg:city":"Oupeye",
    "sg:classifiers":[
        {
            "category":"Cafe",
            "type":"Food & Drink"
        }
    ],
    "sg:phone":"+32 4 379 18 53",
    "sg:postcode":"4684",
    "sg:province":"Li\u00e8ge",
    "sg:tags":[
        "caf\u00e9s"
    ],
    "wof:name":"Caf\u00c9 L'union",
    "wof:placetype":"venue"
},
  "geometry": {"coordinates":[5.6693868637,50.7321052551],"type":"Point"}
}