{
  "type": "Feature",
  "properties": {
    "addr:full":"St Klarastraat 34 Brugge West-Vlaanderen 8000",
    "addr:housenumber":"34",
    "addr:postcode":"8000",
    "addr:street":"Klarastraat",
    "iso:country":"BE",
    "sg:address":"St Klarastraat 34",
    "sg:city":"Brugge",
    "sg:orig_category":"Agences Matrimoniales et de Rencontre. Etablissements Erotiques",
    "sg:phone":"+32 473 24 67 28",
    "sg:postcode":"8000",
    "sg:province":"West-Vlaanderen",
    "wof:name":"Regina",
    "wof:placetype":"venue"
},
  "geometry": {"coordinates":[3.2226760387,51.2155189514],"type":"Point"}
}