{
  "type": "Feature",
  "properties": {
    "addr:full":"Dadizelestraat 14 Ledegem West-Vlaanderen 8880",
    "addr:housenumber":"14",
    "addr:postcode":"8880",
    "addr:street":"Dadizelestraat",
    "iso:country":"BE",
    "sg:address":"Dadizelestraat 14",
    "sg:city":"Ledegem",
    "sg:orig_category":"Groententeelt",
    "sg:phone":"+32 56 50 97 81",
    "sg:postcode":"8880",
    "sg:province":"West-Vlaanderen",
    "wof:name":"Geert Breyne",
    "wof:placetype":"venue"
},
  "geometry": {"coordinates":[3.1031498909,50.8555831909],"type":"Point"}
}