{
  "type": "Feature",
  "properties": {
    "addr:full":"Ginderbuiten 105 Mol Antwerpen 2400",
    "addr:housenumber":"105",
    "addr:postcode":"2400",
    "addr:street":"Ginderbuiten",
    "iso:country":"BE",
    "sg:address":"Ginderbuiten 105",
    "sg:city":"Mol",
    "sg:classifiers":[
        {
            "category":"Fast Food",
            "type":"Food & Drink"
        }
    ],
    "sg:phone":"+32 14 31 40 00",
    "sg:postcode":"2400",
    "sg:province":"Antwerpen",
    "sg:tags":[
        "fried",
        "stand",
        "potato"
    ],
    "wof:name":"Tom's Diner",
    "wof:placetype":"venue"
},
  "geometry": {"coordinates":[5.146900177,51.2030792236],"type":"Point"}
}