{
  "type": "Feature",
  "properties": {
    "addr:full":"Rue Des Taxandres 21 Box 6 Bruxelles (etterbeek) Bruxelles-Capitale 1040",
    "addr:housenumber":"21;6",
    "addr:postcode":"1040",
    "addr:street":"Rue Des Taxandres;Box",
    "iso:country":"BE",
    "sg:address":"Rue Des Taxandres 21 Box 6",
    "sg:city":"Bruxelles (etterbeek)",
    "sg:classifiers":[
        {
            "category":"Professional",
            "subcategory":"Lawyer & Legal Services",
            "type":"Services"
        }
    ],
    "sg:phone":"+32 2 734 73 35",
    "sg:postcode":"1040",
    "sg:province":"Bruxelles-Capitale",
    "wof:name":"Reypens Paul",
    "wof:placetype":"venue"
},
  "geometry": {"coordinates":[4.4020280838,50.8364715576],"type":"Point"}
}