{
  "type": "Feature",
  "properties": {
    "addr:full":"Vijverstraat 31 Sint-niklaas (belsele) Oost-Vlaanderen 9111",
    "addr:housenumber":"31",
    "addr:postcode":"9111",
    "addr:street":"Vijverstraat",
    "iso:country":"BE",
    "sg:address":"Vijverstraat 31",
    "sg:city":"Sint-niklaas (belsele)",
    "sg:classifiers":[
        {
            "category":"Health Services",
            "subcategory":"Health Practitioner",
            "type":"Services"
        }
    ],
    "sg:phone":"+32 3 772 29 24",
    "sg:postcode":"9111",
    "sg:province":"Oost-Vlaanderen",
    "sg:tags":[
        "physiotherapist"
    ],
    "wof:name":"Buyle Dirk",
    "wof:placetype":"venue"
},
  "geometry": {"coordinates":[4.083137989,51.1433753967],"type":"Point"}
}