{
  "type": "Feature",
  "properties": {
    "iso:country":"BE",
    "sg:address":"Rue Des Ponts 64",
    "sg:city":"Ans",
    "sg:classifiers":[
        {
            "category":"Real Estate",
            "subcategory":"Architect",
            "type":"Services"
        }
    ],
    "sg:phone":"+32 4 263 83 93",
    "sg:postcode":"4430",
    "sg:province":"Li\u00e8ge",
    "wof:name":"Maquet J-c",
    "wof:placetype":"venue"
},
  "geometry": {"coordinates":[5.516119957,50.6616592407],"type":"Point"}
}