{
  "type": "Feature",
  "properties": {
    "addr:full":"Nieuwe Kerkstraat 71 Kruibeke Oost-Vlaanderen 9150",
    "addr:housenumber":"71",
    "addr:postcode":"9150",
    "addr:street":"Nieuwe Kerkstraat",
    "iso:country":"BE",
    "sg:address":"Nieuwe Kerkstraat 71",
    "sg:city":"Kruibeke",
    "sg:classifiers":[
        {
            "category":"Insurance",
            "subcategory":"Insurance Agent",
            "type":"Services"
        }
    ],
    "sg:phone":"+32 3 774 51 44",
    "sg:postcode":"9150",
    "sg:province":"Oost-Vlaanderen",
    "sg:tags":[
        "verzekeringsmakelaars",
        "expert"
    ],
    "wof:name":"R. Van Havere",
    "wof:placetype":"venue"
},
  "geometry": {"coordinates":[4.3109378815,51.1754226685],"type":"Point"}
}