{
  "type": "Feature",
  "properties": {
    "iso:country":"BE",
    "sg:address":"Rue De La Demoiselle 9",
    "sg:city":"Saint-l\u00e9ger",
    "sg:classifiers":[
        {
            "category":"Parking",
            "subcategory":"Lot",
            "type":"Transportation"
        }
    ],
    "sg:phone":"+32 63 23 91 35",
    "sg:postcode":"6747",
    "sg:province":"Luxembourg",
    "sg:tags":[
        "parking-places",
        "laying-out"
    ],
    "wof:name":"Hissette N",
    "wof:placetype":"venue"
},
  "geometry": {"coordinates":[5.6541252136,49.6137962341],"type":"Point"}
}