{
  "type": "Feature",
  "properties": {
    "addr:full":"Bauwelstraat 2 Kortenaken Vlaams-Brabant 3470",
    "addr:housenumber":"2",
    "addr:postcode":"3470",
    "addr:street":"Bauwelstraat",
    "iso:country":"BE",
    "sg:address":"Bauwelstraat 2",
    "sg:city":"Kortenaken",
    "sg:classifiers":[
        {
            "category":"Bars & Pubs",
            "type":"Food & Drink"
        }
    ],
    "sg:phone":"+32 11 58 75 21",
    "sg:postcode":"3470",
    "sg:province":"Vlaams-Brabant",
    "wof:name":"Hoef (de)",
    "wof:placetype":"venue"
},
  "geometry": {"coordinates":[5.036523819,50.8922386169],"type":"Point"}
}