{
  "type": "Feature",
  "properties": {
    "addr:full":"Avenue Louis Lepoutre 28 Elsene/ixelles Bruxelles-Capitale 1050",
    "addr:housenumber":"28",
    "addr:postcode":"1050",
    "addr:street":"Avenue Louis Lepoutre",
    "iso:country":"BE",
    "sg:address":"Avenue Louis Lepoutre 28",
    "sg:city":"Elsene/ixelles",
    "sg:orig_category":"M\u00e9decins and sp\u00e9cialistes",
    "sg:phone":"+32 2 343 03 93",
    "sg:postcode":"1050",
    "sg:province":"Bruxelles-Capitale",
    "wof:name":"Thierry Ceurvorst",
    "wof:placetype":"venue"
},
  "geometry": {"coordinates":[4.3588290215,50.8194122314],"type":"Point"}
}