{
  "type": "Feature",
  "properties": {
    "addr:full":"Rue Albert 1er 384 Erquelinnes Hainaut 6560",
    "addr:housenumber":"384",
    "addr:postcode":"6560",
    "addr:street":"Rue Albert 1Er",
    "iso:country":"BE",
    "sg:address":"Rue Albert 1er 384",
    "sg:city":"Erquelinnes",
    "sg:classifiers":[
        {
            "category":"Personal",
            "subcategory":"Piercing",
            "type":"Services"
        }
    ],
    "sg:phone":"+32 476 85 02 57",
    "sg:postcode":"6560",
    "sg:province":"Hainaut",
    "sg:tags":[
        "piercings",
        "tatoeages"
    ],
    "wof:name":"Tattoo' Vu",
    "wof:placetype":"venue"
},
  "geometry": {"coordinates":[4.1240048409,50.3106956482],"type":"Point"}
}