{
  "type": "Feature",
  "properties": {
    "addr:full":"Rue Jules Destr\u00e9e 1 Gr\u00e2ce-hollogne (gr\u00e2ce-berleur) Li\u00e8ge 4460",
    "addr:housenumber":"1",
    "addr:postcode":"4460",
    "addr:street":"Rue Jules Destre\u0301E;Gra\u0302Ce-Berleur",
    "iso:country":"BE",
    "sg:address":"Rue Jules Destr\u00e9e 1",
    "sg:city":"Gr\u00e2ce-hollogne (gr\u00e2ce-berleur)",
    "sg:classifiers":[
        {
            "category":"Professional",
            "subcategory":"Detective & Security Services",
            "type":"Services"
        }
    ],
    "sg:phone":"+32 4 239 16 76",
    "sg:postcode":"4460",
    "sg:province":"Li\u00e8ge",
    "sg:tags":[
        "guard"
    ],
    "wof:name":"Cal'security",
    "wof:placetype":"venue"
},
  "geometry": {"coordinates":[5.5073361397,50.6405754089],"type":"Point"}
}