{
  "type": "Feature",
  "properties": {
    "addr:full":"Industrieweg 5 Leuven (heverlee) Vlaams-Brabant 3001",
    "addr:housenumber":"5",
    "addr:postcode":"3001",
    "addr:street":"Industrieweg",
    "iso:country":"BE",
    "sg:address":"Industrieweg 5",
    "sg:city":"Leuven (heverlee)",
    "sg:orig_category":"Non-Classified Establishments",
    "sg:phone":"+32 16 40 05 00",
    "sg:postcode":"3001",
    "sg:province":"Vlaams-Brabant",
    "wof:name":"Givatec Bvba",
    "wof:placetype":"venue"
},
  "geometry": {"coordinates":[4.72371912,50.8453216553],"type":"Point"}
}