{
  "type": "Feature",
  "properties": {
    "addr:full":"Korspelsesteenweg 225 Beringen Limburg 3581",
    "addr:housenumber":"225",
    "addr:postcode":"3581",
    "addr:street":"Korspelsesteenweg",
    "iso:country":"BE",
    "sg:address":"Korspelsesteenweg 225",
    "sg:city":"Beringen",
    "sg:orig_category":"Kapsalons",
    "sg:phone":"+32 11 39 35 08",
    "sg:postcode":"3581",
    "sg:province":"Limburg",
    "wof:name":"Agna De Meulemeester",
    "wof:placetype":"venue"
},
  "geometry": {"coordinates":[5.2345099449,51.0883598328],"type":"Point"}
}