{
  "type": "Feature",
  "properties": {
    "iso:country":"BE",
    "sg:address":"Meiveld 6",
    "sg:city":"Asse (relegem)",
    "sg:classifiers":[
        {
            "category":"Professional",
            "subcategory":"Accounting & Tax Preparation",
            "type":"Services"
        }
    ],
    "sg:phone":"+32 2 460 18 95",
    "sg:postcode":"1731",
    "sg:province":"Vlaams-Brabant",
    "sg:tags":[
        "bookkeeper"
    ],
    "wof:name":"Junius M",
    "wof:placetype":"venue"
},
  "geometry": {"coordinates":[4.2887210846,50.9065742493],"type":"Point"}
}