{
  "type": "Feature",
  "properties": {
    "addr:full":"Lichtenbuscherstrasse 115 Raeren Li\u00e8ge 4731",
    "addr:housenumber":"115",
    "addr:postcode":"4731",
    "addr:street":"Lichtenbuscherstrasse",
    "iso:country":"BE",
    "sg:address":"Lichtenbuscherstrasse 115",
    "sg:city":"Raeren",
    "sg:orig_category":"Boekhouders",
    "sg:phone":"+32 87 85 22 79",
    "sg:postcode":"4731",
    "sg:province":"Li\u00e8ge",
    "wof:name":"Nathalie Kessler",
    "wof:placetype":"venue"
},
  "geometry": {"coordinates":[6.0931529999,50.6969528198],"type":"Point"}
}