{
  "type": "Feature",
  "properties": {
    "addr:full":"Rue Chapelle-dieu 33 Gembloux Namur 5030",
    "addr:housenumber":"33",
    "addr:postcode":"5030",
    "addr:street":"Rue Chapelle-Dieu;Namur",
    "iso:country":"BE",
    "sg:address":"Rue Chapelle-dieu 33",
    "sg:city":"Gembloux",
    "sg:orig_category":"Boekhouders",
    "sg:phone":"+32 81 61 39 62",
    "sg:postcode":"5030",
    "sg:province":"Namur",
    "wof:name":"Francoise Sokay",
    "wof:placetype":"venue"
},
  "geometry": {"coordinates":[4.6984372139,50.5583724976],"type":"Point"}
}