{
  "type": "Feature",
  "properties": {
    "iso:country":"BE",
    "sg:address":"Kuringersteenweg 526",
    "sg:city":"Hasselt (kuringen)",
    "sg:classifiers":[
        {
            "category":"Autos & Motor Vehicles",
            "subcategory":"Fuel & Gas Station",
            "type":"Retail Goods"
        }
    ],
    "sg:phone":"+32 11 25 15 92",
    "sg:postcode":"3511",
    "sg:province":"Limburg",
    "wof:name":"Esso-gerann Bvba ( Verboven )",
    "wof:placetype":"venue"
},
  "geometry": {"coordinates":[5.2892398834,50.9426689148],"type":"Point"}
}