{
  "type": "Feature",
  "properties": {
    "addr:full":"Haantjeslei 70b-74 Antwerpen Antwerpen 2018",
    "addr:housenumber":"70b-74",
    "addr:postcode":"2018",
    "addr:street":"Haantjeslei",
    "iso:country":"BE",
    "sg:address":"Haantjeslei 70b-74",
    "sg:city":"Antwerpen",
    "sg:orig_category":"Farmaceutische bereidingen and geneesmiddelen Fab",
    "sg:phone":"+32 3 237 43 63",
    "sg:postcode":"2018",
    "sg:province":"Antwerpen",
    "wof:name":"Laboratoria Wolfs",
    "wof:placetype":"venue"
},
  "geometry": {"coordinates":[4.3997869492,51.2024803162],"type":"Point"}
}