{
  "type": "Feature",
  "properties": {
    "iso:country":"BE",
    "sg:address":"Zouavenpad 10",
    "sg:city":"Koksijde",
    "sg:orig_category":"Eleveurs and marchands de porcs",
    "sg:phone":"+32 58 23 38 56",
    "sg:postcode":"8670",
    "sg:province":"West-Vlaanderen",
    "wof:name":"Lucien Reunbrouck",
    "wof:placetype":"venue"
},
  "geometry": {"coordinates":[2.6391119957,51.1213302612],"type":"Point"}
}