{
  "type": "Feature",
  "properties": {
    "iso:country":"BE",
    "sg:address":"Sint Rochusstraat 56",
    "sg:city":"Aalst",
    "sg:orig_category":"Bloemen and planten",
    "sg:phone":"+32 53 83 05 55",
    "sg:postcode":"9320",
    "sg:province":"Oost-Vlaanderen",
    "wof:name":"Bloemist Hoebeeck",
    "wof:placetype":"venue"
},
  "geometry": {"coordinates":[4.0006108284,50.9164924622],"type":"Point"}
}