{
  "type": "Feature",
  "properties": {
    "addr:full":"Besmelaan 18 Vorst/forest Bruxelles-Capitale 1190",
    "addr:housenumber":"18",
    "addr:postcode":"1190",
    "addr:street":"Besmelaan;/ Forest",
    "iso:country":"BE",
    "sg:address":"Besmelaan 18",
    "sg:city":"Vorst/forest",
    "sg:orig_category":"Ambassades and consulaten",
    "sg:phone":"+32 2 344 69 74",
    "sg:postcode":"1190",
    "sg:province":"Bruxelles-Capitale",
    "wof:name":"Ambassade & Consulaat Van Mongoli\u00cb",
    "wof:placetype":"venue"
},
  "geometry": {"coordinates":[4.3353319168,50.8196487427],"type":"Point"}
}