{
  "type": "Feature",
  "properties": {
    "addr:full":"Sint-jacobsnieuwweg 12 Ieper West-Vlaanderen 8900",
    "addr:housenumber":"12",
    "addr:postcode":"8900",
    "addr:street":"Sint-Jacobsnieuwweg",
    "iso:country":"BE",
    "sg:address":"Sint-jacobsnieuwweg 12",
    "sg:city":"Ieper",
    "sg:classifiers":[
        {
            "category":"Communications",
            "subcategory":"Television Station",
            "type":"Services"
        }
    ],
    "sg:phone":"+32 57 21 95 07",
    "sg:postcode":"8900",
    "sg:province":"West-Vlaanderen",
    "sg:tags":[
        "report",
        "video"
    ],
    "wof:name":"Ldi Videoproducties",
    "wof:placetype":"venue"
},
  "geometry": {"coordinates":[2.8893060684,50.84948349],"type":"Point"}
}