{
  "type": "Feature",
  "properties": {
    "addr:full":"Provinciesteenweg 213 Boechout Antwerpen 2530",
    "addr:housenumber":"213",
    "addr:postcode":"2530",
    "addr:street":"Provinciesteenweg",
    "iso:country":"BE",
    "sg:address":"Provinciesteenweg 213",
    "sg:city":"Boechout",
    "sg:classifiers":[
        {
            "category":"Professional",
            "subcategory":"Accounting & Tax Preparation",
            "type":"Services"
        }
    ],
    "sg:phone":"+32 3 454 36 21",
    "sg:postcode":"2530",
    "sg:province":"Antwerpen",
    "sg:tags":[
        "bookkeeper"
    ],
    "wof:name":"Shiana Bvba",
    "wof:placetype":"venue"
},
  "geometry": {"coordinates":[4.4997611046,51.1648406982],"type":"Point"}
}