{
  "type": "Feature",
  "properties": {
    "iso:country":"BE",
    "sg:address":"Hof Somergem 58",
    "sg:city":"Aalst",
    "sg:classifiers":[
        {
            "category":"Personal",
            "subcategory":"Beauty Salon",
            "type":"Services"
        }
    ],
    "sg:phone":"+32 53 77 57 76",
    "sg:postcode":"9300",
    "sg:province":"Oost-Vlaanderen",
    "wof:name":"Beauty & Style",
    "wof:placetype":"venue"
},
  "geometry": {"coordinates":[4.0782799721,50.9282493591],"type":"Point"}
}