{
  "type": "Feature",
  "properties": {
    "iso:country":"BE",
    "sg:address":"Paalstraat 8",
    "sg:city":"Brugge",
    "sg:classifiers":[
        {
            "category":"Professional",
            "subcategory":"Art Services",
            "type":"Services"
        }
    ],
    "sg:phone":"+32 50 34 94 31",
    "sg:postcode":"8000",
    "sg:province":"West-Vlaanderen",
    "sg:tags":[
        "graphic",
        "designer"
    ],
    "wof:name":"Corpus",
    "wof:placetype":"venue"
},
  "geometry": {"coordinates":[3.2159850597,51.2060165405],"type":"Point"}
}