{
  "type": "Feature",
  "properties": {
    "addr:full":"Av. Princesse Elisabeth 54 Schaarbeek/schaerbeek Bruxelles-Capitale 1030",
    "addr:housenumber":"54",
    "addr:postcode":"1030",
    "addr:street":"Av. Princesse Elisabeth",
    "iso:country":"BE",
    "sg:address":"Av. Princesse Elisabeth 54",
    "sg:city":"Schaarbeek/schaerbeek",
    "sg:orig_category":"M\u00e9decins and sp\u00e9cialistes",
    "sg:phone":"+32 2 245 61 09",
    "sg:postcode":"1030",
    "sg:province":"Bruxelles-Capitale",
    "wof:name":"Christilla Coussement",
    "wof:placetype":"venue"
},
  "geometry": {"coordinates":[4.3770098686,50.8733024597],"type":"Point"}
}