{
  "type": "Feature",
  "properties": {
    "addr:full":"Rue De Vise 782 Li\u00c8ge Li\u00e8ge 4020",
    "addr:housenumber":"782",
    "addr:postcode":"4020",
    "addr:street":"Rue De Vise",
    "iso:country":"BE",
    "sg:address":"Rue De Vise 782",
    "sg:city":"Li\u00c8ge",
    "sg:orig_category":"Enseignement maternel and primaire",
    "sg:phone":"+32 4 362 32 77",
    "sg:postcode":"4020",
    "sg:province":"Li\u00e8ge",
    "wof:name":"Ecole Matern. Communale",
    "wof:placetype":"venue"
},
  "geometry": {"coordinates":[5.6463298798,50.6544799805],"type":"Point"}
}