{
  "type": "Feature",
  "properties": {
    "iso:country":"BE",
    "sg:address":"Oude Bemdens 40",
    "sg:city":"Houthalen-helchteren",
    "sg:orig_category":"Artiesten and kunstenaars",
    "sg:phone":"+32 11 52 62 84",
    "sg:postcode":"3530",
    "sg:province":"Limburg",
    "wof:name":"Andres Pedrosa-ibanez",
    "wof:placetype":"venue"
},
  "geometry": {"coordinates":[5.3771328926,51.0245132446],"type":"Point"}
}