{
  "type": "Feature",
  "properties": {
    "addr:full":"Plattesteen 11 Bruxelles Bruxelles-Capitale 1000",
    "addr:housenumber":"11",
    "addr:postcode":"1000",
    "addr:street":"Plattesteen",
    "iso:country":"BE",
    "sg:address":"Plattesteen 11",
    "sg:city":"Bruxelles",
    "sg:classifiers":[
        {
            "category":"Coffee & Tea",
            "type":"Food & Drink"
        }
    ],
    "sg:phone":"+32 2 512 32 26",
    "sg:postcode":"1000",
    "sg:province":"Bruxelles-Capitale",
    "sg:tags":[
        "retail",
        "-"
    ],
    "wof:name":"Maison Au Th\u00e9 (la)",
    "wof:placetype":"venue"
},
  "geometry": {"coordinates":[4.348692894,50.8465690613],"type":"Point"}
}