{
  "type": "Feature",
  "properties": {
    "addr:full":"Brusselsesteenweg 107 Halle Vlaams-Brabant 1500",
    "addr:housenumber":"107",
    "addr:postcode":"1500",
    "addr:street":"Brusselsesteenweg",
    "iso:country":"BE",
    "sg:address":"Brusselsesteenweg 107",
    "sg:city":"Halle",
    "sg:orig_category":"Ordinateurs and \u00e9quipement informatique. Entretien and r\u00e9parations de machines de bureau and ordinat",
    "sg:phone":"+32 2 361 10 89",
    "sg:postcode":"1500",
    "sg:province":"Vlaams-Brabant",
    "wof:name":"Compucity",
    "wof:placetype":"venue"
},
  "geometry": {"coordinates":[4.238743782,50.7407264709],"type":"Point"}
}