{
  "type": "Feature",
  "properties": {
    "addr:full":"Belseledorp 215 Sint-niklaas (belsele) Oost-Vlaanderen 9111",
    "addr:housenumber":"215",
    "addr:postcode":"9111",
    "iso:country":"BE",
    "sg:address":"Belseledorp 215",
    "sg:city":"Sint-niklaas (belsele)",
    "sg:classifiers":[
        {
            "category":"Health Services",
            "subcategory":"Doctor",
            "type":"Services"
        }
    ],
    "sg:phone":"+32 3 722 03 25",
    "sg:postcode":"9111",
    "sg:province":"Oost-Vlaanderen",
    "sg:tags":[
        "medicinephysicians",
        "surgeon"
    ],
    "wof:name":"Bontinck H",
    "wof:placetype":"venue"
},
  "geometry": {"coordinates":[4.0800700188,51.1433792114],"type":"Point"}
}