{
  "type": "Feature",
  "properties": {
    "iso:country":"BE",
    "sg:address":"Eikenlei 15",
    "sg:city":"Brasschaat",
    "sg:orig_category":"Artsen and specialisten",
    "sg:phone":"+32 3 645 46 60",
    "sg:postcode":"2930",
    "sg:province":"Antwerpen",
    "wof:name":"Eduard Kusters",
    "wof:placetype":"venue"
},
  "geometry": {"coordinates":[4.4660720825,51.2723274231],"type":"Point"}
}