{
  "type": "Feature",
  "properties": {
    "addr:full":"Chauss\u00e9e De Wavre 259a Wanze Li\u00e8ge 4520",
    "addr:housenumber":"259a",
    "addr:postcode":"4520",
    "addr:street":"Chausse\u0301E De Wavre",
    "iso:country":"BE",
    "sg:address":"Chauss\u00e9e De Wavre 259a",
    "sg:city":"Wanze",
    "sg:classifiers":[
        {
            "category":"Restaurant",
            "type":"Food & Drink"
        }
    ],
    "sg:phone":"+32 85 23 30 01",
    "sg:postcode":"4520",
    "sg:province":"Li\u00e8ge",
    "sg:tags":[
        "pasta"
    ],
    "wof:name":"Come A Casa S.a.",
    "wof:placetype":"venue"
},
  "geometry": {"coordinates":[5.1949601173,50.5390548706],"type":"Point"}
}