{
  "type": "Feature",
  "properties": {
    "addr:full":"Ch De Bastogne 62 Longlier Luxembourg 6840",
    "addr:housenumber":"62",
    "addr:postcode":"6840",
    "addr:street":"Ch De Bastogne",
    "iso:country":"BE",
    "sg:address":"Ch De Bastogne 62",
    "sg:city":"Longlier",
    "sg:classifiers":[
        {
            "category":"Autos & Motor Vehicles",
            "subcategory":"Automobile Sales",
            "type":"Retail Goods"
        }
    ],
    "sg:phone":"+32 61 27 77 97",
    "sg:postcode":"6840",
    "sg:province":"Luxembourg",
    "sg:tags":[
        "equipment",
        "motor-cars",
        "transport"
    ],
    "wof:name":"Carrosserie Delaval",
    "wof:placetype":"venue"
},
  "geometry": {"coordinates":[5.4582891464,49.8565254211],"type":"Point"}
}