{
  "type": "Feature",
  "properties": {
    "addr:full":"Katelijnestraat 92 Brugge West-Vlaanderen 8000",
    "addr:housenumber":"92",
    "addr:postcode":"8000",
    "addr:street":"Katelijnestraat",
    "iso:country":"BE",
    "sg:address":"Katelijnestraat 92",
    "sg:city":"Brugge",
    "sg:classifiers":[
        {
            "category":"Fast Food",
            "type":"Food & Drink"
        }
    ],
    "sg:phone":"+32 50 34 10 01",
    "sg:postcode":"8000",
    "sg:province":"West-Vlaanderen",
    "sg:tags":[
        "meeneem",
        "restaurant"
    ],
    "wof:name":"Pizza \u00b4t Hoekske",
    "wof:placetype":"venue"
},
  "geometry": {"coordinates":[3.2272920609,51.201259613],"type":"Point"}
}