{
  "type": "Feature",
  "properties": {
    "addr:full":"Binnenveld 29 Balen Antwerpen 2490",
    "addr:housenumber":"29",
    "addr:postcode":"2490",
    "addr:street":"Binnenveld",
    "iso:country":"BE",
    "sg:address":"Binnenveld 29",
    "sg:city":"Balen",
    "sg:orig_category":"Eleveurs and marchands de porcs",
    "sg:phone":"+32 14 81 78 80",
    "sg:postcode":"2490",
    "sg:province":"Antwerpen",
    "wof:name":"Geert Boonen",
    "wof:placetype":"venue"
},
  "geometry": {"coordinates":[5.2548551559,51.1687049866],"type":"Point"}
}