{
  "type": "Feature",
  "properties": {
    "iso:country":"BE",
    "sg:address":"Rue Carlo Mahy 1",
    "sg:city":"Binche",
    "sg:orig_category":"Kapsalons",
    "sg:phone":"+32 64 33 18 82",
    "sg:postcode":"7130",
    "sg:province":"Hainaut",
    "wof:name":"Coiffure Marie-ange",
    "wof:placetype":"venue"
},
  "geometry": {"coordinates":[4.1677670479,50.4123420715],"type":"Point"}
}