{
  "type": "Feature",
  "properties": {
    "addr:full":"Hagenbroeksesteenweg 276 Lier Antwerpen 2500",
    "addr:housenumber":"276",
    "addr:postcode":"2500",
    "addr:street":"Hagenbroeksesteenweg",
    "iso:country":"BE",
    "sg:address":"Hagenbroeksesteenweg 276",
    "sg:city":"Lier",
    "sg:orig_category":"Goederenvervoer over de weg",
    "sg:phone":"+32 3 480 86 37",
    "sg:postcode":"2500",
    "sg:province":"Antwerpen",
    "wof:name":"Bercky",
    "wof:placetype":"venue"
},
  "geometry": {"coordinates":[4.5551080704,51.1553764343],"type":"Point"}
}