{
  "type": "Feature",
  "properties": {
    "addr:full":"Chauss\u00c9e De Chimay 129 Beaumont Hainaut 6500",
    "addr:housenumber":"129",
    "addr:postcode":"6500",
    "addr:street":"Chausse\u0301E De Chimay;Hainaut",
    "iso:country":"BE",
    "sg:address":"Chauss\u00c9e De Chimay 129",
    "sg:city":"Beaumont",
    "sg:classifiers":[
        {
            "category":"Fast Food",
            "type":"Food & Drink"
        }
    ],
    "sg:phone":"+32 60 45 63 42",
    "sg:postcode":"6500",
    "sg:province":"Hainaut",
    "sg:tags":[
        "restaurant",
        "\u00c0",
        "domicile",
        "emporter",
        "livraison",
        "restaurants"
    ],
    "wof:name":"Le Lorroir",
    "wof:placetype":"venue"
},
  "geometry": {"coordinates":[4.2337999344,50.2296600342],"type":"Point"}
}