{
  "type": "Feature",
  "properties": {
    "addr:full":"Lode De Boningelaan 16 Kortrijk West-Vlaanderen 8500",
    "addr:housenumber":"16",
    "addr:postcode":"8500",
    "addr:street":"Lode De Boningelaan",
    "iso:country":"BE",
    "sg:address":"Lode De Boningelaan 16",
    "sg:city":"Kortrijk",
    "sg:classifiers":[
        {
            "category":"Professional",
            "subcategory":"Management & Consulting",
            "type":"Services"
        }
    ],
    "sg:phone":"+32 56 25 88 64",
    "sg:postcode":"8500",
    "sg:province":"West-Vlaanderen",
    "sg:tags":[
        "marketing",
        "-",
        "consultant"
    ],
    "wof:name":"Ragheno Marketing Service",
    "wof:placetype":"venue"
},
  "geometry": {"coordinates":[3.2810220718,50.8254890442],"type":"Point"}
}