{
  "type": "Feature",
  "properties": {
    "iso:country":"BE",
    "sg:address":"Hoek 33",
    "sg:city":"Hamont-achel",
    "sg:orig_category":"Bedrijfscatering",
    "sg:phone":"+32 11 64 38 10",
    "sg:postcode":"3930",
    "sg:province":"Limburg",
    "wof:name":"Jean-paul Verweyen",
    "wof:placetype":"venue"
},
  "geometry": {"coordinates":[5.4849729538,51.2502098083],"type":"Point"}
}