{
  "type": "Feature",
  "properties": {
    "iso:country":"BE",
    "sg:address":"Rue Vise Voie 37",
    "sg:city":"Oupeye",
    "sg:orig_category":"Kapsalons",
    "sg:phone":"+32 4 264 72 29",
    "sg:postcode":"4680",
    "sg:province":"Li\u00e8ge",
    "wof:name":"Coiffure Harmonie",
    "wof:placetype":"venue"
},
  "geometry": {"coordinates":[5.6423649788,50.7075805664],"type":"Point"}
}