{
  "type": "Feature",
  "properties": {
    "iso:country":"BE",
    "sg:address":"Oudstrijdersstraat 23",
    "sg:city":"Vilvoorde (peutie)",
    "sg:classifiers":[
        {
            "category":"Health Services",
            "subcategory":"Dentist",
            "type":"Services"
        }
    ],
    "sg:phone":"+32 2 252 18 98",
    "sg:postcode":"1800",
    "sg:province":"Vlaams-Brabant",
    "wof:name":"Benoit N",
    "wof:placetype":"venue"
},
  "geometry": {"coordinates":[4.4562602043,50.9273681641],"type":"Point"}
}