{
  "type": "Feature",
  "properties": {
    "addr:full":"Rue Saint-adalbert 9d Box 28 Li\u00e8ge 1 Li\u00e8ge 4000",
    "addr:housenumber":"9d box 28;1",
    "addr:postcode":"4000",
    "addr:street":"Rue Saint-Adalbert;Lie\u0300Ge",
    "iso:country":"BE",
    "sg:address":"Rue Saint-adalbert 9d Box 28",
    "sg:city":"Li\u00e8ge 1",
    "sg:classifiers":[
        {
            "category":"Professional",
            "subcategory":"Detective & Security Services",
            "type":"Services"
        }
    ],
    "sg:phone":"+32 4 221 25 30",
    "sg:postcode":"4000",
    "sg:province":"Li\u00e8ge",
    "sg:tags":[
        "agency"
    ],
    "wof:name":"Fiore (i.i.a)",
    "wof:placetype":"venue"
},
  "geometry": {"coordinates":[5.5695700645,50.6421966553],"type":"Point"}
}