{
  "type": "Feature",
  "properties": {
    "addr:full":"Boulevard Fr\u00e8re-orban 12-12 Li\u00e8ge 1 Li\u00e8ge 4000",
    "addr:postcode":"12-12;4000",
    "addr:street":"Boulevard Fre\u0300Re-Orban",
    "iso:country":"BE",
    "sg:address":"Boulevard Fr\u00e8re-orban 12-12",
    "sg:city":"Li\u00e8ge 1",
    "sg:classifiers":[
        {
            "category":"Health Services",
            "subcategory":"Dentist",
            "type":"Services"
        }
    ],
    "sg:phone":"+32 4 221 44 04",
    "sg:postcode":"4000",
    "sg:province":"Li\u00e8ge",
    "wof:name":"Litwak Edouard",
    "wof:placetype":"venue"
},
  "geometry": {"coordinates":[5.5714187622,50.6344528198],"type":"Point"}
}