{
  "type": "Feature",
  "properties": {
    "addr:full":"Aannemersstraat 186-188 Gent Oost-Vlaanderen 9040",
    "addr:housenumber":"186-188",
    "addr:postcode":"9040",
    "addr:street":"Aannemersstraat;Oost-Vlaanderen",
    "iso:country":"BE",
    "sg:address":"Aannemersstraat 186-188",
    "sg:city":"Gent",
    "sg:orig_category":"Formation and enseignement. Conseils en syst\u00e8mes informatiques",
    "sg:phone":"+32 9 219 00 71",
    "sg:postcode":"9040",
    "sg:province":"Oost-Vlaanderen",
    "wof:name":"C-luma",
    "wof:placetype":"venue"
},
  "geometry": {"coordinates":[3.7520689964,51.0497817993],"type":"Point"}
}