{
  "type": "Feature",
  "properties": {
    "iso:country":"BE",
    "sg:address":"Emiel-neirynckstraat 11",
    "sg:city":"Izegem",
    "sg:classifiers":[
        {
            "category":"Bakery",
            "type":"Food & Drink"
        }
    ],
    "sg:phone":"+32 51 30 91 10",
    "sg:postcode":"8870",
    "sg:province":"West-Vlaanderen",
    "sg:tags":[
        "confectioner",
        "baker"
    ],
    "wof:name":"Verfaillie J P",
    "wof:placetype":"venue"
},
  "geometry": {"coordinates":[3.2259790897,50.9123191833],"type":"Point"}
}