{
  "type": "Feature",
  "properties": {
    "iso:country":"BE",
    "sg:address":"Jan De Cordesstraat 40",
    "sg:city":"Putte",
    "sg:classifiers":[
        {
            "category":"Insurance",
            "subcategory":"Insurance Agent",
            "type":"Services"
        }
    ],
    "sg:phone":"+32 15 75 56 75",
    "sg:postcode":"2580",
    "sg:province":"Antwerpen",
    "sg:tags":[
        "verzekeringsmakelaars",
        "expert"
    ],
    "wof:name":"Gysbrechts Zakenkantoor",
    "wof:placetype":"venue"
},
  "geometry": {"coordinates":[4.6673598289,51.0590324402],"type":"Point"}
}