{
  "type": "Feature",
  "properties": {
    "addr:full":"Klokketuin 78 Anzegem West-Vlaanderen 8570",
    "addr:housenumber":"78",
    "addr:postcode":"8570",
    "addr:street":"Klokketuin",
    "iso:country":"BE",
    "sg:address":"Klokketuin 78",
    "sg:city":"Anzegem",
    "sg:classifiers":[
        {
            "category":"Cafe",
            "type":"Food & Drink"
        }
    ],
    "sg:phone":"+32 56 68 90 29",
    "sg:postcode":"8570",
    "sg:province":"West-Vlaanderen",
    "sg:tags":[
        "caf\u00e9s"
    ],
    "wof:name":"Geert Titeca",
    "wof:placetype":"venue"
},
  "geometry": {"coordinates":[3.4443941116,50.8471794128],"type":"Point"}
}