{
  "type": "Feature",
  "properties": {
    "iso:country":"BE",
    "sg:address":"Rue Des Volontaires 1",
    "sg:city":"Tournai",
    "sg:classifiers":[
        {
            "category":"Communications",
            "subcategory":"Film & Video Production",
            "type":"Services"
        }
    ],
    "sg:phone":"+32 69 36 09 92",
    "sg:postcode":"7500",
    "sg:province":"Hainaut",
    "sg:tags":[
        "hiring",
        "-"
    ],
    "wof:name":"Image Tournai",
    "wof:placetype":"venue"
},
  "geometry": {"coordinates":[3.3998498917,50.6108093262],"type":"Point"}
}