{
  "type": "Feature",
  "properties": {
    "addr:full":"Hoevenzavellaan 22 Genk Limburg 3600",
    "addr:housenumber":"22",
    "addr:postcode":"3600",
    "addr:street":"Hoevenzavellaan",
    "iso:country":"BE",
    "sg:address":"Hoevenzavellaan 22",
    "sg:city":"Genk",
    "sg:classifiers":[
        {
            "category":"Cafe",
            "type":"Food & Drink"
        }
    ],
    "sg:phone":"+32 89 38 33 94",
    "sg:postcode":"3600",
    "sg:province":"Limburg",
    "sg:tags":[
        "caf\u00e9s"
    ],
    "wof:name":"Caf\u00c9 Atlas Torres",
    "wof:placetype":"venue"
},
  "geometry": {"coordinates":[5.5076398849,51.0010604858],"type":"Point"}
}