{
  "type": "Feature",
  "properties": {
    "iso:country":"BE",
    "sg:address":"Schuurhovenveld 2020",
    "sg:city":"Sint-truiden",
    "sg:classifiers":[
        {
            "category":"Autos & Motor Vehicles",
            "subcategory":"Automobile Sales",
            "type":"Retail Goods"
        }
    ],
    "sg:phone":"+32 11 78 55 15",
    "sg:postcode":"3800",
    "sg:province":"Limburg",
    "sg:tags":[
        "equipment",
        "motor-cars",
        "transport"
    ],
    "wof:name":"Pick & Pay Bvba",
    "wof:placetype":"venue"
},
  "geometry": {"coordinates":[5.1863641739,50.8153343201],"type":"Point"}
}