{
  "type": "Feature",
  "properties": {
    "iso:country":"BE",
    "sg:address":"Rue Ferdinand Nicolay 130",
    "sg:city":"Seraing",
    "sg:orig_category":"Electrom\u00e9nager, t\u00e9l\u00e9visions and radios. R\u00e9parations d'appareils \u00e9lectrom\u00e9nagers",
    "sg:phone":"+32 4 337 02 05",
    "sg:postcode":"4102",
    "sg:province":"Li\u00e8ge",
    "wof:name":"Gauthier Raoul & Cie",
    "wof:placetype":"venue"
},
  "geometry": {"coordinates":[5.5407109261,50.6041946411],"type":"Point"}
}