{
  "type": "Feature",
  "properties": {
    "iso:country":"BE",
    "sg:address":"Baliestraat 84 Box 11",
    "sg:city":"Brugge",
    "sg:classifiers":[
        {
            "category":"Shopping",
            "subcategory":"Shoes",
            "type":"Retail Goods"
        }
    ],
    "sg:phone":"+32 50 34 03 96",
    "sg:postcode":"8000",
    "sg:province":"West-Vlaanderen",
    "sg:tags":[
        "slipper",
        "-"
    ],
    "wof:name":"St-gillis Schoenen",
    "wof:placetype":"venue"
},
  "geometry": {"coordinates":[3.226047039,51.2175788879],"type":"Point"}
}