{
  "type": "Feature",
  "properties": {
    "iso:country":"BE",
    "sg:address":"Emiel Vlieberghlaan 8",
    "sg:city":"Overpelt",
    "sg:classifiers":[
        {
            "category":"Freight",
            "type":"Transportation"
        }
    ],
    "sg:phone":"+32 11 80 99 15",
    "sg:postcode":"3900",
    "sg:province":"Limburg",
    "sg:tags":[
        "container",
        "-",
        "transport"
    ],
    "wof:name":"Atrex Bvba",
    "wof:placetype":"venue"
},
  "geometry": {"coordinates":[5.381248951,51.225933075],"type":"Point"}
}