{
  "type": "Feature",
  "properties": {
    "iso:country":"BE",
    "sg:address":"Rue Raoul Nachez 1",
    "sg:city":"Brugelette (m\u00e9vergnies-lez-lens)",
    "sg:classifiers":[
        {
            "category":"Insurance",
            "subcategory":"Insurance Agent",
            "type":"Services"
        }
    ],
    "sg:phone":"+32 68 45 45 74",
    "sg:postcode":"7942",
    "sg:province":"Hainaut",
    "sg:tags":[
        "broker"
    ],
    "wof:name":"Agh Delcubonde-houssin Sprl",
    "wof:placetype":"venue"
},
  "geometry": {"coordinates":[3.8516540527,50.6067810059],"type":"Point"}
}