{
  "type": "Feature",
  "properties": {
    "iso:country":"BE",
    "sg:address":"Rue Du Lion-d'or 30",
    "sg:city":"Bouillon",
    "sg:orig_category":"Sportclubs",
    "sg:phone":"+32 61 46 69 47",
    "sg:postcode":"6830",
    "sg:province":"Luxembourg",
    "wof:name":"P.c. La Semois Bouillon",
    "wof:placetype":"venue"
},
  "geometry": {"coordinates":[5.1133699417,49.7692985535],"type":"Point"}
}