{
  "type": "Feature",
  "properties": {
    "addr:full":"Kellestraat 58 Bruxelles (woluwe-saint-lambert) Bruxelles-Capitale 1200",
    "addr:housenumber":"58",
    "addr:postcode":"1200",
    "addr:street":"Kellestraat",
    "iso:country":"BE",
    "sg:address":"Kellestraat 58",
    "sg:city":"Bruxelles (woluwe-saint-lambert)",
    "sg:classifiers":[
        {
            "category":"Bars & Pubs",
            "type":"Food & Drink"
        }
    ],
    "sg:phone":"+32 2 770 09 09",
    "sg:postcode":"1200",
    "sg:province":"Bruxelles-Capitale",
    "wof:name":"Robert (chez)",
    "wof:placetype":"venue"
},
  "geometry": {"coordinates":[4.4396939278,50.8343963623],"type":"Point"}
}