{
  "type": "Feature",
  "properties": {
    "addr:full":"Zuidlaan 327 Wetteren Oost-Vlaanderen 9230",
    "addr:housenumber":"327",
    "addr:postcode":"9230",
    "addr:street":"Zuidlaan",
    "iso:country":"BE",
    "sg:address":"Zuidlaan 327",
    "sg:city":"Wetteren",
    "sg:orig_category":"Ordinateurs and \u00e9quipement informatique",
    "sg:phone":"+32 9 366 15 06",
    "sg:postcode":"9230",
    "sg:province":"Oost-Vlaanderen",
    "wof:name":"Technovisie",
    "wof:placetype":"venue"
},
  "geometry": {"coordinates":[3.85145998,50.9911499023],"type":"Point"}
}