{
  "type": "Feature",
  "properties": {
    "addr:full":"Bosgatstraat 35 Maarkedal (schorisse) Oost-Vlaanderen 9688",
    "addr:housenumber":"35",
    "addr:postcode":"9688",
    "addr:street":"Bosgatstraat",
    "iso:country":"BE",
    "sg:address":"Bosgatstraat 35",
    "sg:city":"Maarkedal (schorisse)",
    "sg:classifiers":[
        {
            "category":"Autos & Motor Vehicles",
            "subcategory":"Recreational Vehicle Sales",
            "type":"Retail Goods"
        }
    ],
    "sg:phone":"+32 55 45 62 25",
    "sg:postcode":"9688",
    "sg:province":"Oost-Vlaanderen",
    "sg:tags":[
        "installation",
        "metal",
        "-",
        "surface",
        "machine",
        "treatment"
    ],
    "wof:name":"Vandenbossche A",
    "wof:placetype":"venue"
},
  "geometry": {"coordinates":[3.6927790642,50.7853088379],"type":"Point"}
}