{
  "type": "Feature",
  "properties": {
    "addr:full":"Neervelden 21 Brasschaat Antwerpen 2930",
    "addr:housenumber":"21",
    "addr:postcode":"2930",
    "addr:street":"Neervelden",
    "iso:country":"BE",
    "sg:address":"Neervelden 21",
    "sg:city":"Brasschaat",
    "sg:classifiers":[
        {
            "category":"Insurance",
            "subcategory":"Insurance Agent",
            "type":"Services"
        }
    ],
    "sg:phone":"+32 3 653 30 33",
    "sg:postcode":"2930",
    "sg:province":"Antwerpen",
    "sg:tags":[
        "broker"
    ],
    "wof:name":"Vanreusel Koen Bvba",
    "wof:placetype":"venue"
},
  "geometry": {"coordinates":[4.5012478828,51.3084068298],"type":"Point"}
}