{
  "type": "Feature",
  "properties": {
    "iso:country":"BE",
    "sg:address":"Rue De La Cr\u00cate 32",
    "sg:city":"Vloesberg/flobecq",
    "sg:orig_category":"Enseignement maternel and primaire. Enseignement secondaire g\u00e9n\u00e9ral",
    "sg:phone":"+32 68 44 66 51",
    "sg:postcode":"7880",
    "sg:province":"Hainaut",
    "wof:name":"Ecole Fondamentale",
    "wof:placetype":"venue"
},
  "geometry": {"coordinates":[3.739356041,50.7336120605],"type":"Point"}
}