{
  "type": "Feature",
  "properties": {
    "iso:country":"BE",
    "sg:address":"Heideken 2",
    "sg:city":"Lubbeek",
    "sg:orig_category":"Fruitteelt",
    "sg:phone":"+32 16 73 53 39",
    "sg:postcode":"3210",
    "sg:province":"Vlaams-Brabant",
    "wof:name":"Georges De Becker",
    "wof:placetype":"venue"
},
  "geometry": {"coordinates":[4.8317980766,50.8678398132],"type":"Point"}
}