{
  "type": "Feature",
  "properties": {
    "addr:full":"Achterstenhoek 3 Lille Antwerpen 2275",
    "addr:housenumber":"3",
    "addr:postcode":"2275",
    "addr:street":"Achterstenhoek",
    "iso:country":"BE",
    "sg:address":"Achterstenhoek 3",
    "sg:city":"Lille",
    "sg:orig_category":"Charpentes and couvertures",
    "sg:phone":"+32 14 88 31 31",
    "sg:postcode":"2275",
    "sg:province":"Antwerpen",
    "wof:name":"Van Mechelen",
    "wof:placetype":"venue"
},
  "geometry": {"coordinates":[4.8126368523,51.2484474182],"type":"Point"}
}