{
  "type": "Feature",
  "properties": {
    "addr:full":"Rue General De Gaulle 24 Courcelles Hainaut 6180",
    "addr:housenumber":"24",
    "addr:postcode":"6180",
    "addr:street":"Rue General De Gaulle",
    "iso:country":"BE",
    "sg:address":"Rue General De Gaulle 24",
    "sg:city":"Courcelles",
    "sg:orig_category":"Swatch. Bijouteries and horlogeries. R\u00e9parations d'horloges, montres and bijoux. Eclairage et \u00e9quipe",
    "sg:phone":"+32 71 45 01 30",
    "sg:postcode":"6180",
    "sg:province":"Hainaut",
    "wof:name":"Horlogerie Plumet",
    "wof:placetype":"venue"
},
  "geometry": {"coordinates":[4.3800258636,50.4591026306],"type":"Point"}
}