{
  "type": "Feature",
  "properties": {
    "addr:full":"Rue Gustave Demoulin 65 Plombieres/plombieres Li\u00e8ge 4850",
    "addr:housenumber":"65",
    "addr:postcode":"4850",
    "addr:street":"Rue Gustave Demoulin",
    "iso:country":"BE",
    "sg:address":"Rue Gustave Demoulin 65",
    "sg:city":"Plombieres/plombieres",
    "sg:orig_category":"Artsen and specialisten",
    "sg:phone":"+32 87 78 63 48",
    "sg:postcode":"4850",
    "sg:province":"Li\u00e8ge",
    "wof:name":"Hilde Govaerts",
    "wof:placetype":"venue"
},
  "geometry": {"coordinates":[5.9626002312,50.7068138123],"type":"Point"}
}