{
  "type": "Feature",
  "properties": {
    "addr:full":"Wijngaardstraat 50 Kortrijk West-Vlaanderen 8500",
    "addr:housenumber":"50",
    "addr:postcode":"8500",
    "addr:street":"Wijngaardstraat",
    "iso:country":"BE",
    "sg:address":"Wijngaardstraat 50",
    "sg:city":"Kortrijk",
    "sg:orig_category":"Editeurs de journaux. Editeurs de revues and p\u00e9riodiques",
    "sg:phone":"+32 56 26 08 30",
    "sg:postcode":"8500",
    "sg:province":"West-Vlaanderen",
    "wof:name":"Het Volk",
    "wof:placetype":"venue"
},
  "geometry": {"coordinates":[3.2710809708,50.8262062073],"type":"Point"}
}