{
  "type": "Feature",
  "properties": {
    "addr:full":"Rue Fernand Gobiet 9 Binche Hainaut 7134",
    "addr:housenumber":"9",
    "addr:postcode":"7134",
    "addr:street":"Rue Fernand Gobiet",
    "iso:country":"BE",
    "sg:address":"Rue Fernand Gobiet 9",
    "sg:city":"Binche",
    "sg:orig_category":"Epiceries",
    "sg:phone":"+32 64 34 12 20",
    "sg:postcode":"7134",
    "sg:province":"Hainaut",
    "wof:name":"D.c.s. Alimentation",
    "wof:placetype":"venue"
},
  "geometry": {"coordinates":[4.1926608086,50.4201431274],"type":"Point"}
}