{
  "type": "Feature",
  "properties": {
    "addr:full":"Avenue De L'astronomie 14 Sint-joost-ten-node/saint-josse-ten-noode Bruxelles-Capitale 1210",
    "addr:housenumber":"14",
    "addr:postcode":"1210",
    "addr:street":"Avenue De L'Astronomie",
    "iso:country":"BE",
    "sg:address":"Avenue De L'astronomie 14",
    "sg:city":"Sint-joost-ten-node/saint-josse-ten-noode",
    "sg:orig_category":"Cr\u00e9dits divers",
    "sg:postcode":"1210",
    "sg:province":"Bruxelles-Capitale",
    "wof:name":"Bancontact-mister Cash",
    "wof:placetype":"venue"
},
  "geometry": {"coordinates":[4.3692269325,50.8510704041],"type":"Point"}
}