{
  "type": "Feature",
  "properties": {
    "addr:full":"De Kemmeterlaan 1 Gent Oost-Vlaanderen 9031",
    "addr:housenumber":"1",
    "addr:postcode":"9031",
    "addr:street":"Kemmeterlaan;Oost-Vlaanderen",
    "iso:country":"BE",
    "sg:address":"De Kemmeterlaan 1",
    "sg:city":"Gent",
    "sg:orig_category":"Projectontwikkelaars",
    "sg:phone":"+32 9 227 43 89",
    "sg:postcode":"9031",
    "sg:province":"Oost-Vlaanderen",
    "wof:name":"Present+plus",
    "wof:placetype":"venue"
},
  "geometry": {"coordinates":[3.6525430679,51.0508460999],"type":"Point"}
}