{
  "type": "Feature",
  "properties": {
    "iso:country":"BE",
    "sg:address":"Rue Royale 10",
    "sg:city":"Bassenge",
    "sg:orig_category":"Mat\u00e9riel m\u00e9dical and orthop\u00e9dique and proth\u00e8ses Fab",
    "sg:phone":"+32 4 286 40 31",
    "sg:postcode":"4690",
    "sg:province":"Li\u00e8ge",
    "wof:name":"Vincent Briat",
    "wof:placetype":"venue"
},
  "geometry": {"coordinates":[5.6095638275,50.7592353821],"type":"Point"}
}