{
  "type": "Feature",
  "properties": {
    "addr:full":"Sint-denijsestraat 100ba Kortrijk West-Vlaanderen 8500",
    "addr:postcode":"8500",
    "iso:country":"BE",
    "sg:address":"Sint-denijsestraat 100ba",
    "sg:city":"Kortrijk",
    "sg:orig_category":"V\u00eatements pour b\u00e9b\u00e9s and enfants",
    "sg:phone":"+32 56 22 27 90",
    "sg:postcode":"8500",
    "sg:province":"West-Vlaanderen",
    "wof:name":"Huis Roodkapje",
    "wof:placetype":"venue"
},
  "geometry": {"coordinates":[3.2727200985,50.8218383789],"type":"Point"}
}