{
  "type": "Feature",
  "properties": {
    "addr:full":"Aalmoezenijestraat 82 Oosterzele Oost-Vlaanderen 9860",
    "addr:housenumber":"82",
    "addr:postcode":"9860",
    "addr:street":"Aalmoezenijestraat;Oost-Vlaanderen",
    "iso:country":"BE",
    "sg:address":"Aalmoezenijestraat 82",
    "sg:city":"Oosterzele",
    "sg:orig_category":"Woningbouw",
    "sg:phone":"+32 9 362 72 47",
    "sg:postcode":"9860",
    "sg:province":"Oost-Vlaanderen",
    "wof:name":"De Meiboom",
    "wof:placetype":"venue"
},
  "geometry": {"coordinates":[3.8036899567,50.9731330872],"type":"Point"}
}