{
  "type": "Feature",
  "properties": {
    "addr:full":"Rospijkstraat 16 Ninove Oost-Vlaanderen 9406",
    "addr:housenumber":"16",
    "addr:postcode":"9406",
    "addr:street":"Rospijkstraat",
    "iso:country":"BE",
    "sg:address":"Rospijkstraat 16",
    "sg:city":"Ninove",
    "sg:orig_category":"Eleveurs de bovins",
    "sg:phone":"+32 54 32 82 85",
    "sg:postcode":"9406",
    "sg:province":"Oost-Vlaanderen",
    "wof:name":"Denise Torrekens",
    "wof:placetype":"venue"
},
  "geometry": {"coordinates":[4.0031919479,50.8454017639],"type":"Point"}
}