{
  "type": "Feature",
  "properties": {
    "addr:full":"Chauss\u00c9e De Waterloo 153 Sint-gillis/saint-gilles Bruxelles-Capitale 1060",
    "addr:housenumber":"153",
    "addr:postcode":"1060",
    "addr:street":"Chausse\u0301E De Waterloo",
    "iso:country":"BE",
    "sg:address":"Chauss\u00c9e De Waterloo 153",
    "sg:city":"Sint-gillis/saint-gilles",
    "sg:orig_category":"Pain, p\u00e2tisseries and confiseries",
    "sg:phone":"+32 2 538 32 76",
    "sg:postcode":"1060",
    "sg:province":"Bruxelles-Capitale",
    "wof:name":"Leonidas",
    "wof:placetype":"venue"
},
  "geometry": {"coordinates":[4.3442621231,50.8275146484],"type":"Point"}
}