{
  "type": "Feature",
  "properties": {
    "iso:country":"BE",
    "sg:address":"Oudenaardsesteenweg 821",
    "sg:city":"Erpe-mere (burst)",
    "sg:classifiers":[
        {
            "category":"Autos & Motor Vehicles",
            "subcategory":"Fuel & Gas Station",
            "type":"Retail Goods"
        }
    ],
    "sg:phone":"+32 53 62 25 00",
    "sg:postcode":"9420",
    "sg:province":"Oost-Vlaanderen",
    "sg:tags":[
        "repair",
        "drier",
        "laundry",
        "-",
        "machine",
        "mainten",
        "washing",
        "automatic"
    ],
    "wof:name":"Schotte J",
    "wof:placetype":"venue"
},
  "geometry": {"coordinates":[3.9209759235,50.9135246277],"type":"Point"}
}