{
  "type": "Feature",
  "properties": {
    "addr:full":"Alfons Braeckmanlaan 164 Gent (sint-amandsberg) Oost-Vlaanderen 9040",
    "addr:housenumber":"164",
    "addr:postcode":"9040",
    "addr:street":"Braeckmanlaan",
    "iso:country":"BE",
    "sg:address":"Alfons Braeckmanlaan 164",
    "sg:city":"Gent (sint-amandsberg)",
    "sg:orig_category":"Newspapers, magazines, periodicals - Distribution",
    "sg:phone":"+32 9 228 49 25",
    "sg:postcode":"9040",
    "sg:province":"Oost-Vlaanderen",
    "wof:name":"Westveld ('t)",
    "wof:placetype":"venue"
},
  "geometry": {"coordinates":[3.7727839947,51.0640258789],"type":"Point"}
}