{
  "type": "Feature",
  "properties": {
    "addr:full":"Boulevard Leopold Ii 143 Bruxelles (molenbeek-saint-jean) Bruxelles-Capitale 1080",
    "addr:housenumber":"143",
    "addr:postcode":"1080",
    "addr:street":"Boulevard Leopold Ii",
    "iso:country":"BE",
    "sg:address":"Boulevard Leopold Ii 143",
    "sg:city":"Bruxelles (molenbeek-saint-jean)",
    "sg:classifiers":[
        {
            "category":"Bars & Pubs",
            "type":"Food & Drink"
        }
    ],
    "sg:phone":"+32 2 420 09 14",
    "sg:postcode":"1080",
    "sg:province":"Bruxelles-Capitale",
    "wof:name":"Duc De Brabant",
    "wof:placetype":"venue"
},
  "geometry": {"coordinates":[4.3378658295,50.8613777161],"type":"Point"}
}