{
  "type": "Feature",
  "properties": {
    "addr:full":"Offerandestraat 60 Antwerpen Antwerpen 2060",
    "addr:housenumber":"60",
    "addr:postcode":"2060",
    "addr:street":"Offerandestraat",
    "iso:country":"BE",
    "sg:address":"Offerandestraat 60",
    "sg:city":"Antwerpen",
    "sg:orig_category":"Cr\u00e8ches and garderies d'enfants",
    "sg:phone":"+32 3 231 83 50",
    "sg:postcode":"2060",
    "sg:province":"Antwerpen",
    "wof:name":"Stedelijke Peutertuin",
    "wof:placetype":"venue"
},
  "geometry": {"coordinates":[4.425796032,51.2203712463],"type":"Point"}
}