{
  "type": "Feature",
  "properties": {
    "addr:full":"Counhaye 14 Welkenraedt/welkenraedt Li\u00e8ge 4841",
    "addr:housenumber":"14",
    "addr:postcode":"4841",
    "addr:street":"Counhaye",
    "iso:country":"BE",
    "sg:address":"Counhaye 14",
    "sg:city":"Welkenraedt/welkenraedt",
    "sg:orig_category":"Rundveehouders Varkenskwekers",
    "sg:phone":"+32 87 44 64 53",
    "sg:postcode":"4841",
    "sg:province":"Li\u00e8ge",
    "wof:name":"Hubert Charlier-royen",
    "wof:placetype":"venue"
},
  "geometry": {"coordinates":[5.9050040245,50.6550674438],"type":"Point"}
}