{
  "type": "Feature",
  "properties": {
    "addr:full":"Vennestraat 110 Genk Limburg 3600",
    "addr:housenumber":"110",
    "addr:postcode":"3600",
    "addr:street":"Vennestraat",
    "iso:country":"BE",
    "sg:address":"Vennestraat 110",
    "sg:city":"Genk",
    "sg:orig_category":"Epiceries. Fruits and l\u00e9gumes",
    "sg:phone":"+32 89 35 36 77",
    "sg:postcode":"3600",
    "sg:province":"Limburg",
    "wof:name":"Supermarkt",
    "wof:placetype":"venue"
},
  "geometry": {"coordinates":[5.4905991554,50.9791412354],"type":"Point"}
}