{
  "type": "Feature",
  "properties": {
    "addr:full":"Rue Du Centre 80 Lierneux Li\u00e8ge 4990",
    "addr:housenumber":"80",
    "addr:postcode":"4990",
    "addr:street":"Rue Du Centre",
    "iso:country":"BE",
    "sg:address":"Rue Du Centre 80",
    "sg:city":"Lierneux",
    "sg:orig_category":"Toeristische diensten",
    "sg:phone":"+32 80 31 97 85",
    "sg:postcode":"4990",
    "sg:province":"Li\u00e8ge",
    "wof:name":"Syndicat D'initiative",
    "wof:placetype":"venue"
},
  "geometry": {"coordinates":[5.7945179939,50.2835769653],"type":"Point"}
}