{
  "type": "Feature",
  "properties": {
    "addr:full":"Zavelstraat 13 Mol Antwerpen 2400",
    "addr:housenumber":"13",
    "addr:postcode":"2400",
    "addr:street":"Zavelstraat",
    "iso:country":"BE",
    "sg:address":"Zavelstraat 13",
    "sg:city":"Mol",
    "sg:orig_category":"Pain, p\u00e2tisseries and confiseries",
    "sg:phone":"+32 14 32 13 57",
    "sg:postcode":"2400",
    "sg:province":"Antwerpen",
    "wof:name":"Jos Peelaerts",
    "wof:placetype":"venue"
},
  "geometry": {"coordinates":[5.1289200783,51.1993255615],"type":"Point"}
}