{
  "type": "Feature",
  "properties": {
    "iso:country":"BE",
    "sg:address":"Winkelstraat 4-8",
    "sg:city":"Lanaken",
    "sg:classifiers":[
        {
            "category":"Shopping",
            "subcategory":"Luggage & Leather Goods",
            "type":"Retail Goods"
        }
    ],
    "sg:phone":"+32 89 71 27 21",
    "sg:postcode":"3620",
    "sg:province":"Limburg",
    "sg:tags":[
        "-"
    ],
    "wof:name":"Jokado Select",
    "wof:placetype":"venue"
},
  "geometry": {"coordinates":[5.6494398117,50.8883094788],"type":"Point"}
}