{
  "type": "Feature",
  "properties": {
    "addr:full":"Rue De Bouny 81 Fleron Li\u00e8ge 4624",
    "addr:housenumber":"81",
    "addr:postcode":"4624",
    "addr:street":"Rue De Bouny",
    "iso:country":"BE",
    "sg:address":"Rue De Bouny 81",
    "sg:city":"Fleron",
    "sg:orig_category":"Enseignement maternel and primaire",
    "sg:phone":"+32 4 355 91 39",
    "sg:postcode":"4624",
    "sg:province":"Li\u00e8ge",
    "wof:name":"Ecole Prim. Communale",
    "wof:placetype":"venue"
},
  "geometry": {"coordinates":[5.6654500961,50.6067504883],"type":"Point"}
}