{
  "type": "Feature",
  "properties": {
    "addr:full":"Rue Du Cheval Blanc 14 Fexhe-le-haut-clocher Li\u00e8ge 4347",
    "addr:housenumber":"14",
    "addr:postcode":"4347",
    "addr:street":"Rue Du Cheval Blanc",
    "iso:country":"BE",
    "sg:address":"Rue Du Cheval Blanc 14",
    "sg:city":"Fexhe-le-haut-clocher",
    "sg:orig_category":"Eleveurs and marchands de porcs. Eleveurs de bovins",
    "sg:phone":"+32 4 250 31 69",
    "sg:postcode":"4347",
    "sg:province":"Li\u00e8ge",
    "wof:name":"Joseph Fastre",
    "wof:placetype":"venue"
},
  "geometry": {"coordinates":[5.3917508125,50.6815719604],"type":"Point"}
}