{
  "type": "Feature",
  "properties": {
    "iso:country":"BE",
    "sg:address":"Compogne 445",
    "sg:city":"Bertogne",
    "sg:classifiers":[
        {
            "category":"Building & Trades",
            "subcategory":"Landscaping Services",
            "type":"Services"
        }
    ],
    "sg:phone":"+32 61 21 79 10",
    "sg:postcode":"6687",
    "sg:province":"Luxembourg",
    "sg:tags":[
        "forestry"
    ],
    "wof:name":"Magein B",
    "wof:placetype":"venue"
},
  "geometry": {"coordinates":[5.712389946,50.0865707397],"type":"Point"}
}