{
  "type": "Feature",
  "properties": {
    "addr:full":"Avenue De La Gare 39 Arlon Luxembourg 6700",
    "addr:housenumber":"39",
    "addr:postcode":"6700",
    "addr:street":"Avenue De La Gare",
    "iso:country":"BE",
    "sg:address":"Avenue De La Gare 39",
    "sg:city":"Arlon",
    "sg:classifiers":[
        {
            "category":"Cafe",
            "type":"Food & Drink"
        }
    ],
    "sg:phone":"+32 63 22 51 52",
    "sg:postcode":"6700",
    "sg:province":"Luxembourg",
    "sg:tags":[
        "caf\u00e9s"
    ],
    "wof:name":"Caf\u00c9 Namurois",
    "wof:placetype":"venue"
},
  "geometry": {"coordinates":[5.810063839,49.6805610657],"type":"Point"}
}