{
  "type": "Feature",
  "properties": {
    "addr:full":"Frans Beirenslaan 3 Borsbeek Antwerpen 2150",
    "addr:housenumber":"3",
    "addr:postcode":"2150",
    "addr:street":"Frans Beirenslaan",
    "iso:country":"BE",
    "sg:address":"Frans Beirenslaan 3",
    "sg:city":"Borsbeek",
    "sg:orig_category":"Non-Classified Establishments",
    "sg:phone":"+32 3 366 17 70",
    "sg:postcode":"2150",
    "sg:province":"Antwerpen",
    "wof:name":"Sanal Nv",
    "wof:placetype":"venue"
},
  "geometry": {"coordinates":[4.4764537811,51.1916923523],"type":"Point"}
}