{
  "type": "Feature",
  "properties": {
    "addr:full":"Hontseindestraat 90 Sint-laureins Oost-Vlaanderen 9981",
    "addr:housenumber":"90",
    "addr:postcode":"9981",
    "addr:street":"Hontseindestraat",
    "iso:country":"BE",
    "sg:address":"Hontseindestraat 90",
    "sg:city":"Sint-laureins",
    "sg:orig_category":"Rundveehouders Varkenskwekers",
    "sg:phone":"+32 9 379 81 31",
    "sg:postcode":"9981",
    "sg:province":"Oost-Vlaanderen",
    "wof:name":"Gilbert Maenhout",
    "wof:placetype":"venue"
},
  "geometry": {"coordinates":[3.5318689346,51.271270752],"type":"Point"}
}