{
  "type": "Feature",
  "properties": {
    "addr:full":"Frankrijklei 114 Antwerpen Antwerpen 2000",
    "addr:housenumber":"114",
    "addr:postcode":"2000",
    "addr:street":"Frankrijklei",
    "iso:country":"BE",
    "sg:address":"Frankrijklei 114",
    "sg:city":"Antwerpen",
    "sg:orig_category":"Banques and organismes de cr\u00e9dit",
    "sg:phone":"+32 3 234 72 11",
    "sg:postcode":"2000",
    "sg:province":"Antwerpen",
    "wof:name":"Ippa",
    "wof:placetype":"venue"
},
  "geometry": {"coordinates":[4.4118418694,51.2145690918],"type":"Point"}
}