{
  "type": "Feature",
  "properties": {
    "iso:country":"BE",
    "sg:address":"Route De Durbuy 99",
    "sg:city":"Durbuy",
    "sg:orig_category":"Begrafeniswezen Natuursteenbewerking",
    "sg:phone":"+32 86 21 15 38",
    "sg:postcode":"6940",
    "sg:province":"Luxembourg",
    "wof:name":"Pompes Fun\u00c8bres De Ourthe",
    "wof:placetype":"venue"
},
  "geometry": {"coordinates":[5.4543361664,50.3515777588],"type":"Point"}
}