{
  "type": "Feature",
  "properties": {
    "addr:full":"Miraeusstraat 10 Antwerpen Antwerpen 2018",
    "addr:housenumber":"10",
    "addr:postcode":"2018",
    "addr:street":"Miraeusstraat",
    "iso:country":"BE",
    "sg:address":"Miraeusstraat 10",
    "sg:city":"Antwerpen",
    "sg:orig_category":"Agences d'exp\u00e9dition",
    "sg:phone":"+32 3 237 63 26",
    "sg:postcode":"2018",
    "sg:province":"Antwerpen",
    "wof:name":"Gibau",
    "wof:placetype":"venue"
},
  "geometry": {"coordinates":[4.4002861977,51.206489563],"type":"Point"}
}