{
  "type": "Feature",
  "properties": {
    "iso:country":"BE",
    "sg:address":"Snepstraat 11",
    "sg:city":"Lokeren",
    "sg:orig_category":"Mat\u00e9riel m\u00e9dical and orthop\u00e9dique and proth\u00e8ses Fab",
    "sg:phone":"+32 9 348 65 08",
    "sg:postcode":"9160",
    "sg:province":"Oost-Vlaanderen",
    "wof:name":"G. De Witte",
    "wof:placetype":"venue"
},
  "geometry": {"coordinates":[4.0036129951,51.110710144],"type":"Point"}
}