{
  "type": "Feature",
  "properties": {
    "addr:full":"Florali\u00ebnstraat 19 Oostkamp West-Vlaanderen 8020",
    "addr:housenumber":"19",
    "addr:postcode":"8020",
    "addr:street":"Floralie\u0308Nstraat",
    "iso:country":"BE",
    "sg:address":"Florali\u00ebnstraat 19",
    "sg:city":"Oostkamp",
    "sg:classifiers":[
        {
            "category":"Building & Trades",
            "subcategory":"Construction",
            "type":"Services"
        }
    ],
    "sg:phone":"+32 50 39 78 29",
    "sg:postcode":"8020",
    "sg:province":"West-Vlaanderen",
    "sg:tags":[
        "carpenter"
    ],
    "wof:name":"Mylle K",
    "wof:placetype":"venue"
},
  "geometry": {"coordinates":[3.2326049805,51.1751060486],"type":"Point"}
}