{
  "type": "Feature",
  "properties": {
    "addr:full":"Rue De Mons 14 Soignies Hainaut 7060",
    "addr:housenumber":"14",
    "addr:postcode":"7060",
    "addr:street":"Rue De Mons",
    "iso:country":"BE",
    "sg:address":"Rue De Mons 14",
    "sg:city":"Soignies",
    "sg:orig_category":"Bagage and lederwaren",
    "sg:phone":"+32 67 33 25 88",
    "sg:postcode":"7060",
    "sg:province":"Hainaut",
    "wof:name":"Maison Sabrina",
    "wof:placetype":"venue"
},
  "geometry": {"coordinates":[4.066836834,50.5715522766],"type":"Point"}
}