{
  "type": "Feature",
  "properties": {
    "iso:country":"BE",
    "sg:address":"Filip De Pillecynstraat 21",
    "sg:city":"Zele",
    "sg:orig_category":"Rev\u00eatements pour sols and murs. Peinture",
    "sg:phone":"+32 52 44 89 62",
    "sg:postcode":"9240",
    "sg:province":"Oost-Vlaanderen",
    "wof:name":"Michel Vandemoortel",
    "wof:placetype":"venue"
},
  "geometry": {"coordinates":[4.0346250534,51.0582008362],"type":"Point"}
}