{
  "type": "Feature",
  "properties": {
    "addr:full":"Rue Emile Vandervelde 172 Mons Hainaut 7033",
    "addr:housenumber":"172",
    "addr:postcode":"7033",
    "addr:street":"Rue Emile Vandervelde;Hainaut",
    "iso:country":"BE",
    "sg:address":"Rue Emile Vandervelde 172",
    "sg:city":"Mons",
    "sg:orig_category":"Schoonmaakbedrijven and ongediertebestrijding Wasserijen, Reiniging and Droogkuis",
    "sg:phone":"+32 65 36 18 90",
    "sg:postcode":"7033",
    "sg:province":"Hainaut",
    "wof:name":"Eden Services",
    "wof:placetype":"venue"
},
  "geometry": {"coordinates":[3.936455965,50.4392318726],"type":"Point"}
}