{
  "type": "Feature",
  "properties": {
    "iso:country":"BE",
    "sg:address":"Sint-guidostraat 44",
    "sg:city":"Anderlecht/anderlecht",
    "sg:orig_category":"Slagers",
    "sg:phone":"+32 2 521 92 81",
    "sg:postcode":"1070",
    "sg:province":"Bruxelles-Capitale",
    "wof:name":"Geert Van Deputte/g. Van Deputte",
    "wof:placetype":"venue"
},
  "geometry": {"coordinates":[4.3039469719,50.8356628418],"type":"Point"}
}