{
  "type": "Feature",
  "properties": {
    "iso:country":"BE",
    "sg:address":"Oude Houtlei 107",
    "sg:city":"Gent",
    "sg:orig_category":"Advocaten and juridische adviseurs Balie van Gent",
    "sg:phone":"+32 9 223 00 28",
    "sg:postcode":"9000",
    "sg:province":"Oost-Vlaanderen",
    "wof:name":"Blomme Johan",
    "wof:placetype":"venue"
},
  "geometry": {"coordinates":[3.717345953,51.0506439209],"type":"Point"}
}