{
  "type": "Feature",
  "properties": {
    "addr:full":"Leuvensestraat 51 Tienen Vlaams-Brabant 3300",
    "addr:housenumber":"51",
    "addr:postcode":"3300",
    "addr:street":"Leuvensestraat",
    "iso:country":"BE",
    "sg:address":"Leuvensestraat 51",
    "sg:city":"Tienen",
    "sg:classifiers":[
        {
            "category":"Shopping",
            "subcategory":"Clothing, Apparel, & Fashions",
            "type":"Retail Goods"
        }
    ],
    "sg:phone":"+32 16 81 17 90",
    "sg:postcode":"3300",
    "sg:province":"Vlaams-Brabant",
    "sg:tags":[
        "ondergoed",
        "lingerie"
    ],
    "wof:name":"Linca",
    "wof:placetype":"venue"
},
  "geometry": {"coordinates":[4.9340882301,50.8092308044],"type":"Point"}
}