{
  "type": "Feature",
  "properties": {
    "addr:full":"Rivierenlaan 13 Bonheiden Antwerpen 2820",
    "addr:housenumber":"13",
    "addr:postcode":"2820",
    "addr:street":"Rivierenlaan",
    "iso:country":"BE",
    "sg:address":"Rivierenlaan 13",
    "sg:city":"Bonheiden",
    "sg:orig_category":"Loodgieterij, verwarming and sanitaire installaties",
    "sg:phone":"+32 15 52 04 88",
    "sg:postcode":"2820",
    "sg:province":"Antwerpen",
    "wof:name":"Frank Serneels",
    "wof:placetype":"venue"
},
  "geometry": {"coordinates":[4.5496602058,51.0218009949],"type":"Point"}
}