{
  "type": "Feature",
  "properties": {
    "addr:full":"Ieperlaan 92 Brussel/bruxelles Bruxelles-Capitale 1000",
    "addr:housenumber":"92",
    "addr:postcode":"1000",
    "addr:street":"Ieperlaan;/",
    "iso:country":"BE",
    "sg:address":"Ieperlaan 92",
    "sg:city":"Brussel/bruxelles",
    "sg:orig_category":"Boekhouders",
    "sg:phone":"+32 2 223 22 09",
    "sg:postcode":"1000",
    "sg:province":"Bruxelles-Capitale",
    "wof:name":"Willy Tilman",
    "wof:placetype":"venue"
},
  "geometry": {"coordinates":[4.3465189934,50.8582267761],"type":"Point"}
}