{
  "type": "Feature",
  "properties": {
    "addr:full":"Rue De Bouillon 61 Beauraing Namur 5570",
    "addr:housenumber":"61",
    "addr:postcode":"5570",
    "addr:street":"Rue De Bouillon",
    "iso:country":"BE",
    "sg:address":"Rue De Bouillon 61",
    "sg:city":"Beauraing",
    "sg:orig_category":"Maroquinerie Fab",
    "sg:phone":"+32 82 71 12 92",
    "sg:postcode":"5570",
    "sg:province":"Namur",
    "wof:name":"Toucuir & Tecebe",
    "wof:placetype":"venue"
},
  "geometry": {"coordinates":[4.9577388763,50.1085166931],"type":"Point"}
}