{
  "type": "Feature",
  "properties": {
    "iso:country":"BE",
    "sg:address":"Hasseltsesteenweg 209",
    "sg:city":"Beringen",
    "sg:classifiers":[
        {
            "category":"Cafe",
            "type":"Food & Drink"
        }
    ],
    "sg:phone":"+32 11 42 76 90",
    "sg:postcode":"3580",
    "sg:province":"Limburg",
    "sg:tags":[
        "caf\u00e9s"
    ],
    "wof:name":"Lucien Verachtert",
    "wof:placetype":"venue"
},
  "geometry": {"coordinates":[5.2416000366,51.0378684998],"type":"Point"}
}