{
  "type": "Feature",
  "properties": {
    "addr:full":"Rue D\u00b4olloy 43 Viroinval Namur 5670",
    "addr:housenumber":"43",
    "addr:postcode":"5670",
    "addr:street":"Rue D\u00b4Olloy",
    "iso:country":"BE",
    "sg:address":"Rue D\u00b4olloy 43",
    "sg:city":"Viroinval",
    "sg:classifiers":[
        {
            "category":"Travel",
            "subcategory":"Hotels & Motels",
            "type":"Entertainment"
        }
    ],
    "sg:phone":"+32 60 39 95 25",
    "sg:postcode":"5670",
    "sg:province":"Namur",
    "sg:tags":[
        "restaurant"
    ],
    "wof:name":"L\u00b4or\u00c9e Du Bois",
    "wof:placetype":"venue"
},
  "geometry": {"coordinates":[4.6331958771,50.0251808167],"type":"Point"}
}