{
  "type": "Feature",
  "properties": {
    "addr:full":"Kruineikestraat 26 Haacht (tildonk) Vlaams-Brabant 3150",
    "addr:housenumber":"26",
    "addr:postcode":"3150",
    "addr:street":"Kruineikestraat",
    "iso:country":"BE",
    "sg:address":"Kruineikestraat 26",
    "sg:city":"Haacht (tildonk)",
    "sg:classifiers":[
        {
            "category":"Building & Trades",
            "subcategory":"Pest Control",
            "type":"Services"
        }
    ],
    "sg:phone":"+32 16 60 59 85",
    "sg:postcode":"3150",
    "sg:province":"Vlaams-Brabant",
    "sg:tags":[
        "painting",
        "contractor"
    ],
    "wof:name":"De Kerf E & Zn",
    "wof:placetype":"venue"
},
  "geometry": {"coordinates":[4.6438570023,50.9460716248],"type":"Point"}
}