{
  "type": "Feature",
  "properties": {
    "addr:full":"Rue De Brabant 114 Schaarbeek/schaerbeek Bruxelles-Capitale 1030",
    "addr:housenumber":"114",
    "addr:postcode":"1030",
    "addr:street":"Rue De Brabant",
    "iso:country":"BE",
    "sg:address":"Rue De Brabant 114",
    "sg:city":"Schaarbeek/schaerbeek",
    "sg:classifiers":[
        {
            "category":"Manufacturing",
            "subcategory":"Textiles",
            "type":"Manufacturing & Wholesale Goods"
        }
    ],
    "sg:phone":"+32 2 218 83 86",
    "sg:postcode":"1030",
    "sg:province":"Bruxelles-Capitale",
    "wof:name":"Brabant",
    "wof:placetype":"venue"
},
  "geometry": {"coordinates":[4.3641319275,50.8615455627],"type":"Point"}
}