{
  "type": "Feature",
  "properties": {
    "iso:country":"BE",
    "sg:address":"Veldstraat 44",
    "sg:city":"Ichtegem",
    "sg:classifiers":[
        {
            "category":"Freight",
            "type":"Transportation"
        }
    ],
    "sg:phone":"+32 51 58 11 34",
    "sg:postcode":"8480",
    "sg:province":"West-Vlaanderen",
    "sg:tags":[
        "-",
        "transport"
    ],
    "wof:name":"Hollevoet Bvba",
    "wof:placetype":"venue"
},
  "geometry": {"coordinates":[3.0383870602,51.0850906372],"type":"Point"}
}