{
  "type": "Feature",
  "properties": {
    "iso:country":"BE",
    "sg:address":"Grote Steenweg 580",
    "sg:city":"Antwerpen (berchem)",
    "sg:classifiers":[
        {
            "category":"Professional",
            "subcategory":"Business Services",
            "type":"Services"
        }
    ],
    "sg:phone":"+32 3 239 15 50",
    "sg:postcode":"2600",
    "sg:province":"Antwerpen",
    "sg:tags":[
        "bookkeeping"
    ],
    "wof:name":"Cefiac Bvba",
    "wof:placetype":"venue"
},
  "geometry": {"coordinates":[4.4174151421,51.1974411011],"type":"Point"}
}