{
  "type": "Feature",
  "properties": {
    "iso:country":"BE",
    "sg:address":"De Heuvel 27",
    "sg:city":"Genk",
    "sg:orig_category":"Ordinateurs and \u00e9quipement informatique",
    "sg:phone":"+32 89 35 57 63",
    "sg:postcode":"3600",
    "sg:province":"Limburg",
    "wof:name":"Low Budget Software",
    "wof:placetype":"venue"
},
  "geometry": {"coordinates":[5.4575681686,50.9718170166],"type":"Point"}
}