{
  "type": "Feature",
  "properties": {
    "addr:full":"Tieltstraat 219bb Meulebeke West-Vlaanderen 8760",
    "addr:housenumber":"219bb",
    "addr:postcode":"8760",
    "addr:street":"Tieltstraat",
    "iso:country":"BE",
    "sg:address":"Tieltstraat 219bb",
    "sg:city":"Meulebeke",
    "sg:orig_category":"Fleurs and plantes",
    "sg:phone":"+32 51 40 57 28",
    "sg:postcode":"8760",
    "sg:province":"West-Vlaanderen",
    "wof:name":"Lieven Dobbels",
    "wof:placetype":"venue"
},
  "geometry": {"coordinates":[3.3071498871,50.9730911255],"type":"Point"}
}