{
  "type": "Feature",
  "properties": {
    "addr:full":"Chauss\u00c9e De Bruxelles 359 Charleroi Hainaut 6040",
    "addr:housenumber":"359",
    "addr:postcode":"6040",
    "addr:street":"Chausse\u0301E De Bruxelles;Hainaut",
    "iso:country":"BE",
    "sg:address":"Chauss\u00c9e De Bruxelles 359",
    "sg:city":"Charleroi",
    "sg:classifiers":[
        {
            "category":"Fast Food",
            "type":"Food & Drink"
        }
    ],
    "sg:phone":"+32 71 35 64 69",
    "sg:postcode":"6040",
    "sg:province":"Hainaut",
    "sg:tags":[
        "\u00c0",
        "emporter",
        "restaurants"
    ],
    "wof:name":"Friterie Chez Carine",
    "wof:placetype":"venue"
},
  "geometry": {"coordinates":[4.4343881607,50.448600769],"type":"Point"}
}