{
  "type": "Feature",
  "properties": {
    "iso:country":"BE",
    "sg:address":"Place De Waressaix 12ba",
    "sg:city":"Estinnes",
    "sg:orig_category":"Begrafeniswezen",
    "sg:phone":"+32 65 58 65 32",
    "sg:postcode":"7120",
    "sg:province":"Hainaut",
    "wof:name":"Catherine & Succ.",
    "wof:placetype":"venue"
},
  "geometry": {"coordinates":[4.0862698555,50.386264801],"type":"Point"}
}