{
  "type": "Feature",
  "properties": {
    "addr:full":"Turkeijensteenweg 21 Pittem West-Vlaanderen 8740",
    "addr:housenumber":"21",
    "addr:postcode":"8740",
    "addr:street":"Turkeijensteenweg",
    "iso:country":"BE",
    "sg:address":"Turkeijensteenweg 21",
    "sg:city":"Pittem",
    "sg:orig_category":"Eleveurs de bovins",
    "sg:phone":"+32 51 46 69 07",
    "sg:postcode":"8740",
    "sg:province":"West-Vlaanderen",
    "wof:name":"Norbert Verdonck",
    "wof:placetype":"venue"
},
  "geometry": {"coordinates":[3.2795159817,51.0138092041],"type":"Point"}
}