{
  "type": "Feature",
  "properties": {
    "iso:country":"BE",
    "sg:address":"Pontweg 3",
    "sg:city":"Lokeren",
    "sg:classifiers":[
        {
            "category":"Restaurant",
            "type":"Food & Drink"
        }
    ],
    "sg:phone":"+32 9 348 29 43",
    "sg:postcode":"9160",
    "sg:province":"Oost-Vlaanderen",
    "wof:name":"Palinghuis Daknam",
    "wof:placetype":"venue"
},
  "geometry": {"coordinates":[3.9997699261,51.1303901672],"type":"Point"}
}