{
  "type": "Feature",
  "properties": {
    "addr:full":"Avenue Norbert Gille 94 Bruxelles (anderlecht) Bruxelles-Capitale 1070",
    "addr:housenumber":"94",
    "addr:postcode":"1070",
    "addr:street":"Avenue Norbert Gille",
    "iso:country":"BE",
    "sg:address":"Avenue Norbert Gille 94",
    "sg:city":"Bruxelles (anderlecht)",
    "sg:classifiers":[
        {
            "category":"Building & Trades",
            "subcategory":"Plumbing",
            "type":"Services"
        }
    ],
    "sg:phone":"+32 2 465 71 43",
    "sg:postcode":"1070",
    "sg:province":"Bruxelles-Capitale",
    "sg:tags":[
        "contractor"
    ],
    "wof:name":"Dakdeko",
    "wof:placetype":"venue"
},
  "geometry": {"coordinates":[4.3137378693,50.8450622559],"type":"Point"}
}