{
  "type": "Feature",
  "properties": {
    "addr:full":"Rue Ferdinand Nicolay 553 Saint-nicolas (tilleur) Li\u00e8ge 4420",
    "addr:housenumber":"553",
    "addr:postcode":"4420",
    "addr:street":"Rue Ferdinand Nicolay;Tilleur",
    "iso:country":"BE",
    "sg:address":"Rue Ferdinand Nicolay 553",
    "sg:city":"Saint-nicolas (tilleur)",
    "sg:classifiers":[
        {
            "category":"Personal",
            "subcategory":"Beauty Salon",
            "type":"Services"
        }
    ],
    "sg:phone":"+32 4 247 36 31",
    "sg:postcode":"4420",
    "sg:province":"Li\u00e8ge",
    "sg:tags":[
        "child",
        "-",
        "hairdressing"
    ],
    "wof:name":"New Men (mr Testa)",
    "wof:placetype":"venue"
},
  "geometry": {"coordinates":[5.5313000679,50.6251296997],"type":"Point"}
}