{
  "type": "Feature",
  "properties": {
    "addr:full":"Burg. Callewaertlaan 10 Lichtervelde West-Vlaanderen 8810",
    "addr:housenumber":"10",
    "addr:postcode":"8810",
    "addr:street":"Burg. Callewaertlaan",
    "iso:country":"BE",
    "sg:address":"Burg. Callewaertlaan 10",
    "sg:city":"Lichtervelde",
    "sg:orig_category":"Parfumeries. Instituts de beaut\u00e9. Centres de relaxation and bien-\u00eatre",
    "sg:phone":"+32 51 72 27 90",
    "sg:postcode":"8810",
    "sg:province":"West-Vlaanderen",
    "wof:name":"Esthetiek Renier",
    "wof:placetype":"venue"
},
  "geometry": {"coordinates":[3.1389501095,51.0278625488],"type":"Point"}
}