{
  "type": "Feature",
  "properties": {
    "iso:country":"BE",
    "sg:address":"Brugsestraat 176",
    "sg:city":"Zedelgem",
    "sg:orig_category":"Rundveehouders Varkenskwekers",
    "sg:phone":"+32 50 20 94 23",
    "sg:postcode":"8210",
    "sg:province":"West-Vlaanderen",
    "wof:name":"Walter Boone",
    "wof:placetype":"venue"
},
  "geometry": {"coordinates":[3.1293919086,51.12525177],"type":"Point"}
}