{
  "type": "Feature",
  "properties": {
    "addr:full":"Place Vaxelaire 18 Anh\u00c9e Namur 5537",
    "addr:housenumber":"18",
    "addr:postcode":"5537",
    "addr:street":"Place Vaxelaire",
    "iso:country":"BE",
    "sg:address":"Place Vaxelaire 18",
    "sg:city":"Anh\u00c9e",
    "sg:classifiers":[
        {
            "category":"Fast Food",
            "type":"Food & Drink"
        }
    ],
    "sg:phone":"+32 71 79 60 94",
    "sg:postcode":"5537",
    "sg:province":"Namur",
    "sg:tags":[
        "meeneem",
        "restaurant"
    ],
    "wof:name":"Au Campagnard",
    "wof:placetype":"venue"
},
  "geometry": {"coordinates":[4.7969799042,50.3342208862],"type":"Point"}
}