{
  "type": "Feature",
  "properties": {
    "addr:full":"Meynaertkouter 10 Deerlijk West-Vlaanderen 8540",
    "addr:housenumber":"10",
    "addr:postcode":"8540",
    "addr:street":"Meynaertkouter",
    "iso:country":"BE",
    "sg:address":"Meynaertkouter 10",
    "sg:city":"Deerlijk",
    "sg:classifiers":[
        {
            "category":"Professional",
            "subcategory":"Accounting & Tax Preparation",
            "type":"Services"
        }
    ],
    "sg:phone":"+32 56 72 65 68",
    "sg:postcode":"8540",
    "sg:province":"West-Vlaanderen",
    "sg:tags":[
        "bookkeeper"
    ],
    "wof:name":"Carrette C",
    "wof:placetype":"venue"
},
  "geometry": {"coordinates":[3.3724179268,50.8566055298],"type":"Point"}
}