{
  "type": "Feature",
  "properties": {
    "iso:country":"BE",
    "sg:address":"Aulnoitstraat 11",
    "sg:city":"Vloesberg/flobecq",
    "sg:orig_category":"Rundveehouders",
    "sg:phone":"+32 68 44 70 37",
    "sg:postcode":"7880",
    "sg:province":"Hainaut",
    "wof:name":"Guy Marbaix",
    "wof:placetype":"venue"
},
  "geometry": {"coordinates":[3.765360117,50.7420158386],"type":"Point"}
}