{
  "type": "Feature",
  "properties": {
    "iso:country":"BE",
    "sg:address":"Place Coronmeuse 16",
    "sg:city":"Li\u00e8ge 1",
    "sg:classifiers":[
        {
            "category":"Retail",
            "subcategory":"Funeral Services",
            "type":"Services"
        }
    ],
    "sg:phone":"+32 4 264 12 22",
    "sg:postcode":"4000",
    "sg:province":"Li\u00e8ge",
    "sg:tags":[
        "director"
    ],
    "wof:name":"Ciborgs",
    "wof:placetype":"venue"
},
  "geometry": {"coordinates":[5.6117868423,50.655216217],"type":"Point"}
}