{
  "type": "Feature",
  "properties": {
    "addr:full":"Avenue Des Mille M\u00c8tres 85 Sint-pieters-woluwe/woluwe-saint-pierre Bruxelles-Capitale 1150",
    "addr:housenumber":"85",
    "addr:postcode":"1150",
    "addr:street":"Avenue Des Mille Me\u0300Tres;/",
    "iso:country":"BE",
    "sg:address":"Avenue Des Mille M\u00c8tres 85",
    "sg:city":"Sint-pieters-woluwe/woluwe-saint-pierre",
    "sg:orig_category":"Experts-comptables",
    "sg:phone":"+32 2 779 19 91",
    "sg:postcode":"1150",
    "sg:province":"Bruxelles-Capitale",
    "wof:name":"Paul Moreau",
    "wof:placetype":"venue"
},
  "geometry": {"coordinates":[4.4635639191,50.8367919922],"type":"Point"}
}