{
  "type": "Feature",
  "properties": {
    "iso:country":"BE",
    "sg:address":"Boomsesteenweg 68",
    "sg:city":"Aartselaar",
    "sg:classifiers":[
        {
            "category":"Shopping",
            "subcategory":"Clothing, Apparel, & Fashions",
            "type":"Retail Goods"
        }
    ],
    "sg:phone":"+32 3 844 34 44",
    "sg:postcode":"2630",
    "sg:province":"Antwerpen",
    "sg:tags":[
        "large",
        "-",
        "clothing",
        "sale-rooms"
    ],
    "wof:name":"Pecotex Mode",
    "wof:placetype":"venue"
},
  "geometry": {"coordinates":[4.3710961342,51.1145935059],"type":"Point"}
}