{
  "type": "Feature",
  "properties": {
    "addr:full":"Schroonhoek 19 Evergem Oost-Vlaanderen 9940",
    "addr:housenumber":"19",
    "addr:postcode":"9940",
    "addr:street":"Schroonhoek;Oost-Vlaanderen",
    "iso:country":"BE",
    "sg:address":"Schroonhoek 19",
    "sg:city":"Evergem",
    "sg:orig_category":"Paramedische behandelingen",
    "sg:phone":"+32 9 357 36 87",
    "sg:postcode":"9940",
    "sg:province":"Oost-Vlaanderen",
    "wof:name":"Christel Van Speybroeck",
    "wof:placetype":"venue"
},
  "geometry": {"coordinates":[3.6590979099,51.1519241333],"type":"Point"}
}