{
  "type": "Feature",
  "properties": {
    "addr:full":"Rue Albert I 43 P\u00e9ruwelz Hainaut 7600",
    "addr:housenumber":"43",
    "addr:postcode":"7600",
    "addr:street":"Rue Albert I",
    "iso:country":"BE",
    "sg:address":"Rue Albert I 43",
    "sg:city":"P\u00e9ruwelz",
    "sg:classifiers":[
        {
            "category":"Food & Beverages",
            "subcategory":"Chocolate",
            "type":"Retail Goods"
        }
    ],
    "sg:phone":"+32 69 77 60 89",
    "sg:postcode":"7600",
    "sg:province":"Hainaut",
    "sg:tags":[
        "confectionery",
        "-"
    ],
    "wof:name":"D\u00e9lice D'or Sa",
    "wof:placetype":"venue"
},
  "geometry": {"coordinates":[3.5906949043,50.5075836182],"type":"Point"}
}