{
  "type": "Feature",
  "properties": {
    "addr:full":"Van Geertstraat 30 Antwerpen Antwerpen 2140",
    "addr:housenumber":"30",
    "addr:postcode":"2140",
    "addr:street":"Geertstraat",
    "iso:country":"BE",
    "sg:address":"Van Geertstraat 30",
    "sg:city":"Antwerpen",
    "sg:orig_category":"Artistes ind\u00e9pendants",
    "sg:phone":"+32 3 236 69 29",
    "sg:postcode":"2140",
    "sg:province":"Antwerpen",
    "wof:name":"Sofie Decleir",
    "wof:placetype":"venue"
},
  "geometry": {"coordinates":[4.4280700684,51.2164115906],"type":"Point"}
}