{
  "type": "Feature",
  "properties": {
    "iso:country":"BE",
    "sg:address":"Avenue De La Houssi\u00c8re 78",
    "sg:city":"Braine-le-comte",
    "sg:orig_category":"Apotheken Ziekenhuizen and zorginstellingen",
    "sg:phone":"+32 67 55 03 11",
    "sg:postcode":"7090",
    "sg:province":"Hainaut",
    "wof:name":"Centre Hospitalier",
    "wof:placetype":"venue"
},
  "geometry": {"coordinates":[4.1510648727,50.610168457],"type":"Point"}
}