{
  "type": "Feature",
  "properties": {
    "iso:country":"BE",
    "sg:address":"Boulevard Joseph Tirou 91",
    "sg:city":"Charleroi",
    "sg:orig_category":"Instituts de beaut\u00e9",
    "sg:phone":"+32 71 31 56 15",
    "sg:postcode":"6000",
    "sg:province":"Hainaut",
    "wof:name":"Le Bel F.",
    "wof:placetype":"venue"
},
  "geometry": {"coordinates":[4.4418148994,50.4085197449],"type":"Point"}
}