{
  "type": "Feature",
  "properties": {
    "iso:country":"BE",
    "sg:address":"Dreve Des Maricolles 107",
    "sg:city":"Berchem-sainte-agathe",
    "sg:orig_category":"Diverse bedrijfsbeheeradviesbureaus",
    "sg:phone":"+32 2 465 63 67",
    "sg:postcode":"1082",
    "sg:province":"Bruxelles-Capitale",
    "wof:name":"Apsad",
    "wof:placetype":"venue"
},
  "geometry": {"coordinates":[4.287812233,50.8587646484],"type":"Point"}
}