{
  "type": "Feature",
  "properties": {
    "addr:full":"Avenue Marnix 17 Brussel/bruxelles Bruxelles-Capitale 1000",
    "addr:housenumber":"17",
    "addr:postcode":"1000",
    "addr:street":"Avenue Marnix;/",
    "iso:country":"BE",
    "sg:address":"Avenue Marnix 17",
    "sg:city":"Brussel/bruxelles",
    "sg:orig_category":"Cr\u00e9dit \u00e0 la consommation. Pr\u00eats hypoth\u00e9caires and cr\u00e9dits immobiliers",
    "sg:phone":"+32 2 551 99 50",
    "sg:postcode":"1000",
    "sg:province":"Bruxelles-Capitale",
    "wof:name":"Deutsche Bank",
    "wof:placetype":"venue"
},
  "geometry": {"coordinates":[4.3640460968,50.8391113281],"type":"Point"}
}