{
  "type": "Feature",
  "properties": {
    "iso:country":"BE",
    "sg:address":"Olijftakstraat 30",
    "sg:city":"Antwerpen",
    "sg:classifiers":[
        {
            "category":"Food & Beverages",
            "subcategory":"Groceries & Convenience Stores",
            "type":"Retail Goods"
        }
    ],
    "sg:phone":"+32 3 234 19 58",
    "sg:postcode":"2060",
    "sg:province":"Antwerpen",
    "sg:tags":[
        "grocer"
    ],
    "wof:name":"Willemse C",
    "wof:placetype":"venue"
},
  "geometry": {"coordinates":[4.4172201157,51.2237129211],"type":"Point"}
}