{
  "type": "Feature",
  "properties": {
    "iso:country":"BE",
    "sg:address":"Lievevrouwestraat 59",
    "sg:city":"Ranst",
    "sg:classifiers":[
        {
            "category":"Banks & Credit Unions",
            "subcategory":"Financial Services",
            "type":"Services"
        }
    ],
    "sg:phone":"+32 3 485 55 52",
    "sg:postcode":"2520",
    "sg:province":"Antwerpen",
    "sg:tags":[
        "loan",
        "mortgage"
    ],
    "wof:name":"Van Beeck",
    "wof:placetype":"venue"
},
  "geometry": {"coordinates":[4.5630130768,51.1884002686],"type":"Point"}
}