{
  "type": "Feature",
  "properties": {
    "iso:country":"BE",
    "sg:address":"Sint-janstraat 4",
    "sg:city":"Rumst",
    "sg:orig_category":"Pleisterwerk Woningbouw",
    "sg:phone":"+32 3 844 40 61",
    "sg:postcode":"2840",
    "sg:province":"Antwerpen",
    "wof:name":"Mercken",
    "wof:placetype":"venue"
},
  "geometry": {"coordinates":[4.3835039139,51.11120224],"type":"Point"}
}