{
  "type": "Feature",
  "properties": {
    "addr:full":"Stationsstraat 9 Aalst Oost-Vlaanderen 9300",
    "addr:housenumber":"9",
    "addr:postcode":"9300",
    "addr:street":"Stationsstraat",
    "iso:country":"BE",
    "sg:address":"Stationsstraat 9",
    "sg:city":"Aalst",
    "sg:classifiers":[
        {
            "category":"Health Services",
            "subcategory":"Health Practitioner",
            "type":"Services"
        }
    ],
    "sg:phone":"+32 475 23 48 22",
    "sg:postcode":"9300",
    "sg:province":"Oost-Vlaanderen",
    "sg:tags":[
        "osteopath"
    ],
    "wof:name":"Van Neck H",
    "wof:placetype":"venue"
},
  "geometry": {"coordinates":[4.0374121666,50.9414787292],"type":"Point"}
}