{
  "type": "Feature",
  "properties": {
    "addr:full":"Chauss\u00e9e Romaine 37 Oreye Li\u00e8ge 4360",
    "addr:housenumber":"37",
    "addr:postcode":"4360",
    "addr:street":"Chausse\u0301E Romaine",
    "iso:country":"BE",
    "sg:address":"Chauss\u00e9e Romaine 37",
    "sg:city":"Oreye",
    "sg:classifiers":[
        {
            "category":"Health Services",
            "subcategory":"Nursing And Care Facility",
            "type":"Services"
        }
    ],
    "sg:phone":"+32 19 67 74 75",
    "sg:postcode":"4360",
    "sg:province":"Li\u00e8ge",
    "sg:tags":[
        "home"
    ],
    "wof:name":"Malchair V",
    "wof:placetype":"venue"
},
  "geometry": {"coordinates":[5.3494801521,50.733581543],"type":"Point"}
}