{
  "type": "Feature",
  "properties": {
    "addr:full":"Hertooie 13 Gent (zwijnaarde) Oost-Vlaanderen 9052",
    "addr:housenumber":"13",
    "addr:postcode":"9052",
    "addr:street":"Hertooie",
    "iso:country":"BE",
    "sg:address":"Hertooie 13",
    "sg:city":"Gent (zwijnaarde)",
    "sg:classifiers":[
        {
            "category":"Health Services",
            "subcategory":"Health Practitioner",
            "type":"Services"
        }
    ],
    "sg:phone":"+32 9 220 51 97",
    "sg:postcode":"9052",
    "sg:province":"Oost-Vlaanderen",
    "sg:tags":[
        "physiotherapist"
    ],
    "wof:name":"Hoste Peggy",
    "wof:placetype":"venue"
},
  "geometry": {"coordinates":[3.7167270184,51.0002937317],"type":"Point"}
}