{
  "type": "Feature",
  "properties": {
    "iso:country":"BE",
    "sg:address":"Nieuwstraat 66",
    "sg:city":"Wervik",
    "sg:orig_category":"Kapsalons",
    "sg:phone":"+32 56 31 19 97",
    "sg:postcode":"8940",
    "sg:province":"West-Vlaanderen",
    "wof:name":"Coiffure Andr\u00c9",
    "wof:placetype":"venue"
},
  "geometry": {"coordinates":[3.040815115,50.7799530029],"type":"Point"}
}