{
  "type": "Feature",
  "properties": {
    "addr:full":"Sint-truidersteenweg 1 Tongeren Limburg 3700",
    "addr:housenumber":"1",
    "addr:postcode":"3700",
    "addr:street":"Sint-Truidersteenweg",
    "iso:country":"BE",
    "sg:address":"Sint-truidersteenweg 1",
    "sg:city":"Tongeren",
    "sg:classifiers":[
        {
            "category":"Cafe",
            "type":"Food & Drink"
        }
    ],
    "sg:phone":"+32 12 23 46 02",
    "sg:postcode":"3700",
    "sg:province":"Limburg",
    "sg:tags":[
        "caf\u00e9s"
    ],
    "wof:name":"Caf\u00c9 Gretry",
    "wof:placetype":"venue"
},
  "geometry": {"coordinates":[5.4631547928,50.7807312012],"type":"Point"}
}