{
  "type": "Feature",
  "properties": {
    "addr:full":"110 Rue Bois-bourdon 7080 Frameries 110",
    "addr:housenumber":"110;110",
    "addr:postcode":"7080",
    "addr:street":"Rue Bois-Bourdon",
    "iso:country":"BE",
    "sg:address":"110",
    "sg:city":"Rue Bois-bourdon 7080 Frameries",
    "sg:classifiers":[
        {
            "category":"Food & Beverages",
            "subcategory":"Groceries & Convenience Stores",
            "type":"Retail Goods"
        }
    ],
    "sg:phone":"+32 65 67 36 80",
    "sg:postcode":"110",
    "sg:tags":[
        "product",
        "related"
    ],
    "wof:name":"Centragro Scrl",
    "wof:placetype":"venue"
},
  "geometry": {"coordinates":[3.9093689919,50.4016647339],"type":"Point"}
}