{
  "type": "Feature",
  "properties": {
    "addr:full":"Zandstr 6 Wortel Antwerpen 2323",
    "addr:housenumber":"6",
    "addr:postcode":"2323",
    "addr:street":"Zandstr",
    "iso:country":"BE",
    "sg:address":"Zandstr 6",
    "sg:city":"Wortel",
    "sg:classifiers":[
        {
            "category":"Home & Garden",
            "subcategory":"Furniture",
            "type":"Retail Goods"
        }
    ],
    "sg:phone":"+32 3 314 82 90",
    "sg:postcode":"2323",
    "sg:province":"Antwerpen",
    "sg:tags":[
        "wood"
    ],
    "wof:name":"Houtzagerij Van Erck Nv",
    "wof:placetype":"venue"
},
  "geometry": {"coordinates":[4.7942008972,51.3939857483],"type":"Point"}
}