{
  "type": "Feature",
  "properties": {
    "addr:full":"Hemelstraat 42 Antwerpen Antwerpen 2018",
    "addr:housenumber":"42",
    "addr:postcode":"2018",
    "addr:street":"Hemelstraat",
    "iso:country":"BE",
    "sg:address":"Hemelstraat 42",
    "sg:city":"Antwerpen",
    "sg:orig_category":"Industri\u00eble wasserijen and droogkuis",
    "sg:phone":"+32 3 232 22 06",
    "sg:postcode":"2018",
    "sg:province":"Antwerpen",
    "wof:name":"Drynet",
    "wof:placetype":"venue"
},
  "geometry": {"coordinates":[4.4104709625,51.2091331482],"type":"Point"}
}