{
  "type": "Feature",
  "properties": {
    "addr:full":"Sleutelbaan 10 Begijnendijk Vlaams-Brabant 3130",
    "addr:housenumber":"10",
    "addr:postcode":"3130",
    "addr:street":"Sleutelbaan",
    "iso:country":"BE",
    "sg:address":"Sleutelbaan 10",
    "sg:city":"Begijnendijk",
    "sg:orig_category":"Artsen and specialisten",
    "sg:phone":"+32 16 69 88 11",
    "sg:postcode":"3130",
    "sg:province":"Vlaams-Brabant",
    "wof:name":"F. Ceulemans",
    "wof:placetype":"venue"
},
  "geometry": {"coordinates":[4.8000349998,51.0247001648],"type":"Point"}
}