{
  "type": "Feature",
  "properties": {
    "addr:full":"Kroonstraat 247 Beringen (beverlo) Limburg 3581",
    "addr:housenumber":"247",
    "addr:postcode":"3581",
    "addr:street":"Kroonstraat",
    "iso:country":"BE",
    "sg:address":"Kroonstraat 247",
    "sg:city":"Beringen (beverlo)",
    "sg:classifiers":[
        {
            "category":"Bars & Pubs",
            "type":"Food & Drink"
        }
    ],
    "sg:phone":"+32 11 40 30 93",
    "sg:postcode":"3581",
    "sg:province":"Limburg",
    "sg:tags":[
        "tavern"
    ],
    "wof:name":"De Postkoets",
    "wof:placetype":"venue"
},
  "geometry": {"coordinates":[5.2692751884,51.0918197632],"type":"Point"}
}