{
  "type": "Feature",
  "properties": {
    "iso:country":"BE",
    "sg:address":"Rue Thier D\u00b4oupeye 16",
    "sg:city":"Oupeye",
    "sg:classifiers":[
        {
            "category":"Fast Food",
            "type":"Food & Drink"
        }
    ],
    "sg:phone":"+32 4 264 70 68",
    "sg:postcode":"4683",
    "sg:province":"Li\u00e8ge",
    "sg:tags":[
        "\u00c0",
        "emporter",
        "restaurants"
    ],
    "wof:name":"Pizza Renato",
    "wof:placetype":"venue"
},
  "geometry": {"coordinates":[5.6495499611,50.6958198547],"type":"Point"}
}