{
  "type": "Feature",
  "properties": {
    "addr:full":"Oudergemselaan 342 Etterbeek/etterbeek Bruxelles-Capitale 1040",
    "addr:housenumber":"342",
    "addr:postcode":"1040",
    "addr:street":"Oudergemselaan",
    "iso:country":"BE",
    "sg:address":"Oudergemselaan 342",
    "sg:city":"Etterbeek/etterbeek",
    "sg:orig_category":"Apotheken",
    "sg:phone":"+32 2 647 43 93",
    "sg:postcode":"1040",
    "sg:province":"Bruxelles-Capitale",
    "wof:name":"Michel Brosteaux",
    "wof:placetype":"venue"
},
  "geometry": {"coordinates":[4.3901591301,50.8308677673],"type":"Point"}
}