{
  "type": "Feature",
  "properties": {
    "addr:full":"Rue Des Canons 4 Comines-warneton Hainaut 7780",
    "addr:housenumber":"4",
    "addr:postcode":"7780",
    "addr:street":"Rue Des Canons",
    "iso:country":"BE",
    "sg:address":"Rue Des Canons 4",
    "sg:city":"Comines-warneton",
    "sg:orig_category":"Animations diverses",
    "sg:phone":"+32 56 55 63 69",
    "sg:postcode":"7780",
    "sg:province":"Hainaut",
    "wof:name":"Odaert P",
    "wof:placetype":"venue"
},
  "geometry": {"coordinates":[2.9970300198,50.7672691345],"type":"Point"}
}