{
  "type": "Feature",
  "properties": {
    "addr:full":"Ieperstraat 25 Menen West-Vlaanderen 8930",
    "addr:housenumber":"25",
    "addr:postcode":"8930",
    "addr:street":"Ieperstraat",
    "iso:country":"BE",
    "sg:address":"Ieperstraat 25",
    "sg:city":"Menen",
    "sg:classifiers":[
        {
            "category":"Insurance",
            "subcategory":"Insurance Agent",
            "type":"Services"
        }
    ],
    "sg:phone":"+32 56 51 16 77",
    "sg:postcode":"8930",
    "sg:province":"West-Vlaanderen",
    "sg:tags":[
        "broker"
    ],
    "wof:name":"Braems Verzekeringskantoor",
    "wof:placetype":"venue"
},
  "geometry": {"coordinates":[3.1181380749,50.7966537476],"type":"Point"}
}