{
  "type": "Feature",
  "properties": {
    "addr:full":"Koninklijke Jachtstraat 29 Oudergem/auderghem Bruxelles-Capitale 1160",
    "addr:housenumber":"29",
    "addr:postcode":"1160",
    "addr:street":"Koninklijke Jachtstraat;/",
    "iso:country":"BE",
    "sg:address":"Koninklijke Jachtstraat 29",
    "sg:city":"Oudergem/auderghem",
    "sg:orig_category":"Decoratieve kunst and kunstbenodigdheden",
    "sg:phone":"+32 2 640 45 84",
    "sg:postcode":"1160",
    "sg:province":"Bruxelles-Capitale",
    "wof:name":"J.f. Forton",
    "wof:placetype":"venue"
},
  "geometry": {"coordinates":[4.4029960632,50.821472168],"type":"Point"}
}