{
  "type": "Feature",
  "properties": {
    "addr:full":"Rue Du Temple 22 La Louviere Hainaut 7100",
    "addr:housenumber":"22",
    "addr:postcode":"7100",
    "addr:street":"Rue Du Temple",
    "iso:country":"BE",
    "sg:address":"Rue Du Temple 22",
    "sg:city":"La Louviere",
    "sg:classifiers":[
        {
            "category":"Shopping",
            "subcategory":"Clothing, Apparel, & Fashions",
            "type":"Retail Goods"
        }
    ],
    "sg:phone":"+32 64 22 79 53",
    "sg:postcode":"7100",
    "sg:province":"Hainaut",
    "sg:tags":[
        "ondergoed",
        "lingerie"
    ],
    "wof:name":"Maison Corsouple",
    "wof:placetype":"venue"
},
  "geometry": {"coordinates":[4.1883468628,50.4767913818],"type":"Point"}
}