{
  "type": "Feature",
  "properties": {
    "iso:country":"BE",
    "sg:address":"Cokaifagne 52bb",
    "sg:city":"Jalhay",
    "sg:orig_category":"Dranken Gh",
    "sg:phone":"+32 87 47 43 86",
    "sg:postcode":"4845",
    "sg:province":"Li\u00e8ge",
    "wof:name":"Les Foug\u00c8res",
    "wof:placetype":"venue"
},
  "geometry": {"coordinates":[5.967373848,50.4873275757],"type":"Point"}
}