{
  "type": "Feature",
  "properties": {
    "iso:country":"BE",
    "sg:address":"Golfclub 1",
    "sg:city":"Houthalen-helchteren (houthalen)",
    "sg:classifiers":[
        {
            "category":"Arena",
            "subcategory":"Sports Club",
            "type":"Entertainment"
        }
    ],
    "sg:phone":"+32 89 38 35 43",
    "sg:postcode":"3530",
    "sg:province":"Limburg",
    "wof:name":"Limburg Golf En Country Club",
    "wof:placetype":"venue"
},
  "geometry": {"coordinates":[5.434773922,51.0222930908],"type":"Point"}
}