{
  "type": "Feature",
  "properties": {
    "addr:full":"Boulevard De La Woluwe 28 Bruxelles (woluwe-saint-pierre) Bruxelles-Capitale 1150",
    "addr:housenumber":"28",
    "addr:postcode":"1150",
    "addr:street":"Boulevard De La Woluwe",
    "iso:country":"BE",
    "sg:address":"Boulevard De La Woluwe 28",
    "sg:city":"Bruxelles (woluwe-saint-pierre)",
    "sg:classifiers":[
        {
            "category":"Food & Beverages",
            "subcategory":"Supermarket",
            "type":"Retail Goods"
        }
    ],
    "sg:phone":"+32 2 771 20 60",
    "sg:postcode":"1150",
    "sg:province":"Bruxelles-Capitale",
    "sg:tags":[
        "department",
        "store"
    ],
    "wof:name":"Rob",
    "wof:placetype":"venue"
},
  "geometry": {"coordinates":[4.434440136,50.8372688293],"type":"Point"}
}