{
  "type": "Feature",
  "properties": {
    "addr:full":"Eug\u00c8ne Keymplein 49 Watermaal-bosvoorde/watermael-boitsfort Bruxelles-Capitale 1170",
    "addr:housenumber":"49",
    "addr:postcode":"1170",
    "addr:street":"Euge\u0300Ne Keymplein",
    "iso:country":"BE",
    "sg:address":"Eug\u00c8ne Keymplein 49",
    "sg:city":"Watermaal-bosvoorde/watermael-boitsfort",
    "sg:orig_category":"Diverse kredietdiensten",
    "sg:postcode":"1170",
    "sg:province":"Bruxelles-Capitale",
    "wof:name":"Bancontact-mister Cash",
    "wof:placetype":"venue"
},
  "geometry": {"coordinates":[4.4030508995,50.8091964722],"type":"Point"}
}