{
  "type": "Feature",
  "properties": {
    "iso:country":"BE",
    "sg:address":"Stationsstraat 3",
    "sg:city":"Avelgem",
    "sg:orig_category":"Boucheries",
    "sg:phone":"+32 56 64 42 11",
    "sg:postcode":"8580",
    "sg:province":"West-Vlaanderen",
    "wof:name":"Erik Verdonckt",
    "wof:placetype":"venue"
},
  "geometry": {"coordinates":[3.4432299137,50.7714233398],"type":"Point"}
}