{
  "type": "Feature",
  "properties": {
    "iso:country":"BE",
    "sg:address":"Isschot 22",
    "sg:city":"Kasterlee",
    "sg:classifiers":[
        {
            "category":"Recreation",
            "subcategory":"Arcade",
            "type":"Entertainment"
        }
    ],
    "sg:phone":"+32 14 85 15 66",
    "sg:postcode":"2460",
    "sg:province":"Antwerpen",
    "sg:tags":[
        "machine",
        "amusement"
    ],
    "wof:name":"Hovak Bvba",
    "wof:placetype":"venue"
},
  "geometry": {"coordinates":[4.9905991554,51.2505149841],"type":"Point"}
}