{
  "type": "Feature",
  "properties": {
    "iso:country":"BE",
    "sg:address":"Bevelse Steenweg 53",
    "sg:city":"Herenthout",
    "sg:orig_category":"Huisdierenkwekers",
    "sg:phone":"+32 14 51 38 94",
    "sg:postcode":"2270",
    "sg:province":"Antwerpen",
    "wof:name":"Kenn.von Spitzbubezwinger",
    "wof:placetype":"venue"
},
  "geometry": {"coordinates":[4.7229809761,51.1340904236],"type":"Point"}
}