{
  "type": "Feature",
  "properties": {
    "addr:full":"Oscar Verschuerestraat 3 Waregem West-Vlaanderen 8790",
    "addr:housenumber":"3",
    "addr:postcode":"8790",
    "addr:street":"Verschuerestraat",
    "iso:country":"BE",
    "sg:address":"Oscar Verschuerestraat 3",
    "sg:city":"Waregem",
    "sg:classifiers":[
        {
            "category":"Health Services",
            "subcategory":"Nursing And Care Facility",
            "type":"Services"
        }
    ],
    "sg:phone":"+32 56 61 00 52",
    "sg:postcode":"8790",
    "sg:province":"West-Vlaanderen",
    "sg:tags":[
        "home",
        "rest"
    ],
    "wof:name":"Acropolys Bvba",
    "wof:placetype":"venue"
},
  "geometry": {"coordinates":[3.4307999611,50.8874206543],"type":"Point"}
}