{
  "type": "Feature",
  "properties": {
    "iso:country":"BE",
    "sg:address":"Rue De Bronne 1",
    "sg:city":"Jodoigne",
    "sg:orig_category":"Ordinateurs and \u00e9quipement informatique",
    "sg:phone":"+32 10 81 33 72",
    "sg:postcode":"1370",
    "sg:province":"Brabant Wallon",
    "wof:name":"I F R",
    "wof:placetype":"venue"
},
  "geometry": {"coordinates":[4.8948540688,50.7404022217],"type":"Point"}
}