{
  "type": "Feature",
  "properties": {
    "iso:country":"BE",
    "sg:address":"Bouwmeestersstraat 17",
    "sg:city":"Gent",
    "sg:orig_category":"Loodgieterij, verwarming and sanitaire installaties",
    "sg:phone":"+32 9 228 01 40",
    "sg:postcode":"9040",
    "sg:province":"Oost-Vlaanderen",
    "wof:name":"Fa. Francet",
    "wof:placetype":"venue"
},
  "geometry": {"coordinates":[3.7471470833,51.0502243042],"type":"Point"}
}