{
  "type": "Feature",
  "properties": {
    "iso:country":"BE",
    "sg:address":"Rue De P\u00e2turages 57bis",
    "sg:city":"Colfontaine (wasmes)",
    "sg:classifiers":[
        {
            "category":"Cinema",
            "subcategory":"Movie Theater",
            "type":"Entertainment"
        }
    ],
    "sg:phone":"+32 65 66 33 41",
    "sg:postcode":"7340",
    "sg:province":"Hainaut",
    "wof:name":"Cam\u00e9o (le)",
    "wof:placetype":"venue"
},
  "geometry": {"coordinates":[3.8485589027,50.4123916626],"type":"Point"}
}