{
  "type": "Feature",
  "properties": {
    "iso:country":"BE",
    "sg:address":"Langestraat 28",
    "sg:city":"Mol",
    "sg:orig_category":"Pain, p\u00e2tisseries and confiseries",
    "sg:phone":"+32 14 82 02 75",
    "sg:postcode":"2400",
    "sg:province":"Antwerpen",
    "wof:name":"Rudi Wouters",
    "wof:placetype":"venue"
},
  "geometry": {"coordinates":[5.2205271721,51.190410614],"type":"Point"}
}