{
  "type": "Feature",
  "properties": {
    "iso:country":"BE",
    "sg:address":"Meensesteenweg 18ba",
    "sg:city":"Moorslede",
    "sg:orig_category":"Voertuigen",
    "sg:phone":"+32 56 50 44 13",
    "sg:postcode":"8890",
    "sg:province":"West-Vlaanderen",
    "wof:name":"H. Beikoghli Ardebili",
    "wof:placetype":"venue"
},
  "geometry": {"coordinates":[3.1135530472,50.889503479],"type":"Point"}
}