{
  "type": "Feature",
  "properties": {
    "addr:full":"Kapellestraat 8 C Langdorp Vlaams-Brabant 3201",
    "addr:housenumber":"8 c",
    "addr:postcode":"3201",
    "addr:street":"Kapellestraat",
    "iso:country":"BE",
    "sg:address":"Kapellestraat 8 C",
    "sg:city":"Langdorp",
    "sg:orig_category":"Diensten voor huisdieren",
    "sg:phone":"+32 16 56 47 00",
    "sg:postcode":"3201",
    "sg:province":"Vlaams-Brabant",
    "wof:name":"Doggies Self Dog Wash",
    "wof:placetype":"venue"
},
  "geometry": {"coordinates":[4.8535470963,51.007194519],"type":"Point"}
}