{
  "type": "Feature",
  "properties": {
    "addr:full":"Avenue De Marlagne 14 Namur Namur 5000",
    "addr:housenumber":"14",
    "addr:postcode":"5000",
    "addr:street":"Avenue De Marlagne",
    "iso:country":"BE",
    "sg:address":"Avenue De Marlagne 14",
    "sg:city":"Namur",
    "sg:orig_category":"Journaux. Tabac. Librairies",
    "sg:phone":"+32 81 73 66 29",
    "sg:postcode":"5000",
    "sg:province":"Namur",
    "wof:name":"Librairie De La Marlagne",
    "wof:placetype":"venue"
},
  "geometry": {"coordinates":[4.8427548409,50.4596366882],"type":"Point"}
}