{
  "type": "Feature",
  "properties": {
    "addr:full":"Gentsesteenweg 65 Harelbeke West-Vlaanderen 8530",
    "addr:housenumber":"65",
    "addr:postcode":"8530",
    "addr:street":"Gentsesteenweg",
    "iso:country":"BE",
    "sg:address":"Gentsesteenweg 65",
    "sg:city":"Harelbeke",
    "sg:orig_category":"Grands magasins",
    "sg:phone":"+32 14367",
    "sg:postcode":"8530",
    "sg:province":"West-Vlaanderen",
    "wof:name":"Lidl",
    "wof:placetype":"venue"
},
  "geometry": {"coordinates":[3.3205139637,50.8616523743],"type":"Point"}
}