{
  "type": "Feature",
  "properties": {
    "iso:country":"BE",
    "sg:address":"Zonnedauwstraat 1",
    "sg:city":"Merelbeke",
    "sg:classifiers":[
        {
            "category":"Banks & Credit Unions",
            "subcategory":"Investment Brokerage",
            "type":"Services"
        }
    ],
    "sg:phone":"+32 9 230 23 54",
    "sg:postcode":"9820",
    "sg:province":"Oost-Vlaanderen",
    "sg:tags":[
        "repair",
        "-",
        "installation",
        "sanitary",
        "article"
    ],
    "wof:name":"Goormachtig J & Zn",
    "wof:placetype":"venue"
},
  "geometry": {"coordinates":[3.7661840916,51.0095443726],"type":"Point"}
}