{
  "type": "Feature",
  "properties": {
    "iso:country":"BE",
    "sg:address":"Rue De L'enseignement 37",
    "sg:city":"Nivelles",
    "sg:orig_category":"V\u00e9t\u00e9rinaires",
    "sg:phone":"+32 67 84 34 34",
    "sg:postcode":"1400",
    "sg:province":"Brabant Wallon",
    "wof:name":"Jacques D'halluin",
    "wof:placetype":"venue"
},
  "geometry": {"coordinates":[4.325512886,50.6060523987],"type":"Point"}
}