{
  "type": "Feature",
  "properties": {
    "iso:country":"BE",
    "sg:address":"Grotestraat 163",
    "sg:city":"Genk",
    "sg:orig_category":"Boekhouders",
    "sg:phone":"+32 89 35 90 69",
    "sg:postcode":"3600",
    "sg:province":"Limburg",
    "wof:name":"Gerda Roux",
    "wof:placetype":"venue"
},
  "geometry": {"coordinates":[5.486330986,50.9632606506],"type":"Point"}
}