{
  "type": "Feature",
  "properties": {
    "iso:country":"BE",
    "sg:address":"Maastrichtersteenweg 86",
    "sg:city":"Riemst",
    "sg:orig_category":"Artsen and specialisten",
    "sg:phone":"+32 12 45 44 84",
    "sg:postcode":"3770",
    "sg:province":"Limburg",
    "wof:name":"Christophe Wolfs",
    "wof:placetype":"venue"
},
  "geometry": {"coordinates":[5.612569809,50.8188209534],"type":"Point"}
}