{
  "type": "Feature",
  "properties": {
    "addr:full":"Kasterstraat 99 Wetteren Oost-Vlaanderen 9230",
    "addr:housenumber":"99",
    "addr:postcode":"9230",
    "addr:street":"Kasterstraat",
    "iso:country":"BE",
    "sg:address":"Kasterstraat 99",
    "sg:city":"Wetteren",
    "sg:orig_category":"Eleveurs de bovins",
    "sg:phone":"+32 9 369 33 51",
    "sg:postcode":"9230",
    "sg:province":"Oost-Vlaanderen",
    "wof:name":"Roland Van Waelvelde",
    "wof:placetype":"venue"
},
  "geometry": {"coordinates":[3.8876760006,51.0124092102],"type":"Point"}
}