{
  "type": "Feature",
  "properties": {
    "addr:full":"Avenue Baron De Lhoneux 20 Namur (jambes) Namur 5100",
    "addr:housenumber":"20",
    "addr:postcode":"5100",
    "addr:street":"Avenue Baron De Lhoneux",
    "iso:country":"BE",
    "sg:address":"Avenue Baron De Lhoneux 20",
    "sg:city":"Namur (jambes)",
    "sg:classifiers":[
        {
            "category":"Utilities",
            "subcategory":"Telephone",
            "type":"Services"
        }
    ],
    "sg:phone":"+32 81 30 26 41",
    "sg:postcode":"5100",
    "sg:province":"Namur",
    "sg:tags":[
        "-",
        "internet"
    ],
    "wof:name":"Astronef",
    "wof:placetype":"venue"
},
  "geometry": {"coordinates":[4.8713750839,50.4566345215],"type":"Point"}
}