{
  "type": "Feature",
  "properties": {
    "addr:full":"Rue De Wand 172 Bruxelles Bruxelles-Capitale 1020",
    "addr:housenumber":"172",
    "addr:postcode":"1020",
    "addr:street":"Rue De Wand",
    "iso:country":"BE",
    "sg:address":"Rue De Wand 172",
    "sg:city":"Bruxelles",
    "sg:classifiers":[
        {
            "category":"Shopping",
            "subcategory":"Books",
            "type":"Retail Goods"
        }
    ],
    "sg:phone":"+32 2 268 61 45",
    "sg:postcode":"1020",
    "sg:province":"Bruxelles-Capitale",
    "sg:tags":[
        "bookseller"
    ],
    "wof:name":"Mutsaard (de)",
    "wof:placetype":"venue"
},
  "geometry": {"coordinates":[4.36043787,50.9011001587],"type":"Point"}
}