{
  "type": "Feature",
  "properties": {
    "addr:full":"Torhoutsesteenweg 78a Oostende West-Vlaanderen 8400",
    "addr:housenumber":"78a",
    "addr:postcode":"8400",
    "addr:street":"Torhoutsesteenweg",
    "iso:country":"BE",
    "sg:address":"Torhoutsesteenweg 78a",
    "sg:city":"Oostende",
    "sg:classifiers":[
        {
            "category":"Restaurant",
            "type":"Food & Drink"
        }
    ],
    "sg:phone":"+32 59 70 28 57",
    "sg:postcode":"8400",
    "sg:province":"West-Vlaanderen",
    "wof:name":"Petit Paris",
    "wof:placetype":"venue"
},
  "geometry": {"coordinates":[2.9091970921,51.2245330811],"type":"Point"}
}