{
  "type": "Feature",
  "properties": {
    "addr:full":"Rue Haute Bourlotte 13 Silly Hainaut 7830",
    "addr:housenumber":"13",
    "addr:postcode":"7830",
    "addr:street":"Rue Haute Bourlotte",
    "iso:country":"BE",
    "sg:address":"Rue Haute Bourlotte 13",
    "sg:city":"Silly",
    "sg:orig_category":"Installation \u00e9lectrique r\u00e9sidentielle",
    "sg:phone":"+32 2 395 80 61",
    "sg:postcode":"7830",
    "sg:province":"Hainaut",
    "wof:name":"Th. Verstappen",
    "wof:placetype":"venue"
},
  "geometry": {"coordinates":[4.058049202,50.6615638733],"type":"Point"}
}