{
  "type": "Feature",
  "properties": {
    "iso:country":"BE",
    "sg:address":"Kasteelstraat 4",
    "sg:city":"Avelgem",
    "sg:classifiers":[
        {
            "category":"Cafe",
            "type":"Food & Drink"
        }
    ],
    "sg:phone":"+32 56 64 48 80",
    "sg:postcode":"8580",
    "sg:province":"West-Vlaanderen",
    "sg:tags":[
        "caf\u00e9s"
    ],
    "wof:name":"Eveline Pauwels",
    "wof:placetype":"venue"
},
  "geometry": {"coordinates":[3.4477820396,50.7758178711],"type":"Point"}
}