{
  "type": "Feature",
  "properties": {
    "addr:full":"Veldonkbos 36 Tremelo Vlaams-Brabant 3120",
    "addr:housenumber":"36",
    "addr:postcode":"3120",
    "addr:street":"Veldonkbos",
    "iso:country":"BE",
    "sg:address":"Veldonkbos 36",
    "sg:city":"Tremelo",
    "sg:orig_category":"Imprimeries and copyshops",
    "sg:phone":"+32 16 52 00 14",
    "sg:postcode":"3120",
    "sg:province":"Vlaams-Brabant",
    "wof:name":"Art Graphicz",
    "wof:placetype":"venue"
},
  "geometry": {"coordinates":[4.7453122139,50.9855690002],"type":"Point"}
}