{
  "type": "Feature",
  "properties": {
    "iso:country":"BE",
    "sg:address":"Markt 5",
    "sg:city":"Kasterlee",
    "sg:orig_category":"Journaux. Tabac",
    "sg:phone":"+32 14 85 07 62",
    "sg:postcode":"2460",
    "sg:province":"Antwerpen",
    "wof:name":"Huis Otten",
    "wof:placetype":"venue"
},
  "geometry": {"coordinates":[4.9671821594,51.2407264709],"type":"Point"}
}