{
  "type": "Feature",
  "properties": {
    "iso:country":"BE",
    "sg:address":"Hoge Vosbergstraat 46",
    "sg:city":"Rumst",
    "sg:classifiers":[
        {
            "category":"Professional",
            "type":"Services"
        }
    ],
    "sg:phone":"+32 15 31 25 48",
    "sg:postcode":"2840",
    "sg:province":"Antwerpen",
    "sg:tags":[
        "surveyor",
        "-",
        "valuer"
    ],
    "wof:name":"Scan E & E",
    "wof:placetype":"venue"
},
  "geometry": {"coordinates":[4.459321022,51.0882148743],"type":"Point"}
}