{
  "type": "Feature",
  "properties": {
    "addr:full":"Meersstraat 63 Destelbergen (heusden) Oost-Vlaanderen 9070",
    "addr:housenumber":"63",
    "addr:postcode":"9070",
    "addr:street":"Meersstraat",
    "iso:country":"BE",
    "sg:address":"Meersstraat 63",
    "sg:city":"Destelbergen (heusden)",
    "sg:classifiers":[
        {
            "category":"Bars & Pubs",
            "type":"Food & Drink"
        }
    ],
    "sg:phone":"+32 9 230 68 49",
    "sg:postcode":"9070",
    "sg:province":"Oost-Vlaanderen",
    "wof:name":"Nog Nooit Gedacht",
    "wof:placetype":"venue"
},
  "geometry": {"coordinates":[3.7942590714,51.0400238037],"type":"Point"}
}