{
  "type": "Feature",
  "properties": {
    "addr:full":"Rue De La Meuse 6 Hasti\u00e8re (hasti\u00e8re-par-del\u00e0) Namur 5541",
    "addr:housenumber":"6",
    "addr:postcode":"5541",
    "addr:street":"Rue De La Meuse",
    "iso:country":"BE",
    "sg:address":"Rue De La Meuse 6",
    "sg:city":"Hasti\u00e8re (hasti\u00e8re-par-del\u00e0)",
    "sg:classifiers":[
        {
            "category":"Tea Room",
            "subcategory":"None",
            "type":"Food & Drink"
        }
    ],
    "sg:phone":"+32 82 64 49 63",
    "sg:postcode":"5541",
    "sg:province":"Namur",
    "wof:name":"Hastiere-plage",
    "wof:placetype":"venue"
},
  "geometry": {"coordinates":[4.827890873,50.215171814],"type":"Point"}
}