{
  "type": "Feature",
  "properties": {
    "iso:country":"BE",
    "sg:address":"Rue De L'energie 101",
    "sg:city":"Charleroi (marcinelle)",
    "sg:orig_category":"Non-Classified Establishments",
    "sg:phone":"+32 71 47 24 49",
    "sg:postcode":"6001",
    "sg:province":"Hainaut",
    "wof:name":"Di Lena G",
    "wof:placetype":"venue"
},
  "geometry": {"coordinates":[4.4491629601,50.3901672363],"type":"Point"}
}