{
  "type": "Feature",
  "properties": {
    "addr:full":"Lagesteenweg 10 Grimbergen Vlaams-Brabant 1850",
    "addr:housenumber":"10",
    "addr:postcode":"1850",
    "addr:street":"Lagesteenweg",
    "iso:country":"BE",
    "sg:address":"Lagesteenweg 10",
    "sg:city":"Grimbergen",
    "sg:classifiers":[
        {
            "category":"Personal",
            "subcategory":"Beauty Salon",
            "type":"Services"
        }
    ],
    "sg:phone":"+32 2 270 06 69",
    "sg:postcode":"1850",
    "sg:province":"Vlaams-Brabant",
    "sg:tags":[
        "lady",
        "-",
        "hairdressing"
    ],
    "wof:name":"Nathalie",
    "wof:placetype":"venue"
},
  "geometry": {"coordinates":[4.3698368073,50.9330673218],"type":"Point"}
}