{
  "type": "Feature",
  "properties": {
    "iso:country":"BE",
    "sg:address":"Zwevegemstraat 134",
    "sg:city":"Zwevegem (otegem)",
    "sg:classifiers":[
        {
            "category":"Home & Garden",
            "subcategory":"Garden Supply",
            "type":"Retail Goods"
        }
    ],
    "sg:phone":"+32 56 49 01 04",
    "sg:postcode":"8553",
    "sg:province":"West-Vlaanderen",
    "sg:tags":[
        "lawn",
        "mower"
    ],
    "wof:name":"Lietaer & Devos",
    "wof:placetype":"venue"
},
  "geometry": {"coordinates":[3.4005150795,50.8166732788],"type":"Point"}
}