{
  "type": "Feature",
  "properties": {
    "addr:full":"Rode Dreef 8 Wijnegem Antwerpen 2110",
    "addr:housenumber":"8",
    "addr:postcode":"2110",
    "addr:street":"Rode Dreef",
    "iso:country":"BE",
    "sg:address":"Rode Dreef 8",
    "sg:city":"Wijnegem",
    "sg:orig_category":"Architecten",
    "sg:phone":"+32 3 353 86 34",
    "sg:postcode":"2110",
    "sg:province":"Antwerpen",
    "wof:name":"Ingrid Lemmens",
    "wof:placetype":"venue"
},
  "geometry": {"coordinates":[4.5444560051,51.2266387939],"type":"Point"}
}