{
  "type": "Feature",
  "properties": {
    "addr:full":"Bruggestraat 271 Beernem (oedelem) West-Vlaanderen 8730",
    "addr:housenumber":"271",
    "addr:postcode":"8730",
    "addr:street":"Bruggestraat",
    "iso:country":"BE",
    "sg:address":"Bruggestraat 271",
    "sg:city":"Beernem (oedelem)",
    "sg:classifiers":[
        {
            "category":"Sports & Exercise",
            "subcategory":"Stables",
            "type":"Entertainment"
        }
    ],
    "sg:phone":"+32 50 35 60 18",
    "sg:postcode":"8730",
    "sg:province":"West-Vlaanderen",
    "sg:tags":[
        "riding",
        "school"
    ],
    "wof:name":"Yves Transport Nv",
    "wof:placetype":"venue"
},
  "geometry": {"coordinates":[3.2903270721,51.1870880127],"type":"Point"}
}