{
  "type": "Feature",
  "properties": {
    "addr:full":"Brabantdam 115 Gent Oost-Vlaanderen 9000",
    "addr:housenumber":"115",
    "addr:postcode":"9000",
    "addr:street":"Brabantdam;Oost-Vlaanderen",
    "iso:country":"BE",
    "sg:address":"Brabantdam 115",
    "sg:city":"Gent",
    "sg:classifiers":[
        {
            "category":"Deli",
            "type":"Food & Drink"
        }
    ],
    "sg:phone":"+32 9 225 21 59",
    "sg:postcode":"9000",
    "sg:province":"Oost-Vlaanderen",
    "sg:tags":[
        "delicatessen"
    ],
    "wof:name":"Primeur",
    "wof:placetype":"venue"
},
  "geometry": {"coordinates":[3.7314929962,51.0499191284],"type":"Point"}
}