{
  "type": "Feature",
  "properties": {
    "addr:full":"Gallaitstraat 12 Schaarbeek/schaerbeek Bruxelles-Capitale 1030",
    "addr:housenumber":"12",
    "addr:postcode":"1030",
    "addr:street":"Gallaitstraat",
    "iso:country":"BE",
    "sg:address":"Gallaitstraat 12",
    "sg:city":"Schaarbeek/schaerbeek",
    "sg:orig_category":"Industri\u00eble wasserijen and droogkuis",
    "sg:postcode":"1030",
    "sg:province":"Bruxelles-Capitale",
    "wof:name":"Ipsomat",
    "wof:placetype":"venue"
},
  "geometry": {"coordinates":[4.3672242165,50.8651161194],"type":"Point"}
}