{
  "type": "Feature",
  "properties": {
    "iso:country":"BE",
    "sg:address":"Rue Tombeux 16",
    "sg:city":"Donceel (haneffe)",
    "sg:classifiers":[
        {
            "category":"Home & Garden",
            "subcategory":"Garden Supply",
            "type":"Retail Goods"
        }
    ],
    "sg:phone":"+32 4 259 53 19",
    "sg:postcode":"4357",
    "sg:province":"Li\u00e8ge",
    "sg:tags":[
        "machine",
        "agricultural",
        "-"
    ],
    "wof:name":"Masset L Ets",
    "wof:placetype":"venue"
},
  "geometry": {"coordinates":[5.3224949837,50.6385879517],"type":"Point"}
}