{
  "type": "Feature",
  "properties": {
    "iso:country":"BE",
    "sg:address":"Ringlaan 10",
    "sg:city":"Melle",
    "sg:orig_category":"DIVERSE RECREATIEVE ACTIVITEITEN",
    "sg:phone":"+32 9 230 53 09",
    "sg:postcode":"9090",
    "sg:province":"Oost-Vlaanderen",
    "wof:name":"B.c. Wetthra",
    "wof:placetype":"venue"
},
  "geometry": {"coordinates":[3.7746369839,51.021484375],"type":"Point"}
}