{
  "type": "Feature",
  "properties": {
    "addr:full":"Kapellendries 58 Wetteren Oost-Vlaanderen 9230",
    "addr:housenumber":"58",
    "addr:postcode":"9230",
    "addr:street":"Kapellendries",
    "iso:country":"BE",
    "sg:address":"Kapellendries 58",
    "sg:city":"Wetteren",
    "sg:classifiers":[
        {
            "category":"Personal",
            "subcategory":"Beauty Salon",
            "type":"Services"
        }
    ],
    "sg:phone":"+32 9 368 00 91",
    "sg:postcode":"9230",
    "sg:province":"Oost-Vlaanderen",
    "sg:tags":[
        "lady",
        "-",
        "hairdressing"
    ],
    "wof:name":"Carine",
    "wof:placetype":"venue"
},
  "geometry": {"coordinates":[3.8818209171,51.0113525391],"type":"Point"}
}