{
  "type": "Feature",
  "properties": {
    "addr:full":"Bois Des Chevreuils 29 Esneux (tilff) Li\u00e8ge 4130",
    "addr:housenumber":"29",
    "addr:postcode":"4130",
    "addr:street":"Bois Des Chevreuils",
    "iso:country":"BE",
    "sg:address":"Bois Des Chevreuils 29",
    "sg:city":"Esneux (tilff)",
    "sg:classifiers":[
        {
            "category":"Professional",
            "subcategory":"Engineering",
            "type":"Services"
        }
    ],
    "sg:phone":"+32 4 368 55 47",
    "sg:postcode":"4130",
    "sg:province":"Li\u00e8ge",
    "sg:tags":[
        "-"
    ],
    "wof:name":"Boulanger (bureau D'etude) Sa",
    "wof:placetype":"venue"
},
  "geometry": {"coordinates":[5.6090087891,50.5640716553],"type":"Point"}
}