{
  "type": "Feature",
  "properties": {
    "iso:country":"BE",
    "sg:address":"Opitterpoort 1a",
    "sg:city":"Bree",
    "sg:classifiers":[
        {
            "category":"Communications",
            "subcategory":"Film & Video Production",
            "type":"Services"
        }
    ],
    "sg:phone":"+32 89 46 34 43",
    "sg:postcode":"3960",
    "sg:province":"Limburg",
    "sg:tags":[
        "hiring",
        "-"
    ],
    "wof:name":"Movie Station",
    "wof:placetype":"venue"
},
  "geometry": {"coordinates":[5.6015949249,51.1403923035],"type":"Point"}
}