{
  "type": "Feature",
  "properties": {
    "iso:country":"BE",
    "sg:address":"Rue Docteur De Meersman 6",
    "sg:city":"Bruxelles (anderlecht)",
    "sg:classifiers":[
        {
            "category":"Bars & Pubs",
            "type":"Food & Drink"
        }
    ],
    "sg:phone":"+32 2 527 45 40",
    "sg:postcode":"1070",
    "sg:province":"Bruxelles-Capitale",
    "wof:name":"Retiro (el)",
    "wof:placetype":"venue"
},
  "geometry": {"coordinates":[4.3350400925,50.8434066772],"type":"Point"}
}