{
  "type": "Feature",
  "properties": {
    "addr:full":"Parkstraat 15 Overpelt Limburg 3900",
    "addr:housenumber":"15",
    "addr:postcode":"3900",
    "addr:street":"Parkstraat",
    "iso:country":"BE",
    "sg:address":"Parkstraat 15",
    "sg:city":"Overpelt",
    "sg:orig_category":"Enseignement maternel and primaire",
    "sg:phone":"+32 11 64 17 34",
    "sg:postcode":"3900",
    "sg:province":"Limburg",
    "wof:name":"Vrije Basisschool",
    "wof:placetype":"venue"
},
  "geometry": {"coordinates":[5.4044780731,51.1936683655],"type":"Point"}
}