{
  "type": "Feature",
  "properties": {
    "iso:country":"BE",
    "sg:address":"Nieuwpoortlaan 9",
    "sg:city":"Middelkerke",
    "sg:orig_category":"Journaux. Tabac",
    "sg:phone":"+32 58 23 33 93",
    "sg:postcode":"8434",
    "sg:province":"West-Vlaanderen",
    "wof:name":"Luc Maertens",
    "wof:placetype":"venue"
},
  "geometry": {"coordinates":[2.7562561035,51.1480751038],"type":"Point"}
}