{
  "type": "Feature",
  "properties": {
    "addr:full":"Rue Ferrer 91 Charleroi (gosselies) Hainaut 6041",
    "addr:housenumber":"91",
    "addr:postcode":"6041",
    "addr:street":"Rue Ferrer",
    "iso:country":"BE",
    "sg:address":"Rue Ferrer 91",
    "sg:city":"Charleroi (gosselies)",
    "sg:classifiers":[
        {
            "category":"Shopping",
            "subcategory":"Pets & Pet Supplies",
            "type":"Retail Goods"
        }
    ],
    "sg:phone":"+32 71 35 07 58",
    "sg:postcode":"6041",
    "sg:province":"Hainaut",
    "sg:tags":[
        "shop",
        "-"
    ],
    "wof:name":"Poisson Dor\u00e9",
    "wof:placetype":"venue"
},
  "geometry": {"coordinates":[4.4082751274,50.4225273132],"type":"Point"}
}