{
  "type": "Feature",
  "properties": {
    "addr:full":"Assesteenweg 117-5b Ternat Vlaams-Brabant 1740",
    "addr:housenumber":"117-5b",
    "addr:postcode":"1740",
    "addr:street":"Assesteenweg",
    "iso:country":"BE",
    "sg:address":"Assesteenweg 117-5b",
    "sg:city":"Ternat",
    "sg:classifiers":[
        {
            "category":"Professional",
            "subcategory":"Detective & Security Services",
            "type":"Services"
        }
    ],
    "sg:phone":"+32 2 426 66 88",
    "sg:postcode":"1740",
    "sg:province":"Vlaams-Brabant",
    "sg:tags":[
        "installation",
        "alarm",
        "-",
        "system"
    ],
    "wof:name":"Rocket Security Systems",
    "wof:placetype":"venue"
},
  "geometry": {"coordinates":[4.1677031517,50.8755073547],"type":"Point"}
}