{
  "type": "Feature",
  "properties": {
    "iso:country":"BE",
    "sg:address":"Molenvest 13",
    "sg:city":"Herentals",
    "sg:classifiers":[
        {
            "category":"Communications",
            "type":"Services"
        }
    ],
    "sg:phone":"+32 14 50 79 40",
    "sg:postcode":"2200",
    "sg:province":"Antwerpen",
    "sg:tags":[
        "translator"
    ],
    "wof:name":"Dhaxley",
    "wof:placetype":"venue"
},
  "geometry": {"coordinates":[4.8309788704,51.1765785217],"type":"Point"}
}