{
  "type": "Feature",
  "properties": {
    "iso:country":"BE",
    "sg:address":"Valkstraat 23",
    "sg:city":"Peer",
    "sg:orig_category":"Artsen and specialisten",
    "sg:phone":"+32 11 63 73 37",
    "sg:postcode":"3990",
    "sg:province":"Limburg",
    "wof:name":"P. Thiry",
    "wof:placetype":"venue"
},
  "geometry": {"coordinates":[5.4564218521,51.1360740662],"type":"Point"}
}