{
  "type": "Feature",
  "properties": {
    "iso:country":"BE",
    "sg:address":"Heirbaan 3",
    "sg:city":"Kruibeke",
    "sg:orig_category":"Non-Classified Establishments",
    "sg:phone":"+32 3 252 70 13",
    "sg:postcode":"9150",
    "sg:province":"Oost-Vlaanderen",
    "wof:name":"B-line",
    "wof:placetype":"venue"
},
  "geometry": {"coordinates":[4.3027591705,51.1904335022],"type":"Point"}
}