{
  "type": "Feature",
  "properties": {
    "iso:country":"BE",
    "sg:address":"Keizerstraat 18b",
    "sg:city":"Mechelen",
    "sg:classifiers":[
        {
            "category":"Insurance",
            "subcategory":"Insurance Agent",
            "type":"Services"
        }
    ],
    "sg:phone":"+32 15 34 34 35",
    "sg:postcode":"2800",
    "sg:province":"Antwerpen",
    "sg:tags":[
        "broker"
    ],
    "wof:name":"Guy Peeters & Partners Bvba",
    "wof:placetype":"venue"
},
  "geometry": {"coordinates":[4.4861121178,51.0288047791],"type":"Point"}
}