{
  "type": "Feature",
  "properties": {
    "iso:country":"BE",
    "sg:address":"Pathoekeweg 41",
    "sg:city":"Brugge",
    "sg:classifiers":[
        {
            "category":"Government",
            "subcategory":"Post Office",
            "type":"Public Place"
        }
    ],
    "sg:phone":"+32 50 45 63 11",
    "sg:postcode":"8000",
    "sg:province":"West-Vlaanderen",
    "sg:tags":[
        "disposal",
        "recycling",
        "treatment",
        "analysis",
        "waste"
    ],
    "wof:name":"Intercommunale Vuilverwijdering & Verwerking Brugge C.v.b.a.",
    "wof:placetype":"venue"
},
  "geometry": {"coordinates":[3.2114799023,51.2524795532],"type":"Point"}
}