{
  "type": "Feature",
  "properties": {
    "addr:full":"Geelseweg 8 Herentals Antwerpen 2200",
    "addr:housenumber":"8",
    "addr:postcode":"2200",
    "addr:street":"Geelseweg",
    "iso:country":"BE",
    "sg:address":"Geelseweg 8",
    "sg:city":"Herentals",
    "sg:orig_category":"Autombile concessionaires",
    "sg:phone":"+32 14 28 68 28",
    "sg:postcode":"2200",
    "sg:province":"Antwerpen",
    "wof:name":"Gar Ennekens Bvba",
    "wof:placetype":"venue"
},
  "geometry": {"coordinates":[4.8501620293,51.1694030762],"type":"Point"}
}