{
  "type": "Feature",
  "properties": {
    "iso:country":"BE",
    "sg:address":"Bois Du Foyau 27",
    "sg:city":"Braine-le-ch\u00e2teau",
    "sg:classifiers":[
        {
            "category":"Health Services",
            "subcategory":"Medical Lab",
            "type":"Services"
        }
    ],
    "sg:phone":"+32 2 366 46 61",
    "sg:postcode":"1440",
    "sg:province":"Brabant Wallon",
    "sg:tags":[
        "laboratory",
        "dental"
    ],
    "wof:name":"Verhaeghe J",
    "wof:placetype":"venue"
},
  "geometry": {"coordinates":[4.2790131569,50.6708908081],"type":"Point"}
}