{
  "type": "Feature",
  "properties": {
    "addr:full":"Marktplein 12 Landen Vlaams-Brabant 3400",
    "addr:housenumber":"12",
    "addr:postcode":"3400",
    "addr:street":"Marktplein",
    "iso:country":"BE",
    "sg:address":"Marktplein 12",
    "sg:city":"Landen",
    "sg:classifiers":[
        {
            "category":"Bars & Pubs",
            "type":"Food & Drink"
        }
    ],
    "sg:phone":"+32 11 88 56 99",
    "sg:postcode":"3400",
    "sg:province":"Vlaams-Brabant",
    "sg:tags":[
        "tavern"
    ],
    "wof:name":"De Met",
    "wof:placetype":"venue"
},
  "geometry": {"coordinates":[5.0808668137,50.7529373169],"type":"Point"}
}