{
  "type": "Feature",
  "properties": {
    "iso:country":"BE",
    "sg:address":"Chazallaan 59",
    "sg:city":"Schaarbeek/schaerbeek",
    "sg:orig_category":"Medische apparatuur, orthopedische artikelen and prothesen Fab",
    "sg:phone":"+32 2 736 28 54",
    "sg:postcode":"1030",
    "sg:province":"Bruxelles-Capitale",
    "wof:name":"A. Schoonaert",
    "wof:placetype":"venue"
},
  "geometry": {"coordinates":[4.3893380165,50.8553466797],"type":"Point"}
}