{
  "type": "Feature",
  "properties": {
    "addr:full":"Leuken 40 Lommel Limburg 3920",
    "addr:housenumber":"40",
    "addr:postcode":"3920",
    "addr:street":"Leuken",
    "iso:country":"BE",
    "sg:address":"Leuken 40",
    "sg:city":"Lommel",
    "sg:orig_category":"Banques and organismes de cr\u00e9dit",
    "sg:phone":"+32 11 64 34 76",
    "sg:postcode":"3920",
    "sg:province":"Limburg",
    "wof:name":"Centea",
    "wof:placetype":"venue"
},
  "geometry": {"coordinates":[5.3679919243,51.2339859009],"type":"Point"}
}