{
  "type": "Feature",
  "properties": {
    "addr:full":"Schoolstraat 1 Hoeselt Limburg 3730",
    "addr:housenumber":"1",
    "addr:postcode":"3730",
    "addr:street":"Schoolstraat",
    "iso:country":"BE",
    "sg:address":"Schoolstraat 1",
    "sg:city":"Hoeselt",
    "sg:orig_category":"Enseignement maternel and primaire",
    "sg:phone":"+32 12 23 75 16",
    "sg:postcode":"3730",
    "sg:province":"Limburg",
    "wof:name":"Gemeentelijke Basisschool",
    "wof:placetype":"venue"
},
  "geometry": {"coordinates":[5.4900598526,50.8275604248],"type":"Point"}
}