{
  "type": "Feature",
  "properties": {
    "addr:full":"Scheepswerfstraat 15 Dendermonde Oost-Vlaanderen 9200",
    "addr:housenumber":"15",
    "addr:postcode":"9200",
    "addr:street":"Scheepswerfstraat;Oost-Vlaanderen",
    "iso:country":"BE",
    "sg:address":"Scheepswerfstraat 15",
    "sg:city":"Dendermonde",
    "sg:classifiers":[
        {
            "category":"Sports & Exercise",
            "subcategory":"Sports Center",
            "type":"Entertainment"
        }
    ],
    "sg:phone":"+32 475 68 31 60",
    "sg:postcode":"9200",
    "sg:province":"Oost-Vlaanderen",
    "sg:tags":[
        "club",
        "article",
        "de",
        "camping"
    ],
    "wof:name":"Aeros Padi Duikcentrum",
    "wof:placetype":"venue"
},
  "geometry": {"coordinates":[4.0983099937,51.0315208435],"type":"Point"}
}