{
  "type": "Feature",
  "properties": {
    "iso:country":"BE",
    "sg:address":"Rue D'arlon 5",
    "sg:city":"Messancy",
    "sg:classifiers":[
        {
            "category":"Health Services",
            "subcategory":"Health Practitioner",
            "type":"Services"
        }
    ],
    "sg:phone":"+32 496 21 04 56",
    "sg:postcode":"6780",
    "sg:province":"Luxembourg",
    "sg:tags":[
        "therapist",
        "speech"
    ],
    "wof:name":"Lambert Marie-france",
    "wof:placetype":"venue"
},
  "geometry": {"coordinates":[5.8129239082,49.5961532593],"type":"Point"}
}