{
  "type": "Feature",
  "properties": {
    "addr:full":"Stationsstraat 35a Haaltert Oost-Vlaanderen 9450",
    "addr:housenumber":"35a",
    "addr:postcode":"9450",
    "addr:street":"Stationsstraat",
    "iso:country":"BE",
    "sg:address":"Stationsstraat 35a",
    "sg:city":"Haaltert",
    "sg:classifiers":[
        {
            "category":"Shopping",
            "subcategory":"Optician",
            "type":"Retail Goods"
        }
    ],
    "sg:phone":"+32 53 83 05 69",
    "sg:postcode":"9450",
    "sg:province":"Oost-Vlaanderen",
    "sg:tags":[
        "-"
    ],
    "wof:name":"Van Pottelbergh A",
    "wof:placetype":"venue"
},
  "geometry": {"coordinates":[4.0099258423,50.9026145935],"type":"Point"}
}