{
  "type": "Feature",
  "properties": {
    "iso:country":"BE",
    "sg:address":"Rue Tourette 152",
    "sg:city":"Charleroi",
    "sg:classifiers":[
        {
            "category":"Professional",
            "subcategory":"Engineering",
            "type":"Services"
        }
    ],
    "sg:phone":"+32 71 30 44 72",
    "sg:postcode":"6000",
    "sg:province":"Hainaut",
    "sg:tags":[
        "-"
    ],
    "wof:name":"E.c.a.m. Sc",
    "wof:placetype":"venue"
},
  "geometry": {"coordinates":[4.4466600418,50.4236793518],"type":"Point"}
}