{
  "type": "Feature",
  "properties": {
    "iso:country":"BE",
    "sg:address":"Rue De Corbuha 11",
    "sg:city":"Chiny",
    "sg:orig_category":"Eleveurs de bovins",
    "sg:phone":"+32 61 31 26 87",
    "sg:postcode":"6810",
    "sg:province":"Luxembourg",
    "wof:name":"Rene Pierrard",
    "wof:placetype":"venue"
},
  "geometry": {"coordinates":[5.3408069611,49.7372589111],"type":"Point"}
}