{
  "type": "Feature",
  "properties": {
    "iso:country":"BE",
    "sg:address":"Beringsesteenweg 3",
    "sg:city":"Leopoldsburg",
    "sg:classifiers":[
        {
            "category":"Personal",
            "subcategory":"Beauty Salon",
            "type":"Services"
        }
    ],
    "sg:phone":"+32 11 34 29 46",
    "sg:postcode":"3971",
    "sg:province":"Limburg",
    "sg:tags":[
        "de",
        "coiffure"
    ],
    "wof:name":"Coiffure Jef",
    "wof:placetype":"venue"
},
  "geometry": {"coordinates":[5.2280840874,51.107711792],"type":"Point"}
}