{
  "type": "Feature",
  "properties": {
    "addr:full":"Chem Des Artisans 1 Mazy Namur 5032",
    "addr:housenumber":"1",
    "addr:postcode":"5032",
    "addr:street":"Mazy Namur",
    "iso:country":"BE",
    "sg:address":"Chem Des Artisans 1",
    "sg:city":"Mazy",
    "sg:classifiers":[
        {
            "category":"Health Services",
            "subcategory":"Health Practitioner",
            "type":"Services"
        }
    ],
    "sg:phone":"+32 496 10 31 99",
    "sg:postcode":"5032",
    "sg:province":"Namur",
    "sg:tags":[
        "physiotherapist"
    ],
    "wof:name":"Plovier Sybille",
    "wof:placetype":"venue"
},
  "geometry": {"coordinates":[4.738424778,50.5091285706],"type":"Point"}
}