{
  "type": "Feature",
  "properties": {
    "addr:full":"Archimedesstraat 50 Brussel/bruxelles Bruxelles-Capitale 1000",
    "addr:housenumber":"50",
    "addr:postcode":"1000",
    "addr:street":"Archimedesstraat;/",
    "iso:country":"BE",
    "sg:address":"Archimedesstraat 50",
    "sg:city":"Brussel/bruxelles",
    "sg:classifiers":[
        {
            "category":"Restaurant",
            "type":"Food & Drink"
        }
    ],
    "sg:phone":"+32 2 230 70 47",
    "sg:postcode":"1000",
    "sg:province":"Bruxelles-Capitale",
    "sg:tags":[
        "organisatie",
        "feesten",
        "van",
        "catering"
    ],
    "wof:name":"Restaurant Dal Padrino",
    "wof:placetype":"venue"
},
  "geometry": {"coordinates":[4.383482933,50.8456039429],"type":"Point"}
}