{
  "type": "Feature",
  "properties": {
    "addr:full":"Antwerpsesteenweg 270 Kapellen Antwerpen 2950",
    "addr:housenumber":"270",
    "addr:postcode":"2950",
    "addr:street":"Antwerpsesteenweg",
    "iso:country":"BE",
    "sg:address":"Antwerpsesteenweg 270",
    "sg:city":"Kapellen",
    "sg:classifiers":[
        {
            "category":"Health Services",
            "subcategory":"Health Practitioner",
            "type":"Services"
        }
    ],
    "sg:phone":"+32 3 605 59 69",
    "sg:postcode":"2950",
    "sg:province":"Antwerpen",
    "sg:tags":[
        "physiotherapist"
    ],
    "wof:name":"Ickx P",
    "wof:placetype":"venue"
},
  "geometry": {"coordinates":[4.4367852211,51.3020362854],"type":"Point"}
}