{
  "type": "Feature",
  "properties": {
    "iso:country":"BE",
    "sg:address":"Markekerkstraat 13",
    "sg:city":"Kortrijk (marke)",
    "sg:classifiers":[
        {
            "category":"Insurance",
            "subcategory":"Insurance Agent",
            "type":"Services"
        }
    ],
    "sg:phone":"+32 56 24 90 25",
    "sg:postcode":"8510",
    "sg:province":"West-Vlaanderen",
    "sg:tags":[
        "broker"
    ],
    "wof:name":"Verzekeringen Ouvrein Nv",
    "wof:placetype":"venue"
},
  "geometry": {"coordinates":[3.2327079773,50.8072395325],"type":"Point"}
}