{
  "type": "Feature",
  "properties": {
    "addr:full":"Zoutwerf 5 Mechelen Antwerpen 2800",
    "addr:housenumber":"5",
    "addr:postcode":"2800",
    "addr:street":"Zoutwerf",
    "iso:country":"BE",
    "sg:address":"Zoutwerf 5",
    "sg:city":"Mechelen",
    "sg:classifiers":[
        {
            "category":"Arts & Performance",
            "subcategory":"Symphony",
            "type":"Entertainment"
        }
    ],
    "sg:phone":"+32 15 71 59 01",
    "sg:postcode":"2800",
    "sg:province":"Antwerpen",
    "sg:tags":[
        "orchestra"
    ],
    "wof:name":"Beethoven Academie Cvba",
    "wof:placetype":"venue"
},
  "geometry": {"coordinates":[4.4782028198,51.0255508423],"type":"Point"}
}