{
  "type": "Feature",
  "properties": {
    "iso:country":"BE",
    "sg:address":"Van Immerseelstraat 29-33",
    "sg:city":"Antwerpen",
    "sg:classifiers":[
        {
            "category":"Education",
            "subcategory":"School",
            "type":"Public Place"
        }
    ],
    "sg:phone":"+32 3 232 11 33",
    "sg:postcode":"2018",
    "sg:province":"Antwerpen",
    "sg:tags":[
        "primary"
    ],
    "wof:name":"Benoth Jeruzalem",
    "wof:placetype":"venue"
},
  "geometry": {"coordinates":[4.4233260155,51.2122039795],"type":"Point"}
}