{
  "type": "Feature",
  "properties": {
    "addr:full":"Noorderlaan 78 Antwerpen Antwerpen 2030",
    "addr:housenumber":"78",
    "addr:postcode":"2030",
    "addr:street":"Noorderlaan",
    "iso:country":"BE",
    "sg:address":"Noorderlaan 78",
    "sg:city":"Antwerpen",
    "sg:classifiers":[
        {
            "category":"Wholesale",
            "subcategory":"Machinery & Supplies",
            "type":"Manufacturing & Wholesale Goods"
        }
    ],
    "sg:phone":"+32 3 542 46 35",
    "sg:postcode":"2030",
    "sg:province":"Antwerpen",
    "sg:tags":[
        "equipment",
        "ship"
    ],
    "wof:name":"Odijk's Handelsmaatschappij Nv",
    "wof:placetype":"venue"
},
  "geometry": {"coordinates":[4.4209651947,51.2421455383],"type":"Point"}
}