{
  "type": "Feature",
  "properties": {
    "iso:country":"BE",
    "sg:address":"Rue D'harvengt 4",
    "sg:city":"Mons",
    "sg:orig_category":"Installatie van houten of kunststof schrijnwerk",
    "sg:phone":"+32 65 58 67 77",
    "sg:postcode":"7022",
    "sg:province":"Hainaut",
    "wof:name":"Marcel Wilmart",
    "wof:placetype":"venue"
},
  "geometry": {"coordinates":[4.0135121346,50.4074668884],"type":"Point"}
}