{
  "type": "Feature",
  "properties": {
    "addr:full":"Sint-bernardusstraat 4 Lier Antwerpen 2500",
    "addr:housenumber":"4",
    "addr:postcode":"2500",
    "addr:street":"Sint-Bernardusstraat",
    "iso:country":"BE",
    "sg:address":"Sint-bernardusstraat 4",
    "sg:city":"Lier",
    "sg:classifiers":[
        {
            "category":"Juice Bar",
            "subcategory":"None",
            "type":"Food & Drink"
        }
    ],
    "sg:phone":"+32 3 480 51 55",
    "sg:postcode":"2500",
    "sg:province":"Antwerpen",
    "sg:tags":[
        "water",
        "soft"
    ],
    "wof:name":"Bogaerts / Boco Drinks",
    "wof:placetype":"venue"
},
  "geometry": {"coordinates":[4.5741839409,51.1463508606],"type":"Point"}
}