{
  "type": "Feature",
  "properties": {
    "addr:full":"Rue De La Mirande 13b Houyet Namur 5561",
    "addr:housenumber":"13b",
    "addr:postcode":"5561",
    "addr:street":"Rue De La Mirande",
    "iso:country":"BE",
    "sg:address":"Rue De La Mirande 13b",
    "sg:city":"Houyet",
    "sg:orig_category":"Fitnesscentra Sportclubs Sportterreinen and installaties behalve sportcentra",
    "sg:phone":"+32 82 66 79 80",
    "sg:postcode":"5561",
    "sg:province":"Namur",
    "wof:name":"Club Doroth\u00c9e",
    "wof:placetype":"venue"
},
  "geometry": {"coordinates":[5.0096502304,50.229221344],"type":"Point"}
}