{
  "type": "Feature",
  "properties": {
    "iso:country":"BE",
    "sg:address":"Paardenmarktstraat 147",
    "sg:city":"Tervuren",
    "sg:orig_category":"Slagers",
    "sg:phone":"+32 2 767 90 44",
    "sg:postcode":"3080",
    "sg:province":"Vlaams-Brabant",
    "wof:name":"Beenhouwerij Eddy",
    "wof:placetype":"venue"
},
  "geometry": {"coordinates":[4.5061898232,50.8193664551],"type":"Point"}
}