{
  "type": "Feature",
  "properties": {
    "iso:country":"BE",
    "sg:address":"Rue De La Station 69",
    "sg:city":"Mouscron",
    "sg:classifiers":[
        {
            "category":"Professional",
            "subcategory":"Lawyer & Legal Services",
            "type":"Services"
        }
    ],
    "sg:phone":"+32 56 33 49 75",
    "sg:postcode":"7700",
    "sg:province":"Hainaut",
    "wof:name":"Gerbovits L",
    "wof:placetype":"venue"
},
  "geometry": {"coordinates":[3.2215080261,50.7436256409],"type":"Point"}
}