{
  "type": "Feature",
  "properties": {
    "iso:country":"BE",
    "sg:address":"Rue De La Roche Fatale 49",
    "sg:city":"Brussel",
    "sg:orig_category":"Woningbouw",
    "sg:phone":"+32 2 772 78 03",
    "sg:postcode":"1200",
    "sg:province":"Bruxelles-Capitale",
    "wof:name":"Eurostani",
    "wof:placetype":"venue"
},
  "geometry": {"coordinates":[4.4194149971,50.8438873291],"type":"Point"}
}