{
  "type": "Feature",
  "properties": {
    "iso:country":"BE",
    "sg:address":"R. Jean-georges-scholtus 12",
    "sg:city":"Bastogne",
    "sg:orig_category":"Artiesten and kunstenaars",
    "sg:phone":"+32 61 21 42 82",
    "sg:postcode":"6600",
    "sg:province":"Luxembourg",
    "wof:name":"M.l. Mertz",
    "wof:placetype":"venue"
},
  "geometry": {"coordinates":[5.7065858841,50.0044822693],"type":"Point"}
}