{
  "type": "Feature",
  "properties": {
    "addr:full":"Rue Des Foss\u00e9s 36 Virton Luxembourg 6760",
    "addr:housenumber":"36",
    "addr:postcode":"6760",
    "addr:street":"Rue Des Fosse\u0301S",
    "iso:country":"BE",
    "sg:address":"Rue Des Foss\u00e9s 36",
    "sg:city":"Virton",
    "sg:classifiers":[
        {
            "category":"Home & Garden",
            "subcategory":"Building Materials",
            "type":"Retail Goods"
        }
    ],
    "sg:phone":"+32 63 57 07 61",
    "sg:postcode":"6760",
    "sg:province":"Luxembourg",
    "sg:tags":[
        "wall",
        "cupboard"
    ],
    "wof:name":"Nulle Part Ailleurs",
    "wof:placetype":"venue"
},
  "geometry": {"coordinates":[5.5341272354,49.566947937],"type":"Point"}
}