{
  "type": "Feature",
  "properties": {
    "iso:country":"BE",
    "sg:address":"Koolmijnlaan 210",
    "sg:city":"Heusden-zolder",
    "sg:orig_category":"Loodgieterij, verwarming and sanitaire installaties",
    "sg:phone":"+32 11 57 15 42",
    "sg:postcode":"3550",
    "sg:province":"Limburg",
    "wof:name":"Rakiy Jilali",
    "wof:placetype":"venue"
},
  "geometry": {"coordinates":[5.3135170937,51.0414276123],"type":"Point"}
}