{
  "type": "Feature",
  "properties": {
    "addr:full":"Wolvertemsesteenweg 198 Merchtem Vlaams-Brabant 1785",
    "addr:housenumber":"198",
    "addr:postcode":"1785",
    "addr:street":"Wolvertemsesteenweg",
    "iso:country":"BE",
    "sg:address":"Wolvertemsesteenweg 198",
    "sg:city":"Merchtem",
    "sg:classifiers":[
        {
            "category":"Building & Trades",
            "subcategory":"Landscaping Services",
            "type":"Services"
        }
    ],
    "sg:phone":"+32 52 37 66 94",
    "sg:postcode":"1785",
    "sg:province":"Vlaams-Brabant",
    "sg:tags":[
        "gardening",
        "garden",
        "maintenance"
    ],
    "wof:name":"De Cock",
    "wof:placetype":"venue"
},
  "geometry": {"coordinates":[4.2612080574,50.9534912109],"type":"Point"}
}