{
  "type": "Feature",
  "properties": {
    "iso:country":"BE",
    "sg:address":"Chemin Du Haut-neubois 7",
    "sg:city":"Spa",
    "sg:classifiers":[
        {
            "category":"Building & Trades",
            "subcategory":"Pest Control",
            "type":"Services"
        }
    ],
    "sg:phone":"+32 87 77 48 68",
    "sg:postcode":"4900",
    "sg:province":"Li\u00e8ge",
    "sg:tags":[
        "painting",
        "contractor"
    ],
    "wof:name":"Hendrick E",
    "wof:placetype":"venue"
},
  "geometry": {"coordinates":[5.8987350464,50.4879798889],"type":"Point"}
}