{
  "type": "Feature",
  "properties": {
    "iso:country":"BE",
    "sg:address":"Verbrand Nieuwland 67",
    "sg:city":"Brugge",
    "sg:classifiers":[
        {
            "category":"Real Estate",
            "subcategory":"Architect",
            "type":"Services"
        }
    ],
    "sg:phone":"+32 50 33 09 86",
    "sg:postcode":"8000",
    "sg:province":"West-Vlaanderen",
    "wof:name":"Delaey B",
    "wof:placetype":"venue"
},
  "geometry": {"coordinates":[3.2349839211,51.2110824585],"type":"Point"}
}