{
  "type": "Feature",
  "properties": {
    "addr:full":"Koolskampstraat 24 Pittem West-Vlaanderen 8740",
    "addr:housenumber":"24",
    "addr:postcode":"8740",
    "addr:street":"Koolskampstraat",
    "iso:country":"BE",
    "sg:address":"Koolskampstraat 24",
    "sg:city":"Pittem",
    "sg:orig_category":"Decoratieve kunst and kunstbenodigdheden Plaatsen van vloer- and muurbekleding Schilders",
    "sg:phone":"+32 51 46 69 93",
    "sg:postcode":"8740",
    "sg:province":"West-Vlaanderen",
    "wof:name":"Publi Lettral",
    "wof:placetype":"venue"
},
  "geometry": {"coordinates":[3.2590909004,50.9950332642],"type":"Point"}
}