{
  "type": "Feature",
  "properties": {
    "addr:full":"Brugstraat 115 Brecht (sint-job-in-'t Goor) Antwerpen 2960",
    "addr:housenumber":"115",
    "addr:postcode":"2960",
    "addr:street":"Brugstraat;' T Goor",
    "iso:country":"BE",
    "sg:address":"Brugstraat 115",
    "sg:city":"Brecht (sint-job-in-'t Goor)",
    "sg:classifiers":[
        {
            "category":"Retail",
            "subcategory":"Auto Repair",
            "type":"Services"
        }
    ],
    "sg:phone":"+32 3 636 01 50",
    "sg:postcode":"2960",
    "sg:province":"Antwerpen",
    "sg:tags":[
        "breakdown",
        "automobile",
        "-",
        "recovery"
    ],
    "wof:name":"Roger & Zoon",
    "wof:placetype":"venue"
},
  "geometry": {"coordinates":[4.5730037689,51.2980537415],"type":"Point"}
}