{
  "type": "Feature",
  "properties": {
    "addr:full":"Fritz Vinckelaan 2 Bredene West-Vlaanderen 8450",
    "addr:housenumber":"2",
    "addr:postcode":"8450",
    "addr:street":"Vinckelaan",
    "iso:country":"BE",
    "sg:address":"Fritz Vinckelaan 2",
    "sg:city":"Bredene",
    "sg:classifiers":[
        {
            "category":"Communications",
            "subcategory":"Film & Video Production",
            "type":"Services"
        }
    ],
    "sg:phone":"+32 59 33 17 67",
    "sg:postcode":"8450",
    "sg:province":"West-Vlaanderen",
    "sg:tags":[
        "multimedia",
        "-",
        "system"
    ],
    "wof:name":"Compu-coast Bvba",
    "wof:placetype":"venue"
},
  "geometry": {"coordinates":[2.9617359638,51.224105835],"type":"Point"}
}