{
  "type": "Feature",
  "properties": {
    "addr:full":"Frankrijklaan 46 Bredene West-Vlaanderen 8450",
    "addr:housenumber":"46",
    "addr:postcode":"8450",
    "addr:street":"Frankrijklaan",
    "iso:country":"BE",
    "sg:address":"Frankrijklaan 46",
    "sg:city":"Bredene",
    "sg:classifiers":[
        {
            "category":"Government",
            "subcategory":"Post Office",
            "type":"Public Place"
        }
    ],
    "sg:phone":"+32 59 32 35 27",
    "sg:postcode":"8450",
    "sg:province":"West-Vlaanderen",
    "sg:tags":[
        "stamp"
    ],
    "wof:name":"Deplacie W",
    "wof:placetype":"venue"
},
  "geometry": {"coordinates":[2.9570128918,51.2430763245],"type":"Point"}
}