{
  "type": "Feature",
  "properties": {
    "iso:country":"BE",
    "sg:address":"Brugstraat 30",
    "sg:city":"Stekene",
    "sg:orig_category":"Solariums",
    "sg:phone":"+32 3 779 67 88",
    "sg:postcode":"9190",
    "sg:province":"Oost-Vlaanderen",
    "wof:name":"Nicky",
    "wof:placetype":"venue"
},
  "geometry": {"coordinates":[4.0343570709,51.2012672424],"type":"Point"}
}