{
  "type": "Feature",
  "properties": {
    "iso:country":"BE",
    "sg:address":"Rue 't Serclaes De Tilly 3",
    "sg:city":"Charleroi (montignies-sur-sambre)",
    "sg:classifiers":[
        {
            "category":"Insurance",
            "subcategory":"Insurance Agent",
            "type":"Services"
        }
    ],
    "sg:phone":"+32 71 31 46 27",
    "sg:postcode":"6061",
    "sg:province":"Hainaut",
    "sg:tags":[
        "broker"
    ],
    "wof:name":"Losseau John Assur",
    "wof:placetype":"venue"
},
  "geometry": {"coordinates":[4.4556407928,50.4068603516],"type":"Point"}
}