{
  "type": "Feature",
  "properties": {
    "iso:country":"BE",
    "sg:address":"Nederkouter 42",
    "sg:city":"Gent",
    "sg:classifiers":[
        {
            "category":"Cafe",
            "type":"Food & Drink"
        }
    ],
    "sg:phone":"+32 9 269 07 69",
    "sg:postcode":"9000",
    "sg:province":"Oost-Vlaanderen",
    "sg:tags":[
        "snack-bars"
    ],
    "wof:name":"Greenway Foods",
    "wof:placetype":"venue"
},
  "geometry": {"coordinates":[3.7216789722,51.0475120544],"type":"Point"}
}