{
  "type": "Feature",
  "properties": {
    "iso:country":"BE",
    "sg:address":"Vlindersstraat 26",
    "sg:city":"Hasselt",
    "sg:classifiers":[
        {
            "category":"Real Estate",
            "subcategory":"Architect",
            "type":"Services"
        }
    ],
    "sg:phone":"+32 11 24 27 55",
    "sg:postcode":"3500",
    "sg:province":"Limburg",
    "wof:name":"Smeuninx H",
    "wof:placetype":"venue"
},
  "geometry": {"coordinates":[5.3506197929,50.9308509827],"type":"Point"}
}