{
  "type": "Feature",
  "properties": {
    "iso:country":"BE",
    "sg:address":"Rue Des Foss\u00e9s Fleuris 43",
    "sg:city":"Namur",
    "sg:classifiers":[
        {
            "category":"Military Area",
            "subcategory":"Air Force Base",
            "type":"Public Place"
        }
    ],
    "sg:phone":"+32 81 22 75 67",
    "sg:postcode":"5000",
    "sg:province":"Namur",
    "sg:tags":[
        "herb",
        "-",
        "medicinal"
    ],
    "wof:name":"Alba Sc-la Maison Des Plantes Sprl",
    "wof:placetype":"venue"
},
  "geometry": {"coordinates":[4.8641791344,50.4623260498],"type":"Point"}
}