{
  "type": "Feature",
  "properties": {
    "addr:full":"Rue Mattot 83 Waterloo Brabant Wallon 1410",
    "addr:housenumber":"83",
    "addr:postcode":"1410",
    "addr:street":"Rue Mattot",
    "iso:country":"BE",
    "sg:address":"Rue Mattot 83",
    "sg:city":"Waterloo",
    "sg:classifiers":[
        {
            "category":"Building & Trades",
            "subcategory":"Landscaping Services",
            "type":"Services"
        }
    ],
    "sg:phone":"+32 2 353 05 44",
    "sg:postcode":"1410",
    "sg:province":"Brabant Wallon",
    "sg:tags":[
        "handicraft"
    ],
    "wof:name":"Youngner Pottery",
    "wof:placetype":"venue"
},
  "geometry": {"coordinates":[4.3791370392,50.7114524841],"type":"Point"}
}