{
  "type": "Feature",
  "properties": {
    "addr:full":"Kruisstraat 169-171 Tremelo Vlaams-Brabant 3120",
    "addr:housenumber":"169-171",
    "addr:postcode":"3120",
    "addr:street":"Kruisstraat",
    "iso:country":"BE",
    "sg:address":"Kruisstraat 169-171",
    "sg:city":"Tremelo",
    "sg:orig_category":"Imprimeries and copyshops. Services fun\u00e9raires",
    "sg:phone":"+32 16 53 21 76",
    "sg:postcode":"3120",
    "sg:province":"Vlaams-Brabant",
    "wof:name":"Begrafenissen Eraly",
    "wof:placetype":"venue"
},
  "geometry": {"coordinates":[4.6921000481,50.994758606],"type":"Point"}
}