{
  "type": "Feature",
  "properties": {
    "addr:full":"Woluwedal 24 Zaventem Vlaams-Brabant 1932",
    "addr:housenumber":"24",
    "addr:postcode":"1932",
    "addr:street":"Woluwedal",
    "iso:country":"BE",
    "sg:address":"Woluwedal 24",
    "sg:city":"Zaventem",
    "sg:classifiers":[
        {
            "category":"Parking",
            "subcategory":"Garage",
            "type":"Transportation"
        }
    ],
    "sg:phone":"+32 3 570 52 11",
    "sg:postcode":"1932",
    "sg:province":"Vlaams-Brabant",
    "sg:tags":[
        "polypropylene",
        "pp"
    ],
    "wof:name":"Borealis Kallo Nv",
    "wof:placetype":"venue"
},
  "geometry": {"coordinates":[-94.1347808838,42.4365272522],"type":"Point"}
}