{
  "type": "Feature",
  "properties": {
    "iso:country":"BE",
    "sg:address":"Bruegelhof 8",
    "sg:city":"Lennik (sint-kwintens-lennik)",
    "sg:classifiers":[
        {
            "category":"Building & Trades",
            "subcategory":"Plumbing",
            "type":"Services"
        }
    ],
    "sg:phone":"+32 2 532 50 68",
    "sg:postcode":"1750",
    "sg:province":"Vlaams-Brabant",
    "sg:tags":[
        "repair",
        "mainten",
        "-",
        "central",
        "heating"
    ],
    "wof:name":"Warrand A",
    "wof:placetype":"venue"
},
  "geometry": {"coordinates":[4.1591129303,50.8027267456],"type":"Point"}
}