{
  "type": "Feature",
  "properties": {
    "addr:full":"Oscar Verschuerestraat 55 Waregem West-Vlaanderen 8790",
    "addr:housenumber":"55",
    "addr:postcode":"8790",
    "addr:street":"Verschuerestraat",
    "iso:country":"BE",
    "sg:address":"Oscar Verschuerestraat 55",
    "sg:city":"Waregem",
    "sg:classifiers":[
        {
            "category":"Wholesale",
            "subcategory":"Medical Equipment & Supplies",
            "type":"Manufacturing & Wholesale Goods"
        }
    ],
    "sg:phone":"+32 56 61 55 75",
    "sg:postcode":"8790",
    "sg:province":"West-Vlaanderen",
    "sg:tags":[
        "aid",
        "hearing"
    ],
    "wof:name":"Hoorcentrum Auris",
    "wof:placetype":"venue"
},
  "geometry": {"coordinates":[3.4285891056,50.8859138489],"type":"Point"}
}