{
  "type": "Feature",
  "properties": {
    "addr:full":"Schurhovenveld 3220 Sint-truiden Limburg 3800",
    "addr:postcode":"3220;3800",
    "addr:street":"Schurhovenveld",
    "iso:country":"BE",
    "sg:address":"Schurhovenveld 3220",
    "sg:city":"Sint-truiden",
    "sg:classifiers":[
        {
            "category":"Home & Garden",
            "subcategory":"Furniture",
            "type":"Retail Goods"
        }
    ],
    "sg:phone":"+32 11 68 96 68",
    "sg:postcode":"3800",
    "sg:province":"Limburg",
    "sg:tags":[
        "bathroom"
    ],
    "wof:name":"Assenti B.v.b.a.",
    "wof:placetype":"venue"
},
  "geometry": {"coordinates":[5.1863641739,50.8153343201],"type":"Point"}
}