{
  "type": "Feature",
  "properties": {
    "iso:country":"BE",
    "sg:address":"Rue Hennequin 3",
    "sg:city":"Li\u00c8ge",
    "sg:orig_category":"Salles de spectacles",
    "sg:phone":"+32 4 227 74 04",
    "sg:postcode":"4000",
    "sg:province":"Li\u00e8ge",
    "wof:name":"Campagnie Du Parking",
    "wof:placetype":"venue"
},
  "geometry": {"coordinates":[5.594836235,50.6584472656],"type":"Point"}
}