{
  "type": "Feature",
  "properties": {
    "addr:full":"Bernard Hamelinckstraat 20 Gent (drongen) Oost-Vlaanderen 9031",
    "addr:housenumber":"20",
    "addr:postcode":"9031",
    "addr:street":"Hamelinckstraat",
    "iso:country":"BE",
    "sg:address":"Bernard Hamelinckstraat 20",
    "sg:city":"Gent (drongen)",
    "sg:classifiers":[
        {
            "category":"Professional",
            "subcategory":"Engineering",
            "type":"Services"
        }
    ],
    "sg:phone":"+32 9 226 16 18",
    "sg:postcode":"9031",
    "sg:province":"Oost-Vlaanderen",
    "sg:tags":[
        "environmental",
        "technique",
        "-"
    ],
    "wof:name":"Aqua Ph Industries Bvba",
    "wof:placetype":"venue"
},
  "geometry": {"coordinates":[3.6374819279,51.0679206848],"type":"Point"}
}