{
  "type": "Feature",
  "properties": {
    "addr:full":"Rue Du Ch\u00eanois 182 Charleroi (lodelinsart) Hainaut 6042",
    "addr:housenumber":"182",
    "addr:postcode":"6042",
    "addr:street":"Rue Du Che\u0302Nois",
    "iso:country":"BE",
    "sg:address":"Rue Du Ch\u00eanois 182",
    "sg:city":"Charleroi (lodelinsart)",
    "sg:classifiers":[
        {
            "category":"Freight",
            "type":"Transportation"
        }
    ],
    "sg:phone":"+32 71 50 65 55",
    "sg:postcode":"6042",
    "sg:province":"Hainaut",
    "sg:tags":[
        "-",
        "transport"
    ],
    "wof:name":"Duchesne Transport",
    "wof:placetype":"venue"
},
  "geometry": {"coordinates":[4.4441328049,50.4260902405],"type":"Point"}
}