{
  "type": "Feature",
  "properties": {
    "iso:country":"BE",
    "sg:address":"Avenue De La Gare 3",
    "sg:city":"Aubange",
    "sg:orig_category":"Pharmaciens",
    "sg:phone":"+32 63 37 10 39",
    "sg:postcode":"6790",
    "sg:province":"Luxembourg",
    "wof:name":"Pharmalorraine",
    "wof:placetype":"venue"
},
  "geometry": {"coordinates":[5.8032398224,49.5674247742],"type":"Point"}
}