{
  "type": "Feature",
  "properties": {
    "addr:full":"Nieuwstraat 12 Asse Vlaams-Brabant 1730",
    "addr:housenumber":"12",
    "addr:postcode":"1730",
    "addr:street":"Nieuwstraat",
    "iso:country":"BE",
    "sg:address":"Nieuwstraat 12",
    "sg:city":"Asse",
    "sg:orig_category":"Medische and orthopedische apparaten Opticiens",
    "sg:phone":"+32 2 452 65 55",
    "sg:postcode":"1730",
    "sg:province":"Vlaams-Brabant",
    "wof:name":"Optiek Heyvaert",
    "wof:placetype":"venue"
},
  "geometry": {"coordinates":[4.1959319115,50.9114723206],"type":"Point"}
}