{
  "type": "Feature",
  "properties": {
    "addr:full":"Blaesstraat 174 Brussel/bruxelles Bruxelles-Capitale 1000",
    "addr:housenumber":"174",
    "addr:postcode":"1000",
    "addr:street":"Blaesstraat;/",
    "iso:country":"BE",
    "sg:address":"Blaesstraat 174",
    "sg:city":"Brussel/bruxelles",
    "sg:orig_category":"Decoratieve kunst and kunstbenodigdheden",
    "sg:phone":"+32 2 513 22 63",
    "sg:postcode":"1000",
    "sg:province":"Bruxelles-Capitale",
    "wof:name":"Galerie Du Vieux March\u00c9",
    "wof:placetype":"venue"
},
  "geometry": {"coordinates":[4.3456301689,50.8362541199],"type":"Point"}
}