{
  "type": "Feature",
  "properties": {
    "addr:full":"Rue Bois L'ev\u00eaque 2 Andenne (nam\u00eache) Namur 5300",
    "addr:housenumber":"2",
    "addr:postcode":"5300",
    "addr:street":"Rue Bois L'Eve \u0302Que",
    "iso:country":"BE",
    "sg:address":"Rue Bois L'ev\u00eaque 2",
    "sg:city":"Andenne (nam\u00eache)",
    "sg:classifiers":[
        {
            "category":"Retail",
            "subcategory":"Auto Repair",
            "type":"Services"
        }
    ],
    "sg:phone":"+32 81 58 17 06",
    "sg:postcode":"5300",
    "sg:province":"Namur",
    "sg:tags":[
        "garage"
    ],
    "wof:name":"De Luca",
    "wof:placetype":"venue"
},
  "geometry": {"coordinates":[4.9975528717,50.4716873169],"type":"Point"}
}