{
  "type": "Feature",
  "properties": {
    "addr:full":"Warmestraat 32a Maldegem Oost-Vlaanderen 9990",
    "addr:housenumber":"32a",
    "addr:postcode":"9990",
    "addr:street":"Warmestraat",
    "iso:country":"BE",
    "sg:address":"Warmestraat 32a",
    "sg:city":"Maldegem",
    "sg:classifiers":[
        {
            "category":"Home & Garden",
            "subcategory":"Carpets & Floor Coverings",
            "type":"Retail Goods"
        }
    ],
    "sg:phone":"+32 50 71 10 64",
    "sg:postcode":"9990",
    "sg:province":"Oost-Vlaanderen",
    "sg:tags":[
        "parquet"
    ],
    "wof:name":"Van De Keere Bvba",
    "wof:placetype":"venue"
},
  "geometry": {"coordinates":[3.4723219872,51.2151374817],"type":"Point"}
}