{
  "type": "Feature",
  "properties": {
    "addr:full":"Oostnieuwkerkesteenweg 116-120 Roeselare West-Vlaanderen 8800",
    "addr:housenumber":"116-120",
    "addr:postcode":"8800",
    "addr:street":"Oostnieuwkerkesteenweg",
    "iso:country":"BE",
    "sg:address":"Oostnieuwkerkesteenweg 116-120",
    "sg:city":"Roeselare",
    "sg:classifiers":[
        {
            "category":"Manufacturing",
            "subcategory":"Metals",
            "type":"Manufacturing & Wholesale Goods"
        }
    ],
    "sg:phone":"+32 51 24 14 08",
    "sg:postcode":"8800",
    "sg:province":"West-Vlaanderen",
    "sg:tags":[
        "metallurgy",
        "steel",
        "metalworking"
    ],
    "wof:name":"Vuylsteke Gebroeders Nv",
    "wof:placetype":"venue"
},
  "geometry": {"coordinates":[3.0996599197,50.9469413757],"type":"Point"}
}