{
  "type": "Feature",
  "properties": {
    "addr:full":"Rue Foss\u00c9 Au Loups 11 Brussel Bruxelles-Capitale 1000",
    "addr:housenumber":"11",
    "addr:postcode":"1000",
    "addr:street":"Rue Fosse\u0301 Au Loups",
    "iso:country":"BE",
    "sg:address":"Rue Foss\u00c9 Au Loups 11",
    "sg:city":"Brussel",
    "sg:classifiers":[
        {
            "category":"Fast Food",
            "type":"Food & Drink"
        }
    ],
    "sg:phone":"+32 2 219 15 68",
    "sg:postcode":"1000",
    "sg:province":"Bruxelles-Capitale",
    "sg:tags":[
        "\u00c0",
        "restaurants",
        "emporter",
        "restaurant"
    ],
    "wof:name":"Le Tassilli",
    "wof:placetype":"venue"
},
  "geometry": {"coordinates":[4.3541760445,50.8502464294],"type":"Point"}
}