{
  "type": "Feature",
  "properties": {
    "iso:country":"BE",
    "sg:address":"Dikkebusseweg 516",
    "sg:city":"Ieper (dikkebus)",
    "sg:classifiers":[
        {
            "category":"Bakery",
            "type":"Food & Drink"
        }
    ],
    "sg:phone":"+32 57 36 03 91",
    "sg:postcode":"8900",
    "sg:province":"West-Vlaanderen",
    "sg:tags":[
        "confectioner",
        "baker"
    ],
    "wof:name":"De Rederijker",
    "wof:placetype":"venue"
},
  "geometry": {"coordinates":[2.8651199341,50.8389701843],"type":"Point"}
}