{
  "type": "Feature",
  "properties": {
    "iso:country":"BE",
    "sg:address":"Hannekenshoek 9",
    "sg:city":"Herentals",
    "sg:classifiers":[
        {
            "category":"Utilities",
            "subcategory":"Recycling",
            "type":"Services"
        }
    ],
    "sg:phone":"+32 14 21 21 18",
    "sg:postcode":"2200",
    "sg:province":"Antwerpen",
    "wof:name":"Andries",
    "wof:placetype":"venue"
},
  "geometry": {"coordinates":[4.8351988792,51.1681404114],"type":"Point"}
}