{
  "type": "Feature",
  "properties": {
    "iso:country":"BE",
    "sg:address":"Rue Grande 5",
    "sg:city":"Mons (maisi\u00e8res)",
    "sg:classifiers":[
        {
            "category":"Building & Trades",
            "subcategory":"Cleaning & Sanitation",
            "type":"Services"
        }
    ],
    "sg:phone":"+32 65 33 41 36",
    "sg:postcode":"7020",
    "sg:province":"Hainaut",
    "sg:tags":[
        "sweep",
        "chimney"
    ],
    "wof:name":"Marmich S",
    "wof:placetype":"venue"
},
  "geometry": {"coordinates":[3.9553449154,50.4761772156],"type":"Point"}
}