{
  "type": "Feature",
  "properties": {
    "addr:full":"Bree\u00ebrsteenweg 336 Kinrooi Limburg 3640",
    "addr:housenumber":"336",
    "addr:postcode":"3640",
    "addr:street":"Breee\u0308Rsteenweg",
    "iso:country":"BE",
    "sg:address":"Bree\u00ebrsteenweg 336",
    "sg:city":"Kinrooi",
    "sg:classifiers":[
        {
            "category":"Retail",
            "subcategory":"Auto Repair",
            "type":"Services"
        }
    ],
    "sg:phone":"+32 89 70 25 10",
    "sg:postcode":"3640",
    "sg:province":"Limburg",
    "sg:tags":[
        "lpg",
        "automobile",
        "-",
        "system"
    ],
    "wof:name":"Jacobs B Garage",
    "wof:placetype":"venue"
},
  "geometry": {"coordinates":[5.7324528694,51.145778656],"type":"Point"}
}