{
  "type": "Feature",
  "properties": {
    "addr:full":"Fabriekstraat 15 Brasschaat Antwerpen 2930",
    "addr:housenumber":"15",
    "addr:postcode":"2930",
    "addr:street":"Fabriekstraat",
    "iso:country":"BE",
    "sg:address":"Fabriekstraat 15",
    "sg:city":"Brasschaat",
    "sg:classifiers":[
        {
            "category":"Building & Trades",
            "subcategory":"Landscaping Services",
            "type":"Services"
        }
    ],
    "sg:phone":"+32 3 605 13 56",
    "sg:postcode":"2930",
    "sg:province":"Antwerpen",
    "sg:tags":[
        "gardening",
        "garden",
        "maintenance"
    ],
    "wof:name":"Verbist J",
    "wof:placetype":"venue"
},
  "geometry": {"coordinates":[4.4571537971,51.3006706238],"type":"Point"}
}