{
  "type": "Feature",
  "properties": {
    "iso:country":"BE",
    "sg:address":"Moderne-schoolstraat 13",
    "sg:city":"Anderlecht",
    "sg:orig_category":"Bagage and lederwaren Bagage and lederwaren Fab",
    "sg:phone":"+32 2 522 92 39",
    "sg:postcode":"1070",
    "sg:province":"Bruxelles-Capitale",
    "wof:name":"Sacelux-nosac",
    "wof:placetype":"venue"
},
  "geometry": {"coordinates":[4.3259959221,50.8368186951],"type":"Point"}
}