{
  "type": "Feature",
  "properties": {
    "addr:full":"Joseph Brandstraat 108 Schaarbeek/schaerbeek Bruxelles-Capitale 1030",
    "addr:housenumber":"108",
    "addr:postcode":"1030",
    "addr:street":"Joseph Brandstraat",
    "iso:country":"BE",
    "sg:address":"Joseph Brandstraat 108",
    "sg:city":"Schaarbeek/schaerbeek",
    "sg:orig_category":"Advocaten and juridische adviseurs",
    "sg:phone":"+32 2 242 37 67",
    "sg:postcode":"1030",
    "sg:province":"Bruxelles-Capitale",
    "wof:name":"Fabienne Vanderplaetsen",
    "wof:placetype":"venue"
},
  "geometry": {"coordinates":[4.3769130707,50.8649559021],"type":"Point"}
}