{
  "type": "Feature",
  "properties": {
    "addr:full":"Vollezelestraat 22 Gooik (oetingen) Vlaams-Brabant 1755",
    "addr:housenumber":"22",
    "addr:postcode":"1755",
    "addr:street":"Vollezelestraat",
    "iso:country":"BE",
    "sg:address":"Vollezelestraat 22",
    "sg:city":"Gooik (oetingen)",
    "sg:classifiers":[
        {
            "category":"Professional",
            "subcategory":"Lawyer & Legal Services",
            "type":"Services"
        }
    ],
    "sg:phone":"+32 54 56 60 60",
    "sg:postcode":"1755",
    "sg:province":"Vlaams-Brabant",
    "wof:name":"Fran\u00e7ois B",
    "wof:placetype":"venue"
},
  "geometry": {"coordinates":[4.0591931343,50.7725486755],"type":"Point"}
}