{
  "type": "Feature",
  "properties": {
    "addr:full":"Nieuwe Molenstraat 180 Sint-niklaas Oost-Vlaanderen 9100",
    "addr:housenumber":"180",
    "addr:postcode":"9100",
    "addr:street":"Nieuwe Molenstraat",
    "iso:country":"BE",
    "sg:address":"Nieuwe Molenstraat 180",
    "sg:city":"Sint-niklaas",
    "sg:classifiers":[
        {
            "category":"Professional",
            "subcategory":"Management & Consulting",
            "type":"Services"
        }
    ],
    "sg:phone":"+32 3 766 60 36",
    "sg:postcode":"9100",
    "sg:province":"Oost-Vlaanderen",
    "sg:tags":[
        "consultant"
    ],
    "wof:name":"Raebema Bvba",
    "wof:placetype":"venue"
},
  "geometry": {"coordinates":[4.1586079597,51.1723556519],"type":"Point"}
}