{
  "type": "Feature",
  "properties": {
    "iso:country":"BE",
    "sg:address":"Dubbeekstraat 44",
    "sg:city":"Aarschot",
    "sg:orig_category":"Groententeelt",
    "sg:phone":"+32 16 56 08 88",
    "sg:postcode":"3200",
    "sg:province":"Vlaams-Brabant",
    "wof:name":"Desire Van De Gaer",
    "wof:placetype":"venue"
},
  "geometry": {"coordinates":[4.8392601013,50.9741172791],"type":"Point"}
}