{
  "type": "Feature",
  "properties": {
    "iso:country":"BE",
    "sg:address":"Lindeveldstraat 30",
    "sg:city":"Geraardsbergen (zandbergen)",
    "sg:classifiers":[
        {
            "category":"Bars & Pubs",
            "type":"Food & Drink"
        }
    ],
    "sg:phone":"+32 54 33 54 75",
    "sg:postcode":"9506",
    "sg:province":"Oost-Vlaanderen",
    "wof:name":"Eldorado",
    "wof:placetype":"venue"
},
  "geometry": {"coordinates":[3.9595599174,50.791885376],"type":"Point"}
}