{
  "type": "Feature",
  "properties": {
    "addr:full":"Place Emile Dupont 10 Li\u00c8ge Li\u00e8ge 4000",
    "addr:housenumber":"10",
    "addr:postcode":"4000",
    "addr:street":"Place Emile Dupont",
    "iso:country":"BE",
    "sg:address":"Place Emile Dupont 10",
    "sg:city":"Li\u00c8ge",
    "sg:classifiers":[
        {
            "category":"Shopping Center",
            "type":"Public Place"
        }
    ],
    "sg:phone":"+32 4 223 51 23",
    "sg:postcode":"4000",
    "sg:province":"Li\u00e8ge",
    "sg:tags":[
        "enseignement",
        "formation"
    ],
    "wof:name":"Acad\u00c9mie Des Langues",
    "wof:placetype":"venue"
},
  "geometry": {"coordinates":[5.5708880424,50.6363830566],"type":"Point"}
}