{
  "type": "Feature",
  "properties": {
    "iso:country":"BE",
    "sg:address":"Hopmarkt 3 Box 13",
    "sg:city":"Aalst",
    "sg:classifiers":[
        {
            "category":"Professional",
            "subcategory":"Accounting & Tax Preparation",
            "type":"Services"
        }
    ],
    "sg:phone":"+32 53 21 69 49",
    "sg:postcode":"9300",
    "sg:province":"Oost-Vlaanderen",
    "sg:tags":[
        "bookkeeper"
    ],
    "wof:name":"Opdecam G",
    "wof:placetype":"venue"
},
  "geometry": {"coordinates":[4.0376348495,50.938079834],"type":"Point"}
}