{
  "type": "Feature",
  "properties": {
    "iso:country":"BE",
    "sg:address":"Den Elst 46",
    "sg:city":"Herent",
    "sg:classifiers":[
        {
            "category":"Building & Trades",
            "subcategory":"Construction",
            "type":"Services"
        }
    ],
    "sg:phone":"+32 16 22 86 37",
    "sg:postcode":"3020",
    "sg:province":"Vlaams-Brabant",
    "sg:tags":[
        "stucco",
        "contractor"
    ],
    "wof:name":"Van Campenhout",
    "wof:placetype":"venue"
},
  "geometry": {"coordinates":[4.6672048569,50.9218482971],"type":"Point"}
}