{
  "type": "Feature",
  "properties": {
    "iso:country":"BE",
    "sg:address":"Krickelstein 9",
    "sg:city":"Kelmis",
    "sg:classifiers":[
        {
            "category":"Professional",
            "subcategory":"Accounting & Tax Preparation",
            "type":"Services"
        }
    ],
    "sg:phone":"+32 87 65 79 80",
    "sg:postcode":"4720",
    "sg:province":"Li\u00e8ge",
    "sg:tags":[
        "bookkeeper"
    ],
    "wof:name":"Bonni S",
    "wof:placetype":"venue"
},
  "geometry": {"coordinates":[6.0036392212,50.7098960876],"type":"Point"}
}