{
  "type": "Feature",
  "properties": {
    "addr:full":"Marathonstraat 2 Gent Oost-Vlaanderen 9000",
    "addr:housenumber":"2",
    "addr:postcode":"9000",
    "addr:street":"Marathonstraat;Oost-Vlaanderen",
    "iso:country":"BE",
    "sg:address":"Marathonstraat 2",
    "sg:city":"Gent",
    "sg:orig_category":"Diverse bedrijfsbeheeradviesbureaus",
    "sg:phone":"+32 9 221 41 27",
    "sg:postcode":"9000",
    "sg:province":"Oost-Vlaanderen",
    "wof:name":"Andr\u00c9 Veo",
    "wof:placetype":"venue"
},
  "geometry": {"coordinates":[3.6970388889,51.0426902771],"type":"Point"}
}