{
  "type": "Feature",
  "properties": {
    "addr:full":"Olmenstraat 25 Oostkamp West-Vlaanderen 8020",
    "addr:housenumber":"25",
    "addr:postcode":"8020",
    "addr:street":"Olmenstraat",
    "iso:country":"BE",
    "sg:address":"Olmenstraat 25",
    "sg:city":"Oostkamp",
    "sg:orig_category":"Sportclubs Sportterreinen and installaties behalve sportcentra",
    "sg:phone":"+32 50 35 57 76",
    "sg:postcode":"8020",
    "sg:province":"West-Vlaanderen",
    "wof:name":"K.s.k. Steenbrugge",
    "wof:placetype":"venue"
},
  "geometry": {"coordinates":[3.2425611019,51.1784362793],"type":"Point"}
}