{
  "type": "Feature",
  "properties": {
    "addr:full":"Gabriellestraat 63 Ukkel/uccle Bruxelles-Capitale 1180",
    "addr:housenumber":"63",
    "addr:postcode":"1180",
    "addr:street":"Gabriellestraat;/",
    "iso:country":"BE",
    "sg:address":"Gabriellestraat 63",
    "sg:city":"Ukkel/uccle",
    "sg:orig_category":"Artiesten and kunstenaars",
    "sg:phone":"+32 2 344 56 53",
    "sg:postcode":"1180",
    "sg:province":"Bruxelles-Capitale",
    "wof:name":"R. Grand Jean",
    "wof:placetype":"venue"
},
  "geometry": {"coordinates":[4.359539032,50.8135452271],"type":"Point"}
}