{
  "type": "Feature",
  "properties": {
    "iso:country":"BE",
    "sg:address":"Guido Gezellelaan 25",
    "sg:city":"Bonheiden",
    "sg:classifiers":[
        {
            "category":"Wholesale",
            "subcategory":"Beer",
            "type":"Manufacturing & Wholesale Goods"
        }
    ],
    "sg:phone":"+32 15 33 15 08",
    "sg:postcode":"2820",
    "sg:province":"Antwerpen",
    "sg:tags":[
        "ale",
        "-"
    ],
    "wof:name":"Verhoeven F Bvba",
    "wof:placetype":"venue"
},
  "geometry": {"coordinates":[4.5505948067,51.0211715698],"type":"Point"}
}