{
  "type": "Feature",
  "properties": {
    "addr:full":"Hoflandstraat 2 Lo-reninge West-Vlaanderen 8647",
    "addr:housenumber":"2",
    "addr:postcode":"8647",
    "addr:street":"Hoflandstraat",
    "iso:country":"BE",
    "sg:address":"Hoflandstraat 2",
    "sg:city":"Lo-reninge",
    "sg:orig_category":"Schoonheidssalons",
    "sg:phone":"+32 57 40 05 71",
    "sg:postcode":"8647",
    "sg:province":"West-Vlaanderen",
    "wof:name":"Pedicure Catherine",
    "wof:placetype":"venue"
},
  "geometry": {"coordinates":[2.7781729698,50.9400901794],"type":"Point"}
}