{
  "type": "Feature",
  "properties": {
    "iso:country":"BE",
    "sg:address":"Avenue Du Onze Novembre 29",
    "sg:city":"Bruxelles (etterbeek)",
    "sg:classifiers":[
        {
            "category":"Professional",
            "subcategory":"Business Services",
            "type":"Services"
        }
    ],
    "sg:phone":"+32 2 732 50 75",
    "sg:postcode":"1040",
    "sg:province":"Bruxelles-Capitale",
    "sg:tags":[
        "automobile",
        "-",
        "assessor"
    ],
    "wof:name":"Stainier M Sprl",
    "wof:placetype":"venue"
},
  "geometry": {"coordinates":[4.3939890862,50.8327941895],"type":"Point"}
}