{
  "type": "Feature",
  "properties": {
    "addr:full":"Kroonwinningstraat 127 Hasselt Limburg 3500",
    "addr:housenumber":"127",
    "addr:postcode":"3500",
    "addr:street":"Kroonwinningstraat",
    "iso:country":"BE",
    "sg:address":"Kroonwinningstraat 127",
    "sg:city":"Hasselt",
    "sg:orig_category":"Artsen and specialisten",
    "sg:phone":"+32 11 27 48 87",
    "sg:postcode":"3500",
    "sg:province":"Limburg",
    "wof:name":"Geert Van Loo",
    "wof:placetype":"venue"
},
  "geometry": {"coordinates":[5.3588972092,50.9166259766],"type":"Point"}
}