{
  "type": "Feature",
  "properties": {
    "iso:country":"BE",
    "sg:address":"Hooghaag 5",
    "sg:city":"Hamont-achel",
    "sg:orig_category":"Schoonheidssalons",
    "sg:phone":"+32 11 64 33 90",
    "sg:postcode":"3930",
    "sg:province":"Limburg",
    "wof:name":"Instituut Silcare",
    "wof:placetype":"venue"
},
  "geometry": {"coordinates":[5.4751691818,51.249004364],"type":"Point"}
}