{
  "type": "Feature",
  "properties": {
    "addr:full":"Sint-antoniusstraat 45 Oud-turnhout Antwerpen 2360",
    "addr:housenumber":"45",
    "addr:postcode":"2360",
    "addr:street":"Sint-Antoniusstraat",
    "iso:country":"BE",
    "sg:address":"Sint-antoniusstraat 45",
    "sg:city":"Oud-turnhout",
    "sg:classifiers":[
        {
            "category":"Personal",
            "subcategory":"Nail Salon",
            "type":"Services"
        }
    ],
    "sg:phone":"+32 14 43 99 48",
    "sg:postcode":"2360",
    "sg:province":"Antwerpen",
    "sg:tags":[
        "pedicure"
    ],
    "wof:name":"Goossens B",
    "wof:placetype":"venue"
},
  "geometry": {"coordinates":[4.973982811,51.3404922485],"type":"Point"}
}