{
  "type": "Feature",
  "properties": {
    "iso:country":"BE",
    "sg:address":"Rue Olivier Gille 62",
    "sg:city":"Chatelet",
    "sg:orig_category":"Plaatsen van vloer- and muurbekleding Schilders",
    "sg:phone":"+32 71 38 31 36",
    "sg:postcode":"6200",
    "sg:province":"Hainaut",
    "wof:name":"Claude Renard",
    "wof:placetype":"venue"
},
  "geometry": {"coordinates":[4.533217907,50.4014282227],"type":"Point"}
}