{
  "type": "Feature",
  "properties": {
    "addr:full":"Balgerhoekstraat 65 Wingene West-Vlaanderen 8750",
    "addr:housenumber":"65",
    "addr:postcode":"8750",
    "addr:street":"Balgerhoekstraat",
    "iso:country":"BE",
    "sg:address":"Balgerhoekstraat 65",
    "sg:city":"Wingene",
    "sg:classifiers":[
        {
            "category":"Parking",
            "subcategory":"Garage",
            "type":"Transportation"
        }
    ],
    "sg:phone":"+32 51 65 58 93",
    "sg:postcode":"8750",
    "sg:province":"West-Vlaanderen",
    "sg:tags":[
        "truck",
        "-",
        "dump",
        "transport"
    ],
    "wof:name":"Anntrans Cv",
    "wof:placetype":"venue"
},
  "geometry": {"coordinates":[3.3201301098,51.0658111572],"type":"Point"}
}