{
  "type": "Feature",
  "properties": {
    "addr:full":"Rue De La Bruy\u00c8re 215 Rixensart Brabant Wallon 1332",
    "addr:housenumber":"215",
    "addr:postcode":"1332",
    "addr:street":"Rue De La Bruye\u0300Re;Wallon",
    "iso:country":"BE",
    "sg:address":"Rue De La Bruy\u00c8re 215",
    "sg:city":"Rixensart",
    "sg:orig_category":"Epiceries. Grands magasins. Supermarch\u00e9s",
    "sg:phone":"+32 2 653 63 68",
    "sg:postcode":"1332",
    "sg:province":"Brabant Wallon",
    "wof:name":"Gb Contact",
    "wof:placetype":"venue"
},
  "geometry": {"coordinates":[4.4866280556,50.7265892029],"type":"Point"}
}