{
  "type": "Feature",
  "properties": {
    "addr:full":"Combrue 2 Celles (pottes) Hainaut 7760",
    "addr:housenumber":"2",
    "addr:postcode":"7760",
    "addr:street":"Combrue",
    "iso:country":"BE",
    "sg:address":"Combrue 2",
    "sg:city":"Celles (pottes)",
    "sg:classifiers":[
        {
            "category":"Real Estate",
            "subcategory":"Architect",
            "type":"Services"
        }
    ],
    "sg:phone":"+32 69 45 43 58",
    "sg:postcode":"7760",
    "sg:province":"Hainaut",
    "wof:name":"Dorange Ph",
    "wof:placetype":"venue"
},
  "geometry": {"coordinates":[3.4128890038,50.7317390442],"type":"Point"}
}