{
  "type": "Feature",
  "properties": {
    "addr:full":"Westlaan 159 Roeselare West-Vlaanderen 8800",
    "addr:housenumber":"159",
    "addr:postcode":"8800",
    "addr:street":"Westlaan",
    "iso:country":"BE",
    "sg:address":"Westlaan 159",
    "sg:city":"Roeselare",
    "sg:orig_category":"Diverse zakelijke dienstverlening Public-relationsbureaus",
    "sg:phone":"+32 51 24 88 48",
    "sg:postcode":"8800",
    "sg:province":"West-Vlaanderen",
    "wof:name":"Twice Entertainment",
    "wof:placetype":"venue"
},
  "geometry": {"coordinates":[3.1143100262,50.9420013428],"type":"Point"}
}