{
  "type": "Feature",
  "properties": {
    "iso:country":"BE",
    "sg:address":"Charles De Kerchovelaan 193",
    "sg:city":"Gent",
    "sg:classifiers":[
        {
            "category":"Professional",
            "subcategory":"Business Services",
            "type":"Services"
        }
    ],
    "sg:phone":"+32 9 245 28 08",
    "sg:postcode":"9000",
    "sg:province":"Oost-Vlaanderen",
    "sg:tags":[
        "aux",
        "diver",
        "entreprises"
    ],
    "wof:name":"New Center Immo",
    "wof:placetype":"venue"
},
  "geometry": {"coordinates":[3.7235760689,51.0398139954],"type":"Point"}
}