{
  "type": "Feature",
  "properties": {
    "addr:full":"Fortlaan 77 Gent Oost-Vlaanderen 9000",
    "addr:housenumber":"77",
    "addr:postcode":"9000",
    "addr:street":"Fortlaan;Oost-Vlaanderen",
    "iso:country":"BE",
    "sg:address":"Fortlaan 77",
    "sg:city":"Gent",
    "sg:classifiers":[
        {
            "category":"Health Services",
            "subcategory":"Doctor",
            "type":"Services"
        }
    ],
    "sg:phone":"+32 9 222 61 99",
    "sg:postcode":"9000",
    "sg:province":"Oost-Vlaanderen",
    "sg:tags":[
        "medicinephysicians",
        "surgeon"
    ],
    "wof:name":"Cornelis Jean",
    "wof:placetype":"venue"
},
  "geometry": {"coordinates":[3.7182750702,51.0354385376],"type":"Point"}
}