{
  "type": "Feature",
  "properties": {
    "iso:country":"BE",
    "sg:address":"Place H\u00d4tel De Ville 15",
    "sg:city":"Wavre",
    "sg:orig_category":"Avocats and conseillers juridiques",
    "sg:phone":"+32 10 24 45 45",
    "sg:postcode":"1300",
    "sg:province":"Brabant Wallon",
    "wof:name":"Emmanuelle Delvaux",
    "wof:placetype":"venue"
},
  "geometry": {"coordinates":[4.6084318161,50.7160720825],"type":"Point"}
}