{
  "type": "Feature",
  "properties": {
    "addr:full":"Brechtsebaan 22 Schoten Antwerpen 2900",
    "addr:housenumber":"22",
    "addr:postcode":"2900",
    "addr:street":"Brechtsebaan",
    "iso:country":"BE",
    "sg:address":"Brechtsebaan 22",
    "sg:city":"Schoten",
    "sg:classifiers":[
        {
            "category":"Building & Trades",
            "subcategory":"Construction",
            "type":"Services"
        }
    ],
    "sg:phone":"+32 3 680 12 23",
    "sg:postcode":"2900",
    "sg:province":"Antwerpen",
    "sg:tags":[
        "cloakroom",
        "installation",
        "-"
    ],
    "wof:name":"Blika-koppen",
    "wof:placetype":"venue"
},
  "geometry": {"coordinates":[4.5107097626,51.2652397156],"type":"Point"}
}