{
  "type": "Feature",
  "properties": {
    "addr:full":"Industriepark Schoorstraat 7-9 Maaseik Limburg 3680",
    "addr:housenumber":"7-9",
    "addr:postcode":"3680",
    "addr:street":"Industriepark Schoorstraat",
    "iso:country":"BE",
    "sg:address":"Industriepark Schoorstraat 7-9",
    "sg:city":"Maaseik",
    "sg:classifiers":[
        {
            "category":"Manufacturing",
            "subcategory":"Paper Products",
            "type":"Manufacturing & Wholesale Goods"
        }
    ],
    "sg:phone":"+32 89 56 85 56",
    "sg:postcode":"3680",
    "sg:province":"Limburg",
    "sg:tags":[
        "wool",
        "item",
        "made",
        "cardboard",
        "holiday",
        "easter",
        "christmas"
    ],
    "wof:name":"Wimmers-hermans Nv",
    "wof:placetype":"venue"
},
  "geometry": {"coordinates":[5.750620842,51.1053886414],"type":"Point"}
}