{
  "type": "Feature",
  "properties": {
    "addr:full":"Baudelostraat 15 Gent Oost-Vlaanderen 9000",
    "addr:housenumber":"15",
    "addr:postcode":"9000",
    "addr:street":"Baudelostraat;Oost-Vlaanderen",
    "iso:country":"BE",
    "sg:address":"Baudelostraat 15",
    "sg:city":"Gent",
    "sg:classifiers":[
        {
            "category":"Shopping",
            "subcategory":"Clothing, Apparel, & Fashions",
            "type":"Retail Goods"
        }
    ],
    "sg:phone":"+32 9 233 23 11",
    "sg:postcode":"9000",
    "sg:province":"Oost-Vlaanderen",
    "sg:tags":[
        "boutique"
    ],
    "wof:name":"Alternatief Boetiek",
    "wof:placetype":"venue"
},
  "geometry": {"coordinates":[3.7262630463,51.0576629639],"type":"Point"}
}