{
  "type": "Feature",
  "properties": {
    "addr:full":"Avenue De Broqueville 15 Bruxelles (woluwe-saint-lambert) Bruxelles-Capitale 1200",
    "addr:housenumber":"15",
    "addr:postcode":"1200",
    "addr:street":"Avenue De Broqueville",
    "iso:country":"BE",
    "sg:address":"Avenue De Broqueville 15",
    "sg:city":"Bruxelles (woluwe-saint-lambert)",
    "sg:classifiers":[
        {
            "category":"Health Services",
            "subcategory":"Health Practitioner",
            "type":"Services"
        }
    ],
    "sg:phone":"+32 2 734 37 58",
    "sg:postcode":"1200",
    "sg:province":"Bruxelles-Capitale",
    "sg:tags":[
        "physiotherapist"
    ],
    "wof:name":"Leroy Martine",
    "wof:placetype":"venue"
},
  "geometry": {"coordinates":[4.4102339745,50.8387641907],"type":"Point"}
}