{
  "type": "Feature",
  "properties": {
    "iso:country":"BE",
    "sg:address":"Rue Du D\u00c9barcad\u00c8re 61",
    "sg:city":"Charleroi",
    "sg:orig_category":"Installatie van houten of kunststof schrijnwerk SMEEDWERK, METAALBEWERKING AND POEDERMETALLURGIE",
    "sg:phone":"+32 71 36 00 15",
    "sg:postcode":"6001",
    "sg:province":"Hainaut",
    "wof:name":"Atelier Social Metalgroup",
    "wof:placetype":"venue"
},
  "geometry": {"coordinates":[4.4366297722,50.3767318726],"type":"Point"}
}