{
  "type": "Feature",
  "properties": {
    "iso:country":"BE",
    "sg:address":"Spoorweglaan 29",
    "sg:city":"Sint-niklaas",
    "sg:orig_category":"Maatkleding Fab",
    "sg:phone":"+32 3 766 24 70",
    "sg:postcode":"9100",
    "sg:province":"Oost-Vlaanderen",
    "wof:name":"Gina Tondat",
    "wof:placetype":"venue"
},
  "geometry": {"coordinates":[4.1353449821,51.1686706543],"type":"Point"}
}