{
  "type": "Feature",
  "properties": {
    "addr:full":"Place Des Martyrs 18a Charleroi (jumet) Hainaut 6040",
    "addr:housenumber":"18a",
    "addr:postcode":"6040",
    "addr:street":"Place Des Martyrs",
    "iso:country":"BE",
    "sg:address":"Place Des Martyrs 18a",
    "sg:city":"Charleroi (jumet)",
    "sg:classifiers":[
        {
            "category":"Home & Garden",
            "subcategory":"Hardware",
            "type":"Retail Goods"
        }
    ],
    "sg:postcode":"6040",
    "sg:province":"Hainaut",
    "sg:tags":[
        "nut",
        "bolt"
    ],
    "wof:name":"Hamos Holland Bv",
    "wof:placetype":"venue"
},
  "geometry": {"coordinates":[4.7726049423,51.8235549927],"type":"Point"}
}