{
  "type": "Feature",
  "properties": {
    "iso:country":"BE",
    "sg:address":"Rue Pierre 53",
    "sg:city":"Tournai",
    "sg:classifiers":[
        {
            "category":"Cafe",
            "type":"Food & Drink"
        }
    ],
    "sg:phone":"+32 69 21 28 79",
    "sg:postcode":"7540",
    "sg:province":"Hainaut",
    "sg:tags":[
        "caf\u00e9s"
    ],
    "wof:name":"Gilette Dubois",
    "wof:placetype":"venue"
},
  "geometry": {"coordinates":[3.388010025,50.6226921082],"type":"Point"}
}