{
  "type": "Feature",
  "properties": {
    "iso:country":"BE",
    "sg:address":"Roterijstraat 46",
    "sg:city":"Kuurne",
    "sg:orig_category":"Charpentes and couvertures",
    "sg:phone":"+32 56 35 14 31",
    "sg:postcode":"8520",
    "sg:province":"West-Vlaanderen",
    "wof:name":"Depreeuw",
    "wof:placetype":"venue"
},
  "geometry": {"coordinates":[3.2801148891,50.8446960449],"type":"Point"}
}