{
  "type": "Feature",
  "properties": {
    "iso:country":"BE",
    "sg:address":"Moerenstraat 120",
    "sg:city":"Arendonk",
    "sg:orig_category":"Agences d'exp\u00e9dition",
    "sg:phone":"+32 14 67 12 11",
    "sg:postcode":"2370",
    "sg:province":"Antwerpen",
    "wof:name":"Agrotrans",
    "wof:placetype":"venue"
},
  "geometry": {"coordinates":[5.1140871048,51.319278717],"type":"Point"}
}