{
  "type": "Feature",
  "properties": {
    "addr:full":"Dorpsstraat 90 Stabroek Antwerpen 2940",
    "addr:housenumber":"90",
    "addr:postcode":"2940",
    "addr:street":"Dorpsstraat",
    "iso:country":"BE",
    "sg:address":"Dorpsstraat 90",
    "sg:city":"Stabroek",
    "sg:classifiers":[
        {
            "category":"Shopping",
            "subcategory":"Florist",
            "type":"Retail Goods"
        }
    ],
    "sg:phone":"+32 3 569 09 25",
    "sg:postcode":"2940",
    "sg:province":"Antwerpen",
    "wof:name":"Gerbera",
    "wof:placetype":"venue"
},
  "geometry": {"coordinates":[4.3682861328,51.3332023621],"type":"Point"}
}