{
  "type": "Feature",
  "properties": {
    "iso:country":"BE",
    "sg:address":"Chauss\u00c9e De Namur 122",
    "sg:city":"Sart-dames-avelines",
    "sg:orig_category":"Installation \u00e9lectrique r\u00e9sidentielle",
    "sg:phone":"+32 71 87 88 12",
    "sg:postcode":"1495",
    "sg:province":"Brabant Wallon",
    "wof:name":"Cap Security",
    "wof:placetype":"venue"
},
  "geometry": {"coordinates":[4.5012750626,50.5523414612],"type":"Point"}
}