{
  "type": "Feature",
  "properties": {
    "iso:country":"BE",
    "sg:address":"Koning Albertstraat 74",
    "sg:city":"Diest",
    "sg:orig_category":"Tijdelijke werkgelegenheid and uitzendkantoren",
    "sg:phone":"+32 13 35 35 35",
    "sg:postcode":"3290",
    "sg:province":"Vlaams-Brabant",
    "wof:name":"Actief Interim",
    "wof:placetype":"venue"
},
  "geometry": {"coordinates":[5.0588340759,50.9816246033],"type":"Point"}
}