{
  "type": "Feature",
  "properties": {
    "iso:country":"BE",
    "sg:address":"Heikemp 1002",
    "sg:city":"Kinrooi",
    "sg:orig_category":"Apparatus, Containers, Boilers, And Tanks Of Steel",
    "sg:phone":"+32 89 70 12 49",
    "sg:postcode":"3640",
    "sg:province":"Limburg",
    "wof:name":"Jan Smolders Nv",
    "wof:placetype":"venue"
},
  "geometry": {"coordinates":[5.7216539383,51.1798706055],"type":"Point"}
}