{
  "type": "Feature",
  "properties": {
    "addr:full":"Avenue Des Dauphins 19 Villers-la-ville (sart-dames-avelines) Brabant Wallon 1495",
    "addr:housenumber":"19",
    "addr:postcode":"1495",
    "addr:street":"Avenue Des Dauphins",
    "iso:country":"BE",
    "sg:address":"Avenue Des Dauphins 19",
    "sg:city":"Villers-la-ville (sart-dames-avelines)",
    "sg:classifiers":[
        {
            "category":"Insurance",
            "subcategory":"Insurance Agent",
            "type":"Services"
        }
    ],
    "sg:phone":"+32 67 77 34 99",
    "sg:postcode":"1495",
    "sg:province":"Brabant Wallon",
    "sg:tags":[
        "broker"
    ],
    "wof:name":"Philippe M",
    "wof:placetype":"venue"
},
  "geometry": {"coordinates":[4.530477047,50.5786132812],"type":"Point"}
}