{
  "type": "Feature",
  "properties": {
    "iso:country":"BE",
    "sg:address":"Rue Alfred Smeets 14",
    "sg:city":"Seraing",
    "sg:orig_category":"Fleurop Interflora",
    "sg:phone":"+32 2 242 29 64",
    "sg:postcode":"4100",
    "sg:province":"Li\u00e8ge",
    "wof:name":"Machiels",
    "wof:placetype":"venue"
},
  "geometry": {"coordinates":[5.5150299072,50.6052894592],"type":"Point"}
}