{
  "type": "Feature",
  "properties": {
    "iso:country":"BE",
    "sg:address":"Rue De La Paille 55",
    "sg:city":"Bassenge",
    "sg:orig_category":"Werk and personeelsselectie",
    "sg:phone":"+32 4 286 91 62",
    "sg:postcode":"4690",
    "sg:province":"Li\u00e8ge",
    "wof:name":"Ale Bassenge",
    "wof:placetype":"venue"
},
  "geometry": {"coordinates":[5.6102480888,50.7593383789],"type":"Point"}
}