{
  "type": "Feature",
  "properties": {
    "iso:country":"BE",
    "sg:address":"Rue Albert Dumont 66",
    "sg:city":"Chimay",
    "sg:orig_category":"Rundveehouders",
    "sg:phone":"+32 60 21 10 85",
    "sg:postcode":"6463",
    "sg:province":"Hainaut",
    "wof:name":"Freddy Herbage",
    "wof:placetype":"venue"
},
  "geometry": {"coordinates":[4.3847999573,50.0929412842],"type":"Point"}
}