{
  "type": "Feature",
  "properties": {
    "addr:full":"Ervaertstraat 10 Borgloon Limburg 3840",
    "addr:housenumber":"10",
    "addr:postcode":"3840",
    "addr:street":"Ervaertstraat",
    "iso:country":"BE",
    "sg:address":"Ervaertstraat 10",
    "sg:city":"Borgloon",
    "sg:orig_category":"Openbare veiligheid",
    "sg:phone":"+32 12 74 14 16",
    "sg:postcode":"3840",
    "sg:province":"Limburg",
    "wof:name":"Federale Politie",
    "wof:placetype":"venue"
},
  "geometry": {"coordinates":[5.3444581032,50.8095359802],"type":"Point"}
}