{
  "type": "Feature",
  "properties": {
    "addr:full":"Pont Aux Lions 2 Verviers Li\u00e8ge 4800",
    "addr:housenumber":"2",
    "addr:postcode":"4800",
    "addr:street":"Pont Aux Lions",
    "iso:country":"BE",
    "sg:address":"Pont Aux Lions 2",
    "sg:city":"Verviers",
    "sg:orig_category":"Fournitures de bureau. Art and fournitures artistiques",
    "sg:phone":"+32 87 31 52 23",
    "sg:postcode":"4800",
    "sg:province":"Li\u00e8ge",
    "wof:name":"P.n.b.",
    "wof:placetype":"venue"
},
  "geometry": {"coordinates":[5.8616228104,50.5934906006],"type":"Point"}
}