{
  "type": "Feature",
  "properties": {
    "addr:full":"Chauss\u00e9e De Tournai 53 Frasnes-lez-anvaing (wattripont) Hainaut 7910",
    "addr:housenumber":"53;7910",
    "addr:street":"Chausse\u0301E De Tournai;Wattripont Hainaut",
    "iso:country":"BE",
    "sg:address":"Chauss\u00e9e De Tournai 53",
    "sg:city":"Frasnes-lez-anvaing (wattripont)",
    "sg:classifiers":[
        {
            "category":"Building & Trades",
            "subcategory":"Landscaping Services",
            "type":"Services"
        }
    ],
    "sg:phone":"+32 69 76 84 65",
    "sg:postcode":"7910",
    "sg:province":"Hainaut",
    "sg:tags":[
        "gardening",
        "garden",
        "maintenance"
    ],
    "wof:name":"Laureyns P",
    "wof:placetype":"venue"
},
  "geometry": {"coordinates":[3.5423519611,50.7291297913],"type":"Point"}
}