{
  "type": "Feature",
  "properties": {
    "iso:country":"BE",
    "sg:address":"Van Malderstraat 91",
    "sg:city":"Sint-jans-molenbeek/molenbeek-saint-jean",
    "sg:orig_category":"Herstellingen and onderhoud van auto's",
    "sg:phone":"+32 2 414 99 79",
    "sg:postcode":"1080",
    "sg:province":"Bruxelles-Capitale",
    "wof:name":"Garage Van Malder-express",
    "wof:placetype":"venue"
},
  "geometry": {"coordinates":[4.3256211281,50.8538703918],"type":"Point"}
}