{
  "type": "Feature",
  "properties": {
    "iso:country":"BE",
    "sg:address":"Lijsterbolstraat 10",
    "sg:city":"Kontich",
    "sg:classifiers":[
        {
            "category":"Professional",
            "subcategory":"Accounting & Tax Preparation",
            "type":"Services"
        }
    ],
    "sg:phone":"+32 3 458 30 25",
    "sg:postcode":"2550",
    "sg:province":"Antwerpen",
    "sg:tags":[
        "bookkeeper"
    ],
    "wof:name":"Acs Nv",
    "wof:placetype":"venue"
},
  "geometry": {"coordinates":[4.4488520622,51.1298446655],"type":"Point"}
}