{
  "type": "Feature",
  "properties": {
    "addr:full":"Rue Colonel Bourg 107 Bruxelles (evere) Bruxelles-Capitale 1140",
    "addr:housenumber":"107",
    "addr:postcode":"1140",
    "addr:street":"Rue Colonel Bourg",
    "iso:country":"BE",
    "sg:address":"Rue Colonel Bourg 107",
    "sg:city":"Bruxelles (evere)",
    "sg:classifiers":[
        {
            "category":"Real Estate",
            "subcategory":"Real Estate Services",
            "type":"Services"
        }
    ],
    "sg:phone":"+32 2 726 87 31",
    "sg:postcode":"1140",
    "sg:province":"Bruxelles-Capitale",
    "wof:name":"Riverside Investments",
    "wof:placetype":"venue"
},
  "geometry": {"coordinates":[4.4131970406,50.8537635803],"type":"Point"}
}