{
  "type": "Feature",
  "properties": {
    "addr:full":"Rue Remy Soetens 40 Bruxelles (jette) Bruxelles-Capitale 1090",
    "addr:housenumber":"40",
    "addr:postcode":"1090",
    "addr:street":"Rue Remy Soetens",
    "iso:country":"BE",
    "sg:address":"Rue Remy Soetens 40",
    "sg:city":"Bruxelles (jette)",
    "sg:classifiers":[
        {
            "category":"Shopping",
            "subcategory":"Pets & Pet Supplies",
            "type":"Retail Goods"
        }
    ],
    "sg:phone":"+32 2 479 18 23",
    "sg:postcode":"1090",
    "sg:province":"Bruxelles-Capitale",
    "sg:tags":[
        "-",
        "foundry"
    ],
    "wof:name":"H\u00fcttenes-albertus Belgium Nv",
    "wof:placetype":"venue"
},
  "geometry": {"coordinates":[4.3197140694,50.8869476318],"type":"Point"}
}