{
  "type": "Feature",
  "properties": {
    "iso:country":"BE",
    "sg:address":"Vloedbeemdenstraat 5",
    "sg:city":"Balen",
    "sg:orig_category":"Woningbouw",
    "sg:phone":"+32 14 30 20 34",
    "sg:postcode":"2491",
    "sg:province":"Antwerpen",
    "wof:name":"Lodewijckx Johan",
    "wof:placetype":"venue"
},
  "geometry": {"coordinates":[5.1510548592,51.1413841248],"type":"Point"}
}