{
  "type": "Feature",
  "properties": {
    "iso:country":"BE",
    "sg:address":"Kerseveldmeers 15",
    "sg:city":"Opwijk",
    "sg:orig_category":"Installatie van houten of kunststof schrijnwerk",
    "sg:phone":"+32 52 35 51 53",
    "sg:postcode":"1745",
    "sg:province":"Vlaams-Brabant",
    "wof:name":"De Brandt",
    "wof:placetype":"venue"
},
  "geometry": {"coordinates":[4.1558279991,50.9654998779],"type":"Point"}
}