{
  "type": "Feature",
  "properties": {
    "iso:country":"BE",
    "sg:address":"Toeffelhoek 36",
    "sg:city":"Boechout",
    "sg:orig_category":"Groenten and fruit Gh Groententeelt",
    "sg:phone":"+32 3 455 48 71",
    "sg:postcode":"2531",
    "sg:province":"Antwerpen",
    "wof:name":"Romeco",
    "wof:placetype":"venue"
},
  "geometry": {"coordinates":[4.5110869408,51.1776275635],"type":"Point"}
}