{
  "type": "Feature",
  "properties": {
    "addr:full":"Kruisstraat 101b2 Duffel Antwerpen 2570",
    "addr:housenumber":"101b2",
    "addr:postcode":"2570",
    "addr:street":"Kruisstraat",
    "iso:country":"BE",
    "sg:address":"Kruisstraat 101b2",
    "sg:city":"Duffel",
    "sg:orig_category":"Landmeters",
    "sg:phone":"+32 15 32 03 56",
    "sg:postcode":"2570",
    "sg:province":"Antwerpen",
    "wof:name":"Peter Liekens",
    "wof:placetype":"venue"
},
  "geometry": {"coordinates":[4.4847831726,51.0899429321],"type":"Point"}
}