{
  "type": "Feature",
  "properties": {
    "addr:full":"Rekhof 22 Poperinge West-Vlaanderen 8970",
    "addr:housenumber":"22",
    "addr:postcode":"8970",
    "addr:street":"Rekhof",
    "iso:country":"BE",
    "sg:address":"Rekhof 22",
    "sg:city":"Poperinge",
    "sg:orig_category":"Artsen and specialisten",
    "sg:phone":"+32 57 33 85 74",
    "sg:postcode":"8970",
    "sg:province":"West-Vlaanderen",
    "wof:name":"Consultatiebur.jonge Kind",
    "wof:placetype":"venue"
},
  "geometry": {"coordinates":[2.7280569077,50.8531188965],"type":"Point"}
}