{
  "type": "Feature",
  "properties": {
    "iso:country":"BE",
    "sg:address":"Les Hauts De Meuse 32",
    "sg:city":"Namur",
    "sg:orig_category":"Studios photographiques",
    "sg:phone":"+32 81 30 61 95",
    "sg:postcode":"5101",
    "sg:province":"Namur",
    "wof:name":"Michel Massart",
    "wof:placetype":"venue"
},
  "geometry": {"coordinates":[4.8940701485,50.4329376221],"type":"Point"}
}