{
  "type": "Feature",
  "properties": {
    "iso:country":"BE",
    "sg:address":"Paanderstraat 71",
    "sg:city":"Meulebeke",
    "sg:orig_category":"Plomberie, chauffage and installations sanitaires",
    "sg:phone":"+32 51 48 68 67",
    "sg:postcode":"8760",
    "sg:province":"West-Vlaanderen",
    "wof:name":"Danny Bruyneel",
    "wof:placetype":"venue"
},
  "geometry": {"coordinates":[3.3084270954,50.9414291382],"type":"Point"}
}