{
  "type": "Feature",
  "properties": {
    "addr:full":"Rue Des Technologies 22 Ottignies-louvain-la-neuve Brabant Wallon 1340",
    "addr:housenumber":"22",
    "addr:postcode":"1340",
    "addr:street":"Rue Des Technologies",
    "iso:country":"BE",
    "sg:address":"Rue Des Technologies 22",
    "sg:city":"Ottignies-louvain-la-neuve",
    "sg:orig_category":"Kantoormachines Fab Papierwaren and schoolbenodigdheden Gh",
    "sg:phone":"+32 10 61 38 38",
    "sg:postcode":"1340",
    "sg:province":"Brabant Wallon",
    "wof:name":"C.p. Bourg",
    "wof:placetype":"venue"
},
  "geometry": {"coordinates":[4.5687651634,50.6590232849],"type":"Point"}
}