{
  "type": "Feature",
  "properties": {
    "iso:country":"BE",
    "sg:address":"Chauss\u00e9e D'alsemberg 432",
    "sg:city":"Bruxelles (uccle)",
    "sg:classifiers":[
        {
            "category":"Shopping",
            "subcategory":"Crafts & Fabrics",
            "type":"Retail Goods"
        }
    ],
    "sg:postcode":"1180",
    "sg:province":"Bruxelles-Capitale",
    "sg:tags":[
        "pleating",
        "embroidery"
    ],
    "wof:name":"Maisons Clothes (m.concept) Sa",
    "wof:placetype":"venue"
},
  "geometry": {"coordinates":[4.3382558823,50.8114204407],"type":"Point"}
}