{
  "type": "Feature",
  "properties": {
    "addr:full":"Avenue Reine Astrid 78 Verviers Li\u00e8ge 4802",
    "addr:housenumber":"78",
    "addr:postcode":"4802",
    "addr:street":"Avenue Reine Astrid",
    "iso:country":"BE",
    "sg:address":"Avenue Reine Astrid 78",
    "sg:city":"Verviers",
    "sg:classifiers":[
        {
            "category":"Autos & Motor Vehicles",
            "subcategory":"Fuel & Gas Station",
            "type":"Retail Goods"
        }
    ],
    "sg:phone":"+32 87 33 36 10",
    "sg:postcode":"4802",
    "sg:province":"Li\u00e8ge",
    "sg:tags":[
        "stations-service",
        "carburants"
    ],
    "wof:name":"Shell",
    "wof:placetype":"venue"
},
  "geometry": {"coordinates":[5.8818840981,50.5849075317],"type":"Point"}
}