{
  "type": "Feature",
  "properties": {
    "iso:country":"BE",
    "sg:address":"Steenweg Van Aalst 110",
    "sg:city":"Dendermonde",
    "sg:orig_category":"Rusthuizen and serviceflats",
    "sg:phone":"+32 52 22 19 75",
    "sg:postcode":"9200",
    "sg:province":"Oost-Vlaanderen",
    "wof:name":"Home Kasteelhof",
    "wof:placetype":"venue"
},
  "geometry": {"coordinates":[4.0683197975,51.0246810913],"type":"Point"}
}