{
  "type": "Feature",
  "properties": {
    "iso:country":"BE",
    "sg:address":"Kerkhofdries 5",
    "sg:city":"Sint-amands",
    "sg:classifiers":[
        {
            "category":"Real Estate",
            "subcategory":"Real Estate Services",
            "type":"Services"
        }
    ],
    "sg:phone":"+32 52 34 18 41",
    "sg:postcode":"2890",
    "sg:province":"Antwerpen",
    "wof:name":"Sybimmo",
    "wof:placetype":"venue"
},
  "geometry": {"coordinates":[4.2055659294,51.0557441711],"type":"Point"}
}