{
  "type": "Feature",
  "properties": {
    "addr:full":"Rijmenamsebaan 19 Boortmeerbeek Vlaams-Brabant 3190",
    "addr:housenumber":"19",
    "addr:postcode":"3190",
    "addr:street":"Rijmenamsebaan",
    "iso:country":"BE",
    "sg:address":"Rijmenamsebaan 19",
    "sg:city":"Boortmeerbeek",
    "sg:orig_category":"Epiceries",
    "sg:phone":"+32 15 51 24 35",
    "sg:postcode":"3190",
    "sg:province":"Vlaams-Brabant",
    "wof:name":"Monique Servaes",
    "wof:placetype":"venue"
},
  "geometry": {"coordinates":[4.5743851662,50.9852676392],"type":"Point"}
}