{
  "type": "Feature",
  "properties": {
    "iso:country":"BE",
    "sg:address":"Rigessel 14",
    "sg:city":"Rotselaar (wezemaal)",
    "sg:classifiers":[
        {
            "category":"Professional",
            "subcategory":"Computer Services",
            "type":"Services"
        }
    ],
    "sg:phone":"+32 16 89 35 01",
    "sg:postcode":"3111",
    "sg:province":"Vlaams-Brabant",
    "sg:tags":[
        "repair",
        "processing",
        "-",
        "maintenance",
        "data"
    ],
    "wof:name":"Third Party Maintenance Bvba",
    "wof:placetype":"venue"
},
  "geometry": {"coordinates":[4.7498202324,50.9451293945],"type":"Point"}
}