{
  "type": "Feature",
  "properties": {
    "iso:country":"BE",
    "sg:address":"Savooistraat 31-33",
    "sg:city":"Ninove",
    "sg:orig_category":"Boucheries",
    "sg:phone":"+32 54 33 74 56",
    "sg:postcode":"9400",
    "sg:province":"Oost-Vlaanderen",
    "wof:name":"Beenhouw. Johan & Carine",
    "wof:placetype":"venue"
},
  "geometry": {"coordinates":[4.0167832375,50.8374481201],"type":"Point"}
}