{
  "type": "Feature",
  "properties": {
    "addr:full":"Dr. Peetersstraat 90 Geel Antwerpen 2440",
    "addr:housenumber":"90",
    "addr:postcode":"2440",
    "addr:street":"Dr. Peetersstraat",
    "iso:country":"BE",
    "sg:address":"Dr. Peetersstraat 90",
    "sg:city":"Geel",
    "sg:orig_category":"Ruimtes voor conferenties, recepties and feesten",
    "sg:phone":"+32 14 58 66 68",
    "sg:postcode":"2440",
    "sg:province":"Antwerpen",
    "wof:name":"Elsum",
    "wof:placetype":"venue"
},
  "geometry": {"coordinates":[4.9760069847,51.1626167297],"type":"Point"}
}