{
  "type": "Feature",
  "properties": {
    "addr:full":"Tongersesteenweg 185 Hoeselt Limburg 3730",
    "addr:housenumber":"185",
    "addr:postcode":"3730",
    "addr:street":"Tongersesteenweg",
    "iso:country":"BE",
    "sg:address":"Tongersesteenweg 185",
    "sg:city":"Hoeselt",
    "sg:classifiers":[
        {
            "category":"Bars & Pubs",
            "type":"Food & Drink"
        }
    ],
    "sg:phone":"+32 12 23 50 80",
    "sg:postcode":"3730",
    "sg:province":"Limburg",
    "wof:name":"Bij Sophie En Henri",
    "wof:placetype":"venue"
},
  "geometry": {"coordinates":[5.4673390388,50.8197441101],"type":"Point"}
}