{
  "type": "Feature",
  "properties": {
    "iso:country":"BE",
    "sg:address":"Rue Neuve 2",
    "sg:city":"Gerpinnes",
    "sg:classifiers":[
        {
            "category":"Shopping",
            "subcategory":"Optician",
            "type":"Retail Goods"
        }
    ],
    "sg:phone":"+32 71 22 07 39",
    "sg:postcode":"6280",
    "sg:province":"Hainaut",
    "sg:tags":[
        "-"
    ],
    "wof:name":"Hardy's Optique",
    "wof:placetype":"venue"
},
  "geometry": {"coordinates":[4.4715561867,50.3453102112],"type":"Point"}
}