{
  "type": "Feature",
  "properties": {
    "addr:full":"Rue Julien Ghuysen 0 Blegny Li\u00e8ge 4670",
    "addr:housenumber":"0",
    "addr:postcode":"4670",
    "addr:street":"Rue Julien Ghuysen",
    "iso:country":"BE",
    "sg:address":"Rue Julien Ghuysen 0",
    "sg:city":"Blegny",
    "sg:orig_category":"Volwassenenonderwijs",
    "sg:phone":"+32 4 387 94 11",
    "sg:postcode":"4670",
    "sg:province":"Li\u00e8ge",
    "wof:name":"Inst.enseign.prom.sociale",
    "wof:placetype":"venue"
},
  "geometry": {"coordinates":[5.7270197868,50.6714172363],"type":"Point"}
}