{
  "type": "Feature",
  "properties": {
    "iso:country":"BE",
    "sg:address":"Boulevard Des Invalides 117 Box 1",
    "sg:city":"Bruxelles (auderghem)",
    "sg:classifiers":[
        {
            "category":"Professional",
            "subcategory":"Credit Reporting & Collection",
            "type":"Services"
        }
    ],
    "sg:phone":"+32 2 673 90 08",
    "sg:postcode":"1160",
    "sg:province":"Bruxelles-Capitale",
    "sg:tags":[
        "bailiff"
    ],
    "wof:name":"Verhamme P",
    "wof:placetype":"venue"
},
  "geometry": {"coordinates":[4.4126029015,50.8177070618],"type":"Point"}
}