{
  "type": "Feature",
  "properties": {
    "iso:country":"BE",
    "sg:address":"Rue De Matignolle 14",
    "sg:city":"Doische",
    "sg:classifiers":[
        {
            "category":"Military Area",
            "subcategory":"Army Base",
            "type":"Public Place"
        }
    ],
    "sg:phone":"+32 60 39 91 98",
    "sg:postcode":"5680",
    "sg:province":"Namur",
    "sg:tags":[
        "de",
        "caf\u00e9s",
        "terrain",
        "camping"
    ],
    "wof:name":"Camping Fontaine Du Roy",
    "wof:placetype":"venue"
},
  "geometry": {"coordinates":[4.64935112,50.1131401062],"type":"Point"}
}