{
  "type": "Feature",
  "properties": {
    "iso:country":"BE",
    "sg:address":"Patersstraat 88",
    "sg:city":"Turnhout",
    "sg:classifiers":[
        {
            "category":"Home & Garden",
            "subcategory":"Home Furnishings",
            "type":"Retail Goods"
        }
    ],
    "sg:phone":"+32 14 41 77 76",
    "sg:postcode":"2300",
    "sg:province":"Antwerpen",
    "sg:tags":[
        "-",
        "bed",
        "mattress"
    ],
    "wof:name":"Bio-shop De Pimpernel Nv",
    "wof:placetype":"venue"
},
  "geometry": {"coordinates":[4.9496831894,51.326625824],"type":"Point"}
}