{
  "type": "Feature",
  "properties": {
    "iso:country":"BE",
    "sg:address":"Oude Zeedijkstraat 26",
    "sg:city":"Kortemark",
    "sg:orig_category":"Eleveurs and marchands de porcs",
    "sg:phone":"+32 51 72 25 94",
    "sg:postcode":"8610",
    "sg:province":"West-Vlaanderen",
    "wof:name":"Georges Desender",
    "wof:placetype":"venue"
},
  "geometry": {"coordinates":[3.0673289299,51.0173492432],"type":"Point"}
}