{
  "type": "Feature",
  "properties": {
    "iso:country":"BE",
    "sg:address":"De Wittestraat 53",
    "sg:city":"Antwerpen",
    "sg:orig_category":"Dierenartsen",
    "sg:phone":"+32 3 218 50 66",
    "sg:postcode":"2600",
    "sg:province":"Antwerpen",
    "wof:name":"Diana Brosens",
    "wof:placetype":"venue"
},
  "geometry": {"coordinates":[4.3858428001,51.1888122559],"type":"Point"}
}