{
  "type": "Feature",
  "properties": {
    "iso:country":"BE",
    "sg:address":"Sainlez 25",
    "sg:city":"Fauvillers",
    "sg:orig_category":"Eleveurs de bovins",
    "sg:phone":"+32 61 21 27 66",
    "sg:postcode":"6637",
    "sg:province":"Luxembourg",
    "wof:name":"Marcel Demande",
    "wof:placetype":"venue"
},
  "geometry": {"coordinates":[5.7133150101,49.9212493896],"type":"Point"}
}