{
  "type": "Feature",
  "properties": {
    "iso:country":"BE",
    "sg:address":"Pontfort 71",
    "sg:city":"Retie",
    "sg:orig_category":"Eleveurs de bovins",
    "sg:phone":"+32 14 37 82 72",
    "sg:postcode":"2470",
    "sg:province":"Antwerpen",
    "wof:name":"Karel Vennekens",
    "wof:placetype":"venue"
},
  "geometry": {"coordinates":[5.0508999825,51.2622566223],"type":"Point"}
}