{
  "type": "Feature",
  "properties": {
    "addr:full":"Weertersteenweg 326 Kinrooi (molenbeersel) Limburg 3640",
    "addr:housenumber":"326",
    "addr:postcode":"3640",
    "addr:street":"Weertersteenweg",
    "iso:country":"BE",
    "sg:address":"Weertersteenweg 326",
    "sg:city":"Kinrooi (molenbeersel)",
    "sg:classifiers":[
        {
            "category":"Insurance",
            "subcategory":"Insurance Agent",
            "type":"Services"
        }
    ],
    "sg:phone":"+32 89 70 16 06",
    "sg:postcode":"3640",
    "sg:province":"Limburg",
    "sg:tags":[
        "broker"
    ],
    "wof:name":"Van Eijgen Vof",
    "wof:placetype":"venue"
},
  "geometry": {"coordinates":[5.7421097755,51.1599807739],"type":"Point"}
}