{
  "type": "Feature",
  "properties": {
    "addr:full":"Genkersteenweg 388 Genk Limburg 3600",
    "addr:housenumber":"388",
    "addr:postcode":"3600",
    "addr:street":"Genkersteenweg",
    "iso:country":"BE",
    "sg:address":"Genkersteenweg 388",
    "sg:city":"Genk",
    "sg:orig_category":"Boekhouders",
    "sg:phone":"+32 89 35 31 24",
    "sg:postcode":"3600",
    "sg:province":"Limburg",
    "wof:name":"Hermans Paul",
    "wof:placetype":"venue"
},
  "geometry": {"coordinates":[5.4990148544,50.9635848999],"type":"Point"}
}