{
  "type": "Feature",
  "properties": {
    "addr:full":"Rue Du Panorama 3 Wemmel Vlaams-Brabant 1780",
    "addr:housenumber":"3",
    "addr:postcode":"1780",
    "addr:street":"Rue Du Panorama;Vlaams-Brabant",
    "iso:country":"BE",
    "sg:address":"Rue Du Panorama 3",
    "sg:city":"Wemmel",
    "sg:classifiers":[
        {
            "category":"Health Services",
            "subcategory":"Dentist",
            "type":"Services"
        }
    ],
    "sg:phone":"+32 2 460 68 82",
    "sg:postcode":"1780",
    "sg:province":"Vlaams-Brabant",
    "wof:name":"Pira M",
    "wof:placetype":"venue"
},
  "geometry": {"coordinates":[4.3250751495,50.9029541016],"type":"Point"}
}