{
  "type": "Feature",
  "properties": {
    "addr:full":"Chauss\u00c9e De Mons 16 Nivelles Brabant Wallon 1400",
    "addr:housenumber":"16",
    "addr:postcode":"1400",
    "addr:street":"Chausse\u0301E De Mons",
    "iso:country":"BE",
    "sg:address":"Chauss\u00c9e De Mons 16",
    "sg:city":"Nivelles",
    "sg:orig_category":"Magasins de r\u00e9parations d'articles personnels et m\u00e9nagers divers. V\u00eatements pour Dames. V\u00eatements",
    "sg:phone":"+32 67 21 06 47",
    "sg:postcode":"1400",
    "sg:province":"Brabant Wallon",
    "wof:name":"La Touche-atout",
    "wof:placetype":"venue"
},
  "geometry": {"coordinates":[4.3190760612,50.5942344666],"type":"Point"}
}