{
  "type": "Feature",
  "properties": {
    "addr:full":"Leopoldlaan 182 Middelkerke West-Vlaanderen 8430",
    "addr:housenumber":"182",
    "addr:postcode":"8430",
    "addr:street":"Leopoldlaan",
    "iso:country":"BE",
    "sg:address":"Leopoldlaan 182",
    "sg:city":"Middelkerke",
    "sg:orig_category":"Sportclubs Sportterreinen and installaties behalve sportcentra",
    "sg:phone":"+32 475 95 22 44",
    "sg:postcode":"8430",
    "sg:province":"West-Vlaanderen",
    "wof:name":"V.v. Leffinge",
    "wof:placetype":"venue"
},
  "geometry": {"coordinates":[2.8054270744,51.1836700439],"type":"Point"}
}