{
  "type": "Feature",
  "properties": {
    "iso:country":"BE",
    "sg:address":"Rue Des Glands 70",
    "sg:city":"Bruxelles (forest)",
    "sg:classifiers":[
        {
            "category":"Sports & Exercise",
            "subcategory":"Gym",
            "type":"Entertainment"
        }
    ],
    "sg:phone":"+32 2 347 38 19",
    "sg:postcode":"1190",
    "sg:province":"Bruxelles-Capitale",
    "sg:tags":[
        "fitness"
    ],
    "wof:name":"Pool's Fitness Center",
    "wof:placetype":"venue"
},
  "geometry": {"coordinates":[4.3290328979,50.8190498352],"type":"Point"}
}