{
  "type": "Feature",
  "properties": {
    "addr:full":"Chauss\u00c9e De Vilvorde 17 Brussel/bruxelles Bruxelles-Capitale 1020",
    "addr:housenumber":"17",
    "addr:postcode":"1020",
    "addr:street":"Chausse\u0301E De Vilvorde;/",
    "iso:country":"BE",
    "sg:address":"Chauss\u00c9e De Vilvorde 17",
    "sg:city":"Brussel/bruxelles",
    "sg:classifiers":[
        {
            "category":"Autos & Motor Vehicles",
            "subcategory":"Fuel & Gas Station",
            "type":"Retail Goods"
        }
    ],
    "sg:phone":"+32 2 245 41 82",
    "sg:postcode":"1020",
    "sg:province":"Bruxelles-Capitale",
    "sg:tags":[
        "stations-service",
        "carburants"
    ],
    "wof:name":"Texaco",
    "wof:placetype":"venue"
},
  "geometry": {"coordinates":[4.375,50.8826255798],"type":"Point"}
}