{
  "type": "Feature",
  "properties": {
    "iso:country":"BE",
    "sg:address":"Faubourg De Namur 17",
    "sg:city":"Nivelles",
    "sg:classifiers":[
        {
            "category":"Education",
            "subcategory":"School",
            "type":"Public Place"
        }
    ],
    "sg:phone":"+32 67 21 86 15",
    "sg:postcode":"1400",
    "sg:province":"Brabant Wallon",
    "sg:tags":[
        "primary"
    ],
    "wof:name":"Athen\u00e9e Royal De Nivelles",
    "wof:placetype":"venue"
},
  "geometry": {"coordinates":[4.3369059563,50.5995407104],"type":"Point"}
}