{
  "type": "Feature",
  "properties": {
    "iso:country":"BE",
    "sg:address":"Rue Thier Oulet 75",
    "sg:city":"Engis",
    "sg:classifiers":[
        {
            "category":"Real Estate",
            "subcategory":"Architect",
            "type":"Services"
        }
    ],
    "sg:phone":"+32 4 275 16 53",
    "sg:postcode":"4480",
    "sg:province":"Li\u00e8ge",
    "wof:name":"Richel D",
    "wof:placetype":"venue"
},
  "geometry": {"coordinates":[5.3915281296,50.5820159912],"type":"Point"}
}