{
  "type": "Feature",
  "properties": {
    "iso:country":"BE",
    "sg:address":"Duffelshoek 41",
    "sg:city":"Kontich",
    "sg:classifiers":[
        {
            "category":"Building & Trades",
            "subcategory":"Pest Control",
            "type":"Services"
        }
    ],
    "sg:phone":"+32 3 458 42 78",
    "sg:postcode":"2550",
    "sg:province":"Antwerpen",
    "sg:tags":[
        "painting",
        "contractor"
    ],
    "wof:name":"Francis Mario",
    "wof:placetype":"venue"
},
  "geometry": {"coordinates":[4.472799778,51.1236076355],"type":"Point"}
}