{
  "type": "Feature",
  "properties": {
    "iso:country":"BE",
    "sg:address":"Zwaluwstraat 1",
    "sg:city":"Staden",
    "sg:classifiers":[
        {
            "category":"Food & Beverages",
            "subcategory":"Ethnic Foods",
            "type":"Retail Goods"
        }
    ],
    "sg:phone":"+32 51 22 69 25",
    "sg:postcode":"8840",
    "sg:province":"West-Vlaanderen",
    "sg:tags":[
        "article",
        "b\u00e9b\u00e9s",
        "v\u00eatements",
        "pour",
        "dames"
    ],
    "wof:name":"Huis Florence",
    "wof:placetype":"venue"
},
  "geometry": {"coordinates":[3.0643808842,50.9399986267],"type":"Point"}
}