{
  "type": "Feature",
  "properties": {
    "addr:full":"Rue De La Dr\u00e8ve 68 Mons (ghlin) Hainaut 7011",
    "addr:housenumber":"68",
    "addr:postcode":"7011",
    "addr:street":"Rue De La Dre\u0300Ve",
    "iso:country":"BE",
    "sg:address":"Rue De La Dr\u00e8ve 68",
    "sg:city":"Mons (ghlin)",
    "sg:classifiers":[
        {
            "category":"Insurance",
            "subcategory":"Insurance Agent",
            "type":"Services"
        }
    ],
    "sg:phone":"+32 65 31 74 81",
    "sg:postcode":"7011",
    "sg:province":"Hainaut",
    "sg:tags":[
        "broker"
    ],
    "wof:name":"Inter Assur Mvf Sprl",
    "wof:placetype":"venue"
},
  "geometry": {"coordinates":[3.912539959,50.4712982178],"type":"Point"}
}