{
  "type": "Feature",
  "properties": {
    "addr:full":"Baronielaan 10 Izegem West-Vlaanderen 8870",
    "addr:housenumber":"10",
    "addr:postcode":"8870",
    "addr:street":"Baronielaan",
    "iso:country":"BE",
    "sg:address":"Baronielaan 10",
    "sg:city":"Izegem",
    "sg:classifiers":[
        {
            "category":"Health Services",
            "subcategory":"Health Practitioner",
            "type":"Services"
        }
    ],
    "sg:phone":"+32 51 30 46 75",
    "sg:postcode":"8870",
    "sg:province":"West-Vlaanderen",
    "sg:tags":[
        "physiotherapist"
    ],
    "wof:name":"Mercier D",
    "wof:placetype":"venue"
},
  "geometry": {"coordinates":[3.2214639187,50.9149932861],"type":"Point"}
}