{
  "type": "Feature",
  "properties": {
    "addr:full":"Buke 46 Zottegem (leeuwergem) Oost-Vlaanderen 9620",
    "addr:housenumber":"46",
    "addr:postcode":"9620",
    "addr:street":"Buke",
    "iso:country":"BE",
    "sg:address":"Buke 46",
    "sg:city":"Zottegem (leeuwergem)",
    "sg:classifiers":[
        {
            "category":"Retail",
            "subcategory":"Auto Rental",
            "type":"Services"
        }
    ],
    "sg:phone":"+32 9 360 04 00",
    "sg:postcode":"9620",
    "sg:province":"Oost-Vlaanderen",
    "sg:tags":[
        "automobile",
        "-",
        "car",
        "self-drive"
    ],
    "wof:name":"Galle",
    "wof:placetype":"venue"
},
  "geometry": {"coordinates":[3.815144062,50.8758621216],"type":"Point"}
}