{
  "type": "Feature",
  "properties": {
    "addr:full":"Weg Naar Zwartberg 40 Opglabbeek Limburg 3660",
    "addr:housenumber":"40",
    "addr:postcode":"3660",
    "addr:street":"Weg Naar Zwartberg",
    "iso:country":"BE",
    "sg:address":"Weg Naar Zwartberg 40",
    "sg:city":"Opglabbeek",
    "sg:classifiers":[
        {
            "category":"Shopping",
            "subcategory":"Crafts & Fabrics",
            "type":"Retail Goods"
        }
    ],
    "sg:phone":"+32 89 85 44 38",
    "sg:postcode":"3660",
    "sg:province":"Limburg",
    "sg:tags":[
        "plant",
        "flower",
        "artificial"
    ],
    "wof:name":"Gv-center Bvba",
    "wof:placetype":"venue"
},
  "geometry": {"coordinates":[5.5791950226,51.0418968201],"type":"Point"}
}