{
  "type": "Feature",
  "properties": {
    "iso:country":"BE",
    "sg:address":"Ettelgemsestraat 17",
    "sg:city":"Oudenburg",
    "sg:orig_category":"Journaux. Tabac",
    "sg:phone":"+32 59 26 73 33",
    "sg:postcode":"8460",
    "sg:province":"West-Vlaanderen",
    "wof:name":"Boekhandel Conny",
    "wof:placetype":"venue"
},
  "geometry": {"coordinates":[3.0088720322,51.1841888428],"type":"Point"}
}