{
  "type": "Feature",
  "properties": {
    "addr:full":"Rue De La Scierie 8 Dinant Namur 5500",
    "addr:housenumber":"8",
    "addr:postcode":"5500",
    "addr:street":"Rue De La Scierie",
    "iso:country":"BE",
    "sg:address":"Rue De La Scierie 8",
    "sg:city":"Dinant",
    "sg:classifiers":[
        {
            "category":"Building & Trades",
            "subcategory":"Construction",
            "type":"Services"
        }
    ],
    "sg:phone":"+32 82 22 44 74",
    "sg:postcode":"5500",
    "sg:province":"Namur",
    "sg:tags":[
        "carpenter"
    ],
    "wof:name":"Leroy M",
    "wof:placetype":"venue"
},
  "geometry": {"coordinates":[4.955698967,50.2649040222],"type":"Point"}
}