{
  "type": "Feature",
  "properties": {
    "addr:full":"Koningin Astridlaan 3 Maaseik Limburg 3680",
    "addr:housenumber":"3",
    "addr:postcode":"3680",
    "addr:street":"Koningin Astridlaan",
    "iso:country":"BE",
    "sg:address":"Koningin Astridlaan 3",
    "sg:city":"Maaseik",
    "sg:orig_category":"Alimentation sp\u00e9cialis\u00e9e. Epiceries",
    "sg:phone":"+32 89 56 60 35",
    "sg:postcode":"3680",
    "sg:province":"Limburg",
    "wof:name":"Ahmed Fayek",
    "wof:placetype":"venue"
},
  "geometry": {"coordinates":[5.7799749374,51.0977058411],"type":"Point"}
}