{
  "type": "Feature",
  "properties": {
    "addr:full":"Rue De Lille 7 Frameries Hainaut 7080",
    "addr:housenumber":"7",
    "addr:postcode":"7080",
    "addr:street":"Rue De Lille",
    "iso:country":"BE",
    "sg:address":"Rue De Lille 7",
    "sg:city":"Frameries",
    "sg:orig_category":"Artsen and specialisten",
    "sg:phone":"+32 65 67 45 86",
    "sg:postcode":"7080",
    "sg:province":"Hainaut",
    "wof:name":"Carl Dehon",
    "wof:placetype":"venue"
},
  "geometry": {"coordinates":[3.896517992,50.409362793],"type":"Point"}
}