{
  "type": "Feature",
  "properties": {
    "addr:full":"Luithagen-haven 12/ Haven 200 Antwerpen Antwerpen 2030",
    "addr:housenumber":"12 /;200",
    "addr:postcode":"2030",
    "addr:street":"Luithagen-Haven;Haven",
    "iso:country":"BE",
    "sg:address":"Luithagen-haven 12/ Haven 200",
    "sg:city":"Antwerpen",
    "sg:classifiers":[
        {
            "category":"Autos & Motor Vehicles",
            "subcategory":"Automobile Sales",
            "type":"Retail Goods"
        }
    ],
    "sg:phone":"+32 3 221 25 01",
    "sg:postcode":"2030",
    "sg:province":"Antwerpen",
    "sg:tags":[
        "equipment",
        "transport"
    ],
    "wof:name":"Handico Terminals Nv",
    "wof:placetype":"venue"
},
  "geometry": {"coordinates":[4.3837938309,51.2598266602],"type":"Point"}
}