{
  "type": "Feature",
  "properties": {
    "addr:full":"Avenue De La Gare 170 Hotton Luxembourg 6990",
    "addr:housenumber":"170",
    "addr:postcode":"6990",
    "addr:street":"Avenue De La Gare",
    "iso:country":"BE",
    "sg:address":"Avenue De La Gare 170",
    "sg:city":"Hotton",
    "sg:classifiers":[
        {
            "category":"Wholesale",
            "subcategory":"Fruits & Vegetables",
            "type":"Manufacturing & Wholesale Goods"
        }
    ],
    "sg:phone":"+32 84 46 61 45",
    "sg:postcode":"6990",
    "sg:province":"Luxembourg",
    "sg:tags":[
        "whol",
        "-",
        "potato"
    ],
    "wof:name":"Gillet-montjoie",
    "wof:placetype":"venue"
},
  "geometry": {"coordinates":[5.439209938,50.2756614685],"type":"Point"}
}