{
  "type": "Feature",
  "properties": {
    "iso:country":"BE",
    "sg:address":"Quai Des Charbonnages 88-90",
    "sg:city":"Sint-jans-molenbeek",
    "sg:orig_category":"Eclairage et \u00e9quipements du foyer. Quincailleries. Rev\u00eatements de sols and murs",
    "sg:phone":"+32 2 411 48 80",
    "sg:postcode":"1080",
    "sg:province":"Bruxelles-Capitale",
    "wof:name":"Carpetland",
    "wof:placetype":"venue"
},
  "geometry": {"coordinates":[4.3455300331,50.8587188721],"type":"Point"}
}