{
  "type": "Feature",
  "properties": {
    "addr:full":"Rue De La Prison 36a La Hulpe Brabant Wallon 1310",
    "addr:housenumber":"36a",
    "addr:postcode":"1310",
    "addr:street":"Rue De La Prison",
    "iso:country":"BE",
    "sg:address":"Rue De La Prison 36a",
    "sg:city":"La Hulpe",
    "sg:classifiers":[
        {
            "category":"Professional",
            "subcategory":"Management & Consulting",
            "type":"Services"
        }
    ],
    "sg:phone":"+32 2 654 19 00",
    "sg:postcode":"1310",
    "sg:province":"Brabant Wallon",
    "sg:tags":[
        "consultant",
        "agency",
        "advertising"
    ],
    "wof:name":"O G Production",
    "wof:placetype":"venue"
},
  "geometry": {"coordinates":[4.4682149887,50.7205581665],"type":"Point"}
}