{
  "type": "Feature",
  "properties": {
    "iso:country":"BE",
    "sg:address":"Sint-rochusstraat 16",
    "sg:city":"Aalst",
    "sg:orig_category":"Brood, gebak and snoepgoed",
    "sg:phone":"+32 53 83 95 69",
    "sg:postcode":"9320",
    "sg:province":"Oost-Vlaanderen",
    "wof:name":"De Tuinen",
    "wof:placetype":"venue"
},
  "geometry": {"coordinates":[4.003027916,50.9174575806],"type":"Point"}
}