{
  "type": "Feature",
  "properties": {
    "iso:country":"BE",
    "sg:address":"Halensebaan 36",
    "sg:city":"Bekkevoort",
    "sg:classifiers":[
        {
            "category":"Fast Food",
            "type":"Food & Drink"
        }
    ],
    "sg:phone":"+32 16 63 36 63",
    "sg:postcode":"3461",
    "sg:province":"Vlaams-Brabant",
    "sg:tags":[
        "\u00c0",
        "emporter",
        "restaurants"
    ],
    "wof:name":"Het Frituurke",
    "wof:placetype":"venue"
},
  "geometry": {"coordinates":[4.9291071892,50.9158859253],"type":"Point"}
}