{
  "type": "Feature",
  "properties": {
    "addr:full":"Rue Defoy 175 Florennes Namur 5620",
    "addr:housenumber":"175",
    "addr:postcode":"5620",
    "addr:street":"Rue Defoy",
    "iso:country":"BE",
    "sg:address":"Rue Defoy 175",
    "sg:city":"Florennes",
    "sg:orig_category":"Installatie van houten of kunststof schrijnwerk",
    "sg:phone":"+32 82 68 81 38",
    "sg:postcode":"5620",
    "sg:province":"Namur",
    "wof:name":"Marcel Degraux",
    "wof:placetype":"venue"
},
  "geometry": {"coordinates":[4.6889500618,50.2309112549],"type":"Point"}
}