{
  "type": "Feature",
  "properties": {
    "iso:country":"BE",
    "sg:address":"Rue De Mons 28b1",
    "sg:city":"Braine-le-comte",
    "sg:orig_category":"Diverse grafische activiteiten",
    "sg:phone":"+32 67 55 20 06",
    "sg:postcode":"7090",
    "sg:province":"Hainaut",
    "wof:name":"Sylvestre Visztricz",
    "wof:placetype":"venue"
},
  "geometry": {"coordinates":[4.1346611977,50.6090316772],"type":"Point"}
}