{
  "type": "Feature",
  "properties": {
    "addr:full":"Guido Gezellelaan 169 Heusden-zolder Limburg 3550",
    "addr:housenumber":"169",
    "addr:postcode":"3550",
    "addr:street":"Guido Gezellelaan",
    "iso:country":"BE",
    "sg:address":"Guido Gezellelaan 169",
    "sg:city":"Heusden-zolder",
    "sg:orig_category":"Meubles D\u00e9taillants, Am\u00e9nagement de B\u00e2timents et de Cuisines",
    "sg:phone":"+32 11 42 97 97",
    "sg:postcode":"3550",
    "sg:province":"Limburg",
    "wof:name":"Casimir Meubelen",
    "wof:placetype":"venue"
},
  "geometry": {"coordinates":[5.2695980072,51.0272102356],"type":"Point"}
}