{
  "type": "Feature",
  "properties": {
    "iso:country":"BE",
    "sg:address":"Esenstraat 56",
    "sg:city":"Kortemark",
    "sg:orig_category":"Peinture. Rev\u00eatements pour sols and murs",
    "sg:phone":"+32 51 56 82 79",
    "sg:postcode":"8610",
    "sg:province":"West-Vlaanderen",
    "wof:name":"Geert Vandromme",
    "wof:placetype":"venue"
},
  "geometry": {"coordinates":[2.9541599751,51.0171928406],"type":"Point"}
}