{
  "type": "Feature",
  "properties": {
    "addr:full":"Ramskapellestraat 88 Nieuwpoort West-Vlaanderen 8620",
    "addr:housenumber":"88",
    "addr:postcode":"8620",
    "addr:street":"Ramskapellestraat",
    "iso:country":"BE",
    "sg:address":"Ramskapellestraat 88",
    "sg:city":"Nieuwpoort",
    "sg:orig_category":"Banques and organismes de cr\u00e9dit",
    "sg:phone":"+32 58 23 46 03",
    "sg:postcode":"8620",
    "sg:province":"West-Vlaanderen",
    "wof:name":"Groep Argenta",
    "wof:placetype":"venue"
},
  "geometry": {"coordinates":[2.762018919,51.1085243225],"type":"Point"}
}