{
  "type": "Feature",
  "properties": {
    "addr:full":"Drongensesteenweg 3 Gent Oost-Vlaanderen 9000",
    "addr:housenumber":"3",
    "addr:postcode":"9000",
    "addr:street":"Drongensesteenweg;Oost-Vlaanderen",
    "iso:country":"BE",
    "sg:address":"Drongensesteenweg 3",
    "sg:city":"Gent",
    "sg:orig_category":"Newspapers, magazines, periodicals - Distribution",
    "sg:phone":"+32 9 227 29 76",
    "sg:postcode":"9000",
    "sg:province":"Oost-Vlaanderen",
    "wof:name":"Klavertje Vier",
    "wof:placetype":"venue"
},
  "geometry": {"coordinates":[3.7019300461,51.0577278137],"type":"Point"}
}