{
  "type": "Feature",
  "properties": {
    "iso:country":"BE",
    "sg:address":"Rue Pierreuse 7",
    "sg:city":"Li\u00c8ge",
    "sg:orig_category":"Avocats and conseillers juridiques",
    "sg:phone":"+32 4 221 18 04",
    "sg:postcode":"4000",
    "sg:province":"Li\u00e8ge",
    "wof:name":"A. Lambert",
    "wof:placetype":"venue"
},
  "geometry": {"coordinates":[5.5738329887,50.6465606689],"type":"Point"}
}