{
  "type": "Feature",
  "properties": {
    "iso:country":"BE",
    "sg:address":"Rue Pont D'avroy 29",
    "sg:city":"Li\u00e8ge 1",
    "sg:classifiers":[
        {
            "category":"Health Services",
            "subcategory":"Dentist",
            "type":"Services"
        }
    ],
    "sg:phone":"+32 4 223 34 49",
    "sg:postcode":"4000",
    "sg:province":"Li\u00e8ge",
    "wof:name":"Dratler R",
    "wof:placetype":"venue"
},
  "geometry": {"coordinates":[5.5697932243,50.6404037476],"type":"Point"}
}