{
  "type": "Feature",
  "properties": {
    "addr:full":"Rue De Beaumont 40 Charleroi Hainaut 6030",
    "addr:housenumber":"40",
    "addr:postcode":"6030",
    "addr:street":"Rue De Beaumont;Hainaut",
    "iso:country":"BE",
    "sg:address":"Rue De Beaumont 40",
    "sg:city":"Charleroi",
    "sg:orig_category":"Brood, gebak and snoepgoed",
    "sg:phone":"+32 71 51 60 16",
    "sg:postcode":"6030",
    "sg:province":"Hainaut",
    "wof:name":"P\u00c2tisserie Le Ballotin",
    "wof:placetype":"venue"
},
  "geometry": {"coordinates":[4.3958830833,50.4056816101],"type":"Point"}
}