{
  "type": "Feature",
  "properties": {
    "iso:country":"BE",
    "sg:address":"Torenstraat 13",
    "sg:city":"Lokeren",
    "sg:classifiers":[
        {
            "category":"Social Services",
            "type":"Services"
        }
    ],
    "sg:phone":"+32 9 348 80 00",
    "sg:postcode":"9160",
    "sg:province":"Oost-Vlaanderen",
    "wof:name":"Azymuth",
    "wof:placetype":"venue"
},
  "geometry": {"coordinates":[3.9913980961,51.105342865],"type":"Point"}
}