{
  "type": "Feature",
  "properties": {
    "iso:country":"BE",
    "sg:address":"Textielstraat 12",
    "sg:city":"Waregem",
    "sg:classifiers":[
        {
            "category":"Manufacturing",
            "subcategory":"Textiles",
            "type":"Manufacturing & Wholesale Goods"
        }
    ],
    "sg:phone":"+32 56 72 94 60",
    "sg:postcode":"8790",
    "sg:province":"West-Vlaanderen",
    "sg:tags":[
        "finishing"
    ],
    "wof:name":"Acratex Bvba",
    "wof:placetype":"venue"
},
  "geometry": {"coordinates":[3.3997499943,50.8583717346],"type":"Point"}
}