{
  "type": "Feature",
  "properties": {
    "addr:full":"Brandstraat 16 Lokeren Oost-Vlaanderen 9160",
    "addr:housenumber":"16",
    "addr:postcode":"9160",
    "addr:street":"Brandstraat",
    "iso:country":"BE",
    "sg:address":"Brandstraat 16",
    "sg:city":"Lokeren",
    "sg:classifiers":[
        {
            "category":"Professional",
            "subcategory":"Computer Services",
            "type":"Services"
        }
    ],
    "sg:phone":"+32 9 340 66 76",
    "sg:postcode":"9160",
    "sg:province":"Oost-Vlaanderen",
    "sg:tags":[
        "-",
        "processing",
        "data",
        "software"
    ],
    "wof:name":"Software Developments Nv",
    "wof:placetype":"venue"
},
  "geometry": {"coordinates":[4.0082421303,51.0822906494],"type":"Point"}
}