{
  "type": "Feature",
  "properties": {
    "iso:country":"BE",
    "sg:address":"Route De Villers 17",
    "sg:city":"Anthisnes",
    "sg:orig_category":"Betonnen bouwelementen Fab",
    "sg:phone":"+32 4 383 62 52",
    "sg:postcode":"4162",
    "sg:province":"Li\u00e8ge",
    "wof:name":"Jules Simon",
    "wof:placetype":"venue"
},
  "geometry": {"coordinates":[5.5004739761,50.4883041382],"type":"Point"}
}