{
  "type": "Feature",
  "properties": {
    "iso:country":"BE",
    "sg:address":"Stadionstraat 16",
    "sg:city":"Stekene",
    "sg:orig_category":"Studios photographiques. Equipement photographique",
    "sg:phone":"+32 3 779 88 98",
    "sg:postcode":"9190",
    "sg:province":"Oost-Vlaanderen",
    "wof:name":"Patrick Bassleer",
    "wof:placetype":"venue"
},
  "geometry": {"coordinates":[4.0419020653,51.2056503296],"type":"Point"}
}