{
  "type": "Feature",
  "properties": {
    "iso:country":"BE",
    "sg:address":"Rue Des Corettes 36b",
    "sg:city":"Bertrix",
    "sg:orig_category":"Baby- and kinderkleding Babyspullen",
    "sg:phone":"+32 61 41 27 22",
    "sg:postcode":"6880",
    "sg:province":"Luxembourg",
    "wof:name":"Espace J",
    "wof:placetype":"venue"
},
  "geometry": {"coordinates":[5.2575669289,49.8544540405],"type":"Point"}
}