{
  "type": "Feature",
  "properties": {
    "iso:country":"BE",
    "sg:address":"Rue Destouvelles 41",
    "sg:city":"Bruxelles (schaerbeek)",
    "sg:classifiers":[
        {
            "category":"Taxi",
            "type":"Transportation"
        }
    ],
    "sg:phone":"+32 2 201 08 66",
    "sg:postcode":"1030",
    "sg:province":"Bruxelles-Capitale",
    "sg:tags":[
        "delivery",
        "van",
        "-"
    ],
    "wof:name":"Boughaz",
    "wof:placetype":"venue"
},
  "geometry": {"coordinates":[4.3618478775,50.8675689697],"type":"Point"}
}