{
  "type": "Feature",
  "properties": {
    "iso:country":"BE",
    "sg:address":"Emiel Van Dorenlaan 113",
    "sg:city":"Genk",
    "sg:orig_category":"HERSTELLING ELEKTRISCHE HUISHOUDAPPARATEN",
    "sg:phone":"+32 89 38 38 72",
    "sg:postcode":"3600",
    "sg:province":"Limburg",
    "wof:name":"Vincenzo Rizzo",
    "wof:placetype":"venue"
},
  "geometry": {"coordinates":[5.5133991241,50.9816551208],"type":"Point"}
}