{
  "type": "Feature",
  "properties": {
    "addr:full":"Kapellestraat 26 Oostende West-Vlaanderen 8400",
    "addr:housenumber":"26",
    "addr:postcode":"8400",
    "addr:street":"Kapellestraat",
    "iso:country":"BE",
    "sg:address":"Kapellestraat 26",
    "sg:city":"Oostende",
    "sg:orig_category":"V\u00eatements",
    "sg:phone":"+32 59 80 25 85",
    "sg:postcode":"8400",
    "sg:province":"West-Vlaanderen",
    "wof:name":"Huis Skin",
    "wof:placetype":"venue"
},
  "geometry": {"coordinates":[2.9188380241,51.2305450439],"type":"Point"}
}