{
  "type": "Feature",
  "properties": {
    "iso:country":"BE",
    "sg:address":"Machelgemstraat 66",
    "sg:city":"Zwalm",
    "sg:orig_category":"Catering and organisatie van feesten",
    "sg:phone":"+32 9 360 41 37",
    "sg:postcode":"9630",
    "sg:province":"Oost-Vlaanderen",
    "wof:name":"Joost De Bremme",
    "wof:placetype":"venue"
},
  "geometry": {"coordinates":[3.7642710209,50.8624382019],"type":"Point"}
}