{
  "type": "Feature",
  "properties": {
    "addr:full":"Maurits Sabbestraat 114b101 Mechelen Antwerpen 2800",
    "addr:housenumber":"114b101",
    "addr:postcode":"2800",
    "addr:street":"Maurits Sabbestraat",
    "iso:country":"BE",
    "sg:address":"Maurits Sabbestraat 114b101",
    "sg:city":"Mechelen",
    "sg:orig_category":"Charpentes and couvertures",
    "sg:phone":"+32 15 21 27 32",
    "sg:postcode":"2800",
    "sg:province":"Antwerpen",
    "wof:name":"Dakwerken Wouters",
    "wof:placetype":"venue"
},
  "geometry": {"coordinates":[4.4745960236,51.0372619629],"type":"Point"}
}