{
  "type": "Feature",
  "properties": {
    "iso:country":"BE",
    "sg:address":"Steenweg Op Weelde 12",
    "sg:city":"Merksplas",
    "sg:orig_category":"Eleveurs and marchands de porcs",
    "sg:phone":"+32 14 63 41 60",
    "sg:postcode":"2330",
    "sg:province":"Antwerpen",
    "wof:name":"Gustaaf Aerts",
    "wof:placetype":"venue"
},
  "geometry": {"coordinates":[4.8776011467,51.3780860901],"type":"Point"}
}