{
  "type": "Feature",
  "properties": {
    "addr:full":"Lichterveldestraat 18 Wingene West-Vlaanderen 8750",
    "addr:housenumber":"18",
    "addr:postcode":"8750",
    "addr:street":"Lichterveldestraat",
    "iso:country":"BE",
    "sg:address":"Lichterveldestraat 18",
    "sg:city":"Wingene",
    "sg:orig_category":"Gespecialiseerde residenti\u00eble bouw Woningbouw",
    "sg:phone":"+32 51 61 22 41",
    "sg:postcode":"8750",
    "sg:province":"West-Vlaanderen",
    "wof:name":"Vacama",
    "wof:placetype":"venue"
},
  "geometry": {"coordinates":[3.2088820934,51.0363540649],"type":"Point"}
}