{
  "type": "Feature",
  "properties": {
    "iso:country":"BE",
    "sg:address":"Reigerstraat 32",
    "sg:city":"Roeselare",
    "sg:orig_category":"Services de Nettoyage and de D\u00e9sinfection",
    "sg:phone":"+32 51 22 30 91",
    "sg:postcode":"8800",
    "sg:province":"West-Vlaanderen",
    "wof:name":"A.c. Asseloos",
    "wof:placetype":"venue"
},
  "geometry": {"coordinates":[3.1059250832,50.9595451355],"type":"Point"}
}