{
  "type": "Feature",
  "properties": {
    "addr:full":"Heldenplein 2 Vilvoorde Vlaams-Brabant 1800",
    "addr:housenumber":"2",
    "addr:postcode":"1800",
    "addr:street":"Heldenplein",
    "iso:country":"BE",
    "sg:address":"Heldenplein 2",
    "sg:city":"Vilvoorde",
    "sg:classifiers":[
        {
            "category":"Bars & Pubs",
            "subcategory":"Wine Bar",
            "type":"Food & Drink"
        }
    ],
    "sg:phone":"+32 2 251 00 99",
    "sg:postcode":"1800",
    "sg:province":"Vlaams-Brabant",
    "sg:tags":[
        "caf\u00c9s",
        "restaurants"
    ],
    "wof:name":"Caf\u00c9 Bij De Ket",
    "wof:placetype":"venue"
},
  "geometry": {"coordinates":[4.4251060486,50.9263877869],"type":"Point"}
}