{
  "type": "Feature",
  "properties": {
    "iso:country":"BE",
    "sg:address":"Maurice Lagravi\u00c8restraat 45",
    "sg:city":"Bredene",
    "sg:orig_category":"Diverse organisaties and verenigingen",
    "sg:phone":"+32 59 32 32 12",
    "sg:postcode":"8450",
    "sg:province":"West-Vlaanderen",
    "wof:name":"Animal First Dierenbesch.",
    "wof:placetype":"venue"
},
  "geometry": {"coordinates":[2.9660260677,51.2240600586],"type":"Point"}
}