{
  "type": "Feature",
  "properties": {
    "iso:country":"BE",
    "sg:address":"Vredelaan 33",
    "sg:city":"Zemst (weerde)",
    "sg:orig_category":"Non-Classified Establishments",
    "sg:phone":"+32 15 62 08 87",
    "sg:postcode":"1982",
    "sg:province":"Vlaams-Brabant",
    "wof:name":"Defi International Belgium Bvba",
    "wof:placetype":"venue"
},
  "geometry": {"coordinates":[4.4780859947,50.9747962952],"type":"Point"}
}