{
  "type": "Feature",
  "properties": {
    "addr:full":"Kuurnsestraat 12 Harelbeke (hulste) West-Vlaanderen 8531",
    "addr:housenumber":"12",
    "addr:postcode":"8531",
    "addr:street":"Kuurnsestraat",
    "iso:country":"BE",
    "sg:address":"Kuurnsestraat 12",
    "sg:city":"Harelbeke (hulste)",
    "sg:classifiers":[
        {
            "category":"Professional",
            "subcategory":"Engineering",
            "type":"Services"
        }
    ],
    "sg:phone":"+32 56 68 00 07",
    "sg:postcode":"8531",
    "sg:province":"West-Vlaanderen",
    "sg:tags":[
        "-"
    ],
    "wof:name":"Fff Design",
    "wof:placetype":"venue"
},
  "geometry": {"coordinates":[3.298402071,50.8807258606],"type":"Point"}
}