{
  "type": "Feature",
  "properties": {
    "addr:full":"Avenue Du Gris Moulin 39 La Hulpe Brabant Wallon 1310",
    "addr:housenumber":"39",
    "addr:postcode":"1310",
    "addr:street":"Avenue Du Gris Moulin",
    "iso:country":"BE",
    "sg:address":"Avenue Du Gris Moulin 39",
    "sg:city":"La Hulpe",
    "sg:orig_category":"D\u00e9corateurs d'int\u00e9rieur",
    "sg:phone":"+32 2 653 25 56",
    "sg:postcode":"1310",
    "sg:province":"Brabant Wallon",
    "wof:name":"Paul Nannetti",
    "wof:placetype":"venue"
},
  "geometry": {"coordinates":[4.4762558937,50.7304077148],"type":"Point"}
}