{
  "type": "Feature",
  "properties": {
    "iso:country":"BE",
    "sg:address":"Blokellestraat 61",
    "sg:city":"Zwevegem",
    "sg:orig_category":"Installation de menuiserie m\u00e9tallique",
    "sg:phone":"+32 56 75 84 56",
    "sg:postcode":"8550",
    "sg:province":"West-Vlaanderen",
    "wof:name":"Dirk Bettens",
    "wof:placetype":"venue"
},
  "geometry": {"coordinates":[3.3474481106,50.8134841919],"type":"Point"}
}