{
  "type": "Feature",
  "properties": {
    "addr:full":"Gullegemsestraat 148 Ledegem West-Vlaanderen 8880",
    "addr:housenumber":"148",
    "addr:postcode":"8880",
    "addr:street":"Gullegemsestraat",
    "iso:country":"BE",
    "sg:address":"Gullegemsestraat 148",
    "sg:city":"Ledegem",
    "sg:orig_category":"Poissonniers and \u00e9caillers",
    "sg:phone":"+32 56 50 11 06",
    "sg:postcode":"8880",
    "sg:province":"West-Vlaanderen",
    "wof:name":"Pascal Cinjaere",
    "wof:placetype":"venue"
},
  "geometry": {"coordinates":[3.1840670109,50.8669776917],"type":"Point"}
}