{
  "type": "Feature",
  "properties": {
    "addr:full":"Bosstraat 62 Maaseik Limburg 3680",
    "addr:housenumber":"62",
    "addr:postcode":"3680",
    "addr:street":"Bosstraat",
    "iso:country":"BE",
    "sg:address":"Bosstraat 62",
    "sg:city":"Maaseik",
    "sg:classifiers":[
        {
            "category":"Cafe",
            "type":"Food & Drink"
        }
    ],
    "sg:phone":"+32 89 81 15 20",
    "sg:postcode":"3680",
    "sg:province":"Limburg",
    "sg:tags":[
        "snack-bars"
    ],
    "wof:name":"Aubergine",
    "wof:placetype":"venue"
},
  "geometry": {"coordinates":[5.7878851891,51.0955314636],"type":"Point"}
}