{
  "type": "Feature",
  "properties": {
    "iso:country":"BE",
    "sg:address":"Engelstraat 83",
    "sg:city":"Ichtegem",
    "sg:classifiers":[
        {
            "category":"Personal",
            "subcategory":"Nail Salon",
            "type":"Services"
        }
    ],
    "sg:phone":"+32 51 58 97 40",
    "sg:postcode":"8480",
    "sg:province":"West-Vlaanderen",
    "sg:tags":[
        "pedicure"
    ],
    "wof:name":"Vogue",
    "wof:placetype":"venue"
},
  "geometry": {"coordinates":[3.0176959038,51.094165802],"type":"Point"}
}