{
  "type": "Feature",
  "properties": {
    "iso:country":"BE",
    "sg:address":"Van Benedenlaan 19",
    "sg:city":"Mechelen",
    "sg:orig_category":"M\u00e9decins and sp\u00e9cialistes",
    "sg:phone":"+32 15 41 16 24",
    "sg:postcode":"2800",
    "sg:province":"Antwerpen",
    "wof:name":"Jacques Debois",
    "wof:placetype":"venue"
},
  "geometry": {"coordinates":[4.4754638672,51.0214118958],"type":"Point"}
}