{
  "type": "Feature",
  "properties": {
    "addr:full":"Kortrijksesteenweg 215 Harelbeke West-Vlaanderen 8530",
    "addr:housenumber":"215",
    "addr:postcode":"8530",
    "addr:street":"Kortrijksesteenweg",
    "iso:country":"BE",
    "sg:address":"Kortrijksesteenweg 215",
    "sg:city":"Harelbeke",
    "sg:classifiers":[
        {
            "category":"Home & Garden",
            "subcategory":"Building Materials",
            "type":"Retail Goods"
        }
    ],
    "sg:phone":"+32 56 70 60 09",
    "sg:postcode":"8530",
    "sg:province":"West-Vlaanderen",
    "sg:tags":[
        "-",
        "fireplace",
        "open",
        "ornamental"
    ],
    "wof:name":"Manhaeve-demoor",
    "wof:placetype":"venue"
},
  "geometry": {"coordinates":[3.2967529297,50.8461837769],"type":"Point"}
}