{
  "type": "Feature",
  "properties": {
    "addr:full":"Place Albert Ier 15 Malmedy Li\u00e8ge 4960",
    "addr:housenumber":"15",
    "addr:postcode":"4960",
    "addr:street":"Place Albert Ier",
    "iso:country":"BE",
    "sg:address":"Place Albert Ier 15",
    "sg:city":"Malmedy",
    "sg:orig_category":"Immobili\u00ebnkantoren Landmeters",
    "sg:phone":"+32 80 79 98 18",
    "sg:postcode":"4960",
    "sg:province":"Li\u00e8ge",
    "wof:name":"P & R Immo",
    "wof:placetype":"venue"
},
  "geometry": {"coordinates":[6.0294837952,50.4254989624],"type":"Point"}
}