{
  "type": "Feature",
  "properties": {
    "addr:full":"Avenue E. De Thibault 35 Etterbeek Bruxelles-Capitale 1040",
    "addr:housenumber":"35",
    "addr:postcode":"1040",
    "addr:street":"Avenue E. De Thibault",
    "iso:country":"BE",
    "sg:address":"Avenue E. De Thibault 35",
    "sg:city":"Etterbeek",
    "sg:orig_category":"Farmaceutische producten Gh",
    "sg:phone":"+32 2 735 43 40",
    "sg:postcode":"1040",
    "sg:province":"Bruxelles-Capitale",
    "wof:name":"Kerckaert Dental Equipment",
    "wof:placetype":"venue"
},
  "geometry": {"coordinates":[4.397110939,50.8342590332],"type":"Point"}
}