{
  "type": "Feature",
  "properties": {
    "iso:country":"BE",
    "sg:address":"Vondelstraat 18",
    "sg:city":"Antwerpen",
    "sg:orig_category":"Biens d'occasion",
    "sg:phone":"+32 3 233 36 30",
    "sg:postcode":"2060",
    "sg:province":"Antwerpen",
    "wof:name":"Huis Erna-tex",
    "wof:placetype":"venue"
},
  "geometry": {"coordinates":[4.4165849686,51.2244758606],"type":"Point"}
}