{
  "type": "Feature",
  "properties": {
    "addr:full":"Stationsstraat 111 Berlaar Antwerpen 2590",
    "addr:housenumber":"111",
    "addr:postcode":"2590",
    "addr:street":"Stationsstraat",
    "iso:country":"BE",
    "sg:address":"Stationsstraat 111",
    "sg:city":"Berlaar",
    "sg:classifiers":[
        {
            "category":"Personal",
            "subcategory":"Beauty Salon",
            "type":"Services"
        }
    ],
    "sg:phone":"+32 3 464 21 32",
    "sg:postcode":"2590",
    "sg:province":"Antwerpen",
    "sg:tags":[
        "lady",
        "-",
        "hairdressing"
    ],
    "wof:name":"Impro Vision",
    "wof:placetype":"venue"
},
  "geometry": {"coordinates":[4.6448941231,51.1147918701],"type":"Point"}
}