{
  "type": "Feature",
  "properties": {
    "addr:full":"F. Istasstraat 12 Landen Vlaams-Brabant 3404",
    "addr:housenumber":"12",
    "addr:postcode":"3404",
    "addr:street":"F. Istasstraat",
    "iso:country":"BE",
    "sg:address":"F. Istasstraat 12",
    "sg:city":"Landen",
    "sg:orig_category":"Rundveehouders",
    "sg:phone":"+32 11 88 17 82",
    "sg:postcode":"3404",
    "sg:province":"Vlaams-Brabant",
    "wof:name":"Boonen Jean & Alfons",
    "wof:placetype":"venue"
},
  "geometry": {"coordinates":[5.0787191391,50.7768478394],"type":"Point"}
}