{
  "type": "Feature",
  "properties": {
    "addr:full":"Van Overbekelaan 231b25 Ganshoren/ganshoren Bruxelles-Capitale 1083",
    "addr:housenumber":"231b25",
    "addr:postcode":"1083",
    "addr:street":"Van Overbekelaan",
    "iso:country":"BE",
    "sg:address":"Van Overbekelaan 231b25",
    "sg:city":"Ganshoren/ganshoren",
    "sg:orig_category":"Sociale huisvestingsmaatschappijen",
    "sg:phone":"+32 2 426 23 94",
    "sg:postcode":"1083",
    "sg:province":"Bruxelles-Capitale",
    "wof:name":"Les Villas De Ganshoren",
    "wof:placetype":"venue"
},
  "geometry": {"coordinates":[4.3074631691,50.8755302429],"type":"Point"}
}