{
  "type": "Feature",
  "properties": {
    "addr:full":"Pierre Sorellaan 26 Koksijde West-Vlaanderen 8670",
    "addr:housenumber":"26",
    "addr:postcode":"8670",
    "addr:street":"Sorellaan",
    "iso:country":"BE",
    "sg:address":"Pierre Sorellaan 26",
    "sg:city":"Koksijde",
    "sg:orig_category":"Kapsalons Mobiele kappers",
    "sg:phone":"+32 58 51 17 39",
    "sg:postcode":"8670",
    "sg:province":"West-Vlaanderen",
    "wof:name":"Coiffure Danny",
    "wof:placetype":"venue"
},
  "geometry": {"coordinates":[2.6378629208,51.1192169189],"type":"Point"}
}