{
  "type": "Feature",
  "properties": {
    "addr:full":"Rue Du Page 20 Bruxelles (ixelles) Bruxelles-Capitale 1050",
    "addr:housenumber":"20",
    "addr:postcode":"1050",
    "addr:street":"Rue Du Page",
    "iso:country":"BE",
    "sg:address":"Rue Du Page 20",
    "sg:city":"Bruxelles (ixelles)",
    "sg:classifiers":[
        {
            "category":"Professional",
            "subcategory":"Testing Lab",
            "type":"Services"
        }
    ],
    "sg:phone":"+32 2 538 20 97",
    "sg:postcode":"1050",
    "sg:province":"Bruxelles-Capitale",
    "sg:tags":[
        "chemist"
    ],
    "wof:name":"Frenkel J-m",
    "wof:placetype":"venue"
},
  "geometry": {"coordinates":[4.3593430519,50.8236274719],"type":"Point"}
}