{
  "type": "Feature",
  "properties": {
    "addr:full":"Oswald Ponettestraat 68 Ronse/renaix Oost-Vlaanderen 9600",
    "addr:housenumber":"68",
    "addr:postcode":"9600",
    "addr:street":"Ponettestraat",
    "iso:country":"BE",
    "sg:address":"Oswald Ponettestraat 68",
    "sg:city":"Ronse/renaix",
    "sg:orig_category":"Elektrische installaties voor woningen Winkelinrichting and handelsuitrusting Gh",
    "sg:phone":"+32 55 21 10 60",
    "sg:postcode":"9600",
    "sg:province":"Oost-Vlaanderen",
    "wof:name":"Francis Wallemacq",
    "wof:placetype":"venue"
},
  "geometry": {"coordinates":[3.5992999077,50.7470397949],"type":"Point"}
}