{
  "type": "Feature",
  "properties": {
    "iso:country":"BE",
    "sg:address":"Kerkstraat 18",
    "sg:city":"Landen",
    "sg:classifiers":[
        {
            "category":"Health Services",
            "subcategory":"Dentist",
            "type":"Services"
        }
    ],
    "sg:phone":"+32 11 88 23 74",
    "sg:postcode":"3400",
    "sg:province":"Vlaams-Brabant",
    "wof:name":"Herbots E",
    "wof:placetype":"venue"
},
  "geometry": {"coordinates":[5.0808157921,50.7555503845],"type":"Point"}
}