{
  "type": "Feature",
  "properties": {
    "iso:country":"BE",
    "sg:address":"Rue Du Quesnoy 63",
    "sg:city":"Dour (wih\u00e9ries)",
    "sg:classifiers":[
        {
            "category":"Manufacturing",
            "subcategory":"Furniture",
            "type":"Manufacturing & Wholesale Goods"
        }
    ],
    "sg:phone":"+32 65 63 10 00",
    "sg:postcode":"7370",
    "sg:province":"Hainaut",
    "sg:tags":[
        "made",
        "-",
        "custom"
    ],
    "wof:name":"Stievenart Cl",
    "wof:placetype":"venue"
},
  "geometry": {"coordinates":[3.7589070797,50.3854827881],"type":"Point"}
}