{
  "type": "Feature",
  "properties": {
    "addr:full":"Geluwestraat 18 Zonnebeke West-Vlaanderen 8980",
    "addr:housenumber":"18",
    "addr:postcode":"8980",
    "addr:street":"Geluwestraat",
    "iso:country":"BE",
    "sg:address":"Geluwestraat 18",
    "sg:city":"Zonnebeke",
    "sg:orig_category":"Verplichte sociale verzekeringen",
    "sg:phone":"+32 57 46 82 66",
    "sg:postcode":"8980",
    "sg:province":"West-Vlaanderen",
    "wof:name":"Christelijke Mutualiteit",
    "wof:placetype":"venue"
},
  "geometry": {"coordinates":[3.0261530876,50.847618103],"type":"Point"}
}