{
  "type": "Feature",
  "properties": {
    "addr:full":"Jagerij 122 Oudenaarde Oost-Vlaanderen 9700",
    "addr:housenumber":"122",
    "addr:postcode":"9700",
    "addr:street":"Jagerij",
    "iso:country":"BE",
    "sg:address":"Jagerij 122",
    "sg:city":"Oudenaarde",
    "sg:orig_category":"Caf\u00e9s Pensions Vakantiehuizen",
    "sg:phone":"+32 55 45 63 00",
    "sg:postcode":"9700",
    "sg:province":"Oost-Vlaanderen",
    "wof:name":"Taverne 't Materke",
    "wof:placetype":"venue"
},
  "geometry": {"coordinates":[3.6795198917,50.8430213928],"type":"Point"}
}