{
  "type": "Feature",
  "properties": {
    "iso:country":"BE",
    "sg:address":"Rue Du Haut Donjon 8",
    "sg:city":"Leuze-en-hainaut (pipaix)",
    "sg:classifiers":[
        {
            "category":"Retail",
            "subcategory":"Auto Repair",
            "type":"Services"
        }
    ],
    "sg:phone":"+32 69 66 33 51",
    "sg:postcode":"7904",
    "sg:province":"Hainaut",
    "sg:tags":[
        "automobile-body"
    ],
    "wof:name":"Ostyn M",
    "wof:placetype":"venue"
},
  "geometry": {"coordinates":[3.5873920918,50.5804328918],"type":"Point"}
}