{
  "type": "Feature",
  "properties": {
    "iso:country":"BE",
    "sg:address":"Heirstraat 10",
    "sg:city":"Dendermonde",
    "sg:orig_category":"Banques and organismes de cr\u00e9dit",
    "sg:phone":"+32 52 21 47 57",
    "sg:postcode":"9200",
    "sg:province":"Oost-Vlaanderen",
    "wof:name":"Kbc",
    "wof:placetype":"venue"
},
  "geometry": {"coordinates":[4.0581598282,51.0292205811],"type":"Point"}
}