{
  "type": "Feature",
  "properties": {
    "iso:country":"BE",
    "sg:address":"Rue Alphonse Collin 11",
    "sg:city":"Rixensart",
    "sg:orig_category":"Cr\u00e8ches and garderies d'enfants",
    "sg:phone":"+32 2 653 09 93",
    "sg:postcode":"1330",
    "sg:province":"Brabant Wallon",
    "wof:name":"Cr\u00c8che La Ribambelle",
    "wof:placetype":"venue"
},
  "geometry": {"coordinates":[4.5333919525,50.7111167908],"type":"Point"}
}