{
  "type": "Feature",
  "properties": {
    "addr:full":"Rue Am\u00c9ricaine 136 Elsene/ixelles Bruxelles-Capitale 1050",
    "addr:housenumber":"136",
    "addr:postcode":"1050",
    "addr:street":"Rue Ame\u0301Ricaine",
    "iso:country":"BE",
    "sg:address":"Rue Am\u00c9ricaine 136",
    "sg:city":"Elsene/ixelles",
    "sg:orig_category":"Enseignement maternel and primaire",
    "sg:phone":"+32 2 515 61 11",
    "sg:postcode":"1050",
    "sg:province":"Bruxelles-Capitale",
    "wof:name":"Ecole Fond. Communale",
    "wof:placetype":"venue"
},
  "geometry": {"coordinates":[4.3613610268,50.8226699829],"type":"Point"}
}