{
  "type": "Feature",
  "properties": {
    "iso:country":"BE",
    "sg:address":"Bruggestraat 218",
    "sg:city":"Ingelmunster",
    "sg:orig_category":"DIVERSE RECREATIEVE ACTIVITEITEN Dierentuinen, botanische tuinen, sterrenwachten and natuurreservate",
    "sg:phone":"+32 51 30 15 42",
    "sg:postcode":"8770",
    "sg:province":"West-Vlaanderen",
    "wof:name":"Dierenpark Aviflora",
    "wof:placetype":"venue"
},
  "geometry": {"coordinates":[3.2512869835,50.9320220947],"type":"Point"}
}