{
  "type": "Feature",
  "properties": {
    "addr:full":"Dieweg 137 Bruxelles (uccle) Bruxelles-Capitale 1180",
    "addr:housenumber":"137",
    "addr:postcode":"1180",
    "addr:street":"Dieweg",
    "iso:country":"BE",
    "sg:address":"Dieweg 137",
    "sg:city":"Bruxelles (uccle)",
    "sg:classifiers":[
        {
            "category":"Real Estate",
            "subcategory":"Architect",
            "type":"Services"
        }
    ],
    "sg:phone":"+32 2 374 11 61",
    "sg:postcode":"1180",
    "sg:province":"Bruxelles-Capitale",
    "wof:name":"Verdussen Ph",
    "wof:placetype":"venue"
},
  "geometry": {"coordinates":[4.3501858711,50.7966499329],"type":"Point"}
}