{
  "type": "Feature",
  "properties": {
    "iso:country":"BE",
    "sg:address":"Rue Neuve 15",
    "sg:city":"Gr\u00e2ce-hollogne (hollogne-aux-pierres)",
    "sg:classifiers":[
        {
            "category":"Education",
            "subcategory":"Music School",
            "type":"Public Place"
        }
    ],
    "sg:phone":"+32 4 233 16 46",
    "sg:postcode":"4460",
    "sg:province":"Li\u00e8ge",
    "sg:tags":[
        "-",
        "teacher",
        "private"
    ],
    "wof:name":"Cornet F",
    "wof:placetype":"venue"
},
  "geometry": {"coordinates":[5.4749407768,50.6298599243],"type":"Point"}
}