{
  "type": "Feature",
  "properties": {
    "iso:country":"BE",
    "sg:address":"Ronsesestraat 125",
    "sg:city":"Brakel (opbrakel)",
    "sg:classifiers":[
        {
            "category":"Home & Garden",
            "subcategory":"Building Materials",
            "type":"Retail Goods"
        }
    ],
    "sg:phone":"+32 55 42 26 63",
    "sg:postcode":"9660",
    "sg:province":"Oost-Vlaanderen",
    "sg:tags":[
        "veranda"
    ],
    "wof:name":"Alvama",
    "wof:placetype":"venue"
},
  "geometry": {"coordinates":[3.7642250061,50.8031082153],"type":"Point"}
}