{
  "type": "Feature",
  "properties": {
    "addr:full":"Mechelseweg 21 Aalst (baardegem) Oost-Vlaanderen 9310",
    "addr:housenumber":"21",
    "addr:postcode":"9310",
    "addr:street":"Mechelseweg",
    "iso:country":"BE",
    "sg:address":"Mechelseweg 21",
    "sg:city":"Aalst (baardegem)",
    "sg:classifiers":[
        {
            "category":"Building & Trades",
            "subcategory":"Construction",
            "type":"Services"
        }
    ],
    "sg:phone":"+32 52 35 72 71",
    "sg:postcode":"9310",
    "sg:province":"Oost-Vlaanderen",
    "sg:tags":[
        "installation",
        "-",
        "central",
        "heating"
    ],
    "wof:name":"Blindeman Luc Bvba",
    "wof:placetype":"venue"
},
  "geometry": {"coordinates":[4.1369919777,50.9563064575],"type":"Point"}
}