{
  "type": "Feature",
  "properties": {
    "addr:full":"Avenue Max Buset 38 La Louvi\u00c8re Hainaut 7100",
    "addr:housenumber":"38",
    "addr:postcode":"7100",
    "addr:street":"Avenue Max Buset",
    "iso:country":"BE",
    "sg:address":"Avenue Max Buset 38",
    "sg:city":"La Louvi\u00c8re",
    "sg:orig_category":"Paramedische behandelingen",
    "sg:phone":"+32 64 23 87 71",
    "sg:postcode":"7100",
    "sg:province":"Hainaut",
    "wof:name":"Au Fil Des Jours",
    "wof:placetype":"venue"
},
  "geometry": {"coordinates":[4.2062191963,50.4786758423],"type":"Point"}
}