{
  "type": "Feature",
  "properties": {
    "addr:full":"Broederminstraat 15 Antwerpen Antwerpen 2018",
    "addr:housenumber":"15",
    "addr:postcode":"2018",
    "addr:street":"Broederminstraat",
    "iso:country":"BE",
    "sg:address":"Broederminstraat 15",
    "sg:city":"Antwerpen",
    "sg:orig_category":"Kapsalons",
    "sg:phone":"+32 3 238 46 61",
    "sg:postcode":"2018",
    "sg:province":"Antwerpen",
    "wof:name":"Coiffure Lisy",
    "wof:placetype":"venue"
},
  "geometry": {"coordinates":[4.3935160637,51.2029418945],"type":"Point"}
}