{
  "type": "Feature",
  "properties": {
    "iso:country":"BE",
    "sg:address":"Quai De Rome 5b81",
    "sg:city":"Li\u00c8ge",
    "sg:orig_category":"M\u00e9decins and sp\u00e9cialistes",
    "sg:phone":"+32 4 253 30 42",
    "sg:postcode":"4000",
    "sg:province":"Li\u00e8ge",
    "wof:name":"Jean-claude Saint-georges",
    "wof:placetype":"venue"
},
  "geometry": {"coordinates":[5.5739088058,50.6261634827],"type":"Point"}
}