{
  "type": "Feature",
  "properties": {
    "addr:full":"Lange Kroonstraat 193 Boechout Antwerpen 2530",
    "addr:housenumber":"193",
    "addr:postcode":"2530",
    "addr:street":"Lange Kroonstraat",
    "iso:country":"BE",
    "sg:address":"Lange Kroonstraat 193",
    "sg:city":"Boechout",
    "sg:orig_category":"Woningbouw",
    "sg:phone":"+32 3 455 64 15",
    "sg:postcode":"2530",
    "sg:province":"Antwerpen",
    "wof:name":"Van Hoylandt R.",
    "wof:placetype":"venue"
},
  "geometry": {"coordinates":[4.4852108955,51.166519165],"type":"Point"}
}