{
  "type": "Feature",
  "properties": {
    "addr:full":"Leuvensesteenweg 685 Mechelen Antwerpen 2812",
    "addr:housenumber":"685",
    "addr:postcode":"2812",
    "addr:street":"Leuvensesteenweg",
    "iso:country":"BE",
    "sg:address":"Leuvensesteenweg 685",
    "sg:city":"Mechelen",
    "sg:classifiers":[
        {
            "category":"Restaurant",
            "type":"Food & Drink"
        }
    ],
    "sg:phone":"+32 15 41 16 92",
    "sg:postcode":"2812",
    "sg:province":"Antwerpen",
    "wof:name":"'t Wit Huizeke",
    "wof:placetype":"venue"
},
  "geometry": {"coordinates":[4.5251698494,50.9989585876],"type":"Point"}
}