{
  "type": "Feature",
  "properties": {
    "addr:full":"Joris De Leeuwstraat 16 Box 1 Machelen Vlaams-Brabant 1830",
    "addr:housenumber":"16;1",
    "addr:postcode":"1830",
    "addr:street":"Joris De Leeuwstraat;Box",
    "iso:country":"BE",
    "sg:address":"Joris De Leeuwstraat 16 Box 1",
    "sg:city":"Machelen",
    "sg:classifiers":[
        {
            "category":"Communications",
            "type":"Services"
        }
    ],
    "sg:phone":"+32 2 253 36 64",
    "sg:postcode":"1830",
    "sg:province":"Vlaams-Brabant",
    "sg:tags":[
        "translator"
    ],
    "wof:name":"Eureka Business Services Bvba",
    "wof:placetype":"venue"
},
  "geometry": {"coordinates":[4.4501547813,50.9187927246],"type":"Point"}
}