{
  "type": "Feature",
  "properties": {
    "iso:country":"BE",
    "sg:address":"Godfried Kurthstraat 1a Box 6",
    "sg:city":"Asse",
    "sg:classifiers":[
        {
            "category":"Professional",
            "subcategory":"Computer Services",
            "type":"Services"
        }
    ],
    "sg:phone":"+32 2 452 22 96",
    "sg:postcode":"1730",
    "sg:province":"Vlaams-Brabant",
    "sg:tags":[
        "-",
        "processing",
        "data",
        "software"
    ],
    "wof:name":"Aikon Bvba",
    "wof:placetype":"venue"
},
  "geometry": {"coordinates":[4.1932821274,50.9139938354],"type":"Point"}
}