{
  "type": "Feature",
  "properties": {
    "iso:country":"BE",
    "sg:address":"Diesterstraat 111",
    "sg:city":"Tessenderlo",
    "sg:orig_category":"Pain, p\u00e2tisseries and confiseries",
    "sg:phone":"+32 13 67 53 52",
    "sg:postcode":"3980",
    "sg:province":"Limburg",
    "wof:name":"Van Decraen Crista",
    "wof:placetype":"venue"
},
  "geometry": {"coordinates":[5.0891838074,51.0617103577],"type":"Point"}
}