{
  "type": "Feature",
  "properties": {
    "addr:full":"De Daries 47 Arendonk Antwerpen 2370",
    "addr:housenumber":"47",
    "addr:postcode":"2370",
    "addr:street":"De Daries",
    "iso:country":"BE",
    "sg:address":"De Daries 47",
    "sg:city":"Arendonk",
    "sg:classifiers":[
        {
            "category":"Food & Beverages",
            "subcategory":"Chocolate",
            "type":"Retail Goods"
        }
    ],
    "sg:phone":"+32 14 67 32 95",
    "sg:postcode":"2370",
    "sg:province":"Antwerpen",
    "sg:tags":[
        "confectionery",
        "-"
    ],
    "wof:name":"Caramel",
    "wof:placetype":"venue"
},
  "geometry": {"coordinates":[5.0799121857,51.3190994263],"type":"Point"}
}