{
  "type": "Feature",
  "properties": {
    "iso:country":"BE",
    "sg:address":"Waaslandlaan 5",
    "sg:city":"Lokeren",
    "sg:classifiers":[
        {
            "category":"Food & Beverages",
            "subcategory":"Groceries & Convenience Stores",
            "type":"Retail Goods"
        }
    ],
    "sg:phone":"+32 9 340 59 20",
    "sg:postcode":"9160",
    "sg:province":"Oost-Vlaanderen",
    "sg:tags":[
        "product",
        "related"
    ],
    "wof:name":"Confiserie Trefin Nv",
    "wof:placetype":"venue"
},
  "geometry": {"coordinates":[4.0117487907,51.1207046509],"type":"Point"}
}