{
  "type": "Feature",
  "properties": {
    "iso:country":"BE",
    "sg:address":"Bolderstraat 160 Box 3",
    "sg:city":"Riemst (valmeer)",
    "sg:classifiers":[
        {
            "category":"Retail",
            "subcategory":"Animal Services",
            "type":"Services"
        }
    ],
    "sg:phone":"+32 12 45 13 72",
    "sg:postcode":"3770",
    "sg:province":"Limburg",
    "sg:tags":[
        "grooming",
        "-",
        "dog"
    ],
    "wof:name":"Goofy",
    "wof:placetype":"venue"
},
  "geometry": {"coordinates":[5.5974469185,50.7895240784],"type":"Point"}
}