{
  "type": "Feature",
  "properties": {
    "addr:full":"Dorp Oost 26 Lochristi Oost-Vlaanderen 9080",
    "addr:housenumber":"26",
    "addr:postcode":"9080",
    "addr:street":"Dorp Oost",
    "iso:country":"BE",
    "sg:address":"Dorp Oost 26",
    "sg:city":"Lochristi",
    "sg:orig_category":"Bloemen and planten",
    "sg:phone":"+32 9 355 80 53",
    "sg:postcode":"9080",
    "sg:province":"Oost-Vlaanderen",
    "wof:name":"Naudis",
    "wof:placetype":"venue"
},
  "geometry": {"coordinates":[3.8359229565,51.0968437195],"type":"Point"}
}