{
  "type": "Feature",
  "properties": {
    "iso:country":"BE",
    "sg:address":"Pastoriestraat 23",
    "sg:city":"Nijlen (kessel)",
    "sg:orig_category":"Non-Classified Establishments",
    "sg:phone":"+32 3 480 11 74",
    "sg:postcode":"2560",
    "sg:province":"Antwerpen",
    "wof:name":"Vervoort Gebr",
    "wof:placetype":"venue"
},
  "geometry": {"coordinates":[4.6278848648,51.140663147],"type":"Point"}
}