{
  "type": "Feature",
  "properties": {
    "iso:country":"BE",
    "sg:address":"Rue De L\u00b4ath\u00c9n\u00c9e 60",
    "sg:city":"Tournai",
    "sg:orig_category":"Tijdelijke werkgelegenheid and uitzendkantoren",
    "sg:phone":"+32 69 25 33 40",
    "sg:postcode":"7500",
    "sg:province":"Hainaut",
    "wof:name":"T. Interim",
    "wof:placetype":"venue"
},
  "geometry": {"coordinates":[3.3960800171,50.6111297607],"type":"Point"}
}