{
  "type": "Feature",
  "properties": {
    "iso:country":"BE",
    "sg:address":"Schoolstraat 5",
    "sg:city":"Geraardsbergen",
    "sg:orig_category":"Sportclubs",
    "sg:phone":"+32 54 41 47 61",
    "sg:postcode":"9500",
    "sg:province":"Oost-Vlaanderen",
    "wof:name":"Ver. Duivenliefhebbers",
    "wof:placetype":"venue"
},
  "geometry": {"coordinates":[3.8493659496,50.7682647705],"type":"Point"}
}