{
  "type": "Feature",
  "properties": {
    "iso:country":"BE",
    "sg:address":"Onderbegen 32",
    "sg:city":"Gent",
    "sg:orig_category":"Antiquit\u00e9s",
    "sg:phone":"+32 9 225 16 07",
    "sg:postcode":"9000",
    "sg:province":"Oost-Vlaanderen",
    "wof:name":"Michel Verhaeghe",
    "wof:placetype":"venue"
},
  "geometry": {"coordinates":[3.71961689,51.0524139404],"type":"Point"}
}