{
  "type": "Feature",
  "properties": {
    "addr:full":"Lombaardenstraat 40 Leuven Vlaams-Brabant 3000",
    "addr:housenumber":"40",
    "addr:postcode":"3000",
    "addr:street":"Lombaardenstraat",
    "iso:country":"BE",
    "sg:address":"Lombaardenstraat 40",
    "sg:city":"Leuven",
    "sg:classifiers":[
        {
            "category":"Professional",
            "subcategory":"Computer Services",
            "type":"Services"
        }
    ],
    "sg:phone":"+32 16 23 64 50",
    "sg:postcode":"3000",
    "sg:province":"Vlaams-Brabant",
    "sg:tags":[
        "webdesign",
        "-",
        "internet"
    ],
    "wof:name":"Spoton Solutions",
    "wof:placetype":"venue"
},
  "geometry": {"coordinates":[4.7013998032,50.8840751648],"type":"Point"}
}