{
  "type": "Feature",
  "properties": {
    "addr:full":"Rue Col. Aviat. Daumerie 7 Brugelette Hainaut 7940",
    "addr:housenumber":"7",
    "addr:postcode":"7940",
    "addr:street":"Rue Col. Aviat. Daumerie;Hainaut",
    "iso:country":"BE",
    "sg:address":"Rue Col. Aviat. Daumerie 7",
    "sg:city":"Brugelette",
    "sg:orig_category":"Kansspelen",
    "sg:phone":"+32 68 45 44 08",
    "sg:postcode":"7940",
    "sg:province":"Hainaut",
    "wof:name":"Ladbroke",
    "wof:placetype":"venue"
},
  "geometry": {"coordinates":[3.8516790867,50.5948371887],"type":"Point"}
}