{
  "type": "Feature",
  "properties": {
    "addr:full":"Van Haelenstraat 45 Bornem Antwerpen 2880",
    "addr:housenumber":"45",
    "addr:postcode":"2880",
    "addr:street":"Van Haelenstraat",
    "iso:country":"BE",
    "sg:address":"Van Haelenstraat 45",
    "sg:city":"Bornem",
    "sg:orig_category":"Herstellingen and onderhoud van auto's Voertuigen",
    "sg:phone":"+32 3 889 03 35",
    "sg:postcode":"2880",
    "sg:province":"Antwerpen",
    "wof:name":"Garage Van Haelen",
    "wof:placetype":"venue"
},
  "geometry": {"coordinates":[4.2655591965,51.1030731201],"type":"Point"}
}