{
  "type": "Feature",
  "properties": {
    "addr:full":"Ingelmunstersestraat 21 Izegem West-Vlaanderen 8870",
    "addr:housenumber":"21",
    "addr:postcode":"8870",
    "addr:street":"Ingelmunstersestraat",
    "iso:country":"BE",
    "sg:address":"Ingelmunstersestraat 21",
    "sg:city":"Izegem",
    "sg:classifiers":[
        {
            "category":"Fast Food",
            "type":"Food & Drink"
        }
    ],
    "sg:phone":"+32 477 55 56 46",
    "sg:postcode":"8870",
    "sg:province":"West-Vlaanderen",
    "sg:tags":[
        "fried",
        "stand",
        "potato"
    ],
    "wof:name":"Brochetje ('t)",
    "wof:placetype":"venue"
},
  "geometry": {"coordinates":[3.2319200039,50.9239425659],"type":"Point"}
}