{
  "type": "Feature",
  "properties": {
    "iso:country":"BE",
    "sg:address":"Avenue De Jette 272",
    "sg:city":"Bruxelles (jette)",
    "sg:classifiers":[
        {
            "category":"Retail",
            "subcategory":"Repair Shop",
            "type":"Services"
        }
    ],
    "sg:phone":"+32 2 427 61 52",
    "sg:postcode":"1090",
    "sg:province":"Bruxelles-Capitale",
    "sg:tags":[
        "-",
        "clothing",
        "alteration"
    ],
    "wof:name":"Maison couture",
    "wof:placetype":"venue"
},
  "geometry": {"coordinates":[4.324657917,50.87134552],"type":"Point"}
}