{
  "type": "Feature",
  "properties": {
    "addr:full":"Wiekstraat 80 Genk Limburg 3600",
    "addr:housenumber":"80",
    "addr:postcode":"3600",
    "addr:street":"Wiekstraat",
    "iso:country":"BE",
    "sg:address":"Wiekstraat 80",
    "sg:city":"Genk",
    "sg:classifiers":[
        {
            "category":"Arena",
            "subcategory":"Sports Club",
            "type":"Entertainment"
        }
    ],
    "sg:phone":"+32 89 35 85 40",
    "sg:postcode":"3600",
    "sg:province":"Limburg",
    "sg:tags":[
        "terrain",
        "hors",
        "de",
        "installation",
        "sportifs"
    ],
    "wof:name":"Cobox 76",
    "wof:placetype":"venue"
},
  "geometry": {"coordinates":[5.4566068649,50.9636573792],"type":"Point"}
}