{
  "type": "Feature",
  "properties": {
    "addr:full":"Sint-amandsstraat 24 Grimbergen Vlaams-Brabant 1853",
    "addr:housenumber":"24",
    "addr:postcode":"1853",
    "addr:street":"Sint-Amandsstraat",
    "iso:country":"BE",
    "sg:address":"Sint-amandsstraat 24",
    "sg:city":"Grimbergen",
    "sg:classifiers":[
        {
            "category":"Building & Trades",
            "subcategory":"Plumbing",
            "type":"Services"
        }
    ],
    "sg:phone":"+32 2 267 55 33",
    "sg:postcode":"1853",
    "sg:province":"Vlaams-Brabant",
    "sg:tags":[
        "diver",
        "commerce",
        "gr",
        "pour",
        "equipement"
    ],
    "wof:name":"Emile Van Cauter",
    "wof:placetype":"venue"
},
  "geometry": {"coordinates":[4.3576331139,50.9091186523],"type":"Point"}
}