{
  "type": "Feature",
  "properties": {
    "iso:country":"BE",
    "sg:address":"Aalterbaan 129",
    "sg:city":"Maldegem",
    "sg:classifiers":[
        {
            "category":"Shopping",
            "subcategory":"Antiques",
            "type":"Retail Goods"
        }
    ],
    "sg:phone":"+32 50 71 63 04",
    "sg:postcode":"9990",
    "sg:province":"Oost-Vlaanderen",
    "wof:name":"Antiek Loys Lucha",
    "wof:placetype":"venue"
},
  "geometry": {"coordinates":[3.4513549805,51.2011680603],"type":"Point"}
}