{
  "type": "Feature",
  "properties": {
    "addr:full":"Waterloose Steenweg 1351 Ukkel/uccle Bruxelles-Capitale 1180",
    "addr:housenumber":"1351",
    "addr:postcode":"1180",
    "addr:street":"Waterloose Steenweg;/",
    "iso:country":"BE",
    "sg:address":"Waterloose Steenweg 1351",
    "sg:city":"Ukkel/uccle",
    "sg:orig_category":"Baby- and kinderkleding",
    "sg:phone":"+32 2 374 30 17",
    "sg:postcode":"1180",
    "sg:province":"Bruxelles-Capitale",
    "wof:name":"Kid Jaco",
    "wof:placetype":"venue"
},
  "geometry": {"coordinates":[4.3747181892,50.7900886536],"type":"Point"}
}