{
  "type": "Feature",
  "properties": {
    "addr:full":"Rue Louis Thys 6 Bruxelles (woluwe-saint-pierre) Bruxelles-Capitale 1150",
    "addr:housenumber":"6",
    "addr:postcode":"1150",
    "addr:street":"Rue Louis Thys",
    "iso:country":"BE",
    "sg:address":"Rue Louis Thys 6",
    "sg:city":"Bruxelles (woluwe-saint-pierre)",
    "sg:classifiers":[
        {
            "category":"Shopping",
            "subcategory":"Florist",
            "type":"Retail Goods"
        }
    ],
    "sg:phone":"+32 2 772 44 83",
    "sg:postcode":"1150",
    "sg:province":"Bruxelles-Capitale",
    "wof:name":"Fleur D'\u00d4",
    "wof:placetype":"venue"
},
  "geometry": {"coordinates":[4.4323239326,50.8372612],"type":"Point"}
}