{
  "type": "Feature",
  "properties": {
    "addr:full":"Rue De L'angle 2 Antoing Hainaut 7640",
    "addr:housenumber":"2",
    "addr:postcode":"7640",
    "addr:street":"Rue De L'Angle",
    "iso:country":"BE",
    "sg:address":"Rue De L'angle 2",
    "sg:city":"Antoing",
    "sg:orig_category":"Woningbouw",
    "sg:phone":"+32 69 44 26 91",
    "sg:postcode":"7640",
    "sg:province":"Hainaut",
    "wof:name":"Patrick Decarpentrie",
    "wof:placetype":"venue"
},
  "geometry": {"coordinates":[3.4527668953,50.5512008667],"type":"Point"}
}