{
  "type": "Feature",
  "properties": {
    "addr:full":"Brusselsesteenweg 46 Ninove Oost-Vlaanderen 9400",
    "addr:housenumber":"46",
    "addr:postcode":"9400",
    "addr:street":"Brusselsesteenweg",
    "iso:country":"BE",
    "sg:address":"Brusselsesteenweg 46",
    "sg:city":"Ninove",
    "sg:orig_category":"Dierenartsen",
    "sg:phone":"+32 54 34 16 09",
    "sg:postcode":"9400",
    "sg:province":"Oost-Vlaanderen",
    "wof:name":"Peter Buyl",
    "wof:placetype":"venue"
},
  "geometry": {"coordinates":[4.0273389816,50.8283233643],"type":"Point"}
}