{
  "type": "Feature",
  "properties": {
    "addr:full":"Brusselsesteenweg 2 Lebbeke Oost-Vlaanderen 9280",
    "addr:housenumber":"2",
    "addr:postcode":"9280",
    "addr:street":"Brusselsesteenweg",
    "iso:country":"BE",
    "sg:address":"Brusselsesteenweg 2",
    "sg:city":"Lebbeke",
    "sg:orig_category":"S\u00e9curit\u00e9 sociale",
    "sg:phone":"+32 52 40 97 61",
    "sg:postcode":"9280",
    "sg:province":"Oost-Vlaanderen",
    "wof:name":"Christelijke Mutualiteit",
    "wof:placetype":"venue"
},
  "geometry": {"coordinates":[4.1299300194,50.9974708557],"type":"Point"}
}