{
  "type": "Feature",
  "properties": {
    "addr:full":"Dorpsstraat 26 Stabroek Antwerpen 2940",
    "addr:housenumber":"26",
    "addr:postcode":"2940",
    "addr:street":"Dorpsstraat",
    "iso:country":"BE",
    "sg:address":"Dorpsstraat 26",
    "sg:city":"Stabroek",
    "sg:orig_category":"Opticiens",
    "sg:phone":"+32 3 568 81 26",
    "sg:postcode":"2940",
    "sg:province":"Antwerpen",
    "wof:name":"Jacqueline Tessens",
    "wof:placetype":"venue"
},
  "geometry": {"coordinates":[4.363858223,51.3313369751],"type":"Point"}
}