{
  "type": "Feature",
  "properties": {
    "addr:full":"Oud-strijderslaan 4 Zonnebeke (beselare) West-Vlaanderen 8980",
    "addr:housenumber":"4",
    "addr:postcode":"8980",
    "addr:street":"Oud-Strijderslaan",
    "iso:country":"BE",
    "sg:address":"Oud-strijderslaan 4",
    "sg:city":"Zonnebeke (beselare)",
    "sg:classifiers":[
        {
            "category":"Utilities",
            "subcategory":"Natural Gas",
            "type":"Services"
        }
    ],
    "sg:phone":"+32 475 67 18 87",
    "sg:postcode":"8980",
    "sg:province":"West-Vlaanderen",
    "sg:tags":[
        "firework"
    ],
    "wof:name":"Touch Pyrotechniek",
    "wof:placetype":"venue"
},
  "geometry": {"coordinates":[3.0267560482,50.8512153625],"type":"Point"}
}