{
  "type": "Feature",
  "properties": {
    "addr:full":"Stationsstraat 93 Sint-niklaas Oost-Vlaanderen 9100",
    "addr:housenumber":"93",
    "addr:postcode":"9100",
    "addr:street":"Stationsstraat",
    "iso:country":"BE",
    "sg:address":"Stationsstraat 93",
    "sg:city":"Sint-niklaas",
    "sg:classifiers":[
        {
            "category":"Manufacturing",
            "subcategory":"Textiles",
            "type":"Manufacturing & Wholesale Goods"
        }
    ],
    "sg:phone":"+32 3 766 69 60",
    "sg:postcode":"9100",
    "sg:province":"Oost-Vlaanderen",
    "wof:name":"Huis Verlinden",
    "wof:placetype":"venue"
},
  "geometry": {"coordinates":[4.1423339844,51.1683807373],"type":"Point"}
}