{
  "type": "Feature",
  "properties": {
    "iso:country":"BE",
    "sg:address":"Prelaat Deckersstraat 4b2",
    "sg:city":"Kalmthout",
    "sg:orig_category":"Fleurs and plantes",
    "sg:phone":"+32 3 667 23 53",
    "sg:postcode":"2920",
    "sg:province":"Antwerpen",
    "wof:name":"Huis De Groof",
    "wof:placetype":"venue"
},
  "geometry": {"coordinates":[4.5173401833,51.43542099],"type":"Point"}
}