{
  "type": "Feature",
  "properties": {
    "addr:full":"Sint-gillislaan 102 Dendermonde Oost-Vlaanderen 9200",
    "addr:housenumber":"102",
    "addr:postcode":"9200",
    "addr:street":"Sint-Gillislaan;Oost-Vlaanderen",
    "iso:country":"BE",
    "sg:address":"Sint-gillislaan 102",
    "sg:city":"Dendermonde",
    "sg:classifiers":[
        {
            "category":"Shopping",
            "subcategory":"Crafts & Fabrics",
            "type":"Retail Goods"
        }
    ],
    "sg:phone":"+32 52 22 17 57",
    "sg:postcode":"9200",
    "sg:province":"Oost-Vlaanderen",
    "sg:tags":[
        "ceramic"
    ],
    "wof:name":"Spittaels-de Vriese",
    "wof:placetype":"venue"
},
  "geometry": {"coordinates":[4.1117610931,51.0182571411],"type":"Point"}
}