{
  "type": "Feature",
  "properties": {
    "iso:country":"BE",
    "sg:address":"Place Sainte-v\u00e9ronique 12",
    "sg:city":"Li\u00e8ge 1",
    "sg:classifiers":[
        {
            "category":"Professional",
            "subcategory":"Printing & Photocopies",
            "type":"Services"
        }
    ],
    "sg:phone":"+32 4 254 14 24",
    "sg:postcode":"4000",
    "sg:province":"Li\u00e8ge",
    "sg:tags":[
        "-",
        "plan",
        "reproduction"
    ],
    "wof:name":"Exacto",
    "wof:placetype":"venue"
},
  "geometry": {"coordinates":[5.5652041435,50.6319732666],"type":"Point"}
}