{
  "type": "Feature",
  "properties": {
    "iso:country":"BE",
    "sg:address":"Otterstraat 212",
    "sg:city":"Turnhout",
    "sg:classifiers":[
        {
            "category":"Government",
            "subcategory":"Post Office",
            "type":"Public Place"
        }
    ],
    "sg:phone":"+32 14 41 14 03",
    "sg:postcode":"2300",
    "sg:province":"Antwerpen",
    "sg:tags":[
        "access",
        "-",
        "part",
        "truck"
    ],
    "wof:name":"Claeys Auto-onderdelen",
    "wof:placetype":"venue"
},
  "geometry": {"coordinates":[4.9572000504,51.3212890625],"type":"Point"}
}