{
  "type": "Feature",
  "properties": {
    "iso:country":"BE",
    "sg:address":"Colliemolenstraat 4",
    "sg:city":"Staden",
    "sg:orig_category":"Groententeelt",
    "sg:phone":"+32 51 20 59 66",
    "sg:postcode":"8840",
    "sg:province":"West-Vlaanderen",
    "wof:name":"Geert Wybaillie",
    "wof:placetype":"venue"
},
  "geometry": {"coordinates":[3.0531690121,50.9271430969],"type":"Point"}
}