{
  "type": "Feature",
  "properties": {
    "iso:country":"BE",
    "sg:address":"Kervijnstraat 6",
    "sg:city":"Harelbeke",
    "sg:orig_category":"S\u00e9curit\u00e9 sociale",
    "sg:phone":"+32 56 70 32 48",
    "sg:postcode":"8531",
    "sg:province":"West-Vlaanderen",
    "wof:name":"Hulpe Voor Wederhulpe",
    "wof:placetype":"venue"
},
  "geometry": {"coordinates":[3.3109710217,50.8747558594],"type":"Point"}
}