{
  "type": "Feature",
  "properties": {
    "iso:country":"BE",
    "sg:address":"Chemin De La Praye 15a",
    "sg:city":"Braine L'alleud (braine-l'alleud)",
    "sg:classifiers":[
        {
            "category":"Social Services",
            "subcategory":"Retirement Home",
            "type":"Services"
        }
    ],
    "sg:phone":"+32 2 385 00 75",
    "sg:postcode":"1420",
    "sg:province":"Brabant Wallon",
    "sg:tags":[
        "society",
        "protection",
        "animal"
    ],
    "wof:name":"Animaux En P\u00e9ril",
    "wof:placetype":"venue"
},
  "geometry": {"coordinates":[7.0635519028,47.0832939148],"type":"Point"}
}