{
  "type": "Feature",
  "properties": {
    "addr:full":"Boulevard Delwart 1 Tournai Hainaut 7500",
    "addr:housenumber":"1",
    "addr:postcode":"7500",
    "addr:street":"Boulevard Delwart",
    "iso:country":"BE",
    "sg:address":"Boulevard Delwart 1",
    "sg:city":"Tournai",
    "sg:orig_category":"Ordinateurs and \u00e9quipement informatique. Entretien and r\u00e9parations de machines de bureau and ordinat",
    "sg:phone":"+32 69 84 77 20",
    "sg:postcode":"7500",
    "sg:province":"Hainaut",
    "wof:name":"Micro-engineering",
    "wof:placetype":"venue"
},
  "geometry": {"coordinates":[3.3840250969,50.6141929626],"type":"Point"}
}