{
  "type": "Feature",
  "properties": {
    "addr:full":"Grauwe Torenwal 22 Bree Limburg 3960",
    "addr:housenumber":"22",
    "addr:postcode":"3960",
    "addr:street":"Grauwe Torenwal",
    "iso:country":"BE",
    "sg:address":"Grauwe Torenwal 22",
    "sg:city":"Bree",
    "sg:orig_category":"Rijscholen",
    "sg:phone":"+32 89 46 14 87",
    "sg:postcode":"3960",
    "sg:province":"Limburg",
    "wof:name":"Auto- & Motorrijschool Satory",
    "wof:placetype":"venue"
},
  "geometry": {"coordinates":[5.6005239487,51.1398696899],"type":"Point"}
}