{
  "type": "Feature",
  "properties": {
    "addr:full":"Bollisstraat 39 Peer Limburg 3990",
    "addr:housenumber":"39",
    "addr:postcode":"3990",
    "addr:street":"Bollisstraat",
    "iso:country":"BE",
    "sg:address":"Bollisstraat 39",
    "sg:city":"Peer",
    "sg:orig_category":"Charpentes and couvertures",
    "sg:phone":"+32 11 63 31 17",
    "sg:postcode":"3990",
    "sg:province":"Limburg",
    "wof:name":"Dakwerken Maes",
    "wof:placetype":"venue"
},
  "geometry": {"coordinates":[5.411550045,51.1347999573],"type":"Point"}
}