{
  "type": "Feature",
  "properties": {
    "iso:country":"BE",
    "sg:address":"Sint-gillislaan 147",
    "sg:city":"Dendermonde",
    "sg:orig_category":"Baby- and kinderkleding",
    "sg:phone":"+32 52 21 24 67",
    "sg:postcode":"9200",
    "sg:province":"Oost-Vlaanderen",
    "wof:name":"De Ooievaar",
    "wof:placetype":"venue"
},
  "geometry": {"coordinates":[4.1119561195,51.0186424255],"type":"Point"}
}