{
  "type": "Feature",
  "properties": {
    "addr:full":"Chauss\u00e9e De Louvain 947 Bruxelles (evere) Bruxelles-Capitale 1140",
    "addr:housenumber":"947",
    "addr:postcode":"1140",
    "addr:street":"Chausse\u0301E De Louvain",
    "iso:country":"BE",
    "sg:address":"Chauss\u00e9e De Louvain 947",
    "sg:city":"Bruxelles (evere)",
    "sg:classifiers":[
        {
            "category":"Communications",
            "type":"Services"
        }
    ],
    "sg:phone":"+32 2 705 10 15",
    "sg:postcode":"1140",
    "sg:province":"Bruxelles-Capitale",
    "sg:tags":[
        "telecommunication"
    ],
    "wof:name":"Hitech",
    "wof:placetype":"venue"
},
  "geometry": {"coordinates":[4.4207401276,50.8607673645],"type":"Point"}
}