{
  "type": "Feature",
  "properties": {
    "addr:full":"Brusselsesteenweg 372 Gent (ledeberg) Oost-Vlaanderen 9050",
    "addr:housenumber":"372",
    "addr:postcode":"9050",
    "addr:street":"Brusselsesteenweg",
    "iso:country":"BE",
    "sg:address":"Brusselsesteenweg 372",
    "sg:city":"Gent (ledeberg)",
    "sg:classifiers":[
        {
            "category":"Communications",
            "subcategory":"Film & Video Production",
            "type":"Services"
        }
    ],
    "sg:phone":"+32 9 329 64 82",
    "sg:postcode":"9050",
    "sg:province":"Oost-Vlaanderen",
    "sg:tags":[
        "producer",
        "realizators"
    ],
    "wof:name":"Outrah Bvba",
    "wof:placetype":"venue"
},
  "geometry": {"coordinates":[3.7432849407,51.0403404236],"type":"Point"}
}