{
  "type": "Feature",
  "properties": {
    "addr:full":"Hoogpoort 3a Gent Oost-Vlaanderen 9000",
    "addr:housenumber":"3a",
    "addr:postcode":"9000",
    "addr:street":"Hoogpoort;Oost-Vlaanderen",
    "iso:country":"BE",
    "sg:address":"Hoogpoort 3a",
    "sg:city":"Gent",
    "sg:classifiers":[
        {
            "category":"Shopping",
            "subcategory":"Shoes",
            "type":"Retail Goods"
        }
    ],
    "sg:phone":"+32 9 225 54 54",
    "sg:postcode":"9000",
    "sg:province":"Oost-Vlaanderen",
    "sg:tags":[
        "slipper",
        "-"
    ],
    "wof:name":"Bethsabis",
    "wof:placetype":"venue"
},
  "geometry": {"coordinates":[3.7228109837,51.0558242798],"type":"Point"}
}