{
  "type": "Feature",
  "properties": {
    "addr:full":"Rue Fays 34 Flemalle Li\u00e8ge 4400",
    "addr:housenumber":"34",
    "addr:postcode":"4400",
    "addr:street":"Rue Fays",
    "iso:country":"BE",
    "sg:address":"Rue Fays 34",
    "sg:city":"Flemalle",
    "sg:orig_category":"Brood, gebak and snoepgoed",
    "sg:phone":"+32 4 275 03 10",
    "sg:postcode":"4400",
    "sg:province":"Li\u00e8ge",
    "wof:name":"Caroline Nihoul",
    "wof:placetype":"venue"
},
  "geometry": {"coordinates":[5.442961216,50.5821990967],"type":"Point"}
}