{
  "type": "Feature",
  "properties": {
    "addr:full":"Opvelpsestraat 10 Bierbeek Vlaams-Brabant 3360",
    "addr:housenumber":"10",
    "addr:postcode":"3360",
    "addr:street":"Opvelpsestraat",
    "iso:country":"BE",
    "sg:address":"Opvelpsestraat 10",
    "sg:city":"Bierbeek",
    "sg:classifiers":[
        {
            "category":"Health Services",
            "subcategory":"Dentist",
            "type":"Services"
        }
    ],
    "sg:phone":"+32 16 46 29 73",
    "sg:postcode":"3360",
    "sg:province":"Vlaams-Brabant",
    "wof:name":"Van Cappellen Hildegard",
    "wof:placetype":"venue"
},
  "geometry": {"coordinates":[4.7638101578,50.8260688782],"type":"Point"}
}