{
  "type": "Feature",
  "properties": {
    "addr:full":"Astridlaan 18 Vosselaar Antwerpen 2350",
    "addr:housenumber":"18",
    "addr:postcode":"2350",
    "addr:street":"Astridlaan",
    "iso:country":"BE",
    "sg:address":"Astridlaan 18",
    "sg:city":"Vosselaar",
    "sg:classifiers":[
        {
            "category":"Professional",
            "subcategory":"Accounting & Tax Preparation",
            "type":"Services"
        }
    ],
    "sg:phone":"+32 14 61 83 93",
    "sg:postcode":"2350",
    "sg:province":"Antwerpen",
    "sg:tags":[
        "bookkeeper"
    ],
    "wof:name":"Borgers P",
    "wof:placetype":"venue"
},
  "geometry": {"coordinates":[4.8762288094,51.3087768555],"type":"Point"}
}