{
  "type": "Feature",
  "properties": {
    "iso:country":"BE",
    "sg:address":"Avenue Jacques Sermon 36",
    "sg:city":"Bruxelles (ganshoren)",
    "sg:classifiers":[
        {
            "category":"Health Services",
            "subcategory":"Dentist",
            "type":"Services"
        }
    ],
    "sg:phone":"+32 2 420 28 36",
    "sg:postcode":"1083",
    "sg:province":"Bruxelles-Capitale",
    "wof:name":"Vander Donckt Didier",
    "wof:placetype":"venue"
},
  "geometry": {"coordinates":[4.3210430145,50.8686599731],"type":"Point"}
}