{
  "type": "Feature",
  "properties": {
    "iso:country":"BE",
    "sg:address":"Rue Du Roua 39",
    "sg:city":"Ans (alleur)",
    "sg:classifiers":[
        {
            "category":"Science Facility",
            "type":"Public Place"
        }
    ],
    "sg:phone":"+32 4 263 73 42",
    "sg:postcode":"4432",
    "sg:province":"Li\u00e8ge",
    "sg:tags":[
        "industrial",
        "-",
        "robot"
    ],
    "wof:name":"K.j.m Automation",
    "wof:placetype":"venue"
},
  "geometry": {"coordinates":[5.5095758438,50.6728973389],"type":"Point"}
}