{
  "type": "Feature",
  "properties": {
    "iso:country":"BE",
    "sg:address":"Houwendijk 15",
    "sg:city":"Arendonk",
    "sg:classifiers":[
        {
            "category":"Farming",
            "subcategory":"Farm & Veterinary Services",
            "type":"Manufacturing & Wholesale Goods"
        }
    ],
    "sg:phone":"+32 14 67 99 24",
    "sg:postcode":"2370",
    "sg:province":"Antwerpen",
    "sg:tags":[
        "agricultural",
        "contractor"
    ],
    "wof:name":"Hagrico",
    "wof:placetype":"venue"
},
  "geometry": {"coordinates":[5.0574398041,51.3095397949],"type":"Point"}
}