{
  "type": "Feature",
  "properties": {
    "iso:country":"BE",
    "sg:address":"Parklaan 20 Box 1",
    "sg:city":"Zaventem",
    "sg:classifiers":[
        {
            "category":"Real Estate",
            "subcategory":"Architect",
            "type":"Services"
        }
    ],
    "sg:phone":"+32 2 721 17 49",
    "sg:postcode":"1930",
    "sg:province":"Vlaams-Brabant",
    "wof:name":"Deroover M",
    "wof:placetype":"venue"
},
  "geometry": {"coordinates":[4.4745130539,50.8809928894],"type":"Point"}
}