{
  "type": "Feature",
  "properties": {
    "addr:full":"Rue Des Fripiers 13 Namur Namur 5000",
    "addr:housenumber":"13",
    "addr:postcode":"5000",
    "addr:street":"Rue Des Fripiers",
    "iso:country":"BE",
    "sg:address":"Rue Des Fripiers 13",
    "sg:city":"Namur",
    "sg:classifiers":[
        {
            "category":"Shopping",
            "subcategory":"Jewelry",
            "type":"Retail Goods"
        }
    ],
    "sg:phone":"+32 81 22 02 02",
    "sg:postcode":"5000",
    "sg:province":"Namur",
    "sg:tags":[
        "purchase",
        "-",
        "sale",
        "gold"
    ],
    "wof:name":"D'or Et Argent",
    "wof:placetype":"venue"
},
  "geometry": {"coordinates":[4.8655061722,50.462978363],"type":"Point"}
}