{
  "type": "Feature",
  "properties": {
    "iso:country":"BE",
    "sg:address":"Grote Markt 66be",
    "sg:city":"Westerlo",
    "sg:orig_category":"Artistes ind\u00e9pendants",
    "sg:phone":"+32 14 54 83 72",
    "sg:postcode":"2260",
    "sg:province":"Antwerpen",
    "wof:name":"Mirei Bonte",
    "wof:placetype":"venue"
},
  "geometry": {"coordinates":[4.9173531532,51.0862579346],"type":"Point"}
}