{
  "type": "Feature",
  "properties": {
    "addr:full":"Noorddoorgang 9 Brussel/bruxelles Bruxelles-Capitale 1000",
    "addr:housenumber":"9",
    "addr:postcode":"1000",
    "addr:street":"Noorddoorgang;/",
    "iso:country":"BE",
    "sg:address":"Noorddoorgang 9",
    "sg:city":"Brussel/bruxelles",
    "sg:orig_category":"Bloemen and planten",
    "sg:phone":"+32 2 223 76 86",
    "sg:postcode":"1000",
    "sg:province":"Bruxelles-Capitale",
    "wof:name":"Maxime\u00b4s",
    "wof:placetype":"venue"
},
  "geometry": {"coordinates":[4.3684039116,50.848575592],"type":"Point"}
}