{
  "type": "Feature",
  "properties": {
    "iso:country":"BE",
    "sg:address":"Joseph G\u00c9rardstraat 16",
    "sg:city":"Gent",
    "sg:orig_category":"Enseignement maternel and primaire",
    "sg:phone":"+32 9 228 52 67",
    "sg:postcode":"9040",
    "sg:province":"Oost-Vlaanderen",
    "wof:name":"Vrije Basisschool",
    "wof:placetype":"venue"
},
  "geometry": {"coordinates":[3.7473919392,51.0615882874],"type":"Point"}
}