{
  "type": "Feature",
  "properties": {
    "iso:country":"BE",
    "sg:address":"Chauss\u00e9e De Mons 11",
    "sg:city":"Anderlues",
    "sg:classifiers":[
        {
            "category":"Shopping",
            "subcategory":"Books",
            "type":"Retail Goods"
        }
    ],
    "sg:phone":"+32 71 52 31 38",
    "sg:postcode":"6150",
    "sg:province":"Hainaut",
    "sg:tags":[
        "bookseller"
    ],
    "wof:name":"Librairie Du Monument Sc",
    "wof:placetype":"venue"
},
  "geometry": {"coordinates":[4.2877259254,50.4038581848],"type":"Point"}
}