{
  "type": "Feature",
  "properties": {
    "iso:country":"BE",
    "sg:address":"Chauss\u00e9e De Marenne 13",
    "sg:city":"Marche-en-famenne",
    "sg:classifiers":[
        {
            "category":"Transit Center",
            "subcategory":"Passenger",
            "type":"Transportation"
        }
    ],
    "sg:phone":"+32 84 31 16 47",
    "sg:postcode":"6900",
    "sg:province":"Luxembourg",
    "sg:tags":[
        "taxidermist"
    ],
    "wof:name":"Alexandre",
    "wof:placetype":"venue"
},
  "geometry": {"coordinates":[5.3478970528,50.2277755737],"type":"Point"}
}