{
  "type": "Feature",
  "properties": {
    "iso:country":"BE",
    "sg:address":"Rue De Montigny 19",
    "sg:city":"Charleroi",
    "sg:classifiers":[
        {
            "category":"Health Services",
            "subcategory":"Dentist",
            "type":"Services"
        }
    ],
    "sg:phone":"+32 71 32 71 28",
    "sg:postcode":"6000",
    "sg:province":"Hainaut",
    "wof:name":"Dumont D",
    "wof:placetype":"venue"
},
  "geometry": {"coordinates":[4.4437317848,50.4083213806],"type":"Point"}
}