{
  "type": "Feature",
  "properties": {
    "addr:full":"Hasseltweg 194 Genk Limburg 3600",
    "addr:housenumber":"194",
    "addr:postcode":"3600",
    "addr:street":"Hasseltweg",
    "iso:country":"BE",
    "sg:address":"Hasseltweg 194",
    "sg:city":"Genk",
    "sg:orig_category":"Installation de menuiserie en bois and plastique",
    "sg:phone":"+32 89 36 32 60",
    "sg:postcode":"3600",
    "sg:province":"Limburg",
    "wof:name":"Az Verandas Genk Sa",
    "wof:placetype":"venue"
},
  "geometry": {"coordinates":[5.4545211792,50.9608001709],"type":"Point"}
}