{
  "type": "Feature",
  "properties": {
    "addr:full":". Eupen (groot) Li\u00e8ge 4700",
    "addr:postcode":"4700",
    "addr:street":"Groot Lie\u0300Ge",
    "iso:country":"BE",
    "sg:address":".",
    "sg:city":"Eupen (groot)",
    "sg:orig_category":"Apotheken",
    "sg:phone":"+32 900 10 500",
    "sg:postcode":"4700",
    "sg:province":"Li\u00e8ge",
    "wof:name":"Apothekers Van Wacht",
    "wof:placetype":"venue"
},
  "geometry": {"coordinates":[6.0296521187,50.6318206787],"type":"Point"}
}