{
  "type": "Feature",
  "properties": {
    "addr:full":"Uwenberg 14 Beersel Vlaams-Brabant 1650",
    "addr:housenumber":"14",
    "addr:postcode":"1650",
    "addr:street":"Uwenberg",
    "iso:country":"BE",
    "sg:address":"Uwenberg 14",
    "sg:city":"Beersel",
    "sg:orig_category":"Mus\u00e9es and patrimoine culturel",
    "sg:phone":"+32 2 377 15 57",
    "sg:postcode":"1650",
    "sg:province":"Vlaams-Brabant",
    "wof:name":"Herman Teirlinckhuis",
    "wof:placetype":"venue"
},
  "geometry": {"coordinates":[4.3068771362,50.7667274475],"type":"Point"}
}