{
  "type": "Feature",
  "properties": {
    "iso:country":"BE",
    "sg:address":"Rue Grande 24",
    "sg:city":"Couvin (br\u00fbly)",
    "sg:classifiers":[
        {
            "category":"Bars & Pubs",
            "type":"Food & Drink"
        }
    ],
    "sg:phone":"+32 60 31 14 85",
    "sg:postcode":"5660",
    "sg:province":"Namur",
    "wof:name":"Strada (la)",
    "wof:placetype":"venue"
},
  "geometry": {"coordinates":[4.524928093,49.9697113037],"type":"Point"}
}