{
  "type": "Feature",
  "properties": {
    "addr:full":"Route De Soiron 1 Pepinster Li\u00e8ge 4860",
    "addr:housenumber":"1",
    "addr:postcode":"4860",
    "addr:street":"Route De Soiron",
    "iso:country":"BE",
    "sg:address":"Route De Soiron 1",
    "sg:city":"Pepinster",
    "sg:orig_category":"Enseignement maternel and primaire",
    "sg:phone":"+32 87 46 00 28",
    "sg:postcode":"4860",
    "sg:province":"Li\u00e8ge",
    "wof:name":"Ecole Fondamentale",
    "wof:placetype":"venue"
},
  "geometry": {"coordinates":[5.7904448509,50.5748329163],"type":"Point"}
}