{
  "type": "Feature",
  "properties": {
    "addr:full":"Brusselsesteenweg 437 Asse Vlaams-Brabant 1731",
    "addr:housenumber":"437",
    "addr:postcode":"1731",
    "addr:street":"Brusselsesteenweg",
    "iso:country":"BE",
    "sg:address":"Brusselsesteenweg 437",
    "sg:city":"Asse",
    "sg:orig_category":"Diverse zakelijke dienstverlening",
    "sg:phone":"+32 2 481 06 70",
    "sg:postcode":"1731",
    "sg:province":"Vlaams-Brabant",
    "wof:name":"C.i.b. Travel",
    "wof:placetype":"venue"
},
  "geometry": {"coordinates":[4.2689390182,50.8876800537],"type":"Point"}
}