{
  "type": "Feature",
  "properties": {
    "addr:full":"Dudzeelse Steenweg 121-133 Brugge West-Vlaanderen 8000",
    "addr:housenumber":"121-133",
    "addr:postcode":"8000",
    "addr:street":"Dudzeelse Steenweg",
    "iso:country":"BE",
    "sg:address":"Dudzeelse Steenweg 121-133",
    "sg:city":"Brugge",
    "sg:classifiers":[
        {
            "category":"Autos & Motor Vehicles",
            "subcategory":"Automobile Sales",
            "type":"Retail Goods"
        }
    ],
    "sg:phone":"+32 50 33 09 10",
    "sg:postcode":"8000",
    "sg:province":"West-Vlaanderen",
    "sg:tags":[
        "car",
        "used",
        "-"
    ],
    "wof:name":"Snauwaert",
    "wof:placetype":"venue"
},
  "geometry": {"coordinates":[3.2276248932,51.2291183472],"type":"Point"}
}