{
  "type": "Feature",
  "properties": {
    "addr:full":"Rue De La Carri\u00c8re 2 Marche-en-famenne Luxembourg 6900",
    "addr:housenumber":"2",
    "addr:postcode":"6900",
    "addr:street":"Rue De La Carrie\u0300Re",
    "iso:country":"BE",
    "sg:address":"Rue De La Carri\u00c8re 2",
    "sg:city":"Marche-en-famenne",
    "sg:orig_category":"Rev\u00eatements pour sols and murs",
    "sg:phone":"+32 84 31 30 90",
    "sg:postcode":"6900",
    "sg:province":"Luxembourg",
    "wof:name":"Marc Legrand",
    "wof:placetype":"venue"
},
  "geometry": {"coordinates":[5.3365840912,50.2099456787],"type":"Point"}
}