{
  "type": "Feature",
  "properties": {
    "iso:country":"BE",
    "sg:address":"Turnhoutseweg 18",
    "sg:city":"Geel",
    "sg:classifiers":[
        {
            "category":"Food & Beverages",
            "subcategory":"Fruits & Vegetables",
            "type":"Retail Goods"
        }
    ],
    "sg:phone":"+32 14 85 28 37",
    "sg:postcode":"2440",
    "sg:province":"Antwerpen",
    "sg:tags":[
        "l\u00e9gumes",
        "gr"
    ],
    "wof:name":"Walter Janssens",
    "wof:placetype":"venue"
},
  "geometry": {"coordinates":[4.9788789749,51.2058753967],"type":"Point"}
}