{
  "type": "Feature",
  "properties": {
    "addr:full":"Rue Emile Feron 75 Bruxelles (saint-gilles) Bruxelles-Capitale 1060",
    "addr:housenumber":"75",
    "addr:postcode":"1060",
    "addr:street":"Rue Emile Feron",
    "iso:country":"BE",
    "sg:address":"Rue Emile Feron 75",
    "sg:city":"Bruxelles (saint-gilles)",
    "sg:classifiers":[
        {
            "category":"Wholesale",
            "subcategory":"Books, Periodicals, & Newspapers",
            "type":"Manufacturing & Wholesale Goods"
        }
    ],
    "sg:phone":"+32 2 538 51 49",
    "sg:postcode":"1060",
    "sg:province":"Bruxelles-Capitale",
    "sg:tags":[
        "publisher"
    ],
    "wof:name":"Eurokom",
    "wof:placetype":"venue"
},
  "geometry": {"coordinates":[4.337790966,50.8324661255],"type":"Point"}
}