{
  "type": "Feature",
  "properties": {
    "iso:country":"BE",
    "sg:address":"Bodegemstraat 9",
    "sg:city":"Dilbeek (itterbeek)",
    "sg:classifiers":[
        {
            "category":"Building & Trades",
            "subcategory":"Construction",
            "type":"Services"
        }
    ],
    "sg:phone":"+32 2 463 56 46",
    "sg:postcode":"1701",
    "sg:province":"Vlaams-Brabant",
    "sg:tags":[
        "duct",
        "underground",
        "ducting"
    ],
    "wof:name":"A",
    "wof:placetype":"venue"
},
  "geometry": {"coordinates":[4.2409729958,50.8427391052],"type":"Point"}
}