{
  "type": "Feature",
  "properties": {
    "addr:full":"Akelei 62 Sint-katelijne-waver Antwerpen 2860",
    "addr:housenumber":"62",
    "addr:postcode":"2860",
    "addr:street":"Akelei",
    "iso:country":"BE",
    "sg:address":"Akelei 62",
    "sg:city":"Sint-katelijne-waver",
    "sg:orig_category":"M\u00e9decins and sp\u00e9cialistes",
    "sg:phone":"+32 15 55 44 45",
    "sg:postcode":"2860",
    "sg:province":"Antwerpen",
    "wof:name":"Luc C.r. Janssens",
    "wof:placetype":"venue"
},
  "geometry": {"coordinates":[4.5168809891,51.0460205078],"type":"Point"}
}