{
  "type": "Feature",
  "properties": {
    "iso:country":"BE",
    "sg:address":"Avenue Des Celtes 28",
    "sg:city":"Bruxelles (etterbeek)",
    "sg:classifiers":[
        {
            "category":"Insurance",
            "subcategory":"Insurance Agent",
            "type":"Services"
        }
    ],
    "sg:phone":"+32 2 736 00 07",
    "sg:postcode":"1040",
    "sg:province":"Bruxelles-Capitale",
    "sg:tags":[
        "broker"
    ],
    "wof:name":"Van Ingelgem A & Fils Sa",
    "wof:placetype":"venue"
},
  "geometry": {"coordinates":[4.3978857994,50.8383522034],"type":"Point"}
}