{
  "type": "Feature",
  "properties": {
    "addr:full":"Jagerslaan 2ba Vosselaar Antwerpen 2350",
    "addr:housenumber":"2ba",
    "addr:postcode":"2350",
    "addr:street":"Jagerslaan",
    "iso:country":"BE",
    "sg:address":"Jagerslaan 2ba",
    "sg:city":"Vosselaar",
    "sg:orig_category":"Instituts de beaut\u00e9",
    "sg:phone":"+32 14 43 70 51",
    "sg:postcode":"2350",
    "sg:province":"Antwerpen",
    "wof:name":"Pedicure Peditin",
    "wof:placetype":"venue"
},
  "geometry": {"coordinates":[4.9050140381,51.3167533875],"type":"Point"}
}