{
  "type": "Feature",
  "properties": {
    "addr:full":"Hoogstraat 3 Aalst (hofstade) Oost-Vlaanderen 9308",
    "addr:housenumber":"3",
    "addr:postcode":"9308",
    "addr:street":"Hoogstraat",
    "iso:country":"BE",
    "sg:address":"Hoogstraat 3",
    "sg:city":"Aalst (hofstade)",
    "sg:classifiers":[
        {
            "category":"Bakery",
            "type":"Food & Drink"
        }
    ],
    "sg:phone":"+32 53 77 38 65",
    "sg:postcode":"9308",
    "sg:province":"Oost-Vlaanderen",
    "sg:tags":[
        "confectioner",
        "baker"
    ],
    "wof:name":"Verleysen A",
    "wof:placetype":"venue"
},
  "geometry": {"coordinates":[4.0615320206,50.9491729736],"type":"Point"}
}