{
  "type": "Feature",
  "properties": {
    "addr:full":"Emile Bockstaellaan 275 Brussel/bruxelles Bruxelles-Capitale 1020",
    "addr:housenumber":"275",
    "addr:postcode":"1020",
    "addr:street":"Emile Bockstaellaan;/",
    "iso:country":"BE",
    "sg:address":"Emile Bockstaellaan 275",
    "sg:city":"Brussel/bruxelles",
    "sg:orig_category":"Boekhandels Krantenwinkels Rookartikelen",
    "sg:phone":"+32 2 479 74 27",
    "sg:postcode":"1020",
    "sg:province":"Bruxelles-Capitale",
    "wof:name":"Bockstael 2000",
    "wof:placetype":"venue"
},
  "geometry": {"coordinates":[4.3478598595,50.880443573],"type":"Point"}
}