{
  "type": "Feature",
  "properties": {
    "addr:full":"Nijverheidslaan 9c Anzegem (vichte) West-Vlaanderen 8570",
    "addr:housenumber":"9c",
    "addr:postcode":"8570",
    "addr:street":"Nijverheidslaan",
    "iso:country":"BE",
    "sg:address":"Nijverheidslaan 9c",
    "sg:city":"Anzegem (vichte)",
    "sg:classifiers":[
        {
            "category":"Building & Trades",
            "subcategory":"Plumbing",
            "type":"Services"
        }
    ],
    "sg:phone":"+32 56 77 38 75",
    "sg:postcode":"8570",
    "sg:province":"West-Vlaanderen",
    "sg:tags":[
        "pipe",
        "cardboard",
        "-"
    ],
    "wof:name":"Acarta Nv",
    "wof:placetype":"venue"
},
  "geometry": {"coordinates":[3.3910589218,50.8303222656],"type":"Point"}
}