{
  "type": "Feature",
  "properties": {
    "addr:full":"Nieuwkerkestraat 48b2 Heuvelland West-Vlaanderen 8953",
    "addr:housenumber":"48b2",
    "addr:postcode":"8953",
    "addr:street":"Nieuwkerkestraat",
    "iso:country":"BE",
    "sg:address":"Nieuwkerkestraat 48b2",
    "sg:city":"Heuvelland",
    "sg:orig_category":"Fruits and l\u00e9gumes Produits \u00e0 base de pommes de terre Gr",
    "sg:phone":"+32 56 58 87 37",
    "sg:postcode":"8953",
    "sg:province":"West-Vlaanderen",
    "wof:name":"Jolie",
    "wof:placetype":"venue"
},
  "geometry": {"coordinates":[2.8918950558,50.7656745911],"type":"Point"}
}