{
  "type": "Feature",
  "properties": {
    "addr:full":"Zandstraat 31a Scherpenheuvel-zichem (averbode) Vlaams-Brabant 3271",
    "addr:housenumber":"31a",
    "addr:postcode":"3271",
    "addr:street":"Zandstraat",
    "iso:country":"BE",
    "sg:address":"Zandstraat 31a",
    "sg:city":"Scherpenheuvel-zichem (averbode)",
    "sg:classifiers":[
        {
            "category":"Insurance",
            "subcategory":"Insurance Agent",
            "type":"Services"
        }
    ],
    "sg:phone":"+32 13 77 64 77",
    "sg:postcode":"3271",
    "sg:province":"Vlaams-Brabant",
    "sg:tags":[
        "broker"
    ],
    "wof:name":"Blevi",
    "wof:placetype":"venue"
},
  "geometry": {"coordinates":[4.978700161,51.0273475647],"type":"Point"}
}