{
  "type": "Feature",
  "properties": {
    "iso:country":"BE",
    "sg:address":"Rue Joseph Wauters 291",
    "sg:city":"Charleroi",
    "sg:orig_category":"Kantoormateriaal Krantenwinkels Rookartikelen",
    "sg:phone":"+32 71 33 01 42",
    "sg:postcode":"6020",
    "sg:province":"Hainaut",
    "wof:name":"Librairie Bronchain",
    "wof:placetype":"venue"
},
  "geometry": {"coordinates":[4.4281148911,50.4222564697],"type":"Point"}
}