{
  "type": "Feature",
  "properties": {
    "addr:full":"Oost-gistelhof 2 Brugge West-Vlaanderen 8000",
    "addr:housenumber":"2",
    "addr:postcode":"8000",
    "addr:street":"Oost-Gistelhof",
    "iso:country":"BE",
    "sg:address":"Oost-gistelhof 2",
    "sg:city":"Brugge",
    "sg:orig_category":"H\u00f4tels",
    "sg:phone":"+32 50 34 03 24",
    "sg:postcode":"8000",
    "sg:province":"West-Vlaanderen",
    "wof:name":"Hotel Ter Brughe",
    "wof:placetype":"venue"
},
  "geometry": {"coordinates":[3.2256009579,51.2133560181],"type":"Point"}
}