{
  "type": "Feature",
  "properties": {
    "addr:full":"R\u00c9sidence Ma Campagne 20 Komen-waasten/comines-warneton Hainaut 7781",
    "addr:housenumber":"20",
    "addr:postcode":"7781",
    "addr:street":"Komen-Waasten;Hainaut",
    "iso:country":"BE",
    "sg:address":"R\u00c9sidence Ma Campagne 20",
    "sg:city":"Komen-waasten/comines-warneton",
    "sg:classifiers":[
        {
            "category":"Arena",
            "subcategory":"Sports Club",
            "type":"Entertainment"
        }
    ],
    "sg:phone":"+32 56 55 82 30",
    "sg:postcode":"7781",
    "sg:province":"Hainaut",
    "sg:tags":[
        "de"
    ],
    "wof:name":"B.c. Badco",
    "wof:placetype":"venue"
},
  "geometry": {"coordinates":[2.9549469948,50.788394928],"type":"Point"}
}