{
  "type": "Feature",
  "properties": {
    "addr:full":"Place Charles Rogier 3 Bruxelles (saint-josse-ten-noode) Bruxelles-Capitale 1210",
    "addr:housenumber":"3",
    "addr:postcode":"1210",
    "addr:street":"Place Charles Rogier",
    "iso:country":"BE",
    "sg:address":"Place Charles Rogier 3",
    "sg:city":"Bruxelles (saint-josse-ten-noode)",
    "sg:classifiers":[
        {
            "category":"Organizations",
            "subcategory":"Professional Association",
            "type":"Services"
        }
    ],
    "sg:phone":"+32 2 224 31 17",
    "sg:postcode":"1210",
    "sg:province":"Bruxelles-Capitale",
    "sg:tags":[
        "trade-union",
        "federation"
    ],
    "wof:name":"Association Des Ma\u00eetres Cuisiniers De Belgique",
    "wof:placetype":"venue"
},
  "geometry": {"coordinates":[4.3582291603,50.8560714722],"type":"Point"}
}