{
  "type": "Feature",
  "properties": {
    "addr:full":"Rue Bernard Hecquet 24 Beloeil Hainaut 7973",
    "addr:housenumber":"24",
    "addr:postcode":"7973",
    "addr:street":"Rue Bernard Hecquet",
    "iso:country":"BE",
    "sg:address":"Rue Bernard Hecquet 24",
    "sg:city":"Beloeil",
    "sg:orig_category":"Verhuur televisie- and audiovisuele apparatuur",
    "sg:phone":"+32 69 57 89 89",
    "sg:postcode":"7973",
    "sg:province":"Hainaut",
    "wof:name":"U.k.s. Sonorisation",
    "wof:placetype":"venue"
},
  "geometry": {"coordinates":[3.7185389996,50.5071601868],"type":"Point"}
}