{
  "type": "Feature",
  "properties": {
    "addr:full":"Avenue Louise 65 /7 Bruxelles Bruxelles-Capitale 1050",
    "addr:housenumber":"65 / 7",
    "addr:postcode":"1050",
    "addr:street":"Avenue Louise",
    "iso:country":"BE",
    "sg:address":"Avenue Louise 65 /7",
    "sg:city":"Bruxelles",
    "sg:classifiers":[
        {
            "category":"Banks & Credit Unions",
            "subcategory":"Financial Services",
            "type":"Services"
        }
    ],
    "sg:phone":"+32 2 535 29 11",
    "sg:postcode":"1050",
    "sg:province":"Bruxelles-Capitale",
    "sg:tags":[
        "banking",
        "finance",
        "insurance"
    ],
    "wof:name":"Mevr Martine De Witte",
    "wof:placetype":"venue"
},
  "geometry": {"coordinates":[4.3577671051,50.8326416016],"type":"Point"}
}