{
  "type": "Feature",
  "properties": {
    "iso:country":"BE",
    "sg:address":"Watermolenstraat 34",
    "sg:city":"Londerzeel",
    "sg:orig_category":"Advocaten and juridische adviseurs",
    "sg:phone":"+32 52 30 55 99",
    "sg:postcode":"1840",
    "sg:province":"Vlaams-Brabant",
    "wof:name":"Danny Aerts",
    "wof:placetype":"venue"
},
  "geometry": {"coordinates":[4.2829580307,51.0016441345],"type":"Point"}
}