{
  "type": "Feature",
  "properties": {
    "addr:full":"Liersesteenweg 96 Lint Antwerpen 2547",
    "addr:housenumber":"96",
    "addr:postcode":"2547",
    "addr:street":"Liersesteenweg",
    "iso:country":"BE",
    "sg:address":"Liersesteenweg 96",
    "sg:city":"Lint",
    "sg:classifiers":[
        {
            "category":"Cafe",
            "type":"Food & Drink"
        }
    ],
    "sg:phone":"+32 3 455 76 75",
    "sg:postcode":"2547",
    "sg:province":"Antwerpen",
    "sg:tags":[
        "caf\u00e9s"
    ],
    "wof:name":"K.f.c. Lint",
    "wof:placetype":"venue"
},
  "geometry": {"coordinates":[4.5016579628,51.1266784668],"type":"Point"}
}