{
  "type": "Feature",
  "properties": {
    "addr:full":"Otterstraat 58 Dendermonde Oost-Vlaanderen 9200",
    "addr:housenumber":"58",
    "addr:postcode":"9200",
    "addr:street":"Otterstraat;Oost-Vlaanderen",
    "iso:country":"BE",
    "sg:address":"Otterstraat 58",
    "sg:city":"Dendermonde",
    "sg:classifiers":[
        {
            "category":"Organizations",
            "subcategory":"Community Association",
            "type":"Services"
        }
    ],
    "sg:phone":"+32 52 21 28 23",
    "sg:postcode":"9200",
    "sg:province":"Oost-Vlaanderen",
    "sg:tags":[
        "organisation"
    ],
    "wof:name":"Jeugdhuis Zenith",
    "wof:placetype":"venue"
},
  "geometry": {"coordinates":[4.1087408066,51.0225296021],"type":"Point"}
}