{
  "type": "Feature",
  "properties": {
    "iso:country":"BE",
    "sg:address":"Nijverh. Begijnenmeers 75",
    "sg:city":"Liedekerke",
    "sg:classifiers":[
        {
            "category":"Health Services",
            "subcategory":"Medical Lab",
            "type":"Services"
        }
    ],
    "sg:phone":"+32 53 66 55 80",
    "sg:postcode":"1770",
    "sg:province":"Vlaams-Brabant",
    "sg:tags":[
        "chemical",
        "pharmaceutical",
        "pharmacy"
    ],
    "wof:name":"Bellino Bvba",
    "wof:placetype":"venue"
},
  "geometry": {"coordinates":[4.0924229622,50.8836593628],"type":"Point"}
}