{
  "type": "Feature",
  "properties": {
    "addr:full":"Rue De La Roche 43 Hotton (hampteau) Luxembourg 6990",
    "addr:housenumber":"43",
    "addr:postcode":"6990",
    "addr:street":"Rue De La",
    "iso:country":"BE",
    "sg:address":"Rue De La Roche 43",
    "sg:city":"Hotton (hampteau)",
    "sg:classifiers":[
        {
            "category":"Personal",
            "subcategory":"Beauty Salon",
            "type":"Services"
        }
    ],
    "sg:phone":"+32 84 46 62 68",
    "sg:postcode":"6990",
    "sg:province":"Luxembourg",
    "sg:tags":[
        "lady",
        "-",
        "hairdressing"
    ],
    "wof:name":"Marie-louise",
    "wof:placetype":"venue"
},
  "geometry": {"coordinates":[5.4709892273,50.2582969666],"type":"Point"}
}