{
  "type": "Feature",
  "properties": {
    "iso:country":"BE",
    "sg:address":"Vaart Rechts 18",
    "sg:city":"Zomergem",
    "sg:orig_category":"Elektrische installaties voor woningen",
    "sg:phone":"+32 9 372 43 41",
    "sg:postcode":"9930",
    "sg:province":"Oost-Vlaanderen",
    "wof:name":"Vereecke G",
    "wof:placetype":"venue"
},
  "geometry": {"coordinates":[3.5743100643,51.1172103882],"type":"Point"}
}