{
  "type": "Feature",
  "properties": {
    "iso:country":"BE",
    "sg:address":"Meulestedekaai 455",
    "sg:city":"Gent",
    "sg:orig_category":"Postkantoren Verzekeringsmakelaars and experts",
    "sg:phone":"+32 9 251 16 48",
    "sg:postcode":"9000",
    "sg:province":"Oost-Vlaanderen",
    "wof:name":"De Post",
    "wof:placetype":"venue"
},
  "geometry": {"coordinates":[3.7269580364,51.0867424011],"type":"Point"}
}