{
  "type": "Feature",
  "properties": {
    "iso:country":"BE",
    "sg:address":"Overbeekstraat 60",
    "sg:city":"Kortessem",
    "sg:orig_category":"Pleisterwerk",
    "sg:phone":"+32 12 23 46 42",
    "sg:postcode":"3724",
    "sg:province":"Limburg",
    "wof:name":"Joannes Thewissen",
    "wof:placetype":"venue"
},
  "geometry": {"coordinates":[5.4242839813,50.8359107971],"type":"Point"}
}