{
  "type": "Feature",
  "properties": {
    "addr:full":"Grand'rue 52 Thuin Hainaut 6530",
    "addr:housenumber":"52",
    "addr:postcode":"6530",
    "addr:street":"Grand'Rue",
    "iso:country":"BE",
    "sg:address":"Grand'rue 52",
    "sg:city":"Thuin",
    "sg:orig_category":"Enseignement maternel and primaire",
    "sg:phone":"+32 71 59 04 20",
    "sg:postcode":"6530",
    "sg:province":"Hainaut",
    "wof:name":"Ecole Fondamentale",
    "wof:placetype":"venue"
},
  "geometry": {"coordinates":[4.2896828651,50.3388442993],"type":"Point"}
}