{
  "type": "Feature",
  "properties": {
    "addr:full":"Dikkebusseweg 112 Ieper West-Vlaanderen 8900",
    "addr:housenumber":"112",
    "addr:postcode":"8900",
    "iso:country":"BE",
    "sg:address":"Dikkebusseweg 112",
    "sg:city":"Ieper",
    "sg:orig_category":"Kapsalons",
    "sg:phone":"+32 57 20 17 99",
    "sg:postcode":"8900",
    "sg:province":"West-Vlaanderen",
    "wof:name":"Coiffure Charme",
    "wof:placetype":"venue"
},
  "geometry": {"coordinates":[2.873087883,50.8428382874],"type":"Point"}
}