{
  "type": "Feature",
  "properties": {
    "addr:full":"Cit\u00c9 Du Moulin 45b6 Li\u00c8ge Li\u00e8ge 4000",
    "addr:housenumber":"45b6",
    "addr:postcode":"4000",
    "addr:street":"Cite\u0301 Du Moulin",
    "iso:country":"BE",
    "sg:address":"Cit\u00c9 Du Moulin 45b6",
    "sg:city":"Li\u00c8ge",
    "sg:orig_category":"Slagers",
    "sg:phone":"+32 4 224 29 35",
    "sg:postcode":"4000",
    "sg:province":"Li\u00e8ge",
    "wof:name":"Iman Meral",
    "wof:placetype":"venue"
},
  "geometry": {"coordinates":[5.5490908623,50.6506996155],"type":"Point"}
}