{
  "type": "Feature",
  "properties": {
    "iso:country":"BE",
    "sg:address":"Rue Edmond Bonehill 121",
    "sg:city":"Bruxelles (molenbeek-saint-jean)",
    "sg:classifiers":[
        {
            "category":"Manufacturing",
            "subcategory":"Metals",
            "type":"Manufacturing & Wholesale Goods"
        }
    ],
    "sg:phone":"+32 2 410 16 19",
    "sg:postcode":"1080",
    "sg:province":"Bruxelles-Capitale",
    "sg:tags":[
        "working"
    ],
    "wof:name":"Alvarez (ets)",
    "wof:placetype":"venue"
},
  "geometry": {"coordinates":[4.3246049881,50.8500785828],"type":"Point"}
}