{
  "type": "Feature",
  "properties": {
    "addr:full":"Lierseweg 136 Herentals Antwerpen 2200",
    "addr:housenumber":"136",
    "addr:postcode":"2200",
    "addr:street":"Lierseweg",
    "iso:country":"BE",
    "sg:address":"Lierseweg 136",
    "sg:city":"Herentals",
    "sg:classifiers":[
        {
            "category":"Social Services",
            "type":"Services"
        }
    ],
    "sg:phone":"+32 14 21 26 98",
    "sg:postcode":"2200",
    "sg:province":"Antwerpen",
    "wof:name":"Kringloopcentra",
    "wof:placetype":"venue"
},
  "geometry": {"coordinates":[4.8231568336,51.1753387451],"type":"Point"}
}