{
  "type": "Feature",
  "properties": {
    "addr:full":"Kortemarkstraat 37 Ichtegem West-Vlaanderen 8480",
    "addr:housenumber":"37",
    "addr:postcode":"8480",
    "addr:street":"Kortemarkstraat",
    "iso:country":"BE",
    "sg:address":"Kortemarkstraat 37",
    "sg:city":"Ichtegem",
    "sg:orig_category":"Entretien and r\u00e9parations de voitures",
    "sg:phone":"+32 51 58 89 54",
    "sg:postcode":"8480",
    "sg:province":"West-Vlaanderen",
    "wof:name":"Garage Vanden Driessche",
    "wof:placetype":"venue"
},
  "geometry": {"coordinates":[3.0278849602,51.0772399902],"type":"Point"}
}