{
  "type": "Feature",
  "properties": {
    "iso:country":"BE",
    "sg:address":"Langestraat 111",
    "sg:city":"Hulshout (houtvenne)",
    "sg:classifiers":[
        {
            "category":"Freight",
            "type":"Transportation"
        }
    ],
    "sg:phone":"+32 16 69 87 80",
    "sg:postcode":"2235",
    "sg:province":"Antwerpen",
    "sg:tags":[
        "-",
        "transport"
    ],
    "wof:name":"Verrycken Vervoer Bvba",
    "wof:placetype":"venue"
},
  "geometry": {"coordinates":[4.8012151718,51.0350532532],"type":"Point"}
}