{
  "type": "Feature",
  "properties": {
    "addr:full":"Broche De Ferstraat 132 Moeskroen/mouscron Hainaut 7712",
    "addr:housenumber":"132",
    "addr:postcode":"7712",
    "addr:street":"Ferstraat",
    "iso:country":"BE",
    "sg:address":"Broche De Ferstraat 132",
    "sg:city":"Moeskroen/mouscron",
    "sg:orig_category":"Herstelling and restauratie van meubelen Textiel",
    "sg:phone":"+32 56 33 53 86",
    "sg:postcode":"7712",
    "sg:province":"Hainaut",
    "wof:name":"Yves Bayart",
    "wof:placetype":"venue"
},
  "geometry": {"coordinates":[3.216121912,50.7154121399],"type":"Point"}
}