{
  "type": "Feature",
  "properties": {
    "addr:full":"Lindenstraat 7 Keerbergen Vlaams-Brabant 3140",
    "addr:housenumber":"7",
    "addr:postcode":"3140",
    "addr:street":"Lindenstraat",
    "iso:country":"BE",
    "sg:address":"Lindenstraat 7",
    "sg:city":"Keerbergen",
    "sg:classifiers":[
        {
            "category":"Manufacturing",
            "subcategory":"Tools & Machinery",
            "type":"Manufacturing & Wholesale Goods"
        }
    ],
    "sg:phone":"+32 15 51 41 31",
    "sg:postcode":"3140",
    "sg:province":"Vlaams-Brabant",
    "sg:tags":[
        "-"
    ],
    "wof:name":"Vadro Bvba",
    "wof:placetype":"venue"
},
  "geometry": {"coordinates":[4.6330909729,51.0020027161],"type":"Point"}
}