{
  "type": "Feature",
  "properties": {
    "addr:full":"All\u00c9e Des Sport 12 Gerpinnes Hainaut 6280",
    "addr:housenumber":"12",
    "addr:postcode":"6280",
    "addr:street":"Alle\u0301E Des Sport;Hainaut",
    "iso:country":"BE",
    "sg:address":"All\u00c9e Des Sport 12",
    "sg:city":"Gerpinnes",
    "sg:classifiers":[
        {
            "category":"Arena",
            "subcategory":"Sports Club",
            "type":"Entertainment"
        }
    ],
    "sg:phone":"+32 71 60 11 60",
    "sg:postcode":"6280",
    "sg:province":"Hainaut",
    "sg:tags":[
        "de"
    ],
    "wof:name":"Todokan",
    "wof:placetype":"venue"
},
  "geometry": {"coordinates":[4.5276851654,50.3365364075],"type":"Point"}
}