{
  "type": "Feature",
  "properties": {
    "iso:country":"BE",
    "sg:address":"Chauss\u00e9e De Ninove 499",
    "sg:city":"Renaix",
    "sg:classifiers":[
        {
            "category":"Autos & Motor Vehicles",
            "subcategory":"Fuel & Gas Station",
            "type":"Retail Goods"
        }
    ],
    "sg:phone":"+32 55 20 69 90",
    "sg:postcode":"9600",
    "sg:province":"Oost-Vlaanderen",
    "wof:name":"Esso-bossuyt R & Co",
    "wof:placetype":"venue"
},
  "geometry": {"coordinates":[3.6383860111,50.753200531],"type":"Point"}
}