{
  "type": "Feature",
  "properties": {
    "iso:country":"BE",
    "sg:address":"Rue Du Midi 25",
    "sg:city":"Renaix",
    "sg:classifiers":[
        {
            "category":"Travel",
            "subcategory":"Hotels & Motels",
            "type":"Entertainment"
        }
    ],
    "sg:phone":"+32 55 21 91 11",
    "sg:postcode":"9600",
    "sg:province":"Oost-Vlaanderen",
    "wof:name":"Lou Pahou (hostellerie)",
    "wof:placetype":"venue"
},
  "geometry": {"coordinates":[3.6036229134,50.7456703186],"type":"Point"}
}