{
  "type": "Feature",
  "properties": {
    "addr:full":"Wittenonnenstraat 28 Hasselt Limburg 3500",
    "addr:housenumber":"28",
    "addr:postcode":"3500",
    "addr:street":"Wittenonnenstraat",
    "iso:country":"BE",
    "sg:address":"Wittenonnenstraat 28",
    "sg:city":"Hasselt",
    "sg:classifiers":[
        {
            "category":"Restaurant",
            "type":"Food & Drink"
        }
    ],
    "sg:phone":"+32 11 24 32 28",
    "sg:postcode":"3500",
    "sg:province":"Limburg",
    "wof:name":"'t Borrelhuis",
    "wof:placetype":"venue"
},
  "geometry": {"coordinates":[5.3408608437,50.9328117371],"type":"Point"}
}