{
  "type": "Feature",
  "properties": {
    "addr:full":"De Drij Dreven 2a Zonhoven Limburg 3520",
    "addr:housenumber":"2a",
    "addr:postcode":"3520",
    "addr:street":"De Drij Dreven",
    "iso:country":"BE",
    "sg:address":"De Drij Dreven 2a",
    "sg:city":"Zonhoven",
    "sg:classifiers":[
        {
            "category":"Real Estate",
            "subcategory":"Surveying",
            "type":"Services"
        }
    ],
    "sg:phone":"+32 11 82 53 69",
    "sg:postcode":"3520",
    "sg:province":"Limburg",
    "sg:tags":[
        "lettering",
        "letter"
    ],
    "wof:name":"Theunissen S",
    "wof:placetype":"venue"
},
  "geometry": {"coordinates":[5.3319988251,51.0026855469],"type":"Point"}
}