{
  "type": "Feature",
  "properties": {
    "addr:full":"Pastoriestraat 1 Kapelle-op-den-bos Vlaams-Brabant 1880",
    "addr:housenumber":"1",
    "addr:postcode":"1880",
    "addr:street":"Pastoriestraat",
    "iso:country":"BE",
    "sg:address":"Pastoriestraat 1",
    "sg:city":"Kapelle-op-den-bos",
    "sg:classifiers":[
        {
            "category":"Education",
            "subcategory":"Library",
            "type":"Public Place"
        }
    ],
    "sg:phone":"+32 15 71 54 22",
    "sg:postcode":"1880",
    "sg:province":"Vlaams-Brabant",
    "wof:name":"Plaatselijke Openbare Bibliotheek",
    "wof:placetype":"venue"
},
  "geometry": {"coordinates":[4.3559341431,51.0137405396],"type":"Point"}
}