{
  "type": "Feature",
  "properties": {
    "addr:full":"Kanaalstraat 19 Zelzate Oost-Vlaanderen 9060",
    "addr:housenumber":"19",
    "addr:postcode":"9060",
    "addr:street":"Kanaalstraat",
    "iso:country":"BE",
    "sg:address":"Kanaalstraat 19",
    "sg:city":"Zelzate",
    "sg:orig_category":"Schoonmaakbedrijven and ongediertebestrijding",
    "sg:phone":"+32 9 342 94 25",
    "sg:postcode":"9060",
    "sg:province":"Oost-Vlaanderen",
    "wof:name":"Willems Schoonmaakorgan.",
    "wof:placetype":"venue"
},
  "geometry": {"coordinates":[3.8068430424,51.2013206482],"type":"Point"}
}