{
  "type": "Feature",
  "properties": {
    "iso:country":"BE",
    "sg:address":"Rue Longchamps 12",
    "sg:city":"Genappe (baisy-thy)",
    "sg:classifiers":[
        {
            "category":"Real Estate",
            "subcategory":"Architect",
            "type":"Services"
        }
    ],
    "sg:phone":"+32 67 78 00 16",
    "sg:postcode":"1470",
    "sg:province":"Brabant Wallon",
    "wof:name":"Tumerelle J",
    "wof:placetype":"venue"
},
  "geometry": {"coordinates":[4.4620041847,50.6020736694],"type":"Point"}
}