{
  "type": "Feature",
  "properties": {
    "iso:country":"BE",
    "sg:address":"Rubensstraat 151",
    "sg:city":"Turnhout",
    "sg:orig_category":"Beautyfarms, relaxatie and lichamelijk welzijn",
    "sg:phone":"+32 14 42 43 29",
    "sg:postcode":"2300",
    "sg:province":"Antwerpen",
    "wof:name":"Zonnestudio",
    "wof:placetype":"venue"
},
  "geometry": {"coordinates":[4.9439311028,51.3143959045],"type":"Point"}
}