{
  "type": "Feature",
  "properties": {
    "iso:country":"BE",
    "sg:address":"Auguste Reyerslaan 1b7",
    "sg:city":"Schaarbeek/schaerbeek",
    "sg:classifiers":[
        {
            "category":"Insurance",
            "subcategory":"Insurance Agent",
            "type":"Services"
        }
    ],
    "sg:phone":"+32 2 733 35 42",
    "sg:postcode":"1030",
    "sg:province":"Bruxelles-Capitale",
    "sg:tags":[
        "verzekeringsmakelaars",
        "expert"
    ],
    "wof:name":"H. De Buisseret",
    "wof:placetype":"venue"
},
  "geometry": {"coordinates":[4.3986282349,50.8544578552],"type":"Point"}
}