{
  "type": "Feature",
  "properties": {
    "iso:country":"BE",
    "sg:address":"Avenue De La Gare 22b1",
    "sg:city":"Fleurus",
    "sg:orig_category":"Artsen and specialisten",
    "sg:phone":"+32 71 81 59 90",
    "sg:postcode":"6220",
    "sg:province":"Hainaut",
    "wof:name":"Dominique Carly",
    "wof:placetype":"venue"
},
  "geometry": {"coordinates":[4.5450291634,50.482749939],"type":"Point"}
}