{
  "type": "Feature",
  "properties": {
    "addr:full":"Ridderstraat 16 Herk-de-stad Limburg 3540",
    "addr:housenumber":"16",
    "addr:postcode":"3540",
    "addr:street":"Ridderstraat",
    "iso:country":"BE",
    "sg:address":"Ridderstraat 16",
    "sg:city":"Herk-de-stad",
    "sg:classifiers":[
        {
            "category":"Shopping",
            "subcategory":"Clothing, Apparel, & Fashions",
            "type":"Retail Goods"
        }
    ],
    "sg:phone":"+32 13 52 38 98",
    "sg:postcode":"3540",
    "sg:province":"Limburg",
    "sg:tags":[
        "-",
        "clothing",
        "child"
    ],
    "wof:name":"Happy Kids",
    "wof:placetype":"venue"
},
  "geometry": {"coordinates":[5.1686081886,50.940574646],"type":"Point"}
}