{
  "type": "Feature",
  "properties": {
    "addr:full":"Malta 12 Bree Limburg 3960",
    "addr:housenumber":"12",
    "addr:postcode":"3960",
    "addr:street":"Malta",
    "iso:country":"BE",
    "sg:address":"Malta 12",
    "sg:city":"Bree",
    "sg:orig_category":"Boucheries",
    "sg:phone":"+32 89 46 19 59",
    "sg:postcode":"3960",
    "sg:province":"Limburg",
    "wof:name":"Beenhouwerij Brebels",
    "wof:placetype":"venue"
},
  "geometry": {"coordinates":[5.6015868187,51.1420783997],"type":"Point"}
}