{
  "type": "Feature",
  "properties": {
    "iso:country":"BE",
    "sg:address":"Chauss\u00c9e De Leuze 272",
    "sg:city":"Ronse/renaix",
    "sg:orig_category":"D\u00e9taillants en pi\u00e8ces and accessoires de voitures. Pi\u00e8ces and accessoires de v\u00e9hicules automobiles G",
    "sg:phone":"+32 55 23 71 31",
    "sg:postcode":"9600",
    "sg:province":"Oost-Vlaanderen",
    "wof:name":"Donkerwolke",
    "wof:placetype":"venue"
},
  "geometry": {"coordinates":[3.5894389153,50.7318458557],"type":"Point"}
}