{
  "type": "Feature",
  "properties": {
    "addr:full":"Chemin De La Bruyere 19 Genappe Brabant Wallon 1473",
    "addr:housenumber":"19",
    "addr:postcode":"1473",
    "addr:street":"Chemin De La Bruyere;Wallon",
    "iso:country":"BE",
    "sg:address":"Chemin De La Bruyere 19",
    "sg:city":"Genappe",
    "sg:orig_category":"M\u00e9decins and sp\u00e9cialistes",
    "sg:phone":"+32 67 77 12 31",
    "sg:postcode":"1473",
    "sg:province":"Brabant Wallon",
    "wof:name":"F. Capet",
    "wof:placetype":"venue"
},
  "geometry": {"coordinates":[4.4642100334,50.6322898865],"type":"Point"}
}