{
  "type": "Feature",
  "properties": {
    "addr:full":"Leopoldplein 2bb Lier Antwerpen 2500",
    "addr:housenumber":"2bb",
    "addr:postcode":"2500",
    "addr:street":"Leopoldplein",
    "iso:country":"BE",
    "sg:address":"Leopoldplein 2bb",
    "sg:city":"Lier",
    "sg:classifiers":[
        {
            "category":"Cafe",
            "type":"Food & Drink"
        }
    ],
    "sg:phone":"+32 3 489 09 53",
    "sg:postcode":"2500",
    "sg:province":"Antwerpen",
    "sg:tags":[
        "caf\u00e9s"
    ],
    "wof:name":"Belina Vercauteren",
    "wof:placetype":"venue"
},
  "geometry": {"coordinates":[4.5634760857,51.1354789734],"type":"Point"}
}