{
  "type": "Feature",
  "properties": {
    "addr:full":"Rue De Serbie 81 Vorst/forest Bruxelles-Capitale 1190",
    "addr:housenumber":"81",
    "addr:postcode":"1190",
    "addr:street":"Rue De Serbie;/ Forest",
    "iso:country":"BE",
    "sg:address":"Rue De Serbie 81",
    "sg:city":"Vorst/forest",
    "sg:orig_category":"Studios photographiques",
    "sg:phone":"+32 2 534 53 32",
    "sg:postcode":"1190",
    "sg:province":"Bruxelles-Capitale",
    "wof:name":"Julien Claessens",
    "wof:placetype":"venue"
},
  "geometry": {"coordinates":[4.331788063,50.82837677],"type":"Point"}
}