{
  "type": "Feature",
  "properties": {
    "iso:country":"BE",
    "sg:address":"Chauss\u00c9e De Wavre 66",
    "sg:city":"Elsene/ixelles",
    "sg:orig_category":"Chaussures",
    "sg:phone":"+32 2 513 06 38",
    "sg:postcode":"1050",
    "sg:province":"Bruxelles-Capitale",
    "wof:name":"Raitex",
    "wof:placetype":"venue"
},
  "geometry": {"coordinates":[4.3650832176,50.8369522095],"type":"Point"}
}