{
  "type": "Feature",
  "properties": {
    "addr:full":"Lange Minnestraat 52 Lebbeke Oost-Vlaanderen 9280",
    "addr:housenumber":"52",
    "addr:postcode":"9280",
    "addr:street":"Lange Minnestraat",
    "iso:country":"BE",
    "sg:address":"Lange Minnestraat 52",
    "sg:city":"Lebbeke",
    "sg:classifiers":[
        {
            "category":"Professional",
            "subcategory":"Testing Lab",
            "type":"Services"
        }
    ],
    "sg:phone":"+32 52 35 62 30",
    "sg:postcode":"9280",
    "sg:province":"Oost-Vlaanderen",
    "sg:tags":[
        "chemist"
    ],
    "wof:name":"De Turck R",
    "wof:placetype":"venue"
},
  "geometry": {"coordinates":[4.1441779137,50.9843559265],"type":"Point"}
}