{
  "type": "Feature",
  "properties": {
    "addr:full":"Brugstraat 20 Berlare Oost-Vlaanderen 9290",
    "addr:housenumber":"20",
    "addr:postcode":"9290",
    "addr:street":"Brugstraat",
    "iso:country":"BE",
    "sg:address":"Brugstraat 20",
    "sg:city":"Berlare",
    "sg:orig_category":"Entretien and r\u00e9parations de voitures",
    "sg:phone":"+32 52 42 72 85",
    "sg:postcode":"9290",
    "sg:province":"Oost-Vlaanderen",
    "wof:name":"Fa. Mustang",
    "wof:placetype":"venue"
},
  "geometry": {"coordinates":[4.0068879128,51.0105361938],"type":"Point"}
}