{
  "type": "Feature",
  "properties": {
    "iso:country":"BE",
    "sg:address":"Rue Du Thier 13",
    "sg:city":"Waimes/waimes",
    "sg:orig_category":"Eleveurs de bovins",
    "sg:phone":"+32 80 44 66 33",
    "sg:postcode":"4950",
    "sg:province":"Li\u00e8ge",
    "wof:name":"Clement Etienne",
    "wof:placetype":"venue"
},
  "geometry": {"coordinates":[6.1421399117,50.448600769],"type":"Point"}
}