{
  "type": "Feature",
  "properties": {
    "iso:country":"BE",
    "sg:address":"Nieuwstraat 29",
    "sg:city":"Denderleeuw",
    "sg:orig_category":"Electrom\u00e9nager, t\u00e9l\u00e9visions and radios",
    "sg:phone":"+32 53 66 61 16",
    "sg:postcode":"9470",
    "sg:province":"Oost-Vlaanderen",
    "wof:name":"Diependael",
    "wof:placetype":"venue"
},
  "geometry": {"coordinates":[4.0735111237,50.8802337646],"type":"Point"}
}