{
  "type": "Feature",
  "properties": {
    "addr:full":"Sch\u00f6nefelderweg 162 Eupen Li\u00e8ge 4700",
    "addr:housenumber":"162",
    "addr:postcode":"4700",
    "iso:country":"BE",
    "sg:address":"Sch\u00f6nefelderweg 162",
    "sg:city":"Eupen",
    "sg:classifiers":[
        {
            "category":"Communications",
            "type":"Services"
        }
    ],
    "sg:phone":"+32 87 74 05 91",
    "sg:postcode":"4700",
    "sg:province":"Li\u00e8ge",
    "sg:tags":[
        "translator"
    ],
    "wof:name":"Van Bossuyt",
    "wof:placetype":"venue"
},
  "geometry": {"coordinates":[6.0607800484,50.6297912598],"type":"Point"}
}