{
  "type": "Feature",
  "properties": {
    "iso:country":"BE",
    "sg:address":"Rue De La Dr\u00cave 26",
    "sg:city":"Clavier",
    "sg:orig_category":"Installation \u00e9lectrique r\u00e9sidentielle. R\u00e9parations \u00e0 domicile d'appareils \u00e9lectriques. R\u00e9parations d",
    "sg:phone":"+32 86 34 41 44",
    "sg:postcode":"4560",
    "sg:province":"Li\u00e8ge",
    "wof:name":"Jose Devillers",
    "wof:placetype":"venue"
},
  "geometry": {"coordinates":[5.3575191498,50.4288978577],"type":"Point"}
}