{
  "type": "Feature",
  "properties": {
    "addr:full":"Route De La Gileppe 22a Jalhay Li\u00e8ge 4845",
    "addr:housenumber":"22a",
    "addr:postcode":"4845",
    "addr:street":"Route De La Gileppe",
    "iso:country":"BE",
    "sg:address":"Route De La Gileppe 22a",
    "sg:city":"Jalhay",
    "sg:classifiers":[
        {
            "category":"Arts & Performance",
            "subcategory":"Theater",
            "type":"Entertainment"
        }
    ],
    "sg:phone":"+32 87 64 60 64",
    "sg:postcode":"4845",
    "sg:province":"Li\u00e8ge",
    "sg:tags":[
        "theatrical",
        "agency"
    ],
    "wof:name":"Amelie Productions Sprl",
    "wof:placetype":"venue"
},
  "geometry": {"coordinates":[5.9666728973,50.5653648376],"type":"Point"}
}