{
  "type": "Feature",
  "properties": {
    "iso:country":"BE",
    "sg:address":"Sint-amandsstraat 15",
    "sg:city":"Brugge",
    "sg:orig_category":"Eclairage et \u00e9quipements du foyer",
    "sg:phone":"+32 50 34 15 13",
    "sg:postcode":"8000",
    "sg:province":"West-Vlaanderen",
    "wof:name":"Imaginaire",
    "wof:placetype":"venue"
},
  "geometry": {"coordinates":[3.2225730419,51.208404541],"type":"Point"}
}