{
  "type": "Feature",
  "properties": {
    "addr:full":"Olmenstraat 7 Torhout West-Vlaanderen 8820",
    "addr:housenumber":"7",
    "addr:postcode":"8820",
    "addr:street":"Olmenstraat",
    "iso:country":"BE",
    "sg:address":"Olmenstraat 7",
    "sg:city":"Torhout",
    "sg:orig_category":"Installation de menuiserie en bois and plastique",
    "sg:phone":"+32 50 21 23 01",
    "sg:postcode":"8820",
    "sg:province":"West-Vlaanderen",
    "wof:name":"Rombaut",
    "wof:placetype":"venue"
},
  "geometry": {"coordinates":[3.0842850208,51.0696487427],"type":"Point"}
}