{
  "type": "Feature",
  "properties": {
    "addr:full":"Chauss\u00c9e De Wemmel 146 Jette Bruxelles-Capitale 1090",
    "addr:housenumber":"146",
    "addr:postcode":"1090",
    "addr:street":"Chausse\u0301E De Wemmel",
    "iso:country":"BE",
    "sg:address":"Chauss\u00c9e De Wemmel 146",
    "sg:city":"Jette",
    "sg:orig_category":"Plomberie, chauffage and installations sanitaires",
    "sg:phone":"+32 2 426 17 81",
    "sg:postcode":"1090",
    "sg:province":"Bruxelles-Capitale",
    "wof:name":"Csp Sprl-bvba",
    "wof:placetype":"venue"
},
  "geometry": {"coordinates":[4.3234767914,50.8771209717],"type":"Point"}
}