{
  "type": "Feature",
  "properties": {
    "addr:full":"Rue Des Savoyards 11 Marche-en-famenne Luxembourg 6900",
    "addr:housenumber":"11",
    "addr:postcode":"6900",
    "addr:street":"Rue Des Savoyards",
    "iso:country":"BE",
    "sg:address":"Rue Des Savoyards 11",
    "sg:city":"Marche-en-famenne",
    "sg:orig_category":"V\u00eatements pour b\u00e9b\u00e9s and enfants. V\u00eatements pour Hommes. V\u00eatements pour Dames",
    "sg:phone":"+32 84 32 21 73",
    "sg:postcode":"6900",
    "sg:province":"Luxembourg",
    "wof:name":"Fe. Jery & Co",
    "wof:placetype":"venue"
},
  "geometry": {"coordinates":[5.3447031975,50.2271194458],"type":"Point"}
}