{
  "type": "Feature",
  "properties": {
    "iso:country":"BE",
    "sg:address":"Rue Sarts De Wannebecq 6",
    "sg:city":"Lessines",
    "sg:orig_category":"Serres and speciale beglazing",
    "sg:phone":"+32 68 33 35 94",
    "sg:postcode":"7861",
    "sg:province":"Hainaut",
    "wof:name":"Glass Service Isolation",
    "wof:placetype":"venue"
},
  "geometry": {"coordinates":[3.8158209324,50.6867485046],"type":"Point"}
}