{
  "type": "Feature",
  "properties": {
    "iso:country":"BE",
    "sg:address":"Rue Visart De Bocarm\u00e9 5",
    "sg:city":"Namur (temploux)",
    "sg:classifiers":[
        {
            "category":"Education",
            "subcategory":"Special Training",
            "type":"Public Place"
        }
    ],
    "sg:phone":"+32 81 56 80 68",
    "sg:postcode":"5020",
    "sg:province":"Namur",
    "sg:tags":[
        "school",
        "flying"
    ],
    "wof:name":"Halleux Lenoble Sprl",
    "wof:placetype":"venue"
},
  "geometry": {"coordinates":[4.7952418327,50.4352035522],"type":"Point"}
}