{
  "type": "Feature",
  "properties": {
    "addr:full":"Zandstraat 75 Turnhout Antwerpen 2300",
    "addr:housenumber":"75",
    "addr:postcode":"2300",
    "addr:street":"Zandstraat",
    "iso:country":"BE",
    "sg:address":"Zandstraat 75",
    "sg:city":"Turnhout",
    "sg:classifiers":[
        {
            "category":"Food & Beverages",
            "subcategory":"Fruits & Vegetables",
            "type":"Retail Goods"
        }
    ],
    "sg:phone":"+32 14 41 18 48",
    "sg:postcode":"2300",
    "sg:province":"Antwerpen",
    "sg:tags":[
        "l\u00e9gumes",
        "gr"
    ],
    "wof:name":"Jacobus Van Laarhoven",
    "wof:placetype":"venue"
},
  "geometry": {"coordinates":[4.9343547821,51.3203735352],"type":"Point"}
}