{
  "type": "Feature",
  "properties": {
    "iso:country":"BE",
    "sg:address":"Rue D'eghez\u00e9e 23",
    "sg:city":"Fernelmont (forville)",
    "sg:classifiers":[
        {
            "category":"Real Estate",
            "subcategory":"Architect",
            "type":"Services"
        }
    ],
    "sg:phone":"+32 81 83 38 78",
    "sg:postcode":"5380",
    "sg:province":"Namur",
    "wof:name":"Bertin S",
    "wof:placetype":"venue"
},
  "geometry": {"coordinates":[5.0028247833,50.572467804],"type":"Point"}
}