{
  "type": "Feature",
  "properties": {
    "addr:full":"Slozenstraat 1 Meise Vlaams-Brabant 1861",
    "addr:housenumber":"1",
    "addr:postcode":"1861",
    "addr:street":"Slozenstraat",
    "iso:country":"BE",
    "sg:address":"Slozenstraat 1",
    "sg:city":"Meise",
    "sg:orig_category":"Rundveehouders",
    "sg:phone":"+32 52 30 91 97",
    "sg:postcode":"1861",
    "sg:province":"Vlaams-Brabant",
    "wof:name":"Frans Van Ransbeeck",
    "wof:placetype":"venue"
},
  "geometry": {"coordinates":[4.291079998,50.9803619385],"type":"Point"}
}