{
  "type": "Feature",
  "properties": {
    "addr:full":"Rue De Cousis 125bb Chapelle-lez-herlaimont Hainaut 7160",
    "addr:housenumber":"125bb",
    "addr:postcode":"7160",
    "addr:street":"Rue De Cousis",
    "iso:country":"BE",
    "sg:address":"Rue De Cousis 125bb",
    "sg:city":"Chapelle-lez-herlaimont",
    "sg:orig_category":"Schoonmaakbedrijven and ongediertebestrijding",
    "sg:phone":"+32 64 45 02 42",
    "sg:postcode":"7160",
    "sg:province":"Hainaut",
    "wof:name":"Luigino Epis",
    "wof:placetype":"venue"
},
  "geometry": {"coordinates":[4.2773070335,50.4864768982],"type":"Point"}
}