{
  "type": "Feature",
  "properties": {
    "addr:full":"Rue L\u00c9on Simon 8 Andenne Namur 5300",
    "addr:housenumber":"8",
    "addr:postcode":"5300",
    "addr:street":"Rue Le\u0301On Simon",
    "iso:country":"BE",
    "sg:address":"Rue L\u00c9on Simon 8",
    "sg:city":"Andenne",
    "sg:orig_category":"Verplichte sociale verzekeringen",
    "sg:phone":"+32 85 84 48 50",
    "sg:postcode":"5300",
    "sg:province":"Namur",
    "wof:name":"Mutualite Neutre",
    "wof:placetype":"venue"
},
  "geometry": {"coordinates":[5.0975899696,50.4872360229],"type":"Point"}
}