{
  "type": "Feature",
  "properties": {
    "addr:full":"Rue Des \u00celes 5 Stavelot Li\u00e8ge 4970",
    "addr:housenumber":"5",
    "addr:postcode":"4970",
    "addr:street":"Rue Des I\u0302Les",
    "iso:country":"BE",
    "sg:address":"Rue Des \u00celes 5",
    "sg:city":"Stavelot",
    "sg:classifiers":[
        {
            "category":"Professional",
            "subcategory":"Engineering",
            "type":"Services"
        }
    ],
    "sg:phone":"+32 80 86 25 41",
    "sg:postcode":"4970",
    "sg:province":"Li\u00e8ge",
    "sg:tags":[
        "machine",
        "-",
        "mechanical"
    ],
    "wof:name":"Egc Sa",
    "wof:placetype":"venue"
},
  "geometry": {"coordinates":[5.925134182,50.3938102722],"type":"Point"}
}