{
  "type": "Feature",
  "properties": {
    "iso:country":"BE",
    "sg:address":"Rue De Fer 105",
    "sg:city":"Namur",
    "sg:classifiers":[
        {
            "category":"Parking",
            "subcategory":"Garage",
            "type":"Transportation"
        }
    ],
    "sg:phone":"+32 81 22 32 04",
    "sg:postcode":"5000",
    "sg:province":"Namur",
    "wof:name":"Parking Du Centre",
    "wof:placetype":"venue"
},
  "geometry": {"coordinates":[4.8652977943,50.4670524597],"type":"Point"}
}