{
  "type": "Feature",
  "properties": {
    "addr:full":"Tiensesteenweg 109 Bierbeek (korbeek-lo) Vlaams-Brabant 3360",
    "addr:housenumber":"109",
    "addr:postcode":"3360",
    "addr:street":"Tiensesteenweg",
    "iso:country":"BE",
    "sg:address":"Tiensesteenweg 109",
    "sg:city":"Bierbeek (korbeek-lo)",
    "sg:classifiers":[
        {
            "category":"Bakery",
            "type":"Food & Drink"
        }
    ],
    "sg:phone":"+32 16 46 11 49",
    "sg:postcode":"3360",
    "sg:province":"Vlaams-Brabant",
    "sg:tags":[
        "confectioner",
        "baker"
    ],
    "wof:name":"Depotter-van Biesen",
    "wof:placetype":"venue"
},
  "geometry": {"coordinates":[4.7620887756,50.8627471924],"type":"Point"}
}