{
  "type": "Feature",
  "properties": {
    "iso:country":"BE",
    "sg:address":"Avenue D'audenarde 1ba",
    "sg:city":"Tournai",
    "sg:classifiers":[
        {
            "category":"Insurance",
            "subcategory":"Life Insurance",
            "type":"Services"
        }
    ],
    "sg:phone":"+32 69 22 24 28",
    "sg:postcode":"7540",
    "sg:province":"Hainaut",
    "sg:tags":[
        "assurance"
    ],
    "wof:name":"Dubois & Leulier",
    "wof:placetype":"venue"
},
  "geometry": {"coordinates":[3.3779420853,50.6316261292],"type":"Point"}
}