{
  "type": "Feature",
  "properties": {
    "addr:full":"Rue Des Lavandi\u00e8res 23 Bouillon (poupehan) Luxembourg 6830",
    "addr:housenumber":"23",
    "addr:postcode":"6830",
    "addr:street":"Rue Des Lavandie\u0300Res",
    "iso:country":"BE",
    "sg:address":"Rue Des Lavandi\u00e8res 23",
    "sg:city":"Bouillon (poupehan)",
    "sg:classifiers":[
        {
            "category":"Building & Trades",
            "subcategory":"Construction",
            "type":"Services"
        }
    ],
    "sg:phone":"+32 61 46 82 58",
    "sg:postcode":"6830",
    "sg:province":"Luxembourg",
    "sg:tags":[
        "carpenter"
    ],
    "wof:name":"Mees P",
    "wof:placetype":"venue"
},
  "geometry": {"coordinates":[5.0699849129,49.7954597473],"type":"Point"}
}