{
  "type": "Feature",
  "properties": {
    "addr:full":"Rue Bertaux Joseph 1 Charleroi (jumet) Hainaut 6040",
    "addr:housenumber":"1",
    "addr:postcode":"6040",
    "addr:street":"Rue Bertaux Joseph",
    "iso:country":"BE",
    "sg:address":"Rue Bertaux Joseph 1",
    "sg:city":"Charleroi (jumet)",
    "sg:classifiers":[
        {
            "category":"Utilities",
            "subcategory":"Refuse",
            "type":"Services"
        }
    ],
    "sg:phone":"+32 71 35 35 60",
    "sg:postcode":"6040",
    "sg:province":"Hainaut",
    "sg:tags":[
        "removal"
    ],
    "wof:name":"Demenagement Huart",
    "wof:placetype":"venue"
},
  "geometry": {"coordinates":[4.4356069565,50.4469947815],"type":"Point"}
}