{
  "type": "Feature",
  "properties": {
    "addr:full":"Wapenmakersstraat 7 Brugge West-Vlaanderen 8000",
    "addr:housenumber":"7",
    "addr:postcode":"8000",
    "addr:street":"Wapenmakersstraat",
    "iso:country":"BE",
    "sg:address":"Wapenmakersstraat 7",
    "sg:city":"Brugge",
    "sg:orig_category":"Fleurs and plantes",
    "sg:phone":"+32 50 33 48 12",
    "sg:postcode":"8000",
    "sg:province":"West-Vlaanderen",
    "wof:name":"Ludwig Vandaele",
    "wof:placetype":"venue"
},
  "geometry": {"coordinates":[3.226514101,51.2098693848],"type":"Point"}
}