{
  "type": "Feature",
  "properties": {
    "addr:full":"Gemeentestraat 31bb Nijlen Antwerpen 2560",
    "addr:housenumber":"31bb",
    "addr:postcode":"2560",
    "addr:street":"Gemeentestraat",
    "iso:country":"BE",
    "sg:address":"Gemeentestraat 31bb",
    "sg:city":"Nijlen",
    "sg:classifiers":[
        {
            "category":"Insurance",
            "subcategory":"Life Insurance",
            "type":"Services"
        }
    ],
    "sg:phone":"+32 3 411 01 39",
    "sg:postcode":"2560",
    "sg:province":"Antwerpen",
    "sg:tags":[
        "assurance"
    ],
    "wof:name":"Dipa & Nevelsteen",
    "wof:placetype":"venue"
},
  "geometry": {"coordinates":[4.6731858253,51.1613807678],"type":"Point"}
}