{
  "type": "Feature",
  "properties": {
    "addr:full":"Molenstraat 261 Grimbergen (humbeek) Vlaams-Brabant 1851",
    "addr:housenumber":"261",
    "addr:postcode":"1851",
    "addr:street":"Molenstraat",
    "iso:country":"BE",
    "sg:address":"Molenstraat 261",
    "sg:city":"Grimbergen (humbeek)",
    "sg:classifiers":[
        {
            "category":"Utilities",
            "subcategory":"Fuel Oil & Lpg",
            "type":"Services"
        }
    ],
    "sg:phone":"+32 2 266 80 80",
    "sg:postcode":"1851",
    "sg:province":"Vlaams-Brabant",
    "wof:name":"Verdickt Henri",
    "wof:placetype":"venue"
},
  "geometry": {"coordinates":[4.3657298088,50.9720802307],"type":"Point"}
}