{
  "type": "Feature",
  "properties": {
    "iso:country":"BE",
    "sg:address":"De Robianostraat 18",
    "sg:city":"Tervuren",
    "sg:orig_category":"M\u00e9decines alternatives",
    "sg:phone":"+32 2 767 90 32",
    "sg:postcode":"3080",
    "sg:province":"Vlaams-Brabant",
    "wof:name":"C. Rousseau",
    "wof:placetype":"venue"
},
  "geometry": {"coordinates":[4.5069332123,50.8244132996],"type":"Point"}
}