{
  "type": "Feature",
  "properties": {
    "addr:full":"'s Gravenstraat 58 Nazareth Oost-Vlaanderen 9810",
    "addr:housenumber":"58",
    "addr:postcode":"9810",
    "addr:street":"' S Gravenstraat",
    "iso:country":"BE",
    "sg:address":"'s Gravenstraat 58",
    "sg:city":"Nazareth",
    "sg:orig_category":"Elektrische installaties voor woningen",
    "sg:phone":"+32 9 385 88 81",
    "sg:postcode":"9810",
    "sg:province":"Oost-Vlaanderen",
    "wof:name":"Alcotec",
    "wof:placetype":"venue"
},
  "geometry": {"coordinates":[3.5951368809,50.9601554871],"type":"Point"}
}