{
  "type": "Feature",
  "properties": {
    "addr:full":"Chemin Des Baraques 40 Waterloo Brabant Wallon 1410",
    "addr:housenumber":"40",
    "addr:postcode":"1410",
    "addr:street":"Chemin Des Baraques",
    "iso:country":"BE",
    "sg:address":"Chemin Des Baraques 40",
    "sg:city":"Waterloo",
    "sg:orig_category":"Services pour animaux domestiques",
    "sg:phone":"+32 2 354 26 72",
    "sg:postcode":"1410",
    "sg:province":"Brabant Wallon",
    "wof:name":"Les Baraques",
    "wof:placetype":"venue"
},
  "geometry": {"coordinates":[4.4260392189,50.7051773071],"type":"Point"}
}