{
  "type": "Feature",
  "properties": {
    "iso:country":"BE",
    "sg:address":"Bovenhoek 22",
    "sg:city":"Lebbeke",
    "sg:orig_category":"V\u00e9hicules automobiles. Entretien and r\u00e9parations de voitures",
    "sg:phone":"+32 53 78 60 32",
    "sg:postcode":"9280",
    "sg:province":"Oost-Vlaanderen",
    "wof:name":"Garage Pieters",
    "wof:placetype":"venue"
},
  "geometry": {"coordinates":[4.0869441032,50.9808692932],"type":"Point"}
}