{
  "type": "Feature",
  "properties": {
    "addr:full":"Antwerpsesteenweg 342 Lier Antwerpen 2500",
    "addr:housenumber":"342",
    "addr:postcode":"2500",
    "addr:street":"Antwerpsesteenweg",
    "iso:country":"BE",
    "sg:address":"Antwerpsesteenweg 342",
    "sg:city":"Lier",
    "sg:classifiers":[
        {
            "category":"Autos & Motor Vehicles",
            "subcategory":"Motorcycle Sales",
            "type":"Retail Goods"
        }
    ],
    "sg:phone":"+32 3 489 23 11",
    "sg:postcode":"2500",
    "sg:province":"Antwerpen",
    "sg:tags":[
        "motorbike"
    ],
    "wof:name":"Motor Service Selbach-mss",
    "wof:placetype":"venue"
},
  "geometry": {"coordinates":[4.5428209305,51.145488739],"type":"Point"}
}