{
  "type": "Feature",
  "properties": {
    "iso:country":"BE",
    "sg:address":"Rue Du Baron D'obin 132",
    "sg:city":"Wasseiges",
    "sg:classifiers":[
        {
            "category":"Fast Food",
            "type":"Food & Drink"
        }
    ],
    "sg:phone":"+32 81 85 65 25",
    "sg:postcode":"4219",
    "sg:province":"Li\u00e8ge",
    "sg:tags":[
        "fried",
        "stand",
        "potato"
    ],
    "wof:name":"Au P'tit Creux",
    "wof:placetype":"venue"
},
  "geometry": {"coordinates":[5.003909111,50.6229629517],"type":"Point"}
}