{
  "type": "Feature",
  "properties": {
    "addr:full":"Landbouwersstraat 10 De Panne West-Vlaanderen 8660",
    "addr:housenumber":"10",
    "addr:postcode":"8660",
    "addr:street":"Landbouwersstraat",
    "iso:country":"BE",
    "sg:address":"Landbouwersstraat 10",
    "sg:city":"De Panne",
    "sg:orig_category":"Tuinbenodigdheden",
    "sg:phone":"+32 58 41 25 49",
    "sg:postcode":"8660",
    "sg:province":"West-Vlaanderen",
    "wof:name":"Cabines Weekend",
    "wof:placetype":"venue"
},
  "geometry": {"coordinates":[2.6138150692,51.0935287476],"type":"Point"}
}