{
  "type": "Feature",
  "properties": {
    "iso:country":"BE",
    "sg:address":"Boulevard Pierre Mayence 1",
    "sg:city":"Charleroi",
    "sg:classifiers":[
        {
            "category":"Manufacturing",
            "subcategory":"Petroleum Products",
            "type":"Manufacturing & Wholesale Goods"
        }
    ],
    "sg:phone":"+32 71 27 12 11",
    "sg:postcode":"6000",
    "sg:province":"Hainaut",
    "sg:tags":[
        "production",
        "combustible",
        "de",
        "distribution",
        "gaz"
    ],
    "wof:name":"I.g.h.",
    "wof:placetype":"venue"
},
  "geometry": {"coordinates":[4.4515490532,50.407585144],"type":"Point"}
}