{
  "type": "Feature",
  "properties": {
    "addr:full":"Statiestraat 19 Antwerpen Antwerpen 2018",
    "addr:housenumber":"19",
    "addr:postcode":"2018",
    "addr:street":"Statiestraat",
    "iso:country":"BE",
    "sg:address":"Statiestraat 19",
    "sg:city":"Antwerpen",
    "sg:classifiers":[
        {
            "category":"Fast Food",
            "type":"Food & Drink"
        }
    ],
    "sg:phone":"+32 3 233 57 57",
    "sg:postcode":"2018",
    "sg:province":"Antwerpen",
    "sg:tags":[
        "meeneem",
        "restaurant"
    ],
    "wof:name":"Roma",
    "wof:placetype":"venue"
},
  "geometry": {"coordinates":[4.4191827774,51.218296051],"type":"Point"}
}