{
  "type": "Feature",
  "properties": {
    "addr:full":"Rue Grande 33 Beloeil Hainaut 7971",
    "addr:housenumber":"33",
    "addr:postcode":"7971",
    "addr:street":"Rue Grande",
    "iso:country":"BE",
    "sg:address":"Rue Grande 33",
    "sg:city":"Beloeil",
    "sg:orig_category":"V\u00eatements pour Dames. V\u00eatements pour Hommes. V\u00eatements pour b\u00e9b\u00e9s and enfants",
    "sg:phone":"+32 69 57 54 73",
    "sg:postcode":"7971",
    "sg:province":"Hainaut",
    "wof:name":"Maison Saffre",
    "wof:placetype":"venue"
},
  "geometry": {"coordinates":[3.6594901085,50.521030426],"type":"Point"}
}