{
  "type": "Feature",
  "properties": {
    "addr:full":"Rue De Huy 109 Hannut (villers-le-peuplier) Li\u00e8ge 4280",
    "addr:housenumber":"109",
    "addr:postcode":"4280",
    "addr:street":"Rue De Huy;Villers-Le-Peuplier",
    "iso:country":"BE",
    "sg:address":"Rue De Huy 109",
    "sg:city":"Hannut (villers-le-peuplier)",
    "sg:classifiers":[
        {
            "category":"Autos & Motor Vehicles",
            "subcategory":"Automobile Sales",
            "type":"Retail Goods"
        }
    ],
    "sg:phone":"+32 19 51 59 57",
    "sg:postcode":"4280",
    "sg:province":"Li\u00e8ge",
    "sg:tags":[
        "car",
        "used",
        "-"
    ],
    "wof:name":"Seb & Ric Auto",
    "wof:placetype":"venue"
},
  "geometry": {"coordinates":[5.0926198959,50.6642913818],"type":"Point"}
}