{
  "type": "Feature",
  "properties": {
    "iso:country":"BE",
    "sg:address":"Rijksweg 195",
    "sg:city":"Maasmechelen",
    "sg:orig_category":"Plaatsen van vloer- and muurbekleding Schilders",
    "sg:phone":"+32 89 77 38 20",
    "sg:postcode":"3630",
    "sg:province":"Limburg",
    "wof:name":"Driessens",
    "wof:placetype":"venue"
},
  "geometry": {"coordinates":[5.7006402016,50.9777984619],"type":"Point"}
}