{
  "type": "Feature",
  "properties": {
    "addr:full":"Chauss\u00e9e Du Roeulx 114b Soignies Hainaut 7060",
    "addr:housenumber":"114b",
    "addr:postcode":"7060",
    "addr:street":"Chausse\u0301E Du Roeulx",
    "iso:country":"BE",
    "sg:address":"Chauss\u00e9e Du Roeulx 114b",
    "sg:city":"Soignies",
    "sg:classifiers":[
        {
            "category":"Manufacturing",
            "subcategory":"Glass & Minerals",
            "type":"Manufacturing & Wholesale Goods"
        }
    ],
    "sg:phone":"+32 67 33 43 16",
    "sg:postcode":"7060",
    "sg:province":"Hainaut",
    "sg:tags":[
        "automobile",
        "-"
    ],
    "wof:name":"Ets Olivier Thewissen",
    "wof:placetype":"venue"
},
  "geometry": {"coordinates":[4.0694298744,50.568977356],"type":"Point"}
}