{
  "type": "Feature",
  "properties": {
    "iso:country":"BE",
    "sg:address":"Leopoldstraat 93",
    "sg:city":"Mechelen",
    "sg:orig_category":"Huwelijks- and Relatiebureaus",
    "sg:phone":"+32 15 41 17 10",
    "sg:postcode":"2800",
    "sg:province":"Antwerpen",
    "wof:name":"Happy People",
    "wof:placetype":"venue"
},
  "geometry": {"coordinates":[4.4810647964,51.0186157227],"type":"Point"}
}