{
  "type": "Feature",
  "properties": {
    "addr:full":"Grote Breebeemdlaan 5 Hasselt (kuringen) Limburg 3511",
    "addr:housenumber":"5",
    "addr:postcode":"3511",
    "addr:street":"Grote Breebeemdlaan",
    "iso:country":"BE",
    "sg:address":"Grote Breebeemdlaan 5",
    "sg:city":"Hasselt (kuringen)",
    "sg:classifiers":[
        {
            "category":"Communications",
            "type":"Services"
        }
    ],
    "sg:phone":"+32 11 25 20 99",
    "sg:postcode":"3511",
    "sg:province":"Limburg",
    "sg:tags":[
        "translator"
    ],
    "wof:name":"Tringova M",
    "wof:placetype":"venue"
},
  "geometry": {"coordinates":[5.3007969856,50.9473114014],"type":"Point"}
}