{
  "type": "Feature",
  "properties": {
    "iso:country":"BE",
    "sg:address":"Chauss\u00e9e De Philippeville 58",
    "sg:city":"Couvin (mariembourg)",
    "sg:classifiers":[
        {
            "category":"Retail",
            "subcategory":"Auto Repair",
            "type":"Services"
        }
    ],
    "sg:phone":"+32 60 31 18 13",
    "sg:postcode":"5660",
    "sg:province":"Namur",
    "sg:tags":[
        "garage"
    ],
    "wof:name":"Bellenger C (garage)",
    "wof:placetype":"venue"
},
  "geometry": {"coordinates":[4.5215997696,50.0891494751],"type":"Point"}
}