{
  "type": "Feature",
  "properties": {
    "addr:full":"Dorpsstraat 100 Overpelt Limburg 3900",
    "addr:housenumber":"100",
    "addr:postcode":"3900",
    "addr:street":"Dorpsstraat",
    "iso:country":"BE",
    "sg:address":"Dorpsstraat 100",
    "sg:city":"Overpelt",
    "sg:orig_category":"Banken and kredietinstellingen",
    "sg:phone":"+32 11 66 61 41",
    "sg:postcode":"3900",
    "sg:province":"Limburg",
    "wof:name":"Daniels & Gielen Bvba",
    "wof:placetype":"venue"
},
  "geometry": {"coordinates":[5.4228219986,51.211856842],"type":"Point"}
}