{
  "type": "Feature",
  "properties": {
    "addr:full":"Onderstraat 98 Gavere Oost-Vlaanderen 9890",
    "addr:housenumber":"98",
    "addr:postcode":"9890",
    "addr:street":"Onderstraat",
    "iso:country":"BE",
    "sg:address":"Onderstraat 98",
    "sg:city":"Gavere",
    "sg:classifiers":[
        {
            "category":"Retail",
            "subcategory":"Event Space",
            "type":"Services"
        }
    ],
    "sg:phone":"+32 9 384 87 67",
    "sg:postcode":"9890",
    "sg:province":"Oost-Vlaanderen",
    "sg:tags":[
        "rental",
        "-",
        "hall"
    ],
    "wof:name":"Kelderke ('t)",
    "wof:placetype":"venue"
},
  "geometry": {"coordinates":[3.6606049538,50.9306640625],"type":"Point"}
}