{
  "type": "Feature",
  "properties": {
    "addr:full":"Rue De L' Etang 1 Incourt Brabant Wallon 1315",
    "addr:housenumber":"1",
    "addr:postcode":"1315",
    "addr:street":"Rue De L ' Etang",
    "iso:country":"BE",
    "sg:address":"Rue De L' Etang 1",
    "sg:city":"Incourt",
    "sg:classifiers":[
        {
            "category":"Building & Trades",
            "subcategory":"Landscaping Services",
            "type":"Services"
        }
    ],
    "sg:phone":"+32 10 88 87 19",
    "sg:postcode":"1315",
    "sg:province":"Brabant Wallon",
    "sg:tags":[
        "earth",
        "moving"
    ],
    "wof:name":"Dupont G. S.p.r.l.",
    "wof:placetype":"venue"
},
  "geometry": {"coordinates":[2.1278650761,50.3441352844],"type":"Point"}
}