{
  "type": "Feature",
  "properties": {
    "iso:country":"BE",
    "sg:address":"Rue De L'automne 28",
    "sg:city":"Elsene/ixelles",
    "sg:orig_category":"Entretien and r\u00e9parations de voitures",
    "sg:phone":"+32 2 648 73 20",
    "sg:postcode":"1050",
    "sg:province":"Bruxelles-Capitale",
    "wof:name":"P.m.r.",
    "wof:placetype":"venue"
},
  "geometry": {"coordinates":[4.3889122009,50.819568634],"type":"Point"}
}