{
  "type": "Feature",
  "properties": {
    "addr:full":"Chauss\u00e9e De Gand 204 Bruxelles (molenbeek-saint-jean) Bruxelles-Capitale 1080",
    "addr:housenumber":"204",
    "addr:postcode":"1080",
    "addr:street":"Chausse\u0301E De Gand",
    "iso:country":"BE",
    "sg:address":"Chauss\u00e9e De Gand 204",
    "sg:city":"Bruxelles (molenbeek-saint-jean)",
    "sg:classifiers":[
        {
            "category":"Health Services",
            "subcategory":"Doctor",
            "type":"Services"
        }
    ],
    "sg:phone":"+32 2 411 66 33",
    "sg:postcode":"1080",
    "sg:province":"Bruxelles-Capitale",
    "sg:tags":[
        "medicinephysicians",
        "surgeon"
    ],
    "wof:name":"Hanafi Z",
    "wof:placetype":"venue"
},
  "geometry": {"coordinates":[4.3320980072,50.8569488525],"type":"Point"}
}