{
  "type": "Feature",
  "properties": {
    "addr:full":"Leopold Ii Laan 148 Sint-jans-molenbeek/molenbeek-saint-jean Bruxelles-Capitale 1080",
    "addr:housenumber":"148;/",
    "addr:postcode":"1080",
    "addr:street":"Leopold Ii Laan;Sint-Jans-Molenbeek",
    "iso:country":"BE",
    "sg:address":"Leopold Ii Laan 148",
    "sg:city":"Sint-jans-molenbeek/molenbeek-saint-jean",
    "sg:orig_category":"Antiek",
    "sg:phone":"+32 2 414 00 53",
    "sg:postcode":"1080",
    "sg:province":"Bruxelles-Capitale",
    "wof:name":"Maison Ghisoni-giordano",
    "wof:placetype":"venue"
},
  "geometry": {"coordinates":[4.3371310234,50.8610305786],"type":"Point"}
}