{
  "type": "Feature",
  "properties": {
    "addr:full":"Onze-lieve-vrouwstraat 2 Gent (oostakker) Oost-Vlaanderen 9041",
    "addr:housenumber":"2",
    "addr:postcode":"9041",
    "addr:street":"Onze-Lieve-Vrouwstraat",
    "iso:country":"BE",
    "sg:address":"Onze-lieve-vrouwstraat 2",
    "sg:city":"Gent (oostakker)",
    "sg:classifiers":[
        {
            "category":"Building & Trades",
            "subcategory":"Pest Control",
            "type":"Services"
        }
    ],
    "sg:phone":"+32 9 251 53 43",
    "sg:postcode":"9041",
    "sg:province":"Oost-Vlaanderen",
    "sg:tags":[
        "painting",
        "contractor"
    ],
    "wof:name":"Van Overmeiren P",
    "wof:placetype":"venue"
},
  "geometry": {"coordinates":[3.7642490864,51.080329895],"type":"Point"}
}