{
  "type": "Feature",
  "properties": {
    "addr:full":"Place G\u00e9n\u00e9ral Meiser 14 Bruxelles (schaerbeek) Bruxelles-Capitale 1030",
    "addr:housenumber":"14",
    "addr:postcode":"1030",
    "addr:street":"Place Ge\u0301Ne\u0301Ral Meiser",
    "iso:country":"BE",
    "sg:address":"Place G\u00e9n\u00e9ral Meiser 14",
    "sg:city":"Bruxelles (schaerbeek)",
    "sg:classifiers":[
        {
            "category":"Health Services",
            "subcategory":"Doctor",
            "type":"Services"
        }
    ],
    "sg:phone":"+32 2 705 34 86",
    "sg:postcode":"1030",
    "sg:province":"Bruxelles-Capitale",
    "sg:tags":[
        "medicinephysicians",
        "surgeon"
    ],
    "wof:name":"Lajzerowicz Evelyne",
    "wof:placetype":"venue"
},
  "geometry": {"coordinates":[4.3978838921,50.8551254272],"type":"Point"}
}