{
  "type": "Feature",
  "properties": {
    "iso:country":"BE",
    "sg:address":"Nederholbeekstraat 140",
    "sg:city":"Maarkedal",
    "sg:classifiers":[
        {
            "category":"Military Area",
            "subcategory":"Armory",
            "type":"Public Place"
        }
    ],
    "sg:phone":"+32 55 31 21 67",
    "sg:postcode":"9680",
    "sg:province":"Oost-Vlaanderen",
    "sg:tags":[
        "armes",
        "munition"
    ],
    "wof:name":"Huis Arbo",
    "wof:placetype":"venue"
},
  "geometry": {"coordinates":[3.6218791008,50.8030395508],"type":"Point"}
}