{
  "type": "Feature",
  "properties": {
    "iso:country":"BE",
    "sg:address":"Driekoningenstraat 41",
    "sg:city":"Sint-niklaas",
    "sg:classifiers":[
        {
            "category":"Building & Trades",
            "subcategory":"Pest Control",
            "type":"Services"
        }
    ],
    "sg:phone":"+32 3 776 29 39",
    "sg:postcode":"9100",
    "sg:province":"Oost-Vlaanderen",
    "sg:tags":[
        "painting",
        "contractor"
    ],
    "wof:name":"Baetens L",
    "wof:placetype":"venue"
},
  "geometry": {"coordinates":[4.1402797699,51.1717300415],"type":"Point"}
}