{
  "type": "Feature",
  "properties": {
    "addr:full":"Ninoofsesteenweg 535 Dilbeek (itterbeek) Vlaams-Brabant 1701",
    "addr:housenumber":"535",
    "addr:postcode":"1701",
    "addr:street":"Ninoofsesteenweg",
    "iso:country":"BE",
    "sg:address":"Ninoofsesteenweg 535",
    "sg:city":"Dilbeek (itterbeek)",
    "sg:classifiers":[
        {
            "category":"Retail",
            "subcategory":"Auto Repair",
            "type":"Services"
        }
    ],
    "sg:phone":"+32 2 569 16 99",
    "sg:postcode":"1701",
    "sg:province":"Vlaams-Brabant",
    "sg:tags":[
        "breakdown",
        "automobile",
        "-",
        "recovery"
    ],
    "wof:name":"Crono Bvba",
    "wof:placetype":"venue"
},
  "geometry": {"coordinates":[4.2474551201,50.842716217],"type":"Point"}
}