{
  "type": "Feature",
  "properties": {
    "addr:full":"Papestraat 7-8 Wevelgem West-Vlaanderen 8560",
    "addr:housenumber":"7-8",
    "addr:postcode":"8560",
    "addr:street":"Papestraat",
    "iso:country":"BE",
    "sg:address":"Papestraat 7-8",
    "sg:city":"Wevelgem",
    "sg:classifiers":[
        {
            "category":"Wholesale",
            "subcategory":"Vending Machines",
            "type":"Manufacturing & Wholesale Goods"
        }
    ],
    "sg:phone":"+32 56 41 65 01",
    "sg:postcode":"8560",
    "sg:province":"West-Vlaanderen",
    "sg:tags":[
        "mat\u00e9riel",
        "de",
        "bureau",
        "gr",
        "fournitures"
    ],
    "wof:name":"Buro Service",
    "wof:placetype":"venue"
},
  "geometry": {"coordinates":[3.1811449528,50.8122062683],"type":"Point"}
}