{
  "type": "Feature",
  "properties": {
    "addr:full":"Graaf De Smet De Naeyerlaan 19 Oostende West-Vlaanderen 8400",
    "addr:housenumber":"19",
    "addr:postcode":"8400",
    "addr:street":"Graaf De Smet De Naeyerlaan",
    "iso:country":"BE",
    "sg:address":"Graaf De Smet De Naeyerlaan 19",
    "sg:city":"Oostende",
    "sg:classifiers":[
        {
            "category":"Arts & Performance",
            "subcategory":"Theater",
            "type":"Entertainment"
        }
    ],
    "sg:phone":"+32 59 50 70 40",
    "sg:postcode":"8400",
    "sg:province":"West-Vlaanderen",
    "sg:tags":[
        "concert-halls",
        "theatre"
    ],
    "wof:name":"Illusie (de)",
    "wof:placetype":"venue"
},
  "geometry": {"coordinates":[2.92374897,51.2256584167],"type":"Point"}
}