{
  "type": "Feature",
  "properties": {
    "addr:full":"Rue Maria Thom\u00e9e 1 Ath Hainaut 7800",
    "addr:housenumber":"1",
    "addr:postcode":"7800",
    "addr:street":"Rue Maria Thome\u0301E",
    "iso:country":"BE",
    "sg:address":"Rue Maria Thom\u00e9e 1",
    "sg:city":"Ath",
    "sg:classifiers":[
        {
            "category":"Health Services",
            "subcategory":"Health Practitioner",
            "type":"Services"
        }
    ],
    "sg:phone":"+32 68 26 26 37",
    "sg:postcode":"7800",
    "sg:province":"Hainaut",
    "sg:tags":[
        "physiotherapist"
    ],
    "wof:name":"Wallemacq Eric",
    "wof:placetype":"venue"
},
  "geometry": {"coordinates":[3.7773780823,50.6344985962],"type":"Point"}
}