{
  "type": "Feature",
  "properties": {
    "addr:full":"Rue Motte 28 Beaumont (str\u00e9e) Hainaut 6511",
    "addr:housenumber":"28",
    "addr:postcode":"6511",
    "addr:street":"Rue Motte",
    "iso:country":"BE",
    "sg:address":"Rue Motte 28",
    "sg:city":"Beaumont (str\u00e9e)",
    "sg:classifiers":[
        {
            "category":"Personal",
            "subcategory":"Massage",
            "type":"Services"
        }
    ],
    "sg:phone":"+32 71 53 40 19",
    "sg:postcode":"6511",
    "sg:province":"Hainaut",
    "wof:name":"Callens M.r.",
    "wof:placetype":"venue"
},
  "geometry": {"coordinates":[4.2931098938,50.277671814],"type":"Point"}
}