{
  "type": "Feature",
  "properties": {
    "addr:full":"Norbert Neeckxlaan 50b Lommel Limburg 3920",
    "addr:housenumber":"50b",
    "addr:postcode":"3920",
    "addr:street":"Neeckxlaan",
    "iso:country":"BE",
    "sg:address":"Norbert Neeckxlaan 50b",
    "sg:city":"Lommel",
    "sg:orig_category":"S\u00e9lection de personnel and placement",
    "sg:phone":"+32 11 54 22 49",
    "sg:postcode":"3920",
    "sg:province":"Limburg",
    "wof:name":"Vdab",
    "wof:placetype":"venue"
},
  "geometry": {"coordinates":[5.3247599602,51.2261352539],"type":"Point"}
}