{
  "type": "Feature",
  "properties": {
    "addr:full":"Bredestraat 13 Scherpenheuvel-zichem Vlaams-Brabant 3271",
    "addr:housenumber":"13",
    "addr:postcode":"3271",
    "addr:street":"Bredestraat",
    "iso:country":"BE",
    "sg:address":"Bredestraat 13",
    "sg:city":"Scherpenheuvel-zichem",
    "sg:classifiers":[
        {
            "category":"Arena",
            "subcategory":"Sports Club",
            "type":"Entertainment"
        }
    ],
    "sg:phone":"+32 13 78 24 47",
    "sg:postcode":"3271",
    "sg:province":"Vlaams-Brabant",
    "sg:tags":[
        "terrain",
        "hors",
        "de",
        "installation",
        "sportifs"
    ],
    "wof:name":"K. Everbeur Sp. Averbode",
    "wof:placetype":"venue"
},
  "geometry": {"coordinates":[4.9853920937,51.0228767395],"type":"Point"}
}