{
  "type": "Feature",
  "properties": {
    "iso:country":"BE",
    "sg:address":"Waverse Steenweg 1073",
    "sg:city":"Oudergem/auderghem",
    "sg:orig_category":"Advocaten and juridische adviseurs",
    "sg:phone":"+32 2 629 00 70",
    "sg:postcode":"1160",
    "sg:province":"Bruxelles-Capitale",
    "wof:name":"Aurore Smoliar",
    "wof:placetype":"venue"
},
  "geometry": {"coordinates":[4.3996109962,50.8245048523],"type":"Point"}
}