{
  "type": "Feature",
  "properties": {
    "addr:full":"Tervuursestw 156-158 Bertem Vlaams-Brabant 3060",
    "addr:housenumber":"156-158",
    "addr:postcode":"3060",
    "iso:country":"BE",
    "sg:address":"Tervuursestw 156-158",
    "sg:city":"Bertem",
    "sg:classifiers":[
        {
            "category":"Banks & Credit Unions",
            "subcategory":"Bank",
            "type":"Services"
        }
    ],
    "sg:phone":"+32 16 48 92 34",
    "sg:postcode":"3060",
    "sg:province":"Vlaams-Brabant",
    "wof:name":"Gemeentekrediet",
    "wof:placetype":"venue"
},
  "geometry": {"coordinates":[4.6322240829,50.8662910461],"type":"Point"}
}