{
  "type": "Feature",
  "properties": {
    "iso:country":"BE",
    "sg:address":"Stationsstraat 54",
    "sg:city":"Leopoldsburg",
    "sg:classifiers":[
        {
            "category":"Shopping",
            "subcategory":"Clothing, Apparel, & Fashions",
            "type":"Retail Goods"
        }
    ],
    "sg:phone":"+32 11 34 40 71",
    "sg:postcode":"3970",
    "sg:province":"Limburg",
    "sg:tags":[
        "clothing",
        "-",
        "motorbike",
        "equipment"
    ],
    "wof:name":"Kasjbah",
    "wof:placetype":"venue"
},
  "geometry": {"coordinates":[5.2600140572,51.1175308228],"type":"Point"}
}