{
  "type": "Feature",
  "properties": {
    "addr:full":"Aachener Strasse 3-5 Eupen/eupen Li\u00e8ge 4700",
    "addr:housenumber":"3-5",
    "addr:postcode":"4700",
    "addr:street":"Aachener Strasse",
    "iso:country":"BE",
    "sg:address":"Aachener Strasse 3-5",
    "sg:city":"Eupen/eupen",
    "sg:orig_category":"Sociale secretariaten",
    "sg:phone":"+32 87 55 72 72",
    "sg:postcode":"4700",
    "sg:province":"Li\u00e8ge",
    "wof:name":"Alia",
    "wof:placetype":"venue"
},
  "geometry": {"coordinates":[6.0308761597,50.6322288513],"type":"Point"}
}