{
  "type": "Feature",
  "properties": {
    "iso:country":"BE",
    "sg:address":"Bruggestraat 335",
    "sg:city":"Ingelmunster",
    "sg:orig_category":"Producteurs de l\u00e9gumes",
    "sg:phone":"+32 51 48 61 18",
    "sg:postcode":"8770",
    "sg:province":"West-Vlaanderen",
    "wof:name":"Geert Sentobin",
    "wof:placetype":"venue"
},
  "geometry": {"coordinates":[3.2477378845,50.9446678162],"type":"Point"}
}