{
  "type": "Feature",
  "properties": {
    "addr:full":"Koningin Fabiolapark 256 Sint-niklaas Oost-Vlaanderen 9100",
    "addr:housenumber":"256",
    "addr:postcode":"9100",
    "addr:street":"Koningin Fabiolapark",
    "iso:country":"BE",
    "sg:address":"Koningin Fabiolapark 256",
    "sg:city":"Sint-niklaas",
    "sg:orig_category":"Loodgieterij, verwarming and sanitaire installaties",
    "sg:phone":"+32 3 776 38 50",
    "sg:postcode":"9100",
    "sg:province":"Oost-Vlaanderen",
    "wof:name":"Moorthamer Eddy",
    "wof:placetype":"venue"
},
  "geometry": {"coordinates":[4.1574449539,51.1542663574],"type":"Point"}
}