{
  "type": "Feature",
  "properties": {
    "addr:full":"Chauss\u00c9e De Boondael 436 Bruxelles Bruxelles-Capitale 1050",
    "addr:housenumber":"436",
    "addr:postcode":"1050",
    "addr:street":"Chausse\u0301E De Boondael",
    "iso:country":"BE",
    "sg:address":"Chauss\u00c9e De Boondael 436",
    "sg:city":"Bruxelles",
    "sg:classifiers":[
        {
            "category":"Restaurant",
            "type":"Food & Drink"
        }
    ],
    "sg:phone":"+32 2 647 56 21",
    "sg:postcode":"1050",
    "sg:province":"Bruxelles-Capitale",
    "wof:name":"L'orchidee Blanche",
    "wof:placetype":"venue"
},
  "geometry": {"coordinates":[4.389108181,50.8169784546],"type":"Point"}
}