{
  "type": "Feature",
  "properties": {
    "iso:country":"BE",
    "sg:address":"Oudstrijdersplein",
    "sg:city":"Ninove",
    "sg:classifiers":[
        {
            "category":"Home & Garden",
            "subcategory":"Home Furnishings",
            "type":"Retail Goods"
        }
    ],
    "sg:phone":"+32 54 33 18 17",
    "sg:postcode":"9400",
    "sg:province":"Oost-Vlaanderen",
    "sg:tags":[
        "curtain",
        "-",
        "fixture"
    ],
    "wof:name":"Penne Woningtextiel",
    "wof:placetype":"venue"
},
  "geometry": {"coordinates":[4.0226349831,50.8350982666],"type":"Point"}
}