{
  "type": "Feature",
  "properties": {
    "iso:country":"BE",
    "sg:address":"Fabriekstraat 3",
    "sg:city":"Neerpelt",
    "sg:orig_category":"V\u00e9t\u00e9rinaires",
    "sg:phone":"+32 11 64 21 57",
    "sg:postcode":"3910",
    "sg:province":"Limburg",
    "wof:name":"S. Peeters",
    "wof:placetype":"venue"
},
  "geometry": {"coordinates":[5.4291920662,51.2300338745],"type":"Point"}
}