{
  "type": "Feature",
  "properties": {
    "addr:full":"Mandellaan 324 Roeselare West-Vlaanderen 8800",
    "addr:housenumber":"324",
    "addr:postcode":"8800",
    "addr:street":"Mandellaan",
    "iso:country":"BE",
    "sg:address":"Mandellaan 324",
    "sg:city":"Roeselare",
    "sg:classifiers":[
        {
            "category":"Retail",
            "subcategory":"Veterinary Services",
            "type":"Services"
        }
    ],
    "sg:phone":"+32 51 24 53 00",
    "sg:postcode":"8800",
    "sg:province":"West-Vlaanderen",
    "sg:tags":[
        "veterinarian"
    ],
    "wof:name":"Neirynck W",
    "wof:placetype":"venue"
},
  "geometry": {"coordinates":[3.1425659657,50.9473953247],"type":"Point"}
}