{
  "type": "Feature",
  "properties": {
    "iso:country":"BE",
    "sg:address":"14",
    "sg:city":"Place Cardinal Mercier 1300 Wavre",
    "sg:classifiers":[
        {
            "category":"Shopping",
            "subcategory":"Clothing, Apparel, & Fashions",
            "type":"Retail Goods"
        }
    ],
    "sg:phone":"+32 10 22 61 83",
    "sg:postcode":"14",
    "sg:tags":[
        "textile",
        "clothing",
        "clothes"
    ],
    "wof:name":"Patrick Lefebvre Import Sprl",
    "wof:placetype":"venue"
},
  "geometry": {"coordinates":[4.6102600098,50.7168197632],"type":"Point"}
}