{
  "type": "Feature",
  "properties": {
    "addr:full":"Vreyshorring 58 Lommel Limburg 3920",
    "addr:housenumber":"58",
    "addr:postcode":"3920",
    "addr:street":"Vreyshorring",
    "iso:country":"BE",
    "sg:address":"Vreyshorring 58",
    "sg:city":"Lommel",
    "sg:orig_category":"Banques and organismes de cr\u00e9dit",
    "sg:phone":"+32 11 54 29 29",
    "sg:postcode":"3920",
    "sg:province":"Limburg",
    "wof:name":"Anhyp",
    "wof:placetype":"venue"
},
  "geometry": {"coordinates":[5.3067588806,51.2277374268],"type":"Point"}
}