{
  "type": "Feature",
  "properties": {
    "iso:country":"BE",
    "sg:address":"Alfred Nichelsstraat 4",
    "sg:city":"Aalst",
    "sg:classifiers":[
        {
            "category":"Health Services",
            "subcategory":"Doctor",
            "type":"Services"
        }
    ],
    "sg:phone":"+32 53 70 04 07",
    "sg:postcode":"9300",
    "sg:province":"Oost-Vlaanderen",
    "sg:tags":[
        "medicinephysicians",
        "surgeon"
    ],
    "wof:name":"Debackere Ann",
    "wof:placetype":"venue"
},
  "geometry": {"coordinates":[4.0447101593,50.9348335266],"type":"Point"}
}