{
  "type": "Feature",
  "properties": {
    "iso:country":"BE",
    "sg:address":"Champ Des P\u00c9trales 14",
    "sg:city":"Rixensart",
    "sg:orig_category":"Traitements param\u00e9dicaux",
    "sg:phone":"+32 2 653 89 76",
    "sg:postcode":"1332",
    "sg:province":"Brabant Wallon",
    "wof:name":"Ch. Johansson",
    "wof:placetype":"venue"
},
  "geometry": {"coordinates":[4.4948878288,50.7255439758],"type":"Point"}
}