{
  "type": "Feature",
  "properties": {
    "addr:full":"Brusselsesteenweg 161 Merchtem Vlaams-Brabant 1785",
    "addr:housenumber":"161",
    "addr:postcode":"1785",
    "addr:street":"Brusselsesteenweg",
    "iso:country":"BE",
    "sg:address":"Brusselsesteenweg 161",
    "sg:city":"Merchtem",
    "sg:orig_category":"Jeux and jouets",
    "sg:phone":"+32 52 37 01 34",
    "sg:postcode":"1785",
    "sg:province":"Vlaams-Brabant",
    "wof:name":"Baby Plus Vanderstraeten",
    "wof:placetype":"venue"
},
  "geometry": {"coordinates":[4.2449059486,50.9489974976],"type":"Point"}
}