{
  "type": "Feature",
  "properties": {
    "addr:full":"Rue Les Oies 39 Chaudfontaine Li\u00e8ge 4052",
    "addr:housenumber":"39",
    "addr:postcode":"4052",
    "addr:street":"Rue Les Oies",
    "iso:country":"BE",
    "sg:address":"Rue Les Oies 39",
    "sg:city":"Chaudfontaine",
    "sg:orig_category":"Installation \u00e9lectrique r\u00e9sidentielle",
    "sg:phone":"+32 4 368 78 05",
    "sg:postcode":"4052",
    "sg:province":"Li\u00e8ge",
    "wof:name":"Luc Lacremans",
    "wof:placetype":"venue"
},
  "geometry": {"coordinates":[5.6215009689,50.5649833679],"type":"Point"}
}