{
  "type": "Feature",
  "properties": {
    "iso:country":"BE",
    "sg:address":"Beverenstraat 135",
    "sg:city":"Lichtervelde",
    "sg:classifiers":[
        {
            "category":"Food & Beverages",
            "subcategory":"Meat & Fish",
            "type":"Retail Goods"
        }
    ],
    "sg:phone":"+32 51 72 34 51",
    "sg:postcode":"8810",
    "sg:province":"West-Vlaanderen",
    "sg:tags":[
        "-",
        "livestock"
    ],
    "wof:name":"Vierstraete",
    "wof:placetype":"venue"
},
  "geometry": {"coordinates":[3.15269804,51.0122375488],"type":"Point"}
}