{
  "type": "Feature",
  "properties": {
    "iso:country":"BE",
    "sg:address":"Liersesteenweg 11 Box 1",
    "sg:city":"Berlaar",
    "sg:classifiers":[
        {
            "category":"Health Services",
            "subcategory":"Health Practitioner",
            "type":"Services"
        }
    ],
    "sg:phone":"+32 3 482 33 62",
    "sg:postcode":"2590",
    "sg:province":"Antwerpen",
    "sg:tags":[
        "physiotherapist"
    ],
    "wof:name":"Van De Putte Frank",
    "wof:placetype":"venue"
},
  "geometry": {"coordinates":[4.6493802071,51.1170349121],"type":"Point"}
}