{
  "type": "Feature",
  "properties": {
    "addr:full":"Rue De L'autonomie 22 Anderlecht Bruxelles-Capitale 1070",
    "addr:housenumber":"22",
    "addr:postcode":"1070",
    "addr:street":"Rue De L'Autonomie",
    "iso:country":"BE",
    "sg:address":"Rue De L'autonomie 22",
    "sg:city":"Anderlecht",
    "sg:orig_category":"Editeurs de revues and p\u00e9riodiques. Editeurs de journaux",
    "sg:phone":"+32 2 527 25 75",
    "sg:postcode":"1070",
    "sg:province":"Bruxelles-Capitale",
    "wof:name":"Fapeo",
    "wof:placetype":"venue"
},
  "geometry": {"coordinates":[4.3378691673,50.8400611877],"type":"Point"}
}