{
  "type": "Feature",
  "properties": {
    "addr:full":"Rue Du Couvent 39 Mouscron Hainaut 7700",
    "addr:housenumber":"39",
    "addr:postcode":"7700",
    "addr:street":"Rue Du Couvent",
    "iso:country":"BE",
    "sg:address":"Rue Du Couvent 39",
    "sg:city":"Mouscron",
    "sg:classifiers":[
        {
            "category":"Health Services",
            "subcategory":"Hospital",
            "type":"Services"
        }
    ],
    "sg:phone":"+32 56 85 81 51",
    "sg:postcode":"7700",
    "sg:province":"Hainaut",
    "wof:name":"Centre Hospitalier De Mouscron Asbl",
    "wof:placetype":"venue"
},
  "geometry": {"coordinates":[3.1998310089,50.7423706055],"type":"Point"}
}