{
  "type": "Feature",
  "properties": {
    "addr:full":"Bekegemstraat 2 Jabbeke West-Vlaanderen 8490",
    "addr:housenumber":"2",
    "addr:postcode":"8490",
    "addr:street":"Bekegemstraat",
    "iso:country":"BE",
    "sg:address":"Bekegemstraat 2",
    "sg:city":"Jabbeke",
    "sg:orig_category":"Journaux. Souvenirs and objets artisanaux",
    "sg:phone":"+32 50 81 59 79",
    "sg:postcode":"8490",
    "sg:province":"West-Vlaanderen",
    "wof:name":"Liktuur",
    "wof:placetype":"venue"
},
  "geometry": {"coordinates":[3.0688829422,51.1661491394],"type":"Point"}
}