{
  "type": "Feature",
  "properties": {
    "iso:country":"BE",
    "sg:address":"Sluis 155ba",
    "sg:city":"Mol",
    "sg:orig_category":"Musea and historische gebouwen",
    "sg:phone":"+32 14 31 74 35",
    "sg:postcode":"2400",
    "sg:province":"Antwerpen",
    "wof:name":"Jakob Smitsmuseum",
    "wof:placetype":"venue"
},
  "geometry": {"coordinates":[5.1341900826,51.2111816406],"type":"Point"}
}