{
  "type": "Feature",
  "properties": {
    "iso:country":"BE",
    "sg:address":"Hooiwege 39",
    "sg:city":"Evergem",
    "sg:orig_category":"Artsen and specialisten",
    "sg:phone":"+32 9 357 47 22",
    "sg:postcode":"9940",
    "sg:province":"Oost-Vlaanderen",
    "wof:name":"Renny Billiet",
    "wof:placetype":"venue"
},
  "geometry": {"coordinates":[3.6750519276,51.1415672302],"type":"Point"}
}