{
  "type": "Feature",
  "properties": {
    "iso:country":"BE",
    "sg:address":"Boeckxplein 1",
    "sg:city":"Aarschot (langdorp)",
    "sg:classifiers":[
        {
            "category":"Professional",
            "subcategory":"Testing Lab",
            "type":"Services"
        }
    ],
    "sg:phone":"+32 13 77 26 33",
    "sg:postcode":"3201",
    "sg:province":"Vlaams-Brabant",
    "sg:tags":[
        "chemist"
    ],
    "wof:name":"Van Gramberen R",
    "wof:placetype":"venue"
},
  "geometry": {"coordinates":[4.8698401451,50.9937286377],"type":"Point"}
}