{
  "type": "Feature",
  "properties": {
    "addr:full":"Tervuursesteenweg 639 Zemst Vlaams-Brabant 1982",
    "addr:housenumber":"639",
    "addr:postcode":"1982",
    "addr:street":"Tervuursesteenweg;Vlaams-Brabant",
    "iso:country":"BE",
    "sg:address":"Tervuursesteenweg 639",
    "sg:city":"Zemst",
    "sg:orig_category":"Mat\u00e9riel m\u00e9dical and orthop\u00e9dique and proth\u00e8ses Fab",
    "sg:phone":"+32 15 61 24 14",
    "sg:postcode":"1982",
    "sg:province":"Vlaams-Brabant",
    "wof:name":"Tony Opdebeeck",
    "wof:placetype":"venue"
},
  "geometry": {"coordinates":[4.498041153,50.9582595825],"type":"Point"}
}