{
  "type": "Feature",
  "properties": {
    "iso:country":"BE",
    "sg:address":"Paellepelstraat 33",
    "sg:city":"Ninove",
    "sg:orig_category":"Woningbouw",
    "sg:phone":"+32 54 34 38 85",
    "sg:postcode":"9400",
    "sg:province":"Oost-Vlaanderen",
    "wof:name":"Van Vaerenbergh",
    "wof:placetype":"venue"
},
  "geometry": {"coordinates":[4.0232000351,50.8349113464],"type":"Point"}
}