{
  "type": "Feature",
  "properties": {
    "iso:country":"BE",
    "sg:address":"Elzenweg 3",
    "sg:city":"Rijkevorsel",
    "sg:orig_category":"Ordinateurs and \u00e9quipement informatique",
    "sg:phone":"+32 3 312 07 59",
    "sg:postcode":"2310",
    "sg:province":"Antwerpen",
    "wof:name":"De Vrij Leon - Arthur",
    "wof:placetype":"venue"
},
  "geometry": {"coordinates":[4.7798762321,51.3310241699],"type":"Point"}
}