{
  "type": "Feature",
  "properties": {
    "addr:full":"Kruisstraat 42 Berlare Oost-Vlaanderen 9290",
    "addr:housenumber":"42",
    "addr:postcode":"9290",
    "addr:street":"Kruisstraat",
    "iso:country":"BE",
    "sg:address":"Kruisstraat 42",
    "sg:city":"Berlare",
    "sg:orig_category":"Opticiens",
    "sg:phone":"+32 495 53 83 62",
    "sg:postcode":"9290",
    "sg:province":"Oost-Vlaanderen",
    "wof:name":"Optiek Stroobant J.",
    "wof:placetype":"venue"
},
  "geometry": {"coordinates":[3.9574348927,51.0474014282],"type":"Point"}
}