{
  "type": "Feature",
  "properties": {
    "addr:full":"Korte Scholiersstraat 28 Antwerpen Antwerpen 2060",
    "addr:housenumber":"28",
    "addr:postcode":"2060",
    "addr:street":"Korte Scholiersstraat",
    "iso:country":"BE",
    "sg:address":"Korte Scholiersstraat 28",
    "sg:city":"Antwerpen",
    "sg:classifiers":[
        {
            "category":"Arts & Performance",
            "subcategory":"Theater",
            "type":"Entertainment"
        }
    ],
    "sg:phone":"+32 3 213 11 92",
    "sg:postcode":"2060",
    "sg:province":"Antwerpen",
    "sg:tags":[
        "concert-halls",
        "theatre"
    ],
    "wof:name":"Poppentheater Pili-pili",
    "wof:placetype":"venue"
},
  "geometry": {"coordinates":[4.4272828102,51.2240715027],"type":"Point"}
}