{
  "type": "Feature",
  "properties": {
    "addr:full":"Vieux Tauves 107bd Andenne Namur 5300",
    "addr:postcode":"5300",
    "addr:street":"Namur",
    "iso:country":"BE",
    "sg:address":"Vieux Tauves 107bd",
    "sg:city":"Andenne",
    "sg:classifiers":[
        {
            "category":"Arena",
            "subcategory":"Sports Club",
            "type":"Entertainment"
        }
    ],
    "sg:phone":"+32 81 61 20 87",
    "sg:postcode":"5300",
    "sg:province":"Namur",
    "sg:tags":[
        "terrain",
        "hors",
        "de",
        "installation",
        "sportifs"
    ],
    "wof:name":"F.c. Saint-lambert",
    "wof:placetype":"venue"
},
  "geometry": {"coordinates":[5.1213750839,50.4588546753],"type":"Point"}
}