{
  "type": "Feature",
  "properties": {
    "iso:country":"BE",
    "sg:address":"Brandstraat 1a",
    "sg:city":"Puurs",
    "sg:orig_category":"Diverse organisaties and verenigingen",
    "sg:phone":"+32 3 899 15 06",
    "sg:postcode":"2870",
    "sg:province":"Antwerpen",
    "wof:name":"Vksj Puurs",
    "wof:placetype":"venue"
},
  "geometry": {"coordinates":[4.2753400803,51.0686416626],"type":"Point"}
}