{
  "type": "Feature",
  "properties": {
    "addr:full":"Rijksweg 80 Zulte (machelen) Oost-Vlaanderen 9870",
    "addr:housenumber":"80",
    "addr:postcode":"9870",
    "addr:street":"Rijksweg",
    "iso:country":"BE",
    "sg:address":"Rijksweg 80",
    "sg:city":"Zulte (machelen)",
    "sg:orig_category":"Non-Classified Establishments",
    "sg:phone":"+32 9 380 07 47",
    "sg:postcode":"9870",
    "sg:province":"Oost-Vlaanderen",
    "wof:name":"Best Performance Bvba",
    "wof:placetype":"venue"
},
  "geometry": {"coordinates":[3.4954109192,50.956451416],"type":"Point"}
}