{
  "type": "Feature",
  "properties": {
    "addr:full":"Centre 52 Thimister-clermont Li\u00e8ge 4890",
    "addr:housenumber":"52",
    "addr:postcode":"4890",
    "iso:country":"BE",
    "sg:address":"Centre 52",
    "sg:city":"Thimister-clermont",
    "sg:orig_category":"Installation \u00e9lectrique r\u00e9sidentielle",
    "sg:phone":"+32 87 44 70 05",
    "sg:postcode":"4890",
    "sg:province":"Li\u00e8ge",
    "wof:name":"Eric Baumans",
    "wof:placetype":"venue"
},
  "geometry": {"coordinates":[5.864730835,50.6531257629],"type":"Point"}
}