{
  "type": "Feature",
  "properties": {
    "addr:full":"Burgemeester Bollenstraat 64 Hasselt Limburg 3500",
    "addr:housenumber":"64",
    "addr:postcode":"3500",
    "addr:street":"Burgemeester Bollenstraat",
    "iso:country":"BE",
    "sg:address":"Burgemeester Bollenstraat 64",
    "sg:city":"Hasselt",
    "sg:classifiers":[
        {
            "category":"Shopping",
            "subcategory":"Crafts & Fabrics",
            "type":"Retail Goods"
        }
    ],
    "sg:phone":"+32 11 22 66 67",
    "sg:postcode":"3500",
    "sg:province":"Limburg",
    "sg:tags":[
        "hi-fi",
        "equipment",
        "stereophonic",
        "-"
    ],
    "wof:name":"Bose Lifestyle Center",
    "wof:placetype":"venue"
},
  "geometry": {"coordinates":[5.3330788612,50.932598114],"type":"Point"}
}