{
  "type": "Feature",
  "properties": {
    "addr:full":"Kievitstraat 3 Beernem West-Vlaanderen 8730",
    "addr:housenumber":"3",
    "addr:postcode":"8730",
    "addr:street":"Kievitstraat",
    "iso:country":"BE",
    "sg:address":"Kievitstraat 3",
    "sg:city":"Beernem",
    "sg:classifiers":[
        {
            "category":"Home & Garden",
            "subcategory":"Kitchen Supply",
            "type":"Retail Goods"
        }
    ],
    "sg:phone":"+32 50 79 04 07",
    "sg:postcode":"8730",
    "sg:province":"West-Vlaanderen",
    "sg:tags":[
        "installation"
    ],
    "wof:name":"Mulier F",
    "wof:placetype":"venue"
},
  "geometry": {"coordinates":[3.3238239288,51.1257972717],"type":"Point"}
}