{
  "type": "Feature",
  "properties": {
    "iso:country":"BE",
    "sg:address":"Dennenstraat 20",
    "sg:city":"Meeuwen-gruitrode",
    "sg:orig_category":"Installatie van houten of kunststof schrijnwerk",
    "sg:phone":"+32 89 46 25 85",
    "sg:postcode":"3670",
    "sg:province":"Limburg",
    "wof:name":"Johan Thaens",
    "wof:placetype":"venue"
},
  "geometry": {"coordinates":[5.5543408394,51.106212616],"type":"Point"}
}