{
  "type": "Feature",
  "properties": {
    "addr:full":"Steinroth 20 Eupen Li\u00e8ge 4700",
    "addr:housenumber":"20",
    "addr:postcode":"4700",
    "addr:street":"Steinroth",
    "iso:country":"BE",
    "sg:address":"Steinroth 20",
    "sg:city":"Eupen",
    "sg:classifiers":[
        {
            "category":"Arena",
            "subcategory":"Sports Club",
            "type":"Entertainment"
        }
    ],
    "sg:phone":"+32 87 74 29 02",
    "sg:postcode":"4700",
    "sg:province":"Li\u00e8ge",
    "sg:tags":[
        "de"
    ],
    "wof:name":"Yacht De La Vesdre",
    "wof:placetype":"venue"
},
  "geometry": {"coordinates":[6.0244598389,50.6260948181],"type":"Point"}
}