{
  "type": "Feature",
  "properties": {
    "addr:full":"Het Laar 3ba Lille Antwerpen 2275",
    "addr:housenumber":"3ba",
    "addr:postcode":"2275",
    "addr:street":"Het Laar",
    "iso:country":"BE",
    "sg:address":"Het Laar 3ba",
    "sg:city":"Lille",
    "sg:orig_category":"Eleveurs de bovins",
    "sg:phone":"+32 14 55 14 68",
    "sg:postcode":"2275",
    "sg:province":"Antwerpen",
    "wof:name":"Ludo Daneels",
    "wof:placetype":"venue"
},
  "geometry": {"coordinates":[4.8638939857,51.2849121094],"type":"Point"}
}