{
  "type": "Feature",
  "properties": {
    "iso:country":"BE",
    "sg:address":"Grand Rue 25/108",
    "sg:city":"Ottignies-louvain-la-neuve",
    "sg:orig_category":"Agences d'exp\u00e9dition",
    "sg:phone":"+32 10 45 20 91",
    "sg:postcode":"1348",
    "sg:province":"Brabant Wallon",
    "wof:name":"Idalco",
    "wof:placetype":"venue"
},
  "geometry": {"coordinates":[4.614274025,50.6692466736],"type":"Point"}
}