{
  "type": "Feature",
  "properties": {
    "iso:country":"BE",
    "sg:address":"Rue Neuve 28",
    "sg:city":"Huy",
    "sg:classifiers":[
        {
            "category":"Cafe",
            "type":"Food & Drink"
        }
    ],
    "sg:phone":"+32 85 25 44 56",
    "sg:postcode":"4500",
    "sg:province":"Li\u00e8ge",
    "sg:tags":[
        "snack-bars"
    ],
    "wof:name":"Casse-croute Sprl",
    "wof:placetype":"venue"
},
  "geometry": {"coordinates":[5.2355761528,50.5210227966],"type":"Point"}
}