{
  "type": "Feature",
  "properties": {
    "iso:country":"BE",
    "sg:address":"Rue Cardinal Mercier 32",
    "sg:city":"Beyne-heusay",
    "sg:classifiers":[
        {
            "category":"Health Services",
            "subcategory":"Hospital",
            "type":"Services"
        }
    ],
    "sg:phone":"+32 4 358 88 84",
    "sg:postcode":"4610",
    "sg:province":"Li\u00e8ge",
    "wof:name":"Centre D'accueil",
    "wof:placetype":"venue"
},
  "geometry": {"coordinates":[5.6600527763,50.6187744141],"type":"Point"}
}