{
  "type": "Feature",
  "properties": {
    "addr:full":"Ambacht. Zone Balendijk 5007 Lommel Limburg 3920",
    "addr:postcode":"5007 lommel;3920",
    "addr:street":"Balendijk",
    "iso:country":"BE",
    "sg:address":"Ambacht. Zone Balendijk 5007",
    "sg:city":"Lommel",
    "sg:orig_category":"Fabrication and montage de mobilier",
    "sg:phone":"+32 11 55 91 55",
    "sg:postcode":"3920",
    "sg:province":"Limburg",
    "wof:name":"Franssen",
    "wof:placetype":"venue"
},
  "geometry": {"coordinates":[5.2664217949,51.2146186829],"type":"Point"}
}