{
  "type": "Feature",
  "properties": {
    "iso:country":"BE",
    "sg:address":"Beau Site 4",
    "sg:city":"Silly",
    "sg:orig_category":"Diensten voor huisdieren",
    "sg:phone":"+32 2 395 52 10",
    "sg:postcode":"7830",
    "sg:province":"Hainaut",
    "wof:name":"Francoise Vanyperzeele",
    "wof:placetype":"venue"
},
  "geometry": {"coordinates":[4.0398101807,50.6654090881],"type":"Point"}
}