{
  "type": "Feature",
  "properties": {
    "iso:country":"BE",
    "sg:address":"Dr\u00e8ve Des H\u00eatres 8",
    "sg:city":"Genappe (bousval)",
    "sg:classifiers":[
        {
            "category":"Building & Trades",
            "subcategory":"Landscaping Services",
            "type":"Services"
        }
    ],
    "sg:phone":"+32 10 61 60 10",
    "sg:postcode":"1470",
    "sg:province":"Brabant Wallon",
    "sg:tags":[
        "gardening",
        "garden",
        "maintenance"
    ],
    "wof:name":"Jardin Passion",
    "wof:placetype":"venue"
},
  "geometry": {"coordinates":[4.5326681137,50.6410064697],"type":"Point"}
}