{
  "type": "Feature",
  "properties": {
    "iso:country":"BE",
    "sg:address":"Route Des Canons 3",
    "sg:city":"Namur",
    "sg:classifiers":[
        {
            "category":"Insurance",
            "subcategory":"Life Insurance",
            "type":"Services"
        }
    ],
    "sg:phone":"+32 81 74 68 46",
    "sg:postcode":"5000",
    "sg:province":"Namur",
    "sg:tags":[
        "assurance"
    ],
    "wof:name":"Aedes",
    "wof:placetype":"venue"
},
  "geometry": {"coordinates":[4.8755168915,50.4660987854],"type":"Point"}
}