{
  "type": "Feature",
  "properties": {
    "iso:country":"BE",
    "sg:address":"Rue De Landen 88",
    "sg:city":"Hannut",
    "sg:orig_category":"Meubelzaken, woning- and keukeninrichting Textiel Verlichting and huishoudartikelen",
    "sg:phone":"+32 19 51 64 76",
    "sg:postcode":"4280",
    "sg:province":"Li\u00e8ge",
    "wof:name":"Casa",
    "wof:placetype":"venue"
},
  "geometry": {"coordinates":[5.0823469162,50.6825180054],"type":"Point"}
}