{
  "type": "Feature",
  "properties": {
    "iso:country":"BE",
    "sg:address":"Rue De L'argentine 52",
    "sg:city":"Terhulpen",
    "sg:orig_category":"Informaticaconsulenten",
    "sg:phone":"+32 2 653 09 96",
    "sg:postcode":"1310",
    "sg:province":"Brabant Wallon",
    "wof:name":"I.i.c.c.",
    "wof:placetype":"venue"
},
  "geometry": {"coordinates":[4.488530159,50.7320671082],"type":"Point"}
}