{
  "type": "Feature",
  "properties": {
    "iso:country":"BE",
    "sg:address":"Mariakerksesteenweg 129",
    "sg:city":"Gent",
    "sg:orig_category":"Diverse opleidingen and onderwijs",
    "sg:phone":"+32 9 226 14 34",
    "sg:postcode":"9031",
    "sg:province":"Oost-Vlaanderen",
    "wof:name":"Dhooge Prolingua",
    "wof:placetype":"venue"
},
  "geometry": {"coordinates":[3.6603660583,51.0559463501],"type":"Point"}
}