{
  "type": "Feature",
  "properties": {
    "iso:country":"BE",
    "sg:address":"Oosteeklo-dorp 51",
    "sg:city":"Assenede (oosteeklo)",
    "sg:classifiers":[
        {
            "category":"Personal",
            "subcategory":"Beauty Salon",
            "type":"Services"
        }
    ],
    "sg:phone":"+32 9 373 66 97",
    "sg:postcode":"9968",
    "sg:province":"Oost-Vlaanderen",
    "sg:tags":[
        "lady",
        "-",
        "hairdressing"
    ],
    "wof:name":"Firmin",
    "wof:placetype":"venue"
},
  "geometry": {"coordinates":[3.6871929169,51.1907310486],"type":"Point"}
}