{
  "type": "Feature",
  "properties": {
    "iso:country":"BE",
    "sg:address":"Muizensteenweg 6",
    "sg:city":"Bonheiden",
    "sg:classifiers":[
        {
            "category":"Insurance",
            "subcategory":"Life Insurance",
            "type":"Services"
        }
    ],
    "sg:phone":"+32 15 51 79 72",
    "sg:postcode":"2820",
    "sg:province":"Antwerpen",
    "sg:tags":[
        "assurance"
    ],
    "wof:name":"Goris & Zoon",
    "wof:placetype":"venue"
},
  "geometry": {"coordinates":[4.5425629616,51.0234565735],"type":"Point"}
}