{
  "type": "Feature",
  "properties": {
    "addr:full":"Rue De Pessoux 18a Ciney (serinchamps) Namur 5590",
    "addr:housenumber":"18a",
    "addr:postcode":"5590",
    "addr:street":"Rue De Pessoux",
    "iso:country":"BE",
    "sg:address":"Rue De Pessoux 18a",
    "sg:city":"Ciney (serinchamps)",
    "sg:classifiers":[
        {
            "category":"Personal",
            "subcategory":"Nail Salon",
            "type":"Services"
        }
    ],
    "sg:phone":"+32 83 68 89 44",
    "sg:postcode":"5590",
    "sg:province":"Namur",
    "sg:tags":[
        "pedicure"
    ],
    "wof:name":"Misson F",
    "wof:placetype":"venue"
},
  "geometry": {"coordinates":[5.1118860245,50.2920417786],"type":"Point"}
}