{
  "type": "Feature",
  "properties": {
    "addr:full":"Oedelemsteenweg 22 Beernem (sint-joris) West-Vlaanderen 8730",
    "addr:housenumber":"22",
    "addr:postcode":"8730",
    "addr:street":"Oedelemsteenweg",
    "iso:country":"BE",
    "sg:address":"Oedelemsteenweg 22",
    "sg:city":"Beernem (sint-joris)",
    "sg:classifiers":[
        {
            "category":"Farming",
            "subcategory":"Livestock Farm",
            "type":"Manufacturing & Wholesale Goods"
        }
    ],
    "sg:phone":"+32 50 78 87 50",
    "sg:postcode":"8730",
    "sg:province":"West-Vlaanderen",
    "sg:tags":[
        "buyer"
    ],
    "wof:name":"Claeys E",
    "wof:placetype":"venue"
},
  "geometry": {"coordinates":[3.3730039597,51.1326675415],"type":"Point"}
}