{
  "type": "Feature",
  "properties": {
    "iso:country":"BE",
    "sg:address":"Schalbroekstraat 175",
    "sg:city":"Lummen",
    "sg:orig_category":"Entretien and r\u00e9parations de voitures",
    "sg:phone":"+32 13 44 23 54",
    "sg:postcode":"3560",
    "sg:province":"Limburg",
    "wof:name":"Garage Schepers",
    "wof:placetype":"venue"
},
  "geometry": {"coordinates":[5.1610198021,50.9720115662],"type":"Point"}
}