{
  "type": "Feature",
  "properties": {
    "iso:country":"BE",
    "sg:address":"Zevenekendorp 101",
    "sg:city":"Lochristi",
    "sg:orig_category":"Zuivelproducten",
    "sg:phone":"+32 9 355 56 37",
    "sg:postcode":"9080",
    "sg:province":"Oost-Vlaanderen",
    "wof:name":"A. Verlee",
    "wof:placetype":"venue"
},
  "geometry": {"coordinates":[3.8947548866,51.1073570251],"type":"Point"}
}