{
  "type": "Feature",
  "properties": {
    "addr:full":"Rue De La Marcelle 102 Couvin Namur 5660",
    "addr:housenumber":"102",
    "addr:postcode":"5660",
    "addr:street":"Rue De La Marcelle",
    "iso:country":"BE",
    "sg:address":"Rue De La Marcelle 102",
    "sg:city":"Couvin",
    "sg:classifiers":[
        {
            "category":"Home & Garden",
            "subcategory":"Household Appliances",
            "type":"Retail Goods"
        }
    ],
    "sg:phone":"+32 60 34 41 07",
    "sg:postcode":"5660",
    "sg:province":"Namur",
    "sg:tags":[
        "repair",
        "mainten",
        "-",
        "electric"
    ],
    "wof:name":"Philippe Gh Ets",
    "wof:placetype":"venue"
},
  "geometry": {"coordinates":[4.496969223,50.048915863],"type":"Point"}
}