{
  "type": "Feature",
  "properties": {
    "iso:country":"BE",
    "sg:address":"Rue Libotte 8",
    "sg:city":"Li\u00c8ge",
    "sg:orig_category":"Biens d'occasion",
    "sg:phone":"+32 4 343 09 99",
    "sg:postcode":"4020",
    "sg:province":"Li\u00e8ge",
    "wof:name":"Le Bazar Li\u00c9geois",
    "wof:placetype":"venue"
},
  "geometry": {"coordinates":[5.5797748566,50.6356735229],"type":"Point"}
}