{
  "type": "Feature",
  "properties": {
    "iso:country":"BE",
    "sg:address":"Groenstraat 1a",
    "sg:city":"Rotselaar",
    "sg:orig_category":"V\u00eatements",
    "sg:phone":"+32 16 44 96 11",
    "sg:postcode":"3110",
    "sg:province":"Vlaams-Brabant",
    "wof:name":"Mega Jeans",
    "wof:placetype":"venue"
},
  "geometry": {"coordinates":[4.709446907,50.9520492554],"type":"Point"}
}