{
  "type": "Feature",
  "properties": {
    "addr:full":"Rue Du Grand Hy 26 Rochefort Namur 5580",
    "addr:housenumber":"26",
    "addr:postcode":"5580",
    "addr:street":"Rue Du Grand Hy",
    "iso:country":"BE",
    "sg:address":"Rue Du Grand Hy 26",
    "sg:city":"Rochefort",
    "sg:orig_category":"Vakantiehuizen",
    "sg:phone":"+32 84 37 77 73",
    "sg:postcode":"5580",
    "sg:province":"Namur",
    "wof:name":"Van Huyneghem-herman",
    "wof:placetype":"venue"
},
  "geometry": {"coordinates":[5.1876559258,50.1230354309],"type":"Point"}
}