{
  "type": "Feature",
  "properties": {
    "addr:full":"Rue Du Bosquet 27 Beloeil Hainaut 7970",
    "addr:housenumber":"27",
    "addr:postcode":"7970",
    "addr:street":"Rue Du Bosquet",
    "iso:country":"BE",
    "sg:address":"Rue Du Bosquet 27",
    "sg:city":"Beloeil",
    "sg:classifiers":[
        {
            "category":"Bars & Pubs",
            "type":"Food & Drink"
        }
    ],
    "sg:phone":"+32 69 68 74 24",
    "sg:postcode":"7970",
    "sg:province":"Hainaut",
    "wof:name":"Ranch (le)",
    "wof:placetype":"venue"
},
  "geometry": {"coordinates":[3.7373199463,50.5434799194],"type":"Point"}
}