{
  "type": "Feature",
  "properties": {
    "addr:full":"Vichtsesteenweg 108 Anzegem West-Vlaanderen 8570",
    "addr:housenumber":"108",
    "addr:postcode":"8570",
    "addr:street":"Vichtsesteenweg",
    "iso:country":"BE",
    "sg:address":"Vichtsesteenweg 108",
    "sg:city":"Anzegem",
    "sg:orig_category":"Caf\u00e9s Ruimtes voor conferenties, recepties and feesten",
    "sg:phone":"+32 56 68 93 93",
    "sg:postcode":"8570",
    "sg:province":"West-Vlaanderen",
    "wof:name":"Rily",
    "wof:placetype":"venue"
},
  "geometry": {"coordinates":[3.4460918903,50.8486976624],"type":"Point"}
}