{
  "type": "Feature",
  "properties": {
    "iso:country":"BE",
    "sg:address":"Wespelaarsestw 19",
    "sg:city":"Haacht",
    "sg:classifiers":[
        {
            "category":"Personal",
            "subcategory":"Beauty Salon",
            "type":"Services"
        }
    ],
    "sg:phone":"+32 16 60 89 40",
    "sg:postcode":"3150",
    "sg:province":"Vlaams-Brabant",
    "sg:tags":[
        "de",
        "coiffure"
    ],
    "wof:name":"Hairstyling Ingrid",
    "wof:placetype":"venue"
},
  "geometry": {"coordinates":[4.6383709908,50.974319458],"type":"Point"}
}