{
  "type": "Feature",
  "properties": {
    "addr:full":"Diestersteenweg 95 Leopoldsburg Limburg 3970",
    "addr:housenumber":"95",
    "addr:postcode":"3970",
    "addr:street":"Diestersteenweg",
    "iso:country":"BE",
    "sg:address":"Diestersteenweg 95",
    "sg:city":"Leopoldsburg",
    "sg:classifiers":[
        {
            "category":"Arts & Performance",
            "subcategory":"Music",
            "type":"Entertainment"
        }
    ],
    "sg:phone":"+32 11 34 48 45",
    "sg:postcode":"3970",
    "sg:province":"Limburg",
    "sg:tags":[
        "disc-jockeys"
    ],
    "wof:name":"Disco Jo-jo",
    "wof:placetype":"venue"
},
  "geometry": {"coordinates":[5.2473011017,51.1140861511],"type":"Point"}
}