{
  "type": "Feature",
  "properties": {
    "addr:full":"Veldenbergstraat 77 Merksplas Antwerpen 2330",
    "addr:housenumber":"77",
    "addr:postcode":"2330",
    "addr:street":"Veldenbergstraat",
    "iso:country":"BE",
    "sg:address":"Veldenbergstraat 77",
    "sg:city":"Merksplas",
    "sg:classifiers":[
        {
            "category":"Retail",
            "subcategory":"Auto Rental",
            "type":"Services"
        }
    ],
    "sg:phone":"+32 14 63 25 56",
    "sg:postcode":"2330",
    "sg:province":"Antwerpen",
    "sg:tags":[
        "milking",
        "machine"
    ],
    "wof:name":"Doms Packo Nv",
    "wof:placetype":"venue"
},
  "geometry": {"coordinates":[4.8415350914,51.3667984009],"type":"Point"}
}