{
  "type": "Feature",
  "properties": {
    "addr:full":"Meisestraat 127 Grimbergen (strombeek-bever) Vlaams-Brabant 1853",
    "addr:housenumber":"127",
    "addr:postcode":"1853",
    "addr:street":"Meisestraat",
    "iso:country":"BE",
    "sg:address":"Meisestraat 127",
    "sg:city":"Grimbergen (strombeek-bever)",
    "sg:orig_category":"Newspapers, magazines, periodicals - Distribution",
    "sg:phone":"+32 2 267 62 37",
    "sg:postcode":"1853",
    "sg:province":"Vlaams-Brabant",
    "wof:name":"Kapelleke ('t)",
    "wof:placetype":"venue"
},
  "geometry": {"coordinates":[4.3493518829,50.9117050171],"type":"Point"}
}