{
  "type": "Feature",
  "properties": {
    "iso:country":"BE",
    "sg:address":"Chauss\u00e9e De Namur 82",
    "sg:city":"Hamois (natoye)",
    "sg:classifiers":[
        {
            "category":"Retail",
            "subcategory":"Auto Repair",
            "type":"Services"
        }
    ],
    "sg:phone":"+32 83 65 51 77",
    "sg:postcode":"5360",
    "sg:province":"Namur",
    "sg:tags":[
        "garage"
    ],
    "wof:name":"Ista",
    "wof:placetype":"venue"
},
  "geometry": {"coordinates":[5.0432748795,50.3584899902],"type":"Point"}
}