{
  "type": "Feature",
  "properties": {
    "addr:full":"Steenberg 72 Ninove (pollare) Oost-Vlaanderen 9401",
    "addr:housenumber":"72",
    "addr:postcode":"9401",
    "addr:street":"Steenberg",
    "iso:country":"BE",
    "sg:address":"Steenberg 72",
    "sg:city":"Ninove (pollare)",
    "sg:classifiers":[
        {
            "category":"Building & Trades",
            "subcategory":"Plumbing",
            "type":"Services"
        }
    ],
    "sg:phone":"+32 54 32 77 75",
    "sg:postcode":"9401",
    "sg:province":"Oost-Vlaanderen",
    "sg:tags":[
        "contractor"
    ],
    "wof:name":"Arijs-de Bisschop",
    "wof:placetype":"venue"
},
  "geometry": {"coordinates":[4.0003948212,50.8114814758],"type":"Point"}
}