{
  "type": "Feature",
  "properties": {
    "iso:country":"BE",
    "sg:address":"Chemin Napol\u00e9on 22",
    "sg:city":"Ham-sur-heure-nalinnes (nalinnes)",
    "sg:classifiers":[
        {
            "category":"Health Services",
            "subcategory":"Health Practitioner",
            "type":"Services"
        }
    ],
    "sg:phone":"+32 71 21 38 49",
    "sg:postcode":"6120",
    "sg:province":"Hainaut",
    "sg:tags":[
        "physiotherapist"
    ],
    "wof:name":"D'amico C",
    "wof:placetype":"venue"
},
  "geometry": {"coordinates":[4.4541449547,50.346736908],"type":"Point"}
}