{
  "type": "Feature",
  "properties": {
    "addr:full":"Mechelsestraat 13-24 Leuven Vlaams-Brabant 3000",
    "addr:postcode":"13-24;3000",
    "addr:street":"Mechelsestraat",
    "iso:country":"BE",
    "sg:address":"Mechelsestraat 13-24",
    "sg:city":"Leuven",
    "sg:classifiers":[
        {
            "category":"Sports & Exercise",
            "subcategory":"Gym",
            "type":"Entertainment"
        }
    ],
    "sg:phone":"+32 16 22 37 54",
    "sg:postcode":"3000",
    "sg:province":"Vlaams-Brabant",
    "sg:tags":[
        "access",
        "gymnastics",
        "-",
        "apparatus",
        "fitness"
    ],
    "wof:name":"Mertens Sport",
    "wof:placetype":"venue"
},
  "geometry": {"coordinates":[4.7000007629,50.8804931641],"type":"Point"}
}