{
  "type": "Feature",
  "properties": {
    "iso:country":"BE",
    "sg:address":"'t Walletje 45",
    "sg:city":"Knokke-heist (westkapelle)",
    "sg:classifiers":[
        {
            "category":"Wholesale",
            "subcategory":"Home Furnishings",
            "type":"Manufacturing & Wholesale Goods"
        }
    ],
    "sg:phone":"+32 50 60 06 36",
    "sg:postcode":"8300",
    "sg:province":"West-Vlaanderen",
    "sg:tags":[
        "storage",
        "-",
        "furniture"
    ],
    "wof:name":"Devos-moreeuw",
    "wof:placetype":"venue"
},
  "geometry": {"coordinates":[3.2878100872,51.3212623596],"type":"Point"}
}