{
  "type": "Feature",
  "properties": {
    "addr:full":"Avenue Du Grand Bois 16 Waterloo Brabant Wallon 1410",
    "addr:housenumber":"16",
    "addr:postcode":"1410",
    "addr:street":"Avenue Du Grand Bois",
    "iso:country":"BE",
    "sg:address":"Avenue Du Grand Bois 16",
    "sg:city":"Waterloo",
    "sg:classifiers":[
        {
            "category":"Professional",
            "subcategory":"Art Services",
            "type":"Services"
        }
    ],
    "sg:phone":"+32 2 354 80 04",
    "sg:postcode":"1410",
    "sg:province":"Brabant Wallon",
    "sg:tags":[
        "photography",
        "reporting",
        "-"
    ],
    "wof:name":"Gillieaux B",
    "wof:placetype":"venue"
},
  "geometry": {"coordinates":[4.3855571747,50.7109107971],"type":"Point"}
}