{
  "type": "Feature",
  "properties": {
    "iso:country":"BE",
    "sg:address":"De Klei 42",
    "sg:city":"Ternat (wambeek)",
    "sg:classifiers":[
        {
            "category":"Wholesale",
            "subcategory":"Chemicals & Plastics",
            "type":"Manufacturing & Wholesale Goods"
        }
    ],
    "sg:phone":"+32 53 66 91 46",
    "sg:postcode":"1741",
    "sg:province":"Vlaams-Brabant",
    "sg:tags":[
        "packing"
    ],
    "wof:name":"Comimex",
    "wof:placetype":"venue"
},
  "geometry": {"coordinates":[4.1282868385,50.8563957214],"type":"Point"}
}