{
  "type": "Feature",
  "properties": {
    "iso:country":"BE",
    "sg:address":"Stationsdreef 213",
    "sg:city":"Roeselare",
    "sg:classifiers":[
        {
            "category":"Sports & Exercise",
            "subcategory":"Ski Slope",
            "type":"Entertainment"
        }
    ],
    "sg:phone":"+32 51 24 55 63",
    "sg:postcode":"8800",
    "sg:province":"West-Vlaanderen",
    "sg:tags":[
        "school",
        "-",
        "rink"
    ],
    "wof:name":"Mont-blanc",
    "wof:placetype":"venue"
},
  "geometry": {"coordinates":[3.1269180775,50.9554977417],"type":"Point"}
}