{
  "type": "Feature",
  "properties": {
    "iso:country":"BE",
    "sg:address":"Rue De France 21",
    "sg:city":"Ath",
    "sg:orig_category":"Antiek Meubelzaken, woning- and keukeninrichting",
    "sg:phone":"+32 68 28 45 14",
    "sg:postcode":"7800",
    "sg:province":"Hainaut",
    "wof:name":"Antiquit\u00c9s Lixon",
    "wof:placetype":"venue"
},
  "geometry": {"coordinates":[3.7750520706,50.6320114136],"type":"Point"}
}