{
  "type": "Feature",
  "properties": {
    "addr:full":"Haven 407 Polderdijkweg 16 Antwerpen Antwerpen 2030",
    "addr:housenumber":"407;16",
    "addr:postcode":"2030",
    "addr:street":"Haven",
    "iso:country":"BE",
    "sg:address":"Haven 407 Polderdijkweg 16",
    "sg:city":"Antwerpen",
    "sg:classifiers":[
        {
            "category":"Utilities",
            "subcategory":"Water",
            "type":"Services"
        }
    ],
    "sg:phone":"+32 3 545 84 11",
    "sg:postcode":"2030",
    "sg:province":"Antwerpen",
    "sg:tags":[
        "drinking",
        "analysis"
    ],
    "wof:name":"Sgs Depauw & Stokoe Nv",
    "wof:placetype":"venue"
},
  "geometry": {"coordinates":[4.343462944,51.2634544373],"type":"Point"}
}