{
  "type": "Feature",
  "properties": {
    "iso:country":"BE",
    "sg:address":"Avenue De Tervueren 216",
    "sg:city":"Sint-pieters-woluwe/woluwe-saint-pierre",
    "sg:orig_category":"Agences de publicit\u00e9",
    "sg:phone":"+32 2 772 10 10",
    "sg:postcode":"1150",
    "sg:province":"Bruxelles-Capitale",
    "wof:name":"Crayon",
    "wof:placetype":"venue"
},
  "geometry": {"coordinates":[4.4500608444,50.8188858032],"type":"Point"}
}