{
  "type": "Feature",
  "properties": {
    "addr:full":"Rue Saint-jean 20 Jodoigne Brabant Wallon 1370",
    "addr:postcode":"20;1370",
    "addr:street":"Rue Saint-Jean",
    "iso:country":"BE",
    "sg:address":"Rue Saint-jean 20",
    "sg:city":"Jodoigne",
    "sg:classifiers":[
        {
            "category":"Recreation",
            "subcategory":"Gun Range",
            "type":"Entertainment"
        }
    ],
    "sg:phone":"+32 10 81 18 82",
    "sg:postcode":"1370",
    "sg:province":"Brabant Wallon",
    "sg:tags":[
        "ammunition",
        "-",
        "retail"
    ],
    "wof:name":"Apache",
    "wof:placetype":"venue"
},
  "geometry": {"coordinates":[4.8707370758,50.724822998],"type":"Point"}
}