{
  "type": "Feature",
  "properties": {
    "iso:country":"BE",
    "sg:address":"Rue Edouard Dereume 64",
    "sg:city":"Rixensart",
    "sg:orig_category":"Sportclubs",
    "sg:phone":"+32 2 653 47 39",
    "sg:postcode":"1330",
    "sg:province":"Brabant Wallon",
    "wof:name":"A.c. Rixensart-wavre",
    "wof:placetype":"venue"
},
  "geometry": {"coordinates":[4.5190119743,50.7181625366],"type":"Point"}
}