{
  "type": "Feature",
  "properties": {
    "iso:country":"BE",
    "sg:address":"Rue L\u00e9on Et Alfred Defuisseaux 26",
    "sg:city":"Herstal",
    "sg:classifiers":[
        {
            "category":"Arts & Performance",
            "subcategory":"Music",
            "type":"Entertainment"
        }
    ],
    "sg:phone":"+32 498 45 12 32",
    "sg:postcode":"4040",
    "sg:province":"Li\u00e8ge",
    "sg:tags":[
        "disc-jockeys"
    ],
    "wof:name":"Virtual Dream",
    "wof:placetype":"venue"
},
  "geometry": {"coordinates":[5.6417498589,50.6829109192],"type":"Point"}
}