{
  "type": "Feature",
  "properties": {
    "addr:full":"Rue De Waugen\u00e9e 25 Ecaussinnes (ecaussinnes-d'enghien) Hainaut 7190",
    "addr:housenumber":"25",
    "addr:postcode":"7190",
    "addr:street":"Rue De Waugene\u0301E;Ecaussinnes-D'Enghien Hainaut",
    "iso:country":"BE",
    "sg:address":"Rue De Waugen\u00e9e 25",
    "sg:city":"Ecaussinnes (ecaussinnes-d'enghien)",
    "sg:classifiers":[
        {
            "category":"Insurance",
            "subcategory":"Insurance Agent",
            "type":"Services"
        }
    ],
    "sg:phone":"+32 67 49 16 76",
    "sg:postcode":"7190",
    "sg:province":"Hainaut",
    "sg:tags":[
        "broker"
    ],
    "wof:name":"Szabo Y",
    "wof:placetype":"venue"
},
  "geometry": {"coordinates":[4.1581530571,50.5736045837],"type":"Point"}
}