{
  "type": "Feature",
  "properties": {
    "addr:full":"Markgravelei 85 Antwerpen Antwerpen 2018",
    "addr:housenumber":"85",
    "addr:postcode":"2018",
    "addr:street":"Markgravelei",
    "iso:country":"BE",
    "sg:address":"Markgravelei 85",
    "sg:city":"Antwerpen",
    "sg:orig_category":"Ordinateurs and \u00e9quipement informatique",
    "sg:phone":"+32 3 248 39 18",
    "sg:postcode":"2018",
    "sg:province":"Antwerpen",
    "wof:name":"Jan Joos Consulting",
    "wof:placetype":"venue"
},
  "geometry": {"coordinates":[4.4021668434,51.1989555359],"type":"Point"}
}