{
  "type": "Feature",
  "properties": {
    "iso:country":"BE",
    "sg:address":"Pieter De Nefstraat 37",
    "sg:city":"Turnhout",
    "sg:orig_category":"Schoenen",
    "sg:phone":"+32 14 41 03 38",
    "sg:postcode":"2300",
    "sg:province":"Antwerpen",
    "wof:name":"Christel Maene",
    "wof:placetype":"venue"
},
  "geometry": {"coordinates":[4.9498591423,51.3215408325],"type":"Point"}
}