{
  "type": "Feature",
  "properties": {
    "addr:full":"Rue Hanoteau 100 Charleroi Hainaut 6060",
    "addr:housenumber":"100",
    "addr:postcode":"6060",
    "addr:street":"Rue Hanoteau;Hainaut",
    "iso:country":"BE",
    "sg:address":"Rue Hanoteau 100",
    "sg:city":"Charleroi",
    "sg:orig_category":"Diverse bouwafwerking and reiniging Pleisterwerk",
    "sg:phone":"+32 71 72 77 88",
    "sg:postcode":"6060",
    "sg:province":"Hainaut",
    "wof:name":"Marchand Et Cie",
    "wof:placetype":"venue"
},
  "geometry": {"coordinates":[4.4880981445,50.4251937866],"type":"Point"}
}