{
  "type": "Feature",
  "properties": {
    "iso:country":"BE",
    "sg:address":"Lange Dijkstraat 57",
    "sg:city":"Antwerpen",
    "sg:classifiers":[
        {
            "category":"Fast Food",
            "type":"Food & Drink"
        }
    ],
    "sg:phone":"+32 473 62 66 09",
    "sg:postcode":"2060",
    "sg:province":"Antwerpen",
    "sg:tags":[
        "fried",
        "stand",
        "potato"
    ],
    "wof:name":"Buddy's",
    "wof:placetype":"venue"
},
  "geometry": {"coordinates":[4.41873312,51.2280349731],"type":"Point"}
}