{
  "type": "Feature",
  "properties": {
    "addr:full":"Avenue De Roodebeek 281 Bruxelles (schaerbeek) Bruxelles-Capitale 1030",
    "addr:housenumber":"281",
    "addr:postcode":"1030",
    "addr:street":"Avenue De Roodebeek",
    "iso:country":"BE",
    "sg:address":"Avenue De Roodebeek 281",
    "sg:city":"Bruxelles (schaerbeek)",
    "sg:classifiers":[
        {
            "category":"Health Services",
            "subcategory":"Doctor",
            "type":"Services"
        }
    ],
    "sg:phone":"+32 2 733 27 47",
    "sg:postcode":"1030",
    "sg:province":"Bruxelles-Capitale",
    "sg:tags":[
        "medicinephysicians",
        "surgeon"
    ],
    "wof:name":"Haenecour L",
    "wof:placetype":"venue"
},
  "geometry": {"coordinates":[4.4085850716,50.8501586914],"type":"Point"}
}