{
  "type": "Feature",
  "properties": {
    "iso:country":"BE",
    "sg:address":"Afrikalaan 287",
    "sg:city":"Gent",
    "sg:classifiers":[
        {
            "category":"Professional",
            "subcategory":"Business Services",
            "type":"Services"
        }
    ],
    "sg:phone":"+32 9 251 13 66",
    "sg:postcode":"9000",
    "sg:province":"Oost-Vlaanderen",
    "sg:tags":[
        "consultant",
        "custom"
    ],
    "wof:name":"Machtelynck T",
    "wof:placetype":"venue"
},
  "geometry": {"coordinates":[3.7376730442,51.070526123],"type":"Point"}
}