{
  "type": "Feature",
  "properties": {
    "addr:full":"Marktplein 12 Brakel (nederbrakel) Oost-Vlaanderen 9660",
    "addr:housenumber":"12",
    "addr:postcode":"9660",
    "addr:street":"Marktplein",
    "iso:country":"BE",
    "sg:address":"Marktplein 12",
    "sg:city":"Brakel (nederbrakel)",
    "sg:classifiers":[
        {
            "category":"Health Services",
            "subcategory":"Dentist",
            "type":"Services"
        }
    ],
    "sg:phone":"+32 55 42 17 91",
    "sg:postcode":"9660",
    "sg:province":"Oost-Vlaanderen",
    "wof:name":"De Prijck A",
    "wof:placetype":"venue"
},
  "geometry": {"coordinates":[3.7652640343,50.8038291931],"type":"Point"}
}