{
  "type": "Feature",
  "properties": {
    "addr:full":"Oppemstraat 3a Tervuren Vlaams-Brabant 3080",
    "addr:housenumber":"3a",
    "addr:postcode":"3080",
    "addr:street":"Oppemstraat",
    "iso:country":"BE",
    "sg:address":"Oppemstraat 3a",
    "sg:city":"Tervuren",
    "sg:classifiers":[
        {
            "category":"Communications",
            "subcategory":"Film & Video Production",
            "type":"Services"
        }
    ],
    "sg:phone":"+32 2 767 39 65",
    "sg:postcode":"3080",
    "sg:province":"Vlaams-Brabant",
    "sg:tags":[
        "hiring",
        "-"
    ],
    "wof:name":"A & M Top Video-megaster",
    "wof:placetype":"venue"
},
  "geometry": {"coordinates":[4.5087652206,50.8248901367],"type":"Point"}
}