{
  "type": "Feature",
  "properties": {
    "iso:country":"BE",
    "sg:address":"Kerkstraat 71",
    "sg:city":"Antwerpen",
    "sg:orig_category":"Artiesten and kunstenaars",
    "sg:phone":"+32 3 235 44 98",
    "sg:postcode":"2060",
    "sg:province":"Antwerpen",
    "wof:name":"De Graef",
    "wof:placetype":"venue"
},
  "geometry": {"coordinates":[4.4311442375,51.2186164856],"type":"Point"}
}