{
  "type": "Feature",
  "properties": {
    "addr:full":"Rue Th\u00c9odore Dujardin 10 Limbourg Li\u00e8ge 4830",
    "addr:housenumber":"10",
    "addr:postcode":"4830",
    "addr:street":"Rue The\u0301Odore Dujardin",
    "iso:country":"BE",
    "sg:address":"Rue Th\u00c9odore Dujardin 10",
    "sg:city":"Limbourg",
    "sg:orig_category":"Artsen and specialisten",
    "sg:phone":"+32 87 76 21 22",
    "sg:postcode":"4830",
    "sg:province":"Li\u00e8ge",
    "wof:name":"Michel Schils",
    "wof:placetype":"venue"
},
  "geometry": {"coordinates":[5.9407401085,50.6112518311],"type":"Point"}
}