{
  "type": "Feature",
  "properties": {
    "addr:full":"Rue Au Bois 357 Bruxelles (woluwe-saint-pierre) Bruxelles-Capitale 1150",
    "addr:housenumber":"357",
    "addr:postcode":"1150",
    "addr:street":"Rue Au Bois",
    "iso:country":"BE",
    "sg:address":"Rue Au Bois 357",
    "sg:city":"Bruxelles (woluwe-saint-pierre)",
    "sg:classifiers":[
        {
            "category":"Professional",
            "subcategory":"Art Services",
            "type":"Services"
        }
    ],
    "sg:phone":"+32 2 770 85 46",
    "sg:postcode":"1150",
    "sg:province":"Bruxelles-Capitale",
    "sg:tags":[
        "graphic",
        "designer"
    ],
    "wof:name":"Wattiau C",
    "wof:placetype":"venue"
},
  "geometry": {"coordinates":[4.4553179741,50.8289794922],"type":"Point"}
}