{
  "type": "Feature",
  "properties": {
    "iso:country":"BE",
    "sg:address":"Aarschotsesteenweg 2",
    "sg:city":"Lier",
    "sg:classifiers":[
        {
            "category":"Education",
            "subcategory":"Dance Studio",
            "type":"Public Place"
        }
    ],
    "sg:phone":"+32 3 480 05 94",
    "sg:postcode":"2500",
    "sg:province":"Antwerpen",
    "sg:tags":[
        "school",
        "dancing"
    ],
    "wof:name":"Rhythm & Feet Vzw",
    "wof:placetype":"venue"
},
  "geometry": {"coordinates":[4.5740699768,51.1248435974],"type":"Point"}
}