{
  "type": "Feature",
  "properties": {
    "addr:full":"Varkensmarkt 24 Brussel/bruxelles Bruxelles-Capitale 1000",
    "addr:housenumber":"24",
    "addr:postcode":"1000",
    "addr:street":"Varkensmarkt;/",
    "iso:country":"BE",
    "sg:address":"Varkensmarkt 24",
    "sg:city":"Brussel/bruxelles",
    "sg:orig_category":"Artsen and specialisten",
    "sg:phone":"+32 2 219 36 11",
    "sg:postcode":"1000",
    "sg:province":"Bruxelles-Capitale",
    "wof:name":"Yvan Kindt",
    "wof:placetype":"venue"
},
  "geometry": {"coordinates":[4.3457422256,50.8535461426],"type":"Point"}
}