{
  "type": "Feature",
  "properties": {
    "iso:country":"BE",
    "sg:address":"Biesputstraat 13b9",
    "sg:city":"Etterbeek/etterbeek",
    "sg:orig_category":"Immobili\u00ebnkantoren",
    "sg:phone":"+32 2 733 37 29",
    "sg:postcode":"1040",
    "sg:province":"Bruxelles-Capitale",
    "wof:name":"Bureau Jolimo-flatobel",
    "wof:placetype":"venue"
},
  "geometry": {"coordinates":[4.3974490166,50.8374862671],"type":"Point"}
}