{
  "type": "Feature",
  "properties": {
    "iso:country":"BE",
    "sg:address":"Square Vergote 31",
    "sg:city":"Bruxelles (schaerbeek)",
    "sg:classifiers":[
        {
            "category":"Health Services",
            "subcategory":"Doctor",
            "type":"Services"
        }
    ],
    "sg:phone":"+32 2 734 90 94",
    "sg:postcode":"1030",
    "sg:province":"Bruxelles-Capitale",
    "sg:tags":[
        "medicinephysicians",
        "surgeon"
    ],
    "wof:name":"L\u00e9onard J P",
    "wof:placetype":"venue"
},
  "geometry": {"coordinates":[4.4033842087,50.845615387],"type":"Point"}
}