{
  "type": "Feature",
  "properties": {
    "addr:full":"Luitenant Liedelstraat 14 Anderlecht Bruxelles-Capitale 1070",
    "addr:housenumber":"14",
    "addr:postcode":"1070",
    "addr:street":"Luitenant Liedelstraat",
    "iso:country":"BE",
    "sg:address":"Luitenant Liedelstraat 14",
    "sg:city":"Anderlecht",
    "sg:orig_category":"Artsen and specialisten",
    "sg:phone":"+32 2 523 23 05",
    "sg:postcode":"1070",
    "sg:province":"Bruxelles-Capitale",
    "wof:name":"Jean-marie Dorsimont",
    "wof:placetype":"venue"
},
  "geometry": {"coordinates":[4.3043341637,50.8302726746],"type":"Point"}
}