{
  "type": "Feature",
  "properties": {
    "addr:full":"Dokter Eduard Moreauxlaan 2 Oostende West-Vlaanderen 8400",
    "addr:housenumber":"2",
    "addr:postcode":"8400",
    "addr:street":"Dokter Eduard Moreauxlaan",
    "iso:country":"BE",
    "sg:address":"Dokter Eduard Moreauxlaan 2",
    "sg:city":"Oostende",
    "sg:classifiers":[
        {
            "category":"Arena",
            "subcategory":"Sports Club",
            "type":"Entertainment"
        }
    ],
    "sg:phone":"+32 59 32 14 52",
    "sg:postcode":"8400",
    "sg:province":"West-Vlaanderen",
    "wof:name":"Kon Jacht Club Oostende",
    "wof:placetype":"venue"
},
  "geometry": {"coordinates":[2.9412519932,51.2245597839],"type":"Point"}
}