{
  "type": "Feature",
  "properties": {
    "addr:full":"Melanedreef 9 Houthulst West-Vlaanderen 8650",
    "addr:housenumber":"9",
    "addr:postcode":"8650",
    "addr:street":"Melanedreef",
    "iso:country":"BE",
    "sg:address":"Melanedreef 9",
    "sg:city":"Houthulst",
    "sg:orig_category":"Eleveurs and marchands de porcs. Eleveurs de bovins",
    "sg:phone":"+32 51 54 44 04",
    "sg:postcode":"8650",
    "sg:province":"West-Vlaanderen",
    "wof:name":"Oswald Puype",
    "wof:placetype":"venue"
},
  "geometry": {"coordinates":[2.9209439754,50.9592018127],"type":"Point"}
}