{
  "type": "Feature",
  "properties": {
    "addr:full":"Rue De Vivy 45 Paliseul Luxembourg 6850",
    "addr:housenumber":"45",
    "addr:postcode":"6850",
    "addr:street":"Rue De Vivy",
    "iso:country":"BE",
    "sg:address":"Rue De Vivy 45",
    "sg:city":"Paliseul",
    "sg:orig_category":"Pharmaciens",
    "sg:phone":"+32 61 53 33 66",
    "sg:postcode":"6850",
    "sg:province":"Luxembourg",
    "wof:name":"A. Desenfans",
    "wof:placetype":"venue"
},
  "geometry": {"coordinates":[5.1349849701,49.9033889771],"type":"Point"}
}