{
  "type": "Feature",
  "properties": {
    "addr:full":"Jan Breydellaan 4 Wingene West-Vlaanderen 8750",
    "addr:housenumber":"4",
    "addr:postcode":"8750",
    "addr:street":"Jan Breydellaan",
    "iso:country":"BE",
    "sg:address":"Jan Breydellaan 4",
    "sg:city":"Wingene",
    "sg:orig_category":"Installation de menuiserie en bois and plastique",
    "sg:phone":"+32 51 61 24 95",
    "sg:postcode":"8750",
    "sg:province":"West-Vlaanderen",
    "wof:name":"Vanderhaegen-vermeulen",
    "wof:placetype":"venue"
},
  "geometry": {"coordinates":[3.2239749432,51.0465736389],"type":"Point"}
}