{
  "type": "Feature",
  "properties": {
    "iso:country":"BE",
    "sg:address":"Rue De Baili\u00c8vre 13",
    "sg:city":"Sivry-rance",
    "sg:orig_category":"Eleveurs de bovins",
    "sg:phone":"+32 60 41 11 28",
    "sg:postcode":"6470",
    "sg:province":"Hainaut",
    "wof:name":"Lucien Graux",
    "wof:placetype":"venue"
},
  "geometry": {"coordinates":[4.2221589088,50.1287612915],"type":"Point"}
}