{
  "type": "Feature",
  "properties": {
    "iso:country":"BE",
    "sg:address":"Gentsebaan 97",
    "sg:city":"Sint-niklaas",
    "sg:orig_category":"R\u00e9alisation de programmes and logiciels",
    "sg:phone":"+32 3 765 16 95",
    "sg:postcode":"9100",
    "sg:province":"Oost-Vlaanderen",
    "wof:name":"Poolers Webdesign",
    "wof:placetype":"venue"
},
  "geometry": {"coordinates":[4.1240859032,51.1488571167],"type":"Point"}
}