{
  "type": "Feature",
  "properties": {
    "iso:country":"BE",
    "sg:address":"Place De Cordes 10",
    "sg:city":"Frasnes-lez-anvaing",
    "sg:classifiers":[
        {
            "category":"Cafe",
            "type":"Food & Drink"
        }
    ],
    "sg:phone":"+32 69 85 91 25",
    "sg:postcode":"7911",
    "sg:province":"Hainaut",
    "sg:tags":[
        "caf\u00e9s"
    ],
    "wof:name":"Leclercq T. & Cie",
    "wof:placetype":"venue"
},
  "geometry": {"coordinates":[3.6192600727,50.6668701172],"type":"Point"}
}