{
  "type": "Feature",
  "properties": {
    "addr:full":"Rue De Wand 49 Brussel/bruxelles Bruxelles-Capitale 1020",
    "addr:housenumber":"49",
    "addr:postcode":"1020",
    "addr:street":"Rue De Wand;/",
    "iso:country":"BE",
    "sg:address":"Rue De Wand 49",
    "sg:city":"Brussel/bruxelles",
    "sg:classifiers":[
        {
            "category":"Fast Food",
            "type":"Food & Drink"
        }
    ],
    "sg:phone":"+32 2 268 45 71",
    "sg:postcode":"1020",
    "sg:province":"Bruxelles-Capitale",
    "sg:tags":[
        "\u00c0",
        "restaurants",
        "emporter",
        "restaurant"
    ],
    "wof:name":"Skievelat",
    "wof:placetype":"venue"
},
  "geometry": {"coordinates":[4.3583641052,50.896697998],"type":"Point"}
}