{
  "type": "Feature",
  "properties": {
    "addr:full":"Avenue Gustave Latinis 41 Bruxelles (schaerbeek) Bruxelles-Capitale 1030",
    "addr:housenumber":"41",
    "addr:postcode":"1030",
    "addr:street":"Avenue Gustave Latinis",
    "iso:country":"BE",
    "sg:address":"Avenue Gustave Latinis 41",
    "sg:city":"Bruxelles (schaerbeek)",
    "sg:classifiers":[
        {
            "category":"Building & Trades",
            "subcategory":"Locksmith",
            "type":"Services"
        }
    ],
    "sg:phone":"+32 2 242 13 19",
    "sg:postcode":"1030",
    "sg:province":"Bruxelles-Capitale",
    "sg:tags":[
        "lock",
        "key"
    ],
    "wof:name":"Dino (chez)",
    "wof:placetype":"venue"
},
  "geometry": {"coordinates":[4.3874130249,50.8664779663],"type":"Point"}
}