{
  "type": "Feature",
  "properties": {
    "iso:country":"BE",
    "sg:address":"Meentakstraat 1a",
    "sg:city":"Meulebeke",
    "sg:classifiers":[
        {
            "category":"Autos & Motor Vehicles",
            "subcategory":"Motorcycle Sales",
            "type":"Retail Goods"
        }
    ],
    "sg:phone":"+32 51 48 91 82",
    "sg:postcode":"8760",
    "sg:province":"West-Vlaanderen",
    "sg:tags":[
        "scooter",
        "-",
        "moped"
    ],
    "wof:name":"D.s. Motoren",
    "wof:placetype":"venue"
},
  "geometry": {"coordinates":[3.3001320362,50.9582862854],"type":"Point"}
}