{
  "type": "Feature",
  "properties": {
    "iso:country":"BE",
    "sg:address":"Geldenaaksebaan 105",
    "sg:city":"Leuven (heverlee)",
    "sg:classifiers":[
        {
            "category":"Retail",
            "subcategory":"Repair Shop",
            "type":"Services"
        }
    ],
    "sg:phone":"+32 16 40 38 55",
    "sg:postcode":"3001",
    "sg:province":"Vlaams-Brabant",
    "sg:tags":[
        "-",
        "clothing",
        "alteration"
    ],
    "wof:name":"Mesotten A",
    "wof:placetype":"venue"
},
  "geometry": {"coordinates":[4.7119221687,50.8633003235],"type":"Point"}
}