{
  "type": "Feature",
  "properties": {
    "addr:full":"Rue Daumerie 73 Genappe Brabant Wallon 1471",
    "addr:housenumber":"73",
    "addr:postcode":"1471",
    "addr:street":"Rue Daumerie;Wallon",
    "iso:country":"BE",
    "sg:address":"Rue Daumerie 73",
    "sg:city":"Genappe",
    "sg:orig_category":"Gespecialiseerde residenti\u00eble bouw",
    "sg:phone":"+32 67 78 08 74",
    "sg:postcode":"1471",
    "sg:province":"Brabant Wallon",
    "wof:name":"Fernand Bodden",
    "wof:placetype":"venue"
},
  "geometry": {"coordinates":[4.442111969,50.5893173218],"type":"Point"}
}