{
  "type": "Feature",
  "properties": {
    "addr:full":"Fortune De Kokerlaan 2 Evergem Oost-Vlaanderen 9940",
    "addr:housenumber":"2",
    "addr:postcode":"9940",
    "addr:street":"Fortune De Kokerlaan;Oost-Vlaanderen",
    "iso:country":"BE",
    "sg:address":"Fortune De Kokerlaan 2",
    "sg:city":"Evergem",
    "sg:orig_category":"Pharmaciens",
    "sg:phone":"+32 9 253 88 55",
    "sg:postcode":"9940",
    "sg:province":"Oost-Vlaanderen",
    "wof:name":"P. Baetens",
    "wof:placetype":"venue"
},
  "geometry": {"coordinates":[3.7090079784,51.1098976135],"type":"Point"}
}