{
  "type": "Feature",
  "properties": {
    "iso:country":"BE",
    "sg:address":"Rue Dewiest Fran\u00e7ois 141",
    "sg:city":"Charleroi (jumet)",
    "sg:classifiers":[
        {
            "category":"Shopping",
            "subcategory":"Books",
            "type":"Retail Goods"
        }
    ],
    "sg:phone":"+32 71 35 28 15",
    "sg:postcode":"6040",
    "sg:province":"Hainaut",
    "sg:tags":[
        "bookseller"
    ],
    "wof:name":"Place (librairie De La)",
    "wof:placetype":"venue"
},
  "geometry": {"coordinates":[4.4145717621,50.435092926],"type":"Point"}
}