{
  "type": "Feature",
  "properties": {
    "addr:full":"Kortrijkstraat 19 Avelgem West-Vlaanderen 8580",
    "addr:housenumber":"19",
    "addr:postcode":"8580",
    "addr:street":"Kortrijkstraat",
    "iso:country":"BE",
    "sg:address":"Kortrijkstraat 19",
    "sg:city":"Avelgem",
    "sg:orig_category":"Gestion des d\u00e9charges and sites d\u00e9finitifs de stockage",
    "sg:phone":"+32 56 64 59 49",
    "sg:postcode":"8580",
    "sg:province":"West-Vlaanderen",
    "wof:name":"Containerpark Avelgem",
    "wof:placetype":"venue"
},
  "geometry": {"coordinates":[3.4426779747,50.7757072449],"type":"Point"}
}