{
  "type": "Feature",
  "properties": {
    "iso:country":"BE",
    "sg:address":"Rue Des Hayettes 118",
    "sg:city":"Namur",
    "sg:classifiers":[
        {
            "category":"Real Estate",
            "subcategory":"Real Estate Services",
            "type":"Services"
        }
    ],
    "sg:phone":"+32 81 87 96 97",
    "sg:postcode":"5000",
    "sg:province":"Namur",
    "wof:name":"Van Loocke Et Simon & Cie Snc",
    "wof:placetype":"venue"
},
  "geometry": {"coordinates":[4.8390898705,50.4546203613],"type":"Point"}
}