{
  "type": "Feature",
  "properties": {
    "iso:country":"BE",
    "sg:address":"Valeriaan 14",
    "sg:city":"Brasschaat",
    "sg:orig_category":"Location d'appareils audio-visuels",
    "sg:phone":"+32 3 653 14 24",
    "sg:postcode":"2930",
    "sg:province":"Antwerpen",
    "wof:name":"Compact Audio Projects",
    "wof:placetype":"venue"
},
  "geometry": {"coordinates":[4.513133049,51.2932510376],"type":"Point"}
}