{
  "type": "Feature",
  "properties": {
    "iso:country":"BE",
    "sg:address":"Avenue Brugmann 16",
    "sg:city":"Sint-gillis/saint-gilles",
    "sg:orig_category":"Architectes",
    "sg:phone":"+32 2 344 64 64",
    "sg:postcode":"1060",
    "sg:province":"Bruxelles-Capitale",
    "wof:name":"Sefik Birkiye",
    "wof:placetype":"venue"
},
  "geometry": {"coordinates":[4.3533649445,50.8218383789],"type":"Point"}
}