{
  "type": "Feature",
  "properties": {
    "addr:full":"Rue De L\u00b4aviation 74 Seraing Li\u00e8ge 4100",
    "addr:housenumber":"74",
    "addr:postcode":"4100",
    "addr:street":"Rue De L\u00b4Aviation",
    "iso:country":"BE",
    "sg:address":"Rue De L\u00b4aviation 74",
    "sg:city":"Seraing",
    "sg:orig_category":"Sportclubs Sportterreinen and installaties behalve sportcentra",
    "sg:phone":"+32 496 33 39 09",
    "sg:postcode":"4100",
    "sg:province":"Li\u00e8ge",
    "wof:name":"R.c. Xv Seraing",
    "wof:placetype":"venue"
},
  "geometry": {"coordinates":[5.5010519028,50.590297699],"type":"Point"}
}