{
  "type": "Feature",
  "properties": {
    "addr:full":"Rue Cit\u00c9 Du Chestia 22 Profondeville Namur 5170",
    "addr:housenumber":"22",
    "addr:postcode":"5170",
    "addr:street":"Rue Cite\u0301 Du Chestia",
    "iso:country":"BE",
    "sg:address":"Rue Cit\u00c9 Du Chestia 22",
    "sg:city":"Profondeville",
    "sg:classifiers":[
        {
            "category":"Insurance",
            "subcategory":"Life Insurance",
            "type":"Services"
        }
    ],
    "sg:phone":"+32 81 43 48 35",
    "sg:postcode":"5170",
    "sg:province":"Namur",
    "sg:tags":[
        "assurance"
    ],
    "wof:name":"D. Pastoret",
    "wof:placetype":"venue"
},
  "geometry": {"coordinates":[4.8674049377,50.3786392212],"type":"Point"}
}