{
  "type": "Feature",
  "properties": {
    "iso:country":"BE",
    "sg:address":"Rue G\u00c9n\u00c9ral Thys 27",
    "sg:city":"Dalhem",
    "sg:orig_category":"Werk and personeelsselectie",
    "sg:phone":"+32 4 374 24 44",
    "sg:postcode":"4607",
    "sg:province":"Li\u00e8ge",
    "wof:name":"Ale Dalhem",
    "wof:placetype":"venue"
},
  "geometry": {"coordinates":[5.7242879868,50.7123413086],"type":"Point"}
}