{
  "type": "Feature",
  "properties": {
    "addr:full":"Kapellestraat 6 Wortegem-petegem Oost-Vlaanderen 9790",
    "addr:housenumber":"6",
    "addr:postcode":"9790",
    "addr:street":"Kapellestraat",
    "iso:country":"BE",
    "sg:address":"Kapellestraat 6",
    "sg:city":"Wortegem-petegem",
    "sg:orig_category":"M\u00e9decins and sp\u00e9cialistes",
    "sg:phone":"+32 56 60 82 11",
    "sg:postcode":"9790",
    "sg:province":"Oost-Vlaanderen",
    "wof:name":"Freddy Van Den Mooter",
    "wof:placetype":"venue"
},
  "geometry": {"coordinates":[3.46814394,50.8747711182],"type":"Point"}
}