{
  "type": "Feature",
  "properties": {
    "iso:country":"BE",
    "sg:address":"Mariakerkelaan 243",
    "sg:city":"Oostende",
    "sg:classifiers":[
        {
            "category":"Health Services",
            "subcategory":"Dentist",
            "type":"Services"
        }
    ],
    "sg:phone":"+32 59 50 56 55",
    "sg:postcode":"8400",
    "sg:province":"West-Vlaanderen",
    "wof:name":"Devillers A",
    "wof:placetype":"venue"
},
  "geometry": {"coordinates":[2.8962340355,51.212223053],"type":"Point"}
}