{
  "type": "Feature",
  "properties": {
    "iso:country":"BE",
    "sg:address":"Vaartstraat 45",
    "sg:city":"Wielsbeke",
    "sg:orig_category":"Varkenskwekers",
    "sg:phone":"+32 56 66 74 87",
    "sg:postcode":"8710",
    "sg:province":"West-Vlaanderen",
    "wof:name":"M Debrabandere",
    "wof:placetype":"venue"
},
  "geometry": {"coordinates":[3.3425900936,50.9005508423],"type":"Point"}
}