{
  "type": "Feature",
  "properties": {
    "addr:full":"Place Louise Godin 15 Namur Namur 5000",
    "addr:housenumber":"15",
    "addr:postcode":"5000",
    "addr:street":"Place Louise Godin",
    "iso:country":"BE",
    "sg:address":"Place Louise Godin 15",
    "sg:city":"Namur",
    "sg:orig_category":"Artsen and specialisten",
    "sg:phone":"+32 81 72 05 74",
    "sg:postcode":"5000",
    "sg:province":"Namur",
    "wof:name":"Pierre Balligand",
    "wof:placetype":"venue"
},
  "geometry": {"coordinates":[4.843059063,50.4603843689],"type":"Point"}
}