{
  "type": "Feature",
  "properties": {
    "iso:country":"BE",
    "sg:address":"Kadijk 23",
    "sg:city":"Overpelt",
    "sg:orig_category":"Sportclubs",
    "sg:phone":"+32 11 64 82 83",
    "sg:postcode":"3900",
    "sg:province":"Limburg",
    "wof:name":"Turnverbond Overpelt",
    "wof:placetype":"venue"
},
  "geometry": {"coordinates":[5.4129781723,51.2109146118],"type":"Point"}
}