{
  "type": "Feature",
  "properties": {
    "iso:country":"BE",
    "sg:address":"Blarenberglaan 2",
    "sg:city":"Mechelen",
    "sg:classifiers":[
        {
            "category":"Professional",
            "subcategory":"Management & Consulting",
            "type":"Services"
        }
    ],
    "sg:phone":"+32 15 78 37 11",
    "sg:postcode":"2800",
    "sg:province":"Antwerpen",
    "sg:tags":[
        "information",
        "technology"
    ],
    "wof:name":"Eds Belgium Electronic Data Systems Nv",
    "wof:placetype":"venue"
},
  "geometry": {"coordinates":[4.4494891167,51.0556106567],"type":"Point"}
}