{
  "type": "Feature",
  "properties": {
    "iso:country":"BE",
    "sg:address":"Route D'ath 108",
    "sg:city":"Mons (nimy)",
    "sg:classifiers":[
        {
            "category":"Health Services",
            "subcategory":"Health Practitioner",
            "type":"Services"
        }
    ],
    "sg:phone":"+32 65 22 68 64",
    "sg:postcode":"7020",
    "sg:province":"Hainaut",
    "sg:tags":[
        "physiotherapist"
    ],
    "wof:name":"Delaunois Anne",
    "wof:placetype":"venue"
},
  "geometry": {"coordinates":[3.9455709457,50.4850540161],"type":"Point"}
}