{
  "type": "Feature",
  "properties": {
    "iso:country":"BE",
    "sg:address":"Lijsterlaan 9",
    "sg:city":"Bornem",
    "sg:orig_category":"Dranken",
    "sg:phone":"+32 3 889 06 35",
    "sg:postcode":"2880",
    "sg:province":"Antwerpen",
    "wof:name":"Boon",
    "wof:placetype":"venue"
},
  "geometry": {"coordinates":[4.2038550377,51.0739746094],"type":"Point"}
}