{
  "type": "Feature",
  "properties": {
    "iso:country":"BE",
    "sg:address":"Bissegemstraat 158",
    "sg:city":"Wevelgem",
    "sg:orig_category":"Tuinen",
    "sg:phone":"+32 56 41 15 97",
    "sg:postcode":"8560",
    "sg:province":"West-Vlaanderen",
    "wof:name":"Vercruysse Tuinen",
    "wof:placetype":"venue"
},
  "geometry": {"coordinates":[3.2106070518,50.8369407654],"type":"Point"}
}