{
  "type": "Feature",
  "properties": {
    "iso:country":"BE",
    "sg:address":"Groeneweg 164",
    "sg:city":"Zulte",
    "sg:orig_category":"Eleveurs de bovins",
    "sg:phone":"+32 9 388 85 56",
    "sg:postcode":"9870",
    "sg:province":"Oost-Vlaanderen",
    "wof:name":"Dirk Van Parys",
    "wof:placetype":"venue"
},
  "geometry": {"coordinates":[3.4892389774,50.9428710938],"type":"Point"}
}