{
  "type": "Feature",
  "properties": {
    "iso:country":"BE",
    "sg:address":"Avenue De L'arm\u00c9e 44",
    "sg:city":"Etterbeek/etterbeek",
    "sg:orig_category":"Artistes ind\u00e9pendants",
    "sg:phone":"+32 2 733 30 43",
    "sg:postcode":"1040",
    "sg:province":"Bruxelles-Capitale",
    "wof:name":"Froustrey",
    "wof:placetype":"venue"
},
  "geometry": {"coordinates":[4.404132843,50.836227417],"type":"Point"}
}