{
  "type": "Feature",
  "properties": {
    "iso:country":"BE",
    "sg:address":"Beukenlaan 86a",
    "sg:city":"Gent",
    "sg:orig_category":"Autoverhuur",
    "sg:phone":"+32 9 220 44 10",
    "sg:postcode":"9051",
    "sg:province":"Oost-Vlaanderen",
    "wof:name":"Keddy",
    "wof:placetype":"venue"
},
  "geometry": {"coordinates":[3.6849329472,51.0318984985],"type":"Point"}
}