{
  "type": "Feature",
  "properties": {
    "addr:full":"Au Point Du Jour 8 Lierneux Li\u00e8ge 4990",
    "addr:housenumber":"8",
    "addr:postcode":"4990",
    "iso:country":"BE",
    "sg:address":"Au Point Du Jour 8",
    "sg:city":"Lierneux",
    "sg:classifiers":[
        {
            "category":"Shopping",
            "subcategory":"Bicycles & Sporting Goods",
            "type":"Retail Goods"
        }
    ],
    "sg:phone":"+32 80 31 90 73",
    "sg:postcode":"4990",
    "sg:province":"Li\u00e8ge",
    "sg:tags":[
        "tyre"
    ],
    "wof:name":"Pneus Du Pont De Lienne",
    "wof:placetype":"venue"
},
  "geometry": {"coordinates":[5.7981901169,50.2925796509],"type":"Point"}
}