{
  "type": "Feature",
  "properties": {
    "addr:full":"Charleroise Steenweg 80 Sint-gillis/saint-gilles Bruxelles-Capitale 1060",
    "addr:housenumber":"80",
    "addr:postcode":"1060",
    "addr:street":"Charleroise Steenweg",
    "iso:country":"BE",
    "sg:address":"Charleroise Steenweg 80",
    "sg:city":"Sint-gillis/saint-gilles",
    "sg:classifiers":[
        {
            "category":"Restaurant",
            "type":"Food & Drink"
        }
    ],
    "sg:phone":"+32 2 534 56 59",
    "sg:postcode":"1060",
    "sg:province":"Bruxelles-Capitale",
    "sg:tags":[
        "caf\u00e9s"
    ],
    "wof:name":"L'esquisse Italian Snack",
    "wof:placetype":"venue"
},
  "geometry": {"coordinates":[4.3559179306,50.8292808533],"type":"Point"}
}