{
  "type": "Feature",
  "properties": {
    "addr:full":"Dennenlaan 8 Rumst Antwerpen 2840",
    "addr:housenumber":"8",
    "addr:postcode":"2840",
    "addr:street":"Dennenlaan",
    "iso:country":"BE",
    "sg:address":"Dennenlaan 8",
    "sg:city":"Rumst",
    "sg:orig_category":"Banken and kredietinstellingen Levensverzekeringsmaatschappijen Verzekeringen vastgoed Verzekeringsm",
    "sg:phone":"+32 3 888 96 31",
    "sg:postcode":"2840",
    "sg:province":"Antwerpen",
    "wof:name":"Zakenkantoor Gielis & Van Hoof",
    "wof:placetype":"venue"
},
  "geometry": {"coordinates":[4.4133381844,51.1023750305],"type":"Point"}
}