{
  "type": "Feature",
  "properties": {
    "iso:country":"BE",
    "sg:address":"Chauss\u00c9e D\u00b4ixelles 206",
    "sg:city":"Elsene/ixelles",
    "sg:orig_category":"M\u00e9decines alternatives",
    "sg:phone":"+32 2 640 27 23",
    "sg:postcode":"1050",
    "sg:province":"Bruxelles-Capitale",
    "wof:name":"Legs And Face Center",
    "wof:placetype":"venue"
},
  "geometry": {"coordinates":[4.3682999611,50.8316688538],"type":"Point"}
}