{
  "type": "Feature",
  "properties": {
    "addr:full":"Matteottistraat 33 Niel Antwerpen 2845",
    "addr:housenumber":"33",
    "addr:postcode":"2845",
    "addr:street":"Matteottistraat",
    "iso:country":"BE",
    "sg:address":"Matteottistraat 33",
    "sg:city":"Niel",
    "sg:orig_category":"Zuivelproducten",
    "sg:phone":"+32 3 888 88 42",
    "sg:postcode":"2845",
    "sg:province":"Antwerpen",
    "wof:name":"Rudi Van Camp",
    "wof:placetype":"venue"
},
  "geometry": {"coordinates":[4.3285398483,51.1140861511],"type":"Point"}
}