{
  "type": "Feature",
  "properties": {
    "iso:country":"BE",
    "sg:address":"Gyselstraat 106",
    "sg:city":"Sint-niklaas",
    "sg:classifiers":[
        {
            "category":"Personal",
            "subcategory":"Beauty Salon",
            "type":"Services"
        }
    ],
    "sg:phone":"+32 3 765 01 98",
    "sg:postcode":"9100",
    "sg:province":"Oost-Vlaanderen",
    "sg:tags":[
        "de",
        "coiffure"
    ],
    "wof:name":"Didier Verschueren",
    "wof:placetype":"venue"
},
  "geometry": {"coordinates":[4.1755461693,51.1960868835],"type":"Point"}
}