{
  "type": "Feature",
  "properties": {
    "iso:country":"BE",
    "sg:address":"Chauss\u00c9e De L'europe 19",
    "sg:city":"Couvin",
    "sg:orig_category":"Pain, p\u00e2tisseries and confiseries",
    "sg:phone":"+32 60 37 77 28",
    "sg:postcode":"5660",
    "sg:province":"Namur",
    "wof:name":"Christian Bataille",
    "wof:placetype":"venue"
},
  "geometry": {"coordinates":[4.4537410736,49.9605827332],"type":"Point"}
}