{
  "type": "Feature",
  "properties": {
    "iso:country":"BE",
    "sg:address":"Singel 6",
    "sg:city":"Borsbeek",
    "sg:classifiers":[
        {
            "category":"Building & Trades",
            "subcategory":"Construction",
            "type":"Services"
        }
    ],
    "sg:phone":"+32 3 321 54 54",
    "sg:postcode":"2150",
    "sg:province":"Antwerpen",
    "sg:tags":[
        "duct",
        "underground",
        "ducting"
    ],
    "wof:name":"Aalosc Bvba",
    "wof:placetype":"venue"
},
  "geometry": {"coordinates":[4.4868679047,51.1980552673],"type":"Point"}
}