{
  "type": "Feature",
  "properties": {
    "iso:country":"BE",
    "sg:address":"Bisschopstraat 42",
    "sg:city":"Antwerpen",
    "sg:classifiers":[
        {
            "category":"Professional",
            "subcategory":"Art Services",
            "type":"Services"
        }
    ],
    "sg:phone":"+32 3 235 34 16",
    "sg:postcode":"2060",
    "sg:province":"Antwerpen",
    "sg:tags":[
        "designer",
        "ontwerpers"
    ],
    "wof:name":"Mark Wauters",
    "wof:placetype":"venue"
},
  "geometry": {"coordinates":[4.4259448051,51.2193450928],"type":"Point"}
}