{
  "type": "Feature",
  "properties": {
    "addr:full":"Stationsstraat 43 Wachtebeke Oost-Vlaanderen 9185",
    "addr:housenumber":"43",
    "addr:postcode":"9185",
    "addr:street":"Stationsstraat",
    "iso:country":"BE",
    "sg:address":"Stationsstraat 43",
    "sg:city":"Wachtebeke",
    "sg:classifiers":[
        {
            "category":"Insurance",
            "subcategory":"Insurance Agent",
            "type":"Services"
        }
    ],
    "sg:phone":"+32 9 345 00 89",
    "sg:postcode":"9185",
    "sg:province":"Oost-Vlaanderen",
    "sg:tags":[
        "broker"
    ],
    "wof:name":"Janda Zakenkantoor Nv",
    "wof:placetype":"venue"
},
  "geometry": {"coordinates":[3.8628129959,51.1734924316],"type":"Point"}
}