{
  "type": "Feature",
  "properties": {
    "addr:full":"Provinciale Steenweg 111 Schelle Antwerpen 2627",
    "addr:housenumber":"111",
    "addr:postcode":"2627",
    "addr:street":"Provinciale Steenweg",
    "iso:country":"BE",
    "sg:address":"Provinciale Steenweg 111",
    "sg:city":"Schelle",
    "sg:orig_category":"Banques and organismes de cr\u00e9dit",
    "sg:phone":"+32 3 887 45 12",
    "sg:postcode":"2627",
    "sg:province":"Antwerpen",
    "wof:name":"Anhyp",
    "wof:placetype":"venue"
},
  "geometry": {"coordinates":[4.3389358521,51.1270103455],"type":"Point"}
}