{
  "type": "Feature",
  "properties": {
    "iso:country":"BE",
    "sg:address":"Koolaerdstraat 88",
    "sg:city":"Gistel",
    "sg:orig_category":"Caf\u00e9s. Entretien and r\u00e9parations de voitures",
    "sg:phone":"+32 59 27 81 41",
    "sg:postcode":"8470",
    "sg:province":"West-Vlaanderen",
    "wof:name":"Garage Westhinder",
    "wof:placetype":"venue"
},
  "geometry": {"coordinates":[2.9552400112,51.1547889709],"type":"Point"}
}