{
  "type": "Feature",
  "properties": {
    "iso:country":"BE",
    "sg:address":"Baalhoek 29",
    "sg:city":"Grimbergen (strombeek-bever)",
    "sg:orig_category":"Non-Classified Establishments",
    "sg:phone":"+32 2 267 48 86",
    "sg:postcode":"1853",
    "sg:province":"Vlaams-Brabant",
    "wof:name":"Van Ewijk-kiekens Bvba",
    "wof:placetype":"venue"
},
  "geometry": {"coordinates":[4.3524808884,50.904800415],"type":"Point"}
}