{
  "type": "Feature",
  "properties": {
    "iso:country":"BE",
    "sg:address":"Bautebrugstraat 4",
    "sg:city":"Pepingen",
    "sg:orig_category":"Eleveurs de bovins",
    "sg:phone":"+32 2 396 26 43",
    "sg:postcode":"1670",
    "sg:province":"Vlaams-Brabant",
    "wof:name":"Jacques Derycke",
    "wof:placetype":"venue"
},
  "geometry": {"coordinates":[4.1170220375,50.7232398987],"type":"Point"}
}