{
  "type": "Feature",
  "properties": {
    "addr:full":"Hugo Verrieststraat 3 Waregem West-Vlaanderen 8790",
    "addr:housenumber":"3",
    "addr:postcode":"8790",
    "addr:street":"Hugo Verrieststraat",
    "iso:country":"BE",
    "sg:address":"Hugo Verrieststraat 3",
    "sg:city":"Waregem",
    "sg:orig_category":"Journaux. Fournitures de bureau. Tabac. Articles de f\u00eate, farces and attrapes",
    "sg:phone":"+32 56 60 98 12",
    "sg:postcode":"8790",
    "sg:province":"West-Vlaanderen",
    "wof:name":"Dagbladhandel De Munk",
    "wof:placetype":"venue"
},
  "geometry": {"coordinates":[3.4148650169,50.8882141113],"type":"Point"}
}