{
  "type": "Feature",
  "properties": {
    "addr:full":"Rue Du Four 4 Chimay Hainaut 6460",
    "addr:housenumber":"4",
    "addr:postcode":"6460",
    "addr:street":"Rue Du Four",
    "iso:country":"BE",
    "sg:address":"Rue Du Four 4",
    "sg:city":"Chimay",
    "sg:orig_category":"Openbare veiligheid",
    "sg:phone":"+32 60 21 12 34",
    "sg:postcode":"6460",
    "sg:province":"Hainaut",
    "wof:name":"Police F\u00c9d\u00c9rale/federale Politie",
    "wof:placetype":"venue"
},
  "geometry": {"coordinates":[4.3143539429,50.0493965149],"type":"Point"}
}