{
  "type": "Feature",
  "properties": {
    "iso:country":"BE",
    "sg:address":"Rue Mary 2",
    "sg:city":"Sombreffe (ligny)",
    "sg:orig_category":"Non-Classified Establishments",
    "sg:phone":"+32 71 88 98 82",
    "sg:postcode":"5140",
    "sg:province":"Namur",
    "wof:name":"B.g.systems And Supplies Sprl",
    "wof:placetype":"venue"
},
  "geometry": {"coordinates":[4.5667319298,50.5142555237],"type":"Point"}
}