{
  "type": "Feature",
  "properties": {
    "iso:country":"BE",
    "sg:address":"Jan Martin Van Lierdelaan 24",
    "sg:city":"Dilbeek (itterbeek)",
    "sg:classifiers":[
        {
            "category":"Arena",
            "subcategory":"Sports Club",
            "type":"Entertainment"
        }
    ],
    "sg:phone":"+32 3 475 16 72",
    "sg:postcode":"1701",
    "sg:province":"Vlaams-Brabant",
    "wof:name":"Steketee Paintball & Survival",
    "wof:placetype":"venue"
},
  "geometry": {"coordinates":[4.4576702118,51.5314025879],"type":"Point"}
}