{
  "type": "Feature",
  "properties": {
    "iso:country":"BE",
    "sg:address":"Pervijzestraat 17",
    "sg:city":"Diksmuide",
    "sg:orig_category":"Electrom\u00e9nager, t\u00e9l\u00e9visions and radios Installation \u00e9lectrique industrielle. Installation \u00e9lectrique",
    "sg:phone":"+32 51 55 50 01",
    "sg:postcode":"8600",
    "sg:province":"West-Vlaanderen",
    "wof:name":"Elektro Decat",
    "wof:placetype":"venue"
},
  "geometry": {"coordinates":[2.793790102,51.063949585],"type":"Point"}
}