{
  "type": "Feature",
  "properties": {
    "addr:full":"Hekkenhoek 25 Dendermonde Oost-Vlaanderen 9200",
    "addr:housenumber":"25",
    "addr:postcode":"9200",
    "addr:street":"Hekkenhoek;Oost-Vlaanderen",
    "iso:country":"BE",
    "sg:address":"Hekkenhoek 25",
    "sg:city":"Dendermonde",
    "sg:orig_category":"Epiceries",
    "sg:phone":"+32 52 21 37 47",
    "sg:postcode":"9200",
    "sg:province":"Oost-Vlaanderen",
    "wof:name":"Etienne Van Couwenberghe",
    "wof:placetype":"venue"
},
  "geometry": {"coordinates":[4.0881152153,51.0509757996],"type":"Point"}
}