{
  "type": "Feature",
  "properties": {
    "addr:full":"Avenue Alphonse Allard 251 Braine-l\u00b4alleud Brabant Wallon 1420",
    "addr:housenumber":"251",
    "addr:postcode":"1420",
    "addr:street":"Avenue Alphonse Allard;Brabant Wallon",
    "iso:country":"BE",
    "sg:address":"Avenue Alphonse Allard 251",
    "sg:city":"Braine-l\u00b4alleud",
    "sg:orig_category":"Agences de publicit\u00e9",
    "sg:phone":"+32 2 384 07 91",
    "sg:postcode":"1420",
    "sg:province":"Brabant Wallon",
    "wof:name":"Nikita Concept",
    "wof:placetype":"venue"
},
  "geometry": {"coordinates":[4.3842129707,50.67370224],"type":"Point"}
}