{
  "type": "Feature",
  "properties": {
    "addr:full":"Rue De Roubaix 207 Mouscron Hainaut 7700",
    "addr:housenumber":"207",
    "addr:postcode":"7700",
    "addr:street":"Rue De Roubaix",
    "iso:country":"BE",
    "sg:address":"Rue De Roubaix 207",
    "sg:city":"Mouscron",
    "sg:classifiers":[
        {
            "category":"Retail",
            "subcategory":"Veterinary Services",
            "type":"Services"
        }
    ],
    "sg:phone":"+32 56 34 54 92",
    "sg:postcode":"7700",
    "sg:province":"Hainaut",
    "sg:tags":[
        "veterinarian"
    ],
    "wof:name":"Charvet R",
    "wof:placetype":"venue"
},
  "geometry": {"coordinates":[3.2066590786,50.7352333069],"type":"Point"}
}