{
  "type": "Feature",
  "properties": {
    "iso:country":"BE",
    "sg:address":"Van Craeyenhemstraat 24",
    "sg:city":"Grobbendonk",
    "sg:classifiers":[
        {
            "category":"Real Estate",
            "subcategory":"Architect",
            "type":"Services"
        }
    ],
    "sg:phone":"+32 14 51 20 58",
    "sg:postcode":"2280",
    "sg:province":"Antwerpen",
    "wof:name":"Smits A",
    "wof:placetype":"venue"
},
  "geometry": {"coordinates":[4.7225079536,51.191318512],"type":"Point"}
}