{
  "type": "Feature",
  "properties": {
    "iso:country":"BE",
    "sg:address":"Rue D'arlon 92",
    "sg:city":"Brussel/bruxelles",
    "sg:orig_category":"Avocats and conseillers juridiques",
    "sg:phone":"+32 2 230 65 30",
    "sg:postcode":"1040",
    "sg:province":"Bruxelles-Capitale",
    "wof:name":"P. Mousel",
    "wof:placetype":"venue"
},
  "geometry": {"coordinates":[4.3736538887,50.8425712585],"type":"Point"}
}