{
  "type": "Feature",
  "properties": {
    "addr:full":"Kloosterstraat 79 Antwerpen Antwerpen 2180",
    "addr:housenumber":"79",
    "addr:postcode":"2180",
    "addr:street":"Kloosterstraat",
    "iso:country":"BE",
    "sg:address":"Kloosterstraat 79",
    "sg:city":"Antwerpen",
    "sg:classifiers":[
        {
            "category":"Personal",
            "subcategory":"Beauty Salon",
            "type":"Services"
        }
    ],
    "sg:phone":"+32 3 542 43 40",
    "sg:postcode":"2180",
    "sg:province":"Antwerpen",
    "sg:tags":[
        "de",
        "coiffure"
    ],
    "wof:name":"Coiffure Jacomo",
    "wof:placetype":"venue"
},
  "geometry": {"coordinates":[4.3945889473,51.215171814],"type":"Point"}
}