{
  "type": "Feature",
  "properties": {
    "iso:country":"BE",
    "sg:address":"Frans De Ceusterlei 27",
    "sg:city":"Schoten",
    "sg:classifiers":[
        {
            "category":"Professional",
            "subcategory":"Art Services",
            "type":"Services"
        }
    ],
    "sg:phone":"+32 3 645 69 98",
    "sg:postcode":"2900",
    "sg:province":"Antwerpen",
    "sg:tags":[
        "photographer"
    ],
    "wof:name":"Van Eetveldt A",
    "wof:placetype":"venue"
},
  "geometry": {"coordinates":[4.4620089531,51.2475471497],"type":"Point"}
}