{
  "type": "Feature",
  "properties": {
    "addr:full":"Achiel Cleynhenslaan 143ba Keerbergen Vlaams-Brabant 3140",
    "addr:postcode":"3140",
    "addr:street":"Achiel Cleynhenslaan 143Ba",
    "iso:country":"BE",
    "sg:address":"Achiel Cleynhenslaan 143ba",
    "sg:city":"Keerbergen",
    "sg:orig_category":"Production de films, t\u00e9l\u00e9films and vid\u00e9os",
    "sg:phone":"+32 15 23 67 60",
    "sg:postcode":"3140",
    "sg:province":"Vlaams-Brabant",
    "wof:name":"Fa. Sebille",
    "wof:placetype":"venue"
},
  "geometry": {"coordinates":[4.6753668785,51.0112075806],"type":"Point"}
}