{
  "type": "Feature",
  "properties": {
    "iso:country":"BE",
    "sg:address":"Ardooisesteenweg 264",
    "sg:city":"Roeselare",
    "sg:classifiers":[
        {
            "category":"Building & Trades",
            "subcategory":"Construction",
            "type":"Services"
        }
    ],
    "sg:phone":"+32 51 20 18 39",
    "sg:postcode":"8800",
    "sg:province":"West-Vlaanderen",
    "sg:tags":[
        "central",
        "heating",
        "system"
    ],
    "wof:name":"Sanitair Vandenweghe B.v.b.a.",
    "wof:placetype":"venue"
},
  "geometry": {"coordinates":[3.1508710384,50.9548683167],"type":"Point"}
}