{
  "type": "Feature",
  "properties": {
    "iso:country":"BE",
    "sg:address":"Butastraat 30",
    "sg:city":"Heusden-zolder",
    "sg:classifiers":[
        {
            "category":"Food & Beverages",
            "subcategory":"Fruits & Vegetables",
            "type":"Retail Goods"
        }
    ],
    "sg:phone":"+32 11 42 74 31",
    "sg:postcode":"3550",
    "sg:province":"Limburg",
    "sg:tags":[
        "l\u00e9gumes",
        "gr"
    ],
    "wof:name":"Jean-pierre Cuyvers",
    "wof:placetype":"venue"
},
  "geometry": {"coordinates":[5.3139648438,51.0231018066],"type":"Point"}
}