{
  "type": "Feature",
  "properties": {
    "addr:full":"Oct De Kerchove D'exaerdestraat 48 Halle (buizingen) Vlaams-Brabant 1501",
    "addr:housenumber":"48",
    "addr:postcode":"1501",
    "addr:street":"D'Exaerdestraat",
    "iso:country":"BE",
    "sg:address":"Oct De Kerchove D'exaerdestraat 48",
    "sg:city":"Halle (buizingen)",
    "sg:classifiers":[
        {
            "category":"Social Services",
            "type":"Services"
        }
    ],
    "sg:phone":"+32 2 361 22 93",
    "sg:postcode":"1501",
    "sg:province":"Vlaams-Brabant",
    "wof:name":"V.p.w. Gewest Halle Ommekaar",
    "wof:placetype":"venue"
},
  "geometry": {"coordinates":[4.2522912025,50.7426109314],"type":"Point"}
}