{
  "type": "Feature",
  "properties": {
    "addr:full":"F\u00c9ronstr\u00c9e 27 Li\u00c8ge Li\u00e8ge 4000",
    "addr:housenumber":"27",
    "addr:postcode":"4000",
    "addr:street":"Fe\u0301Ronstre\u0301E",
    "iso:country":"BE",
    "sg:address":"F\u00c9ronstr\u00c9e 27",
    "sg:city":"Li\u00c8ge",
    "sg:orig_category":"Fotografen and fotostudio's",
    "sg:phone":"+32 4 222 02 25",
    "sg:postcode":"4000",
    "sg:province":"Li\u00e8ge",
    "wof:name":"Luc Lemoine",
    "wof:placetype":"venue"
},
  "geometry": {"coordinates":[5.5779929161,50.6461982727],"type":"Point"}
}