{
  "type": "Feature",
  "properties": {
    "iso:country":"BE",
    "sg:address":"Dorpsstraat 23",
    "sg:city":"Wellen",
    "sg:classifiers":[
        {
            "category":"Home & Garden",
            "subcategory":"Home Furnishings",
            "type":"Retail Goods"
        }
    ],
    "sg:phone":"+32 12 74 41 68",
    "sg:postcode":"3830",
    "sg:province":"Limburg",
    "sg:tags":[
        "interior",
        "decoration"
    ],
    "wof:name":"Kenis (huis)",
    "wof:placetype":"venue"
},
  "geometry": {"coordinates":[5.3341269493,50.8409538269],"type":"Point"}
}