{
  "type": "Feature",
  "properties": {
    "iso:country":"BE",
    "sg:address":"Nieuwmoersestw 139",
    "sg:city":"Essen",
    "sg:classifiers":[
        {
            "category":"Manufacturing",
            "subcategory":"Rubber & Plastics",
            "type":"Manufacturing & Wholesale Goods"
        }
    ],
    "sg:phone":"+32 3 667 74 48",
    "sg:postcode":"2910",
    "sg:province":"Antwerpen",
    "sg:tags":[
        "packaging",
        "material",
        "-"
    ],
    "wof:name":"S A K Nv",
    "wof:placetype":"venue"
},
  "geometry": {"coordinates":[4.499548912,51.4441986084],"type":"Point"}
}