{
  "type": "Feature",
  "properties": {
    "iso:country":"BE",
    "sg:address":"Oudestraat 5",
    "sg:city":"Zonhoven",
    "sg:classifiers":[
        {
            "category":"Arena",
            "subcategory":"Sports Club",
            "type":"Entertainment"
        }
    ],
    "sg:phone":"+32 11 81 58 51",
    "sg:postcode":"3520",
    "sg:province":"Limburg",
    "sg:tags":[
        "terrain",
        "hors",
        "de",
        "installation",
        "sportifs"
    ],
    "wof:name":"Weerstand Zonhoven",
    "wof:placetype":"venue"
},
  "geometry": {"coordinates":[5.3594050407,51.0041427612],"type":"Point"}
}