{
  "type": "Feature",
  "properties": {
    "iso:country":"BE",
    "sg:address":"Weesbeekdal 18",
    "sg:city":"Kortenberg",
    "sg:classifiers":[
        {
            "category":"Arena",
            "subcategory":"Sports Club",
            "type":"Entertainment"
        }
    ],
    "sg:phone":"+32 2 757 07 90",
    "sg:postcode":"3071",
    "sg:province":"Vlaams-Brabant",
    "sg:tags":[
        "de"
    ],
    "wof:name":"V.i.p. Jevaro Sint-agatha-rhode",
    "wof:placetype":"venue"
},
  "geometry": {"coordinates":[4.5519070625,50.9013748169],"type":"Point"}
}