{
  "type": "Feature",
  "properties": {
    "addr:full":"Rue De L'aurore 10 Bruxelles Bruxelles-Capitale 1000",
    "addr:housenumber":"10",
    "addr:postcode":"1000",
    "addr:street":"Rue De L'Aurore",
    "iso:country":"BE",
    "sg:address":"Rue De L'aurore 10",
    "sg:city":"Bruxelles",
    "sg:classifiers":[
        {
            "category":"Shopping",
            "subcategory":"Stationery & Office Supplies",
            "type":"Retail Goods"
        }
    ],
    "sg:phone":"+32 2 640 13 12",
    "sg:postcode":"1000",
    "sg:province":"Bruxelles-Capitale",
    "sg:tags":[
        "fixture"
    ],
    "wof:name":"Symbiance Sc",
    "wof:placetype":"venue"
},
  "geometry": {"coordinates":[4.3519678116,50.8579750061],"type":"Point"}
}