{
  "type": "Feature",
  "properties": {
    "iso:country":"BE",
    "sg:address":"Sint-annaweg 11",
    "sg:city":"Haaltert",
    "sg:orig_category":"Sportclubs",
    "sg:phone":"+32 54 33 22 60",
    "sg:postcode":"9450",
    "sg:province":"Oost-Vlaanderen",
    "wof:name":"V.c. Deco Denderhoutem",
    "wof:placetype":"venue"
},
  "geometry": {"coordinates":[4.0138030052,50.8704185486],"type":"Point"}
}