{
  "type": "Feature",
  "properties": {
    "iso:country":"BE",
    "sg:address":"R. Du March\u00c9 Aux Poulets 32",
    "sg:city":"Brussel/bruxelles",
    "sg:classifiers":[
        {
            "category":"Cafe",
            "type":"Food & Drink"
        }
    ],
    "sg:phone":"+32 2 218 75 90",
    "sg:postcode":"1000",
    "sg:province":"Bruxelles-Capitale",
    "sg:tags":[
        "caf\u00e9s"
    ],
    "wof:name":"Sports Serv. Promotions",
    "wof:placetype":"venue"
},
  "geometry": {"coordinates":[4.3508181572,50.848941803],"type":"Point"}
}