{
  "type": "Feature",
  "properties": {
    "iso:country":"BE",
    "sg:address":"Gemeenteplein 11",
    "sg:city":"Hoegaarden",
    "sg:orig_category":"Epiceries",
    "sg:phone":"+32 16 76 62 42",
    "sg:postcode":"3320",
    "sg:province":"Vlaams-Brabant",
    "wof:name":"Nadine Herreman",
    "wof:placetype":"venue"
},
  "geometry": {"coordinates":[4.8877010345,50.7739944458],"type":"Point"}
}