{
  "type": "Feature",
  "properties": {
    "addr:full":"Rue Des Ardennes 0 Saint-hubert Luxembourg 6870",
    "addr:housenumber":"0",
    "addr:postcode":"6870",
    "addr:street":"Rue Des Ardennes",
    "iso:country":"BE",
    "sg:address":"Rue Des Ardennes 0",
    "sg:city":"Saint-hubert",
    "sg:orig_category":"Jardins botaniques, zoologiques, observatoires and r\u00e9serves naturelles",
    "sg:phone":"+32 61 61 30 10",
    "sg:postcode":"6870",
    "sg:province":"Luxembourg",
    "wof:name":"Roseraie Redout\u00c9",
    "wof:placetype":"venue"
},
  "geometry": {"coordinates":[5.2931900024,50.0140647888],"type":"Point"}
}