{
  "type": "Feature",
  "properties": {
    "iso:country":"BE",
    "sg:address":"Koolmijnlaan 23",
    "sg:city":"Heusden-zolder (heusden)",
    "sg:classifiers":[
        {
            "category":"Real Estate",
            "subcategory":"Surveying",
            "type":"Services"
        }
    ],
    "sg:phone":"+32 11 57 16 46",
    "sg:postcode":"3550",
    "sg:province":"Limburg",
    "sg:tags":[
        "surveyor",
        "land"
    ],
    "wof:name":"Truyers F",
    "wof:placetype":"venue"
},
  "geometry": {"coordinates":[5.2943878174,51.0380249023],"type":"Point"}
}