{
  "type": "Feature",
  "properties": {
    "addr:full":"Oude Heerweg 180 Lokeren Oost-Vlaanderen 9160",
    "addr:housenumber":"180",
    "addr:postcode":"9160",
    "addr:street":"Oude Heerweg",
    "iso:country":"BE",
    "sg:address":"Oude Heerweg 180",
    "sg:city":"Lokeren",
    "sg:classifiers":[
        {
            "category":"Building & Trades",
            "subcategory":"Construction",
            "type":"Services"
        }
    ],
    "sg:phone":"+32 9 348 21 33",
    "sg:postcode":"9160",
    "sg:province":"Oost-Vlaanderen",
    "sg:tags":[
        "installation",
        "-",
        "central",
        "heating"
    ],
    "wof:name":"Roels Bvba",
    "wof:placetype":"venue"
},
  "geometry": {"coordinates":[4.0077610016,51.1160850525],"type":"Point"}
}