{
  "type": "Feature",
  "properties": {
    "addr:full":"Rue De L\u00b4eglise 32 Kelmis/la Calamine Li\u00e8ge 4720",
    "addr:housenumber":"32",
    "addr:postcode":"4720",
    "addr:street":"Rue De L\u00b4Eglise",
    "iso:country":"BE",
    "sg:address":"Rue De L\u00b4eglise 32",
    "sg:city":"Kelmis/la Calamine",
    "sg:orig_category":"V\u00eatements de mariage and c\u00e9r\u00e9monies",
    "sg:phone":"+32 87 65 90 25",
    "sg:postcode":"4720",
    "sg:province":"Li\u00e8ge",
    "wof:name":"Maison Godin Confection",
    "wof:placetype":"venue"
},
  "geometry": {"coordinates":[6.0131120682,50.716178894],"type":"Point"}
}