{
  "type": "Feature",
  "properties": {
    "addr:full":"Schepersweg 93 Genk Limburg 3600",
    "addr:housenumber":"93",
    "addr:postcode":"3600",
    "addr:street":"Schepersweg",
    "iso:country":"BE",
    "sg:address":"Schepersweg 93",
    "sg:city":"Genk",
    "sg:classifiers":[
        {
            "category":"Communications",
            "subcategory":"Film & Video Production",
            "type":"Services"
        }
    ],
    "sg:phone":"+32 89 35 56 61",
    "sg:postcode":"3600",
    "sg:province":"Limburg",
    "sg:tags":[
        "realisation",
        "-"
    ],
    "wof:name":"Didac Films",
    "wof:placetype":"venue"
},
  "geometry": {"coordinates":[5.5474038124,50.9718093872],"type":"Point"}
}