{
  "type": "Feature",
  "properties": {
    "addr:full":"Rue Du Printemps 50-54 Bruxelles (ixelles) Bruxelles-Capitale 1050",
    "addr:postcode":"50-54;1050",
    "addr:street":"Rue Du Printemps",
    "iso:country":"BE",
    "sg:address":"Rue Du Printemps 50-54",
    "sg:city":"Bruxelles (ixelles)",
    "sg:classifiers":[
        {
            "category":"Building & Trades",
            "subcategory":"Construction",
            "type":"Services"
        }
    ],
    "sg:phone":"+32 2 639 08 40",
    "sg:postcode":"1050",
    "sg:province":"Bruxelles-Capitale",
    "sg:tags":[
        "carpenter"
    ],
    "wof:name":"Harpo Sa",
    "wof:placetype":"venue"
},
  "geometry": {"coordinates":[4.3878889084,50.8202323914],"type":"Point"}
}