{
  "type": "Feature",
  "properties": {
    "iso:country":"BE",
    "sg:address":"De Ribaucourtstraat 64",
    "sg:city":"Sint-jans-molenbeek/molenbeek-saint-jean",
    "sg:classifiers":[
        {
            "category":"Fast Food",
            "type":"Food & Drink"
        }
    ],
    "sg:phone":"+32 479 78 05 21",
    "sg:postcode":"1080",
    "sg:province":"Bruxelles-Capitale",
    "sg:tags":[
        "voedingsspeciaalzaken",
        "meeneem",
        "restaurant"
    ],
    "wof:name":"Saidi-snack",
    "wof:placetype":"venue"
},
  "geometry": {"coordinates":[4.3399510384,50.858669281],"type":"Point"}
}