{
  "type": "Feature",
  "properties": {
    "iso:country":"BE",
    "sg:address":"Moorselbaan 201",
    "sg:city":"Aalst",
    "sg:orig_category":"Boissons",
    "sg:phone":"+32 53 70 53 54",
    "sg:postcode":"9300",
    "sg:province":"Oost-Vlaanderen",
    "wof:name":"Wijnhuis Bauwens-gheyssens",
    "wof:placetype":"venue"
},
  "geometry": {"coordinates":[4.0556812286,50.9426612854],"type":"Point"}
}