{
  "type": "Feature",
  "properties": {
    "iso:country":"BE",
    "sg:address":"Avenue Alfred Madoux 143",
    "sg:city":"Bruxelles (woluwe-saint-pierre)",
    "sg:classifiers":[
        {
            "category":"Education",
            "subcategory":"Special Training",
            "type":"Public Place"
        }
    ],
    "sg:phone":"+32 2 779 38 52",
    "sg:postcode":"1150",
    "sg:province":"Bruxelles-Capitale",
    "sg:tags":[
        "professional"
    ],
    "wof:name":"Pa Consult",
    "wof:placetype":"venue"
},
  "geometry": {"coordinates":[4.4513220787,50.830619812],"type":"Point"}
}