{
  "type": "Feature",
  "properties": {
    "addr:full":"Avenue Foch 768 Mons (jemappes) Hainaut 7012",
    "addr:housenumber":"768",
    "addr:postcode":"7012",
    "addr:street":"Avenue Foch",
    "iso:country":"BE",
    "sg:address":"Avenue Foch 768",
    "sg:city":"Mons (jemappes)",
    "sg:classifiers":[
        {
            "category":"Professional",
            "subcategory":"Testing Lab",
            "type":"Services"
        }
    ],
    "sg:phone":"+32 65 82 21 97",
    "sg:postcode":"7012",
    "sg:province":"Hainaut",
    "sg:tags":[
        "chemist"
    ],
    "wof:name":"Orlandi A",
    "wof:placetype":"venue"
},
  "geometry": {"coordinates":[3.8894600868,50.4481964111],"type":"Point"}
}