{
  "type": "Feature",
  "properties": {
    "iso:country":"BE",
    "sg:address":"Neerstraat 65",
    "sg:city":"Waasmunster",
    "sg:classifiers":[
        {
            "category":"Retail",
            "subcategory":"Auto Repair",
            "type":"Services"
        }
    ],
    "sg:phone":"+32 52 46 15 36",
    "sg:postcode":"9250",
    "sg:province":"Oost-Vlaanderen",
    "sg:tags":[
        "garage"
    ],
    "wof:name":"De Rijbel P",
    "wof:placetype":"venue"
},
  "geometry": {"coordinates":[4.0623202324,51.1113433838],"type":"Point"}
}