{
  "type": "Feature",
  "properties": {
    "addr:full":"Weygenstraat 10 B Bertem Vlaams-Brabant 3060",
    "addr:housenumber":"10 b",
    "addr:postcode":"3060",
    "addr:street":"Weygenstraat",
    "iso:country":"BE",
    "sg:address":"Weygenstraat 10 B",
    "sg:city":"Bertem",
    "sg:orig_category":"Artsen and specialisten",
    "sg:phone":"+32 16 48 00 07",
    "sg:postcode":"3060",
    "sg:province":"Vlaams-Brabant",
    "wof:name":"Marie-claire Now\u00c9",
    "wof:placetype":"venue"
},
  "geometry": {"coordinates":[4.6325740814,50.8674888611],"type":"Point"}
}