{
  "type": "Feature",
  "properties": {
    "addr:full":"Roetestraat 3 Duffel Antwerpen 2570",
    "addr:housenumber":"3",
    "addr:postcode":"2570",
    "addr:street":"Roetestraat",
    "iso:country":"BE",
    "sg:address":"Roetestraat 3",
    "sg:city":"Duffel",
    "sg:classifiers":[
        {
            "category":"Farming",
            "subcategory":"Crops",
            "type":"Manufacturing & Wholesale Goods"
        }
    ],
    "sg:phone":"+32 15 31 26 81",
    "sg:postcode":"2570",
    "sg:province":"Antwerpen",
    "sg:tags":[
        "vegetable",
        "fruit",
        "-",
        "grower"
    ],
    "wof:name":"Tuinbouw Nauwelaerts Bvba",
    "wof:placetype":"venue"
},
  "geometry": {"coordinates":[4.4976539612,51.108505249],"type":"Point"}
}