{
  "type": "Feature",
  "properties": {
    "addr:full":"Rue De La Fontaine 8 Bastogne Luxembourg 6600",
    "addr:housenumber":"8",
    "addr:postcode":"6600",
    "addr:street":"Rue De La Fontaine",
    "iso:country":"BE",
    "sg:address":"Rue De La Fontaine 8",
    "sg:city":"Bastogne",
    "sg:orig_category":"Serrures and charni\u00e8res Fab",
    "sg:phone":"+32 61 21 22 61",
    "sg:postcode":"6600",
    "sg:province":"Luxembourg",
    "wof:name":"Euro Locks",
    "wof:placetype":"venue"
},
  "geometry": {"coordinates":[5.72042799,49.9997291565],"type":"Point"}
}