{
  "type": "Feature",
  "properties": {
    "iso:country":"BE",
    "sg:address":"Assesteenweg",
    "sg:city":"Roosdaal (borchtlombeek)",
    "sg:classifiers":[
        {
            "category":"Home & Garden",
            "subcategory":"Building Materials",
            "type":"Retail Goods"
        }
    ],
    "sg:phone":"+32 2 582 27 77",
    "sg:postcode":"1761",
    "sg:province":"Vlaams-Brabant",
    "sg:tags":[
        "house"
    ],
    "wof:name":"Atlanta",
    "wof:placetype":"venue"
},
  "geometry": {"coordinates":[4.136548996,50.848526001],"type":"Point"}
}