{
  "type": "Feature",
  "properties": {
    "addr:full":"Schoolstraat 9 Ranst Antwerpen 2520",
    "addr:housenumber":"9",
    "addr:postcode":"2520",
    "addr:street":"Schoolstraat",
    "iso:country":"BE",
    "sg:address":"Schoolstraat 9",
    "sg:city":"Ranst",
    "sg:classifiers":[
        {
            "category":"Autos & Motor Vehicles",
            "subcategory":"Boat Sales",
            "type":"Retail Goods"
        }
    ],
    "sg:phone":"+32 3 475 06 67",
    "sg:postcode":"2520",
    "sg:province":"Antwerpen",
    "sg:tags":[
        "balloon"
    ],
    "wof:name":"De Zoete Zonde",
    "wof:placetype":"venue"
},
  "geometry": {"coordinates":[4.5609512329,51.1908302307],"type":"Point"}
}