{
  "type": "Feature",
  "properties": {
    "addr:full":"Domein Bokrijk Genk Limburg 3600",
    "addr:postcode":"3600",
    "addr:street":"Limburg",
    "iso:country":"BE",
    "sg:address":"Domein Bokrijk",
    "sg:city":"Genk",
    "sg:orig_category":"RESTAURANTS: LIVRAISON \u00c0 DOMICILE. SALLES DE CONF\u00c9RENCES AND DE R\u00c9CEPTIONS. ACTIVIT\u00c9S R\u00c9CR\u00c9ATIVES DI",
    "sg:phone":"+32 11 26 54 08",
    "sg:postcode":"3600",
    "sg:province":"Limburg",
    "wof:name":"Bokland",
    "wof:placetype":"venue"
},
  "geometry": {"coordinates":[5.4087300301,50.9542160034],"type":"Point"}
}