{
  "type": "Feature",
  "properties": {
    "addr:full":"Breda Straat 121-123 Antwerpen Antwerpen 2060",
    "addr:postcode":"121-123;2060",
    "addr:street":"Breda Straat",
    "iso:country":"BE",
    "sg:address":"Breda Straat 121-123",
    "sg:city":"Antwerpen",
    "sg:classifiers":[
        {
            "category":"Banks & Credit Unions",
            "subcategory":"Investment Brokerage",
            "type":"Services"
        }
    ],
    "sg:phone":"+32 3 206 01 80",
    "sg:postcode":"2060",
    "sg:province":"Antwerpen",
    "sg:tags":[
        "sea",
        "transport",
        "air"
    ],
    "wof:name":"Intership Europe Nv",
    "wof:placetype":"venue"
},
  "geometry": {"coordinates":[4.4241600037,51.2359580994],"type":"Point"}
}