{
  "type": "Feature",
  "properties": {
    "addr:full":"Groendreef 34 Gent Oost-Vlaanderen 9000",
    "addr:housenumber":"34",
    "addr:postcode":"9000",
    "addr:street":"Groendreef;Oost-Vlaanderen",
    "iso:country":"BE",
    "sg:address":"Groendreef 34",
    "sg:city":"Gent",
    "sg:orig_category":"Vitrage. Mat\u00e9riaux de construction Installation de serres, double vitrage and fen\u00eatres",
    "sg:phone":"+32 9 226 20 32",
    "sg:postcode":"9000",
    "sg:province":"Oost-Vlaanderen",
    "wof:name":"Coppens A En Zoon",
    "wof:placetype":"venue"
},
  "geometry": {"coordinates":[3.7037220001,51.061252594],"type":"Point"}
}