{
  "type": "Feature",
  "properties": {
    "addr:full":"Tiensesteenweg 261 Box 4 Bierbeek (korbeek-lo) Vlaams-Brabant 3360",
    "addr:housenumber":"261;4",
    "addr:postcode":"3360",
    "addr:street":"Tiensesteenweg;Box",
    "iso:country":"BE",
    "sg:address":"Tiensesteenweg 261 Box 4",
    "sg:city":"Bierbeek (korbeek-lo)",
    "sg:classifiers":[
        {
            "category":"Home & Garden",
            "subcategory":"Home Furnishings",
            "type":"Retail Goods"
        }
    ],
    "sg:phone":"+32 16 46 48 66",
    "sg:postcode":"3360",
    "sg:province":"Vlaams-Brabant",
    "sg:tags":[
        "-",
        "bed",
        "mattress"
    ],
    "wof:name":"G & C Slaapcomfort Bvba",
    "wof:placetype":"venue"
},
  "geometry": {"coordinates":[4.7903819084,50.8561706543],"type":"Point"}
}