{
  "type": "Feature",
  "properties": {
    "addr:full":"Schonegfem 116 Erpe-mere Oost-Vlaanderen 9420",
    "addr:housenumber":"116",
    "addr:postcode":"9420",
    "iso:country":"BE",
    "sg:address":"Schonegfem 116",
    "sg:city":"Erpe-mere",
    "sg:classifiers":[
        {
            "category":"Arena",
            "subcategory":"Sports Club",
            "type":"Entertainment"
        }
    ],
    "sg:phone":"+32 53 80 91 46",
    "sg:postcode":"9420",
    "sg:province":"Oost-Vlaanderen",
    "sg:tags":[
        "de"
    ],
    "wof:name":"Mawashi",
    "wof:placetype":"venue"
},
  "geometry": {"coordinates":[3.9825189114,50.9310531616],"type":"Point"}
}