{
  "type": "Feature",
  "properties": {
    "addr:full":"Rue De La Coop\u00c9ration 149 Saint-nicolas Li\u00e8ge 4420",
    "addr:housenumber":"149",
    "addr:postcode":"4420",
    "addr:street":"Rue De La Coope\u0301Ration;Saint-Nicolas Lie\u0300Ge",
    "iso:country":"BE",
    "sg:address":"Rue De La Coop\u00c9ration 149",
    "sg:city":"Saint-nicolas",
    "sg:classifiers":[
        {
            "category":"Cafe",
            "type":"Food & Drink"
        }
    ],
    "sg:phone":"+32 4 224 18 45",
    "sg:postcode":"4420",
    "sg:province":"Li\u00e8ge",
    "sg:tags":[
        "caf\u00e9s"
    ],
    "wof:name":"Billard D'istanbul",
    "wof:placetype":"venue"
},
  "geometry": {"coordinates":[5.536397934,50.6394042969],"type":"Point"}
}