{
  "type": "Feature",
  "properties": {
    "iso:country":"BE",
    "sg:address":"Polderstraat 11",
    "sg:city":"Balen (olmen)",
    "sg:classifiers":[
        {
            "category":"Shopping",
            "subcategory":"Clothing, Apparel, & Fashions",
            "type":"Retail Goods"
        }
    ],
    "sg:phone":"+32 14 30 00 59",
    "sg:postcode":"2491",
    "sg:province":"Antwerpen",
    "sg:tags":[
        "lady",
        "clothing",
        "-"
    ],
    "wof:name":"Bylemans",
    "wof:placetype":"venue"
},
  "geometry": {"coordinates":[5.1510548592,51.1413841248],"type":"Point"}
}