{
  "type": "Feature",
  "properties": {
    "iso:country":"BE",
    "sg:address":"Groteweg 25",
    "sg:city":"Geraardsbergen",
    "sg:orig_category":"Cr\u00e8ches and garderies d'enfants",
    "sg:phone":"+32 54 42 19 38",
    "sg:postcode":"9500",
    "sg:province":"Oost-Vlaanderen",
    "wof:name":"Kribbe Zonnestraal",
    "wof:placetype":"venue"
},
  "geometry": {"coordinates":[3.8708300591,50.7675628662],"type":"Point"}
}