{
  "type": "Feature",
  "properties": {
    "addr:full":"Schalienstraat 30 Antwerpen Antwerpen 2000",
    "addr:housenumber":"30",
    "addr:postcode":"2000",
    "addr:street":"Schalienstraat",
    "iso:country":"BE",
    "sg:address":"Schalienstraat 30",
    "sg:city":"Antwerpen",
    "sg:classifiers":[
        {
            "category":"Wholesale",
            "subcategory":"Seafood",
            "type":"Manufacturing & Wholesale Goods"
        }
    ],
    "sg:phone":"+32 3 248 45 93",
    "sg:postcode":"2000",
    "sg:province":"Antwerpen",
    "sg:tags":[
        "whol",
        "fish",
        "-",
        "shellfish"
    ],
    "wof:name":"West Star",
    "wof:placetype":"venue"
},
  "geometry": {"coordinates":[4.3866138458,51.2082862854],"type":"Point"}
}