{
  "type": "Feature",
  "properties": {
    "addr:full":"Boulevard De L'humanite 415 Bruxelles Bruxelles-Capitale 1190",
    "addr:housenumber":"415",
    "addr:postcode":"1190",
    "addr:street":"Boulevard De L'Humanite",
    "iso:country":"BE",
    "sg:address":"Boulevard De L'humanite 415",
    "sg:city":"Bruxelles",
    "sg:classifiers":[
        {
            "category":"Banks & Credit Unions",
            "subcategory":"Financial Services",
            "type":"Services"
        }
    ],
    "sg:phone":"+32 2 332 32 25",
    "sg:postcode":"1190",
    "sg:province":"Bruxelles-Capitale",
    "sg:tags":[
        "detection",
        "ultrasonic",
        "leakage",
        "system"
    ],
    "wof:name":"Sdt International S.a.",
    "wof:placetype":"venue"
},
  "geometry": {"coordinates":[4.3150248528,50.820728302],"type":"Point"}
}