{
  "type": "Feature",
  "properties": {
    "addr:full":"Suikerrui 19 Antwerpen Antwerpen 2000",
    "addr:housenumber":"19",
    "addr:postcode":"2000",
    "addr:street":"Suikerrui",
    "iso:country":"BE",
    "sg:address":"Suikerrui 19",
    "sg:city":"Antwerpen",
    "sg:orig_category":"Musea and historische gebouwen",
    "sg:phone":"+32 3 220 86 00",
    "sg:postcode":"2000",
    "sg:province":"Antwerpen",
    "wof:name":"Etnografisch Museum",
    "wof:placetype":"venue"
},
  "geometry": {"coordinates":[4.398296833,51.2210922241],"type":"Point"}
}