{
  "type": "Feature",
  "properties": {
    "iso:country":"BE",
    "sg:address":"Rue Des Croisiers 29",
    "sg:city":"Namur",
    "sg:orig_category":"Apotheken",
    "sg:phone":"+32 81 22 68 69",
    "sg:postcode":"5000",
    "sg:province":"Namur",
    "wof:name":"Multipharma",
    "wof:placetype":"venue"
},
  "geometry": {"coordinates":[4.8642020226,50.4674682617],"type":"Point"}
}