{
  "type": "Feature",
  "properties": {
    "addr:full":"Nederholbeekstraat 116 Maarkedal Oost-Vlaanderen 9680",
    "addr:housenumber":"116",
    "addr:postcode":"9680",
    "addr:street":"Nederholbeekstraat",
    "iso:country":"BE",
    "sg:address":"Nederholbeekstraat 116",
    "sg:city":"Maarkedal",
    "sg:orig_category":"Slagers",
    "sg:phone":"+32 55 31 19 39",
    "sg:postcode":"9680",
    "sg:province":"Oost-Vlaanderen",
    "wof:name":"Robert Vanbutsele",
    "wof:placetype":"venue"
},
  "geometry": {"coordinates":[3.6216859818,50.8055839539],"type":"Point"}
}