{
  "type": "Feature",
  "properties": {
    "iso:country":"BE",
    "sg:address":"Watersportlaan 9",
    "sg:city":"Nieuwpoort",
    "sg:classifiers":[
        {
            "category":"Metro Station",
            "type":"Transportation"
        }
    ],
    "sg:phone":"+32 58 24 39 36",
    "sg:postcode":"8620",
    "sg:province":"West-Vlaanderen",
    "sg:tags":[
        "repair",
        "ship",
        "mainten",
        "-"
    ],
    "wof:name":"Ship Support Bvba",
    "wof:placetype":"venue"
},
  "geometry": {"coordinates":[2.7460329533,51.1401481628],"type":"Point"}
}