{
  "type": "Feature",
  "properties": {
    "iso:country":"BE",
    "sg:address":"Weg Naar As 93",
    "sg:city":"Genk",
    "sg:classifiers":[
        {
            "category":"Arena",
            "subcategory":"Sports Club",
            "type":"Entertainment"
        }
    ],
    "sg:phone":"+32 89 35 04 76",
    "sg:postcode":"3600",
    "sg:province":"Limburg",
    "wof:name":"Riley Inn (the)",
    "wof:placetype":"venue"
},
  "geometry": {"coordinates":[5.5340800285,50.982219696],"type":"Point"}
}