{
  "type": "Feature",
  "properties": {
    "addr:full":"Laan Op Heusden 59b2 Beringen Limburg 3582",
    "addr:housenumber":"59b2",
    "addr:postcode":"3582",
    "addr:street":"Laan Op Heusden",
    "iso:country":"BE",
    "sg:address":"Laan Op Heusden 59b2",
    "sg:city":"Beringen",
    "sg:orig_category":"Pain, p\u00e2tisseries and confiseries",
    "sg:phone":"+32 11 42 50 70",
    "sg:postcode":"3582",
    "sg:province":"Limburg",
    "wof:name":"Quintens Veerle & Sara",
    "wof:placetype":"venue"
},
  "geometry": {"coordinates":[5.2708749771,51.0595359802],"type":"Point"}
}