{
  "type": "Feature",
  "properties": {
    "addr:full":"Dorpsstraat 13 Beveren Oost-Vlaanderen 9130",
    "addr:housenumber":"13",
    "addr:postcode":"9130",
    "addr:street":"Dorpsstraat",
    "iso:country":"BE",
    "sg:address":"Dorpsstraat 13",
    "sg:city":"Beveren",
    "sg:classifiers":[
        {
            "category":"Restaurant",
            "type":"Food & Drink"
        }
    ],
    "sg:phone":"+32 3 773 45 68",
    "sg:postcode":"9130",
    "sg:province":"Oost-Vlaanderen",
    "wof:name":"Het Dorp",
    "wof:placetype":"venue"
},
  "geometry": {"coordinates":[4.1750750542,51.2897491455],"type":"Point"}
}