{
  "type": "Feature",
  "properties": {
    "addr:full":"Avenue Franchet D'esperey 14 Dinant Namur 5500",
    "addr:housenumber":"14",
    "addr:postcode":"5500",
    "addr:street":"Avenue Franchet D'Esperey",
    "iso:country":"BE",
    "sg:address":"Avenue Franchet D'esperey 14",
    "sg:city":"Dinant",
    "sg:classifiers":[
        {
            "category":"Professional",
            "subcategory":"Lawyer & Legal Services",
            "type":"Services"
        }
    ],
    "sg:phone":"+32 82 22 33 30",
    "sg:postcode":"5500",
    "sg:province":"Namur",
    "wof:name":"Simon Anne",
    "wof:placetype":"venue"
},
  "geometry": {"coordinates":[4.9079170227,50.2621498108],"type":"Point"}
}