{
  "type": "Feature",
  "properties": {
    "addr:full":"Rue Ris-del-val 6 Erezee Luxembourg 6997",
    "addr:housenumber":"6",
    "addr:postcode":"6997",
    "addr:street":"Rue Ris-Del-Val",
    "iso:country":"BE",
    "sg:address":"Rue Ris-del-val 6",
    "sg:city":"Erezee",
    "sg:classifiers":[
        {
            "category":"Fast Food",
            "type":"Food & Drink"
        }
    ],
    "sg:phone":"+32 86 47 70 70",
    "sg:postcode":"6997",
    "sg:province":"Luxembourg",
    "sg:tags":[
        "de",
        "restaurant",
        "organisation",
        "\u00e0",
        "catering",
        "emporter",
        "f\u00eates"
    ],
    "wof:name":"Le Comme Chez Soy",
    "wof:placetype":"venue"
},
  "geometry": {"coordinates":[5.5106158257,50.286819458],"type":"Point"}
}