{
  "type": "Feature",
  "properties": {
    "addr:full":"Ommegangoost 20 Staden West-Vlaanderen 8840",
    "addr:housenumber":"20",
    "addr:postcode":"8840",
    "addr:street":"Ommegangoost",
    "iso:country":"BE",
    "sg:address":"Ommegangoost 20",
    "sg:city":"Staden",
    "sg:orig_category":"Herstelling horloges and juwelen Juwelen and horloges",
    "sg:phone":"+32 51 77 07 61",
    "sg:postcode":"8840",
    "sg:province":"West-Vlaanderen",
    "wof:name":"Westcomputer",
    "wof:placetype":"venue"
},
  "geometry": {"coordinates":[3.0157179832,50.93151474],"type":"Point"}
}