{
  "type": "Feature",
  "properties": {
    "iso:country":"BE",
    "sg:address":"Kortrijkstraat 144",
    "sg:city":"Tielt (groot)",
    "sg:orig_category":"Textiel",
    "sg:phone":"+32 51 40 43 89",
    "sg:postcode":"8700",
    "sg:province":"West-Vlaanderen",
    "wof:name":"Huis Loncke",
    "wof:placetype":"venue"
},
  "geometry": {"coordinates":[3.3257949352,50.9948196411],"type":"Point"}
}