{
  "type": "Feature",
  "properties": {
    "iso:country":"BE",
    "sg:address":"Aven Ackers 11",
    "sg:city":"Beveren (verrebroek)",
    "sg:orig_category":"Pre-press",
    "sg:phone":"+32 3 735 02 61",
    "sg:postcode":"9130",
    "sg:province":"Oost-Vlaanderen",
    "wof:name":"Media Express Nv",
    "wof:placetype":"venue"
},
  "geometry": {"coordinates":[4.1917800903,51.25207901],"type":"Point"}
}