{
  "type": "Feature",
  "properties": {
    "iso:country":"BE",
    "sg:address":"Rue Cl\u00c9mentine 2",
    "sg:city":"Elsene/ixelles",
    "sg:orig_category":"R\u00e9paration and restauration de meubles",
    "sg:phone":"+32 2 646 72 31",
    "sg:postcode":"1050",
    "sg:province":"Bruxelles-Capitale",
    "wof:name":"Kindermans",
    "wof:placetype":"venue"
},
  "geometry": {"coordinates":[4.3747029305,50.8313865662],"type":"Point"}
}