{
  "type": "Feature",
  "properties": {
    "iso:country":"BE",
    "sg:address":"Rue A Fauchille 17",
    "sg:city":"Sint-pieters-woluwe/woluwe-sai",
    "sg:orig_category":"Mat\u00e9riel scientifique and technique Fab",
    "sg:phone":"+32 2 736 80 00",
    "sg:postcode":"1150",
    "sg:province":"Bruxelles-Capitale",
    "wof:name":"Forlab Belgium",
    "wof:placetype":"venue"
},
  "geometry": {"coordinates":[4.4107370377,50.8354225159],"type":"Point"}
}