{
  "type": "Feature",
  "properties": {
    "iso:country":"BE",
    "sg:address":"Rue De La Poterie 37",
    "sg:city":"Mons",
    "sg:orig_category":"Architectes",
    "sg:phone":"+32 65 31 94 29",
    "sg:postcode":"7000",
    "sg:province":"Hainaut",
    "wof:name":"Lucette Fran\u00c7ois",
    "wof:placetype":"venue"
},
  "geometry": {"coordinates":[3.9499499798,50.4531593323],"type":"Point"}
}