{
  "type": "Feature",
  "properties": {
    "iso:country":"BE",
    "sg:address":"Rue De La Pastorale 26",
    "sg:city":"Bruxelles (molenbeek-saint-jean)",
    "sg:classifiers":[
        {
            "category":"Professional",
            "subcategory":"Testing Lab",
            "type":"Services"
        }
    ],
    "sg:phone":"+32 2 411 48 28",
    "sg:postcode":"1080",
    "sg:province":"Bruxelles-Capitale",
    "sg:tags":[
        "laboratory",
        "-"
    ],
    "wof:name":"S M B",
    "wof:placetype":"venue"
},
  "geometry": {"coordinates":[4.3029541969,50.8482818604],"type":"Point"}
}