{
  "type": "Feature",
  "properties": {
    "iso:country":"BE",
    "sg:address":"Oude Baan 57",
    "sg:city":"Maasmechelen (eisden)",
    "sg:classifiers":[
        {
            "category":"Professional",
            "subcategory":"Art Services",
            "type":"Services"
        }
    ],
    "sg:phone":"+32 89 76 13 44",
    "sg:postcode":"3630",
    "sg:province":"Limburg",
    "sg:tags":[
        "photographer"
    ],
    "wof:name":"Foto Leon",
    "wof:placetype":"venue"
},
  "geometry": {"coordinates":[5.6937088966,50.9861297607],"type":"Point"}
}