{
  "type": "Feature",
  "properties": {
    "addr:full":"Chauss\u00c9e De Wavre 1486 Oudergem/auderghem Bruxelles-Capitale 1160",
    "addr:postcode":"1486;1160",
    "addr:street":"Chausse\u0301E De Wavre",
    "iso:country":"BE",
    "sg:address":"Chauss\u00c9e De Wavre 1486",
    "sg:city":"Oudergem/auderghem",
    "sg:orig_category":"Catering and organisation de f\u00eates. Alimentation sp\u00e9cialis\u00e9e. Restaurants",
    "sg:phone":"+32 2 675 08 57",
    "sg:postcode":"1160",
    "sg:province":"Bruxelles-Capitale",
    "wof:name":"Snack-bar Gargantua",
    "wof:placetype":"venue"
},
  "geometry": {"coordinates":[4.4192318916,50.8180351257],"type":"Point"}
}