{
  "type": "Feature",
  "properties": {
    "iso:country":"BE",
    "sg:address":"Av. R. Vandendriessche 5",
    "sg:city":"Sint-pieters-woluwe/woluwe-saint-pierre",
    "sg:orig_category":"Agences de relations publiques. Bureaux d'\u00e9tudes de march\u00e9",
    "sg:phone":"+32 2 771 14 34",
    "sg:postcode":"1150",
    "sg:province":"Bruxelles-Capitale",
    "wof:name":"P R Consult/p.r. Consult",
    "wof:placetype":"venue"
},
  "geometry": {"coordinates":[4.4143271446,50.8349914551],"type":"Point"}
}