{
  "type": "Feature",
  "properties": {
    "iso:country":"BE",
    "sg:address":"Hemelakkers 40",
    "sg:city":"Brasschaat",
    "sg:classifiers":[
        {
            "category":"Government",
            "subcategory":"Police Station",
            "type":"Public Place"
        }
    ],
    "sg:phone":"+32 3 652 93 11",
    "sg:postcode":"2930",
    "sg:province":"Antwerpen",
    "sg:tags":[
        "gendarmerie"
    ],
    "wof:name":"Federale Politie/police F\u00c9d\u00c9rale",
    "wof:placetype":"venue"
},
  "geometry": {"coordinates":[4.484869957,51.2841415405],"type":"Point"}
}