{
  "type": "Feature",
  "properties": {
    "addr:full":"Barri\u00e8re Hinck 2 Sainte-ode (amberloup) Luxembourg 6680",
    "addr:housenumber":"2",
    "addr:postcode":"6680",
    "addr:street":"Hinck;Amberloup",
    "iso:country":"BE",
    "sg:address":"Barri\u00e8re Hinck 2",
    "sg:city":"Sainte-ode (amberloup)",
    "sg:classifiers":[
        {
            "category":"Retail",
            "subcategory":"Auto Repair",
            "type":"Services"
        }
    ],
    "sg:phone":"+32 61 68 86 45",
    "sg:postcode":"6680",
    "sg:province":"Luxembourg",
    "sg:tags":[
        "breakdown",
        "automobile",
        "-",
        "recovery"
    ],
    "wof:name":"Bastien James",
    "wof:placetype":"venue"
},
  "geometry": {"coordinates":[5.5657072067,50.0461959839],"type":"Point"}
}