{
  "type": "Feature",
  "properties": {
    "addr:full":"Bruul 82-88 Mechelen Antwerpen 2800",
    "addr:housenumber":"82-88",
    "addr:postcode":"2800",
    "addr:street":"Bruul",
    "iso:country":"BE",
    "sg:address":"Bruul 82-88",
    "sg:city":"Mechelen",
    "sg:classifiers":[
        {
            "category":"Utilities",
            "subcategory":"Mobile Phone",
            "type":"Services"
        }
    ],
    "sg:phone":"+32 15 29 40 60",
    "sg:postcode":"2800",
    "sg:province":"Antwerpen",
    "sg:tags":[
        "-",
        "gsm"
    ],
    "wof:name":"Teleboetiek Belgacom",
    "wof:placetype":"venue"
},
  "geometry": {"coordinates":[4.4814658165,51.0250167847],"type":"Point"}
}