{
  "type": "Feature",
  "properties": {
    "iso:country":"BE",
    "sg:address":"Beselarestraat 1",
    "sg:city":"Moorslede (dadizele)",
    "sg:classifiers":[
        {
            "category":"Bars & Pubs",
            "type":"Food & Drink"
        }
    ],
    "sg:phone":"+32 56 50 20 66",
    "sg:postcode":"8890",
    "sg:province":"West-Vlaanderen",
    "wof:name":"De Pompeschitter",
    "wof:placetype":"venue"
},
  "geometry": {"coordinates":[3.0939500332,50.8510055542],"type":"Point"}
}