{
  "type": "Feature",
  "properties": {
    "iso:country":"BE",
    "sg:address":"Aalterveld 53",
    "sg:city":"Aalter",
    "sg:orig_category":"Dierenartsen",
    "sg:phone":"+32 9 374 40 04",
    "sg:postcode":"9880",
    "sg:province":"Oost-Vlaanderen",
    "wof:name":"Guido Houpe",
    "wof:placetype":"venue"
},
  "geometry": {"coordinates":[3.4582400322,51.0703315735],"type":"Point"}
}