{
  "type": "Feature",
  "properties": {
    "addr:full":"Steenweg Op Jette 518 Jette/jette Bruxelles-Capitale 1090",
    "addr:housenumber":"518",
    "addr:postcode":"1090",
    "addr:street":"Steenweg Op Jette",
    "iso:country":"BE",
    "sg:address":"Steenweg Op Jette 518",
    "sg:city":"Jette/jette",
    "sg:orig_category":"Herstellingen and onderhoud van auto's",
    "sg:phone":"+32 2 425 36 54",
    "sg:postcode":"1090",
    "sg:province":"Bruxelles-Capitale",
    "wof:name":"Garage Frans Lahaye",
    "wof:placetype":"venue"
},
  "geometry": {"coordinates":[4.3272547722,50.8697052002],"type":"Point"}
}