{
  "type": "Feature",
  "properties": {
    "addr:full":"Place De Jamblinne De Meux 33 Bruxelles (schaerbeek) Bruxelles-Capitale 1030",
    "addr:housenumber":"33",
    "addr:postcode":"1030",
    "addr:street":"Place De Jamblinne De Meux",
    "iso:country":"BE",
    "sg:address":"Place De Jamblinne De Meux 33",
    "sg:city":"Bruxelles (schaerbeek)",
    "sg:orig_category":"Newspapers, magazines, periodicals - Publishers",
    "sg:phone":"+32 2 739 10 27",
    "sg:postcode":"1030",
    "sg:province":"Bruxelles-Capitale",
    "wof:name":"Uz-gezondheidsbrief-lettre De La Sante",
    "wof:placetype":"venue"
},
  "geometry": {"coordinates":[4.3941869736,50.8475570679],"type":"Point"}
}