{
  "type": "Feature",
  "properties": {
    "iso:country":"BE",
    "sg:address":"Herebaan Oost 3 Box 1",
    "sg:city":"Houthalen-helchteren (houthalen)",
    "sg:classifiers":[
        {
            "category":"Professional",
            "subcategory":"Lawyer & Legal Services",
            "type":"Services"
        }
    ],
    "sg:phone":"+32 11 52 40 90",
    "sg:postcode":"3530",
    "sg:province":"Limburg",
    "wof:name":"Van Reusel Lut",
    "wof:placetype":"venue"
},
  "geometry": {"coordinates":[5.3975439072,51.0295028687],"type":"Point"}
}