{
  "type": "Feature",
  "properties": {
    "iso:country":"BE",
    "sg:address":"Stationsstraat 165 Box 1",
    "sg:city":"Essen",
    "sg:classifiers":[
        {
            "category":"Communications",
            "type":"Services"
        }
    ],
    "sg:phone":"+32 3 235 44 56",
    "sg:postcode":"2910",
    "sg:province":"Antwerpen",
    "sg:tags":[
        "translator"
    ],
    "wof:name":"Ad Polonica",
    "wof:placetype":"venue"
},
  "geometry": {"coordinates":[4.4576010704,51.4638748169],"type":"Point"}
}