{
  "type": "Feature",
  "properties": {
    "iso:country":"BE",
    "sg:address":"Ancien-chemin-d'halma 30",
    "sg:city":"Wellin",
    "sg:classifiers":[
        {
            "category":"Health Services",
            "subcategory":"Health Practitioner",
            "type":"Services"
        }
    ],
    "sg:phone":"+32 497 41 52 23",
    "sg:postcode":"6920",
    "sg:province":"Luxembourg",
    "sg:tags":[
        "physiotherapist"
    ],
    "wof:name":"Bourgeois Dani\u00e8le",
    "wof:placetype":"venue"
},
  "geometry": {"coordinates":[5.1150918007,50.081363678],"type":"Point"}
}