{
  "type": "Feature",
  "properties": {
    "addr:full":"St Amandsstraat 34 Grimbergen Vlaams-Brabant 1853",
    "addr:housenumber":"34",
    "addr:postcode":"1853",
    "addr:street":"St Amandsstraat",
    "iso:country":"BE",
    "sg:address":"St Amandsstraat 34",
    "sg:city":"Grimbergen",
    "sg:orig_category":"Boucheries",
    "sg:phone":"+32 2 267 10 79",
    "sg:postcode":"1853",
    "sg:province":"Vlaams-Brabant",
    "wof:name":"Piet Vertonghen",
    "wof:placetype":"venue"
},
  "geometry": {"coordinates":[4.3577060699,50.9089584351],"type":"Point"}
}