{
  "type": "Feature",
  "properties": {
    "iso:country":"BE",
    "sg:address":"Mont 104ba",
    "sg:city":"Ellezelles",
    "sg:orig_category":"Slagers",
    "sg:phone":"+32 68 54 22 81",
    "sg:postcode":"7890",
    "sg:province":"Hainaut",
    "wof:name":"Jacques Bourlez",
    "wof:placetype":"venue"
},
  "geometry": {"coordinates":[3.6760179996,50.7546844482],"type":"Point"}
}