{
  "type": "Feature",
  "properties": {
    "addr:full":"A. Goossensstraat 23 Huldenberg Vlaams-Brabant 3040",
    "addr:housenumber":"23",
    "addr:postcode":"3040",
    "addr:street":"A. Goossensstraat",
    "iso:country":"BE",
    "sg:address":"A. Goossensstraat 23",
    "sg:city":"Huldenberg",
    "sg:classifiers":[
        {
            "category":"Building & Trades",
            "subcategory":"Electrical",
            "type":"Services"
        }
    ],
    "sg:phone":"+32 2 687 24 69",
    "sg:postcode":"3040",
    "sg:province":"Vlaams-Brabant",
    "sg:tags":[
        "electric",
        "-",
        "housewiring",
        "contractor"
    ],
    "wof:name":"Vlek",
    "wof:placetype":"venue"
},
  "geometry": {"coordinates":[4.5849299431,50.7919387817],"type":"Point"}
}