{
  "type": "Feature",
  "properties": {
    "iso:country":"BE",
    "sg:address":"Volksverheffingstraat 70",
    "sg:city":"Aalst",
    "sg:orig_category":"Kapsalons",
    "sg:phone":"+32 53 70 14 37",
    "sg:postcode":"9300",
    "sg:province":"Oost-Vlaanderen",
    "wof:name":"Coiffure Benny",
    "wof:placetype":"venue"
},
  "geometry": {"coordinates":[4.0229439735,50.941493988],"type":"Point"}
}