{
  "type": "Feature",
  "properties": {
    "addr:full":"Bethani\u00cbnlei 91 Zoersel Antwerpen 2980",
    "addr:housenumber":"91",
    "addr:postcode":"2980",
    "addr:street":"Bethanie\u0308Nlei",
    "iso:country":"BE",
    "sg:address":"Bethani\u00cbnlei 91",
    "sg:city":"Zoersel",
    "sg:orig_category":"Antiquit\u00e9s",
    "sg:phone":"+32 3 384 34 49",
    "sg:postcode":"2980",
    "sg:province":"Antwerpen",
    "wof:name":"Blank Decor Max",
    "wof:placetype":"venue"
},
  "geometry": {"coordinates":[4.6367759705,51.2722320557],"type":"Point"}
}