{
  "type": "Feature",
  "properties": {
    "iso:country":"BE",
    "sg:address":"Waterloose Steenweg 234",
    "sg:city":"Sint-genesius-rode/rhode-saint-gen\u00c8se",
    "sg:orig_category":"Reisbureaus",
    "sg:phone":"+32 2 358 35 03",
    "sg:postcode":"1640",
    "sg:province":"Vlaams-Brabant",
    "wof:name":"Cuvelier Cobeltour",
    "wof:placetype":"venue"
},
  "geometry": {"coordinates":[4.3944239616,50.7424888611],"type":"Point"}
}