{
  "type": "Feature",
  "properties": {
    "iso:country":"BE",
    "sg:address":"Rummenweg 9",
    "sg:city":"Sint-truiden",
    "sg:classifiers":[
        {
            "category":"Professional",
            "subcategory":"Lawyer & Legal Services",
            "type":"Services"
        }
    ],
    "sg:phone":"+32 11 78 56 41",
    "sg:postcode":"3800",
    "sg:province":"Limburg",
    "wof:name":"Pokorny Mietta",
    "wof:placetype":"venue"
},
  "geometry": {"coordinates":[5.1828780174,50.8227844238],"type":"Point"}
}