{
  "type": "Feature",
  "properties": {
    "iso:country":"BE",
    "sg:address":"Rue Saint-sang 79",
    "sg:city":"Sambreville",
    "sg:orig_category":"Herstellingen and onderhoud van auto's Voertuigen",
    "sg:phone":"+32 71 77 32 26",
    "sg:postcode":"5060",
    "sg:province":"Namur",
    "wof:name":"Garage Mazuin Fr\u00c8res",
    "wof:placetype":"venue"
},
  "geometry": {"coordinates":[4.6306052208,50.4422531128],"type":"Point"}
}