{
  "type": "Feature",
  "properties": {
    "addr:full":"Arthur Vanderpoortenlaan 6 Lier Antwerpen 2500",
    "addr:housenumber":"6",
    "addr:postcode":"2500",
    "addr:street":"Arthur Vanderpoortenlaan",
    "iso:country":"BE",
    "sg:address":"Arthur Vanderpoortenlaan 6",
    "sg:city":"Lier",
    "sg:orig_category":"Charpentes and couvertures",
    "sg:phone":"+32 3 482 29 41",
    "sg:postcode":"2500",
    "sg:province":"Antwerpen",
    "wof:name":"Wuyts Dakwerken",
    "wof:placetype":"venue"
},
  "geometry": {"coordinates":[4.5771288872,51.129070282],"type":"Point"}
}