{
  "type": "Feature",
  "properties": {
    "iso:country":"BE",
    "sg:address":"Rue De Booze 92b",
    "sg:city":"Bl\u00e9gny (trembleur)",
    "sg:classifiers":[
        {
            "category":"Autos & Motor Vehicles",
            "subcategory":"Motorcycle Sales",
            "type":"Retail Goods"
        }
    ],
    "sg:phone":"+32 4 387 48 89",
    "sg:postcode":"4670",
    "sg:province":"Li\u00e8ge",
    "sg:tags":[
        "motorbike"
    ],
    "wof:name":"Yanauto-moto",
    "wof:placetype":"venue"
},
  "geometry": {"coordinates":[5.7072958946,50.6710205078],"type":"Point"}
}