{
  "type": "Feature",
  "properties": {
    "iso:country":"BE",
    "sg:address":"Boulevard Lambermont 140",
    "sg:city":"Brussel/bruxelles",
    "sg:orig_category":"Magasins sp\u00e9cialis\u00e9s",
    "sg:phone":"+32 2 215 58 00",
    "sg:postcode":"1030",
    "sg:province":"Bruxelles-Capitale",
    "wof:name":"Camaflex",
    "wof:placetype":"venue"
},
  "geometry": {"coordinates":[4.3807039261,50.8721046448],"type":"Point"}
}