{
  "type": "Feature",
  "properties": {
    "iso:country":"BE",
    "sg:address":"Chauss\u00c9e De Gand 1190",
    "sg:city":"Sint-agatha-berchem/berchem-sa",
    "sg:orig_category":"Opticiens",
    "sg:phone":"+32 2 465 67 78",
    "sg:postcode":"1082",
    "sg:province":"Bruxelles-Capitale",
    "wof:name":"Pol Goffinet",
    "wof:placetype":"venue"
},
  "geometry": {"coordinates":[4.2961931229,50.8652038574],"type":"Point"}
}