{
  "type": "Feature",
  "properties": {
    "addr:full":"Willekensmolenstraat 22 Box 2 Hasselt Limburg 3500",
    "addr:housenumber":"22;2",
    "addr:postcode":"3500",
    "addr:street":"Willekensmolenstraat;Box",
    "iso:country":"BE",
    "sg:address":"Willekensmolenstraat 22 Box 2",
    "sg:city":"Hasselt",
    "sg:classifiers":[
        {
            "category":"Building & Trades",
            "subcategory":"Plumbing",
            "type":"Services"
        }
    ],
    "sg:phone":"+32 11 23 18 03",
    "sg:postcode":"3500",
    "sg:province":"Limburg",
    "sg:tags":[
        "repair",
        "mainten",
        "-",
        "central",
        "heating"
    ],
    "wof:name":"Bergmans T",
    "wof:placetype":"venue"
},
  "geometry": {"coordinates":[5.3462529182,50.9313240051],"type":"Point"}
}