{
  "type": "Feature",
  "properties": {
    "addr:full":"Rue Du Beguinage 16 Wavre Brabant Wallon 1300",
    "addr:housenumber":"16;1300",
    "addr:street":"Rue Du Beguinage",
    "iso:country":"BE",
    "sg:address":"Rue Du Beguinage 16",
    "sg:city":"Wavre",
    "sg:orig_category":"Evaluation and estimation de biens immobiliers",
    "sg:phone":"+32 10 24 46 44",
    "sg:postcode":"1300",
    "sg:province":"Brabant Wallon",
    "wof:name":"Alain Coppe",
    "wof:placetype":"venue"
},
  "geometry": {"coordinates":[4.60912323,50.7172622681],"type":"Point"}
}