{
  "type": "Feature",
  "properties": {
    "iso:country":"BE",
    "sg:address":"Kapitteldreef 75",
    "sg:city":"Sint-martens-latem",
    "sg:orig_category":"Artsen and specialisten",
    "sg:phone":"+32 9 282 76 28",
    "sg:postcode":"9830",
    "sg:province":"Oost-Vlaanderen",
    "wof:name":"C. Van Der Poorten",
    "wof:placetype":"venue"
},
  "geometry": {"coordinates":[3.6154201031,51.0071716309],"type":"Point"}
}