{
  "type": "Feature",
  "properties": {
    "addr:full":"Oudstrijdersstraat 31 Sint-pieters-leeuw Vlaams-Brabant 1600",
    "addr:housenumber":"31",
    "addr:postcode":"1600",
    "addr:street":"Oudstrijdersstraat",
    "iso:country":"BE",
    "sg:address":"Oudstrijdersstraat 31",
    "sg:city":"Sint-pieters-leeuw",
    "sg:classifiers":[
        {
            "category":"Transit Center",
            "subcategory":"Freight",
            "type":"Transportation"
        }
    ],
    "sg:phone":"+32 2 378 06 50",
    "sg:postcode":"1600",
    "sg:province":"Vlaams-Brabant",
    "sg:tags":[
        "pallet",
        "truck",
        "hand"
    ],
    "wof:name":"Industrial Lifting Sa",
    "wof:placetype":"venue"
},
  "geometry": {"coordinates":[4.2904438972,50.8081321716],"type":"Point"}
}