{
  "type": "Feature",
  "properties": {
    "addr:full":"Bloemendaalstraat 136 Halen Limburg 3545",
    "addr:housenumber":"136",
    "addr:postcode":"3545",
    "addr:street":"Bloemendaalstraat",
    "iso:country":"BE",
    "sg:address":"Bloemendaalstraat 136",
    "sg:city":"Halen",
    "sg:classifiers":[
        {
            "category":"Parking",
            "subcategory":"Lot",
            "type":"Transportation"
        }
    ],
    "sg:phone":"+32 13 44 38 18",
    "sg:postcode":"3545",
    "sg:province":"Limburg",
    "sg:tags":[
        "armoured",
        "door",
        "fireproof"
    ],
    "wof:name":"Liesenborghs Marc",
    "wof:placetype":"venue"
},
  "geometry": {"coordinates":[5.1125397682,50.9338645935],"type":"Point"}
}