{
  "type": "Feature",
  "properties": {
    "addr:full":"Rue Abbesse 22 Walhain Brabant Wallon 1457",
    "addr:housenumber":"22;1457",
    "addr:street":"Rue Abbesse",
    "iso:country":"BE",
    "sg:address":"Rue Abbesse 22",
    "sg:city":"Walhain",
    "sg:orig_category":"Banken and kredietinstellingen",
    "sg:phone":"+32 10 65 78 98",
    "sg:postcode":"1457",
    "sg:province":"Brabant Wallon",
    "wof:name":"Cbc",
    "wof:placetype":"venue"
},
  "geometry": {"coordinates":[4.6650018692,50.6371803284],"type":"Point"}
}