{
  "type": "Feature",
  "properties": {
    "iso:country":"BE",
    "sg:address":"Leuvensesteenweg 198",
    "sg:city":"Zaventem",
    "sg:classifiers":[
        {
            "category":"Utilities",
            "subcategory":"Telephone",
            "type":"Services"
        }
    ],
    "sg:phone":"+32 2 721 69 02",
    "sg:postcode":"1930",
    "sg:province":"Vlaams-Brabant",
    "sg:tags":[
        "-",
        "internet"
    ],
    "wof:name":"Whise Nv",
    "wof:placetype":"venue"
},
  "geometry": {"coordinates":[4.4682497978,50.8717498779],"type":"Point"}
}