{
  "type": "Feature",
  "properties": {
    "addr:full":"Rue De La Vall\u00e9e 8 Hotton Luxembourg 6990",
    "addr:housenumber":"8",
    "addr:postcode":"6990",
    "addr:street":"Rue De La Valle\u0301E",
    "iso:country":"BE",
    "sg:address":"Rue De La Vall\u00e9e 8",
    "sg:city":"Hotton",
    "sg:classifiers":[
        {
            "category":"Health Services",
            "subcategory":"Doctor",
            "type":"Services"
        }
    ],
    "sg:phone":"+32 84 46 73 96",
    "sg:postcode":"6990",
    "sg:province":"Luxembourg",
    "sg:tags":[
        "medicinephysicians",
        "surgeon"
    ],
    "wof:name":"Lhermitte M-c",
    "wof:placetype":"venue"
},
  "geometry": {"coordinates":[5.4464659691,50.2688560486],"type":"Point"}
}