{
  "type": "Feature",
  "properties": {
    "iso:country":"BE",
    "sg:address":"Consciencestraat 4",
    "sg:city":"Torhout",
    "sg:classifiers":[
        {
            "category":"Building & Trades",
            "subcategory":"Construction",
            "type":"Services"
        }
    ],
    "sg:phone":"+32 50 21 42 20",
    "sg:postcode":"8820",
    "sg:province":"West-Vlaanderen",
    "sg:tags":[
        "stucco",
        "contractor"
    ],
    "wof:name":"Crevits M & D Bvba",
    "wof:placetype":"venue"
},
  "geometry": {"coordinates":[3.1034190655,51.0646705627],"type":"Point"}
}