{
  "type": "Feature",
  "properties": {
    "addr:full":"Schapenstraat 39 Lennik (sint-martens-lennik) Vlaams-Brabant 1750",
    "addr:housenumber":"39",
    "addr:postcode":"1750",
    "addr:street":"Schapenstraat",
    "iso:country":"BE",
    "sg:address":"Schapenstraat 39",
    "sg:city":"Lennik (sint-martens-lennik)",
    "sg:classifiers":[
        {
            "category":"Education",
            "subcategory":"School",
            "type":"Public Place"
        }
    ],
    "sg:phone":"+32 2 532 58 36",
    "sg:postcode":"1750",
    "sg:province":"Vlaams-Brabant",
    "sg:tags":[
        "secondary"
    ],
    "wof:name":"St-godelieve Instituut",
    "wof:placetype":"venue"
},
  "geometry": {"coordinates":[4.1675138474,50.8150367737],"type":"Point"}
}