{
  "type": "Feature",
  "properties": {
    "addr:full":"Place Leblanc 39 Comblain-au-pont Li\u00e8ge 4170",
    "addr:housenumber":"39",
    "addr:postcode":"4170",
    "addr:street":"Place Leblanc",
    "iso:country":"BE",
    "sg:address":"Place Leblanc 39",
    "sg:city":"Comblain-au-pont",
    "sg:orig_category":"Slagers",
    "sg:phone":"+32 4 369 12 37",
    "sg:postcode":"4170",
    "sg:province":"Li\u00e8ge",
    "wof:name":"Paul Coulee",
    "wof:placetype":"venue"
},
  "geometry": {"coordinates":[5.5768799782,50.4758796692],"type":"Point"}
}