{
  "type": "Feature",
  "properties": {
    "iso:country":"BE",
    "sg:address":"Molenberglei 10",
    "sg:city":"Schelle",
    "sg:classifiers":[
        {
            "category":"Home & Garden",
            "subcategory":"Furniture",
            "type":"Retail Goods"
        }
    ],
    "sg:phone":"+32 3 880 80 60",
    "sg:postcode":"2627",
    "sg:province":"Antwerpen",
    "sg:tags":[
        "professional",
        "household",
        "wood"
    ],
    "wof:name":"B.t.j. Europe-eurobib Nv",
    "wof:placetype":"venue"
},
  "geometry": {"coordinates":[4.3380842209,51.1281700134],"type":"Point"}
}