{
  "type": "Feature",
  "properties": {
    "iso:country":"BE",
    "sg:address":"Rue Au Bois 515",
    "sg:city":"Bruxelles (woluwe-saint-pierre)",
    "sg:orig_category":"Non-Classified Establishments",
    "sg:phone":"+32 2 770 34 36",
    "sg:postcode":"1150",
    "sg:province":"Bruxelles-Capitale",
    "wof:name":"Codesols",
    "wof:placetype":"venue"
},
  "geometry": {"coordinates":[4.4589629173,50.82371521],"type":"Point"}
}