{
  "type": "Feature",
  "properties": {
    "iso:country":"BE",
    "sg:address":"Rijsseveldstraat 71",
    "sg:city":"Staden",
    "sg:orig_category":"Installatie van houten of kunststof schrijnwerk",
    "sg:phone":"+32 51 70 30 33",
    "sg:postcode":"8840",
    "sg:province":"West-Vlaanderen",
    "wof:name":"Noel Callewaert",
    "wof:placetype":"venue"
},
  "geometry": {"coordinates":[3.0127930641,50.9751815796],"type":"Point"}
}