{
  "type": "Feature",
  "properties": {
    "addr:full":"Rue De Waremme 30 Villers-le-bouillet Li\u00e8ge 4530",
    "addr:housenumber":"30",
    "addr:postcode":"4530",
    "addr:street":"Rue De Waremme",
    "iso:country":"BE",
    "sg:address":"Rue De Waremme 30",
    "sg:city":"Villers-le-bouillet",
    "sg:orig_category":"Pharmaciens",
    "sg:phone":"+32 85 21 46 00",
    "sg:postcode":"4530",
    "sg:province":"Li\u00e8ge",
    "wof:name":"Pharmacie Du Peuple",
    "wof:placetype":"venue"
},
  "geometry": {"coordinates":[5.2680277824,50.5691375732],"type":"Point"}
}