{
  "type": "Feature",
  "properties": {
    "addr:full":"Kortrijkstraat 47 Avelgem West-Vlaanderen 8580",
    "addr:housenumber":"47",
    "addr:postcode":"8580",
    "addr:street":"Kortrijkstraat",
    "iso:country":"BE",
    "sg:address":"Kortrijkstraat 47",
    "sg:city":"Avelgem",
    "sg:orig_category":"Beheer onroerend goed",
    "sg:phone":"+32 56 64 49 59",
    "sg:postcode":"8580",
    "sg:province":"West-Vlaanderen",
    "wof:name":"Intakt",
    "wof:placetype":"venue"
},
  "geometry": {"coordinates":[3.4400110245,50.7750473022],"type":"Point"}
}