{
  "type": "Feature",
  "properties": {
    "addr:full":"Rue Du Ch\u00eane 38c Ciney (ach\u00eane) Namur 5590",
    "addr:housenumber":"38c",
    "addr:postcode":"5590",
    "addr:street":"Rue Du Che\u0302Ne",
    "iso:country":"BE",
    "sg:address":"Rue Du Ch\u00eane 38c",
    "sg:city":"Ciney (ach\u00eane)",
    "sg:classifiers":[
        {
            "category":"Professional",
            "subcategory":"Testing Lab",
            "type":"Services"
        }
    ],
    "sg:phone":"+32 83 22 03 59",
    "sg:postcode":"5590",
    "sg:province":"Namur",
    "sg:tags":[
        "chemist"
    ],
    "wof:name":"Gillain V",
    "wof:placetype":"venue"
},
  "geometry": {"coordinates":[5.1022520065,50.297088623],"type":"Point"}
}