{
  "type": "Feature",
  "properties": {
    "iso:country":"BE",
    "sg:address":"Ave De Wisterzee 49",
    "sg:city":"Court St. Etienne",
    "sg:classifiers":[
        {
            "category":"Banks & Credit Unions",
            "subcategory":"Bank",
            "type":"Services"
        }
    ],
    "sg:phone":"+32 10 61 43 87",
    "sg:postcode":"1490",
    "sg:province":"Brabant Wallon",
    "wof:name":"Cr\u00e9dit Communal",
    "wof:placetype":"venue"
},
  "geometry": {"coordinates":[4.5638999939,50.6478462219],"type":"Point"}
}