{
  "type": "Feature",
  "properties": {
    "iso:country":"BE",
    "sg:address":"Jean-baptiste D'hanedreef 9",
    "sg:city":"Gent (drongen)",
    "sg:classifiers":[
        {
            "category":"Personal",
            "subcategory":"Sauna",
            "type":"Services"
        }
    ],
    "sg:phone":"+32 9 226 79 87",
    "sg:postcode":"9031",
    "sg:province":"Oost-Vlaanderen",
    "wof:name":"Van Der Aa J",
    "wof:placetype":"venue"
},
  "geometry": {"coordinates":[3.6639389992,51.0534591675],"type":"Point"}
}