{
  "type": "Feature",
  "properties": {
    "iso:country":"BE",
    "sg:address":"Avenue Albert 5",
    "sg:city":"Spa",
    "sg:classifiers":[
        {
            "category":"Banks & Credit Unions",
            "subcategory":"Bureau De Change",
            "type":"Services"
        }
    ],
    "sg:phone":"+32 87 77 05 41",
    "sg:postcode":"4900",
    "sg:province":"Li\u00e8ge",
    "sg:tags":[
        "model",
        "scale",
        "-"
    ],
    "wof:name":"H.m.s. Sc",
    "wof:placetype":"venue"
},
  "geometry": {"coordinates":[5.879073143,50.5016975403],"type":"Point"}
}