{
  "type": "Feature",
  "properties": {
    "iso:country":"BE",
    "sg:address":"Kerkstraat 43",
    "sg:city":"Vorselaar",
    "sg:classifiers":[
        {
            "category":"Food Court",
            "type":"Food & Drink"
        }
    ],
    "sg:phone":"+32 14 51 54 24",
    "sg:postcode":"2290",
    "sg:province":"Antwerpen",
    "sg:tags":[
        "product",
        "related"
    ],
    "wof:name":"Dhr Jozef Van Den Broeck",
    "wof:placetype":"venue"
},
  "geometry": {"coordinates":[4.7690281868,51.2027397156],"type":"Point"}
}