{
  "type": "Feature",
  "properties": {
    "addr:full":"Tinhoutstraat 113 Beernem (oedelem) West-Vlaanderen 8730",
    "addr:housenumber":"113",
    "addr:postcode":"8730",
    "addr:street":"Tinhoutstraat",
    "iso:country":"BE",
    "sg:address":"Tinhoutstraat 113",
    "sg:city":"Beernem (oedelem)",
    "sg:classifiers":[
        {
            "category":"Home & Garden",
            "subcategory":"Hardware",
            "type":"Retail Goods"
        }
    ],
    "sg:postcode":"8730",
    "sg:province":"West-Vlaanderen",
    "sg:tags":[
        "gate",
        "opener",
        "door",
        "automatic"
    ],
    "wof:name":"Ribbers Alg Deurtechn Autom Bv",
    "wof:placetype":"venue"
},
  "geometry": {"coordinates":[4.9470410347,51.681312561],"type":"Point"}
}