{
  "type": "Feature",
  "properties": {
    "addr:full":"Burg 11 Torhout West-Vlaanderen 8820",
    "addr:housenumber":"11",
    "addr:postcode":"8820",
    "addr:street":"Burg",
    "iso:country":"BE",
    "sg:address":"Burg 11",
    "sg:city":"Torhout",
    "sg:orig_category":"Brood, gebak and snoepgoed",
    "sg:phone":"+32 50 21 71 73",
    "sg:postcode":"8820",
    "sg:province":"West-Vlaanderen",
    "wof:name":"Bakkerij Pinguin",
    "wof:placetype":"venue"
},
  "geometry": {"coordinates":[3.1016690731,51.0659179688],"type":"Point"}
}