{
  "type": "Feature",
  "properties": {
    "addr:full":"Zavel 16 Lochristi Oost-Vlaanderen 9080",
    "addr:housenumber":"16",
    "addr:postcode":"9080",
    "addr:street":"Zavel",
    "iso:country":"BE",
    "sg:address":"Zavel 16",
    "sg:city":"Lochristi",
    "sg:orig_category":"Peinture. Rev\u00eatements pour sols and murs",
    "sg:phone":"+32 9 356 70 58",
    "sg:postcode":"9080",
    "sg:province":"Oost-Vlaanderen",
    "wof:name":"Mario De Messemaeker",
    "wof:placetype":"venue"
},
  "geometry": {"coordinates":[3.8852920532,51.1077613831],"type":"Point"}
}