{
  "type": "Feature",
  "properties": {
    "iso:country":"BE",
    "sg:address":"Ruggeveldstraat 65",
    "sg:city":"Wijnegem",
    "sg:classifiers":[
        {
            "category":"Personal",
            "subcategory":"Beauty Salon",
            "type":"Services"
        }
    ],
    "sg:phone":"+32 3 353 70 35",
    "sg:postcode":"2110",
    "sg:province":"Antwerpen",
    "sg:tags":[
        "de",
        "coiffure"
    ],
    "wof:name":"Coiffure Gil",
    "wof:placetype":"venue"
},
  "geometry": {"coordinates":[4.5049591064,51.2275466919],"type":"Point"}
}