{
  "type": "Feature",
  "properties": {
    "addr:full":"Izegemsestraat 95 Roeselare (rumbeke) West-Vlaanderen 8800",
    "addr:housenumber":"95",
    "addr:postcode":"8800",
    "addr:street":"Izegemsestraat",
    "iso:country":"BE",
    "sg:address":"Izegemsestraat 95",
    "sg:city":"Roeselare (rumbeke)",
    "sg:orig_category":"Non-Classified Establishments",
    "sg:phone":"+32 51 20 00 78",
    "sg:postcode":"8800",
    "sg:province":"West-Vlaanderen",
    "wof:name":"Decruy A A Nv",
    "wof:placetype":"venue"
},
  "geometry": {"coordinates":[3.1663980484,50.931224823],"type":"Point"}
}