{
  "type": "Feature",
  "properties": {
    "iso:country":"BE",
    "sg:address":"Chauss\u00e9e D'alsemberg 1235",
    "sg:city":"Bruxelles (uccle)",
    "sg:classifiers":[
        {
            "category":"Insurance",
            "subcategory":"Insurance Agent",
            "type":"Services"
        }
    ],
    "sg:phone":"+32 2 332 20 31",
    "sg:postcode":"1180",
    "sg:province":"Bruxelles-Capitale",
    "sg:tags":[
        "broker"
    ],
    "wof:name":"Segassur Sprl C/o Segers & Associ\u00e9s",
    "wof:placetype":"venue"
},
  "geometry": {"coordinates":[4.32833004,50.7851448059],"type":"Point"}
}