{
  "type": "Feature",
  "properties": {
    "iso:country":"BE",
    "sg:address":"Boondaalse Steenweg 6",
    "sg:city":"Elsene/ixelles",
    "sg:orig_category":"Divers amusement Diverse zakelijke dienstverlening",
    "sg:phone":"+32 2 647 38 38",
    "sg:postcode":"1050",
    "sg:province":"Bruxelles-Capitale",
    "wof:name":"Live Music Now",
    "wof:placetype":"venue"
},
  "geometry": {"coordinates":[4.3934841156,50.8094520569],"type":"Point"}
}