{
  "type": "Feature",
  "properties": {
    "addr:full":"Chauss\u00c9e De Douai 81 Rumes Hainaut 7610",
    "addr:housenumber":"81",
    "addr:postcode":"7610",
    "addr:street":"Chausse\u0301E De Douai",
    "iso:country":"BE",
    "sg:address":"Chauss\u00c9e De Douai 81",
    "sg:city":"Rumes",
    "sg:classifiers":[
        {
            "category":"Cafe",
            "type":"Food & Drink"
        }
    ],
    "sg:phone":"+32 69 64 75 06",
    "sg:postcode":"7610",
    "sg:province":"Hainaut",
    "sg:tags":[
        "caf\u00e9s"
    ],
    "wof:name":"Le Galibier",
    "wof:placetype":"venue"
},
  "geometry": {"coordinates":[3.3052968979,50.5536460876],"type":"Point"}
}