{
  "type": "Feature",
  "properties": {
    "iso:country":"BE",
    "sg:address":"Nationalestraat 119",
    "sg:city":"Antwerpen",
    "sg:orig_category":"Apotheken",
    "sg:phone":"+32 3 233 03 06",
    "sg:postcode":"2000",
    "sg:province":"Antwerpen",
    "wof:name":"De Volksmacht",
    "wof:placetype":"venue"
},
  "geometry": {"coordinates":[4.3977518082,51.2137031555],"type":"Point"}
}