{
  "type": "Feature",
  "properties": {
    "iso:country":"BE",
    "sg:address":"Rue Des Martyrs 12",
    "sg:city":"Verviers",
    "sg:classifiers":[
        {
            "category":"Wholesale",
            "subcategory":"Sporting Goods",
            "type":"Manufacturing & Wholesale Goods"
        }
    ],
    "sg:phone":"+32 87 33 25 43",
    "sg:postcode":"4800",
    "sg:province":"Li\u00e8ge",
    "sg:tags":[
        "sport-",
        "kampeermateriaal"
    ],
    "wof:name":"Moncrief Sports",
    "wof:placetype":"venue"
},
  "geometry": {"coordinates":[5.862347126,50.5921096802],"type":"Point"}
}