{
  "type": "Feature",
  "properties": {
    "iso:country":"BE",
    "sg:address":"Rue Henri Orban 45",
    "sg:city":"Li\u00e8ge 1 (grivegn\u00e9e)",
    "sg:classifiers":[
        {
            "category":"Arts & Performance",
            "subcategory":"Art Gallery",
            "type":"Entertainment"
        }
    ],
    "sg:phone":"+32 4 343 60 43",
    "sg:postcode":"4030",
    "sg:province":"Li\u00e8ge",
    "wof:name":"Baris Manog B 40 30 Belgica",
    "wof:placetype":"venue"
},
  "geometry": {"coordinates":[5.5969228745,50.6199951172],"type":"Point"}
}