{
  "type": "Feature",
  "properties": {
    "addr:full":"Pieter De Conincklaan 50 Brugge West-Vlaanderen 8200",
    "addr:housenumber":"50",
    "addr:postcode":"8200",
    "addr:street":"Pieter De Conincklaan",
    "iso:country":"BE",
    "sg:address":"Pieter De Conincklaan 50",
    "sg:city":"Brugge",
    "sg:orig_category":"Mat\u00e9riaux de construction Gr",
    "sg:phone":"+32 50 82 72 84",
    "sg:postcode":"8200",
    "sg:province":"West-Vlaanderen",
    "wof:name":"Fa. Verraes D.",
    "wof:placetype":"venue"
},
  "geometry": {"coordinates":[3.2067329884,51.2078361511],"type":"Point"}
}