{
  "type": "Feature",
  "properties": {
    "addr:full":"Route D'amberloup 33 Sainte-ode Luxembourg 6680",
    "addr:housenumber":"33",
    "addr:postcode":"6680",
    "addr:street":"Route D'Amberloup",
    "iso:country":"BE",
    "sg:address":"Route D'amberloup 33",
    "sg:city":"Sainte-ode",
    "sg:orig_category":"Kapsalons",
    "sg:phone":"+32 61 68 89 61",
    "sg:postcode":"6680",
    "sg:province":"Luxembourg",
    "wof:name":"Coiffure Evasion",
    "wof:placetype":"venue"
},
  "geometry": {"coordinates":[5.5152039528,50.0248527527],"type":"Point"}
}