{
  "type": "Feature",
  "properties": {
    "addr:full":"Keizer Karellaan 16b3 Ganshoren Bruxelles-Capitale 1083",
    "addr:housenumber":"16b3",
    "addr:postcode":"1083",
    "addr:street":"Keizer Karellaan",
    "iso:country":"BE",
    "sg:address":"Keizer Karellaan 16b3",
    "sg:city":"Ganshoren",
    "sg:orig_category":"Artsen and specialisten",
    "sg:phone":"+32 2 427 64 97",
    "sg:postcode":"1083",
    "sg:province":"Bruxelles-Capitale",
    "wof:name":"Abderrahim El Amari",
    "wof:placetype":"venue"
},
  "geometry": {"coordinates":[4.3131480217,50.8682441711],"type":"Point"}
}