{
  "type": "Feature",
  "properties": {
    "addr:full":"Bergensesteenweg 447 Halle Vlaams-Brabant 1500",
    "addr:housenumber":"447",
    "addr:postcode":"1500",
    "addr:street":"Bergensesteenweg",
    "iso:country":"BE",
    "sg:address":"Bergensesteenweg 447",
    "sg:city":"Halle",
    "sg:orig_category":"V\u00e9hicules automobiles. Entretien and r\u00e9parations de voitures",
    "sg:phone":"+32 2 361 00 16",
    "sg:postcode":"1500",
    "sg:province":"Vlaams-Brabant",
    "wof:name":"Atlanta Motors",
    "wof:placetype":"venue"
},
  "geometry": {"coordinates":[4.2259469032,50.7216567993],"type":"Point"}
}