{
  "type": "Feature",
  "properties": {
    "addr:full":"Herestraat 5 Box 1 Leuven Vlaams-Brabant 3000",
    "addr:housenumber":"5;1",
    "addr:postcode":"3000",
    "addr:street":"Herestraat;Box",
    "iso:country":"BE",
    "sg:address":"Herestraat 5 Box 1",
    "sg:city":"Leuven",
    "sg:classifiers":[
        {
            "category":"Wholesale",
            "subcategory":"Medical Equipment & Supplies",
            "type":"Manufacturing & Wholesale Goods"
        }
    ],
    "sg:phone":"+32 16 23 28 97",
    "sg:postcode":"3000",
    "sg:province":"Vlaams-Brabant",
    "sg:tags":[
        "instrument",
        "apparatus"
    ],
    "wof:name":"Vitatron Belgium Nv",
    "wof:placetype":"venue"
},
  "geometry": {"coordinates":[4.6815900803,50.8801002502],"type":"Point"}
}