{
  "type": "Feature",
  "properties": {
    "iso:country":"BE",
    "sg:address":"Roeselaarsestraat 67",
    "sg:city":"Izegem",
    "sg:classifiers":[
        {
            "category":"Personal",
            "subcategory":"Beauty Salon",
            "type":"Services"
        }
    ],
    "sg:phone":"+32 51 30 49 67",
    "sg:postcode":"8870",
    "sg:province":"West-Vlaanderen",
    "sg:tags":[
        "de",
        "coiffure"
    ],
    "wof:name":"Coiffure Paribel",
    "wof:placetype":"venue"
},
  "geometry": {"coordinates":[3.209387064,50.9190368652],"type":"Point"}
}