{
  "type": "Feature",
  "properties": {
    "addr:full":"Sint - Gerofstraat 48 Gent Oost-Vlaanderen 9031",
    "addr:housenumber":"48",
    "addr:postcode":"9031",
    "addr:street":"Gerofstraat;Oost-Vlaanderen",
    "iso:country":"BE",
    "sg:address":"Sint - Gerofstraat 48",
    "sg:city":"Gent",
    "sg:classifiers":[
        {
            "category":"Wholesale",
            "subcategory":"Sporting Goods",
            "type":"Manufacturing & Wholesale Goods"
        }
    ],
    "sg:phone":"+32 9 236 38 89",
    "sg:postcode":"9031",
    "sg:province":"Oost-Vlaanderen",
    "sg:tags":[
        "sport-",
        "kampeermateriaal"
    ],
    "wof:name":"Fremobici",
    "wof:placetype":"venue"
},
  "geometry": {"coordinates":[3.6305251122,51.045589447],"type":"Point"}
}