{
  "type": "Feature",
  "properties": {
    "iso:country":"BE",
    "sg:address":"Esplanadeplein 21",
    "sg:city":"Aalst",
    "sg:orig_category":"Electrom\u00e9nager, t\u00e9l\u00e9visions and radios",
    "sg:phone":"+32 53 21 53 63",
    "sg:postcode":"9300",
    "sg:province":"Oost-Vlaanderen",
    "wof:name":"Hifinesse",
    "wof:placetype":"venue"
},
  "geometry": {"coordinates":[4.0361318588,50.9407501221],"type":"Point"}
}