{
  "type": "Feature",
  "properties": {
    "iso:country":"BE",
    "sg:address":"Koornemoezen 2",
    "sg:city":"Zedelgem",
    "sg:classifiers":[
        {
            "category":"Communications",
            "subcategory":"Film & Video Production",
            "type":"Services"
        }
    ],
    "sg:phone":"+32 50 39 15 03",
    "sg:postcode":"8210",
    "sg:province":"West-Vlaanderen",
    "sg:tags":[
        "producer",
        "realizators"
    ],
    "wof:name":"De Paepe D",
    "wof:placetype":"venue"
},
  "geometry": {"coordinates":[3.1411550045,51.1507568359],"type":"Point"}
}