{
  "type": "Feature",
  "properties": {
    "addr:full":"Sint Truidersteenweg 39 Herk-de-stad Limburg 3540",
    "addr:housenumber":"39",
    "addr:postcode":"3540",
    "addr:street":"Sint Truidersteenweg",
    "iso:country":"BE",
    "sg:address":"Sint Truidersteenweg 39",
    "sg:city":"Herk-de-stad",
    "sg:orig_category":"Bloemen and planten",
    "sg:phone":"+32 13 55 17 39",
    "sg:postcode":"3540",
    "sg:province":"Limburg",
    "wof:name":"Potsierlijk",
    "wof:placetype":"venue"
},
  "geometry": {"coordinates":[5.1698999405,50.9319725037],"type":"Point"}
}