{
  "type": "Feature",
  "properties": {
    "addr:full":"Rue Arthur Cosyn 22 Brussel/bruxelles Bruxelles-Capitale 1020",
    "addr:housenumber":"22",
    "addr:postcode":"1020",
    "addr:street":"Rue Arthur Cosyn;/",
    "iso:country":"BE",
    "sg:address":"Rue Arthur Cosyn 22",
    "sg:city":"Brussel/bruxelles",
    "sg:orig_category":"M\u00e9decins and sp\u00e9cialistes",
    "sg:phone":"+32 2 478 24 43",
    "sg:postcode":"1020",
    "sg:province":"Bruxelles-Capitale",
    "wof:name":"Adriana Van De Vliet",
    "wof:placetype":"venue"
},
  "geometry": {"coordinates":[4.3580999374,50.8773727417],"type":"Point"}
}