{
  "type": "Feature",
  "properties": {
    "iso:country":"BE",
    "sg:address":"Prekental 8",
    "sg:city":"Ninove",
    "sg:orig_category":"Diensten voor huisdieren",
    "sg:phone":"+32 54 32 55 54",
    "sg:postcode":"9406",
    "sg:province":"Oost-Vlaanderen",
    "wof:name":"Dog-cleaning",
    "wof:placetype":"venue"
},
  "geometry": {"coordinates":[3.9917259216,50.8451347351],"type":"Point"}
}