{
  "type": "Feature",
  "properties": {
    "addr:full":"Herentalseweg 37 Geel Antwerpen 2440",
    "addr:housenumber":"37",
    "addr:postcode":"2440",
    "addr:street":"Herentalseweg",
    "iso:country":"BE",
    "sg:address":"Herentalseweg 37",
    "sg:city":"Geel",
    "sg:classifiers":[
        {
            "category":"Cafe",
            "type":"Food & Drink"
        }
    ],
    "sg:phone":"+32 14 58 18 35",
    "sg:postcode":"2440",
    "sg:province":"Antwerpen",
    "sg:tags":[
        "caf\u00e9s"
    ],
    "wof:name":"Caf\u00c9 Monaco",
    "wof:placetype":"venue"
},
  "geometry": {"coordinates":[4.9307250977,51.1810302734],"type":"Point"}
}