{
  "type": "Feature",
  "properties": {
    "iso:country":"BE",
    "sg:address":"Hellestraat 31",
    "sg:city":"Sint-niklaas (sinaai)",
    "sg:classifiers":[
        {
            "category":"Social Services",
            "subcategory":"Job Training",
            "type":"Services"
        }
    ],
    "sg:phone":"+32 3 722 02 57",
    "sg:postcode":"9112",
    "sg:province":"Oost-Vlaanderen",
    "sg:tags":[
        "personnel"
    ],
    "wof:name":"Adviesbureau Voor Personeelsmanagement Bvba",
    "wof:placetype":"venue"
},
  "geometry": {"coordinates":[4.0255818367,51.148109436],"type":"Point"}
}