{
  "type": "Feature",
  "properties": {
    "addr:full":"Wolvendreef 61a Kortrijk West-Vlaanderen 8500",
    "addr:housenumber":"61a",
    "addr:postcode":"8500",
    "addr:street":"Wolvendreef",
    "iso:country":"BE",
    "sg:address":"Wolvendreef 61a",
    "sg:city":"Kortrijk",
    "sg:classifiers":[
        {
            "category":"Health Services",
            "subcategory":"Doctor",
            "type":"Services"
        }
    ],
    "sg:phone":"+32 56 21 49 80",
    "sg:postcode":"8500",
    "sg:province":"West-Vlaanderen",
    "sg:tags":[
        "medicinephysicians",
        "surgeon"
    ],
    "wof:name":"Janssens L",
    "wof:placetype":"venue"
},
  "geometry": {"coordinates":[3.2622509003,50.8123703003],"type":"Point"}
}