{
  "type": "Feature",
  "properties": {
    "iso:country":"BE",
    "sg:address":"Brandstraat 28",
    "sg:city":"Lochristi",
    "sg:orig_category":"Woningbouw",
    "sg:phone":"+32 9 355 66 21",
    "sg:postcode":"9080",
    "sg:province":"Oost-Vlaanderen",
    "wof:name":"Andre De Blieck",
    "wof:placetype":"venue"
},
  "geometry": {"coordinates":[3.8603520393,51.0713539124],"type":"Point"}
}