{
  "type": "Feature",
  "properties": {
    "iso:country":"BE",
    "sg:address":"Falconplein 16 Ba",
    "sg:city":"Antwerpen",
    "sg:orig_category":"Bijouteries and horlogeries. R\u00e9parations d'horloges, montres and bijoux",
    "sg:phone":"+32 3 225 24 72",
    "sg:postcode":"2000",
    "sg:province":"Antwerpen",
    "wof:name":"Jewellery",
    "wof:placetype":"venue"
},
  "geometry": {"coordinates":[4.3974518776,51.2216911316],"type":"Point"}
}