{
  "type": "Feature",
  "properties": {
    "addr:full":"Rue Henri-de-leez 17 Gembloux Namur 5031",
    "addr:housenumber":"17",
    "addr:postcode":"5031",
    "addr:street":"Rue Henri-De-Leez;Namur",
    "iso:country":"BE",
    "sg:address":"Rue Henri-de-leez 17",
    "sg:city":"Gembloux",
    "sg:orig_category":"Herstelling and restauratie van meubelen",
    "sg:phone":"+32 81 64 09 15",
    "sg:postcode":"5031",
    "sg:province":"Namur",
    "wof:name":"Fe. Hack",
    "wof:placetype":"venue"
},
  "geometry": {"coordinates":[4.7631158829,50.5819892883],"type":"Point"}
}