{
  "type": "Feature",
  "properties": {
    "addr:full":"Rue De Nimy 38 Mons Hainaut 7000",
    "addr:housenumber":"38",
    "addr:postcode":"7000",
    "addr:street":"Rue De Nimy;Hainaut",
    "iso:country":"BE",
    "sg:address":"Rue De Nimy 38",
    "sg:city":"Mons",
    "sg:classifiers":[
        {
            "category":"Bakery",
            "type":"Food & Drink"
        }
    ],
    "sg:phone":"+32 65 34 85 81",
    "sg:postcode":"7000",
    "sg:province":"Hainaut",
    "sg:tags":[
        "confectioner",
        "baker"
    ],
    "wof:name":"De Meyer M",
    "wof:placetype":"venue"
},
  "geometry": {"coordinates":[3.9546279907,50.4562225342],"type":"Point"}
}