{
  "type": "Feature",
  "properties": {
    "iso:country":"BE",
    "sg:address":"Pintestraat 6bb",
    "sg:city":"De Pinte",
    "sg:orig_category":"Krantenwinkels Rookartikelen",
    "sg:phone":"+32 9 282 49 75",
    "sg:postcode":"9840",
    "sg:province":"Oost-Vlaanderen",
    "wof:name":"Huis Dali",
    "wof:placetype":"venue"
},
  "geometry": {"coordinates":[3.6489019394,50.991443634],"type":"Point"}
}