{
  "type": "Feature",
  "properties": {
    "addr:full":"Genkersteenweg 284ba Hasselt Limburg 3500",
    "addr:postcode":"3500",
    "addr:street":"Genkersteenweg 284Ba",
    "iso:country":"BE",
    "sg:address":"Genkersteenweg 284ba",
    "sg:city":"Hasselt",
    "sg:orig_category":"Artiestenbureaus",
    "sg:phone":"+32 11 22 75 20",
    "sg:postcode":"3500",
    "sg:province":"Limburg",
    "wof:name":"Feestzaal Lorka",
    "wof:placetype":"venue"
},
  "geometry": {"coordinates":[5.381734848,50.9450645447],"type":"Point"}
}