{
  "type": "Feature",
  "properties": {
    "addr:full":"Rue De La Cabine 4 Beauraing Namur 5574",
    "addr:housenumber":"4",
    "addr:postcode":"5574",
    "addr:street":"Rue De La Cabine",
    "iso:country":"BE",
    "sg:address":"Rue De La Cabine 4",
    "sg:city":"Beauraing",
    "sg:orig_category":"Action sociale avec h\u00e9bergement",
    "sg:phone":"+32 82 71 42 59",
    "sg:postcode":"5574",
    "sg:province":"Namur",
    "wof:name":"Le Souffle De Vie",
    "wof:placetype":"venue"
},
  "geometry": {"coordinates":[5.0083861351,50.0987586975],"type":"Point"}
}