{
  "type": "Feature",
  "properties": {
    "iso:country":"BE",
    "sg:address":"Chauss\u00e9e De Namur 13",
    "sg:city":"Anh\u00e9e (annevoie-rouillon)",
    "sg:classifiers":[
        {
            "category":"Professional",
            "subcategory":"Management & Consulting",
            "type":"Services"
        }
    ],
    "sg:phone":"+32 82 61 48 78",
    "sg:postcode":"5537",
    "sg:province":"Namur",
    "sg:tags":[
        "consultant",
        "agency",
        "advertising"
    ],
    "wof:name":"Division Phoenix",
    "wof:placetype":"venue"
},
  "geometry": {"coordinates":[4.8736982346,50.3212509155],"type":"Point"}
}