{
  "type": "Feature",
  "properties": {
    "iso:country":"BE",
    "sg:address":"Koning Albertlaan 21",
    "sg:city":"De Pinte",
    "sg:orig_category":"Boekhouders",
    "sg:phone":"+32 9 282 30 28",
    "sg:postcode":"9840",
    "sg:province":"Oost-Vlaanderen",
    "wof:name":"Gaston Eechaute",
    "wof:placetype":"venue"
},
  "geometry": {"coordinates":[3.6507139206,50.9941291809],"type":"Point"}
}