{
  "type": "Feature",
  "properties": {
    "addr:full":"Bosstraat 7 Maaseik Limburg 3680",
    "addr:housenumber":"7",
    "addr:postcode":"3680",
    "addr:street":"Bosstraat",
    "iso:country":"BE",
    "sg:address":"Bosstraat 7",
    "sg:city":"Maaseik",
    "sg:classifiers":[
        {
            "category":"Shopping",
            "subcategory":"Antiques",
            "type":"Retail Goods"
        }
    ],
    "sg:phone":"+32 89 56 43 78",
    "sg:postcode":"3680",
    "sg:province":"Limburg",
    "wof:name":"Lemmens D",
    "wof:placetype":"venue"
},
  "geometry": {"coordinates":[5.790681839,51.0949935913],"type":"Point"}
}