{
  "type": "Feature",
  "properties": {
    "addr:full":"Frankrijklaan 20 Harelbeke West-Vlaanderen 8530",
    "addr:housenumber":"20",
    "addr:postcode":"8530",
    "addr:street":"Frankrijklaan",
    "iso:country":"BE",
    "sg:address":"Frankrijklaan 20",
    "sg:city":"Harelbeke",
    "sg:orig_category":"Installation de menuiserie en bois and plastique",
    "sg:phone":"+32 56 21 01 12",
    "sg:postcode":"8530",
    "sg:province":"West-Vlaanderen",
    "wof:name":"Andy Priels",
    "wof:placetype":"venue"
},
  "geometry": {"coordinates":[3.324835062,50.8544235229],"type":"Point"}
}