{
  "type": "Feature",
  "properties": {
    "addr:full":"Avenue Rogier 2 Box 4 Bruxelles (schaerbeek) Bruxelles-Capitale 1030",
    "addr:housenumber":"2;4",
    "addr:postcode":"1030",
    "addr:street":"Avenue Rogier;Box",
    "iso:country":"BE",
    "sg:address":"Avenue Rogier 2 Box 4",
    "sg:city":"Bruxelles (schaerbeek)",
    "sg:classifiers":[
        {
            "category":"Health Services",
            "subcategory":"Dentist",
            "type":"Services"
        }
    ],
    "sg:phone":"+32 2 215 76 34",
    "sg:postcode":"1030",
    "sg:province":"Bruxelles-Capitale",
    "wof:name":"Spaller Jean-luc",
    "wof:placetype":"venue"
},
  "geometry": {"coordinates":[4.3720760345,50.860786438],"type":"Point"}
}