{
  "type": "Feature",
  "properties": {
    "addr:full":"Rue De La Pav\u00e9e 7 Namur (erpent) Namur 5101",
    "addr:housenumber":"7",
    "addr:postcode":"5101",
    "addr:street":"Rue De La Pave\u0301E",
    "iso:country":"BE",
    "sg:address":"Rue De La Pav\u00e9e 7",
    "sg:city":"Namur (erpent)",
    "sg:classifiers":[
        {
            "category":"Food & Beverages",
            "subcategory":"Specialty",
            "type":"Retail Goods"
        }
    ],
    "sg:phone":"+32 81 80 54 30",
    "sg:postcode":"5101",
    "sg:province":"Namur",
    "sg:tags":[
        "health",
        "dietary",
        "-",
        "biological"
    ],
    "wof:name":"Signe Nature",
    "wof:placetype":"venue"
},
  "geometry": {"coordinates":[4.8990521431,50.4470710754],"type":"Point"}
}