{
  "type": "Feature",
  "properties": {
    "addr:full":"Avenue Jean-fran\u00e7ois Leemans 67 Bruxelles (auderghem) Bruxelles-Capitale 1160",
    "addr:housenumber":"67",
    "addr:postcode":"1160",
    "addr:street":"Avenue Jean-Franc\u0327Ois Leemans",
    "iso:country":"BE",
    "sg:address":"Avenue Jean-fran\u00e7ois Leemans 67",
    "sg:city":"Bruxelles (auderghem)",
    "sg:classifiers":[
        {
            "category":"Real Estate",
            "subcategory":"Surveying",
            "type":"Services"
        }
    ],
    "sg:phone":"+32 2 673 48 10",
    "sg:postcode":"1160",
    "sg:province":"Bruxelles-Capitale",
    "sg:tags":[
        "surveyor",
        "land"
    ],
    "wof:name":"Massart R",
    "wof:placetype":"venue"
},
  "geometry": {"coordinates":[4.4376330376,50.8035736084],"type":"Point"}
}