{
  "type": "Feature",
  "properties": {
    "addr:full":"Breughelstraat 8 Neerpelt Limburg 3910",
    "addr:housenumber":"8",
    "addr:postcode":"3910",
    "addr:street":"Breughelstraat",
    "iso:country":"BE",
    "sg:address":"Breughelstraat 8",
    "sg:city":"Neerpelt",
    "sg:classifiers":[
        {
            "category":"Communications",
            "subcategory":"Film & Video Production",
            "type":"Services"
        }
    ],
    "sg:phone":"+32 11 64 30 73",
    "sg:postcode":"3910",
    "sg:province":"Limburg",
    "sg:tags":[
        "material",
        "audio-visual"
    ],
    "wof:name":"Audio Diffusion",
    "wof:placetype":"venue"
},
  "geometry": {"coordinates":[5.4431500435,51.1920700073],"type":"Point"}
}