{
  "type": "Feature",
  "properties": {
    "iso:country":"BE",
    "sg:address":"Singelstraat 46",
    "sg:city":"Heusden-zolder (heusden)",
    "sg:classifiers":[
        {
            "category":"Insurance",
            "subcategory":"Insurance Agent",
            "type":"Services"
        }
    ],
    "sg:phone":"+32 11 57 29 38",
    "sg:postcode":"3550",
    "sg:province":"Limburg",
    "sg:tags":[
        "broker"
    ],
    "wof:name":"Vermeulen R Verzekeringen Bvba",
    "wof:placetype":"venue"
},
  "geometry": {"coordinates":[5.3065018654,51.0509643555],"type":"Point"}
}