{
  "type": "Feature",
  "properties": {
    "iso:country":"BE",
    "sg:address":"Rue Chiff D'or 10",
    "sg:city":"Saint-nicolas (tilleur)",
    "sg:classifiers":[
        {
            "category":"Professional",
            "subcategory":"Testing Lab",
            "type":"Services"
        }
    ],
    "sg:phone":"+32 4 233 91 96",
    "sg:postcode":"4420",
    "sg:province":"Li\u00e8ge",
    "sg:tags":[
        "laboratory",
        "photographic",
        "film"
    ],
    "wof:name":"Jet Color Sprl",
    "wof:placetype":"venue"
},
  "geometry": {"coordinates":[5.5381298065,50.6303710938],"type":"Point"}
}