{
  "type": "Feature",
  "properties": {
    "addr:full":"Marjoleinstraat 37 Zemst Vlaams-Brabant 1982",
    "addr:housenumber":"37",
    "addr:postcode":"1982",
    "addr:street":"Marjoleinstraat;Vlaams-Brabant",
    "iso:country":"BE",
    "sg:address":"Marjoleinstraat 37",
    "sg:city":"Zemst",
    "sg:classifiers":[
        {
            "category":"Arena",
            "subcategory":"Sports Club",
            "type":"Entertainment"
        }
    ],
    "sg:phone":"+32 15 61 58 54",
    "sg:postcode":"1982",
    "sg:province":"Vlaams-Brabant",
    "sg:tags":[
        "de"
    ],
    "wof:name":"Fratelli Team",
    "wof:placetype":"venue"
},
  "geometry": {"coordinates":[4.5043201447,50.9652290344],"type":"Point"}
}