{
  "type": "Feature",
  "properties": {
    "iso:country":"BE",
    "sg:address":"Hoogkamerstraat 337",
    "sg:city":"Temse",
    "sg:classifiers":[
        {
            "category":"Food & Beverages",
            "subcategory":"Meat & Fish",
            "type":"Retail Goods"
        }
    ],
    "sg:phone":"+32 3 711 11 33",
    "sg:postcode":"9140",
    "sg:province":"Oost-Vlaanderen",
    "sg:tags":[
        "fresh"
    ],
    "wof:name":"Vleeswarenfabriek Damar Nv",
    "wof:placetype":"venue"
},
  "geometry": {"coordinates":[4.187693119,51.1359596252],"type":"Point"}
}