{
  "type": "Feature",
  "properties": {
    "addr:full":"Chauss\u00c9e De L\u00b4europe 160 Couvin Namur 5660",
    "addr:housenumber":"160",
    "addr:postcode":"5660",
    "addr:street":"Chausse\u0301E De L\u00b4Europe",
    "iso:country":"BE",
    "sg:address":"Chauss\u00c9e De L\u00b4europe 160",
    "sg:city":"Couvin",
    "sg:classifiers":[
        {
            "category":"Cafe",
            "type":"Food & Drink"
        }
    ],
    "sg:phone":"+32 60 37 77 64",
    "sg:postcode":"5660",
    "sg:province":"Namur",
    "sg:tags":[
        "caf\u00e9s"
    ],
    "wof:name":"Caf\u00c9 De La Douane",
    "wof:placetype":"venue"
},
  "geometry": {"coordinates":[4.449698925,49.9533996582],"type":"Point"}
}