{
  "type": "Feature",
  "properties": {
    "addr:full":"Fruitmarkt 11 Hasselt Limburg 3500",
    "addr:housenumber":"11",
    "addr:postcode":"3500",
    "addr:street":"Fruitmarkt",
    "iso:country":"BE",
    "sg:address":"Fruitmarkt 11",
    "sg:city":"Hasselt",
    "sg:orig_category":"Location de v\u00eatements, chaussures and textiles",
    "sg:phone":"+32 11 22 32 17",
    "sg:postcode":"3500",
    "sg:province":"Limburg",
    "wof:name":"Sodermans",
    "wof:placetype":"venue"
},
  "geometry": {"coordinates":[5.3382501602,50.9300994873],"type":"Point"}
}