{
  "type": "Feature",
  "properties": {
    "addr:full":"Ruelle Des Beguines 4 Lasne-chapelle-saint-lambert Brabant Wallon 1380",
    "addr:housenumber":"4;1380",
    "addr:street":"Ruelle Des Beguines;Brabant Wallon",
    "iso:country":"BE",
    "sg:address":"Ruelle Des Beguines 4",
    "sg:city":"Lasne-chapelle-saint-lambert",
    "sg:classifiers":[
        {
            "category":"Home & Garden",
            "subcategory":"Home Furnishings",
            "type":"Retail Goods"
        }
    ],
    "sg:phone":"+32 2 652 27 47",
    "sg:postcode":"1380",
    "sg:province":"Brabant Wallon",
    "sg:tags":[
        "interior",
        "decoration"
    ],
    "wof:name":"Rouge De Chine",
    "wof:placetype":"venue"
},
  "geometry": {"coordinates":[4.4815487862,50.6845550537],"type":"Point"}
}