{
  "type": "Feature",
  "properties": {
    "addr:full":"Rivierstraat 97 Wevelgem West-Vlaanderen 8560",
    "addr:housenumber":"97",
    "addr:postcode":"8560",
    "addr:street":"Rivierstraat",
    "iso:country":"BE",
    "sg:address":"Rivierstraat 97",
    "sg:city":"Wevelgem",
    "sg:classifiers":[
        {
            "category":"Cafe",
            "type":"Food & Drink"
        }
    ],
    "sg:phone":"+32 56 41 99 80",
    "sg:postcode":"8560",
    "sg:province":"West-Vlaanderen",
    "sg:tags":[
        "caf\u00e9s"
    ],
    "wof:name":"Werner Bostyn-cannaert",
    "wof:placetype":"venue"
},
  "geometry": {"coordinates":[3.1940801144,50.8074493408],"type":"Point"}
}