{
  "type": "Feature",
  "properties": {
    "addr:full":"Avenue D' Esneux 216bb Esneux Li\u00e8ge 4130",
    "addr:housenumber":"216bb",
    "addr:postcode":"4130",
    "addr:street":"Avenue D ' Esneux",
    "iso:country":"BE",
    "sg:address":"Avenue D' Esneux 216bb",
    "sg:city":"Esneux",
    "sg:orig_category":"Kinderopvang",
    "sg:phone":"+32 4 388 31 41",
    "sg:postcode":"4130",
    "sg:province":"Li\u00e8ge",
    "wof:name":"Cr\u00c8che Les Marmousets",
    "wof:placetype":"venue"
},
  "geometry": {"coordinates":[5.5895581245,50.5499038696],"type":"Point"}
}