{
  "type": "Feature",
  "properties": {
    "addr:full":"Rue De La R\u00c9sistance 247 Remicourt Li\u00e8ge 4351",
    "addr:housenumber":"247",
    "addr:postcode":"4351",
    "addr:street":"Rue De La Re\u0301Sistance",
    "iso:country":"BE",
    "sg:address":"Rue De La R\u00c9sistance 247",
    "sg:city":"Remicourt",
    "sg:orig_category":"Loodgieterij, verwarming and sanitaire installaties",
    "sg:phone":"+32 19 54 54 32",
    "sg:postcode":"4351",
    "sg:province":"Li\u00e8ge",
    "wof:name":"Daniel Heller",
    "wof:placetype":"venue"
},
  "geometry": {"coordinates":[5.3358049393,50.7004585266],"type":"Point"}
}