{
  "type": "Feature",
  "properties": {
    "addr:full":"Hofeinde 21 Vosselaar Antwerpen 2350",
    "addr:housenumber":"21",
    "addr:postcode":"2350",
    "addr:street":"Hofeinde",
    "iso:country":"BE",
    "sg:address":"Hofeinde 21",
    "sg:city":"Vosselaar",
    "sg:classifiers":[
        {
            "category":"Wholesale",
            "subcategory":"Sporting Goods",
            "type":"Manufacturing & Wholesale Goods"
        }
    ],
    "sg:phone":"+32 14 61 12 60",
    "sg:postcode":"2350",
    "sg:province":"Antwerpen",
    "sg:tags":[
        "sport-",
        "kampeermateriaal"
    ],
    "wof:name":"Hcv",
    "wof:placetype":"venue"
},
  "geometry": {"coordinates":[4.8842978477,51.3153190613],"type":"Point"}
}