{
  "type": "Feature",
  "properties": {
    "iso:country":"BE",
    "sg:address":"Rue De Maubeuge 170",
    "sg:city":"Erquelinnes",
    "sg:orig_category":"Algemeen secundair onderwijs",
    "sg:phone":"+32 71 55 59 65",
    "sg:postcode":"6560",
    "sg:province":"Hainaut",
    "wof:name":"Inst.m\u00c9t.constr.& Envir.",
    "wof:placetype":"venue"
},
  "geometry": {"coordinates":[4.1094050407,50.3077392578],"type":"Point"}
}