{
  "type": "Feature",
  "properties": {
    "iso:country":"BE",
    "sg:address":"Schrijnwerkersstraat 21",
    "sg:city":"Hasselt",
    "sg:orig_category":"Bijouteries and horlogeries. R\u00e9parations d'horloges, montres and bijoux",
    "sg:phone":"+32 11 22 76 83",
    "sg:postcode":"3500",
    "sg:province":"Limburg",
    "wof:name":"Bart Bleukx",
    "wof:placetype":"venue"
},
  "geometry": {"coordinates":[5.3363060951,50.93201828],"type":"Point"}
}