{
  "type": "Feature",
  "properties": {
    "addr:full":"Kaasmarkt 30 Wemmel/wemmel Vlaams-Brabant 1780",
    "addr:housenumber":"30",
    "addr:postcode":"1780",
    "addr:street":"Kaasmarkt",
    "iso:country":"BE",
    "sg:address":"Kaasmarkt 30",
    "sg:city":"Wemmel/wemmel",
    "sg:orig_category":"Centres de relaxation and bien-\u00eatre. Instituts de beaut\u00e9. Parfumeries",
    "sg:phone":"+32 2 460 67 90",
    "sg:postcode":"1780",
    "sg:province":"Vlaams-Brabant",
    "wof:name":"Institut La Ragazza",
    "wof:placetype":"venue"
},
  "geometry": {"coordinates":[4.3005228043,50.9085922241],"type":"Point"}
}