{
  "type": "Feature",
  "properties": {
    "iso:country":"BE",
    "sg:address":"Dorpsplein 10",
    "sg:city":"Wevelgem",
    "sg:orig_category":"Brood, gebak and snoepgoed",
    "sg:phone":"+32 56 41 24 75",
    "sg:postcode":"8560",
    "sg:province":"West-Vlaanderen",
    "wof:name":"Alcor",
    "wof:placetype":"venue"
},
  "geometry": {"coordinates":[3.2042748928,50.8434486389],"type":"Point"}
}