{
  "type": "Feature",
  "properties": {
    "addr:full":"Overbekeplein 24 Kortrijk West-Vlaanderen 8500",
    "addr:housenumber":"24",
    "addr:postcode":"8500",
    "addr:street":"Overbekeplein",
    "iso:country":"BE",
    "sg:address":"Overbekeplein 24",
    "sg:city":"Kortrijk",
    "sg:orig_category":"Art and fournitures artistiques",
    "sg:phone":"+32 56 21 64 52",
    "sg:postcode":"8500",
    "sg:province":"West-Vlaanderen",
    "wof:name":"Pictural Art",
    "wof:placetype":"venue"
},
  "geometry": {"coordinates":[3.2688651085,50.8275794983],"type":"Point"}
}