{
  "type": "Feature",
  "properties": {
    "iso:country":"BE",
    "sg:address":"Kontichsesteenweg 83",
    "sg:city":"Aartselaar",
    "sg:orig_category":"Rundveehouders",
    "sg:phone":"+32 3 457 16 54",
    "sg:postcode":"2630",
    "sg:province":"Antwerpen",
    "wof:name":"Paul Van Deyck",
    "wof:placetype":"venue"
},
  "geometry": {"coordinates":[4.4008688927,51.1441230774],"type":"Point"}
}