{
  "type": "Feature",
  "properties": {
    "iso:country":"BE",
    "sg:address":"Avenue De La R\u00e9sistance 2",
    "sg:city":"Eugies",
    "sg:classifiers":[
        {
            "category":"Shopping",
            "subcategory":"Clothing, Apparel, & Fashions",
            "type":"Retail Goods"
        }
    ],
    "sg:phone":"+32 65 67 18 61",
    "sg:postcode":"7080",
    "sg:province":"Hainaut",
    "sg:tags":[
        "textile",
        "clothing",
        "clothes"
    ],
    "wof:name":"Quenon Urbain Sprl",
    "wof:placetype":"venue"
},
  "geometry": {"coordinates":[3.8731479645,50.393699646],"type":"Point"}
}