{
  "type": "Feature",
  "properties": {
    "iso:country":"BE",
    "sg:address":"Rue Du Beau-site 86",
    "sg:city":"Moeskroen/mouscron",
    "sg:orig_category":"Eclairage et \u00e9quipements du foyer. Meubles D\u00e9taillants, Am\u00e9nagement de B\u00e2timents et de Cuisines",
    "sg:phone":"+32 56 33 13 64",
    "sg:postcode":"7700",
    "sg:province":"Hainaut",
    "wof:name":"Lustrerie Du Parc",
    "wof:placetype":"venue"
},
  "geometry": {"coordinates":[3.2323200703,50.7400932312],"type":"Point"}
}