{
  "type": "Feature",
  "properties": {
    "addr:full":"Driemastenbaan 58 Wommelgem Antwerpen 2160",
    "addr:housenumber":"58",
    "addr:postcode":"2160",
    "addr:street":"Driemastenbaan",
    "iso:country":"BE",
    "sg:address":"Driemastenbaan 58",
    "sg:city":"Wommelgem",
    "sg:orig_category":"Caravans, aanhangwagens and opleggers",
    "sg:phone":"+32 3 353 93 53",
    "sg:postcode":"2160",
    "sg:province":"Antwerpen",
    "wof:name":"Fa. Lambrechts",
    "wof:placetype":"venue"
},
  "geometry": {"coordinates":[4.5323381424,51.1941871643],"type":"Point"}
}