{
  "type": "Feature",
  "properties": {
    "addr:full":"Rue Ainseveau 8 Viroinval (nismes) Namur 5670",
    "addr:housenumber":"8",
    "addr:postcode":"5670",
    "addr:street":"Rue Ainseveau",
    "iso:country":"BE",
    "sg:address":"Rue Ainseveau 8",
    "sg:city":"Viroinval (nismes)",
    "sg:classifiers":[
        {
            "category":"Building & Trades",
            "subcategory":"Pest Control",
            "type":"Services"
        }
    ],
    "sg:phone":"+32 60 31 13 60",
    "sg:postcode":"5670",
    "sg:province":"Namur",
    "sg:tags":[
        "painting",
        "contractor"
    ],
    "wof:name":"Laurent A",
    "wof:placetype":"venue"
},
  "geometry": {"coordinates":[4.546353817,50.0753288269],"type":"Point"}
}