{
  "type": "Feature",
  "properties": {
    "iso:country":"BE",
    "sg:address":"Hoogstraatsesteenweg 22",
    "sg:city":"Rijkevorsel",
    "sg:classifiers":[
        {
            "category":"Insurance",
            "subcategory":"Life Insurance",
            "type":"Services"
        }
    ],
    "sg:phone":"+32 3 314 58 14",
    "sg:postcode":"2310",
    "sg:province":"Antwerpen",
    "sg:tags":[
        "assurance"
    ],
    "wof:name":"K. Jacobs",
    "wof:placetype":"venue"
},
  "geometry": {"coordinates":[4.7603387833,51.3515090942],"type":"Point"}
}