{
  "type": "Feature",
  "properties": {
    "addr:full":"Pastoor De Bruynestraat 14 Hamme Oost-Vlaanderen 9220",
    "addr:housenumber":"14",
    "addr:postcode":"9220",
    "addr:street":"Pastoor De Bruynestraat",
    "iso:country":"BE",
    "sg:address":"Pastoor De Bruynestraat 14",
    "sg:city":"Hamme",
    "sg:orig_category":"Parfumeries",
    "sg:phone":"+32 52 48 30 36",
    "sg:postcode":"9220",
    "sg:province":"Oost-Vlaanderen",
    "wof:name":"Dirk Van Duysen",
    "wof:placetype":"venue"
},
  "geometry": {"coordinates":[4.1723232269,51.0463867188],"type":"Point"}
}