{
  "type": "Feature",
  "properties": {
    "addr:full":"Pieter De Nefstraat 4 Turnhout Antwerpen 2300",
    "addr:housenumber":"4",
    "addr:postcode":"2300",
    "addr:street":"Pieter De Nefstraat",
    "iso:country":"BE",
    "sg:address":"Pieter De Nefstraat 4",
    "sg:city":"Turnhout",
    "sg:orig_category":"Enseignement maternel and primaire",
    "sg:phone":"+32 14 41 17 02",
    "sg:postcode":"2300",
    "sg:province":"Antwerpen",
    "wof:name":"Vrije Lagere School",
    "wof:placetype":"venue"
},
  "geometry": {"coordinates":[4.9511399269,51.3212356567],"type":"Point"}
}