{
  "type": "Feature",
  "properties": {
    "iso:country":"BE",
    "sg:address":"Steenstraat 48",
    "sg:city":"Vilvoorde",
    "sg:orig_category":"Kapsalons",
    "sg:phone":"+32 2 267 03 07",
    "sg:postcode":"1800",
    "sg:province":"Vlaams-Brabant",
    "wof:name":"Coiffure Martha",
    "wof:placetype":"venue"
},
  "geometry": {"coordinates":[4.3755230904,50.9057693481],"type":"Point"}
}