{
  "type": "Feature",
  "properties": {
    "addr:full":"Rue Des Combattants 9 Dalhem (warsage) Li\u00e8ge 4608",
    "addr:housenumber":"9",
    "addr:postcode":"4608",
    "addr:street":"Rue Des Combattants",
    "iso:country":"BE",
    "sg:address":"Rue Des Combattants 9",
    "sg:city":"Dalhem (warsage)",
    "sg:classifiers":[
        {
            "category":"Bakery",
            "type":"Food & Drink"
        }
    ],
    "sg:phone":"+32 4 376 71 87",
    "sg:postcode":"4608",
    "sg:province":"Li\u00e8ge",
    "sg:tags":[
        "confectioner",
        "baker"
    ],
    "wof:name":"Biemar P",
    "wof:placetype":"venue"
},
  "geometry": {"coordinates":[5.7657580376,50.7364349365],"type":"Point"}
}