{
  "type": "Feature",
  "properties": {
    "iso:country":"BE",
    "sg:address":"Rue Jules M\u00c9lotte 15",
    "sg:city":"Remicourt",
    "sg:orig_category":"Enseignement maternel and primaire",
    "sg:phone":"+32 19 54 58 54",
    "sg:postcode":"4350",
    "sg:province":"Li\u00e8ge",
    "wof:name":"Ecole Fond. Communale",
    "wof:placetype":"venue"
},
  "geometry": {"coordinates":[5.3215122223,50.679901123],"type":"Point"}
}