{
  "type": "Feature",
  "properties": {
    "addr:full":"Hogenstraat 13 Zoutleeuw Vlaams-Brabant 3440",
    "addr:housenumber":"13",
    "addr:postcode":"3440",
    "addr:street":"Hogenstraat;Vlaams-Brabant",
    "iso:country":"BE",
    "sg:address":"Hogenstraat 13",
    "sg:city":"Zoutleeuw",
    "sg:orig_category":"Peinture. Rev\u00eatements pour sols and murs",
    "sg:phone":"+32 11 58 77 56",
    "sg:postcode":"3440",
    "sg:province":"Vlaams-Brabant",
    "wof:name":"Arthur Busselen",
    "wof:placetype":"venue"
},
  "geometry": {"coordinates":[5.0683221817,50.8821754456],"type":"Point"}
}