{
  "type": "Feature",
  "properties": {
    "iso:country":"BE",
    "sg:address":"Tiensesteenweg 58",
    "sg:city":"Sint-truiden",
    "sg:classifiers":[
        {
            "category":"Restaurant",
            "type":"Food & Drink"
        }
    ],
    "sg:phone":"+32 11 67 45 90",
    "sg:postcode":"3800",
    "sg:province":"Limburg",
    "wof:name":"Kreta",
    "wof:placetype":"venue"
},
  "geometry": {"coordinates":[5.1788649559,50.8149185181],"type":"Point"}
}