{
  "type": "Feature",
  "properties": {
    "addr:full":"Ober-emmels 24bb Sankt Vith/saint-vith Li\u00e8ge 4784",
    "addr:housenumber":"24bb",
    "addr:postcode":"4784",
    "addr:street":"Ober-Emmels",
    "iso:country":"BE",
    "sg:address":"Ober-emmels 24bb",
    "sg:city":"Sankt Vith/saint-vith",
    "sg:orig_category":"Meubles D\u00e9taillants, Am\u00e9nagement de B\u00e2timents et de Cuisines",
    "sg:phone":"+32 80 22 61 28",
    "sg:postcode":"4784",
    "sg:province":"Li\u00e8ge",
    "wof:name":"Nicolas Dhur",
    "wof:placetype":"venue"
},
  "geometry": {"coordinates":[6.0888299942,50.3008003235],"type":"Point"}
}