{
  "type": "Feature",
  "properties": {
    "iso:country":"BE",
    "sg:address":"Nekkerspoelstraat 21",
    "sg:city":"Mechelen",
    "sg:orig_category":"Biblioth\u00e8ques and archives publiques",
    "sg:phone":"+32 15 41 65 92",
    "sg:postcode":"2800",
    "sg:province":"Antwerpen",
    "wof:name":"Speel-o-theek Mechelen",
    "wof:placetype":"venue"
},
  "geometry": {"coordinates":[4.4911408424,51.0305328369],"type":"Point"}
}