{
  "type": "Feature",
  "properties": {
    "addr:full":"Chemise De Clairefontaine 83 Arlon Luxembourg 6700",
    "addr:housenumber":"83",
    "addr:postcode":"6700",
    "iso:country":"BE",
    "sg:address":"Chemise De Clairefontaine 83",
    "sg:city":"Arlon",
    "sg:orig_category":"Installatie van houten of kunststof schrijnwerk",
    "sg:phone":"+32 63 23 37 68",
    "sg:postcode":"6700",
    "sg:province":"Luxembourg",
    "wof:name":"Menulux",
    "wof:placetype":"venue"
},
  "geometry": {"coordinates":[5.8267188072,49.6755638123],"type":"Point"}
}