{
  "type": "Feature",
  "properties": {
    "iso:country":"BE",
    "sg:address":"Pauwengraaf 31 Box 1",
    "sg:city":"Maasmechelen (eisden)",
    "sg:orig_category":"Fiduciairies",
    "sg:phone":"+32 89 79 80 00",
    "sg:postcode":"3630",
    "sg:province":"Limburg",
    "wof:name":"Bakkersdiensten-accountxpress Nv",
    "wof:placetype":"venue"
},
  "geometry": {"coordinates":[5.6961350441,50.963848114],"type":"Point"}
}