{
  "type": "Feature",
  "properties": {
    "iso:country":"BE",
    "sg:address":"Ophovenstraat 95",
    "sg:city":"Maaseik",
    "sg:orig_category":"Benzinestations and brandstoffen",
    "sg:phone":"+32 89 86 40 34",
    "sg:postcode":"3680",
    "sg:province":"Limburg",
    "wof:name":"Craeghs Yvo",
    "wof:placetype":"venue"
},
  "geometry": {"coordinates":[5.791285038,51.0954208374],"type":"Point"}
}