{
  "type": "Feature",
  "properties": {
    "addr:full":"Rue Africaine 27 Bruxelles (saint-gilles) Bruxelles-Capitale 1060",
    "addr:housenumber":"27",
    "addr:postcode":"1060",
    "addr:street":"Rue Africaine",
    "iso:country":"BE",
    "sg:address":"Rue Africaine 27",
    "sg:city":"Bruxelles (saint-gilles)",
    "sg:classifiers":[
        {
            "category":"Education",
            "subcategory":"Special Training",
            "type":"Public Place"
        }
    ],
    "sg:phone":"+32 2 538 37 43",
    "sg:postcode":"1060",
    "sg:province":"Bruxelles-Capitale",
    "sg:tags":[
        "school",
        "language"
    ],
    "wof:name":"Tutti Frutti",
    "wof:placetype":"venue"
},
  "geometry": {"coordinates":[4.3571572304,50.8246040344],"type":"Point"}
}