{
  "type": "Feature",
  "properties": {
    "addr:full":"Rue De Mons 83 Braine-le-comte Hainaut 7090",
    "addr:housenumber":"83",
    "addr:postcode":"7090",
    "addr:street":"Rue De Mons",
    "iso:country":"BE",
    "sg:address":"Rue De Mons 83",
    "sg:city":"Braine-le-comte",
    "sg:orig_category":"M\u00e9decins and sp\u00e9cialistes",
    "sg:phone":"+32 67 55 41 21",
    "sg:postcode":"7090",
    "sg:province":"Hainaut",
    "wof:name":"Patrick Tennstedt",
    "wof:placetype":"venue"
},
  "geometry": {"coordinates":[4.1329369545,50.6073303223],"type":"Point"}
}