{
  "type": "Feature",
  "properties": {
    "addr:full":"Avenue De L'ecuyer 75 Rhode-saint-gen\u00e8se Vlaams-Brabant 1640",
    "addr:housenumber":"75",
    "addr:postcode":"1640",
    "addr:street":"Avenue De L'Ecuyer",
    "iso:country":"BE",
    "sg:address":"Avenue De L'ecuyer 75",
    "sg:city":"Rhode-saint-gen\u00e8se",
    "sg:classifiers":[
        {
            "category":"Real Estate",
            "subcategory":"Architect",
            "type":"Services"
        }
    ],
    "sg:phone":"+32 2 359 97 70",
    "sg:postcode":"1640",
    "sg:province":"Vlaams-Brabant",
    "wof:name":"Cauwe Th",
    "wof:placetype":"venue"
},
  "geometry": {"coordinates":[4.3985099792,50.7361412048],"type":"Point"}
}