{
  "type": "Feature",
  "properties": {
    "addr:full":"Nijlensesteenweg Nijlen (bevel) Antwerpen 2560",
    "addr:postcode":"2560",
    "addr:street":"Nijlensesteenweg",
    "iso:country":"BE",
    "sg:address":"Nijlensesteenweg",
    "sg:city":"Nijlen (bevel)",
    "sg:classifiers":[
        {
            "category":"Fast Food",
            "type":"Food & Drink"
        }
    ],
    "sg:phone":"+32 3 481 90 52",
    "sg:postcode":"2560",
    "sg:province":"Antwerpen",
    "sg:tags":[
        "fried",
        "stand",
        "potato"
    ],
    "wof:name":"Kievit",
    "wof:placetype":"venue"
},
  "geometry": {"coordinates":[4.6363101006,51.1744918823],"type":"Point"}
}