{
  "type": "Feature",
  "properties": {
    "iso:country":"BE",
    "sg:address":"Zandvoortstraat 7",
    "sg:city":"Mechelen",
    "sg:orig_category":"Film-, tv- and videoproductie",
    "sg:phone":"+32 15 20 06 16",
    "sg:postcode":"2800",
    "sg:province":"Antwerpen",
    "wof:name":"Rv Productions Studio",
    "wof:placetype":"venue"
},
  "geometry": {"coordinates":[4.4454889297,51.0504760742],"type":"Point"}
}