{
  "type": "Feature",
  "properties": {
    "iso:country":"BE",
    "sg:address":"Vronerodelaan 129",
    "sg:city":"Ukkel/uccle",
    "sg:orig_category":"Diverse bedrijfsbeheeradviesbureaus",
    "sg:phone":"+32 2 374 95 85",
    "sg:postcode":"1180",
    "sg:province":"Bruxelles-Capitale",
    "wof:name":"Delville Search Partners",
    "wof:placetype":"venue"
},
  "geometry": {"coordinates":[4.3781609535,50.7823143005],"type":"Point"}
}