{
  "type": "Feature",
  "properties": {
    "iso:country":"BE",
    "sg:address":"En Molinay 118",
    "sg:city":"Seraing",
    "sg:classifiers":[
        {
            "category":"Banks & Credit Unions",
            "subcategory":"Bank",
            "type":"Services"
        }
    ],
    "sg:phone":"+32 41374647",
    "sg:postcode":"4100",
    "sg:province":"Li\u00e8ge",
    "wof:name":"Caisse Nationale De, Cr\u00e9dit Professionnel",
    "wof:placetype":"venue"
},
  "geometry": {"coordinates":[5.5142908096,50.6063308716],"type":"Point"}
}