{
  "type": "Feature",
  "properties": {
    "addr:full":"Rue De L'enthousiasme 29 Anderlecht/anderlecht Bruxelles-Capitale 1070",
    "addr:housenumber":"29",
    "addr:postcode":"1070",
    "addr:street":"Rue De L'Enthousiasme",
    "iso:country":"BE",
    "sg:address":"Rue De L'enthousiasme 29",
    "sg:city":"Anderlecht/anderlecht",
    "sg:orig_category":"D\u00e9chets and d\u00e9bris Gr",
    "sg:phone":"+32 2 527 17 09",
    "sg:postcode":"1070",
    "sg:province":"Bruxelles-Capitale",
    "wof:name":"Auguste Vleminckx",
    "wof:placetype":"venue"
},
  "geometry": {"coordinates":[4.2734370232,50.8370552063],"type":"Point"}
}