{
  "type": "Feature",
  "properties": {
    "addr:full":"Rue Saint-paul 14 Binche Hainaut 7130",
    "addr:housenumber":"14",
    "addr:postcode":"7130",
    "addr:street":"Rue Saint-Paul",
    "iso:country":"BE",
    "sg:address":"Rue Saint-paul 14",
    "sg:city":"Binche",
    "sg:orig_category":"Biblioth\u00e8ques and archives publiques",
    "sg:phone":"+32 64 33 49 41",
    "sg:postcode":"7130",
    "sg:province":"Hainaut",
    "wof:name":"Biblioth\u00c8que Publique",
    "wof:placetype":"venue"
},
  "geometry": {"coordinates":[4.1662979126,50.4096870422],"type":"Point"}
}