{
  "type": "Feature",
  "properties": {
    "iso:country":"BE",
    "sg:address":"Rue Masui 147",
    "sg:city":"Schaarbeek/schaerbeek",
    "sg:orig_category":"Agences immobili\u00e8res",
    "sg:phone":"+32 2 201 12 14",
    "sg:postcode":"1030",
    "sg:province":"Bruxelles-Capitale",
    "wof:name":"New Juriconsulting Cy",
    "wof:placetype":"venue"
},
  "geometry": {"coordinates":[4.3626098633,50.8690299988],"type":"Point"}
}