{
  "type": "Feature",
  "properties": {
    "iso:country":"BE",
    "sg:address":"Klauwaartslaan 43 Box 13",
    "sg:city":"Grimbergen (strombeek-bever)",
    "sg:classifiers":[
        {
            "category":"Wholesale",
            "subcategory":"Books, Periodicals, & Newspapers",
            "type":"Manufacturing & Wholesale Goods"
        }
    ],
    "sg:phone":"+32 2 267 45 48",
    "sg:postcode":"1853",
    "sg:province":"Vlaams-Brabant",
    "sg:tags":[
        "hygiene",
        "paper",
        "-"
    ],
    "wof:name":"Sodima Benelux Nv",
    "wof:placetype":"venue"
},
  "geometry": {"coordinates":[4.3519310951,50.9022750854],"type":"Point"}
}