{
  "type": "Feature",
  "properties": {
    "addr:full":"Chauss\u00c9e Verte 165 Saint-georges-sur-meuse Li\u00e8ge 4470",
    "addr:housenumber":"165",
    "addr:postcode":"4470",
    "addr:street":"Chausse\u0301E Verte",
    "iso:country":"BE",
    "sg:address":"Chauss\u00c9e Verte 165",
    "sg:city":"Saint-georges-sur-meuse",
    "sg:orig_category":"Sportclubs",
    "sg:phone":"+32 4 259 67 26",
    "sg:postcode":"4470",
    "sg:province":"Li\u00e8ge",
    "wof:name":"Benjamins De Sur-les-bois",
    "wof:placetype":"venue"
},
  "geometry": {"coordinates":[5.3536500931,50.61510849],"type":"Point"}
}