{
  "type": "Feature",
  "properties": {
    "addr:full":"Rue De Nivelles 136 Braine-le-chateau Brabant Wallon 1440",
    "addr:housenumber":"136",
    "addr:postcode":"1440",
    "addr:street":"Rue De Nivelles;Brabant Wallon",
    "iso:country":"BE",
    "sg:address":"Rue De Nivelles 136",
    "sg:city":"Braine-le-chateau",
    "sg:classifiers":[
        {
            "category":"Cafe",
            "type":"Food & Drink"
        }
    ],
    "sg:phone":"+32 2 366 16 78",
    "sg:postcode":"1440",
    "sg:province":"Brabant Wallon",
    "sg:tags":[
        "caf\u00e9s"
    ],
    "wof:name":"Lux X.-rousseau N.",
    "wof:placetype":"venue"
},
  "geometry": {"coordinates":[4.2759442329,50.6721572876],"type":"Point"}
}