{
  "type": "Feature",
  "properties": {
    "addr:full":"Excelsiorlaan 3 Zaventem Vlaams-Brabant 1930",
    "addr:housenumber":"3",
    "addr:postcode":"1930",
    "addr:street":"Excelsiorlaan",
    "iso:country":"BE",
    "sg:address":"Excelsiorlaan 3",
    "sg:city":"Zaventem",
    "sg:classifiers":[
        {
            "category":"Banks & Credit Unions",
            "subcategory":"Bureau De Change",
            "type":"Services"
        }
    ],
    "sg:phone":"+32 2 715 89 89",
    "sg:postcode":"1930",
    "sg:province":"Vlaams-Brabant",
    "sg:tags":[
        "measuring",
        "control",
        "apparatus"
    ],
    "wof:name":"Tektronix Nv",
    "wof:placetype":"venue"
},
  "geometry": {"coordinates":[4.4566020966,50.8813362122],"type":"Point"}
}