{
  "type": "Feature",
  "properties": {
    "iso:country":"BE",
    "sg:address":"Rue Vacale 5",
    "sg:city":"Sprimont",
    "sg:classifiers":[
        {
            "category":"Building & Trades",
            "subcategory":"Electrical",
            "type":"Services"
        }
    ],
    "sg:phone":"+32 4 382 14 65",
    "sg:postcode":"4140",
    "sg:province":"Li\u00e8ge",
    "sg:tags":[
        "beam",
        "electron",
        "welding"
    ],
    "wof:name":"Soudobeam S.a.",
    "wof:placetype":"venue"
},
  "geometry": {"coordinates":[5.6766710281,50.504776001],"type":"Point"}
}