{
  "type": "Feature",
  "properties": {
    "addr:full":"Welvaartstraat 21 Olen Antwerpen 2250",
    "addr:housenumber":"21",
    "addr:postcode":"2250",
    "addr:street":"Welvaartstraat",
    "iso:country":"BE",
    "sg:address":"Welvaartstraat 21",
    "sg:city":"Olen",
    "sg:classifiers":[
        {
            "category":"Banks & Credit Unions",
            "subcategory":"Bank",
            "type":"Services"
        }
    ],
    "sg:phone":"+32 14 21 21 31",
    "sg:postcode":"2250",
    "sg:province":"Antwerpen",
    "sg:tags":[
        "savings-banks"
    ],
    "wof:name":"Huysmans Verzekeringen Bvba",
    "wof:placetype":"venue"
},
  "geometry": {"coordinates":[4.8995947838,51.1803703308],"type":"Point"}
}