{
  "type": "Feature",
  "properties": {
    "addr:full":"Zuidkaai 18 Izegem West-Vlaanderen 8870",
    "addr:housenumber":"18",
    "addr:postcode":"8870",
    "addr:street":"Zuidkaai",
    "iso:country":"BE",
    "sg:address":"Zuidkaai 18",
    "sg:city":"Izegem",
    "sg:orig_category":"Hout and afgeleiden Gh Houtbewerking and -behandeling IJzerwaren, bouw- and verfmaterialen",
    "sg:phone":"+32 51 31 78 77",
    "sg:postcode":"8870",
    "sg:province":"West-Vlaanderen",
    "wof:name":"Veroutiz",
    "wof:placetype":"venue"
},
  "geometry": {"coordinates":[3.2135500908,50.9226989746],"type":"Point"}
}