{
  "type": "Feature",
  "properties": {
    "addr:full":"Rue Du Merlo 6bb49 Ukkel/uccle Bruxelles-Capitale 1180",
    "addr:housenumber":"6bb49",
    "addr:postcode":"1180",
    "addr:street":"Rue Du Merlo;/",
    "iso:country":"BE",
    "sg:address":"Rue Du Merlo 6bb49",
    "sg:city":"Ukkel/uccle",
    "sg:orig_category":"Avocats and conseillers juridiques",
    "sg:phone":"+32 2 376 99 30",
    "sg:postcode":"1180",
    "sg:province":"Bruxelles-Capitale",
    "wof:name":"Jean-luc Barra",
    "wof:placetype":"venue"
},
  "geometry": {"coordinates":[4.3200850487,50.7987442017],"type":"Point"}
}