{
  "type": "Feature",
  "properties": {
    "addr:full":"Goubauln 26 Drongen Oost-Vlaanderen 9810",
    "addr:housenumber":"26",
    "addr:postcode":"9810",
    "addr:street":"Goubauln",
    "iso:country":"BE",
    "sg:address":"Goubauln 26",
    "sg:city":"Drongen",
    "sg:classifiers":[
        {
            "category":"Banks & Credit Unions",
            "subcategory":"Bank",
            "type":"Services"
        }
    ],
    "sg:phone":"+32 52 26 18 50",
    "sg:postcode":"9810",
    "sg:province":"Oost-Vlaanderen",
    "wof:name":"Famibank",
    "wof:placetype":"venue"
},
  "geometry": {"coordinates":[168.37223815920001,-46.3894195557],"type":"Point"}
}