{
  "type": "Feature",
  "properties": {
    "addr:full":"Denderbellestraat 152 Dendermonde Oost-Vlaanderen 9200",
    "addr:housenumber":"152",
    "addr:postcode":"9200",
    "addr:street":"Denderbellestraat;Oost-Vlaanderen",
    "iso:country":"BE",
    "sg:address":"Denderbellestraat 152",
    "sg:city":"Dendermonde",
    "sg:orig_category":"Zuivelproducten",
    "sg:phone":"+32 52 21 55 18",
    "sg:postcode":"9200",
    "sg:province":"Oost-Vlaanderen",
    "wof:name":"Dream-ice",
    "wof:placetype":"venue"
},
  "geometry": {"coordinates":[4.0940852165,51.0123825073],"type":"Point"}
}