{
  "type": "Feature",
  "properties": {
    "addr:full":"Kolvestraat 76 Brugge West-Vlaanderen 8000",
    "addr:housenumber":"76",
    "addr:postcode":"8000",
    "addr:street":"Kolvestraat",
    "iso:country":"BE",
    "sg:address":"Kolvestraat 76",
    "sg:city":"Brugge",
    "sg:orig_category":"Opel OK Qualit\u00e9 Occasion. Entretien and r\u00e9parations de voitures. V\u00e9hicules automobiles",
    "sg:phone":"+32 50 45 62 62",
    "sg:postcode":"8000",
    "sg:province":"West-Vlaanderen",
    "wof:name":"Garage Degroote",
    "wof:placetype":"venue"
},
  "geometry": {"coordinates":[3.2040560246,51.2430458069],"type":"Point"}
}