{
  "type": "Feature",
  "properties": {
    "iso:country":"BE",
    "sg:address":"Azalealaan 27",
    "sg:city":"Aartselaar",
    "sg:classifiers":[
        {
            "category":"Real Estate",
            "subcategory":"Architect",
            "type":"Services"
        }
    ],
    "sg:phone":"+32 3 887 83 60",
    "sg:postcode":"2630",
    "sg:province":"Antwerpen",
    "wof:name":"Depauw E",
    "wof:placetype":"venue"
},
  "geometry": {"coordinates":[4.3756361008,51.1412773132],"type":"Point"}
}