{
  "type": "Feature",
  "properties": {
    "addr:full":"Speeltuinlaan 12 Mortsel Antwerpen 2640",
    "addr:housenumber":"12",
    "addr:postcode":"2640",
    "addr:street":"Speeltuinlaan",
    "iso:country":"BE",
    "sg:address":"Speeltuinlaan 12",
    "sg:city":"Mortsel",
    "sg:classifiers":[
        {
            "category":"Health Services",
            "subcategory":"Doctor",
            "type":"Services"
        }
    ],
    "sg:phone":"+32 3 448 04 11",
    "sg:postcode":"2640",
    "sg:province":"Antwerpen",
    "sg:tags":[
        "medicinephysicians",
        "surgeon"
    ],
    "wof:name":"Dietlein G",
    "wof:placetype":"venue"
},
  "geometry": {"coordinates":[4.4493150711,51.1777000427],"type":"Point"}
}