{
  "type": "Feature",
  "properties": {
    "iso:country":"BE",
    "sg:address":"Nieuwe Weg 1 Box 3",
    "sg:city":"Zwijndrecht",
    "sg:classifiers":[
        {
            "category":"Professional",
            "type":"Services"
        }
    ],
    "sg:phone":"+32 3 210 97 40",
    "sg:postcode":"2070",
    "sg:province":"Antwerpen",
    "sg:tags":[
        "industrial",
        "work",
        "-",
        "maintenance"
    ],
    "wof:name":"Lemmens Services Nv",
    "wof:placetype":"venue"
},
  "geometry": {"coordinates":[4.319920063,51.2365455627],"type":"Point"}
}