{
  "type": "Feature",
  "properties": {
    "iso:country":"BE",
    "sg:address":"Avenue Saint-pancrace 3 Box 5",
    "sg:city":"Kraainem",
    "sg:classifiers":[
        {
            "category":"Professional",
            "subcategory":"Accounting & Tax Preparation",
            "type":"Services"
        }
    ],
    "sg:phone":"+32 2 721 38 88",
    "sg:postcode":"1950",
    "sg:province":"Vlaams-Brabant",
    "sg:tags":[
        "bookkeeper"
    ],
    "wof:name":"Tyssaen T",
    "wof:placetype":"venue"
},
  "geometry": {"coordinates":[4.4654860497,50.8617668152],"type":"Point"}
}