{
  "type": "Feature",
  "properties": {
    "iso:country":"BE",
    "sg:address":"Oude Markt 16",
    "sg:city":"Dessel",
    "sg:classifiers":[
        {
            "category":"Freight",
            "type":"Transportation"
        }
    ],
    "sg:phone":"+32 14 37 57 66",
    "sg:postcode":"2480",
    "sg:province":"Antwerpen",
    "sg:tags":[
        "-",
        "transport"
    ],
    "wof:name":"Borgers Transport",
    "wof:placetype":"venue"
},
  "geometry": {"coordinates":[5.1173958778,51.2371482849],"type":"Point"}
}