{
  "type": "Feature",
  "properties": {
    "addr:full":"Sportstraat 3 Waarschoot Oost-Vlaanderen 9950",
    "addr:housenumber":"3",
    "addr:postcode":"9950",
    "addr:street":"Sportstraat",
    "iso:country":"BE",
    "sg:address":"Sportstraat 3",
    "sg:city":"Waarschoot",
    "sg:orig_category":"Cafetarias and selfservice restaurants",
    "sg:phone":"+32 9 377 87 32",
    "sg:postcode":"9950",
    "sg:province":"Oost-Vlaanderen",
    "wof:name":"Sportcentrum Waarschoot (cafetaria)",
    "wof:placetype":"venue"
},
  "geometry": {"coordinates":[3.6096510887,51.1544952393],"type":"Point"}
}