{
  "type": "Feature",
  "properties": {
    "addr:full":"Philipstockstraat 18 Brugge West-Vlaanderen 8000",
    "addr:housenumber":"18",
    "addr:postcode":"8000",
    "addr:street":"Philipstockstraat",
    "iso:country":"BE",
    "sg:address":"Philipstockstraat 18",
    "sg:city":"Brugge",
    "sg:classifiers":[
        {
            "category":"Restaurant",
            "type":"Food & Drink"
        }
    ],
    "sg:phone":"+32 50 67 72 01",
    "sg:postcode":"8000",
    "sg:province":"West-Vlaanderen",
    "wof:name":"Perroquet Steackhouse",
    "wof:placetype":"venue"
},
  "geometry": {"coordinates":[3.225990057,51.2094612122],"type":"Point"}
}