{
  "type": "Feature",
  "properties": {
    "iso:country":"BE",
    "sg:address":"Rue De La Station 4",
    "sg:city":"Vielsalm",
    "sg:orig_category":"Vakantiedorpen",
    "sg:phone":"+32 80 21 75 52",
    "sg:postcode":"6690",
    "sg:province":"Luxembourg",
    "wof:name":"Les Doyards",
    "wof:placetype":"venue"
},
  "geometry": {"coordinates":[5.9100999832,50.2786102295],"type":"Point"}
}