{
  "type": "Feature",
  "properties": {
    "iso:country":"BE",
    "sg:address":"Avenue De Merode 99",
    "sg:city":"Rixensart",
    "sg:orig_category":"Agences immobili\u00e8res",
    "sg:phone":"+32 2 653 69 74",
    "sg:postcode":"1330",
    "sg:province":"Brabant Wallon",
    "wof:name":"Bureau Retraco",
    "wof:placetype":"venue"
},
  "geometry": {"coordinates":[4.5198559761,50.7117042542],"type":"Point"}
}