{
  "type": "Feature",
  "properties": {
    "addr:full":"Kanaalstraat 46 Hasselt Limburg 3511",
    "addr:housenumber":"46",
    "addr:postcode":"3511",
    "addr:street":"Kanaalstraat",
    "iso:country":"BE",
    "sg:address":"Kanaalstraat 46",
    "sg:city":"Hasselt",
    "sg:orig_category":"Artiesten and kunstenaars",
    "sg:phone":"+32 11 25 24 03",
    "sg:postcode":"3511",
    "sg:province":"Limburg",
    "wof:name":"Patrick Kuyckx",
    "wof:placetype":"venue"
},
  "geometry": {"coordinates":[5.2709841728,50.9668693542],"type":"Point"}
}