{
  "type": "Feature",
  "properties": {
    "addr:full":"Bedrijvenpark De Veert 1 Willebroek Antwerpen 2830",
    "addr:housenumber":"1",
    "addr:postcode":"2830",
    "addr:street":"Bedrijvenpark De Veert",
    "iso:country":"BE",
    "sg:address":"Bedrijvenpark De Veert 1",
    "sg:city":"Willebroek",
    "sg:classifiers":[
        {
            "category":"Wholesale",
            "subcategory":"Sporting Goods",
            "type":"Manufacturing & Wholesale Goods"
        }
    ],
    "sg:phone":"+32 3 866 42 42",
    "sg:postcode":"2830",
    "sg:province":"Antwerpen",
    "sg:tags":[
        "sport-",
        "kampeermateriaal"
    ],
    "wof:name":"Huis Bever",
    "wof:placetype":"venue"
},
  "geometry": {"coordinates":[4.355424881,51.0601081848],"type":"Point"}
}