{
  "type": "Feature",
  "properties": {
    "addr:full":"Sint-pietersstraat 19 Ieper (elverdinge) West-Vlaanderen 8906",
    "addr:housenumber":"19",
    "addr:postcode":"8906",
    "addr:street":"Sint-Pietersstraat",
    "iso:country":"BE",
    "sg:address":"Sint-pietersstraat 19",
    "sg:city":"Ieper (elverdinge)",
    "sg:classifiers":[
        {
            "category":"Shopping",
            "subcategory":"Pets & Pet Supplies",
            "type":"Retail Goods"
        }
    ],
    "sg:phone":"+32 57 33 39 38",
    "sg:postcode":"8906",
    "sg:province":"West-Vlaanderen",
    "sg:tags":[
        "aquarium",
        "accessory"
    ],
    "wof:name":"Sierviskwekerij 't Bos",
    "wof:placetype":"venue"
},
  "geometry": {"coordinates":[2.8168940544,50.8845558167],"type":"Point"}
}