{
  "type": "Feature",
  "properties": {
    "addr:full":"Rue De Gilly 161 Charleroi (couillet) Hainaut 6010",
    "addr:housenumber":"161",
    "addr:postcode":"6010",
    "addr:street":"Rue De Gilly",
    "iso:country":"BE",
    "sg:address":"Rue De Gilly 161",
    "sg:city":"Charleroi (couillet)",
    "sg:classifiers":[
        {
            "category":"Health Services",
            "subcategory":"Health Practitioner",
            "type":"Services"
        }
    ],
    "sg:phone":"+32 71 43 09 60",
    "sg:postcode":"6010",
    "sg:province":"Hainaut",
    "sg:tags":[
        "physiotherapist"
    ],
    "wof:name":"Ghislain J",
    "wof:placetype":"venue"
},
  "geometry": {"coordinates":[4.4710102081,50.3908576965],"type":"Point"}
}