{
  "type": "Feature",
  "properties": {
    "addr:full":"Statiestraat 29 Berchem Antwerpen 2600",
    "addr:housenumber":"29",
    "addr:postcode":"2600",
    "addr:street":"Statiestraat;Antwerpen",
    "iso:country":"BE",
    "sg:address":"Statiestraat 29",
    "sg:city":"Berchem",
    "sg:orig_category":"Centres de relaxation and bien-\u00eatre",
    "sg:phone":"+32 3 218 68 67",
    "sg:postcode":"2600",
    "sg:province":"Antwerpen",
    "wof:name":"Zonnecenter Oriental",
    "wof:placetype":"venue"
},
  "geometry": {"coordinates":[4.4245500565,51.1975021362],"type":"Point"}
}