{
  "type": "Feature",
  "properties": {
    "addr:full":"Beukendreef 16 Schoten Antwerpen 2900",
    "addr:housenumber":"16",
    "addr:postcode":"2900",
    "addr:street":"Beukendreef",
    "iso:country":"BE",
    "sg:address":"Beukendreef 16",
    "sg:city":"Schoten",
    "sg:orig_category":"Antiquit\u00e9s",
    "sg:phone":"+32 3 663 04 18",
    "sg:postcode":"2900",
    "sg:province":"Antwerpen",
    "wof:name":"J. Boogaerts",
    "wof:placetype":"venue"
},
  "geometry": {"coordinates":[4.5442109108,51.2996406555],"type":"Point"}
}