{
  "type": "Feature",
  "properties": {
    "iso:country":"BE",
    "sg:address":"Place De La Patrie 38",
    "sg:city":"Brussel/bruxelles",
    "sg:orig_category":"Foto-uitrusting",
    "sg:phone":"+32 2 215 17 06",
    "sg:postcode":"1030",
    "sg:province":"Bruxelles-Capitale",
    "wof:name":"Positif Ecran Studio Photo",
    "wof:placetype":"venue"
},
  "geometry": {"coordinates":[4.3918290138,50.8566589355],"type":"Point"}
}