{
  "type": "Feature",
  "properties": {
    "addr:full":"Torhoutsestraat 160 Oostkamp West-Vlaanderen 8020",
    "addr:housenumber":"160",
    "addr:postcode":"8020",
    "addr:street":"Torhoutsestraat",
    "iso:country":"BE",
    "sg:address":"Torhoutsestraat 160",
    "sg:city":"Oostkamp",
    "sg:orig_category":"Woningbouw",
    "sg:phone":"+32 50 27 64 14",
    "sg:postcode":"8020",
    "sg:province":"West-Vlaanderen",
    "wof:name":"Roger De Pestel",
    "wof:placetype":"venue"
},
  "geometry": {"coordinates":[3.1951870918,51.0865325928],"type":"Point"}
}