{
  "type": "Feature",
  "properties": {
    "addr:full":"Rue Robertson 16 Liege Li\u00e8ge 4020",
    "addr:housenumber":"16",
    "addr:postcode":"4020",
    "addr:street":"Rue Robertson",
    "iso:country":"BE",
    "sg:address":"Rue Robertson 16",
    "sg:city":"Liege",
    "sg:orig_category":"Animations diverses",
    "sg:phone":"+32 4 343 28 14",
    "sg:postcode":"4020",
    "sg:province":"Li\u00e8ge",
    "wof:name":"D'auria Tristan Magicien",
    "wof:placetype":"venue"
},
  "geometry": {"coordinates":[5.5837922096,50.6365776062],"type":"Point"}
}