{
  "type": "Feature",
  "properties": {
    "addr:full":"Avenue Blonden 50 - Bte 11 Liege-centre Li\u00e8ge 4000",
    "addr:housenumber":"50 bte 11",
    "addr:postcode":"4000",
    "addr:street":"Avenue Blonden;Liege-Centre Lie\u0300Ge",
    "iso:country":"BE",
    "sg:address":"Avenue Blonden 50 - Bte 11",
    "sg:city":"Liege-centre",
    "sg:orig_category":"Pr\u00eats hypoth\u00e9caires and cr\u00e9dits immobiliers. Cr\u00e9dit \u00e0 la consommation",
    "sg:phone":"+32 4 252 44 22",
    "sg:postcode":"4000",
    "sg:province":"Li\u00e8ge",
    "wof:name":"Cr\u00c9dit Plus",
    "wof:placetype":"venue"
},
  "geometry": {"coordinates":[6.2250900269,44.0888595581],"type":"Point"}
}