{
  "type": "Feature",
  "properties": {
    "iso:country":"BE",
    "sg:address":"Oude Bunders 1608",
    "sg:city":"Maasmechelen",
    "sg:classifiers":[
        {
            "category":"Retail",
            "subcategory":"Auto Repair",
            "type":"Services"
        }
    ],
    "sg:phone":"+32 89 76 48 27",
    "sg:postcode":"3630",
    "sg:province":"Limburg",
    "sg:tags":[
        "automobile-body"
    ],
    "wof:name":"Cardinaels Patrick",
    "wof:placetype":"venue"
},
  "geometry": {"coordinates":[5.7027478218,50.9504241943],"type":"Point"}
}