{
  "type": "Feature",
  "properties": {
    "addr:full":". Ans (groot) Li\u00e8ge 4430",
    "addr:postcode":"4430",
    "addr:street":"Groot Lie\u0300Ge",
    "iso:country":"BE",
    "sg:address":".",
    "sg:city":"Ans (groot)",
    "sg:orig_category":"Apotheken",
    "sg:phone":"+32 900 10 500",
    "sg:postcode":"4430",
    "sg:province":"Li\u00e8ge",
    "wof:name":"Apothekers Van Wacht",
    "wof:placetype":"venue"
},
  "geometry": {"coordinates":[5.5402550697,50.6528816223],"type":"Point"}
}