{
  "type": "Feature",
  "properties": {
    "iso:country":"BE",
    "sg:address":"Avenue De L'equinoxe 5 Box 8",
    "sg:city":"Wavre (limal)",
    "sg:classifiers":[
        {
            "category":"Professional",
            "subcategory":"Management & Consulting",
            "type":"Services"
        }
    ],
    "sg:phone":"+32 10 43 96 90",
    "sg:postcode":"1300",
    "sg:province":"Brabant Wallon",
    "sg:tags":[
        "consultant",
        "agency",
        "advertising"
    ],
    "wof:name":"Abcisse Design Scs",
    "wof:placetype":"venue"
},
  "geometry": {"coordinates":[4.5791578293,50.7018280029],"type":"Point"}
}