{
  "type": "Feature",
  "properties": {
    "addr:full":"Beekstraat 8 Avelgem West-Vlaanderen 8580",
    "addr:housenumber":"8",
    "addr:postcode":"8580",
    "addr:street":"Beekstraat",
    "iso:country":"BE",
    "sg:address":"Beekstraat 8",
    "sg:city":"Avelgem",
    "sg:classifiers":[
        {
            "category":"Arena",
            "subcategory":"Sports Club",
            "type":"Entertainment"
        }
    ],
    "sg:phone":"+32 56 64 70 21",
    "sg:postcode":"8580",
    "sg:province":"West-Vlaanderen",
    "sg:tags":[
        "terrain",
        "hors",
        "de",
        "installation",
        "sportifs"
    ],
    "wof:name":"K.v.k. Avelgem",
    "wof:placetype":"venue"
},
  "geometry": {"coordinates":[3.4475491047,50.7685203552],"type":"Point"}
}