{
  "type": "Feature",
  "properties": {
    "iso:country":"BE",
    "sg:address":"Stationstraat 197",
    "sg:city":"Ardooie",
    "sg:orig_category":"Elektrische installaties voor woningen HERSTELLING ELEKTRISCHE HUISHOUDAPPARATEN Huishoudapparaten, ",
    "sg:phone":"+32 51 74 44 53",
    "sg:postcode":"8850",
    "sg:province":"West-Vlaanderen",
    "wof:name":"Huis Sabbe",
    "wof:placetype":"venue"
},
  "geometry": {"coordinates":[3.2029500008,50.9885368347],"type":"Point"}
}