{
  "type": "Feature",
  "properties": {
    "iso:country":"BE",
    "sg:address":"Ganzendries 39",
    "sg:city":"Steenokkerzeel",
    "sg:orig_category":"Antiquit\u00e9s",
    "sg:phone":"+32 2 751 70 70",
    "sg:postcode":"1820",
    "sg:province":"Vlaams-Brabant",
    "wof:name":"Raphaella De Boeck",
    "wof:placetype":"venue"
},
  "geometry": {"coordinates":[4.4902238846,50.9285125732],"type":"Point"}
}