{
  "type": "Feature",
  "properties": {
    "iso:country":"BE",
    "sg:address":"Chauss\u00e9e De Renaix 96",
    "sg:city":"Lessines",
    "sg:classifiers":[
        {
            "category":"Banks & Credit Unions",
            "subcategory":"Investment Brokerage",
            "type":"Services"
        }
    ],
    "sg:phone":"+32 68 33 53 49",
    "sg:postcode":"7860",
    "sg:province":"Hainaut",
    "sg:tags":[
        "repair",
        "-",
        "installation",
        "sanitary",
        "article"
    ],
    "wof:name":"Gorts B",
    "wof:placetype":"venue"
},
  "geometry": {"coordinates":[3.8205389977,50.7133293152],"type":"Point"}
}