{
  "type": "Feature",
  "properties": {
    "addr:full":"Rue L\u00c9on-mignon 20 Li\u00c8ge Li\u00e8ge 4000",
    "addr:housenumber":"20",
    "addr:postcode":"4000",
    "addr:street":"Rue Le\u0301On-Mignon",
    "iso:country":"BE",
    "sg:address":"Rue L\u00c9on-mignon 20",
    "sg:city":"Li\u00c8ge",
    "sg:classifiers":[
        {
            "category":"Cafe",
            "type":"Food & Drink"
        }
    ],
    "sg:phone":"+32 4 222 07 75",
    "sg:postcode":"4000",
    "sg:province":"Li\u00e8ge",
    "sg:tags":[
        "caf\u00e9s"
    ],
    "wof:name":"Caf\u00c9 La Jungle",
    "wof:placetype":"venue"
},
  "geometry": {"coordinates":[5.5663781166,50.6457252502],"type":"Point"}
}