{
  "type": "Feature",
  "properties": {
    "iso:country":"BE",
    "sg:address":"Jozef Duthoystraat 65",
    "sg:city":"Waregem",
    "sg:orig_category":"HUISBRANDOLIE",
    "sg:phone":"+32 56 60 11 48",
    "sg:postcode":"8790",
    "sg:province":"West-Vlaanderen",
    "wof:name":"Willy Van Der Looven",
    "wof:placetype":"venue"
},
  "geometry": {"coordinates":[3.4214630127,50.8823699951],"type":"Point"}
}