{
  "type": "Feature",
  "properties": {
    "addr:full":"Schoolstraat 17c Aalst (nieuwerkerken) Oost-Vlaanderen 9320",
    "addr:housenumber":"17c",
    "addr:postcode":"9320",
    "addr:street":"Schoolstraat",
    "iso:country":"BE",
    "sg:address":"Schoolstraat 17c",
    "sg:city":"Aalst (nieuwerkerken)",
    "sg:classifiers":[
        {
            "category":"Health Services",
            "subcategory":"Hospital",
            "type":"Services"
        }
    ],
    "sg:phone":"+32 53 83 25 72",
    "sg:postcode":"9320",
    "sg:province":"Oost-Vlaanderen",
    "sg:tags":[
        "ambulance"
    ],
    "wof:name":"Aalst Ambulance-aalst Tax",
    "wof:placetype":"venue"
},
  "geometry": {"coordinates":[4.0553851128,50.9209976196],"type":"Point"}
}