{
  "type": "Feature",
  "properties": {
    "iso:country":"BE",
    "sg:address":"Route De Hautregard 81",
    "sg:city":"Theux",
    "sg:orig_category":"Dierenartsen",
    "sg:phone":"+32 87 37 64 37",
    "sg:postcode":"4910",
    "sg:province":"Li\u00e8ge",
    "wof:name":"Emile Lecluse",
    "wof:placetype":"venue"
},
  "geometry": {"coordinates":[5.7875380516,50.4863700867],"type":"Point"}
}