{
  "type": "Feature",
  "properties": {
    "addr:full":"Rue De Pont 32 Tournai Hainaut 7500",
    "addr:housenumber":"32",
    "addr:postcode":"7500",
    "addr:street":"Rue De Pont",
    "iso:country":"BE",
    "sg:address":"Rue De Pont 32",
    "sg:city":"Tournai",
    "sg:classifiers":[
        {
            "category":"Shopping",
            "subcategory":"Pharmacy",
            "type":"Retail Goods"
        }
    ],
    "sg:phone":"+32 69 22 44 33",
    "sg:postcode":"7500",
    "sg:province":"Hainaut",
    "sg:tags":[
        "store",
        "drug"
    ],
    "wof:name":"Warocquier",
    "wof:placetype":"venue"
},
  "geometry": {"coordinates":[3.3942220211,50.6075515747],"type":"Point"}
}