{
  "type": "Feature",
  "properties": {
    "iso:country":"BE",
    "sg:address":"Rue Du Monast\u00e8re 116",
    "sg:city":"Rixensart",
    "sg:classifiers":[
        {
            "category":"Professional",
            "subcategory":"Employment Agencies",
            "type":"Services"
        }
    ],
    "sg:phone":"+32 2 653 06 70",
    "sg:postcode":"1330",
    "sg:province":"Brabant Wallon",
    "sg:tags":[
        "-",
        "processing",
        "data"
    ],
    "wof:name":"Data +",
    "wof:placetype":"venue"
},
  "geometry": {"coordinates":[4.5303230286,50.6974983215],"type":"Point"}
}