{
  "type": "Feature",
  "properties": {
    "addr:full":"Vakenstraat 25 Rotselaar Vlaams-Brabant 3110",
    "addr:housenumber":"25",
    "addr:postcode":"3110",
    "addr:street":"Vakenstraat",
    "iso:country":"BE",
    "sg:address":"Vakenstraat 25",
    "sg:city":"Rotselaar",
    "sg:orig_category":"Services de Nettoyage and de D\u00e9sinfection. Plomberie, chauffage and installations sanitaires",
    "sg:phone":"+32 16 44 50 76",
    "sg:postcode":"3110",
    "sg:province":"Vlaams-Brabant",
    "wof:name":"Rene Serneels",
    "wof:placetype":"venue"
},
  "geometry": {"coordinates":[4.724105835,50.9635887146],"type":"Point"}
}