{
  "type": "Feature",
  "properties": {
    "addr:full":"Ster 4 Stavelot Li\u00e8ge 4970",
    "addr:housenumber":"4",
    "addr:postcode":"4970",
    "addr:street":"Ster",
    "iso:country":"BE",
    "sg:address":"Ster 4",
    "sg:city":"Stavelot",
    "sg:classifiers":[
        {
            "category":"Building & Trades",
            "subcategory":"Landscaping Services",
            "type":"Services"
        }
    ],
    "sg:phone":"+32 87 64 83 57",
    "sg:postcode":"4970",
    "sg:province":"Li\u00e8ge",
    "sg:tags":[
        "equipment",
        "swimming",
        "-",
        "pool",
        "contractor"
    ],
    "wof:name":"Piscine D'almar",
    "wof:placetype":"venue"
},
  "geometry": {"coordinates":[5.9015932083,50.3929214478],"type":"Point"}
}