{
  "type": "Feature",
  "properties": {
    "iso:country":"BE",
    "sg:address":"Grote Steenweg 127",
    "sg:city":"Lede",
    "sg:orig_category":"Centres de relaxation and bien-\u00eatre",
    "sg:phone":"+32 9 368 20 80",
    "sg:postcode":"9340",
    "sg:province":"Oost-Vlaanderen",
    "wof:name":"Sauna Favor",
    "wof:placetype":"venue"
},
  "geometry": {"coordinates":[3.8987050056,50.9578285217],"type":"Point"}
}