{
  "type": "Feature",
  "properties": {
    "addr:full":"Place De L'ecole Moyenne 1-1 Waremme Li\u00e8ge 4300",
    "addr:housenumber":"1-1",
    "addr:postcode":"4300",
    "addr:street":"Place De L'Ecole Moyenne",
    "iso:country":"BE",
    "sg:address":"Place De L'ecole Moyenne 1-1",
    "sg:city":"Waremme",
    "sg:classifiers":[
        {
            "category":"Banks & Credit Unions",
            "subcategory":"Financial Services",
            "type":"Services"
        }
    ],
    "sg:phone":"+32 19 32 36 05",
    "sg:postcode":"4300",
    "sg:province":"Li\u00e8ge",
    "sg:tags":[
        "financing"
    ],
    "wof:name":"Terrienne De Hesbaye (la)",
    "wof:placetype":"venue"
},
  "geometry": {"coordinates":[5.2557249069,50.6975975037],"type":"Point"}
}