{
  "type": "Feature",
  "properties": {
    "addr:full":"Rue De Gouy 24 Chapelle-lez-herlaimont Hainaut 7160",
    "addr:housenumber":"24",
    "addr:postcode":"7160",
    "addr:street":"Rue De Gouy",
    "iso:country":"BE",
    "sg:address":"Rue De Gouy 24",
    "sg:city":"Chapelle-lez-herlaimont",
    "sg:classifiers":[
        {
            "category":"Shopping",
            "subcategory":"Clothing, Apparel, & Fashions",
            "type":"Retail Goods"
        }
    ],
    "sg:phone":"+32 64 45 18 19",
    "sg:postcode":"7160",
    "sg:province":"Hainaut",
    "sg:tags":[
        "underwear",
        "lingerie",
        "-"
    ],
    "wof:name":"Sauna Institut",
    "wof:placetype":"venue"
},
  "geometry": {"coordinates":[4.2844319344,50.4708061218],"type":"Point"}
}