{
  "type": "Feature",
  "properties": {
    "addr:full":"Leopoldplein 9 De Haan West-Vlaanderen 8420",
    "addr:housenumber":"9",
    "addr:postcode":"8420",
    "addr:street":"Leopoldplein",
    "iso:country":"BE",
    "sg:address":"Leopoldplein 9",
    "sg:city":"De Haan",
    "sg:orig_category":"Pharmaciens",
    "sg:phone":"+32 59 23 36 52",
    "sg:postcode":"8420",
    "sg:province":"West-Vlaanderen",
    "wof:name":"Gerard Devriese",
    "wof:placetype":"venue"
},
  "geometry": {"coordinates":[3.0318779945,51.2742080688],"type":"Point"}
}