{
  "type": "Feature",
  "properties": {
    "addr:full":"Karel Boomstraat 44 Hoogstraten Antwerpen 2320",
    "addr:housenumber":"44",
    "addr:postcode":"2320",
    "addr:street":"Karel Boomstraat",
    "iso:country":"BE",
    "sg:address":"Karel Boomstraat 44",
    "sg:city":"Hoogstraten",
    "sg:orig_category":"Activit\u00e9s d\u00b4action sociale sans h\u00e9bergement",
    "sg:phone":"+32 3 314 68 68",
    "sg:postcode":"2320",
    "sg:province":"Antwerpen",
    "wof:name":"Jip",
    "wof:placetype":"venue"
},
  "geometry": {"coordinates":[4.7564477921,51.4031295776],"type":"Point"}
}