{
  "type": "Feature",
  "properties": {
    "iso:country":"BE",
    "sg:address":"Edmond Hanssenslaan 42",
    "sg:city":"Tervuren",
    "sg:orig_category":"Electrom\u00e9nager, t\u00e9l\u00e9visions and radios. R\u00e9parations d'appareils \u00e9lectrom\u00e9nagers",
    "sg:phone":"+32 2 767 49 51",
    "sg:postcode":"3080",
    "sg:province":"Vlaams-Brabant",
    "wof:name":"T.v. Shop Vandepoel G.",
    "wof:placetype":"venue"
},
  "geometry": {"coordinates":[4.5379800797,50.8394622803],"type":"Point"}
}