{
  "type": "Feature",
  "properties": {
    "addr:full":"Ganzenberg 6 Hamme Oost-Vlaanderen 9220",
    "addr:housenumber":"6",
    "addr:postcode":"9220",
    "addr:street":"Ganzenberg",
    "iso:country":"BE",
    "sg:address":"Ganzenberg 6",
    "sg:city":"Hamme",
    "sg:orig_category":"Enseignement maternel and primaire",
    "sg:phone":"+32 52 47 95 77",
    "sg:postcode":"9220",
    "sg:province":"Oost-Vlaanderen",
    "wof:name":"Vrije Basisschool",
    "wof:placetype":"venue"
},
  "geometry": {"coordinates":[4.1651101112,51.0475845337],"type":"Point"}
}