{
  "type": "Feature",
  "properties": {
    "addr:full":"Avenue Josse Goffin 62 Bruxelles (berchem-sainte-agathe) Bruxelles-Capitale 1082",
    "addr:housenumber":"62",
    "addr:postcode":"1082",
    "addr:street":"Avenue Josse Goffin",
    "iso:country":"BE",
    "sg:address":"Avenue Josse Goffin 62",
    "sg:city":"Bruxelles (berchem-sainte-agathe)",
    "sg:classifiers":[
        {
            "category":"Insurance",
            "subcategory":"Insurance Agent",
            "type":"Services"
        }
    ],
    "sg:phone":"+32 2 469 05 00",
    "sg:postcode":"1082",
    "sg:province":"Bruxelles-Capitale",
    "sg:tags":[
        "broker"
    ],
    "wof:name":"Moens J & C Bureau D'assurances & Pr\u00eats Hypoth\u00e9caires",
    "wof:placetype":"venue"
},
  "geometry": {"coordinates":[4.3001580238,50.8654785156],"type":"Point"}
}