{
  "type": "Feature",
  "properties": {
    "addr:full":"Roger Vandendriesscheln 18b1 Sint-pieters-woluwe/woluwe-saint-pierre Bruxelles-Capitale 1150",
    "addr:postcode":"1150",
    "addr:street":"/",
    "iso:country":"BE",
    "sg:address":"Roger Vandendriesscheln 18b1",
    "sg:city":"Sint-pieters-woluwe/woluwe-saint-pierre",
    "sg:orig_category":"Artsen and specialisten",
    "sg:phone":"+32 2 771 99 36",
    "sg:postcode":"1150",
    "sg:province":"Bruxelles-Capitale",
    "wof:name":"Robert Timmermans",
    "wof:placetype":"venue"
},
  "geometry": {"coordinates":[4.4143028259,50.8344230652],"type":"Point"}
}