{
  "type": "Feature",
  "properties": {
    "addr:full":"Passage De La Bourse 16 Charleroi Hainaut 6000",
    "addr:housenumber":"16",
    "addr:postcode":"6000",
    "addr:street":"Passage De La Bourse;Hainaut",
    "iso:country":"BE",
    "sg:address":"Passage De La Bourse 16",
    "sg:city":"Charleroi",
    "sg:classifiers":[
        {
            "category":"Personal",
            "subcategory":"Beauty Salon",
            "type":"Services"
        }
    ],
    "sg:phone":"+32 71 53 53 10",
    "sg:postcode":"6000",
    "sg:province":"Hainaut",
    "wof:name":"Fleur De Peau (a)",
    "wof:placetype":"venue"
},
  "geometry": {"coordinates":[4.4406170845,50.4071006775],"type":"Point"}
}