{
  "type": "Feature",
  "properties": {
    "addr:full":"Grote Heimelinkstraat 51 Sint-niklaas Oost-Vlaanderen 9100",
    "addr:housenumber":"51",
    "addr:postcode":"9100",
    "addr:street":"Grote Heimelinkstraat",
    "iso:country":"BE",
    "sg:address":"Grote Heimelinkstraat 51",
    "sg:city":"Sint-niklaas",
    "sg:classifiers":[
        {
            "category":"Communications",
            "subcategory":"Radio Station",
            "type":"Services"
        }
    ],
    "sg:phone":"+32 3 766 42 49",
    "sg:postcode":"9100",
    "sg:province":"Oost-Vlaanderen",
    "sg:tags":[
        "medium",
        "broker"
    ],
    "wof:name":"De Decker J-p",
    "wof:placetype":"venue"
},
  "geometry": {"coordinates":[4.1635928154,51.1756324768],"type":"Point"}
}