{
  "type": "Feature",
  "properties": {
    "iso:country":"BE",
    "sg:address":"De Peuthystraat 11",
    "sg:city":"Huldenberg",
    "sg:orig_category":"Banques and organismes de cr\u00e9dit",
    "sg:phone":"+32 2 687 81 95",
    "sg:postcode":"3040",
    "sg:province":"Vlaams-Brabant",
    "wof:name":"Kbc",
    "wof:placetype":"venue"
},
  "geometry": {"coordinates":[4.5828151703,50.7893218994],"type":"Point"}
}