{
  "type": "Feature",
  "properties": {
    "iso:country":"BE",
    "sg:address":"Sint-truidersteenweg 483",
    "sg:city":"Tongeren",
    "sg:orig_category":"Fruitteelt",
    "sg:phone":"+32 12 26 32 18",
    "sg:postcode":"3700",
    "sg:province":"Limburg",
    "wof:name":"Guido Vanvinckenroye",
    "wof:placetype":"venue"
},
  "geometry": {"coordinates":[5.4326448441,50.7797050476],"type":"Point"}
}