{
  "type": "Feature",
  "properties": {
    "iso:country":"BE",
    "sg:address":"Rue L\u00e9opold De Swaef 24",
    "sg:city":"Bruxelles (anderlecht)",
    "sg:orig_category":"Non-Classified Establishments",
    "sg:phone":"+32 2 523 78 93",
    "sg:postcode":"1070",
    "sg:province":"Bruxelles-Capitale",
    "wof:name":"Rausch Sprl",
    "wof:placetype":"venue"
},
  "geometry": {"coordinates":[4.3123011589,50.8458824158],"type":"Point"}
}