{
  "type": "Feature",
  "properties": {
    "addr:full":"Slagbaan 13 Oud-heverlee (haasrode) Vlaams-Brabant 3053",
    "addr:housenumber":"13",
    "addr:postcode":"3053",
    "addr:street":"Slagbaan",
    "iso:country":"BE",
    "sg:address":"Slagbaan 13",
    "sg:city":"Oud-heverlee (haasrode)",
    "sg:classifiers":[
        {
            "category":"Health Services",
            "subcategory":"Doctor",
            "type":"Services"
        }
    ],
    "sg:phone":"+32 16 40 13 33",
    "sg:postcode":"3053",
    "sg:province":"Vlaams-Brabant",
    "sg:tags":[
        "medicinephysicians",
        "surgeon"
    ],
    "wof:name":"Dom R",
    "wof:placetype":"venue"
},
  "geometry": {"coordinates":[4.7224941254,50.8278808594],"type":"Point"}
}