{
  "type": "Feature",
  "properties": {
    "addr:full":"Val Du Fi\u00e8rain 65 Pepinster (wegnez) Li\u00e8ge 4860",
    "addr:housenumber":"65",
    "addr:postcode":"4860",
    "addr:street":"Val Du Fie\u0300Rain",
    "iso:country":"BE",
    "sg:address":"Val Du Fi\u00e8rain 65",
    "sg:city":"Pepinster (wegnez)",
    "sg:classifiers":[
        {
            "category":"Building & Trades",
            "subcategory":"Cleaning & Sanitation",
            "type":"Services"
        }
    ],
    "sg:phone":"+32 87 46 89 00",
    "sg:postcode":"4860",
    "sg:province":"Li\u00e8ge",
    "sg:tags":[
        "blast"
    ],
    "wof:name":"Finck G",
    "wof:placetype":"venue"
},
  "geometry": {"coordinates":[5.8129172325,50.58618927],"type":"Point"}
}