{
  "type": "Feature",
  "properties": {
    "addr:full":"Lichterstraat 48 Puurs Antwerpen 2870",
    "addr:housenumber":"48",
    "addr:postcode":"2870",
    "addr:street":"Lichterstraat",
    "iso:country":"BE",
    "sg:address":"Lichterstraat 48",
    "sg:city":"Puurs",
    "sg:orig_category":"Producteurs de l\u00e9gumes",
    "sg:phone":"+32 3 889 19 50",
    "sg:postcode":"2870",
    "sg:province":"Antwerpen",
    "wof:name":"Eddy Maes",
    "wof:placetype":"venue"
},
  "geometry": {"coordinates":[4.3269901276,51.0583496094],"type":"Point"}
}