{
  "type": "Feature",
  "properties": {
    "addr:full":"Mechelseweg 328 Kapelle-op-den-bos Vlaams-Brabant 1880",
    "addr:housenumber":"328",
    "addr:postcode":"1880",
    "addr:street":"Mechelseweg",
    "iso:country":"BE",
    "sg:address":"Mechelseweg 328",
    "sg:city":"Kapelle-op-den-bos",
    "sg:classifiers":[
        {
            "category":"Professional",
            "subcategory":"Accounting & Tax Preparation",
            "type":"Services"
        }
    ],
    "sg:phone":"+32 15 71 23 04",
    "sg:postcode":"1880",
    "sg:province":"Vlaams-Brabant",
    "sg:tags":[
        "accountant"
    ],
    "wof:name":"Ooms G",
    "wof:placetype":"venue"
},
  "geometry": {"coordinates":[4.3724999428,51.0122146606],"type":"Point"}
}