{
  "type": "Feature",
  "properties": {
    "iso:country":"BE",
    "sg:address":"Stationsstraat 37",
    "sg:city":"Beringen (koersel)",
    "sg:classifiers":[
        {
            "category":"Cafe",
            "type":"Food & Drink"
        }
    ],
    "sg:phone":"+32 11 74 35 53",
    "sg:postcode":"3582",
    "sg:province":"Limburg",
    "sg:tags":[
        "snack-bars"
    ],
    "wof:name":"Tadim Snacks",
    "wof:placetype":"venue"
},
  "geometry": {"coordinates":[5.2223100662,51.0730438232],"type":"Point"}
}