{
  "type": "Feature",
  "properties": {
    "iso:country":"BE",
    "sg:address":"Koolskampstraat 5ba",
    "sg:city":"Lichtervelde",
    "sg:orig_category":"Services fun\u00e9raires",
    "sg:phone":"+32 51 72 54 49",
    "sg:postcode":"8810",
    "sg:province":"West-Vlaanderen",
    "wof:name":"Feryn",
    "wof:placetype":"venue"
},
  "geometry": {"coordinates":[3.1443140507,51.0274162292],"type":"Point"}
}