{
  "type": "Feature",
  "properties": {
    "iso:country":"BE",
    "sg:address":"Nieuwpoortsesteenweg 921",
    "sg:city":"Oostende",
    "sg:orig_category":"Brood, gebak and snoepgoed",
    "sg:phone":"+32 59 70 26 17",
    "sg:postcode":"8400",
    "sg:province":"West-Vlaanderen",
    "wof:name":"Pascal Vanhoutte",
    "wof:placetype":"venue"
},
  "geometry": {"coordinates":[2.8574399948,51.2012825012],"type":"Point"}
}