{
  "type": "Feature",
  "properties": {
    "addr:full":"Jordaenskaai 25 Box 2 Antwerpen Antwerpen 2000",
    "addr:housenumber":"25;2",
    "addr:postcode":"2000",
    "addr:street":"Jordaenskaai;Box",
    "iso:country":"BE",
    "sg:address":"Jordaenskaai 25 Box 2",
    "sg:city":"Antwerpen",
    "sg:classifiers":[
        {
            "category":"Professional",
            "type":"Services"
        }
    ],
    "sg:phone":"+32 3 232 82 38",
    "sg:postcode":"2000",
    "sg:province":"Antwerpen",
    "sg:tags":[
        "forwarding",
        "agency"
    ],
    "wof:name":"E H Harms Gmbh & Co",
    "wof:placetype":"venue"
},
  "geometry": {"coordinates":[4.3982281685,51.2225799561],"type":"Point"}
}