{
  "type": "Feature",
  "properties": {
    "iso:country":"BE",
    "sg:address":"Hoogstraat 9",
    "sg:city":"Oudenaarde",
    "sg:classifiers":[
        {
            "category":"Bars & Pubs",
            "type":"Food & Drink"
        }
    ],
    "sg:phone":"+32 55 31 54 28",
    "sg:postcode":"9700",
    "sg:province":"Oost-Vlaanderen",
    "sg:tags":[
        "tavern"
    ],
    "wof:name":"Olifant",
    "wof:placetype":"venue"
},
  "geometry": {"coordinates":[3.6034789085,50.8440551758],"type":"Point"}
}