{
  "type": "Feature",
  "properties": {
    "addr:full":". Harelbeke (groot) West-Vlaanderen 8530",
    "addr:postcode":"8530",
    "addr:street":"Groot West-Vlaanderen",
    "iso:country":"BE",
    "sg:address":".",
    "sg:city":"Harelbeke (groot)",
    "sg:orig_category":"Apotheken",
    "sg:phone":"+32 900 10 500",
    "sg:postcode":"8530",
    "sg:province":"West-Vlaanderen",
    "wof:name":"Apothekers Van Wacht",
    "wof:placetype":"venue"
},
  "geometry": {"coordinates":[3.3108050823,50.8567314148],"type":"Point"}
}