{
  "type": "Feature",
  "properties": {
    "addr:full":"Frankrijklei 53b6 Antwerpen Antwerpen 2000",
    "addr:housenumber":"53b6",
    "addr:postcode":"2000",
    "addr:street":"Frankrijklei",
    "iso:country":"BE",
    "sg:address":"Frankrijklei 53b6",
    "sg:city":"Antwerpen",
    "sg:orig_category":"Tijdelijke werkgelegenheid and uitzendkantoren",
    "sg:phone":"+32 3 224 80 80",
    "sg:postcode":"2000",
    "sg:province":"Antwerpen",
    "wof:name":"Plus Uitzendkrachten",
    "wof:placetype":"venue"
},
  "geometry": {"coordinates":[4.4147491455,51.2161483765],"type":"Point"}
}