{
  "type": "Feature",
  "properties": {
    "iso:country":"BE",
    "sg:address":"Ninovesteenweg 121",
    "sg:city":"Aalst (groot)",
    "sg:classifiers":[
        {
            "category":"Health Services",
            "subcategory":"Nursing And Care Facility",
            "type":"Services"
        }
    ],
    "sg:phone":"+32 53 82 52 70",
    "sg:postcode":"9320",
    "sg:province":"Oost-Vlaanderen",
    "sg:tags":[
        "public"
    ],
    "wof:name":"Ocmw Aalst Rusthuis De Hopperank",
    "wof:placetype":"venue"
},
  "geometry": {"coordinates":[4.0553851128,50.9209976196],"type":"Point"}
}