{
  "type": "Feature",
  "properties": {
    "iso:country":"BE",
    "sg:address":"Barri\u00e8re D'aubreux 2",
    "sg:city":"Estinnes (rouveroy)",
    "sg:classifiers":[
        {
            "category":"Travel",
            "subcategory":"Hotels & Motels",
            "type":"Entertainment"
        }
    ],
    "sg:phone":"+32 64 77 12 61",
    "sg:postcode":"7120",
    "sg:province":"Hainaut",
    "wof:name":"Hotel Les Ramiers",
    "wof:placetype":"venue"
},
  "geometry": {"coordinates":[4.0862212181,50.3403968811],"type":"Point"}
}