{
  "type": "Feature",
  "properties": {
    "iso:country":"BE",
    "sg:address":"Rector De Ramstraat 80",
    "sg:city":"Nijlen",
    "sg:classifiers":[
        {
            "category":"Real Estate",
            "subcategory":"Architect",
            "type":"Services"
        }
    ],
    "sg:phone":"+32 3 481 99 80",
    "sg:postcode":"2560",
    "sg:province":"Antwerpen",
    "wof:name":"Yskout P",
    "wof:placetype":"venue"
},
  "geometry": {"coordinates":[4.6784968376,51.1585044861],"type":"Point"}
}