{
  "type": "Feature",
  "properties": {
    "addr:full":"Avenue De L'industrie 11 P.i. Du Hain Braine-l'alleud Brabant Wallon 1420",
    "addr:housenumber":"11",
    "addr:postcode":"1420",
    "addr:street":"Avenue De L'Industrie;P.I. Du Hain",
    "iso:country":"BE",
    "sg:address":"Avenue De L'industrie 11 P.i. Du Hain",
    "sg:city":"Braine-l'alleud",
    "sg:classifiers":[
        {
            "category":"Health Services",
            "subcategory":"Medical Lab",
            "type":"Services"
        }
    ],
    "sg:phone":"+32 2 384 60 80",
    "sg:postcode":"1420",
    "sg:province":"Brabant Wallon",
    "sg:tags":[
        "chemical",
        "pharmaceutical",
        "pharmacy"
    ],
    "wof:name":"Bournonville Pharma Sa",
    "wof:placetype":"venue"
},
  "geometry": {"coordinates":[-0.7004899979,47.369140625],"type":"Point"}
}