{
  "type": "Feature",
  "properties": {
    "addr:full":"Dorp 70 Herselt Antwerpen 2230",
    "addr:housenumber":"70",
    "addr:postcode":"2230",
    "addr:street":"Dorp",
    "iso:country":"BE",
    "sg:address":"Dorp 70",
    "sg:city":"Herselt",
    "sg:orig_category":"Boissons",
    "sg:phone":"+32 14 54 68 00",
    "sg:postcode":"2230",
    "sg:province":"Antwerpen",
    "wof:name":"Verbruggen",
    "wof:placetype":"venue"
},
  "geometry": {"coordinates":[4.8836507797,51.05443573],"type":"Point"}
}