{
  "type": "Feature",
  "properties": {
    "addr:full":"Jan Mioenstraat 2 Kortemark West-Vlaanderen 8610",
    "addr:housenumber":"2",
    "addr:postcode":"8610",
    "addr:street":"Mioenstraat",
    "iso:country":"BE",
    "sg:address":"Jan Mioenstraat 2",
    "sg:city":"Kortemark",
    "sg:orig_category":"Entretien and r\u00e9parations de voitures",
    "sg:phone":"+32 51 56 92 91",
    "sg:postcode":"8610",
    "sg:province":"West-Vlaanderen",
    "wof:name":"Allan Pollet",
    "wof:placetype":"venue"
},
  "geometry": {"coordinates":[3.0282940865,51.0166816711],"type":"Point"}
}