{
  "type": "Feature",
  "properties": {
    "addr:full":"Rue Du B\u00e9guinage 14 Bruxelles Bruxelles-Capitale 1000",
    "addr:housenumber":"14",
    "addr:postcode":"1000",
    "addr:street":"Rue Du Be\u0301Guinage",
    "iso:country":"BE",
    "sg:address":"Rue Du B\u00e9guinage 14",
    "sg:city":"Bruxelles",
    "sg:classifiers":[
        {
            "category":"Professional",
            "type":"Services"
        }
    ],
    "sg:phone":"+32 2 218 71 38",
    "sg:postcode":"1000",
    "sg:province":"Bruxelles-Capitale",
    "sg:tags":[
        "entertainer"
    ],
    "wof:name":"Raes E",
    "wof:placetype":"venue"
},
  "geometry": {"coordinates":[4.3493099213,50.8528213501],"type":"Point"}
}