{
  "type": "Feature",
  "properties": {
    "addr:full":"Gentsestraat 1bc Aalst Oost-Vlaanderen 9300",
    "addr:housenumber":"1bc",
    "addr:postcode":"9300",
    "addr:street":"Gentsestraat",
    "iso:country":"BE",
    "sg:address":"Gentsestraat 1bc",
    "sg:city":"Aalst",
    "sg:orig_category":"Equipement photographique. Location de cassettes vid\u00e9o and audio",
    "sg:phone":"+32 53 78 24 14",
    "sg:postcode":"9300",
    "sg:province":"Oost-Vlaanderen",
    "wof:name":"Hollywood Videotheek",
    "wof:placetype":"venue"
},
  "geometry": {"coordinates":[4.0323400497,50.9384994507],"type":"Point"}
}