{
  "type": "Feature",
  "properties": {
    "iso:country":"BE",
    "sg:address":"Eindgracht 3",
    "sg:city":"Genk",
    "sg:classifiers":[
        {
            "category":"Personal",
            "subcategory":"Beauty Salon",
            "type":"Services"
        }
    ],
    "sg:phone":"+32 89 35 45 83",
    "sg:postcode":"3600",
    "sg:province":"Limburg",
    "sg:tags":[
        "de",
        "coiffure"
    ],
    "wof:name":"Roland Coiffure",
    "wof:placetype":"venue"
},
  "geometry": {"coordinates":[5.4948329926,50.963924408],"type":"Point"}
}