{
  "type": "Feature",
  "properties": {
    "addr:full":"Stationsstraat 33 Lanaken Limburg 3620",
    "addr:housenumber":"33",
    "addr:postcode":"3620",
    "addr:street":"Stationsstraat",
    "iso:country":"BE",
    "sg:address":"Stationsstraat 33",
    "sg:city":"Lanaken",
    "sg:classifiers":[
        {
            "category":"Food & Beverages",
            "subcategory":"Chocolate",
            "type":"Retail Goods"
        }
    ],
    "sg:phone":"+32 89 71 38 70",
    "sg:postcode":"3620",
    "sg:province":"Limburg",
    "sg:tags":[
        "confectionery",
        "-"
    ],
    "wof:name":"Leonidas Pralines",
    "wof:placetype":"venue"
},
  "geometry": {"coordinates":[5.6502108574,50.8883018494],"type":"Point"}
}