{
  "type": "Feature",
  "properties": {
    "addr:full":"Rue Des Montenees 7 Marche-en-famenne Luxembourg 6900",
    "addr:housenumber":"7",
    "addr:postcode":"6900",
    "addr:street":"Rue Des Montenees",
    "iso:country":"BE",
    "sg:address":"Rue Des Montenees 7",
    "sg:city":"Marche-en-famenne",
    "sg:orig_category":"Installatie van houten of kunststof schrijnwerk",
    "sg:phone":"+32 84 31 13 09",
    "sg:postcode":"6900",
    "sg:province":"Luxembourg",
    "wof:name":"Thierry Laguesse",
    "wof:placetype":"venue"
},
  "geometry": {"coordinates":[5.3430151939,50.2273483276],"type":"Point"}
}