{
  "type": "Feature",
  "properties": {
    "addr:full":"Grauwe Broedersstraat 39 Diksmuide West-Vlaanderen 8600",
    "addr:housenumber":"39",
    "addr:postcode":"8600",
    "addr:street":"Grauwe Broedersstraat",
    "iso:country":"BE",
    "sg:address":"Grauwe Broedersstraat 39",
    "sg:city":"Diksmuide",
    "sg:orig_category":"Activit\u00e9s r\u00e9cr\u00e9atives diverses",
    "sg:phone":"+32 51 50 14 48",
    "sg:postcode":"8600",
    "sg:province":"West-Vlaanderen",
    "wof:name":"Postzegelclub Edelweiss",
    "wof:placetype":"venue"
},
  "geometry": {"coordinates":[2.8688359261,51.036819458],"type":"Point"}
}