{
  "type": "Feature",
  "properties": {
    "iso:country":"BE",
    "sg:address":"Dr. Vanderhoeydonckstr. 56",
    "sg:city":"Lummen",
    "sg:orig_category":"Artsen and specialisten",
    "sg:phone":"+32 13 53 12 14",
    "sg:postcode":"3560",
    "sg:province":"Limburg",
    "wof:name":"Consultatiebur.jonge Kind",
    "wof:placetype":"venue"
},
  "geometry": {"coordinates":[5.1999998093,50.9850273132],"type":"Point"}
}