{
  "type": "Feature",
  "properties": {
    "iso:country":"BE",
    "sg:address":"Markt 26",
    "sg:city":"Laakdal (forest)",
    "sg:orig_category":"Newspapers, magazines, periodicals - Distribution",
    "sg:phone":"+32 13 67 19 74",
    "sg:postcode":"2430",
    "sg:province":"Antwerpen",
    "wof:name":"Daka",
    "wof:placetype":"venue"
},
  "geometry": {"coordinates":[5.0213799477,51.0807304382],"type":"Point"}
}