{
  "type": "Feature",
  "properties": {
    "addr:full":"Medelaar 75 Zoersel Antwerpen 2980",
    "addr:housenumber":"75",
    "addr:postcode":"2980",
    "addr:street":"Medelaar",
    "iso:country":"BE",
    "sg:address":"Medelaar 75",
    "sg:city":"Zoersel",
    "sg:orig_category":"Transports routiers de marchandises",
    "sg:phone":"+32 3 385 04 34",
    "sg:postcode":"2980",
    "sg:province":"Antwerpen",
    "wof:name":"J.r.",
    "wof:placetype":"venue"
},
  "geometry": {"coordinates":[4.6544299126,51.2543907166],"type":"Point"}
}