{
  "type": "Feature",
  "properties": {
    "addr:full":"Kalenberg 11 Lubbeek Vlaams-Brabant 3210",
    "addr:housenumber":"11",
    "addr:postcode":"3210",
    "addr:street":"Kalenberg",
    "iso:country":"BE",
    "sg:address":"Kalenberg 11",
    "sg:city":"Lubbeek",
    "sg:classifiers":[
        {
            "category":"Professional",
            "type":"Services"
        }
    ],
    "sg:phone":"+32 16 62 04 80",
    "sg:postcode":"3210",
    "sg:province":"Vlaams-Brabant",
    "sg:tags":[
        "industrial",
        "automation"
    ],
    "wof:name":"J L Systems Bvba",
    "wof:placetype":"venue"
},
  "geometry": {"coordinates":[4.8470802307,50.8669166565],"type":"Point"}
}