{
  "type": "Feature",
  "properties": {
    "addr:full":"Beverstraat 3 Herzele (sint-antelinks) Oost-Vlaanderen 9550",
    "addr:housenumber":"3",
    "addr:postcode":"9550",
    "addr:street":"Beverstraat;Sint-Antelinks Oost-Vlaanderen",
    "iso:country":"BE",
    "sg:address":"Beverstraat 3",
    "sg:city":"Herzele (sint-antelinks)",
    "sg:classifiers":[
        {
            "category":"Communications",
            "subcategory":"Film & Video Production",
            "type":"Services"
        }
    ],
    "sg:phone":"+32 54 50 18 59",
    "sg:postcode":"9550",
    "sg:province":"Oost-Vlaanderen",
    "sg:tags":[
        "realisation",
        "-"
    ],
    "wof:name":"Blue Cam Bvba",
    "wof:placetype":"venue"
},
  "geometry": {"coordinates":[3.9204990864,50.8406524658],"type":"Point"}
}