{
  "type": "Feature",
  "properties": {
    "addr:full":"Zondereigen 98 Baarle-hertog Antwerpen 2387",
    "addr:housenumber":"98",
    "addr:postcode":"2387",
    "addr:street":"Zondereigen",
    "iso:country":"BE",
    "sg:address":"Zondereigen 98",
    "sg:city":"Baarle-hertog",
    "sg:orig_category":"Fruitteelt",
    "sg:phone":"+32 14 63 35 54",
    "sg:postcode":"2387",
    "sg:province":"Antwerpen",
    "wof:name":"Josephus Verheyen",
    "wof:placetype":"venue"
},
  "geometry": {"coordinates":[4.8772640228,51.4090995789],"type":"Point"}
}