{
  "type": "Feature",
  "properties": {
    "addr:full":"Grote Snijdersstraat 115 Lebbeke Oost-Vlaanderen 9280",
    "addr:housenumber":"115",
    "addr:postcode":"9280",
    "addr:street":"Grote Snijdersstraat",
    "iso:country":"BE",
    "sg:address":"Grote Snijdersstraat 115",
    "sg:city":"Lebbeke",
    "sg:classifiers":[
        {
            "category":"Retail",
            "subcategory":"Animal Services",
            "type":"Services"
        }
    ],
    "sg:phone":"+32 476 21 56 61",
    "sg:postcode":"9280",
    "sg:province":"Oost-Vlaanderen",
    "sg:tags":[
        "farrier"
    ],
    "wof:name":"De Hauwere G",
    "wof:placetype":"venue"
},
  "geometry": {"coordinates":[4.1477599144,51.0018539429],"type":"Point"}
}