{
  "type": "Feature",
  "properties": {
    "addr:full":"Chauss\u00e9e D'antoing 46 Tournai Hainaut 7500",
    "addr:housenumber":"46",
    "addr:postcode":"7500",
    "addr:street":"Chausse\u0301E D'Antoing",
    "iso:country":"BE",
    "sg:address":"Chauss\u00e9e D'antoing 46",
    "sg:city":"Tournai",
    "sg:classifiers":[
        {
            "category":"Health Services",
            "subcategory":"Health Practitioner",
            "type":"Services"
        }
    ],
    "sg:phone":"+32 69 22 28 13",
    "sg:postcode":"7500",
    "sg:province":"Hainaut",
    "sg:tags":[
        "physiotherapist"
    ],
    "wof:name":"Carpreau P",
    "wof:placetype":"venue"
},
  "geometry": {"coordinates":[3.4029359818,50.5976257324],"type":"Point"}
}