{
  "type": "Feature",
  "properties": {
    "iso:country":"BE",
    "sg:address":"Rue De Boneffe 40",
    "sg:city":"Orp-jauche",
    "sg:orig_category":"Rev\u00eatements pour sols and murs",
    "sg:phone":"+32 81 87 87 63",
    "sg:postcode":"1350",
    "sg:province":"Brabant Wallon",
    "wof:name":"Rudy Wellekens",
    "wof:placetype":"venue"
},
  "geometry": {"coordinates":[4.9603328705,50.6544342041],"type":"Point"}
}