{
  "type": "Feature",
  "properties": {
    "iso:country":"BE",
    "sg:address":"Turfweg 5",
    "sg:city":"Tremelo",
    "sg:orig_category":"Slagers",
    "sg:phone":"+32 16 53 15 76",
    "sg:postcode":"3128",
    "sg:province":"Vlaams-Brabant",
    "wof:name":"Kippenhoekje",
    "wof:placetype":"venue"
},
  "geometry": {"coordinates":[4.7485589981,50.9955329895],"type":"Point"}
}