{
  "type": "Feature",
  "properties": {
    "addr:full":"Hulleken 10 Evergem Oost-Vlaanderen 9940",
    "addr:housenumber":"10",
    "addr:postcode":"9940",
    "addr:street":"Hulleken;Oost-Vlaanderen",
    "iso:country":"BE",
    "sg:address":"Hulleken 10",
    "sg:city":"Evergem",
    "sg:classifiers":[
        {
            "category":"Home & Garden",
            "subcategory":"Home Furnishings",
            "type":"Retail Goods"
        }
    ],
    "sg:phone":"+32 9 357 31 05",
    "sg:postcode":"9940",
    "sg:province":"Oost-Vlaanderen",
    "sg:tags":[
        "-",
        "furniture"
    ],
    "wof:name":"Sleepshop",
    "wof:placetype":"venue"
},
  "geometry": {"coordinates":[3.6819419861,51.1195335388],"type":"Point"}
}