{
  "type": "Feature",
  "properties": {
    "iso:country":"BE",
    "sg:address":"Barri\u00c8re De Fer 51",
    "sg:city":"Spiere-helkijn/espierres-helchin",
    "sg:orig_category":"Supermarch\u00e9s",
    "sg:phone":"+32 56 45 60 60",
    "sg:postcode":"8587",
    "sg:province":"West-Vlaanderen",
    "wof:name":"Gb Contact",
    "wof:placetype":"venue"
},
  "geometry": {"coordinates":[3.3305530548,50.7264633179],"type":"Point"}
}