{
  "type": "Feature",
  "properties": {
    "iso:country":"BE",
    "sg:address":"Cours De Troisfontaines 31",
    "sg:city":"Ottignies-louvain-la-neuve (louvain-la-neuve)",
    "sg:classifiers":[
        {
            "category":"Social Services",
            "type":"Services"
        }
    ],
    "sg:phone":"+32 10 45 12 02",
    "sg:postcode":"1348",
    "sg:province":"Brabant Wallon",
    "wof:name":"Centre De Planning Familial Aimer A Louvain-la-neuve",
    "wof:placetype":"venue"
},
  "geometry": {"coordinates":[4.6207227707,50.6766777039],"type":"Point"}
}