{
  "type": "Feature",
  "properties": {
    "addr:full":"Rue D'albroux 9 Ramillies Brabant Wallon 1367",
    "addr:housenumber":"9",
    "addr:postcode":"1367",
    "addr:street":"Rue D'Albroux",
    "iso:country":"BE",
    "sg:address":"Rue D'albroux 9",
    "sg:city":"Ramillies",
    "sg:orig_category":"Installatie van houten of kunststof schrijnwerk",
    "sg:phone":"+32 81 87 83 03",
    "sg:postcode":"1367",
    "sg:province":"Brabant Wallon",
    "wof:name":"G. Delatte",
    "wof:placetype":"venue"
},
  "geometry": {"coordinates":[4.8680419922,50.6298942566],"type":"Point"}
}