{
  "type": "Feature",
  "properties": {
    "addr:full":"Oudstrijdersplein 15 Halle Vlaams-Brabant 1500",
    "addr:housenumber":"15",
    "addr:postcode":"1500",
    "addr:street":"Oudstrijdersplein",
    "iso:country":"BE",
    "sg:address":"Oudstrijdersplein 15",
    "sg:city":"Halle",
    "sg:orig_category":"Banken and kredietinstellingen",
    "sg:phone":"+32 2 360 11 11",
    "sg:postcode":"1500",
    "sg:province":"Vlaams-Brabant",
    "wof:name":"Citibank",
    "wof:placetype":"venue"
},
  "geometry": {"coordinates":[4.2334589958,50.7344055176],"type":"Point"}
}