{
  "type": "Feature",
  "properties": {
    "iso:country":"BE",
    "sg:address":"Pottelberg 82",
    "sg:city":"Kortrijk",
    "sg:classifiers":[
        {
            "category":"Wholesale",
            "subcategory":"Vending Machines",
            "type":"Manufacturing & Wholesale Goods"
        }
    ],
    "sg:phone":"+32 56 22 37 54",
    "sg:postcode":"8500",
    "sg:province":"West-Vlaanderen",
    "sg:tags":[
        "automobile",
        "-",
        "radiator"
    ],
    "wof:name":"D'haene",
    "wof:placetype":"venue"
},
  "geometry": {"coordinates":[3.2518670559,50.8138275146],"type":"Point"}
}