{
  "type": "Feature",
  "properties": {
    "iso:country":"BE",
    "sg:address":"Gentbruggekouter 26",
    "sg:city":"Gent (gentbrugge)",
    "sg:classifiers":[
        {
            "category":"Communications",
            "subcategory":"Film & Video Production",
            "type":"Services"
        }
    ],
    "sg:phone":"+32 9 230 27 21",
    "sg:postcode":"9050",
    "sg:province":"Oost-Vlaanderen",
    "sg:tags":[
        "realisation",
        "-"
    ],
    "wof:name":"Wildlife Safari Video Production",
    "wof:placetype":"venue"
},
  "geometry": {"coordinates":[3.7636840343,51.0463638306],"type":"Point"}
}