{
  "type": "Feature",
  "properties": {
    "addr:full":"Rue Du Quesnoy 4 Brunehaut Hainaut 7623",
    "addr:housenumber":"4",
    "addr:postcode":"7623",
    "addr:street":"Rue Du Quesnoy",
    "iso:country":"BE",
    "sg:address":"Rue Du Quesnoy 4",
    "sg:city":"Brunehaut",
    "sg:orig_category":"Boomkwekerijen Fruitteelt",
    "sg:phone":"+32 69 34 43 83",
    "sg:postcode":"7623",
    "sg:province":"Hainaut",
    "wof:name":"Joseph Vincent",
    "wof:placetype":"venue"
},
  "geometry": {"coordinates":[3.395236969,50.5050964355],"type":"Point"}
}