{
  "type": "Feature",
  "properties": {
    "addr:full":"Rue Baudoin 1er 14 Courcelles Hainaut 6180",
    "addr:housenumber":"14",
    "addr:postcode":"6180",
    "addr:street":"Rue Baudoin 1Er",
    "iso:country":"BE",
    "sg:address":"Rue Baudoin 1er 14",
    "sg:city":"Courcelles",
    "sg:classifiers":[
        {
            "category":"Professional",
            "subcategory":"Lawyer & Legal Services",
            "type":"Services"
        }
    ],
    "sg:phone":"+32 71 45 29 76",
    "sg:postcode":"6180",
    "sg:province":"Hainaut",
    "wof:name":"Leroy M",
    "wof:placetype":"venue"
},
  "geometry": {"coordinates":[4.3792858124,50.4587554932],"type":"Point"}
}