{
  "type": "Feature",
  "properties": {
    "addr:full":"Rederijkersstraat 7 Wevelgem (gullegem) West-Vlaanderen 8560",
    "addr:housenumber":"7",
    "addr:postcode":"8560",
    "addr:street":"Rederijkersstraat",
    "iso:country":"BE",
    "sg:address":"Rederijkersstraat 7",
    "sg:city":"Wevelgem (gullegem)",
    "sg:classifiers":[
        {
            "category":"Personal",
            "subcategory":"Beauty Salon",
            "type":"Services"
        }
    ],
    "sg:phone":"+32 56 41 40 22",
    "sg:postcode":"8560",
    "sg:province":"West-Vlaanderen",
    "sg:tags":[
        "lady",
        "-",
        "hairdressing"
    ],
    "wof:name":"Esprit Xavier",
    "wof:placetype":"venue"
},
  "geometry": {"coordinates":[3.200824976,50.8431816101],"type":"Point"}
}