{
  "type": "Feature",
  "properties": {
    "iso:country":"BE",
    "sg:address":"Kortedagsteeg 5a",
    "sg:city":"Gent",
    "sg:classifiers":[
        {
            "category":"Shopping",
            "subcategory":"Shoes",
            "type":"Retail Goods"
        }
    ],
    "sg:phone":"+32 9 224 29 43",
    "sg:postcode":"9000",
    "sg:province":"Oost-Vlaanderen",
    "sg:tags":[
        "slipper",
        "-"
    ],
    "wof:name":"Caricci",
    "wof:placetype":"venue"
},
  "geometry": {"coordinates":[3.7263870239,51.0503196716],"type":"Point"}
}