{
  "type": "Feature",
  "properties": {
    "iso:country":"BE",
    "sg:address":"Boulevard De L'ourthe 97",
    "sg:city":"Li\u00c8ge",
    "sg:orig_category":"Traitements param\u00e9dicaux",
    "sg:phone":"+32 4 367 74 52",
    "sg:postcode":"4032",
    "sg:province":"Li\u00e8ge",
    "wof:name":"M.c. Casterman",
    "wof:placetype":"venue"
},
  "geometry": {"coordinates":[5.6108150482,50.6033096313],"type":"Point"}
}