{
  "type": "Feature",
  "properties": {
    "addr:full":"Avenue Du Saphir 21 Sint-genesius-rode/rhode-saint-genese Vlaams-Brabant 1640",
    "addr:housenumber":"21",
    "addr:postcode":"1640",
    "addr:street":"Avenue Du Saphir",
    "iso:country":"BE",
    "sg:address":"Avenue Du Saphir 21",
    "sg:city":"Sint-genesius-rode/rhode-saint-genese",
    "sg:orig_category":"Quincailleries. Plomberie, chauffage and installations sanitaires",
    "sg:phone":"+32 2 380 44 51",
    "sg:postcode":"1640",
    "sg:province":"Vlaams-Brabant",
    "wof:name":"Henri Tassignon",
    "wof:placetype":"venue"
},
  "geometry": {"coordinates":[4.333439827,50.7351837158],"type":"Point"}
}