{
  "type": "Feature",
  "properties": {
    "addr:full":"Hoveniersstraat 9 Aalst Oost-Vlaanderen 9300",
    "addr:housenumber":"9",
    "addr:postcode":"9300",
    "addr:street":"Hoveniersstraat",
    "iso:country":"BE",
    "sg:address":"Hoveniersstraat 9",
    "sg:city":"Aalst",
    "sg:orig_category":"Medische and orthopedische apparaten Opticiens",
    "sg:phone":"+32 53 78 29 70",
    "sg:postcode":"9300",
    "sg:province":"Oost-Vlaanderen",
    "wof:name":"Opticiens Verdoodt",
    "wof:placetype":"venue"
},
  "geometry": {"coordinates":[4.0459032059,50.94165802],"type":"Point"}
}