{
  "type": "Feature",
  "properties": {
    "iso:country":"BE",
    "sg:address":"Dorp-west 18",
    "sg:city":"Lochristi",
    "sg:classifiers":[
        {
            "category":"Insurance",
            "subcategory":"Life Insurance",
            "type":"Services"
        }
    ],
    "sg:phone":"+32 9 356 01 24",
    "sg:postcode":"9080",
    "sg:province":"Oost-Vlaanderen",
    "sg:tags":[
        "assurance"
    ],
    "wof:name":"D.b. Serv.",
    "wof:placetype":"venue"
},
  "geometry": {"coordinates":[3.8326380253,51.0962524414],"type":"Point"}
}