{
  "type": "Feature",
  "properties": {
    "addr:full":"Sparrenstraat 17 Antwerpen Antwerpen 2020",
    "addr:housenumber":"17",
    "addr:postcode":"2020",
    "addr:street":"Sparrenstraat",
    "iso:country":"BE",
    "sg:address":"Sparrenstraat 17",
    "sg:city":"Antwerpen",
    "sg:classifiers":[
        {
            "category":"Recreation",
            "type":"Entertainment"
        }
    ],
    "sg:phone":"+32 3 237 29 14",
    "sg:postcode":"2020",
    "sg:province":"Antwerpen",
    "sg:tags":[
        "diver",
        "amusement"
    ],
    "wof:name":"Kari-legrot-bueno",
    "wof:placetype":"venue"
},
  "geometry": {"coordinates":[4.3937997818,51.1848831177],"type":"Point"}
}