{
  "type": "Feature",
  "properties": {
    "addr:full":"Rue Delvaux 16b Namur Namur 5000",
    "addr:housenumber":"16b",
    "addr:postcode":"5000",
    "addr:street":"Rue Delvaux",
    "iso:country":"BE",
    "sg:address":"Rue Delvaux 16b",
    "sg:city":"Namur",
    "sg:classifiers":[
        {
            "category":"Social Services",
            "subcategory":"Job Training",
            "type":"Services"
        }
    ],
    "sg:phone":"+32 81 26 05 05",
    "sg:postcode":"5000",
    "sg:province":"Namur",
    "sg:tags":[
        "interpreter"
    ],
    "wof:name":"Service D'interpr\u00e9tation Des Sourds De Wallonie",
    "wof:placetype":"venue"
},
  "geometry": {"coordinates":[4.8702330589,50.4677810669],"type":"Point"}
}