{
  "type": "Feature",
  "properties": {
    "iso:country":"BE",
    "sg:address":"Lintsesteenweg 116",
    "sg:city":"Lier",
    "sg:classifiers":[
        {
            "category":"Communications",
            "subcategory":"News Services",
            "type":"Services"
        }
    ],
    "sg:phone":"+32 3 489 22 25",
    "sg:postcode":"2500",
    "sg:province":"Antwerpen",
    "sg:tags":[
        "illustrator"
    ],
    "wof:name":"Janssen M",
    "wof:placetype":"venue"
},
  "geometry": {"coordinates":[4.5343317986,51.1301841736],"type":"Point"}
}