{
  "type": "Feature",
  "properties": {
    "addr:full":"Rue Du Tr\u00d4ne 220 Elsene/ixelles Bruxelles-Capitale 1050",
    "addr:housenumber":"220",
    "addr:postcode":"1050",
    "addr:street":"Rue Du Tro\u0302Ne",
    "iso:country":"BE",
    "sg:address":"Rue Du Tr\u00d4ne 220",
    "sg:city":"Elsene/ixelles",
    "sg:orig_category":"Assistances juridiques",
    "sg:phone":"+32 2 648 02 87",
    "sg:postcode":"1050",
    "sg:province":"Bruxelles-Capitale",
    "wof:name":"Galerie De Paris",
    "wof:placetype":"venue"
},
  "geometry": {"coordinates":[4.3744659424,50.8335800171],"type":"Point"}
}