{
  "type": "Feature",
  "properties": {
    "addr:full":"Stijn Streuvelslaan 35 Avelgem West-Vlaanderen 8580",
    "addr:housenumber":"35",
    "addr:postcode":"8580",
    "addr:street":"Stijn Streuvelslaan",
    "iso:country":"BE",
    "sg:address":"Stijn Streuvelslaan 35",
    "sg:city":"Avelgem",
    "sg:classifiers":[
        {
            "category":"Health Services",
            "subcategory":"Health Practitioner",
            "type":"Services"
        }
    ],
    "sg:phone":"+32 56 64 62 18",
    "sg:postcode":"8580",
    "sg:province":"West-Vlaanderen",
    "sg:tags":[
        "physiotherapist"
    ],
    "wof:name":"Notebaert Viviane",
    "wof:placetype":"venue"
},
  "geometry": {"coordinates":[3.4354128838,50.7743339539],"type":"Point"}
}