{
  "type": "Feature",
  "properties": {
    "addr:full":"Brusselstraat 269 Dilbeek Vlaams-Brabant 1702",
    "addr:housenumber":"269",
    "addr:postcode":"1702",
    "addr:street":"Brusselstraat",
    "iso:country":"BE",
    "sg:address":"Brusselstraat 269",
    "sg:city":"Dilbeek",
    "sg:orig_category":"Begrafeniswezen",
    "sg:phone":"+32 2 466 75 75",
    "sg:postcode":"1702",
    "sg:province":"Vlaams-Brabant",
    "wof:name":"A. Lesage",
    "wof:placetype":"venue"
},
  "geometry": {"coordinates":[4.2605500221,50.870967865],"type":"Point"}
}