{
  "type": "Feature",
  "properties": {
    "iso:country":"BE",
    "sg:address":"J. Anthierenslaan 9",
    "sg:city":"De Pinte",
    "sg:classifiers":[
        {
            "category":"Food & Beverages",
            "subcategory":"Fruits & Vegetables",
            "type":"Retail Goods"
        }
    ],
    "sg:phone":"+32 9 282 59 81",
    "sg:postcode":"9840",
    "sg:province":"Oost-Vlaanderen",
    "sg:tags":[
        "l\u00e9gumes",
        "gr"
    ],
    "wof:name":"Etienne Van Huffel",
    "wof:placetype":"venue"
},
  "geometry": {"coordinates":[3.6543819904,50.9945106506],"type":"Point"}
}