{
  "type": "Feature",
  "properties": {
    "addr:full":"Avenue De Criel 33 Havelange Namur 5370",
    "addr:housenumber":"33",
    "addr:postcode":"5370",
    "addr:street":"Avenue De Criel",
    "iso:country":"BE",
    "sg:address":"Avenue De Criel 33",
    "sg:city":"Havelange",
    "sg:classifiers":[
        {
            "category":"Health Services",
            "subcategory":"Dentist",
            "type":"Services"
        }
    ],
    "sg:phone":"+32 83 63 31 66",
    "sg:postcode":"5370",
    "sg:province":"Namur",
    "wof:name":"Dardenne V\u00e9ronique",
    "wof:placetype":"venue"
},
  "geometry": {"coordinates":[5.2385640144,50.389629364],"type":"Point"}
}