{
  "type": "Feature",
  "properties": {
    "iso:country":"BE",
    "sg:address":"Lambermontlaan 147",
    "sg:city":"Schaarbeek/schaerbeek",
    "sg:orig_category":"Notarissen",
    "sg:phone":"+32 2 215 76 69",
    "sg:postcode":"1030",
    "sg:province":"Bruxelles-Capitale",
    "wof:name":"G. Cluydts",
    "wof:placetype":"venue"
},
  "geometry": {"coordinates":[4.381524086,50.8709449768],"type":"Point"}
}