{
  "type": "Feature",
  "properties": {
    "addr:full":"Ertbrandstraat 282-286 Kapellen Antwerpen 2950",
    "addr:housenumber":"282-286",
    "addr:postcode":"2950",
    "addr:street":"Ertbrandstraat",
    "iso:country":"BE",
    "sg:address":"Ertbrandstraat 282-286",
    "sg:city":"Kapellen",
    "sg:classifiers":[
        {
            "category":"Home & Garden",
            "subcategory":"Home Furnishings",
            "type":"Retail Goods"
        }
    ],
    "sg:phone":"+32 3 315 49 49",
    "sg:postcode":"2950",
    "sg:province":"Antwerpen",
    "sg:tags":[
        "-",
        "furniture"
    ],
    "wof:name":"Costuless",
    "wof:placetype":"venue"
},
  "geometry": {"coordinates":[4.3995399475,51.3481712341],"type":"Point"}
}