{
  "type": "Feature",
  "properties": {
    "iso:country":"BE",
    "sg:address":"Brume 14",
    "sg:city":"Trois-ponts",
    "sg:orig_category":"Travaux de pl\u00e2trage",
    "sg:phone":"+32 80 68 50 15",
    "sg:postcode":"4980",
    "sg:province":"Li\u00e8ge",
    "wof:name":"Feront Claude",
    "wof:placetype":"venue"
},
  "geometry": {"coordinates":[5.8684577942,50.3743667603],"type":"Point"}
}