{
  "type": "Feature",
  "properties": {
    "iso:country":"BE",
    "sg:address":"Rue Gustave Dewalque 21",
    "sg:city":"Stavelot",
    "sg:classifiers":[
        {
            "category":"Professional",
            "subcategory":"Computer Services",
            "type":"Services"
        }
    ],
    "sg:phone":"+32 80 88 09 70",
    "sg:postcode":"4970",
    "sg:province":"Li\u00e8ge",
    "sg:tags":[
        "webdesign",
        "-",
        "internet"
    ],
    "wof:name":"Mro Com",
    "wof:placetype":"venue"
},
  "geometry": {"coordinates":[5.931265831,50.3919754028],"type":"Point"}
}