{
  "type": "Feature",
  "properties": {
    "addr:full":"Lage Kaart 283 Brasschaat Antwerpen 2930",
    "addr:housenumber":"283",
    "addr:postcode":"2930",
    "addr:street":"Lage Kaart",
    "iso:country":"BE",
    "sg:address":"Lage Kaart 283",
    "sg:city":"Brasschaat",
    "sg:orig_category":"Alternatieve geneeskunde",
    "sg:phone":"+32 3 651 93 90",
    "sg:postcode":"2930",
    "sg:province":"Antwerpen",
    "wof:name":"Roland Nuyts",
    "wof:placetype":"venue"
},
  "geometry": {"coordinates":[4.4834108353,51.3025245667],"type":"Point"}
}