{
  "type": "Feature",
  "properties": {
    "addr:full":"Kongoplein 8 Turnhout Antwerpen 2300",
    "addr:housenumber":"8",
    "addr:postcode":"2300",
    "addr:street":"Kongoplein",
    "iso:country":"BE",
    "sg:address":"Kongoplein 8",
    "sg:city":"Turnhout",
    "sg:classifiers":[
        {
            "category":"Personal",
            "subcategory":"Beauty Salon",
            "type":"Services"
        }
    ],
    "sg:phone":"+32 14 42 70 43",
    "sg:postcode":"2300",
    "sg:province":"Antwerpen",
    "sg:tags":[
        "de",
        "coiffure"
    ],
    "wof:name":"Coiffure International",
    "wof:placetype":"venue"
},
  "geometry": {"coordinates":[4.9330530167,51.3237304688],"type":"Point"}
}