{
  "type": "Feature",
  "properties": {
    "iso:country":"BE",
    "sg:address":"Belgradostraat 4",
    "sg:city":"Gent",
    "sg:classifiers":[
        {
            "category":"Cafe",
            "type":"Food & Drink"
        }
    ],
    "sg:phone":"+32 9 233 36 78",
    "sg:postcode":"9000",
    "sg:province":"Oost-Vlaanderen",
    "sg:tags":[
        "caf\u00e9s"
    ],
    "wof:name":"Queens Bar",
    "wof:placetype":"venue"
},
  "geometry": {"coordinates":[3.7309639454,51.0500411987],"type":"Point"}
}