{
  "type": "Feature",
  "properties": {
    "iso:country":"BE",
    "sg:address":"Rue De Presgaux 89",
    "sg:city":"Couvin",
    "sg:orig_category":"Rundveehouders",
    "sg:phone":"+32 60 37 73 53",
    "sg:postcode":"5660",
    "sg:province":"Namur",
    "wof:name":"Yvette Dardenne",
    "wof:placetype":"venue"
},
  "geometry": {"coordinates":[4.4572649002,49.9792137146],"type":"Point"}
}