{
  "type": "Feature",
  "properties": {
    "addr:full":"Jan Persijnstraat 6 Kortrijk West-Vlaanderen 8500",
    "addr:housenumber":"6",
    "addr:postcode":"8500",
    "addr:street":"Jan Persijnstraat",
    "iso:country":"BE",
    "sg:address":"Jan Persijnstraat 6",
    "sg:city":"Kortrijk",
    "sg:classifiers":[
        {
            "category":"Organizations",
            "subcategory":"Community Association",
            "type":"Services"
        }
    ],
    "sg:phone":"+32 56 22 10 01",
    "sg:postcode":"8500",
    "sg:province":"West-Vlaanderen",
    "sg:tags":[
        "cultural"
    ],
    "wof:name":"Limelight Vzw",
    "wof:placetype":"venue"
},
  "geometry": {"coordinates":[3.2634561062,50.8272399902],"type":"Point"}
}