{
  "type": "Feature",
  "properties": {
    "addr:full":"Rue Genly 3ba Montigny-le-tilleul Hainaut 6110",
    "addr:postcode":"3ba;6110",
    "addr:street":"Rue Genly;Hainaut",
    "iso:country":"BE",
    "sg:address":"Rue Genly 3ba",
    "sg:city":"Montigny-le-tilleul",
    "sg:classifiers":[
        {
            "category":"Insurance",
            "subcategory":"Life Insurance",
            "type":"Services"
        }
    ],
    "sg:phone":"+32 71 51 74 70",
    "sg:postcode":"6110",
    "sg:province":"Hainaut",
    "sg:tags":[
        "assurance"
    ],
    "wof:name":"Pierre Agneessens",
    "wof:placetype":"venue"
},
  "geometry": {"coordinates":[4.3779478073,50.3819122314],"type":"Point"}
}