{
  "type": "Feature",
  "properties": {
    "iso:country":"BE",
    "sg:address":"Rue P Devigne 72b20",
    "sg:city":"Brussel",
    "sg:orig_category":"Sportclubs",
    "sg:phone":"+32 2 241 26 90",
    "sg:postcode":"1030",
    "sg:province":"Bruxelles-Capitale",
    "wof:name":"De Gouden Pijl",
    "wof:placetype":"venue"
},
  "geometry": {"coordinates":[4.3909230232,50.8577842712],"type":"Point"}
}