{
  "type": "Feature",
  "properties": {
    "addr:full":"Chemin Du Long Royon 3 Lessines Hainaut 7860",
    "addr:housenumber":"3",
    "addr:postcode":"7860",
    "addr:street":"Chemin Du Long Royon;Hainaut",
    "iso:country":"BE",
    "sg:address":"Chemin Du Long Royon 3",
    "sg:city":"Lessines",
    "sg:orig_category":"M\u00e9decins and sp\u00e9cialistes",
    "sg:phone":"+32 68 33 68 53",
    "sg:postcode":"7860",
    "sg:province":"Hainaut",
    "wof:name":"Monique Helleputte",
    "wof:placetype":"venue"
},
  "geometry": {"coordinates":[3.8105170727,50.7190513611],"type":"Point"}
}