{
  "type": "Feature",
  "properties": {
    "iso:country":"BE",
    "sg:address":"Kerkstraat 16",
    "sg:city":"Nieuwerkerken",
    "sg:orig_category":"Loodgieterij, verwarming and sanitaire installaties",
    "sg:phone":"+32 11 67 23 38",
    "sg:postcode":"3850",
    "sg:province":"Limburg",
    "wof:name":"Joseph Bessemans",
    "wof:placetype":"venue"
},
  "geometry": {"coordinates":[5.1901488304,50.8580436707],"type":"Point"}
}