{
  "type": "Feature",
  "properties": {
    "iso:country":"BE",
    "sg:address":"Rue Emile-vandervelde 100",
    "sg:city":"Nivelles",
    "sg:orig_category":"Avocats and conseillers juridiques",
    "sg:phone":"+32 67 84 14 40",
    "sg:postcode":"1400",
    "sg:province":"Brabant Wallon",
    "wof:name":"Sylvie Planchat",
    "wof:placetype":"venue"
},
  "geometry": {"coordinates":[4.3317952156,50.5943450928],"type":"Point"}
}