{
  "type": "Feature",
  "properties": {
    "addr:full":"Avenue De Joli-bois 2 Sint-pieters-woluwe/woluwe-saint-pierre Bruxelles-Capitale 1150",
    "addr:housenumber":"2",
    "addr:postcode":"1150",
    "addr:street":"Avenue De Joli-Bois;/",
    "iso:country":"BE",
    "sg:address":"Avenue De Joli-bois 2",
    "sg:city":"Sint-pieters-woluwe/woluwe-saint-pierre",
    "sg:orig_category":"Journaux. Tabac",
    "sg:phone":"+32 2 770 75 07",
    "sg:postcode":"1150",
    "sg:province":"Bruxelles-Capitale",
    "wof:name":"Maison L'enfant Roy",
    "wof:placetype":"venue"
},
  "geometry": {"coordinates":[4.4563260078,50.8260955811],"type":"Point"}
}