{
  "type": "Feature",
  "properties": {
    "addr:full":"Rijmenamseweg 48 Bonheiden Antwerpen 2820",
    "addr:housenumber":"48",
    "addr:postcode":"2820",
    "addr:street":"Rijmenamseweg",
    "iso:country":"BE",
    "sg:address":"Rijmenamseweg 48",
    "sg:city":"Bonheiden",
    "sg:classifiers":[
        {
            "category":"Professional",
            "subcategory":"Accounting & Tax Preparation",
            "type":"Services"
        }
    ],
    "sg:phone":"+32 15 51 71 49",
    "sg:postcode":"2820",
    "sg:province":"Antwerpen",
    "sg:tags":[
        "accountant"
    ],
    "wof:name":"Marc Van Den Plas",
    "wof:placetype":"venue"
},
  "geometry": {"coordinates":[4.5543708801,51.0207901001],"type":"Point"}
}