{
  "type": "Feature",
  "properties": {
    "addr:full":"Krekershofweg 12 Maaseik Limburg 3680",
    "addr:housenumber":"12",
    "addr:postcode":"3680",
    "addr:street":"Krekershofweg",
    "iso:country":"BE",
    "sg:address":"Krekershofweg 12",
    "sg:city":"Maaseik",
    "sg:orig_category":"Varkenskwekers",
    "sg:phone":"+32 89 86 32 31",
    "sg:postcode":"3680",
    "sg:province":"Limburg",
    "wof:name":"Dominicus Henckens",
    "wof:placetype":"venue"
},
  "geometry": {"coordinates":[5.7576208115,51.1173210144],"type":"Point"}
}