{
  "type": "Feature",
  "properties": {
    "iso:country":"BE",
    "sg:address":"Koning Albertlaan 12",
    "sg:city":"Maasmechelen",
    "sg:orig_category":"Installation de menuiserie m\u00e9tallique. Installation de serres, double vitrage and fen\u00eatres. Installa",
    "sg:phone":"+32 89 76 41 71",
    "sg:postcode":"3630",
    "sg:province":"Limburg",
    "wof:name":"Glaswerken Yperman",
    "wof:placetype":"venue"
},
  "geometry": {"coordinates":[5.6948652267,50.9675216675],"type":"Point"}
}