{
  "type": "Feature",
  "properties": {
    "addr:full":"Burg. Henrylaan 43 Dilsen-stokkem Limburg 3650",
    "addr:housenumber":"43",
    "addr:postcode":"3650",
    "addr:street":"Burg. Henrylaan",
    "iso:country":"BE",
    "sg:address":"Burg. Henrylaan 43",
    "sg:city":"Dilsen-stokkem",
    "sg:orig_category":"Chaussures. Maroquinerie and articles de voyage",
    "sg:phone":"+32 89 75 56 08",
    "sg:postcode":"3650",
    "sg:province":"Limburg",
    "wof:name":"Vital Luyten",
    "wof:placetype":"venue"
},
  "geometry": {"coordinates":[5.727396965,51.0364189148],"type":"Point"}
}