{
  "type": "Feature",
  "properties": {
    "iso:country":"BE",
    "sg:address":"Oudstrijdersstraat 7",
    "sg:city":"Ingelmunster",
    "sg:orig_category":"Boucheries",
    "sg:phone":"+32 51 30 80 00",
    "sg:postcode":"8770",
    "sg:province":"West-Vlaanderen",
    "wof:name":"Rik Vanquatem",
    "wof:placetype":"venue"
},
  "geometry": {"coordinates":[3.259362936,50.9142303467],"type":"Point"}
}