{
  "type": "Feature",
  "properties": {
    "addr:full":"Assesteenweg 26 Asse Vlaams-Brabant 1730",
    "addr:housenumber":"26",
    "addr:postcode":"1730",
    "addr:street":"Assesteenweg",
    "iso:country":"BE",
    "sg:address":"Assesteenweg 26",
    "sg:city":"Asse",
    "sg:classifiers":[
        {
            "category":"Building & Trades",
            "subcategory":"Landscaping Services",
            "type":"Services"
        }
    ],
    "sg:phone":"+32 2 452 79 93",
    "sg:postcode":"1730",
    "sg:province":"Vlaams-Brabant",
    "sg:tags":[
        "industry",
        "appraisal"
    ],
    "wof:name":"H. De Witte Nv",
    "wof:placetype":"venue"
},
  "geometry": {"coordinates":[4.1641850471,50.913143158],"type":"Point"}
}