{
  "type": "Feature",
  "properties": {
    "addr:full":"Rue Sur Les Vignes 113 Oupeye Li\u00e8ge 4680",
    "addr:housenumber":"113",
    "addr:postcode":"4680",
    "addr:street":"Rue Sur Les Vignes",
    "iso:country":"BE",
    "sg:address":"Rue Sur Les Vignes 113",
    "sg:city":"Oupeye",
    "sg:classifiers":[
        {
            "category":"Health Services",
            "subcategory":"Doctor",
            "type":"Services"
        }
    ],
    "sg:phone":"+32 4 264 76 77",
    "sg:postcode":"4680",
    "sg:province":"Li\u00e8ge",
    "sg:tags":[
        "medicinephysicians",
        "surgeon"
    ],
    "wof:name":"Chapaux C",
    "wof:placetype":"venue"
},
  "geometry": {"coordinates":[5.6544618607,50.7047157288],"type":"Point"}
}