{
  "type": "Feature",
  "properties": {
    "addr:full":"Chauss\u00e9e Churchill 2 Saint-nicolas (montegn\u00e9e) Li\u00e8ge 4420",
    "addr:housenumber":"2",
    "addr:postcode":"4420",
    "addr:street":"Chausse\u0301E Churchill;Montegne\u0301E",
    "iso:country":"BE",
    "sg:address":"Chauss\u00e9e Churchill 2",
    "sg:city":"Saint-nicolas (montegn\u00e9e)",
    "sg:classifiers":[
        {
            "category":"Arena",
            "subcategory":"Sports Club",
            "type":"Entertainment"
        }
    ],
    "sg:phone":"+32 4 246 06 11",
    "sg:postcode":"4420",
    "sg:province":"Li\u00e8ge",
    "wof:name":"Centre Culturel Et Sportif",
    "wof:placetype":"venue"
},
  "geometry": {"coordinates":[5.5280852318,50.6454849243],"type":"Point"}
}