{
  "type": "Feature",
  "properties": {
    "addr:full":"Kempische Steenweg 345-1 Hasselt Limburg 3500",
    "addr:housenumber":"345-1",
    "addr:postcode":"3500",
    "addr:street":"Kempische Steenweg",
    "iso:country":"BE",
    "sg:address":"Kempische Steenweg 345-1",
    "sg:city":"Hasselt",
    "sg:classifiers":[
        {
            "category":"Travel",
            "subcategory":"Travel Agent",
            "type":"Entertainment"
        }
    ],
    "sg:phone":"+32 11 21 01 93",
    "sg:postcode":"3500",
    "sg:province":"Limburg",
    "sg:tags":[
        "agency"
    ],
    "wof:name":"Prima.tours Nv",
    "wof:placetype":"venue"
},
  "geometry": {"coordinates":[5.3410100937,50.9384231567],"type":"Point"}
}