{
  "type": "Feature",
  "properties": {
    "iso:country":"BE",
    "sg:address":"Rue Augustin Delporte 9",
    "sg:city":"Bruxelles (ixelles)",
    "sg:classifiers":[
        {
            "category":"Health Services",
            "subcategory":"Dentist",
            "type":"Services"
        }
    ],
    "sg:phone":"+32 2 648 64 25",
    "sg:postcode":"1050",
    "sg:province":"Bruxelles-Capitale",
    "wof:name":"Mayolet A",
    "wof:placetype":"venue"
},
  "geometry": {"coordinates":[4.3843550682,50.8247909546],"type":"Point"}
}