{
  "type": "Feature",
  "properties": {
    "addr:full":"Sint-gillislaan 63 Dendermonde Oost-Vlaanderen 9200",
    "addr:housenumber":"63",
    "addr:postcode":"9200",
    "addr:street":"Sint-Gillislaan;Oost-Vlaanderen",
    "iso:country":"BE",
    "sg:address":"Sint-gillislaan 63",
    "sg:city":"Dendermonde",
    "sg:orig_category":"M\u00e9decins and sp\u00e9cialistes",
    "sg:phone":"+32 52 21 50 20",
    "sg:postcode":"9200",
    "sg:province":"Oost-Vlaanderen",
    "wof:name":"De Bisschop",
    "wof:placetype":"venue"
},
  "geometry": {"coordinates":[4.1088957787,51.0210609436],"type":"Point"}
}