{
  "type": "Feature",
  "properties": {
    "addr:full":"Stationsstraat 128 Aalter Oost-Vlaanderen 9880",
    "addr:housenumber":"128",
    "addr:postcode":"9880",
    "addr:street":"Stationsstraat",
    "iso:country":"BE",
    "sg:address":"Stationsstraat 128",
    "sg:city":"Aalter",
    "sg:classifiers":[
        {
            "category":"Shopping",
            "subcategory":"Optician",
            "type":"Retail Goods"
        }
    ],
    "sg:phone":"+32 9 374 20 45",
    "sg:postcode":"9880",
    "sg:province":"Oost-Vlaanderen",
    "sg:tags":[
        "-"
    ],
    "wof:name":"Van Bossele-eurovisie Optiek",
    "wof:placetype":"venue"
},
  "geometry": {"coordinates":[3.4482018948,51.0881271362],"type":"Point"}
}