{
  "type": "Feature",
  "properties": {
    "addr:full":"Rue De La Sarte 5ba Chaumont-gistoux Brabant Wallon 1325",
    "addr:housenumber":"5ba",
    "addr:postcode":"1325",
    "addr:street":"Rue De La Sarte",
    "iso:country":"BE",
    "sg:address":"Rue De La Sarte 5ba",
    "sg:city":"Chaumont-gistoux",
    "sg:orig_category":"M\u00e9decins and sp\u00e9cialistes",
    "sg:phone":"+32 10 68 02 25",
    "sg:postcode":"1325",
    "sg:province":"Brabant Wallon",
    "wof:name":"Guy Mathieu",
    "wof:placetype":"venue"
},
  "geometry": {"coordinates":[4.6612758636,50.7008399963],"type":"Point"}
}