{
  "type": "Feature",
  "properties": {
    "iso:country":"BE",
    "sg:address":"Markt 13",
    "sg:city":"Herenthout",
    "sg:orig_category":"DIVERSE RECREATIEVE ACTIVITEITEN",
    "sg:phone":"+32 14 51 26 68",
    "sg:postcode":"2270",
    "sg:province":"Antwerpen",
    "wof:name":"Postzegelklub Herenthout",
    "wof:placetype":"venue"
},
  "geometry": {"coordinates":[4.7563581467,51.1392440796],"type":"Point"}
}