{
  "type": "Feature",
  "properties": {
    "addr:full":"Bochtlaan 16b6 Genk Limburg 3600",
    "addr:housenumber":"16b6",
    "addr:postcode":"3600",
    "addr:street":"Bochtlaan",
    "iso:country":"BE",
    "sg:address":"Bochtlaan 16b6",
    "sg:city":"Genk",
    "sg:orig_category":"Verplichte sociale verzekeringen",
    "sg:phone":"+32 89 36 31 01",
    "sg:postcode":"3600",
    "sg:province":"Limburg",
    "wof:name":"Liberale Mutualiteit",
    "wof:placetype":"venue"
},
  "geometry": {"coordinates":[5.5019979477,50.9670715332],"type":"Point"}
}