{
  "type": "Feature",
  "properties": {
    "iso:country":"BE",
    "sg:address":"Langestraat 90",
    "sg:city":"Ternat",
    "sg:orig_category":"Airconditioning and ventilatie Elektrische installaties voor woningen Loodgieterij, verwarming and s",
    "sg:phone":"+32 2 582 28 20",
    "sg:postcode":"1741",
    "sg:province":"Vlaams-Brabant",
    "wof:name":"Willy Mackens",
    "wof:placetype":"venue"
},
  "geometry": {"coordinates":[4.1738491058,50.8512954712],"type":"Point"}
}