{
  "type": "Feature",
  "properties": {
    "iso:country":"BE",
    "sg:address":"Iepersestraat 38",
    "sg:city":"Roeselare",
    "sg:orig_category":"Slagers",
    "sg:phone":"+32 51 20 80 63",
    "sg:postcode":"8800",
    "sg:province":"West-Vlaanderen",
    "wof:name":"Beenhouwerij Jean",
    "wof:placetype":"venue"
},
  "geometry": {"coordinates":[3.1224200726,50.9424514771],"type":"Point"}
}