{
  "type": "Feature",
  "properties": {
    "addr:full":"Hillestraat 4 Maldegem Oost-Vlaanderen 9991",
    "addr:housenumber":"4",
    "addr:postcode":"9991",
    "addr:street":"Hillestraat",
    "iso:country":"BE",
    "sg:address":"Hillestraat 4",
    "sg:city":"Maldegem",
    "sg:orig_category":"Meubles D\u00e9taillants, Am\u00e9nagement de B\u00e2timents et de Cuisines",
    "sg:phone":"+32 50 71 31 83",
    "sg:postcode":"9991",
    "sg:province":"Oost-Vlaanderen",
    "wof:name":"Huis Miranda",
    "wof:placetype":"venue"
},
  "geometry": {"coordinates":[3.4904689789,51.2032241821],"type":"Point"}
}