{
  "type": "Feature",
  "properties": {
    "iso:country":"BE",
    "sg:address":"Elbampdstraat 1",
    "sg:city":"Hasselt",
    "sg:orig_category":"Varkenskwekers",
    "sg:phone":"+32 11 31 57 65",
    "sg:postcode":"3500",
    "sg:province":"Limburg",
    "wof:name":"Voordeckers Andre En Nico",
    "wof:placetype":"venue"
},
  "geometry": {"coordinates":[5.2861309052,50.9157447815],"type":"Point"}
}