{
  "type": "Feature",
  "properties": {
    "iso:country":"BE",
    "sg:address":"Elsputtersstraat 2ba",
    "sg:city":"Bree",
    "sg:orig_category":"Varkenskwekers",
    "sg:phone":"+32 89 47 38 67",
    "sg:postcode":"3960",
    "sg:province":"Limburg",
    "wof:name":"Julien Pellens",
    "wof:placetype":"venue"
},
  "geometry": {"coordinates":[5.6328721046,51.1521110535],"type":"Point"}
}