{
  "type": "Feature",
  "properties": {
    "iso:country":"BE",
    "sg:address":"Oude Vestingstraat 36",
    "sg:city":"Veurne",
    "sg:orig_category":"RESTAURANTS: H\u00d4TELS",
    "sg:phone":"+32 58 31 59 49",
    "sg:postcode":"8630",
    "sg:province":"West-Vlaanderen",
    "wof:name":"De Loft",
    "wof:placetype":"venue"
},
  "geometry": {"coordinates":[2.6654989719,51.074016571],"type":"Point"}
}