{
  "type": "Feature",
  "properties": {
    "addr:full":"Bijlstraat 186 Beveren (beveren-waas) Oost-Vlaanderen 9120",
    "addr:housenumber":"186",
    "addr:postcode":"9120",
    "addr:street":"Bijlstraat;Oost-Vlaanderen",
    "iso:country":"BE",
    "sg:address":"Bijlstraat 186",
    "sg:city":"Beveren (beveren-waas)",
    "sg:classifiers":[
        {
            "category":"Bars & Pubs",
            "type":"Food & Drink"
        }
    ],
    "sg:phone":"+32 3 755 63 10",
    "sg:postcode":"9120",
    "sg:province":"Oost-Vlaanderen",
    "wof:name":"Oude Pierbol (de)",
    "wof:placetype":"venue"
},
  "geometry": {"coordinates":[4.2423357964,51.2071075439],"type":"Point"}
}