{
  "type": "Feature",
  "properties": {
    "addr:full":"Minervalaan 23b1 Vorst/forest Bruxelles-Capitale 1190",
    "addr:housenumber":"23b1",
    "addr:postcode":"1190",
    "addr:street":"Minervalaan;/ Forest",
    "iso:country":"BE",
    "sg:address":"Minervalaan 23b1",
    "sg:city":"Vorst/forest",
    "sg:orig_category":"Architecten",
    "sg:phone":"+32 2 343 57 98",
    "sg:postcode":"1190",
    "sg:province":"Bruxelles-Capitale",
    "wof:name":"Patrick Beckers",
    "wof:placetype":"venue"
},
  "geometry": {"coordinates":[4.3305921555,50.8104362488],"type":"Point"}
}