{
  "type": "Feature",
  "properties": {
    "iso:country":"BE",
    "sg:address":"Groenstraat 50",
    "sg:city":"Tessenderlo",
    "sg:classifiers":[
        {
            "category":"Personal",
            "subcategory":"Beauty Salon",
            "type":"Services"
        }
    ],
    "sg:phone":"+32 13 67 28 14",
    "sg:postcode":"3980",
    "sg:province":"Limburg",
    "sg:tags":[
        "lady",
        "-",
        "hairdressing"
    ],
    "wof:name":"Hair Design Bvba",
    "wof:placetype":"venue"
},
  "geometry": {"coordinates":[5.0761218071,51.0726890564],"type":"Point"}
}