{
  "type": "Feature",
  "properties": {
    "iso:country":"BE",
    "sg:address":"Rue Verte 63",
    "sg:city":"Seraing",
    "sg:orig_category":"Accumulators",
    "sg:phone":"+32 4 385 10 12",
    "sg:postcode":"4100",
    "sg:province":"Li\u00e8ge",
    "wof:name":"Delfosse D D\u00e9pannage",
    "wof:placetype":"venue"
},
  "geometry": {"coordinates":[5.5053911209,50.580657959],"type":"Point"}
}