{
  "type": "Feature",
  "properties": {
    "addr:full":"Rue Mont-chevreuil 31 Chatelet Hainaut 6200",
    "addr:housenumber":"31",
    "addr:postcode":"6200",
    "addr:street":"Rue Mont-Chevreuil;Hainaut",
    "iso:country":"BE",
    "sg:address":"Rue Mont-chevreuil 31",
    "sg:city":"Chatelet",
    "sg:orig_category":"Charpentes and couvertures. Plomberie, chauffage and installations sanitaires",
    "sg:phone":"+32 71 38 95 60",
    "sg:postcode":"6200",
    "sg:province":"Hainaut",
    "wof:name":"Van Hauwe",
    "wof:placetype":"venue"
},
  "geometry": {"coordinates":[4.5185041428,50.3870887756],"type":"Point"}
}