{
  "type": "Feature",
  "properties": {
    "addr:full":"Veldstraat 4 Ardooie West-Vlaanderen 8850",
    "addr:housenumber":"4",
    "addr:postcode":"8850",
    "addr:street":"Veldstraat",
    "iso:country":"BE",
    "sg:address":"Veldstraat 4",
    "sg:city":"Ardooie",
    "sg:orig_category":"Dakwerken Schilders",
    "sg:phone":"+32 51 74 61 09",
    "sg:postcode":"8850",
    "sg:province":"West-Vlaanderen",
    "wof:name":"Himbrecht-vandeginste",
    "wof:placetype":"venue"
},
  "geometry": {"coordinates":[3.2110540867,50.9718513489],"type":"Point"}
}