{
  "type": "Feature",
  "properties": {
    "iso:country":"BE",
    "sg:address":"Adegemdorp 0",
    "sg:city":"Maldegem",
    "sg:classifiers":[
        {
            "category":"Cafe",
            "type":"Food & Drink"
        }
    ],
    "sg:phone":"+32 50 71 00 32",
    "sg:postcode":"9991",
    "sg:province":"Oost-Vlaanderen",
    "sg:tags":[
        "caf\u00e9s"
    ],
    "wof:name":"Caf\u00c9 Den Hoogen Pad",
    "wof:placetype":"venue"
},
  "geometry": {"coordinates":[3.4865500927,51.2040634155],"type":"Point"}
}