{
  "type": "Feature",
  "properties": {
    "iso:country":"BE",
    "sg:address":"Fays 725",
    "sg:city":"Bertogne",
    "sg:orig_category":"Rundveehouders",
    "sg:phone":"+32 61 21 17 70",
    "sg:postcode":"6688",
    "sg:province":"Luxembourg",
    "wof:name":"Louis Roufosse",
    "wof:placetype":"venue"
},
  "geometry": {"coordinates":[5.6686692238,50.0648956299],"type":"Point"}
}