{
  "type": "Feature",
  "properties": {
    "addr:full":"Rue De L'abbaye 118 Ath Hainaut 7800",
    "addr:housenumber":"118",
    "addr:postcode":"7800",
    "addr:street":"Rue De L'Abbaye",
    "iso:country":"BE",
    "sg:address":"Rue De L'abbaye 118",
    "sg:city":"Ath",
    "sg:classifiers":[
        {
            "category":"Personal",
            "subcategory":"Beauty Salon",
            "type":"Services"
        }
    ],
    "sg:phone":"+32 498 20 90 77",
    "sg:postcode":"7800",
    "sg:province":"Hainaut",
    "wof:name":"Epile Effance",
    "wof:placetype":"venue"
},
  "geometry": {"coordinates":[3.7845621109,50.6279716492],"type":"Point"}
}