{
  "type": "Feature",
  "properties": {
    "addr:full":"Oude Baan 179 Maasmechelen Limburg 3630",
    "addr:housenumber":"179",
    "addr:postcode":"3630",
    "addr:street":"Oude Baan",
    "iso:country":"BE",
    "sg:address":"Oude Baan 179",
    "sg:city":"Maasmechelen",
    "sg:orig_category":"V\u00e9los",
    "sg:phone":"+32 89 76 03 03",
    "sg:postcode":"3630",
    "sg:province":"Limburg",
    "wof:name":"Laurent Breuls",
    "wof:placetype":"venue"
},
  "geometry": {"coordinates":[5.6917691231,50.9804916382],"type":"Point"}
}