{
  "type": "Feature",
  "properties": {
    "iso:country":"BE",
    "sg:address":"Route De Falize 152b43",
    "sg:city":"Malmedy",
    "sg:orig_category":"Bois Gr. Quincailleries. Travail and traitement du bois",
    "sg:phone":"+32 80 33 95 63",
    "sg:postcode":"4960",
    "sg:province":"Li\u00e8ge",
    "wof:name":"M.l. Services",
    "wof:placetype":"venue"
},
  "geometry": {"coordinates":[6.005188942,50.412273407],"type":"Point"}
}