{
  "type": "Feature",
  "properties": {
    "addr:full":"Chauss\u00c9e De Saint-job 674 Ukkel/uccle Bruxelles-Capitale 1180",
    "addr:housenumber":"674",
    "addr:postcode":"1180",
    "addr:street":"Chausse\u0301E De Saint-Job;/",
    "iso:country":"BE",
    "sg:address":"Chauss\u00c9e De Saint-job 674",
    "sg:city":"Ukkel/uccle",
    "sg:classifiers":[
        {
            "category":"Banks & Credit Unions",
            "subcategory":"Investment Brokerage",
            "type":"Services"
        }
    ],
    "sg:phone":"+32 2 375 83 45",
    "sg:postcode":"1180",
    "sg:province":"Bruxelles-Capitale",
    "sg:tags":[
        "de",
        "restaurant",
        "organisation",
        "\u00c0",
        "domicile",
        "catering",
        "livraison",
        "f\u00cates",
        "restaurants"
    ],
    "wof:name":"Au Cygne D'or",
    "wof:placetype":"venue"
},
  "geometry": {"coordinates":[4.365085125,50.7949371338],"type":"Point"}
}