{
  "type": "Feature",
  "properties": {
    "iso:country":"BE",
    "sg:address":"Lauwestraat 17",
    "sg:city":"Wevelgem",
    "sg:orig_category":"Maatkleding Fab",
    "sg:phone":"+32 56 41 23 44",
    "sg:postcode":"8560",
    "sg:province":"West-Vlaanderen",
    "wof:name":"Godfried Robbe",
    "wof:placetype":"venue"
},
  "geometry": {"coordinates":[3.1858279705,50.8080787659],"type":"Point"}
}