{
  "type": "Feature",
  "properties": {
    "addr:full":"Kolonie 46 Lommel Limburg 3920",
    "addr:housenumber":"46",
    "addr:postcode":"3920",
    "addr:street":"Kolonie",
    "iso:country":"BE",
    "sg:address":"Kolonie 46",
    "sg:city":"Lommel",
    "sg:classifiers":[
        {
            "category":"Utilities",
            "subcategory":"Natural Gas",
            "type":"Services"
        }
    ],
    "sg:phone":"+32 11 66 56 86",
    "sg:postcode":"3920",
    "sg:province":"Limburg",
    "sg:tags":[
        "welding"
    ],
    "wof:name":"Theuws J",
    "wof:placetype":"venue"
},
  "geometry": {"coordinates":[5.3790950775,51.2539138794],"type":"Point"}
}