{
  "type": "Feature",
  "properties": {
    "addr:full":"Oosterzelesteenweg 61 Wetteren Oost-Vlaanderen 9230",
    "addr:housenumber":"61",
    "addr:postcode":"9230",
    "addr:street":"Oosterzelesteenweg",
    "iso:country":"BE",
    "sg:address":"Oosterzelesteenweg 61",
    "sg:city":"Wetteren",
    "sg:classifiers":[
        {
            "category":"Cafe",
            "type":"Food & Drink"
        }
    ],
    "sg:phone":"+32 9 369 73 88",
    "sg:postcode":"9230",
    "sg:province":"Oost-Vlaanderen",
    "sg:tags":[
        "caf\u00e9s"
    ],
    "wof:name":"Rosita Moens",
    "wof:placetype":"venue"
},
  "geometry": {"coordinates":[3.8398311138,50.9799194336],"type":"Point"}
}