{
  "type": "Feature",
  "properties": {
    "addr:full":"27 Boulevard Du R&eacute Gent - Brussels Bruxelles-Capitale 1000",
    "addr:housenumber":"27",
    "addr:postcode":"1000",
    "addr:street":"Boulevard Du R & Eacute Gent",
    "iso:country":"BE",
    "sg:address":"27 Boulevard Du R&eacute Gent -",
    "sg:city":"Brussels",
    "sg:classifiers":[
        {
            "category":"Professional",
            "subcategory":"Art Services",
            "type":"Services"
        }
    ],
    "sg:phone":"+32 2 512 22 10",
    "sg:postcode":"1000",
    "sg:province":"Bruxelles-Capitale",
    "sg:tags":[
        "export-import"
    ],
    "wof:name":"American Embassy",
    "wof:placetype":"venue"
},
  "geometry": {"coordinates":[4.3682789803,50.8496437073],"type":"Point"}
}