{
  "type": "Feature",
  "properties": {
    "addr:full":"Kerkstraat 1 Merchtem Vlaams-Brabant 1785",
    "addr:housenumber":"1",
    "addr:postcode":"1785",
    "addr:street":"Kerkstraat",
    "iso:country":"BE",
    "sg:address":"Kerkstraat 1",
    "sg:city":"Merchtem",
    "sg:classifiers":[
        {
            "category":"Restaurant",
            "type":"Food & Drink"
        }
    ],
    "sg:phone":"+32 52 37 27 47",
    "sg:postcode":"1785",
    "sg:province":"Vlaams-Brabant",
    "wof:name":"Butterfly",
    "wof:placetype":"venue"
},
  "geometry": {"coordinates":[4.2324438095,50.9589653015],"type":"Point"}
}