{
  "type": "Feature",
  "properties": {
    "addr:full":"Rue De La Station 35 Rixensart Brabant Wallon 1332",
    "addr:housenumber":"35",
    "addr:postcode":"1332",
    "addr:street":"Rue De La Station;Wallon",
    "iso:country":"BE",
    "sg:address":"Rue De La Station 35",
    "sg:city":"Rixensart",
    "sg:orig_category":"Cr\u00e9dits divers",
    "sg:postcode":"1332",
    "sg:province":"Brabant Wallon",
    "wof:name":"Bancontact-mister Cash",
    "wof:placetype":"venue"
},
  "geometry": {"coordinates":[4.5142650604,50.7251777649],"type":"Point"}
}