{
  "type": "Feature",
  "properties": {
    "addr:full":"Ter Borchtlaan 13 Edegem Antwerpen 2650",
    "addr:housenumber":"13",
    "addr:postcode":"2650",
    "addr:street":"Ter Borchtlaan",
    "iso:country":"BE",
    "sg:address":"Ter Borchtlaan 13",
    "sg:city":"Edegem",
    "sg:orig_category":"Loodgieterij, verwarming and sanitaire installaties",
    "sg:phone":"+32 3 449 77 66",
    "sg:postcode":"2650",
    "sg:province":"Antwerpen",
    "wof:name":"Sanifrank",
    "wof:placetype":"venue"
},
  "geometry": {"coordinates":[4.426402092,51.1580886841],"type":"Point"}
}