{
  "type": "Feature",
  "properties": {
    "addr:full":"Parkstraat 45 Oudenaarde Oost-Vlaanderen 9700",
    "addr:housenumber":"45",
    "addr:postcode":"9700",
    "addr:street":"Parkstraat",
    "iso:country":"BE",
    "sg:address":"Parkstraat 45",
    "sg:city":"Oudenaarde",
    "sg:orig_category":"Immobili\u00ebnkantoren Verzekeringsmakelaars and experts",
    "sg:phone":"+32 55 31 50 89",
    "sg:postcode":"9700",
    "sg:province":"Oost-Vlaanderen",
    "wof:name":"Bernard Colpaert",
    "wof:placetype":"venue"
},
  "geometry": {"coordinates":[3.6105139256,50.8464660645],"type":"Point"}
}