{
  "type": "Feature",
  "properties": {
    "iso:country":"BE",
    "sg:address":"Rue Du Bois 119",
    "sg:city":"Chi\u00c8vres",
    "sg:orig_category":"Eleveurs de bovins",
    "sg:phone":"+32 68 65 80 94",
    "sg:postcode":"7950",
    "sg:province":"Hainaut",
    "wof:name":"Michel Jean - Fagnot",
    "wof:placetype":"venue"
},
  "geometry": {"coordinates":[3.7892799377,50.555229187],"type":"Point"}
}