{
  "type": "Feature",
  "properties": {
    "addr:full":"Rue Albert Ier 115 Farciennes Hainaut 6240",
    "addr:housenumber":"115",
    "addr:postcode":"6240",
    "addr:street":"Rue Albert Ier",
    "iso:country":"BE",
    "sg:address":"Rue Albert Ier 115",
    "sg:city":"Farciennes",
    "sg:classifiers":[
        {
            "category":"Fast Food",
            "type":"Food & Drink"
        }
    ],
    "sg:phone":"+32 71 39 55 50",
    "sg:postcode":"6240",
    "sg:province":"Hainaut",
    "sg:tags":[
        "\u00c0",
        "emporter",
        "restaurants"
    ],
    "wof:name":"Friterie L'entracte",
    "wof:placetype":"venue"
},
  "geometry": {"coordinates":[4.5416650772,50.4246788025],"type":"Point"}
}