{
  "type": "Feature",
  "properties": {
    "addr:full":"Quai Des P\u00c9niches 1 Brussel/bruxelles Bruxelles-Capitale 1000",
    "addr:housenumber":"1",
    "addr:postcode":"1000",
    "addr:street":"Quai Des Pe\u0301Niches;/",
    "iso:country":"BE",
    "sg:address":"Quai Des P\u00c9niches 1",
    "sg:city":"Brussel/bruxelles",
    "sg:orig_category":"Salles de spectacles",
    "sg:phone":"+32 2 203 03 03",
    "sg:postcode":"1000",
    "sg:province":"Bruxelles-Capitale",
    "wof:name":"Fulmar",
    "wof:placetype":"venue"
},
  "geometry": {"coordinates":[4.3470478058,50.8588142395],"type":"Point"}
}