{
  "type": "Feature",
  "properties": {
    "addr:full":"Augustijnslei 180 Brasschaat Antwerpen 2930",
    "addr:housenumber":"180",
    "addr:postcode":"2930",
    "iso:country":"BE",
    "sg:address":"Augustijnslei 180",
    "sg:city":"Brasschaat",
    "sg:orig_category":"R\u00e9alisation de programmes and logiciels",
    "sg:phone":"+32 3 653 14 33",
    "sg:postcode":"2930",
    "sg:province":"Antwerpen",
    "wof:name":"Rebit",
    "wof:placetype":"venue"
},
  "geometry": {"coordinates":[4.4868302345,51.301940918],"type":"Point"}
}