{
  "type": "Feature",
  "properties": {
    "addr:full":"Zouavenstraat 16 Hamme Oost-Vlaanderen 9220",
    "addr:housenumber":"16",
    "addr:postcode":"9220",
    "addr:street":"Zouavenstraat",
    "iso:country":"BE",
    "sg:address":"Zouavenstraat 16",
    "sg:city":"Hamme",
    "sg:classifiers":[
        {
            "category":"Cafe",
            "type":"Food & Drink"
        }
    ],
    "sg:phone":"+32 52 47 91 75",
    "sg:postcode":"9220",
    "sg:province":"Oost-Vlaanderen",
    "sg:tags":[
        "caf\u00e9s"
    ],
    "wof:name":"Parochiale Werken H.hart",
    "wof:placetype":"venue"
},
  "geometry": {"coordinates":[4.1246871948,51.0928840637],"type":"Point"}
}