{
  "type": "Feature",
  "properties": {
    "iso:country":"BE",
    "sg:address":"St. Lenaarstsestw 91",
    "sg:city":"Rijkevorsel",
    "sg:classifiers":[
        {
            "category":"Farming",
            "subcategory":"Farm",
            "type":"Manufacturing & Wholesale Goods"
        }
    ],
    "sg:phone":"+32 3 340 28 70",
    "sg:postcode":"2310",
    "sg:province":"Antwerpen",
    "sg:tags":[
        "horticulture",
        "agriculture",
        "livestock"
    ],
    "wof:name":"Oprins Plant Nv",
    "wof:placetype":"venue"
},
  "geometry": {"coordinates":[4.7370610237,51.347869873],"type":"Point"}
}