{
  "type": "Feature",
  "properties": {
    "iso:country":"BE",
    "sg:address":"Place Polydore Beaufaux 9",
    "sg:city":"Wavre",
    "sg:orig_category":"Pharmaciens",
    "sg:phone":"+32 10 22 27 08",
    "sg:postcode":"1300",
    "sg:province":"Brabant Wallon",
    "wof:name":"E. Mouffe",
    "wof:placetype":"venue"
},
  "geometry": {"coordinates":[4.6246829033,50.7218513489],"type":"Point"}
}