{
  "type": "Feature",
  "properties": {
    "addr:full":"Avenue Albert Ier 16ba Rixensart Brabant Wallon 1332",
    "addr:housenumber":"16ba",
    "addr:postcode":"1332",
    "addr:street":"Avenue Albert Ier;Wallon",
    "iso:country":"BE",
    "sg:address":"Avenue Albert Ier 16ba",
    "sg:city":"Rixensart",
    "sg:orig_category":"Textiles. Eclairage et \u00e9quipements du foyer",
    "sg:phone":"+32 2 654 07 49",
    "sg:postcode":"1332",
    "sg:province":"Brabant Wallon",
    "wof:name":"D\u00c9cor Mazerine",
    "wof:placetype":"venue"
},
  "geometry": {"coordinates":[4.4974551201,50.7170753479],"type":"Point"}
}