{
  "type": "Feature",
  "properties": {
    "addr:full":"Kloosterstraat 88 Bornem Antwerpen 2880",
    "addr:housenumber":"88",
    "addr:postcode":"2880",
    "addr:street":"Kloosterstraat",
    "iso:country":"BE",
    "sg:address":"Kloosterstraat 88",
    "sg:city":"Bornem",
    "sg:orig_category":"Kapsalons",
    "sg:phone":"+32 3 889 24 40",
    "sg:postcode":"2880",
    "sg:province":"Antwerpen",
    "wof:name":"Coiffure Peggy",
    "wof:placetype":"venue"
},
  "geometry": {"coordinates":[4.2245278358,51.093914032],"type":"Point"}
}