{
  "type": "Feature",
  "properties": {
    "iso:country":"BE",
    "sg:address":"Papestraat 3",
    "sg:city":"Ledegem",
    "sg:classifiers":[
        {
            "category":"Retail",
            "subcategory":"Auto Repair",
            "type":"Services"
        }
    ],
    "sg:phone":"+32 56 50 96 85",
    "sg:postcode":"8880",
    "sg:province":"West-Vlaanderen",
    "sg:tags":[
        "garage"
    ],
    "wof:name":"Desimpel K",
    "wof:placetype":"venue"
},
  "geometry": {"coordinates":[3.1218121052,50.8593444824],"type":"Point"}
}