{
  "type": "Feature",
  "properties": {
    "addr:full":"Rue De Couillet 41-43 Ch\u00e2telet Hainaut 6200",
    "addr:housenumber":"41-43",
    "addr:postcode":"6200",
    "addr:street":"Rue De Couillet",
    "iso:country":"BE",
    "sg:address":"Rue De Couillet 41-43",
    "sg:city":"Ch\u00e2telet",
    "sg:classifiers":[
        {
            "category":"Professional",
            "subcategory":"Testing Lab",
            "type":"Services"
        }
    ],
    "sg:phone":"+32 71 38 18 28",
    "sg:postcode":"6200",
    "sg:province":"Hainaut",
    "sg:tags":[
        "chemist"
    ],
    "wof:name":"Pharmacie Blanche Medical",
    "wof:placetype":"venue"
},
  "geometry": {"coordinates":[4.5160398483,50.4036560059],"type":"Point"}
}