{
  "type": "Feature",
  "properties": {
    "addr:full":"Glabbeeksesteenweg 6 Tielt-winge Vlaams-Brabant 3390",
    "addr:housenumber":"6",
    "addr:postcode":"3390",
    "addr:street":"Glabbeeksesteenweg",
    "iso:country":"BE",
    "sg:address":"Glabbeeksesteenweg 6",
    "sg:city":"Tielt-winge",
    "sg:orig_category":"Enseignement maternel and primaire",
    "sg:phone":"+32 16 63 45 32",
    "sg:postcode":"3390",
    "sg:province":"Vlaams-Brabant",
    "wof:name":"B.s.g.o. De Winge",
    "wof:placetype":"venue"
},
  "geometry": {"coordinates":[4.8843212128,50.9079246521],"type":"Point"}
}