{
  "type": "Feature",
  "properties": {
    "iso:country":"BE",
    "sg:address":"Stockay 17",
    "sg:city":"Jalhay",
    "sg:classifiers":[
        {
            "category":"Social Services",
            "subcategory":"Job Training",
            "type":"Services"
        }
    ],
    "sg:phone":"+32 87 47 44 00",
    "sg:postcode":"4845",
    "sg:province":"Li\u00e8ge",
    "sg:tags":[
        "de",
        "terrain",
        "camping"
    ],
    "wof:name":"Camping Touring Club",
    "wof:placetype":"venue"
},
  "geometry": {"coordinates":[5.9721851349,50.5571899414],"type":"Point"}
}