{
  "type": "Feature",
  "properties": {
    "addr:full":"Chauss\u00c9e De Bruxelles 148 Tournai Hainaut 7500",
    "addr:housenumber":"148",
    "addr:postcode":"7500",
    "addr:street":"Chausse\u0301E De Bruxelles",
    "iso:country":"BE",
    "sg:address":"Chauss\u00c9e De Bruxelles 148",
    "sg:city":"Tournai",
    "sg:orig_category":"Jardinage",
    "sg:phone":"+32 69 84 54 80",
    "sg:postcode":"7500",
    "sg:province":"Hainaut",
    "wof:name":"Art-green",
    "wof:placetype":"venue"
},
  "geometry": {"coordinates":[3.4406790733,50.600315094],"type":"Point"}
}