{
  "type": "Feature",
  "properties": {
    "addr:full":"Rue De L' Ange 56 Namen (groot) Namur 5000",
    "addr:housenumber":"56",
    "addr:postcode":"5000",
    "addr:street":"Rue De L ' Ange;Groot Namur",
    "iso:country":"BE",
    "sg:address":"Rue De L' Ange 56",
    "sg:city":"Namen (groot)",
    "sg:orig_category":"V\u00eatements. Textiles",
    "sg:phone":"+32 81 22 24 12",
    "sg:postcode":"5000",
    "sg:province":"Namur",
    "wof:name":"Veritas",
    "wof:placetype":"venue"
},
  "geometry": {"coordinates":[4.8654460907,50.4641723633],"type":"Point"}
}