{
  "type": "Feature",
  "properties": {
    "iso:country":"BE",
    "sg:address":"Kwikstaartstraat 3",
    "sg:city":"Genk",
    "sg:orig_category":"Sportclubs Sportterreinen and installaties behalve sportcentra",
    "sg:phone":"+32 89 38 43 43",
    "sg:postcode":"3600",
    "sg:province":"Limburg",
    "wof:name":"Euro-afro Genk",
    "wof:placetype":"venue"
},
  "geometry": {"coordinates":[5.5218248367,51.00258255],"type":"Point"}
}