{
  "type": "Feature",
  "properties": {
    "iso:country":"BE",
    "sg:address":"Rietbroek 1",
    "sg:city":"Herentals",
    "sg:classifiers":[
        {
            "category":"Parking",
            "subcategory":"Lot",
            "type":"Transportation"
        }
    ],
    "sg:phone":"+32 14 22 28 00",
    "sg:postcode":"2200",
    "sg:province":"Antwerpen",
    "sg:tags":[
        "parking-places",
        "laying-out"
    ],
    "wof:name":"Aannemingen De Peuter Nv",
    "wof:placetype":"venue"
},
  "geometry": {"coordinates":[4.8073978424,51.1699714661],"type":"Point"}
}