{
  "type": "Feature",
  "properties": {
    "iso:country":"BE",
    "sg:address":"Anne Frankplein 17",
    "sg:city":"Hasselt",
    "sg:classifiers":[
        {
            "category":"Health Services",
            "subcategory":"Doctor",
            "type":"Services"
        }
    ],
    "sg:phone":"+32 11 22 43 00",
    "sg:postcode":"3500",
    "sg:province":"Limburg",
    "sg:tags":[
        "medicinephysicians",
        "surgeon"
    ],
    "wof:name":"Lenaerts Jan",
    "wof:placetype":"venue"
},
  "geometry": {"coordinates":[5.3437190056,50.9209899902],"type":"Point"}
}