{
  "type": "Feature",
  "properties": {
    "addr:full":"Kapellekensweg 2 Leuven Vlaams-Brabant 3010",
    "addr:housenumber":"2",
    "addr:postcode":"3010",
    "addr:street":"Kapellekensweg",
    "iso:country":"BE",
    "sg:address":"Kapellekensweg 2",
    "sg:city":"Leuven",
    "sg:classifiers":[
        {
            "category":"Organizations",
            "subcategory":"Community Association",
            "type":"Services"
        }
    ],
    "sg:phone":"+32 16 35 05 50",
    "sg:postcode":"3010",
    "sg:province":"Vlaams-Brabant",
    "sg:tags":[
        "organisation"
    ],
    "wof:name":"Spelewei",
    "wof:placetype":"venue"
},
  "geometry": {"coordinates":[4.7304501534,50.889755249],"type":"Point"}
}