{
  "type": "Feature",
  "properties": {
    "addr:full":"Brusselsesteenweg 298 Wetteren Oost-Vlaanderen 9230",
    "addr:housenumber":"298",
    "addr:postcode":"9230",
    "addr:street":"Brusselsesteenweg",
    "iso:country":"BE",
    "sg:address":"Brusselsesteenweg 298",
    "sg:city":"Wetteren",
    "sg:classifiers":[
        {
            "category":"Real Estate",
            "subcategory":"Real Estate Services",
            "type":"Services"
        }
    ],
    "sg:phone":"+32 9 369 49 56",
    "sg:postcode":"9230",
    "sg:province":"Oost-Vlaanderen",
    "wof:name":"Immo Fratti",
    "wof:placetype":"venue"
},
  "geometry": {"coordinates":[3.8492879868,50.9820327759],"type":"Point"}
}