{
  "type": "Feature",
  "properties": {
    "iso:country":"BE",
    "sg:address":"Rue Martin Sandron 153",
    "sg:city":"Doische",
    "sg:classifiers":[
        {
            "category":"Health Services",
            "subcategory":"Doctor",
            "type":"Services"
        }
    ],
    "sg:phone":"+32 82 67 74 36",
    "sg:postcode":"5680",
    "sg:province":"Namur",
    "sg:tags":[
        "medicinephysicians",
        "surgeon"
    ],
    "wof:name":"Dubuc Mich\u00e8le",
    "wof:placetype":"venue"
},
  "geometry": {"coordinates":[4.7398571968,50.1357650757],"type":"Point"}
}