{
  "type": "Feature",
  "properties": {
    "iso:country":"BE",
    "sg:address":"Kinderlaan 45",
    "sg:city":"Koksijde (oostduinkerke)",
    "sg:classifiers":[
        {
            "category":"Travel",
            "subcategory":"Resort",
            "type":"Entertainment"
        }
    ],
    "sg:phone":"+32 58 23 40 52",
    "sg:postcode":"8670",
    "sg:province":"West-Vlaanderen",
    "sg:tags":[
        "vacation"
    ],
    "wof:name":"Hoge Duin",
    "wof:placetype":"venue"
},
  "geometry": {"coordinates":[2.7093629837,51.1388015747],"type":"Point"}
}