{
  "type": "Feature",
  "properties": {
    "addr:full":"Rue Martin V 40 Sint-lambrechts-woluwe/woluwe-saint-lambert Bruxelles-Capitale 1200",
    "addr:housenumber":"40",
    "addr:postcode":"1200",
    "addr:street":"Rue Martin V",
    "iso:country":"BE",
    "sg:address":"Rue Martin V 40",
    "sg:city":"Sint-lambrechts-woluwe/woluwe-saint-lambert",
    "sg:orig_category":"Ramassage and traitement des d\u00e9chets m\u00e9nagers",
    "sg:phone":"+32 2 775 03 50",
    "sg:postcode":"1200",
    "sg:province":"Bruxelles-Capitale",
    "wof:name":"Fost Plus",
    "wof:placetype":"venue"
},
  "geometry": {"coordinates":[4.4528942108,50.8498077393],"type":"Point"}
}