{
  "type": "Feature",
  "properties": {
    "addr:full":"Rue Hydraulique 12 Sint-joost-ten-node/saint-josse-ten-noode Bruxelles-Capitale 1210",
    "addr:housenumber":"12",
    "addr:postcode":"1210",
    "addr:street":"Rue Hydraulique",
    "iso:country":"BE",
    "sg:address":"Rue Hydraulique 12",
    "sg:city":"Sint-joost-ten-node/saint-josse-ten-noode",
    "sg:orig_category":"R\u00e9parations de chaussures and articles en cuir",
    "sg:phone":"+32 2 217 93 07",
    "sg:postcode":"1210",
    "sg:province":"Bruxelles-Capitale",
    "wof:name":"Diego Vaccarello",
    "wof:placetype":"venue"
},
  "geometry": {"coordinates":[4.3714241982,50.848110199],"type":"Point"}
}