{
  "type": "Feature",
  "properties": {
    "addr:full":"Strijbroeklei 3b41 Sint-katelijne-waver Antwerpen 2860",
    "addr:housenumber":"3b41",
    "addr:postcode":"2860",
    "addr:street":"Strijbroeklei",
    "iso:country":"BE",
    "sg:address":"Strijbroeklei 3b41",
    "sg:city":"Sint-katelijne-waver",
    "sg:orig_category":"Groenten and fruit Gh",
    "sg:phone":"+32 15 31 74 41",
    "sg:postcode":"2860",
    "sg:province":"Antwerpen",
    "wof:name":"Frugro",
    "wof:placetype":"venue"
},
  "geometry": {"coordinates":[4.5131659508,51.0611305237],"type":"Point"}
}