{
  "type": "Feature",
  "properties": {
    "iso:country":"BE",
    "sg:address":"Rue De Waroux 299",
    "sg:city":"Ans",
    "sg:orig_category":"Bouwmaterialen Gh",
    "sg:phone":"+32 4 239 07 00",
    "sg:postcode":"4432",
    "sg:province":"Li\u00e8ge",
    "wof:name":"Techniques Et Materiaux",
    "wof:placetype":"venue"
},
  "geometry": {"coordinates":[5.4966268539,50.6823196411],"type":"Point"}
}