{
  "type": "Feature",
  "properties": {
    "addr:full":"Rue Haute 8 Vise Li\u00e8ge 4600",
    "addr:housenumber":"8",
    "addr:postcode":"4600",
    "addr:street":"Rue Haute",
    "iso:country":"BE",
    "sg:address":"Rue Haute 8",
    "sg:city":"Vise",
    "sg:orig_category":"Brood, gebak and snoepgoed",
    "sg:phone":"+32 4 379 06 26",
    "sg:postcode":"4600",
    "sg:province":"Li\u00e8ge",
    "wof:name":"Question De Go\u00dbts",
    "wof:placetype":"venue"
},
  "geometry": {"coordinates":[5.6950669289,50.734916687],"type":"Point"}
}