{
  "type": "Feature",
  "properties": {
    "addr:full":"Maasdal 142 Halle (lembeek) Vlaams-Brabant 1502",
    "addr:housenumber":"142;1502",
    "addr:street":"Maasdal",
    "iso:country":"BE",
    "sg:address":"Maasdal 142",
    "sg:city":"Halle (lembeek)",
    "sg:classifiers":[
        {
            "category":"Freight",
            "type":"Transportation"
        }
    ],
    "sg:phone":"+32 2 356 56 77",
    "sg:postcode":"1502",
    "sg:province":"Vlaams-Brabant",
    "sg:tags":[
        "-",
        "transport"
    ],
    "wof:name":"Vandenbrande Transport Bvba Bvba",
    "wof:placetype":"venue"
},
  "geometry": {"coordinates":[4.2467341423,50.7094535828],"type":"Point"}
}