{
  "type": "Feature",
  "properties": {
    "iso:country":"BE",
    "sg:address":"Waarloossteenweg 4b",
    "sg:city":"Duffel",
    "sg:classifiers":[
        {
            "category":"Personal",
            "type":"Services"
        }
    ],
    "sg:phone":"+32 15 31 51 59",
    "sg:postcode":"2570",
    "sg:province":"Antwerpen",
    "sg:tags":[
        "party",
        "planning"
    ],
    "wof:name":"Fonteyn (de)",
    "wof:placetype":"venue"
},
  "geometry": {"coordinates":[4.4892268181,51.0996208191],"type":"Point"}
}