{
  "type": "Feature",
  "properties": {
    "addr:full":"Kasteelstraat 54 Assenede Oost-Vlaanderen 9960",
    "addr:housenumber":"54",
    "addr:postcode":"9960",
    "addr:street":"Kasteelstraat",
    "iso:country":"BE",
    "sg:address":"Kasteelstraat 54",
    "sg:city":"Assenede",
    "sg:orig_category":"Artsen and specialisten",
    "sg:phone":"+32 9 344 50 64",
    "sg:postcode":"9960",
    "sg:province":"Oost-Vlaanderen",
    "wof:name":"Paul Cammaert",
    "wof:placetype":"venue"
},
  "geometry": {"coordinates":[3.7522289753,51.2267074585],"type":"Point"}
}