{
  "type": "Feature",
  "properties": {
    "addr:full":"Kloosterstraat 7 Antwerpen Antwerpen 2000",
    "addr:housenumber":"7",
    "addr:postcode":"2000",
    "addr:street":"Kloosterstraat",
    "iso:country":"BE",
    "sg:address":"Kloosterstraat 7",
    "sg:city":"Antwerpen",
    "sg:classifiers":[
        {
            "category":"Real Estate",
            "subcategory":"Architect",
            "type":"Services"
        }
    ],
    "sg:phone":"+32 3 234 23 21",
    "sg:postcode":"2000",
    "sg:province":"Antwerpen",
    "wof:name":"Wendelen S",
    "wof:placetype":"venue"
},
  "geometry": {"coordinates":[4.3958101273,51.2170944214],"type":"Point"}
}