{
  "type": "Feature",
  "properties": {
    "addr:full":"Rue Des Acremonts 9 Lustin Namur 5170",
    "addr:housenumber":"9",
    "addr:postcode":"5170",
    "addr:street":"Rue Des Acremonts",
    "iso:country":"BE",
    "sg:address":"Rue Des Acremonts 9",
    "sg:city":"Lustin",
    "sg:classifiers":[
        {
            "category":"Government",
            "subcategory":"Fire Station",
            "type":"Public Place"
        }
    ],
    "sg:phone":"+32 71 35 69 43",
    "sg:postcode":"5170",
    "sg:province":"Namur",
    "sg:tags":[
        "supraregional",
        "plant",
        "installation",
        "heating"
    ],
    "wof:name":"Etablissements Jordan S.a.",
    "wof:placetype":"venue"
},
  "geometry": {"coordinates":[4.416041851,50.4439849854],"type":"Point"}
}