{
  "type": "Feature",
  "properties": {
    "addr:full":"Hendrik Kennisstraat 18 Edegem Antwerpen 2650",
    "addr:housenumber":"18",
    "addr:postcode":"2650",
    "addr:street":"Hendrik Kennisstraat",
    "iso:country":"BE",
    "sg:address":"Hendrik Kennisstraat 18",
    "sg:city":"Edegem",
    "sg:orig_category":"Installation \u00e9lectrique r\u00e9sidentielle",
    "sg:phone":"+32 3 448 08 56",
    "sg:postcode":"2650",
    "sg:province":"Antwerpen",
    "wof:name":"C. Govers",
    "wof:placetype":"venue"
},
  "geometry": {"coordinates":[4.417760849,51.1637687683],"type":"Point"}
}