{
  "type": "Feature",
  "properties": {
    "addr:full":"Coghenlaan 29 Ukkel/uccle Bruxelles-Capitale 1180",
    "addr:housenumber":"29",
    "addr:postcode":"1180",
    "addr:street":"Coghenlaan;/",
    "iso:country":"BE",
    "sg:address":"Coghenlaan 29",
    "sg:city":"Ukkel/uccle",
    "sg:orig_category":"Architecten",
    "sg:phone":"+32 2 343 06 01",
    "sg:postcode":"1180",
    "sg:province":"Bruxelles-Capitale",
    "wof:name":"Laurent Van Eyck",
    "wof:placetype":"venue"
},
  "geometry": {"coordinates":[4.3400149345,50.8127403259],"type":"Point"}
}