{
  "type": "Feature",
  "properties": {
    "addr:full":"Beringstraat 37 Boortmeerbeek Vlaams-Brabant 3190",
    "addr:housenumber":"37",
    "addr:postcode":"3190",
    "addr:street":"Beringstraat",
    "iso:country":"BE",
    "sg:address":"Beringstraat 37",
    "sg:city":"Boortmeerbeek",
    "sg:classifiers":[
        {
            "category":"Restaurant",
            "type":"Food & Drink"
        }
    ],
    "sg:phone":"+32 15 52 84 28",
    "sg:postcode":"3190",
    "sg:province":"Vlaams-Brabant",
    "wof:name":"De Lork",
    "wof:placetype":"venue"
},
  "geometry": {"coordinates":[4.5716910362,50.9777946472],"type":"Point"}
}