{
  "type": "Feature",
  "properties": {
    "addr:full":"Emile Wautersstraat 119 Brussel/bruxelles Bruxelles-Capitale 1020",
    "addr:housenumber":"119",
    "addr:postcode":"1020",
    "addr:street":"Emile Wautersstraat;/",
    "iso:country":"BE",
    "sg:address":"Emile Wautersstraat 119",
    "sg:city":"Brussel/bruxelles",
    "sg:orig_category":"Woningbouw",
    "sg:phone":"+32 2 479 04 56",
    "sg:postcode":"1020",
    "sg:province":"Bruxelles-Capitale",
    "wof:name":"Troisfontaines",
    "wof:placetype":"venue"
},
  "geometry": {"coordinates":[4.3431348801,50.8888664246],"type":"Point"}
}