{
  "type": "Feature",
  "properties": {
    "addr:full":"Tiensebaan 95 Bekkevoort Vlaams-Brabant 3461",
    "addr:housenumber":"95",
    "addr:postcode":"3461",
    "addr:street":"Tiensebaan",
    "iso:country":"BE",
    "sg:address":"Tiensebaan 95",
    "sg:city":"Bekkevoort",
    "sg:orig_category":"Rundveehouders",
    "sg:phone":"+32 16 77 96 22",
    "sg:postcode":"3461",
    "sg:province":"Vlaams-Brabant",
    "wof:name":"Diana Gilis",
    "wof:placetype":"venue"
},
  "geometry": {"coordinates":[4.9439711571,50.9061813354],"type":"Point"}
}