{
  "type": "Feature",
  "properties": {
    "iso:country":"BE",
    "sg:address":"Brugstraat 5",
    "sg:city":"Avelgem",
    "sg:orig_category":"Plaatsen van vloer- and muurbekleding Vloer- and muurbekleding",
    "sg:phone":"+32 55 38 78 62",
    "sg:postcode":"8581",
    "sg:province":"West-Vlaanderen",
    "wof:name":"Tony Destorme",
    "wof:placetype":"venue"
},
  "geometry": {"coordinates":[3.5000200272,50.7991867065],"type":"Point"}
}