{
  "type": "Feature",
  "properties": {
    "addr:full":"Dorpsstraat 86 Stekene Oost-Vlaanderen 9190",
    "addr:housenumber":"86",
    "addr:postcode":"9190",
    "addr:street":"Dorpsstraat",
    "iso:country":"BE",
    "sg:address":"Dorpsstraat 86",
    "sg:city":"Stekene",
    "sg:classifiers":[
        {
            "category":"Personal",
            "subcategory":"Beauty Salon",
            "type":"Services"
        }
    ],
    "sg:phone":"+32 3 779 51 98",
    "sg:postcode":"9190",
    "sg:province":"Oost-Vlaanderen",
    "wof:name":"Odea",
    "wof:placetype":"venue"
},
  "geometry": {"coordinates":[4.0386490822,51.2039337158],"type":"Point"}
}