{
  "type": "Feature",
  "properties": {
    "iso:country":"BE",
    "sg:address":"Boulevard De La Sauveni\u00c8re 70",
    "sg:city":"Liege",
    "sg:orig_category":"Sociale secretariaten",
    "sg:phone":"+32 4 223 06 76",
    "sg:postcode":"4000",
    "sg:province":"Li\u00e8ge",
    "wof:name":"Intersociale",
    "wof:placetype":"venue"
},
  "geometry": {"coordinates":[5.5664811134,50.6439094543],"type":"Point"}
}