{
  "type": "Feature",
  "properties": {
    "iso:country":"BE",
    "sg:address":"Komenstraat 73",
    "sg:city":"Heuvelland (wijtschate)",
    "sg:classifiers":[
        {
            "category":"Wholesale",
            "subcategory":"Meat",
            "type":"Manufacturing & Wholesale Goods"
        }
    ],
    "sg:phone":"+32 57 45 25 00",
    "sg:postcode":"8953",
    "sg:province":"West-Vlaanderen",
    "sg:tags":[
        "abattoir"
    ],
    "wof:name":"Covameat Nv",
    "wof:placetype":"venue"
},
  "geometry": {"coordinates":[2.9034330845,50.7669219971],"type":"Point"}
}