{
  "type": "Feature",
  "properties": {
    "iso:country":"BE",
    "sg:address":"Wechelsebaan 64",
    "sg:city":"Lille",
    "sg:orig_category":"Non-Classified Establishments",
    "sg:phone":"+32 14 43 58 75",
    "sg:postcode":"2275",
    "sg:province":"Antwerpen",
    "wof:name":"Loraine",
    "wof:placetype":"venue"
},
  "geometry": {"coordinates":[4.8212537766,51.2446022034],"type":"Point"}
}