{
  "type": "Feature",
  "properties": {
    "iso:country":"BE",
    "sg:address":"Oostmalsesteenweg 185",
    "sg:city":"Rijkevorsel",
    "sg:classifiers":[
        {
            "category":"Airport",
            "subcategory":"International",
            "type":"Transportation"
        }
    ],
    "sg:phone":"+32 495 28 25 20",
    "sg:postcode":"2310",
    "sg:province":"Antwerpen",
    "sg:tags":[
        "-",
        "transport"
    ],
    "wof:name":"Transport Verlinden Peter Bvba",
    "wof:placetype":"venue"
},
  "geometry": {"coordinates":[4.7521548271,51.3374824524],"type":"Point"}
}