{
  "type": "Feature",
  "properties": {
    "addr:full":"Dunantstraat 28 Beringen (koersel) Limburg 3582",
    "addr:housenumber":"28",
    "addr:postcode":"3582",
    "addr:street":"Dunantstraat",
    "iso:country":"BE",
    "sg:address":"Dunantstraat 28",
    "sg:city":"Beringen (koersel)",
    "sg:classifiers":[
        {
            "category":"Building & Trades",
            "subcategory":"Cleaning & Sanitation",
            "type":"Services"
        }
    ],
    "sg:phone":"+32 11 73 57 05",
    "sg:postcode":"3582",
    "sg:province":"Limburg",
    "sg:tags":[
        "fa\u00e7ade",
        "maintenance"
    ],
    "wof:name":"Swerts G",
    "wof:placetype":"venue"
},
  "geometry": {"coordinates":[5.2708749771,51.0595359802],"type":"Point"}
}