{
  "type": "Feature",
  "properties": {
    "addr:full":"Rue De Pi\u00c9train 7 Jodoigne Brabant Wallon 1370",
    "addr:housenumber":"7",
    "addr:postcode":"1370",
    "addr:street":"Rue De Pie\u0301Train",
    "iso:country":"BE",
    "sg:address":"Rue De Pi\u00c9train 7",
    "sg:city":"Jodoigne",
    "sg:orig_category":"V\u00eatements sur mesure Fab",
    "sg:phone":"+32 10 81 20 06",
    "sg:postcode":"1370",
    "sg:province":"Brabant Wallon",
    "wof:name":"Marie Michele",
    "wof:placetype":"venue"
},
  "geometry": {"coordinates":[4.8724918365,50.724395752],"type":"Point"}
}