{
  "type": "Feature",
  "properties": {
    "addr:full":"Chemin De La Procession 247 Mons Hainaut 7000",
    "addr:housenumber":"247",
    "addr:postcode":"7000",
    "addr:street":"Chemin De La Procession;Hainaut",
    "iso:country":"BE",
    "sg:address":"Chemin De La Procession 247",
    "sg:city":"Mons",
    "sg:orig_category":"Diverse bedrijfsbeheeradviesbureaus",
    "sg:phone":"+32 65 35 73 00",
    "sg:postcode":"7000",
    "sg:province":"Hainaut",
    "wof:name":"D.p.consult",
    "wof:placetype":"venue"
},
  "geometry": {"coordinates":[3.9668819904,50.4625778198],"type":"Point"}
}