{
  "type": "Feature",
  "properties": {
    "iso:country":"BE",
    "sg:address":"Turkeyenhoeklos 2",
    "sg:city":"Nazareth (eke)",
    "sg:classifiers":[
        {
            "category":"Farming",
            "subcategory":"Fish & Marine Products",
            "type":"Manufacturing & Wholesale Goods"
        }
    ],
    "sg:phone":"+32 9 384 56 12",
    "sg:postcode":"9810",
    "sg:province":"Oost-Vlaanderen",
    "sg:tags":[
        "equipment",
        "fishery"
    ],
    "wof:name":"Snephoek",
    "wof:placetype":"venue"
},
  "geometry": {"coordinates":[3.5967800617,50.9596405029],"type":"Point"}
}