{
  "type": "Feature",
  "properties": {
    "addr:full":"Rue D'anderlues 62 Lobbes Hainaut 6540",
    "addr:housenumber":"62",
    "addr:postcode":"6540",
    "addr:street":"Rue D'Anderlues",
    "iso:country":"BE",
    "sg:address":"Rue D'anderlues 62",
    "sg:city":"Lobbes",
    "sg:orig_category":"Artsen and specialisten",
    "sg:phone":"+32 71 59 19 45",
    "sg:postcode":"6540",
    "sg:province":"Hainaut",
    "wof:name":"Alex Delposen",
    "wof:placetype":"venue"
},
  "geometry": {"coordinates":[4.2760481834,50.3726272583],"type":"Point"}
}