{
  "type": "Feature",
  "properties": {
    "addr:full":"Ruiterstraat 110 Hamont-achel Limburg 3930",
    "addr:housenumber":"110",
    "addr:postcode":"3930",
    "addr:street":"Ruiterstraat",
    "iso:country":"BE",
    "sg:address":"Ruiterstraat 110",
    "sg:city":"Hamont-achel",
    "sg:orig_category":"Eleveurs and marchands de porcs",
    "sg:phone":"+32 11 44 50 73",
    "sg:postcode":"3930",
    "sg:province":"Limburg",
    "wof:name":"Nooijen",
    "wof:placetype":"venue"
},
  "geometry": {"coordinates":[5.5450549126,51.2511863708],"type":"Point"}
}