{
  "type": "Feature",
  "properties": {
    "addr:full":"Pontstraat 80 Waregem West-Vlaanderen 8791",
    "addr:housenumber":"80",
    "addr:postcode":"8791",
    "addr:street":"Pontstraat",
    "iso:country":"BE",
    "sg:address":"Pontstraat 80",
    "sg:city":"Waregem",
    "sg:orig_category":"Meubles D\u00e9taillants, Am\u00e9nagement de B\u00e2timents et de Cuisines",
    "sg:phone":"+32 56 71 46 44",
    "sg:postcode":"8791",
    "sg:province":"West-Vlaanderen",
    "wof:name":"Meubelfabriek Desmet",
    "wof:placetype":"venue"
},
  "geometry": {"coordinates":[3.3268110752,50.8713188171],"type":"Point"}
}