{
  "type": "Feature",
  "properties": {
    "addr:full":"Stationsstraat 51 Deerlijk West-Vlaanderen 8540",
    "addr:housenumber":"51",
    "addr:postcode":"8540",
    "addr:street":"Stationsstraat",
    "iso:country":"BE",
    "sg:address":"Stationsstraat 51",
    "sg:city":"Deerlijk",
    "sg:orig_category":"Boucheries",
    "sg:phone":"+32 56 71 84 65",
    "sg:postcode":"8540",
    "sg:province":"West-Vlaanderen",
    "wof:name":"Claude Taelman",
    "wof:placetype":"venue"
},
  "geometry": {"coordinates":[3.3518130779,50.8506889343],"type":"Point"}
}