{
  "type": "Feature",
  "properties": {
    "addr:full":"Rue Des Biolettes 44 Sprimont Li\u00e8ge 4140",
    "addr:housenumber":"44",
    "addr:postcode":"4140",
    "addr:street":"Rue Des Biolettes",
    "iso:country":"BE",
    "sg:address":"Rue Des Biolettes 44",
    "sg:city":"Sprimont",
    "sg:classifiers":[
        {
            "category":"Banks & Credit Unions",
            "subcategory":"Investment Brokerage",
            "type":"Services"
        }
    ],
    "sg:phone":"+32 4 257 66 66",
    "sg:postcode":"4140",
    "sg:province":"Li\u00e8ge",
    "sg:tags":[
        "auditor"
    ],
    "wof:name":"Lux P",
    "wof:placetype":"venue"
},
  "geometry": {"coordinates":[5.6611199379,50.5175285339],"type":"Point"}
}