{
  "type": "Feature",
  "properties": {
    "addr:full":"Rue Gahy 4 Momignies Hainaut 6590",
    "addr:housenumber":"4",
    "addr:postcode":"6590",
    "addr:street":"Rue Gahy;Hainaut",
    "iso:country":"BE",
    "sg:address":"Rue Gahy 4",
    "sg:city":"Momignies",
    "sg:orig_category":"Rundveehouders Varkenskwekers",
    "sg:phone":"+32 60 51 19 00",
    "sg:postcode":"6590",
    "sg:province":"Hainaut",
    "wof:name":"Martin Vercruysse",
    "wof:placetype":"venue"
},
  "geometry": {"coordinates":[4.1659998894,50.0325889587],"type":"Point"}
}