{
  "type": "Feature",
  "properties": {
    "iso:country":"BE",
    "sg:address":"Geraardsbergsestraat 157",
    "sg:city":"Brakel (nederbrakel)",
    "sg:classifiers":[
        {
            "category":"Professional",
            "subcategory":"Advertising",
            "type":"Services"
        }
    ],
    "sg:phone":"+32 55 42 68 87",
    "sg:postcode":"9660",
    "sg:province":"Oost-Vlaanderen",
    "sg:tags":[
        "painter"
    ],
    "wof:name":"Airbrush-art",
    "wof:placetype":"venue"
},
  "geometry": {"coordinates":[3.7743330002,50.7922859192],"type":"Point"}
}