{
  "type": "Feature",
  "properties": {
    "addr:full":"Chauss\u00e9e De Bruxelles 149-1 Tournai Hainaut 7500",
    "addr:postcode":"149-1;7500",
    "addr:street":"Chausse\u0301E De Bruxelles;Hainaut",
    "iso:country":"BE",
    "sg:address":"Chauss\u00e9e De Bruxelles 149-1",
    "sg:city":"Tournai",
    "sg:classifiers":[
        {
            "category":"Professional",
            "subcategory":"Computer Services",
            "type":"Services"
        }
    ],
    "sg:phone":"+32 69 84 79 54",
    "sg:postcode":"7500",
    "sg:province":"Hainaut",
    "sg:tags":[
        "-",
        "processing",
        "data"
    ],
    "wof:name":"Alphanet",
    "wof:placetype":"venue"
},
  "geometry": {"coordinates":[3.4160020351,50.603969574],"type":"Point"}
}