{
  "type": "Feature",
  "properties": {
    "addr:full":"Wez-des-rulles 2 Bertrix Luxembourg 6880",
    "addr:housenumber":"2",
    "addr:postcode":"6880",
    "addr:street":"Wez-Des-Rulles",
    "iso:country":"BE",
    "sg:address":"Wez-des-rulles 2",
    "sg:city":"Bertrix",
    "sg:orig_category":"D\u00e9molition d\u00b4immeubles and terrassements",
    "sg:phone":"+32 61 41 23 39",
    "sg:postcode":"6880",
    "sg:province":"Luxembourg",
    "wof:name":"Zachary",
    "wof:placetype":"venue"
},
  "geometry": {"coordinates":[5.2655792236,49.8441619873],"type":"Point"}
}