{
  "type": "Feature",
  "properties": {
    "iso:country":"BE",
    "sg:address":"Gentsestraat 47",
    "sg:city":"Aalst",
    "sg:classifiers":[
        {
            "category":"Bars & Pubs",
            "type":"Food & Drink"
        }
    ],
    "sg:phone":"+32 53 60 81 61",
    "sg:postcode":"9300",
    "sg:province":"Oost-Vlaanderen",
    "wof:name":"Oliver Twist",
    "wof:placetype":"venue"
},
  "geometry": {"coordinates":[4.0314559937,50.9378509521],"type":"Point"}
}