{
  "type": "Feature",
  "properties": {
    "iso:country":"BE",
    "sg:address":"Rue Des Martyrs 33",
    "sg:city":"Verviers",
    "sg:classifiers":[
        {
            "category":"Banks & Credit Unions",
            "subcategory":"Financial Services",
            "type":"Services"
        }
    ],
    "sg:phone":"+32 87 34 01 50",
    "sg:postcode":"4800",
    "sg:province":"Li\u00e8ge",
    "sg:tags":[
        "group"
    ],
    "wof:name":"Credior Sa",
    "wof:placetype":"venue"
},
  "geometry": {"coordinates":[5.8632788658,50.5914802551],"type":"Point"}
}