{
  "type": "Feature",
  "properties": {
    "iso:country":"BE",
    "sg:address":"Motstraat 32",
    "sg:city":"Mechelen",
    "sg:classifiers":[
        {
            "category":"Shopping",
            "subcategory":"Books",
            "type":"Retail Goods"
        }
    ],
    "sg:phone":"+32 15 36 36 36",
    "sg:postcode":"2800",
    "sg:province":"Antwerpen",
    "sg:tags":[
        "text",
        "school",
        "books",
        "material",
        "learning"
    ],
    "wof:name":"Wolters Plantyn Nv",
    "wof:placetype":"venue"
},
  "geometry": {"coordinates":[4.4869408607,51.014995575],"type":"Point"}
}