{
  "type": "Feature",
  "properties": {
    "addr:full":"Opitterkiezel 49 Bree Limburg 3960",
    "addr:housenumber":"49",
    "addr:postcode":"3960",
    "addr:street":"Opitterkiezel",
    "iso:country":"BE",
    "sg:address":"Opitterkiezel 49",
    "sg:city":"Bree",
    "sg:orig_category":"Catering and organisation de f\u00eates",
    "sg:phone":"+32 89 47 37 71",
    "sg:postcode":"3960",
    "sg:province":"Limburg",
    "wof:name":"Traiteur Leon",
    "wof:placetype":"venue"
},
  "geometry": {"coordinates":[5.6105751991,51.135761261],"type":"Point"}
}