{
  "type": "Feature",
  "properties": {
    "iso:country":"BE",
    "sg:address":"Aux Sept Pr\u00e9s 11",
    "sg:city":"Marche-en-famenne (on)",
    "sg:classifiers":[
        {
            "category":"Social Services",
            "type":"Services"
        }
    ],
    "sg:phone":"+32 84 21 02 83",
    "sg:postcode":"6900",
    "sg:province":"Luxembourg",
    "wof:name":"Sos Week-end-les Jeunes Tues De La Route Asbl",
    "wof:placetype":"venue"
},
  "geometry": {"coordinates":[5.3160119057,50.2028770447],"type":"Point"}
}