{
  "type": "Feature",
  "properties": {
    "addr:full":"Rue De La Glaci\u00e8re 34 Bruxelles (saint-gilles) Bruxelles-Capitale 1060",
    "addr:housenumber":"34",
    "addr:postcode":"1060",
    "addr:street":"Rue De La Glacie\u0300Re",
    "iso:country":"BE",
    "sg:address":"Rue De La Glaci\u00e8re 34",
    "sg:city":"Bruxelles (saint-gilles)",
    "sg:classifiers":[
        {
            "category":"Retail",
            "subcategory":"Auto Repair",
            "type":"Services"
        }
    ],
    "sg:phone":"+32 2 537 92 21",
    "sg:postcode":"1060",
    "sg:province":"Bruxelles-Capitale",
    "sg:tags":[
        "automobile-body"
    ],
    "wof:name":"Glaci\u00e8re (carrosserie De La)",
    "wof:placetype":"venue"
},
  "geometry": {"coordinates":[4.3509378433,50.822101593],"type":"Point"}
}