{
  "type": "Feature",
  "properties": {
    "addr:full":"Maastrichtersteenweg 198 Maaseik Limburg 3680",
    "addr:housenumber":"198",
    "addr:postcode":"3680",
    "addr:street":"Maastrichtersteenweg",
    "iso:country":"BE",
    "sg:address":"Maastrichtersteenweg 198",
    "sg:city":"Maaseik",
    "sg:classifiers":[
        {
            "category":"Animal Shelter",
            "type":"Public Place"
        }
    ],
    "sg:phone":"+32 89 56 26 16",
    "sg:postcode":"3680",
    "sg:province":"Limburg",
    "sg:tags":[
        "construction",
        "installation",
        "stable"
    ],
    "wof:name":"Sane",
    "wof:placetype":"venue"
},
  "geometry": {"coordinates":[5.7630038261,51.0832290649],"type":"Point"}
}