{
  "type": "Feature",
  "properties": {
    "iso:country":"BE",
    "sg:address":"Avenue Des Anciens Combattants 14",
    "sg:city":"Evere",
    "sg:orig_category":"Centres de relaxation and bien-\u00eatre. Instituts de beaut\u00e9",
    "sg:phone":"+32 2 726 93 98",
    "sg:postcode":"1140",
    "sg:province":"Bruxelles-Capitale",
    "wof:name":"Institut Allure",
    "wof:placetype":"venue"
},
  "geometry": {"coordinates":[4.4140100479,50.8600502014],"type":"Point"}
}