{
  "type": "Feature",
  "properties": {
    "iso:country":"BE",
    "sg:address":"Place De La Paix 1",
    "sg:city":"Bruxelles (evere)",
    "sg:classifiers":[
        {
            "category":"Retail",
            "subcategory":"Driving School",
            "type":"Services"
        }
    ],
    "sg:phone":"+32 2 241 33 33",
    "sg:postcode":"1140",
    "sg:province":"Bruxelles-Capitale",
    "sg:tags":[
        "automobile",
        "officially",
        "-",
        "recognized"
    ],
    "wof:name":"Autorijschool Van Brussel",
    "wof:placetype":"venue"
},
  "geometry": {"coordinates":[4.4005498886,50.8769264221],"type":"Point"}
}