{
  "type": "Feature",
  "properties": {
    "addr:full":"Petit-audenardestraat 19 Moeskroen/mouscron Hainaut 7712",
    "addr:housenumber":"19",
    "addr:postcode":"7712",
    "addr:street":"Petit-Audenardestraat",
    "iso:country":"BE",
    "sg:address":"Petit-audenardestraat 19",
    "sg:city":"Moeskroen/mouscron",
    "sg:orig_category":"MEUBELONTWERP AND -INSTALLATIE",
    "sg:phone":"+32 56 84 08 79",
    "sg:postcode":"7712",
    "sg:province":"Hainaut",
    "wof:name":"Cuisines Design & Tradit.",
    "wof:placetype":"venue"
},
  "geometry": {"coordinates":[3.2535879612,50.714931488],"type":"Point"}
}