{
  "type": "Feature",
  "properties": {
    "addr:full":"Hogerlucht 5 Ronse/renaix Oost-Vlaanderen 9600",
    "addr:housenumber":"5",
    "addr:postcode":"9600",
    "addr:street":"Hogerlucht",
    "iso:country":"BE",
    "sg:address":"Hogerlucht 5",
    "sg:city":"Ronse/renaix",
    "sg:orig_category":"Grands magasins",
    "sg:phone":"+32 55 21 12 91",
    "sg:postcode":"9600",
    "sg:province":"Oost-Vlaanderen",
    "wof:name":"Cindy Vanschamelhout",
    "wof:placetype":"venue"
},
  "geometry": {"coordinates":[3.605437994,50.7553482056],"type":"Point"}
}