{
  "type": "Feature",
  "properties": {
    "addr:full":"Dreefstraat 17a Bierbeek Vlaams-Brabant 3360",
    "addr:housenumber":"17a",
    "addr:postcode":"3360",
    "addr:street":"Dreefstraat",
    "iso:country":"BE",
    "sg:address":"Dreefstraat 17a",
    "sg:city":"Bierbeek",
    "sg:classifiers":[
        {
            "category":"Arena",
            "subcategory":"Sports Club",
            "type":"Entertainment"
        }
    ],
    "sg:phone":"+32 16 46 13 54",
    "sg:postcode":"3360",
    "sg:province":"Vlaams-Brabant",
    "wof:name":"T.c. Bierbeek",
    "wof:placetype":"venue"
},
  "geometry": {"coordinates":[4.7831950188,50.8568763733],"type":"Point"}
}