{
  "type": "Feature",
  "properties": {
    "iso:country":"BE",
    "sg:address":"Kiewitstraat 180",
    "sg:city":"Hasselt",
    "sg:classifiers":[
        {
            "category":"Military Area",
            "subcategory":"Armory",
            "type":"Public Place"
        }
    ],
    "sg:phone":"+32 11 23 13 64",
    "sg:postcode":"3500",
    "sg:province":"Limburg",
    "sg:tags":[
        "blade",
        "industrial",
        "-",
        "knife"
    ],
    "wof:name":"Ramaform",
    "wof:placetype":"venue"
},
  "geometry": {"coordinates":[5.389070034,50.9657783508],"type":"Point"}
}