{
  "type": "Feature",
  "properties": {
    "iso:country":"BE",
    "sg:address":"Armand Segerslei 16",
    "sg:city":"Mortsel",
    "sg:classifiers":[
        {
            "category":"Professional",
            "subcategory":"Lawyer & Legal Services",
            "type":"Services"
        }
    ],
    "sg:phone":"+32 3 449 82 56",
    "sg:postcode":"2640",
    "sg:province":"Antwerpen",
    "wof:name":"Vanrooy Stephan",
    "wof:placetype":"venue"
},
  "geometry": {"coordinates":[4.4461808205,51.1717414856],"type":"Point"}
}