{
  "type": "Feature",
  "properties": {
    "iso:country":"BE",
    "sg:address":"Kapelstraat 16",
    "sg:city":"Baarle-hertog",
    "sg:orig_category":"Rundveehouders",
    "sg:phone":"+32 14 69 92 24",
    "sg:postcode":"2387",
    "sg:province":"Antwerpen",
    "wof:name":"Johannes Van Kaam",
    "wof:placetype":"venue"
},
  "geometry": {"coordinates":[4.9330649376,51.4419593811],"type":"Point"}
}