{
  "type": "Feature",
  "properties": {
    "iso:country":"BE",
    "sg:address":"Dorpsstraat 57-1",
    "sg:city":"Wellen",
    "sg:classifiers":[
        {
            "category":"Insurance",
            "subcategory":"Insurance Agent",
            "type":"Services"
        }
    ],
    "sg:phone":"+32 12 74 10 08",
    "sg:postcode":"3830",
    "sg:province":"Limburg",
    "sg:tags":[
        "broker"
    ],
    "wof:name":"Hayen-feytons/schoofs",
    "wof:placetype":"venue"
},
  "geometry": {"coordinates":[5.3376188278,50.8407440186],"type":"Point"}
}