{
  "type": "Feature",
  "properties": {
    "iso:country":"BE",
    "sg:address":"Bakkersstraat 32",
    "sg:city":"Blankenberge",
    "sg:classifiers":[
        {
            "category":"Shopping",
            "subcategory":"Jewelry",
            "type":"Retail Goods"
        }
    ],
    "sg:phone":"+32 50 41 12 34",
    "sg:postcode":"8370",
    "sg:province":"West-Vlaanderen",
    "sg:tags":[
        "jeweller",
        "-"
    ],
    "wof:name":"Delaro",
    "wof:placetype":"venue"
},
  "geometry": {"coordinates":[3.1278440952,51.3149604797],"type":"Point"}
}