{
  "type": "Feature",
  "properties": {
    "iso:country":"BE",
    "sg:address":"Avenue Louis Bertrand 100ba26",
    "sg:city":"Schaarbeek/schaerbeek",
    "sg:orig_category":"Activit\u00e9s diverses d'imprimerie",
    "sg:phone":"+32 2 241 55 51",
    "sg:postcode":"1030",
    "sg:province":"Bruxelles-Capitale",
    "wof:name":"Totem's",
    "wof:placetype":"venue"
},
  "geometry": {"coordinates":[4.3796467781,50.8644714355],"type":"Point"}
}