{
  "type": "Feature",
  "properties": {
    "iso:country":"BE",
    "sg:address":"Nijverheidsstraat 17",
    "sg:city":"Pittem",
    "sg:classifiers":[
        {
            "category":"Manufacturing",
            "subcategory":"Rubber & Plastics",
            "type":"Manufacturing & Wholesale Goods"
        }
    ],
    "sg:phone":"+32 51 46 68 84",
    "sg:postcode":"8740",
    "sg:province":"West-Vlaanderen",
    "sg:tags":[
        "industrial",
        "-"
    ],
    "wof:name":"S.d.p. Kunststofkonstruktie Bvba",
    "wof:placetype":"venue"
},
  "geometry": {"coordinates":[3.2486739159,50.9918556213],"type":"Point"}
}