{
  "type": "Feature",
  "properties": {
    "iso:country":"BE",
    "sg:address":"Sint-pieterstraat 44",
    "sg:city":"Mol",
    "sg:classifiers":[
        {
            "category":"Health Services",
            "subcategory":"Doctor",
            "type":"Services"
        }
    ],
    "sg:phone":"+32 14 31 56 56",
    "sg:postcode":"2400",
    "sg:province":"Antwerpen",
    "sg:tags":[
        "medicinephysicians",
        "surgeon"
    ],
    "wof:name":"Delport K",
    "wof:placetype":"venue"
},
  "geometry": {"coordinates":[5.1124248505,51.1894836426],"type":"Point"}
}