{
  "type": "Feature",
  "properties": {
    "addr:full":"Chauss\u00c9e De Bruxelles 182 Vorst/forest Bruxelles-Capitale 1190",
    "addr:housenumber":"182",
    "addr:postcode":"1190",
    "addr:street":"Chausse\u0301E De Bruxelles;/ Forest",
    "iso:country":"BE",
    "sg:address":"Chauss\u00c9e De Bruxelles 182",
    "sg:city":"Vorst/forest",
    "sg:orig_category":"Artistes ind\u00e9pendants",
    "sg:phone":"+32 2 343 94 31",
    "sg:postcode":"1190",
    "sg:province":"Bruxelles-Capitale",
    "wof:name":"Emilio Danero Iglesias",
    "wof:placetype":"venue"
},
  "geometry": {"coordinates":[4.3260908127,50.8147850037],"type":"Point"}
}