{
  "type": "Feature",
  "properties": {
    "addr:full":"Korenbloemstraat 2 Torhout West-Vlaanderen 8820",
    "addr:housenumber":"2",
    "addr:postcode":"8820",
    "addr:street":"Korenbloemstraat",
    "iso:country":"BE",
    "sg:address":"Korenbloemstraat 2",
    "sg:city":"Torhout",
    "sg:classifiers":[
        {
            "category":"Home & Garden",
            "subcategory":"Kitchen Supply",
            "type":"Retail Goods"
        }
    ],
    "sg:phone":"+32 50 21 26 20",
    "sg:postcode":"8820",
    "sg:province":"West-Vlaanderen",
    "sg:tags":[
        "installation"
    ],
    "wof:name":"Vanbesien W",
    "wof:placetype":"venue"
},
  "geometry": {"coordinates":[3.1274650097,51.0832138062],"type":"Point"}
}