{
  "type": "Feature",
  "properties": {
    "iso:country":"BE",
    "sg:address":"Drogenbossesteenweg 102ba",
    "sg:city":"Ukkel/uccle",
    "sg:classifiers":[
        {
            "category":"Insurance",
            "subcategory":"Insurance Agent",
            "type":"Services"
        }
    ],
    "sg:phone":"+32 2 332 04 65",
    "sg:postcode":"1180",
    "sg:province":"Bruxelles-Capitale",
    "sg:tags":[
        "verzekeringsmakelaars",
        "expert"
    ],
    "wof:name":"Codelfinance",
    "wof:placetype":"venue"
},
  "geometry": {"coordinates":[4.3257451057,50.7866592407],"type":"Point"}
}