{
  "type": "Feature",
  "properties": {
    "iso:country":"BE",
    "sg:address":"Wijerstraat 1a Box 12",
    "sg:city":"Bilzen",
    "sg:classifiers":[
        {
            "category":"Autos & Motor Vehicles",
            "subcategory":"Auto Supplies",
            "type":"Retail Goods"
        }
    ],
    "sg:phone":"+32 479 55 95 40",
    "sg:postcode":"3740",
    "sg:province":"Limburg",
    "sg:tags":[
        "access",
        "automobile",
        "part",
        "-"
    ],
    "wof:name":"Mobile Technology Bvba",
    "wof:placetype":"venue"
},
  "geometry": {"coordinates":[5.5195260048,50.8728713989],"type":"Point"}
}