{
  "type": "Feature",
  "properties": {
    "iso:country":"BE",
    "sg:address":"Zonnebloemlaan 10",
    "sg:city":"Rumst",
    "sg:orig_category":"Artsen and specialisten",
    "sg:phone":"+32 3 888 17 37",
    "sg:postcode":"2840",
    "sg:province":"Antwerpen",
    "wof:name":"M. Eycken",
    "wof:placetype":"venue"
},
  "geometry": {"coordinates":[4.3922948837,51.1107635498],"type":"Point"}
}