{
  "type": "Feature",
  "properties": {
    "iso:country":"BE",
    "sg:address":"Chauss\u00c9e De Bruxelles 45ba",
    "sg:city":"Tournai",
    "sg:orig_category":"Entretien and r\u00e9parations de voitures. Stations-service and carburants",
    "sg:phone":"+32 69 22 30 71",
    "sg:postcode":"7500",
    "sg:province":"Hainaut",
    "wof:name":"Garage Monnaert Daniel",
    "wof:placetype":"venue"
},
  "geometry": {"coordinates":[3.4086360931,50.6050415039],"type":"Point"}
}