{
  "type": "Feature",
  "properties": {
    "addr:full":"Nieuwe Staatsbaan 23 Oud-turnhout Antwerpen 2360",
    "addr:housenumber":"23",
    "addr:postcode":"2360",
    "addr:street":"Nieuwe Staatsbaan",
    "iso:country":"BE",
    "sg:address":"Nieuwe Staatsbaan 23",
    "sg:city":"Oud-turnhout",
    "sg:orig_category":"Woningbouw",
    "sg:phone":"+32 14 45 44 60",
    "sg:postcode":"2360",
    "sg:province":"Antwerpen",
    "wof:name":"Danny Jansens",
    "wof:placetype":"venue"
},
  "geometry": {"coordinates":[5.0374832153,51.3125915527],"type":"Point"}
}