{
  "type": "Feature",
  "properties": {
    "iso:country":"BE",
    "sg:address":"Bruggesteenweg 30bb",
    "sg:city":"Hooglede",
    "sg:orig_category":"Installation \u00e9lectrique r\u00e9sidentielle. Plomberie, chauffage and installations sanitaires",
    "sg:phone":"+32 51 72 51 74",
    "sg:postcode":"8830",
    "sg:province":"West-Vlaanderen",
    "wof:name":"E.v.s.",
    "wof:placetype":"venue"
},
  "geometry": {"coordinates":[3.0844810009,50.9788475037],"type":"Point"}
}