{
  "type": "Feature",
  "properties": {
    "iso:country":"BE",
    "sg:address":"Albert I Laan 166",
    "sg:city":"Nieuwpoort",
    "sg:orig_category":"Textiel Verlichting and huishoudartikelen",
    "sg:phone":"+32 58 23 92 16",
    "sg:postcode":"8620",
    "sg:province":"West-Vlaanderen",
    "wof:name":"Deplanter Duo",
    "wof:placetype":"venue"
},
  "geometry": {"coordinates":[2.7196938992,51.1497764587],"type":"Point"}
}