{
  "type": "Feature",
  "properties": {
    "addr:full":"Klosterstrasse 9b Sankt Vith Li\u00e8ge 4780",
    "addr:housenumber":"9b",
    "addr:postcode":"4780",
    "addr:street":"Klosterstrasse",
    "iso:country":"BE",
    "sg:address":"Klosterstrasse 9b",
    "sg:city":"Sankt Vith",
    "sg:classifiers":[
        {
            "category":"Health Services",
            "subcategory":"Nursing And Care Facility",
            "type":"Services"
        }
    ],
    "sg:phone":"+32 80 22 99 94",
    "sg:postcode":"4780",
    "sg:province":"Li\u00e8ge",
    "sg:tags":[
        "home",
        "rest"
    ],
    "wof:name":"Seniorenheim St-elisabeth",
    "wof:placetype":"venue"
},
  "geometry": {"coordinates":[6.1268110275,50.2772865295],"type":"Point"}
}