{
  "type": "Feature",
  "properties": {
    "iso:country":"BE",
    "sg:address":"Rue De La Station 98",
    "sg:city":"Herve",
    "sg:orig_category":"Slagers",
    "sg:phone":"+32 87 67 51 32",
    "sg:postcode":"4650",
    "sg:province":"Li\u00e8ge",
    "wof:name":"Univian",
    "wof:placetype":"venue"
},
  "geometry": {"coordinates":[5.7916197777,50.6421318054],"type":"Point"}
}