{
  "type": "Feature",
  "properties": {
    "iso:country":"BE",
    "sg:address":"Avenue Hittelet 156",
    "sg:city":"Jemeppe-sur-sambre",
    "sg:orig_category":"Gespecialiseerde niet-residenti\u00eble bouw",
    "sg:phone":"+32 71 78 32 72",
    "sg:postcode":"5190",
    "sg:province":"Namur",
    "wof:name":"Jemeppe Construction",
    "wof:placetype":"venue"
},
  "geometry": {"coordinates":[4.6641540527,50.4609260559],"type":"Point"}
}