{
  "type": "Feature",
  "properties": {
    "addr:full":". Hoeselt (groot) Limburg 3730",
    "addr:postcode":"3730",
    "addr:street":"Groot Limburg",
    "iso:country":"BE",
    "sg:address":".",
    "sg:city":"Hoeselt (groot)",
    "sg:orig_category":"Apotheken",
    "sg:phone":"+32 900 10 500",
    "sg:postcode":"3730",
    "sg:province":"Limburg",
    "wof:name":"Apothekers Van Wacht",
    "wof:placetype":"venue"
},
  "geometry": {"coordinates":[5.4883198738,50.8499450684],"type":"Point"}
}