{
  "type": "Feature",
  "properties": {
    "addr:full":"Dorpsstraat 85 Stabroek Antwerpen 2940",
    "addr:housenumber":"85",
    "addr:postcode":"2940",
    "addr:street":"Dorpsstraat",
    "iso:country":"BE",
    "sg:address":"Dorpsstraat 85",
    "sg:city":"Stabroek",
    "sg:orig_category":"Paramedische behandelingen",
    "sg:phone":"+32 3 568 04 85",
    "sg:postcode":"2940",
    "sg:province":"Antwerpen",
    "wof:name":"H. Claessens",
    "wof:placetype":"venue"
},
  "geometry": {"coordinates":[4.3687019348,51.3337020874],"type":"Point"}
}