{
  "type": "Feature",
  "properties": {
    "iso:country":"BE",
    "sg:address":"Kapellestraat 39",
    "sg:city":"Hamme",
    "sg:orig_category":"Opticiens",
    "sg:phone":"+32 52 47 78 62",
    "sg:postcode":"9220",
    "sg:province":"Oost-Vlaanderen",
    "wof:name":"Luc Van Kerckhoven",
    "wof:placetype":"venue"
},
  "geometry": {"coordinates":[4.1431369781,51.0953483582],"type":"Point"}
}