{
  "type": "Feature",
  "properties": {
    "iso:country":"BE",
    "sg:address":"Dingensstraat 1",
    "sg:city":"Bree",
    "sg:classifiers":[
        {
            "category":"Farming",
            "subcategory":"Farm & Veterinary Services",
            "type":"Manufacturing & Wholesale Goods"
        }
    ],
    "sg:phone":"+32 89 46 11 69",
    "sg:postcode":"3960",
    "sg:province":"Limburg",
    "sg:tags":[
        "agricultural",
        "contractor"
    ],
    "wof:name":"Broekx Nv",
    "wof:placetype":"venue"
},
  "geometry": {"coordinates":[5.6088957787,51.1295127869],"type":"Point"}
}