{
  "type": "Feature",
  "properties": {
    "addr:full":"Schurhovenveld 1020b101 Sint-truiden Limburg 3800",
    "addr:housenumber":"1020b101",
    "addr:postcode":"3800",
    "addr:street":"Schurhovenveld",
    "iso:country":"BE",
    "sg:address":"Schurhovenveld 1020b101",
    "sg:city":"Sint-truiden",
    "sg:orig_category":"Beheer onroerend goed",
    "sg:phone":"+32 11 68 57 19",
    "sg:postcode":"3800",
    "sg:province":"Limburg",
    "wof:name":"Immor",
    "wof:placetype":"venue"
},
  "geometry": {"coordinates":[5.1863641739,50.8153343201],"type":"Point"}
}