{
  "type": "Feature",
  "properties": {
    "iso:country":"BE",
    "sg:address":"Naamsevest 18",
    "sg:city":"Leuven",
    "sg:orig_category":"S\u00e9curit\u00e9 sociale",
    "sg:phone":"+32 16 22 39 76",
    "sg:postcode":"3000",
    "sg:province":"Vlaams-Brabant",
    "wof:name":"Ziekenfonds De Familie",
    "wof:placetype":"venue"
},
  "geometry": {"coordinates":[4.6994671822,50.8685836792],"type":"Point"}
}