{
  "type": "Feature",
  "properties": {
    "iso:country":"BE",
    "sg:address":"Rue Du Radoux 38",
    "sg:city":"Rebecq",
    "sg:orig_category":"Forge, Moulage and Profilage des M\u00e9taux",
    "sg:phone":"+32 2 395 50 59",
    "sg:postcode":"1430",
    "sg:province":"Brabant Wallon",
    "wof:name":"Hofman Ferronerie",
    "wof:placetype":"venue"
},
  "geometry": {"coordinates":[4.1147360802,50.705783844],"type":"Point"}
}