{
  "type": "Feature",
  "properties": {
    "addr:full":"Place De Carni\u00c8res 23 Morlanwelz Hainaut 7141",
    "addr:housenumber":"23",
    "addr:postcode":"7141",
    "addr:street":"Place De Carnie\u0300Res",
    "iso:country":"BE",
    "sg:address":"Place De Carni\u00c8res 23",
    "sg:city":"Morlanwelz",
    "sg:orig_category":"Pain, p\u00e2tisseries and confiseries",
    "sg:phone":"+32 64 44 82 31",
    "sg:postcode":"7141",
    "sg:province":"Hainaut",
    "wof:name":"Debast Alain",
    "wof:placetype":"venue"
},
  "geometry": {"coordinates":[4.2548599243,50.4414405823],"type":"Point"}
}