{
  "type": "Feature",
  "properties": {
    "addr:full":"Centrumstraat 5 Zulte Oost-Vlaanderen 9870",
    "addr:housenumber":"5",
    "addr:postcode":"9870",
    "addr:street":"Centrumstraat",
    "iso:country":"BE",
    "sg:address":"Centrumstraat 5",
    "sg:city":"Zulte",
    "sg:orig_category":"Openbare veiligheid",
    "sg:phone":"+32 9 388 72 87",
    "sg:postcode":"9870",
    "sg:province":"Oost-Vlaanderen",
    "wof:name":"Federale Politie",
    "wof:placetype":"venue"
},
  "geometry": {"coordinates":[3.4661970139,50.9359893799],"type":"Point"}
}