{
  "type": "Feature",
  "properties": {
    "addr:full":"Schootschansweg 8 Heusden-zolder (heusden) Limburg 3550",
    "addr:housenumber":"8",
    "addr:postcode":"3550",
    "addr:street":"Schootschansweg",
    "iso:country":"BE",
    "sg:address":"Schootschansweg 8",
    "sg:city":"Heusden-zolder (heusden)",
    "sg:classifiers":[
        {
            "category":"Professional",
            "subcategory":"Lawyer & Legal Services",
            "type":"Services"
        }
    ],
    "sg:phone":"+32 11 42 18 04",
    "sg:postcode":"3550",
    "sg:province":"Limburg",
    "wof:name":"Roelands Michel",
    "wof:placetype":"venue"
},
  "geometry": {"coordinates":[5.2870969772,51.0312614441],"type":"Point"}
}