{
  "type": "Feature",
  "properties": {
    "addr:full":"Antwerpsesteenweg 295 Kapellen Antwerpen 2950",
    "addr:housenumber":"295",
    "addr:postcode":"2950",
    "addr:street":"Antwerpsesteenweg",
    "iso:country":"BE",
    "sg:address":"Antwerpsesteenweg 295",
    "sg:city":"Kapellen",
    "sg:classifiers":[
        {
            "category":"Insurance",
            "subcategory":"Life Insurance",
            "type":"Services"
        }
    ],
    "sg:phone":"+32 3 664 39 14",
    "sg:postcode":"2950",
    "sg:province":"Antwerpen",
    "sg:tags":[
        "assurance"
    ],
    "wof:name":"Fa. Van Bavel",
    "wof:placetype":"venue"
},
  "geometry": {"coordinates":[4.4389300346,51.2997131348],"type":"Point"}
}