{
  "type": "Feature",
  "properties": {
    "addr:full":"Langstraat 29 Maasmechelen (eisden) Limburg 3630",
    "addr:housenumber":"29",
    "addr:postcode":"3630",
    "addr:street":"Langstraat",
    "iso:country":"BE",
    "sg:address":"Langstraat 29",
    "sg:city":"Maasmechelen (eisden)",
    "sg:classifiers":[
        {
            "category":"Bars & Pubs",
            "subcategory":"Nightclub",
            "type":"Food & Drink"
        }
    ],
    "sg:phone":"+32 89 76 58 13",
    "sg:postcode":"3630",
    "sg:province":"Limburg",
    "wof:name":"Tijlhoeve",
    "wof:placetype":"venue"
},
  "geometry": {"coordinates":[5.7119579315,50.9848899841],"type":"Point"}
}