{
  "type": "Feature",
  "properties": {
    "addr:full":"Rue De La Bruy\u00c8re 230 Rixensart Brabant Wallon 1332",
    "addr:housenumber":"230",
    "addr:postcode":"1332",
    "addr:street":"Rue De La Bruye\u0300Re;Wallon",
    "iso:country":"BE",
    "sg:address":"Rue De La Bruy\u00c8re 230",
    "sg:city":"Rixensart",
    "sg:classifiers":[
        {
            "category":"Cafe",
            "type":"Food & Drink"
        }
    ],
    "sg:phone":"+32 2 654 01 60",
    "sg:postcode":"1332",
    "sg:province":"Brabant Wallon",
    "sg:tags":[
        "caf\u00e9s"
    ],
    "wof:name":"Caf\u00c9 Cl\u00c9ment",
    "wof:placetype":"venue"
},
  "geometry": {"coordinates":[4.4868159294,50.7268600464],"type":"Point"}
}