{
  "type": "Feature",
  "properties": {
    "addr:full":"Rue Remy Soetens 53 Bruxelles (jette) Bruxelles-Capitale 1090",
    "addr:housenumber":"53",
    "addr:postcode":"1090",
    "addr:street":"Rue Remy Soetens",
    "iso:country":"BE",
    "sg:address":"Rue Remy Soetens 53",
    "sg:city":"Bruxelles (jette)",
    "sg:classifiers":[
        {
            "category":"Health Services",
            "subcategory":"Health Practitioner",
            "type":"Services"
        }
    ],
    "sg:phone":"+32 2 479 40 80",
    "sg:postcode":"1090",
    "sg:province":"Bruxelles-Capitale",
    "sg:tags":[
        "physiotherapist"
    ],
    "wof:name":"Dubois Philippe",
    "wof:placetype":"venue"
},
  "geometry": {"coordinates":[4.3200469017,50.8865661621],"type":"Point"}
}