{
  "type": "Feature",
  "properties": {
    "iso:country":"BE",
    "sg:address":"Dirk Martensstraat 79",
    "sg:city":"Aalst",
    "sg:classifiers":[
        {
            "category":"Banks & Credit Unions",
            "subcategory":"Financial Services",
            "type":"Services"
        }
    ],
    "sg:phone":"+32 53 62 49 57",
    "sg:postcode":"9300",
    "sg:province":"Oost-Vlaanderen",
    "sg:tags":[
        "financing"
    ],
    "wof:name":"Leencentrale Aalst",
    "wof:placetype":"venue"
},
  "geometry": {"coordinates":[4.0314822197,50.9412460327],"type":"Point"}
}