{
  "type": "Feature",
  "properties": {
    "iso:country":"BE",
    "sg:address":"Try Des Marais 69",
    "sg:city":"Walcourt",
    "sg:classifiers":[
        {
            "category":"Insurance",
            "subcategory":"Insurance Agent",
            "type":"Services"
        }
    ],
    "sg:phone":"+32 71 70 15 75",
    "sg:postcode":"5651",
    "sg:province":"Namur",
    "sg:tags":[
        "verzekeringsmakelaars",
        "expert"
    ],
    "wof:name":"Bureau Chapeaux Olivier",
    "wof:placetype":"venue"
},
  "geometry": {"coordinates":[4.4879198074,50.3163032532],"type":"Point"}
}