{
  "type": "Feature",
  "properties": {
    "addr:full":"Rue Piervenne 146 Ciney Namur 5590",
    "addr:housenumber":"146",
    "addr:postcode":"5590",
    "addr:street":"Rue Piervenne",
    "iso:country":"BE",
    "sg:address":"Rue Piervenne 146",
    "sg:city":"Ciney",
    "sg:classifiers":[
        {
            "category":"Professional",
            "subcategory":"Lawyer & Legal Services",
            "type":"Services"
        }
    ],
    "sg:phone":"+32 83 21 24 30",
    "sg:postcode":"5590",
    "sg:province":"Namur",
    "wof:name":"Lefebvre R",
    "wof:placetype":"venue"
},
  "geometry": {"coordinates":[5.0916819572,50.291721344],"type":"Point"}
}