{
  "type": "Feature",
  "properties": {
    "addr:full":"Mechelsestraat 140 Leuven Vlaams-Brabant 3000",
    "addr:housenumber":"140",
    "addr:postcode":"3000",
    "addr:street":"Mechelsestraat",
    "iso:country":"BE",
    "sg:address":"Mechelsestraat 140",
    "sg:city":"Leuven",
    "sg:orig_category":"Krantenuitgeverijen Krantenwinkels Rookartikelen Tijdschriftenuitgeverijen",
    "sg:phone":"+32 16 23 70 06",
    "sg:postcode":"3000",
    "sg:province":"Vlaams-Brabant",
    "wof:name":"Wouters",
    "wof:placetype":"venue"
},
  "geometry": {"coordinates":[4.6982541084,50.8845100403],"type":"Point"}
}