{
  "type": "Feature",
  "properties": {
    "addr:full":"Hoekstraat 2 Bocholt Limburg 3950",
    "addr:housenumber":"2",
    "addr:postcode":"3950",
    "addr:street":"Hoekstraat",
    "iso:country":"BE",
    "sg:address":"Hoekstraat 2",
    "sg:city":"Bocholt",
    "sg:orig_category":"Dakwerken",
    "sg:phone":"+32 89 46 14 47",
    "sg:postcode":"3950",
    "sg:province":"Limburg",
    "wof:name":"Janssens",
    "wof:placetype":"venue"
},
  "geometry": {"coordinates":[5.5849580765,51.1808776855],"type":"Point"}
}