{
  "type": "Feature",
  "properties": {
    "iso:country":"BE",
    "sg:address":"Place Georges Brugmann 19",
    "sg:city":"Bruxelles (ixelles)",
    "sg:classifiers":[
        {
            "category":"Shopping",
            "subcategory":"Clothing, Apparel, & Fashions",
            "type":"Retail Goods"
        }
    ],
    "sg:phone":"+32 2 344 48 91",
    "sg:postcode":"1050",
    "sg:province":"Bruxelles-Capitale",
    "sg:tags":[
        "lady",
        "clothing",
        "-"
    ],
    "wof:name":"Rouge De Gris",
    "wof:placetype":"venue"
},
  "geometry": {"coordinates":[4.3534722328,50.8170852661],"type":"Point"}
}