{
  "type": "Feature",
  "properties": {
    "iso:country":"BE",
    "sg:address":"Overijsesteenweg 73",
    "sg:city":"Tervuren",
    "sg:orig_category":"Producteurs de fruits",
    "sg:phone":"+32 2 687 82 79",
    "sg:postcode":"3080",
    "sg:province":"Vlaams-Brabant",
    "wof:name":"De Vos Patrick & Benny",
    "wof:placetype":"venue"
},
  "geometry": {"coordinates":[4.5524001122,50.8035392761],"type":"Point"}
}