{
  "type": "Feature",
  "properties": {
    "iso:country":"BE",
    "sg:address":"Rue Des Mineurs 192",
    "sg:city":"Quaregnon",
    "sg:classifiers":[
        {
            "category":"Autos & Motor Vehicles",
            "subcategory":"Automobile Sales",
            "type":"Retail Goods"
        }
    ],
    "sg:phone":"+32 65 67 20 48",
    "sg:postcode":"7390",
    "sg:province":"Hainaut",
    "sg:tags":[
        "workshop",
        "upholstery"
    ],
    "wof:name":"Etablissement Deladri\u00e8re S.p.r.l.",
    "wof:placetype":"venue"
},
  "geometry": {"coordinates":[3.8530600071,50.4244003296],"type":"Point"}
}