{
  "type": "Feature",
  "properties": {
    "iso:country":"BE",
    "sg:address":"Viverselweg 24",
    "sg:city":"Heusden-zolder",
    "sg:orig_category":"Woningbouw",
    "sg:phone":"+32 11 53 38 71",
    "sg:postcode":"3550",
    "sg:province":"Limburg",
    "wof:name":"Claes A",
    "wof:placetype":"venue"
},
  "geometry": {"coordinates":[5.2694158554,51.0079650879],"type":"Point"}
}