{
  "type": "Feature",
  "properties": {
    "iso:country":"BE",
    "sg:address":"Woluwe Shopping Center",
    "sg:city":"Bruxelles (woluwe-saint-lambert)",
    "sg:classifiers":[
        {
            "category":"Shopping",
            "subcategory":"Bicycles & Sporting Goods",
            "type":"Retail Goods"
        }
    ],
    "sg:phone":"+32 2 770 03 26",
    "sg:postcode":"1200",
    "sg:province":"Bruxelles-Capitale",
    "sg:tags":[
        "sport",
        "-"
    ],
    "wof:name":"All-sports",
    "wof:placetype":"venue"
},
  "geometry": {"coordinates":[4.4168701172,50.8531761169],"type":"Point"}
}