{
  "type": "Feature",
  "properties": {
    "addr:full":"Rue Royale 10 Cerfontaine (silenrieux) Namur 5630",
    "addr:housenumber":"10",
    "addr:postcode":"5630",
    "addr:street":"Rue Royale",
    "iso:country":"BE",
    "sg:address":"Rue Royale 10",
    "sg:city":"Cerfontaine (silenrieux)",
    "sg:classifiers":[
        {
            "category":"Retail",
            "subcategory":"Auto Repair",
            "type":"Services"
        }
    ],
    "sg:phone":"+32 71 63 33 74",
    "sg:postcode":"5630",
    "sg:province":"Namur",
    "sg:tags":[
        "automobile-body"
    ],
    "wof:name":"Carrosserie 2000",
    "wof:placetype":"venue"
},
  "geometry": {"coordinates":[4.4487199783,50.2156639099],"type":"Point"}
}