{
  "type": "Feature",
  "properties": {
    "iso:country":"BE",
    "sg:address":"Molenakkerstraat",
    "sg:city":"Wuustwezel",
    "sg:orig_category":"Installation de menuiserie en bois and plastique",
    "sg:phone":"+32 3 669 68 87",
    "sg:postcode":"2990",
    "sg:province":"Antwerpen",
    "wof:name":"Van Dijck",
    "wof:placetype":"venue"
},
  "geometry": {"coordinates":[4.6426429749,51.3949813843],"type":"Point"}
}