{
  "type": "Feature",
  "properties": {
    "iso:country":"BE",
    "sg:address":"Clos Du Cheval D'argent 27",
    "sg:city":"Elsene/ixelles",
    "sg:orig_category":"M\u00e9decins and sp\u00e9cialistes",
    "sg:phone":"+32 2 673 23 71",
    "sg:postcode":"1050",
    "sg:province":"Bruxelles-Capitale",
    "wof:name":"Claude Van Dyk",
    "wof:placetype":"venue"
},
  "geometry": {"coordinates":[4.3919987679,50.8104362488],"type":"Point"}
}