{
  "type": "Feature",
  "properties": {
    "addr:full":"Dorp-wichelen 1 Wichelen Oost-Vlaanderen 9260",
    "addr:housenumber":"1",
    "addr:postcode":"9260",
    "addr:street":"Dorp-Wichelen",
    "iso:country":"BE",
    "sg:address":"Dorp-wichelen 1",
    "sg:city":"Wichelen",
    "sg:orig_category":"Banken and kredietinstellingen",
    "sg:phone":"+32 9 369 13 87",
    "sg:postcode":"9260",
    "sg:province":"Oost-Vlaanderen",
    "wof:name":"Kbc",
    "wof:placetype":"venue"
},
  "geometry": {"coordinates":[3.9743049145,51.0067749023],"type":"Point"}
}