{
  "type": "Feature",
  "properties": {
    "iso:country":"BE",
    "sg:address":"Polderdreef 69",
    "sg:city":"De Pinte",
    "sg:orig_category":"Secretariaatsdiensten",
    "sg:phone":"+32 9 282 22 66",
    "sg:postcode":"9840",
    "sg:province":"Oost-Vlaanderen",
    "wof:name":"Fasttype Office",
    "wof:placetype":"venue"
},
  "geometry": {"coordinates":[3.6654191017,50.9879112244],"type":"Point"}
}