{
  "type": "Feature",
  "properties": {
    "iso:country":"BE",
    "sg:address":"Scheutlaan 252",
    "sg:city":"Anderlecht",
    "sg:orig_category":"Plaatsen van vloer- and muurbekleding Schilders",
    "sg:phone":"+32 2 521 12 06",
    "sg:postcode":"1070",
    "sg:province":"Bruxelles-Capitale",
    "wof:name":"Jean Renson",
    "wof:placetype":"venue"
},
  "geometry": {"coordinates":[4.3094677925,50.8463554382],"type":"Point"}
}