{
  "type": "Feature",
  "properties": {
    "iso:country":"BE",
    "sg:address":"Avenue Du Silence 70",
    "sg:city":"Ukkel/uccle",
    "sg:classifiers":[
        {
            "category":"Cafe",
            "type":"Food & Drink"
        }
    ],
    "sg:phone":"+32 2 332 26 23",
    "sg:postcode":"1180",
    "sg:province":"Bruxelles-Capitale",
    "sg:tags":[
        "caf\u00e9s"
    ],
    "wof:name":"Caf\u00c9 Le Silence",
    "wof:placetype":"venue"
},
  "geometry": {"coordinates":[4.3306221962,50.7834739685],"type":"Point"}
}