{
  "type": "Feature",
  "properties": {
    "addr:full":"Rattenhaus 24 Raeren (eynatten) Li\u00e8ge 4731",
    "addr:housenumber":"24",
    "addr:postcode":"4731",
    "addr:street":"Rattenhaus",
    "iso:country":"BE",
    "sg:address":"Rattenhaus 24",
    "sg:city":"Raeren (eynatten)",
    "sg:classifiers":[
        {
            "category":"Health Services",
            "subcategory":"Health Practitioner",
            "type":"Services"
        }
    ],
    "sg:phone":"+32 87 85 28 07",
    "sg:postcode":"4731",
    "sg:province":"Li\u00e8ge",
    "sg:tags":[
        "physiotherapist"
    ],
    "wof:name":"Wimmenauer E",
    "wof:placetype":"venue"
},
  "geometry": {"coordinates":[6.1059031487,50.6882553101],"type":"Point"}
}