{
  "type": "Feature",
  "properties": {
    "iso:country":"BE",
    "sg:address":"Rue Albert 72",
    "sg:city":"Tournai",
    "sg:orig_category":"M\u00e9decins and sp\u00e9cialistes",
    "sg:phone":"+32 69 21 53 92",
    "sg:postcode":"7540",
    "sg:province":"Hainaut",
    "wof:name":"Jean-fran\u00c7ois Moreau",
    "wof:placetype":"venue"
},
  "geometry": {"coordinates":[3.5024220943,50.5714874268],"type":"Point"}
}