{
  "type": "Feature",
  "properties": {
    "addr:full":"Neremstraat 140 Tongeren Limburg 3700",
    "addr:housenumber":"140",
    "addr:postcode":"3700",
    "addr:street":"Neremstraat",
    "iso:country":"BE",
    "sg:address":"Neremstraat 140",
    "sg:city":"Tongeren",
    "sg:orig_category":"Banken and kredietinstellingen",
    "sg:phone":"+32 12 23 05 64",
    "sg:postcode":"3700",
    "sg:province":"Limburg",
    "wof:name":"Kbc",
    "wof:placetype":"venue"
},
  "geometry": {"coordinates":[5.4636240005,50.7807197571],"type":"Point"}
}