{
  "type": "Feature",
  "properties": {
    "iso:country":"BE",
    "sg:address":"Kardinaal Sterckxstraat 40",
    "sg:city":"Boechout",
    "sg:classifiers":[
        {
            "category":"Professional",
            "subcategory":"Accounting & Tax Preparation",
            "type":"Services"
        }
    ],
    "sg:phone":"+32 3 326 06 26",
    "sg:postcode":"2530",
    "sg:province":"Antwerpen",
    "sg:tags":[
        "accountant"
    ],
    "wof:name":"Croux R",
    "wof:placetype":"venue"
},
  "geometry": {"coordinates":[4.4985327721,51.1684494019],"type":"Point"}
}