{
  "type": "Feature",
  "properties": {
    "addr:full":"Rue Albert I 49 Pont-\u00e0-celles (viesville) Hainaut 6230",
    "addr:housenumber":"49",
    "addr:postcode":"6230",
    "addr:street":"Rue Albert I",
    "iso:country":"BE",
    "sg:address":"Rue Albert I 49",
    "sg:city":"Pont-\u00e0-celles (viesville)",
    "sg:classifiers":[
        {
            "category":"Bakery",
            "type":"Food & Drink"
        }
    ],
    "sg:phone":"+32 71 37 00 94",
    "sg:postcode":"6230",
    "sg:province":"Hainaut",
    "sg:tags":[
        "confectioner",
        "baker"
    ],
    "wof:name":"Sarrasin (le)",
    "wof:placetype":"venue"
},
  "geometry": {"coordinates":[4.3707361221,50.507106781],"type":"Point"}
}