{
  "type": "Feature",
  "properties": {
    "iso:country":"BE",
    "sg:address":"Sint-martinuskerkstraat 76",
    "sg:city":"Ganshoren",
    "sg:classifiers":[
        {
            "category":"Cafe",
            "type":"Food & Drink"
        }
    ],
    "sg:phone":"+32 2 427 83 85",
    "sg:postcode":"1083",
    "sg:province":"Bruxelles-Capitale",
    "sg:tags":[
        "caf\u00e9s"
    ],
    "wof:name":"'t Klubke",
    "wof:placetype":"venue"
},
  "geometry": {"coordinates":[4.3124370575,50.8725128174],"type":"Point"}
}