{
  "type": "Feature",
  "properties": {
    "addr:full":"Vriesenrot 5 Dendermonde (sint-gillis-bij-dendermonde) Oost-Vlaanderen 9200",
    "addr:housenumber":"5",
    "addr:postcode":"9200",
    "addr:street":"Vriesenrot",
    "iso:country":"BE",
    "sg:address":"Vriesenrot 5",
    "sg:city":"Dendermonde (sint-gillis-bij-dendermonde)",
    "sg:classifiers":[
        {
            "category":"Utilities",
            "subcategory":"Electric",
            "type":"Services"
        }
    ],
    "sg:phone":"+32 52 20 34 10",
    "sg:postcode":"9200",
    "sg:province":"Oost-Vlaanderen",
    "sg:tags":[
        "energy",
        "renewable"
    ],
    "wof:name":"Stafco Bvba",
    "wof:placetype":"venue"
},
  "geometry": {"coordinates":[4.1328001022,51.0345993042],"type":"Point"}
}