{
  "type": "Feature",
  "properties": {
    "iso:country":"BE",
    "sg:address":"Urselweg 6ba",
    "sg:city":"Maldegem",
    "sg:orig_category":"Woningbouw",
    "sg:phone":"+32 50 71 93 31",
    "sg:postcode":"9990",
    "sg:province":"Oost-Vlaanderen",
    "wof:name":"Christiaan Dobbelaere",
    "wof:placetype":"venue"
},
  "geometry": {"coordinates":[3.4661900997,51.1760902405],"type":"Point"}
}