{
  "type": "Feature",
  "properties": {
    "addr:full":"Koolkerkse Steenweg 123 Brugge West-Vlaanderen 8000",
    "addr:housenumber":"123",
    "addr:postcode":"8000",
    "addr:street":"Koolkerkse Steenweg",
    "iso:country":"BE",
    "sg:address":"Koolkerkse Steenweg 123",
    "sg:city":"Brugge",
    "sg:classifiers":[
        {
            "category":"Wholesale",
            "subcategory":"Beer",
            "type":"Manufacturing & Wholesale Goods"
        }
    ],
    "sg:phone":"+32 50 33 16 11",
    "sg:postcode":"8000",
    "sg:province":"West-Vlaanderen",
    "sg:tags":[
        "ale",
        "-"
    ],
    "wof:name":"Lievens L",
    "wof:placetype":"venue"
},
  "geometry": {"coordinates":[3.2368619442,51.2267684937],"type":"Point"}
}