{
  "type": "Feature",
  "properties": {
    "addr:full":"Vanderkinderestraat 442 Ukkel/uccle Bruxelles-Capitale 1180",
    "addr:housenumber":"442",
    "addr:postcode":"1180",
    "addr:street":"Vanderkinderestraat;/",
    "iso:country":"BE",
    "sg:address":"Vanderkinderestraat 442",
    "sg:city":"Ukkel/uccle",
    "sg:orig_category":"Herstellingen and onderhoud van auto's Onderdelen and accessoires voor auto's",
    "sg:phone":"+32 2 345 69 79",
    "sg:postcode":"1180",
    "sg:province":"Bruxelles-Capitale",
    "wof:name":"Midas",
    "wof:placetype":"venue"
},
  "geometry": {"coordinates":[4.3604240417,50.814491272],"type":"Point"}
}