{
  "type": "Feature",
  "properties": {
    "iso:country":"BE",
    "sg:address":"Driesstraat 35-39",
    "sg:city":"Zele",
    "sg:orig_category":"IJzerwaren, bouw- and verfmaterialen Plaatsen van vloer- and muurbekleding Schilders Verlichting and",
    "sg:phone":"+32 52 44 44 70",
    "sg:postcode":"9240",
    "sg:province":"Oost-Vlaanderen",
    "wof:name":"Mira Zele",
    "wof:placetype":"venue"
},
  "geometry": {"coordinates":[4.0315380096,51.0691184998],"type":"Point"}
}