{
  "type": "Feature",
  "properties": {
    "iso:country":"BE",
    "sg:address":"Kruisstraat 12",
    "sg:city":"Hechtel-eksel (eksel)",
    "sg:classifiers":[
        {
            "category":"Autos & Motor Vehicles",
            "subcategory":"Automobile Sales",
            "type":"Retail Goods"
        }
    ],
    "sg:phone":"+32 11 73 48 53",
    "sg:postcode":"3941",
    "sg:province":"Limburg",
    "sg:tags":[
        "car",
        "used",
        "-"
    ],
    "wof:name":"Beyen R",
    "wof:placetype":"venue"
},
  "geometry": {"coordinates":[5.410159111,51.1586494446],"type":"Point"}
}