{
  "type": "Feature",
  "properties": {
    "iso:country":"BE",
    "sg:address":"Schelfheidestraat 28",
    "sg:city":"Nieuwerkerken",
    "sg:classifiers":[
        {
            "category":"Banks & Credit Unions",
            "subcategory":"Investment Brokerage",
            "type":"Services"
        }
    ],
    "sg:phone":"+32 11 68 69 39",
    "sg:postcode":"3850",
    "sg:province":"Limburg",
    "sg:tags":[
        "remediation",
        "soil",
        "protection"
    ],
    "wof:name":"Kempeneers Roger",
    "wof:placetype":"venue"
},
  "geometry": {"coordinates":[5.1835398674,50.8746185303],"type":"Point"}
}