{
  "type": "Feature",
  "properties": {
    "iso:country":"BE",
    "sg:address":"Brugsestraat 115",
    "sg:city":"Oostkamp",
    "sg:orig_category":"Eclairage et \u00e9quipements du foyer. Textiles",
    "sg:phone":"+32 50 82 74 95",
    "sg:postcode":"8020",
    "sg:province":"West-Vlaanderen",
    "wof:name":"Fa. Reyserhove",
    "wof:placetype":"venue"
},
  "geometry": {"coordinates":[3.2346420288,51.1607017517],"type":"Point"}
}