{
  "type": "Feature",
  "properties": {
    "addr:full":"Tacambaroplein 3 Oudenaarde (groot) Oost-Vlaanderen 9700",
    "addr:housenumber":"3",
    "addr:postcode":"9700",
    "addr:street":"Tacambaroplein;Groot Oost-Vlaanderen",
    "iso:country":"BE",
    "sg:address":"Tacambaroplein 3",
    "sg:city":"Oudenaarde (groot)",
    "sg:orig_category":"Supermarch\u00e9s",
    "sg:phone":"+32 55 30 34 35",
    "sg:postcode":"9700",
    "sg:province":"Oost-Vlaanderen",
    "wof:name":"Colruyt",
    "wof:placetype":"venue"
},
  "geometry": {"coordinates":[3.6014308929,50.8470306396],"type":"Point"}
}