{
  "type": "Feature",
  "properties": {
    "addr:full":"Rue Du Saint-esprit 2 Bruxelles Bruxelles-Capitale 1000",
    "addr:housenumber":"2",
    "addr:postcode":"1000",
    "addr:street":"Rue Du Saint-Esprit",
    "iso:country":"BE",
    "sg:address":"Rue Du Saint-esprit 2",
    "sg:city":"Bruxelles",
    "sg:classifiers":[
        {
            "category":"Community Center",
            "subcategory":"Youth",
            "type":"Public Place"
        }
    ],
    "sg:phone":"+32 2 511 04 36",
    "sg:postcode":"1000",
    "sg:province":"Bruxelles-Capitale",
    "sg:tags":[
        "club"
    ],
    "wof:name":"Breughel",
    "wof:placetype":"venue"
},
  "geometry": {"coordinates":[4.3479700089,50.8474578857],"type":"Point"}
}