{
  "type": "Feature",
  "properties": {
    "addr:full":"Rue Du Sablon 119 Bastogne Luxembourg 6600",
    "addr:housenumber":"119",
    "addr:postcode":"6600",
    "addr:street":"Rue Du Sablon",
    "iso:country":"BE",
    "sg:address":"Rue Du Sablon 119",
    "sg:city":"Bastogne",
    "sg:orig_category":"Diverse producten Gh",
    "sg:phone":"+32 61 21 71 00",
    "sg:postcode":"6600",
    "sg:province":"Luxembourg",
    "wof:name":"Tonton Lulu - Tks",
    "wof:placetype":"venue"
},
  "geometry": {"coordinates":[5.7183628082,50.0030479431],"type":"Point"}
}