{
  "type": "Feature",
  "properties": {
    "addr:full":"Ave Albert I. 1 Fosses La Ville Namur 5660",
    "addr:housenumber":"1",
    "addr:postcode":"5660",
    "addr:street":"Ave Albert I.",
    "iso:country":"BE",
    "sg:address":"Ave Albert I. 1",
    "sg:city":"Fosses La Ville",
    "sg:classifiers":[
        {
            "category":"Banks & Credit Unions",
            "subcategory":"Bank",
            "type":"Services"
        }
    ],
    "sg:phone":"+32 71 71 14 00",
    "sg:postcode":"5660",
    "sg:province":"Namur",
    "wof:name":"Aslk-cger Bank",
    "wof:placetype":"venue"
},
  "geometry": {"coordinates":[134.61526489260001,-32.599319458],"type":"Point"}
}