{
  "type": "Feature",
  "properties": {
    "addr:full":"Molenstraat 5 Meeuwen-gruitrode Limburg 3670",
    "addr:housenumber":"5",
    "addr:postcode":"3670",
    "addr:street":"Molenstraat",
    "iso:country":"BE",
    "sg:address":"Molenstraat 5",
    "sg:city":"Meeuwen-gruitrode",
    "sg:classifiers":[
        {
            "category":"Restaurant",
            "type":"Food & Drink"
        }
    ],
    "sg:phone":"+32 11 79 29 69",
    "sg:postcode":"3670",
    "sg:province":"Limburg",
    "wof:name":"Taverne De Dorpermolen",
    "wof:placetype":"venue"
},
  "geometry": {"coordinates":[5.514526844,51.1053466797],"type":"Point"}
}