{
  "type": "Feature",
  "properties": {
    "iso:country":"BE",
    "sg:address":"Beschavingstraat 13",
    "sg:city":"Antwerpen",
    "sg:orig_category":"Agences d'exp\u00e9dition",
    "sg:phone":"+32 3 238 23 88",
    "sg:postcode":"2020",
    "sg:province":"Antwerpen",
    "wof:name":"Belgo Malienne",
    "wof:placetype":"venue"
},
  "geometry": {"coordinates":[4.3958678246,51.1910018921],"type":"Point"}
}