{
  "type": "Feature",
  "properties": {
    "iso:country":"BE",
    "sg:address":"Prins Albertlaan 29",
    "sg:city":"De Panne",
    "sg:orig_category":"Elektrische installaties voor woningen",
    "sg:phone":"+32 58 41 27 28",
    "sg:postcode":"8660",
    "sg:province":"West-Vlaanderen",
    "wof:name":"Camilius Leemans",
    "wof:placetype":"venue"
},
  "geometry": {"coordinates":[2.5950939655,51.0992164612],"type":"Point"}
}