{
  "type": "Feature",
  "properties": {
    "iso:country":"BE",
    "sg:address":"Kleine Hellekensstraat 48ba",
    "sg:city":"Zonhoven",
    "sg:orig_category":"Binnenhuisarchitecten Verlichting and huishoudartikelen Winkelinrichting and handelsuitrusting Gh",
    "sg:phone":"+32 11 81 82 32",
    "sg:postcode":"3520",
    "sg:province":"Limburg",
    "wof:name":"Fa. Langendries",
    "wof:placetype":"venue"
},
  "geometry": {"coordinates":[5.3614449501,50.9823417664],"type":"Point"}
}