{
  "type": "Feature",
  "properties": {
    "iso:country":"BE",
    "sg:address":"Sint-eloois-winkelsestraat 63a",
    "sg:city":"Roeselare (oekene)",
    "sg:classifiers":[
        {
            "category":"Personal",
            "subcategory":"Nail Salon",
            "type":"Services"
        }
    ],
    "sg:phone":"+32 51 20 33 06",
    "sg:postcode":"8800",
    "sg:province":"West-Vlaanderen",
    "sg:tags":[
        "pedicure"
    ],
    "wof:name":"Desmet R",
    "wof:placetype":"venue"
},
  "geometry": {"coordinates":[3.160572052,50.912311554],"type":"Point"}
}