{
  "type": "Feature",
  "properties": {
    "iso:country":"BE",
    "sg:address":"Sint-benedictusstraat 132",
    "sg:city":"Mortsel",
    "sg:classifiers":[
        {
            "category":"Professional",
            "subcategory":"Lawyer & Legal Services",
            "type":"Services"
        }
    ],
    "sg:phone":"+32 3 449 20 10",
    "sg:postcode":"2640",
    "sg:province":"Antwerpen",
    "wof:name":"Schouterden G",
    "wof:placetype":"venue"
},
  "geometry": {"coordinates":[4.4573721886,51.1691665649],"type":"Point"}
}