{
  "type": "Feature",
  "properties": {
    "addr:full":"Pleinstraat 100 Alken Limburg 3570",
    "addr:housenumber":"100",
    "addr:postcode":"3570",
    "addr:street":"Pleinstraat",
    "iso:country":"BE",
    "sg:address":"Pleinstraat 100",
    "sg:city":"Alken",
    "sg:orig_category":"Installation \u00e9lectrique r\u00e9sidentielle",
    "sg:phone":"+32 11 59 19 09",
    "sg:postcode":"3570",
    "sg:province":"Limburg",
    "wof:name":"Philippe Peeters",
    "wof:placetype":"venue"
},
  "geometry": {"coordinates":[5.2807641029,50.8612060547],"type":"Point"}
}