{
  "type": "Feature",
  "properties": {
    "addr:full":"Langendorpweg 1 Jabbeke West-Vlaanderen 8490",
    "addr:housenumber":"1",
    "addr:postcode":"8490",
    "addr:street":"Langendorpweg",
    "iso:country":"BE",
    "sg:address":"Langendorpweg 1",
    "sg:city":"Jabbeke",
    "sg:orig_category":"Eleveurs and marchands de porcs",
    "sg:phone":"+32 50 81 17 76",
    "sg:postcode":"8490",
    "sg:province":"West-Vlaanderen",
    "wof:name":"Julien Vermeire",
    "wof:placetype":"venue"
},
  "geometry": {"coordinates":[3.0819609165,51.2235908508],"type":"Point"}
}