{
  "type": "Feature",
  "properties": {
    "addr:full":"Standplaats 114 Duffel Antwerpen 2570",
    "addr:housenumber":"114",
    "addr:postcode":"2570",
    "addr:street":"Standplaats",
    "iso:country":"BE",
    "sg:address":"Standplaats 114",
    "sg:city":"Duffel",
    "sg:classifiers":[
        {
            "category":"Health Services",
            "subcategory":"Health Practitioner",
            "type":"Services"
        }
    ],
    "sg:phone":"+32 15 31 19 27",
    "sg:postcode":"2570",
    "sg:province":"Antwerpen",
    "sg:tags":[
        "physiotherapist"
    ],
    "wof:name":"Cauwenbergh H",
    "wof:placetype":"venue"
},
  "geometry": {"coordinates":[4.4916491508,51.0889511108],"type":"Point"}
}