{
  "type": "Feature",
  "properties": {
    "iso:country":"BE",
    "sg:address":"Chauss\u00c9e D'audenarde 158",
    "sg:city":"Pecq",
    "sg:orig_category":"Installation de menuiserie en bois and plastique",
    "sg:phone":"+32 69 55 78 40",
    "sg:postcode":"7742",
    "sg:province":"Hainaut",
    "wof:name":"Philippe Braem",
    "wof:placetype":"venue"
},
  "geometry": {"coordinates":[3.3613989353,50.6959838867],"type":"Point"}
}