{
  "type": "Feature",
  "properties": {
    "iso:country":"BE",
    "sg:address":"Kontichsesteenweg 64",
    "sg:city":"Aartselaar",
    "sg:classifiers":[
        {
            "category":"Autos & Motor Vehicles",
            "subcategory":"Fuel & Gas Station",
            "type":"Retail Goods"
        }
    ],
    "sg:phone":"+32 3 457 03 17",
    "sg:postcode":"2630",
    "sg:province":"Antwerpen",
    "wof:name":"Van Dyck Bvba",
    "wof:placetype":"venue"
},
  "geometry": {"coordinates":[4.3924307823,51.1447410583],"type":"Point"}
}