{
  "type": "Feature",
  "properties": {
    "addr:full":"Bernstraat 18 Asper Oost-Vlaanderen 9890",
    "addr:housenumber":"18",
    "addr:postcode":"9890",
    "addr:street":"Bernstraat",
    "iso:country":"BE",
    "sg:address":"Bernstraat 18",
    "sg:city":"Asper",
    "sg:orig_category":"Woningbouw",
    "sg:phone":"+32 9 384 12 68",
    "sg:postcode":"9890",
    "sg:province":"Oost-Vlaanderen",
    "wof:name":"De Bruycker Gebroeders",
    "wof:placetype":"venue"
},
  "geometry": {"coordinates":[3.6388618946,50.9372291565],"type":"Point"}
}