{
  "type": "Feature",
  "properties": {
    "addr:full":"Dellestraat 24 Industrieterrein Lummen Limburg 3560",
    "addr:housenumber":"24",
    "addr:postcode":"3560",
    "addr:street":"Dellestraat;Industrieterrein Lummen Limburg",
    "iso:country":"BE",
    "sg:address":"Dellestraat 24 Industrieterrein",
    "sg:city":"Lummen",
    "sg:classifiers":[
        {
            "category":"Manufacturing",
            "subcategory":"Metals",
            "type":"Manufacturing & Wholesale Goods"
        }
    ],
    "sg:phone":"+32 13 52 17 37",
    "sg:postcode":"3560",
    "sg:province":"Limburg",
    "sg:tags":[
        "-",
        "machine",
        "equipment",
        "engineering",
        "machinery",
        "mechanical"
    ],
    "wof:name":"Plasmajet Nv",
    "wof:placetype":"venue"
},
  "geometry": {"coordinates":[5.2381591797,51.0159606934],"type":"Point"}
}