{
  "type": "Feature",
  "properties": {
    "addr:full":"Elfde-liniestraat 24 Hasselt Limburg 3500",
    "addr:housenumber":"24",
    "addr:postcode":"3500",
    "addr:street":"Elfde-Liniestraat",
    "iso:country":"BE",
    "sg:address":"Elfde-liniestraat 24",
    "sg:city":"Hasselt",
    "sg:orig_category":"Formation permanente",
    "sg:phone":"+32 11 26 73 51",
    "sg:postcode":"3500",
    "sg:province":"Limburg",
    "wof:name":"Prov.centr.moderne Talen",
    "wof:placetype":"venue"
},
  "geometry": {"coordinates":[5.3480467796,50.936794281],"type":"Point"}
}