{
  "type": "Feature",
  "properties": {
    "addr:full":"Avenue Fran\u00e7ois De Lhoneux 11 Yvoir Namur 5530",
    "addr:housenumber":"11",
    "addr:postcode":"5530",
    "addr:street":"Avenue Franc\u0327Ois De Lhoneux",
    "iso:country":"BE",
    "sg:address":"Avenue Fran\u00e7ois De Lhoneux 11",
    "sg:city":"Yvoir",
    "sg:classifiers":[
        {
            "category":"Bakery",
            "type":"Food & Drink"
        }
    ],
    "sg:phone":"+32 82 61 27 80",
    "sg:postcode":"5530",
    "sg:province":"Namur",
    "sg:tags":[
        "confectioner",
        "baker"
    ],
    "wof:name":"Champagne O",
    "wof:placetype":"venue"
},
  "geometry": {"coordinates":[4.8774881363,50.326713562],"type":"Point"}
}