{
  "type": "Feature",
  "properties": {
    "addr:full":"Oerenstraat 4a Veurne West-Vlaanderen 8630",
    "addr:housenumber":"4a",
    "addr:postcode":"8630",
    "addr:street":"Oerenstraat",
    "iso:country":"BE",
    "sg:address":"Oerenstraat 4a",
    "sg:city":"Veurne",
    "sg:classifiers":[
        {
            "category":"Recreation",
            "type":"Entertainment"
        }
    ],
    "sg:phone":"+32 58 31 15 87",
    "sg:postcode":"8630",
    "sg:province":"West-Vlaanderen",
    "sg:tags":[
        "diver",
        "amusement"
    ],
    "wof:name":"Dj Yves",
    "wof:placetype":"venue"
},
  "geometry": {"coordinates":[2.6943099499,51.0305671692],"type":"Point"}
}