{
  "type": "Feature",
  "properties": {
    "addr:full":"Leffingestraat 85 Oostende West-Vlaanderen 8400",
    "addr:housenumber":"85",
    "addr:postcode":"8400",
    "addr:street":"Leffingestraat",
    "iso:country":"BE",
    "sg:address":"Leffingestraat 85",
    "sg:city":"Oostende",
    "sg:classifiers":[
        {
            "category":"Retail",
            "subcategory":"Event Space",
            "type":"Services"
        }
    ],
    "sg:phone":"+32 59 80 04 37",
    "sg:postcode":"8400",
    "sg:province":"West-Vlaanderen",
    "sg:tags":[
        "organisation"
    ],
    "wof:name":"Jeugd & Muziek-oostende",
    "wof:placetype":"venue"
},
  "geometry": {"coordinates":[2.9100179672,51.2191848755],"type":"Point"}
}