{
  "type": "Feature",
  "properties": {
    "addr:full":"Lindeboomstraat 11-1a Antwerpen Antwerpen 2060",
    "addr:housenumber":"11-1a",
    "addr:postcode":"2060",
    "addr:street":"Lindeboomstraat",
    "iso:country":"BE",
    "sg:address":"Lindeboomstraat 11-1a",
    "sg:city":"Antwerpen",
    "sg:classifiers":[
        {
            "category":"Real Estate",
            "subcategory":"Real Estate Services",
            "type":"Services"
        }
    ],
    "sg:phone":"+32 496 20 58 51",
    "sg:postcode":"2060",
    "sg:province":"Antwerpen",
    "wof:name":"Immo Lombart",
    "wof:placetype":"venue"
},
  "geometry": {"coordinates":[4.4363760948,51.2200660706],"type":"Point"}
}