{
  "type": "Feature",
  "properties": {
    "iso:country":"BE",
    "sg:address":"Vierde Lansierslaan 33",
    "sg:city":"Tienen",
    "sg:classifiers":[
        {
            "category":"Real Estate",
            "subcategory":"Architect",
            "type":"Services"
        }
    ],
    "sg:phone":"+32 16 81 30 04",
    "sg:postcode":"3300",
    "sg:province":"Vlaams-Brabant",
    "wof:name":"Strijckmans P",
    "wof:placetype":"venue"
},
  "geometry": {"coordinates":[4.928249836,50.8090591431],"type":"Point"}
}