{
  "type": "Feature",
  "properties": {
    "iso:country":"BE",
    "sg:address":"Schellebellestraat 8",
    "sg:city":"Roeselare",
    "sg:classifiers":[
        {
            "category":"Food & Beverages",
            "subcategory":"Fruits & Vegetables",
            "type":"Retail Goods"
        }
    ],
    "sg:phone":"+32 51 24 78 12",
    "sg:postcode":"8800",
    "sg:province":"West-Vlaanderen",
    "sg:tags":[
        "groenten"
    ],
    "wof:name":"Frucon",
    "wof:placetype":"venue"
},
  "geometry": {"coordinates":[3.1405889988,50.9490661621],"type":"Point"}
}