{
  "type": "Feature",
  "properties": {
    "iso:country":"BE",
    "sg:address":"Rue Saint-pierre 49",
    "sg:city":"Mouscron",
    "sg:classifiers":[
        {
            "category":"Shopping",
            "subcategory":"Hobbies, Toys, & Games",
            "type":"Retail Goods"
        }
    ],
    "sg:phone":"+32 56 33 16 50",
    "sg:postcode":"7700",
    "sg:province":"Hainaut",
    "sg:tags":[
        "toy",
        "-"
    ],
    "wof:name":"Mammy",
    "wof:placetype":"venue"
},
  "geometry": {"coordinates":[3.2160050869,50.7417564392],"type":"Point"}
}