{
  "type": "Feature",
  "properties": {
    "addr:full":"Rue Du Poin\u00e7on 47 Box 6 Bruxelles Bruxelles-Capitale 1000",
    "addr:housenumber":"47;6",
    "addr:postcode":"1000",
    "addr:street":"Rue Du Poinc\u0327On;Box",
    "iso:country":"BE",
    "sg:address":"Rue Du Poin\u00e7on 47 Box 6",
    "sg:city":"Bruxelles",
    "sg:classifiers":[
        {
            "category":"Utilities",
            "subcategory":"Telephone",
            "type":"Services"
        }
    ],
    "sg:phone":"+32 2 511 80 01",
    "sg:postcode":"1000",
    "sg:province":"Bruxelles-Capitale",
    "sg:tags":[
        "-",
        "internet"
    ],
    "wof:name":"Nicola\u00ef S",
    "wof:placetype":"venue"
},
  "geometry": {"coordinates":[4.3479762077,50.842086792],"type":"Point"}
}