{
  "type": "Feature",
  "properties": {
    "iso:country":"BE",
    "sg:address":"Burg. Maenhautstr. 92",
    "sg:city":"Merelbeke",
    "sg:orig_category":"Taxis services sp\u00e9ciaux. Salles de conf\u00e9rences and de r\u00e9ceptions",
    "sg:phone":"+32 9 252 11 87",
    "sg:postcode":"9820",
    "sg:province":"Oost-Vlaanderen",
    "wof:name":"Hof Ten Bosch",
    "wof:placetype":"venue"
},
  "geometry": {"coordinates":[3.7645070553,50.9889678955],"type":"Point"}
}