{
  "type": "Feature",
  "properties": {
    "iso:country":"BE",
    "sg:address":"Zandvoordeschorredijkstraat 71",
    "sg:city":"Oostende (stene)",
    "sg:classifiers":[
        {
            "category":"Professional",
            "subcategory":"Advertising",
            "type":"Services"
        }
    ],
    "sg:phone":"+32 59 51 25 26",
    "sg:postcode":"8400",
    "sg:province":"West-Vlaanderen",
    "sg:tags":[
        "painter"
    ],
    "wof:name":"Motief",
    "wof:placetype":"venue"
},
  "geometry": {"coordinates":[2.940860033,51.2070159912],"type":"Point"}
}