{
  "type": "Feature",
  "properties": {
    "addr:full":"Heilig-hartstraat 13 Izegem West-Vlaanderen 8870",
    "addr:housenumber":"13",
    "addr:postcode":"8870",
    "addr:street":"Heilig-Hartstraat",
    "iso:country":"BE",
    "sg:address":"Heilig-hartstraat 13",
    "sg:city":"Izegem",
    "sg:classifiers":[
        {
            "category":"Health Services",
            "subcategory":"Dentist",
            "type":"Services"
        }
    ],
    "sg:phone":"+32 51 31 89 12",
    "sg:postcode":"8870",
    "sg:province":"West-Vlaanderen",
    "wof:name":"Vandeputte Natalie",
    "wof:placetype":"venue"
},
  "geometry": {"coordinates":[3.2083420753,50.9174156189],"type":"Point"}
}