{
  "type": "Feature",
  "properties": {
    "addr:full":"Rue Pr\u00e9 Mack 814 Theux (la Reid) Li\u00e8ge 4910",
    "addr:housenumber":"814",
    "addr:postcode":"4910",
    "addr:street":"Rue Pre\u0301 Mack;La Reid",
    "iso:country":"BE",
    "sg:address":"Rue Pr\u00e9 Mack 814",
    "sg:city":"Theux (la Reid)",
    "sg:classifiers":[
        {
            "category":"Manufacturing",
            "subcategory":"Lumber",
            "type":"Manufacturing & Wholesale Goods"
        }
    ],
    "sg:phone":"+32 87 37 61 65",
    "sg:postcode":"4910",
    "sg:province":"Li\u00e8ge",
    "sg:tags":[
        "timber"
    ],
    "wof:name":"Schmitz P",
    "wof:placetype":"venue"
},
  "geometry": {"coordinates":[5.7941951752,50.4703102112],"type":"Point"}
}