{
  "type": "Feature",
  "properties": {
    "addr:full":"Nieuwstraat 11 Essen Antwerpen 2910",
    "addr:housenumber":"11",
    "addr:postcode":"2910",
    "addr:street":"Nieuwstraat",
    "iso:country":"BE",
    "sg:address":"Nieuwstraat 11",
    "sg:city":"Essen",
    "sg:classifiers":[
        {
            "category":"Banks & Credit Unions",
            "subcategory":"Investment Brokerage",
            "type":"Services"
        }
    ],
    "sg:phone":"+32 3 667 68 89",
    "sg:postcode":"2910",
    "sg:province":"Antwerpen",
    "sg:tags":[
        "article",
        "b\u00e9b\u00e9s",
        "v\u00eatements",
        "pour",
        "dame"
    ],
    "wof:name":"Moriaantje",
    "wof:placetype":"venue"
},
  "geometry": {"coordinates":[4.4706120491,51.4657974243],"type":"Point"}
}