{
  "type": "Feature",
  "properties": {
    "addr:full":"Lange Leemstraat 242 Antwerpen Antwerpen 2018",
    "addr:housenumber":"242",
    "addr:postcode":"2018",
    "addr:street":"Lange Leemstraat",
    "iso:country":"BE",
    "sg:address":"Lange Leemstraat 242",
    "sg:city":"Antwerpen",
    "sg:classifiers":[
        {
            "category":"Real Estate",
            "subcategory":"Architect",
            "type":"Services"
        }
    ],
    "sg:phone":"+32 3 281 84 43",
    "sg:postcode":"2018",
    "sg:province":"Antwerpen",
    "wof:name":"Sprangers D",
    "wof:placetype":"venue"
},
  "geometry": {"coordinates":[4.4205751419,51.2044143677],"type":"Point"}
}