{
  "type": "Feature",
  "properties": {
    "addr:full":"Avenue Guillaume De Greef 11 Bruxelles (jette) Bruxelles-Capitale 1090",
    "addr:housenumber":"11",
    "addr:postcode":"1090",
    "addr:street":"Avenue Guillaume De Greef",
    "iso:country":"BE",
    "sg:address":"Avenue Guillaume De Greef 11",
    "sg:city":"Bruxelles (jette)",
    "sg:classifiers":[
        {
            "category":"Health Services",
            "subcategory":"Health Practitioner",
            "type":"Services"
        }
    ],
    "sg:phone":"+32 2 478 32 70",
    "sg:postcode":"1090",
    "sg:province":"Bruxelles-Capitale",
    "sg:tags":[
        "physiotherapist"
    ],
    "wof:name":"Gr\u00e9goire E",
    "wof:placetype":"venue"
},
  "geometry": {"coordinates":[4.3355879784,50.8832969666],"type":"Point"}
}