{
  "type": "Feature",
  "properties": {
    "addr:full":"Heiveldekens 9bb Kontich Antwerpen 2550",
    "addr:housenumber":"9bb",
    "addr:postcode":"2550",
    "addr:street":"Heiveldekens",
    "iso:country":"BE",
    "sg:address":"Heiveldekens 9bb",
    "sg:city":"Kontich",
    "sg:orig_category":"Entretien and r\u00e9parations de voitures",
    "sg:phone":"+32 3 457 36 26",
    "sg:postcode":"2550",
    "sg:province":"Antwerpen",
    "wof:name":"Continental Autoglass",
    "wof:placetype":"venue"
},
  "geometry": {"coordinates":[4.4596071243,51.1225585938],"type":"Point"}
}