{
  "type": "Feature",
  "properties": {
    "iso:country":"BE",
    "sg:address":"Antwerpsesteenweg 223",
    "sg:city":"Vosselaar",
    "sg:classifiers":[
        {
            "category":"Restaurant",
            "type":"Food & Drink"
        }
    ],
    "sg:phone":"+32 14 61 85 07",
    "sg:postcode":"2350",
    "sg:province":"Antwerpen",
    "wof:name":"De Farmasie",
    "wof:placetype":"venue"
},
  "geometry": {"coordinates":[4.8753237724,51.3128929138],"type":"Point"}
}