{
  "type": "Feature",
  "properties": {
    "addr:full":"Vismarkt 7 Hasselt Limburg 3500",
    "addr:housenumber":"7",
    "addr:postcode":"3500",
    "addr:street":"Vismarkt",
    "iso:country":"BE",
    "sg:address":"Vismarkt 7",
    "sg:city":"Hasselt",
    "sg:classifiers":[
        {
            "category":"Personal",
            "subcategory":"Beauty Salon",
            "type":"Services"
        }
    ],
    "sg:phone":"+32 11 22 86 76",
    "sg:postcode":"3500",
    "sg:province":"Limburg",
    "sg:tags":[
        "de",
        "coiffure"
    ],
    "wof:name":"Coiffure Urbain & Stephan",
    "wof:placetype":"venue"
},
  "geometry": {"coordinates":[5.3384552002,50.9295387268],"type":"Point"}
}