{
  "type": "Feature",
  "properties": {
    "iso:country":"BE",
    "sg:address":"Chauss\u00e9e De Namur 56",
    "sg:city":"Eghez\u00e9e",
    "sg:classifiers":[
        {
            "category":"Banks & Credit Unions",
            "subcategory":"Investment Brokerage",
            "type":"Services"
        }
    ],
    "sg:phone":"+32 81 81 13 68",
    "sg:postcode":"5310",
    "sg:province":"Namur",
    "sg:tags":[
        "repair",
        "-",
        "installation",
        "sanitary",
        "article"
    ],
    "wof:name":"Aquatech",
    "wof:placetype":"venue"
},
  "geometry": {"coordinates":[4.9118528366,50.5869255066],"type":"Point"}
}