{
  "type": "Feature",
  "properties": {
    "iso:country":"BE",
    "sg:address":"Kasteelstraat 10",
    "sg:city":"Bornem",
    "sg:orig_category":"Voedingsspeciaalzaken",
    "sg:phone":"+32 3 889 44 34",
    "sg:postcode":"2880",
    "sg:province":"Antwerpen",
    "wof:name":"Delicatessa",
    "wof:placetype":"venue"
},
  "geometry": {"coordinates":[4.2338781357,51.1000518799],"type":"Point"}
}