{
  "type": "Feature",
  "properties": {
    "addr:full":"Missionarissenlaan 35 Anderlecht/anderlecht Bruxelles-Capitale 1070",
    "addr:housenumber":"35",
    "addr:postcode":"1070",
    "addr:street":"Missionarissenlaan",
    "iso:country":"BE",
    "sg:address":"Missionarissenlaan 35",
    "sg:city":"Anderlecht/anderlecht",
    "sg:orig_category":"Artsen and specialisten",
    "sg:phone":"+32 2 410 92 68",
    "sg:postcode":"1070",
    "sg:province":"Bruxelles-Capitale",
    "wof:name":"Patrick Votion",
    "wof:placetype":"venue"
},
  "geometry": {"coordinates":[4.3077311516,50.8492965698],"type":"Point"}
}