{
  "type": "Feature",
  "properties": {
    "addr:full":"Rue Jules Debecker 64 Bruxelles (koekelberg) Bruxelles-Capitale 1081",
    "addr:housenumber":"64",
    "addr:postcode":"1081",
    "addr:street":"Rue Jules Debecker",
    "iso:country":"BE",
    "sg:address":"Rue Jules Debecker 64",
    "sg:city":"Bruxelles (koekelberg)",
    "sg:classifiers":[
        {
            "category":"Wholesale",
            "subcategory":"Vending Machines",
            "type":"Manufacturing & Wholesale Goods"
        }
    ],
    "sg:phone":"+32 2 410 55 37",
    "sg:postcode":"1081",
    "sg:province":"Bruxelles-Capitale",
    "sg:tags":[
        "filling",
        "sealing"
    ],
    "wof:name":"Schuilenburg Nv",
    "wof:placetype":"venue"
},
  "geometry": {"coordinates":[4.3289461136,50.8610153198],"type":"Point"}
}