{
  "type": "Feature",
  "properties": {
    "iso:country":"BE",
    "sg:address":"Dorpsstraat 78",
    "sg:city":"As",
    "sg:orig_category":"Brood, gebak and snoepgoed",
    "sg:phone":"+32 89 65 73 26",
    "sg:postcode":"3665",
    "sg:province":"Limburg",
    "wof:name":"Nicolas Teelen",
    "wof:placetype":"venue"
},
  "geometry": {"coordinates":[5.5821909904,51.0065460205],"type":"Point"}
}