{
  "type": "Feature",
  "properties": {
    "addr:full":"Delften 23 Malle Antwerpen 2390",
    "addr:housenumber":"23",
    "addr:postcode":"2390",
    "addr:street":"Delften",
    "iso:country":"BE",
    "sg:address":"Delften 23",
    "sg:city":"Malle",
    "sg:orig_category":"Installation de menuiserie en bois and plastique",
    "sg:phone":"+32 3 311 52 34",
    "sg:postcode":"2390",
    "sg:province":"Antwerpen",
    "wof:name":"Leo Elst",
    "wof:placetype":"venue"
},
  "geometry": {"coordinates":[4.7112011909,51.2873764038],"type":"Point"}
}