{
  "type": "Feature",
  "properties": {
    "addr:full":"Rue De Danemark 5 Bruxelles (saint-gilles) Bruxelles-Capitale 1060",
    "addr:housenumber":"5",
    "addr:postcode":"1060",
    "addr:street":"Rue De Danemark",
    "iso:country":"BE",
    "sg:address":"Rue De Danemark 5",
    "sg:city":"Bruxelles (saint-gilles)",
    "sg:classifiers":[
        {
            "category":"Arts & Performance",
            "subcategory":"Theater",
            "type":"Entertainment"
        }
    ],
    "sg:phone":"+32 2 538 90 08",
    "sg:postcode":"1060",
    "sg:province":"Bruxelles-Capitale",
    "sg:tags":[
        "theatrical",
        "agency"
    ],
    "wof:name":"Agence Artistique Cinna",
    "wof:placetype":"venue"
},
  "geometry": {"coordinates":[4.3344368935,50.8325119019],"type":"Point"}
}