{
  "type": "Feature",
  "properties": {
    "addr:full":"Tuinlaan 58 Sint-niklaas Oost-Vlaanderen 9111",
    "addr:housenumber":"58",
    "addr:postcode":"9111",
    "addr:street":"Tuinlaan",
    "iso:country":"BE",
    "sg:address":"Tuinlaan 58",
    "sg:city":"Sint-niklaas",
    "sg:orig_category":"Sportclubs",
    "sg:phone":"+32 3 776 11 62",
    "sg:postcode":"9111",
    "sg:province":"Oost-Vlaanderen",
    "wof:name":"Seniors Petanque Club",
    "wof:placetype":"venue"
},
  "geometry": {"coordinates":[4.1098661423,51.1528205872],"type":"Point"}
}