{
  "type": "Feature",
  "properties": {
    "addr:full":"Albert Panisstraat 34 Beveren (beveren-waas) Oost-Vlaanderen 9120",
    "addr:housenumber":"34",
    "addr:postcode":"9120",
    "addr:street":"Albert Panisstraat;Oost-Vlaanderen",
    "iso:country":"BE",
    "sg:address":"Albert Panisstraat 34",
    "sg:city":"Beveren (beveren-waas)",
    "sg:orig_category":"Leisure articles",
    "sg:phone":"+32 3 775 28 79",
    "sg:postcode":"9120",
    "sg:province":"Oost-Vlaanderen",
    "wof:name":"K & C",
    "wof:placetype":"venue"
},
  "geometry": {"coordinates":[4.2483987808,51.2093811035],"type":"Point"}
}