{
  "type": "Feature",
  "properties": {
    "addr:full":"Servaes Daemsstraat 52 Herentals Antwerpen 2200",
    "addr:housenumber":"52",
    "addr:postcode":"2200",
    "addr:street":"Servaes Daemsstraat",
    "iso:country":"BE",
    "sg:address":"Servaes Daemsstraat 52",
    "sg:city":"Herentals",
    "sg:orig_category":"Foto-uitrusting Fotografen and fotostudio's",
    "sg:phone":"+32 14 26 24 93",
    "sg:postcode":"2200",
    "sg:province":"Antwerpen",
    "wof:name":"Fotooms",
    "wof:placetype":"venue"
},
  "geometry": {"coordinates":[4.833507061,51.1431999207],"type":"Point"}
}