{
  "type": "Feature",
  "properties": {
    "addr:full":"Avenue Arthur Dezangr\u00c9 20 Kraainem Vlaams-Brabant 1950",
    "addr:housenumber":"20",
    "addr:postcode":"1950",
    "addr:street":"Avenue Arthur Dezangre\u0301",
    "iso:country":"BE",
    "sg:address":"Avenue Arthur Dezangr\u00c9 20",
    "sg:city":"Kraainem",
    "sg:classifiers":[
        {
            "category":"Cafe",
            "type":"Food & Drink"
        }
    ],
    "sg:phone":"+32 2 721 47 87",
    "sg:postcode":"1950",
    "sg:province":"Vlaams-Brabant",
    "sg:tags":[
        "caf\u00e9s"
    ],
    "wof:name":"Bra-bel",
    "wof:placetype":"venue"
},
  "geometry": {"coordinates":[4.4683790207,50.8618087769],"type":"Point"}
}