{
  "type": "Feature",
  "properties": {
    "addr:full":"Chauss\u00c9e De Lille 337 Tournai Hainaut 7500",
    "addr:housenumber":"337",
    "addr:postcode":"7500",
    "addr:street":"Chausse\u0301E De Lille",
    "iso:country":"BE",
    "sg:address":"Chauss\u00c9e De Lille 337",
    "sg:city":"Tournai",
    "sg:orig_category":"Alternatieve geneeskunde",
    "sg:phone":"+32 69 21 46 12",
    "sg:postcode":"7500",
    "sg:province":"Hainaut",
    "wof:name":"M. Helin",
    "wof:placetype":"venue"
},
  "geometry": {"coordinates":[3.3808679581,50.6065254211],"type":"Point"}
}