{
  "type": "Feature",
  "properties": {
    "addr:full":"Sauvegardestraat 41 Puurs Antwerpen 2870",
    "addr:housenumber":"41",
    "addr:postcode":"2870",
    "addr:street":"Sauvegardestraat",
    "iso:country":"BE",
    "sg:address":"Sauvegardestraat 41",
    "sg:city":"Puurs",
    "sg:orig_category":"Banken and kredietinstellingen",
    "sg:phone":"+32 3 886 53 00",
    "sg:postcode":"2870",
    "sg:province":"Antwerpen",
    "wof:name":"Fortis",
    "wof:placetype":"venue"
},
  "geometry": {"coordinates":[4.3246231079,51.0814437866],"type":"Point"}
}