{
  "type": "Feature",
  "properties": {
    "addr:full":"Grepstraat 91 Merelbeke Oost-Vlaanderen 9820",
    "addr:housenumber":"91",
    "addr:postcode":"9820",
    "addr:street":"Grepstraat",
    "iso:country":"BE",
    "sg:address":"Grepstraat 91",
    "sg:city":"Merelbeke",
    "sg:orig_category":"Herstellingen and onderhoud van auto's",
    "sg:phone":"+32 9 362 02 40",
    "sg:postcode":"9820",
    "sg:province":"Oost-Vlaanderen",
    "wof:name":"Antoine Geirnaert",
    "wof:placetype":"venue"
},
  "geometry": {"coordinates":[3.718239069,50.9652862549],"type":"Point"}
}