{
  "type": "Feature",
  "properties": {
    "iso:country":"BE",
    "sg:address":"Baarledorpstraat 52a",
    "sg:city":"Gent (drongen)",
    "sg:classifiers":[
        {
            "category":"Retail",
            "subcategory":"Car Wash",
            "type":"Services"
        }
    ],
    "sg:phone":"+32 9 281 11 75",
    "sg:postcode":"9031",
    "sg:province":"Oost-Vlaanderen",
    "sg:tags":[
        "automobile",
        "washing",
        "-",
        "truck"
    ],
    "wof:name":"Barlo",
    "wof:placetype":"venue"
},
  "geometry": {"coordinates":[3.620290041,51.0372390747],"type":"Point"}
}