{
  "type": "Feature",
  "properties": {
    "addr:full":"Hogenhovestraat 80 Tielt West-Vlaanderen 8700",
    "addr:housenumber":"80",
    "addr:postcode":"8700",
    "addr:street":"Hogenhovestraat",
    "iso:country":"BE",
    "sg:address":"Hogenhovestraat 80",
    "sg:city":"Tielt",
    "sg:orig_category":"Woningbouw",
    "sg:phone":"+32 51 63 34 05",
    "sg:postcode":"8700",
    "sg:province":"West-Vlaanderen",
    "wof:name":"Van Wassenhove M.",
    "wof:placetype":"venue"
},
  "geometry": {"coordinates":[3.4168610573,50.9846878052],"type":"Point"}
}