{
  "type": "Feature",
  "properties": {
    "iso:country":"BE",
    "sg:address":"Casselsestraat 44",
    "sg:city":"Ieper",
    "sg:orig_category":"Produits chimiques Gr",
    "sg:phone":"+32 57 33 76 76",
    "sg:postcode":"8908",
    "sg:province":"West-Vlaanderen",
    "wof:name":"Depochim",
    "wof:placetype":"venue"
},
  "geometry": {"coordinates":[2.799943924,50.849697113],"type":"Point"}
}