{
  "type": "Feature",
  "properties": {
    "iso:country":"BE",
    "sg:address":"Brugmannlaan 9",
    "sg:city":"Sint-gillis/saint-gilles",
    "sg:orig_category":"Artsen and specialisten",
    "sg:phone":"+32 2 537 35 67",
    "sg:postcode":"1060",
    "sg:province":"Bruxelles-Capitale",
    "wof:name":"Robert Van Malleghem",
    "wof:placetype":"venue"
},
  "geometry": {"coordinates":[4.3533530235,50.8224258423],"type":"Point"}
}