{
  "type": "Feature",
  "properties": {
    "iso:country":"BE",
    "sg:address":"Rue Mont De Coliat 13",
    "sg:city":"Philippeville (franchimont)",
    "sg:classifiers":[
        {
            "category":"Building & Trades",
            "subcategory":"Electrical",
            "type":"Services"
        }
    ],
    "sg:phone":"+32 71 66 67 36",
    "sg:postcode":"5600",
    "sg:province":"Namur",
    "sg:tags":[
        "electric",
        "-",
        "housewiring",
        "contractor"
    ],
    "wof:name":"Electricit\u00e9 Service Sa",
    "wof:placetype":"venue"
},
  "geometry": {"coordinates":[4.6395111084,50.1884498596],"type":"Point"}
}