{
  "type": "Feature",
  "properties": {
    "addr:full":"Pastorijstraat 40 Wingene West-Vlaanderen 8750",
    "addr:housenumber":"40",
    "addr:postcode":"8750",
    "addr:street":"Pastorijstraat",
    "iso:country":"BE",
    "sg:address":"Pastorijstraat 40",
    "sg:city":"Wingene",
    "sg:orig_category":"Activit\u00e9s d\u00b4action sociale sans h\u00e9bergement",
    "sg:phone":"+32 51 61 16 49",
    "sg:postcode":"8750",
    "sg:province":"West-Vlaanderen",
    "wof:name":"Rode Kruis Zwevezele",
    "wof:placetype":"venue"
},
  "geometry": {"coordinates":[3.2141699791,51.0365905762],"type":"Point"}
}