{
  "type": "Feature",
  "properties": {
    "iso:country":"BE",
    "sg:address":"Koepoortstraat 15",
    "sg:city":"Meerhout",
    "sg:orig_category":"Loodgieterij, verwarming and sanitaire installaties",
    "sg:phone":"+32 14 30 95 81",
    "sg:postcode":"2450",
    "sg:province":"Antwerpen",
    "wof:name":"Peeters Karel",
    "wof:placetype":"venue"
},
  "geometry": {"coordinates":[5.0512671471,51.1220283508],"type":"Point"}
}