{
  "type": "Feature",
  "properties": {
    "addr:full":"Rue De La Verdure 26 Frameries Hainaut 7080",
    "addr:housenumber":"26",
    "addr:postcode":"7080",
    "addr:street":"Rue De La Verdure",
    "iso:country":"BE",
    "sg:address":"Rue De La Verdure 26",
    "sg:city":"Frameries",
    "sg:orig_category":"Pharmaciens",
    "sg:phone":"+32 65 67 14 25",
    "sg:postcode":"7080",
    "sg:province":"Hainaut",
    "wof:name":"U Pharmacie De Tollenaere",
    "wof:placetype":"venue"
},
  "geometry": {"coordinates":[3.9013249874,50.4052352905],"type":"Point"}
}