{
  "type": "Feature",
  "properties": {
    "iso:country":"BE",
    "sg:address":"Noordlaan 4bb",
    "sg:city":"Genk",
    "sg:orig_category":"Artsen and specialisten",
    "sg:phone":"+32 89 35 20 31",
    "sg:postcode":"3600",
    "sg:province":"Limburg",
    "wof:name":"Paul Heremans",
    "wof:placetype":"venue"
},
  "geometry": {"coordinates":[5.4834251404,50.9779586792],"type":"Point"}
}