{
  "type": "Feature",
  "properties": {
    "addr:full":"Zepperenweg 184 Sint-truiden Limburg 3800",
    "addr:housenumber":"184",
    "addr:postcode":"sint-truiden;3800",
    "addr:street":"Zepperenweg",
    "iso:country":"BE",
    "sg:address":"Zepperenweg 184",
    "sg:city":"Sint-truiden",
    "sg:classifiers":[
        {
            "category":"Food & Beverages",
            "subcategory":"Fruits & Vegetables",
            "type":"Retail Goods"
        }
    ],
    "sg:phone":"+32 11 68 95 07",
    "sg:postcode":"3800",
    "sg:province":"Limburg",
    "sg:tags":[
        "l\u00e9gumes"
    ],
    "wof:name":"Michel Nicolay",
    "wof:placetype":"venue"
},
  "geometry": {"coordinates":[5.2172560692,50.8199806213],"type":"Point"}
}