{
  "type": "Feature",
  "properties": {
    "addr:full":"Pachtgoeddreef 29 Gent (drongen) Oost-Vlaanderen 9031",
    "addr:housenumber":"29",
    "addr:postcode":"9031",
    "addr:street":"Pachtgoeddreef",
    "iso:country":"BE",
    "sg:address":"Pachtgoeddreef 29",
    "sg:city":"Gent (drongen)",
    "sg:classifiers":[
        {
            "category":"Professional",
            "subcategory":"Management & Consulting",
            "type":"Services"
        }
    ],
    "sg:phone":"+32 9 329 81 76",
    "sg:postcode":"9031",
    "sg:province":"Oost-Vlaanderen",
    "sg:tags":[
        "-",
        "processing",
        "data",
        "consultant"
    ],
    "wof:name":"Casneuf A",
    "wof:placetype":"venue"
},
  "geometry": {"coordinates":[3.6612660885,51.0594596863],"type":"Point"}
}