{
  "type": "Feature",
  "properties": {
    "iso:country":"BE",
    "sg:address":"Stationsstraat 22",
    "sg:city":"Willebroek",
    "sg:orig_category":"S\u00e9curit\u00e9 sociale",
    "sg:phone":"+32 3 886 30 91",
    "sg:postcode":"2830",
    "sg:province":"Antwerpen",
    "wof:name":"Vl. Neutraal Ziekenfonds",
    "wof:placetype":"venue"
},
  "geometry": {"coordinates":[4.3604459763,51.063243866],"type":"Point"}
}