{
  "type": "Feature",
  "properties": {
    "iso:country":"BE",
    "sg:address":"Augustijnslei 199b2",
    "sg:city":"Brasschaat",
    "sg:orig_category":"Advocaten and juridische adviseurs",
    "sg:phone":"+32 3 653 48 32",
    "sg:postcode":"2930",
    "sg:province":"Antwerpen",
    "wof:name":"Luc Verheyen",
    "wof:placetype":"venue"
},
  "geometry": {"coordinates":[4.487598896,51.2988395691],"type":"Point"}
}