{
  "type": "Feature",
  "properties": {
    "addr:full":"R\u00e9sidence Du Vert Mont 85 Tournai (chercq) Hainaut 7521",
    "addr:housenumber":"85",
    "addr:postcode":"7521",
    "addr:street":"Re\u0301Sidence Du Vert Mont",
    "iso:country":"BE",
    "sg:address":"R\u00e9sidence Du Vert Mont 85",
    "sg:city":"Tournai (chercq)",
    "sg:classifiers":[
        {
            "category":"Professional",
            "subcategory":"Accounting & Tax Preparation",
            "type":"Services"
        }
    ],
    "sg:phone":"+32 69 21 31 19",
    "sg:postcode":"7521",
    "sg:province":"Hainaut",
    "sg:tags":[
        "bookkeeper"
    ],
    "wof:name":"Gestcompta Sprl",
    "wof:placetype":"venue"
},
  "geometry": {"coordinates":[3.4131510258,50.5913276672],"type":"Point"}
}