{
  "type": "Feature",
  "properties": {
    "iso:country":"BE",
    "sg:address":"Werft 24",
    "sg:city":"Geel",
    "sg:classifiers":[
        {
            "category":"Social Services",
            "type":"Services"
        }
    ],
    "sg:phone":"+32 14 58 40 58",
    "sg:postcode":"2440",
    "sg:province":"Antwerpen",
    "wof:name":"Pitstop Tck",
    "wof:placetype":"venue"
},
  "geometry": {"coordinates":[4.9867730141,51.1617507935],"type":"Point"}
}