{
  "type": "Feature",
  "properties": {
    "addr:full":"Rue Du Temple 2 La Louvi\u00e8re Hainaut 7100",
    "addr:housenumber":"2",
    "addr:postcode":"7100",
    "addr:street":"Rue Du Temple",
    "iso:country":"BE",
    "sg:address":"Rue Du Temple 2",
    "sg:city":"La Louvi\u00e8re",
    "sg:classifiers":[
        {
            "category":"Cafe",
            "type":"Food & Drink"
        }
    ],
    "sg:phone":"+32 64 22 23 03",
    "sg:postcode":"7100",
    "sg:province":"Hainaut",
    "sg:tags":[
        "snack-bars"
    ],
    "wof:name":"Casse - Croute (le)",
    "wof:placetype":"venue"
},
  "geometry": {"coordinates":[4.1887950897,50.477180481],"type":"Point"}
}