{
  "type": "Feature",
  "properties": {
    "iso:country":"BE",
    "sg:address":"Zeshoekstraat 58",
    "sg:city":"Stekene",
    "sg:classifiers":[
        {
            "category":"Building & Trades",
            "subcategory":"Landscaping Services",
            "type":"Services"
        }
    ],
    "sg:phone":"+32 3 779 58 35",
    "sg:postcode":"9190",
    "sg:province":"Oost-Vlaanderen",
    "sg:tags":[
        "gardening",
        "garden",
        "maintenance"
    ],
    "wof:name":"Goossens F",
    "wof:placetype":"venue"
},
  "geometry": {"coordinates":[4.0286560059,51.2017593384],"type":"Point"}
}