{
  "type": "Feature",
  "properties": {
    "addr:full":"Beekstraat 48 Gistel West-Vlaanderen 8470",
    "addr:housenumber":"48",
    "addr:postcode":"8470",
    "addr:street":"Beekstraat",
    "iso:country":"BE",
    "sg:address":"Beekstraat 48",
    "sg:city":"Gistel",
    "sg:classifiers":[
        {
            "category":"Utilities",
            "subcategory":"Water",
            "type":"Services"
        }
    ],
    "sg:phone":"+32 59 43 07 07",
    "sg:postcode":"8470",
    "sg:province":"West-Vlaanderen",
    "sg:tags":[
        "purification"
    ],
    "wof:name":"Innveco",
    "wof:placetype":"venue"
},
  "geometry": {"coordinates":[2.9616520405,51.1199836731],"type":"Point"}
}