{
  "type": "Feature",
  "properties": {
    "addr:full":"Lourdesstraat 68 Gent (oostakker) Oost-Vlaanderen 9041",
    "addr:housenumber":"68",
    "addr:postcode":"9041",
    "addr:street":"Lourdesstraat",
    "iso:country":"BE",
    "sg:address":"Lourdesstraat 68",
    "sg:city":"Gent (oostakker)",
    "sg:classifiers":[
        {
            "category":"Fast Food",
            "type":"Food & Drink"
        }
    ],
    "sg:phone":"+32 9 251 69 65",
    "sg:postcode":"9041",
    "sg:province":"Oost-Vlaanderen",
    "sg:tags":[
        "fried",
        "stand",
        "potato"
    ],
    "wof:name":"Domino",
    "wof:placetype":"venue"
},
  "geometry": {"coordinates":[3.7573299408,51.0796928406],"type":"Point"}
}