{
  "type": "Feature",
  "properties": {
    "addr:full":"Zwaanhof 8 Roeselare West-Vlaanderen 8800",
    "addr:housenumber":"8",
    "addr:postcode":"8800",
    "addr:street":"Zwaanhof",
    "iso:country":"BE",
    "sg:address":"Zwaanhof 8",
    "sg:city":"Roeselare",
    "sg:classifiers":[
        {
            "category":"Health Services",
            "subcategory":"Health Practitioner",
            "type":"Services"
        }
    ],
    "sg:phone":"+32 51 20 62 26",
    "sg:postcode":"8800",
    "sg:province":"West-Vlaanderen",
    "sg:tags":[
        "physiotherapist"
    ],
    "wof:name":"Vinken Freddy",
    "wof:placetype":"venue"
},
  "geometry": {"coordinates":[3.1272189617,50.9355812073],"type":"Point"}
}