{
  "type": "Feature",
  "properties": {
    "iso:country":"BE",
    "sg:address":"Ommegangstraat 41",
    "sg:city":"Izegem",
    "sg:orig_category":"Kinderopvang",
    "sg:phone":"+32 51 31 36 51",
    "sg:postcode":"8870",
    "sg:province":"West-Vlaanderen",
    "wof:name":"Engelbewaarder",
    "wof:placetype":"venue"
},
  "geometry": {"coordinates":[3.2094709873,50.9170417786],"type":"Point"}
}