{
  "type": "Feature",
  "properties": {
    "addr:full":"Clos Des Aub\u00e9pines 13 Awans Li\u00e8ge 4340",
    "addr:housenumber":"13",
    "addr:postcode":"4340",
    "addr:street":"Clos Des Aube\u0301Pines",
    "iso:country":"BE",
    "sg:address":"Clos Des Aub\u00e9pines 13",
    "sg:city":"Awans",
    "sg:orig_category":"Bonsa\u00ef",
    "sg:phone":"+32 4 246 20 28",
    "sg:postcode":"4340",
    "sg:province":"Li\u00e8ge",
    "wof:name":"Bonsa\u00ef Club De Li\u00e8ge",
    "wof:placetype":"venue"
},
  "geometry": {"coordinates":[5.4636750221,50.6740074158],"type":"Point"}
}