{
  "type": "Feature",
  "properties": {
    "addr:full":"Rue De Virginal 164b106 Tubize Brabant Wallon 1480",
    "addr:housenumber":"164b106",
    "addr:postcode":"1480",
    "addr:street":"Rue De Virginal;Wallon",
    "iso:country":"BE",
    "sg:address":"Rue De Virginal 164b106",
    "sg:city":"Tubize",
    "sg:orig_category":"Plomberie, chauffage and installations sanitaires",
    "sg:phone":"+32 2 355 01 44",
    "sg:postcode":"1480",
    "sg:province":"Brabant Wallon",
    "wof:name":"Qualitherm",
    "wof:placetype":"venue"
},
  "geometry": {"coordinates":[4.2061338425,50.671875],"type":"Point"}
}