{
  "type": "Feature",
  "properties": {
    "addr:full":"Bellestraat 44 Sint-niklaas Oost-Vlaanderen 9100",
    "addr:housenumber":"44",
    "addr:postcode":"9100",
    "addr:street":"Bellestraat",
    "iso:country":"BE",
    "sg:address":"Bellestraat 44",
    "sg:city":"Sint-niklaas",
    "sg:classifiers":[
        {
            "category":"Health Services",
            "subcategory":"Nursing And Care Facility",
            "type":"Services"
        }
    ],
    "sg:phone":"+32 3 776 79 67",
    "sg:postcode":"9100",
    "sg:province":"Oost-Vlaanderen",
    "sg:tags":[
        "home",
        "rest"
    ],
    "wof:name":"Witte Huis ('t)",
    "wof:placetype":"venue"
},
  "geometry": {"coordinates":[4.1702427864,51.1739082336],"type":"Point"}
}