{
  "type": "Feature",
  "properties": {
    "iso:country":"BE",
    "sg:address":"Weggevoerdenstraat 136",
    "sg:city":"Leuven (wilsele)",
    "sg:classifiers":[
        {
            "category":"Building & Trades",
            "subcategory":"Construction",
            "type":"Services"
        }
    ],
    "sg:phone":"+32 16 44 83 42",
    "sg:postcode":"3012",
    "sg:province":"Vlaams-Brabant",
    "sg:tags":[
        "ecological"
    ],
    "wof:name":"Willem-vereycken Bvba",
    "wof:placetype":"venue"
},
  "geometry": {"coordinates":[4.7123408318,50.92552948],"type":"Point"}
}