{
  "type": "Feature",
  "properties": {
    "iso:country":"BE",
    "sg:address":"Rue De La Venne 16",
    "sg:city":"Bertrix",
    "sg:classifiers":[
        {
            "category":"Real Estate",
            "subcategory":"Surveying",
            "type":"Services"
        }
    ],
    "sg:phone":"+32 61 41 40 00",
    "sg:postcode":"6880",
    "sg:province":"Luxembourg",
    "sg:tags":[
        "surveyor",
        "land"
    ],
    "wof:name":"De La Hamayde D",
    "wof:placetype":"venue"
},
  "geometry": {"coordinates":[5.2537989616,49.8450164795],"type":"Point"}
}