{
  "type": "Feature",
  "properties": {
    "addr:full":"Val Des Seigneurs 13 Sint-pieters-woluwe/woluwe-saint-pierre Bruxelles-Capitale 1150",
    "addr:housenumber":"13",
    "addr:postcode":"1150",
    "addr:street":"Val Des Seigneurs;/",
    "iso:country":"BE",
    "sg:address":"Val Des Seigneurs 13",
    "sg:city":"Sint-pieters-woluwe/woluwe-saint-pierre",
    "sg:classifiers":[
        {
            "category":"Insurance",
            "subcategory":"Life Insurance",
            "type":"Services"
        }
    ],
    "sg:phone":"+32 2 775 92 60",
    "sg:postcode":"1150",
    "sg:province":"Bruxelles-Capitale",
    "sg:tags":[
        "assurance"
    ],
    "wof:name":"Topecho",
    "wof:placetype":"venue"
},
  "geometry": {"coordinates":[4.463160038,50.8399620056],"type":"Point"}
}