{
  "type": "Feature",
  "properties": {
    "iso:country":"BE",
    "sg:address":"Rue De Stalle 107",
    "sg:city":"Bruxelles (uccle)",
    "sg:classifiers":[
        {
            "category":"Autos & Motor Vehicles",
            "subcategory":"Auto Supplies",
            "type":"Retail Goods"
        }
    ],
    "sg:phone":"+32 2 376 45 24",
    "sg:postcode":"1180",
    "sg:province":"Bruxelles-Capitale",
    "sg:tags":[
        "access",
        "automobile",
        "part",
        "-"
    ],
    "wof:name":"Bmw Recup (techni-motor)",
    "wof:placetype":"venue"
},
  "geometry": {"coordinates":[4.324611187,50.7962341309],"type":"Point"}
}