{
  "type": "Feature",
  "properties": {
    "addr:full":"Ohiostraat 200 Oudenaarde Oost-Vlaanderen 9700",
    "addr:housenumber":"200",
    "addr:postcode":"9700",
    "addr:street":"Ohiostraat",
    "iso:country":"BE",
    "sg:address":"Ohiostraat 200",
    "sg:city":"Oudenaarde",
    "sg:orig_category":"V\u00e9t\u00e9rinaires",
    "sg:phone":"+32 55 30 41 81",
    "sg:postcode":"9700",
    "sg:province":"Oost-Vlaanderen",
    "wof:name":"L. De Clercq",
    "wof:placetype":"venue"
},
  "geometry": {"coordinates":[3.6221060753,50.8700180054],"type":"Point"}
}