{
  "type": "Feature",
  "properties": {
    "addr:full":"Rue Ma Campagne 3 Waterloo Brabant Wallon 1410",
    "addr:housenumber":"3",
    "addr:postcode":"1410",
    "addr:street":"Rue Ma Campagne",
    "iso:country":"BE",
    "sg:address":"Rue Ma Campagne 3",
    "sg:city":"Waterloo",
    "sg:classifiers":[
        {
            "category":"Professional",
            "subcategory":"Lawyer & Legal Services",
            "type":"Services"
        }
    ],
    "sg:phone":"+32 2 354 89 47",
    "sg:postcode":"1410",
    "sg:province":"Brabant Wallon",
    "wof:name":"Bouillet Marie-anne",
    "wof:placetype":"venue"
},
  "geometry": {"coordinates":[4.3817958832,50.70703125],"type":"Point"}
}