{
  "type": "Feature",
  "properties": {
    "addr:full":"Hulshoekstraat 31 Lummen (linkhout) Limburg 3560",
    "addr:housenumber":"31",
    "addr:postcode":"3560",
    "addr:street":"Hulshoekstraat",
    "iso:country":"BE",
    "sg:address":"Hulshoekstraat 31",
    "sg:city":"Lummen (linkhout)",
    "sg:classifiers":[
        {
            "category":"Personal",
            "subcategory":"Beauty Salon",
            "type":"Services"
        }
    ],
    "sg:phone":"+32 13 46 18 82",
    "sg:postcode":"3560",
    "sg:province":"Limburg",
    "wof:name":"Anne",
    "wof:placetype":"venue"
},
  "geometry": {"coordinates":[5.1437821388,50.9681510925],"type":"Point"}
}