{
  "type": "Feature",
  "properties": {
    "addr:full":"Stationsstraat 42 Houthalen-helchteren Limburg 3530",
    "addr:housenumber":"42",
    "addr:postcode":"3530",
    "addr:street":"Stationsstraat",
    "iso:country":"BE",
    "sg:address":"Stationsstraat 42",
    "sg:city":"Houthalen-helchteren",
    "sg:orig_category":"Installatie van houten of kunststof schrijnwerk",
    "sg:phone":"+32 11 60 10 00",
    "sg:postcode":"3530",
    "sg:province":"Limburg",
    "wof:name":"Soho Design",
    "wof:placetype":"venue"
},
  "geometry": {"coordinates":[5.366145134,51.0300636292],"type":"Point"}
}