{
  "type": "Feature",
  "properties": {
    "iso:country":"BE",
    "sg:address":"Dorpsstraat 22",
    "sg:city":"Herstappe/herstappe",
    "sg:orig_category":"Rundveehouders",
    "sg:phone":"+32 12 23 55 62",
    "sg:postcode":"3717",
    "sg:province":"Limburg",
    "wof:name":"Maurice Prosmans",
    "wof:placetype":"venue"
},
  "geometry": {"coordinates":[5.4238061905,50.7275428772],"type":"Point"}
}