{
  "type": "Feature",
  "properties": {
    "addr:full":"Chainrue 11 Durbuy Luxembourg 6940",
    "addr:housenumber":"11",
    "addr:postcode":"6940",
    "addr:street":"Chainrue",
    "iso:country":"BE",
    "sg:address":"Chainrue 11",
    "sg:city":"Durbuy",
    "sg:orig_category":"Boekhouders",
    "sg:phone":"+32 86 21 03 53",
    "sg:postcode":"6940",
    "sg:province":"Luxembourg",
    "wof:name":"A. Stassin",
    "wof:placetype":"venue"
},
  "geometry": {"coordinates":[5.4543361664,50.3515777588],"type":"Point"}
}