{
  "type": "Feature",
  "properties": {
    "addr:full":"Blijkstraat 1b1 Beringen Limburg 3580",
    "addr:housenumber":"1b1",
    "addr:postcode":"3580",
    "addr:street":"Blijkstraat",
    "iso:country":"BE",
    "sg:address":"Blijkstraat 1b1",
    "sg:city":"Beringen",
    "sg:orig_category":"Advocaten and juridische adviseurs",
    "sg:phone":"+32 11 45 29 69",
    "sg:postcode":"3580",
    "sg:province":"Limburg",
    "wof:name":"Bert Schoofs",
    "wof:placetype":"venue"
},
  "geometry": {"coordinates":[5.2224087715,51.0489387512],"type":"Point"}
}