{
  "type": "Feature",
  "properties": {
    "addr:full":"Rue Du Beau Lieu 2 Jodoigne Brabant Wallon 1370",
    "addr:housenumber":"2",
    "addr:postcode":"1370",
    "addr:street":"Rue Du Beau Lieu",
    "iso:country":"BE",
    "sg:address":"Rue Du Beau Lieu 2",
    "sg:city":"Jodoigne",
    "sg:classifiers":[
        {
            "category":"Arena",
            "subcategory":"Sports Club",
            "type":"Entertainment"
        }
    ],
    "sg:phone":"+32 10 81 24 81",
    "sg:postcode":"1370",
    "sg:province":"Brabant Wallon",
    "sg:tags":[
        "de"
    ],
    "wof:name":"T.c. L'ermitage",
    "wof:placetype":"venue"
},
  "geometry": {"coordinates":[4.8262162209,50.7158508301],"type":"Point"}
}