{
  "type": "Feature",
  "properties": {
    "iso:country":"BE",
    "sg:address":"Rue Du Poirier 6",
    "sg:city":"Ecaussinnes",
    "sg:orig_category":"Textiel",
    "sg:phone":"+32 67 44 22 87",
    "sg:postcode":"7191",
    "sg:province":"Hainaut",
    "wof:name":"Berg\u00c8re De France",
    "wof:placetype":"venue"
},
  "geometry": {"coordinates":[4.212097168,50.5823822021],"type":"Point"}
}