{
  "type": "Feature",
  "properties": {
    "iso:country":"BE",
    "sg:address":"Tenbos 65",
    "sg:city":"Elsene/ixelles",
    "sg:orig_category":"Architecten",
    "sg:phone":"+32 2 646 36 33",
    "sg:postcode":"1050",
    "sg:province":"Bruxelles-Capitale",
    "wof:name":"Olivier Soenens",
    "wof:placetype":"venue"
},
  "geometry": {"coordinates":[4.3637828827,50.8226203918],"type":"Point"}
}