{
  "type": "Feature",
  "properties": {
    "addr:full":"Muggenberglei 30 Antwerpen Antwerpen 2100",
    "addr:housenumber":"30",
    "addr:postcode":"2100",
    "addr:street":"Muggenberglei",
    "iso:country":"BE",
    "sg:address":"Muggenberglei 30",
    "sg:city":"Antwerpen",
    "sg:orig_category":"M\u00e9decins and sp\u00e9cialistes",
    "sg:phone":"+32 3 322 70 26",
    "sg:postcode":"2100",
    "sg:province":"Antwerpen",
    "wof:name":"Robrecht De Laet",
    "wof:placetype":"venue"
},
  "geometry": {"coordinates":[4.4586100578,51.2203941345],"type":"Point"}
}