{
  "type": "Feature",
  "properties": {
    "addr:full":"Ruddershovestraat 16b1 Zottegem Oost-Vlaanderen 9620",
    "addr:housenumber":"16b1",
    "addr:postcode":"9620",
    "addr:street":"Ruddershovestraat",
    "iso:country":"BE",
    "sg:address":"Ruddershovestraat 16b1",
    "sg:city":"Zottegem",
    "sg:orig_category":"Rundveehouders",
    "sg:phone":"+32 55 49 94 27",
    "sg:postcode":"9620",
    "sg:province":"Oost-Vlaanderen",
    "wof:name":"Antoine Van Tomme",
    "wof:placetype":"venue"
},
  "geometry": {"coordinates":[3.8112111092,50.871181488],"type":"Point"}
}