{
  "type": "Feature",
  "properties": {
    "iso:country":"BE",
    "sg:address":"Rue De Rosi\u00e8res 103",
    "sg:city":"Rixensart (genval)",
    "sg:classifiers":[
        {
            "category":"Real Estate",
            "subcategory":"Architect",
            "type":"Services"
        }
    ],
    "sg:phone":"+32 2 653 66 16",
    "sg:postcode":"1332",
    "sg:province":"Brabant Wallon",
    "wof:name":"Colin B",
    "wof:placetype":"venue"
},
  "geometry": {"coordinates":[4.521504879,50.7259254456],"type":"Point"}
}