{
  "type": "Feature",
  "properties": {
    "addr:full":"Rue De Plate 18 Saint-leger Luxembourg 6747",
    "addr:housenumber":"18",
    "addr:postcode":"6747",
    "addr:street":"Rue De Plate",
    "iso:country":"BE",
    "sg:address":"Rue De Plate 18",
    "sg:city":"Saint-leger",
    "sg:classifiers":[
        {
            "category":"Arena",
            "subcategory":"Sports Club",
            "type":"Entertainment"
        }
    ],
    "sg:phone":"+32 63 22 49 16",
    "sg:postcode":"6747",
    "sg:province":"Luxembourg",
    "sg:tags":[
        "terrain",
        "hors",
        "de",
        "installation",
        "sportifs"
    ],
    "wof:name":"Entente Sp. Meix-le-tige",
    "wof:placetype":"venue"
},
  "geometry": {"coordinates":[5.7198061943,49.6136627197],"type":"Point"}
}