{
  "type": "Feature",
  "properties": {
    "addr:full":"Kaardijk 30 Puurs (ruisbroek) Antwerpen 2870",
    "addr:housenumber":"30",
    "addr:postcode":"2870",
    "addr:street":"Kaardijk",
    "iso:country":"BE",
    "sg:address":"Kaardijk 30",
    "sg:city":"Puurs (ruisbroek)",
    "sg:classifiers":[
        {
            "category":"Building & Trades",
            "subcategory":"Equipment Rental",
            "type":"Services"
        }
    ],
    "sg:phone":"+32 3 886 77 00",
    "sg:postcode":"2870",
    "sg:province":"Antwerpen",
    "sg:tags":[
        "use",
        "apparatus",
        "tool",
        "-",
        "professional",
        "machines"
    ],
    "wof:name":"Goovaerts G",
    "wof:placetype":"venue"
},
  "geometry": {"coordinates":[4.3328251839,51.0850524902],"type":"Point"}
}