{
  "type": "Feature",
  "properties": {
    "addr:full":"Begonialaan 28 Harelbeke (hulste) West-Vlaanderen 8531",
    "addr:housenumber":"28",
    "addr:postcode":"8531",
    "addr:street":"Begonialaan",
    "iso:country":"BE",
    "sg:address":"Begonialaan 28",
    "sg:city":"Harelbeke (hulste)",
    "sg:classifiers":[
        {
            "category":"Banks & Credit Unions",
            "subcategory":"Bank",
            "type":"Services"
        }
    ],
    "sg:phone":"+32 56 71 43 85",
    "sg:postcode":"8531",
    "sg:province":"West-Vlaanderen",
    "sg:tags":[
        "savings-banks"
    ],
    "wof:name":"Argenta",
    "wof:placetype":"venue"
},
  "geometry": {"coordinates":[3.2897489071,50.8862915039],"type":"Point"}
}