{
  "type": "Feature",
  "properties": {
    "addr:full":"Rue De Grand Bigard 150 Bruxelles (berchem-sainte-agathe) Bruxelles-Capitale 1082",
    "addr:housenumber":"150",
    "addr:postcode":"1082",
    "addr:street":"Rue De Grand Bigard",
    "iso:country":"BE",
    "sg:address":"Rue De Grand Bigard 150",
    "sg:city":"Bruxelles (berchem-sainte-agathe)",
    "sg:orig_category":"Non-Classified Establishments",
    "sg:phone":"+32 2 469 16 12",
    "sg:postcode":"1082",
    "sg:province":"Bruxelles-Capitale",
    "wof:name":"P.c.a. Scrl",
    "wof:placetype":"venue"
},
  "geometry": {"coordinates":[4.2984418869,50.8594360352],"type":"Point"}
}