{
  "type": "Feature",
  "properties": {
    "iso:country":"BE",
    "sg:address":"Koedreef 5",
    "sg:city":"Oostrozebeke",
    "sg:classifiers":[
        {
            "category":"Manufacturing",
            "subcategory":"Rubber & Plastics",
            "type":"Manufacturing & Wholesale Goods"
        }
    ],
    "sg:phone":"+32 56 66 44 99",
    "sg:postcode":"8780",
    "sg:province":"West-Vlaanderen",
    "sg:tags":[
        "industrial",
        "-"
    ],
    "wof:name":"Mecoplas Nv",
    "wof:placetype":"venue"
},
  "geometry": {"coordinates":[3.3039600849,50.915725708],"type":"Point"}
}