{
  "type": "Feature",
  "properties": {
    "addr:full":"Chamb\u00c9rystraat 42 Etterbeek/etterbeek Bruxelles-Capitale 1040",
    "addr:housenumber":"42",
    "addr:postcode":"1040",
    "addr:street":"Chambe\u0301Rystraat",
    "iso:country":"BE",
    "sg:address":"Chamb\u00c9rystraat 42",
    "sg:city":"Etterbeek/etterbeek",
    "sg:orig_category":"Artiesten and kunstenaars",
    "sg:phone":"+32 2 648 09 24",
    "sg:postcode":"1040",
    "sg:province":"Bruxelles-Capitale",
    "wof:name":"Imprimerie Point J.p.",
    "wof:placetype":"venue"
},
  "geometry": {"coordinates":[4.3878550529,50.8306655884],"type":"Point"}
}