{
  "type": "Feature",
  "properties": {
    "addr:full":"Lindendreef 9 Kortrijk (rollegem) West-Vlaanderen 8510",
    "addr:housenumber":"9",
    "addr:postcode":"8510",
    "addr:street":"Lindendreef",
    "iso:country":"BE",
    "sg:address":"Lindendreef 9",
    "sg:city":"Kortrijk (rollegem)",
    "sg:classifiers":[
        {
            "category":"Health Services",
            "subcategory":"Doctor",
            "type":"Services"
        }
    ],
    "sg:phone":"+32 56 22 84 13",
    "sg:postcode":"8510",
    "sg:province":"West-Vlaanderen",
    "sg:tags":[
        "medicinephysicians",
        "surgeon"
    ],
    "wof:name":"Deconinck K",
    "wof:placetype":"venue"
},
  "geometry": {"coordinates":[3.2657339573,50.7906684875],"type":"Point"}
}