{
  "type": "Feature",
  "properties": {
    "iso:country":"BE",
    "sg:address":"Rue Paradis 50",
    "sg:city":"Li\u00c8ge (grand)",
    "sg:orig_category":"Sociale secretariaten",
    "sg:phone":"+32 4 229 67 00",
    "sg:postcode":"4000",
    "sg:province":"Li\u00e8ge",
    "wof:name":"Office National Des Pensions",
    "wof:placetype":"venue"
},
  "geometry": {"coordinates":[5.5705709457,50.6266937256],"type":"Point"}
}