{
  "type": "Feature",
  "properties": {
    "iso:country":"BE",
    "sg:address":"Vlaanderenstr 110",
    "sg:city":"Gent",
    "sg:classifiers":[
        {
            "category":"Food Court",
            "type":"Food & Drink"
        }
    ],
    "sg:phone":"+32 9 225 00 36",
    "sg:postcode":"9000",
    "sg:province":"Oost-Vlaanderen",
    "sg:tags":[
        "product",
        "related"
    ],
    "wof:name":"Van Den Bussche Marcel En Zonen M.",
    "wof:placetype":"venue"
},
  "geometry": {"coordinates":[3.7307190895,51.0493278503],"type":"Point"}
}