{
  "type": "Feature",
  "properties": {
    "iso:country":"BE",
    "sg:address":"Sint-petrus En Paulusstraat 16a",
    "sg:city":"Roeselare (rumbeke)",
    "sg:classifiers":[
        {
            "category":"Professional",
            "subcategory":"Computer Services",
            "type":"Services"
        }
    ],
    "sg:phone":"+32 51 20 15 55",
    "sg:postcode":"8800",
    "sg:province":"West-Vlaanderen",
    "sg:tags":[
        "network"
    ],
    "wof:name":"X.akt Bvba",
    "wof:placetype":"venue"
},
  "geometry": {"coordinates":[3.1549339294,50.9345169067],"type":"Point"}
}