{
  "type": "Feature",
  "properties": {
    "iso:country":"BE",
    "sg:address":"Lusstraat 29",
    "sg:city":"Erpe-mere (burst)",
    "sg:classifiers":[
        {
            "category":"Building & Trades",
            "subcategory":"Construction",
            "type":"Services"
        }
    ],
    "sg:phone":"+32 53 62 56 00",
    "sg:postcode":"9420",
    "sg:province":"Oost-Vlaanderen",
    "sg:tags":[
        "carpenter"
    ],
    "wof:name":"Van Steenberghe M",
    "wof:placetype":"venue"
},
  "geometry": {"coordinates":[3.9234390259,50.9047737122],"type":"Point"}
}