{
  "type": "Feature",
  "properties": {
    "iso:country":"BE",
    "sg:address":"Senator A Jeurissenlaan 1210",
    "sg:city":"Zonhoven",
    "sg:orig_category":"Non-Classified Establishments",
    "sg:phone":"+32 11 81 93 00",
    "sg:postcode":"3520",
    "sg:province":"Limburg",
    "wof:name":"Art\u00e9 Nv",
    "wof:placetype":"venue"
},
  "geometry": {"coordinates":[5.3837771416,50.9981460571],"type":"Point"}
}