{
  "type": "Feature",
  "properties": {
    "addr:full":"Oude Kuringerbaan 69 Hasselt Limburg 3500",
    "addr:housenumber":"69",
    "addr:postcode":"3500",
    "addr:street":"Oude Kuringerbaan",
    "iso:country":"BE",
    "sg:address":"Oude Kuringerbaan 69",
    "sg:city":"Hasselt",
    "sg:orig_category":"Schoonheidssalons",
    "sg:phone":"+32 11 25 15 94",
    "sg:postcode":"3500",
    "sg:province":"Limburg",
    "wof:name":"Instituut Esthetique",
    "wof:placetype":"venue"
},
  "geometry": {"coordinates":[5.3242430687,50.9348487854],"type":"Point"}
}