{
  "type": "Feature",
  "properties": {
    "iso:country":"BE",
    "sg:address":"Sint-aarnoutstraat 7",
    "sg:city":"Zedelgem",
    "sg:orig_category":"Plaatsen van vloer- and muurbekleding Woningbouw",
    "sg:phone":"+32 50 20 08 26",
    "sg:postcode":"8211",
    "sg:province":"West-Vlaanderen",
    "wof:name":"Fernand Vandycke",
    "wof:placetype":"venue"
},
  "geometry": {"coordinates":[3.0907199383,51.1116676331],"type":"Point"}
}