{
  "type": "Feature",
  "properties": {
    "addr:full":"Rue Fontainas 27 Bruxelles (saint-gilles) Bruxelles-Capitale 1060",
    "addr:housenumber":"27",
    "addr:postcode":"1060",
    "addr:street":"Rue Fontainas",
    "iso:country":"BE",
    "sg:address":"Rue Fontainas 27",
    "sg:city":"Bruxelles (saint-gilles)",
    "sg:classifiers":[
        {
            "category":"Professional",
            "type":"Services"
        }
    ],
    "sg:phone":"+32 2 537 41 99",
    "sg:postcode":"1060",
    "sg:province":"Bruxelles-Capitale",
    "sg:tags":[
        "writer"
    ],
    "wof:name":"Heilporn S",
    "wof:placetype":"venue"
},
  "geometry": {"coordinates":[4.3412427902,50.8333396912],"type":"Point"}
}