{
  "type": "Feature",
  "properties": {
    "iso:country":"BE",
    "sg:address":"Kennedylaan 7",
    "sg:city":"Kortrijk",
    "sg:classifiers":[
        {
            "category":"Social Services",
            "subcategory":"Child Care",
            "type":"Services"
        }
    ],
    "sg:phone":"+32 56 25 81 00",
    "sg:postcode":"8500",
    "sg:province":"West-Vlaanderen",
    "sg:tags":[
        "consulting",
        "management"
    ],
    "wof:name":"Tmp De Wiite & Morel Nv",
    "wof:placetype":"venue"
},
  "geometry": {"coordinates":[3.274559021,50.8030395508],"type":"Point"}
}