{
  "type": "Feature",
  "properties": {
    "iso:country":"BE",
    "sg:address":"Rue Du Grand Hospice 23ba",
    "sg:city":"Brussel/bruxelles",
    "sg:orig_category":"Epiceries",
    "sg:phone":"+32 2 218 42 78",
    "sg:postcode":"1000",
    "sg:province":"Bruxelles-Capitale",
    "wof:name":"Joseph Depever",
    "wof:placetype":"venue"
},
  "geometry": {"coordinates":[4.3476419449,50.8536682129],"type":"Point"}
}