{
  "type": "Feature",
  "properties": {
    "iso:country":"BE",
    "sg:address":"Waide Des Dames 76",
    "sg:city":"Li\u00e8ge 1 (grivegn\u00e9e)",
    "sg:classifiers":[
        {
            "category":"Personal",
            "subcategory":"Beauty Salon",
            "type":"Services"
        }
    ],
    "sg:phone":"+32 4 342 32 80",
    "sg:postcode":"4030",
    "sg:province":"Li\u00e8ge",
    "sg:tags":[
        "lady",
        "-",
        "hairdressing"
    ],
    "wof:name":"Edouard",
    "wof:placetype":"venue"
},
  "geometry": {"coordinates":[5.6066298485,50.6288986206],"type":"Point"}
}