{
  "type": "Feature",
  "properties": {
    "addr:full":"Warandeberg 30 Wezembeek-oppem Vlaams-Brabant 1970",
    "addr:housenumber":"30",
    "addr:postcode":"1970",
    "addr:street":"Warandeberg",
    "iso:country":"BE",
    "sg:address":"Warandeberg 30",
    "sg:city":"Wezembeek-oppem",
    "sg:classifiers":[
        {
            "category":"Manufacturing",
            "subcategory":"Paper Products",
            "type":"Manufacturing & Wholesale Goods"
        }
    ],
    "sg:phone":"+32 2 731 69 30",
    "sg:postcode":"1970",
    "sg:province":"Vlaams-Brabant",
    "sg:tags":[
        "industry",
        "impregnating",
        "agent"
    ],
    "wof:name":"Nicolay Charles S.p.r.l.",
    "wof:placetype":"venue"
},
  "geometry": {"coordinates":[4.4847140312,50.8563156128],"type":"Point"}
}