{
  "type": "Feature",
  "properties": {
    "iso:country":"BE",
    "sg:address":"Avenue Fonsny 113",
    "sg:city":"Bruxelles (saint-gilles)",
    "sg:classifiers":[
        {
            "category":"Social Services",
            "subcategory":"Child Care",
            "type":"Services"
        }
    ],
    "sg:phone":"+32 2 539 15 52",
    "sg:postcode":"1060",
    "sg:province":"Bruxelles-Capitale",
    "sg:tags":[
        "home"
    ],
    "wof:name":"Maison De La Rue De France Communaut\u00e9s Des 2 Coeurs",
    "wof:placetype":"venue"
},
  "geometry": {"coordinates":[4.3315038681,50.83045578],"type":"Point"}
}