{
  "type": "Feature",
  "properties": {
    "iso:country":"BE",
    "sg:address":"Plantin En Moretuslei 331",
    "sg:city":"Antwerpen",
    "sg:orig_category":"Ordinateurs and \u00e9quipement informatique. Formation and enseignement. R\u00e9alisation de programmes and l",
    "sg:phone":"+32 3 257 25 75",
    "sg:postcode":"2140",
    "sg:province":"Antwerpen",
    "wof:name":"Cryns Software Solutions",
    "wof:placetype":"venue"
},
  "geometry": {"coordinates":[4.4332199097,51.2137565613],"type":"Point"}
}