{
  "type": "Feature",
  "properties": {
    "addr:full":"Spoorweglaan 18 Pittem West-Vlaanderen 8740",
    "addr:housenumber":"18",
    "addr:postcode":"8740",
    "addr:street":"Spoorweglaan",
    "iso:country":"BE",
    "sg:address":"Spoorweglaan 18",
    "sg:city":"Pittem",
    "sg:orig_category":"Artsen and specialisten",
    "sg:phone":"+32 51 46 70 72",
    "sg:postcode":"8740",
    "sg:province":"West-Vlaanderen",
    "wof:name":"Ann Pollet",
    "wof:placetype":"venue"
},
  "geometry": {"coordinates":[3.2600190639,50.9903717041],"type":"Point"}
}