{
  "type": "Feature",
  "properties": {
    "iso:country":"BE",
    "sg:address":"Nieuwstraat 28a",
    "sg:city":"Opwijk",
    "sg:orig_category":"Biljart- and snookerzalen Caf\u00e9s",
    "sg:phone":"+32 52 35 58 38",
    "sg:postcode":"1745",
    "sg:province":"Vlaams-Brabant",
    "wof:name":"Snooker Palace",
    "wof:placetype":"venue"
},
  "geometry": {"coordinates":[4.1766009331,50.9693145752],"type":"Point"}
}