{
  "type": "Feature",
  "properties": {
    "addr:full":"Beverlosesteenweg 26 Beringen Limburg 3583",
    "addr:housenumber":"26",
    "addr:postcode":"3583",
    "addr:street":"Beverlosesteenweg",
    "iso:country":"BE",
    "sg:address":"Beverlosesteenweg 26",
    "sg:city":"Beringen",
    "sg:orig_category":"Epiceries",
    "sg:phone":"+32 11 42 26 22",
    "sg:postcode":"3583",
    "sg:province":"Limburg",
    "wof:name":"Claes A. & M.",
    "wof:placetype":"venue"
},
  "geometry": {"coordinates":[5.1706700325,51.0389442444],"type":"Point"}
}