{
  "type": "Feature",
  "properties": {
    "iso:country":"BE",
    "sg:address":"De Bergen 49",
    "sg:city":"Bonheiden",
    "sg:classifiers":[
        {
            "category":"Social Services",
            "subcategory":"Child Care",
            "type":"Services"
        }
    ],
    "sg:phone":"+32 15 51 21 89",
    "sg:postcode":"2820",
    "sg:province":"Antwerpen",
    "sg:tags":[
        "home"
    ],
    "wof:name":"Jeugddorp",
    "wof:placetype":"venue"
},
  "geometry": {"coordinates":[4.5712370872,51.0161781311],"type":"Point"}
}