{
  "type": "Feature",
  "properties": {
    "addr:full":"Wijnegem Shopping Center Wijnegem Antwerpen 2110",
    "addr:postcode":"2110",
    "iso:country":"BE",
    "sg:address":"Wijnegem Shopping Center",
    "sg:city":"Wijnegem",
    "sg:classifiers":[
        {
            "category":"Banks & Credit Unions",
            "subcategory":"Investment Brokerage",
            "type":"Services"
        }
    ],
    "sg:phone":"+32 3 353 95 65",
    "sg:postcode":"2110",
    "sg:province":"Antwerpen",
    "sg:tags":[
        "jean",
        "casual",
        "wear"
    ],
    "wof:name":"Vet",
    "wof:placetype":"venue"
},
  "geometry": {"coordinates":[4.5248470306,51.2279434204],"type":"Point"}
}