{
  "type": "Feature",
  "properties": {
    "iso:country":"BE",
    "sg:address":"Rue Des Ecoles 42",
    "sg:city":"Lens (montignies-lez-lens)",
    "sg:classifiers":[
        {
            "category":"Home & Garden",
            "subcategory":"Household Appliances",
            "type":"Retail Goods"
        }
    ],
    "sg:phone":"+32 65 22 68 31",
    "sg:postcode":"7870",
    "sg:province":"Hainaut",
    "sg:tags":[
        "repair",
        "mainten",
        "-",
        "electric"
    ],
    "wof:name":"Ergot Ets",
    "wof:placetype":"venue"
},
  "geometry": {"coordinates":[3.9415268898,50.5639266968],"type":"Point"}
}