{
  "type": "Feature",
  "properties": {
    "iso:country":"BE",
    "sg:address":"Place Rogier 1",
    "sg:city":"Bruxelles",
    "sg:orig_category":"RESTAURANTS: RESTAURANTS",
    "sg:phone":"+32 2 203 20 03",
    "sg:postcode":"1000",
    "sg:province":"Bruxelles-Capitale",
    "wof:name":"Le Saint Germain",
    "wof:placetype":"venue"
},
  "geometry": {"coordinates":[4.3603858948,50.8547935486],"type":"Point"}
}