{
  "type": "Feature",
  "properties": {
    "addr:full":"Spanjestraat 97 Sint-gillis/saint-gilles Bruxelles-Capitale 1060",
    "addr:housenumber":"97",
    "addr:postcode":"1060",
    "addr:street":"Spanjestraat",
    "iso:country":"BE",
    "sg:address":"Spanjestraat 97",
    "sg:city":"Sint-gillis/saint-gilles",
    "sg:orig_category":"Artsen and specialisten",
    "sg:phone":"+32 2 534 53 52",
    "sg:postcode":"1060",
    "sg:province":"Bruxelles-Capitale",
    "wof:name":"Marie-anne Meeus",
    "wof:placetype":"venue"
},
  "geometry": {"coordinates":[4.3526391983,50.8243865967],"type":"Point"}
}