{
  "type": "Feature",
  "properties": {
    "addr:full":"Opeindestraat 14 Kortessem Limburg 3720",
    "addr:housenumber":"14",
    "addr:postcode":"3720",
    "addr:street":"Opeindestraat;Limburg",
    "iso:country":"BE",
    "sg:address":"Opeindestraat 14",
    "sg:city":"Kortessem",
    "sg:classifiers":[
        {
            "category":"Farming",
            "subcategory":"Crops",
            "type":"Manufacturing & Wholesale Goods"
        }
    ],
    "sg:phone":"+32 11 37 69 64",
    "sg:postcode":"3720",
    "sg:province":"Limburg",
    "sg:tags":[
        "vegetable",
        "fruit",
        "-",
        "grower"
    ],
    "wof:name":"Groven P",
    "wof:placetype":"venue"
},
  "geometry": {"coordinates":[5.3864488602,50.8567008972],"type":"Point"}
}