{
  "type": "Feature",
  "properties": {
    "iso:country":"BE",
    "sg:address":"Rue De L'eglise 20",
    "sg:city":"Weismes (robertville)",
    "sg:classifiers":[
        {
            "category":"Health Services",
            "subcategory":"Health Practitioner",
            "type":"Services"
        }
    ],
    "sg:phone":"+32 80 44 53 95",
    "sg:postcode":"4950",
    "sg:province":"Li\u00e8ge",
    "sg:tags":[
        "physiotherapist"
    ],
    "wof:name":"Caillet M F",
    "wof:placetype":"venue"
},
  "geometry": {"coordinates":[6.1104340553,50.4672698975],"type":"Point"}
}