{
  "type": "Feature",
  "properties": {
    "addr:full":"Stoeterijlaan 110 Sint-pieters-woluwe/woluwe-saint-pierre Bruxelles-Capitale 1150",
    "addr:housenumber":"110",
    "addr:postcode":"1150",
    "addr:street":"Stoeterijlaan;/",
    "iso:country":"BE",
    "sg:address":"Stoeterijlaan 110",
    "sg:city":"Sint-pieters-woluwe/woluwe-saint-pierre",
    "sg:orig_category":"Fotografen and fotostudio's",
    "sg:phone":"+32 2 779 93 92",
    "sg:postcode":"1150",
    "sg:province":"Bruxelles-Capitale",
    "wof:name":"Vincent De Duytsche",
    "wof:placetype":"venue"
},
  "geometry": {"coordinates":[4.4606118202,50.8294448853],"type":"Point"}
}