{
  "type": "Feature",
  "properties": {
    "addr:full":"Brusselsesteenweg 444a Gent Oost-Vlaanderen 9050",
    "addr:housenumber":"444a",
    "addr:postcode":"9050",
    "addr:street":"Brusselsesteenweg;Oost-Vlaanderen",
    "iso:country":"BE",
    "sg:address":"Brusselsesteenweg 444a",
    "sg:city":"Gent",
    "sg:orig_category":"D\u00e9taillants en pi\u00e8ces and accessoires de voitures. Entretien and r\u00e9parations de voitures",
    "sg:phone":"+32 9 230 68 95",
    "sg:postcode":"9050",
    "sg:province":"Oost-Vlaanderen",
    "wof:name":"Speedy",
    "wof:placetype":"venue"
},
  "geometry": {"coordinates":[3.7470419407,51.0385055542],"type":"Point"}
}