{
  "type": "Feature",
  "properties": {
    "addr:full":"Rempart Saint-joseph 25 Enghien Hainaut 7850",
    "addr:housenumber":"25",
    "addr:postcode":"7850",
    "addr:street":"Rempart Saint-Joseph",
    "iso:country":"BE",
    "sg:address":"Rempart Saint-joseph 25",
    "sg:city":"Enghien",
    "sg:classifiers":[
        {
            "category":"Education",
            "subcategory":"Dance Studio",
            "type":"Public Place"
        }
    ],
    "sg:phone":"+32 2 395 77 75",
    "sg:postcode":"7850",
    "sg:province":"Hainaut",
    "sg:tags":[
        "school",
        "dancing"
    ],
    "wof:name":"Les Jeunes Talents Asbl",
    "wof:placetype":"venue"
},
  "geometry": {"coordinates":[4.0375599861,50.6963768005],"type":"Point"}
}