{
  "type": "Feature",
  "properties": {
    "addr:full":"Aachener Strasse 24a Eupen Li\u00e8ge 4700",
    "addr:housenumber":"24a",
    "addr:postcode":"4700",
    "addr:street":"Aachener Strasse",
    "iso:country":"BE",
    "sg:address":"Aachener Strasse 24a",
    "sg:city":"Eupen",
    "sg:orig_category":"Ambassades and consulats",
    "sg:phone":"+32 87 55 71 81",
    "sg:postcode":"4700",
    "sg:province":"Li\u00e8ge",
    "wof:name":"Consulat Von Ostenreich",
    "wof:placetype":"venue"
},
  "geometry": {"coordinates":[6.031981945,50.6331100464],"type":"Point"}
}