{
  "type": "Feature",
  "properties": {
    "iso:country":"BE",
    "sg:address":"Kleitkalseide 170",
    "sg:city":"Maldegem",
    "sg:classifiers":[
        {
            "category":"Home & Garden",
            "subcategory":"Household Appliances",
            "type":"Retail Goods"
        }
    ],
    "sg:phone":"+32 50 71 40 54",
    "sg:postcode":"9990",
    "sg:province":"Oost-Vlaanderen",
    "sg:tags":[
        "repair",
        "mainten",
        "-",
        "electric"
    ],
    "wof:name":"Geyssens I",
    "wof:placetype":"venue"
},
  "geometry": {"coordinates":[3.4516589642,51.1779060364],"type":"Point"}
}