{
  "type": "Feature",
  "properties": {
    "addr:full":"Oostendelaan 10 Middelkerke (groot) West-Vlaanderen 8430",
    "addr:housenumber":"10",
    "addr:postcode":"8430",
    "addr:street":"Oostendelaan;Groot West-Vlaanderen",
    "iso:country":"BE",
    "sg:address":"Oostendelaan 10",
    "sg:city":"Middelkerke (groot)",
    "sg:classifiers":[
        {
            "category":"Personal",
            "subcategory":"Beauty Salon",
            "type":"Services"
        }
    ],
    "sg:phone":"+32 59 30 21 56",
    "sg:postcode":"8430",
    "sg:province":"West-Vlaanderen",
    "sg:tags":[
        "de",
        "coiffure"
    ],
    "wof:name":"Nancy's Hair Fashion",
    "wof:placetype":"venue"
},
  "geometry": {"coordinates":[2.8216209412,51.1852760315],"type":"Point"}
}