{
  "type": "Feature",
  "properties": {
    "iso:country":"BE",
    "sg:address":"Koning Albertlaan 94",
    "sg:city":"Lommel",
    "sg:classifiers":[
        {
            "category":"Structure",
            "subcategory":"Office Building",
            "type":"Public Place"
        }
    ],
    "sg:phone":"+32 11 54 37 65",
    "sg:postcode":"3920",
    "sg:province":"Limburg",
    "sg:tags":[
        "-",
        "type",
        "door",
        "sliding",
        "overhead"
    ],
    "wof:name":"Quanten Fred",
    "wof:placetype":"venue"
},
  "geometry": {"coordinates":[5.3257040977,51.2300796509],"type":"Point"}
}