{
  "type": "Feature",
  "properties": {
    "addr:full":"Rue Ernest Drisse 13 Binche Hainaut 7130",
    "addr:housenumber":"13",
    "addr:postcode":"7130",
    "addr:street":"Rue Ernest Drisse",
    "iso:country":"BE",
    "sg:address":"Rue Ernest Drisse 13",
    "sg:city":"Binche",
    "sg:classifiers":[
        {
            "category":"Transit Center",
            "subcategory":"Passenger",
            "type":"Transportation"
        }
    ],
    "sg:phone":"+32 64 33 53 56",
    "sg:postcode":"7130",
    "sg:province":"Hainaut",
    "sg:tags":[
        "taxidermist"
    ],
    "wof:name":"Hecq A",
    "wof:placetype":"venue"
},
  "geometry": {"coordinates":[4.1651749611,50.4169845581],"type":"Point"}
}