{
  "type": "Feature",
  "properties": {
    "iso:country":"BE",
    "sg:address":"Hendrik Consciencestraat 10ba",
    "sg:city":"Diksmuide",
    "sg:orig_category":"Epiceries",
    "sg:phone":"+32 51 50 35 78",
    "sg:postcode":"8600",
    "sg:province":"West-Vlaanderen",
    "wof:name":"De Bazaar",
    "wof:placetype":"venue"
},
  "geometry": {"coordinates":[2.8657801151,51.0334663391],"type":"Point"}
}