{
  "type": "Feature",
  "properties": {
    "iso:country":"BE",
    "sg:address":"De Schom 15",
    "sg:city":"Genk",
    "sg:classifiers":[
        {
            "category":"Wholesale",
            "subcategory":"Meat",
            "type":"Manufacturing & Wholesale Goods"
        }
    ],
    "sg:phone":"+32 89 30 56 76",
    "sg:postcode":"3600",
    "sg:province":"Limburg",
    "sg:tags":[
        "whol",
        "-"
    ],
    "wof:name":"Industriele Beenhouwerij Johny",
    "wof:placetype":"venue"
},
  "geometry": {"coordinates":[5.4582691193,50.948135376],"type":"Point"}
}