{
  "type": "Feature",
  "properties": {
    "addr:full":"Rue Gilles-demarteau 15 Li\u00e8ge 1 Li\u00e8ge 4000",
    "addr:housenumber":"15;1",
    "addr:postcode":"4000",
    "addr:street":"Rue Gilles-Demarteau",
    "iso:country":"BE",
    "sg:address":"Rue Gilles-demarteau 15",
    "sg:city":"Li\u00e8ge 1",
    "sg:classifiers":[
        {
            "category":"Health Services",
            "subcategory":"Health Practitioner",
            "type":"Services"
        }
    ],
    "sg:phone":"+32 4 253 20 90",
    "sg:postcode":"4000",
    "sg:province":"Li\u00e8ge",
    "sg:tags":[
        "physiotherapist"
    ],
    "wof:name":"Verheecke Th",
    "wof:placetype":"venue"
},
  "geometry": {"coordinates":[5.5506129265,50.6355247498],"type":"Point"}
}