{
  "type": "Feature",
  "properties": {
    "addr:full":"Potaardestraat 89 Lebbeke Oost-Vlaanderen 9280",
    "addr:housenumber":"89",
    "addr:postcode":"9280",
    "addr:street":"Potaardestraat",
    "iso:country":"BE",
    "sg:address":"Potaardestraat 89",
    "sg:city":"Lebbeke",
    "sg:classifiers":[
        {
            "category":"Freight",
            "type":"Transportation"
        }
    ],
    "sg:phone":"+32 52 41 56 39",
    "sg:postcode":"9280",
    "sg:province":"Oost-Vlaanderen",
    "sg:tags":[
        "-",
        "transport"
    ],
    "wof:name":"Tonnytrans Bvba",
    "wof:placetype":"venue"
},
  "geometry": {"coordinates":[4.1572871208,51.0021476746],"type":"Point"}
}