{
  "type": "Feature",
  "properties": {
    "iso:country":"BE",
    "sg:address":"Rue De Fayembois 53",
    "sg:city":"Beyne-heusay",
    "sg:orig_category":"Diverse bouwinstallaties Verlichtingsapparaten and elektrische lampen Fab",
    "sg:phone":"+32 4 365 57 78",
    "sg:postcode":"4610",
    "sg:province":"Li\u00e8ge",
    "wof:name":"Elfel N\u00c9on",
    "wof:placetype":"venue"
},
  "geometry": {"coordinates":[5.6464848518,50.6271591187],"type":"Point"}
}