{
  "type": "Feature",
  "properties": {
    "addr:full":"Route De L'eau Rouge 6 Stavelot Li\u00e8ge 4970",
    "addr:housenumber":"6",
    "addr:postcode":"4970",
    "addr:street":"Route De L'Eau Rouge",
    "iso:country":"BE",
    "sg:address":"Route De L'eau Rouge 6",
    "sg:city":"Stavelot",
    "sg:orig_category":"Ramassage and traitement des d\u00e9chets m\u00e9nagers",
    "sg:phone":"+32 80 86 28 62",
    "sg:postcode":"4970",
    "sg:province":"Li\u00e8ge",
    "wof:name":"Albert Fr\u00c8res",
    "wof:placetype":"venue"
},
  "geometry": {"coordinates":[5.9491348267,50.4184608459],"type":"Point"}
}