{
  "type": "Feature",
  "properties": {
    "addr:full":"Naamsesteenweg 400 Box 11 Leuven (heverlee) Vlaams-Brabant 3001",
    "addr:housenumber":"400 box 11",
    "addr:postcode":"3001",
    "addr:street":"Naamsesteenweg",
    "iso:country":"BE",
    "sg:address":"Naamsesteenweg 400 Box 11",
    "sg:city":"Leuven (heverlee)",
    "sg:classifiers":[
        {
            "category":"Social Services",
            "subcategory":"Job Training",
            "type":"Services"
        }
    ],
    "sg:phone":"+32 16 40 67 05",
    "sg:postcode":"3001",
    "sg:province":"Vlaams-Brabant",
    "sg:tags":[
        "personnel"
    ],
    "wof:name":"Centrum Voor Consulting En Training In Communicatie",
    "wof:placetype":"venue"
},
  "geometry": {"coordinates":[4.6955780983,50.8560600281],"type":"Point"}
}