{
  "type": "Feature",
  "properties": {
    "iso:country":"BE",
    "sg:address":"Brugse Heirweg 68",
    "sg:city":"Stekene",
    "sg:classifiers":[
        {
            "category":"Cafe",
            "type":"Food & Drink"
        }
    ],
    "sg:phone":"+32 9 346 71 71",
    "sg:postcode":"9190",
    "sg:province":"Oost-Vlaanderen",
    "sg:tags":[
        "caf\u00e9s"
    ],
    "wof:name":"Caroline Claerhout",
    "wof:placetype":"venue"
},
  "geometry": {"coordinates":[4.0168581009,51.1892738342],"type":"Point"}
}