{
  "type": "Feature",
  "properties": {
    "addr:full":"Moenplaats 11 Zwevegem 8552",
    "addr:housenumber":"11",
    "addr:postcode":"8552",
    "addr:street":"Moenplaats",
    "iso:country":"BE",
    "sg:address":"Moenplaats 11",
    "sg:city":"Zwevegem",
    "sg:orig_category":"Woningbouw",
    "sg:phone":"+32 56 64 74 70",
    "sg:postcode":"8552",
    "wof:name":"Breda David",
    "wof:placetype":"venue"
},
  "geometry": {"coordinates":[3.3989980221,50.7683372498],"type":"Point"}
}