{
  "type": "Feature",
  "properties": {
    "iso:country":"BE",
    "sg:address":"Pulse Steenweg 1",
    "sg:city":"Grobbendonk",
    "sg:classifiers":[
        {
            "category":"Bars & Pubs",
            "subcategory":"Nightclub",
            "type":"Food & Drink"
        }
    ],
    "sg:phone":"+32 14 51 43 53",
    "sg:postcode":"2280",
    "sg:province":"Antwerpen",
    "sg:tags":[
        "nachtclubs",
        "dancing"
    ],
    "wof:name":"Cap 3000",
    "wof:placetype":"venue"
},
  "geometry": {"coordinates":[4.7185359001,51.1952209473],"type":"Point"}
}