{
  "type": "Feature",
  "properties": {
    "addr:full":"Hoetsel 32 Zomergem Oost-Vlaanderen 9930",
    "addr:housenumber":"32",
    "addr:postcode":"9930",
    "addr:street":"Hoetsel",
    "iso:country":"BE",
    "sg:address":"Hoetsel 32",
    "sg:city":"Zomergem",
    "sg:classifiers":[
        {
            "category":"Building & Trades",
            "subcategory":"Landscaping Services",
            "type":"Services"
        }
    ],
    "sg:phone":"+32 9 370 82 90",
    "sg:postcode":"9930",
    "sg:province":"Oost-Vlaanderen",
    "sg:tags":[
        "gardening",
        "garden",
        "maintenance"
    ],
    "wof:name":"Pieters S",
    "wof:placetype":"venue"
},
  "geometry": {"coordinates":[3.5272789001,51.1119537354],"type":"Point"}
}