{
  "type": "Feature",
  "properties": {
    "addr:full":"Ruitersdreef 63 Waregem West-Vlaanderen 8790",
    "addr:housenumber":"63",
    "addr:postcode":"8790",
    "addr:street":"Ruitersdreef",
    "iso:country":"BE",
    "sg:address":"Ruitersdreef 63",
    "sg:city":"Waregem",
    "sg:classifiers":[
        {
            "category":"Professional",
            "subcategory":"Accounting & Tax Preparation",
            "type":"Services"
        }
    ],
    "sg:phone":"+32 56 60 43 67",
    "sg:postcode":"8790",
    "sg:province":"West-Vlaanderen",
    "sg:tags":[
        "accountant"
    ],
    "wof:name":"Colpaert Frans & Co Vof",
    "wof:placetype":"venue"
},
  "geometry": {"coordinates":[3.4477350712,50.878238678],"type":"Point"}
}