{
  "type": "Feature",
  "properties": {
    "iso:country":"BE",
    "sg:address":"Botermarkt 17",
    "sg:city":"Hasselt",
    "sg:classifiers":[
        {
            "category":"Shopping",
            "subcategory":"Clothing, Apparel, & Fashions",
            "type":"Retail Goods"
        }
    ],
    "sg:phone":"+32 11 21 04 86",
    "sg:postcode":"3500",
    "sg:province":"Limburg",
    "sg:tags":[
        "clothing",
        "-",
        "gentleman"
    ],
    "wof:name":"State Of Art Shop Hasselt",
    "wof:placetype":"venue"
},
  "geometry": {"coordinates":[5.3389849663,50.9304046631],"type":"Point"}
}