{
  "type": "Feature",
  "properties": {
    "iso:country":"BE",
    "sg:address":"Rue De Luttre 121",
    "sg:city":"Courcelles",
    "sg:classifiers":[
        {
            "category":"Fast Food",
            "type":"Food & Drink"
        }
    ],
    "sg:phone":"+32 71 84 04 04",
    "sg:postcode":"6181",
    "sg:province":"Hainaut",
    "sg:tags":[
        "\u00c0",
        "emporter",
        "restaurants"
    ],
    "wof:name":"Friterie Michel Snack",
    "wof:placetype":"venue"
},
  "geometry": {"coordinates":[4.3373432159,50.4911422729],"type":"Point"}
}