{
  "type": "Feature",
  "properties": {
    "iso:country":"BE",
    "sg:address":"Rue Armand Staquet 36",
    "sg:city":"Fleurus (saint-amand)",
    "sg:classifiers":[
        {
            "category":"Personal",
            "subcategory":"Nail Salon",
            "type":"Services"
        }
    ],
    "sg:phone":"+32 71 81 22 03",
    "sg:postcode":"6221",
    "sg:province":"Hainaut",
    "sg:tags":[
        "pedicure"
    ],
    "wof:name":"Moratti",
    "wof:placetype":"venue"
},
  "geometry": {"coordinates":[4.5451278687,50.5142593384],"type":"Point"}
}