{
  "type": "Feature",
  "properties": {
    "addr:full":"Breendonkstraat 211-248 Willebroek Antwerpen 2830",
    "addr:housenumber":"211-248",
    "addr:postcode":"2830",
    "addr:street":"Breendonkstraat",
    "iso:country":"BE",
    "sg:address":"Breendonkstraat 211-248",
    "sg:city":"Willebroek",
    "sg:classifiers":[
        {
            "category":"Sports & Exercise",
            "subcategory":"Swimming Pool",
            "type":"Entertainment"
        }
    ],
    "sg:postcode":"2830",
    "sg:province":"Antwerpen",
    "sg:tags":[
        "tank",
        "septic"
    ],
    "wof:name":"Lathouwers",
    "wof:placetype":"venue"
},
  "geometry": {"coordinates":[4.3432621956,51.0484352112],"type":"Point"}
}