{
  "type": "Feature",
  "properties": {
    "addr:full":"Eigenaarsstraat 13 Ravels Antwerpen 2380",
    "addr:housenumber":"13",
    "addr:postcode":"2380",
    "addr:street":"Eigenaarsstraat",
    "iso:country":"BE",
    "sg:address":"Eigenaarsstraat 13",
    "sg:city":"Ravels",
    "sg:classifiers":[
        {
            "category":"Arena",
            "subcategory":"Sports Club",
            "type":"Entertainment"
        }
    ],
    "sg:phone":"+32 14 65 56 10",
    "sg:postcode":"2380",
    "sg:province":"Antwerpen",
    "sg:tags":[
        "de"
    ],
    "wof:name":"Aikikai Ravels",
    "wof:placetype":"venue"
},
  "geometry": {"coordinates":[4.9857239723,51.3685684204],"type":"Point"}
}