{
  "type": "Feature",
  "properties": {
    "addr:full":"Avenue De La Petite Cense 17a Rixensart Brabant Wallon 1331",
    "addr:housenumber":"17a",
    "addr:postcode":"1331",
    "addr:street":"Avenue De La Petite Cense;Wallon",
    "iso:country":"BE",
    "sg:address":"Avenue De La Petite Cense 17a",
    "sg:city":"Rixensart",
    "sg:orig_category":"Koerierbedrijven",
    "sg:phone":"+32 2 653 39 16",
    "sg:postcode":"1331",
    "sg:province":"Brabant Wallon",
    "wof:name":"Transport Blue Line",
    "wof:placetype":"venue"
},
  "geometry": {"coordinates":[4.5378098488,50.7319068909],"type":"Point"}
}