{
  "type": "Feature",
  "properties": {
    "addr:full":"Houtenkruisdam 11 Kruibeke Oost-Vlaanderen 9150",
    "addr:housenumber":"11",
    "addr:postcode":"9150",
    "addr:street":"Houtenkruisdam",
    "iso:country":"BE",
    "sg:address":"Houtenkruisdam 11",
    "sg:city":"Kruibeke",
    "sg:orig_category":"Enregistrements sonores",
    "sg:phone":"+32 3 774 31 71",
    "sg:postcode":"9150",
    "sg:province":"Oost-Vlaanderen",
    "wof:name":"Rhythmist Productions",
    "wof:placetype":"venue"
},
  "geometry": {"coordinates":[4.3029828072,51.1553878784],"type":"Point"}
}