{
  "type": "Feature",
  "properties": {
    "iso:country":"BE",
    "sg:address":"Brugmannlaan 4",
    "sg:city":"Sint-gillis/saint-gilles",
    "sg:classifiers":[
        {
            "category":"Fast Food",
            "type":"Food & Drink"
        }
    ],
    "sg:phone":"+32 2 347 19 48",
    "sg:postcode":"1060",
    "sg:province":"Bruxelles-Capitale",
    "sg:tags":[
        "meeneem",
        "restaurant"
    ],
    "wof:name":"Fleurs D'asie",
    "wof:placetype":"venue"
},
  "geometry": {"coordinates":[4.3537888527,50.8224258423],"type":"Point"}
}