{
  "type": "Feature",
  "properties": {
    "iso:country":"BE",
    "sg:address":"Rue De Don\u00e9a 6",
    "sg:city":"Embourg",
    "sg:classifiers":[
        {
            "category":"Building & Trades",
            "subcategory":"Construction",
            "type":"Services"
        }
    ],
    "sg:phone":"+32 4 366 13 29",
    "sg:postcode":"4053",
    "sg:province":"Li\u00e8ge",
    "sg:tags":[
        "pattern",
        "foundry"
    ],
    "wof:name":"Modelage Du Nord Sprl",
    "wof:placetype":"venue"
},
  "geometry": {"coordinates":[5.6051030159,50.59141922],"type":"Point"}
}