{
  "type": "Feature",
  "properties": {
    "addr:full":"Liersebaan 11 Zandhoven Antwerpen 2240",
    "addr:housenumber":"11",
    "addr:postcode":"2240",
    "addr:street":"Liersebaan",
    "iso:country":"BE",
    "sg:address":"Liersebaan 11",
    "sg:city":"Zandhoven",
    "sg:classifiers":[
        {
            "category":"Cafe",
            "type":"Food & Drink"
        }
    ],
    "sg:phone":"+32 3 484 61 67",
    "sg:postcode":"2240",
    "sg:province":"Antwerpen",
    "sg:tags":[
        "snack-bars"
    ],
    "wof:name":"Broodtrommel (de)",
    "wof:placetype":"venue"
},
  "geometry": {"coordinates":[4.6591901779,51.2147636414],"type":"Point"}
}