{
  "type": "Feature",
  "properties": {
    "iso:country":"BE",
    "sg:address":"Stationsstraat 106",
    "sg:city":"Nazareth",
    "sg:orig_category":"Installatie van houten of kunststof schrijnwerk",
    "sg:phone":"+32 9 385 71 13",
    "sg:postcode":"9810",
    "sg:province":"Oost-Vlaanderen",
    "wof:name":"Hilaire De Sutter",
    "wof:placetype":"venue"
},
  "geometry": {"coordinates":[3.6309781075,50.9597854614],"type":"Point"}
}