{
  "type": "Feature",
  "properties": {
    "addr:full":"Hekkerstraat 46 Wetteren Oost-Vlaanderen 9230",
    "addr:housenumber":"46",
    "addr:postcode":"9230",
    "addr:street":"Hekkerstraat",
    "iso:country":"BE",
    "sg:address":"Hekkerstraat 46",
    "sg:city":"Wetteren",
    "sg:orig_category":"Newspapers, magazines, periodicals - Distribution",
    "sg:phone":"+32 9 369 29 27",
    "sg:postcode":"9230",
    "sg:province":"Oost-Vlaanderen",
    "wof:name":"Nissens H",
    "wof:placetype":"venue"
},
  "geometry": {"coordinates":[3.8869490623,51.0050506592],"type":"Point"}
}