{
  "type": "Feature",
  "properties": {
    "iso:country":"BE",
    "sg:address":"Rue Labie 1",
    "sg:city":"Eghezee",
    "sg:orig_category":"SMEEDWERK, METAALBEWERKING AND POEDERMETALLURGIE",
    "sg:phone":"+32 81 51 18 93",
    "sg:postcode":"5310",
    "sg:province":"Namur",
    "wof:name":"Jacquemin L.",
    "wof:placetype":"venue"
},
  "geometry": {"coordinates":[4.9090051651,50.561958313],"type":"Point"}
}