{
  "type": "Feature",
  "properties": {
    "iso:country":"BE",
    "sg:address":"Six-planes 29",
    "sg:city":"Bievre",
    "sg:orig_category":"Eleveurs de bovins",
    "sg:phone":"+32 61 50 02 90",
    "sg:postcode":"5555",
    "sg:province":"Namur",
    "wof:name":"Jean Leonet",
    "wof:placetype":"venue"
},
  "geometry": {"coordinates":[4.9711680412,49.8813476562],"type":"Point"}
}