{
  "type": "Feature",
  "properties": {
    "iso:country":"BE",
    "sg:address":"Grijspeerdstraat 30",
    "sg:city":"Hooglede",
    "sg:orig_category":"Varkenskwekers",
    "sg:phone":"+32 51 72 25 16",
    "sg:postcode":"8830",
    "sg:province":"West-Vlaanderen",
    "wof:name":"Roger Demare",
    "wof:placetype":"venue"
},
  "geometry": {"coordinates":[3.0906879902,51.0042572021],"type":"Point"}
}