{
  "type": "Feature",
  "properties": {
    "iso:country":"BE",
    "sg:address":"Rue Du Pr\u00c9vot 119",
    "sg:city":"Elsene/ixelles",
    "sg:orig_category":"Gestion de portefeuilles and fortunes, conseils en placements",
    "sg:phone":"+32 2 346 35 76",
    "sg:postcode":"1050",
    "sg:province":"Bruxelles-Capitale",
    "wof:name":"Pozzi P",
    "wof:placetype":"venue"
},
  "geometry": {"coordinates":[4.3617510796,50.8205337524],"type":"Point"}
}