{
  "type": "Feature",
  "properties": {
    "addr:full":"Tenberg 81 Ninove (meerbeke) Oost-Vlaanderen 9402",
    "addr:housenumber":"81",
    "addr:postcode":"9402",
    "addr:street":"Tenberg",
    "iso:country":"BE",
    "sg:address":"Tenberg 81",
    "sg:city":"Ninove (meerbeke)",
    "sg:classifiers":[
        {
            "category":"Ice Cream",
            "type":"Food & Drink"
        }
    ],
    "sg:phone":"+32 54 32 39 79",
    "sg:postcode":"9402",
    "sg:province":"Oost-Vlaanderen",
    "wof:name":"Steenhout R",
    "wof:placetype":"venue"
},
  "geometry": {"coordinates":[4.054599762,50.8210258484],"type":"Point"}
}