{
  "type": "Feature",
  "properties": {
    "iso:country":"BE",
    "sg:address":"Rue Du Fourneau 2",
    "sg:city":"Couvin",
    "sg:orig_category":"Eleveurs de bovins",
    "sg:phone":"+32 60 34 49 60",
    "sg:postcode":"5660",
    "sg:province":"Namur",
    "wof:name":"Jules Andre",
    "wof:placetype":"venue"
},
  "geometry": {"coordinates":[4.421462059,50.0347099304],"type":"Point"}
}