{
  "type": "Feature",
  "properties": {
    "addr:full":"Avenue Paul Pastur 39-45-49 Charleroi Hainaut 6001",
    "addr:postcode":"39-45-49;6001",
    "addr:street":"Avenue Paul Pastur;Hainaut",
    "iso:country":"BE",
    "sg:address":"Avenue Paul Pastur 39-45-49",
    "sg:city":"Charleroi",
    "sg:orig_category":"V\u00e9hicules automobiles",
    "sg:phone":"+32 71 36 51 59",
    "sg:postcode":"6001",
    "sg:province":"Hainaut",
    "wof:name":"Tutto-sportcars",
    "wof:placetype":"venue"
},
  "geometry": {"coordinates":[4.4448251724,50.3973655701],"type":"Point"}
}