{
  "type": "Feature",
  "properties": {
    "iso:country":"BE",
    "sg:address":"Avenue Winston Churchill 104",
    "sg:city":"Bruxelles (uccle)",
    "sg:classifiers":[
        {
            "category":"Insurance",
            "subcategory":"Insurance Agent",
            "type":"Services"
        }
    ],
    "sg:phone":"+32 2 340 16 00",
    "sg:postcode":"1180",
    "sg:province":"Bruxelles-Capitale",
    "sg:tags":[
        "broker"
    ],
    "wof:name":"Gar\u00e7on-m.l.d.",
    "wof:placetype":"venue"
},
  "geometry": {"coordinates":[4.352930069,50.8123016357],"type":"Point"}
}