{
  "type": "Feature",
  "properties": {
    "iso:country":"BE",
    "sg:address":"Eugene Flageyplein 22",
    "sg:city":"Elsene/ixelles",
    "sg:orig_category":"Kapsalons",
    "sg:phone":"+32 2 648 62 89",
    "sg:postcode":"1050",
    "sg:province":"Bruxelles-Capitale",
    "wof:name":"Coiffure Lotus",
    "wof:placetype":"venue"
},
  "geometry": {"coordinates":[4.3735141754,50.8278312683],"type":"Point"}
}