{
  "type": "Feature",
  "properties": {
    "iso:country":"BE",
    "sg:address":"Awan Fanson 40",
    "sg:city":"Aywaille",
    "sg:classifiers":[
        {
            "category":"Banks & Credit Unions",
            "subcategory":"Investment Brokerage",
            "type":"Services"
        }
    ],
    "sg:phone":"+32 4 384 71 72",
    "sg:postcode":"4920",
    "sg:province":"Li\u00e8ge",
    "sg:tags":[
        "fence"
    ],
    "wof:name":"Van Bogget Michel",
    "wof:placetype":"venue"
},
  "geometry": {"coordinates":[5.629488945,50.4524307251],"type":"Point"}
}