{
  "type": "Feature",
  "properties": {
    "addr:full":"Turnhoutsebaan 286bd Schilde Antwerpen 2970",
    "addr:housenumber":"286bd",
    "addr:postcode":"2970",
    "addr:street":"Turnhoutsebaan",
    "iso:country":"BE",
    "sg:address":"Turnhoutsebaan 286bd",
    "sg:city":"Schilde",
    "sg:classifiers":[
        {
            "category":"Shopping",
            "subcategory":"Clothing, Apparel, & Fashions",
            "type":"Retail Goods"
        }
    ],
    "sg:phone":"+32 3 383 27 79",
    "sg:postcode":"2970",
    "sg:province":"Antwerpen",
    "sg:tags":[
        "lingerie",
        "sous-v\u00eatements"
    ],
    "wof:name":"Huis Pastel",
    "wof:placetype":"venue"
},
  "geometry": {"coordinates":[4.5822248459,51.2402610779],"type":"Point"}
}