{
  "type": "Feature",
  "properties": {
    "iso:country":"BE",
    "sg:address":"Rue D'udange 31",
    "sg:city":"Saint-leger",
    "sg:orig_category":"Installatie van houten of kunststof schrijnwerk",
    "sg:phone":"+32 63 22 21 99",
    "sg:postcode":"6747",
    "sg:province":"Luxembourg",
    "wof:name":"Ch\u00c2ssis Confort Lux",
    "wof:placetype":"venue"
},
  "geometry": {"coordinates":[5.7240281105,49.6187438965],"type":"Point"}
}