{
  "type": "Feature",
  "properties": {
    "iso:country":"BE",
    "sg:address":"Kiliaanstraat 75",
    "sg:city":"Duffel",
    "sg:orig_category":"V\u00eatements. V\u00eatements pour b\u00e9b\u00e9s and enfants",
    "sg:phone":"+32 15 31 97 38",
    "sg:postcode":"2570",
    "sg:province":"Antwerpen",
    "wof:name":"Tinta",
    "wof:placetype":"venue"
},
  "geometry": {"coordinates":[4.501540184,51.0951385498],"type":"Point"}
}