{
  "type": "Feature",
  "properties": {
    "addr:full":"Koerselsebaan 26 Heusden-zolder (heusden) Limburg 3550",
    "addr:housenumber":"26",
    "addr:postcode":"3550",
    "addr:street":"Koerselsebaan",
    "iso:country":"BE",
    "sg:address":"Koerselsebaan 26",
    "sg:city":"Heusden-zolder (heusden)",
    "sg:orig_category":"Newspapers, magazines, periodicals - Distribution",
    "sg:phone":"+32 11 42 33 08",
    "sg:postcode":"3550",
    "sg:province":"Limburg",
    "wof:name":"Punteke ('t)",
    "wof:placetype":"venue"
},
  "geometry": {"coordinates":[5.2820281982,51.03490448],"type":"Point"}
}