{
  "type": "Feature",
  "properties": {
    "addr:full":"Rue Bovesse 45 Aubange (athus) Luxembourg 6791",
    "addr:housenumber":"45",
    "addr:postcode":"6791",
    "addr:street":"Rue Bovesse",
    "iso:country":"BE",
    "sg:address":"Rue Bovesse 45",
    "sg:city":"Aubange (athus)",
    "sg:classifiers":[
        {
            "category":"Real Estate",
            "subcategory":"Surveying",
            "type":"Services"
        }
    ],
    "sg:phone":"+32 63 38 98 60",
    "sg:postcode":"6791",
    "sg:province":"Luxembourg",
    "sg:tags":[
        "surveyor",
        "land"
    ],
    "wof:name":"Boucq R",
    "wof:placetype":"venue"
},
  "geometry": {"coordinates":[5.8368301392,49.5627288818],"type":"Point"}
}