{
  "type": "Feature",
  "properties": {
    "addr:full":"Rue Joseph-lamotte 9 Rochefort Namur 5580",
    "addr:housenumber":"9",
    "addr:postcode":"5580",
    "addr:street":"Rue Joseph-Lamotte",
    "iso:country":"BE",
    "sg:address":"Rue Joseph-lamotte 9",
    "sg:city":"Rochefort",
    "sg:orig_category":"Epiceries",
    "sg:phone":"+32 84 37 72 31",
    "sg:postcode":"5580",
    "sg:province":"Namur",
    "wof:name":"Spar",
    "wof:placetype":"venue"
},
  "geometry": {"coordinates":[5.1864151955,50.1259994507],"type":"Point"}
}