{
  "type": "Feature",
  "properties": {
    "iso:country":"BE",
    "sg:address":"Rue Fraischamps 157",
    "sg:city":"Li\u00e8ge 1 (grivegn\u00e9e)",
    "sg:classifiers":[
        {
            "category":"Retail",
            "subcategory":"Animal Services",
            "type":"Services"
        }
    ],
    "sg:phone":"+32 4 344 58 59",
    "sg:postcode":"4030",
    "sg:province":"Li\u00e8ge",
    "sg:tags":[
        "grooming",
        "-",
        "dog"
    ],
    "wof:name":"Tobby Toutou",
    "wof:placetype":"venue"
},
  "geometry": {"coordinates":[5.6055660248,50.6295394897],"type":"Point"}
}