{
  "type": "Feature",
  "properties": {
    "addr:full":"Chauss\u00c9e De L'ourthe 8 Marche-en-famenne Luxembourg 6900",
    "addr:housenumber":"8",
    "addr:postcode":"6900",
    "addr:street":"Chausse\u0301E De L'Ourthe",
    "iso:country":"BE",
    "sg:address":"Chauss\u00c9e De L'ourthe 8",
    "sg:city":"Marche-en-famenne",
    "sg:orig_category":"Boucheries",
    "sg:phone":"+32 84 31 67 41",
    "sg:postcode":"6900",
    "sg:province":"Luxembourg",
    "wof:name":"Gaston Seron",
    "wof:placetype":"venue"
},
  "geometry": {"coordinates":[5.3442978859,50.229839325],"type":"Point"}
}