{
  "type": "Feature",
  "properties": {
    "iso:country":"BE",
    "sg:address":"Rue G\u00c9n\u00c9ral Freyberg 11bc",
    "sg:city":"Lessines",
    "sg:orig_category":"Imprimeries and copyshops",
    "sg:phone":"+32 68 33 34 13",
    "sg:postcode":"7860",
    "sg:province":"Hainaut",
    "wof:name":"Guy Van Nieuwenhove",
    "wof:placetype":"venue"
},
  "geometry": {"coordinates":[3.8335990906,50.7118988037],"type":"Point"}
}