{
  "type": "Feature",
  "properties": {
    "iso:country":"BE",
    "sg:address":"Hertenlaan 36",
    "sg:city":"Beveren",
    "sg:orig_category":"Elektrische installaties voor woningen",
    "sg:phone":"+32 3 775 76 24",
    "sg:postcode":"9120",
    "sg:province":"Oost-Vlaanderen",
    "wof:name":"Jan Beullens",
    "wof:placetype":"venue"
},
  "geometry": {"coordinates":[4.2769598961,51.229309082],"type":"Point"}
}