{
  "type": "Feature",
  "properties": {
    "addr:full":"Rue De Profondsart 15 Ottignies-louvain-la-neuve (limelette) Brabant Wallon 1342",
    "addr:housenumber":"15",
    "addr:postcode":"1342",
    "addr:street":"Rue De Profondsart",
    "iso:country":"BE",
    "sg:address":"Rue De Profondsart 15",
    "sg:city":"Ottignies-louvain-la-neuve (limelette)",
    "sg:classifiers":[
        {
            "category":"Retail",
            "subcategory":"Auto Repair",
            "type":"Services"
        }
    ],
    "sg:phone":"+32 10 41 20 02",
    "sg:postcode":"1342",
    "sg:province":"Brabant Wallon",
    "sg:tags":[
        "breakdown",
        "automobile",
        "-",
        "recovery"
    ],
    "wof:name":"Droulans Bernard",
    "wof:placetype":"venue"
},
  "geometry": {"coordinates":[4.5465512276,50.6904983521],"type":"Point"}
}