{
  "type": "Feature",
  "properties": {
    "addr:full":"Schildekensstraat 51 Lede Oost-Vlaanderen 9340",
    "addr:housenumber":"51",
    "addr:postcode":"9340",
    "addr:street":"Schildekensstraat",
    "iso:country":"BE",
    "sg:address":"Schildekensstraat 51",
    "sg:city":"Lede",
    "sg:orig_category":"Gespecialiseerde niet-residenti\u00eble bouw",
    "sg:phone":"+32 9 366 27 90",
    "sg:postcode":"9340",
    "sg:province":"Oost-Vlaanderen",
    "wof:name":"Dirk Stroobant",
    "wof:placetype":"venue"
},
  "geometry": {"coordinates":[3.9343619347,50.9664764404],"type":"Point"}
}