{
  "type": "Feature",
  "properties": {
    "iso:country":"BE",
    "sg:address":"Place De B\u00c2latre 117",
    "sg:city":"Jemeppe-sur-sambre",
    "sg:orig_category":"Traitement and rev\u00eatement des m\u00e9taux",
    "sg:phone":"+32 81 63 48 67",
    "sg:postcode":"5190",
    "sg:province":"Namur",
    "wof:name":"Ledieu",
    "wof:placetype":"venue"
},
  "geometry": {"coordinates":[4.6703448296,50.4645042419],"type":"Point"}
}