{
  "type": "Feature",
  "properties": {
    "iso:country":"BE",
    "sg:address":"Rue Haute 26",
    "sg:city":"Wavre",
    "sg:orig_category":"Dameskledingzaken",
    "sg:phone":"+32 10 24 26 52",
    "sg:postcode":"1300",
    "sg:province":"Brabant Wallon",
    "wof:name":"Mony",
    "wof:placetype":"venue"
},
  "geometry": {"coordinates":[4.6092309952,50.7163505554],"type":"Point"}
}