{
  "type": "Feature",
  "properties": {
    "addr:full":"Nieuwe Kerkstraat 4 Nevele Oost-Vlaanderen 9850",
    "addr:housenumber":"4",
    "addr:postcode":"9850",
    "addr:street":"Nieuwe Kerkstraat",
    "iso:country":"BE",
    "sg:address":"Nieuwe Kerkstraat 4",
    "sg:city":"Nevele",
    "sg:orig_category":"Producteurs de fruits. Eleveurs and marchands de porcs",
    "sg:phone":"+32 9 371 81 23",
    "sg:postcode":"9850",
    "sg:province":"Oost-Vlaanderen",
    "wof:name":"Daniel Vlaemynck",
    "wof:placetype":"venue"
},
  "geometry": {"coordinates":[3.5732479095,51.05651474],"type":"Point"}
}