{
  "type": "Feature",
  "properties": {
    "iso:country":"BE",
    "sg:address":"Av. Evariste De Meersman 70",
    "sg:city":"Sint-agatha-berchem/berchem-sainte-agathe",
    "sg:classifiers":[
        {
            "category":"Restaurant",
            "type":"Food & Drink"
        }
    ],
    "sg:phone":"+32 2 465 39 75",
    "sg:postcode":"1082",
    "sg:province":"Bruxelles-Capitale",
    "sg:tags":[
        "caf\u00e9s"
    ],
    "wof:name":"Taverne Wutsburgh",
    "wof:placetype":"venue"
},
  "geometry": {"coordinates":[4.3020849228,50.8594017029],"type":"Point"}
}