{
  "type": "Feature",
  "properties": {
    "addr:full":"Rue Berckmans 83 Sint-gillis/saint-gilles Bruxelles-Capitale 1060",
    "addr:housenumber":"83",
    "addr:postcode":"1060",
    "addr:street":"Rue Berckmans",
    "iso:country":"BE",
    "sg:address":"Rue Berckmans 83",
    "sg:city":"Sint-gillis/saint-gilles",
    "sg:classifiers":[
        {
            "category":"Home & Garden",
            "subcategory":"Hardware",
            "type":"Retail Goods"
        }
    ],
    "sg:phone":"+32 2 534 40 80",
    "sg:postcode":"1060",
    "sg:province":"Bruxelles-Capitale",
    "sg:tags":[
        "quincailleries",
        "bois",
        "gr"
    ],
    "wof:name":"Timber Trading & Consult.",
    "wof:placetype":"venue"
},
  "geometry": {"coordinates":[4.3530402184,50.8320999146],"type":"Point"}
}