{
  "type": "Feature",
  "properties": {
    "addr:full":"Rue Albert Thomas 92 Dison Li\u00e8ge 4821",
    "addr:housenumber":"92",
    "addr:postcode":"4821",
    "addr:street":"Rue Albert Thomas",
    "iso:country":"BE",
    "sg:address":"Rue Albert Thomas 92",
    "sg:city":"Dison",
    "sg:orig_category":"Mat\u00e9riel scientifique and technique Fab",
    "sg:phone":"+32 87 33 31 19",
    "sg:postcode":"4821",
    "sg:province":"Li\u00e8ge",
    "wof:name":"Ista",
    "wof:placetype":"venue"
},
  "geometry": {"coordinates":[5.8704037666,50.6007919312],"type":"Point"}
}