{
  "type": "Feature",
  "properties": {
    "addr:full":"Keizer Karellaan 86 Ganshoren Bruxelles-Capitale 1083",
    "addr:housenumber":"86",
    "addr:postcode":"1083",
    "addr:street":"Keizer Karellaan",
    "iso:country":"BE",
    "sg:address":"Keizer Karellaan 86",
    "sg:city":"Ganshoren",
    "sg:classifiers":[
        {
            "category":"Restaurant",
            "type":"Food & Drink"
        }
    ],
    "sg:phone":"+32 2 424 11 41",
    "sg:postcode":"1083",
    "sg:province":"Bruxelles-Capitale",
    "sg:tags":[
        "caf\u00e9s"
    ],
    "wof:name":"Taverne Les Divas",
    "wof:placetype":"venue"
},
  "geometry": {"coordinates":[4.3103661537,50.8689956665],"type":"Point"}
}