{
  "type": "Feature",
  "properties": {
    "iso:country":"BE",
    "sg:address":"Rue Du Pont De Pierres 26",
    "sg:city":"Court-saint-etienne",
    "sg:classifiers":[
        {
            "category":"Personal",
            "subcategory":"Beauty Salon",
            "type":"Services"
        }
    ],
    "sg:phone":"+32 10 61 49 29",
    "sg:postcode":"1490",
    "sg:province":"Brabant Wallon",
    "sg:tags":[
        "de",
        "coiffure"
    ],
    "wof:name":"Jean-marie Vennekens",
    "wof:placetype":"venue"
},
  "geometry": {"coordinates":[4.5558781624,50.6409492493],"type":"Point"}
}