{
  "type": "Feature",
  "properties": {
    "addr:full":"Zilverpand 24 Brugge West-Vlaanderen 8000",
    "addr:housenumber":"24",
    "addr:postcode":"8000",
    "addr:street":"Zilverpand",
    "iso:country":"BE",
    "sg:address":"Zilverpand 24",
    "sg:city":"Brugge",
    "sg:classifiers":[
        {
            "category":"Shopping",
            "subcategory":"Clothing, Apparel, & Fashions",
            "type":"Retail Goods"
        }
    ],
    "sg:phone":"+32 50 33 88 62",
    "sg:postcode":"8000",
    "sg:province":"West-Vlaanderen",
    "sg:tags":[
        "-",
        "clothing",
        "child"
    ],
    "wof:name":"Scoubidou Bvba",
    "wof:placetype":"venue"
},
  "geometry": {"coordinates":[3.2214679718,51.2072257996],"type":"Point"}
}