{
  "type": "Feature",
  "properties": {
    "iso:country":"BE",
    "sg:address":"Gasthuisvelden 15",
    "sg:city":"Sint-katelijne-waver",
    "sg:orig_category":"Reclamebureaus",
    "sg:phone":"+32 15 31 41 00",
    "sg:postcode":"2860",
    "sg:province":"Antwerpen",
    "wof:name":"Feremans",
    "wof:placetype":"venue"
},
  "geometry": {"coordinates":[4.5540289879,51.0693817139],"type":"Point"}
}