{
  "type": "Feature",
  "properties": {
    "iso:country":"BE",
    "sg:address":"Gistelsesteenweg 616",
    "sg:city":"Oostende",
    "sg:orig_category":"V\u00e9hicules automobiles",
    "sg:phone":"+32 59 26 81 94",
    "sg:postcode":"8400",
    "sg:province":"West-Vlaanderen",
    "wof:name":"Willy De Brauwer",
    "wof:placetype":"venue"
},
  "geometry": {"coordinates":[2.9356911182,51.2021255493],"type":"Point"}
}