{
  "type": "Feature",
  "properties": {
    "iso:country":"BE",
    "sg:address":"Neerhovenstraat 23",
    "sg:city":"Meeuwen-gruitrode (gruitrode)",
    "sg:classifiers":[
        {
            "category":"Health Services",
            "subcategory":"Health Practitioner",
            "type":"Services"
        }
    ],
    "sg:phone":"+32 89 85 49 68",
    "sg:postcode":"3670",
    "sg:province":"Limburg",
    "sg:tags":[
        "physiotherapist"
    ],
    "wof:name":"Vandewal Jean",
    "wof:placetype":"venue"
},
  "geometry": {"coordinates":[5.5205497742,51.0963516235],"type":"Point"}
}