{
  "type": "Feature",
  "properties": {
    "iso:country":"BE",
    "sg:address":"Rue Rodenbach 48",
    "sg:city":"Bruxelles (forest)",
    "sg:classifiers":[
        {
            "category":"Building & Trades",
            "subcategory":"Construction",
            "type":"Services"
        }
    ],
    "sg:phone":"+32 2 344 42 23",
    "sg:postcode":"1190",
    "sg:province":"Bruxelles-Capitale",
    "sg:tags":[
        "industrial",
        "design"
    ],
    "wof:name":"Atelier De Cr\u00e9ation",
    "wof:placetype":"venue"
},
  "geometry": {"coordinates":[4.3444299698,50.8186378479],"type":"Point"}
}