{
  "type": "Feature",
  "properties": {
    "addr:full":"Rue Du Roi Albert 78 Colfontaine Hainaut 7340",
    "addr:housenumber":"78",
    "addr:postcode":"7340",
    "addr:street":"Rue Du Roi Albert",
    "iso:country":"BE",
    "sg:address":"Rue Du Roi Albert 78",
    "sg:city":"Colfontaine",
    "sg:classifiers":[
        {
            "category":"Personal",
            "subcategory":"Beauty Salon",
            "type":"Services"
        }
    ],
    "sg:phone":"+32 65 51 24 95",
    "sg:postcode":"7340",
    "sg:province":"Hainaut",
    "sg:tags":[
        "de",
        "coiffure"
    ],
    "wof:name":"Rosalie Giusti",
    "wof:placetype":"venue"
},
  "geometry": {"coordinates":[3.8371379375,50.4069747925],"type":"Point"}
}