{
  "type": "Feature",
  "properties": {
    "iso:country":"BE",
    "sg:address":"Tervurenlaan 90",
    "sg:city":"Etterbeek/etterbeek",
    "sg:orig_category":"Reisbureaus",
    "sg:phone":"+32 2 735 52 64",
    "sg:postcode":"1040",
    "sg:province":"Bruxelles-Capitale",
    "wof:name":"Central Tourisme",
    "wof:placetype":"venue"
},
  "geometry": {"coordinates":[4.4044828415,50.8384246826],"type":"Point"}
}