{
  "type": "Feature",
  "properties": {
    "iso:country":"BE",
    "sg:address":"Ave Tamaris 2",
    "sg:city":"St. Jans",
    "sg:classifiers":[
        {
            "category":"Banks & Credit Unions",
            "subcategory":"Bank",
            "type":"Services"
        }
    ],
    "sg:phone":"+32 2 411 10 66",
    "sg:postcode":"1080",
    "sg:province":"Bruxelles-Capitale",
    "wof:name":"G\u00e9n\u00e9rale De Banque Sa",
    "wof:placetype":"venue"
},
  "geometry": {"coordinates":[5.8989601135,43.0887107849],"type":"Point"}
}