{
  "type": "Feature",
  "properties": {
    "iso:country":"BE",
    "sg:address":"Place L. D'andrimont 1",
    "sg:city":"Limbourg (grand)",
    "sg:orig_category":"Banques and organismes de cr\u00e9dit",
    "sg:phone":"+32 87 76 01 60",
    "sg:postcode":"4830",
    "sg:province":"Li\u00e8ge",
    "wof:name":"Bbl",
    "wof:placetype":"venue"
},
  "geometry": {"coordinates":[5.941904068,50.6199378967],"type":"Point"}
}