{
  "type": "Feature",
  "properties": {
    "addr:full":"Veldenstraat 14 Retie Antwerpen 2470",
    "addr:housenumber":"14",
    "addr:postcode":"2470",
    "addr:street":"Veldenstraat",
    "iso:country":"BE",
    "sg:address":"Veldenstraat 14",
    "sg:city":"Retie",
    "sg:classifiers":[
        {
            "category":"Recreation",
            "subcategory":"Amusement Park",
            "type":"Entertainment"
        }
    ],
    "sg:phone":"+32 14 37 27 27",
    "sg:postcode":"2470",
    "sg:province":"Antwerpen",
    "sg:tags":[
        "attraction",
        "-",
        "sale",
        "fair",
        "hiring"
    ],
    "wof:name":"Attractie Verhuur Chatho",
    "wof:placetype":"venue"
},
  "geometry": {"coordinates":[5.0784740448,51.2732887268],"type":"Point"}
}