{
  "type": "Feature",
  "properties": {
    "iso:country":"BE",
    "sg:address":"Burg 63b10",
    "sg:city":"Torhout",
    "sg:classifiers":[
        {
            "category":"Arena",
            "subcategory":"Sports Club",
            "type":"Entertainment"
        }
    ],
    "sg:phone":"+32 50 21 58 71",
    "sg:postcode":"8820",
    "sg:province":"West-Vlaanderen",
    "sg:tags":[
        "de"
    ],
    "wof:name":"W.t.c. De Thouroutnaere",
    "wof:placetype":"venue"
},
  "geometry": {"coordinates":[3.1016008854,51.0674285889],"type":"Point"}
}