{
  "type": "Feature",
  "properties": {
    "addr:full":"Bergenstraat 37 Zedelgem (veldegem) West-Vlaanderen 8210",
    "addr:housenumber":"37",
    "addr:postcode":"8210",
    "addr:street":"Bergenstraat",
    "iso:country":"BE",
    "sg:address":"Bergenstraat 37",
    "sg:city":"Zedelgem (veldegem)",
    "sg:classifiers":[
        {
            "category":"Retail",
            "subcategory":"Auto Repair",
            "type":"Services"
        }
    ],
    "sg:phone":"+32 50 27 81 21",
    "sg:postcode":"8210",
    "sg:province":"West-Vlaanderen",
    "sg:tags":[
        "garage"
    ],
    "wof:name":"Joly H & Zn",
    "wof:placetype":"venue"
},
  "geometry": {"coordinates":[3.1458399296,51.1376457214],"type":"Point"}
}