{
  "type": "Feature",
  "properties": {
    "addr:full":"Lindestraat 62 Berlare Oost-Vlaanderen 9290",
    "addr:housenumber":"62",
    "addr:postcode":"9290",
    "addr:street":"Lindestraat",
    "iso:country":"BE",
    "sg:address":"Lindestraat 62",
    "sg:city":"Berlare",
    "sg:orig_category":"Artsen and specialisten",
    "sg:phone":"+32 9 367 60 68",
    "sg:postcode":"9290",
    "sg:province":"Oost-Vlaanderen",
    "wof:name":"Mario Bastini",
    "wof:placetype":"venue"
},
  "geometry": {"coordinates":[4.005710125,51.0165214539],"type":"Point"}
}