{
  "type": "Feature",
  "properties": {
    "addr:full":"Burgemeester Vandenbogaerdelaan 38 Izegem West-Vlaanderen 8870",
    "addr:housenumber":"38",
    "addr:postcode":"8870",
    "addr:street":"Burgemeester Vandenbogaerdelaan",
    "iso:country":"BE",
    "sg:address":"Burgemeester Vandenbogaerdelaan 38",
    "sg:city":"Izegem",
    "sg:orig_category":"Non-Classified Establishments",
    "sg:phone":"+32 51 30 08 39",
    "sg:postcode":"8870",
    "sg:province":"West-Vlaanderen",
    "wof:name":"Isybel Bvba",
    "wof:placetype":"venue"
},
  "geometry": {"coordinates":[3.211081028,50.9147224426],"type":"Point"}
}