{
  "type": "Feature",
  "properties": {
    "addr:full":"Oudenaardsesteenweg 526 Erpe-mere (bambrugge) Oost-Vlaanderen 9420",
    "addr:housenumber":"526",
    "addr:postcode":"9420",
    "addr:street":"Oudenaardsesteenweg",
    "iso:country":"BE",
    "sg:address":"Oudenaardsesteenweg 526",
    "sg:city":"Erpe-mere (bambrugge)",
    "sg:classifiers":[
        {
            "category":"Health Services",
            "subcategory":"Dentist",
            "type":"Services"
        }
    ],
    "sg:phone":"+32 53 63 06 26",
    "sg:postcode":"9420",
    "sg:province":"Oost-Vlaanderen",
    "wof:name":"Genetello Joris",
    "wof:placetype":"venue"
},
  "geometry": {"coordinates":[3.9433600903,50.9210662842],"type":"Point"}
}