{
  "type": "Feature",
  "properties": {
    "iso:country":"BE",
    "sg:address":"Koningin Astridlaan 65",
    "sg:city":"Hasselt",
    "sg:classifiers":[
        {
            "category":"Health Services",
            "subcategory":"Hospital",
            "type":"Services"
        }
    ],
    "sg:phone":"+32 11 23 51 95",
    "sg:postcode":"3500",
    "sg:province":"Limburg",
    "wof:name":"Dagopvang Vzw Centrum Voor Activering En Arbeidszorg",
    "wof:placetype":"venue"
},
  "geometry": {"coordinates":[5.3298721313,50.9320220947],"type":"Point"}
}