{
  "type": "Feature",
  "properties": {
    "iso:country":"BE",
    "sg:address":"Mechelseweg 138",
    "sg:city":"Kapelle-op-den-bos",
    "sg:classifiers":[
        {
            "category":"Insurance",
            "subcategory":"Insurance Agent",
            "type":"Services"
        }
    ],
    "sg:phone":"+32 15 71 55 00",
    "sg:postcode":"1880",
    "sg:province":"Vlaams-Brabant",
    "sg:tags":[
        "broker"
    ],
    "wof:name":"Lamberts Peter Vof",
    "wof:placetype":"venue"
},
  "geometry": {"coordinates":[4.358148098,51.0126457214],"type":"Point"}
}