{
  "type": "Feature",
  "properties": {
    "iso:country":"BE",
    "sg:address":"Industrieweg 12",
    "sg:city":"Boom",
    "sg:classifiers":[
        {
            "category":"Banks & Credit Unions",
            "subcategory":"Bank",
            "type":"Services"
        }
    ],
    "sg:phone":"+32 3 844 25 00",
    "sg:postcode":"2850",
    "sg:province":"Antwerpen",
    "sg:tags":[
        "bag",
        "polyethylene",
        "carrier",
        "pe"
    ],
    "wof:name":"Flanders Plastics Nv",
    "wof:placetype":"venue"
},
  "geometry": {"coordinates":[4.3537101746,51.1001739502],"type":"Point"}
}