{
  "type": "Feature",
  "properties": {
    "iso:country":"BE",
    "sg:address":"Faubourg De Binche 24c",
    "sg:city":"Le Roeulx",
    "sg:classifiers":[
        {
            "category":"Food & Beverages",
            "subcategory":"Liquor & Beverages",
            "type":"Retail Goods"
        }
    ],
    "sg:phone":"+32 64 67 73 56",
    "sg:postcode":"7070",
    "sg:province":"Hainaut",
    "sg:tags":[
        "-",
        "spirit",
        "wine"
    ],
    "wof:name":"Marygnac",
    "wof:placetype":"venue"
},
  "geometry": {"coordinates":[4.1098017693,50.4984169006],"type":"Point"}
}