{
  "type": "Feature",
  "properties": {
    "addr:full":"Prins Albertstraat 36 Sint-niklaas Oost-Vlaanderen 9100",
    "addr:housenumber":"36",
    "addr:postcode":"9100",
    "addr:street":"Prins Albertstraat",
    "iso:country":"BE",
    "sg:address":"Prins Albertstraat 36",
    "sg:city":"Sint-niklaas",
    "sg:classifiers":[
        {
            "category":"Professional",
            "subcategory":"Lawyer & Legal Services",
            "type":"Services"
        }
    ],
    "sg:phone":"+32 3 776 78 65",
    "sg:postcode":"9100",
    "sg:province":"Oost-Vlaanderen",
    "wof:name":"De Smet Serge",
    "wof:placetype":"venue"
},
  "geometry": {"coordinates":[4.1440458298,51.169593811],"type":"Point"}
}