{
  "type": "Feature",
  "properties": {
    "addr:full":"Kattevennen 23 Genk Limburg 3600",
    "addr:housenumber":"23",
    "addr:postcode":"3600",
    "addr:street":"Kattevennen",
    "iso:country":"BE",
    "sg:address":"Kattevennen 23",
    "sg:city":"Genk",
    "sg:orig_category":"Location d'articles de sport, de sport nautique and de camping. Installations and terrains de sport ",
    "sg:phone":"+32 89 36 35 02",
    "sg:postcode":"3600",
    "sg:province":"Limburg",
    "wof:name":"Skiclub Kattevennen",
    "wof:placetype":"venue"
},
  "geometry": {"coordinates":[5.5337018967,50.9555549622],"type":"Point"}
}