{
  "type": "Feature",
  "properties": {
    "addr:full":"Elisabethlaan 348 Oostende West-Vlaanderen 8400",
    "addr:housenumber":"348",
    "addr:postcode":"8400",
    "addr:street":"Elisabethlaan",
    "iso:country":"BE",
    "sg:address":"Elisabethlaan 348",
    "sg:city":"Oostende",
    "sg:orig_category":"Secr\u00e9tariats. Composition and photogravure",
    "sg:phone":"+32 59 51 38 92",
    "sg:postcode":"8400",
    "sg:province":"West-Vlaanderen",
    "wof:name":"Steelandt",
    "wof:placetype":"venue"
},
  "geometry": {"coordinates":[2.9078500271,51.214466095],"type":"Point"}
}