{
  "type": "Feature",
  "properties": {
    "addr:full":"Rue Du Bois 27a Braine-le-comte Hainaut 7090",
    "addr:housenumber":"27a",
    "addr:postcode":"7090",
    "addr:street":"Rue Du Bois",
    "iso:country":"BE",
    "sg:address":"Rue Du Bois 27a",
    "sg:city":"Braine-le-comte",
    "sg:orig_category":"Procesbesturingssystemen Fab",
    "sg:phone":"+32 67 63 81 21",
    "sg:postcode":"7090",
    "sg:province":"Hainaut",
    "wof:name":"A.c.m. Prodesign",
    "wof:placetype":"venue"
},
  "geometry": {"coordinates":[4.1657857895,50.6015434265],"type":"Point"}
}