{
  "type": "Feature",
  "properties": {
    "addr:full":"Kanaalweg 89 Tessenderlo Limburg 3980",
    "addr:housenumber":"89",
    "addr:postcode":"3980",
    "addr:street":"Kanaalweg",
    "iso:country":"BE",
    "sg:address":"Kanaalweg 89",
    "sg:city":"Tessenderlo",
    "sg:classifiers":[
        {
            "category":"Manufacturing",
            "subcategory":"Building Materials",
            "type":"Manufacturing & Wholesale Goods"
        }
    ],
    "sg:phone":"+32 13 78 18 39",
    "sg:postcode":"3980",
    "sg:province":"Limburg",
    "sg:tags":[
        "boiler",
        "manufacturer"
    ],
    "wof:name":"Stijnen Alfons Bvba",
    "wof:placetype":"venue"
},
  "geometry": {"coordinates":[5.1669950485,51.076587677],"type":"Point"}
}