{
  "type": "Feature",
  "properties": {
    "addr:full":"Veurnestraat 61/63 De Panne West-Vlaanderen 8660",
    "addr:housenumber":"61 / 63",
    "addr:postcode":"8660",
    "addr:street":"Veurnestraat",
    "iso:country":"BE",
    "sg:address":"Veurnestraat 61/63",
    "sg:city":"De Panne",
    "sg:orig_category":"Royal Canin. Fruits and l\u00e9gumes Animaux domestiques and accessoires. Produits \u00e0 base de pommes de te",
    "sg:phone":"+32 58 41 16 55",
    "sg:postcode":"8660",
    "sg:province":"West-Vlaanderen",
    "wof:name":"Faunami",
    "wof:placetype":"venue"
},
  "geometry": {"coordinates":[2.5920341015,51.0956535339],"type":"Point"}
}