{
  "type": "Feature",
  "properties": {
    "iso:country":"BE",
    "sg:address":"Gaspeldoornlaan 22",
    "sg:city":"Brasschaat",
    "sg:classifiers":[
        {
            "category":"Building & Trades",
            "subcategory":"Electrical",
            "type":"Services"
        }
    ],
    "sg:phone":"+32 3 651 41 77",
    "sg:postcode":"2930",
    "sg:province":"Antwerpen",
    "sg:tags":[
        "industrial",
        "-",
        "electric",
        "contractor"
    ],
    "wof:name":"Bosep Nv",
    "wof:placetype":"venue"
},
  "geometry": {"coordinates":[4.5078749657,51.3039894104],"type":"Point"}
}