{
  "type": "Feature",
  "properties": {
    "addr:full":"Rue De L\u00b4enseignement 49ba Fontaine-l\u00b4ev\u00caque Hainaut 6140",
    "addr:housenumber":"49ba",
    "addr:postcode":"6140",
    "addr:street":"Rue De L\u00b4Enseignement;Hainaut",
    "iso:country":"BE",
    "sg:address":"Rue De L\u00b4enseignement 49ba",
    "sg:city":"Fontaine-l\u00b4ev\u00caque",
    "sg:orig_category":"Enseignement maternel and primaire",
    "sg:phone":"+32 71 52 36 20",
    "sg:postcode":"6140",
    "sg:province":"Hainaut",
    "wof:name":"E.f.c. Leo Collard",
    "wof:placetype":"venue"
},
  "geometry": {"coordinates":[4.3208971024,50.4097747803],"type":"Point"}
}