{
  "type": "Feature",
  "properties": {
    "addr:full":"Laagland 20 Beveren (kieldrecht) Oost-Vlaanderen 9130",
    "addr:housenumber":"20",
    "addr:postcode":"9130",
    "addr:street":"Laagland",
    "iso:country":"BE",
    "sg:address":"Laagland 20",
    "sg:city":"Beveren (kieldrecht)",
    "sg:classifiers":[
        {
            "category":"Shopping",
            "subcategory":"Crafts & Fabrics",
            "type":"Retail Goods"
        }
    ],
    "sg:phone":"+32 3 773 35 85",
    "sg:postcode":"9130",
    "sg:province":"Oost-Vlaanderen",
    "sg:tags":[
        "cloth",
        "cleaning"
    ],
    "wof:name":"Ha-ra\u00ae",
    "wof:placetype":"venue"
},
  "geometry": {"coordinates":[4.1806898117,51.2877807617],"type":"Point"}
}