{
  "type": "Feature",
  "properties": {
    "addr:full":"Schutterstraat 19 Arendonk Antwerpen 2370",
    "addr:housenumber":"19",
    "addr:postcode":"2370",
    "addr:street":"Schutterstraat",
    "iso:country":"BE",
    "sg:address":"Schutterstraat 19",
    "sg:city":"Arendonk",
    "sg:classifiers":[
        {
            "category":"Fast Food",
            "type":"Food & Drink"
        }
    ],
    "sg:phone":"+32 14 67 71 08",
    "sg:postcode":"2370",
    "sg:province":"Antwerpen",
    "sg:tags":[
        "fried",
        "stand",
        "potato"
    ],
    "wof:name":"Lekkerbek",
    "wof:placetype":"venue"
},
  "geometry": {"coordinates":[5.0795998573,51.324005127],"type":"Point"}
}