{
  "type": "Feature",
  "properties": {
    "addr:full":"Rijkmakerlaan 33 Essen Antwerpen 2910",
    "addr:housenumber":"33",
    "addr:postcode":"2910",
    "addr:street":"Rijkmakerlaan",
    "iso:country":"BE",
    "sg:address":"Rijkmakerlaan 33",
    "sg:city":"Essen",
    "sg:classifiers":[
        {
            "category":"Bakery",
            "type":"Food & Drink"
        }
    ],
    "sg:phone":"+32 3 667 31 18",
    "sg:postcode":"2910",
    "sg:province":"Antwerpen",
    "sg:tags":[
        "confectioner",
        "baker"
    ],
    "wof:name":"Van De Sanden - Van Hoeydonck",
    "wof:placetype":"venue"
},
  "geometry": {"coordinates":[4.5003218651,51.4472465515],"type":"Point"}
}