{
  "type": "Feature",
  "properties": {
    "iso:country":"BE",
    "sg:address":"Avergat 18",
    "sg:city":"Riemst",
    "sg:orig_category":"Schoonheidssalons",
    "sg:phone":"+32 12 45 26 78",
    "sg:postcode":"3770",
    "sg:province":"Limburg",
    "wof:name":"Louis Meex",
    "wof:placetype":"venue"
},
  "geometry": {"coordinates":[5.668774128,50.8091430664],"type":"Point"}
}