{
  "type": "Feature",
  "properties": {
    "addr:full":"Rue Du Lombard 71-73-75 Brussel/bruxelles Bruxelles-Capitale 1000",
    "addr:postcode":"71-73-75;/ bruxelles;1000",
    "addr:street":"Rue Du Lombard",
    "iso:country":"BE",
    "sg:address":"Rue Du Lombard 71-73-75",
    "sg:city":"Brussel/bruxelles",
    "sg:orig_category":"Location de v\u00eatements, chaussures and textiles. Articles de f\u00eate, farces and attrapes",
    "sg:phone":"+32 2 512 23 87",
    "sg:postcode":"1000",
    "sg:province":"Bruxelles-Capitale",
    "wof:name":"Picard-megafun",
    "wof:placetype":"venue"
},
  "geometry": {"coordinates":[4.3513898849,50.8584594727],"type":"Point"}
}