{
  "type": "Feature",
  "properties": {
    "iso:country":"BE",
    "sg:address":"Hoefstadstraat 95",
    "sg:city":"Genk",
    "sg:classifiers":[
        {
            "category":"Professional",
            "subcategory":"Computer Services",
            "type":"Services"
        }
    ],
    "sg:phone":"+32 89 24 06 10",
    "sg:postcode":"3600",
    "sg:province":"Limburg",
    "sg:tags":[
        "-",
        "processing",
        "data"
    ],
    "wof:name":"Vb System Bvba",
    "wof:placetype":"venue"
},
  "geometry": {"coordinates":[5.5056118965,50.9797706604],"type":"Point"}
}