{
  "type": "Feature",
  "properties": {
    "addr:full":"Aardenburgkalseide 331 Maldegem Oost-Vlaanderen 9990",
    "addr:housenumber":"331",
    "addr:postcode":"9990",
    "iso:country":"BE",
    "sg:address":"Aardenburgkalseide 331",
    "sg:city":"Maldegem",
    "sg:classifiers":[
        {
            "category":"Food & Beverages",
            "subcategory":"Meat & Fish",
            "type":"Retail Goods"
        }
    ],
    "sg:phone":"+32 50 71 10 24",
    "sg:postcode":"9990",
    "sg:province":"Oost-Vlaanderen",
    "sg:tags":[
        "-",
        "livestock"
    ],
    "wof:name":"De Sloovere",
    "wof:placetype":"venue"
},
  "geometry": {"coordinates":[3.4469730854,51.2270545959],"type":"Point"}
}