{
  "type": "Feature",
  "properties": {
    "iso:country":"BE",
    "sg:address":"Vredelaan 12",
    "sg:city":"Houthalen-helchteren (houthalen)",
    "sg:classifiers":[
        {
            "category":"Professional",
            "subcategory":"Lawyer & Legal Services",
            "type":"Services"
        }
    ],
    "sg:phone":"+32 11 81 13 03",
    "sg:postcode":"3530",
    "sg:province":"Limburg",
    "wof:name":"Moonen Hugo",
    "wof:placetype":"venue"
},
  "geometry": {"coordinates":[5.3727550507,51.0317001343],"type":"Point"}
}