{
  "type": "Feature",
  "properties": {
    "iso:country":"BE",
    "sg:address":"Sint-trudostraat 12",
    "sg:city":"Gingelom (buvingen)",
    "sg:classifiers":[
        {
            "category":"Building & Trades",
            "subcategory":"Construction",
            "type":"Services"
        }
    ],
    "sg:phone":"+32 11 88 46 38",
    "sg:postcode":"3891",
    "sg:province":"Limburg",
    "sg:tags":[
        "stucco",
        "contractor"
    ],
    "wof:name":"Bamps J",
    "wof:placetype":"venue"
},
  "geometry": {"coordinates":[5.1762452126,50.753162384],"type":"Point"}
}