{
  "type": "Feature",
  "properties": {
    "addr:full":"Klerkenstraat 104 Houthulst West-Vlaanderen 8650",
    "addr:housenumber":"104",
    "addr:postcode":"8650",
    "addr:street":"Klerkenstraat",
    "iso:country":"BE",
    "sg:address":"Klerkenstraat 104",
    "sg:city":"Houthulst",
    "sg:orig_category":"Services de Nettoyage and de D\u00e9sinfection",
    "sg:phone":"+32 51 50 51 69",
    "sg:postcode":"8650",
    "sg:province":"West-Vlaanderen",
    "wof:name":"Schoonmaakbedrijf Claude",
    "wof:placetype":"venue"
},
  "geometry": {"coordinates":[2.9370999336,50.9833984375],"type":"Point"}
}