{
  "type": "Feature",
  "properties": {
    "iso:country":"BE",
    "sg:address":"Rue Du Fonterbois 13",
    "sg:city":"Charleroi (mont-sur-marchienne)",
    "sg:classifiers":[
        {
            "category":"Health Services",
            "subcategory":"Health Practitioner",
            "type":"Services"
        }
    ],
    "sg:phone":"+32 71 43 50 61",
    "sg:postcode":"6032",
    "sg:province":"Hainaut",
    "sg:tags":[
        "physiotherapist"
    ],
    "wof:name":"Philippe Anne",
    "wof:placetype":"venue"
},
  "geometry": {"coordinates":[4.4123630524,50.3680686951],"type":"Point"}
}