{
  "type": "Feature",
  "properties": {
    "iso:country":"BE",
    "sg:address":"Rue Marie Joile 16",
    "sg:city":"Mons (havr\u00e9)",
    "sg:classifiers":[
        {
            "category":"Home & Garden",
            "subcategory":"Furniture",
            "type":"Retail Goods"
        }
    ],
    "sg:phone":"+32 65 40 04 00",
    "sg:postcode":"7021",
    "sg:province":"Hainaut",
    "sg:tags":[
        "-"
    ],
    "wof:name":"Guy Lange-import Garden",
    "wof:placetype":"venue"
},
  "geometry": {"coordinates":[4.0456829071,50.4640655518],"type":"Point"}
}