{
  "type": "Feature",
  "properties": {
    "addr:full":"Rue Antoine Andr\u00e9 46 Wavre (limal) Brabant Wallon 1300",
    "addr:housenumber":"46",
    "addr:postcode":"1300",
    "addr:street":"Rue Antoine Andre\u0301;Wallon",
    "iso:country":"BE",
    "sg:address":"Rue Antoine Andr\u00e9 46",
    "sg:city":"Wavre (limal)",
    "sg:classifiers":[
        {
            "category":"Autos & Motor Vehicles",
            "subcategory":"Auto Supplies",
            "type":"Retail Goods"
        }
    ],
    "sg:phone":"+32 10 41 52 64",
    "sg:postcode":"1300",
    "sg:province":"Brabant Wallon",
    "sg:tags":[
        "machine",
        "laundry",
        "-"
    ],
    "wof:name":"Siplet Sprl",
    "wof:placetype":"venue"
},
  "geometry": {"coordinates":[4.5872688293,50.6897354126],"type":"Point"}
}