{
  "type": "Feature",
  "properties": {
    "addr:full":"Dr\u00c8ve Des Alli\u00c9s 52 Thuin Hainaut 6530",
    "addr:housenumber":"52",
    "addr:postcode":"6530",
    "addr:street":"Dre\u0300Ve Des Allie\u0301S",
    "iso:country":"BE",
    "sg:address":"Dr\u00c8ve Des Alli\u00c9s 52",
    "sg:city":"Thuin",
    "sg:classifiers":[
        {
            "category":"Insurance",
            "subcategory":"Insurance Agent",
            "type":"Services"
        }
    ],
    "sg:phone":"+32 71 59 16 55",
    "sg:postcode":"6530",
    "sg:province":"Hainaut",
    "sg:tags":[
        "verzekeringsmakelaars",
        "expert"
    ],
    "wof:name":"Bur.d'affaires Huart J.m.",
    "wof:placetype":"venue"
},
  "geometry": {"coordinates":[4.3011608124,50.3399238586],"type":"Point"}
}