{
  "type": "Feature",
  "properties": {
    "addr:full":"Kleineveldstraat 114 Tienen Vlaams-Brabant 3300",
    "addr:housenumber":"114",
    "addr:postcode":"3300",
    "addr:street":"Kleineveldstraat",
    "iso:country":"BE",
    "sg:address":"Kleineveldstraat 114",
    "sg:city":"Tienen",
    "sg:orig_category":"Varkenskwekers",
    "sg:phone":"+32 16 81 34 32",
    "sg:postcode":"3300",
    "sg:province":"Vlaams-Brabant",
    "wof:name":"Jules Vanderveken",
    "wof:placetype":"venue"
},
  "geometry": {"coordinates":[4.930077076,50.8096694946],"type":"Point"}
}