{
  "type": "Feature",
  "properties": {
    "iso:country":"BE",
    "sg:address":"Avenue Du Fort-jaco 61",
    "sg:city":"Ukkel/uccle",
    "sg:classifiers":[
        {
            "category":"Cinema",
            "subcategory":"Movie Rental",
            "type":"Entertainment"
        }
    ],
    "sg:phone":"+32 2 375 06 20",
    "sg:postcode":"1180",
    "sg:province":"Bruxelles-Capitale",
    "sg:tags":[
        "de",
        "cassette",
        "location",
        "vid\u00e9o",
        "audio"
    ],
    "wof:name":"Cin\u00c9bank Vid\u00c9o 24h/24",
    "wof:placetype":"venue"
},
  "geometry": {"coordinates":[4.3783798218,50.7893371582],"type":"Point"}
}