{
  "type": "Feature",
  "properties": {
    "iso:country":"BE",
    "sg:address":"Habiemont 16",
    "sg:city":"Stoumont",
    "sg:orig_category":"Eleveurs de bovins",
    "sg:phone":"+32 86 43 30 37",
    "sg:postcode":"4987",
    "sg:province":"Li\u00e8ge",
    "wof:name":"Albert Bodson",
    "wof:placetype":"venue"
},
  "geometry": {"coordinates":[5.8098897934,50.4056663513],"type":"Point"}
}