{
  "type": "Feature",
  "properties": {
    "addr:full":"Staatsbaan 233 Kortemark (zarren-werken) West-Vlaanderen 8610",
    "addr:housenumber":"233",
    "addr:postcode":"8610",
    "addr:street":"Staatsbaan",
    "iso:country":"BE",
    "sg:address":"Staatsbaan 233",
    "sg:city":"Kortemark (zarren-werken)",
    "sg:classifiers":[
        {
            "category":"Wholesale",
            "subcategory":"Fruits & Vegetables",
            "type":"Manufacturing & Wholesale Goods"
        }
    ],
    "sg:phone":"+32 51 56 64 56",
    "sg:postcode":"8610",
    "sg:province":"West-Vlaanderen",
    "sg:tags":[
        "whol",
        "-"
    ],
    "wof:name":"Mandeville Groenten Bvba",
    "wof:placetype":"venue"
},
  "geometry": {"coordinates":[3.0162580013,51.0216026306],"type":"Point"}
}