{
  "type": "Feature",
  "properties": {
    "iso:country":"BE",
    "sg:address":"Rue Du Doyard 18",
    "sg:city":"Bastogne",
    "sg:classifiers":[
        {
            "category":"Home & Garden",
            "subcategory":"Home Furnishings",
            "type":"Retail Goods"
        }
    ],
    "sg:phone":"+32 61 21 43 48",
    "sg:postcode":"6600",
    "sg:province":"Luxembourg",
    "sg:tags":[
        "interior",
        "decoration"
    ],
    "wof:name":"Fontaine D",
    "wof:placetype":"venue"
},
  "geometry": {"coordinates":[5.7220578194,50.014667511],"type":"Point"}
}