{
  "type": "Feature",
  "properties": {
    "addr:full":"Rue Neuve-chauss\u00c9e 173 P\u00c9ruwelz Hainaut 7600",
    "addr:housenumber":"173",
    "addr:postcode":"7600",
    "addr:street":"Rue Neuve-Chausse\u0301E",
    "iso:country":"BE",
    "sg:address":"Rue Neuve-chauss\u00c9e 173",
    "sg:city":"P\u00c9ruwelz",
    "sg:orig_category":"Herstellingen and onderhoud van auto's",
    "sg:phone":"+32 69 78 04 26",
    "sg:postcode":"7600",
    "sg:province":"Hainaut",
    "wof:name":"Center Wash A.d.n.",
    "wof:placetype":"venue"
},
  "geometry": {"coordinates":[3.6016590595,50.5301437378],"type":"Point"}
}