{
  "type": "Feature",
  "properties": {
    "addr:full":"Westpoeselstraat 3 Lo-reninge West-Vlaanderen 8647",
    "addr:housenumber":"3",
    "addr:postcode":"8647",
    "addr:street":"Westpoeselstraat",
    "iso:country":"BE",
    "sg:address":"Westpoeselstraat 3",
    "sg:city":"Lo-reninge",
    "sg:orig_category":"Boomkwekerijen Gespecialiseerde residenti\u00eble bouw Tuinen",
    "sg:phone":"+32 51 54 47 37",
    "sg:postcode":"8647",
    "sg:province":"West-Vlaanderen",
    "wof:name":"Deheeger Marc",
    "wof:placetype":"venue"
},
  "geometry": {"coordinates":[2.8293159008,50.9501075745],"type":"Point"}
}