{
  "type": "Feature",
  "properties": {
    "addr:full":"All\u00c9e De La Commanderie 24 Gerpinnes Hainaut 6280",
    "addr:housenumber":"24",
    "addr:postcode":"6280",
    "addr:street":"Alle\u0301E De La Commanderie;Hainaut",
    "iso:country":"BE",
    "sg:address":"All\u00c9e De La Commanderie 24",
    "sg:city":"Gerpinnes",
    "sg:classifiers":[
        {
            "category":"Insurance",
            "subcategory":"Insurance Agent",
            "type":"Services"
        }
    ],
    "sg:phone":"+32 71 21 47 52",
    "sg:postcode":"6280",
    "sg:province":"Hainaut",
    "sg:tags":[
        "verzekeringsmakelaars",
        "expert"
    ],
    "wof:name":"M. Tufano",
    "wof:placetype":"venue"
},
  "geometry": {"coordinates":[4.4762802124,50.3308601379],"type":"Point"}
}