{
  "type": "Feature",
  "properties": {
    "iso:country":"BE",
    "sg:address":"Marktplaats 15",
    "sg:city":"Moorslede",
    "sg:orig_category":"Boucheries",
    "sg:phone":"+32 51 77 10 48",
    "sg:postcode":"8890",
    "sg:province":"West-Vlaanderen",
    "wof:name":"Rik Vanhaverbeke",
    "wof:placetype":"venue"
},
  "geometry": {"coordinates":[3.0627770424,50.8912734985],"type":"Point"}
}