{
  "type": "Feature",
  "properties": {
    "iso:country":"BE",
    "sg:address":"Fond Jean-p\u00c2ques 4",
    "sg:city":"Ottignies-louvain-la-neuve",
    "sg:orig_category":"Boekenuitgeverijen",
    "sg:phone":"+32 10 48 25 11",
    "sg:postcode":"1348",
    "sg:province":"Brabant Wallon",
    "wof:name":"Editions Larciers",
    "wof:placetype":"venue"
},
  "geometry": {"coordinates":[4.6362800598,50.6618118286],"type":"Point"}
}