{
  "type": "Feature",
  "properties": {
    "addr:full":"Karel Oomsstraat 37 Antwerpen Antwerpen 2018",
    "addr:housenumber":"37",
    "addr:postcode":"2018",
    "addr:street":"Karel Oomsstraat",
    "iso:country":"BE",
    "sg:address":"Karel Oomsstraat 37",
    "sg:city":"Antwerpen",
    "sg:classifiers":[
        {
            "category":"Social Services",
            "type":"Services"
        }
    ],
    "sg:phone":"+32 3 290 22 90",
    "sg:postcode":"2018",
    "sg:province":"Antwerpen",
    "wof:name":"Domus Flandria",
    "wof:placetype":"venue"
},
  "geometry": {"coordinates":[4.4091410637,51.1949234009],"type":"Point"}
}