{
  "type": "Feature",
  "properties": {
    "addr:full":"Achter Kennes 7 Herselt (ramsel) Antwerpen 2230",
    "addr:housenumber":"7",
    "addr:postcode":"2230",
    "addr:street":"Achter Kennes",
    "iso:country":"BE",
    "sg:address":"Achter Kennes 7",
    "sg:city":"Herselt (ramsel)",
    "sg:classifiers":[
        {
            "category":"Train Station",
            "subcategory":"Rail",
            "type":"Transportation"
        }
    ],
    "sg:phone":"+32 16 69 54 91",
    "sg:postcode":"2230",
    "sg:province":"Antwerpen",
    "sg:tags":[
        "bulk",
        "good",
        "-",
        "transport"
    ],
    "wof:name":"Nylau Bvba",
    "wof:placetype":"venue"
},
  "geometry": {"coordinates":[4.8302578926,51.0337867737],"type":"Point"}
}