{
  "type": "Feature",
  "properties": {
    "iso:country":"BE",
    "sg:address":"Tour 39",
    "sg:city":"Durbuy (heyd)",
    "sg:classifiers":[
        {
            "category":"Building & Trades",
            "subcategory":"Construction",
            "type":"Services"
        }
    ],
    "sg:phone":"+32 86 21 21 01",
    "sg:postcode":"6941",
    "sg:province":"Luxembourg",
    "sg:tags":[
        "carpenter"
    ],
    "wof:name":"Xhignesse Christian Sprl",
    "wof:placetype":"venue"
},
  "geometry": {"coordinates":[5.536465168,50.3530082703],"type":"Point"}
}