{
  "type": "Feature",
  "properties": {
    "addr:full":"Petite Gesves 17 Gesves Namur 5340",
    "addr:housenumber":"17",
    "addr:postcode":"5340",
    "addr:street":"Petite Gesves",
    "iso:country":"BE",
    "sg:address":"Petite Gesves 17",
    "sg:city":"Gesves",
    "sg:orig_category":"Herstellingen and onderhoud van auto's",
    "sg:phone":"+32 83 67 74 22",
    "sg:postcode":"5340",
    "sg:province":"Namur",
    "wof:name":"Philippe Gendrin",
    "wof:placetype":"venue"
},
  "geometry": {"coordinates":[5.0722317696,50.4019889832],"type":"Point"}
}