{
  "type": "Feature",
  "properties": {
    "iso:country":"BE",
    "sg:address":"Parc Ind. Vall\u00c9e Du Hain 16",
    "sg:city":"Braine-le-chateau",
    "sg:orig_category":"Pi\u00e8ces and accessoires de v\u00e9hicules automobiles Gr",
    "sg:phone":"+32 2 366 99 17",
    "sg:postcode":"1440",
    "sg:province":"Brabant Wallon",
    "wof:name":"Valeo Distribution Belg.",
    "wof:placetype":"venue"
},
  "geometry": {"coordinates":[4.2687120438,50.6824455261],"type":"Point"}
}