{
  "type": "Feature",
  "properties": {
    "iso:country":"BE",
    "sg:address":"Windmolen 3",
    "sg:city":"Tessenderlo",
    "sg:classifiers":[
        {
            "category":"Home & Garden",
            "subcategory":"Home Furnishings",
            "type":"Retail Goods"
        }
    ],
    "sg:phone":"+32 13 67 54 00",
    "sg:postcode":"3980",
    "sg:province":"Limburg",
    "sg:tags":[
        "interior",
        "decoration"
    ],
    "wof:name":"Gefra Interieurs",
    "wof:placetype":"venue"
},
  "geometry": {"coordinates":[5.0785551071,51.0787734985],"type":"Point"}
}