{
  "type": "Feature",
  "properties": {
    "iso:country":"BE",
    "sg:address":"Rue Du Centenaire 16ba",
    "sg:city":"Komen-waasten/comines-warneton",
    "sg:orig_category":"Banques and organismes de cr\u00e9dit",
    "sg:phone":"+32 56 58 52 00",
    "sg:postcode":"7783",
    "sg:province":"Hainaut",
    "wof:name":"Dexia",
    "wof:placetype":"venue"
},
  "geometry": {"coordinates":[2.8828949928,50.7069244385],"type":"Point"}
}