{
  "type": "Feature",
  "properties": {
    "addr:full":"Hildering 27 Vorselaar Antwerpen 2290",
    "addr:housenumber":"27",
    "addr:postcode":"2290",
    "addr:street":"Hildering",
    "iso:country":"BE",
    "sg:address":"Hildering 27",
    "sg:city":"Vorselaar",
    "sg:orig_category":"Cr\u00e8ches and garderies d'enfants",
    "sg:phone":"+32 14 51 99 92",
    "sg:postcode":"2290",
    "sg:province":"Antwerpen",
    "wof:name":"Het Kinderparadijs",
    "wof:placetype":"venue"
},
  "geometry": {"coordinates":[4.7662730217,51.1994895935],"type":"Point"}
}