{
  "type": "Feature",
  "properties": {
    "addr:full":"Av. Edison 27 Wavre Brabant Wallon 1300",
    "addr:housenumber":"27;1300",
    "addr:street":"Av. Edison",
    "iso:country":"BE",
    "sg:address":"Av. Edison 27",
    "sg:city":"Wavre",
    "sg:classifiers":[
        {
            "category":"Wholesale",
            "subcategory":"Plants",
            "type":"Manufacturing & Wholesale Goods"
        }
    ],
    "sg:phone":"+32 10 24 11 11",
    "sg:postcode":"1300",
    "sg:province":"Brabant Wallon",
    "sg:tags":[
        "machine",
        "industrial",
        "automation"
    ],
    "wof:name":"Steel S.a.",
    "wof:placetype":"venue"
},
  "geometry": {"coordinates":[4.6000800133,50.7384185791],"type":"Point"}
}