{
  "type": "Feature",
  "properties": {
    "addr:full":"Rue Saint-gilles 13 Li\u00c8ge Li\u00e8ge 4000",
    "addr:housenumber":"13",
    "addr:postcode":"4000",
    "addr:street":"Rue Saint-Gilles",
    "iso:country":"BE",
    "sg:address":"Rue Saint-gilles 13",
    "sg:city":"Li\u00c8ge",
    "sg:orig_category":"Brood, gebak and snoepgoed Restaurants",
    "sg:phone":"+32 4 223 55 39",
    "sg:postcode":"4000",
    "sg:province":"Li\u00e8ge",
    "wof:name":"Gerard Franchi",
    "wof:placetype":"venue"
},
  "geometry": {"coordinates":[5.5678138733,50.6396713257],"type":"Point"}
}