{
  "type": "Feature",
  "properties": {
    "addr:full":"Camiel Fremaultstraat 11 Nazareth Oost-Vlaanderen 9810",
    "addr:housenumber":"11",
    "addr:postcode":"9810",
    "addr:street":"Camiel Fremaultstraat",
    "iso:country":"BE",
    "sg:address":"Camiel Fremaultstraat 11",
    "sg:city":"Nazareth",
    "sg:orig_category":"Binnenhuisarchitecten Installatie van houten of kunststof schrijnwerk",
    "sg:phone":"+32 9 385 86 26",
    "sg:postcode":"9810",
    "sg:province":"Oost-Vlaanderen",
    "wof:name":"Veja",
    "wof:placetype":"venue"
},
  "geometry": {"coordinates":[3.5921831131,50.958820343],"type":"Point"}
}