{
  "type": "Feature",
  "properties": {
    "iso:country":"BE",
    "sg:address":"Rue L\u00e9on Hachez 3",
    "sg:city":"Soignies",
    "sg:classifiers":[
        {
            "category":"Shopping",
            "subcategory":"Optician",
            "type":"Retail Goods"
        }
    ],
    "sg:phone":"+32 67 34 07 87",
    "sg:postcode":"7060",
    "sg:province":"Hainaut",
    "sg:tags":[
        "-"
    ],
    "wof:name":"Vision Espace",
    "wof:placetype":"venue"
},
  "geometry": {"coordinates":[4.0702910423,50.5801048279],"type":"Point"}
}