{
  "type": "Feature",
  "properties": {
    "addr:full":"Rue De L\u00b4ath\u00c9n\u00c9e 11 Aubange Luxembourg 6791",
    "addr:housenumber":"11",
    "addr:postcode":"6791",
    "addr:street":"Rue De L\u00b4Athe\u0301Ne\u0301E",
    "iso:country":"BE",
    "sg:address":"Rue De L\u00b4ath\u00c9n\u00c9e 11",
    "sg:city":"Aubange",
    "sg:orig_category":"Sportclubs",
    "sg:phone":"+32 63 38 77 61",
    "sg:postcode":"6791",
    "sg:province":"Luxembourg",
    "wof:name":"J.c. Athus",
    "wof:placetype":"venue"
},
  "geometry": {"coordinates":[5.838157177,49.5669174194],"type":"Point"}
}