{
  "type": "Feature",
  "properties": {
    "iso:country":"BE",
    "sg:address":"Avenue De L'enseignement 15",
    "sg:city":"Saint-ghislain",
    "sg:classifiers":[
        {
            "category":"Health Services",
            "subcategory":"Health Practitioner",
            "type":"Services"
        }
    ],
    "sg:phone":"+32 65 78 60 07",
    "sg:postcode":"7330",
    "sg:province":"Hainaut",
    "sg:tags":[
        "physiotherapist"
    ],
    "wof:name":"F\u00e9vry Patrick",
    "wof:placetype":"venue"
},
  "geometry": {"coordinates":[3.8193309307,50.4469795227],"type":"Point"}
}