{
  "type": "Feature",
  "properties": {
    "iso:country":"BE",
    "sg:address":"Adolf Buylstraat 29",
    "sg:city":"Oostende",
    "sg:classifiers":[
        {
            "category":"Shopping",
            "subcategory":"Clothing, Apparel, & Fashions",
            "type":"Retail Goods"
        }
    ],
    "sg:phone":"+32 59 51 73 42",
    "sg:postcode":"8400",
    "sg:province":"West-Vlaanderen",
    "sg:tags":[
        "v\u00eatements",
        "pour",
        "dame"
    ],
    "wof:name":"Cache-cache",
    "wof:placetype":"venue"
},
  "geometry": {"coordinates":[2.9153060913,51.2314872742],"type":"Point"}
}