{
  "type": "Feature",
  "properties": {
    "addr:full":"Avenue Des Arts 36 Bruxelles Bruxelles-Capitale 1000",
    "addr:housenumber":"36",
    "addr:postcode":"1000",
    "addr:street":"Avenue Des Arts",
    "iso:country":"BE",
    "sg:address":"Avenue Des Arts 36",
    "sg:city":"Bruxelles",
    "sg:classifiers":[
        {
            "category":"Social Services",
            "subcategory":"Job Training",
            "type":"Services"
        }
    ],
    "sg:phone":"+32 2 514 36 36",
    "sg:postcode":"1000",
    "sg:province":"Bruxelles-Capitale",
    "sg:tags":[
        "personnel",
        "-selection",
        "recruitment"
    ],
    "wof:name":"Nexus Consulting Sa",
    "wof:placetype":"venue"
},
  "geometry": {"coordinates":[4.367099762,50.8424911499],"type":"Point"}
}