{
  "type": "Feature",
  "properties": {
    "iso:country":"BE",
    "sg:address":"Fosses Verger 38b",
    "sg:city":"Olne",
    "sg:orig_category":"Woningbouw",
    "sg:phone":"+32 87 26 75 72",
    "sg:postcode":"4877",
    "sg:province":"Li\u00e8ge",
    "wof:name":"Bernard Stempien",
    "wof:placetype":"venue"
},
  "geometry": {"coordinates":[5.7335600853,50.5896339417],"type":"Point"}
}