{
  "type": "Feature",
  "properties": {
    "iso:country":"BE",
    "sg:address":"L\u00c9on Theodorstraat 12",
    "sg:city":"Jette",
    "sg:orig_category":"Kapsalons",
    "sg:phone":"+32 2 427 75 65",
    "sg:postcode":"1090",
    "sg:province":"Bruxelles-Capitale",
    "wof:name":"Coiffure New Difference",
    "wof:placetype":"venue"
},
  "geometry": {"coordinates":[4.3257389069,50.8736457825],"type":"Point"}
}