{
  "type": "Feature",
  "properties": {
    "iso:country":"BE",
    "sg:address":"Plantijnstraat 10",
    "sg:city":"Oostende (stene)",
    "sg:classifiers":[
        {
            "category":"Building & Trades",
            "subcategory":"Construction",
            "type":"Services"
        }
    ],
    "sg:phone":"+32 59 50 10 35",
    "sg:postcode":"8400",
    "sg:province":"West-Vlaanderen",
    "sg:tags":[
        "carpenter"
    ],
    "wof:name":"Vandaele Nv",
    "wof:placetype":"venue"
},
  "geometry": {"coordinates":[2.9402089119,51.2127456665],"type":"Point"}
}