{
  "type": "Feature",
  "properties": {
    "iso:country":"BE",
    "sg:address":"Waterstraat 64",
    "sg:city":"Bilzen",
    "sg:orig_category":"D\u00e9corateurs d'int\u00e9rieur",
    "sg:phone":"+32 89 49 17 09",
    "sg:postcode":"3740",
    "sg:province":"Limburg",
    "wof:name":"Lindelau Toon",
    "wof:placetype":"venue"
},
  "geometry": {"coordinates":[5.5251498222,50.8968505859],"type":"Point"}
}