{
  "type": "Feature",
  "properties": {
    "iso:country":"BE",
    "sg:address":"Hoekeinde 109",
    "sg:city":"Merksplas",
    "sg:orig_category":"Eleveurs and marchands de porcs",
    "sg:phone":"+32 14 63 36 82",
    "sg:postcode":"2330",
    "sg:province":"Antwerpen",
    "wof:name":"Benny Hereijgers",
    "wof:placetype":"venue"
},
  "geometry": {"coordinates":[4.8579998016,51.386100769],"type":"Point"}
}