{
  "type": "Feature",
  "properties": {
    "addr:full":"Oude Holrakkerstraat 12 Hasselt Limburg 3510",
    "addr:housenumber":"12",
    "addr:postcode":"3510",
    "addr:street":"Oude Holrakkerstraat",
    "iso:country":"BE",
    "sg:address":"Oude Holrakkerstraat 12",
    "sg:city":"Hasselt",
    "sg:orig_category":"M\u00e9decins and sp\u00e9cialistes",
    "sg:phone":"+32 11 85 13 26",
    "sg:postcode":"3510",
    "sg:province":"Limburg",
    "wof:name":"Johan Vijgen",
    "wof:placetype":"venue"
},
  "geometry": {"coordinates":[5.2531552315,50.9474906921],"type":"Point"}
}