{
  "type": "Feature",
  "properties": {
    "addr:full":"Rue Henri Lema\u00cetre 1 Namur Namur 5000",
    "addr:housenumber":"1",
    "addr:postcode":"5000",
    "addr:street":"Rue Henri Lemai\u0302Tre",
    "iso:country":"BE",
    "sg:address":"Rue Henri Lema\u00cetre 1",
    "sg:city":"Namur",
    "sg:orig_category":"Artsen and specialisten",
    "sg:phone":"+32 81 73 58 76",
    "sg:postcode":"5000",
    "sg:province":"Namur",
    "wof:name":"Dominique Miest",
    "wof:placetype":"venue"
},
  "geometry": {"coordinates":[4.853099823,50.4662017822],"type":"Point"}
}