{
  "type": "Feature",
  "properties": {
    "addr:full":"Melkouwensteenweg 115 Berlaar Antwerpen 2590",
    "addr:housenumber":"115",
    "addr:postcode":"2590",
    "addr:street":"Melkouwensteenweg",
    "iso:country":"BE",
    "sg:address":"Melkouwensteenweg 115",
    "sg:city":"Berlaar",
    "sg:classifiers":[
        {
            "category":"Building & Trades",
            "subcategory":"Equipment Rental",
            "type":"Services"
        }
    ],
    "sg:phone":"+32 15 24 74 35",
    "sg:postcode":"2590",
    "sg:province":"Antwerpen",
    "sg:tags":[
        "sound",
        "-",
        "system"
    ],
    "wof:name":"Hit-star",
    "wof:placetype":"venue"
},
  "geometry": {"coordinates":[4.6699581146,51.0911369324],"type":"Point"}
}