{
  "type": "Feature",
  "properties": {
    "addr:full":"Chemin Du Br\u00fbl\u00e9 12 Tournai (mourcourt) Hainaut 7543",
    "addr:housenumber":"12",
    "addr:postcode":"7543",
    "addr:street":"Chemin Du Bru\u0302Le\u0301",
    "iso:country":"BE",
    "sg:address":"Chemin Du Br\u00fbl\u00e9 12",
    "sg:city":"Tournai (mourcourt)",
    "sg:classifiers":[
        {
            "category":"Health Services",
            "subcategory":"Health Practitioner",
            "type":"Services"
        }
    ],
    "sg:phone":"+32 69 85 90 88",
    "sg:postcode":"7543",
    "sg:province":"Hainaut",
    "sg:tags":[
        "therapist",
        "speech"
    ],
    "wof:name":"Nottebaert Lise",
    "wof:placetype":"venue"
},
  "geometry": {"coordinates":[3.4323489666,50.6714897156],"type":"Point"}
}