{
  "type": "Feature",
  "properties": {
    "iso:country":"BE",
    "sg:address":"Ch Dath 244",
    "sg:city":"Enghien",
    "sg:classifiers":[
        {
            "category":"Manufacturing",
            "subcategory":"Paper Products",
            "type":"Manufacturing & Wholesale Goods"
        }
    ],
    "sg:phone":"+32 2 397 01 10",
    "sg:postcode":"7850",
    "sg:province":"Hainaut",
    "sg:tags":[
        "finished",
        "cardboard",
        "-"
    ],
    "wof:name":"Lievin Sa",
    "wof:placetype":"venue"
},
  "geometry": {"coordinates":[4.0334649086,50.6914863586],"type":"Point"}
}