{
  "type": "Feature",
  "properties": {
    "iso:country":"BE",
    "sg:address":"Courtil 95",
    "sg:city":"Gouvy",
    "sg:orig_category":"Paramedische behandelingen",
    "sg:phone":"+32 80 21 62 62",
    "sg:postcode":"6671",
    "sg:province":"Luxembourg",
    "wof:name":"M.e. Bossiroy",
    "wof:placetype":"venue"
},
  "geometry": {"coordinates":[5.9144568443,50.2133255005],"type":"Point"}
}