{
  "type": "Feature",
  "properties": {
    "iso:country":"BE",
    "sg:address":"Dreef 82",
    "sg:city":"Zomergem",
    "sg:classifiers":[
        {
            "category":"Insurance",
            "subcategory":"Insurance Agent",
            "type":"Services"
        }
    ],
    "sg:phone":"+32 9 372 86 86",
    "sg:postcode":"9930",
    "sg:province":"Oost-Vlaanderen",
    "sg:tags":[
        "broker"
    ],
    "wof:name":"Pattyn (kantoor)",
    "wof:placetype":"venue"
},
  "geometry": {"coordinates":[3.5659399033,51.1194648743],"type":"Point"}
}