{
  "type": "Feature",
  "properties": {
    "iso:country":"BE",
    "sg:address":"Rue Washington 59",
    "sg:city":"Bruxelles (ixelles)",
    "sg:classifiers":[
        {
            "category":"Communications",
            "type":"Services"
        }
    ],
    "sg:phone":"+32 2 544 14 00",
    "sg:postcode":"1050",
    "sg:province":"Bruxelles-Capitale",
    "sg:tags":[
        "translator"
    ],
    "wof:name":"Bouquette M",
    "wof:placetype":"venue"
},
  "geometry": {"coordinates":[4.3630108833,50.823387146],"type":"Point"}
}