{
  "type": "Feature",
  "properties": {
    "addr:full":"Rue De Virelles 28 Chimay Hainaut 6460",
    "addr:housenumber":"28",
    "addr:postcode":"6460",
    "addr:street":"Rue De Virelles",
    "iso:country":"BE",
    "sg:address":"Rue De Virelles 28",
    "sg:city":"Chimay",
    "sg:orig_category":"Elektrische installaties voor woningen HERSTELLING ELEKTRISCHE HUISHOUDAPPARATEN Huishoudapparaten, ",
    "sg:phone":"+32 60 21 26 83",
    "sg:postcode":"6460",
    "sg:province":"Hainaut",
    "wof:name":"Christian Delsaux",
    "wof:placetype":"venue"
},
  "geometry": {"coordinates":[4.325480938,50.0503158569],"type":"Point"}
}