{
  "type": "Feature",
  "properties": {
    "addr:full":"Turnhoutsebaan 266 Schilde Antwerpen 2970",
    "addr:housenumber":"266",
    "addr:postcode":"2970",
    "addr:street":"Turnhoutsebaan",
    "iso:country":"BE",
    "sg:address":"Turnhoutsebaan 266",
    "sg:city":"Schilde",
    "sg:classifiers":[
        {
            "category":"Shopping",
            "subcategory":"Hobbies, Toys, & Games",
            "type":"Retail Goods"
        }
    ],
    "sg:phone":"+32 3 464 23 25",
    "sg:postcode":"2970",
    "sg:province":"Antwerpen",
    "sg:tags":[
        "toy",
        "-"
    ],
    "wof:name":"Toverplaneet (de)",
    "wof:placetype":"venue"
},
  "geometry": {"coordinates":[4.5813908577,51.2398414612],"type":"Point"}
}