{
  "type": "Feature",
  "properties": {
    "addr:full":"Beersellaan 34 Ukkel/uccle Bruxelles-Capitale 1180",
    "addr:housenumber":"34",
    "addr:postcode":"1180",
    "addr:street":"Beersellaan;/",
    "iso:country":"BE",
    "sg:address":"Beersellaan 34",
    "sg:city":"Ukkel/uccle",
    "sg:orig_category":"Slagers",
    "sg:phone":"+32 2 376 04 98",
    "sg:postcode":"1180",
    "sg:province":"Bruxelles-Capitale",
    "wof:name":"Biagio Provenzano",
    "wof:placetype":"venue"
},
  "geometry": {"coordinates":[4.3266282082,50.7857627869],"type":"Point"}
}