{
  "type": "Feature",
  "properties": {
    "addr:full":"Chauss\u00e9e De Louvain 312 Wavre Brabant Wallon 1300",
    "addr:housenumber":"312;1300",
    "addr:street":"Chausse\u0301E De Louvain",
    "iso:country":"BE",
    "sg:address":"Chauss\u00e9e De Louvain 312",
    "sg:city":"Wavre",
    "sg:classifiers":[
        {
            "category":"Home & Garden",
            "subcategory":"Home Furnishings",
            "type":"Retail Goods"
        }
    ],
    "sg:phone":"+32 10 68 15 67",
    "sg:postcode":"1300",
    "sg:province":"Brabant Wallon",
    "sg:tags":[
        "-",
        "bed",
        "mattress"
    ],
    "wof:name":"Dreamworld",
    "wof:placetype":"venue"
},
  "geometry": {"coordinates":[4.6241488457,50.7201576233],"type":"Point"}
}