{
  "type": "Feature",
  "properties": {
    "iso:country":"BE",
    "sg:address":"Koning Leopoldlaan 4",
    "sg:city":"Maldegem",
    "sg:orig_category":"Plaatsen van vloer- and muurbekleding Schilders",
    "sg:phone":"+32 50 71 63 55",
    "sg:postcode":"9990",
    "sg:province":"Oost-Vlaanderen",
    "wof:name":"Erik D'hoore",
    "wof:placetype":"venue"
},
  "geometry": {"coordinates":[3.4527740479,51.2037506104],"type":"Point"}
}