{
  "type": "Feature",
  "properties": {
    "iso:country":"BE",
    "sg:address":"Stormestraat 105",
    "sg:city":"Waregem",
    "sg:orig_category":"V\u00eatements pour Hommes. V\u00eatements pour Dames",
    "sg:phone":"+32 56 60 13 30",
    "sg:postcode":"8790",
    "sg:province":"West-Vlaanderen",
    "wof:name":"Femina",
    "wof:placetype":"venue"
},
  "geometry": {"coordinates":[3.4275660515,50.8850784302],"type":"Point"}
}