{
  "type": "Feature",
  "properties": {
    "iso:country":"BE",
    "sg:address":"Diederikstraat 2",
    "sg:city":"Assenede",
    "sg:orig_category":"Electrom\u00e9nager, t\u00e9l\u00e9visions and radios",
    "sg:phone":"+32 9 344 62 92",
    "sg:postcode":"9960",
    "sg:province":"Oost-Vlaanderen",
    "wof:name":"Agnes Pacque",
    "wof:placetype":"venue"
},
  "geometry": {"coordinates":[3.7526791096,51.227268219],"type":"Point"}
}