{
  "type": "Feature",
  "properties": {
    "addr:full":"Rue Bonne Esp\u00e9rance 11 Mettet Namur 5640",
    "addr:housenumber":"11",
    "addr:postcode":"5640",
    "addr:street":"Rue Bonne Espe\u0301Rance",
    "iso:country":"BE",
    "sg:address":"Rue Bonne Esp\u00e9rance 11",
    "sg:city":"Mettet",
    "sg:classifiers":[
        {
            "category":"Home & Garden",
            "subcategory":"Garden Supply",
            "type":"Retail Goods"
        }
    ],
    "sg:phone":"+32 71 72 89 21",
    "sg:postcode":"5640",
    "sg:province":"Namur",
    "sg:tags":[
        "seed",
        "-"
    ],
    "wof:name":"Van Den Bergh-stefan",
    "wof:placetype":"venue"
},
  "geometry": {"coordinates":[4.6671490669,50.3220367432],"type":"Point"}
}