{
  "type": "Feature",
  "properties": {
    "iso:country":"BE",
    "sg:address":"Rue De L'ath\u00e9n\u00e9e 20",
    "sg:city":"Charleroi",
    "sg:classifiers":[
        {
            "category":"Professional",
            "subcategory":"Lawyer & Legal Services",
            "type":"Services"
        }
    ],
    "sg:phone":"+32 71 33 04 52",
    "sg:postcode":"6000",
    "sg:province":"Hainaut",
    "wof:name":"Grenier Jean",
    "wof:placetype":"venue"
},
  "geometry": {"coordinates":[4.4488668442,50.4077949524],"type":"Point"}
}