{
  "type": "Feature",
  "properties": {
    "iso:country":"BE",
    "sg:address":"Brusselsesteenweg 505 A",
    "sg:city":"Waterloo",
    "sg:orig_category":"Sport- and kampeermateriaal Verhuur voertuigen behalve auto's",
    "sg:phone":"+32 2 384 47 51",
    "sg:postcode":"1410",
    "sg:province":"Brabant Wallon",
    "wof:name":"Camping Relax",
    "wof:placetype":"venue"
},
  "geometry": {"coordinates":[4.404460907,50.6934890747],"type":"Point"}
}