{
  "type": "Feature",
  "properties": {
    "iso:country":"BE",
    "sg:address":"Flierenbos 63",
    "sg:city":"Arendonk",
    "sg:orig_category":"Packard Bell Nec. Ordinateurs and \u00e9quipement informatique",
    "sg:phone":"+32 14 67 16 40",
    "sg:postcode":"2370",
    "sg:province":"Antwerpen",
    "wof:name":"Idc",
    "wof:placetype":"venue"
},
  "geometry": {"coordinates":[5.0942659378,51.3348426819],"type":"Point"}
}