{
  "type": "Feature",
  "properties": {
    "iso:country":"BE",
    "sg:address":"Interleuvenlaan 25",
    "sg:city":"Heverlee",
    "sg:classifiers":[
        {
            "category":"Professional",
            "subcategory":"Testing Lab",
            "type":"Services"
        }
    ],
    "sg:phone":"+32 16 40 20 00",
    "sg:postcode":"3001",
    "sg:province":"Vlaams-Brabant",
    "sg:tags":[
        "laboratory"
    ],
    "wof:name":"Hercules Betz Dearborn Nv",
    "wof:placetype":"venue"
},
  "geometry": {"coordinates":[4.7361750603,50.8476066589],"type":"Point"}
}