{
  "type": "Feature",
  "properties": {
    "addr:full":"Koning Leopoldstraat 31 Antwerpen Antwerpen 2610",
    "addr:housenumber":"31",
    "addr:postcode":"2610",
    "addr:street":"Koning Leopoldstraat",
    "iso:country":"BE",
    "sg:address":"Koning Leopoldstraat 31",
    "sg:city":"Antwerpen",
    "sg:orig_category":"Huishoudapparaten, televisies and radio's Industri\u00eble elektrische installaties",
    "sg:phone":"+32 3 830 00 16",
    "sg:postcode":"2610",
    "sg:province":"Antwerpen",
    "wof:name":"A.d.m.-elektro",
    "wof:placetype":"venue"
},
  "geometry": {"coordinates":[4.4072117805,51.2145423889],"type":"Point"}
}