{
  "type": "Feature",
  "properties": {
    "iso:country":"BE",
    "sg:address":"Lichterveldestraat 45",
    "sg:city":"Kortemark",
    "sg:classifiers":[
        {
            "category":"Home & Garden",
            "subcategory":"Building Materials",
            "type":"Retail Goods"
        }
    ],
    "sg:phone":"+32 51 57 13 05",
    "sg:postcode":"8610",
    "sg:province":"West-Vlaanderen",
    "sg:tags":[
        "granite",
        "stone",
        "natural",
        "marble"
    ],
    "wof:name":"Fergico",
    "wof:placetype":"venue"
},
  "geometry": {"coordinates":[3.0481131077,51.0285339355],"type":"Point"}
}