{
  "type": "Feature",
  "properties": {
    "iso:country":"BE",
    "sg:address":"Molenvijverstraat 36",
    "sg:city":"Beverlo",
    "sg:orig_category":"Antiek Installatie van houten of kunststof schrijnwerk Schilders",
    "sg:phone":"+32 11 34 81 75",
    "sg:postcode":"3581",
    "sg:province":"Limburg",
    "wof:name":"Interiors Projects Realizations",
    "wof:placetype":"venue"
},
  "geometry": {"coordinates":[5.2268238068,51.0946350098],"type":"Point"}
}