{
  "type": "Feature",
  "properties": {
    "iso:country":"BE",
    "sg:address":"Duinhoekstraat 123b50",
    "sg:city":"De Panne",
    "sg:classifiers":[
        {
            "category":"Real Estate",
            "subcategory":"Developer",
            "type":"Services"
        }
    ],
    "sg:phone":"+32 58 41 48 05",
    "sg:postcode":"8660",
    "sg:province":"West-Vlaanderen",
    "sg:tags":[
        "plomberie",
        "chauffage",
        "mat\u00e9riel",
        "gr",
        "pour"
    ],
    "wof:name":"Armathour Eternal Art",
    "wof:placetype":"venue"
},
  "geometry": {"coordinates":[2.5880720615,51.0820274353],"type":"Point"}
}