{
  "type": "Feature",
  "properties": {
    "addr:full":"Rue Des Eburons 62 Li\u00e8ge 1 Li\u00e8ge 4000",
    "addr:housenumber":"62;1",
    "addr:postcode":"4000",
    "addr:street":"Rue Des Eburons",
    "iso:country":"BE",
    "sg:address":"Rue Des Eburons 62",
    "sg:city":"Li\u00e8ge 1",
    "sg:classifiers":[
        {
            "category":"Health Services",
            "subcategory":"Health Practitioner",
            "type":"Services"
        }
    ],
    "sg:phone":"+32 4 252 95 53",
    "sg:postcode":"4000",
    "sg:province":"Li\u00e8ge",
    "sg:tags":[
        "physiotherapist"
    ],
    "wof:name":"Weltjens V\u00e9ronique",
    "wof:placetype":"venue"
},
  "geometry": {"coordinates":[5.5614318848,50.6295204163],"type":"Point"}
}