{
  "type": "Feature",
  "properties": {
    "iso:country":"BE",
    "sg:address":"Rue Des Hayettes 27",
    "sg:city":"Ham-sur-heure-nalinnes",
    "sg:orig_category":"Artsen and specialisten",
    "sg:phone":"+32 71 21 68 53",
    "sg:postcode":"6120",
    "sg:province":"Hainaut",
    "wof:name":"Ph. Vilain",
    "wof:placetype":"venue"
},
  "geometry": {"coordinates":[4.3970799446,50.3020172119],"type":"Point"}
}