{
  "type": "Feature",
  "properties": {
    "iso:country":"BE",
    "sg:address":"Hebbestraat 102",
    "sg:city":"Hamme (moerzeke)",
    "sg:classifiers":[
        {
            "category":"Retail",
            "subcategory":"Auto Repair",
            "type":"Services"
        }
    ],
    "sg:phone":"+32 52 47 77 69",
    "sg:postcode":"9220",
    "sg:province":"Oost-Vlaanderen",
    "sg:tags":[
        "automobile-body"
    ],
    "wof:name":"Gar Meeus Bvba",
    "wof:placetype":"venue"
},
  "geometry": {"coordinates":[4.1356267929,51.0624847412],"type":"Point"}
}