{
  "type": "Feature",
  "properties": {
    "iso:country":"BE",
    "sg:address":"Rue De La Ri\u00e8ze 152",
    "sg:city":"Couvin (cul-des-sarts)",
    "sg:classifiers":[
        {
            "category":"Shopping",
            "subcategory":"Stationery & Office Supplies",
            "type":"Retail Goods"
        }
    ],
    "sg:phone":"+32 60 37 79 07",
    "sg:postcode":"5660",
    "sg:province":"Namur",
    "sg:tags":[
        "partition"
    ],
    "wof:name":"Ets Jacques Bernard Sprl",
    "wof:placetype":"venue"
},
  "geometry": {"coordinates":[4.4592900276,49.963470459],"type":"Point"}
}