{
  "type": "Feature",
  "properties": {
    "iso:country":"BE",
    "sg:address":"Bergstraat 2",
    "sg:city":"Kortrijk (aalbeke)",
    "sg:orig_category":"Non-Classified Establishments",
    "sg:phone":"+32 56 42 21 11",
    "sg:postcode":"8511",
    "sg:province":"West-Vlaanderen",
    "wof:name":"Actine",
    "wof:placetype":"venue"
},
  "geometry": {"coordinates":[3.2302689552,50.7782554626],"type":"Point"}
}