{
  "type": "Feature",
  "properties": {
    "addr:full":"Kelfsstraat 81 Haacht (tildonk) Vlaams-Brabant 3150",
    "addr:housenumber":"81",
    "addr:postcode":"3150",
    "addr:street":"Kelfsstraat",
    "iso:country":"BE",
    "sg:address":"Kelfsstraat 81",
    "sg:city":"Haacht (tildonk)",
    "sg:classifiers":[
        {
            "category":"Building & Trades",
            "subcategory":"Plumbing",
            "type":"Services"
        }
    ],
    "sg:phone":"+32 16 60 86 10",
    "sg:postcode":"3150",
    "sg:province":"Vlaams-Brabant",
    "sg:tags":[
        "repair",
        "mainten",
        "-",
        "central",
        "heating"
    ],
    "wof:name":"Flam Control Bvba",
    "wof:placetype":"venue"
},
  "geometry": {"coordinates":[4.6816391945,50.9493255615],"type":"Point"}
}