{
  "type": "Feature",
  "properties": {
    "addr:full":"Brabantdam 35h Gent Oost-Vlaanderen 9000",
    "addr:housenumber":"35h",
    "addr:postcode":"9000",
    "addr:street":"Brabantdam;Oost-Vlaanderen",
    "iso:country":"BE",
    "sg:address":"Brabantdam 35h",
    "sg:city":"Gent",
    "sg:classifiers":[
        {
            "category":"Tea Room",
            "subcategory":"None",
            "type":"Food & Drink"
        }
    ],
    "sg:phone":"+32 9 224 26 44",
    "sg:postcode":"9000",
    "sg:province":"Oost-Vlaanderen",
    "wof:name":"De Braempoort Tea-room Bvba",
    "wof:placetype":"venue"
},
  "geometry": {"coordinates":[3.7284700871,51.0505447388],"type":"Point"}
}