{
  "type": "Feature",
  "properties": {
    "iso:country":"BE",
    "sg:address":"Rue Haut Rejet 293g",
    "sg:city":"Tournai (havinnes)",
    "sg:classifiers":[
        {
            "category":"Personal",
            "subcategory":"Nail Salon",
            "type":"Services"
        }
    ],
    "sg:phone":"+32 69 54 60 55",
    "sg:postcode":"7531",
    "sg:province":"Hainaut",
    "sg:tags":[
        "pedicure"
    ],
    "wof:name":"Drossart A",
    "wof:placetype":"venue"
},
  "geometry": {"coordinates":[3.4855790138,50.6231155396],"type":"Point"}
}