{
  "type": "Feature",
  "properties": {
    "addr:full":"Chemin Du Lanternier 21 Lasne Brabant Wallon 1380",
    "addr:housenumber":"21",
    "addr:postcode":"1380",
    "addr:street":"Chemin Du Lanternier",
    "iso:country":"BE",
    "sg:address":"Chemin Du Lanternier 21",
    "sg:city":"Lasne",
    "sg:orig_category":"Beheer onroerend goed",
    "sg:phone":"+32 2 633 13 65",
    "sg:postcode":"1380",
    "sg:province":"Brabant Wallon",
    "wof:name":"Paul Potez",
    "wof:placetype":"venue"
},
  "geometry": {"coordinates":[4.4278988838,50.6630744934],"type":"Point"}
}