{
  "type": "Feature",
  "properties": {
    "iso:country":"BE",
    "sg:address":"Sint-rijkersstraat 16",
    "sg:city":"Alveringem",
    "sg:orig_category":"Banken and kredietinstellingen",
    "sg:phone":"+32 58 28 85 67",
    "sg:postcode":"8690",
    "sg:province":"West-Vlaanderen",
    "wof:name":"Fortis",
    "wof:placetype":"venue"
},
  "geometry": {"coordinates":[2.6881999969,51.0084381104],"type":"Point"}
}