{
  "type": "Feature",
  "properties": {
    "addr:full":"Rue Martin-sandron 153 Doische Namur 5680",
    "addr:housenumber":"153",
    "addr:postcode":"5680",
    "addr:street":"Rue Martin-Sandron",
    "iso:country":"BE",
    "sg:address":"Rue Martin-sandron 153",
    "sg:city":"Doische",
    "sg:orig_category":"M\u00e9decins and sp\u00e9cialistes",
    "sg:phone":"+32 82 67 74 36",
    "sg:postcode":"5680",
    "sg:province":"Namur",
    "wof:name":"Mich\u00c8le Dubuc",
    "wof:placetype":"venue"
},
  "geometry": {"coordinates":[4.7398571968,50.1357650757],"type":"Point"}
}