{
  "type": "Feature",
  "properties": {
    "addr:full":"Rue Du Grand Central 47 Charleroi Hainaut 6000",
    "addr:housenumber":"47",
    "addr:postcode":"6000",
    "addr:street":"Rue Du Grand Central;Hainaut",
    "iso:country":"BE",
    "sg:address":"Rue Du Grand Central 47",
    "sg:city":"Charleroi",
    "sg:classifiers":[
        {
            "category":"Restaurant",
            "type":"Food & Drink"
        }
    ],
    "sg:phone":"+32 71 32 95 76",
    "sg:postcode":"6000",
    "sg:province":"Hainaut",
    "wof:name":"Restaurant Albert",
    "wof:placetype":"venue"
},
  "geometry": {"coordinates":[4.4369430542,50.4096488953],"type":"Point"}
}