{
  "type": "Feature",
  "properties": {
    "addr:full":"Chauss\u00c9e De Maubeuge 506 Mons Hainaut 7022",
    "addr:housenumber":"506",
    "addr:postcode":"7022",
    "addr:street":"Chausse\u0301E De Maubeuge;Hainaut",
    "iso:country":"BE",
    "sg:address":"Chauss\u00c9e De Maubeuge 506",
    "sg:city":"Mons",
    "sg:orig_category":"Herstellingen and onderhoud van auto's Voertuigen",
    "sg:phone":"+32 65 35 45 51",
    "sg:postcode":"7022",
    "sg:province":"Hainaut",
    "wof:name":"Cousin & Fils",
    "wof:placetype":"venue"
},
  "geometry": {"coordinates":[3.9483699799,50.4251174927],"type":"Point"}
}