{
  "type": "Feature",
  "properties": {
    "addr:full":"Rue Camille Lemonnier 45 Elsene/ixelles Bruxelles-Capitale 1050",
    "addr:housenumber":"45",
    "addr:postcode":"1050",
    "addr:street":"Rue Camille Lemonnier",
    "iso:country":"BE",
    "sg:address":"Rue Camille Lemonnier 45",
    "sg:city":"Elsene/ixelles",
    "sg:classifiers":[
        {
            "category":"Arena",
            "subcategory":"Sports Club",
            "type":"Entertainment"
        }
    ],
    "sg:phone":"+32 2 344 58 13",
    "sg:postcode":"1050",
    "sg:province":"Bruxelles-Capitale",
    "sg:tags":[
        "de"
    ],
    "wof:name":"H.c. La Sapini\u00c8re",
    "wof:placetype":"venue"
},
  "geometry": {"coordinates":[4.3592271805,50.8182868958],"type":"Point"}
}