{
  "type": "Feature",
  "properties": {
    "iso:country":"BE",
    "sg:address":"Smekenstraat 51",
    "sg:city":"Malle",
    "sg:orig_category":"Instituts de beaut\u00e9",
    "sg:phone":"+32 3 311 58 93",
    "sg:postcode":"2390",
    "sg:province":"Antwerpen",
    "wof:name":"Lutgart Goossens",
    "wof:placetype":"venue"
},
  "geometry": {"coordinates":[4.7463469505,51.304359436],"type":"Point"}
}