{
  "type": "Feature",
  "properties": {
    "iso:country":"BE",
    "sg:address":"Gullegemsestraat 18",
    "sg:city":"Ledegem",
    "sg:orig_category":"Poissonniers and \u00e9caillers",
    "sg:phone":"+32 56 50 45 67",
    "sg:postcode":"8880",
    "sg:province":"West-Vlaanderen",
    "wof:name":"Huis Zeeweelde",
    "wof:placetype":"venue"
},
  "geometry": {"coordinates":[3.1802508831,50.8741264343],"type":"Point"}
}