{
  "type": "Feature",
  "properties": {
    "addr:full":"Sint-vincentiusplaats 19 Evere/evere Bruxelles-Capitale 1140",
    "addr:housenumber":"19",
    "addr:postcode":"1140",
    "addr:street":"Sint-Vincentiusplaats",
    "iso:country":"BE",
    "sg:address":"Sint-vincentiusplaats 19",
    "sg:city":"Evere/evere",
    "sg:orig_category":"Kapsalons",
    "sg:phone":"+32 2 241 03 49",
    "sg:postcode":"1140",
    "sg:province":"Bruxelles-Capitale",
    "wof:name":"Coiffure A. & C.",
    "wof:placetype":"venue"
},
  "geometry": {"coordinates":[4.4033517838,50.8809318542],"type":"Point"}
}