{
  "type": "Feature",
  "properties": {
    "iso:country":"BE",
    "sg:address":"Pontstraat 4",
    "sg:city":"Aalst",
    "sg:classifiers":[
        {
            "category":"Real Estate",
            "subcategory":"Architect",
            "type":"Services"
        }
    ],
    "sg:phone":"+32 53 77 95 12",
    "sg:postcode":"9300",
    "sg:province":"Oost-Vlaanderen",
    "wof:name":"Simal L",
    "wof:placetype":"venue"
},
  "geometry": {"coordinates":[4.0413908958,50.9374008179],"type":"Point"}
}