{
  "type": "Feature",
  "properties": {
    "addr:full":"Wolfsdonksesteenweg 16 Herselt Antwerpen 2230",
    "addr:housenumber":"16",
    "addr:postcode":"2230",
    "addr:street":"Wolfsdonksesteenweg",
    "iso:country":"BE",
    "sg:address":"Wolfsdonksesteenweg 16",
    "sg:city":"Herselt",
    "sg:classifiers":[
        {
            "category":"Retail",
            "subcategory":"Repair Shop",
            "type":"Services"
        }
    ],
    "sg:phone":"+32 14 54 57 76",
    "sg:postcode":"2230",
    "sg:province":"Antwerpen",
    "sg:tags":[
        "radio",
        "television",
        "-",
        "maintenance"
    ],
    "wof:name":"Hijne T.v.",
    "wof:placetype":"venue"
},
  "geometry": {"coordinates":[4.8816227913,51.0514793396],"type":"Point"}
}