{
  "type": "Feature",
  "properties": {
    "addr:full":"Leuvensesteenweg 142 Aarschot Vlaams-Brabant 3200",
    "addr:housenumber":"142",
    "addr:postcode":"3200",
    "addr:street":"Leuvensesteenweg",
    "iso:country":"BE",
    "sg:address":"Leuvensesteenweg 142",
    "sg:city":"Aarschot",
    "sg:orig_category":"Action sociale avec h\u00e9bergement",
    "sg:phone":"+32 16 56 45 63",
    "sg:postcode":"3200",
    "sg:province":"Vlaams-Brabant",
    "wof:name":"De Hal",
    "wof:placetype":"venue"
},
  "geometry": {"coordinates":[4.8293781281,50.98254776],"type":"Point"}
}