{
  "type": "Feature",
  "properties": {
    "addr:full":"Avenue De La Belle Province 107bb Braine-l`alleud Brabant Wallon 1420",
    "addr:housenumber":"107bb",
    "addr:postcode":"1420",
    "addr:street":"Avenue De La Belle Province;Brabant Wallon",
    "iso:country":"BE",
    "sg:address":"Avenue De La Belle Province 107bb",
    "sg:city":"Braine-l`alleud",
    "sg:classifiers":[
        {
            "category":"Cafe",
            "type":"Food & Drink"
        }
    ],
    "sg:phone":"+32 2 387 04 05",
    "sg:postcode":"1420",
    "sg:province":"Brabant Wallon",
    "sg:tags":[
        "caf\u00e9s"
    ],
    "wof:name":"L'anti-t",
    "wof:placetype":"venue"
},
  "geometry": {"coordinates":[5.8036999702,45.9799995422],"type":"Point"}
}