{
  "type": "Feature",
  "properties": {
    "addr:full":"Kleine Daalstraat 28 Bus 1 Zaventem Vlaams-Brabant 1930",
    "addr:housenumber":"28 bus 1",
    "addr:postcode":"1930",
    "addr:street":"Kleine Daalstraat",
    "iso:country":"BE",
    "sg:address":"Kleine Daalstraat 28 Bus 1",
    "sg:city":"Zaventem",
    "sg:classifiers":[
        {
            "category":"Military Area",
            "subcategory":"Coast Guard Base",
            "type":"Public Place"
        }
    ],
    "sg:phone":"+32 2 709 77 70",
    "sg:postcode":"1930",
    "sg:province":"Vlaams-Brabant",
    "sg:tags":[
        "steel",
        "flat",
        "stainless"
    ],
    "wof:name":"Alpha Steel N.v.-s.a.",
    "wof:placetype":"venue"
},
  "geometry": {"coordinates":[4.4690389633,50.881023407],"type":"Point"}
}