{
  "type": "Feature",
  "properties": {
    "addr:full":"Ieperse Steenweg 47 Veurne West-Vlaanderen 8630",
    "addr:housenumber":"47",
    "addr:postcode":"8630",
    "addr:street":"Steenweg",
    "iso:country":"BE",
    "sg:address":"Ieperse Steenweg 47",
    "sg:city":"Veurne",
    "sg:orig_category":"V\u00e9t\u00e9rinaires",
    "sg:phone":"+32 58 31 48 28",
    "sg:postcode":"8630",
    "sg:province":"West-Vlaanderen",
    "wof:name":"Olivier Debakker",
    "wof:placetype":"venue"
},
  "geometry": {"coordinates":[2.6655640602,51.0657653809],"type":"Point"}
}