{
  "type": "Feature",
  "properties": {
    "addr:full":"Chemin Pav\u00e9 Molembais 26 Jodoigne Brabant Wallon 1370",
    "addr:housenumber":"26",
    "addr:postcode":"1370",
    "addr:street":"Chemin Pave\u0301 Molembais",
    "iso:country":"BE",
    "sg:address":"Chemin Pav\u00e9 Molembais 26",
    "sg:city":"Jodoigne",
    "sg:classifiers":[
        {
            "category":"Real Estate",
            "subcategory":"Architect",
            "type":"Services"
        }
    ],
    "sg:phone":"+32 10 81 68 11",
    "sg:postcode":"1370",
    "sg:province":"Brabant Wallon",
    "wof:name":"Dandoy A",
    "wof:placetype":"venue"
},
  "geometry": {"coordinates":[4.8886399269,50.7052192688],"type":"Point"}
}