{
  "type": "Feature",
  "properties": {
    "addr:full":"Chauss\u00e9e D'anvers 8 Bruxelles Bruxelles-Capitale 1000",
    "addr:housenumber":"8",
    "addr:postcode":"1000",
    "addr:street":"Chausse\u0301E D'Anvers",
    "iso:country":"BE",
    "sg:address":"Chauss\u00e9e D'anvers 8",
    "sg:city":"Bruxelles",
    "sg:classifiers":[
        {
            "category":"Bars & Pubs",
            "type":"Food & Drink"
        }
    ],
    "sg:phone":"+32 2 203 57 66",
    "sg:postcode":"1000",
    "sg:province":"Bruxelles-Capitale",
    "sg:tags":[
        "tavern"
    ],
    "wof:name":"Bier Huys-gouvernement (le)",
    "wof:placetype":"venue"
},
  "geometry": {"coordinates":[4.3531241417,50.8571662903],"type":"Point"}
}