{
  "type": "Feature",
  "properties": {
    "iso:country":"BE",
    "sg:address":"Tervuursesteenweg 536",
    "sg:city":"Zemst",
    "sg:orig_category":"Belastingconsulenten Diverse juridische dienstverlening",
    "sg:phone":"+32 15 61 01 60",
    "sg:postcode":"1982",
    "sg:province":"Vlaams-Brabant",
    "wof:name":"J. Hoho",
    "wof:placetype":"venue"
},
  "geometry": {"coordinates":[4.5041818619,50.9767417908],"type":"Point"}
}