{
  "type": "Feature",
  "properties": {
    "iso:country":"BE",
    "sg:address":"Rue Du Petit Ch\u00eane 4",
    "sg:city":"Li\u00e8ge 1",
    "sg:classifiers":[
        {
            "category":"Retail",
            "subcategory":"Auto Repair",
            "type":"Services"
        }
    ],
    "sg:phone":"+32 4 227 11 11",
    "sg:postcode":"4000",
    "sg:province":"Li\u00e8ge",
    "sg:tags":[
        "automobile-body"
    ],
    "wof:name":"Sinatra.s",
    "wof:placetype":"venue"
},
  "geometry": {"coordinates":[5.6058411598,50.6551361084],"type":"Point"}
}