{
  "type": "Feature",
  "properties": {
    "iso:country":"BE",
    "sg:address":"Rue De La Prison 36",
    "sg:city":"La Hulpe",
    "sg:orig_category":"Artistes ind\u00e9pendants",
    "sg:phone":"+32 2 653 32 51",
    "sg:postcode":"1310",
    "sg:province":"Brabant Wallon",
    "wof:name":"Raymond Ghys",
    "wof:placetype":"venue"
},
  "geometry": {"coordinates":[4.4682149887,50.7205581665],"type":"Point"}
}