{
  "type": "Feature",
  "properties": {
    "addr:full":"Avenue Jules Bordet 13 Evere/evere Bruxelles-Capitale 1140",
    "addr:housenumber":"13",
    "addr:postcode":"1140",
    "addr:street":"Avenue Jules Bordet",
    "iso:country":"BE",
    "sg:address":"Avenue Jules Bordet 13",
    "sg:city":"Evere/evere",
    "sg:orig_category":"Produits pharmaceutiques Fab",
    "sg:phone":"+32 2 726 95 84",
    "sg:postcode":"1140",
    "sg:province":"Bruxelles-Capitale",
    "wof:name":"I.m.b.",
    "wof:placetype":"venue"
},
  "geometry": {"coordinates":[4.4158301353,50.8725662231],"type":"Point"}
}