{
  "type": "Feature",
  "properties": {
    "addr:full":"Gemeneweideweg-noord 4 Brugge (sint-kruis) West-Vlaanderen 8310",
    "addr:housenumber":"4",
    "addr:postcode":"8310",
    "addr:street":"Gemeneweideweg-Noord",
    "iso:country":"BE",
    "sg:address":"Gemeneweideweg-noord 4",
    "sg:city":"Brugge (sint-kruis)",
    "sg:classifiers":[
        {
            "category":"Brewery",
            "type":"Food & Drink"
        }
    ],
    "sg:phone":"+32 50 37 15 37",
    "sg:postcode":"8310",
    "sg:province":"West-Vlaanderen",
    "wof:name":"Coenco",
    "wof:placetype":"venue"
},
  "geometry": {"coordinates":[3.264318943,51.214931488],"type":"Point"}
}