{
  "type": "Feature",
  "properties": {
    "addr:full":"De Coninckplein 30 Antwerpen Antwerpen 2000",
    "addr:housenumber":"30",
    "addr:postcode":"2000",
    "iso:country":"BE",
    "sg:address":"De Coninckplein 30",
    "sg:city":"Antwerpen",
    "sg:classifiers":[
        {
            "category":"Restaurant",
            "type":"Food & Drink"
        }
    ],
    "sg:phone":"+32 3 226 94 99",
    "sg:postcode":"2000",
    "sg:province":"Antwerpen",
    "wof:name":"Sangam",
    "wof:placetype":"venue"
},
  "geometry": {"coordinates":[4.4212222099,51.2215843201],"type":"Point"}
}