{
  "type": "Feature",
  "properties": {
    "iso:country":"BE",
    "sg:address":"Staatsbaan 123",
    "sg:city":"Kortemark",
    "sg:orig_category":"Motorfietsen Tuinbenodigdheden Voertuigen",
    "sg:phone":"+32 51 56 75 59",
    "sg:postcode":"8610",
    "sg:province":"West-Vlaanderen",
    "wof:name":"Viaene Lionel",
    "wof:placetype":"venue"
},
  "geometry": {"coordinates":[3.0162580013,51.0216026306],"type":"Point"}
}