{
  "type": "Feature",
  "properties": {
    "iso:country":"BE",
    "sg:address":"Rollebeekstraat 31",
    "sg:city":"Brussel/bruxelles",
    "sg:classifiers":[
        {
            "category":"Restaurant",
            "type":"Food & Drink"
        }
    ],
    "sg:phone":"+32 2 513 10 62",
    "sg:postcode":"1000",
    "sg:province":"Bruxelles-Capitale",
    "wof:name":"La Tortue Du Zoute",
    "wof:placetype":"venue"
},
  "geometry": {"coordinates":[4.3530788422,50.841796875],"type":"Point"}
}