{
  "type": "Feature",
  "properties": {
    "iso:country":"BE",
    "sg:address":"Rue Michel 128",
    "sg:city":"Oupeye",
    "sg:orig_category":"Pleisterwerk",
    "sg:phone":"+32 4 374 13 53",
    "sg:postcode":"4684",
    "sg:province":"Li\u00e8ge",
    "wof:name":"A.d. Plafonnage",
    "wof:placetype":"venue"
},
  "geometry": {"coordinates":[5.6733579636,50.7375526428],"type":"Point"}
}