{
  "type": "Feature",
  "properties": {
    "addr:full":"Hoogstraatsebaan 18 Brecht Antwerpen 2960",
    "addr:housenumber":"18",
    "addr:postcode":"2960",
    "addr:street":"Hoogstraatsebaan",
    "iso:country":"BE",
    "sg:address":"Hoogstraatsebaan 18",
    "sg:city":"Brecht",
    "sg:classifiers":[
        {
            "category":"Fast Food",
            "type":"Food & Drink"
        }
    ],
    "sg:phone":"+32 3 313 00 37",
    "sg:postcode":"2960",
    "sg:province":"Antwerpen",
    "sg:tags":[
        "meeneem",
        "restaurant"
    ],
    "wof:name":"China Garden",
    "wof:placetype":"venue"
},
  "geometry": {"coordinates":[4.6415200233,51.3512115479],"type":"Point"}
}