{
  "type": "Feature",
  "properties": {
    "iso:country":"BE",
    "sg:address":"Merelnest 1",
    "sg:city":"Kortenaken",
    "sg:classifiers":[
        {
            "category":"Food & Beverages",
            "subcategory":"Fruits & Vegetables",
            "type":"Retail Goods"
        }
    ],
    "sg:phone":"+32 11 58 74 65",
    "sg:postcode":"3470",
    "sg:province":"Vlaams-Brabant",
    "sg:tags":[
        "l\u00e9gumes"
    ],
    "wof:name":"D. Rummens",
    "wof:placetype":"venue"
},
  "geometry": {"coordinates":[5.052752018,50.8862228394],"type":"Point"}
}