{
  "type": "Feature",
  "properties": {
    "iso:country":"BE",
    "sg:address":"Demerstraat 31",
    "sg:city":"Hasselt",
    "sg:orig_category":"Chaussures. Maroquinerie and articles de voyage",
    "sg:phone":"+32 11 23 69 33",
    "sg:postcode":"3500",
    "sg:province":"Limburg",
    "wof:name":"Huis Divergence",
    "wof:placetype":"venue"
},
  "geometry": {"coordinates":[5.3379778862,50.931552887],"type":"Point"}
}