{
  "type": "Feature",
  "properties": {
    "iso:country":"BE",
    "sg:address":"Priester Coulonstraat 1",
    "sg:city":"Menen (rekkem)",
    "sg:classifiers":[
        {
            "category":"Building & Trades",
            "subcategory":"Electrical",
            "type":"Services"
        }
    ],
    "sg:phone":"+32 56 42 77 57",
    "sg:postcode":"8930",
    "sg:province":"West-Vlaanderen",
    "sg:tags":[
        "-",
        "electric",
        "contractor"
    ],
    "wof:name":"Fabry P",
    "wof:placetype":"venue"
},
  "geometry": {"coordinates":[3.1647911072,50.7829818726],"type":"Point"}
}