{
  "type": "Feature",
  "properties": {
    "iso:country":"BE",
    "sg:address":"Sch\u00f6nefelderweg 14",
    "sg:city":"Eupen",
    "sg:classifiers":[
        {
            "category":"Arena",
            "subcategory":"Sports Club",
            "type":"Entertainment"
        }
    ],
    "sg:phone":"+32 87 56 99 70",
    "sg:postcode":"4700",
    "sg:province":"Li\u00e8ge",
    "wof:name":"Ligue Francophone De Judo",
    "wof:placetype":"venue"
},
  "geometry": {"coordinates":[6.0438370705,50.6275939941],"type":"Point"}
}