{
  "type": "Feature",
  "properties": {
    "addr:full":"Korte Nieuwstraat 12 Aalst Oost-Vlaanderen 9300",
    "addr:housenumber":"12",
    "addr:postcode":"9300",
    "addr:street":"Korte Nieuwstraat",
    "iso:country":"BE",
    "sg:address":"Korte Nieuwstraat 12",
    "sg:city":"Aalst",
    "sg:classifiers":[
        {
            "category":"Organizations",
            "subcategory":"Community Association",
            "type":"Services"
        }
    ],
    "sg:phone":"+32 53 72 94 20",
    "sg:postcode":"9300",
    "sg:province":"Oost-Vlaanderen",
    "sg:tags":[
        "environment",
        "organisation",
        "-"
    ],
    "wof:name":"Milieuboot (de)",
    "wof:placetype":"venue"
},
  "geometry": {"coordinates":[4.0355892181,50.9370765686],"type":"Point"}
}