{
  "type": "Feature",
  "properties": {
    "addr:full":"Aachenerstrasse 212 Raeren/raeren Li\u00e8ge 4730",
    "addr:housenumber":"212",
    "addr:postcode":"4730",
    "addr:street":"Aachenerstrasse",
    "iso:country":"BE",
    "sg:address":"Aachenerstrasse 212",
    "sg:city":"Raeren/raeren",
    "sg:orig_category":"Schoenen",
    "sg:phone":"+32 87 65 32 23",
    "sg:postcode":"4730",
    "sg:province":"Li\u00e8ge",
    "wof:name":"Brantano",
    "wof:placetype":"venue"
},
  "geometry": {"coordinates":[6.0901751518,50.7137184143],"type":"Point"}
}