{
  "type": "Feature",
  "properties": {
    "addr:full":"Molenstraat 6b1 Westerlo Antwerpen 2260",
    "addr:housenumber":"6b1",
    "addr:postcode":"2260",
    "addr:street":"Molenstraat",
    "iso:country":"BE",
    "sg:address":"Molenstraat 6b1",
    "sg:city":"Westerlo",
    "sg:orig_category":"Installation \u00e9lectrique r\u00e9sidentielle",
    "sg:phone":"+32 16 68 08 14",
    "sg:postcode":"2260",
    "sg:province":"Antwerpen",
    "wof:name":"Merath",
    "wof:placetype":"venue"
},
  "geometry": {"coordinates":[4.8497748375,51.0857162476],"type":"Point"}
}