{
  "type": "Feature",
  "properties": {
    "addr:full":"Schriekstraat 32 Nijlen Antwerpen 2560",
    "addr:housenumber":"32",
    "addr:postcode":"2560",
    "addr:street":"Schriekstraat",
    "iso:country":"BE",
    "sg:address":"Schriekstraat 32",
    "sg:city":"Nijlen",
    "sg:orig_category":"Quincailleries. Mat\u00e9riaux de construction Plomberie, chauffage and installations sanitaires. Charpen",
    "sg:phone":"+32 3 481 72 25",
    "sg:postcode":"2560",
    "sg:province":"Antwerpen",
    "wof:name":"Ludo Havelaerts Dakwerken",
    "wof:placetype":"venue"
},
  "geometry": {"coordinates":[4.6932740211,51.1727790833],"type":"Point"}
}