{
  "type": "Feature",
  "properties": {
    "iso:country":"BE",
    "sg:address":"Broodstraat 16",
    "sg:city":"Oudenaarde",
    "sg:orig_category":"Antiquit\u00e9s",
    "sg:phone":"+32 55 31 20 35",
    "sg:postcode":"9700",
    "sg:province":"Oost-Vlaanderen",
    "wof:name":"Huis Vanderwee\u00cbn",
    "wof:placetype":"venue"
},
  "geometry": {"coordinates":[3.6057529449,50.843132019],"type":"Point"}
}