{
  "type": "Feature",
  "properties": {
    "addr:full":"Rue Brigade Piron 353 Charleroi (montignies-sur-sambre) Hainaut 6061",
    "addr:housenumber":"353",
    "addr:postcode":"6061",
    "addr:street":"Rue Brigade Piron",
    "iso:country":"BE",
    "sg:address":"Rue Brigade Piron 353",
    "sg:city":"Charleroi (montignies-sur-sambre)",
    "sg:classifiers":[
        {
            "category":"Personal",
            "subcategory":"Barber",
            "type":"Services"
        }
    ],
    "sg:phone":"+32 71 32 05 77",
    "sg:postcode":"6061",
    "sg:province":"Hainaut",
    "sg:tags":[
        "gentleman",
        "salon",
        "-",
        "hairdressing"
    ],
    "wof:name":"Maurice",
    "wof:placetype":"venue"
},
  "geometry": {"coordinates":[4.4541201591,50.4084014893],"type":"Point"}
}