{
  "type": "Feature",
  "properties": {
    "iso:country":"BE",
    "sg:address":"Missiehuislei 25",
    "sg:city":"Kalmthout",
    "sg:orig_category":"Artsen and specialisten",
    "sg:phone":"+32 3 666 36 72",
    "sg:postcode":"2920",
    "sg:province":"Antwerpen",
    "wof:name":"Jenny F. Van Der Veer",
    "wof:placetype":"venue"
},
  "geometry": {"coordinates":[4.4699120522,51.3570594788],"type":"Point"}
}