{
  "type": "Feature",
  "properties": {
    "iso:country":"BE",
    "sg:address":"Chauss\u00e9e De Li\u00e8ge 19-20",
    "sg:city":"Plombi\u00e8res (montzen)",
    "sg:classifiers":[
        {
            "category":"Sports & Exercise",
            "subcategory":"Skate Park",
            "type":"Entertainment"
        }
    ],
    "sg:phone":"+32 87 78 64 61",
    "sg:postcode":"4850",
    "sg:province":"Li\u00e8ge",
    "sg:tags":[
        "mushroom"
    ],
    "wof:name":"Van Eys J",
    "wof:placetype":"venue"
},
  "geometry": {"coordinates":[5.9722509384,50.6980895996],"type":"Point"}
}