{
  "type": "Feature",
  "properties": {
    "addr:full":"Meensestw 168 Kortrijk West-Vlaanderen 8501",
    "addr:housenumber":"168",
    "addr:postcode":"8501",
    "iso:country":"BE",
    "sg:address":"Meensestw 168",
    "sg:city":"Kortrijk",
    "sg:classifiers":[
        {
            "category":"Manufacturing",
            "subcategory":"Metals",
            "type":"Manufacturing & Wholesale Goods"
        }
    ],
    "sg:phone":"+32 56 35 60 45",
    "sg:postcode":"8501",
    "sg:province":"West-Vlaanderen",
    "sg:tags":[
        "metallurgy",
        "-",
        "metalworking",
        "metallic",
        "machine",
        "engineering",
        "finished",
        "mechanical"
    ],
    "wof:name":"Electro Beheydt Bvba",
    "wof:placetype":"venue"
},
  "geometry": {"coordinates":[3.2336709499,50.8435592651],"type":"Point"}
}