{
  "type": "Feature",
  "properties": {
    "iso:country":"BE",
    "sg:address":"Latemstraat 79",
    "sg:city":"Sint-martens-latem",
    "sg:classifiers":[
        {
            "category":"Shopping",
            "subcategory":"Gifts & Souvenirs",
            "type":"Retail Goods"
        }
    ],
    "sg:phone":"+32 9 282 84 13",
    "sg:postcode":"9830",
    "sg:province":"Oost-Vlaanderen",
    "sg:tags":[
        "-"
    ],
    "wof:name":"Casa Nova",
    "wof:placetype":"venue"
},
  "geometry": {"coordinates":[3.6352870464,51.0176887512],"type":"Point"}
}