{
  "type": "Feature",
  "properties": {
    "addr:full":"Lijsterstraat 7 Beringen Limburg 3583",
    "addr:housenumber":"7",
    "addr:postcode":"3583",
    "addr:street":"Lijsterstraat",
    "iso:country":"BE",
    "sg:address":"Lijsterstraat 7",
    "sg:city":"Beringen",
    "sg:orig_category":"Gespecialiseerde residenti\u00eble bouw",
    "sg:phone":"+32 11 42 83 97",
    "sg:postcode":"3583",
    "sg:province":"Limburg",
    "wof:name":"Marc Gielen",
    "wof:placetype":"venue"
},
  "geometry": {"coordinates":[5.1706700325,51.0389442444],"type":"Point"}
}