{
  "type": "Feature",
  "properties": {
    "iso:country":"BE",
    "sg:address":"Kriekelaerestraat 13",
    "sg:city":"Pepingen",
    "sg:orig_category":"Eleveurs de bovins. Eleveurs and marchands de porcs",
    "sg:phone":"+32 2 356 81 88",
    "sg:postcode":"1674",
    "sg:province":"Vlaams-Brabant",
    "wof:name":"Maurits Stalpaert",
    "wof:placetype":"venue"
},
  "geometry": {"coordinates":[4.15209198,50.7413864136],"type":"Point"}
}