{
  "type": "Feature",
  "properties": {
    "addr:full":"4e Reg. Karabiniersstr. 10 Zonnebeke West-Vlaanderen 8980",
    "addr:housenumber":"10",
    "addr:postcode":"8980",
    "addr:street":"4E;Karabiniersstr.",
    "iso:country":"BE",
    "sg:address":"4e Reg. Karabiniersstr. 10",
    "sg:city":"Zonnebeke",
    "sg:orig_category":"S\u00e9curit\u00e9 sociale",
    "sg:phone":"+32 51 77 16 84",
    "sg:postcode":"8980",
    "sg:province":"West-Vlaanderen",
    "wof:name":"Christelijke Mutualiteit",
    "wof:placetype":"venue"
},
  "geometry": {"coordinates":[2.9872550964,50.8730812073],"type":"Point"}
}