{
  "type": "Feature",
  "properties": {
    "addr:full":"Hoogweg 1 Wervik West-Vlaanderen 8940",
    "addr:housenumber":"1",
    "addr:postcode":"8940",
    "addr:street":"Hoogweg",
    "iso:country":"BE",
    "sg:address":"Hoogweg 1",
    "sg:city":"Wervik",
    "sg:classifiers":[
        {
            "category":"Fast Food",
            "type":"Food & Drink"
        }
    ],
    "sg:phone":"+32 56 31 43 32",
    "sg:postcode":"8940",
    "sg:province":"West-Vlaanderen",
    "sg:tags":[
        "fried",
        "stand",
        "potato"
    ],
    "wof:name":"Bolero",
    "wof:placetype":"venue"
},
  "geometry": {"coordinates":[3.0503540039,50.7874183655],"type":"Point"}
}