{
  "type": "Feature",
  "properties": {
    "addr:full":"Rue Des M\u00c9l\u00c8zes 23 Elsene/ixelles Bruxelles-Capitale 1050",
    "addr:housenumber":"23",
    "addr:postcode":"1050",
    "addr:street":"Rue Des Me\u0301Le\u0300Zes",
    "iso:country":"BE",
    "sg:address":"Rue Des M\u00c9l\u00c8zes 23",
    "sg:city":"Elsene/ixelles",
    "sg:orig_category":"Avocats and conseillers juridiques",
    "sg:phone":"+32 2 649 68 70",
    "sg:postcode":"1050",
    "sg:province":"Bruxelles-Capitale",
    "wof:name":"Foret P.",
    "wof:placetype":"venue"
},
  "geometry": {"coordinates":[4.363904953,50.8208312988],"type":"Point"}
}