{
  "type": "Feature",
  "properties": {
    "iso:country":"BE",
    "sg:address":"Armand Hertzstraat 54",
    "sg:city":"Hasselt",
    "sg:classifiers":[
        {
            "category":"Insurance",
            "subcategory":"Life Insurance",
            "type":"Services"
        }
    ],
    "sg:phone":"+32 11 25 20 08",
    "sg:postcode":"3500",
    "sg:province":"Limburg",
    "sg:tags":[
        "assurance"
    ],
    "wof:name":"H. Box",
    "wof:placetype":"venue"
},
  "geometry": {"coordinates":[5.3343372345,50.9374847412],"type":"Point"}
}