{
  "type": "Feature",
  "properties": {
    "iso:country":"BE",
    "sg:address":"Melkerijstraat 1",
    "sg:city":"Ichtegem",
    "sg:orig_category":"Plaatsen van vloer- and muurbekleding Schilders",
    "sg:phone":"+32 51 58 32 48",
    "sg:postcode":"8480",
    "sg:province":"West-Vlaanderen",
    "wof:name":"Allary",
    "wof:placetype":"venue"
},
  "geometry": {"coordinates":[3.0139799118,51.0952339172],"type":"Point"}
}