{
  "type": "Feature",
  "properties": {
    "addr:full":"Urnestraat 28 Peer Limburg 3990",
    "addr:housenumber":"28",
    "addr:postcode":"3990",
    "addr:street":"Urnestraat",
    "iso:country":"BE",
    "sg:address":"Urnestraat 28",
    "sg:city":"Peer",
    "sg:classifiers":[
        {
            "category":"Arena",
            "subcategory":"Sports Club",
            "type":"Entertainment"
        }
    ],
    "sg:phone":"+32 11 63 34 51",
    "sg:postcode":"3990",
    "sg:province":"Limburg",
    "sg:tags":[
        "de"
    ],
    "wof:name":"M.t.b. The Power Bikers",
    "wof:placetype":"venue"
},
  "geometry": {"coordinates":[5.512720108,51.1583557129],"type":"Point"}
}