{
  "type": "Feature",
  "properties": {
    "addr:full":"Rue Du Moustier 24 Jurbise Hainaut 7050",
    "addr:housenumber":"24",
    "addr:postcode":"7050",
    "addr:street":"Rue Du Moustier",
    "iso:country":"BE",
    "sg:address":"Rue Du Moustier 24",
    "sg:city":"Jurbise",
    "sg:orig_category":"Dranken",
    "sg:phone":"+32 65 22 82 42",
    "sg:postcode":"7050",
    "sg:province":"Hainaut",
    "wof:name":"Pascal Mauroy",
    "wof:placetype":"venue"
},
  "geometry": {"coordinates":[3.9048080444,50.5329666138],"type":"Point"}
}