{
  "type": "Feature",
  "properties": {
    "iso:country":"BE",
    "sg:address":"Avenue Edouard Benes 165b4",
    "sg:city":"Bruxelles",
    "sg:orig_category":"Laboratory Equipment, Custom-Made",
    "sg:phone":"+32 3 322 52 94",
    "sg:postcode":"1080",
    "sg:province":"Bruxelles-Capitale",
    "wof:name":"Exacta B.v.b.a.",
    "wof:placetype":"venue"
},
  "geometry": {"coordinates":[4.4535717964,51.2100791931],"type":"Point"}
}