{
  "type": "Feature",
  "properties": {
    "addr:full":"Rue De L'institut Messancy Luxembourg 6780",
    "addr:postcode":"6780",
    "addr:street":"Rue De L'Institut",
    "iso:country":"BE",
    "sg:address":"Rue De L'institut",
    "sg:city":"Messancy",
    "sg:orig_category":"Supermarkten",
    "sg:postcode":"6780",
    "sg:province":"Luxembourg",
    "wof:name":"Aldi",
    "wof:placetype":"venue"
},
  "geometry": {"coordinates":[5.8070831299,49.6149902344],"type":"Point"}
}