{
  "type": "Feature",
  "properties": {
    "addr:full":"Hollestraat 53 Galmaarden Vlaams-Brabant 1570",
    "addr:housenumber":"53",
    "addr:postcode":"1570",
    "addr:street":"Hollestraat",
    "iso:country":"BE",
    "sg:address":"Hollestraat 53",
    "sg:city":"Galmaarden",
    "sg:orig_category":"Eleveurs de bovins",
    "sg:phone":"+32 54 58 80 52",
    "sg:postcode":"1570",
    "sg:province":"Vlaams-Brabant",
    "wof:name":"Karel Van Der Perre",
    "wof:placetype":"venue"
},
  "geometry": {"coordinates":[3.9938299656,50.7523384094],"type":"Point"}
}