{
  "type": "Feature",
  "properties": {
    "iso:country":"BE",
    "sg:address":"Burg. Callewaertlaan 59",
    "sg:city":"Lichtervelde",
    "sg:classifiers":[
        {
            "category":"Food & Beverages",
            "subcategory":"Fruits & Vegetables",
            "type":"Retail Goods"
        }
    ],
    "sg:phone":"+32 51 72 59 57",
    "sg:postcode":"8810",
    "sg:province":"West-Vlaanderen",
    "sg:tags":[
        "groenten"
    ],
    "wof:name":"Marnix Vergote",
    "wof:placetype":"venue"
},
  "geometry": {"coordinates":[3.1331210136,51.026676178],"type":"Point"}
}