{
  "type": "Feature",
  "properties": {
    "iso:country":"BE",
    "sg:address":"Langdorpsesteenweg 229",
    "sg:city":"Aarschot",
    "sg:orig_category":"Banken and kredietinstellingen",
    "sg:phone":"+32 16 56 48 97",
    "sg:postcode":"3201",
    "sg:province":"Vlaams-Brabant",
    "wof:name":"Centea",
    "wof:placetype":"venue"
},
  "geometry": {"coordinates":[4.8590221405,50.9931983948],"type":"Point"}
}