{
  "type": "Feature",
  "properties": {
    "addr:full":"Rue Royale 4bbis Jurbise Hainaut 7050",
    "addr:postcode":"7050",
    "addr:street":"Rue Royale",
    "iso:country":"BE",
    "sg:address":"Rue Royale 4bbis",
    "sg:city":"Jurbise",
    "sg:orig_category":"Eleveurs de bovins",
    "sg:phone":"+32 65 22 76 76",
    "sg:postcode":"7050",
    "sg:province":"Hainaut",
    "wof:name":"Christian Lannoy",
    "wof:placetype":"venue"
},
  "geometry": {"coordinates":[3.842097044,50.5458564758],"type":"Point"}
}