{
  "type": "Feature",
  "properties": {
    "iso:country":"BE",
    "sg:address":"Rue De La Costerie 2",
    "sg:city":"Clavier (bois - Et - Borsu)",
    "sg:classifiers":[
        {
            "category":"Manufacturing",
            "subcategory":"Metals",
            "type":"Manufacturing & Wholesale Goods"
        }
    ],
    "sg:phone":"+32 86 34 49 52",
    "sg:postcode":"4560",
    "sg:province":"Li\u00e8ge",
    "sg:tags":[
        "ironwork"
    ],
    "wof:name":"Atelier Tilman P",
    "wof:placetype":"venue"
},
  "geometry": {"coordinates":[5.3210220337,50.3883705139],"type":"Point"}
}