{
  "type": "Feature",
  "properties": {
    "addr:full":"Pervijzestraat 46 Diksmuide West-Vlaanderen 8600",
    "addr:housenumber":"46",
    "addr:postcode":"8600",
    "addr:street":"Pervijzestraat",
    "iso:country":"BE",
    "sg:address":"Pervijzestraat 46",
    "sg:city":"Diksmuide",
    "sg:orig_category":"Dierenartsen",
    "sg:phone":"+32 51 55 55 50",
    "sg:postcode":"8600",
    "sg:province":"West-Vlaanderen",
    "wof:name":"Joost Callebert",
    "wof:placetype":"venue"
},
  "geometry": {"coordinates":[2.8018169403,51.0519218445],"type":"Point"}
}