{
  "type": "Feature",
  "properties": {
    "addr:full":"Rozendaalstraat 12 Ieper West-Vlaanderen 8900",
    "addr:housenumber":"12",
    "addr:postcode":"8900",
    "addr:street":"Rozendaalstraat",
    "iso:country":"BE",
    "sg:address":"Rozendaalstraat 12",
    "sg:city":"Ieper",
    "sg:classifiers":[
        {
            "category":"Shopping",
            "subcategory":"Computers & Home Electronics",
            "type":"Retail Goods"
        }
    ],
    "sg:phone":"+32 57 22 61 31",
    "sg:postcode":"8900",
    "sg:province":"West-Vlaanderen",
    "sg:tags":[
        "equipment",
        "electrical",
        "component",
        "electric",
        "electronic"
    ],
    "wof:name":"Melexis Nv",
    "wof:placetype":"venue"
},
  "geometry": {"coordinates":[2.8826489449,50.8762283325],"type":"Point"}
}