{
  "type": "Feature",
  "properties": {
    "addr:full":"Stationsstraat 16 Olen Antwerpen 2250",
    "addr:housenumber":"16",
    "addr:postcode":"2250",
    "addr:street":"Stationsstraat",
    "iso:country":"BE",
    "sg:address":"Stationsstraat 16",
    "sg:city":"Olen",
    "sg:orig_category":"Newspapers, magazines, periodicals - Distribution",
    "sg:phone":"+32 14 22 66 24",
    "sg:postcode":"2250",
    "sg:province":"Antwerpen",
    "wof:name":"Snoepkrantje (het)",
    "wof:placetype":"venue"
},
  "geometry": {"coordinates":[4.904253006,51.169178009],"type":"Point"}
}