{
  "type": "Feature",
  "properties": {
    "iso:country":"BE",
    "sg:address":"Rue Du Faubourg 14",
    "sg:city":"Komen-waasten/comines-warneton",
    "sg:classifiers":[
        {
            "category":"Cafe",
            "type":"Food & Drink"
        }
    ],
    "sg:phone":"+32 56 55 81 42",
    "sg:postcode":"7780",
    "sg:province":"Hainaut",
    "sg:tags":[
        "caf\u00e9s"
    ],
    "wof:name":"Nadine Gosseye",
    "wof:placetype":"venue"
},
  "geometry": {"coordinates":[3.0025498867,50.7670783997],"type":"Point"}
}