{
  "type": "Feature",
  "properties": {
    "iso:country":"BE",
    "sg:address":"Rue Lucien Nam\u00eache 19",
    "sg:city":"Namur",
    "sg:classifiers":[
        {
            "category":"Real Estate",
            "subcategory":"Architect",
            "type":"Services"
        }
    ],
    "sg:phone":"+32 81 30 95 02",
    "sg:postcode":"5000",
    "sg:province":"Namur",
    "wof:name":"Falmagne X",
    "wof:placetype":"venue"
},
  "geometry": {"coordinates":[4.8685970306,50.4663848877],"type":"Point"}
}