{
  "type": "Feature",
  "properties": {
    "iso:country":"BE",
    "sg:address":"Place Albert I 3",
    "sg:city":"Thuin",
    "sg:classifiers":[
        {
            "category":"Bars & Pubs",
            "type":"Food & Drink"
        }
    ],
    "sg:phone":"+32 71 59 33 33",
    "sg:postcode":"6530",
    "sg:province":"Hainaut",
    "sg:tags":[
        "tavern"
    ],
    "wof:name":"Rapido (le)",
    "wof:placetype":"venue"
},
  "geometry": {"coordinates":[4.2868890762,50.3393630981],"type":"Point"}
}