{
  "type": "Feature",
  "properties": {
    "iso:country":"BE",
    "sg:address":"Edelknaapstraat 29",
    "sg:city":"Elsene (brussel)",
    "sg:orig_category":"Location de voitures",
    "sg:phone":"+32 2 538 25 91",
    "sg:postcode":"1050",
    "sg:province":"Bruxelles-Capitale",
    "wof:name":"Europcar",
    "wof:placetype":"venue"
},
  "geometry": {"coordinates":[4.3588418961,50.8236503601],"type":"Point"}
}