{
  "type": "Feature",
  "properties": {
    "addr:full":"D'oyestraat 35 Sint-truiden Limburg 3800",
    "addr:housenumber":"35",
    "addr:postcode":"3800",
    "addr:street":"D'Oyestraat",
    "iso:country":"BE",
    "sg:address":"D'oyestraat 35",
    "sg:city":"Sint-truiden",
    "sg:orig_category":"Schoonheidssalons",
    "sg:phone":"+32 11 68 48 14",
    "sg:postcode":"3800",
    "sg:province":"Limburg",
    "wof:name":"Maria Schreurs",
    "wof:placetype":"venue"
},
  "geometry": {"coordinates":[5.2494120598,50.8257408142],"type":"Point"}
}