{
  "type": "Feature",
  "properties": {
    "addr:full":"Driesstraat 121 Avelgem West-Vlaanderen 8580",
    "addr:housenumber":"121",
    "addr:postcode":"8580",
    "addr:street":"Driesstraat",
    "iso:country":"BE",
    "sg:address":"Driesstraat 121",
    "sg:city":"Avelgem",
    "sg:classifiers":[
        {
            "category":"Cafe",
            "type":"Food & Drink"
        }
    ],
    "sg:phone":"+32 56 64 56 63",
    "sg:postcode":"8580",
    "sg:province":"West-Vlaanderen",
    "sg:tags":[
        "caf\u00e9s"
    ],
    "wof:name":"Kurt Janssens",
    "wof:placetype":"venue"
},
  "geometry": {"coordinates":[3.4354529381,50.7812271118],"type":"Point"}
}