{
  "type": "Feature",
  "properties": {
    "iso:country":"BE",
    "sg:address":"Avenue Du Luxembourg 15",
    "sg:city":"Li\u00c8ge",
    "sg:orig_category":"Avocats and conseillers juridiques",
    "sg:phone":"+32 4 342 35 95",
    "sg:postcode":"4020",
    "sg:province":"Li\u00e8ge",
    "wof:name":"L. Ligot",
    "wof:placetype":"venue"
},
  "geometry": {"coordinates":[5.5844101906,50.6225967407],"type":"Point"}
}