{
  "type": "Feature",
  "properties": {
    "addr:full":"Rue Du Binet 11 Esneux Li\u00e8ge 4130",
    "addr:housenumber":"11",
    "addr:postcode":"4130",
    "addr:street":"Rue Du Binet",
    "iso:country":"BE",
    "sg:address":"Rue Du Binet 11",
    "sg:city":"Esneux",
    "sg:orig_category":"Fleurs and plantes",
    "sg:phone":"+32 4 388 31 53",
    "sg:postcode":"4130",
    "sg:province":"Li\u00e8ge",
    "wof:name":"Bouhy",
    "wof:placetype":"venue"
},
  "geometry": {"coordinates":[5.5669360161,50.5327568054],"type":"Point"}
}