{
  "type": "Feature",
  "properties": {
    "addr:full":"Tremelobaan 268 Keerbergen Vlaams-Brabant 3140",
    "addr:housenumber":"268",
    "addr:postcode":"3140",
    "addr:street":"Tremelobaan",
    "iso:country":"BE",
    "sg:address":"Tremelobaan 268",
    "sg:city":"Keerbergen",
    "sg:classifiers":[
        {
            "category":"Bakery",
            "type":"Food & Drink"
        }
    ],
    "sg:phone":"+32 16 53 57 89",
    "sg:postcode":"3140",
    "sg:province":"Vlaams-Brabant",
    "sg:tags":[
        "confectioner",
        "baker"
    ],
    "wof:name":"Croissy",
    "wof:placetype":"venue"
},
  "geometry": {"coordinates":[4.6911578178,50.9947929382],"type":"Point"}
}