{
  "type": "Feature",
  "properties": {
    "addr:full":"Oudevaartplaats 76 Antwerpen Antwerpen 2000",
    "addr:housenumber":"76",
    "addr:postcode":"2000",
    "addr:street":"Oudevaartplaats",
    "iso:country":"BE",
    "sg:address":"Oudevaartplaats 76",
    "sg:city":"Antwerpen",
    "sg:orig_category":"Rookartikelen",
    "sg:phone":"+32 3 232 04 05",
    "sg:postcode":"2000",
    "sg:province":"Antwerpen",
    "wof:name":"Walter Janssens",
    "wof:placetype":"venue"
},
  "geometry": {"coordinates":[4.4089860916,51.2130966187],"type":"Point"}
}