{
  "type": "Feature",
  "properties": {
    "iso:country":"BE",
    "sg:address":"Fazantenlaan 12",
    "sg:city":"Zandhoven",
    "sg:orig_category":"Traitements param\u00e9dicaux",
    "sg:phone":"+32 3 484 57 83",
    "sg:postcode":"2242",
    "sg:province":"Antwerpen",
    "wof:name":"P. Braeckmans",
    "wof:placetype":"venue"
},
  "geometry": {"coordinates":[4.6976280212,51.2180252075],"type":"Point"}
}