{
  "type": "Feature",
  "properties": {
    "addr:full":"Avenue Des Myrtes 12 Sint-jans-molenbeek/molenbeek-saint-jean Bruxelles-Capitale 1080",
    "addr:housenumber":"12",
    "addr:postcode":"1080",
    "addr:street":"Avenue Des Myrtes",
    "iso:country":"BE",
    "sg:address":"Avenue Des Myrtes 12",
    "sg:city":"Sint-jans-molenbeek/molenbeek-saint-jean",
    "sg:classifiers":[
        {
            "category":"Insurance",
            "subcategory":"Life Insurance",
            "type":"Services"
        }
    ],
    "sg:phone":"+32 2 465 27 49",
    "sg:postcode":"1080",
    "sg:province":"Bruxelles-Capitale",
    "sg:tags":[
        "assurance"
    ],
    "wof:name":"R. Claeys",
    "wof:placetype":"venue"
},
  "geometry": {"coordinates":[4.3052430153,50.8597068787],"type":"Point"}
}