{
  "type": "Feature",
  "properties": {
    "addr:full":"Avenue Ducp\u00c9tiaux 1 Sint-gillis/saint-gilles Bruxelles-Capitale 1060",
    "addr:housenumber":"1",
    "addr:postcode":"1060",
    "addr:street":"Avenue Ducpe\u0301Tiaux",
    "iso:country":"BE",
    "sg:address":"Avenue Ducp\u00c9tiaux 1",
    "sg:city":"Sint-gillis/saint-gilles",
    "sg:orig_category":"Epiceries",
    "sg:phone":"+32 2 538 38 73",
    "sg:postcode":"1060",
    "sg:province":"Bruxelles-Capitale",
    "wof:name":"Maison Mesa",
    "wof:placetype":"venue"
},
  "geometry": {"coordinates":[4.3535408974,50.8239097595],"type":"Point"}
}