{
  "type": "Feature",
  "properties": {
    "iso:country":"BE",
    "sg:address":"Champ Des P\u00c9trales 1b1",
    "sg:city":"Rixensart",
    "sg:orig_category":"Alternatieve geneeskunde",
    "sg:phone":"+32 2 652 04 69",
    "sg:postcode":"1332",
    "sg:province":"Brabant Wallon",
    "wof:name":"Poilvache M.d.o.",
    "wof:placetype":"venue"
},
  "geometry": {"coordinates":[4.4943752289,50.7258148193],"type":"Point"}
}