{
  "type": "Feature",
  "properties": {
    "addr:full":"Meensesteenweg 520 Roeselare West-Vlaanderen 8800",
    "addr:housenumber":"520",
    "addr:postcode":"8800",
    "addr:street":"Meensesteenweg",
    "iso:country":"BE",
    "sg:address":"Meensesteenweg 520",
    "sg:city":"Roeselare",
    "sg:classifiers":[
        {
            "category":"Home & Garden",
            "subcategory":"Kitchen Supply",
            "type":"Retail Goods"
        }
    ],
    "sg:phone":"+32 51 20 60 97",
    "sg:postcode":"8800",
    "sg:province":"West-Vlaanderen",
    "sg:tags":[
        "installation"
    ],
    "wof:name":"Vanraes Keukens Bvba",
    "wof:placetype":"venue"
},
  "geometry": {"coordinates":[3.1157040596,50.9139518738],"type":"Point"}
}