{
  "type": "Feature",
  "properties": {
    "addr:full":"Rue L\u00c9on Hachez 3 Soignies Hainaut 7060",
    "addr:housenumber":"3",
    "addr:postcode":"7060",
    "addr:street":"Rue Le\u0301On Hachez",
    "iso:country":"BE",
    "sg:address":"Rue L\u00c9on Hachez 3",
    "sg:city":"Soignies",
    "sg:orig_category":"Medische and orthopedische apparaten Opticiens",
    "sg:phone":"+32 67 34 07 87",
    "sg:postcode":"7060",
    "sg:province":"Hainaut",
    "wof:name":"Maison Vision Espace",
    "wof:placetype":"venue"
},
  "geometry": {"coordinates":[4.0702910423,50.5801048279],"type":"Point"}
}