{
  "type": "Feature",
  "properties": {
    "iso:country":"BE",
    "sg:address":"Herseltsesteenweg 63",
    "sg:city":"Aarschot",
    "sg:classifiers":[
        {
            "category":"Cafe",
            "type":"Food & Drink"
        }
    ],
    "sg:phone":"+32 495 54 53 25",
    "sg:postcode":"3200",
    "sg:province":"Vlaams-Brabant",
    "sg:tags":[
        "snack-bars"
    ],
    "wof:name":"Big Ben Hut",
    "wof:placetype":"venue"
},
  "geometry": {"coordinates":[4.83766222,50.9944114685],"type":"Point"}
}