{
  "type": "Feature",
  "properties": {
    "iso:country":"BE",
    "sg:address":"Place Jos\u00c9phine Charlotte 28",
    "sg:city":"Namur",
    "sg:orig_category":"Banken and kredietinstellingen",
    "sg:phone":"+32 81 30 18 80",
    "sg:postcode":"5100",
    "sg:province":"Namur",
    "wof:name":"Bbl",
    "wof:placetype":"venue"
},
  "geometry": {"coordinates":[4.8713750839,50.4566345215],"type":"Point"}
}