{
  "type": "Feature",
  "properties": {
    "iso:country":"BE",
    "sg:address":"Bellevuestraat 14",
    "sg:city":"Izegem",
    "sg:classifiers":[
        {
            "category":"Cafe",
            "type":"Food & Drink"
        }
    ],
    "sg:phone":"+32 51 31 43 04",
    "sg:postcode":"8870",
    "sg:province":"West-Vlaanderen",
    "sg:tags":[
        "caf\u00e9s"
    ],
    "wof:name":"Hein Dekiere",
    "wof:placetype":"venue"
},
  "geometry": {"coordinates":[3.2056350708,50.9193344116],"type":"Point"}
}