{
  "type": "Feature",
  "properties": {
    "addr:full":"Dorp-oost 69 Lochristi Oost-Vlaanderen 9080",
    "addr:housenumber":"69",
    "addr:postcode":"9080",
    "addr:street":"Dorp-Oost",
    "iso:country":"BE",
    "sg:address":"Dorp-oost 69",
    "sg:city":"Lochristi",
    "sg:orig_category":"Plaatsen van vloer- and muurbekleding Schilders",
    "sg:phone":"+32 9 355 26 75",
    "sg:postcode":"9080",
    "sg:province":"Oost-Vlaanderen",
    "wof:name":"Dirk Aelterman",
    "wof:placetype":"venue"
},
  "geometry": {"coordinates":[3.8390738964,51.0981864929],"type":"Point"}
}