{
  "type": "Feature",
  "properties": {
    "addr:full":"Kortewaagstraat 180 Menen West-Vlaanderen 8930",
    "addr:housenumber":"180",
    "addr:postcode":"8930",
    "addr:street":"Kortewaagstraat",
    "iso:country":"BE",
    "sg:address":"Kortewaagstraat 180",
    "sg:city":"Menen",
    "sg:classifiers":[
        {
            "category":"Retail",
            "subcategory":"Auto Repair",
            "type":"Services"
        }
    ],
    "sg:phone":"+32 56 51 50 70",
    "sg:postcode":"8930",
    "sg:province":"West-Vlaanderen",
    "sg:tags":[
        "garage"
    ],
    "wof:name":"Vanackere J",
    "wof:placetype":"venue"
},
  "geometry": {"coordinates":[3.1222889423,50.8270530701],"type":"Point"}
}