{
  "type": "Feature",
  "properties": {
    "iso:country":"BE",
    "sg:address":"Sur-les-march\u00c9s 162ba",
    "sg:city":"Florennes",
    "sg:orig_category":"Artsen and specialisten",
    "sg:phone":"+32 71 50 00 41",
    "sg:postcode":"5621",
    "sg:province":"Namur",
    "wof:name":"Fr\u00c9d\u00c9ric Delhaye",
    "wof:placetype":"venue"
},
  "geometry": {"coordinates":[4.5446882248,50.3094139099],"type":"Point"}
}