{
  "type": "Feature",
  "properties": {
    "iso:country":"BE",
    "sg:address":"Venlosesteenweg 16",
    "sg:city":"Maaseik",
    "sg:classifiers":[
        {
            "category":"Banks & Credit Unions",
            "subcategory":"Investment Brokerage",
            "type":"Services"
        }
    ],
    "sg:phone":"+32 89 56 40 46",
    "sg:postcode":"3680",
    "sg:province":"Limburg",
    "sg:tags":[
        "printing",
        "-"
    ],
    "wof:name":"Denis",
    "wof:placetype":"venue"
},
  "geometry": {"coordinates":[5.795211792,51.0977096558],"type":"Point"}
}