{
  "type": "Feature",
  "properties": {
    "iso:country":"BE",
    "sg:address":"Luikerstraat 72",
    "sg:city":"Sint-truiden",
    "sg:orig_category":"Chaussures",
    "sg:phone":"+32 11 68 21 23",
    "sg:postcode":"3800",
    "sg:province":"Limburg",
    "wof:name":"Rikiki",
    "wof:placetype":"venue"
},
  "geometry": {"coordinates":[5.1927480698,50.8098449707],"type":"Point"}
}