{
  "type": "Feature",
  "properties": {
    "addr:full":"Chauss\u00e9e De Charleroi 145 Anderlues Hainaut 6150",
    "addr:housenumber":"145",
    "addr:postcode":"6150",
    "addr:street":"Chausse\u0301E De Charleroi",
    "iso:country":"BE",
    "sg:address":"Chauss\u00e9e De Charleroi 145",
    "sg:city":"Anderlues",
    "sg:classifiers":[
        {
            "category":"Autos & Motor Vehicles",
            "subcategory":"Automobile Sales",
            "type":"Retail Goods"
        }
    ],
    "sg:phone":"+32 71 52 42 19",
    "sg:postcode":"6150",
    "sg:province":"Hainaut",
    "sg:tags":[
        "car",
        "used",
        "-"
    ],
    "wof:name":"Nelis-anderlues Sa",
    "wof:placetype":"venue"
},
  "geometry": {"coordinates":[4.2867498398,50.4063224792],"type":"Point"}
}