{
  "type": "Feature",
  "properties": {
    "iso:country":"BE",
    "sg:address":"Sint-gillislaan 104",
    "sg:city":"Dendermonde",
    "sg:orig_category":"Schoonheidssalons",
    "sg:phone":"+32 52 21 21 30",
    "sg:postcode":"9200",
    "sg:province":"Oost-Vlaanderen",
    "wof:name":"Beatrijs Halet",
    "wof:placetype":"venue"
},
  "geometry": {"coordinates":[4.1117238998,51.0183105469],"type":"Point"}
}