{
  "type": "Feature",
  "properties": {
    "iso:country":"BE",
    "sg:address":"Gaversesteenweg 200",
    "sg:city":"Merelbeke",
    "sg:orig_category":"Schoonheidssalons",
    "sg:phone":"+32 9 230 75 71",
    "sg:postcode":"9820",
    "sg:province":"Oost-Vlaanderen",
    "wof:name":"Gracie Myttenaere",
    "wof:placetype":"venue"
},
  "geometry": {"coordinates":[3.7372820377,50.9956855774],"type":"Point"}
}