{
  "type": "Feature",
  "properties": {
    "addr:full":"Av. K & H De Raedemaeker 11 Wemmel/wemmel Vlaams-Brabant 1780",
    "addr:housenumber":"11",
    "addr:postcode":"1780",
    "addr:street":"Av.",
    "iso:country":"BE",
    "sg:address":"Av. K & H De Raedemaeker 11",
    "sg:city":"Wemmel/wemmel",
    "sg:orig_category":"Parfumeries",
    "sg:phone":"+32 2 460 13 08",
    "sg:postcode":"1780",
    "sg:province":"Vlaams-Brabant",
    "wof:name":"Armand Hermans",
    "wof:placetype":"venue"
},
  "geometry": {"coordinates":[4.3011250496,50.9091072083],"type":"Point"}
}