{
  "type": "Feature",
  "properties": {
    "iso:country":"BE",
    "sg:address":"Grote Leiestraat 30",
    "sg:city":"Anzegem",
    "sg:classifiers":[
        {
            "category":"Real Estate",
            "subcategory":"Architect",
            "type":"Services"
        }
    ],
    "sg:phone":"+32 56 68 93 10",
    "sg:postcode":"8570",
    "sg:province":"West-Vlaanderen",
    "wof:name":"Janssens J",
    "wof:placetype":"venue"
},
  "geometry": {"coordinates":[3.4662809372,50.8468360901],"type":"Point"}
}