{
  "type": "Feature",
  "properties": {
    "iso:country":"BE",
    "sg:address":"Jacob Van Maerlantstraat 15",
    "sg:city":"Brugge",
    "sg:classifiers":[
        {
            "category":"Banks & Credit Unions",
            "subcategory":"Bureau De Change",
            "type":"Services"
        }
    ],
    "sg:phone":"+32 50 34 12 07",
    "sg:postcode":"8000",
    "sg:province":"West-Vlaanderen",
    "sg:tags":[
        "measuring",
        "control",
        "apparatus"
    ],
    "wof:name":"Calimet Bvba",
    "wof:placetype":"venue"
},
  "geometry": {"coordinates":[3.229790926,51.2284812927],"type":"Point"}
}