{
  "type": "Feature",
  "properties": {
    "addr:full":"Diestersesteenweg 55 Beringen Limburg 3583",
    "addr:housenumber":"55",
    "addr:postcode":"3583",
    "addr:street":"Diestersesteenweg",
    "iso:country":"BE",
    "sg:address":"Diestersesteenweg 55",
    "sg:city":"Beringen",
    "sg:orig_category":"Installatie van houten of kunststof schrijnwerk Installatie van metalen schrijnwerk",
    "sg:phone":"+32 11 45 50 95",
    "sg:postcode":"3583",
    "sg:province":"Limburg",
    "wof:name":"Raamprof",
    "wof:placetype":"venue"
},
  "geometry": {"coordinates":[5.1706700325,51.0389442444],"type":"Point"}
}