{
  "type": "Feature",
  "properties": {
    "iso:country":"BE",
    "sg:address":"Rue Au Beurre 23",
    "sg:city":"Brussel/bruxelles",
    "sg:classifiers":[
        {
            "category":"Banks & Credit Unions",
            "subcategory":"Financial Services",
            "type":"Services"
        }
    ],
    "sg:phone":"+32 2 511 56 30",
    "sg:postcode":"1000",
    "sg:province":"Bruxelles-Capitale",
    "sg:tags":[
        "financier"
    ],
    "wof:name":"Basle",
    "wof:placetype":"venue"
},
  "geometry": {"coordinates":[4.3512711525,50.8475799561],"type":"Point"}
}