{
  "type": "Feature",
  "properties": {
    "iso:country":"BE",
    "sg:address":"Kapelstraat 70",
    "sg:city":"Schriek",
    "sg:classifiers":[
        {
            "category":"Professional",
            "subcategory":"Engineering",
            "type":"Services"
        }
    ],
    "sg:phone":"+32 15 73 07 07",
    "sg:postcode":"2223",
    "sg:province":"Antwerpen",
    "sg:tags":[
        "road",
        "surfacing",
        "asphalt",
        "highway"
    ],
    "wof:name":"Mini-asfalt Nv",
    "wof:placetype":"venue"
},
  "geometry": {"coordinates":[4.7085762024,51.0083847046],"type":"Point"}
}