{
  "type": "Feature",
  "properties": {
    "addr:full":"Duinenstraat 20 Overpelt Limburg 3900",
    "addr:housenumber":"20",
    "addr:postcode":"3900",
    "addr:street":"Duinenstraat",
    "iso:country":"BE",
    "sg:address":"Duinenstraat 20",
    "sg:city":"Overpelt",
    "sg:orig_category":"Installation \u00e9lectrique r\u00e9sidentielle. Plomberie, chauffage and installations sanitaires",
    "sg:phone":"+32 11 66 26 44",
    "sg:postcode":"3900",
    "sg:province":"Limburg",
    "wof:name":"Marcel Loots",
    "wof:placetype":"venue"
},
  "geometry": {"coordinates":[5.411757946,51.2268333435],"type":"Point"}
}