{
  "type": "Feature",
  "properties": {
    "addr:full":"Rue De L'industrie 20 Nivelles Brabant Wallon 1400",
    "addr:housenumber":"20",
    "addr:postcode":"1400",
    "addr:street":"Rue De L'Industrie",
    "iso:country":"BE",
    "sg:address":"Rue De L'industrie 20",
    "sg:city":"Nivelles",
    "sg:classifiers":[
        {
            "category":"Building & Trades",
            "subcategory":"Construction",
            "type":"Services"
        }
    ],
    "sg:phone":"+32 71 78 68 32",
    "sg:postcode":"1400",
    "sg:province":"Brabant Wallon",
    "sg:tags":[
        "ventilating",
        "system"
    ],
    "wof:name":"Cofathec Benelux Sa",
    "wof:placetype":"venue"
},
  "geometry": {"coordinates":[4.3556470871,50.5864639282],"type":"Point"}
}