{
  "type": "Feature",
  "properties": {
    "addr:full":"Rue Du Broux 1 Beauvechain Brabant Wallon 1320",
    "addr:housenumber":"1",
    "addr:postcode":"1320",
    "addr:street":"Rue Du Broux",
    "iso:country":"BE",
    "sg:address":"Rue Du Broux 1",
    "sg:city":"Beauvechain",
    "sg:orig_category":"Woningbouw",
    "sg:phone":"+32 10 86 12 27",
    "sg:postcode":"1320",
    "sg:province":"Brabant Wallon",
    "wof:name":"Michel Calin",
    "wof:placetype":"venue"
},
  "geometry": {"coordinates":[4.7763700485,50.7783241272],"type":"Point"}
}