{
  "type": "Feature",
  "properties": {
    "addr:full":"Rue De Laubespin 69 Bruxelles Bruxelles-Capitale 1020",
    "addr:housenumber":"69",
    "addr:postcode":"1020",
    "addr:street":"Rue De Laubespin",
    "iso:country":"BE",
    "sg:address":"Rue De Laubespin 69",
    "sg:city":"Bruxelles",
    "sg:classifiers":[
        {
            "category":"Professional",
            "subcategory":"Management & Consulting",
            "type":"Services"
        }
    ],
    "sg:phone":"+32 2 479 47 26",
    "sg:postcode":"1020",
    "sg:province":"Bruxelles-Capitale",
    "sg:tags":[
        "consultant",
        "agency",
        "advertising"
    ],
    "wof:name":"Curve",
    "wof:placetype":"venue"
},
  "geometry": {"coordinates":[4.336977005,50.8870124817],"type":"Point"}
}