{
  "type": "Feature",
  "properties": {
    "addr:full":"Rue Blaes 238 Bruxelles Bruxelles-Capitale 1000",
    "addr:housenumber":"238",
    "addr:postcode":"1000",
    "addr:street":"Rue Blaes",
    "iso:country":"BE",
    "sg:address":"Rue Blaes 238",
    "sg:city":"Bruxelles",
    "sg:classifiers":[
        {
            "category":"Organizations",
            "subcategory":"Community Association",
            "type":"Services"
        }
    ],
    "sg:phone":"+32 2 502 35 69",
    "sg:postcode":"1000",
    "sg:province":"Bruxelles-Capitale",
    "sg:tags":[
        "cultural"
    ],
    "wof:name":"Artomanie",
    "wof:placetype":"venue"
},
  "geometry": {"coordinates":[4.3441438675,50.8349227905],"type":"Point"}
}