{
  "type": "Feature",
  "properties": {
    "iso:country":"BE",
    "sg:address":"Oudenburgsesteenweg 1",
    "sg:city":"Oostende",
    "sg:orig_category":"Herstellingen and onderhoud van auto's",
    "sg:phone":"+32 59 70 60 60",
    "sg:postcode":"8400",
    "sg:province":"West-Vlaanderen",
    "wof:name":"Garage Ingehelbrecht",
    "wof:placetype":"venue"
},
  "geometry": {"coordinates":[2.9511950016,51.2206382751],"type":"Point"}
}