{
  "type": "Feature",
  "properties": {
    "iso:country":"BE",
    "sg:address":"Drongensveldweg 4",
    "sg:city":"Meulebeke",
    "sg:orig_category":"Solar protection - Outside",
    "sg:phone":"+32 51 40 05 39",
    "sg:postcode":"8760",
    "sg:province":"West-Vlaanderen",
    "wof:name":"D\u00e9.m.l.",
    "wof:placetype":"venue"
},
  "geometry": {"coordinates":[3.3206000328,50.9681549072],"type":"Point"}
}