{
  "type": "Feature",
  "properties": {
    "iso:country":"BE",
    "sg:address":"Rue Du Bois Du Sart 20",
    "sg:city":"Amay",
    "sg:orig_category":"Eleveurs de bovins",
    "sg:phone":"+32 85 31 11 95",
    "sg:postcode":"4540",
    "sg:province":"Li\u00e8ge",
    "wof:name":"Andre Duchesne",
    "wof:placetype":"venue"
},
  "geometry": {"coordinates":[5.2831487656,50.5552558899],"type":"Point"}
}