{
  "type": "Feature",
  "properties": {
    "addr:full":"Fraiture 35 Vielsalm Luxembourg 6690",
    "addr:housenumber":"35",
    "addr:postcode":"6690",
    "addr:street":"Fraiture",
    "iso:country":"BE",
    "sg:address":"Fraiture 35",
    "sg:city":"Vielsalm",
    "sg:orig_category":"Rundveehouders Varkenskwekers",
    "sg:phone":"+32 80 41 87 77",
    "sg:postcode":"6690",
    "sg:province":"Luxembourg",
    "wof:name":"Victor Boulanger",
    "wof:placetype":"venue"
},
  "geometry": {"coordinates":[5.7267398834,50.2556724548],"type":"Point"}
}