{
  "type": "Feature",
  "properties": {
    "addr:full":"Onze-lieve-vrouwplein 66 Herent Vlaams-Brabant 3020",
    "addr:housenumber":"66",
    "addr:postcode":"3020",
    "addr:street":"Onze-Lieve-Vrouwplein",
    "iso:country":"BE",
    "sg:address":"Onze-lieve-vrouwplein 66",
    "sg:city":"Herent",
    "sg:orig_category":"Plaatsen van vloer- and muurbekleding Schilders Textiel Verlichting and huishoudartikelen Vloer- and",
    "sg:phone":"+32 16 22 59 42",
    "sg:postcode":"3020",
    "sg:province":"Vlaams-Brabant",
    "wof:name":"Craps & Zn",
    "wof:placetype":"venue"
},
  "geometry": {"coordinates":[4.6742548943,50.9073753357],"type":"Point"}
}