{
  "type": "Feature",
  "properties": {
    "addr:full":"Rue Des Echevins 1 Bruxelles (ixelles) Bruxelles-Capitale 1050",
    "addr:housenumber":"1",
    "addr:postcode":"1050",
    "addr:street":"Rue Des Echevins",
    "iso:country":"BE",
    "sg:address":"Rue Des Echevins 1",
    "sg:city":"Bruxelles (ixelles)",
    "sg:classifiers":[
        {
            "category":"Personal",
            "subcategory":"Beauty Salon",
            "type":"Services"
        }
    ],
    "sg:phone":"+32 2 647 64 03",
    "sg:postcode":"1050",
    "sg:province":"Bruxelles-Capitale",
    "sg:tags":[
        "lady",
        "-",
        "hairdressing"
    ],
    "wof:name":"Guy",
    "wof:placetype":"venue"
},
  "geometry": {"coordinates":[4.37606287,50.8237304688],"type":"Point"}
}