{
  "type": "Feature",
  "properties": {
    "iso:country":"BE",
    "sg:address":"Kleine Moerstraat 7",
    "sg:city":"Evergem",
    "sg:orig_category":"D\u00e9m\u00e9nagements. Fruits and l\u00e9gumes Transports routiers de marchandises",
    "sg:phone":"+32 9 253 55 00",
    "sg:postcode":"9940",
    "sg:province":"Oost-Vlaanderen",
    "wof:name":"Transport De Decker G",
    "wof:placetype":"venue"
},
  "geometry": {"coordinates":[3.6555969715,51.1011428833],"type":"Point"}
}