{
  "type": "Feature",
  "properties": {
    "addr:full":"Moleneinde 16 Evergem Oost-Vlaanderen 9940",
    "addr:housenumber":"16",
    "addr:postcode":"9940",
    "addr:street":"Moleneinde;Oost-Vlaanderen",
    "iso:country":"BE",
    "sg:address":"Moleneinde 16",
    "sg:city":"Evergem",
    "sg:classifiers":[
        {
            "category":"Home & Garden",
            "subcategory":"Home Furnishings",
            "type":"Retail Goods"
        }
    ],
    "sg:phone":"+32 9 357 32 28",
    "sg:postcode":"9940",
    "sg:province":"Oost-Vlaanderen",
    "sg:tags":[
        "part",
        "upholstery"
    ],
    "wof:name":"Bral L",
    "wof:placetype":"venue"
},
  "geometry": {"coordinates":[3.6733469963,51.1029891968],"type":"Point"}
}