{
  "type": "Feature",
  "properties": {
    "iso:country":"BE",
    "sg:address":"Menenstraat 22",
    "sg:city":"Sint-jans-molenbeek/molenbeek-saint-jean",
    "sg:orig_category":"Schoenen",
    "sg:phone":"+32 2 411 91 11",
    "sg:postcode":"1080",
    "sg:province":"Bruxelles-Capitale",
    "wof:name":"Trade Promotion Service",
    "wof:placetype":"venue"
},
  "geometry": {"coordinates":[4.3285150528,50.8560638428],"type":"Point"}
}