{
  "type": "Feature",
  "properties": {
    "addr:full":"Kaai 4 Diest Vlaams-Brabant 3290",
    "addr:housenumber":"4",
    "addr:postcode":"3290",
    "addr:street":"Kaai",
    "iso:country":"BE",
    "sg:address":"Kaai 4",
    "sg:city":"Diest",
    "sg:classifiers":[
        {
            "category":"Bars & Pubs",
            "type":"Food & Drink"
        }
    ],
    "sg:phone":"+32 13 32 63 41",
    "sg:postcode":"3290",
    "sg:province":"Vlaams-Brabant",
    "wof:name":"Puur Genot('t)",
    "wof:placetype":"venue"
},
  "geometry": {"coordinates":[5.0492148399,50.9847068787],"type":"Point"}
}