{
  "type": "Feature",
  "properties": {
    "iso:country":"BE",
    "sg:address":"Rue De Bertinchamps 4",
    "sg:city":"Gembloux",
    "sg:classifiers":[
        {
            "category":"Sports & Exercise",
            "subcategory":"Sports Center",
            "type":"Entertainment"
        }
    ],
    "sg:phone":"+32 81 63 36 63",
    "sg:postcode":"5032",
    "sg:province":"Namur",
    "sg:tags":[
        "terrain",
        "hors",
        "de",
        "installation",
        "sportifs"
    ],
    "wof:name":"Bertinchamps Kid's Club",
    "wof:placetype":"venue"
},
  "geometry": {"coordinates":[4.738424778,50.5091285706],"type":"Point"}
}