{
  "type": "Feature",
  "properties": {
    "addr:full":"Bogaerdestraat 25a Zoutleeuw Vlaams-Brabant 3440",
    "addr:housenumber":"25a",
    "addr:postcode":"3440",
    "addr:street":"Bogaerdestraat;Vlaams-Brabant",
    "iso:country":"BE",
    "sg:address":"Bogaerdestraat 25a",
    "sg:city":"Zoutleeuw",
    "sg:classifiers":[
        {
            "category":"Personal",
            "subcategory":"Beauty Salon",
            "type":"Services"
        }
    ],
    "sg:phone":"+32 11 78 01 32",
    "sg:postcode":"3440",
    "sg:province":"Vlaams-Brabant",
    "sg:tags":[
        "de",
        "coiffure"
    ],
    "wof:name":"Maria Boyen",
    "wof:placetype":"venue"
},
  "geometry": {"coordinates":[5.1042709351,50.835018158],"type":"Point"}
}