{
  "type": "Feature",
  "properties": {
    "iso:country":"BE",
    "sg:address":"Marie-jos\u00c9laan 78",
    "sg:city":"Sint-lambrechts-woluwe/woluwe-saint-lambert",
    "sg:orig_category":"Boekbinderijen and afwerking",
    "sg:phone":"+32 2 733 31 64",
    "sg:postcode":"1200",
    "sg:province":"Bruxelles-Capitale",
    "wof:name":"Baudouin De Briey",
    "wof:placetype":"venue"
},
  "geometry": {"coordinates":[4.4103860855,50.8452644348],"type":"Point"}
}