{
  "type": "Feature",
  "properties": {
    "addr:full":"Visserskaai 12 Oostende West-Vlaanderen 8400",
    "addr:housenumber":"12",
    "addr:postcode":"8400",
    "addr:street":"Visserskaai",
    "iso:country":"BE",
    "sg:address":"Visserskaai 12",
    "sg:city":"Oostende",
    "sg:classifiers":[
        {
            "category":"Restaurant",
            "type":"Food & Drink"
        }
    ],
    "sg:phone":"+32 59 70 35 69",
    "sg:postcode":"8400",
    "sg:province":"West-Vlaanderen",
    "wof:name":"'t Galjoen",
    "wof:placetype":"venue"
},
  "geometry": {"coordinates":[2.9228909016,51.2311897278],"type":"Point"}
}