{
  "type": "Feature",
  "properties": {
    "addr:full":"Dorpsstraat 133 Stekene Oost-Vlaanderen 9190",
    "addr:housenumber":"133",
    "addr:postcode":"9190",
    "addr:street":"Dorpsstraat",
    "iso:country":"BE",
    "sg:address":"Dorpsstraat 133",
    "sg:city":"Stekene",
    "sg:classifiers":[
        {
            "category":"Bars & Pubs",
            "type":"Food & Drink"
        }
    ],
    "sg:phone":"+32 3 779 75 09",
    "sg:postcode":"9190",
    "sg:province":"Oost-Vlaanderen",
    "wof:name":"Bridge (den)",
    "wof:placetype":"venue"
},
  "geometry": {"coordinates":[4.038670063,51.2035903931],"type":"Point"}
}