{
  "type": "Feature",
  "properties": {
    "iso:country":"BE",
    "sg:address":"Rue Des Tombes 39",
    "sg:city":"Wanze (antheit)",
    "sg:classifiers":[
        {
            "category":"Health Services",
            "subcategory":"Nursing And Care Facility",
            "type":"Services"
        }
    ],
    "sg:phone":"+32 85 23 01 39",
    "sg:postcode":"4520",
    "sg:province":"Li\u00e8ge",
    "sg:tags":[
        "home"
    ],
    "wof:name":"Blehen-develeer C",
    "wof:placetype":"venue"
},
  "geometry": {"coordinates":[5.2285780907,50.5520935059],"type":"Point"}
}