{
  "type": "Feature",
  "properties": {
    "addr:full":"Lakerweg 58 Kinrooi Limburg 3640",
    "addr:housenumber":"58",
    "addr:postcode":"3640",
    "addr:street":"Lakerweg",
    "iso:country":"BE",
    "sg:address":"Lakerweg 58",
    "sg:city":"Kinrooi",
    "sg:classifiers":[
        {
            "category":"Tea Room",
            "subcategory":"None",
            "type":"Food & Drink"
        }
    ],
    "sg:phone":"+32 89 70 33 61",
    "sg:postcode":"3640",
    "sg:province":"Limburg",
    "wof:name":"Stampertje ('t)",
    "wof:placetype":"venue"
},
  "geometry": {"coordinates":[5.7721529007,51.1455421448],"type":"Point"}
}