{
  "type": "Feature",
  "properties": {
    "addr:full":"Dorpsstraat 65 Wuustwezel Antwerpen 2990",
    "addr:housenumber":"65",
    "addr:postcode":"2990",
    "addr:street":"Dorpsstraat",
    "iso:country":"BE",
    "sg:address":"Dorpsstraat 65",
    "sg:city":"Wuustwezel",
    "sg:classifiers":[
        {
            "category":"Health Services",
            "subcategory":"Dentist",
            "type":"Services"
        }
    ],
    "sg:phone":"+32 3 669 60 32",
    "sg:postcode":"2990",
    "sg:province":"Antwerpen",
    "wof:name":"Mennes Luc",
    "wof:placetype":"venue"
},
  "geometry": {"coordinates":[4.5957398415,51.3883247375],"type":"Point"}
}