{
  "type": "Feature",
  "properties": {
    "addr:full":"Rue Des Campanules 12 Seraing (ougr\u00e9e) Li\u00e8ge 4102",
    "addr:housenumber":"12",
    "addr:postcode":"4102",
    "addr:street":"Rue Des Campanules",
    "iso:country":"BE",
    "sg:address":"Rue Des Campanules 12",
    "sg:city":"Seraing (ougr\u00e9e)",
    "sg:classifiers":[
        {
            "category":"Health Services",
            "subcategory":"Health Practitioner",
            "type":"Services"
        }
    ],
    "sg:phone":"+32 4 336 44 12",
    "sg:postcode":"4102",
    "sg:province":"Li\u00e8ge",
    "sg:tags":[
        "physiotherapist"
    ],
    "wof:name":"Jasselette Luc",
    "wof:placetype":"venue"
},
  "geometry": {"coordinates":[5.5412859917,50.5875892639],"type":"Point"}
}