{
  "type": "Feature",
  "properties": {
    "iso:country":"BE",
    "sg:address":"Diestsestraat 175",
    "sg:city":"Leuven",
    "sg:orig_category":"Brood, gebak and snoepgoed Speelgoed",
    "sg:phone":"+32 16 22 57 61",
    "sg:postcode":"3000",
    "sg:province":"Vlaams-Brabant",
    "wof:name":"Toys 4 All",
    "wof:placetype":"venue"
},
  "geometry": {"coordinates":[4.7097201347,50.8815612793],"type":"Point"}
}