{
  "type": "Feature",
  "properties": {
    "addr:full":"Kasteelstraat 13 Hoeilaart Vlaams-Brabant 1560",
    "addr:housenumber":"13",
    "addr:postcode":"1560",
    "addr:street":"Kasteelstraat",
    "iso:country":"BE",
    "sg:address":"Kasteelstraat 13",
    "sg:city":"Hoeilaart",
    "sg:classifiers":[
        {
            "category":"Arena",
            "subcategory":"Sports Club",
            "type":"Entertainment"
        }
    ],
    "sg:phone":"+32 2 657 44 15",
    "sg:postcode":"1560",
    "sg:province":"Vlaams-Brabant",
    "sg:tags":[
        "de"
    ],
    "wof:name":"Judoclub Budo No-ki",
    "wof:placetype":"venue"
},
  "geometry": {"coordinates":[4.4682650566,50.7657775879],"type":"Point"}
}