{
  "type": "Feature",
  "properties": {
    "iso:country":"BE",
    "sg:address":"Schoolstraat 22",
    "sg:city":"Erpe-mere",
    "sg:orig_category":"Airconditioning and ventilatie Loodgieterij and centrale verwarming Gh",
    "sg:phone":"+32 53 83 35 06",
    "sg:postcode":"9420",
    "sg:province":"Oost-Vlaanderen",
    "wof:name":"aero",
    "wof:placetype":"venue"
},
  "geometry": {"coordinates":[3.9723420143,50.9128494263],"type":"Point"}
}