{
  "type": "Feature",
  "properties": {
    "iso:country":"BE",
    "sg:address":"Kerkplein 18",
    "sg:city":"Melsele",
    "sg:classifiers":[
        {
            "category":"Professional",
            "subcategory":"Advertising",
            "type":"Services"
        }
    ],
    "sg:phone":"+32 3 755 65 39",
    "sg:postcode":"9120",
    "sg:province":"Oost-Vlaanderen",
    "sg:tags":[
        "product-related",
        "article",
        "marzipan",
        "chocolate"
    ],
    "wof:name":"Stevens Brood & Banket B.v.b.a.",
    "wof:placetype":"venue"
},
  "geometry": {"coordinates":[4.280921936,51.2222938538],"type":"Point"}
}