{
  "type": "Feature",
  "properties": {
    "addr:full":"Klaverhulleweg 5 Heuvelland West-Vlaanderen 8953",
    "addr:housenumber":"5",
    "addr:postcode":"8953",
    "addr:street":"Klaverhulleweg",
    "iso:country":"BE",
    "sg:address":"Klaverhulleweg 5",
    "sg:city":"Heuvelland",
    "sg:orig_category":"Eleveurs de bovins",
    "sg:phone":"+32 57 44 45 74",
    "sg:postcode":"8953",
    "sg:province":"West-Vlaanderen",
    "wof:name":"Wilfried Sinnaeve",
    "wof:placetype":"venue"
},
  "geometry": {"coordinates":[2.8796629906,50.7801475525],"type":"Point"}
}