{
  "type": "Feature",
  "properties": {
    "iso:country":"BE",
    "sg:address":"Olfkenskouterlaan 6",
    "sg:city":"Melle",
    "sg:orig_category":"Experts-comptables",
    "sg:phone":"+32 9 231 72 59",
    "sg:postcode":"9090",
    "sg:province":"Oost-Vlaanderen",
    "wof:name":"Vermussche D.",
    "wof:placetype":"venue"
},
  "geometry": {"coordinates":[3.770401001,51.0140151978],"type":"Point"}
}