{
  "type": "Feature",
  "properties": {
    "iso:country":"BE",
    "sg:address":"Rue Du Belv\u00e9d\u00e8re 1",
    "sg:city":"Martelange",
    "sg:classifiers":[
        {
            "category":"Health Services",
            "subcategory":"Health Practitioner",
            "type":"Services"
        }
    ],
    "sg:phone":"+32 63 60 16 59",
    "sg:postcode":"6630",
    "sg:province":"Luxembourg",
    "sg:tags":[
        "therapist",
        "speech"
    ],
    "wof:name":"Dernoeden C",
    "wof:placetype":"venue"
},
  "geometry": {"coordinates":[5.7334489822,49.832862854],"type":"Point"}
}