{
  "type": "Feature",
  "properties": {
    "addr:full":"Brugsesteenweg 10 Roeselare West-Vlaanderen 8800",
    "addr:housenumber":"10",
    "addr:postcode":"8800",
    "addr:street":"Brugsesteenweg",
    "iso:country":"BE",
    "sg:address":"Brugsesteenweg 10",
    "sg:city":"Roeselare",
    "sg:classifiers":[
        {
            "category":"Restaurant",
            "type":"Food & Drink"
        }
    ],
    "sg:phone":"+32 51 22 01 67",
    "sg:postcode":"8800",
    "sg:province":"West-Vlaanderen",
    "wof:name":"El Greco",
    "wof:placetype":"venue"
},
  "geometry": {"coordinates":[3.1209390163,50.9518165588],"type":"Point"}
}