{
  "type": "Feature",
  "properties": {
    "iso:country":"BE",
    "sg:address":"Rue Des Rubaniers 3",
    "sg:city":"Comines-warneton",
    "sg:orig_category":"Meubles D\u00e9taillants, Am\u00e9nagement de B\u00e2timents et de Cuisines",
    "sg:phone":"+32 56 55 49 49",
    "sg:postcode":"7780",
    "sg:province":"Hainaut",
    "wof:name":"Tremmer & New Concorde",
    "wof:placetype":"venue"
},
  "geometry": {"coordinates":[3.008286953,50.7827072144],"type":"Point"}
}