{
  "type": "Feature",
  "properties": {
    "addr:full":"Rue De La Grenouillette 22h Bruxelles Bruxelles-Capitale 1130",
    "addr:housenumber":"22h",
    "addr:postcode":"1130",
    "addr:street":"Rue De La Grenouillette",
    "iso:country":"BE",
    "sg:address":"Rue De La Grenouillette 22h",
    "sg:city":"Bruxelles",
    "sg:classifiers":[
        {
            "category":"Building & Trades",
            "subcategory":"Pest Control",
            "type":"Services"
        }
    ],
    "sg:phone":"+32 2 245 60 43",
    "sg:postcode":"1130",
    "sg:province":"Bruxelles-Capitale",
    "sg:tags":[
        "machine",
        "vending"
    ],
    "wof:name":"Tabaccomat Sa",
    "wof:placetype":"venue"
},
  "geometry": {"coordinates":[4.4172420502,50.8834724426],"type":"Point"}
}