{
  "type": "Feature",
  "properties": {
    "iso:country":"BE",
    "sg:address":"'s Gravenwinkelstraat 7",
    "sg:city":"Torhout",
    "sg:classifiers":[
        {
            "category":"Personal",
            "subcategory":"Beauty Salon",
            "type":"Services"
        }
    ],
    "sg:phone":"+32 50 21 12 96",
    "sg:postcode":"8820",
    "sg:province":"West-Vlaanderen",
    "wof:name":"Charme",
    "wof:placetype":"venue"
},
  "geometry": {"coordinates":[3.0999910831,51.0674476624],"type":"Point"}
}