{
  "type": "Feature",
  "properties": {
    "addr:full":"Place Communale 4ba Silly Hainaut 7830",
    "addr:postcode":"7830",
    "addr:street":"Place Communale 4Ba",
    "iso:country":"BE",
    "sg:address":"Place Communale 4ba",
    "sg:city":"Silly",
    "sg:orig_category":"Epiceries",
    "sg:phone":"+32 68 55 13 73",
    "sg:postcode":"7830",
    "sg:province":"Hainaut",
    "wof:name":"Jos\u00c9e R\u00c9my",
    "wof:placetype":"venue"
},
  "geometry": {"coordinates":[3.9235730171,50.6486282349],"type":"Point"}
}