{
  "type": "Feature",
  "properties": {
    "addr:full":"Grote Steenweg 60 Linter Vlaams-Brabant 3350",
    "addr:housenumber":"60",
    "addr:postcode":"3350",
    "addr:street":"Grote Steenweg;Vlaams-Brabant",
    "iso:country":"BE",
    "sg:address":"Grote Steenweg 60",
    "sg:city":"Linter",
    "sg:orig_category":"Epiceries",
    "sg:phone":"+32 11 78 12 79",
    "sg:postcode":"3350",
    "sg:province":"Vlaams-Brabant",
    "wof:name":"Prima",
    "wof:placetype":"venue"
},
  "geometry": {"coordinates":[5.0346398354,50.841129303],"type":"Point"}
}