{
  "type": "Feature",
  "properties": {
    "iso:country":"BE",
    "sg:address":"Rue Du Carme 21",
    "sg:city":"Beloeil",
    "sg:orig_category":"Schoonheidssalons",
    "sg:phone":"+32 69 57 69 34",
    "sg:postcode":"7971",
    "sg:province":"Hainaut",
    "wof:name":"Michelle Verdonck",
    "wof:placetype":"venue"
},
  "geometry": {"coordinates":[3.6464340687,50.522190094],"type":"Point"}
}