{
  "type": "Feature",
  "properties": {
    "iso:country":"BE",
    "sg:address":"Rue Duch\u00eane 13",
    "sg:city":"Neupr\u00e9 (rotheux-rimi\u00e8re)",
    "sg:classifiers":[
        {
            "category":"Community Center",
            "type":"Public Place"
        }
    ],
    "sg:phone":"+32 475 64 32 41",
    "sg:postcode":"4120",
    "sg:province":"Li\u00e8ge",
    "sg:tags":[
        "medical"
    ],
    "wof:name":"Neupr\u00e9 Sant\u00e9 Nandrin",
    "wof:placetype":"venue"
},
  "geometry": {"coordinates":[5.4838118553,50.5361213684],"type":"Point"}
}