{
  "type": "Feature",
  "properties": {
    "addr:full":"Bormtestraat 159 Stekene Oost-Vlaanderen 9190",
    "addr:housenumber":"159",
    "addr:postcode":"9190",
    "addr:street":"Bormtestraat",
    "iso:country":"BE",
    "sg:address":"Bormtestraat 159",
    "sg:city":"Stekene",
    "sg:classifiers":[
        {
            "category":"Personal",
            "subcategory":"Beauty Salon",
            "type":"Services"
        }
    ],
    "sg:phone":"+32 3 789 00 99",
    "sg:postcode":"9190",
    "sg:province":"Oost-Vlaanderen",
    "sg:tags":[
        "lady",
        "-",
        "hairdressing"
    ],
    "wof:name":"Tamara's Haarmode",
    "wof:placetype":"venue"
},
  "geometry": {"coordinates":[4.0503640175,51.1984863281],"type":"Point"}
}