{
  "type": "Feature",
  "properties": {
    "iso:country":"BE",
    "sg:address":"Gildenplein 6",
    "sg:city":"Houthalen-helchteren",
    "sg:orig_category":"DIVERSE RECREATIEVE ACTIVITEITEN",
    "sg:phone":"+32 11 60 33 76",
    "sg:postcode":"3530",
    "sg:province":"Limburg",
    "wof:name":"B.c. Molenheide",
    "wof:placetype":"venue"
},
  "geometry": {"coordinates":[5.3964138031,51.0285835266],"type":"Point"}
}