{
  "type": "Feature",
  "properties": {
    "iso:country":"BE",
    "sg:address":"Spinnerijstraat 15",
    "sg:city":"Berlare",
    "sg:classifiers":[
        {
            "category":"Food & Beverages",
            "subcategory":"Specialty",
            "type":"Retail Goods"
        }
    ],
    "sg:phone":"+32 52 42 33 82",
    "sg:postcode":"9290",
    "sg:province":"Oost-Vlaanderen",
    "sg:tags":[
        "health",
        "dietary",
        "-",
        "biological"
    ],
    "wof:name":"Hellemans",
    "wof:placetype":"venue"
},
  "geometry": {"coordinates":[3.9986400604,51.0240859985],"type":"Point"}
}