{
  "type": "Feature",
  "properties": {
    "addr:full":"Kartuizersvest 113 Lier Antwerpen 2500",
    "addr:housenumber":"113",
    "addr:postcode":"2500",
    "addr:street":"Kartuizersvest",
    "iso:country":"BE",
    "sg:address":"Kartuizersvest 113",
    "sg:city":"Lier",
    "sg:classifiers":[
        {
            "category":"Restaurant",
            "type":"Food & Drink"
        }
    ],
    "sg:phone":"+32 3 488 47 09",
    "sg:postcode":"2500",
    "sg:province":"Antwerpen",
    "wof:name":"Minos Palace",
    "wof:placetype":"venue"
},
  "geometry": {"coordinates":[4.5710220337,51.1349449158],"type":"Point"}
}