{
  "type": "Feature",
  "properties": {
    "addr:full":"Rue Henri Baron 12 Li\u00e8ge 1 Li\u00e8ge 4000",
    "addr:housenumber":"12;1",
    "addr:postcode":"4000",
    "addr:street":"Rue Henri Baron",
    "iso:country":"BE",
    "sg:address":"Rue Henri Baron 12",
    "sg:city":"Li\u00e8ge 1",
    "sg:classifiers":[
        {
            "category":"Recreation",
            "subcategory":"Fishing",
            "type":"Entertainment"
        }
    ],
    "sg:phone":"+32 4 226 58 59",
    "sg:postcode":"4000",
    "sg:province":"Li\u00e8ge",
    "sg:tags":[
        "tackle"
    ],
    "wof:name":"Patricia (chez)",
    "wof:placetype":"venue"
},
  "geometry": {"coordinates":[5.5532460213,50.6472091675],"type":"Point"}
}