{
  "type": "Feature",
  "properties": {
    "addr:full":"Chauss\u00e9e D'antoing 2 Tournai Hainaut 7500",
    "addr:housenumber":"2",
    "addr:postcode":"7500",
    "addr:street":"Chausse\u0301E D'Antoing",
    "iso:country":"BE",
    "sg:address":"Chauss\u00e9e D'antoing 2",
    "sg:city":"Tournai",
    "sg:classifiers":[
        {
            "category":"Bars & Pubs",
            "type":"Food & Drink"
        }
    ],
    "sg:phone":"+32 69 22 07 09",
    "sg:postcode":"7500",
    "sg:province":"Hainaut",
    "wof:name":"Auberge De Valenciennes",
    "wof:placetype":"venue"
},
  "geometry": {"coordinates":[3.4011371136,50.5988197327],"type":"Point"}
}