{
  "type": "Feature",
  "properties": {
    "addr:full":"Dikke-beuklaan 76 Jette Bruxelles-Capitale 1090",
    "addr:housenumber":"76",
    "addr:postcode":"1090",
    "addr:street":"Dikke-Beuklaan",
    "iso:country":"BE",
    "sg:address":"Dikke-beuklaan 76",
    "sg:city":"Jette",
    "sg:orig_category":"Artsen and specialisten",
    "sg:phone":"+32 2 478 86 92",
    "sg:postcode":"1090",
    "sg:province":"Bruxelles-Capitale",
    "wof:name":"Pascal Wauters",
    "wof:placetype":"venue"
},
  "geometry": {"coordinates":[4.3116240501,50.8923110962],"type":"Point"}
}