{
  "type": "Feature",
  "properties": {
    "addr:full":"Rozenlaan 11 Rumst Antwerpen 2840",
    "addr:housenumber":"11",
    "addr:postcode":"2840",
    "addr:street":"Rozenlaan",
    "iso:country":"BE",
    "sg:address":"Rozenlaan 11",
    "sg:city":"Rumst",
    "sg:orig_category":"Dierentuinen, botanische tuinen, sterrenwachten and natuurreservaten",
    "sg:phone":"+32 3 844 24 38",
    "sg:postcode":"2840",
    "sg:province":"Antwerpen",
    "wof:name":"Arboretum Van Rumst",
    "wof:placetype":"venue"
},
  "geometry": {"coordinates":[4.3883509636,51.1052131653],"type":"Point"}
}