{
  "type": "Feature",
  "properties": {
    "addr:full":"Gasstraat 150 Antwerpen Antwerpen 2060",
    "addr:housenumber":"150",
    "addr:postcode":"2060",
    "addr:street":"Gasstraat",
    "iso:country":"BE",
    "sg:address":"Gasstraat 150",
    "sg:city":"Antwerpen",
    "sg:classifiers":[
        {
            "category":"Shopping",
            "subcategory":"Computers & Home Electronics",
            "type":"Retail Goods"
        }
    ],
    "sg:phone":"+32 3 234 30 40",
    "sg:postcode":"2060",
    "sg:province":"Antwerpen",
    "sg:tags":[
        "plate",
        "name"
    ],
    "wof:name":"Alugrav",
    "wof:placetype":"venue"
},
  "geometry": {"coordinates":[4.426197052,51.2233581543],"type":"Point"}
}