{
  "type": "Feature",
  "properties": {
    "addr:full":"Rue D'audenarde 14bc Ellezelles Hainaut 7890",
    "addr:housenumber":"14bc",
    "addr:postcode":"7890",
    "addr:street":"Rue D'Audenarde",
    "iso:country":"BE",
    "sg:address":"Rue D'audenarde 14bc",
    "sg:city":"Ellezelles",
    "sg:classifiers":[
        {
            "category":"Insurance",
            "subcategory":"Insurance Agent",
            "type":"Services"
        }
    ],
    "sg:phone":"+32 68 54 31 31",
    "sg:postcode":"7890",
    "sg:province":"Hainaut",
    "sg:tags":[
        "verzekeringsmakelaars",
        "expert"
    ],
    "wof:name":"Fagnard",
    "wof:placetype":"venue"
},
  "geometry": {"coordinates":[3.6821789742,50.7357559204],"type":"Point"}
}