{
  "type": "Feature",
  "properties": {
    "addr:full":"Rue Du Bois 10 Habay Luxembourg 6724",
    "addr:housenumber":"10",
    "addr:postcode":"6724",
    "addr:street":"Rue Du Bois",
    "iso:country":"BE",
    "sg:address":"Rue Du Bois 10",
    "sg:city":"Habay",
    "sg:orig_category":"Charpentes and couvertures",
    "sg:phone":"+32 63 41 13 45",
    "sg:postcode":"6724",
    "sg:province":"Luxembourg",
    "wof:name":"Remience",
    "wof:placetype":"venue"
},
  "geometry": {"coordinates":[5.5588588715,49.7208442688],"type":"Point"}
}