{
  "type": "Feature",
  "properties": {
    "iso:country":"BE",
    "sg:address":"Industrieweg 137",
    "sg:city":"Beringen (paal)",
    "sg:classifiers":[
        {
            "category":"Building & Trades",
            "subcategory":"Pest Control",
            "type":"Services"
        }
    ],
    "sg:phone":"+32 11 45 01 45",
    "sg:postcode":"3583",
    "sg:province":"Limburg",
    "sg:tags":[
        "drive",
        "chain"
    ],
    "wof:name":"Gunnebo Lifting-s.k.p.",
    "wof:placetype":"venue"
},
  "geometry": {"coordinates":[5.1706700325,51.0389442444],"type":"Point"}
}