{
  "type": "Feature",
  "properties": {
    "addr:full":"Klodsbergweg 10 Zonhoven Limburg 3520",
    "addr:housenumber":"10",
    "addr:postcode":"3520",
    "addr:street":"Klodsbergweg",
    "iso:country":"BE",
    "sg:address":"Klodsbergweg 10",
    "sg:city":"Zonhoven",
    "sg:orig_category":"Rusthuizen and serviceflats",
    "sg:phone":"+32 11 81 32 25",
    "sg:postcode":"3520",
    "sg:province":"Limburg",
    "wof:name":"Het Pand",
    "wof:placetype":"venue"
},
  "geometry": {"coordinates":[5.3630800247,50.9920387268],"type":"Point"}
}