{
  "type": "Feature",
  "properties": {
    "iso:country":"BE",
    "sg:address":"Zandstraat 14",
    "sg:city":"Herentals (groot)",
    "sg:orig_category":"V\u00eatements pour b\u00e9b\u00e9s and enfants",
    "sg:phone":"+32 14 21 87 53",
    "sg:postcode":"2200",
    "sg:province":"Antwerpen",
    "wof:name":"Topkid",
    "wof:placetype":"venue"
},
  "geometry": {"coordinates":[4.8352780342,51.1770439148],"type":"Point"}
}