{
  "type": "Feature",
  "properties": {
    "iso:country":"BE",
    "sg:address":"Grote Leiestraat 72",
    "sg:city":"Anzegem",
    "sg:orig_category":"Brood, gebak and snoepgoed",
    "sg:phone":"+32 56 68 17 27",
    "sg:postcode":"8570",
    "sg:province":"West-Vlaanderen",
    "wof:name":"Pedro Gardin",
    "wof:placetype":"venue"
},
  "geometry": {"coordinates":[3.4598689079,50.854724884],"type":"Point"}
}