{
  "type": "Feature",
  "properties": {
    "addr:full":"Trieux \u00e0 P\u00e9quets 19 Erquelinnes (montignies-saint-christophe) Hainaut 6560",
    "addr:housenumber":"19",
    "addr:postcode":"6560",
    "iso:country":"BE",
    "sg:address":"Trieux \u00e0 P\u00e9quets 19",
    "sg:city":"Erquelinnes (montignies-saint-christophe)",
    "sg:classifiers":[
        {
            "category":"Health Services",
            "subcategory":"Health Practitioner",
            "type":"Services"
        }
    ],
    "sg:phone":"+32 71 55 42 88",
    "sg:postcode":"6560",
    "sg:province":"Hainaut",
    "sg:tags":[
        "physiotherapist"
    ],
    "wof:name":"Nachtergaele M",
    "wof:placetype":"venue"
},
  "geometry": {"coordinates":[4.1934719086,50.2824897766],"type":"Point"}
}