{
  "type": "Feature",
  "properties": {
    "iso:country":"BE",
    "sg:address":"Grand'rue 55",
    "sg:city":"Mont-saint-guibert",
    "sg:classifiers":[
        {
            "category":"Travel",
            "subcategory":"Travel Agent",
            "type":"Entertainment"
        }
    ],
    "sg:phone":"+32 10 65 18 30",
    "sg:postcode":"1435",
    "sg:province":"Brabant Wallon",
    "sg:tags":[
        "agency"
    ],
    "wof:name":"Kallima Tours Sprl",
    "wof:placetype":"venue"
},
  "geometry": {"coordinates":[4.6107521057,50.6339874268],"type":"Point"}
}