{
  "type": "Feature",
  "properties": {
    "addr:full":"Middeldorpe 27 Sint-laureins Oost-Vlaanderen 9980",
    "addr:housenumber":"27",
    "addr:postcode":"9980",
    "addr:street":"Middeldorpe",
    "iso:country":"BE",
    "sg:address":"Middeldorpe 27",
    "sg:city":"Sint-laureins",
    "sg:orig_category":"Rundveehouders",
    "sg:phone":"+32 9 379 99 23",
    "sg:postcode":"9980",
    "sg:province":"Oost-Vlaanderen",
    "wof:name":"Rudi Hermie",
    "wof:placetype":"venue"
},
  "geometry": {"coordinates":[3.4854769707,51.2370567322],"type":"Point"}
}