{
  "type": "Feature",
  "properties": {
    "addr:full":"Boulevard Bara 42 Tournai Hainaut 7500",
    "addr:housenumber":"42",
    "addr:postcode":"7500",
    "addr:street":"Boulevard Bara",
    "iso:country":"BE",
    "sg:address":"Boulevard Bara 42",
    "sg:city":"Tournai",
    "sg:orig_category":"Boekhouders",
    "sg:phone":"+32 69 22 00 94",
    "sg:postcode":"7500",
    "sg:province":"Hainaut",
    "wof:name":"Serge Collie",
    "wof:placetype":"venue"
},
  "geometry": {"coordinates":[3.3839430809,50.6033096313],"type":"Point"}
}