{
  "type": "Feature",
  "properties": {
    "addr:full":"Rue Des Moulins 19 Comines-warneton (comines) Hainaut 7780",
    "addr:housenumber":"19",
    "addr:postcode":"7780",
    "addr:street":"Rue Des Moulins",
    "iso:country":"BE",
    "sg:address":"Rue Des Moulins 19",
    "sg:city":"Comines-warneton (comines)",
    "sg:classifiers":[
        {
            "category":"Health Services",
            "subcategory":"Nursing And Care Facility",
            "type":"Services"
        }
    ],
    "sg:phone":"+32 56 55 88 53",
    "sg:postcode":"7780",
    "sg:province":"Hainaut",
    "sg:tags":[
        "home",
        "rest"
    ],
    "wof:name":"Ch\u00e2teau Dumont-ch\u00e2teau De La Lys Sa",
    "wof:placetype":"venue"
},
  "geometry": {"coordinates":[3.0037870407,50.7655029297],"type":"Point"}
}