{
  "type": "Feature",
  "properties": {
    "iso:country":"BE",
    "sg:address":"Avenue De La Reine 275",
    "sg:city":"Brussel",
    "sg:orig_category":"Agences d'exp\u00e9dition",
    "sg:phone":"+32 2 425 72 01",
    "sg:postcode":"1020",
    "sg:province":"Bruxelles-Capitale",
    "wof:name":"Geomatica",
    "wof:placetype":"venue"
},
  "geometry": {"coordinates":[4.3589482307,50.8748054504],"type":"Point"}
}