{
  "type": "Feature",
  "properties": {
    "addr:full":"Rue De Tournai 6 Leuze-en-hainaut Hainaut 7900",
    "addr:housenumber":"6",
    "addr:postcode":"7900",
    "addr:street":"Rue De Tournai",
    "iso:country":"BE",
    "sg:address":"Rue De Tournai 6",
    "sg:city":"Leuze-en-hainaut",
    "sg:orig_category":"Verplichte sociale verzekeringen",
    "sg:phone":"+32 69 67 02 09",
    "sg:postcode":"7900",
    "sg:province":"Hainaut",
    "wof:name":"Mutualite Liberale",
    "wof:placetype":"venue"
},
  "geometry": {"coordinates":[3.6175858974,50.5986824036],"type":"Point"}
}