{
  "type": "Feature",
  "properties": {
    "addr:full":"Avenue Albert Dumont 2a Bruxelles (woluwe-saint-lambert) Bruxelles-Capitale 1200",
    "addr:housenumber":"2a",
    "addr:postcode":"1200",
    "addr:street":"Avenue Albert Dumont",
    "iso:country":"BE",
    "sg:address":"Avenue Albert Dumont 2a",
    "sg:city":"Bruxelles (woluwe-saint-lambert)",
    "sg:classifiers":[
        {
            "category":"Bakery",
            "type":"Food & Drink"
        }
    ],
    "sg:phone":"+32 2 771 19 29",
    "sg:postcode":"1200",
    "sg:province":"Bruxelles-Capitale",
    "sg:tags":[
        "confectioner",
        "baker"
    ],
    "wof:name":"Kapelleveld",
    "wof:placetype":"venue"
},
  "geometry": {"coordinates":[4.4501781464,50.8471107483],"type":"Point"}
}