{
  "type": "Feature",
  "properties": {
    "addr:full":"Dendermondesesteenweg 227 Opwijk Vlaams-Brabant 1745",
    "addr:housenumber":"227",
    "addr:postcode":"1745",
    "addr:street":"Dendermondesesteenweg",
    "iso:country":"BE",
    "sg:address":"Dendermondesesteenweg 227",
    "sg:city":"Opwijk",
    "sg:orig_category":"Installatie van houten of kunststof schrijnwerk Installatie van metalen schrijnwerk",
    "sg:phone":"+32 52 35 13 19",
    "sg:postcode":"1745",
    "sg:province":"Vlaams-Brabant",
    "wof:name":"Coveral",
    "wof:placetype":"venue"
},
  "geometry": {"coordinates":[4.1490578651,50.9705200195],"type":"Point"}
}