{
  "type": "Feature",
  "properties": {
    "addr:full":"Place Gambetta 26 Charleroi Hainaut 6044",
    "addr:housenumber":"26",
    "addr:postcode":"6044",
    "addr:street":"Place Gambetta;Hainaut",
    "iso:country":"BE",
    "sg:address":"Place Gambetta 26",
    "sg:city":"Charleroi",
    "sg:orig_category":"Banken and kredietinstellingen",
    "sg:phone":"+32 71 45 11 22",
    "sg:postcode":"6044",
    "sg:province":"Hainaut",
    "wof:name":"Bbl",
    "wof:placetype":"venue"
},
  "geometry": {"coordinates":[4.3887767792,50.4426040649],"type":"Point"}
}