{
  "type": "Feature",
  "properties": {
    "addr:full":"Dr. Rubbenslaan 5 Lede Oost-Vlaanderen 9340",
    "addr:housenumber":"5",
    "addr:postcode":"9340",
    "addr:street":"Dr. Rubbenslaan",
    "iso:country":"BE",
    "sg:address":"Dr. Rubbenslaan 5",
    "sg:city":"Lede",
    "sg:classifiers":[
        {
            "category":"Retail",
            "subcategory":"Car Wash",
            "type":"Services"
        }
    ],
    "sg:phone":"+32 53 80 00 38",
    "sg:postcode":"9340",
    "sg:province":"Oost-Vlaanderen",
    "sg:tags":[
        "machine",
        "mat\u00e9riel",
        "de",
        "bureau",
        "fournitures"
    ],
    "wof:name":"File",
    "wof:placetype":"venue"
},
  "geometry": {"coordinates":[3.9877479076,50.9720954895],"type":"Point"}
}