{
  "type": "Feature",
  "properties": {
    "addr:full":"Chauss\u00c9e De Gand 1186 Sint-agatha-berchem/berchem-sainte-agathe Bruxelles-Capitale 1082",
    "addr:housenumber":"1186",
    "addr:postcode":"1082",
    "addr:street":"Chausse\u0301E De Gand;/",
    "iso:country":"BE",
    "sg:address":"Chauss\u00c9e De Gand 1186",
    "sg:city":"Sint-agatha-berchem/berchem-sainte-agathe",
    "sg:orig_category":"V\u00eatements",
    "sg:phone":"+32 2 465 31 09",
    "sg:postcode":"1082",
    "sg:province":"Bruxelles-Capitale",
    "wof:name":"C.t.f.",
    "wof:placetype":"venue"
},
  "geometry": {"coordinates":[4.296271801,50.8651351929],"type":"Point"}
}