{
  "type": "Feature",
  "properties": {
    "addr:full":"Rue Lambert Crickx 21 Bruxelles (anderlecht) Bruxelles-Capitale 1070",
    "addr:housenumber":"21",
    "addr:postcode":"1070",
    "addr:street":"Rue Lambert Crickx",
    "iso:country":"BE",
    "sg:address":"Rue Lambert Crickx 21",
    "sg:city":"Bruxelles (anderlecht)",
    "sg:orig_category":"Non-Classified Establishments",
    "sg:phone":"+32 2 521 68 60",
    "sg:postcode":"1070",
    "sg:province":"Bruxelles-Capitale",
    "wof:name":"Anti Stress (l') Sprlu",
    "wof:placetype":"venue"
},
  "geometry": {"coordinates":[4.3387598991,50.8277587891],"type":"Point"}
}