{
  "type": "Feature",
  "properties": {
    "addr:full":"Dessous La Ville 2 Libramont-chevigny Luxembourg 6800",
    "addr:housenumber":"2",
    "addr:postcode":"6800",
    "addr:street":"Dessous La Ville",
    "iso:country":"BE",
    "sg:address":"Dessous La Ville 2",
    "sg:city":"Libramont-chevigny",
    "sg:orig_category":"HERSTELLING ELEKTRISCHE HUISHOUDAPPARATEN Huishoudapparaten, televisies and radio's",
    "sg:phone":"+32 61 22 21 56",
    "sg:postcode":"6800",
    "sg:province":"Luxembourg",
    "wof:name":"Deduffeleer Cyprien",
    "wof:placetype":"venue"
},
  "geometry": {"coordinates":[5.3761348724,49.9199943542],"type":"Point"}
}