{
  "type": "Feature",
  "properties": {
    "iso:country":"BE",
    "sg:address":"Oude Molenstraat 119",
    "sg:city":"Ukkel/uccle",
    "sg:classifiers":[
        {
            "category":"Professional",
            "subcategory":"Accounting & Tax Preparation",
            "type":"Services"
        }
    ],
    "sg:phone":"+32 2 374 05 09",
    "sg:postcode":"1180",
    "sg:province":"Bruxelles-Capitale",
    "sg:tags":[
        "accountant"
    ],
    "wof:name":"Jean-marie Hendrick",
    "wof:placetype":"venue"
},
  "geometry": {"coordinates":[4.3665008545,50.7902793884],"type":"Point"}
}