{
  "type": "Feature",
  "properties": {
    "addr:full":"Julius Vuylstekelaan 5 Antwerpen Antwerpen 2050",
    "addr:housenumber":"5",
    "addr:postcode":"2050",
    "addr:street":"Julius Vuylstekelaan",
    "iso:country":"BE",
    "sg:address":"Julius Vuylstekelaan 5",
    "sg:city":"Antwerpen",
    "sg:classifiers":[
        {
            "category":"Health Services",
            "subcategory":"Dentist",
            "type":"Services"
        }
    ],
    "sg:phone":"+32 3 219 62 15",
    "sg:postcode":"2050",
    "sg:province":"Antwerpen",
    "wof:name":"Cuyt J",
    "wof:placetype":"venue"
},
  "geometry": {"coordinates":[4.3794331551,51.2290039062],"type":"Point"}
}