{
  "type": "Feature",
  "properties": {
    "addr:full":"Rue De Brabant 147 Bruxelles (schaerbeek) Bruxelles-Capitale 1030",
    "addr:housenumber":"147",
    "addr:postcode":"1030",
    "addr:street":"Rue De Brabant",
    "iso:country":"BE",
    "sg:address":"Rue De Brabant 147",
    "sg:city":"Bruxelles (schaerbeek)",
    "sg:classifiers":[
        {
            "category":"Shopping",
            "subcategory":"Clothing, Apparel, & Fashions",
            "type":"Retail Goods"
        }
    ],
    "sg:phone":"+32 2 242 98 44",
    "sg:postcode":"1030",
    "sg:province":"Bruxelles-Capitale",
    "sg:tags":[
        "-",
        "clothing",
        "child"
    ],
    "wof:name":"Mikatex",
    "wof:placetype":"venue"
},
  "geometry": {"coordinates":[4.3649477959,50.8624954224],"type":"Point"}
}