{
  "type": "Feature",
  "properties": {
    "addr:full":"Edm. De Coussemakerstr. 2 Antwerpen Antwerpen 2050",
    "addr:housenumber":"2",
    "addr:postcode":"2050",
    "addr:street":"Edm.;Coussemakerstr.",
    "iso:country":"BE",
    "sg:address":"Edm. De Coussemakerstr. 2",
    "sg:city":"Antwerpen",
    "sg:orig_category":"Supermarch\u00e9s",
    "sg:postcode":"2050",
    "sg:province":"Antwerpen",
    "wof:name":"Aldi",
    "wof:placetype":"venue"
},
  "geometry": {"coordinates":[4.3737258911,51.2197341919],"type":"Point"}
}