{
  "type": "Feature",
  "properties": {
    "addr:full":"Lichtaartsebaan 216b1 Kasterlee Antwerpen 2460",
    "addr:housenumber":"216b1",
    "addr:postcode":"2460",
    "addr:street":"Lichtaartsebaan",
    "iso:country":"BE",
    "sg:address":"Lichtaartsebaan 216b1",
    "sg:city":"Kasterlee",
    "sg:orig_category":"Sportclubs",
    "sg:phone":"+32 14 22 16 22",
    "sg:postcode":"2460",
    "sg:province":"Antwerpen",
    "wof:name":"Herentalse T.c.",
    "wof:placetype":"venue"
},
  "geometry": {"coordinates":[4.9378399849,51.2311286926],"type":"Point"}
}