{
  "type": "Feature",
  "properties": {
    "addr:full":"Herentalsebaan 94 Ranst Antwerpen 2520",
    "addr:housenumber":"94",
    "addr:postcode":"2520",
    "addr:street":"Herentalsebaan",
    "iso:country":"BE",
    "sg:address":"Herentalsebaan 94",
    "sg:city":"Ranst",
    "sg:classifiers":[
        {
            "category":"Manufacturing",
            "subcategory":"Metals",
            "type":"Manufacturing & Wholesale Goods"
        }
    ],
    "sg:phone":"+32 297256828",
    "sg:postcode":"2520",
    "sg:province":"Antwerpen",
    "sg:tags":[
        "die",
        "aluminium",
        "casting"
    ],
    "wof:name":"Swildens",
    "wof:placetype":"venue"
},
  "geometry": {"coordinates":[4.5422391891,51.1868782043],"type":"Point"}
}