{
  "type": "Feature",
  "properties": {
    "iso:country":"BE",
    "sg:address":"Boulevard Sylvain Dupuis 209b9",
    "sg:city":"Anderlecht/anderlecht",
    "sg:orig_category":"Imprimeries and copyshops",
    "sg:phone":"+32 2 523 63 66",
    "sg:postcode":"1070",
    "sg:province":"Bruxelles-Capitale",
    "wof:name":"Digital Printing International",
    "wof:placetype":"venue"
},
  "geometry": {"coordinates":[4.2951798439,50.837310791],"type":"Point"}
}