{
  "type": "Feature",
  "properties": {
    "iso:country":"BE",
    "sg:address":"Rumbeeksesteenweg 292",
    "sg:city":"Roeselare",
    "sg:classifiers":[
        {
            "category":"Government",
            "subcategory":"Post Office",
            "type":"Public Place"
        }
    ],
    "sg:phone":"+32 51 20 61 94",
    "sg:postcode":"8800",
    "sg:province":"West-Vlaanderen",
    "sg:tags":[
        "stamp"
    ],
    "wof:name":"Gunst R",
    "wof:placetype":"venue"
},
  "geometry": {"coordinates":[3.1396169662,50.9375762939],"type":"Point"}
}