{
  "type": "Feature",
  "properties": {
    "addr:full":"Rue Ry De Brabant 59a Manage (bellecourt) Hainaut 7170",
    "addr:housenumber":"59a",
    "addr:postcode":"7170",
    "addr:street":"Rue Ry De Brabant",
    "iso:country":"BE",
    "sg:address":"Rue Ry De Brabant 59a",
    "sg:city":"Manage (bellecourt)",
    "sg:classifiers":[
        {
            "category":"Professional",
            "subcategory":"Employment Agencies",
            "type":"Services"
        }
    ],
    "sg:phone":"+32 64 55 83 55",
    "sg:postcode":"7170",
    "sg:province":"Hainaut",
    "wof:name":"First Class Service Scrl",
    "wof:placetype":"venue"
},
  "geometry": {"coordinates":[4.2692751884,50.4899215698],"type":"Point"}
}