{
  "type": "Feature",
  "properties": {
    "addr:full":"J.b. Woutersstraat 8b1 Haacht Vlaams-Brabant 3150",
    "addr:housenumber":"8b1",
    "addr:postcode":"3150",
    "addr:street":"J.B. Woutersstraat",
    "iso:country":"BE",
    "sg:address":"J.b. Woutersstraat 8b1",
    "sg:city":"Haacht",
    "sg:classifiers":[
        {
            "category":"Fast Food",
            "type":"Food & Drink"
        }
    ],
    "sg:phone":"+32 16 60 71 93",
    "sg:postcode":"3150",
    "sg:province":"Vlaams-Brabant",
    "sg:tags":[
        "\u00c0",
        "emporter",
        "restaurants"
    ],
    "wof:name":"Frituur 't Pleintje",
    "wof:placetype":"venue"
},
  "geometry": {"coordinates":[4.609251976,50.9585380554],"type":"Point"}
}