{
  "type": "Feature",
  "properties": {
    "iso:country":"BE",
    "sg:address":"Schoolweg 1",
    "sg:city":"Willebroek",
    "sg:orig_category":"Travail and traitement du bois. Quincailleries. Bois Gr",
    "sg:phone":"+32 3 886 52 76",
    "sg:postcode":"2830",
    "sg:province":"Antwerpen",
    "wof:name":"Labee Vezelpers",
    "wof:placetype":"venue"
},
  "geometry": {"coordinates":[4.3590388298,51.0612182617],"type":"Point"}
}