{
  "type": "Feature",
  "properties": {
    "iso:country":"BE",
    "sg:address":"Havikstraat 4",
    "sg:city":"Harelbeke",
    "sg:orig_category":"Koekjes, gebak and taart Fab",
    "sg:phone":"+32 56 72 70 76",
    "sg:postcode":"8531",
    "sg:province":"West-Vlaanderen",
    "wof:name":"Fa. Seyad",
    "wof:placetype":"venue"
},
  "geometry": {"coordinates":[3.300344944,50.8812408447],"type":"Point"}
}