{
  "type": "Feature",
  "properties": {
    "addr:full":"Veldstraat 32 Damme West-Vlaanderen 8340",
    "addr:housenumber":"32",
    "addr:postcode":"8340",
    "addr:street":"Veldstraat",
    "iso:country":"BE",
    "sg:address":"Veldstraat 32",
    "sg:city":"Damme",
    "sg:orig_category":"Rundveehouders",
    "sg:phone":"+32 50 36 17 36",
    "sg:postcode":"8340",
    "sg:province":"West-Vlaanderen",
    "wof:name":"Leon Neyt",
    "wof:placetype":"venue"
},
  "geometry": {"coordinates":[3.3178579807,51.2090072632],"type":"Point"}
}