{
  "type": "Feature",
  "properties": {
    "addr:full":"Alfons Pieterslaan 42 Oostende West-Vlaanderen 8400",
    "addr:housenumber":"42",
    "addr:postcode":"8400",
    "addr:street":"Alfons Pieterslaan",
    "iso:country":"BE",
    "sg:address":"Alfons Pieterslaan 42",
    "sg:city":"Oostende",
    "sg:orig_category":"Blanchisseries and teintureries",
    "sg:phone":"+32 59 70 70 74",
    "sg:postcode":"8400",
    "sg:province":"West-Vlaanderen",
    "wof:name":"Perfect-shop",
    "wof:placetype":"venue"
},
  "geometry": {"coordinates":[2.9140870571,51.2259368896],"type":"Point"}
}