{
  "type": "Feature",
  "properties": {
    "iso:country":"BE",
    "sg:address":"Rue Baudemont 26",
    "sg:city":"Itter",
    "sg:orig_category":"Diverse bedrijfsbeheeradviesbureaus",
    "sg:phone":"+32 57 64 88 56",
    "sg:postcode":"1460",
    "sg:province":"Brabant Wallon",
    "wof:name":"Vrydagh",
    "wof:placetype":"venue"
},
  "geometry": {"coordinates":[4.2676148415,50.6472206116],"type":"Point"}
}