{
  "type": "Feature",
  "properties": {
    "addr:full":"Dorp 47 Lommel Limburg 3920",
    "addr:housenumber":"47",
    "addr:postcode":"3920",
    "addr:street":"Dorp",
    "iso:country":"BE",
    "sg:address":"Dorp 47",
    "sg:city":"Lommel",
    "sg:orig_category":"Textiel",
    "sg:phone":"+32 11 54 65 95",
    "sg:postcode":"3920",
    "sg:province":"Limburg",
    "wof:name":"Huis Modestiek",
    "wof:placetype":"venue"
},
  "geometry": {"coordinates":[5.3071022034,51.2301902771],"type":"Point"}
}