{
  "type": "Feature",
  "properties": {
    "addr:full":"Voordries 52 Oosterzele Oost-Vlaanderen 9860",
    "addr:housenumber":"52",
    "addr:postcode":"9860",
    "addr:street":"Voordries;Oost-Vlaanderen",
    "iso:country":"BE",
    "sg:address":"Voordries 52",
    "sg:city":"Oosterzele",
    "sg:orig_category":"Schoonheidssalons",
    "sg:phone":"+32 9 362 34 63",
    "sg:postcode":"9860",
    "sg:province":"Oost-Vlaanderen",
    "wof:name":"Pedicure Braekman",
    "wof:placetype":"venue"
},
  "geometry": {"coordinates":[3.8066558838,50.9502868652],"type":"Point"}
}