{
  "type": "Feature",
  "properties": {
    "iso:country":"BE",
    "sg:address":"Eigenlostraat 160",
    "sg:city":"Sint-niklaas",
    "sg:classifiers":[
        {
            "category":"Real Estate",
            "subcategory":"Architect",
            "type":"Services"
        }
    ],
    "sg:phone":"+32 3 711 06 99",
    "sg:postcode":"9100",
    "sg:province":"Oost-Vlaanderen",
    "wof:name":"Goossens V",
    "wof:placetype":"venue"
},
  "geometry": {"coordinates":[4.1904129982,51.1516838074],"type":"Point"}
}