{
  "type": "Feature",
  "properties": {
    "iso:country":"BE",
    "sg:address":"Wortegemplein 5",
    "sg:city":"Wortegem-petegem",
    "sg:orig_category":"Epiceries",
    "sg:phone":"+32 56 68 86 33",
    "sg:postcode":"9790",
    "sg:province":"Oost-Vlaanderen",
    "wof:name":"Merlier Jules & Laura",
    "wof:placetype":"venue"
},
  "geometry": {"coordinates":[3.5084280968,50.8529052734],"type":"Point"}
}