{
  "type": "Feature",
  "properties": {
    "addr:full":"Rue Adolphe Doneux 58 Eghezee Namur 5310",
    "addr:housenumber":"58",
    "addr:postcode":"5310",
    "addr:street":"Rue Adolphe Doneux;Namur",
    "iso:country":"BE",
    "sg:address":"Rue Adolphe Doneux 58",
    "sg:city":"Eghezee",
    "sg:orig_category":"Herstellingen and onderhoud van auto's",
    "sg:phone":"+32 81 81 16 19",
    "sg:postcode":"5310",
    "sg:province":"Namur",
    "wof:name":"Paul Hincq",
    "wof:placetype":"venue"
},
  "geometry": {"coordinates":[4.930811882,50.600353241],"type":"Point"}
}