{
  "type": "Feature",
  "properties": {
    "addr:full":"Ringbaan 5bf Maldegem Oost-Vlaanderen 9991",
    "addr:postcode":"9991",
    "addr:street":"Ringbaan 5Bf",
    "iso:country":"BE",
    "sg:address":"Ringbaan 5bf",
    "sg:city":"Maldegem",
    "sg:orig_category":"Plomberie, chauffage and installations sanitaires",
    "sg:phone":"+32 50 71 03 06",
    "sg:postcode":"9991",
    "sg:province":"Oost-Vlaanderen",
    "wof:name":"Wilfried Bral",
    "wof:placetype":"venue"
},
  "geometry": {"coordinates":[3.4825220108,51.1964302063],"type":"Point"}
}