{
  "type": "Feature",
  "properties": {
    "iso:country":"BE",
    "sg:address":"Wagenbrugstraat 2",
    "sg:city":"Roeselare",
    "sg:orig_category":"Pain, p\u00e2tisseries and confiseries",
    "sg:phone":"+32 51 24 30 38",
    "sg:postcode":"8800",
    "sg:province":"West-Vlaanderen",
    "wof:name":"R. & R. Fiems",
    "wof:placetype":"venue"
},
  "geometry": {"coordinates":[3.1420099735,50.9789009094],"type":"Point"}
}