{
  "type": "Feature",
  "properties": {
    "iso:country":"BE",
    "sg:address":"Fosselstraat 69",
    "sg:city":"Affligem",
    "sg:orig_category":"Production and transformation de viande",
    "sg:phone":"+32 53 66 70 14",
    "sg:postcode":"1790",
    "sg:province":"Vlaams-Brabant",
    "wof:name":"Fa. Hoffman",
    "wof:placetype":"venue"
},
  "geometry": {"coordinates":[4.1120052338,50.9126472473],"type":"Point"}
}