{
  "type": "Feature",
  "properties": {
    "addr:full":"Chauss\u00c9e De March\u00c9 506 Namur Namur 5101",
    "addr:housenumber":"506",
    "addr:postcode":"5101",
    "addr:street":"Chausse\u0301E De Marche\u0301",
    "iso:country":"BE",
    "sg:address":"Chauss\u00c9e De March\u00c9 506",
    "sg:city":"Namur",
    "sg:orig_category":"Diverse kredietdiensten",
    "sg:postcode":"5101",
    "sg:province":"Namur",
    "wof:name":"Bancontact-mister Cash",
    "wof:placetype":"venue"
},
  "geometry": {"coordinates":[4.9006061554,50.4446487427],"type":"Point"}
}