{
  "type": "Feature",
  "properties": {
    "iso:country":"BE",
    "sg:address":"La Fourche 25",
    "sg:city":"Manhay (grandmenil)",
    "sg:classifiers":[
        {
            "category":"Museum",
            "type":"Entertainment"
        }
    ],
    "sg:phone":"+32 86 43 34 65",
    "sg:postcode":"6960",
    "sg:province":"Luxembourg",
    "wof:name":"Ecr\u00e9meuse (mus\u00e9e De L')",
    "wof:placetype":"venue"
},
  "geometry": {"coordinates":[5.6851758957,50.3374786377],"type":"Point"}
}