{
  "type": "Feature",
  "properties": {
    "iso:country":"BE",
    "sg:address":"Rue En-dessous 2",
    "sg:city":"Walcourt",
    "sg:orig_category":"Installation de menuiserie en bois and plastique. Services fun\u00e9raires",
    "sg:phone":"+32 71 65 50 07",
    "sg:postcode":"5650",
    "sg:province":"Namur",
    "wof:name":"Fun\u00c9railles Debry",
    "wof:placetype":"venue"
},
  "geometry": {"coordinates":[4.4313349724,50.2514762878],"type":"Point"}
}