{
  "type": "Feature",
  "properties": {
    "addr:full":"Rue De La Flaminette 9 Fleurus Hainaut 6224",
    "addr:housenumber":"9",
    "addr:postcode":"6224",
    "addr:street":"Rue De La Flaminette",
    "iso:country":"BE",
    "sg:address":"Rue De La Flaminette 9",
    "sg:city":"Fleurus",
    "sg:classifiers":[
        {
            "category":"Food & Beverages",
            "subcategory":"Fruits & Vegetables",
            "type":"Retail Goods"
        }
    ],
    "sg:phone":"+32 71 81 04 33",
    "sg:postcode":"6224",
    "sg:province":"Hainaut",
    "sg:tags":[
        "groenten"
    ],
    "wof:name":"La Flaminette",
    "wof:placetype":"venue"
},
  "geometry": {"coordinates":[4.5752048492,50.4971313477],"type":"Point"}
}