{
  "type": "Feature",
  "properties": {
    "addr:full":"Leiestraat 46 Kuurne West-Vlaanderen 8520",
    "addr:housenumber":"46",
    "addr:postcode":"8520",
    "addr:street":"Leiestraat",
    "iso:country":"BE",
    "sg:address":"Leiestraat 46",
    "sg:city":"Kuurne",
    "sg:classifiers":[
        {
            "category":"Home & Garden",
            "subcategory":"Kitchen Supply",
            "type":"Retail Goods"
        }
    ],
    "sg:phone":"+32 56 70 03 81",
    "sg:postcode":"8520",
    "sg:province":"West-Vlaanderen",
    "sg:tags":[
        "installation"
    ],
    "wof:name":"Maelfait G",
    "wof:placetype":"venue"
},
  "geometry": {"coordinates":[3.2914459705,50.8520736694],"type":"Point"}
}