{
  "type": "Feature",
  "properties": {
    "addr:full":"Halfdreef 1 Beveren (beveren-waas) Oost-Vlaanderen 9120",
    "addr:housenumber":"1",
    "addr:postcode":"9120",
    "addr:street":"Halfdreef;Oost-Vlaanderen",
    "iso:country":"BE",
    "sg:address":"Halfdreef 1",
    "sg:city":"Beveren (beveren-waas)",
    "sg:classifiers":[
        {
            "category":"Fast Food",
            "type":"Food & Drink"
        }
    ],
    "sg:phone":"+32 3 755 42 04",
    "sg:postcode":"9120",
    "sg:province":"Oost-Vlaanderen",
    "sg:tags":[
        "fried",
        "stand",
        "potato"
    ],
    "wof:name":"Tante Nancy",
    "wof:placetype":"venue"
},
  "geometry": {"coordinates":[4.2534079552,51.2226028442],"type":"Point"}
}