{
  "type": "Feature",
  "properties": {
    "addr:full":"Sint-pietersstraat 4 Poperinge West-Vlaanderen 8970",
    "addr:housenumber":"4",
    "addr:postcode":"8970",
    "addr:street":"Sint-Pietersstraat",
    "iso:country":"BE",
    "sg:address":"Sint-pietersstraat 4",
    "sg:city":"Poperinge",
    "sg:orig_category":"Rundveehouders",
    "sg:postcode":"8970",
    "sg:province":"West-Vlaanderen",
    "wof:name":"Gerard Spenninck",
    "wof:placetype":"venue"
},
  "geometry": {"coordinates":[2.7700839043,50.8413772583],"type":"Point"}
}