{
  "type": "Feature",
  "properties": {
    "addr:full":"Nonnebossen 24 Zonnebeke West-Vlaanderen 8980",
    "addr:housenumber":"24",
    "addr:postcode":"8980",
    "addr:street":"Nonnebossen",
    "iso:country":"BE",
    "sg:address":"Nonnebossen 24",
    "sg:city":"Zonnebeke",
    "sg:orig_category":"Rundveehouders",
    "sg:phone":"+32 57 46 66 87",
    "sg:postcode":"8980",
    "sg:province":"West-Vlaanderen",
    "wof:name":"Daniel Verschaeve",
    "wof:placetype":"venue"
},
  "geometry": {"coordinates":[2.9697949886,50.8543891907],"type":"Point"}
}