{
  "type": "Feature",
  "properties": {
    "addr:full":"Kraanlei 25 Gent Oost-Vlaanderen 9000",
    "addr:housenumber":"25",
    "addr:postcode":"9000",
    "addr:street":"Kraanlei;Oost-Vlaanderen",
    "iso:country":"BE",
    "sg:address":"Kraanlei 25",
    "sg:city":"Gent",
    "sg:classifiers":[
        {
            "category":"Restaurant",
            "type":"Food & Drink"
        }
    ],
    "sg:phone":"+32 9 224 28 94",
    "sg:postcode":"9000",
    "sg:province":"Oost-Vlaanderen",
    "wof:name":"Rest. Le Moulin \u00c0 Poivre",
    "wof:placetype":"venue"
},
  "geometry": {"coordinates":[3.7222290039,51.0568580627],"type":"Point"}
}