{
  "type": "Feature",
  "properties": {
    "addr:full":"Heirbaan 17 Linter (neerlinter) Vlaams-Brabant 3350",
    "addr:housenumber":"17",
    "addr:postcode":"3350",
    "addr:street":"Heirbaan",
    "iso:country":"BE",
    "sg:address":"Heirbaan 17",
    "sg:city":"Linter (neerlinter)",
    "sg:classifiers":[
        {
            "category":"Farming",
            "subcategory":"Livestock Farm",
            "type":"Manufacturing & Wholesale Goods"
        }
    ],
    "sg:phone":"+32 11 78 06 26",
    "sg:postcode":"3350",
    "sg:province":"Vlaams-Brabant",
    "sg:tags":[
        "buyer"
    ],
    "wof:name":"Thiry L",
    "wof:placetype":"venue"
},
  "geometry": {"coordinates":[5.0378499031,50.8465385437],"type":"Point"}
}