{
  "type": "Feature",
  "properties": {
    "iso:country":"BE",
    "sg:address":"Boulevard Walter De Marvis 22",
    "sg:city":"Tournai",
    "sg:classifiers":[
        {
            "category":"Shopping",
            "subcategory":"Florist",
            "type":"Retail Goods"
        }
    ],
    "sg:phone":"+32 69 21 36 77",
    "sg:postcode":"7500",
    "sg:province":"Hainaut",
    "wof:name":"Gerbera (la)",
    "wof:placetype":"venue"
},
  "geometry": {"coordinates":[3.399586916,50.6073875427],"type":"Point"}
}