{
  "type": "Feature",
  "properties": {
    "addr:full":"Industrieweg 9 Malle (oostmalle) Antwerpen 2390",
    "addr:housenumber":"9",
    "addr:postcode":"2390",
    "addr:street":"Industrieweg",
    "iso:country":"BE",
    "sg:address":"Industrieweg 9",
    "sg:city":"Malle (oostmalle)",
    "sg:classifiers":[
        {
            "category":"Wholesale",
            "subcategory":"Construction Materials",
            "type":"Manufacturing & Wholesale Goods"
        }
    ],
    "sg:phone":"+32 3 309 01 66",
    "sg:postcode":"2390",
    "sg:province":"Antwerpen",
    "sg:tags":[
        "tubing",
        "industrial"
    ],
    "wof:name":"Conip Bvba",
    "wof:placetype":"venue"
},
  "geometry": {"coordinates":[4.7146577835,51.2956123352],"type":"Point"}
}