{
  "type": "Feature",
  "properties": {
    "addr:full":"De Schiervelstraat 3 Tongeren Limburg 3700",
    "addr:housenumber":"3",
    "addr:postcode":"3700",
    "addr:street":"Schiervelstraat",
    "iso:country":"BE",
    "sg:address":"De Schiervelstraat 3",
    "sg:city":"Tongeren",
    "sg:classifiers":[
        {
            "category":"Bars & Pubs",
            "type":"Food & Drink"
        }
    ],
    "sg:phone":"+32 12 39 42 42",
    "sg:postcode":"3700",
    "sg:province":"Limburg",
    "wof:name":"Sweerd ('t)",
    "wof:placetype":"venue"
},
  "geometry": {"coordinates":[5.4676890373,50.7823028564],"type":"Point"}
}