{
  "type": "Feature",
  "properties": {
    "iso:country":"BE",
    "sg:address":"Laarstraat 5",
    "sg:city":"Ranst",
    "sg:orig_category":"G\u00e9om\u00e8tres",
    "sg:phone":"+32 3 485 61 92",
    "sg:postcode":"2520",
    "sg:province":"Antwerpen",
    "wof:name":"Constant De Schutter",
    "wof:placetype":"venue"
},
  "geometry": {"coordinates":[4.566827774,51.1921882629],"type":"Point"}
}