{
  "type": "Feature",
  "properties": {
    "addr:full":"Missiestraat 4 Box 2-2 Buggenhout Oost-Vlaanderen 9255",
    "addr:housenumber":"4 box 2-2",
    "addr:postcode":"9255",
    "addr:street":"Missiestraat",
    "iso:country":"BE",
    "sg:address":"Missiestraat 4 Box 2-2",
    "sg:city":"Buggenhout",
    "sg:classifiers":[
        {
            "category":"Real Estate",
            "subcategory":"Developer",
            "type":"Services"
        }
    ],
    "sg:phone":"+32 52 34 57 50",
    "sg:postcode":"9255",
    "sg:province":"Oost-Vlaanderen",
    "sg:tags":[
        "project"
    ],
    "wof:name":"Hero Construct Nv",
    "wof:placetype":"venue"
},
  "geometry": {"coordinates":[4.2018060684,51.0139122009],"type":"Point"}
}