{
  "type": "Feature",
  "properties": {
    "addr:full":"Korte Gasthuisstraat 73 Turnhout Antwerpen 2300",
    "addr:housenumber":"73",
    "addr:postcode":"2300",
    "addr:street":"Korte Gasthuisstraat",
    "iso:country":"BE",
    "sg:address":"Korte Gasthuisstraat 73",
    "sg:city":"Turnhout",
    "sg:orig_category":"Banken and kredietinstellingen",
    "sg:phone":"+32 14 41 85 31",
    "sg:postcode":"2300",
    "sg:province":"Antwerpen",
    "wof:name":"Landbouwkrediet",
    "wof:placetype":"venue"
},
  "geometry": {"coordinates":[4.9434962273,51.3223800659],"type":"Point"}
}