{
  "type": "Feature",
  "properties": {
    "addr:full":"Kontichsesteenweg 14 Aartselaar Antwerpen 2630",
    "addr:housenumber":"14",
    "addr:postcode":"2630",
    "addr:street":"Kontichsesteenweg",
    "iso:country":"BE",
    "sg:address":"Kontichsesteenweg 14",
    "sg:city":"Aartselaar",
    "sg:orig_category":"Autombile concessionaires",
    "sg:phone":"+32 3 877 34 30",
    "sg:postcode":"2630",
    "sg:province":"Antwerpen",
    "wof:name":"Chrysler-car Dealership",
    "wof:placetype":"venue"
},
  "geometry": {"coordinates":[4.3832259178,51.1426887512],"type":"Point"}
}