{
  "type": "Feature",
  "properties": {
    "addr:full":"Rue De Belgrade 48 Vorst/forest Bruxelles-Capitale 1190",
    "addr:housenumber":"48",
    "addr:postcode":"1190",
    "addr:street":"Rue De Belgrade;/ Forest",
    "iso:country":"BE",
    "sg:address":"Rue De Belgrade 48",
    "sg:city":"Vorst/forest",
    "sg:orig_category":"Studios photographiques",
    "sg:phone":"+32 2 538 43 82",
    "sg:postcode":"1190",
    "sg:province":"Bruxelles-Capitale",
    "wof:name":"Anthierens Erik",
    "wof:placetype":"venue"
},
  "geometry": {"coordinates":[4.3293318748,50.828086853],"type":"Point"}
}