{
  "type": "Feature",
  "properties": {
    "iso:country":"BE",
    "sg:address":"Chauss\u00e9e De Nivelles 15a",
    "sg:city":"Waremme (oleye)",
    "sg:classifiers":[
        {
            "category":"Building & Trades",
            "subcategory":"Plumbing",
            "type":"Services"
        }
    ],
    "sg:phone":"+32 19 32 73 59",
    "sg:postcode":"4300",
    "sg:province":"Li\u00e8ge",
    "sg:tags":[
        "repair",
        "mainten",
        "-",
        "central",
        "heating"
    ],
    "wof:name":"Baillien Michel",
    "wof:placetype":"venue"
},
  "geometry": {"coordinates":[5.2726230621,50.7140350342],"type":"Point"}
}