{
  "type": "Feature",
  "properties": {
    "iso:country":"BE",
    "sg:address":"Dokter Bruwierlaan 4",
    "sg:city":"Ichtegem",
    "sg:classifiers":[
        {
            "category":"Retail",
            "subcategory":"Event Space",
            "type":"Services"
        }
    ],
    "sg:phone":"+32 51 58 11 58",
    "sg:postcode":"8480",
    "sg:province":"West-Vlaanderen",
    "sg:tags":[
        "rental",
        "-",
        "hall"
    ],
    "wof:name":"Wit Paard ('t)",
    "wof:placetype":"venue"
},
  "geometry": {"coordinates":[3.0114209652,51.0927009583],"type":"Point"}
}