{
  "type": "Feature",
  "properties": {
    "addr:full":"Diegemstraat 95 Machelen Vlaams-Brabant 1830",
    "addr:housenumber":"95",
    "addr:postcode":"1830",
    "addr:street":"Diegemstraat",
    "iso:country":"BE",
    "sg:address":"Diegemstraat 95",
    "sg:city":"Machelen",
    "sg:classifiers":[
        {
            "category":"Professional",
            "subcategory":"Accounting & Tax Preparation",
            "type":"Services"
        }
    ],
    "sg:phone":"+32 2 251 39 18",
    "sg:postcode":"1830",
    "sg:province":"Vlaams-Brabant",
    "sg:tags":[
        "bookkeeper"
    ],
    "wof:name":"Saffer P",
    "wof:placetype":"venue"
},
  "geometry": {"coordinates":[4.4359660149,50.9057769775],"type":"Point"}
}