{
  "type": "Feature",
  "properties": {
    "iso:country":"BE",
    "sg:address":"Rue Du Linchet 4",
    "sg:city":"Mont-saint-guibert (corbais)",
    "sg:classifiers":[
        {
            "category":"Building & Trades",
            "subcategory":"Landscaping Services",
            "type":"Services"
        }
    ],
    "sg:phone":"+32 10 65 51 65",
    "sg:postcode":"1435",
    "sg:province":"Brabant Wallon",
    "sg:tags":[
        "architect",
        "landscape"
    ],
    "wof:name":"Marchal & Co Sa",
    "wof:placetype":"venue"
},
  "geometry": {"coordinates":[4.6617422104,50.6497268677],"type":"Point"}
}