{
  "type": "Feature",
  "properties": {
    "iso:country":"BE",
    "sg:address":"Pastorijstraat 14",
    "sg:city":"Westerlo",
    "sg:classifiers":[
        {
            "category":"Banks & Credit Unions",
            "subcategory":"Investment Brokerage",
            "type":"Services"
        }
    ],
    "sg:phone":"+32 3 270 12 00",
    "sg:postcode":"2260",
    "sg:province":"Antwerpen",
    "sg:tags":[
        "auditor"
    ],
    "wof:name":"Boons R",
    "wof:placetype":"venue"
},
  "geometry": {"coordinates":[4.8352627754,51.0878791809],"type":"Point"}
}