{
  "type": "Feature",
  "properties": {
    "addr:full":"Ernest Brengierstraat 6b1 Oostrozebeke West-Vlaanderen 8780",
    "addr:housenumber":"6b1",
    "addr:postcode":"8780",
    "addr:street":"Ernest Brengierstraat",
    "iso:country":"BE",
    "sg:address":"Ernest Brengierstraat 6b1",
    "sg:city":"Oostrozebeke",
    "sg:classifiers":[
        {
            "category":"Government",
            "subcategory":"Police Station",
            "type":"Public Place"
        }
    ],
    "sg:phone":"+32 56 67 11 50",
    "sg:postcode":"8780",
    "sg:province":"West-Vlaanderen",
    "sg:tags":[
        "gendarmerie"
    ],
    "wof:name":"Federale Politie",
    "wof:placetype":"venue"
},
  "geometry": {"coordinates":[3.3343369961,50.9205436707],"type":"Point"}
}