{
  "type": "Feature",
  "properties": {
    "iso:country":"BE",
    "sg:address":"Oude Heerweg 1",
    "sg:city":"Deerlijk",
    "sg:orig_category":"Non-Classified Establishments",
    "sg:phone":"+32 56 77 99 43",
    "sg:postcode":"8540",
    "sg:province":"West-Vlaanderen",
    "wof:name":"Belo Mohairfluweel",
    "wof:placetype":"venue"
},
  "geometry": {"coordinates":[3.3523840904,50.8264274597],"type":"Point"}
}