{
  "type": "Feature",
  "properties": {
    "iso:country":"BE",
    "sg:address":"Rue De Birmingham 101-103",
    "sg:city":"Sint-jans-molenbeek/molenbeek-",
    "sg:orig_category":"Maisons de repos and r\u00e9sidences",
    "sg:phone":"+32 2 410 36 40",
    "sg:postcode":"1080",
    "sg:province":"Bruxelles-Capitale",
    "wof:name":"Home Birmingham",
    "wof:placetype":"venue"
},
  "geometry": {"coordinates":[4.3241329193,50.846572876],"type":"Point"}
}