{
  "type": "Feature",
  "properties": {
    "iso:country":"BE",
    "sg:address":"Lindeplein 15",
    "sg:city":"Mol",
    "sg:orig_category":"Boucheries",
    "sg:phone":"+32 14 31 11 57",
    "sg:postcode":"2400",
    "sg:province":"Antwerpen",
    "wof:name":"Gustaaf Luyckx",
    "wof:placetype":"venue"
},
  "geometry": {"coordinates":[5.0777978897,51.1881561279],"type":"Point"}
}