{
  "type": "Feature",
  "properties": {
    "iso:country":"BE",
    "sg:address":"Nieuwstraat 14",
    "sg:city":"Ingelmunster",
    "sg:orig_category":"Sportclubs",
    "sg:phone":"+32 51 31 86 50",
    "sg:postcode":"8770",
    "sg:province":"West-Vlaanderen",
    "wof:name":"Luchtkarabijnclub De Piottke",
    "wof:placetype":"venue"
},
  "geometry": {"coordinates":[3.2527639866,50.9227218628],"type":"Point"}
}