{
  "type": "Feature",
  "properties": {
    "addr:full":"Dieweg 133 Ukkel/uccle Bruxelles-Capitale 1180",
    "addr:housenumber":"133",
    "addr:postcode":"1180",
    "addr:street":"Dieweg;/",
    "iso:country":"BE",
    "sg:address":"Dieweg 133",
    "sg:city":"Ukkel/uccle",
    "sg:orig_category":"Sportclubs",
    "sg:phone":"+32 2 374 61 71",
    "sg:postcode":"1180",
    "sg:province":"Bruxelles-Capitale",
    "wof:name":"Club Presse Belge De Golf",
    "wof:placetype":"venue"
},
  "geometry": {"coordinates":[4.3494119644,50.796459198],"type":"Point"}
}