{
  "type": "Feature",
  "properties": {
    "addr:full":"Tarwelaan 21 Overijse Vlaams-Brabant 3090",
    "addr:housenumber":"21",
    "addr:postcode":"3090",
    "addr:street":"Tarwelaan",
    "iso:country":"BE",
    "sg:address":"Tarwelaan 21",
    "sg:city":"Overijse",
    "sg:classifiers":[
        {
            "category":"Health Services",
            "subcategory":"Health Practitioner",
            "type":"Services"
        }
    ],
    "sg:phone":"+32 2 657 93 49",
    "sg:postcode":"3090",
    "sg:province":"Vlaams-Brabant",
    "sg:tags":[
        "physiotherapist"
    ],
    "wof:name":"Odeurs Arlette",
    "wof:placetype":"venue"
},
  "geometry": {"coordinates":[4.4952487946,50.7743263245],"type":"Point"}
}