{
  "type": "Feature",
  "properties": {
    "iso:country":"BE",
    "sg:address":"Pieter De Nefstraat 6",
    "sg:city":"Turnhout",
    "sg:orig_category":"Artsen and specialisten",
    "sg:phone":"+32 14 43 51 01",
    "sg:postcode":"2300",
    "sg:province":"Antwerpen",
    "wof:name":"J.p. Raes",
    "wof:placetype":"venue"
},
  "geometry": {"coordinates":[4.9509367943,51.3212471008],"type":"Point"}
}