{
  "type": "Feature",
  "properties": {
    "iso:country":"BE",
    "sg:address":"Rue Du Moulin 220",
    "sg:city":"Ohey",
    "sg:orig_category":"Autombile concessionaires",
    "sg:phone":"+32 85 61 22 96",
    "sg:postcode":"5350",
    "sg:province":"Namur",
    "wof:name":"Gar Graux Ph",
    "wof:placetype":"venue"
},
  "geometry": {"coordinates":[5.1258001328,50.4361953735],"type":"Point"}
}