{
  "type": "Feature",
  "properties": {
    "addr:full":"Dreef 36 Essen Antwerpen 2910",
    "addr:housenumber":"36",
    "addr:postcode":"2910",
    "addr:street":"Dreef",
    "iso:country":"BE",
    "sg:address":"Dreef 36",
    "sg:city":"Essen",
    "sg:orig_category":"Verlichting and huishoudartikelen",
    "sg:phone":"+32 3 667 42 66",
    "sg:postcode":"2910",
    "sg:province":"Antwerpen",
    "wof:name":"Electro Vorsselmans",
    "wof:placetype":"venue"
},
  "geometry": {"coordinates":[4.4745249748,51.4683303833],"type":"Point"}
}