{
  "type": "Feature",
  "properties": {
    "iso:country":"BE",
    "sg:address":"Boulevard Audent 29",
    "sg:city":"Charleroi",
    "sg:classifiers":[
        {
            "category":"Arts & Performance",
            "subcategory":"Theater",
            "type":"Entertainment"
        }
    ],
    "sg:phone":"+32 71 63 49 70",
    "sg:postcode":"6000",
    "sg:province":"Hainaut",
    "sg:tags":[
        "group",
        "theatre"
    ],
    "wof:name":"Th\u00e9\u00e2tre De La Guimbarde Asbl",
    "wof:placetype":"venue"
},
  "geometry": {"coordinates":[4.4449062347,50.4099197388],"type":"Point"}
}