{
  "type": "Feature",
  "properties": {
    "addr:full":"Winston Churchilllaan 148a Ukkel/uccle Bruxelles-Capitale 1180",
    "addr:housenumber":"148a",
    "addr:postcode":"1180",
    "addr:street":"Winston Churchilllaan;/",
    "iso:country":"BE",
    "sg:address":"Winston Churchilllaan 148a",
    "sg:city":"Ukkel/uccle",
    "sg:classifiers":[
        {
            "category":"Restaurant",
            "type":"Food & Drink"
        }
    ],
    "sg:phone":"+32 2 345 66 63",
    "sg:postcode":"1180",
    "sg:province":"Bruxelles-Capitale",
    "wof:name":"L'estanquet",
    "wof:placetype":"venue"
},
  "geometry": {"coordinates":[4.3572840691,50.8117103577],"type":"Point"}
}