{
  "type": "Feature",
  "properties": {
    "addr:full":"Jagerslaan 23 Tervuren Vlaams-Brabant 3080",
    "addr:housenumber":"23",
    "addr:postcode":"3080",
    "addr:street":"Jagerslaan",
    "iso:country":"BE",
    "sg:address":"Jagerslaan 23",
    "sg:city":"Tervuren",
    "sg:orig_category":"M\u00e9decins and sp\u00e9cialistes",
    "sg:phone":"+32 2 767 24 23",
    "sg:postcode":"3080",
    "sg:province":"Vlaams-Brabant",
    "wof:name":"F. De Zegher",
    "wof:placetype":"venue"
},
  "geometry": {"coordinates":[4.5526199341,50.8423805237],"type":"Point"}
}