{
  "type": "Feature",
  "properties": {
    "iso:country":"BE",
    "sg:address":"Rue De Wansijn 76",
    "sg:city":"Bruxelles (uccle)",
    "sg:classifiers":[
        {
            "category":"Shopping",
            "subcategory":"Florist",
            "type":"Retail Goods"
        }
    ],
    "sg:phone":"+32 2 375 76 86",
    "sg:postcode":"1180",
    "sg:province":"Bruxelles-Capitale",
    "wof:name":"Ile Aux Fleurs",
    "wof:placetype":"venue"
},
  "geometry": {"coordinates":[4.3600811958,50.7896575928],"type":"Point"}
}