{
  "type": "Feature",
  "properties": {
    "addr:full":"Chauss\u00e9e De Heusy 254 Verviers Li\u00e8ge 4800",
    "addr:housenumber":"254",
    "addr:postcode":"4800",
    "addr:street":"Chausse\u0301E De Heusy",
    "iso:country":"BE",
    "sg:address":"Chauss\u00e9e De Heusy 254",
    "sg:city":"Verviers",
    "sg:classifiers":[
        {
            "category":"Insurance",
            "subcategory":"Insurance Agent",
            "type":"Services"
        }
    ],
    "sg:phone":"+32 87 22 96 68",
    "sg:postcode":"4800",
    "sg:province":"Li\u00e8ge",
    "sg:tags":[
        "broker"
    ],
    "wof:name":"Beaupain L",
    "wof:placetype":"venue"
},
  "geometry": {"coordinates":[5.8653259277,50.5831718445],"type":"Point"}
}