{
  "type": "Feature",
  "properties": {
    "addr:full":"Chauss\u00e9e De Bruxelles 49 Genappe (glabais) Brabant Wallon 1473",
    "addr:housenumber":"49",
    "addr:postcode":"1473",
    "addr:street":"Chausse\u0301E De Bruxelles;Wallon",
    "iso:country":"BE",
    "sg:address":"Chauss\u00e9e De Bruxelles 49",
    "sg:city":"Genappe (glabais)",
    "sg:classifiers":[
        {
            "category":"Building & Trades",
            "subcategory":"Construction",
            "type":"Services"
        }
    ],
    "sg:phone":"+32 67 77 37 01",
    "sg:postcode":"1473",
    "sg:province":"Brabant Wallon",
    "sg:tags":[
        "installation",
        "-",
        "central",
        "heating"
    ],
    "wof:name":"Conforkit-a.e.i.c.c. Sprl",
    "wof:placetype":"venue"
},
  "geometry": {"coordinates":[4.4322447777,50.6305961609],"type":"Point"}
}