{
  "type": "Feature",
  "properties": {
    "addr:full":"Ommegangstraat 25 Liedekerke Vlaams-Brabant 1770",
    "addr:housenumber":"25",
    "addr:postcode":"1770",
    "addr:street":"Ommegangstraat;Vlaams-Brabant",
    "iso:country":"BE",
    "sg:address":"Ommegangstraat 25",
    "sg:city":"Liedekerke",
    "sg:orig_category":"M\u00e9decins and sp\u00e9cialistes",
    "sg:phone":"+32 53 66 75 23",
    "sg:postcode":"1770",
    "sg:province":"Vlaams-Brabant",
    "wof:name":"L. Cassiman",
    "wof:placetype":"venue"
},
  "geometry": {"coordinates":[4.0943598747,50.8761444092],"type":"Point"}
}