{
  "type": "Feature",
  "properties": {
    "iso:country":"BE",
    "sg:address":"Brugsesteenweg 390",
    "sg:city":"Kuurne",
    "sg:classifiers":[
        {
            "category":"Home & Garden",
            "subcategory":"Furniture",
            "type":"Retail Goods"
        }
    ],
    "sg:phone":"+32 56 75 99 99",
    "sg:postcode":"8520",
    "sg:province":"West-Vlaanderen",
    "sg:tags":[
        "-"
    ],
    "wof:name":"Arkade-gloster Nv",
    "wof:placetype":"venue"
},
  "geometry": {"coordinates":[3.2716169357,50.8699836731],"type":"Point"}
}