{
  "type": "Feature",
  "properties": {
    "addr:full":"Cardijnplein 14 Bornem 2680",
    "addr:housenumber":"14",
    "addr:postcode":"2680",
    "addr:street":"Cardijnplein",
    "iso:country":"BE",
    "sg:address":"Cardijnplein 14",
    "sg:city":"Bornem",
    "sg:classifiers":[
        {
            "category":"Banks & Credit Unions",
            "subcategory":"Bank",
            "type":"Services"
        }
    ],
    "sg:phone":"+32 3 889 39 02",
    "sg:postcode":"2680",
    "wof:name":"Aslk-cger Bank",
    "wof:placetype":"venue"
},
  "geometry": {"coordinates":[145.93003845210001,-34.3445014954],"type":"Point"}
}