{
  "type": "Feature",
  "properties": {
    "iso:country":"BE",
    "sg:address":"Lievevrouwestraat 23",
    "sg:city":"Ranst",
    "sg:classifiers":[
        {
            "category":"Building & Trades",
            "subcategory":"Construction",
            "type":"Services"
        }
    ],
    "sg:phone":"+32 3 485 66 38",
    "sg:postcode":"2520",
    "sg:province":"Antwerpen",
    "sg:tags":[
        "installation",
        "-",
        "central",
        "heating"
    ],
    "wof:name":"Immo Norda Heating Bvba",
    "wof:placetype":"venue"
},
  "geometry": {"coordinates":[4.5617117882,51.1893959045],"type":"Point"}
}