{
  "type": "Feature",
  "properties": {
    "addr:full":"Kleine Wouwerlaan 67 Meise Vlaams-Brabant 1860",
    "addr:housenumber":"67",
    "addr:postcode":"1860",
    "addr:street":"Kleine Wouwerlaan",
    "iso:country":"BE",
    "sg:address":"Kleine Wouwerlaan 67",
    "sg:city":"Meise",
    "sg:orig_category":"Banques and organismes de cr\u00e9dit",
    "sg:phone":"+32 2 269 59 74",
    "sg:postcode":"1860",
    "sg:province":"Vlaams-Brabant",
    "wof:name":"Centea",
    "wof:placetype":"venue"
},
  "geometry": {"coordinates":[4.3161511421,50.9363059998],"type":"Point"}
}