{
  "type": "Feature",
  "properties": {
    "iso:country":"BE",
    "sg:address":"Ter Ferrants 16ba",
    "sg:city":"Kuurne",
    "sg:orig_category":"Produits surgel\u00e9s Gr",
    "sg:phone":"+32 56 35 76 74",
    "sg:postcode":"8520",
    "sg:province":"West-Vlaanderen",
    "wof:name":"Roomcentrale De Neve",
    "wof:placetype":"venue"
},
  "geometry": {"coordinates":[3.2652139664,50.8496437073],"type":"Point"}
}