{
  "type": "Feature",
  "properties": {
    "addr:full":"Grand'place 41b Nivelles Brabant Wallon 1400",
    "addr:housenumber":"41b",
    "addr:postcode":"1400",
    "addr:street":"Grand'Place",
    "iso:country":"BE",
    "sg:address":"Grand'place 41b",
    "sg:city":"Nivelles",
    "sg:orig_category":"M\u00e9decins and sp\u00e9cialistes",
    "sg:phone":"+32 67 21 92 18",
    "sg:postcode":"1400",
    "sg:province":"Brabant Wallon",
    "wof:name":"Renaud Stinglhamber",
    "wof:placetype":"venue"
},
  "geometry": {"coordinates":[4.3232650757,50.596786499],"type":"Point"}
}