{
  "type": "Feature",
  "properties": {
    "addr:full":"Pijnbroekstraat 184 Sint-pieters-leeuw Vlaams-Brabant 1600",
    "addr:housenumber":"184",
    "addr:postcode":"1600",
    "addr:street":"Pijnbroekstraat",
    "iso:country":"BE",
    "sg:address":"Pijnbroekstraat 184",
    "sg:city":"Sint-pieters-leeuw",
    "sg:orig_category":"HUISBRANDOLIE",
    "sg:phone":"+32 2 356 61 46",
    "sg:postcode":"1600",
    "sg:province":"Vlaams-Brabant",
    "wof:name":"Jean Steens",
    "wof:placetype":"venue"
},
  "geometry": {"coordinates":[4.2334861755,50.7646751404],"type":"Point"}
}