{
  "type": "Feature",
  "properties": {
    "iso:country":"BE",
    "sg:address":"Rue Saint-l\u00c9onard 116",
    "sg:city":"Li\u00c8ge",
    "sg:orig_category":"Pain, p\u00e2tisseries and confiseries",
    "sg:phone":"+32 4 227 15 32",
    "sg:postcode":"4000",
    "sg:province":"Li\u00e8ge",
    "wof:name":"Recettes De Grand-m\u00c8re",
    "wof:placetype":"venue"
},
  "geometry": {"coordinates":[5.5881910324,50.6483840942],"type":"Point"}
}