{
  "type": "Feature",
  "properties": {
    "addr:full":"Avenue G\u00e9n\u00e9ral Aymes 1 Gembloux-sur-orneau (gembloux) Namur 5030",
    "addr:housenumber":"1",
    "addr:postcode":"5030",
    "addr:street":"Avenue Ge\u0301Ne\u0301Ral Aymes;Namur",
    "iso:country":"BE",
    "sg:address":"Avenue G\u00e9n\u00e9ral Aymes 1",
    "sg:city":"Gembloux-sur-orneau (gembloux)",
    "sg:classifiers":[
        {
            "category":"Shopping",
            "subcategory":"Pets & Pet Supplies",
            "type":"Retail Goods"
        }
    ],
    "sg:phone":"+32 81 61 58 24",
    "sg:postcode":"5030",
    "sg:province":"Namur",
    "sg:tags":[
        "aquarium",
        "accessory"
    ],
    "wof:name":"Aquatique (l')",
    "wof:placetype":"venue"
},
  "geometry": {"coordinates":[4.6839699745,50.5623283386],"type":"Point"}
}