{
  "type": "Feature",
  "properties": {
    "iso:country":"BE",
    "sg:address":"Avenue Frank Courtens 131",
    "sg:city":"Schaarbeek/schaerbeek",
    "sg:orig_category":"Boekenuitgeverijen Platenmaatschappijen",
    "sg:phone":"+32 2 705 06 22",
    "sg:postcode":"1030",
    "sg:province":"Bruxelles-Capitale",
    "wof:name":"Chryslie Music",
    "wof:placetype":"venue"
},
  "geometry": {"coordinates":[4.403192997,50.8600234985],"type":"Point"}
}