{
  "type": "Feature",
  "properties": {
    "iso:country":"BE",
    "sg:address":"Rue Brigade Piron 20",
    "sg:city":"Charleroi (montignies-sur-sambre)",
    "sg:classifiers":[
        {
            "category":"Health Services",
            "subcategory":"Health Practitioner",
            "type":"Services"
        }
    ],
    "sg:phone":"+32 71 33 08 04",
    "sg:postcode":"6061",
    "sg:province":"Hainaut",
    "sg:tags":[
        "physiotherapist"
    ],
    "wof:name":"Jacot Isabelle",
    "wof:placetype":"venue"
},
  "geometry": {"coordinates":[4.4657521248,50.4040489197],"type":"Point"}
}