{
  "type": "Feature",
  "properties": {
    "addr:full":"Rue Le Faubourg 14 Couvin (dailly) Namur 5660",
    "addr:housenumber":"14",
    "addr:postcode":"5660",
    "addr:street":"Rue Le Faubourg;Dailly",
    "iso:country":"BE",
    "sg:address":"Rue Le Faubourg 14",
    "sg:city":"Couvin (dailly)",
    "sg:classifiers":[
        {
            "category":"Professional",
            "subcategory":"Accounting & Tax Preparation",
            "type":"Services"
        }
    ],
    "sg:phone":"+32 478 31 81 42",
    "sg:postcode":"5660",
    "sg:province":"Namur",
    "sg:tags":[
        "bookkeeper"
    ],
    "wof:name":"Ostheimer N",
    "wof:placetype":"venue"
},
  "geometry": {"coordinates":[4.4350218773,50.0563049316],"type":"Point"}
}