{
  "type": "Feature",
  "properties": {
    "iso:country":"BE",
    "sg:address":"Rue De Boussu 216b1",
    "sg:city":"Saint-ghislain",
    "sg:classifiers":[
        {
            "category":"Cafe",
            "type":"Food & Drink"
        }
    ],
    "sg:phone":"+32 65 52 01 92",
    "sg:postcode":"7334",
    "sg:province":"Hainaut",
    "sg:tags":[
        "caf\u00e9s"
    ],
    "wof:name":"Caf\u00c9 Le Penalty",
    "wof:placetype":"venue"
},
  "geometry": {"coordinates":[3.7779951096,50.4636955261],"type":"Point"}
}