{
  "type": "Feature",
  "properties": {
    "iso:country":"BE",
    "sg:address":"Neremstraat 60",
    "sg:city":"Tongeren",
    "sg:orig_category":"Eleveurs and marchands de porcs",
    "sg:phone":"+32 12 23 65 16",
    "sg:postcode":"3700",
    "sg:province":"Limburg",
    "wof:name":"Marcel Tilkin",
    "wof:placetype":"venue"
},
  "geometry": {"coordinates":[5.4733800888,50.7776031494],"type":"Point"}
}