{
  "type": "Feature",
  "properties": {
    "addr:full":"Oude Pastorijstraat 21 Hamont-achel (achel) Limburg 3930",
    "addr:housenumber":"21",
    "addr:postcode":"3930",
    "addr:street":"Oude Pastorijstraat",
    "iso:country":"BE",
    "sg:address":"Oude Pastorijstraat 21",
    "sg:city":"Hamont-achel (achel)",
    "sg:classifiers":[
        {
            "category":"Retail",
            "subcategory":"Auto Repair",
            "type":"Services"
        }
    ],
    "sg:phone":"+32 11 64 53 66",
    "sg:postcode":"3930",
    "sg:province":"Limburg",
    "sg:tags":[
        "garage"
    ],
    "wof:name":"Huybers/citroen",
    "wof:placetype":"venue"
},
  "geometry": {"coordinates":[5.4705018997,51.2582397461],"type":"Point"}
}