{
  "type": "Feature",
  "properties": {
    "addr:full":"Rue Jean-de-boheme 11 Marche-en-famenne Luxembourg 6900",
    "addr:housenumber":"11",
    "addr:postcode":"6900",
    "addr:street":"Rue Jean-De-Boheme",
    "iso:country":"BE",
    "sg:address":"Rue Jean-de-boheme 11",
    "sg:city":"Marche-en-famenne",
    "sg:orig_category":"Advocaten and juridische adviseurs",
    "sg:phone":"+32 84 31 12 52",
    "sg:postcode":"6900",
    "sg:province":"Luxembourg",
    "wof:name":"Pierre Lenelle",
    "wof:placetype":"venue"
},
  "geometry": {"coordinates":[5.3442168236,50.2284164429],"type":"Point"}
}