{
  "type": "Feature",
  "properties": {
    "iso:country":"BE",
    "sg:address":"Achterweg 16",
    "sg:city":"Aalst",
    "sg:orig_category":"Services de publipostage",
    "sg:phone":"+32 53 71 13 14",
    "sg:postcode":"9300",
    "sg:province":"Oost-Vlaanderen",
    "wof:name":"No\u00cbl B.",
    "wof:placetype":"venue"
},
  "geometry": {"coordinates":[4.0760140419,50.9464912415],"type":"Point"}
}