{
  "type": "Feature",
  "properties": {
    "iso:country":"BE",
    "sg:address":"Guldendelle 57",
    "sg:city":"Zaventem",
    "sg:orig_category":"Timbres, monnaies and troph\u00e9es",
    "sg:phone":"+32 2 759 56 04",
    "sg:postcode":"1930",
    "sg:province":"Vlaams-Brabant",
    "wof:name":"Maison Philamil",
    "wof:placetype":"venue"
},
  "geometry": {"coordinates":[4.5161519051,50.8813743591],"type":"Point"}
}