{
  "type": "Feature",
  "properties": {
    "addr:full":"Chauss\u00e9e De Huy 71 Chaumont-gistoux Brabant Wallon 1325",
    "addr:housenumber":"71",
    "addr:postcode":"1325",
    "addr:street":"Chausse\u0301E De Huy",
    "iso:country":"BE",
    "sg:address":"Chauss\u00e9e De Huy 71",
    "sg:city":"Chaumont-gistoux",
    "sg:classifiers":[
        {
            "category":"Organizations",
            "subcategory":"Professional Association",
            "type":"Services"
        }
    ],
    "sg:phone":"+32 10 68 96 86",
    "sg:postcode":"1325",
    "sg:province":"Brabant Wallon",
    "sg:tags":[
        "organisation",
        "seminar"
    ],
    "wof:name":"Or Ange Bleu (l')",
    "wof:placetype":"venue"
},
  "geometry": {"coordinates":[4.6871581078,50.6898727417],"type":"Point"}
}