{
  "type": "Feature",
  "properties": {
    "iso:country":"BE",
    "sg:address":"Strandlaan 241",
    "sg:city":"Koksijde",
    "sg:classifiers":[
        {
            "category":"Personal",
            "subcategory":"Beauty Salon",
            "type":"Services"
        }
    ],
    "sg:phone":"+32 58 52 42 04",
    "sg:postcode":"8670",
    "sg:province":"West-Vlaanderen",
    "wof:name":"Amber",
    "wof:placetype":"venue"
},
  "geometry": {"coordinates":[2.6135759354,51.1082801819],"type":"Point"}
}