{
  "type": "Feature",
  "properties": {
    "addr:full":"Schoterweg 281 Tessenderlo Limburg 3980",
    "addr:housenumber":"281",
    "addr:postcode":"3980",
    "addr:street":"Schoterweg",
    "iso:country":"BE",
    "sg:address":"Schoterweg 281",
    "sg:city":"Tessenderlo",
    "sg:orig_category":"Landmeters",
    "sg:phone":"+32 13 67 19 08",
    "sg:postcode":"3980",
    "sg:province":"Limburg",
    "wof:name":"Michel Raeyen",
    "wof:placetype":"venue"
},
  "geometry": {"coordinates":[5.0272369385,51.0670623779],"type":"Point"}
}