{
  "type": "Feature",
  "properties": {
    "addr:full":"Havermarkt 39-41 Box 2 Hasselt Limburg 3500",
    "addr:housenumber":"39-41;2",
    "addr:postcode":"3500",
    "addr:street":"Havermarkt;Box",
    "iso:country":"BE",
    "sg:address":"Havermarkt 39-41 Box 2",
    "sg:city":"Hasselt",
    "sg:classifiers":[
        {
            "category":"Banks & Credit Unions",
            "subcategory":"Financial Services",
            "type":"Services"
        }
    ],
    "sg:phone":"+32 11 22 29 99",
    "sg:postcode":"3500",
    "sg:province":"Limburg",
    "sg:tags":[
        "loan",
        "mortgage"
    ],
    "wof:name":"Immotheker Hamers Romanski",
    "wof:placetype":"venue"
},
  "geometry": {"coordinates":[5.3345217705,50.9294395447],"type":"Point"}
}