{
  "type": "Feature",
  "properties": {
    "iso:country":"BE",
    "sg:address":"Kleine Laan 10",
    "sg:city":"Sint-niklaas",
    "sg:orig_category":"Brood, gebak and snoepgoed",
    "sg:phone":"+32 3 776 61 41",
    "sg:postcode":"9100",
    "sg:province":"Oost-Vlaanderen",
    "wof:name":"Bakkerij Alex",
    "wof:placetype":"venue"
},
  "geometry": {"coordinates":[4.1399130821,51.1697998047],"type":"Point"}
}