{
  "type": "Feature",
  "properties": {
    "addr:full":"Rue Laurent Vandenhoven 56 Bruxelles (evere) Bruxelles-Capitale 1140",
    "addr:housenumber":"56",
    "addr:postcode":"1140",
    "addr:street":"Rue Laurent Vandenhoven",
    "iso:country":"BE",
    "sg:address":"Rue Laurent Vandenhoven 56",
    "sg:city":"Bruxelles (evere)",
    "sg:classifiers":[
        {
            "category":"Bars & Pubs",
            "type":"Food & Drink"
        }
    ],
    "sg:phone":"+32 2 218 02 85",
    "sg:postcode":"1140",
    "sg:province":"Bruxelles-Capitale",
    "wof:name":"Calypso",
    "wof:placetype":"venue"
},
  "geometry": {"coordinates":[4.4054589272,50.8822059631],"type":"Point"}
}