{
  "type": "Feature",
  "properties": {
    "iso:country":"BE",
    "sg:address":"Koning Albertstraat 69",
    "sg:city":"Mechelen",
    "sg:classifiers":[
        {
            "category":"Fast Food",
            "type":"Food & Drink"
        }
    ],
    "sg:phone":"+32 15 20 89 36",
    "sg:postcode":"2800",
    "sg:province":"Antwerpen",
    "sg:tags":[
        "fried",
        "stand",
        "potato"
    ],
    "wof:name":"Van Grootven G",
    "wof:placetype":"venue"
},
  "geometry": {"coordinates":[4.4705262184,51.0257949829],"type":"Point"}
}