{
  "type": "Feature",
  "properties": {
    "iso:country":"BE",
    "sg:address":"Stationsstraat 6",
    "sg:city":"Meise",
    "sg:orig_category":"Ordinateurs and \u00e9quipement informatique",
    "sg:phone":"+32 78 16 94 09",
    "sg:postcode":"1861",
    "sg:province":"Vlaams-Brabant",
    "wof:name":"Macsimum",
    "wof:placetype":"venue"
},
  "geometry": {"coordinates":[4.3097190857,50.9500045776],"type":"Point"}
}