{
  "type": "Feature",
  "properties": {
    "iso:country":"BE",
    "sg:address":"Chauss\u00c9e De Mons 11",
    "sg:city":"Anderlues",
    "sg:orig_category":"Tabac. Journaux. Librairies. Fournitures de bureau",
    "sg:phone":"+32 71 52 31 38",
    "sg:postcode":"6150",
    "sg:province":"Hainaut",
    "wof:name":"Librairie Du Monument",
    "wof:placetype":"venue"
},
  "geometry": {"coordinates":[4.2877259254,50.4038581848],"type":"Point"}
}