{
  "type": "Feature",
  "properties": {
    "iso:country":"BE",
    "sg:address":"Rue Justin Sauvenier 37",
    "sg:city":"Bl\u00e9gny (barchon)",
    "sg:classifiers":[
        {
            "category":"Manufacturing",
            "subcategory":"Tools & Machinery",
            "type":"Manufacturing & Wholesale Goods"
        }
    ],
    "sg:phone":"+32 4 387 61 90",
    "sg:postcode":"4671",
    "sg:province":"Li\u00e8ge",
    "sg:tags":[
        "machine"
    ],
    "wof:name":"Erd\u00e9mac 1895 Sprl",
    "wof:placetype":"venue"
},
  "geometry": {"coordinates":[5.7031908035,50.6690330505],"type":"Point"}
}