{
  "type": "Feature",
  "properties": {
    "addr:full":"Rue Du M\u00e9nil 1 Braine L'alleud (braine-l'alleud) Brabant Wallon 1420",
    "addr:housenumber":"1",
    "addr:postcode":"1420",
    "addr:street":"Rue Du Me\u0301Nil",
    "iso:country":"BE",
    "sg:address":"Rue Du M\u00e9nil 1",
    "sg:city":"Braine L'alleud (braine-l'alleud)",
    "sg:classifiers":[
        {
            "category":"Shopping",
            "subcategory":"Florist",
            "type":"Retail Goods"
        }
    ],
    "sg:phone":"+32 2 384 09 99",
    "sg:postcode":"1420",
    "sg:province":"Brabant Wallon",
    "wof:name":"Racines",
    "wof:placetype":"venue"
},
  "geometry": {"coordinates":[-75.60595703120001,37.7877616882],"type":"Point"}
}