{
  "type": "Feature",
  "properties": {
    "addr:full":"Avenue Vanp\u00e9e 7 Wavre Brabant Wallon 1300",
    "addr:housenumber":"7;1300",
    "addr:street":"Avenue Vanpe\u0301E",
    "iso:country":"BE",
    "sg:address":"Avenue Vanp\u00e9e 7",
    "sg:city":"Wavre",
    "sg:classifiers":[
        {
            "category":"Retail",
            "subcategory":"Repair Shop",
            "type":"Services"
        }
    ],
    "sg:phone":"+32 10 22 83 90",
    "sg:postcode":"1300",
    "sg:province":"Brabant Wallon",
    "sg:tags":[
        "-",
        "clothing",
        "alteration"
    ],
    "wof:name":"Paty Couture",
    "wof:placetype":"venue"
},
  "geometry": {"coordinates":[4.6133780479,50.7203941345],"type":"Point"}
}