{
  "type": "Feature",
  "properties": {
    "iso:country":"BE",
    "sg:address":"Halleux 2",
    "sg:city":"Comblain-au-pont",
    "sg:classifiers":[
        {
            "category":"Organizations",
            "subcategory":"Professional Association",
            "type":"Services"
        }
    ],
    "sg:phone":"+32 4 369 29 27",
    "sg:postcode":"4170",
    "sg:province":"Li\u00e8ge",
    "sg:tags":[
        "organisation",
        "seminar"
    ],
    "wof:name":"Le Moulin Du Halleux Sprl",
    "wof:placetype":"venue"
},
  "geometry": {"coordinates":[5.5790548325,50.4735450745],"type":"Point"}
}