{
  "type": "Feature",
  "properties": {
    "addr:full":"Hoogstraat 74 Denderleeuw (iddergem) Oost-Vlaanderen 9472",
    "addr:housenumber":"74",
    "addr:postcode":"9472",
    "addr:street":"Hoogstraat",
    "iso:country":"BE",
    "sg:address":"Hoogstraat 74",
    "sg:city":"Denderleeuw (iddergem)",
    "sg:classifiers":[
        {
            "category":"Retail",
            "subcategory":"Repair Shop",
            "type":"Services"
        }
    ],
    "sg:phone":"+32 53 66 08 64",
    "sg:postcode":"9472",
    "sg:province":"Oost-Vlaanderen",
    "wof:name":"Karwei-dienst Danny",
    "wof:placetype":"venue"
},
  "geometry": {"coordinates":[4.0501790047,50.8752746582],"type":"Point"}
}