{
  "type": "Feature",
  "properties": {
    "iso:country":"BE",
    "sg:address":"Zeelaan 257",
    "sg:city":"Koksijde",
    "sg:classifiers":[
        {
            "category":"Restaurant",
            "type":"Food & Drink"
        }
    ],
    "sg:phone":"+32 58 51 30 85",
    "sg:postcode":"8670",
    "sg:province":"West-Vlaanderen",
    "wof:name":"Mouscronnoise",
    "wof:placetype":"venue"
},
  "geometry": {"coordinates":[2.6368970871,51.1171073914],"type":"Point"}
}