{
  "type": "Feature",
  "properties": {
    "addr:full":"Rue De Bomel 104 Namur Namur 5000",
    "addr:housenumber":"104",
    "addr:postcode":"5000",
    "addr:street":"Rue De Bomel",
    "iso:country":"BE",
    "sg:address":"Rue De Bomel 104",
    "sg:city":"Namur",
    "sg:classifiers":[
        {
            "category":"Retail",
            "subcategory":"Veterinary Services",
            "type":"Services"
        }
    ],
    "sg:phone":"+32 81 22 55 89",
    "sg:postcode":"5000",
    "sg:province":"Namur",
    "sg:tags":[
        "veterinarian"
    ],
    "wof:name":"Comps Y",
    "wof:placetype":"venue"
},
  "geometry": {"coordinates":[4.8652300835,50.4738082886],"type":"Point"}
}