{
  "type": "Feature",
  "properties": {
    "iso:country":"BE",
    "sg:address":"Rue De Tilleur 118-140",
    "sg:city":"Saint-nicolas",
    "sg:classifiers":[
        {
            "category":"Transit Center",
            "subcategory":"Passenger",
            "type":"Transportation"
        }
    ],
    "sg:phone":"+32 477 27 04 57",
    "sg:postcode":"4420",
    "sg:province":"Li\u00e8ge",
    "sg:tags":[
        "car",
        "trailer"
    ],
    "wof:name":"Atelier Jean Del'cour-eta",
    "wof:placetype":"venue"
},
  "geometry": {"coordinates":[5.5453600883,50.6301422119],"type":"Point"}
}