{
  "type": "Feature",
  "properties": {
    "iso:country":"BE",
    "sg:address":"Stationsstraat 59",
    "sg:city":"Dilsen-stokkem (elen)",
    "sg:classifiers":[
        {
            "category":"Retail",
            "subcategory":"Event Space",
            "type":"Services"
        }
    ],
    "sg:phone":"+32 496 20 92 62",
    "sg:postcode":"3650",
    "sg:province":"Limburg",
    "sg:tags":[
        "organisation"
    ],
    "wof:name":"Maverick Events",
    "wof:placetype":"venue"
},
  "geometry": {"coordinates":[5.7448577881,51.0685119629],"type":"Point"}
}