{
  "type": "Feature",
  "properties": {
    "iso:country":"BE",
    "sg:address":"Rue Sainte-mon\u00e9gonde 44",
    "sg:city":"Chimay (salles)",
    "sg:classifiers":[
        {
            "category":"Cafe",
            "type":"Food & Drink"
        }
    ],
    "sg:phone":"+32 60 21 50 99",
    "sg:postcode":"6460",
    "sg:province":"Hainaut",
    "sg:tags":[
        "snack-bars"
    ],
    "wof:name":"Grange Saint-antoine (la)",
    "wof:placetype":"venue"
},
  "geometry": {"coordinates":[4.2464499474,50.0559997559],"type":"Point"}
}