{
  "type": "Feature",
  "properties": {
    "iso:country":"BE",
    "sg:address":"Provinciale Steenweg 55",
    "sg:city":"Schelle",
    "sg:orig_category":"Caf\u00e9s Ruimtes voor conferenties, recepties and feesten",
    "sg:phone":"+32 3 877 36 63",
    "sg:postcode":"2627",
    "sg:province":"Antwerpen",
    "wof:name":"Taverne Ravenstein",
    "wof:placetype":"venue"
},
  "geometry": {"coordinates":[4.3368811607,51.1286849976],"type":"Point"}
}