{
  "type": "Feature",
  "properties": {
    "addr:full":"Opstal Dries 12 Buggenhout Oost-Vlaanderen 9255",
    "addr:housenumber":"12",
    "addr:postcode":"9255",
    "addr:street":"Opstal Dries",
    "iso:country":"BE",
    "sg:address":"Opstal Dries 12",
    "sg:city":"Buggenhout",
    "sg:orig_category":"Epiceries",
    "sg:phone":"+32 52 35 75 63",
    "sg:postcode":"9255",
    "sg:province":"Oost-Vlaanderen",
    "wof:name":"J De Backer",
    "wof:placetype":"venue"
},
  "geometry": {"coordinates":[4.2179598808,51.028339386],"type":"Point"}
}