{
  "type": "Feature",
  "properties": {
    "iso:country":"BE",
    "sg:address":"Rooierheidestraat 53",
    "sg:city":"Diepenbeek",
    "sg:classifiers":[
        {
            "category":"Building & Trades",
            "subcategory":"Construction",
            "type":"Services"
        }
    ],
    "sg:phone":"+32 11 32 11 03",
    "sg:postcode":"3590",
    "sg:province":"Limburg",
    "sg:tags":[
        "installation",
        "-",
        "central",
        "heating"
    ],
    "wof:name":"Minerva Franco",
    "wof:placetype":"venue"
},
  "geometry": {"coordinates":[5.4143109322,50.9323272705],"type":"Point"}
}