{
  "type": "Feature",
  "properties": {
    "addr:full":"Rue Du Verger 8 Bruxelles (auderghem) Bruxelles-Capitale 1160",
    "addr:housenumber":"8",
    "addr:postcode":"1160",
    "addr:street":"Rue Du Verger",
    "iso:country":"BE",
    "sg:address":"Rue Du Verger 8",
    "sg:city":"Bruxelles (auderghem)",
    "sg:classifiers":[
        {
            "category":"Home & Garden",
            "subcategory":"Home Furnishings",
            "type":"Retail Goods"
        }
    ],
    "sg:phone":"+32 2 675 11 72",
    "sg:postcode":"1160",
    "sg:province":"Bruxelles-Capitale",
    "sg:tags":[
        "interior",
        "decoration"
    ],
    "wof:name":"Vanneste A",
    "wof:placetype":"venue"
},
  "geometry": {"coordinates":[4.430316925,50.8175125122],"type":"Point"}
}