{
  "type": "Feature",
  "properties": {
    "addr:full":"Chauss\u00e9e De Charleroi 97 Anderlues Hainaut 6150",
    "addr:housenumber":"97",
    "addr:postcode":"6150",
    "addr:street":"Chausse\u0301E De Charleroi",
    "iso:country":"BE",
    "sg:address":"Chauss\u00e9e De Charleroi 97",
    "sg:city":"Anderlues",
    "sg:orig_category":"Autombile concessionaires",
    "sg:phone":"+32 71 52 50 75",
    "sg:postcode":"6150",
    "sg:province":"Hainaut",
    "wof:name":"Ets Daniel Van Der Maren Sprl",
    "wof:placetype":"venue"
},
  "geometry": {"coordinates":[4.2808380127,50.4061775208],"type":"Point"}
}