{
  "type": "Feature",
  "properties": {
    "addr:full":"Rue De L'eglise 113 B Gembloux Namur 5030",
    "addr:housenumber":"113 b",
    "addr:postcode":"5030",
    "addr:street":"Rue De L'Eglise;Namur",
    "iso:country":"BE",
    "sg:address":"Rue De L'eglise 113 B",
    "sg:city":"Gembloux",
    "sg:orig_category":"Tabac. Journaux. Librairies",
    "sg:phone":"+32 81 61 36 00",
    "sg:postcode":"5030",
    "sg:province":"Namur",
    "wof:name":"Anne Bologne",
    "wof:placetype":"venue"
},
  "geometry": {"coordinates":[4.7223258018,50.5513153076],"type":"Point"}
}