{
  "type": "Feature",
  "properties": {
    "addr:full":"Rue Jehoge 45 Ferri\u00e8res (xhoris) Li\u00e8ge 4190",
    "addr:housenumber":"45",
    "addr:postcode":"4190",
    "addr:street":"Rue Jehoge",
    "iso:country":"BE",
    "sg:address":"Rue Jehoge 45",
    "sg:city":"Ferri\u00e8res (xhoris)",
    "sg:classifiers":[
        {
            "category":"Health Services",
            "subcategory":"Health Practitioner",
            "type":"Services"
        }
    ],
    "sg:phone":"+32 4 369 41 06",
    "sg:postcode":"4190",
    "sg:province":"Li\u00e8ge",
    "sg:tags":[
        "physiotherapist"
    ],
    "wof:name":"Rixhon Christophe",
    "wof:placetype":"venue"
},
  "geometry": {"coordinates":[5.6147069931,50.4452705383],"type":"Point"}
}