{
  "type": "Feature",
  "properties": {
    "addr:full":"Rue De La Loi 85 Bruxelles (etterbeek) Bruxelles-Capitale 1040",
    "addr:housenumber":"85",
    "addr:postcode":"1040",
    "addr:street":"Rue De La Loi",
    "iso:country":"BE",
    "sg:address":"Rue De La Loi 85",
    "sg:city":"Bruxelles (etterbeek)",
    "sg:classifiers":[
        {
            "category":"Professional",
            "subcategory":"Management & Consulting",
            "type":"Services"
        }
    ],
    "sg:phone":"+32 2 286 51 67",
    "sg:postcode":"1040",
    "sg:province":"Bruxelles-Capitale",
    "sg:tags":[
        "consultant"
    ],
    "wof:name":"Polytecna European Consulting Group",
    "wof:placetype":"venue"
},
  "geometry": {"coordinates":[4.376270771,50.8438186646],"type":"Point"}
}