{
  "type": "Feature",
  "properties": {
    "iso:country":"BE",
    "sg:address":"Rue Gustave Bo\u00cbl 156",
    "sg:city":"La Louviere",
    "sg:classifiers":[
        {
            "category":"Restaurant",
            "type":"Food & Drink"
        }
    ],
    "sg:phone":"+32 64 21 72 33",
    "sg:postcode":"7100",
    "sg:province":"Hainaut",
    "wof:name":"L'arlecchino",
    "wof:placetype":"venue"
},
  "geometry": {"coordinates":[4.1721892357,50.4798164368],"type":"Point"}
}