{
  "type": "Feature",
  "properties": {
    "addr:full":"Avenue Du Beau Site 26 La Hulpe Brabant Wallon 1310",
    "addr:housenumber":"26",
    "addr:postcode":"1310",
    "addr:street":"Avenue Du Beau Site",
    "iso:country":"BE",
    "sg:address":"Avenue Du Beau Site 26",
    "sg:city":"La Hulpe",
    "sg:classifiers":[
        {
            "category":"Taxi",
            "type":"Transportation"
        }
    ],
    "sg:phone":"+32 2 653 20 00",
    "sg:postcode":"1310",
    "sg:province":"Brabant Wallon",
    "sg:tags":[
        "taxicab"
    ],
    "wof:name":"Taxis De La Hulpe Sprl",
    "wof:placetype":"venue"
},
  "geometry": {"coordinates":[4.4852027893,50.7333488464],"type":"Point"}
}