{
  "type": "Feature",
  "properties": {
    "addr:full":"Pikkelstraat 37 Deerlijk West-Vlaanderen 8540",
    "addr:housenumber":"37",
    "addr:postcode":"8540",
    "addr:street":"Pikkelstraat",
    "iso:country":"BE",
    "sg:address":"Pikkelstraat 37",
    "sg:city":"Deerlijk",
    "sg:orig_category":"Administration d'immeubles. Comptables",
    "sg:phone":"+32 56 71 67 07",
    "sg:postcode":"8540",
    "sg:province":"West-Vlaanderen",
    "wof:name":"Robert Vandendriessche",
    "wof:placetype":"venue"
},
  "geometry": {"coordinates":[3.3550360203,50.8591423035],"type":"Point"}
}