{
  "type": "Feature",
  "properties": {
    "iso:country":"BE",
    "sg:address":"Mortierstraat 39",
    "sg:city":"Brugge",
    "sg:orig_category":"Artiesten and kunstenaars",
    "sg:phone":"+32 50 33 57 19",
    "sg:postcode":"8000",
    "sg:province":"West-Vlaanderen",
    "wof:name":"Frank Slabbinck",
    "wof:placetype":"venue"
},
  "geometry": {"coordinates":[3.2160279751,51.2085189819],"type":"Point"}
}