{
  "type": "Feature",
  "properties": {
    "addr:full":"Stationsstraat 49 Alken Limburg 3570",
    "addr:housenumber":"49",
    "addr:postcode":"3570",
    "addr:street":"Stationsstraat",
    "iso:country":"BE",
    "sg:address":"Stationsstraat 49",
    "sg:city":"Alken",
    "sg:classifiers":[
        {
            "category":"Insurance",
            "subcategory":"Life Insurance",
            "type":"Services"
        }
    ],
    "sg:phone":"+32 11 31 31 78",
    "sg:postcode":"3570",
    "sg:province":"Limburg",
    "sg:tags":[
        "assurance"
    ],
    "wof:name":"Martens & Co",
    "wof:placetype":"venue"
},
  "geometry": {"coordinates":[5.3015551567,50.8817749023],"type":"Point"}
}