{
  "type": "Feature",
  "properties": {
    "iso:country":"BE",
    "sg:address":"Offerandestraat 102",
    "sg:city":"Antwerpen",
    "sg:orig_category":"Zuivelproducten",
    "sg:phone":"+32 3 235 45 20",
    "sg:postcode":"2060",
    "sg:province":"Antwerpen",
    "wof:name":"Rudolf Van Impe",
    "wof:placetype":"venue"
},
  "geometry": {"coordinates":[4.4271688461,51.2210578918],"type":"Point"}
}