{
  "type": "Feature",
  "properties": {
    "addr:full":"Leuvensebaan 217 Putte Antwerpen 2580",
    "addr:housenumber":"217",
    "addr:postcode":"2580",
    "addr:street":"Leuvensebaan",
    "iso:country":"BE",
    "sg:address":"Leuvensebaan 217",
    "sg:city":"Putte",
    "sg:classifiers":[
        {
            "category":"Professional",
            "subcategory":"Management & Consulting",
            "type":"Services"
        }
    ],
    "sg:phone":"+32 15 75 40 48",
    "sg:postcode":"2580",
    "sg:province":"Antwerpen",
    "sg:tags":[
        "consultant"
    ],
    "wof:name":"Rim Consult Bvba",
    "wof:placetype":"venue"
},
  "geometry": {"coordinates":[4.635392189,51.0323486328],"type":"Point"}
}