{
  "type": "Feature",
  "properties": {
    "addr:full":"Antoon Sanderusstraat 21 Gent Oost-Vlaanderen 9000",
    "addr:housenumber":"21",
    "addr:postcode":"9000",
    "addr:street":"Antoon Sanderusstraat;Oost-Vlaanderen",
    "iso:country":"BE",
    "sg:address":"Antoon Sanderusstraat 21",
    "sg:city":"Gent",
    "sg:orig_category":"Artiesten and kunstenaars",
    "sg:phone":"+32 9 225 62 61",
    "sg:postcode":"9000",
    "sg:province":"Oost-Vlaanderen",
    "wof:name":"Walter De Dauw",
    "wof:placetype":"venue"
},
  "geometry": {"coordinates":[3.7274260521,51.0640258789],"type":"Point"}
}