{
  "type": "Feature",
  "properties": {
    "addr:full":"Desguinlei 226 Antwerpen Antwerpen 2018",
    "addr:housenumber":"226",
    "addr:postcode":"2018",
    "addr:street":"Desguinlei",
    "iso:country":"BE",
    "sg:address":"Desguinlei 226",
    "sg:city":"Antwerpen",
    "sg:classifiers":[
        {
            "category":"Health Services",
            "subcategory":"Dentist",
            "type":"Services"
        }
    ],
    "sg:phone":"+32 3 237 39 80",
    "sg:postcode":"2018",
    "sg:province":"Antwerpen",
    "wof:name":"D'hoore J",
    "wof:placetype":"venue"
},
  "geometry": {"coordinates":[4.3970179558,51.1968269348],"type":"Point"}
}