{
  "type": "Feature",
  "properties": {
    "addr:full":"Kantineplein 3 Leuven Vlaams-Brabant 3001",
    "addr:housenumber":"3",
    "addr:postcode":"3001",
    "addr:street":"Kantineplein",
    "iso:country":"BE",
    "sg:address":"Kantineplein 3",
    "sg:city":"Leuven",
    "sg:orig_category":"RESTAURANTS: SALLES DE CONF\u00c9RENCES AND DE R\u00c9CEPTIONS",
    "sg:phone":"+32 16 22 20 84",
    "sg:postcode":"3001",
    "sg:province":"Vlaams-Brabant",
    "wof:name":"De Oude Kantien",
    "wof:placetype":"venue"
},
  "geometry": {"coordinates":[4.6853690147,50.8609848022],"type":"Point"}
}