{
  "type": "Feature",
  "properties": {
    "addr:full":"Tiensevest 2 Sint-truiden Limburg 3800",
    "addr:housenumber":"2",
    "addr:postcode":"3800",
    "addr:street":"Tiensevest",
    "iso:country":"BE",
    "sg:address":"Tiensevest 2",
    "sg:city":"Sint-truiden",
    "sg:classifiers":[
        {
            "category":"Shopping",
            "subcategory":"Florist",
            "type":"Retail Goods"
        }
    ],
    "sg:phone":"+32 11 69 48 54",
    "sg:postcode":"3800",
    "sg:province":"Limburg",
    "wof:name":"Willems P",
    "wof:placetype":"venue"
},
  "geometry": {"coordinates":[5.1843547821,50.8132400513],"type":"Point"}
}