{
  "type": "Feature",
  "properties": {
    "iso:country":"BE",
    "sg:address":"Kpt. R. Wouterslaan 14",
    "sg:city":"Wemmel/wemmel",
    "sg:orig_category":"Artsen and specialisten",
    "sg:phone":"+32 2 460 10 27",
    "sg:postcode":"1780",
    "sg:province":"Vlaams-Brabant",
    "wof:name":"Henri Pintens",
    "wof:placetype":"venue"
},
  "geometry": {"coordinates":[4.3070898056,50.9067382812],"type":"Point"}
}