{
  "type": "Feature",
  "properties": {
    "addr:full":"Oude Leuvensestr 47 Tienen (groot) Vlaams-Brabant 3300",
    "addr:housenumber":"47",
    "addr:postcode":"3300",
    "addr:street":"Oude Leuvensestr;Groot Vlaams-Brabant",
    "iso:country":"BE",
    "sg:address":"Oude Leuvensestr 47",
    "sg:city":"Tienen (groot)",
    "sg:orig_category":"Kapsalons",
    "sg:phone":"+32 16 81 75 17",
    "sg:postcode":"3300",
    "sg:province":"Vlaams-Brabant",
    "wof:name":"Carl",
    "wof:placetype":"venue"
},
  "geometry": {"coordinates":[4.9342670441,50.8091888428],"type":"Point"}
}