{
  "type": "Feature",
  "properties": {
    "addr:full":"Rue Sainte-marguerite 132 Li\u00e8ge 1 Li\u00e8ge 4000",
    "addr:housenumber":"132;1",
    "addr:postcode":"4000",
    "addr:street":"Rue Sainte-Marguerite",
    "iso:country":"BE",
    "sg:address":"Rue Sainte-marguerite 132",
    "sg:city":"Li\u00e8ge 1",
    "sg:classifiers":[
        {
            "category":"Shopping",
            "subcategory":"Discount & Variety Stores",
            "type":"Retail Goods"
        }
    ],
    "sg:phone":"+32 4 224 28 34",
    "sg:postcode":"4000",
    "sg:province":"Li\u00e8ge",
    "sg:tags":[
        "shop",
        "night"
    ],
    "wof:name":"Bott",
    "wof:placetype":"venue"
},
  "geometry": {"coordinates":[5.558825016,50.6461982727],"type":"Point"}
}