{
  "type": "Feature",
  "properties": {
    "addr:full":"Grote Markt Sint-truiden Limburg 3800",
    "addr:postcode":"3800",
    "addr:street":"Grote Markt",
    "iso:country":"BE",
    "sg:address":"Grote Markt",
    "sg:city":"Sint-truiden",
    "sg:classifiers":[
        {
            "category":"Shopping",
            "subcategory":"Clothing, Apparel, & Fashions",
            "type":"Retail Goods"
        }
    ],
    "sg:phone":"+32 11 68 12 07",
    "sg:postcode":"3800",
    "sg:province":"Limburg",
    "sg:tags":[
        "underwear",
        "lingerie",
        "-"
    ],
    "wof:name":"An",
    "wof:placetype":"venue"
},
  "geometry": {"coordinates":[5.1859350204,50.815776825],"type":"Point"}
}