{
  "type": "Feature",
  "properties": {
    "iso:country":"BE",
    "sg:address":"Hogeschoollaan 32",
    "sg:city":"Elsene/ixelles",
    "sg:orig_category":"Juwelen and horloges",
    "sg:phone":"+32 2 646 88 47",
    "sg:postcode":"1050",
    "sg:province":"Bruxelles-Capitale",
    "wof:name":"Maison Cosyns",
    "wof:placetype":"venue"
},
  "geometry": {"coordinates":[4.3884139061,50.814994812],"type":"Point"}
}