{
  "type": "Feature",
  "properties": {
    "iso:country":"BE",
    "sg:address":"Rue De L'epine 1",
    "sg:city":"Ottignies-louvain-la-neuve",
    "sg:orig_category":"Sportclubs",
    "sg:phone":"+32 10 45 27 16",
    "sg:postcode":"1340",
    "sg:province":"Brabant Wallon",
    "wof:name":"T.c. Du Parc",
    "wof:placetype":"venue"
},
  "geometry": {"coordinates":[4.5915808678,50.6672363281],"type":"Point"}
}