{
  "type": "Feature",
  "properties": {
    "iso:country":"BE",
    "sg:address":"J. B. Vandercammenstraat 6",
    "sg:city":"Oudergem/auderghem",
    "sg:orig_category":"Artiesten and kunstenaars",
    "sg:phone":"+32 2 673 79 53",
    "sg:postcode":"1160",
    "sg:province":"Bruxelles-Capitale",
    "wof:name":"B. De Saint-l\u00c9ger",
    "wof:placetype":"venue"
},
  "geometry": {"coordinates":[4.434481144,50.8029441833],"type":"Point"}
}