{
  "type": "Feature",
  "properties": {
    "addr:full":"Agora 9 Ottignies-louvain-la-neuve Brabant Wallon 1348",
    "addr:housenumber":"9",
    "addr:postcode":"1348",
    "addr:street":"Agora",
    "iso:country":"BE",
    "sg:address":"Agora 9",
    "sg:city":"Ottignies-louvain-la-neuve",
    "sg:orig_category":"Imprimeries and copyshops",
    "sg:phone":"+32 10 45 30 85",
    "sg:postcode":"1348",
    "sg:province":"Brabant Wallon",
    "wof:name":"Fac-copy",
    "wof:placetype":"venue"
},
  "geometry": {"coordinates":[4.567553997,50.6661262512],"type":"Point"}
}