{
  "type": "Feature",
  "properties": {
    "addr:full":"Overwinningstraat 4 Willebroek Antwerpen 2830",
    "addr:housenumber":"4",
    "addr:postcode":"2830",
    "addr:street":"Overwinningstraat",
    "iso:country":"BE",
    "sg:address":"Overwinningstraat 4",
    "sg:city":"Willebroek",
    "sg:classifiers":[
        {
            "category":"Cafe",
            "type":"Food & Drink"
        }
    ],
    "sg:phone":"+32 3 886 36 30",
    "sg:postcode":"2830",
    "sg:province":"Antwerpen",
    "sg:tags":[
        "snack-bars"
    ],
    "wof:name":"Kruimeltje",
    "wof:placetype":"venue"
},
  "geometry": {"coordinates":[4.3599038124,51.0598258972],"type":"Point"}
}