{
  "type": "Feature",
  "properties": {
    "addr:full":"Rue Du Midi 100a Bruxelles Bruxelles-Capitale 1000",
    "addr:housenumber":"100a",
    "addr:postcode":"1000",
    "addr:street":"Rue Du Midi",
    "iso:country":"BE",
    "sg:address":"Rue Du Midi 100a",
    "sg:city":"Bruxelles",
    "sg:classifiers":[
        {
            "category":"Cafe",
            "type":"Food & Drink"
        }
    ],
    "sg:phone":"+32 2 511 71 01",
    "sg:postcode":"1000",
    "sg:province":"Bruxelles-Capitale",
    "sg:tags":[
        "snack-bars"
    ],
    "wof:name":"Cricotte",
    "wof:placetype":"venue"
},
  "geometry": {"coordinates":[4.3487977982,50.8450164795],"type":"Point"}
}