{
  "type": "Feature",
  "properties": {
    "iso:country":"BE",
    "sg:address":"Abdijstraat 5",
    "sg:city":"Gistel",
    "sg:classifiers":[
        {
            "category":"Retail",
            "subcategory":"Auto Repair",
            "type":"Services"
        }
    ],
    "sg:phone":"+32 59 27 83 15",
    "sg:postcode":"8470",
    "sg:province":"West-Vlaanderen",
    "sg:tags":[
        "garage"
    ],
    "wof:name":"Museeuw E",
    "wof:placetype":"venue"
},
  "geometry": {"coordinates":[2.9458329678,51.1533889771],"type":"Point"}
}