{
  "type": "Feature",
  "properties": {
    "addr:full":"Quai De-gaulle 26 Li\u00e8ge 1 (li\u00e8ge 2) Li\u00e8ge 4020",
    "addr:housenumber":"26;1;2",
    "addr:postcode":"4020",
    "addr:street":"Quai De-Gaulle",
    "iso:country":"BE",
    "sg:address":"Quai De-gaulle 26",
    "sg:city":"Li\u00e8ge 1 (li\u00e8ge 2)",
    "sg:classifiers":[
        {
            "category":"Professional",
            "subcategory":"Management & Consulting",
            "type":"Services"
        }
    ],
    "sg:phone":"+32 4 341 05 68",
    "sg:postcode":"4020",
    "sg:province":"Li\u00e8ge",
    "sg:tags":[
        "marketing",
        "-",
        "direct",
        "consultant"
    ],
    "wof:name":"G S V Consulting Scrl Scrl",
    "wof:placetype":"venue"
},
  "geometry": {"coordinates":[5.5790801048,50.6412391663],"type":"Point"}
}