{
  "type": "Feature",
  "properties": {
    "iso:country":"BE",
    "sg:address":"Brusselsesteenweg 6a",
    "sg:city":"Herent",
    "sg:orig_category":"Bouwmaterialen Gh Chemicali\u00ebn Gh",
    "sg:phone":"+32 16 23 79 17",
    "sg:postcode":"3020",
    "sg:province":"Vlaams-Brabant",
    "wof:name":"Boermans",
    "wof:placetype":"venue"
},
  "geometry": {"coordinates":[4.6711268425,50.8860168457],"type":"Point"}
}