{
  "type": "Feature",
  "properties": {
    "addr:full":"Nerenweg 41ba Laarne Oost-Vlaanderen 9270",
    "addr:housenumber":"41ba",
    "addr:postcode":"9270",
    "addr:street":"Nerenweg",
    "iso:country":"BE",
    "sg:address":"Nerenweg 41ba",
    "sg:city":"Laarne",
    "sg:orig_category":"Installation \u00e9lectrique r\u00e9sidentielle. Electrom\u00e9nager, t\u00e9l\u00e9visions and radios. R\u00e9parations d'apparei",
    "sg:phone":"+32 9 367 93 39",
    "sg:postcode":"9270",
    "sg:province":"Oost-Vlaanderen",
    "wof:name":"Geert Verhoeven",
    "wof:placetype":"venue"
},
  "geometry": {"coordinates":[3.9123558998,51.0361366272],"type":"Point"}
}