{
  "type": "Feature",
  "properties": {
    "addr:full":"Rue Marie-christine 66 Brussel/bruxelles Bruxelles-Capitale 1020",
    "addr:housenumber":"66",
    "addr:postcode":"1020",
    "addr:street":"Rue Marie-Christine;/",
    "iso:country":"BE",
    "sg:address":"Rue Marie-christine 66",
    "sg:city":"Brussel/bruxelles",
    "sg:classifiers":[
        {
            "category":"Fast Food",
            "type":"Food & Drink"
        }
    ],
    "sg:phone":"+32 2 424 00 26",
    "sg:postcode":"1020",
    "sg:province":"Bruxelles-Capitale",
    "sg:tags":[
        "\u00c0",
        "emporter",
        "restaurants"
    ],
    "wof:name":"Efes",
    "wof:placetype":"venue"
},
  "geometry": {"coordinates":[4.3562121391,50.8743667603],"type":"Point"}
}