{
  "type": "Feature",
  "properties": {
    "iso:country":"BE",
    "sg:address":"Rue De La Lys 20",
    "sg:city":"Tournai",
    "sg:classifiers":[
        {
            "category":"Cafe",
            "type":"Food & Drink"
        }
    ],
    "sg:phone":"+32 69 22 60 40",
    "sg:postcode":"7500",
    "sg:province":"Hainaut",
    "sg:tags":[
        "caf\u00e9s"
    ],
    "wof:name":"Caf\u00c9 Du Garage",
    "wof:placetype":"venue"
},
  "geometry": {"coordinates":[3.405299902,50.599861145],"type":"Point"}
}