{
  "type": "Feature",
  "properties": {
    "iso:country":"BE",
    "sg:address":"Cadixstraat 1",
    "sg:city":"Antwerpen",
    "sg:classifiers":[
        {
            "category":"Cafe",
            "type":"Food & Drink"
        }
    ],
    "sg:phone":"+32 3 232 22 26",
    "sg:postcode":"2000",
    "sg:province":"Antwerpen",
    "sg:tags":[
        "caf\u00e9s"
    ],
    "wof:name":"Yvonne Beeckmans",
    "wof:placetype":"venue"
},
  "geometry": {"coordinates":[4.409512043,51.233417511],"type":"Point"}
}