{
  "type": "Feature",
  "properties": {
    "addr:full":"Lombeekstraat 47 Affligem (essene) Vlaams-Brabant 1790",
    "addr:housenumber":"47",
    "addr:postcode":"1790",
    "addr:street":"Lombeekstraat",
    "iso:country":"BE",
    "sg:address":"Lombeekstraat 47",
    "sg:city":"Affligem (essene)",
    "sg:classifiers":[
        {
            "category":"Banks & Credit Unions",
            "subcategory":"Investment Brokerage",
            "type":"Services"
        }
    ],
    "sg:phone":"+32 2 582 16 20",
    "sg:postcode":"1790",
    "sg:province":"Vlaams-Brabant",
    "sg:tags":[
        "repair",
        "-",
        "installation",
        "sanitary",
        "article"
    ],
    "wof:name":"Callebaut Michel Bvba",
    "wof:placetype":"venue"
},
  "geometry": {"coordinates":[4.1369709969,50.8940925598],"type":"Point"}
}