{
  "type": "Feature",
  "properties": {
    "addr:full":"Schoonstraat 165 Evergem Oost-Vlaanderen 9940",
    "addr:housenumber":"165",
    "addr:postcode":"9940",
    "addr:street":"Schoonstraat;Oost-Vlaanderen",
    "iso:country":"BE",
    "sg:address":"Schoonstraat 165",
    "sg:city":"Evergem",
    "sg:orig_category":"Animaux domestiques and accessoires",
    "sg:phone":"+32 9 253 07 82",
    "sg:postcode":"9940",
    "sg:province":"Oost-Vlaanderen",
    "wof:name":"Willy Lybaert",
    "wof:placetype":"venue"
},
  "geometry": {"coordinates":[3.6780650616,51.1054878235],"type":"Point"}
}