{
  "type": "Feature",
  "properties": {
    "iso:country":"BE",
    "sg:address":"Speltenlei 10",
    "sg:city":"Schelle",
    "sg:orig_category":"Rundveehouders",
    "sg:phone":"+32 3 887 59 37",
    "sg:postcode":"2627",
    "sg:province":"Antwerpen",
    "wof:name":"Willy Lemmens",
    "wof:placetype":"venue"
},
  "geometry": {"coordinates":[4.3538918495,51.1220779419],"type":"Point"}
}