{
  "type": "Feature",
  "properties": {
    "addr:full":"Esplanade Ren\u00e9 Magritte 5 Charleroi (couillet) Hainaut 6010",
    "addr:housenumber":"5",
    "addr:postcode":"6010",
    "addr:street":"Esplanade Rene\u0301 Magritte",
    "iso:country":"BE",
    "sg:address":"Esplanade Ren\u00e9 Magritte 5",
    "sg:city":"Charleroi (couillet)",
    "sg:classifiers":[
        {
            "category":"Professional",
            "subcategory":"Accounting & Tax Preparation",
            "type":"Services"
        }
    ],
    "sg:phone":"+32 71 47 49 38",
    "sg:postcode":"6010",
    "sg:province":"Hainaut",
    "sg:tags":[
        "accountant"
    ],
    "wof:name":"Thibaut C",
    "wof:placetype":"venue"
},
  "geometry": {"coordinates":[4.458425045,50.3926963806],"type":"Point"}
}