{
  "type": "Feature",
  "properties": {
    "iso:country":"BE",
    "sg:address":"Nieuwstraat 30b3",
    "sg:city":"Sint-niklaas",
    "sg:orig_category":"Paramedische behandelingen",
    "sg:phone":"+32 3 765 19 44",
    "sg:postcode":"9100",
    "sg:province":"Oost-Vlaanderen",
    "wof:name":"I. Haeck",
    "wof:placetype":"venue"
},
  "geometry": {"coordinates":[4.1377339363,51.1626815796],"type":"Point"}
}