{
  "type": "Feature",
  "properties": {
    "addr:full":"Gentpoortstraat 60 Deinze Oost-Vlaanderen 9800",
    "addr:housenumber":"60",
    "addr:postcode":"9800",
    "addr:street":"Gentpoortstraat",
    "iso:country":"BE",
    "sg:address":"Gentpoortstraat 60",
    "sg:city":"Deinze",
    "sg:orig_category":"Hypotheken and hypotheekbanken Verbruikerskredietinstellingen",
    "sg:phone":"+32 9 380 00 69",
    "sg:postcode":"9800",
    "sg:province":"Oost-Vlaanderen",
    "wof:name":"Advies- En Leenkantoor",
    "wof:placetype":"venue"
},
  "geometry": {"coordinates":[3.5297670364,50.9849777222],"type":"Point"}
}