{
  "type": "Feature",
  "properties": {
    "addr:full":"Molenstraat 8 Waarschoot Oost-Vlaanderen 9950",
    "addr:housenumber":"8",
    "addr:postcode":"9950",
    "addr:street":"Molenstraat",
    "iso:country":"BE",
    "sg:address":"Molenstraat 8",
    "sg:city":"Waarschoot",
    "sg:classifiers":[
        {
            "category":"Professional",
            "subcategory":"Management & Consulting",
            "type":"Services"
        }
    ],
    "sg:phone":"+32 9 378 19 13",
    "sg:postcode":"9950",
    "sg:province":"Oost-Vlaanderen",
    "sg:tags":[
        "consultant",
        "agency",
        "advertising"
    ],
    "wof:name":"Jan Jacobs Copywriter Bvba",
    "wof:placetype":"venue"
},
  "geometry": {"coordinates":[3.6120870113,51.1518516541],"type":"Point"}
}