{
  "type": "Feature",
  "properties": {
    "iso:country":"BE",
    "sg:address":"Rue Des Bellaires 15",
    "sg:city":"Fernelmont",
    "sg:orig_category":"Installation \u00e9lectrique r\u00e9sidentielle. Eleveurs de bovins",
    "sg:phone":"+32 81 83 37 20",
    "sg:postcode":"5380",
    "sg:province":"Namur",
    "wof:name":"Roger Pirotte",
    "wof:placetype":"venue"
},
  "geometry": {"coordinates":[4.9692687988,50.5631752014],"type":"Point"}
}