{
  "type": "Feature",
  "properties": {
    "iso:country":"BE",
    "sg:address":"Rue De Fiennes 7",
    "sg:city":"Bruxelles (anderlecht)",
    "sg:orig_category":"Non-Classified Establishments",
    "sg:phone":"+32 2 523 58 94",
    "sg:postcode":"1070",
    "sg:province":"Bruxelles-Capitale",
    "wof:name":"Gatex Import-export",
    "wof:placetype":"venue"
},
  "geometry": {"coordinates":[4.3352131844,50.8391418457],"type":"Point"}
}