{
  "type": "Feature",
  "properties": {
    "iso:country":"BE",
    "sg:address":"Chauss\u00c9e De Charleroi 9a",
    "sg:city":"Sint-gillis/saint-gilles",
    "sg:orig_category":"Equipement photographique",
    "sg:phone":"+32 2 538 75 32",
    "sg:postcode":"1060",
    "sg:province":"Bruxelles-Capitale",
    "wof:name":"Flash One",
    "wof:placetype":"venue"
},
  "geometry": {"coordinates":[4.356965065,50.8334236145],"type":"Point"}
}