{
  "type": "Feature",
  "properties": {
    "iso:country":"BE",
    "sg:address":"Pachtgoeddreef 37",
    "sg:city":"Gent",
    "sg:orig_category":"Bloemen and planten",
    "sg:phone":"+32 9 227 72 08",
    "sg:postcode":"9031",
    "sg:province":"Oost-Vlaanderen",
    "wof:name":"Groendecoraties Fleurbaey",
    "wof:placetype":"venue"
},
  "geometry": {"coordinates":[3.6615600586,51.0596504211],"type":"Point"}
}