{
  "type": "Feature",
  "properties": {
    "iso:country":"BE",
    "sg:address":"Kortrijkstraat 32",
    "sg:city":"Lubbeek (linden)",
    "sg:classifiers":[
        {
            "category":"Professional",
            "subcategory":"Management & Consulting",
            "type":"Services"
        }
    ],
    "sg:phone":"+32 16 26 16 49",
    "sg:postcode":"3210",
    "sg:province":"Vlaams-Brabant",
    "sg:tags":[
        "consultant"
    ],
    "wof:name":"Sykhold Management Bvba",
    "wof:placetype":"venue"
},
  "geometry": {"coordinates":[4.841878891,50.881729126],"type":"Point"}
}