{
  "type": "Feature",
  "properties": {
    "iso:country":"BE",
    "sg:address":"Donkstraat 63",
    "sg:city":"Maldegem",
    "sg:classifiers":[
        {
            "category":"Building & Trades",
            "subcategory":"Electrical",
            "type":"Services"
        }
    ],
    "sg:phone":"+32 50 71 98 71",
    "sg:postcode":"9990",
    "sg:province":"Oost-Vlaanderen",
    "sg:tags":[
        "electric",
        "-",
        "housewiring",
        "contractor"
    ],
    "wof:name":"Alg Elektriciteitswerken Vanlatum",
    "wof:placetype":"venue"
},
  "geometry": {"coordinates":[3.3832349777,51.2141609192],"type":"Point"}
}