{
  "type": "Feature",
  "properties": {
    "addr:full":"Plezantstraat 4 Sint-gillis-waas Oost-Vlaanderen 9170",
    "addr:housenumber":"4",
    "addr:postcode":"9170",
    "addr:street":"Plezantstraat",
    "iso:country":"BE",
    "sg:address":"Plezantstraat 4",
    "sg:city":"Sint-gillis-waas",
    "sg:classifiers":[
        {
            "category":"Restaurant",
            "type":"Food & Drink"
        }
    ],
    "sg:phone":"+32 3 773 37 64",
    "sg:postcode":"9170",
    "sg:province":"Oost-Vlaanderen",
    "wof:name":"Hof Ter Polder",
    "wof:placetype":"venue"
},
  "geometry": {"coordinates":[4.1463260651,51.2601585388],"type":"Point"}
}