{
  "type": "Feature",
  "properties": {
    "iso:country":"BE",
    "sg:address":"Putlaan 35",
    "sg:city":"Edegem",
    "sg:classifiers":[
        {
            "category":"Sports & Exercise",
            "subcategory":"Gym",
            "type":"Entertainment"
        }
    ],
    "sg:phone":"+32 3 457 25 22",
    "sg:postcode":"2650",
    "sg:province":"Antwerpen",
    "sg:tags":[
        "fitness"
    ],
    "wof:name":"Roblo Services Bvba",
    "wof:placetype":"venue"
},
  "geometry": {"coordinates":[4.4557762146,51.1515235901],"type":"Point"}
}