{
  "type": "Feature",
  "properties": {
    "iso:country":"BE",
    "sg:address":"Vrijheid 161",
    "sg:city":"Hoogstraten",
    "sg:orig_category":"Artsen and specialisten",
    "sg:phone":"+32 3 314 15 26",
    "sg:postcode":"2320",
    "sg:province":"Antwerpen",
    "wof:name":"Mark Accou",
    "wof:placetype":"venue"
},
  "geometry": {"coordinates":[4.7609930038,51.4002342224],"type":"Point"}
}