{
  "type": "Feature",
  "properties": {
    "iso:country":"BE",
    "sg:address":"Dani\u00eblsstraat 25",
    "sg:city":"Hasselt",
    "sg:classifiers":[
        {
            "category":"Banks & Credit Unions",
            "subcategory":"Investment Brokerage",
            "type":"Services"
        }
    ],
    "sg:phone":"+32 11 28 17 06",
    "sg:postcode":"3500",
    "sg:province":"Limburg",
    "sg:tags":[
        "fence"
    ],
    "wof:name":"Fences Bvba",
    "wof:placetype":"venue"
},
  "geometry": {"coordinates":[5.3477191925,50.9188537598],"type":"Point"}
}