{
  "type": "Feature",
  "properties": {
    "addr:full":"Avenue Du Rond-point 8b Rixensart Brabant Wallon 1330",
    "addr:housenumber":"8b",
    "addr:postcode":"1330",
    "addr:street":"Avenue Du Rond-Point;Wallon",
    "iso:country":"BE",
    "sg:address":"Avenue Du Rond-point 8b",
    "sg:city":"Rixensart",
    "sg:orig_category":"HERSTELLING ELEKTRISCHE HUISHOUDAPPARATEN Huishoudapparaten, televisies and radio's MEUBELONTWERP AN",
    "sg:phone":"+32 2 653 01 82",
    "sg:postcode":"1330",
    "sg:province":"Brabant Wallon",
    "wof:name":"P Tagnon Services",
    "wof:placetype":"venue"
},
  "geometry": {"coordinates":[4.5274701118,50.7104110718],"type":"Point"}
}