{
  "type": "Feature",
  "properties": {
    "iso:country":"BE",
    "sg:address":"Louizastraat 31",
    "sg:city":"Mechelen",
    "sg:orig_category":"Advocaten and juridische adviseurs",
    "sg:phone":"+32 15 41 35 96",
    "sg:postcode":"2800",
    "sg:province":"Antwerpen",
    "wof:name":"Wim Jorissen",
    "wof:placetype":"venue"
},
  "geometry": {"coordinates":[4.4779458046,51.0214424133],"type":"Point"}
}