{
  "type": "Feature",
  "properties": {
    "iso:country":"BE",
    "sg:address":"Rue Saint-roch 3",
    "sg:city":"Ch\u00e2telet",
    "sg:classifiers":[
        {
            "category":"Health Services",
            "subcategory":"Health Practitioner",
            "type":"Services"
        }
    ],
    "sg:phone":"+32 71 38 30 47",
    "sg:postcode":"6200",
    "sg:province":"Hainaut",
    "sg:tags":[
        "physiotherapist"
    ],
    "wof:name":"Lardinois Thierry",
    "wof:placetype":"venue"
},
  "geometry": {"coordinates":[4.5311379433,50.4000740051],"type":"Point"}
}