{
  "type": "Feature",
  "properties": {
    "iso:country":"BE",
    "sg:address":"Rue De La Station 67",
    "sg:city":"Chapelle-lez-herlaimont",
    "sg:orig_category":"Rev\u00eatements de sols and murs",
    "sg:phone":"+32 64 45 12 04",
    "sg:postcode":"7160",
    "sg:province":"Hainaut",
    "wof:name":"Chantier Moderne Chapell.",
    "wof:placetype":"venue"
},
  "geometry": {"coordinates":[4.2764029503,50.4678039551],"type":"Point"}
}