{
  "type": "Feature",
  "properties": {
    "addr:full":"Boomsesteenweg 943 Wilrijk Antwerpen 2610",
    "addr:housenumber":"943",
    "addr:postcode":"2610",
    "addr:street":"Boomsesteenweg;Antwerpen",
    "iso:country":"BE",
    "sg:address":"Boomsesteenweg 943",
    "sg:city":"Wilrijk",
    "sg:classifiers":[
        {
            "category":"Manufacturing",
            "subcategory":"Printing",
            "type":"Manufacturing & Wholesale Goods"
        }
    ],
    "sg:phone":"+32 3 828 12 13",
    "sg:postcode":"2610",
    "sg:province":"Antwerpen",
    "sg:tags":[
        "publishing"
    ],
    "wof:name":"De Brauwere Drukkerij Nv",
    "wof:placetype":"venue"
},
  "geometry": {"coordinates":[4.3826851845,51.152885437],"type":"Point"}
}