{
  "type": "Feature",
  "properties": {
    "addr:full":"Rue Mitoyenne 23 Baelen/baelen Li\u00e8ge 4837",
    "addr:housenumber":"23",
    "addr:postcode":"4837",
    "addr:street":"Rue Mitoyenne",
    "iso:country":"BE",
    "sg:address":"Rue Mitoyenne 23",
    "sg:city":"Baelen/baelen",
    "sg:orig_category":"Meubles D\u00e9taillants, Am\u00e9nagement de B\u00e2timents et de Cuisines",
    "sg:phone":"+32 87 88 13 11",
    "sg:postcode":"4837",
    "sg:province":"Li\u00e8ge",
    "wof:name":"Zimmerman M\u00d6ebel",
    "wof:placetype":"venue"
},
  "geometry": {"coordinates":[6.0038318634,50.6473274231],"type":"Point"}
}