{
  "type": "Feature",
  "properties": {
    "addr:full":"Kapelaan Smitslaan 22 Edegem Antwerpen 2650",
    "addr:housenumber":"22",
    "addr:postcode":"2650",
    "addr:street":"Kapelaan Smitslaan",
    "iso:country":"BE",
    "sg:address":"Kapelaan Smitslaan 22",
    "sg:city":"Edegem",
    "sg:orig_category":"M\u00e9decines alternatives",
    "sg:phone":"+32 3 457 50 70",
    "sg:postcode":"2650",
    "sg:province":"Antwerpen",
    "wof:name":"Nathalie Van Look",
    "wof:placetype":"venue"
},
  "geometry": {"coordinates":[4.4448800087,51.1503181458],"type":"Point"}
}