{
  "type": "Feature",
  "properties": {
    "addr:full":"Ingelmunstersteenweg 1 Meulebeke West-Vlaanderen 8760",
    "addr:housenumber":"1",
    "addr:postcode":"8760",
    "addr:street":"Ingelmunstersteenweg",
    "iso:country":"BE",
    "sg:address":"Ingelmunstersteenweg 1",
    "sg:city":"Meulebeke",
    "sg:orig_category":"Entretien and r\u00e9parations de voitures. V\u00e9hicules automobiles",
    "sg:phone":"+32 51 48 96 86",
    "sg:postcode":"8760",
    "sg:province":"West-Vlaanderen",
    "wof:name":"Autocenter Van Iseghem B.",
    "wof:placetype":"venue"
},
  "geometry": {"coordinates":[3.2762451172,50.9460525513],"type":"Point"}
}