{
  "type": "Feature",
  "properties": {
    "addr:full":"Rue Germaine Dewandre 5 Charleroi (mont-sur-marchienne) Hainaut 6032",
    "addr:housenumber":"5",
    "addr:postcode":"6032",
    "addr:street":"Rue Germaine Dewandre",
    "iso:country":"BE",
    "sg:address":"Rue Germaine Dewandre 5",
    "sg:city":"Charleroi (mont-sur-marchienne)",
    "sg:classifiers":[
        {
            "category":"Personal",
            "subcategory":"Psychics & Astrologers",
            "type":"Services"
        }
    ],
    "sg:phone":"+32 71 51 53 47",
    "sg:postcode":"6032",
    "sg:province":"Hainaut",
    "sg:tags":[
        "astrology"
    ],
    "wof:name":"Marianne R",
    "wof:placetype":"venue"
},
  "geometry": {"coordinates":[4.3974070549,50.3707237244],"type":"Point"}
}