{
  "type": "Feature",
  "properties": {
    "iso:country":"BE",
    "sg:address":"Raverschootstraat 224",
    "sg:city":"Eeklo",
    "sg:classifiers":[
        {
            "category":"Retail",
            "subcategory":"Repair Shop",
            "type":"Services"
        }
    ],
    "sg:phone":"+32 9 377 89 03",
    "sg:postcode":"9900",
    "sg:province":"Oost-Vlaanderen",
    "sg:tags":[
        "upholsterer"
    ],
    "wof:name":"Van Kerckhoven N",
    "wof:placetype":"venue"
},
  "geometry": {"coordinates":[3.5444159508,51.1880950928],"type":"Point"}
}