{
  "type": "Feature",
  "properties": {
    "iso:country":"BE",
    "sg:address":"Rue Outre 55",
    "sg:city":"Frasnes-lez-anvaing",
    "sg:orig_category":"Installatie van houten of kunststof schrijnwerk",
    "sg:phone":"+32 69 86 83 03",
    "sg:postcode":"7910",
    "sg:province":"Hainaut",
    "wof:name":"Dany Stievenart",
    "wof:placetype":"venue"
},
  "geometry": {"coordinates":[3.5563681126,50.685005188],"type":"Point"}
}