{
  "type": "Feature",
  "properties": {
    "addr:full":"Chauss\u00c9e De Dinant 106bb Profondeville Namur 5170",
    "addr:housenumber":"106bb",
    "addr:postcode":"5170",
    "addr:street":"Chausse\u0301E De Dinant",
    "iso:country":"BE",
    "sg:address":"Chauss\u00c9e De Dinant 106bb",
    "sg:city":"Profondeville",
    "sg:classifiers":[
        {
            "category":"Fast Food",
            "type":"Food & Drink"
        }
    ],
    "sg:phone":"+32 81 41 42 48",
    "sg:postcode":"5170",
    "sg:province":"Namur",
    "sg:tags":[
        "\u00c0",
        "emporter",
        "restaurants"
    ],
    "wof:name":"Friterie Piwi's",
    "wof:placetype":"venue"
},
  "geometry": {"coordinates":[4.8716230392,50.3659362793],"type":"Point"}
}