{
  "type": "Feature",
  "properties": {
    "iso:country":"BE",
    "sg:address":"Gheeraerdtslaan 7",
    "sg:city":"Aalst",
    "sg:classifiers":[
        {
            "category":"Restaurant",
            "type":"Food & Drink"
        }
    ],
    "sg:phone":"+32 53 77 49 73",
    "sg:postcode":"9300",
    "sg:province":"Oost-Vlaanderen",
    "sg:tags":[
        "caf\u00e9s"
    ],
    "wof:name":"Taverne Hazard",
    "wof:placetype":"venue"
},
  "geometry": {"coordinates":[4.0366458893,50.9444847107],"type":"Point"}
}