{
  "type": "Feature",
  "properties": {
    "iso:country":"BE",
    "sg:address":"Elsenesteenweg 104",
    "sg:city":"Elsene/ixelles",
    "sg:orig_category":"Speelgoed",
    "sg:phone":"+32 2 514 17 03",
    "sg:postcode":"1050",
    "sg:province":"Bruxelles-Capitale",
    "wof:name":"Christiaensen",
    "wof:placetype":"venue"
},
  "geometry": {"coordinates":[4.3640489578,50.8353652954],"type":"Point"}
}