{
  "type": "Feature",
  "properties": {
    "addr:full":"Oosthoekstraat 6 Tielt West-Vlaanderen 8700",
    "addr:housenumber":"6",
    "addr:postcode":"8700",
    "addr:street":"Oosthoekstraat",
    "iso:country":"BE",
    "sg:address":"Oosthoekstraat 6",
    "sg:city":"Tielt",
    "sg:orig_category":"Tuinbenodigdheden",
    "sg:phone":"+32 51 68 83 77",
    "sg:postcode":"8700",
    "sg:province":"West-Vlaanderen",
    "wof:name":"Julien Demey",
    "wof:placetype":"venue"
},
  "geometry": {"coordinates":[3.4053559303,51.0137557983],"type":"Point"}
}