{
  "type": "Feature",
  "properties": {
    "addr:full":"Kwerpseweg 6 Kampenhout Vlaams-Brabant 1910",
    "addr:housenumber":"6",
    "addr:postcode":"1910",
    "addr:street":"Kwerpseweg",
    "iso:country":"BE",
    "sg:address":"Kwerpseweg 6",
    "sg:city":"Kampenhout",
    "sg:orig_category":"Mazda Voertuigen",
    "sg:phone":"+32 16 65 51 37",
    "sg:postcode":"1910",
    "sg:province":"Vlaams-Brabant",
    "wof:name":"Driessens & Zn B.v.b.a.",
    "wof:placetype":"venue"
},
  "geometry": {"coordinates":[4.5635991096,50.916847229],"type":"Point"}
}