{
  "type": "Feature",
  "properties": {
    "iso:country":"BE",
    "sg:address":"Mechelse Steenweg 225a",
    "sg:city":"Antwerpen",
    "sg:classifiers":[
        {
            "category":"Personal",
            "subcategory":"Beauty Salon",
            "type":"Services"
        }
    ],
    "sg:phone":"+32 3 218 86 36",
    "sg:postcode":"2018",
    "sg:province":"Antwerpen",
    "wof:name":"Vivace",
    "wof:placetype":"venue"
},
  "geometry": {"coordinates":[4.4125590324,51.2024841309],"type":"Point"}
}