{
  "type": "Feature",
  "properties": {
    "iso:country":"BE",
    "sg:address":"Kemmeken 17",
    "sg:city":"Merchtem",
    "sg:orig_category":"Traitements param\u00e9dicaux",
    "sg:phone":"+32 52 35 83 97",
    "sg:postcode":"1785",
    "sg:province":"Vlaams-Brabant",
    "wof:name":"J. Deneudt",
    "wof:placetype":"venue"
},
  "geometry": {"coordinates":[4.2031741142,50.9731330872],"type":"Point"}
}