{
  "type": "Feature",
  "properties": {
    "addr:full":"Bonte Pierstraat 14 Middelkerke West-Vlaanderen 8432",
    "addr:housenumber":"14",
    "addr:postcode":"8432",
    "addr:street":"Pierstraat",
    "iso:country":"BE",
    "sg:address":"Bonte Pierstraat 14",
    "sg:city":"Middelkerke",
    "sg:classifiers":[
        {
            "category":"Arena",
            "subcategory":"Sports Club",
            "type":"Entertainment"
        }
    ],
    "sg:phone":"+32 59 30 33 10",
    "sg:postcode":"8432",
    "sg:province":"West-Vlaanderen",
    "sg:tags":[
        "de"
    ],
    "wof:name":"V.c. Fleris",
    "wof:placetype":"venue"
},
  "geometry": {"coordinates":[2.8788070679,51.1765289307],"type":"Point"}
}