{
  "type": "Feature",
  "properties": {
    "addr:full":"Place Fran\u00e7ois Faniel 18 Wanze Li\u00e8ge 4520",
    "addr:housenumber":"18",
    "addr:postcode":"4520",
    "addr:street":"Place Franc\u0327Ois Faniel",
    "iso:country":"BE",
    "sg:address":"Place Fran\u00e7ois Faniel 18",
    "sg:city":"Wanze",
    "sg:classifiers":[
        {
            "category":"Professional",
            "subcategory":"Lawyer & Legal Services",
            "type":"Services"
        }
    ],
    "sg:phone":"+32 85 25 14 04",
    "sg:postcode":"4520",
    "sg:province":"Li\u00e8ge",
    "wof:name":"Mokeddem N",
    "wof:placetype":"venue"
},
  "geometry": {"coordinates":[5.2156391144,50.5357437134],"type":"Point"}
}