{
  "type": "Feature",
  "properties": {
    "iso:country":"BE",
    "sg:address":"Robert Molsstraat 43",
    "sg:city":"Antwerpen",
    "sg:orig_category":"Artsen and specialisten",
    "sg:phone":"+32 3 238 80 66",
    "sg:postcode":"2018",
    "sg:province":"Antwerpen",
    "wof:name":"W. Greyson",
    "wof:placetype":"venue"
},
  "geometry": {"coordinates":[4.4019317627,51.1997947693],"type":"Point"}
}