{
  "type": "Feature",
  "properties": {
    "addr:full":"Au Dessus Du Rabais Virton Luxembourg 6760",
    "addr:postcode":"6760",
    "addr:street":"Au Dessus Du Rabais",
    "iso:country":"BE",
    "sg:address":"Au Dessus Du Rabais",
    "sg:city":"Virton",
    "sg:classifiers":[
        {
            "category":"Travel",
            "subcategory":"Hotels & Motels",
            "type":"Entertainment"
        }
    ],
    "sg:phone":"+32 63 57 70 84",
    "sg:postcode":"6760",
    "sg:province":"Luxembourg",
    "wof:name":"Venerie (la)",
    "wof:placetype":"venue"
},
  "geometry": {"coordinates":[5.5529909134,49.5831375122],"type":"Point"}
}