{
  "type": "Feature",
  "properties": {
    "iso:country":"BE",
    "sg:address":"Berlingmolenstraat 32",
    "sg:city":"Ardooie",
    "sg:classifiers":[
        {
            "category":"Professional",
            "subcategory":"Art Services",
            "type":"Services"
        }
    ],
    "sg:phone":"+32 51 74 80 38",
    "sg:postcode":"8850",
    "sg:province":"West-Vlaanderen",
    "sg:tags":[
        "sculptor"
    ],
    "wof:name":"Vandenbussche B",
    "wof:placetype":"venue"
},
  "geometry": {"coordinates":[3.2037570477,50.9826889038],"type":"Point"}
}