{
  "type": "Feature",
  "properties": {
    "addr:full":"Kuurnsesteenweg 21 Kortrijk West-Vlaanderen 8500",
    "addr:housenumber":"21",
    "addr:postcode":"8500",
    "addr:street":"Kuurnsesteenweg",
    "iso:country":"BE",
    "sg:address":"Kuurnsesteenweg 21",
    "sg:city":"Kortrijk",
    "sg:orig_category":"Artsen and specialisten",
    "sg:phone":"+32 56 37 35 43",
    "sg:postcode":"8500",
    "sg:province":"West-Vlaanderen",
    "wof:name":"Carole Decerf",
    "wof:placetype":"venue"
},
  "geometry": {"coordinates":[3.2655820847,50.8402137756],"type":"Point"}
}