{
  "type": "Feature",
  "properties": {
    "iso:country":"BE",
    "sg:address":"Rue De La Clinique 11",
    "sg:city":"Vielsalm",
    "sg:classifiers":[
        {
            "category":"Retail",
            "subcategory":"Auto Repair",
            "type":"Services"
        }
    ],
    "sg:phone":"+32 80 21 67 61",
    "sg:postcode":"6690",
    "sg:province":"Luxembourg",
    "sg:tags":[
        "automobile",
        "servic",
        "electrical",
        "-"
    ],
    "wof:name":"Werner J",
    "wof:placetype":"venue"
},
  "geometry": {"coordinates":[5.9208989143,50.2815475464],"type":"Point"}
}