{
  "type": "Feature",
  "properties": {
    "iso:country":"BE",
    "sg:address":"Dendermondse Steenweg 56",
    "sg:city":"Sint-niklaas",
    "sg:classifiers":[
        {
            "category":"Real Estate",
            "subcategory":"Architect",
            "type":"Services"
        }
    ],
    "sg:phone":"+32 486 39 54 11",
    "sg:postcode":"9100",
    "sg:province":"Oost-Vlaanderen",
    "wof:name":"Coppens T",
    "wof:placetype":"venue"
},
  "geometry": {"coordinates":[4.1478571892,51.1466674805],"type":"Point"}
}