{
  "type": "Feature",
  "properties": {
    "addr:full":"Rue Du Pont 26 Vaux-sur-s\u00fbre (sibret) Luxembourg 6640",
    "addr:housenumber":"26",
    "addr:postcode":"6640",
    "addr:street":"Rue Du Pont",
    "iso:country":"BE",
    "sg:address":"Rue Du Pont 26",
    "sg:city":"Vaux-sur-s\u00fbre (sibret)",
    "sg:classifiers":[
        {
            "category":"Professional",
            "subcategory":"Art Services",
            "type":"Services"
        }
    ],
    "sg:phone":"+32 61 26 64 99",
    "sg:postcode":"6640",
    "sg:province":"Luxembourg",
    "sg:tags":[
        "picture",
        "framer"
    ],
    "wof:name":"Encadrements L Lambert",
    "wof:placetype":"venue"
},
  "geometry": {"coordinates":[5.636174202,49.9630699158],"type":"Point"}
}