{
  "type": "Feature",
  "properties": {
    "iso:country":"BE",
    "sg:address":"Centrumstraat 36",
    "sg:city":"Zulte",
    "sg:orig_category":"Rev\u00eatements pour sols and murs. Peinture. Eclairage et \u00e9quipements du foyer",
    "sg:phone":"+32 9 388 88 77",
    "sg:postcode":"9870",
    "sg:province":"Oost-Vlaanderen",
    "wof:name":"Andre Michels",
    "wof:placetype":"venue"
},
  "geometry": {"coordinates":[3.4673800468,50.9343070984],"type":"Point"}
}