{
  "type": "Feature",
  "properties": {
    "iso:country":"BE",
    "sg:address":"Rue Chef Lieu 20",
    "sg:city":"Silly (hellebecq)",
    "sg:classifiers":[
        {
            "category":"Retail",
            "subcategory":"Veterinary Services",
            "type":"Services"
        }
    ],
    "sg:phone":"+32 68 55 18 32",
    "sg:postcode":"7830",
    "sg:province":"Hainaut",
    "sg:tags":[
        "veterinarian"
    ],
    "wof:name":"Crochelet F",
    "wof:placetype":"venue"
},
  "geometry": {"coordinates":[3.8919389248,50.6651382446],"type":"Point"}
}