{
  "type": "Feature",
  "properties": {
    "addr:full":"Alster 9 Burg-reuland/burg-reuland Li\u00e8ge 4790",
    "addr:housenumber":"9",
    "addr:postcode":"4790",
    "addr:street":"Alster",
    "iso:country":"BE",
    "sg:address":"Alster 9",
    "sg:city":"Burg-reuland/burg-reuland",
    "sg:orig_category":"Rundveehouders",
    "sg:phone":"+32 80 32 94 49",
    "sg:postcode":"4790",
    "sg:province":"Li\u00e8ge",
    "wof:name":"Michel Weber",
    "wof:placetype":"venue"
},
  "geometry": {"coordinates":[6.1250658035,50.2108840942],"type":"Point"}
}