{
  "type": "Feature",
  "properties": {
    "addr:full":"Majoor Woodstraat 16 Oostkamp West-Vlaanderen 8020",
    "addr:housenumber":"16",
    "addr:postcode":"8020",
    "addr:street":"Majoor Woodstraat",
    "iso:country":"BE",
    "sg:address":"Majoor Woodstraat 16",
    "sg:city":"Oostkamp",
    "sg:orig_category":"Eclairage et \u00e9quipements du foyer. D\u00e9corateurs d'int\u00e9rieur. Installation de menuiserie m\u00e9tallique",
    "sg:phone":"+32 50 84 02 09",
    "sg:postcode":"8020",
    "sg:province":"West-Vlaanderen",
    "wof:name":"De Wever",
    "wof:placetype":"venue"
},
  "geometry": {"coordinates":[3.2343080044,51.1545982361],"type":"Point"}
}