{
  "type": "Feature",
  "properties": {
    "iso:country":"BE",
    "sg:address":"Poperingseweg 249",
    "sg:city":"Ieper",
    "sg:orig_category":"Traitements param\u00e9dicaux",
    "sg:phone":"+32 57 21 66 33",
    "sg:postcode":"8908",
    "sg:province":"West-Vlaanderen",
    "wof:name":"D. Declerck",
    "wof:placetype":"venue"
},
  "geometry": {"coordinates":[2.8307759762,50.8528862],"type":"Point"}
}