{
  "type": "Feature",
  "properties": {
    "iso:country":"BE",
    "sg:address":"Rue Du Parc 69",
    "sg:city":"La Louviere",
    "sg:orig_category":"Advocaten and juridische adviseurs",
    "sg:phone":"+32 64 22 19 23",
    "sg:postcode":"7100",
    "sg:province":"Hainaut",
    "wof:name":"Lisbeth Vanquaelle",
    "wof:placetype":"venue"
},
  "geometry": {"coordinates":[4.1925878525,50.4771957397],"type":"Point"}
}