{
  "type": "Feature",
  "properties": {
    "iso:country":"BE",
    "sg:address":"Markt 20",
    "sg:city":"Maaseik",
    "sg:classifiers":[
        {
            "category":"Restaurant",
            "type":"Food & Drink"
        }
    ],
    "sg:phone":"+32 89 57 28 60",
    "sg:postcode":"3680",
    "sg:province":"Limburg",
    "wof:name":"Vivendum",
    "wof:placetype":"venue"
},
  "geometry": {"coordinates":[5.7918481827,51.0943183899],"type":"Point"}
}