{
  "type": "Feature",
  "properties": {
    "iso:country":"BE",
    "sg:address":"Polbroek 6",
    "sg:city":"Sint-lievens-houtem",
    "sg:orig_category":"Herstelling and restauratie van meubelen Winkelinrichting and handelsuitrusting Gh",
    "sg:phone":"+32 53 62 96 06",
    "sg:postcode":"9520",
    "sg:province":"Oost-Vlaanderen",
    "wof:name":"Jean Caufrier",
    "wof:placetype":"venue"
},
  "geometry": {"coordinates":[3.8538460732,50.9203605652],"type":"Point"}
}