{
  "type": "Feature",
  "properties": {
    "iso:country":"BE",
    "sg:address":"Rue Du Moulin De Falogne 16",
    "sg:city":"Nandrin",
    "sg:orig_category":"Experts-comptables",
    "sg:phone":"+32 4 371 24 72",
    "sg:postcode":"4550",
    "sg:province":"Li\u00e8ge",
    "wof:name":"F. Renard",
    "wof:placetype":"venue"
},
  "geometry": {"coordinates":[5.401922226,50.5386657715],"type":"Point"}
}