{
  "type": "Feature",
  "properties": {
    "addr:full":"Mechelsestraat 62 Londerzeel Vlaams-Brabant 1840",
    "addr:housenumber":"62",
    "addr:postcode":"1840",
    "addr:street":"Mechelsestraat",
    "iso:country":"BE",
    "sg:address":"Mechelsestraat 62",
    "sg:city":"Londerzeel",
    "sg:orig_category":"V\u00e9t\u00e9rinaires",
    "sg:phone":"+32 52 30 23 70",
    "sg:postcode":"1840",
    "sg:province":"Vlaams-Brabant",
    "wof:name":"Magda Van Cauwenberghe",
    "wof:placetype":"venue"
},
  "geometry": {"coordinates":[4.3058857918,51.0040893555],"type":"Point"}
}