{
  "type": "Feature",
  "properties": {
    "addr:full":"Grote Markt 5c Wevelgem West-Vlaanderen 8560",
    "addr:housenumber":"5c",
    "addr:postcode":"8560",
    "addr:street":"Grote Markt",
    "iso:country":"BE",
    "sg:address":"Grote Markt 5c",
    "sg:city":"Wevelgem",
    "sg:classifiers":[
        {
            "category":"Real Estate",
            "subcategory":"Surveying",
            "type":"Services"
        }
    ],
    "sg:phone":"+32 56 41 04 10",
    "sg:postcode":"8560",
    "sg:province":"West-Vlaanderen",
    "sg:tags":[
        "surveyor",
        "land"
    ],
    "wof:name":"Walraeve P",
    "wof:placetype":"venue"
},
  "geometry": {"coordinates":[3.1848890781,50.8091964722],"type":"Point"}
}