{
  "type": "Feature",
  "properties": {
    "addr:full":"Warempage 9ba La Roche-en-ardenne Luxembourg 6983",
    "addr:housenumber":"9ba",
    "addr:postcode":"6983",
    "addr:street":"Warempage",
    "iso:country":"BE",
    "sg:address":"Warempage 9ba",
    "sg:city":"La Roche-en-ardenne",
    "sg:orig_category":"Bouwmaterialen Gh Installatie van houten of kunststof schrijnwerk MEUBELONTWERP AND -INSTALLATIE",
    "sg:phone":"+32 84 43 31 99",
    "sg:postcode":"6983",
    "sg:province":"Luxembourg",
    "wof:name":"Sibret Benoit M M E",
    "wof:placetype":"venue"
},
  "geometry": {"coordinates":[5.6396098137,50.1205406189],"type":"Point"}
}