{
  "type": "Feature",
  "properties": {
    "addr:full":"Heiendestraat 52 Lokeren Oost-Vlaanderen 9160",
    "addr:housenumber":"52",
    "addr:postcode":"9160",
    "addr:street":"Heiendestraat",
    "iso:country":"BE",
    "sg:address":"Heiendestraat 52",
    "sg:city":"Lokeren",
    "sg:classifiers":[
        {
            "category":"Insurance",
            "subcategory":"Insurance Agent",
            "type":"Services"
        }
    ],
    "sg:phone":"+32 9 348 62 38",
    "sg:postcode":"9160",
    "sg:province":"Oost-Vlaanderen",
    "sg:tags":[
        "broker"
    ],
    "wof:name":"Kantoor Van Hille L",
    "wof:placetype":"venue"
},
  "geometry": {"coordinates":[3.9528870583,51.083656311],"type":"Point"}
}