{
  "type": "Feature",
  "properties": {
    "addr:full":"Rue De Boncelles 343 Seraing Li\u00e8ge 4102",
    "addr:housenumber":"343",
    "addr:postcode":"4102",
    "addr:street":"Rue De Boncelles",
    "iso:country":"BE",
    "sg:address":"Rue De Boncelles 343",
    "sg:city":"Seraing",
    "sg:orig_category":"Installation \u00e9lectrique r\u00e9sidentielle. Construction de maisons",
    "sg:phone":"+32 4 337 49 91",
    "sg:postcode":"4102",
    "sg:province":"Li\u00e8ge",
    "wof:name":"Bati-elec Services",
    "wof:placetype":"venue"
},
  "geometry": {"coordinates":[5.5316781998,50.5975532532],"type":"Point"}
}