{
  "type": "Feature",
  "properties": {
    "addr:full":"Heirweg 45 Moerbeke (moerbeke-waas) Oost-Vlaanderen 9180",
    "addr:housenumber":"45",
    "addr:postcode":"9180",
    "addr:street":"Heirweg",
    "iso:country":"BE",
    "sg:address":"Heirweg 45",
    "sg:city":"Moerbeke (moerbeke-waas)",
    "sg:classifiers":[
        {
            "category":"Recreation",
            "subcategory":"Fishing",
            "type":"Entertainment"
        }
    ],
    "sg:phone":"+32 9 346 75 85",
    "sg:postcode":"9180",
    "sg:province":"Oost-Vlaanderen",
    "sg:tags":[
        "tackle"
    ],
    "wof:name":"De Witte",
    "wof:placetype":"venue"
},
  "geometry": {"coordinates":[3.9756369591,51.1765136719],"type":"Point"}
}