{
  "type": "Feature",
  "properties": {
    "addr:full":"Heldergemstraat 54 Haaltert (heldergem) Oost-Vlaanderen 9450",
    "addr:housenumber":"54",
    "addr:postcode":"9450",
    "addr:street":"Heldergemstraat",
    "iso:country":"BE",
    "sg:address":"Heldergemstraat 54",
    "sg:city":"Haaltert (heldergem)",
    "sg:classifiers":[
        {
            "category":"Health Services",
            "subcategory":"Dentist",
            "type":"Services"
        }
    ],
    "sg:phone":"+32 53 62 19 00",
    "sg:postcode":"9450",
    "sg:province":"Oost-Vlaanderen",
    "wof:name":"De Schryver A",
    "wof:placetype":"venue"
},
  "geometry": {"coordinates":[3.9585208893,50.8749313354],"type":"Point"}
}