{
  "type": "Feature",
  "properties": {
    "addr:full":"Ijzeren Bareel 59 Spiere-helkijn/espierres-helchin West-Vlaanderen 8587",
    "addr:housenumber":"59",
    "addr:postcode":"8587",
    "addr:street":"Ijzeren Bareel",
    "iso:country":"BE",
    "sg:address":"Ijzeren Bareel 59",
    "sg:city":"Spiere-helkijn/espierres-helchin",
    "sg:classifiers":[
        {
            "category":"Cafe",
            "type":"Food & Drink"
        }
    ],
    "sg:phone":"+32 56 45 55 80",
    "sg:postcode":"8587",
    "sg:province":"West-Vlaanderen",
    "sg:tags":[
        "caf\u00e9s"
    ],
    "wof:name":"Caf\u00c9 Bascule",
    "wof:placetype":"venue"
},
  "geometry": {"coordinates":[3.3307158947,50.7259101868],"type":"Point"}
}