{
  "type": "Feature",
  "properties": {
    "iso:country":"BE",
    "sg:address":"Rue Chavez 22",
    "sg:city":"Etalle",
    "sg:orig_category":"Pleisterwerk",
    "sg:phone":"+32 63 45 58 13",
    "sg:postcode":"6741",
    "sg:province":"Luxembourg",
    "wof:name":"Fe. Philippe Fr\u00c8res",
    "wof:placetype":"venue"
},
  "geometry": {"coordinates":[5.6673212051,49.6705703735],"type":"Point"}
}