{
  "type": "Feature",
  "properties": {
    "iso:country":"BE",
    "sg:address":"Stationstraat 137",
    "sg:city":"Haacht",
    "sg:classifiers":[
        {
            "category":"Retail",
            "subcategory":"Auto Repair",
            "type":"Services"
        }
    ],
    "sg:phone":"+32 16 60 09 79",
    "sg:postcode":"3150",
    "sg:province":"Vlaams-Brabant",
    "sg:tags":[
        "garage"
    ],
    "wof:name":"Haacht Motors Bvba",
    "wof:placetype":"venue"
},
  "geometry": {"coordinates":[4.6228938103,50.9714431763],"type":"Point"}
}