{
  "type": "Feature",
  "properties": {
    "addr:full":"Paul Hymanslaan 2 Sint-lambrechts-woluwe/woluwe-saint-lambert Bruxelles-Capitale 1200",
    "addr:housenumber":"2",
    "addr:postcode":"1200",
    "addr:street":"Hymanslaan",
    "iso:country":"BE",
    "sg:address":"Paul Hymanslaan 2",
    "sg:city":"Sint-lambrechts-woluwe/woluwe-saint-lambert",
    "sg:orig_category":"Kinderopvang",
    "sg:phone":"+32 2 761 29 74",
    "sg:postcode":"1200",
    "sg:province":"Bruxelles-Capitale",
    "wof:name":"Administr.comm.de W.s.l.",
    "wof:placetype":"venue"
},
  "geometry": {"coordinates":[4.4258089066,50.8439483643],"type":"Point"}
}