{
  "type": "Feature",
  "properties": {
    "addr:full":"Rue Wazon 9 Luik Li\u00e8ge 4000",
    "addr:housenumber":"9",
    "addr:postcode":"4000",
    "addr:street":"Rue Wazon",
    "iso:country":"BE",
    "sg:address":"Rue Wazon 9",
    "sg:city":"Luik",
    "sg:orig_category":"Articles m\u00e9dicaux and orthop\u00e9diques",
    "sg:phone":"+32 4 222 22 01",
    "sg:postcode":"4000",
    "sg:province":"Li\u00e8ge",
    "wof:name":"Omikron",
    "wof:placetype":"venue"
},
  "geometry": {"coordinates":[5.557557106,50.6370735168],"type":"Point"}
}