{
  "type": "Feature",
  "properties": {
    "addr:full":"Biesstraat 3 Zwalm Oost-Vlaanderen 9636",
    "addr:housenumber":"3",
    "addr:postcode":"9636",
    "addr:street":"Biesstraat;Oost-Vlaanderen",
    "iso:country":"BE",
    "sg:address":"Biesstraat 3",
    "sg:city":"Zwalm",
    "sg:orig_category":"Diverse voedingsmiddelen Gh",
    "sg:phone":"+32 55 49 73 01",
    "sg:postcode":"9636",
    "sg:province":"Oost-Vlaanderen",
    "wof:name":"Euro Moules",
    "wof:placetype":"venue"
},
  "geometry": {"coordinates":[3.6889920235,50.8874282837],"type":"Point"}
}