{
  "type": "Feature",
  "properties": {
    "addr:full":"Rue Des Saules 48 Lasne (ohain) Brabant Wallon 1380",
    "addr:housenumber":"48",
    "addr:postcode":"1380",
    "addr:street":"Rue Des Saules;Wallon",
    "iso:country":"BE",
    "sg:address":"Rue Des Saules 48",
    "sg:city":"Lasne (ohain)",
    "sg:classifiers":[
        {
            "category":"Banks & Credit Unions",
            "subcategory":"Investment Brokerage",
            "type":"Services"
        }
    ],
    "sg:phone":"+32 2 351 59 49",
    "sg:postcode":"1380",
    "sg:province":"Brabant Wallon",
    "sg:tags":[
        "auditor"
    ],
    "wof:name":"Misselyn V",
    "wof:placetype":"venue"
},
  "geometry": {"coordinates":[4.483235836,50.6850166321],"type":"Point"}
}