{
  "type": "Feature",
  "properties": {
    "addr:full":"Avenue De Messidor 198 Box 6 Bruxelles (uccle) Bruxelles-Capitale 1180",
    "addr:housenumber":"198;6",
    "addr:postcode":"1180",
    "addr:street":"Avenue De Messidor;Box",
    "iso:country":"BE",
    "sg:address":"Avenue De Messidor 198 Box 6",
    "sg:city":"Bruxelles (uccle)",
    "sg:classifiers":[
        {
            "category":"Real Estate",
            "subcategory":"Architect",
            "type":"Services"
        }
    ],
    "sg:phone":"+32 2 345 90 35",
    "sg:postcode":"1180",
    "sg:province":"Bruxelles-Capitale",
    "wof:name":"Boelens M",
    "wof:placetype":"venue"
},
  "geometry": {"coordinates":[4.3483800888,50.8107795715],"type":"Point"}
}