{
  "type": "Feature",
  "properties": {
    "addr:full":"Rue Lhoir 97 Tertre Hainaut 7333",
    "addr:housenumber":"97",
    "addr:postcode":"7333",
    "addr:street":"Rue Lhoir;Hainaut",
    "iso:country":"BE",
    "sg:address":"Rue Lhoir 97",
    "sg:city":"Tertre",
    "sg:classifiers":[
        {
            "category":"Manufacturing",
            "subcategory":"Metals",
            "type":"Manufacturing & Wholesale Goods"
        }
    ],
    "sg:phone":"+32 65 64 33 51",
    "sg:postcode":"7333",
    "sg:province":"Hainaut",
    "sg:tags":[
        "processing"
    ],
    "wof:name":"Les Ateliers De Tertre A.s.b.l.",
    "wof:placetype":"venue"
},
  "geometry": {"coordinates":[3.826900959,50.4647521973],"type":"Point"}
}