{
  "type": "Feature",
  "properties": {
    "iso:country":"BE",
    "sg:address":"Arsenaalstraat 58",
    "sg:city":"Gent (gentbrugge)",
    "sg:classifiers":[
        {
            "category":"Building & Trades",
            "subcategory":"Cleaning & Sanitation",
            "type":"Services"
        }
    ],
    "sg:phone":"+32 9 231 01 55",
    "sg:postcode":"9050",
    "sg:province":"Oost-Vlaanderen",
    "sg:tags":[
        "cleaner",
        "window"
    ],
    "wof:name":"Sven Clean",
    "wof:placetype":"venue"
},
  "geometry": {"coordinates":[3.7554769516,51.0278892517],"type":"Point"}
}