{
  "type": "Feature",
  "properties": {
    "addr:full":"Diepestraat 138 Aalst Oost-Vlaanderen 9300",
    "addr:housenumber":"138",
    "addr:postcode":"9300",
    "addr:street":"Diepestraat",
    "iso:country":"BE",
    "sg:address":"Diepestraat 138",
    "sg:city":"Aalst",
    "sg:orig_category":"Rev\u00eatements de sols and murs. Eclairage et \u00e9quipements du foyer. Art and fournitures artistiques",
    "sg:phone":"+32 53 77 30 63",
    "sg:postcode":"9300",
    "sg:province":"Oost-Vlaanderen",
    "wof:name":"'t Sperreken",
    "wof:placetype":"venue"
},
  "geometry": {"coordinates":[4.0344319344,50.9286079407],"type":"Point"}
}