{
  "type": "Feature",
  "properties": {
    "iso:country":"BE",
    "sg:address":"Vieille Voie-de-tongres 83",
    "sg:city":"Li\u00c8ge",
    "sg:orig_category":"Winkelinrichting and handelsuitrusting Gh",
    "sg:phone":"+32 4 226 04 31",
    "sg:postcode":"4000",
    "sg:province":"Li\u00e8ge",
    "wof:name":"Andr\u00c9 Joachims",
    "wof:placetype":"venue"
},
  "geometry": {"coordinates":[5.5689611435,50.6592483521],"type":"Point"}
}