{
  "type": "Feature",
  "properties": {
    "iso:country":"BE",
    "sg:address":"Notestraat 64a",
    "sg:city":"Ternat (sint-katherina-lombeek)",
    "sg:classifiers":[
        {
            "category":"Health Services",
            "subcategory":"Doctor",
            "type":"Services"
        }
    ],
    "sg:phone":"+32 2 582 29 13",
    "sg:postcode":"1742",
    "sg:province":"Vlaams-Brabant",
    "sg:tags":[
        "medicinephysicians",
        "surgeon"
    ],
    "wof:name":"De Troch Chantal",
    "wof:placetype":"venue"
},
  "geometry": {"coordinates":[4.1402549744,50.8730316162],"type":"Point"}
}