{
  "type": "Feature",
  "properties": {
    "iso:country":"BE",
    "sg:address":"Klein Bijgaardenstraat 27",
    "sg:city":"Sint-pieters-leeuw",
    "sg:classifiers":[
        {
            "category":"Home & Garden",
            "subcategory":"Kitchen Supply",
            "type":"Retail Goods"
        }
    ],
    "sg:phone":"+32 2 331 19 72",
    "sg:postcode":"1600",
    "sg:province":"Vlaams-Brabant",
    "sg:tags":[
        "-",
        "industrial",
        "installation",
        "equipment"
    ],
    "wof:name":"New Horeca Service",
    "wof:placetype":"venue"
},
  "geometry": {"coordinates":[4.2824897766,50.7984733582],"type":"Point"}
}