{
  "type": "Feature",
  "properties": {
    "addr:full":"Industrielaan 5a Diepenbeek Limburg 3590",
    "addr:housenumber":"5a",
    "addr:postcode":"3590",
    "addr:street":"Industrielaan",
    "iso:country":"BE",
    "sg:address":"Industrielaan 5a",
    "sg:city":"Diepenbeek",
    "sg:orig_category":"Airconditioning and ventilatie Loodgieterij, verwarming and sanitaire installaties",
    "sg:phone":"+32 11 33 17 99",
    "sg:postcode":"3590",
    "sg:province":"Limburg",
    "wof:name":"Huygen En Van Ende",
    "wof:placetype":"venue"
},
  "geometry": {"coordinates":[5.4252538681,50.9093055725],"type":"Point"}
}