{
  "type": "Feature",
  "properties": {
    "addr:full":"Broekkant 56 Opglabbeek Limburg 3660",
    "addr:housenumber":"56",
    "addr:postcode":"3660",
    "addr:street":"Broekkant",
    "iso:country":"BE",
    "sg:address":"Broekkant 56",
    "sg:city":"Opglabbeek",
    "sg:orig_category":"Eleveurs de volaille",
    "sg:phone":"+32 89 85 43 56",
    "sg:postcode":"3660",
    "sg:province":"Limburg",
    "wof:name":"Maria Cuppens",
    "wof:placetype":"venue"
},
  "geometry": {"coordinates":[5.5902328491,51.0378265381],"type":"Point"}
}