{
  "type": "Feature",
  "properties": {
    "iso:country":"BE",
    "sg:address":"Rue Depouhon 14",
    "sg:city":"Verviers",
    "sg:orig_category":"Alternatieve geneeskunde Artsen and specialisten",
    "sg:phone":"+32 87 31 61 98",
    "sg:postcode":"4800",
    "sg:province":"Li\u00e8ge",
    "wof:name":"Yvon Piron",
    "wof:placetype":"venue"
},
  "geometry": {"coordinates":[5.8594508171,50.5917663574],"type":"Point"}
}