{
  "type": "Feature",
  "properties": {
    "addr:full":"Pierstraat 182 Kontich Antwerpen 2550",
    "addr:housenumber":"182",
    "addr:postcode":"2550",
    "addr:street":"Pierstraat",
    "iso:country":"BE",
    "sg:address":"Pierstraat 182",
    "sg:city":"Kontich",
    "sg:orig_category":"Enseignement maternel and primaire",
    "sg:phone":"+32 3 457 28 67",
    "sg:postcode":"2550",
    "sg:province":"Antwerpen",
    "wof:name":"Vrije Kleuterschool",
    "wof:placetype":"venue"
},
  "geometry": {"coordinates":[4.4240550995,51.1301803589],"type":"Point"}
}