{
  "type": "Feature",
  "properties": {
    "addr:full":"Geraardsbergenstraat 155 Oudenaarde Oost-Vlaanderen 9700",
    "addr:housenumber":"155",
    "addr:postcode":"9700",
    "addr:street":"Geraardsbergenstraat",
    "iso:country":"BE",
    "sg:address":"Geraardsbergenstraat 155",
    "sg:city":"Oudenaarde",
    "sg:classifiers":[
        {
            "category":"Bars & Pubs",
            "type":"Food & Drink"
        }
    ],
    "sg:phone":"+32 55 31 24 01",
    "sg:postcode":"9700",
    "sg:province":"Oost-Vlaanderen",
    "wof:name":"Groenenboom",
    "wof:placetype":"venue"
},
  "geometry": {"coordinates":[3.6416499615,50.829208374],"type":"Point"}
}