{
  "type": "Feature",
  "properties": {
    "addr:full":"Mechelsesteenweg 89 Dendermonde Oost-Vlaanderen 9200",
    "addr:housenumber":"89",
    "addr:postcode":"9200",
    "addr:street":"Mechelsesteenweg;Oost-Vlaanderen",
    "iso:country":"BE",
    "sg:address":"Mechelsesteenweg 89",
    "sg:city":"Dendermonde",
    "sg:classifiers":[
        {
            "category":"Food & Beverages",
            "subcategory":"Fruits & Vegetables",
            "type":"Retail Goods"
        }
    ],
    "sg:phone":"+32 52 21 14 89",
    "sg:postcode":"9200",
    "sg:province":"Oost-Vlaanderen",
    "sg:tags":[
        "groenten"
    ],
    "wof:name":"De Seizoenen",
    "wof:placetype":"venue"
},
  "geometry": {"coordinates":[4.1182842255,51.0362014771],"type":"Point"}
}