{
  "type": "Feature",
  "properties": {
    "addr:full":"Kloosterstraat 2 Kruibeke Oost-Vlaanderen 9150",
    "addr:housenumber":"2",
    "addr:postcode":"9150",
    "addr:street":"Kloosterstraat",
    "iso:country":"BE",
    "sg:address":"Kloosterstraat 2",
    "sg:city":"Kruibeke",
    "sg:orig_category":"Herstelling horloges and juwelen Juwelen and horloges",
    "sg:phone":"+32 3 774 11 89",
    "sg:postcode":"9150",
    "sg:province":"Oost-Vlaanderen",
    "wof:name":"Veresta",
    "wof:placetype":"venue"
},
  "geometry": {"coordinates":[4.289812088,51.1273841858],"type":"Point"}
}