{
  "type": "Feature",
  "properties": {
    "iso:country":"BE",
    "sg:address":"Brugstraat 45",
    "sg:city":"Beveren",
    "sg:classifiers":[
        {
            "category":"Insurance",
            "subcategory":"Insurance Agent",
            "type":"Services"
        }
    ],
    "sg:phone":"+32 3 775 80 22",
    "sg:postcode":"9120",
    "sg:province":"Oost-Vlaanderen",
    "sg:tags":[
        "verzekeringsmakelaars",
        "expert"
    ],
    "wof:name":"Zakenkantoor Van Goethem",
    "wof:placetype":"venue"
},
  "geometry": {"coordinates":[4.1980237961,51.2200164795],"type":"Point"}
}