{
  "type": "Feature",
  "properties": {
    "addr:full":"Klokkeputstraat 120 Roeselare West-Vlaanderen 8800",
    "addr:housenumber":"120",
    "addr:postcode":"8800",
    "addr:street":"Klokkeputstraat",
    "iso:country":"BE",
    "sg:address":"Klokkeputstraat 120",
    "sg:city":"Roeselare",
    "sg:orig_category":"Woningbouw",
    "sg:phone":"+32 51 21 11 96",
    "sg:postcode":"8800",
    "sg:province":"West-Vlaanderen",
    "wof:name":"Christophe Vanderschaeghe",
    "wof:placetype":"venue"
},
  "geometry": {"coordinates":[3.102504015,50.9644393921],"type":"Point"}
}