{
  "type": "Feature",
  "properties": {
    "iso:country":"BE",
    "sg:address":"Rue Josaphat 49-53",
    "sg:city":"Bruxelles (schaerbeek)",
    "sg:classifiers":[
        {
            "category":"Shopping",
            "subcategory":"Clothing, Apparel, & Fashions",
            "type":"Retail Goods"
        }
    ],
    "sg:phone":"+32 2 217 93 22",
    "sg:postcode":"1030",
    "sg:province":"Bruxelles-Capitale",
    "sg:tags":[
        "lady",
        "clothing",
        "-"
    ],
    "wof:name":"Dora Textile Sc",
    "wof:placetype":"venue"
},
  "geometry": {"coordinates":[4.3730678558,50.8574943542],"type":"Point"}
}