{
  "type": "Feature",
  "properties": {
    "addr:full":"Beliweg 281kaai Antwerpen Antwerpen 2030",
    "addr:postcode":"2030",
    "iso:country":"BE",
    "sg:address":"Beliweg 281kaai",
    "sg:city":"Antwerpen",
    "sg:classifiers":[
        {
            "category":"Utilities",
            "subcategory":"Fuel Oil & Lpg",
            "type":"Services"
        }
    ],
    "sg:phone":"+32 3 545 68 11",
    "sg:postcode":"2030",
    "sg:province":"Antwerpen",
    "sg:tags":[
        "refinery"
    ],
    "wof:name":"Nynas",
    "wof:placetype":"venue"
},
  "geometry": {"coordinates":[4.3861298561,51.2502708435],"type":"Point"}
}