{
  "type": "Feature",
  "properties": {
    "iso:country":"BE",
    "sg:address":"Rue Grande Pierr\u00e8re 9a",
    "sg:city":"Sambreville (falisolle)",
    "sg:classifiers":[
        {
            "category":"Taxi",
            "type":"Transportation"
        }
    ],
    "sg:phone":"+32 496 60 17 17",
    "sg:postcode":"5060",
    "sg:province":"Namur",
    "sg:tags":[
        "taxicab"
    ],
    "wof:name":"Kristax Sprl",
    "wof:placetype":"venue"
},
  "geometry": {"coordinates":[4.6302089691,50.424495697],"type":"Point"}
}