{
  "type": "Feature",
  "properties": {
    "addr:full":"Brugmannlaan 292 Ukkel/uccle Bruxelles-Capitale 1180",
    "addr:housenumber":"292",
    "addr:postcode":"1180",
    "addr:street":"Brugmannlaan;/",
    "iso:country":"BE",
    "sg:address":"Brugmannlaan 292",
    "sg:city":"Ukkel/uccle",
    "sg:orig_category":"Artsen and specialisten",
    "sg:phone":"+32 2 343 54 59",
    "sg:postcode":"1180",
    "sg:province":"Bruxelles-Capitale",
    "wof:name":"Jean-pierre Vandenput",
    "wof:placetype":"venue"
},
  "geometry": {"coordinates":[4.3470849991,50.8121795654],"type":"Point"}
}