{
  "type": "Feature",
  "properties": {
    "iso:country":"BE",
    "sg:address":"Moerheide 119",
    "sg:city":"Hamme",
    "sg:orig_category":"Entretien and r\u00e9parations de voitures",
    "sg:phone":"+32 52 47 19 70",
    "sg:postcode":"9220",
    "sg:province":"Oost-Vlaanderen",
    "wof:name":"Rudy Windey",
    "wof:placetype":"venue"
},
  "geometry": {"coordinates":[4.1090450287,51.0928077698],"type":"Point"}
}