{
  "type": "Feature",
  "properties": {
    "iso:country":"BE",
    "sg:address":"Avenue Du Joli Mai 10",
    "sg:city":"Rixensart (genval)",
    "sg:classifiers":[
        {
            "category":"Banks & Credit Unions",
            "subcategory":"Investment Brokerage",
            "type":"Services"
        }
    ],
    "sg:phone":"+32 478 33 52 48",
    "sg:postcode":"1332",
    "sg:province":"Brabant Wallon",
    "sg:tags":[
        "auditor"
    ],
    "wof:name":"Bastogne Sandrine Sprl",
    "wof:placetype":"venue"
},
  "geometry": {"coordinates":[4.510351181,50.7256011963],"type":"Point"}
}