{
  "type": "Feature",
  "properties": {
    "iso:country":"BE",
    "sg:address":"Baron R. De Vironlaan 38",
    "sg:city":"Dilbeek",
    "sg:orig_category":"M\u00e9decins and sp\u00e9cialistes",
    "sg:phone":"+32 2 466 04 90",
    "sg:postcode":"1700",
    "sg:province":"Vlaams-Brabant",
    "wof:name":"Jean Pollet",
    "wof:placetype":"venue"
},
  "geometry": {"coordinates":[4.2681207657,50.8473892212],"type":"Point"}
}