{
  "type": "Feature",
  "properties": {
    "iso:country":"BE",
    "sg:address":"Lange Molensstraat 60",
    "sg:city":"Vilvoorde",
    "sg:classifiers":[
        {
            "category":"Restaurant",
            "type":"Food & Drink"
        }
    ],
    "sg:phone":"+32 2 251 04 72",
    "sg:postcode":"1800",
    "sg:province":"Vlaams-Brabant",
    "wof:name":"De Rembrandt",
    "wof:placetype":"venue"
},
  "geometry": {"coordinates":[4.4235081673,50.9275665283],"type":"Point"}
}