{
  "type": "Feature",
  "properties": {
    "addr:full":"Ieperstraat 29 Wervik (geluwe) West-Vlaanderen 8940",
    "addr:housenumber":"29",
    "addr:postcode":"8940",
    "addr:street":"Ieperstraat",
    "iso:country":"BE",
    "sg:address":"Ieperstraat 29",
    "sg:city":"Wervik (geluwe)",
    "sg:classifiers":[
        {
            "category":"Bars & Pubs",
            "type":"Food & Drink"
        }
    ],
    "sg:phone":"+32 56 51 64 35",
    "sg:postcode":"8940",
    "sg:province":"West-Vlaanderen",
    "wof:name":"St-krispijn",
    "wof:placetype":"venue"
},
  "geometry": {"coordinates":[3.0728890896,50.8105773926],"type":"Point"}
}