{
  "type": "Feature",
  "properties": {
    "addr:full":"Sur La Heid 22 Aywaille (sougn\u00e9-remouchamps) Li\u00e8ge 4920",
    "addr:housenumber":"22",
    "addr:postcode":"4920",
    "addr:street":"La Heid;Sougne\u0301-Remouchamps",
    "iso:country":"BE",
    "sg:address":"Sur La Heid 22",
    "sg:city":"Aywaille (sougn\u00e9-remouchamps)",
    "sg:classifiers":[
        {
            "category":"Real Estate",
            "subcategory":"Architect",
            "type":"Services"
        }
    ],
    "sg:phone":"+32 4 382 25 88",
    "sg:postcode":"4920",
    "sg:province":"Li\u00e8ge",
    "wof:name":"Alexandre J-c",
    "wof:placetype":"venue"
},
  "geometry": {"coordinates":[5.6793370247,50.4764328003],"type":"Point"}
}