{
  "type": "Feature",
  "properties": {
    "addr:full":"Bld. De La Sauveni\u00c8re 160 Liege Li\u00e8ge 4000",
    "addr:housenumber":"160",
    "addr:postcode":"4000",
    "addr:street":"De La Sauvenie\u0300Re",
    "iso:country":"BE",
    "sg:address":"Bld. De La Sauveni\u00c8re 160",
    "sg:city":"Liege",
    "sg:classifiers":[
        {
            "category":"Fast Food",
            "type":"Food & Drink"
        }
    ],
    "sg:phone":"+32 4 232 03 03",
    "sg:postcode":"4000",
    "sg:province":"Li\u00e8ge",
    "sg:tags":[
        "meeneem",
        "restaurant"
    ],
    "wof:name":"Pitza Service",
    "wof:placetype":"venue"
},
  "geometry": {"coordinates":[5.567565918,50.6408157349],"type":"Point"}
}