{
  "type": "Feature",
  "properties": {
    "addr:full":"Avenue Professeur Henrijean 42d Spa Li\u00e8ge 4900",
    "addr:housenumber":"42d",
    "addr:postcode":"4900",
    "addr:street":"Avenue Professeur Henrijean",
    "iso:country":"BE",
    "sg:address":"Avenue Professeur Henrijean 42d",
    "sg:city":"Spa",
    "sg:classifiers":[
        {
            "category":"Social Services",
            "subcategory":"Job Training",
            "type":"Services"
        }
    ],
    "sg:phone":"+32 87 77 04 42",
    "sg:postcode":"4900",
    "sg:province":"Li\u00e8ge",
    "sg:tags":[
        "coordinator",
        "safety"
    ],
    "wof:name":"Exas Sprl",
    "wof:placetype":"venue"
},
  "geometry": {"coordinates":[5.8562531471,50.4828948975],"type":"Point"}
}