{
  "type": "Feature",
  "properties": {
    "addr:full":"Den Bremt 63 Herent Vlaams-Brabant 3020",
    "addr:housenumber":"63",
    "addr:postcode":"3020",
    "addr:street":"Den Bremt",
    "iso:country":"BE",
    "sg:address":"Den Bremt 63",
    "sg:city":"Herent",
    "sg:orig_category":"Charpentes and couvertures. Plomberie, chauffage and installations sanitaires",
    "sg:phone":"+32 16 22 41 30",
    "sg:postcode":"3020",
    "sg:province":"Vlaams-Brabant",
    "wof:name":"Gustave",
    "wof:placetype":"venue"
},
  "geometry": {"coordinates":[4.6629328728,50.9034767151],"type":"Point"}
}