{
  "type": "Feature",
  "properties": {
    "iso:country":"BE",
    "sg:address":"Rue De Scrawelle 61",
    "sg:city":"Seneffe",
    "sg:orig_category":"Charpentes and couvertures",
    "sg:phone":"+32 64 54 87 71",
    "sg:postcode":"7180",
    "sg:province":"Hainaut",
    "wof:name":"Fernand Senterre",
    "wof:placetype":"venue"
},
  "geometry": {"coordinates":[4.2449731827,50.5358581543],"type":"Point"}
}