{
  "type": "Feature",
  "properties": {
    "addr:full":"Christoffelpolder 1 Sint-laureins Oost-Vlaanderen 9988",
    "addr:housenumber":"1",
    "addr:postcode":"9988",
    "addr:street":"Christoffelpolder",
    "iso:country":"BE",
    "sg:address":"Christoffelpolder 1",
    "sg:city":"Sint-laureins",
    "sg:orig_category":"Groenten and fruit Gh",
    "sg:phone":"+32 9 373 68 08",
    "sg:postcode":"9988",
    "sg:province":"Oost-Vlaanderen",
    "wof:name":"Eric Dessomviele",
    "wof:placetype":"venue"
},
  "geometry": {"coordinates":[3.6384758949,51.2580070496],"type":"Point"}
}