{
  "type": "Feature",
  "properties": {
    "addr:full":"Molenstraat 8 Kontich Antwerpen 2550",
    "addr:housenumber":"8",
    "addr:postcode":"2550",
    "addr:street":"Molenstraat",
    "iso:country":"BE",
    "sg:address":"Molenstraat 8",
    "sg:city":"Kontich",
    "sg:orig_category":"Slagers",
    "sg:phone":"+32 3 457 03 12",
    "sg:postcode":"2550",
    "sg:province":"Antwerpen",
    "wof:name":"Luc Crauwels",
    "wof:placetype":"venue"
},
  "geometry": {"coordinates":[4.4444189072,51.1354484558],"type":"Point"}
}