{
  "type": "Feature",
  "properties": {
    "addr:full":"Uitkerksestraat 3 De Haan West-Vlaanderen 8420",
    "addr:housenumber":"3",
    "addr:postcode":"8420",
    "addr:street":"Uitkerksestraat",
    "iso:country":"BE",
    "sg:address":"Uitkerksestraat 3",
    "sg:city":"De Haan",
    "sg:orig_category":"Eleveurs and marchands de porcs. Eleveurs de bovins",
    "sg:phone":"+32 50 41 83 73",
    "sg:postcode":"8420",
    "sg:province":"West-Vlaanderen",
    "wof:name":"Lucas Fleurbaey",
    "wof:placetype":"venue"
},
  "geometry": {"coordinates":[3.1025350094,51.2935447693],"type":"Point"}
}