{
  "type": "Feature",
  "properties": {
    "iso:country":"BE",
    "sg:address":"L. Kriegelstraat 37",
    "sg:city":"Huldenberg",
    "sg:classifiers":[
        {
            "category":"Home & Garden",
            "subcategory":"Carpets & Floor Coverings",
            "type":"Retail Goods"
        }
    ],
    "sg:phone":"+32 16 47 21 95",
    "sg:postcode":"3040",
    "sg:province":"Vlaams-Brabant",
    "sg:tags":[
        "whol",
        "-",
        "grape",
        "grower"
    ],
    "wof:name":"Meyhi H",
    "wof:placetype":"venue"
},
  "geometry": {"coordinates":[4.598762989,50.796421051],"type":"Point"}
}