{
  "type": "Feature",
  "properties": {
    "addr:full":"Dreef 4 Scherpenheuvel-zichem Vlaams-Brabant 3270",
    "addr:housenumber":"4",
    "addr:postcode":"3270",
    "addr:street":"Dreef",
    "iso:country":"BE",
    "sg:address":"Dreef 4",
    "sg:city":"Scherpenheuvel-zichem",
    "sg:classifiers":[
        {
            "category":"Personal",
            "subcategory":"Beauty Salon",
            "type":"Services"
        }
    ],
    "sg:phone":"+32 13 77 39 45",
    "sg:postcode":"3270",
    "sg:province":"Vlaams-Brabant",
    "sg:tags":[
        "de",
        "coiffure"
    ],
    "wof:name":"N. Mattheus",
    "wof:placetype":"venue"
},
  "geometry": {"coordinates":[4.9466028214,50.9644241333],"type":"Point"}
}