{
  "type": "Feature",
  "properties": {
    "iso:country":"BE",
    "sg:address":"Holven 42",
    "sg:city":"Geel",
    "sg:classifiers":[
        {
            "category":"Real Estate",
            "subcategory":"Architect",
            "type":"Services"
        }
    ],
    "sg:phone":"+32 14 56 08 03",
    "sg:postcode":"2440",
    "sg:province":"Antwerpen",
    "wof:name":"Peeters T",
    "wof:placetype":"venue"
},
  "geometry": {"coordinates":[4.9852581024,51.1703186035],"type":"Point"}
}