{
  "type": "Feature",
  "properties": {
    "addr:full":"Place Des D\u00c9port\u00c9s 9 Li\u00c8ge Li\u00e8ge 4000",
    "addr:housenumber":"9",
    "addr:postcode":"4000",
    "addr:street":"Place Des De\u0301Porte\u0301S",
    "iso:country":"BE",
    "sg:address":"Place Des D\u00c9port\u00c9s 9",
    "sg:city":"Li\u00c8ge",
    "sg:orig_category":"Maisons de repos and r\u00e9sidences",
    "sg:phone":"+32 4 228 91 60",
    "sg:postcode":"4000",
    "sg:province":"Li\u00e8ge",
    "wof:name":"R\u00c9sidence Maghin",
    "wof:placetype":"venue"
},
  "geometry": {"coordinates":[5.5859889984,50.6484107971],"type":"Point"}
}