{
  "type": "Feature",
  "properties": {
    "addr:full":"O.l. Vrouwstraat 17 Neerpelt Limburg 3910",
    "addr:housenumber":"17",
    "addr:postcode":"3910",
    "addr:street":"O.L. Vrouwstraat",
    "iso:country":"BE",
    "sg:address":"O.l. Vrouwstraat 17",
    "sg:city":"Neerpelt",
    "sg:orig_category":"Metalen constructies Fab",
    "sg:phone":"+32 11 64 30 54",
    "sg:postcode":"3910",
    "sg:province":"Limburg",
    "wof:name":"Almoc",
    "wof:placetype":"venue"
},
  "geometry": {"coordinates":[5.434855938,51.2285919189],"type":"Point"}
}