{
  "type": "Feature",
  "properties": {
    "iso:country":"BE",
    "sg:address":"Rue Du Pont 8",
    "sg:city":"Andenne",
    "sg:orig_category":"Verplichte sociale verzekeringen",
    "sg:phone":"+32 85 84 24 65",
    "sg:postcode":"5300",
    "sg:province":"Namur",
    "wof:name":"Mutualit\u00c9 Chr\u00c9tienne",
    "wof:placetype":"venue"
},
  "geometry": {"coordinates":[5.0964798927,50.4916229248],"type":"Point"}
}