{
  "type": "Feature",
  "properties": {
    "addr:full":"Wilde Heide 87 Haacht Vlaams-Brabant 3150",
    "addr:housenumber":"87",
    "addr:postcode":"3150",
    "addr:street":"Wilde Heide",
    "iso:country":"BE",
    "sg:address":"Wilde Heide 87",
    "sg:city":"Haacht",
    "sg:classifiers":[
        {
            "category":"Professional",
            "subcategory":"Art Services",
            "type":"Services"
        }
    ],
    "sg:phone":"+32 16 60 72 89",
    "sg:postcode":"3150",
    "sg:province":"Vlaams-Brabant",
    "sg:tags":[
        "realization",
        "audio-visual"
    ],
    "wof:name":"Van Meerbeeck R",
    "wof:placetype":"venue"
},
  "geometry": {"coordinates":[4.6543889046,50.9820518494],"type":"Point"}
}