{
  "type": "Feature",
  "properties": {
    "addr:full":"Rue Pierre Du Diable 14b5 Namur Namur 5100",
    "addr:housenumber":"14b5",
    "addr:postcode":"5100",
    "addr:street":"Rue Pierre Du Diable",
    "iso:country":"BE",
    "sg:address":"Rue Pierre Du Diable 14b5",
    "sg:city":"Namur",
    "sg:classifiers":[
        {
            "category":"Cafe",
            "type":"Food & Drink"
        }
    ],
    "sg:phone":"+32 81 30 43 51",
    "sg:postcode":"5100",
    "sg:province":"Namur",
    "sg:tags":[
        "caf\u00e9s"
    ],
    "wof:name":"Odette Lecaillon",
    "wof:placetype":"venue"
},
  "geometry": {"coordinates":[4.8713750839,50.4566345215],"type":"Point"}
}