{
  "type": "Feature",
  "properties": {
    "addr:full":"Duisburgsesteenweg 61 Overijse Vlaams-Brabant 3090",
    "addr:housenumber":"61",
    "addr:postcode":"3090",
    "addr:street":"Duisburgsesteenweg",
    "iso:country":"BE",
    "sg:address":"Duisburgsesteenweg 61",
    "sg:city":"Overijse",
    "sg:orig_category":"Avocats and conseillers juridiques",
    "sg:phone":"+32 2 687 66 71",
    "sg:postcode":"3090",
    "sg:province":"Vlaams-Brabant",
    "wof:name":"P. Vanderosieren",
    "wof:placetype":"venue"
},
  "geometry": {"coordinates":[4.5402998924,50.789730072],"type":"Point"}
}