{
  "type": "Feature",
  "properties": {
    "addr:full":"Rue Grimard 301 Charleroi (montignies-sur-sambre) Hainaut 6061",
    "addr:housenumber":"301",
    "addr:postcode":"6061",
    "addr:street":"Rue Grimard",
    "iso:country":"BE",
    "sg:address":"Rue Grimard 301",
    "sg:city":"Charleroi (montignies-sur-sambre)",
    "sg:classifiers":[
        {
            "category":"Bars & Pubs",
            "type":"Food & Drink"
        }
    ],
    "sg:phone":"+32 71 31 26 12",
    "sg:postcode":"6061",
    "sg:province":"Hainaut",
    "wof:name":"Maison Du Peuple",
    "wof:placetype":"venue"
},
  "geometry": {"coordinates":[4.4690651894,50.4099082947],"type":"Point"}
}