{
  "type": "Feature",
  "properties": {
    "addr:full":"Noordlaan 54 Wetteren Oost-Vlaanderen 9230",
    "addr:housenumber":"54",
    "addr:postcode":"9230",
    "addr:street":"Noordlaan",
    "iso:country":"BE",
    "sg:address":"Noordlaan 54",
    "sg:city":"Wetteren",
    "sg:classifiers":[
        {
            "category":"Professional",
            "subcategory":"Accounting & Tax Preparation",
            "type":"Services"
        }
    ],
    "sg:phone":"+32 9 368 15 81",
    "sg:postcode":"9230",
    "sg:province":"Oost-Vlaanderen",
    "sg:tags":[
        "accountant"
    ],
    "wof:name":"Dani\u00cbl De Winter",
    "wof:placetype":"venue"
},
  "geometry": {"coordinates":[3.8702309132,51.0012054443],"type":"Point"}
}