{
  "type": "Feature",
  "properties": {
    "addr:full":"Grote Baan 119 Box 2 Hasselt (kuringen) Limburg 3511",
    "addr:housenumber":"119;2",
    "addr:postcode":"3511",
    "addr:street":"Grote Baan;Box",
    "iso:country":"BE",
    "sg:address":"Grote Baan 119 Box 2",
    "sg:city":"Hasselt (kuringen)",
    "sg:orig_category":"Fiduciairies",
    "sg:phone":"+32 11 25 69 92",
    "sg:postcode":"3511",
    "sg:province":"Limburg",
    "wof:name":"United & Joris Services Bvba",
    "wof:placetype":"venue"
},
  "geometry": {"coordinates":[5.300057888,50.9417495728],"type":"Point"}
}