{
  "type": "Feature",
  "properties": {
    "iso:country":"BE",
    "sg:address":"Lepelstraat 8",
    "sg:city":"Lommel",
    "sg:classifiers":[
        {
            "category":"Bakery",
            "type":"Food & Drink"
        }
    ],
    "sg:phone":"+32 11 54 45 46",
    "sg:postcode":"3920",
    "sg:province":"Limburg",
    "sg:tags":[
        "confectioner",
        "baker"
    ],
    "wof:name":"Rabijns",
    "wof:placetype":"venue"
},
  "geometry": {"coordinates":[5.3100399971,51.2311096191],"type":"Point"}
}