{
  "type": "Feature",
  "properties": {
    "iso:country":"BE",
    "sg:address":"Avenue De L'atlantique 128",
    "sg:city":"Sint-pieters-woluwe/woluwe-saint-pierre",
    "sg:orig_category":"Epiceries",
    "sg:phone":"+32 2 770 87 34",
    "sg:postcode":"1150",
    "sg:province":"Bruxelles-Capitale",
    "wof:name":"Maison Choisifin",
    "wof:placetype":"venue"
},
  "geometry": {"coordinates":[4.4186611176,50.82787323],"type":"Point"}
}