{
  "type": "Feature",
  "properties": {
    "addr:full":"Vinkstraat 21 Watermaal-bosvoorde/watermael-boitsfort Bruxelles-Capitale 1170",
    "addr:housenumber":"21",
    "addr:postcode":"1170",
    "addr:street":"Vinkstraat",
    "iso:country":"BE",
    "sg:address":"Vinkstraat 21",
    "sg:city":"Watermaal-bosvoorde/watermael-boitsfort",
    "sg:orig_category":"Fotografen and fotostudio's",
    "sg:phone":"+32 2 675 31 51",
    "sg:postcode":"1170",
    "sg:province":"Bruxelles-Capitale",
    "wof:name":"Fe. Dohet Alain",
    "wof:placetype":"venue"
},
  "geometry": {"coordinates":[4.4111289978,50.7978439331],"type":"Point"}
}