{
  "type": "Feature",
  "properties": {
    "addr:full":"Sint-martinusstraat 63 Westerlo Antwerpen 2260",
    "addr:housenumber":"63",
    "addr:postcode":"2260",
    "addr:street":"Sint-Martinusstraat",
    "iso:country":"BE",
    "sg:address":"Sint-martinusstraat 63",
    "sg:city":"Westerlo",
    "sg:classifiers":[
        {
            "category":"Health Services",
            "subcategory":"Doctor",
            "type":"Services"
        }
    ],
    "sg:phone":"+32 14 54 91 31",
    "sg:postcode":"2260",
    "sg:province":"Antwerpen",
    "sg:tags":[
        "medicinephysicians",
        "surgeon"
    ],
    "wof:name":"Lamberts Godelieve",
    "wof:placetype":"venue"
},
  "geometry": {"coordinates":[4.9150071144,51.0922546387],"type":"Point"}
}