{
  "type": "Feature",
  "properties": {
    "iso:country":"BE",
    "sg:address":"Avenue De La Couronne 506",
    "sg:city":"Elsene/ixelles",
    "sg:orig_category":"Entretien and r\u00e9parations de voitures. D\u00e9taillants en pi\u00e8ces and accessoires de voitures",
    "sg:phone":"+32 2 649 55 39",
    "sg:postcode":"1050",
    "sg:province":"Bruxelles-Capitale",
    "wof:name":"Speedy",
    "wof:placetype":"venue"
},
  "geometry": {"coordinates":[4.3916320801,50.8194503784],"type":"Point"}
}