{
  "type": "Feature",
  "properties": {
    "addr:full":"Rue De Rochefort 233-223 Beauraing Namur 5570",
    "addr:postcode":"233-223;5570",
    "addr:street":"Rue De Rochefort",
    "iso:country":"BE",
    "sg:address":"Rue De Rochefort 233-223",
    "sg:city":"Beauraing",
    "sg:classifiers":[
        {
            "category":"Manufacturing",
            "subcategory":"Textiles",
            "type":"Manufacturing & Wholesale Goods"
        }
    ],
    "sg:phone":"+32 82 71 14 44",
    "sg:postcode":"5570",
    "sg:province":"Namur",
    "sg:tags":[
        "refractory",
        "material"
    ],
    "wof:name":"Sokao R\u00e9fractaire",
    "wof:placetype":"venue"
},
  "geometry": {"coordinates":[4.979847908,50.1208229065],"type":"Point"}
}