{
  "type": "Feature",
  "properties": {
    "addr:full":"Lindenstraat 70 Vilvoorde Vlaams-Brabant 1800",
    "addr:housenumber":"70",
    "addr:postcode":"1800",
    "addr:street":"Lindenstraat",
    "iso:country":"BE",
    "sg:address":"Lindenstraat 70",
    "sg:city":"Vilvoorde",
    "sg:orig_category":"Verplichte sociale verzekeringen",
    "sg:phone":"+32 2 253 14 83",
    "sg:postcode":"1800",
    "sg:province":"Vlaams-Brabant",
    "wof:name":"Socialist. Mutualiteit",
    "wof:placetype":"venue"
},
  "geometry": {"coordinates":[4.4563121796,50.9277763367],"type":"Point"}
}