{
  "type": "Feature",
  "properties": {
    "iso:country":"BE",
    "sg:address":"Rue De La Campagne 2",
    "sg:city":"Huy",
    "sg:orig_category":"Herstellingen and onderhoud aan huis voor voertuigen",
    "sg:phone":"+32 85 25 20 04",
    "sg:postcode":"4500",
    "sg:province":"Li\u00e8ge",
    "wof:name":"Garage Du Mont Falise",
    "wof:placetype":"venue"
},
  "geometry": {"coordinates":[5.2598891258,50.5342979431],"type":"Point"}
}