{
  "type": "Feature",
  "properties": {
    "iso:country":"BE",
    "sg:address":"Ankerrui 26b18",
    "sg:city":"Antwerpen",
    "sg:orig_category":"Agences d'exp\u00e9dition",
    "sg:phone":"+32 3 226 01 05",
    "sg:postcode":"2000",
    "sg:province":"Antwerpen",
    "wof:name":"Railtrans",
    "wof:placetype":"venue"
},
  "geometry": {"coordinates":[4.4113888741,51.2267799377],"type":"Point"}
}