{
  "type": "Feature",
  "properties": {
    "iso:country":"BE",
    "sg:address":"Neundorf 25",
    "sg:city":"Sankt Vith (crombach)",
    "sg:classifiers":[
        {
            "category":"Retail",
            "subcategory":"Event Space",
            "type":"Services"
        }
    ],
    "sg:phone":"+32 80 22 13 52",
    "sg:postcode":"4784",
    "sg:province":"Li\u00e8ge",
    "sg:tags":[
        "rental",
        "-",
        "hall"
    ],
    "wof:name":"Vereinslokal Neundorf V.o.",
    "wof:placetype":"venue"
},
  "geometry": {"coordinates":[6.0675911903,50.2596511841],"type":"Point"}
}