{
  "type": "Feature",
  "properties": {
    "addr:full":"Avenue Van Volxem 400-402 Bruxelles (forest) Bruxelles-Capitale 1190",
    "addr:postcode":"400-402;1190",
    "addr:street":"Avenue Van Volxem",
    "iso:country":"BE",
    "sg:address":"Avenue Van Volxem 400-402",
    "sg:city":"Bruxelles (forest)",
    "sg:classifiers":[
        {
            "category":"Health Services",
            "subcategory":"Hospital",
            "type":"Services"
        }
    ],
    "sg:phone":"+32 2 344 17 17",
    "sg:postcode":"1190",
    "sg:province":"Bruxelles-Capitale",
    "sg:tags":[
        "ambulance"
    ],
    "wof:name":"M\u00e9dical Assistance Sa",
    "wof:placetype":"venue"
},
  "geometry": {"coordinates":[4.3270611763,50.8272476196],"type":"Point"}
}