{
  "type": "Feature",
  "properties": {
    "addr:full":"Stationsstraat 40 Ieper West-Vlaanderen 8900",
    "addr:housenumber":"40",
    "addr:postcode":"8900",
    "addr:street":"Stationsstraat",
    "iso:country":"BE",
    "sg:address":"Stationsstraat 40",
    "sg:city":"Ieper",
    "sg:classifiers":[
        {
            "category":"Fast Food",
            "type":"Food & Drink"
        }
    ],
    "sg:phone":"+32 57 36 55 03",
    "sg:postcode":"8900",
    "sg:province":"West-Vlaanderen",
    "sg:tags":[
        "fried",
        "stand",
        "potato"
    ],
    "wof:name":"Pink Panter",
    "wof:placetype":"venue"
},
  "geometry": {"coordinates":[2.879805088,50.8486366272],"type":"Point"}
}