{
  "type": "Feature",
  "properties": {
    "addr:full":"Grand'place 23 Huy Li\u00e8ge 4500",
    "addr:housenumber":"23",
    "addr:postcode":"4500",
    "addr:street":"Grand'Place",
    "iso:country":"BE",
    "sg:address":"Grand'place 23",
    "sg:city":"Huy",
    "sg:classifiers":[
        {
            "category":"Bars & Pubs",
            "type":"Food & Drink"
        }
    ],
    "sg:phone":"+32 85 23 63 81",
    "sg:postcode":"4500",
    "sg:province":"Li\u00e8ge",
    "wof:name":"Jazz Matazz",
    "wof:placetype":"venue"
},
  "geometry": {"coordinates":[5.2410359383,50.5180206299],"type":"Point"}
}