{
  "type": "Feature",
  "properties": {
    "addr:full":"Lijsterstraat 10 Ingelmunster West-Vlaanderen 8770",
    "addr:housenumber":"10",
    "addr:postcode":"8770",
    "addr:street":"Lijsterstraat",
    "iso:country":"BE",
    "sg:address":"Lijsterstraat 10",
    "sg:city":"Ingelmunster",
    "sg:classifiers":[
        {
            "category":"Building & Trades",
            "subcategory":"Electrical",
            "type":"Services"
        }
    ],
    "sg:phone":"+32 51 31 01 37",
    "sg:postcode":"8770",
    "sg:province":"West-Vlaanderen",
    "sg:tags":[
        "electric",
        "-",
        "housewiring",
        "contractor"
    ],
    "wof:name":"Debrouwere K",
    "wof:placetype":"venue"
},
  "geometry": {"coordinates":[3.2506439686,50.9106864929],"type":"Point"}
}