{
  "type": "Feature",
  "properties": {
    "iso:country":"BE",
    "sg:address":"Rue Van Eyck 44",
    "sg:city":"Elsene/ixelles",
    "sg:orig_category":"Dameskledingzaken",
    "sg:phone":"+32 2 649 84 14",
    "sg:postcode":"1050",
    "sg:province":"Bruxelles-Capitale",
    "wof:name":"Richard Diffusion",
    "wof:placetype":"venue"
},
  "geometry": {"coordinates":[4.368639946,50.8195877075],"type":"Point"}
}