{
  "type": "Feature",
  "properties": {
    "iso:country":"BE",
    "sg:address":"Baudeloostraat 48",
    "sg:city":"Tielt",
    "sg:orig_category":"Rundveehouders",
    "sg:phone":"+32 51 63 60 85",
    "sg:postcode":"8700",
    "sg:province":"West-Vlaanderen",
    "wof:name":"Hilaire Van Vynckt",
    "wof:placetype":"venue"
},
  "geometry": {"coordinates":[3.4318659306,50.9953804016],"type":"Point"}
}