{
  "type": "Feature",
  "properties": {
    "iso:country":"BE",
    "sg:address":"Donderveldstraat 14",
    "sg:city":"Herk-de-stad (schulen)",
    "sg:classifiers":[
        {
            "category":"Professional",
            "subcategory":"Art Services",
            "type":"Services"
        }
    ],
    "sg:phone":"+32 13 55 49 07",
    "sg:postcode":"3540",
    "sg:province":"Limburg",
    "sg:tags":[
        "interior",
        "designer"
    ],
    "wof:name":"Kwanten P",
    "wof:placetype":"venue"
},
  "geometry": {"coordinates":[5.1997079849,50.960067749],"type":"Point"}
}