{
  "type": "Feature",
  "properties": {
    "addr:full":"Hontseindestraat 45 Sint-laureins Oost-Vlaanderen 9981",
    "addr:housenumber":"45",
    "addr:postcode":"9981",
    "addr:street":"Hontseindestraat",
    "iso:country":"BE",
    "sg:address":"Hontseindestraat 45",
    "sg:city":"Sint-laureins",
    "sg:orig_category":"Producteurs de l\u00e9gumes",
    "sg:phone":"+32 9 379 81 46",
    "sg:postcode":"9981",
    "sg:province":"Oost-Vlaanderen",
    "wof:name":"Herlibo",
    "wof:placetype":"venue"
},
  "geometry": {"coordinates":[3.536534071,51.2775650024],"type":"Point"}
}