{
  "type": "Feature",
  "properties": {
    "addr:full":"Chauss\u00c9e De Soignies 26 Silly (grand) Hainaut 7830",
    "addr:housenumber":"26",
    "addr:postcode":"7830",
    "addr:street":"Chausse\u0301E De Soignies",
    "iso:country":"BE",
    "sg:address":"Chauss\u00c9e De Soignies 26",
    "sg:city":"Silly (grand)",
    "sg:classifiers":[
        {
            "category":"Personal",
            "subcategory":"Beauty Salon",
            "type":"Services"
        }
    ],
    "sg:phone":"+32 2 395 51 46",
    "sg:postcode":"7830",
    "sg:province":"Hainaut",
    "sg:tags":[
        "de",
        "coiffure"
    ],
    "wof:name":"Coiffure Christiane",
    "wof:placetype":"venue"
},
  "geometry": {"coordinates":[3.9024889469,50.6475601196],"type":"Point"}
}