{
  "type": "Feature",
  "properties": {
    "iso:country":"BE",
    "sg:address":"Hofstraat 4",
    "sg:city":"Ravels",
    "sg:orig_category":"Non-Classified Establishments",
    "sg:phone":"+32 14 65 26 31",
    "sg:postcode":"2380",
    "sg:province":"Antwerpen",
    "wof:name":"Bovera Bvba",
    "wof:placetype":"venue"
},
  "geometry": {"coordinates":[5.0300722122,51.3920593262],"type":"Point"}
}