{
  "type": "Feature",
  "properties": {
    "addr:full":"Brusselsesteenweg 52 Lebbeke Oost-Vlaanderen 9280",
    "addr:housenumber":"52",
    "addr:postcode":"9280",
    "addr:street":"Brusselsesteenweg",
    "iso:country":"BE",
    "sg:address":"Brusselsesteenweg 52",
    "sg:city":"Lebbeke",
    "sg:classifiers":[
        {
            "category":"Home & Garden",
            "subcategory":"Home Furnishings",
            "type":"Retail Goods"
        }
    ],
    "sg:phone":"+32 52 41 03 76",
    "sg:postcode":"9280",
    "sg:province":"Oost-Vlaanderen",
    "sg:tags":[
        "curtain",
        "-",
        "fixture"
    ],
    "wof:name":"Hiel A M",
    "wof:placetype":"venue"
},
  "geometry": {"coordinates":[4.1290721893,50.9990005493],"type":"Point"}
}