{
  "type": "Feature",
  "properties": {
    "addr:full":"Capucienenstraat 55 Ieper West-Vlaanderen 8900",
    "addr:housenumber":"55",
    "addr:postcode":"8900",
    "addr:street":"Capucienenstraat",
    "iso:country":"BE",
    "sg:address":"Capucienenstraat 55",
    "sg:city":"Ieper",
    "sg:orig_category":"Brood, gebak and snoepgoed Zuivelproducten",
    "sg:phone":"+32 57 20 51 58",
    "sg:postcode":"8900",
    "sg:province":"West-Vlaanderen",
    "wof:name":"Bakkerij Spruytte L & Zn",
    "wof:placetype":"venue"
},
  "geometry": {"coordinates":[2.8697071075,50.8436737061],"type":"Point"}
}