{
  "type": "Feature",
  "properties": {
    "addr:full":"Dorp 14 Ravels (poppel) Antwerpen 2382",
    "addr:housenumber":"14",
    "addr:postcode":"2382",
    "addr:street":"Dorp",
    "iso:country":"BE",
    "sg:address":"Dorp 14",
    "sg:city":"Ravels (poppel)",
    "sg:classifiers":[
        {
            "category":"Real Estate",
            "subcategory":"Real Estate Services",
            "type":"Services"
        }
    ],
    "sg:phone":"+32 14 65 98 11",
    "sg:postcode":"2382",
    "sg:province":"Antwerpen",
    "wof:name":"Povamij",
    "wof:placetype":"venue"
},
  "geometry": {"coordinates":[5.041768074,51.4469108582],"type":"Point"}
}