{
  "type": "Feature",
  "properties": {
    "addr:full":"Avenue Des Fran\u00c7ais 32 Lincent Li\u00e8ge 4287",
    "addr:housenumber":"32",
    "addr:postcode":"4287",
    "addr:street":"Avenue Des Franc\u0327Ais",
    "iso:country":"BE",
    "sg:address":"Avenue Des Fran\u00c7ais 32",
    "sg:city":"Lincent",
    "sg:orig_category":"Sportterreinen and installaties behalve sportcentra",
    "sg:phone":"+32 19 63 21 51",
    "sg:postcode":"4287",
    "sg:province":"Li\u00e8ge",
    "wof:name":"Ecurie De Pellaines",
    "wof:placetype":"venue"
},
  "geometry": {"coordinates":[5.0010318756,50.7176971436],"type":"Point"}
}