{
  "type": "Feature",
  "properties": {
    "addr:full":"Boekhout 10 Tielt-winge Vlaams-Brabant 3390",
    "addr:housenumber":"10",
    "addr:postcode":"3390",
    "addr:street":"Boekhout",
    "iso:country":"BE",
    "sg:address":"Boekhout 10",
    "sg:city":"Tielt-winge",
    "sg:classifiers":[
        {
            "category":"Cafe",
            "type":"Food & Drink"
        }
    ],
    "sg:phone":"+32 16 50 23 84",
    "sg:postcode":"3390",
    "sg:province":"Vlaams-Brabant",
    "sg:tags":[
        "caf\u00e9s"
    ],
    "wof:name":"Tieltse Hondenver.",
    "wof:placetype":"venue"
},
  "geometry": {"coordinates":[4.9013252258,50.9501647949],"type":"Point"}
}