{
  "type": "Feature",
  "properties": {
    "addr:full":"Fr\u00e8re-orbanstraat 99 Oostende West-Vlaanderen 8400",
    "addr:housenumber":"99",
    "addr:postcode":"8400",
    "addr:street":"Fre\u0300Re-Orbanstraat",
    "iso:country":"BE",
    "sg:address":"Fr\u00e8re-orbanstraat 99",
    "sg:city":"Oostende",
    "sg:classifiers":[
        {
            "category":"Building & Trades",
            "subcategory":"Construction",
            "type":"Services"
        }
    ],
    "sg:phone":"+32 59 80 30 36",
    "sg:postcode":"8400",
    "sg:province":"West-Vlaanderen",
    "sg:tags":[
        "duct",
        "underground",
        "ducting"
    ],
    "wof:name":"Abo-service",
    "wof:placetype":"venue"
},
  "geometry": {"coordinates":[2.9128899574,51.2189788818],"type":"Point"}
}