{
  "type": "Feature",
  "properties": {
    "iso:country":"BE",
    "sg:address":"Rue De Martelange 3",
    "sg:city":"Saint-hubert",
    "sg:orig_category":"Kampeerterreinen",
    "sg:phone":"+32 61 61 12 69",
    "sg:postcode":"6870",
    "sg:province":"Luxembourg",
    "wof:name":"Europacamp",
    "wof:placetype":"venue"
},
  "geometry": {"coordinates":[5.373360157,50.0256156921],"type":"Point"}
}