{
  "type": "Feature",
  "properties": {
    "addr:full":"Groot Eyssel 68ba Hoogstraten Antwerpen 2328",
    "addr:housenumber":"68ba",
    "addr:postcode":"2328",
    "addr:street":"Groot Eyssel",
    "iso:country":"BE",
    "sg:address":"Groot Eyssel 68ba",
    "sg:city":"Hoogstraten",
    "sg:orig_category":"Producteurs de fruits",
    "sg:phone":"+32 3 315 75 43",
    "sg:postcode":"2328",
    "sg:province":"Antwerpen",
    "wof:name":"Leemans Willy",
    "wof:placetype":"venue"
},
  "geometry": {"coordinates":[4.7675690651,51.4783287048],"type":"Point"}
}