{
  "type": "Feature",
  "properties": {
    "iso:country":"BE",
    "sg:address":"Chemin Des Bruy\u00c8res 2",
    "sg:city":"Hamoir",
    "sg:orig_category":"Belastingconsulenten Diverse bedrijfsbeheeradviesbureaus Diverse juridische dienstverlening",
    "sg:phone":"+32 86 38 81 88",
    "sg:postcode":"4180",
    "sg:province":"Li\u00e8ge",
    "wof:name":"Fiduciaire Ourthe Ambl\u00c8ve",
    "wof:placetype":"venue"
},
  "geometry": {"coordinates":[5.5402297974,50.4259490967],"type":"Point"}
}