{
  "type": "Feature",
  "properties": {
    "addr:full":"Rue De La Montagne 10 Lontzen Li\u00e8ge 4710",
    "addr:housenumber":"10",
    "addr:postcode":"4710",
    "addr:street":"Rue De La Montagne",
    "iso:country":"BE",
    "sg:address":"Rue De La Montagne 10",
    "sg:city":"Lontzen",
    "sg:orig_category":"Plomberie, chauffage and installations sanitaires",
    "sg:phone":"+32 87 65 61 70",
    "sg:postcode":"4710",
    "sg:province":"Li\u00e8ge",
    "wof:name":"P. Malicki",
    "wof:placetype":"venue"
},
  "geometry": {"coordinates":[6.0085000992,50.6827507019],"type":"Point"}
}