{
  "type": "Feature",
  "properties": {
    "iso:country":"BE",
    "sg:address":"Kapiteintjesstraat",
    "sg:city":"Aalst",
    "sg:orig_category":"Mat\u00e9riel de T\u00e9l\u00e9communication. Electrom\u00e9nager, t\u00e9l\u00e9visions and radios",
    "sg:phone":"+32 53 70 75 85",
    "sg:postcode":"9300",
    "sg:province":"Oost-Vlaanderen",
    "wof:name":"Eldi-tf",
    "wof:placetype":"venue"
},
  "geometry": {"coordinates":[4.0351629257,50.9350128174],"type":"Point"}
}