{
  "type": "Feature",
  "properties": {
    "addr:full":"Rue Karel Vande Woestijne 87 Bruxelles (anderlecht) Bruxelles-Capitale 1070",
    "addr:housenumber":"87",
    "addr:postcode":"1070",
    "addr:street":"Rue Karel Vande Woestijne",
    "iso:country":"BE",
    "sg:address":"Rue Karel Vande Woestijne 87",
    "sg:city":"Bruxelles (anderlecht)",
    "sg:classifiers":[
        {
            "category":"Health Services",
            "subcategory":"Health Practitioner",
            "type":"Services"
        }
    ],
    "sg:phone":"+32 2 520 47 07",
    "sg:postcode":"1070",
    "sg:province":"Bruxelles-Capitale",
    "sg:tags":[
        "physiotherapist"
    ],
    "wof:name":"Gretser E",
    "wof:placetype":"venue"
},
  "geometry": {"coordinates":[4.2914228439,50.8361053467],"type":"Point"}
}