{
  "type": "Feature",
  "properties": {
    "addr:full":"Avenue Des Ch\u00canes 48 Charleroi Hainaut 6001",
    "addr:housenumber":"48",
    "addr:postcode":"6001",
    "addr:street":"Avenue Des Che\u0302Nes;Hainaut",
    "iso:country":"BE",
    "sg:address":"Avenue Des Ch\u00canes 48",
    "sg:city":"Charleroi",
    "sg:orig_category":"Artiesten and kunstenaars",
    "sg:phone":"+32 71 36 23 68",
    "sg:postcode":"6001",
    "sg:province":"Hainaut",
    "wof:name":"A. Chevalier",
    "wof:placetype":"venue"
},
  "geometry": {"coordinates":[4.4562830925,50.3775901794],"type":"Point"}
}