{
  "type": "Feature",
  "properties": {
    "addr:full":"Souverainestr 64 Deinze Oost-Vlaanderen 9800",
    "addr:housenumber":"64",
    "addr:postcode":"9800",
    "addr:street":"Souverainestr",
    "iso:country":"BE",
    "sg:address":"Souverainestr 64",
    "sg:city":"Deinze",
    "sg:classifiers":[
        {
            "category":"Professional",
            "type":"Services"
        }
    ],
    "sg:phone":"+32 9 387 00 57",
    "sg:postcode":"9800",
    "sg:province":"Oost-Vlaanderen",
    "sg:tags":[
        "transport",
        "road"
    ],
    "wof:name":"Transport Van Renterghem Nv",
    "wof:placetype":"venue"
},
  "geometry": {"coordinates":[3.530174017,50.9863166809],"type":"Point"}
}