{
  "type": "Feature",
  "properties": {
    "addr:full":"Rue Georges Maroye 68 Fleurus (saint-amand) Hainaut 6221",
    "addr:housenumber":"68",
    "addr:postcode":"6221",
    "addr:street":"Rue Georges Maroye",
    "iso:country":"BE",
    "sg:address":"Rue Georges Maroye 68",
    "sg:city":"Fleurus (saint-amand)",
    "sg:classifiers":[
        {
            "category":"Food & Beverages",
            "subcategory":"Specialty",
            "type":"Retail Goods"
        }
    ],
    "sg:phone":"+32 71 81 39 76",
    "sg:postcode":"6221",
    "sg:province":"Hainaut",
    "sg:tags":[
        "health",
        "dietary",
        "-",
        "biological"
    ],
    "wof:name":"L'herbier 2000",
    "wof:placetype":"venue"
},
  "geometry": {"coordinates":[4.5451278687,50.5142593384],"type":"Point"}
}