{
  "type": "Feature",
  "properties": {
    "addr:full":"Brakelstraat 49 Zottegem Oost-Vlaanderen 9620",
    "addr:housenumber":"49",
    "addr:postcode":"9620",
    "addr:street":"Brakelstraat",
    "iso:country":"BE",
    "sg:address":"Brakelstraat 49",
    "sg:city":"Zottegem",
    "sg:orig_category":"Landmeters",
    "sg:phone":"+32 9 360 06 66",
    "sg:postcode":"9620",
    "sg:province":"Oost-Vlaanderen",
    "wof:name":"Marc Van Liefde",
    "wof:placetype":"venue"
},
  "geometry": {"coordinates":[3.8112111092,50.871181488],"type":"Point"}
}