{
  "type": "Feature",
  "properties": {
    "addr:full":"Gentsesteenweg 257 Zottegem Oost-Vlaanderen 9620",
    "addr:housenumber":"257",
    "addr:postcode":"9620",
    "addr:street":"Gentsesteenweg",
    "iso:country":"BE",
    "sg:address":"Gentsesteenweg 257",
    "sg:city":"Zottegem",
    "sg:orig_category":"Dancings and bo\u00eetes de nuit",
    "sg:phone":"+32 9 361 14 79",
    "sg:postcode":"9620",
    "sg:province":"Oost-Vlaanderen",
    "wof:name":"Atmozphere",
    "wof:placetype":"venue"
},
  "geometry": {"coordinates":[3.8112111092,50.871181488],"type":"Point"}
}