{
  "type": "Feature",
  "properties": {
    "iso:country":"BE",
    "sg:address":"Maastrichterstraat 1-30",
    "sg:city":"Hasselt",
    "sg:classifiers":[
        {
            "category":"Shopping",
            "subcategory":"Beauty & Cosmetics",
            "type":"Retail Goods"
        }
    ],
    "sg:phone":"+32 11 24 32 20",
    "sg:postcode":"3500",
    "sg:province":"Limburg",
    "sg:tags":[
        "-",
        "perfumery"
    ],
    "wof:name":"Stunt (de)",
    "wof:placetype":"venue"
},
  "geometry": {"coordinates":[5.3379402161,50.9291534424],"type":"Point"}
}