{
  "type": "Feature",
  "properties": {
    "addr:full":"Breemputstraat 150 Vilvoorde Vlaams-Brabant 1800",
    "addr:housenumber":"150",
    "addr:postcode":"1800",
    "addr:street":"Breemputstraat",
    "iso:country":"BE",
    "sg:address":"Breemputstraat 150",
    "sg:city":"Vilvoorde",
    "sg:orig_category":"M\u00e9decins and sp\u00e9cialistes",
    "sg:phone":"+32 2 251 95 35",
    "sg:postcode":"1800",
    "sg:province":"Vlaams-Brabant",
    "wof:name":"R. Deraemaecker",
    "wof:placetype":"venue"
},
  "geometry": {"coordinates":[4.4030919075,50.9215164185],"type":"Point"}
}