{
  "type": "Feature",
  "properties": {
    "addr:full":"Rue De Chi\u00e8vres 355 Saint-ghislain (neufmaison) Hainaut 7332",
    "addr:housenumber":"355",
    "addr:postcode":"7332",
    "addr:street":"Rue De Chie\u0300Vres",
    "iso:country":"BE",
    "sg:address":"Rue De Chi\u00e8vres 355",
    "sg:city":"Saint-ghislain (neufmaison)",
    "sg:classifiers":[
        {
            "category":"Real Estate",
            "subcategory":"Architect",
            "type":"Services"
        }
    ],
    "sg:phone":"+32 65 62 03 53",
    "sg:postcode":"7332",
    "sg:province":"Hainaut",
    "wof:name":"Robinet P",
    "wof:placetype":"venue"
},
  "geometry": {"coordinates":[3.786839962,50.5054969788],"type":"Point"}
}