{
  "type": "Feature",
  "properties": {
    "iso:country":"BE",
    "sg:address":"Mizerikstraat 32",
    "sg:city":"Diepenbeek",
    "sg:orig_category":"Fietsen",
    "sg:phone":"+32 11 32 45 13",
    "sg:postcode":"3590",
    "sg:province":"Limburg",
    "wof:name":"Geert Pipeleers",
    "wof:placetype":"venue"
},
  "geometry": {"coordinates":[5.4001507759,50.9354286194],"type":"Point"}
}