{
  "type": "Feature",
  "properties": {
    "iso:country":"BE",
    "sg:address":"Lepelstraat 13",
    "sg:city":"Laarne",
    "sg:classifiers":[
        {
            "category":"Food & Beverages",
            "subcategory":"Candy",
            "type":"Retail Goods"
        }
    ],
    "sg:phone":"+32 9 365 00 99",
    "sg:postcode":"9270",
    "sg:province":"Oost-Vlaanderen",
    "wof:name":"Katy",
    "wof:placetype":"venue"
},
  "geometry": {"coordinates":[3.8519759178,51.0302848816],"type":"Point"}
}