{
  "type": "Feature",
  "properties": {
    "addr:full":"Rue De Pont 47 Tournai Hainaut 7500",
    "addr:housenumber":"47",
    "addr:postcode":"7500",
    "addr:street":"Rue De Pont",
    "iso:country":"BE",
    "sg:address":"Rue De Pont 47",
    "sg:city":"Tournai",
    "sg:orig_category":"Kapsalons Schoonheidssalons",
    "sg:phone":"+32 69 22 52 78",
    "sg:postcode":"7500",
    "sg:province":"Hainaut",
    "wof:name":"Institut Camille Albane",
    "wof:placetype":"venue"
},
  "geometry": {"coordinates":[3.3948090076,50.6076774597],"type":"Point"}
}