{
  "type": "Feature",
  "properties": {
    "iso:country":"BE",
    "sg:address":"Graaf Jansdijk 372",
    "sg:city":"Knokke-heist",
    "sg:orig_category":"Plaatsen van vloer- and muurbekleding Schilders",
    "sg:phone":"+32 50 60 78 29",
    "sg:postcode":"8300",
    "sg:province":"West-Vlaanderen",
    "wof:name":"Robert Devos",
    "wof:placetype":"venue"
},
  "geometry": {"coordinates":[3.3224699497,51.3378944397],"type":"Point"}
}