{
  "type": "Feature",
  "properties": {
    "iso:country":"BE",
    "sg:address":"Edingsesteenweg 325",
    "sg:city":"Ninove",
    "sg:orig_category":"Equipement photographique. Studios photographiques",
    "sg:phone":"+32 54 33 10 50",
    "sg:postcode":"9400",
    "sg:province":"Oost-Vlaanderen",
    "wof:name":"Foto Goossens M.",
    "wof:placetype":"venue"
},
  "geometry": {"coordinates":[4.0263299942,50.8269996643],"type":"Point"}
}