{
  "type": "Feature",
  "properties": {
    "addr:full":"Drukkerijstraat 17 Zele Oost-Vlaanderen 9240",
    "addr:housenumber":"17",
    "addr:postcode":"9240",
    "addr:street":"Drukkerijstraat",
    "iso:country":"BE",
    "sg:address":"Drukkerijstraat 17",
    "sg:city":"Zele",
    "sg:orig_category":"Fotogravure and zetwerk Krantenuitgeverijen Secretariaatsdiensten Tijdschriftenuitgeverijen",
    "sg:phone":"+32 52 45 07 11",
    "sg:postcode":"9240",
    "sg:province":"Oost-Vlaanderen",
    "wof:name":"Electronic Pre-press",
    "wof:placetype":"venue"
},
  "geometry": {"coordinates":[4.049680233,51.0727806091],"type":"Point"}
}