{
  "type": "Feature",
  "properties": {
    "iso:country":"BE",
    "sg:address":"Keerbaan 27",
    "sg:city":"Wommelgem",
    "sg:orig_category":"Informaticaconsulenten Software ontwikkeling and ontwerp",
    "sg:phone":"+32 3 354 48 79",
    "sg:postcode":"2160",
    "sg:province":"Antwerpen",
    "wof:name":"Devosoft",
    "wof:placetype":"venue"
},
  "geometry": {"coordinates":[4.5322141647,51.208984375],"type":"Point"}
}