{
  "type": "Feature",
  "properties": {
    "addr:full":"Rue Du Rivage 58 Jodoigne (m\u00e9lin) Brabant Wallon 1370",
    "addr:housenumber":"58",
    "addr:postcode":"1370",
    "addr:street":"Rue Du Rivage;Wallon",
    "iso:country":"BE",
    "sg:address":"Rue Du Rivage 58",
    "sg:city":"Jodoigne (m\u00e9lin)",
    "sg:classifiers":[
        {
            "category":"Building & Trades",
            "subcategory":"Plumbing",
            "type":"Services"
        }
    ],
    "sg:phone":"+32 10 81 69 90",
    "sg:postcode":"1370",
    "sg:province":"Brabant Wallon",
    "sg:tags":[
        "contractor"
    ],
    "wof:name":"Evo Renove Bvba",
    "wof:placetype":"venue"
},
  "geometry": {"coordinates":[4.8379421234,50.740901947],"type":"Point"}
}