{
  "type": "Feature",
  "properties": {
    "addr:full":"Klein Veerle 104 Brecht Antwerpen 2960",
    "addr:housenumber":"104",
    "addr:postcode":"2960",
    "addr:street":"Klein Veerle",
    "iso:country":"BE",
    "sg:address":"Klein Veerle 104",
    "sg:city":"Brecht",
    "sg:orig_category":"M\u00e9decins and sp\u00e9cialistes",
    "sg:phone":"+32 3 313 87 00",
    "sg:postcode":"2960",
    "sg:province":"Antwerpen",
    "wof:name":"P. Beld\u00c9",
    "wof:placetype":"venue"
},
  "geometry": {"coordinates":[4.6660299301,51.3344802856],"type":"Point"}
}