{
  "type": "Feature",
  "properties": {
    "iso:country":"BE",
    "sg:address":"Rue De La Bruskaie 93",
    "sg:city":"Florennes",
    "sg:orig_category":"Verplichte sociale verzekeringen",
    "sg:phone":"+32 82 68 84 19",
    "sg:postcode":"5620",
    "sg:province":"Namur",
    "wof:name":"La Femada",
    "wof:placetype":"venue"
},
  "geometry": {"coordinates":[4.6906070709,50.2321434021],"type":"Point"}
}