{
  "type": "Feature",
  "properties": {
    "addr:full":"Portugezenstraat 1 Kruibeke (bazel) Oost-Vlaanderen 9150",
    "addr:housenumber":"1",
    "addr:postcode":"9150",
    "addr:street":"Portugezenstraat",
    "iso:country":"BE",
    "sg:address":"Portugezenstraat 1",
    "sg:city":"Kruibeke (bazel)",
    "sg:classifiers":[
        {
            "category":"Building & Trades",
            "subcategory":"Cleaning & Sanitation",
            "type":"Services"
        }
    ],
    "sg:phone":"+32 3 774 52 19",
    "sg:postcode":"9150",
    "sg:province":"Oost-Vlaanderen",
    "sg:tags":[
        "janitor"
    ],
    "wof:name":"Ypsilon Services Bvba",
    "wof:placetype":"venue"
},
  "geometry": {"coordinates":[4.2703390121,51.1455955505],"type":"Point"}
}