{
  "type": "Feature",
  "properties": {
    "iso:country":"BE",
    "sg:address":"Rue Du Roussart 124",
    "sg:city":"Waterloo",
    "sg:orig_category":"G\u00e9om\u00e8tres",
    "sg:phone":"+32 2 354 98 83",
    "sg:postcode":"1410",
    "sg:province":"Brabant Wallon",
    "wof:name":"Raymond Pierre",
    "wof:placetype":"venue"
},
  "geometry": {"coordinates":[4.4095082283,50.7022132874],"type":"Point"}
}