{
  "type": "Feature",
  "properties": {
    "addr:full":"Chauss\u00e9e De Ninove 654 Bruxelles (anderlecht) Bruxelles-Capitale 1070",
    "addr:housenumber":"654",
    "addr:postcode":"1070",
    "addr:street":"Chausse\u0301E De Ninove",
    "iso:country":"BE",
    "sg:address":"Chauss\u00e9e De Ninove 654",
    "sg:city":"Bruxelles (anderlecht)",
    "sg:classifiers":[
        {
            "category":"Professional",
            "subcategory":"Advertising",
            "type":"Services"
        }
    ],
    "sg:phone":"+32 2 521 10 05",
    "sg:postcode":"1070",
    "sg:province":"Bruxelles-Capitale",
    "sg:tags":[
        "item",
        "-",
        "business",
        "gift",
        "promotional"
    ],
    "wof:name":"Devico",
    "wof:placetype":"venue"
},
  "geometry": {"coordinates":[4.2997541428,50.8468399048],"type":"Point"}
}