{
  "type": "Feature",
  "properties": {
    "iso:country":"BE",
    "sg:address":"Chauss\u00c9e Brunehaut 95",
    "sg:city":"Beloeil",
    "sg:orig_category":"R\u00e9parations de chaussures and articles en cuir",
    "sg:phone":"+32 69 57 97 41",
    "sg:postcode":"7972",
    "sg:province":"Hainaut",
    "wof:name":"Jean Bachy",
    "wof:placetype":"venue"
},
  "geometry": {"coordinates":[3.690969944,50.542301178],"type":"Point"}
}