{
  "type": "Feature",
  "properties": {
    "iso:country":"BE",
    "sg:address":"Vanderkinderestraat 376",
    "sg:city":"Ukkel/uccle",
    "sg:orig_category":"Herstellingen and onderhoud van auto's Voertuigen",
    "sg:phone":"+32 2 344 44 03",
    "sg:postcode":"1180",
    "sg:province":"Bruxelles-Capitale",
    "wof:name":"Garage De L'avenue",
    "wof:placetype":"venue"
},
  "geometry": {"coordinates":[4.3573122025,50.8143692017],"type":"Point"}
}