{
  "type": "Feature",
  "properties": {
    "addr:full":"Rue De Praetere 36 Bruxelles (ixelles) Bruxelles-Capitale 1050",
    "addr:housenumber":"36",
    "addr:postcode":"1050",
    "addr:street":"Rue De Praetere",
    "iso:country":"BE",
    "sg:address":"Rue De Praetere 36",
    "sg:city":"Bruxelles (ixelles)",
    "sg:classifiers":[
        {
            "category":"Professional",
            "subcategory":"Management & Consulting",
            "type":"Services"
        }
    ],
    "sg:phone":"+32 2 644 34 97",
    "sg:postcode":"1050",
    "sg:province":"Bruxelles-Capitale",
    "sg:tags":[
        "consultant",
        "agency",
        "advertising"
    ],
    "wof:name":"Alsberge C",
    "wof:placetype":"venue"
},
  "geometry": {"coordinates":[4.3688488007,50.8163146973],"type":"Point"}
}