{
  "type": "Feature",
  "properties": {
    "iso:country":"BE",
    "sg:address":"Buitenlaan 11",
    "sg:city":"Genk",
    "sg:orig_category":"Artsen and specialisten",
    "sg:phone":"+32 89 35 15 76",
    "sg:postcode":"3600",
    "sg:province":"Limburg",
    "wof:name":"Germeaux Jacques",
    "wof:placetype":"venue"
},
  "geometry": {"coordinates":[5.4665222168,50.9745025635],"type":"Point"}
}