{
  "type": "Feature",
  "properties": {
    "addr:full":"Rollegemkerkstraat 56 Kortrijk West-Vlaanderen 8510",
    "addr:housenumber":"56",
    "addr:postcode":"8510",
    "addr:street":"Rollegemkerkstraat",
    "iso:country":"BE",
    "sg:address":"Rollegemkerkstraat 56",
    "sg:city":"Kortrijk",
    "sg:classifiers":[
        {
            "category":"Restaurant",
            "type":"Food & Drink"
        }
    ],
    "sg:phone":"+32 56 21 51 64",
    "sg:postcode":"8510",
    "sg:province":"West-Vlaanderen",
    "sg:tags":[
        "caf\u00e9s"
    ],
    "wof:name":"Elckerlyc",
    "wof:placetype":"venue"
},
  "geometry": {"coordinates":[3.2587759495,50.7677078247],"type":"Point"}
}