{
  "type": "Feature",
  "properties": {
    "iso:country":"BE",
    "sg:address":"Chauss\u00e9e De Tongres 289",
    "sg:city":"Li\u00e8ge 1 (rocourt)",
    "sg:classifiers":[
        {
            "category":"Shopping",
            "subcategory":"Hobbies, Toys, & Games",
            "type":"Retail Goods"
        }
    ],
    "sg:phone":"+32 4 239 02 39",
    "sg:postcode":"4000",
    "sg:province":"Li\u00e8ge",
    "sg:tags":[
        "computer",
        "video"
    ],
    "wof:name":"Broze",
    "wof:placetype":"venue"
},
  "geometry": {"coordinates":[5.5486969948,50.6714515686],"type":"Point"}
}