{
  "type": "Feature",
  "properties": {
    "addr:full":"Stationstraat 23 Wielsbeke West-Vlaanderen 8710",
    "addr:housenumber":"23",
    "addr:postcode":"8710",
    "addr:street":"Stationstraat;West-Vlaanderen",
    "iso:country":"BE",
    "sg:address":"Stationstraat 23",
    "sg:city":"Wielsbeke",
    "sg:orig_category":"Non-Classified Establishments",
    "sg:phone":"+32 56 66 26 35",
    "sg:postcode":"8710",
    "sg:province":"West-Vlaanderen",
    "wof:name":"Deva International Bvba",
    "wof:placetype":"venue"
},
  "geometry": {"coordinates":[3.3742399216,50.9044494629],"type":"Point"}
}