{
  "type": "Feature",
  "properties": {
    "iso:country":"BE",
    "sg:address":"Rue Du Ch\u00c2teau 19",
    "sg:city":"Beloeil",
    "sg:orig_category":"Pharmaciens",
    "sg:phone":"+32 69 68 95 46",
    "sg:postcode":"7970",
    "sg:province":"Hainaut",
    "wof:name":"Yvan Demel",
    "wof:placetype":"venue"
},
  "geometry": {"coordinates":[3.7336258888,50.5495643616],"type":"Point"}
}