{
  "type": "Feature",
  "properties": {
    "iso:country":"BE",
    "sg:address":"Mechelsesteenweg 118",
    "sg:city":"Vilvoorde",
    "sg:orig_category":"Brood, gebak and snoepgoed",
    "sg:phone":"+32 2 251 67 99",
    "sg:postcode":"1800",
    "sg:province":"Vlaams-Brabant",
    "wof:name":"Jamai",
    "wof:placetype":"venue"
},
  "geometry": {"coordinates":[4.4260082245,50.9334793091],"type":"Point"}
}