{
  "type": "Feature",
  "properties": {
    "addr:full":"Rue Auguste-hock 21 Li\u00e8ge 1 (li\u00e8ge 2) Li\u00e8ge 4020",
    "addr:housenumber":"21;1;2",
    "addr:postcode":"4020",
    "addr:street":"Rue Auguste-Hock",
    "iso:country":"BE",
    "sg:address":"Rue Auguste-hock 21",
    "sg:city":"Li\u00e8ge 1 (li\u00e8ge 2)",
    "sg:classifiers":[
        {
            "category":"Professional",
            "subcategory":"Testing Lab",
            "type":"Services"
        }
    ],
    "sg:phone":"+32 4 343 00 44",
    "sg:postcode":"4020",
    "sg:province":"Li\u00e8ge",
    "sg:tags":[
        "laboratory",
        "photographic",
        "film"
    ],
    "wof:name":"Ikone Sprl",
    "wof:placetype":"venue"
},
  "geometry": {"coordinates":[5.5808200836,50.6272239685],"type":"Point"}
}