{
  "type": "Feature",
  "properties": {
    "iso:country":"BE",
    "sg:address":"Stationsstraat 84",
    "sg:city":"Rotselaar",
    "sg:classifiers":[
        {
            "category":"Manufacturing",
            "subcategory":"Furniture",
            "type":"Manufacturing & Wholesale Goods"
        }
    ],
    "sg:phone":"+32 16 44 48 16",
    "sg:postcode":"3110",
    "sg:province":"Vlaams-Brabant",
    "sg:tags":[
        "juvenile",
        "-"
    ],
    "wof:name":"De Toren Bvba",
    "wof:placetype":"venue"
},
  "geometry": {"coordinates":[4.7214179039,50.946975708],"type":"Point"}
}