{
  "type": "Feature",
  "properties": {
    "addr:full":"Rue Emmanuel Jacquet 19 Charleroi Hainaut 6044",
    "addr:housenumber":"19",
    "addr:postcode":"6044",
    "addr:street":"Rue Emmanuel Jacquet;Hainaut",
    "iso:country":"BE",
    "sg:address":"Rue Emmanuel Jacquet 19",
    "sg:city":"Charleroi",
    "sg:orig_category":"Artsen and specialisten",
    "sg:phone":"+32 71 35 33 77",
    "sg:postcode":"6044",
    "sg:province":"Hainaut",
    "wof:name":"Simone Pets",
    "wof:placetype":"venue"
},
  "geometry": {"coordinates":[4.3968777657,50.437374115],"type":"Point"}
}