{
  "type": "Feature",
  "properties": {
    "iso:country":"BE",
    "sg:address":"Rue Fran\u00e7ois Dorz\u00e9e 33",
    "sg:city":"Boussu",
    "sg:classifiers":[
        {
            "category":"Health Services",
            "subcategory":"Health Practitioner",
            "type":"Services"
        }
    ],
    "sg:phone":"+32 476 79 06 57",
    "sg:postcode":"7300",
    "sg:province":"Hainaut",
    "sg:tags":[
        "physiotherapist"
    ],
    "wof:name":"Debackere Daniel",
    "wof:placetype":"venue"
},
  "geometry": {"coordinates":[3.7981829643,50.4338798523],"type":"Point"}
}