{
  "type": "Feature",
  "properties": {
    "addr:full":"Grand-rue 89 Chatelet Hainaut 6200",
    "addr:housenumber":"89",
    "addr:postcode":"6200",
    "addr:street":"Grand-Rue;Hainaut",
    "iso:country":"BE",
    "sg:address":"Grand-rue 89",
    "sg:city":"Chatelet",
    "sg:orig_category":"Cr\u00e9dit \u00e0 la consommation. Pr\u00eats hypoth\u00e9caires and cr\u00e9dits immobiliers",
    "sg:phone":"+32 71 38 04 26",
    "sg:postcode":"6200",
    "sg:province":"Hainaut",
    "wof:name":"Cr\u00c9d.soc.&pet.prop.r\u00c9unis",
    "wof:placetype":"venue"
},
  "geometry": {"coordinates":[4.5288381577,50.4015769958],"type":"Point"}
}