{
  "type": "Feature",
  "properties": {
    "iso:country":"BE",
    "sg:address":"Kapelstraat 7",
    "sg:city":"Geel",
    "sg:classifiers":[
        {
            "category":"Bus Stop",
            "subcategory":"None",
            "type":"Transportation"
        }
    ],
    "sg:phone":"+32 14 58 31 87",
    "sg:postcode":"2440",
    "sg:province":"Antwerpen",
    "sg:tags":[
        "electricity",
        "-",
        "high",
        "low",
        "cabin",
        "voltage"
    ],
    "wof:name":"Elektro Constructie Gys Nv",
    "wof:placetype":"venue"
},
  "geometry": {"coordinates":[4.9839301109,51.175983429],"type":"Point"}
}