{
  "type": "Feature",
  "properties": {
    "addr:full":"Chauss\u00c9e De Stockel 231b11 Sint-lambrechts-woluwe/woluwe-saint-lambert Bruxelles-Capitale 1200",
    "addr:housenumber":"231b11 sint-lambrechts-woluwe",
    "addr:postcode":"1200",
    "addr:street":"Chausse\u0301E De Stockel",
    "iso:country":"BE",
    "sg:address":"Chauss\u00c9e De Stockel 231b11",
    "sg:city":"Sint-lambrechts-woluwe/woluwe-saint-lambert",
    "sg:orig_category":"Agences immobili\u00e8res",
    "sg:phone":"+32 2 779 96 59",
    "sg:postcode":"1200",
    "sg:province":"Bruxelles-Capitale",
    "wof:name":"Immo B.r.",
    "wof:placetype":"venue"
},
  "geometry": {"coordinates":[4.4471879005,50.8412094116],"type":"Point"}
}