{
  "type": "Feature",
  "properties": {
    "addr:full":"Emile Verhaerenstraat 1bd Sint-amands Antwerpen 2890",
    "addr:housenumber":"1bd",
    "addr:postcode":"2890",
    "addr:street":"Emile Verhaerenstraat",
    "iso:country":"BE",
    "sg:address":"Emile Verhaerenstraat 1bd",
    "sg:city":"Sint-amands",
    "sg:orig_category":"Elektrische installaties voor woningen Huishoudapparaten, televisies and radio's",
    "sg:phone":"+32 52 33 22 60",
    "sg:postcode":"2890",
    "sg:province":"Antwerpen",
    "wof:name":"Brusselmans Elektro",
    "wof:placetype":"venue"
},
  "geometry": {"coordinates":[4.2012958527,51.0602111816],"type":"Point"}
}