{
  "type": "Feature",
  "properties": {
    "iso:country":"BE",
    "sg:address":"Rue Des Quatre Carr\u00e9s 6",
    "sg:city":"Chaumont-gistoux (dion-valmont)",
    "sg:classifiers":[
        {
            "category":"Manufacturing",
            "subcategory":"Chemicals & Compounds",
            "type":"Manufacturing & Wholesale Goods"
        }
    ],
    "sg:phone":"+32 10 68 06 12",
    "sg:postcode":"1325",
    "sg:province":"Brabant Wallon",
    "sg:tags":[
        "pharmaceutical",
        "product"
    ],
    "wof:name":"Dynamed",
    "wof:placetype":"venue"
},
  "geometry": {"coordinates":[4.6641030312,50.698928833],"type":"Point"}
}