{
  "type": "Feature",
  "properties": {
    "addr:full":"Deinzestraat 163 Oudenaarde Oost-Vlaanderen 9700",
    "addr:housenumber":"163",
    "addr:postcode":"9700",
    "addr:street":"Deinzestraat",
    "iso:country":"BE",
    "sg:address":"Deinzestraat 163",
    "sg:city":"Oudenaarde",
    "sg:classifiers":[
        {
            "category":"Autos & Motor Vehicles",
            "subcategory":"Fuel & Gas Station",
            "type":"Retail Goods"
        }
    ],
    "sg:phone":"+32 55 31 63 84",
    "sg:postcode":"9700",
    "sg:province":"Oost-Vlaanderen",
    "wof:name":"De Coninck W",
    "wof:placetype":"venue"
},
  "geometry": {"coordinates":[3.579668045,50.8600082397],"type":"Point"}
}