{
  "type": "Feature",
  "properties": {
    "addr:full":"Rue De L'ecole 35 Welkenraedt Li\u00e8ge 4840",
    "addr:housenumber":"35",
    "addr:postcode":"4840",
    "addr:street":"Rue De L'Ecole",
    "iso:country":"BE",
    "sg:address":"Rue De L'ecole 35",
    "sg:city":"Welkenraedt",
    "sg:orig_category":"Kapsalons",
    "sg:phone":"+32 87 88 08 53",
    "sg:postcode":"4840",
    "sg:province":"Li\u00e8ge",
    "wof:name":"Coiffure Cools",
    "wof:placetype":"venue"
},
  "geometry": {"coordinates":[5.9680399895,50.6617698669],"type":"Point"}
}