{
  "type": "Feature",
  "properties": {
    "iso:country":"BE",
    "sg:address":"Rue De La Forge 37",
    "sg:city":"Septon",
    "sg:classifiers":[
        {
            "category":"Exhibition Hall",
            "type":"Public Place"
        }
    ],
    "sg:phone":"+32 86 21 15 15",
    "sg:postcode":"6940",
    "sg:province":"Luxembourg",
    "sg:tags":[
        "steel"
    ],
    "wof:name":"Simon S.p.r.l.",
    "wof:placetype":"venue"
},
  "geometry": {"coordinates":[5.4301390648,50.3626098633],"type":"Point"}
}