{
  "type": "Feature",
  "properties": {
    "addr:full":"Dorp-oost 38 Lochristi Oost-Vlaanderen 9080",
    "addr:housenumber":"38",
    "addr:postcode":"9080",
    "addr:street":"Dorp-Oost",
    "iso:country":"BE",
    "sg:address":"Dorp-oost 38",
    "sg:city":"Lochristi",
    "sg:classifiers":[
        {
            "category":"Personal",
            "subcategory":"Beauty Salon",
            "type":"Services"
        }
    ],
    "sg:phone":"+32 9 355 16 28",
    "sg:postcode":"9080",
    "sg:province":"Oost-Vlaanderen",
    "sg:tags":[
        "lady",
        "-",
        "hairdressing"
    ],
    "wof:name":"Hairstudio Exclusiv",
    "wof:placetype":"venue"
},
  "geometry": {"coordinates":[3.8377099037,51.0973625183],"type":"Point"}
}