{
  "type": "Feature",
  "properties": {
    "addr:full":"Chauss\u00c9e De Waterloo 491 Elsene/ixelles Bruxelles-Capitale 1050",
    "addr:housenumber":"491",
    "addr:postcode":"1050",
    "addr:street":"Chausse\u0301E De Waterloo",
    "iso:country":"BE",
    "sg:address":"Chauss\u00c9e De Waterloo 491",
    "sg:city":"Elsene/ixelles",
    "sg:orig_category":"Cr\u00e8ches and garderies d'enfants",
    "sg:phone":"+32 2 345 46 33",
    "sg:postcode":"1050",
    "sg:province":"Bruxelles-Capitale",
    "wof:name":"Garderie Le Soleil",
    "wof:placetype":"venue"
},
  "geometry": {"coordinates":[4.3585300446,50.8203964233],"type":"Point"}
}