{
  "type": "Feature",
  "properties": {
    "addr:full":"Souverainestraat 60 Deinze Oost-Vlaanderen 9800",
    "addr:housenumber":"60",
    "addr:postcode":"9800",
    "addr:street":"Souverainestraat",
    "iso:country":"BE",
    "sg:address":"Souverainestraat 60",
    "sg:city":"Deinze",
    "sg:orig_category":"Meubles D\u00e9taillants, Am\u00e9nagement de B\u00e2timents et de Cuisines",
    "sg:phone":"+32 9 386 87 56",
    "sg:postcode":"9800",
    "sg:province":"Oost-Vlaanderen",
    "wof:name":"Meubelen Tacas",
    "wof:placetype":"venue"
},
  "geometry": {"coordinates":[3.530174017,50.9863166809],"type":"Point"}
}