{
  "type": "Feature",
  "properties": {
    "iso:country":"BE",
    "sg:address":"Rue Du Moh\u00c9ry 40",
    "sg:city":"Hannut",
    "sg:orig_category":"Apotheken",
    "sg:phone":"+32 19 69 91 45",
    "sg:postcode":"4280",
    "sg:province":"Li\u00e8ge",
    "wof:name":"Yvonne Vanderoost",
    "wof:placetype":"venue"
},
  "geometry": {"coordinates":[5.0688080788,50.6208229065],"type":"Point"}
}