{
  "type": "Feature",
  "properties": {
    "iso:country":"BE",
    "sg:address":"Rue Notaire Malengreaux 6",
    "sg:city":"Colfontaine",
    "sg:orig_category":"Pleisterwerk Woningbouw",
    "sg:phone":"+32 65 67 41 23",
    "sg:postcode":"7340",
    "sg:province":"Hainaut",
    "wof:name":"Patrick Lassoie",
    "wof:placetype":"venue"
},
  "geometry": {"coordinates":[3.8614759445,50.4197540283],"type":"Point"}
}