{
  "type": "Feature",
  "properties": {
    "addr:full":"Avenue Des M\u00c9l\u00c8zes 20 Neupre Li\u00e8ge 4121",
    "addr:housenumber":"20",
    "addr:postcode":"4121",
    "addr:street":"Avenue Des Me\u0301Le\u0300Zes",
    "iso:country":"BE",
    "sg:address":"Avenue Des M\u00c9l\u00c8zes 20",
    "sg:city":"Neupre",
    "sg:orig_category":"Traitements param\u00e9dicaux",
    "sg:phone":"+32 4 371 59 47",
    "sg:postcode":"4121",
    "sg:province":"Li\u00e8ge",
    "wof:name":"M. Dewandre Duez",
    "wof:placetype":"venue"
},
  "geometry": {"coordinates":[5.4744682312,50.5442848206],"type":"Point"}
}