{
  "type": "Feature",
  "properties": {
    "addr:full":"Boulevard Lambermont 176 Schaarbeek/schaerbeek Bruxelles-Capitale 1030",
    "addr:housenumber":"176",
    "addr:postcode":"1030",
    "addr:street":"Boulevard Lambermont",
    "iso:country":"BE",
    "sg:address":"Boulevard Lambermont 176",
    "sg:city":"Schaarbeek/schaerbeek",
    "sg:orig_category":"Avocats and conseillers juridiques",
    "sg:phone":"+32 2 215 97 88",
    "sg:postcode":"1030",
    "sg:province":"Bruxelles-Capitale",
    "wof:name":"E. Taveirne",
    "wof:placetype":"venue"
},
  "geometry": {"coordinates":[4.3822388649,50.8711624146],"type":"Point"}
}