{
  "type": "Feature",
  "properties": {
    "addr:full":"Rue Des Paquis 15 Meix-devant-virton Luxembourg 6769",
    "addr:housenumber":"15",
    "addr:postcode":"6769",
    "addr:street":"Rue Des Paquis",
    "iso:country":"BE",
    "sg:address":"Rue Des Paquis 15",
    "sg:city":"Meix-devant-virton",
    "sg:orig_category":"Enseignement maternel and primaire",
    "sg:phone":"+32 63 57 06 04",
    "sg:postcode":"6769",
    "sg:province":"Luxembourg",
    "wof:name":"Ecole Fondamentale Libre",
    "wof:placetype":"venue"
},
  "geometry": {"coordinates":[5.4952301979,49.5764884949],"type":"Point"}
}