{
  "type": "Feature",
  "properties": {
    "iso:country":"BE",
    "sg:address":"Vrijheid 74",
    "sg:city":"Arendonk",
    "sg:orig_category":"V\u00eatements pour b\u00e9b\u00e9s and enfants. Articles pour b\u00e9b\u00e9s",
    "sg:phone":"+32 14 67 07 86",
    "sg:postcode":"2370",
    "sg:province":"Antwerpen",
    "wof:name":"Huis Cloe",
    "wof:placetype":"venue"
},
  "geometry": {"coordinates":[5.0902271271,51.321308136],"type":"Point"}
}