{
  "type": "Feature",
  "properties": {
    "addr:full":"Jasmijnlaan 8 Sint-pieters-leeuw Vlaams-Brabant 1600",
    "addr:housenumber":"8",
    "addr:postcode":"1600",
    "addr:street":"Jasmijnlaan",
    "iso:country":"BE",
    "sg:address":"Jasmijnlaan 8",
    "sg:city":"Sint-pieters-leeuw",
    "sg:classifiers":[
        {
            "category":"Health Services",
            "subcategory":"Doctor",
            "type":"Services"
        }
    ],
    "sg:phone":"+32 2 377 97 53",
    "sg:postcode":"1600",
    "sg:province":"Vlaams-Brabant",
    "sg:tags":[
        "medicinephysicians",
        "surgeon"
    ],
    "wof:name":"Hendrickx A",
    "wof:placetype":"venue"
},
  "geometry": {"coordinates":[4.2715687752,50.7996139526],"type":"Point"}
}