{
  "type": "Feature",
  "properties": {
    "addr:full":"Halveweg 59 Box 1 Zonhoven Limburg 3520",
    "addr:housenumber":"59",
    "addr:postcode":"3520",
    "addr:street":"Halveweg;Box 1",
    "iso:country":"BE",
    "sg:address":"Halveweg 59 Box 1",
    "sg:city":"Zonhoven",
    "sg:classifiers":[
        {
            "category":"Professional",
            "subcategory":"Management & Consulting",
            "type":"Services"
        }
    ],
    "sg:phone":"+32 11 53 77 70",
    "sg:postcode":"3520",
    "sg:province":"Limburg",
    "sg:tags":[
        "consultant",
        "law"
    ],
    "wof:name":"Jacobs M",
    "wof:placetype":"venue"
},
  "geometry": {"coordinates":[5.3485498428,50.9895896912],"type":"Point"}
}