{
  "type": "Feature",
  "properties": {
    "iso:country":"BE",
    "sg:address":"Rue Taille Guerry 11",
    "sg:city":"Ohey",
    "sg:orig_category":"Woningbouw",
    "sg:phone":"+32 85 61 18 24",
    "sg:postcode":"5350",
    "sg:province":"Namur",
    "wof:name":"Gustave Herbiet",
    "wof:placetype":"venue"
},
  "geometry": {"coordinates":[5.1152248383,50.4488182068],"type":"Point"}
}