{
  "type": "Feature",
  "properties": {
    "iso:country":"BE",
    "sg:address":"Kemmelbergweg 40",
    "sg:city":"Heuvelland",
    "sg:classifiers":[
        {
            "category":"Banks & Credit Unions",
            "subcategory":"Bureau De Change",
            "type":"Services"
        }
    ],
    "sg:phone":"+32 57 44 40 69",
    "sg:postcode":"8950",
    "sg:province":"West-Vlaanderen",
    "sg:tags":[
        "restaurant",
        "organisation",
        "\u00c0",
        "domicile",
        "fast",
        "catering",
        "livraison",
        "f\u00cates",
        "restaurants"
    ],
    "wof:name":"De Alverman",
    "wof:placetype":"venue"
},
  "geometry": {"coordinates":[2.825979948,50.74634552],"type":"Point"}
}