{
  "type": "Feature",
  "properties": {
    "addr:full":"Jacques Eggermontstraat 39 Gent Oost-Vlaanderen 9050",
    "addr:housenumber":"39",
    "addr:postcode":"9050",
    "addr:street":"Eggermontstraat;Oost-Vlaanderen",
    "iso:country":"BE",
    "sg:address":"Jacques Eggermontstraat 39",
    "sg:city":"Gent",
    "sg:classifiers":[
        {
            "category":"Personal",
            "subcategory":"Beauty Salon",
            "type":"Services"
        }
    ],
    "sg:phone":"+32 9 232 13 59",
    "sg:postcode":"9050",
    "sg:province":"Oost-Vlaanderen",
    "sg:tags":[
        "de",
        "coiffure"
    ],
    "wof:name":"Studio M.",
    "wof:placetype":"venue"
},
  "geometry": {"coordinates":[3.7410058975,51.0371704102],"type":"Point"}
}