{
  "type": "Feature",
  "properties": {
    "iso:country":"BE",
    "sg:address":"Hoogpoort 12",
    "sg:city":"Wetteren",
    "sg:orig_category":"Meubelzaken, woning- and keukeninrichting",
    "sg:phone":"+32 9 369 16 55",
    "sg:postcode":"9230",
    "sg:province":"Oost-Vlaanderen",
    "wof:name":"Braeckman",
    "wof:placetype":"venue"
},
  "geometry": {"coordinates":[3.8626129627,50.9681510925],"type":"Point"}
}