{
  "type": "Feature",
  "properties": {
    "iso:country":"BE",
    "sg:address":"Rue Jean Wilmotte 17",
    "sg:city":"Aywaille",
    "sg:classifiers":[
        {
            "category":"Professional",
            "subcategory":"Art Services",
            "type":"Services"
        }
    ],
    "sg:phone":"+32 4 384 62 14",
    "sg:postcode":"4920",
    "sg:province":"Li\u00e8ge",
    "sg:tags":[
        "photography",
        "reporting",
        "-"
    ],
    "wof:name":"Riga M",
    "wof:placetype":"venue"
},
  "geometry": {"coordinates":[5.6761331558,50.4736022949],"type":"Point"}
}