{
  "type": "Feature",
  "properties": {
    "addr:full":"Steenweg 58 Denderleeuw Oost-Vlaanderen 9473",
    "addr:housenumber":"58",
    "addr:postcode":"9473",
    "addr:street":"Steenweg",
    "iso:country":"BE",
    "sg:address":"Steenweg 58",
    "sg:city":"Denderleeuw",
    "sg:orig_category":"Woningbouw",
    "sg:phone":"+32 53 68 04 49",
    "sg:postcode":"9473",
    "sg:province":"Oost-Vlaanderen",
    "wof:name":"Danny De Bolle",
    "wof:placetype":"venue"
},
  "geometry": {"coordinates":[4.0552902222,50.9055023193],"type":"Point"}
}