{
  "type": "Feature",
  "properties": {
    "iso:country":"BE",
    "sg:address":"Steenweg Op Brussel 340",
    "sg:city":"Overijse",
    "sg:orig_category":"Plomberie, chauffage and installations sanitaires",
    "sg:phone":"+32 2 689 22 92",
    "sg:postcode":"3090",
    "sg:province":"Vlaams-Brabant",
    "wof:name":"Turbowinds",
    "wof:placetype":"venue"
},
  "geometry": {"coordinates":[4.5077381134,50.7832832336],"type":"Point"}
}