{
  "type": "Feature",
  "properties": {
    "addr:full":"Doolweg 6 Borsbeek Antwerpen 2150",
    "addr:housenumber":"6",
    "addr:postcode":"2150",
    "addr:street":"Doolweg",
    "iso:country":"BE",
    "sg:address":"Doolweg 6",
    "sg:city":"Borsbeek",
    "sg:classifiers":[
        {
            "category":"Health Services",
            "subcategory":"Nursing And Care Facility",
            "type":"Services"
        }
    ],
    "sg:phone":"+32 3 366 50 90",
    "sg:postcode":"2150",
    "sg:province":"Antwerpen",
    "sg:tags":[
        "home",
        "rest"
    ],
    "wof:name":"Compostela Vzw",
    "wof:placetype":"venue"
},
  "geometry": {"coordinates":[4.4891748428,51.1924667358],"type":"Point"}
}