{
  "type": "Feature",
  "properties": {
    "addr:full":"Rue Du Prado 1a Sint-jans-molenbeek/molenbeek- Bruxelles-Capitale 1080",
    "addr:housenumber":"1a",
    "addr:postcode":"1080",
    "addr:street":"Rue Du Prado;Molenbeek",
    "iso:country":"BE",
    "sg:address":"Rue Du Prado 1a",
    "sg:city":"Sint-jans-molenbeek/molenbeek-",
    "sg:orig_category":"Mat\u00e9riel de T\u00e9l\u00e9communication",
    "sg:phone":"+32 2 411 98 38",
    "sg:postcode":"1080",
    "sg:province":"Bruxelles-Capitale",
    "wof:name":"J.r.a.",
    "wof:placetype":"venue"
},
  "geometry": {"coordinates":[4.3375120163,50.8536834717],"type":"Point"}
}