{
  "type": "Feature",
  "properties": {
    "iso:country":"BE",
    "sg:address":"Voorstraat 95",
    "sg:city":"Kaprijke",
    "sg:orig_category":"Epiceries",
    "sg:phone":"+32 9 373 42 72",
    "sg:postcode":"9970",
    "sg:province":"Oost-Vlaanderen",
    "wof:name":"Cado Supermarkt",
    "wof:placetype":"venue"
},
  "geometry": {"coordinates":[3.6087810993,51.2183647156],"type":"Point"}
}