{
  "type": "Feature",
  "properties": {
    "addr:full":"Liverpoolstraat 3 Sint-jans-molenbeek/molenbeek-saint-jean Bruxelles-Capitale 1080",
    "addr:housenumber":"3",
    "addr:postcode":"1080",
    "addr:street":"Liverpoolstraat",
    "iso:country":"BE",
    "sg:address":"Liverpoolstraat 3",
    "sg:city":"Sint-jans-molenbeek/molenbeek-saint-jean",
    "sg:classifiers":[
        {
            "category":"Food & Beverages",
            "subcategory":"Fruits & Vegetables",
            "type":"Retail Goods"
        }
    ],
    "sg:phone":"+32 2 522 87 01",
    "sg:postcode":"1080",
    "sg:province":"Bruxelles-Capitale",
    "sg:tags":[
        "groenten"
    ],
    "wof:name":"Mohamed Moussaoui",
    "wof:placetype":"venue"
},
  "geometry": {"coordinates":[4.3298330307,50.8467826843],"type":"Point"}
}