{
  "type": "Feature",
  "properties": {
    "addr:full":"Turnhoutsebaan 261 Wijnegem Antwerpen 2110",
    "addr:housenumber":"261",
    "addr:postcode":"2110",
    "addr:street":"Turnhoutsebaan",
    "iso:country":"BE",
    "sg:address":"Turnhoutsebaan 261",
    "sg:city":"Wijnegem",
    "sg:classifiers":[
        {
            "category":"Professional",
            "subcategory":"Testing Lab",
            "type":"Services"
        }
    ],
    "sg:phone":"+32 3 353 82 16",
    "sg:postcode":"2110",
    "sg:province":"Antwerpen",
    "sg:tags":[
        "chemist"
    ],
    "wof:name":"De Vlier",
    "wof:placetype":"venue"
},
  "geometry": {"coordinates":[4.5170989037,51.2265777588],"type":"Point"}
}