{
  "type": "Feature",
  "properties": {
    "iso:country":"BE",
    "sg:address":"Zeven Bunderlaan 262b3",
    "sg:city":"Vorst/forest",
    "sg:orig_category":"Woningbouw",
    "sg:phone":"+32 2 347 24 81",
    "sg:postcode":"1190",
    "sg:province":"Bruxelles-Capitale",
    "wof:name":"Orod",
    "wof:placetype":"venue"
},
  "geometry": {"coordinates":[4.3315238953,50.8085021973],"type":"Point"}
}