{
  "type": "Feature",
  "properties": {
    "iso:country":"BE",
    "sg:address":"Emiel Clauslaan 128",
    "sg:city":"Deinze (astene)",
    "sg:classifiers":[
        {
            "category":"Professional",
            "subcategory":"Lawyer & Legal Services",
            "type":"Services"
        }
    ],
    "sg:phone":"+32 9 281 00 40",
    "sg:postcode":"9800",
    "sg:province":"Oost-Vlaanderen",
    "wof:name":"Devooght Peter",
    "wof:placetype":"venue"
},
  "geometry": {"coordinates":[3.5279901028,50.9846496582],"type":"Point"}
}