{
  "type": "Feature",
  "properties": {
    "addr:full":"Nieuwstraat 19 Knesselare Oost-Vlaanderen 9910",
    "addr:housenumber":"19",
    "addr:postcode":"9910",
    "addr:street":"Nieuwstraat;Oost-Vlaanderen",
    "iso:country":"BE",
    "sg:address":"Nieuwstraat 19",
    "sg:city":"Knesselare",
    "sg:orig_category":"Artsen and specialisten",
    "sg:phone":"+32 9 374 12 27",
    "sg:postcode":"9910",
    "sg:province":"Oost-Vlaanderen",
    "wof:name":"Labo Rathe Paul",
    "wof:placetype":"venue"
},
  "geometry": {"coordinates":[3.4174180031,51.1437072754],"type":"Point"}
}