{
  "type": "Feature",
  "properties": {
    "addr:full":"Avenue D'aix-la-chapelle 60 Li\u00c8ge Li\u00e8ge 4020",
    "addr:housenumber":"60",
    "addr:postcode":"4020",
    "addr:street":"Avenue D'Aix-La-Chapelle",
    "iso:country":"BE",
    "sg:address":"Avenue D'aix-la-chapelle 60",
    "sg:city":"Li\u00c8ge",
    "sg:orig_category":"Maisons de repos and r\u00e9sidences",
    "sg:phone":"+32 4 367 46 24",
    "sg:postcode":"4020",
    "sg:province":"Li\u00e8ge",
    "wof:name":"La Clairi\u00c8re De Fayenbois",
    "wof:placetype":"venue"
},
  "geometry": {"coordinates":[5.6240730286,50.6354179382],"type":"Point"}
}