{
  "type": "Feature",
  "properties": {
    "addr:full":"Gooikeveldstraat 34 Gooik Vlaams-Brabant 1755",
    "addr:housenumber":"34",
    "addr:postcode":"1755",
    "addr:street":"Gooikeveldstraat",
    "iso:country":"BE",
    "sg:address":"Gooikeveldstraat 34",
    "sg:city":"Gooik",
    "sg:classifiers":[
        {
            "category":"Personal",
            "subcategory":"Beauty Salon",
            "type":"Services"
        }
    ],
    "sg:phone":"+32 2 532 51 27",
    "sg:postcode":"1755",
    "sg:province":"Vlaams-Brabant",
    "sg:tags":[
        "de",
        "coiffure"
    ],
    "wof:name":"Rudy Van Hassel",
    "wof:placetype":"venue"
},
  "geometry": {"coordinates":[4.1180739403,50.7925758362],"type":"Point"}
}