{
  "type": "Feature",
  "properties": {
    "addr:full":"Charles De Kerchovelaan 16 Gent Oost-Vlaanderen 9000",
    "addr:housenumber":"16",
    "addr:postcode":"9000",
    "addr:street":"Charles De Kerchovelaan;Oost-Vlaanderen",
    "iso:country":"BE",
    "sg:address":"Charles De Kerchovelaan 16",
    "sg:city":"Gent",
    "sg:orig_category":"Deurwaarders",
    "sg:phone":"+32 9 221 45 42",
    "sg:postcode":"9000",
    "sg:province":"Oost-Vlaanderen",
    "wof:name":"Guy Geldof",
    "wof:placetype":"venue"
},
  "geometry": {"coordinates":[3.7196559906,51.0413665771],"type":"Point"}
}