{
  "type": "Feature",
  "properties": {
    "iso:country":"BE",
    "sg:address":"Breucq 14",
    "sg:city":"Ronse/renaix",
    "sg:orig_category":"Entretien and r\u00e9parations de voitures",
    "sg:phone":"+32 55 21 90 65",
    "sg:postcode":"9600",
    "sg:province":"Oost-Vlaanderen",
    "wof:name":"Dirk Declercq",
    "wof:placetype":"venue"
},
  "geometry": {"coordinates":[3.6633059978,50.756690979],"type":"Point"}
}