{
  "type": "Feature",
  "properties": {
    "addr:full":"Boulevard Du Souverain 144 Oudergem/auderghem Bruxelles-Capitale 1160",
    "addr:housenumber":"144",
    "addr:postcode":"1160",
    "addr:street":"Boulevard Du Souverain;/",
    "iso:country":"BE",
    "sg:address":"Boulevard Du Souverain 144",
    "sg:city":"Oudergem/auderghem",
    "sg:orig_category":"M\u00e9decins and sp\u00e9cialistes",
    "sg:phone":"+32 2 675 12 47",
    "sg:postcode":"1160",
    "sg:province":"Bruxelles-Capitale",
    "wof:name":"Maurice Anckaert",
    "wof:placetype":"venue"
},
  "geometry": {"coordinates":[4.4285049438,50.8190536499],"type":"Point"}
}