{
  "type": "Feature",
  "properties": {
    "addr:full":"Rue Debast 42 Quievrain Hainaut 7380",
    "addr:housenumber":"42",
    "addr:postcode":"7380",
    "addr:street":"Rue Debast;Hainaut",
    "iso:country":"BE",
    "sg:address":"Rue Debast 42",
    "sg:city":"Quievrain",
    "sg:orig_category":"M\u00e9decins and sp\u00e9cialistes",
    "sg:phone":"+32 65 45 70 57",
    "sg:postcode":"7380",
    "sg:province":"Hainaut",
    "wof:name":"M. Hallez",
    "wof:placetype":"venue"
},
  "geometry": {"coordinates":[3.6859629154,50.4071083069],"type":"Point"}
}