{
  "type": "Feature",
  "properties": {
    "addr:full":"Tervuursesteenweg 190b33 Leuven Vlaams-Brabant 3001",
    "addr:housenumber":"190b33",
    "addr:postcode":"3001",
    "addr:street":"Tervuursesteenweg",
    "iso:country":"BE",
    "sg:address":"Tervuursesteenweg 190b33",
    "sg:city":"Leuven",
    "sg:orig_category":"Pain, p\u00e2tisseries and confiseries",
    "sg:phone":"+32 16 22 14 57",
    "sg:postcode":"3001",
    "sg:province":"Vlaams-Brabant",
    "wof:name":"Alexander Van Bever",
    "wof:placetype":"venue"
},
  "geometry": {"coordinates":[4.6720070839,50.8744354248],"type":"Point"}
}