{
  "type": "Feature",
  "properties": {
    "iso:country":"BE",
    "sg:address":"Rue De Rabais 26",
    "sg:city":"Virton",
    "sg:orig_category":"Installation \u00e9lectrique r\u00e9sidentielle",
    "sg:phone":"+32 63 57 68 31",
    "sg:postcode":"6760",
    "sg:province":"Luxembourg",
    "wof:name":"Thierry Vaillant",
    "wof:placetype":"venue"
},
  "geometry": {"coordinates":[5.5628709793,49.5805244446],"type":"Point"}
}