{
  "type": "Feature",
  "properties": {
    "addr:full":"Karel Nerinckxhof 6 Kortenberg Vlaams-Brabant 3078",
    "addr:housenumber":"6",
    "addr:postcode":"3078",
    "addr:street":"Karel Nerinckxhof;Vlaams-Brabant",
    "iso:country":"BE",
    "sg:address":"Karel Nerinckxhof 6",
    "sg:city":"Kortenberg",
    "sg:orig_category":"Traitements param\u00e9dicaux",
    "sg:phone":"+32 2 757 14 04",
    "sg:postcode":"3078",
    "sg:province":"Vlaams-Brabant",
    "wof:name":"A. Heirman",
    "wof:placetype":"venue"
},
  "geometry": {"coordinates":[4.5912909508,50.879737854],"type":"Point"}
}