{
  "type": "Feature",
  "properties": {
    "iso:country":"BE",
    "sg:address":"Wolstraat 43",
    "sg:city":"Antwerpen",
    "sg:classifiers":[
        {
            "category":"Restaurant",
            "type":"Food & Drink"
        }
    ],
    "sg:phone":"+32 3 226 47 49",
    "sg:postcode":"2000",
    "sg:province":"Antwerpen",
    "wof:name":"Via Via",
    "wof:placetype":"venue"
},
  "geometry": {"coordinates":[4.4043149948,51.221572876],"type":"Point"}
}