{
  "type": "Feature",
  "properties": {
    "iso:country":"BE",
    "sg:address":"Chemin De Sauci 4",
    "sg:city":"Bouillon (vivy)",
    "sg:classifiers":[
        {
            "category":"Travel",
            "subcategory":"Resort",
            "type":"Entertainment"
        }
    ],
    "sg:phone":"+32 61 46 74 71",
    "sg:postcode":"6833",
    "sg:province":"Luxembourg",
    "sg:tags":[
        "farm",
        "house",
        "holiday",
        "guest"
    ],
    "wof:name":"Bauduin J",
    "wof:placetype":"venue"
},
  "geometry": {"coordinates":[5.0365228653,49.865940094],"type":"Point"}
}