{
  "type": "Feature",
  "properties": {
    "addr:full":"Valkenburgstraat 25 Antwerpen Antwerpen 2018",
    "addr:housenumber":"25",
    "addr:postcode":"2018",
    "addr:street":"Valkenburgstraat",
    "iso:country":"BE",
    "sg:address":"Valkenburgstraat 25",
    "sg:city":"Antwerpen",
    "sg:orig_category":"Artiesten and kunstenaars",
    "sg:phone":"+32 3 238 86 94",
    "sg:postcode":"2018",
    "sg:province":"Antwerpen",
    "wof:name":"Tomballe",
    "wof:placetype":"venue"
},
  "geometry": {"coordinates":[4.4092020988,51.2022323608],"type":"Point"}
}