{
  "type": "Feature",
  "properties": {
    "addr:full":"Dreef 4 Ternat Vlaams-Brabant 1740",
    "addr:housenumber":"4",
    "addr:postcode":"1740",
    "addr:street":"Dreef",
    "iso:country":"BE",
    "sg:address":"Dreef 4",
    "sg:city":"Ternat",
    "sg:classifiers":[
        {
            "category":"Professional",
            "type":"Services"
        }
    ],
    "sg:phone":"+32 2 582 72 72",
    "sg:postcode":"1740",
    "sg:province":"Vlaams-Brabant",
    "sg:tags":[
        "surveyor",
        "-",
        "valuer"
    ],
    "wof:name":"Expertisebureau Ir Germeau",
    "wof:placetype":"venue"
},
  "geometry": {"coordinates":[4.1754059792,50.8715553284],"type":"Point"}
}