{
  "type": "Feature",
  "properties": {
    "addr:full":"Rue No\u00cbl 3 Charleroi Hainaut 6060",
    "addr:housenumber":"3",
    "addr:postcode":"6060",
    "addr:street":"Rue Noe\u0308L;Hainaut",
    "iso:country":"BE",
    "sg:address":"Rue No\u00cbl 3",
    "sg:city":"Charleroi",
    "sg:orig_category":"Traitements param\u00e9dicaux",
    "sg:phone":"+32 71 41 01 48",
    "sg:postcode":"6060",
    "sg:province":"Hainaut",
    "wof:name":"Gisadi",
    "wof:placetype":"venue"
},
  "geometry": {"coordinates":[4.4880981445,50.4251937866],"type":"Point"}
}