{
  "type": "Feature",
  "properties": {
    "addr:full":"Rue De Boussu 7 Walcourt Namur 5650",
    "addr:housenumber":"7",
    "addr:postcode":"5650",
    "addr:street":"Rue De Boussu",
    "iso:country":"BE",
    "sg:address":"Rue De Boussu 7",
    "sg:city":"Walcourt",
    "sg:orig_category":"Installatie van houten of kunststof schrijnwerk",
    "sg:phone":"+32 71 63 31 77",
    "sg:postcode":"5650",
    "sg:province":"Namur",
    "wof:name":"Jean-claude Mouvet",
    "wof:placetype":"venue"
},
  "geometry": {"coordinates":[4.4313349724,50.2514762878],"type":"Point"}
}