{
  "type": "Feature",
  "properties": {
    "addr:full":"Lange Noordstraat 38 Antwerpen Antwerpen 2000",
    "addr:housenumber":"38",
    "addr:postcode":"2000",
    "addr:street":"Lange Noordstraat",
    "iso:country":"BE",
    "sg:address":"Lange Noordstraat 38",
    "sg:city":"Antwerpen",
    "sg:classifiers":[
        {
            "category":"Real Estate",
            "subcategory":"Architect",
            "type":"Services"
        }
    ],
    "sg:phone":"+32 3 234 95 35",
    "sg:postcode":"2000",
    "sg:province":"Antwerpen",
    "wof:name":"Pannemans K",
    "wof:placetype":"venue"
},
  "geometry": {"coordinates":[4.4071211815,51.2244224548],"type":"Point"}
}