{
  "type": "Feature",
  "properties": {
    "addr:full":"Rue Jos\u00e9phine Rauscent 53 Wavre (limal) Brabant Wallon 1300",
    "addr:housenumber":"53",
    "addr:postcode":"1300",
    "addr:street":"Rue Jose\u0301Phine Rauscent;Wallon",
    "iso:country":"BE",
    "sg:address":"Rue Jos\u00e9phine Rauscent 53",
    "sg:city":"Wavre (limal)",
    "sg:classifiers":[
        {
            "category":"Building & Trades",
            "subcategory":"Construction",
            "type":"Services"
        }
    ],
    "sg:phone":"+32 495 63 16 68",
    "sg:postcode":"1300",
    "sg:province":"Brabant Wallon",
    "sg:tags":[
        "stucco",
        "contractor"
    ],
    "wof:name":"Micbat Sprlu",
    "wof:placetype":"venue"
},
  "geometry": {"coordinates":[4.6116552353,50.7134132385],"type":"Point"}
}