{
  "type": "Feature",
  "properties": {
    "iso:country":"BE",
    "sg:address":"Lippenslaan 94",
    "sg:city":"Knokke-heist",
    "sg:orig_category":"Textiel",
    "sg:phone":"+32 50 62 35 63",
    "sg:postcode":"8300",
    "sg:province":"West-Vlaanderen",
    "wof:name":"Huis Papillon",
    "wof:placetype":"venue"
},
  "geometry": {"coordinates":[3.2882649899,51.3443603516],"type":"Point"}
}