{
  "type": "Feature",
  "properties": {
    "iso:country":"BE",
    "sg:address":"Rue Du Monast\u00e8re 26",
    "sg:city":"Seraing",
    "sg:classifiers":[
        {
            "category":"Health Services",
            "subcategory":"Health Practitioner",
            "type":"Services"
        }
    ],
    "sg:phone":"+32 4 337 80 64",
    "sg:postcode":"4100",
    "sg:province":"Li\u00e8ge",
    "sg:tags":[
        "physiotherapist"
    ],
    "wof:name":"Mawet Annie",
    "wof:placetype":"venue"
},
  "geometry": {"coordinates":[5.4896597862,50.5943412781],"type":"Point"}
}