{
  "type": "Feature",
  "properties": {
    "addr:full":"Leuvensesteenweg 559 Kortenberg Vlaams-Brabant 3070",
    "addr:housenumber":"559",
    "addr:postcode":"3070",
    "addr:street":"Leuvensesteenweg;Vlaams-Brabant",
    "iso:country":"BE",
    "sg:address":"Leuvensesteenweg 559",
    "sg:city":"Kortenberg",
    "sg:orig_category":"Eclairage et \u00e9quipements du foyer. Jardinage. Meubles D\u00e9taillants, Am\u00e9nagement de B\u00e2timents et de Cu",
    "sg:phone":"+32 2 759 63 96",
    "sg:postcode":"3070",
    "sg:province":"Vlaams-Brabant",
    "wof:name":"Huis Etcetera",
    "wof:placetype":"venue"
},
  "geometry": {"coordinates":[4.5568108559,50.8902893066],"type":"Point"}
}