{
  "type": "Feature",
  "properties": {
    "iso:country":"BE",
    "sg:address":"Dambrugstraat 7",
    "sg:city":"Beveren (melsele)",
    "sg:classifiers":[
        {
            "category":"Real Estate",
            "subcategory":"Real Estate Services",
            "type":"Services"
        }
    ],
    "sg:phone":"+32 3 775 78 79",
    "sg:postcode":"9120",
    "sg:province":"Oost-Vlaanderen",
    "wof:name":"Selekt",
    "wof:placetype":"venue"
},
  "geometry": {"coordinates":[4.282597065,51.2221488953],"type":"Point"}
}