{
  "type": "Feature",
  "properties": {
    "addr:full":"Rue Willems 24 Sint-joost-ten-node/saint-josse-ten-noode Bruxelles-Capitale 1210",
    "addr:housenumber":"24",
    "addr:postcode":"1210",
    "addr:street":"Rue Willems",
    "iso:country":"BE",
    "sg:address":"Rue Willems 24",
    "sg:city":"Sint-joost-ten-node/saint-josse-ten-noode",
    "sg:orig_category":"S\u00e9curit\u00e9 sociale",
    "sg:phone":"+32 2 230 07 83",
    "sg:postcode":"1210",
    "sg:province":"Bruxelles-Capitale",
    "wof:name":"Christelijke Mutualiteit",
    "wof:placetype":"venue"
},
  "geometry": {"coordinates":[4.3762078285,50.8492736816],"type":"Point"}
}