{
  "type": "Feature",
  "properties": {
    "addr:full":"Avenue De Tervueren 96 Bruxelles (etterbeek) Bruxelles-Capitale 1040",
    "addr:housenumber":"96",
    "addr:postcode":"1040",
    "addr:street":"Avenue De Tervueren",
    "iso:country":"BE",
    "sg:address":"Avenue De Tervueren 96",
    "sg:city":"Bruxelles (etterbeek)",
    "sg:classifiers":[
        {
            "category":"Insurance",
            "subcategory":"Insurance Agent",
            "type":"Services"
        }
    ],
    "sg:phone":"+32 2 743 04 30",
    "sg:postcode":"1040",
    "sg:province":"Bruxelles-Capitale",
    "sg:tags":[
        "-",
        "representative"
    ],
    "wof:name":"Aia Pool",
    "wof:placetype":"venue"
},
  "geometry": {"coordinates":[4.4048199654,50.8383674622],"type":"Point"}
}