{
  "type": "Feature",
  "properties": {
    "addr:full":"Markt 30 Langemark-poelkapelle West-Vlaanderen 8920",
    "addr:housenumber":"30",
    "addr:postcode":"8920",
    "addr:street":"Markt",
    "iso:country":"BE",
    "sg:address":"Markt 30",
    "sg:city":"Langemark-poelkapelle",
    "sg:orig_category":"Meubles D\u00e9taillants, Am\u00e9nagement de B\u00e2timents et de Cuisines",
    "sg:phone":"+32 57 48 83 65",
    "sg:postcode":"8920",
    "sg:province":"West-Vlaanderen",
    "wof:name":"Andre Veracx",
    "wof:placetype":"venue"
},
  "geometry": {"coordinates":[2.919770956,50.9132423401],"type":"Point"}
}