{
  "type": "Feature",
  "properties": {
    "iso:country":"BE",
    "sg:address":"Steenweg 225",
    "sg:city":"Heers",
    "sg:orig_category":"Eleveurs de bovins",
    "sg:phone":"+32 11 48 46 61",
    "sg:postcode":"3870",
    "sg:province":"Limburg",
    "wof:name":"Karel Brone",
    "wof:placetype":"venue"
},
  "geometry": {"coordinates":[5.3051409721,50.7472610474],"type":"Point"}
}