{
  "type": "Feature",
  "properties": {
    "iso:country":"BE",
    "sg:address":"Rue De Marcasse 8",
    "sg:city":"Colfontaine",
    "sg:orig_category":"Postkantoren Verzekeringsmakelaars and experts",
    "sg:phone":"+32 65 67 30 64",
    "sg:postcode":"7340",
    "sg:province":"Hainaut",
    "wof:name":"La Poste",
    "wof:placetype":"venue"
},
  "geometry": {"coordinates":[3.837198019,50.4090080261],"type":"Point"}
}