{
  "type": "Feature",
  "properties": {
    "iso:country":"BE",
    "sg:address":"Schoolstraat 14",
    "sg:city":"Mechelen",
    "sg:classifiers":[
        {
            "category":"Restaurant",
            "type":"Food & Drink"
        }
    ],
    "sg:phone":"+32 15 21 64 62",
    "sg:postcode":"2800",
    "sg:province":"Antwerpen",
    "wof:name":"Las Tapas",
    "wof:placetype":"venue"
},
  "geometry": {"coordinates":[4.4803748131,51.0291213989],"type":"Point"}
}