{
  "type": "Feature",
  "properties": {
    "iso:country":"BE",
    "sg:address":"Van Trierstraat 50",
    "sg:city":"Antwerpen",
    "sg:orig_category":"Herstelling leer and schoeisel",
    "sg:phone":"+32 3 248 10 87",
    "sg:postcode":"2018",
    "sg:province":"Antwerpen",
    "wof:name":"Abdelali Drissi",
    "wof:placetype":"venue"
},
  "geometry": {"coordinates":[4.4004130363,51.2001876831],"type":"Point"}
}