{
  "type": "Feature",
  "properties": {
    "iso:country":"BE",
    "sg:address":"Orveiestraat 8",
    "sg:city":"Zwevegem",
    "sg:classifiers":[
        {
            "category":"Health Services",
            "subcategory":"Health Practitioner",
            "type":"Services"
        }
    ],
    "sg:phone":"+32 56 75 86 39",
    "sg:postcode":"8550",
    "sg:province":"West-Vlaanderen",
    "sg:tags":[
        "therapist",
        "speech"
    ],
    "wof:name":"Callens-vandamme Marleen Bvba",
    "wof:placetype":"venue"
},
  "geometry": {"coordinates":[3.3615510464,50.7966194153],"type":"Point"}
}