{
  "type": "Feature",
  "properties": {
    "iso:country":"BE",
    "sg:address":"Rue Du Dragon 129",
    "sg:city":"Mouscron",
    "sg:classifiers":[
        {
            "category":"Insurance",
            "subcategory":"Insurance Agent",
            "type":"Services"
        }
    ],
    "sg:phone":"+32 56 33 23 02",
    "sg:postcode":"7700",
    "sg:province":"Hainaut",
    "sg:tags":[
        "broker"
    ],
    "wof:name":"Deconinck & Keppers Sprl",
    "wof:placetype":"venue"
},
  "geometry": {"coordinates":[3.206911087,50.7425003052],"type":"Point"}
}