{
  "type": "Feature",
  "properties": {
    "iso:country":"BE",
    "sg:address":"Stationsstr 2",
    "sg:city":"St. Truiden",
    "sg:classifiers":[
        {
            "category":"Banks & Credit Unions",
            "subcategory":"Bank",
            "type":"Services"
        }
    ],
    "sg:postcode":"3800",
    "sg:province":"Limburg",
    "wof:name":"Ibis 4 Sa",
    "wof:placetype":"venue"
},
  "geometry": {"coordinates":[4.5675501823,50.6661186218],"type":"Point"}
}