{
  "type": "Feature",
  "properties": {
    "addr:full":"Martelaarslaan 260 Gent Oost-Vlaanderen 9000",
    "addr:housenumber":"260",
    "addr:postcode":"9000",
    "addr:street":"Martelaarslaan;Oost-Vlaanderen",
    "iso:country":"BE",
    "sg:address":"Martelaarslaan 260",
    "sg:city":"Gent",
    "sg:classifiers":[
        {
            "category":"Real Estate",
            "subcategory":"Architect",
            "type":"Services"
        }
    ],
    "sg:phone":"+32 9 234 04 30",
    "sg:postcode":"9000",
    "sg:province":"Oost-Vlaanderen",
    "wof:name":"Bockaert E",
    "wof:placetype":"venue"
},
  "geometry": {"coordinates":[3.7111570835,51.0472145081],"type":"Point"}
}