{
  "type": "Feature",
  "properties": {
    "iso:country":"BE",
    "sg:address":"Sinjorendreef 34",
    "sg:city":"Zoersel",
    "sg:classifiers":[
        {
            "category":"Taxi",
            "type":"Transportation"
        }
    ],
    "sg:phone":"+32 3 383 59 57",
    "sg:postcode":"2980",
    "sg:province":"Antwerpen",
    "sg:tags":[
        "taxicab"
    ],
    "wof:name":"De Keyser",
    "wof:placetype":"venue"
},
  "geometry": {"coordinates":[4.662815094,51.2623329163],"type":"Point"}
}