{
  "type": "Feature",
  "properties": {
    "addr:full":"Rue Des Champs 1 Flemalle Li\u00e8ge 4400",
    "addr:housenumber":"1",
    "addr:postcode":"4400",
    "addr:street":"Rue Des Champs",
    "iso:country":"BE",
    "sg:address":"Rue Des Champs 1",
    "sg:city":"Flemalle",
    "sg:orig_category":"Diverse juridische dienstverlening",
    "sg:phone":"+32 4 233 79 77",
    "sg:postcode":"4400",
    "sg:province":"Li\u00e8ge",
    "wof:name":"Daniel Degroot",
    "wof:placetype":"venue"
},
  "geometry": {"coordinates":[5.4651479721,50.6215591431],"type":"Point"}
}