{
  "type": "Feature",
  "properties": {
    "addr:full":"Rue De Bruxelles 18 Esneux Li\u00e8ge 4130",
    "addr:housenumber":"18",
    "addr:postcode":"4130",
    "addr:street":"Rue De Bruxelles",
    "iso:country":"BE",
    "sg:address":"Rue De Bruxelles 18",
    "sg:city":"Esneux",
    "sg:classifiers":[
        {
            "category":"Home & Garden",
            "subcategory":"Household Appliances",
            "type":"Retail Goods"
        }
    ],
    "sg:phone":"+32 4 380 10 78",
    "sg:postcode":"4130",
    "sg:province":"Li\u00e8ge",
    "sg:tags":[
        "repair",
        "mainten",
        "-",
        "electric"
    ],
    "wof:name":"Electro Esneux",
    "wof:placetype":"venue"
},
  "geometry": {"coordinates":[5.5665998459,50.5311317444],"type":"Point"}
}