{
  "type": "Feature",
  "properties": {
    "addr:full":"Poelstraat 151 Merelbeke Oost-Vlaanderen 9820",
    "addr:housenumber":"151",
    "addr:postcode":"9820",
    "addr:street":"Poelstraat",
    "iso:country":"BE",
    "sg:address":"Poelstraat 151",
    "sg:city":"Merelbeke",
    "sg:classifiers":[
        {
            "category":"Home & Garden",
            "subcategory":"Carpets & Floor Coverings",
            "type":"Retail Goods"
        }
    ],
    "sg:phone":"+32 9 230 90 61",
    "sg:postcode":"9820",
    "sg:province":"Oost-Vlaanderen",
    "sg:tags":[
        "layer",
        "mosaicists"
    ],
    "wof:name":"Meersschaut",
    "wof:placetype":"venue"
},
  "geometry": {"coordinates":[3.7573709488,50.9815711975],"type":"Point"}
}