{
  "type": "Feature",
  "properties": {
    "addr:full":"Rue Reine Astrid 10 Wanze (antheit) Li\u00e8ge 4520",
    "addr:housenumber":"10",
    "addr:postcode":"4520",
    "addr:street":"Rue Reine Astrid",
    "iso:country":"BE",
    "sg:address":"Rue Reine Astrid 10",
    "sg:city":"Wanze (antheit)",
    "sg:classifiers":[
        {
            "category":"Building & Trades",
            "subcategory":"Plumbing",
            "type":"Services"
        }
    ],
    "sg:phone":"+32 85 23 17 74",
    "sg:postcode":"4520",
    "sg:province":"Li\u00e8ge",
    "sg:tags":[
        "repair",
        "mainten",
        "-",
        "central",
        "heating"
    ],
    "wof:name":"Delvaux J-p",
    "wof:placetype":"venue"
},
  "geometry": {"coordinates":[5.232790947,50.5507316589],"type":"Point"}
}