{
  "type": "Feature",
  "properties": {
    "addr:full":"Place Des Peintres 7-104 Ottignies-louvain-la-neuve (louvain-la-neuve) Brabant Wallon 1348",
    "addr:housenumber":"7-104",
    "addr:postcode":"1348",
    "addr:street":"Place Des Peintres",
    "iso:country":"BE",
    "sg:address":"Place Des Peintres 7-104",
    "sg:city":"Ottignies-louvain-la-neuve (louvain-la-neuve)",
    "sg:classifiers":[
        {
            "category":"Health Services",
            "subcategory":"Doctor",
            "type":"Services"
        }
    ],
    "sg:phone":"+32 10 45 52 96",
    "sg:postcode":"1348",
    "sg:province":"Brabant Wallon",
    "sg:tags":[
        "medicinephysicians",
        "surgeon"
    ],
    "wof:name":"Hingot A",
    "wof:placetype":"venue"
},
  "geometry": {"coordinates":[4.6075987816,50.6661376953],"type":"Point"}
}