{
  "type": "Feature",
  "properties": {
    "iso:country":"BE",
    "sg:address":"Langeveldstraat 109",
    "sg:city":"Ukkel/uccle",
    "sg:orig_category":"Advocaten and juridische adviseurs",
    "sg:phone":"+32 2 372 00 83",
    "sg:postcode":"1180",
    "sg:province":"Bruxelles-Capitale",
    "wof:name":"Jo\u00cblle Maison",
    "wof:placetype":"venue"
},
  "geometry": {"coordinates":[4.3655948639,50.8061485291],"type":"Point"}
}