{
  "type": "Feature",
  "properties": {
    "addr:full":"J. De Troozlaan 7 Blankenberge West-Vlaanderen 8370",
    "addr:housenumber":"7",
    "addr:postcode":"8370",
    "addr:street":"J. De Troozlaan",
    "iso:country":"BE",
    "sg:address":"J. De Troozlaan 7",
    "sg:city":"Blankenberge",
    "sg:orig_category":"Artsen and specialisten",
    "sg:phone":"+32 50 41 46 40",
    "sg:postcode":"8370",
    "sg:province":"West-Vlaanderen",
    "wof:name":"Guido Claessens",
    "wof:placetype":"venue"
},
  "geometry": {"coordinates":[3.1366438866,51.3172225952],"type":"Point"}
}