{
  "type": "Feature",
  "properties": {
    "addr:full":"Chauss\u00c9e De Bruxelles 215 Waterloo Brabant Wallon 1410",
    "addr:housenumber":"215",
    "addr:postcode":"1410",
    "addr:street":"Chausse\u0301E De Bruxelles",
    "iso:country":"BE",
    "sg:address":"Chauss\u00c9e De Bruxelles 215",
    "sg:city":"Waterloo",
    "sg:orig_category":"DIENSTEN VOOR TELECOMMUNICATIE Mobistar Centres Telecommunicatieapparaten Telecommunicatiesystemen",
    "sg:phone":"+32 2 351 65 20",
    "sg:postcode":"1410",
    "sg:province":"Brabant Wallon",
    "wof:name":"Mobistar Center Musical Car",
    "wof:placetype":"venue"
},
  "geometry": {"coordinates":[4.3989610672,50.7154388428],"type":"Point"}
}