{
  "type": "Feature",
  "properties": {
    "addr:full":"Annastraat 16 Bilzen Limburg 3740",
    "addr:housenumber":"16",
    "addr:postcode":"3740",
    "addr:street":"Annastraat",
    "iso:country":"BE",
    "sg:address":"Annastraat 16",
    "sg:city":"Bilzen",
    "sg:orig_category":"Woningbouw",
    "sg:phone":"+32 89 41 10 89",
    "sg:postcode":"3740",
    "sg:province":"Limburg",
    "wof:name":"Hensen",
    "wof:placetype":"venue"
},
  "geometry": {"coordinates":[5.5709471703,50.8600502014],"type":"Point"}
}