{
  "type": "Feature",
  "properties": {
    "addr:full":"'t Angereelstraat 44 Ninove Oost-Vlaanderen 9400",
    "addr:housenumber":"44",
    "addr:postcode":"9400",
    "addr:street":"';Angereelstraat",
    "iso:country":"BE",
    "sg:address":"'t Angereelstraat 44",
    "sg:city":"Ninove",
    "sg:orig_category":"Boucheries",
    "sg:phone":"+32 54 32 47 18",
    "sg:postcode":"9400",
    "sg:province":"Oost-Vlaanderen",
    "wof:name":"Lieven De Meyer",
    "wof:placetype":"venue"
},
  "geometry": {"coordinates":[3.9687490463,50.8182983398],"type":"Point"}
}