{
  "type": "Feature",
  "properties": {
    "iso:country":"BE",
    "sg:address":"Dadizeelsestraat 295",
    "sg:city":"Moorslede",
    "sg:classifiers":[
        {
            "category":"Restaurant",
            "type":"Food & Drink"
        }
    ],
    "sg:phone":"+32 56 50 99 80",
    "sg:postcode":"8890",
    "sg:province":"West-Vlaanderen",
    "wof:name":"T Spaans Dak",
    "wof:placetype":"venue"
},
  "geometry": {"coordinates":[3.0926070213,50.8541870117],"type":"Point"}
}