{
  "type": "Feature",
  "properties": {
    "addr:full":"Rue G\u00e9n\u00e9ral De Gaulle 71 Li\u00e8ge 1 (bressoux) Li\u00e8ge 4020",
    "addr:housenumber":"71;1",
    "addr:postcode":"4020",
    "addr:street":"Rue Ge\u0301Ne\u0301Ral De Gaulle",
    "iso:country":"BE",
    "sg:address":"Rue G\u00e9n\u00e9ral De Gaulle 71",
    "sg:city":"Li\u00e8ge 1 (bressoux)",
    "sg:classifiers":[
        {
            "category":"Organizations",
            "subcategory":"Community Association",
            "type":"Services"
        }
    ],
    "sg:phone":"+32 4 342 69 97",
    "sg:postcode":"4020",
    "sg:province":"Li\u00e8ge",
    "sg:tags":[
        "cultural"
    ],
    "wof:name":"Criwe Asbl",
    "wof:placetype":"venue"
},
  "geometry": {"coordinates":[5.5947198868,50.6419830322],"type":"Point"}
}