{
  "type": "Feature",
  "properties": {
    "addr:full":"Rue De La Gare 1 Quievrain Hainaut 7380",
    "addr:housenumber":"1",
    "addr:postcode":"7380",
    "addr:street":"Rue De La Gare;Hainaut",
    "iso:country":"BE",
    "sg:address":"Rue De La Gare 1",
    "sg:city":"Quievrain",
    "sg:orig_category":"Enseignement maternel and primaire",
    "sg:phone":"+32 65 45 79 32",
    "sg:postcode":"7380",
    "sg:province":"Hainaut",
    "wof:name":"Ecole Fondamentale",
    "wof:placetype":"venue"
},
  "geometry": {"coordinates":[3.684429884,50.407951355],"type":"Point"}
}