{
  "type": "Feature",
  "properties": {
    "iso:country":"BE",
    "sg:address":"Rue Du Petchy 2",
    "sg:city":"Gerpinnes",
    "sg:orig_category":"Rundveehouders",
    "sg:phone":"+32 71 50 25 40",
    "sg:postcode":"6280",
    "sg:province":"Hainaut",
    "wof:name":"Rene Vandeverre",
    "wof:placetype":"venue"
},
  "geometry": {"coordinates":[4.5010499954,50.3429794312],"type":"Point"}
}