{
  "type": "Feature",
  "properties": {
    "addr:full":"Markekerkstraat 26 Kortrijk West-Vlaanderen 8510",
    "addr:housenumber":"26",
    "addr:postcode":"8510",
    "addr:street":"Markekerkstraat",
    "iso:country":"BE",
    "sg:address":"Markekerkstraat 26",
    "sg:city":"Kortrijk",
    "sg:orig_category":"Foto-uitrusting Fotografen and fotostudio's",
    "sg:phone":"+32 56 21 03 26",
    "sg:postcode":"8510",
    "sg:province":"West-Vlaanderen",
    "wof:name":"Clair-obscur",
    "wof:placetype":"venue"
},
  "geometry": {"coordinates":[3.2317049503,50.8082427979],"type":"Point"}
}