{
  "type": "Feature",
  "properties": {
    "iso:country":"BE",
    "sg:address":"Rue De La R\u00e9sistance 15",
    "sg:city":"Huy",
    "sg:classifiers":[
        {
            "category":"Professional",
            "subcategory":"Lawyer & Legal Services",
            "type":"Services"
        }
    ],
    "sg:phone":"+32 85 21 17 22",
    "sg:postcode":"4500",
    "sg:province":"Li\u00e8ge",
    "wof:name":"Charpentier Philippe",
    "wof:placetype":"venue"
},
  "geometry": {"coordinates":[5.2435388565,50.5204658508],"type":"Point"}
}