{
  "type": "Feature",
  "properties": {
    "iso:country":"BE",
    "sg:address":"Rue Des Carri\u00c8res 18",
    "sg:city":"Perwez",
    "sg:orig_category":"Agences immobili\u00e8res",
    "sg:phone":"+32 81 65 94 01",
    "sg:postcode":"1360",
    "sg:province":"Brabant Wallon",
    "wof:name":"Orwell",
    "wof:placetype":"venue"
},
  "geometry": {"coordinates":[4.8119068146,50.6262588501],"type":"Point"}
}