{
  "type": "Feature",
  "properties": {
    "addr:full":"Zandvoordedorpstr 34 Oostende West-Vlaanderen 8400",
    "addr:housenumber":"34",
    "addr:postcode":"8400",
    "addr:street":"Zandvoordedorpstr",
    "iso:country":"BE",
    "sg:address":"Zandvoordedorpstr 34",
    "sg:city":"Oostende",
    "sg:classifiers":[
        {
            "category":"Banks & Credit Unions",
            "subcategory":"Bank",
            "type":"Services"
        }
    ],
    "sg:phone":"+32 59 26 80 32",
    "sg:postcode":"8400",
    "sg:province":"West-Vlaanderen",
    "wof:name":"Aslk-cger Bank",
    "wof:placetype":"venue"
},
  "geometry": {"coordinates":[2.9367740154,51.2164421082],"type":"Point"}
}