{
  "type": "Feature",
  "properties": {
    "iso:country":"BE",
    "sg:address":"Tramstraat 42",
    "sg:city":"Tielt",
    "sg:orig_category":"Instituts de beaut\u00e9",
    "sg:phone":"+32 51 40 36 31",
    "sg:postcode":"8700",
    "sg:province":"West-Vlaanderen",
    "wof:name":"Bart Strosse",
    "wof:placetype":"venue"
},
  "geometry": {"coordinates":[3.3285241127,51.0023002625],"type":"Point"}
}