{
  "type": "Feature",
  "properties": {
    "addr:full":"Rue Saint-laurent 2 Bassenge (glons) Li\u00e8ge 4690",
    "addr:housenumber":"2",
    "addr:postcode":"4690",
    "addr:street":"Rue Saint-Laurent;Glons",
    "iso:country":"BE",
    "sg:address":"Rue Saint-laurent 2",
    "sg:city":"Bassenge (glons)",
    "sg:classifiers":[
        {
            "category":"Government",
            "subcategory":"Post Office",
            "type":"Public Place"
        }
    ],
    "sg:phone":"+32 4 286 16 97",
    "sg:postcode":"4690",
    "sg:province":"Li\u00e8ge",
    "sg:tags":[
        "access",
        "-",
        "part",
        "truck"
    ],
    "wof:name":"Swinnen J",
    "wof:placetype":"venue"
},
  "geometry": {"coordinates":[5.5425601006,50.7529792786],"type":"Point"}
}