{
  "type": "Feature",
  "properties": {
    "addr:full":"Pastoor Weytslaan 7 Kalmthout Antwerpen 2920",
    "addr:housenumber":"7",
    "addr:postcode":"2920",
    "addr:street":"Pastoor Weytslaan",
    "iso:country":"BE",
    "sg:address":"Pastoor Weytslaan 7",
    "sg:city":"Kalmthout",
    "sg:orig_category":"Banques and organismes de cr\u00e9dit",
    "sg:phone":"+32 3 666 98 58",
    "sg:postcode":"2920",
    "sg:province":"Antwerpen",
    "wof:name":"Beroepskrediet",
    "wof:placetype":"venue"
},
  "geometry": {"coordinates":[4.4726848602,51.3925170898],"type":"Point"}
}