{
  "type": "Feature",
  "properties": {
    "addr:full":"Verboekt 133b3 Laakdal Antwerpen 2430",
    "addr:housenumber":"133b3",
    "addr:postcode":"2430",
    "addr:street":"Verboekt",
    "iso:country":"BE",
    "sg:address":"Verboekt 133b3",
    "sg:city":"Laakdal",
    "sg:orig_category":"Activit\u00e9s d\u00b4action sociale sans h\u00e9bergement",
    "sg:postcode":"2430",
    "sg:province":"Antwerpen",
    "wof:name":"Rode Kruis Veerle",
    "wof:placetype":"venue"
},
  "geometry": {"coordinates":[5.0872821808,51.0938682556],"type":"Point"}
}