{
  "type": "Feature",
  "properties": {
    "iso:country":"BE",
    "sg:address":"Boondaalse Steenweg 182",
    "sg:city":"Elsene/ixelles",
    "sg:orig_category":"Apotheken",
    "sg:phone":"+32 2 649 30 09",
    "sg:postcode":"1050",
    "sg:province":"Bruxelles-Capitale",
    "wof:name":"D. De Pauw",
    "wof:placetype":"venue"
},
  "geometry": {"coordinates":[4.379524231,50.822303772],"type":"Point"}
}