{
  "type": "Feature",
  "properties": {
    "addr:full":"Kanaalstraat 103 Evergem (ertvelde) Oost-Vlaanderen 9940",
    "addr:housenumber":"103",
    "addr:postcode":"9940",
    "addr:street":"Kanaalstraat;Ertvelde Oost-Vlaanderen",
    "iso:country":"BE",
    "sg:address":"Kanaalstraat 103",
    "sg:city":"Evergem (ertvelde)",
    "sg:classifiers":[
        {
            "category":"Building & Trades",
            "subcategory":"Construction",
            "type":"Services"
        }
    ],
    "sg:phone":"+32 9 344 98 30",
    "sg:postcode":"9940",
    "sg:province":"Oost-Vlaanderen",
    "sg:tags":[
        "carpenter"
    ],
    "wof:name":"Standaert F",
    "wof:placetype":"venue"
},
  "geometry": {"coordinates":[3.7101800442,51.1111564636],"type":"Point"}
}