{
  "type": "Feature",
  "properties": {
    "iso:country":"BE",
    "sg:address":"Rue Del'vaux 10",
    "sg:city":"Gembloux",
    "sg:orig_category":"Pain, p\u00e2tisseries and confiseries",
    "sg:phone":"+32 81 64 03 79",
    "sg:postcode":"5031",
    "sg:province":"Namur",
    "wof:name":"Alain Goffaux",
    "wof:placetype":"venue"
},
  "geometry": {"coordinates":[4.769343853,50.581943512],"type":"Point"}
}