{
  "type": "Feature",
  "properties": {
    "addr:full":"Meistraat 1a Berlaar Antwerpen 2590",
    "addr:housenumber":"1a",
    "addr:postcode":"2590",
    "addr:street":"Meistraat",
    "iso:country":"BE",
    "sg:address":"Meistraat 1a",
    "sg:city":"Berlaar",
    "sg:classifiers":[
        {
            "category":"Professional",
            "subcategory":"Accounting & Tax Preparation",
            "type":"Services"
        }
    ],
    "sg:phone":"+32 3 420 02 20",
    "sg:postcode":"2590",
    "sg:province":"Antwerpen",
    "sg:tags":[
        "accountant"
    ],
    "wof:name":"Van Noten H",
    "wof:placetype":"venue"
},
  "geometry": {"coordinates":[4.653439045,51.1130905151],"type":"Point"}
}