{
  "type": "Feature",
  "properties": {
    "iso:country":"BE",
    "sg:address":"Ieperstraat 192",
    "sg:city":"Zonnebeke",
    "sg:orig_category":"Huisvuilophaling and -verwerking",
    "sg:phone":"+32 51 77 06 25",
    "sg:postcode":"8980",
    "sg:province":"West-Vlaanderen",
    "wof:name":"Inafzo",
    "wof:placetype":"venue"
},
  "geometry": {"coordinates":[2.9638938904,50.8707580566],"type":"Point"}
}