{
  "type": "Feature",
  "properties": {
    "iso:country":"BE",
    "sg:address":"Clem. Vanophemstraat 72",
    "sg:city":"Overijse",
    "sg:classifiers":[
        {
            "category":"Shopping",
            "subcategory":"Pets & Pet Supplies",
            "type":"Retail Goods"
        }
    ],
    "sg:phone":"+32 2 688 13 22",
    "sg:postcode":"3090",
    "sg:province":"Vlaams-Brabant",
    "sg:tags":[
        "aquarium",
        "accessory"
    ],
    "wof:name":"Wintrop",
    "wof:placetype":"venue"
},
  "geometry": {"coordinates":[4.5270929337,50.7822685242],"type":"Point"}
}