{
  "type": "Feature",
  "properties": {
    "iso:country":"BE",
    "sg:address":"Rue Lintermans 2",
    "sg:city":"Seneffe",
    "sg:classifiers":[
        {
            "category":"Food & Beverages",
            "subcategory":"Groceries & Convenience Stores",
            "type":"Retail Goods"
        }
    ],
    "sg:phone":"+32 64 55 70 07",
    "sg:postcode":"7180",
    "sg:province":"Hainaut",
    "sg:tags":[
        "grocer"
    ],
    "wof:name":"Inter-battard",
    "wof:placetype":"venue"
},
  "geometry": {"coordinates":[4.2560348511,50.5300636292],"type":"Point"}
}