{
  "type": "Feature",
  "properties": {
    "addr:full":"Rue Arbre Saint-pierre 49 Ellezelles Hainaut 7890",
    "addr:housenumber":"49",
    "addr:postcode":"7890",
    "addr:street":"Rue Arbre Saint-Pierre",
    "iso:country":"BE",
    "sg:address":"Rue Arbre Saint-pierre 49",
    "sg:city":"Ellezelles",
    "sg:classifiers":[
        {
            "category":"Food & Beverages",
            "subcategory":"Liquor & Beverages",
            "type":"Retail Goods"
        }
    ],
    "sg:phone":"+32 68 54 21 45",
    "sg:postcode":"7890",
    "sg:province":"Hainaut",
    "sg:tags":[
        "-",
        "spirit",
        "wine"
    ],
    "wof:name":"Cellier St-pierre",
    "wof:placetype":"venue"
},
  "geometry": {"coordinates":[3.6831851006,50.7156181335],"type":"Point"}
}