{
  "type": "Feature",
  "properties": {
    "iso:country":"BE",
    "sg:address":"Rue Du Coq 11b47",
    "sg:city":"Huy",
    "sg:orig_category":"Schoonheidssalons",
    "sg:phone":"+32 85 21 45 07",
    "sg:postcode":"4500",
    "sg:province":"Li\u00e8ge",
    "wof:name":"V\u00c9ronique Simal",
    "wof:placetype":"venue"
},
  "geometry": {"coordinates":[5.2415809631,50.5192909241],"type":"Point"}
}