{
  "type": "Feature",
  "properties": {
    "iso:country":"BE",
    "sg:address":"Esperantostraat 1",
    "sg:city":"Gent",
    "sg:orig_category":"Boissons",
    "sg:phone":"+32 9 228 31 88",
    "sg:postcode":"9040",
    "sg:province":"Oost-Vlaanderen",
    "wof:name":"Jamichot",
    "wof:placetype":"venue"
},
  "geometry": {"coordinates":[3.7669420242,51.0717887878],"type":"Point"}
}