{
  "type": "Feature",
  "properties": {
    "iso:country":"BE",
    "sg:address":"Rue Du Petit Pont 9",
    "sg:city":"Mouscron",
    "sg:classifiers":[
        {
            "category":"Professional",
            "subcategory":"Art Services",
            "type":"Services"
        }
    ],
    "sg:phone":"+32 56 34 45 17",
    "sg:postcode":"7700",
    "sg:province":"Hainaut",
    "sg:tags":[
        "photographer"
    ],
    "wof:name":"Images De Marc",
    "wof:placetype":"venue"
},
  "geometry": {"coordinates":[3.2278649807,50.7502403259],"type":"Point"}
}