{
  "type": "Feature",
  "properties": {
    "iso:country":"BE",
    "sg:address":"Rue De L'american-legion 78",
    "sg:city":"Bastogne",
    "sg:orig_category":"Winkelinrichting and handelsuitrusting Gh",
    "sg:phone":"+32 61 21 41 66",
    "sg:postcode":"6600",
    "sg:province":"Luxembourg",
    "wof:name":"Moka D'or",
    "wof:placetype":"venue"
},
  "geometry": {"coordinates":[5.7284879684,50.0024452209],"type":"Point"}
}