{
  "type": "Feature",
  "properties": {
    "addr:full":"Achteraard 7 Hoogstraten Antwerpen 2322",
    "addr:housenumber":"7",
    "addr:postcode":"2322",
    "addr:street":"Achteraard",
    "iso:country":"BE",
    "sg:address":"Achteraard 7",
    "sg:city":"Hoogstraten",
    "sg:orig_category":"Rundveehouders",
    "sg:phone":"+32 3 314 68 46",
    "sg:postcode":"2322",
    "sg:province":"Antwerpen",
    "wof:name":"Jan Mertens",
    "wof:placetype":"venue"
},
  "geometry": {"coordinates":[4.763384819,51.4160041809],"type":"Point"}
}