{
  "type": "Feature",
  "properties": {
    "addr:full":"Maastrichterstraat 24 Tongeren Limburg 3700",
    "addr:housenumber":"24",
    "addr:postcode":"3700",
    "addr:street":"Maastrichterstraat",
    "iso:country":"BE",
    "sg:address":"Maastrichterstraat 24",
    "sg:city":"Tongeren",
    "sg:orig_category":"Foto-uitrusting Fotografen and fotostudio's",
    "sg:phone":"+32 12 23 14 25",
    "sg:postcode":"3700",
    "sg:province":"Limburg",
    "wof:name":"Fa. Christiaens",
    "wof:placetype":"venue"
},
  "geometry": {"coordinates":[5.4649310112,50.7817687988],"type":"Point"}
}