{
  "type": "Feature",
  "properties": {
    "addr:full":"Geetkouterstraat 40 Linter Vlaams-Brabant 3350",
    "addr:housenumber":"40",
    "addr:postcode":"3350",
    "addr:street":"Geetkouterstraat;Vlaams-Brabant",
    "iso:country":"BE",
    "sg:address":"Geetkouterstraat 40",
    "sg:city":"Linter",
    "sg:orig_category":"Rundveehouders Varkenskwekers",
    "sg:phone":"+32 16 78 85 49",
    "sg:postcode":"3350",
    "sg:province":"Vlaams-Brabant",
    "wof:name":"Karel Petre",
    "wof:placetype":"venue"
},
  "geometry": {"coordinates":[5.0185861588,50.820980072],"type":"Point"}
}