{
  "type": "Feature",
  "properties": {
    "addr:full":"Korte Steenstraat 2bb Kortrijk West-Vlaanderen 8500",
    "addr:housenumber":"2bb",
    "addr:postcode":"8500",
    "addr:street":"Korte Steenstraat",
    "iso:country":"BE",
    "sg:address":"Korte Steenstraat 2bb",
    "sg:city":"Kortrijk",
    "sg:orig_category":"Dameskledingzaken",
    "sg:phone":"+32 56 25 76 10",
    "sg:postcode":"8500",
    "sg:province":"West-Vlaanderen",
    "wof:name":"Mexx",
    "wof:placetype":"venue"
},
  "geometry": {"coordinates":[3.2671830654,50.8272438049],"type":"Point"}
}