{
  "type": "Feature",
  "properties": {
    "addr:full":"Rue Trou Du Renard 8 Beyne-heusay Li\u00e8ge 4610",
    "addr:housenumber":"8",
    "addr:postcode":"4610",
    "addr:street":"Rue Trou Du Renard",
    "iso:country":"BE",
    "sg:address":"Rue Trou Du Renard 8",
    "sg:city":"Beyne-heusay",
    "sg:classifiers":[
        {
            "category":"Insurance",
            "subcategory":"Insurance Agent",
            "type":"Services"
        }
    ],
    "sg:phone":"+32 4 358 98 67",
    "sg:postcode":"4610",
    "sg:province":"Li\u00e8ge",
    "sg:tags":[
        "verzekeringsmakelaars",
        "expert"
    ],
    "wof:name":"M. Szendrei",
    "wof:placetype":"venue"
},
  "geometry": {"coordinates":[5.6587600708,50.624710083],"type":"Point"}
}