{
  "type": "Feature",
  "properties": {
    "addr:full":"Langenbergstraat 7 Bornem Antwerpen 2880",
    "addr:housenumber":"7",
    "addr:postcode":"2880",
    "addr:street":"Langenbergstraat",
    "iso:country":"BE",
    "sg:address":"Langenbergstraat 7",
    "sg:city":"Bornem",
    "sg:classifiers":[
        {
            "category":"Farming",
            "subcategory":"Fish & Marine Products",
            "type":"Manufacturing & Wholesale Goods"
        }
    ],
    "sg:phone":"+32 3 889 15 55",
    "sg:postcode":"2880",
    "sg:province":"Antwerpen",
    "sg:tags":[
        "retail",
        "-",
        "shellfish"
    ],
    "wof:name":"Saeys K",
    "wof:placetype":"venue"
},
  "geometry": {"coordinates":[4.1944279671,51.0766830444],"type":"Point"}
}