{
  "type": "Feature",
  "properties": {
    "addr:full":"Shopping Ii Genk Limburg 3600",
    "addr:postcode":"3600",
    "addr:street":"Limburg",
    "iso:country":"BE",
    "sg:address":"Shopping Ii",
    "sg:city":"Genk",
    "sg:classifiers":[
        {
            "category":"Shopping",
            "subcategory":"Pets & Pet Supplies",
            "type":"Retail Goods"
        }
    ],
    "sg:phone":"+32 89 30 83 69",
    "sg:postcode":"3600",
    "sg:province":"Limburg",
    "sg:tags":[
        "shop",
        "-"
    ],
    "wof:name":"Lucky Petshop",
    "wof:placetype":"venue"
},
  "geometry": {"coordinates":[5.4990148544,50.9635848999],"type":"Point"}
}