{
  "type": "Feature",
  "properties": {
    "addr:full":"Rue Des Martyrs 16 Andenne Namur 5300",
    "addr:housenumber":"16",
    "addr:postcode":"5300",
    "addr:street":"Rue Des Martyrs",
    "iso:country":"BE",
    "sg:address":"Rue Des Martyrs 16",
    "sg:city":"Andenne",
    "sg:orig_category":"Entretien and r\u00e9parations de voitures. V\u00e9hicules automobiles",
    "sg:phone":"+32 85 82 62 22",
    "sg:postcode":"5300",
    "sg:province":"Namur",
    "wof:name":"Thierry Misson",
    "wof:placetype":"venue"
},
  "geometry": {"coordinates":[5.0982642174,50.4863739014],"type":"Point"}
}