{
  "type": "Feature",
  "properties": {
    "addr:full":"Rue Gavette 6 Peruwelz Hainaut 7600",
    "addr:housenumber":"6",
    "addr:postcode":"7600",
    "addr:street":"Rue Gavette;Hainaut",
    "iso:country":"BE",
    "sg:address":"Rue Gavette 6",
    "sg:city":"Peruwelz",
    "sg:orig_category":"Installation de menuiserie en bois and plastique",
    "sg:phone":"+32 69 77 22 51",
    "sg:postcode":"7600",
    "sg:province":"Hainaut",
    "wof:name":"Vandrepotte",
    "wof:placetype":"venue"
},
  "geometry": {"coordinates":[3.5883080959,50.5006790161],"type":"Point"}
}