{
  "type": "Feature",
  "properties": {
    "iso:country":"BE",
    "sg:address":"Gentsesteenweg 86",
    "sg:city":"Eeklo",
    "sg:orig_category":"Radioproductie and uitzendingen Televisieproductie and uitzendingen",
    "sg:phone":"+32 9 378 07 78",
    "sg:postcode":"9900",
    "sg:province":"Oost-Vlaanderen",
    "wof:name":"Radio A.v.s.",
    "wof:placetype":"venue"
},
  "geometry": {"coordinates":[3.5821011066,51.1743812561],"type":"Point"}
}