{
  "type": "Feature",
  "properties": {
    "addr:full":"Avenue Louise 475 Bruxelles (ixelles) Bruxelles-Capitale 1050",
    "addr:housenumber":"475",
    "addr:postcode":"1050",
    "addr:street":"Avenue Louise",
    "iso:country":"BE",
    "sg:address":"Avenue Louise 475",
    "sg:city":"Bruxelles (ixelles)",
    "sg:classifiers":[
        {
            "category":"Government",
            "subcategory":"Embassy",
            "type":"Public Place"
        }
    ],
    "sg:phone":"+32 2 649 90 55",
    "sg:postcode":"1050",
    "sg:province":"Bruxelles-Capitale",
    "sg:tags":[
        "consulate"
    ],
    "wof:name":"Paraguay (ambassade)",
    "wof:placetype":"venue"
},
  "geometry": {"coordinates":[4.3712029457,50.8171958923],"type":"Point"}
}