{
  "type": "Feature",
  "properties": {
    "addr:full":"Ninoofsesteenweg 84 Dilbeek Vlaams-Brabant 1700",
    "addr:housenumber":"84",
    "addr:postcode":"1700",
    "addr:street":"Ninoofsesteenweg",
    "iso:country":"BE",
    "sg:address":"Ninoofsesteenweg 84",
    "sg:city":"Dilbeek",
    "sg:orig_category":"Diverse kredietdiensten",
    "sg:postcode":"1700",
    "sg:province":"Vlaams-Brabant",
    "wof:name":"Bancontact-mister Cash",
    "wof:placetype":"venue"
},
  "geometry": {"coordinates":[4.2778568268,50.8450012207],"type":"Point"}
}