{
  "type": "Feature",
  "properties": {
    "addr:full":"Herbert Hooverlaan 106 Sint-lambrechts-woluwe/woluwe-saint-lambert Bruxelles-Capitale 1200",
    "addr:housenumber":"106;/",
    "addr:postcode":"1200",
    "addr:street":"Herbert Hooverlaan;Sint-Lambrechts-Woluwe",
    "iso:country":"BE",
    "sg:address":"Herbert Hooverlaan 106",
    "sg:city":"Sint-lambrechts-woluwe/woluwe-saint-lambert",
    "sg:orig_category":"Elektrische installaties voor woningen",
    "sg:phone":"+32 2 735 61 31",
    "sg:postcode":"1200",
    "sg:province":"Bruxelles-Capitale",
    "wof:name":"Fe. De Greef",
    "wof:placetype":"venue"
},
  "geometry": {"coordinates":[4.4098210335,50.8484344482],"type":"Point"}
}