{
  "type": "Feature",
  "properties": {
    "iso:country":"BE",
    "sg:address":"Rue De La Jonqueliere 1",
    "sg:city":"Florenville",
    "sg:orig_category":"Dierenartsen",
    "sg:phone":"+32 61 31 23 55",
    "sg:postcode":"6820",
    "sg:province":"Luxembourg",
    "wof:name":"Marc Lamort",
    "wof:placetype":"venue"
},
  "geometry": {"coordinates":[5.1798028946,49.7177085876],"type":"Point"}
}