{
  "type": "Feature",
  "properties": {
    "addr:full":"Ketteniserstrasse 57 Lontzen (walhorn) Li\u00e8ge 4711",
    "addr:housenumber":"57",
    "addr:postcode":"4711",
    "addr:street":"Ketteniserstrasse",
    "iso:country":"BE",
    "sg:address":"Ketteniserstrasse 57",
    "sg:city":"Lontzen (walhorn)",
    "sg:classifiers":[
        {
            "category":"Banks & Credit Unions",
            "subcategory":"Investment Brokerage",
            "type":"Services"
        }
    ],
    "sg:phone":"+32 87 55 37 44",
    "sg:postcode":"4711",
    "sg:province":"Li\u00e8ge",
    "sg:tags":[
        "repair",
        "-",
        "installation",
        "sanitary",
        "article"
    ],
    "wof:name":"Belleflamme R",
    "wof:placetype":"venue"
},
  "geometry": {"coordinates":[6.047369957,50.6752853394],"type":"Point"}
}