{
  "type": "Feature",
  "properties": {
    "addr:full":"Neuville 74 Stoumont (chevron) Li\u00e8ge 4987",
    "addr:housenumber":"74",
    "addr:postcode":"4987",
    "addr:street":"Neuville",
    "iso:country":"BE",
    "sg:address":"Neuville 74",
    "sg:city":"Stoumont (chevron)",
    "sg:classifiers":[
        {
            "category":"Building & Trades",
            "subcategory":"Construction",
            "type":"Services"
        }
    ],
    "sg:phone":"+32 495 88 46 94",
    "sg:postcode":"4987",
    "sg:province":"Li\u00e8ge",
    "sg:tags":[
        "carpenter"
    ],
    "wof:name":"Bonivers T",
    "wof:placetype":"venue"
},
  "geometry": {"coordinates":[5.8098897934,50.4056663513],"type":"Point"}
}