{
  "type": "Feature",
  "properties": {
    "iso:country":"BE",
    "sg:address":"Heidestraat 81",
    "sg:city":"Tervuren (duisburg)",
    "sg:classifiers":[
        {
            "category":"Home & Garden",
            "subcategory":"Furniture",
            "type":"Retail Goods"
        }
    ],
    "sg:phone":"+32 2 767 72 43",
    "sg:postcode":"3080",
    "sg:province":"Vlaams-Brabant",
    "sg:tags":[
        "-"
    ],
    "wof:name":"Gloster-viridee",
    "wof:placetype":"venue"
},
  "geometry": {"coordinates":[4.5439310074,50.8123016357],"type":"Point"}
}