{
  "type": "Feature",
  "properties": {
    "addr:full":"Rue De La Cornette Bertrix (auby-sur-semois) Luxembourg 6880",
    "addr:postcode":"6880",
    "addr:street":"Rue De La Cornette",
    "iso:country":"BE",
    "sg:address":"Rue De La Cornette",
    "sg:city":"Bertrix (auby-sur-semois)",
    "sg:classifiers":[
        {
            "category":"Farming",
            "subcategory":"Fish & Marine Products",
            "type":"Manufacturing & Wholesale Goods"
        }
    ],
    "sg:phone":"+32 61 41 37 34",
    "sg:postcode":"6880",
    "sg:province":"Luxembourg",
    "sg:tags":[
        "breeding"
    ],
    "wof:name":"Truite Des Alleines (la)",
    "wof:placetype":"venue"
},
  "geometry": {"coordinates":[5.2535948753,49.8544845581],"type":"Point"}
}