{
  "type": "Feature",
  "properties": {
    "addr:full":"Venelle Des Acers 10 Wavre Brabant Wallon 1300",
    "addr:housenumber":"10;1300",
    "addr:street":"Venelle Des Acers",
    "iso:country":"BE",
    "sg:address":"Venelle Des Acers 10",
    "sg:city":"Wavre",
    "sg:classifiers":[
        {
            "category":"Communications",
            "type":"Services"
        }
    ],
    "sg:phone":"+32 10 24 41 42",
    "sg:postcode":"1300",
    "sg:province":"Brabant Wallon",
    "sg:tags":[
        "translator"
    ],
    "wof:name":"Russian Language For Every Body",
    "wof:placetype":"venue"
},
  "geometry": {"coordinates":[4.6180782318,50.707408905],"type":"Point"}
}