{
  "type": "Feature",
  "properties": {
    "addr:full":"Route De La-roche 2ba Tenneville Luxembourg 6970",
    "addr:housenumber":"2ba",
    "addr:postcode":"6970",
    "addr:street":"Route De La-Roche",
    "iso:country":"BE",
    "sg:address":"Route De La-roche 2ba",
    "sg:city":"Tenneville",
    "sg:classifiers":[
        {
            "category":"Arena",
            "subcategory":"Sports Club",
            "type":"Entertainment"
        }
    ],
    "sg:phone":"+32 84 45 57 07",
    "sg:postcode":"6970",
    "sg:province":"Luxembourg",
    "sg:tags":[
        "terrain",
        "hors",
        "de",
        "installation",
        "sportifs"
    ],
    "wof:name":"Tenneville Sports",
    "wof:placetype":"venue"
},
  "geometry": {"coordinates":[5.5363850594,50.0870285034],"type":"Point"}
}