{
  "type": "Feature",
  "properties": {
    "iso:country":"BE",
    "sg:address":"Clamarastraat 6",
    "sg:city":"Lo-reninge",
    "sg:orig_category":"Producteurs de l\u00e9gumes",
    "sg:phone":"+32 58 28 82 34",
    "sg:postcode":"8647",
    "sg:province":"West-Vlaanderen",
    "wof:name":"Eddy Ryckeboer",
    "wof:placetype":"venue"
},
  "geometry": {"coordinates":[2.7187590599,50.9869346619],"type":"Point"}
}