{
  "type": "Feature",
  "properties": {
    "iso:country":"BE",
    "sg:address":"Zandstraat 94",
    "sg:city":"Beveren",
    "sg:orig_category":"Eleveurs de bovins",
    "sg:phone":"+32 3 775 74 06",
    "sg:postcode":"9120",
    "sg:province":"Oost-Vlaanderen",
    "wof:name":"Raphael Van Royen",
    "wof:placetype":"venue"
},
  "geometry": {"coordinates":[4.2362098694,51.1870079041],"type":"Point"}
}