{
  "type": "Feature",
  "properties": {
    "iso:country":"BE",
    "sg:address":"Bommelslaan 6",
    "sg:city":"Lochristi",
    "sg:orig_category":"Installation de menuiserie en bois and plastique",
    "sg:phone":"+32 9 355 09 33",
    "sg:postcode":"9080",
    "sg:province":"Oost-Vlaanderen",
    "wof:name":"Eric Van Uytvanck",
    "wof:placetype":"venue"
},
  "geometry": {"coordinates":[3.8567490578,51.0891151428],"type":"Point"}
}