{
  "type": "Feature",
  "properties": {
    "addr:full":"Marktplein 8 Dilbeek Vlaams-Brabant 1700",
    "addr:housenumber":"8",
    "addr:postcode":"1700",
    "addr:street":"Marktplein",
    "iso:country":"BE",
    "sg:address":"Marktplein 8",
    "sg:city":"Dilbeek",
    "sg:orig_category":"Enseignement maternel and primaire",
    "sg:phone":"+32 2 569 55 78",
    "sg:postcode":"1700",
    "sg:province":"Vlaams-Brabant",
    "wof:name":"Gemeentel. Lagere School",
    "wof:placetype":"venue"
},
  "geometry": {"coordinates":[4.2637429237,50.8446960449],"type":"Point"}
}