{
  "type": "Feature",
  "properties": {
    "addr:full":"Parvis St Georges 2 Grez-doiceau Brabant Wallon 1390",
    "addr:housenumber":"2",
    "addr:postcode":"1390",
    "addr:street":"Parvis St Georges",
    "iso:country":"BE",
    "sg:address":"Parvis St Georges 2",
    "sg:city":"Grez-doiceau",
    "sg:orig_category":"Enseignement maternel and primaire",
    "sg:phone":"+32 10 84 44 25",
    "sg:postcode":"1390",
    "sg:province":"Brabant Wallon",
    "wof:name":"Ecole Fondamentale Libre",
    "wof:placetype":"venue"
},
  "geometry": {"coordinates":[4.6961297989,50.7377891541],"type":"Point"}
}