{
  "type": "Feature",
  "properties": {
    "iso:country":"BE",
    "sg:address":"Rue Joseph Wauters 10",
    "sg:city":"Nivelles",
    "sg:classifiers":[
        {
            "category":"Retail",
            "subcategory":"Veterinary Services",
            "type":"Services"
        }
    ],
    "sg:phone":"+32 67 21 44 33",
    "sg:postcode":"1400",
    "sg:province":"Brabant Wallon",
    "sg:tags":[
        "veterinarian"
    ],
    "wof:name":"Maquigny D",
    "wof:placetype":"venue"
},
  "geometry": {"coordinates":[4.3190078735,50.6013145447],"type":"Point"}
}