{
  "type": "Feature",
  "properties": {
    "addr:full":"Rue Du Pot-d\u00b4or 10ba Li\u00c8ge Li\u00e8ge 4000",
    "addr:housenumber":"10ba",
    "addr:postcode":"4000",
    "addr:street":"Rue Du Pot-D\u00b4Or",
    "iso:country":"BE",
    "sg:address":"Rue Du Pot-d\u00b4or 10ba",
    "sg:city":"Li\u00c8ge",
    "sg:orig_category":"V\u00eatements sur mesure Fab",
    "sg:phone":"+32 4 223 11 15",
    "sg:postcode":"4000",
    "sg:province":"Li\u00e8ge",
    "wof:name":"Maison Krug",
    "wof:placetype":"venue"
},
  "geometry": {"coordinates":[5.5703639984,50.6420555115],"type":"Point"}
}