{
  "type": "Feature",
  "properties": {
    "iso:country":"BE",
    "sg:address":"Winkelomstraat 26",
    "sg:city":"Bilzen",
    "sg:orig_category":"Services fun\u00e9raires",
    "sg:phone":"+32 89 41 66 61",
    "sg:postcode":"3740",
    "sg:province":"Limburg",
    "wof:name":"M. & D.",
    "wof:placetype":"venue"
},
  "geometry": {"coordinates":[5.5793862343,50.8745536804],"type":"Point"}
}