{
  "type": "Feature",
  "properties": {
    "iso:country":"BE",
    "sg:address":"Heibaan 245",
    "sg:city":"Hulshout",
    "sg:orig_category":"Installation de menuiserie m\u00e9tallique",
    "sg:phone":"+32 16 69 84 07",
    "sg:postcode":"2235",
    "sg:province":"Antwerpen",
    "wof:name":"Peeters Karel",
    "wof:placetype":"venue"
},
  "geometry": {"coordinates":[4.8269162178,51.0736808777],"type":"Point"}
}