{
  "type": "Feature",
  "properties": {
    "addr:full":"Avenue Prekelinden 18 Bruxelles (woluwe-saint-lambert) Bruxelles-Capitale 1200",
    "addr:housenumber":"18",
    "addr:postcode":"1200",
    "addr:street":"Avenue Prekelinden",
    "iso:country":"BE",
    "sg:address":"Avenue Prekelinden 18",
    "sg:city":"Bruxelles (woluwe-saint-lambert)",
    "sg:classifiers":[
        {
            "category":"Personal",
            "subcategory":"Beauty Salon",
            "type":"Services"
        }
    ],
    "sg:phone":"+32 2 734 81 21",
    "sg:postcode":"1200",
    "sg:province":"Bruxelles-Capitale",
    "sg:tags":[
        "lady",
        "-",
        "hairdressing"
    ],
    "wof:name":"Di Fiore",
    "wof:placetype":"venue"
},
  "geometry": {"coordinates":[4.4107861519,50.8397712708],"type":"Point"}
}