{
  "type": "Feature",
  "properties": {
    "addr:full":"Rue Fran\u00c7ois G\u00c9rard 10 Flemalle Li\u00e8ge 4400",
    "addr:housenumber":"10",
    "addr:postcode":"4400",
    "addr:street":"Rue Franc\u0327Ois Ge\u0301Rard",
    "iso:country":"BE",
    "sg:address":"Rue Fran\u00c7ois G\u00c9rard 10",
    "sg:city":"Flemalle",
    "sg:orig_category":"Restaurants Ruimtes voor conferenties, recepties and feesten",
    "sg:phone":"+32 4 337 18 43",
    "sg:postcode":"4400",
    "sg:province":"Li\u00e8ge",
    "wof:name":"Chez Cha-cha",
    "wof:placetype":"venue"
},
  "geometry": {"coordinates":[5.4645709991,50.5884857178],"type":"Point"}
}