{
  "type": "Feature",
  "properties": {
    "iso:country":"BE",
    "sg:address":"Rue De La Sablonniere 10",
    "sg:city":"Li\u00c8ge",
    "sg:orig_category":"Tabac",
    "sg:phone":"+32 4 365 76 45",
    "sg:postcode":"4031",
    "sg:province":"Li\u00e8ge",
    "wof:name":"Auguste Dejardin",
    "wof:placetype":"venue"
},
  "geometry": {"coordinates":[5.5713119507,50.5937995911],"type":"Point"}
}