{
  "type": "Feature",
  "properties": {
    "addr:full":"Rue Van Opr\u00e9 97 Namur (jambes) Namur 5100",
    "addr:housenumber":"97",
    "addr:postcode":"5100",
    "addr:street":"Rue Van Opre\u0301",
    "iso:country":"BE",
    "sg:address":"Rue Van Opr\u00e9 97",
    "sg:city":"Namur (jambes)",
    "sg:classifiers":[
        {
            "category":"Health Services",
            "subcategory":"Doctor",
            "type":"Services"
        }
    ],
    "sg:phone":"+32 81 30 02 61",
    "sg:postcode":"5100",
    "sg:province":"Namur",
    "sg:tags":[
        "medicinephysicians",
        "surgeon"
    ],
    "wof:name":"De Grez Thierry",
    "wof:placetype":"venue"
},
  "geometry": {"coordinates":[4.8759670258,50.4609184265],"type":"Point"}
}