{
  "type": "Feature",
  "properties": {
    "addr:full":"Heirstraat 382 Maasmechelen (opgrimbie) Limburg 3630",
    "addr:housenumber":"382",
    "addr:postcode":"3630",
    "addr:street":"Heirstraat",
    "iso:country":"BE",
    "sg:address":"Heirstraat 382",
    "sg:city":"Maasmechelen (opgrimbie)",
    "sg:classifiers":[
        {
            "category":"Personal",
            "subcategory":"Beauty Salon",
            "type":"Services"
        }
    ],
    "sg:phone":"+32 89 77 51 35",
    "sg:postcode":"3630",
    "sg:province":"Limburg",
    "sg:tags":[
        "lady",
        "-",
        "hairdressing"
    ],
    "wof:name":"Anna-maria",
    "wof:placetype":"venue"
},
  "geometry": {"coordinates":[5.6846699715,50.9509391785],"type":"Point"}
}