{
  "type": "Feature",
  "properties": {
    "addr:full":"Koninginnegalerij 19 Brussel/bruxelles Bruxelles-Capitale 1000",
    "addr:housenumber":"19",
    "addr:postcode":"1000",
    "addr:street":"Koninginnegalerij;/",
    "iso:country":"BE",
    "sg:address":"Koninginnegalerij 19",
    "sg:city":"Brussel/bruxelles",
    "sg:orig_category":"Herstelling horloges and juwelen Juwelen and horloges",
    "sg:phone":"+32 2 512 55 21",
    "sg:postcode":"1000",
    "sg:province":"Bruxelles-Capitale",
    "wof:name":"Maison Lagard\u00c8re",
    "wof:placetype":"venue"
},
  "geometry": {"coordinates":[4.3540658951,50.8492355347],"type":"Point"}
}