{
  "type": "Feature",
  "properties": {
    "iso:country":"BE",
    "sg:address":"Rue Du Luxembourg 4",
    "sg:city":"Hannut",
    "sg:orig_category":"Groenten and fruit Gh",
    "sg:phone":"+32 19 51 44 72",
    "sg:postcode":"4280",
    "sg:province":"Li\u00e8ge",
    "wof:name":"Hannut-fruit",
    "wof:placetype":"venue"
},
  "geometry": {"coordinates":[5.0868358612,50.6775016785],"type":"Point"}
}