{
  "type": "Feature",
  "properties": {
    "addr:full":"Rue De Lusambo 34a Bruxelles (forest) Bruxelles-Capitale 1190",
    "addr:housenumber":"34a",
    "addr:postcode":"1190",
    "addr:street":"Rue De Lusambo",
    "iso:country":"BE",
    "sg:address":"Rue De Lusambo 34a",
    "sg:city":"Bruxelles (forest)",
    "sg:classifiers":[
        {
            "category":"Home & Garden",
            "subcategory":"Building Materials",
            "type":"Retail Goods"
        }
    ],
    "sg:phone":"+32 2 332 03 80",
    "sg:postcode":"1190",
    "sg:province":"Bruxelles-Capitale",
    "sg:tags":[
        "cutting",
        "laser",
        "welding"
    ],
    "wof:name":"Metalpress Industrie Sa",
    "wof:placetype":"venue"
},
  "geometry": {"coordinates":[4.3134498596,50.8011016846],"type":"Point"}
}