{
  "type": "Feature",
  "properties": {
    "iso:country":"BE",
    "sg:address":"Staatsbaan 88",
    "sg:city":"Lanaken",
    "sg:classifiers":[
        {
            "category":"Fast Food",
            "type":"Food & Drink"
        }
    ],
    "sg:phone":"+32 89 71 59 56",
    "sg:postcode":"3620",
    "sg:province":"Limburg",
    "sg:tags":[
        "\u00c0",
        "emporter",
        "restaurants"
    ],
    "wof:name":"Frituur Modern",
    "wof:placetype":"venue"
},
  "geometry": {"coordinates":[5.6822190285,50.9120521545],"type":"Point"}
}