{
  "type": "Feature",
  "properties": {
    "addr:full":"Place De La Madeleine 7 Chatelet Hainaut 6200",
    "addr:housenumber":"7",
    "addr:postcode":"6200",
    "addr:street":"Place De La Madeleine;Hainaut",
    "iso:country":"BE",
    "sg:address":"Place De La Madeleine 7",
    "sg:city":"Chatelet",
    "sg:classifiers":[
        {
            "category":"Cafe",
            "type":"Food & Drink"
        }
    ],
    "sg:phone":"+32 71 38 11 74",
    "sg:postcode":"6200",
    "sg:province":"Hainaut",
    "sg:tags":[
        "caf\u00e9s"
    ],
    "wof:name":"Caf\u00c9 De La Madeleine",
    "wof:placetype":"venue"
},
  "geometry": {"coordinates":[4.5203638077,50.4134902954],"type":"Point"}
}