{
  "type": "Feature",
  "properties": {
    "iso:country":"BE",
    "sg:address":"Avenue George Henri 285",
    "sg:city":"Brussel/bruxelles",
    "sg:orig_category":"HERSTELLING ELEKTRISCHE HUISHOUDAPPARATEN Huishoudapparaten, televisies and radio's Telecommunicatie",
    "sg:phone":"+32 2 735 45 90",
    "sg:postcode":"1200",
    "sg:province":"Bruxelles-Capitale",
    "wof:name":"L'etoile",
    "wof:placetype":"venue"
},
  "geometry": {"coordinates":[4.4128379822,50.8437461853],"type":"Point"}
}