{
  "type": "Feature",
  "properties": {
    "addr:full":"Rue Henri Vandermaelen 40 Sint-pieters-woluwe/woluwe-saint-pierre Bruxelles-Capitale 1150",
    "addr:housenumber":"40",
    "addr:postcode":"1150",
    "addr:street":"Rue Henri Vandermaelen;/",
    "iso:country":"BE",
    "sg:address":"Rue Henri Vandermaelen 40",
    "sg:city":"Sint-pieters-woluwe/woluwe-saint-pierre",
    "sg:orig_category":"Experts-comptables",
    "sg:phone":"+32 2 772 91 37",
    "sg:postcode":"1150",
    "sg:province":"Bruxelles-Capitale",
    "wof:name":"Ferdinand Dubrule",
    "wof:placetype":"venue"
},
  "geometry": {"coordinates":[4.4616670609,50.841796875],"type":"Point"}
}