{
  "type": "Feature",
  "properties": {
    "addr:full":"Pottebezemstraat 16 Torhout West-Vlaanderen 8820",
    "addr:housenumber":"16",
    "addr:postcode":"8820",
    "addr:street":"Pottebezemstraat",
    "iso:country":"BE",
    "sg:address":"Pottebezemstraat 16",
    "sg:city":"Torhout",
    "sg:classifiers":[
        {
            "category":"Sports & Exercise",
            "subcategory":"Stables",
            "type":"Entertainment"
        }
    ],
    "sg:phone":"+32 50 21 33 49",
    "sg:postcode":"8820",
    "sg:province":"West-Vlaanderen",
    "sg:tags":[
        "riding",
        "school"
    ],
    "wof:name":"Stoeterij Deloof Bvba",
    "wof:placetype":"venue"
},
  "geometry": {"coordinates":[3.1188600063,51.0830841064],"type":"Point"}
}