{
  "type": "Feature",
  "properties": {
    "iso:country":"BE",
    "sg:address":"Zeelaan 158b501",
    "sg:city":"Koksijde",
    "sg:orig_category":"Schoonmaakbedrijven and ongediertebestrijding",
    "sg:phone":"+32 58 51 76 48",
    "sg:postcode":"8670",
    "sg:province":"West-Vlaanderen",
    "wof:name":"Eddy Verpoest",
    "wof:placetype":"venue"
},
  "geometry": {"coordinates":[2.6403648853,51.1143074036],"type":"Point"}
}