{
  "type": "Feature",
  "properties": {
    "addr:full":"Avenue Carton De Wiart 81 Jette/jette Bruxelles-Capitale 1090",
    "addr:housenumber":"81",
    "addr:postcode":"1090",
    "addr:street":"Avenue Carton De Wiart",
    "iso:country":"BE",
    "sg:address":"Avenue Carton De Wiart 81",
    "sg:city":"Jette/jette",
    "sg:orig_category":"Studios photographiques",
    "sg:phone":"+32 2 428 14 08",
    "sg:postcode":"1090",
    "sg:province":"Bruxelles-Capitale",
    "wof:name":"Francois Belvaux Thibault",
    "wof:placetype":"venue"
},
  "geometry": {"coordinates":[4.3296790123,50.8678627014],"type":"Point"}
}