{
  "type": "Feature",
  "properties": {
    "iso:country":"BE",
    "sg:address":"Hazelaarstraat 8",
    "sg:city":"Kortrijk",
    "sg:classifiers":[
        {
            "category":"Bars & Pubs",
            "type":"Food & Drink"
        }
    ],
    "sg:phone":"+32 56 22 20 69",
    "sg:postcode":"8500",
    "sg:province":"West-Vlaanderen",
    "wof:name":"Caf\u00e9 Des Arts",
    "wof:placetype":"venue"
},
  "geometry": {"coordinates":[3.2652869225,50.8260688782],"type":"Point"}
}