{
  "type": "Feature",
  "properties": {
    "addr:full":"Sparrenlaan 16 Vosselaar Antwerpen 2350",
    "addr:housenumber":"16",
    "addr:postcode":"2350",
    "addr:street":"Sparrenlaan",
    "iso:country":"BE",
    "sg:address":"Sparrenlaan 16",
    "sg:city":"Vosselaar",
    "sg:classifiers":[
        {
            "category":"Real Estate",
            "subcategory":"Architect",
            "type":"Services"
        }
    ],
    "sg:phone":"+32 14 61 38 51",
    "sg:postcode":"2350",
    "sg:province":"Antwerpen",
    "wof:name":"Sysmans E",
    "wof:placetype":"venue"
},
  "geometry": {"coordinates":[4.8859510422,51.3162765503],"type":"Point"}
}