{
  "type": "Feature",
  "properties": {
    "addr:full":"All\u00c9e Dubois 19 Chaudfontaine Li\u00e8ge 4052",
    "addr:housenumber":"19",
    "addr:postcode":"4052",
    "addr:street":"Alle\u0301E Dubois",
    "iso:country":"BE",
    "sg:address":"All\u00c9e Dubois 19",
    "sg:city":"Chaudfontaine",
    "sg:orig_category":"Artiesten and kunstenaars",
    "sg:phone":"+32 4 368 84 60",
    "sg:postcode":"4052",
    "sg:province":"Li\u00e8ge",
    "wof:name":"Jean Dupont",
    "wof:placetype":"venue"
},
  "geometry": {"coordinates":[5.6392202377,50.5586051941],"type":"Point"}
}