{
  "type": "Feature",
  "properties": {
    "addr:full":"Neerstraat 1 Roeselare (rumbeke) West-Vlaanderen 8800",
    "addr:housenumber":"1",
    "addr:postcode":"8800",
    "addr:street":"Neerstraat",
    "iso:country":"BE",
    "sg:address":"Neerstraat 1",
    "sg:city":"Roeselare (rumbeke)",
    "sg:classifiers":[
        {
            "category":"Health Services",
            "subcategory":"Doctor",
            "type":"Services"
        }
    ],
    "sg:phone":"+32 51 21 02 49",
    "sg:postcode":"8800",
    "sg:province":"West-Vlaanderen",
    "sg:tags":[
        "medicinephysicians",
        "surgeon"
    ],
    "wof:name":"Deruytter Marc",
    "wof:placetype":"venue"
},
  "geometry": {"coordinates":[3.122740984,50.925819397],"type":"Point"}
}