{
  "type": "Feature",
  "properties": {
    "iso:country":"BE",
    "sg:address":"Rue Puits-en-sock 34-36",
    "sg:city":"Li\u00e8ge 1 (li\u00e8ge 2)",
    "sg:classifiers":[
        {
            "category":"Autos & Motor Vehicles",
            "subcategory":"Fuel & Gas Station",
            "type":"Retail Goods"
        }
    ],
    "sg:phone":"+32 4 343 52 41",
    "sg:postcode":"4020",
    "sg:province":"Li\u00e8ge",
    "sg:tags":[
        "repair",
        "drier",
        "laundry",
        "-",
        "machine",
        "mainten",
        "washing",
        "automatic"
    ],
    "wof:name":"Olivier",
    "wof:placetype":"venue"
},
  "geometry": {"coordinates":[5.5827898979,50.6405754089],"type":"Point"}
}