{
  "type": "Feature",
  "properties": {
    "iso:country":"BE",
    "sg:address":"Rue Des Brasseurs 6",
    "sg:city":"Chatelet",
    "sg:orig_category":"Fleurs and plantes",
    "sg:phone":"+32 71 38 23 09",
    "sg:postcode":"6200",
    "sg:province":"Hainaut",
    "wof:name":"Fleurs Carine Quisenaire",
    "wof:placetype":"venue"
},
  "geometry": {"coordinates":[4.5202522278,50.4039497375],"type":"Point"}
}