{
  "type": "Feature",
  "properties": {
    "addr:full":"Rue Porte De Li\u00c8ge 59ba Waremme Li\u00e8ge 4300",
    "addr:housenumber":"59ba",
    "addr:postcode":"4300",
    "addr:street":"Rue Porte De Lie\u0300Ge",
    "iso:country":"BE",
    "sg:address":"Rue Porte De Li\u00c8ge 59ba",
    "sg:city":"Waremme",
    "sg:classifiers":[
        {
            "category":"Food & Beverages",
            "subcategory":"Fruits & Vegetables",
            "type":"Retail Goods"
        }
    ],
    "sg:phone":"+32 19 33 15 24",
    "sg:postcode":"4300",
    "sg:province":"Li\u00e8ge",
    "sg:tags":[
        "groenten"
    ],
    "wof:name":"Maison A Croquer",
    "wof:placetype":"venue"
},
  "geometry": {"coordinates":[5.261177063,50.697933197],"type":"Point"}
}