{
  "type": "Feature",
  "properties": {
    "iso:country":"BE",
    "sg:address":"Gebr.van Raemdonckstraat 30",
    "sg:city":"Roeselare",
    "sg:orig_category":"Woningbouw",
    "sg:phone":"+32 51 21 09 52",
    "sg:postcode":"8800",
    "sg:province":"West-Vlaanderen",
    "wof:name":"Bincquet Koen",
    "wof:placetype":"venue"
},
  "geometry": {"coordinates":[3.1664569378,50.9282035828],"type":"Point"}
}