{
  "type": "Feature",
  "properties": {
    "addr:full":"Stalpaertstraat 7 Koekelare West-Vlaanderen 8680",
    "addr:housenumber":"7",
    "addr:postcode":"8680",
    "addr:street":"Stalpaertstraat",
    "iso:country":"BE",
    "sg:address":"Stalpaertstraat 7",
    "sg:city":"Koekelare",
    "sg:classifiers":[
        {
            "category":"Home & Garden",
            "subcategory":"Building Materials",
            "type":"Retail Goods"
        }
    ],
    "sg:phone":"+32 51 58 40 81",
    "sg:postcode":"8680",
    "sg:province":"West-Vlaanderen",
    "sg:tags":[
        "cutting",
        "laser",
        "welding"
    ],
    "wof:name":"A P R-aquacutting Bvba",
    "wof:placetype":"venue"
},
  "geometry": {"coordinates":[2.9668440819,51.091583252],"type":"Point"}
}