{
  "type": "Feature",
  "properties": {
    "addr:full":"Bld De La Sauveni\u00c8re 138 Li\u00c8ge Li\u00e8ge 4000",
    "addr:housenumber":"138",
    "addr:postcode":"4000",
    "addr:street":"Bld De La Sauvenie\u0300Re",
    "iso:country":"BE",
    "sg:address":"Bld De La Sauveni\u00c8re 138",
    "sg:city":"Li\u00c8ge",
    "sg:orig_category":"Tijdelijke werkgelegenheid and uitzendkantoren",
    "sg:phone":"+32 4 223 01 91",
    "sg:postcode":"4000",
    "sg:province":"Li\u00e8ge",
    "wof:name":"Daoust Int\u00c9rim",
    "wof:placetype":"venue"
},
  "geometry": {"coordinates":[5.5669789314,50.6413116455],"type":"Point"}
}