{
  "type": "Feature",
  "properties": {
    "iso:country":"BE",
    "sg:address":"Avenue De La Constitution 78",
    "sg:city":"Bruxelles (jette)",
    "sg:classifiers":[
        {
            "category":"Professional",
            "subcategory":"Advertising",
            "type":"Services"
        }
    ],
    "sg:phone":"+32 2 420 42 24",
    "sg:postcode":"1090",
    "sg:province":"Bruxelles-Capitale",
    "sg:tags":[
        "photography"
    ],
    "wof:name":"Philippe Dijkmans Photography Sprl",
    "wof:placetype":"venue"
},
  "geometry": {"coordinates":[4.3235778809,50.8682022095],"type":"Point"}
}