{
  "type": "Feature",
  "properties": {
    "addr:full":"Herentalsebaan 127b1 Antwerpen Antwerpen 2100",
    "addr:housenumber":"127b1",
    "addr:postcode":"2100",
    "addr:street":"Herentalsebaan",
    "iso:country":"BE",
    "sg:address":"Herentalsebaan 127b1",
    "sg:city":"Antwerpen",
    "sg:classifiers":[
        {
            "category":"Arena",
            "subcategory":"Sports Club",
            "type":"Entertainment"
        }
    ],
    "sg:phone":"+32 3 237 04 38",
    "sg:postcode":"2100",
    "sg:province":"Antwerpen",
    "sg:tags":[
        "de"
    ],
    "wof:name":"B.c. Anehta",
    "wof:placetype":"venue"
},
  "geometry": {"coordinates":[4.4586100578,51.2203941345],"type":"Point"}
}