{
  "type": "Feature",
  "properties": {
    "iso:country":"BE",
    "sg:address":"Rue Longue Hayoulle 5",
    "sg:city":"Fleron",
    "sg:orig_category":"Installatie van houten of kunststof schrijnwerk",
    "sg:phone":"+32 4 385 23 44",
    "sg:postcode":"4620",
    "sg:province":"Li\u00e8ge",
    "wof:name":"Bati-concept",
    "wof:placetype":"venue"
},
  "geometry": {"coordinates":[5.6874217987,50.6105804443],"type":"Point"}
}