{
  "type": "Feature",
  "properties": {
    "addr:full":"Bogaardestraat 228bb Maldegem Oost-Vlaanderen 9990",
    "addr:housenumber":"228bb",
    "addr:postcode":"9990",
    "addr:street":"Bogaardestraat",
    "iso:country":"BE",
    "sg:address":"Bogaardestraat 228bb",
    "sg:city":"Maldegem",
    "sg:orig_category":"Matelas Fab",
    "sg:phone":"+32 50 71 36 11",
    "sg:postcode":"9990",
    "sg:province":"Oost-Vlaanderen",
    "wof:name":"L S Industries",
    "wof:placetype":"venue"
},
  "geometry": {"coordinates":[3.4317169189,51.1991996765],"type":"Point"}
}