{
  "type": "Feature",
  "properties": {
    "addr:full":"Kieksbroek 23 Antwerpen Antwerpen 2020",
    "addr:housenumber":"23",
    "addr:postcode":"2020",
    "addr:street":"Kieksbroek",
    "iso:country":"BE",
    "sg:address":"Kieksbroek 23",
    "sg:city":"Antwerpen",
    "sg:orig_category":"Poissonniers and \u00e9caillers. Commerces alimentaires sp\u00e9cialis\u00e9s Gr",
    "sg:phone":"+32 3 238 47 89",
    "sg:postcode":"2020",
    "sg:province":"Antwerpen",
    "wof:name":"Mosselhandel Bart",
    "wof:placetype":"venue"
},
  "geometry": {"coordinates":[4.3810501099,51.1914710999],"type":"Point"}
}