{
  "type": "Feature",
  "properties": {
    "iso:country":"BE",
    "sg:address":"Molenstraat 2",
    "sg:city":"Galmaarden",
    "sg:orig_category":"Herstellingen and onderhoud van auto's",
    "sg:phone":"+32 54 56 61 36",
    "sg:postcode":"1570",
    "sg:province":"Vlaams-Brabant",
    "wof:name":"Garage Boone",
    "wof:placetype":"venue"
},
  "geometry": {"coordinates":[4.0276942253,50.7663917542],"type":"Point"}
}