{
  "type": "Feature",
  "properties": {
    "addr:full":"Oosterwijkseweg 8 Olen Antwerpen 2250",
    "addr:housenumber":"8",
    "addr:postcode":"2250",
    "addr:street":"Oosterwijkseweg",
    "iso:country":"BE",
    "sg:address":"Oosterwijkseweg 8",
    "sg:city":"Olen",
    "sg:orig_category":"Banken and kredietinstellingen Verzekeringsmakelaars and experts",
    "sg:phone":"+32 14 26 55 55",
    "sg:postcode":"2250",
    "sg:province":"Antwerpen",
    "wof:name":"Anhyp",
    "wof:placetype":"venue"
},
  "geometry": {"coordinates":[4.8602528572,51.1424293518],"type":"Point"}
}