{
  "type": "Feature",
  "properties": {
    "addr:full":"Rue Jacquet 61 Rochefort Namur 5560",
    "addr:housenumber":"61",
    "addr:postcode":"5560",
    "addr:street":"Rue Jacquet",
    "iso:country":"BE",
    "sg:address":"Rue Jacquet 61",
    "sg:city":"Rochefort",
    "sg:orig_category":"Pensions de famille",
    "sg:phone":"+32 84 21 08 52",
    "sg:postcode":"5560",
    "sg:province":"Namur",
    "wof:name":"Le Vieux Carmel",
    "wof:placetype":"venue"
},
  "geometry": {"coordinates":[5.2220931053,50.1548309326],"type":"Point"}
}