{
  "type": "Feature",
  "properties": {
    "addr:full":"Chauss\u00c9e D'alsemberg 806 Ukkel/uccle Bruxelles-Capitale 1180",
    "addr:housenumber":"806",
    "addr:postcode":"1180",
    "addr:street":"Chausse\u0301E D'Alsemberg;/",
    "iso:country":"BE",
    "sg:address":"Chauss\u00c9e D'alsemberg 806",
    "sg:city":"Ukkel/uccle",
    "sg:orig_category":"Secr\u00e9tariats",
    "sg:phone":"+32 2 332 14 14",
    "sg:postcode":"1180",
    "sg:province":"Bruxelles-Capitale",
    "wof:name":"A.p. Diffusion",
    "wof:placetype":"venue"
},
  "geometry": {"coordinates":[4.3365111351,50.7981414795],"type":"Point"}
}