{
  "type": "Feature",
  "properties": {
    "addr:full":"Kehrweg 53 Eupen Li\u00e8ge 4700",
    "addr:housenumber":"53",
    "addr:postcode":"4700",
    "addr:street":"Kehrweg",
    "iso:country":"BE",
    "sg:address":"Kehrweg 53",
    "sg:city":"Eupen",
    "sg:classifiers":[
        {
            "category":"Communications",
            "type":"Services"
        }
    ],
    "sg:phone":"+32 87 55 79 16",
    "sg:postcode":"4700",
    "sg:province":"Li\u00e8ge",
    "sg:tags":[
        "translator"
    ],
    "wof:name":"Vandriessche D",
    "wof:placetype":"venue"
},
  "geometry": {"coordinates":[6.0510311127,50.6216163635],"type":"Point"}
}