{
  "type": "Feature",
  "properties": {
    "iso:country":"BE",
    "sg:address":"Schaatbroekstraat 12",
    "sg:city":"Overijse",
    "sg:orig_category":"Advocaten and juridische adviseurs",
    "sg:phone":"+32 475 51 38 17",
    "sg:postcode":"3090",
    "sg:province":"Vlaams-Brabant",
    "wof:name":"Josette Peeters",
    "wof:placetype":"venue"
},
  "geometry": {"coordinates":[4.5872631073,50.7639160156],"type":"Point"}
}