{
  "type": "Feature",
  "properties": {
    "iso:country":"BE",
    "sg:address":"Postbus 156",
    "sg:city":"Zaventem1",
    "sg:classifiers":[
        {
            "category":"Manufacturing",
            "subcategory":"Aerospace",
            "type":"Manufacturing & Wholesale Goods"
        }
    ],
    "sg:phone":"+32 2 725 33 77",
    "sg:postcode":"1930",
    "sg:province":"Vlaams-Brabant",
    "sg:tags":[
        "equipment",
        "airplane"
    ],
    "wof:name":"European Air Support Sa",
    "wof:placetype":"venue"
},
  "geometry": {"coordinates":[4.3534531593,50.8516769409],"type":"Point"}
}