{
  "type": "Feature",
  "properties": {
    "addr:full":"Rue P\u00c9pin 15 Pepinster Li\u00e8ge 4860",
    "addr:housenumber":"15",
    "addr:postcode":"4860",
    "addr:street":"Rue Pe\u0301Pin",
    "iso:country":"BE",
    "sg:address":"Rue P\u00c9pin 15",
    "sg:city":"Pepinster",
    "sg:orig_category":"Banken and kredietinstellingen",
    "sg:phone":"+32 87 46 01 81",
    "sg:postcode":"4860",
    "sg:province":"Li\u00e8ge",
    "wof:name":"Ippa",
    "wof:placetype":"venue"
},
  "geometry": {"coordinates":[5.8038802147,50.5671615601],"type":"Point"}
}