{
  "type": "Feature",
  "properties": {
    "addr:full":"Speystraat 2 Damme West-Vlaanderen 8340",
    "addr:housenumber":"2",
    "addr:postcode":"8340",
    "addr:street":"Speystraat",
    "iso:country":"BE",
    "sg:address":"Speystraat 2",
    "sg:city":"Damme",
    "sg:orig_category":"Enseignement maternel and primaire",
    "sg:phone":"+32 50 35 68 97",
    "sg:postcode":"8340",
    "sg:province":"West-Vlaanderen",
    "wof:name":"Gemeentelijke Basisschool",
    "wof:placetype":"venue"
},
  "geometry": {"coordinates":[3.2813529968,51.2521247864],"type":"Point"}
}