{
  "type": "Feature",
  "properties": {
    "iso:country":"BE",
    "sg:address":"Chauss\u00c9e De Dinant 27b5",
    "sg:city":"Anhee",
    "sg:classifiers":[
        {
            "category":"Arena",
            "subcategory":"Sports Club",
            "type":"Entertainment"
        }
    ],
    "sg:phone":"+32 82 61 12 01",
    "sg:postcode":"5537",
    "sg:province":"Namur",
    "sg:tags":[
        "terrain",
        "hors",
        "de",
        "installation",
        "sportifs"
    ],
    "wof:name":"R.c.s. Ent. Mosane",
    "wof:placetype":"venue"
},
  "geometry": {"coordinates":[4.8821730614,50.3072280884],"type":"Point"}
}