{
  "type": "Feature",
  "properties": {
    "addr:full":"Overheulestraat 87 Wevelgem (moorsele) West-Vlaanderen 8560",
    "addr:housenumber":"87",
    "addr:postcode":"8560",
    "addr:street":"Overheulestraat",
    "iso:country":"BE",
    "sg:address":"Overheulestraat 87",
    "sg:city":"Wevelgem (moorsele)",
    "sg:classifiers":[
        {
            "category":"Retail",
            "subcategory":"Auto Repair",
            "type":"Services"
        }
    ],
    "sg:phone":"+32 56 41 24 13",
    "sg:postcode":"8560",
    "sg:province":"West-Vlaanderen",
    "sg:tags":[
        "garage"
    ],
    "wof:name":"Vandewalle",
    "wof:placetype":"venue"
},
  "geometry": {"coordinates":[3.1643669605,50.8438491821],"type":"Point"}
}