{
  "type": "Feature",
  "properties": {
    "iso:country":"BE",
    "sg:address":"Gebroeders Tassetstraat 54",
    "sg:city":"Leuven (wijgmaal)",
    "sg:classifiers":[
        {
            "category":"Professional",
            "subcategory":"Accounting & Tax Preparation",
            "type":"Services"
        }
    ],
    "sg:phone":"+32 16 89 51 48",
    "sg:postcode":"3018",
    "sg:province":"Vlaams-Brabant",
    "sg:tags":[
        "bookkeeper"
    ],
    "wof:name":"Van Moere S",
    "wof:placetype":"venue"
},
  "geometry": {"coordinates":[4.6962218285,50.9246635437],"type":"Point"}
}