{
  "type": "Feature",
  "properties": {
    "addr:full":"24 Bd Du Souverain Bruxelles Bruxelles-Capitale 1170",
    "addr:housenumber":"24",
    "addr:postcode":"1170",
    "addr:street":"Bd Du Souverain",
    "iso:country":"BE",
    "sg:address":"24 Bd Du Souverain",
    "sg:city":"Bruxelles",
    "sg:classifiers":[
        {
            "category":"Shopping",
            "subcategory":"Gifts & Souvenirs",
            "type":"Retail Goods"
        }
    ],
    "sg:phone":"+32 2 674 18 11",
    "sg:postcode":"1170",
    "sg:province":"Bruxelles-Capitale",
    "sg:tags":[
        "product",
        "miscellaneous"
    ],
    "wof:name":"Philip Morris Belgium Sa",
    "wof:placetype":"venue"
},
  "geometry": {"coordinates":[4.4268651009,50.8100204468],"type":"Point"}
}