{
  "type": "Feature",
  "properties": {
    "iso:country":"BE",
    "sg:address":"Boombekelaan 14",
    "sg:city":"Hoboken",
    "sg:classifiers":[
        {
            "category":"Utilities",
            "subcategory":"Telephone",
            "type":"Services"
        }
    ],
    "sg:phone":"+32 3 820 02 00",
    "sg:postcode":"2660",
    "sg:province":"Antwerpen",
    "sg:tags":[
        "telecommunication"
    ],
    "wof:name":"Interkommunale Voor Teledistributie Van Het Gewest A Cvba",
    "wof:placetype":"venue"
},
  "geometry": {"coordinates":[4.339430809,51.1795082092],"type":"Point"}
}