{
  "type": "Feature",
  "properties": {
    "addr:full":"Industriezone 23 Ronse Oost-Vlaanderen 9600",
    "addr:housenumber":"23",
    "addr:postcode":"9600",
    "addr:street":"Industriezone",
    "iso:country":"BE",
    "sg:address":"Industriezone 23",
    "sg:city":"Ronse",
    "sg:classifiers":[
        {
            "category":"Manufacturing",
            "subcategory":"Chemicals & Compounds",
            "type":"Manufacturing & Wholesale Goods"
        }
    ],
    "sg:phone":"+32 55 23 51 51",
    "sg:postcode":"9600",
    "sg:province":"Oost-Vlaanderen",
    "sg:tags":[
        "pharmaceutical",
        "chemistry",
        "-",
        "by-product"
    ],
    "wof:name":"Ideal Tape Incorporate",
    "wof:placetype":"venue"
},
  "geometry": {"coordinates":[3.5993049145,50.7470397949],"type":"Point"}
}