{
  "type": "Feature",
  "properties": {
    "addr:full":"Dorpstraat 74 Zwijndrecht Antwerpen 2070",
    "addr:housenumber":"74",
    "addr:postcode":"2070",
    "addr:street":"Dorpstraat",
    "iso:country":"BE",
    "sg:address":"Dorpstraat 74",
    "sg:city":"Zwijndrecht",
    "sg:orig_category":"Pain, p\u00e2tisseries and confiseries",
    "sg:phone":"+32 3 252 70 28",
    "sg:postcode":"2070",
    "sg:province":"Antwerpen",
    "wof:name":"H En G Van Brempt",
    "wof:placetype":"venue"
},
  "geometry": {"coordinates":[4.3433389664,51.2020606995],"type":"Point"}
}