{
  "type": "Feature",
  "properties": {
    "addr:full":"Waterbossen 11 Londerzeel (malderen) Vlaams-Brabant 1840",
    "addr:housenumber":"11",
    "addr:postcode":"1840",
    "addr:street":"Waterbossen",
    "iso:country":"BE",
    "sg:address":"Waterbossen 11",
    "sg:city":"Londerzeel (malderen)",
    "sg:classifiers":[
        {
            "category":"Banks & Credit Unions",
            "subcategory":"Investment Brokerage",
            "type":"Services"
        }
    ],
    "sg:phone":"+32 52 30 20 59",
    "sg:postcode":"1840",
    "sg:province":"Vlaams-Brabant",
    "wof:name":"Mavico Investments Nv",
    "wof:placetype":"venue"
},
  "geometry": {"coordinates":[4.258658886,51.0148391724],"type":"Point"}
}