{
  "type": "Feature",
  "properties": {
    "iso:country":"BE",
    "sg:address":"Rue De Herve 558",
    "sg:city":"Beyne-heusay",
    "sg:orig_category":"Elektrische installaties voor woningen",
    "sg:phone":"+32 4 367 25 58",
    "sg:postcode":"4610",
    "sg:province":"Li\u00e8ge",
    "wof:name":"Alain Richl",
    "wof:placetype":"venue"
},
  "geometry": {"coordinates":[5.6398839951,50.6262512207],"type":"Point"}
}