{
  "type": "Feature",
  "properties": {
    "iso:country":"BE",
    "sg:address":"Clos Sainte Rita 11",
    "sg:city":"Braine-l`alleud",
    "sg:orig_category":"Software ontwikkeling and ontwerp",
    "sg:phone":"+32 2 384 85 78",
    "sg:postcode":"1420",
    "sg:province":"Brabant Wallon",
    "wof:name":"Belcentre Design",
    "wof:placetype":"venue"
},
  "geometry": {"coordinates":[5.8036999702,45.9799995422],"type":"Point"}
}