{
  "type": "Feature",
  "properties": {
    "iso:country":"BE",
    "sg:address":"Rue Du Moulin 213",
    "sg:city":"Ohey",
    "sg:orig_category":"Landbouwmachines Gh",
    "sg:phone":"+32 85 61 16 10",
    "sg:postcode":"5350",
    "sg:province":"Namur",
    "wof:name":"Julien Besure",
    "wof:placetype":"venue"
},
  "geometry": {"coordinates":[5.1247210503,50.4356460571],"type":"Point"}
}