{
  "type": "Feature",
  "properties": {
    "iso:country":"BE",
    "sg:address":"Westerlosesteenweg 173",
    "sg:city":"Herselt",
    "sg:classifiers":[
        {
            "category":"Restaurant",
            "type":"Food & Drink"
        }
    ],
    "sg:phone":"+32 14 54 11 16",
    "sg:postcode":"2230",
    "sg:province":"Antwerpen",
    "wof:name":"Castel",
    "wof:placetype":"venue"
},
  "geometry": {"coordinates":[4.8923602104,51.0659103394],"type":"Point"}
}