{
  "type": "Feature",
  "properties": {
    "iso:country":"BE",
    "sg:address":"Rue Du Nouveau Si\u00e8ge 36",
    "sg:city":"Herstal (milmort)",
    "sg:classifiers":[
        {
            "category":"Personal",
            "subcategory":"Beauty Salon",
            "type":"Services"
        }
    ],
    "sg:phone":"+32 4 278 42 28",
    "sg:postcode":"4041",
    "sg:province":"Li\u00e8ge",
    "sg:tags":[
        "lady",
        "-",
        "hairdressing"
    ],
    "wof:name":"Daphn\u00e9 Coiffure",
    "wof:placetype":"venue"
},
  "geometry": {"coordinates":[5.5997672081,50.6855773926],"type":"Point"}
}