{
  "type": "Feature",
  "properties": {
    "addr:full":"Koningstraat 14 Menen West-Vlaanderen 8930",
    "addr:housenumber":"14",
    "addr:postcode":"8930",
    "addr:street":"Koningstraat",
    "iso:country":"BE",
    "sg:address":"Koningstraat 14",
    "sg:city":"Menen",
    "sg:classifiers":[
        {
            "category":"Social Services",
            "type":"Services"
        }
    ],
    "sg:phone":"+32 56 51 01 90",
    "sg:postcode":"8930",
    "sg:province":"West-Vlaanderen",
    "wof:name":"Werkwinkel",
    "wof:placetype":"venue"
},
  "geometry": {"coordinates":[3.1190259457,50.7969055176],"type":"Point"}
}