{
  "type": "Feature",
  "properties": {
    "addr:full":"Stationsstraat 36 Haaltert Oost-Vlaanderen 9450",
    "addr:housenumber":"36",
    "addr:postcode":"9450",
    "addr:street":"Stationsstraat",
    "iso:country":"BE",
    "sg:address":"Stationsstraat 36",
    "sg:city":"Haaltert",
    "sg:orig_category":"Landmeters and schatters",
    "sg:phone":"+32 53 83 12 94",
    "sg:postcode":"9450",
    "sg:province":"Oost-Vlaanderen",
    "wof:name":"Bureau Deruwe Hein",
    "wof:placetype":"venue"
},
  "geometry": {"coordinates":[4.0092391968,50.9021987915],"type":"Point"}
}