{
  "type": "Feature",
  "properties": {
    "addr:full":"Vinkestraat 65 Wevelgem West-Vlaanderen 8560",
    "addr:housenumber":"65",
    "addr:postcode":"8560",
    "addr:street":"Vinkestraat",
    "iso:country":"BE",
    "sg:address":"Vinkestraat 65",
    "sg:city":"Wevelgem",
    "sg:classifiers":[
        {
            "category":"Home & Garden",
            "subcategory":"Home Furnishings",
            "type":"Retail Goods"
        }
    ],
    "sg:phone":"+32 56 40 33 54",
    "sg:postcode":"8560",
    "sg:province":"West-Vlaanderen",
    "sg:tags":[
        "interior",
        "decoration"
    ],
    "wof:name":"Verfaillie L",
    "wof:placetype":"venue"
},
  "geometry": {"coordinates":[3.181677103,50.8214759827],"type":"Point"}
}