{
  "type": "Feature",
  "properties": {
    "iso:country":"BE",
    "sg:address":"Chauss\u00e9e De La Hulpe 61",
    "sg:city":"Bruxelles (uccle)",
    "sg:classifiers":[
        {
            "category":"Organizations",
            "subcategory":"Community Association",
            "type":"Services"
        }
    ],
    "sg:phone":"+32 2 673 35 04",
    "sg:postcode":"1180",
    "sg:province":"Bruxelles-Capitale",
    "sg:tags":[
        "cultural"
    ],
    "wof:name":"International Menuhin Association",
    "wof:placetype":"venue"
},
  "geometry": {"coordinates":[4.3994059563,50.7963523865],"type":"Point"}
}