{
  "type": "Feature",
  "properties": {
    "addr:full":"Gentstraat 58 Meulebeke West-Vlaanderen 8760",
    "addr:housenumber":"58",
    "addr:postcode":"8760",
    "addr:street":"Gentstraat",
    "iso:country":"BE",
    "sg:address":"Gentstraat 58",
    "sg:city":"Meulebeke",
    "sg:classifiers":[
        {
            "category":"Utilities",
            "subcategory":"Recycling",
            "type":"Services"
        }
    ],
    "sg:phone":"+32 51 33 50 60",
    "sg:postcode":"8760",
    "sg:province":"West-Vlaanderen",
    "sg:tags":[
        "plastic"
    ],
    "wof:name":"Matco Nv",
    "wof:placetype":"venue"
},
  "geometry": {"coordinates":[3.2964498997,50.9478607178],"type":"Point"}
}