{
  "type": "Feature",
  "properties": {
    "addr:full":"Hofkwartier 4 Herentals Antwerpen 2200",
    "addr:housenumber":"4",
    "addr:postcode":"2200",
    "addr:street":"Hofkwartier",
    "iso:country":"BE",
    "sg:address":"Hofkwartier 4",
    "sg:city":"Herentals",
    "sg:classifiers":[
        {
            "category":"Shopping",
            "subcategory":"Clothing, Apparel, & Fashions",
            "type":"Retail Goods"
        }
    ],
    "sg:phone":"+32 14 22 50 03",
    "sg:postcode":"2200",
    "sg:province":"Antwerpen",
    "sg:tags":[
        "v\u00eatements",
        "pour",
        "dame"
    ],
    "wof:name":"Jessie",
    "wof:placetype":"venue"
},
  "geometry": {"coordinates":[4.8359289169,51.1781196594],"type":"Point"}
}