{
  "type": "Feature",
  "properties": {
    "addr:full":"Korte Trieststraat 1bb Aalst Oost-Vlaanderen 9310",
    "addr:housenumber":"1bb",
    "addr:postcode":"9310",
    "addr:street":"Korte Trieststraat",
    "iso:country":"BE",
    "sg:address":"Korte Trieststraat 1bb",
    "sg:city":"Aalst",
    "sg:orig_category":"Woningbouw",
    "sg:phone":"+32 53 21 23 00",
    "sg:postcode":"9310",
    "sg:province":"Oost-Vlaanderen",
    "wof:name":"Redant",
    "wof:placetype":"venue"
},
  "geometry": {"coordinates":[4.1088018417,50.9706115723],"type":"Point"}
}