{
  "type": "Feature",
  "properties": {
    "iso:country":"BE",
    "sg:address":"Rue Du Corbeau 40",
    "sg:city":"Ch\u00e2telet (ch\u00e2telineau)",
    "sg:classifiers":[
        {
            "category":"Personal",
            "subcategory":"Barber",
            "type":"Services"
        }
    ],
    "sg:phone":"+32 71 39 83 59",
    "sg:postcode":"6200",
    "sg:province":"Hainaut",
    "sg:tags":[
        "gentleman",
        "salon",
        "-",
        "hairdressing"
    ],
    "wof:name":"Gillet M",
    "wof:placetype":"venue"
},
  "geometry": {"coordinates":[4.4921908379,50.4113845825],"type":"Point"}
}