{
  "type": "Feature",
  "properties": {
    "iso:country":"BE",
    "sg:address":"Oudedijk 26",
    "sg:city":"Turnhout",
    "sg:orig_category":"Advocaten and juridische adviseurs",
    "sg:phone":"+32 14 42 02 18",
    "sg:postcode":"2300",
    "sg:province":"Antwerpen",
    "wof:name":"Kirsten Thijs",
    "wof:placetype":"venue"
},
  "geometry": {"coordinates":[4.9609651566,51.313369751],"type":"Point"}
}