{
  "type": "Feature",
  "properties": {
    "iso:country":"BE",
    "sg:address":"Koningin Astridlaan 10",
    "sg:city":"Neerpelt",
    "sg:classifiers":[
        {
            "category":"Cafe",
            "type":"Food & Drink"
        }
    ],
    "sg:phone":"+32 11 64 47 59",
    "sg:postcode":"3910",
    "sg:province":"Limburg",
    "sg:tags":[
        "caf\u00e9s"
    ],
    "wof:name":"Johannes Meusen",
    "wof:placetype":"venue"
},
  "geometry": {"coordinates":[5.4269018173,51.2307243347],"type":"Point"}
}