{
  "type": "Feature",
  "properties": {
    "addr:full":"Hondiuslaan 42 Duffel Antwerpen 2570",
    "addr:housenumber":"42",
    "addr:postcode":"2570",
    "addr:street":"Hondiuslaan",
    "iso:country":"BE",
    "sg:address":"Hondiuslaan 42",
    "sg:city":"Duffel",
    "sg:classifiers":[
        {
            "category":"Arena",
            "subcategory":"Sports Club",
            "type":"Entertainment"
        }
    ],
    "sg:phone":"+32 15 31 56 49",
    "sg:postcode":"2570",
    "sg:province":"Antwerpen",
    "sg:tags":[
        "installation",
        "sportifs",
        "de",
        "terrain",
        "hors",
        "caf\u00e9s"
    ],
    "wof:name":"K.f.c. Duffel",
    "wof:placetype":"venue"
},
  "geometry": {"coordinates":[4.5012311935,51.0929145813],"type":"Point"}
}