{
  "type": "Feature",
  "properties": {
    "iso:country":"BE",
    "sg:address":"Avenue Du Destrier 24",
    "sg:city":"Evere/evere",
    "sg:orig_category":"Location de logements sociaux",
    "sg:phone":"+32 2 705 20 89",
    "sg:postcode":"1140",
    "sg:province":"Bruxelles-Capitale",
    "wof:name":"Brussels Thuis",
    "wof:placetype":"venue"
},
  "geometry": {"coordinates":[4.4094228745,50.8584938049],"type":"Point"}
}