{
  "type": "Feature",
  "properties": {
    "iso:country":"BE",
    "sg:address":"Duivenstraat 5",
    "sg:city":"Vosselaar",
    "sg:orig_category":"Fa\u00e7ade covering",
    "sg:phone":"+32 14 61 43 75",
    "sg:postcode":"2350",
    "sg:province":"Antwerpen",
    "wof:name":"Jvg",
    "wof:placetype":"venue"
},
  "geometry": {"coordinates":[4.8842468262,51.3019676208],"type":"Point"}
}