{
  "type": "Feature",
  "properties": {
    "addr:full":"Moeskroenstraat 677 Menen West-Vlaanderen 8930",
    "addr:housenumber":"677",
    "addr:postcode":"8930",
    "addr:street":"Moeskroenstraat",
    "iso:country":"BE",
    "sg:address":"Moeskroenstraat 677",
    "sg:city":"Menen",
    "sg:orig_category":"Afval and schroot Gh",
    "sg:phone":"+32 56 41 54 15",
    "sg:postcode":"8930",
    "sg:province":"West-Vlaanderen",
    "wof:name":"Symaco",
    "wof:placetype":"venue"
},
  "geometry": {"coordinates":[3.1586298943,50.787361145],"type":"Point"}
}