{
  "type": "Feature",
  "properties": {
    "iso:country":"BE",
    "sg:address":"Hasseltsebaan 112",
    "sg:city":"Hechtel-eksel",
    "sg:orig_category":"Instituts de beaut\u00e9",
    "sg:phone":"+32 11 73 44 87",
    "sg:postcode":"3940",
    "sg:province":"Limburg",
    "wof:name":"Bea Vanvinckenroye",
    "wof:placetype":"venue"
},
  "geometry": {"coordinates":[5.3746128082,51.0967674255],"type":"Point"}
}