{
  "type": "Feature",
  "properties": {
    "addr:full":"Broekkantstraat 43 Meeuwen-gruitrode Limburg 3670",
    "addr:housenumber":"43",
    "addr:postcode":"3670",
    "addr:street":"Broekkantstraat",
    "iso:country":"BE",
    "sg:address":"Broekkantstraat 43",
    "sg:city":"Meeuwen-gruitrode",
    "sg:orig_category":"Woningbouw",
    "sg:phone":"+32 11 79 22 63",
    "sg:postcode":"3670",
    "sg:province":"Limburg",
    "wof:name":"Jaak Huskens",
    "wof:placetype":"venue"
},
  "geometry": {"coordinates":[5.5102930069,51.0917472839],"type":"Point"}
}