{
  "type": "Feature",
  "properties": {
    "addr:full":"Zandputstraat 98 Menen West-Vlaanderen 8930",
    "addr:housenumber":"98",
    "addr:postcode":"8930",
    "addr:street":"Zandputstraat",
    "iso:country":"BE",
    "sg:address":"Zandputstraat 98",
    "sg:city":"Menen",
    "sg:orig_category":"Kapsalons",
    "sg:phone":"+32 56 51 34 27",
    "sg:postcode":"8930",
    "sg:province":"West-Vlaanderen",
    "wof:name":"Myriam Devriese",
    "wof:placetype":"venue"
},
  "geometry": {"coordinates":[3.1174459457,50.8037757874],"type":"Point"}
}