{
  "type": "Feature",
  "properties": {
    "addr:full":"Sint-amandinastraat 31-33 Leopoldsburg Limburg 3970",
    "addr:postcode":"31-33;3970",
    "addr:street":"Sint-Amandinastraat",
    "iso:country":"BE",
    "sg:address":"Sint-amandinastraat 31-33",
    "sg:city":"Leopoldsburg",
    "sg:classifiers":[
        {
            "category":"Professional",
            "subcategory":"Printing & Photocopies",
            "type":"Services"
        }
    ],
    "sg:phone":"+32 11 34 52 58",
    "sg:postcode":"3970",
    "sg:province":"Limburg",
    "sg:tags":[
        "silkscreen",
        "-"
    ],
    "wof:name":"Screen Expres Bvba",
    "wof:placetype":"venue"
},
  "geometry": {"coordinates":[5.2573151588,51.1368179321],"type":"Point"}
}