{
  "type": "Feature",
  "properties": {
    "addr:full":"Hochstrasse 177 Eupen Li\u00e8ge 4700",
    "addr:housenumber":"177",
    "addr:postcode":"4700",
    "addr:street":"Hochstrasse",
    "iso:country":"BE",
    "sg:address":"Hochstrasse 177",
    "sg:city":"Eupen",
    "sg:classifiers":[
        {
            "category":"Sports & Exercise",
            "subcategory":"Bicycle Rental",
            "type":"Entertainment"
        }
    ],
    "sg:phone":"+32 87 32 17 17",
    "sg:postcode":"4700",
    "sg:province":"Li\u00e8ge",
    "sg:tags":[
        "equipment",
        "athletics"
    ],
    "wof:name":"Megaform A.g.",
    "wof:placetype":"venue"
},
  "geometry": {"coordinates":[6.024274826,50.6445007324],"type":"Point"}
}