{
  "type": "Feature",
  "properties": {
    "addr:full":"Rue Jules Mattez 28 Courcelles Hainaut 6182",
    "addr:housenumber":"28",
    "addr:postcode":"6182",
    "addr:street":"Rue Jules Mattez",
    "iso:country":"BE",
    "sg:address":"Rue Jules Mattez 28",
    "sg:city":"Courcelles",
    "sg:orig_category":"Dierenartsen",
    "sg:phone":"+32 71 46 20 47",
    "sg:postcode":"6182",
    "sg:province":"Hainaut",
    "wof:name":"Fabienne Godin",
    "wof:placetype":"venue"
},
  "geometry": {"coordinates":[4.3511500359,50.4487037659],"type":"Point"}
}