{
  "type": "Feature",
  "properties": {
    "addr:full":"Martelaarslaan 326 Gent Oost-Vlaanderen 9000",
    "addr:housenumber":"326",
    "addr:postcode":"9000",
    "addr:street":"Martelaarslaan;Oost-Vlaanderen",
    "iso:country":"BE",
    "sg:address":"Martelaarslaan 326",
    "sg:city":"Gent",
    "sg:orig_category":"Artiesten and kunstenaars",
    "sg:phone":"+32 9 223 16 76",
    "sg:postcode":"9000",
    "sg:province":"Oost-Vlaanderen",
    "wof:name":"Peter Marichael",
    "wof:placetype":"venue"
},
  "geometry": {"coordinates":[3.7103290558,51.0476608276],"type":"Point"}
}