{
  "type": "Feature",
  "properties": {
    "addr:full":"Rue Du Mont\u00e9n\u00e9gro 61 Bruxelles (forest) Bruxelles-Capitale 1190",
    "addr:housenumber":"61",
    "addr:postcode":"1190",
    "addr:street":"Rue Du Monte\u0301Ne\u0301Gro",
    "iso:country":"BE",
    "sg:address":"Rue Du Mont\u00e9n\u00e9gro 61",
    "sg:city":"Bruxelles (forest)",
    "sg:classifiers":[
        {
            "category":"Food & Beverages",
            "subcategory":"Groceries & Convenience Stores",
            "type":"Retail Goods"
        }
    ],
    "sg:phone":"+32 2 537 73 92",
    "sg:postcode":"1190",
    "sg:province":"Bruxelles-Capitale",
    "sg:tags":[
        "grocer"
    ],
    "wof:name":"Tufan Kaya Sprl",
    "wof:placetype":"venue"
},
  "geometry": {"coordinates":[4.3356351852,50.8269844055],"type":"Point"}
}