{
  "type": "Feature",
  "properties": {
    "addr:full":"Gemeenteplein 53 Knokke-heist (knokke) West-Vlaanderen 8300",
    "addr:housenumber":"53",
    "addr:postcode":"8300",
    "addr:street":"Gemeenteplein",
    "iso:country":"BE",
    "sg:address":"Gemeenteplein 53",
    "sg:city":"Knokke-heist (knokke)",
    "sg:classifiers":[
        {
            "category":"Shopping",
            "subcategory":"Florist",
            "type":"Retail Goods"
        }
    ],
    "sg:phone":"+32 50 61 63 30",
    "sg:postcode":"8300",
    "sg:province":"West-Vlaanderen",
    "wof:name":"Zuidkant (de)",
    "wof:placetype":"venue"
},
  "geometry": {"coordinates":[3.2920799255,51.3407936096],"type":"Point"}
}