{
  "type": "Feature",
  "properties": {
    "addr:full":"Sint-amelbergalaan 10 Temse Oost-Vlaanderen 9140",
    "addr:housenumber":"10",
    "addr:postcode":"9140",
    "addr:street":"Sint-Amelbergalaan",
    "iso:country":"BE",
    "sg:address":"Sint-amelbergalaan 10",
    "sg:city":"Temse",
    "sg:classifiers":[
        {
            "category":"Restaurant",
            "type":"Food & Drink"
        }
    ],
    "sg:phone":"+32 3 771 58 70",
    "sg:postcode":"9140",
    "sg:province":"Oost-Vlaanderen",
    "wof:name":"Tearoom Tea-time",
    "wof:placetype":"venue"
},
  "geometry": {"coordinates":[4.2022771835,51.1265640259],"type":"Point"}
}