{
  "type": "Feature",
  "properties": {
    "iso:country":"BE",
    "sg:address":"Hemelstraat 133a",
    "sg:city":"Dendermonde",
    "sg:classifiers":[
        {
            "category":"Social Services",
            "subcategory":"Child Care",
            "type":"Services"
        }
    ],
    "sg:phone":"+32 52 21 58 03",
    "sg:postcode":"9200",
    "sg:province":"Oost-Vlaanderen",
    "sg:tags":[
        "baby",
        "nursery",
        "day",
        "sitting"
    ],
    "wof:name":"Dienst Voor Opvanggezinnen",
    "wof:placetype":"venue"
},
  "geometry": {"coordinates":[4.1038370132,51.021446228],"type":"Point"}
}