{
  "type": "Feature",
  "properties": {
    "iso:country":"BE",
    "sg:address":"Vieille Rue Du Moulin 330",
    "sg:city":"Ukkel/uccle",
    "sg:orig_category":"Artistes ind\u00e9pendants",
    "sg:phone":"+32 2 374 12 79",
    "sg:postcode":"1180",
    "sg:province":"Bruxelles-Capitale",
    "wof:name":"D\u00c9sir\u00c9e Olmi",
    "wof:placetype":"venue"
},
  "geometry": {"coordinates":[4.3743948936,50.7897071838],"type":"Point"}
}