{
  "type": "Feature",
  "properties": {
    "addr:full":"Rue Lieutenant Cotton 21 Vloesberg/flobecq Hainaut 7880",
    "addr:housenumber":"21",
    "addr:postcode":"7880",
    "addr:street":"Rue Lieutenant Cotton;Hainaut",
    "iso:country":"BE",
    "sg:address":"Rue Lieutenant Cotton 21",
    "sg:city":"Vloesberg/flobecq",
    "sg:orig_category":"Quincailleries",
    "sg:phone":"+32 68 44 76 81",
    "sg:postcode":"7880",
    "sg:province":"Hainaut",
    "wof:name":"Paradis Du Bricoleur",
    "wof:placetype":"venue"
},
  "geometry": {"coordinates":[3.7405350208,50.7359046936],"type":"Point"}
}