{
  "type": "Feature",
  "properties": {
    "addr:full":"Tienne Jean Fl\u00e9mal 77 Grez-doiceau Brabant Wallon 1390",
    "addr:housenumber":"77",
    "addr:postcode":"1390",
    "addr:street":"Tienne",
    "iso:country":"BE",
    "sg:address":"Tienne Jean Fl\u00e9mal 77",
    "sg:city":"Grez-doiceau",
    "sg:classifiers":[
        {
            "category":"Health Services",
            "subcategory":"Health Practitioner",
            "type":"Services"
        }
    ],
    "sg:phone":"+32 10 84 27 41",
    "sg:postcode":"1390",
    "sg:province":"Brabant Wallon",
    "sg:tags":[
        "physiotherapist"
    ],
    "wof:name":"Capart S",
    "wof:placetype":"venue"
},
  "geometry": {"coordinates":[4.6483879089,50.7307739258],"type":"Point"}
}