{
  "type": "Feature",
  "properties": {
    "iso:country":"BE",
    "sg:address":"Egenhovenstraat 163",
    "sg:city":"Bertem",
    "sg:orig_category":"Catering and organisation de f\u00eates",
    "sg:phone":"+32 16 49 07 34",
    "sg:postcode":"3060",
    "sg:province":"Vlaams-Brabant",
    "wof:name":"Traiteur Tara-roggeman",
    "wof:placetype":"venue"
},
  "geometry": {"coordinates":[4.6434540749,50.8623962402],"type":"Point"}
}