{
  "type": "Feature",
  "properties": {
    "addr:full":"Rue De Li\u00c8ge 31 Bomal-sur-ourthe Luxembourg 6941",
    "addr:housenumber":"31",
    "addr:postcode":"6941",
    "addr:street":"Rue De Lie\u0300Ge",
    "iso:country":"BE",
    "sg:address":"Rue De Li\u00c8ge 31",
    "sg:city":"Bomal-sur-ourthe",
    "sg:orig_category":"Bloemen and planten Fleurop Interflora",
    "sg:phone":"+32 86 21 12 07",
    "sg:postcode":"6941",
    "sg:province":"Luxembourg",
    "wof:name":"Lesage",
    "wof:placetype":"venue"
},
  "geometry": {"coordinates":[5.5237569809,50.3794937134],"type":"Point"}
}