{
  "type": "Feature",
  "properties": {
    "iso:country":"BE",
    "sg:address":"Gemeentehuisstraat 19",
    "sg:city":"Ternat",
    "sg:orig_category":"Enseignement maternel and primaire",
    "sg:phone":"+32 2 582 52 76",
    "sg:postcode":"1740",
    "sg:province":"Vlaams-Brabant",
    "wof:name":"B.s.g.o. Horizon",
    "wof:placetype":"venue"
},
  "geometry": {"coordinates":[4.1798810959,50.8704719543],"type":"Point"}
}