{
  "type": "Feature",
  "properties": {
    "addr:full":"Mandenmakerstraat 10 Sint-niklaas Oost-Vlaanderen 9100",
    "addr:housenumber":"10",
    "addr:postcode":"9100",
    "addr:street":"Mandenmakerstraat",
    "iso:country":"BE",
    "sg:address":"Mandenmakerstraat 10",
    "sg:city":"Sint-niklaas",
    "sg:classifiers":[
        {
            "category":"Education",
            "subcategory":"Dance Studio",
            "type":"Public Place"
        }
    ],
    "sg:phone":"+32 3 777 68 07",
    "sg:postcode":"9100",
    "sg:province":"Oost-Vlaanderen",
    "sg:tags":[
        "school",
        "dancing"
    ],
    "wof:name":"Arbijn-verlee",
    "wof:placetype":"venue"
},
  "geometry": {"coordinates":[4.1407880783,51.1510658264],"type":"Point"}
}