{
  "type": "Feature",
  "properties": {
    "addr:full":"Sur-les-march\u00c9s 188 Florennes Namur 5621",
    "addr:housenumber":"188",
    "addr:postcode":"5621",
    "iso:country":"BE",
    "sg:address":"Sur-les-march\u00c9s 188",
    "sg:city":"Florennes",
    "sg:orig_category":"Fantasieartikelen Verhuur textielartikelen and schoenen",
    "sg:phone":"+32 71 50 39 73",
    "sg:postcode":"5621",
    "sg:province":"Namur",
    "wof:name":"Aux Mascarades",
    "wof:placetype":"venue"
},
  "geometry": {"coordinates":[4.5490231514,50.3102722168],"type":"Point"}
}