{
  "type": "Feature",
  "properties": {
    "iso:country":"BE",
    "sg:address":"Acacialaan 2",
    "sg:city":"Beringen",
    "sg:orig_category":"Industri\u00eble wasserijen and droogkuis Wasserijen, Reiniging and Droogkuis",
    "sg:phone":"+32 11 42 24 05",
    "sg:postcode":"3583",
    "sg:province":"Limburg",
    "wof:name":"Lux Shop Paal",
    "wof:placetype":"venue"
},
  "geometry": {"coordinates":[5.1706700325,51.0389442444],"type":"Point"}
}