{
  "type": "Feature",
  "properties": {
    "iso:country":"BE",
    "sg:address":"Zavelstraat 32",
    "sg:city":"Zonhoven",
    "sg:classifiers":[
        {
            "category":"Insurance",
            "subcategory":"Insurance Agent",
            "type":"Services"
        }
    ],
    "sg:phone":"+32 11 81 13 61",
    "sg:postcode":"3520",
    "sg:province":"Limburg",
    "sg:tags":[
        "broker"
    ],
    "wof:name":"Jaeken S Zakenkantoor",
    "wof:placetype":"venue"
},
  "geometry": {"coordinates":[5.3649859428,50.996055603],"type":"Point"}
}