{
  "type": "Feature",
  "properties": {
    "iso:country":"BE",
    "sg:address":"Schansstraat 10",
    "sg:city":"As (groot)",
    "sg:orig_category":"Kapsalons",
    "sg:phone":"+32 89 65 73 86",
    "sg:postcode":"3665",
    "sg:province":"Limburg",
    "wof:name":"Bloemen Dirckx J",
    "wof:placetype":"venue"
},
  "geometry": {"coordinates":[5.5858078003,51.0028762817],"type":"Point"}
}