{
  "type": "Feature",
  "properties": {
    "addr:full":"Rue Du Point D'arr\u00eat 2 Habay (rulles) Luxembourg 6724",
    "addr:housenumber":"2",
    "addr:postcode":"6724",
    "addr:street":"Rue Du Point D'Arre \u0302T",
    "iso:country":"BE",
    "sg:address":"Rue Du Point D'arr\u00eat 2",
    "sg:city":"Habay (rulles)",
    "sg:classifiers":[
        {
            "category":"Building & Trades",
            "subcategory":"Construction",
            "type":"Services"
        }
    ],
    "sg:phone":"+32 63 41 22 07",
    "sg:postcode":"6724",
    "sg:province":"Luxembourg",
    "sg:tags":[
        "carpenter"
    ],
    "wof:name":"Condrotte F",
    "wof:placetype":"venue"
},
  "geometry": {"coordinates":[5.5596818924,49.7192344666],"type":"Point"}
}