{
  "type": "Feature",
  "properties": {
    "addr:full":"Molenstraat 4 Hooglede West-Vlaanderen 8830",
    "addr:housenumber":"4",
    "addr:postcode":"8830",
    "addr:street":"Molenstraat",
    "iso:country":"BE",
    "sg:address":"Molenstraat 4",
    "sg:city":"Hooglede",
    "sg:orig_category":"Landmeters",
    "sg:phone":"+32 51 24 67 86",
    "sg:postcode":"8830",
    "sg:province":"West-Vlaanderen",
    "wof:name":"Francois Collette",
    "wof:placetype":"venue"
},
  "geometry": {"coordinates":[3.0944190025,50.9810142517],"type":"Point"}
}