{
  "type": "Feature",
  "properties": {
    "addr:full":"Lundenstr 74 Deurne Antwerpen 2100",
    "addr:housenumber":"74",
    "addr:postcode":"2100",
    "addr:street":"Lundenstr",
    "iso:country":"BE",
    "sg:address":"Lundenstr 74",
    "sg:city":"Deurne",
    "sg:classifiers":[
        {
            "category":"Professional",
            "subcategory":"Engineering",
            "type":"Services"
        }
    ],
    "sg:phone":"+32 3 326 59 00",
    "sg:postcode":"2100",
    "sg:province":"Antwerpen",
    "sg:tags":[
        "machine",
        "-",
        "jewellery",
        "mechanical"
    ],
    "wof:name":"Antwerpse Etuisfabriek Van Camp Nv",
    "wof:placetype":"venue"
},
  "geometry": {"coordinates":[4.4638037682,51.2224731445],"type":"Point"}
}