{
  "type": "Feature",
  "properties": {
    "addr:full":"Koning Albertstraat 7 Diest Vlaams-Brabant 3290",
    "addr:housenumber":"7",
    "addr:postcode":"3290",
    "addr:street":"Koning Albertstraat",
    "iso:country":"BE",
    "sg:address":"Koning Albertstraat 7",
    "sg:city":"Diest",
    "sg:orig_category":"Brood, gebak and snoepgoed",
    "sg:phone":"+32 13 33 74 11",
    "sg:postcode":"3290",
    "sg:province":"Vlaams-Brabant",
    "wof:name":"Bakkerij Walter",
    "wof:placetype":"venue"
},
  "geometry": {"coordinates":[5.0522289276,50.9852714539],"type":"Point"}
}