{
  "type": "Feature",
  "properties": {
    "addr:full":"Rue Fourneau 7 Marchin Li\u00e8ge 4570",
    "addr:housenumber":"7",
    "addr:postcode":"4570",
    "addr:street":"Rue Fourneau",
    "iso:country":"BE",
    "sg:address":"Rue Fourneau 7",
    "sg:city":"Marchin",
    "sg:classifiers":[
        {
            "category":"Retail",
            "subcategory":"Veterinary Services",
            "type":"Services"
        }
    ],
    "sg:phone":"+32 85 51 14 23",
    "sg:postcode":"4570",
    "sg:province":"Li\u00e8ge",
    "sg:tags":[
        "veterinarian"
    ],
    "wof:name":"Kersten B",
    "wof:placetype":"venue"
},
  "geometry": {"coordinates":[5.2366781235,50.4803314209],"type":"Point"}
}