{
  "type": "Feature",
  "properties": {
    "addr:full":"Avenue Brugmann 425bd Ukkel/uccle Bruxelles-Capitale 1180",
    "addr:postcode":"1180",
    "addr:street":"Avenue Brugmann 425Bd",
    "iso:country":"BE",
    "sg:address":"Avenue Brugmann 425bd",
    "sg:city":"Ukkel/uccle",
    "sg:orig_category":"M\u00e9decins and sp\u00e9cialistes",
    "sg:phone":"+32 2 344 74 05",
    "sg:postcode":"1180",
    "sg:province":"Bruxelles-Capitale",
    "wof:name":"Christine Parmentier",
    "wof:placetype":"venue"
},
  "geometry": {"coordinates":[4.3433580399,50.8067703247],"type":"Point"}
}