{
  "type": "Feature",
  "properties": {
    "addr:full":"Mechelsesteenweg 592 Zaventem Vlaams-Brabant 1930",
    "addr:housenumber":"592",
    "addr:postcode":"1930",
    "addr:street":"Mechelsesteenweg",
    "iso:country":"BE",
    "sg:address":"Mechelsesteenweg 592",
    "sg:city":"Zaventem",
    "sg:orig_category":"Sportclubs Sportterreinen and installaties behalve sportcentra",
    "sg:phone":"+32 2 757 02 85",
    "sg:postcode":"1930",
    "sg:province":"Vlaams-Brabant",
    "wof:name":"Nossegem Sk",
    "wof:placetype":"venue"
},
  "geometry": {"coordinates":[4.5089697838,50.8874206543],"type":"Point"}
}