{
  "type": "Feature",
  "properties": {
    "iso:country":"BE",
    "sg:address":"Leugenboomstraat 32",
    "sg:city":"Ichtegem",
    "sg:orig_category":"Eleveurs de bovins. Eleveurs and marchands de porcs",
    "sg:phone":"+32 59 27 72 15",
    "sg:postcode":"8480",
    "sg:province":"West-Vlaanderen",
    "wof:name":"Patriek Stael",
    "wof:placetype":"venue"
},
  "geometry": {"coordinates":[2.9955298901,51.1188621521],"type":"Point"}
}