{
  "type": "Feature",
  "properties": {
    "addr:full":"Krijgelstraat 8ba Wichelen Oost-Vlaanderen 9260",
    "addr:postcode":"9260",
    "addr:street":"Krijgelstraat;Oost-Vlaanderen",
    "iso:country":"BE",
    "sg:address":"Krijgelstraat 8ba",
    "sg:city":"Wichelen",
    "sg:orig_category":"Rundveehouders",
    "sg:phone":"+32 9 369 90 94",
    "sg:postcode":"9260",
    "sg:province":"Oost-Vlaanderen",
    "wof:name":"Jacqueline Samson",
    "wof:placetype":"venue"
},
  "geometry": {"coordinates":[3.9535429478,50.9963531494],"type":"Point"}
}