{
  "type": "Feature",
  "properties": {
    "iso:country":"BE",
    "sg:address":"Arthur Latourstraat 13",
    "sg:city":"Gent (ledeberg)",
    "sg:classifiers":[
        {
            "category":"Building & Trades",
            "subcategory":"Equipment Rental",
            "type":"Services"
        }
    ],
    "sg:phone":"+32 9 232 28 01",
    "sg:postcode":"9050",
    "sg:province":"Oost-Vlaanderen",
    "sg:tags":[
        "sound",
        "-",
        "system"
    ],
    "wof:name":"Van Zele Raf",
    "wof:placetype":"venue"
},
  "geometry": {"coordinates":[3.7434630394,51.0410652161],"type":"Point"}
}