{
  "type": "Feature",
  "properties": {
    "addr:full":"Rue Ren\u00c9 Christiaens 25 Oudergem/auderghem Bruxelles-Capitale 1160",
    "addr:housenumber":"25",
    "addr:postcode":"1160",
    "addr:street":"Rue Rene\u0301 Christiaens;/",
    "iso:country":"BE",
    "sg:address":"Rue Ren\u00c9 Christiaens 25",
    "sg:city":"Oudergem/auderghem",
    "sg:orig_category":"Eclairage et \u00e9quipements du foyer. Peinture. Rev\u00eatements pour sols and murs. D\u00e9corateurs d'int\u00e9rieur",
    "sg:phone":"+32 2 662 23 62",
    "sg:postcode":"1160",
    "sg:province":"Bruxelles-Capitale",
    "wof:name":"Rousseau",
    "wof:placetype":"venue"
},
  "geometry": {"coordinates":[4.4409461021,50.807258606],"type":"Point"}
}