{
  "type": "Feature",
  "properties": {
    "addr:full":"Schulstrasse 1 Eupen/eupen Li\u00e8ge 4700",
    "addr:housenumber":"1",
    "addr:postcode":"4700",
    "addr:street":"Schulstrasse",
    "iso:country":"BE",
    "sg:address":"Schulstrasse 1",
    "sg:city":"Eupen/eupen",
    "sg:orig_category":"Voedingsspeciaalzaken",
    "sg:phone":"+32 87 74 23 22",
    "sg:postcode":"4700",
    "sg:province":"Li\u00e8ge",
    "wof:name":"Reformhaus",
    "wof:placetype":"venue"
},
  "geometry": {"coordinates":[6.0345802307,50.6302947998],"type":"Point"}
}