{
  "type": "Feature",
  "properties": {
    "addr:full":"Roeselaarsestraat 166 Izegem West-Vlaanderen 8870",
    "addr:housenumber":"166",
    "addr:postcode":"8870",
    "addr:street":"Roeselaarsestraat",
    "iso:country":"BE",
    "sg:address":"Roeselaarsestraat 166",
    "sg:city":"Izegem",
    "sg:orig_category":"Eclairage et \u00e9quipements du foyer. Souvenirs and objets artisanaux",
    "sg:phone":"+32 51 30 53 09",
    "sg:postcode":"8870",
    "sg:province":"West-Vlaanderen",
    "wof:name":"Huis De Wieke",
    "wof:placetype":"venue"
},
  "geometry": {"coordinates":[3.20616889,50.9201278687],"type":"Point"}
}