{
  "type": "Feature",
  "properties": {
    "addr:full":"Mierdsedijk 105ba Ravels Antwerpen 2382",
    "addr:postcode":"2382",
    "iso:country":"BE",
    "sg:address":"Mierdsedijk 105ba",
    "sg:city":"Ravels",
    "sg:orig_category":"Eleveurs de bovins",
    "sg:phone":"+32 14 65 61 56",
    "sg:postcode":"2382",
    "sg:province":"Antwerpen",
    "wof:name":"Louis Haagen",
    "wof:placetype":"venue"
},
  "geometry": {"coordinates":[5.041768074,51.4469108582],"type":"Point"}
}