{
  "type": "Feature",
  "properties": {
    "iso:country":"BE",
    "sg:address":"Arenbergstraat",
    "sg:city":"Antwerpen (groot)",
    "sg:orig_category":"Assistances juridiques",
    "sg:phone":"+32 3 225 00 60",
    "sg:postcode":"2000",
    "sg:province":"Antwerpen",
    "wof:name":"Antwerps Octrooi- En Merkenbureau",
    "wof:placetype":"venue"
},
  "geometry": {"coordinates":[4.405960083,51.215221405],"type":"Point"}
}