{
  "type": "Feature",
  "properties": {
    "iso:country":"BE",
    "sg:address":"Chauss\u00c9e De March\u00c9 80",
    "sg:city":"Assesse",
    "sg:orig_category":"Postkantoren Verzekeringsmakelaars and experts",
    "sg:phone":"+32 83 65 51 22",
    "sg:postcode":"5330",
    "sg:province":"Namur",
    "wof:name":"La Poste",
    "wof:placetype":"venue"
},
  "geometry": {"coordinates":[5.0268921852,50.3665351868],"type":"Point"}
}