{
  "type": "Feature",
  "properties": {
    "iso:country":"BE",
    "sg:address":"Frans Halsvest 94b001",
    "sg:city":"Mechelen",
    "sg:orig_category":"Kapsalons",
    "sg:phone":"+32 15 20 06 41",
    "sg:postcode":"2800",
    "sg:province":"Antwerpen",
    "wof:name":"Coiffure Elite",
    "wof:placetype":"venue"
},
  "geometry": {"coordinates":[4.4887452126,51.0300292969],"type":"Point"}
}