{
  "type": "Feature",
  "properties": {
    "addr:full":"Rue Sainry 49 Trooz (for\u00eat) Li\u00e8ge 4870",
    "addr:housenumber":"49",
    "addr:postcode":"4870",
    "addr:street":"Rue Sainry;Fore\u0302T",
    "iso:country":"BE",
    "sg:address":"Rue Sainry 49",
    "sg:city":"Trooz (for\u00eat)",
    "sg:classifiers":[
        {
            "category":"Building & Trades",
            "subcategory":"Construction",
            "type":"Services"
        }
    ],
    "sg:phone":"+32 4 351 87 37",
    "sg:postcode":"4870",
    "sg:province":"Li\u00e8ge",
    "sg:tags":[
        "carpenter"
    ],
    "wof:name":"Simons Sprl",
    "wof:placetype":"venue"
},
  "geometry": {"coordinates":[5.6734352112,50.5785331726],"type":"Point"}
}