{
  "type": "Feature",
  "properties": {
    "addr:full":"Borrewal 18 Nevele Oost-Vlaanderen 9850",
    "addr:housenumber":"18",
    "addr:postcode":"9850",
    "addr:street":"Borrewal",
    "iso:country":"BE",
    "sg:address":"Borrewal 18",
    "sg:city":"Nevele",
    "sg:orig_category":"Ordinateurs and \u00e9quipement informatique",
    "sg:phone":"+32 9 371 42 96",
    "sg:postcode":"9850",
    "sg:province":"Oost-Vlaanderen",
    "wof:name":"Xerxes",
    "wof:placetype":"venue"
},
  "geometry": {"coordinates":[3.5459508896,51.0378494263],"type":"Point"}
}