{
  "type": "Feature",
  "properties": {
    "iso:country":"BE",
    "sg:address":"Larenstraat 2",
    "sg:city":"Lummen",
    "sg:orig_category":"Rundveehouders",
    "sg:phone":"+32 13 52 18 31",
    "sg:postcode":"3560",
    "sg:province":"Limburg",
    "wof:name":"Marc Maris",
    "wof:placetype":"venue"
},
  "geometry": {"coordinates":[5.1802501678,51.0015983582],"type":"Point"}
}