{
  "type": "Feature",
  "properties": {
    "addr:full":"Rue De L'abbaye D'aulne 2 Fontaine-l'ev\u00eaque (leernes) Hainaut 6142",
    "addr:housenumber":"2",
    "addr:postcode":"6142",
    "addr:street":"Rue De L'Abbaye D'Aulne;Hainaut",
    "iso:country":"BE",
    "sg:address":"Rue De L'abbaye D'aulne 2",
    "sg:city":"Fontaine-l'ev\u00eaque (leernes)",
    "sg:classifiers":[
        {
            "category":"Social Services",
            "subcategory":"Child Care",
            "type":"Services"
        }
    ],
    "sg:phone":"+32 71 51 54 65",
    "sg:postcode":"6142",
    "sg:province":"Hainaut",
    "sg:tags":[
        "home"
    ],
    "wof:name":"Institut Royal St-exup\u00e9ry Imp",
    "wof:placetype":"venue"
},
  "geometry": {"coordinates":[-111.9644622803,46.2507972717],"type":"Point"}
}