{
  "type": "Feature",
  "properties": {
    "addr:full":"Heemstraat 60 Wondelgem Oost-Vlaanderen 9032",
    "addr:housenumber":"60",
    "addr:postcode":"9032",
    "addr:street":"Heemstraat",
    "iso:country":"BE",
    "sg:address":"Heemstraat 60",
    "sg:city":"Wondelgem",
    "sg:orig_category":"Fotografen and fotostudio's",
    "sg:phone":"+32 478 31 72 08",
    "sg:postcode":"9032",
    "sg:province":"Oost-Vlaanderen",
    "wof:name":"Raoul Verbeke",
    "wof:placetype":"venue"
},
  "geometry": {"coordinates":[3.7122058868,51.0860862732],"type":"Point"}
}