{
  "type": "Feature",
  "properties": {
    "iso:country":"BE",
    "sg:address":"Chemin Des Garmilles 41",
    "sg:city":"La Hulpe",
    "sg:orig_category":"Boomkwekerijen Tuinen",
    "sg:phone":"+32 2 353 21 59",
    "sg:postcode":"1310",
    "sg:province":"Brabant Wallon",
    "wof:name":"Van De Velde L.",
    "wof:placetype":"venue"
},
  "geometry": {"coordinates":[4.4431138039,50.719367981],"type":"Point"}
}