{
  "type": "Feature",
  "properties": {
    "iso:country":"BE",
    "sg:address":"Industriestraat 16",
    "sg:city":"Ruiselede",
    "sg:orig_category":"Non-Classified Establishments",
    "sg:phone":"+32 51 68 00 10",
    "sg:postcode":"8755",
    "sg:province":"West-Vlaanderen",
    "wof:name":"Geerts Bvba",
    "wof:placetype":"venue"
},
  "geometry": {"coordinates":[3.4087851048,51.0468444824],"type":"Point"}
}