{
  "type": "Feature",
  "properties": {
    "iso:country":"BE",
    "sg:address":"Grote Pieter Potstraat 36",
    "sg:city":"Antwerpen",
    "sg:classifiers":[
        {
            "category":"Restaurant",
            "type":"Food & Drink"
        }
    ],
    "sg:phone":"+32 3 234 04 32",
    "sg:postcode":"2000",
    "sg:province":"Antwerpen",
    "wof:name":"In Den Bloeyenden Wyngaerdt",
    "wof:placetype":"venue"
},
  "geometry": {"coordinates":[4.397110939,51.2199516296],"type":"Point"}
}