{
  "type": "Feature",
  "properties": {
    "iso:country":"BE",
    "sg:address":"Stevinstraat 8b36",
    "sg:city":"Brussel/bruxelles",
    "sg:orig_category":"Boekhouders",
    "sg:phone":"+32 2 230 06 90",
    "sg:postcode":"1000",
    "sg:province":"Bruxelles-Capitale",
    "wof:name":"F.h.o.",
    "wof:placetype":"venue"
},
  "geometry": {"coordinates":[4.3750910759,50.8461456299],"type":"Point"}
}