{
  "type": "Feature",
  "properties": {
    "iso:country":"BE",
    "sg:address":"Rue Valere Letot 73",
    "sg:city":"Jurbise",
    "sg:orig_category":"Papierwaren Reclamebureaus",
    "sg:phone":"+32 65 22 73 94",
    "sg:postcode":"7050",
    "sg:province":"Hainaut",
    "wof:name":"A.g.p. Leurident",
    "wof:placetype":"venue"
},
  "geometry": {"coordinates":[3.8595221043,50.509853363],"type":"Point"}
}