{
  "type": "Feature",
  "properties": {
    "addr:full":"Chauss\u00c9e Des Ballons 445 Moeskroen/mouscron Hainaut 7712",
    "addr:housenumber":"445",
    "addr:postcode":"7712",
    "addr:street":"Chausse\u0301E Des Ballons",
    "iso:country":"BE",
    "sg:address":"Chauss\u00c9e Des Ballons 445",
    "sg:city":"Moeskroen/mouscron",
    "sg:classifiers":[
        {
            "category":"Food & Beverages",
            "subcategory":"Fruits & Vegetables",
            "type":"Retail Goods"
        }
    ],
    "sg:phone":"+32 56 33 32 70",
    "sg:postcode":"7712",
    "sg:province":"Hainaut",
    "sg:tags":[
        "l\u00e9gumes",
        "gr"
    ],
    "wof:name":"Werner Vergote",
    "wof:placetype":"venue"
},
  "geometry": {"coordinates":[3.2179059982,50.7151756287],"type":"Point"}
}