{
  "type": "Feature",
  "properties": {
    "iso:country":"BE",
    "sg:address":"Gemeentehuisstraat 18",
    "sg:city":"Kampenhout",
    "sg:orig_category":"Slagers",
    "sg:phone":"+32 16 65 51 22",
    "sg:postcode":"1910",
    "sg:province":"Vlaams-Brabant",
    "wof:name":"Jan Gellens",
    "wof:placetype":"venue"
},
  "geometry": {"coordinates":[4.5503969193,50.9411354065],"type":"Point"}
}