{
  "type": "Feature",
  "properties": {
    "addr:full":"Academiestraat 2b10 Brugge West-Vlaanderen 8000",
    "addr:housenumber":"2b10",
    "addr:postcode":"8000",
    "addr:street":"Academiestraat",
    "iso:country":"BE",
    "sg:address":"Academiestraat 2b10",
    "sg:city":"Brugge",
    "sg:orig_category":"Quincailleries. Eclairage et \u00e9quipements du foyer. Rev\u00eatements de sols and murs. Drogueries. Rev\u00eatem",
    "sg:phone":"+32 50 33 37 49",
    "sg:postcode":"8000",
    "sg:province":"West-Vlaanderen",
    "wof:name":"Maly (huis)",
    "wof:placetype":"venue"
},
  "geometry": {"coordinates":[3.2243158817,51.2111587524],"type":"Point"}
}