{
  "type": "Feature",
  "properties": {
    "iso:country":"BE",
    "sg:address":"Putkapelstraat 105a",
    "sg:city":"Gent",
    "sg:classifiers":[
        {
            "category":"Insurance",
            "subcategory":"Insurance Agent",
            "type":"Services"
        }
    ],
    "sg:phone":"+32 9 221 74 47",
    "sg:postcode":"9051",
    "sg:province":"Oost-Vlaanderen",
    "sg:tags":[
        "verzekeringsmakelaars",
        "expert"
    ],
    "wof:name":"De Hainaut-blommaert",
    "wof:placetype":"venue"
},
  "geometry": {"coordinates":[3.6930449009,51.0229454041],"type":"Point"}
}