{
  "type": "Feature",
  "properties": {
    "addr:full":"Dikkebusseweg 31 Ieper West-Vlaanderen 8900",
    "addr:housenumber":"31",
    "addr:postcode":"8900",
    "addr:street":"Dikkebusseweg",
    "iso:country":"BE",
    "sg:address":"Dikkebusseweg 31",
    "sg:city":"Ieper",
    "sg:orig_category":"Caf\u00e9s. Fleurs and plantes",
    "sg:phone":"+32 57 21 97 38",
    "sg:postcode":"8900",
    "sg:province":"West-Vlaanderen",
    "wof:name":"Huis Floristic",
    "wof:placetype":"venue"
},
  "geometry": {"coordinates":[2.8759629726,50.8444213867],"type":"Point"}
}