{
  "type": "Feature",
  "properties": {
    "iso:country":"BE",
    "sg:address":"Grote Heerweg 139",
    "sg:city":"Waregem",
    "sg:orig_category":"Entretien and r\u00e9parations de voitures",
    "sg:phone":"+32 56 71 98 95",
    "sg:postcode":"8791",
    "sg:province":"West-Vlaanderen",
    "wof:name":"Galle Trucks & Trailers",
    "wof:placetype":"venue"
},
  "geometry": {"coordinates":[3.335588932,50.8791465759],"type":"Point"}
}