{
  "type": "Feature",
  "properties": {
    "iso:country":"BE",
    "sg:address":"Bevrijdingslaan 12",
    "sg:city":"Ninove",
    "sg:classifiers":[
        {
            "category":"Building & Trades",
            "subcategory":"Construction",
            "type":"Services"
        }
    ],
    "sg:phone":"+32 54 33 84 60",
    "sg:postcode":"9400",
    "sg:province":"Oost-Vlaanderen",
    "sg:tags":[
        "carpenter"
    ],
    "wof:name":"Etbo Bvba",
    "wof:placetype":"venue"
},
  "geometry": {"coordinates":[4.0194759369,50.832988739],"type":"Point"}
}