{
  "type": "Feature",
  "properties": {
    "addr:full":"Rue Bergifoss\u00e9 1 Boussu Hainaut 7300",
    "addr:housenumber":"1",
    "addr:postcode":"7300",
    "addr:street":"Rue Bergifosse\u0301",
    "iso:country":"BE",
    "sg:address":"Rue Bergifoss\u00e9 1",
    "sg:city":"Boussu",
    "sg:classifiers":[
        {
            "category":"Transit Center",
            "subcategory":"Freight",
            "type":"Transportation"
        }
    ],
    "sg:phone":"+32 65 78 08 37",
    "sg:postcode":"7300",
    "sg:province":"Hainaut",
    "sg:tags":[
        "metallurgy",
        "pipe",
        "metalworking",
        "sheet"
    ],
    "wof:name":"Sirte Sprl",
    "wof:placetype":"venue"
},
  "geometry": {"coordinates":[3.7986800671,50.4328308105],"type":"Point"}
}