{
  "type": "Feature",
  "properties": {
    "addr:full":"Quai Donat Casterman 47 Tournai Hainaut 7500",
    "addr:housenumber":"47",
    "addr:postcode":"7500",
    "addr:street":"Quai Donat Casterman",
    "iso:country":"BE",
    "sg:address":"Quai Donat Casterman 47",
    "sg:city":"Tournai",
    "sg:classifiers":[
        {
            "category":"Airport",
            "subcategory":"International",
            "type":"Transportation"
        }
    ],
    "sg:phone":"+32 69 88 92 11",
    "sg:postcode":"7500",
    "sg:province":"Hainaut",
    "sg:tags":[
        "-",
        "transport"
    ],
    "wof:name":"Lotigier Sa",
    "wof:placetype":"venue"
},
  "geometry": {"coordinates":[3.3799180984,50.6156196594],"type":"Point"}
}