{
  "type": "Feature",
  "properties": {
    "iso:country":"BE",
    "sg:address":"Rue Du Grand Central 65",
    "sg:city":"Charleroi",
    "sg:classifiers":[
        {
            "category":"Fast Food",
            "type":"Food & Drink"
        }
    ],
    "sg:phone":"+32 71 30 08 75",
    "sg:postcode":"6000",
    "sg:province":"Hainaut",
    "sg:tags":[
        "voedingsspeciaalzaken",
        "meeneem",
        "restaurant"
    ],
    "wof:name":"Al Cappuccino",
    "wof:placetype":"venue"
},
  "geometry": {"coordinates":[4.4367461205,50.4091110229],"type":"Point"}
}