{
  "type": "Feature",
  "properties": {
    "addr:full":"Kerkstraat 46 Kuurne West-Vlaanderen 8520",
    "addr:housenumber":"46",
    "addr:postcode":"8520",
    "addr:street":"Kerkstraat",
    "iso:country":"BE",
    "sg:address":"Kerkstraat 46",
    "sg:city":"Kuurne",
    "sg:orig_category":"Kapsalons",
    "sg:phone":"+32 56 71 06 96",
    "sg:postcode":"8520",
    "sg:province":"West-Vlaanderen",
    "wof:name":"Neyrinck Intercoiffure",
    "wof:placetype":"venue"
},
  "geometry": {"coordinates":[3.2869989872,50.8527336121],"type":"Point"}
}