{
  "type": "Feature",
  "properties": {
    "iso:country":"BE",
    "sg:address":"Rue Sainte-genevi\u00c8ve 13",
    "sg:city":"Assesse",
    "sg:orig_category":"Installation \u00e9lectrique r\u00e9sidentielle",
    "sg:phone":"+32 83 65 60 37",
    "sg:postcode":"5334",
    "sg:province":"Namur",
    "wof:name":"Jean Toussaint",
    "wof:placetype":"venue"
},
  "geometry": {"coordinates":[5.0712032318,50.3732261658],"type":"Point"}
}