{
  "type": "Feature",
  "properties": {
    "iso:country":"BE",
    "sg:address":"Korte Gasthuisstraat 26",
    "sg:city":"Turnhout",
    "sg:classifiers":[
        {
            "category":"Shopping",
            "subcategory":"Clothing, Apparel, & Fashions",
            "type":"Retail Goods"
        }
    ],
    "sg:phone":"+32 14 42 46 82",
    "sg:postcode":"2300",
    "sg:province":"Antwerpen",
    "sg:tags":[
        "boutique"
    ],
    "wof:name":"New Collection",
    "wof:placetype":"venue"
},
  "geometry": {"coordinates":[4.9463858604,51.3224754333],"type":"Point"}
}