{
  "type": "Feature",
  "properties": {
    "iso:country":"BE",
    "sg:address":"Meerlaarstraat 163",
    "sg:city":"Laakdal",
    "sg:orig_category":"Installation de menuiserie en bois and plastique",
    "sg:phone":"+32 13 66 13 99",
    "sg:postcode":"2430",
    "sg:province":"Antwerpen",
    "wof:name":"Michael Vorsters",
    "wof:placetype":"venue"
},
  "geometry": {"coordinates":[5.0891089439,51.0860519409],"type":"Point"}
}