{
  "type": "Feature",
  "properties": {
    "iso:country":"BE",
    "sg:address":"Steenbergstraat 3",
    "sg:city":"Bree",
    "sg:orig_category":"Rundveehouders Varkenskwekers",
    "sg:phone":"+32 89 46 26 41",
    "sg:postcode":"3960",
    "sg:province":"Limburg",
    "wof:name":"Emiel Clijsters",
    "wof:placetype":"venue"
},
  "geometry": {"coordinates":[5.6188797951,51.1290206909],"type":"Point"}
}