{
  "type": "Feature",
  "properties": {
    "addr:full":"Weegse 11 Evergem (sleidinge) Oost-Vlaanderen 9940",
    "addr:housenumber":"11",
    "addr:postcode":"9940",
    "addr:street":"Weegse",
    "iso:country":"BE",
    "sg:address":"Weegse 11",
    "sg:city":"Evergem (sleidinge)",
    "sg:classifiers":[
        {
            "category":"Health Services",
            "subcategory":"Dentist",
            "type":"Services"
        }
    ],
    "sg:phone":"+32 9 357 67 51",
    "sg:postcode":"9940",
    "sg:province":"Oost-Vlaanderen",
    "wof:name":"Lippens Filip",
    "wof:placetype":"venue"
},
  "geometry": {"coordinates":[3.6645410061,51.1248855591],"type":"Point"}
}