{
  "type": "Feature",
  "properties": {
    "addr:full":"Rue Capronnier 36 Bruxelles (schaerbeek) Bruxelles-Capitale 1030",
    "addr:housenumber":"36",
    "addr:postcode":"1030",
    "addr:street":"Rue Capronnier",
    "iso:country":"BE",
    "sg:address":"Rue Capronnier 36",
    "sg:city":"Bruxelles (schaerbeek)",
    "sg:classifiers":[
        {
            "category":"Bars & Pubs",
            "type":"Food & Drink"
        }
    ],
    "sg:phone":"+32 2 245 41 17",
    "sg:postcode":"1030",
    "sg:province":"Bruxelles-Capitale",
    "wof:name":"Laurent (chez)",
    "wof:placetype":"venue"
},
  "geometry": {"coordinates":[4.3739180565,50.8735466003],"type":"Point"}
}