{
  "type": "Feature",
  "properties": {
    "iso:country":"BE",
    "sg:address":"Grand'rue 43",
    "sg:city":"Mont-saint-guibert",
    "sg:classifiers":[
        {
            "category":"Health Services",
            "subcategory":"Dentist",
            "type":"Services"
        }
    ],
    "sg:phone":"+32 10 65 84 54",
    "sg:postcode":"1435",
    "sg:province":"Brabant Wallon",
    "wof:name":"De Potter Alain",
    "wof:placetype":"venue"
},
  "geometry": {"coordinates":[4.6107521057,50.6339874268],"type":"Point"}
}