{
  "type": "Feature",
  "properties": {
    "addr:full":"Rue De Marchienne 8 Thuin Hainaut 6534",
    "addr:housenumber":"8",
    "addr:postcode":"6534",
    "addr:street":"Rue De Marchienne",
    "iso:country":"BE",
    "sg:address":"Rue De Marchienne 8",
    "sg:city":"Thuin",
    "sg:orig_category":"Banken and kredietinstellingen",
    "sg:phone":"+32 71 51 85 60",
    "sg:postcode":"6534",
    "sg:province":"Hainaut",
    "wof:name":"Dexia",
    "wof:placetype":"venue"
},
  "geometry": {"coordinates":[4.3518109322,50.3341140747],"type":"Point"}
}