{
  "type": "Feature",
  "properties": {
    "addr:full":"Beerveldestraat 64 Lokeren Oost-Vlaanderen 9160",
    "addr:housenumber":"64",
    "addr:postcode":"9160",
    "addr:street":"Beerveldestraat",
    "iso:country":"BE",
    "sg:address":"Beerveldestraat 64",
    "sg:city":"Lokeren",
    "sg:classifiers":[
        {
            "category":"Home & Garden",
            "subcategory":"Garden Supply",
            "type":"Retail Goods"
        }
    ],
    "sg:phone":"+32 9 349 13 31",
    "sg:postcode":"9160",
    "sg:province":"Oost-Vlaanderen",
    "wof:name":"Achten Renaat",
    "wof:placetype":"venue"
},
  "geometry": {"coordinates":[3.9318609238,51.0847702026],"type":"Point"}
}