{
  "type": "Feature",
  "properties": {
    "addr:full":"Mechelsestraat 58 Westerlo Antwerpen 2260",
    "addr:housenumber":"58",
    "addr:postcode":"2260",
    "addr:street":"Mechelsestraat",
    "iso:country":"BE",
    "sg:address":"Mechelsestraat 58",
    "sg:city":"Westerlo",
    "sg:orig_category":"Kapsalons",
    "sg:phone":"+32 14 21 26 17",
    "sg:postcode":"2260",
    "sg:province":"Antwerpen",
    "wof:name":"Coiffure Marleen",
    "wof:placetype":"venue"
},
  "geometry": {"coordinates":[4.8954439163,51.1387252808],"type":"Point"}
}