{
  "type": "Feature",
  "properties": {
    "addr:full":"Kortrijksesteenweg 180b11 Harelbeke West-Vlaanderen 8530",
    "addr:housenumber":"180b11",
    "addr:postcode":"8530",
    "addr:street":"Kortrijksesteenweg",
    "iso:country":"BE",
    "sg:address":"Kortrijksesteenweg 180b11",
    "sg:city":"Harelbeke",
    "sg:classifiers":[
        {
            "category":"Cafe",
            "type":"Food & Drink"
        }
    ],
    "sg:phone":"+32 56 70 53 59",
    "sg:postcode":"8530",
    "sg:province":"West-Vlaanderen",
    "sg:tags":[
        "caf\u00e9s"
    ],
    "wof:name":"Anastacia Cagampang",
    "wof:placetype":"venue"
},
  "geometry": {"coordinates":[3.2970659733,50.8467941284],"type":"Point"}
}