{
  "type": "Feature",
  "properties": {
    "addr:full":"Jan Breydelstraat 100 Harelbeke West-Vlaanderen 8530",
    "addr:housenumber":"100",
    "addr:postcode":"8530",
    "addr:street":"Jan Breydelstraat",
    "iso:country":"BE",
    "sg:address":"Jan Breydelstraat 100",
    "sg:city":"Harelbeke",
    "sg:classifiers":[
        {
            "category":"Communications",
            "subcategory":"Film & Video Production",
            "type":"Services"
        }
    ],
    "sg:phone":"+32 56 70 68 21",
    "sg:postcode":"8530",
    "sg:province":"West-Vlaanderen",
    "sg:tags":[
        "material",
        "audio-visual"
    ],
    "wof:name":"Vision-concepts",
    "wof:placetype":"venue"
},
  "geometry": {"coordinates":[3.295732975,50.8412017822],"type":"Point"}
}