{
  "type": "Feature",
  "properties": {
    "iso:country":"BE",
    "sg:address":"Terhulpsesteenweg 178b3",
    "sg:city":"Watermaal-bosvoorde/watermael-boitsfort",
    "sg:orig_category":"Marketingbureaus Marktonderzoekbureaus",
    "sg:phone":"+32 2 675 36 20",
    "sg:postcode":"1170",
    "sg:province":"Bruxelles-Capitale",
    "wof:name":"Bureau Survey & Action",
    "wof:placetype":"venue"
},
  "geometry": {"coordinates":[4.406908989,50.7956581116],"type":"Point"}
}