{
  "type": "Feature",
  "properties": {
    "iso:country":"BE",
    "sg:address":"Rue Alexandre Markelbach 70",
    "sg:city":"Bruxelles (schaerbeek)",
    "sg:classifiers":[
        {
            "category":"Arena",
            "subcategory":"Sports Club",
            "type":"Entertainment"
        }
    ],
    "sg:phone":"+32 2 241 49 88",
    "sg:postcode":"1030",
    "sg:province":"Bruxelles-Capitale",
    "sg:tags":[
        "martial art",
        "accessory"
    ],
    "wof:name":"Meibukan Asbl",
    "wof:placetype":"venue"
},
  "geometry": {"coordinates":[4.3830609322,50.8552017212],"type":"Point"}
}