{
  "type": "Feature",
  "properties": {
    "addr:full":"Chauss\u00c9e De Bruxelles 432 Tournai Hainaut 7500",
    "addr:housenumber":"432",
    "addr:postcode":"7500",
    "addr:street":"Chausse\u0301E De Bruxelles",
    "iso:country":"BE",
    "sg:address":"Chauss\u00c9e De Bruxelles 432",
    "sg:city":"Tournai",
    "sg:classifiers":[
        {
            "category":"Restaurant",
            "type":"Food & Drink"
        }
    ],
    "sg:phone":"+32 69 21 64 04",
    "sg:postcode":"7500",
    "sg:province":"Hainaut",
    "wof:name":"Le Gastronome",
    "wof:placetype":"venue"
},
  "geometry": {"coordinates":[3.4388380051,50.6009788513],"type":"Point"}
}