{
  "type": "Feature",
  "properties": {
    "addr:full":"Van Leriuslaan 170 Boom Antwerpen 2850",
    "addr:housenumber":"170",
    "addr:postcode":"2850",
    "addr:street":"Van Leriuslaan",
    "iso:country":"BE",
    "sg:address":"Van Leriuslaan 170",
    "sg:city":"Boom",
    "sg:classifiers":[
        {
            "category":"Bars & Pubs",
            "type":"Food & Drink"
        }
    ],
    "sg:phone":"+32 3 844 13 24",
    "sg:postcode":"2850",
    "sg:province":"Antwerpen",
    "wof:name":"Strandjutter (de)",
    "wof:placetype":"venue"
},
  "geometry": {"coordinates":[4.3758020401,51.0978546143],"type":"Point"}
}