{
  "type": "Feature",
  "properties": {
    "iso:country":"BE",
    "sg:address":"Lombardsijdestraat 120",
    "sg:city":"Brussel/bruxelles",
    "sg:orig_category":"Sportclubs",
    "sg:phone":"+32 2 476 00 43",
    "sg:postcode":"1120",
    "sg:province":"Bruxelles-Capitale",
    "wof:name":"Aidiko N.o.h.",
    "wof:placetype":"venue"
},
  "geometry": {"coordinates":[4.3772239685,50.8930664062],"type":"Point"}
}