{
  "type": "Feature",
  "properties": {
    "iso:country":"BE",
    "sg:address":"Albert I -promenade 63",
    "sg:city":"Oostende",
    "sg:classifiers":[
        {
            "category":"Restaurant",
            "type":"Food & Drink"
        }
    ],
    "sg:phone":"+32 59 80 21 15",
    "sg:postcode":"8400",
    "sg:province":"West-Vlaanderen",
    "sg:tags":[
        "caf\u00e9s"
    ],
    "wof:name":"Taverne Continental",
    "wof:placetype":"venue"
},
  "geometry": {"coordinates":[2.9105010033,51.230430603],"type":"Point"}
}