{
  "type": "Feature",
  "properties": {
    "addr:full":"Engelandstraat 35 Sint-gillis Bruxelles-Capitale 1060",
    "addr:housenumber":"35",
    "addr:postcode":"1060",
    "addr:street":"Engelandstraat",
    "iso:country":"BE",
    "sg:address":"Engelandstraat 35",
    "sg:city":"Sint-gillis",
    "sg:orig_category":"Plaatsen van vloer- and muurbekleding Schilders",
    "sg:phone":"+32 2 537 72 02",
    "sg:postcode":"1060",
    "sg:province":"Bruxelles-Capitale",
    "wof:name":"Agneessens & Fils",
    "wof:placetype":"venue"
},
  "geometry": {"coordinates":[4.3399858475,50.835067749],"type":"Point"}
}