{
  "type": "Feature",
  "properties": {
    "addr:full":"Rue De La Station 70 Ans Li\u00e8ge 4430",
    "addr:housenumber":"70",
    "addr:postcode":"4430",
    "addr:street":"Rue De La Station",
    "iso:country":"BE",
    "sg:address":"Rue De La Station 70",
    "sg:city":"Ans",
    "sg:orig_category":"Eleveurs d'animaux domestiques. Services pour animaux domestiques",
    "sg:phone":"+32 4 247 45 74",
    "sg:postcode":"4430",
    "sg:province":"Li\u00e8ge",
    "wof:name":"Jappy Toutou",
    "wof:placetype":"venue"
},
  "geometry": {"coordinates":[5.5099949837,50.6618499756],"type":"Point"}
}