{
  "type": "Feature",
  "properties": {
    "addr:full":"Baaikensstr. 9 Zele Oost-Vlaanderen 9240",
    "addr:housenumber":"9",
    "addr:postcode":"9240",
    "addr:street":"Baaikensstr.",
    "iso:country":"BE",
    "sg:address":"Baaikensstr. 9",
    "sg:city":"Zele",
    "sg:classifiers":[
        {
            "category":"Building & Trades",
            "subcategory":"Construction",
            "type":"Services"
        }
    ],
    "sg:phone":"+32 52 45 63 70",
    "sg:postcode":"9240",
    "sg:province":"Oost-Vlaanderen",
    "sg:tags":[
        "machine",
        "work",
        "-",
        "environment",
        "equipment",
        "engineering",
        "machinery",
        "mechanical",
        "public"
    ],
    "wof:name":"Verhofste Nv",
    "wof:placetype":"venue"
},
  "geometry": {"coordinates":[4.0536150932,51.0809593201],"type":"Point"}
}