{
  "type": "Feature",
  "properties": {
    "addr:full":"Route De Ciney 16 Rochefort Namur 5580",
    "addr:housenumber":"16",
    "addr:postcode":"5580",
    "addr:street":"Route De Ciney",
    "iso:country":"BE",
    "sg:address":"Route De Ciney 16",
    "sg:city":"Rochefort",
    "sg:classifiers":[
        {
            "category":"Home & Garden",
            "subcategory":"Furniture",
            "type":"Retail Goods"
        }
    ],
    "sg:phone":"+32 84 22 07 70",
    "sg:postcode":"5580",
    "sg:province":"Namur",
    "sg:tags":[
        "kitchen"
    ],
    "wof:name":"Lejac S.a.",
    "wof:placetype":"venue"
},
  "geometry": {"coordinates":[5.2104840279,50.176197052],"type":"Point"}
}