{
  "type": "Feature",
  "properties": {
    "iso:country":"BE",
    "sg:address":"Rue Albert Ier 316ba",
    "sg:city":"Erquelinnes",
    "sg:classifiers":[
        {
            "category":"Cafe",
            "type":"Food & Drink"
        }
    ],
    "sg:phone":"+32 71 55 52 50",
    "sg:postcode":"6560",
    "sg:province":"Hainaut",
    "sg:tags":[
        "caf\u00e9s"
    ],
    "wof:name":"Freddy Mathieu",
    "wof:placetype":"venue"
},
  "geometry": {"coordinates":[4.1128802299,50.3046112061],"type":"Point"}
}