{
  "type": "Feature",
  "properties": {
    "addr:full":"Kempenaarweg 4-6 Antwerpen Antwerpen 2030",
    "addr:housenumber":"4-6",
    "addr:postcode":"2030",
    "addr:street":"Kempenaarweg",
    "iso:country":"BE",
    "sg:address":"Kempenaarweg 4-6",
    "sg:city":"Antwerpen",
    "sg:classifiers":[
        {
            "category":"Utilities",
            "subcategory":"Recycling",
            "type":"Services"
        }
    ],
    "sg:phone":"+32 3 541 61 37",
    "sg:postcode":"2030",
    "sg:province":"Antwerpen",
    "wof:name":"Educar Vzw",
    "wof:placetype":"venue"
},
  "geometry": {"coordinates":[4.4130368233,51.2520942688],"type":"Point"}
}