{
  "type": "Feature",
  "properties": {
    "iso:country":"BE",
    "sg:address":"Gr. De Smet De Naeyerln 12",
    "sg:city":"Oostende",
    "sg:orig_category":"Apotheken",
    "sg:phone":"+32 59 70 20 52",
    "sg:postcode":"8400",
    "sg:province":"West-Vlaanderen",
    "wof:name":"Apotheek Van Dender",
    "wof:placetype":"venue"
},
  "geometry": {"coordinates":[2.9237880707,51.2259864807],"type":"Point"}
}