{
  "type": "Feature",
  "properties": {
    "addr:full":"Grote Baan 76 Herk-de-stad Limburg 3540",
    "addr:housenumber":"76",
    "addr:postcode":"3540",
    "addr:street":"Grote Baan",
    "iso:country":"BE",
    "sg:address":"Grote Baan 76",
    "sg:city":"Herk-de-stad",
    "sg:classifiers":[
        {
            "category":"Wholesale",
            "subcategory":"Vending Machines",
            "type":"Manufacturing & Wholesale Goods"
        }
    ],
    "sg:phone":"+32 13 44 22 44",
    "sg:postcode":"3540",
    "sg:province":"Limburg",
    "sg:tags":[
        "mat\u00e9riel",
        "de",
        "bureau",
        "gr",
        "fournitures"
    ],
    "wof:name":"Kantoormachines Vandijck",
    "wof:placetype":"venue"
},
  "geometry": {"coordinates":[5.1218409538,50.9485435486],"type":"Point"}
}