{
  "type": "Feature",
  "properties": {
    "addr:full":"Dorpsstraat 10ba Tielt-winge Vlaams-Brabant 3390",
    "addr:housenumber":"10ba",
    "addr:postcode":"3390",
    "addr:street":"Dorpsstraat",
    "iso:country":"BE",
    "sg:address":"Dorpsstraat 10ba",
    "sg:city":"Tielt-winge",
    "sg:orig_category":"Banken and kredietinstellingen",
    "sg:phone":"+32 16 63 45 17",
    "sg:postcode":"3390",
    "sg:province":"Vlaams-Brabant",
    "wof:name":"Kbc",
    "wof:placetype":"venue"
},
  "geometry": {"coordinates":[4.9125900269,50.9441719055],"type":"Point"}
}