{
  "type": "Feature",
  "properties": {
    "iso:country":"BE",
    "sg:address":"Rue Du Moulin 5",
    "sg:city":"Hamoir",
    "sg:classifiers":[
        {
            "category":"Health Services",
            "subcategory":"Doctor",
            "type":"Services"
        }
    ],
    "sg:phone":"+32 86 38 86 06",
    "sg:postcode":"4180",
    "sg:province":"Li\u00e8ge",
    "sg:tags":[
        "medicinephysicians",
        "surgeon"
    ],
    "wof:name":"Guisse Michel",
    "wof:placetype":"venue"
},
  "geometry": {"coordinates":[5.5327138901,50.4258232117],"type":"Point"}
}