{
  "type": "Feature",
  "properties": {
    "addr:full":"Torhoutsesteenweg 674 Oostende West-Vlaanderen 8400",
    "addr:housenumber":"674",
    "addr:postcode":"8400",
    "addr:street":"Torhoutsesteenweg",
    "iso:country":"BE",
    "sg:address":"Torhoutsesteenweg 674",
    "sg:city":"Oostende",
    "sg:orig_category":"V\u00e9hicules automobiles. Entretien and r\u00e9parations de voitures",
    "sg:phone":"+32 59 80 07 60",
    "sg:postcode":"8400",
    "sg:province":"West-Vlaanderen",
    "wof:name":"Junior Cars",
    "wof:placetype":"venue"
},
  "geometry": {"coordinates":[2.9064500332,51.2142601013],"type":"Point"}
}