{
  "type": "Feature",
  "properties": {
    "addr:full":"Wijnendalestraat 207 Roeselare West-Vlaanderen 8800",
    "addr:housenumber":"207",
    "addr:postcode":"8800",
    "addr:street":"Wijnendalestraat",
    "iso:country":"BE",
    "sg:address":"Wijnendalestraat 207",
    "sg:city":"Roeselare",
    "sg:classifiers":[
        {
            "category":"Structure",
            "subcategory":"Building",
            "type":"Public Place"
        }
    ],
    "sg:phone":"+32 51 20 83 23",
    "sg:postcode":"8800",
    "sg:province":"West-Vlaanderen",
    "sg:tags":[
        "apartment"
    ],
    "wof:name":"Vinckier-cloet B.v.b.a.",
    "wof:placetype":"venue"
},
  "geometry": {"coordinates":[3.1216139793,50.9724464417],"type":"Point"}
}