{
  "type": "Feature",
  "properties": {
    "addr:full":"Place Des Combattants 1 Charleroi (goutroux) Hainaut 6030",
    "addr:housenumber":"1",
    "addr:postcode":"6030",
    "addr:street":"Place Des Combattants",
    "iso:country":"BE",
    "sg:address":"Place Des Combattants 1",
    "sg:city":"Charleroi (goutroux)",
    "sg:classifiers":[
        {
            "category":"Bars & Pubs",
            "type":"Food & Drink"
        }
    ],
    "sg:phone":"+32 71 31 80 81",
    "sg:postcode":"6030",
    "sg:province":"Hainaut",
    "wof:name":"Bijou (le)",
    "wof:placetype":"venue"
},
  "geometry": {"coordinates":[4.3933801651,50.4121894836],"type":"Point"}
}