{
  "type": "Feature",
  "properties": {
    "iso:country":"BE",
    "sg:address":"Les Trixhes 24",
    "sg:city":"Thimister-clermont (clermont)",
    "sg:classifiers":[
        {
            "category":"Building & Trades",
            "subcategory":"Construction",
            "type":"Services"
        }
    ],
    "sg:phone":"+32 87 68 60 04",
    "sg:postcode":"4890",
    "sg:province":"Li\u00e8ge",
    "sg:tags":[
        "installation",
        "-",
        "central",
        "heating"
    ],
    "wof:name":"Mar\u00e9chal Robert",
    "wof:placetype":"venue"
},
  "geometry": {"coordinates":[5.8477897644,50.6816291809],"type":"Point"}
}