{
  "type": "Feature",
  "properties": {
    "addr:full":"Rue Fran\u00c7ois Dorz\u00c9e 111 Boussu Hainaut 7300",
    "addr:housenumber":"111",
    "addr:postcode":"7300",
    "addr:street":"Rue Franc\u0327Ois Dorze\u0301E",
    "iso:country":"BE",
    "sg:address":"Rue Fran\u00c7ois Dorz\u00c9e 111",
    "sg:city":"Boussu",
    "sg:orig_category":"Brood, gebak and snoepgoed",
    "sg:phone":"+32 65 78 34 69",
    "sg:postcode":"7300",
    "sg:province":"Hainaut",
    "wof:name":"J. Delvaux",
    "wof:placetype":"venue"
},
  "geometry": {"coordinates":[3.8019111156,50.4323348999],"type":"Point"}
}