{
  "type": "Feature",
  "properties": {
    "iso:country":"BE",
    "sg:address":"Chauss\u00c9e De Namur 73",
    "sg:city":"Gembloux",
    "sg:orig_category":"Groenten and fruit Gh",
    "sg:phone":"+32 81 61 08 71",
    "sg:postcode":"5030",
    "sg:province":"Namur",
    "wof:name":"La Pommeraie",
    "wof:placetype":"venue"
},
  "geometry": {"coordinates":[4.7037668228,50.5566940308],"type":"Point"}
}