{
  "type": "Feature",
  "properties": {
    "addr:full":"Wetstraat 15 Etterbeek Bruxelles-Capitale 1040",
    "addr:housenumber":"15",
    "addr:postcode":"1040",
    "addr:street":"Wetstraat",
    "iso:country":"BE",
    "sg:address":"Wetstraat 15",
    "sg:city":"Etterbeek",
    "sg:orig_category":"Beheer onroerend goed Immobili\u00ebnkantoren",
    "sg:phone":"+32 2 230 01 06",
    "sg:postcode":"1040",
    "sg:province":"Bruxelles-Capitale",
    "wof:name":"St.martinus Properties/st.martins Properties",
    "wof:placetype":"venue"
},
  "geometry": {"coordinates":[4.3870849609,50.8363609314],"type":"Point"}
}