{
  "type": "Feature",
  "properties": {
    "addr:full":"Brand Whitlocklaan 24 Sint-lambrechts-woluwe/woluwe-saint-lambert Bruxelles-Capitale 1200",
    "addr:housenumber":"24",
    "addr:postcode":"1200",
    "addr:street":"Brand Whitlocklaan",
    "iso:country":"BE",
    "sg:address":"Brand Whitlocklaan 24",
    "sg:city":"Sint-lambrechts-woluwe/woluwe-saint-lambert",
    "sg:orig_category":"Platenmaatschappijen",
    "sg:phone":"+32 2 775 81 40",
    "sg:postcode":"1200",
    "sg:province":"Bruxelles-Capitale",
    "wof:name":"Universal Music",
    "wof:placetype":"venue"
},
  "geometry": {"coordinates":[4.4082670212,50.8392944336],"type":"Point"}
}