{
  "type": "Feature",
  "properties": {
    "iso:country":"BE",
    "sg:address":"Avenue Albert Einstein 7",
    "sg:city":"Louvain-la-neuve",
    "sg:classifiers":[
        {
            "category":"Shopping",
            "subcategory":"Pawn Shop",
            "type":"Retail Goods"
        }
    ],
    "sg:phone":"+32 3 829 89 11",
    "sg:postcode":"1348",
    "sg:province":"Brabant Wallon",
    "sg:tags":[
        "modular",
        "fitting"
    ],
    "wof:name":"Hansa Mertens Nv",
    "wof:placetype":"venue"
},
  "geometry": {"coordinates":[4.370953083,51.1576118469],"type":"Point"}
}