{
  "type": "Feature",
  "properties": {
    "addr:full":"Kleine Asstraat 2 Koekelare West-Vlaanderen 8680",
    "addr:housenumber":"2",
    "addr:postcode":"8680",
    "addr:street":"Kleine Asstraat",
    "iso:country":"BE",
    "sg:address":"Kleine Asstraat 2",
    "sg:city":"Koekelare",
    "sg:orig_category":"Enseignement maternel and primaire",
    "sg:phone":"+32 51 58 20 02",
    "sg:postcode":"8680",
    "sg:province":"West-Vlaanderen",
    "wof:name":"Vrije Basisschool",
    "wof:placetype":"venue"
},
  "geometry": {"coordinates":[2.9400351048,51.0849494934],"type":"Point"}
}