{
  "type": "Feature",
  "properties": {
    "iso:country":"BE",
    "sg:address":"Avenue De Beaufort 7-1",
    "sg:city":"Huy",
    "sg:classifiers":[
        {
            "category":"Building & Trades",
            "subcategory":"Construction",
            "type":"Services"
        }
    ],
    "sg:phone":"+32 85 21 76 30",
    "sg:postcode":"4500",
    "sg:province":"Li\u00e8ge",
    "sg:tags":[
        "machine",
        "hiring"
    ],
    "wof:name":"Tomrental S.p.r.l.",
    "wof:placetype":"venue"
},
  "geometry": {"coordinates":[5.1705851555,50.5109634399],"type":"Point"}
}