{
  "type": "Feature",
  "properties": {
    "addr:full":"Mgr. Meulemanstraat 49 Sint-lievens-houtem Oost-Vlaanderen 9520",
    "addr:housenumber":"49",
    "addr:postcode":"9520",
    "addr:street":"Mgr. Meulemanstraat",
    "iso:country":"BE",
    "sg:address":"Mgr. Meulemanstraat 49",
    "sg:city":"Sint-lievens-houtem",
    "sg:orig_category":"Slagers",
    "sg:phone":"+32 53 62 81 07",
    "sg:postcode":"9520",
    "sg:province":"Oost-Vlaanderen",
    "wof:name":"Lieven D'hauwers",
    "wof:placetype":"venue"
},
  "geometry": {"coordinates":[3.8486878872,50.9238891602],"type":"Point"}
}