{
  "type": "Feature",
  "properties": {
    "addr:full":"Rue Puits-marie 101 Seraing Li\u00e8ge 4100",
    "addr:housenumber":"101",
    "addr:postcode":"4100",
    "addr:street":"Rue Puits-Marie",
    "iso:country":"BE",
    "sg:address":"Rue Puits-marie 101",
    "sg:city":"Seraing",
    "sg:classifiers":[
        {
            "category":"Retail",
            "subcategory":"Auto Repair",
            "type":"Services"
        }
    ],
    "sg:phone":"+32 4 336 77 88",
    "sg:postcode":"4100",
    "sg:province":"Li\u00e8ge",
    "sg:tags":[
        "automobile-body"
    ],
    "wof:name":"Isa Car Sprl",
    "wof:placetype":"venue"
},
  "geometry": {"coordinates":[5.5234498978,50.6064910889],"type":"Point"}
}