{
  "type": "Feature",
  "properties": {
    "addr:full":"Holleweg 1 Tongeren (vreren) Limburg 3700",
    "addr:housenumber":"1",
    "addr:postcode":"3700",
    "addr:street":"Holleweg",
    "iso:country":"BE",
    "sg:address":"Holleweg 1",
    "sg:city":"Tongeren (vreren)",
    "sg:classifiers":[
        {
            "category":"Professional",
            "subcategory":"Management & Consulting",
            "type":"Services"
        }
    ],
    "sg:phone":"+32 12 39 26 47",
    "sg:postcode":"3700",
    "sg:province":"Limburg",
    "sg:tags":[
        "tax-consultants"
    ],
    "wof:name":"Mantels M",
    "wof:placetype":"venue"
},
  "geometry": {"coordinates":[5.49477005,50.7511711121],"type":"Point"}
}