{
  "type": "Feature",
  "properties": {
    "iso:country":"BE",
    "sg:address":"Rue Du Stiersoux 24",
    "sg:city":"Sprimont",
    "sg:classifiers":[
        {
            "category":"Home & Garden",
            "subcategory":"Carpets & Floor Coverings",
            "type":"Retail Goods"
        }
    ],
    "sg:phone":"+32 4 382 13 53",
    "sg:postcode":"4140",
    "sg:province":"Li\u00e8ge",
    "sg:tags":[
        "tile"
    ],
    "wof:name":"Delaitte B",
    "wof:placetype":"venue"
},
  "geometry": {"coordinates":[5.6592841148,50.5059127808],"type":"Point"}
}