{
  "type": "Feature",
  "properties": {
    "iso:country":"BE",
    "sg:address":"Wingepark 25",
    "sg:city":"Rotselaar",
    "sg:classifiers":[
        {
            "category":"Professional",
            "subcategory":"Advertising",
            "type":"Services"
        }
    ],
    "sg:phone":"+32 16 44 77 78",
    "sg:postcode":"3110",
    "sg:province":"Vlaams-Brabant",
    "sg:tags":[
        "communication",
        "medium"
    ],
    "wof:name":"Markant Bvba",
    "wof:placetype":"venue"
},
  "geometry": {"coordinates":[4.7456021309,50.9411735535],"type":"Point"}
}