{
  "type": "Feature",
  "properties": {
    "addr:full":"Boseind 134bb Neerpelt Limburg 3910",
    "addr:postcode":"3910",
    "iso:country":"BE",
    "sg:address":"Boseind 134bb",
    "sg:city":"Neerpelt",
    "sg:orig_category":"Catering and organisation de f\u00eates",
    "sg:phone":"+32 11 66 14 59",
    "sg:postcode":"3910",
    "sg:province":"Limburg",
    "wof:name":"Traiteur Anita",
    "wof:placetype":"venue"
},
  "geometry": {"coordinates":[5.4408230782,51.2137298584],"type":"Point"}
}