{
  "type": "Feature",
  "properties": {
    "addr:full":"Bredabaan 129bb Brasschaat Antwerpen 2930",
    "addr:housenumber":"129bb",
    "addr:postcode":"2930",
    "addr:street":"Bredabaan",
    "iso:country":"BE",
    "sg:address":"Bredabaan 129bb",
    "sg:city":"Brasschaat",
    "sg:orig_category":"Syst\u00e8mes de t\u00e9l\u00e9communications",
    "sg:phone":"+32 3 650 10 30",
    "sg:postcode":"2930",
    "sg:province":"Antwerpen",
    "wof:name":"Tadicom Belgium",
    "wof:placetype":"venue"
},
  "geometry": {"coordinates":[4.4829530716,51.2841796875],"type":"Point"}
}