{
  "type": "Feature",
  "properties": {
    "addr:full":"Rue De Fl\u00e9ron 20 Fl\u00e9ron (magn\u00e9e) Li\u00e8ge 4623",
    "addr:housenumber":"20",
    "addr:postcode":"4623",
    "addr:street":"Rue De Fle\u0301Ron",
    "iso:country":"BE",
    "sg:address":"Rue De Fl\u00e9ron 20",
    "sg:city":"Fl\u00e9ron (magn\u00e9e)",
    "sg:classifiers":[
        {
            "category":"Building & Trades",
            "subcategory":"Construction",
            "type":"Services"
        }
    ],
    "sg:phone":"+32 4 358 84 00",
    "sg:postcode":"4623",
    "sg:province":"Li\u00e8ge",
    "sg:tags":[
        "carpenter"
    ],
    "wof:name":"Selles R",
    "wof:placetype":"venue"
},
  "geometry": {"coordinates":[5.6799798012,50.6048316956],"type":"Point"}
}