{
  "type": "Feature",
  "properties": {
    "iso:country":"BE",
    "sg:address":"Chauss\u00c9e De Helmet 35",
    "sg:city":"Schaarbeek/schaerbeek",
    "sg:orig_category":"Biens d'occasion",
    "sg:phone":"+32 2 242 17 04",
    "sg:postcode":"1030",
    "sg:province":"Bruxelles-Capitale",
    "wof:name":"Fe. Brolencoeur",
    "wof:placetype":"venue"
},
  "geometry": {"coordinates":[4.3801941872,50.8696937561],"type":"Point"}
}