{
  "type": "Feature",
  "properties": {
    "iso:country":"BE",
    "sg:address":"Sint-jobsesteenweg 495",
    "sg:city":"Ukkel/uccle",
    "sg:orig_category":"Binnenhuisarchitecten",
    "sg:phone":"+32 2 374 37 87",
    "sg:postcode":"1180",
    "sg:province":"Bruxelles-Capitale",
    "wof:name":"Atelier Parallele",
    "wof:placetype":"venue"
},
  "geometry": {"coordinates":[4.3525800705,50.7919273376],"type":"Point"}
}