{
  "type": "Feature",
  "properties": {
    "addr:full":"Rue Tour Petit Ch\u00c2teau 66 Soignies Hainaut 7060",
    "addr:housenumber":"66",
    "addr:postcode":"7060",
    "addr:street":"Rue Tour Petit Cha\u0302Teau",
    "iso:country":"BE",
    "sg:address":"Rue Tour Petit Ch\u00c2teau 66",
    "sg:city":"Soignies",
    "sg:orig_category":"Experts-comptables",
    "sg:phone":"+32 67 33 53 64",
    "sg:postcode":"7060",
    "sg:province":"Hainaut",
    "wof:name":"Michel Legrand",
    "wof:placetype":"venue"
},
  "geometry": {"coordinates":[4.0634207726,50.572052002],"type":"Point"}
}