{
  "type": "Feature",
  "properties": {
    "addr:full":"Av De Heppignies Zi Heppignies Hainaut 6220",
    "addr:postcode":"6220",
    "addr:street":"Av De Heppignies Zi Heppignies Hainaut",
    "iso:country":"BE",
    "sg:address":"Av De Heppignies Zi",
    "sg:city":"Heppignies",
    "sg:classifiers":[
        {
            "category":"Professional",
            "subcategory":"Engineering",
            "type":"Services"
        }
    ],
    "sg:phone":"+32 71 37 37 95",
    "sg:postcode":"6220",
    "sg:province":"Hainaut",
    "sg:tags":[
        "machine",
        "chemistry",
        "-",
        "mechanical"
    ],
    "wof:name":"Immucor",
    "wof:placetype":"venue"
},
  "geometry": {"coordinates":[4.5496749878,50.4825363159],"type":"Point"}
}