{
  "type": "Feature",
  "properties": {
    "addr:full":"Strandlaan 232 Koksijde West-Vlaanderen 8670",
    "addr:housenumber":"232",
    "addr:postcode":"8670",
    "addr:street":"Strandlaan",
    "iso:country":"BE",
    "sg:address":"Strandlaan 232",
    "sg:city":"Koksijde",
    "sg:orig_category":"Apotheken",
    "sg:phone":"+32 58 51 24 85",
    "sg:postcode":"8670",
    "sg:province":"West-Vlaanderen",
    "wof:name":"Idesmedica",
    "wof:placetype":"venue"
},
  "geometry": {"coordinates":[2.6133730412,51.108745575],"type":"Point"}
}