{
  "type": "Feature",
  "properties": {
    "addr:full":"Jan Persijnstraat 1 Kortrijk West-Vlaanderen 8500",
    "addr:housenumber":"1",
    "addr:postcode":"8500",
    "addr:street":"Jan Persijnstraat",
    "iso:country":"BE",
    "sg:address":"Jan Persijnstraat 1",
    "sg:city":"Kortrijk",
    "sg:orig_category":"Studios photographiques. Equipement photographique",
    "sg:phone":"+32 56 21 66 22",
    "sg:postcode":"8500",
    "sg:province":"West-Vlaanderen",
    "wof:name":"Kristien Soreyn",
    "wof:placetype":"venue"
},
  "geometry": {"coordinates":[3.2637209892,50.8275375366],"type":"Point"}
}