{
  "type": "Feature",
  "properties": {
    "iso:country":"BE",
    "sg:address":"Chauss\u00c9e De Waterloo 56-58",
    "sg:city":"Saint-gilles",
    "sg:orig_category":"Kleding Werk- and beschermkleding Fab",
    "sg:phone":"+32 2 537 04 56",
    "sg:postcode":"1060",
    "sg:province":"Bruxelles-Capitale",
    "wof:name":"Van Assche",
    "wof:placetype":"venue"
},
  "geometry": {"coordinates":[4.3448138237,50.8308181763],"type":"Point"}
}