{
  "type": "Feature",
  "properties": {
    "addr:full":"Wiedauwkaai 123 Gent Oost-Vlaanderen 9000",
    "addr:housenumber":"123",
    "addr:postcode":"9000",
    "addr:street":"Wiedauwkaai;Oost-Vlaanderen",
    "iso:country":"BE",
    "sg:address":"Wiedauwkaai 123",
    "sg:city":"Gent",
    "sg:orig_category":"Afbraak- and draineerwerken",
    "sg:phone":"+32 9 253 43 73",
    "sg:postcode":"9000",
    "sg:province":"Oost-Vlaanderen",
    "wof:name":"Fort-trans",
    "wof:placetype":"venue"
},
  "geometry": {"coordinates":[3.7255949974,51.0872116089],"type":"Point"}
}