{
  "type": "Feature",
  "properties": {
    "iso:country":"BE",
    "sg:address":"Rue Le Sart 9",
    "sg:city":"Amay",
    "sg:orig_category":"Tweedehandsgoederen",
    "sg:phone":"+32 85 31 50 92",
    "sg:postcode":"4540",
    "sg:province":"Li\u00e8ge",
    "wof:name":"Broc-ant",
    "wof:placetype":"venue"
},
  "geometry": {"coordinates":[5.3274970055,50.5569725037],"type":"Point"}
}