{
  "type": "Feature",
  "properties": {
    "iso:country":"BE",
    "sg:address":"Grote Markt 4",
    "sg:city":"Zoutleeuw",
    "sg:orig_category":"Non-Classified Establishments",
    "sg:phone":"+32 11 78 42 83",
    "sg:postcode":"3440",
    "sg:province":"Vlaams-Brabant",
    "wof:name":"Renaerts Vleeswaren Voco",
    "wof:placetype":"venue"
},
  "geometry": {"coordinates":[5.1026902199,50.8328971863],"type":"Point"}
}