{
  "type": "Feature",
  "properties": {
    "iso:country":"BE",
    "sg:address":"Rue Try Des Rudes 51",
    "sg:city":"Chastre",
    "sg:orig_category":"Rev\u00eatements pour sols and murs. Charpentes and couvertures. Peinture",
    "sg:phone":"+32 81 61 38 09",
    "sg:postcode":"1450",
    "sg:province":"Brabant Wallon",
    "wof:name":"Van Wonterghem Fr\u00c8res",
    "wof:placetype":"venue"
},
  "geometry": {"coordinates":[4.6532201767,50.5711708069],"type":"Point"}
}