{
  "type": "Feature",
  "properties": {
    "addr:full":"Quai Aux Hu\u00cetres Wavre Brabant Wallon 1300",
    "addr:housenumber":"1300",
    "addr:street":"Quai Aux Hui\u0302Tres",
    "iso:country":"BE",
    "sg:address":"Quai Aux Hu\u00cetres",
    "sg:city":"Wavre",
    "sg:orig_category":"Voedingsspeciaalzaken",
    "sg:phone":"+32 10 22 85 83",
    "sg:postcode":"1300",
    "sg:province":"Brabant Wallon",
    "wof:name":"Dame Nature",
    "wof:placetype":"venue"
},
  "geometry": {"coordinates":[4.6115560532,50.7149887085],"type":"Point"}
}