{
  "type": "Feature",
  "properties": {
    "addr:full":"Provincieweg 503 Herzele Oost-Vlaanderen 9550",
    "addr:housenumber":"503",
    "addr:postcode":"9550",
    "addr:street":"Provincieweg;Oost-Vlaanderen",
    "iso:country":"BE",
    "sg:address":"Provincieweg 503",
    "sg:city":"Herzele",
    "sg:orig_category":"Avocats and conseillers juridiques",
    "sg:phone":"+32 9 361 07 99",
    "sg:postcode":"9550",
    "sg:province":"Oost-Vlaanderen",
    "wof:name":"Lieven Pluym",
    "wof:placetype":"venue"
},
  "geometry": {"coordinates":[3.8787400723,50.8998908997],"type":"Point"}
}