{
  "type": "Feature",
  "properties": {
    "iso:country":"BE",
    "sg:address":"Rue Ferdinand Nicolay 443",
    "sg:city":"Saint-nicolas",
    "sg:classifiers":[
        {
            "category":"Professional",
            "subcategory":"Art Services",
            "type":"Services"
        }
    ],
    "sg:phone":"+32 4 234 34 14",
    "sg:postcode":"4420",
    "sg:province":"Li\u00e8ge",
    "sg:tags":[
        "installation",
        "cafe",
        "-",
        "equipment"
    ],
    "wof:name":"Horeca Primalux",
    "wof:placetype":"venue"
},
  "geometry": {"coordinates":[5.5316700935,50.6254386902],"type":"Point"}
}