{
  "type": "Feature",
  "properties": {
    "addr:full":"Speiestraat 133 Wervik West-Vlaanderen 8940",
    "addr:housenumber":"133",
    "addr:postcode":"8940",
    "addr:street":"Speiestraat",
    "iso:country":"BE",
    "sg:address":"Speiestraat 133",
    "sg:city":"Wervik",
    "sg:orig_category":"Kapsalons",
    "sg:phone":"+32 56 31 23 50",
    "sg:postcode":"8940",
    "sg:province":"West-Vlaanderen",
    "wof:name":"Coiffure Sonia",
    "wof:placetype":"venue"
},
  "geometry": {"coordinates":[3.0532419682,50.7812957764],"type":"Point"}
}