{
  "type": "Feature",
  "properties": {
    "addr:full":"Rue Masui 111 Brussel/bruxelles Bruxelles-Capitale 1000",
    "addr:housenumber":"111",
    "addr:postcode":"1000",
    "addr:street":"Rue Masui;/",
    "iso:country":"BE",
    "sg:address":"Rue Masui 111",
    "sg:city":"Brussel/bruxelles",
    "sg:orig_category":"Epiceries",
    "sg:phone":"+32 2 203 21 05",
    "sg:postcode":"1000",
    "sg:province":"Bruxelles-Capitale",
    "wof:name":"Maison Metro",
    "wof:placetype":"venue"
},
  "geometry": {"coordinates":[4.3600540161,50.8674316406],"type":"Point"}
}