{
  "type": "Feature",
  "properties": {
    "addr:full":"Hagelandstraat 6 Halen Limburg 3545",
    "addr:housenumber":"6",
    "addr:postcode":"3545",
    "addr:street":"Hagelandstraat",
    "iso:country":"BE",
    "sg:address":"Hagelandstraat 6",
    "sg:city":"Halen",
    "sg:classifiers":[
        {
            "category":"Travel",
            "subcategory":"Bed & Breakfast",
            "type":"Entertainment"
        }
    ],
    "sg:phone":"+32 13 44 23 60",
    "sg:postcode":"3545",
    "sg:province":"Limburg",
    "sg:tags":[
        "ladder"
    ],
    "wof:name":"Das Bvba",
    "wof:placetype":"venue"
},
  "geometry": {"coordinates":[5.0623831749,50.9326095581],"type":"Point"}
}