{
  "type": "Feature",
  "properties": {
    "iso:country":"BE",
    "sg:address":"Rue Pont Bara 37",
    "sg:city":"Erquelinnes (solre-sur-sambre)",
    "sg:classifiers":[
        {
            "category":"Personal",
            "subcategory":"Beauty Salon",
            "type":"Services"
        }
    ],
    "sg:phone":"+32 71 55 77 81",
    "sg:postcode":"6560",
    "sg:province":"Hainaut",
    "sg:tags":[
        "lady",
        "-",
        "hairdressing"
    ],
    "wof:name":"Boucle D'or (la)",
    "wof:placetype":"venue"
},
  "geometry": {"coordinates":[4.1585068703,50.3070640564],"type":"Point"}
}