{
  "type": "Feature",
  "properties": {
    "addr:full":"Bredabaan 459 Brasschaat Antwerpen 2930",
    "addr:housenumber":"459",
    "addr:postcode":"2930",
    "addr:street":"Bredabaan",
    "iso:country":"BE",
    "sg:address":"Bredabaan 459",
    "sg:city":"Brasschaat",
    "sg:orig_category":"Procesbesturingssystemen Fab",
    "sg:phone":"+32 3 650 14 20",
    "sg:postcode":"2930",
    "sg:province":"Antwerpen",
    "wof:name":"Devlop Systems",
    "wof:placetype":"venue"
},
  "geometry": {"coordinates":[4.4949908257,51.2929954529],"type":"Point"}
}