{
  "type": "Feature",
  "properties": {
    "iso:country":"BE",
    "sg:address":"Rue Des Flaches 123",
    "sg:city":"Gerpinnes",
    "sg:orig_category":"Services pour animaux domestiques",
    "sg:phone":"+32 71 50 34 58",
    "sg:postcode":"6280",
    "sg:province":"Hainaut",
    "wof:name":"Au Petit Cabot\u00b4in",
    "wof:placetype":"venue"
},
  "geometry": {"coordinates":[4.5029101372,50.3350791931],"type":"Point"}
}