{
  "type": "Feature",
  "properties": {
    "iso:country":"BE",
    "sg:address":"Brugmannlaan 520",
    "sg:city":"Ukkel/uccle",
    "sg:orig_category":"Boekenuitgeverijen",
    "sg:phone":"+32 2 344 63 59",
    "sg:postcode":"1180",
    "sg:province":"Bruxelles-Capitale",
    "wof:name":"Sharmila Production",
    "wof:placetype":"venue"
},
  "geometry": {"coordinates":[4.3383588791,50.8009986877],"type":"Point"}
}