{
  "type": "Feature",
  "properties": {
    "iso:country":"BE",
    "sg:address":"Leeuwstraat 3",
    "sg:city":"Deinze",
    "sg:orig_category":"Kapsalons",
    "sg:phone":"+32 9 386 11 15",
    "sg:postcode":"9800",
    "sg:province":"Oost-Vlaanderen",
    "wof:name":"Coiffure Annette",
    "wof:placetype":"venue"
},
  "geometry": {"coordinates":[3.5012590885,50.9966049194],"type":"Point"}
}