{
  "type": "Feature",
  "properties": {
    "iso:country":"BE",
    "sg:address":"Gildenstraat 7 Box A",
    "sg:city":"Londerzeel",
    "sg:classifiers":[
        {
            "category":"Autos & Motor Vehicles",
            "subcategory":"Boat Sales",
            "type":"Retail Goods"
        }
    ],
    "sg:phone":"+32 52 30 69 00",
    "sg:postcode":"1840",
    "sg:province":"Vlaams-Brabant",
    "sg:tags":[
        "balloon"
    ],
    "wof:name":"Balouke Bvba",
    "wof:placetype":"venue"
},
  "geometry": {"coordinates":[4.3011660576,51.0014343262],"type":"Point"}
}