{
  "type": "Feature",
  "properties": {
    "iso:country":"BE",
    "sg:address":"'t Hofveld 10",
    "sg:city":"Dilbeek (groot - Bijgaarden)",
    "sg:classifiers":[
        {
            "category":"Science Facility",
            "type":"Public Place"
        }
    ],
    "sg:phone":"+32 2 468 50 76",
    "sg:postcode":"1702",
    "sg:province":"Vlaams-Brabant",
    "sg:tags":[
        "-",
        "management",
        "data",
        "processing"
    ],
    "wof:name":"Idg Hardware Service",
    "wof:placetype":"venue"
},
  "geometry": {"coordinates":[4.2737159729,50.8696746826],"type":"Point"}
}