{
  "type": "Feature",
  "properties": {
    "iso:country":"BE",
    "sg:address":"Noordstraat 19",
    "sg:city":"Gent",
    "sg:orig_category":"Slagers",
    "sg:phone":"+32 9 225 51 37",
    "sg:postcode":"9000",
    "sg:province":"Oost-Vlaanderen",
    "wof:name":"Slagerij Du Nord",
    "wof:placetype":"venue"
},
  "geometry": {"coordinates":[3.7086069584,51.0570678711],"type":"Point"}
}