{
  "type": "Feature",
  "properties": {
    "iso:country":"BE",
    "sg:address":"Fissebosstraat 14",
    "sg:city":"Peer",
    "sg:classifiers":[
        {
            "category":"Professional",
            "subcategory":"Advertising",
            "type":"Services"
        }
    ],
    "sg:phone":"+32 11 63 52 69",
    "sg:postcode":"3990",
    "sg:province":"Limburg",
    "sg:tags":[
        "item",
        "-",
        "business",
        "gift",
        "promotional"
    ],
    "wof:name":"Noel Gielen - Originol",
    "wof:placetype":"venue"
},
  "geometry": {"coordinates":[5.4706130028,51.1296691895],"type":"Point"}
}