{
  "type": "Feature",
  "properties": {
    "addr:full":"Capartlaan 13 Jette/jette Bruxelles-Capitale 1090",
    "addr:housenumber":"13",
    "addr:postcode":"1090",
    "addr:street":"Capartlaan",
    "iso:country":"BE",
    "sg:address":"Capartlaan 13",
    "sg:city":"Jette/jette",
    "sg:orig_category":"Artiesten and kunstenaars",
    "sg:phone":"+32 2 479 45 31",
    "sg:postcode":"1090",
    "sg:province":"Bruxelles-Capitale",
    "wof:name":"Jacquy Maridor",
    "wof:placetype":"venue"
},
  "geometry": {"coordinates":[4.3207011223,50.8855552673],"type":"Point"}
}