{
  "type": "Feature",
  "properties": {
    "iso:country":"BE",
    "sg:address":"Andr\u00c9 Nouilleplein 5",
    "sg:city":"Vloesberg/flobecq",
    "sg:orig_category":"Postkantoren Verzekeringsmakelaars and experts",
    "sg:phone":"+32 68 44 73 08",
    "sg:postcode":"7880",
    "sg:province":"Hainaut",
    "wof:name":"De Post",
    "wof:placetype":"venue"
},
  "geometry": {"coordinates":[3.7384300232,50.7368011475],"type":"Point"}
}