{
  "type": "Feature",
  "properties": {
    "addr:full":"Rue De Fouron 31 Dalhem Li\u00e8ge 4607",
    "addr:housenumber":"31",
    "addr:postcode":"4607",
    "addr:street":"Rue De Fouron",
    "iso:country":"BE",
    "sg:address":"Rue De Fouron 31",
    "sg:city":"Dalhem",
    "sg:orig_category":"Binnenhuisarchitecten",
    "sg:phone":"+32 4 379 54 18",
    "sg:postcode":"4607",
    "sg:province":"Li\u00e8ge",
    "wof:name":"Philippe Spee",
    "wof:placetype":"venue"
},
  "geometry": {"coordinates":[5.7345838547,50.7442932129],"type":"Point"}
}