{
  "type": "Feature",
  "properties": {
    "addr:full":"Slachthuislaan 50 Brussel/bruxelles Bruxelles-Capitale 1000",
    "addr:housenumber":"50",
    "addr:postcode":"1000",
    "addr:street":"Slachthuislaan;/",
    "iso:country":"BE",
    "sg:address":"Slachthuislaan 50",
    "sg:city":"Brussel/bruxelles",
    "sg:orig_category":"Volwassenenonderwijs",
    "sg:phone":"+32 2 279 51 00",
    "sg:postcode":"1000",
    "sg:province":"Bruxelles-Capitale",
    "wof:name":"Cours Industr. & Commerc.",
    "wof:placetype":"venue"
},
  "geometry": {"coordinates":[4.3391299248,50.8449287415],"type":"Point"}
}