{
  "type": "Feature",
  "properties": {
    "addr:full":"Legerlaan 128 Etterbeek Bruxelles-Capitale 1040",
    "addr:housenumber":"128",
    "addr:postcode":"1040",
    "addr:street":"Legerlaan",
    "iso:country":"BE",
    "sg:address":"Legerlaan 128",
    "sg:city":"Etterbeek",
    "sg:orig_category":"Industri\u00eble wasserijen and droogkuis",
    "sg:phone":"+32 2 735 56 92",
    "sg:postcode":"1040",
    "sg:province":"Bruxelles-Capitale",
    "wof:name":"B.t.b.",
    "wof:placetype":"venue"
},
  "geometry": {"coordinates":[4.4029197693,50.8338546753],"type":"Point"}
}