{
  "type": "Feature",
  "properties": {
    "iso:country":"BE",
    "sg:address":"Schouwburgplaats 2",
    "sg:city":"Maldegem",
    "sg:classifiers":[
        {
            "category":"Restaurant",
            "type":"Food & Drink"
        }
    ],
    "sg:phone":"+32 50 71 15 22",
    "sg:postcode":"9990",
    "sg:province":"Oost-Vlaanderen",
    "sg:tags":[
        "de",
        "organisation",
        "\u00e0",
        "fast",
        "catering",
        "emporter",
        "f\u00eates",
        "restaurants"
    ],
    "wof:name":"Zoetendale",
    "wof:placetype":"venue"
},
  "geometry": {"coordinates":[3.4485049248,51.2083625793],"type":"Point"}
}