{
  "type": "Feature",
  "properties": {
    "addr:full":"Brusselsesteenweg 35 Asse Vlaams-Brabant 1730",
    "addr:housenumber":"35",
    "addr:postcode":"1730",
    "addr:street":"Brusselsesteenweg",
    "iso:country":"BE",
    "sg:address":"Brusselsesteenweg 35",
    "sg:city":"Asse",
    "sg:orig_category":"Journaux. Tabac",
    "sg:phone":"+32 2 452 62 56",
    "sg:postcode":"1730",
    "sg:province":"Vlaams-Brabant",
    "wof:name":"Dagbladhandel Verscheure",
    "wof:placetype":"venue"
},
  "geometry": {"coordinates":[4.2105550766,50.9046554565],"type":"Point"}
}