{
  "type": "Feature",
  "properties": {
    "addr:full":"Chauss\u00c9e De Waterloo 174 Sint-genesius-rode/rhode-saint-genese Vlaams-Brabant 1640",
    "addr:housenumber":"174",
    "addr:postcode":"1640",
    "addr:street":"Chausse\u0301E De Waterloo",
    "iso:country":"BE",
    "sg:address":"Chauss\u00c9e De Waterloo 174",
    "sg:city":"Sint-genesius-rode/rhode-saint-genese",
    "sg:orig_category":"Antiquit\u00e9s",
    "sg:phone":"+32 2 358 28 08",
    "sg:postcode":"1640",
    "sg:province":"Vlaams-Brabant",
    "wof:name":"Galerie St.germain",
    "wof:placetype":"venue"
},
  "geometry": {"coordinates":[4.3935680389,50.7489318848],"type":"Point"}
}