{
  "type": "Feature",
  "properties": {
    "addr:full":"Leugenberg 270 Antwerpen (ekeren) Antwerpen 2180",
    "addr:housenumber":"270",
    "addr:postcode":"2180",
    "addr:street":"Leugenberg",
    "iso:country":"BE",
    "sg:address":"Leugenberg 270",
    "sg:city":"Antwerpen (ekeren)",
    "sg:classifiers":[
        {
            "category":"Bars & Pubs",
            "type":"Food & Drink"
        }
    ],
    "sg:phone":"+32 3 665 13 72",
    "sg:postcode":"2180",
    "sg:province":"Antwerpen",
    "sg:tags":[
        "tavern"
    ],
    "wof:name":"Koolpot Bvba",
    "wof:placetype":"venue"
},
  "geometry": {"coordinates":[4.4102401733,51.3030204773],"type":"Point"}
}