{
  "type": "Feature",
  "properties": {
    "iso:country":"BE",
    "sg:address":"Rue De La Halle 12",
    "sg:city":"Namur",
    "sg:orig_category":"Pain, p\u00e2tisseries and confiseries",
    "sg:phone":"+32 81 22 30 31",
    "sg:postcode":"5000",
    "sg:province":"Namur",
    "wof:name":"Jacques Allard",
    "wof:placetype":"venue"
},
  "geometry": {"coordinates":[4.8652482033,50.4627723694],"type":"Point"}
}