{
  "type": "Feature",
  "properties": {
    "iso:country":"BE",
    "sg:address":"Marktplein 14",
    "sg:city":"Harelbeke",
    "sg:orig_category":"Editeurs de journaux. Editeurs de revues and p\u00e9riodiques",
    "sg:phone":"+32 56 72 35 15",
    "sg:postcode":"8530",
    "sg:province":"West-Vlaanderen",
    "wof:name":"Vdk Press",
    "wof:placetype":"venue"
},
  "geometry": {"coordinates":[3.3106799126,50.8566589355],"type":"Point"}
}