{
  "type": "Feature",
  "properties": {
    "iso:country":"BE",
    "sg:address":"Platanendreef 7",
    "sg:city":"Waregem",
    "sg:orig_category":"Boucheries",
    "sg:phone":"+32 56 60 10 64",
    "sg:postcode":"8790",
    "sg:province":"West-Vlaanderen",
    "wof:name":"Slagerij Van Assche",
    "wof:placetype":"venue"
},
  "geometry": {"coordinates":[3.4005138874,50.8630142212],"type":"Point"}
}