{
  "type": "Feature",
  "properties": {
    "addr:full":"Dikberd 14 Herentals Antwerpen 2200",
    "addr:housenumber":"14",
    "addr:postcode":"2200",
    "addr:street":"Dikberd",
    "iso:country":"BE",
    "sg:address":"Dikberd 14",
    "sg:city":"Herentals",
    "sg:classifiers":[
        {
            "category":"Banks & Credit Unions",
            "subcategory":"Investment Brokerage",
            "type":"Services"
        }
    ],
    "sg:phone":"+32 14 21 11 42",
    "sg:postcode":"2200",
    "sg:province":"Antwerpen",
    "sg:tags":[
        "-",
        "plastic"
    ],
    "wof:name":"Voordeckers Herentals Nv",
    "wof:placetype":"venue"
},
  "geometry": {"coordinates":[4.850440979,51.1658248901],"type":"Point"}
}