{
  "type": "Feature",
  "properties": {
    "addr:full":"Rue Campagne De Bellaire 63 Fleron Li\u00e8ge 4621",
    "addr:housenumber":"63",
    "addr:postcode":"4621",
    "addr:street":"Rue Campagne De Bellaire",
    "iso:country":"BE",
    "sg:address":"Rue Campagne De Bellaire 63",
    "sg:city":"Fleron",
    "sg:classifiers":[
        {
            "category":"Personal",
            "subcategory":"Beauty Salon",
            "type":"Services"
        }
    ],
    "sg:phone":"+32 4 362 83 01",
    "sg:postcode":"4621",
    "sg:province":"Li\u00e8ge",
    "sg:tags":[
        "de",
        "coiffure"
    ],
    "wof:name":"Coiffure Ista",
    "wof:placetype":"venue"
},
  "geometry": {"coordinates":[5.6963891983,50.628704071],"type":"Point"}
}