{
  "type": "Feature",
  "properties": {
    "iso:country":"BE",
    "sg:address":"Route De Spa 155",
    "sg:city":"Francorchamps",
    "sg:orig_category":"RESTAURANTS: H\u00d4TELS",
    "sg:phone":"+32 87 27 53 11",
    "sg:postcode":"4970",
    "sg:province":"Li\u00e8ge",
    "wof:name":"Hostellerie Du Roannay",
    "wof:placetype":"venue"
},
  "geometry": {"coordinates":[5.9526767731,50.456615448],"type":"Point"}
}