{
  "type": "Feature",
  "properties": {
    "addr:full":"Rue L\u00c9opold 18 Dinant Namur 5500",
    "addr:housenumber":"18",
    "addr:postcode":"5500",
    "addr:street":"Rue Le\u0301Opold",
    "iso:country":"BE",
    "sg:address":"Rue L\u00c9opold 18",
    "sg:city":"Dinant",
    "sg:orig_category":"Herstelling horloges and juwelen Juwelen and horloges",
    "sg:phone":"+32 82 22 30 44",
    "sg:postcode":"5500",
    "sg:province":"Namur",
    "wof:name":"Maison Paul",
    "wof:placetype":"venue"
},
  "geometry": {"coordinates":[4.9169378281,50.2553482056],"type":"Point"}
}