{
  "type": "Feature",
  "properties": {
    "addr:full":"Rue Des Biston 1 Philippeville Namur 5600",
    "addr:housenumber":"1",
    "addr:postcode":"5600",
    "addr:street":"Rue Des Biston",
    "iso:country":"BE",
    "sg:address":"Rue Des Biston 1",
    "sg:city":"Philippeville",
    "sg:orig_category":"Enseignement maternel and primaire",
    "sg:phone":"+32 71 66 80 68",
    "sg:postcode":"5600",
    "sg:province":"Namur",
    "wof:name":"Ecole Prim. Communale",
    "wof:placetype":"venue"
},
  "geometry": {"coordinates":[4.6066560745,50.1897277832],"type":"Point"}
}