{
  "type": "Feature",
  "properties": {
    "addr:full":"Broechemlei 82 Ranst Antwerpen 2520",
    "addr:housenumber":"82",
    "addr:postcode":"2520",
    "addr:street":"Broechemlei",
    "iso:country":"BE",
    "sg:address":"Broechemlei 82",
    "sg:city":"Ranst",
    "sg:orig_category":"Producteurs de l\u00e9gumes",
    "sg:phone":"+32 3 485 57 52",
    "sg:postcode":"2520",
    "sg:province":"Antwerpen",
    "wof:name":"Frans Michiels",
    "wof:placetype":"venue"
},
  "geometry": {"coordinates":[4.5699300766,51.187625885],"type":"Point"}
}