{
  "type": "Feature",
  "properties": {
    "iso:country":"BE",
    "sg:address":"Jezus Eiklaan 2",
    "sg:city":"Tervuren",
    "sg:classifiers":[
        {
            "category":"Professional",
            "subcategory":"Testing Lab",
            "type":"Services"
        }
    ],
    "sg:phone":"+32 2 767 44 86",
    "sg:postcode":"3080",
    "sg:province":"Vlaams-Brabant",
    "sg:tags":[
        "chemist"
    ],
    "wof:name":"Apotheek Boone",
    "wof:placetype":"venue"
},
  "geometry": {"coordinates":[4.5055828094,50.8190765381],"type":"Point"}
}