{
  "type": "Feature",
  "properties": {
    "iso:country":"BE",
    "sg:address":"Rue De La D\u00e9portation 33",
    "sg:city":"Beaumont",
    "sg:classifiers":[
        {
            "category":"Education",
            "subcategory":"Dance Studio",
            "type":"Public Place"
        }
    ],
    "sg:phone":"+32 60 41 29 41",
    "sg:postcode":"6500",
    "sg:province":"Hainaut",
    "sg:tags":[
        "school",
        "dancing"
    ],
    "wof:name":"Centre De Danse D. Houben",
    "wof:placetype":"venue"
},
  "geometry": {"coordinates":[4.2383971214,50.2378959656],"type":"Point"}
}