{
  "type": "Feature",
  "properties": {
    "addr:full":"Orteliuskaai 2-4b26 Antwerpen Antwerpen 2000",
    "addr:housenumber":"2-4b26",
    "addr:postcode":"2000",
    "addr:street":"Orteliuskaai",
    "iso:country":"BE",
    "sg:address":"Orteliuskaai 2-4b26",
    "sg:city":"Antwerpen",
    "sg:orig_category":"Produits chimiques Gr",
    "sg:phone":"+32 3 205 93 70",
    "sg:postcode":"2000",
    "sg:province":"Antwerpen",
    "wof:name":"Petrochem Distribution",
    "wof:placetype":"venue"
},
  "geometry": {"coordinates":[4.4000592232,51.2254562378],"type":"Point"}
}