{
  "type": "Feature",
  "properties": {
    "addr:full":"Pelikaansstraat 92 Antwerpen Antwerpen 2018",
    "addr:housenumber":"92",
    "addr:postcode":"2018",
    "addr:street":"Pelikaansstraat",
    "iso:country":"BE",
    "sg:address":"Pelikaansstraat 92",
    "sg:city":"Antwerpen",
    "sg:orig_category":"Produits interm\u00e9diaires Gr",
    "sg:phone":"+32 3 233 73 07",
    "sg:postcode":"2018",
    "sg:province":"Antwerpen",
    "wof:name":"Bart L.b.",
    "wof:placetype":"venue"
},
  "geometry": {"coordinates":[4.4204611778,51.2141609192],"type":"Point"}
}