{
  "type": "Feature",
  "properties": {
    "addr:full":"Rue Des Crupes 8 Tournai Hainaut 7542",
    "addr:housenumber":"8",
    "addr:postcode":"7542",
    "addr:street":"Rue Des Crupes",
    "iso:country":"BE",
    "sg:address":"Rue Des Crupes 8",
    "sg:city":"Tournai",
    "sg:classifiers":[
        {
            "category":"Cafe",
            "type":"Food & Drink"
        }
    ],
    "sg:phone":"+32 69 23 57 60",
    "sg:postcode":"7542",
    "sg:province":"Hainaut",
    "sg:tags":[
        "caf\u00e9s"
    ],
    "wof:name":"Caf\u00c9 Au Cerf",
    "wof:placetype":"venue"
},
  "geometry": {"coordinates":[3.4037110806,50.6507339478],"type":"Point"}
}