{
  "type": "Feature",
  "properties": {
    "addr:full":"A. Boudrystraat 2 Koksijde West-Vlaanderen 8670",
    "addr:housenumber":"2",
    "addr:postcode":"8670",
    "addr:street":"Boudrystraat",
    "iso:country":"BE",
    "sg:address":"A. Boudrystraat 2",
    "sg:city":"Koksijde",
    "sg:orig_category":"Krantenwinkels Rookartikelen",
    "sg:phone":"+32 58 51 95 32",
    "sg:postcode":"8670",
    "sg:province":"West-Vlaanderen",
    "wof:name":"Christian Vanloocke",
    "wof:placetype":"venue"
},
  "geometry": {"coordinates":[2.67937994,51.1163063049],"type":"Point"}
}