{
  "type": "Feature",
  "properties": {
    "iso:country":"BE",
    "sg:address":"Lombaardstraat 51",
    "sg:city":"Sint-katelijne-waver",
    "sg:classifiers":[
        {
            "category":"Wholesale",
            "subcategory":"Plants",
            "type":"Manufacturing & Wholesale Goods"
        }
    ],
    "sg:phone":"+32 15 55 16 11",
    "sg:postcode":"2860",
    "sg:province":"Antwerpen",
    "sg:tags":[
        "whol",
        "flower",
        "-",
        "grower"
    ],
    "wof:name":"Goossens Bvba",
    "wof:placetype":"venue"
},
  "geometry": {"coordinates":[4.5317931175,51.0534286499],"type":"Point"}
}