{
  "type": "Feature",
  "properties": {
    "addr:full":"Rue De Philippeville 67 Ham-sur-heure-nalinnes (nalinnes) Hainaut 6120",
    "addr:housenumber":"67",
    "addr:postcode":"6120",
    "addr:street":"Rue De Philippeville;Hainaut",
    "iso:country":"BE",
    "sg:address":"Rue De Philippeville 67",
    "sg:city":"Ham-sur-heure-nalinnes (nalinnes)",
    "sg:classifiers":[
        {
            "category":"Home & Garden",
            "subcategory":"Home Furnishings",
            "type":"Retail Goods"
        }
    ],
    "sg:phone":"+32 71 21 39 25",
    "sg:postcode":"6120",
    "sg:province":"Hainaut",
    "sg:tags":[
        "curtain",
        "-",
        "fixture"
    ],
    "wof:name":"Mireille Martigny",
    "wof:placetype":"venue"
},
  "geometry": {"coordinates":[4.4746389389,50.3375930786],"type":"Point"}
}