{
  "type": "Feature",
  "properties": {
    "iso:country":"BE",
    "sg:address":"Route De L\u00b4ambleve 50",
    "sg:city":"Stoumont",
    "sg:orig_category":"HERSTELLING ELEKTRISCHE HUISHOUDAPPARATEN Huishoudapparaten, televisies and radio's",
    "sg:phone":"+32 80 78 54 67",
    "sg:postcode":"4987",
    "sg:province":"Li\u00e8ge",
    "wof:name":"Cremer",
    "wof:placetype":"venue"
},
  "geometry": {"coordinates":[5.808054924,50.4086227417],"type":"Point"}
}