{
  "type": "Feature",
  "properties": {
    "iso:country":"BE",
    "sg:address":"Elenestraat 281",
    "sg:city":"Zottegem",
    "sg:classifiers":[
        {
            "category":"Arena",
            "subcategory":"Sports Club",
            "type":"Entertainment"
        }
    ],
    "sg:phone":"+32 9 361 20 86",
    "sg:postcode":"9620",
    "sg:province":"Oost-Vlaanderen",
    "sg:tags":[
        "de"
    ],
    "wof:name":"T.c. Zottegem",
    "wof:placetype":"venue"
},
  "geometry": {"coordinates":[3.8086929321,50.8774681091],"type":"Point"}
}