{
  "type": "Feature",
  "properties": {
    "addr:full":"Mulstraat 10 Genk (waterschei) Limburg 3600",
    "addr:housenumber":"10",
    "addr:postcode":"3600",
    "addr:street":"Mulstraat",
    "iso:country":"BE",
    "sg:address":"Mulstraat 10",
    "sg:city":"Genk (waterschei)",
    "sg:orig_category":"Non-Classified Establishments",
    "sg:phone":"+32 89 81 07 81",
    "sg:postcode":"3600",
    "sg:province":"Limburg",
    "wof:name":"Regi Textiel Nv",
    "wof:placetype":"venue"
},
  "geometry": {"coordinates":[5.4990148544,50.9635848999],"type":"Point"}
}