{
  "type": "Feature",
  "properties": {
    "addr:full":"Motbroekstraat 53 Tielt-winge Vlaams-Brabant 3390",
    "addr:housenumber":"53",
    "addr:postcode":"3390",
    "addr:street":"Motbroekstraat",
    "iso:country":"BE",
    "sg:address":"Motbroekstraat 53",
    "sg:city":"Tielt-winge",
    "sg:classifiers":[
        {
            "category":"Arena",
            "subcategory":"Sports Club",
            "type":"Entertainment"
        }
    ],
    "sg:phone":"+32 16 63 39 93",
    "sg:postcode":"3390",
    "sg:province":"Vlaams-Brabant",
    "sg:tags":[
        "terrain",
        "hors",
        "de",
        "installation",
        "sportifs"
    ],
    "wof:name":"S.j.v. Motbroek",
    "wof:placetype":"venue"
},
  "geometry": {"coordinates":[4.8743720055,50.9215011597],"type":"Point"}
}