{
  "type": "Feature",
  "properties": {
    "addr:full":"Route Du Condroz 221 Neupr\u00c9 Li\u00e8ge 4120",
    "addr:housenumber":"221",
    "addr:postcode":"4120",
    "addr:street":"Route Du Condroz",
    "iso:country":"BE",
    "sg:address":"Route Du Condroz 221",
    "sg:city":"Neupr\u00c9",
    "sg:orig_category":"Woningbouw",
    "sg:phone":"+32 4 372 14 51",
    "sg:postcode":"4120",
    "sg:province":"Li\u00e8ge",
    "wof:name":"Goffin B\u00c2timents",
    "wof:placetype":"venue"
},
  "geometry": {"coordinates":[5.4400258064,50.540977478],"type":"Point"}
}