{
  "type": "Feature",
  "properties": {
    "addr:full":"Rue Pierre Renard 10 Orp-jauche (noduwez) Brabant Wallon 1350",
    "addr:housenumber":"10",
    "addr:postcode":"1350",
    "addr:street":"Rue Pierre Renard",
    "iso:country":"BE",
    "sg:address":"Rue Pierre Renard 10",
    "sg:city":"Orp-jauche (noduwez)",
    "sg:classifiers":[
        {
            "category":"Retail",
            "subcategory":"Event Space",
            "type":"Services"
        }
    ],
    "sg:phone":"+32 19 65 57 92",
    "sg:postcode":"1350",
    "sg:province":"Brabant Wallon",
    "sg:tags":[
        "rental",
        "-",
        "hall"
    ],
    "wof:name":"Ferme Du Gollard",
    "wof:placetype":"venue"
},
  "geometry": {"coordinates":[4.9649558067,50.729549408],"type":"Point"}
}