{
  "type": "Feature",
  "properties": {
    "iso:country":"BE",
    "sg:address":"Place Des Arsilliers 2ba",
    "sg:city":"Malmedy",
    "sg:orig_category":"Overheidsdiensten",
    "sg:phone":"+32 80 79 97 30",
    "sg:postcode":"4960",
    "sg:province":"Li\u00e8ge",
    "wof:name":"C.p.a.s.",
    "wof:placetype":"venue"
},
  "geometry": {"coordinates":[6.0253019333,50.423160553],"type":"Point"}
}