{
  "type": "Feature",
  "properties": {
    "addr:full":"Oostrozebekestraat 284 Ingelmunster West-Vlaanderen 8770",
    "addr:housenumber":"284",
    "addr:postcode":"8770",
    "addr:street":"Oostrozebekestraat",
    "iso:country":"BE",
    "sg:address":"Oostrozebekestraat 284",
    "sg:city":"Ingelmunster",
    "sg:classifiers":[
        {
            "category":"Professional",
            "subcategory":"Art Services",
            "type":"Services"
        }
    ],
    "sg:phone":"+32 56 66 52 17",
    "sg:postcode":"8770",
    "sg:province":"West-Vlaanderen",
    "sg:tags":[
        "shop",
        "paint",
        "spraying"
    ],
    "wof:name":"L.c.i. Painting Systems",
    "wof:placetype":"venue"
},
  "geometry": {"coordinates":[3.2855279446,50.916229248],"type":"Point"}
}