{
  "type": "Feature",
  "properties": {
    "addr:full":"Rue J. Besne 131 Koekelberg Bruxelles-Capitale 1081",
    "addr:housenumber":"131",
    "addr:postcode":"1081",
    "addr:street":"Rue J. Besne",
    "iso:country":"BE",
    "sg:address":"Rue J. Besne 131",
    "sg:city":"Koekelberg",
    "sg:orig_category":"V\u00e9hicules automobiles",
    "sg:phone":"+32 2 358 49 58",
    "sg:postcode":"1081",
    "sg:province":"Bruxelles-Capitale",
    "wof:name":"Vintage Classics Intern.",
    "wof:placetype":"venue"
},
  "geometry": {"coordinates":[4.3315048218,50.8606834412],"type":"Point"}
}