{
  "type": "Feature",
  "properties": {
    "iso:country":"BE",
    "sg:address":"Stoofstraat 21",
    "sg:city":"Merchtem",
    "sg:classifiers":[
        {
            "category":"Food & Beverages",
            "subcategory":"Supermarket",
            "type":"Retail Goods"
        }
    ],
    "sg:phone":"+32 52 37 16 64",
    "sg:postcode":"1785",
    "sg:province":"Vlaams-Brabant",
    "sg:tags":[
        "department",
        "store"
    ],
    "wof:name":"Battard Noord Nv",
    "wof:placetype":"venue"
},
  "geometry": {"coordinates":[4.2338662148,50.9569587708],"type":"Point"}
}