{
  "type": "Feature",
  "properties": {
    "iso:country":"BE",
    "sg:address":"Justin Scheepmansstraat 7",
    "sg:city":"Oud-heverlee",
    "sg:classifiers":[
        {
            "category":"Health Services",
            "subcategory":"Health Practitioner",
            "type":"Services"
        }
    ],
    "sg:phone":"+32 16 47 19 49",
    "sg:postcode":"3050",
    "sg:province":"Vlaams-Brabant",
    "sg:tags":[
        "psychologist"
    ],
    "wof:name":"Allemeersch B",
    "wof:placetype":"venue"
},
  "geometry": {"coordinates":[4.6561379433,50.8157730103],"type":"Point"}
}