{
  "type": "Feature",
  "properties": {
    "addr:full":"Geerdegem Schonenberg 17 Mechelen Antwerpen 2800",
    "addr:housenumber":"17",
    "addr:postcode":"2800",
    "addr:street":"Schonenberg",
    "iso:country":"BE",
    "sg:address":"Geerdegem Schonenberg 17",
    "sg:city":"Mechelen",
    "sg:classifiers":[
        {
            "category":"Bakery",
            "type":"Food & Drink"
        }
    ],
    "sg:phone":"+32 15 43 33 01",
    "sg:postcode":"2800",
    "sg:province":"Antwerpen",
    "sg:tags":[
        "confectioner",
        "baker"
    ],
    "wof:name":"Kadetje ('t)",
    "wof:placetype":"venue"
},
  "geometry": {"coordinates":[4.4672207832,51.0169830322],"type":"Point"}
}