{
  "type": "Feature",
  "properties": {
    "addr:full":"Albert Li\u00c9nartstraat 11bc Aalst Oost-Vlaanderen 9300",
    "addr:housenumber":"11bc",
    "addr:postcode":"9300",
    "addr:street":"Albert Lie\u0301Nartstraat",
    "iso:country":"BE",
    "sg:address":"Albert Li\u00c9nartstraat 11bc",
    "sg:city":"Aalst",
    "sg:orig_category":"Epiceries",
    "sg:phone":"+32 53 77 40 82",
    "sg:postcode":"9300",
    "sg:province":"Oost-Vlaanderen",
    "wof:name":"Marcella Annaert",
    "wof:placetype":"venue"
},
  "geometry": {"coordinates":[4.0394029617,50.9414482117],"type":"Point"}
}