{
  "type": "Feature",
  "properties": {
    "iso:country":"BE",
    "sg:address":"Rue Hamoir 76b1",
    "sg:city":"La Louvi\u00c8re",
    "sg:orig_category":"Avocats and conseillers juridiques",
    "sg:phone":"+32 64 26 53 47",
    "sg:postcode":"7100",
    "sg:province":"Hainaut",
    "wof:name":"Virginie Wins",
    "wof:placetype":"venue"
},
  "geometry": {"coordinates":[4.1906661987,50.4746208191],"type":"Point"}
}