{
  "type": "Feature",
  "properties": {
    "addr:full":"Laureysstraat 27 Edegem Antwerpen 2650",
    "addr:housenumber":"27",
    "addr:postcode":"2650",
    "addr:street":"Laureysstraat",
    "iso:country":"BE",
    "sg:address":"Laureysstraat 27",
    "sg:city":"Edegem",
    "sg:classifiers":[
        {
            "category":"Utilities",
            "subcategory":"Telephone",
            "type":"Services"
        }
    ],
    "sg:phone":"+32 3 458 16 24",
    "sg:postcode":"2650",
    "sg:province":"Antwerpen",
    "sg:tags":[
        "-",
        "internet"
    ],
    "wof:name":"Veremo",
    "wof:placetype":"venue"
},
  "geometry": {"coordinates":[4.4470148087,51.1604499817],"type":"Point"}
}