{
  "type": "Feature",
  "properties": {
    "iso:country":"BE",
    "sg:address":"Rue De L'eglise 5",
    "sg:city":"Dalhem",
    "sg:orig_category":"Rundveehouders",
    "sg:phone":"+32 4 376 60 81",
    "sg:postcode":"4607",
    "sg:province":"Li\u00e8ge",
    "wof:name":"Roger Didderen",
    "wof:placetype":"venue"
},
  "geometry": {"coordinates":[5.7397208214,50.7303314209],"type":"Point"}
}