{
  "type": "Feature",
  "properties": {
    "iso:country":"BE",
    "sg:address":"Route De Mons 553b1",
    "sg:city":"Binche",
    "sg:classifiers":[
        {
            "category":"Insurance",
            "subcategory":"Life Insurance",
            "type":"Services"
        }
    ],
    "sg:phone":"+32 64 33 59 01",
    "sg:postcode":"7130",
    "sg:province":"Hainaut",
    "sg:tags":[
        "assurance"
    ],
    "wof:name":"Vitapro\u00b4 Assurances",
    "wof:placetype":"venue"
},
  "geometry": {"coordinates":[4.1599001884,50.4136390686],"type":"Point"}
}