{
  "type": "Feature",
  "properties": {
    "addr:full":"Avenue De Tervueren 37 Bruxelles (etterbeek) Bruxelles-Capitale 1040",
    "addr:housenumber":"37",
    "addr:postcode":"1040",
    "addr:street":"Avenue De Tervueren",
    "iso:country":"BE",
    "sg:address":"Avenue De Tervueren 37",
    "sg:city":"Bruxelles (etterbeek)",
    "sg:classifiers":[
        {
            "category":"Real Estate",
            "subcategory":"Real Estate Services",
            "type":"Services"
        }
    ],
    "sg:phone":"+32 2 732 37 24",
    "sg:postcode":"1040",
    "sg:province":"Bruxelles-Capitale",
    "wof:name":"Rainbow Properties",
    "wof:placetype":"venue"
},
  "geometry": {"coordinates":[4.3994631767,50.8388214111],"type":"Point"}
}