{
  "type": "Feature",
  "properties": {
    "addr:full":"Vredelaan 24 Houthalen-helchteren Limburg 3530",
    "addr:housenumber":"24",
    "addr:postcode":"3530",
    "addr:street":"Vredelaan",
    "iso:country":"BE",
    "sg:address":"Vredelaan 24",
    "sg:city":"Houthalen-helchteren",
    "sg:classifiers":[
        {
            "category":"Fast Food",
            "type":"Food & Drink"
        }
    ],
    "sg:phone":"+32 11 52 50 05",
    "sg:postcode":"3530",
    "sg:province":"Limburg",
    "sg:tags":[
        "\u00c0",
        "emporter",
        "restaurants"
    ],
    "wof:name":"Frituur Via Vai",
    "wof:placetype":"venue"
},
  "geometry": {"coordinates":[5.373688221,51.0317459106],"type":"Point"}
}