{
  "type": "Feature",
  "properties": {
    "addr:full":"Landegemdorp 1 Box 3 Nevele (landegem) Oost-Vlaanderen 9850",
    "addr:housenumber":"1;3",
    "addr:postcode":"9850",
    "addr:street":"Landegemdorp;Box",
    "iso:country":"BE",
    "sg:address":"Landegemdorp 1 Box 3",
    "sg:city":"Nevele (landegem)",
    "sg:orig_category":"Non-Classified Establishments",
    "sg:phone":"+32 9 371 45 86",
    "sg:postcode":"9850",
    "sg:province":"Oost-Vlaanderen",
    "wof:name":"Protodesign Bvba",
    "wof:placetype":"venue"
},
  "geometry": {"coordinates":[3.5680780411,51.0571289062],"type":"Point"}
}