{
  "type": "Feature",
  "properties": {
    "addr:full":"Basilieklaan 226ba Scherpenheuvel-zichem Vlaams-Brabant 3270",
    "addr:postcode":"3270",
    "addr:street":"Basilieklaan;Vlaams-Brabant",
    "iso:country":"BE",
    "sg:address":"Basilieklaan 226ba",
    "sg:city":"Scherpenheuvel-zichem",
    "sg:orig_category":"Eclairage et \u00e9quipements du foyer",
    "sg:phone":"+32 13 78 18 32",
    "sg:postcode":"3270",
    "sg:province":"Vlaams-Brabant",
    "wof:name":"P. & S. Electronics",
    "wof:placetype":"venue"
},
  "geometry": {"coordinates":[4.9648752213,50.979259491],"type":"Point"}
}