{
  "type": "Feature",
  "properties": {
    "iso:country":"BE",
    "sg:address":"Petrus Stokmanslaan 15",
    "sg:city":"Kapellen",
    "sg:classifiers":[
        {
            "category":"Real Estate",
            "subcategory":"Surveying",
            "type":"Services"
        }
    ],
    "sg:phone":"+32 3 605 06 17",
    "sg:postcode":"2950",
    "sg:province":"Antwerpen",
    "sg:tags":[
        "surveyor",
        "land"
    ],
    "wof:name":"Hermans B",
    "wof:placetype":"venue"
},
  "geometry": {"coordinates":[4.4462370872,51.3269042969],"type":"Point"}
}