{
  "type": "Feature",
  "properties": {
    "addr:full":"Neringe 71 Tielt-winge Vlaams-Brabant 3390",
    "addr:housenumber":"71",
    "addr:postcode":"3390",
    "addr:street":"Neringe",
    "iso:country":"BE",
    "sg:address":"Neringe 71",
    "sg:city":"Tielt-winge",
    "sg:orig_category":"Activit\u00e9s r\u00e9cr\u00e9atives diverses",
    "sg:phone":"+32 16 64 05 05",
    "sg:postcode":"3390",
    "sg:province":"Vlaams-Brabant",
    "wof:name":"B.c. 't Begijntje",
    "wof:placetype":"venue"
},
  "geometry": {"coordinates":[4.9038281441,50.9413642883],"type":"Point"}
}