{
  "type": "Feature",
  "properties": {
    "addr:full":"Antwerpseweg 103 Geel Antwerpen 2440",
    "addr:housenumber":"103",
    "addr:postcode":"2440",
    "addr:street":"Antwerpseweg",
    "iso:country":"BE",
    "sg:address":"Antwerpseweg 103",
    "sg:city":"Geel",
    "sg:classifiers":[
        {
            "category":"Shopping",
            "subcategory":"Computers & Home Electronics",
            "type":"Retail Goods"
        }
    ],
    "sg:phone":"+32 14 59 27 90",
    "sg:postcode":"2440",
    "sg:province":"Antwerpen",
    "sg:tags":[
        "personal",
        "-",
        "processing",
        "data"
    ],
    "wof:name":"Chameleon Computers Bvba",
    "wof:placetype":"venue"
},
  "geometry": {"coordinates":[4.9552497864,51.1453895569],"type":"Point"}
}