{
  "type": "Feature",
  "properties": {
    "iso:country":"BE",
    "sg:address":"Langemarkstraat 67",
    "sg:city":"Zonnebeke",
    "sg:classifiers":[
        {
            "category":"Building & Trades",
            "subcategory":"Pest Control",
            "type":"Services"
        }
    ],
    "sg:phone":"+32 51 77 78 13",
    "sg:postcode":"8980",
    "sg:province":"West-Vlaanderen",
    "sg:tags":[
        "industry",
        "-",
        "plastic"
    ],
    "wof:name":"Dekeyser Plastic Bvba",
    "wof:placetype":"venue"
},
  "geometry": {"coordinates":[2.9823551178,50.8758583069],"type":"Point"}
}