{
  "type": "Feature",
  "properties": {
    "iso:country":"BE",
    "sg:address":"Rue Les Digues 2",
    "sg:city":"Theux",
    "sg:classifiers":[
        {
            "category":"Home & Garden",
            "subcategory":"Home Furnishings",
            "type":"Retail Goods"
        }
    ],
    "sg:phone":"+32 87 32 99 40",
    "sg:postcode":"4910",
    "sg:province":"Li\u00e8ge",
    "sg:tags":[
        "part",
        "upholstery"
    ],
    "wof:name":"Jegama Sprl",
    "wof:placetype":"venue"
},
  "geometry": {"coordinates":[5.8313350677,50.4923706055],"type":"Point"}
}