{
  "type": "Feature",
  "properties": {
    "iso:country":"BE",
    "sg:address":"Russelt 19",
    "sg:city":"Wellen",
    "sg:classifiers":[
        {
            "category":"Building & Trades",
            "subcategory":"Construction",
            "type":"Services"
        }
    ],
    "sg:phone":"+32 11 31 40 42",
    "sg:postcode":"3830",
    "sg:province":"Limburg",
    "sg:tags":[
        "stucco",
        "contractor"
    ],
    "wof:name":"Philtjens Roger & Zoon",
    "wof:placetype":"venue"
},
  "geometry": {"coordinates":[5.3161048889,50.8486404419],"type":"Point"}
}