{
  "type": "Feature",
  "properties": {
    "addr:full":"Rue De Baudemont 29 Ittre Brabant Wallon 1460",
    "addr:housenumber":"29;1460",
    "addr:street":"Rue De Baudemont",
    "iso:country":"BE",
    "sg:address":"Rue De Baudemont 29",
    "sg:city":"Ittre",
    "sg:orig_category":"Diverse bedrijfsbeheeradviesbureaus",
    "sg:phone":"+32 67 21 36 79",
    "sg:postcode":"1460",
    "sg:province":"Brabant Wallon",
    "wof:name":"Pascinfo Belgium",
    "wof:placetype":"venue"
},
  "geometry": {"coordinates":[4.2724738121,50.6424713135],"type":"Point"}
}