{
  "type": "Feature",
  "properties": {
    "addr:full":"Boulevard Joseph Tirou 70 Charleroi Hainaut 6000",
    "addr:housenumber":"70",
    "addr:postcode":"6000",
    "addr:street":"Boulevard Joseph Tirou;Hainaut",
    "iso:country":"BE",
    "sg:address":"Boulevard Joseph Tirou 70",
    "sg:city":"Charleroi",
    "sg:classifiers":[
        {
            "category":"Arena",
            "subcategory":"Sports Club",
            "type":"Entertainment"
        }
    ],
    "sg:phone":"+32 71 33 06 94",
    "sg:postcode":"6000",
    "sg:province":"Hainaut",
    "wof:name":"Acad\u00e9mie Sud Billard",
    "wof:placetype":"venue"
},
  "geometry": {"coordinates":[4.4432001114,50.4076385498],"type":"Point"}
}