{
  "type": "Feature",
  "properties": {
    "addr:full":"Oordegemdorp 38 Lede Oost-Vlaanderen 9340",
    "addr:housenumber":"38",
    "addr:postcode":"9340",
    "addr:street":"Oordegemdorp",
    "iso:country":"BE",
    "sg:address":"Oordegemdorp 38",
    "sg:city":"Lede",
    "sg:classifiers":[
        {
            "category":"Cafe",
            "type":"Food & Drink"
        }
    ],
    "sg:phone":"+32 9 369 69 24",
    "sg:postcode":"9340",
    "sg:province":"Oost-Vlaanderen",
    "sg:tags":[
        "caf\u00e9s"
    ],
    "wof:name":"Caf\u00c9 De Zoete Inval",
    "wof:placetype":"venue"
},
  "geometry": {"coordinates":[3.9773280621,50.9667625427],"type":"Point"}
}