{
  "type": "Feature",
  "properties": {
    "iso:country":"BE",
    "sg:address":"Van Landeghemstraat 100",
    "sg:city":"Sint-niklaas",
    "sg:classifiers":[
        {
            "category":"Professional",
            "subcategory":"Accounting & Tax Preparation",
            "type":"Services"
        }
    ],
    "sg:phone":"+32 3 776 68 98",
    "sg:postcode":"9100",
    "sg:province":"Oost-Vlaanderen",
    "sg:tags":[
        "bookkeeper"
    ],
    "wof:name":"Janofra Cv",
    "wof:placetype":"venue"
},
  "geometry": {"coordinates":[4.1852860451,51.168384552],"type":"Point"}
}