{
  "type": "Feature",
  "properties": {
    "iso:country":"BE",
    "sg:address":"Amerstraat 23",
    "sg:city":"Aarschot",
    "sg:classifiers":[
        {
            "category":"Insurance",
            "subcategory":"Insurance Agent",
            "type":"Services"
        }
    ],
    "sg:phone":"+32 16 56 77 81",
    "sg:postcode":"3200",
    "sg:province":"Vlaams-Brabant",
    "sg:tags":[
        "broker"
    ],
    "wof:name":"Beets Jozef Zakenkantoor Bvba",
    "wof:placetype":"venue"
},
  "geometry": {"coordinates":[4.8359208107,50.9864044189],"type":"Point"}
}