{
  "type": "Feature",
  "properties": {
    "addr:full":"Appeldonkstraat 96 Willebroek Antwerpen 2830",
    "addr:housenumber":"96",
    "addr:postcode":"2830",
    "addr:street":"Appeldonkstraat",
    "iso:country":"BE",
    "sg:address":"Appeldonkstraat 96",
    "sg:city":"Willebroek",
    "sg:orig_category":"Loodgieterij, verwarming and sanitaire installaties",
    "sg:phone":"+32 3 886 59 31",
    "sg:postcode":"2830",
    "sg:province":"Antwerpen",
    "wof:name":"Renaat Jacobs",
    "wof:placetype":"venue"
},
  "geometry": {"coordinates":[4.3566398621,51.0692596436],"type":"Point"}
}