{
  "type": "Feature",
  "properties": {
    "iso:country":"BE",
    "sg:address":"Franklin Rooseveltlaan 91",
    "sg:city":"Gent",
    "sg:orig_category":"Mutualities",
    "sg:phone":"+32 9 269 54 00",
    "sg:postcode":"9000",
    "sg:province":"Oost-Vlaanderen",
    "wof:name":"H.z.i.v.",
    "wof:placetype":"venue"
},
  "geometry": {"coordinates":[3.730173111,51.0466423035],"type":"Point"}
}