{
  "type": "Feature",
  "properties": {
    "iso:country":"BE",
    "sg:address":"Georges Brugmannplein 3",
    "sg:city":"Elsene",
    "sg:orig_category":"Brood, gebak and snoepgoed Restaurants",
    "sg:phone":"+32 2 343 62 67",
    "sg:postcode":"1050",
    "sg:province":"Bruxelles-Capitale",
    "wof:name":"Gaudron",
    "wof:placetype":"venue"
},
  "geometry": {"coordinates":[4.3549661636,50.8178100586],"type":"Point"}
}