{
  "type": "Feature",
  "properties": {
    "iso:country":"BE",
    "sg:address":"Louizalaan 195",
    "sg:city":"Brussel/bruxelles",
    "sg:orig_category":"Herstellingswinkels voor diverse persoonlijke and huishoudartikelen Ontwerpers and designers",
    "sg:phone":"+32 2 640 36 99",
    "sg:postcode":"1050",
    "sg:province":"Bruxelles-Capitale",
    "wof:name":"Fran\u00c7ois Borceux",
    "wof:placetype":"venue"
},
  "geometry": {"coordinates":[4.356962204,50.8341941833],"type":"Point"}
}