{
  "type": "Feature",
  "properties": {
    "addr:full":"Rue D'en Haut 16 Yvoir (dorinne) Namur 5530",
    "addr:housenumber":"16",
    "addr:postcode":"5530",
    "addr:street":"Rue D'En Haut",
    "iso:country":"BE",
    "sg:address":"Rue D'en Haut 16",
    "sg:city":"Yvoir (dorinne)",
    "sg:classifiers":[
        {
            "category":"Shopping",
            "subcategory":"Stationery & Office Supplies",
            "type":"Retail Goods"
        }
    ],
    "sg:phone":"+32 83 69 00 02",
    "sg:postcode":"5530",
    "sg:province":"Namur",
    "sg:tags":[
        "partition"
    ],
    "wof:name":"Willame J-m",
    "wof:placetype":"venue"
},
  "geometry": {"coordinates":[4.9083228111,50.352558136],"type":"Point"}
}