{
  "type": "Feature",
  "properties": {
    "addr:full":"Koning Albertlaan 42 Gent Oost-Vlaanderen 9000",
    "addr:housenumber":"42",
    "addr:postcode":"9000",
    "addr:street":"Koning Albertlaan;Oost-Vlaanderen",
    "iso:country":"BE",
    "sg:address":"Koning Albertlaan 42",
    "sg:city":"Gent",
    "sg:classifiers":[
        {
            "category":"Health Services",
            "subcategory":"Dentist",
            "type":"Services"
        }
    ],
    "sg:phone":"+32 9 221 65 64",
    "sg:postcode":"9000",
    "sg:province":"Oost-Vlaanderen",
    "wof:name":"Van Hoorick Peter",
    "wof:placetype":"venue"
},
  "geometry": {"coordinates":[3.7110021114,51.0382041931],"type":"Point"}
}