{
  "type": "Feature",
  "properties": {
    "iso:country":"BE",
    "sg:address":"Avenue De Merode 119",
    "sg:city":"Rixensart",
    "sg:classifiers":[
        {
            "category":"Professional",
            "subcategory":"Management & Consulting",
            "type":"Services"
        }
    ],
    "sg:phone":"+32 2 687 66 51",
    "sg:postcode":"1330",
    "sg:province":"Brabant Wallon",
    "sg:tags":[
        "consultant",
        "agency",
        "advertising"
    ],
    "wof:name":"De Keyser P",
    "wof:placetype":"venue"
},
  "geometry": {"coordinates":[4.5181341171,50.7117233276],"type":"Point"}
}