{
  "type": "Feature",
  "properties": {
    "addr:full":"Nieuwe Baan 9 Lokeren (eksaarde) Oost-Vlaanderen 9160",
    "addr:housenumber":"9",
    "addr:postcode":"9160",
    "addr:street":"Nieuwe Baan;Lokeren Eksaarde Oost-Vlaanderen",
    "iso:country":"BE",
    "sg:address":"Nieuwe Baan 9",
    "sg:city":"Lokeren (eksaarde)",
    "sg:classifiers":[
        {
            "category":"Building & Trades",
            "subcategory":"Landscaping Services",
            "type":"Services"
        }
    ],
    "sg:phone":"+32 9 346 84 71",
    "sg:postcode":"9160",
    "sg:province":"Oost-Vlaanderen",
    "sg:tags":[
        "-",
        "lopping",
        "work",
        "tree",
        "felling"
    ],
    "wof:name":"Carpentier Nv",
    "wof:placetype":"venue"
},
  "geometry": {"coordinates":[3.9915370941,51.1544265747],"type":"Point"}
}