{
  "type": "Feature",
  "properties": {
    "addr:full":"Rue Gilles Binchois 7 Binche Hainaut 7130",
    "addr:housenumber":"7",
    "addr:postcode":"7130",
    "addr:street":"Rue Gilles Binchois",
    "iso:country":"BE",
    "sg:address":"Rue Gilles Binchois 7",
    "sg:city":"Binche",
    "sg:orig_category":"Journaux. Tabac",
    "sg:phone":"+32 64 33 46 83",
    "sg:postcode":"7130",
    "sg:province":"Hainaut",
    "wof:name":"Librairie De La Gare",
    "wof:placetype":"venue"
},
  "geometry": {"coordinates":[4.1712198257,50.4093513489],"type":"Point"}
}