{
  "type": "Feature",
  "properties": {
    "addr:full":"Rue De Bomer\u00e9e 317 Montigny-le-tilleul Hainaut 6110",
    "addr:housenumber":"317",
    "addr:postcode":"6110",
    "addr:street":"Rue De Bomere\u0301E",
    "iso:country":"BE",
    "sg:address":"Rue De Bomer\u00e9e 317",
    "sg:city":"Montigny-le-tilleul",
    "sg:classifiers":[
        {
            "category":"Personal",
            "subcategory":"Nail Salon",
            "type":"Services"
        }
    ],
    "sg:phone":"+32 71 51 51 54",
    "sg:postcode":"6110",
    "sg:province":"Hainaut",
    "sg:tags":[
        "pedicure"
    ],
    "wof:name":"Van Riel M",
    "wof:placetype":"venue"
},
  "geometry": {"coordinates":[4.3903918266,50.3673057556],"type":"Point"}
}