{
  "type": "Feature",
  "properties": {
    "addr:full":"Landegemstraat 36 Nevele (vosselare) Oost-Vlaanderen 9850",
    "addr:housenumber":"36",
    "addr:postcode":"9850",
    "addr:street":"Landegemstraat",
    "iso:country":"BE",
    "sg:address":"Landegemstraat 36",
    "sg:city":"Nevele (vosselare)",
    "sg:classifiers":[
        {
            "category":"Health Services",
            "subcategory":"Health Practitioner",
            "type":"Services"
        }
    ],
    "sg:phone":"+32 9 371 59 95",
    "sg:postcode":"9850",
    "sg:province":"Oost-Vlaanderen",
    "sg:tags":[
        "therapist",
        "speech"
    ],
    "wof:name":"Holluyn Ine",
    "wof:placetype":"venue"
},
  "geometry": {"coordinates":[3.5602200031,51.0344581604],"type":"Point"}
}