{
  "type": "Feature",
  "properties": {
    "addr:full":"Schallebijterslaan 17 Watermaal-bosvoorde/watermael-boitsfort Bruxelles-Capitale 1170",
    "addr:housenumber":"17",
    "addr:postcode":"1170",
    "addr:street":"Schallebijterslaan",
    "iso:country":"BE",
    "sg:address":"Schallebijterslaan 17",
    "sg:city":"Watermaal-bosvoorde/watermael-boitsfort",
    "sg:orig_category":"Binnenhuisarchitecten",
    "sg:phone":"+32 2 672 54 56",
    "sg:postcode":"1170",
    "sg:province":"Bruxelles-Capitale",
    "wof:name":"Yves Hubert",
    "wof:placetype":"venue"
},
  "geometry": {"coordinates":[4.4030499458,50.7977256775],"type":"Point"}
}