{
  "type": "Feature",
  "properties": {
    "iso:country":"BE",
    "sg:address":"Rue Des Perdrix 51",
    "sg:city":"Mouscron",
    "sg:classifiers":[
        {
            "category":"Real Estate",
            "subcategory":"Architect",
            "type":"Services"
        }
    ],
    "sg:phone":"+32 56 33 23 47",
    "sg:postcode":"7700",
    "sg:province":"Hainaut",
    "wof:name":"Devolder G",
    "wof:placetype":"venue"
},
  "geometry": {"coordinates":[3.2195589542,50.7565841675],"type":"Point"}
}