{
  "type": "Feature",
  "properties": {
    "iso:country":"BE",
    "sg:address":"Pastoor Christiaensstr. 11",
    "sg:city":"Berlare",
    "sg:orig_category":"Voedingsspeciaalzaken",
    "sg:phone":"+32 52 42 52 10",
    "sg:postcode":"9290",
    "sg:province":"Oost-Vlaanderen",
    "wof:name":"Huis 't Natuurtje",
    "wof:placetype":"venue"
},
  "geometry": {"coordinates":[4.0074090958,51.0131111145],"type":"Point"}
}