{
  "type": "Feature",
  "properties": {
    "addr:full":"Poelkapellestraat 16bc Houthulst West-Vlaanderen 8650",
    "addr:housenumber":"16bc",
    "addr:postcode":"8650",
    "addr:street":"Poelkapellestraat",
    "iso:country":"BE",
    "sg:address":"Poelkapellestraat 16bc",
    "sg:city":"Houthulst",
    "sg:classifiers":[
        {
            "category":"Insurance",
            "subcategory":"Life Insurance",
            "type":"Services"
        }
    ],
    "sg:phone":"+32 51 70 29 33",
    "sg:postcode":"8650",
    "sg:province":"West-Vlaanderen",
    "sg:tags":[
        "assurance"
    ],
    "wof:name":"A. Vandesteene",
    "wof:placetype":"venue"
},
  "geometry": {"coordinates":[2.946461916,50.9740333557],"type":"Point"}
}