{
  "type": "Feature",
  "properties": {
    "iso:country":"BE",
    "sg:address":"Veldebergstraat 97",
    "sg:city":"Merksplas",
    "sg:orig_category":"Clubs de sport. Auberges de jeunesse and refuges. Terrains de camping. Caravanes and remorques. Acti",
    "sg:phone":"+32 14 63 39 29",
    "sg:postcode":"2330",
    "sg:province":"Antwerpen",
    "wof:name":"Molenzijdse Heide",
    "wof:placetype":"venue"
},
  "geometry": {"coordinates":[4.8390378952,51.3696327209],"type":"Point"}
}