{
  "type": "Feature",
  "properties": {
    "iso:country":"BE",
    "sg:address":"Rue Auguste Scohy 234",
    "sg:city":"Aiseau-presles (pont-de-loup)",
    "sg:classifiers":[
        {
            "category":"Home & Garden",
            "subcategory":"Carpets & Floor Coverings",
            "type":"Retail Goods"
        }
    ],
    "sg:phone":"+32 71 39 61 34",
    "sg:postcode":"6250",
    "sg:province":"Hainaut",
    "sg:tags":[
        "layer",
        "mosaicists"
    ],
    "wof:name":"Tomaselli C",
    "wof:placetype":"venue"
},
  "geometry": {"coordinates":[4.5566759109,50.412437439],"type":"Point"}
}