{
  "type": "Feature",
  "properties": {
    "iso:country":"BE",
    "sg:address":"Industriepark 20",
    "sg:city":"Heist-op-den-berg",
    "sg:orig_category":"Travaux de pl\u00e2trage. Produits chimiques Gr",
    "sg:phone":"+32 15 24 19 68",
    "sg:postcode":"2220",
    "sg:province":"Antwerpen",
    "wof:name":"Bouwchemie Remmers",
    "wof:placetype":"venue"
},
  "geometry": {"coordinates":[4.7264471054,51.0614318848],"type":"Point"}
}