{
  "type": "Feature",
  "properties": {
    "iso:country":"BE",
    "sg:address":"Avenue De Maire 179",
    "sg:city":"Tournai",
    "sg:classifiers":[
        {
            "category":"Professional",
            "subcategory":"Printing & Photocopies",
            "type":"Services"
        }
    ],
    "sg:phone":"+32 69 88 84 00",
    "sg:postcode":"7500",
    "sg:province":"Hainaut",
    "sg:tags":[
        "offset"
    ],
    "wof:name":"Artistic Imprimerie S.a.",
    "wof:placetype":"venue"
},
  "geometry": {"coordinates":[3.3708930016,50.6201591492],"type":"Point"}
}