{
  "type": "Feature",
  "properties": {
    "iso:country":"BE",
    "sg:address":"Nieuwlandlaan 16",
    "sg:city":"Aarschot",
    "sg:classifiers":[
        {
            "category":"Personal",
            "subcategory":"Beauty Salon",
            "type":"Services"
        }
    ],
    "sg:phone":"+32 16 57 22 53",
    "sg:postcode":"3200",
    "sg:province":"Vlaams-Brabant",
    "sg:tags":[
        "equipment",
        "hairdressing",
        "-",
        "supply"
    ],
    "wof:name":"Pivot Point Lsc Formation Coiffure",
    "wof:placetype":"venue"
},
  "geometry": {"coordinates":[4.8159370422,50.9856872559],"type":"Point"}
}