{
  "type": "Feature",
  "properties": {
    "iso:country":"BE",
    "sg:address":"Grote Steenweg 133",
    "sg:city":"Geetbets (rummen)",
    "sg:classifiers":[
        {
            "category":"Food & Beverages",
            "subcategory":"Fruits & Vegetables",
            "type":"Retail Goods"
        }
    ],
    "sg:postcode":"3454",
    "sg:province":"Vlaams-Brabant",
    "sg:tags":[
        "-"
    ],
    "wof:name":"Pascy",
    "wof:placetype":"venue"
},
  "geometry": {"coordinates":[5.1756949425,50.9009361267],"type":"Point"}
}