{
  "type": "Feature",
  "properties": {
    "iso:country":"BE",
    "sg:address":"Viide Olympiadelaan 125-5",
    "sg:city":"Antwerpen",
    "sg:classifiers":[
        {
            "category":"Communications",
            "subcategory":"Film & Video Production",
            "type":"Services"
        }
    ],
    "sg:phone":"+32 3 288 70 07",
    "sg:postcode":"2020",
    "sg:province":"Antwerpen",
    "sg:tags":[
        "movie",
        "maker"
    ],
    "wof:name":"Cartoon Productions",
    "wof:placetype":"venue"
},
  "geometry": {"coordinates":[4.3832330704,51.1829376221],"type":"Point"}
}