{
  "type": "Feature",
  "properties": {
    "addr:full":"Zonnestraat 4 Ronse/renaix Oost-Vlaanderen 9600",
    "addr:housenumber":"4",
    "addr:postcode":"9600",
    "addr:street":"Zonnestraat",
    "iso:country":"BE",
    "sg:address":"Zonnestraat 4",
    "sg:city":"Ronse/renaix",
    "sg:orig_category":"Supermarkten",
    "sg:phone":"+32 55 20 77 30",
    "sg:postcode":"9600",
    "sg:province":"Oost-Vlaanderen",
    "wof:name":"Delhaize",
    "wof:placetype":"venue"
},
  "geometry": {"coordinates":[3.5992999077,50.7470397949],"type":"Point"}
}