{
  "type": "Feature",
  "properties": {
    "addr:full":"Roth 6 Aarschot Vlaams-Brabant 3202",
    "addr:housenumber":"6",
    "addr:postcode":"3202",
    "addr:street":"Roth",
    "iso:country":"BE",
    "sg:address":"Roth 6",
    "sg:city":"Aarschot",
    "sg:orig_category":"Producteurs de l\u00e9gumes",
    "sg:phone":"+32 16 50 20 95",
    "sg:postcode":"3202",
    "sg:province":"Vlaams-Brabant",
    "wof:name":"Willy Matteus",
    "wof:placetype":"venue"
},
  "geometry": {"coordinates":[4.8801660538,50.9776725769],"type":"Point"}
}