{
  "type": "Feature",
  "properties": {
    "iso:country":"BE",
    "sg:address":"Rue De La Gendarmerie 59",
    "sg:city":"Aubange",
    "sg:classifiers":[
        {
            "category":"Professional",
            "subcategory":"Management & Consulting",
            "type":"Services"
        }
    ],
    "sg:phone":"+32 63 38 34 30",
    "sg:postcode":"6790",
    "sg:province":"Luxembourg",
    "sg:tags":[
        "consultant"
    ],
    "wof:name":"Dediste J",
    "wof:placetype":"venue"
},
  "geometry": {"coordinates":[5.8134307861,49.5701065063],"type":"Point"}
}