{
  "type": "Feature",
  "properties": {
    "addr:full":"Walstraat 17 Borgloon Limburg 3840",
    "addr:housenumber":"17",
    "addr:postcode":"3840",
    "addr:street":"Walstraat",
    "iso:country":"BE",
    "sg:address":"Walstraat 17",
    "sg:city":"Borgloon",
    "sg:classifiers":[
        {
            "category":"Food & Beverages",
            "subcategory":"Fruits & Vegetables",
            "type":"Retail Goods"
        }
    ],
    "sg:phone":"+32 12 74 29 51",
    "sg:postcode":"3840",
    "sg:province":"Limburg",
    "sg:tags":[
        "l\u00e9gumes",
        "gr"
    ],
    "wof:name":"Fa. Ambiorix",
    "wof:placetype":"venue"
},
  "geometry": {"coordinates":[5.3472728729,50.8051376343],"type":"Point"}
}