{
  "type": "Feature",
  "properties": {
    "iso:country":"BE",
    "sg:address":"Speldenstraat 71",
    "sg:city":"Wervik",
    "sg:classifiers":[
        {
            "category":"Shopping",
            "subcategory":"Florist",
            "type":"Retail Goods"
        }
    ],
    "sg:phone":"+32 56 31 09 88",
    "sg:postcode":"8940",
    "sg:province":"West-Vlaanderen",
    "wof:name":"Fine Fleur Angelo",
    "wof:placetype":"venue"
},
  "geometry": {"coordinates":[3.0418279171,50.782787323],"type":"Point"}
}