{
  "type": "Feature",
  "properties": {
    "iso:country":"BE",
    "sg:address":"Rue Dartois 34",
    "sg:city":"Li\u00c8ge",
    "sg:orig_category":"M\u00e9decins and sp\u00e9cialistes",
    "sg:phone":"+32 4 252 39 57",
    "sg:postcode":"4000",
    "sg:province":"Li\u00e8ge",
    "wof:name":"B. Germain",
    "wof:placetype":"venue"
},
  "geometry": {"coordinates":[5.5661897659,50.6277580261],"type":"Point"}
}