{
  "type": "Feature",
  "properties": {
    "iso:country":"BE",
    "sg:address":"Bruul 76",
    "sg:city":"Mechelen",
    "sg:orig_category":"V\u00eatements pour b\u00e9b\u00e9s and enfants",
    "sg:phone":"+32 15 27 58 24",
    "sg:postcode":"2800",
    "sg:province":"Antwerpen",
    "wof:name":"Kid Cool",
    "wof:placetype":"venue"
},
  "geometry": {"coordinates":[4.4814839363,51.0251541138],"type":"Point"}
}