{
  "type": "Feature",
  "properties": {
    "iso:country":"BE",
    "sg:address":"Merestr 1",
    "sg:city":"Maarkedal",
    "sg:classifiers":[
        {
            "category":"Banks & Credit Unions",
            "subcategory":"Bank",
            "type":"Services"
        }
    ],
    "sg:phone":"+32 55 21 41 10",
    "sg:postcode":"9681",
    "sg:province":"Oost-Vlaanderen",
    "wof:name":"Famibank",
    "wof:placetype":"venue"
},
  "geometry": {"coordinates":[3.5915079117,50.7919692993],"type":"Point"}
}