{
  "type": "Feature",
  "properties": {
    "addr:full":"Kievitlaan 10 Brecht Antwerpen 2960",
    "addr:housenumber":"10",
    "addr:postcode":"2960",
    "addr:street":"Kievitlaan",
    "iso:country":"BE",
    "sg:address":"Kievitlaan 10",
    "sg:city":"Brecht",
    "sg:orig_category":"Huishoudapparaten, televisies and radio's",
    "sg:phone":"+32 3 663 13 55",
    "sg:postcode":"2960",
    "sg:province":"Antwerpen",
    "wof:name":"Scoop",
    "wof:placetype":"venue"
},
  "geometry": {"coordinates":[4.5662851334,51.3081970215],"type":"Point"}
}