{
  "type": "Feature",
  "properties": {
    "iso:country":"BE",
    "sg:address":"Rue Du Tirogne 47",
    "sg:city":"Grace-hollogne",
    "sg:orig_category":"Banques and organismes de cr\u00e9dit",
    "sg:phone":"+32 4 233 12 29",
    "sg:postcode":"4460",
    "sg:province":"Li\u00e8ge",
    "wof:name":"Cr\u00c9dit \u00c0 L\u00b4industrie",
    "wof:placetype":"venue"
},
  "geometry": {"coordinates":[5.4756088257,50.6321144104],"type":"Point"}
}