{
  "type": "Feature",
  "properties": {
    "addr:full":"Quai Marcellis 13 Li\u00c8ge Li\u00e8ge 4020",
    "addr:housenumber":"13",
    "addr:postcode":"4020",
    "addr:street":"Quai Marcellis",
    "iso:country":"BE",
    "sg:address":"Quai Marcellis 13",
    "sg:city":"Li\u00c8ge",
    "sg:orig_category":"Avocats and conseillers juridiques",
    "sg:phone":"+32 4 342 30 66",
    "sg:postcode":"4020",
    "sg:province":"Li\u00e8ge",
    "wof:name":"C. Muraille",
    "wof:placetype":"venue"
},
  "geometry": {"coordinates":[5.5757188797,50.6351623535],"type":"Point"}
}