{
  "type": "Feature",
  "properties": {
    "addr:full":"Rue De La Molign\u00c9e 28 Oudergem/auderghem Bruxelles-Capitale 1160",
    "addr:housenumber":"28",
    "addr:postcode":"1160",
    "addr:street":"Rue De La Moligne\u0301E;/",
    "iso:country":"BE",
    "sg:address":"Rue De La Molign\u00c9e 28",
    "sg:city":"Oudergem/auderghem",
    "sg:orig_category":"R\u00e9parations \u00e0 domicile d'articles divers. Plomberie, chauffage and installations sanitaires. Charpen",
    "sg:phone":"+32 2 736 18 47",
    "sg:postcode":"1160",
    "sg:province":"Bruxelles-Capitale",
    "wof:name":"A Moyses Hydrogroupe",
    "wof:placetype":"venue"
},
  "geometry": {"coordinates":[4.4041051865,50.8251037598],"type":"Point"}
}