{
  "type": "Feature",
  "properties": {
    "addr:full":"Rue Malibran 85 Elsene/ixelles Bruxelles-Capitale 1050",
    "addr:housenumber":"85",
    "addr:postcode":"1050",
    "addr:street":"Rue Malibran",
    "iso:country":"BE",
    "sg:address":"Rue Malibran 85",
    "sg:city":"Elsene/ixelles",
    "sg:orig_category":"Pain, p\u00e2tisseries and confiseries",
    "sg:phone":"+32 2 644 24 43",
    "sg:postcode":"1050",
    "sg:province":"Bruxelles-Capitale",
    "wof:name":"Orientale",
    "wof:placetype":"venue"
},
  "geometry": {"coordinates":[4.3740592003,50.8313560486],"type":"Point"}
}