{
  "type": "Feature",
  "properties": {
    "iso:country":"BE",
    "sg:address":"Rue G\u00c9n\u00c9ral Fiv\u00c9 7a",
    "sg:city":"Etterbeek",
    "sg:orig_category":"Ordinateurs and \u00e9quipement informatique. Conseils en syst\u00e8mes informatiques. R\u00e9alisation de programm",
    "sg:phone":"+32 2 644 03 74",
    "sg:postcode":"1040",
    "sg:province":"Bruxelles-Capitale",
    "wof:name":"Info-rayane",
    "wof:placetype":"venue"
},
  "geometry": {"coordinates":[4.3937129974,50.8286437988],"type":"Point"}
}