{
  "type": "Feature",
  "properties": {
    "addr:full":"Zandvoordestraat 409 Oostende West-Vlaanderen 8400",
    "addr:housenumber":"409",
    "addr:postcode":"8400",
    "addr:street":"Zandvoordestraat",
    "iso:country":"BE",
    "sg:address":"Zandvoordestraat 409",
    "sg:city":"Oostende",
    "sg:classifiers":[
        {
            "category":"Building & Trades",
            "subcategory":"Pest Control",
            "type":"Services"
        }
    ],
    "sg:phone":"+32 59 80 53 23",
    "sg:postcode":"8400",
    "sg:province":"West-Vlaanderen",
    "sg:tags":[
        "painting",
        "contractor"
    ],
    "wof:name":"Kindt-maes",
    "wof:placetype":"venue"
},
  "geometry": {"coordinates":[2.9586520195,51.2106628418],"type":"Point"}
}