{
  "type": "Feature",
  "properties": {
    "addr:full":"Grand Place 2 Mons Hainaut 7000",
    "addr:housenumber":"2",
    "addr:postcode":"7000",
    "addr:street":"Grand Place;Hainaut",
    "iso:country":"BE",
    "sg:address":"Grand Place 2",
    "sg:city":"Mons",
    "sg:orig_category":"RESTAURANTS: RESTAURANTS. RESTAURANTS FAST FOOD AND \u00c0 EMPORTER",
    "sg:phone":"+32 65 36 29 30",
    "sg:postcode":"7000",
    "sg:province":"Hainaut",
    "wof:name":"La Pizzarella",
    "wof:placetype":"venue"
},
  "geometry": {"coordinates":[3.9520070553,50.4541931152],"type":"Point"}
}