{
  "type": "Feature",
  "properties": {
    "addr:full":"Herenweg 92 Tongeren Limburg 3700",
    "addr:housenumber":"92",
    "addr:postcode":"3700",
    "addr:street":"Herenweg",
    "iso:country":"BE",
    "sg:address":"Herenweg 92",
    "sg:city":"Tongeren",
    "sg:classifiers":[
        {
            "category":"Transit Center",
            "subcategory":"Freight",
            "type":"Transportation"
        }
    ],
    "sg:phone":"+32 12 23 14 48",
    "sg:postcode":"3700",
    "sg:province":"Limburg",
    "sg:tags":[
        "tanker",
        "-",
        "transport"
    ],
    "wof:name":"Vliers Transport Bvba",
    "wof:placetype":"venue"
},
  "geometry": {"coordinates":[5.4450821877,50.7764282227],"type":"Point"}
}