{
  "type": "Feature",
  "properties": {
    "addr:full":"Alfons De Cockplein 13 Machelen Vlaams-Brabant 1831",
    "addr:housenumber":"13",
    "addr:postcode":"1831",
    "addr:street":"Alfons De Cockplein",
    "iso:country":"BE",
    "sg:address":"Alfons De Cockplein 13",
    "sg:city":"Machelen",
    "sg:orig_category":"Pharmaciens",
    "sg:phone":"+32 2 720 55 45",
    "sg:postcode":"1831",
    "sg:province":"Vlaams-Brabant",
    "wof:name":"Apoteek Nysen-dekempeneer",
    "wof:placetype":"venue"
},
  "geometry": {"coordinates":[4.4360017776,50.8947143555],"type":"Point"}
}