{
  "type": "Feature",
  "properties": {
    "iso:country":"BE",
    "sg:address":"Rue Remy Himmer 117",
    "sg:city":"Dinant",
    "sg:classifiers":[
        {
            "category":"Home & Garden",
            "subcategory":"Kitchen Supply",
            "type":"Retail Goods"
        }
    ],
    "sg:phone":"+32 474 69 04 76",
    "sg:postcode":"5500",
    "sg:province":"Namur",
    "sg:tags":[
        "installation"
    ],
    "wof:name":"N.p. Meubles",
    "wof:placetype":"venue"
},
  "geometry": {"coordinates":[4.9541101456,50.2747116089],"type":"Point"}
}