{
  "type": "Feature",
  "properties": {
    "addr:full":"Herenthoutsesteenweg 186 Nijlen Antwerpen 2560",
    "addr:housenumber":"186",
    "addr:postcode":"2560",
    "addr:street":"Herenthoutsesteenweg",
    "iso:country":"BE",
    "sg:address":"Herenthoutsesteenweg 186",
    "sg:city":"Nijlen",
    "sg:orig_category":"Kapsalons",
    "sg:phone":"+32 3 411 03 18",
    "sg:postcode":"2560",
    "sg:province":"Antwerpen",
    "wof:name":"Coiffure Beauty",
    "wof:placetype":"venue"
},
  "geometry": {"coordinates":[4.7160310745,51.1478881836],"type":"Point"}
}