{
  "type": "Feature",
  "properties": {
    "addr:full":"De Biezen 6 Arendonk Antwerpen 2370",
    "addr:housenumber":"6",
    "addr:postcode":"2370",
    "addr:street":"De Biezen",
    "iso:country":"BE",
    "sg:address":"De Biezen 6",
    "sg:city":"Arendonk",
    "sg:orig_category":"Eleveurs and marchands de porcs",
    "sg:phone":"+32 14 67 71 77",
    "sg:postcode":"2370",
    "sg:province":"Antwerpen",
    "wof:name":"Danny Spoormans",
    "wof:placetype":"venue"
},
  "geometry": {"coordinates":[5.1115961075,51.3142700195],"type":"Point"}
}