{
  "type": "Feature",
  "properties": {
    "iso:country":"BE",
    "sg:address":"Dorpsplaats 9",
    "sg:city":"Malle",
    "sg:orig_category":"Brood, gebak and snoepgoed",
    "sg:phone":"+32 3 312 05 54",
    "sg:postcode":"2390",
    "sg:province":"Antwerpen",
    "wof:name":"Frans Boeckx",
    "wof:placetype":"venue"
},
  "geometry": {"coordinates":[4.7337880135,51.3024635315],"type":"Point"}
}