{
  "type": "Feature",
  "properties": {
    "iso:country":"BE",
    "sg:address":"Palfreniersstraat 28",
    "sg:city":"Roeselare",
    "sg:orig_category":"Animations diverses",
    "sg:phone":"+32 51 20 37 24",
    "sg:postcode":"8800",
    "sg:province":"West-Vlaanderen",
    "wof:name":"Christophe Platteeuw",
    "wof:placetype":"venue"
},
  "geometry": {"coordinates":[3.1503601074,50.9280891418],"type":"Point"}
}