{
  "type": "Feature",
  "properties": {
    "iso:country":"BE",
    "sg:address":"Stationstraat 107",
    "sg:city":"Ardooie",
    "sg:orig_category":"Dranken",
    "sg:phone":"+32 51 74 40 47",
    "sg:postcode":"8850",
    "sg:province":"West-Vlaanderen",
    "wof:name":"Eeckhout",
    "wof:placetype":"venue"
},
  "geometry": {"coordinates":[3.2016000748,50.9831237793],"type":"Point"}
}