{
  "type": "Feature",
  "properties": {
    "iso:country":"BE",
    "sg:address":"Rue Champ De Mars 8a",
    "sg:city":"Elsene/ixelles",
    "sg:classifiers":[
        {
            "category":"Restaurant",
            "type":"Food & Drink"
        }
    ],
    "sg:phone":"+32 2 511 64 21",
    "sg:postcode":"1050",
    "sg:province":"Bruxelles-Capitale",
    "wof:name":"Adulis",
    "wof:placetype":"venue"
},
  "geometry": {"coordinates":[4.3628411293,50.8385238647],"type":"Point"}
}