{
  "type": "Feature",
  "properties": {
    "iso:country":"BE",
    "sg:address":"Boulevard De La Woluwe 20",
    "sg:city":"Sint-pieters-woluwe/woluwe-saint-pierre",
    "sg:orig_category":"Centres sportifs",
    "sg:phone":"+32 2 772 35 13",
    "sg:postcode":"1150",
    "sg:province":"Bruxelles-Capitale",
    "wof:name":"Sportzaal St.jozefcollege",
    "wof:placetype":"venue"
},
  "geometry": {"coordinates":[4.4341621399,50.8363723755],"type":"Point"}
}