{
  "type": "Feature",
  "properties": {
    "addr:full":"Rue Du Centry 24 Grez-doiceau Brabant Wallon 1390",
    "addr:housenumber":"24",
    "addr:postcode":"1390",
    "addr:street":"Rue Du Centry",
    "iso:country":"BE",
    "sg:address":"Rue Du Centry 24",
    "sg:city":"Grez-doiceau",
    "sg:classifiers":[
        {
            "category":"Health Services",
            "subcategory":"Dentist",
            "type":"Services"
        }
    ],
    "sg:phone":"+32 10 84 09 18",
    "sg:postcode":"1390",
    "sg:province":"Brabant Wallon",
    "wof:name":"De Bruyn Chantal",
    "wof:placetype":"venue"
},
  "geometry": {"coordinates":[4.6891231537,50.7384643555],"type":"Point"}
}