{
  "type": "Feature",
  "properties": {
    "addr:full":"Rue Du Tige 16 Anthisnes Li\u00e8ge 4160",
    "addr:housenumber":"16",
    "addr:postcode":"4160",
    "addr:street":"Rue Du Tige",
    "iso:country":"BE",
    "sg:address":"Rue Du Tige 16",
    "sg:city":"Anthisnes",
    "sg:classifiers":[
        {
            "category":"Health Services",
            "subcategory":"Doctor",
            "type":"Services"
        }
    ],
    "sg:phone":"+32 4 383 68 65",
    "sg:postcode":"4160",
    "sg:province":"Li\u00e8ge",
    "sg:tags":[
        "medicinephysicians",
        "surgeon"
    ],
    "wof:name":"Grosjean Denis",
    "wof:placetype":"venue"
},
  "geometry": {"coordinates":[5.5241498947,50.4859695435],"type":"Point"}
}