{
  "type": "Feature",
  "properties": {
    "addr:full":"Lange Beeldekensstraat 210 Antwerpen Antwerpen 2060",
    "addr:housenumber":"210",
    "addr:postcode":"2060",
    "addr:street":"Lange Beeldekensstraat",
    "iso:country":"BE",
    "sg:address":"Lange Beeldekensstraat 210",
    "sg:city":"Antwerpen",
    "sg:orig_category":"Quincailleries. Mat\u00e9riel pour plomberie and chauffage Plomberie, chauffage and installations sanitai",
    "sg:phone":"+32 3 235 09 40",
    "sg:postcode":"2060",
    "sg:province":"Antwerpen",
    "wof:name":"Staelens F.",
    "wof:placetype":"venue"
},
  "geometry": {"coordinates":[4.4314050674,51.2212638855],"type":"Point"}
}