{
  "type": "Feature",
  "properties": {
    "iso:country":"BE",
    "sg:address":"Windberg 287",
    "sg:city":"Wemmel",
    "sg:classifiers":[
        {
            "category":"Manufacturing",
            "subcategory":"Lumber",
            "type":"Manufacturing & Wholesale Goods"
        }
    ],
    "sg:phone":"+32 2 460 12 53",
    "sg:postcode":"1780",
    "sg:province":"Vlaams-Brabant",
    "sg:tags":[
        "timber"
    ],
    "wof:name":"Sofobois",
    "wof:placetype":"venue"
},
  "geometry": {"coordinates":[4.2961258888,50.9141044617],"type":"Point"}
}