{
  "type": "Feature",
  "properties": {
    "iso:country":"BE",
    "sg:address":"Route Ancienne Fronti\u00e8re 27",
    "sg:city":"Malmedy (beverc\u00e9)",
    "sg:classifiers":[
        {
            "category":"Health Services",
            "subcategory":"Health Practitioner",
            "type":"Services"
        }
    ],
    "sg:phone":"+32 80 33 88 07",
    "sg:postcode":"4960",
    "sg:province":"Li\u00e8ge",
    "sg:tags":[
        "physiotherapist"
    ],
    "wof:name":"Sehovic Fatima",
    "wof:placetype":"venue"
},
  "geometry": {"coordinates":[5.9872779846,50.4258041382],"type":"Point"}
}