{
  "type": "Feature",
  "properties": {
    "iso:country":"BE",
    "sg:address":"Sint-amandsstraat 61",
    "sg:city":"Roeselare",
    "sg:classifiers":[
        {
            "category":"Autos & Motor Vehicles",
            "subcategory":"Motorcycle Sales",
            "type":"Retail Goods"
        }
    ],
    "sg:phone":"+32 51 22 98 75",
    "sg:postcode":"8800",
    "sg:province":"West-Vlaanderen",
    "sg:tags":[
        "motorbike"
    ],
    "wof:name":"Moto-ateljee Lieven Desmet",
    "wof:placetype":"venue"
},
  "geometry": {"coordinates":[3.1242229939,50.9486351013],"type":"Point"}
}