{
  "type": "Feature",
  "properties": {
    "addr:full":"Rue Murillo 35 Brussel/bruxelles Bruxelles-Capitale 1000",
    "addr:housenumber":"35",
    "addr:postcode":"1000",
    "addr:street":"Rue Murillo;/",
    "iso:country":"BE",
    "sg:address":"Rue Murillo 35",
    "sg:city":"Brussel/bruxelles",
    "sg:orig_category":"Mat\u00e9riel m\u00e9dical and orthop\u00e9dique and proth\u00e8ses Fab",
    "sg:phone":"+32 2 734 05 40",
    "sg:postcode":"1000",
    "sg:province":"Bruxelles-Capitale",
    "wof:name":"Claude Keerens",
    "wof:placetype":"venue"
},
  "geometry": {"coordinates":[4.3946738243,50.8438949585],"type":"Point"}
}