{
  "type": "Feature",
  "properties": {
    "addr:full":"Slachterijstraat 42 Westerlo Antwerpen 2260",
    "addr:housenumber":"42",
    "addr:postcode":"2260",
    "addr:street":"Slachterijstraat",
    "iso:country":"BE",
    "sg:address":"Slachterijstraat 42",
    "sg:city":"Westerlo",
    "sg:orig_category":"Installation de menuiserie en bois and plastique",
    "sg:phone":"+32 14 26 46 10",
    "sg:postcode":"2260",
    "sg:province":"Antwerpen",
    "wof:name":"Van Gyes",
    "wof:placetype":"venue"
},
  "geometry": {"coordinates":[4.8641810417,51.1032943726],"type":"Point"}
}