{
  "type": "Feature",
  "properties": {
    "iso:country":"BE",
    "sg:address":"Kerkstraat 14",
    "sg:city":"Sint-amands",
    "sg:classifiers":[
        {
            "category":"Health Services",
            "subcategory":"Health Practitioner",
            "type":"Services"
        }
    ],
    "sg:phone":"+32 52 33 40 26",
    "sg:postcode":"2890",
    "sg:province":"Antwerpen",
    "sg:tags":[
        "physiotherapist"
    ],
    "wof:name":"Govaerts Jos\u00e9e",
    "wof:placetype":"venue"
},
  "geometry": {"coordinates":[4.2025818825,51.0565795898],"type":"Point"}
}