{
  "type": "Feature",
  "properties": {
    "addr:full":"Rue Mont-ste.aldegonde 34 Modave Li\u00e8ge 4577",
    "addr:housenumber":"34",
    "addr:postcode":"4577",
    "addr:street":"Rue Mont-Ste.Aldegonde",
    "iso:country":"BE",
    "sg:address":"Rue Mont-ste.aldegonde 34",
    "sg:city":"Modave",
    "sg:orig_category":"Artsen and specialisten",
    "sg:phone":"+32 85 41 34 20",
    "sg:postcode":"4577",
    "sg:province":"Li\u00e8ge",
    "wof:name":"F. Zenobi",
    "wof:placetype":"venue"
},
  "geometry": {"coordinates":[5.2947869301,50.4828262329],"type":"Point"}
}