{
  "type": "Feature",
  "properties": {
    "addr:full":"Haerlinckstraat 42 Merelbeke (melsen) Oost-Vlaanderen 9820",
    "addr:housenumber":"42",
    "addr:postcode":"9820",
    "addr:street":"Haerlinckstraat",
    "iso:country":"BE",
    "sg:address":"Haerlinckstraat 42",
    "sg:city":"Merelbeke (melsen)",
    "sg:classifiers":[
        {
            "category":"Personal",
            "subcategory":"Beauty Salon",
            "type":"Services"
        }
    ],
    "sg:phone":"+32 9 362 97 01",
    "sg:postcode":"9820",
    "sg:province":"Oost-Vlaanderen",
    "sg:tags":[
        "lady",
        "-",
        "hairdressing"
    ],
    "wof:name":"Maggy",
    "wof:placetype":"venue"
},
  "geometry": {"coordinates":[3.708646059,50.9610061646],"type":"Point"}
}