{
  "type": "Feature",
  "properties": {
    "iso:country":"BE",
    "sg:address":"Kapelsestrraat 127",
    "sg:city":"Kapellen",
    "sg:orig_category":"Rev\u00eatements de sols and murs. Installation de menuiserie en bois and plastique. Fabrication and mont",
    "sg:phone":"+32 3 660 15 00",
    "sg:postcode":"2950",
    "sg:province":"Antwerpen",
    "wof:name":"Thys Interieurgroep",
    "wof:placetype":"venue"
},
  "geometry": {"coordinates":[4.4132537842,51.3310623169],"type":"Point"}
}