{
  "type": "Feature",
  "properties": {
    "addr:full":". Buggenhout (groot) Oost-Vlaanderen 9255",
    "addr:postcode":"9255",
    "addr:street":"Groot Oost-Vlaanderen",
    "iso:country":"BE",
    "sg:address":".",
    "sg:city":"Buggenhout (groot)",
    "sg:orig_category":"Apotheken",
    "sg:phone":"+32 900 10 500",
    "sg:postcode":"9255",
    "sg:province":"Oost-Vlaanderen",
    "wof:name":"Apothekers Van Wacht",
    "wof:placetype":"venue"
},
  "geometry": {"coordinates":[4.2018060684,51.0139122009],"type":"Point"}
}