{
  "type": "Feature",
  "properties": {
    "addr:full":"Rupelweg 4 Boom Antwerpen 2850",
    "addr:housenumber":"4",
    "addr:postcode":"2850",
    "addr:street":"Rupelweg",
    "iso:country":"BE",
    "sg:address":"Rupelweg 4",
    "sg:city":"Boom",
    "sg:orig_category":"Installation de menuiserie en bois and plastique",
    "sg:phone":"+32 3 888 67 13",
    "sg:postcode":"2850",
    "sg:province":"Antwerpen",
    "wof:name":"Fa. V.a.p.",
    "wof:placetype":"venue"
},
  "geometry": {"coordinates":[4.3557829857,51.0936737061],"type":"Point"}
}