{
  "type": "Feature",
  "properties": {
    "iso:country":"BE",
    "sg:address":"Sint-martensstraat 40",
    "sg:city":"Brakel",
    "sg:orig_category":"Kapsalons Mobiele kappers",
    "sg:phone":"+32 55 42 42 45",
    "sg:postcode":"9660",
    "sg:province":"Oost-Vlaanderen",
    "wof:name":"Kapsalon Gerda",
    "wof:placetype":"venue"
},
  "geometry": {"coordinates":[3.7465269566,50.790397644],"type":"Point"}
}