{
  "type": "Feature",
  "properties": {
    "iso:country":"BE",
    "sg:address":"Boomsesteenweg 333",
    "sg:city":"Antwerpen",
    "sg:orig_category":"Instituts de beaut\u00e9",
    "sg:phone":"+32 3 248 24 34",
    "sg:postcode":"2020",
    "sg:province":"Antwerpen",
    "wof:name":"Viviane Daems",
    "wof:placetype":"venue"
},
  "geometry": {"coordinates":[4.3882851601,51.1866455078],"type":"Point"}
}