{
  "type": "Feature",
  "properties": {
    "addr:full":"Mettestraat 21 Hasselt Limburg 3511",
    "addr:housenumber":"21",
    "addr:postcode":"3511",
    "addr:street":"Mettestraat",
    "iso:country":"BE",
    "sg:address":"Mettestraat 21",
    "sg:city":"Hasselt",
    "sg:orig_category":"Eleveurs de bovins",
    "sg:phone":"+32 11 25 56 56",
    "sg:postcode":"3511",
    "sg:province":"Limburg",
    "wof:name":"Elza Marechal",
    "wof:placetype":"venue"
},
  "geometry": {"coordinates":[5.2903051376,50.9325180054],"type":"Point"}
}