{
  "type": "Feature",
  "properties": {
    "addr:full":"Rue De Grimohaye 22 Wavre (limal) Brabant Wallon 1300",
    "addr:housenumber":"22",
    "addr:postcode":"1300",
    "addr:street":"Rue De Grimohaye;Wallon",
    "iso:country":"BE",
    "sg:address":"Rue De Grimohaye 22",
    "sg:city":"Wavre (limal)",
    "sg:classifiers":[
        {
            "category":"Professional",
            "subcategory":"Accounting & Tax Preparation",
            "type":"Services"
        }
    ],
    "sg:phone":"+32 10 41 95 30",
    "sg:postcode":"1300",
    "sg:province":"Brabant Wallon",
    "sg:tags":[
        "bookkeeper"
    ],
    "wof:name":"De Vuijst G",
    "wof:placetype":"venue"
},
  "geometry": {"coordinates":[4.5671710968,50.6943740845],"type":"Point"}
}