{
  "type": "Feature",
  "properties": {
    "iso:country":"BE",
    "sg:address":"Wildemansstraat 4",
    "sg:city":"Kontich",
    "sg:orig_category":"Travaux de finition and nettoyage de b\u00e2timents",
    "sg:phone":"+32 3 457 92 43",
    "sg:postcode":"2550",
    "sg:province":"Antwerpen",
    "wof:name":"Percy Zagers",
    "wof:placetype":"venue"
},
  "geometry": {"coordinates":[4.4519309998,51.1111717224],"type":"Point"}
}