{
  "type": "Feature",
  "properties": {
    "addr:full":"Kapellstrasse 4 Kelmis Li\u00e8ge 4720",
    "addr:housenumber":"4",
    "addr:postcode":"4720",
    "addr:street":"Kapellstrasse",
    "iso:country":"BE",
    "sg:address":"Kapellstrasse 4",
    "sg:city":"Kelmis",
    "sg:classifiers":[
        {
            "category":"Shopping",
            "subcategory":"Clothing, Apparel, & Fashions",
            "type":"Retail Goods"
        }
    ],
    "sg:phone":"+32 87 65 24 93",
    "sg:postcode":"4720",
    "sg:province":"Li\u00e8ge",
    "sg:tags":[
        "lady",
        "clothing",
        "-"
    ],
    "wof:name":"Mode (la)",
    "wof:placetype":"venue"
},
  "geometry": {"coordinates":[6.0140810013,50.7149963379],"type":"Point"}
}