{
  "type": "Feature",
  "properties": {
    "addr:full":"Herbesthaler Strasse 303 Eupen Li\u00e8ge 4700",
    "addr:housenumber":"303",
    "addr:postcode":"4700",
    "addr:street":"Herbesthaler Strasse",
    "iso:country":"BE",
    "sg:address":"Herbesthaler Strasse 303",
    "sg:city":"Eupen",
    "sg:orig_category":"Diverse meubelen Fab Glaszetten and glaswerk Installatie van metalen schrijnwerk Serres and speciale",
    "sg:phone":"+32 87 32 11 11",
    "sg:postcode":"4700",
    "sg:province":"Li\u00e8ge",
    "wof:name":"Wagener - Jowaco",
    "wof:placetype":"venue"
},
  "geometry": {"coordinates":[6.0110998154,50.6427307129],"type":"Point"}
}