{
  "type": "Feature",
  "properties": {
    "addr:full":"Faubourg De Bruxelles 110 Charleroi (gosselies) Hainaut 6041",
    "addr:housenumber":"110",
    "addr:postcode":"6041",
    "addr:street":"Faubourg De Bruxelles",
    "iso:country":"BE",
    "sg:address":"Faubourg De Bruxelles 110",
    "sg:city":"Charleroi (gosselies)",
    "sg:classifiers":[
        {
            "category":"Arena",
            "subcategory":"Sports Club",
            "type":"Entertainment"
        }
    ],
    "sg:phone":"+32 71 34 13 78",
    "sg:postcode":"6041",
    "sg:province":"Hainaut",
    "sg:tags":[
        "federation"
    ],
    "wof:name":"F\u00e9d\u00e9ration Sportive De L'enseignement De La Communaut\u00e9 Fran\u00e7aise",
    "wof:placetype":"venue"
},
  "geometry": {"coordinates":[4.4314317703,50.4685935974],"type":"Point"}
}