{
  "type": "Feature",
  "properties": {
    "addr:full":"Sint-elooistraat 30 Merelbeke Oost-Vlaanderen 9820",
    "addr:housenumber":"30",
    "addr:postcode":"9820",
    "addr:street":"Sint-Elooistraat",
    "iso:country":"BE",
    "sg:address":"Sint-elooistraat 30",
    "sg:city":"Merelbeke",
    "sg:classifiers":[
        {
            "category":"Wholesale",
            "subcategory":"Farm Supplies",
            "type":"Manufacturing & Wholesale Goods"
        }
    ],
    "sg:phone":"+32 9 362 63 11",
    "sg:postcode":"9820",
    "sg:province":"Oost-Vlaanderen",
    "sg:tags":[
        "machine",
        "agricoles",
        "mat\u00e9riel",
        "gr"
    ],
    "wof:name":"Eric Callaert",
    "wof:placetype":"venue"
},
  "geometry": {"coordinates":[3.7325179577,50.9738540649],"type":"Point"}
}