{
  "type": "Feature",
  "properties": {
    "addr:full":"Berouw 55 Gent Oost-Vlaanderen 9000",
    "addr:housenumber":"55",
    "addr:postcode":"9000",
    "addr:street":"Berouw;Oost-Vlaanderen",
    "iso:country":"BE",
    "sg:address":"Berouw 55",
    "sg:city":"Gent",
    "sg:orig_category":"Mus\u00e9es and patrimoine culturel",
    "sg:phone":"+32 9 225 05 42",
    "sg:postcode":"9000",
    "sg:province":"Oost-Vlaanderen",
    "wof:name":"Mus. Hortus Michel-thiery",
    "wof:placetype":"venue"
},
  "geometry": {"coordinates":[3.7251420021,51.0646514893],"type":"Point"}
}