{
  "type": "Feature",
  "properties": {
    "addr:full":"Rue De La Volont\u00e9 5 Bruxelles (anderlecht) Bruxelles-Capitale 1070",
    "addr:housenumber":"5",
    "addr:postcode":"1070",
    "addr:street":"Rue De La Volonte\u0301",
    "iso:country":"BE",
    "sg:address":"Rue De La Volont\u00e9 5",
    "sg:city":"Bruxelles (anderlecht)",
    "sg:classifiers":[
        {
            "category":"Professional",
            "subcategory":"Art Services",
            "type":"Services"
        }
    ],
    "sg:phone":"+32 2 522 13 62",
    "sg:postcode":"1070",
    "sg:province":"Bruxelles-Capitale",
    "sg:tags":[
        "graphic",
        "designer"
    ],
    "wof:name":"De Maet C",
    "wof:placetype":"venue"
},
  "geometry": {"coordinates":[4.2957777977,50.8201522827],"type":"Point"}
}