{
  "type": "Feature",
  "properties": {
    "iso:country":"BE",
    "sg:address":"Rue L\u00c9on Dop\u00c9r\u00c9 36",
    "sg:city":"Jette/jette",
    "sg:orig_category":"Services pour animaux domestiques",
    "sg:phone":"+32 2 426 56 12",
    "sg:postcode":"1090",
    "sg:province":"Bruxelles-Capitale",
    "wof:name":"Nicole Coppin",
    "wof:placetype":"venue"
},
  "geometry": {"coordinates":[4.3230609894,50.8757972717],"type":"Point"}
}