{
  "type": "Feature",
  "properties": {
    "iso:country":"BE",
    "sg:address":"Tervuursesteenweg 482",
    "sg:city":"Bertem (leefdaal)",
    "sg:classifiers":[
        {
            "category":"Building & Trades",
            "subcategory":"Plumbing",
            "type":"Services"
        }
    ],
    "sg:phone":"+32 2 767 14 27",
    "sg:postcode":"3061",
    "sg:province":"Vlaams-Brabant",
    "sg:tags":[
        "contractor"
    ],
    "wof:name":"Keyaerts Sanitair",
    "wof:placetype":"venue"
},
  "geometry": {"coordinates":[4.5911397934,50.8475608826],"type":"Point"}
}