{
  "type": "Feature",
  "properties": {
    "iso:country":"BE",
    "sg:address":"Schoolstraat 1",
    "sg:city":"Meerhout",
    "sg:orig_category":"Centres sportifs",
    "sg:phone":"+32 14 30 31 01",
    "sg:postcode":"2450",
    "sg:province":"Antwerpen",
    "wof:name":"Sportzaal Gemeenteschool",
    "wof:placetype":"venue"
},
  "geometry": {"coordinates":[5.0778121948,51.1280097961],"type":"Point"}
}