{
  "type": "Feature",
  "properties": {
    "addr:full":"Rue Du Mail 14 Elsene/ixelles Bruxelles-Capitale 1050",
    "addr:housenumber":"14",
    "addr:postcode":"1050",
    "addr:street":"Rue Du Mail",
    "iso:country":"BE",
    "sg:address":"Rue Du Mail 14",
    "sg:city":"Elsene/ixelles",
    "sg:orig_category":"M\u00e9decins and sp\u00e9cialistes",
    "sg:phone":"+32 2 538 16 08",
    "sg:postcode":"1050",
    "sg:province":"Bruxelles-Capitale",
    "wof:name":"Fernand Neuray",
    "wof:placetype":"venue"
},
  "geometry": {"coordinates":[4.3612098694,50.8233146667],"type":"Point"}
}