{
  "type": "Feature",
  "properties": {
    "iso:country":"BE",
    "sg:address":"Graaf Van Hoornestraat 2a",
    "sg:city":"Antwerpen",
    "sg:classifiers":[
        {
            "category":"Food & Beverages",
            "subcategory":"Supermarket",
            "type":"Retail Goods"
        }
    ],
    "sg:phone":"+32 3 237 22 75",
    "sg:postcode":"2000",
    "sg:province":"Antwerpen",
    "sg:tags":[
        "department",
        "store"
    ],
    "wof:name":"Nobel & Co Bvba",
    "wof:placetype":"venue"
},
  "geometry": {"coordinates":[4.3926692009,51.2079200745],"type":"Point"}
}