{
  "type": "Feature",
  "properties": {
    "addr:full":"Krokuslaan 18 Lier Antwerpen 2500",
    "addr:housenumber":"18",
    "addr:postcode":"2500",
    "addr:street":"Krokuslaan",
    "iso:country":"BE",
    "sg:address":"Krokuslaan 18",
    "sg:city":"Lier",
    "sg:classifiers":[
        {
            "category":"Personal",
            "subcategory":"Nail Salon",
            "type":"Services"
        }
    ],
    "sg:phone":"+32 3 488 46 05",
    "sg:postcode":"2500",
    "sg:province":"Antwerpen",
    "sg:tags":[
        "pedicure"
    ],
    "wof:name":"Smets G",
    "wof:placetype":"venue"
},
  "geometry": {"coordinates":[4.5512948036,51.1372299194],"type":"Point"}
}