{
  "type": "Feature",
  "properties": {
    "addr:full":"Grand Rue 13 Ch\u00e2telet Hainaut 6200",
    "addr:housenumber":"13",
    "addr:postcode":"6200",
    "addr:street":"Grand Rue",
    "iso:country":"BE",
    "sg:address":"Grand Rue 13",
    "sg:city":"Ch\u00e2telet",
    "sg:classifiers":[
        {
            "category":"Retail",
            "subcategory":"Veterinary Services",
            "type":"Services"
        }
    ],
    "sg:phone":"+32 71 39 84 39",
    "sg:postcode":"6200",
    "sg:province":"Hainaut",
    "sg:tags":[
        "veterinarian"
    ],
    "wof:name":"Hayen L",
    "wof:placetype":"venue"
},
  "geometry": {"coordinates":[4.527089119,50.4032287598],"type":"Point"}
}