{
  "type": "Feature",
  "properties": {
    "iso:country":"BE",
    "sg:address":"Savaanstraat 7",
    "sg:city":"Gent-centrum",
    "sg:orig_category":"Avocats and conseillers juridiques",
    "sg:phone":"+32 9 223 84 21",
    "sg:postcode":"9000",
    "sg:province":"Oost-Vlaanderen",
    "wof:name":"Van Caenegem Peter",
    "wof:placetype":"venue"
},
  "geometry": {"coordinates":[3.7217159271,51.0487861633],"type":"Point"}
}