{
  "type": "Feature",
  "properties": {
    "addr:full":"Gistelse Steenweg 58 Brugge West-Vlaanderen 8200",
    "addr:housenumber":"58",
    "addr:postcode":"8200",
    "addr:street":"Gistelse Steenweg",
    "iso:country":"BE",
    "sg:address":"Gistelse Steenweg 58",
    "sg:city":"Brugge",
    "sg:orig_category":"Apotheken",
    "sg:phone":"+32 50 31 38 12",
    "sg:postcode":"8200",
    "sg:province":"West-Vlaanderen",
    "wof:name":"Christine Dieryck",
    "wof:placetype":"venue"
},
  "geometry": {"coordinates":[3.2075059414,51.2037086487],"type":"Point"}
}