{
  "type": "Feature",
  "properties": {
    "addr:full":"Brug J Van Aperenstraat 10 Hoogstraten Antwerpen 2320",
    "addr:housenumber":"10",
    "addr:postcode":"2320",
    "addr:street":"Brug;Aperenstraat",
    "iso:country":"BE",
    "sg:address":"Brug J Van Aperenstraat 10",
    "sg:city":"Hoogstraten",
    "sg:classifiers":[
        {
            "category":"Building & Trades",
            "subcategory":"Landscaping Services",
            "type":"Services"
        }
    ],
    "sg:phone":"+32 3 314 86 60",
    "sg:postcode":"2320",
    "sg:province":"Antwerpen",
    "sg:tags":[
        "etude",
        "technique",
        "ing\u00e9nierie"
    ],
    "wof:name":"Blockx J Ir Ateliers",
    "wof:placetype":"venue"
},
  "geometry": {"coordinates":[4.7582840919,51.4002151489],"type":"Point"}
}