{
  "type": "Feature",
  "properties": {
    "addr:full":"Ichtegemstraat 44 Kortemark West-Vlaanderen 8610",
    "addr:housenumber":"44",
    "addr:postcode":"8610",
    "addr:street":"Ichtegemstraat",
    "iso:country":"BE",
    "sg:address":"Ichtegemstraat 44",
    "sg:city":"Kortemark",
    "sg:classifiers":[
        {
            "category":"Personal",
            "subcategory":"Beauty Salon",
            "type":"Services"
        }
    ],
    "sg:phone":"+32 51 57 06 76",
    "sg:postcode":"8610",
    "sg:province":"West-Vlaanderen",
    "sg:tags":[
        "lady",
        "-",
        "hairdressing"
    ],
    "wof:name":"Huyst A",
    "wof:placetype":"venue"
},
  "geometry": {"coordinates":[3.0353820324,51.0385322571],"type":"Point"}
}