{
  "type": "Feature",
  "properties": {
    "addr:full":"Vossemberg 62 Tervuren Vlaams-Brabant 3080",
    "addr:housenumber":"62",
    "addr:postcode":"3080",
    "addr:street":"Vossemberg",
    "iso:country":"BE",
    "sg:address":"Vossemberg 62",
    "sg:city":"Tervuren",
    "sg:orig_category":"Groententeelt",
    "sg:phone":"+32 2 767 46 56",
    "sg:postcode":"3080",
    "sg:province":"Vlaams-Brabant",
    "wof:name":"Bruno Vander Elst",
    "wof:placetype":"venue"
},
  "geometry": {"coordinates":[4.5659279823,50.8286476135],"type":"Point"}
}