{
  "type": "Feature",
  "properties": {
    "iso:country":"BE",
    "sg:address":"Handzameplein 28",
    "sg:city":"Kortemark",
    "sg:orig_category":"Fotografen and fotostudio's",
    "sg:phone":"+32 51 56 99 50",
    "sg:postcode":"8610",
    "sg:province":"West-Vlaanderen",
    "wof:name":"Peter Dewulf",
    "wof:placetype":"venue"
},
  "geometry": {"coordinates":[3.0364470482,51.0293006897],"type":"Point"}
}