{
  "type": "Feature",
  "properties": {
    "addr:full":"Steenweg 34 Mechelen Antwerpen 2800",
    "addr:housenumber":"34",
    "addr:postcode":"2800",
    "addr:street":"Steenweg",
    "iso:country":"BE",
    "sg:address":"Steenweg 34",
    "sg:city":"Mechelen",
    "sg:orig_category":"Art and fournitures artistiques. Salles de spectacles",
    "sg:phone":"+32 15 20 03 22",
    "sg:postcode":"2800",
    "sg:province":"Antwerpen",
    "wof:name":"Alkader",
    "wof:placetype":"venue"
},
  "geometry": {"coordinates":[4.4790000916,51.0282516479],"type":"Point"}
}