{
  "type": "Feature",
  "properties": {
    "addr:full":"Kipdorpvest 38 Antwerpen Antwerpen 2000",
    "addr:housenumber":"38",
    "addr:postcode":"2000",
    "addr:street":"Kipdorpvest",
    "iso:country":"BE",
    "sg:address":"Kipdorpvest 38",
    "sg:city":"Antwerpen",
    "sg:classifiers":[
        {
            "category":"Restaurant",
            "type":"Food & Drink"
        }
    ],
    "sg:phone":"+32 3 226 30 16",
    "sg:postcode":"2000",
    "sg:province":"Antwerpen",
    "wof:name":"Moderato",
    "wof:placetype":"venue"
},
  "geometry": {"coordinates":[4.4139900208,51.2179336548],"type":"Point"}
}