{
  "type": "Feature",
  "properties": {
    "addr:full":"Stationslaan 27 Tongeren Limburg 3700",
    "addr:housenumber":"27",
    "addr:postcode":"3700",
    "addr:street":"Stationslaan",
    "iso:country":"BE",
    "sg:address":"Stationslaan 27",
    "sg:city":"Tongeren",
    "sg:classifiers":[
        {
            "category":"Insurance",
            "subcategory":"Life Insurance",
            "type":"Services"
        }
    ],
    "sg:phone":"+32 12 39 05 11",
    "sg:postcode":"3700",
    "sg:province":"Limburg",
    "sg:tags":[
        "assurance"
    ],
    "wof:name":"P&v",
    "wof:placetype":"venue"
},
  "geometry": {"coordinates":[5.4721841812,50.7834777832],"type":"Point"}
}