{
  "type": "Feature",
  "properties": {
    "iso:country":"BE",
    "sg:address":"Chauss\u00c9e De Mariemont 2",
    "sg:city":"Morlanwelz",
    "sg:orig_category":"Openbare veiligheid",
    "sg:phone":"+32 64 44 22 24",
    "sg:postcode":"7140",
    "sg:province":"Hainaut",
    "wof:name":"Police F\u00c9d\u00c9rale/federale Politie",
    "wof:placetype":"venue"
},
  "geometry": {"coordinates":[4.2352399826,50.4534683228],"type":"Point"}
}