{
  "type": "Feature",
  "properties": {
    "addr:full":"Schoolstraat 2 Dikkelvenne Oost-Vlaanderen 9890",
    "addr:housenumber":"2",
    "addr:postcode":"9890",
    "addr:street":"Schoolstraat;Oost-Vlaanderen",
    "iso:country":"BE",
    "sg:address":"Schoolstraat 2",
    "sg:city":"Dikkelvenne",
    "sg:classifiers":[
        {
            "category":"Shopping",
            "subcategory":"Clothing, Apparel, & Fashions",
            "type":"Retail Goods"
        }
    ],
    "sg:phone":"+32 9 384 84 00",
    "sg:postcode":"9890",
    "sg:province":"Oost-Vlaanderen",
    "sg:tags":[
        "textile",
        "clothing",
        "clothes"
    ],
    "wof:name":"Flanders Confection Nv",
    "wof:placetype":"venue"
},
  "geometry": {"coordinates":[3.6588599682,50.9283752441],"type":"Point"}
}