{
  "type": "Feature",
  "properties": {
    "addr:full":"Rue De La Buscaille 13 Pont-a-celles Hainaut 6230",
    "addr:housenumber":"13",
    "addr:postcode":"6230",
    "addr:street":"Rue De La Buscaille",
    "iso:country":"BE",
    "sg:address":"Rue De La Buscaille 13",
    "sg:city":"Pont-a-celles",
    "sg:orig_category":"HUISBRANDOLIE",
    "sg:phone":"+32 71 84 55 25",
    "sg:postcode":"6230",
    "sg:province":"Hainaut",
    "wof:name":"Dascotte",
    "wof:placetype":"venue"
},
  "geometry": {"coordinates":[4.3687210083,50.5327796936],"type":"Point"}
}