{
  "type": "Feature",
  "properties": {
    "addr:full":"R De La Foret 66 Tenneville Luxembourg 6970",
    "addr:housenumber":"66",
    "addr:postcode":"6970",
    "iso:country":"BE",
    "sg:address":"R De La Foret 66",
    "sg:city":"Tenneville",
    "sg:classifiers":[
        {
            "category":"Health Services",
            "subcategory":"Nursing And Care Facility",
            "type":"Services"
        }
    ],
    "sg:phone":"+32 84 45 53 30",
    "sg:postcode":"6970",
    "sg:province":"Luxembourg",
    "sg:tags":[
        "home",
        "rest"
    ],
    "wof:name":"R\u00e9sidence De La For\u00eat",
    "wof:placetype":"venue"
},
  "geometry": {"coordinates":[5.5048799515,50.0882911682],"type":"Point"}
}