{
  "type": "Feature",
  "properties": {
    "addr:full":"Doorniksewijk 103 Kortrijk West-Vlaanderen 8500",
    "addr:housenumber":"103",
    "addr:postcode":"8500",
    "iso:country":"BE",
    "sg:address":"Doorniksewijk 103",
    "sg:city":"Kortrijk",
    "sg:classifiers":[
        {
            "category":"Home & Garden",
            "subcategory":"Home Furnishings",
            "type":"Retail Goods"
        }
    ],
    "sg:phone":"+32 56 21 19 77",
    "sg:postcode":"8500",
    "sg:province":"West-Vlaanderen",
    "sg:tags":[
        "curtain",
        "-",
        "fixture"
    ],
    "wof:name":"Verana Nv",
    "wof:placetype":"venue"
},
  "geometry": {"coordinates":[3.2695300579,50.8193435669],"type":"Point"}
}