{
  "type": "Feature",
  "properties": {
    "iso:country":"BE",
    "sg:address":"Lagesteenweg 20",
    "sg:city":"Grimbergen",
    "sg:orig_category":"Dameskledingzaken Herenkledingzaken Lingerie and ondergoed",
    "sg:phone":"+32 2 270 82 87",
    "sg:postcode":"1850",
    "sg:province":"Vlaams-Brabant",
    "wof:name":"Huis Bona Dea",
    "wof:placetype":"venue"
},
  "geometry": {"coordinates":[4.3695039749,50.9328765869],"type":"Point"}
}