{
  "type": "Feature",
  "properties": {
    "iso:country":"BE",
    "sg:address":"Avenue Du Ch\u00e2teau 91",
    "sg:city":"Mouscron",
    "sg:classifiers":[
        {
            "category":"Professional",
            "subcategory":"Accounting & Tax Preparation",
            "type":"Services"
        }
    ],
    "sg:phone":"+32 56 33 25 67",
    "sg:postcode":"7700",
    "sg:province":"Hainaut",
    "sg:tags":[
        "accountant"
    ],
    "wof:name":"Santel\u00e9 W",
    "wof:placetype":"venue"
},
  "geometry": {"coordinates":[3.2257189751,50.7461891174],"type":"Point"}
}