{
  "type": "Feature",
  "properties": {
    "addr:full":"Saint Germain 166d Pepinster Li\u00e8ge 4860",
    "addr:housenumber":"166d",
    "addr:postcode":"4860",
    "iso:country":"BE",
    "sg:address":"Saint Germain 166d",
    "sg:city":"Pepinster",
    "sg:classifiers":[
        {
            "category":"Cinema",
            "subcategory":"Movie Theater",
            "type":"Entertainment"
        }
    ],
    "sg:phone":"+32 87 46 31 22",
    "sg:postcode":"4860",
    "sg:province":"Li\u00e8ge",
    "wof:name":"Cin\u00e9 Galerie",
    "wof:placetype":"venue"
},
  "geometry": {"coordinates":[5.792719841,50.585609436],"type":"Point"}
}