{
  "type": "Feature",
  "properties": {
    "iso:country":"BE",
    "sg:address":"Gabrielle Petitstraat 2",
    "sg:city":"Moeskroen/mouscron",
    "sg:orig_category":"Winkelinrichting and handelsuitrusting Gh",
    "sg:phone":"+32 56 48 59 11",
    "sg:postcode":"7711",
    "sg:province":"Hainaut",
    "wof:name":"Francis Saffers",
    "wof:placetype":"venue"
},
  "geometry": {"coordinates":[3.3081281185,50.7210540771],"type":"Point"}
}