{
  "type": "Feature",
  "properties": {
    "iso:country":"BE",
    "sg:address":"Woudstraat 19",
    "sg:city":"Genk",
    "sg:classifiers":[
        {
            "category":"Freight",
            "type":"Transportation"
        }
    ],
    "sg:phone":"+32 89 84 11 22",
    "sg:postcode":"3600",
    "sg:province":"Limburg",
    "sg:tags":[
        "-",
        "transport"
    ],
    "wof:name":"B&b Belgium Express",
    "wof:placetype":"venue"
},
  "geometry": {"coordinates":[5.4761857986,51.0025215149],"type":"Point"}
}