{
  "type": "Feature",
  "properties": {
    "iso:country":"BE",
    "sg:address":"Plein 8",
    "sg:city":"Vorselaar",
    "sg:classifiers":[
        {
            "category":"Parking",
            "subcategory":"Garage",
            "type":"Transportation"
        }
    ],
    "sg:phone":"+32 14 50 00 38",
    "sg:postcode":"2290",
    "sg:province":"Antwerpen",
    "sg:tags":[
        "truck",
        "-",
        "dump",
        "transport"
    ],
    "wof:name":"Van Oeckel R",
    "wof:placetype":"venue"
},
  "geometry": {"coordinates":[4.7764568329,51.2304649353],"type":"Point"}
}