{
  "type": "Feature",
  "properties": {
    "addr:full":"Wasvenweg 4 Wuustwezel (loenhout) Antwerpen 2990",
    "addr:housenumber":"4",
    "addr:postcode":"2990",
    "addr:street":"Wasvenweg",
    "iso:country":"BE",
    "sg:address":"Wasvenweg 4",
    "sg:city":"Wuustwezel (loenhout)",
    "sg:classifiers":[
        {
            "category":"Farming",
            "subcategory":"Crops",
            "type":"Manufacturing & Wholesale Goods"
        }
    ],
    "sg:phone":"+32 3 669 89 27",
    "sg:postcode":"2990",
    "sg:province":"Antwerpen",
    "sg:tags":[
        "vegetable",
        "fruit",
        "-",
        "grower"
    ],
    "wof:name":"V W Tuinderijen",
    "wof:placetype":"venue"
},
  "geometry": {"coordinates":[4.6737499237,51.4231033325],"type":"Point"}
}