{
  "type": "Feature",
  "properties": {
    "addr:full":"Begeveldstraat 36 Bilzen (beverst) Limburg 3740",
    "addr:housenumber":"36",
    "addr:postcode":"3740",
    "addr:street":"Begeveldstraat",
    "iso:country":"BE",
    "sg:address":"Begeveldstraat 36",
    "sg:city":"Bilzen (beverst)",
    "sg:classifiers":[
        {
            "category":"Real Estate",
            "subcategory":"Architect",
            "type":"Services"
        }
    ],
    "sg:phone":"+32 11 32 12 04",
    "sg:postcode":"3740",
    "sg:province":"Limburg",
    "wof:name":"Schils N",
    "wof:placetype":"venue"
},
  "geometry": {"coordinates":[5.463367939,50.9085044861],"type":"Point"}
}