{
  "type": "Feature",
  "properties": {
    "iso:country":"BE",
    "sg:address":"Rue De L\u00b4ancienne Place 3",
    "sg:city":"Brunehaut",
    "sg:orig_category":"Traitements param\u00e9dicaux",
    "sg:phone":"+32 69 34 67 67",
    "sg:postcode":"7622",
    "sg:province":"Hainaut",
    "wof:name":"N. Wilfart",
    "wof:placetype":"venue"
},
  "geometry": {"coordinates":[3.4469599724,50.5208015442],"type":"Point"}
}