{
  "type": "Feature",
  "properties": {
    "addr:full":". Kaprijke (groot) Oost-Vlaanderen 9970",
    "addr:postcode":"9970",
    "addr:street":"Groot Oost-Vlaanderen",
    "iso:country":"BE",
    "sg:address":".",
    "sg:city":"Kaprijke (groot)",
    "sg:orig_category":"Apotheken",
    "sg:phone":"+32 900 10 500",
    "sg:postcode":"9970",
    "sg:province":"Oost-Vlaanderen",
    "wof:name":"Apothekers Van Wacht",
    "wof:placetype":"venue"
},
  "geometry": {"coordinates":[3.617675066,51.2182540894],"type":"Point"}
}