{
  "type": "Feature",
  "properties": {
    "iso:country":"BE",
    "sg:address":"Kasteelstraat 9",
    "sg:city":"Tervuren",
    "sg:orig_category":"Immobili\u00ebnkantoren Landmeters and schatters",
    "sg:phone":"+32 16 65 04 54",
    "sg:postcode":"3080",
    "sg:province":"Vlaams-Brabant",
    "wof:name":"Vuerinckx",
    "wof:placetype":"venue"
},
  "geometry": {"coordinates":[4.5138731003,50.823348999],"type":"Point"}
}