{
  "type": "Feature",
  "properties": {
    "iso:country":"BE",
    "sg:address":"Gebr. Vandeveldestraat 103",
    "sg:city":"Gent",
    "sg:classifiers":[
        {
            "category":"Cafe",
            "type":"Food & Drink"
        }
    ],
    "sg:phone":"+32 9 223 33 79",
    "sg:postcode":"9000",
    "sg:province":"Oost-Vlaanderen",
    "sg:tags":[
        "caf\u00e9s"
    ],
    "wof:name":"Caf\u00c9 De Kikker",
    "wof:placetype":"venue"
},
  "geometry": {"coordinates":[3.7180309296,51.0503120422],"type":"Point"}
}