{
  "type": "Feature",
  "properties": {
    "iso:country":"BE",
    "sg:address":"Hoogstraat 367bb",
    "sg:city":"Duffel",
    "sg:orig_category":"Landbouwmachines Gh",
    "sg:phone":"+32 15 31 93 82",
    "sg:postcode":"2570",
    "sg:province":"Antwerpen",
    "wof:name":"Van Edom Eric",
    "wof:placetype":"venue"
},
  "geometry": {"coordinates":[4.5449399948,51.0937423706],"type":"Point"}
}