{
  "type": "Feature",
  "properties": {
    "addr:full":"Martenslindestraat 55 Bilzen Limburg 3742",
    "addr:housenumber":"55",
    "addr:postcode":"3742",
    "addr:street":"Martenslindestraat",
    "iso:country":"BE",
    "sg:address":"Martenslindestraat 55",
    "sg:city":"Bilzen",
    "sg:orig_category":"M\u00e9decins and sp\u00e9cialistes",
    "sg:phone":"+32 89 41 55 90",
    "sg:postcode":"3742",
    "sg:province":"Limburg",
    "wof:name":"A. Vande Kerckhove",
    "wof:placetype":"venue"
},
  "geometry": {"coordinates":[5.5358967781,50.8510665894],"type":"Point"}
}