{
  "type": "Feature",
  "properties": {
    "addr:full":"Rue De Marchienne 32-34 Montigny-le-tilleul Hainaut 6110",
    "addr:postcode":"32-34;6110",
    "addr:street":"Rue De Marchienne;Hainaut",
    "iso:country":"BE",
    "sg:address":"Rue De Marchienne 32-34",
    "sg:city":"Montigny-le-tilleul",
    "sg:classifiers":[
        {
            "category":"Health Services",
            "subcategory":"Doctor",
            "type":"Services"
        }
    ],
    "sg:phone":"+32 71 51 80 56",
    "sg:postcode":"6110",
    "sg:province":"Hainaut",
    "sg:tags":[
        "medicinephysicians",
        "surgeon"
    ],
    "wof:name":"Halford G",
    "wof:placetype":"venue"
},
  "geometry": {"coordinates":[4.3804569244,50.3804893494],"type":"Point"}
}