{
  "type": "Feature",
  "properties": {
    "addr:full":"Vuilstraat 7 Geraardsbergen Oost-Vlaanderen 9506",
    "addr:housenumber":"7",
    "addr:postcode":"9506",
    "addr:street":"Vuilstraat",
    "iso:country":"BE",
    "sg:address":"Vuilstraat 7",
    "sg:city":"Geraardsbergen",
    "sg:orig_category":"Woningbouw",
    "sg:phone":"+32 54 50 37 09",
    "sg:postcode":"9506",
    "sg:province":"Oost-Vlaanderen",
    "wof:name":"Hemeryckx",
    "wof:placetype":"venue"
},
  "geometry": {"coordinates":[3.9169108868,50.8150787354],"type":"Point"}
}