{
  "type": "Feature",
  "properties": {
    "iso:country":"BE",
    "sg:address":"Maastrichterstraat 13",
    "sg:city":"Tongeren",
    "sg:orig_category":"Fleurs and plantes",
    "sg:phone":"+32 12 23 90 25",
    "sg:postcode":"3700",
    "sg:province":"Limburg",
    "wof:name":"Il Verde In Festa",
    "wof:placetype":"venue"
},
  "geometry": {"coordinates":[5.4645180702,50.7814865112],"type":"Point"}
}