{
  "type": "Feature",
  "properties": {
    "addr:full":"Merodestraat 6 Beveren Oost-Vlaanderen 9130",
    "addr:housenumber":"6",
    "addr:postcode":"9130",
    "addr:street":"Merodestraat",
    "iso:country":"BE",
    "sg:address":"Merodestraat 6",
    "sg:city":"Beveren",
    "sg:orig_category":"Cr\u00e9meries. Epiceries",
    "sg:phone":"+32 3 773 42 63",
    "sg:postcode":"9130",
    "sg:province":"Oost-Vlaanderen",
    "wof:name":"Suurd",
    "wof:placetype":"venue"
},
  "geometry": {"coordinates":[4.1700639725,51.2891387939],"type":"Point"}
}