{
  "type": "Feature",
  "properties": {
    "iso:country":"BE",
    "sg:address":"Padweg 19",
    "sg:city":"Zele",
    "sg:orig_category":"Goederenvervoer over de weg",
    "sg:phone":"+32 52 44 69 28",
    "sg:postcode":"9240",
    "sg:province":"Oost-Vlaanderen",
    "wof:name":"Neirynck Robert",
    "wof:placetype":"venue"
},
  "geometry": {"coordinates":[4.0254130363,51.0641899109],"type":"Point"}
}