{
  "type": "Feature",
  "properties": {
    "addr:full":"Ternatsestraat 67 Affligem Vlaams-Brabant 1790",
    "addr:housenumber":"67",
    "addr:postcode":"1790",
    "addr:street":"Ternatsestraat",
    "iso:country":"BE",
    "sg:address":"Ternatsestraat 67",
    "sg:city":"Affligem",
    "sg:orig_category":"M\u00e9decins and sp\u00e9cialistes",
    "sg:phone":"+32 2 582 12 96",
    "sg:postcode":"1790",
    "sg:province":"Vlaams-Brabant",
    "wof:name":"Philippe De Ryck",
    "wof:placetype":"venue"
},
  "geometry": {"coordinates":[4.1381731033,50.8979873657],"type":"Point"}
}