{
  "type": "Feature",
  "properties": {
    "addr:full":"Eindepoel 14 Vosselaar Antwerpen 2350",
    "addr:housenumber":"14",
    "addr:postcode":"2350",
    "addr:street":"Eindepoel",
    "iso:country":"BE",
    "sg:address":"Eindepoel 14",
    "sg:city":"Vosselaar",
    "sg:classifiers":[
        {
            "category":"Health Services",
            "subcategory":"Doctor",
            "type":"Services"
        }
    ],
    "sg:phone":"+32 14 61 21 57",
    "sg:postcode":"2350",
    "sg:province":"Antwerpen",
    "sg:tags":[
        "medicinephysicians",
        "surgeon"
    ],
    "wof:name":"Geenen I",
    "wof:placetype":"venue"
},
  "geometry": {"coordinates":[4.8724870682,51.3163490295],"type":"Point"}
}