{
  "type": "Feature",
  "properties": {
    "addr:full":"Weimanstraat 42 Zuienkerke West-Vlaanderen 8377",
    "addr:housenumber":"42",
    "addr:postcode":"8377",
    "addr:street":"Weimanstraat",
    "iso:country":"BE",
    "sg:address":"Weimanstraat 42",
    "sg:city":"Zuienkerke",
    "sg:orig_category":"Advocaten and juridische adviseurs",
    "sg:phone":"+32 50 31 02 97",
    "sg:postcode":"8377",
    "sg:province":"West-Vlaanderen",
    "wof:name":"Moeykens & De Loose",
    "wof:placetype":"venue"
},
  "geometry": {"coordinates":[3.1815440655,51.2538604736],"type":"Point"}
}