{
  "type": "Feature",
  "properties": {
    "iso:country":"BE",
    "sg:address":"Kattestraat 40",
    "sg:city":"Ham",
    "sg:orig_category":"R\u00e9alisation de programmes and logiciels",
    "sg:phone":"+32 11 34 50 20",
    "sg:postcode":"3945",
    "sg:province":"Limburg",
    "wof:name":"The Belgian Webvertisers",
    "wof:placetype":"venue"
},
  "geometry": {"coordinates":[5.1776199341,51.1046104431],"type":"Point"}
}