{
  "type": "Feature",
  "properties": {
    "addr:full":"Place Emile Dupont 15 Li\u00c8ge Li\u00e8ge 4000",
    "addr:housenumber":"15",
    "addr:postcode":"4000",
    "addr:street":"Place Emile Dupont",
    "iso:country":"BE",
    "sg:address":"Place Emile Dupont 15",
    "sg:city":"Li\u00c8ge",
    "sg:orig_category":"M\u00e9decins and sp\u00e9cialistes",
    "sg:phone":"+32 4 223 51 61",
    "sg:postcode":"4000",
    "sg:province":"Li\u00e8ge",
    "wof:name":"Beno\u00cet Rennotte",
    "wof:placetype":"venue"
},
  "geometry": {"coordinates":[5.5702171326,50.6362495422],"type":"Point"}
}