{
  "type": "Feature",
  "properties": {
    "addr:full":"Kraanlei 43 Gent Oost-Vlaanderen 9000",
    "addr:housenumber":"43",
    "addr:postcode":"9000",
    "addr:street":"Kraanlei;Oost-Vlaanderen",
    "iso:country":"BE",
    "sg:address":"Kraanlei 43",
    "sg:city":"Gent",
    "sg:orig_category":"Meubelzaken, woning- and keukeninrichting",
    "sg:phone":"+32 9 234 34 59",
    "sg:postcode":"9000",
    "sg:province":"Oost-Vlaanderen",
    "wof:name":"Raj",
    "wof:placetype":"venue"
},
  "geometry": {"coordinates":[3.7228760719,51.0572357178],"type":"Point"}
}