{
  "type": "Feature",
  "properties": {
    "addr:full":"Vaartstraat 15 Ieper West-Vlaanderen 8902",
    "addr:housenumber":"15",
    "addr:postcode":"8902",
    "addr:street":"Vaartstraat",
    "iso:country":"BE",
    "sg:address":"Vaartstraat 15",
    "sg:city":"Ieper",
    "sg:orig_category":"Eleveurs and marchands de porcs",
    "sg:phone":"+32 57 20 52 26",
    "sg:postcode":"8902",
    "sg:province":"West-Vlaanderen",
    "wof:name":"Maurice Capoen",
    "wof:placetype":"venue"
},
  "geometry": {"coordinates":[2.8952419758,50.8162918091],"type":"Point"}
}