{
  "type": "Feature",
  "properties": {
    "iso:country":"BE",
    "sg:address":"Melselestraat 79",
    "sg:city":"Zwijndrecht",
    "sg:orig_category":"Fruitteelt Groententeelt",
    "sg:phone":"+32 3 252 56 49",
    "sg:postcode":"2070",
    "sg:province":"Antwerpen",
    "wof:name":"Andre De Langhe",
    "wof:placetype":"venue"
},
  "geometry": {"coordinates":[4.3119502068,51.2170295715],"type":"Point"}
}