{
  "type": "Feature",
  "properties": {
    "iso:country":"BE",
    "sg:address":"Rue Lahaut 109",
    "sg:city":"Seraing",
    "sg:classifiers":[
        {
            "category":"Building & Trades",
            "subcategory":"Electrical",
            "type":"Services"
        }
    ],
    "sg:phone":"+32 4 336 98 08",
    "sg:postcode":"4100",
    "sg:province":"Li\u00e8ge",
    "sg:tags":[
        "electric",
        "-",
        "housewiring",
        "contractor"
    ],
    "wof:name":"Aeg Electricite Koch Sa",
    "wof:placetype":"venue"
},
  "geometry": {"coordinates":[5.5110030174,50.5927963257],"type":"Point"}
}