{
  "type": "Feature",
  "properties": {
    "addr:full":"Grand-route 207 Flemalle Li\u00e8ge 4400",
    "addr:housenumber":"207",
    "addr:postcode":"4400",
    "addr:street":"Grand-Route",
    "iso:country":"BE",
    "sg:address":"Grand-route 207",
    "sg:city":"Flemalle",
    "sg:orig_category":"Entretien and r\u00e9parations de voitures. V\u00e9hicules automobiles",
    "sg:phone":"+32 4 332 85 39",
    "sg:postcode":"4400",
    "sg:province":"Li\u00e8ge",
    "wof:name":"Mahy",
    "wof:placetype":"venue"
},
  "geometry": {"coordinates":[5.4748520851,50.600894928],"type":"Point"}
}