{
  "type": "Feature",
  "properties": {
    "iso:country":"BE",
    "sg:address":"Bosstraat 23",
    "sg:city":"Waasmunster",
    "sg:classifiers":[
        {
            "category":"Utilities",
            "subcategory":"Cable",
            "type":"Services"
        }
    ],
    "sg:phone":"+32 3 727 01 50",
    "sg:postcode":"9250",
    "sg:province":"Oost-Vlaanderen",
    "sg:tags":[
        "rope",
        "twine"
    ],
    "wof:name":"Verkoopkantoor Fybron Nv",
    "wof:placetype":"venue"
},
  "geometry": {"coordinates":[4.0992360115,51.1275863647],"type":"Point"}
}