{
  "type": "Feature",
  "properties": {
    "iso:country":"BE",
    "sg:address":"Avenue Henri Liebrecht 78b13",
    "sg:city":"Jette",
    "sg:classifiers":[
        {
            "category":"Arena",
            "subcategory":"Sports Club",
            "type":"Entertainment"
        }
    ],
    "sg:phone":"+32 2 478 27 84",
    "sg:postcode":"1090",
    "sg:province":"Bruxelles-Capitale",
    "sg:tags":[
        "de"
    ],
    "wof:name":"Wolu Plong\u00c9e",
    "wof:placetype":"venue"
},
  "geometry": {"coordinates":[4.3177309036,50.8908653259],"type":"Point"}
}