{
  "type": "Feature",
  "properties": {
    "addr:full":"Rue De Malines 50 Brussel/bruxelles Bruxelles-Capitale 1000",
    "addr:housenumber":"50",
    "addr:postcode":"1000",
    "addr:street":"Rue De Malines;/",
    "iso:country":"BE",
    "sg:address":"Rue De Malines 50",
    "sg:city":"Brussel/bruxelles",
    "sg:orig_category":"Schoenen",
    "sg:phone":"+32 2 219 76 36",
    "sg:postcode":"1000",
    "sg:province":"Bruxelles-Capitale",
    "wof:name":"Key West",
    "wof:placetype":"venue"
},
  "geometry": {"coordinates":[4.3572201729,50.853969574],"type":"Point"}
}