{
  "type": "Feature",
  "properties": {
    "addr:full":"Rue Hamoir 11 La Louvi\u00e8re Hainaut 7100",
    "addr:housenumber":"11",
    "addr:postcode":"7100",
    "addr:street":"Rue Hamoir",
    "iso:country":"BE",
    "sg:address":"Rue Hamoir 11",
    "sg:city":"La Louvi\u00e8re",
    "sg:classifiers":[
        {
            "category":"Personal",
            "subcategory":"Beauty Salon",
            "type":"Services"
        }
    ],
    "sg:phone":"+32 64 33 31 69",
    "sg:postcode":"7100",
    "sg:province":"Hainaut",
    "sg:tags":[
        "lady",
        "-",
        "hairdressing"
    ],
    "wof:name":"N H C",
    "wof:placetype":"venue"
},
  "geometry": {"coordinates":[4.1871590614,50.4750404358],"type":"Point"}
}