{
  "type": "Feature",
  "properties": {
    "addr:full":"Eikerlandstraat 16 Puurs Antwerpen 2870",
    "addr:housenumber":"16",
    "addr:postcode":"2870",
    "addr:street":"Eikerlandstraat",
    "iso:country":"BE",
    "sg:address":"Eikerlandstraat 16",
    "sg:city":"Puurs",
    "sg:orig_category":"Paramedische behandelingen",
    "sg:phone":"+32 3 886 24 13",
    "sg:postcode":"2870",
    "sg:province":"Antwerpen",
    "wof:name":"Van Tricht",
    "wof:placetype":"venue"
},
  "geometry": {"coordinates":[4.3282690048,51.0776672363],"type":"Point"}
}