{
  "type": "Feature",
  "properties": {
    "addr:full":"Kelverstraat 27 Aarschot (langdorp) Vlaams-Brabant 3201",
    "addr:housenumber":"27",
    "addr:postcode":"3201",
    "addr:street":"Kelverstraat",
    "iso:country":"BE",
    "sg:address":"Kelverstraat 27",
    "sg:city":"Aarschot (langdorp)",
    "sg:classifiers":[
        {
            "category":"Health Services",
            "subcategory":"Health Practitioner",
            "type":"Services"
        }
    ],
    "sg:phone":"+32 16 56 22 01",
    "sg:postcode":"3201",
    "sg:province":"Vlaams-Brabant",
    "sg:tags":[
        "psychologist"
    ],
    "wof:name":"Crauwels R",
    "wof:placetype":"venue"
},
  "geometry": {"coordinates":[4.8520998955,51.0069465637],"type":"Point"}
}