{
  "type": "Feature",
  "properties": {
    "iso:country":"BE",
    "sg:address":"Rue Inchebroux 6",
    "sg:city":"Chaumont-gistoux",
    "sg:classifiers":[
        {
            "category":"Professional",
            "subcategory":"Business Services",
            "type":"Services"
        }
    ],
    "sg:phone":"+32 10 68 85 26",
    "sg:postcode":"1325",
    "sg:province":"Brabant Wallon",
    "sg:tags":[
        "aux",
        "diver",
        "entreprises"
    ],
    "wof:name":"Improart",
    "wof:placetype":"venue"
},
  "geometry": {"coordinates":[4.6920771599,50.68932724],"type":"Point"}
}