{
  "type": "Feature",
  "properties": {
    "addr:full":"Kattendijkdok Westkaai 28 Antwerpen Antwerpen 2000",
    "addr:housenumber":"28",
    "addr:postcode":"2000",
    "addr:street":"Westkaai",
    "iso:country":"BE",
    "sg:address":"Kattendijkdok Westkaai 28",
    "sg:city":"Antwerpen",
    "sg:classifiers":[
        {
            "category":"Professional",
            "subcategory":"Business Services",
            "type":"Services"
        }
    ],
    "sg:phone":"+32 3 202 41 81",
    "sg:postcode":"2000",
    "sg:province":"Antwerpen",
    "sg:tags":[
        "consultant",
        "custom"
    ],
    "wof:name":"De Buysscher & Brenders Nv",
    "wof:placetype":"venue"
},
  "geometry": {"coordinates":[4.4049282074,51.2319602966],"type":"Point"}
}