{
  "type": "Feature",
  "properties": {
    "addr:full":"Luikersteenweg 402 Tongeren Limburg 3700",
    "addr:housenumber":"402",
    "addr:postcode":"3700",
    "addr:street":"Luikersteenweg",
    "iso:country":"BE",
    "sg:address":"Luikersteenweg 402",
    "sg:city":"Tongeren",
    "sg:orig_category":"Catering and organisatie van feesten Fast food and meeneem restaurants Restaurants",
    "sg:phone":"+32 12 23 77 92",
    "sg:postcode":"3700",
    "sg:province":"Limburg",
    "wof:name":"Dinner Garden",
    "wof:placetype":"venue"
},
  "geometry": {"coordinates":[5.4735560417,50.7634391785],"type":"Point"}
}