{
  "type": "Feature",
  "properties": {
    "addr:full":"Koningsplein 8 Hamme (moerzeke) Oost-Vlaanderen 9220",
    "addr:housenumber":"8",
    "addr:postcode":"9220",
    "addr:street":"Koningsplein",
    "iso:country":"BE",
    "sg:address":"Koningsplein 8",
    "sg:city":"Hamme (moerzeke)",
    "sg:classifiers":[
        {
            "category":"Bars & Pubs",
            "type":"Food & Drink"
        }
    ],
    "sg:phone":"+32 52 47 99 55",
    "sg:postcode":"9220",
    "sg:province":"Oost-Vlaanderen",
    "wof:name":"Vier Gekroonden (de)",
    "wof:placetype":"venue"
},
  "geometry": {"coordinates":[4.1495127678,51.0616798401],"type":"Point"}
}