{
  "type": "Feature",
  "properties": {
    "addr:full":"Rue De La Lib\u00e9ration 4 Braine-le-ch\u00e2teau Brabant Wallon 1440",
    "addr:housenumber":"4",
    "addr:postcode":"1440",
    "addr:street":"Rue De La Libe\u0301Ration",
    "iso:country":"BE",
    "sg:address":"Rue De La Lib\u00e9ration 4",
    "sg:city":"Braine-le-ch\u00e2teau",
    "sg:classifiers":[
        {
            "category":"Education",
            "subcategory":"School",
            "type":"Public Place"
        }
    ],
    "sg:phone":"+32 2 366 03 87",
    "sg:postcode":"1440",
    "sg:province":"Brabant Wallon",
    "sg:tags":[
        "primary"
    ],
    "wof:name":"Ecole Libre Mixte St-remy",
    "wof:placetype":"venue"
},
  "geometry": {"coordinates":[4.2680640221,50.6823768616],"type":"Point"}
}