{
  "type": "Feature",
  "properties": {
    "addr:full":"Borredam 26 Ternat Vlaams-Brabant 1740",
    "addr:housenumber":"26",
    "addr:postcode":"1740",
    "addr:street":"Borredam",
    "iso:country":"BE",
    "sg:address":"Borredam 26",
    "sg:city":"Ternat",
    "sg:classifiers":[
        {
            "category":"Professional",
            "subcategory":"Accounting & Tax Preparation",
            "type":"Services"
        }
    ],
    "sg:phone":"+32 2 569 87 94",
    "sg:postcode":"1740",
    "sg:province":"Vlaams-Brabant",
    "sg:tags":[
        "bookkeeper"
    ],
    "wof:name":"De Paepe P",
    "wof:placetype":"venue"
},
  "geometry": {"coordinates":[4.1758098602,50.8726196289],"type":"Point"}
}