{
  "type": "Feature",
  "properties": {
    "iso:country":"BE",
    "sg:address":"Liersesteenweg 206",
    "sg:city":"Aarschot",
    "sg:classifiers":[
        {
            "category":"Autos & Motor Vehicles",
            "subcategory":"Automobile Sales",
            "type":"Retail Goods"
        }
    ],
    "sg:phone":"+32 16 44 31 21",
    "sg:postcode":"3200",
    "sg:province":"Vlaams-Brabant",
    "sg:tags":[
        "delivery",
        "-",
        "used",
        "van",
        "truck"
    ],
    "wof:name":"Storms B",
    "wof:placetype":"venue"
},
  "geometry": {"coordinates":[4.8184399605,51.0059013367],"type":"Point"}
}