{
  "type": "Feature",
  "properties": {
    "iso:country":"BE",
    "sg:address":"Chauss\u00e9e D'armenti\u00e8res 20a",
    "sg:city":"Messines",
    "sg:classifiers":[
        {
            "category":"Home & Garden",
            "subcategory":"Carpets & Floor Coverings",
            "type":"Retail Goods"
        }
    ],
    "sg:phone":"+32 57 44 50 55",
    "sg:postcode":"8957",
    "sg:province":"West-Vlaanderen",
    "sg:tags":[
        "layer",
        "mosaicists"
    ],
    "wof:name":"Pauwels Vloerdersbedrijf Bvba",
    "wof:placetype":"venue"
},
  "geometry": {"coordinates":[2.9005498886,50.7598686218],"type":"Point"}
}