{
  "type": "Feature",
  "properties": {
    "iso:country":"BE",
    "sg:address":"Westakkerstraat 13",
    "sg:city":"Assenede",
    "sg:orig_category":"Rundveehouders Varkenskwekers",
    "sg:phone":"+32 9 373 70 98",
    "sg:postcode":"9968",
    "sg:province":"Oost-Vlaanderen",
    "wof:name":"Rene Wauters",
    "wof:placetype":"venue"
},
  "geometry": {"coordinates":[3.6699590683,51.2013206482],"type":"Point"}
}