{
  "type": "Feature",
  "properties": {
    "addr:full":"Rue De La Fosse Au Sable 42 Braine-l'alleud Brabant Wallon 1420",
    "addr:housenumber":"42",
    "addr:postcode":"1420",
    "addr:street":"Rue De La Fosse Au Sable",
    "iso:country":"BE",
    "sg:address":"Rue De La Fosse Au Sable 42",
    "sg:city":"Braine-l'alleud",
    "sg:classifiers":[
        {
            "category":"Personal",
            "subcategory":"Beauty Salon",
            "type":"Services"
        }
    ],
    "sg:phone":"+32 2 387 08 20",
    "sg:postcode":"1420",
    "sg:province":"Brabant Wallon",
    "sg:tags":[
        "de",
        "coiffure"
    ],
    "wof:name":"Coiffure Christelle",
    "wof:placetype":"venue"
},
  "geometry": {"coordinates":[-83.3254165649,44.4110298157],"type":"Point"}
}