{
  "type": "Feature",
  "properties": {
    "iso:country":"BE",
    "sg:address":"Schanstraat 55",
    "sg:city":"Heusden-zolder",
    "sg:orig_category":"Produits chimiques Gr",
    "sg:phone":"+32 11 57 17 87",
    "sg:postcode":"3550",
    "sg:province":"Limburg",
    "wof:name":"Eco-joy",
    "wof:placetype":"venue"
},
  "geometry": {"coordinates":[5.2955870628,51.0403175354],"type":"Point"}
}