{
  "type": "Feature",
  "properties": {
    "iso:country":"BE",
    "sg:address":"Diksmuidse Heerweg 56",
    "sg:city":"Brugge",
    "sg:orig_category":"Pensions de famille",
    "sg:phone":"+32 50 38 92 47",
    "sg:postcode":"8200",
    "sg:province":"West-Vlaanderen",
    "wof:name":"Van Damme M",
    "wof:placetype":"venue"
},
  "geometry": {"coordinates":[3.2000570297,51.1998901367],"type":"Point"}
}