{
  "type": "Feature",
  "properties": {
    "addr:full":"Kruisvindingsstraat 34 Tongeren Limburg 3700",
    "addr:housenumber":"34",
    "addr:postcode":"3700",
    "addr:street":"Kruisvindingsstraat",
    "iso:country":"BE",
    "sg:address":"Kruisvindingsstraat 34",
    "sg:city":"Tongeren",
    "sg:orig_category":"Dakwerken Loodgieterij, verwarming and sanitaire installaties",
    "sg:phone":"+32 12 39 54 00",
    "sg:postcode":"3700",
    "sg:province":"Limburg",
    "wof:name":"Marcel Vanhay",
    "wof:placetype":"venue"
},
  "geometry": {"coordinates":[5.4636240005,50.7807197571],"type":"Point"}
}