{
  "type": "Feature",
  "properties": {
    "iso:country":"BE",
    "sg:address":"Chemin De Stock 43",
    "sg:city":"Ath",
    "sg:orig_category":"Industri\u00eble and commerci\u00eble bouw",
    "sg:phone":"+32 68 64 51 23",
    "sg:postcode":"7812",
    "sg:province":"Hainaut",
    "wof:name":"Eddy Lemaire",
    "wof:placetype":"venue"
},
  "geometry": {"coordinates":[3.7168750763,50.6487159729],"type":"Point"}
}