{
  "type": "Feature",
  "properties": {
    "addr:full":"Rue De La Montagne 13 Walcourt Namur 5650",
    "addr:housenumber":"13",
    "addr:postcode":"5650",
    "addr:street":"Rue De La Montagne",
    "iso:country":"BE",
    "sg:address":"Rue De La Montagne 13",
    "sg:city":"Walcourt",
    "sg:classifiers":[
        {
            "category":"Personal",
            "subcategory":"Beauty Salon",
            "type":"Services"
        }
    ],
    "sg:phone":"+32 71 61 41 93",
    "sg:postcode":"5650",
    "sg:province":"Namur",
    "sg:tags":[
        "de",
        "coiffure"
    ],
    "wof:name":"Florence",
    "wof:placetype":"venue"
},
  "geometry": {"coordinates":[4.4328708649,50.2539978027],"type":"Point"}
}