{
  "type": "Feature",
  "properties": {
    "iso:country":"BE",
    "sg:address":"Oude Steenweg 5",
    "sg:city":"Blankenberge",
    "sg:classifiers":[
        {
            "category":"Arena",
            "subcategory":"Sports Club",
            "type":"Entertainment"
        }
    ],
    "sg:phone":"+32 50 41 29 80",
    "sg:postcode":"8370",
    "sg:province":"West-Vlaanderen",
    "sg:tags":[
        "de"
    ],
    "wof:name":"De Reisduif",
    "wof:placetype":"venue"
},
  "geometry": {"coordinates":[3.1378250122,51.3085479736],"type":"Point"}
}