{
  "type": "Feature",
  "properties": {
    "addr:full":"Quai Aux Briques 4 Brussel/bruxelles Bruxelles-Capitale 1000",
    "addr:housenumber":"4",
    "addr:postcode":"1000",
    "addr:street":"Quai Aux Briques;/",
    "iso:country":"BE",
    "sg:address":"Quai Aux Briques 4",
    "sg:city":"Brussel/bruxelles",
    "sg:classifiers":[
        {
            "category":"Restaurant",
            "type":"Food & Drink"
        }
    ],
    "sg:phone":"+32 2 512 56 40",
    "sg:postcode":"1000",
    "sg:province":"Bruxelles-Capitale",
    "wof:name":"Rugbyman Nr 1",
    "wof:placetype":"venue"
},
  "geometry": {"coordinates":[4.3480877876,50.8510780334],"type":"Point"}
}