{
  "type": "Feature",
  "properties": {
    "addr:full":"Bloemenlaan 77 Maasmechelen Limburg 3630",
    "addr:housenumber":"77",
    "addr:postcode":"3630",
    "addr:street":"Bloemenlaan",
    "iso:country":"BE",
    "sg:address":"Bloemenlaan 77",
    "sg:city":"Maasmechelen",
    "sg:classifiers":[
        {
            "category":"Restaurant",
            "type":"Food & Drink"
        }
    ],
    "sg:phone":"+32 89 77 48 98",
    "sg:postcode":"3630",
    "sg:province":"Limburg",
    "sg:tags":[
        "\u00c0",
        "domicile",
        "fast",
        "emporter",
        "livraison",
        "restaurants"
    ],
    "wof:name":"Pizza- Foon",
    "wof:placetype":"venue"
},
  "geometry": {"coordinates":[5.7006950378,50.9813652039],"type":"Point"}
}