{
  "type": "Feature",
  "properties": {
    "iso:country":"BE",
    "sg:address":"Leuvensesteenweg 226",
    "sg:city":"Kortenberg",
    "sg:orig_category":"Bijouteries and horlogeries. R\u00e9parations d'horloges, montres and bijoux",
    "sg:phone":"+32 2 759 58 27",
    "sg:postcode":"3070",
    "sg:province":"Vlaams-Brabant",
    "wof:name":"De Backer",
    "wof:placetype":"venue"
},
  "geometry": {"coordinates":[4.540304184,50.8871765137],"type":"Point"}
}