{
  "type": "Feature",
  "properties": {
    "iso:country":"BE",
    "sg:address":"Kortrijksestraat 86",
    "sg:city":"Moorslede",
    "sg:orig_category":"Dakwerken",
    "sg:phone":"+32 56 50 40 96",
    "sg:postcode":"8890",
    "sg:province":"West-Vlaanderen",
    "wof:name":"Wavan",
    "wof:placetype":"venue"
},
  "geometry": {"coordinates":[3.0637769699,50.891456604],"type":"Point"}
}