{
  "type": "Feature",
  "properties": {
    "iso:country":"BE",
    "sg:address":"Watervallestraat 54",
    "sg:city":"Ichtegem",
    "sg:orig_category":"M\u00e9decines alternatives",
    "sg:phone":"+32 50 81 23 43",
    "sg:postcode":"8480",
    "sg:province":"West-Vlaanderen",
    "wof:name":"P. Depuydt",
    "wof:placetype":"venue"
},
  "geometry": {"coordinates":[3.0448179245,51.1554603577],"type":"Point"}
}