{
  "type": "Feature",
  "properties": {
    "addr:full":"Nieuwe Weg 1 (naviga Building) Zwijndrecht Antwerpen 2070",
    "addr:housenumber":"1;building",
    "addr:postcode":"2070",
    "addr:street":"Nieuwe Weg",
    "iso:country":"BE",
    "sg:address":"Nieuwe Weg 1 (naviga Building)",
    "sg:city":"Zwijndrecht",
    "sg:orig_category":"Heavy-Duty Shelves",
    "sg:phone":"+32 3 211 05 23",
    "sg:postcode":"2070",
    "sg:province":"Antwerpen",
    "wof:name":"Esmena Storage Systems",
    "wof:placetype":"venue"
},
  "geometry": {"coordinates":[4.319920063,51.2365455627],"type":"Point"}
}