{
  "type": "Feature",
  "properties": {
    "iso:country":"BE",
    "sg:address":"Belle-ruelle 39",
    "sg:city":"Philippeville",
    "sg:orig_category":"Rev\u00eatements pour sols and murs. Peinture",
    "sg:phone":"+32 475 62 33 23",
    "sg:postcode":"5600",
    "sg:province":"Namur",
    "wof:name":"Jean-francois Goisse",
    "wof:placetype":"venue"
},
  "geometry": {"coordinates":[4.5276679993,50.2167549133],"type":"Point"}
}