{
  "type": "Feature",
  "properties": {
    "addr:full":"Rue De Bellaire 15 Gesves Namur 5340",
    "addr:housenumber":"15",
    "addr:postcode":"5340",
    "addr:street":"Rue De Bellaire",
    "iso:country":"BE",
    "sg:address":"Rue De Bellaire 15",
    "sg:city":"Gesves",
    "sg:orig_category":"Imprimeries and copyshops",
    "sg:phone":"+32 85 84 43 99",
    "sg:postcode":"5340",
    "sg:province":"Namur",
    "wof:name":"Jean-claude Garnier",
    "wof:placetype":"venue"
},
  "geometry": {"coordinates":[5.0738229752,50.4594688416],"type":"Point"}
}