{
  "type": "Feature",
  "properties": {
    "iso:country":"BE",
    "sg:address":"Place Franklin-delano Roosevelt 62",
    "sg:city":"Courcelles",
    "sg:classifiers":[
        {
            "category":"Shopping",
            "subcategory":"Beauty & Cosmetics",
            "type":"Retail Goods"
        }
    ],
    "sg:phone":"+32 71 45 17 92",
    "sg:postcode":"6180",
    "sg:province":"Hainaut",
    "sg:tags":[
        "-",
        "perfumery"
    ],
    "wof:name":"Duvivier M-c",
    "wof:placetype":"venue"
},
  "geometry": {"coordinates":[4.3805718422,50.4605064392],"type":"Point"}
}