{
  "type": "Feature",
  "properties": {
    "iso:country":"BE",
    "sg:address":"Verbindingslaan 47",
    "sg:city":"Leuven (heverlee)",
    "sg:classifiers":[
        {
            "category":"Health Services",
            "subcategory":"Doctor",
            "type":"Services"
        }
    ],
    "sg:phone":"+32 16 40 10 34",
    "sg:postcode":"3001",
    "sg:province":"Vlaams-Brabant",
    "sg:tags":[
        "medicinephysicians",
        "surgeon"
    ],
    "wof:name":"Lemmens J",
    "wof:placetype":"venue"
},
  "geometry": {"coordinates":[4.7020487785,50.8594512939],"type":"Point"}
}