{
  "type": "Feature",
  "properties": {
    "iso:country":"BE",
    "sg:address":"Peter Benoitlaan 34",
    "sg:city":"Beveren (beveren-waas)",
    "sg:classifiers":[
        {
            "category":"Personal",
            "subcategory":"Beauty Salon",
            "type":"Services"
        }
    ],
    "sg:phone":"+32 3 775 69 95",
    "sg:postcode":"9120",
    "sg:province":"Oost-Vlaanderen",
    "wof:name":"Matheussen V",
    "wof:placetype":"venue"
},
  "geometry": {"coordinates":[4.2351250648,51.2097206116],"type":"Point"}
}