{
  "type": "Feature",
  "properties": {
    "addr:full":"Rue Max Roos 34 Bruxelles (schaerbeek) Bruxelles-Capitale 1030",
    "addr:housenumber":"34",
    "addr:postcode":"1030",
    "addr:street":"Rue Max Roos",
    "iso:country":"BE",
    "sg:address":"Rue Max Roos 34",
    "sg:city":"Bruxelles (schaerbeek)",
    "sg:classifiers":[
        {
            "category":"Communications",
            "type":"Services"
        }
    ],
    "sg:phone":"+32 2 241 88 59",
    "sg:postcode":"1030",
    "sg:province":"Bruxelles-Capitale",
    "sg:tags":[
        "translator"
    ],
    "wof:name":"Vansina P",
    "wof:placetype":"venue"
},
  "geometry": {"coordinates":[4.3768768311,50.8756484985],"type":"Point"}
}