{
  "type": "Feature",
  "properties": {
    "iso:country":"BE",
    "sg:address":"Chauss\u00e9e De Charleroi 116",
    "sg:city":"Bruxelles (saint-gilles)",
    "sg:classifiers":[
        {
            "category":"Shopping",
            "subcategory":"Computers & Home Electronics",
            "type":"Retail Goods"
        }
    ],
    "sg:phone":"+32 2 536 21 11",
    "sg:postcode":"1060",
    "sg:province":"Bruxelles-Capitale",
    "sg:tags":[
        "personal",
        "-",
        "processing",
        "data"
    ],
    "wof:name":"Fujitsu Siemens Computers(g-720420-072) Nv",
    "wof:placetype":"venue"
},
  "geometry": {"coordinates":[4.3554530144,50.8278083801],"type":"Point"}
}