{
  "type": "Feature",
  "properties": {
    "addr:full":"Avenue Ernest Solvay 44 Tubize Brabant Wallon 1480",
    "addr:housenumber":"44",
    "addr:postcode":"1480",
    "addr:street":"Avenue Ernest Solvay;Wallon",
    "iso:country":"BE",
    "sg:address":"Avenue Ernest Solvay 44",
    "sg:city":"Tubize",
    "sg:orig_category":"Bedrijfscatering",
    "sg:phone":"+32 2 355 08 41",
    "sg:postcode":"1480",
    "sg:province":"Brabant Wallon",
    "wof:name":"Mr. Food",
    "wof:placetype":"venue"
},
  "geometry": {"coordinates":[4.204308033,50.6932029724],"type":"Point"}
}