{
  "type": "Feature",
  "properties": {
    "iso:country":"BE",
    "sg:address":"Maastrichterweg 149",
    "sg:city":"Lanaken",
    "sg:orig_category":"Meubelzaken, woning- and keukeninrichting",
    "sg:phone":"+32 89 71 19 30",
    "sg:postcode":"3620",
    "sg:province":"Limburg",
    "wof:name":"Top Living",
    "wof:placetype":"venue"
},
  "geometry": {"coordinates":[5.6584839821,50.8915367126],"type":"Point"}
}