{
  "type": "Feature",
  "properties": {
    "iso:country":"BE",
    "sg:address":"Route De Maffe 166",
    "sg:city":"Havelange",
    "sg:orig_category":"Meubles D\u00e9taillants, Am\u00e9nagement de B\u00e2timents et de Cuisines. Eclairage et \u00e9quipements du foyer",
    "sg:phone":"+32 83 63 31 57",
    "sg:postcode":"5372",
    "sg:province":"Namur",
    "wof:name":"Ets. Charlier",
    "wof:placetype":"venue"
},
  "geometry": {"coordinates":[5.3459229469,50.3537750244],"type":"Point"}
}