{
  "type": "Feature",
  "properties": {
    "addr:full":"Rue De Bouvy 86 La Louviere Hainaut 7100",
    "addr:housenumber":"86",
    "addr:postcode":"7100",
    "addr:street":"Rue De Bouvy",
    "iso:country":"BE",
    "sg:address":"Rue De Bouvy 86",
    "sg:city":"La Louviere",
    "sg:orig_category":"RESTAURANTS: FAST FOOD AND \u00c0 EMPORTER. RESTAURANTS. SALLES DE CONF\u00c9RENCES AND DE R\u00c9CEPTIONS",
    "sg:phone":"+32 64 22 87 87",
    "sg:postcode":"7100",
    "sg:province":"Hainaut",
    "wof:name":"L'auberge De La Louve",
    "wof:placetype":"venue"
},
  "geometry": {"coordinates":[4.1835222244,50.4721679688],"type":"Point"}
}