{
  "type": "Feature",
  "properties": {
    "addr:full":"Rue Adolphe-damseaux 37 Gembloux Namur 5030",
    "addr:housenumber":"37",
    "addr:postcode":"5030",
    "addr:street":"Rue Adolphe-Damseaux;Namur",
    "iso:country":"BE",
    "sg:address":"Rue Adolphe-damseaux 37",
    "sg:city":"Gembloux",
    "sg:orig_category":"Architectes. Evaluation and estimation de biens immobiliers",
    "sg:phone":"+32 81 61 20 59",
    "sg:postcode":"5030",
    "sg:province":"Namur",
    "wof:name":"Jacques Willam",
    "wof:placetype":"venue"
},
  "geometry": {"coordinates":[4.6891951561,50.5622253418],"type":"Point"}
}