{
  "type": "Feature",
  "properties": {
    "addr:full":"Rue Charles Magnette 12d Li\u00e8ge 1 Li\u00e8ge 4000",
    "addr:housenumber":"12d;1",
    "addr:postcode":"4000",
    "addr:street":"Rue Charles Magnette",
    "iso:country":"BE",
    "sg:address":"Rue Charles Magnette 12d",
    "sg:city":"Li\u00e8ge 1",
    "sg:classifiers":[
        {
            "category":"Personal",
            "subcategory":"Beauty Salon",
            "type":"Services"
        }
    ],
    "sg:phone":"+32 4 223 57 20",
    "sg:postcode":"4000",
    "sg:province":"Li\u00e8ge",
    "sg:tags":[
        "slimming"
    ],
    "wof:name":"Espace Beaute",
    "wof:placetype":"venue"
},
  "geometry": {"coordinates":[5.5730280876,50.6409187317],"type":"Point"}
}