{
  "type": "Feature",
  "properties": {
    "iso:country":"BE",
    "sg:address":"Langenakkerstraat 77",
    "sg:city":"Wellen",
    "sg:classifiers":[
        {
            "category":"Shopping",
            "subcategory":"Bicycles & Sporting Goods",
            "type":"Retail Goods"
        }
    ],
    "sg:phone":"+32 11 37 73 27",
    "sg:postcode":"3830",
    "sg:province":"Limburg",
    "sg:tags":[
        "tyre"
    ],
    "wof:name":"Bex",
    "wof:placetype":"venue"
},
  "geometry": {"coordinates":[5.3549218178,50.8566551208],"type":"Point"}
}