{
  "type": "Feature",
  "properties": {
    "iso:country":"BE",
    "sg:address":"Groeneweg 1",
    "sg:city":"Wichelen",
    "sg:orig_category":"Fietsen",
    "sg:phone":"+32 9 369 09 58",
    "sg:postcode":"9260",
    "sg:province":"Oost-Vlaanderen",
    "wof:name":"D. & S. Bikes",
    "wof:placetype":"venue"
},
  "geometry": {"coordinates":[3.9256799221,50.9851455688],"type":"Point"}
}