{
  "type": "Feature",
  "properties": {
    "iso:country":"BE",
    "sg:address":"Rue De La Baume 297",
    "sg:city":"Seraing",
    "sg:orig_category":"Bloemen and planten Fleurop Interflora",
    "sg:phone":"+32 4 337 20 33",
    "sg:postcode":"4100",
    "sg:province":"Li\u00e8ge",
    "wof:name":"Fleurs Dewar",
    "wof:placetype":"venue"
},
  "geometry": {"coordinates":[5.5110249519,50.5992584229],"type":"Point"}
}