{
  "type": "Feature",
  "properties": {
    "addr:full":"Bouwelse Steenweg 62 Herenthout Antwerpen 2270",
    "addr:housenumber":"62",
    "addr:postcode":"2270",
    "addr:street":"Bouwelse Steenweg",
    "iso:country":"BE",
    "sg:address":"Bouwelse Steenweg 62",
    "sg:city":"Herenthout",
    "sg:orig_category":"Non-Classified Establishments",
    "sg:phone":"+32 14 51 71 91",
    "sg:postcode":"2270",
    "sg:province":"Antwerpen",
    "wof:name":"Bittoun Textielagentschap Bvba",
    "wof:placetype":"venue"
},
  "geometry": {"coordinates":[4.7541880608,51.1434745789],"type":"Point"}
}