{
  "type": "Feature",
  "properties": {
    "addr:full":"Rue De Dinant 16 Gedinne Namur 5575",
    "addr:housenumber":"16",
    "addr:postcode":"5575",
    "addr:street":"Rue De Dinant",
    "iso:country":"BE",
    "sg:address":"Rue De Dinant 16",
    "sg:city":"Gedinne",
    "sg:classifiers":[
        {
            "category":"Fast Food",
            "type":"Food & Drink"
        }
    ],
    "sg:phone":"+32 61 58 87 29",
    "sg:postcode":"5575",
    "sg:province":"Namur",
    "sg:tags":[
        "\u00c0",
        "restaurants",
        "emporter",
        "restaurant"
    ],
    "wof:name":"Chez Zorba",
    "wof:placetype":"venue"
},
  "geometry": {"coordinates":[4.9366869926,49.9814414978],"type":"Point"}
}