{
  "type": "Feature",
  "properties": {
    "addr:full":"Rue Du Chabut 3 Beauvechain Brabant Wallon 1320",
    "addr:housenumber":"3",
    "addr:postcode":"1320",
    "addr:street":"Rue Du Chabut",
    "iso:country":"BE",
    "sg:address":"Rue Du Chabut 3",
    "sg:city":"Beauvechain",
    "sg:orig_category":"Speciaalzaken",
    "sg:phone":"+32 10 86 01 88",
    "sg:postcode":"1320",
    "sg:province":"Brabant Wallon",
    "wof:name":"Fr\u00c9d\u00c9ric Angely",
    "wof:placetype":"venue"
},
  "geometry": {"coordinates":[4.7210450172,50.7739524841],"type":"Point"}
}