{
  "type": "Feature",
  "properties": {
    "addr:full":"Geerwijnstraat 13 Brugge West-Vlaanderen 8000",
    "addr:housenumber":"13",
    "addr:postcode":"8000",
    "addr:street":"Geerwijnstraat",
    "iso:country":"BE",
    "sg:address":"Geerwijnstraat 13",
    "sg:city":"Brugge",
    "sg:orig_category":"Notarissen",
    "sg:phone":"+32 50 33 37 42",
    "sg:postcode":"8000",
    "sg:province":"West-Vlaanderen",
    "wof:name":"E. Baudry",
    "wof:placetype":"venue"
},
  "geometry": {"coordinates":[3.2203519344,51.2094116211],"type":"Point"}
}