{
  "type": "Feature",
  "properties": {
    "addr:full":"Mussenbaan 26 Zandhoven Antwerpen 2240",
    "addr:housenumber":"26",
    "addr:postcode":"2240",
    "addr:street":"Mussenbaan",
    "iso:country":"BE",
    "sg:address":"Mussenbaan 26",
    "sg:city":"Zandhoven",
    "sg:orig_category":"Eleveurs de bovins",
    "sg:phone":"+32 3 484 40 90",
    "sg:postcode":"2240",
    "sg:province":"Antwerpen",
    "wof:name":"Jozef Van Beirendonck",
    "wof:placetype":"venue"
},
  "geometry": {"coordinates":[4.6486568451,51.2196807861],"type":"Point"}
}