{
  "type": "Feature",
  "properties": {
    "addr:full":"Rue De L'industrie 52 Brussel/bruxelles Bruxelles-Capitale 1040",
    "addr:housenumber":"52",
    "addr:postcode":"1040",
    "addr:street":"Rue De L'Industrie;/",
    "iso:country":"BE",
    "sg:address":"Rue De L'industrie 52",
    "sg:city":"Brussel/bruxelles",
    "sg:orig_category":"Assurances habitation compagnies. Pr\u00eats hypoth\u00e9caires and cr\u00e9dits immobiliers. Assurances vie compag",
    "sg:phone":"+32 2 288 91 11",
    "sg:postcode":"1040",
    "sg:province":"Bruxelles-Capitale",
    "wof:name":"Fina Life",
    "wof:placetype":"venue"
},
  "geometry": {"coordinates":[4.3709812164,50.8449134827],"type":"Point"}
}