{
  "type": "Feature",
  "properties": {
    "addr:full":"Hoogstadestraat 48 Alveringem West-Vlaanderen 8690",
    "addr:housenumber":"48",
    "addr:postcode":"8690",
    "addr:street":"Hoogstadestraat",
    "iso:country":"BE",
    "sg:address":"Hoogstadestraat 48",
    "sg:city":"Alveringem",
    "sg:orig_category":"Banques and organismes de cr\u00e9dit",
    "sg:phone":"+32 58 28 82 42",
    "sg:postcode":"8690",
    "sg:province":"West-Vlaanderen",
    "wof:name":"De Vaderlandsche",
    "wof:placetype":"venue"
},
  "geometry": {"coordinates":[2.6850340366,51.0017242432],"type":"Point"}
}