{
  "type": "Feature",
  "properties": {
    "addr:full":"Stationsstraat 24 Brugge West-Vlaanderen 8380",
    "addr:housenumber":"24",
    "addr:postcode":"8380",
    "addr:street":"Stationsstraat",
    "iso:country":"BE",
    "sg:address":"Stationsstraat 24",
    "sg:city":"Brugge",
    "sg:orig_category":"Fruits and l\u00e9gumes. Epiceries",
    "sg:phone":"+32 50 54 66 30",
    "sg:postcode":"8380",
    "sg:province":"West-Vlaanderen",
    "wof:name":"Eddy Bruynooghe",
    "wof:placetype":"venue"
},
  "geometry": {"coordinates":[3.2111020088,51.2020645142],"type":"Point"}
}