{
  "type": "Feature",
  "properties": {
    "addr:full":"Koninklijkebaan 5 De Haan West-Vlaanderen 8420",
    "addr:housenumber":"5",
    "addr:postcode":"8420",
    "addr:street":"Koninklijkebaan",
    "iso:country":"BE",
    "sg:address":"Koninklijkebaan 5",
    "sg:city":"De Haan",
    "sg:orig_category":"Enseignement maternel and primaire",
    "sg:phone":"+32 59 23 56 38",
    "sg:postcode":"8420",
    "sg:province":"West-Vlaanderen",
    "wof:name":"Bubao La Ruche",
    "wof:placetype":"venue"
},
  "geometry": {"coordinates":[3.0263900757,51.2758903503],"type":"Point"}
}