{
  "type": "Feature",
  "properties": {
    "addr:full":"Molenstraat 16 Diksmuide West-Vlaanderen 8600",
    "addr:housenumber":"16",
    "addr:postcode":"8600",
    "addr:street":"Molenstraat",
    "iso:country":"BE",
    "sg:address":"Molenstraat 16",
    "sg:city":"Diksmuide",
    "sg:orig_category":"Eleveurs and marchands de porcs. Eleveurs de bovins",
    "sg:phone":"+32 51 55 56 74",
    "sg:postcode":"8600",
    "sg:province":"West-Vlaanderen",
    "wof:name":"Geert Casselman",
    "wof:placetype":"venue"
},
  "geometry": {"coordinates":[2.7816200256,51.0711212158],"type":"Point"}
}