{
  "type": "Feature",
  "properties": {
    "addr:full":"Rue De L'enseignement 15 Sprimont Li\u00e8ge 4140",
    "addr:housenumber":"15",
    "addr:postcode":"4140",
    "addr:street":"Rue De L'Enseignement",
    "iso:country":"BE",
    "sg:address":"Rue De L'enseignement 15",
    "sg:city":"Sprimont",
    "sg:orig_category":"Activit\u00e9s r\u00e9cr\u00e9atives diverses",
    "sg:phone":"+32 4 382 14 55",
    "sg:postcode":"4140",
    "sg:province":"Li\u00e8ge",
    "wof:name":"Faucheurs De Marguerites",
    "wof:placetype":"venue"
},
  "geometry": {"coordinates":[5.6320528984,50.5140304565],"type":"Point"}
}