{
  "type": "Feature",
  "properties": {
    "iso:country":"BE",
    "sg:address":"Prekelindenlaan 153",
    "sg:city":"Sint-lambrechts-woluwe/woluwe-saint-lambert",
    "sg:orig_category":"Artiesten and kunstenaars",
    "sg:phone":"+32 2 733 85 80",
    "sg:postcode":"1200",
    "sg:province":"Bruxelles-Capitale",
    "wof:name":"Atelier Z\u00dcrni",
    "wof:placetype":"venue"
},
  "geometry": {"coordinates":[4.4074392319,50.8446998596],"type":"Point"}
}