{
  "type": "Feature",
  "properties": {
    "iso:country":"BE",
    "sg:address":"Tulpenlaan 5",
    "sg:city":"Tienen",
    "sg:orig_category":"Woningbouw",
    "sg:phone":"+32 16 81 64 18",
    "sg:postcode":"3300",
    "sg:province":"Vlaams-Brabant",
    "wof:name":"Paul Hendrickx",
    "wof:placetype":"venue"
},
  "geometry": {"coordinates":[4.9496059418,50.8184089661],"type":"Point"}
}