{
  "type": "Feature",
  "properties": {
    "iso:country":"BE",
    "sg:address":"Euphrosina Beernaertstr. 116",
    "sg:city":"Oostende",
    "sg:orig_category":"Avocats and conseillers juridiques",
    "sg:phone":"+32 59 70 30 99",
    "sg:postcode":"8400",
    "sg:province":"West-Vlaanderen",
    "wof:name":"A. Porta",
    "wof:placetype":"venue"
},
  "geometry": {"coordinates":[2.9111340046,51.2266845703],"type":"Point"}
}