{
  "type": "Feature",
  "properties": {
    "addr:full":"Oudenaardsesteenweg 42 Gent Oost-Vlaanderen 9000",
    "addr:housenumber":"42",
    "addr:postcode":"9000",
    "addr:street":"Oudenaardsesteenweg;Oost-Vlaanderen",
    "iso:country":"BE",
    "sg:address":"Oudenaardsesteenweg 42",
    "sg:city":"Gent",
    "sg:classifiers":[
        {
            "category":"Professional",
            "subcategory":"Engineering",
            "type":"Services"
        }
    ],
    "sg:phone":"+32 9 222 74 45",
    "sg:postcode":"9000",
    "sg:province":"Oost-Vlaanderen",
    "sg:tags":[
        "civil",
        "offices-"
    ],
    "wof:name":"Riessauw",
    "wof:placetype":"venue"
},
  "geometry": {"coordinates":[3.7090990543,51.0236816406],"type":"Point"}
}