{
  "type": "Feature",
  "properties": {
    "addr:full":"Ravesteinstraat 58 Boortmeerbeek (hever) Vlaams-Brabant 3191",
    "addr:housenumber":"58",
    "addr:postcode":"3191",
    "addr:street":"Ravesteinstraat",
    "iso:country":"BE",
    "sg:address":"Ravesteinstraat 58",
    "sg:city":"Boortmeerbeek (hever)",
    "sg:classifiers":[
        {
            "category":"Health Services",
            "subcategory":"Medical Lab",
            "type":"Services"
        }
    ],
    "sg:phone":"+32 15 52 03 18",
    "sg:postcode":"3191",
    "sg:province":"Vlaams-Brabant",
    "sg:tags":[
        "laboratory",
        "dental"
    ],
    "wof:name":"Van Craen Dentaaltechniek",
    "wof:placetype":"venue"
},
  "geometry": {"coordinates":[4.5509138107,50.997959137],"type":"Point"}
}