{
  "type": "Feature",
  "properties": {
    "addr:full":"Place Puissant 10 Comblain-au-pont (poulseur) Li\u00e8ge 4171",
    "addr:housenumber":"10",
    "addr:postcode":"4171",
    "addr:street":"Place Puissant",
    "iso:country":"BE",
    "sg:address":"Place Puissant 10",
    "sg:city":"Comblain-au-pont (poulseur)",
    "sg:classifiers":[
        {
            "category":"Bars & Pubs",
            "type":"Food & Drink"
        }
    ],
    "sg:phone":"+32 4 380 42 87",
    "sg:postcode":"4171",
    "sg:province":"Li\u00e8ge",
    "wof:name":"Poul's (le)",
    "wof:placetype":"venue"
},
  "geometry": {"coordinates":[5.5787978172,50.5088386536],"type":"Point"}
}