{
  "type": "Feature",
  "properties": {
    "addr:full":"Rue De La Station 6 Genappe Brabant Wallon 1470",
    "addr:housenumber":"6",
    "addr:postcode":"1470",
    "addr:street":"Rue De La Station;Wallon",
    "iso:country":"BE",
    "sg:address":"Rue De La Station 6",
    "sg:city":"Genappe",
    "sg:classifiers":[
        {
            "category":"Restaurant",
            "type":"Food & Drink"
        }
    ],
    "sg:phone":"+32 67 78 03 36",
    "sg:postcode":"1470",
    "sg:province":"Brabant Wallon",
    "wof:name":"Chez Mamy",
    "wof:placetype":"venue"
},
  "geometry": {"coordinates":[4.4499349594,50.6084976196],"type":"Point"}
}