{
  "type": "Feature",
  "properties": {
    "iso:country":"BE",
    "sg:address":"Avenue Des Vallons 2",
    "sg:city":"Waterloo",
    "sg:classifiers":[
        {
            "category":"Autos & Motor Vehicles",
            "subcategory":"Fuel & Gas Station",
            "type":"Retail Goods"
        }
    ],
    "sg:phone":"+32 2 354 84 57",
    "sg:postcode":"1410",
    "sg:province":"Brabant Wallon",
    "sg:tags":[
        "stations-service",
        "carburants"
    ],
    "wof:name":"Willy Langlet",
    "wof:placetype":"venue"
},
  "geometry": {"coordinates":[4.4043269157,50.6981468201],"type":"Point"}
}