{
  "type": "Feature",
  "properties": {
    "addr:full":"Koolmijnlaan 114 Heusden-zolder (heusden) Limburg 3550",
    "addr:housenumber":"114",
    "addr:postcode":"3550",
    "addr:street":"Koolmijnlaan",
    "iso:country":"BE",
    "sg:address":"Koolmijnlaan 114",
    "sg:city":"Heusden-zolder (heusden)",
    "sg:classifiers":[
        {
            "category":"Professional",
            "subcategory":"Computer Services",
            "type":"Services"
        }
    ],
    "sg:phone":"+32 11 81 12 85",
    "sg:postcode":"3550",
    "sg:province":"Limburg",
    "sg:tags":[
        "-",
        "processing",
        "data",
        "software"
    ],
    "wof:name":"Pc Palace",
    "wof:placetype":"venue"
},
  "geometry": {"coordinates":[5.3020920753,51.0398864746],"type":"Point"}
}