{
  "type": "Feature",
  "properties": {
    "addr:full":"Wittestraat 88 Antwerpen Antwerpen 2020",
    "addr:housenumber":"88",
    "addr:postcode":"2020",
    "addr:street":"Wittestraat",
    "iso:country":"BE",
    "sg:address":"Wittestraat 88",
    "sg:city":"Antwerpen",
    "sg:classifiers":[
        {
            "category":"Food & Beverages",
            "subcategory":"Supermarket",
            "type":"Retail Goods"
        }
    ],
    "sg:phone":"+32 3 288 53 94",
    "sg:postcode":"2020",
    "sg:province":"Antwerpen",
    "sg:tags":[
        "department",
        "store"
    ],
    "wof:name":"A & O 2000",
    "wof:placetype":"venue"
},
  "geometry": {"coordinates":[4.3846411705,51.1882781982],"type":"Point"}
}