{
  "type": "Feature",
  "properties": {
    "addr:full":"Tervuursestraat 4 Leuven Vlaams-Brabant 3000",
    "addr:housenumber":"4",
    "addr:postcode":"3000",
    "addr:street":"Tervuursestraat",
    "iso:country":"BE",
    "sg:address":"Tervuursestraat 4",
    "sg:city":"Leuven",
    "sg:orig_category":"Cr\u00e9dits divers",
    "sg:postcode":"3000",
    "sg:province":"Vlaams-Brabant",
    "wof:name":"Bancontact-mister Cash",
    "wof:placetype":"venue"
},
  "geometry": {"coordinates":[4.6889591217,50.8794593811],"type":"Point"}
}