{
  "type": "Feature",
  "properties": {
    "iso:country":"BE",
    "sg:address":"Vondelen 48",
    "sg:city":"Haaltert",
    "sg:orig_category":"Immobili\u00ebnkantoren",
    "sg:phone":"+32 53 83 17 66",
    "sg:postcode":"9450",
    "sg:province":"Oost-Vlaanderen",
    "wof:name":"Euriamcom",
    "wof:placetype":"venue"
},
  "geometry": {"coordinates":[4.0146050453,50.8857574463],"type":"Point"}
}