{
  "type": "Feature",
  "properties": {
    "iso:country":"BE",
    "sg:address":"Rue Hollebeek 449",
    "sg:city":"Linkebeek",
    "sg:classifiers":[
        {
            "category":"Real Estate",
            "subcategory":"Architect",
            "type":"Services"
        }
    ],
    "sg:phone":"+32 2 358 28 57",
    "sg:postcode":"1630",
    "sg:province":"Vlaams-Brabant",
    "wof:name":"Neve De Mevergnies V",
    "wof:placetype":"venue"
},
  "geometry": {"coordinates":[4.3606801033,50.7633781433],"type":"Point"}
}