{
  "type": "Feature",
  "properties": {
    "addr:full":"Rue Taravis\u00c9e 10 Dinant Namur 5503",
    "addr:housenumber":"10",
    "addr:postcode":"5503",
    "addr:street":"Rue Taravise\u0301E",
    "iso:country":"BE",
    "sg:address":"Rue Taravis\u00c9e 10",
    "sg:city":"Dinant",
    "sg:orig_category":"M\u00e9decins and sp\u00e9cialistes",
    "sg:phone":"+32 82 22 48 06",
    "sg:postcode":"5503",
    "sg:province":"Namur",
    "wof:name":"Jean-marie Despas",
    "wof:placetype":"venue"
},
  "geometry": {"coordinates":[4.952393055,50.2550506592],"type":"Point"}
}