{
  "type": "Feature",
  "properties": {
    "addr:full":"Route De Luxembourg 111 Arlon Luxembourg 6706",
    "addr:housenumber":"111",
    "addr:postcode":"6706",
    "addr:street":"Route De Luxembourg",
    "iso:country":"BE",
    "sg:address":"Route De Luxembourg 111",
    "sg:city":"Arlon",
    "sg:classifiers":[
        {
            "category":"Shopping",
            "subcategory":"Clothing, Apparel, & Fashions",
            "type":"Retail Goods"
        }
    ],
    "sg:phone":"+32 63 22 70 71",
    "sg:postcode":"6706",
    "sg:province":"Luxembourg",
    "sg:tags":[
        "v\u00eatements",
        "pour",
        "dame"
    ],
    "wof:name":"Elise Noel",
    "wof:placetype":"venue"
},
  "geometry": {"coordinates":[5.8697757721,49.6491928101],"type":"Point"}
}