{
  "type": "Feature",
  "properties": {
    "iso:country":"BE",
    "sg:address":"Grand Place 5",
    "sg:city":"Aubange (halanzy)",
    "sg:classifiers":[
        {
            "category":"Banks & Credit Unions",
            "subcategory":"Financial Services",
            "type":"Services"
        }
    ],
    "sg:phone":"+32 63 67 50 50",
    "sg:postcode":"6792",
    "sg:province":"Luxembourg",
    "sg:tags":[
        "financing"
    ],
    "wof:name":"Reding Sprl",
    "wof:placetype":"venue"
},
  "geometry": {"coordinates":[5.7421941757,49.5597839355],"type":"Point"}
}