{
  "type": "Feature",
  "properties": {
    "addr:full":"Boulevard De La Sauveni\u00c8re 119 Li\u00c8ge Li\u00e8ge 4000",
    "addr:housenumber":"119",
    "addr:postcode":"4000",
    "addr:street":"Boulevard De La Sauvenie\u0300Re",
    "iso:country":"BE",
    "sg:address":"Boulevard De La Sauveni\u00c8re 119",
    "sg:city":"Li\u00c8ge",
    "sg:orig_category":"Banken and kredietinstellingen",
    "sg:phone":"+32 4 222 47 47",
    "sg:postcode":"4000",
    "sg:province":"Li\u00e8ge",
    "wof:name":"Centea",
    "wof:placetype":"venue"
},
  "geometry": {"coordinates":[5.5673131943,50.6416397095],"type":"Point"}
}