{
  "type": "Feature",
  "properties": {
    "iso:country":"BE",
    "sg:address":"Rue Des Fagnes 17",
    "sg:city":"Flemalle",
    "sg:classifiers":[
        {
            "category":"Restaurant",
            "type":"Food & Drink"
        }
    ],
    "sg:phone":"+32 4 275 70 63",
    "sg:postcode":"4400",
    "sg:province":"Li\u00e8ge",
    "wof:name":"La Fourchette Des Fagnes",
    "wof:placetype":"venue"
},
  "geometry": {"coordinates":[5.4576430321,50.5693130493],"type":"Point"}
}