{
  "type": "Feature",
  "properties": {
    "addr:full":"Korenbloemenlaan 11 Sint-genesius-rode/rhode-saint-genese Vlaams-Brabant 1640",
    "addr:housenumber":"11",
    "addr:postcode":"1640",
    "addr:street":"Korenbloemenlaan",
    "iso:country":"BE",
    "sg:address":"Korenbloemenlaan 11",
    "sg:city":"Sint-genesius-rode/rhode-saint-genese",
    "sg:orig_category":"Immobili\u00ebnkantoren",
    "sg:phone":"+32 2 358 38 10",
    "sg:postcode":"1640",
    "sg:province":"Vlaams-Brabant",
    "wof:name":"Carimmo Real- Estate",
    "wof:placetype":"venue"
},
  "geometry": {"coordinates":[4.3857288361,50.7364501953],"type":"Point"}
}