{
  "type": "Feature",
  "properties": {
    "addr:full":"Rue De La Gare 21 Gouvy (limerl\u00e9) Luxembourg 6670",
    "addr:housenumber":"21",
    "addr:postcode":"6670",
    "addr:street":"Rue De La Gare",
    "iso:country":"BE",
    "sg:address":"Rue De La Gare 21",
    "sg:city":"Gouvy (limerl\u00e9)",
    "sg:classifiers":[
        {
            "category":"Wholesale",
            "subcategory":"Wine & Distilled Alcoholic Beverages",
            "type":"Manufacturing & Wholesale Goods"
        }
    ],
    "sg:phone":"+32 80 51 70 57",
    "sg:postcode":"6670",
    "sg:province":"Luxembourg",
    "sg:tags":[
        "whol",
        "-",
        "spirit",
        "mfg"
    ],
    "wof:name":"Babelvin",
    "wof:placetype":"venue"
},
  "geometry": {"coordinates":[5.9545922279,50.189781189],"type":"Point"}
}