{
  "type": "Feature",
  "properties": {
    "addr:full":"Van Arteveldestraat 65-67 Antwerpen Antwerpen 2060",
    "addr:postcode":"65-67;2060",
    "addr:street":"Van Arteveldestraat",
    "iso:country":"BE",
    "sg:address":"Van Arteveldestraat 65-67",
    "sg:city":"Antwerpen",
    "sg:classifiers":[
        {
            "category":"Restaurant",
            "type":"Food & Drink"
        }
    ],
    "sg:phone":"+32 3 225 06 54",
    "sg:postcode":"2060",
    "sg:province":"Antwerpen",
    "wof:name":"Full Sing",
    "wof:placetype":"venue"
},
  "geometry": {"coordinates":[4.4196610451,51.2209320068],"type":"Point"}
}