{
  "type": "Feature",
  "properties": {
    "iso:country":"BE",
    "sg:address":"Rue De Montigny 46",
    "sg:city":"Charleroi",
    "sg:orig_category":"Notarissen",
    "sg:phone":"+32 71 32 66 81",
    "sg:postcode":"6000",
    "sg:province":"Hainaut",
    "wof:name":"Jean-paul Gregoire",
    "wof:placetype":"venue"
},
  "geometry": {"coordinates":[4.445608139,50.4082603455],"type":"Point"}
}