{
  "type": "Feature",
  "properties": {
    "iso:country":"BE",
    "sg:address":"Hugo Verrieststraat 118",
    "sg:city":"Roeselare",
    "sg:classifiers":[
        {
            "category":"Manufacturing",
            "subcategory":"Lumber",
            "type":"Manufacturing & Wholesale Goods"
        }
    ],
    "sg:phone":"+32 51 20 00 39",
    "sg:postcode":"8800",
    "sg:province":"West-Vlaanderen",
    "sg:tags":[
        "timber"
    ],
    "wof:name":"Delbeke-carbonez Nv",
    "wof:placetype":"venue"
},
  "geometry": {"coordinates":[3.1217589378,50.952091217],"type":"Point"}
}