{
  "type": "Feature",
  "properties": {
    "addr:full":"Ketelstraat 39a Geetbets (rummen) Vlaams-Brabant 3454",
    "addr:housenumber":"39a",
    "addr:postcode":"3454",
    "addr:street":"Ketelstraat",
    "iso:country":"BE",
    "sg:address":"Ketelstraat 39a",
    "sg:city":"Geetbets (rummen)",
    "sg:classifiers":[
        {
            "category":"Health Services",
            "subcategory":"Dentist",
            "type":"Services"
        }
    ],
    "sg:phone":"+32 11 58 94 76",
    "sg:postcode":"3454",
    "sg:province":"Vlaams-Brabant",
    "wof:name":"Baekelandt P",
    "wof:placetype":"venue"
},
  "geometry": {"coordinates":[5.162168026,50.8917961121],"type":"Point"}
}