{
  "type": "Feature",
  "properties": {
    "addr:full":"Rue De La Vaussale 9 Li\u00e8ge 1 (angleur) Li\u00e8ge 4031",
    "addr:housenumber":"9;1",
    "addr:postcode":"4031",
    "addr:street":"Rue De La Vaussale",
    "iso:country":"BE",
    "sg:address":"Rue De La Vaussale 9",
    "sg:city":"Li\u00e8ge 1 (angleur)",
    "sg:classifiers":[
        {
            "category":"Shopping",
            "subcategory":"Books",
            "type":"Retail Goods"
        }
    ],
    "sg:phone":"+32 4 365 78 25",
    "sg:postcode":"4031",
    "sg:province":"Li\u00e8ge",
    "sg:tags":[
        "bookseller"
    ],
    "wof:name":"Librairie Du Centre",
    "wof:placetype":"venue"
},
  "geometry": {"coordinates":[5.6008439064,50.6120071411],"type":"Point"}
}