{
  "type": "Feature",
  "properties": {
    "iso:country":"BE",
    "sg:address":"Ohioplein 200",
    "sg:city":"Oudenaarde",
    "sg:classifiers":[
        {
            "category":"Retail",
            "subcategory":"Veterinary Services",
            "type":"Services"
        }
    ],
    "sg:phone":"+32 55 30 41 81",
    "sg:postcode":"9700",
    "sg:province":"Oost-Vlaanderen",
    "sg:tags":[
        "veterinarian"
    ],
    "wof:name":"De Clercq L",
    "wof:placetype":"venue"
},
  "geometry": {"coordinates":[3.6242599487,50.8708190918],"type":"Point"}
}