{
  "type": "Feature",
  "properties": {
    "addr:full":"Rue Nouvelle 4 Ham-sur-heure-nalinnes Hainaut 6120",
    "addr:housenumber":"4",
    "addr:postcode":"6120",
    "addr:street":"Rue Nouvelle;Hainaut",
    "iso:country":"BE",
    "sg:address":"Rue Nouvelle 4",
    "sg:city":"Ham-sur-heure-nalinnes",
    "sg:orig_category":"Vakantiehuizen",
    "sg:phone":"+32 71 21 80 12",
    "sg:postcode":"6120",
    "sg:province":"Hainaut",
    "wof:name":"La Charmille",
    "wof:placetype":"venue"
},
  "geometry": {"coordinates":[4.4332180023,50.3479385376],"type":"Point"}
}