{
  "type": "Feature",
  "properties": {
    "iso:country":"BE",
    "sg:address":"Meensesteenweg 260",
    "sg:city":"Kortrijk (bissegem)",
    "sg:classifiers":[
        {
            "category":"Home & Garden",
            "subcategory":"Hardware",
            "type":"Retail Goods"
        }
    ],
    "sg:phone":"+32 56 35 29 32",
    "sg:postcode":"8501",
    "sg:province":"West-Vlaanderen",
    "sg:tags":[
        "builders'",
        "-",
        "furniture"
    ],
    "wof:name":"Aludoor",
    "wof:placetype":"venue"
},
  "geometry": {"coordinates":[3.2310740948,50.8246688843],"type":"Point"}
}