{
  "type": "Feature",
  "properties": {
    "addr:full":"Jan Van Boendalestraat 5 Roeselare West-Vlaanderen 8800",
    "addr:housenumber":"5",
    "addr:postcode":"8800",
    "addr:street":"Jan Van Boendalestraat",
    "iso:country":"BE",
    "sg:address":"Jan Van Boendalestraat 5",
    "sg:city":"Roeselare",
    "sg:classifiers":[
        {
            "category":"Health Services",
            "subcategory":"Health Practitioner",
            "type":"Services"
        }
    ],
    "sg:phone":"+32 51 21 17 40",
    "sg:postcode":"8800",
    "sg:province":"West-Vlaanderen",
    "sg:tags":[
        "physiotherapist"
    ],
    "wof:name":"Speliers Fernand",
    "wof:placetype":"venue"
},
  "geometry": {"coordinates":[3.129062891,50.9636459351],"type":"Point"}
}