{
  "type": "Feature",
  "properties": {
    "iso:country":"BE",
    "sg:address":"Avenue Du Gris Moulin 67",
    "sg:city":"La Hulpe",
    "sg:orig_category":"Artsen and specialisten",
    "sg:phone":"+32 2 653 14 65",
    "sg:postcode":"1310",
    "sg:province":"Brabant Wallon",
    "wof:name":"Philippe Lebecq",
    "wof:placetype":"venue"
},
  "geometry": {"coordinates":[4.4739151001,50.7355690002],"type":"Point"}
}