{
  "type": "Feature",
  "properties": {
    "iso:country":"BE",
    "sg:address":"Wingensesteenweg 128a",
    "sg:city":"Tielt",
    "sg:classifiers":[
        {
            "category":"Professional",
            "subcategory":"Management & Consulting",
            "type":"Services"
        }
    ],
    "sg:phone":"+32 51 65 67 82",
    "sg:postcode":"8700",
    "sg:province":"West-Vlaanderen",
    "sg:tags":[
        "tax-consultants"
    ],
    "wof:name":"Tack K",
    "wof:placetype":"venue"
},
  "geometry": {"coordinates":[3.3039851189,51.0297813416],"type":"Point"}
}