{
  "type": "Feature",
  "properties": {
    "addr:full":"Spurkerweg 34 Bilzen Limburg 3740",
    "addr:housenumber":"34",
    "addr:postcode":"3740",
    "addr:street":"Spurkerweg",
    "iso:country":"BE",
    "sg:address":"Spurkerweg 34",
    "sg:city":"Bilzen",
    "sg:classifiers":[
        {
            "category":"Professional",
            "subcategory":"Lawyer & Legal Services",
            "type":"Services"
        }
    ],
    "sg:phone":"+32 89 49 13 97",
    "sg:postcode":"3740",
    "sg:province":"Limburg",
    "wof:name":"Bollen Greet",
    "wof:placetype":"venue"
},
  "geometry": {"coordinates":[5.5111379623,50.8772201538],"type":"Point"}
}