{
  "type": "Feature",
  "properties": {
    "addr:full":"Chauss\u00e9e De Dinant 1178 Namur (w\u00e9pion) Namur 5100",
    "addr:postcode":"1178;5100",
    "addr:street":"Chausse\u0301E De Dinant",
    "iso:country":"BE",
    "sg:address":"Chauss\u00e9e De Dinant 1178",
    "sg:city":"Namur (w\u00e9pion)",
    "sg:classifiers":[
        {
            "category":"Home & Garden",
            "subcategory":"Garden Supply",
            "type":"Retail Goods"
        }
    ],
    "sg:phone":"+32 81 46 03 03",
    "sg:postcode":"5100",
    "sg:province":"Namur",
    "sg:tags":[
        "lawn",
        "mower"
    ],
    "wof:name":"Cassart Ets",
    "wof:placetype":"venue"
},
  "geometry": {"coordinates":[4.8803238869,50.412612915],"type":"Point"}
}