{
  "type": "Feature",
  "properties": {
    "addr:full":"Rue Harmois 32 La Louviere Hainaut 7100",
    "addr:housenumber":"32",
    "addr:postcode":"7100",
    "addr:street":"Rue Harmois",
    "iso:country":"BE",
    "sg:address":"Rue Harmois 32",
    "sg:city":"La Louviere",
    "sg:orig_category":"Graphologues, astrologues, voyants and radiesth\u00e9sistes",
    "sg:phone":"+32 64 84 90 17",
    "sg:postcode":"7100",
    "sg:province":"Hainaut",
    "wof:name":"Information Parascientifique",
    "wof:placetype":"venue"
},
  "geometry": {"coordinates":[4.1850848198,50.4748649597],"type":"Point"}
}