{
  "type": "Feature",
  "properties": {
    "addr:full":"Aarschotsestw 114 Wilsele Vlaams-Brabant 3012",
    "addr:housenumber":"114",
    "addr:postcode":"3012",
    "iso:country":"BE",
    "sg:address":"Aarschotsestw 114",
    "sg:city":"Wilsele",
    "sg:classifiers":[
        {
            "category":"Manufacturing",
            "subcategory":"Rubber & Plastics",
            "type":"Manufacturing & Wholesale Goods"
        }
    ],
    "sg:phone":"+32 16 30 13 01",
    "sg:postcode":"3012",
    "sg:province":"Vlaams-Brabant",
    "sg:tags":[
        "packaging",
        "material",
        "-"
    ],
    "wof:name":"Varia Pack",
    "wof:placetype":"venue"
},
  "geometry": {"coordinates":[4.7072558403,50.8978614807],"type":"Point"}
}