{
  "type": "Feature",
  "properties": {
    "iso:country":"BE",
    "sg:address":"Begeertenlaan 21",
    "sg:city":"Evere/evere",
    "sg:orig_category":"Drukkerijen and copyshops Secretariaatsdiensten",
    "sg:phone":"+32 2 705 45 45",
    "sg:postcode":"1140",
    "sg:province":"Bruxelles-Capitale",
    "wof:name":"A. Gillis",
    "wof:placetype":"venue"
},
  "geometry": {"coordinates":[4.4118800163,50.8595542908],"type":"Point"}
}