{
  "type": "Feature",
  "properties": {
    "iso:country":"BE",
    "sg:address":"Rue \u00c0 Dettes 142",
    "sg:city":"Anderlues",
    "sg:orig_category":"Landbouwmachines Gh",
    "sg:phone":"+32 71 54 57 00",
    "sg:postcode":"6150",
    "sg:province":"Hainaut",
    "wof:name":"Tison",
    "wof:placetype":"venue"
},
  "geometry": {"coordinates":[4.2667689323,50.3867607117],"type":"Point"}
}