{
  "type": "Feature",
  "properties": {
    "addr:full":"Kalmthoutse Steenweg 167 Wuustwezel Antwerpen 2990",
    "addr:housenumber":"167",
    "addr:postcode":"2990",
    "addr:street":"Kalmthoutse Steenweg",
    "iso:country":"BE",
    "sg:address":"Kalmthoutse Steenweg 167",
    "sg:city":"Wuustwezel",
    "sg:classifiers":[
        {
            "category":"Food & Beverages",
            "subcategory":"Groceries & Convenience Stores",
            "type":"Retail Goods"
        }
    ],
    "sg:phone":"+32 3 669 58 66",
    "sg:postcode":"2990",
    "sg:province":"Antwerpen",
    "sg:tags":[
        "grocer"
    ],
    "wof:name":"Winkeltje ('t)",
    "wof:placetype":"venue"
},
  "geometry": {"coordinates":[4.5222349167,51.3835868835],"type":"Point"}
}