{
  "type": "Feature",
  "properties": {
    "addr:full":"Rue De Flandre 66 Bruxelles Bruxelles-Capitale 1000",
    "addr:housenumber":"66",
    "addr:postcode":"1000",
    "addr:street":"Rue De Flandre",
    "iso:country":"BE",
    "sg:address":"Rue De Flandre 66",
    "sg:city":"Bruxelles",
    "sg:classifiers":[
        {
            "category":"Professional",
            "subcategory":"Advertising",
            "type":"Services"
        }
    ],
    "sg:phone":"+32 2 514 50 40",
    "sg:postcode":"1000",
    "sg:province":"Bruxelles-Capitale",
    "sg:tags":[
        "film"
    ],
    "wof:name":"Pix & Motion Filmproduction",
    "wof:placetype":"venue"
},
  "geometry": {"coordinates":[4.3461461067,50.8517341614],"type":"Point"}
}