{
  "type": "Feature",
  "properties": {
    "addr:full":"Zoerselhoek 23 Zoersel Antwerpen 2980",
    "addr:housenumber":"23",
    "addr:postcode":"2980",
    "addr:street":"Zoerselhoek",
    "iso:country":"BE",
    "sg:address":"Zoerselhoek 23",
    "sg:city":"Zoersel",
    "sg:orig_category":"Jardinage",
    "sg:phone":"+32 3 384 27 02",
    "sg:postcode":"2980",
    "sg:province":"Antwerpen",
    "wof:name":"Wuyts",
    "wof:placetype":"venue"
},
  "geometry": {"coordinates":[4.6547231674,51.2623405457],"type":"Point"}
}