{
  "type": "Feature",
  "properties": {
    "addr:full":"Diestsesteenweg 96 Lubbeek (linden) Vlaams-Brabant 3210",
    "addr:housenumber":"96",
    "addr:postcode":"3210",
    "addr:street":"Diestsesteenweg",
    "iso:country":"BE",
    "sg:address":"Diestsesteenweg 96",
    "sg:city":"Lubbeek (linden)",
    "sg:classifiers":[
        {
            "category":"Professional",
            "subcategory":"Advertising",
            "type":"Services"
        }
    ],
    "sg:phone":"+32 16 62 11 43",
    "sg:postcode":"3210",
    "sg:province":"Vlaams-Brabant",
    "sg:tags":[
        "clothes"
    ],
    "wof:name":"Imago-textiel Bvba",
    "wof:placetype":"venue"
},
  "geometry": {"coordinates":[4.8095397949,50.8933792114],"type":"Point"}
}