{
  "type": "Feature",
  "properties": {
    "addr:full":"Lindenallee 13 B\u00fctgenbach Li\u00e8ge 4750",
    "addr:housenumber":"13",
    "addr:postcode":"4750",
    "addr:street":"Lindenallee",
    "iso:country":"BE",
    "sg:address":"Lindenallee 13",
    "sg:city":"B\u00fctgenbach",
    "sg:classifiers":[
        {
            "category":"Education",
            "subcategory":"Dance Studio",
            "type":"Public Place"
        }
    ],
    "sg:phone":"+32 80 44 50 39",
    "sg:postcode":"4750",
    "sg:province":"Li\u00e8ge",
    "sg:tags":[
        "school",
        "dancing"
    ],
    "wof:name":"Hot Shoes Rock'n Roll Club",
    "wof:placetype":"venue"
},
  "geometry": {"coordinates":[6.202586174,50.4235954285],"type":"Point"}
}