{
  "type": "Feature",
  "properties": {
    "addr:full":"Ierlandstraat 3 Geel Antwerpen 2440",
    "addr:housenumber":"3",
    "addr:postcode":"2440",
    "addr:street":"Ierlandstraat",
    "iso:country":"BE",
    "sg:address":"Ierlandstraat 3",
    "sg:city":"Geel",
    "sg:classifiers":[
        {
            "category":"Professional",
            "subcategory":"Management & Consulting",
            "type":"Services"
        }
    ],
    "sg:phone":"+32 14 59 48 50",
    "sg:postcode":"2440",
    "sg:province":"Antwerpen",
    "sg:tags":[
        "consultant",
        "agency",
        "advertising"
    ],
    "wof:name":"Triceps",
    "wof:placetype":"venue"
},
  "geometry": {"coordinates":[5.0353550911,51.195186615],"type":"Point"}
}