{
  "type": "Feature",
  "properties": {
    "iso:country":"BE",
    "sg:address":"Chauss\u00c9e De Gilly 142",
    "sg:city":"Fleurus",
    "sg:orig_category":"Orphelinats. Instituts pour enfants en difficult\u00e9",
    "sg:phone":"+32 71 39 25 90",
    "sg:postcode":"6220",
    "sg:province":"Hainaut",
    "wof:name":"Auberge Du Mar\u00c9chal Ney",
    "wof:placetype":"venue"
},
  "geometry": {"coordinates":[4.5225601196,50.4503097534],"type":"Point"}
}