{
  "type": "Feature",
  "properties": {
    "iso:country":"BE",
    "sg:address":"Rue Emile Tumelaire 93",
    "sg:city":"Charleroi",
    "sg:orig_category":"Avocats and conseillers juridiques",
    "sg:phone":"+32 71 30 93 87",
    "sg:postcode":"6000",
    "sg:province":"Hainaut",
    "wof:name":"G. Scarna",
    "wof:placetype":"venue"
},
  "geometry": {"coordinates":[4.4516558647,50.4091072083],"type":"Point"}
}