{
  "type": "Feature",
  "properties": {
    "iso:country":"BE",
    "sg:address":"Zwarte Schuurstraat 2",
    "sg:city":"Mol",
    "sg:orig_category":"Producteurs de l\u00e9gumes",
    "sg:phone":"+32 14 81 00 38",
    "sg:postcode":"2400",
    "sg:province":"Antwerpen",
    "wof:name":"Francois Aerts",
    "wof:placetype":"venue"
},
  "geometry": {"coordinates":[5.2038898468,51.2080917358],"type":"Point"}
}