{
  "type": "Feature",
  "properties": {
    "addr:full":"Place De Bouvignies 35 Ath Hainaut 7803",
    "addr:housenumber":"35",
    "addr:postcode":"7803",
    "addr:street":"Place De Bouvignies",
    "iso:country":"BE",
    "sg:address":"Place De Bouvignies 35",
    "sg:city":"Ath",
    "sg:orig_category":"Enseignement maternel and primaire",
    "sg:phone":"+32 68 28 69 25",
    "sg:postcode":"7803",
    "sg:province":"Hainaut",
    "wof:name":"Ecole Fond. Communale",
    "wof:placetype":"venue"
},
  "geometry": {"coordinates":[3.7681910992,50.6463928223],"type":"Point"}
}