{
  "type": "Feature",
  "properties": {
    "iso:country":"BE",
    "sg:address":"Rue De La Tasni\u00c8re 3",
    "sg:city":"Perwez",
    "sg:orig_category":"Elektrische installaties voor woningen",
    "sg:phone":"+32 81 65 58 11",
    "sg:postcode":"1360",
    "sg:province":"Brabant Wallon",
    "wof:name":"Jean-pierre Flemal",
    "wof:placetype":"venue"
},
  "geometry": {"coordinates":[4.7643418312,50.6403961182],"type":"Point"}
}