{
  "type": "Feature",
  "properties": {
    "addr:full":"Vossenplein 2 Brussel Bruxelles-Capitale 1000",
    "addr:housenumber":"2",
    "addr:postcode":"1000",
    "addr:street":"Vossenplein",
    "iso:country":"BE",
    "sg:address":"Vossenplein 2",
    "sg:city":"Brussel",
    "sg:classifiers":[
        {
            "category":"Fast Food",
            "type":"Food & Drink"
        }
    ],
    "sg:phone":"+32 2 512 23 72",
    "sg:postcode":"1000",
    "sg:province":"Bruxelles-Capitale",
    "sg:tags":[
        "meeneem",
        "restaurant"
    ],
    "wof:name":"Homage \u00c0 Ma Fritte",
    "wof:placetype":"venue"
},
  "geometry": {"coordinates":[4.3467311859,50.8374671936],"type":"Point"}
}