{
  "type": "Feature",
  "properties": {
    "addr:full":"Rue Hawis 61 Soumagne Li\u00e8ge 4630",
    "addr:housenumber":"61",
    "addr:postcode":"4630",
    "addr:street":"Rue Hawis",
    "iso:country":"BE",
    "sg:address":"Rue Hawis 61",
    "sg:city":"Soumagne",
    "sg:orig_category":"Artsen and specialisten",
    "sg:phone":"+32 4 377 16 45",
    "sg:postcode":"4630",
    "sg:province":"Li\u00e8ge",
    "wof:name":"Paul Nemery",
    "wof:placetype":"venue"
},
  "geometry": {"coordinates":[5.73036623,50.6194953918],"type":"Point"}
}