{
  "type": "Feature",
  "properties": {
    "addr:full":"Lommelsebaan 7 Hechtel-eksel (hechtel) Limburg 3940",
    "addr:housenumber":"7",
    "addr:postcode":"3940",
    "addr:street":"Lommelsebaan",
    "iso:country":"BE",
    "sg:address":"Lommelsebaan 7",
    "sg:city":"Hechtel-eksel (hechtel)",
    "sg:classifiers":[
        {
            "category":"Retail",
            "subcategory":"Repair Shop",
            "type":"Services"
        }
    ],
    "sg:phone":"+32 11 60 33 80",
    "sg:postcode":"3940",
    "sg:province":"Limburg",
    "wof:name":"Veko",
    "wof:placetype":"venue"
},
  "geometry": {"coordinates":[5.364795208,51.1255340576],"type":"Point"}
}