{
  "type": "Feature",
  "properties": {
    "addr:full":"All\u00e9e Des P\u00e2querettes 9 Vis\u00e9 Li\u00e8ge 4600",
    "addr:housenumber":"9",
    "addr:postcode":"4600",
    "addr:street":"Alle\u0301E Des Pa\u0302Querettes",
    "iso:country":"BE",
    "sg:address":"All\u00e9e Des P\u00e2querettes 9",
    "sg:city":"Vis\u00e9",
    "sg:classifiers":[
        {
            "category":"Building & Trades",
            "subcategory":"Construction",
            "type":"Services"
        }
    ],
    "sg:phone":"+32 4 379 23 33",
    "sg:postcode":"4600",
    "sg:province":"Li\u00e8ge",
    "sg:tags":[
        "tool",
        "cutting"
    ],
    "wof:name":"Combidex Cutting Tools Sprl",
    "wof:placetype":"venue"
},
  "geometry": {"coordinates":[5.7055768967,50.7332878113],"type":"Point"}
}