{
  "type": "Feature",
  "properties": {
    "iso:country":"BE",
    "sg:address":"Kruisstraat 9",
    "sg:city":"Vleteren",
    "sg:orig_category":"Eleveurs and marchands de porcs",
    "sg:phone":"+32 57 40 08 07",
    "sg:postcode":"8640",
    "sg:province":"West-Vlaanderen",
    "wof:name":"Delcovar",
    "wof:placetype":"venue"
},
  "geometry": {"coordinates":[2.7000060081,50.9094161987],"type":"Point"}
}