{
  "type": "Feature",
  "properties": {
    "iso:country":"BE",
    "sg:address":"Prins Leopoldstraat 1",
    "sg:city":"Brugge (sint-kruis)",
    "sg:classifiers":[
        {
            "category":"Real Estate",
            "subcategory":"Architect",
            "type":"Services"
        }
    ],
    "sg:phone":"+32 50 37 32 39",
    "sg:postcode":"8310",
    "sg:province":"West-Vlaanderen",
    "wof:name":"Goes P",
    "wof:placetype":"venue"
},
  "geometry": {"coordinates":[3.2478199005,51.2133636475],"type":"Point"}
}