{
  "type": "Feature",
  "properties": {
    "iso:country":"BE",
    "sg:address":"Hoge Brugstraat 27",
    "sg:city":"Heist-op-den-berg",
    "sg:classifiers":[
        {
            "category":"Manufacturing",
            "subcategory":"Textiles",
            "type":"Manufacturing & Wholesale Goods"
        }
    ],
    "sg:phone":"+32 15 24 62 93",
    "sg:postcode":"2220",
    "sg:province":"Antwerpen",
    "sg:tags":[
        "machinery"
    ],
    "wof:name":"Textimat Bvba",
    "wof:placetype":"venue"
},
  "geometry": {"coordinates":[4.7156629562,51.0686454773],"type":"Point"}
}