{
  "type": "Feature",
  "properties": {
    "addr:full":"Avenue Winston Churchill 207 Ukkel/uccle Bruxelles-Capitale 1180",
    "addr:housenumber":"207",
    "addr:postcode":"1180",
    "addr:street":"Avenue Winston Churchill;/",
    "iso:country":"BE",
    "sg:address":"Avenue Winston Churchill 207",
    "sg:city":"Ukkel/uccle",
    "sg:orig_category":"Production de films, t\u00e9l\u00e9films and vid\u00e9os",
    "sg:phone":"+32 2 344 49 30",
    "sg:postcode":"1180",
    "sg:province":"Bruxelles-Capitale",
    "wof:name":"Aligator Film",
    "wof:placetype":"venue"
},
  "geometry": {"coordinates":[4.3649902344,50.8114433289],"type":"Point"}
}