{
  "type": "Feature",
  "properties": {
    "iso:country":"BE",
    "sg:address":"Rue De Wand 189",
    "sg:city":"Bruxelles",
    "sg:classifiers":[
        {
            "category":"Professional",
            "subcategory":"Management & Consulting",
            "type":"Services"
        }
    ],
    "sg:phone":"+32 2 262 00 20",
    "sg:postcode":"1020",
    "sg:province":"Bruxelles-Capitale",
    "sg:tags":[
        "tax-consultants"
    ],
    "wof:name":"Silverberg Ph Scs",
    "wof:placetype":"venue"
},
  "geometry": {"coordinates":[4.3602991104,50.8994903564],"type":"Point"}
}