{
  "type": "Feature",
  "properties": {
    "iso:country":"BE",
    "sg:address":"Rue Du Canon 71",
    "sg:city":"Ath",
    "sg:orig_category":"Instituts de beaut\u00e9",
    "sg:phone":"+32 68 28 62 09",
    "sg:postcode":"7800",
    "sg:province":"Hainaut",
    "wof:name":"Myriam Verplaetse",
    "wof:placetype":"venue"
},
  "geometry": {"coordinates":[3.7697849274,50.639503479],"type":"Point"}
}