{
  "type": "Feature",
  "properties": {
    "addr:full":"Winkelomseheide 65 Geel Antwerpen 2440",
    "addr:housenumber":"65",
    "addr:postcode":"2440",
    "addr:street":"Winkelomseheide",
    "iso:country":"BE",
    "sg:address":"Winkelomseheide 65",
    "sg:city":"Geel",
    "sg:orig_category":"Fietsen",
    "sg:phone":"+32 14 58 40 35",
    "sg:postcode":"2440",
    "sg:province":"Antwerpen",
    "wof:name":"Alfons De Bal",
    "wof:placetype":"venue"
},
  "geometry": {"coordinates":[5.0106301308,51.1373100281],"type":"Point"}
}