{
  "type": "Feature",
  "properties": {
    "addr:full":"Steenweg Op Drogenbos 244 Drogenbos/drogenbos Vlaams-Brabant 1620",
    "addr:housenumber":"244",
    "addr:postcode":"1620",
    "addr:street":"Steenweg Op Drogenbos",
    "iso:country":"BE",
    "sg:address":"Steenweg Op Drogenbos 244",
    "sg:city":"Drogenbos/drogenbos",
    "sg:orig_category":"Notarissen",
    "sg:phone":"+32 2 377 51 17",
    "sg:postcode":"1620",
    "sg:province":"Vlaams-Brabant",
    "wof:name":"H.j. Dufaux",
    "wof:placetype":"venue"
},
  "geometry": {"coordinates":[4.3195400238,50.7855606079],"type":"Point"}
}