{
  "type": "Feature",
  "properties": {
    "iso:country":"BE",
    "sg:address":"Boulevard E De Laveleye 191",
    "sg:city":"Liege",
    "sg:classifiers":[
        {
            "category":"Real Estate",
            "subcategory":"Real Estate Services",
            "type":"Services"
        }
    ],
    "sg:phone":"+32 4 340 35 06",
    "sg:postcode":"4020",
    "sg:province":"Li\u00e8ge",
    "wof:name":"Socogin",
    "wof:placetype":"venue"
},
  "geometry": {"coordinates":[5.5917029381,50.6196784973],"type":"Point"}
}