{
  "type": "Feature",
  "properties": {
    "addr:full":"Schorbeekstraat 19 Kortrijk West-Vlaanderen 8511",
    "addr:housenumber":"19",
    "addr:postcode":"8511",
    "addr:street":"Schorbeekstraat",
    "iso:country":"BE",
    "sg:address":"Schorbeekstraat 19",
    "sg:city":"Kortrijk",
    "sg:orig_category":"Voertuigen",
    "sg:phone":"+32 56 42 32 47",
    "sg:postcode":"8511",
    "sg:province":"West-Vlaanderen",
    "wof:name":"Autohandel Alcars",
    "wof:placetype":"venue"
},
  "geometry": {"coordinates":[3.2302849293,50.7784767151],"type":"Point"}
}