{
  "type": "Feature",
  "properties": {
    "addr:full":"Westlaan 263 Roeselare West-Vlaanderen 8800",
    "addr:housenumber":"263",
    "addr:postcode":"8800",
    "addr:street":"Westlaan",
    "iso:country":"BE",
    "sg:address":"Westlaan 263",
    "sg:city":"Roeselare",
    "sg:orig_category":"V\u00e9hicules automobiles. Pi\u00e8ces and accessoires de v\u00e9hicules automobiles Location de voitures",
    "sg:phone":"+32 51 22 12 22",
    "sg:postcode":"8800",
    "sg:province":"West-Vlaanderen",
    "wof:name":"Garage Vynckier",
    "wof:placetype":"venue"
},
  "geometry": {"coordinates":[3.1129860878,50.9452552795],"type":"Point"}
}