{
  "type": "Feature",
  "properties": {
    "iso:country":"BE",
    "sg:address":"Lange Elzenstraat 123d",
    "sg:city":"Antwerpen",
    "sg:classifiers":[
        {
            "category":"Food & Beverages",
            "subcategory":"Groceries & Convenience Stores",
            "type":"Retail Goods"
        }
    ],
    "sg:phone":"+32 3 238 51 00",
    "sg:postcode":"2018",
    "sg:province":"Antwerpen",
    "sg:tags":[
        "disposable"
    ],
    "wof:name":"Distrifirst Nv",
    "wof:placetype":"venue"
},
  "geometry": {"coordinates":[4.3951749802,51.1976051331],"type":"Point"}
}