{
  "type": "Feature",
  "properties": {
    "addr:full":"Chauss\u00e9e De Mons 20 Nivelles Brabant Wallon 1400",
    "addr:housenumber":"20",
    "addr:postcode":"1400",
    "addr:street":"Chausse\u0301E De Mons",
    "iso:country":"BE",
    "sg:address":"Chauss\u00e9e De Mons 20",
    "sg:city":"Nivelles",
    "sg:classifiers":[
        {
            "category":"Food & Beverages",
            "subcategory":"Supermarket",
            "type":"Retail Goods"
        }
    ],
    "sg:phone":"+32 67 89 39 11",
    "sg:postcode":"1400",
    "sg:province":"Brabant Wallon",
    "sg:tags":[
        "department",
        "store"
    ],
    "wof:name":"Hema-belgie",
    "wof:placetype":"venue"
},
  "geometry": {"coordinates":[4.3188657761,50.5941085815],"type":"Point"}
}