{
  "type": "Feature",
  "properties": {
    "iso:country":"BE",
    "sg:address":"Hoekstraat 3",
    "sg:city":"Anzegem",
    "sg:orig_category":"Stations-service and carburants. Entretien and r\u00e9parations de voitures. D\u00e9taillants en pi\u00e8ces and ac",
    "sg:phone":"+32 56 77 44 28",
    "sg:postcode":"8570",
    "sg:province":"West-Vlaanderen",
    "wof:name":"Garage Declercq",
    "wof:placetype":"venue"
},
  "geometry": {"coordinates":[3.404820919,50.8357887268],"type":"Point"}
}