{
  "type": "Feature",
  "properties": {
    "addr:full":"Van Cauwenberghelaan 11 Herne Vlaams-Brabant 1540",
    "addr:housenumber":"11",
    "addr:postcode":"1540",
    "addr:street":"Cauwenberghelaan",
    "iso:country":"BE",
    "sg:address":"Van Cauwenberghelaan 11",
    "sg:city":"Herne",
    "sg:orig_category":"Loodgieterij, verwarming and sanitaire installaties",
    "sg:phone":"+32 2 396 26 94",
    "sg:postcode":"1540",
    "sg:province":"Vlaams-Brabant",
    "wof:name":"Lucien Van Audenhove",
    "wof:placetype":"venue"
},
  "geometry": {"coordinates":[4.0612878799,50.7107086182],"type":"Point"}
}