{
  "type": "Feature",
  "properties": {
    "addr:full":"Rue J Deflandre 6 Chaudfontaine Li\u00e8ge 4053",
    "addr:housenumber":"6",
    "addr:postcode":"4053",
    "addr:street":"Rue J Deflandre",
    "iso:country":"BE",
    "sg:address":"Rue J Deflandre 6",
    "sg:city":"Chaudfontaine",
    "sg:classifiers":[
        {
            "category":"Building & Trades",
            "subcategory":"Plumbing",
            "type":"Services"
        }
    ],
    "sg:phone":"+32 4 361 68 88",
    "sg:postcode":"4053",
    "sg:province":"Li\u00e8ge",
    "sg:tags":[
        "diver",
        "commerce",
        "gr",
        "pour",
        "equipement"
    ],
    "wof:name":"Hotel-pro",
    "wof:placetype":"venue"
},
  "geometry": {"coordinates":[5.6061329842,50.6015510559],"type":"Point"}
}