{
  "type": "Feature",
  "properties": {
    "addr:full":"Wondelgemkaai Gent Oost-Vlaanderen 9000",
    "addr:postcode":"9000",
    "addr:street":"Oost-Vlaanderen",
    "iso:country":"BE",
    "sg:address":"Wondelgemkaai",
    "sg:city":"Gent",
    "sg:classifiers":[
        {
            "category":"Professional",
            "subcategory":"Engineering",
            "type":"Services"
        }
    ],
    "sg:phone":"+32 9 253 91 24",
    "sg:postcode":"9000",
    "sg:province":"Oost-Vlaanderen",
    "sg:tags":[
        "machine",
        "-",
        "mechanical"
    ],
    "wof:name":"Zaman Yves & Co Nv",
    "wof:placetype":"venue"
},
  "geometry": {"coordinates":[3.7302000523,51.0952453613],"type":"Point"}
}