{
  "type": "Feature",
  "properties": {
    "addr:full":"Mosdijk 11ba Lier Antwerpen 2500",
    "addr:housenumber":"11ba",
    "addr:postcode":"2500",
    "addr:street":"Mosdijk",
    "iso:country":"BE",
    "sg:address":"Mosdijk 11ba",
    "sg:city":"Lier",
    "sg:orig_category":"Evaluation and estimation de biens immobiliers",
    "sg:phone":"+32 3 480 94 47",
    "sg:postcode":"2500",
    "sg:province":"Antwerpen",
    "wof:name":"Viktor Ceulemans",
    "wof:placetype":"venue"
},
  "geometry": {"coordinates":[4.5738492012,51.1317672729],"type":"Point"}
}