{
  "type": "Feature",
  "properties": {
    "addr:full":"Rue Des Ecoles 5 Amay Li\u00e8ge 4540",
    "addr:housenumber":"5",
    "addr:postcode":"4540",
    "addr:street":"Rue Des Ecoles",
    "iso:country":"BE",
    "sg:address":"Rue Des Ecoles 5",
    "sg:city":"Amay",
    "sg:orig_category":"Enseignement maternel and primaire",
    "sg:phone":"+32 85 31 36 66",
    "sg:postcode":"4540",
    "sg:province":"Li\u00e8ge",
    "wof:name":"Ecole Fond. Communale",
    "wof:placetype":"venue"
},
  "geometry": {"coordinates":[5.3096017838,50.5551567078],"type":"Point"}
}