{
  "type": "Feature",
  "properties": {
    "iso:country":"BE",
    "sg:address":"Chemin Du Fort De Suarl\u00e9e 12",
    "sg:city":"Namur (suarl\u00e9e)",
    "sg:classifiers":[
        {
            "category":"Recreation",
            "subcategory":"Campground",
            "type":"Entertainment"
        }
    ],
    "sg:phone":"+32 81 56 75 68",
    "sg:postcode":"5020",
    "sg:province":"Namur",
    "sg:tags":[
        "site",
        "camping"
    ],
    "wof:name":"Camping Domaine De Suarl\u00e9e",
    "wof:placetype":"venue"
},
  "geometry": {"coordinates":[4.7991380692,50.49477005],"type":"Point"}
}