{
  "type": "Feature",
  "properties": {
    "iso:country":"BE",
    "sg:address":"Chauss\u00e9e De Tongres 198",
    "sg:city":"Li\u00e8ge 1 (rocourt)",
    "sg:classifiers":[
        {
            "category":"Retail",
            "subcategory":"Event Space",
            "type":"Services"
        }
    ],
    "sg:phone":"+32 4 224 40 93",
    "sg:postcode":"4000",
    "sg:province":"Li\u00e8ge",
    "sg:tags":[
        "rental",
        "-",
        "hall"
    ],
    "wof:name":"Hollywood Studio",
    "wof:placetype":"venue"
},
  "geometry": {"coordinates":[5.5552577972,50.668056488],"type":"Point"}
}