{
  "type": "Feature",
  "properties": {
    "iso:country":"BE",
    "sg:address":"Kouterstraat 3",
    "sg:city":"Waasmunster",
    "sg:orig_category":"Enseignement maternel and primaire",
    "sg:phone":"+32 52 46 99 88",
    "sg:postcode":"9250",
    "sg:province":"Oost-Vlaanderen",
    "wof:name":"B.s.g.o. Kouterbos",
    "wof:placetype":"venue"
},
  "geometry": {"coordinates":[4.0836501122,51.1111068726],"type":"Point"}
}