{
  "type": "Feature",
  "properties": {
    "iso:country":"BE",
    "sg:address":"Chauss\u00c9e De Charleroi 244",
    "sg:city":"Sint-gillis/saint-gilles",
    "sg:orig_category":"Chaussures",
    "sg:phone":"+32 2 537 69 96",
    "sg:postcode":"1060",
    "sg:province":"Bruxelles-Capitale",
    "wof:name":"Maison Chantrain",
    "wof:placetype":"venue"
},
  "geometry": {"coordinates":[4.3541197777,50.8232498169],"type":"Point"}
}