{
  "type": "Feature",
  "properties": {
    "addr:full":"Bookmolenstraat 28 Sint-niklaas (belsele) Oost-Vlaanderen 9111",
    "addr:housenumber":"28",
    "addr:postcode":"9111",
    "addr:street":"Bookmolenstraat",
    "iso:country":"BE",
    "sg:address":"Bookmolenstraat 28",
    "sg:city":"Sint-niklaas (belsele)",
    "sg:orig_category":"Non-Classified Establishments",
    "sg:phone":"+32 3 722 92 50",
    "sg:postcode":"9111",
    "sg:province":"Oost-Vlaanderen",
    "wof:name":"Fierens Mengvoeders Nv",
    "wof:placetype":"venue"
},
  "geometry": {"coordinates":[4.1067948341,51.1470298767],"type":"Point"}
}