{
  "type": "Feature",
  "properties": {
    "addr:full":"Prins Albertplein 4 Koksijde West-Vlaanderen 8670",
    "addr:housenumber":"4",
    "addr:postcode":"8670",
    "addr:street":"Prins Albertplein",
    "iso:country":"BE",
    "sg:address":"Prins Albertplein 4",
    "sg:city":"Koksijde",
    "sg:classifiers":[
        {
            "category":"Food & Beverages",
            "subcategory":"Groceries & Convenience Stores",
            "type":"Retail Goods"
        }
    ],
    "sg:phone":"+32 58 51 32 66",
    "sg:postcode":"8670",
    "sg:province":"West-Vlaanderen",
    "sg:tags":[
        "grocer"
    ],
    "wof:name":"Vanlerberghe K",
    "wof:placetype":"venue"
},
  "geometry": {"coordinates":[2.6296510696,51.118812561],"type":"Point"}
}