{
  "type": "Feature",
  "properties": {
    "iso:country":"BE",
    "sg:address":"Zandvleugestraat 3",
    "sg:city":"Ruiselede",
    "sg:classifiers":[
        {
            "category":"Professional",
            "subcategory":"Computer Services",
            "type":"Services"
        }
    ],
    "sg:phone":"+32 51 68 67 84",
    "sg:postcode":"8755",
    "sg:province":"West-Vlaanderen",
    "sg:tags":[
        "-",
        "processing",
        "data",
        "software"
    ],
    "wof:name":"A.b.m.",
    "wof:placetype":"venue"
},
  "geometry": {"coordinates":[3.3889660835,51.0547943115],"type":"Point"}
}