{
  "type": "Feature",
  "properties": {
    "iso:country":"BE",
    "sg:address":"Route De Henri Chapelle 43",
    "sg:city":"Dison (andrimont)",
    "sg:classifiers":[
        {
            "category":"Building & Trades",
            "subcategory":"Plumbing",
            "type":"Services"
        }
    ],
    "sg:phone":"+32 87 30 04 53",
    "sg:postcode":"4821",
    "sg:province":"Li\u00e8ge",
    "sg:tags":[
        "contractor"
    ],
    "wof:name":"Orban M",
    "wof:placetype":"venue"
},
  "geometry": {"coordinates":[5.8857679367,50.6166267395],"type":"Point"}
}