{
  "type": "Feature",
  "properties": {
    "iso:country":"BE",
    "sg:address":"Leuvensesteenweg 679",
    "sg:city":"Kortenberg (erps-kwerps)",
    "sg:classifiers":[
        {
            "category":"Professional",
            "type":"Services"
        }
    ],
    "sg:phone":"+32 2 756 87 11",
    "sg:postcode":"3071",
    "sg:province":"Vlaams-Brabant",
    "sg:tags":[
        "leasing"
    ],
    "wof:name":"D'ieteren Lease Sa",
    "wof:placetype":"venue"
},
  "geometry": {"coordinates":[4.5639209747,50.8910102844],"type":"Point"}
}