{
  "type": "Feature",
  "properties": {
    "addr:full":"Avenue Georges Henri 324 Bruxelles (woluwe-saint-lambert) Bruxelles-Capitale 1200",
    "addr:housenumber":"324",
    "addr:postcode":"1200",
    "addr:street":"Avenue Georges Henri",
    "iso:country":"BE",
    "sg:address":"Avenue Georges Henri 324",
    "sg:city":"Bruxelles (woluwe-saint-lambert)",
    "sg:classifiers":[
        {
            "category":"Real Estate",
            "subcategory":"Architect",
            "type":"Services"
        }
    ],
    "sg:phone":"+32 2 736 19 79",
    "sg:postcode":"1200",
    "sg:province":"Bruxelles-Capitale",
    "wof:name":"Denis G",
    "wof:placetype":"venue"
},
  "geometry": {"coordinates":[4.4096231461,50.8432502747],"type":"Point"}
}