{
  "type": "Feature",
  "properties": {
    "addr:full":"Kakemanstraat 19 Lebbeke Oost-Vlaanderen 9280",
    "addr:housenumber":"19",
    "addr:postcode":"9280",
    "addr:street":"Kakemanstraat",
    "iso:country":"BE",
    "sg:address":"Kakemanstraat 19",
    "sg:city":"Lebbeke",
    "sg:classifiers":[
        {
            "category":"Building & Trades",
            "subcategory":"Cleaning & Sanitation",
            "type":"Services"
        }
    ],
    "sg:phone":"+32 52 35 17 80",
    "sg:postcode":"9280",
    "sg:province":"Oost-Vlaanderen",
    "sg:tags":[
        "fa\u00e7ade",
        "maintenance"
    ],
    "wof:name":"Van Ransbeeck V.r.i.c",
    "wof:placetype":"venue"
},
  "geometry": {"coordinates":[4.1597080231,50.9932022095],"type":"Point"}
}