{
  "type": "Feature",
  "properties": {
    "iso:country":"BE",
    "sg:address":"Bredabaan 782",
    "sg:city":"Brasschaat",
    "sg:classifiers":[
        {
            "category":"Cafe",
            "type":"Food & Drink"
        }
    ],
    "sg:phone":"+32 3 633 24 44",
    "sg:postcode":"2930",
    "sg:province":"Antwerpen",
    "sg:tags":[
        "caf\u00e9s"
    ],
    "wof:name":"Alida Jamotte",
    "wof:placetype":"venue"
},
  "geometry": {"coordinates":[4.5202898979,51.3237190247],"type":"Point"}
}