{
  "type": "Feature",
  "properties": {
    "addr:full":"Rue Saint Sang 16a Sambreville Namur 5060",
    "addr:housenumber":"16a",
    "addr:postcode":"5060",
    "addr:street":"Rue Saint Sang",
    "iso:country":"BE",
    "sg:address":"Rue Saint Sang 16a",
    "sg:city":"Sambreville",
    "sg:orig_category":"Huishoudapparaten, televisies and radio's",
    "sg:phone":"+32 71 77 73 75",
    "sg:postcode":"5060",
    "sg:province":"Namur",
    "wof:name":"Air Plus",
    "wof:placetype":"venue"
},
  "geometry": {"coordinates":[4.6284990311,50.4444503784],"type":"Point"}
}