{
  "type": "Feature",
  "properties": {
    "iso:country":"BE",
    "sg:address":"Avenue Henri Bourgys 81",
    "sg:city":"Waterloo",
    "sg:classifiers":[
        {
            "category":"Bakery",
            "type":"Food & Drink"
        }
    ],
    "sg:phone":"+32 2 763 17 21",
    "sg:postcode":"1410",
    "sg:province":"Brabant Wallon",
    "sg:tags":[
        "confectioner",
        "baker"
    ],
    "wof:name":"Grain De Vie (le)",
    "wof:placetype":"venue"
},
  "geometry": {"coordinates":[4.3890738487,50.7294082642],"type":"Point"}
}