{
  "type": "Feature",
  "properties": {
    "addr:full":"Rue De Ransbeek 310 Bruxelles Bruxelles-Capitale 1120",
    "addr:housenumber":"310",
    "addr:postcode":"1120",
    "addr:street":"Rue De Ransbeek",
    "iso:country":"BE",
    "sg:address":"Rue De Ransbeek 310",
    "sg:city":"Bruxelles",
    "sg:classifiers":[
        {
            "category":"Health Services",
            "subcategory":"Medical Lab",
            "type":"Services"
        }
    ],
    "sg:phone":"+32 2 264 22 45",
    "sg:postcode":"1120",
    "sg:province":"Bruxelles-Capitale",
    "sg:tags":[
        "chemical",
        "pharmaceutical",
        "pharmacy"
    ],
    "wof:name":"Peptisyntha Et Cie Sa",
    "wof:placetype":"venue"
},
  "geometry": {"coordinates":[4.4016680717,50.9030647278],"type":"Point"}
}