{
  "type": "Feature",
  "properties": {
    "addr:full":"Avenue Du Panth\u00e9on 13 Bruxelles (koekelberg) Bruxelles-Capitale 1081",
    "addr:housenumber":"13",
    "addr:postcode":"1081",
    "addr:street":"Avenue Du Panthe\u0301On",
    "iso:country":"BE",
    "sg:address":"Avenue Du Panth\u00e9on 13",
    "sg:city":"Bruxelles (koekelberg)",
    "sg:classifiers":[
        {
            "category":"Professional",
            "subcategory":"Management & Consulting",
            "type":"Services"
        }
    ],
    "sg:phone":"+32 2 414 87 74",
    "sg:postcode":"1081",
    "sg:province":"Bruxelles-Capitale",
    "sg:tags":[
        "consultant",
        "agency",
        "advertising"
    ],
    "wof:name":"Swing",
    "wof:placetype":"venue"
},
  "geometry": {"coordinates":[4.3246917725,50.8634338379],"type":"Point"}
}