{
  "type": "Feature",
  "properties": {
    "addr:full":"Karnemelkstraat 17 Roeselare West-Vlaanderen 8800",
    "addr:housenumber":"17",
    "addr:postcode":"8800",
    "addr:street":"Karnemelkstraat",
    "iso:country":"BE",
    "sg:address":"Karnemelkstraat 17",
    "sg:city":"Roeselare",
    "sg:orig_category":"Non-Classified Establishments",
    "sg:phone":"+32 51 20 32 16",
    "sg:postcode":"8800",
    "sg:province":"West-Vlaanderen",
    "wof:name":"Deckmyn Y",
    "wof:placetype":"venue"
},
  "geometry": {"coordinates":[3.1217970848,50.9450187683],"type":"Point"}
}