{
  "type": "Feature",
  "properties": {
    "addr:full":"Rue Des Foss\u00c9s 9 Viroinval Namur 5670",
    "addr:housenumber":"9",
    "addr:postcode":"5670",
    "addr:street":"Rue Des Fosse\u0301S",
    "iso:country":"BE",
    "sg:address":"Rue Des Foss\u00c9s 9",
    "sg:city":"Viroinval",
    "sg:orig_category":"Vakantiehuizen",
    "sg:phone":"+32 60 45 61 39",
    "sg:postcode":"5670",
    "sg:province":"Namur",
    "wof:name":"Le Chabot",
    "wof:placetype":"venue"
},
  "geometry": {"coordinates":[4.6357388496,50.078956604],"type":"Point"}
}