{
  "type": "Feature",
  "properties": {
    "addr:full":"Rue De Royenne 38 Grez-doiceau Brabant Wallon 1390",
    "addr:housenumber":"38",
    "addr:postcode":"1390",
    "addr:street":"Rue De Royenne",
    "iso:country":"BE",
    "sg:address":"Rue De Royenne 38",
    "sg:city":"Grez-doiceau",
    "sg:classifiers":[
        {
            "category":"Professional",
            "subcategory":"Accounting & Tax Preparation",
            "type":"Services"
        }
    ],
    "sg:phone":"+32 10 84 47 18",
    "sg:postcode":"1390",
    "sg:province":"Brabant Wallon",
    "sg:tags":[
        "accountant"
    ],
    "wof:name":"Ph. Lambert",
    "wof:placetype":"venue"
},
  "geometry": {"coordinates":[4.699452877,50.7188186646],"type":"Point"}
}