{
  "type": "Feature",
  "properties": {
    "addr:full":"Maastrichtersteenweg 82 Hasselt Limburg 3500",
    "addr:housenumber":"82",
    "addr:postcode":"3500",
    "addr:street":"Maastrichtersteenweg",
    "iso:country":"BE",
    "sg:address":"Maastrichtersteenweg 82",
    "sg:city":"Hasselt",
    "sg:classifiers":[
        {
            "category":"Professional",
            "subcategory":"Art Services",
            "type":"Services"
        }
    ],
    "sg:phone":"+32 11 24 15 98",
    "sg:postcode":"3500",
    "sg:province":"Limburg",
    "sg:tags":[
        "interior",
        "designer"
    ],
    "wof:name":"Moens C",
    "wof:placetype":"venue"
},
  "geometry": {"coordinates":[5.3488469124,50.9301185608],"type":"Point"}
}