{
  "type": "Feature",
  "properties": {
    "addr:full":"Wijnegem Shopping Center 353 Wijnegem Antwerpen 2110",
    "addr:housenumber":"353",
    "addr:postcode":"2110",
    "iso:country":"BE",
    "sg:address":"Wijnegem Shopping Center 353",
    "sg:city":"Wijnegem",
    "sg:classifiers":[
        {
            "category":"Bars & Pubs",
            "type":"Food & Drink"
        }
    ],
    "sg:phone":"+32 3 353 33 72",
    "sg:postcode":"2110",
    "sg:province":"Antwerpen",
    "sg:tags":[
        "tavern"
    ],
    "wof:name":"De Bibliotheek",
    "wof:placetype":"venue"
},
  "geometry": {"coordinates":[4.5248470306,51.2279434204],"type":"Point"}
}