{
  "type": "Feature",
  "properties": {
    "addr:full":"Laagweg 69 Wervik West-Vlaanderen 8940",
    "addr:housenumber":"69",
    "addr:postcode":"8940",
    "addr:street":"Laagweg",
    "iso:country":"BE",
    "sg:address":"Laagweg 69",
    "sg:city":"Wervik",
    "sg:classifiers":[
        {
            "category":"Bakery",
            "type":"Food & Drink"
        }
    ],
    "sg:phone":"+32 56 31 13 24",
    "sg:postcode":"8940",
    "sg:province":"West-Vlaanderen",
    "sg:tags":[
        "confectioner",
        "baker"
    ],
    "wof:name":"De Vrekere A",
    "wof:placetype":"venue"
},
  "geometry": {"coordinates":[3.0756309032,50.7848548889],"type":"Point"}
}