{
  "type": "Feature",
  "properties": {
    "iso:country":"BE",
    "sg:address":"Diestsesteenweg 58bb",
    "sg:city":"Aarschot",
    "sg:orig_category":"Dameskledingzaken",
    "sg:phone":"+32 16 56 78 50",
    "sg:postcode":"3200",
    "sg:province":"Vlaams-Brabant",
    "wof:name":"Huis Nicoline",
    "wof:placetype":"venue"
},
  "geometry": {"coordinates":[4.8554720879,50.9795799255],"type":"Point"}
}