{
  "type": "Feature",
  "properties": {
    "addr:full":"Grote Baan 181 Beveren (melsele) Oost-Vlaanderen 9120",
    "addr:housenumber":"181",
    "addr:postcode":"9120",
    "addr:street":"Grote Baan",
    "iso:country":"BE",
    "sg:address":"Grote Baan 181",
    "sg:city":"Beveren (melsele)",
    "sg:classifiers":[
        {
            "category":"Bars & Pubs",
            "type":"Food & Drink"
        }
    ],
    "sg:phone":"+32 3 775 67 10",
    "sg:postcode":"9120",
    "sg:province":"Oost-Vlaanderen",
    "wof:name":"De Kadans",
    "wof:placetype":"venue"
},
  "geometry": {"coordinates":[4.2868947983,51.2204170227],"type":"Point"}
}