{
  "type": "Feature",
  "properties": {
    "iso:country":"BE",
    "sg:address":"Rue Royale 97 Box 19",
    "sg:city":"Bruxelles",
    "sg:classifiers":[
        {
            "category":"Professional",
            "subcategory":"Lawyer & Legal Services",
            "type":"Services"
        }
    ],
    "sg:phone":"+32 2 217 23 92",
    "sg:postcode":"1000",
    "sg:province":"Bruxelles-Capitale",
    "wof:name":"Coessens P",
    "wof:placetype":"venue"
},
  "geometry": {"coordinates":[4.3647990227,50.850982666],"type":"Point"}
}