{
  "type": "Feature",
  "properties": {
    "iso:country":"BE",
    "sg:address":"Rue Ernest Salu 77",
    "sg:city":"Brussel/bruxelles",
    "sg:orig_category":"Epiceries",
    "sg:phone":"+32 2 478 85 27",
    "sg:postcode":"1020",
    "sg:province":"Bruxelles-Capitale",
    "wof:name":"Le Petit March\u00c9",
    "wof:placetype":"venue"
},
  "geometry": {"coordinates":[4.3388800621,50.8868713379],"type":"Point"}
}