{
  "type": "Feature",
  "properties": {
    "iso:country":"BE",
    "sg:address":"Veurnseweg 532",
    "sg:city":"Ieper",
    "sg:orig_category":"M\u00e9decins and sp\u00e9cialistes",
    "sg:phone":"+32 57 42 20 38",
    "sg:postcode":"8906",
    "sg:province":"West-Vlaanderen",
    "wof:name":"H. Touquet",
    "wof:placetype":"venue"
},
  "geometry": {"coordinates":[2.8197200298,50.8853683472],"type":"Point"}
}