{
  "type": "Feature",
  "properties": {
    "addr:full":"Place Des Nations-unies 7 Li\u00c8ge Li\u00e8ge 4020",
    "addr:housenumber":"7",
    "addr:postcode":"4020",
    "addr:street":"Place Des Nations-Unies",
    "iso:country":"BE",
    "sg:address":"Place Des Nations-unies 7",
    "sg:city":"Li\u00c8ge",
    "sg:orig_category":"Avocats and conseillers juridiques",
    "sg:phone":"+32 4 342 30 50",
    "sg:postcode":"4020",
    "sg:province":"Li\u00e8ge",
    "wof:name":"V\u00c9ronique Bertrand",
    "wof:placetype":"venue"
},
  "geometry": {"coordinates":[5.585793972,50.6220970154],"type":"Point"}
}