{
  "type": "Feature",
  "properties": {
    "iso:country":"BE",
    "sg:address":"Thommen 54",
    "sg:city":"Burg-reuland",
    "sg:orig_category":"Kapsalons Rundveehouders",
    "sg:phone":"+32 80 32 96 84",
    "sg:postcode":"4791",
    "sg:province":"Li\u00e8ge",
    "wof:name":"Annette Kohnen",
    "wof:placetype":"venue"
},
  "geometry": {"coordinates":[6.0944099426,50.2024497986],"type":"Point"}
}