{
  "type": "Feature",
  "properties": {
    "addr:full":"Oudstrijderslaan 11 Zoersel Antwerpen 2980",
    "addr:housenumber":"11",
    "addr:postcode":"2980",
    "addr:street":"Oudstrijderslaan",
    "iso:country":"BE",
    "sg:address":"Oudstrijderslaan 11",
    "sg:city":"Zoersel",
    "sg:classifiers":[
        {
            "category":"Professional",
            "subcategory":"Accounting & Tax Preparation",
            "type":"Services"
        }
    ],
    "sg:phone":"+32 3 385 21 51",
    "sg:postcode":"2980",
    "sg:province":"Antwerpen",
    "sg:tags":[
        "bookkeeper"
    ],
    "wof:name":"Beyltiens D",
    "wof:placetype":"venue"
},
  "geometry": {"coordinates":[4.6541948318,51.2587890625],"type":"Point"}
}