{
  "type": "Feature",
  "properties": {
    "addr:full":"Gentsesteenweg 1072 Sint-agatha-berchem/berchem-sainte-agathe Bruxelles-Capitale 1082",
    "addr:housenumber":"1072",
    "addr:postcode":"1082",
    "addr:street":"Gentsesteenweg;/",
    "iso:country":"BE",
    "sg:address":"Gentsesteenweg 1072",
    "sg:city":"Sint-agatha-berchem/berchem-sainte-agathe",
    "sg:orig_category":"Diensten voor huisdieren",
    "sg:phone":"+32 2 465 40 47",
    "sg:postcode":"1082",
    "sg:province":"Bruxelles-Capitale",
    "wof:name":"Qat-pat",
    "wof:placetype":"venue"
},
  "geometry": {"coordinates":[4.3026328087,50.8614425659],"type":"Point"}
}