{
  "type": "Feature",
  "properties": {
    "addr:full":"Rue L\u00e9opold 38 Charleroi Hainaut 6000",
    "addr:housenumber":"38",
    "addr:postcode":"6000",
    "addr:street":"Rue Le\u0301Opold;Hainaut",
    "iso:country":"BE",
    "sg:address":"Rue L\u00e9opold 38",
    "sg:city":"Charleroi",
    "sg:classifiers":[
        {
            "category":"Health Services",
            "subcategory":"Health Practitioner",
            "type":"Services"
        }
    ],
    "sg:phone":"+32 71 30 95 05",
    "sg:postcode":"6000",
    "sg:province":"Hainaut",
    "sg:tags":[
        "therapist",
        "speech"
    ],
    "wof:name":"Pirlot Christine",
    "wof:placetype":"venue"
},
  "geometry": {"coordinates":[4.4427142143,50.4064826965],"type":"Point"}
}