{
  "type": "Feature",
  "properties": {
    "addr:full":"Rue Belle Vue 27 Hasti\u00e8re (hasti\u00e8re-par-del\u00e0) Namur 5541",
    "addr:housenumber":"27",
    "addr:postcode":"5541",
    "addr:street":"Rue Belle Vue",
    "iso:country":"BE",
    "sg:address":"Rue Belle Vue 27",
    "sg:city":"Hasti\u00e8re (hasti\u00e8re-par-del\u00e0)",
    "sg:classifiers":[
        {
            "category":"Professional",
            "subcategory":"Accounting & Tax Preparation",
            "type":"Services"
        }
    ],
    "sg:phone":"+32 82 64 60 93",
    "sg:postcode":"5541",
    "sg:province":"Namur",
    "sg:tags":[
        "accountant"
    ],
    "wof:name":"Massaux Ph",
    "wof:placetype":"venue"
},
  "geometry": {"coordinates":[4.8267650604,50.2132148743],"type":"Point"}
}