{
  "type": "Feature",
  "properties": {
    "iso:country":"BE",
    "sg:address":"Aarschotsesteenweg 221",
    "sg:city":"Rotselaar (wezemaal)",
    "sg:classifiers":[
        {
            "category":"Health Services",
            "subcategory":"Doctor",
            "type":"Services"
        }
    ],
    "sg:phone":"+32 16 58 02 80",
    "sg:postcode":"3111",
    "sg:province":"Vlaams-Brabant",
    "sg:tags":[
        "medicinephysicians",
        "surgeon"
    ],
    "wof:name":"Allaert H",
    "wof:placetype":"venue"
},
  "geometry": {"coordinates":[4.7545700073,50.9493255615],"type":"Point"}
}