{
  "type": "Feature",
  "properties": {
    "iso:country":"BE",
    "sg:address":"Malmedyer Strasse 8",
    "sg:city":"Sankt Vith",
    "sg:classifiers":[
        {
            "category":"Insurance",
            "subcategory":"Insurance Agent",
            "type":"Services"
        }
    ],
    "sg:phone":"+32 80 22 90 02",
    "sg:postcode":"4780",
    "sg:province":"Li\u00e8ge",
    "sg:tags":[
        "broker"
    ],
    "wof:name":"Trost Freddy Sprl",
    "wof:placetype":"venue"
},
  "geometry": {"coordinates":[6.1240010262,50.2830924988],"type":"Point"}
}