{
  "type": "Feature",
  "properties": {
    "addr:full":"Hovestraat 98 Arendonk Antwerpen 2370",
    "addr:housenumber":"98",
    "addr:postcode":"2370",
    "addr:street":"Hovestraat",
    "iso:country":"BE",
    "sg:address":"Hovestraat 98",
    "sg:city":"Arendonk",
    "sg:orig_category":"H\u00f4tels",
    "sg:phone":"+32 14 67 00 12",
    "sg:postcode":"2370",
    "sg:province":"Antwerpen",
    "wof:name":"De Kempen",
    "wof:placetype":"venue"
},
  "geometry": {"coordinates":[5.0874757767,51.3182601929],"type":"Point"}
}