{
  "type": "Feature",
  "properties": {
    "iso:country":"BE",
    "sg:address":"Hendrik Beyaertstraat 22",
    "sg:city":"Kortrijk",
    "sg:orig_category":"Avocats and conseillers juridiques",
    "sg:phone":"+32 56 22 41 39",
    "sg:postcode":"8500",
    "sg:province":"West-Vlaanderen",
    "wof:name":"W. Bulckaert",
    "wof:placetype":"venue"
},
  "geometry": {"coordinates":[3.2577490807,50.8282203674],"type":"Point"}
}