{
  "type": "Feature",
  "properties": {
    "addr:full":"Reigerstraat 3 Wijnegem Antwerpen 2110",
    "addr:housenumber":"3",
    "addr:postcode":"2110",
    "addr:street":"Reigerstraat",
    "iso:country":"BE",
    "sg:address":"Reigerstraat 3",
    "sg:city":"Wijnegem",
    "sg:classifiers":[
        {
            "category":"Retail",
            "subcategory":"Repair Shop",
            "type":"Services"
        }
    ],
    "sg:phone":"+32 3 685 10 51",
    "sg:postcode":"2110",
    "sg:province":"Antwerpen",
    "sg:tags":[
        "radio",
        "television",
        "-",
        "maintenance"
    ],
    "wof:name":"Beta Repair Bvba",
    "wof:placetype":"venue"
},
  "geometry": {"coordinates":[4.5249671936,51.2329063416],"type":"Point"}
}