{
  "type": "Feature",
  "properties": {
    "addr:full":"Rue Chamont 26 La Roche-en-ardenne Luxembourg 6980",
    "addr:housenumber":"26",
    "addr:postcode":"6980",
    "addr:street":"Rue Chamont",
    "iso:country":"BE",
    "sg:address":"Rue Chamont 26",
    "sg:city":"La Roche-en-ardenne",
    "sg:classifiers":[
        {
            "category":"Travel",
            "subcategory":"Hotels & Motels",
            "type":"Entertainment"
        }
    ],
    "sg:phone":"+32 84 41 11 24",
    "sg:postcode":"6980",
    "sg:province":"Luxembourg",
    "wof:name":"H\u00d4tel Moderne",
    "wof:placetype":"venue"
},
  "geometry": {"coordinates":[5.5776629448,50.1843681335],"type":"Point"}
}