{
  "type": "Feature",
  "properties": {
    "addr:full":"Rue Fran\u00e7ois Gay 86 Bruxelles (woluwe-saint-pierre) Bruxelles-Capitale 1150",
    "addr:housenumber":"86",
    "addr:postcode":"1150",
    "addr:street":"Rue Franc\u0327Ois Gay",
    "iso:country":"BE",
    "sg:address":"Rue Fran\u00e7ois Gay 86",
    "sg:city":"Bruxelles (woluwe-saint-pierre)",
    "sg:classifiers":[
        {
            "category":"Social Services",
            "type":"Services"
        }
    ],
    "sg:phone":"+32 2 771 38 46",
    "sg:postcode":"1150",
    "sg:province":"Bruxelles-Capitale",
    "wof:name":"Maison (la) Asbl",
    "wof:placetype":"venue"
},
  "geometry": {"coordinates":[4.427295208,50.8377609253],"type":"Point"}
}