{
  "type": "Feature",
  "properties": {
    "iso:country":"BE",
    "sg:address":"Kapittel 10",
    "sg:city":"Halle",
    "sg:classifiers":[
        {
            "category":"Restaurant",
            "type":"Food & Drink"
        }
    ],
    "sg:phone":"+32 2 380 14 21",
    "sg:postcode":"1500",
    "sg:province":"Vlaams-Brabant",
    "wof:name":"'t Kriekske",
    "wof:placetype":"venue"
},
  "geometry": {"coordinates":[4.2851572037,50.7172851562],"type":"Point"}
}