{
  "type": "Feature",
  "properties": {
    "iso:country":"BE",
    "sg:address":"Meistraat 110a",
    "sg:city":"Dessel",
    "sg:classifiers":[
        {
            "category":"Insurance",
            "subcategory":"Insurance Agent",
            "type":"Services"
        }
    ],
    "sg:phone":"+32 14 37 75 15",
    "sg:postcode":"2480",
    "sg:province":"Antwerpen",
    "sg:tags":[
        "verzekeringsmakelaars",
        "expert"
    ],
    "wof:name":"G. Minnen",
    "wof:placetype":"venue"
},
  "geometry": {"coordinates":[5.1602301598,51.2412605286],"type":"Point"}
}