{
  "type": "Feature",
  "properties": {
    "iso:country":"BE",
    "sg:address":"Nieuwstraat 21",
    "sg:city":"Avelgem",
    "sg:orig_category":"Sportclubs",
    "sg:phone":"+32 55 38 61 92",
    "sg:postcode":"8581",
    "sg:province":"West-Vlaanderen",
    "wof:name":"Karateclub",
    "wof:placetype":"venue"
},
  "geometry": {"coordinates":[3.4830150604,50.7927474976],"type":"Point"}
}