{
  "type": "Feature",
  "properties": {
    "addr:full":"Lindestraat 325 Evere/evere Bruxelles-Capitale 1140",
    "addr:housenumber":"325",
    "addr:postcode":"1140",
    "addr:street":"Lindestraat",
    "iso:country":"BE",
    "sg:address":"Lindestraat 325",
    "sg:city":"Evere/evere",
    "sg:orig_category":"Brood, gebak and snoepgoed",
    "sg:phone":"+32 2 215 42 62",
    "sg:postcode":"1140",
    "sg:province":"Bruxelles-Capitale",
    "wof:name":"P\u00c2tisserie Martin",
    "wof:placetype":"venue"
},
  "geometry": {"coordinates":[4.3959851265,50.8693237305],"type":"Point"}
}