{
  "type": "Feature",
  "properties": {
    "addr:full":"Rue Du Village 32 Aubange Luxembourg 6790",
    "addr:housenumber":"32",
    "addr:postcode":"6790",
    "addr:street":"Rue Du Village",
    "iso:country":"BE",
    "sg:address":"Rue Du Village 32",
    "sg:city":"Aubange",
    "sg:orig_category":"Boucheries",
    "sg:phone":"+32 63 38 83 92",
    "sg:postcode":"6790",
    "sg:province":"Luxembourg",
    "wof:name":"Philippe Martin",
    "wof:placetype":"venue"
},
  "geometry": {"coordinates":[5.8079857826,49.5677108765],"type":"Point"}
}