{
  "type": "Feature",
  "properties": {
    "addr:full":"Rue De La Hate 9 Bouillon (corbion) Luxembourg 6838",
    "addr:housenumber":"9",
    "addr:postcode":"6838",
    "addr:street":"Rue De La Hate",
    "iso:country":"BE",
    "sg:address":"Rue De La Hate 9",
    "sg:city":"Bouillon (corbion)",
    "sg:classifiers":[
        {
            "category":"Transit Center",
            "subcategory":"Passenger",
            "type":"Transportation"
        }
    ],
    "sg:phone":"+32 61 46 61 02",
    "sg:postcode":"6838",
    "sg:province":"Luxembourg",
    "sg:tags":[
        "car",
        "trailer"
    ],
    "wof:name":"Brasseur Thierry Sprl",
    "wof:placetype":"venue"
},
  "geometry": {"coordinates":[5.0071702003,49.7973403931],"type":"Point"}
}