{
  "type": "Feature",
  "properties": {
    "addr:full":"Chauss\u00c9e Montgomery 18 Rumes Hainaut 7610",
    "addr:housenumber":"18",
    "addr:postcode":"7610",
    "addr:street":"Chausse\u0301E Montgomery",
    "iso:country":"BE",
    "sg:address":"Chauss\u00c9e Montgomery 18",
    "sg:city":"Rumes",
    "sg:orig_category":"S\u00e9curit\u00e9 sociale",
    "sg:phone":"+32 69 64 97 10",
    "sg:postcode":"7610",
    "sg:province":"Hainaut",
    "wof:name":"Les Amis R\u00c9unis",
    "wof:placetype":"venue"
},
  "geometry": {"coordinates":[3.3052899837,50.5535392761],"type":"Point"}
}