{
  "type": "Feature",
  "properties": {
    "iso:country":"BE",
    "sg:address":"Bruggestraat 31",
    "sg:city":"Ichtegem",
    "sg:orig_category":"Decoratieve kunst and kunstbenodigdheden",
    "sg:phone":"+32 59 29 81 47",
    "sg:postcode":"8480",
    "sg:province":"West-Vlaanderen",
    "wof:name":"Andre Verlinde",
    "wof:placetype":"venue"
},
  "geometry": {"coordinates":[3.0302829742,51.1304779053],"type":"Point"}
}