{
  "type": "Feature",
  "properties": {
    "addr:full":"Bergensesteenweg 157 Sint-pieters-leeuw Vlaams-Brabant 1600",
    "addr:housenumber":"157",
    "addr:postcode":"1600",
    "addr:street":"Bergensesteenweg",
    "iso:country":"BE",
    "sg:address":"Bergensesteenweg 157",
    "sg:city":"Sint-pieters-leeuw",
    "sg:orig_category":"Installation de menuiserie en bois and plastique",
    "sg:phone":"+32 2 377 62 84",
    "sg:postcode":"1600",
    "sg:province":"Vlaams-Brabant",
    "wof:name":"Jadeco",
    "wof:placetype":"venue"
},
  "geometry": {"coordinates":[4.2880468369,50.7991828918],"type":"Point"}
}