{
  "type": "Feature",
  "properties": {
    "addr:full":"Rue Du Quesnoy 161 La Louviere Hainaut 7100",
    "addr:housenumber":"161",
    "addr:postcode":"7100",
    "addr:street":"Rue Du Quesnoy",
    "iso:country":"BE",
    "sg:address":"Rue Du Quesnoy 161",
    "sg:city":"La Louviere",
    "sg:orig_category":"Eleveurs de bovins",
    "sg:phone":"+32 64 22 31 58",
    "sg:postcode":"7100",
    "sg:province":"Hainaut",
    "wof:name":"Guy Desmet",
    "wof:placetype":"venue"
},
  "geometry": {"coordinates":[4.1850848198,50.4748649597],"type":"Point"}
}