{
  "type": "Feature",
  "properties": {
    "addr:full":"Berg\u00e9vest 5 Tienen Vlaams-Brabant 3300",
    "addr:housenumber":"5",
    "addr:postcode":"3300",
    "addr:street":"Berge\u0301Vest",
    "iso:country":"BE",
    "sg:address":"Berg\u00e9vest 5",
    "sg:city":"Tienen",
    "sg:classifiers":[
        {
            "category":"Real Estate",
            "subcategory":"Architect",
            "type":"Services"
        }
    ],
    "sg:phone":"+32 16 82 48 04",
    "sg:postcode":"3300",
    "sg:province":"Vlaams-Brabant",
    "wof:name":"Bricteux D",
    "wof:placetype":"venue"
},
  "geometry": {"coordinates":[4.9466872215,50.8045310974],"type":"Point"}
}