{
  "type": "Feature",
  "properties": {
    "addr:full":"Heerbaan 43 Londerzeel (steenhuffel) Vlaams-Brabant 1840",
    "addr:housenumber":"43",
    "addr:postcode":"1840",
    "addr:street":"Heerbaan",
    "iso:country":"BE",
    "sg:address":"Heerbaan 43",
    "sg:city":"Londerzeel (steenhuffel)",
    "sg:classifiers":[
        {
            "category":"Real Estate",
            "subcategory":"Architect",
            "type":"Services"
        }
    ],
    "sg:phone":"+32 52 30 58 45",
    "sg:postcode":"1840",
    "sg:province":"Vlaams-Brabant",
    "wof:name":"De Schouwer B",
    "wof:placetype":"venue"
},
  "geometry": {"coordinates":[4.2590761185,50.99010849],"type":"Point"}
}