{
  "type": "Feature",
  "properties": {
    "iso:country":"BE",
    "sg:address":"Sint-katelijnestraat 60",
    "sg:city":"Mechelen",
    "sg:orig_category":"Kapsalons",
    "sg:phone":"+32 15 21 69 73",
    "sg:postcode":"2800",
    "sg:province":"Antwerpen",
    "wof:name":"Coiffure Harze",
    "wof:placetype":"venue"
},
  "geometry": {"coordinates":[4.4763150215,51.0309753418],"type":"Point"}
}