{
  "type": "Feature",
  "properties": {
    "addr:full":"Rue De La Station 1 Seraing Li\u00e8ge 4101",
    "addr:housenumber":"1",
    "addr:postcode":"4101",
    "addr:street":"Rue De La Station",
    "iso:country":"BE",
    "sg:address":"Rue De La Station 1",
    "sg:city":"Seraing",
    "sg:classifiers":[
        {
            "category":"Food & Beverages",
            "subcategory":"Fruits & Vegetables",
            "type":"Retail Goods"
        }
    ],
    "sg:phone":"+32 4 234 40 20",
    "sg:postcode":"4101",
    "sg:province":"Li\u00e8ge",
    "sg:tags":[
        "groenten"
    ],
    "wof:name":"Maison L'etal",
    "wof:placetype":"venue"
},
  "geometry": {"coordinates":[5.5005230904,50.6147651672],"type":"Point"}
}