{
  "type": "Feature",
  "properties": {
    "iso:country":"BE",
    "sg:address":"Avenue Paul-henri Spaak 29",
    "sg:city":"Sint-gillis/saint-gilles",
    "sg:classifiers":[
        {
            "category":"Insurance",
            "subcategory":"Life Insurance",
            "type":"Services"
        }
    ],
    "sg:phone":"+32 2 523 12 30",
    "sg:postcode":"1060",
    "sg:province":"Bruxelles-Capitale",
    "sg:tags":[
        "assurance"
    ],
    "wof:name":"Comptoir D'assurances",
    "wof:placetype":"venue"
},
  "geometry": {"coordinates":[4.3366851807,50.8380775452],"type":"Point"}
}