{
  "type": "Feature",
  "properties": {
    "iso:country":"BE",
    "sg:address":"Rue Sankt-roch 11",
    "sg:city":"Plombieres",
    "sg:orig_category":"Kapsalons",
    "sg:phone":"+32 87 78 49 10",
    "sg:postcode":"4850",
    "sg:province":"Li\u00e8ge",
    "wof:name":"Coiffure Schoonbroodt",
    "wof:placetype":"venue"
},
  "geometry": {"coordinates":[5.9555931091,50.7241706848],"type":"Point"}
}