{
  "type": "Feature",
  "properties": {
    "addr:full":"Steylsstraat 119 Brussel/bruxelles Bruxelles-Capitale 1020",
    "addr:housenumber":"119",
    "addr:postcode":"1020",
    "addr:street":"Steylsstraat;/",
    "iso:country":"BE",
    "sg:address":"Steylsstraat 119",
    "sg:city":"Brussel/bruxelles",
    "sg:orig_category":"Dranken",
    "sg:phone":"+32 2 423 71 11",
    "sg:postcode":"1020",
    "sg:province":"Bruxelles-Capitale",
    "wof:name":"Fourcroy-renglet",
    "wof:placetype":"venue"
},
  "geometry": {"coordinates":[4.3397798538,50.8791732788],"type":"Point"}
}