{
  "type": "Feature",
  "properties": {
    "iso:country":"BE",
    "sg:address":"Bilkske 63",
    "sg:city":"Brugge",
    "sg:orig_category":"Drukkerijen and copyshops",
    "sg:phone":"+32 50 33 71 14",
    "sg:postcode":"8000",
    "sg:province":"West-Vlaanderen",
    "wof:name":"Fernand Vanhulle",
    "wof:placetype":"venue"
},
  "geometry": {"coordinates":[3.2371509075,51.208530426],"type":"Point"}
}