{
  "type": "Feature",
  "properties": {
    "iso:country":"BE",
    "sg:address":"Rue Haut Baty 41",
    "sg:city":"Sambreville (arsimont)",
    "sg:classifiers":[
        {
            "category":"Health Services",
            "subcategory":"Doctor",
            "type":"Services"
        }
    ],
    "sg:phone":"+32 71 74 17 90",
    "sg:postcode":"5060",
    "sg:province":"Namur",
    "sg:tags":[
        "medicinephysicians",
        "surgeon"
    ],
    "wof:name":"Hubert Michel",
    "wof:placetype":"venue"
},
  "geometry": {"coordinates":[4.6460199356,50.4287261963],"type":"Point"}
}