{
  "type": "Feature",
  "properties": {
    "iso:country":"BE",
    "sg:address":"Rue Des Bruy\u00c8res 148",
    "sg:city":"Mons",
    "sg:orig_category":"Marketingbureaus Marktonderzoekbureaus",
    "sg:phone":"+32 65 31 88 63",
    "sg:postcode":"7034",
    "sg:province":"Hainaut",
    "wof:name":"Publi Marketing",
    "wof:placetype":"venue"
},
  "geometry": {"coordinates":[4.0086159706,50.4765396118],"type":"Point"}
}