{
  "type": "Feature",
  "properties": {
    "iso:country":"BE",
    "sg:address":"Aachener Strasse 59",
    "sg:city":"Eupen",
    "sg:classifiers":[
        {
            "category":"Building & Trades",
            "subcategory":"Construction",
            "type":"Services"
        }
    ],
    "sg:phone":"+32 87 55 57 35",
    "sg:postcode":"4700",
    "sg:province":"Li\u00e8ge",
    "sg:tags":[
        "installation",
        "-",
        "central",
        "heating"
    ],
    "wof:name":"Henotherm",
    "wof:placetype":"venue"
},
  "geometry": {"coordinates":[6.0337371826,50.6336364746],"type":"Point"}
}