{
  "type": "Feature",
  "properties": {
    "iso:country":"BE",
    "sg:address":"Busbekestraat 20",
    "sg:city":"Menen",
    "sg:orig_category":"Etablissements Erotiques",
    "sg:phone":"+32 56 53 18 43",
    "sg:postcode":"8930",
    "sg:province":"West-Vlaanderen",
    "wof:name":"Bar Cap D'agde",
    "wof:placetype":"venue"
},
  "geometry": {"coordinates":[3.0950500965,50.7823600769],"type":"Point"}
}