{
  "type": "Feature",
  "properties": {
    "addr:full":"Rodt 117 Sankt Vith/saint-vith Li\u00e8ge 4784",
    "addr:housenumber":"117",
    "addr:postcode":"4784",
    "addr:street":"Rodt",
    "iso:country":"BE",
    "sg:address":"Rodt 117",
    "sg:city":"Sankt Vith/saint-vith",
    "sg:orig_category":"Eleveurs de bovins",
    "sg:phone":"+32 80 22 70 27",
    "sg:postcode":"4784",
    "sg:province":"Li\u00e8ge",
    "wof:name":"Heribert Arens",
    "wof:placetype":"venue"
},
  "geometry": {"coordinates":[6.0675911903,50.2596511841],"type":"Point"}
}