{
  "type": "Feature",
  "properties": {
    "iso:country":"BE",
    "sg:address":"Molenstraat 7",
    "sg:city":"Evergem (ertvelde)",
    "sg:classifiers":[
        {
            "category":"Health Services",
            "subcategory":"Health Practitioner",
            "type":"Services"
        }
    ],
    "sg:phone":"+32 9 344 92 15",
    "sg:postcode":"9940",
    "sg:province":"Oost-Vlaanderen",
    "sg:tags":[
        "physiotherapist"
    ],
    "wof:name":"Honor\u00e9 Beatrijs",
    "wof:placetype":"venue"
},
  "geometry": {"coordinates":[3.6737270355,51.1031265259],"type":"Point"}
}