{
  "type": "Feature",
  "properties": {
    "addr:full":"Avenue Louise 193b26 Brussel/bruxelles Bruxelles-Capitale 1050",
    "addr:housenumber":"193b26",
    "addr:postcode":"1050",
    "addr:street":"Avenue Louise;/",
    "iso:country":"BE",
    "sg:address":"Avenue Louise 193b26",
    "sg:city":"Brussel/bruxelles",
    "sg:orig_category":"M\u00e9decins and sp\u00e9cialistes",
    "sg:phone":"+32 2 647 14 01",
    "sg:postcode":"1050",
    "sg:province":"Bruxelles-Capitale",
    "wof:name":"Jacques De Brabandere",
    "wof:placetype":"venue"
},
  "geometry": {"coordinates":[4.355919838,50.8357810974],"type":"Point"}
}