{
  "type": "Feature",
  "properties": {
    "iso:country":"BE",
    "sg:address":"Rue Miville 4",
    "sg:city":"Seraing (jemeppe-sur-meuse)",
    "sg:classifiers":[
        {
            "category":"Professional",
            "subcategory":"Lawyer & Legal Services",
            "type":"Services"
        }
    ],
    "sg:phone":"+32 4 234 34 22",
    "sg:postcode":"4101",
    "sg:province":"Li\u00e8ge",
    "wof:name":"Horne Gerald",
    "wof:placetype":"venue"
},
  "geometry": {"coordinates":[5.5037307739,50.6172485352],"type":"Point"}
}