{
  "type": "Feature",
  "properties": {
    "iso:country":"BE",
    "sg:address":"Rue Devant Le Bois 12",
    "sg:city":"Paliseul (carlsbourg)",
    "sg:classifiers":[
        {
            "category":"Health Services",
            "subcategory":"Medical Lab",
            "type":"Services"
        }
    ],
    "sg:phone":"+32 61 53 46 03",
    "sg:postcode":"6850",
    "sg:province":"Luxembourg",
    "sg:tags":[
        "laboratory",
        "dental"
    ],
    "wof:name":"Jeunehomme-legrand",
    "wof:placetype":"venue"
},
  "geometry": {"coordinates":[5.0795497894,49.8887176514],"type":"Point"}
}