{
  "type": "Feature",
  "properties": {
    "addr:full":"Rue De L'eglise 11 Estaimpuis Hainaut 7730",
    "addr:housenumber":"11",
    "addr:postcode":"7730",
    "addr:street":"Rue De L'Eglise;Hainaut",
    "iso:country":"BE",
    "sg:address":"Rue De L'eglise 11",
    "sg:city":"Estaimpuis",
    "sg:orig_category":"Enseignement maternel and primaire",
    "sg:phone":"+32 56 48 85 85",
    "sg:postcode":"7730",
    "sg:province":"Hainaut",
    "wof:name":"Ecole Matern. Communale",
    "wof:placetype":"venue"
},
  "geometry": {"coordinates":[3.2633109093,50.7064819336],"type":"Point"}
}