{
  "type": "Feature",
  "properties": {
    "iso:country":"BE",
    "sg:address":"Dendermondesteenweg 661",
    "sg:city":"Destelbergen",
    "sg:classifiers":[
        {
            "category":"Retail",
            "subcategory":"Auto Repair",
            "type":"Services"
        }
    ],
    "sg:phone":"+32 9 228 22 69",
    "sg:postcode":"9070",
    "sg:province":"Oost-Vlaanderen",
    "sg:tags":[
        "garage"
    ],
    "wof:name":"Van Poucke Garage Bvba",
    "wof:placetype":"venue"
},
  "geometry": {"coordinates":[3.8097980022,51.0577850342],"type":"Point"}
}