{
  "type": "Feature",
  "properties": {
    "iso:country":"BE",
    "sg:address":"Steenweg Naar Halle 10",
    "sg:city":"Beersel (alsemberg)",
    "sg:classifiers":[
        {
            "category":"Shopping",
            "subcategory":"Crafts & Fabrics",
            "type":"Retail Goods"
        }
    ],
    "sg:phone":"+32 2 381 28 85",
    "sg:postcode":"1652",
    "sg:province":"Vlaams-Brabant",
    "sg:tags":[
        "plant",
        "flower",
        "artificial"
    ],
    "wof:name":"Folium",
    "wof:placetype":"venue"
},
  "geometry": {"coordinates":[4.3242602348,50.7340583801],"type":"Point"}
}