{
  "type": "Feature",
  "properties": {
    "addr:full":"Akkerlaan 12 Schoten Antwerpen 2900",
    "addr:housenumber":"12",
    "addr:postcode":"2900",
    "addr:street":"Akkerlaan",
    "iso:country":"BE",
    "sg:address":"Akkerlaan 12",
    "sg:city":"Schoten",
    "sg:orig_category":"Charpentes and couvertures",
    "sg:phone":"+32 3 658 11 27",
    "sg:postcode":"2900",
    "sg:province":"Antwerpen",
    "wof:name":"Schotense Dakwerken",
    "wof:placetype":"venue"
},
  "geometry": {"coordinates":[4.5081181526,51.2475013733],"type":"Point"}
}