{
  "type": "Feature",
  "properties": {
    "addr:full":"Avenue Reine Astrid 122 Verviers Li\u00e8ge 4802",
    "addr:housenumber":"122",
    "addr:postcode":"4802",
    "addr:street":"Avenue Reine Astrid",
    "iso:country":"BE",
    "sg:address":"Avenue Reine Astrid 122",
    "sg:city":"Verviers",
    "sg:orig_category":"Pharmaciens",
    "sg:phone":"+32 87 22 02 04",
    "sg:postcode":"4802",
    "sg:province":"Li\u00e8ge",
    "wof:name":"Pharmacie Populaire",
    "wof:placetype":"venue"
},
  "geometry": {"coordinates":[5.8828988075,50.5846061707],"type":"Point"}
}