{
  "type": "Feature",
  "properties": {
    "addr:full":"Lakenmeerstraat 6 Nazareth Oost-Vlaanderen 9810",
    "addr:housenumber":"6",
    "addr:postcode":"9810",
    "addr:street":"Lakenmeerstraat",
    "iso:country":"BE",
    "sg:address":"Lakenmeerstraat 6",
    "sg:city":"Nazareth",
    "sg:classifiers":[
        {
            "category":"Personal",
            "subcategory":"Beauty Salon",
            "type":"Services"
        }
    ],
    "sg:phone":"+32 9 385 71 56",
    "sg:postcode":"9810",
    "sg:province":"Oost-Vlaanderen",
    "sg:tags":[
        "de",
        "coiffure"
    ],
    "wof:name":"Edmond Devos",
    "wof:placetype":"venue"
},
  "geometry": {"coordinates":[3.639952898,50.9718933105],"type":"Point"}
}