{
  "type": "Feature",
  "properties": {
    "addr:full":"Kattestraat 15 Merchtem Vlaams-Brabant 1785",
    "addr:housenumber":"15",
    "addr:postcode":"1785",
    "addr:street":"Kattestraat",
    "iso:country":"BE",
    "sg:address":"Kattestraat 15",
    "sg:city":"Merchtem",
    "sg:orig_category":"Artsen and specialisten",
    "sg:phone":"+32 52 37 43 06",
    "sg:postcode":"1785",
    "sg:province":"Vlaams-Brabant",
    "wof:name":"F. Van Hove",
    "wof:placetype":"venue"
},
  "geometry": {"coordinates":[4.2293081284,50.9602661133],"type":"Point"}
}