{
  "type": "Feature",
  "properties": {
    "iso:country":"BE",
    "sg:address":"Vaart Zuid 39",
    "sg:city":"Beernem (sint-joris)",
    "sg:classifiers":[
        {
            "category":"Retail",
            "subcategory":"Auto Rental",
            "type":"Services"
        }
    ],
    "sg:phone":"+32 50 79 25 28",
    "sg:postcode":"8730",
    "sg:province":"West-Vlaanderen",
    "sg:tags":[
        "automobile",
        "-",
        "car",
        "self-drive"
    ],
    "wof:name":"Pjp",
    "wof:placetype":"venue"
},
  "geometry": {"coordinates":[3.3660979271,51.1285095215],"type":"Point"}
}