{
  "type": "Feature",
  "properties": {
    "addr:full":"Decoenestraat 8 Zwalm Oost-Vlaanderen 9630",
    "addr:housenumber":"8",
    "addr:postcode":"9630",
    "addr:street":"Decoenestraat;Oost-Vlaanderen",
    "iso:country":"BE",
    "sg:address":"Decoenestraat 8",
    "sg:city":"Zwalm",
    "sg:orig_category":"Enseignement maternel and primaire",
    "sg:phone":"+32 55 49 81 43",
    "sg:postcode":"9630",
    "sg:province":"Oost-Vlaanderen",
    "wof:name":"Vrije Basisschool",
    "wof:placetype":"venue"
},
  "geometry": {"coordinates":[3.7317240238,50.8781585693],"type":"Point"}
}