{
  "type": "Feature",
  "properties": {
    "iso:country":"BE",
    "sg:address":"Eikenlaan 16",
    "sg:city":"Oudenburg",
    "sg:orig_category":"Gespecialiseerde residenti\u00eble bouw",
    "sg:phone":"+32 59 26 53 76",
    "sg:postcode":"8460",
    "sg:province":"West-Vlaanderen",
    "wof:name":"Geert Grauwet",
    "wof:placetype":"venue"
},
  "geometry": {"coordinates":[3.0023450851,51.1840553284],"type":"Point"}
}