{
  "type": "Feature",
  "properties": {
    "addr:full":"Carton De Wiartlaan 86 Jette Bruxelles-Capitale 1090",
    "addr:housenumber":"86",
    "addr:postcode":"1090",
    "addr:street":"Carton De Wiartlaan",
    "iso:country":"BE",
    "sg:address":"Carton De Wiartlaan 86",
    "sg:city":"Jette",
    "sg:orig_category":"Artsen and specialisten",
    "sg:phone":"+32 2 424 07 18",
    "sg:postcode":"1090",
    "sg:province":"Bruxelles-Capitale",
    "wof:name":"Abdel Benchillal",
    "wof:placetype":"venue"
},
  "geometry": {"coordinates":[4.3297581673,50.8676719666],"type":"Point"}
}