{
  "type": "Feature",
  "properties": {
    "iso:country":"BE",
    "sg:address":"Zwaluwenlaan 37",
    "sg:city":"Aartselaar",
    "sg:orig_category":"Beautyfarms, relaxatie and lichamelijk welzijn Diverse voedingsmiddelen Gh Schoonheidssalons",
    "sg:phone":"+32 3 887 22 12",
    "sg:postcode":"2630",
    "sg:province":"Antwerpen",
    "wof:name":"Instituut Corinne",
    "wof:placetype":"venue"
},
  "geometry": {"coordinates":[4.3845100403,51.1290130615],"type":"Point"}
}