{
  "type": "Feature",
  "properties": {
    "addr:full":"Van Putlei 75 Lint Antwerpen 2547",
    "addr:housenumber":"75",
    "addr:postcode":"2547",
    "iso:country":"BE",
    "sg:address":"Van Putlei 75",
    "sg:city":"Lint",
    "sg:classifiers":[
        {
            "category":"Health Services",
            "subcategory":"Dentist",
            "type":"Services"
        }
    ],
    "sg:phone":"+32 3 455 81 16",
    "sg:postcode":"2547",
    "sg:province":"Antwerpen",
    "wof:name":"Peeters M",
    "wof:placetype":"venue"
},
  "geometry": {"coordinates":[4.4885091782,51.1276664734],"type":"Point"}
}