{
  "type": "Feature",
  "properties": {
    "addr:full":"Place Renan 4b Saint-nicolas (montegn\u00e9e) Li\u00e8ge 4420",
    "addr:housenumber":"4b",
    "addr:postcode":"4420",
    "addr:street":"Place Renan;Montegne\u0301E",
    "iso:country":"BE",
    "sg:address":"Place Renan 4b",
    "sg:city":"Saint-nicolas (montegn\u00e9e)",
    "sg:classifiers":[
        {
            "category":"Real Estate",
            "subcategory":"Real Estate Services",
            "type":"Services"
        }
    ],
    "sg:phone":"+32 4 235 62 14",
    "sg:postcode":"4420",
    "sg:province":"Li\u00e8ge",
    "wof:name":"Agial Immobilier",
    "wof:placetype":"venue"
},
  "geometry": {"coordinates":[5.5194220543,50.6308326721],"type":"Point"}
}