{
  "type": "Feature",
  "properties": {
    "addr:full":"Route De La Basse Sambre 0 Charleroi Hainaut 6061",
    "addr:housenumber":"0",
    "addr:postcode":"6061",
    "addr:street":"Route De La Basse Sambre;Hainaut",
    "iso:country":"BE",
    "sg:address":"Route De La Basse Sambre 0",
    "sg:city":"Charleroi",
    "sg:classifiers":[
        {
            "category":"Travel",
            "subcategory":"Hotels & Motels",
            "type":"Entertainment"
        }
    ],
    "sg:phone":"+32 71 42 01 68",
    "sg:postcode":"6061",
    "sg:province":"Hainaut",
    "sg:tags":[
        "restaurant"
    ],
    "wof:name":"H\u00d4tel Les Balladins",
    "wof:placetype":"venue"
},
  "geometry": {"coordinates":[4.4582672119,50.416557312],"type":"Point"}
}