{
  "type": "Feature",
  "properties": {
    "addr:full":"Hoekstraat 2 Bevel Antwerpen 2560",
    "addr:housenumber":"2",
    "addr:postcode":"2560",
    "addr:street":"Hoekstraat",
    "iso:country":"BE",
    "sg:address":"Hoekstraat 2",
    "sg:city":"Bevel",
    "sg:orig_category":"Loodgieterij, verwarming and sanitaire installaties",
    "sg:phone":"+32 3 481 88 48",
    "sg:postcode":"2560",
    "sg:province":"Antwerpen",
    "wof:name":"C.v.k.",
    "wof:placetype":"venue"
},
  "geometry": {"coordinates":[4.6866059303,51.1421585083],"type":"Point"}
}