{
  "type": "Feature",
  "properties": {
    "iso:country":"BE",
    "sg:address":"Bergstraat 129",
    "sg:city":"Heist-op-den-berg",
    "sg:orig_category":"Antiek Meubelzaken, woning- and keukeninrichting",
    "sg:phone":"+32 15 24 12 99",
    "sg:postcode":"2220",
    "sg:province":"Antwerpen",
    "wof:name":"Jonny Brems",
    "wof:placetype":"venue"
},
  "geometry": {"coordinates":[4.7188138962,51.0766830444],"type":"Point"}
}