{
  "type": "Feature",
  "properties": {
    "addr:full":"Groenstraat 102 Herent Vlaams-Brabant 3020",
    "addr:housenumber":"102",
    "addr:postcode":"3020",
    "addr:street":"Groenstraat",
    "iso:country":"BE",
    "sg:address":"Groenstraat 102",
    "sg:city":"Herent",
    "sg:classifiers":[
        {
            "category":"Professional",
            "subcategory":"Detective & Security Services",
            "type":"Services"
        }
    ],
    "sg:phone":"+32 16 48 94 98",
    "sg:postcode":"3020",
    "sg:province":"Vlaams-Brabant",
    "sg:tags":[
        "fab",
        "de",
        "travail",
        "v\u00eatements",
        "protection"
    ],
    "wof:name":"A.c. Ronsmans",
    "wof:placetype":"venue"
},
  "geometry": {"coordinates":[4.6599397659,50.9282112122],"type":"Point"}
}