{
  "type": "Feature",
  "properties": {
    "iso:country":"BE",
    "sg:address":"Baron Arthur Verhaegenlaan 49",
    "sg:city":"Merelbeke",
    "sg:classifiers":[
        {
            "category":"Building & Trades",
            "subcategory":"Construction",
            "type":"Services"
        }
    ],
    "sg:phone":"+32 9 230 31 52",
    "sg:postcode":"9820",
    "sg:province":"Oost-Vlaanderen",
    "sg:tags":[
        "carpenter"
    ],
    "wof:name":"De Loore Raf Bvba",
    "wof:placetype":"venue"
},
  "geometry": {"coordinates":[3.7522659302,50.9982643127],"type":"Point"}
}