{
  "type": "Feature",
  "properties": {
    "addr:full":"Doornzele Dries 156 Evergem Oost-Vlaanderen 9940",
    "addr:housenumber":"156",
    "addr:postcode":"9940",
    "addr:street":"Dries;Oost-Vlaanderen",
    "iso:country":"BE",
    "sg:address":"Doornzele Dries 156",
    "sg:city":"Evergem",
    "sg:orig_category":"Loodgieterij, verwarming and sanitaire installaties",
    "sg:phone":"+32 9 253 77 44",
    "sg:postcode":"9940",
    "sg:province":"Oost-Vlaanderen",
    "wof:name":"Van Hautem-dernicourt",
    "wof:placetype":"venue"
},
  "geometry": {"coordinates":[3.7729930878,51.1442451477],"type":"Point"}
}