{
  "type": "Feature",
  "properties": {
    "iso:country":"BE",
    "sg:address":"Zeedijk 629",
    "sg:city":"Knokke-heist",
    "sg:orig_category":"Beheer onroerend goed Immobili\u00ebnkantoren Projectontwikkelaars Vakantiehuizen",
    "sg:phone":"+32 50 60 34 71",
    "sg:postcode":"8300",
    "sg:province":"West-Vlaanderen",
    "wof:name":"Immo Melkert",
    "wof:placetype":"venue"
},
  "geometry": {"coordinates":[3.287694931,51.3467254639],"type":"Point"}
}