{
  "type": "Feature",
  "properties": {
    "addr:full":"Rue Du Culot 60 Perwez Brabant Wallon 1360",
    "addr:housenumber":"60",
    "addr:postcode":"1360",
    "addr:street":"Rue Du Culot",
    "iso:country":"BE",
    "sg:address":"Rue Du Culot 60",
    "sg:city":"Perwez",
    "sg:orig_category":"Dierenartsen",
    "sg:phone":"+32 81 65 52 38",
    "sg:postcode":"1360",
    "sg:province":"Brabant Wallon",
    "wof:name":"Michel Jandrain",
    "wof:placetype":"venue"
},
  "geometry": {"coordinates":[4.785577774,50.6378326416],"type":"Point"}
}