{
  "type": "Feature",
  "properties": {
    "iso:country":"BE",
    "sg:address":"Onafhankelijkheidstraat 51",
    "sg:city":"Sint-jans-molenbeek/molenbeek-saint-jean",
    "sg:orig_category":"Dakwerken",
    "sg:phone":"+32 2 410 05 90",
    "sg:postcode":"1080",
    "sg:province":"Bruxelles-Capitale",
    "wof:name":"Dekkers/socobra",
    "wof:placetype":"venue"
},
  "geometry": {"coordinates":[4.3314070702,50.8515167236],"type":"Point"}
}