{
  "type": "Feature",
  "properties": {
    "addr:full":"Avenue Reine Astrid 4-6 Wavre Brabant Wallon 1300",
    "addr:housenumber":"4-6;1300",
    "addr:street":"Avenue Reine Astrid",
    "iso:country":"BE",
    "sg:address":"Avenue Reine Astrid 4-6",
    "sg:city":"Wavre",
    "sg:orig_category":"Bagage and lederwaren Schoenen Sport- and kampeermateriaal",
    "sg:phone":"+32 10 24 62 41",
    "sg:postcode":"1300",
    "sg:province":"Brabant Wallon",
    "wof:name":"Brantano",
    "wof:placetype":"venue"
},
  "geometry": {"coordinates":[4.6180968285,50.7151870728],"type":"Point"}
}