{
  "type": "Feature",
  "properties": {
    "addr:full":"Maaseikersteenweg 8 Lanaken Limburg 3620",
    "addr:housenumber":"8",
    "addr:postcode":"3620",
    "addr:street":"Maaseikersteenweg",
    "iso:country":"BE",
    "sg:address":"Maaseikersteenweg 8",
    "sg:city":"Lanaken",
    "sg:classifiers":[
        {
            "category":"Cafe",
            "type":"Food & Drink"
        }
    ],
    "sg:phone":"+32 89 71 40 37",
    "sg:postcode":"3620",
    "sg:province":"Limburg",
    "sg:tags":[
        "caf\u00e9s"
    ],
    "wof:name":"Caf\u00c9 Gondarina",
    "wof:placetype":"venue"
},
  "geometry": {"coordinates":[5.6733198166,50.8823890686],"type":"Point"}
}