{
  "type": "Feature",
  "properties": {
    "addr:full":"Chauss\u00c9e De Dinant 108 Profondeville Namur 5170",
    "addr:housenumber":"108",
    "addr:postcode":"5170",
    "addr:street":"Chausse\u0301E De Dinant",
    "iso:country":"BE",
    "sg:address":"Chauss\u00c9e De Dinant 108",
    "sg:city":"Profondeville",
    "sg:orig_category":"Herstellingen and onderhoud van auto's Voertuigen",
    "sg:phone":"+32 81 41 16 51",
    "sg:postcode":"5170",
    "sg:province":"Namur",
    "wof:name":"Garage Gautot",
    "wof:placetype":"venue"
},
  "geometry": {"coordinates":[4.8711299896,50.3652572632],"type":"Point"}
}