{
  "type": "Feature",
  "properties": {
    "iso:country":"BE",
    "sg:address":"Ambachtsstraat 18",
    "sg:city":"Mol",
    "sg:orig_category":"Protection civile",
    "sg:phone":"+32 14 33 74 41",
    "sg:postcode":"2400",
    "sg:province":"Antwerpen",
    "wof:name":"Brandweerkazerne",
    "wof:placetype":"venue"
},
  "geometry": {"coordinates":[5.0982117653,51.1901016235],"type":"Point"}
}