{
  "type": "Feature",
  "properties": {
    "addr:full":"Spoorwegstraat 3 Sint-truiden Limburg 3800",
    "addr:housenumber":"3",
    "addr:postcode":"3800",
    "addr:street":"Spoorwegstraat",
    "iso:country":"BE",
    "sg:address":"Spoorwegstraat 3",
    "sg:city":"Sint-truiden",
    "sg:classifiers":[
        {
            "category":"Professional",
            "type":"Services"
        }
    ],
    "sg:phone":"+32 11 68 24 79",
    "sg:postcode":"3800",
    "sg:province":"Limburg",
    "sg:tags":[
        "surveyor",
        "-",
        "valuer"
    ],
    "wof:name":"Radoux R",
    "wof:placetype":"venue"
},
  "geometry": {"coordinates":[5.1795129776,50.8194961548],"type":"Point"}
}