{
  "type": "Feature",
  "properties": {
    "addr:full":"Route De Bohon 21 Durbuy Luxembourg 6940",
    "addr:housenumber":"21",
    "addr:postcode":"6940",
    "addr:street":"Route De Bohon",
    "iso:country":"BE",
    "sg:address":"Route De Bohon 21",
    "sg:city":"Durbuy",
    "sg:orig_category":"Organisation de salons, expositions and bourses. Maisons de vacances",
    "sg:phone":"+32 86 21 46 00",
    "sg:postcode":"6940",
    "sg:province":"Luxembourg",
    "wof:name":"R\u00c9sidence Durbuy",
    "wof:placetype":"venue"
},
  "geometry": {"coordinates":[5.475279808,50.3566017151],"type":"Point"}
}