{
  "type": "Feature",
  "properties": {
    "iso:country":"BE",
    "sg:address":"Leuvensesteenweg 195",
    "sg:city":"Kortenberg",
    "sg:orig_category":"Software ontwikkeling and ontwerp",
    "sg:phone":"+32 2 759 30 91",
    "sg:postcode":"3070",
    "sg:province":"Vlaams-Brabant",
    "wof:name":"R.o.c.s.",
    "wof:placetype":"venue"
},
  "geometry": {"coordinates":[4.5319390297,50.8851394653],"type":"Point"}
}