{
  "type": "Feature",
  "properties": {
    "addr:full":"Prinsenstraat 5 Turnhout Antwerpen 2300",
    "addr:housenumber":"5",
    "addr:postcode":"2300",
    "addr:street":"Prinsenstraat",
    "iso:country":"BE",
    "sg:address":"Prinsenstraat 5",
    "sg:city":"Turnhout",
    "sg:classifiers":[
        {
            "category":"Insurance",
            "subcategory":"Insurance Agent",
            "type":"Services"
        }
    ],
    "sg:phone":"+32 14 43 98 98",
    "sg:postcode":"2300",
    "sg:province":"Antwerpen",
    "sg:tags":[
        "broker"
    ],
    "wof:name":"Zakenkantoor Frank Dielis Bvba",
    "wof:placetype":"venue"
},
  "geometry": {"coordinates":[4.9331932068,51.3217544556],"type":"Point"}
}