{
  "type": "Feature",
  "properties": {
    "iso:country":"BE",
    "sg:address":"Haringrodestraat 49",
    "sg:city":"Antwerpen",
    "sg:classifiers":[
        {
            "category":"Communications",
            "type":"Services"
        }
    ],
    "sg:phone":"+32 3 239 51 78",
    "sg:postcode":"2018",
    "sg:province":"Antwerpen",
    "sg:tags":[
        "translator"
    ],
    "wof:name":"Solignac B",
    "wof:placetype":"venue"
},
  "geometry": {"coordinates":[4.4155569077,51.2019844055],"type":"Point"}
}