{
  "type": "Feature",
  "properties": {
    "addr:full":"Hogebrugstraat 6 Vleteren West-Vlaanderen 8640",
    "addr:housenumber":"6",
    "addr:postcode":"8640",
    "addr:street":"Hogebrugstraat",
    "iso:country":"BE",
    "sg:address":"Hogebrugstraat 6",
    "sg:city":"Vleteren",
    "sg:orig_category":"Herstellingen and onderhoud van auto's",
    "sg:phone":"+32 57 40 07 61",
    "sg:postcode":"8640",
    "sg:province":"West-Vlaanderen",
    "wof:name":"Maurice Cuvelier Wily",
    "wof:placetype":"venue"
},
  "geometry": {"coordinates":[2.7311410904,50.9280853271],"type":"Point"}
}