{
  "type": "Feature",
  "properties": {
    "addr:full":"Hendrik Heymanplein 108 Sint-niklaas Oost-Vlaanderen 9100",
    "addr:housenumber":"108",
    "addr:postcode":"9100",
    "iso:country":"BE",
    "sg:address":"Hendrik Heymanplein 108",
    "sg:city":"Sint-niklaas",
    "sg:orig_category":"Foto-uitrusting",
    "sg:phone":"+32 3 777 82 50",
    "sg:postcode":"9100",
    "sg:province":"Oost-Vlaanderen",
    "wof:name":"Huis Bastiaens",
    "wof:placetype":"venue"
},
  "geometry": {"coordinates":[4.1414909363,51.1618843079],"type":"Point"}
}