{
  "type": "Feature",
  "properties": {
    "addr:full":"Ilsestraat 81 Westerlo Antwerpen 2260",
    "addr:housenumber":"81",
    "addr:postcode":"2260",
    "addr:street":"Ilsestraat",
    "iso:country":"BE",
    "sg:address":"Ilsestraat 81",
    "sg:city":"Westerlo",
    "sg:orig_category":"Rundveehouders",
    "sg:phone":"+32 14 26 56 33",
    "sg:postcode":"2260",
    "sg:province":"Antwerpen",
    "wof:name":"Maria Pauwels",
    "wof:placetype":"venue"
},
  "geometry": {"coordinates":[4.8877129555,51.1356315613],"type":"Point"}
}