{
  "type": "Feature",
  "properties": {
    "addr:full":"Rue Sainte-anne 25 Fleurus Hainaut 6220",
    "addr:housenumber":"25",
    "addr:postcode":"6220",
    "addr:street":"Rue Sainte-Anne",
    "iso:country":"BE",
    "sg:address":"Rue Sainte-anne 25",
    "sg:city":"Fleurus",
    "sg:orig_category":"Articles de sport, camping and jouets Gr",
    "sg:phone":"+32 71 81 50 76",
    "sg:postcode":"6220",
    "sg:province":"Hainaut",
    "wof:name":"Cado-mattei",
    "wof:placetype":"venue"
},
  "geometry": {"coordinates":[4.5524711609,50.4819145203],"type":"Point"}
}