{
  "type": "Feature",
  "properties": {
    "addr:full":"Dr\u00e8ve D'ormes 25 Braives Li\u00e8ge 4260",
    "addr:housenumber":"25",
    "addr:postcode":"4260",
    "addr:street":"Dre\u0300Ve D'Ormes",
    "iso:country":"BE",
    "sg:address":"Dr\u00e8ve D'ormes 25",
    "sg:city":"Braives",
    "sg:classifiers":[
        {
            "category":"Health Services",
            "subcategory":"Health Practitioner",
            "type":"Services"
        }
    ],
    "sg:phone":"+32 19 69 97 90",
    "sg:postcode":"4260",
    "sg:province":"Li\u00e8ge",
    "sg:tags":[
        "physiotherapist"
    ],
    "wof:name":"Wiliquet D",
    "wof:placetype":"venue"
},
  "geometry": {"coordinates":[5.1404252052,50.6343040466],"type":"Point"}
}