{
  "type": "Feature",
  "properties": {
    "iso:country":"BE",
    "sg:address":"Rue Zeecrabbe 30",
    "sg:city":"Bruxelles (uccle)",
    "sg:classifiers":[
        {
            "category":"Professional",
            "subcategory":"Accounting & Tax Preparation",
            "type":"Services"
        }
    ],
    "sg:phone":"+32 2 374 30 19",
    "sg:postcode":"1180",
    "sg:province":"Bruxelles-Capitale",
    "sg:tags":[
        "bookkeeper"
    ],
    "wof:name":"Ariel B",
    "wof:placetype":"venue"
},
  "geometry": {"coordinates":[4.3557190895,50.8052253723],"type":"Point"}
}