{
  "type": "Feature",
  "properties": {
    "iso:country":"BE",
    "sg:address":"Ohiostraat 195",
    "sg:city":"Oudenaarde",
    "sg:orig_category":"Epiceries",
    "sg:phone":"+32 55 31 29 86",
    "sg:postcode":"9700",
    "sg:province":"Oost-Vlaanderen",
    "wof:name":"Hilda Clauwaert",
    "wof:placetype":"venue"
},
  "geometry": {"coordinates":[3.6262938976,50.8699378967],"type":"Point"}
}