{
  "type": "Feature",
  "properties": {
    "iso:country":"BE",
    "sg:address":"Lierbaan 2",
    "sg:city":"Putte",
    "sg:classifiers":[
        {
            "category":"Shopping",
            "subcategory":"Clothing, Apparel, & Fashions",
            "type":"Retail Goods"
        }
    ],
    "sg:phone":"+32 15 75 37 62",
    "sg:postcode":"2580",
    "sg:province":"Antwerpen",
    "sg:tags":[
        "lady",
        "clothing",
        "-"
    ],
    "wof:name":"Papo Mode Bvba",
    "wof:placetype":"venue"
},
  "geometry": {"coordinates":[4.6291260719,51.0551300049],"type":"Point"}
}