{
  "type": "Feature",
  "properties": {
    "addr:full":"Louis Melsensstraat 8 Leuven Vlaams-Brabant 3000",
    "addr:housenumber":"8",
    "addr:postcode":"3000",
    "addr:street":"Louis Melsensstraat",
    "iso:country":"BE",
    "sg:address":"Louis Melsensstraat 8",
    "sg:city":"Leuven",
    "sg:classifiers":[
        {
            "category":"Real Estate",
            "subcategory":"Real Estate Services",
            "type":"Services"
        }
    ],
    "sg:phone":"+32 16 22 63 25",
    "sg:postcode":"3000",
    "sg:province":"Vlaams-Brabant",
    "wof:name":"Verimass Leuven Nv",
    "wof:placetype":"venue"
},
  "geometry": {"coordinates":[4.7086858749,50.8808746338],"type":"Point"}
}