{
  "type": "Feature",
  "properties": {
    "iso:country":"BE",
    "sg:address":"Rue L. Mar\u00c9chal 154",
    "sg:city":"Oreye",
    "sg:orig_category":"Boekhouders",
    "sg:phone":"+32 19 67 81 56",
    "sg:postcode":"4360",
    "sg:province":"Li\u00e8ge",
    "wof:name":"Patrick Bessemans",
    "wof:placetype":"venue"
},
  "geometry": {"coordinates":[5.3298149109,50.71824646],"type":"Point"}
}