{
  "type": "Feature",
  "properties": {
    "addr:full":"Grote Baan 114 Hulshout Antwerpen 2235",
    "addr:housenumber":"114",
    "addr:postcode":"2235",
    "addr:street":"Grote Baan",
    "iso:country":"BE",
    "sg:address":"Grote Baan 114",
    "sg:city":"Hulshout",
    "sg:orig_category":"Bagage and lederwaren Schoenen",
    "sg:phone":"+32 15 22 60 29",
    "sg:postcode":"2235",
    "sg:province":"Antwerpen",
    "wof:name":"Scalini Shoes",
    "wof:placetype":"venue"
},
  "geometry": {"coordinates":[4.7901039124,51.0750541687],"type":"Point"}
}