{
  "type": "Feature",
  "properties": {
    "iso:country":"BE",
    "sg:address":"Groeneweg 49ba",
    "sg:city":"Overijse",
    "sg:orig_category":"Producteurs de l\u00e9gumes",
    "sg:phone":"+32 2 687 64 73",
    "sg:postcode":"3090",
    "sg:province":"Vlaams-Brabant",
    "wof:name":"Jozef De Kerk",
    "wof:placetype":"venue"
},
  "geometry": {"coordinates":[4.5438380241,50.787563324],"type":"Point"}
}