{
  "type": "Feature",
  "properties": {
    "addr:full":"Goor 32 Kasterlee Antwerpen 2460",
    "addr:housenumber":"32",
    "addr:postcode":"2460",
    "addr:street":"Goor",
    "iso:country":"BE",
    "sg:address":"Goor 32",
    "sg:city":"Kasterlee",
    "sg:classifiers":[
        {
            "category":"Professional",
            "subcategory":"Accounting & Tax Preparation",
            "type":"Services"
        }
    ],
    "sg:phone":"+32 14 85 15 21",
    "sg:postcode":"2460",
    "sg:province":"Antwerpen",
    "sg:tags":[
        "bookkeeper"
    ],
    "wof:name":"Gijbels R",
    "wof:placetype":"venue"
},
  "geometry": {"coordinates":[4.94683218,51.22423172],"type":"Point"}
}