{
  "type": "Feature",
  "properties": {
    "addr:full":"Haut-v\u00c2 2 Manhay Luxembourg 6960",
    "addr:housenumber":"2",
    "addr:postcode":"6960",
    "addr:street":"Haut-Va\u0302",
    "iso:country":"BE",
    "sg:address":"Haut-v\u00c2 2",
    "sg:city":"Manhay",
    "sg:orig_category":"Herstellingswinkels voor diverse persoonlijke and huishoudartikelen",
    "sg:phone":"+32 86 45 59 41",
    "sg:postcode":"6960",
    "sg:province":"Luxembourg",
    "wof:name":"Couture Wyeme",
    "wof:placetype":"venue"
},
  "geometry": {"coordinates":[5.6754698753,50.291759491],"type":"Point"}
}