{
  "type": "Feature",
  "properties": {
    "addr:full":"Ichtegemstraat 144 Koekelare West-Vlaanderen 8680",
    "addr:housenumber":"144",
    "addr:postcode":"8680",
    "addr:street":"Ichtegemstraat",
    "iso:country":"BE",
    "sg:address":"Ichtegemstraat 144",
    "sg:city":"Koekelare",
    "sg:classifiers":[
        {
            "category":"Social Services",
            "type":"Services"
        }
    ],
    "sg:phone":"+32 51 58 08 85",
    "sg:postcode":"8680",
    "sg:province":"West-Vlaanderen",
    "wof:name":"Weduwen & Weduwenaars West-vlaanderen",
    "wof:placetype":"venue"
},
  "geometry": {"coordinates":[2.9946920872,51.0908317566],"type":"Point"}
}