{
  "type": "Feature",
  "properties": {
    "addr:full":"Laan Van Beethoven 36 Anderlecht (brussel) Bruxelles-Capitale 1070",
    "addr:housenumber":"36",
    "addr:postcode":"1070",
    "addr:street":"Laan Van Beethoven",
    "iso:country":"BE",
    "sg:address":"Laan Van Beethoven 36",
    "sg:city":"Anderlecht (brussel)",
    "sg:classifiers":[
        {
            "category":"Personal",
            "subcategory":"Beauty Salon",
            "type":"Services"
        }
    ],
    "sg:phone":"+32 2 522 29 22",
    "sg:postcode":"1070",
    "sg:province":"Bruxelles-Capitale",
    "sg:tags":[
        "de",
        "coiffure"
    ],
    "wof:name":"Andree",
    "wof:placetype":"venue"
},
  "geometry": {"coordinates":[4.2981090546,50.8296394348],"type":"Point"}
}