{
  "type": "Feature",
  "properties": {
    "iso:country":"BE",
    "sg:address":"Lange Elzenstraat 102",
    "sg:city":"Antwerpen",
    "sg:classifiers":[
        {
            "category":"Health Services",
            "subcategory":"Health Practitioner",
            "type":"Services"
        }
    ],
    "sg:phone":"+32 3 248 17 56",
    "sg:postcode":"2018",
    "sg:province":"Antwerpen",
    "sg:tags":[
        "psychologist"
    ],
    "wof:name":"Cools B",
    "wof:placetype":"venue"
},
  "geometry": {"coordinates":[4.3944292068,51.1990203857],"type":"Point"}
}