{
  "type": "Feature",
  "properties": {
    "addr:full":"Leopold Ii-laan 26b10 Oostende West-Vlaanderen 8400",
    "addr:housenumber":"26b10",
    "addr:postcode":"8400",
    "addr:street":"Leopold Ii-Laan",
    "iso:country":"BE",
    "sg:address":"Leopold Ii-laan 26b10",
    "sg:city":"Oostende",
    "sg:orig_category":"Maisons de vacances. Administration d'immeubles. Agences immobili\u00e8res",
    "sg:phone":"+32 59 50 08 24",
    "sg:postcode":"8400",
    "sg:province":"West-Vlaanderen",
    "wof:name":"Agence Horemans",
    "wof:placetype":"venue"
},
  "geometry": {"coordinates":[2.9129989147,51.2306442261],"type":"Point"}
}