{
  "type": "Feature",
  "properties": {
    "addr:full":"205 Gentse Steenweg 9620 Zottegem 205",
    "addr:housenumber":"205",
    "addr:postcode":"9620;205",
    "addr:street":"Gentse Steenweg",
    "iso:country":"BE",
    "sg:address":"205",
    "sg:city":"Gentse Steenweg 9620 Zottegem",
    "sg:classifiers":[
        {
            "category":"Travel",
            "subcategory":"Hotels & Motels",
            "type":"Entertainment"
        }
    ],
    "sg:phone":"+32 9 360 55 28",
    "sg:postcode":"205",
    "sg:tags":[
        "hotels",
        "business",
        "restaurant"
    ],
    "wof:name":"Van Daele Werner M.",
    "wof:placetype":"venue"
},
  "geometry": {"coordinates":[3.8454051018,50.8647537231],"type":"Point"}
}