{
  "type": "Feature",
  "properties": {
    "addr:full":"Chauss\u00c9e De Wavre 824 Etterbeek/etterbeek Bruxelles-Capitale 1040",
    "addr:housenumber":"824",
    "addr:postcode":"1040",
    "addr:street":"Chausse\u0301E De Wavre",
    "iso:country":"BE",
    "sg:address":"Chauss\u00c9e De Wavre 824",
    "sg:city":"Etterbeek/etterbeek",
    "sg:orig_category":"R\u00e9parations d'horloges, montres and bijoux. Bijouteries and horlogeries",
    "sg:phone":"+32 2 647 44 39",
    "sg:postcode":"1040",
    "sg:province":"Bruxelles-Capitale",
    "wof:name":"Maison Piffet",
    "wof:placetype":"venue"
},
  "geometry": {"coordinates":[4.3929190636,50.8289070129],"type":"Point"}
}