{
  "type": "Feature",
  "properties": {
    "addr:full":"Rue Reine Astrid 51-2 Les Bons Villers (frasnes-lez-gosselies) Hainaut 6210",
    "addr:housenumber":"51-2",
    "addr:postcode":"6210",
    "addr:street":"Rue Reine Astrid",
    "iso:country":"BE",
    "sg:address":"Rue Reine Astrid 51-2",
    "sg:city":"Les Bons Villers (frasnes-lez-gosselies)",
    "sg:classifiers":[
        {
            "category":"Professional",
            "subcategory":"Testing Lab",
            "type":"Services"
        }
    ],
    "sg:phone":"+32 71 85 10 34",
    "sg:postcode":"6210",
    "sg:province":"Hainaut",
    "sg:tags":[
        "chemist"
    ],
    "wof:name":"Pharmacie De La Grande Rue",
    "wof:placetype":"venue"
},
  "geometry": {"coordinates":[4.4511561394,50.5378227234],"type":"Point"}
}