{
  "type": "Feature",
  "properties": {
    "addr:full":"Groenstraat 1 Neerpelt Limburg 3910",
    "addr:housenumber":"1",
    "addr:postcode":"3910",
    "addr:street":"Groenstraat",
    "iso:country":"BE",
    "sg:address":"Groenstraat 1",
    "sg:city":"Neerpelt",
    "sg:classifiers":[
        {
            "category":"Restaurant",
            "type":"Food & Drink"
        }
    ],
    "sg:phone":"+32 11 64 24 12",
    "sg:postcode":"3910",
    "sg:province":"Limburg",
    "wof:name":"Ijssalon Lucca",
    "wof:placetype":"venue"
},
  "geometry": {"coordinates":[5.4340748787,51.228477478],"type":"Point"}
}