{
  "type": "Feature",
  "properties": {
    "addr:full":"Joannes Van Meirhaeghestraat 2 Box 2 Rumst (reet) Antwerpen 2840",
    "addr:housenumber":"2;2",
    "addr:postcode":"2840",
    "addr:street":"Joannes Van Meirhaeghestraat;Box",
    "iso:country":"BE",
    "sg:address":"Joannes Van Meirhaeghestraat 2 Box 2",
    "sg:city":"Rumst (reet)",
    "sg:classifiers":[
        {
            "category":"Banks & Credit Unions",
            "subcategory":"Investment Brokerage",
            "type":"Services"
        }
    ],
    "sg:phone":"+32 3 825 72 76",
    "sg:postcode":"2840",
    "sg:province":"Antwerpen",
    "sg:tags":[
        "fence"
    ],
    "wof:name":"Busschots",
    "wof:placetype":"venue"
},
  "geometry": {"coordinates":[4.411839962,51.1044197083],"type":"Point"}
}