{
  "type": "Feature",
  "properties": {
    "addr:full":"Rue De Su\u00e8de 36 Bruxelles (saint-gilles) Bruxelles-Capitale 1060",
    "addr:housenumber":"36",
    "addr:postcode":"1060",
    "addr:street":"Rue De Sue\u0300De",
    "iso:country":"BE",
    "sg:address":"Rue De Su\u00e8de 36",
    "sg:city":"Bruxelles (saint-gilles)",
    "sg:classifiers":[
        {
            "category":"Real Estate",
            "subcategory":"Architect",
            "type":"Services"
        }
    ],
    "sg:phone":"+32 2 544 06 52",
    "sg:postcode":"1060",
    "sg:province":"Bruxelles-Capitale",
    "wof:name":"Mercier Ch",
    "wof:placetype":"venue"
},
  "geometry": {"coordinates":[4.3386888504,50.8338623047],"type":"Point"}
}