{
  "type": "Feature",
  "properties": {
    "iso:country":"BE",
    "sg:address":"Molenstraat 91b5-6",
    "sg:city":"Eeklo",
    "sg:orig_category":"Boekhouders",
    "sg:phone":"+32 9 377 38 41",
    "sg:postcode":"9900",
    "sg:province":"Oost-Vlaanderen",
    "wof:name":"Alex De Baets",
    "wof:placetype":"venue"
},
  "geometry": {"coordinates":[3.5601599216,51.1873283386],"type":"Point"}
}