{
  "type": "Feature",
  "properties": {
    "addr:full":"Place Du Marais 75c Theux (la Reid) Li\u00e8ge 4910",
    "addr:housenumber":"75c",
    "addr:postcode":"4910",
    "addr:street":"Place Du Marais;La Reid",
    "iso:country":"BE",
    "sg:address":"Place Du Marais 75c",
    "sg:city":"Theux (la Reid)",
    "sg:classifiers":[
        {
            "category":"Retail",
            "subcategory":"Auto Repair",
            "type":"Services"
        }
    ],
    "sg:phone":"+32 87 37 61 15",
    "sg:postcode":"4910",
    "sg:province":"Li\u00e8ge",
    "sg:tags":[
        "garage"
    ],
    "wof:name":"Geoland Sprl",
    "wof:placetype":"venue"
},
  "geometry": {"coordinates":[5.7903251648,50.4895515442],"type":"Point"}
}