{
  "type": "Feature",
  "properties": {
    "addr:full":"Beukenhofstraat 42 Anzegem West-Vlaanderen 8570",
    "addr:housenumber":"42",
    "addr:postcode":"8570",
    "addr:street":"Beukenhofstraat",
    "iso:country":"BE",
    "sg:address":"Beukenhofstraat 42",
    "sg:city":"Anzegem",
    "sg:orig_category":"Openbare veiligheid",
    "sg:phone":"+32 56 77 67 12",
    "sg:postcode":"8570",
    "sg:province":"West-Vlaanderen",
    "wof:name":"Federale Politie",
    "wof:placetype":"venue"
},
  "geometry": {"coordinates":[3.3985850811,50.837184906],"type":"Point"}
}