{
  "type": "Feature",
  "properties": {
    "addr:full":"Vredestraat 15 Box 2 Aalst (erembodegem) Oost-Vlaanderen 9320",
    "addr:housenumber":"15;2",
    "addr:postcode":"9320",
    "addr:street":"Vredestraat;Box",
    "iso:country":"BE",
    "sg:address":"Vredestraat 15 Box 2",
    "sg:city":"Aalst (erembodegem)",
    "sg:classifiers":[
        {
            "category":"Building & Trades",
            "subcategory":"Pest Control",
            "type":"Services"
        }
    ],
    "sg:phone":"+32 53 41 56 80",
    "sg:postcode":"9320",
    "sg:province":"Oost-Vlaanderen",
    "sg:tags":[
        "painting",
        "contractor"
    ],
    "wof:name":"Matthijs Y",
    "wof:placetype":"venue"
},
  "geometry": {"coordinates":[4.0337910652,50.9389419556],"type":"Point"}
}