{
  "type": "Feature",
  "properties": {
    "iso:country":"BE",
    "sg:address":"Parkstraat 31",
    "sg:city":"Kortenberg",
    "sg:orig_category":"Quincailleries",
    "sg:phone":"+32 2 759 57 43",
    "sg:postcode":"3070",
    "sg:province":"Vlaams-Brabant",
    "wof:name":"De Groene Verver",
    "wof:placetype":"venue"
},
  "geometry": {"coordinates":[4.5413661003,50.8898887634],"type":"Point"}
}