{
  "type": "Feature",
  "properties": {
    "addr:full":"Commanster 40 Vielsalm Luxembourg 6690",
    "addr:housenumber":"40",
    "addr:postcode":"6690",
    "addr:street":"Commanster",
    "iso:country":"BE",
    "sg:address":"Commanster 40",
    "sg:city":"Vielsalm",
    "sg:classifiers":[
        {
            "category":"Organizations",
            "subcategory":"Professional Association",
            "type":"Services"
        }
    ],
    "sg:phone":"+32 80 21 45 85",
    "sg:postcode":"6690",
    "sg:province":"Luxembourg",
    "sg:tags":[
        "organisation",
        "seminar"
    ],
    "wof:name":"Centrum Commanster Sprl",
    "wof:placetype":"venue"
},
  "geometry": {"coordinates":[5.9167118073,50.28540802],"type":"Point"}
}