{
  "type": "Feature",
  "properties": {
    "addr:full":"Voskenslaan 292 Gent Oost-Vlaanderen 9000",
    "addr:housenumber":"292",
    "addr:postcode":"9000",
    "addr:street":"Voskenslaan;Oost-Vlaanderen",
    "iso:country":"BE",
    "sg:address":"Voskenslaan 292",
    "sg:city":"Gent",
    "sg:classifiers":[
        {
            "category":"Arts & Performance",
            "subcategory":"Symphony",
            "type":"Entertainment"
        }
    ],
    "sg:phone":"+32 9 221 90 90",
    "sg:postcode":"9000",
    "sg:province":"Oost-Vlaanderen",
    "sg:tags":[
        "orchestra"
    ],
    "wof:name":"Groot Internationaal Orkest",
    "wof:placetype":"venue"
},
  "geometry": {"coordinates":[3.7059259415,51.0305976868],"type":"Point"}
}