{
  "type": "Feature",
  "properties": {
    "iso:country":"BE",
    "sg:address":"Ringlaan 34b234",
    "sg:city":"Kortrijk",
    "sg:orig_category":"Studios photographiques",
    "sg:phone":"+32 56 35 94 96",
    "sg:postcode":"8500",
    "sg:province":"West-Vlaanderen",
    "wof:name":"Portrait Studio's",
    "wof:placetype":"venue"
},
  "geometry": {"coordinates":[3.2646589279,50.8452682495],"type":"Point"}
}