{
  "type": "Feature",
  "properties": {
    "iso:country":"BE",
    "sg:address":"Kempenplein 15",
    "sg:city":"Neerpelt",
    "sg:classifiers":[
        {
            "category":"Shopping",
            "subcategory":"Clothing, Apparel, & Fashions",
            "type":"Retail Goods"
        }
    ],
    "sg:phone":"+32 11 66 14 66",
    "sg:postcode":"3910",
    "sg:province":"Limburg",
    "sg:tags":[
        "boutique"
    ],
    "wof:name":"Bovo",
    "wof:placetype":"venue"
},
  "geometry": {"coordinates":[5.4328331947,51.2285766602],"type":"Point"}
}