{
  "type": "Feature",
  "properties": {
    "addr:full":"Ingooigemplaats 68 Anzegem (ingooigem) West-Vlaanderen 8570",
    "addr:housenumber":"68",
    "addr:postcode":"8570",
    "addr:street":"Ingooigemplaats",
    "iso:country":"BE",
    "sg:address":"Ingooigemplaats 68",
    "sg:city":"Anzegem (ingooigem)",
    "sg:classifiers":[
        {
            "category":"Autos & Motor Vehicles",
            "subcategory":"Fuel & Gas Station",
            "type":"Retail Goods"
        }
    ],
    "sg:phone":"+32 56 77 72 86",
    "sg:postcode":"8570",
    "sg:province":"West-Vlaanderen",
    "wof:name":"Avet K En Co",
    "wof:placetype":"venue"
},
  "geometry": {"coordinates":[3.4280779362,50.8195152283],"type":"Point"}
}