{
  "type": "Feature",
  "properties": {
    "addr:full":"Rue Camille Charlier 10a Namur (flawinne) Namur 5020",
    "addr:housenumber":"10a",
    "addr:postcode":"5020",
    "addr:street":"Rue Camille Charlier",
    "iso:country":"BE",
    "sg:address":"Rue Camille Charlier 10a",
    "sg:city":"Namur (flawinne)",
    "sg:classifiers":[
        {
            "category":"Structure",
            "subcategory":"Office Building",
            "type":"Public Place"
        }
    ],
    "sg:phone":"+32 81 73 73 26",
    "sg:postcode":"5020",
    "sg:province":"Namur",
    "sg:tags":[
        "roofing",
        "slate"
    ],
    "wof:name":"Wynants Guy Et Fils Sprl",
    "wof:placetype":"venue"
},
  "geometry": {"coordinates":[4.7952418327,50.4352035522],"type":"Point"}
}