{
  "type": "Feature",
  "properties": {
    "addr:full":"Rue Th\u00e9ophile De Baisieux 156 Bruxelles Bruxelles-Capitale 1020",
    "addr:housenumber":"156",
    "addr:postcode":"1020",
    "addr:street":"Rue The\u0301Ophile De Baisieux",
    "iso:country":"BE",
    "sg:address":"Rue Th\u00e9ophile De Baisieux 156",
    "sg:city":"Bruxelles",
    "sg:classifiers":[
        {
            "category":"Real Estate",
            "subcategory":"Architect",
            "type":"Services"
        }
    ],
    "sg:phone":"+32 2 478 74 25",
    "sg:postcode":"1020",
    "sg:province":"Bruxelles-Capitale",
    "wof:name":"Dewaele I",
    "wof:placetype":"venue"
},
  "geometry": {"coordinates":[4.3361520767,50.8872070312],"type":"Point"}
}