{
  "type": "Feature",
  "properties": {
    "addr:full":"Belseledorp 20 Sint-niklaas Oost-Vlaanderen 9111",
    "addr:housenumber":"20",
    "addr:postcode":"9111",
    "addr:street":"Belseledorp",
    "iso:country":"BE",
    "sg:address":"Belseledorp 20",
    "sg:city":"Sint-niklaas",
    "sg:orig_category":"Dierenartsen",
    "sg:phone":"+32 3 772 26 66",
    "sg:postcode":"9111",
    "sg:province":"Oost-Vlaanderen",
    "wof:name":"Joris Van Oost",
    "wof:placetype":"venue"
},
  "geometry": {"coordinates":[4.0936899185,51.1464385986],"type":"Point"}
}