{
  "type": "Feature",
  "properties": {
    "addr:full":"Industrieweg 1 Aartselaar Antwerpen 2630",
    "addr:housenumber":"1",
    "addr:postcode":"2630",
    "addr:street":"Industrieweg",
    "iso:country":"BE",
    "sg:address":"Industrieweg 1",
    "sg:city":"Aartselaar",
    "sg:classifiers":[
        {
            "category":"Government",
            "subcategory":"Department Of Motor Vehicles",
            "type":"Public Place"
        }
    ],
    "sg:phone":"+32 3 887 97 21",
    "sg:postcode":"2630",
    "sg:province":"Antwerpen",
    "sg:tags":[
        "equipment",
        "industrial",
        "transport",
        "motor-cars"
    ],
    "wof:name":"Hella Nv",
    "wof:placetype":"venue"
},
  "geometry": {"coordinates":[4.3707637787,51.1315727234],"type":"Point"}
}