{
  "type": "Feature",
  "properties": {
    "iso:country":"BE",
    "sg:address":"Dwarsstraat 44",
    "sg:city":"Denderleeuw",
    "sg:orig_category":"Boissons",
    "sg:phone":"+32 53 66 67 50",
    "sg:postcode":"9470",
    "sg:province":"Oost-Vlaanderen",
    "wof:name":"Xavier Van Bossuyt",
    "wof:placetype":"venue"
},
  "geometry": {"coordinates":[4.0762290955,50.8852882385],"type":"Point"}
}