{
  "type": "Feature",
  "properties": {
    "iso:country":"BE",
    "sg:address":"Rue De La Chapelle 57",
    "sg:city":"Chiny",
    "sg:orig_category":"Rundveehouders",
    "sg:phone":"+32 61 31 28 72",
    "sg:postcode":"6810",
    "sg:province":"Luxembourg",
    "wof:name":"Michel Hankard",
    "wof:placetype":"venue"
},
  "geometry": {"coordinates":[5.4363617897,49.682510376],"type":"Point"}
}