{
  "type": "Feature",
  "properties": {
    "iso:country":"BE",
    "sg:address":"Gustaaf C. De Bruynestr. 1",
    "sg:city":"Lille",
    "sg:orig_category":"Elektrische installaties voor woningen HERSTELLING ELEKTRISCHE HUISHOUDAPPARATEN Huishoudapparaten, ",
    "sg:phone":"+32 14 88 27 25",
    "sg:postcode":"2275",
    "sg:province":"Antwerpen",
    "wof:name":"Harry Proost",
    "wof:placetype":"venue"
},
  "geometry": {"coordinates":[4.8420758247,51.2283973694],"type":"Point"}
}