{
  "type": "Feature",
  "properties": {
    "iso:country":"BE",
    "sg:address":"Moleneinde 13",
    "sg:city":"Lochristi",
    "sg:orig_category":"P\u00e9pini\u00e9ristes",
    "sg:phone":"+32 9 355 27 76",
    "sg:postcode":"9080",
    "sg:province":"Oost-Vlaanderen",
    "wof:name":"Hosna",
    "wof:placetype":"venue"
},
  "geometry": {"coordinates":[3.8575661182,51.1310043335],"type":"Point"}
}