{
  "type": "Feature",
  "properties": {
    "addr:full":"Julius De Geyterstraat 261 Antwerpen Antwerpen 2610",
    "addr:housenumber":"261",
    "addr:postcode":"2610",
    "addr:street":"Julius De Geyterstraat",
    "iso:country":"BE",
    "sg:address":"Julius De Geyterstraat 261",
    "sg:city":"Antwerpen",
    "sg:orig_category":"Sportclubs",
    "sg:phone":"+32 3 828 25 08",
    "sg:postcode":"2610",
    "sg:province":"Antwerpen",
    "wof:name":"H.c. Sasja",
    "wof:placetype":"venue"
},
  "geometry": {"coordinates":[4.3844881058,51.1807441711],"type":"Point"}
}