{
  "type": "Feature",
  "properties": {
    "iso:country":"BE",
    "sg:address":"Menensesteenweg 86",
    "sg:city":"Wervik",
    "sg:orig_category":"Diverse bouwafwerking and reiniging Woningbouw",
    "sg:phone":"+32 56 31 15 35",
    "sg:postcode":"8940",
    "sg:province":"West-Vlaanderen",
    "wof:name":"Carton Freddy",
    "wof:placetype":"venue"
},
  "geometry": {"coordinates":[3.06208992,50.7820320129],"type":"Point"}
}