{
  "type": "Feature",
  "properties": {
    "iso:country":"BE",
    "sg:address":"Rooienkapel 27",
    "sg:city":"Lille",
    "sg:orig_category":"Elektrische installaties voor woningen",
    "sg:phone":"+32 14 55 23 61",
    "sg:postcode":"2275",
    "sg:province":"Antwerpen",
    "wof:name":"Stephan Tuyaerts",
    "wof:placetype":"venue"
},
  "geometry": {"coordinates":[4.881152153,51.2763710022],"type":"Point"}
}