{
  "type": "Feature",
  "properties": {
    "iso:country":"BE",
    "sg:address":"Groenstraat 18",
    "sg:city":"Herselt",
    "sg:orig_category":"M\u00e9decins and sp\u00e9cialistes",
    "sg:phone":"+32 14 54 93 94",
    "sg:postcode":"2230",
    "sg:province":"Antwerpen",
    "wof:name":"M. Van Braeckel",
    "wof:placetype":"venue"
},
  "geometry": {"coordinates":[4.925921917,51.0424919128],"type":"Point"}
}