{
  "type": "Feature",
  "properties": {
    "iso:country":"BE",
    "sg:address":"Heikant 27",
    "sg:city":"Heusden-zolder",
    "sg:orig_category":"GROENTEN AND FRUIT Groenten and fruit Gh",
    "sg:phone":"+32 11 53 68 36",
    "sg:postcode":"3550",
    "sg:province":"Limburg",
    "wof:name":"Fruithal",
    "wof:placetype":"venue"
},
  "geometry": {"coordinates":[5.3024320602,51.0164833069],"type":"Point"}
}