{
  "type": "Feature",
  "properties": {
    "addr:full":"Stasegemsestraat 67 Kortrijk West-Vlaanderen 8500",
    "addr:housenumber":"67",
    "addr:postcode":"8500",
    "addr:street":"Stasegemsestraat",
    "iso:country":"BE",
    "sg:address":"Stasegemsestraat 67",
    "sg:city":"Kortrijk",
    "sg:classifiers":[
        {
            "category":"Shopping",
            "subcategory":"Musical Instruments",
            "type":"Retail Goods"
        }
    ],
    "sg:phone":"+32 56 22 90 62",
    "sg:postcode":"8500",
    "sg:province":"West-Vlaanderen",
    "sg:tags":[
        "-"
    ],
    "wof:name":"Orgelhuis Delobelle",
    "wof:placetype":"venue"
},
  "geometry": {"coordinates":[3.2788159847,50.8315811157],"type":"Point"}
}