{
  "type": "Feature",
  "properties": {
    "iso:country":"BE",
    "sg:address":"Leuerbroekstraat 1082",
    "sg:city":"Kinrooi",
    "sg:orig_category":"SMEEDWERK, METAALBEWERKING AND POEDERMETALLURGIE",
    "sg:phone":"+32 89 70 32 42",
    "sg:postcode":"3640",
    "sg:province":"Limburg",
    "wof:name":"J.segers",
    "wof:placetype":"venue"
},
  "geometry": {"coordinates":[5.7518138885,51.1371650696],"type":"Point"}
}