{
  "type": "Feature",
  "properties": {
    "addr:full":"Ambachtsteenweg 34a Merelbeke Oost-Vlaanderen 9820",
    "addr:housenumber":"34a",
    "addr:postcode":"9820",
    "addr:street":"Ambachtsteenweg",
    "iso:country":"BE",
    "sg:address":"Ambachtsteenweg 34a",
    "sg:city":"Merelbeke",
    "sg:orig_category":"Mat\u00e9riel de T\u00e9l\u00e9communication",
    "sg:phone":"+32 9 272 57 57",
    "sg:postcode":"9820",
    "sg:province":"Oost-Vlaanderen",
    "wof:name":"Agami",
    "wof:placetype":"venue"
},
  "geometry": {"coordinates":[3.7622919083,50.9931678772],"type":"Point"}
}