{
  "type": "Feature",
  "properties": {
    "iso:country":"BE",
    "sg:address":"Diksmuidseweg 342",
    "sg:city":"Boezinge",
    "sg:orig_category":"Royal Canin. Fleurs and plantes. Articles de jardin",
    "sg:phone":"+32 57 42 32 27",
    "sg:postcode":"8904",
    "sg:province":"West-Vlaanderen",
    "wof:name":"Aveve Vandenberghe Frank",
    "wof:placetype":"venue"
},
  "geometry": {"coordinates":[2.8624110222,50.8921661377],"type":"Point"}
}