{
  "type": "Feature",
  "properties": {
    "iso:country":"BE",
    "sg:address":"Rue Du Ch\u00e2teau 23",
    "sg:city":"Renaix",
    "sg:classifiers":[
        {
            "category":"Professional",
            "type":"Services"
        }
    ],
    "sg:phone":"+32 55 21 07 78",
    "sg:postcode":"9600",
    "sg:province":"Oost-Vlaanderen",
    "sg:tags":[
        "entertainer"
    ],
    "wof:name":"Ray Davis",
    "wof:placetype":"venue"
},
  "geometry": {"coordinates":[3.5952680111,50.7472763062],"type":"Point"}
}