{
  "type": "Feature",
  "properties": {
    "iso:country":"BE",
    "sg:address":"Rue De La Concorde 3",
    "sg:city":"La Louviere",
    "sg:classifiers":[
        {
            "category":"Cafe",
            "type":"Food & Drink"
        }
    ],
    "sg:phone":"+32 64 21 59 06",
    "sg:postcode":"7100",
    "sg:province":"Hainaut",
    "sg:tags":[
        "caf\u00e9s"
    ],
    "wof:name":"Les Amis",
    "wof:placetype":"venue"
},
  "geometry": {"coordinates":[4.1883811951,50.479019165],"type":"Point"}
}