{
  "type": "Feature",
  "properties": {
    "addr:full":"Molenstraat 1 A Wetteren Oost-Vlaanderen 9230",
    "addr:housenumber":"1 a",
    "addr:postcode":"9230",
    "addr:street":"Molenstraat",
    "iso:country":"BE",
    "sg:address":"Molenstraat 1 A",
    "sg:city":"Wetteren",
    "sg:classifiers":[
        {
            "category":"Insurance",
            "subcategory":"Life Insurance",
            "type":"Services"
        }
    ],
    "sg:phone":"+32 9 366 06 70",
    "sg:postcode":"9230",
    "sg:province":"Oost-Vlaanderen",
    "sg:tags":[
        "assurance"
    ],
    "wof:name":"Dvv",
    "wof:placetype":"venue"
},
  "geometry": {"coordinates":[3.8872520924,51.0071144104],"type":"Point"}
}