{
  "type": "Feature",
  "properties": {
    "addr:full":"Streepstraat 152 Kapellen Antwerpen 2950",
    "addr:housenumber":"152",
    "addr:postcode":"2950",
    "addr:street":"Streepstraat",
    "iso:country":"BE",
    "sg:address":"Streepstraat 152",
    "sg:city":"Kapellen",
    "sg:classifiers":[
        {
            "category":"Cafe",
            "type":"Food & Drink"
        }
    ],
    "sg:phone":"+32 3 664 99 13",
    "sg:postcode":"2950",
    "sg:province":"Antwerpen",
    "sg:tags":[
        "caf\u00e9s"
    ],
    "wof:name":"Tennisclub 80",
    "wof:placetype":"venue"
},
  "geometry": {"coordinates":[4.4185638428,51.3161277771],"type":"Point"}
}