{
  "type": "Feature",
  "properties": {
    "iso:country":"BE",
    "sg:address":"De Haernestraat 171",
    "sg:city":"Etterbeek",
    "sg:orig_category":"Apotheken",
    "sg:phone":"+32 2 648 32 00",
    "sg:postcode":"1040",
    "sg:province":"Bruxelles-Capitale",
    "wof:name":"Pharmacie V.g.w. & Partn.",
    "wof:placetype":"venue"
},
  "geometry": {"coordinates":[4.3851242065,50.8282546997],"type":"Point"}
}