{
  "type": "Feature",
  "properties": {
    "addr:full":"Burgemeester Vandenbogaerdelaan 24 Box 7 Izegem West-Vlaanderen 8870",
    "addr:housenumber":"24;7",
    "addr:postcode":"8870",
    "addr:street":"Burgemeester Vandenbogaerdelaan;Box",
    "iso:country":"BE",
    "sg:address":"Burgemeester Vandenbogaerdelaan 24 Box 7",
    "sg:city":"Izegem",
    "sg:classifiers":[
        {
            "category":"Personal",
            "subcategory":"Beauty Salon",
            "type":"Services"
        }
    ],
    "sg:phone":"+32 51 32 13 05",
    "sg:postcode":"8870",
    "sg:province":"West-Vlaanderen",
    "sg:tags":[
        "lady",
        "-",
        "hairdressing"
    ],
    "wof:name":"Haircreation B.e.",
    "wof:placetype":"venue"
},
  "geometry": {"coordinates":[3.2113249302,50.9151725769],"type":"Point"}
}