{
  "type": "Feature",
  "properties": {
    "iso:country":"BE",
    "sg:address":"Rue Du Calvaire 9",
    "sg:city":"Sivry-rance",
    "sg:orig_category":"Speciaalzaken",
    "sg:phone":"+32 60 41 10 98",
    "sg:postcode":"6470",
    "sg:province":"Hainaut",
    "wof:name":"Andruetan Georges Et Fils",
    "wof:placetype":"venue"
},
  "geometry": {"coordinates":[4.2721500397,50.1363182068],"type":"Point"}
}