{
  "type": "Feature",
  "properties": {
    "iso:country":"BE",
    "sg:address":"Raverschootstraat 189",
    "sg:city":"Eeklo",
    "sg:orig_category":"Instituts de beaut\u00e9",
    "sg:phone":"+32 9 377 53 65",
    "sg:postcode":"9900",
    "sg:province":"Oost-Vlaanderen",
    "wof:name":"Happy Feet",
    "wof:placetype":"venue"
},
  "geometry": {"coordinates":[3.5459010601,51.1878433228],"type":"Point"}
}