{
  "type": "Feature",
  "properties": {
    "addr:full":"Rue Du Gouvernement 1 Ath Hainaut 7800",
    "addr:housenumber":"1",
    "addr:postcode":"7800",
    "addr:street":"Rue Du Gouvernement",
    "iso:country":"BE",
    "sg:address":"Rue Du Gouvernement 1",
    "sg:city":"Ath",
    "sg:classifiers":[
        {
            "category":"Organizations",
            "subcategory":"Community Association",
            "type":"Services"
        }
    ],
    "sg:phone":"+32 68 26 99 99",
    "sg:postcode":"7800",
    "sg:province":"Hainaut",
    "sg:tags":[
        "cultural"
    ],
    "wof:name":"Maison Culturelle D'ath",
    "wof:placetype":"venue"
},
  "geometry": {"coordinates":[3.7766799927,50.6309204102],"type":"Point"}
}