{
  "type": "Feature",
  "properties": {
    "iso:country":"BE",
    "sg:address":"Poederleese 46",
    "sg:city":"Lille",
    "sg:orig_category":"Entretien and r\u00e9parations de voitures. V\u00e9hicules automobiles",
    "sg:phone":"+32 14 88 14 56",
    "sg:postcode":"2275",
    "sg:province":"Antwerpen",
    "wof:name":"Garage Adri",
    "wof:placetype":"venue"
},
  "geometry": {"coordinates":[4.8280210495,51.234752655],"type":"Point"}
}