{
  "type": "Feature",
  "properties": {
    "addr:full":"Westerlaan 1b22 Waregem West-Vlaanderen 8790",
    "addr:housenumber":"1b22",
    "addr:postcode":"8790",
    "addr:street":"Westerlaan",
    "iso:country":"BE",
    "sg:address":"Westerlaan 1b22",
    "sg:city":"Waregem",
    "sg:orig_category":"Epiceries",
    "sg:phone":"+32 56 61 40 82",
    "sg:postcode":"8790",
    "sg:province":"West-Vlaanderen",
    "wof:name":"Defra",
    "wof:placetype":"venue"
},
  "geometry": {"coordinates":[3.4250090122,50.8832206726],"type":"Point"}
}