{
  "type": "Feature",
  "properties": {
    "iso:country":"BE",
    "sg:address":"Place Matt\u00c9otti 17",
    "sg:city":"La Louviere",
    "sg:orig_category":"Pain, p\u00e2tisseries and confiseries",
    "sg:phone":"+32 64 22 78 21",
    "sg:postcode":"7100",
    "sg:province":"Hainaut",
    "wof:name":"Boulangerie Godefroid",
    "wof:placetype":"venue"
},
  "geometry": {"coordinates":[4.193505764,50.4742622375],"type":"Point"}
}