{
  "type": "Feature",
  "properties": {
    "addr:full":"Tienderstraat 62 Maaseik Limburg 3680",
    "addr:housenumber":"62",
    "addr:postcode":"3680",
    "addr:street":"Tienderstraat",
    "iso:country":"BE",
    "sg:address":"Tienderstraat 62",
    "sg:city":"Maaseik",
    "sg:orig_category":"Travaux de pl\u00e2trage",
    "sg:phone":"+32 89 86 46 66",
    "sg:postcode":"3680",
    "sg:province":"Limburg",
    "wof:name":"Fa. Breemans",
    "wof:placetype":"venue"
},
  "geometry": {"coordinates":[5.791285038,51.0954208374],"type":"Point"}
}