{
  "type": "Feature",
  "properties": {
    "iso:country":"BE",
    "sg:address":"Plein 10",
    "sg:city":"Tongeren",
    "sg:orig_category":"Non-Classified Establishments",
    "sg:phone":"+32 12 23 20 76",
    "sg:postcode":"3700",
    "sg:province":"Limburg",
    "wof:name":"Bovie Charcuterie Nv",
    "wof:placetype":"venue"
},
  "geometry": {"coordinates":[5.4636201859,50.7796821594],"type":"Point"}
}