{
  "type": "Feature",
  "properties": {
    "addr:full":"Machelenstr 16 Vilvoorde Vlaams-Brabant 1800",
    "addr:housenumber":"16",
    "addr:postcode":"1800",
    "addr:street":"Machelenstr",
    "iso:country":"BE",
    "sg:address":"Machelenstr 16",
    "sg:city":"Vilvoorde",
    "sg:classifiers":[
        {
            "category":"Manufacturing",
            "subcategory":"Wood Products",
            "type":"Manufacturing & Wholesale Goods"
        }
    ],
    "sg:phone":"+32 2 253 39 30",
    "sg:postcode":"1800",
    "sg:province":"Vlaams-Brabant",
    "sg:tags":[
        "professional",
        "furniture"
    ],
    "wof:name":"Procura Nv",
    "wof:placetype":"venue"
},
  "geometry": {"coordinates":[4.4261231422,50.9184646606],"type":"Point"}
}