{
  "type": "Feature",
  "properties": {
    "iso:country":"BE",
    "sg:address":"Marktstraat 38",
    "sg:city":"Nieuwpoort",
    "sg:classifiers":[
        {
            "category":"Retail",
            "subcategory":"Laundry & Dry Cleaning",
            "type":"Services"
        }
    ],
    "sg:phone":"+32 58 23 43 11",
    "sg:postcode":"8620",
    "sg:province":"West-Vlaanderen",
    "sg:tags":[
        "dyer",
        "cleaner"
    ],
    "wof:name":"Gudrun-declercq-vyvey Bvba",
    "wof:placetype":"venue"
},
  "geometry": {"coordinates":[2.7522120476,51.1307258606],"type":"Point"}
}