{
  "type": "Feature",
  "properties": {
    "addr:full":"Rid. Walter Van Havreln 257 Schoten Antwerpen 2900",
    "addr:housenumber":"257",
    "addr:postcode":"2900",
    "iso:country":"BE",
    "sg:address":"Rid. Walter Van Havreln 257",
    "sg:city":"Schoten",
    "sg:orig_category":"M\u00e9decins and sp\u00e9cialistes",
    "sg:phone":"+32 3 685 28 20",
    "sg:postcode":"2900",
    "sg:province":"Antwerpen",
    "wof:name":"Veronique Janssens",
    "wof:placetype":"venue"
},
  "geometry": {"coordinates":[4.4874668121,51.2522850037],"type":"Point"}
}