{
  "type": "Feature",
  "properties": {
    "iso:country":"BE",
    "sg:address":"Chauss\u00e9e De Maubeuge 324",
    "sg:city":"Mons (hyon)",
    "sg:classifiers":[
        {
            "category":"Personal",
            "subcategory":"Beauty Salon",
            "type":"Services"
        }
    ],
    "sg:phone":"+32 65 34 61 81",
    "sg:postcode":"7022",
    "sg:province":"Hainaut",
    "sg:tags":[
        "lady",
        "-",
        "hairdressing"
    ],
    "wof:name":"Cr\u00e9a-style",
    "wof:placetype":"venue"
},
  "geometry": {"coordinates":[3.9473879337,50.4345054626],"type":"Point"}
}