{
  "type": "Feature",
  "properties": {
    "addr:full":"Rue De Battice 130 A Aubel Li\u00e8ge 4880",
    "addr:housenumber":"130 a",
    "addr:postcode":"4880",
    "addr:street":"Rue De Battice",
    "iso:country":"BE",
    "sg:address":"Rue De Battice 130 A",
    "sg:city":"Aubel",
    "sg:orig_category":"Entretien and r\u00e9parations de voitures. V\u00e9hicules automobiles",
    "sg:phone":"+32 87 68 85 85",
    "sg:postcode":"4880",
    "sg:province":"Li\u00e8ge",
    "wof:name":"Citro\u00cbn Willemsens Aubel",
    "wof:placetype":"venue"
},
  "geometry": {"coordinates":[5.8539347649,50.691493988],"type":"Point"}
}