{
  "type": "Feature",
  "properties": {
    "addr:full":"Kerkstraat 51 Waasmunster Oost-Vlaanderen 9250",
    "addr:housenumber":"51",
    "addr:postcode":"9250",
    "addr:street":"Kerkstraat",
    "iso:country":"BE",
    "sg:address":"Kerkstraat 51",
    "sg:city":"Waasmunster",
    "sg:orig_category":"Kunstonderwijs",
    "sg:phone":"+32 52 46 32 33",
    "sg:postcode":"9250",
    "sg:province":"Oost-Vlaanderen",
    "wof:name":"Acad. Beeldende Kunsten",
    "wof:placetype":"venue"
},
  "geometry": {"coordinates":[4.0852999687,51.1064529419],"type":"Point"}
}