{
  "type": "Feature",
  "properties": {
    "addr:full":"Chauss\u00c9e De Charleroi 60 Lasne Brabant Wallon 1380",
    "addr:housenumber":"60",
    "addr:postcode":"1380",
    "addr:street":"Chausse\u0301E De Charleroi",
    "iso:country":"BE",
    "sg:address":"Chauss\u00c9e De Charleroi 60",
    "sg:city":"Lasne",
    "sg:classifiers":[
        {
            "category":"Cafe",
            "type":"Food & Drink"
        }
    ],
    "sg:phone":"+32 2 384 70 92",
    "sg:postcode":"1380",
    "sg:province":"Brabant Wallon",
    "sg:tags":[
        "caf\u00e9s"
    ],
    "wof:name":"Angela Uterga",
    "wof:placetype":"venue"
},
  "geometry": {"coordinates":[4.4125699997,50.6564598083],"type":"Point"}
}