{
  "type": "Feature",
  "properties": {
    "iso:country":"BE",
    "sg:address":"Helstraat 25",
    "sg:city":"Diepenbeek",
    "sg:orig_category":"Woningbouw",
    "sg:phone":"+32 11 33 16 54",
    "sg:postcode":"3590",
    "sg:province":"Limburg",
    "wof:name":"Bouwonderneming Claesen",
    "wof:placetype":"venue"
},
  "geometry": {"coordinates":[5.4208240509,50.8851585388],"type":"Point"}
}