{
  "type": "Feature",
  "properties": {
    "addr:full":"Dorp 76 Bonheiden Antwerpen 2820",
    "addr:housenumber":"76",
    "addr:postcode":"2820",
    "addr:street":"Dorp",
    "iso:country":"BE",
    "sg:address":"Dorp 76",
    "sg:city":"Bonheiden",
    "sg:orig_category":"Agences immobili\u00e8res. Services divers aux entreprises",
    "sg:phone":"+32 15 52 83 28",
    "sg:postcode":"2820",
    "sg:province":"Antwerpen",
    "wof:name":"Bureau Leysen Ignace",
    "wof:placetype":"venue"
},
  "geometry": {"coordinates":[4.5449399948,51.0234336853],"type":"Point"}
}