{
  "type": "Feature",
  "properties": {
    "addr:full":"Kerkstraat 22 Zelzate Oost-Vlaanderen 9060",
    "addr:housenumber":"22",
    "addr:postcode":"9060",
    "addr:street":"Kerkstraat",
    "iso:country":"BE",
    "sg:address":"Kerkstraat 22",
    "sg:city":"Zelzate",
    "sg:orig_category":"Juwelen and horloges Opticiens",
    "sg:phone":"+32 9 345 96 17",
    "sg:postcode":"9060",
    "sg:province":"Oost-Vlaanderen",
    "wof:name":"Verhulst-neyt",
    "wof:placetype":"venue"
},
  "geometry": {"coordinates":[3.8132650852,51.200050354],"type":"Point"}
}