{
  "type": "Feature",
  "properties": {
    "iso:country":"BE",
    "sg:address":"Meiboomstraat 71",
    "sg:city":"Wingene",
    "sg:orig_category":"Eleveurs and marchands de porcs",
    "sg:phone":"+32 51 61 29 25",
    "sg:postcode":"8750",
    "sg:province":"West-Vlaanderen",
    "wof:name":"Dirk Lekens",
    "wof:placetype":"venue"
},
  "geometry": {"coordinates":[3.1818919182,51.02318573],"type":"Point"}
}