{
  "type": "Feature",
  "properties": {
    "iso:country":"BE",
    "sg:address":"Nachtegaalstraat 7",
    "sg:city":"Peer",
    "sg:orig_category":"Woningbouw",
    "sg:phone":"+32 11 63 12 03",
    "sg:postcode":"3990",
    "sg:province":"Limburg",
    "wof:name":"Maurits Frederix",
    "wof:placetype":"venue"
},
  "geometry": {"coordinates":[5.4586420059,51.1364135742],"type":"Point"}
}