{
  "type": "Feature",
  "properties": {
    "addr:full":"Leuvensesteenweg 240 Boortmeerbeek Vlaams-Brabant 3190",
    "addr:housenumber":"240",
    "addr:postcode":"3190",
    "addr:street":"Leuvensesteenweg",
    "iso:country":"BE",
    "sg:address":"Leuvensesteenweg 240",
    "sg:city":"Boortmeerbeek",
    "sg:classifiers":[
        {
            "category":"Travel",
            "subcategory":"Hotels & Motels",
            "type":"Entertainment"
        }
    ],
    "sg:phone":"+32 15 51 57 09",
    "sg:postcode":"3190",
    "sg:province":"Vlaams-Brabant",
    "wof:name":"Hotel Classics",
    "wof:placetype":"venue"
},
  "geometry": {"coordinates":[4.5633239746,50.974445343],"type":"Point"}
}