{
  "type": "Feature",
  "properties": {
    "addr:full":"Dendermondesteenweg 447 Destelbergen Oost-Vlaanderen 9070",
    "addr:housenumber":"447",
    "addr:postcode":"9070",
    "addr:street":"Dendermondesteenweg",
    "iso:country":"BE",
    "sg:address":"Dendermondesteenweg 447",
    "sg:city":"Destelbergen",
    "sg:orig_category":"Banken and kredietinstellingen",
    "sg:phone":"+32 9 228 55 11",
    "sg:postcode":"9070",
    "sg:province":"Oost-Vlaanderen",
    "wof:name":"Dexia",
    "wof:placetype":"venue"
},
  "geometry": {"coordinates":[3.7969310284,51.0560874939],"type":"Point"}
}