{
  "type": "Feature",
  "properties": {
    "addr:full":"Rue Albert-elisabeth 26 Binche Hainaut 7134",
    "addr:housenumber":"26",
    "addr:postcode":"7134",
    "addr:street":"Rue Albert-Elisabeth",
    "iso:country":"BE",
    "sg:address":"Rue Albert-elisabeth 26",
    "sg:city":"Binche",
    "sg:orig_category":"M\u00e9decins and sp\u00e9cialistes",
    "sg:phone":"+32 64 33 51 93",
    "sg:postcode":"7134",
    "sg:province":"Hainaut",
    "wof:name":"Herv\u00c9 Jeunieaux",
    "wof:placetype":"venue"
},
  "geometry": {"coordinates":[4.1812000275,50.4355392456],"type":"Point"}
}