{
  "type": "Feature",
  "properties": {
    "iso:country":"BE",
    "sg:address":"Goudstraat 31",
    "sg:city":"Gent",
    "sg:orig_category":"Brood, gebak and snoepgoed",
    "sg:phone":"+32 9 225 43 00",
    "sg:postcode":"9000",
    "sg:province":"Oost-Vlaanderen",
    "wof:name":"Bakkerij Dutilleul",
    "wof:placetype":"venue"
},
  "geometry": {"coordinates":[3.7278430462,51.0597648621],"type":"Point"}
}