{
  "type": "Feature",
  "properties": {
    "addr:full":"Bredabaan 412 Brasschaat Antwerpen 2930",
    "addr:housenumber":"412",
    "addr:postcode":"2930",
    "addr:street":"Bredabaan",
    "iso:country":"BE",
    "sg:address":"Bredabaan 412",
    "sg:city":"Brasschaat",
    "sg:classifiers":[
        {
            "category":"Personal",
            "subcategory":"Beauty Salon",
            "type":"Services"
        }
    ],
    "sg:phone":"+32 3 651 92 35",
    "sg:postcode":"2930",
    "sg:province":"Antwerpen",
    "sg:tags":[
        "de",
        "coiffure"
    ],
    "wof:name":"Freddy Baetens",
    "wof:placetype":"venue"
},
  "geometry": {"coordinates":[4.4959211349,51.2946624756],"type":"Point"}
}