{
  "type": "Feature",
  "properties": {
    "addr:full":"Rue De La Croisette 34 Tubize Brabant Wallon 1480",
    "addr:housenumber":"34",
    "addr:postcode":"1480",
    "addr:street":"Rue De La Croisette;Wallon",
    "iso:country":"BE",
    "sg:address":"Rue De La Croisette 34",
    "sg:city":"Tubize",
    "sg:orig_category":"Avocats and conseillers juridiques",
    "sg:phone":"+32 2 355 97 91",
    "sg:postcode":"1480",
    "sg:province":"Brabant Wallon",
    "wof:name":"O. Bertouille",
    "wof:placetype":"venue"
},
  "geometry": {"coordinates":[4.2015080452,50.6915473938],"type":"Point"}
}