{
  "type": "Feature",
  "properties": {
    "iso:country":"BE",
    "sg:address":"Fin-de-ville 27",
    "sg:city":"Houffalize",
    "sg:orig_category":"Cr\u00e9meries",
    "sg:phone":"+32 61 28 84 84",
    "sg:postcode":"6660",
    "sg:province":"Luxembourg",
    "wof:name":"Alain France",
    "wof:placetype":"venue"
},
  "geometry": {"coordinates":[5.7833418846,50.1363868713],"type":"Point"}
}