{
  "type": "Feature",
  "properties": {
    "addr:full":"Ingberthoeveweg 3 B Aartselaar Antwerpen 2630",
    "addr:housenumber":"3 b",
    "addr:postcode":"2630",
    "addr:street":"Ingberthoeveweg",
    "iso:country":"BE",
    "sg:address":"Ingberthoeveweg 3 B",
    "sg:city":"Aartselaar",
    "sg:classifiers":[
        {
            "category":"Professional",
            "subcategory":"Engineering",
            "type":"Services"
        }
    ],
    "sg:phone":"+32 3 457 91 32",
    "sg:postcode":"2630",
    "sg:province":"Antwerpen",
    "sg:tags":[
        "machine",
        "-",
        "mechanical"
    ],
    "wof:name":"Europe Commercial Refrigiration Nv",
    "wof:placetype":"venue"
},
  "geometry": {"coordinates":[4.3969092369,51.1482505798],"type":"Point"}
}