{
  "type": "Feature",
  "properties": {
    "iso:country":"BE",
    "sg:address":"Sint-gabri\u00cblstraat 19",
    "sg:city":"Boechout",
    "sg:orig_category":"Boekhouders",
    "sg:phone":"+32 3 454 06 08",
    "sg:postcode":"2530",
    "sg:province":"Antwerpen",
    "wof:name":"Piet Degraeve",
    "wof:placetype":"venue"
},
  "geometry": {"coordinates":[4.4852638245,51.1622772217],"type":"Point"}
}