{
  "type": "Feature",
  "properties": {
    "addr:full":"Rue De La Justice 86 Neufch\u00e2teau Luxembourg 6840",
    "addr:housenumber":"86",
    "addr:postcode":"6840",
    "addr:street":"Rue De La Justice",
    "iso:country":"BE",
    "sg:address":"Rue De La Justice 86",
    "sg:city":"Neufch\u00e2teau",
    "sg:classifiers":[
        {
            "category":"Health Services",
            "subcategory":"Doctor",
            "type":"Services"
        }
    ],
    "sg:phone":"+32 61 27 10 57",
    "sg:postcode":"6840",
    "sg:province":"Luxembourg",
    "sg:tags":[
        "medicinephysicians",
        "surgeon"
    ],
    "wof:name":"Bourdon Michel",
    "wof:placetype":"venue"
},
  "geometry": {"coordinates":[5.4551639557,49.8435668945],"type":"Point"}
}