{
  "type": "Feature",
  "properties": {
    "addr:full":"Rue Seumay 151 Perwez Brabant Wallon 1360",
    "addr:housenumber":"151",
    "addr:postcode":"1360",
    "addr:street":"Rue Seumay",
    "iso:country":"BE",
    "sg:address":"Rue Seumay 151",
    "sg:city":"Perwez",
    "sg:orig_category":"Sportterreinen and installaties behalve sportcentra",
    "sg:phone":"+32 81 65 50 77",
    "sg:postcode":"1360",
    "sg:province":"Brabant Wallon",
    "wof:name":"La Bruy\u00c8re",
    "wof:placetype":"venue"
},
  "geometry": {"coordinates":[4.8339681625,50.6338195801],"type":"Point"}
}