{
  "type": "Feature",
  "properties": {
    "addr:full":"Bremlaan 5 Knokke-heist West-Vlaanderen 8300",
    "addr:housenumber":"5",
    "addr:postcode":"8300",
    "addr:street":"Bremlaan",
    "iso:country":"BE",
    "sg:address":"Bremlaan 5",
    "sg:city":"Knokke-heist",
    "sg:orig_category":"Rusthuizen and serviceflats",
    "sg:phone":"+32 50 63 36 00",
    "sg:postcode":"8300",
    "sg:province":"West-Vlaanderen",
    "wof:name":"Bejaardenzorg Lindenhove",
    "wof:placetype":"venue"
},
  "geometry": {"coordinates":[3.3038029671,51.3374137878],"type":"Point"}
}