{
  "type": "Feature",
  "properties": {
    "addr:full":"Rue Cronque 2 Mons Hainaut 7000",
    "addr:housenumber":"2",
    "addr:postcode":"7000",
    "addr:street":"Rue Cronque;Hainaut",
    "iso:country":"BE",
    "sg:address":"Rue Cronque 2",
    "sg:city":"Mons",
    "sg:classifiers":[
        {
            "category":"Real Estate",
            "subcategory":"Architect",
            "type":"Services"
        }
    ],
    "sg:phone":"+32 65 35 16 52",
    "sg:postcode":"7000",
    "sg:province":"Hainaut",
    "wof:name":"Godart A",
    "wof:placetype":"venue"
},
  "geometry": {"coordinates":[3.9513099194,50.4543991089],"type":"Point"}
}