{
  "type": "Feature",
  "properties": {
    "addr:full":"Vinkendal 41 Gent (drongen) Oost-Vlaanderen 9031",
    "addr:housenumber":"41",
    "addr:postcode":"9031",
    "addr:street":"Vinkendal",
    "iso:country":"BE",
    "sg:address":"Vinkendal 41",
    "sg:city":"Gent (drongen)",
    "sg:classifiers":[
        {
            "category":"Personal",
            "type":"Services"
        }
    ],
    "sg:phone":"+32 9 226 47 16",
    "sg:postcode":"9031",
    "sg:province":"Oost-Vlaanderen",
    "sg:tags":[
        "clothing",
        "men's",
        "tailor",
        "-"
    ],
    "wof:name":"Rigole J",
    "wof:placetype":"venue"
},
  "geometry": {"coordinates":[3.637403965,51.0619621277],"type":"Point"}
}