{
  "type": "Feature",
  "properties": {
    "addr:full":"Lage Rooy 10 Hoogstraten Antwerpen 2328",
    "addr:housenumber":"10",
    "addr:postcode":"2328",
    "addr:street":"Lage Rooy",
    "iso:country":"BE",
    "sg:address":"Lage Rooy 10",
    "sg:city":"Hoogstraten",
    "sg:orig_category":"Producteurs de fruits",
    "sg:phone":"+32 3 315 86 95",
    "sg:postcode":"2328",
    "sg:province":"Antwerpen",
    "wof:name":"Harrie Voeten",
    "wof:placetype":"venue"
},
  "geometry": {"coordinates":[4.8065729141,51.467792511],"type":"Point"}
}