{
  "type": "Feature",
  "properties": {
    "iso:country":"BE",
    "sg:address":"Rue Lecomte 114",
    "sg:city":"Namur",
    "sg:classifiers":[
        {
            "category":"Building & Trades",
            "subcategory":"Landscaping Services",
            "type":"Services"
        }
    ],
    "sg:phone":"+32 81 46 00 59",
    "sg:postcode":"5000",
    "sg:province":"Namur",
    "sg:tags":[
        "gardening",
        "garden",
        "maintenance"
    ],
    "wof:name":"Deleau B",
    "wof:placetype":"venue"
},
  "geometry": {"coordinates":[4.8491649628,50.4362068176],"type":"Point"}
}