{
  "type": "Feature",
  "properties": {
    "iso:country":"BE",
    "sg:address":"Grand\u00b4rue 40ba",
    "sg:city":"Durbuy",
    "sg:orig_category":"Openbare bibliotheken and archieven",
    "sg:phone":"+32 86 21 26 41",
    "sg:postcode":"6940",
    "sg:province":"Luxembourg",
    "wof:name":"Biblioth\u00c8que Publique",
    "wof:placetype":"venue"
},
  "geometry": {"coordinates":[5.4936180115,50.3507614136],"type":"Point"}
}