{
  "type": "Feature",
  "properties": {
    "iso:country":"BE",
    "sg:address":"Marollestraat 3",
    "sg:city":"Oudenaarde",
    "sg:orig_category":"Installatie van houten of kunststof schrijnwerk",
    "sg:phone":"+32 55 31 29 36",
    "sg:postcode":"9700",
    "sg:province":"Oost-Vlaanderen",
    "wof:name":"Lucien Veys",
    "wof:placetype":"venue"
},
  "geometry": {"coordinates":[3.5823230743,50.8757400513],"type":"Point"}
}