{
  "type": "Feature",
  "properties": {
    "addr:full":"Rue De L'abb\u00e9 Toussaint 17 Weismes (robertville) Li\u00e8ge 4950",
    "addr:housenumber":"17",
    "addr:postcode":"4950",
    "addr:street":"Rue De L'Abbe \u0301 Toussaint;Robertville",
    "iso:country":"BE",
    "sg:address":"Rue De L'abb\u00e9 Toussaint 17",
    "sg:city":"Weismes (robertville)",
    "sg:classifiers":[
        {
            "category":"Health Services",
            "subcategory":"Health Practitioner",
            "type":"Services"
        }
    ],
    "sg:phone":"+32 80 44 69 56",
    "sg:postcode":"4950",
    "sg:province":"Li\u00e8ge",
    "sg:tags":[
        "physiotherapist"
    ],
    "wof:name":"Magn\u00e9e Elisabeth",
    "wof:placetype":"venue"
},
  "geometry": {"coordinates":[6.1077699661,50.463760376],"type":"Point"}
}