{
  "type": "Feature",
  "properties": {
    "addr:full":"Armand Campenhoutstraat 18 Elsene/ixelles Bruxelles-Capitale 1050",
    "addr:housenumber":"18",
    "addr:postcode":"1050",
    "addr:street":"Armand Campenhoutstraat",
    "iso:country":"BE",
    "sg:address":"Armand Campenhoutstraat 18",
    "sg:city":"Elsene/ixelles",
    "sg:orig_category":"Artsen and specialisten",
    "sg:phone":"+32 2 640 65 94",
    "sg:postcode":"1050",
    "sg:province":"Bruxelles-Capitale",
    "wof:name":"Paolo Cassano",
    "wof:placetype":"venue"
},
  "geometry": {"coordinates":[4.361664772,50.8245697021],"type":"Point"}
}