{
  "type": "Feature",
  "properties": {
    "iso:country":"BE",
    "sg:address":"Zoutstraat 39",
    "sg:city":"Sint-truiden",
    "sg:orig_category":"Deurwaarders",
    "sg:phone":"+32 11 68 88 54",
    "sg:postcode":"3800",
    "sg:province":"Limburg",
    "wof:name":"G. Moria",
    "wof:placetype":"venue"
},
  "geometry": {"coordinates":[5.1838870049,50.8167915344],"type":"Point"}
}