{
  "type": "Feature",
  "properties": {
    "addr:full":"Place Du Tomberg 8 Bruxelles (woluwe-saint-lambert) Bruxelles-Capitale 1200",
    "addr:housenumber":"8",
    "addr:postcode":"1200",
    "addr:street":"Place Du Tomberg",
    "iso:country":"BE",
    "sg:address":"Place Du Tomberg 8",
    "sg:city":"Bruxelles (woluwe-saint-lambert)",
    "sg:classifiers":[
        {
            "category":"Health Services",
            "subcategory":"Doctor",
            "type":"Services"
        }
    ],
    "sg:phone":"+32 2 762 94 13",
    "sg:postcode":"1200",
    "sg:province":"Bruxelles-Capitale",
    "sg:tags":[
        "medicinephysicians",
        "surgeon"
    ],
    "wof:name":"Abras J-cl",
    "wof:placetype":"venue"
},
  "geometry": {"coordinates":[4.4271969795,50.8438034058],"type":"Point"}
}