{
  "type": "Feature",
  "properties": {
    "iso:country":"BE",
    "sg:address":"Groenplein 10b2",
    "sg:city":"Zelzate",
    "sg:orig_category":"Slagers",
    "sg:phone":"+32 9 344 68 70",
    "sg:postcode":"9060",
    "sg:province":"Oost-Vlaanderen",
    "wof:name":"Urbain Verslype",
    "wof:placetype":"venue"
},
  "geometry": {"coordinates":[3.7941329479,51.195854187],"type":"Point"}
}