{
  "type": "Feature",
  "properties": {
    "iso:country":"BE",
    "sg:address":"Rue De L'h\u00f4tel De Ville 36",
    "sg:city":"Spa",
    "sg:classifiers":[
        {
            "category":"Professional",
            "subcategory":"Art Services",
            "type":"Services"
        }
    ],
    "sg:phone":"+32 87 77 24 57",
    "sg:postcode":"4900",
    "sg:province":"Li\u00e8ge",
    "sg:tags":[
        "picture",
        "framer"
    ],
    "wof:name":"Contours Encadrements",
    "wof:placetype":"venue"
},
  "geometry": {"coordinates":[5.8666071892,50.4930763245],"type":"Point"}
}