{
  "type": "Feature",
  "properties": {
    "iso:country":"BE",
    "sg:address":"Kerkstraat 50",
    "sg:city":"Lommel",
    "sg:orig_category":"Verlichting and huishoudartikelen",
    "sg:phone":"+32 11 54 40 54",
    "sg:postcode":"3920",
    "sg:province":"Limburg",
    "wof:name":"Robert Eykholt",
    "wof:placetype":"venue"
},
  "geometry": {"coordinates":[5.3124709129,51.2293014526],"type":"Point"}
}