{
  "type": "Feature",
  "properties": {
    "iso:country":"BE",
    "sg:address":"Lange Leemstraat 117",
    "sg:city":"Antwerpen",
    "sg:orig_category":"M\u00e9decins and sp\u00e9cialistes",
    "sg:phone":"+32 3 230 15 16",
    "sg:postcode":"2018",
    "sg:province":"Antwerpen",
    "wof:name":"Els Thomas",
    "wof:placetype":"venue"
},
  "geometry": {"coordinates":[4.3951001167,51.198009491],"type":"Point"}
}