{
  "type": "Feature",
  "properties": {
    "addr:full":"Brugsesteenweg 281a Eeklo Oost-Vlaanderen 9900",
    "addr:housenumber":"281a",
    "addr:postcode":"9900",
    "addr:street":"Brugsesteenweg",
    "iso:country":"BE",
    "sg:address":"Brugsesteenweg 281a",
    "sg:city":"Eeklo",
    "sg:classifiers":[
        {
            "category":"Food & Beverages",
            "subcategory":"Meat & Fish",
            "type":"Retail Goods"
        }
    ],
    "sg:phone":"+32 9 377 60 18",
    "sg:postcode":"9900",
    "sg:province":"Oost-Vlaanderen",
    "sg:tags":[
        "-",
        "livestock"
    ],
    "wof:name":"Voeders De Craene Bart",
    "wof:placetype":"venue"
},
  "geometry": {"coordinates":[3.5312650204,51.1978263855],"type":"Point"}
}