{
  "type": "Feature",
  "properties": {
    "addr:full":"Steenweg Op Turnhout 8 Oud-turnhout Antwerpen 2360",
    "addr:housenumber":"8",
    "addr:postcode":"2360",
    "addr:street":"Steenweg Op Turnhout",
    "iso:country":"BE",
    "sg:address":"Steenweg Op Turnhout 8",
    "sg:city":"Oud-turnhout",
    "sg:classifiers":[
        {
            "category":"Bars & Pubs",
            "type":"Food & Drink"
        }
    ],
    "sg:phone":"+32 14 45 29 66",
    "sg:postcode":"2360",
    "sg:province":"Antwerpen",
    "wof:name":"Prijsvlucht (de)",
    "wof:placetype":"venue"
},
  "geometry": {"coordinates":[4.9805178642,51.3187484741],"type":"Point"}
}