{
  "type": "Feature",
  "properties": {
    "iso:country":"BE",
    "sg:address":"Klein Holland 61 Box 1",
    "sg:city":"Londerzeel",
    "sg:classifiers":[
        {
            "category":"Structure",
            "subcategory":"Office Building",
            "type":"Public Place"
        }
    ],
    "sg:phone":"+32 52 30 59 71",
    "sg:postcode":"1840",
    "sg:province":"Vlaams-Brabant",
    "sg:tags":[
        "drawing"
    ],
    "wof:name":"Architraaf Sooghen J",
    "wof:placetype":"venue"
},
  "geometry": {"coordinates":[4.2974791527,51.0122718811],"type":"Point"}
}