{
  "type": "Feature",
  "properties": {
    "addr:full":"Avenue Du Grand Bois 6 Waterloo Brabant Wallon 1410",
    "addr:housenumber":"6",
    "addr:postcode":"1410",
    "addr:street":"Avenue Du Grand Bois",
    "iso:country":"BE",
    "sg:address":"Avenue Du Grand Bois 6",
    "sg:city":"Waterloo",
    "sg:classifiers":[
        {
            "category":"Banks & Credit Unions",
            "subcategory":"Investment Brokerage",
            "type":"Services"
        }
    ],
    "sg:phone":"+32 2 354 89 85",
    "sg:postcode":"1410",
    "sg:province":"Brabant Wallon",
    "wof:name":"Ags Invest",
    "wof:placetype":"venue"
},
  "geometry": {"coordinates":[4.3842921257,50.7109909058],"type":"Point"}
}