{
  "type": "Feature",
  "properties": {
    "addr:full":"Chemin D' Audregnies 5 Hensies Hainaut 7350",
    "addr:housenumber":"5",
    "addr:postcode":"7350",
    "addr:street":"Chemin D ' Audregnies",
    "iso:country":"BE",
    "sg:address":"Chemin D' Audregnies 5",
    "sg:city":"Hensies",
    "sg:orig_category":"Rundveehouders",
    "sg:phone":"+32 65 65 24 45",
    "sg:postcode":"7350",
    "sg:province":"Hainaut",
    "wof:name":"Etienne Meersseman",
    "wof:placetype":"venue"
},
  "geometry": {"coordinates":[3.7387609482,50.4241333008],"type":"Point"}
}