{
  "type": "Feature",
  "properties": {
    "addr:full":"Avenue Ernest Cambier 28 Bruxelles (schaerbeek) Bruxelles-Capitale 1030",
    "addr:housenumber":"28",
    "addr:postcode":"1030",
    "addr:street":"Avenue Ernest Cambier",
    "iso:country":"BE",
    "sg:address":"Avenue Ernest Cambier 28",
    "sg:city":"Bruxelles (schaerbeek)",
    "sg:classifiers":[
        {
            "category":"Communications",
            "subcategory":"Film & Video Production",
            "type":"Services"
        }
    ],
    "sg:phone":"+32 2 705 78 03",
    "sg:postcode":"1030",
    "sg:province":"Bruxelles-Capitale",
    "sg:tags":[
        "material",
        "audio-visual"
    ],
    "wof:name":"Applications Audiovisuelles Sprl",
    "wof:placetype":"venue"
},
  "geometry": {"coordinates":[4.3968391418,50.8561477661],"type":"Point"}
}