{
  "type": "Feature",
  "properties": {
    "iso:country":"BE",
    "sg:address":"Overeinde 18",
    "sg:city":"As",
    "sg:orig_category":"Auto-\u00e9coles",
    "sg:phone":"+32 89 65 78 33",
    "sg:postcode":"3665",
    "sg:province":"Limburg",
    "wof:name":"Autorijschool Jacobs",
    "wof:placetype":"venue"
},
  "geometry": {"coordinates":[5.5895009041,51.0116004944],"type":"Point"}
}