{
  "type": "Feature",
  "properties": {
    "addr:full":"Sint-godelievedreef 15 Brugge (sint-kruis) West-Vlaanderen 8310",
    "addr:housenumber":"15",
    "addr:postcode":"8310",
    "addr:street":"Sint-Godelievedreef",
    "iso:country":"BE",
    "sg:address":"Sint-godelievedreef 15",
    "sg:city":"Brugge (sint-kruis)",
    "sg:classifiers":[
        {
            "category":"Real Estate",
            "subcategory":"Architect",
            "type":"Services"
        }
    ],
    "sg:phone":"+32 50 35 39 89",
    "sg:postcode":"8310",
    "sg:province":"West-Vlaanderen",
    "wof:name":"Ostyn G",
    "wof:placetype":"venue"
},
  "geometry": {"coordinates":[3.2397520542,51.222694397],"type":"Point"}
}