{
  "type": "Feature",
  "properties": {
    "addr:full":"Rue Des Patriotes Brussel/bruxelles Bruxelles-Capitale 1000",
    "addr:postcode":"1000",
    "addr:street":"Rue Des Patriotes",
    "iso:country":"BE",
    "sg:address":"Rue Des Patriotes",
    "sg:city":"Brussel/bruxelles",
    "sg:orig_category":"Graphologues, astrologues, voyants and radiesth\u00e9sistes",
    "sg:phone":"+32 475 98 01 73",
    "sg:postcode":"1000",
    "sg:province":"Bruxelles-Capitale",
    "wof:name":"Nauriane",
    "wof:placetype":"venue"
},
  "geometry": {"coordinates":[4.392182827,50.8472061157],"type":"Point"}
}