{
  "type": "Feature",
  "properties": {
    "iso:country":"BE",
    "sg:address":"Lokerhoutstraat 79",
    "sg:city":"Lokeren",
    "sg:classifiers":[
        {
            "category":"Health Services",
            "subcategory":"Health Practitioner",
            "type":"Services"
        }
    ],
    "sg:phone":"+32 9 348 70 99",
    "sg:postcode":"9160",
    "sg:province":"Oost-Vlaanderen",
    "sg:tags":[
        "alternative",
        "therapy",
        "treatment"
    ],
    "wof:name":"Roels M",
    "wof:placetype":"venue"
},
  "geometry": {"coordinates":[3.995677948,51.0954742432],"type":"Point"}
}