{
  "type": "Feature",
  "properties": {
    "addr:full":"Kerkomstraat 18 Tienen (kumtich) Vlaams-Brabant 3300",
    "addr:housenumber":"18",
    "addr:postcode":"3300",
    "addr:street":"Kerkomstraat",
    "iso:country":"BE",
    "sg:address":"Kerkomstraat 18",
    "sg:city":"Tienen (kumtich)",
    "sg:classifiers":[
        {
            "category":"Health Services",
            "subcategory":"Health Practitioner",
            "type":"Services"
        }
    ],
    "sg:phone":"+32 16 81 03 92",
    "sg:postcode":"3300",
    "sg:province":"Vlaams-Brabant",
    "sg:tags":[
        "physiotherapist"
    ],
    "wof:name":"Luypaert F",
    "wof:placetype":"venue"
},
  "geometry": {"coordinates":[4.930077076,50.8096694946],"type":"Point"}
}