{
  "type": "Feature",
  "properties": {
    "addr:full":"Rijselstraat 4 Menen West-Vlaanderen 8930",
    "addr:housenumber":"4",
    "addr:postcode":"8930",
    "addr:street":"Rijselstraat",
    "iso:country":"BE",
    "sg:address":"Rijselstraat 4",
    "sg:city":"Menen",
    "sg:orig_category":"Artsen and specialisten",
    "sg:phone":"+32 56 51 18 80",
    "sg:postcode":"8930",
    "sg:province":"West-Vlaanderen",
    "wof:name":"Joseph Ververken",
    "wof:placetype":"venue"
},
  "geometry": {"coordinates":[3.121694088,50.7961730957],"type":"Point"}
}