{
  "type": "Feature",
  "properties": {
    "iso:country":"BE",
    "sg:address":"Bredevoorde 14",
    "sg:city":"Oudenburg",
    "sg:orig_category":"Pleisterwerk",
    "sg:phone":"+32 59 26 77 62",
    "sg:postcode":"8460",
    "sg:province":"West-Vlaanderen",
    "wof:name":"Henry Murphy",
    "wof:placetype":"venue"
},
  "geometry": {"coordinates":[2.9833021164,51.1934013367],"type":"Point"}
}