{
  "type": "Feature",
  "properties": {
    "addr:full":"Gentsesteenweg 343 Erpe-mere Oost-Vlaanderen 9420",
    "addr:housenumber":"343",
    "addr:postcode":"9420",
    "addr:street":"Gentsesteenweg",
    "iso:country":"BE",
    "sg:address":"Gentsesteenweg 343",
    "sg:city":"Erpe-mere",
    "sg:classifiers":[
        {
            "category":"Cafe",
            "type":"Food & Drink"
        }
    ],
    "sg:phone":"+32 53 80 51 23",
    "sg:postcode":"9420",
    "sg:province":"Oost-Vlaanderen",
    "sg:tags":[
        "caf\u00e9s"
    ],
    "wof:name":"Conny",
    "wof:placetype":"venue"
},
  "geometry": {"coordinates":[3.9637999535,50.9456787109],"type":"Point"}
}