{
  "type": "Feature",
  "properties": {
    "iso:country":"BE",
    "sg:address":"Roesbeke 13",
    "sg:city":"Ninove",
    "sg:orig_category":"Traitements param\u00e9dicaux",
    "sg:phone":"+32 54 33 75 78",
    "sg:postcode":"9402",
    "sg:province":"Oost-Vlaanderen",
    "wof:name":"V. Lepoivre",
    "wof:placetype":"venue"
},
  "geometry": {"coordinates":[4.0395750999,50.8249015808],"type":"Point"}
}