{
  "type": "Feature",
  "properties": {
    "iso:country":"BE",
    "sg:address":"Zeelaan 61b1",
    "sg:city":"Koksijde",
    "sg:orig_category":"Slagers Zuivelproducten",
    "sg:phone":"+32 58 52 12 36",
    "sg:postcode":"8670",
    "sg:province":"West-Vlaanderen",
    "wof:name":"Frank Dekien",
    "wof:placetype":"venue"
},
  "geometry": {"coordinates":[2.6485660076,51.1065444946],"type":"Point"}
}