{
  "type": "Feature",
  "properties": {
    "addr:full":"Avenue De La Ferme Rose 14 Bruxelles (uccle) Bruxelles-Capitale 1180",
    "addr:housenumber":"14",
    "addr:postcode":"1180",
    "addr:street":"Avenue De La Ferme Rose",
    "iso:country":"BE",
    "sg:address":"Avenue De La Ferme Rose 14",
    "sg:city":"Bruxelles (uccle)",
    "sg:classifiers":[
        {
            "category":"Health Services",
            "subcategory":"Doctor",
            "type":"Services"
        }
    ],
    "sg:phone":"+32 2 343 76 49",
    "sg:postcode":"1180",
    "sg:province":"Bruxelles-Capitale",
    "sg:tags":[
        "medicinephysicians",
        "surgeon"
    ],
    "wof:name":"Capelluto E",
    "wof:placetype":"venue"
},
  "geometry": {"coordinates":[4.3483800888,50.8068618774],"type":"Point"}
}