{
  "type": "Feature",
  "properties": {
    "iso:country":"BE",
    "sg:address":"Rue De La Justice 380",
    "sg:city":"Chatelet",
    "sg:orig_category":"Traitements param\u00e9dicaux",
    "sg:phone":"+32 71 39 17 12",
    "sg:postcode":"6200",
    "sg:province":"Hainaut",
    "wof:name":"C. Camus",
    "wof:placetype":"venue"
},
  "geometry": {"coordinates":[4.5450639725,50.3877906799],"type":"Point"}
}