{
  "type": "Feature",
  "properties": {
    "addr:full":"Stoepestraat 32 Evergem Oost-Vlaanderen 9940",
    "addr:housenumber":"32",
    "addr:postcode":"9940",
    "addr:street":"Stoepestraat;Oost-Vlaanderen",
    "iso:country":"BE",
    "sg:address":"Stoepestraat 32",
    "sg:city":"Evergem",
    "sg:orig_category":"Artistes ind\u00e9pendants",
    "sg:phone":"+32 9 344 05 60",
    "sg:postcode":"9940",
    "sg:province":"Oost-Vlaanderen",
    "wof:name":"Koenraad Maes",
    "wof:placetype":"venue"
},
  "geometry": {"coordinates":[3.753770113,51.1878585815],"type":"Point"}
}