{
  "type": "Feature",
  "properties": {
    "iso:country":"BE",
    "sg:address":"Bredabaan 446",
    "sg:city":"Brasschaat",
    "sg:orig_category":"Bloemen and planten",
    "sg:phone":"+32 3 651 49 26",
    "sg:postcode":"2930",
    "sg:province":"Antwerpen",
    "wof:name":"Bosmans H",
    "wof:placetype":"venue"
},
  "geometry": {"coordinates":[4.4968709946,51.2957801819],"type":"Point"}
}