{
  "type": "Feature",
  "properties": {
    "iso:country":"BE",
    "sg:address":"Troonstraat 1",
    "sg:city":"Elsene/ixelles",
    "sg:orig_category":"Salles de spectacles",
    "sg:phone":"+32 2 547 23 83",
    "sg:postcode":"1050",
    "sg:province":"Bruxelles-Capitale",
    "wof:name":"Galerij Bbl-marnix",
    "wof:placetype":"venue"
},
  "geometry": {"coordinates":[4.3676099777,50.8389511108],"type":"Point"}
}