{
  "type": "Feature",
  "properties": {
    "addr:full":"Rue De La Place 3 Antoing Hainaut 7640",
    "addr:housenumber":"3",
    "addr:postcode":"7640",
    "addr:street":"Rue De La Place",
    "iso:country":"BE",
    "sg:address":"Rue De La Place 3",
    "sg:city":"Antoing",
    "sg:orig_category":"Jeux de hasard",
    "sg:phone":"+32 69 44 26 06",
    "sg:postcode":"7640",
    "sg:province":"Hainaut",
    "wof:name":"Pmu",
    "wof:placetype":"venue"
},
  "geometry": {"coordinates":[3.4539549351,50.5522727966],"type":"Point"}
}