{
  "type": "Feature",
  "properties": {
    "addr:full":"Meensesteenweg 316 Kortrijk (bissegem) West-Vlaanderen 8501",
    "addr:housenumber":"316",
    "addr:postcode":"8501",
    "addr:street":"Meensesteenweg",
    "iso:country":"BE",
    "sg:address":"Meensesteenweg 316",
    "sg:city":"Kortrijk (bissegem)",
    "sg:classifiers":[
        {
            "category":"Real Estate",
            "subcategory":"Real Estate Services",
            "type":"Services"
        }
    ],
    "sg:phone":"+32 56 35 95 60",
    "sg:postcode":"8501",
    "sg:province":"West-Vlaanderen",
    "wof:name":"Alpha 2000",
    "wof:placetype":"venue"
},
  "geometry": {"coordinates":[3.227451086,50.8239135742],"type":"Point"}
}