{
  "type": "Feature",
  "properties": {
    "iso:country":"BE",
    "sg:address":"Munthofstraat 53",
    "sg:city":"Sint-gillis/saint-gilles",
    "sg:orig_category":"Artsen and specialisten",
    "sg:phone":"+32 2 537 22 04",
    "sg:postcode":"1060",
    "sg:province":"Bruxelles-Capitale",
    "wof:name":"Aleksander Biernacki",
    "wof:placetype":"venue"
},
  "geometry": {"coordinates":[4.3485531807,50.8314361572],"type":"Point"}
}