{
  "type": "Feature",
  "properties": {
    "iso:country":"BE",
    "sg:address":"Grand-rue 56",
    "sg:city":"Fontaine-l\u00b4ev\u00caque",
    "sg:orig_category":"Epiceries",
    "sg:phone":"+32 71 52 44 08",
    "sg:postcode":"6140",
    "sg:province":"Hainaut",
    "wof:name":"Pluba",
    "wof:placetype":"venue"
},
  "geometry": {"coordinates":[4.3212800026,50.4115409851],"type":"Point"}
}