{
  "type": "Feature",
  "properties": {
    "addr:full":"Oude Bevelsesteenweg 126 Nijlen Antwerpen 2560",
    "addr:housenumber":"126",
    "addr:postcode":"2560",
    "addr:street":"Oude Bevelsesteenweg",
    "iso:country":"BE",
    "sg:address":"Oude Bevelsesteenweg 126",
    "sg:city":"Nijlen",
    "sg:orig_category":"Fournitures de bureau",
    "sg:phone":"+32 3 481 90 20",
    "sg:postcode":"2560",
    "sg:province":"Antwerpen",
    "wof:name":"Montamic",
    "wof:placetype":"venue"
},
  "geometry": {"coordinates":[4.6745128632,51.153049469],"type":"Point"}
}