{
  "type": "Feature",
  "properties": {
    "iso:country":"BE",
    "sg:address":"G.j. Martinstraat 11",
    "sg:city":"Sint-pieters-woluwe/woluwe-saint-pierre",
    "sg:orig_category":"Alternatieve geneeskunde",
    "sg:phone":"+32 475 64 93 47",
    "sg:postcode":"1150",
    "sg:province":"Bruxelles-Capitale",
    "wof:name":"Fabienne Demuynck",
    "wof:placetype":"venue"
},
  "geometry": {"coordinates":[4.4258861542,50.8372154236],"type":"Point"}
}