{
  "type": "Feature",
  "properties": {
    "addr:full":"Avenue Hanlet 9a Verviers (heusy) Li\u00e8ge 4802",
    "addr:housenumber":"9a",
    "addr:postcode":"4802",
    "addr:street":"Avenue Hanlet",
    "iso:country":"BE",
    "sg:address":"Avenue Hanlet 9a",
    "sg:city":"Verviers (heusy)",
    "sg:classifiers":[
        {
            "category":"Health Services",
            "subcategory":"Doctor",
            "type":"Services"
        }
    ],
    "sg:phone":"+32 87 23 01 69",
    "sg:postcode":"4802",
    "sg:province":"Li\u00e8ge",
    "sg:tags":[
        "medicinephysicians",
        "surgeon"
    ],
    "wof:name":"Beco Jacques",
    "wof:placetype":"venue"
},
  "geometry": {"coordinates":[5.8671250343,50.5714111328],"type":"Point"}
}