{
  "type": "Feature",
  "properties": {
    "iso:country":"BE",
    "sg:address":"Rue D'enneilles 17",
    "sg:city":"Somme-leuze (noiseux)",
    "sg:orig_category":"Non-Classified Establishments",
    "sg:phone":"+32 86 32 24 16",
    "sg:postcode":"5377",
    "sg:province":"Namur",
    "wof:name":"Acv. Ballistics",
    "wof:placetype":"venue"
},
  "geometry": {"coordinates":[5.3769659996,50.3151855469],"type":"Point"}
}