{
  "type": "Feature",
  "properties": {
    "iso:country":"BE",
    "sg:address":"Parc Industriel 22",
    "sg:city":"Braine L'alleud (braine-l'alleud)",
    "sg:classifiers":[
        {
            "category":"Building & Trades",
            "subcategory":"Construction",
            "type":"Services"
        }
    ],
    "sg:phone":"+32 2 384 96 50",
    "sg:postcode":"1420",
    "sg:province":"Brabant Wallon",
    "sg:tags":[
        "work",
        "waterproofing"
    ],
    "wof:name":"Murprotec Nv",
    "wof:placetype":"venue"
},
  "geometry": {"coordinates":[0.4667930007,49.574848175],"type":"Point"}
}