{
  "type": "Feature",
  "properties": {
    "addr:full":"Mechelsesteenweg 290 Kontich Antwerpen 2550",
    "addr:housenumber":"290",
    "addr:postcode":"2550",
    "addr:street":"Mechelsesteenweg",
    "iso:country":"BE",
    "sg:address":"Mechelsesteenweg 290",
    "sg:city":"Kontich",
    "sg:orig_category":"Decoration Articles For The Retail Trade",
    "sg:phone":"+32 3 457 97 22",
    "sg:postcode":"2550",
    "sg:province":"Antwerpen",
    "wof:name":"V.a. Trading Nv",
    "wof:placetype":"venue"
},
  "geometry": {"coordinates":[4.4497351646,51.1215515137],"type":"Point"}
}