{
  "type": "Feature",
  "properties": {
    "iso:country":"BE",
    "sg:address":"Wielewaallaan 22",
    "sg:city":"Kortrijk",
    "sg:orig_category":"Elektrische installaties voor woningen",
    "sg:phone":"+32 56 72 96 01",
    "sg:postcode":"8500",
    "sg:province":"West-Vlaanderen",
    "wof:name":"Valere Vanden Berghe",
    "wof:placetype":"venue"
},
  "geometry": {"coordinates":[3.2996299267,50.813911438],"type":"Point"}
}