{
  "type": "Feature",
  "properties": {
    "iso:country":"BE",
    "sg:address":"Rue De Gembloux 18",
    "sg:city":"La Bruy\u00e8re (rhisnes)",
    "sg:classifiers":[
        {
            "category":"Landmark",
            "subcategory":"Tourist Attraction",
            "type":"Public Place"
        }
    ],
    "sg:postcode":"5080",
    "sg:province":"Namur",
    "sg:tags":[
        "-",
        "tourism",
        "interest",
        "sight"
    ],
    "wof:name":"Grottes Du Pont D'arcole",
    "wof:placetype":"venue"
},
  "geometry": {"coordinates":[4.7983970642,50.4983406067],"type":"Point"}
}