{
  "type": "Feature",
  "properties": {
    "iso:country":"BE",
    "sg:address":"Mosselgoren 154",
    "sg:city":"Geel",
    "sg:classifiers":[
        {
            "category":"Professional",
            "subcategory":"Management & Consulting",
            "type":"Services"
        }
    ],
    "sg:phone":"+32 478 45 65 86",
    "sg:postcode":"2440",
    "sg:province":"Antwerpen",
    "sg:tags":[
        "consultant"
    ],
    "wof:name":"Luc De Reu Consultancy Com V",
    "wof:placetype":"venue"
},
  "geometry": {"coordinates":[4.9262499809,51.1923294067],"type":"Point"}
}