{
  "type": "Feature",
  "properties": {
    "addr:full":"Rue De Roubaix 6 Tournai (templeuve) Hainaut 7520",
    "addr:housenumber":"6",
    "addr:postcode":"7520",
    "addr:street":"Rue De Roubaix",
    "iso:country":"BE",
    "sg:address":"Rue De Roubaix 6",
    "sg:city":"Tournai (templeuve)",
    "sg:classifiers":[
        {
            "category":"Community Center",
            "type":"Public Place"
        }
    ],
    "sg:phone":"+32 69 35 15 77",
    "sg:postcode":"7520",
    "sg:province":"Hainaut",
    "sg:tags":[
        "medical"
    ],
    "wof:name":"Centre De Soins M\u00e9dicaux Dumortier",
    "wof:placetype":"venue"
},
  "geometry": {"coordinates":[3.2823140621,50.6448020935],"type":"Point"}
}