{
  "type": "Feature",
  "properties": {
    "addr:full":"G. De Donderstraat 29 Grimbergen Vlaams-Brabant 1852",
    "addr:housenumber":"29",
    "addr:postcode":"1852",
    "addr:street":"G.;Donderstraat",
    "iso:country":"BE",
    "sg:address":"G. De Donderstraat 29",
    "sg:city":"Grimbergen",
    "sg:classifiers":[
        {
            "category":"Cafe",
            "type":"Food & Drink"
        }
    ],
    "sg:phone":"+32 2 269 19 69",
    "sg:postcode":"1852",
    "sg:province":"Vlaams-Brabant",
    "sg:tags":[
        "caf\u00e9s"
    ],
    "wof:name":"Caf\u00c9 Sportman",
    "wof:placetype":"venue"
},
  "geometry": {"coordinates":[4.3681287766,50.954788208],"type":"Point"}
}