{
  "type": "Feature",
  "properties": {
    "iso:country":"BE",
    "sg:address":"Tongersesteenweg 10",
    "sg:city":"Sint-truiden",
    "sg:classifiers":[
        {
            "category":"Health Services",
            "subcategory":"Dentist",
            "type":"Services"
        }
    ],
    "sg:phone":"+32 11 68 68 02",
    "sg:postcode":"3800",
    "sg:province":"Limburg",
    "wof:name":"Vannitsen Marc",
    "wof:placetype":"venue"
},
  "geometry": {"coordinates":[5.1902699471,50.8132133484],"type":"Point"}
}