{
  "type": "Feature",
  "properties": {
    "iso:country":"BE",
    "sg:address":"Chauss\u00e9e De Namur 5a",
    "sg:city":"Villers-la-ville (sart-dames-avelines)",
    "sg:classifiers":[
        {
            "category":"Real Estate",
            "subcategory":"Developer",
            "type":"Services"
        }
    ],
    "sg:phone":"+32 71 87 69 90",
    "sg:postcode":"1495",
    "sg:province":"Brabant Wallon",
    "sg:tags":[
        "project"
    ],
    "wof:name":"Robert Le Grelle Entreprises Sprl",
    "wof:placetype":"venue"
},
  "geometry": {"coordinates":[4.4784150124,50.561580658],"type":"Point"}
}