{
  "type": "Feature",
  "properties": {
    "iso:country":"BE",
    "sg:address":"Bld De La Sauveni\u00c8re 145",
    "sg:city":"Li\u00c8ge",
    "sg:orig_category":"Erotische Etablissementen",
    "sg:phone":"+32 4 222 04 82",
    "sg:postcode":"4000",
    "sg:province":"Li\u00e8ge",
    "wof:name":"Le Must",
    "wof:placetype":"venue"
},
  "geometry": {"coordinates":[5.5686759949,50.6406211853],"type":"Point"}
}