{
  "type": "Feature",
  "properties": {
    "iso:country":"BE",
    "sg:address":"Clos Des Rocteurs 6",
    "sg:city":"Soignies",
    "sg:orig_category":"Experts-comptables",
    "sg:phone":"+32 67 33 14 58",
    "sg:postcode":"7060",
    "sg:province":"Hainaut",
    "wof:name":"Rudy Paridaens",
    "wof:placetype":"venue"
},
  "geometry": {"coordinates":[4.085050106,50.5697784424],"type":"Point"}
}