{
  "type": "Feature",
  "properties": {
    "addr:full":"Jubelfeestlaan 16 Sint-jans-molenbeek/molenbeek-saint-jean Bruxelles-Capitale 1080",
    "addr:housenumber":"16",
    "addr:postcode":"1080",
    "addr:street":"Jubelfeestlaan",
    "iso:country":"BE",
    "sg:address":"Jubelfeestlaan 16",
    "sg:city":"Sint-jans-molenbeek/molenbeek-saint-jean",
    "sg:orig_category":"Artsen and specialisten",
    "sg:phone":"+32 2 420 55 06",
    "sg:postcode":"1080",
    "sg:province":"Bruxelles-Capitale",
    "wof:name":"V. Dzamba Bienvenu",
    "wof:placetype":"venue"
},
  "geometry": {"coordinates":[4.3377728462,50.8616447449],"type":"Point"}
}