{
  "type": "Feature",
  "properties": {
    "iso:country":"BE",
    "sg:address":"Ruelle Du Clerc 12",
    "sg:city":"Leuze-en-hainaut",
    "sg:orig_category":"Advocaten and juridische adviseurs",
    "sg:phone":"+32 69 66 31 02",
    "sg:postcode":"7904",
    "sg:province":"Hainaut",
    "wof:name":"J.m. Lepape",
    "wof:placetype":"venue"
},
  "geometry": {"coordinates":[3.5772929192,50.5823097229],"type":"Point"}
}