{
  "type": "Feature",
  "properties": {
    "addr:full":"Sint-bonifaasstraat 1 Elsene/ixelles Bruxelles-Capitale 1050",
    "addr:housenumber":"1",
    "addr:postcode":"1050",
    "addr:street":"Sint-Bonifaasstraat",
    "iso:country":"BE",
    "sg:address":"Sint-bonifaasstraat 1",
    "sg:city":"Elsene/ixelles",
    "sg:orig_category":"Dameskledingzaken",
    "sg:phone":"+32 2 514 22 63",
    "sg:postcode":"1050",
    "sg:province":"Bruxelles-Capitale",
    "wof:name":"Alia",
    "wof:placetype":"venue"
},
  "geometry": {"coordinates":[4.3651537895,50.835849762],"type":"Point"}
}