{
  "type": "Feature",
  "properties": {
    "iso:country":"BE",
    "sg:address":"Rue Albert Et Louis Curvers 44",
    "sg:city":"Chaudfontaine",
    "sg:orig_category":"Ordinateurs and \u00e9quipement informatique",
    "sg:phone":"+32 4 365 69 62",
    "sg:postcode":"4053",
    "sg:province":"Li\u00e8ge",
    "wof:name":"Abcomput",
    "wof:placetype":"venue"
},
  "geometry": {"coordinates":[5.6141529083,50.5951919556],"type":"Point"}
}