{
  "type": "Feature",
  "properties": {
    "addr:full":"Molenstraat 47 Genk Limburg 3600",
    "addr:housenumber":"47",
    "addr:postcode":"3600",
    "addr:street":"Molenstraat",
    "iso:country":"BE",
    "sg:address":"Molenstraat 47",
    "sg:city":"Genk",
    "sg:classifiers":[
        {
            "category":"Shopping",
            "subcategory":"Antiques",
            "type":"Retail Goods"
        }
    ],
    "sg:phone":"+32 89 35 27 06",
    "sg:postcode":"3600",
    "sg:province":"Limburg",
    "wof:name":"Driessen Schreurs Antiekgaleri",
    "wof:placetype":"venue"
},
  "geometry": {"coordinates":[5.5035219193,50.9643707275],"type":"Point"}
}