{
  "type": "Feature",
  "properties": {
    "addr:full":"Provinciebaan 10 Staden West-Vlaanderen 8840",
    "addr:housenumber":"10",
    "addr:postcode":"8840",
    "addr:street":"Provinciebaan",
    "iso:country":"BE",
    "sg:address":"Provinciebaan 10",
    "sg:city":"Staden",
    "sg:orig_category":"Herstellingen and onderhoud van auto's",
    "sg:phone":"+32 51 77 85 19",
    "sg:postcode":"8840",
    "sg:province":"West-Vlaanderen",
    "wof:name":"Stefaan Vanlerberghe",
    "wof:placetype":"venue"
},
  "geometry": {"coordinates":[3.0457150936,50.9539299011],"type":"Point"}
}