{
  "type": "Feature",
  "properties": {
    "iso:country":"BE",
    "sg:address":"Rue Chinrue 22",
    "sg:city":"Theux",
    "sg:orig_category":"Schoonheidssalons",
    "sg:phone":"+32 87 53 01 31",
    "sg:postcode":"4910",
    "sg:province":"Li\u00e8ge",
    "wof:name":"Didier Wilwerth",
    "wof:placetype":"venue"
},
  "geometry": {"coordinates":[5.8119330406,50.5359573364],"type":"Point"}
}