{
  "type": "Feature",
  "properties": {
    "addr:full":"Route De Lessines 24 Frasnes-lez-anvaing (frasnes - Lez - Buissenal) Hainaut 7911",
    "addr:housenumber":"24",
    "addr:postcode":"7911",
    "addr:street":"Route De Lessines",
    "iso:country":"BE",
    "sg:address":"Route De Lessines 24",
    "sg:city":"Frasnes-lez-anvaing (frasnes - Lez - Buissenal)",
    "sg:classifiers":[
        {
            "category":"Shopping",
            "subcategory":"Pets & Pet Supplies",
            "type":"Retail Goods"
        }
    ],
    "sg:phone":"+32 69 86 66 36",
    "sg:postcode":"7911",
    "sg:province":"Hainaut",
    "sg:tags":[
        "shop",
        "-"
    ],
    "wof:name":"Clam",
    "wof:placetype":"venue"
},
  "geometry": {"coordinates":[3.6283259392,50.6719665527],"type":"Point"}
}