{
  "type": "Feature",
  "properties": {
    "iso:country":"BE",
    "sg:address":"Pauwengraaf 2",
    "sg:city":"Maasmechelen",
    "sg:orig_category":"RESTAURANTS: H\u00d4TELS",
    "sg:phone":"+32 89 76 01 26",
    "sg:postcode":"3630",
    "sg:province":"Limburg",
    "wof:name":"Lika",
    "wof:placetype":"venue"
},
  "geometry": {"coordinates":[5.6961350441,50.963848114],"type":"Point"}
}