{
  "type": "Feature",
  "properties": {
    "iso:country":"BE",
    "sg:address":"Expoelstraat 12",
    "sg:city":"Mechelen (hombeek)",
    "sg:classifiers":[
        {
            "category":"Farming",
            "subcategory":"Livestock Farm",
            "type":"Manufacturing & Wholesale Goods"
        }
    ],
    "sg:phone":"+32 15 41 03 21",
    "sg:postcode":"2811",
    "sg:province":"Antwerpen",
    "sg:tags":[
        "buyer"
    ],
    "wof:name":"Van Beveren R",
    "wof:placetype":"venue"
},
  "geometry": {"coordinates":[4.3934187889,51.0110397339],"type":"Point"}
}