{
  "type": "Feature",
  "properties": {
    "iso:country":"BE",
    "sg:address":"Roeselaarsestraat 98",
    "sg:city":"Izegem",
    "sg:classifiers":[
        {
            "category":"Professional",
            "subcategory":"Computer Services",
            "type":"Services"
        }
    ],
    "sg:postcode":"8870",
    "sg:tags":[
        "saas-monitoring-security"
    ],
    "wof:name":"Gibeon",
    "wof:placetype":"venue"
},
  "geometry": {"coordinates":[3.2081508,50.919587],"type":"Point"}
}