{
  "type": "Feature",
  "properties": {
    "iso:country":"BE",
    "sg:address":"Rue Franklin-roosevelt 31",
    "sg:city":"Neufchateau",
    "sg:orig_category":"M\u00e9decins and sp\u00e9cialistes",
    "sg:phone":"+32 61 27 88 06",
    "sg:postcode":"6840",
    "sg:province":"Luxembourg",
    "wof:name":"Christian Pire",
    "wof:placetype":"venue"
},
  "geometry": {"coordinates":[5.4341888428,49.841583252],"type":"Point"}
}