{
  "type": "Feature",
  "properties": {
    "iso:country":"BE",
    "sg:address":"Polderdijkweg 16",
    "sg:city":"Antwerpen",
    "sg:classifiers":[
        {
            "category":"Shopping Center",
            "type":"Public Place"
        }
    ],
    "sg:phone":"+32 3 545 85 80",
    "sg:postcode":"2030",
    "sg:province":"Antwerpen",
    "sg:tags":[
        "enseignement",
        "formation"
    ],
    "wof:name":"S.g.s. Training Instit.",
    "wof:placetype":"venue"
},
  "geometry": {"coordinates":[4.343462944,51.2634544373],"type":"Point"}
}