{
  "type": "Feature",
  "properties": {
    "addr:full":"Keizerstraat 131 Beveren (haasdonk) Oost-Vlaanderen 9120",
    "addr:housenumber":"131",
    "addr:postcode":"9120",
    "addr:street":"Keizerstraat",
    "iso:country":"BE",
    "sg:address":"Keizerstraat 131",
    "sg:city":"Beveren (haasdonk)",
    "sg:classifiers":[
        {
            "category":"Retail",
            "subcategory":"Auto Repair",
            "type":"Services"
        }
    ],
    "sg:phone":"+32 3 775 70 03",
    "sg:postcode":"9120",
    "sg:province":"Oost-Vlaanderen",
    "sg:tags":[
        "automobile-body"
    ],
    "wof:name":"Van Raemdonck K",
    "wof:placetype":"venue"
},
  "geometry": {"coordinates":[4.2465162277,51.181892395],"type":"Point"}
}