{
  "type": "Feature",
  "properties": {
    "addr:full":"Chauss\u00c9e De Boondael 18 Elsene/ixelles Bruxelles-Capitale 1050",
    "addr:housenumber":"18",
    "addr:postcode":"1050",
    "addr:street":"Chausse\u0301E De Boondael",
    "iso:country":"BE",
    "sg:address":"Chauss\u00c9e De Boondael 18",
    "sg:city":"Elsene/ixelles",
    "sg:classifiers":[
        {
            "category":"Personal",
            "subcategory":"Beauty Salon",
            "type":"Services"
        }
    ],
    "sg:phone":"+32 2 647 61 07",
    "sg:postcode":"1050",
    "sg:province":"Bruxelles-Capitale",
    "sg:tags":[
        "de",
        "coiffure"
    ],
    "wof:name":"Coiffure Creatif",
    "wof:placetype":"venue"
},
  "geometry": {"coordinates":[4.3744821548,50.8273010254],"type":"Point"}
}