{
  "type": "Feature",
  "properties": {
    "addr:full":"Titecastraat 36 Brugge (sint-michiels) West-Vlaanderen 8200",
    "addr:housenumber":"36",
    "addr:postcode":"8200",
    "addr:street":"Titecastraat",
    "iso:country":"BE",
    "sg:address":"Titecastraat 36",
    "sg:city":"Brugge (sint-michiels)",
    "sg:classifiers":[
        {
            "category":"Shopping",
            "subcategory":"Crafts & Fabrics",
            "type":"Retail Goods"
        }
    ],
    "sg:phone":"+32 50 39 35 39",
    "sg:postcode":"8200",
    "sg:province":"West-Vlaanderen",
    "sg:tags":[
        "ceramic"
    ],
    "wof:name":"Terracotta",
    "wof:placetype":"venue"
},
  "geometry": {"coordinates":[3.2030448914,51.1939125061],"type":"Point"}
}