{
  "type": "Feature",
  "properties": {
    "iso:country":"BE",
    "sg:address":"Rue De La Laiterie 37",
    "sg:city":"Soumagne",
    "sg:orig_category":"Elektrische installaties voor woningen",
    "sg:phone":"+32 4 377 43 29",
    "sg:postcode":"4632",
    "sg:province":"Li\u00e8ge",
    "wof:name":"J.l.b. Entreprise",
    "wof:placetype":"venue"
},
  "geometry": {"coordinates":[5.7313871384,50.6486778259],"type":"Point"}
}