{
  "type": "Feature",
  "properties": {
    "iso:country":"BE",
    "sg:address":"Rue Joseph-laubain 1",
    "sg:city":"Gembloux",
    "sg:orig_category":"Fietsen Herstellingen motorfietsen Motorfietsen",
    "sg:phone":"+32 81 61 10 08",
    "sg:postcode":"5030",
    "sg:province":"Namur",
    "wof:name":"Michel Salmon",
    "wof:placetype":"venue"
},
  "geometry": {"coordinates":[4.6993942261,50.5582389832],"type":"Point"}
}