{
  "type": "Feature",
  "properties": {
    "addr:full":"Burgemeester Philipslaan 0 Maaseik Limburg 3680",
    "addr:housenumber":"0",
    "addr:postcode":"3680",
    "addr:street":"Burgemeester Philipslaan",
    "iso:country":"BE",
    "sg:address":"Burgemeester Philipslaan 0",
    "sg:city":"Maaseik",
    "sg:orig_category":"Blanchisseries and teintureries",
    "sg:phone":"+32 89 56 65 13",
    "sg:postcode":"3680",
    "sg:province":"Limburg",
    "wof:name":"Wassalon Hellings",
    "wof:placetype":"venue"
},
  "geometry": {"coordinates":[5.7900848389,51.0970497131],"type":"Point"}
}