{
  "type": "Feature",
  "properties": {
    "iso:country":"BE",
    "sg:address":"Kerkstraat 98",
    "sg:city":"Sint-gillis-waas",
    "sg:classifiers":[
        {
            "category":"Real Estate",
            "subcategory":"Architect",
            "type":"Services"
        }
    ],
    "sg:phone":"+32 3 707 08 18",
    "sg:postcode":"9170",
    "sg:province":"Oost-Vlaanderen",
    "wof:name":"Wilssens E",
    "wof:placetype":"venue"
},
  "geometry": {"coordinates":[4.1259589195,51.2185592651],"type":"Point"}
}