{
  "type": "Feature",
  "properties": {
    "iso:country":"BE",
    "sg:address":"Vilvoordsesteenweg 336",
    "sg:city":"Grimbergen",
    "sg:orig_category":"Mat\u00e9riel m\u00e9dical and orthop\u00e9dique and proth\u00e8ses Fab",
    "sg:phone":"+32 2 251 97 43",
    "sg:postcode":"1850",
    "sg:province":"Vlaams-Brabant",
    "wof:name":"Paul De Bernardin",
    "wof:placetype":"venue"
},
  "geometry": {"coordinates":[4.3928070068,50.9260902405],"type":"Point"}
}