{
  "type": "Feature",
  "properties": {
    "iso:country":"BE",
    "sg:address":"Rue De Binche 77",
    "sg:city":"Merbes-le-ch\u00c2teau",
    "sg:orig_category":"Eleveurs de bovins",
    "sg:phone":"+32 71 55 50 56",
    "sg:postcode":"6567",
    "sg:province":"Hainaut",
    "wof:name":"Daniel Aulit",
    "wof:placetype":"venue"
},
  "geometry": {"coordinates":[4.1760048866,50.3387641907],"type":"Point"}
}