{
  "type": "Feature",
  "properties": {
    "addr:full":"Rue De La Station 96 Waterloo Brabant Wallon 1410",
    "addr:housenumber":"96",
    "addr:postcode":"1410",
    "addr:street":"Rue De La Station",
    "iso:country":"BE",
    "sg:address":"Rue De La Station 96",
    "sg:city":"Waterloo",
    "sg:orig_category":"Cr\u00e8ches and garderies d'enfants. Activit\u00e9s r\u00e9cr\u00e9atives diverses",
    "sg:phone":"+32 2 353 03 43",
    "sg:postcode":"1410",
    "sg:province":"Brabant Wallon",
    "wof:name":"La Petite Ecole",
    "wof:placetype":"venue"
},
  "geometry": {"coordinates":[4.3920297623,50.7168731689],"type":"Point"}
}