{
  "type": "Feature",
  "properties": {
    "addr:full":"Ninoofsesteenweg 176 Dilbeek Vlaams-Brabant 1700",
    "addr:housenumber":"176",
    "addr:postcode":"1700",
    "addr:street":"Ninoofsesteenweg",
    "iso:country":"BE",
    "sg:address":"Ninoofsesteenweg 176",
    "sg:city":"Dilbeek",
    "sg:orig_category":"S\u00e9curit\u00e9 sociale",
    "sg:phone":"+32 2 569 28 89",
    "sg:postcode":"1700",
    "sg:province":"Vlaams-Brabant",
    "wof:name":"St.michielsbond",
    "wof:placetype":"venue"
},
  "geometry": {"coordinates":[4.2725791931,50.8445549011],"type":"Point"}
}