{
  "type": "Feature",
  "properties": {
    "addr:full":"Arcadelaan 40 Knokke-heist (heist-aan-zee) West-Vlaanderen 8301",
    "addr:housenumber":"40",
    "addr:postcode":"8301",
    "addr:street":"Arcadelaan",
    "iso:country":"BE",
    "sg:address":"Arcadelaan 40",
    "sg:city":"Knokke-heist (heist-aan-zee)",
    "sg:classifiers":[
        {
            "category":"Building & Trades",
            "subcategory":"Construction",
            "type":"Services"
        }
    ],
    "sg:phone":"+32 50 51 11 59",
    "sg:postcode":"8301",
    "sg:province":"West-Vlaanderen",
    "sg:tags":[
        "equipment",
        "sports-hall"
    ],
    "wof:name":"Poly-nederland",
    "wof:placetype":"venue"
},
  "geometry": {"coordinates":[3.2689790726,51.3415985107],"type":"Point"}
}