{
  "type": "Feature",
  "properties": {
    "addr:full":"Chemin De Ster 7 Stavelot Li\u00e8ge 4970",
    "addr:housenumber":"7",
    "addr:postcode":"4970",
    "addr:street":"Chemin De Ster",
    "iso:country":"BE",
    "sg:address":"Chemin De Ster 7",
    "sg:city":"Stavelot",
    "sg:classifiers":[
        {
            "category":"Recreation",
            "type":"Entertainment"
        }
    ],
    "sg:phone":"+32 80 88 05 69",
    "sg:postcode":"4970",
    "sg:province":"Li\u00e8ge",
    "sg:tags":[
        "diver",
        "amusement"
    ],
    "wof:name":"First Club",
    "wof:placetype":"venue"
},
  "geometry": {"coordinates":[5.912484169,50.3914718628],"type":"Point"}
}