{
  "type": "Feature",
  "properties": {
    "iso:country":"BE",
    "sg:address":"Diepmeerstraat 20",
    "sg:city":"Buggenhout",
    "sg:orig_category":"Motos. Entretien and r\u00e9parations de voitures. R\u00e9parations and entretien de motos",
    "sg:phone":"+32 52 33 74 70",
    "sg:postcode":"9255",
    "sg:province":"Oost-Vlaanderen",
    "wof:name":"Jo's Motorshop",
    "wof:placetype":"venue"
},
  "geometry": {"coordinates":[4.1903839111,51.025226593],"type":"Point"}
}