{
  "type": "Feature",
  "properties": {
    "addr:full":"Lijsterhoek 14 Beernem West-Vlaanderen 8730",
    "addr:housenumber":"14",
    "addr:postcode":"8730",
    "addr:street":"Lijsterhoek",
    "iso:country":"BE",
    "sg:address":"Lijsterhoek 14",
    "sg:city":"Beernem",
    "sg:orig_category":"Meubles D\u00e9taillants, Am\u00e9nagement de B\u00e2timents et de Cuisines",
    "sg:phone":"+32 50 79 13 03",
    "sg:postcode":"8730",
    "sg:province":"West-Vlaanderen",
    "wof:name":"Geoffrey Van Hulle",
    "wof:placetype":"venue"
},
  "geometry": {"coordinates":[3.3205609322,51.1522216797],"type":"Point"}
}