{
  "type": "Feature",
  "properties": {
    "iso:country":"BE",
    "sg:address":"Trieststraat 2",
    "sg:city":"Sint-gillis-waas",
    "sg:orig_category":"Fruitteelt",
    "sg:phone":"+32 3 770 73 37",
    "sg:postcode":"9170",
    "sg:province":"Oost-Vlaanderen",
    "wof:name":"Paul Rotthier",
    "wof:placetype":"venue"
},
  "geometry": {"coordinates":[4.1396842003,51.2279777527],"type":"Point"}
}