{
  "type": "Feature",
  "properties": {
    "addr:full":"Rue Joseph Ii 120 Bruxelles Bruxelles-Capitale 1000",
    "addr:housenumber":"120",
    "addr:postcode":"1000",
    "addr:street":"Rue Joseph Ii",
    "iso:country":"BE",
    "sg:address":"Rue Joseph Ii 120",
    "sg:city":"Bruxelles",
    "sg:classifiers":[
        {
            "category":"Social Services",
            "type":"Services"
        }
    ],
    "sg:phone":"+32 2 230 64 90",
    "sg:postcode":"1000",
    "sg:province":"Bruxelles-Capitale",
    "wof:name":"Forum Jeunesse De La Communaut\u00e9 Europ\u00e9enne",
    "wof:placetype":"venue"
},
  "geometry": {"coordinates":[4.3785238266,50.8445777893],"type":"Point"}
}