{
  "type": "Feature",
  "properties": {
    "addr:full":"Chaussee Verte 199 Saint-georges-sur-meuse Li\u00e8ge 4470",
    "addr:housenumber":"199",
    "addr:postcode":"4470",
    "addr:street":"Chaussee;Saint-Georges-Sur-Meuse Lie\u0300Ge",
    "iso:country":"BE",
    "sg:address":"Chaussee Verte 199",
    "sg:city":"Saint-georges-sur-meuse",
    "sg:classifiers":[
        {
            "category":"Real Estate",
            "subcategory":"Real Estate Services",
            "type":"Services"
        }
    ],
    "sg:phone":"+32 4 239 08 08",
    "sg:postcode":"4470",
    "sg:province":"Li\u00e8ge",
    "sg:tags":[
        "moving"
    ],
    "wof:name":"Fossoul D\u00e9m\u00e9nagement S.p.r.l.",
    "wof:placetype":"venue"
},
  "geometry": {"coordinates":[5.3562898636,50.620010376],"type":"Point"}
}