{
  "type": "Feature",
  "properties": {
    "addr:full":"Korte Minnestraat 26 Lebbeke Oost-Vlaanderen 9280",
    "addr:housenumber":"26",
    "addr:postcode":"9280",
    "addr:street":"Korte Minnestraat",
    "iso:country":"BE",
    "sg:address":"Korte Minnestraat 26",
    "sg:city":"Lebbeke",
    "sg:classifiers":[
        {
            "category":"Real Estate",
            "subcategory":"Architect",
            "type":"Services"
        }
    ],
    "sg:phone":"+32 52 35 10 75",
    "sg:postcode":"9280",
    "sg:province":"Oost-Vlaanderen",
    "wof:name":"Aelbrecht P",
    "wof:placetype":"venue"
},
  "geometry": {"coordinates":[4.1386461258,50.9811935425],"type":"Point"}
}