{
  "type": "Feature",
  "properties": {
    "addr:full":"Rue Bon 7 Erquelinnes Hainaut 6560",
    "addr:housenumber":"7",
    "addr:postcode":"6560",
    "addr:street":"Rue Bon",
    "iso:country":"BE",
    "sg:address":"Rue Bon 7",
    "sg:city":"Erquelinnes",
    "sg:orig_category":"Dierenartsen",
    "sg:phone":"+32 71 55 82 70",
    "sg:postcode":"6560",
    "sg:province":"Hainaut",
    "wof:name":"Bernard Christiaens",
    "wof:placetype":"venue"
},
  "geometry": {"coordinates":[4.1277937889,50.3133125305],"type":"Point"}
}