{
  "type": "Feature",
  "properties": {
    "iso:country":"BE",
    "sg:address":"55",
    "sg:city":"Grandroute 1435 Mont-saint-guibert",
    "sg:classifiers":[
        {
            "category":"Home & Garden",
            "subcategory":"Furniture",
            "type":"Retail Goods"
        }
    ],
    "sg:phone":"+32 10 65 00 45",
    "sg:postcode":"55",
    "sg:tags":[
        "household",
        "wood"
    ],
    "wof:name":"Menuiserie Saint-andre Sprl",
    "wof:placetype":"venue"
},
  "geometry": {"coordinates":[4.6453728676,50.6449165344],"type":"Point"}
}