{
  "type": "Feature",
  "properties": {
    "iso:country":"BE",
    "sg:address":"Felix Timmermanshof 15",
    "sg:city":"Nijlen",
    "sg:classifiers":[
        {
            "category":"Shopping",
            "subcategory":"Music",
            "type":"Retail Goods"
        }
    ],
    "sg:phone":"+32 3 411 23 56",
    "sg:postcode":"2560",
    "sg:province":"Antwerpen",
    "sg:tags":[
        "-",
        "cd's",
        "recorded",
        "cassette"
    ],
    "wof:name":"Retro World Belgium",
    "wof:placetype":"venue"
},
  "geometry": {"coordinates":[4.6982340813,51.1701164246],"type":"Point"}
}