{
  "type": "Feature",
  "properties": {
    "iso:country":"BE",
    "sg:address":"Avenue Ferdauci 35",
    "sg:city":"Brussel/bruxelles",
    "sg:orig_category":"M\u00e9decins and sp\u00e9cialistes",
    "sg:phone":"+32 2 268 48 84",
    "sg:postcode":"1020",
    "sg:province":"Bruxelles-Capitale",
    "wof:name":"Huib Lodewijks",
    "wof:placetype":"venue"
},
  "geometry": {"coordinates":[4.3655757904,50.8940925598],"type":"Point"}
}