{
  "type": "Feature",
  "properties": {
    "addr:full":"Menenstraat 17-19 Wevelgem West-Vlaanderen 8560",
    "addr:postcode":"17-19;8560",
    "addr:street":"Menenstraat",
    "iso:country":"BE",
    "sg:address":"Menenstraat 17-19",
    "sg:city":"Wevelgem",
    "sg:classifiers":[
        {
            "category":"Bars & Pubs",
            "type":"Food & Drink"
        }
    ],
    "sg:phone":"+32 56 42 29 08",
    "sg:postcode":"8560",
    "sg:province":"West-Vlaanderen",
    "wof:name":"Pompke ('t)",
    "wof:placetype":"venue"
},
  "geometry": {"coordinates":[3.1767950058,50.8073921204],"type":"Point"}
}