{
  "type": "Feature",
  "properties": {
    "iso:country":"BE",
    "sg:address":"Rue Saint-mathias 19",
    "sg:city":"Arlon (bonnert)",
    "sg:classifiers":[
        {
            "category":"Taxi",
            "type":"Transportation"
        }
    ],
    "sg:phone":"+32 63 22 18 97",
    "sg:postcode":"6700",
    "sg:province":"Luxembourg",
    "sg:tags":[
        "taxicab"
    ],
    "wof:name":"Taxi-euro",
    "wof:placetype":"venue"
},
  "geometry": {"coordinates":[5.8320150375,49.6845741272],"type":"Point"}
}