{
  "type": "Feature",
  "properties": {
    "addr:full":"Rue De Moncheret 48 Gerpinnes Hainaut 6280",
    "addr:housenumber":"48",
    "addr:postcode":"6280",
    "addr:street":"Rue De Moncheret;Hainaut",
    "iso:country":"BE",
    "sg:address":"Rue De Moncheret 48",
    "sg:city":"Gerpinnes",
    "sg:orig_category":"Banques and organismes de cr\u00e9dit",
    "sg:phone":"+32 71 50 15 65",
    "sg:postcode":"6280",
    "sg:province":"Hainaut",
    "wof:name":"Dexia",
    "wof:placetype":"venue"
},
  "geometry": {"coordinates":[4.5308351517,50.3463401794],"type":"Point"}
}