{
  "type": "Feature",
  "properties": {
    "addr:full":"Boulevard Th\u00e9o Lambert 21 Bruxelles (anderlecht) Bruxelles-Capitale 1070",
    "addr:housenumber":"21",
    "addr:postcode":"1070",
    "addr:street":"Boulevard The\u0301O Lambert",
    "iso:country":"BE",
    "sg:address":"Boulevard Th\u00e9o Lambert 21",
    "sg:city":"Bruxelles (anderlecht)",
    "sg:classifiers":[
        {
            "category":"Real Estate",
            "subcategory":"Real Estate Services",
            "type":"Services"
        }
    ],
    "sg:phone":"+32 2 521 13 18",
    "sg:postcode":"1070",
    "sg:province":"Bruxelles-Capitale",
    "wof:name":"I.m.c.",
    "wof:placetype":"venue"
},
  "geometry": {"coordinates":[4.2988519669,50.8286552429],"type":"Point"}
}