{
  "type": "Feature",
  "properties": {
    "iso:country":"BE",
    "sg:address":"Kuilenstraat 76",
    "sg:city":"Tongeren (vreren)",
    "sg:classifiers":[
        {
            "category":"Banks & Credit Unions",
            "subcategory":"Investment Brokerage",
            "type":"Services"
        }
    ],
    "sg:phone":"+32 12 39 32 76",
    "sg:postcode":"3700",
    "sg:province":"Limburg",
    "sg:tags":[
        "fence"
    ],
    "wof:name":"Van Kieldonck Christian",
    "wof:placetype":"venue"
},
  "geometry": {"coordinates":[5.4694681168,50.7801628113],"type":"Point"}
}