{
  "type": "Feature",
  "properties": {
    "addr:full":"Koekelbronstraat 5b Broekom Limburg 3840",
    "addr:housenumber":"5b",
    "addr:postcode":"3840",
    "addr:street":"Koekelbronstraat",
    "iso:country":"BE",
    "sg:address":"Koekelbronstraat 5b",
    "sg:city":"Broekom",
    "sg:orig_category":"Threader Dies",
    "sg:phone":"+32 12 74 10 05",
    "sg:postcode":"3840",
    "sg:province":"Limburg",
    "wof:name":"Yerna Johnny",
    "wof:placetype":"venue"
},
  "geometry": {"coordinates":[5.3320760727,50.7813262939],"type":"Point"}
}