{
  "type": "Feature",
  "properties": {
    "iso:country":"BE",
    "sg:address":"Kruisveldstraat 8b4",
    "sg:city":"Aalst",
    "sg:orig_category":"Artsen and specialisten",
    "sg:phone":"+32 53 71 12 26",
    "sg:postcode":"9300",
    "sg:province":"Oost-Vlaanderen",
    "wof:name":"Jan Germonpre",
    "wof:placetype":"venue"
},
  "geometry": {"coordinates":[4.058382988,50.9456634521],"type":"Point"}
}