{
  "type": "Feature",
  "properties": {
    "addr:full":"Rue De Landen 51d Hannut Li\u00e8ge 4280",
    "addr:housenumber":"51d",
    "addr:postcode":"4280",
    "addr:street":"Rue De Landen",
    "iso:country":"BE",
    "sg:address":"Rue De Landen 51d",
    "sg:city":"Hannut",
    "sg:classifiers":[
        {
            "category":"Home & Garden",
            "subcategory":"Building Materials",
            "type":"Retail Goods"
        }
    ],
    "sg:phone":"+32 19 51 20 60",
    "sg:postcode":"4280",
    "sg:province":"Li\u00e8ge",
    "sg:tags":[
        "article",
        "-",
        "do-it-yourself"
    ],
    "wof:name":"Brico + Dullaers",
    "wof:placetype":"venue"
},
  "geometry": {"coordinates":[5.0819439888,50.6812095642],"type":"Point"}
}