{
  "type": "Feature",
  "properties": {
    "addr:full":"Zwijnaardsesteenweg 755 Gent Oost-Vlaanderen 9000",
    "addr:housenumber":"755",
    "addr:postcode":"9000",
    "addr:street":"Zwijnaardsesteenweg;Oost-Vlaanderen",
    "iso:country":"BE",
    "sg:address":"Zwijnaardsesteenweg 755",
    "sg:city":"Gent",
    "sg:orig_category":"Bloemen and planten",
    "sg:phone":"+32 9 220 92 33",
    "sg:postcode":"9000",
    "sg:province":"Oost-Vlaanderen",
    "wof:name":"Brigitte",
    "wof:placetype":"venue"
},
  "geometry": {"coordinates":[3.7200119495,51.0185050964],"type":"Point"}
}