{
  "type": "Feature",
  "properties": {
    "iso:country":"BE",
    "sg:address":"Place De La Lib\u00c9ration 12",
    "sg:city":"Ath",
    "sg:orig_category":"Epiceries",
    "sg:phone":"+32 68 28 34 39",
    "sg:postcode":"7800",
    "sg:province":"Hainaut",
    "wof:name":"Maison La Chaumi\u00c8re",
    "wof:placetype":"venue"
},
  "geometry": {"coordinates":[3.7725191116,50.6343040466],"type":"Point"}
}