{
  "type": "Feature",
  "properties": {
    "addr:full":"Rue Astrid 1 Charleroi (gosselies) Hainaut 6041",
    "addr:housenumber":"1",
    "addr:postcode":"6041",
    "addr:street":"Rue Astrid",
    "iso:country":"BE",
    "sg:address":"Rue Astrid 1",
    "sg:city":"Charleroi (gosselies)",
    "sg:classifiers":[
        {
            "category":"Sports & Exercise",
            "subcategory":"Tennis Court",
            "type":"Entertainment"
        }
    ],
    "sg:phone":"+32 71 35 11 05",
    "sg:postcode":"6041",
    "sg:province":"Hainaut",
    "sg:tags":[
        "shoe"
    ],
    "wof:name":"Mike Sports",
    "wof:placetype":"venue"
},
  "geometry": {"coordinates":[4.4314317703,50.4685935974],"type":"Point"}
}