{
  "type": "Feature",
  "properties": {
    "addr:full":"Sportstraat 4 Lanaken Limburg 3620",
    "addr:housenumber":"4",
    "addr:postcode":"3620",
    "addr:street":"Sportstraat",
    "iso:country":"BE",
    "sg:address":"Sportstraat 4",
    "sg:city":"Lanaken",
    "sg:orig_category":"Diensten voor huisdieren",
    "sg:phone":"+32 89 71 38 81",
    "sg:postcode":"3620",
    "sg:province":"Limburg",
    "wof:name":"Ludo Packle",
    "wof:placetype":"venue"
},
  "geometry": {"coordinates":[5.6612691879,50.8976516724],"type":"Point"}
}