{
  "type": "Feature",
  "properties": {
    "iso:country":"BE",
    "sg:address":"Rue D'hainin 98",
    "sg:city":"Hensies (hainin)",
    "sg:classifiers":[
        {
            "category":"Professional",
            "subcategory":"Computer Services",
            "type":"Services"
        }
    ],
    "sg:phone":"+32 65 51 26 85",
    "sg:postcode":"7350",
    "sg:province":"Hainaut",
    "sg:tags":[
        "-",
        "processing",
        "data"
    ],
    "wof:name":"Cauchie S",
    "wof:placetype":"venue"
},
  "geometry": {"coordinates":[3.7654309273,50.4354934692],"type":"Point"}
}