{
  "type": "Feature",
  "properties": {
    "addr:full":"Buyckstraat 22 Anzegem West-Vlaanderen 8570",
    "addr:housenumber":"22",
    "addr:postcode":"8570",
    "addr:street":"Buyckstraat",
    "iso:country":"BE",
    "sg:address":"Buyckstraat 22",
    "sg:city":"Anzegem",
    "sg:orig_category":"Installation de menuiserie en bois and plastique",
    "sg:phone":"+32 56 68 17 16",
    "sg:postcode":"8570",
    "sg:province":"West-Vlaanderen",
    "wof:name":"Do-it",
    "wof:placetype":"venue"
},
  "geometry": {"coordinates":[3.4759759903,50.8345222473],"type":"Point"}
}