{
  "type": "Feature",
  "properties": {
    "iso:country":"BE",
    "sg:address":"Rue Des Trieux 14",
    "sg:city":"La Louviere",
    "sg:classifiers":[
        {
            "category":"Shopping",
            "subcategory":"Baby Store",
            "type":"Retail Goods"
        }
    ],
    "sg:phone":"+32 64 28 22 12",
    "sg:postcode":"7110",
    "sg:province":"Hainaut",
    "sg:tags":[
        "article",
        "b\u00e9b\u00e9s",
        "pour"
    ],
    "wof:name":"Bonjour Bebe",
    "wof:placetype":"venue"
},
  "geometry": {"coordinates":[4.1505050659,50.4826698303],"type":"Point"}
}