{
  "type": "Feature",
  "properties": {
    "iso:country":"BE",
    "sg:address":"Mechelbaan 467",
    "sg:city":"Putte",
    "sg:orig_category":"Plaatsen van vloer- and muurbekleding Vloer- and muurbekleding",
    "sg:phone":"+32 15 75 54 39",
    "sg:postcode":"2580",
    "sg:province":"Antwerpen",
    "wof:name":"Getena",
    "wof:placetype":"venue"
},
  "geometry": {"coordinates":[4.6308999062,51.0557594299],"type":"Point"}
}