{
  "type": "Feature",
  "properties": {
    "iso:country":"BE",
    "sg:address":"Eikstraat 15",
    "sg:city":"Lochristi",
    "sg:orig_category":"Plantes and fleurs Gr",
    "sg:phone":"+32 9 355 72 21",
    "sg:postcode":"9080",
    "sg:province":"Oost-Vlaanderen",
    "wof:name":"Van Hecke P",
    "wof:placetype":"venue"
},
  "geometry": {"coordinates":[3.8819539547,51.1023406982],"type":"Point"}
}