{
  "type": "Feature",
  "properties": {
    "iso:country":"BE",
    "sg:address":"Loddershoekstraat 1",
    "sg:city":"Ternat (wambeek)",
    "sg:classifiers":[
        {
            "category":"Health Services",
            "subcategory":"Doctor",
            "type":"Services"
        }
    ],
    "sg:phone":"+32 2 582 55 14",
    "sg:postcode":"1741",
    "sg:province":"Vlaams-Brabant",
    "sg:tags":[
        "medicinephysicians",
        "surgeon"
    ],
    "wof:name":"Bvba Jose Huylebroek",
    "wof:placetype":"venue"
},
  "geometry": {"coordinates":[4.1424207687,50.8601341248],"type":"Point"}
}