{
  "type": "Feature",
  "properties": {
    "addr:full":"Maandagmarkt 12-14 Halle Vlaams-Brabant 1500",
    "addr:housenumber":"12-14",
    "addr:postcode":"1500",
    "iso:country":"BE",
    "sg:address":"Maandagmarkt 12-14",
    "sg:city":"Halle",
    "sg:classifiers":[
        {
            "category":"Shopping",
            "subcategory":"Clothing, Apparel, & Fashions",
            "type":"Retail Goods"
        }
    ],
    "sg:phone":"+32 2 356 71 62",
    "sg:postcode":"1500",
    "sg:province":"Vlaams-Brabant",
    "sg:tags":[
        "boutique"
    ],
    "wof:name":"Popsy",
    "wof:placetype":"venue"
},
  "geometry": {"coordinates":[4.2367949486,50.7359695435],"type":"Point"}
}