{
  "type": "Feature",
  "properties": {
    "addr:full":"Molenstraat 24 Laarne Oost-Vlaanderen 9270",
    "addr:housenumber":"24",
    "addr:postcode":"9270",
    "addr:street":"Molenstraat",
    "iso:country":"BE",
    "sg:address":"Molenstraat 24",
    "sg:city":"Laarne",
    "sg:classifiers":[
        {
            "category":"Health Services",
            "subcategory":"Dentist",
            "type":"Services"
        }
    ],
    "sg:phone":"+32 9 369 85 90",
    "sg:postcode":"9270",
    "sg:province":"Oost-Vlaanderen",
    "wof:name":"Vagenende E",
    "wof:placetype":"venue"
},
  "geometry": {"coordinates":[3.8533658981,51.0288696289],"type":"Point"}
}