{
  "type": "Feature",
  "properties": {
    "iso:country":"BE",
    "sg:address":"Rue Jean Philippe 26",
    "sg:city":"Lasne",
    "sg:orig_category":"Landmeters",
    "sg:phone":"+32 2 653 82 96",
    "sg:postcode":"1380",
    "sg:province":"Brabant Wallon",
    "wof:name":"Guy Berghmans",
    "wof:placetype":"venue"
},
  "geometry": {"coordinates":[4.4598679543,50.7175254822],"type":"Point"}
}