{
  "type": "Feature",
  "properties": {
    "addr:full":"Rue Du Pressoir 36 Libramont-chevigny (libramont) Luxembourg 6800",
    "addr:housenumber":"36",
    "addr:postcode":"6800",
    "addr:street":"Rue Du Pressoir",
    "iso:country":"BE",
    "sg:address":"Rue Du Pressoir 36",
    "sg:city":"Libramont-chevigny (libramont)",
    "sg:classifiers":[
        {
            "category":"Real Estate",
            "subcategory":"Architect",
            "type":"Services"
        }
    ],
    "sg:phone":"+32 61 23 38 55",
    "sg:postcode":"6800",
    "sg:province":"Luxembourg",
    "wof:name":"Reginster E",
    "wof:placetype":"venue"
},
  "geometry": {"coordinates":[5.3761348724,49.9199943542],"type":"Point"}
}