{
  "type": "Feature",
  "properties": {
    "iso:country":"BE",
    "sg:address":"Rue Gaston Barla 31",
    "sg:city":"Theux (polleur)",
    "sg:classifiers":[
        {
            "category":"Health Services",
            "subcategory":"Health Practitioner",
            "type":"Services"
        }
    ],
    "sg:phone":"+32 87 22 83 68",
    "sg:postcode":"4910",
    "sg:province":"Li\u00e8ge",
    "sg:tags":[
        "physiotherapist"
    ],
    "wof:name":"Peeters Alexandre",
    "wof:placetype":"venue"
},
  "geometry": {"coordinates":[5.8884468079,50.5543746948],"type":"Point"}
}