{
  "type": "Feature",
  "properties": {
    "addr:full":"De Klerckstraat 10 Knokke-heist (knokke) West-Vlaanderen 8300",
    "addr:housenumber":"10",
    "addr:postcode":"8300",
    "addr:street":"Klerckstraat",
    "iso:country":"BE",
    "sg:address":"De Klerckstraat 10",
    "sg:city":"Knokke-heist (knokke)",
    "sg:classifiers":[
        {
            "category":"Building & Trades",
            "subcategory":"Electrical",
            "type":"Services"
        }
    ],
    "sg:phone":"+32 50 60 97 53",
    "sg:postcode":"8300",
    "sg:province":"West-Vlaanderen",
    "sg:tags":[
        "electric",
        "-",
        "housewiring",
        "contractor"
    ],
    "wof:name":"Ovelec",
    "wof:placetype":"venue"
},
  "geometry": {"coordinates":[3.2941179276,51.3403892517],"type":"Point"}
}