{
  "type": "Feature",
  "properties": {
    "iso:country":"BE",
    "sg:address":"Rue De La Trinit\u00c9 14",
    "sg:city":"Cerfontaine",
    "sg:orig_category":"Eleveurs de bovins",
    "sg:phone":"+32 71 64 41 14",
    "sg:postcode":"5630",
    "sg:province":"Namur",
    "wof:name":"Jean-pierre Goblet",
    "wof:placetype":"venue"
},
  "geometry": {"coordinates":[4.4226531982,50.1733055115],"type":"Point"}
}