{
  "type": "Feature",
  "properties": {
    "addr:full":"Route De Mont St Jean 8 Hoeilaart Vlaams-Brabant 1560",
    "addr:housenumber":"8",
    "addr:postcode":"1560",
    "addr:street":"Route De Mont St Jean",
    "iso:country":"BE",
    "sg:address":"Route De Mont St Jean 8",
    "sg:city":"Hoeilaart",
    "sg:orig_category":"Diensten voor huisdieren Sportterreinen and installaties behalve sportcentra",
    "sg:phone":"+32 2 675 08 97",
    "sg:postcode":"1560",
    "sg:province":"Vlaams-Brabant",
    "wof:name":"Poney Circus",
    "wof:placetype":"venue"
},
  "geometry": {"coordinates":[4.4796628952,50.7626152039],"type":"Point"}
}