{
  "type": "Feature",
  "properties": {
    "addr:full":"Molenbos 65 Nijlen Antwerpen 2560",
    "addr:housenumber":"65",
    "addr:postcode":"2560",
    "addr:street":"Molenbos",
    "iso:country":"BE",
    "sg:address":"Molenbos 65",
    "sg:city":"Nijlen",
    "sg:classifiers":[
        {
            "category":"Cafe",
            "type":"Food & Drink"
        }
    ],
    "sg:phone":"+32 3 481 63 81",
    "sg:postcode":"2560",
    "sg:province":"Antwerpen",
    "sg:tags":[
        "caf\u00e9s"
    ],
    "wof:name":"Walter Lambrechts",
    "wof:placetype":"venue"
},
  "geometry": {"coordinates":[4.6797208786,51.1517944336],"type":"Point"}
}