{
  "type": "Feature",
  "properties": {
    "addr:full":"Avenue Des Traquets 147b Bruxelles (auderghem) Bruxelles-Capitale 1160",
    "addr:housenumber":"147b",
    "addr:postcode":"1160",
    "addr:street":"Avenue Des Traquets",
    "iso:country":"BE",
    "sg:address":"Avenue Des Traquets 147b",
    "sg:city":"Bruxelles (auderghem)",
    "sg:classifiers":[
        {
            "category":"Health Services",
            "subcategory":"Doctor",
            "type":"Services"
        }
    ],
    "sg:phone":"+32 2 660 84 84",
    "sg:postcode":"1160",
    "sg:province":"Bruxelles-Capitale",
    "sg:tags":[
        "medicinephysicians",
        "surgeon"
    ],
    "wof:name":"De Vos A",
    "wof:placetype":"venue"
},
  "geometry": {"coordinates":[4.4197201729,50.8221206665],"type":"Point"}
}