{
  "type": "Feature",
  "properties": {
    "iso:country":"BE",
    "sg:address":"Julius Dooghelaan 83",
    "sg:city":"Brugge",
    "sg:orig_category":"Brood, gebak and snoepgoed",
    "sg:phone":"+32 50 35 49 51",
    "sg:postcode":"8310",
    "sg:province":"West-Vlaanderen",
    "wof:name":"Bakkerij Ronny",
    "wof:placetype":"venue"
},
  "geometry": {"coordinates":[3.2394099236,51.2177505493],"type":"Point"}
}