{
  "type": "Feature",
  "properties": {
    "iso:country":"BE",
    "sg:address":"Rue Marconi 217",
    "sg:city":"Vorst/forest",
    "sg:orig_category":"Services fun\u00e9raires",
    "sg:phone":"+32 2 345 58 30",
    "sg:postcode":"1190",
    "sg:province":"Bruxelles-Capitale",
    "wof:name":"Vanhorenbeke & Zoon/vanhorenbeke & Fils",
    "wof:placetype":"venue"
},
  "geometry": {"coordinates":[4.3410830498,50.8154678345],"type":"Point"}
}