{
  "type": "Feature",
  "properties": {
    "iso:country":"BE",
    "sg:address":"Rue Des H\u00eatres 82",
    "sg:city":"Bastogne",
    "sg:classifiers":[
        {
            "category":"Health Services",
            "subcategory":"Doctor",
            "type":"Services"
        }
    ],
    "sg:phone":"+32 61 21 21 46",
    "sg:postcode":"6600",
    "sg:province":"Luxembourg",
    "sg:tags":[
        "medicinephysicians",
        "surgeon"
    ],
    "wof:name":"Leclercq Jacques",
    "wof:placetype":"venue"
},
  "geometry": {"coordinates":[5.7306132317,50.0045852661],"type":"Point"}
}