{
  "type": "Feature",
  "properties": {
    "iso:country":"BE",
    "sg:address":"Marktplein 1",
    "sg:city":"Wingene",
    "sg:orig_category":"Artsen and specialisten",
    "sg:phone":"+32 51 61 39 75",
    "sg:postcode":"8750",
    "sg:province":"West-Vlaanderen",
    "wof:name":"Marjan Thomare",
    "wof:placetype":"venue"
},
  "geometry": {"coordinates":[3.2783250809,51.0577087402],"type":"Point"}
}