{
  "type": "Feature",
  "properties": {
    "addr:full":"Gebroeders Vandeveldestraat 99 Gent Oost-Vlaanderen 9000",
    "addr:housenumber":"99",
    "addr:postcode":"9000",
    "addr:street":"Gebroeders Vandeveldestraat;Oost-Vlaanderen",
    "iso:country":"BE",
    "sg:address":"Gebroeders Vandeveldestraat 99",
    "sg:city":"Gent",
    "sg:orig_category":"Avocats and conseillers juridiques. Balie van Gent. Avocats and conseillers juridiques. Balie van Ge",
    "sg:phone":"+32 9 223 41 46",
    "sg:postcode":"9000",
    "sg:province":"Oost-Vlaanderen",
    "wof:name":"Boelaert Carlo",
    "wof:placetype":"venue"
},
  "geometry": {"coordinates":[3.7181649208,51.0503959656],"type":"Point"}
}