{
  "type": "Feature",
  "properties": {
    "iso:country":"BE",
    "sg:address":"Molenlaan 25",
    "sg:city":"Lichtervelde",
    "sg:classifiers":[
        {
            "category":"Utilities",
            "subcategory":"Recycling",
            "type":"Services"
        }
    ],
    "sg:phone":"+32 51 72 43 20",
    "sg:postcode":"8810",
    "sg:province":"West-Vlaanderen",
    "sg:tags":[
        "rubbish",
        "removal"
    ],
    "wof:name":"Devoogt-declercq Bvba",
    "wof:placetype":"venue"
},
  "geometry": {"coordinates":[3.1502389908,51.0250816345],"type":"Point"}
}