{
  "type": "Feature",
  "properties": {
    "iso:country":"BE",
    "sg:address":"Route De La Scierie 1",
    "sg:city":"Manhay (dochamps)",
    "sg:classifiers":[
        {
            "category":"Health Services",
            "subcategory":"Health Practitioner",
            "type":"Services"
        }
    ],
    "sg:phone":"+32 86 45 51 81",
    "sg:postcode":"6960",
    "sg:province":"Luxembourg",
    "sg:tags":[
        "physiotherapist"
    ],
    "wof:name":"Chignesse G",
    "wof:placetype":"venue"
},
  "geometry": {"coordinates":[5.6323652267,50.2535324097],"type":"Point"}
}