{
  "type": "Feature",
  "properties": {
    "iso:country":"BE",
    "sg:address":"Rue Du Gouvernement 25",
    "sg:city":"Mons",
    "sg:classifiers":[
        {
            "category":"Arena",
            "subcategory":"Sports Club",
            "type":"Entertainment"
        }
    ],
    "sg:phone":"+32 65 33 59 33",
    "sg:postcode":"7000",
    "sg:province":"Hainaut",
    "sg:tags":[
        "de"
    ],
    "wof:name":"P.c. L'esp\u00c9rance",
    "wof:placetype":"venue"
},
  "geometry": {"coordinates":[3.9577829838,50.4555702209],"type":"Point"}
}