{
  "type": "Feature",
  "properties": {
    "addr:full":"Blauwesteenstraat 108b Kontich Antwerpen 2550",
    "addr:housenumber":"108b",
    "addr:postcode":"2550",
    "addr:street":"Blauwesteenstraat",
    "iso:country":"BE",
    "sg:address":"Blauwesteenstraat 108b",
    "sg:city":"Kontich",
    "sg:classifiers":[
        {
            "category":"Building & Trades",
            "subcategory":"Construction",
            "type":"Services"
        }
    ],
    "sg:phone":"+32 3 458 52 01",
    "sg:postcode":"2550",
    "sg:province":"Antwerpen",
    "sg:tags":[
        "carpenter"
    ],
    "wof:name":"Cleys J",
    "wof:placetype":"venue"
},
  "geometry": {"coordinates":[4.4524288177,51.1257591248],"type":"Point"}
}