{
  "type": "Feature",
  "properties": {
    "addr:full":"Rue Henri Grenier 17 Orp-jauche Brabant Wallon 1350",
    "addr:housenumber":"17",
    "addr:postcode":"1350",
    "addr:street":"Rue Henri Grenier",
    "iso:country":"BE",
    "sg:address":"Rue Henri Grenier 17",
    "sg:city":"Orp-jauche",
    "sg:orig_category":"D\u00e9chets and d\u00e9bris Gr",
    "sg:phone":"+32 19 63 43 17",
    "sg:postcode":"1350",
    "sg:province":"Brabant Wallon",
    "wof:name":"Louison Desbesel",
    "wof:placetype":"venue"
},
  "geometry": {"coordinates":[4.9848179817,50.6927146912],"type":"Point"}
}