{
  "type": "Feature",
  "properties": {
    "iso:country":"BE",
    "sg:address":"Haverwerf 14",
    "sg:city":"Mechelen",
    "sg:orig_category":"Artistes ind\u00e9pendants. Animations diverses",
    "sg:phone":"+32 15 33 02 20",
    "sg:postcode":"2800",
    "sg:province":"Antwerpen",
    "wof:name":"Connie Neefs",
    "wof:placetype":"venue"
},
  "geometry": {"coordinates":[4.475025177,51.0267868042],"type":"Point"}
}