{
  "type": "Feature",
  "properties": {
    "addr:full":"Devoerlaan 104 Vilvoorde Vlaams-Brabant 1800",
    "addr:housenumber":"104",
    "addr:postcode":"1800",
    "addr:street":"Devoerlaan",
    "iso:country":"BE",
    "sg:address":"Devoerlaan 104",
    "sg:city":"Vilvoorde",
    "sg:orig_category":"Traitements param\u00e9dicaux",
    "sg:phone":"+32 2 267 85 58",
    "sg:postcode":"1800",
    "sg:province":"Vlaams-Brabant",
    "wof:name":"Isabelle Craenembroeck",
    "wof:placetype":"venue"
},
  "geometry": {"coordinates":[4.3685059547,50.9144058228],"type":"Point"}
}