{
  "type": "Feature",
  "properties": {
    "addr:full":"Place Des Braban\u00c7ons 9 Ottignies-louvain-la-neuve Brabant Wallon 1348",
    "addr:housenumber":"9",
    "addr:postcode":"1348",
    "addr:street":"Place Des Brabanc\u0327Ons",
    "iso:country":"BE",
    "sg:address":"Place Des Braban\u00c7ons 9",
    "sg:city":"Ottignies-louvain-la-neuve",
    "sg:classifiers":[
        {
            "category":"Personal",
            "subcategory":"Beauty Salon",
            "type":"Services"
        }
    ],
    "sg:phone":"+32 10 45 15 46",
    "sg:postcode":"1348",
    "sg:province":"Brabant Wallon",
    "sg:tags":[
        "de",
        "coiffure"
    ],
    "wof:name":"Coiffure Antoine",
    "wof:placetype":"venue"
},
  "geometry": {"coordinates":[4.616256237,50.6686515808],"type":"Point"}
}