{
  "type": "Feature",
  "properties": {
    "addr:full":"Vlindersstraat 293 Anderlecht/anderlecht Bruxelles-Capitale 1070",
    "addr:housenumber":"293",
    "addr:postcode":"1070",
    "addr:street":"Vlindersstraat",
    "iso:country":"BE",
    "sg:address":"Vlindersstraat 293",
    "sg:city":"Anderlecht/anderlecht",
    "sg:orig_category":"Artsen and specialisten",
    "sg:phone":"+32 2 527 04 20",
    "sg:postcode":"1070",
    "sg:province":"Bruxelles-Capitale",
    "wof:name":"Abrassart",
    "wof:placetype":"venue"
},
  "geometry": {"coordinates":[4.2657709122,50.8350486755],"type":"Point"}
}