{
  "type": "Feature",
  "properties": {
    "addr:full":"Rue Du Mont-gallois 50 Mouscron Hainaut 7700",
    "addr:housenumber":"50",
    "addr:postcode":"7700",
    "addr:street":"Rue Du Mont-Gallois",
    "iso:country":"BE",
    "sg:address":"Rue Du Mont-gallois 50",
    "sg:city":"Mouscron",
    "sg:orig_category":"Artistes ind\u00e9pendants. Vitrage. Transformation and fa\u00e7onnage du verre plat",
    "sg:phone":"+32 56 84 09 50",
    "sg:postcode":"7700",
    "sg:province":"Hainaut",
    "wof:name":"Lr Vitraux",
    "wof:placetype":"venue"
},
  "geometry": {"coordinates":[3.2295000553,50.7517204285],"type":"Point"}
}