{
  "type": "Feature",
  "properties": {
    "iso:country":"BE",
    "sg:address":"Chemin Des Glaneurs 3",
    "sg:city":"Chaumont-gistoux",
    "sg:orig_category":"Diverse bedrijfsbeheeradviesbureaus",
    "sg:phone":"+32 10 22 49 30",
    "sg:postcode":"1325",
    "sg:province":"Brabant Wallon",
    "wof:name":"P.p. Management",
    "wof:placetype":"venue"
},
  "geometry": {"coordinates":[4.6394891739,50.6936454773],"type":"Point"}
}