{
  "type": "Feature",
  "properties": {
    "iso:country":"BE",
    "sg:address":"Chauss\u00c9e D'alsemberg 803",
    "sg:city":"Ukkel/uccle",
    "sg:orig_category":"V\u00eatements pour b\u00e9b\u00e9s and enfants. V\u00eatements pour Dames. Articles pour b\u00e9b\u00e9s",
    "sg:phone":"+32 2 376 66 56",
    "sg:postcode":"1180",
    "sg:province":"Bruxelles-Capitale",
    "wof:name":"Pr\u00c9maman",
    "wof:placetype":"venue"
},
  "geometry": {"coordinates":[4.3364491463,50.802066803],"type":"Point"}
}