{
  "type": "Feature",
  "properties": {
    "iso:country":"BE",
    "sg:address":"Chemin \u00e0 Rocs 30",
    "sg:city":"Soignies (horrues)",
    "sg:classifiers":[
        {
            "category":"Education",
            "subcategory":"Music School",
            "type":"Public Place"
        }
    ],
    "sg:phone":"+32 67 33 15 60",
    "sg:postcode":"7060",
    "sg:province":"Hainaut",
    "sg:tags":[
        "-",
        "teacher",
        "private"
    ],
    "wof:name":"Petits Malins (les) Asbl",
    "wof:placetype":"venue"
},
  "geometry": {"coordinates":[4.0724000931,50.5779037476],"type":"Point"}
}