{
  "type": "Feature",
  "properties": {
    "iso:country":"BE",
    "sg:address":"Kuringersteenweg 496",
    "sg:city":"Kuringen",
    "sg:orig_category":"Meubelzaken, woning- and keukeninrichting Textiel",
    "sg:phone":"+32 11 25 29 29",
    "sg:postcode":"3511",
    "sg:province":"Limburg",
    "wof:name":"Sleepy Kuringen",
    "wof:placetype":"venue"
},
  "geometry": {"coordinates":[5.2839150429,50.943107605],"type":"Point"}
}