{
  "type": "Feature",
  "properties": {
    "iso:country":"BE",
    "sg:address":"Rue Kerckx 4",
    "sg:city":"Elsene/ixelles",
    "sg:classifiers":[
        {
            "category":"Taxi",
            "type":"Transportation"
        }
    ],
    "sg:phone":"+32 2 644 17 52",
    "sg:postcode":"1050",
    "sg:province":"Bruxelles-Capitale",
    "wof:name":"Ali Agharas",
    "wof:placetype":"venue"
},
  "geometry": {"coordinates":[4.3740291595,50.8306770325],"type":"Point"}
}