{
  "type": "Feature",
  "properties": {
    "iso:country":"BE",
    "sg:address":"Ravenbergstraat 34",
    "sg:city":"Mechelen",
    "sg:classifiers":[
        {
            "category":"Health Services",
            "subcategory":"Health Practitioner",
            "type":"Services"
        }
    ],
    "sg:phone":"+32 15 41 26 43",
    "sg:postcode":"2800",
    "sg:province":"Antwerpen",
    "sg:tags":[
        "physiotherapist"
    ],
    "wof:name":"De Ryck J",
    "wof:placetype":"venue"
},
  "geometry": {"coordinates":[4.4797258377,51.0220108032],"type":"Point"}
}