{
  "type": "Feature",
  "properties": {
    "iso:country":"BE",
    "sg:address":"Chemin Du Prince 23",
    "sg:city":"Jurbise (erbisoeul)",
    "sg:classifiers":[
        {
            "category":"Health Services",
            "subcategory":"Health Practitioner",
            "type":"Services"
        }
    ],
    "sg:phone":"+32 65 22 59 72",
    "sg:postcode":"7050",
    "sg:province":"Hainaut",
    "sg:tags":[
        "physiotherapist"
    ],
    "wof:name":"Albrecht Christine",
    "wof:placetype":"venue"
},
  "geometry": {"coordinates":[3.8867061138,50.5067825317],"type":"Point"}
}