{
  "type": "Feature",
  "properties": {
    "addr:full":"Rupelweg 6 Boom Antwerpen 2850",
    "addr:housenumber":"6",
    "addr:postcode":"2850",
    "addr:street":"Rupelweg",
    "iso:country":"BE",
    "sg:address":"Rupelweg 6",
    "sg:city":"Boom",
    "sg:classifiers":[
        {
            "category":"Utilities",
            "subcategory":"Recycling",
            "type":"Services"
        }
    ],
    "sg:phone":"+32 3 844 20 25",
    "sg:postcode":"2850",
    "sg:province":"Antwerpen",
    "sg:tags":[
        "rubbish",
        "removal"
    ],
    "wof:name":"Big-city",
    "wof:placetype":"venue"
},
  "geometry": {"coordinates":[4.3560271263,51.0938873291],"type":"Point"}
}