{
  "type": "Feature",
  "properties": {
    "addr:full":"Koolstraat 49 Aalst Oost-Vlaanderen 9300",
    "addr:housenumber":"49",
    "addr:postcode":"9300",
    "addr:street":"Koolstraat",
    "iso:country":"BE",
    "sg:address":"Koolstraat 49",
    "sg:city":"Aalst",
    "sg:classifiers":[
        {
            "category":"Shopping",
            "subcategory":"Clothing, Apparel, & Fashions",
            "type":"Retail Goods"
        }
    ],
    "sg:phone":"+32 53 70 39 80",
    "sg:postcode":"9300",
    "sg:province":"Oost-Vlaanderen",
    "sg:tags":[
        "lingerie",
        "sous-v\u00eatements"
    ],
    "wof:name":"Huis Caroline",
    "wof:placetype":"venue"
},
  "geometry": {"coordinates":[4.0272250175,50.9391860962],"type":"Point"}
}