{
  "type": "Feature",
  "properties": {
    "addr:full":"Eindstraat 1bf Neerpelt Limburg 3910",
    "addr:housenumber":"1bf",
    "addr:postcode":"3910",
    "addr:street":"Eindstraat",
    "iso:country":"BE",
    "sg:address":"Eindstraat 1bf",
    "sg:city":"Neerpelt",
    "sg:orig_category":"Installatie van metalen schrijnwerk",
    "sg:phone":"+32 11 66 16 67",
    "sg:postcode":"3910",
    "sg:province":"Limburg",
    "wof:name":"H.r.",
    "wof:placetype":"venue"
},
  "geometry": {"coordinates":[5.4367799759,51.2402305603],"type":"Point"}
}