{
  "type": "Feature",
  "properties": {
    "addr:full":"Peterseliestraat 28 Brugge West-Vlaanderen 8000",
    "addr:housenumber":"28",
    "addr:postcode":"8000",
    "addr:street":"Peterseliestraat",
    "iso:country":"BE",
    "sg:address":"Peterseliestraat 28",
    "sg:city":"Brugge",
    "sg:classifiers":[
        {
            "category":"Personal",
            "subcategory":"Beauty Salon",
            "type":"Services"
        }
    ],
    "sg:phone":"+32 50 34 42 32",
    "sg:postcode":"8000",
    "sg:province":"West-Vlaanderen",
    "sg:tags":[
        "de",
        "coiffure"
    ],
    "wof:name":"Petra Alloo",
    "wof:placetype":"venue"
},
  "geometry": {"coordinates":[3.2362849712,51.2166442871],"type":"Point"}
}