{
  "type": "Feature",
  "properties": {
    "iso:country":"BE",
    "sg:address":"Grootheide 129",
    "sg:city":"Bornem",
    "sg:classifiers":[
        {
            "category":"Real Estate",
            "subcategory":"Architect",
            "type":"Services"
        }
    ],
    "sg:phone":"+32 3 889 49 89",
    "sg:postcode":"2880",
    "sg:province":"Antwerpen",
    "wof:name":"Walschap W",
    "wof:placetype":"venue"
},
  "geometry": {"coordinates":[4.2216567993,51.0873374939],"type":"Point"}
}