{
  "type": "Feature",
  "properties": {
    "addr:full":"Kortrijksesteenweg 376 Gent Oost-Vlaanderen 9000",
    "addr:housenumber":"376",
    "addr:postcode":"9000",
    "addr:street":"Kortrijksesteenweg;Oost-Vlaanderen",
    "iso:country":"BE",
    "sg:address":"Kortrijksesteenweg 376",
    "sg:city":"Gent",
    "sg:orig_category":"Levensverzekeringsmaatschappijen Verzekeringen vastgoed",
    "sg:phone":"+32 9 221 92 83",
    "sg:postcode":"9000",
    "sg:province":"Oost-Vlaanderen",
    "wof:name":"Partners",
    "wof:placetype":"venue"
},
  "geometry": {"coordinates":[3.7157990932,51.0374832153],"type":"Point"}
}