{
  "type": "Feature",
  "properties": {
    "iso:country":"BE",
    "sg:address":"Japanse Torenstraat 13b28",
    "sg:city":"Brussel/bruxelles",
    "sg:orig_category":"Immobili\u00ebnkantoren",
    "sg:phone":"+32 2 262 32 43",
    "sg:postcode":"1120",
    "sg:province":"Bruxelles-Capitale",
    "wof:name":"A.i.s.b.-s.i.k.b.",
    "wof:placetype":"venue"
},
  "geometry": {"coordinates":[4.3717279434,50.895816803],"type":"Point"}
}