{
  "type": "Feature",
  "properties": {
    "iso:country":"BE",
    "sg:address":"Blerebergstraat 115",
    "sg:city":"Tielt-winge (tielt)",
    "sg:classifiers":[
        {
            "category":"Building & Trades",
            "subcategory":"Cleaning & Sanitation",
            "type":"Services"
        }
    ],
    "sg:phone":"+32 16 63 27 38",
    "sg:postcode":"3390",
    "sg:province":"Vlaams-Brabant",
    "sg:tags":[
        "fa\u00e7ade",
        "maintenance"
    ],
    "wof:name":"Euro-voeg Bvba",
    "wof:placetype":"venue"
},
  "geometry": {"coordinates":[4.9109601974,50.9262924194],"type":"Point"}
}