{
  "type": "Feature",
  "properties": {
    "addr:full":"Astridplein 11 Koksijde (oostduinkerke) West-Vlaanderen 8670",
    "addr:housenumber":"11",
    "addr:postcode":"8670",
    "addr:street":"Astridplein",
    "iso:country":"BE",
    "sg:address":"Astridplein 11",
    "sg:city":"Koksijde (oostduinkerke)",
    "sg:classifiers":[
        {
            "category":"Travel",
            "subcategory":"Hotels & Motels",
            "type":"Entertainment"
        }
    ],
    "sg:phone":"+32 58 52 08 69",
    "sg:postcode":"8670",
    "sg:province":"West-Vlaanderen",
    "wof:name":"Albert I Hotel/britannia Beach Hotel",
    "wof:placetype":"venue"
},
  "geometry": {"coordinates":[2.6715319157,51.1322135925],"type":"Point"}
}