{
  "type": "Feature",
  "properties": {
    "addr:full":"Zandstraat 83 Herentals Antwerpen 2200",
    "addr:housenumber":"83",
    "addr:postcode":"2200",
    "addr:street":"Zandstraat",
    "iso:country":"BE",
    "sg:address":"Zandstraat 83",
    "sg:city":"Herentals",
    "sg:classifiers":[
        {
            "category":"Restaurant",
            "type":"Food & Drink"
        }
    ],
    "sg:phone":"+32 14 21 91 57",
    "sg:postcode":"2200",
    "sg:province":"Antwerpen",
    "wof:name":"Maxim's",
    "wof:placetype":"venue"
},
  "geometry": {"coordinates":[4.8311681747,51.1771011353],"type":"Point"}
}