{
  "type": "Feature",
  "properties": {
    "addr:full":"Rue Du Ch\u00e2teau 55 Houyet (wanlin) Namur 5564",
    "addr:housenumber":"55",
    "addr:postcode":"5564",
    "addr:street":"Rue Du Cha\u0302Teau",
    "iso:country":"BE",
    "sg:address":"Rue Du Ch\u00e2teau 55",
    "sg:city":"Houyet (wanlin)",
    "sg:classifiers":[
        {
            "category":"Home & Garden",
            "subcategory":"Garden Supply",
            "type":"Retail Goods"
        }
    ],
    "sg:phone":"+32 82 66 65 03",
    "sg:postcode":"5564",
    "sg:province":"Namur",
    "wof:name":"Jardilesse Sc",
    "wof:placetype":"venue"
},
  "geometry": {"coordinates":[5.0614261627,50.1595497131],"type":"Point"}
}