{
  "type": "Feature",
  "properties": {
    "iso:country":"BE",
    "sg:address":"Vakenstraat 18",
    "sg:city":"Rotselaar",
    "sg:classifiers":[
        {
            "category":"Arena",
            "subcategory":"Sports Club",
            "type":"Entertainment"
        }
    ],
    "sg:phone":"+32 16 44 45 17",
    "sg:postcode":"3110",
    "sg:province":"Vlaams-Brabant",
    "wof:name":"Meander (de)",
    "wof:placetype":"venue"
},
  "geometry": {"coordinates":[4.7227339745,50.9631385803],"type":"Point"}
}