{
  "type": "Feature",
  "properties": {
    "addr:full":"Chee De Ninove 255-273 Molenbeek-saint-jean (bruxelles) Bruxelles-Capitale 1080",
    "addr:postcode":"255-273;1080",
    "addr:street":"Chee De Ninove",
    "iso:country":"BE",
    "sg:address":"Chee De Ninove 255-273",
    "sg:city":"Molenbeek-saint-jean (bruxelles)",
    "sg:orig_category":"Quincailleries",
    "sg:phone":"+32 2 410 22 30",
    "sg:postcode":"1080",
    "sg:province":"Bruxelles-Capitale",
    "wof:name":"Brico",
    "wof:placetype":"venue"
},
  "geometry": {"coordinates":[4.3173599243,50.8486099243],"type":"Point"}
}