{
  "type": "Feature",
  "properties": {
    "addr:full":"Rue Alfred Stevens 104 Bruxelles Bruxelles-Capitale 1020",
    "addr:housenumber":"104",
    "addr:postcode":"1020",
    "addr:street":"Rue Alfred Stevens",
    "iso:country":"BE",
    "sg:address":"Rue Alfred Stevens 104",
    "sg:city":"Bruxelles",
    "sg:classifiers":[
        {
            "category":"Professional",
            "subcategory":"Testing Lab",
            "type":"Services"
        }
    ],
    "sg:phone":"+32 2 478 02 77",
    "sg:postcode":"1020",
    "sg:province":"Bruxelles-Capitale",
    "sg:tags":[
        "chemist"
    ],
    "wof:name":"Eyckerman C",
    "wof:placetype":"venue"
},
  "geometry": {"coordinates":[4.343310833,50.8847885132],"type":"Point"}
}