{
  "type": "Feature",
  "properties": {
    "addr:full":"Bevrijdingslaan 17 Anzegem (kaster) West-Vlaanderen 8572",
    "addr:housenumber":"17",
    "addr:postcode":"8572",
    "addr:street":"Bevrijdingslaan",
    "iso:country":"BE",
    "sg:address":"Bevrijdingslaan 17",
    "sg:city":"Anzegem (kaster)",
    "sg:classifiers":[
        {
            "category":"Retail",
            "subcategory":"Auto Repair",
            "type":"Services"
        }
    ],
    "sg:phone":"+32 56 68 82 46",
    "sg:postcode":"8572",
    "sg:province":"West-Vlaanderen",
    "sg:tags":[
        "garage"
    ],
    "wof:name":"Gilva/malfait D",
    "wof:placetype":"venue"
},
  "geometry": {"coordinates":[3.4903049469,50.8221244812],"type":"Point"}
}