{
  "type": "Feature",
  "properties": {
    "addr:full":"Rue De La Renaissance 51 Juprelle (voroux-lez-liers) Li\u00e8ge 4451",
    "addr:housenumber":"51",
    "addr:postcode":"4451",
    "addr:street":"Rue De La Renaissance;Voroux-Lez-Liers",
    "iso:country":"BE",
    "sg:address":"Rue De La Renaissance 51",
    "sg:city":"Juprelle (voroux-lez-liers)",
    "sg:classifiers":[
        {
            "category":"Health Services",
            "subcategory":"Doctor",
            "type":"Services"
        }
    ],
    "sg:phone":"+32 4 278 00 28",
    "sg:postcode":"4451",
    "sg:province":"Li\u00e8ge",
    "sg:tags":[
        "medicinephysicians",
        "surgeon"
    ],
    "wof:name":"Lamberechts A (mme)",
    "wof:placetype":"venue"
},
  "geometry": {"coordinates":[5.5574398041,50.6846809387],"type":"Point"}
}