{
  "type": "Feature",
  "properties": {
    "addr:full":"Rue De Cras-avernas 7 Hannut Li\u00e8ge 4280",
    "addr:housenumber":"7",
    "addr:postcode":"4280",
    "addr:street":"Rue De Cras-Avernas",
    "iso:country":"BE",
    "sg:address":"Rue De Cras-avernas 7",
    "sg:city":"Hannut",
    "sg:classifiers":[
        {
            "category":"Manufacturing",
            "subcategory":"Glass & Minerals",
            "type":"Manufacturing & Wholesale Goods"
        }
    ],
    "sg:phone":"+32 19 51 12 20",
    "sg:postcode":"4280",
    "sg:province":"Li\u00e8ge",
    "sg:tags":[
        "frame"
    ],
    "wof:name":"Fran\u00e7oise-duchesne Optics S.a",
    "wof:placetype":"venue"
},
  "geometry": {"coordinates":[5.0926918983,50.6962966919],"type":"Point"}
}