{
  "type": "Feature",
  "properties": {
    "iso:country":"BE",
    "sg:address":"Minister A. De Clercklaan 31",
    "sg:city":"Kortrijk",
    "sg:classifiers":[
        {
            "category":"Health Services",
            "subcategory":"Health Practitioner",
            "type":"Services"
        }
    ],
    "sg:phone":"+32 56 22 19 58",
    "sg:postcode":"8500",
    "sg:province":"West-Vlaanderen",
    "sg:tags":[
        "physiotherapist"
    ],
    "wof:name":"Colpaert F",
    "wof:placetype":"venue"
},
  "geometry": {"coordinates":[3.2814850807,50.8101348877],"type":"Point"}
}