{
  "type": "Feature",
  "properties": {
    "iso:country":"BE",
    "sg:address":"Oude Bevelsesteenweg 70",
    "sg:city":"Nijlen (kessel)",
    "sg:classifiers":[
        {
            "category":"Home & Garden",
            "subcategory":"Home Furnishings",
            "type":"Retail Goods"
        }
    ],
    "sg:phone":"+32 3 440 14 45",
    "sg:postcode":"2560",
    "sg:province":"Antwerpen",
    "sg:tags":[
        "interior",
        "decoration"
    ],
    "wof:name":"Nicolay Decor",
    "wof:placetype":"venue"
},
  "geometry": {"coordinates":[4.6733560562,51.1552124023],"type":"Point"}
}