{
  "type": "Feature",
  "properties": {
    "addr:full":"Beukenstraat 3 Torhout West-Vlaanderen 8820",
    "addr:housenumber":"3",
    "addr:postcode":"8820",
    "addr:street":"Beukenstraat",
    "iso:country":"BE",
    "sg:address":"Beukenstraat 3",
    "sg:city":"Torhout",
    "sg:orig_category":"Peinture. Rev\u00eatements pour sols and murs",
    "sg:phone":"+32 50 21 14 12",
    "sg:postcode":"8820",
    "sg:province":"West-Vlaanderen",
    "wof:name":"De Schutter & Zn",
    "wof:placetype":"venue"
},
  "geometry": {"coordinates":[3.0855829716,51.0688819885],"type":"Point"}
}