{
  "type": "Feature",
  "properties": {
    "iso:country":"BE",
    "sg:address":"Koninklijke Baan 335",
    "sg:city":"Koksijde",
    "sg:orig_category":"Voertuigen",
    "sg:phone":"+32 58 51 57 24",
    "sg:postcode":"8670",
    "sg:province":"West-Vlaanderen",
    "wof:name":"Leo Vyvey",
    "wof:placetype":"venue"
},
  "geometry": {"coordinates":[2.6268680096,51.1137161255],"type":"Point"}
}