{
  "type": "Feature",
  "properties": {
    "addr:full":"Malosewaver 28 Geel Antwerpen 2440",
    "addr:housenumber":"28",
    "addr:postcode":"2440",
    "addr:street":"Malosewaver",
    "iso:country":"BE",
    "sg:address":"Malosewaver 28",
    "sg:city":"Geel",
    "sg:orig_category":"Eleveurs de bovins",
    "sg:phone":"+32 14 58 07 65",
    "sg:postcode":"2440",
    "sg:province":"Antwerpen",
    "wof:name":"Van Herck",
    "wof:placetype":"venue"
},
  "geometry": {"coordinates":[5.0356330872,51.157245636],"type":"Point"}
}