{
  "type": "Feature",
  "properties": {
    "iso:country":"BE",
    "sg:address":"Oudeberg 2",
    "sg:city":"Geraardsbergen",
    "sg:orig_category":"Restaurants Ruimtes voor conferenties, recepties and feesten",
    "sg:phone":"+32 54 41 05 77",
    "sg:postcode":"9500",
    "sg:province":"Oost-Vlaanderen",
    "wof:name":"'t Hemelrijck",
    "wof:placetype":"venue"
},
  "geometry": {"coordinates":[3.8907959461,50.7722587585],"type":"Point"}
}