{
  "type": "Feature",
  "properties": {
    "iso:country":"BE",
    "sg:address":"Chemin De La Dr\u00e8ve 27",
    "sg:city":"Erquelinnes (montignies-saint-christophe)",
    "sg:classifiers":[
        {
            "category":"Building & Trades",
            "subcategory":"Cleaning & Sanitation",
            "type":"Services"
        }
    ],
    "sg:phone":"+32 71 55 44 71",
    "sg:postcode":"6560",
    "sg:province":"Hainaut",
    "sg:tags":[
        "cleaner",
        "window"
    ],
    "wof:name":"Petrisot Sprl",
    "wof:placetype":"venue"
},
  "geometry": {"coordinates":[4.1920080185,50.2836265564],"type":"Point"}
}