{
  "type": "Feature",
  "properties": {
    "addr:full":"Richard Orlentstraat 30 Zwijndrecht Antwerpen 2070",
    "addr:housenumber":"30",
    "addr:postcode":"2070",
    "addr:street":"Richard Orlentstraat",
    "iso:country":"BE",
    "sg:address":"Richard Orlentstraat 30",
    "sg:city":"Zwijndrecht",
    "sg:orig_category":"Epiceries",
    "sg:phone":"+32 3 252 74 05",
    "sg:postcode":"2070",
    "sg:province":"Antwerpen",
    "wof:name":"Agnes Van Roeyen",
    "wof:placetype":"venue"
},
  "geometry": {"coordinates":[4.3249440193,51.2207107544],"type":"Point"}
}