{
  "type": "Feature",
  "properties": {
    "iso:country":"BE",
    "sg:address":"Rue Longue 4",
    "sg:city":"Beauvechain",
    "sg:orig_category":"S\u00e9curit\u00e9 sociale",
    "sg:phone":"+32 10 86 70 25",
    "sg:postcode":"1320",
    "sg:province":"Brabant Wallon",
    "wof:name":"La Femada",
    "wof:placetype":"venue"
},
  "geometry": {"coordinates":[4.7815728188,50.7577514648],"type":"Point"}
}