{
  "type": "Feature",
  "properties": {
    "iso:country":"BE",
    "sg:address":"Rue Du Vivier 37",
    "sg:city":"Elsene/ixelles",
    "sg:orig_category":"Editeurs de journaux. Editeurs de revues and p\u00e9riodiques",
    "sg:phone":"+32 2 647 44 27",
    "sg:postcode":"1050",
    "sg:province":"Bruxelles-Capitale",
    "wof:name":"Duthois Christine",
    "wof:placetype":"venue"
},
  "geometry": {"coordinates":[4.3800477982,50.8309555054],"type":"Point"}
}