{
  "type": "Feature",
  "properties": {
    "iso:country":"BE",
    "sg:address":"Zandstraat 58",
    "sg:city":"Herentals",
    "sg:classifiers":[
        {
            "category":"Manufacturing",
            "subcategory":"Textiles",
            "type":"Manufacturing & Wholesale Goods"
        }
    ],
    "sg:phone":"+32 14 21 67 58",
    "sg:postcode":"2200",
    "sg:province":"Antwerpen",
    "sg:tags":[
        "retail",
        "-"
    ],
    "wof:name":"Figli Textiel",
    "wof:placetype":"venue"
},
  "geometry": {"coordinates":[4.8328461647,51.1770515442],"type":"Point"}
}