{
  "type": "Feature",
  "properties": {
    "iso:country":"BE",
    "sg:address":"Madeliefjeslaan 9",
    "sg:city":"Bornem",
    "sg:orig_category":"Sportclubs",
    "sg:phone":"+32 3 889 53 60",
    "sg:postcode":"2880",
    "sg:province":"Antwerpen",
    "wof:name":"Sparta Bornem",
    "wof:placetype":"venue"
},
  "geometry": {"coordinates":[4.218711853,51.0860939026],"type":"Point"}
}