{
  "type": "Feature",
  "properties": {
    "iso:country":"BE",
    "sg:address":"Rue De Dinant 81",
    "sg:city":"Nivelles",
    "sg:orig_category":"Opsporingsdiensten and detectivebureaus",
    "sg:phone":"+32 67 21 90 02",
    "sg:postcode":"1401",
    "sg:province":"Brabant Wallon",
    "wof:name":"Remi Paesmans",
    "wof:placetype":"venue"
},
  "geometry": {"coordinates":[4.3463602066,50.6209869385],"type":"Point"}
}