{
  "type": "Feature",
  "properties": {
    "iso:country":"BE",
    "sg:address":"Brusselsesteenweg 140",
    "sg:city":"Wetteren",
    "sg:classifiers":[
        {
            "category":"Cafe",
            "type":"Food & Drink"
        }
    ],
    "sg:phone":"+32 9 252 40 18",
    "sg:postcode":"9230",
    "sg:province":"Oost-Vlaanderen",
    "sg:tags":[
        "caf\u00e9s"
    ],
    "wof:name":"Caf\u00c9 Palace",
    "wof:placetype":"venue"
},
  "geometry": {"coordinates":[3.8451399803,50.9841995239],"type":"Point"}
}