{
  "type": "Feature",
  "properties": {
    "addr:full":"Place Jean Vander Elst 3 Bruxelles (uccle) Bruxelles-Capitale 1180",
    "addr:housenumber":"3",
    "addr:postcode":"1180",
    "addr:street":"Place Jean Vander Elst",
    "iso:country":"BE",
    "sg:address":"Place Jean Vander Elst 3",
    "sg:city":"Bruxelles (uccle)",
    "sg:classifiers":[
        {
            "category":"Personal",
            "subcategory":"Beauty Salon",
            "type":"Services"
        }
    ],
    "sg:phone":"+32 2 345 66 29",
    "sg:postcode":"1180",
    "sg:province":"Bruxelles-Capitale",
    "sg:tags":[
        "lady",
        "-",
        "hairdressing"
    ],
    "wof:name":"Raymond",
    "wof:placetype":"venue"
},
  "geometry": {"coordinates":[4.3344478607,50.8039703369],"type":"Point"}
}