{
  "type": "Feature",
  "properties": {
    "iso:country":"BE",
    "sg:address":"Chauss\u00e9e De Renaix 190",
    "sg:city":"Tournai",
    "sg:classifiers":[
        {
            "category":"Health Services",
            "subcategory":"Health Practitioner",
            "type":"Services"
        }
    ],
    "sg:phone":"+32 69 23 50 33",
    "sg:postcode":"7500",
    "sg:province":"Hainaut",
    "sg:tags":[
        "physiotherapist"
    ],
    "wof:name":"Rigaut P",
    "wof:placetype":"venue"
},
  "geometry": {"coordinates":[3.4107730389,50.6156921387],"type":"Point"}
}