{
  "type": "Feature",
  "properties": {
    "addr:full":"Rue Pirette 19 Vis\u00e9 (cheratte) Li\u00e8ge 4602",
    "addr:housenumber":"19",
    "addr:postcode":"4602",
    "addr:street":"Rue Pirette;Cheratte",
    "iso:country":"BE",
    "sg:address":"Rue Pirette 19",
    "sg:city":"Vis\u00e9 (cheratte)",
    "sg:classifiers":[
        {
            "category":"Insurance",
            "subcategory":"Insurance Agent",
            "type":"Services"
        }
    ],
    "sg:phone":"+32 4 362 94 89",
    "sg:postcode":"4602",
    "sg:province":"Li\u00e8ge",
    "sg:tags":[
        "broker"
    ],
    "wof:name":"A.c.pa. Sc E. & N. Paoloni",
    "wof:placetype":"venue"
},
  "geometry": {"coordinates":[5.6808729172,50.6883506775],"type":"Point"}
}