{
  "type": "Feature",
  "properties": {
    "iso:country":"BE",
    "sg:address":"Bargiekaai 3",
    "sg:city":"Gent",
    "sg:classifiers":[
        {
            "category":"Depot",
            "subcategory":"Train",
            "type":"Transportation"
        }
    ],
    "sg:phone":"+32 9 223 90 27",
    "sg:postcode":"9000",
    "sg:province":"Oost-Vlaanderen",
    "sg:tags":[
        "gear",
        "lifting"
    ],
    "wof:name":"Vialec Bvba",
    "wof:placetype":"venue"
},
  "geometry": {"coordinates":[3.7076189518,51.0582923889],"type":"Point"}
}