{
  "type": "Feature",
  "properties": {
    "iso:country":"BE",
    "sg:address":"Knoksebaan 8",
    "sg:city":"Damme (oostkerke - Hoeke)",
    "sg:classifiers":[
        {
            "category":"Farming",
            "subcategory":"Livestock Farm",
            "type":"Manufacturing & Wholesale Goods"
        }
    ],
    "sg:phone":"+32 50 51 51 18",
    "sg:postcode":"8340",
    "sg:province":"West-Vlaanderen",
    "sg:tags":[
        "buyer"
    ],
    "wof:name":"Deceuninck P",
    "wof:placetype":"venue"
},
  "geometry": {"coordinates":[3.2778820992,51.3012962341],"type":"Point"}
}