{
  "type": "Feature",
  "properties": {
    "addr:full":"Kleine Karmelietenstraat 3 Geraardsbergen Oost-Vlaanderen 9500",
    "addr:housenumber":"3",
    "addr:postcode":"9500",
    "addr:street":"Kleine Karmelietenstraat",
    "iso:country":"BE",
    "sg:address":"Kleine Karmelietenstraat 3",
    "sg:city":"Geraardsbergen",
    "sg:orig_category":"Formation permanente",
    "sg:phone":"+32 54 41 22 96",
    "sg:postcode":"9500",
    "sg:province":"Oost-Vlaanderen",
    "wof:name":"Leerg. Sociale Promotie",
    "wof:placetype":"venue"
},
  "geometry": {"coordinates":[3.8787479401,50.7733306885],"type":"Point"}
}