{
  "type": "Feature",
  "properties": {
    "addr:full":"Place Du Sablon 77 Dison Li\u00e8ge 4820",
    "addr:housenumber":"77",
    "addr:postcode":"4820",
    "addr:street":"Place Du Sablon",
    "iso:country":"BE",
    "sg:address":"Place Du Sablon 77",
    "sg:city":"Dison",
    "sg:orig_category":"Artsen and specialisten",
    "sg:phone":"+32 87 33 80 37",
    "sg:postcode":"4820",
    "sg:province":"Li\u00e8ge",
    "wof:name":"Johann\u00c8s Schindler",
    "wof:placetype":"venue"
},
  "geometry": {"coordinates":[5.8541498184,50.6110839844],"type":"Point"}
}