{
  "type": "Feature",
  "properties": {
    "addr:full":"Chauss\u00e9e De Fleurus 17 Charleroi (gilly) Hainaut 6060",
    "addr:housenumber":"17",
    "addr:postcode":"6060",
    "addr:street":"Chausse\u0301E De Fleurus",
    "iso:country":"BE",
    "sg:address":"Chauss\u00e9e De Fleurus 17",
    "sg:city":"Charleroi (gilly)",
    "sg:classifiers":[
        {
            "category":"Shopping",
            "subcategory":"Bridal",
            "type":"Retail Goods"
        }
    ],
    "sg:phone":"+32 71 48 97 60",
    "sg:postcode":"6060",
    "sg:province":"Hainaut",
    "sg:tags":[
        "list",
        "-",
        "present",
        "wedding"
    ],
    "wof:name":"Hocq Cadeaux",
    "wof:placetype":"venue"
},
  "geometry": {"coordinates":[4.4724750519,50.443523407],"type":"Point"}
}