{
  "type": "Feature",
  "properties": {
    "addr:full":"Brugsevaart 108 Gent (mariakerke) Oost-Vlaanderen 9030",
    "addr:housenumber":"108",
    "addr:postcode":"9030",
    "addr:street":"Brugsevaart",
    "iso:country":"BE",
    "sg:address":"Brugsevaart 108",
    "sg:city":"Gent (mariakerke)",
    "sg:classifiers":[
        {
            "category":"Autos & Motor Vehicles",
            "subcategory":"Automobile Sales",
            "type":"Retail Goods"
        }
    ],
    "sg:phone":"+32 9 226 82 62",
    "sg:postcode":"9030",
    "sg:province":"Oost-Vlaanderen",
    "sg:tags":[
        "car",
        "used",
        "-"
    ],
    "wof:name":"Aelterman R",
    "wof:placetype":"venue"
},
  "geometry": {"coordinates":[3.6727399826,51.0806083679],"type":"Point"}
}