{
  "type": "Feature",
  "properties": {
    "iso:country":"BE",
    "sg:address":"Leuvenselaan 29",
    "sg:city":"Tienen",
    "sg:orig_category":"Architecten",
    "sg:phone":"+32 16 81 29 81",
    "sg:postcode":"3300",
    "sg:province":"Vlaams-Brabant",
    "wof:name":"Roger Casterman",
    "wof:placetype":"venue"
},
  "geometry": {"coordinates":[4.9285850525,50.8101806641],"type":"Point"}
}