{
  "type": "Feature",
  "properties": {
    "addr:full":"Haaggatstraat 31 Kortenberg Vlaams-Brabant 3071",
    "addr:housenumber":"31",
    "addr:postcode":"3071",
    "addr:street":"Haaggatstraat;Vlaams-Brabant",
    "iso:country":"BE",
    "sg:address":"Haaggatstraat 31",
    "sg:city":"Kortenberg",
    "sg:classifiers":[
        {
            "category":"Insurance",
            "subcategory":"Insurance Agent",
            "type":"Services"
        }
    ],
    "sg:phone":"+32 2 759 46 81",
    "sg:postcode":"3071",
    "sg:province":"Vlaams-Brabant",
    "sg:tags":[
        "verzekeringsmakelaars",
        "expert"
    ],
    "wof:name":"J. Van Dyck",
    "wof:placetype":"venue"
},
  "geometry": {"coordinates":[4.5759830475,50.9057197571],"type":"Point"}
}