{
  "type": "Feature",
  "properties": {
    "addr:full":"Rue Bollette 71 Saint-nicolas (montegn\u00e9e) Li\u00e8ge 4420",
    "addr:housenumber":"71",
    "addr:postcode":"4420",
    "addr:street":"Rue Bollette;Montegne\u0301E",
    "iso:country":"BE",
    "sg:address":"Rue Bollette 71",
    "sg:city":"Saint-nicolas (montegn\u00e9e)",
    "sg:classifiers":[
        {
            "category":"Building & Trades",
            "subcategory":"Construction",
            "type":"Services"
        }
    ],
    "sg:phone":"+32 4 247 27 13",
    "sg:postcode":"4420",
    "sg:province":"Li\u00e8ge",
    "sg:tags":[
        "roofing",
        "material",
        "-"
    ],
    "wof:name":"Md Toiture",
    "wof:placetype":"venue"
},
  "geometry": {"coordinates":[5.5198907852,50.6368751526],"type":"Point"}
}