{
  "type": "Feature",
  "properties": {
    "addr:full":"Riddersstraat 38 Gingelom (montenaken) Limburg 3890",
    "addr:housenumber":"38",
    "addr:postcode":"3890",
    "addr:street":"Riddersstraat",
    "iso:country":"BE",
    "sg:address":"Riddersstraat 38",
    "sg:city":"Gingelom (montenaken)",
    "sg:classifiers":[
        {
            "category":"Health Services",
            "subcategory":"Health Practitioner",
            "type":"Services"
        }
    ],
    "sg:phone":"+32 11 83 12 83",
    "sg:postcode":"3890",
    "sg:province":"Limburg",
    "sg:tags":[
        "physiotherapist"
    ],
    "wof:name":"Heusdens Tony",
    "wof:placetype":"venue"
},
  "geometry": {"coordinates":[5.1374640465,50.7232475281],"type":"Point"}
}