{
  "type": "Feature",
  "properties": {
    "addr:full":"Vredestraat 1 Wevelgem West-Vlaanderen 8560",
    "addr:housenumber":"1",
    "addr:postcode":"8560",
    "addr:street":"Vredestraat",
    "iso:country":"BE",
    "sg:address":"Vredestraat 1",
    "sg:city":"Wevelgem",
    "sg:classifiers":[
        {
            "category":"Arena",
            "subcategory":"Sports Club",
            "type":"Entertainment"
        }
    ],
    "sg:phone":"+32 56 41 33 96",
    "sg:postcode":"8560",
    "sg:province":"West-Vlaanderen",
    "sg:tags":[
        "de"
    ],
    "wof:name":"T.c. Bloemenhof",
    "wof:placetype":"venue"
},
  "geometry": {"coordinates":[3.1741349697,50.8230514526],"type":"Point"}
}