{
  "type": "Feature",
  "properties": {
    "addr:full":"Limburgerstrasse 150 Lontzen Li\u00e8ge 4710",
    "addr:housenumber":"150",
    "addr:postcode":"4710",
    "addr:street":"Limburgerstrasse",
    "iso:country":"BE",
    "sg:address":"Limburgerstrasse 150",
    "sg:city":"Lontzen",
    "sg:classifiers":[
        {
            "category":"Farming",
            "subcategory":"Farm & Veterinary Services",
            "type":"Manufacturing & Wholesale Goods"
        }
    ],
    "sg:phone":"+32 87 88 34 66",
    "sg:postcode":"4710",
    "sg:province":"Li\u00e8ge",
    "sg:tags":[
        "agricultural",
        "contractor"
    ],
    "wof:name":"Lohnunternehmen Steyns Sprlu",
    "wof:placetype":"venue"
},
  "geometry": {"coordinates":[6.0007858276,50.6669502258],"type":"Point"}
}