{
  "type": "Feature",
  "properties": {
    "addr:full":"Vooruitgangstraat 1 Aalst Oost-Vlaanderen 9300",
    "addr:housenumber":"1",
    "addr:postcode":"9300",
    "addr:street":"Vooruitgangstraat",
    "iso:country":"BE",
    "sg:address":"Vooruitgangstraat 1",
    "sg:city":"Aalst",
    "sg:classifiers":[
        {
            "category":"Fast Food",
            "type":"Food & Drink"
        }
    ],
    "sg:phone":"+32 53 77 53 22",
    "sg:postcode":"9300",
    "sg:province":"Oost-Vlaanderen",
    "sg:tags":[
        "meeneem",
        "restaurant"
    ],
    "wof:name":"Snack-bar Nicky",
    "wof:placetype":"venue"
},
  "geometry": {"coordinates":[4.0381622314,50.9426803589],"type":"Point"}
}