{
  "type": "Feature",
  "properties": {
    "addr:full":"Pannestraat 7 Deinze (grammene) Oost-Vlaanderen 9800",
    "addr:housenumber":"7",
    "addr:postcode":"9800",
    "addr:street":"Pannestraat",
    "iso:country":"BE",
    "sg:address":"Pannestraat 7",
    "sg:city":"Deinze (grammene)",
    "sg:classifiers":[
        {
            "category":"Personal",
            "subcategory":"Beauty Salon",
            "type":"Services"
        }
    ],
    "sg:phone":"+32 51 63 66 08",
    "sg:postcode":"9800",
    "sg:province":"Oost-Vlaanderen",
    "sg:tags":[
        "lady",
        "-",
        "hairdressing"
    ],
    "wof:name":"Sophie",
    "wof:placetype":"venue"
},
  "geometry": {"coordinates":[3.4654560089,50.9774894714],"type":"Point"}
}