{
  "type": "Feature",
  "properties": {
    "addr:full":"Franklin Rooseveltlaan 204 Brussel/bruxelles Bruxelles-Capitale 1050",
    "addr:housenumber":"204",
    "addr:postcode":"1050",
    "addr:street":"Franklin Rooseveltlaan;/",
    "iso:country":"BE",
    "sg:address":"Franklin Rooseveltlaan 204",
    "sg:city":"Brussel/bruxelles",
    "sg:orig_category":"Advocaten and juridische adviseurs",
    "sg:phone":"+32 2 672 11 44",
    "sg:postcode":"1050",
    "sg:province":"Bruxelles-Capitale",
    "wof:name":"C\u00c9dric Janssens",
    "wof:placetype":"venue"
},
  "geometry": {"coordinates":[4.3899841309,50.8015480042],"type":"Point"}
}