{
  "type": "Feature",
  "properties": {
    "iso:country":"BE",
    "sg:address":"Laurierstraat 4",
    "sg:city":"Mol",
    "sg:orig_category":"Artsen and specialisten",
    "sg:phone":"+32 14 81 45 83",
    "sg:postcode":"2400",
    "sg:province":"Antwerpen",
    "wof:name":"Pascal Knapen",
    "wof:placetype":"venue"
},
  "geometry": {"coordinates":[5.213493824,51.1938934326],"type":"Point"}
}