{
  "type": "Feature",
  "properties": {
    "iso:country":"BE",
    "sg:address":"Schipstraat 33",
    "sg:city":"Nieuwpoort",
    "sg:classifiers":[
        {
            "category":"Building & Trades",
            "subcategory":"Construction",
            "type":"Services"
        }
    ],
    "sg:phone":"+32 58 23 71 93",
    "sg:postcode":"8620",
    "sg:province":"West-Vlaanderen",
    "sg:tags":[
        "carpenter"
    ],
    "wof:name":"Decraemer Gebr",
    "wof:placetype":"venue"
},
  "geometry": {"coordinates":[2.7530219555,51.1310691833],"type":"Point"}
}