{
  "type": "Feature",
  "properties": {
    "addr:full":"Gentpoortstraat 60b1 Deinze Oost-Vlaanderen 9800",
    "addr:housenumber":"60b1",
    "addr:postcode":"9800",
    "addr:street":"Gentpoortstraat",
    "iso:country":"BE",
    "sg:address":"Gentpoortstraat 60b1",
    "sg:city":"Deinze",
    "sg:orig_category":"Auto-\u00e9coles",
    "sg:phone":"+32 9 380 14 14",
    "sg:postcode":"9800",
    "sg:province":"Oost-Vlaanderen",
    "wof:name":"Int. Autorijsch. J. Lampe",
    "wof:placetype":"venue"
},
  "geometry": {"coordinates":[3.5297670364,50.9849777222],"type":"Point"}
}