{
  "type": "Feature",
  "properties": {
    "addr:full":"Torhoutsesteenweg 90f Oostende West-Vlaanderen 8400",
    "addr:housenumber":"90f",
    "addr:postcode":"8400",
    "addr:street":"Torhoutsesteenweg",
    "iso:country":"BE",
    "sg:address":"Torhoutsesteenweg 90f",
    "sg:city":"Oostende",
    "sg:classifiers":[
        {
            "category":"Shopping",
            "subcategory":"Bicycles & Sporting Goods",
            "type":"Retail Goods"
        }
    ],
    "sg:phone":"+32 59 50 30 53",
    "sg:postcode":"8400",
    "sg:province":"West-Vlaanderen",
    "sg:tags":[
        "sport",
        "-"
    ],
    "wof:name":"Skate Shop-vision Street Wear",
    "wof:placetype":"venue"
},
  "geometry": {"coordinates":[2.9088830948,51.2231559753],"type":"Point"}
}