{
  "type": "Feature",
  "properties": {
    "addr:full":"Rue Chasseurs-ardennais 8 Bastogne Luxembourg 6600",
    "addr:housenumber":"8",
    "addr:postcode":"6600",
    "addr:street":"Rue Chasseurs-Ardennais",
    "iso:country":"BE",
    "sg:address":"Rue Chasseurs-ardennais 8",
    "sg:city":"Bastogne",
    "sg:orig_category":"V\u00e9t\u00e9rinaires",
    "sg:phone":"+32 61 21 43 21",
    "sg:postcode":"6600",
    "sg:province":"Luxembourg",
    "wof:name":"Claude Morsomme",
    "wof:placetype":"venue"
},
  "geometry": {"coordinates":[5.7060508728,50.0050010681],"type":"Point"}
}