{
  "type": "Feature",
  "properties": {
    "addr:full":"Lessiusstraat 7 Brecht Antwerpen 2960",
    "addr:housenumber":"7",
    "addr:postcode":"2960",
    "addr:street":"Lessiusstraat",
    "iso:country":"BE",
    "sg:address":"Lessiusstraat 7",
    "sg:city":"Brecht",
    "sg:orig_category":"Artiesten and kunstenaars",
    "sg:phone":"+32 3 290 88 59",
    "sg:postcode":"2960",
    "sg:province":"Antwerpen",
    "wof:name":"M. Missinne",
    "wof:placetype":"venue"
},
  "geometry": {"coordinates":[4.643807888,51.3510742188],"type":"Point"}
}