{
  "type": "Feature",
  "properties": {
    "iso:country":"BE",
    "sg:address":"Jacob Jacobsstraat 48",
    "sg:city":"Antwerpen",
    "sg:classifiers":[
        {
            "category":"Transit Center",
            "subcategory":"Freight",
            "type":"Transportation"
        }
    ],
    "sg:phone":"+32 3 233 33 20",
    "sg:postcode":"2018",
    "sg:province":"Antwerpen",
    "sg:tags":[
        "import",
        "export",
        "-"
    ],
    "wof:name":"Insight Q",
    "wof:placetype":"venue"
},
  "geometry": {"coordinates":[4.420882225,51.2111740112],"type":"Point"}
}