{
  "type": "Feature",
  "properties": {
    "addr:full":"Handelskantoorstraat 8 Koekelberg Bruxelles-Capitale 1081",
    "addr:housenumber":"8",
    "addr:postcode":"1081",
    "addr:street":"Handelskantoorstraat",
    "iso:country":"BE",
    "sg:address":"Handelskantoorstraat 8",
    "sg:city":"Koekelberg",
    "sg:orig_category":"Schoonmaakbedrijven and ongediertebestrijding",
    "sg:phone":"+32 2 414 74 58",
    "sg:postcode":"1081",
    "sg:province":"Bruxelles-Capitale",
    "wof:name":"Vitro-flex",
    "wof:placetype":"venue"
},
  "geometry": {"coordinates":[4.3136291504,50.865032196],"type":"Point"}
}