{
  "type": "Feature",
  "properties": {
    "iso:country":"BE",
    "sg:address":"Rue Deux-eglises 41",
    "sg:city":"Brussel/bruxelles",
    "sg:orig_category":"Organisations politiques",
    "sg:phone":"+32 2 238 01 11",
    "sg:postcode":"1000",
    "sg:province":"Bruxelles-Capitale",
    "wof:name":"Cdh",
    "wof:placetype":"venue"
},
  "geometry": {"coordinates":[4.3731598854,50.8467674255],"type":"Point"}
}