{
  "type": "Feature",
  "properties": {
    "addr:full":"Rue De Rochefort 239 Beauraing Namur 5570",
    "addr:housenumber":"239",
    "addr:postcode":"5570",
    "addr:street":"Rue De Rochefort",
    "iso:country":"BE",
    "sg:address":"Rue De Rochefort 239",
    "sg:city":"Beauraing",
    "sg:classifiers":[
        {
            "category":"Home & Garden",
            "subcategory":"Carpets & Floor Coverings",
            "type":"Retail Goods"
        }
    ],
    "sg:phone":"+32 82 61 57 51",
    "sg:postcode":"5570",
    "sg:province":"Namur",
    "sg:tags":[
        "tile"
    ],
    "wof:name":"Beauraing Ceramic Sa",
    "wof:placetype":"venue"
},
  "geometry": {"coordinates":[4.9804668427,50.1209983826],"type":"Point"}
}