{
  "type": "Feature",
  "properties": {
    "addr:full":"Rue Du Tara 7 Rumes Hainaut 7610",
    "addr:housenumber":"7",
    "addr:postcode":"7610",
    "addr:street":"Rue Du Tara",
    "iso:country":"BE",
    "sg:address":"Rue Du Tara 7",
    "sg:city":"Rumes",
    "sg:classifiers":[
        {
            "category":"Personal",
            "subcategory":"Beauty Salon",
            "type":"Services"
        }
    ],
    "sg:phone":"+32 69 64 86 84",
    "sg:postcode":"7610",
    "sg:province":"Hainaut",
    "sg:tags":[
        "lady",
        "-",
        "hairdressing"
    ],
    "wof:name":"Henrotte R",
    "wof:placetype":"venue"
},
  "geometry": {"coordinates":[3.3027191162,50.5481872559],"type":"Point"}
}