{
  "type": "Feature",
  "properties": {
    "addr:full":"Rue Saumont 11 Marche-en-famenne Luxembourg 6900",
    "addr:housenumber":"11",
    "addr:postcode":"6900",
    "addr:street":"Rue Saumont",
    "iso:country":"BE",
    "sg:address":"Rue Saumont 11",
    "sg:city":"Marche-en-famenne",
    "sg:orig_category":"Secr\u00e9tariats",
    "sg:phone":"+32 84 32 23 52",
    "sg:postcode":"6900",
    "sg:province":"Luxembourg",
    "wof:name":"Noirhomme",
    "wof:placetype":"venue"
},
  "geometry": {"coordinates":[5.300494194,50.2274627686],"type":"Point"}
}