{
  "type": "Feature",
  "properties": {
    "iso:country":"BE",
    "sg:address":"Rue Warmonceau 304",
    "sg:city":"Charleroi",
    "sg:classifiers":[
        {
            "category":"Fast Food",
            "type":"Food & Drink"
        }
    ],
    "sg:phone":"+32 71 41 96 05",
    "sg:postcode":"6000",
    "sg:province":"Hainaut",
    "sg:tags":[
        "fried",
        "stand",
        "potato"
    ],
    "wof:name":"Maria (chez)",
    "wof:placetype":"venue"
},
  "geometry": {"coordinates":[4.4622368813,50.4286880493],"type":"Point"}
}