{
  "type": "Feature",
  "properties": {
    "iso:country":"BE",
    "sg:address":"Lodewijk Coiseaukaai 7a",
    "sg:city":"Brugge",
    "sg:classifiers":[
        {
            "category":"Autos & Motor Vehicles",
            "subcategory":"Boat Sales",
            "type":"Retail Goods"
        }
    ],
    "sg:phone":"+32 50 33 70 50",
    "sg:postcode":"8000",
    "sg:province":"West-Vlaanderen",
    "sg:tags":[
        "engine",
        "marine",
        "-"
    ],
    "wof:name":"Flanders Ship Repair",
    "wof:placetype":"venue"
},
  "geometry": {"coordinates":[3.2261660099,51.2305412292],"type":"Point"}
}