{
  "type": "Feature",
  "properties": {
    "iso:country":"BE",
    "sg:address":"Brakelsesteenweg 371",
    "sg:city":"Ninove (outer)",
    "sg:classifiers":[
        {
            "category":"Autos & Motor Vehicles",
            "subcategory":"Automobile Sales",
            "type":"Retail Goods"
        }
    ],
    "sg:phone":"+32 54 34 14 82",
    "sg:postcode":"9406",
    "sg:province":"Oost-Vlaanderen",
    "sg:tags":[
        "car",
        "used",
        "-"
    ],
    "wof:name":"Euromobiel Nv",
    "wof:placetype":"venue"
},
  "geometry": {"coordinates":[3.9793899059,50.8325614929],"type":"Point"}
}