{
  "type": "Feature",
  "properties": {
    "iso:country":"BE",
    "sg:address":"Eikelstraat 65",
    "sg:city":"Vorst/forest",
    "sg:classifiers":[
        {
            "category":"Food & Beverages",
            "subcategory":"Candy",
            "type":"Retail Goods"
        }
    ],
    "sg:phone":"+32 2 347 14 15",
    "sg:postcode":"1190",
    "sg:province":"Bruxelles-Capitale",
    "sg:tags":[
        "fab",
        "producten",
        "diverse"
    ],
    "wof:name":"Van De Wiele & Fils",
    "wof:placetype":"venue"
},
  "geometry": {"coordinates":[4.3179101944,50.8105888367],"type":"Point"}
}