{
  "type": "Feature",
  "properties": {
    "addr:full":"Koning Boudewijnstraat 2 Gent Oost-Vlaanderen 9000",
    "addr:housenumber":"2",
    "addr:postcode":"9000",
    "addr:street":"Koning Boudewijnstraat;Oost-Vlaanderen",
    "iso:country":"BE",
    "sg:address":"Koning Boudewijnstraat 2",
    "sg:city":"Gent",
    "sg:classifiers":[
        {
            "category":"Personal",
            "subcategory":"Tattoo Parlor",
            "type":"Services"
        }
    ],
    "sg:phone":"+32 9 330 80 73",
    "sg:postcode":"9000",
    "sg:province":"Oost-Vlaanderen",
    "sg:tags":[
        "tattooists"
    ],
    "wof:name":"Phucipino",
    "wof:placetype":"venue"
},
  "geometry": {"coordinates":[3.7099249363,51.0372924805],"type":"Point"}
}