{
  "type": "Feature",
  "properties": {
    "iso:country":"BE",
    "sg:address":"Doorniksesteenweg 81ba1",
    "sg:city":"Kortrijk",
    "sg:orig_category":"Herstellingen and onderhoud van auto's",
    "sg:phone":"+32 56 20 60 21",
    "sg:postcode":"8500",
    "sg:province":"West-Vlaanderen",
    "wof:name":"Smart",
    "wof:placetype":"venue"
},
  "geometry": {"coordinates":[3.2784368992,50.8091964722],"type":"Point"}
}