{
  "type": "Feature",
  "properties": {
    "iso:country":"BE",
    "sg:address":"Kimpestraat 25",
    "sg:city":"Brakel",
    "sg:orig_category":"Woningbouw",
    "sg:phone":"+32 55 42 78 58",
    "sg:postcode":"9660",
    "sg:province":"Oost-Vlaanderen",
    "wof:name":"Johan Van De Wattijne",
    "wof:placetype":"venue"
},
  "geometry": {"coordinates":[3.7274549007,50.7920379639],"type":"Point"}
}