{
  "type": "Feature",
  "properties": {
    "iso:country":"BE",
    "sg:address":"Rue De Huy 54 Box 2",
    "sg:city":"Waremme",
    "sg:classifiers":[
        {
            "category":"Utilities",
            "subcategory":"Natural Gas",
            "type":"Services"
        }
    ],
    "sg:phone":"+32 19 54 65 94",
    "sg:postcode":"4300",
    "sg:province":"Li\u00e8ge",
    "sg:tags":[
        "industrial",
        "-"
    ],
    "wof:name":"F. Air Service",
    "wof:placetype":"venue"
},
  "geometry": {"coordinates":[5.2507472038,50.6913414001],"type":"Point"}
}