{
  "type": "Feature",
  "properties": {
    "addr:full":"Knijffelingstraat 21 Ardooie West-Vlaanderen 8851",
    "addr:housenumber":"21",
    "addr:postcode":"8851",
    "addr:street":"Knijffelingstraat",
    "iso:country":"BE",
    "sg:address":"Knijffelingstraat 21",
    "sg:city":"Ardooie",
    "sg:orig_category":"V\u00e9t\u00e9rinaires",
    "sg:phone":"+32 51 74 68 51",
    "sg:postcode":"8851",
    "sg:province":"West-Vlaanderen",
    "wof:name":"Erik Vergauwe",
    "wof:placetype":"venue"
},
  "geometry": {"coordinates":[3.2043828964,51.000743866],"type":"Point"}
}