{
  "type": "Feature",
  "properties": {
    "addr:full":"Brusselsestweg 341 Overijse Vlaams-Brabant 3090",
    "addr:housenumber":"341",
    "addr:postcode":"3090",
    "iso:country":"BE",
    "sg:address":"Brusselsestweg 341",
    "sg:city":"Overijse",
    "sg:orig_category":"Herstellingen and onderhoud van auto's Voertuigen",
    "sg:phone":"+32 2 687 64 30",
    "sg:postcode":"3090",
    "sg:province":"Vlaams-Brabant",
    "wof:name":"Garage Merckx",
    "wof:placetype":"venue"
},
  "geometry": {"coordinates":[4.5093021393,50.7824325562],"type":"Point"}
}