{
  "type": "Feature",
  "properties": {
    "iso:country":"BE",
    "sg:address":"Place Du Monument 5",
    "sg:city":"Cerfontaine",
    "sg:orig_category":"Pain, p\u00e2tisseries and confiseries",
    "sg:phone":"+32 71 64 44 57",
    "sg:postcode":"5630",
    "sg:province":"Namur",
    "wof:name":"Bopamo",
    "wof:placetype":"venue"
},
  "geometry": {"coordinates":[4.4111189842,50.1704521179],"type":"Point"}
}