{
  "type": "Feature",
  "properties": {
    "iso:country":"BE",
    "sg:address":"Rue De Douvres 28",
    "sg:city":"Anderlecht",
    "sg:orig_category":"Imprimeries and copyshops. Composition and photogravure. Secr\u00e9tariats",
    "sg:phone":"+32 2 520 21 53",
    "sg:postcode":"1070",
    "sg:province":"Bruxelles-Capitale",
    "wof:name":"D.g. Screen",
    "wof:placetype":"venue"
},
  "geometry": {"coordinates":[4.3140339851,50.8349533081],"type":"Point"}
}