{
  "type": "Feature",
  "properties": {
    "iso:country":"BE",
    "sg:address":"Rue Mitoyenne 175",
    "sg:city":"Welkenraedt",
    "sg:classifiers":[
        {
            "category":"Restaurant",
            "type":"Food & Drink"
        }
    ],
    "sg:phone":"+32 87 88 29 23",
    "sg:postcode":"4840",
    "sg:province":"Li\u00e8ge",
    "sg:tags":[
        "organisatie",
        "feesten",
        "van",
        "catering"
    ],
    "wof:name":"Comme Chez Vous",
    "wof:placetype":"venue"
},
  "geometry": {"coordinates":[5.9792499542,50.6617736816],"type":"Point"}
}