{
  "type": "Feature",
  "properties": {
    "addr:full":"Nieuwlandlaan 9 Aarschot Vlaams-Brabant 3200",
    "addr:housenumber":"9",
    "addr:postcode":"3200",
    "addr:street":"Nieuwlandlaan",
    "iso:country":"BE",
    "sg:address":"Nieuwlandlaan 9",
    "sg:city":"Aarschot",
    "sg:orig_category":"Farmaceutische producten Gh",
    "sg:phone":"+32 16 57 10 76",
    "sg:postcode":"3200",
    "sg:province":"Vlaams-Brabant",
    "wof:name":"A.m.p.",
    "wof:placetype":"venue"
},
  "geometry": {"coordinates":[4.8046221733,50.9755172729],"type":"Point"}
}