{
  "type": "Feature",
  "properties": {
    "addr:full":"Gemeentestraat 41 Lubbeek Vlaams-Brabant 3210",
    "addr:housenumber":"41",
    "addr:postcode":"3210",
    "addr:street":"Gemeentestraat",
    "iso:country":"BE",
    "sg:address":"Gemeentestraat 41",
    "sg:city":"Lubbeek",
    "sg:orig_category":"Kapsalons",
    "sg:phone":"+32 16 62 04 08",
    "sg:postcode":"3210",
    "sg:province":"Vlaams-Brabant",
    "wof:name":"Coiffure Hair City",
    "wof:placetype":"venue"
},
  "geometry": {"coordinates":[4.7714891434,50.8942832947],"type":"Point"}
}