{
  "type": "Feature",
  "properties": {
    "iso:country":"BE",
    "sg:address":"Rozenlaan 16",
    "sg:city":"Sint-katelijne-waver",
    "sg:orig_category":"Antiek",
    "sg:phone":"+32 15 55 19 12",
    "sg:postcode":"2861",
    "sg:province":"Antwerpen",
    "wof:name":"Art Collection",
    "wof:placetype":"venue"
},
  "geometry": {"coordinates":[4.5420269966,51.0487289429],"type":"Point"}
}