{
  "type": "Feature",
  "properties": {
    "addr:full":"Ketelstraat 14 Zemst (weerde) Vlaams-Brabant 1982",
    "addr:housenumber":"14",
    "addr:postcode":"1982",
    "addr:street":"Ketelstraat",
    "iso:country":"BE",
    "sg:address":"Ketelstraat 14",
    "sg:city":"Zemst (weerde)",
    "sg:classifiers":[
        {
            "category":"Professional",
            "subcategory":"Computer Services",
            "type":"Services"
        }
    ],
    "sg:phone":"+32 495 57 19 81",
    "sg:postcode":"1982",
    "sg:province":"Vlaams-Brabant",
    "sg:tags":[
        "-",
        "processing",
        "data",
        "software"
    ],
    "wof:name":"Sommico Bvba",
    "wof:placetype":"venue"
},
  "geometry": {"coordinates":[4.4809861183,50.9733314514],"type":"Point"}
}