{
  "type": "Feature",
  "properties": {
    "addr:full":"Lepelstraat 18 Staden West-Vlaanderen 8840",
    "addr:housenumber":"18",
    "addr:postcode":"8840",
    "addr:street":"Lepelstraat",
    "iso:country":"BE",
    "sg:address":"Lepelstraat 18",
    "sg:city":"Staden",
    "sg:classifiers":[
        {
            "category":"Organizations",
            "subcategory":"Community Association",
            "type":"Services"
        }
    ],
    "sg:phone":"+32 51 22 09 11",
    "sg:postcode":"8840",
    "sg:province":"West-Vlaanderen",
    "sg:tags":[
        "organisation"
    ],
    "wof:name":"Jeugdhuis Dolce Vita",
    "wof:placetype":"venue"
},
  "geometry": {"coordinates":[3.0577170849,50.9408874512],"type":"Point"}
}