{
  "type": "Feature",
  "properties": {
    "addr:full":"Bld De Smet De Naeyer 549 Brussel/bruxelles Bruxelles-Capitale 1020",
    "addr:housenumber":"549",
    "addr:postcode":"1020",
    "addr:street":"Bld De Smet De Naeyer;/",
    "iso:country":"BE",
    "sg:address":"Bld De Smet De Naeyer 549",
    "sg:city":"Brussel/bruxelles",
    "sg:orig_category":"V\u00e9t\u00e9rinaires",
    "sg:phone":"+32 2 479 54 15",
    "sg:postcode":"1020",
    "sg:province":"Bruxelles-Capitale",
    "wof:name":"Pierre Toubeau",
    "wof:placetype":"venue"
},
  "geometry": {"coordinates":[4.3393440247,50.8852081299],"type":"Point"}
}