{
  "type": "Feature",
  "properties": {
    "iso:country":"BE",
    "sg:address":"Steenweg 50",
    "sg:city":"Lanaken",
    "sg:orig_category":"Slagers",
    "sg:phone":"+32 89 71 13 80",
    "sg:postcode":"3621",
    "sg:province":"Limburg",
    "wof:name":"Budgetslager",
    "wof:placetype":"venue"
},
  "geometry": {"coordinates":[5.6839709282,50.9169807434],"type":"Point"}
}