{
  "type": "Feature",
  "properties": {
    "addr:full":"Plaats 41 Moorslede (dadizele) West-Vlaanderen 8890",
    "addr:housenumber":"41",
    "addr:postcode":"8890",
    "addr:street":"Plaats",
    "iso:country":"BE",
    "sg:address":"Plaats 41",
    "sg:city":"Moorslede (dadizele)",
    "sg:classifiers":[
        {
            "category":"Shopping",
            "subcategory":"Clothing, Apparel, & Fashions",
            "type":"Retail Goods"
        }
    ],
    "sg:phone":"+32 56 50 53 93",
    "sg:postcode":"8890",
    "sg:province":"West-Vlaanderen",
    "sg:tags":[
        "lady",
        "clothing",
        "-"
    ],
    "wof:name":"B.f.h. Bvba",
    "wof:placetype":"venue"
},
  "geometry": {"coordinates":[3.0952401161,50.8516616821],"type":"Point"}
}