{
  "type": "Feature",
  "properties": {
    "iso:country":"BE",
    "sg:address":"Grote Baan 38",
    "sg:city":"Waasmunster",
    "sg:classifiers":[
        {
            "category":"Retail",
            "subcategory":"Auto Repair",
            "type":"Services"
        }
    ],
    "sg:phone":"+32 3 772 37 86",
    "sg:postcode":"9250",
    "sg:province":"Oost-Vlaanderen",
    "sg:tags":[
        "garage"
    ],
    "wof:name":"Taelman",
    "wof:placetype":"venue"
},
  "geometry": {"coordinates":[4.0641198158,51.136264801],"type":"Point"}
}