{
  "type": "Feature",
  "properties": {
    "iso:country":"BE",
    "sg:address":"Rue De Florennes 16",
    "sg:city":"Mettet",
    "sg:orig_category":"V\u00e9t\u00e9rinaires",
    "sg:phone":"+32 71 72 70 14",
    "sg:postcode":"5640",
    "sg:province":"Namur",
    "wof:name":"Jean-marie Lecomte",
    "wof:placetype":"venue"
},
  "geometry": {"coordinates":[4.6601099968,50.3162612915],"type":"Point"}
}