{
  "type": "Feature",
  "properties": {
    "addr:full":"Zwarte Weg 1 Antwerpen Antwerpen 2030",
    "addr:housenumber":"1",
    "addr:postcode":"2030",
    "addr:street":"Zwarte Weg",
    "iso:country":"BE",
    "sg:address":"Zwarte Weg 1",
    "sg:city":"Antwerpen",
    "sg:classifiers":[
        {
            "category":"Government",
            "subcategory":"Post Office",
            "type":"Public Place"
        }
    ],
    "sg:phone":"+32 3 546 02 60",
    "sg:postcode":"2030",
    "sg:province":"Antwerpen",
    "sg:tags":[
        "engine",
        "assembly",
        "diesel"
    ],
    "wof:name":"Deutz Belgium Nv",
    "wof:placetype":"venue"
},
  "geometry": {"coordinates":[4.3846688271,51.2447090149],"type":"Point"}
}