{
  "type": "Feature",
  "properties": {
    "addr:full":"Rue Bodrissart 17ba Waterloo Brabant Wallon 1410",
    "addr:housenumber":"17ba",
    "addr:postcode":"1410",
    "addr:street":"Rue Bodrissart",
    "iso:country":"BE",
    "sg:address":"Rue Bodrissart 17ba",
    "sg:city":"Waterloo",
    "sg:orig_category":"Artsen and specialisten",
    "sg:phone":"+32 2 353 01 82",
    "sg:postcode":"1410",
    "sg:province":"Brabant Wallon",
    "wof:name":"C. Destree",
    "wof:placetype":"venue"
},
  "geometry": {"coordinates":[4.3783798218,50.7093200684],"type":"Point"}
}