{
  "type": "Feature",
  "properties": {
    "addr:full":"Albert I Promenade 62b Oostende West-Vlaanderen 8400",
    "addr:housenumber":"62b",
    "addr:postcode":"8400",
    "addr:street":"Albert I Promenade",
    "iso:country":"BE",
    "sg:address":"Albert I Promenade 62b",
    "sg:city":"Oostende",
    "sg:orig_category":"Restaurants Ruimtes voor conferenties, recepties and feesten",
    "sg:phone":"+32 59 80 39 65",
    "sg:postcode":"8400",
    "sg:province":"West-Vlaanderen",
    "wof:name":"Petit Nice",
    "wof:placetype":"venue"
},
  "geometry": {"coordinates":[2.9106450081,51.2305030823],"type":"Point"}
}