{
  "type": "Feature",
  "properties": {
    "iso:country":"BE",
    "sg:address":"Chauss\u00e9e De Soignies 131",
    "sg:city":"Le Roeulx",
    "sg:classifiers":[
        {
            "category":"Brewery",
            "type":"Food & Drink"
        }
    ],
    "sg:phone":"+32 64 67 52 52",
    "sg:postcode":"7070",
    "sg:province":"Hainaut",
    "wof:name":"Fran\u00e7ois Drink",
    "wof:placetype":"venue"
},
  "geometry": {"coordinates":[4.0977687836,50.5264549255],"type":"Point"}
}