{
  "type": "Feature",
  "properties": {
    "iso:country":"BE",
    "sg:address":"Tiensesteenweg 276",
    "sg:city":"Leuven",
    "sg:orig_category":"Belastingconsulenten Boekhouders Diverse juridische dienstverlening",
    "sg:phone":"+32 16 25 08 48",
    "sg:postcode":"3010",
    "sg:province":"Vlaams-Brabant",
    "wof:name":"Langens",
    "wof:placetype":"venue"
},
  "geometry": {"coordinates":[4.7132282257,50.8736724854],"type":"Point"}
}