{
  "type": "Feature",
  "properties": {
    "addr:full":"Avenue Marie-louise 7 Sint-genesius-rode/rhode-saint-gen\u00c8se Vlaams-Brabant 1640",
    "addr:housenumber":"7",
    "addr:postcode":"1640",
    "addr:street":"Avenue Marie-Louise",
    "iso:country":"BE",
    "sg:address":"Avenue Marie-louise 7",
    "sg:city":"Sint-genesius-rode/rhode-saint-gen\u00c8se",
    "sg:orig_category":"Plomberie, chauffage and installations sanitaires",
    "sg:phone":"+32 2 358 57 03",
    "sg:postcode":"1640",
    "sg:province":"Vlaams-Brabant",
    "wof:name":"Emmanuel Tyberghien",
    "wof:placetype":"venue"
},
  "geometry": {"coordinates":[4.3729200363,50.7553215027],"type":"Point"}
}