{
  "type": "Feature",
  "properties": {
    "addr:full":"Rue De La Principaut\u00c9 1 Assesse Namur 5336",
    "addr:housenumber":"1",
    "addr:postcode":"5336",
    "addr:street":"Rue De La Principaute\u0301",
    "iso:country":"BE",
    "sg:address":"Rue De La Principaut\u00c9 1",
    "sg:city":"Assesse",
    "sg:orig_category":"Plomberie, chauffage and installations sanitaires",
    "sg:phone":"+32 83 65 55 03",
    "sg:postcode":"5336",
    "sg:province":"Namur",
    "wof:name":"Van Baelen & Cie",
    "wof:placetype":"venue"
},
  "geometry": {"coordinates":[4.9845099449,50.3809318542],"type":"Point"}
}