{
  "type": "Feature",
  "properties": {
    "addr:full":"Schooldreef 58 Mol Antwerpen 2400",
    "addr:housenumber":"58",
    "addr:postcode":"2400",
    "addr:street":"Schooldreef",
    "iso:country":"BE",
    "sg:address":"Schooldreef 58",
    "sg:city":"Mol",
    "sg:classifiers":[
        {
            "category":"Professional",
            "subcategory":"Testing Lab",
            "type":"Services"
        }
    ],
    "sg:phone":"+32 14 81 00 77",
    "sg:postcode":"2400",
    "sg:province":"Antwerpen",
    "sg:tags":[
        "chemist"
    ],
    "wof:name":"Huens C",
    "wof:placetype":"venue"
},
  "geometry": {"coordinates":[5.2064580917,51.209438324],"type":"Point"}
}