{
  "type": "Feature",
  "properties": {
    "iso:country":"BE",
    "sg:address":"Erperheidestraat 2 Box 3",
    "sg:city":"Peer (grote Brogel)",
    "sg:classifiers":[
        {
            "category":"Travel",
            "subcategory":"Resort",
            "type":"Entertainment"
        }
    ],
    "sg:phone":"+32 11 54 82 00",
    "sg:postcode":"3990",
    "sg:province":"Limburg",
    "sg:tags":[
        "vacation"
    ],
    "wof:name":"Center Parcs Belgi\u00eb",
    "wof:placetype":"venue"
},
  "geometry": {"coordinates":[5.5019788742,51.1306495667],"type":"Point"}
}