{
  "type": "Feature",
  "properties": {
    "iso:country":"BE",
    "sg:address":"Val Vert 30",
    "sg:city":"Graven",
    "sg:orig_category":"Tuinen",
    "sg:phone":"+32 10 84 19 79",
    "sg:postcode":"1390",
    "sg:province":"Brabant Wallon",
    "wof:name":"Morren",
    "wof:placetype":"venue"
},
  "geometry": {"coordinates":[4.6567511559,50.7665977478],"type":"Point"}
}