{
  "type": "Feature",
  "properties": {
    "addr:full":"Rue De La Consolation 20 Schaarbeek/schaerbeek Bruxelles-Capitale 1030",
    "addr:housenumber":"20",
    "addr:postcode":"1030",
    "addr:street":"Rue De La Consolation",
    "iso:country":"BE",
    "sg:address":"Rue De La Consolation 20",
    "sg:city":"Schaarbeek/schaerbeek",
    "sg:orig_category":"Epiceries",
    "sg:phone":"+32 2 242 53 96",
    "sg:postcode":"1030",
    "sg:province":"Bruxelles-Capitale",
    "wof:name":"Erkomarket",
    "wof:placetype":"venue"
},
  "geometry": {"coordinates":[4.376511097,50.8566665649],"type":"Point"}
}