{
  "type": "Feature",
  "properties": {
    "addr:full":"Autolei 309 Wommelgem Antwerpen 2160",
    "addr:housenumber":"309",
    "addr:postcode":"2160",
    "iso:country":"BE",
    "sg:address":"Autolei 309",
    "sg:city":"Wommelgem",
    "sg:orig_category":"Reisbureaus",
    "sg:phone":"+32 3 354 12 00",
    "sg:postcode":"2160",
    "sg:province":"Antwerpen",
    "wof:name":"Paradiso Tours",
    "wof:placetype":"venue"
},
  "geometry": {"coordinates":[4.4934468269,51.21251297],"type":"Point"}
}