{
  "type": "Feature",
  "properties": {
    "addr:full":"Rue Chasseurs Ardennais 115 Tintigny Luxembourg 6730",
    "addr:housenumber":"115",
    "addr:postcode":"6730",
    "addr:street":"Rue Chasseurs Ardennais",
    "iso:country":"BE",
    "sg:address":"Rue Chasseurs Ardennais 115",
    "sg:city":"Tintigny",
    "sg:orig_category":"Installation \u00e9lectrique r\u00e9sidentielle",
    "sg:phone":"+32 63 44 47 24",
    "sg:postcode":"6730",
    "sg:province":"Luxembourg",
    "wof:name":"Fe. Orban",
    "wof:placetype":"venue"
},
  "geometry": {"coordinates":[5.4737119675,49.6768951416],"type":"Point"}
}