{
  "type": "Feature",
  "properties": {
    "iso:country":"BE",
    "sg:address":"Stationsstraat 2",
    "sg:city":"Waregem",
    "sg:orig_category":"V\u00eatements pour Hommes",
    "sg:phone":"+32 56 60 86 93",
    "sg:postcode":"8790",
    "sg:province":"West-Vlaanderen",
    "wof:name":"Huis Eldolux",
    "wof:placetype":"venue"
},
  "geometry": {"coordinates":[3.4315319061,50.8871116638],"type":"Point"}
}