{
  "type": "Feature",
  "properties": {
    "addr:full":"Leuvensestraat 16a Vilvoorde Vlaams-Brabant 1800",
    "addr:housenumber":"16a",
    "addr:postcode":"1800",
    "addr:street":"Leuvensestraat",
    "iso:country":"BE",
    "sg:address":"Leuvensestraat 16a",
    "sg:city":"Vilvoorde",
    "sg:classifiers":[
        {
            "category":"Shopping",
            "subcategory":"Jewelry",
            "type":"Retail Goods"
        }
    ],
    "sg:phone":"+32 2 251 13 10",
    "sg:postcode":"1800",
    "sg:province":"Vlaams-Brabant",
    "sg:tags":[
        "jeweller",
        "-"
    ],
    "wof:name":"Van Hoof Bvba",
    "wof:placetype":"venue"
},
  "geometry": {"coordinates":[4.4248280525,50.9285621643],"type":"Point"}
}