{
  "type": "Feature",
  "properties": {
    "addr:full":"Hoogstraat 177 Herzele Oost-Vlaanderen 9550",
    "addr:housenumber":"177",
    "addr:postcode":"9550",
    "addr:street":"Hoogstraat;Oost-Vlaanderen",
    "iso:country":"BE",
    "sg:address":"Hoogstraat 177",
    "sg:city":"Herzele",
    "sg:classifiers":[
        {
            "category":"Manufacturing",
            "subcategory":"Textiles",
            "type":"Manufacturing & Wholesale Goods"
        }
    ],
    "sg:phone":"+32 53 63 02 00",
    "sg:postcode":"9550",
    "sg:province":"Oost-Vlaanderen",
    "sg:tags":[
        "curtain",
        "fabric"
    ],
    "wof:name":"Boelaert - Moens B.v.b.a.",
    "wof:placetype":"venue"
},
  "geometry": {"coordinates":[3.8651800156,50.8779296875],"type":"Point"}
}