{
  "type": "Feature",
  "properties": {
    "addr:full":"Grand Place 26 La Louviere Hainaut 7100",
    "addr:housenumber":"26",
    "addr:postcode":"7100",
    "addr:street":"Grand Place",
    "iso:country":"BE",
    "sg:address":"Grand Place 26",
    "sg:city":"La Louviere",
    "sg:orig_category":"Supermarch\u00e9s",
    "sg:phone":"+32 64 28 51 61",
    "sg:postcode":"7100",
    "sg:province":"Hainaut",
    "wof:name":"Super C",
    "wof:placetype":"venue"
},
  "geometry": {"coordinates":[4.1850848198,50.4748649597],"type":"Point"}
}