{
  "type": "Feature",
  "properties": {
    "iso:country":"BE",
    "sg:address":"Grote Markt 19 Box 1",
    "sg:city":"Izegem",
    "sg:classifiers":[
        {
            "category":"Personal",
            "subcategory":"Beauty Salon",
            "type":"Services"
        }
    ],
    "sg:phone":"+32 51 31 25 90",
    "sg:postcode":"8870",
    "sg:province":"West-Vlaanderen",
    "sg:tags":[
        "lady",
        "-",
        "hairdressing"
    ],
    "wof:name":"Bg Hairdressing",
    "wof:placetype":"venue"
},
  "geometry": {"coordinates":[3.2148489952,50.9183387756],"type":"Point"}
}