{
  "type": "Feature",
  "properties": {
    "addr:full":"Tiyou D'hestreu 23 Anthisnes (tavier) Li\u00e8ge 4163",
    "addr:housenumber":"23",
    "addr:postcode":"4163",
    "addr:street":"Anthisnes Tavier",
    "iso:country":"BE",
    "sg:address":"Tiyou D'hestreu 23",
    "sg:city":"Anthisnes (tavier)",
    "sg:classifiers":[
        {
            "category":"Building & Trades",
            "subcategory":"Construction",
            "type":"Services"
        }
    ],
    "sg:phone":"+32 4 383 69 38",
    "sg:postcode":"4163",
    "sg:province":"Li\u00e8ge",
    "sg:tags":[
        "carpenter"
    ],
    "wof:name":"Jeunechamps A & Fils",
    "wof:placetype":"venue"
},
  "geometry": {"coordinates":[5.5019922256,50.506893158],"type":"Point"}
}