{
  "type": "Feature",
  "properties": {
    "iso:country":"BE",
    "sg:address":"Wijerken 144",
    "sg:city":"Lommel",
    "sg:orig_category":"Boekhouders",
    "sg:phone":"+32 11 55 18 09",
    "sg:postcode":"3920",
    "sg:province":"Limburg",
    "wof:name":"Theodorus Brusselaers",
    "wof:placetype":"venue"
},
  "geometry": {"coordinates":[5.2934150696,51.235710144],"type":"Point"}
}