{
  "type": "Feature",
  "properties": {
    "iso:country":"BE",
    "sg:address":"Rue Dries 203",
    "sg:city":"Bruxelles (woluwe-saint-lambert)",
    "sg:classifiers":[
        {
            "category":"Building & Trades",
            "subcategory":"Plumbing",
            "type":"Services"
        }
    ],
    "sg:phone":"+32 2 762 74 31",
    "sg:postcode":"1200",
    "sg:province":"Bruxelles-Capitale",
    "sg:tags":[
        "contractor"
    ],
    "wof:name":"Daoust C",
    "wof:placetype":"venue"
},
  "geometry": {"coordinates":[4.4228467941,50.8448829651],"type":"Point"}
}