{
  "type": "Feature",
  "properties": {
    "iso:country":"BE",
    "sg:address":"Rue Louis Lumi\u00c8re 17",
    "sg:city":"Vorst/forest",
    "sg:orig_category":"Mus\u00e9es and patrimoine culturel",
    "sg:phone":"+32 2 376 52 97",
    "sg:postcode":"1190",
    "sg:province":"Bruxelles-Capitale",
    "wof:name":"Brussels Little Museum",
    "wof:placetype":"venue"
},
  "geometry": {"coordinates":[4.3159618378,50.8039741516],"type":"Point"}
}