{
  "type": "Feature",
  "properties": {
    "addr:full":"Dorp 18a Wachtebeke Oost-Vlaanderen 9185",
    "addr:housenumber":"18a",
    "addr:postcode":"9185",
    "addr:street":"Dorp",
    "iso:country":"BE",
    "sg:address":"Dorp 18a",
    "sg:city":"Wachtebeke",
    "sg:classifiers":[
        {
            "category":"Health Services",
            "subcategory":"Dentist",
            "type":"Services"
        }
    ],
    "sg:phone":"+32 9 345 98 05",
    "sg:postcode":"9185",
    "sg:province":"Oost-Vlaanderen",
    "wof:name":"Van Der Aa P",
    "wof:placetype":"venue"
},
  "geometry": {"coordinates":[3.8554189205,51.1673660278],"type":"Point"}
}