{
  "type": "Feature",
  "properties": {
    "addr:full":"Rue De Tenbosch 94 Bruxelles (ixelles) Bruxelles-Capitale 1050",
    "addr:housenumber":"94",
    "addr:postcode":"1050",
    "addr:street":"Rue De Tenbosch",
    "iso:country":"BE",
    "sg:address":"Rue De Tenbosch 94",
    "sg:city":"Bruxelles (ixelles)",
    "sg:classifiers":[
        {
            "category":"Professional",
            "subcategory":"Management & Consulting",
            "type":"Services"
        }
    ],
    "sg:phone":"+32 2 343 31 15",
    "sg:postcode":"1050",
    "sg:province":"Bruxelles-Capitale",
    "sg:tags":[
        "-",
        "processing",
        "data",
        "consultant"
    ],
    "wof:name":"Czarevich",
    "wof:placetype":"venue"
},
  "geometry": {"coordinates":[4.3618831635,50.8212013245],"type":"Point"}
}