{
  "type": "Feature",
  "properties": {
    "iso:country":"BE",
    "sg:address":"De Wandstraat 123",
    "sg:city":"Brussel/bruxelles",
    "sg:orig_category":"Brood, gebak and snoepgoed",
    "sg:phone":"+32 2 268 39 85",
    "sg:postcode":"1020",
    "sg:province":"Bruxelles-Capitale",
    "wof:name":"Corn\u00c9 Port-royal Chocolatier",
    "wof:placetype":"venue"
},
  "geometry": {"coordinates":[4.3597359657,50.898563385],"type":"Point"}
}