{
  "type": "Feature",
  "properties": {
    "iso:country":"BE",
    "sg:address":"Wakkensesteenweg 30a",
    "sg:city":"Tielt",
    "sg:classifiers":[
        {
            "category":"Home & Garden",
            "subcategory":"Carpets & Floor Coverings",
            "type":"Retail Goods"
        }
    ],
    "sg:phone":"+32 51 40 34 70",
    "sg:postcode":"8700",
    "sg:province":"West-Vlaanderen",
    "sg:tags":[
        "layer",
        "mosaicists"
    ],
    "wof:name":"De Maeght Bvba",
    "wof:placetype":"venue"
},
  "geometry": {"coordinates":[3.3538839817,50.9740753174],"type":"Point"}
}