{
  "type": "Feature",
  "properties": {
    "addr:full":"Rozenhoedkaai 7 Brugge West-Vlaanderen 8000",
    "addr:housenumber":"7",
    "addr:postcode":"8000",
    "addr:street":"Rozenhoedkaai",
    "iso:country":"BE",
    "sg:address":"Rozenhoedkaai 7",
    "sg:city":"Brugge",
    "sg:orig_category":"Non-Classified Establishments",
    "sg:phone":"+32 50 34 21 07",
    "sg:postcode":"8000",
    "sg:province":"West-Vlaanderen",
    "wof:name":"Lace Pearl",
    "wof:placetype":"venue"
},
  "geometry": {"coordinates":[3.2278079987,51.2071304321],"type":"Point"}
}