{
  "type": "Feature",
  "properties": {
    "addr:full":"Groendreef 18 Harelbeke West-Vlaanderen 8530",
    "addr:housenumber":"18",
    "addr:postcode":"8530",
    "addr:street":"Groendreef",
    "iso:country":"BE",
    "sg:address":"Groendreef 18",
    "sg:city":"Harelbeke",
    "sg:orig_category":"M\u00e9decins and sp\u00e9cialistes",
    "sg:phone":"+32 56 22 23 31",
    "sg:postcode":"8530",
    "sg:province":"West-Vlaanderen",
    "wof:name":"Joseph Danneels",
    "wof:placetype":"venue"
},
  "geometry": {"coordinates":[3.311522007,50.8322906494],"type":"Point"}
}