{
  "type": "Feature",
  "properties": {
    "addr:full":"Rue Georges Hendrickx 2 Incourt Brabant Wallon 1315",
    "addr:housenumber":"2",
    "addr:postcode":"1315",
    "addr:street":"Rue Georges Hendrickx",
    "iso:country":"BE",
    "sg:address":"Rue Georges Hendrickx 2",
    "sg:city":"Incourt",
    "sg:orig_category":"DIVERSE RECREATIEVE ACTIVITEITEN",
    "sg:phone":"+32 10 84 49 60",
    "sg:postcode":"1315",
    "sg:province":"Brabant Wallon",
    "wof:name":"B.c. La Cure",
    "wof:placetype":"venue"
},
  "geometry": {"coordinates":[4.799115181,50.6915283203],"type":"Point"}
}