{
  "type": "Feature",
  "properties": {
    "addr:full":"Rue Des Am\u00c9ricains 12 Ans Li\u00e8ge 4432",
    "addr:housenumber":"12",
    "addr:postcode":"4432",
    "addr:street":"Rue Des Ame\u0301Ricains",
    "iso:country":"BE",
    "sg:address":"Rue Des Am\u00c9ricains 12",
    "sg:city":"Ans",
    "sg:orig_category":"Traitements param\u00e9dicaux",
    "sg:phone":"+32 4 246 43 04",
    "sg:postcode":"4432",
    "sg:province":"Li\u00e8ge",
    "wof:name":"Brakmeyn",
    "wof:placetype":"venue"
},
  "geometry": {"coordinates":[5.5108451843,50.6731529236],"type":"Point"}
}