{
  "type": "Feature",
  "properties": {
    "iso:country":"BE",
    "sg:address":"Rue Du Vieux Moulin 33",
    "sg:city":"Charleroi",
    "sg:orig_category":"Kapsalons Schoonheidssalons",
    "sg:phone":"+32 71 43 10 36",
    "sg:postcode":"6001",
    "sg:province":"Hainaut",
    "wof:name":"P\u00c9dicure Mireille",
    "wof:placetype":"venue"
},
  "geometry": {"coordinates":[4.4474830627,50.3968925476],"type":"Point"}
}