{
  "type": "Feature",
  "properties": {
    "addr:full":"Sint-katelijnestraat 43 Brussel/bruxelles Bruxelles-Capitale 1000",
    "addr:housenumber":"43",
    "addr:postcode":"1000",
    "addr:street":"Sint-Katelijnestraat;/",
    "iso:country":"BE",
    "sg:address":"Sint-katelijnestraat 43",
    "sg:city":"Brussel/bruxelles",
    "sg:orig_category":"Verplichte sociale verzekeringen",
    "sg:phone":"+32 2 512 15 28",
    "sg:postcode":"1000",
    "sg:province":"Bruxelles-Capitale",
    "wof:name":"Mutualit\u00c9 Socialiste",
    "wof:placetype":"venue"
},
  "geometry": {"coordinates":[4.3481388092,50.8504943848],"type":"Point"}
}