{
  "type": "Feature",
  "properties": {
    "iso:country":"BE",
    "sg:address":"Oude Geelsebaan 1",
    "sg:city":"Laakdal (veerle)",
    "sg:orig_category":"Newspapers, magazines, periodicals - Distribution",
    "sg:phone":"+32 14 84 12 54",
    "sg:postcode":"2431",
    "sg:province":"Antwerpen",
    "wof:name":"Nirvana-center",
    "wof:placetype":"venue"
},
  "geometry": {"coordinates":[4.9808039665,51.0682487488],"type":"Point"}
}