{
  "type": "Feature",
  "properties": {
    "addr:full":"Kleine Wouwer 67 Meise Vlaams-Brabant 1860",
    "addr:housenumber":"67",
    "addr:postcode":"1860",
    "addr:street":"Kleine Wouwer",
    "iso:country":"BE",
    "sg:address":"Kleine Wouwer 67",
    "sg:city":"Meise",
    "sg:classifiers":[
        {
            "category":"Insurance",
            "subcategory":"Insurance Agent",
            "type":"Services"
        }
    ],
    "sg:phone":"+32 2 269 59 74",
    "sg:postcode":"1860",
    "sg:province":"Vlaams-Brabant",
    "sg:tags":[
        "broker"
    ],
    "wof:name":"D'hert Bvba",
    "wof:placetype":"venue"
},
  "geometry": {"coordinates":[4.3161511421,50.9363059998],"type":"Point"}
}