{
  "type": "Feature",
  "properties": {
    "addr:full":"Rue Des Chartreux 19b22 Brussel Bruxelles-Capitale 1000",
    "addr:housenumber":"19b22",
    "addr:postcode":"1000",
    "addr:street":"Rue Des Chartreux",
    "iso:country":"BE",
    "sg:address":"Rue Des Chartreux 19b22",
    "sg:city":"Brussel",
    "sg:orig_category":"Woningbouw",
    "sg:phone":"+32 2 513 50 24",
    "sg:postcode":"1000",
    "sg:province":"Bruxelles-Capitale",
    "wof:name":"Statua Sprl",
    "wof:placetype":"venue"
},
  "geometry": {"coordinates":[4.3464798927,50.8489494324],"type":"Point"}
}