{
  "type": "Feature",
  "properties": {
    "iso:country":"BE",
    "sg:address":"Gr\u00c9trystraat 26",
    "sg:city":"Brussel/bruxelles",
    "sg:orig_category":"Maatschappelijke dienstverlening",
    "sg:phone":"+32 2 209 07 20",
    "sg:postcode":"1000",
    "sg:province":"Bruxelles-Capitale",
    "wof:name":"Int. Jeugdcentrum Vl.gem.",
    "wof:placetype":"venue"
},
  "geometry": {"coordinates":[4.3522801399,50.8492202759],"type":"Point"}
}