{
  "type": "Feature",
  "properties": {
    "addr:full":"Campionlei 13 Vilvoorde Vlaams-Brabant 1800",
    "addr:housenumber":"13",
    "addr:postcode":"1800",
    "addr:street":"Campionlei",
    "iso:country":"BE",
    "sg:address":"Campionlei 13",
    "sg:city":"Vilvoorde",
    "sg:orig_category":"Forge, Moulage and Profilage des M\u00e9taux. Constructions non r\u00e9sidentielles sp\u00e9cifiques",
    "sg:phone":"+32 2 251 40 70",
    "sg:postcode":"1800",
    "sg:province":"Vlaams-Brabant",
    "wof:name":"Multipose",
    "wof:placetype":"venue"
},
  "geometry": {"coordinates":[4.4312958717,50.9279785156],"type":"Point"}
}