{
  "type": "Feature",
  "properties": {
    "addr:full":"Albert Vanderkinderestr. 12a Sint-jans-molenbeek/molenbeek-saint-jean Bruxelles-Capitale 1080",
    "addr:housenumber":"12a sint-jans-molenbeek",
    "addr:postcode":"1080",
    "iso:country":"BE",
    "sg:address":"Albert Vanderkinderestr. 12a",
    "sg:city":"Sint-jans-molenbeek/molenbeek-saint-jean",
    "sg:orig_category":"Afvalwaterverwerking and ontstoppingsdiensten",
    "sg:phone":"+32 2 410 17 80",
    "sg:postcode":"1080",
    "sg:province":"Bruxelles-Capitale",
    "wof:name":"D.m.o.",
    "wof:placetype":"venue"
},
  "geometry": {"coordinates":[4.3291201591,50.8504295349],"type":"Point"}
}