{
  "type": "Feature",
  "properties": {
    "addr:full":"Torkonjestraat 21 Kortrijk (marke) West-Vlaanderen 8510",
    "addr:housenumber":"21",
    "addr:postcode":"8510",
    "addr:street":"Torkonjestraat",
    "iso:country":"BE",
    "sg:address":"Torkonjestraat 21",
    "sg:city":"Kortrijk (marke)",
    "sg:classifiers":[
        {
            "category":"Shopping",
            "type":"Retail Goods"
        }
    ],
    "sg:phone":"+32 56 25 52 52",
    "sg:postcode":"8510",
    "sg:province":"West-Vlaanderen",
    "sg:tags":[
        "product",
        "cleaning",
        "maintenance"
    ],
    "wof:name":"Cleaningboy Bvba",
    "wof:placetype":"venue"
},
  "geometry": {"coordinates":[3.2410149574,50.795501709],"type":"Point"}
}