{
  "type": "Feature",
  "properties": {
    "addr:full":"Renaat Desmedtstraat 4 Staden West-Vlaanderen 8840",
    "addr:housenumber":"4",
    "addr:postcode":"8840",
    "addr:street":"Renaat Desmedtstraat",
    "iso:country":"BE",
    "sg:address":"Renaat Desmedtstraat 4",
    "sg:city":"Staden",
    "sg:orig_category":"Producteurs de l\u00e9gumes",
    "sg:phone":"+32 51 70 05 06",
    "sg:postcode":"8840",
    "sg:province":"West-Vlaanderen",
    "wof:name":"Luc Hoedt",
    "wof:placetype":"venue"
},
  "geometry": {"coordinates":[3.0249819756,50.9874343872],"type":"Point"}
}