{
  "type": "Feature",
  "properties": {
    "addr:full":"Rue Jean Paquot 65ba Elsene/ixelles Bruxelles-Capitale 1050",
    "addr:housenumber":"65ba",
    "addr:postcode":"1050",
    "addr:street":"Rue Jean Paquot",
    "iso:country":"BE",
    "sg:address":"Rue Jean Paquot 65ba",
    "sg:city":"Elsene/ixelles",
    "sg:orig_category":"M\u00e9decins and sp\u00e9cialistes",
    "sg:phone":"+32 2 641 44 45",
    "sg:postcode":"1050",
    "sg:province":"Bruxelles-Capitale",
    "wof:name":"Consultation Nourrissons",
    "wof:placetype":"venue"
},
  "geometry": {"coordinates":[4.3796310425,50.8247718811],"type":"Point"}
}