{
  "type": "Feature",
  "properties": {
    "addr:full":"Molenstraat 10 Stabroek (hoevenen) Antwerpen 2940",
    "addr:housenumber":"10",
    "addr:postcode":"2940",
    "addr:street":"Molenstraat",
    "iso:country":"BE",
    "sg:address":"Molenstraat 10",
    "sg:city":"Stabroek (hoevenen)",
    "sg:classifiers":[
        {
            "category":"Real Estate",
            "subcategory":"Architect",
            "type":"Services"
        }
    ],
    "sg:phone":"+32 3 605 30 31",
    "sg:postcode":"2940",
    "sg:province":"Antwerpen",
    "wof:name":"Cools B",
    "wof:placetype":"venue"
},
  "geometry": {"coordinates":[4.398651123,51.3452072144],"type":"Point"}
}