{
  "type": "Feature",
  "properties": {
    "addr:full":"Grotestraat 62 De Haan (vlissegem) West-Vlaanderen 8421",
    "addr:housenumber":"62;8421",
    "addr:street":"Grotestraat",
    "iso:country":"BE",
    "sg:address":"Grotestraat 62",
    "sg:city":"De Haan (vlissegem)",
    "sg:classifiers":[
        {
            "category":"Shopping",
            "subcategory":"Baby Store",
            "type":"Retail Goods"
        }
    ],
    "sg:phone":"+32 59 23 51 59",
    "sg:postcode":"8421",
    "sg:province":"West-Vlaanderen",
    "sg:tags":[
        "midwife"
    ],
    "wof:name":"Geleleens C",
    "wof:placetype":"venue"
},
  "geometry": {"coordinates":[3.0411510468,51.2712516785],"type":"Point"}
}