{
  "type": "Feature",
  "properties": {
    "iso:country":"BE",
    "sg:address":"Moststraat 5",
    "sg:city":"Gent",
    "sg:orig_category":"Zuivelproducten",
    "sg:phone":"+32 9 251 03 13",
    "sg:postcode":"9041",
    "sg:province":"Oost-Vlaanderen",
    "wof:name":"Luc Boelaert",
    "wof:placetype":"venue"
},
  "geometry": {"coordinates":[3.7769579887,51.1037635803],"type":"Point"}
}