{
  "type": "Feature",
  "properties": {
    "addr:full":"Avenue Du Lac 100 Rixensart Brabant Wallon 1332",
    "addr:housenumber":"100",
    "addr:postcode":"1332",
    "addr:street":"Avenue Du Lac;Wallon",
    "iso:country":"BE",
    "sg:address":"Avenue Du Lac 100",
    "sg:city":"Rixensart",
    "sg:classifiers":[
        {
            "category":"Restaurant",
            "type":"Food & Drink"
        }
    ],
    "sg:phone":"+32 2 654 12 18",
    "sg:postcode":"1332",
    "sg:province":"Brabant Wallon",
    "wof:name":"Rest. Le Caraquin Du Lac",
    "wof:placetype":"venue"
},
  "geometry": {"coordinates":[4.511179924,50.7301292419],"type":"Point"}
}