{
  "type": "Feature",
  "properties": {
    "iso:country":"BE",
    "sg:address":"Opperstraat 40",
    "sg:city":"Elsene/ixelles",
    "sg:orig_category":"Artiesten and kunstenaars Divers amusement",
    "sg:phone":"+32 2 289 09 10",
    "sg:postcode":"1050",
    "sg:province":"Bruxelles-Capitale",
    "wof:name":"Allez, Gorilles! Product.",
    "wof:placetype":"venue"
},
  "geometry": {"coordinates":[4.3646569252,50.8327064514],"type":"Point"}
}