{
  "type": "Feature",
  "properties": {
    "addr:full":"Vijfwegenstraat 13 Izegem West-Vlaanderen 8870",
    "addr:housenumber":"13",
    "addr:postcode":"8870",
    "addr:street":"Vijfwegenstraat",
    "iso:country":"BE",
    "sg:address":"Vijfwegenstraat 13",
    "sg:city":"Izegem",
    "sg:classifiers":[
        {
            "category":"Manufacturing",
            "subcategory":"Motor Vehicles & Parts",
            "type":"Manufacturing & Wholesale Goods"
        }
    ],
    "sg:phone":"+32 51 30 39 65",
    "sg:postcode":"8870",
    "sg:province":"West-Vlaanderen",
    "sg:tags":[
        "radiator",
        "panelling"
    ],
    "wof:name":"Wer-kreatie",
    "wof:placetype":"venue"
},
  "geometry": {"coordinates":[3.2162029743,50.92552948],"type":"Point"}
}