{
  "type": "Feature",
  "properties": {
    "addr:full":"Quai De Gaulle 13 Li\u00c8ge Li\u00e8ge 4020",
    "addr:housenumber":"13",
    "addr:postcode":"4020",
    "addr:street":"Quai De Gaulle",
    "iso:country":"BE",
    "sg:address":"Quai De Gaulle 13",
    "sg:city":"Li\u00c8ge",
    "sg:orig_category":"Artsen and specialisten",
    "sg:phone":"+32 4 343 09 65",
    "sg:postcode":"4020",
    "sg:province":"Li\u00e8ge",
    "wof:name":"Mireille Nzolameso Nkosi",
    "wof:placetype":"venue"
},
  "geometry": {"coordinates":[5.5794129372,50.6422462463],"type":"Point"}
}