{
  "type": "Feature",
  "properties": {
    "iso:country":"BE",
    "sg:address":"Rue De L'oseraie 9",
    "sg:city":"Vise",
    "sg:orig_category":"Tuinen",
    "sg:phone":"+32 4 379 59 29",
    "sg:postcode":"4600",
    "sg:province":"Li\u00e8ge",
    "wof:name":"Ernotte",
    "wof:placetype":"venue"
},
  "geometry": {"coordinates":[5.6999330521,50.7177047729],"type":"Point"}
}