{
  "type": "Feature",
  "properties": {
    "addr:full":"Jules Sermonstraat 17 Sint-pieters-leeuw Vlaams-Brabant 1600",
    "addr:housenumber":"17",
    "addr:postcode":"1600",
    "addr:street":"Sermonstraat",
    "iso:country":"BE",
    "sg:address":"Jules Sermonstraat 17",
    "sg:city":"Sint-pieters-leeuw",
    "sg:classifiers":[
        {
            "category":"Health Services",
            "subcategory":"Nursing And Care Facility",
            "type":"Services"
        }
    ],
    "sg:phone":"+32 2 377 18 90",
    "sg:postcode":"1600",
    "sg:province":"Vlaams-Brabant",
    "sg:tags":[
        "home",
        "rest"
    ],
    "wof:name":"St-antonius Vzw",
    "wof:placetype":"venue"
},
  "geometry": {"coordinates":[4.242910862,50.7774238586],"type":"Point"}
}