{
  "type": "Feature",
  "properties": {
    "addr:full":"Diksmuidsesteenweg 350 Roeselare West-Vlaanderen 8800",
    "addr:housenumber":"350",
    "addr:postcode":"8800",
    "addr:street":"Diksmuidsesteenweg",
    "iso:country":"BE",
    "sg:address":"Diksmuidsesteenweg 350",
    "sg:city":"Roeselare",
    "sg:orig_category":"V\u00eatements",
    "sg:phone":"+32 51 20 68 86",
    "sg:postcode":"8800",
    "sg:province":"West-Vlaanderen",
    "wof:name":"Jeansdepot",
    "wof:placetype":"venue"
},
  "geometry": {"coordinates":[3.1063539982,50.9491958618],"type":"Point"}
}