{
  "type": "Feature",
  "properties": {
    "iso:country":"BE",
    "sg:address":"Haasstrasse 19",
    "sg:city":"Eupen/eupen",
    "sg:orig_category":"Slagers",
    "sg:phone":"+32 87 55 49 09",
    "sg:postcode":"4700",
    "sg:province":"Li\u00e8ge",
    "wof:name":"Wilhelm Heinrichs",
    "wof:placetype":"venue"
},
  "geometry": {"coordinates":[6.0374588966,50.623462677],"type":"Point"}
}