{
  "type": "Feature",
  "properties": {
    "iso:country":"BE",
    "sg:address":"Rue De La Lasne 102",
    "sg:city":"Lasne",
    "sg:orig_category":"Agences immobili\u00e8res",
    "sg:phone":"+32 2 633 55 05",
    "sg:postcode":"1380",
    "sg:province":"Brabant Wallon",
    "wof:name":"Lasne Consult",
    "wof:placetype":"venue"
},
  "geometry": {"coordinates":[4.4943079948,50.6963005066],"type":"Point"}
}