{
  "type": "Feature",
  "properties": {
    "iso:country":"BE",
    "sg:address":"Brugsestraat 204",
    "sg:city":"Zedelgem",
    "sg:orig_category":"R\u00e9alisation de programmes and logiciels. Ordinateurs and \u00e9quipement informatique",
    "sg:phone":"+32 50 59 85 35",
    "sg:postcode":"8210",
    "sg:province":"West-Vlaanderen",
    "wof:name":"General Software Asist",
    "wof:placetype":"venue"
},
  "geometry": {"coordinates":[3.1413829327,51.1273002625],"type":"Point"}
}