{
  "type": "Feature",
  "properties": {
    "addr:full":"Herentalsstraat 52 Turnhout Antwerpen 2300",
    "addr:housenumber":"52",
    "addr:postcode":"2300",
    "addr:street":"Herentalsstraat",
    "iso:country":"BE",
    "sg:address":"Herentalsstraat 52",
    "sg:city":"Turnhout",
    "sg:orig_category":"Artsen and specialisten",
    "sg:phone":"+32 14 41 50 44",
    "sg:postcode":"2300",
    "sg:province":"Antwerpen",
    "wof:name":"Michel De Peuter",
    "wof:placetype":"venue"
},
  "geometry": {"coordinates":[4.9493641853,51.3199615479],"type":"Point"}
}