{
  "type": "Feature",
  "properties": {
    "iso:country":"BE",
    "sg:address":"Kasteelstraat 30",
    "sg:city":"Kortrijk",
    "sg:classifiers":[
        {
            "category":"Retail",
            "subcategory":"Auto Repair",
            "type":"Services"
        }
    ],
    "sg:phone":"+32 56 22 20 18",
    "sg:postcode":"8500",
    "sg:province":"West-Vlaanderen",
    "sg:tags":[
        "garage"
    ],
    "wof:name":"Devoldere G",
    "wof:placetype":"venue"
},
  "geometry": {"coordinates":[3.2613890171,50.8290252686],"type":"Point"}
}