{
  "type": "Feature",
  "properties": {
    "iso:country":"BE",
    "sg:address":"Leuvensestraat 11",
    "sg:city":"Tienen",
    "sg:classifiers":[
        {
            "category":"Utilities",
            "subcategory":"Mobile Phone",
            "type":"Services"
        }
    ],
    "sg:phone":"+32 16 56 10 62",
    "sg:postcode":"3300",
    "sg:province":"Vlaams-Brabant",
    "sg:tags":[
        "-",
        "gsm"
    ],
    "wof:name":"Mobistar Center Tienen",
    "wof:placetype":"venue"
},
  "geometry": {"coordinates":[4.9291129112,50.810005188],"type":"Point"}
}