{
  "type": "Feature",
  "properties": {
    "addr:full":"Degr\u00c9s-des-tisserands 37 Li\u00c8ge Li\u00e8ge 4000",
    "addr:housenumber":"37",
    "addr:postcode":"4000",
    "addr:street":"Degre\u0301S-Des-Tisserands",
    "iso:country":"BE",
    "sg:address":"Degr\u00c9s-des-tisserands 37",
    "sg:city":"Li\u00c8ge",
    "sg:orig_category":"Zalen voor culturele evenementen",
    "sg:phone":"+32 4 224 26 94",
    "sg:postcode":"4000",
    "sg:province":"Li\u00e8ge",
    "wof:name":"Th\u00c9\u00c2tre Fraction Neige",
    "wof:placetype":"venue"
},
  "geometry": {"coordinates":[5.5634231567,50.6447219849],"type":"Point"}
}