{
  "type": "Feature",
  "properties": {
    "addr:full":"Mechelseweg 22 Aalst (baardegem) Oost-Vlaanderen 9310",
    "addr:housenumber":"22",
    "addr:postcode":"9310",
    "addr:street":"Mechelseweg",
    "iso:country":"BE",
    "sg:address":"Mechelseweg 22",
    "sg:city":"Aalst (baardegem)",
    "sg:orig_category":"Scenery Stage-, film-, and television",
    "sg:phone":"+32 475 49 29 48",
    "sg:postcode":"9310",
    "sg:province":"Oost-Vlaanderen",
    "wof:name":"Pdk-creaties Bvba",
    "wof:placetype":"venue"
},
  "geometry": {"coordinates":[4.1377639771,50.9561767578],"type":"Point"}
}