{
  "type": "Feature",
  "properties": {
    "addr:full":"Rue Du Pr\u00c9v\u00d4t 8-10 Elsene/ixelles Bruxelles-Capitale 1050",
    "addr:housenumber":"8-10",
    "addr:postcode":"1050",
    "addr:street":"Rue Du Pre\u0301Vo\u0302T",
    "iso:country":"BE",
    "sg:address":"Rue Du Pr\u00c9v\u00d4t 8-10",
    "sg:city":"Elsene/ixelles",
    "sg:orig_category":"Herstellingen and onderhoud van auto's Onderdelen and accessoires voor auto's Voertuigen",
    "sg:phone":"+32 2 537 98 44",
    "sg:postcode":"1050",
    "sg:province":"Bruxelles-Capitale",
    "wof:name":"Anciens Smaers",
    "wof:placetype":"venue"
},
  "geometry": {"coordinates":[4.3581171036,50.8222961426],"type":"Point"}
}