{
  "type": "Feature",
  "properties": {
    "addr:full":"Place De La Chapelle 1 Mons Hainaut 7022",
    "addr:housenumber":"1",
    "addr:postcode":"7022",
    "addr:street":"Place De La Chapelle;Hainaut",
    "iso:country":"BE",
    "sg:address":"Place De La Chapelle 1",
    "sg:city":"Mons",
    "sg:orig_category":"Banken and kredietinstellingen",
    "sg:phone":"+32 65 33 56 91",
    "sg:postcode":"7022",
    "sg:province":"Hainaut",
    "wof:name":"Fortis",
    "wof:placetype":"venue"
},
  "geometry": {"coordinates":[4.0181078911,50.4045410156],"type":"Point"}
}