{
  "type": "Feature",
  "properties": {
    "addr:full":"Spelonckvaart 36 Moerbeke Oost-Vlaanderen 9180",
    "addr:housenumber":"36",
    "addr:postcode":"9180",
    "addr:street":"Spelonckvaart",
    "iso:country":"BE",
    "sg:address":"Spelonckvaart 36",
    "sg:city":"Moerbeke",
    "sg:orig_category":"Eleveurs de bovins. Eleveurs and marchands de porcs",
    "sg:phone":"+32 9 346 72 72",
    "sg:postcode":"9180",
    "sg:province":"Oost-Vlaanderen",
    "wof:name":"Willy Tollenaere",
    "wof:placetype":"venue"
},
  "geometry": {"coordinates":[3.9539179802,51.1804275513],"type":"Point"}
}