{
  "type": "Feature",
  "properties": {
    "addr:full":"Rue Des Viaducs 181c Mons Hainaut 7020",
    "addr:housenumber":"181c",
    "addr:postcode":"7020",
    "addr:street":"Rue Des Viaducs;Hainaut",
    "iso:country":"BE",
    "sg:address":"Rue Des Viaducs 181c",
    "sg:city":"Mons",
    "sg:orig_category":"Biens d'occasion",
    "sg:phone":"+32 65 84 15 50",
    "sg:postcode":"7020",
    "sg:province":"Hainaut",
    "wof:name":"Pass\u00c9 Pr\u00c9sent Nimysien",
    "wof:placetype":"venue"
},
  "geometry": {"coordinates":[3.9553449154,50.4761772156],"type":"Point"}
}