{
  "type": "Feature",
  "properties": {
    "addr:full":"Rue Du Carmel 8ba Doische Namur 5680",
    "addr:housenumber":"8ba",
    "addr:postcode":"5680",
    "addr:street":"Rue Du Carmel",
    "iso:country":"BE",
    "sg:address":"Rue Du Carmel 8ba",
    "sg:city":"Doische",
    "sg:orig_category":"Pain, p\u00e2tisseries and confiseries",
    "sg:phone":"+32 60 39 90 12",
    "sg:postcode":"5680",
    "sg:province":"Namur",
    "wof:name":"Charlemagne",
    "wof:placetype":"venue"
},
  "geometry": {"coordinates":[4.6466832161,50.1194419861],"type":"Point"}
}