{
  "type": "Feature",
  "properties": {
    "iso:country":"BE",
    "sg:address":"Bruggestraat 64",
    "sg:city":"Hooglede",
    "sg:classifiers":[
        {
            "category":"Cafe",
            "type":"Food & Drink"
        }
    ],
    "sg:phone":"+32 51 20 36 65",
    "sg:postcode":"8830",
    "sg:province":"West-Vlaanderen",
    "sg:tags":[
        "caf\u00e9s"
    ],
    "wof:name":"Wim Vermaut",
    "wof:placetype":"venue"
},
  "geometry": {"coordinates":[3.0875198841,50.9796295166],"type":"Point"}
}