{
  "type": "Feature",
  "properties": {
    "addr:full":"Rue Des Cloutiers 98 Fleron Li\u00e8ge 4621",
    "addr:housenumber":"98",
    "addr:postcode":"4621",
    "addr:street":"Rue Des Cloutiers",
    "iso:country":"BE",
    "sg:address":"Rue Des Cloutiers 98",
    "sg:city":"Fleron",
    "sg:classifiers":[
        {
            "category":"Personal",
            "subcategory":"Beauty Salon",
            "type":"Services"
        }
    ],
    "sg:phone":"+32 4 358 34 52",
    "sg:postcode":"4621",
    "sg:province":"Li\u00e8ge",
    "sg:tags":[
        "de",
        "coiffure"
    ],
    "wof:name":"Jeanine Monseur",
    "wof:placetype":"venue"
},
  "geometry": {"coordinates":[5.6985001564,50.6245498657],"type":"Point"}
}