{
  "type": "Feature",
  "properties": {
    "addr:full":"Rue Du P\u00e2turage 13 Bruxelles Bruxelles-Capitale 1120",
    "addr:housenumber":"13",
    "addr:postcode":"1120",
    "addr:street":"Rue Du Pa\u0302Turage",
    "iso:country":"BE",
    "sg:address":"Rue Du P\u00e2turage 13",
    "sg:city":"Bruxelles",
    "sg:classifiers":[
        {
            "category":"Health Services",
            "subcategory":"Doctor",
            "type":"Services"
        }
    ],
    "sg:phone":"+32 2 268 48 01",
    "sg:postcode":"1120",
    "sg:province":"Bruxelles-Capitale",
    "sg:tags":[
        "medicinephysicians",
        "surgeon"
    ],
    "wof:name":"Dooreman P",
    "wof:placetype":"venue"
},
  "geometry": {"coordinates":[4.38002491,50.8951644897],"type":"Point"}
}