{
  "type": "Feature",
  "properties": {
    "iso:country":"BE",
    "sg:address":"Schransstraat 15",
    "sg:city":"Grobbendonk",
    "sg:classifiers":[
        {
            "category":"Shopping",
            "subcategory":"Gifts & Souvenirs",
            "type":"Retail Goods"
        }
    ],
    "sg:phone":"+32 477 77 78 17",
    "sg:postcode":"2280",
    "sg:province":"Antwerpen",
    "sg:tags":[
        "-"
    ],
    "wof:name":"Tilly Cambr\u00e9 Decorations",
    "wof:placetype":"venue"
},
  "geometry": {"coordinates":[4.7399587631,51.1929016113],"type":"Point"}
}