{
  "type": "Feature",
  "properties": {
    "iso:country":"BE",
    "sg:address":"Rue Grande 246",
    "sg:city":"Mons (maisi\u00e8res)",
    "sg:classifiers":[
        {
            "category":"Professional",
            "subcategory":"Computer Services",
            "type":"Services"
        }
    ],
    "sg:phone":"+32 65 73 19 07",
    "sg:postcode":"7020",
    "sg:province":"Hainaut",
    "sg:tags":[
        "-",
        "processing",
        "data"
    ],
    "wof:name":"Sh Connect & Computer Sa",
    "wof:placetype":"venue"
},
  "geometry": {"coordinates":[3.9553449154,50.4761772156],"type":"Point"}
}