{
  "type": "Feature",
  "properties": {
    "addr:full":"Grote Markt 41 Zelzate Oost-Vlaanderen 9060",
    "addr:housenumber":"41",
    "addr:postcode":"9060",
    "addr:street":"Grote Markt",
    "iso:country":"BE",
    "sg:address":"Grote Markt 41",
    "sg:city":"Zelzate",
    "sg:orig_category":"Boucheries",
    "sg:phone":"+32 9 345 80 80",
    "sg:postcode":"9060",
    "sg:province":"Oost-Vlaanderen",
    "wof:name":"Slagerij De Mol",
    "wof:placetype":"venue"
},
  "geometry": {"coordinates":[3.8108758926,51.2011604309],"type":"Point"}
}