{
  "type": "Feature",
  "properties": {
    "iso:country":"BE",
    "sg:address":"Zandbergen 18",
    "sg:city":"Dessel",
    "sg:classifiers":[
        {
            "category":"Shopping",
            "subcategory":"Bicycles & Sporting Goods",
            "type":"Retail Goods"
        }
    ],
    "sg:phone":"+32 14 32 60 50",
    "sg:postcode":"2480",
    "sg:province":"Antwerpen",
    "sg:tags":[
        "tyre"
    ],
    "wof:name":"Jacobs Trading Nv",
    "wof:placetype":"venue"
},
  "geometry": {"coordinates":[5.0722851753,51.2307090759],"type":"Point"}
}