{
  "type": "Feature",
  "properties": {
    "iso:country":"BE",
    "sg:address":"Watersniplein 1",
    "sg:city":"Brecht",
    "sg:orig_category":"Plantes and fleurs Gr",
    "sg:phone":"+32 3 636 40 73",
    "sg:postcode":"2960",
    "sg:province":"Antwerpen",
    "wof:name":"Van Der Lans",
    "wof:placetype":"venue"
},
  "geometry": {"coordinates":[4.5642461777,51.308971405],"type":"Point"}
}