{
  "type": "Feature",
  "properties": {
    "addr:full":"Clos Fernand Tonnet 10 Bruxelles (jette) Bruxelles-Capitale 1090",
    "addr:housenumber":"10",
    "addr:postcode":"1090",
    "addr:street":"Clos Fernand Tonnet",
    "iso:country":"BE",
    "sg:address":"Clos Fernand Tonnet 10",
    "sg:city":"Bruxelles (jette)",
    "sg:classifiers":[
        {
            "category":"Professional",
            "subcategory":"Accounting & Tax Preparation",
            "type":"Services"
        }
    ],
    "sg:phone":"+32 2 478 86 18",
    "sg:postcode":"1090",
    "sg:province":"Bruxelles-Capitale",
    "sg:tags":[
        "accountant"
    ],
    "wof:name":"Van Eeckhout P",
    "wof:placetype":"venue"
},
  "geometry": {"coordinates":[4.3211932182,50.8923187256],"type":"Point"}
}