{
  "type": "Feature",
  "properties": {
    "iso:country":"BE",
    "sg:address":"Kempischesteenweg 108",
    "sg:city":"Hasselt",
    "sg:classifiers":[
        {
            "category":"Restaurant",
            "type":"Food & Drink"
        }
    ],
    "sg:phone":"+32 11 21 07 17",
    "sg:postcode":"3500",
    "sg:province":"Limburg",
    "wof:name":"Villa Kerasus",
    "wof:placetype":"venue"
},
  "geometry": {"coordinates":[5.3406829834,50.9379234314],"type":"Point"}
}