{
  "type": "Feature",
  "properties": {
    "addr:full":"August De Batslaan 39 Temse Oost-Vlaanderen 9140",
    "addr:housenumber":"39",
    "addr:postcode":"9140",
    "addr:street":"August;Batslaan",
    "iso:country":"BE",
    "sg:address":"August De Batslaan 39",
    "sg:city":"Temse",
    "sg:classifiers":[
        {
            "category":"Cafe",
            "type":"Food & Drink"
        }
    ],
    "sg:phone":"+32 3 711 22 93",
    "sg:postcode":"9140",
    "sg:province":"Oost-Vlaanderen",
    "sg:tags":[
        "caf\u00e9s"
    ],
    "wof:name":"Rony Behiels",
    "wof:placetype":"venue"
},
  "geometry": {"coordinates":[4.1997828484,51.1319618225],"type":"Point"}
}