{
  "type": "Feature",
  "properties": {
    "addr:full":"Kapelsesteenweg 80 Brasschaat Antwerpen 2930",
    "addr:housenumber":"80",
    "addr:postcode":"2930",
    "addr:street":"Kapelsesteenweg",
    "iso:country":"BE",
    "sg:address":"Kapelsesteenweg 80",
    "sg:city":"Brasschaat",
    "sg:classifiers":[
        {
            "category":"Professional",
            "type":"Services"
        }
    ],
    "sg:phone":"+32 3 645 24 79",
    "sg:postcode":"2930",
    "sg:province":"Antwerpen",
    "sg:tags":[
        "surveyor",
        "-",
        "valuer"
    ],
    "wof:name":"Schrauwen",
    "wof:placetype":"venue"
},
  "geometry": {"coordinates":[4.4575171471,51.2735671997],"type":"Point"}
}