{
  "type": "Feature",
  "properties": {
    "addr:full":"R De L'avedelle 123 Ecaussinnes Hainaut 7190",
    "addr:housenumber":"123",
    "addr:postcode":"7190",
    "addr:street":"Hainaut",
    "iso:country":"BE",
    "sg:address":"R De L'avedelle 123",
    "sg:city":"Ecaussinnes",
    "sg:classifiers":[
        {
            "category":"Structure",
            "subcategory":"Office Building",
            "type":"Public Place"
        }
    ],
    "sg:phone":"+32 67 44 31 99",
    "sg:postcode":"7190",
    "sg:province":"Hainaut",
    "sg:tags":[
        "roofing",
        "slate"
    ],
    "wof:name":"Beghain Jean Sprl",
    "wof:placetype":"venue"
},
  "geometry": {"coordinates":[4.1780881882,50.5571212769],"type":"Point"}
}