{
  "type": "Feature",
  "properties": {
    "iso:country":"BE",
    "sg:address":"Klaprozenlaan 30",
    "sg:city":"Oostende",
    "sg:orig_category":"Boekenuitgeverijen Muziekinstrumenten",
    "sg:phone":"+32 59 70 32 22",
    "sg:postcode":"8400",
    "sg:province":"West-Vlaanderen",
    "wof:name":"Uitgave Andel Edition",
    "wof:placetype":"venue"
},
  "geometry": {"coordinates":[2.9126999378,51.2312583923],"type":"Point"}
}