{
  "type": "Feature",
  "properties": {
    "addr:full":"Koningin Astridlaan 82 Turnhout Antwerpen 2300",
    "addr:housenumber":"82",
    "addr:postcode":"2300",
    "addr:street":"Koningin Astridlaan",
    "iso:country":"BE",
    "sg:address":"Koningin Astridlaan 82",
    "sg:city":"Turnhout",
    "sg:classifiers":[
        {
            "category":"Home & Garden",
            "subcategory":"Building Materials",
            "type":"Retail Goods"
        }
    ],
    "sg:phone":"+32 14 41 75 02",
    "sg:postcode":"2300",
    "sg:province":"Antwerpen",
    "sg:tags":[
        "window"
    ],
    "wof:name":"Janssen Jef Ramen Turnhout",
    "wof:placetype":"venue"
},
  "geometry": {"coordinates":[4.9217262268,51.3240814209],"type":"Point"}
}