{
  "type": "Feature",
  "properties": {
    "addr:full":"Wijnendalestraat 104 Diksmuide West-Vlaanderen 8600",
    "addr:housenumber":"104",
    "addr:postcode":"8600",
    "addr:street":"Wijnendalestraat",
    "iso:country":"BE",
    "sg:address":"Wijnendalestraat 104",
    "sg:city":"Diksmuide",
    "sg:orig_category":"Epiceries",
    "sg:phone":"+32 51 50 13 36",
    "sg:postcode":"8600",
    "sg:province":"West-Vlaanderen",
    "wof:name":"Chr. Wynsberghe",
    "wof:placetype":"venue"
},
  "geometry": {"coordinates":[2.897589922,51.0601081848],"type":"Point"}
}