{
  "type": "Feature",
  "properties": {
    "iso:country":"BE",
    "sg:address":"Heldergemstraat 169",
    "sg:city":"Haaltert",
    "sg:orig_category":"Sportclubs Sportterreinen and installaties behalve sportcentra",
    "sg:phone":"+32 53 62 38 05",
    "sg:postcode":"9450",
    "sg:province":"Oost-Vlaanderen",
    "wof:name":"Sp. Heldergem",
    "wof:placetype":"venue"
},
  "geometry": {"coordinates":[3.9541289806,50.8814125061],"type":"Point"}
}