{
  "type": "Feature",
  "properties": {
    "addr:full":"Haverveldstraat 44 Heusden-zolder Limburg 3550",
    "addr:housenumber":"44",
    "addr:postcode":"3550",
    "addr:street":"Haverveldstraat",
    "iso:country":"BE",
    "sg:address":"Haverveldstraat 44",
    "sg:city":"Heusden-zolder",
    "sg:orig_category":"Fotografen and fotostudio's",
    "sg:phone":"+32 11 53 34 29",
    "sg:postcode":"3550",
    "sg:province":"Limburg",
    "wof:name":"Anton Van Duffel",
    "wof:placetype":"venue"
},
  "geometry": {"coordinates":[5.3063678741,51.0200080872],"type":"Point"}
}