{
  "type": "Feature",
  "properties": {
    "addr:full":"Kortrijksesteenweg 135 Deinze Oost-Vlaanderen 9800",
    "addr:housenumber":"135",
    "addr:postcode":"9800",
    "addr:street":"Kortrijksesteenweg",
    "iso:country":"BE",
    "sg:address":"Kortrijksesteenweg 135",
    "sg:city":"Deinze",
    "sg:classifiers":[
        {
            "category":"Personal",
            "subcategory":"Beauty Salon",
            "type":"Services"
        }
    ],
    "sg:phone":"+32 9 380 25 30",
    "sg:postcode":"9800",
    "sg:province":"Oost-Vlaanderen",
    "sg:tags":[
        "de",
        "coiffure"
    ],
    "wof:name":"Sylvie Bauwens",
    "wof:placetype":"venue"
},
  "geometry": {"coordinates":[3.5250399113,50.9756698608],"type":"Point"}
}