{
  "type": "Feature",
  "properties": {
    "addr:full":"Quai Du Roi Albert 77 Li\u00e8ge 1 (li\u00e8ge 2) Li\u00e8ge 4020",
    "addr:housenumber":"77;1;2",
    "addr:postcode":"4020",
    "addr:street":"Quai Du Roi Albert",
    "iso:country":"BE",
    "sg:address":"Quai Du Roi Albert 77",
    "sg:city":"Li\u00e8ge 1 (li\u00e8ge 2)",
    "sg:classifiers":[
        {
            "category":"Professional",
            "subcategory":"Lawyer & Legal Services",
            "type":"Services"
        }
    ],
    "sg:phone":"+32 4 344 48 45",
    "sg:postcode":"4020",
    "sg:province":"Li\u00e8ge",
    "wof:name":"Ellouze Mohamed",
    "wof:placetype":"venue"
},
  "geometry": {"coordinates":[5.5963511467,50.6454811096],"type":"Point"}
}