{
  "type": "Feature",
  "properties": {
    "addr:full":"Rue Monplaisir 16 Beloeil Hainaut 7972",
    "addr:housenumber":"16",
    "addr:postcode":"7972",
    "addr:street":"Rue Monplaisir",
    "iso:country":"BE",
    "sg:address":"Rue Monplaisir 16",
    "sg:city":"Beloeil",
    "sg:orig_category":"Glaszetten and glaswerk",
    "sg:phone":"+32 69 68 74 22",
    "sg:postcode":"7972",
    "sg:province":"Hainaut",
    "wof:name":"Sebastien Vinckier",
    "wof:placetype":"venue"
},
  "geometry": {"coordinates":[3.6723101139,50.560005188],"type":"Point"}
}