{
  "type": "Feature",
  "properties": {
    "iso:country":"BE",
    "sg:address":"Honingstraat 10",
    "sg:city":"Olen",
    "sg:classifiers":[
        {
            "category":"Ice Cream",
            "type":"Food & Drink"
        }
    ],
    "sg:phone":"+32 14 21 45 06",
    "sg:postcode":"2250",
    "sg:province":"Antwerpen",
    "wof:name":"Heuninghof ('t)",
    "wof:placetype":"venue"
},
  "geometry": {"coordinates":[4.8657188416,51.1501502991],"type":"Point"}
}