{
  "type": "Feature",
  "properties": {
    "addr:full":"Broekstraat 48 Kinrooi Limburg 3640",
    "addr:housenumber":"48",
    "addr:postcode":"3640",
    "addr:street":"Broekstraat",
    "iso:country":"BE",
    "sg:address":"Broekstraat 48",
    "sg:city":"Kinrooi",
    "sg:orig_category":"D\u00e9molition d\u00b4immeubles and terrassements",
    "sg:phone":"+32 89 70 21 39",
    "sg:postcode":"3640",
    "sg:province":"Limburg",
    "wof:name":"Heymans Grondwerken",
    "wof:placetype":"venue"
},
  "geometry": {"coordinates":[5.7166819572,51.1517105103],"type":"Point"}
}