{
  "type": "Feature",
  "properties": {
    "iso:country":"BE",
    "sg:address":"Dreef 36a",
    "sg:city":"Hoogstraten (meerle)",
    "sg:classifiers":[
        {
            "category":"Travel",
            "subcategory":"Resort",
            "type":"Entertainment"
        }
    ],
    "sg:phone":"+32 3 315 94 16",
    "sg:postcode":"2328",
    "sg:province":"Antwerpen",
    "sg:tags":[
        "vacation"
    ],
    "wof:name":"Elegast-meerseldreef",
    "wof:placetype":"venue"
},
  "geometry": {"coordinates":[4.8041949272,51.4741134644],"type":"Point"}
}