{
  "type": "Feature",
  "properties": {
    "addr:full":"Clos Saint Pierre 4 Hastiere Namur 5541",
    "addr:housenumber":"4",
    "addr:postcode":"5541",
    "addr:street":"Hastiere Namur",
    "iso:country":"BE",
    "sg:address":"Clos Saint Pierre 4",
    "sg:city":"Hastiere",
    "sg:orig_category":"Drogisterijen Plaatsen van vloer- and muurbekleding Schilders",
    "sg:phone":"+32 82 64 50 32",
    "sg:postcode":"5541",
    "sg:province":"Namur",
    "wof:name":"Libert Freddy & Michel",
    "wof:placetype":"venue"
},
  "geometry": {"coordinates":[4.8279438019,50.2129325867],"type":"Point"}
}