{
  "type": "Feature",
  "properties": {
    "iso:country":"BE",
    "sg:address":"Gachardstraat 63",
    "sg:city":"Elsene/ixelles",
    "sg:orig_category":"Advocaten and juridische adviseurs",
    "sg:phone":"+32 2 648 50 49",
    "sg:postcode":"1050",
    "sg:province":"Bruxelles-Capitale",
    "wof:name":"Dammans P.",
    "wof:placetype":"venue"
},
  "geometry": {"coordinates":[4.367688179,50.8260269165],"type":"Point"}
}