{
  "type": "Feature",
  "properties": {
    "addr:full":"Westmoere 16 Jabbeke (snellegem) West-Vlaanderen 8490",
    "addr:housenumber":"16",
    "addr:postcode":"8490",
    "addr:street":"Westmoere",
    "iso:country":"BE",
    "sg:address":"Westmoere 16",
    "sg:city":"Jabbeke (snellegem)",
    "sg:classifiers":[
        {
            "category":"Professional",
            "subcategory":"Computer Services",
            "type":"Services"
        }
    ],
    "sg:phone":"+32 496 52 33 00",
    "sg:postcode":"8490",
    "sg:province":"West-Vlaanderen",
    "sg:tags":[
        "-",
        "processing",
        "data"
    ],
    "wof:name":"Davitec",
    "wof:placetype":"venue"
},
  "geometry": {"coordinates":[3.1222100258,51.1670837402],"type":"Point"}
}