{
  "type": "Feature",
  "properties": {
    "addr:full":"Markt 1 Zottegem Oost-Vlaanderen 9620",
    "addr:housenumber":"1",
    "addr:postcode":"9620",
    "addr:street":"Markt",
    "iso:country":"BE",
    "sg:address":"Markt 1",
    "sg:city":"Zottegem",
    "sg:orig_category":"Offices du tourisme",
    "sg:phone":"+32 9 364 64 64",
    "sg:postcode":"9620",
    "sg:province":"Oost-Vlaanderen",
    "wof:name":"G.v.v.v. Zwalmstreek",
    "wof:placetype":"venue"
},
  "geometry": {"coordinates":[3.8104670048,50.8697891235],"type":"Point"}
}