{
  "type": "Feature",
  "properties": {
    "iso:country":"BE",
    "sg:address":"Rozenbosstraat 71",
    "sg:city":"Nieuwerkerken",
    "sg:classifiers":[
        {
            "category":"Personal",
            "subcategory":"Beauty Salon",
            "type":"Services"
        }
    ],
    "sg:phone":"+32 11 68 96 74",
    "sg:postcode":"3850",
    "sg:province":"Limburg",
    "sg:tags":[
        "lady",
        "-",
        "hairdressing"
    ],
    "wof:name":"Marina",
    "wof:placetype":"venue"
},
  "geometry": {"coordinates":[5.1992278099,50.8774871826],"type":"Point"}
}