{
  "type": "Feature",
  "properties": {
    "addr:full":"Dr. Van De Perrestraat 277 Box 17 Geel Antwerpen 2440",
    "addr:housenumber":"277 box 17",
    "addr:postcode":"2440",
    "addr:street":"Dr. Van De Perrestraat",
    "iso:country":"BE",
    "sg:address":"Dr. Van De Perrestraat 277 Box 17",
    "sg:city":"Geel",
    "sg:classifiers":[
        {
            "category":"Professional",
            "subcategory":"Accounting & Tax Preparation",
            "type":"Services"
        }
    ],
    "sg:phone":"+32 14 58 03 00",
    "sg:postcode":"2440",
    "sg:province":"Antwerpen",
    "sg:tags":[
        "accountant"
    ],
    "wof:name":"Cuypers M",
    "wof:placetype":"venue"
},
  "geometry": {"coordinates":[4.9856328964,51.1801757812],"type":"Point"}
}