{
  "type": "Feature",
  "properties": {
    "iso:country":"BE",
    "sg:address":"Egemstraat 73",
    "sg:city":"Pittem",
    "sg:orig_category":"Eleveurs and marchands de porcs",
    "sg:phone":"+32 51 46 61 92",
    "sg:postcode":"8740",
    "sg:province":"West-Vlaanderen",
    "wof:name":"Gilbert Werbrouck",
    "wof:placetype":"venue"
},
  "geometry": {"coordinates":[3.2580459118,51.0051841736],"type":"Point"}
}