{
  "type": "Feature",
  "properties": {
    "iso:country":"BE",
    "sg:address":"Fazantenstraat 9",
    "sg:city":"Opglabbeek",
    "sg:orig_category":"Ramassage and traitement des d\u00e9chets m\u00e9nagers",
    "sg:phone":"+32 89 85 59 54",
    "sg:postcode":"3660",
    "sg:province":"Limburg",
    "wof:name":"Hubert Berghs",
    "wof:placetype":"venue"
},
  "geometry": {"coordinates":[5.5444540977,51.0293884277],"type":"Point"}
}