{
  "type": "Feature",
  "properties": {
    "iso:country":"BE",
    "sg:address":"Rue Vandernoot 2",
    "sg:city":"Sint-jans-molenbeek/molenbeek-",
    "sg:orig_category":"Gestion de media publicitaires",
    "sg:phone":"+32 2 425 37 57",
    "sg:postcode":"1080",
    "sg:province":"Bruxelles-Capitale",
    "wof:name":"Belgoposter",
    "wof:placetype":"venue"
},
  "geometry": {"coordinates":[4.3341631889,50.8625335693],"type":"Point"}
}