{
  "type": "Feature",
  "properties": {
    "iso:country":"BE",
    "sg:address":"Simarstrasse 33",
    "sg:city":"Eupen",
    "sg:classifiers":[
        {
            "category":"Organizations",
            "subcategory":"Professional Association",
            "type":"Services"
        }
    ],
    "sg:phone":"+32 87 55 48 04",
    "sg:postcode":"4700",
    "sg:province":"Li\u00e8ge",
    "sg:tags":[
        "tie",
        "scarf"
    ],
    "wof:name":"Hema Distribution",
    "wof:placetype":"venue"
},
  "geometry": {"coordinates":[6.0300707817,50.6339378357],"type":"Point"}
}