{
  "type": "Feature",
  "properties": {
    "addr:full":"Avenue Des Myrtilles 25 Ukkel/uccle Bruxelles-Capitale 1180",
    "addr:housenumber":"25",
    "addr:postcode":"1180",
    "addr:street":"Avenue Des Myrtilles;/",
    "iso:country":"BE",
    "sg:address":"Avenue Des Myrtilles 25",
    "sg:city":"Ukkel/uccle",
    "sg:orig_category":"Lampes and appareils \u00e9lectriques Fab. Travaux d\u00b4installation divers",
    "sg:phone":"+32 2 241 07 78",
    "sg:postcode":"1180",
    "sg:province":"Bruxelles-Capitale",
    "wof:name":"Night & Day Signs",
    "wof:placetype":"venue"
},
  "geometry": {"coordinates":[4.3642811775,50.7783088684],"type":"Point"}
}