{
  "type": "Feature",
  "properties": {
    "iso:country":"BE",
    "sg:address":"Leysstraat 1",
    "sg:city":"Antwerpen",
    "sg:classifiers":[
        {
            "category":"Shopping",
            "subcategory":"Clothing, Apparel, & Fashions",
            "type":"Retail Goods"
        }
    ],
    "sg:phone":"+32 3 231 54 93",
    "sg:postcode":"2000",
    "sg:province":"Antwerpen",
    "sg:tags":[
        "underwear",
        "lingerie",
        "-"
    ],
    "wof:name":"Damart",
    "wof:placetype":"venue"
},
  "geometry": {"coordinates":[4.4130167961,51.2184638977],"type":"Point"}
}