{
  "type": "Feature",
  "properties": {
    "iso:country":"BE",
    "sg:address":"Wallebosstraat 10",
    "sg:city":"Gavere",
    "sg:classifiers":[
        {
            "category":"Insurance",
            "subcategory":"Life Insurance",
            "type":"Services"
        }
    ],
    "sg:phone":"+32 9 384 59 35",
    "sg:postcode":"9890",
    "sg:province":"Oost-Vlaanderen",
    "sg:tags":[
        "assurance"
    ],
    "wof:name":"Marc Verstraeten",
    "wof:placetype":"venue"
},
  "geometry": {"coordinates":[3.6401588917,50.91822052],"type":"Point"}
}