{
  "type": "Feature",
  "properties": {
    "addr:full":"Rue Pagnot 1 Tournai (gaurain-ramecroix) Hainaut 7530",
    "addr:housenumber":"1",
    "addr:postcode":"7530",
    "addr:street":"Rue Pagnot",
    "iso:country":"BE",
    "sg:address":"Rue Pagnot 1",
    "sg:city":"Tournai (gaurain-ramecroix)",
    "sg:classifiers":[
        {
            "category":"Professional",
            "subcategory":"Accounting & Tax Preparation",
            "type":"Services"
        }
    ],
    "sg:phone":"+32 69 54 61 40",
    "sg:postcode":"7530",
    "sg:province":"Hainaut",
    "sg:tags":[
        "bookkeeper"
    ],
    "wof:name":"Cuignet J-m",
    "wof:placetype":"venue"
},
  "geometry": {"coordinates":[3.472673893,50.595500946],"type":"Point"}
}