{
  "type": "Feature",
  "properties": {
    "addr:full":"Broeckborre 1 Zoersel Vlaams-Brabant 1500",
    "addr:housenumber":"1",
    "addr:postcode":"1500",
    "addr:street":"Broeckborre",
    "iso:country":"BE",
    "sg:address":"Broeckborre 1",
    "sg:city":"Zoersel",
    "sg:classifiers":[
        {
            "category":"Arena",
            "subcategory":"Sports Club",
            "type":"Entertainment"
        }
    ],
    "sg:phone":"+32 2 360 07 72",
    "sg:postcode":"1500",
    "sg:province":"Vlaams-Brabant",
    "sg:tags":[
        "de"
    ],
    "wof:name":"Mudukwan Academy Brussels",
    "wof:placetype":"venue"
},
  "geometry": {"coordinates":[4.2332601547,50.737953186],"type":"Point"}
}