{
  "type": "Feature",
  "properties": {
    "addr:full":"Ringlaan 1 Kuurne West-Vlaanderen 8520",
    "addr:housenumber":"1",
    "addr:postcode":"8520",
    "addr:street":"Ringlaan",
    "iso:country":"BE",
    "sg:address":"Ringlaan 1",
    "sg:city":"Kuurne",
    "sg:orig_category":"Herstelling leer and schoeisel Herstellingswinkels voor diverse persoonlijke and huishoudartikelen",
    "sg:phone":"+32 56 35 60 56",
    "sg:postcode":"8520",
    "sg:province":"West-Vlaanderen",
    "wof:name":"Mister Minit",
    "wof:placetype":"venue"
},
  "geometry": {"coordinates":[3.2716701031,50.844493866],"type":"Point"}
}