{
  "type": "Feature",
  "properties": {
    "addr:full":"Chauss\u00c9e De Mons Anderlues Hainaut 6150",
    "addr:postcode":"6150",
    "addr:street":"Chausse\u0301E De Mons;Hainaut",
    "iso:country":"BE",
    "sg:address":"Chauss\u00c9e De Mons",
    "sg:city":"Anderlues",
    "sg:orig_category":"Huisdierenkwekers",
    "sg:phone":"+32 64 33 04 51",
    "sg:postcode":"6150",
    "sg:province":"Hainaut",
    "wof:name":"Bergers Allemands De La Chtrolidas",
    "wof:placetype":"venue"
},
  "geometry": {"coordinates":[4.2281751633,50.4076957703],"type":"Point"}
}