{
  "type": "Feature",
  "properties": {
    "iso:country":"BE",
    "sg:address":"Rue De La Vall\u00c9e 55",
    "sg:city":"Chatelet",
    "sg:orig_category":"Pain, p\u00e2tisseries and confiseries",
    "sg:phone":"+32 71 38 15 24",
    "sg:postcode":"6200",
    "sg:province":"Hainaut",
    "wof:name":"P\u00c2tisserie Hustin",
    "wof:placetype":"venue"
},
  "geometry": {"coordinates":[4.5236740112,50.4041366577],"type":"Point"}
}