{
  "type": "Feature",
  "properties": {
    "iso:country":"BE",
    "sg:address":"7",
    "sg:city":"Groenmolenstraat 3570 Alken",
    "sg:classifiers":[
        {
            "category":"Wholesale",
            "subcategory":"Meat",
            "type":"Manufacturing & Wholesale Goods"
        }
    ],
    "sg:phone":"+32 11 31 31 88",
    "sg:postcode":"7",
    "sg:tags":[
        "food",
        "cooked",
        "product",
        "related"
    ],
    "wof:name":"Schepers Vleesbedrijf Nv",
    "wof:placetype":"venue"
},
  "geometry": {"coordinates":[5.2987627983,50.8843574524],"type":"Point"}
}