{
  "type": "Feature",
  "properties": {
    "addr:full":"Handbalstraat 2 Gent Oost-Vlaanderen 9000",
    "addr:housenumber":"2",
    "addr:postcode":"9000",
    "addr:street":"Handbalstraat;Oost-Vlaanderen",
    "iso:country":"BE",
    "sg:address":"Handbalstraat 2",
    "sg:city":"Gent",
    "sg:orig_category":"Studios photographiques",
    "sg:phone":"+32 9 220 54 91",
    "sg:postcode":"9000",
    "sg:province":"Oost-Vlaanderen",
    "wof:name":"Photography Sven Everaert",
    "wof:placetype":"venue"
},
  "geometry": {"coordinates":[3.7096450329,51.0408477783],"type":"Point"}
}