{
  "type": "Feature",
  "properties": {
    "iso:country":"BE",
    "sg:address":"Singel 5 B3",
    "sg:city":"Kontich",
    "sg:orig_category":"Editeurs de livres",
    "sg:phone":"+32 3 457 07 10",
    "sg:postcode":"2550",
    "sg:province":"Antwerpen",
    "wof:name":"B.m.c. Publishing",
    "wof:placetype":"venue"
},
  "geometry": {"coordinates":[4.4727702141,51.1256446838],"type":"Point"}
}