{
  "type": "Feature",
  "properties": {
    "addr:full":"Steenstraat 11 Erpe-mere Oost-Vlaanderen 9420",
    "addr:housenumber":"11",
    "addr:postcode":"9420",
    "addr:street":"Steenstraat",
    "iso:country":"BE",
    "sg:address":"Steenstraat 11",
    "sg:city":"Erpe-mere",
    "sg:orig_category":"V\u00eatements pour Dames. V\u00eatements pour Hommes",
    "sg:phone":"+32 53 83 19 09",
    "sg:postcode":"9420",
    "sg:province":"Oost-Vlaanderen",
    "wof:name":"Alain Provost",
    "wof:placetype":"venue"
},
  "geometry": {"coordinates":[3.9688370228,50.9219093323],"type":"Point"}
}