{
  "type": "Feature",
  "properties": {
    "addr:full":"Hoogstraat 117 Genk Limburg 3600",
    "addr:housenumber":"117",
    "addr:postcode":"3600",
    "addr:street":"Hoogstraat",
    "iso:country":"BE",
    "sg:address":"Hoogstraat 117",
    "sg:city":"Genk",
    "sg:classifiers":[
        {
            "category":"Health Services",
            "subcategory":"Dentist",
            "type":"Services"
        }
    ],
    "sg:phone":"+32 89 35 79 07",
    "sg:postcode":"3600",
    "sg:province":"Limburg",
    "wof:name":"Gyselinck M",
    "wof:placetype":"venue"
},
  "geometry": {"coordinates":[5.5076680183,50.9569511414],"type":"Point"}
}