{
  "type": "Feature",
  "properties": {
    "addr:full":"Rue De L'eglise 26 Aubange Luxembourg 6791",
    "addr:housenumber":"26",
    "addr:postcode":"6791",
    "addr:street":"Rue De L'Eglise",
    "iso:country":"BE",
    "sg:address":"Rue De L'eglise 26",
    "sg:city":"Aubange",
    "sg:classifiers":[
        {
            "category":"Professional",
            "subcategory":"Accounting & Tax Preparation",
            "type":"Services"
        }
    ],
    "sg:phone":"+32 63 37 89 92",
    "sg:postcode":"6791",
    "sg:province":"Luxembourg",
    "sg:tags":[
        "accountant"
    ],
    "wof:name":"Andre Brosius",
    "wof:placetype":"venue"
},
  "geometry": {"coordinates":[5.8343157768,49.5660514832],"type":"Point"}
}