{
  "type": "Feature",
  "properties": {
    "iso:country":"BE",
    "sg:address":"Baron R. De Vironlaan 44",
    "sg:city":"Dilbeek",
    "sg:orig_category":"Persagentschappen",
    "sg:phone":"+32 2 466 46 81",
    "sg:postcode":"1700",
    "sg:province":"Vlaams-Brabant",
    "wof:name":"Madeleine Sergooris",
    "wof:placetype":"venue"
},
  "geometry": {"coordinates":[4.2684698105,50.8472824097],"type":"Point"}
}