{
  "type": "Feature",
  "properties": {
    "iso:country":"BE",
    "sg:address":"Herseltsesteenweg 45",
    "sg:city":"Aarschot",
    "sg:classifiers":[
        {
            "category":"Autos & Motor Vehicles",
            "subcategory":"Fuel & Gas Station",
            "type":"Retail Goods"
        }
    ],
    "sg:phone":"+32 16 56 91 98",
    "sg:postcode":"3200",
    "sg:province":"Vlaams-Brabant",
    "sg:tags":[
        "stations-service",
        "carburants"
    ],
    "wof:name":"Shell",
    "wof:placetype":"venue"
},
  "geometry": {"coordinates":[4.8380851746,50.9938392639],"type":"Point"}
}