{
  "type": "Feature",
  "properties": {
    "addr:full":"Rue Fran\u00c7ois Vandamme 104 Ham-sur-heure-nalinnes Hainaut 6120",
    "addr:housenumber":"104",
    "addr:postcode":"6120",
    "addr:street":"Rue Franc\u0327Ois Vandamme;Hainaut",
    "iso:country":"BE",
    "sg:address":"Rue Fran\u00c7ois Vandamme 104",
    "sg:city":"Ham-sur-heure-nalinnes",
    "sg:orig_category":"Loodgieterij, verwarming and sanitaire installaties",
    "sg:phone":"+32 71 21 96 31",
    "sg:postcode":"6120",
    "sg:province":"Hainaut",
    "wof:name":"Jean-pierre Moreau",
    "wof:placetype":"venue"
},
  "geometry": {"coordinates":[4.4193220139,50.3530578613],"type":"Point"}
}