{
  "type": "Feature",
  "properties": {
    "iso:country":"BE",
    "sg:address":"Eernegemweg 154",
    "sg:city":"Jabbeke",
    "sg:orig_category":"Groententeelt",
    "sg:phone":"+32 50 81 18 39",
    "sg:postcode":"8490",
    "sg:province":"West-Vlaanderen",
    "wof:name":"Rutoma",
    "wof:placetype":"venue"
},
  "geometry": {"coordinates":[3.095140934,51.1611862183],"type":"Point"}
}