{
  "type": "Feature",
  "properties": {
    "addr:full":"Gelemanstraat 10 Kortenaken Vlaams-Brabant 3470",
    "addr:housenumber":"10",
    "addr:postcode":"3470",
    "addr:street":"Gelemanstraat",
    "iso:country":"BE",
    "sg:address":"Gelemanstraat 10",
    "sg:city":"Kortenaken",
    "sg:orig_category":"SMEEDWERK, METAALBEWERKING AND POEDERMETALLURGIE",
    "sg:phone":"+32 11 58 86 94",
    "sg:postcode":"3470",
    "sg:province":"Vlaams-Brabant",
    "wof:name":"Nolmans",
    "wof:placetype":"venue"
},
  "geometry": {"coordinates":[5.0808157921,50.9093360901],"type":"Point"}
}