{
  "type": "Feature",
  "properties": {
    "iso:country":"BE",
    "sg:address":"Brouwerijstraat 48",
    "sg:city":"Drogenbos/drogenbos",
    "sg:orig_category":"Plaatsen van vloer- and muurbekleding Schilders",
    "sg:phone":"+32 2 377 98 58",
    "sg:postcode":"1620",
    "sg:province":"Vlaams-Brabant",
    "wof:name":"Marc Teghem",
    "wof:placetype":"venue"
},
  "geometry": {"coordinates":[4.3184337616,50.787727356],"type":"Point"}
}