{
  "type": "Feature",
  "properties": {
    "iso:country":"BE",
    "sg:address":"Route Nationale 4 47",
    "sg:city":"Nassogne (bande)",
    "sg:classifiers":[
        {
            "category":"Retail",
            "subcategory":"Auto Repair",
            "type":"Services"
        }
    ],
    "sg:phone":"+32 84 34 44 24",
    "sg:postcode":"6951",
    "sg:province":"Luxembourg",
    "sg:tags":[
        "garage"
    ],
    "wof:name":"Maquel Josy Sprl",
    "wof:placetype":"venue"
},
  "geometry": {"coordinates":[5.4151701927,50.1667518616],"type":"Point"}
}