{
  "type": "Feature",
  "properties": {
    "iso:country":"BE",
    "sg:address":"Rappoortlaan 24",
    "sg:city":"Putte",
    "sg:orig_category":"M\u00e9decins and sp\u00e9cialistes",
    "sg:phone":"+32 15 75 61 06",
    "sg:postcode":"2580",
    "sg:province":"Antwerpen",
    "wof:name":"Paul Van Goolen",
    "wof:placetype":"venue"
},
  "geometry": {"coordinates":[4.6255931854,51.0596656799],"type":"Point"}
}