{
  "type": "Feature",
  "properties": {
    "addr:full":"Val Des Seigneurs 141b2 Sint-pieters-woluwe/woluwe-sai Bruxelles-Capitale 1150",
    "addr:housenumber":"141b2",
    "addr:postcode":"1150",
    "addr:street":"Val Des Seigneurs",
    "iso:country":"BE",
    "sg:address":"Val Des Seigneurs 141b2",
    "sg:city":"Sint-pieters-woluwe/woluwe-sai",
    "sg:classifiers":[
        {
            "category":"Insurance",
            "subcategory":"Insurance Agent",
            "type":"Services"
        }
    ],
    "sg:phone":"+32 2 772 90 91",
    "sg:postcode":"1150",
    "sg:province":"Bruxelles-Capitale",
    "sg:tags":[
        "verzekeringsmakelaars",
        "expert"
    ],
    "wof:name":"Biagioni-mathou",
    "wof:placetype":"venue"
},
  "geometry": {"coordinates":[4.4575099945,50.8429336548],"type":"Point"}
}