{
  "type": "Feature",
  "properties": {
    "iso:country":"BE",
    "sg:address":"Mellestraat 196",
    "sg:city":"Kortrijk (heule)",
    "sg:classifiers":[
        {
            "category":"Manufacturing",
            "subcategory":"Textiles",
            "type":"Manufacturing & Wholesale Goods"
        }
    ],
    "sg:phone":"+32 56 37 00 36",
    "sg:postcode":"8501",
    "sg:province":"West-Vlaanderen",
    "sg:tags":[
        "spinning",
        "weaving",
        "mill"
    ],
    "wof:name":"Verbatex Nv",
    "wof:placetype":"venue"
},
  "geometry": {"coordinates":[3.227807045,50.8525848389],"type":"Point"}
}