{
  "type": "Feature",
  "properties": {
    "iso:country":"BE",
    "sg:address":"Rodestraat 25",
    "sg:city":"Diest (schaffen)",
    "sg:classifiers":[
        {
            "category":"Professional",
            "subcategory":"Art Services",
            "type":"Services"
        }
    ],
    "sg:phone":"+32 13 33 76 85",
    "sg:postcode":"3290",
    "sg:province":"Vlaams-Brabant",
    "sg:tags":[
        "children's",
        "animation"
    ],
    "wof:name":"Clown Bweno",
    "wof:placetype":"venue"
},
  "geometry": {"coordinates":[5.0554509163,51.0082168579],"type":"Point"}
}