{
  "type": "Feature",
  "properties": {
    "addr:full":"Stenen-kruisstraat 76 Sint-gillis/saint-gilles Bruxelles-Capitale 1060",
    "addr:housenumber":"76",
    "addr:postcode":"1060",
    "addr:street":"Stenen-Kruisstraat",
    "iso:country":"BE",
    "sg:address":"Stenen-kruisstraat 76",
    "sg:city":"Sint-gillis/saint-gilles",
    "sg:orig_category":"Loodgieterij, verwarming and sanitaire installaties",
    "sg:phone":"+32 2 537 32 59",
    "sg:postcode":"1060",
    "sg:province":"Bruxelles-Capitale",
    "wof:name":"Francis Snoecx",
    "wof:placetype":"venue"
},
  "geometry": {"coordinates":[4.3517317772,50.8289680481],"type":"Point"}
}