{
  "type": "Feature",
  "properties": {
    "addr:full":"Braambergstraat 5 Brugge West-Vlaanderen 8000",
    "addr:housenumber":"5",
    "addr:postcode":"8000",
    "addr:street":"Braambergstraat",
    "iso:country":"BE",
    "sg:address":"Braambergstraat 5",
    "sg:city":"Brugge",
    "sg:orig_category":"Epiceries. Equipement photographique",
    "sg:phone":"+32 50 33 33 69",
    "sg:postcode":"8000",
    "sg:province":"West-Vlaanderen",
    "wof:name":"Dorine Missault",
    "wof:placetype":"venue"
},
  "geometry": {"coordinates":[3.2280879021,51.2075805664],"type":"Point"}
}