{
  "type": "Feature",
  "properties": {
    "iso:country":"BE",
    "sg:address":"Kasteeldreef 97",
    "sg:city":"Beveren",
    "sg:orig_category":"Kapsalons",
    "sg:phone":"+32 3 775 82 75",
    "sg:postcode":"9120",
    "sg:province":"Oost-Vlaanderen",
    "wof:name":"Maria",
    "wof:placetype":"venue"
},
  "geometry": {"coordinates":[4.2551708221,51.2178726196],"type":"Point"}
}