{
  "type": "Feature",
  "properties": {
    "addr:full":"Rue De Li\u00c8ge 292 Kelmis/la Calamine Li\u00e8ge 4720",
    "addr:housenumber":"292",
    "addr:postcode":"4720",
    "addr:street":"Rue De Lie\u0300Ge",
    "iso:country":"BE",
    "sg:address":"Rue De Li\u00c8ge 292",
    "sg:city":"Kelmis/la Calamine",
    "sg:orig_category":"V\u00e9hicules automobiles",
    "sg:phone":"+32 87 65 82 85",
    "sg:postcode":"4720",
    "sg:province":"Li\u00e8ge",
    "wof:name":"Autorog",
    "wof:placetype":"venue"
},
  "geometry": {"coordinates":[6.0147500038,50.731098175],"type":"Point"}
}