{
  "type": "Feature",
  "properties": {
    "iso:country":"BE",
    "sg:address":"Rue De La Hate 9",
    "sg:city":"Corbion",
    "sg:classifiers":[
        {
            "category":"Transit Center",
            "subcategory":"Freight",
            "type":"Transportation"
        }
    ],
    "sg:phone":"+32 61 46 61 02",
    "sg:postcode":"6838",
    "sg:province":"Luxembourg",
    "sg:tags":[
        "hazardous",
        "material"
    ],
    "wof:name":"Tbt Transports S.a.",
    "wof:placetype":"venue"
},
  "geometry": {"coordinates":[5.011469841,49.796333313],"type":"Point"}
}