{
  "type": "Feature",
  "properties": {
    "addr:full":"Rue L\u00c9opold 46 Li\u00c8ge Li\u00e8ge 4000",
    "addr:housenumber":"46",
    "addr:postcode":"4000",
    "addr:street":"Rue Le\u0301Opold",
    "iso:country":"BE",
    "sg:address":"Rue L\u00c9opold 46",
    "sg:city":"Li\u00c8ge",
    "sg:orig_category":"Pain, p\u00e2tisseries and confiseries",
    "sg:phone":"+32 4 223 39 18",
    "sg:postcode":"4000",
    "sg:province":"Li\u00e8ge",
    "wof:name":"La Gourmandise",
    "wof:placetype":"venue"
},
  "geometry": {"coordinates":[5.5771970749,50.6439933777],"type":"Point"}
}