{
  "type": "Feature",
  "properties": {
    "iso:country":"BE",
    "sg:address":"Staatsbaan 151",
    "sg:city":"Bekkevoort",
    "sg:classifiers":[
        {
            "category":"Fast Food",
            "type":"Food & Drink"
        }
    ],
    "sg:phone":"+32 13 32 25 94",
    "sg:postcode":"3460",
    "sg:province":"Vlaams-Brabant",
    "sg:tags":[
        "meeneem",
        "restaurant"
    ],
    "wof:name":"Frituur Tropical",
    "wof:placetype":"venue"
},
  "geometry": {"coordinates":[4.9818239212,50.9467735291],"type":"Point"}
}