{
  "type": "Feature",
  "properties": {
    "iso:country":"BE",
    "sg:address":"Vichteplaats 32",
    "sg:city":"Anzegem",
    "sg:orig_category":"Boucheries",
    "sg:phone":"+32 56 77 70 40",
    "sg:postcode":"8570",
    "sg:province":"West-Vlaanderen",
    "wof:name":"Patriek Cappelle",
    "wof:placetype":"venue"
},
  "geometry": {"coordinates":[3.4037110806,50.8358802795],"type":"Point"}
}