{
  "type": "Feature",
  "properties": {
    "iso:country":"BE",
    "sg:address":"Place Communale 3b4",
    "sg:city":"Jemeppe-sur-sambre",
    "sg:orig_category":"Caf\u00e9s Rookartikelen",
    "sg:phone":"+32 71 78 79 79",
    "sg:postcode":"5190",
    "sg:province":"Namur",
    "wof:name":"Caf\u00c9 Au Bureau",
    "wof:placetype":"venue"
},
  "geometry": {"coordinates":[4.66852808,50.4657821655],"type":"Point"}
}