{
  "type": "Feature",
  "properties": {
    "addr:full":"Assesteenweg 236 Ternat (sint-katherina-lombeek) Vlaams-Brabant 1742",
    "addr:housenumber":"236",
    "addr:postcode":"1742",
    "addr:street":"Assesteenweg",
    "iso:country":"BE",
    "sg:address":"Assesteenweg 236",
    "sg:city":"Ternat (sint-katherina-lombeek)",
    "sg:classifiers":[
        {
            "category":"Home & Garden",
            "subcategory":"Kitchen Supply",
            "type":"Retail Goods"
        }
    ],
    "sg:phone":"+32 2 582 53 03",
    "sg:postcode":"1742",
    "sg:province":"Vlaams-Brabant",
    "sg:tags":[
        "installation"
    ],
    "wof:name":"Keuken & Design Bvba",
    "wof:placetype":"venue"
},
  "geometry": {"coordinates":[4.1620998383,50.8723297119],"type":"Point"}
}