{
  "type": "Feature",
  "properties": {
    "iso:country":"BE",
    "sg:address":"Hansez 34",
    "sg:city":"Olne",
    "sg:orig_category":"Eleveurs de bovins",
    "sg:phone":"+32 87 26 83 50",
    "sg:postcode":"4877",
    "sg:province":"Li\u00e8ge",
    "wof:name":"Franz Delrez",
    "wof:placetype":"venue"
},
  "geometry": {"coordinates":[5.7238330841,50.5783615112],"type":"Point"}
}