{
  "type": "Feature",
  "properties": {
    "iso:country":"BE",
    "sg:address":"Rue De La Posterie 19",
    "sg:city":"Gembloux-sur-orneau (gembloux)",
    "sg:orig_category":"Non-Classified Establishments",
    "sg:phone":"+32 81 62 60 60",
    "sg:postcode":"5030",
    "sg:province":"Namur",
    "wof:name":"Megadis Sa",
    "wof:placetype":"venue"
},
  "geometry": {"coordinates":[4.7069568634,50.576133728],"type":"Point"}
}