{
  "type": "Feature",
  "properties": {
    "addr:full":"Rue Des Muriers 5bb Jemeppe-sur-sambre Namur 5190",
    "addr:housenumber":"5bb",
    "addr:postcode":"5190",
    "addr:street":"Rue Des Muriers",
    "iso:country":"BE",
    "sg:address":"Rue Des Muriers 5bb",
    "sg:city":"Jemeppe-sur-sambre",
    "sg:orig_category":"Ramassage and traitement des d\u00e9chets m\u00e9nagers",
    "sg:phone":"+32 71 78 43 15",
    "sg:postcode":"5190",
    "sg:province":"Namur",
    "wof:name":"P.p.h.",
    "wof:placetype":"venue"
},
  "geometry": {"coordinates":[4.7086181641,50.467830658],"type":"Point"}
}