{
  "type": "Feature",
  "properties": {
    "iso:country":"BE",
    "sg:address":"Boulevard Aristide Briand 44",
    "sg:city":"Bruxelles (anderlecht)",
    "sg:classifiers":[
        {
            "category":"Manufacturing",
            "subcategory":"Tools & Machinery",
            "type":"Manufacturing & Wholesale Goods"
        }
    ],
    "sg:phone":"+32 2 521 30 55",
    "sg:postcode":"1070",
    "sg:province":"Bruxelles-Capitale",
    "sg:tags":[
        "-"
    ],
    "wof:name":"Landresse Ets Sprl",
    "wof:placetype":"venue"
},
  "geometry": {"coordinates":[4.3011159897,50.8284912109],"type":"Point"}
}