{
  "type": "Feature",
  "properties": {
    "iso:country":"BE",
    "sg:address":"Sint-trudoplein 10",
    "sg:city":"Houthalen-helchteren",
    "sg:orig_category":"Notarissen",
    "sg:phone":"+32 11 60 88 40",
    "sg:postcode":"3530",
    "sg:province":"Limburg",
    "wof:name":"Guido Bax",
    "wof:placetype":"venue"
},
  "geometry": {"coordinates":[5.3719201088,51.0310020447],"type":"Point"}
}