{
  "type": "Feature",
  "properties": {
    "addr:full":"Florimont Leirensstraat 44 Wetteren Oost-Vlaanderen 9230",
    "addr:housenumber":"44",
    "addr:postcode":"9230",
    "addr:street":"Florimont Leirensstraat",
    "iso:country":"BE",
    "sg:address":"Florimont Leirensstraat 44",
    "sg:city":"Wetteren",
    "sg:orig_category":"Schoenen",
    "sg:phone":"+32 9 369 04 41",
    "sg:postcode":"9230",
    "sg:province":"Oost-Vlaanderen",
    "wof:name":"Shoes In The Box",
    "wof:placetype":"venue"
},
  "geometry": {"coordinates":[3.8838610649,51.0051040649],"type":"Point"}
}