{
  "type": "Feature",
  "properties": {
    "addr:full":"Rue G\u00e9n\u00e9ral Leman 22 Seneffe Hainaut 7180",
    "addr:housenumber":"22",
    "addr:postcode":"7180",
    "addr:street":"Rue Ge\u0301Ne\u0301Ral Leman",
    "iso:country":"BE",
    "sg:address":"Rue G\u00e9n\u00e9ral Leman 22",
    "sg:city":"Seneffe",
    "sg:classifiers":[
        {
            "category":"Shopping",
            "subcategory":"Shoes",
            "type":"Retail Goods"
        }
    ],
    "sg:phone":"+32 64 55 77 42",
    "sg:postcode":"7180",
    "sg:province":"Hainaut",
    "sg:tags":[
        "slipper",
        "-"
    ],
    "wof:name":"Barra D",
    "wof:placetype":"venue"
},
  "geometry": {"coordinates":[4.2567811012,50.5286750793],"type":"Point"}
}