{
  "type": "Feature",
  "properties": {
    "iso:country":"BE",
    "sg:address":"Hoeksken 16",
    "sg:city":"Sint-lievens-houtem",
    "sg:orig_category":"Services fun\u00e9raires",
    "sg:phone":"+32 53 62 33 75",
    "sg:postcode":"9520",
    "sg:province":"Oost-Vlaanderen",
    "wof:name":"Andre Pluym",
    "wof:placetype":"venue"
},
  "geometry": {"coordinates":[3.8510410786,50.9209098816],"type":"Point"}
}