{
  "type": "Feature",
  "properties": {
    "addr:full":"Sint-truidensesteenweg 217 Linter (orsmaal-gussenhoven) Vlaams-Brabant 3350",
    "addr:housenumber":"217",
    "addr:postcode":"3350",
    "addr:street":"Sint-Truidensesteenweg",
    "iso:country":"BE",
    "sg:address":"Sint-truidensesteenweg 217",
    "sg:city":"Linter (orsmaal-gussenhoven)",
    "sg:classifiers":[
        {
            "category":"Shopping",
            "subcategory":"Antiques",
            "type":"Retail Goods"
        }
    ],
    "sg:phone":"+32 11 78 13 10",
    "sg:postcode":"3350",
    "sg:province":"Vlaams-Brabant",
    "wof:name":"Verbeelen J",
    "wof:placetype":"venue"
},
  "geometry": {"coordinates":[5.0664710999,50.8039588928],"type":"Point"}
}