{
  "type": "Feature",
  "properties": {
    "iso:country":"BE",
    "sg:address":"Oppemstraat 61",
    "sg:city":"Tervuren",
    "sg:orig_category":"Gestion des d\u00e9charges and sites d\u00e9finitifs de stockage",
    "sg:phone":"+32 2 767 15 16",
    "sg:postcode":"3080",
    "sg:province":"Vlaams-Brabant",
    "wof:name":"Containerpark Tervuren",
    "wof:placetype":"venue"
},
  "geometry": {"coordinates":[4.5072741508,50.8280258179],"type":"Point"}
}