{
  "type": "Feature",
  "properties": {
    "addr:full":"Dorpsstraat 68 Wuustwezel Antwerpen 2990",
    "addr:housenumber":"68",
    "addr:postcode":"2990",
    "addr:street":"Dorpsstraat",
    "iso:country":"BE",
    "sg:address":"Dorpsstraat 68",
    "sg:city":"Wuustwezel",
    "sg:classifiers":[
        {
            "category":"Food & Beverages",
            "subcategory":"Fruits & Vegetables",
            "type":"Retail Goods"
        }
    ],
    "sg:phone":"+32 3 669 62 31",
    "sg:postcode":"2990",
    "sg:province":"Antwerpen",
    "sg:tags":[
        "l\u00e9gumes"
    ],
    "wof:name":"Pascal Delcroix",
    "wof:placetype":"venue"
},
  "geometry": {"coordinates":[4.5970492363,51.3882484436],"type":"Point"}
}