{
  "type": "Feature",
  "properties": {
    "addr:full":"Elzenstraat 11 Torhout West-Vlaanderen 8820",
    "addr:housenumber":"11",
    "addr:postcode":"8820",
    "addr:street":"Elzenstraat",
    "iso:country":"BE",
    "sg:address":"Elzenstraat 11",
    "sg:city":"Torhout",
    "sg:orig_category":"Varkenskwekers",
    "sg:phone":"+32 51 72 27 60",
    "sg:postcode":"8820",
    "sg:province":"West-Vlaanderen",
    "wof:name":"Marcel Wydooghe",
    "wof:placetype":"venue"
},
  "geometry": {"coordinates":[3.0730109215,51.0200309753],"type":"Point"}
}