{
  "type": "Feature",
  "properties": {
    "addr:full":"Mechelsesteenweg 40 Kampenhout Vlaams-Brabant 1910",
    "addr:housenumber":"40",
    "addr:postcode":"1910",
    "addr:street":"Mechelsesteenweg",
    "iso:country":"BE",
    "sg:address":"Mechelsesteenweg 40",
    "sg:city":"Kampenhout",
    "sg:classifiers":[
        {
            "category":"Fast Food",
            "type":"Food & Drink"
        }
    ],
    "sg:phone":"+32 16 60 40 22",
    "sg:postcode":"1910",
    "sg:province":"Vlaams-Brabant",
    "sg:tags":[
        "\u00c0",
        "restaurants",
        "emporter",
        "restaurant"
    ],
    "wof:name":"Mcdonald's",
    "wof:placetype":"venue"
},
  "geometry": {"coordinates":[4.5871310234,50.9597206116],"type":"Point"}
}