{
  "type": "Feature",
  "properties": {
    "iso:country":"BE",
    "sg:address":"Tereken 82",
    "sg:city":"Sint-niklaas",
    "sg:orig_category":"Cr\u00e9meries",
    "sg:phone":"+32 3 777 97 75",
    "sg:postcode":"9100",
    "sg:province":"Oost-Vlaanderen",
    "wof:name":"Huis Knapp-knapp",
    "wof:placetype":"venue"
},
  "geometry": {"coordinates":[4.1484818459,51.1524887085],"type":"Point"}
}