{
  "type": "Feature",
  "properties": {
    "addr:full":"Rue De Bossi\u00e8re 46 Gembloux-sur-orneau (mazy) Namur 5032",
    "addr:housenumber":"46",
    "addr:postcode":"5032",
    "addr:street":"Rue De Bossie\u0300Re;Mazy",
    "iso:country":"BE",
    "sg:address":"Rue De Bossi\u00e8re 46",
    "sg:city":"Gembloux-sur-orneau (mazy)",
    "sg:classifiers":[
        {
            "category":"Home & Garden",
            "subcategory":"Carpets & Floor Coverings",
            "type":"Retail Goods"
        }
    ],
    "sg:phone":"+32 81 63 33 57",
    "sg:postcode":"5032",
    "sg:province":"Namur",
    "sg:tags":[
        "tile"
    ],
    "wof:name":"Bock",
    "wof:placetype":"venue"
},
  "geometry": {"coordinates":[4.6785697937,50.5147209167],"type":"Point"}
}