{
  "type": "Feature",
  "properties": {
    "iso:country":"BE",
    "sg:address":"Bosstraat 46",
    "sg:city":"Ternat (sint-katherina-lombeek)",
    "sg:classifiers":[
        {
            "category":"Shopping",
            "subcategory":"Computers & Home Electronics",
            "type":"Retail Goods"
        }
    ],
    "sg:phone":"+32 2 582 86 04",
    "sg:postcode":"1742",
    "sg:province":"Vlaams-Brabant",
    "sg:tags":[
        "spare",
        "part",
        "processing",
        "-",
        "data"
    ],
    "wof:name":"Business Computers & Consultancy",
    "wof:placetype":"venue"
},
  "geometry": {"coordinates":[4.1322522163,50.8710327148],"type":"Point"}
}