{
  "type": "Feature",
  "properties": {
    "addr:full":"Rue De La Lib\u00e9ration 46 Braine-le-ch\u00e2teau Brabant Wallon 1440",
    "addr:housenumber":"46",
    "addr:postcode":"1440",
    "addr:street":"Rue De La Libe\u0301Ration",
    "iso:country":"BE",
    "sg:address":"Rue De La Lib\u00e9ration 46",
    "sg:city":"Braine-le-ch\u00e2teau",
    "sg:classifiers":[
        {
            "category":"Professional",
            "subcategory":"Testing Lab",
            "type":"Services"
        }
    ],
    "sg:phone":"+32 2 366 90 65",
    "sg:postcode":"1440",
    "sg:province":"Brabant Wallon",
    "sg:tags":[
        "chemist"
    ],
    "wof:name":"Guillaume G",
    "wof:placetype":"venue"
},
  "geometry": {"coordinates":[4.2713241577,50.6824455261],"type":"Point"}
}