{
  "type": "Feature",
  "properties": {
    "addr:full":"Begoniastraat 36 Nazareth Oost-Vlaanderen 9810",
    "addr:housenumber":"36",
    "addr:postcode":"9810",
    "addr:street":"Begoniastraat",
    "iso:country":"BE",
    "sg:address":"Begoniastraat 36",
    "sg:city":"Nazareth",
    "sg:orig_category":"V\u00e9hicules automobiles. Entretien and r\u00e9parations de voitures",
    "sg:phone":"+32 9 385 82 11",
    "sg:postcode":"9810",
    "sg:province":"Oost-Vlaanderen",
    "wof:name":"Garage Martens",
    "wof:placetype":"venue"
},
  "geometry": {"coordinates":[3.6571900845,50.9777336121],"type":"Point"}
}