{
  "type": "Feature",
  "properties": {
    "iso:country":"BE",
    "sg:address":"Brugsesteenweg 340",
    "sg:city":"Gent",
    "sg:orig_category":"Agences immobili\u00e8res",
    "sg:phone":"+32 9 236 17 28",
    "sg:postcode":"9000",
    "sg:province":"Oost-Vlaanderen",
    "wof:name":"Bureau Jorimmo",
    "wof:placetype":"venue"
},
  "geometry": {"coordinates":[3.6862919331,51.0679855347],"type":"Point"}
}