{
  "type": "Feature",
  "properties": {
    "addr:full":"Rue Des Ardennes 185 Durbuy Luxembourg 6941",
    "addr:housenumber":"185",
    "addr:postcode":"6941",
    "addr:street":"Rue Des Ardennes",
    "iso:country":"BE",
    "sg:address":"Rue Des Ardennes 185",
    "sg:city":"Durbuy",
    "sg:orig_category":"Installation de menuiserie en bois and plastique",
    "sg:phone":"+32 86 21 14 67",
    "sg:postcode":"6941",
    "sg:province":"Luxembourg",
    "wof:name":"Rene Ponthier",
    "wof:placetype":"venue"
},
  "geometry": {"coordinates":[5.5354399681,50.3694381714],"type":"Point"}
}