{
  "type": "Feature",
  "properties": {
    "addr:full":"Pardostraat 16 Damme West-Vlaanderen 8340",
    "addr:housenumber":"16",
    "addr:postcode":"8340",
    "addr:street":"Pardostraat",
    "iso:country":"BE",
    "sg:address":"Pardostraat 16",
    "sg:city":"Damme",
    "sg:orig_category":"Installatie van houten of kunststof schrijnwerk",
    "sg:phone":"+32 50 35 37 74",
    "sg:postcode":"8340",
    "sg:province":"West-Vlaanderen",
    "wof:name":"Orego",
    "wof:placetype":"venue"
},
  "geometry": {"coordinates":[3.3167510033,51.2042312622],"type":"Point"}
}