{
  "type": "Feature",
  "properties": {
    "iso:country":"BE",
    "sg:address":"Rue Ortmans-hauzeur 13",
    "sg:city":"Verviers",
    "sg:orig_category":"Agences immobili\u00e8res",
    "sg:phone":"+32 87 33 88 04",
    "sg:postcode":"4800",
    "sg:province":"Li\u00e8ge",
    "wof:name":"Immobili\u00c8re Assimo",
    "wof:placetype":"venue"
},
  "geometry": {"coordinates":[5.8655180931,50.5933151245],"type":"Point"}
}