{
  "type": "Feature",
  "properties": {
    "addr:full":"Rue Lambert Marlet 40 Blegny Li\u00e8ge 4670",
    "addr:housenumber":"40",
    "addr:postcode":"4670",
    "addr:street":"Rue Lambert Marlet",
    "iso:country":"BE",
    "sg:address":"Rue Lambert Marlet 40",
    "sg:city":"Blegny",
    "sg:classifiers":[
        {
            "category":"Cafe",
            "type":"Food & Drink"
        }
    ],
    "sg:phone":"+32 4 387 59 43",
    "sg:postcode":"4670",
    "sg:province":"Li\u00e8ge",
    "sg:tags":[
        "caf\u00e9s"
    ],
    "wof:name":"Caf\u00c9 Chez Maria",
    "wof:placetype":"venue"
},
  "geometry": {"coordinates":[5.724919796,50.6725769043],"type":"Point"}
}