{
  "type": "Feature",
  "properties": {
    "addr:full":"Kortrijkstraat 412 Wevelgem West-Vlaanderen 8560",
    "addr:housenumber":"412",
    "addr:postcode":"8560",
    "addr:street":"Kortrijkstraat",
    "iso:country":"BE",
    "sg:address":"Kortrijkstraat 412",
    "sg:city":"Wevelgem",
    "sg:orig_category":"Boucheries",
    "sg:phone":"+32 56 42 78 89",
    "sg:postcode":"8560",
    "sg:province":"West-Vlaanderen",
    "wof:name":"Fa. Filet Pur",
    "wof:placetype":"venue"
},
  "geometry": {"coordinates":[3.2141830921,50.8174362183],"type":"Point"}
}