{
  "type": "Feature",
  "properties": {
    "addr:full":"Graaf De Ferrarisgaarde 15 Sint-pieters-woluwe/woluwe-saint-pierre Bruxelles-Capitale 1150",
    "addr:housenumber":"15",
    "addr:postcode":"1150",
    "addr:street":"Graaf De Ferrarisgaarde;/",
    "iso:country":"BE",
    "sg:address":"Graaf De Ferrarisgaarde 15",
    "sg:city":"Sint-pieters-woluwe/woluwe-saint-pierre",
    "sg:orig_category":"Boekenuitgeverijen",
    "sg:phone":"+32 2 762 29 72",
    "sg:postcode":"1150",
    "sg:province":"Bruxelles-Capitale",
    "wof:name":"Imotep",
    "wof:placetype":"venue"
},
  "geometry": {"coordinates":[4.4477190971,50.83776474],"type":"Point"}
}