{
  "type": "Feature",
  "properties": {
    "iso:country":"BE",
    "sg:address":"Rue De Marchienne 70",
    "sg:city":"Charleroi",
    "sg:orig_category":"Advocaten and juridische adviseurs",
    "sg:phone":"+32 71 43 04 82",
    "sg:postcode":"6032",
    "sg:province":"Hainaut",
    "wof:name":"Marie-fran\u00c7oise Charlier",
    "wof:placetype":"venue"
},
  "geometry": {"coordinates":[4.4048418999,50.3940200806],"type":"Point"}
}