{
  "type": "Feature",
  "properties": {
    "iso:country":"BE",
    "sg:address":"Morinnestraat 18",
    "sg:city":"Kortrijk",
    "sg:classifiers":[
        {
            "category":"Building & Trades",
            "subcategory":"Construction",
            "type":"Services"
        }
    ],
    "sg:phone":"+32 56 22 32 69",
    "sg:postcode":"8500",
    "sg:province":"West-Vlaanderen",
    "sg:tags":[
        "textile",
        "machine"
    ],
    "wof:name":"Dusix Nv",
    "wof:placetype":"venue"
},
  "geometry": {"coordinates":[3.3006749153,50.8159484863],"type":"Point"}
}