{
  "type": "Feature",
  "properties": {
    "addr:full":"Nijverheidstraat 5a Nieuwpoort West-Vlaanderen 8620",
    "addr:housenumber":"5a",
    "addr:postcode":"8620",
    "addr:street":"Nijverheidstraat",
    "iso:country":"BE",
    "sg:address":"Nijverheidstraat 5a",
    "sg:city":"Nieuwpoort",
    "sg:classifiers":[
        {
            "category":"Shopping",
            "subcategory":"Party Supplies",
            "type":"Retail Goods"
        }
    ],
    "sg:phone":"+32 58 23 59 99",
    "sg:postcode":"8620",
    "sg:province":"West-Vlaanderen",
    "sg:tags":[
        "ice-cream",
        "-",
        "parlour"
    ],
    "wof:name":"Kumex Bvba",
    "wof:placetype":"venue"
},
  "geometry": {"coordinates":[2.75842309,51.1299514771],"type":"Point"}
}