{
  "type": "Feature",
  "properties": {
    "iso:country":"BE",
    "sg:address":"Klinkersbos 12",
    "sg:city":"Retie",
    "sg:orig_category":"Eleveurs d'animaux domestiques. Animaux domestiques and accessoires",
    "sg:phone":"+32 14 37 86 60",
    "sg:postcode":"2470",
    "sg:province":"Antwerpen",
    "wof:name":"Antonius Luijten",
    "wof:placetype":"venue"
},
  "geometry": {"coordinates":[5.1205759048,51.2771987915],"type":"Point"}
}