{
  "type": "Feature",
  "properties": {
    "iso:country":"BE",
    "sg:address":"Isabellalei 3a",
    "sg:city":"Antwerpen",
    "sg:classifiers":[
        {
            "category":"Real Estate",
            "subcategory":"Architect",
            "type":"Services"
        }
    ],
    "sg:phone":"+32 3 281 10 68",
    "sg:postcode":"2018",
    "sg:province":"Antwerpen",
    "wof:name":"Schelkens C",
    "wof:placetype":"venue"
},
  "geometry": {"coordinates":[4.4151649475,51.2067451477],"type":"Point"}
}