{
  "type": "Feature",
  "properties": {
    "iso:country":"BE",
    "sg:address":"Appeldijkstraat 2",
    "sg:city":"Bornem",
    "sg:orig_category":"RESTAURANTS: CAF\u00c9S",
    "sg:phone":"+32 3 889 94 49",
    "sg:postcode":"2880",
    "sg:province":"Antwerpen",
    "wof:name":"Oud Gemeentehuis",
    "wof:placetype":"venue"
},
  "geometry": {"coordinates":[4.1925139427,51.0996055603],"type":"Point"}
}