{
  "type": "Feature",
  "properties": {
    "iso:country":"BE",
    "sg:address":"Rue De Huccorgne 12",
    "sg:city":"Schilde",
    "sg:orig_category":"Installation de menuiserie en bois and plastique",
    "sg:phone":"+32 85 71 16 47",
    "sg:postcode":"4217",
    "sg:province":"Li\u00e8ge",
    "wof:name":"Bragard Pascal",
    "wof:placetype":"venue"
},
  "geometry": {"coordinates":[5.0985798836,50.5489196777],"type":"Point"}
}