{
  "type": "Feature",
  "properties": {
    "iso:country":"BE",
    "sg:address":"Kortrijksestraat 302",
    "sg:city":"Kortrijk",
    "sg:orig_category":"Boucheries",
    "sg:phone":"+32 56 37 03 80",
    "sg:postcode":"8501",
    "sg:province":"West-Vlaanderen",
    "wof:name":"Wim Comeine",
    "wof:placetype":"venue"
},
  "geometry": {"coordinates":[3.2476799488,50.835521698],"type":"Point"}
}