{
  "type": "Feature",
  "properties": {
    "iso:country":"BE",
    "sg:address":"Texasstraat 9",
    "sg:city":"Vorst",
    "sg:orig_category":"Viessmann. Plomberie, chauffage and installations sanitaires. Quincailleries",
    "sg:phone":"+32 2 345 24 43",
    "sg:postcode":"1190",
    "sg:province":"Bruxelles-Capitale",
    "wof:name":"Fosset Bruno",
    "wof:placetype":"venue"
},
  "geometry": {"coordinates":[4.3198189735,50.8130226135],"type":"Point"}
}