{
  "type": "Feature",
  "properties": {
    "iso:country":"BE",
    "sg:address":"Deinsesteenweg 270",
    "sg:city":"Tielt (aarsele)",
    "sg:classifiers":[
        {
            "category":"Home & Garden",
            "subcategory":"Home Furnishings",
            "type":"Retail Goods"
        }
    ],
    "sg:phone":"+32 51 63 64 92",
    "sg:postcode":"8700",
    "sg:province":"West-Vlaanderen",
    "sg:tags":[
        "interior",
        "decoration"
    ],
    "wof:name":"Kuna-inrichtingen",
    "wof:placetype":"venue"
},
  "geometry": {"coordinates":[3.3780350685,50.9952201843],"type":"Point"}
}