{
  "type": "Feature",
  "properties": {
    "addr:full":"Rue Du Cul Du Qu'vau 12-14 Colfontaine (p\u00e2turages) Hainaut 7340",
    "addr:housenumber":"12-14",
    "addr:postcode":"7340",
    "addr:street":"Rue Du Cul Du Qu'Vau",
    "iso:country":"BE",
    "sg:address":"Rue Du Cul Du Qu'vau 12-14",
    "sg:city":"Colfontaine (p\u00e2turages)",
    "sg:classifiers":[
        {
            "category":"Home & Garden",
            "subcategory":"Building Materials",
            "type":"Retail Goods"
        }
    ],
    "sg:phone":"+32 477 63 52 19",
    "sg:postcode":"7340",
    "sg:province":"Hainaut",
    "sg:tags":[
        "veranda"
    ],
    "wof:name":"Deco-verres",
    "wof:placetype":"venue"
},
  "geometry": {"coordinates":[3.8489329815,50.401512146],"type":"Point"}
}