{
  "type": "Feature",
  "properties": {
    "addr:full":"Parklaan 103 Aalst Oost-Vlaanderen 9300",
    "addr:housenumber":"103",
    "addr:postcode":"9300",
    "addr:street":"Parklaan",
    "iso:country":"BE",
    "sg:address":"Parklaan 103",
    "sg:city":"Aalst",
    "sg:orig_category":"Onderdelen and accessoires voor auto's",
    "sg:phone":"+32 53 77 78 09",
    "sg:postcode":"9300",
    "sg:province":"Oost-Vlaanderen",
    "wof:name":"Car Music Factory",
    "wof:placetype":"venue"
},
  "geometry": {"coordinates":[4.0402131081,50.9299736023],"type":"Point"}
}