{
  "type": "Feature",
  "properties": {
    "iso:country":"BE",
    "sg:address":"Autolei 145-151",
    "sg:city":"Wommelgem",
    "sg:orig_category":"Entretien and r\u00e9parations de voitures. Pi\u00e8ces and accessoires de v\u00e9hicules automobiles Gr",
    "sg:phone":"+32 3 321 48 12",
    "sg:postcode":"2160",
    "sg:province":"Antwerpen",
    "wof:name":"Cat Cams",
    "wof:placetype":"venue"
},
  "geometry": {"coordinates":[4.4888701439,51.2063598633],"type":"Point"}
}