{
  "type": "Feature",
  "properties": {
    "addr:full":"Waregemstraat 96 Deerlijk West-Vlaanderen 8540",
    "addr:housenumber":"96",
    "addr:postcode":"8540",
    "addr:street":"Waregemstraat",
    "iso:country":"BE",
    "sg:address":"Waregemstraat 96",
    "sg:city":"Deerlijk",
    "sg:classifiers":[
        {
            "category":"Food & Beverages",
            "subcategory":"Fruits & Vegetables",
            "type":"Retail Goods"
        }
    ],
    "sg:phone":"+32 56 70 12 85",
    "sg:postcode":"8540",
    "sg:province":"West-Vlaanderen",
    "sg:tags":[
        "l\u00e9gumes"
    ],
    "wof:name":"Cedric Hellyn",
    "wof:placetype":"venue"
},
  "geometry": {"coordinates":[3.3657140732,50.8555374146],"type":"Point"}
}