{
  "type": "Feature",
  "properties": {
    "addr:full":"Schijfwerpersstraat 145 Antwerpen Antwerpen 2020",
    "addr:housenumber":"145",
    "addr:postcode":"2020",
    "addr:street":"Schijfwerpersstraat",
    "iso:country":"BE",
    "sg:address":"Schijfwerpersstraat 145",
    "sg:city":"Antwerpen",
    "sg:orig_category":"Activit\u00e9s d\u00b4action sociale sans h\u00e9bergement",
    "sg:phone":"+32 3 828 69 00",
    "sg:postcode":"2020",
    "sg:province":"Antwerpen",
    "wof:name":"Hiv-vereniging Vlaanderen De Witte Raven",
    "wof:placetype":"venue"
},
  "geometry": {"coordinates":[4.3834819794,51.1818275452],"type":"Point"}
}