{
  "type": "Feature",
  "properties": {
    "iso:country":"BE",
    "sg:address":"Hopstraat 62",
    "sg:city":"Ternat (sint-katherina-lombeek)",
    "sg:classifiers":[
        {
            "category":"Real Estate",
            "subcategory":"Architect",
            "type":"Services"
        }
    ],
    "sg:phone":"+32 53 66 44 56",
    "sg:postcode":"1742",
    "sg:province":"Vlaams-Brabant",
    "wof:name":"Roeland F",
    "wof:placetype":"venue"
},
  "geometry": {"coordinates":[4.1077599525,50.8821029663],"type":"Point"}
}