{
  "type": "Feature",
  "properties": {
    "iso:country":"BE",
    "sg:address":"Grens 16a",
    "sg:city":"Poppel",
    "sg:classifiers":[
        {
            "category":"Professional",
            "type":"Services"
        }
    ],
    "sg:phone":"+32 14 65 54 12",
    "sg:postcode":"2382",
    "sg:province":"Antwerpen",
    "sg:tags":[
        "transport",
        "road"
    ],
    "wof:name":"Belgische Vervoeronderneming Constant Heeren Nv",
    "wof:placetype":"venue"
},
  "geometry": {"coordinates":[5.0483999252,51.4706192017],"type":"Point"}
}