{
  "type": "Feature",
  "properties": {
    "addr:full":"Rue Antoine Br\u00c9art 89 Sint-gillis/saint-gilles Bruxelles-Capitale 1060",
    "addr:housenumber":"89",
    "addr:postcode":"1060",
    "addr:street":"Rue Antoine Bre\u0301Art",
    "iso:country":"BE",
    "sg:address":"Rue Antoine Br\u00c9art 89",
    "sg:city":"Sint-gillis/saint-gilles",
    "sg:orig_category":"Jardinage",
    "sg:phone":"+32 2 538 20 23",
    "sg:postcode":"1060",
    "sg:province":"Bruxelles-Capitale",
    "wof:name":"Jacques Thiriart",
    "wof:placetype":"venue"
},
  "geometry": {"coordinates":[4.3460359573,50.8234977722],"type":"Point"}
}