{
  "type": "Feature",
  "properties": {
    "addr:full":"Piewittedreef 2 Wingene West-Vlaanderen 8750",
    "addr:housenumber":"2",
    "addr:postcode":"8750",
    "addr:street":"Piewittedreef",
    "iso:country":"BE",
    "sg:address":"Piewittedreef 2",
    "sg:city":"Wingene",
    "sg:classifiers":[
        {
            "category":"Farming",
            "subcategory":"Farm & Veterinary Services",
            "type":"Manufacturing & Wholesale Goods"
        }
    ],
    "sg:phone":"+32 50 27 75 83",
    "sg:postcode":"8750",
    "sg:province":"West-Vlaanderen",
    "sg:tags":[
        "agricultural",
        "contractor"
    ],
    "wof:name":"Derycke E",
    "wof:placetype":"venue"
},
  "geometry": {"coordinates":[3.2850899696,51.0946388245],"type":"Point"}
}