{
  "type": "Feature",
  "properties": {
    "iso:country":"BE",
    "sg:address":"Blvd.du Cuivre Et Du Zinc 21",
    "sg:city":"Grivegnee",
    "sg:orig_category":"Huisdieren and benodigdheden Royal Canin",
    "sg:phone":"+32 4 349 15 70",
    "sg:postcode":"4030",
    "sg:province":"Li\u00e8ge",
    "wof:name":"Tom & Co.",
    "wof:placetype":"venue"
},
  "geometry": {"coordinates":[5.5929489136,50.6234359741],"type":"Point"}
}