{
  "type": "Feature",
  "properties": {
    "iso:country":"BE",
    "sg:address":"Rue De La Fuss\u00c9e 40",
    "sg:city":"Brussel/bruxelles",
    "sg:orig_category":"Mat\u00e9riel de T\u00e9l\u00e9communication",
    "sg:phone":"+32 70 22 23 32",
    "sg:postcode":"1130",
    "sg:province":"Bruxelles-Capitale",
    "wof:name":"Ericsson",
    "wof:placetype":"venue"
},
  "geometry": {"coordinates":[4.4161977768,50.8774642944],"type":"Point"}
}