{
  "type": "Feature",
  "properties": {
    "addr:full":"Torhoutsesteenweg 469 Oostende West-Vlaanderen 8400",
    "addr:housenumber":"469",
    "addr:postcode":"8400",
    "addr:street":"Torhoutsesteenweg",
    "iso:country":"BE",
    "sg:address":"Torhoutsesteenweg 469",
    "sg:city":"Oostende",
    "sg:orig_category":"Autombile concessionaires",
    "sg:phone":"+32 59 50 93 84",
    "sg:postcode":"8400",
    "sg:province":"West-Vlaanderen",
    "wof:name":"De Brauwer H",
    "wof:placetype":"venue"
},
  "geometry": {"coordinates":[2.9052810669,51.2103500366],"type":"Point"}
}