{
  "type": "Feature",
  "properties": {
    "iso:country":"BE",
    "sg:address":"Tieltsestraat 4a",
    "sg:city":"Ardooie (koolskamp)",
    "sg:classifiers":[
        {
            "category":"Real Estate",
            "subcategory":"Architect",
            "type":"Services"
        }
    ],
    "sg:phone":"+32 51 74 64 17",
    "sg:postcode":"8851",
    "sg:province":"West-Vlaanderen",
    "wof:name":"Bossuyt Jan",
    "wof:placetype":"venue"
},
  "geometry": {"coordinates":[3.2124640942,51.0016822815],"type":"Point"}
}