{
  "type": "Feature",
  "properties": {
    "addr:full":"Chauss\u00c9e Saint-pierre 221 Etterbeek Bruxelles-Capitale 1040",
    "addr:housenumber":"221",
    "addr:postcode":"1040",
    "addr:street":"Chausse\u0301E Saint-Pierre",
    "iso:country":"BE",
    "sg:address":"Chauss\u00c9e Saint-pierre 221",
    "sg:city":"Etterbeek",
    "sg:orig_category":"Electrom\u00e9nager, t\u00e9l\u00e9visions and radios. Installation \u00e9lectrique r\u00e9sidentielle",
    "sg:phone":"+32 2 736 60 89",
    "sg:postcode":"1040",
    "sg:province":"Bruxelles-Capitale",
    "wof:name":"Vincent Balfroid",
    "wof:placetype":"venue"
},
  "geometry": {"coordinates":[4.3908991814,50.836555481],"type":"Point"}
}