{
  "type": "Feature",
  "properties": {
    "addr:full":"Noorderlaan 660-haven 500 Antwerpen Antwerpen 2030",
    "addr:housenumber":"660-haven 500",
    "addr:postcode":"2030",
    "addr:street":"Noorderlaan",
    "iso:country":"BE",
    "sg:address":"Noorderlaan 660-haven 500",
    "sg:city":"Antwerpen",
    "sg:classifiers":[
        {
            "category":"Wholesale",
            "subcategory":"Motor Vehicles",
            "type":"Manufacturing & Wholesale Goods"
        }
    ],
    "sg:phone":"+32 3 820 32 11",
    "sg:postcode":"2030",
    "sg:province":"Antwerpen",
    "sg:tags":[
        "tube",
        "inner",
        "tyre"
    ],
    "wof:name":"Goodyear Dunlop Belgium Nv",
    "wof:placetype":"venue"
},
  "geometry": {"coordinates":[4.3886761665,51.157207489],"type":"Point"}
}