{
  "type": "Feature",
  "properties": {
    "addr:full":"All\u00c9e Du Long-f\u00c9tu 1 Nivelles Brabant Wallon 1400",
    "addr:housenumber":"1",
    "addr:postcode":"1400",
    "addr:street":"Alle\u0301E Du Long-Fe\u0301Tu",
    "iso:country":"BE",
    "sg:address":"All\u00c9e Du Long-f\u00c9tu 1",
    "sg:city":"Nivelles",
    "sg:orig_category":"Boekhouders",
    "sg:phone":"+32 67 21 78 12",
    "sg:postcode":"1400",
    "sg:province":"Brabant Wallon",
    "wof:name":"Paul Dujardin",
    "wof:placetype":"venue"
},
  "geometry": {"coordinates":[4.3417520523,50.6043014526],"type":"Point"}
}