{
  "type": "Feature",
  "properties": {
    "iso:country":"BE",
    "sg:address":"Tongersesteenweg 123",
    "sg:city":"Sint-truiden",
    "sg:orig_category":"Banques and organismes de cr\u00e9dit",
    "sg:phone":"+32 11 68 54 31",
    "sg:postcode":"3800",
    "sg:province":"Limburg",
    "wof:name":"Landbouwkrediet",
    "wof:placetype":"venue"
},
  "geometry": {"coordinates":[5.2007541656,50.8110084534],"type":"Point"}
}