{
  "type": "Feature",
  "properties": {
    "iso:country":"BE",
    "sg:address":"Rue Saint-jean 1",
    "sg:city":"Arlon",
    "sg:orig_category":"Speelgoed",
    "sg:phone":"+32 63 22 61 55",
    "sg:postcode":"6700",
    "sg:province":"Luxembourg",
    "wof:name":"Let's Play",
    "wof:placetype":"venue"
},
  "geometry": {"coordinates":[5.8172807693,49.6826972961],"type":"Point"}
}