{
  "type": "Feature",
  "properties": {
    "addr:full":"J.b. Devlemincklaan 142 Zaventem Vlaams-Brabant 1930",
    "addr:housenumber":"142",
    "addr:postcode":"1930",
    "addr:street":"J.B. Devlemincklaan",
    "iso:country":"BE",
    "sg:address":"J.b. Devlemincklaan 142",
    "sg:city":"Zaventem",
    "sg:orig_category":"Ordinateurs and \u00e9quipement informatique. Jeux and jouets",
    "sg:phone":"+32 2 720 93 80",
    "sg:postcode":"1930",
    "sg:province":"Vlaams-Brabant",
    "wof:name":"J P Electronics",
    "wof:placetype":"venue"
},
  "geometry": {"coordinates":[4.4766058922,50.8721542358],"type":"Point"}
}