{
  "type": "Feature",
  "properties": {
    "addr:full":"Rue De La Bourse 151 Saint-georges-sur-meuse Li\u00e8ge 4470",
    "addr:housenumber":"151",
    "addr:postcode":"saint-georges-sur-meuse;4470",
    "addr:street":"Rue De La Bourse",
    "iso:country":"BE",
    "sg:address":"Rue De La Bourse 151",
    "sg:city":"Saint-georges-sur-meuse",
    "sg:orig_category":"Schilders Verlichting and huishoudartikelen",
    "sg:phone":"+32 4 275 50 14",
    "sg:postcode":"4470",
    "sg:province":"Li\u00e8ge",
    "wof:name":"David Collin",
    "wof:placetype":"venue"
},
  "geometry": {"coordinates":[5.3457651138,50.5739250183],"type":"Point"}
}