{
  "type": "Feature",
  "properties": {
    "iso:country":"BE",
    "sg:address":"Dirk Martensstraat 21",
    "sg:city":"Sint-andries",
    "sg:classifiers":[
        {
            "category":"Shopping",
            "subcategory":"Clothing, Apparel, & Fashions",
            "type":"Retail Goods"
        }
    ],
    "sg:phone":"+32 50 45 49 10",
    "sg:postcode":"8200",
    "sg:province":"West-Vlaanderen",
    "sg:tags":[
        "textile",
        "clothing",
        "clothes"
    ],
    "wof:name":"Vemtex Nv",
    "wof:placetype":"venue"
},
  "geometry": {"coordinates":[3.1921260357,51.2116508484],"type":"Point"}
}