{
  "type": "Feature",
  "properties": {
    "iso:country":"BE",
    "sg:address":"Rue Du Fays 34",
    "sg:city":"Fosses-la-ville (aisemont)",
    "sg:classifiers":[
        {
            "category":"Building & Trades",
            "subcategory":"Pest Control",
            "type":"Services"
        }
    ],
    "sg:phone":"+32 71 71 17 24",
    "sg:postcode":"5070",
    "sg:province":"Namur",
    "sg:tags":[
        "painting",
        "contractor"
    ],
    "wof:name":"De Boose Fr\u00e8res Sprl",
    "wof:placetype":"venue"
},
  "geometry": {"coordinates":[4.6598501205,50.4052352905],"type":"Point"}
}