{
  "type": "Feature",
  "properties": {
    "addr:full":"Place Du March\u00e9 33 Herve (battice) Li\u00e8ge 4651",
    "addr:housenumber":"33",
    "addr:postcode":"4651",
    "addr:street":"Place Du Marche\u0301",
    "iso:country":"BE",
    "sg:address":"Place Du March\u00e9 33",
    "sg:city":"Herve (battice)",
    "sg:classifiers":[
        {
            "category":"Bakery",
            "type":"Food & Drink"
        }
    ],
    "sg:phone":"+32 87 67 87 72",
    "sg:postcode":"4651",
    "sg:province":"Li\u00e8ge",
    "sg:tags":[
        "confectioner",
        "baker"
    ],
    "wof:name":"Sacr\u00e9 Sa",
    "wof:placetype":"venue"
},
  "geometry": {"coordinates":[5.8210268021,50.647567749],"type":"Point"}
}