{
  "type": "Feature",
  "properties": {
    "addr:full":"Markt 15 Bilzen Limburg 3740",
    "addr:housenumber":"15",
    "addr:postcode":"3740",
    "addr:street":"Markt",
    "iso:country":"BE",
    "sg:address":"Markt 15",
    "sg:city":"Bilzen",
    "sg:classifiers":[
        {
            "category":"Banks & Credit Unions",
            "subcategory":"Bank",
            "type":"Services"
        }
    ],
    "sg:phone":"+32 11 41 10 09",
    "sg:postcode":"3740",
    "sg:province":"Limburg",
    "wof:name":"Banque Bruxelles Lambert Sa",
    "wof:placetype":"venue"
},
  "geometry": {"coordinates":[5.5133070946,50.8699760437],"type":"Point"}
}