{
  "type": "Feature",
  "properties": {
    "addr:full":"Rue Haute 103 Herve Li\u00e8ge 4650",
    "addr:housenumber":"103",
    "addr:postcode":"4650",
    "addr:street":"Rue Haute",
    "iso:country":"BE",
    "sg:address":"Rue Haute 103",
    "sg:city":"Herve",
    "sg:classifiers":[
        {
            "category":"Personal",
            "subcategory":"Beauty Salon",
            "type":"Services"
        }
    ],
    "sg:phone":"+32 87 66 02 27",
    "sg:postcode":"4650",
    "sg:province":"Li\u00e8ge",
    "sg:tags":[
        "de",
        "coiffure"
    ],
    "wof:name":"Fernand Lejeune",
    "wof:placetype":"venue"
},
  "geometry": {"coordinates":[5.7956547737,50.6437644958],"type":"Point"}
}