{
  "type": "Feature",
  "properties": {
    "iso:country":"BE",
    "sg:address":"Place Leopold 16",
    "sg:city":"Chimay",
    "sg:classifiers":[
        {
            "category":"Government",
            "subcategory":"Fire Station",
            "type":"Public Place"
        }
    ],
    "sg:phone":"+32 60 21 53 02",
    "sg:postcode":"6460",
    "sg:province":"Hainaut",
    "sg:tags":[
        "packard",
        "nec",
        "bell"
    ],
    "wof:name":"Adam`s Computer Chimay",
    "wof:placetype":"venue"
},
  "geometry": {"coordinates":[4.3170919418,50.0472221375],"type":"Point"}
}