{
  "type": "Feature",
  "properties": {
    "addr:full":"Lochtens Malle Antwerpen 2390",
    "addr:postcode":"2390",
    "addr:street":"Lochtens",
    "iso:country":"BE",
    "sg:address":"Lochtens",
    "sg:city":"Malle",
    "sg:orig_category":"Mat\u00e9riel de contr\u00f4le des processus industriels Fab",
    "sg:phone":"+32 3 312 45 54",
    "sg:postcode":"2390",
    "sg:province":"Antwerpen",
    "wof:name":"Verstappen B",
    "wof:placetype":"venue"
},
  "geometry": {"coordinates":[4.7324090004,51.3099327087],"type":"Point"}
}