{
  "type": "Feature",
  "properties": {
    "addr:full":"Fasbinderstraat 3 Tremelo (baal) Vlaams-Brabant 3128",
    "addr:housenumber":"3",
    "addr:postcode":"3128",
    "addr:street":"Fasbinderstraat",
    "iso:country":"BE",
    "sg:address":"Fasbinderstraat 3",
    "sg:city":"Tremelo (baal)",
    "sg:classifiers":[
        {
            "category":"Recreation",
            "subcategory":"Amusement Park",
            "type":"Entertainment"
        }
    ],
    "sg:phone":"+32 496 15 19 86",
    "sg:postcode":"3128",
    "sg:province":"Vlaams-Brabant",
    "sg:tags":[
        "attraction",
        "-",
        "sale",
        "fair",
        "hiring"
    ],
    "wof:name":"Easy Fun",
    "wof:placetype":"venue"
},
  "geometry": {"coordinates":[4.7501358986,50.9974250793],"type":"Point"}
}