{
  "type": "Feature",
  "properties": {
    "addr:full":"Kwakkelhoekstraat 89 Nieuwkerken-waas Oost-Vlaanderen 9100",
    "addr:housenumber":"89",
    "addr:postcode":"9100",
    "addr:street":"Kwakkelhoekstraat;Oost-Vlaanderen",
    "iso:country":"BE",
    "sg:address":"Kwakkelhoekstraat 89",
    "sg:city":"Nieuwkerken-waas",
    "sg:classifiers":[
        {
            "category":"Manufacturing",
            "subcategory":"Metals",
            "type":"Manufacturing & Wholesale Goods"
        }
    ],
    "sg:phone":"+32 3 777 07 28",
    "sg:postcode":"9100",
    "sg:province":"Oost-Vlaanderen",
    "sg:tags":[
        "metallurgy",
        "steel",
        "metalworking"
    ],
    "wof:name":"Sadu-abrasives Bvba",
    "wof:placetype":"venue"
},
  "geometry": {"coordinates":[4.1861438751,51.1927337646],"type":"Point"}
}