{
  "type": "Feature",
  "properties": {
    "addr:full":"Rue Ferme Marchand 8 Ittre Brabant Wallon 1460",
    "addr:housenumber":"8;1460",
    "addr:street":"Rue Ferme Marchand",
    "iso:country":"BE",
    "sg:address":"Rue Ferme Marchand 8",
    "sg:city":"Ittre",
    "sg:orig_category":"Herstellingen and onderhoud van auto's Voertuigen",
    "sg:phone":"+32 67 64 68 74",
    "sg:postcode":"1460",
    "sg:province":"Brabant Wallon",
    "wof:name":"Garage Van Hemelen",
    "wof:placetype":"venue"
},
  "geometry": {"coordinates":[4.2010221481,50.6523857117],"type":"Point"}
}