{
  "type": "Feature",
  "properties": {
    "iso:country":"BE",
    "sg:address":"Rue De La Follmillen 14",
    "sg:city":"Arlon",
    "sg:orig_category":"Rundveehouders",
    "sg:phone":"+32 63 21 68 59",
    "sg:postcode":"6700",
    "sg:province":"Luxembourg",
    "wof:name":"Jean Tines",
    "wof:placetype":"venue"
},
  "geometry": {"coordinates":[5.7936820984,49.69713974],"type":"Point"}
}