{
  "type": "Feature",
  "properties": {
    "iso:country":"BE",
    "sg:address":"Oudburgweg 29",
    "sg:city":"Sint-martens-latem",
    "sg:classifiers":[
        {
            "category":"Shopping",
            "subcategory":"Florist",
            "type":"Retail Goods"
        }
    ],
    "sg:phone":"+32 9 282 52 29",
    "sg:postcode":"9830",
    "sg:province":"Oost-Vlaanderen",
    "wof:name":"Steyaert F",
    "wof:placetype":"venue"
},
  "geometry": {"coordinates":[3.6471409798,51.0185165405],"type":"Point"}
}