{
  "type": "Feature",
  "properties": {
    "addr:full":"Teleweidestraat 1 Pepingen Vlaams-Brabant 1670",
    "addr:housenumber":"1",
    "addr:postcode":"1670",
    "addr:street":"Teleweidestraat",
    "iso:country":"BE",
    "sg:address":"Teleweidestraat 1",
    "sg:city":"Pepingen",
    "sg:orig_category":"Eleveurs de bovins",
    "sg:phone":"+32 2 356 21 80",
    "sg:postcode":"1670",
    "sg:province":"Vlaams-Brabant",
    "wof:name":"Andre Leroy",
    "wof:placetype":"venue"
},
  "geometry": {"coordinates":[4.1342411041,50.7427482605],"type":"Point"}
}