{
  "type": "Feature",
  "properties": {
    "addr:full":"Rue Andr\u00e9 Masquelier 10 Mons Hainaut 7000",
    "addr:housenumber":"10",
    "addr:postcode":"7000",
    "addr:street":"Rue Andre\u0301 Masquelier;Hainaut",
    "iso:country":"BE",
    "sg:address":"Rue Andr\u00e9 Masquelier 10",
    "sg:city":"Mons",
    "sg:classifiers":[
        {
            "category":"Bars & Pubs",
            "type":"Food & Drink"
        }
    ],
    "sg:phone":"+32 65 31 67 73",
    "sg:postcode":"7000",
    "sg:province":"Hainaut",
    "wof:name":"Jardin (le)",
    "wof:placetype":"venue"
},
  "geometry": {"coordinates":[3.9436020851,50.4515380859],"type":"Point"}
}