{
  "type": "Feature",
  "properties": {
    "addr:full":"Kleempstraat 61 Laarne Oost-Vlaanderen 9270",
    "addr:housenumber":"61",
    "addr:postcode":"9270",
    "addr:street":"Kleempstraat",
    "iso:country":"BE",
    "sg:address":"Kleempstraat 61",
    "sg:city":"Laarne",
    "sg:orig_category":"Leisure articles",
    "sg:phone":"+32 9 366 34 19",
    "sg:postcode":"9270",
    "sg:province":"Oost-Vlaanderen",
    "wof:name":"Hobby-atelier De Berenzolder",
    "wof:placetype":"venue"
},
  "geometry": {"coordinates":[3.8592219353,51.0285301208],"type":"Point"}
}