{
  "type": "Feature",
  "properties": {
    "addr:full":"Rue D'h\u00c9rinnes 18 Enghien Hainaut 7850",
    "addr:housenumber":"18",
    "addr:postcode":"7850",
    "addr:street":"Rue D'He \u0301Rinnes",
    "iso:country":"BE",
    "sg:address":"Rue D'h\u00c9rinnes 18",
    "sg:city":"Enghien",
    "sg:orig_category":"V\u00eatements pour Hommes. V\u00eatements pour Dames",
    "sg:phone":"+32 2 395 42 52",
    "sg:postcode":"7850",
    "sg:province":"Hainaut",
    "wof:name":"Alessi",
    "wof:placetype":"venue"
},
  "geometry": {"coordinates":[4.0389709473,50.6938972473],"type":"Point"}
}