{
  "type": "Feature",
  "properties": {
    "iso:country":"BE",
    "sg:address":"Grote Markt 55",
    "sg:city":"Sint-truiden",
    "sg:classifiers":[
        {
            "category":"Shopping",
            "subcategory":"Optician",
            "type":"Retail Goods"
        }
    ],
    "sg:phone":"+32 11 68 29 03",
    "sg:postcode":"3800",
    "sg:province":"Limburg",
    "sg:tags":[
        "-"
    ],
    "wof:name":"Mignon J",
    "wof:placetype":"venue"
},
  "geometry": {"coordinates":[5.1858620644,50.81590271],"type":"Point"}
}