{
  "type": "Feature",
  "properties": {
    "iso:country":"BE",
    "sg:address":"Heiwijkstraat 65",
    "sg:city":"Merelbeke",
    "sg:classifiers":[
        {
            "category":"Professional",
            "subcategory":"Computer Services",
            "type":"Services"
        }
    ],
    "sg:phone":"+32 9 230 83 59",
    "sg:postcode":"9820",
    "sg:province":"Oost-Vlaanderen",
    "sg:tags":[
        "webdesign",
        "-",
        "internet"
    ],
    "wof:name":"E-quies",
    "wof:placetype":"venue"
},
  "geometry": {"coordinates":[3.7671511173,51.0084838867],"type":"Point"}
}