{
  "type": "Feature",
  "properties": {
    "addr:full":"Kerkstraat 12 Hamont-achel Limburg 3930",
    "addr:housenumber":"12",
    "addr:postcode":"3930",
    "addr:street":"Kerkstraat",
    "iso:country":"BE",
    "sg:address":"Kerkstraat 12",
    "sg:city":"Hamont-achel",
    "sg:classifiers":[
        {
            "category":"Insurance",
            "subcategory":"Insurance Agent",
            "type":"Services"
        }
    ],
    "sg:phone":"+32 11 44 68 30",
    "sg:postcode":"3930",
    "sg:province":"Limburg",
    "sg:tags":[
        "verzekeringsmakelaars",
        "expert"
    ],
    "wof:name":"Dvv",
    "wof:placetype":"venue"
},
  "geometry": {"coordinates":[5.5450549126,51.2511863708],"type":"Point"}
}