{
  "type": "Feature",
  "properties": {
    "iso:country":"BE",
    "sg:address":"Heultjedorp 6",
    "sg:city":"Westerlo",
    "sg:classifiers":[
        {
            "category":"Bars & Pubs",
            "type":"Food & Drink"
        }
    ],
    "sg:phone":"+32 16 69 42 70",
    "sg:postcode":"2260",
    "sg:province":"Antwerpen",
    "wof:name":"Kafeeke ('t)",
    "wof:placetype":"venue"
},
  "geometry": {"coordinates":[4.8401679993,51.08984375],"type":"Point"}
}