{
  "type": "Feature",
  "properties": {
    "addr:full":"Brugsesteenweg 66 Pittem West-Vlaanderen 8740",
    "addr:housenumber":"66",
    "addr:postcode":"8740",
    "addr:street":"Brugsesteenweg",
    "iso:country":"BE",
    "sg:address":"Brugsesteenweg 66",
    "sg:city":"Pittem",
    "sg:classifiers":[
        {
            "category":"Sports & Exercise",
            "subcategory":"Skate Park",
            "type":"Entertainment"
        }
    ],
    "sg:phone":"+32 51 48 58 97",
    "sg:postcode":"8740",
    "sg:province":"West-Vlaanderen",
    "sg:tags":[
        "mushroom"
    ],
    "wof:name":"Districhamp",
    "wof:placetype":"venue"
},
  "geometry": {"coordinates":[3.2388379574,50.9890213013],"type":"Point"}
}