{
  "type": "Feature",
  "properties": {
    "addr:full":"Tervuursesteenweg 224 Steenokkerzeel Vlaams-Brabant 1820",
    "addr:housenumber":"224",
    "addr:postcode":"1820",
    "addr:street":"Tervuursesteenweg",
    "iso:country":"BE",
    "sg:address":"Tervuursesteenweg 224",
    "sg:city":"Steenokkerzeel",
    "sg:orig_category":"Notarissen",
    "sg:phone":"+32 2 751 95 22",
    "sg:postcode":"1820",
    "sg:province":"Vlaams-Brabant",
    "wof:name":"Filip De Sagher",
    "wof:placetype":"venue"
},
  "geometry": {"coordinates":[4.4999241829,50.9209480286],"type":"Point"}
}