{
  "type": "Feature",
  "properties": {
    "addr:full":"Kaaslei 4 Putte Antwerpen 2580",
    "addr:housenumber":"4",
    "addr:postcode":"2580",
    "addr:street":"Kaaslei",
    "iso:country":"BE",
    "sg:address":"Kaaslei 4",
    "sg:city":"Putte",
    "sg:classifiers":[
        {
            "category":"Recreation",
            "subcategory":"Amusement Park",
            "type":"Entertainment"
        }
    ],
    "sg:phone":"+32 15 76 15 61",
    "sg:postcode":"2580",
    "sg:province":"Antwerpen",
    "sg:tags":[
        "attraction",
        "-",
        "sale",
        "fair",
        "hiring"
    ],
    "wof:name":"A & P Projects",
    "wof:placetype":"venue"
},
  "geometry": {"coordinates":[4.643266201,51.0356292725],"type":"Point"}
}