{
  "type": "Feature",
  "properties": {
    "iso:country":"BE",
    "sg:address":"Rue Des Augustins 3",
    "sg:city":"Huy",
    "sg:orig_category":"Opticiens",
    "sg:phone":"+32 85 21 74 01",
    "sg:postcode":"4500",
    "sg:province":"Li\u00e8ge",
    "wof:name":"Nicole Villers",
    "wof:placetype":"venue"
},
  "geometry": {"coordinates":[5.2407121658,50.5191078186],"type":"Point"}
}