{
  "type": "Feature",
  "properties": {
    "addr:full":"Treurenborg 1kaai 420 Antwerpen Antwerpen 2030",
    "addr:housenumber":"420",
    "addr:postcode":"2030",
    "iso:country":"BE",
    "sg:address":"Treurenborg 1kaai 420",
    "sg:city":"Antwerpen",
    "sg:classifiers":[
        {
            "category":"Banks & Credit Unions",
            "subcategory":"Investment Brokerage",
            "type":"Services"
        }
    ],
    "sg:phone":"+32 3 543 89 11",
    "sg:postcode":"2030",
    "sg:province":"Antwerpen",
    "sg:tags":[
        "transshipment",
        "port"
    ],
    "wof:name":"Nova & Hesse-noord Natie Stevedoring Nv",
    "wof:placetype":"venue"
},
  "geometry": {"coordinates":[4.3742909431,51.2703781128],"type":"Point"}
}