{
  "type": "Feature",
  "properties": {
    "iso:country":"BE",
    "sg:address":"Molenweg 153",
    "sg:city":"Zonhoven",
    "sg:orig_category":"Woningbouw",
    "sg:phone":"+32 11 81 11 53",
    "sg:postcode":"3520",
    "sg:province":"Limburg",
    "wof:name":"Roberto Sferlazza",
    "wof:placetype":"venue"
},
  "geometry": {"coordinates":[5.4194397926,50.9846572876],"type":"Point"}
}