{
  "type": "Feature",
  "properties": {
    "iso:country":"BE",
    "sg:address":"Rue Zaman 1",
    "sg:city":"Eghezee",
    "sg:orig_category":"Boucheries",
    "sg:phone":"+32 81 85 57 11",
    "sg:postcode":"5310",
    "sg:province":"Namur",
    "wof:name":"Elevage Rigo",
    "wof:placetype":"venue"
},
  "geometry": {"coordinates":[4.9725232124,50.6297912598],"type":"Point"}
}