{
  "type": "Feature",
  "properties": {
    "addr:full":"Wellingtonstraat 48 Oostende West-Vlaanderen 8400",
    "addr:housenumber":"48",
    "addr:postcode":"8400",
    "addr:street":"Wellingtonstraat",
    "iso:country":"BE",
    "sg:address":"Wellingtonstraat 48",
    "sg:city":"Oostende",
    "sg:orig_category":"Voedingsspeciaalzaken",
    "sg:phone":"+32 59 50 02 35",
    "sg:postcode":"8400",
    "sg:province":"West-Vlaanderen",
    "wof:name":"Huis Pot Pourrie",
    "wof:placetype":"venue"
},
  "geometry": {"coordinates":[2.9061839581,51.2256278992],"type":"Point"}
}