{
  "type": "Feature",
  "properties": {
    "addr:full":"Rue Jean-joseph Piret 125 Gerpinnes Hainaut 6280",
    "addr:housenumber":"125",
    "addr:postcode":"6280",
    "addr:street":"Rue Jean-Joseph Piret;Hainaut",
    "iso:country":"BE",
    "sg:address":"Rue Jean-joseph Piret 125",
    "sg:city":"Gerpinnes",
    "sg:orig_category":"Boucheries",
    "sg:phone":"+32 71 50 18 29",
    "sg:postcode":"6280",
    "sg:province":"Hainaut",
    "wof:name":"Andr\u00c9 Romain",
    "wof:placetype":"venue"
},
  "geometry": {"coordinates":[4.4979100227,50.3425483704],"type":"Point"}
}