{
  "type": "Feature",
  "properties": {
    "iso:country":"BE",
    "sg:address":"Paul Deschanellaan 138b15",
    "sg:city":"Schaarbeek/schaerbeek",
    "sg:orig_category":"Artsen and specialisten",
    "sg:phone":"+32 2 241 57 58",
    "sg:postcode":"1030",
    "sg:province":"Bruxelles-Capitale",
    "wof:name":"C\u00c9cile Dewalque",
    "wof:placetype":"venue"
},
  "geometry": {"coordinates":[4.3787369728,50.8580360413],"type":"Point"}
}