{
  "type": "Feature",
  "properties": {
    "addr:full":"Zeeweg Zuid 11 Zedelgem West-Vlaanderen 8211",
    "addr:housenumber":"11",
    "addr:postcode":"8211",
    "addr:street":"Zeeweg Zuid",
    "iso:country":"BE",
    "sg:address":"Zeeweg Zuid 11",
    "sg:city":"Zedelgem",
    "sg:orig_category":"Varkenskwekers",
    "sg:phone":"+32 50 21 43 83",
    "sg:postcode":"8211",
    "sg:province":"West-Vlaanderen",
    "wof:name":"Luc Blondeel",
    "wof:placetype":"venue"
},
  "geometry": {"coordinates":[3.0823550224,51.1022872925],"type":"Point"}
}