{
  "type": "Feature",
  "properties": {
    "addr:full":"Rue Gognat 154 Florennes (hanzinne) Namur 5621",
    "addr:housenumber":"154",
    "addr:postcode":"5621",
    "addr:street":"Rue Gognat",
    "iso:country":"BE",
    "sg:address":"Rue Gognat 154",
    "sg:city":"Florennes (hanzinne)",
    "sg:classifiers":[
        {
            "category":"Travel",
            "subcategory":"Resort",
            "type":"Entertainment"
        }
    ],
    "sg:phone":"+32 71 50 18 11",
    "sg:postcode":"5621",
    "sg:province":"Namur",
    "sg:tags":[
        "farm",
        "house",
        "holiday",
        "guest"
    ],
    "wof:name":"Ferme De La Prevote",
    "wof:placetype":"venue"
},
  "geometry": {"coordinates":[4.5435042381,50.3093185425],"type":"Point"}
}