{
  "type": "Feature",
  "properties": {
    "iso:country":"BE",
    "sg:address":"Zandvoordestraat 505",
    "sg:city":"Oostende",
    "sg:classifiers":[
        {
            "category":"Utilities",
            "subcategory":"Cable",
            "type":"Services"
        }
    ],
    "sg:phone":"+32 59 51 73 55",
    "sg:postcode":"8400",
    "sg:province":"West-Vlaanderen",
    "sg:tags":[
        "rope",
        "twine"
    ],
    "wof:name":"Duranet Bvba",
    "wof:placetype":"venue"
},
  "geometry": {"coordinates":[2.9744100571,51.2072257996],"type":"Point"}
}