{
  "type": "Feature",
  "properties": {
    "iso:country":"BE",
    "sg:address":"Dorpsstraat 30b5",
    "sg:city":"Overpelt",
    "sg:orig_category":"Boekhouders",
    "sg:phone":"+32 11 80 13 09",
    "sg:postcode":"3900",
    "sg:province":"Limburg",
    "wof:name":"Danny Drees",
    "wof:placetype":"venue"
},
  "geometry": {"coordinates":[5.4249238968,51.214302063],"type":"Point"}
}