{
  "type": "Feature",
  "properties": {
    "iso:country":"BE",
    "sg:address":"Dorpheidestraat 101",
    "sg:city":"Diepenbeek",
    "sg:orig_category":"Installation \u00e9lectrique r\u00e9sidentielle",
    "sg:phone":"+32 11 32 28 31",
    "sg:postcode":"3590",
    "sg:province":"Limburg",
    "wof:name":"Armand Cornelis",
    "wof:placetype":"venue"
},
  "geometry": {"coordinates":[5.4319701195,50.9295921326],"type":"Point"}
}