{
  "type": "Feature",
  "properties": {
    "iso:country":"BE",
    "sg:address":"Zoning De Biron 1",
    "sg:city":"Ciney",
    "sg:orig_category":"Electrom\u00e9nager, t\u00e9l\u00e9visions and radios. R\u00e9parations d'appareils \u00e9lectrom\u00e9nagers. Mat\u00e9riel de T\u00e9l\u00e9com",
    "sg:phone":"+32 83 21 50 03",
    "sg:postcode":"5590",
    "sg:province":"Namur",
    "wof:name":"Euro Center",
    "wof:placetype":"venue"
},
  "geometry": {"coordinates":[5.1075692177,50.2941894531],"type":"Point"}
}