{
  "type": "Feature",
  "properties": {
    "iso:country":"BE",
    "sg:address":"Rue Des Coqs 135b",
    "sg:city":"Gr\u00e2ce-hollogne (hollogne-aux-pierres)",
    "sg:classifiers":[
        {
            "category":"Retail",
            "subcategory":"Auto Repair",
            "type":"Services"
        }
    ],
    "sg:phone":"+32 4 233 33 91",
    "sg:postcode":"4460",
    "sg:province":"Li\u00e8ge",
    "sg:tags":[
        "garage"
    ],
    "wof:name":"Garage Miko",
    "wof:placetype":"venue"
},
  "geometry": {"coordinates":[5.4755649567,50.6357269287],"type":"Point"}
}