{
  "type": "Feature",
  "properties": {
    "iso:country":"BE",
    "sg:address":"A. Rodenbachstraat 29",
    "sg:city":"Blankenberge",
    "sg:classifiers":[
        {
            "category":"Professional",
            "subcategory":"Accounting & Tax Preparation",
            "type":"Services"
        }
    ],
    "sg:phone":"+32 50 42 78 06",
    "sg:postcode":"8370",
    "sg:province":"West-Vlaanderen",
    "sg:tags":[
        "accountant"
    ],
    "wof:name":"De Rycker A",
    "wof:placetype":"venue"
},
  "geometry": {"coordinates":[3.123775959,51.3084869385],"type":"Point"}
}