{
  "type": "Feature",
  "properties": {
    "addr:full":"Rue Basse-wez 53 Li\u00e8ge 1 (li\u00e8ge 2) Li\u00e8ge 4020",
    "addr:housenumber":"53;1;2",
    "addr:postcode":"4020",
    "addr:street":"Rue Basse-Wez",
    "iso:country":"BE",
    "sg:address":"Rue Basse-wez 53",
    "sg:city":"Li\u00e8ge 1 (li\u00e8ge 2)",
    "sg:orig_category":"Ice-cream parlours",
    "sg:phone":"+32 4 343 43 02",
    "sg:postcode":"4020",
    "sg:province":"Li\u00e8ge",
    "wof:name":"Francois S",
    "wof:placetype":"venue"
},
  "geometry": {"coordinates":[5.5878038406,50.636554718],"type":"Point"}
}