{
  "type": "Feature",
  "properties": {
    "addr:full":"Rue Godefroid 38b Namur Namur 5000",
    "addr:housenumber":"38b",
    "addr:postcode":"5000",
    "addr:street":"Rue Godefroid",
    "iso:country":"BE",
    "sg:address":"Rue Godefroid 38b",
    "sg:city":"Namur",
    "sg:classifiers":[
        {
            "category":"Health Services",
            "subcategory":"Doctor",
            "type":"Services"
        }
    ],
    "sg:phone":"+32 81 22 79 22",
    "sg:postcode":"5000",
    "sg:province":"Namur",
    "sg:tags":[
        "medicinephysicians",
        "surgeon"
    ],
    "wof:name":"De Boodt Martine",
    "wof:placetype":"venue"
},
  "geometry": {"coordinates":[4.8626561165,50.4669494629],"type":"Point"}
}