{
  "type": "Feature",
  "properties": {
    "addr:full":"Wezelsebaan 90ba Schoten Antwerpen 2900",
    "addr:housenumber":"90ba",
    "addr:postcode":"2900",
    "addr:street":"Wezelsebaan",
    "iso:country":"BE",
    "sg:address":"Wezelsebaan 90ba",
    "sg:city":"Schoten",
    "sg:orig_category":"Studios photographiques",
    "sg:phone":"+32 3 658 08 92",
    "sg:postcode":"2900",
    "sg:province":"Antwerpen",
    "wof:name":"Danny Van Wonterghem",
    "wof:placetype":"venue"
},
  "geometry": {"coordinates":[4.5162568092,51.2601203918],"type":"Point"}
}