{
  "type": "Feature",
  "properties": {
    "addr:full":"Pav\u00e9 De Soignies 36 Enghien Hainaut 7850",
    "addr:housenumber":"36",
    "addr:postcode":"7850",
    "iso:country":"BE",
    "sg:address":"Pav\u00e9 De Soignies 36",
    "sg:city":"Enghien",
    "sg:classifiers":[
        {
            "category":"Arena",
            "subcategory":"Sports Club",
            "type":"Entertainment"
        }
    ],
    "sg:phone":"+32 2 397 01 99",
    "sg:postcode":"7850",
    "sg:province":"Hainaut",
    "wof:name":"Golf-club D'enghien",
    "wof:placetype":"venue"
},
  "geometry": {"coordinates":[4.0316939354,50.6822471619],"type":"Point"}
}