{
  "type": "Feature",
  "properties": {
    "addr:full":"Rue Tillieux 57 Namur (jambes) Namur 5100",
    "addr:housenumber":"57",
    "addr:postcode":"5100",
    "addr:street":"Rue Tillieux",
    "iso:country":"BE",
    "sg:address":"Rue Tillieux 57",
    "sg:city":"Namur (jambes)",
    "sg:classifiers":[
        {
            "category":"Health Services",
            "subcategory":"Doctor",
            "type":"Services"
        }
    ],
    "sg:phone":"+32 81 30 60 70",
    "sg:postcode":"5100",
    "sg:province":"Namur",
    "sg:tags":[
        "medicinephysicians",
        "surgeon"
    ],
    "wof:name":"Dervaux I",
    "wof:placetype":"venue"
},
  "geometry": {"coordinates":[4.8713750839,50.4566345215],"type":"Point"}
}