{
  "type": "Feature",
  "properties": {
    "iso:country":"BE",
    "sg:address":"Rue Waressaix 55",
    "sg:city":"Morlanwelz",
    "sg:orig_category":"Apotheken",
    "sg:phone":"+32 64 44 80 11",
    "sg:postcode":"7141",
    "sg:province":"Hainaut",
    "wof:name":"Alain Dallons",
    "wof:placetype":"venue"
},
  "geometry": {"coordinates":[4.2576799393,50.4437103271],"type":"Point"}
}