{
  "type": "Feature",
  "properties": {
    "iso:country":"BE",
    "sg:address":"Rue Des Alli\u00c9s 2a",
    "sg:city":"Frameries",
    "sg:orig_category":"Huishoudapparaten, televisies and radio's",
    "sg:phone":"+32 65 67 14 84",
    "sg:postcode":"7080",
    "sg:province":"Hainaut",
    "wof:name":"Gallez",
    "wof:placetype":"venue"
},
  "geometry": {"coordinates":[3.8952260017,50.4109039307],"type":"Point"}
}