{
  "type": "Feature",
  "properties": {
    "addr:full":"Gaspeldoornstraat 7 Dilsen-stokkem (lanklaar) Limburg 3650",
    "addr:housenumber":"7",
    "addr:postcode":"3650",
    "addr:street":"Gaspeldoornstraat",
    "iso:country":"BE",
    "sg:address":"Gaspeldoornstraat 7",
    "sg:city":"Dilsen-stokkem (lanklaar)",
    "sg:classifiers":[
        {
            "category":"Professional",
            "subcategory":"Engineering",
            "type":"Services"
        }
    ],
    "sg:phone":"+32 89 79 39 20",
    "sg:postcode":"3650",
    "sg:province":"Limburg",
    "sg:tags":[
        "workshop"
    ],
    "wof:name":"Clijsters",
    "wof:placetype":"venue"
},
  "geometry": {"coordinates":[5.727396965,51.0364189148],"type":"Point"}
}