{
  "type": "Feature",
  "properties": {
    "addr:full":"Rue Saint-gilles 450 Li\u00e8ge 1 Li\u00e8ge 4000",
    "addr:housenumber":"450;1",
    "addr:postcode":"4000",
    "addr:street":"Rue Saint-Gilles",
    "iso:country":"BE",
    "sg:address":"Rue Saint-gilles 450",
    "sg:city":"Li\u00e8ge 1",
    "sg:classifiers":[
        {
            "category":"Professional",
            "subcategory":"Computer Services",
            "type":"Services"
        }
    ],
    "sg:phone":"+32 4 253 60 00",
    "sg:postcode":"4000",
    "sg:province":"Li\u00e8ge",
    "sg:tags":[
        "-",
        "processing",
        "data",
        "software"
    ],
    "wof:name":"Burlet Mercel Sprl",
    "wof:placetype":"venue"
},
  "geometry": {"coordinates":[5.5510759354,50.6337356567],"type":"Point"}
}