{
  "type": "Feature",
  "properties": {
    "iso:country":"BE",
    "sg:address":"Markt 20",
    "sg:city":"Meerhout",
    "sg:classifiers":[
        {
            "category":"Bars & Pubs",
            "type":"Food & Drink"
        }
    ],
    "sg:phone":"+32 14 30 13 89",
    "sg:postcode":"2450",
    "sg:province":"Antwerpen",
    "sg:tags":[
        "tavern"
    ],
    "wof:name":"Agua Loca (el)",
    "wof:placetype":"venue"
},
  "geometry": {"coordinates":[5.0779151917,51.1319160461],"type":"Point"}
}