{
  "type": "Feature",
  "properties": {
    "iso:country":"BE",
    "sg:address":"Sint-maartensstraat 23",
    "sg:city":"Olen",
    "sg:orig_category":"D\u00e9corateurs d'int\u00e9rieur. Rev\u00eatements pour sols and murs. Eclairage et \u00e9quipements du foyer. Peinture",
    "sg:phone":"+32 14 26 31 01",
    "sg:postcode":"2250",
    "sg:province":"Antwerpen",
    "wof:name":"Decor Peeters",
    "wof:placetype":"venue"
},
  "geometry": {"coordinates":[4.8575668335,51.1439361572],"type":"Point"}
}