{
  "type": "Feature",
  "properties": {
    "iso:country":"BE",
    "sg:address":"Rue De Stoumont 57",
    "sg:city":"Philippeville",
    "sg:orig_category":"Onderdelen and accessoires voor auto's",
    "sg:phone":"+32 71 66 88 48",
    "sg:postcode":"5600",
    "sg:province":"Namur",
    "wof:name":"Beno\u00cet Detraux",
    "wof:placetype":"venue"
},
  "geometry": {"coordinates":[4.6346998215,50.1861763],"type":"Point"}
}