{
  "type": "Feature",
  "properties": {
    "addr:full":"Mereldreef 23 Waasmunster Oost-Vlaanderen 9250",
    "addr:housenumber":"23",
    "addr:postcode":"9250",
    "addr:street":"Mereldreef",
    "iso:country":"BE",
    "sg:address":"Mereldreef 23",
    "sg:city":"Waasmunster",
    "sg:orig_category":"M\u00e9decins and sp\u00e9cialistes",
    "sg:phone":"+32 3 772 54 50",
    "sg:postcode":"9250",
    "sg:province":"Oost-Vlaanderen",
    "wof:name":"Channa O. Debruyne",
    "wof:placetype":"venue"
},
  "geometry": {"coordinates":[4.092400074,51.1271018982],"type":"Point"}
}