{
  "type": "Feature",
  "properties": {
    "addr:full":"Kempische Steenweg 21 Hasselt Limburg 3500",
    "addr:housenumber":"21",
    "addr:postcode":"3500",
    "addr:street":"Kempische Steenweg",
    "iso:country":"BE",
    "sg:address":"Kempische Steenweg 21",
    "sg:city":"Hasselt",
    "sg:orig_category":"MEUBELONTWERP AND -INSTALLATIE",
    "sg:phone":"+32 78 71 73 10",
    "sg:postcode":"3500",
    "sg:province":"Limburg",
    "wof:name":"Dea Plus",
    "wof:placetype":"venue"
},
  "geometry": {"coordinates":[5.3398389816,50.9347038269],"type":"Point"}
}