{
  "type": "Feature",
  "properties": {
    "iso:country":"BE",
    "sg:address":"Rue Des Juifs 47",
    "sg:city":"Chi\u00e8vres (grosage)",
    "sg:classifiers":[
        {
            "category":"Social Services",
            "type":"Services"
        }
    ],
    "sg:phone":"+32 69 68 94 01",
    "sg:postcode":"7950",
    "sg:province":"Hainaut",
    "sg:tags":[
        "handicapped",
        "-"
    ],
    "wof:name":"Renouveau (le)",
    "wof:placetype":"venue"
},
  "geometry": {"coordinates":[3.7605600357,50.5427856445],"type":"Point"}
}