{
  "type": "Feature",
  "properties": {
    "addr:full":"Vluchtenboerstraat 45 Gavere Oost-Vlaanderen 9890",
    "addr:housenumber":"45",
    "addr:postcode":"9890",
    "addr:street":"Vluchtenboerstraat",
    "iso:country":"BE",
    "sg:address":"Vluchtenboerstraat 45",
    "sg:city":"Gavere",
    "sg:orig_category":"Airconditioning and ventilatie Elektrische installaties voor woningen Winkelinrichting and handelsui",
    "sg:phone":"+32 9 384 35 85",
    "sg:postcode":"9890",
    "sg:province":"Oost-Vlaanderen",
    "wof:name":"De Noyette Etienne",
    "wof:placetype":"venue"
},
  "geometry": {"coordinates":[3.6723520756,50.9282493591],"type":"Point"}
}