{
  "type": "Feature",
  "properties": {
    "addr:full":"Westkerksestraat 17 Oudenburg West-Vlaanderen 8460",
    "addr:housenumber":"17",
    "addr:postcode":"8460",
    "addr:street":"Westkerksestraat",
    "iso:country":"BE",
    "sg:address":"Westkerksestraat 17",
    "sg:city":"Oudenburg",
    "sg:classifiers":[
        {
            "category":"Insurance",
            "subcategory":"Life Insurance",
            "type":"Services"
        }
    ],
    "sg:phone":"+32 59 26 67 42",
    "sg:postcode":"8460",
    "sg:province":"West-Vlaanderen",
    "sg:tags":[
        "assurance"
    ],
    "wof:name":"I. Acke",
    "wof:placetype":"venue"
},
  "geometry": {"coordinates":[3.0045828819,51.180557251],"type":"Point"}
}