{
  "type": "Feature",
  "properties": {
    "addr:full":"Koning Leopold Ii 17d Gent Oost-Vlaanderen 9000",
    "addr:housenumber":"17d",
    "addr:postcode":"9000",
    "addr:street":"Koning Leopold Ii;Oost-Vlaanderen",
    "iso:country":"BE",
    "sg:address":"Koning Leopold Ii 17d",
    "sg:city":"Gent",
    "sg:orig_category":"Projectontwikkelaars",
    "sg:phone":"+32 9 220 00 95",
    "sg:postcode":"9000",
    "sg:province":"Oost-Vlaanderen",
    "wof:name":"Derveaux W.",
    "wof:placetype":"venue"
},
  "geometry": {"coordinates":[3.7193710804,51.0406303406],"type":"Point"}
}