{
  "type": "Feature",
  "properties": {
    "addr:full":"Ophemstraat 109b Oud-heverlee Vlaams-Brabant 3050",
    "addr:housenumber":"109b",
    "addr:postcode":"3050",
    "addr:street":"Ophemstraat",
    "iso:country":"BE",
    "sg:address":"Ophemstraat 109b",
    "sg:city":"Oud-heverlee",
    "sg:classifiers":[
        {
            "category":"Home & Garden",
            "subcategory":"Kitchen Supply",
            "type":"Retail Goods"
        }
    ],
    "sg:phone":"+32 16 47 03 70",
    "sg:postcode":"3050",
    "sg:province":"Vlaams-Brabant",
    "sg:tags":[
        "installation"
    ],
    "wof:name":"Kitchenpoint",
    "wof:placetype":"venue"
},
  "geometry": {"coordinates":[4.6479120255,50.8298797607],"type":"Point"}
}