{
  "type": "Feature",
  "properties": {
    "addr:full":"Krabbenijkstraat 108 Sint-lievens-houtem Oost-Vlaanderen 9520",
    "addr:housenumber":"108",
    "addr:postcode":"9520",
    "addr:street":"Krabbenijkstraat",
    "iso:country":"BE",
    "sg:address":"Krabbenijkstraat 108",
    "sg:city":"Sint-lievens-houtem",
    "sg:orig_category":"Bloemen and planten",
    "sg:phone":"+32 53 62 37 96",
    "sg:postcode":"9520",
    "sg:province":"Oost-Vlaanderen",
    "wof:name":"Bloemenweelde",
    "wof:placetype":"venue"
},
  "geometry": {"coordinates":[3.8715999126,50.9210281372],"type":"Point"}
}