{
  "type": "Feature",
  "properties": {
    "addr:full":"Rue De Neuve-eglise 21 Mesen/messines West-Vlaanderen 8957",
    "addr:housenumber":"21",
    "addr:postcode":"8957",
    "addr:street":"Rue De Neuve-Eglise",
    "iso:country":"BE",
    "sg:address":"Rue De Neuve-eglise 21",
    "sg:city":"Mesen/messines",
    "sg:orig_category":"Eleveurs de bovins. Eleveurs and marchands de porcs",
    "sg:phone":"+32 57 44 54 24",
    "sg:postcode":"8957",
    "sg:province":"West-Vlaanderen",
    "wof:name":"Roger Rousere",
    "wof:placetype":"venue"
},
  "geometry": {"coordinates":[2.8714139462,50.7602539062],"type":"Point"}
}