{
  "type": "Feature",
  "properties": {
    "addr:full":"Rue De Mons 36 Charleroi Hainaut 6000",
    "addr:housenumber":"36",
    "addr:postcode":"6000",
    "addr:street":"Rue De Mons;Hainaut",
    "iso:country":"BE",
    "sg:address":"Rue De Mons 36",
    "sg:city":"Charleroi",
    "sg:classifiers":[
        {
            "category":"Professional",
            "subcategory":"Detective & Security Services",
            "type":"Services"
        }
    ],
    "sg:phone":"+32 71 27 72 77",
    "sg:postcode":"6000",
    "sg:province":"Hainaut",
    "sg:tags":[
        "door",
        "videophones",
        "operating",
        "equipment"
    ],
    "wof:name":"Tasiaux Ets",
    "wof:placetype":"venue"
},
  "geometry": {"coordinates":[4.4346299171,50.4120445251],"type":"Point"}
}