{
  "type": "Feature",
  "properties": {
    "addr:full":"Brouwersvliet 18 Antwerpen Antwerpen 2000",
    "addr:housenumber":"18",
    "addr:postcode":"2000",
    "addr:street":"Brouwersvliet",
    "iso:country":"BE",
    "sg:address":"Brouwersvliet 18",
    "sg:city":"Antwerpen",
    "sg:classifiers":[
        {
            "category":"Bars & Pubs",
            "type":"Food & Drink"
        }
    ],
    "sg:phone":"+32 3 233 17 10",
    "sg:postcode":"2000",
    "sg:province":"Antwerpen",
    "sg:tags":[
        "tavern"
    ],
    "wof:name":"Continental Bvba",
    "wof:placetype":"venue"
},
  "geometry": {"coordinates":[4.4037718773,51.2267189026],"type":"Point"}
}