{
  "type": "Feature",
  "properties": {
    "addr:full":"Grote Markt 28 Aarschot Vlaams-Brabant 3200",
    "addr:housenumber":"28",
    "addr:postcode":"3200",
    "addr:street":"Grote Markt",
    "iso:country":"BE",
    "sg:address":"Grote Markt 28",
    "sg:city":"Aarschot",
    "sg:classifiers":[
        {
            "category":"Professional",
            "subcategory":"Accounting & Tax Preparation",
            "type":"Services"
        }
    ],
    "sg:phone":"+32 16 55 33 40",
    "sg:postcode":"3200",
    "sg:province":"Vlaams-Brabant",
    "sg:tags":[
        "accountant"
    ],
    "wof:name":"Accountantskantoor Drt & Partners Bvba",
    "wof:placetype":"venue"
},
  "geometry": {"coordinates":[4.8368000984,50.9844589233],"type":"Point"}
}