{
  "type": "Feature",
  "properties": {
    "iso:country":"BE",
    "sg:address":"Rue Gatti De Gamond 239b4",
    "sg:city":"Ukkel/uccle",
    "sg:orig_category":"Avocats and conseillers juridiques",
    "sg:phone":"+32 2 376 00 08",
    "sg:postcode":"1180",
    "sg:province":"Bruxelles-Capitale",
    "wof:name":"D. Casaer",
    "wof:placetype":"venue"
},
  "geometry": {"coordinates":[4.3273849487,50.7990913391],"type":"Point"}
}