{
  "type": "Feature",
  "properties": {
    "addr:full":"Kloosterstraat 22 Wervik West-Vlaanderen 8940",
    "addr:housenumber":"22",
    "addr:postcode":"8940",
    "addr:street":"Kloosterstraat",
    "iso:country":"BE",
    "sg:address":"Kloosterstraat 22",
    "sg:city":"Wervik",
    "sg:orig_category":"Drogisterijen",
    "sg:phone":"+32 56 53 06 96",
    "sg:postcode":"8940",
    "sg:province":"West-Vlaanderen",
    "wof:name":"Paul Demyttenaere",
    "wof:placetype":"venue"
},
  "geometry": {"coordinates":[3.0737540722,50.8122406006],"type":"Point"}
}