{
  "type": "Feature",
  "properties": {
    "iso:country":"BE",
    "sg:address":"Aarschotsesteenweg 638",
    "sg:city":"Tienen",
    "sg:orig_category":"Enseignement maternel and primaire",
    "sg:phone":"+32 16 81 81 86",
    "sg:postcode":"3300",
    "sg:province":"Vlaams-Brabant",
    "wof:name":"Stedelijke Basisschool",
    "wof:placetype":"venue"
},
  "geometry": {"coordinates":[4.9232897758,50.8266296387],"type":"Point"}
}