{
  "type": "Feature",
  "properties": {
    "iso:country":"BE",
    "sg:address":"Recollettenlei 43",
    "sg:city":"Gent",
    "sg:classifiers":[
        {
            "category":"Professional",
            "subcategory":"Lawyer & Legal Services",
            "type":"Services"
        }
    ],
    "sg:phone":"+32 9 223 65 50",
    "sg:postcode":"9000",
    "sg:province":"Oost-Vlaanderen",
    "wof:name":"Van De Steene Ann",
    "wof:placetype":"venue"
},
  "geometry": {"coordinates":[3.7196500301,51.0496292114],"type":"Point"}
}