{
  "type": "Feature",
  "properties": {
    "addr:full":"Avenue Heydenberg 29 Sint-lambrechts-woluwe/woluwe-saint-lambert Bruxelles-Capitale 1200",
    "addr:housenumber":"29",
    "addr:postcode":"1200",
    "addr:street":"Avenue Heydenberg",
    "iso:country":"BE",
    "sg:address":"Avenue Heydenberg 29",
    "sg:city":"Sint-lambrechts-woluwe/woluwe-saint-lambert",
    "sg:orig_category":"Production de films, t\u00e9l\u00e9films and vid\u00e9os",
    "sg:phone":"+32 2 771 74 63",
    "sg:postcode":"1200",
    "sg:province":"Bruxelles-Capitale",
    "wof:name":"Stefaan Fortemps",
    "wof:placetype":"venue"
},
  "geometry": {"coordinates":[4.4170918465,50.8467254639],"type":"Point"}
}