{
  "type": "Feature",
  "properties": {
    "addr:full":"Grand'rue 36ba Mont-saint-guibert Brabant Wallon 1435",
    "addr:housenumber":"36ba",
    "addr:postcode":"1435",
    "addr:street":"Grand'Rue",
    "iso:country":"BE",
    "sg:address":"Grand'rue 36ba",
    "sg:city":"Mont-saint-guibert",
    "sg:orig_category":"Kapsalons",
    "sg:phone":"+32 10 65 64 61",
    "sg:postcode":"1435",
    "sg:province":"Brabant Wallon",
    "wof:name":"Christiane Gramme",
    "wof:placetype":"venue"
},
  "geometry": {"coordinates":[4.6107521057,50.6339874268],"type":"Point"}
}