{
  "type": "Feature",
  "properties": {
    "iso:country":"BE",
    "sg:address":"Rue Godecharle 39",
    "sg:city":"Elsene/ixelles",
    "sg:orig_category":"Antiquit\u00e9s",
    "sg:phone":"+32 2 648 98 06",
    "sg:postcode":"1050",
    "sg:province":"Bruxelles-Capitale",
    "wof:name":"Au Vieux Magasin",
    "wof:placetype":"venue"
},
  "geometry": {"coordinates":[4.3735737801,50.8359680176],"type":"Point"}
}