{
  "type": "Feature",
  "properties": {
    "addr:full":"Chauss\u00e9e De Boondael 475 Bruxelles (ixelles) Bruxelles-Capitale 1050",
    "addr:housenumber":"475",
    "addr:postcode":"1050",
    "addr:street":"Chausse\u0301E De Boondael",
    "iso:country":"BE",
    "sg:address":"Chauss\u00e9e De Boondael 475",
    "sg:city":"Bruxelles (ixelles)",
    "sg:classifiers":[
        {
            "category":"Bars & Pubs",
            "type":"Food & Drink"
        }
    ],
    "sg:phone":"+32 2 649 08 20",
    "sg:postcode":"1050",
    "sg:province":"Bruxelles-Capitale",
    "sg:tags":[
        "tavern"
    ],
    "wof:name":"Universit\u00e9 (l')",
    "wof:placetype":"venue"
},
  "geometry": {"coordinates":[4.3858799934,50.8180007935],"type":"Point"}
}