{
  "type": "Feature",
  "properties": {
    "addr:full":"Kapelanielaan 13d Temse Oost-Vlaanderen 9140",
    "addr:housenumber":"13d",
    "addr:postcode":"9140",
    "addr:street":"Kapelanielaan",
    "iso:country":"BE",
    "sg:address":"Kapelanielaan 13d",
    "sg:city":"Temse",
    "sg:classifiers":[
        {
            "category":"Professional",
            "subcategory":"Engineering",
            "type":"Services"
        }
    ],
    "sg:phone":"+32 3 710 58 10",
    "sg:postcode":"9140",
    "sg:province":"Oost-Vlaanderen",
    "sg:tags":[
        "technical",
        "equipment",
        "offices-"
    ],
    "wof:name":"Multi Nv",
    "wof:placetype":"venue"
},
  "geometry": {"coordinates":[4.1807317734,51.1369667053],"type":"Point"}
}