{
  "type": "Feature",
  "properties": {
    "iso:country":"BE",
    "sg:address":"Waaienburgseweg 51",
    "sg:city":"Poperinge (krombeke)",
    "sg:classifiers":[
        {
            "category":"Professional",
            "subcategory":"Engineering",
            "type":"Services"
        }
    ],
    "sg:phone":"+32 57 30 15 15",
    "sg:postcode":"8972",
    "sg:province":"West-Vlaanderen",
    "sg:tags":[
        "-"
    ],
    "wof:name":"Pieter Top Projects Bvba",
    "wof:placetype":"venue"
},
  "geometry": {"coordinates":[2.6731009483,50.9153060913],"type":"Point"}
}