{
  "type": "Feature",
  "properties": {
    "iso:country":"BE",
    "sg:address":"Victor Soensstraat 8",
    "sg:city":"Grimbergen (strombeek-bever)",
    "sg:classifiers":[
        {
            "category":"Shopping",
            "subcategory":"Shoes",
            "type":"Retail Goods"
        }
    ],
    "sg:phone":"+32 2 267 19 11",
    "sg:postcode":"1853",
    "sg:province":"Vlaams-Brabant",
    "sg:tags":[
        "slipper",
        "-"
    ],
    "wof:name":"Ovide",
    "wof:placetype":"venue"
},
  "geometry": {"coordinates":[4.3541002274,50.9092102051],"type":"Point"}
}