{
  "type": "Feature",
  "properties": {
    "iso:country":"BE",
    "sg:address":"Kerkstraat 5",
    "sg:city":"Wetteren",
    "sg:classifiers":[
        {
            "category":"Bars & Pubs",
            "type":"Food & Drink"
        }
    ],
    "sg:phone":"+32 9 369 35 11",
    "sg:postcode":"9230",
    "sg:province":"Oost-Vlaanderen",
    "wof:name":"Stadhuis",
    "wof:placetype":"venue"
},
  "geometry": {"coordinates":[3.8863999844,51.0055847168],"type":"Point"}
}