{
  "type": "Feature",
  "properties": {
    "addr:full":"Chauss\u00e9e De Louvain 567 Bruxelles (schaerbeek) Bruxelles-Capitale 1030",
    "addr:housenumber":"567",
    "addr:postcode":"1030",
    "addr:street":"Chausse\u0301E De Louvain",
    "iso:country":"BE",
    "sg:address":"Chauss\u00e9e De Louvain 567",
    "sg:city":"Bruxelles (schaerbeek)",
    "sg:classifiers":[
        {
            "category":"Bars & Pubs",
            "type":"Food & Drink"
        }
    ],
    "sg:phone":"+32 2 705 86 43",
    "sg:postcode":"1030",
    "sg:province":"Bruxelles-Capitale",
    "sg:tags":[
        "tavern"
    ],
    "wof:name":"Prince D'orange (le)",
    "wof:placetype":"venue"
},
  "geometry": {"coordinates":[4.401307106,50.8559150696],"type":"Point"}
}