{
  "type": "Feature",
  "properties": {
    "iso:country":"BE",
    "sg:address":"Rue A Canadas 17",
    "sg:city":"Nalinnes",
    "sg:classifiers":[
        {
            "category":"Banks & Credit Unions",
            "subcategory":"Bank",
            "type":"Services"
        }
    ],
    "sg:phone":"+32 60 21 34 01",
    "sg:postcode":"6290",
    "wof:name":"Banque Bruxelles Lambert Sa",
    "wof:placetype":"venue"
},
  "geometry": {"coordinates":[105.4087295532,30.4185390472],"type":"Point"}
}