{
  "type": "Feature",
  "properties": {
    "addr:full":"Rochefortplein 1 Vorst/forest Bruxelles-Capitale 1190",
    "addr:housenumber":"1",
    "addr:postcode":"1190",
    "addr:street":"Rochefortplein;/ Forest",
    "iso:country":"BE",
    "sg:address":"Rochefortplein 1",
    "sg:city":"Vorst/forest",
    "sg:orig_category":"Biljart- and snookerzalen Restaurants",
    "sg:phone":"+32 2 538 67 76",
    "sg:postcode":"1190",
    "sg:province":"Bruxelles-Capitale",
    "wof:name":"La Belle-vue",
    "wof:placetype":"venue"
},
  "geometry": {"coordinates":[4.3349051476,50.82396698],"type":"Point"}
}