{
  "type": "Feature",
  "properties": {
    "addr:full":"Oordegemstraat 16 Sint-lievens-houtem Oost-Vlaanderen 9520",
    "addr:housenumber":"16",
    "addr:postcode":"9520",
    "addr:street":"Oordegemstraat;Oost-Vlaanderen",
    "iso:country":"BE",
    "sg:address":"Oordegemstraat 16",
    "sg:city":"Sint-lievens-houtem",
    "sg:orig_category":"Medische apparatuur, orthopedische artikelen and prothesen Fab",
    "sg:phone":"+32 53 62 26 83",
    "sg:postcode":"9520",
    "sg:province":"Oost-Vlaanderen",
    "wof:name":"Bernard Van Bever",
    "wof:placetype":"venue"
},
  "geometry": {"coordinates":[3.9032320976,50.9330940247],"type":"Point"}
}