{
  "type": "Feature",
  "properties": {
    "addr:full":"Rue Antoine Degive 1 Gr\u00c2ce-hollogne Li\u00e8ge 4460",
    "addr:housenumber":"1",
    "addr:postcode":"4460",
    "addr:street":"Rue Antoine Degive",
    "iso:country":"BE",
    "sg:address":"Rue Antoine Degive 1",
    "sg:city":"Gr\u00c2ce-hollogne",
    "sg:orig_category":"Formation permanente",
    "sg:phone":"+32 4 233 53 15",
    "sg:postcode":"4460",
    "sg:province":"Li\u00e8ge",
    "wof:name":"Inst.enseign.prom.sociale",
    "wof:placetype":"venue"
},
  "geometry": {"coordinates":[5.5044941902,50.6450920105],"type":"Point"}
}