{
  "type": "Feature",
  "properties": {
    "iso:country":"BE",
    "sg:address":"Rue Auguste Lambiotte 28-30",
    "sg:city":"Bruxelles (schaerbeek)",
    "sg:classifiers":[
        {
            "category":"Building & Trades",
            "subcategory":"Electrical",
            "type":"Services"
        }
    ],
    "sg:phone":"+32 2 215 88 87",
    "sg:postcode":"1030",
    "sg:province":"Bruxelles-Capitale",
    "sg:tags":[
        "-",
        "electric",
        "contractor"
    ],
    "wof:name":"Feyens Nestor Et Fils Sa",
    "wof:placetype":"venue"
},
  "geometry": {"coordinates":[4.3878221512,50.8566055298],"type":"Point"}
}