{
  "type": "Feature",
  "properties": {
    "addr:full":"Keiemdorpstraat 134 Diksmuide (keiem) West-Vlaanderen 8600",
    "addr:housenumber":"134",
    "addr:postcode":"8600",
    "addr:street":"Keiemdorpstraat",
    "iso:country":"BE",
    "sg:address":"Keiemdorpstraat 134",
    "sg:city":"Diksmuide (keiem)",
    "sg:classifiers":[
        {
            "category":"Food & Beverages",
            "subcategory":"Meat & Fish",
            "type":"Retail Goods"
        }
    ],
    "sg:phone":"+32 51 50 11 05",
    "sg:postcode":"8600",
    "sg:province":"West-Vlaanderen",
    "sg:tags":[
        "poultry",
        "whol",
        "game",
        "-"
    ],
    "wof:name":"Laleman F",
    "wof:placetype":"venue"
},
  "geometry": {"coordinates":[2.8827550411,51.0827903748],"type":"Point"}
}