{
  "type": "Feature",
  "properties": {
    "addr:full":"Rue Gustave Fuss 37 Schaarbeek/schaerbeek Bruxelles-Capitale 1030",
    "addr:housenumber":"37",
    "addr:postcode":"1030",
    "addr:street":"Rue Gustave Fuss",
    "iso:country":"BE",
    "sg:address":"Rue Gustave Fuss 37",
    "sg:city":"Schaarbeek/schaerbeek",
    "sg:orig_category":"Artistes ind\u00e9pendants",
    "sg:phone":"+32 2 734 29 42",
    "sg:postcode":"1030",
    "sg:province":"Bruxelles-Capitale",
    "wof:name":"Yvonne Segers",
    "wof:placetype":"venue"
},
  "geometry": {"coordinates":[4.3800301552,50.852935791],"type":"Point"}
}