{
  "type": "Feature",
  "properties": {
    "addr:full":"Beverlaai 3 Kortrijk West-Vlaanderen 8500",
    "addr:housenumber":"3",
    "addr:postcode":"8500",
    "addr:street":"Beverlaai",
    "iso:country":"BE",
    "sg:address":"Beverlaai 3",
    "sg:city":"Kortrijk",
    "sg:classifiers":[
        {
            "category":"Insurance",
            "subcategory":"Life Insurance",
            "type":"Services"
        }
    ],
    "sg:phone":"+32 56 22 14 60",
    "sg:postcode":"8500",
    "sg:province":"West-Vlaanderen",
    "sg:tags":[
        "assurance"
    ],
    "wof:name":"Calewaert",
    "wof:placetype":"venue"
},
  "geometry": {"coordinates":[3.2678821087,50.8223342896],"type":"Point"}
}