{
  "type": "Feature",
  "properties": {
    "iso:country":"BE",
    "sg:address":"Rue Du Ch\u00c2teau D'eau 4",
    "sg:city":"Oupeye",
    "sg:orig_category":"Huisdieren and benodigdheden",
    "sg:phone":"+32 4 264 42 29",
    "sg:postcode":"4680",
    "sg:province":"Li\u00e8ge",
    "wof:name":"A.a.a.f.",
    "wof:placetype":"venue"
},
  "geometry": {"coordinates":[5.6481118202,50.7045249939],"type":"Point"}
}