{
  "type": "Feature",
  "properties": {
    "addr:full":"Broekstraat 74 Meise Vlaams-Brabant 1860",
    "addr:housenumber":"74",
    "addr:postcode":"1860",
    "addr:street":"Broekstraat",
    "iso:country":"BE",
    "sg:address":"Broekstraat 74",
    "sg:city":"Meise",
    "sg:classifiers":[
        {
            "category":"Building & Trades",
            "subcategory":"Plumbing",
            "type":"Services"
        }
    ],
    "sg:phone":"+32 2 269 95 29",
    "sg:postcode":"1860",
    "sg:province":"Vlaams-Brabant",
    "sg:tags":[
        "repair",
        "mainten",
        "-",
        "central",
        "heating"
    ],
    "wof:name":"Ooms R",
    "wof:placetype":"venue"
},
  "geometry": {"coordinates":[4.3406801224,50.9671897888],"type":"Point"}
}