{
  "type": "Feature",
  "properties": {
    "addr:full":"Moorselestraat 227 Wevelgem West-Vlaanderen 8560",
    "addr:housenumber":"227",
    "addr:postcode":"8560",
    "addr:street":"Moorselestraat",
    "iso:country":"BE",
    "sg:address":"Moorselestraat 227",
    "sg:city":"Wevelgem",
    "sg:classifiers":[
        {
            "category":"Bars & Pubs",
            "type":"Food & Drink"
        }
    ],
    "sg:phone":"+32 56 41 63 07",
    "sg:postcode":"8560",
    "sg:province":"West-Vlaanderen",
    "sg:tags":[
        "tavern"
    ],
    "wof:name":"Brouwerijtje",
    "wof:placetype":"venue"
},
  "geometry": {"coordinates":[3.1647200584,50.8193778992],"type":"Point"}
}