{
  "type": "Feature",
  "properties": {
    "iso:country":"BE",
    "sg:address":"Rue Des Moutons 58",
    "sg:city":"Bruxelles (uccle)",
    "sg:classifiers":[
        {
            "category":"Wholesale",
            "subcategory":"Plants",
            "type":"Manufacturing & Wholesale Goods"
        }
    ],
    "sg:phone":"+32 2 269 60 61",
    "sg:postcode":"1180",
    "sg:province":"Bruxelles-Capitale",
    "sg:tags":[
        "whol",
        "flower",
        "-",
        "grower"
    ],
    "wof:name":"Ryckaert Fran\u00e7ois Sprl",
    "wof:placetype":"venue"
},
  "geometry": {"coordinates":[4.3381919861,50.7943878174],"type":"Point"}
}