{
  "type": "Feature",
  "properties": {
    "addr:full":"Nicolas Doyenstraat 52 Sint-jans-molenbeek/molenbeek-saint-jean Bruxelles-Capitale 1080",
    "addr:housenumber":"52",
    "addr:postcode":"1080",
    "addr:street":"Nicolas Doyenstraat",
    "iso:country":"BE",
    "sg:address":"Nicolas Doyenstraat 52",
    "sg:city":"Sint-jans-molenbeek/molenbeek-saint-jean",
    "sg:orig_category":"Herstellingen and onderhoud van auto's",
    "sg:phone":"+32 2 410 50 50",
    "sg:postcode":"1080",
    "sg:province":"Bruxelles-Capitale",
    "wof:name":"Transrent",
    "wof:placetype":"venue"
},
  "geometry": {"coordinates":[4.3228521347,50.8468093872],"type":"Point"}
}