{
  "type": "Feature",
  "properties": {
    "iso:country":"BE",
    "sg:address":"Mechelsevest 84",
    "sg:city":"Leuven",
    "sg:orig_category":"Enseignement secondaire technique and professionnel",
    "sg:phone":"+32 16 23 69 51",
    "sg:postcode":"3000",
    "sg:province":"Vlaams-Brabant",
    "wof:name":"Instituut De Wijnpers",
    "wof:placetype":"venue"
},
  "geometry": {"coordinates":[4.6876001358,50.8862762451],"type":"Point"}
}