{
  "type": "Feature",
  "properties": {
    "iso:country":"BE",
    "sg:address":"Tennisstraat 9",
    "sg:city":"Eeklo",
    "sg:orig_category":"Balie van Gent. Avocats and conseillers juridiques",
    "sg:phone":"+32 9 377 52 25",
    "sg:postcode":"9900",
    "sg:province":"Oost-Vlaanderen",
    "wof:name":"De Wispelaere Eddy",
    "wof:placetype":"venue"
},
  "geometry": {"coordinates":[3.5838520527,51.1803817749],"type":"Point"}
}