{
  "type": "Feature",
  "properties": {
    "addr:full":"Groenestraat 30 Ruiselede West-Vlaanderen 8755",
    "addr:housenumber":"30",
    "addr:postcode":"8755",
    "addr:street":"Groenestraat",
    "iso:country":"BE",
    "sg:address":"Groenestraat 30",
    "sg:city":"Ruiselede",
    "sg:orig_category":"Elektrische installaties voor woningen",
    "sg:phone":"+32 51 68 98 86",
    "sg:postcode":"8755",
    "sg:province":"West-Vlaanderen",
    "wof:name":"Patrick Verstraete",
    "wof:placetype":"venue"
},
  "geometry": {"coordinates":[3.3917040825,51.0377082825],"type":"Point"}
}