{
  "type": "Feature",
  "properties": {
    "addr:full":"Kaai 118 Terminal Zuidnatie Antwerpen Antwerpen 2030",
    "addr:housenumber":"118",
    "addr:postcode":"2030",
    "addr:street":"Kaai",
    "iso:country":"BE",
    "sg:address":"Kaai 118 Terminal Zuidnatie",
    "sg:city":"Antwerpen",
    "sg:classifiers":[
        {
            "category":"Professional",
            "type":"Services"
        }
    ],
    "sg:phone":"+32 3 226 11 26",
    "sg:postcode":"2030",
    "sg:province":"Antwerpen",
    "sg:tags":[
        "transport",
        "road"
    ],
    "wof:name":"Wine Logistics International Nv",
    "wof:placetype":"venue"
},
  "geometry": {"coordinates":[4.3637099266,51.2742385864],"type":"Point"}
}