{
  "type": "Feature",
  "properties": {
    "iso:country":"BE",
    "sg:address":"74",
    "sg:city":"Vloeiende 2950 Kapellen",
    "sg:classifiers":[
        {
            "category":"Building & Trades",
            "subcategory":"Construction",
            "type":"Services"
        }
    ],
    "sg:phone":"+32 3 664 46 32",
    "sg:postcode":"74",
    "sg:tags":[
        "work",
        "public"
    ],
    "wof:name":"Quireyns Bvba",
    "wof:placetype":"venue"
},
  "geometry": {"coordinates":[4.4260931015,51.2933731079],"type":"Point"}
}