{
  "type": "Feature",
  "properties": {
    "addr:full":"Beenhouwerstraat 20 Willebroek Antwerpen 2830",
    "addr:housenumber":"20",
    "addr:postcode":"2830",
    "addr:street":"Beenhouwerstraat",
    "iso:country":"BE",
    "sg:address":"Beenhouwerstraat 20",
    "sg:city":"Willebroek",
    "sg:orig_category":"Eleveurs de bovins",
    "sg:phone":"+32 3 886 99 64",
    "sg:postcode":"2830",
    "sg:province":"Antwerpen",
    "wof:name":"Harry Peeters",
    "wof:placetype":"venue"
},
  "geometry": {"coordinates":[4.4054899216,51.0621376038],"type":"Point"}
}