{
  "type": "Feature",
  "properties": {
    "addr:full":"Rue Charles Sambon 16 Wavre Brabant Wallon 1300",
    "addr:housenumber":"16;1300",
    "addr:street":"Rue Charles Sambon",
    "iso:country":"BE",
    "sg:address":"Rue Charles Sambon 16",
    "sg:city":"Wavre",
    "sg:classifiers":[
        {
            "category":"Travel",
            "subcategory":"Travel Agent",
            "type":"Entertainment"
        }
    ],
    "sg:phone":"+32 10 24 49 40",
    "sg:postcode":"1300",
    "sg:province":"Brabant Wallon",
    "sg:tags":[
        "agency"
    ],
    "wof:name":"Nouvelles Fronti\u00e8res",
    "wof:placetype":"venue"
},
  "geometry": {"coordinates":[4.6109991074,50.716342926],"type":"Point"}
}