{
  "type": "Feature",
  "properties": {
    "addr:full":"Rue D'angleur 94 Esneux Li\u00e8ge 4130",
    "addr:housenumber":"94",
    "addr:postcode":"4130",
    "addr:street":"Rue D'Angleur",
    "iso:country":"BE",
    "sg:address":"Rue D'angleur 94",
    "sg:city":"Esneux",
    "sg:orig_category":"Bloemen and planten Tuinen",
    "sg:phone":"+32 4 388 14 79",
    "sg:postcode":"4130",
    "sg:province":"Li\u00e8ge",
    "wof:name":"P\u00c9pini\u00c8res De Tillf",
    "wof:placetype":"venue"
},
  "geometry": {"coordinates":[5.5993161201,50.5749206543],"type":"Point"}
}