{
  "type": "Feature",
  "properties": {
    "addr:full":"Hovestraat 45 Edegem Antwerpen 2650",
    "addr:housenumber":"45",
    "addr:postcode":"2650",
    "addr:street":"Hovestraat",
    "iso:country":"BE",
    "sg:address":"Hovestraat 45",
    "sg:city":"Edegem",
    "sg:orig_category":"Brood, gebak and snoepgoed",
    "sg:phone":"+32 3 457 05 68",
    "sg:postcode":"2650",
    "sg:province":"Antwerpen",
    "wof:name":"Convents Bakkerij",
    "wof:placetype":"venue"
},
  "geometry": {"coordinates":[4.448674202,51.1555938721],"type":"Point"}
}