{
  "type": "Feature",
  "properties": {
    "addr:full":"Rue Des Comtes De Luxembourg 41 Durbuy Luxembourg 6940",
    "addr:housenumber":"41",
    "addr:postcode":"6940",
    "addr:street":"Rue Des Comtes De Luxembourg",
    "iso:country":"BE",
    "sg:address":"Rue Des Comtes De Luxembourg 41",
    "sg:city":"Durbuy",
    "sg:orig_category":"Hotels Restaurants Ruimtes voor conferenties, recepties and feesten",
    "sg:phone":"+32 86 21 39 95",
    "sg:postcode":"6940",
    "sg:province":"Luxembourg",
    "wof:name":"Hotel Tropical",
    "wof:placetype":"venue"
},
  "geometry": {"coordinates":[5.4655041695,50.3456306458],"type":"Point"}
}