{
  "type": "Feature",
  "properties": {
    "addr:full":"Roeselarestraat 18 Wevelgem West-Vlaanderen 8560",
    "addr:housenumber":"18",
    "addr:postcode":"8560",
    "addr:street":"Roeselarestraat",
    "iso:country":"BE",
    "sg:address":"Roeselarestraat 18",
    "sg:city":"Wevelgem",
    "sg:orig_category":"Slagers",
    "sg:phone":"+32 56 42 20 56",
    "sg:postcode":"8560",
    "sg:province":"West-Vlaanderen",
    "wof:name":"Bij Ignace",
    "wof:placetype":"venue"
},
  "geometry": {"coordinates":[3.1810541153,50.811340332],"type":"Point"}
}