{
  "type": "Feature",
  "properties": {
    "iso:country":"BE",
    "sg:address":"Rue Emile Cornez 52",
    "sg:city":"Dour",
    "sg:classifiers":[
        {
            "category":"Health Services",
            "subcategory":"Nursing And Care Facility",
            "type":"Services"
        }
    ],
    "sg:phone":"+32 65 65 98 01",
    "sg:postcode":"7370",
    "sg:province":"Hainaut",
    "sg:tags":[
        "home"
    ],
    "wof:name":"Harmegnies G",
    "wof:placetype":"venue"
},
  "geometry": {"coordinates":[3.7720201015,50.4023475647],"type":"Point"}
}