{
  "type": "Feature",
  "properties": {
    "iso:country":"BE",
    "sg:address":"Delaeystraat 48",
    "sg:city":"Hooglede",
    "sg:orig_category":"Mat\u00e9riaux de construction Gr",
    "sg:phone":"+32 51 70 55 20",
    "sg:postcode":"8830",
    "sg:province":"West-Vlaanderen",
    "wof:name":"Devooght",
    "wof:placetype":"venue"
},
  "geometry": {"coordinates":[3.0337929726,50.9908103943],"type":"Point"}
}