{
  "type": "Feature",
  "properties": {
    "iso:country":"BE",
    "sg:address":"Frambozenstraat 7",
    "sg:city":"Hasselt (kuringen)",
    "sg:classifiers":[
        {
            "category":"Banks & Credit Unions",
            "subcategory":"Investment Brokerage",
            "type":"Services"
        }
    ],
    "sg:phone":"+32 11 87 31 01",
    "sg:postcode":"3511",
    "sg:province":"Limburg",
    "sg:tags":[
        "auditor"
    ],
    "wof:name":"Corthouts D",
    "wof:placetype":"venue"
},
  "geometry": {"coordinates":[5.315530777,50.9510345459],"type":"Point"}
}