{
  "type": "Feature",
  "properties": {
    "iso:country":"BE",
    "sg:address":"Rue De L'ecluse 16",
    "sg:city":"Tournai",
    "sg:orig_category":"R\u00e9cup\u00e9ration de mati\u00e8res m\u00e9talliques recyclables and d\u00e9molisseurs de voitures. Entretien et r\u00e9parati",
    "sg:phone":"+32 69 21 01 47",
    "sg:postcode":"7540",
    "sg:province":"Hainaut",
    "wof:name":"Tournai-depannage",
    "wof:placetype":"venue"
},
  "geometry": {"coordinates":[3.3767828941,50.6262664795],"type":"Point"}
}