{
  "type": "Feature",
  "properties": {
    "iso:country":"BE",
    "sg:address":"Rue De La Flache 242",
    "sg:city":"La Louviere",
    "sg:orig_category":"Plomberie, chauffage and installations sanitaires",
    "sg:phone":"+32 64 22 43 80",
    "sg:postcode":"7100",
    "sg:province":"Hainaut",
    "wof:name":"Wandels",
    "wof:placetype":"venue"
},
  "geometry": {"coordinates":[4.2081108093,50.4858551025],"type":"Point"}
}