{
  "type": "Feature",
  "properties": {
    "iso:country":"BE",
    "sg:address":"Rue Des Sports 1",
    "sg:city":"L\u00e9glise (mellier)",
    "sg:orig_category":"Autombile concessionaires",
    "sg:phone":"+32 63 43 35 68",
    "sg:postcode":"6860",
    "sg:province":"Luxembourg",
    "wof:name":"Gar Philipin P",
    "wof:placetype":"venue"
},
  "geometry": {"coordinates":[5.5248599052,49.774269104],"type":"Point"}
}