{
  "type": "Feature",
  "properties": {
    "addr:full":"Rue De Diekirch 45 Arlon Luxembourg 6700",
    "addr:housenumber":"45",
    "addr:postcode":"6700",
    "addr:street":"Rue De Diekirch",
    "iso:country":"BE",
    "sg:address":"Rue De Diekirch 45",
    "sg:city":"Arlon",
    "sg:orig_category":"Magasins de r\u00e9parations d'articles personnels et m\u00e9nagers divers",
    "sg:phone":"+32 63 22 56 00",
    "sg:postcode":"6700",
    "sg:province":"Luxembourg",
    "wof:name":"Securilux",
    "wof:placetype":"venue"
},
  "geometry": {"coordinates":[5.8140888214,49.6853599548],"type":"Point"}
}