{
  "type": "Feature",
  "properties": {
    "iso:country":"BE",
    "sg:address":"Rue Longue Haie 23",
    "sg:city":"Elsene/ixelles",
    "sg:classifiers":[
        {
            "category":"Restaurant",
            "type":"Food & Drink"
        }
    ],
    "sg:phone":"+32 2 646 09 07",
    "sg:postcode":"1050",
    "sg:province":"Bruxelles-Capitale",
    "wof:name":"Le Ket De La Tartine",
    "wof:placetype":"venue"
},
  "geometry": {"coordinates":[4.3657932281,50.8361167908],"type":"Point"}
}