{
  "type": "Feature",
  "properties": {
    "addr:full":"Rue Jean Laurent 41 Musson 6778",
    "addr:housenumber":"41",
    "addr:postcode":"6778",
    "addr:street":"Rue Jean Laurent",
    "iso:country":"BE",
    "sg:address":"Rue Jean Laurent 41",
    "sg:city":"Musson",
    "sg:classifiers":[
        {
            "category":"Banks & Credit Unions",
            "subcategory":"Bank",
            "type":"Services"
        }
    ],
    "sg:phone":"+32 63 67 79 97",
    "sg:postcode":"6778",
    "wof:name":"Aslk-cger Bank",
    "wof:placetype":"venue"
},
  "geometry": {"coordinates":[6.4404702187,49.6756095886],"type":"Point"}
}