{
  "type": "Feature",
  "properties": {
    "iso:country":"BE",
    "sg:address":"Galgstraat 73",
    "sg:city":"Sint-pieters-leeuw",
    "sg:orig_category":"Bloemen and planten",
    "sg:phone":"+32 2 377 17 87",
    "sg:postcode":"1600",
    "sg:province":"Vlaams-Brabant",
    "wof:name":"Huis Zuunflor",
    "wof:placetype":"venue"
},
  "geometry": {"coordinates":[4.2635631561,50.7853240967],"type":"Point"}
}