{
  "type": "Feature",
  "properties": {
    "iso:country":"BE",
    "sg:address":"Avenue Emile Bossaert 7",
    "sg:city":"Koekelberg",
    "sg:orig_category":"M\u00e9decines alternatives. Instituts de beaut\u00e9",
    "sg:phone":"+32 2 414 76 18",
    "sg:postcode":"1081",
    "sg:province":"Bruxelles-Capitale",
    "wof:name":"Eric Vanmalder/e. Van Malder",
    "wof:placetype":"venue"
},
  "geometry": {"coordinates":[4.3189458847,50.8646507263],"type":"Point"}
}