{
  "type": "Feature",
  "properties": {
    "addr:full":"Geldmunt 2 Gent Oost-Vlaanderen 9000",
    "addr:housenumber":"2",
    "addr:postcode":"9000",
    "addr:street":"Geldmunt;Oost-Vlaanderen",
    "iso:country":"BE",
    "sg:address":"Geldmunt 2",
    "sg:city":"Gent",
    "sg:classifiers":[
        {
            "category":"Fast Food",
            "type":"Food & Drink"
        }
    ],
    "sg:phone":"+32 9 223 89 01",
    "sg:postcode":"9000",
    "sg:province":"Oost-Vlaanderen",
    "sg:tags":[
        "meeneem",
        "restaurant"
    ],
    "wof:name":"Pizzeria Al Castello",
    "wof:placetype":"venue"
},
  "geometry": {"coordinates":[3.7215321064,51.0572013855],"type":"Point"}
}