{
  "type": "Feature",
  "properties": {
    "addr:full":"Melkbos 8 Ninove Oost-Vlaanderen 9404",
    "addr:housenumber":"8",
    "addr:postcode":"9404",
    "addr:street":"Melkbos",
    "iso:country":"BE",
    "sg:address":"Melkbos 8",
    "sg:city":"Ninove",
    "sg:orig_category":"Installation de menuiserie en bois and plastique. Peinture. Fabrication and montage de mobilier. Rev",
    "sg:phone":"+32 54 33 12 26",
    "sg:postcode":"9404",
    "sg:province":"Oost-Vlaanderen",
    "wof:name":"Herman De Rouck",
    "wof:placetype":"venue"
},
  "geometry": {"coordinates":[3.9570000172,50.8419036865],"type":"Point"}
}