{
  "type": "Feature",
  "properties": {
    "addr:full":"L Gevaertstraat 66 Mortsel Antwerpen 2640",
    "addr:housenumber":"66",
    "addr:postcode":"2640",
    "addr:street":"L Gevaertstraat",
    "iso:country":"BE",
    "sg:address":"L Gevaertstraat 66",
    "sg:city":"Mortsel",
    "sg:orig_category":"Verlichting and huishoudartikelen",
    "sg:phone":"+32 3 440 51 06",
    "sg:postcode":"2640",
    "sg:province":"Antwerpen",
    "wof:name":"Verreyke H",
    "wof:placetype":"venue"
},
  "geometry": {"coordinates":[4.4430170059,51.1761550903],"type":"Point"}
}