{
  "type": "Feature",
  "properties": {
    "iso:country":"BE",
    "sg:address":"Wiezelo 15",
    "sg:city":"Wuustwezel",
    "sg:classifiers":[
        {
            "category":"Professional",
            "subcategory":"Art Services",
            "type":"Services"
        }
    ],
    "sg:phone":"+32 3 633 35 62",
    "sg:postcode":"2990",
    "sg:province":"Antwerpen",
    "sg:tags":[
        "realization",
        "audio-visual"
    ],
    "wof:name":"Final Draft",
    "wof:placetype":"venue"
},
  "geometry": {"coordinates":[4.5525541306,51.3565254211],"type":"Point"}
}