{
  "type": "Feature",
  "properties": {
    "addr:full":"Parklaan 104 Sint-niklaas Oost-Vlaanderen 9100",
    "addr:housenumber":"104",
    "addr:postcode":"9100",
    "addr:street":"Parklaan",
    "iso:country":"BE",
    "sg:address":"Parklaan 104",
    "sg:city":"Sint-niklaas",
    "sg:orig_category":"Banken and kredietinstellingen",
    "sg:phone":"+32 3 776 49 91",
    "sg:postcode":"9100",
    "sg:province":"Oost-Vlaanderen",
    "wof:name":"Fortis",
    "wof:placetype":"venue"
},
  "geometry": {"coordinates":[4.1542978287,51.156375885],"type":"Point"}
}