{
  "type": "Feature",
  "properties": {
    "addr:full":"Rue Saint-quentin 5 Enghien Hainaut 7850",
    "addr:housenumber":"5",
    "addr:postcode":"7850",
    "addr:street":"Rue Saint-Quentin",
    "iso:country":"BE",
    "sg:address":"Rue Saint-quentin 5",
    "sg:city":"Enghien",
    "sg:classifiers":[
        {
            "category":"Health Services",
            "subcategory":"Doctor",
            "type":"Services"
        }
    ],
    "sg:phone":"+32 2 395 73 09",
    "sg:postcode":"7850",
    "sg:province":"Hainaut",
    "sg:tags":[
        "medicinephysicians",
        "surgeon"
    ],
    "wof:name":"Dewavre L\u00e9on",
    "wof:placetype":"venue"
},
  "geometry": {"coordinates":[4.0435218811,50.694442749],"type":"Point"}
}