{
  "type": "Feature",
  "properties": {
    "addr:full":"Kinstraat 6ba Riemst Limburg 3770",
    "addr:housenumber":"6ba",
    "addr:postcode":"3770",
    "addr:street":"Kinstraat",
    "iso:country":"BE",
    "sg:address":"Kinstraat 6ba",
    "sg:city":"Riemst",
    "sg:classifiers":[
        {
            "category":"Restaurant",
            "type":"Food & Drink"
        }
    ],
    "sg:phone":"+32 12 45 60 16",
    "sg:postcode":"3770",
    "sg:province":"Limburg",
    "sg:tags":[
        "caf\u00e9s"
    ],
    "wof:name":"Taverne Cheers",
    "wof:placetype":"venue"
},
  "geometry": {"coordinates":[5.5898852348,50.8329315186],"type":"Point"}
}