{
  "type": "Feature",
  "properties": {
    "iso:country":"BE",
    "sg:address":"Kamershoek 143",
    "sg:city":"Zele",
    "sg:orig_category":"Entretien and r\u00e9parations de voitures",
    "sg:phone":"+32 52 44 71 55",
    "sg:postcode":"9240",
    "sg:province":"Oost-Vlaanderen",
    "wof:name":"Juliaan Buerms",
    "wof:placetype":"venue"
},
  "geometry": {"coordinates":[4.0103459358,51.0437507629],"type":"Point"}
}