{
  "type": "Feature",
  "properties": {
    "addr:full":"Edegemsestraat 191 Mortsel Antwerpen 2640",
    "addr:housenumber":"191",
    "addr:postcode":"2640",
    "addr:street":"Edegemsestraat",
    "iso:country":"BE",
    "sg:address":"Edegemsestraat 191",
    "sg:city":"Mortsel",
    "sg:classifiers":[
        {
            "category":"Retail",
            "subcategory":"Auto Repair",
            "type":"Services"
        }
    ],
    "sg:phone":"+32 3 449 32 26",
    "sg:postcode":"2640",
    "sg:province":"Antwerpen",
    "sg:tags":[
        "garage"
    ],
    "wof:name":"Thielens-renault",
    "wof:placetype":"venue"
},
  "geometry": {"coordinates":[4.4446401596,51.1655464172],"type":"Point"}
}