{
  "type": "Feature",
  "properties": {
    "addr:full":"Rue Des Gen\u00eats 5 Esneux (tilff) Li\u00e8ge 4130",
    "addr:housenumber":"5",
    "addr:postcode":"4130",
    "addr:street":"Rue Des Gene\u0302Ts",
    "iso:country":"BE",
    "sg:address":"Rue Des Gen\u00eats 5",
    "sg:city":"Esneux (tilff)",
    "sg:classifiers":[
        {
            "category":"Insurance",
            "subcategory":"Insurance Agent",
            "type":"Services"
        }
    ],
    "sg:phone":"+32 4 388 32 77",
    "sg:postcode":"4130",
    "sg:province":"Li\u00e8ge",
    "sg:tags":[
        "broker"
    ],
    "wof:name":"Hossay M",
    "wof:placetype":"venue"
},
  "geometry": {"coordinates":[5.5795259476,50.5759468079],"type":"Point"}
}