{
  "type": "Feature",
  "properties": {
    "iso:country":"BE",
    "sg:address":"Hoogmolendijk 2",
    "sg:city":"Schoten",
    "sg:orig_category":"Travaux d'isolation. Installation de menuiserie m\u00e9tallique",
    "sg:phone":"+32 3 355 11 99",
    "sg:postcode":"2900",
    "sg:province":"Antwerpen",
    "wof:name":"P. & W.",
    "wof:placetype":"venue"
},
  "geometry": {"coordinates":[4.4913220406,51.2403106689],"type":"Point"}
}