{
  "type": "Feature",
  "properties": {
    "iso:country":"BE",
    "sg:address":"Zwaanhofweg 19",
    "sg:city":"Ieper",
    "sg:classifiers":[
        {
            "category":"Manufacturing",
            "subcategory":"Textiles",
            "type":"Manufacturing & Wholesale Goods"
        }
    ],
    "sg:phone":"+32 57 22 80 39",
    "sg:postcode":"8900",
    "sg:province":"West-Vlaanderen",
    "sg:tags":[
        "machinery"
    ],
    "wof:name":"T.m.c. Machinebouw",
    "wof:placetype":"venue"
},
  "geometry": {"coordinates":[2.8855280876,50.8741035461],"type":"Point"}
}