{
  "type": "Feature",
  "properties": {
    "iso:country":"BE",
    "sg:address":"Jef Peetersstraat 1b1",
    "sg:city":"Turnhout",
    "sg:orig_category":"M\u00e9decins and sp\u00e9cialistes",
    "sg:phone":"+32 14 41 55 38",
    "sg:postcode":"2300",
    "sg:province":"Antwerpen",
    "wof:name":"Jozef Poortmans",
    "wof:placetype":"venue"
},
  "geometry": {"coordinates":[4.9230680466,51.3227157593],"type":"Point"}
}