{
  "type": "Feature",
  "properties": {
    "iso:country":"BE",
    "sg:address":"Kloosterweg 27",
    "sg:city":"Aalst",
    "sg:orig_category":"Woningbouw",
    "sg:phone":"+32 53 21 58 33",
    "sg:postcode":"9300",
    "sg:province":"Oost-Vlaanderen",
    "wof:name":"Pijck Julien",
    "wof:placetype":"venue"
},
  "geometry": {"coordinates":[4.069683075,50.9271583557],"type":"Point"}
}