{
  "type": "Feature",
  "properties": {
    "iso:country":"BE",
    "sg:address":"Holven 30",
    "sg:city":"Geel",
    "sg:orig_category":"Locations de machines and \u00e9quipement pour la construction. D\u00e9molition d\u00b4immeubles and terrassements.",
    "sg:phone":"+32 14 58 96 34",
    "sg:postcode":"2440",
    "sg:province":"Antwerpen",
    "wof:name":"Cuypers Karel",
    "wof:placetype":"venue"
},
  "geometry": {"coordinates":[4.9857749939,51.1699104309],"type":"Point"}
}