{
  "type": "Feature",
  "properties": {
    "iso:country":"BE",
    "sg:address":"Avenue E.herman 400",
    "sg:city":"Bois-d'haine",
    "sg:orig_category":"Royal Canin. Animaux domestiques and accessoires. Articles de jardin",
    "sg:phone":"+32 64 22 38 22",
    "sg:postcode":"7170",
    "sg:province":"Hainaut",
    "wof:name":"Aveve Hobby Vert",
    "wof:placetype":"venue"
},
  "geometry": {"coordinates":[-80.4158630371,38.6953582764],"type":"Point"}
}