{
  "type": "Feature",
  "properties": {
    "iso:country":"BE",
    "sg:address":"Vliegveld 31",
    "sg:city":"Wevelgem",
    "sg:classifiers":[
        {
            "category":"Retail",
            "subcategory":"Car Wash",
            "type":"Services"
        }
    ],
    "sg:phone":"+32 56 40 31 57",
    "sg:postcode":"8560",
    "sg:province":"West-Vlaanderen",
    "sg:tags":[
        "polishing",
        "product",
        "cleaning"
    ],
    "wof:name":"C.t.s. Nv",
    "wof:placetype":"venue"
},
  "geometry": {"coordinates":[3.2028779984,50.8178710938],"type":"Point"}
}