{
  "type": "Feature",
  "properties": {
    "addr:full":"Doornkouterstraat 10 Zonnebeke (passendale) West-Vlaanderen 8980",
    "addr:housenumber":"10",
    "addr:postcode":"8980",
    "addr:street":"Doornkouterstraat",
    "iso:country":"BE",
    "sg:address":"Doornkouterstraat 10",
    "sg:city":"Zonnebeke (passendale)",
    "sg:classifiers":[
        {
            "category":"Farming",
            "subcategory":"Crops",
            "type":"Manufacturing & Wholesale Goods"
        }
    ],
    "sg:phone":"+32 51 77 81 71",
    "sg:postcode":"8980",
    "sg:province":"West-Vlaanderen",
    "sg:tags":[
        "vegetable",
        "fruit",
        "-",
        "grower"
    ],
    "wof:name":"Nollet F",
    "wof:placetype":"venue"
},
  "geometry": {"coordinates":[2.9872550964,50.8730812073],"type":"Point"}
}