{
  "type": "Feature",
  "properties": {
    "addr:full":"Bld Emile De Laveleye 132bb Li\u00c8ge Li\u00e8ge 4020",
    "addr:housenumber":"132bb",
    "addr:postcode":"4020",
    "addr:street":"Bld Emile De Laveleye",
    "iso:country":"BE",
    "sg:address":"Bld Emile De Laveleye 132bb",
    "sg:city":"Li\u00c8ge",
    "sg:orig_category":"RESTAURANTS: CAF\u00c9S",
    "sg:phone":"+32 4 343 04 00",
    "sg:postcode":"4020",
    "sg:province":"Li\u00e8ge",
    "wof:name":"Le Pub",
    "wof:placetype":"venue"
},
  "geometry": {"coordinates":[5.5910000801,50.6199302673],"type":"Point"}
}