{
  "type": "Feature",
  "properties": {
    "addr:full":"Burgemeester Callewaertlaan 134 Lichtervelde West-Vlaanderen 8810",
    "addr:housenumber":"134",
    "addr:postcode":"8810",
    "addr:street":"Burgemeester Callewaertlaan",
    "iso:country":"BE",
    "sg:address":"Burgemeester Callewaertlaan 134",
    "sg:city":"Lichtervelde",
    "sg:classifiers":[
        {
            "category":"Insurance",
            "subcategory":"Insurance Agent",
            "type":"Services"
        }
    ],
    "sg:phone":"+32 51 72 24 36",
    "sg:postcode":"8810",
    "sg:province":"West-Vlaanderen",
    "sg:tags":[
        "broker"
    ],
    "wof:name":"De Groote",
    "wof:placetype":"venue"
},
  "geometry": {"coordinates":[3.1292479038,51.0257339478],"type":"Point"}
}