{
  "type": "Feature",
  "properties": {
    "addr:full":"Lange Nieuwstraat 31b1 Antwerpen Antwerpen 2000",
    "addr:housenumber":"31b1",
    "addr:postcode":"2000",
    "addr:street":"Lange Nieuwstraat",
    "iso:country":"BE",
    "sg:address":"Lange Nieuwstraat 31b1",
    "sg:city":"Antwerpen",
    "sg:orig_category":"Boissons",
    "sg:phone":"+32 3 226 02 51",
    "sg:postcode":"2000",
    "sg:province":"Antwerpen",
    "wof:name":"Galtraco",
    "wof:placetype":"venue"
},
  "geometry": {"coordinates":[4.4077849388,51.2199478149],"type":"Point"}
}