{
  "type": "Feature",
  "properties": {
    "iso:country":"BE",
    "sg:address":"Rue Du Luxembourg 47-51",
    "sg:city":"Bruxelles (ixelles)",
    "sg:classifiers":[
        {
            "category":"Insurance",
            "subcategory":"Insurance Agent",
            "type":"Services"
        }
    ],
    "sg:phone":"+32 2 513 40 30",
    "sg:postcode":"1050",
    "sg:province":"Bruxelles-Capitale",
    "sg:tags":[
        "-",
        "representative"
    ],
    "wof:name":"Axa Art",
    "wof:placetype":"venue"
},
  "geometry": {"coordinates":[4.3716769218,50.8392562866],"type":"Point"}
}