{
  "type": "Feature",
  "properties": {
    "addr:full":"Dries 69b Aalst (nieuwerkerken) Oost-Vlaanderen 9320",
    "addr:housenumber":"69b",
    "addr:postcode":"9320",
    "addr:street":"Dries",
    "iso:country":"BE",
    "sg:address":"Dries 69b",
    "sg:city":"Aalst (nieuwerkerken)",
    "sg:classifiers":[
        {
            "category":"Manufacturing",
            "subcategory":"Building Materials",
            "type":"Manufacturing & Wholesale Goods"
        }
    ],
    "sg:phone":"+32 53 83 13 52",
    "sg:postcode":"9320",
    "sg:province":"Oost-Vlaanderen",
    "sg:tags":[
        "fixture",
        "store"
    ],
    "wof:name":"Vergalle Interieur Nv",
    "wof:placetype":"venue"
},
  "geometry": {"coordinates":[4.0553851128,50.9209976196],"type":"Point"}
}