{
  "type": "Feature",
  "properties": {
    "iso:country":"BE",
    "sg:address":"Sint-jansstraat 105",
    "sg:city":"Sint-laureins (sint-jan-in-eremo)",
    "sg:classifiers":[
        {
            "category":"Bars & Pubs",
            "type":"Food & Drink"
        }
    ],
    "sg:phone":"+32 9 379 96 18",
    "sg:postcode":"9982",
    "sg:province":"Oost-Vlaanderen",
    "sg:tags":[
        "tavern"
    ],
    "wof:name":"St-jans Gasthof",
    "wof:placetype":"venue"
},
  "geometry": {"coordinates":[3.5783209801,51.2710914612],"type":"Point"}
}