{
  "type": "Feature",
  "properties": {
    "addr:full":"Rue De Rosi\u00c8res 72 Rixensart Brabant Wallon 1332",
    "addr:housenumber":"72",
    "addr:postcode":"1332",
    "addr:street":"Rue De Rosie\u0300Res;Wallon",
    "iso:country":"BE",
    "sg:address":"Rue De Rosi\u00c8res 72",
    "sg:city":"Rixensart",
    "sg:orig_category":"Mat\u00e9riel m\u00e9dical and orthop\u00e9dique and proth\u00e8ses Fab",
    "sg:phone":"+32 2 654 12 71",
    "sg:postcode":"1332",
    "sg:province":"Brabant Wallon",
    "wof:name":"De Pauw",
    "wof:placetype":"venue"
},
  "geometry": {"coordinates":[4.5191240311,50.7248077393],"type":"Point"}
}