{
  "type": "Feature",
  "properties": {
    "addr:full":"Lijsterbeslaan 24 Brecht Antwerpen 2960",
    "addr:housenumber":"24",
    "addr:postcode":"2960",
    "addr:street":"Lijsterbeslaan",
    "iso:country":"BE",
    "sg:address":"Lijsterbeslaan 24",
    "sg:city":"Brecht",
    "sg:classifiers":[
        {
            "category":"Real Estate",
            "subcategory":"Architect",
            "type":"Services"
        }
    ],
    "sg:phone":"+32 3 636 02 32",
    "sg:postcode":"2960",
    "sg:province":"Antwerpen",
    "wof:name":"Moors G",
    "wof:placetype":"venue"
},
  "geometry": {"coordinates":[4.6415200233,51.3512115479],"type":"Point"}
}