{
  "type": "Feature",
  "properties": {
    "iso:country":"BE",
    "sg:address":"Rue Du Val-saint-lambert 245",
    "sg:city":"Seraing",
    "sg:orig_category":"Eclairage et \u00e9quipements du foyer. Souvenirs and objets artisanaux. Grossistes divers",
    "sg:phone":"+32 4 337 09 60",
    "sg:postcode":"4100",
    "sg:province":"Li\u00e8ge",
    "wof:name":"Christallerie Val-st.lambert",
    "wof:placetype":"venue"
},
  "geometry": {"coordinates":[5.4937901497,50.6035003662],"type":"Point"}
}