{
  "type": "Feature",
  "properties": {
    "iso:country":"BE",
    "sg:address":"Sint-sebastiaansstraat 4",
    "sg:city":"Brugge (sint-andries)",
    "sg:classifiers":[
        {
            "category":"Banks & Credit Unions",
            "subcategory":"Investment Brokerage",
            "type":"Services"
        }
    ],
    "sg:phone":"+32 50 39 56 94",
    "sg:postcode":"8200",
    "sg:province":"West-Vlaanderen",
    "sg:tags":[
        "incentive"
    ],
    "wof:name":"Deswaene M",
    "wof:placetype":"venue"
},
  "geometry": {"coordinates":[3.2034909725,51.2002944946],"type":"Point"}
}