{
  "type": "Feature",
  "properties": {
    "addr:full":"Schrijberg 101 Sint-niklaas (belsele) Oost-Vlaanderen 9111",
    "addr:housenumber":"101",
    "addr:postcode":"9111",
    "addr:street":"Schrijberg",
    "iso:country":"BE",
    "sg:address":"Schrijberg 101",
    "sg:city":"Sint-niklaas (belsele)",
    "sg:orig_category":"Oldtimers",
    "sg:phone":"+32 3 772 30 18",
    "sg:postcode":"9111",
    "sg:province":"Oost-Vlaanderen",
    "wof:name":"De Witte F",
    "wof:placetype":"venue"
},
  "geometry": {"coordinates":[4.068502903,51.1407051086],"type":"Point"}
}