{
  "type": "Feature",
  "properties": {
    "iso:country":"BE",
    "sg:address":"Rue De Gosselies 11-15",
    "sg:city":"Bruxelles (molenbeek-saint-jean)",
    "sg:orig_category":"Non-Classified Establishments",
    "sg:phone":"+32 2 523 01 84",
    "sg:postcode":"1080",
    "sg:province":"Bruxelles-Capitale",
    "wof:name":"Pelletier & Co Sa",
    "wof:placetype":"venue"
},
  "geometry": {"coordinates":[4.3317861557,50.8477058411],"type":"Point"}
}