{
  "type": "Feature",
  "properties": {
    "addr:full":"Meidoornstraat 24 Sint-katelijne-waver Antwerpen 2860",
    "addr:housenumber":"24",
    "addr:postcode":"2860",
    "addr:street":"Meidoornstraat",
    "iso:country":"BE",
    "sg:address":"Meidoornstraat 24",
    "sg:city":"Sint-katelijne-waver",
    "sg:orig_category":"Eleveurs d'animaux domestiques",
    "sg:phone":"+32 15 55 45 83",
    "sg:postcode":"2860",
    "sg:province":"Antwerpen",
    "wof:name":"Cattery Koeblai-khan",
    "wof:placetype":"venue"
},
  "geometry": {"coordinates":[4.5053110123,51.0444488525],"type":"Point"}
}