{
  "type": "Feature",
  "properties": {
    "iso:country":"BE",
    "sg:address":"Graslei 6",
    "sg:city":"Gent",
    "sg:classifiers":[
        {
            "category":"Arts & Performance",
            "subcategory":"Music",
            "type":"Entertainment"
        }
    ],
    "sg:phone":"+32 9 329 59 21",
    "sg:postcode":"9000",
    "sg:province":"Oost-Vlaanderen",
    "sg:tags":[
        "disc-jockeys"
    ],
    "wof:name":"Studio Splendid Discobar & Karaoke",
    "wof:placetype":"venue"
},
  "geometry": {"coordinates":[3.7208790779,51.054851532],"type":"Point"}
}