{
  "type": "Feature",
  "properties": {
    "iso:country":"BE",
    "sg:address":"Handelsstraat 10",
    "sg:city":"Veurne (steenkerke)",
    "sg:classifiers":[
        {
            "category":"Wholesale",
            "subcategory":"Vending Machines",
            "type":"Manufacturing & Wholesale Goods"
        }
    ],
    "sg:phone":"+32 58 31 56 80",
    "sg:postcode":"8630",
    "sg:province":"West-Vlaanderen",
    "sg:tags":[
        "-",
        "electric",
        "motor"
    ],
    "wof:name":"Ems Electro Motor Service Nv",
    "wof:placetype":"venue"
},
  "geometry": {"coordinates":[2.6852200031,51.0669136047],"type":"Point"}
}