{
  "type": "Feature",
  "properties": {
    "iso:country":"BE",
    "sg:address":"Wulverikstraat 24",
    "sg:city":"Kortrijk (bissegem)",
    "sg:classifiers":[
        {
            "category":"Arts & Performance",
            "subcategory":"Symphony",
            "type":"Entertainment"
        }
    ],
    "sg:phone":"+32 496 27 55 55",
    "sg:postcode":"8501",
    "sg:province":"West-Vlaanderen",
    "sg:tags":[
        "orchestra"
    ],
    "wof:name":"Master Of Arts",
    "wof:placetype":"venue"
},
  "geometry": {"coordinates":[3.235822916,50.8268547058],"type":"Point"}
}