{
  "type": "Feature",
  "properties": {
    "addr:full":"Rue De La V\u00e9rit\u00e9 22 Bruxelles (anderlecht) Bruxelles-Capitale 1070",
    "addr:housenumber":"22",
    "addr:postcode":"1070",
    "addr:street":"Rue De La Ve\u0301Rite\u0301",
    "iso:country":"BE",
    "sg:address":"Rue De La V\u00e9rit\u00e9 22",
    "sg:city":"Bruxelles (anderlecht)",
    "sg:classifiers":[
        {
            "category":"Health Services",
            "subcategory":"Health Practitioner",
            "type":"Services"
        }
    ],
    "sg:phone":"+32 2 520 64 84",
    "sg:postcode":"1070",
    "sg:province":"Bruxelles-Capitale",
    "sg:tags":[
        "physiotherapist"
    ],
    "wof:name":"De Vadder Linda & Ass Skcr Sprl",
    "wof:placetype":"venue"
},
  "geometry": {"coordinates":[4.3095870018,50.8391876221],"type":"Point"}
}