{
  "type": "Feature",
  "properties": {
    "addr:full":"Gentse Steenweg 54 Lokeren Oost-Vlaanderen 9160",
    "addr:housenumber":"54",
    "addr:postcode":"9160",
    "addr:street":"Gentse Steenweg",
    "iso:country":"BE",
    "sg:address":"Gentse Steenweg 54",
    "sg:city":"Lokeren",
    "sg:orig_category":"Instellingen voor mindervalide volwassenen",
    "sg:phone":"+32 9 348 53 34",
    "sg:postcode":"9160",
    "sg:province":"Oost-Vlaanderen",
    "wof:name":"De Sperwer",
    "wof:placetype":"venue"
},
  "geometry": {"coordinates":[3.9625320435,51.1109962463],"type":"Point"}
}