{
  "type": "Feature",
  "properties": {
    "addr:full":"Aalststraat 96 Oudenaarde Oost-Vlaanderen 9700",
    "addr:housenumber":"96",
    "addr:postcode":"9700",
    "addr:street":"Aalststraat",
    "iso:country":"BE",
    "sg:address":"Aalststraat 96",
    "sg:city":"Oudenaarde",
    "sg:orig_category":"Non-Classified Establishments",
    "sg:phone":"+32 55 31 86 00",
    "sg:postcode":"9700",
    "sg:province":"Oost-Vlaanderen",
    "wof:name":"Van Haver",
    "wof:placetype":"venue"
},
  "geometry": {"coordinates":[3.614759922,50.8401107788],"type":"Point"}
}