{
  "type": "Feature",
  "properties": {
    "iso:country":"BE",
    "sg:address":"Elshout 7",
    "sg:city":"Asse",
    "sg:orig_category":"Plantes and fleurs Fleurs and plantes",
    "sg:phone":"+32 2 452 89 38",
    "sg:postcode":"1730",
    "sg:province":"Vlaams-Brabant",
    "wof:name":"De Baerdemaeker",
    "wof:placetype":"venue"
},
  "geometry": {"coordinates":[4.1587262154,50.9031486511],"type":"Point"}
}