{
  "type": "Feature",
  "properties": {
    "iso:country":"BE",
    "sg:address":"Route De Nam\u00cache 12",
    "sg:city":"Eghezee",
    "sg:orig_category":"Enseignement maternel and primaire",
    "sg:phone":"+32 81 51 25 24",
    "sg:postcode":"5310",
    "sg:province":"Namur",
    "wof:name":"Ecole Fond. Communale",
    "wof:placetype":"venue"
},
  "geometry": {"coordinates":[4.9098110199,50.5599822998],"type":"Point"}
}