{
  "type": "Feature",
  "properties": {
    "iso:country":"BE",
    "sg:address":"Kaulillerweg 114",
    "sg:city":"Peer",
    "sg:orig_category":"Installation de menuiserie en bois and plastique",
    "sg:phone":"+32 11 63 35 13",
    "sg:postcode":"3990",
    "sg:province":"Limburg",
    "wof:name":"Lambert Janssen",
    "wof:placetype":"venue"
},
  "geometry": {"coordinates":[5.5129461288,51.1649131775],"type":"Point"}
}