{
  "type": "Feature",
  "properties": {
    "addr:full":"Noeverselaan 14 Boom Antwerpen 2850",
    "addr:housenumber":"14",
    "addr:postcode":"2850",
    "addr:street":"Noeverselaan",
    "iso:country":"BE",
    "sg:address":"Noeverselaan 14",
    "sg:city":"Boom",
    "sg:classifiers":[
        {
            "category":"Government",
            "subcategory":"Police Station",
            "type":"Public Place"
        }
    ],
    "sg:phone":"+32 3 888 00 13",
    "sg:postcode":"2850",
    "sg:province":"Antwerpen",
    "sg:tags":[
        "gendarmerie"
    ],
    "wof:name":"Federale Politie",
    "wof:placetype":"venue"
},
  "geometry": {"coordinates":[4.3663988113,51.1009559631],"type":"Point"}
}