{
  "type": "Feature",
  "properties": {
    "addr:full":"Rue Louis Jamme 36 Li\u00c8ge Li\u00e8ge 4020",
    "addr:housenumber":"36",
    "addr:postcode":"4020",
    "addr:street":"Rue Louis Jamme",
    "iso:country":"BE",
    "sg:address":"Rue Louis Jamme 36",
    "sg:city":"Li\u00c8ge",
    "sg:classifiers":[
        {
            "category":"Personal",
            "subcategory":"Beauty Salon",
            "type":"Services"
        }
    ],
    "sg:phone":"+32 4 343 89 52",
    "sg:postcode":"4020",
    "sg:province":"Li\u00e8ge",
    "sg:tags":[
        "de",
        "coiffure"
    ],
    "wof:name":"Art Et Coiffure",
    "wof:placetype":"venue"
},
  "geometry": {"coordinates":[5.5857920647,50.6381072998],"type":"Point"}
}