{
  "type": "Feature",
  "properties": {
    "iso:country":"BE",
    "sg:address":"Chauss\u00e9e De Philippeville 35",
    "sg:city":"Gerpinnes",
    "sg:classifiers":[
        {
            "category":"Education",
            "subcategory":"School",
            "type":"Public Place"
        }
    ],
    "sg:phone":"+32 71 36 57 83",
    "sg:postcode":"6280",
    "sg:province":"Hainaut",
    "sg:tags":[
        "secondary"
    ],
    "wof:name":"Institut Notre Dame De Loverval",
    "wof:placetype":"venue"
},
  "geometry": {"coordinates":[4.4702749252,50.3601760864],"type":"Point"}
}