{
  "type": "Feature",
  "properties": {
    "iso:country":"BE",
    "sg:address":"Oude Baan 143",
    "sg:city":"Diest",
    "sg:classifiers":[
        {
            "category":"Taxi",
            "type":"Transportation"
        }
    ],
    "sg:phone":"+32 13 52 38 10",
    "sg:postcode":"3290",
    "sg:province":"Vlaams-Brabant",
    "sg:tags":[
        "air"
    ],
    "wof:name":"Vhm Helicopter Services",
    "wof:placetype":"venue"
},
  "geometry": {"coordinates":[5.0646901131,50.9757614136],"type":"Point"}
}