{
  "type": "Feature",
  "properties": {
    "iso:country":"BE",
    "sg:address":"Hoogstraat 29",
    "sg:city":"Steenokkerzeel",
    "sg:orig_category":"Zuivelproducten",
    "sg:phone":"+32 16 65 09 64",
    "sg:postcode":"1820",
    "sg:province":"Vlaams-Brabant",
    "wof:name":"Emiel Uylenbroeck",
    "wof:placetype":"venue"
},
  "geometry": {"coordinates":[4.5030331612,50.9484786987],"type":"Point"}
}