{
  "type": "Feature",
  "properties": {
    "iso:country":"BE",
    "sg:address":"Vliegveldlaan 22",
    "sg:city":"Peer (kleine Brogel)",
    "sg:classifiers":[
        {
            "category":"Communications",
            "subcategory":"Television Station",
            "type":"Services"
        }
    ],
    "sg:phone":"+32 11 61 24 94",
    "sg:postcode":"3990",
    "sg:province":"Limburg",
    "sg:tags":[
        "report",
        "video"
    ],
    "wof:name":"De Schonkeren J",
    "wof:placetype":"venue"
},
  "geometry": {"coordinates":[5.4533009529,51.1329536438],"type":"Point"}
}