{
  "type": "Feature",
  "properties": {
    "iso:country":"BE",
    "sg:address":"Sint-jobsesteenweg 475b5",
    "sg:city":"Ukkel/uccle",
    "sg:orig_category":"Boekhouders",
    "sg:phone":"+32 2 375 72 87",
    "sg:postcode":"1180",
    "sg:province":"Bruxelles-Capitale",
    "wof:name":"Christophe Moulart",
    "wof:placetype":"venue"
},
  "geometry": {"coordinates":[4.3505401611,50.7918167114],"type":"Point"}
}