{
  "type": "Feature",
  "properties": {
    "addr:full":"Edinsesteenweg 364 Ninove Oost-Vlaanderen 9400",
    "addr:housenumber":"364",
    "addr:postcode":"9400",
    "addr:street":"Edinsesteenweg",
    "iso:country":"BE",
    "sg:address":"Edinsesteenweg 364",
    "sg:city":"Ninove",
    "sg:orig_category":"V\u00eatements",
    "sg:phone":"+32 54 34 48 43",
    "sg:postcode":"9400",
    "sg:province":"Oost-Vlaanderen",
    "wof:name":"Top Jeans",
    "wof:placetype":"venue"
},
  "geometry": {"coordinates":[4.0241699219,50.7991142273],"type":"Point"}
}