{
  "type": "Feature",
  "properties": {
    "iso:country":"BE",
    "sg:address":"Magdalenastraat 33",
    "sg:city":"Kontich",
    "sg:orig_category":"Avocats and conseillers juridiques",
    "sg:phone":"+32 3 458 47 47",
    "sg:postcode":"2550",
    "sg:province":"Antwerpen",
    "wof:name":"Nancy Peeters",
    "wof:placetype":"venue"
},
  "geometry": {"coordinates":[4.4470281601,51.1344795227],"type":"Point"}
}