{
  "type": "Feature",
  "properties": {
    "addr:full":"Molenstraat 63 Heusden-zolder (zolder) Limburg 3550",
    "addr:housenumber":"63",
    "addr:postcode":"3550",
    "addr:street":"Molenstraat",
    "iso:country":"BE",
    "sg:address":"Molenstraat 63",
    "sg:city":"Heusden-zolder (zolder)",
    "sg:classifiers":[
        {
            "category":"Shopping",
            "subcategory":"Antiques",
            "type":"Retail Goods"
        }
    ],
    "sg:phone":"+32 89 46 63 38",
    "sg:postcode":"3550",
    "sg:province":"Limburg",
    "wof:name":"Juvijns Antiek",
    "wof:placetype":"venue"
},
  "geometry": {"coordinates":[5.312256813,51.0274963379],"type":"Point"}
}