{
  "type": "Feature",
  "properties": {
    "addr:full":"Chauss\u00c9e D'enghien 10 Soignies Hainaut 7060",
    "addr:housenumber":"10",
    "addr:postcode":"7060",
    "addr:street":"Chausse\u0301E D'Enghien",
    "iso:country":"BE",
    "sg:address":"Chauss\u00c9e D'enghien 10",
    "sg:city":"Soignies",
    "sg:orig_category":"R\u00e9parations and entretien de motos. Motos. V\u00e9los",
    "sg:phone":"+32 67 33 32 94",
    "sg:postcode":"7060",
    "sg:province":"Hainaut",
    "wof:name":"Cycle. Ruelle",
    "wof:placetype":"venue"
},
  "geometry": {"coordinates":[4.067838192,50.5818138123],"type":"Point"}
}