{
  "type": "Feature",
  "properties": {
    "iso:country":"BE",
    "sg:address":"Kerkstraat 34",
    "sg:city":"Laakdal (forest)",
    "sg:classifiers":[
        {
            "category":"Freight",
            "type":"Transportation"
        }
    ],
    "sg:phone":"+32 13 66 25 92",
    "sg:postcode":"2430",
    "sg:province":"Antwerpen",
    "sg:tags":[
        "-",
        "transport"
    ],
    "wof:name":"Ribus F",
    "wof:placetype":"venue"
},
  "geometry": {"coordinates":[5.019174099,51.0751800537],"type":"Point"}
}