{
  "type": "Feature",
  "properties": {
    "addr:full":"Grote Baan 120 Sint-niklaas (nieuwkerken-waas) Oost-Vlaanderen 9100",
    "addr:housenumber":"120",
    "addr:postcode":"9100",
    "addr:street":"Grote Baan;Nieuwkerken-Waas",
    "iso:country":"BE",
    "sg:address":"Grote Baan 120",
    "sg:city":"Sint-niklaas (nieuwkerken-waas)",
    "sg:classifiers":[
        {
            "category":"Food & Beverages",
            "subcategory":"Farmers Market",
            "type":"Retail Goods"
        }
    ],
    "sg:phone":"+32 3 775 40 96",
    "sg:postcode":"9100",
    "sg:province":"Oost-Vlaanderen",
    "sg:tags":[
        "fried",
        "van",
        "potato"
    ],
    "wof:name":"Drowa Bvba",
    "wof:placetype":"venue"
},
  "geometry": {"coordinates":[4.2005839348,51.1861343384],"type":"Point"}
}