{
  "type": "Feature",
  "properties": {
    "addr:full":"Rue Des Marronniers 7 Villers-le-bouillet Li\u00e8ge 4530",
    "addr:housenumber":"7",
    "addr:postcode":"4530",
    "addr:street":"Rue Des Marronniers",
    "iso:country":"BE",
    "sg:address":"Rue Des Marronniers 7",
    "sg:city":"Villers-le-bouillet",
    "sg:classifiers":[
        {
            "category":"Government",
            "subcategory":"Post Office",
            "type":"Public Place"
        }
    ],
    "sg:phone":"+32 85 23 03 90",
    "sg:postcode":"4530",
    "sg:province":"Li\u00e8ge",
    "sg:tags":[
        "yoga"
    ],
    "wof:name":"Villers Yoga Club",
    "wof:placetype":"venue"
},
  "geometry": {"coordinates":[5.2660698891,50.5699043274],"type":"Point"}
}