{
  "type": "Feature",
  "properties": {
    "addr:full":"Gospertstrasse 85 Eupen Li\u00e8ge 4700",
    "addr:housenumber":"85",
    "addr:postcode":"4700",
    "addr:street":"Gospertstrasse",
    "iso:country":"BE",
    "sg:address":"Gospertstrasse 85",
    "sg:city":"Eupen",
    "sg:orig_category":"Apotheken",
    "sg:phone":"+32 87 74 24 66",
    "sg:postcode":"4700",
    "sg:province":"Li\u00e8ge",
    "wof:name":"Mertens Apotheek",
    "wof:placetype":"venue"
},
  "geometry": {"coordinates":[6.0367832184,50.6324996948],"type":"Point"}
}