{
  "type": "Feature",
  "properties": {
    "addr:full":"H. Hartlaan 138 Lokeren Oost-Vlaanderen 9160",
    "addr:housenumber":"138",
    "addr:postcode":"9160",
    "addr:street":"Hartlaan",
    "iso:country":"BE",
    "sg:address":"H. Hartlaan 138",
    "sg:city":"Lokeren",
    "sg:orig_category":"Textiel Verlichting and huishoudartikelen",
    "sg:phone":"+32 9 348 25 28",
    "sg:postcode":"9160",
    "sg:province":"Oost-Vlaanderen",
    "wof:name":"Huis Van Lent",
    "wof:placetype":"venue"
},
  "geometry": {"coordinates":[3.9891619682,51.0967407227],"type":"Point"}
}