{
  "type": "Feature",
  "properties": {
    "iso:country":"BE",
    "sg:address":"Forelstraat 27",
    "sg:city":"Gent",
    "sg:orig_category":"Drukkerijen and copyshops",
    "sg:phone":"+32 9 223 22 72",
    "sg:postcode":"9000",
    "sg:province":"Oost-Vlaanderen",
    "wof:name":"E.m.f.",
    "wof:placetype":"venue"
},
  "geometry": {"coordinates":[3.7403159142,51.0476837158],"type":"Point"}
}