{
  "type": "Feature",
  "properties": {
    "addr:full":"Rue De La Noire Bouteille 2 Seneffe Hainaut 7180",
    "addr:housenumber":"2",
    "addr:postcode":"7180",
    "addr:street":"Rue De La;Bouteille",
    "iso:country":"BE",
    "sg:address":"Rue De La Noire Bouteille 2",
    "sg:city":"Seneffe",
    "sg:orig_category":"Jardinage",
    "sg:phone":"+32 64 55 84 22",
    "sg:postcode":"7180",
    "sg:province":"Hainaut",
    "wof:name":"Jacquemotte D",
    "wof:placetype":"venue"
},
  "geometry": {"coordinates":[4.2711400986,50.5330581665],"type":"Point"}
}