{
  "type": "Feature",
  "properties": {
    "iso:country":"BE",
    "sg:address":"Dr\u00e8ve De Maison Bois 33",
    "sg:city":"Theux",
    "sg:classifiers":[
        {
            "category":"Building & Trades",
            "subcategory":"Pest Control",
            "type":"Services"
        }
    ],
    "sg:phone":"+32 87 22 83 62",
    "sg:postcode":"4910",
    "sg:province":"Li\u00e8ge",
    "sg:tags":[
        "painting",
        "contractor"
    ],
    "wof:name":"Waleffe L",
    "wof:placetype":"venue"
},
  "geometry": {"coordinates":[5.8637242317,50.5619926453],"type":"Point"}
}