{
  "type": "Feature",
  "properties": {
    "addr:full":"Aarschotsesteenweg 63 Tienen Vlaams-Brabant 3300",
    "addr:housenumber":"63",
    "addr:postcode":"3300",
    "addr:street":"Aarschotsesteenweg",
    "iso:country":"BE",
    "sg:address":"Aarschotsesteenweg 63",
    "sg:city":"Tienen",
    "sg:orig_category":"Grands magasins",
    "sg:phone":"+32 16 81 23 98",
    "sg:postcode":"3300",
    "sg:province":"Vlaams-Brabant",
    "wof:name":"Boogaerts",
    "wof:placetype":"venue"
},
  "geometry": {"coordinates":[4.9269199371,50.8164978027],"type":"Point"}
}