{
  "type": "Feature",
  "properties": {
    "iso:country":"BE",
    "sg:address":"Berlingmolenstraat 18",
    "sg:city":"Ardooie",
    "sg:orig_category":"Woningbouw",
    "sg:phone":"+32 51 74 81 53",
    "sg:postcode":"8850",
    "sg:province":"West-Vlaanderen",
    "wof:name":"Dierkens F",
    "wof:placetype":"venue"
},
  "geometry": {"coordinates":[3.2021319866,50.982421875],"type":"Point"}
}