{
  "type": "Feature",
  "properties": {
    "iso:country":"BE",
    "sg:address":"Gaasbeeksesteenweg 46",
    "sg:city":"Halle",
    "sg:classifiers":[
        {
            "category":"Cafe",
            "type":"Food & Drink"
        }
    ],
    "sg:phone":"+32 2 356 48 48",
    "sg:postcode":"1500",
    "sg:province":"Vlaams-Brabant",
    "sg:tags":[
        "caf\u00e9s"
    ],
    "wof:name":"Pascale Vandenhoeck",
    "wof:placetype":"venue"
},
  "geometry": {"coordinates":[4.229613781,50.743850708],"type":"Point"}
}