{
  "type": "Feature",
  "properties": {
    "addr:full":"Olmensebaan 40 Balen Antwerpen 2490",
    "addr:housenumber":"40",
    "addr:postcode":"2490",
    "addr:street":"Olmensebaan",
    "iso:country":"BE",
    "sg:address":"Olmensebaan 40",
    "sg:city":"Balen",
    "sg:orig_category":"Gespecialiseerde residenti\u00eble bouw",
    "sg:phone":"+32 14 31 67 03",
    "sg:postcode":"2490",
    "sg:province":"Antwerpen",
    "wof:name":"Jan Hens",
    "wof:placetype":"venue"
},
  "geometry": {"coordinates":[5.1372938156,51.1714324951],"type":"Point"}
}