{
  "type": "Feature",
  "properties": {
    "addr:full":"Eikestraat 10 Tervuren Vlaams-Brabant 3080",
    "addr:housenumber":"10",
    "addr:postcode":"3080",
    "addr:street":"Eikestraat",
    "iso:country":"BE",
    "sg:address":"Eikestraat 10",
    "sg:city":"Tervuren",
    "sg:orig_category":"M\u00e9decins and sp\u00e9cialistes",
    "sg:phone":"+32 2 767 47 54",
    "sg:postcode":"3080",
    "sg:province":"Vlaams-Brabant",
    "wof:name":"Ilse Van Gerven",
    "wof:placetype":"venue"
},
  "geometry": {"coordinates":[4.5059671402,50.8164787292],"type":"Point"}
}