{
  "type": "Feature",
  "properties": {
    "addr:full":"Rue Du Moulin 16 Etalle Luxembourg 6740",
    "addr:housenumber":"16",
    "addr:postcode":"6740",
    "addr:street":"Rue Du Moulin",
    "iso:country":"BE",
    "sg:address":"Rue Du Moulin 16",
    "sg:city":"Etalle",
    "sg:orig_category":"Muziekinstrumenten",
    "sg:phone":"+32 63 45 59 22",
    "sg:postcode":"6740",
    "sg:province":"Luxembourg",
    "wof:name":"L'atelier Du Piano",
    "wof:placetype":"venue"
},
  "geometry": {"coordinates":[5.6011657715,49.6739959717],"type":"Point"}
}