{
  "type": "Feature",
  "properties": {
    "iso:country":"BE",
    "sg:address":"Drieselstraat 5",
    "sg:city":"Gent (oostakker)",
    "sg:classifiers":[
        {
            "category":"Building & Trades",
            "subcategory":"Pest Control",
            "type":"Services"
        }
    ],
    "sg:phone":"+32 9 251 28 77",
    "sg:postcode":"9041",
    "sg:province":"Oost-Vlaanderen",
    "sg:tags":[
        "painting",
        "contractor"
    ],
    "wof:name":"Moenaert T",
    "wof:placetype":"venue"
},
  "geometry": {"coordinates":[3.7776958942,51.0978355408],"type":"Point"}
}