{
  "type": "Feature",
  "properties": {
    "iso:country":"BE",
    "sg:address":"Kerkstraat 1",
    "sg:city":"Hoogstraten",
    "sg:orig_category":"Banken and kredietinstellingen",
    "sg:phone":"+32 3 315 78 34",
    "sg:postcode":"2328",
    "sg:province":"Antwerpen",
    "wof:name":"Fortis",
    "wof:placetype":"venue"
},
  "geometry": {"coordinates":[4.8031578064,51.4739265442],"type":"Point"}
}