{
  "type": "Feature",
  "properties": {
    "iso:country":"BE",
    "sg:address":"Kapellekensbampsstraat 17",
    "sg:city":"Hasselt",
    "sg:classifiers":[
        {
            "category":"Arena",
            "subcategory":"Sports Club",
            "type":"Entertainment"
        }
    ],
    "sg:phone":"+32 11 27 46 56",
    "sg:postcode":"3500",
    "sg:province":"Limburg",
    "sg:tags":[
        "terrain",
        "hors",
        "de",
        "installation",
        "sportifs"
    ],
    "wof:name":"Runkster Tennisclub",
    "wof:placetype":"venue"
},
  "geometry": {"coordinates":[5.3170337677,50.9277076721],"type":"Point"}
}