{
  "type": "Feature",
  "properties": {
    "addr:full":"Rue De Calonne 120 Tournai Hainaut 7521",
    "addr:housenumber":"120",
    "addr:postcode":"7521",
    "addr:street":"Rue De Calonne",
    "iso:country":"BE",
    "sg:address":"Rue De Calonne 120",
    "sg:city":"Tournai",
    "sg:orig_category":"Animaux domestiques and accessoires",
    "sg:phone":"+32 69 84 17 36",
    "sg:postcode":"7521",
    "sg:province":"Hainaut",
    "wof:name":"Marc Parent",
    "wof:placetype":"venue"
},
  "geometry": {"coordinates":[3.4249870777,50.5871162415],"type":"Point"}
}