{
  "type": "Feature",
  "properties": {
    "addr:full":"Rue Hamal 63 Courcelles Hainaut 6180",
    "addr:housenumber":"63",
    "addr:postcode":"6180",
    "addr:street":"Rue Hamal",
    "iso:country":"BE",
    "sg:address":"Rue Hamal 63",
    "sg:city":"Courcelles",
    "sg:classifiers":[
        {
            "category":"Arena",
            "subcategory":"Sports Club",
            "type":"Entertainment"
        }
    ],
    "sg:phone":"+32 71 46 14 18",
    "sg:postcode":"6180",
    "sg:province":"Hainaut",
    "wof:name":"R.u.s. Courcelloise",
    "wof:placetype":"venue"
},
  "geometry": {"coordinates":[4.376180172,50.4796218872],"type":"Point"}
}