{
  "type": "Feature",
  "properties": {
    "iso:country":"BE",
    "sg:address":"Zandstraat 148",
    "sg:city":"Sint-gillis-waas",
    "sg:orig_category":"Gespecialiseerde residenti\u00eble bouw",
    "sg:phone":"+32 3 779 91 87",
    "sg:postcode":"9170",
    "sg:province":"Oost-Vlaanderen",
    "wof:name":"Charles Heirman",
    "wof:placetype":"venue"
},
  "geometry": {"coordinates":[4.0812802315,51.1997718811],"type":"Point"}
}