{
  "type": "Feature",
  "properties": {
    "addr:full":"Krommewege 82 Maldegem Oost-Vlaanderen 9990",
    "addr:housenumber":"82",
    "addr:postcode":"9990",
    "addr:street":"Krommewege",
    "iso:country":"BE",
    "sg:address":"Krommewege 82",
    "sg:city":"Maldegem",
    "sg:classifiers":[
        {
            "category":"Manufacturing",
            "subcategory":"Motor Vehicles & Parts",
            "type":"Manufacturing & Wholesale Goods"
        }
    ],
    "sg:phone":"+32 50 71 41 33",
    "sg:postcode":"9990",
    "sg:province":"Oost-Vlaanderen",
    "sg:tags":[
        "machine",
        "-",
        "indivisible",
        "transport"
    ],
    "wof:name":"Vermeulen Rudolf Bvba",
    "wof:placetype":"venue"
},
  "geometry": {"coordinates":[3.4703900814,51.1936912537],"type":"Point"}
}