{
  "type": "Feature",
  "properties": {
    "addr:full":"Alfons Jeurissenstraat 163 Diepenbeek Limburg 3590",
    "addr:housenumber":"163",
    "addr:postcode":"3590",
    "addr:street":"Alfons Jeurissenstraat",
    "iso:country":"BE",
    "sg:address":"Alfons Jeurissenstraat 163",
    "sg:city":"Diepenbeek",
    "sg:orig_category":"Entretien and r\u00e9parations de voitures",
    "sg:phone":"+32 11 32 23 60",
    "sg:postcode":"3590",
    "sg:province":"Limburg",
    "wof:name":"Garage Aldo",
    "wof:placetype":"venue"
},
  "geometry": {"coordinates":[5.4359378815,50.9329109192],"type":"Point"}
}