{
  "type": "Feature",
  "properties": {
    "addr:full":"Grotestraat 18 De Haan West-Vlaanderen 8420",
    "addr:housenumber":"18",
    "addr:postcode":"8420",
    "addr:street":"Grotestraat",
    "iso:country":"BE",
    "sg:address":"Grotestraat 18",
    "sg:city":"De Haan",
    "sg:orig_category":"Enseignement maternel and primaire",
    "sg:phone":"+32 59 23 57 26",
    "sg:postcode":"8420",
    "sg:province":"West-Vlaanderen",
    "wof:name":"Vrije Basisschool",
    "wof:placetype":"venue"
},
  "geometry": {"coordinates":[3.0357379913,51.2709922791],"type":"Point"}
}