{
  "type": "Feature",
  "properties": {
    "addr:full":"Tulpenlaan 19 Overijse Vlaams-Brabant 3090",
    "addr:housenumber":"19",
    "addr:postcode":"3090",
    "addr:street":"Tulpenlaan",
    "iso:country":"BE",
    "sg:address":"Tulpenlaan 19",
    "sg:city":"Overijse",
    "sg:classifiers":[
        {
            "category":"Health Services",
            "subcategory":"Health Practitioner",
            "type":"Services"
        }
    ],
    "sg:phone":"+32 2 657 20 58",
    "sg:postcode":"3090",
    "sg:province":"Vlaams-Brabant",
    "sg:tags":[
        "physiotherapist"
    ],
    "wof:name":"Cnudde Claudine",
    "wof:placetype":"venue"
},
  "geometry": {"coordinates":[4.4893369675,50.7960395813],"type":"Point"}
}