{
  "type": "Feature",
  "properties": {
    "iso:country":"BE",
    "sg:address":"Izegemsestraat 226",
    "sg:city":"Kortrijk",
    "sg:classifiers":[
        {
            "category":"Cafe",
            "type":"Food & Drink"
        }
    ],
    "sg:phone":"+32 56 36 02 11",
    "sg:postcode":"8500",
    "sg:province":"West-Vlaanderen",
    "sg:tags":[
        "caf\u00e9s"
    ],
    "wof:name":"Eric Neirinck",
    "wof:placetype":"venue"
},
  "geometry": {"coordinates":[3.2572340965,50.8414230347],"type":"Point"}
}