{
  "type": "Feature",
  "properties": {
    "iso:country":"BE",
    "sg:address":"Heulestraat 150",
    "sg:city":"Wevelgem (gullegem)",
    "sg:classifiers":[
        {
            "category":"Home & Garden",
            "subcategory":"Building Materials",
            "type":"Retail Goods"
        }
    ],
    "sg:phone":"+32 56 35 14 90",
    "sg:postcode":"8560",
    "sg:province":"West-Vlaanderen",
    "sg:tags":[
        "window"
    ],
    "wof:name":"Pyfferoen Bvba",
    "wof:placetype":"venue"
},
  "geometry": {"coordinates":[3.218724966,50.8428916931],"type":"Point"}
}