{
  "type": "Feature",
  "properties": {
    "addr:full":"Dijkstraat 63 Beveren (melsele) Oost-Vlaanderen 9120",
    "addr:housenumber":"63",
    "addr:postcode":"9120",
    "addr:street":"Dijkstraat",
    "iso:country":"BE",
    "sg:address":"Dijkstraat 63",
    "sg:city":"Beveren (melsele)",
    "sg:classifiers":[
        {
            "category":"Home & Garden",
            "subcategory":"Home Furnishings",
            "type":"Retail Goods"
        }
    ],
    "sg:phone":"+32 3 755 10 10",
    "sg:postcode":"9120",
    "sg:province":"Oost-Vlaanderen",
    "sg:tags":[
        "-",
        "freezer",
        "refrigerator"
    ],
    "wof:name":"De Ryck P",
    "wof:placetype":"venue"
},
  "geometry": {"coordinates":[4.2760128975,51.2269706726],"type":"Point"}
}