{
  "type": "Feature",
  "properties": {
    "iso:country":"BE",
    "sg:address":"Rue D'harscamp 58",
    "sg:city":"Li\u00e8ge 1 (li\u00e8ge 2)",
    "sg:classifiers":[
        {
            "category":"Professional",
            "subcategory":"Business Services",
            "type":"Services"
        }
    ],
    "sg:phone":"+32 4 342 59 00",
    "sg:postcode":"4020",
    "sg:province":"Li\u00e8ge",
    "sg:tags":[
        "bookkeeping"
    ],
    "wof:name":"Cofigeco",
    "wof:placetype":"venue"
},
  "geometry": {"coordinates":[5.5804710388,50.6330413818],"type":"Point"}
}