{
  "type": "Feature",
  "properties": {
    "addr:full":"Leuvensestraat 44 Leuven (kessel-lo) Vlaams-Brabant 3010",
    "addr:housenumber":"44",
    "addr:postcode":"3010",
    "addr:street":"Leuvensestraat",
    "iso:country":"BE",
    "sg:address":"Leuvensestraat 44",
    "sg:city":"Leuven (kessel-lo)",
    "sg:classifiers":[
        {
            "category":"Shopping",
            "subcategory":"Jewelry",
            "type":"Retail Goods"
        }
    ],
    "sg:phone":"+32 16 35 54 42",
    "sg:postcode":"3010",
    "sg:province":"Vlaams-Brabant",
    "sg:tags":[
        "jeweller",
        "-"
    ],
    "wof:name":"Skiriou",
    "wof:placetype":"venue"
},
  "geometry": {"coordinates":[4.7304501534,50.889755249],"type":"Point"}
}