{
  "type": "Feature",
  "properties": {
    "iso:country":"BE",
    "sg:address":"Rue De L'amercoeur 59",
    "sg:city":"Li\u00c8ge",
    "sg:orig_category":"Bruids- and ceremoniekledij",
    "sg:phone":"+32 4 343 50 74",
    "sg:postcode":"4020",
    "sg:province":"Li\u00e8ge",
    "wof:name":"Maison Carla",
    "wof:placetype":"venue"
},
  "geometry": {"coordinates":[5.590318203,50.6365814209],"type":"Point"}
}