{
  "type": "Feature",
  "properties": {
    "addr:full":"Voormezeledorp 12 Ieper West-Vlaanderen 8902",
    "addr:housenumber":"12",
    "addr:postcode":"8902",
    "addr:street":"Voormezeledorp",
    "iso:country":"BE",
    "sg:address":"Voormezeledorp 12",
    "sg:city":"Ieper",
    "sg:orig_category":"Installation de menuiserie en bois and plastique",
    "sg:phone":"+32 57 21 64 64",
    "sg:postcode":"8902",
    "sg:province":"West-Vlaanderen",
    "wof:name":"Vandendaele L.",
    "wof:placetype":"venue"
},
  "geometry": {"coordinates":[2.9219009876,50.8342857361],"type":"Point"}
}