{
  "type": "Feature",
  "properties": {
    "addr:full":"Emile Maxlaan 167 Schaarbeek/schaerbeek Bruxelles-Capitale 1030",
    "addr:housenumber":"167",
    "addr:postcode":"1030",
    "addr:street":"Emile Maxlaan",
    "iso:country":"BE",
    "sg:address":"Emile Maxlaan 167",
    "sg:city":"Schaarbeek/schaerbeek",
    "sg:orig_category":"Artsen and specialisten",
    "sg:phone":"+32 2 742 90 99",
    "sg:postcode":"1030",
    "sg:province":"Bruxelles-Capitale",
    "wof:name":"Alb\u00c9ric Fierens",
    "wof:placetype":"venue"
},
  "geometry": {"coordinates":[4.3995480537,50.8514900208],"type":"Point"}
}