{
  "type": "Feature",
  "properties": {
    "addr:full":"Kouterbaan 44 Sint-martens-latem Oost-Vlaanderen 9830",
    "addr:housenumber":"44",
    "addr:postcode":"9830",
    "addr:street":"Kouterbaan",
    "iso:country":"BE",
    "sg:address":"Kouterbaan 44",
    "sg:city":"Sint-martens-latem",
    "sg:orig_category":"Travaux d\u00b4installation divers",
    "sg:phone":"+32 9 282 53 78",
    "sg:postcode":"9830",
    "sg:province":"Oost-Vlaanderen",
    "wof:name":"Remotec",
    "wof:placetype":"venue"
},
  "geometry": {"coordinates":[3.6369349957,51.0141105652],"type":"Point"}
}