{
  "type": "Feature",
  "properties": {
    "iso:country":"BE",
    "sg:address":"Rue Ernest Solvay 475",
    "sg:city":"Li\u00e8ge 1 (sclessin)",
    "sg:classifiers":[
        {
            "category":"Professional",
            "subcategory":"Accounting & Tax Preparation",
            "type":"Services"
        }
    ],
    "sg:phone":"+32 4 234 97 79",
    "sg:postcode":"4000",
    "sg:province":"Li\u00e8ge",
    "sg:tags":[
        "bookkeeper"
    ],
    "wof:name":"Fabri T",
    "wof:placetype":"venue"
},
  "geometry": {"coordinates":[5.5399827957,50.6115722656],"type":"Point"}
}