{
  "type": "Feature",
  "properties": {
    "iso:country":"BE",
    "sg:address":"Gildestraat 11",
    "sg:city":"Landen (wange)",
    "sg:classifiers":[
        {
            "category":"Utilities",
            "subcategory":"Fuel Oil & Lpg",
            "type":"Services"
        }
    ],
    "sg:phone":"+32 16 78 80 71",
    "sg:postcode":"3400",
    "sg:province":"Vlaams-Brabant",
    "wof:name":"Jacobs W",
    "wof:placetype":"venue"
},
  "geometry": {"coordinates":[5.0236778259,50.7896842957],"type":"Point"}
}