{
  "type": "Feature",
  "properties": {
    "iso:country":"BE",
    "sg:address":"Chauss\u00e9e De Waremme 159",
    "sg:city":"Huy",
    "sg:classifiers":[
        {
            "category":"Communications",
            "subcategory":"Film & Video Production",
            "type":"Services"
        }
    ],
    "sg:phone":"+32 498 43 53 02",
    "sg:postcode":"4500",
    "sg:province":"Li\u00e8ge",
    "sg:tags":[
        "sound",
        "recording",
        "studio"
    ],
    "wof:name":"Bastianelli F",
    "wof:placetype":"venue"
},
  "geometry": {"coordinates":[5.2451720238,50.5358581543],"type":"Point"}
}