{
  "type": "Feature",
  "properties": {
    "addr:full":"Chauss\u00e9e De Namur 89 Wavre Brabant Wallon 1300",
    "addr:housenumber":"89;1300",
    "addr:street":"Chausse\u0301E De Namur",
    "iso:country":"BE",
    "sg:address":"Chauss\u00e9e De Namur 89",
    "sg:city":"Wavre",
    "sg:classifiers":[
        {
            "category":"Autos & Motor Vehicles",
            "subcategory":"Motorcycle Sales",
            "type":"Retail Goods"
        }
    ],
    "sg:phone":"+32 10 24 14 44",
    "sg:postcode":"1300",
    "sg:province":"Brabant Wallon",
    "sg:tags":[
        "motorbike"
    ],
    "wof:name":"Vanesse Moto",
    "wof:placetype":"venue"
},
  "geometry": {"coordinates":[4.6130661964,50.7116966248],"type":"Point"}
}