{
  "type": "Feature",
  "properties": {
    "addr:full":"Prins Leopoldlei 4 Mortsel Antwerpen 2640",
    "addr:housenumber":"4",
    "addr:postcode":"2640",
    "addr:street":"Prins Leopoldlei",
    "iso:country":"BE",
    "sg:address":"Prins Leopoldlei 4",
    "sg:city":"Mortsel",
    "sg:classifiers":[
        {
            "category":"Food & Beverages",
            "subcategory":"Fruits & Vegetables",
            "type":"Retail Goods"
        }
    ],
    "sg:phone":"+32 3 449 57 55",
    "sg:postcode":"2640",
    "sg:province":"Antwerpen",
    "sg:tags":[
        "l\u00e9gumes"
    ],
    "wof:name":"Huis Florus",
    "wof:placetype":"venue"
},
  "geometry": {"coordinates":[4.4547019005,51.1697845459],"type":"Point"}
}