{
  "type": "Feature",
  "properties": {
    "iso:country":"BE",
    "sg:address":"Rue De L\u00b4egalit\u00c9 43",
    "sg:city":"Mons",
    "sg:orig_category":"Installation de menuiserie m\u00e9tallique. Installation de menuiserie en bois and plastique",
    "sg:phone":"+32 65 33 85 02",
    "sg:postcode":"7020",
    "sg:province":"Hainaut",
    "wof:name":"Fe. Baltus Volets",
    "wof:placetype":"venue"
},
  "geometry": {"coordinates":[3.9553449154,50.4761772156],"type":"Point"}
}