{
  "type": "Feature",
  "properties": {
    "iso:country":"BE",
    "sg:address":"S. Vernieuwestraat 6",
    "sg:city":"Blankenberge",
    "sg:classifiers":[
        {
            "category":"Insurance",
            "subcategory":"Insurance Agent",
            "type":"Services"
        }
    ],
    "sg:phone":"+32 50 41 44 56",
    "sg:postcode":"8370",
    "sg:province":"West-Vlaanderen",
    "sg:tags":[
        "broker"
    ],
    "wof:name":"Argenta",
    "wof:placetype":"venue"
},
  "geometry": {"coordinates":[3.1265621185,51.313835144],"type":"Point"}
}