{
  "type": "Feature",
  "properties": {
    "addr:full":"Avenue Baden Powell 3 Bruxelles (woluwe-saint-lambert) Bruxelles-Capitale 1200",
    "addr:housenumber":"3",
    "addr:postcode":"1200",
    "addr:street":"Avenue Baden Powell",
    "iso:country":"BE",
    "sg:address":"Avenue Baden Powell 3",
    "sg:city":"Bruxelles (woluwe-saint-lambert)",
    "sg:classifiers":[
        {
            "category":"Health Services",
            "subcategory":"Health Practitioner",
            "type":"Services"
        }
    ],
    "sg:phone":"+32 2 770 74 15",
    "sg:postcode":"1200",
    "sg:province":"Bruxelles-Capitale",
    "sg:tags":[
        "physiotherapist"
    ],
    "wof:name":"Remy A",
    "wof:placetype":"venue"
},
  "geometry": {"coordinates":[4.429708004,50.844543457],"type":"Point"}
}