{
  "type": "Feature",
  "properties": {
    "iso:country":"BE",
    "sg:address":"Sportweg 1",
    "sg:city":"Stabroek",
    "sg:classifiers":[
        {
            "category":"Cafe",
            "type":"Food & Drink"
        }
    ],
    "sg:phone":"+32 3 568 99 77",
    "sg:postcode":"2940",
    "sg:province":"Antwerpen",
    "sg:tags":[
        "caf\u00e9s"
    ],
    "wof:name":"Heirman-van Hoorick",
    "wof:placetype":"venue"
},
  "geometry": {"coordinates":[4.3683748245,51.3347511292],"type":"Point"}
}