{
  "type": "Feature",
  "properties": {
    "iso:country":"BE",
    "sg:address":"Gitsestraat 364",
    "sg:city":"Roeselare",
    "sg:orig_category":"Entretien and r\u00e9parations de voitures",
    "sg:phone":"+32 51 22 76 95",
    "sg:postcode":"8800",
    "sg:province":"West-Vlaanderen",
    "wof:name":"Danny Vincke",
    "wof:placetype":"venue"
},
  "geometry": {"coordinates":[3.1172320843,50.9634475708],"type":"Point"}
}