{
  "type": "Feature",
  "properties": {
    "iso:country":"BE",
    "sg:address":"Noordzandstraat 9",
    "sg:city":"Brugge",
    "sg:orig_category":"Lingerie and ondergoed Textiel Verlichting and huishoudartikelen",
    "sg:phone":"+32 50 33 58 08",
    "sg:postcode":"8000",
    "sg:province":"West-Vlaanderen",
    "wof:name":"Huis Picco Bello",
    "wof:placetype":"venue"
},
  "geometry": {"coordinates":[3.2211630344,51.2081108093],"type":"Point"}
}