{
  "type": "Feature",
  "properties": {
    "iso:country":"BE",
    "sg:address":"Rue Des Ecoles 19",
    "sg:city":"Le Roeulx",
    "sg:orig_category":"Eleveurs de bovins",
    "sg:phone":"+32 64 66 25 67",
    "sg:postcode":"7070",
    "sg:province":"Hainaut",
    "wof:name":"Willy Bouret",
    "wof:placetype":"venue"
},
  "geometry": {"coordinates":[4.0928559303,50.4749488831],"type":"Point"}
}