{
  "type": "Feature",
  "properties": {
    "iso:country":"BE",
    "sg:address":"Steenstraat 170",
    "sg:city":"Lede",
    "sg:classifiers":[
        {
            "category":"Home & Garden",
            "subcategory":"Building Materials",
            "type":"Retail Goods"
        }
    ],
    "sg:phone":"+32 53 77 16 04",
    "sg:postcode":"9340",
    "sg:province":"Oost-Vlaanderen",
    "sg:tags":[
        "window"
    ],
    "wof:name":"Van Wesemael G",
    "wof:placetype":"venue"
},
  "geometry": {"coordinates":[4.0111727715,50.9629135132],"type":"Point"}
}