{
  "type": "Feature",
  "properties": {
    "addr:full":"Sint-gillislaan 169 Dendermonde Oost-Vlaanderen 9200",
    "addr:housenumber":"169",
    "addr:postcode":"9200",
    "addr:street":"Sint-Gillislaan;Oost-Vlaanderen",
    "iso:country":"BE",
    "sg:address":"Sint-gillislaan 169",
    "sg:city":"Dendermonde",
    "sg:classifiers":[
        {
            "category":"Health Services",
            "subcategory":"Dentist",
            "type":"Services"
        }
    ],
    "sg:phone":"+32 52 21 24 28",
    "sg:postcode":"9200",
    "sg:province":"Oost-Vlaanderen",
    "wof:name":"Decaestecker A",
    "wof:placetype":"venue"
},
  "geometry": {"coordinates":[4.1122970581,51.0181617737],"type":"Point"}
}