{
  "type": "Feature",
  "properties": {
    "iso:country":"BE",
    "sg:address":"Avenue Colonel Picquart 65",
    "sg:city":"Bruxelles (schaerbeek)",
    "sg:classifiers":[
        {
            "category":"Retail",
            "subcategory":"Auto Repair",
            "type":"Services"
        }
    ],
    "sg:phone":"+32 2 245 12 99",
    "sg:postcode":"1030",
    "sg:province":"Bruxelles-Capitale",
    "sg:tags":[
        "automobile",
        "-",
        "wrecking"
    ],
    "wof:name":"Auto-enl\u00e8vement",
    "wof:placetype":"venue"
},
  "geometry": {"coordinates":[4.3835167885,50.8774642944],"type":"Point"}
}