{
  "type": "Feature",
  "properties": {
    "iso:country":"BE",
    "sg:address":"Avenue De Mersch 303",
    "sg:city":"Arlon",
    "sg:orig_category":"Entretien and r\u00e9parations de voitures",
    "sg:phone":"+32 63 22 57 71",
    "sg:postcode":"6700",
    "sg:province":"Luxembourg",
    "wof:name":"Garage Scattolo",
    "wof:placetype":"venue"
},
  "geometry": {"coordinates":[5.8407897949,49.6921463013],"type":"Point"}
}