{
  "type": "Feature",
  "properties": {
    "addr:full":"Klein Broekstraat 32 Linter Vlaams-Brabant 3350",
    "addr:housenumber":"32",
    "addr:postcode":"3350",
    "addr:street":"Klein Broekstraat;Vlaams-Brabant",
    "iso:country":"BE",
    "sg:address":"Klein Broekstraat 32",
    "sg:city":"Linter",
    "sg:orig_category":"Schoonheidssalons",
    "sg:phone":"+32 16 78 98 49",
    "sg:postcode":"3350",
    "sg:province":"Vlaams-Brabant",
    "wof:name":"Deldime L",
    "wof:placetype":"venue"
},
  "geometry": {"coordinates":[5.0232439041,50.811088562],"type":"Point"}
}