{
  "type": "Feature",
  "properties": {
    "iso:country":"BE",
    "sg:address":"Markt 6",
    "sg:city":"Geraardsbergen",
    "sg:classifiers":[
        {
            "category":"Cafe",
            "type":"Food & Drink"
        }
    ],
    "sg:phone":"+32 54 41 60 61",
    "sg:postcode":"9500",
    "sg:province":"Oost-Vlaanderen",
    "sg:tags":[
        "caf\u00e9s"
    ],
    "wof:name":"Paul Van Liefferinge",
    "wof:placetype":"venue"
},
  "geometry": {"coordinates":[3.8826959133,50.7724609375],"type":"Point"}
}