{
  "type": "Feature",
  "properties": {
    "addr:full":"Stokerijstraat 100 Wijnegem Antwerpen 2110",
    "addr:housenumber":"100",
    "addr:postcode":"2110",
    "addr:street":"Stokerijstraat",
    "iso:country":"BE",
    "sg:address":"Stokerijstraat 100",
    "sg:city":"Wijnegem",
    "sg:orig_category":"Boekhouders",
    "sg:phone":"+32 3 353 95 36",
    "sg:postcode":"2110",
    "sg:province":"Antwerpen",
    "wof:name":"Marc Dierckx",
    "wof:placetype":"venue"
},
  "geometry": {"coordinates":[4.5413827896,51.2247314453],"type":"Point"}
}