{
  "type": "Feature",
  "properties": {
    "addr:full":"G. Van Der Steenstraat 123 Lennik Vlaams-Brabant 1750",
    "addr:housenumber":"123;1750",
    "addr:street":"G. Van Der Steenstraat;Vlaams-Brabant",
    "iso:country":"BE",
    "sg:address":"G. Van Der Steenstraat 123",
    "sg:city":"Lennik",
    "sg:classifiers":[
        {
            "category":"Cafe",
            "type":"Food & Drink"
        }
    ],
    "sg:phone":"+32 2 532 47 53",
    "sg:postcode":"1750",
    "sg:province":"Vlaams-Brabant",
    "sg:tags":[
        "caf\u00e9s"
    ],
    "wof:name":"Alain Fleurus",
    "wof:placetype":"venue"
},
  "geometry": {"coordinates":[4.1545958519,50.799079895],"type":"Point"}
}