{
  "type": "Feature",
  "properties": {
    "addr:full":"Bedrifsstraat 14 Hasselt Limburg 3500",
    "addr:housenumber":"14",
    "addr:postcode":"3500",
    "addr:street":"Bedrifsstraat",
    "iso:country":"BE",
    "sg:address":"Bedrifsstraat 14",
    "sg:city":"Hasselt",
    "sg:orig_category":"Electrom\u00e9nager, t\u00e9l\u00e9visions and radios Gr",
    "sg:phone":"+32 11 22 94 02",
    "sg:postcode":"3500",
    "sg:province":"Limburg",
    "wof:name":"C.d.h. Industries",
    "wof:placetype":"venue"
},
  "geometry": {"coordinates":[5.362596035,50.9554786682],"type":"Point"}
}