{
  "type": "Feature",
  "properties": {
    "iso:country":"BE",
    "sg:address":"Koerselsebaan 43",
    "sg:city":"Heusden-zolder",
    "sg:orig_category":"M\u00e9decins and sp\u00e9cialistes",
    "sg:phone":"+32 11 42 06 09",
    "sg:postcode":"3550",
    "sg:province":"Limburg",
    "wof:name":"Stefan Weyens",
    "wof:placetype":"venue"
},
  "geometry": {"coordinates":[5.2812857628,51.0356445312],"type":"Point"}
}