{
  "type": "Feature",
  "properties": {
    "iso:country":"BE",
    "sg:address":"Scheepzatestraat 5",
    "sg:city":"Gent",
    "sg:classifiers":[
        {
            "category":"Utilities",
            "subcategory":"Recycling",
            "type":"Services"
        }
    ],
    "sg:phone":"+32 9 251 32 53",
    "sg:postcode":"9000",
    "sg:province":"Oost-Vlaanderen",
    "wof:name":"Retra Nv",
    "wof:placetype":"venue"
},
  "geometry": {"coordinates":[3.741476059,51.0946731567],"type":"Point"}
}