{
  "type": "Feature",
  "properties": {
    "addr:full":"Grossenbusch 56 Raeren Li\u00e8ge 4730",
    "addr:housenumber":"56",
    "addr:postcode":"4730",
    "addr:street":"Grossenbusch",
    "iso:country":"BE",
    "sg:address":"Grossenbusch 56",
    "sg:city":"Raeren",
    "sg:orig_category":"Eclairage et \u00e9quipements du foyer. Textiles",
    "sg:phone":"+32 87 65 72 71",
    "sg:postcode":"4730",
    "sg:province":"Li\u00e8ge",
    "wof:name":"Fa. Deroka",
    "wof:placetype":"venue"
},
  "geometry": {"coordinates":[6.0799207687,50.7107658386],"type":"Point"}
}