{
  "type": "Feature",
  "properties": {
    "addr:full":"Quai De Rome 112 Liege Li\u00e8ge 4000",
    "addr:housenumber":"112",
    "addr:postcode":"4000",
    "addr:street":"Quai De Rome",
    "iso:country":"BE",
    "sg:address":"Quai De Rome 112",
    "sg:city":"Liege",
    "sg:orig_category":"Plaatsen van vloer- and muurbekleding Schilders Verlichting and huishoudartikelen",
    "sg:phone":"+32 4 252 97 70",
    "sg:postcode":"4000",
    "sg:province":"Li\u00e8ge",
    "wof:name":"Monsieur Bronkart",
    "wof:placetype":"venue"
},
  "geometry": {"coordinates":[5.5781297684,50.6196899414],"type":"Point"}
}