{
  "type": "Feature",
  "properties": {
    "addr:full":"Coupure Links 73 Gent Oost-Vlaanderen 9000",
    "addr:housenumber":"73",
    "addr:postcode":"9000",
    "addr:street":"Coupure Links;Oost-Vlaanderen",
    "iso:country":"BE",
    "sg:address":"Coupure Links 73",
    "sg:city":"Gent",
    "sg:classifiers":[
        {
            "category":"Personal",
            "subcategory":"Beauty Salon",
            "type":"Services"
        }
    ],
    "sg:phone":"+32 9 225 01 31",
    "sg:postcode":"9000",
    "sg:province":"Oost-Vlaanderen",
    "sg:tags":[
        "de",
        "coiffure"
    ],
    "wof:name":"David De Cubber",
    "wof:placetype":"venue"
},
  "geometry": {"coordinates":[3.7192940712,51.0464324951],"type":"Point"}
}