{
  "type": "Feature",
  "properties": {
    "iso:country":"BE",
    "sg:address":"Route De Barvaux 4",
    "sg:city":"Durbuy",
    "sg:orig_category":"Traitements param\u00e9dicaux",
    "sg:phone":"+32 477 26 35 00",
    "sg:postcode":"6940",
    "sg:province":"Luxembourg",
    "wof:name":"F. Colla",
    "wof:placetype":"venue"
},
  "geometry": {"coordinates":[5.4543361664,50.3515777588],"type":"Point"}
}