{
  "type": "Feature",
  "properties": {
    "iso:country":"BE",
    "sg:address":"Chauss\u00c9e D'eghez\u00c9e 52",
    "sg:city":"La Bruyere",
    "sg:orig_category":"Artsen and specialisten",
    "sg:phone":"+32 81 56 70 14",
    "sg:postcode":"5081",
    "sg:province":"Namur",
    "wof:name":"Jacques Quaresme",
    "wof:placetype":"venue"
},
  "geometry": {"coordinates":[4.7865719795,50.5369911194],"type":"Point"}
}