{
  "type": "Feature",
  "properties": {
    "iso:country":"BE",
    "sg:address":"Oostnieuwkerksestraat 5",
    "sg:city":"Moorslede",
    "sg:orig_category":"Fleurs and plantes",
    "sg:phone":"+32 51 77 11 42",
    "sg:postcode":"8890",
    "sg:province":"West-Vlaanderen",
    "wof:name":"Geert Bonte",
    "wof:placetype":"venue"
},
  "geometry": {"coordinates":[3.0558719635,50.9004211426],"type":"Point"}
}