{
  "type": "Feature",
  "properties": {
    "iso:country":"BE",
    "sg:address":"Rue Du Concours 15",
    "sg:city":"Bruxelles (watermael-boitsfort)",
    "sg:classifiers":[
        {
            "category":"Community Center",
            "subcategory":"Youth",
            "type":"Public Place"
        }
    ],
    "sg:phone":"+32 2 662 20 43",
    "sg:postcode":"1170",
    "sg:province":"Bruxelles-Capitale",
    "sg:tags":[
        "club"
    ],
    "wof:name":"Club Neptune Asbl",
    "wof:placetype":"venue"
},
  "geometry": {"coordinates":[4.4177951813,50.7974243164],"type":"Point"}
}