{
  "type": "Feature",
  "properties": {
    "addr:full":"Clos Chapelle Aux Champs 30 Box 51 Bruxelles (woluwe-saint-lambert) Bruxelles-Capitale 1200",
    "addr:housenumber":"30 box 51",
    "addr:postcode":"1200",
    "addr:street":"Clos Chapelle Aux Champs",
    "iso:country":"BE",
    "sg:address":"Clos Chapelle Aux Champs 30 Box 51",
    "sg:city":"Bruxelles (woluwe-saint-lambert)",
    "sg:classifiers":[
        {
            "category":"Health Services",
            "subcategory":"Hospital",
            "type":"Services"
        }
    ],
    "sg:phone":"+32 2 771 17 64",
    "sg:postcode":"1200",
    "sg:province":"Bruxelles-Capitale",
    "wof:name":"Centre De D\u00e9pistage Du Cancer U.c.l.",
    "wof:placetype":"venue"
},
  "geometry": {"coordinates":[4.4498109818,50.8496398926],"type":"Point"}
}