{
  "type": "Feature",
  "properties": {
    "iso:country":"BE",
    "sg:address":"Jordaenslaan 7",
    "sg:city":"De Haan",
    "sg:orig_category":"Vakantiehuizen",
    "sg:phone":"+32 59 23 55 11",
    "sg:postcode":"8420",
    "sg:province":"West-Vlaanderen",
    "wof:name":"Cobbaert Mon S\u00c9jour",
    "wof:placetype":"venue"
},
  "geometry": {"coordinates":[3.0356531143,51.2774276733],"type":"Point"}
}