{
  "type": "Feature",
  "properties": {
    "iso:country":"BE",
    "sg:address":"Veemarkt 50",
    "sg:city":"Mechelen",
    "sg:orig_category":"M\u00e9decins and sp\u00e9cialistes",
    "sg:phone":"+32 15 20 53 42",
    "sg:postcode":"2800",
    "sg:province":"Antwerpen",
    "wof:name":"H. Van Vooren",
    "wof:placetype":"venue"
},
  "geometry": {"coordinates":[4.484749794,51.028968811],"type":"Point"}
}