{
  "type": "Feature",
  "properties": {
    "addr:full":"Mannebeekstraat 31 Waregem West-Vlaanderen 8790",
    "addr:housenumber":"31",
    "addr:postcode":"8790",
    "addr:street":"Mannebeekstraat",
    "iso:country":"BE",
    "sg:address":"Mannebeekstraat 31",
    "sg:city":"Waregem",
    "sg:orig_category":"Non-Classified Establishments",
    "sg:phone":"+32 56 62 21 30",
    "sg:postcode":"8790",
    "sg:province":"West-Vlaanderen",
    "wof:name":"Axioma Nv",
    "wof:placetype":"venue"
},
  "geometry": {"coordinates":[3.4235260487,50.8612365723],"type":"Point"}
}