{
  "type": "Feature",
  "properties": {
    "addr:full":"Rue Des Combattants 107 Verviers Li\u00e8ge 4800",
    "addr:housenumber":"107",
    "addr:postcode":"4800",
    "addr:street":"Rue Des Combattants",
    "iso:country":"BE",
    "sg:address":"Rue Des Combattants 107",
    "sg:city":"Verviers",
    "sg:classifiers":[
        {
            "category":"Cafe",
            "type":"Food & Drink"
        }
    ],
    "sg:phone":"+32 87 33 99 59",
    "sg:postcode":"4800",
    "sg:province":"Li\u00e8ge",
    "sg:tags":[
        "caf\u00e9s"
    ],
    "wof:name":"Daniel Durbut",
    "wof:placetype":"venue"
},
  "geometry": {"coordinates":[5.8475799561,50.5951309204],"type":"Point"}
}