{
  "type": "Feature",
  "properties": {
    "iso:country":"BE",
    "sg:address":"Benedenstraat 1",
    "sg:city":"Sint-lievens-houtem",
    "sg:orig_category":"Slagers",
    "sg:phone":"+32 9 362 69 75",
    "sg:postcode":"9520",
    "sg:province":"Oost-Vlaanderen",
    "wof:name":"Frans Vyverman",
    "wof:placetype":"venue"
},
  "geometry": {"coordinates":[3.8698968887,50.9458045959],"type":"Point"}
}