{
  "type": "Feature",
  "properties": {
    "addr:full":"Tervuursesteenweg 241 Mechelen Antwerpen 2800",
    "addr:housenumber":"241",
    "addr:postcode":"2800",
    "addr:street":"Tervuursesteenweg",
    "iso:country":"BE",
    "sg:address":"Tervuursesteenweg 241",
    "sg:city":"Mechelen",
    "sg:orig_category":"D\u00e9molition d\u00b4immeubles and terrassements",
    "sg:phone":"+32 15 42 02 12",
    "sg:postcode":"2800",
    "sg:province":"Antwerpen",
    "wof:name":"D. Meys",
    "wof:placetype":"venue"
},
  "geometry": {"coordinates":[4.4853749275,51.0072631836],"type":"Point"}
}