{
  "type": "Feature",
  "properties": {
    "addr:full":"E. Claeslaan 4 Brecht Antwerpen 2960",
    "addr:housenumber":"4",
    "addr:postcode":"2960",
    "addr:street":"E. Claeslaan",
    "iso:country":"BE",
    "sg:address":"E. Claeslaan 4",
    "sg:city":"Brecht",
    "sg:orig_category":"Kapsalons",
    "sg:phone":"+32 3 313 05 98",
    "sg:postcode":"2960",
    "sg:province":"Antwerpen",
    "wof:name":"Nadia Raes",
    "wof:placetype":"venue"
},
  "geometry": {"coordinates":[4.6415200233,51.3512115479],"type":"Point"}
}