{
  "type": "Feature",
  "properties": {
    "iso:country":"BE",
    "sg:address":"Nispert 5",
    "sg:city":"Eupen",
    "sg:orig_category":"Installatie van metalen schrijnwerk",
    "sg:phone":"+32 87 74 25 09",
    "sg:postcode":"4700",
    "sg:province":"Li\u00e8ge",
    "wof:name":"Kuttig H",
    "wof:placetype":"venue"
},
  "geometry": {"coordinates":[6.0296521187,50.6318206787],"type":"Point"}
}