{
  "type": "Feature",
  "properties": {
    "addr:full":"Rue Winston Churchill 212 Courcelles Hainaut 6180",
    "addr:housenumber":"212",
    "addr:postcode":"6180",
    "addr:street":"Rue Winston Churchill",
    "iso:country":"BE",
    "sg:address":"Rue Winston Churchill 212",
    "sg:city":"Courcelles",
    "sg:classifiers":[
        {
            "category":"Home & Garden",
            "subcategory":"Building Materials",
            "type":"Retail Goods"
        }
    ],
    "sg:phone":"+32 71 36 64 15",
    "sg:postcode":"6180",
    "sg:province":"Hainaut",
    "sg:tags":[
        "window"
    ],
    "wof:name":"Chassis Socomeba Sprl",
    "wof:placetype":"venue"
},
  "geometry": {"coordinates":[4.3918800354,50.462890625],"type":"Point"}
}