{
  "type": "Feature",
  "properties": {
    "addr:full":"Dalstraat 79 Mol Antwerpen 2400",
    "addr:housenumber":"79",
    "addr:postcode":"2400",
    "addr:street":"Dalstraat",
    "iso:country":"BE",
    "sg:address":"Dalstraat 79",
    "sg:city":"Mol",
    "sg:classifiers":[
        {
            "category":"Arena",
            "subcategory":"Sports Club",
            "type":"Entertainment"
        }
    ],
    "sg:phone":"+32 14 31 93 59",
    "sg:postcode":"2400",
    "sg:province":"Antwerpen",
    "sg:tags":[
        "de"
    ],
    "wof:name":"Givo Recreatie",
    "wof:placetype":"venue"
},
  "geometry": {"coordinates":[5.1343259811,51.201839447],"type":"Point"}
}