{
  "type": "Feature",
  "properties": {
    "addr:full":"Vloeyenbergdreef 4 Schilde Antwerpen 2970",
    "addr:housenumber":"4",
    "addr:postcode":"2970",
    "addr:street":"Vloeyenbergdreef",
    "iso:country":"BE",
    "sg:address":"Vloeyenbergdreef 4",
    "sg:city":"Schilde",
    "sg:orig_category":"Artsen and specialisten",
    "sg:phone":"+32 3 383 30 43",
    "sg:postcode":"2970",
    "sg:province":"Antwerpen",
    "wof:name":"Bernard Van Dijk",
    "wof:placetype":"venue"
},
  "geometry": {"coordinates":[4.5734109879,51.2385635376],"type":"Point"}
}