{
  "type": "Feature",
  "properties": {
    "iso:country":"BE",
    "sg:address":"Weverstraat 137",
    "sg:city":"Sint-niklaas",
    "sg:orig_category":"Sportclubs",
    "sg:phone":"+32 3 777 03 67",
    "sg:postcode":"9100",
    "sg:province":"Oost-Vlaanderen",
    "wof:name":"Malpertus T.c. M.t.c.",
    "wof:placetype":"venue"
},
  "geometry": {"coordinates":[4.131775856,51.1299819946],"type":"Point"}
}