{
  "type": "Feature",
  "properties": {
    "addr:full":"Hof Ter Mereweg 78 Tienen Vlaams-Brabant 3300",
    "addr:housenumber":"78",
    "addr:postcode":"3300",
    "addr:street":"Hof Ter Mereweg",
    "iso:country":"BE",
    "sg:address":"Hof Ter Mereweg 78",
    "sg:city":"Tienen",
    "sg:classifiers":[
        {
            "category":"Arena",
            "subcategory":"Sports Club",
            "type":"Entertainment"
        }
    ],
    "sg:phone":"+32 16 82 38 88",
    "sg:postcode":"3300",
    "sg:province":"Vlaams-Brabant",
    "sg:tags":[
        "terrain",
        "hors",
        "de",
        "installation",
        "sportifs"
    ],
    "wof:name":"V.v. Houtem",
    "wof:placetype":"venue"
},
  "geometry": {"coordinates":[4.9950590134,50.8346290588],"type":"Point"}
}