{
  "type": "Feature",
  "properties": {
    "iso:country":"BE",
    "sg:address":"Pr\u00c9-cawiai 2",
    "sg:city":"Durbuy",
    "sg:classifiers":[
        {
            "category":"Social Services",
            "subcategory":"Job Training",
            "type":"Services"
        }
    ],
    "sg:phone":"+32 86 21 18 65",
    "sg:postcode":"6941",
    "sg:province":"Luxembourg",
    "sg:tags":[
        "de",
        "terrain",
        "camping"
    ],
    "wof:name":"Camping International",
    "wof:placetype":"venue"
},
  "geometry": {"coordinates":[5.5201120377,50.3758277893],"type":"Point"}
}