{
  "type": "Feature",
  "properties": {
    "addr:full":"Putsesteenweg 355 Bonheiden Antwerpen 2820",
    "addr:housenumber":"355",
    "addr:postcode":"2820",
    "addr:street":"Putsesteenweg",
    "iso:country":"BE",
    "sg:address":"Putsesteenweg 355",
    "sg:city":"Bonheiden",
    "sg:orig_category":"Dranken",
    "sg:phone":"+32 15 55 09 58",
    "sg:postcode":"2820",
    "sg:province":"Antwerpen",
    "wof:name":"Op De Beeck",
    "wof:placetype":"venue"
},
  "geometry": {"coordinates":[4.5448999405,51.036441803],"type":"Point"}
}