{
  "type": "Feature",
  "properties": {
    "iso:country":"BE",
    "sg:address":"Grijspeerdstraat 75",
    "sg:city":"Hooglede",
    "sg:orig_category":"Producteurs de l\u00e9gumes",
    "sg:phone":"+32 51 72 55 33",
    "sg:postcode":"8830",
    "sg:province":"West-Vlaanderen",
    "wof:name":"Noel Vandecasteele",
    "wof:placetype":"venue"
},
  "geometry": {"coordinates":[3.0890719891,51.0051078796],"type":"Point"}
}