{
  "type": "Feature",
  "properties": {
    "addr:full":"Avenue D'italie 36a Box 10 Bruxelles (ixelles) Bruxelles-Capitale 1050",
    "addr:housenumber":"36a box 10",
    "addr:postcode":"1050",
    "addr:street":"Avenue D'Italie",
    "iso:country":"BE",
    "sg:address":"Avenue D'italie 36a Box 10",
    "sg:city":"Bruxelles (ixelles)",
    "sg:classifiers":[
        {
            "category":"Professional",
            "subcategory":"Lawyer & Legal Services",
            "type":"Services"
        }
    ],
    "sg:phone":"+32 2 735 58 10",
    "sg:postcode":"1050",
    "sg:province":"Bruxelles-Capitale",
    "wof:name":"Bonhivers O",
    "wof:placetype":"venue"
},
  "geometry": {"coordinates":[4.3920178413,50.8043861389],"type":"Point"}
}