{
  "type": "Feature",
  "properties": {
    "iso:country":"BE",
    "sg:address":"Jonkershovestraat 217",
    "sg:city":"Houthulst",
    "sg:orig_category":"Entretien and r\u00e9parations de voitures",
    "sg:phone":"+32 51 54 63 54",
    "sg:postcode":"8650",
    "sg:province":"West-Vlaanderen",
    "wof:name":"Fa. Vercruysse-pinseel",
    "wof:placetype":"venue"
},
  "geometry": {"coordinates":[2.9245901108,50.9711494446],"type":"Point"}
}