{
  "type": "Feature",
  "properties": {
    "addr:full":"Rue W.lallemand 49 Luik Li\u00e8ge 4030",
    "addr:housenumber":"49",
    "addr:postcode":"4030",
    "addr:street":"Rue W.Lallemand",
    "iso:country":"BE",
    "sg:address":"Rue W.lallemand 49",
    "sg:city":"Luik",
    "sg:orig_category":"Fotografen and fotostudio's",
    "sg:phone":"+32 4 342 14 87",
    "sg:postcode":"4030",
    "sg:province":"Li\u00e8ge",
    "wof:name":"Sup Air Vision",
    "wof:placetype":"venue"
},
  "geometry": {"coordinates":[5.6046648026,50.6188240051],"type":"Point"}
}