{
  "type": "Feature",
  "properties": {
    "addr:full":"Steenweg 330 Alken Limburg 3570",
    "addr:housenumber":"330",
    "addr:postcode":"3570",
    "addr:street":"Steenweg",
    "iso:country":"BE",
    "sg:address":"Steenweg 330",
    "sg:city":"Alken",
    "sg:orig_category":"Fruitteelt",
    "sg:phone":"+32 11 31 40 64",
    "sg:postcode":"3570",
    "sg:province":"Limburg",
    "wof:name":"Armin Mathys",
    "wof:placetype":"venue"
},
  "geometry": {"coordinates":[5.2615981102,50.8730583191],"type":"Point"}
}