{
  "type": "Feature",
  "properties": {
    "iso:country":"BE",
    "sg:address":"Huffeselestraat 26",
    "sg:city":"Tielt",
    "sg:classifiers":[
        {
            "category":"Personal",
            "subcategory":"Beauty Salon",
            "type":"Services"
        }
    ],
    "sg:phone":"+32 51 40 19 76",
    "sg:postcode":"8700",
    "sg:province":"West-Vlaanderen",
    "sg:tags":[
        "de",
        "coiffure"
    ],
    "wof:name":"Hairstyling Severine",
    "wof:placetype":"venue"
},
  "geometry": {"coordinates":[3.324712038,50.9869842529],"type":"Point"}
}