{
  "type": "Feature",
  "properties": {
    "addr:full":"Maastrichterstraat 345 Bilzen Limburg 3740",
    "addr:housenumber":"345",
    "addr:postcode":"3740",
    "addr:street":"Maastrichterstraat",
    "iso:country":"BE",
    "sg:address":"Maastrichterstraat 345",
    "sg:city":"Bilzen",
    "sg:classifiers":[
        {
            "category":"Bars & Pubs",
            "type":"Food & Drink"
        }
    ],
    "sg:phone":"+32 89 41 13 12",
    "sg:postcode":"3740",
    "sg:province":"Limburg",
    "wof:name":"De Lantaarn",
    "wof:placetype":"venue"
},
  "geometry": {"coordinates":[5.5271902084,50.8648300171],"type":"Point"}
}