{
  "type": "Feature",
  "properties": {
    "addr:full":"Guido Gezellestraat 21-1 Dilbeek (groot - Bijgaarden) Vlaams-Brabant 1702",
    "addr:housenumber":"21-1;1702",
    "addr:street":"Guido Gezellestraat;Groot Bijgaarden Vlaams-Brabant",
    "iso:country":"BE",
    "sg:address":"Guido Gezellestraat 21-1",
    "sg:city":"Dilbeek (groot - Bijgaarden)",
    "sg:classifiers":[
        {
            "category":"Health Services",
            "subcategory":"Health Practitioner",
            "type":"Services"
        }
    ],
    "sg:phone":"+32 477 37 78 78",
    "sg:postcode":"1702",
    "sg:province":"Vlaams-Brabant",
    "sg:tags":[
        "physiotherapist"
    ],
    "wof:name":"Van Campenhout Kurt",
    "wof:placetype":"venue"
},
  "geometry": {"coordinates":[4.273665905,50.8671569824],"type":"Point"}
}