{
  "type": "Feature",
  "properties": {
    "addr:full":"Nachtegaalstraat 18 Torhout West-Vlaanderen 8820",
    "addr:housenumber":"18",
    "addr:postcode":"8820",
    "addr:street":"Nachtegaalstraat",
    "iso:country":"BE",
    "sg:address":"Nachtegaalstraat 18",
    "sg:city":"Torhout",
    "sg:classifiers":[
        {
            "category":"Building & Trades",
            "subcategory":"Construction",
            "type":"Services"
        }
    ],
    "sg:phone":"+32 50 21 59 22",
    "sg:postcode":"8820",
    "sg:province":"West-Vlaanderen",
    "sg:tags":[
        "stucco",
        "contractor"
    ],
    "wof:name":"Maekelbergh Peter Bvba",
    "wof:placetype":"venue"
},
  "geometry": {"coordinates":[3.1208128929,51.0628013611],"type":"Point"}
}