{
  "type": "Feature",
  "properties": {
    "addr:full":"Place Des Wallons 55 Ottignies-louvain-la-neuve Brabant Wallon 1348",
    "addr:housenumber":"55",
    "addr:postcode":"1348",
    "addr:street":"Place Des Wallons",
    "iso:country":"BE",
    "sg:address":"Place Des Wallons 55",
    "sg:city":"Ottignies-louvain-la-neuve",
    "sg:orig_category":"Pain, p\u00e2tisseries and confiseries",
    "sg:phone":"+32 10 45 23 39",
    "sg:postcode":"1348",
    "sg:province":"Brabant Wallon",
    "wof:name":"Boulangerie Ardennaise",
    "wof:placetype":"venue"
},
  "geometry": {"coordinates":[4.6171569824,50.6685676575],"type":"Point"}
}