{
  "type": "Feature",
  "properties": {
    "addr:full":"Rue De Flines 45 Peruwelz Hainaut 7604",
    "addr:housenumber":"45",
    "addr:postcode":"7604",
    "addr:street":"Rue De Flines;Hainaut",
    "iso:country":"BE",
    "sg:address":"Rue De Flines 45",
    "sg:city":"Peruwelz",
    "sg:orig_category":"Imprimeries and copyshops",
    "sg:phone":"+32 69 77 50 86",
    "sg:postcode":"7604",
    "sg:province":"Hainaut",
    "wof:name":"Biker Print",
    "wof:placetype":"venue"
},
  "geometry": {"coordinates":[3.5121939182,50.533039093],"type":"Point"}
}