{
  "type": "Feature",
  "properties": {
    "iso:country":"BE",
    "sg:address":"Zondereigen 96ba",
    "sg:city":"Baarle-hertog",
    "sg:orig_category":"Eleveurs and marchands de porcs. Eleveurs de bovins",
    "sg:phone":"+32 14 63 34 35",
    "sg:postcode":"2387",
    "sg:province":"Antwerpen",
    "wof:name":"Jozef Voet",
    "wof:placetype":"venue"
},
  "geometry": {"coordinates":[4.8752770424,51.4090576172],"type":"Point"}
}