{
  "type": "Feature",
  "properties": {
    "iso:country":"BE",
    "sg:address":"Av Louise 327",
    "sg:city":"Bruxelles",
    "sg:classifiers":[
        {
            "category":"Banks & Credit Unions",
            "subcategory":"Financial Services",
            "type":"Services"
        }
    ],
    "sg:phone":"+32 2 648 02 77",
    "sg:postcode":"1050",
    "sg:province":"Bruxelles-Capitale",
    "sg:tags":[
        "banking",
        "finance",
        "insurance"
    ],
    "wof:name":"Kemper Sa",
    "wof:placetype":"venue"
},
  "geometry": {"coordinates":[4.3685421944,50.8223876953],"type":"Point"}
}