{
  "type": "Feature",
  "properties": {
    "addr:full":"Schransdreef 17 Overijse Vlaams-Brabant 3090",
    "addr:housenumber":"17",
    "addr:postcode":"3090",
    "addr:street":"Schransdreef",
    "iso:country":"BE",
    "sg:address":"Schransdreef 17",
    "sg:city":"Overijse",
    "sg:classifiers":[
        {
            "category":"Food & Beverages",
            "subcategory":"Fruits & Vegetables",
            "type":"Retail Goods"
        }
    ],
    "sg:phone":"+32 2 657 15 46",
    "sg:postcode":"3090",
    "sg:province":"Vlaams-Brabant",
    "sg:tags":[
        "l\u00e9gumes",
        "gr"
    ],
    "wof:name":"Andre Lisen",
    "wof:placetype":"venue"
},
  "geometry": {"coordinates":[4.5065059662,50.7940483093],"type":"Point"}
}