{
  "type": "Feature",
  "properties": {
    "iso:country":"BE",
    "sg:address":"Rue De La Haie",
    "sg:city":"Roux-miroir",
    "sg:orig_category":"Peinture",
    "sg:phone":"+32 475 82 89 53",
    "sg:postcode":"1315",
    "sg:province":"Brabant Wallon",
    "wof:name":"Beaumont D\u00c9coration",
    "wof:placetype":"venue"
},
  "geometry": {"coordinates":[4.7851839066,50.7172012329],"type":"Point"}
}