{
  "type": "Feature",
  "properties": {
    "iso:country":"BE",
    "sg:address":"Sint-jansplein 17",
    "sg:city":"Antwerpen",
    "sg:classifiers":[
        {
            "category":"Building & Trades",
            "subcategory":"Electrical",
            "type":"Services"
        }
    ],
    "sg:phone":"+32 3 231 19 58",
    "sg:postcode":"2060",
    "sg:province":"Antwerpen",
    "sg:tags":[
        "industrial",
        "-",
        "electric",
        "contractor"
    ],
    "wof:name":"Electro-industrielle Bvba",
    "wof:placetype":"venue"
},
  "geometry": {"coordinates":[4.4187469482,51.2253875732],"type":"Point"}
}