{
  "type": "Feature",
  "properties": {
    "addr:full":"Waterloose Steenweg 961 Ukkel/uccle Bruxelles-Capitale 1180",
    "addr:housenumber":"961",
    "addr:postcode":"1180",
    "addr:street":"Waterloose Steenweg;/",
    "iso:country":"BE",
    "sg:address":"Waterloose Steenweg 961",
    "sg:city":"Ukkel/uccle",
    "sg:orig_category":"Rusthuizen and serviceflats",
    "sg:phone":"+32 2 373 64 11",
    "sg:postcode":"1180",
    "sg:province":"Bruxelles-Capitale",
    "wof:name":"Home Nazareth/maison De Repos Nazareth",
    "wof:placetype":"venue"
},
  "geometry": {"coordinates":[4.3714690208,50.8065109253],"type":"Point"}
}