{
  "type": "Feature",
  "properties": {
    "addr:full":"Rue De Laeken 149-151 Bruxelles Bruxelles-Capitale 1000",
    "addr:postcode":"149-151;1000",
    "addr:street":"Rue De Laeken",
    "iso:country":"BE",
    "sg:address":"Rue De Laeken 149-151",
    "sg:city":"Bruxelles",
    "sg:orig_category":"Non-Classified Establishments",
    "sg:phone":"+32 2 217 40 30",
    "sg:postcode":"1000",
    "sg:province":"Bruxelles-Capitale",
    "wof:name":"Interpaint",
    "wof:placetype":"venue"
},
  "geometry": {"coordinates":[4.352493763,50.8550758362],"type":"Point"}
}