{
  "type": "Feature",
  "properties": {
    "addr:full":"Rue Catalogne 54 Villers-la-ville (marbais) Brabant Wallon 1495",
    "addr:housenumber":"54",
    "addr:postcode":"1495",
    "addr:street":"Rue Catalogne",
    "iso:country":"BE",
    "sg:address":"Rue Catalogne 54",
    "sg:city":"Villers-la-ville (marbais)",
    "sg:classifiers":[
        {
            "category":"Home & Garden",
            "subcategory":"Kitchen Supply",
            "type":"Retail Goods"
        }
    ],
    "sg:phone":"+32 71 87 67 64",
    "sg:postcode":"1495",
    "sg:province":"Brabant Wallon",
    "sg:tags":[
        "-",
        "industrial",
        "installation",
        "equipment"
    ],
    "wof:name":"Noe J",
    "wof:placetype":"venue"
},
  "geometry": {"coordinates":[4.530477047,50.5786132812],"type":"Point"}
}