{
  "type": "Feature",
  "properties": {
    "iso:country":"BE",
    "sg:address":"Rue Theys 3ba",
    "sg:city":"Wanze",
    "sg:orig_category":"Immobili\u00ebnkantoren",
    "sg:phone":"+32 85 21 50 95",
    "sg:postcode":"4520",
    "sg:province":"Li\u00e8ge",
    "wof:name":"Trans Europe Immobili\u00c8re",
    "wof:placetype":"venue"
},
  "geometry": {"coordinates":[5.2139430046,50.5367546082],"type":"Point"}
}