{
  "type": "Feature",
  "properties": {
    "iso:country":"BE",
    "sg:address":"Rue Du Gazetier 16",
    "sg:city":"Morlanwelz",
    "sg:orig_category":"Artistes ind\u00e9pendants. M\u00e9decins and sp\u00e9cialistes",
    "sg:phone":"+32 64 44 27 19",
    "sg:postcode":"7140",
    "sg:province":"Hainaut",
    "wof:name":"M. Gaudy",
    "wof:placetype":"venue"
},
  "geometry": {"coordinates":[4.2475910187,50.4566268921],"type":"Point"}
}