{
  "type": "Feature",
  "properties": {
    "iso:country":"BE",
    "sg:address":"Loofblommestraat 18",
    "sg:city":"Gent (sint-denijs-westrem - Afsnee)",
    "sg:classifiers":[
        {
            "category":"Education",
            "subcategory":"School",
            "type":"Public Place"
        }
    ],
    "sg:phone":"+32 9 280 02 40",
    "sg:postcode":"9051",
    "sg:province":"Oost-Vlaanderen",
    "sg:tags":[
        "supply"
    ],
    "wof:name":"Blauw Pen (de)",
    "wof:placetype":"venue"
},
  "geometry": {"coordinates":[3.6690559387,51.0216598511],"type":"Point"}
}