{
  "type": "Feature",
  "properties": {
    "iso:country":"BE",
    "sg:address":"Frans Van Gielstraat 26",
    "sg:city":"Malle (oostmalle)",
    "sg:classifiers":[
        {
            "category":"Building & Trades",
            "subcategory":"Equipment Rental",
            "type":"Services"
        }
    ],
    "sg:phone":"+32 3 312 19 78",
    "sg:postcode":"2390",
    "sg:province":"Antwerpen",
    "sg:tags":[
        "use",
        "apparatus",
        "tool",
        "-",
        "professional",
        "machines"
    ],
    "wof:name":"Koyen J",
    "wof:placetype":"venue"
},
  "geometry": {"coordinates":[4.7453961372,51.3084526062],"type":"Point"}
}