{
  "type": "Feature",
  "properties": {
    "addr:full":"Bois Ten Bosse 17 Flobecq Hainaut 7880",
    "addr:housenumber":"17",
    "addr:postcode":"7880",
    "addr:street":"Bois Ten Bosse;Hainaut",
    "iso:country":"BE",
    "sg:address":"Bois Ten Bosse 17",
    "sg:city":"Flobecq",
    "sg:classifiers":[
        {
            "category":"Building & Trades",
            "subcategory":"Electrical",
            "type":"Services"
        }
    ],
    "sg:phone":"+32 68 44 78 88",
    "sg:postcode":"7880",
    "sg:province":"Hainaut",
    "sg:tags":[
        "electric",
        "-",
        "housewiring",
        "contractor"
    ],
    "wof:name":"Rasmont Fort Sprl",
    "wof:placetype":"venue"
},
  "geometry": {"coordinates":[3.7315649986,50.7681045532],"type":"Point"}
}