{
  "type": "Feature",
  "properties": {
    "addr:full":"Louis Mettewielaan 73b5 Sint-jans-molenbeek/molenbeek-saint-jean Bruxelles-Capitale 1080",
    "addr:housenumber":"73b5",
    "addr:postcode":"1080",
    "addr:street":"Louis Mettewielaan",
    "iso:country":"BE",
    "sg:address":"Louis Mettewielaan 73b5",
    "sg:city":"Sint-jans-molenbeek/molenbeek-saint-jean",
    "sg:orig_category":"Artsen and specialisten",
    "sg:phone":"+32 2 469 23 97",
    "sg:postcode":"1080",
    "sg:province":"Bruxelles-Capitale",
    "wof:name":"Danielle Helderweirt",
    "wof:placetype":"venue"
},
  "geometry": {"coordinates":[4.3049740791,50.8546180725],"type":"Point"}
}