{
  "type": "Feature",
  "properties": {
    "addr:full":"Rijksweg 111 Wielsbeke (sint-baafs-vijve) West-Vlaanderen 8710",
    "addr:housenumber":"111",
    "addr:postcode":"8710",
    "addr:street":"Rijksweg",
    "iso:country":"BE",
    "sg:address":"Rijksweg 111",
    "sg:city":"Wielsbeke (sint-baafs-vijve)",
    "sg:classifiers":[
        {
            "category":"Retail",
            "subcategory":"Auto Repair",
            "type":"Services"
        }
    ],
    "sg:phone":"+32 56 60 25 72",
    "sg:postcode":"8710",
    "sg:province":"West-Vlaanderen",
    "sg:tags":[
        "automobile-body"
    ],
    "wof:name":"Medard",
    "wof:placetype":"venue"
},
  "geometry": {"coordinates":[3.3838999271,50.9110298157],"type":"Point"}
}