{
  "type": "Feature",
  "properties": {
    "iso:country":"BE",
    "sg:address":"Chauss\u00c9e De Lille 307",
    "sg:city":"Tournai",
    "sg:classifiers":[
        {
            "category":"Insurance",
            "subcategory":"Insurance Agent",
            "type":"Services"
        }
    ],
    "sg:phone":"+32 69 23 26 62",
    "sg:postcode":"7500",
    "sg:province":"Hainaut",
    "sg:tags":[
        "verzekeringsmakelaars",
        "expert"
    ],
    "wof:name":"Agapi",
    "wof:placetype":"venue"
},
  "geometry": {"coordinates":[3.3808679581,50.6065254211],"type":"Point"}
}