{
  "type": "Feature",
  "properties": {
    "addr:full":"Nieuwstraat 120 Asse Vlaams-Brabant 1730",
    "addr:housenumber":"120",
    "addr:postcode":"1730",
    "addr:street":"Nieuwstraat",
    "iso:country":"BE",
    "sg:address":"Nieuwstraat 120",
    "sg:city":"Asse",
    "sg:orig_category":"Elektrische installaties voor woningen",
    "sg:phone":"+32 2 452 65 85",
    "sg:postcode":"1730",
    "sg:province":"Vlaams-Brabant",
    "wof:name":"Merens Elektro",
    "wof:placetype":"venue"
},
  "geometry": {"coordinates":[4.1917600632,50.9076843262],"type":"Point"}
}