{
  "type": "Feature",
  "properties": {
    "iso:country":"BE",
    "sg:address":"Dorpsstraat 111",
    "sg:city":"Lanaken",
    "sg:orig_category":"MEUBELONTWERP AND -INSTALLATIE",
    "sg:phone":"+32 89 72 24 53",
    "sg:postcode":"3620",
    "sg:province":"Limburg",
    "wof:name":"Michel Massot",
    "wof:placetype":"venue"
},
  "geometry": {"coordinates":[5.6551351547,50.8912277222],"type":"Point"}
}