{
  "type": "Feature",
  "properties": {
    "addr:full":"Avenue De La Chasse 140 Bruxelles (etterbeek) Bruxelles-Capitale 1040",
    "addr:housenumber":"140",
    "addr:postcode":"1040",
    "addr:street":"Avenue De La Chasse",
    "iso:country":"BE",
    "sg:address":"Avenue De La Chasse 140",
    "sg:city":"Bruxelles (etterbeek)",
    "sg:classifiers":[
        {
            "category":"Professional",
            "subcategory":"Employment Agencies",
            "type":"Services"
        }
    ],
    "sg:phone":"+32 2 732 61 60",
    "sg:postcode":"1040",
    "sg:province":"Bruxelles-Capitale",
    "sg:tags":[
        "market",
        "research"
    ],
    "wof:name":"Amalfi International",
    "wof:placetype":"venue"
},
  "geometry": {"coordinates":[4.3933830261,50.8345756531],"type":"Point"}
}