{
  "type": "Feature",
  "properties": {
    "addr:full":"Rue Du Centre 16 Somme-leuze Namur 5377",
    "addr:housenumber":"16",
    "addr:postcode":"5377",
    "addr:street":"Rue Du Centre",
    "iso:country":"BE",
    "sg:address":"Rue Du Centre 16",
    "sg:city":"Somme-leuze",
    "sg:classifiers":[
        {
            "category":"Fast Food",
            "type":"Food & Drink"
        }
    ],
    "sg:phone":"+32 84 31 51 80",
    "sg:postcode":"5377",
    "sg:province":"Namur",
    "sg:tags":[
        "hotel",
        "meeneem",
        "restaurant"
    ],
    "wof:name":"Le Capucin Gourmand",
    "wof:placetype":"venue"
},
  "geometry": {"coordinates":[5.340171814,50.2875671387],"type":"Point"}
}