{
  "type": "Feature",
  "properties": {
    "addr:full":"Krommestraat 7 Mechelen Antwerpen 2800",
    "addr:housenumber":"7",
    "addr:postcode":"2800",
    "addr:street":"Krommestraat",
    "iso:country":"BE",
    "sg:address":"Krommestraat 7",
    "sg:city":"Mechelen",
    "sg:classifiers":[
        {
            "category":"Social Services",
            "type":"Services"
        }
    ],
    "sg:phone":"+32 15 21 17 88",
    "sg:postcode":"2800",
    "sg:province":"Antwerpen",
    "wof:name":"Dagcentrum Bohets",
    "wof:placetype":"venue"
},
  "geometry": {"coordinates":[4.4736652374,51.0324897766],"type":"Point"}
}