{
  "type": "Feature",
  "properties": {
    "iso:country":"BE",
    "sg:address":"Monnikenwerve 86",
    "sg:city":"Brugge",
    "sg:orig_category":"Non-Classified Establishments",
    "sg:phone":"+32 50 31 40 46",
    "sg:postcode":"8000",
    "sg:province":"West-Vlaanderen",
    "wof:name":"Bevepe Bvba",
    "wof:placetype":"venue"
},
  "geometry": {"coordinates":[3.2036180496,51.2466392517],"type":"Point"}
}