{
  "type": "Feature",
  "properties": {
    "addr:full":"Kuurnesteenweg 8 Kortrijk West-Vlaanderen 8500",
    "addr:housenumber":"8",
    "addr:postcode":"8500",
    "addr:street":"Kuurnesteenweg",
    "iso:country":"BE",
    "sg:address":"Kuurnesteenweg 8",
    "sg:city":"Kortrijk",
    "sg:orig_category":"Traducteurs and interpr\u00e8tes",
    "sg:phone":"+32 56 37 33 70",
    "sg:postcode":"8500",
    "sg:province":"West-Vlaanderen",
    "wof:name":"Vanantwerpen K. Cbtip/bkvtf",
    "wof:placetype":"venue"
},
  "geometry": {"coordinates":[3.2644889355,50.8395347595],"type":"Point"}
}