{
  "type": "Feature",
  "properties": {
    "iso:country":"BE",
    "sg:address":"Berkenlaan 48",
    "sg:city":"Zoersel",
    "sg:classifiers":[
        {
            "category":"Parking",
            "subcategory":"Lot",
            "type":"Transportation"
        }
    ],
    "sg:phone":"+32 3 384 09 33",
    "sg:postcode":"2980",
    "sg:province":"Antwerpen",
    "sg:tags":[
        "parking-places",
        "laying-out"
    ],
    "wof:name":"Sebreghts Gebr Bvba",
    "wof:placetype":"venue"
},
  "geometry": {"coordinates":[4.6563720703,51.2371520996],"type":"Point"}
}