{
  "type": "Feature",
  "properties": {
    "addr:full":"Sint-beggaberg 9 Leuven Vlaams-Brabant 3000",
    "addr:housenumber":"9",
    "addr:postcode":"3000",
    "addr:street":"Sint-Beggaberg",
    "iso:country":"BE",
    "sg:address":"Sint-beggaberg 9",
    "sg:city":"Leuven",
    "sg:classifiers":[
        {
            "category":"Personal",
            "subcategory":"Beauty Salon",
            "type":"Services"
        }
    ],
    "sg:phone":"+32 16 22 88 24",
    "sg:postcode":"3000",
    "sg:province":"Vlaams-Brabant",
    "sg:tags":[
        "lady",
        "-",
        "hairdressing"
    ],
    "wof:name":"Van Rijmenant A",
    "wof:placetype":"venue"
},
  "geometry": {"coordinates":[4.6989898682,50.8708763123],"type":"Point"}
}