{
  "type": "Feature",
  "properties": {
    "iso:country":"BE",
    "sg:address":"Langenakkerstraat 117",
    "sg:city":"Wellen",
    "sg:orig_category":"Woningbouw",
    "sg:phone":"+32 11 37 57 11",
    "sg:postcode":"3830",
    "sg:province":"Limburg",
    "wof:name":"Bouwbedrijf Dirk Coenen",
    "wof:placetype":"venue"
},
  "geometry": {"coordinates":[5.3555130959,50.8600082397],"type":"Point"}
}