{
  "type": "Feature",
  "properties": {
    "iso:country":"BE",
    "sg:address":"Rue Lucien Nam\u00cache 17",
    "sg:city":"Namur",
    "sg:orig_category":"Administration d'immeubles",
    "sg:phone":"+32 81 22 68 98",
    "sg:postcode":"5000",
    "sg:province":"Namur",
    "wof:name":"L. Merlevede",
    "wof:placetype":"venue"
},
  "geometry": {"coordinates":[4.8686499596,50.4660568237],"type":"Point"}
}