{
  "type": "Feature",
  "properties": {
    "addr:full":"Boondaalse Steenweg 129 Elsene/ixelles Bruxelles-Capitale 1050",
    "addr:housenumber":"129",
    "addr:postcode":"1050",
    "addr:street":"Boondaalse Steenweg",
    "iso:country":"BE",
    "sg:address":"Boondaalse Steenweg 129",
    "sg:city":"Elsene/ixelles",
    "sg:orig_category":"Herenkledingzaken",
    "sg:phone":"+32 2 648 91 11",
    "sg:postcode":"1050",
    "sg:province":"Bruxelles-Capitale",
    "wof:name":"Galanta",
    "wof:placetype":"venue"
},
  "geometry": {"coordinates":[4.3769512177,50.8245506287],"type":"Point"}
}