{
  "type": "Feature",
  "properties": {
    "iso:country":"BE",
    "sg:address":"Rue De Chesseroux 5",
    "sg:city":"Herve (battice)",
    "sg:classifiers":[
        {
            "category":"Professional",
            "subcategory":"Advertising",
            "type":"Services"
        }
    ],
    "sg:phone":"+32 87 66 08 45",
    "sg:postcode":"4651",
    "sg:province":"Li\u00e8ge",
    "sg:tags":[
        "item",
        "-",
        "business",
        "gift",
        "promotional"
    ],
    "wof:name":"B.w.s. Sprl",
    "wof:placetype":"venue"
},
  "geometry": {"coordinates":[5.809926033,50.6497650146],"type":"Point"}
}