{
  "type": "Feature",
  "properties": {
    "iso:country":"BE",
    "sg:address":"March\u00e9 Aux L\u00e9gumes 21",
    "sg:city":"Arlon",
    "sg:classifiers":[
        {
            "category":"Cafe",
            "type":"Food & Drink"
        }
    ],
    "sg:phone":"+32 63 22 27 68",
    "sg:postcode":"6700",
    "sg:province":"Luxembourg",
    "sg:tags":[
        "snack-bars"
    ],
    "wof:name":"Paluca",
    "wof:placetype":"venue"
},
  "geometry": {"coordinates":[5.8130202293,49.6839790344],"type":"Point"}
}