{
  "type": "Feature",
  "properties": {
    "addr:full":"Industriezone Ervaert Tivoli 11 Borgloon Limburg 3840",
    "addr:housenumber":"11",
    "addr:postcode":"3840",
    "addr:street":"Industriezone Ervaert Tivoli",
    "iso:country":"BE",
    "sg:address":"Industriezone Ervaert Tivoli 11",
    "sg:city":"Borgloon",
    "sg:classifiers":[
        {
            "category":"Home & Garden",
            "subcategory":"Building Materials",
            "type":"Retail Goods"
        }
    ],
    "sg:phone":"+32 12 74 22 31",
    "sg:postcode":"3840",
    "sg:province":"Limburg",
    "sg:tags":[
        "veranda"
    ],
    "wof:name":"All Plastic Bvba",
    "wof:placetype":"venue"
},
  "geometry": {"coordinates":[5.3441700935,50.8012466431],"type":"Point"}
}