{
  "type": "Feature",
  "properties": {
    "addr:full":"Schildesteenweg 72 Ranst (oelegem) Antwerpen 2520",
    "addr:housenumber":"72",
    "addr:postcode":"2520",
    "addr:street":"Schildesteenweg",
    "iso:country":"BE",
    "sg:address":"Schildesteenweg 72",
    "sg:city":"Ranst (oelegem)",
    "sg:classifiers":[
        {
            "category":"Home & Garden",
            "subcategory":"Kitchen Supply",
            "type":"Retail Goods"
        }
    ],
    "sg:phone":"+32 3 384 02 70",
    "sg:postcode":"2520",
    "sg:province":"Antwerpen",
    "sg:tags":[
        "installation"
    ],
    "wof:name":"Oudermans L",
    "wof:placetype":"venue"
},
  "geometry": {"coordinates":[4.5992422104,51.2173576355],"type":"Point"}
}