{
  "type": "Feature",
  "properties": {
    "iso:country":"BE",
    "sg:address":"Frankrijklei 109",
    "sg:city":"Antwerpen",
    "sg:classifiers":[
        {
            "category":"Shopping",
            "subcategory":"Bicycles & Sporting Goods",
            "type":"Retail Goods"
        }
    ],
    "sg:phone":"+32 3 226 18 73",
    "sg:postcode":"2000",
    "sg:province":"Antwerpen",
    "sg:tags":[
        "equipment",
        "camping"
    ],
    "wof:name":"De Kampeerder Bvba",
    "wof:placetype":"venue"
},
  "geometry": {"coordinates":[4.4104251862,51.2125587463],"type":"Point"}
}