{
  "type": "Feature",
  "properties": {
    "iso:country":"BE",
    "sg:address":"P.i.",
    "sg:city":"Perwez",
    "sg:classifiers":[
        {
            "category":"Manufacturing",
            "subcategory":"Metals",
            "type":"Manufacturing & Wholesale Goods"
        }
    ],
    "sg:phone":"+32 81 65 80 40",
    "sg:postcode":"1360",
    "sg:province":"Brabant Wallon",
    "sg:tags":[
        "-",
        "machine",
        "equipment",
        "engineering",
        "machinery",
        "mechanical"
    ],
    "wof:name":"D R M Services Sa",
    "wof:placetype":"venue"
},
  "geometry": {"coordinates":[4.8050098419,50.6224861145],"type":"Point"}
}