{
  "type": "Feature",
  "properties": {
    "addr:full":"Zandstraat 187 Heusden-zolder Limburg 3550",
    "addr:housenumber":"187",
    "addr:postcode":"3550",
    "addr:street":"Zandstraat",
    "iso:country":"BE",
    "sg:address":"Zandstraat 187",
    "sg:city":"Heusden-zolder",
    "sg:orig_category":"Woningbouw",
    "sg:phone":"+32 11 87 31 98",
    "sg:postcode":"3550",
    "sg:province":"Limburg",
    "wof:name":"Livra",
    "wof:placetype":"venue"
},
  "geometry": {"coordinates":[5.3000240326,50.9849624634],"type":"Point"}
}