{
  "type": "Feature",
  "properties": {
    "iso:country":"BE",
    "sg:address":"Vrijheidsstraat 12",
    "sg:city":"Rotselaar",
    "sg:classifiers":[
        {
            "category":"Wholesale",
            "subcategory":"Scrap",
            "type":"Manufacturing & Wholesale Goods"
        }
    ],
    "sg:phone":"+32 16 44 47 11",
    "sg:postcode":"3110",
    "sg:province":"Vlaams-Brabant",
    "sg:tags":[
        "metal"
    ],
    "wof:name":"Dechamps & Zn",
    "wof:placetype":"venue"
},
  "geometry": {"coordinates":[4.6940941811,50.9441833496],"type":"Point"}
}