{
  "type": "Feature",
  "properties": {
    "addr:full":"Fortbaan 56 Schoten Antwerpen 2900",
    "addr:housenumber":"56",
    "addr:postcode":"2900",
    "addr:street":"Fortbaan",
    "iso:country":"BE",
    "sg:address":"Fortbaan 56",
    "sg:city":"Schoten",
    "sg:orig_category":"Schoonheidssalons",
    "sg:phone":"+32 3 651 40 16",
    "sg:postcode":"2900",
    "sg:province":"Antwerpen",
    "wof:name":"Betty Van Den Keybus",
    "wof:placetype":"venue"
},
  "geometry": {"coordinates":[4.5200171471,51.2778549194],"type":"Point"}
}