{
  "type": "Feature",
  "properties": {
    "iso:country":"BE",
    "sg:address":"Elizabetlaan 86",
    "sg:city":"Knokke-heist",
    "sg:orig_category":"Artsen and specialisten",
    "sg:phone":"+32 50 61 16 56",
    "sg:postcode":"8300",
    "sg:province":"West-Vlaanderen",
    "wof:name":"Calix De Clercq",
    "wof:placetype":"venue"
},
  "geometry": {"coordinates":[3.2911529541,51.3471412659],"type":"Point"}
}