{
  "type": "Feature",
  "properties": {
    "iso:country":"BE",
    "sg:address":"Meerlaan 137",
    "sg:city":"Knokke-heist (knokke)",
    "sg:classifiers":[
        {
            "category":"Social Services",
            "subcategory":"Job Training",
            "type":"Services"
        }
    ],
    "sg:phone":"+32 50 60 67 65",
    "sg:postcode":"8300",
    "sg:province":"West-Vlaanderen",
    "sg:tags":[
        "interpreter"
    ],
    "wof:name":"Jurion K",
    "wof:placetype":"venue"
},
  "geometry": {"coordinates":[3.2755610943,51.3457756042],"type":"Point"}
}