{
  "type": "Feature",
  "properties": {
    "addr:full":"Albrechtlaan 21 Aalst Oost-Vlaanderen 9300",
    "addr:housenumber":"21",
    "addr:postcode":"9300",
    "addr:street":"Albrechtlaan",
    "iso:country":"BE",
    "sg:address":"Albrechtlaan 21",
    "sg:city":"Aalst",
    "sg:orig_category":"Evaluation and estimation de biens immobiliers",
    "sg:phone":"+32 53 21 14 40",
    "sg:postcode":"9300",
    "sg:province":"Oost-Vlaanderen",
    "wof:name":"Vastgoedadvies",
    "wof:placetype":"venue"
},
  "geometry": {"coordinates":[4.0550441742,50.9354057312],"type":"Point"}
}