{
  "type": "Feature",
  "properties": {
    "addr:full":"Rue D'oignies 129 Aiseau-presles (aiseau) Hainaut 6250",
    "addr:housenumber":"129",
    "addr:postcode":"6250",
    "addr:street":"Rue D'Oignies",
    "iso:country":"BE",
    "sg:address":"Rue D'oignies 129",
    "sg:city":"Aiseau-presles (aiseau)",
    "sg:classifiers":[
        {
            "category":"Building & Trades",
            "subcategory":"Construction",
            "type":"Services"
        }
    ],
    "sg:phone":"+32 71 74 03 00",
    "sg:postcode":"6250",
    "sg:province":"Hainaut",
    "sg:tags":[
        "builder",
        "chimney"
    ],
    "wof:name":"Serra (ets)",
    "wof:placetype":"venue"
},
  "geometry": {"coordinates":[4.608397007,50.4262924194],"type":"Point"}
}