{
  "type": "Feature",
  "properties": {
    "iso:country":"BE",
    "sg:address":"Hoogvorstweg 6",
    "sg:city":"Tervuren",
    "sg:orig_category":"Immobili\u00ebnkantoren",
    "sg:phone":"+32 2 767 59 32",
    "sg:postcode":"3080",
    "sg:province":"Vlaams-Brabant",
    "wof:name":"Home Hunter",
    "wof:placetype":"venue"
},
  "geometry": {"coordinates":[4.4985737801,50.823551178],"type":"Point"}
}