{
  "type": "Feature",
  "properties": {
    "iso:country":"BE",
    "sg:address":"Nekkersberglaan 10",
    "sg:city":"Gent",
    "sg:orig_category":"Journaux. Epiceries",
    "sg:phone":"+32 9 222 74 15",
    "sg:postcode":"9000",
    "sg:province":"Oost-Vlaanderen",
    "wof:name":"Centra Madrik",
    "wof:placetype":"venue"
},
  "geometry": {"coordinates":[3.6974570751,51.0450325012],"type":"Point"}
}