{
  "type": "Feature",
  "properties": {
    "iso:country":"BE",
    "sg:address":"Chauss\u00c9e De La Verte Voie 103",
    "sg:city":"Wavre",
    "sg:orig_category":"Experts-comptables. Comptables. Conseillers fiscaux. Assistances juridiques",
    "sg:phone":"+32 10 24 44 56",
    "sg:postcode":"1300",
    "sg:province":"Brabant Wallon",
    "wof:name":"Beno\u00cet Meurmans",
    "wof:placetype":"venue"
},
  "geometry": {"coordinates":[4.6084370613,50.7324981689],"type":"Point"}
}