{
  "type": "Feature",
  "properties": {
    "addr:full":"Rue Emile Tumelaire 19 Charleroi Hainaut 6000",
    "addr:housenumber":"19",
    "addr:postcode":"6000",
    "addr:street":"Rue Emile Tumelaire;Hainaut",
    "iso:country":"BE",
    "sg:address":"Rue Emile Tumelaire 19",
    "sg:city":"Charleroi",
    "sg:classifiers":[
        {
            "category":"Restaurant",
            "type":"Food & Drink"
        }
    ],
    "sg:phone":"+32 71 30 77 40",
    "sg:postcode":"6000",
    "sg:province":"Hainaut",
    "wof:name":"L'amaryllis",
    "wof:placetype":"venue"
},
  "geometry": {"coordinates":[4.447329998,50.4110603333],"type":"Point"}
}