{
  "type": "Feature",
  "properties": {
    "addr:full":"Mansionstraat 20 Wuustwezel Antwerpen 2990",
    "addr:housenumber":"20",
    "addr:postcode":"2990",
    "addr:street":"Mansionstraat",
    "iso:country":"BE",
    "sg:address":"Mansionstraat 20",
    "sg:city":"Wuustwezel",
    "sg:classifiers":[
        {
            "category":"Shopping",
            "subcategory":"Hobbies, Toys, & Games",
            "type":"Retail Goods"
        }
    ],
    "sg:phone":"+32 3 633 15 35",
    "sg:postcode":"2990",
    "sg:province":"Antwerpen",
    "sg:tags":[
        "computer",
        "video"
    ],
    "wof:name":"Cdline",
    "wof:placetype":"venue"
},
  "geometry": {"coordinates":[4.5526080132,51.3609313965],"type":"Point"}
}