{
  "type": "Feature",
  "properties": {
    "addr:full":"Nerenweg 41a Laarne (kalken) Oost-Vlaanderen 9270",
    "addr:housenumber":"41a",
    "addr:postcode":"9270",
    "addr:street":"Nerenweg",
    "iso:country":"BE",
    "sg:address":"Nerenweg 41a",
    "sg:city":"Laarne (kalken)",
    "sg:classifiers":[
        {
            "category":"Home & Garden",
            "subcategory":"Household Appliances",
            "type":"Retail Goods"
        }
    ],
    "sg:phone":"+32 9 367 93 39",
    "sg:postcode":"9270",
    "sg:province":"Oost-Vlaanderen",
    "sg:tags":[
        "repair",
        "mainten",
        "-",
        "electric"
    ],
    "wof:name":"Verhoeven Elektro",
    "wof:placetype":"venue"
},
  "geometry": {"coordinates":[3.9123558998,51.0361366272],"type":"Point"}
}