{
  "type": "Feature",
  "properties": {
    "iso:country":"BE",
    "sg:address":"Place De Jamagne 11",
    "sg:city":"Jamagne",
    "sg:orig_category":"Computers and computerapparatuur Kantoormateriaal",
    "sg:phone":"+32 494 85 87 56",
    "sg:postcode":"5600",
    "sg:province":"Namur",
    "wof:name":"Multimedia House",
    "wof:placetype":"venue"
},
  "geometry": {"coordinates":[4.5328559875,50.2195205688],"type":"Point"}
}