{
  "type": "Feature",
  "properties": {
    "addr:full":"Chauss\u00e9e De Namur 34 Nivelles Brabant Wallon 1400",
    "addr:housenumber":"34",
    "addr:postcode":"1400",
    "addr:street":"Chausse\u0301E De Namur",
    "iso:country":"BE",
    "sg:address":"Chauss\u00e9e De Namur 34",
    "sg:city":"Nivelles",
    "sg:classifiers":[
        {
            "category":"Health Services",
            "subcategory":"Hospital",
            "type":"Services"
        }
    ],
    "sg:phone":"+32 67 84 23 13",
    "sg:postcode":"1400",
    "sg:province":"Brabant Wallon",
    "wof:name":"Agathos",
    "wof:placetype":"venue"
},
  "geometry": {"coordinates":[4.3466629982,50.598991394],"type":"Point"}
}