{
  "type": "Feature",
  "properties": {
    "iso:country":"BE",
    "sg:address":"Koningin Fabiolastraat 54",
    "sg:city":"Wevelgem (gullegem)",
    "sg:classifiers":[
        {
            "category":"Professional",
            "subcategory":"Printing & Photocopies",
            "type":"Services"
        }
    ],
    "sg:phone":"+32 56 41 82 14",
    "sg:postcode":"8560",
    "sg:province":"West-Vlaanderen",
    "sg:tags":[
        "trophy",
        "medal"
    ],
    "wof:name":"Marca-hico Cvoha",
    "wof:placetype":"venue"
},
  "geometry": {"coordinates":[3.2018229961,50.8404121399],"type":"Point"}
}