{
  "type": "Feature",
  "properties": {
    "addr:full":"7170 Manage Hainaut 7170",
    "addr:postcode":"7170;7170",
    "addr:street":"Hainaut",
    "iso:country":"BE",
    "sg:address":"7170",
    "sg:city":"Manage",
    "sg:classifiers":[
        {
            "category":"Taxi",
            "type":"Transportation"
        }
    ],
    "sg:phone":"+32 64 84 91 91",
    "sg:postcode":"7170",
    "sg:province":"Hainaut",
    "wof:name":"Taxi Manageois",
    "wof:placetype":"venue"
},
  "geometry": {"coordinates":[4.2327899933,50.5008239746],"type":"Point"}
}