{
  "type": "Feature",
  "properties": {
    "iso:country":"BE",
    "sg:address":"Koopvaardijlaan 43",
    "sg:city":"Gent",
    "sg:orig_category":"B\u00e9ton pr\u00eat \u00e0 l'emploi Fab",
    "sg:phone":"+32 9 223 88 20",
    "sg:postcode":"9000",
    "sg:province":"Oost-Vlaanderen",
    "wof:name":"Readymix",
    "wof:placetype":"venue"
},
  "geometry": {"coordinates":[3.7385649681,51.0601882935],"type":"Point"}
}