{
  "type": "Feature",
  "properties": {
    "addr:full":"Guldensporenpark 30 Merelbeke Oost-Vlaanderen 9820",
    "addr:housenumber":"30",
    "addr:postcode":"9820",
    "addr:street":"Guldensporenpark",
    "iso:country":"BE",
    "sg:address":"Guldensporenpark 30",
    "sg:city":"Merelbeke",
    "sg:classifiers":[
        {
            "category":"Utilities",
            "subcategory":"Electric",
            "type":"Services"
        }
    ],
    "sg:phone":"+32 9 210 38 11",
    "sg:postcode":"9820",
    "sg:province":"Oost-Vlaanderen",
    "sg:tags":[
        "electricity",
        "electronic",
        "electrical",
        "equipment"
    ],
    "wof:name":"Ge Power Controls Belgium Bvba",
    "wof:placetype":"venue"
},
  "geometry": {"coordinates":[3.7559390068,51.0053787231],"type":"Point"}
}