{
  "type": "Feature",
  "properties": {
    "addr:full":"Weg Naar Zwartberg 88a Houthalen-helchteren (houthalen) Limburg 3530",
    "addr:housenumber":"88a",
    "addr:postcode":"3530",
    "addr:street":"Weg Naar Zwartberg",
    "iso:country":"BE",
    "sg:address":"Weg Naar Zwartberg 88a",
    "sg:city":"Houthalen-helchteren (houthalen)",
    "sg:classifiers":[
        {
            "category":"Food & Beverages",
            "subcategory":"Supermarket",
            "type":"Retail Goods"
        }
    ],
    "sg:phone":"+32 89 84 53 76",
    "sg:postcode":"3530",
    "sg:province":"Limburg",
    "sg:tags":[
        "department",
        "store"
    ],
    "wof:name":"Corragio",
    "wof:placetype":"venue"
},
  "geometry": {"coordinates":[5.4662008286,51.022277832],"type":"Point"}
}