{
  "type": "Feature",
  "properties": {
    "iso:country":"BE",
    "sg:address":"Chauss\u00e9e De Louvain 52",
    "sg:city":"Wavre",
    "sg:classifiers":[
        {
            "category":"Bakery",
            "type":"Food & Drink"
        }
    ],
    "sg:phone":"+32 10 22 77 74",
    "sg:postcode":"1300",
    "sg:province":"Brabant Wallon",
    "sg:tags":[
        "confectioner",
        "baker"
    ],
    "wof:name":"Delcorps-gillot",
    "wof:placetype":"venue"
},
  "geometry": {"coordinates":[4.6156949997,50.7148704529],"type":"Point"}
}