{
  "type": "Feature",
  "properties": {
    "addr:full":"Vissersplein 8 Oostende West-Vlaanderen 8400",
    "addr:housenumber":"8",
    "addr:postcode":"8400",
    "addr:street":"Vissersplein",
    "iso:country":"BE",
    "sg:address":"Vissersplein 8",
    "sg:city":"Oostende",
    "sg:classifiers":[
        {
            "category":"Tea Room",
            "subcategory":"None",
            "type":"Food & Drink"
        }
    ],
    "sg:phone":"+32 59 70 68 15",
    "sg:postcode":"8400",
    "sg:province":"West-Vlaanderen",
    "wof:name":"Montgomery",
    "wof:placetype":"venue"
},
  "geometry": {"coordinates":[2.9231879711,51.2307548523],"type":"Point"}
}