{
  "type": "Feature",
  "properties": {
    "iso:country":"BE",
    "sg:address":"Molendijk 17",
    "sg:city":"Hamont-achel",
    "sg:orig_category":"Brood, gebak and snoepgoed",
    "sg:phone":"+32 11 66 57 90",
    "sg:postcode":"3930",
    "sg:province":"Limburg",
    "wof:name":"Eric Schuermans",
    "wof:placetype":"venue"
},
  "geometry": {"coordinates":[5.4777917862,51.2652778625],"type":"Point"}
}