{
  "type": "Feature",
  "properties": {
    "iso:country":"BE",
    "sg:address":"Louis Mettewielaan 67b4",
    "sg:city":"Sint-jans-molenbeek/molenbeek-saint-jean",
    "sg:orig_category":"Apotheken",
    "sg:phone":"+32 2 537 81 29",
    "sg:postcode":"1080",
    "sg:province":"Bruxelles-Capitale",
    "wof:name":"Pharmacie Sauveni\u00c8re",
    "wof:placetype":"venue"
},
  "geometry": {"coordinates":[4.3059000969,50.8550605774],"type":"Point"}
}