{
  "type": "Feature",
  "properties": {
    "addr:full":"Rue Louis Franson 23 La Louviere Hainaut 7100",
    "addr:housenumber":"23",
    "addr:postcode":"7100",
    "addr:street":"Rue Louis Franson",
    "iso:country":"BE",
    "sg:address":"Rue Louis Franson 23",
    "sg:city":"La Louviere",
    "sg:orig_category":"Artsen and specialisten",
    "sg:phone":"+32 64 22 16 03",
    "sg:postcode":"7100",
    "sg:province":"Hainaut",
    "wof:name":"Labo Dr. Vinken Willy",
    "wof:placetype":"venue"
},
  "geometry": {"coordinates":[4.1808300018,50.4708595276],"type":"Point"}
}