{
  "type": "Feature",
  "properties": {
    "iso:country":"BE",
    "sg:address":"Gatti De Gamondstraat 145",
    "sg:city":"Ukkel",
    "sg:classifiers":[
        {
            "category":"Professional",
            "subcategory":"Engineering",
            "type":"Services"
        }
    ],
    "sg:phone":"+32 2 332 35 32",
    "sg:postcode":"1180",
    "sg:province":"Bruxelles-Capitale",
    "wof:name":"Ob-si Nv",
    "wof:placetype":"venue"
},
  "geometry": {"coordinates":[4.3274250031,50.8021621704],"type":"Point"}
}