{
  "type": "Feature",
  "properties": {
    "iso:country":"BE",
    "sg:address":"Kerkstraat 39",
    "sg:city":"Boutersem (kerkom)",
    "sg:classifiers":[
        {
            "category":"Transit Center",
            "subcategory":"Passenger",
            "type":"Transportation"
        }
    ],
    "sg:phone":"+32 16 73 31 19",
    "sg:postcode":"3370",
    "sg:province":"Vlaams-Brabant",
    "sg:tags":[
        "sand",
        "gravel"
    ],
    "wof:name":"Wouters E",
    "wof:placetype":"venue"
},
  "geometry": {"coordinates":[4.8307170868,50.8303451538],"type":"Point"}
}