{
  "type": "Feature",
  "properties": {
    "addr:full":"Rue De Malispr\u00c9 9 Rochefort Namur 5580",
    "addr:housenumber":"9",
    "addr:postcode":"5580",
    "addr:street":"Rue De Malispre\u0301",
    "iso:country":"BE",
    "sg:address":"Rue De Malispr\u00c9 9",
    "sg:city":"Rochefort",
    "sg:orig_category":"V\u00e9t\u00e9rinaires",
    "sg:phone":"+32 84 37 79 55",
    "sg:postcode":"5580",
    "sg:province":"Namur",
    "wof:name":"Didier Vanderbiest",
    "wof:placetype":"venue"
},
  "geometry": {"coordinates":[5.2231431007,50.1608505249],"type":"Point"}
}