{
  "type": "Feature",
  "properties": {
    "addr:full":"Sportlaan 1 Zomergem Oost-Vlaanderen 9930",
    "addr:housenumber":"1",
    "addr:postcode":"9930",
    "addr:street":"Sportlaan",
    "iso:country":"BE",
    "sg:address":"Sportlaan 1",
    "sg:city":"Zomergem",
    "sg:classifiers":[
        {
            "category":"Government",
            "subcategory":"Police Station",
            "type":"Public Place"
        }
    ],
    "sg:phone":"+32 9 372 70 13",
    "sg:postcode":"9930",
    "sg:province":"Oost-Vlaanderen",
    "sg:tags":[
        "gendarmerie"
    ],
    "wof:name":"Federale Politie/police F\u00c9d\u00c9rale",
    "wof:placetype":"venue"
},
  "geometry": {"coordinates":[3.5606300831,51.12266922],"type":"Point"}
}