{
  "type": "Feature",
  "properties": {
    "addr:full":"Rue Fontaine Saint-pierre 1j Assesse Namur 5330",
    "addr:housenumber":"1j",
    "addr:postcode":"5330",
    "addr:street":"Rue Fontaine Saint-Pierre",
    "iso:country":"BE",
    "sg:address":"Rue Fontaine Saint-pierre 1j",
    "sg:city":"Assesse",
    "sg:classifiers":[
        {
            "category":"Professional",
            "subcategory":"Computer Services",
            "type":"Services"
        }
    ],
    "sg:phone":"+32 83 66 05 00",
    "sg:postcode":"5330",
    "sg:province":"Namur",
    "sg:tags":[
        "-",
        "processing",
        "data",
        "software"
    ],
    "wof:name":"Archibel",
    "wof:placetype":"venue"
},
  "geometry": {"coordinates":[5.0442857742,50.3694496155],"type":"Point"}
}