{
  "type": "Feature",
  "properties": {
    "addr:full":"Biezenstraat 2 Roeselare West-Vlaanderen 8800",
    "addr:housenumber":"2",
    "addr:postcode":"8800",
    "addr:street":"Biezenstraat",
    "iso:country":"BE",
    "sg:address":"Biezenstraat 2",
    "sg:city":"Roeselare",
    "sg:classifiers":[
        {
            "category":"Health Services",
            "subcategory":"Health Practitioner",
            "type":"Services"
        }
    ],
    "sg:phone":"+32 51 25 27 21",
    "sg:postcode":"8800",
    "sg:province":"West-Vlaanderen",
    "sg:tags":[
        "alternative",
        "therapy",
        "treatment"
    ],
    "wof:name":"Dekostere S-kyo-instituut",
    "wof:placetype":"venue"
},
  "geometry": {"coordinates":[3.1052029133,50.9589805603],"type":"Point"}
}