{
  "type": "Feature",
  "properties": {
    "addr:full":"Nieuweweg 3 Boechout Antwerpen 2530",
    "addr:housenumber":"3",
    "addr:postcode":"2530",
    "addr:street":"Nieuweweg",
    "iso:country":"BE",
    "sg:address":"Nieuweweg 3",
    "sg:city":"Boechout",
    "sg:orig_category":"Eleveurs de bovins",
    "sg:phone":"+32 3 480 20 72",
    "sg:postcode":"2530",
    "sg:province":"Antwerpen",
    "wof:name":"Leon De Vos",
    "wof:placetype":"venue"
},
  "geometry": {"coordinates":[4.5363841057,51.1612663269],"type":"Point"}
}