{
  "type": "Feature",
  "properties": {
    "addr:full":"Rue Biez Du Moulin 50 Seraing (ougr\u00e9e) Li\u00e8ge 4102",
    "addr:housenumber":"50",
    "addr:postcode":"4102",
    "addr:street":"Rue Biez Du Moulin",
    "iso:country":"BE",
    "sg:address":"Rue Biez Du Moulin 50",
    "sg:city":"Seraing (ougr\u00e9e)",
    "sg:classifiers":[
        {
            "category":"Fast Food",
            "type":"Food & Drink"
        }
    ],
    "sg:phone":"+32 4 337 04 56",
    "sg:postcode":"4102",
    "sg:province":"Li\u00e8ge",
    "sg:tags":[
        "fried",
        "stand",
        "potato"
    ],
    "wof:name":"Biez Du Moulin",
    "wof:placetype":"venue"
},
  "geometry": {"coordinates":[5.5419778824,50.6002655029],"type":"Point"}
}