{
  "type": "Feature",
  "properties": {
    "iso:country":"BE",
    "sg:address":"Kalkenstraat",
    "sg:city":"Buggenhout",
    "sg:classifiers":[
        {
            "category":"Exhibition Hall",
            "type":"Public Place"
        }
    ],
    "sg:phone":"+32 52 34 15 11",
    "sg:postcode":"9255",
    "sg:province":"Oost-Vlaanderen",
    "sg:tags":[
        "stand"
    ],
    "wof:name":"Diverso Standenbouw",
    "wof:placetype":"venue"
},
  "geometry": {"coordinates":[4.2049851418,51.004901886],"type":"Point"}
}