{
  "type": "Feature",
  "properties": {
    "addr:full":"Emile Bouilliotstraat 29b7 Elsene/ixelles Bruxelles-Capitale 1050",
    "addr:housenumber":"29b7",
    "addr:postcode":"1050",
    "addr:street":"Emile Bouilliotstraat",
    "iso:country":"BE",
    "sg:address":"Emile Bouilliotstraat 29b7",
    "sg:city":"Elsene/ixelles",
    "sg:orig_category":"Artsen and specialisten",
    "sg:phone":"+32 2 347 42 68",
    "sg:postcode":"1050",
    "sg:province":"Bruxelles-Capitale",
    "wof:name":"Charles Gosseries",
    "wof:placetype":"venue"
},
  "geometry": {"coordinates":[4.3540511131,50.8184890747],"type":"Point"}
}