{
  "type": "Feature",
  "properties": {
    "iso:country":"BE",
    "sg:address":"Oude Baan 5",
    "sg:city":"Rijkevorsel",
    "sg:orig_category":"Producteurs de l\u00e9gumes",
    "sg:phone":"+32 3 314 63 33",
    "sg:postcode":"2310",
    "sg:province":"Antwerpen",
    "wof:name":"Frans Hermans",
    "wof:placetype":"venue"
},
  "geometry": {"coordinates":[4.7421588898,51.3436393738],"type":"Point"}
}