{
  "type": "Feature",
  "properties": {
    "addr:full":"Strandlaan 49 Koksijde West-Vlaanderen 8670",
    "addr:housenumber":"49",
    "addr:postcode":"8670",
    "addr:street":"Strandlaan",
    "iso:country":"BE",
    "sg:address":"Strandlaan 49",
    "sg:city":"Koksijde",
    "sg:orig_category":"Woningbouw",
    "sg:phone":"+32 58 51 50 73",
    "sg:postcode":"8670",
    "sg:province":"West-Vlaanderen",
    "wof:name":"Norbert Meirlevede",
    "wof:placetype":"venue"
},
  "geometry": {"coordinates":[2.6269450188,51.1023979187],"type":"Point"}
}