{
  "type": "Feature",
  "properties": {
    "addr:full":"Graanmarkt 17 Aalst Oost-Vlaanderen 9300",
    "addr:housenumber":"17",
    "addr:postcode":"9300",
    "addr:street":"Graanmarkt",
    "iso:country":"BE",
    "sg:address":"Graanmarkt 17",
    "sg:city":"Aalst",
    "sg:orig_category":"Advocaten and juridische adviseurs",
    "sg:phone":"+32 53 78 56 98",
    "sg:postcode":"9300",
    "sg:province":"Oost-Vlaanderen",
    "wof:name":"Bernadette Neckebrouck",
    "wof:placetype":"venue"
},
  "geometry": {"coordinates":[4.0400180817,50.9398193359],"type":"Point"}
}