{
  "type": "Feature",
  "properties": {
    "addr:full":"Mermansstraat 20 Turnhout Antwerpen 2300",
    "addr:housenumber":"20",
    "addr:postcode":"2300",
    "addr:street":"Mermansstraat",
    "iso:country":"BE",
    "sg:address":"Mermansstraat 20",
    "sg:city":"Turnhout",
    "sg:classifiers":[
        {
            "category":"Social Services",
            "type":"Services"
        }
    ],
    "sg:phone":"+32 14 41 27 25",
    "sg:postcode":"2300",
    "sg:province":"Antwerpen",
    "sg:tags":[
        "handicapped",
        "-"
    ],
    "wof:name":"Muylenberg",
    "wof:placetype":"venue"
},
  "geometry": {"coordinates":[4.9514579773,51.3192825317],"type":"Point"}
}