{
  "type": "Feature",
  "properties": {
    "addr:full":"Kabbeeksesteenweg Tienen Vlaams-Brabant 3300",
    "addr:postcode":"3300",
    "addr:street":"Kabbeeksesteenweg",
    "iso:country":"BE",
    "sg:address":"Kabbeeksesteenweg",
    "sg:city":"Tienen",
    "sg:classifiers":[
        {
            "category":"Fast Food",
            "type":"Food & Drink"
        }
    ],
    "sg:phone":"+32 16 81 70 28",
    "sg:postcode":"3300",
    "sg:province":"Vlaams-Brabant",
    "sg:tags":[
        "\u00c0",
        "emporter",
        "restaurants"
    ],
    "wof:name":"Frituur Kabbeeksesteenweg",
    "wof:placetype":"venue"
},
  "geometry": {"coordinates":[4.930077076,50.8096694946],"type":"Point"}
}