{
  "type": "Feature",
  "properties": {
    "addr:full":"Vrijheidstraat 15bh Temse Oost-Vlaanderen 9140",
    "addr:housenumber":"15bh",
    "addr:postcode":"9140",
    "addr:street":"Vrijheidstraat",
    "iso:country":"BE",
    "sg:address":"Vrijheidstraat 15bh",
    "sg:city":"Temse",
    "sg:classifiers":[
        {
            "category":"Shopping",
            "subcategory":"Clothing, Apparel, & Fashions",
            "type":"Retail Goods"
        }
    ],
    "sg:phone":"+32 3 771 28 13",
    "sg:postcode":"9140",
    "sg:province":"Oost-Vlaanderen",
    "sg:tags":[
        "v\u00eatements",
        "pour",
        "dame"
    ],
    "wof:name":"Claudia",
    "wof:placetype":"venue"
},
  "geometry": {"coordinates":[4.2187328339,51.128326416],"type":"Point"}
}