{
  "type": "Feature",
  "properties": {
    "iso:country":"BE",
    "sg:address":"Fortbaan 19a",
    "sg:city":"Schoten",
    "sg:classifiers":[
        {
            "category":"Building & Trades",
            "subcategory":"Electrical",
            "type":"Services"
        }
    ],
    "sg:phone":"+32 3 651 56 68",
    "sg:postcode":"2900",
    "sg:province":"Antwerpen",
    "sg:tags":[
        "heating"
    ],
    "wof:name":"Dimplex Electro Staes",
    "wof:placetype":"venue"
},
  "geometry": {"coordinates":[4.520512104,51.2760124207],"type":"Point"}
}