{
  "type": "Feature",
  "properties": {
    "addr:full":"Populierenlaan 16 Anzegem West-Vlaanderen 8570",
    "addr:housenumber":"16",
    "addr:postcode":"8570",
    "addr:street":"Populierenlaan",
    "iso:country":"BE",
    "sg:address":"Populierenlaan 16",
    "sg:city":"Anzegem",
    "sg:orig_category":"Installation de menuiserie en bois and plastique",
    "sg:phone":"+32 56 77 83 88",
    "sg:postcode":"8570",
    "sg:province":"West-Vlaanderen",
    "wof:name":"Vandemeulebroucke P.",
    "wof:placetype":"venue"
},
  "geometry": {"coordinates":[3.3991270065,50.8407478333],"type":"Point"}
}