{
  "type": "Feature",
  "properties": {
    "addr:full":"Varenlaan 9 Beersel Vlaams-Brabant 1652",
    "addr:housenumber":"9",
    "addr:postcode":"1652",
    "addr:street":"Varenlaan",
    "iso:country":"BE",
    "sg:address":"Varenlaan 9",
    "sg:city":"Beersel",
    "sg:orig_category":"Plaatsen van vloer- and muurbekleding Schilders Verlichting and huishoudartikelen",
    "sg:phone":"+32 2 380 20 98",
    "sg:postcode":"1652",
    "sg:province":"Vlaams-Brabant",
    "wof:name":"Arti-decor",
    "wof:placetype":"venue"
},
  "geometry": {"coordinates":[4.3259072304,50.7482566833],"type":"Point"}
}