{
  "type": "Feature",
  "properties": {
    "iso:country":"BE",
    "sg:address":"Zemstbaan 136",
    "sg:city":"Mechelen",
    "sg:orig_category":"Sportclubs",
    "sg:phone":"+32 15 42 34 23",
    "sg:postcode":"2800",
    "sg:province":"Antwerpen",
    "wof:name":"V.c. Hofo Kapelle-o.d.bos",
    "wof:placetype":"venue"
},
  "geometry": {"coordinates":[4.4716510773,50.9962806702],"type":"Point"}
}