{
  "type": "Feature",
  "properties": {
    "addr:full":"Kapelstraat 2 Bierbeek (honsem) Vlaams-Brabant 3360",
    "addr:housenumber":"2",
    "addr:postcode":"3360",
    "addr:street":"Kapelstraat",
    "iso:country":"BE",
    "sg:address":"Kapelstraat 2",
    "sg:city":"Bierbeek (honsem)",
    "sg:classifiers":[
        {
            "category":"Shopping",
            "subcategory":"Crafts & Fabrics",
            "type":"Retail Goods"
        }
    ],
    "sg:phone":"+32 16 73 40 88",
    "sg:postcode":"3360",
    "sg:province":"Vlaams-Brabant",
    "sg:tags":[
        "ceramic"
    ],
    "wof:name":"Swentibold Keramiek",
    "wof:placetype":"venue"
},
  "geometry": {"coordinates":[4.794547081,50.8083000183],"type":"Point"}
}