{
  "type": "Feature",
  "properties": {
    "iso:country":"BE",
    "sg:address":"Rue Willy Ernst 43",
    "sg:city":"Charleroi",
    "sg:classifiers":[
        {
            "category":"Bars & Pubs",
            "type":"Food & Drink"
        }
    ],
    "sg:phone":"+32 71 32 91 21",
    "sg:postcode":"6000",
    "sg:province":"Hainaut",
    "wof:name":"Vigne (la)",
    "wof:placetype":"venue"
},
  "geometry": {"coordinates":[4.4497241974,50.4098510742],"type":"Point"}
}