{
  "type": "Feature",
  "properties": {
    "addr:full":"2800 Mechelen Antwerpen 2800",
    "addr:postcode":"2800;2800",
    "iso:country":"BE",
    "sg:address":"2800",
    "sg:city":"Mechelen",
    "sg:orig_category":"Etablissements Erotiques",
    "sg:phone":"+32 15 20 11 01",
    "sg:postcode":"2800",
    "sg:province":"Antwerpen",
    "wof:name":"Marijke",
    "wof:placetype":"venue"
},
  "geometry": {"coordinates":[4.4678602219,51.0348815918],"type":"Point"}
}