{
  "type": "Feature",
  "properties": {
    "iso:country":"BE",
    "sg:address":"Rue Fragn\u00c9e 175",
    "sg:city":"Liege",
    "sg:orig_category":"Jeux de hasard",
    "sg:phone":"+32 4 254 20 96",
    "sg:postcode":"4000",
    "sg:province":"Li\u00e8ge",
    "wof:name":"Dumoulin Agence Hippique",
    "wof:placetype":"venue"
},
  "geometry": {"coordinates":[5.578110218,50.6206436157],"type":"Point"}
}