{
  "type": "Feature",
  "properties": {
    "addr:full":"Rue De Charneux 94 Herve Li\u00e8ge 4650",
    "addr:housenumber":"94",
    "addr:postcode":"4650",
    "addr:street":"Rue De Charneux",
    "iso:country":"BE",
    "sg:address":"Rue De Charneux 94",
    "sg:city":"Herve",
    "sg:classifiers":[
        {
            "category":"Farming",
            "subcategory":"Livestock Farm",
            "type":"Manufacturing & Wholesale Goods"
        }
    ],
    "sg:phone":"+32 87 69 35 20",
    "sg:postcode":"4650",
    "sg:province":"Li\u00e8ge",
    "sg:tags":[
        "buyer"
    ],
    "wof:name":"Hall De Cri\u00e9e",
    "wof:placetype":"venue"
},
  "geometry": {"coordinates":[5.7964501381,50.6460800171],"type":"Point"}
}