{
  "type": "Feature",
  "properties": {
    "addr:full":"Reusestraat 29 Roosdaal (borchtlombeek) Vlaams-Brabant 1761",
    "addr:housenumber":"29",
    "addr:postcode":"1761",
    "addr:street":"Reusestraat",
    "iso:country":"BE",
    "sg:address":"Reusestraat 29",
    "sg:city":"Roosdaal (borchtlombeek)",
    "sg:classifiers":[
        {
            "category":"Manufacturing",
            "subcategory":"Metals",
            "type":"Manufacturing & Wholesale Goods"
        }
    ],
    "sg:phone":"+32 53 67 22 03",
    "sg:postcode":"1761",
    "sg:province":"Vlaams-Brabant",
    "sg:tags":[
        "ironwork"
    ],
    "wof:name":"Verbeeren Metaalwerken Bvba",
    "wof:placetype":"venue"
},
  "geometry": {"coordinates":[4.136548996,50.848526001],"type":"Point"}
}