{
  "type": "Feature",
  "properties": {
    "addr:full":"Sint-baafskerkstraat 5 Brugge West-Vlaanderen 8200",
    "addr:housenumber":"5",
    "addr:postcode":"8200",
    "addr:street":"Sint-Baafskerkstraat",
    "iso:country":"BE",
    "sg:address":"Sint-baafskerkstraat 5",
    "sg:city":"Brugge",
    "sg:orig_category":"Sociale huisvestingsmaatschappijen Woningbouw",
    "sg:phone":"+32 50 39 28 34",
    "sg:postcode":"8200",
    "sg:province":"West-Vlaanderen",
    "wof:name":"Multibouw",
    "wof:placetype":"venue"
},
  "geometry": {"coordinates":[3.2050559521,51.2022895813],"type":"Point"}
}