{
  "type": "Feature",
  "properties": {
    "addr:full":"Avenue De La Cit\u00c9 2 Binche Hainaut 7130",
    "addr:housenumber":"2",
    "addr:postcode":"7130",
    "addr:street":"Avenue De La Cite\u0301",
    "iso:country":"BE",
    "sg:address":"Avenue De La Cit\u00c9 2",
    "sg:city":"Binche",
    "sg:orig_category":"HERSTELLING ELEKTRISCHE HUISHOUDAPPARATEN Huishoudapparaten, televisies and radio's",
    "sg:phone":"+32 64 33 74 28",
    "sg:postcode":"7130",
    "sg:province":"Hainaut",
    "wof:name":"Fe. Benacchio",
    "wof:placetype":"venue"
},
  "geometry": {"coordinates":[4.0892529488,50.4328193665],"type":"Point"}
}