{
  "type": "Feature",
  "properties": {
    "addr:full":"Pieter Breugellaan 32 Peer (kleine Brogel) Limburg 3990",
    "addr:housenumber":"32",
    "addr:postcode":"3990",
    "addr:street":"Pieter Breugellaan;Kleine Brogel Limburg",
    "iso:country":"BE",
    "sg:address":"Pieter Breugellaan 32",
    "sg:city":"Peer (kleine Brogel)",
    "sg:classifiers":[
        {
            "category":"Health Services",
            "subcategory":"Health Practitioner",
            "type":"Services"
        }
    ],
    "sg:phone":"+32 11 63 24 27",
    "sg:postcode":"3990",
    "sg:province":"Limburg",
    "sg:tags":[
        "physiotherapist"
    ],
    "wof:name":"Roex G",
    "wof:placetype":"venue"
},
  "geometry": {"coordinates":[5.4533009529,51.1329536438],"type":"Point"}
}