{
  "type": "Feature",
  "properties": {
    "addr:full":"All\u00e9e Des Sorbiers 5 Gerpinnes Hainaut 6280",
    "addr:housenumber":"5",
    "addr:postcode":"6280",
    "addr:street":"Alle\u0301E Des Sorbiers;Hainaut",
    "iso:country":"BE",
    "sg:address":"All\u00e9e Des Sorbiers 5",
    "sg:city":"Gerpinnes",
    "sg:classifiers":[
        {
            "category":"Wholesale",
            "subcategory":"Meat",
            "type":"Manufacturing & Wholesale Goods"
        }
    ],
    "sg:phone":"+32 71 21 65 08",
    "sg:postcode":"6280",
    "sg:province":"Hainaut",
    "sg:tags":[
        "whol",
        "-"
    ],
    "wof:name":"Dussart Jean Sa",
    "wof:placetype":"venue"
},
  "geometry": {"coordinates":[4.4746527672,50.3447875977],"type":"Point"}
}