{
  "type": "Feature",
  "properties": {
    "iso:country":"BE",
    "sg:address":"Sint-quirinuslaan 17",
    "sg:city":"Asse (zellik)",
    "sg:orig_category":"Non-Classified Establishments",
    "sg:phone":"+32 2 466 19 94",
    "sg:postcode":"1731",
    "sg:province":"Vlaams-Brabant",
    "wof:name":"Roussel J Bvba",
    "wof:placetype":"venue"
},
  "geometry": {"coordinates":[4.26770401,50.8867835999],"type":"Point"}
}