{
  "type": "Feature",
  "properties": {
    "addr:full":"Rijksweg 161 Maasmechelen Limburg 3630",
    "addr:housenumber":"161",
    "addr:postcode":"3630",
    "addr:street":"Rijksweg",
    "iso:country":"BE",
    "sg:address":"Rijksweg 161",
    "sg:city":"Maasmechelen",
    "sg:classifiers":[
        {
            "category":"Professional",
            "subcategory":"Accounting & Tax Preparation",
            "type":"Services"
        }
    ],
    "sg:phone":"+32 89 77 46 90",
    "sg:postcode":"3630",
    "sg:province":"Limburg",
    "sg:tags":[
        "bookkeeper"
    ],
    "wof:name":"Meuris J-j",
    "wof:placetype":"venue"
},
  "geometry": {"coordinates":[5.701086998,50.9788475037],"type":"Point"}
}