{
  "type": "Feature",
  "properties": {
    "addr:full":"Chauss\u00c9e De Wavre 80 Jodoigne Brabant Wallon 1370",
    "addr:housenumber":"80",
    "addr:postcode":"1370",
    "addr:street":"Chausse\u0301E De Wavre",
    "iso:country":"BE",
    "sg:address":"Chauss\u00c9e De Wavre 80",
    "sg:city":"Jodoigne",
    "sg:orig_category":"V\u00e9hicules automobiles",
    "sg:phone":"+32 10 81 54 90",
    "sg:postcode":"1370",
    "sg:province":"Brabant Wallon",
    "wof:name":"R.g. Automobiles",
    "wof:placetype":"venue"
},
  "geometry": {"coordinates":[4.8587441444,50.7240753174],"type":"Point"}
}