{
  "type": "Feature",
  "properties": {
    "addr:full":"Vlinderstraat 21 Heusden-zolder Limburg 3550",
    "addr:housenumber":"21",
    "addr:postcode":"3550",
    "addr:street":"Vlinderstraat",
    "iso:country":"BE",
    "sg:address":"Vlinderstraat 21",
    "sg:city":"Heusden-zolder",
    "sg:orig_category":"Services de s\u00e9curit\u00e9 and entreprises de gardiennage",
    "sg:phone":"+32 11 53 95 10",
    "sg:postcode":"3550",
    "sg:province":"Limburg",
    "wof:name":"Group 4 Total Security",
    "wof:placetype":"venue"
},
  "geometry": {"coordinates":[5.3440680504,51.0201721191],"type":"Point"}
}