{
  "type": "Feature",
  "properties": {
    "addr:full":"Chauss\u00e9e De Mons 909-913 Bruxelles (anderlecht) Bruxelles-Capitale 1070",
    "addr:postcode":"909-913;1070",
    "addr:street":"Chausse\u0301E De Mons",
    "iso:country":"BE",
    "sg:address":"Chauss\u00e9e De Mons 909-913",
    "sg:city":"Bruxelles (anderlecht)",
    "sg:classifiers":[
        {
            "category":"Autos & Motor Vehicles",
            "subcategory":"Auto Supplies",
            "type":"Retail Goods"
        }
    ],
    "sg:phone":"+32 2 526 22 05",
    "sg:postcode":"1070",
    "sg:province":"Bruxelles-Capitale",
    "sg:tags":[
        "access",
        "automobile",
        "part",
        "-"
    ],
    "wof:name":"Stappers Belgium Sa",
    "wof:placetype":"venue"
},
  "geometry": {"coordinates":[4.300383091,50.8270797729],"type":"Point"}
}