{
  "type": "Feature",
  "properties": {
    "iso:country":"BE",
    "sg:address":"Brusselsesteenweg 742",
    "sg:city":"Asse",
    "sg:orig_category":"Huishoudapparaten, televisies and radio's Motoren, transformatoren and generatoren Fab Verhuur telev",
    "sg:phone":"+32 2 466 86 86",
    "sg:postcode":"1731",
    "sg:province":"Vlaams-Brabant",
    "wof:name":"Bulterys/b&l Lighting Services",
    "wof:placetype":"venue"
},
  "geometry": {"coordinates":[4.2801418304,50.8788032532],"type":"Point"}
}