{
  "type": "Feature",
  "properties": {
    "addr:full":"Brandstraat 39 Temse Oost-Vlaanderen 9140",
    "addr:housenumber":"39",
    "addr:postcode":"9140",
    "addr:street":"Brandstraat",
    "iso:country":"BE",
    "sg:address":"Brandstraat 39",
    "sg:city":"Temse",
    "sg:orig_category":"Plomberie, chauffage and installations sanitaires",
    "sg:phone":"+32 3 777 94 82",
    "sg:postcode":"9140",
    "sg:province":"Oost-Vlaanderen",
    "wof:name":"T.l.",
    "wof:placetype":"venue"
},
  "geometry": {"coordinates":[4.1916661263,51.1577301025],"type":"Point"}
}