{
  "type": "Feature",
  "properties": {
    "iso:country":"BE",
    "sg:address":"K. Deswertlaan 16",
    "sg:city":"Blankenberge",
    "sg:orig_category":"Diverse juridische dienstverlening",
    "sg:phone":"+32 50 41 89 21",
    "sg:postcode":"8370",
    "sg:province":"West-Vlaanderen",
    "wof:name":"Verkoopzaal Eric",
    "wof:placetype":"venue"
},
  "geometry": {"coordinates":[3.1309289932,51.3114700317],"type":"Point"}
}