{
  "type": "Feature",
  "properties": {
    "iso:country":"BE",
    "sg:address":"Lange Leemstraat 15",
    "sg:city":"Antwerpen",
    "sg:orig_category":"Auto-\u00e9coles",
    "sg:phone":"+32 3 234 36 35",
    "sg:postcode":"2018",
    "sg:province":"Antwerpen",
    "wof:name":"A.r.m.",
    "wof:placetype":"venue"
},
  "geometry": {"coordinates":[4.4099230766,51.2103347778],"type":"Point"}
}