{
  "type": "Feature",
  "properties": {
    "iso:country":"BE",
    "sg:address":"Koningsstraat 163",
    "sg:city":"Sint-joost-ten-node/saint-josse-ten-noode",
    "sg:orig_category":"Marktonderzoekbureaus",
    "sg:phone":"+32 2 227 63 80",
    "sg:postcode":"1210",
    "sg:province":"Bruxelles-Capitale",
    "wof:name":"C.b.e.m.",
    "wof:placetype":"venue"
},
  "geometry": {"coordinates":[4.3663702011,50.8540229797],"type":"Point"}
}