{
  "type": "Feature",
  "properties": {
    "iso:country":"BE",
    "sg:address":"Carnotstraat 36",
    "sg:city":"Antwerpen",
    "sg:orig_category":"Brood, gebak and snoepgoed",
    "sg:phone":"+32 3 227 30 63",
    "sg:postcode":"2060",
    "sg:province":"Antwerpen",
    "wof:name":"G.v.chocolate Consultancy",
    "wof:placetype":"venue"
},
  "geometry": {"coordinates":[4.4236731529,51.2185249329],"type":"Point"}
}