{
  "type": "Feature",
  "properties": {
    "iso:country":"BE",
    "sg:address":"Burn.-rte Anc. Fronti\u00c8re 32",
    "sg:city":"Malmedy/malmedy",
    "sg:orig_category":"Travaux de pl\u00e2trage",
    "sg:phone":"+32 80 33 79 56",
    "sg:postcode":"4960",
    "sg:province":"Li\u00e8ge",
    "wof:name":"Gilbert Demoulin",
    "wof:placetype":"venue"
},
  "geometry": {"coordinates":[6.0551772118,50.37657547],"type":"Point"}
}