{
  "type": "Feature",
  "properties": {
    "addr:full":"Rue Du Blanc Seau 315 Tourcoing 59200",
    "addr:housenumber":"315",
    "addr:postcode":"59200",
    "addr:street":"Rue Du Blanc Seau",
    "iso:country":"BE",
    "sg:address":"Rue Du Blanc Seau 315",
    "sg:city":"Tourcoing",
    "sg:classifiers":[
        {
            "category":"Personal",
            "subcategory":"Tattoo Parlor",
            "type":"Services"
        }
    ],
    "sg:phone":"+33 3 20 36 67 50",
    "sg:postcode":"59200",
    "sg:tags":[
        "tattooists"
    ],
    "wof:name":"Flotattoo",
    "wof:placetype":"venue"
},
  "geometry": {"coordinates":[3.1593749523,50.7223892212],"type":"Point"}
}