{
  "type": "Feature",
  "properties": {
    "addr:full":"Halmaalweg 107 Sint-truiden Limburg 3800",
    "addr:housenumber":"107",
    "addr:postcode":"3800",
    "addr:street":"Halmaalweg",
    "iso:country":"BE",
    "sg:address":"Halmaalweg 107",
    "sg:city":"Sint-truiden",
    "sg:classifiers":[
        {
            "category":"Personal",
            "subcategory":"Beauty Salon",
            "type":"Services"
        }
    ],
    "sg:phone":"+32 11 68 86 49",
    "sg:postcode":"3800",
    "sg:province":"Limburg",
    "sg:tags":[
        "lady",
        "-",
        "hairdressing"
    ],
    "wof:name":"Annie",
    "wof:placetype":"venue"
},
  "geometry": {"coordinates":[5.1682610512,50.8115081787],"type":"Point"}
}