{
  "type": "Feature",
  "properties": {
    "addr:full":"Rue Des Gen\u00cats 55 Bastogne Luxembourg 6600",
    "addr:housenumber":"55",
    "addr:postcode":"6600",
    "addr:street":"Rue Des Gene\u0302Ts",
    "iso:country":"BE",
    "sg:address":"Rue Des Gen\u00cats 55",
    "sg:city":"Bastogne",
    "sg:orig_category":"Instituts de beaut\u00e9. Traitements param\u00e9dicaux",
    "sg:phone":"+32 61 21 87 82",
    "sg:postcode":"6600",
    "sg:province":"Luxembourg",
    "wof:name":"Leyder",
    "wof:placetype":"venue"
},
  "geometry": {"coordinates":[5.6968002319,50.0008964539],"type":"Point"}
}