{
  "type": "Feature",
  "properties": {
    "addr:full":"Doorniksestraat 5 Box 62 Kortrijk West-Vlaanderen 8500",
    "addr:housenumber":"5 box 62",
    "addr:postcode":"8500",
    "addr:street":"Doorniksestraat",
    "iso:country":"BE",
    "sg:address":"Doorniksestraat 5 Box 62",
    "sg:city":"Kortrijk",
    "sg:classifiers":[
        {
            "category":"Health Services",
            "subcategory":"Doctor",
            "type":"Services"
        }
    ],
    "sg:phone":"+32 56 21 60 96",
    "sg:postcode":"8500",
    "sg:province":"West-Vlaanderen",
    "sg:tags":[
        "medicinephysicians",
        "surgeon"
    ],
    "wof:name":"Budiharto J",
    "wof:placetype":"venue"
},
  "geometry": {"coordinates":[3.2705149651,50.8167228699],"type":"Point"}
}