{
  "type": "Feature",
  "properties": {
    "addr:full":"Chemin De Chaumont 5 Malmedy/malmedy Li\u00e8ge 4960",
    "addr:housenumber":"5",
    "addr:postcode":"4960",
    "addr:street":"Chemin De Chaumont",
    "iso:country":"BE",
    "sg:address":"Chemin De Chaumont 5",
    "sg:city":"Malmedy/malmedy",
    "sg:orig_category":"Eleveurs de bovins",
    "sg:phone":"+32 80 33 02 51",
    "sg:postcode":"4960",
    "sg:province":"Li\u00e8ge",
    "wof:name":"Charles Albert",
    "wof:placetype":"venue"
},
  "geometry": {"coordinates":[6.0192089081,50.4419822693],"type":"Point"}
}