{
  "type": "Feature",
  "properties": {
    "iso:country":"BE",
    "sg:address":"Tempelare 12",
    "sg:city":"Lo-reninge",
    "sg:orig_category":"Quincailleries. Epiceries",
    "sg:phone":"+32 57 40 04 32",
    "sg:postcode":"8647",
    "sg:province":"West-Vlaanderen",
    "wof:name":"Bossaert",
    "wof:placetype":"venue"
},
  "geometry": {"coordinates":[2.7676479816,50.9136886597],"type":"Point"}
}