{
  "type": "Feature",
  "properties": {
    "iso:country":"BE",
    "sg:address":"Nieuwstraat 29",
    "sg:city":"Wevelgem",
    "sg:orig_category":"Voedingsspeciaalzaken",
    "sg:phone":"+32 56 41 97 73",
    "sg:postcode":"8560",
    "sg:province":"West-Vlaanderen",
    "wof:name":"Huis Den Engel",
    "wof:placetype":"venue"
},
  "geometry": {"coordinates":[3.1794669628,50.8108940125],"type":"Point"}
}