{
  "type": "Feature",
  "properties": {
    "iso:country":"BE",
    "sg:address":"Boudewijnlaan 34",
    "sg:city":"Heist-op-den-berg",
    "sg:orig_category":"Experts-comptables",
    "sg:phone":"+32 15 25 10 60",
    "sg:postcode":"2220",
    "sg:province":"Antwerpen",
    "wof:name":"M. Gorris",
    "wof:placetype":"venue"
},
  "geometry": {"coordinates":[4.7192320824,51.0733604431],"type":"Point"}
}