{
  "type": "Feature",
  "properties": {
    "addr:full":"Zuidervest 62 Peer Limburg 3990",
    "addr:housenumber":"62",
    "addr:postcode":"3990",
    "addr:street":"Zuidervest",
    "iso:country":"BE",
    "sg:address":"Zuidervest 62",
    "sg:city":"Peer",
    "sg:classifiers":[
        {
            "category":"Arena",
            "subcategory":"Sports Club",
            "type":"Entertainment"
        }
    ],
    "sg:phone":"+32 11 63 17 50",
    "sg:postcode":"3990",
    "sg:province":"Limburg",
    "sg:tags":[
        "de"
    ],
    "wof:name":"Sportiva Peer",
    "wof:placetype":"venue"
},
  "geometry": {"coordinates":[5.4503898621,51.1326560974],"type":"Point"}
}