{
  "type": "Feature",
  "properties": {
    "iso:country":"BE",
    "sg:address":"Rue Du Page 3",
    "sg:city":"Braine-le-comte",
    "sg:orig_category":"Artsen and specialisten",
    "sg:phone":"+32 67 64 71 51",
    "sg:postcode":"7090",
    "sg:province":"Hainaut",
    "wof:name":"Jo\u00cbl Baguet",
    "wof:placetype":"venue"
},
  "geometry": {"coordinates":[4.2194600105,50.6086540222],"type":"Point"}
}