{
  "type": "Feature",
  "properties": {
    "iso:country":"BE",
    "sg:address":"Vaartstraat 45",
    "sg:city":"Laarne",
    "sg:orig_category":"Banken and kredietinstellingen",
    "sg:phone":"+32 9 367 59 29",
    "sg:postcode":"9270",
    "sg:province":"Oost-Vlaanderen",
    "wof:name":"Kbc",
    "wof:placetype":"venue"
},
  "geometry": {"coordinates":[3.8489339352,51.0294075012],"type":"Point"}
}