{
  "type": "Feature",
  "properties": {
    "iso:country":"BE",
    "sg:address":"Adegem Dorp 15",
    "sg:city":"Maldegem (adegem)",
    "sg:classifiers":[
        {
            "category":"Bars & Pubs",
            "type":"Food & Drink"
        }
    ],
    "sg:phone":"+32 50 71 14 19",
    "sg:postcode":"9991",
    "sg:province":"Oost-Vlaanderen",
    "wof:name":"Damberd",
    "wof:placetype":"venue"
},
  "geometry": {"coordinates":[3.4865539074,51.2028541565],"type":"Point"}
}