{
  "type": "Feature",
  "properties": {
    "addr:full":"Rietlaan 11 Menen West-Vlaanderen 8930",
    "addr:housenumber":"11",
    "addr:postcode":"8930",
    "addr:street":"Rietlaan",
    "iso:country":"BE",
    "sg:address":"Rietlaan 11",
    "sg:city":"Menen",
    "sg:classifiers":[
        {
            "category":"Personal",
            "subcategory":"Beauty Salon",
            "type":"Services"
        }
    ],
    "sg:phone":"+32 56 42 24 04",
    "sg:postcode":"8930",
    "sg:province":"West-Vlaanderen",
    "sg:tags":[
        "de",
        "coiffure"
    ],
    "wof:name":"Coiffure Arne",
    "wof:placetype":"venue"
},
  "geometry": {"coordinates":[3.1209149361,50.7961845398],"type":"Point"}
}