{
  "type": "Feature",
  "properties": {
    "iso:country":"BE",
    "sg:address":"Kloosterstraat 1",
    "sg:city":"Kortrijk (marke)",
    "sg:classifiers":[
        {
            "category":"Health Services",
            "subcategory":"Doctor",
            "type":"Services"
        }
    ],
    "sg:phone":"+32 56 21 81 90",
    "sg:postcode":"8510",
    "sg:province":"West-Vlaanderen",
    "sg:tags":[
        "medicinephysicians",
        "surgeon"
    ],
    "wof:name":"Dewispelaere Lode",
    "wof:placetype":"venue"
},
  "geometry": {"coordinates":[3.2804789543,50.77551651],"type":"Point"}
}