{
  "type": "Feature",
  "properties": {
    "iso:country":"BE",
    "sg:address":"Chauss\u00c9e De Charleroi 657",
    "sg:city":"Fleurus",
    "sg:classifiers":[
        {
            "category":"Restaurant",
            "type":"Food & Drink"
        }
    ],
    "sg:phone":"+32 71 81 14 02",
    "sg:postcode":"6220",
    "sg:province":"Hainaut",
    "wof:name":"Restaurant Rialto",
    "wof:placetype":"venue"
},
  "geometry": {"coordinates":[4.5383300781,50.4679107666],"type":"Point"}
}