{
  "type": "Feature",
  "properties": {
    "addr:full":"Deerlijkseweg 164 Waregem West-Vlaanderen 8790",
    "addr:housenumber":"164",
    "addr:postcode":"8790",
    "iso:country":"BE",
    "sg:address":"Deerlijkseweg 164",
    "sg:city":"Waregem",
    "sg:orig_category":"Meubles D\u00e9taillants, Am\u00e9nagement de B\u00e2timents et de Cuisines",
    "sg:phone":"+32 56 60 24 45",
    "sg:postcode":"8790",
    "sg:province":"West-Vlaanderen",
    "wof:name":"Andemeubel",
    "wof:placetype":"venue"
},
  "geometry": {"coordinates":[3.4023430347,50.8688812256],"type":"Point"}
}