{
  "type": "Feature",
  "properties": {
    "addr:full":"Bergstraat 16 Heist-op-den-berg Antwerpen 2220",
    "addr:housenumber":"16",
    "addr:postcode":"2220",
    "addr:street":"Bergstraat",
    "iso:country":"BE",
    "sg:address":"Bergstraat 16",
    "sg:city":"Heist-op-den-berg",
    "sg:classifiers":[
        {
            "category":"Cafe",
            "type":"Food & Drink"
        }
    ],
    "sg:phone":"+32 15 24 10 31",
    "sg:postcode":"2220",
    "sg:province":"Antwerpen",
    "sg:tags":[
        "caf\u00e9s"
    ],
    "wof:name":"Caf\u00c9 Centrum",
    "wof:placetype":"venue"
},
  "geometry": {"coordinates":[4.72585392,51.0755805969],"type":"Point"}
}