{
  "type": "Feature",
  "properties": {
    "addr:full":"Zwevezelestraat 100 Lichtervelde West-Vlaanderen 8810",
    "addr:housenumber":"100",
    "addr:postcode":"8810",
    "addr:street":"Zwevezelestraat",
    "iso:country":"BE",
    "sg:address":"Zwevezelestraat 100",
    "sg:city":"Lichtervelde",
    "sg:classifiers":[
        {
            "category":"Building & Trades",
            "subcategory":"Landscaping Services",
            "type":"Services"
        }
    ],
    "sg:phone":"+32 51 72 37 83",
    "sg:postcode":"8810",
    "sg:province":"West-Vlaanderen",
    "sg:tags":[
        "gardening",
        "garden",
        "maintenance"
    ],
    "wof:name":"Van Moerkercke J",
    "wof:placetype":"venue"
},
  "geometry": {"coordinates":[3.154086113,51.0321388245],"type":"Point"}
}