{
  "type": "Feature",
  "properties": {
    "addr:full":"Nieuwstraat 17 Essen Antwerpen 2910",
    "addr:housenumber":"17",
    "addr:postcode":"2910",
    "addr:street":"Nieuwstraat",
    "iso:country":"BE",
    "sg:address":"Nieuwstraat 17",
    "sg:city":"Essen",
    "sg:classifiers":[
        {
            "category":"Shopping",
            "subcategory":"Clothing, Apparel, & Fashions",
            "type":"Retail Goods"
        }
    ],
    "sg:phone":"+32 3 677 31 17",
    "sg:postcode":"2910",
    "sg:province":"Antwerpen",
    "sg:tags":[
        "boutique"
    ],
    "wof:name":"Jeles",
    "wof:placetype":"venue"
},
  "geometry": {"coordinates":[4.4703259468,51.4660453796],"type":"Point"}
}