{
  "type": "Feature",
  "properties": {
    "addr:full":"Namoussart 10ba Neufchateau Luxembourg 6840",
    "addr:housenumber":"10ba",
    "addr:postcode":"6840",
    "addr:street":"Namoussart",
    "iso:country":"BE",
    "sg:address":"Namoussart 10ba",
    "sg:city":"Neufchateau",
    "sg:orig_category":"Rundveehouders",
    "sg:phone":"+32 61 27 88 55",
    "sg:postcode":"6840",
    "sg:province":"Luxembourg",
    "wof:name":"Francis Rigaux",
    "wof:placetype":"venue"
},
  "geometry": {"coordinates":[5.4993400574,49.835319519],"type":"Point"}
}