{
  "type": "Feature",
  "properties": {
    "addr:full":"Kloosterstraat 84 Antwerpen (hoboken) Antwerpen 2660",
    "addr:housenumber":"84",
    "addr:postcode":"2660",
    "addr:street":"Kloosterstraat",
    "iso:country":"BE",
    "sg:address":"Kloosterstraat 84",
    "sg:city":"Antwerpen (hoboken)",
    "sg:classifiers":[
        {
            "category":"Health Services",
            "subcategory":"Doctor",
            "type":"Services"
        }
    ],
    "sg:phone":"+32 3 825 49 38",
    "sg:postcode":"2660",
    "sg:province":"Antwerpen",
    "sg:tags":[
        "medicinephysicians",
        "surgeon"
    ],
    "wof:name":"Dossche A",
    "wof:placetype":"venue"
},
  "geometry": {"coordinates":[4.3940739632,51.2148399353],"type":"Point"}
}