{
  "type": "Feature",
  "properties": {
    "iso:country":"BE",
    "sg:address":"Moerstraat 32",
    "sg:city":"Zandhoven (pulderbos)",
    "sg:classifiers":[
        {
            "category":"Real Estate",
            "subcategory":"Architect",
            "type":"Services"
        }
    ],
    "sg:phone":"+32 3 464 09 98",
    "sg:postcode":"2242",
    "sg:province":"Antwerpen",
    "wof:name":"Verbraeken P",
    "wof:placetype":"venue"
},
  "geometry": {"coordinates":[4.7053518295,51.2189559937],"type":"Point"}
}