{
  "type": "Feature",
  "properties": {
    "addr:full":"Chemin Du Croquet 1 Bruxelles Bruxelles-Capitale 1000",
    "addr:housenumber":"1",
    "addr:postcode":"1000",
    "addr:street":"Chemin Du Croquet",
    "iso:country":"BE",
    "sg:address":"Chemin Du Croquet 1",
    "sg:city":"Bruxelles",
    "sg:classifiers":[
        {
            "category":"Recreation",
            "subcategory":"Dance Hall",
            "type":"Entertainment"
        }
    ],
    "sg:phone":"+32 2 649 08 64",
    "sg:postcode":"1000",
    "sg:province":"Bruxelles-Capitale",
    "sg:tags":[
        "discotheque"
    ],
    "wof:name":"Jeux D'hiver",
    "wof:placetype":"venue"
},
  "geometry": {"coordinates":[4.3496851921,50.8483848572],"type":"Point"}
}