{
  "type": "Feature",
  "properties": {
    "addr:full":"Kattenberg 27 Zottegem (erwetegem) Oost-Vlaanderen 9620",
    "addr:housenumber":"27",
    "addr:postcode":"9620",
    "addr:street":"Kattenberg",
    "iso:country":"BE",
    "sg:address":"Kattenberg 27",
    "sg:city":"Zottegem (erwetegem)",
    "sg:classifiers":[
        {
            "category":"Health Services",
            "subcategory":"Health Practitioner",
            "type":"Services"
        }
    ],
    "sg:phone":"+32 9 360 03 61",
    "sg:postcode":"9620",
    "sg:province":"Oost-Vlaanderen",
    "sg:tags":[
        "physiotherapist"
    ],
    "wof:name":"Ghysels Murielle",
    "wof:placetype":"venue"
},
  "geometry": {"coordinates":[3.8112111092,50.871181488],"type":"Point"}
}