{
  "type": "Feature",
  "properties": {
    "iso:country":"BE",
    "sg:address":"Schoolstraat 25",
    "sg:city":"Kapelle-op-den-bos",
    "sg:orig_category":"Sportclubs",
    "sg:phone":"+32 15 71 24 67",
    "sg:postcode":"1880",
    "sg:province":"Vlaams-Brabant",
    "wof:name":"Noord Brabant",
    "wof:placetype":"venue"
},
  "geometry": {"coordinates":[4.3589792252,51.0115776062],"type":"Point"}
}