{
  "type": "Feature",
  "properties": {
    "iso:country":"BE",
    "sg:address":"Weg Naar As 84b2",
    "sg:city":"Genk",
    "sg:orig_category":"V\u00eatements pour Hommes",
    "sg:phone":"+32 89 36 39 07",
    "sg:postcode":"3600",
    "sg:province":"Limburg",
    "wof:name":"I Dottori",
    "wof:placetype":"venue"
},
  "geometry": {"coordinates":[5.5111279488,50.9694900513],"type":"Point"}
}