{
  "type": "Feature",
  "properties": {
    "iso:country":"BE",
    "sg:address":"Jakob Van Arteveldestraat 11",
    "sg:city":"Wevelgem",
    "sg:classifiers":[
        {
            "category":"Professional",
            "subcategory":"Detective & Security Services",
            "type":"Services"
        }
    ],
    "sg:phone":"+32 56 41 74 86",
    "sg:postcode":"8560",
    "sg:province":"West-Vlaanderen",
    "sg:tags":[
        "installation",
        "alarm",
        "-",
        "system"
    ],
    "wof:name":"Alarm Service International",
    "wof:placetype":"venue"
},
  "geometry": {"coordinates":[3.1796379089,50.8184738159],"type":"Point"}
}