{
  "type": "Feature",
  "properties": {
    "addr:full":"Avenue Gen Aymes 52 Gembloux Namur 5030",
    "addr:housenumber":"52",
    "addr:postcode":"5030",
    "addr:street":"Avenue Gen Aymes;Namur",
    "iso:country":"BE",
    "sg:address":"Avenue Gen Aymes 52",
    "sg:city":"Gembloux",
    "sg:orig_category":"D\u00e9molition d\u00b4immeubles and terrassements",
    "sg:phone":"+32 81 61 19 85",
    "sg:postcode":"5030",
    "sg:province":"Namur",
    "wof:name":"Thonon R",
    "wof:placetype":"venue"
},
  "geometry": {"coordinates":[4.679019928,50.5643501282],"type":"Point"}
}