{
  "type": "Feature",
  "properties": {
    "addr:full":"Rue Auguste Masset 8 Saint-nicolas (montegn\u00e9e) Li\u00e8ge 4420",
    "addr:housenumber":"8",
    "addr:postcode":"4420",
    "addr:street":"Rue Auguste Masset;Montegne\u0301E",
    "iso:country":"BE",
    "sg:address":"Rue Auguste Masset 8",
    "sg:city":"Saint-nicolas (montegn\u00e9e)",
    "sg:classifiers":[
        {
            "category":"Health Services",
            "subcategory":"Doctor",
            "type":"Services"
        }
    ],
    "sg:phone":"+32 4 247 19 48",
    "sg:postcode":"4420",
    "sg:province":"Li\u00e8ge",
    "sg:tags":[
        "medicinephysicians",
        "surgeon"
    ],
    "wof:name":"Benmouna A",
    "wof:placetype":"venue"
},
  "geometry": {"coordinates":[5.5224561691,50.6375656128],"type":"Point"}
}