{
  "type": "Feature",
  "properties": {
    "iso:country":"BE",
    "sg:address":"Kerkeveldstraat 14",
    "sg:city":"Dilbeek",
    "sg:orig_category":"Boekhouders",
    "sg:phone":"+32 2 569 48 47",
    "sg:postcode":"1700",
    "sg:province":"Vlaams-Brabant",
    "wof:name":"Nicole De Somviele",
    "wof:placetype":"venue"
},
  "geometry": {"coordinates":[4.2491149902,50.8472518921],"type":"Point"}
}