{
  "type": "Feature",
  "properties": {
    "addr:full":"Samr\u00e9e 84 La Roche-en-ardenne (samr\u00e9e) Luxembourg 6982",
    "addr:housenumber":"84",
    "addr:postcode":"6982",
    "addr:street":"Samre\u0301E",
    "iso:country":"BE",
    "sg:address":"Samr\u00e9e 84",
    "sg:city":"La Roche-en-ardenne (samr\u00e9e)",
    "sg:classifiers":[
        {
            "category":"Travel",
            "subcategory":"Resort",
            "type":"Entertainment"
        }
    ],
    "sg:phone":"+32 84 44 46 00",
    "sg:postcode":"6982",
    "sg:province":"Luxembourg",
    "sg:tags":[
        "rental",
        "accomodation",
        "holiday",
        "-"
    ],
    "wof:name":"Domaine De L'alu",
    "wof:placetype":"venue"
},
  "geometry": {"coordinates":[5.638133049,50.2120666504],"type":"Point"}
}