{
  "type": "Feature",
  "properties": {
    "addr:full":"Dorpsstraat 21ba Sint-genesius-rode/rhode-saint-genese Vlaams-Brabant 1640",
    "addr:housenumber":"21ba",
    "addr:postcode":"1640",
    "addr:street":"Dorpsstraat",
    "iso:country":"BE",
    "sg:address":"Dorpsstraat 21ba",
    "sg:city":"Sint-genesius-rode/rhode-saint-genese",
    "sg:classifiers":[
        {
            "category":"Fast Food",
            "type":"Food & Drink"
        }
    ],
    "sg:phone":"+32 2 381 07 33",
    "sg:postcode":"1640",
    "sg:province":"Vlaams-Brabant",
    "sg:tags":[
        "huis",
        "aan",
        "levering",
        "meeneem",
        "restaurant"
    ],
    "wof:name":"La Fontaine D'or",
    "wof:placetype":"venue"
},
  "geometry": {"coordinates":[4.344233036,50.7448539734],"type":"Point"}
}