{
  "type": "Feature",
  "properties": {
    "iso:country":"BE",
    "sg:address":"Heizegemweg 2",
    "sg:city":"Antwerpen",
    "sg:orig_category":"Agences d'exp\u00e9dition",
    "sg:phone":"+32 3 544 90 90",
    "sg:postcode":"2030",
    "sg:province":"Antwerpen",
    "wof:name":"Kube En Kubenz Belgi\u00cb",
    "wof:placetype":"venue"
},
  "geometry": {"coordinates":[4.3756289482,51.2670593262],"type":"Point"}
}