{
  "type": "Feature",
  "properties": {
    "addr:full":"Rue Du Centre 18 Welkenraedt Li\u00e8ge 4840",
    "addr:housenumber":"18",
    "addr:postcode":"4840",
    "addr:street":"Rue Du Centre",
    "iso:country":"BE",
    "sg:address":"Rue Du Centre 18",
    "sg:city":"Welkenraedt",
    "sg:orig_category":"Woningbouw",
    "sg:phone":"+32 87 89 06 51",
    "sg:postcode":"4840",
    "sg:province":"Li\u00e8ge",
    "wof:name":"Denis Minder",
    "wof:placetype":"venue"
},
  "geometry": {"coordinates":[5.9719657898,50.6598854065],"type":"Point"}
}