{
  "type": "Feature",
  "properties": {
    "addr:full":"Grand Place 10a Rebecq (rebecq-rognon) Brabant Wallon 1430",
    "addr:housenumber":"10a",
    "addr:postcode":"1430",
    "addr:street":"Grand Place;Wallon",
    "iso:country":"BE",
    "sg:address":"Grand Place 10a",
    "sg:city":"Rebecq (rebecq-rognon)",
    "sg:classifiers":[
        {
            "category":"Food & Beverages",
            "subcategory":"Groceries & Convenience Stores",
            "type":"Retail Goods"
        }
    ],
    "sg:phone":"+32 67 63 76 47",
    "sg:postcode":"1430",
    "sg:province":"Brabant Wallon",
    "sg:tags":[
        "grocer"
    ],
    "wof:name":"Chaumi\u00e8re (la)",
    "wof:placetype":"venue"
},
  "geometry": {"coordinates":[4.131799221,50.6653022766],"type":"Point"}
}