{
  "type": "Feature",
  "properties": {
    "iso:country":"BE",
    "sg:address":"Korte Kwikaardweg 16",
    "sg:city":"Zoersel",
    "sg:classifiers":[
        {
            "category":"Banks & Credit Unions",
            "subcategory":"Investment Brokerage",
            "type":"Services"
        }
    ],
    "sg:phone":"+32 3 448 28 56",
    "sg:postcode":"2980",
    "sg:province":"Antwerpen",
    "sg:tags":[
        "auditor"
    ],
    "wof:name":"Van Impe P",
    "wof:placetype":"venue"
},
  "geometry": {"coordinates":[4.611700058,51.2597885132],"type":"Point"}
}