{
  "type": "Feature",
  "properties": {
    "addr:full":"Rue Du Ministre 5 Watermaal-bosvoorde/watermael-boitsfort Bruxelles-Capitale 1170",
    "addr:housenumber":"5",
    "addr:postcode":"1170",
    "addr:street":"Rue Du Ministre",
    "iso:country":"BE",
    "sg:address":"Rue Du Ministre 5",
    "sg:city":"Watermaal-bosvoorde/watermael-boitsfort",
    "sg:classifiers":[
        {
            "category":"Organizations",
            "subcategory":"Community Association",
            "type":"Services"
        }
    ],
    "sg:phone":"+32 2 673 53 80",
    "sg:postcode":"1170",
    "sg:province":"Bruxelles-Capitale",
    "sg:tags":[
        "organisation"
    ],
    "wof:name":"M.j. Le P'tit Monde",
    "wof:placetype":"venue"
},
  "geometry": {"coordinates":[4.4165401459,50.798614502],"type":"Point"}
}