{
  "type": "Feature",
  "properties": {
    "addr:full":"Sint-joriskaai 1 Gent Oost-Vlaanderen 9000",
    "addr:housenumber":"1",
    "addr:postcode":"9000",
    "addr:street":"Sint-Joriskaai;Oost-Vlaanderen",
    "iso:country":"BE",
    "sg:address":"Sint-joriskaai 1",
    "sg:city":"Gent",
    "sg:classifiers":[
        {
            "category":"Health Services",
            "subcategory":"Health Practitioner",
            "type":"Services"
        }
    ],
    "sg:phone":"+32 9 233 96 82",
    "sg:postcode":"9000",
    "sg:province":"Oost-Vlaanderen",
    "sg:tags":[
        "physiotherapist"
    ],
    "wof:name":"De Winter Liliane",
    "wof:placetype":"venue"
},
  "geometry": {"coordinates":[3.7329130173,51.0562133789],"type":"Point"}
}