{
  "type": "Feature",
  "properties": {
    "iso:country":"BE",
    "sg:address":"Sint-pieterszuidstraat 50",
    "sg:city":"Brugge",
    "sg:classifiers":[
        {
            "category":"Restaurant",
            "type":"Food & Drink"
        }
    ],
    "sg:phone":"+32 50 31 75 27",
    "sg:postcode":"8000",
    "sg:province":"West-Vlaanderen",
    "sg:tags":[
        "industrial",
        "kitchen",
        "catering"
    ],
    "wof:name":"Brugse Vleescentrale",
    "wof:placetype":"venue"
},
  "geometry": {"coordinates":[3.2357850075,51.2169532776],"type":"Point"}
}