{
  "type": "Feature",
  "properties": {
    "addr:full":"Antwerpsesteenweg 403 Gent (sint-amandsberg) Oost-Vlaanderen 9040",
    "addr:housenumber":"403",
    "addr:postcode":"9040",
    "addr:street":"Antwerpsesteenweg",
    "iso:country":"BE",
    "sg:address":"Antwerpsesteenweg 403",
    "sg:city":"Gent (sint-amandsberg)",
    "sg:classifiers":[
        {
            "category":"Real Estate",
            "subcategory":"Architect",
            "type":"Services"
        }
    ],
    "sg:phone":"+32 9 238 32 00",
    "sg:postcode":"9040",
    "sg:province":"Oost-Vlaanderen",
    "wof:name":"Coppens F",
    "wof:placetype":"venue"
},
  "geometry": {"coordinates":[3.7548298836,51.0661697388],"type":"Point"}
}