{
  "type": "Feature",
  "properties": {
    "addr:full":"Rollebaan 2 Rhode-saint-gen\u00e8se Vlaams-Brabant 1640",
    "addr:housenumber":"2",
    "addr:postcode":"1640",
    "addr:street":"Rollebaan",
    "iso:country":"BE",
    "sg:address":"Rollebaan 2",
    "sg:city":"Rhode-saint-gen\u00e8se",
    "sg:classifiers":[
        {
            "category":"Building & Trades",
            "subcategory":"Landscaping Services",
            "type":"Services"
        }
    ],
    "sg:phone":"+32 2 381 22 89",
    "sg:postcode":"1640",
    "sg:province":"Vlaams-Brabant",
    "sg:tags":[
        "architect",
        "landscape"
    ],
    "wof:name":"Voesterzoons W",
    "wof:placetype":"venue"
},
  "geometry": {"coordinates":[4.351099968,50.7449417114],"type":"Point"}
}