{
  "type": "Feature",
  "properties": {
    "addr:full":"Prinsenlaan 32 Oostende West-Vlaanderen 8400",
    "addr:housenumber":"32",
    "addr:postcode":"8400",
    "addr:street":"Prinsenlaan",
    "iso:country":"BE",
    "sg:address":"Prinsenlaan 32",
    "sg:city":"Oostende",
    "sg:classifiers":[
        {
            "category":"Health Services",
            "subcategory":"Doctor",
            "type":"Services"
        }
    ],
    "sg:phone":"+32 59 70 18 00",
    "sg:postcode":"8400",
    "sg:province":"West-Vlaanderen",
    "sg:tags":[
        "medicinephysicians",
        "surgeon"
    ],
    "wof:name":"Cornelli K",
    "wof:placetype":"venue"
},
  "geometry": {"coordinates":[2.9112520218,51.2209396362],"type":"Point"}
}