{
  "type": "Feature",
  "properties": {
    "iso:country":"BE",
    "sg:address":"Rue Royale 181",
    "sg:city":"Bruxelles (saint-josse-ten-noode)",
    "sg:classifiers":[
        {
            "category":"Social Services",
            "subcategory":"Job Training",
            "type":"Services"
        }
    ],
    "sg:phone":"+32 2 218 21 01",
    "sg:postcode":"1210",
    "sg:province":"Bruxelles-Capitale",
    "sg:tags":[
        "personnel",
        "-selection",
        "recruitment"
    ],
    "wof:name":"D.d.h. Consult",
    "wof:placetype":"venue"
},
  "geometry": {"coordinates":[4.3666749001,50.8547859192],"type":"Point"}
}