{
  "type": "Feature",
  "properties": {
    "iso:country":"BE",
    "sg:address":"Bruggestraat 141",
    "sg:city":"Menen",
    "sg:classifiers":[
        {
            "category":"Health Services",
            "subcategory":"Dentist",
            "type":"Services"
        }
    ],
    "sg:phone":"+32 56 51 31 88",
    "sg:postcode":"8930",
    "sg:province":"West-Vlaanderen",
    "wof:name":"Verbeke Ronald",
    "wof:placetype":"venue"
},
  "geometry": {"coordinates":[3.1238489151,50.8009109497],"type":"Point"}
}