{
  "type": "Feature",
  "properties": {
    "addr:full":"Rumbeeksesteenweg 329 Roeselare West-Vlaanderen 8800",
    "addr:housenumber":"329",
    "addr:postcode":"8800",
    "addr:street":"Rumbeeksesteenweg",
    "iso:country":"BE",
    "sg:address":"Rumbeeksesteenweg 329",
    "sg:city":"Roeselare",
    "sg:classifiers":[
        {
            "category":"Bars & Pubs",
            "type":"Food & Drink"
        }
    ],
    "sg:phone":"+32 51 22 06 61",
    "sg:postcode":"8800",
    "sg:province":"West-Vlaanderen",
    "wof:name":"Vierweg (de)",
    "wof:placetype":"venue"
},
  "geometry": {"coordinates":[3.1376209259,50.9380836487],"type":"Point"}
}