{
  "type": "Feature",
  "properties": {
    "addr:full":"Chauss\u00c9e De Li\u00c8ge 139 Namur Namur 5100",
    "addr:housenumber":"139",
    "addr:postcode":"5100",
    "addr:street":"Chausse\u0301E De Lie\u0300Ge",
    "iso:country":"BE",
    "sg:address":"Chauss\u00c9e De Li\u00c8ge 139",
    "sg:city":"Namur",
    "sg:orig_category":"Sportclubs",
    "sg:phone":"+32 81 30 88 65",
    "sg:postcode":"5100",
    "sg:province":"Namur",
    "wof:name":"R.h.c. Namurois",
    "wof:placetype":"venue"
},
  "geometry": {"coordinates":[4.8713750839,50.4566345215],"type":"Point"}
}