{
  "type": "Feature",
  "properties": {
    "iso:country":"BE",
    "sg:address":"Rijselstraat 41",
    "sg:city":"Menen",
    "sg:classifiers":[
        {
            "category":"Bars & Pubs",
            "type":"Food & Drink"
        }
    ],
    "sg:phone":"+32 496 77 15 59",
    "sg:postcode":"8930",
    "sg:province":"West-Vlaanderen",
    "wof:name":"Capitole",
    "wof:placetype":"venue"
},
  "geometry": {"coordinates":[3.1220319271,50.7944488525],"type":"Point"}
}