{
  "type": "Feature",
  "properties": {
    "iso:country":"BE",
    "sg:address":"Nazarethdreef 101",
    "sg:city":"Lier",
    "sg:classifiers":[
        {
            "category":"Sports & Exercise",
            "subcategory":"Sports Center",
            "type":"Entertainment"
        }
    ],
    "sg:phone":"+32 3 480 85 58",
    "sg:postcode":"2500",
    "sg:province":"Antwerpen",
    "sg:tags":[
        "game"
    ],
    "wof:name":"Lauwers Guy Arthur M.",
    "wof:placetype":"venue"
},
  "geometry": {"coordinates":[4.5707178116,51.1302833557],"type":"Point"}
}