{
  "type": "Feature",
  "properties": {
    "addr:full":"Chauss\u00c9e De Louvain 289 Waterloo Brabant Wallon 1410",
    "addr:housenumber":"289",
    "addr:postcode":"1410",
    "addr:street":"Chausse\u0301E De Louvain",
    "iso:country":"BE",
    "sg:address":"Chauss\u00c9e De Louvain 289",
    "sg:city":"Waterloo",
    "sg:orig_category":"Mat\u00e9riel \u00e9lectrique and \u00e9lectronique Gr",
    "sg:phone":"+32 2 357 09 40",
    "sg:postcode":"1410",
    "sg:province":"Brabant Wallon",
    "wof:name":"Nussbaumer & Co",
    "wof:placetype":"venue"
},
  "geometry": {"coordinates":[4.4281859398,50.7028579712],"type":"Point"}
}