{
  "type": "Feature",
  "properties": {
    "iso:country":"BE",
    "sg:address":"Stationsstraat 253",
    "sg:city":"Rotselaar",
    "sg:orig_category":"Boucheries",
    "sg:phone":"+32 16 44 74 67",
    "sg:postcode":"3110",
    "sg:province":"Vlaams-Brabant",
    "wof:name":"Roger Van Nuffelen",
    "wof:placetype":"venue"
},
  "geometry": {"coordinates":[4.7360501289,50.9398002625],"type":"Point"}
}