{
  "type": "Feature",
  "properties": {
    "iso:country":"BE",
    "sg:address":"Avenue Mascaux 172",
    "sg:city":"Marcinelle",
    "sg:classifiers":[
        {
            "category":"Shopping",
            "subcategory":"Stationery & Office Supplies",
            "type":"Retail Goods"
        }
    ],
    "sg:phone":"+32 71 43 29 56",
    "sg:postcode":"6001",
    "sg:province":"Hainaut",
    "sg:tags":[
        "furniture"
    ],
    "wof:name":"Buro Hall Sprl",
    "wof:placetype":"venue"
},
  "geometry": {"coordinates":[4.4422178268,50.3952713013],"type":"Point"}
}