{
  "type": "Feature",
  "properties": {
    "iso:country":"BE",
    "sg:address":"Avenue Des Croix De Feu 1b29",
    "sg:city":"La Louviere",
    "sg:orig_category":"Maatschappelijke dienstverlening",
    "sg:phone":"+32 64 22 41 41",
    "sg:postcode":"7100",
    "sg:province":"Hainaut",
    "wof:name":"Aide Et Pr\u00c9vention Enfants-parents",
    "wof:placetype":"venue"
},
  "geometry": {"coordinates":[4.2008948326,50.4794387817],"type":"Point"}
}