{
  "type": "Feature",
  "properties": {
    "addr:full":"Vlietestraat 145 Harelbeke West-Vlaanderen 8531",
    "addr:housenumber":"145",
    "addr:postcode":"8531",
    "addr:street":"Vlietestraat",
    "iso:country":"BE",
    "sg:address":"Vlietestraat 145",
    "sg:city":"Harelbeke",
    "sg:orig_category":"Banken and kredietinstellingen",
    "sg:phone":"+32 56 72 09 09",
    "sg:postcode":"8531",
    "sg:province":"West-Vlaanderen",
    "wof:name":"Groep Argenta",
    "wof:placetype":"venue"
},
  "geometry": {"coordinates":[3.298156023,50.8814811707],"type":"Point"}
}