{
  "type": "Feature",
  "properties": {
    "addr:full":"Chem.bois De Steenkerque 5 Soignies Hainaut 7060",
    "addr:housenumber":"5",
    "addr:postcode":"7060",
    "iso:country":"BE",
    "sg:address":"Chem.bois De Steenkerque 5",
    "sg:city":"Soignies",
    "sg:orig_category":"Rundveehouders",
    "sg:phone":"+32 67 45 85 02",
    "sg:postcode":"7060",
    "sg:province":"Hainaut",
    "wof:name":"Bernard Nactergal",
    "wof:placetype":"venue"
},
  "geometry": {"coordinates":[4.0739741325,50.5803413391],"type":"Point"}
}