{
  "type": "Feature",
  "properties": {
    "addr:full":"Mechelbaan 45d Heist-op-den-berg (groot) Antwerpen 2221",
    "addr:housenumber":"45d",
    "addr:postcode":"2221",
    "addr:street":"Mechelbaan;Groot Antwerpen",
    "iso:country":"BE",
    "sg:address":"Mechelbaan 45d",
    "sg:city":"Heist-op-den-berg (groot)",
    "sg:orig_category":"Auto-\u00e9coles",
    "sg:phone":"+32 15 24 15 97",
    "sg:postcode":"2221",
    "sg:province":"Antwerpen",
    "wof:name":"Jos De Reys En Zonen",
    "wof:placetype":"venue"
},
  "geometry": {"coordinates":[4.7739758492,51.0512428284],"type":"Point"}
}