{
  "type": "Feature",
  "properties": {
    "iso:country":"BE",
    "sg:address":"Hoge Steenweg 3",
    "sg:city":"Grimbergen",
    "sg:orig_category":"Fleurs and plantes",
    "sg:phone":"+32 2 270 97 50",
    "sg:postcode":"1850",
    "sg:province":"Vlaams-Brabant",
    "wof:name":"Quillaja Flowers",
    "wof:placetype":"venue"
},
  "geometry": {"coordinates":[4.3714132309,50.9332504272],"type":"Point"}
}