{
  "type": "Feature",
  "properties": {
    "addr:full":"Hoornzeelstraat 24 Tervuren Vlaams-Brabant 3080",
    "addr:housenumber":"24",
    "addr:postcode":"3080",
    "addr:street":"Hoornzeelstraat",
    "iso:country":"BE",
    "sg:address":"Hoornzeelstraat 24",
    "sg:city":"Tervuren",
    "sg:classifiers":[
        {
            "category":"Utilities",
            "subcategory":"Telephone",
            "type":"Services"
        }
    ],
    "sg:phone":"+32 2 766 11 80",
    "sg:postcode":"3080",
    "sg:province":"Vlaams-Brabant",
    "sg:tags":[
        "-",
        "internet"
    ],
    "wof:name":"Leapfrog Communications",
    "wof:placetype":"venue"
},
  "geometry": {"coordinates":[4.5134239197,50.8221092224],"type":"Point"}
}