{
  "type": "Feature",
  "properties": {
    "addr:full":"Rue Du Commerce 13 Chatelet Hainaut 6200",
    "addr:housenumber":"13",
    "addr:postcode":"6200",
    "addr:street":"Rue Du Commerce;Hainaut",
    "iso:country":"BE",
    "sg:address":"Rue Du Commerce 13",
    "sg:city":"Chatelet",
    "sg:orig_category":"Boucheries",
    "sg:phone":"+32 71 38 11 29",
    "sg:postcode":"6200",
    "sg:province":"Hainaut",
    "wof:name":"La Roti De La Lande",
    "wof:placetype":"venue"
},
  "geometry": {"coordinates":[4.5216479301,50.4049720764],"type":"Point"}
}