{
  "type": "Feature",
  "properties": {
    "addr:full":"Seestrasse 24 B\u00fctgenbach Li\u00e8ge 4750",
    "addr:housenumber":"24",
    "addr:postcode":"4750",
    "addr:street":"Seestrasse",
    "iso:country":"BE",
    "sg:address":"Seestrasse 24",
    "sg:city":"B\u00fctgenbach",
    "sg:classifiers":[
        {
            "category":"Bars & Pubs",
            "type":"Food & Drink"
        }
    ],
    "sg:phone":"+32 80 44 77 99",
    "sg:postcode":"4750",
    "sg:province":"Li\u00e8ge",
    "wof:name":"Pub (the) Cafe",
    "wof:placetype":"venue"
},
  "geometry": {"coordinates":[6.2078390121,50.4261131287],"type":"Point"}
}