{
  "type": "Feature",
  "properties": {
    "addr:full":"Hondstraat 33 Izegem West-Vlaanderen 8870",
    "addr:housenumber":"33",
    "addr:postcode":"8870",
    "addr:street":"Hondstraat",
    "iso:country":"BE",
    "sg:address":"Hondstraat 33",
    "sg:city":"Izegem",
    "sg:classifiers":[
        {
            "category":"Shopping",
            "subcategory":"Optician",
            "type":"Retail Goods"
        }
    ],
    "sg:phone":"+32 51 31 34 41",
    "sg:postcode":"8870",
    "sg:province":"West-Vlaanderen",
    "sg:tags":[
        "-"
    ],
    "wof:name":"Declercq Optiek",
    "wof:placetype":"venue"
},
  "geometry": {"coordinates":[3.2113249302,50.9202842712],"type":"Point"}
}