{
  "type": "Feature",
  "properties": {
    "addr:full":"Avenue Z\u00e9nobe Gramme 20 Tubize (saintes) Brabant Wallon 1480",
    "addr:housenumber":"20",
    "addr:postcode":"1480",
    "addr:street":"Avenue Ze\u0301Nobe Gramme",
    "iso:country":"BE",
    "sg:address":"Avenue Z\u00e9nobe Gramme 20",
    "sg:city":"Tubize (saintes)",
    "sg:orig_category":"Non-Classified Establishments",
    "sg:phone":"+32 2 411 69 33",
    "sg:postcode":"1480",
    "sg:province":"Brabant Wallon",
    "wof:name":"Servais",
    "wof:placetype":"venue"
},
  "geometry": {"coordinates":[4.1775999069,50.7075462341],"type":"Point"}
}