{
  "type": "Feature",
  "properties": {
    "iso:country":"BE",
    "sg:address":"Kempenarestraat 60",
    "sg:city":"Sint-katelijne-waver",
    "sg:classifiers":[
        {
            "category":"Autos & Motor Vehicles",
            "subcategory":"Auto Supplies",
            "type":"Retail Goods"
        }
    ],
    "sg:phone":"+32 15 55 26 62",
    "sg:postcode":"2860",
    "sg:province":"Antwerpen",
    "sg:tags":[
        "semi-trailers",
        "industrial",
        "-",
        "trailer"
    ],
    "wof:name":"Interim Cargo",
    "wof:placetype":"venue"
},
  "geometry": {"coordinates":[4.5237851143,51.0598907471],"type":"Point"}
}