{
  "type": "Feature",
  "properties": {
    "iso:country":"BE",
    "sg:address":"Fransehoeveweg 6",
    "sg:city":"Ranst",
    "sg:orig_category":"Fruitteelt Pluimveekwekers Rundveehouders",
    "sg:phone":"+32 3 480 82 17",
    "sg:postcode":"2520",
    "sg:province":"Antwerpen",
    "wof:name":"Hugo Verhaegen",
    "wof:placetype":"venue"
},
  "geometry": {"coordinates":[4.5956659317,51.1668930054],"type":"Point"}
}