{
  "type": "Feature",
  "properties": {
    "addr:full":"Greenhillstraat 31 Brugge West-Vlaanderen 8310",
    "addr:housenumber":"31",
    "addr:postcode":"8310",
    "addr:street":"Greenhillstraat",
    "iso:country":"BE",
    "sg:address":"Greenhillstraat 31",
    "sg:city":"Brugge",
    "sg:orig_category":"Fleurs and plantes",
    "sg:phone":"+32 50 36 24 77",
    "sg:postcode":"8310",
    "sg:province":"West-Vlaanderen",
    "wof:name":"Huis Glamis",
    "wof:placetype":"venue"
},
  "geometry": {"coordinates":[3.235724926,51.191696167],"type":"Point"}
}