{
  "type": "Feature",
  "properties": {
    "addr:full":"Albert I Laan 215 Nieuwpoort West-Vlaanderen 8620",
    "addr:housenumber":"215",
    "addr:postcode":"8620",
    "addr:street":"Albert I Laan",
    "iso:country":"BE",
    "sg:address":"Albert I Laan 215",
    "sg:city":"Nieuwpoort",
    "sg:classifiers":[
        {
            "category":"Recreation",
            "subcategory":"Arcade",
            "type":"Entertainment"
        }
    ],
    "sg:phone":"+32 58 23 04 30",
    "sg:postcode":"8620",
    "sg:province":"West-Vlaanderen",
    "sg:tags":[
        "machine",
        "amusement"
    ],
    "wof:name":"Peter Pan(lunapark)",
    "wof:placetype":"venue"
},
  "geometry": {"coordinates":[2.7158970833,51.1482162476],"type":"Point"}
}