{
  "type": "Feature",
  "properties": {
    "iso:country":"BE",
    "sg:address":"Filip Vander Elststraat 26",
    "sg:city":"Brussel/bruxelles",
    "sg:orig_category":"Zalen voor culturele evenementen",
    "sg:phone":"+32 2 262 07 08",
    "sg:postcode":"1120",
    "sg:province":"Bruxelles-Capitale",
    "wof:name":"G-loft Art Promotion",
    "wof:placetype":"venue"
},
  "geometry": {"coordinates":[4.3842511177,50.8941764832],"type":"Point"}
}