{
  "type": "Feature",
  "properties": {
    "addr:full":"Chauss\u00c9e Des Grenadiers 20 Bassenge Li\u00e8ge 4690",
    "addr:housenumber":"20",
    "addr:postcode":"4690",
    "addr:street":"Chausse\u0301E Des Grenadiers",
    "iso:country":"BE",
    "sg:address":"Chauss\u00c9e Des Grenadiers 20",
    "sg:city":"Bassenge",
    "sg:orig_category":"Cr\u00e9meries",
    "sg:phone":"+32 4 286 43 83",
    "sg:postcode":"4690",
    "sg:province":"Li\u00e8ge",
    "wof:name":"Jean-marie Slangen",
    "wof:placetype":"venue"
},
  "geometry": {"coordinates":[5.6722140312,50.8009376526],"type":"Point"}
}