{
  "type": "Feature",
  "properties": {
    "addr:full":"Avenue D' Esneux 69 Esneux Li\u00e8ge 4130",
    "addr:housenumber":"69",
    "addr:postcode":"4130",
    "addr:street":"Avenue D ' Esneux",
    "iso:country":"BE",
    "sg:address":"Avenue D' Esneux 69",
    "sg:city":"Esneux",
    "sg:orig_category":"Articles de camping and de sport. Animaux domestiques and accessoires",
    "sg:phone":"+32 4 388 22 06",
    "sg:postcode":"4130",
    "sg:province":"Li\u00e8ge",
    "wof:name":"Maison L'epuisette",
    "wof:placetype":"venue"
},
  "geometry": {"coordinates":[5.5908060074,50.5476646423],"type":"Point"}
}