{
  "type": "Feature",
  "properties": {
    "iso:country":"BE",
    "sg:address":"Nieuwedijk 2",
    "sg:city":"Arendonk",
    "sg:orig_category":"Producteurs de fruits",
    "sg:phone":"+32 14 67 81 45",
    "sg:postcode":"2370",
    "sg:province":"Antwerpen",
    "wof:name":"August Segers",
    "wof:placetype":"venue"
},
  "geometry": {"coordinates":[5.0914487839,51.2978172302],"type":"Point"}
}