{
  "type": "Feature",
  "properties": {
    "iso:country":"BE",
    "sg:address":"Rue De La Baronne Lemonnier 122",
    "sg:city":"Rochefort (lavaux-sainte-anne)",
    "sg:classifiers":[
        {
            "category":"Manufacturing",
            "subcategory":"Tobacco Products",
            "type":"Manufacturing & Wholesale Goods"
        }
    ],
    "sg:phone":"+32 84 38 83 09",
    "sg:postcode":"5580",
    "sg:province":"Namur",
    "sg:tags":[
        "soil",
        "peat"
    ],
    "wof:name":"Monseu Sa",
    "wof:placetype":"venue"
},
  "geometry": {"coordinates":[5.0925340652,50.1140365601],"type":"Point"}
}