{
  "type": "Feature",
  "properties": {
    "addr:full":"Broekkanstraat 60 Opglabbeek Limburg 3660",
    "addr:housenumber":"60",
    "addr:postcode":"3660",
    "addr:street":"Broekkanstraat",
    "iso:country":"BE",
    "sg:address":"Broekkanstraat 60",
    "sg:city":"Opglabbeek",
    "sg:orig_category":"Rev\u00eatements de sols and murs",
    "sg:phone":"+32 89 85 87 56",
    "sg:postcode":"3660",
    "sg:province":"Limburg",
    "wof:name":"Ronny Gielen",
    "wof:placetype":"venue"
},
  "geometry": {"coordinates":[5.5902972221,51.0373497009],"type":"Point"}
}