{
  "type": "Feature",
  "properties": {
    "iso:country":"BE",
    "sg:address":"Stationsstraat 42",
    "sg:city":"Balen",
    "sg:orig_category":"Medische apparatuur, orthopedische artikelen and prothesen Fab",
    "sg:phone":"+32 14 81 43 09",
    "sg:postcode":"2490",
    "sg:province":"Antwerpen",
    "wof:name":"Dent-service",
    "wof:placetype":"venue"
},
  "geometry": {"coordinates":[5.1651740074,51.1688804626],"type":"Point"}
}