{
  "type": "Feature",
  "properties": {
    "addr:full":"Sint-amandinastraat 35 Leopoldsburg Limburg 3970",
    "addr:housenumber":"35",
    "addr:postcode":"3970",
    "addr:street":"Sint-Amandinastraat",
    "iso:country":"BE",
    "sg:address":"Sint-amandinastraat 35",
    "sg:city":"Leopoldsburg",
    "sg:orig_category":"Diverse bouwafwerking and reiniging Plaatsen van vloer- and muurbekleding Schilders",
    "sg:phone":"+32 11 34 76 16",
    "sg:postcode":"3970",
    "sg:province":"Limburg",
    "wof:name":"Van Gompel",
    "wof:placetype":"venue"
},
  "geometry": {"coordinates":[5.2571468353,51.1377601624],"type":"Point"}
}