{
  "type": "Feature",
  "properties": {
    "addr:full":"Roskamstraat 22 Merelbeke Oost-Vlaanderen 9820",
    "addr:housenumber":"22",
    "addr:postcode":"9820",
    "addr:street":"Roskamstraat",
    "iso:country":"BE",
    "sg:address":"Roskamstraat 22",
    "sg:city":"Merelbeke",
    "sg:classifiers":[
        {
            "category":"Shopping",
            "subcategory":"Pets & Pet Supplies",
            "type":"Retail Goods"
        }
    ],
    "sg:phone":"+32 9 230 85 94",
    "sg:postcode":"9820",
    "sg:province":"Oost-Vlaanderen",
    "sg:tags":[
        "shop",
        "-"
    ],
    "wof:name":"Petshop De Roskam",
    "wof:placetype":"venue"
},
  "geometry": {"coordinates":[3.7573881149,50.9967384338],"type":"Point"}
}