{
  "type": "Feature",
  "properties": {
    "iso:country":"BE",
    "sg:address":"Rue De La Limite 36",
    "sg:city":"Wavre",
    "sg:orig_category":"D\u00e9taillants en pi\u00e8ces and accessoires de voitures",
    "sg:phone":"+32 10 24 87 58",
    "sg:postcode":"1300",
    "sg:province":"Brabant Wallon",
    "wof:name":"Jeanquart",
    "wof:placetype":"venue"
},
  "geometry": {"coordinates":[4.6071147919,50.7170066833],"type":"Point"}
}