{
  "type": "Feature",
  "properties": {
    "addr:full":"Rue Andr\u00e9 Hennebicq 24 Tournai Hainaut 7500",
    "addr:housenumber":"24",
    "addr:postcode":"7500",
    "addr:street":"Rue Andre\u0301 Hennebicq",
    "iso:country":"BE",
    "sg:address":"Rue Andr\u00e9 Hennebicq 24",
    "sg:city":"Tournai",
    "sg:classifiers":[
        {
            "category":"Personal",
            "subcategory":"Psychics & Astrologers",
            "type":"Services"
        }
    ],
    "sg:phone":"+32 69 21 48 68",
    "sg:postcode":"7500",
    "sg:province":"Hainaut",
    "sg:tags":[
        "astrology"
    ],
    "wof:name":"Karina",
    "wof:placetype":"venue"
},
  "geometry": {"coordinates":[3.3840200901,50.6009788513],"type":"Point"}
}