{
  "type": "Feature",
  "properties": {
    "iso:country":"BE",
    "sg:address":"Oostnieuwkerksesteenweg 59",
    "sg:city":"Roeselare",
    "sg:orig_category":"Fruitteelt Groenten and fruit Gh",
    "sg:phone":"+32 51 22 08 44",
    "sg:postcode":"8800",
    "sg:province":"West-Vlaanderen",
    "wof:name":"Maes Gebroeders",
    "wof:placetype":"venue"
},
  "geometry": {"coordinates":[3.1043291092,50.9472808838],"type":"Point"}
}