{
  "type": "Feature",
  "properties": {
    "addr:full":"Bredabaan 334 Brasschaat Antwerpen 2930",
    "addr:housenumber":"334",
    "addr:postcode":"2930",
    "addr:street":"Bredabaan",
    "iso:country":"BE",
    "sg:address":"Bredabaan 334",
    "sg:city":"Brasschaat",
    "sg:classifiers":[
        {
            "category":"Cafe",
            "type":"Food & Drink"
        }
    ],
    "sg:phone":"+32 3 652 16 97",
    "sg:postcode":"2930",
    "sg:province":"Antwerpen",
    "sg:tags":[
        "snack-bars"
    ],
    "wof:name":"Finesse",
    "wof:placetype":"venue"
},
  "geometry": {"coordinates":[4.4937448502,51.2920341492],"type":"Point"}
}