{
  "type": "Feature",
  "properties": {
    "addr:full":"Molemstraat 118 Lummen Limburg 3560",
    "addr:housenumber":"118",
    "addr:postcode":"3560",
    "addr:street":"Molemstraat",
    "iso:country":"BE",
    "sg:address":"Molemstraat 118",
    "sg:city":"Lummen",
    "sg:orig_category":"Equipement divers pour commerces Installation de menuiserie en bois and plastique. Meubles D\u00e9taillan",
    "sg:phone":"+32 13 53 95 95",
    "sg:postcode":"3560",
    "sg:province":"Limburg",
    "wof:name":"Gebroeders Luyten",
    "wof:placetype":"venue"
},
  "geometry": {"coordinates":[5.2156729698,51.0004501343],"type":"Point"}
}