{
  "type": "Feature",
  "properties": {
    "iso:country":"BE",
    "sg:address":"Amsterdamstraat 60",
    "sg:city":"Oostende",
    "sg:orig_category":"Diverse juridische dienstverlening",
    "sg:phone":"+32 59 80 38 29",
    "sg:postcode":"8400",
    "sg:province":"West-Vlaanderen",
    "wof:name":"Verkoopzaal Oud En Nieuw",
    "wof:placetype":"venue"
},
  "geometry": {"coordinates":[2.9144349098,51.2248077393],"type":"Point"}
}