{
  "type": "Feature",
  "properties": {
    "addr:full":"'s Graventafelstraat 41 Zonnebeke (passendale) West-Vlaanderen 8980",
    "addr:housenumber":"41",
    "addr:postcode":"8980",
    "addr:street":"' S Graventafelstraat",
    "iso:country":"BE",
    "sg:address":"'s Graventafelstraat 41",
    "sg:city":"Zonnebeke (passendale)",
    "sg:classifiers":[
        {
            "category":"Structure",
            "subcategory":"Office Building",
            "type":"Public Place"
        }
    ],
    "sg:phone":"+32 51 77 73 36",
    "sg:postcode":"8980",
    "sg:province":"West-Vlaanderen",
    "sg:tags":[
        "-",
        "type",
        "door",
        "sliding",
        "overhead"
    ],
    "wof:name":"Beheyt A Krial",
    "wof:placetype":"venue"
},
  "geometry": {"coordinates":[2.9976239204,50.8993415833],"type":"Point"}
}