{
  "type": "Feature",
  "properties": {
    "addr:full":"Avenue Henri Conscience 256 Bruxelles (evere) Bruxelles-Capitale 1140",
    "addr:housenumber":"256",
    "addr:postcode":"1140",
    "addr:street":"Avenue Henri Conscience",
    "iso:country":"BE",
    "sg:address":"Avenue Henri Conscience 256",
    "sg:city":"Bruxelles (evere)",
    "sg:classifiers":[
        {
            "category":"Retail",
            "subcategory":"Auto Repair",
            "type":"Services"
        }
    ],
    "sg:phone":"+32 2 215 21 40",
    "sg:postcode":"1140",
    "sg:province":"Bruxelles-Capitale",
    "sg:tags":[
        "garage"
    ],
    "wof:name":"Brussel's Car Sprl (carrosserie)",
    "wof:placetype":"venue"
},
  "geometry": {"coordinates":[4.4026842117,50.8737792969],"type":"Point"}
}