{
  "type": "Feature",
  "properties": {
    "addr:full":"Place Du M\u00d4le 5 Braine-l\u00b4alleud Brabant Wallon 1420",
    "addr:housenumber":"5",
    "addr:postcode":"1420",
    "addr:street":"Place Du Mo\u0302Le;Brabant Wallon",
    "iso:country":"BE",
    "sg:address":"Place Du M\u00d4le 5",
    "sg:city":"Braine-l\u00b4alleud",
    "sg:orig_category":"Action sociale avec h\u00e9bergement",
    "sg:phone":"+32 2 389 08 96",
    "sg:postcode":"1420",
    "sg:province":"Brabant Wallon",
    "wof:name":"C.i.a.s.",
    "wof:placetype":"venue"
},
  "geometry": {"coordinates":[4.3705148697,50.6835632324],"type":"Point"}
}