{
  "type": "Feature",
  "properties": {
    "iso:country":"BE",
    "sg:address":"Ringlaan 25",
    "sg:city":"Ichtegem",
    "sg:orig_category":"Installatie van houten of kunststof schrijnwerk",
    "sg:phone":"+32 51 58 88 05",
    "sg:postcode":"8480",
    "sg:province":"West-Vlaanderen",
    "wof:name":"Roland Vandenberghe",
    "wof:placetype":"venue"
},
  "geometry": {"coordinates":[3.0262310505,51.1022148132],"type":"Point"}
}