{
  "type": "Feature",
  "properties": {
    "iso:country":"BE",
    "sg:address":"Braambos 12",
    "sg:city":"Lennik",
    "sg:orig_category":"Installatie van houten of kunststof schrijnwerk",
    "sg:phone":"+32 54 32 35 11",
    "sg:postcode":"1750",
    "sg:province":"Vlaams-Brabant",
    "wof:name":"Willems Frans",
    "wof:placetype":"venue"
},
  "geometry": {"coordinates":[4.129532814,50.8366355896],"type":"Point"}
}