{
  "type": "Feature",
  "properties": {
    "addr:full":"Kanaalstraat 22 Neerpelt (sint-huibrechts-lille) Limburg 3910",
    "addr:housenumber":"22",
    "addr:postcode":"3910",
    "addr:street":"Kanaalstraat",
    "iso:country":"BE",
    "sg:address":"Kanaalstraat 22",
    "sg:city":"Neerpelt (sint-huibrechts-lille)",
    "sg:classifiers":[
        {
            "category":"Real Estate",
            "subcategory":"Architect",
            "type":"Services"
        }
    ],
    "sg:phone":"+32 11 64 88 82",
    "sg:postcode":"3910",
    "sg:province":"Limburg",
    "wof:name":"Kampers F",
    "wof:placetype":"venue"
},
  "geometry": {"coordinates":[5.4850969315,51.2279586792],"type":"Point"}
}