{
  "type": "Feature",
  "properties": {
    "iso:country":"BE",
    "sg:address":"Markt 26",
    "sg:city":"Laakdal (forest)",
    "sg:classifiers":[
        {
            "category":"Health Services",
            "subcategory":"Health Practitioner",
            "type":"Services"
        }
    ],
    "sg:phone":"+32 13 67 67 02",
    "sg:postcode":"2430",
    "sg:province":"Antwerpen",
    "sg:tags":[
        "physiotherapist"
    ],
    "wof:name":"Cenens Jessy",
    "wof:placetype":"venue"
},
  "geometry": {"coordinates":[5.0213799477,51.0807304382],"type":"Point"}
}