{
  "type": "Feature",
  "properties": {
    "iso:country":"BE",
    "sg:address":"Prins Boudewijnlaan 405",
    "sg:city":"Edegem",
    "sg:classifiers":[
        {
            "category":"Home & Garden",
            "subcategory":"Home Furnishings",
            "type":"Retail Goods"
        }
    ],
    "sg:phone":"+32 3 825 17 16",
    "sg:postcode":"2650",
    "sg:province":"Antwerpen",
    "sg:tags":[
        "interior",
        "decoration"
    ],
    "wof:name":"Keymeulen Eric Bvba",
    "wof:placetype":"venue"
},
  "geometry": {"coordinates":[4.4263648987,51.1683425903],"type":"Point"}
}