{
  "type": "Feature",
  "properties": {
    "iso:country":"BE",
    "sg:address":"Av G\u00e9n Baron Empain 31",
    "sg:city":"Bruxelles",
    "sg:classifiers":[
        {
            "category":"Professional",
            "subcategory":"Advertising",
            "type":"Services"
        }
    ],
    "sg:phone":"+32 2 771 05 35",
    "sg:postcode":"1150",
    "sg:province":"Bruxelles-Capitale",
    "sg:tags":[
        "marketing",
        "medium",
        "communication"
    ],
    "wof:name":"Belgium Contact Communication",
    "wof:placetype":"venue"
},
  "geometry": {"coordinates":[4.440018177,50.8247413635],"type":"Point"}
}