{
  "type": "Feature",
  "properties": {
    "iso:country":"BE",
    "sg:address":"Ninoofse Steenweg 237",
    "sg:city":"Gooik",
    "sg:orig_category":"G\u00e9om\u00e8tres",
    "sg:phone":"+32 2 532 52 24",
    "sg:postcode":"1755",
    "sg:province":"Vlaams-Brabant",
    "wof:name":"Guido Decoster",
    "wof:placetype":"venue"
},
  "geometry": {"coordinates":[4.0883002281,50.7812805176],"type":"Point"}
}