{
  "type": "Feature",
  "properties": {
    "addr:full":"Rue Des Bouveleurs 42 Charleroi (marcinelle) Hainaut 6001",
    "addr:housenumber":"42",
    "addr:postcode":"6001",
    "addr:street":"Rue Des Bouveleurs",
    "iso:country":"BE",
    "sg:address":"Rue Des Bouveleurs 42",
    "sg:city":"Charleroi (marcinelle)",
    "sg:classifiers":[
        {
            "category":"Building & Trades",
            "subcategory":"Pest Control",
            "type":"Services"
        }
    ],
    "sg:phone":"+32 71 47 08 84",
    "sg:postcode":"6001",
    "sg:province":"Hainaut",
    "sg:tags":[
        "painting",
        "contractor"
    ],
    "wof:name":"Latistyl",
    "wof:placetype":"venue"
},
  "geometry": {"coordinates":[4.4446339607,50.3944206238],"type":"Point"}
}