{
  "type": "Feature",
  "properties": {
    "addr:full":"Augustijnenlaan 62 Herentals Antwerpen 2200",
    "addr:housenumber":"62",
    "addr:postcode":"2200",
    "addr:street":"Augustijnenlaan",
    "iso:country":"BE",
    "sg:address":"Augustijnenlaan 62",
    "sg:city":"Herentals",
    "sg:classifiers":[
        {
            "category":"Personal",
            "subcategory":"Beauty Salon",
            "type":"Services"
        }
    ],
    "sg:phone":"+32 14 21 88 41",
    "sg:postcode":"2200",
    "sg:province":"Antwerpen",
    "sg:tags":[
        "de",
        "coiffure"
    ],
    "wof:name":"Coiffure Anne Mie",
    "wof:placetype":"venue"
},
  "geometry": {"coordinates":[4.8461260796,51.1762123108],"type":"Point"}
}