{
  "type": "Feature",
  "properties": {
    "addr:full":"Bld Guillaume Van Haelen 180b7 Vorst/forest Bruxelles-Capitale 1190",
    "addr:housenumber":"180b7",
    "addr:postcode":"1190",
    "addr:street":"Bld Guillaume Van Haelen;/ Forest",
    "iso:country":"BE",
    "sg:address":"Bld Guillaume Van Haelen 180b7",
    "sg:city":"Vorst/forest",
    "sg:orig_category":"Avocats and conseillers juridiques",
    "sg:phone":"+32 2 344 91 65",
    "sg:postcode":"1190",
    "sg:province":"Bruxelles-Capitale",
    "wof:name":"A. De Winter",
    "wof:placetype":"venue"
},
  "geometry": {"coordinates":[4.3334541321,50.8236198425],"type":"Point"}
}