{
  "type": "Feature",
  "properties": {
    "iso:country":"BE",
    "sg:address":"Rue Praile 34",
    "sg:city":"Ham-sur-heure-nalinnes (nalinnes)",
    "sg:classifiers":[
        {
            "category":"Health Services",
            "subcategory":"Doctor",
            "type":"Services"
        }
    ],
    "sg:phone":"+32 71 21 46 51",
    "sg:postcode":"6120",
    "sg:province":"Hainaut",
    "sg:tags":[
        "medicinephysicians",
        "surgeon"
    ],
    "wof:name":"Barthelemy Marc",
    "wof:placetype":"venue"
},
  "geometry": {"coordinates":[4.4509420395,50.3231201172],"type":"Point"}
}