{
  "type": "Feature",
  "properties": {
    "addr:full":"Rue Emile Delva 66 Brussel/bruxelles Bruxelles-Capitale 1020",
    "addr:housenumber":"66",
    "addr:postcode":"1020",
    "addr:street":"Rue Emile Delva;/",
    "iso:country":"BE",
    "sg:address":"Rue Emile Delva 66",
    "sg:city":"Brussel/bruxelles",
    "sg:classifiers":[
        {
            "category":"Arena",
            "subcategory":"Sports Club",
            "type":"Entertainment"
        }
    ],
    "sg:phone":"+32 2 425 41 99",
    "sg:postcode":"1020",
    "sg:province":"Bruxelles-Capitale",
    "sg:tags":[
        "terrain",
        "hors",
        "de",
        "installation",
        "sportifs"
    ],
    "wof:name":"Racing Forest Ovetense",
    "wof:placetype":"venue"
},
  "geometry": {"coordinates":[4.3423647881,50.8785629272],"type":"Point"}
}