{
  "type": "Feature",
  "properties": {
    "addr:full":"2 Avenue Nouvelle Vieux-genappe Brabant Wallon 1472",
    "addr:housenumber":"2",
    "addr:postcode":"1472",
    "addr:street":"Avenue Nouvelle Vieux-Genappe Brabant Wallon",
    "iso:country":"BE",
    "sg:address":"2 Avenue Nouvelle",
    "sg:city":"Vieux-genappe",
    "sg:classifiers":[
        {
            "category":"Building & Trades",
            "subcategory":"Construction",
            "type":"Services"
        }
    ],
    "sg:phone":"+32 67 87 77 20",
    "sg:postcode":"1472",
    "sg:province":"Brabant Wallon",
    "sg:tags":[
        "work",
        "public"
    ],
    "wof:name":"Les Entreprises Generales Louis Christophe Sprl",
    "wof:placetype":"venue"
},
  "geometry": {"coordinates":[4.4454898834,50.6119804382],"type":"Point"}
}