{
  "type": "Feature",
  "properties": {
    "addr:full":"Burgemeester J. Van Aperenstraat 20 Hoogstraten Antwerpen 2320",
    "addr:housenumber":"20",
    "addr:postcode":"2320",
    "addr:street":"Burgemeester J. Van Aperenstraat",
    "iso:country":"BE",
    "sg:address":"Burgemeester J. Van Aperenstraat 20",
    "sg:city":"Hoogstraten",
    "sg:classifiers":[
        {
            "category":"Professional",
            "subcategory":"Management & Consulting",
            "type":"Services"
        }
    ],
    "sg:phone":"+32 3 314 86 65",
    "sg:postcode":"2320",
    "sg:province":"Antwerpen",
    "sg:tags":[
        "tax-consultants"
    ],
    "wof:name":"Ansoms G",
    "wof:placetype":"venue"
},
  "geometry": {"coordinates":[4.7574038506,51.4000816345],"type":"Point"}
}