{
  "type": "Feature",
  "properties": {
    "iso:country":"BE",
    "sg:address":"Hof Ter Bloemmolens 41",
    "sg:city":"Diksmuide",
    "sg:classifiers":[
        {
            "category":"Personal",
            "subcategory":"Barber",
            "type":"Services"
        }
    ],
    "sg:phone":"+32 51 50 08 89",
    "sg:postcode":"8600",
    "sg:province":"West-Vlaanderen",
    "sg:tags":[
        "gentleman",
        "salon",
        "-",
        "hairdressing"
    ],
    "wof:name":"Vanacker R",
    "wof:placetype":"venue"
},
  "geometry": {"coordinates":[2.8568029404,51.0342712402],"type":"Point"}
}