{
  "type": "Feature",
  "properties": {
    "iso:country":"BE",
    "sg:address":"Gammel 77",
    "sg:city":"Rijkevorsel",
    "sg:orig_category":"Souvenirs and objets artisanaux. Fleurs and plantes. Articles de jardin",
    "sg:phone":"+32 3 314 69 39",
    "sg:postcode":"2310",
    "sg:province":"Antwerpen",
    "wof:name":"Segers Center",
    "wof:placetype":"venue"
},
  "geometry": {"coordinates":[4.7566328049,51.3753242493],"type":"Point"}
}