{
  "type": "Feature",
  "properties": {
    "addr:full":"Rue Des D\u00e9port\u00e9s 10 Jurbise (masnuy-saint-jean) Hainaut 7050",
    "addr:housenumber":"10",
    "addr:postcode":"7050",
    "addr:street":"Rue Des De\u0301Porte\u0301S",
    "iso:country":"BE",
    "sg:address":"Rue Des D\u00e9port\u00e9s 10",
    "sg:city":"Jurbise (masnuy-saint-jean)",
    "sg:classifiers":[
        {
            "category":"Farming",
            "subcategory":"Livestock Farm",
            "type":"Manufacturing & Wholesale Goods"
        }
    ],
    "sg:phone":"+32 65 22 94 03",
    "sg:postcode":"7050",
    "sg:province":"Hainaut",
    "sg:tags":[
        "buyer"
    ],
    "wof:name":"Dupont X",
    "wof:placetype":"venue"
},
  "geometry": {"coordinates":[3.945775032,50.5302658081],"type":"Point"}
}