{
  "type": "Feature",
  "properties": {
    "iso:country":"BE",
    "sg:address":"Dorpsstraat 119",
    "sg:city":"Sint-laureins",
    "sg:classifiers":[
        {
            "category":"Bars & Pubs",
            "type":"Food & Drink"
        }
    ],
    "sg:phone":"+32 9 379 86 47",
    "sg:postcode":"9980",
    "sg:province":"Oost-Vlaanderen",
    "wof:name":"Boldershof",
    "wof:placetype":"venue"
},
  "geometry": {"coordinates":[3.5268809795,51.241230011],"type":"Point"}
}