{
  "type": "Feature",
  "properties": {
    "iso:country":"BE",
    "sg:address":"Avenue Du Bourgmestre Jean Materne 60-62",
    "sg:city":"Namur (jambes)",
    "sg:classifiers":[
        {
            "category":"Shopping",
            "subcategory":"Clothing, Apparel, & Fashions",
            "type":"Retail Goods"
        }
    ],
    "sg:phone":"+32 81 30 17 37",
    "sg:postcode":"5100",
    "sg:province":"Namur",
    "sg:tags":[
        "boutique"
    ],
    "wof:name":"Couture Georgette",
    "wof:placetype":"venue"
},
  "geometry": {"coordinates":[4.8713750839,50.4566345215],"type":"Point"}
}