{
  "type": "Feature",
  "properties": {
    "addr:full":"Urselseweg 13 Knesselare Oost-Vlaanderen 9910",
    "addr:housenumber":"13",
    "addr:postcode":"9910",
    "addr:street":"Urselseweg;Oost-Vlaanderen",
    "iso:country":"BE",
    "sg:address":"Urselseweg 13",
    "sg:city":"Knesselare",
    "sg:orig_category":"Sportclubs",
    "sg:phone":"+32 9 374 61 06",
    "sg:postcode":"9910",
    "sg:province":"Oost-Vlaanderen",
    "wof:name":"Jiptjan Kb Brugge",
    "wof:placetype":"venue"
},
  "geometry": {"coordinates":[3.4190459251,51.1369400024],"type":"Point"}
}