{
  "type": "Feature",
  "properties": {
    "iso:country":"BE",
    "sg:address":"Kwaadbeek 82",
    "sg:city":"Oosterzele",
    "sg:classifiers":[
        {
            "category":"Professional",
            "subcategory":"Accounting & Tax Preparation",
            "type":"Services"
        }
    ],
    "sg:phone":"+32 9 362 60 72",
    "sg:postcode":"9860",
    "sg:province":"Oost-Vlaanderen",
    "sg:tags":[
        "accountant"
    ],
    "wof:name":"Erik Martens",
    "wof:placetype":"venue"
},
  "geometry": {"coordinates":[3.8266279697,50.9629249573],"type":"Point"}
}