{
  "type": "Feature",
  "properties": {
    "addr:full":"Chemin Des Deux Maisons 73 Box 33-34 Bruxelles (woluwe-saint-lambert) Bruxelles-Capitale 1200",
    "addr:housenumber":"73 box 33-34",
    "addr:postcode":"1200",
    "addr:street":"Chemin Des Deux Maisons",
    "iso:country":"BE",
    "sg:address":"Chemin Des Deux Maisons 73 Box 33-34",
    "sg:city":"Bruxelles (woluwe-saint-lambert)",
    "sg:classifiers":[
        {
            "category":"Health Services",
            "subcategory":"Health Practitioner",
            "type":"Services"
        }
    ],
    "sg:phone":"+32 2 779 34 27",
    "sg:postcode":"1200",
    "sg:province":"Bruxelles-Capitale",
    "sg:tags":[
        "alternative",
        "therapy",
        "treatment"
    ],
    "wof:name":"Aura Soma Belgium Sprl",
    "wof:placetype":"venue"
},
  "geometry": {"coordinates":[4.4252500534,50.8438148499],"type":"Point"}
}