{
  "type": "Feature",
  "properties": {
    "addr:full":"Rue De Verviers 181 Herve Li\u00e8ge 4650",
    "addr:housenumber":"181",
    "addr:postcode":"4650",
    "addr:street":"Rue De Verviers",
    "iso:country":"BE",
    "sg:address":"Rue De Verviers 181",
    "sg:city":"Herve",
    "sg:orig_category":"Equipement divers pour commerces Alimentation sp\u00e9cialis\u00e9e",
    "sg:phone":"+32 87 67 91 73",
    "sg:postcode":"4650",
    "sg:province":"Li\u00e8ge",
    "wof:name":"Caf\u00c9s Li\u00c9geois",
    "wof:placetype":"venue"
},
  "geometry": {"coordinates":[5.8269128799,50.6248207092],"type":"Point"}
}