{
  "type": "Feature",
  "properties": {
    "iso:country":"BE",
    "sg:address":"Rue De L'harmonie 9",
    "sg:city":"Herve",
    "sg:classifiers":[
        {
            "category":"Health Services",
            "subcategory":"Health Practitioner",
            "type":"Services"
        }
    ],
    "sg:phone":"+32 87 67 59 46",
    "sg:postcode":"4650",
    "sg:province":"Li\u00e8ge",
    "sg:tags":[
        "therapist",
        "speech"
    ],
    "wof:name":"Mertens-delhaye A",
    "wof:placetype":"venue"
},
  "geometry": {"coordinates":[5.7966132164,50.6391181946],"type":"Point"}
}