{
  "type": "Feature",
  "properties": {
    "addr:full":"Ruelle De For\u00eat 3 Charleroi (mont-sur-marchienne) Hainaut 6032",
    "addr:housenumber":"3",
    "addr:postcode":"6032",
    "addr:street":"Ruelle De Fore\u0302T",
    "iso:country":"BE",
    "sg:address":"Ruelle De For\u00eat 3",
    "sg:city":"Charleroi (mont-sur-marchienne)",
    "sg:classifiers":[
        {
            "category":"Building & Trades",
            "subcategory":"Landscaping Services",
            "type":"Services"
        }
    ],
    "sg:phone":"+32 71 47 55 02",
    "sg:postcode":"6032",
    "sg:province":"Hainaut",
    "sg:tags":[
        "gardening",
        "garden",
        "maintenance"
    ],
    "wof:name":"Michaux S",
    "wof:placetype":"venue"
},
  "geometry": {"coordinates":[4.4063482285,50.3992462158],"type":"Point"}
}