{
  "type": "Feature",
  "properties": {
    "iso:country":"BE",
    "sg:address":"Rue Gustave Wauthier 36",
    "sg:city":"Sambreville",
    "sg:orig_category":"Salles de conf\u00e9rences and de r\u00e9ceptions. Caf\u00e9s",
    "sg:phone":"+32 71 77 59 64",
    "sg:postcode":"5060",
    "sg:province":"Namur",
    "wof:name":"Le Moulin De La Fluette",
    "wof:placetype":"venue"
},
  "geometry": {"coordinates":[4.6285200119,50.4448738098],"type":"Point"}
}