{
  "type": "Feature",
  "properties": {
    "addr:full":"Grote Baan 124 Sint-niklaas (nieuwkerken-waas) Oost-Vlaanderen 9100",
    "addr:housenumber":"124",
    "addr:postcode":"9100",
    "addr:street":"Grote Baan",
    "iso:country":"BE",
    "sg:address":"Grote Baan 124",
    "sg:city":"Sint-niklaas (nieuwkerken-waas)",
    "sg:classifiers":[
        {
            "category":"Organizations",
            "subcategory":"Professional Association",
            "type":"Services"
        }
    ],
    "sg:phone":"+32 16 40 15 03",
    "sg:postcode":"9100",
    "sg:province":"Oost-Vlaanderen",
    "sg:tags":[
        "tie",
        "scarf"
    ],
    "wof:name":"Altio Bv",
    "wof:placetype":"venue"
},
  "geometry": {"coordinates":[5.1428499222,51.6863708496],"type":"Point"}
}