{
  "type": "Feature",
  "properties": {
    "iso:country":"BE",
    "sg:address":"Epiceastraat 40",
    "sg:city":"Mol",
    "sg:classifiers":[
        {
            "category":"Autos & Motor Vehicles",
            "subcategory":"Fuel & Gas Station",
            "type":"Retail Goods"
        }
    ],
    "sg:phone":"+32 14 81 36 70",
    "sg:postcode":"2400",
    "sg:province":"Antwerpen",
    "sg:tags":[
        "stations-service",
        "carburants"
    ],
    "wof:name":"Paul Mahieu",
    "wof:placetype":"venue"
},
  "geometry": {"coordinates":[5.1931872368,51.190246582],"type":"Point"}
}