{
  "type": "Feature",
  "properties": {
    "addr:full":"Pastoor Paquaylaan 101 Heusden-zolder Limburg 3550",
    "addr:housenumber":"101",
    "addr:postcode":"3550",
    "addr:street":"Pastoor Paquaylaan",
    "iso:country":"BE",
    "sg:address":"Pastoor Paquaylaan 101",
    "sg:city":"Heusden-zolder",
    "sg:classifiers":[
        {
            "category":"Cafe",
            "type":"Food & Drink"
        }
    ],
    "sg:phone":"+32 11 57 44 14",
    "sg:postcode":"3550",
    "sg:province":"Limburg",
    "sg:tags":[
        "caf\u00e9s"
    ],
    "wof:name":"Caf\u00c9 Trefpunt",
    "wof:placetype":"venue"
},
  "geometry": {"coordinates":[5.3078107834,51.0433616638],"type":"Point"}
}