{
  "type": "Feature",
  "properties": {
    "iso:country":"BE",
    "sg:address":"Rue Sombre 36",
    "sg:city":"Bruxelles (woluwe-saint-lambert)",
    "sg:classifiers":[
        {
            "category":"Health Services",
            "subcategory":"Health Practitioner",
            "type":"Services"
        }
    ],
    "sg:phone":"+32 2 640 48 10",
    "sg:postcode":"1200",
    "sg:province":"Bruxelles-Capitale",
    "sg:tags":[
        "therapist",
        "speech"
    ],
    "wof:name":"Baudart G",
    "wof:placetype":"venue"
},
  "geometry": {"coordinates":[4.4316120148,50.8403282166],"type":"Point"}
}