{
  "type": "Feature",
  "properties": {
    "iso:country":"BE",
    "sg:address":"Place Chanteraine 25",
    "sg:city":"La Roche-en-ardenne",
    "sg:classifiers":[
        {
            "category":"Insurance",
            "subcategory":"Insurance Agent",
            "type":"Services"
        }
    ],
    "sg:phone":"+32 84 41 21 07",
    "sg:postcode":"6980",
    "sg:province":"Luxembourg",
    "sg:tags":[
        "verzekeringsmakelaars",
        "expert"
    ],
    "wof:name":"Kbc Assurances",
    "wof:placetype":"venue"
},
  "geometry": {"coordinates":[5.5745720863,50.1814193726],"type":"Point"}
}