{
  "type": "Feature",
  "properties": {
    "addr:full":"Rue Longue 10a Ch\u00e2telet (bouffioulx) Hainaut 6200",
    "addr:housenumber":"10a",
    "addr:postcode":"6200",
    "addr:street":"Rue Longue",
    "iso:country":"BE",
    "sg:address":"Rue Longue 10a",
    "sg:city":"Ch\u00e2telet (bouffioulx)",
    "sg:classifiers":[
        {
            "category":"Health Services",
            "subcategory":"Health Practitioner",
            "type":"Services"
        }
    ],
    "sg:phone":"+32 71 50 30 76",
    "sg:postcode":"6200",
    "sg:province":"Hainaut",
    "sg:tags":[
        "physiotherapist"
    ],
    "wof:name":"Ovando F",
    "wof:placetype":"venue"
},
  "geometry": {"coordinates":[4.495059967,50.374786377],"type":"Point"}
}