{
  "type": "Feature",
  "properties": {
    "addr:full":"Vlessersweg 36 Dilsen-stokkem Limburg 3650",
    "addr:housenumber":"36",
    "addr:postcode":"3650",
    "addr:street":"Vlessersweg",
    "iso:country":"BE",
    "sg:address":"Vlessersweg 36",
    "sg:city":"Dilsen-stokkem",
    "sg:orig_category":"Verplichte sociale verzekeringen",
    "sg:phone":"+32 89 75 51 67",
    "sg:postcode":"3650",
    "sg:province":"Limburg",
    "wof:name":"De Voorzorg",
    "wof:placetype":"venue"
},
  "geometry": {"coordinates":[5.7210278511,51.0346908569],"type":"Point"}
}