{
  "type": "Feature",
  "properties": {
    "addr:full":"Smedenstraat 96 Lier Antwerpen 2500",
    "addr:housenumber":"96",
    "addr:postcode":"2500",
    "addr:street":"Smedenstraat",
    "iso:country":"BE",
    "sg:address":"Smedenstraat 96",
    "sg:city":"Lier",
    "sg:classifiers":[
        {
            "category":"Building & Trades",
            "subcategory":"Pest Control",
            "type":"Services"
        }
    ],
    "sg:phone":"+32 3 480 02 73",
    "sg:postcode":"2500",
    "sg:province":"Antwerpen",
    "sg:tags":[
        "painting",
        "contractor"
    ],
    "wof:name":"Van Bouchout & Zn Bvba",
    "wof:placetype":"venue"
},
  "geometry": {"coordinates":[4.5462021828,51.1401672363],"type":"Point"}
}