{
  "type": "Feature",
  "properties": {
    "iso:country":"BE",
    "sg:address":"Chauss\u00e9e De Luingne 386",
    "sg:city":"Mouscron (herseaux)",
    "sg:classifiers":[
        {
            "category":"Building & Trades",
            "subcategory":"Construction",
            "type":"Services"
        }
    ],
    "sg:phone":"+32 56 84 35 75",
    "sg:postcode":"7712",
    "sg:province":"Hainaut",
    "sg:tags":[
        "stucco",
        "contractor"
    ],
    "wof:name":"Ocmant D",
    "wof:placetype":"venue"
},
  "geometry": {"coordinates":[3.2333300114,50.7353591919],"type":"Point"}
}