{
  "type": "Feature",
  "properties": {
    "iso:country":"BE",
    "sg:address":"Oude Vest 135",
    "sg:city":"Dendermonde",
    "sg:orig_category":"Opticiens",
    "sg:phone":"+32 52 22 25 24",
    "sg:postcode":"9200",
    "sg:province":"Oost-Vlaanderen",
    "wof:name":"Huis Colaes",
    "wof:placetype":"venue"
},
  "geometry": {"coordinates":[4.1047348976,51.0317687988],"type":"Point"}
}