{
  "type": "Feature",
  "properties": {
    "iso:country":"BE",
    "sg:address":"Rue Hubert Hanot 15",
    "sg:city":"Villers-le-bouillet (vaux-et-borset)",
    "sg:classifiers":[
        {
            "category":"Insurance",
            "subcategory":"Insurance Agent",
            "type":"Services"
        }
    ],
    "sg:phone":"+32 19 56 91 80",
    "sg:postcode":"4530",
    "sg:province":"Li\u00e8ge",
    "sg:tags":[
        "broker"
    ],
    "wof:name":"Fontana",
    "wof:placetype":"venue"
},
  "geometry": {"coordinates":[5.2331838608,50.610496521],"type":"Point"}
}