{
  "type": "Feature",
  "properties": {
    "addr:full":"Snellegemsestraat 69a Zedelgem West-Vlaanderen 8210",
    "addr:housenumber":"69a",
    "addr:postcode":"8210",
    "addr:street":"Snellegemsestraat",
    "iso:country":"BE",
    "sg:address":"Snellegemsestraat 69a",
    "sg:city":"Zedelgem",
    "sg:classifiers":[
        {
            "category":"Home & Garden",
            "subcategory":"Building Materials",
            "type":"Retail Goods"
        }
    ],
    "sg:phone":"+32 50 20 89 83",
    "sg:postcode":"8210",
    "sg:province":"West-Vlaanderen",
    "sg:tags":[
        "window"
    ],
    "wof:name":"Arhudson Bvba",
    "wof:placetype":"venue"
},
  "geometry": {"coordinates":[3.1314179897,51.1490325928],"type":"Point"}
}