{
  "type": "Feature",
  "properties": {
    "addr:full":"Rue Emile Vandervelde 5 Courcelles Hainaut 6182",
    "addr:housenumber":"5",
    "addr:postcode":"6182",
    "addr:street":"Rue Emile Vandervelde",
    "iso:country":"BE",
    "sg:address":"Rue Emile Vandervelde 5",
    "sg:city":"Courcelles",
    "sg:classifiers":[
        {
            "category":"Government",
            "subcategory":"Police Station",
            "type":"Public Place"
        }
    ],
    "sg:phone":"+32 71 46 99 91",
    "sg:postcode":"6182",
    "sg:province":"Hainaut",
    "sg:tags":[
        "gendarmerie"
    ],
    "wof:name":"Police F\u00c9d\u00c9rale/federale Politie",
    "wof:placetype":"venue"
},
  "geometry": {"coordinates":[4.3542299271,50.4462013245],"type":"Point"}
}