{
  "type": "Feature",
  "properties": {
    "iso:country":"BE",
    "sg:address":"Visserkaai 29",
    "sg:city":"Kortrijk",
    "sg:orig_category":"Bouwmaterialen Gh",
    "sg:phone":"+32 56 24 96 09",
    "sg:postcode":"8500",
    "sg:province":"West-Vlaanderen",
    "wof:name":"Littoral",
    "wof:placetype":"venue"
},
  "geometry": {"coordinates":[3.2859890461,50.8307723999],"type":"Point"}
}