{
  "type": "Feature",
  "properties": {
    "addr:full":"Domeinlaan 145 Vorst/forest Bruxelles-Capitale 1190",
    "addr:housenumber":"145",
    "addr:postcode":"1190",
    "addr:street":"Domeinlaan;/ Forest",
    "iso:country":"BE",
    "sg:address":"Domeinlaan 145",
    "sg:city":"Vorst/forest",
    "sg:orig_category":"Textiel",
    "sg:phone":"+32 2 343 93 27",
    "sg:postcode":"1190",
    "sg:province":"Bruxelles-Capitale",
    "wof:name":"Graphie",
    "wof:placetype":"venue"
},
  "geometry": {"coordinates":[4.3295679092,50.8114471436],"type":"Point"}
}