{
  "type": "Feature",
  "properties": {
    "iso:country":"BE",
    "sg:address":"Harmoniepad 4",
    "sg:city":"Vilvoorde",
    "sg:classifiers":[
        {
            "category":"Banks & Credit Unions",
            "subcategory":"Investment Brokerage",
            "type":"Services"
        }
    ],
    "sg:phone":"+32 2 252 53 25",
    "sg:postcode":"1800",
    "sg:province":"Vlaams-Brabant",
    "sg:tags":[
        "repair",
        "-",
        "installation",
        "sanitary",
        "article"
    ],
    "wof:name":"Reynvoet H",
    "wof:placetype":"venue"
},
  "geometry": {"coordinates":[4.4694638252,50.9495124817],"type":"Point"}
}