{
  "type": "Feature",
  "properties": {
    "iso:country":"BE",
    "sg:address":"Wittenweg 3",
    "sg:city":"Zoutleeuw",
    "sg:classifiers":[
        {
            "category":"Personal",
            "subcategory":"Beauty Salon",
            "type":"Services"
        }
    ],
    "sg:phone":"+32 11 78 49 12",
    "sg:postcode":"3440",
    "sg:province":"Vlaams-Brabant",
    "sg:tags":[
        "de",
        "coiffure"
    ],
    "wof:name":"Chris Van Wanghe",
    "wof:placetype":"venue"
},
  "geometry": {"coordinates":[5.0941371918,50.8011856079],"type":"Point"}
}