{
  "type": "Feature",
  "properties": {
    "addr:full":"Onthaalsquare 8 Evere Bruxelles-Capitale 1140",
    "addr:housenumber":"8",
    "addr:postcode":"1140",
    "addr:street":"Onthaalsquare",
    "iso:country":"BE",
    "sg:address":"Onthaalsquare 8",
    "sg:city":"Evere",
    "sg:orig_category":"Sportclubs",
    "sg:phone":"+32 477 23 54 67",
    "sg:postcode":"1140",
    "sg:province":"Bruxelles-Capitale",
    "wof:name":"Iris B.b.c. Bruxelles",
    "wof:placetype":"venue"
},
  "geometry": {"coordinates":[4.3959999084,50.8717269897],"type":"Point"}
}