{
  "type": "Feature",
  "properties": {
    "iso:country":"BE",
    "sg:address":"Place Guido Gezelle 10",
    "sg:city":"Ganshoren",
    "sg:orig_category":"Fleurs and plantes",
    "sg:phone":"+32 2 427 64 53",
    "sg:postcode":"1083",
    "sg:province":"Bruxelles-Capitale",
    "wof:name":"Nicole",
    "wof:placetype":"venue"
},
  "geometry": {"coordinates":[4.313934803,50.873664856],"type":"Point"}
}