{
  "type": "Feature",
  "properties": {
    "addr:full":"Rue Du Cimeti\u00c8re 1 Erquelinnes Hainaut 6560",
    "addr:housenumber":"1",
    "addr:postcode":"6560",
    "addr:street":"Rue Du Cimetie\u0300Re",
    "iso:country":"BE",
    "sg:address":"Rue Du Cimeti\u00c8re 1",
    "sg:city":"Erquelinnes",
    "sg:orig_category":"Artsen and specialisten",
    "sg:phone":"+32 64 77 11 44",
    "sg:postcode":"6560",
    "sg:province":"Hainaut",
    "wof:name":"Michel Vanhaudenarde",
    "wof:placetype":"venue"
},
  "geometry": {"coordinates":[4.0733089447,50.3285331726],"type":"Point"}
}