{
  "type": "Feature",
  "properties": {
    "iso:country":"BE",
    "sg:address":"Rue De L'etang 3",
    "sg:city":"Momignies",
    "sg:orig_category":"Rundveehouders",
    "sg:phone":"+32 60 51 15 94",
    "sg:postcode":"6593",
    "sg:province":"Hainaut",
    "wof:name":"Maurice Lejeune",
    "wof:placetype":"venue"
},
  "geometry": {"coordinates":[4.1909599304,49.9823913574],"type":"Point"}
}