{
  "type": "Feature",
  "properties": {
    "addr:full":"Rue Du Fr\u00c8re M\u00c9rantius 14 Virton Luxembourg 6760",
    "addr:housenumber":"14",
    "addr:postcode":"6760",
    "addr:street":"Rue Du Fre\u0300Re Me\u0301Rantius",
    "iso:country":"BE",
    "sg:address":"Rue Du Fr\u00c8re M\u00c9rantius 14",
    "sg:city":"Virton",
    "sg:orig_category":"Boekhouders",
    "sg:phone":"+32 63 57 16 49",
    "sg:postcode":"6760",
    "sg:province":"Luxembourg",
    "wof:name":"Martine Romain",
    "wof:placetype":"venue"
},
  "geometry": {"coordinates":[5.5938081741,49.5368156433],"type":"Point"}
}