{
  "type": "Feature",
  "properties": {
    "addr:full":"Rue Joseph Bens 127 Ukkel/uccle Bruxelles-Capitale 1180",
    "addr:housenumber":"127",
    "addr:postcode":"1180",
    "addr:street":"Rue Joseph Bens;/",
    "iso:country":"BE",
    "sg:address":"Rue Joseph Bens 127",
    "sg:city":"Ukkel/uccle",
    "sg:orig_category":"Production de films, t\u00e9l\u00e9films and vid\u00e9os",
    "sg:phone":"+32 2 346 16 84",
    "sg:postcode":"1180",
    "sg:province":"Bruxelles-Capitale",
    "wof:name":"P.p.a.",
    "wof:placetype":"venue"
},
  "geometry": {"coordinates":[4.3316860199,50.8065872192],"type":"Point"}
}