{
  "type": "Feature",
  "properties": {
    "iso:country":"BE",
    "sg:address":"Rooigemstraat 42",
    "sg:city":"Oosterzele (balegem)",
    "sg:classifiers":[
        {
            "category":"Food & Beverages",
            "subcategory":"Supermarket",
            "type":"Retail Goods"
        }
    ],
    "sg:phone":"+32 9 363 07 23",
    "sg:postcode":"9860",
    "sg:province":"Oost-Vlaanderen",
    "sg:tags":[
        "department",
        "store"
    ],
    "wof:name":"Cado",
    "wof:placetype":"venue"
},
  "geometry": {"coordinates":[3.8105750084,50.9456481934],"type":"Point"}
}