{
  "type": "Feature",
  "properties": {
    "addr:full":"Rodt 89a Sankt Vith Li\u00e8ge 4784",
    "addr:housenumber":"89a",
    "addr:postcode":"4784",
    "addr:street":"Rodt",
    "iso:country":"BE",
    "sg:address":"Rodt 89a",
    "sg:city":"Sankt Vith",
    "sg:orig_category":"Mus\u00e9es and patrimoine culturel",
    "sg:phone":"+32 80 22 63 01",
    "sg:postcode":"4784",
    "sg:province":"Li\u00e8ge",
    "wof:name":"Mus\u00c9e De La Bi\u00c8re",
    "wof:placetype":"venue"
},
  "geometry": {"coordinates":[6.0691699982,50.2871894836],"type":"Point"}
}