{
  "type": "Feature",
  "properties": {
    "iso:country":"BE",
    "sg:address":"Rue De Creyen 0",
    "sg:city":"Hannut",
    "sg:orig_category":"Openbare bibliotheken and archieven",
    "sg:phone":"+32 19 51 23 94",
    "sg:postcode":"4280",
    "sg:province":"Li\u00e8ge",
    "wof:name":"Ludoth\u00c8que Mille Borne",
    "wof:placetype":"venue"
},
  "geometry": {"coordinates":[5.0708861351,50.6675796509],"type":"Point"}
}