{
  "type": "Feature",
  "properties": {
    "iso:country":"BE",
    "sg:address":"Tuinlaan 56",
    "sg:city":"Sint-niklaas",
    "sg:orig_category":"Industri\u00eble elektrische installaties",
    "sg:phone":"+32 3 776 35 15",
    "sg:postcode":"9111",
    "sg:province":"Oost-Vlaanderen",
    "wof:name":"Leten",
    "wof:placetype":"venue"
},
  "geometry": {"coordinates":[4.1095781326,51.1527290344],"type":"Point"}
}