{
  "type": "Feature",
  "properties": {
    "addr:full":"Neervenweg 81 Wuustwezel Antwerpen 2990",
    "addr:housenumber":"81",
    "addr:postcode":"2990",
    "addr:street":"Neervenweg",
    "iso:country":"BE",
    "sg:address":"Neervenweg 81",
    "sg:city":"Wuustwezel",
    "sg:orig_category":"Eleveurs de bovins. Eleveurs and marchands de porcs",
    "sg:phone":"+32 3 669 64 55",
    "sg:postcode":"2990",
    "sg:province":"Antwerpen",
    "wof:name":"Adriaan Van Dijck",
    "wof:placetype":"venue"
},
  "geometry": {"coordinates":[4.6311497688,51.3938407898],"type":"Point"}
}