{
  "type": "Feature",
  "properties": {
    "iso:country":"BE",
    "sg:address":"Brieslaan 34",
    "sg:city":"Brussel/bruxelles",
    "sg:classifiers":[
        {
            "category":"Communications",
            "subcategory":"Film & Video Production",
            "type":"Services"
        }
    ],
    "sg:phone":"+32 2 268 34 38",
    "sg:postcode":"1020",
    "sg:province":"Bruxelles-Capitale",
    "sg:tags":[
        "platen",
        "cassette",
        "cd's"
    ],
    "wof:name":"Micky's Shop",
    "wof:placetype":"venue"
},
  "geometry": {"coordinates":[4.3581562042,50.8972434998],"type":"Point"}
}