{
  "type": "Feature",
  "properties": {
    "addr:full":"Place Du March\u00c9 35 Herve Li\u00e8ge 4651",
    "addr:housenumber":"35",
    "addr:postcode":"4651",
    "addr:street":"Place Du Marche\u0301",
    "iso:country":"BE",
    "sg:address":"Place Du March\u00c9 35",
    "sg:city":"Herve",
    "sg:orig_category":"Gespecialiseerde niet-residenti\u00eble bouw Installatie van metalen schrijnwerk Verlichting and huishoud",
    "sg:phone":"+32 87 67 49 06",
    "sg:postcode":"4651",
    "sg:province":"Li\u00e8ge",
    "wof:name":"Maison Bemelmans",
    "wof:placetype":"venue"
},
  "geometry": {"coordinates":[5.8209810257,50.6475296021],"type":"Point"}
}