{
  "type": "Feature",
  "properties": {
    "addr:full":"Stationsstraat 40 Neerpelt Limburg 3910",
    "addr:housenumber":"40",
    "addr:postcode":"3910",
    "addr:street":"Stationsstraat",
    "iso:country":"BE",
    "sg:address":"Stationsstraat 40",
    "sg:city":"Neerpelt",
    "sg:orig_category":"V\u00e9hicules automobiles",
    "sg:phone":"+32 11 64 58 18",
    "sg:postcode":"3910",
    "sg:province":"Limburg",
    "wof:name":"Auto\u00b4s Berben",
    "wof:placetype":"venue"
},
  "geometry": {"coordinates":[5.4362277985,51.2260017395],"type":"Point"}
}