{
  "type": "Feature",
  "properties": {
    "addr:full":"Bijlokevest 141 Gent Oost-Vlaanderen 9000",
    "addr:housenumber":"141",
    "addr:postcode":"9000",
    "addr:street":"Bijlokevest;Oost-Vlaanderen",
    "iso:country":"BE",
    "sg:address":"Bijlokevest 141",
    "sg:city":"Gent",
    "sg:orig_category":"D\u00e9corateurs d'int\u00e9rieur",
    "sg:phone":"+32 9 233 15 12",
    "sg:postcode":"9000",
    "sg:province":"Oost-Vlaanderen",
    "wof:name":"Joris Van Ransbeeck",
    "wof:placetype":"venue"
},
  "geometry": {"coordinates":[3.7107429504,51.0480995178],"type":"Point"}
}