{
  "type": "Feature",
  "properties": {
    "addr:full":"Kollegestraat 1 Geel Antwerpen 2440",
    "addr:housenumber":"1",
    "addr:postcode":"2440",
    "addr:street":"Kollegestraat",
    "iso:country":"BE",
    "sg:address":"Kollegestraat 1",
    "sg:city":"Geel",
    "sg:classifiers":[
        {
            "category":"Food & Beverages",
            "subcategory":"Chocolate",
            "type":"Retail Goods"
        }
    ],
    "sg:phone":"+32 14 58 61 06",
    "sg:postcode":"2440",
    "sg:province":"Antwerpen",
    "sg:tags":[
        "confectionery",
        "-"
    ],
    "wof:name":"Leonidas",
    "wof:placetype":"venue"
},
  "geometry": {"coordinates":[4.9917998314,51.1605148315],"type":"Point"}
}