{
  "type": "Feature",
  "properties": {
    "iso:country":"BE",
    "sg:address":"Smalvoortstraat 35 Box 4",
    "sg:city":"Turnhout",
    "sg:classifiers":[
        {
            "category":"Professional",
            "subcategory":"Management & Consulting",
            "type":"Services"
        }
    ],
    "sg:phone":"+32 14 41 27 44",
    "sg:postcode":"2300",
    "sg:province":"Antwerpen",
    "sg:tags":[
        "consultant",
        "-",
        "legislation",
        "social"
    ],
    "wof:name":"Kas Voor Het Jaarlijks Verlof Papierverwerkende Nijverheid Turnhout",
    "wof:placetype":"venue"
},
  "geometry": {"coordinates":[4.9535098076,51.3164253235],"type":"Point"}
}