{
  "type": "Feature",
  "properties": {
    "iso:country":"BE",
    "sg:address":"Stationsstraat 67",
    "sg:city":"Leopoldsburg",
    "sg:orig_category":"Eclairage et \u00e9quipements du foyer",
    "sg:phone":"+32 11 34 62 41",
    "sg:postcode":"3970",
    "sg:province":"Limburg",
    "wof:name":"Blokker",
    "wof:placetype":"venue"
},
  "geometry": {"coordinates":[5.2593688965,51.1177520752],"type":"Point"}
}