{
  "type": "Feature",
  "properties": {
    "iso:country":"BE",
    "sg:address":"Rue Bonaventure 4",
    "sg:city":"Jette/jette",
    "sg:orig_category":"V\u00e9t\u00e9rinaires",
    "sg:phone":"+32 2 478 64 51",
    "sg:postcode":"1090",
    "sg:province":"Bruxelles-Capitale",
    "wof:name":"Henri Van Lierde/h. Van Lierde",
    "wof:placetype":"venue"
},
  "geometry": {"coordinates":[4.3184227943,50.8852500916],"type":"Point"}
}