{
  "type": "Feature",
  "properties": {
    "addr:full":"Bankstraat 25 Kortenberg Vlaams-Brabant 3078",
    "addr:housenumber":"25",
    "addr:postcode":"3078",
    "addr:street":"Bankstraat;Vlaams-Brabant",
    "iso:country":"BE",
    "sg:address":"Bankstraat 25",
    "sg:city":"Kortenberg",
    "sg:classifiers":[
        {
            "category":"Arena",
            "subcategory":"Sports Club",
            "type":"Entertainment"
        }
    ],
    "sg:phone":"+32 2 759 49 51",
    "sg:postcode":"3078",
    "sg:province":"Vlaams-Brabant",
    "sg:tags":[
        "terrain",
        "hors",
        "de",
        "installation",
        "sportifs"
    ],
    "wof:name":"V.v. St.everberg",
    "wof:placetype":"venue"
},
  "geometry": {"coordinates":[4.5625720024,50.8801879883],"type":"Point"}
}