{
  "type": "Feature",
  "properties": {
    "iso:country":"BE",
    "sg:address":"Aire Autorouti\u00c8re Tellin-libin E411",
    "sg:city":"Libin",
    "sg:classifiers":[
        {
            "category":"Restaurant",
            "type":"Food & Drink"
        }
    ],
    "sg:phone":"+32 61 65 51 51",
    "sg:postcode":"6890",
    "sg:province":"Luxembourg",
    "wof:name":"La Porte Du Luxembourg",
    "wof:placetype":"venue"
},
  "geometry": {"coordinates":[5.2355642319,49.9358863831],"type":"Point"}
}