{
  "type": "Feature",
  "properties": {
    "iso:country":"BE",
    "sg:address":"Rue De La Station 12",
    "sg:city":"Bl\u00e9gny (trembleur)",
    "sg:classifiers":[
        {
            "category":"Building & Trades",
            "subcategory":"Electrical",
            "type":"Services"
        }
    ],
    "sg:phone":"+32 4 387 40 18",
    "sg:postcode":"4670",
    "sg:province":"Li\u00e8ge",
    "sg:tags":[
        "tool",
        "electric"
    ],
    "wof:name":"Denooz",
    "wof:placetype":"venue"
},
  "geometry": {"coordinates":[5.7251057625,50.6740150452],"type":"Point"}
}