{
  "type": "Feature",
  "properties": {
    "addr:full":"Maldersesteenweg 127 Londerzeel Vlaams-Brabant 1840",
    "addr:housenumber":"127",
    "addr:postcode":"1840",
    "addr:street":"Maldersesteenweg",
    "iso:country":"BE",
    "sg:address":"Maldersesteenweg 127",
    "sg:city":"Londerzeel",
    "sg:classifiers":[
        {
            "category":"Building & Trades",
            "subcategory":"Construction",
            "type":"Services"
        }
    ],
    "sg:phone":"+32 52 30 13 20",
    "sg:postcode":"1840",
    "sg:province":"Vlaams-Brabant",
    "sg:tags":[
        "installation",
        "-",
        "central",
        "heating"
    ],
    "wof:name":"Van De Voorde J",
    "wof:placetype":"venue"
},
  "geometry": {"coordinates":[4.2757549286,51.0267753601],"type":"Point"}
}