{
  "type": "Feature",
  "properties": {
    "iso:country":"BE",
    "sg:address":"Antwerpsestraat 300",
    "sg:city":"Boom",
    "sg:classifiers":[
        {
            "category":"Restaurant",
            "type":"Food & Drink"
        }
    ],
    "sg:phone":"+32 3 888 65 68",
    "sg:postcode":"2850",
    "sg:province":"Antwerpen",
    "wof:name":"Beukenhof",
    "wof:placetype":"venue"
},
  "geometry": {"coordinates":[4.367275238,51.0965499878],"type":"Point"}
}