{
  "type": "Feature",
  "properties": {
    "addr:full":"Bremveldlaan 53 Mortsel Antwerpen 2640",
    "addr:housenumber":"53",
    "addr:postcode":"2640",
    "addr:street":"Bremveldlaan",
    "iso:country":"BE",
    "sg:address":"Bremveldlaan 53",
    "sg:city":"Mortsel",
    "sg:classifiers":[
        {
            "category":"Arena",
            "subcategory":"Sports Club",
            "type":"Entertainment"
        }
    ],
    "sg:phone":"+32 3 454 28 42",
    "sg:postcode":"2640",
    "sg:province":"Antwerpen",
    "wof:name":"Creactief Vzw",
    "wof:placetype":"venue"
},
  "geometry": {"coordinates":[4.4678688049,51.1659164429],"type":"Point"}
}