{
  "type": "Feature",
  "properties": {
    "iso:country":"BE",
    "sg:address":"Rue Saint-lambert 7ba",
    "sg:city":"Burdinne",
    "sg:orig_category":"Sportclubs",
    "sg:phone":"+32 81 83 55 50",
    "sg:postcode":"4210",
    "sg:province":"Li\u00e8ge",
    "wof:name":"Raquette Joyeuse",
    "wof:placetype":"venue"
},
  "geometry": {"coordinates":[5.0481529236,50.5784187317],"type":"Point"}
}