{
  "type": "Feature",
  "properties": {
    "addr:full":"Vestingstraat 59b1 Antwerpen Antwerpen 2018",
    "addr:housenumber":"59b1",
    "addr:postcode":"2018",
    "addr:street":"Vestingstraat",
    "iso:country":"BE",
    "sg:address":"Vestingstraat 59b1",
    "sg:city":"Antwerpen",
    "sg:orig_category":"Horloges, m\u00e9taux pr\u00e9cieux and bijoux Bijoux Fab. Produits interm\u00e9diaires Gr",
    "sg:phone":"+32 3 233 93 99",
    "sg:postcode":"2018",
    "sg:province":"Antwerpen",
    "wof:name":"Continental Pearls Corp",
    "wof:placetype":"venue"
},
  "geometry": {"coordinates":[4.4197587967,51.2160987854],"type":"Point"}
}