{
  "type": "Feature",
  "properties": {
    "iso:country":"BE",
    "sg:address":"Rue De L'h\u00d4tellerie 45",
    "sg:city":"Lessines",
    "sg:orig_category":"Kapsalons",
    "sg:phone":"+32 68 33 33 84",
    "sg:postcode":"7860",
    "sg:province":"Hainaut",
    "wof:name":"Coiffure Ginette",
    "wof:placetype":"venue"
},
  "geometry": {"coordinates":[3.838135004,50.7103691101],"type":"Point"}
}