{
  "type": "Feature",
  "properties": {
    "iso:country":"BE",
    "sg:address":"Samberstraat 71",
    "sg:city":"Antwerpen",
    "sg:orig_category":"Mat\u00e9riaux de construction Quincailleries. Mat\u00e9riel pour plomberie and chauffage Gr",
    "sg:phone":"+32 3 231 34 31",
    "sg:postcode":"2060",
    "sg:province":"Antwerpen",
    "wof:name":"Cash & Carry",
    "wof:placetype":"venue"
},
  "geometry": {"coordinates":[4.4284920692,51.2343444824],"type":"Point"}
}