{
  "type": "Feature",
  "properties": {
    "iso:country":"BE",
    "sg:address":"Rue Du Bout 10",
    "sg:city":"Ouffet",
    "sg:orig_category":"Sous-v\u00eatements and lingerie. Installation \u00e9lectrique r\u00e9sidentielle",
    "sg:phone":"+32 86 36 67 20",
    "sg:postcode":"4590",
    "sg:province":"Li\u00e8ge",
    "wof:name":"Hincq M.",
    "wof:placetype":"venue"
},
  "geometry": {"coordinates":[5.4616909027,50.4358520508],"type":"Point"}
}