{
  "type": "Feature",
  "properties": {
    "iso:country":"BE",
    "sg:address":"Rue Rochers De Fr\u00e8ne 7",
    "sg:city":"Profondeville (lustin)",
    "sg:classifiers":[
        {
            "category":"Professional",
            "subcategory":"Computer Services",
            "type":"Services"
        }
    ],
    "sg:phone":"+32 475 80 69 46",
    "sg:postcode":"5170",
    "sg:province":"Namur",
    "sg:tags":[
        "webdesign",
        "-",
        "internet"
    ],
    "wof:name":"Csa",
    "wof:placetype":"venue"
},
  "geometry": {"coordinates":[4.8674049377,50.3786392212],"type":"Point"}
}