{
  "type": "Feature",
  "properties": {
    "addr:full":"Bruggestraat 437 Menen West-Vlaanderen 8930",
    "addr:housenumber":"437",
    "addr:postcode":"8930",
    "addr:street":"Bruggestraat",
    "iso:country":"BE",
    "sg:address":"Bruggestraat 437",
    "sg:city":"Menen",
    "sg:orig_category":"Onderdelen and accessoires voertuigen Gh",
    "sg:phone":"+32 56 51 33 98",
    "sg:postcode":"8930",
    "sg:province":"West-Vlaanderen",
    "wof:name":"Vandendriessche",
    "wof:placetype":"venue"
},
  "geometry": {"coordinates":[3.1220290661,50.8102874756],"type":"Point"}
}