{
  "type": "Feature",
  "properties": {
    "addr:full":"Sint-jansstraat 13 Waregem West-Vlaanderen 8791",
    "addr:housenumber":"13",
    "addr:postcode":"8791",
    "addr:street":"Sint-Jansstraat",
    "iso:country":"BE",
    "sg:address":"Sint-jansstraat 13",
    "sg:city":"Waregem",
    "sg:orig_category":"Epiceries",
    "sg:phone":"+32 56 72 61 13",
    "sg:postcode":"8791",
    "sg:province":"West-Vlaanderen",
    "wof:name":"Daisy Vanmeerhaeghe",
    "wof:placetype":"venue"
},
  "geometry": {"coordinates":[3.3358769417,50.8698348999],"type":"Point"}
}