{
  "type": "Feature",
  "properties": {
    "iso:country":"BE",
    "sg:address":"Kasteelstraat 74",
    "sg:city":"De Panne",
    "sg:orig_category":"Brood, gebak and snoepgoed",
    "sg:phone":"+32 58 41 17 37",
    "sg:postcode":"8660",
    "sg:province":"West-Vlaanderen",
    "wof:name":"Pieter Van Huele",
    "wof:placetype":"venue"
},
  "geometry": {"coordinates":[2.5914859772,51.0961494446],"type":"Point"}
}