{
  "type": "Feature",
  "properties": {
    "iso:country":"BE",
    "sg:address":"Gistelsesteenweg 609",
    "sg:city":"Oostende",
    "sg:orig_category":"Rundveehouders",
    "sg:phone":"+32 59 26 88 74",
    "sg:postcode":"8400",
    "sg:province":"West-Vlaanderen",
    "wof:name":"Peter Scharlaken",
    "wof:placetype":"venue"
},
  "geometry": {"coordinates":[2.935669899,51.2024002075],"type":"Point"}
}