{
  "type": "Feature",
  "properties": {
    "addr:full":"Heilaar 38 Arendonk Antwerpen 2370",
    "addr:housenumber":"38",
    "addr:postcode":"2370",
    "addr:street":"Heilaar",
    "iso:country":"BE",
    "sg:address":"Heilaar 38",
    "sg:city":"Arendonk",
    "sg:orig_category":"Peinture. Rev\u00eatements pour sols and murs",
    "sg:phone":"+32 14 67 28 85",
    "sg:postcode":"2370",
    "sg:province":"Antwerpen",
    "wof:name":"Fa. Van Dael",
    "wof:placetype":"venue"
},
  "geometry": {"coordinates":[5.0725340843,51.318195343],"type":"Point"}
}