{
  "type": "Feature",
  "properties": {
    "iso:country":"BE",
    "sg:address":"Gentseweg 303",
    "sg:city":"Beveren (beveren-waas)",
    "sg:classifiers":[
        {
            "category":"Autos & Motor Vehicles",
            "subcategory":"Motorcycle Sales",
            "type":"Retail Goods"
        }
    ],
    "sg:phone":"+32 3 775 68 70",
    "sg:postcode":"9120",
    "sg:province":"Oost-Vlaanderen",
    "sg:tags":[
        "scooter",
        "-",
        "moped"
    ],
    "wof:name":"Daeco Bikes-de Corte",
    "wof:placetype":"venue"
},
  "geometry": {"coordinates":[4.2198901176,51.1956481934],"type":"Point"}
}