{
  "type": "Feature",
  "properties": {
    "addr:full":"Hoogstraat 30 Zwalm Oost-Vlaanderen 9636",
    "addr:housenumber":"30",
    "addr:postcode":"9636",
    "addr:street":"Hoogstraat;Oost-Vlaanderen",
    "iso:country":"BE",
    "sg:address":"Hoogstraat 30",
    "sg:city":"Zwalm",
    "sg:orig_category":"Installation \u00e9lectrique r\u00e9sidentielle",
    "sg:phone":"+32 55 49 95 52",
    "sg:postcode":"9636",
    "sg:province":"Oost-Vlaanderen",
    "wof:name":"Galerij Balcaen",
    "wof:placetype":"venue"
},
  "geometry": {"coordinates":[3.6839599609,50.8842773438],"type":"Point"}
}