{
  "type": "Feature",
  "properties": {
    "iso:country":"BE",
    "sg:address":"A. Vandenpeereboomplein 9",
    "sg:city":"Ieper",
    "sg:orig_category":"Electrom\u00e9nager, t\u00e9l\u00e9visions and radios. Jeux and jouets",
    "sg:phone":"+32 57 20 21 41",
    "sg:postcode":"8900",
    "sg:province":"West-Vlaanderen",
    "wof:name":"Elsteco",
    "wof:placetype":"venue"
},
  "geometry": {"coordinates":[2.884141922,50.851108551],"type":"Point"}
}