{
  "type": "Feature",
  "properties": {
    "addr:full":"Nobelstraat 122 Tremelo (baal) Vlaams-Brabant 3128",
    "addr:housenumber":"122",
    "addr:postcode":"3128",
    "addr:street":"Nobelstraat",
    "iso:country":"BE",
    "sg:address":"Nobelstraat 122",
    "sg:city":"Tremelo (baal)",
    "sg:classifiers":[
        {
            "category":"Freight",
            "type":"Transportation"
        }
    ],
    "sg:phone":"+32 16 53 37 60",
    "sg:postcode":"3128",
    "sg:province":"Vlaams-Brabant",
    "sg:tags":[
        "-",
        "transport"
    ],
    "wof:name":"Van Houtvinck Bvba",
    "wof:placetype":"venue"
},
  "geometry": {"coordinates":[4.7461571693,51.0119400024],"type":"Point"}
}