{
  "type": "Feature",
  "properties": {
    "iso:country":"BE",
    "sg:address":"Europalaan 44",
    "sg:city":"Genk",
    "sg:orig_category":"V\u00eatements. Chaussures. Maroquinerie and articles de voyage",
    "sg:phone":"+32 89 30 43 73",
    "sg:postcode":"3600",
    "sg:province":"Limburg",
    "wof:name":"Pronti",
    "wof:placetype":"venue"
},
  "geometry": {"coordinates":[5.4972801208,50.9661712646],"type":"Point"}
}