{
  "type": "Feature",
  "properties": {
    "addr:full":"Rue Du Ch\u00e2teau 53 Genappe (bousval) Brabant Wallon 1470",
    "addr:housenumber":"53",
    "addr:postcode":"1470",
    "addr:street":"Rue Du Cha\u0302Teau;Wallon",
    "iso:country":"BE",
    "sg:address":"Rue Du Ch\u00e2teau 53",
    "sg:city":"Genappe (bousval)",
    "sg:classifiers":[
        {
            "category":"Home & Garden",
            "subcategory":"Carpets & Floor Coverings",
            "type":"Retail Goods"
        }
    ],
    "sg:phone":"+32 67 78 04 95",
    "sg:postcode":"1470",
    "sg:province":"Brabant Wallon",
    "sg:tags":[
        "oriental"
    ],
    "wof:name":"Classicorient",
    "wof:placetype":"venue"
},
  "geometry": {"coordinates":[4.5172052383,50.6172637939],"type":"Point"}
}