{
  "type": "Feature",
  "properties": {
    "iso:country":"BE",
    "sg:address":"Chauss\u00e9e Du Roeulx 233",
    "sg:city":"Mons",
    "sg:classifiers":[
        {
            "category":"Building & Trades",
            "subcategory":"Construction",
            "type":"Services"
        }
    ],
    "sg:phone":"+32 65 31 47 35",
    "sg:postcode":"7000",
    "sg:province":"Hainaut",
    "sg:tags":[
        "stucco",
        "contractor"
    ],
    "wof:name":"Stano P Ets",
    "wof:placetype":"venue"
},
  "geometry": {"coordinates":[3.9781661034,50.4568214417],"type":"Point"}
}