{
  "type": "Feature",
  "properties": {
    "addr:full":"Marnixlaan 24 Brussel/bruxelles Bruxelles-Capitale 1000",
    "addr:housenumber":"24",
    "addr:postcode":"1000",
    "addr:street":"Marnixlaan;/",
    "iso:country":"BE",
    "sg:address":"Marnixlaan 24",
    "sg:city":"Brussel/bruxelles",
    "sg:orig_category":"Levensverzekeringsmaatschappijen Verzekeringen vastgoed",
    "sg:phone":"+32 2 738 40 00",
    "sg:postcode":"1000",
    "sg:province":"Bruxelles-Capitale",
    "wof:name":"B.b.l. Insurance",
    "wof:placetype":"venue"
},
  "geometry": {"coordinates":[4.3651299477,50.8398284912],"type":"Point"}
}