{
  "type": "Feature",
  "properties": {
    "iso:country":"BE",
    "sg:address":"Kursaal-oosthelling 11",
    "sg:city":"Oostende",
    "sg:classifiers":[
        {
            "category":"Restaurant",
            "type":"Food & Drink"
        }
    ],
    "sg:phone":"+32 59 70 18 36",
    "sg:postcode":"8400",
    "sg:province":"West-Vlaanderen",
    "wof:name":"Tea-room Au Pinguin",
    "wof:placetype":"venue"
},
  "geometry": {"coordinates":[2.9123849869,51.2325744629],"type":"Point"}
}