{
  "type": "Feature",
  "properties": {
    "addr:full":"Arkstraat 40 Lanaken Limburg 3620",
    "addr:housenumber":"40",
    "addr:postcode":"3620",
    "addr:street":"Arkstraat",
    "iso:country":"BE",
    "sg:address":"Arkstraat 40",
    "sg:city":"Lanaken",
    "sg:orig_category":"Artsen and specialisten",
    "sg:phone":"+32 89 71 50 39",
    "sg:postcode":"3620",
    "sg:province":"Limburg",
    "wof:name":"W. Thomassen",
    "wof:placetype":"venue"
},
  "geometry": {"coordinates":[5.6475720406,50.8903465271],"type":"Point"}
}