{
  "type": "Feature",
  "properties": {
    "iso:country":"BE",
    "sg:address":"Premi\u00c8re Avenue 165",
    "sg:city":"Herstal",
    "sg:orig_category":"Installation de menuiserie en bois and plastique. Installation \u00e9lectrique industrielle. Rev\u00eatements ",
    "sg:phone":"+32 4 264 09 25",
    "sg:postcode":"4040",
    "sg:province":"Li\u00e8ge",
    "wof:name":"Jean Wust",
    "wof:placetype":"venue"
},
  "geometry": {"coordinates":[5.6154317856,50.6897239685],"type":"Point"}
}