{
  "type": "Feature",
  "properties": {
    "iso:country":"BE",
    "sg:address":"Groenstraat 46",
    "sg:city":"Mechelen",
    "sg:classifiers":[
        {
            "category":"Manufacturing",
            "subcategory":"Tools & Machinery",
            "type":"Manufacturing & Wholesale Goods"
        }
    ],
    "sg:phone":"+32 15 41 87 45",
    "sg:postcode":"2800",
    "sg:province":"Antwerpen",
    "sg:tags":[
        "scale"
    ],
    "wof:name":"Verheyden Kalibratie Bvba",
    "wof:placetype":"venue"
},
  "geometry": {"coordinates":[4.4762539864,51.0220222473],"type":"Point"}
}