{
  "type": "Feature",
  "properties": {
    "iso:country":"BE",
    "sg:address":"Avenue Franklin Roosevelt 45",
    "sg:city":"Bruxelles (ixelles)",
    "sg:classifiers":[
        {
            "category":"Government",
            "subcategory":"Embassy",
            "type":"Public Place"
        }
    ],
    "sg:phone":"+32 2 649 20 44",
    "sg:postcode":"1050",
    "sg:province":"Bruxelles-Capitale",
    "sg:tags":[
        "consulate"
    ],
    "wof:name":"Saoedi-arabi\u00eb (ambassade)",
    "wof:placetype":"venue"
},
  "geometry": {"coordinates":[4.3824701309,50.8099365234],"type":"Point"}
}