{
  "type": "Feature",
  "properties": {
    "iso:country":"BE",
    "sg:address":"Steenweg Asse 186",
    "sg:city":"Herne",
    "sg:orig_category":"Elektrische installaties voor woningen Woningbouw",
    "sg:phone":"+32 54 56 64 16",
    "sg:postcode":"1540",
    "sg:province":"Vlaams-Brabant",
    "wof:name":"Timmermans Freddy",
    "wof:placetype":"venue"
},
  "geometry": {"coordinates":[4.1014671326,50.7497406006],"type":"Point"}
}