{
  "type": "Feature",
  "properties": {
    "addr:full":"Haverreep 9 Assenede Oost-Vlaanderen 9960",
    "addr:housenumber":"9",
    "addr:postcode":"9960",
    "addr:street":"Haverreep",
    "iso:country":"BE",
    "sg:address":"Haverreep 9",
    "sg:city":"Assenede",
    "sg:classifiers":[
        {
            "category":"Metro Station",
            "type":"Transportation"
        }
    ],
    "sg:phone":"+32 9 343 06 00",
    "sg:postcode":"9960",
    "sg:province":"Oost-Vlaanderen",
    "sg:tags":[
        "repair",
        "ship",
        "mainten",
        "-"
    ],
    "wof:name":"Lear Marine Service Belgium Bvba",
    "wof:placetype":"venue"
},
  "geometry": {"coordinates":[3.7639100552,51.2056465149],"type":"Point"}
}