{
  "type": "Feature",
  "properties": {
    "iso:country":"BE",
    "sg:address":"Merksemsebaan 300",
    "sg:city":"Wijnegem",
    "sg:orig_category":"Non-Classified Establishments",
    "sg:phone":"+32 3 324 78 50",
    "sg:postcode":"2110",
    "sg:province":"Antwerpen",
    "wof:name":"Longerstaey Nv",
    "wof:placetype":"venue"
},
  "geometry": {"coordinates":[4.4924502373,51.2357292175],"type":"Point"}
}