{
  "type": "Feature",
  "properties": {
    "iso:country":"BE",
    "sg:address":"Abeelseweg 178",
    "sg:city":"Poperinge",
    "sg:classifiers":[
        {
            "category":"Building & Trades",
            "subcategory":"Construction",
            "type":"Services"
        }
    ],
    "sg:phone":"+32 57 33 65 61",
    "sg:postcode":"8970",
    "sg:province":"West-Vlaanderen",
    "sg:tags":[
        "stucco",
        "contractor"
    ],
    "wof:name":"Eran",
    "wof:placetype":"venue"
},
  "geometry": {"coordinates":[2.7028329372,50.8384475708],"type":"Point"}
}