{
  "type": "Feature",
  "properties": {
    "iso:country":"BE",
    "sg:address":"Rue Paul Pastur 320",
    "sg:city":"Quaregnon",
    "sg:orig_category":"Apotheken",
    "sg:phone":"+32 65 78 40 49",
    "sg:postcode":"7390",
    "sg:province":"Hainaut",
    "wof:name":"Alain Cannuyer",
    "wof:placetype":"venue"
},
  "geometry": {"coordinates":[3.8569149971,50.4492378235],"type":"Point"}
}