{
  "type": "Feature",
  "properties": {
    "addr:full":"Grand'rue 6 Gembloux-sur-orneau (gembloux) Namur 5030",
    "addr:housenumber":"6",
    "addr:postcode":"5030",
    "addr:street":"Grand'Rue;Namur",
    "iso:country":"BE",
    "sg:address":"Grand'rue 6",
    "sg:city":"Gembloux-sur-orneau (gembloux)",
    "sg:classifiers":[
        {
            "category":"Bars & Pubs",
            "type":"Food & Drink"
        }
    ],
    "sg:phone":"+32 81 61 22 20",
    "sg:postcode":"5030",
    "sg:province":"Namur",
    "wof:name":"Clair Obscur (le)",
    "wof:placetype":"venue"
},
  "geometry": {"coordinates":[4.6945400238,50.5666313171],"type":"Point"}
}