{
  "type": "Feature",
  "properties": {
    "addr:full":"Blauwhoevestraat 14 Rumst Antwerpen 2840",
    "addr:housenumber":"14",
    "addr:postcode":"2840",
    "addr:street":"Blauwhoevestraat",
    "iso:country":"BE",
    "sg:address":"Blauwhoevestraat 14",
    "sg:city":"Rumst",
    "sg:orig_category":"Fa\u00e7ade covering",
    "sg:postcode":"2840",
    "sg:province":"Antwerpen",
    "wof:name":"Cq Communications",
    "wof:placetype":"venue"
},
  "geometry": {"coordinates":[5.7037811279,51.2550163269],"type":"Point"}
}