{
  "type": "Feature",
  "properties": {
    "iso:country":"BE",
    "sg:address":"Ijzerlaan 14",
    "sg:city":"Scherpenheuvel-zichem",
    "sg:orig_category":"Quincailleries",
    "sg:phone":"+32 13 77 56 25",
    "sg:postcode":"3270",
    "sg:province":"Vlaams-Brabant",
    "wof:name":"Brico",
    "wof:placetype":"venue"
},
  "geometry": {"coordinates":[4.9500021935,50.9765167236],"type":"Point"}
}