{
  "type": "Feature",
  "properties": {
    "addr:full":"Kruisstraat 24 Tremelo Vlaams-Brabant 3120",
    "addr:housenumber":"24",
    "addr:postcode":"3120",
    "addr:street":"Kruisstraat",
    "iso:country":"BE",
    "sg:address":"Kruisstraat 24",
    "sg:city":"Tremelo",
    "sg:orig_category":"Openbare veiligheid",
    "sg:phone":"+32 16 53 11 23",
    "sg:postcode":"3120",
    "sg:province":"Vlaams-Brabant",
    "wof:name":"Federale Politie/police F\u00c9d\u00c9rale",
    "wof:placetype":"venue"
},
  "geometry": {"coordinates":[4.7024178505,50.9933128357],"type":"Point"}
}