{
  "type": "Feature",
  "properties": {
    "iso:country":"BE",
    "sg:address":"Guldensporenplein 16",
    "sg:city":"Hasselt",
    "sg:classifiers":[
        {
            "category":"Shopping",
            "subcategory":"Books",
            "type":"Retail Goods"
        }
    ],
    "sg:phone":"+32 11 24 18 28",
    "sg:postcode":"3500",
    "sg:province":"Limburg",
    "sg:tags":[
        "bookseller"
    ],
    "wof:name":"Gramadoelas",
    "wof:placetype":"venue"
},
  "geometry": {"coordinates":[5.3445968628,50.929851532],"type":"Point"}
}