{
  "type": "Feature",
  "properties": {
    "addr:full":"Henleykaai 3r Gent Oost-Vlaanderen 9000",
    "addr:housenumber":"3r",
    "addr:postcode":"9000",
    "addr:street":"Henleykaai;Oost-Vlaanderen",
    "iso:country":"BE",
    "sg:address":"Henleykaai 3r",
    "sg:city":"Gent",
    "sg:classifiers":[
        {
            "category":"Professional",
            "subcategory":"Lawyer & Legal Services",
            "type":"Services"
        }
    ],
    "sg:phone":"+32 9 267 35 50",
    "sg:postcode":"9000",
    "sg:province":"Oost-Vlaanderen",
    "wof:name":"Van Den Bossche L",
    "wof:placetype":"venue"
},
  "geometry": {"coordinates":[3.7171800137,51.0428695679],"type":"Point"}
}