{
  "type": "Feature",
  "properties": {
    "iso:country":"BE",
    "sg:address":"Quai Du Roi Albert 59 Box 2",
    "sg:city":"Li\u00e8ge 1 (li\u00e8ge 2)",
    "sg:classifiers":[
        {
            "category":"Shopping",
            "subcategory":"Baby Store",
            "type":"Retail Goods"
        }
    ],
    "sg:phone":"+32 4 343 26 24",
    "sg:postcode":"4020",
    "sg:province":"Li\u00e8ge",
    "sg:tags":[
        "hostess"
    ],
    "wof:name":"Dynamic Consult",
    "wof:placetype":"venue"
},
  "geometry": {"coordinates":[5.5949258804,50.6449546814],"type":"Point"}
}