{
  "type": "Feature",
  "properties": {
    "addr:full":"Liersesteenweg 35 Berlaar Antwerpen 2590",
    "addr:housenumber":"35",
    "addr:postcode":"2590",
    "addr:street":"Liersesteenweg",
    "iso:country":"BE",
    "sg:address":"Liersesteenweg 35",
    "sg:city":"Berlaar",
    "sg:orig_category":"Drukkerijen and copyshops",
    "sg:phone":"+32 3 422 55 55",
    "sg:postcode":"2590",
    "sg:province":"Antwerpen",
    "wof:name":"Steylaerts",
    "wof:placetype":"venue"
},
  "geometry": {"coordinates":[4.6474719048,51.1171112061],"type":"Point"}
}