{
  "type": "Feature",
  "properties": {
    "addr:full":"Grand Route 80a Huy Li\u00e8ge 4500",
    "addr:postcode":"4500",
    "addr:street":"Grand Route 80A",
    "iso:country":"BE",
    "sg:address":"Grand Route 80a",
    "sg:city":"Huy",
    "sg:classifiers":[
        {
            "category":"Shopping",
            "subcategory":"Pets & Pet Supplies",
            "type":"Retail Goods"
        }
    ],
    "sg:phone":"+32 85 25 57 59",
    "sg:postcode":"4500",
    "sg:province":"Li\u00e8ge",
    "sg:tags":[
        "aquarium",
        "accessory"
    ],
    "wof:name":"Aqua-select",
    "wof:placetype":"venue"
},
  "geometry": {"coordinates":[5.263010025,50.5304527283],"type":"Point"}
}