{
  "type": "Feature",
  "properties": {
    "addr:full":"Witvenstraat 69 Stabroek Antwerpen 2940",
    "addr:housenumber":"69",
    "addr:postcode":"2940",
    "addr:street":"Witvenstraat",
    "iso:country":"BE",
    "sg:address":"Witvenstraat 69",
    "sg:city":"Stabroek",
    "sg:orig_category":"Banken and kredietinstellingen",
    "sg:phone":"+32 3 664 69 78",
    "sg:postcode":"2940",
    "sg:province":"Antwerpen",
    "wof:name":"Groep Argenta",
    "wof:placetype":"venue"
},
  "geometry": {"coordinates":[4.3649148941,51.331943512],"type":"Point"}
}