{
  "type": "Feature",
  "properties": {
    "addr:full":"Avenue De Selliers De Moranville 33 Bruxelles (berchem-sainte-agathe) Bruxelles-Capitale 1082",
    "addr:housenumber":"33",
    "addr:postcode":"1082",
    "addr:street":"Avenue De Selliers De Moranville",
    "iso:country":"BE",
    "sg:address":"Avenue De Selliers De Moranville 33",
    "sg:city":"Bruxelles (berchem-sainte-agathe)",
    "sg:classifiers":[
        {
            "category":"Home & Garden",
            "subcategory":"Kitchen Supply",
            "type":"Retail Goods"
        }
    ],
    "sg:phone":"+32 2 482 32 50",
    "sg:postcode":"1082",
    "sg:province":"Bruxelles-Capitale",
    "sg:tags":[
        "equipment",
        "aircleaning"
    ],
    "wof:name":"A*",
    "wof:placetype":"venue"
},
  "geometry": {"coordinates":[4.2914748192,50.8681106567],"type":"Point"}
}