{
  "type": "Feature",
  "properties": {
    "addr:full":"Zwaarveld 62 Hamme Oost-Vlaanderen 9220",
    "addr:housenumber":"62",
    "addr:postcode":"9220",
    "addr:street":"Zwaarveld",
    "iso:country":"BE",
    "sg:address":"Zwaarveld 62",
    "sg:city":"Hamme",
    "sg:classifiers":[
        {
            "category":"Freight",
            "type":"Transportation"
        }
    ],
    "sg:phone":"+32 52 49 99 60",
    "sg:postcode":"9220",
    "sg:province":"Oost-Vlaanderen",
    "sg:tags":[
        "-",
        "transport"
    ],
    "wof:name":"Ijsewijn Transport Bvba",
    "wof:placetype":"venue"
},
  "geometry": {"coordinates":[4.1368360519,51.0758132935],"type":"Point"}
}