{
  "type": "Feature",
  "properties": {
    "addr:full":"Potaardegaarde 7 Kraainem/kraainem Vlaams-Brabant 1950",
    "addr:housenumber":"7",
    "addr:postcode":"1950",
    "addr:street":"Potaardegaarde",
    "iso:country":"BE",
    "sg:address":"Potaardegaarde 7",
    "sg:city":"Kraainem/kraainem",
    "sg:orig_category":"Artsen and specialisten",
    "sg:phone":"+32 2 782 01 61",
    "sg:postcode":"1950",
    "sg:province":"Vlaams-Brabant",
    "wof:name":"Andr\u00c9 Lhoir",
    "wof:placetype":"venue"
},
  "geometry": {"coordinates":[4.4703722,50.8389511108],"type":"Point"}
}