{
  "type": "Feature",
  "properties": {
    "addr:full":"Albert I-straat 27 Moeskroen/mouscron Hainaut 7700",
    "addr:housenumber":"27",
    "addr:postcode":"7700",
    "addr:street":"Albert I-Straat",
    "iso:country":"BE",
    "sg:address":"Albert I-straat 27",
    "sg:city":"Moeskroen/mouscron",
    "sg:orig_category":"Kapsalons",
    "sg:phone":"+32 56 34 50 76",
    "sg:postcode":"7700",
    "sg:province":"Hainaut",
    "wof:name":"Coiffure Veronique",
    "wof:placetype":"venue"
},
  "geometry": {"coordinates":[3.236782074,50.74243927],"type":"Point"}
}