{
  "type": "Feature",
  "properties": {
    "addr:full":"Oudekapellestraat 24 Diksmuide West-Vlaanderen 8600",
    "addr:housenumber":"24",
    "addr:postcode":"8600",
    "addr:street":"Oudekapellestraat",
    "iso:country":"BE",
    "sg:address":"Oudekapellestraat 24",
    "sg:city":"Diksmuide",
    "sg:orig_category":"Rundveehouders",
    "sg:phone":"+32 51 50 20 18",
    "sg:postcode":"8600",
    "sg:province":"West-Vlaanderen",
    "wof:name":"Andr\u00c9 Maeckelbergh",
    "wof:placetype":"venue"
},
  "geometry": {"coordinates":[2.8256640434,51.0316047668],"type":"Point"}
}