{
  "type": "Feature",
  "properties": {
    "iso:country":"BE",
    "sg:address":"Multatuliplein 1",
    "sg:city":"Antwerpen",
    "sg:orig_category":"Transports terrestres de voyageurs",
    "sg:phone":"+32 3 575 82 00",
    "sg:postcode":"2050",
    "sg:province":"Antwerpen",
    "wof:name":"Bivak Reizen",
    "wof:placetype":"venue"
},
  "geometry": {"coordinates":[4.3846712112,51.2223052979],"type":"Point"}
}