{
  "type": "Feature",
  "properties": {
    "addr:full":"Koning Albertlaan 7 Maaseik Limburg 3680",
    "addr:housenumber":"7",
    "addr:postcode":"3680",
    "addr:street":"Koning Albertlaan",
    "iso:country":"BE",
    "sg:address":"Koning Albertlaan 7",
    "sg:city":"Maaseik",
    "sg:classifiers":[
        {
            "category":"Health Services",
            "subcategory":"Dentist",
            "type":"Services"
        }
    ],
    "sg:phone":"+32 89 56 47 06",
    "sg:postcode":"3680",
    "sg:province":"Limburg",
    "wof:name":"Paredis E",
    "wof:placetype":"venue"
},
  "geometry": {"coordinates":[5.7848100662,51.0963745117],"type":"Point"}
}