{
  "type": "Feature",
  "properties": {
    "addr:full":"Rue D'omerie 28 Tournai (kain) Hainaut 7540",
    "addr:housenumber":"28",
    "addr:postcode":"7540",
    "addr:street":"Rue D'Omerie",
    "iso:country":"BE",
    "sg:address":"Rue D'omerie 28",
    "sg:city":"Tournai (kain)",
    "sg:classifiers":[
        {
            "category":"Building & Trades",
            "subcategory":"Electrical",
            "type":"Services"
        }
    ],
    "sg:phone":"+32 69 84 41 12",
    "sg:postcode":"7540",
    "sg:province":"Hainaut",
    "sg:tags":[
        "electric",
        "-",
        "housewiring",
        "contractor"
    ],
    "wof:name":"Renard B",
    "wof:placetype":"venue"
},
  "geometry": {"coordinates":[3.3927969933,50.6396408081],"type":"Point"}
}