{
  "type": "Feature",
  "properties": {
    "addr:full":"Nijverheidsstraat 12 Oevel Antwerpen 2260",
    "addr:housenumber":"12",
    "addr:postcode":"2260",
    "addr:street":"Nijverheidsstraat",
    "iso:country":"BE",
    "sg:address":"Nijverheidsstraat 12",
    "sg:city":"Oevel",
    "sg:classifiers":[
        {
            "category":"Manufacturing",
            "subcategory":"Motor Vehicles & Parts",
            "type":"Manufacturing & Wholesale Goods"
        }
    ],
    "sg:phone":"+32 14 57 47 11",
    "sg:postcode":"2260",
    "sg:province":"Antwerpen",
    "sg:tags":[
        "pipe",
        "exhaust"
    ],
    "wof:name":"Bosal Benelux Nv",
    "wof:placetype":"venue"
},
  "geometry": {"coordinates":[4.9310178757,51.1354789734],"type":"Point"}
}