{
  "type": "Feature",
  "properties": {
    "iso:country":"BE",
    "sg:address":"Hoogstraat 14",
    "sg:city":"Bierbeek",
    "sg:classifiers":[
        {
            "category":"Building & Trades",
            "subcategory":"Pest Control",
            "type":"Services"
        }
    ],
    "sg:phone":"+32 16 46 07 66",
    "sg:postcode":"3360",
    "sg:province":"Vlaams-Brabant",
    "sg:tags":[
        "painting",
        "contractor"
    ],
    "wof:name":"Van Brusselen E Bvba",
    "wof:placetype":"venue"
},
  "geometry": {"coordinates":[4.7547621727,50.8287124634],"type":"Point"}
}