{
  "type": "Feature",
  "properties": {
    "addr:full":"Rue De La Croix Jurlet 251 Herstal Li\u00e8ge 4040",
    "addr:housenumber":"251",
    "addr:postcode":"4040",
    "addr:street":"Rue De La Croix Jurlet",
    "iso:country":"BE",
    "sg:address":"Rue De La Croix Jurlet 251",
    "sg:city":"Herstal",
    "sg:classifiers":[
        {
            "category":"Retail",
            "subcategory":"Funeral Services",
            "type":"Services"
        }
    ],
    "sg:phone":"+32 4 264 02 50",
    "sg:postcode":"4040",
    "sg:province":"Li\u00e8ge",
    "sg:tags":[
        "director"
    ],
    "wof:name":"Pirard Fun\u00e9railles",
    "wof:placetype":"venue"
},
  "geometry": {"coordinates":[5.6318697929,50.6730194092],"type":"Point"}
}