{
  "type": "Feature",
  "properties": {
    "iso:country":"BE",
    "sg:address":"Kruishoutemsesteenweg 150",
    "sg:city":"Zingem",
    "sg:classifiers":[
        {
            "category":"Insurance",
            "subcategory":"Insurance Agent",
            "type":"Services"
        }
    ],
    "sg:phone":"+32 9 384 44 11",
    "sg:postcode":"9750",
    "sg:province":"Oost-Vlaanderen",
    "sg:tags":[
        "broker"
    ],
    "wof:name":"De Bruycker-callens",
    "wof:placetype":"venue"
},
  "geometry": {"coordinates":[3.636934042,50.9094924927],"type":"Point"}
}