{
  "type": "Feature",
  "properties": {
    "iso:country":"BE",
    "sg:address":"Rue Des Chartreux 4",
    "sg:city":"Bruxelles",
    "sg:classifiers":[
        {
            "category":"Cafe",
            "type":"Food & Drink"
        }
    ],
    "sg:phone":"+32 2 513 92 60",
    "sg:postcode":"1000",
    "sg:province":"Bruxelles-Capitale",
    "sg:tags":[
        "snack-bars"
    ],
    "wof:name":"Snack News",
    "wof:placetype":"venue"
},
  "geometry": {"coordinates":[4.347533226,50.8486976624],"type":"Point"}
}