{
  "type": "Feature",
  "properties": {
    "iso:country":"BE",
    "sg:city":"Saint-remy-geest",
    "sg:classifiers":[
        {
            "category":"Wholesale",
            "subcategory":"Plants",
            "type":"Manufacturing & Wholesale Goods"
        }
    ],
    "sg:phone":"+32 10 81 03 99",
    "sg:postcode":"1370",
    "sg:province":"Brabant Wallon",
    "sg:tags":[
        "decoration",
        "flower",
        "-"
    ],
    "wof:name":"Arbor & Flore",
    "wof:placetype":"venue"
},
  "geometry": {"coordinates":[4.859292984,50.7474861145],"type":"Point"}
}