{
  "type": "Feature",
  "properties": {
    "iso:country":"BE",
    "sg:address":"Mannenberg 157",
    "sg:city":"Scherpenheuvel-zichem (zichem)",
    "sg:classifiers":[
        {
            "category":"Professional",
            "subcategory":"Art Services",
            "type":"Services"
        }
    ],
    "sg:phone":"+32 13 78 22 34",
    "sg:postcode":"3271",
    "sg:province":"Vlaams-Brabant",
    "sg:tags":[
        "interior",
        "designer"
    ],
    "wof:name":"L.s.n. Design",
    "wof:placetype":"venue"
},
  "geometry": {"coordinates":[4.9869728088,51.0017662048],"type":"Point"}
}