{
  "type": "Feature",
  "properties": {
    "iso:country":"BE",
    "sg:address":"Rue L\u00c9on-mathieu 39",
    "sg:city":"Gedinne",
    "sg:orig_category":"Eleveurs de bovins",
    "sg:phone":"+32 61 58 86 00",
    "sg:postcode":"5575",
    "sg:province":"Namur",
    "wof:name":"Jean Baijot",
    "wof:placetype":"venue"
},
  "geometry": {"coordinates":[4.8832058907,49.9895782471],"type":"Point"}
}