{
  "type": "Feature",
  "properties": {
    "addr:full":"Rue De La Hunelle 16 Beloeil Hainaut 7970",
    "addr:housenumber":"16",
    "addr:postcode":"7970",
    "addr:street":"Rue De La Hunelle",
    "iso:country":"BE",
    "sg:address":"Rue De La Hunelle 16",
    "sg:city":"Beloeil",
    "sg:orig_category":"Animaux domestiques and accessoires",
    "sg:phone":"+32 69 68 94 43",
    "sg:postcode":"7970",
    "sg:province":"Hainaut",
    "wof:name":"Quertinier",
    "wof:placetype":"venue"
},
  "geometry": {"coordinates":[3.7328600883,50.5515899658],"type":"Point"}
}