{
  "type": "Feature",
  "properties": {
    "addr:full":"Van Schoonhovenstraat 23 Antwerpen Antwerpen 2060",
    "addr:housenumber":"23",
    "addr:postcode":"2060",
    "addr:street":"Van Schoonhovenstraat",
    "iso:country":"BE",
    "sg:address":"Van Schoonhovenstraat 23",
    "sg:city":"Antwerpen",
    "sg:orig_category":"Slagers",
    "sg:phone":"+32 3 233 55 79",
    "sg:postcode":"2060",
    "sg:province":"Antwerpen",
    "wof:name":"Beenhouw. Devarwaere & Zn",
    "wof:placetype":"venue"
},
  "geometry": {"coordinates":[4.4216570854,51.2200622559],"type":"Point"}
}