{
  "type": "Feature",
  "properties": {
    "addr:full":"Hagellaan 7 Olen Antwerpen 2250",
    "addr:housenumber":"7",
    "addr:postcode":"2250",
    "addr:street":"Hagellaan",
    "iso:country":"BE",
    "sg:address":"Hagellaan 7",
    "sg:city":"Olen",
    "sg:orig_category":"Drukkerijen and copyshops",
    "sg:phone":"+32 14 23 27 41",
    "sg:postcode":"2250",
    "sg:province":"Antwerpen",
    "wof:name":"Vanlommel",
    "wof:placetype":"venue"
},
  "geometry": {"coordinates":[4.8600449562,51.1438446045],"type":"Point"}
}