{
  "type": "Feature",
  "properties": {
    "iso:country":"BE",
    "sg:address":"Kortestraat 3",
    "sg:city":"Leuven",
    "sg:classifiers":[
        {
            "category":"Restaurant",
            "type":"Food & Drink"
        }
    ],
    "sg:phone":"+32 16 22 78 80",
    "sg:postcode":"3000",
    "sg:province":"Vlaams-Brabant",
    "wof:name":"Steak House",
    "wof:placetype":"venue"
},
  "geometry": {"coordinates":[4.7001318932,50.8788909912],"type":"Point"}
}