{
  "type": "Feature",
  "properties": {
    "iso:country":"BE",
    "sg:address":"Grijsbulckstraat 13",
    "sg:city":"Deinze (grammene)",
    "sg:classifiers":[
        {
            "category":"Building & Trades",
            "subcategory":"Landscaping Services",
            "type":"Services"
        }
    ],
    "sg:phone":"+32 51 63 73 65",
    "sg:postcode":"9800",
    "sg:province":"Oost-Vlaanderen",
    "sg:tags":[
        "gardening",
        "garden",
        "maintenance"
    ],
    "wof:name":"Dewitte D",
    "wof:placetype":"venue"
},
  "geometry": {"coordinates":[3.4601800442,50.988483429],"type":"Point"}
}