{
  "type": "Feature",
  "properties": {
    "iso:country":"BE",
    "sg:address":"Gemeentestraat 4ba",
    "sg:city":"Nijlen",
    "sg:classifiers":[
        {
            "category":"Cafe",
            "type":"Food & Drink"
        }
    ],
    "sg:phone":"+32 3 481 69 02",
    "sg:postcode":"2560",
    "sg:province":"Antwerpen",
    "sg:tags":[
        "caf\u00e9s"
    ],
    "wof:name":"Caf\u00c9 Centrum",
    "wof:placetype":"venue"
},
  "geometry": {"coordinates":[4.6703248024,51.1612243652],"type":"Point"}
}