{
  "type": "Feature",
  "properties": {
    "addr:full":"Muikemstraat 9 Assenede Oost-Vlaanderen 9968",
    "addr:housenumber":"9",
    "addr:postcode":"9968",
    "addr:street":"Muikemstraat",
    "iso:country":"BE",
    "sg:address":"Muikemstraat 9",
    "sg:city":"Assenede",
    "sg:orig_category":"V\u00eatements",
    "sg:phone":"+32 9 373 90 15",
    "sg:postcode":"9968",
    "sg:province":"Oost-Vlaanderen",
    "wof:name":"Huis Creato",
    "wof:placetype":"venue"
},
  "geometry": {"coordinates":[3.7125570774,51.1961517334],"type":"Point"}
}