{
  "type": "Feature",
  "properties": {
    "iso:country":"BE",
    "sg:address":"Singel 13",
    "sg:city":"Hasselt",
    "sg:orig_category":"Animations diverses. Installations and terrains de sport hors centres sportifs",
    "sg:phone":"+32 11 30 08 00",
    "sg:postcode":"3500",
    "sg:province":"Limburg",
    "wof:name":"De Schaverdijn",
    "wof:placetype":"venue"
},
  "geometry": {"coordinates":[5.3574280739,50.9270210266],"type":"Point"}
}