{
  "type": "Feature",
  "properties": {
    "iso:country":"BE",
    "sg:address":"Marktstraat 48",
    "sg:city":"Nieuwpoort",
    "sg:orig_category":"Banques and organismes de cr\u00e9dit",
    "sg:phone":"+32 58 22 39 60",
    "sg:postcode":"8620",
    "sg:province":"West-Vlaanderen",
    "wof:name":"Kbc",
    "wof:placetype":"venue"
},
  "geometry": {"coordinates":[2.7521739006,51.1301078796],"type":"Point"}
}