{
  "type": "Feature",
  "properties": {
    "iso:country":"BE",
    "sg:address":"Pandhoevestraat 81",
    "sg:city":"Tremelo (baal)",
    "sg:classifiers":[
        {
            "category":"Personal",
            "subcategory":"Beauty Salon",
            "type":"Services"
        }
    ],
    "sg:phone":"+32 16 53 62 94",
    "sg:postcode":"3128",
    "sg:province":"Vlaams-Brabant",
    "sg:tags":[
        "lady",
        "-",
        "hairdressing"
    ],
    "wof:name":"Gilis S",
    "wof:placetype":"venue"
},
  "geometry": {"coordinates":[4.7553529739,51.0156593323],"type":"Point"}
}