{
  "type": "Feature",
  "properties": {
    "iso:country":"BE",
    "sg:address":"Dr\u00e8ve Des Dix M\u00e8tres 141",
    "sg:city":"Waterloo",
    "sg:classifiers":[
        {
            "category":"Shopping",
            "subcategory":"Antiques",
            "type":"Retail Goods"
        }
    ],
    "sg:phone":"+32 2 351 44 07",
    "sg:postcode":"1410",
    "sg:province":"Brabant Wallon",
    "sg:tags":[
        "restoration"
    ],
    "wof:name":"Baillot",
    "wof:placetype":"venue"
},
  "geometry": {"coordinates":[4.3890838623,50.7210502625],"type":"Point"}
}