{
  "type": "Feature",
  "properties": {
    "iso:country":"BE",
    "sg:address":"Rue Des Garennes 85",
    "sg:city":"Watermaal-bosvoorde/watermael-boitsfort",
    "sg:orig_category":"Editeurs de livres",
    "sg:phone":"+32 2 660 56 68",
    "sg:postcode":"1170",
    "sg:province":"Bruxelles-Capitale",
    "wof:name":"Patrick Printz",
    "wof:placetype":"venue"
},
  "geometry": {"coordinates":[4.4164590836,50.8024902344],"type":"Point"}
}