{
  "type": "Feature",
  "properties": {
    "iso:country":"BE",
    "sg:address":"Rue Dehin 25",
    "sg:city":"Li\u00c8ge",
    "sg:orig_category":"Cr\u00e8ches and garderies d'enfants",
    "sg:phone":"+32 4 224 24 56",
    "sg:postcode":"4000",
    "sg:province":"Li\u00e8ge",
    "wof:name":"Cr\u00c8che Les Calinours",
    "wof:placetype":"venue"
},
  "geometry": {"coordinates":[5.55377388,50.6457481384],"type":"Point"}
}