{
  "type": "Feature",
  "properties": {
    "iso:country":"BE",
    "sg:address":"Koolmijnln 203",
    "sg:city":"Heusden-zolder",
    "sg:classifiers":[
        {
            "category":"Banks & Credit Unions",
            "subcategory":"Financial Services",
            "type":"Services"
        }
    ],
    "sg:phone":"+32 11 57 23 78",
    "sg:postcode":"3550",
    "sg:province":"Limburg",
    "sg:tags":[
        "banking",
        "finance",
        "insurance"
    ],
    "wof:name":"Verzekeringen Vandebroek Nv",
    "wof:placetype":"venue"
},
  "geometry": {"coordinates":[5.3040027618,51.0409164429],"type":"Point"}
}