{
  "type": "Feature",
  "properties": {
    "iso:country":"BE",
    "sg:address":"Plezantstraat 71",
    "sg:city":"Sint-niklaas",
    "sg:orig_category":"Reisbureaus",
    "sg:phone":"+32 3 760 00 00",
    "sg:postcode":"9100",
    "sg:province":"Oost-Vlaanderen",
    "wof:name":"Reizen Connections",
    "wof:placetype":"venue"
},
  "geometry": {"coordinates":[4.1351261139,51.1665534973],"type":"Point"}
}