{
  "type": "Feature",
  "properties": {
    "addr:full":"Kerkstraat 14 Melle Oost-Vlaanderen 9090",
    "addr:housenumber":"14",
    "addr:postcode":"9090",
    "addr:street":"Kerkstraat",
    "iso:country":"BE",
    "sg:address":"Kerkstraat 14",
    "sg:city":"Melle",
    "sg:orig_category":"Eclairage et \u00e9quipements du foyer. Installation \u00e9lectrique r\u00e9sidentielle",
    "sg:phone":"+32 9 252 12 98",
    "sg:postcode":"9090",
    "sg:province":"Oost-Vlaanderen",
    "wof:name":"Marc Carchon",
    "wof:placetype":"venue"
},
  "geometry": {"coordinates":[3.8012781143,51.0039024353],"type":"Point"}
}