{
  "type": "Feature",
  "properties": {
    "addr:full":"Fran\u00c7ois Rigasquare 35 Schaarbeek/schaerbeek Bruxelles-Capitale 1030",
    "addr:housenumber":"35",
    "addr:postcode":"1030",
    "addr:street":"Franc\u0327Ois Rigasquare",
    "iso:country":"BE",
    "sg:address":"Fran\u00c7ois Rigasquare 35",
    "sg:city":"Schaarbeek/schaerbeek",
    "sg:classifiers":[
        {
            "category":"Restaurant",
            "type":"Food & Drink"
        }
    ],
    "sg:phone":"+32 2 242 72 08",
    "sg:postcode":"1030",
    "sg:province":"Bruxelles-Capitale",
    "wof:name":"Restaurant Bacchus",
    "wof:placetype":"venue"
},
  "geometry": {"coordinates":[4.3864760399,50.8744277954],"type":"Point"}
}