{
  "type": "Feature",
  "properties": {
    "iso:country":"BE",
    "sg:address":"Chauss\u00e9e Victor Lampe 125",
    "sg:city":"Lessines (ollignies)",
    "sg:classifiers":[
        {
            "category":"Professional",
            "subcategory":"Lawyer & Legal Services",
            "type":"Services"
        }
    ],
    "sg:phone":"+32 68 33 84 01",
    "sg:postcode":"7866",
    "sg:province":"Hainaut",
    "sg:tags":[
        "notary"
    ],
    "wof:name":"Thomas L",
    "wof:placetype":"venue"
},
  "geometry": {"coordinates":[3.8627839088,50.6809883118],"type":"Point"}
}