{
  "type": "Feature",
  "properties": {
    "addr:full":"Visserij 77 Gent Oost-Vlaanderen 9000",
    "addr:housenumber":"77",
    "addr:postcode":"9000",
    "addr:street":"Visserij;Oost-Vlaanderen",
    "iso:country":"BE",
    "sg:address":"Visserij 77",
    "sg:city":"Gent",
    "sg:classifiers":[
        {
            "category":"Cafe",
            "type":"Food & Drink"
        }
    ],
    "sg:phone":"+32 9 233 81 89",
    "sg:postcode":"9000",
    "sg:province":"Oost-Vlaanderen",
    "sg:tags":[
        "snack-bars"
    ],
    "wof:name":"Beverly Hills Flo Bvba",
    "wof:placetype":"venue"
},
  "geometry": {"coordinates":[3.7378671169,51.0486755371],"type":"Point"}
}