{
  "type": "Feature",
  "properties": {
    "iso:country":"BE",
    "sg:address":"Stationsdreef 176",
    "sg:city":"Roeselare",
    "sg:orig_category":"Binnenhuisarchitecten Verlichting and huishoudartikelen Zalen voor culturele evenementen",
    "sg:phone":"+32 51 22 56 08",
    "sg:postcode":"8800",
    "sg:province":"West-Vlaanderen",
    "wof:name":"Demeester & Berteloot",
    "wof:placetype":"venue"
},
  "geometry": {"coordinates":[3.1268849373,50.9569625854],"type":"Point"}
}