{
  "type": "Feature",
  "properties": {
    "addr:full":"Rue De Monsville 284 Quaregnon Hainaut 7390",
    "addr:housenumber":"284",
    "addr:postcode":"7390",
    "addr:street":"Rue De Monsville",
    "iso:country":"BE",
    "sg:address":"Rue De Monsville 284",
    "sg:city":"Quaregnon",
    "sg:classifiers":[
        {
            "category":"Health Services",
            "subcategory":"Dentist",
            "type":"Services"
        }
    ],
    "sg:phone":"+32 65 77 75 75",
    "sg:postcode":"7390",
    "sg:province":"Hainaut",
    "wof:name":"Bail Claude",
    "wof:placetype":"venue"
},
  "geometry": {"coordinates":[3.8634829521,50.4347572327],"type":"Point"}
}