{
  "type": "Feature",
  "properties": {
    "addr:full":"Esenstraat 35a Kortemark West-Vlaanderen 8610",
    "addr:housenumber":"35a",
    "addr:postcode":"8610",
    "addr:street":"Esenstraat",
    "iso:country":"BE",
    "sg:address":"Esenstraat 35a",
    "sg:city":"Kortemark",
    "sg:orig_category":"Installatie van houten of kunststof schrijnwerk",
    "sg:phone":"+32 51 56 60 03",
    "sg:postcode":"8610",
    "sg:province":"West-Vlaanderen",
    "wof:name":"Loncke",
    "wof:placetype":"venue"
},
  "geometry": {"coordinates":[2.9547510147,51.0170783997],"type":"Point"}
}