{
  "type": "Feature",
  "properties": {
    "addr:full":"Florimond Leirensstraat 28 Wetteren Oost-Vlaanderen 9230",
    "addr:housenumber":"28",
    "addr:postcode":"9230",
    "addr:street":"Florimond Leirensstraat",
    "iso:country":"BE",
    "sg:address":"Florimond Leirensstraat 28",
    "sg:city":"Wetteren",
    "sg:classifiers":[
        {
            "category":"Health Services",
            "subcategory":"Dentist",
            "type":"Services"
        }
    ],
    "sg:phone":"+32 9 366 15 73",
    "sg:postcode":"9230",
    "sg:province":"Oost-Vlaanderen",
    "wof:name":"Van Severen Marie-bernadette",
    "wof:placetype":"venue"
},
  "geometry": {"coordinates":[3.8840041161,51.0055274963],"type":"Point"}
}