{
  "type": "Feature",
  "properties": {
    "iso:country":"BE",
    "sg:address":"Rue L\u00c9opold 40",
    "sg:city":"Herve",
    "sg:classifiers":[
        {
            "category":"Restaurant",
            "type":"Food & Drink"
        }
    ],
    "sg:phone":"+32 87 66 29 96",
    "sg:postcode":"4650",
    "sg:province":"Li\u00e8ge",
    "sg:tags":[
        "caf\u00e9s"
    ],
    "wof:name":"Le Bistrot",
    "wof:placetype":"venue"
},
  "geometry": {"coordinates":[5.7924900055,50.6394462585],"type":"Point"}
}