{
  "type": "Feature",
  "properties": {
    "addr:full":"Rue Des Combattants 30 Lessines (ollignies) Hainaut 7866",
    "addr:housenumber":"30",
    "addr:postcode":"7866",
    "addr:street":"Rue Des Combattants",
    "iso:country":"BE",
    "sg:address":"Rue Des Combattants 30",
    "sg:city":"Lessines (ollignies)",
    "sg:classifiers":[
        {
            "category":"Professional",
            "subcategory":"Testing Lab",
            "type":"Services"
        }
    ],
    "sg:phone":"+32 68 33 28 88",
    "sg:postcode":"7866",
    "sg:province":"Hainaut",
    "sg:tags":[
        "chemist"
    ],
    "wof:name":"Dutry D",
    "wof:placetype":"venue"
},
  "geometry": {"coordinates":[3.8606009483,50.6888504028],"type":"Point"}
}