{
  "type": "Feature",
  "properties": {
    "addr:full":"Rue Bois Sainte-marie 117 Sambreville (auvelais) Namur 5060",
    "addr:housenumber":"117",
    "addr:postcode":"5060",
    "addr:street":"Rue Bois Sainte-Marie",
    "iso:country":"BE",
    "sg:address":"Rue Bois Sainte-marie 117",
    "sg:city":"Sambreville (auvelais)",
    "sg:classifiers":[
        {
            "category":"Building & Trades",
            "subcategory":"Electrical",
            "type":"Services"
        }
    ],
    "sg:phone":"+32 71 77 30 00",
    "sg:postcode":"5060",
    "sg:province":"Namur",
    "sg:tags":[
        "industrial",
        "-",
        "electric",
        "contractor"
    ],
    "wof:name":"Meganelec Sa",
    "wof:placetype":"venue"
},
  "geometry": {"coordinates":[4.6417150497,50.4526062012],"type":"Point"}
}