{
  "type": "Feature",
  "properties": {
    "iso:country":"BE",
    "sg:address":"Gotevlietstraat 10",
    "sg:city":"Brugge",
    "sg:orig_category":"Motoren, transformatoren and generatoren Fab",
    "sg:phone":"+32 50 31 71 22",
    "sg:postcode":"8000",
    "sg:province":"West-Vlaanderen",
    "wof:name":"Duvivier",
    "wof:placetype":"venue"
},
  "geometry": {"coordinates":[3.2083539963,51.2575340271],"type":"Point"}
}