{
  "type": "Feature",
  "properties": {
    "addr:full":"Avenue J.f. Debecker 111 Bruxelles (woluwe-saint-lambert) Bruxelles-Capitale 1200",
    "addr:housenumber":"111",
    "addr:postcode":"1200",
    "addr:street":"Avenue J.F. Debecker",
    "iso:country":"BE",
    "sg:address":"Avenue J.f. Debecker 111",
    "sg:city":"Bruxelles (woluwe-saint-lambert)",
    "sg:classifiers":[
        {
            "category":"Health Services",
            "subcategory":"Doctor",
            "type":"Services"
        }
    ],
    "sg:phone":"+32 2 771 34 33",
    "sg:postcode":"1200",
    "sg:province":"Bruxelles-Capitale",
    "sg:tags":[
        "medicinephysicians",
        "surgeon"
    ],
    "wof:name":"Hachez Marc",
    "wof:placetype":"venue"
},
  "geometry": {"coordinates":[4.4471268654,50.8458404541],"type":"Point"}
}