{
  "type": "Feature",
  "properties": {
    "iso:country":"BE",
    "sg:address":"Zondereigen 12",
    "sg:city":"Baarle-hertog",
    "sg:orig_category":"Eleveurs de bovins",
    "sg:phone":"+32 14 63 30 05",
    "sg:postcode":"2387",
    "sg:province":"Antwerpen",
    "wof:name":"Arnold Timmermans",
    "wof:placetype":"venue"
},
  "geometry": {"coordinates":[4.907145977,51.4043693542],"type":"Point"}
}