{
  "type": "Feature",
  "properties": {
    "addr:full":"Obterrestraat 14 Poperinge (proven) West-Vlaanderen 8972",
    "addr:housenumber":"14",
    "addr:postcode":"8972",
    "addr:street":"Obterrestraat",
    "iso:country":"BE",
    "sg:address":"Obterrestraat 14",
    "sg:city":"Poperinge (proven)",
    "sg:classifiers":[
        {
            "category":"Professional",
            "subcategory":"Testing Lab",
            "type":"Services"
        }
    ],
    "sg:phone":"+32 57 30 11 21",
    "sg:postcode":"8972",
    "sg:province":"West-Vlaanderen",
    "sg:tags":[
        "chemist"
    ],
    "wof:name":"Regheere E",
    "wof:placetype":"venue"
},
  "geometry": {"coordinates":[2.65873909,50.8887176514],"type":"Point"}
}