{
  "type": "Feature",
  "properties": {
    "addr:full":"Korenmarkt 14 Mechelen Antwerpen 2800",
    "addr:housenumber":"14",
    "addr:postcode":"2800",
    "addr:street":"Korenmarkt",
    "iso:country":"BE",
    "sg:address":"Korenmarkt 14",
    "sg:city":"Mechelen",
    "sg:classifiers":[
        {
            "category":"Manufacturing",
            "subcategory":"Musical Instruments",
            "type":"Manufacturing & Wholesale Goods"
        }
    ],
    "sg:phone":"+32 15 33 12 15",
    "sg:postcode":"2800",
    "sg:province":"Antwerpen",
    "sg:tags":[
        "piano"
    ],
    "wof:name":"Muziekcentrum De Monte",
    "wof:placetype":"venue"
},
  "geometry": {"coordinates":[4.4759550095,51.0247764587],"type":"Point"}
}