{
  "type": "Feature",
  "properties": {
    "iso:country":"BE",
    "sg:address":"Coghenlaan 164",
    "sg:city":"Ukkel/uccle",
    "sg:orig_category":"Beautyfarms, relaxatie and lichamelijk welzijn Schoonheidssalons",
    "sg:phone":"+32 2 345 93 65",
    "sg:postcode":"1180",
    "sg:province":"Bruxelles-Capitale",
    "wof:name":"Centre Esth\u00c9tique Coghen",
    "wof:placetype":"venue"
},
  "geometry": {"coordinates":[4.3400998116,50.8083648682],"type":"Point"}
}