{
  "type": "Feature",
  "properties": {
    "iso:country":"BE",
    "sg:address":"Sint-truidersteenweg 465",
    "sg:city":"Borgloon",
    "sg:orig_category":"Pharmaciens",
    "sg:phone":"+32 12 74 22 80",
    "sg:postcode":"3840",
    "sg:province":"Limburg",
    "wof:name":"M. Martens",
    "wof:placetype":"venue"
},
  "geometry": {"coordinates":[5.2771449089,50.8070030212],"type":"Point"}
}