{
  "type": "Feature",
  "properties": {
    "addr:full":"Neutralstrasse 110 Lontzen/lontzen Li\u00e8ge 4710",
    "addr:housenumber":"110",
    "addr:postcode":"4710",
    "addr:street":"Neutralstrasse",
    "iso:country":"BE",
    "sg:address":"Neutralstrasse 110",
    "sg:city":"Lontzen/lontzen",
    "sg:orig_category":"Supermarkten",
    "sg:phone":"+32 87 88 29 77",
    "sg:postcode":"4710",
    "sg:province":"Li\u00e8ge",
    "wof:name":"Central Cash",
    "wof:placetype":"venue"
},
  "geometry": {"coordinates":[5.99229002,50.6763191223],"type":"Point"}
}