{
  "type": "Feature",
  "properties": {
    "addr:full":"Spinnetstraat 5 Zwevegem West-Vlaanderen 8554",
    "addr:housenumber":"5",
    "addr:postcode":"8554",
    "addr:street":"Spinnetstraat",
    "iso:country":"BE",
    "sg:address":"Spinnetstraat 5",
    "sg:city":"Zwevegem",
    "sg:classifiers":[
        {
            "category":"Insurance",
            "subcategory":"Insurance Agent",
            "type":"Services"
        }
    ],
    "sg:phone":"+32 56 45 55 02",
    "sg:postcode":"8554",
    "sg:province":"West-Vlaanderen",
    "sg:tags":[
        "verzekeringsmakelaars",
        "expert"
    ],
    "wof:name":"L. Seynaeve",
    "wof:placetype":"venue"
},
  "geometry": {"coordinates":[3.3706920147,50.7496185303],"type":"Point"}
}