{
  "type": "Feature",
  "properties": {
    "addr:full":"Kapellestraat 5 Aartselaar Antwerpen 2630",
    "addr:housenumber":"5",
    "addr:postcode":"2630",
    "addr:street":"Kapellestraat",
    "iso:country":"BE",
    "sg:address":"Kapellestraat 5",
    "sg:city":"Aartselaar",
    "sg:orig_category":"Kantoormateriaal Krantenwinkels Rookartikelen",
    "sg:phone":"+32 3 887 27 13",
    "sg:postcode":"2630",
    "sg:province":"Antwerpen",
    "wof:name":"'t Krantje",
    "wof:placetype":"venue"
},
  "geometry": {"coordinates":[4.3885569572,51.1333122253],"type":"Point"}
}