{
  "type": "Feature",
  "properties": {
    "addr:full":"Nekkerspoelstraat 77 Mechelen Antwerpen 2800",
    "addr:housenumber":"77",
    "addr:postcode":"2800",
    "addr:street":"Nekkerspoelstraat",
    "iso:country":"BE",
    "sg:address":"Nekkerspoelstraat 77",
    "sg:city":"Mechelen",
    "sg:orig_category":"Entretien and r\u00e9parations de voitures. D\u00e9taillants en pi\u00e8ces and accessoires de voitures",
    "sg:phone":"+32 15 55 72 75",
    "sg:postcode":"2800",
    "sg:province":"Antwerpen",
    "wof:name":"Midas",
    "wof:placetype":"venue"
},
  "geometry": {"coordinates":[4.4930071831,51.0310783386],"type":"Point"}
}