{
  "type": "Feature",
  "properties": {
    "iso:country":"BE",
    "sg:address":"Rue De La Motte 6",
    "sg:city":"Braives (ville-en-hesbaye)",
    "sg:orig_category":"Non-Classified Establishments",
    "sg:phone":"+32 19 69 99 68",
    "sg:postcode":"4260",
    "sg:province":"Li\u00e8ge",
    "wof:name":"Pirard R. Ets",
    "wof:placetype":"venue"
},
  "geometry": {"coordinates":[5.1161818504,50.6170425415],"type":"Point"}
}