{
  "type": "Feature",
  "properties": {
    "iso:country":"BE",
    "sg:address":"K. Madoudreef 10",
    "sg:city":"Brecht",
    "sg:orig_category":"Artsen and specialisten",
    "sg:phone":"+32 3 663 61 31",
    "sg:postcode":"2960",
    "sg:province":"Antwerpen",
    "wof:name":"Joris W. Hellebaut",
    "wof:placetype":"venue"
},
  "geometry": {"coordinates":[4.5576992035,51.3139419556],"type":"Point"}
}