{
  "type": "Feature",
  "properties": {
    "addr:full":"Rue De Tavier 286 Seraing Li\u00e8ge 4100",
    "addr:housenumber":"286",
    "addr:postcode":"4100",
    "addr:street":"Rue De Tavier",
    "iso:country":"BE",
    "sg:address":"Rue De Tavier 286",
    "sg:city":"Seraing",
    "sg:classifiers":[
        {
            "category":"Wholesale",
            "subcategory":"Medical Equipment & Supplies",
            "type":"Manufacturing & Wholesale Goods"
        }
    ],
    "sg:phone":"+32 4 336 06 29",
    "sg:postcode":"4100",
    "sg:province":"Li\u00e8ge",
    "sg:tags":[
        "aid",
        "hearing"
    ],
    "wof:name":"Espace Vision",
    "wof:placetype":"venue"
},
  "geometry": {"coordinates":[5.5066409111,50.5868682861],"type":"Point"}
}