{
  "type": "Feature",
  "properties": {
    "iso:country":"BE",
    "sg:address":"Gistelsteenweg 91a",
    "sg:city":"Jabbeke (varsenare)",
    "sg:classifiers":[
        {
            "category":"Food & Beverages",
            "subcategory":"Fruits & Vegetables",
            "type":"Retail Goods"
        }
    ],
    "sg:phone":"+32 50 39 04 62",
    "sg:postcode":"8490",
    "sg:province":"West-Vlaanderen",
    "sg:tags":[
        "-"
    ],
    "wof:name":"Banaantje ('t)",
    "wof:placetype":"venue"
},
  "geometry": {"coordinates":[3.1111450195,51.1791343689],"type":"Point"}
}