{
  "type": "Feature",
  "properties": {
    "iso:country":"BE",
    "sg:address":"Edmond Parmentierlaan 120",
    "sg:city":"Sint-pieters-woluwe/woluwe-saint-pierre",
    "sg:orig_category":"Artiesten and kunstenaars",
    "sg:phone":"+32 2 772 13 99",
    "sg:postcode":"1150",
    "sg:province":"Bruxelles-Capitale",
    "wof:name":"Axelle Maricq",
    "wof:placetype":"venue"
},
  "geometry": {"coordinates":[4.4435501099,50.8315925598],"type":"Point"}
}