{
  "type": "Feature",
  "properties": {
    "addr:full":"Grote Markt 85 Zelzate Oost-Vlaanderen 9060",
    "addr:housenumber":"85",
    "addr:postcode":"9060",
    "addr:street":"Grote Markt",
    "iso:country":"BE",
    "sg:address":"Grote Markt 85",
    "sg:city":"Zelzate",
    "sg:classifiers":[
        {
            "category":"Shopping",
            "subcategory":"Optician",
            "type":"Retail Goods"
        }
    ],
    "sg:phone":"+32 9 345 71 34",
    "sg:postcode":"9060",
    "sg:province":"Oost-Vlaanderen",
    "sg:tags":[
        "-"
    ],
    "wof:name":"Van Overstraeten J",
    "wof:placetype":"venue"
},
  "geometry": {"coordinates":[3.8118739128,51.1998252869],"type":"Point"}
}