{
  "type": "Feature",
  "properties": {
    "iso:country":"BE",
    "sg:address":"Limburgstraat 22 - 26",
    "sg:city":"Gent",
    "sg:classifiers":[
        {
            "category":"Restaurant",
            "type":"Food & Drink"
        }
    ],
    "sg:phone":"+32 9 223 02 79",
    "sg:postcode":"9000",
    "sg:province":"Oost-Vlaanderen",
    "wof:name":"Restaurant Adriatico",
    "wof:placetype":"venue"
},
  "geometry": {"coordinates":[3.7273139954,51.0524368286],"type":"Point"}
}