{
  "type": "Feature",
  "properties": {
    "addr:full":"Vrijgeweidestraat 62 Oostkamp West-Vlaanderen 8020",
    "addr:housenumber":"62",
    "addr:postcode":"8020",
    "addr:street":"Vrijgeweidestraat",
    "iso:country":"BE",
    "sg:address":"Vrijgeweidestraat 62",
    "sg:city":"Oostkamp",
    "sg:orig_category":"Woningbouw",
    "sg:phone":"+32 50 27 87 35",
    "sg:postcode":"8020",
    "sg:province":"West-Vlaanderen",
    "wof:name":"Pyfenco",
    "wof:placetype":"venue"
},
  "geometry": {"coordinates":[3.1679620743,51.0818328857],"type":"Point"}
}