{
  "type": "Feature",
  "properties": {
    "addr:full":"Zandstraat 5 Bocholt (reppel) Limburg 3950",
    "addr:housenumber":"5",
    "addr:postcode":"3950",
    "addr:street":"Zandstraat",
    "iso:country":"BE",
    "sg:address":"Zandstraat 5",
    "sg:city":"Bocholt (reppel)",
    "sg:classifiers":[
        {
            "category":"Travel",
            "subcategory":"Resort",
            "type":"Entertainment"
        }
    ],
    "sg:phone":"+32 89 46 27 20",
    "sg:postcode":"3950",
    "sg:province":"Limburg",
    "sg:tags":[
        "rental",
        "accomodation",
        "holiday",
        "-"
    ],
    "wof:name":"Bossemushof",
    "wof:placetype":"venue"
},
  "geometry": {"coordinates":[5.5518860817,51.1553611755],"type":"Point"}
}