{
  "type": "Feature",
  "properties": {
    "addr:full":"Rue Du Ch\u00c2teau 166 Anderlues Hainaut 6150",
    "addr:housenumber":"166",
    "addr:postcode":"6150",
    "addr:street":"Rue Du Cha\u0302Teau",
    "iso:country":"BE",
    "sg:address":"Rue Du Ch\u00c2teau 166",
    "sg:city":"Anderlues",
    "sg:orig_category":"Paramedische behandelingen",
    "sg:phone":"+32 71 52 86 21",
    "sg:postcode":"6150",
    "sg:province":"Hainaut",
    "wof:name":"D. Duez",
    "wof:placetype":"venue"
},
  "geometry": {"coordinates":[4.2697629929,50.3960838318],"type":"Point"}
}