{
  "type": "Feature",
  "properties": {
    "iso:country":"BE",
    "sg:address":"Chauss\u00c9e De Louvain 58",
    "sg:city":"Waterloo",
    "sg:orig_category":"Herstellingen and onderhoud van auto's",
    "sg:phone":"+32 2 384 27 18",
    "sg:postcode":"1410",
    "sg:province":"Brabant Wallon",
    "wof:name":"Sodeal",
    "wof:placetype":"venue"
},
  "geometry": {"coordinates":[4.4109039307,50.6907424927],"type":"Point"}
}