{
  "type": "Feature",
  "properties": {
    "iso:country":"BE",
    "sg:address":"Rue Reine Astrid 34",
    "sg:city":"Gembloux-sur-orneau (gembloux)",
    "sg:classifiers":[
        {
            "category":"Health Services",
            "subcategory":"Health Practitioner",
            "type":"Services"
        }
    ],
    "sg:phone":"+32 81 60 07 10",
    "sg:postcode":"5030",
    "sg:province":"Namur",
    "sg:tags":[
        "therapist",
        "speech"
    ],
    "wof:name":"Vanderast L",
    "wof:placetype":"venue"
},
  "geometry": {"coordinates":[4.6992092133,50.5607643127],"type":"Point"}
}