{
  "type": "Feature",
  "properties": {
    "addr:full":"Werthplatz 3 Eupen/eupen Li\u00e8ge 4700",
    "addr:housenumber":"3",
    "addr:postcode":"4700",
    "addr:street":"Werthplatz",
    "iso:country":"BE",
    "sg:address":"Werthplatz 3",
    "sg:city":"Eupen/eupen",
    "sg:orig_category":"Schoonheidssalons",
    "sg:phone":"+32 87 55 45 65",
    "sg:postcode":"4700",
    "sg:province":"Li\u00e8ge",
    "wof:name":"Institut Ath\u00cana",
    "wof:placetype":"venue"
},
  "geometry": {"coordinates":[6.0384459496,50.6324768066],"type":"Point"}
}