{
  "type": "Feature",
  "properties": {
    "iso:country":"BE",
    "sg:address":"All\u00e9e Des Bruy\u00e8res 9",
    "sg:city":"Walcourt (thy-le-ch\u00e2teau)",
    "sg:classifiers":[
        {
            "category":"Home & Garden",
            "subcategory":"Household Appliances",
            "type":"Retail Goods"
        }
    ],
    "sg:phone":"+32 71 22 03 12",
    "sg:postcode":"5651",
    "sg:province":"Namur",
    "sg:tags":[
        "repair",
        "stove",
        "-"
    ],
    "wof:name":"Cheminees Bernard Dupont Sprl",
    "wof:placetype":"venue"
},
  "geometry": {"coordinates":[4.4373688698,50.2993927002],"type":"Point"}
}