{
  "type": "Feature",
  "properties": {
    "addr:full":"Brakelberglei 31 Bonheiden Antwerpen 2820",
    "addr:housenumber":"31",
    "addr:postcode":"2820",
    "addr:street":"Brakelberglei",
    "iso:country":"BE",
    "sg:address":"Brakelberglei 31",
    "sg:city":"Bonheiden",
    "sg:classifiers":[
        {
            "category":"Food & Beverages",
            "subcategory":"Fruits & Vegetables",
            "type":"Retail Goods"
        }
    ],
    "sg:phone":"+32 15 41 37 97",
    "sg:postcode":"2820",
    "sg:province":"Antwerpen",
    "sg:tags":[
        "l\u00e9gumes",
        "gr"
    ],
    "wof:name":"Rik Pauwels En Zonen",
    "wof:placetype":"venue"
},
  "geometry": {"coordinates":[4.5496602058,51.0218009949],"type":"Point"}
}