{
  "type": "Feature",
  "properties": {
    "addr:full":"Chauss\u00e9e D'estaimpuis 201 Mouscron (herseaux) Hainaut 7712",
    "addr:housenumber":"201",
    "addr:postcode":"7712",
    "addr:street":"Chausse\u0301E D'Estaimpuis",
    "iso:country":"BE",
    "sg:address":"Chauss\u00e9e D'estaimpuis 201",
    "sg:city":"Mouscron (herseaux)",
    "sg:classifiers":[
        {
            "category":"Home & Garden",
            "subcategory":"Home Furnishings",
            "type":"Retail Goods"
        }
    ],
    "sg:phone":"+32 56 33 17 31",
    "sg:postcode":"7712",
    "sg:province":"Hainaut",
    "sg:tags":[
        "-",
        "furniture"
    ],
    "wof:name":"Espace Meubles",
    "wof:placetype":"venue"
},
  "geometry": {"coordinates":[3.2489860058,50.7139358521],"type":"Point"}
}