{
  "type": "Feature",
  "properties": {
    "addr:full":"Avenue De L'energie 17 Ans (alleur) Li\u00e8ge 4432",
    "addr:housenumber":"17",
    "addr:postcode":"4432",
    "addr:street":"Avenue De L'Energie",
    "iso:country":"BE",
    "sg:address":"Avenue De L'energie 17",
    "sg:city":"Ans (alleur)",
    "sg:classifiers":[
        {
            "category":"Retail",
            "subcategory":"Event Space",
            "type":"Services"
        }
    ],
    "sg:phone":"+32 4 239 97 39",
    "sg:postcode":"4432",
    "sg:province":"Li\u00e8ge",
    "sg:tags":[
        "organisation"
    ],
    "wof:name":"Euroculture Production Sa",
    "wof:placetype":"venue"
},
  "geometry": {"coordinates":[5.531493187,50.6756629944],"type":"Point"}
}