{
  "type": "Feature",
  "properties": {
    "iso:country":"BE",
    "sg:address":"Stationsstraat 93",
    "sg:city":"Waarschoot",
    "sg:orig_category":"Kapsalons",
    "sg:phone":"+32 9 377 48 36",
    "sg:postcode":"9950",
    "sg:province":"Oost-Vlaanderen",
    "wof:name":"Hair Shop",
    "wof:placetype":"venue"
},
  "geometry": {"coordinates":[3.6126019955,51.1527175903],"type":"Point"}
}