{
  "type": "Feature",
  "properties": {
    "addr:full":"Rue Konkel 155 Sint-pieters-woluwe/woluwe-saint-pierre Bruxelles-Capitale 1150",
    "addr:housenumber":"155",
    "addr:postcode":"1150",
    "addr:street":"Rue Konkel;/",
    "iso:country":"BE",
    "sg:address":"Rue Konkel 155",
    "sg:city":"Sint-pieters-woluwe/woluwe-saint-pierre",
    "sg:orig_category":"M\u00e9decins and sp\u00e9cialistes",
    "sg:phone":"+32 2 762 10 01",
    "sg:postcode":"1150",
    "sg:province":"Bruxelles-Capitale",
    "wof:name":"Mich\u00c8le Piron",
    "wof:placetype":"venue"
},
  "geometry": {"coordinates":[4.4475970268,50.8388900757],"type":"Point"}
}