{
  "type": "Feature",
  "properties": {
    "iso:country":"BE",
    "sg:address":"Wanzelestraat 27a",
    "sg:city":"Wichelen (schellebelle)",
    "sg:classifiers":[
        {
            "category":"Building & Trades",
            "subcategory":"Landscaping Services",
            "type":"Services"
        }
    ],
    "sg:phone":"+32 9 369 15 15",
    "sg:postcode":"9260",
    "sg:province":"Oost-Vlaanderen",
    "sg:tags":[
        "nurseryman"
    ],
    "wof:name":"Praet E",
    "wof:placetype":"venue"
},
  "geometry": {"coordinates":[3.9546840191,50.9942207336],"type":"Point"}
}