{
  "type": "Feature",
  "properties": {
    "addr:full":"Warandestraat 29 Zulte Oost-Vlaanderen 9870",
    "addr:housenumber":"29",
    "addr:postcode":"9870",
    "addr:street":"Warandestraat",
    "iso:country":"BE",
    "sg:address":"Warandestraat 29",
    "sg:city":"Zulte",
    "sg:classifiers":[
        {
            "category":"Building & Trades",
            "subcategory":"Construction",
            "type":"Services"
        }
    ],
    "sg:phone":"+32 9 388 31 99",
    "sg:postcode":"9870",
    "sg:province":"Oost-Vlaanderen",
    "sg:tags":[
        "stucco",
        "contractor"
    ],
    "wof:name":"Evaert P",
    "wof:placetype":"venue"
},
  "geometry": {"coordinates":[3.4548768997,50.924987793],"type":"Point"}
}