{
  "type": "Feature",
  "properties": {
    "iso:country":"BE",
    "sg:address":"Abdijstraat 2b001",
    "sg:city":"Sint-truiden",
    "sg:orig_category":"Chaussures",
    "sg:phone":"+32 11 68 66 33",
    "sg:postcode":"3800",
    "sg:province":"Limburg",
    "wof:name":"Huis Domani",
    "wof:placetype":"venue"
},
  "geometry": {"coordinates":[5.1886482239,50.8192558289],"type":"Point"}
}