{
  "type": "Feature",
  "properties": {
    "addr:full":"Place Du Champ De Mars 5 Elsene/ixelles Bruxelles-Capitale 1050",
    "addr:housenumber":"5",
    "addr:postcode":"1050",
    "addr:street":"Place Du Champ De Mars",
    "iso:country":"BE",
    "sg:address":"Place Du Champ De Mars 5",
    "sg:city":"Elsene/ixelles",
    "sg:orig_category":"Avocats and conseillers juridiques",
    "sg:phone":"+32 2 504 70 00",
    "sg:postcode":"1050",
    "sg:province":"Bruxelles-Capitale",
    "wof:name":"Bruno Lebrun",
    "wof:placetype":"venue"
},
  "geometry": {"coordinates":[4.3629989624,50.838344574],"type":"Point"}
}