{
  "type": "Feature",
  "properties": {
    "addr:full":"Rue Albert Ler 344a Erquelinnes Hainaut 6560",
    "addr:housenumber":"344a",
    "addr:postcode":"6560",
    "addr:street":"Rue Albert Ler",
    "iso:country":"BE",
    "sg:address":"Rue Albert Ler 344a",
    "sg:city":"Erquelinnes",
    "sg:orig_category":"Non-foodwinkels",
    "sg:phone":"+32 71 55 70 24",
    "sg:postcode":"6560",
    "sg:province":"Hainaut",
    "wof:name":"Prix Terrifiants",
    "wof:placetype":"venue"
},
  "geometry": {"coordinates":[4.111907959,50.3042411804],"type":"Point"}
}