{
  "type": "Feature",
  "properties": {
    "addr:full":"Koningsstraat 59 Oostende West-Vlaanderen 8400",
    "addr:housenumber":"59",
    "addr:postcode":"8400",
    "addr:street":"Koningsstraat",
    "iso:country":"BE",
    "sg:address":"Koningsstraat 59",
    "sg:city":"Oostende",
    "sg:classifiers":[
        {
            "category":"Travel",
            "subcategory":"Hotels & Motels",
            "type":"Entertainment"
        }
    ],
    "sg:phone":"+32 59 70 48 21",
    "sg:postcode":"8400",
    "sg:province":"West-Vlaanderen",
    "wof:name":"Kingston",
    "wof:placetype":"venue"
},
  "geometry": {"coordinates":[2.9089829922,51.2286148071],"type":"Point"}
}