{
  "type": "Feature",
  "properties": {
    "addr:full":"Hendrik I Lei 1 Vilvoorde Vlaams-Brabant 1800",
    "addr:housenumber":"1",
    "addr:postcode":"1800",
    "addr:street":"Hendrik I Lei",
    "iso:country":"BE",
    "sg:address":"Hendrik I Lei 1",
    "sg:city":"Vilvoorde",
    "sg:orig_category":"Banques and organismes de cr\u00e9dit",
    "sg:phone":"+32 2 251 21 44",
    "sg:postcode":"1800",
    "sg:province":"Vlaams-Brabant",
    "wof:name":"Fortis",
    "wof:placetype":"venue"
},
  "geometry": {"coordinates":[4.4281320572,50.9309921265],"type":"Point"}
}