{
  "type": "Feature",
  "properties": {
    "addr:full":"Avenue Victor Jacobs 29 Bruxelles (etterbeek) Bruxelles-Capitale 1040",
    "addr:housenumber":"29",
    "addr:postcode":"1040",
    "addr:street":"Avenue Victor Jacobs",
    "iso:country":"BE",
    "sg:address":"Avenue Victor Jacobs 29",
    "sg:city":"Bruxelles (etterbeek)",
    "sg:classifiers":[
        {
            "category":"Professional",
            "subcategory":"Accounting & Tax Preparation",
            "type":"Services"
        }
    ],
    "sg:phone":"+32 2 640 18 10",
    "sg:postcode":"1040",
    "sg:province":"Bruxelles-Capitale",
    "sg:tags":[
        "bookkeeper"
    ],
    "wof:name":"Celik M",
    "wof:placetype":"venue"
},
  "geometry": {"coordinates":[4.3843450546,50.8300590515],"type":"Point"}
}