{
  "type": "Feature",
  "properties": {
    "addr:full":"Fortuinstraat 36 Mechelen Antwerpen 2800",
    "addr:housenumber":"36",
    "addr:postcode":"2800",
    "addr:street":"Fortuinstraat",
    "iso:country":"BE",
    "sg:address":"Fortuinstraat 36",
    "sg:city":"Mechelen",
    "sg:classifiers":[
        {
            "category":"Fast Food",
            "type":"Food & Drink"
        }
    ],
    "sg:phone":"+32 15 41 65 73",
    "sg:postcode":"2800",
    "sg:province":"Antwerpen",
    "sg:tags":[
        "\u00c0",
        "emporter",
        "restaurants"
    ],
    "wof:name":"Freddy Peeters",
    "wof:placetype":"venue"
},
  "geometry": {"coordinates":[4.4659171104,51.019317627],"type":"Point"}
}