{
  "type": "Feature",
  "properties": {
    "addr:full":"Hasseltse Beverzakstraat 41 Hasselt Limburg 3500",
    "addr:housenumber":"41",
    "addr:postcode":"3500",
    "addr:street":"Beverzakstraat",
    "iso:country":"BE",
    "sg:address":"Hasseltse Beverzakstraat 41",
    "sg:city":"Hasselt",
    "sg:orig_category":"Sportclubs",
    "sg:phone":"+32 11 81 41 66",
    "sg:postcode":"3500",
    "sg:province":"Limburg",
    "wof:name":"Ok 50 Zonhoven",
    "wof:placetype":"venue"
},
  "geometry": {"coordinates":[5.3688158989,50.9723548889],"type":"Point"}
}