{
  "type": "Feature",
  "properties": {
    "addr:full":"Kasteelstraat 66 Temse Oost-Vlaanderen 9140",
    "addr:housenumber":"66",
    "addr:postcode":"9140",
    "addr:street":"Kasteelstraat",
    "iso:country":"BE",
    "sg:address":"Kasteelstraat 66",
    "sg:city":"Temse",
    "sg:orig_category":"Avocats and conseillers juridiques",
    "sg:phone":"+32 3 771 01 75",
    "sg:postcode":"9140",
    "sg:province":"Oost-Vlaanderen",
    "wof:name":"Fr. De Cuyper",
    "wof:placetype":"venue"
},
  "geometry": {"coordinates":[4.2175760269,51.1244888306],"type":"Point"}
}