{
  "type": "Feature",
  "properties": {
    "addr:full":"Hoornzeelstraat 8 Tervuren Vlaams-Brabant 3080",
    "addr:housenumber":"8",
    "addr:postcode":"3080",
    "addr:street":"Hoornzeelstraat",
    "iso:country":"BE",
    "sg:address":"Hoornzeelstraat 8",
    "sg:city":"Tervuren",
    "sg:orig_category":"Metallizing",
    "sg:phone":"+32 2 767 35 39",
    "sg:postcode":"3080",
    "sg:province":"Vlaams-Brabant",
    "wof:name":"Vanderlick J P",
    "wof:placetype":"venue"
},
  "geometry": {"coordinates":[4.5135660172,50.8225059509],"type":"Point"}
}