{
  "type": "Feature",
  "properties": {
    "addr:full":"Chauss\u00e9e De Mons 307 Soignies Hainaut 7060",
    "addr:housenumber":"307",
    "addr:postcode":"7060",
    "addr:street":"Chausse\u0301E De Mons",
    "iso:country":"BE",
    "sg:address":"Chauss\u00e9e De Mons 307",
    "sg:city":"Soignies",
    "sg:classifiers":[
        {
            "category":"Building & Trades",
            "subcategory":"Landscaping Services",
            "type":"Services"
        }
    ],
    "sg:phone":"+32 3 664 96 27",
    "sg:postcode":"7060",
    "sg:province":"Hainaut",
    "sg:tags":[
        "equipment",
        "swimming",
        "-",
        "pool",
        "contractor"
    ],
    "wof:name":"Desjoyaux",
    "wof:placetype":"venue"
},
  "geometry": {"coordinates":[4.0502681732,50.5497741699],"type":"Point"}
}