{
  "type": "Feature",
  "properties": {
    "addr:full":"Rue De La Science 44 Charleroi Hainaut 6000",
    "addr:housenumber":"44",
    "addr:postcode":"6000",
    "addr:street":"Rue De La Science;Hainaut",
    "iso:country":"BE",
    "sg:address":"Rue De La Science 44",
    "sg:city":"Charleroi",
    "sg:orig_category":"Advocaten and juridische adviseurs",
    "sg:phone":"+32 71 30 29 87",
    "sg:postcode":"6000",
    "sg:province":"Hainaut",
    "wof:name":"Beno\u00cet Simon",
    "wof:placetype":"venue"
},
  "geometry": {"coordinates":[4.4474787712,50.4127311707],"type":"Point"}
}