{
  "type": "Feature",
  "properties": {
    "addr:full":"Lummense-kiezel 111 Hasselt (kermt) Limburg 3510",
    "addr:housenumber":"111",
    "addr:postcode":"3510",
    "iso:country":"BE",
    "sg:address":"Lummense-kiezel 111",
    "sg:city":"Hasselt (kermt)",
    "sg:classifiers":[
        {
            "category":"Wholesale",
            "subcategory":"Poultry",
            "type":"Manufacturing & Wholesale Goods"
        }
    ],
    "sg:phone":"+32 11 24 34 96",
    "sg:postcode":"3510",
    "sg:province":"Limburg",
    "sg:tags":[
        "whol",
        "-",
        "egg"
    ],
    "wof:name":"Heima Nv",
    "wof:placetype":"venue"
},
  "geometry": {"coordinates":[5.2352910042,50.9626731873],"type":"Point"}
}