{
  "type": "Feature",
  "properties": {
    "addr:full":"Gerechtsstraat 2 Anderlecht Bruxelles-Capitale 1070",
    "addr:housenumber":"2",
    "addr:postcode":"1070",
    "addr:street":"Gerechtsstraat",
    "iso:country":"BE",
    "sg:address":"Gerechtsstraat 2",
    "sg:city":"Anderlecht",
    "sg:classifiers":[
        {
            "category":"Cafe",
            "type":"Food & Drink"
        }
    ],
    "sg:phone":"+32 2 523 35 54",
    "sg:postcode":"1070",
    "sg:province":"Bruxelles-Capitale",
    "sg:tags":[
        "caf\u00e9s"
    ],
    "wof:name":"Caf\u00c9 Chez Michel",
    "wof:placetype":"venue"
},
  "geometry": {"coordinates":[4.3120641708,50.8363571167],"type":"Point"}
}