{
  "type": "Feature",
  "properties": {
    "iso:country":"BE",
    "sg:address":"Georges Huygensstraat 15",
    "sg:city":"Oudergem/auderghem",
    "sg:orig_category":"Boekhouders",
    "sg:phone":"+32 2 660 56 07",
    "sg:postcode":"1160",
    "sg:province":"Bruxelles-Capitale",
    "wof:name":"Chantal Bossens",
    "wof:placetype":"venue"
},
  "geometry": {"coordinates":[4.439426899,50.8107261658],"type":"Point"}
}