{
  "type": "Feature",
  "properties": {
    "addr:full":"Oostnieuwkerksesteenweg 91 Roeselare West-Vlaanderen 8800",
    "addr:housenumber":"91",
    "addr:postcode":"8800",
    "addr:street":"Oostnieuwkerksesteenweg",
    "iso:country":"BE",
    "sg:address":"Oostnieuwkerksesteenweg 91",
    "sg:city":"Roeselare",
    "sg:orig_category":"Loodgieterij, verwarming and sanitaire installaties",
    "sg:phone":"+32 51 20 80 68",
    "sg:postcode":"8800",
    "sg:province":"West-Vlaanderen",
    "wof:name":"Edgard Stragier",
    "wof:placetype":"venue"
},
  "geometry": {"coordinates":[3.1011619568,50.9469299316],"type":"Point"}
}