{
  "type": "Feature",
  "properties": {
    "addr:full":"Otegemstraat 131 Zwevegem West-Vlaanderen 8550",
    "addr:housenumber":"131",
    "addr:postcode":"8550",
    "addr:street":"Otegemstraat",
    "iso:country":"BE",
    "sg:address":"Otegemstraat 131",
    "sg:city":"Zwevegem",
    "sg:orig_category":"Juwelen and horloges",
    "sg:phone":"+32 56 75 40 00",
    "sg:postcode":"8550",
    "sg:province":"West-Vlaanderen",
    "wof:name":"Goldman Number One",
    "wof:placetype":"venue"
},
  "geometry": {"coordinates":[3.3425900936,50.8145027161],"type":"Point"}
}