{
  "type": "Feature",
  "properties": {
    "addr:full":"Krijgsbaan 247 Temse Oost-Vlaanderen 9140",
    "addr:housenumber":"247",
    "addr:postcode":"9140",
    "addr:street":"Krijgsbaan",
    "iso:country":"BE",
    "sg:address":"Krijgsbaan 247",
    "sg:city":"Temse",
    "sg:classifiers":[
        {
            "category":"Manufacturing",
            "subcategory":"Glass & Minerals",
            "type":"Manufacturing & Wholesale Goods"
        }
    ],
    "sg:phone":"+32 3 711 12 07",
    "sg:postcode":"9140",
    "sg:province":"Oost-Vlaanderen",
    "sg:tags":[
        "building",
        "material"
    ],
    "wof:name":"Nsg Europe Nv",
    "wof:placetype":"venue"
},
  "geometry": {"coordinates":[4.2426271439,51.128364563],"type":"Point"}
}