{
  "type": "Feature",
  "properties": {
    "addr:full":"Rue Du Try 13 Andenne Namur 5300",
    "addr:housenumber":"13",
    "addr:postcode":"5300",
    "addr:street":"Rue Du Try",
    "iso:country":"BE",
    "sg:address":"Rue Du Try 13",
    "sg:city":"Andenne",
    "sg:orig_category":"Sportterreinen and installaties behalve sportcentra",
    "sg:phone":"+32 81 58 83 07",
    "sg:postcode":"5300",
    "sg:province":"Namur",
    "wof:name":"Benedicte Legros",
    "wof:placetype":"venue"
},
  "geometry": {"coordinates":[5.0067610741,50.4636459351],"type":"Point"}
}