{
  "type": "Feature",
  "properties": {
    "addr:full":"Hof Ter Bollen 46 Puurs Antwerpen 2870",
    "addr:housenumber":"46",
    "addr:postcode":"2870",
    "addr:street":"Hof Ter Bollen",
    "iso:country":"BE",
    "sg:address":"Hof Ter Bollen 46",
    "sg:city":"Puurs",
    "sg:orig_category":"Jardinage",
    "sg:phone":"+32 3 889 10 34",
    "sg:postcode":"2870",
    "sg:province":"Antwerpen",
    "wof:name":"Aquaplanning",
    "wof:placetype":"venue"
},
  "geometry": {"coordinates":[4.2787809372,51.044921875],"type":"Point"}
}