{
  "type": "Feature",
  "properties": {
    "iso:country":"BE",
    "sg:address":"Eeuwfeestlaan",
    "sg:city":"Lier",
    "sg:classifiers":[
        {
            "category":"Fast Food",
            "type":"Food & Drink"
        }
    ],
    "sg:phone":"+32 3 480 83 39",
    "sg:postcode":"2500",
    "sg:province":"Antwerpen",
    "sg:tags":[
        "fried",
        "stand",
        "potato"
    ],
    "wof:name":"Sporthal",
    "wof:placetype":"venue"
},
  "geometry": {"coordinates":[4.5697951317,51.139289856],"type":"Point"}
}