{
  "type": "Feature",
  "properties": {
    "addr:full":"Ijsbroekstraat 7 Geraardsbergen Oost-Vlaanderen 9506",
    "addr:housenumber":"7",
    "addr:postcode":"9506",
    "addr:street":"Ijsbroekstraat",
    "iso:country":"BE",
    "sg:address":"Ijsbroekstraat 7",
    "sg:city":"Geraardsbergen",
    "sg:orig_category":"Epiceries. Journaux",
    "sg:phone":"+32 54 41 13 27",
    "sg:postcode":"9506",
    "sg:province":"Oost-Vlaanderen",
    "wof:name":"Lutgarde De Lens",
    "wof:placetype":"venue"
},
  "geometry": {"coordinates":[3.8985300064,50.7987060547],"type":"Point"}
}