{
  "type": "Feature",
  "properties": {
    "addr:full":"Boulevard Piercot 4b91 Li\u00c8ge Li\u00e8ge 4000",
    "addr:housenumber":"4b91",
    "addr:postcode":"4000",
    "addr:street":"Boulevard Piercot",
    "iso:country":"BE",
    "sg:address":"Boulevard Piercot 4b91",
    "sg:city":"Li\u00c8ge",
    "sg:classifiers":[
        {
            "category":"Cafe",
            "type":"Food & Drink"
        }
    ],
    "sg:phone":"+32 4 222 48 03",
    "sg:postcode":"4000",
    "sg:province":"Li\u00e8ge",
    "sg:tags":[
        "caf\u00e9s"
    ],
    "wof:name":"Robert Viatour",
    "wof:placetype":"venue"
},
  "geometry": {"coordinates":[5.5724978447,50.636264801],"type":"Point"}
}