{
  "type": "Feature",
  "properties": {
    "iso:country":"BE",
    "sg:address":"Havikstraat 52",
    "sg:city":"Berlaar",
    "sg:orig_category":"Woningbouw",
    "sg:phone":"+32 3 422 58 87",
    "sg:postcode":"2590",
    "sg:province":"Antwerpen",
    "wof:name":"Maurits Voet",
    "wof:placetype":"venue"
},
  "geometry": {"coordinates":[4.6490321159,51.1097068787],"type":"Point"}
}