{
  "type": "Feature",
  "properties": {
    "iso:country":"BE",
    "sg:address":"Glabbeeksesteenweg 4bb",
    "sg:city":"Tielt-winge",
    "sg:orig_category":"Artsen and specialisten",
    "sg:phone":"+32 16 63 56 04",
    "sg:postcode":"3390",
    "sg:province":"Vlaams-Brabant",
    "wof:name":"Kind & Gezin",
    "wof:placetype":"venue"
},
  "geometry": {"coordinates":[4.884267807,50.9081382751],"type":"Point"}
}