{
  "type": "Feature",
  "properties": {
    "iso:country":"BE",
    "sg:address":"Jan Bijlstraat 18",
    "sg:city":"Aalst",
    "sg:classifiers":[
        {
            "category":"Building & Trades",
            "subcategory":"Cleaning & Sanitation",
            "type":"Services"
        }
    ],
    "sg:phone":"+32 53 21 55 55",
    "sg:postcode":"9300",
    "sg:province":"Oost-Vlaanderen",
    "sg:tags":[
        "janitor"
    ],
    "wof:name":"All Clean Bvba",
    "wof:placetype":"venue"
},
  "geometry": {"coordinates":[4.045730114,50.9478149414],"type":"Point"}
}