{
  "type": "Feature",
  "properties": {
    "addr:full":"Bresserdijk 25 Mol Antwerpen 2400",
    "addr:housenumber":"25",
    "addr:postcode":"2400",
    "addr:street":"Bresserdijk",
    "iso:country":"BE",
    "sg:address":"Bresserdijk 25",
    "sg:city":"Mol",
    "sg:classifiers":[
        {
            "category":"Cafe",
            "type":"Food & Drink"
        }
    ],
    "sg:phone":"+32 14 32 17 80",
    "sg:postcode":"2400",
    "sg:province":"Antwerpen",
    "sg:tags":[
        "caf\u00e9s"
    ],
    "wof:name":"Moldernete Kv",
    "wof:placetype":"venue"
},
  "geometry": {"coordinates":[5.1245532036,51.189781189],"type":"Point"}
}