{
  "type": "Feature",
  "properties": {
    "addr:full":"Chauss\u00e9e Du Roi Baudouin 188 Mons (saint-symphorien) Hainaut 7030",
    "addr:housenumber":"188",
    "addr:postcode":"7030",
    "addr:street":"Chausse\u0301E Du Roi Baudouin",
    "iso:country":"BE",
    "sg:address":"Chauss\u00e9e Du Roi Baudouin 188",
    "sg:city":"Mons (saint-symphorien)",
    "sg:classifiers":[
        {
            "category":"Professional",
            "subcategory":"Testing Lab",
            "type":"Services"
        }
    ],
    "sg:phone":"+32 65 35 25 39",
    "sg:postcode":"7030",
    "sg:province":"Hainaut",
    "sg:tags":[
        "chemist"
    ],
    "wof:name":"Quatre Pav\u00e9s (des)",
    "wof:placetype":"venue"
},
  "geometry": {"coordinates":[4.0108299255,50.4393882751],"type":"Point"}
}