{
  "type": "Feature",
  "properties": {
    "iso:country":"BE",
    "sg:address":"Rue Walth\u00e8re-dew\u00e9 1-b",
    "sg:city":"Li\u00e8ge 1",
    "sg:classifiers":[
        {
            "category":"Cafe",
            "type":"Food & Drink"
        }
    ],
    "sg:phone":"+32 4 227 94 66",
    "sg:postcode":"4000",
    "sg:province":"Li\u00e8ge",
    "sg:tags":[
        "snack-bars"
    ],
    "wof:name":"Gargotte (la)",
    "wof:placetype":"venue"
},
  "geometry": {"coordinates":[5.5953359604,50.6623687744],"type":"Point"}
}