{
  "type": "Feature",
  "properties": {
    "addr:full":"Av Major Bovy 1 Battice Li\u00e8ge 4651",
    "addr:housenumber":"1",
    "addr:postcode":"4651",
    "addr:street":"Av Major Bovy",
    "iso:country":"BE",
    "sg:address":"Av Major Bovy 1",
    "sg:city":"Battice",
    "sg:classifiers":[
        {
            "category":"Banks & Credit Unions",
            "subcategory":"Investment Brokerage",
            "type":"Services"
        }
    ],
    "sg:phone":"+32 50 55 73 00",
    "sg:postcode":"4651",
    "sg:province":"Li\u00e8ge",
    "sg:tags":[
        "-",
        "transport",
        "related"
    ],
    "wof:name":"Sea Park Nv",
    "wof:placetype":"venue"
},
  "geometry": {"coordinates":[3.2365760803,51.3160552979],"type":"Point"}
}