{
  "type": "Feature",
  "properties": {
    "addr:full":"Jan Breydelstraat 15 Izegem West-Vlaanderen 8870",
    "addr:housenumber":"15",
    "addr:postcode":"8870",
    "addr:street":"Jan Breydelstraat",
    "iso:country":"BE",
    "sg:address":"Jan Breydelstraat 15",
    "sg:city":"Izegem",
    "sg:orig_category":"Huisdieren and benodigdheden Royal Canin",
    "sg:phone":"+32 51 31 74 36",
    "sg:postcode":"8870",
    "sg:province":"West-Vlaanderen",
    "wof:name":"Demaegdt",
    "wof:placetype":"venue"
},
  "geometry": {"coordinates":[3.1955590248,50.899646759],"type":"Point"}
}