{
  "type": "Feature",
  "properties": {
    "iso:country":"BE",
    "sg:address":"Rue Des Comtes De Salm 24",
    "sg:city":"Vielsalm",
    "sg:classifiers":[
        {
            "category":"Food & Beverages",
            "subcategory":"Groceries & Convenience Stores",
            "type":"Retail Goods"
        }
    ],
    "sg:phone":"+32 80 21 65 00",
    "sg:postcode":"6690",
    "sg:province":"Luxembourg",
    "sg:tags":[
        "grocer"
    ],
    "wof:name":"Petit B\u00e9n\u00e9fice (le)",
    "wof:placetype":"venue"
},
  "geometry": {"coordinates":[5.889234066,50.2681083679],"type":"Point"}
}