{
  "type": "Feature",
  "properties": {
    "iso:country":"BE",
    "sg:address":"Rue Jean G\u00d4me 30",
    "sg:city":"Verviers",
    "sg:classifiers":[
        {
            "category":"Insurance",
            "subcategory":"Insurance Agent",
            "type":"Services"
        }
    ],
    "sg:phone":"+32 87 22 10 85",
    "sg:postcode":"4802",
    "sg:province":"Li\u00e8ge",
    "sg:tags":[
        "verzekeringsmakelaars",
        "expert"
    ],
    "wof:name":"F. Bonjean",
    "wof:placetype":"venue"
},
  "geometry": {"coordinates":[5.8621411324,50.5733566284],"type":"Point"}
}