{
  "type": "Feature",
  "properties": {
    "iso:country":"BE",
    "sg:address":"Espace Sud-route De Phillippeville",
    "sg:city":"Charleroi",
    "sg:orig_category":"Radioproductie and uitzendingen Televisieproductie and uitzendingen",
    "sg:phone":"+32 71 47 37 37",
    "sg:postcode":"6010",
    "sg:province":"Hainaut",
    "wof:name":"T\u00c9l\u00c9sambre",
    "wof:placetype":"venue"
},
  "geometry": {"coordinates":[4.4660949707,50.378993988],"type":"Point"}
}