{
  "type": "Feature",
  "properties": {
    "iso:country":"BE",
    "sg:address":"Prins Boudewijnlaan 146",
    "sg:city":"Edegem",
    "sg:orig_category":"Erotische Etablissementen",
    "sg:phone":"+32 3 458 47 60",
    "sg:postcode":"2650",
    "sg:province":"Antwerpen",
    "wof:name":"Biazaar",
    "wof:placetype":"venue"
},
  "geometry": {"coordinates":[4.4351630211,51.1477432251],"type":"Point"}
}