{
  "type": "Feature",
  "properties": {
    "iso:country":"BE",
    "sg:address":"Rue Sabatier 17",
    "sg:city":"Charleroi",
    "sg:orig_category":"Electrom\u00e9nager, t\u00e9l\u00e9visions and radios. Eclairage et \u00e9quipements du foyer. Fournitures de bureau. Lo",
    "sg:phone":"+32 71 47 01 82",
    "sg:postcode":"6001",
    "sg:province":"Hainaut",
    "wof:name":"Omega Productions",
    "wof:placetype":"venue"
},
  "geometry": {"coordinates":[4.4297618866,50.4016151428],"type":"Point"}
}