{
  "type": "Feature",
  "properties": {
    "addr:full":"Processieweg 46 Tienen Vlaams-Brabant 3300",
    "addr:housenumber":"46",
    "addr:postcode":"3300",
    "addr:street":"Processieweg",
    "iso:country":"BE",
    "sg:address":"Processieweg 46",
    "sg:city":"Tienen",
    "sg:orig_category":"Brood, gebak and snoepgoed",
    "sg:phone":"+32 16 78 00 64",
    "sg:postcode":"3300",
    "sg:province":"Vlaams-Brabant",
    "wof:name":"Ben Dewaelheyns",
    "wof:placetype":"venue"
},
  "geometry": {"coordinates":[4.930077076,50.8096694946],"type":"Point"}
}