{
  "type": "Feature",
  "properties": {
    "addr:full":"Avenue De Fontenelle 0 Fleurus Hainaut 6220",
    "addr:housenumber":"0",
    "addr:postcode":"6220",
    "addr:street":"Avenue De Fontenelle",
    "iso:country":"BE",
    "sg:address":"Avenue De Fontenelle 0",
    "sg:city":"Fleurus",
    "sg:orig_category":"Mat\u00e9riaux de construction Gr",
    "sg:phone":"+32 71 81 80 71",
    "sg:postcode":"6220",
    "sg:province":"Hainaut",
    "wof:name":"Agence Verbockhaven",
    "wof:placetype":"venue"
},
  "geometry": {"coordinates":[4.5305008888,50.4551200867],"type":"Point"}
}