{
  "type": "Feature",
  "properties": {
    "addr:full":"Rue Du Pouly 76bb Philippeville Namur 5600",
    "addr:housenumber":"76bb",
    "addr:postcode":"5600",
    "addr:street":"Rue Du Pouly",
    "iso:country":"BE",
    "sg:address":"Rue Du Pouly 76bb",
    "sg:city":"Philippeville",
    "sg:orig_category":"Drukkerijen and copyshops",
    "sg:phone":"+32 71 66 61 79",
    "sg:postcode":"5600",
    "sg:province":"Namur",
    "wof:name":"Bureau Vanber",
    "wof:placetype":"venue"
},
  "geometry": {"coordinates":[4.5290441513,50.2162666321],"type":"Point"}
}