{
  "type": "Feature",
  "properties": {
    "addr:full":"Rue Waressaix 21 Morlanwelz Hainaut 7141",
    "addr:housenumber":"21",
    "addr:postcode":"7141",
    "addr:street":"Rue Waressaix",
    "iso:country":"BE",
    "sg:address":"Rue Waressaix 21",
    "sg:city":"Morlanwelz",
    "sg:classifiers":[
        {
            "category":"Personal",
            "subcategory":"Beauty Salon",
            "type":"Services"
        }
    ],
    "sg:phone":"+32 64 44 20 51",
    "sg:postcode":"7141",
    "sg:province":"Hainaut",
    "sg:tags":[
        "de",
        "coiffure"
    ],
    "wof:name":"Michele Thermolle",
    "wof:placetype":"venue"
},
  "geometry": {"coordinates":[4.2556791306,50.4438362122],"type":"Point"}
}