{
  "type": "Feature",
  "properties": {
    "iso:country":"BE",
    "sg:address":"Elzestraat 16",
    "sg:city":"Beveren",
    "sg:orig_category":"Tuinen",
    "sg:phone":"+32 3 775 44 17",
    "sg:postcode":"9120",
    "sg:province":"Oost-Vlaanderen",
    "wof:name":"Alcea",
    "wof:placetype":"venue"
},
  "geometry": {"coordinates":[4.231025219,51.2180404663],"type":"Point"}
}