{
  "type": "Feature",
  "properties": {
    "addr:full":"Vleugtstraat 40 Diest Vlaams-Brabant 3290",
    "addr:housenumber":"40",
    "addr:postcode":"3290",
    "addr:street":"Vleugtstraat",
    "iso:country":"BE",
    "sg:address":"Vleugtstraat 40",
    "sg:city":"Diest",
    "sg:orig_category":"Plaatsen van vloer- and muurbekleding",
    "sg:phone":"+32 13 33 68 25",
    "sg:postcode":"3290",
    "sg:province":"Vlaams-Brabant",
    "wof:name":"Fran\u00c7ois Geerinckx",
    "wof:placetype":"venue"
},
  "geometry": {"coordinates":[5.1142029762,51.0192146301],"type":"Point"}
}