{
  "type": "Feature",
  "properties": {
    "addr:full":"Bosdreef 37 Houthulst West-Vlaanderen 8650",
    "addr:housenumber":"37",
    "addr:postcode":"8650",
    "addr:street":"Bosdreef",
    "iso:country":"BE",
    "sg:address":"Bosdreef 37",
    "sg:city":"Houthulst",
    "sg:orig_category":"Bouwmaterialen Gh Woningbouw",
    "sg:phone":"+32 51 54 58 23",
    "sg:postcode":"8650",
    "sg:province":"West-Vlaanderen",
    "wof:name":"Perfectiebouw",
    "wof:placetype":"venue"
},
  "geometry": {"coordinates":[2.9098529816,50.9653511047],"type":"Point"}
}