{
  "type": "Feature",
  "properties": {
    "addr:full":"Hellestraat 68 Ninove Oost-Vlaanderen 9400",
    "addr:housenumber":"68",
    "addr:postcode":"9400",
    "addr:street":"Hellestraat",
    "iso:country":"BE",
    "sg:address":"Hellestraat 68",
    "sg:city":"Ninove",
    "sg:classifiers":[
        {
            "category":"Insurance",
            "subcategory":"Life Insurance",
            "type":"Services"
        }
    ],
    "sg:phone":"+32 54 32 57 75",
    "sg:postcode":"9400",
    "sg:province":"Oost-Vlaanderen",
    "sg:tags":[
        "assurance"
    ],
    "wof:name":"Denderassur",
    "wof:placetype":"venue"
},
  "geometry": {"coordinates":[4.0232000351,50.8349113464],"type":"Point"}
}