{
  "type": "Feature",
  "properties": {
    "iso:country":"BE",
    "sg:address":"Stationsstraat 33",
    "sg:city":"Niel",
    "sg:classifiers":[
        {
            "category":"Building & Trades",
            "subcategory":"Landscaping Services",
            "type":"Services"
        }
    ],
    "sg:phone":"+32 3 888 62 97",
    "sg:postcode":"2845",
    "sg:province":"Antwerpen",
    "sg:tags":[
        "gardening",
        "garden",
        "maintenance"
    ],
    "wof:name":"A.h.d. Bvba",
    "wof:placetype":"venue"
},
  "geometry": {"coordinates":[4.3328380585,51.1124305725],"type":"Point"}
}