{
  "type": "Feature",
  "properties": {
    "iso:country":"BE",
    "sg:address":"Passage Des D\u00c9port\u00c9s 2",
    "sg:city":"Gembloux",
    "sg:orig_category":"Evaluation and estimation de biens immobiliers",
    "sg:phone":"+32 81 62 21 76",
    "sg:postcode":"5030",
    "sg:province":"Namur",
    "wof:name":"Pierre Dehon",
    "wof:placetype":"venue"
},
  "geometry": {"coordinates":[4.6966547966,50.5615730286],"type":"Point"}
}