{
  "type": "Feature",
  "properties": {
    "addr:full":"Rue De La Gare 55 Bertrix Luxembourg 6880",
    "addr:housenumber":"55",
    "addr:postcode":"6880",
    "addr:street":"Rue De La Gare",
    "iso:country":"BE",
    "sg:address":"Rue De La Gare 55",
    "sg:city":"Bertrix",
    "sg:classifiers":[
        {
            "category":"Bars & Pubs",
            "type":"Food & Drink"
        }
    ],
    "sg:phone":"+32 61 41 28 78",
    "sg:postcode":"6880",
    "sg:province":"Luxembourg",
    "wof:name":"Bertry (le)",
    "wof:placetype":"venue"
},
  "geometry": {"coordinates":[5.2620439529,49.8565864563],"type":"Point"}
}