{
  "type": "Feature",
  "properties": {
    "iso:country":"BE",
    "sg:address":"Tereken 96bb/6",
    "sg:city":"Sint-niklaas",
    "sg:classifiers":[
        {
            "category":"Personal",
            "subcategory":"Beauty Salon",
            "type":"Services"
        }
    ],
    "sg:phone":"+32 3 777 68 63",
    "sg:postcode":"9100",
    "sg:province":"Oost-Vlaanderen",
    "sg:tags":[
        "de",
        "coiffure"
    ],
    "wof:name":"Gino De Bruyne",
    "wof:placetype":"venue"
},
  "geometry": {"coordinates":[4.1485671997,51.1518821716],"type":"Point"}
}