{
  "type": "Feature",
  "properties": {
    "addr:full":"Place Du Monument 25 Spa Li\u00e8ge 4900",
    "addr:housenumber":"25",
    "addr:postcode":"4900",
    "addr:street":"Place Du Monument",
    "iso:country":"BE",
    "sg:address":"Place Du Monument 25",
    "sg:city":"Spa",
    "sg:orig_category":"Apotheken",
    "sg:phone":"+32 87 77 13 80",
    "sg:postcode":"4900",
    "sg:province":"Li\u00e8ge",
    "wof:name":"Pharmacie Populaire",
    "wof:placetype":"venue"
},
  "geometry": {"coordinates":[5.8631510735,50.4920539856],"type":"Point"}
}