{
  "type": "Feature",
  "properties": {
    "iso:country":"BE",
    "sg:address":"Rue Jules Adant 12",
    "sg:city":"Kraainem",
    "sg:classifiers":[
        {
            "category":"Building & Trades",
            "subcategory":"Pest Control",
            "type":"Services"
        }
    ],
    "sg:phone":"+32 2 782 12 24",
    "sg:postcode":"1950",
    "sg:province":"Vlaams-Brabant",
    "sg:tags":[
        "painting",
        "contractor"
    ],
    "wof:name":"Francois Claude",
    "wof:placetype":"venue"
},
  "geometry": {"coordinates":[4.4673600197,50.8487586975],"type":"Point"}
}