{
  "type": "Feature",
  "properties": {
    "iso:country":"BE",
    "sg:address":"Rue De La Victoire 11",
    "sg:city":"Thuin (thuillies)",
    "sg:classifiers":[
        {
            "category":"Health Services",
            "subcategory":"Health Practitioner",
            "type":"Services"
        }
    ],
    "sg:phone":"+32 71 53 50 23",
    "sg:postcode":"6536",
    "sg:province":"Hainaut",
    "sg:tags":[
        "physiotherapist"
    ],
    "wof:name":"Hardy Annick",
    "wof:placetype":"venue"
},
  "geometry": {"coordinates":[4.3290910721,50.2941627502],"type":"Point"}
}