{
  "type": "Feature",
  "properties": {
    "addr:full":"Bilzersteenweg 39 Riemst Limburg 3770",
    "addr:housenumber":"39",
    "addr:postcode":"3770",
    "addr:street":"Bilzersteenweg",
    "iso:country":"BE",
    "sg:address":"Bilzersteenweg 39",
    "sg:city":"Riemst",
    "sg:classifiers":[
        {
            "category":"Personal",
            "subcategory":"Beauty Salon",
            "type":"Services"
        }
    ],
    "sg:phone":"+32 12 45 31 70",
    "sg:postcode":"3770",
    "sg:province":"Limburg",
    "sg:tags":[
        "lady",
        "-",
        "hairdressing"
    ],
    "wof:name":"The Principals",
    "wof:placetype":"venue"
},
  "geometry": {"coordinates":[5.5922398567,50.815536499],"type":"Point"}
}