{
  "type": "Feature",
  "properties": {
    "iso:country":"BE",
    "sg:address":"Jagerslaan 28",
    "sg:city":"Kampenhout",
    "sg:orig_category":"Editeurs de livres",
    "sg:phone":"+32 16 65 12 72",
    "sg:postcode":"1910",
    "sg:province":"Vlaams-Brabant",
    "wof:name":"Antonio Antioco",
    "wof:placetype":"venue"
},
  "geometry": {"coordinates":[4.5621137619,50.9309196472],"type":"Point"}
}