{
  "type": "Feature",
  "properties": {
    "addr:full":"Avenue Du Vossegat 10 Box 7 Bruxelles (uccle) Bruxelles-Capitale 1180",
    "addr:housenumber":"10;7",
    "addr:postcode":"1180",
    "addr:street":"Avenue Du Vossegat;Box",
    "iso:country":"BE",
    "sg:address":"Avenue Du Vossegat 10 Box 7",
    "sg:city":"Bruxelles (uccle)",
    "sg:classifiers":[
        {
            "category":"Professional",
            "type":"Services"
        }
    ],
    "sg:phone":"+32 2 376 27 39",
    "sg:postcode":"1180",
    "sg:province":"Bruxelles-Capitale",
    "sg:tags":[
        "writer"
    ],
    "wof:name":"Compere G",
    "wof:placetype":"venue"
},
  "geometry": {"coordinates":[4.3305177689,50.8023834229],"type":"Point"}
}