{
  "type": "Feature",
  "properties": {
    "addr:full":"Rue De Lavaux 7 Musson Luxembourg 6750",
    "addr:housenumber":"7",
    "addr:postcode":"6750",
    "addr:street":"Rue De Lavaux",
    "iso:country":"BE",
    "sg:address":"Rue De Lavaux 7",
    "sg:city":"Musson",
    "sg:orig_category":"Sportclubs Sportterreinen and installaties behalve sportcentra",
    "sg:phone":"+32 63 67 89 17",
    "sg:postcode":"6750",
    "sg:province":"Luxembourg",
    "wof:name":"S.c. Mussy",
    "wof:placetype":"venue"
},
  "geometry": {"coordinates":[5.6625638008,49.573348999],"type":"Point"}
}