{
  "type": "Feature",
  "properties": {
    "addr:full":"Schrovestraat 41 Lebbeke (wieze) Oost-Vlaanderen 9280",
    "addr:housenumber":"41",
    "addr:postcode":"9280",
    "addr:street":"Schrovestraat",
    "iso:country":"BE",
    "sg:address":"Schrovestraat 41",
    "sg:city":"Lebbeke (wieze)",
    "sg:classifiers":[
        {
            "category":"Bars & Pubs",
            "type":"Food & Drink"
        }
    ],
    "sg:phone":"+32 53 78 15 94",
    "sg:postcode":"9280",
    "sg:province":"Oost-Vlaanderen",
    "wof:name":"De Voermanstrust",
    "wof:placetype":"venue"
},
  "geometry": {"coordinates":[4.0783891678,50.976940155],"type":"Point"}
}