{
  "type": "Feature",
  "properties": {
    "addr:full":"Kerkstraat 80 Kaprijke Oost-Vlaanderen 9971",
    "addr:housenumber":"80",
    "addr:postcode":"9971",
    "addr:street":"Kerkstraat",
    "iso:country":"BE",
    "sg:address":"Kerkstraat 80",
    "sg:city":"Kaprijke",
    "sg:orig_category":"Woningbouw",
    "sg:phone":"+32 9 377 41 29",
    "sg:postcode":"9971",
    "sg:province":"Oost-Vlaanderen",
    "wof:name":"Spiessens",
    "wof:placetype":"venue"
},
  "geometry": {"coordinates":[3.6430079937,51.2028999329],"type":"Point"}
}