{
  "type": "Feature",
  "properties": {
    "addr:full":"Rue L\u00e9opold 2 Beyne-heusay Li\u00e8ge 4610",
    "addr:housenumber":"2",
    "addr:postcode":"4610",
    "addr:street":"Rue Le\u0301Opold",
    "iso:country":"BE",
    "sg:address":"Rue L\u00e9opold 2",
    "sg:city":"Beyne-heusay",
    "sg:classifiers":[
        {
            "category":"Home & Garden",
            "subcategory":"Kitchen Supply",
            "type":"Retail Goods"
        }
    ],
    "sg:phone":"+32 4 358 04 50",
    "sg:postcode":"4610",
    "sg:province":"Li\u00e8ge",
    "sg:tags":[
        "installation"
    ],
    "wof:name":"Isabelle & Daniel Sprl",
    "wof:placetype":"venue"
},
  "geometry": {"coordinates":[5.6558527946,50.6213493347],"type":"Point"}
}