{
  "type": "Feature",
  "properties": {
    "iso:country":"BE",
    "sg:address":"Vilvoordelaan 42",
    "sg:city":"Zaventem",
    "sg:classifiers":[
        {
            "category":"Fast Food",
            "type":"Food & Drink"
        }
    ],
    "sg:phone":"+32 2 720 01 08",
    "sg:postcode":"1930",
    "sg:province":"Vlaams-Brabant",
    "sg:tags":[
        "meeneem",
        "restaurant"
    ],
    "wof:name":"Restaurant Da Lino",
    "wof:placetype":"venue"
},
  "geometry": {"coordinates":[4.4710230827,50.8870124817],"type":"Point"}
}