{
  "type": "Feature",
  "properties": {
    "iso:country":"BE",
    "sg:address":"Prinsendreef 6 Box 10",
    "sg:city":"Kapellen (mariaburg)",
    "sg:classifiers":[
        {
            "category":"Professional",
            "subcategory":"Management & Consulting",
            "type":"Services"
        }
    ],
    "sg:phone":"+32 3 605 42 89",
    "sg:postcode":"2950",
    "sg:province":"Antwerpen",
    "sg:tags":[
        "consultant"
    ],
    "wof:name":"Donald Pans Bvba",
    "wof:placetype":"venue"
},
  "geometry": {"coordinates":[4.4386591911,51.3154411316],"type":"Point"}
}