{
  "type": "Feature",
  "properties": {
    "addr:full":"Ichtegemstraat 36b Koekelare West-Vlaanderen 8680",
    "addr:housenumber":"36b",
    "addr:postcode":"8680",
    "addr:street":"Ichtegemstraat",
    "iso:country":"BE",
    "sg:address":"Ichtegemstraat 36b",
    "sg:city":"Koekelare",
    "sg:classifiers":[
        {
            "category":"Building & Trades",
            "subcategory":"Pest Control",
            "type":"Services"
        }
    ],
    "sg:phone":"+32 51 58 45 77",
    "sg:postcode":"8680",
    "sg:province":"West-Vlaanderen",
    "sg:tags":[
        "painting",
        "contractor"
    ],
    "wof:name":"Van Hulle-devisscher Bvba",
    "wof:placetype":"venue"
},
  "geometry": {"coordinates":[2.9830400944,51.0900192261],"type":"Point"}
}