{
  "type": "Feature",
  "properties": {
    "addr:full":"Ruelle Des Messes 12 Modave Li\u00e8ge 4577",
    "addr:housenumber":"12",
    "addr:postcode":"4577",
    "addr:street":"Ruelle Des Messes",
    "iso:country":"BE",
    "sg:address":"Ruelle Des Messes 12",
    "sg:city":"Modave",
    "sg:orig_category":"Apotheken",
    "sg:phone":"+32 85 41 12 34",
    "sg:postcode":"4577",
    "sg:province":"Li\u00e8ge",
    "wof:name":"A. Billen",
    "wof:placetype":"venue"
},
  "geometry": {"coordinates":[5.2960748672,50.4819602966],"type":"Point"}
}