{
  "type": "Feature",
  "properties": {
    "iso:country":"BE",
    "sg:address":"Houtbriel 24",
    "sg:city":"Sint-niklaas",
    "sg:classifiers":[
        {
            "category":"Bars & Pubs",
            "type":"Food & Drink"
        }
    ],
    "sg:phone":"+32 3 777 19 29",
    "sg:postcode":"9100",
    "sg:province":"Oost-Vlaanderen",
    "sg:tags":[
        "tavern"
    ],
    "wof:name":"Irish Inn Bvba",
    "wof:placetype":"venue"
},
  "geometry": {"coordinates":[4.142829895,51.1648788452],"type":"Point"}
}