{
  "type": "Feature",
  "properties": {
    "addr:full":"Ambachtschoolstraat 43 Hasselt Limburg 3500",
    "addr:housenumber":"43",
    "addr:postcode":"3500",
    "addr:street":"Ambachtschoolstraat",
    "iso:country":"BE",
    "sg:address":"Ambachtschoolstraat 43",
    "sg:city":"Hasselt",
    "sg:orig_category":"Etalage- and showroomontwerpers",
    "sg:phone":"+32 11 87 22 60",
    "sg:postcode":"3500",
    "sg:province":"Limburg",
    "wof:name":"Philippe Landuyt",
    "wof:placetype":"venue"
},
  "geometry": {"coordinates":[5.3205728531,50.9344100952],"type":"Point"}
}