{
  "type": "Feature",
  "properties": {
    "iso:country":"BE",
    "sg:address":"Rinkhout 160b1",
    "sg:city":"Zele",
    "sg:orig_category":"Rundveehouders",
    "sg:phone":"+32 52 44 55 76",
    "sg:postcode":"9240",
    "sg:province":"Oost-Vlaanderen",
    "wof:name":"Remigius Van Damme",
    "wof:placetype":"venue"
},
  "geometry": {"coordinates":[4.0584278107,51.0700073242],"type":"Point"}
}