{
  "type": "Feature",
  "properties": {
    "iso:country":"BE",
    "sg:address":"Fontaines 154",
    "sg:city":"Engis (clermont-sous-huy)",
    "sg:classifiers":[
        {
            "category":"Building & Trades",
            "subcategory":"Landscaping Services",
            "type":"Services"
        }
    ],
    "sg:phone":"+32 4 275 44 26",
    "sg:postcode":"4480",
    "sg:province":"Li\u00e8ge",
    "sg:tags":[
        "gardening",
        "garden",
        "maintenance"
    ],
    "wof:name":"Przebienda C",
    "wof:placetype":"venue"
},
  "geometry": {"coordinates":[5.3791890144,50.5524597168],"type":"Point"}
}