{
  "type": "Feature",
  "properties": {
    "addr:full":"B. Van Dammestraat 9 Blankenberge (uitkerke) West-Vlaanderen 8370",
    "addr:housenumber":"9",
    "addr:postcode":"8370",
    "addr:street":"B. Van Dammestraat",
    "iso:country":"BE",
    "sg:address":"B. Van Dammestraat 9",
    "sg:city":"Blankenberge (uitkerke)",
    "sg:classifiers":[
        {
            "category":"Building & Trades",
            "subcategory":"Plumbing",
            "type":"Services"
        }
    ],
    "sg:phone":"+32 475 91 10 75",
    "sg:postcode":"8370",
    "sg:province":"West-Vlaanderen",
    "sg:tags":[
        "contractor"
    ],
    "wof:name":"Van De Cauter Robert",
    "wof:placetype":"venue"
},
  "geometry": {"coordinates":[3.1404349804,51.3053131104],"type":"Point"}
}