{
  "type": "Feature",
  "properties": {
    "iso:country":"BE",
    "sg:address":"Gelmelstraat 53",
    "sg:city":"Hoogstraten",
    "sg:classifiers":[
        {
            "category":"Cafe",
            "type":"Food & Drink"
        }
    ],
    "sg:phone":"+32 3 314 16 49",
    "sg:postcode":"2320",
    "sg:province":"Antwerpen",
    "sg:tags":[
        "snack-bars"
    ],
    "wof:name":"Bagetje ('t)",
    "wof:placetype":"venue"
},
  "geometry": {"coordinates":[4.765127182,51.4024085999],"type":"Point"}
}