{
  "type": "Feature",
  "properties": {
    "addr:full":"Rue Armand Enkart 38 Theux Li\u00e8ge 4910",
    "addr:housenumber":"38",
    "addr:postcode":"4910",
    "addr:street":"Rue Armand Enkart",
    "iso:country":"BE",
    "sg:address":"Rue Armand Enkart 38",
    "sg:city":"Theux",
    "sg:classifiers":[
        {
            "category":"Insurance",
            "subcategory":"Life Insurance",
            "type":"Services"
        }
    ],
    "sg:phone":"+32 87 29 33 80",
    "sg:postcode":"4910",
    "sg:province":"Li\u00e8ge",
    "sg:tags":[
        "assurance"
    ],
    "wof:name":"Phima",
    "wof:placetype":"venue"
},
  "geometry": {"coordinates":[5.8130488396,50.5356216431],"type":"Point"}
}