{
  "type": "Feature",
  "properties": {
    "addr:full":"Drijkoningenstraat 8 Nijlen Antwerpen 2560",
    "addr:housenumber":"8",
    "addr:postcode":"2560",
    "addr:street":"Drijkoningenstraat",
    "iso:country":"BE",
    "sg:address":"Drijkoningenstraat 8",
    "sg:city":"Nijlen",
    "sg:orig_category":"Boekhouders",
    "sg:phone":"+32 3 481 96 63",
    "sg:postcode":"2560",
    "sg:province":"Antwerpen",
    "wof:name":"Bruno Verbraecken",
    "wof:placetype":"venue"
},
  "geometry": {"coordinates":[4.6898770332,51.1718444824],"type":"Point"}
}