{
  "type": "Feature",
  "properties": {
    "iso:country":"BE",
    "sg:address":"Maagdhoek 24",
    "sg:city":"Diksmuide",
    "sg:orig_category":"Non-Classified Establishments",
    "sg:phone":"+32 51 50 02 09",
    "sg:postcode":"8600",
    "sg:province":"West-Vlaanderen",
    "wof:name":"Devisscher F",
    "wof:placetype":"venue"
},
  "geometry": {"coordinates":[2.904337883,51.026058197],"type":"Point"}
}