{
  "type": "Feature",
  "properties": {
    "addr:full":"Haeckstraat 31 Sint-jans-molenbeek/molenbeek-saint-jean Bruxelles-Capitale 1080",
    "addr:housenumber":"31",
    "addr:postcode":"1080",
    "addr:street":"Haeckstraat",
    "iso:country":"BE",
    "sg:address":"Haeckstraat 31",
    "sg:city":"Sint-jans-molenbeek/molenbeek-saint-jean",
    "sg:classifiers":[
        {
            "category":"Food & Beverages",
            "subcategory":"Fruits & Vegetables",
            "type":"Retail Goods"
        }
    ],
    "sg:phone":"+32 2 424 05 15",
    "sg:postcode":"1080",
    "sg:province":"Bruxelles-Capitale",
    "sg:tags":[
        "groenten"
    ],
    "wof:name":"Echo D'iran",
    "wof:placetype":"venue"
},
  "geometry": {"coordinates":[4.334335804,50.8638343811],"type":"Point"}
}