{
  "type": "Feature",
  "properties": {
    "addr:full":"Rue De La Source 68 Bruxelles (saint-gilles) Bruxelles-Capitale 1060",
    "addr:housenumber":"68",
    "addr:postcode":"1060",
    "addr:street":"Rue De La Source",
    "iso:country":"BE",
    "sg:address":"Rue De La Source 68",
    "sg:city":"Bruxelles (saint-gilles)",
    "sg:classifiers":[
        {
            "category":"Professional",
            "subcategory":"Lawyer & Legal Services",
            "type":"Services"
        }
    ],
    "sg:phone":"+32 2 538 36 20",
    "sg:postcode":"1060",
    "sg:province":"Bruxelles-Capitale",
    "wof:name":"Vanderbeck Gilles",
    "wof:placetype":"venue"
},
  "geometry": {"coordinates":[4.3535070419,50.8311538696],"type":"Point"}
}