{
  "type": "Feature",
  "properties": {
    "iso:country":"BE",
    "sg:address":"Ringlaan 39a",
    "sg:city":"Lummen",
    "sg:classifiers":[
        {
            "category":"Home & Garden",
            "subcategory":"Building Materials",
            "type":"Retail Goods"
        }
    ],
    "sg:phone":"+32 13 52 25 68",
    "sg:postcode":"3560",
    "sg:province":"Limburg",
    "sg:tags":[
        "article",
        "-",
        "do-it-yourself"
    ],
    "wof:name":"Doe-het-zelf",
    "wof:placetype":"venue"
},
  "geometry": {"coordinates":[5.1982002258,50.9867286682],"type":"Point"}
}