{
  "type": "Feature",
  "properties": {
    "iso:country":"BE",
    "sg:address":"Boomsesteenweg 325",
    "sg:city":"Antwerpen",
    "sg:classifiers":[
        {
            "category":"Fast Food",
            "type":"Food & Drink"
        }
    ],
    "sg:phone":"+32 3 216 19 50",
    "sg:postcode":"2020",
    "sg:province":"Antwerpen",
    "sg:tags":[
        "huis",
        "aan",
        "levering",
        "meeneem",
        "restaurant"
    ],
    "wof:name":"Pizza Service",
    "wof:placetype":"venue"
},
  "geometry": {"coordinates":[4.3882050514,51.1868095398],"type":"Point"}
}