{
  "type": "Feature",
  "properties": {
    "addr:full":"Brugseweg 342 Ieper West-Vlaanderen 8900",
    "addr:housenumber":"342",
    "addr:postcode":"8900",
    "addr:street":"Brugseweg",
    "iso:country":"BE",
    "sg:address":"Brugseweg 342",
    "sg:city":"Ieper",
    "sg:classifiers":[
        {
            "category":"Insurance",
            "subcategory":"Insurance Agent",
            "type":"Services"
        }
    ],
    "sg:phone":"+32 57 20 28 92",
    "sg:postcode":"8900",
    "sg:province":"West-Vlaanderen",
    "sg:tags":[
        "broker"
    ],
    "wof:name":"Petillion J",
    "wof:placetype":"venue"
},
  "geometry": {"coordinates":[2.896600008,50.8594894409],"type":"Point"}
}