{
  "type": "Feature",
  "properties": {
    "addr:full":"Maria-theresiastraat 20 Leuven Vlaams-Brabant 3000",
    "addr:housenumber":"20",
    "addr:postcode":"3000",
    "addr:street":"Maria-Theresiastraat",
    "iso:country":"BE",
    "sg:address":"Maria-theresiastraat 20",
    "sg:city":"Leuven",
    "sg:orig_category":"Editeurs de journaux. Editeurs de revues and p\u00e9riodiques",
    "sg:phone":"+32 16 31 66 00",
    "sg:postcode":"3000",
    "sg:province":"Vlaams-Brabant",
    "wof:name":"Centrum Lezen-informatie",
    "wof:placetype":"venue"
},
  "geometry": {"coordinates":[4.7100601196,50.876739502],"type":"Point"}
}