{
  "type": "Feature",
  "properties": {
    "addr:full":"Vijfde Liniestraat 16 Rotselaar Vlaams-Brabant 3110",
    "addr:housenumber":"16",
    "addr:postcode":"3110",
    "addr:street":"Vijfde Liniestraat",
    "iso:country":"BE",
    "sg:address":"Vijfde Liniestraat 16",
    "sg:city":"Rotselaar",
    "sg:orig_category":"Blanchisseries and teintureries",
    "sg:phone":"+32 16 44 55 81",
    "sg:postcode":"3110",
    "sg:province":"Vlaams-Brabant",
    "wof:name":"Wasserij Zilverwit",
    "wof:placetype":"venue"
},
  "geometry": {"coordinates":[4.7089791298,50.9499320984],"type":"Point"}
}