{
  "type": "Feature",
  "properties": {
    "addr:full":"Tabaksvest 51 Antwerpen Antwerpen 2000",
    "addr:housenumber":"51",
    "addr:postcode":"2000",
    "addr:street":"Tabaksvest",
    "iso:country":"BE",
    "sg:address":"Tabaksvest 51",
    "sg:city":"Antwerpen",
    "sg:classifiers":[
        {
            "category":"Professional",
            "subcategory":"Engineering",
            "type":"Services"
        }
    ],
    "sg:phone":"+32 3 233 85 25",
    "sg:postcode":"2000",
    "sg:province":"Antwerpen",
    "sg:tags":[
        "-"
    ],
    "wof:name":"Delta Engineers & Contractors",
    "wof:placetype":"venue"
},
  "geometry": {"coordinates":[4.410492897,51.2139358521],"type":"Point"}
}