{
  "type": "Feature",
  "properties": {
    "addr:full":"Broesveldstraat 7 Neerpelt Limburg 3910",
    "addr:housenumber":"7",
    "addr:postcode":"3910",
    "addr:street":"Broesveldstraat",
    "iso:country":"BE",
    "sg:address":"Broesveldstraat 7",
    "sg:city":"Neerpelt",
    "sg:orig_category":"S\u00e9curit\u00e9 sociale",
    "sg:phone":"+32 11 64 26 36",
    "sg:postcode":"3910",
    "sg:province":"Limburg",
    "wof:name":"De Voorzorg",
    "wof:placetype":"venue"
},
  "geometry": {"coordinates":[5.4297370911,51.2294425964],"type":"Point"}
}