{
  "type": "Feature",
  "properties": {
    "iso:country":"BE",
    "sg:address":"Kerkstraat 8",
    "sg:city":"Meulebeke",
    "sg:orig_category":"Rev\u00eatements pour sols and murs. Peinture",
    "sg:phone":"+32 51 74 77 12",
    "sg:postcode":"8760",
    "sg:province":"West-Vlaanderen",
    "wof:name":"Fa. Filez",
    "wof:placetype":"venue"
},
  "geometry": {"coordinates":[3.2874100208,50.9503173828],"type":"Point"}
}