{
  "type": "Feature",
  "properties": {
    "iso:country":"BE",
    "sg:address":"Weg Naar As 60a",
    "sg:city":"Genk",
    "sg:orig_category":"Biblioth\u00e8ques and archives publiques",
    "sg:phone":"+32 89 35 85 65",
    "sg:postcode":"3600",
    "sg:province":"Limburg",
    "wof:name":"De Regenboog",
    "wof:placetype":"venue"
},
  "geometry": {"coordinates":[5.5121388435,50.9677085876],"type":"Point"}
}