{
  "type": "Feature",
  "properties": {
    "addr:full":"Rue Des Meuniers 175 Herstal Li\u00e8ge 4041",
    "addr:housenumber":"175",
    "addr:postcode":"4041",
    "addr:street":"Rue Des Meuniers",
    "iso:country":"BE",
    "sg:address":"Rue Des Meuniers 175",
    "sg:city":"Herstal",
    "sg:orig_category":"Herstellingen and onderhoud van auto's",
    "sg:phone":"+32 4 248 90 62",
    "sg:postcode":"4041",
    "sg:province":"Li\u00e8ge",
    "wof:name":"L.n. Car",
    "wof:placetype":"venue"
},
  "geometry": {"coordinates":[5.6018090248,50.6714820862],"type":"Point"}
}