{
  "type": "Feature",
  "properties": {
    "iso:country":"BE",
    "sg:address":"Bouwmeestersstraat 28b",
    "sg:city":"Gent (sint-amandsberg)",
    "sg:classifiers":[
        {
            "category":"Professional",
            "subcategory":"Art Services",
            "type":"Services"
        }
    ],
    "sg:phone":"+32 9 238 37 91",
    "sg:postcode":"9040",
    "sg:province":"Oost-Vlaanderen",
    "sg:tags":[
        "photographer"
    ],
    "wof:name":"Suykens G",
    "wof:placetype":"venue"
},
  "geometry": {"coordinates":[3.7480010986,51.0503692627],"type":"Point"}
}