{
  "type": "Feature",
  "properties": {
    "addr:full":"Mechelsesteenweg 147 Herent Vlaams-Brabant 3020",
    "addr:housenumber":"147",
    "addr:postcode":"3020",
    "addr:street":"Mechelsesteenweg",
    "iso:country":"BE",
    "sg:address":"Mechelsesteenweg 147",
    "sg:city":"Herent",
    "sg:classifiers":[
        {
            "category":"Health Services",
            "subcategory":"Nursing And Care Facility",
            "type":"Services"
        }
    ],
    "sg:phone":"+32 89 30 05 50",
    "sg:postcode":"3020",
    "sg:province":"Vlaams-Brabant",
    "sg:tags":[
        "home"
    ],
    "wof:name":"Wit-gele Kruis Vlaams-brabant",
    "wof:placetype":"venue"
},
  "geometry": {"coordinates":[4.6834101677,50.8977012634],"type":"Point"}
}