{
  "type": "Feature",
  "properties": {
    "iso:country":"BE",
    "sg:address":"Jan Broeckaertlaan 16",
    "sg:city":"Wetteren",
    "sg:orig_category":"Installation \u00e9lectrique r\u00e9sidentielle",
    "sg:phone":"+32 9 366 43 29",
    "sg:postcode":"9230",
    "sg:province":"Oost-Vlaanderen",
    "wof:name":"Philip Van De Abeele",
    "wof:placetype":"venue"
},
  "geometry": {"coordinates":[3.8857800961,51.0024414062],"type":"Point"}
}