{
  "type": "Feature",
  "properties": {
    "iso:country":"BE",
    "sg:address":"Canadalaan 63",
    "sg:city":"Zonnebeke",
    "sg:orig_category":"Eleveurs de bovins",
    "sg:phone":"+32 51 77 85 90",
    "sg:postcode":"8980",
    "sg:province":"West-Vlaanderen",
    "wof:name":"Werner Lemaire",
    "wof:placetype":"venue"
},
  "geometry": {"coordinates":[2.9992609024,50.8931007385],"type":"Point"}
}