{
  "type": "Feature",
  "properties": {
    "addr:full":"Rue Des R\u00e9collets 65 Vis\u00e9 Li\u00e8ge 4600",
    "addr:housenumber":"65",
    "addr:postcode":"4600",
    "addr:street":"Rue Des Re\u0301Collets",
    "iso:country":"BE",
    "sg:address":"Rue Des R\u00e9collets 65",
    "sg:city":"Vis\u00e9",
    "sg:classifiers":[
        {
            "category":"Professional",
            "subcategory":"Accounting & Tax Preparation",
            "type":"Services"
        }
    ],
    "sg:phone":"+32 4 379 10 08",
    "sg:postcode":"4600",
    "sg:province":"Li\u00e8ge",
    "sg:tags":[
        "bookkeeper"
    ],
    "wof:name":"Garot J",
    "wof:placetype":"venue"
},
  "geometry": {"coordinates":[5.6932969093,50.7371559143],"type":"Point"}
}