{
  "type": "Feature",
  "properties": {
    "addr:full":"Zeedijk 93b817 Oostende West-Vlaanderen 8400",
    "addr:housenumber":"93b817",
    "addr:postcode":"8400",
    "addr:street":"Zeedijk",
    "iso:country":"BE",
    "sg:address":"Zeedijk 93b817",
    "sg:city":"Oostende",
    "sg:orig_category":"Artsen and specialisten",
    "sg:phone":"+32 59 80 21 50",
    "sg:postcode":"8400",
    "sg:province":"West-Vlaanderen",
    "wof:name":"Paul De Beir",
    "wof:placetype":"venue"
},
  "geometry": {"coordinates":[2.9026811123,51.2266311646],"type":"Point"}
}