{
  "type": "Feature",
  "properties": {
    "addr:full":"Seringenstraat 19 Ardooie West-Vlaanderen 8850",
    "addr:housenumber":"19",
    "addr:postcode":"8850",
    "addr:street":"Seringenstraat",
    "iso:country":"BE",
    "sg:address":"Seringenstraat 19",
    "sg:city":"Ardooie",
    "sg:orig_category":"Installation de menuiserie en bois and plastique",
    "sg:phone":"+32 51 74 53 19",
    "sg:postcode":"8850",
    "sg:province":"West-Vlaanderen",
    "wof:name":"Verdoo-schrijn",
    "wof:placetype":"venue"
},
  "geometry": {"coordinates":[3.1922109127,50.977684021],"type":"Point"}
}