{
  "type": "Feature",
  "properties": {
    "addr:full":"Rue De Boncelles 187 Seraing Li\u00e8ge 4102",
    "addr:housenumber":"187",
    "addr:postcode":"4102",
    "addr:street":"Rue De Boncelles",
    "iso:country":"BE",
    "sg:address":"Rue De Boncelles 187",
    "sg:city":"Seraing",
    "sg:orig_category":"Tabac",
    "sg:phone":"+32 4 337 46 46",
    "sg:postcode":"4102",
    "sg:province":"Li\u00e8ge",
    "wof:name":"Maison Testa",
    "wof:placetype":"venue"
},
  "geometry": {"coordinates":[5.534142971,50.6012916565],"type":"Point"}
}