{
  "type": "Feature",
  "properties": {
    "iso:country":"BE",
    "sg:address":"Houtvensesteenweg 32",
    "sg:city":"Herselt (ramsel)",
    "sg:classifiers":[
        {
            "category":"Quarry",
            "type":"Physical Feature"
        }
    ],
    "sg:phone":"+32 16 69 73 15",
    "sg:postcode":"2230",
    "sg:province":"Antwerpen",
    "sg:tags":[
        "granite",
        "work",
        "marble"
    ],
    "wof:name":"Wittockx E",
    "wof:placetype":"venue"
},
  "geometry": {"coordinates":[4.817732811,51.0333404541],"type":"Point"}
}