{
  "type": "Feature",
  "properties": {
    "addr:full":"Chauss\u00c9e De Jolimont 263 La Louviere Hainaut 7100",
    "addr:housenumber":"263",
    "addr:postcode":"7100",
    "addr:street":"Chausse\u0301E De Jolimont",
    "iso:country":"BE",
    "sg:address":"Chauss\u00c9e De Jolimont 263",
    "sg:city":"La Louviere",
    "sg:orig_category":"Secr\u00e9tariats sociaux",
    "sg:phone":"+32 64 27 54 30",
    "sg:postcode":"7100",
    "sg:province":"Hainaut",
    "wof:name":"Secr\u00c9tariat Soc. Seco-m",
    "wof:placetype":"venue"
},
  "geometry": {"coordinates":[4.2143001556,50.4706840515],"type":"Point"}
}