{
  "type": "Feature",
  "properties": {
    "iso:country":"BE",
    "sg:address":"Hasseltsestraat 52-54",
    "sg:city":"Diest",
    "sg:classifiers":[
        {
            "category":"Recreation",
            "subcategory":"Fishing",
            "type":"Entertainment"
        }
    ],
    "sg:phone":"+32 13 31 23 08",
    "sg:postcode":"3290",
    "sg:province":"Vlaams-Brabant",
    "sg:tags":[
        "tackle"
    ],
    "wof:name":"Lemmens",
    "wof:placetype":"venue"
},
  "geometry": {"coordinates":[5.0538139343,50.981136322],"type":"Point"}
}