{
  "type": "Feature",
  "properties": {
    "iso:country":"BE",
    "sg:address":"Chauss\u00c9e De Dinant 12",
    "sg:city":"Anhee",
    "sg:orig_category":"Parfumeries",
    "sg:phone":"+32 82 61 37 97",
    "sg:postcode":"5537",
    "sg:province":"Namur",
    "wof:name":"Valerie Laforet",
    "wof:placetype":"venue"
},
  "geometry": {"coordinates":[4.8813309669,50.3083190918],"type":"Point"}
}