{
  "type": "Feature",
  "properties": {
    "iso:country":"BE",
    "sg:address":"All\u00c9e Des Bleuets 7",
    "sg:city":"Hastiere",
    "sg:orig_category":"Installation \u00e9lectrique r\u00e9sidentielle",
    "sg:phone":"+32 82 64 55 07",
    "sg:postcode":"5540",
    "sg:province":"Namur",
    "wof:name":"Michel Tamenne",
    "wof:placetype":"venue"
},
  "geometry": {"coordinates":[4.8300418854,50.2202453613],"type":"Point"}
}