{
  "type": "Feature",
  "properties": {
    "iso:country":"BE",
    "sg:address":"Frans Massystraat 15",
    "sg:city":"Hasselt",
    "sg:classifiers":[
        {
            "category":"Professional",
            "type":"Services"
        }
    ],
    "sg:phone":"+32 11 22 99 82",
    "sg:postcode":"3500",
    "sg:province":"Limburg",
    "sg:tags":[
        "entertainer"
    ],
    "wof:name":"Fame International Bvba",
    "wof:placetype":"venue"
},
  "geometry": {"coordinates":[5.3283047676,50.9316101074],"type":"Point"}
}