{
  "type": "Feature",
  "properties": {
    "iso:country":"BE",
    "sg:address":"Steenweg Op Vilvoorde 112",
    "sg:city":"Opwijk",
    "sg:orig_category":"Installation de menuiserie m\u00e9tallique",
    "sg:phone":"+32 52 35 55 54",
    "sg:postcode":"1745",
    "sg:province":"Vlaams-Brabant",
    "wof:name":"Van Hoof",
    "wof:placetype":"venue"
},
  "geometry": {"coordinates":[4.1936712265,50.9579124451],"type":"Point"}
}