{
  "type": "Feature",
  "properties": {
    "iso:country":"BE",
    "sg:address":"Rue D'arlon 33",
    "sg:city":"Virton",
    "sg:classifiers":[
        {
            "category":"Health Services",
            "subcategory":"Doctor",
            "type":"Services"
        }
    ],
    "sg:phone":"+32 63 57 17 13",
    "sg:postcode":"6760",
    "sg:province":"Luxembourg",
    "sg:tags":[
        "psychotherapist",
        "psychoanalyst"
    ],
    "wof:name":"Frisch P",
    "wof:placetype":"venue"
},
  "geometry": {"coordinates":[5.5548248291,49.580078125],"type":"Point"}
}