{
  "type": "Feature",
  "properties": {
    "addr:full":"Pr\u00e9 Lutin 2 Namur (malonne) Namur 5020",
    "addr:housenumber":"2",
    "addr:postcode":"5020",
    "addr:street":"Pre\u0301 Lutin",
    "iso:country":"BE",
    "sg:address":"Pr\u00e9 Lutin 2",
    "sg:city":"Namur (malonne)",
    "sg:classifiers":[
        {
            "category":"Communications",
            "subcategory":"Film & Video Production",
            "type":"Services"
        }
    ],
    "sg:phone":"+32 81 44 46 00",
    "sg:postcode":"5020",
    "sg:province":"Namur",
    "sg:tags":[
        "sound",
        "installation",
        "material",
        "-",
        "recording",
        "studio"
    ],
    "wof:name":"Bachy P",
    "wof:placetype":"venue"
},
  "geometry": {"coordinates":[4.7952418327,50.4352035522],"type":"Point"}
}