{
  "type": "Feature",
  "properties": {
    "iso:country":"BE",
    "sg:address":"Rue Du Condroz 15",
    "sg:city":"Ciney",
    "sg:classifiers":[
        {
            "category":"Shopping",
            "subcategory":"Clothing, Apparel, & Fashions",
            "type":"Retail Goods"
        }
    ],
    "sg:phone":"+32 83 21 74 70",
    "sg:postcode":"5590",
    "sg:province":"Namur",
    "sg:tags":[
        "-",
        "clothing",
        "child"
    ],
    "wof:name":"Anges De Douceur",
    "wof:placetype":"venue"
},
  "geometry": {"coordinates":[5.1031928062,50.2970504761],"type":"Point"}
}