{
  "type": "Feature",
  "properties": {
    "addr:full":"Poelstraat 37 Merelbeke Oost-Vlaanderen 9820",
    "addr:housenumber":"37",
    "addr:postcode":"9820",
    "addr:street":"Poelstraat",
    "iso:country":"BE",
    "sg:address":"Poelstraat 37",
    "sg:city":"Merelbeke",
    "sg:classifiers":[
        {
            "category":"Social Services",
            "type":"Services"
        }
    ],
    "sg:phone":"+32 9 210 71 10",
    "sg:postcode":"9820",
    "sg:province":"Oost-Vlaanderen",
    "wof:name":"Ocmw",
    "wof:placetype":"venue"
},
  "geometry": {"coordinates":[3.750191927,50.9880218506],"type":"Point"}
}