{
  "type": "Feature",
  "properties": {
    "addr:full":"Lemallaan 13 De Haan (wenduine) West-Vlaanderen 8420",
    "addr:housenumber":"13",
    "addr:postcode":"8420",
    "addr:street":"Lemallaan",
    "iso:country":"BE",
    "sg:address":"Lemallaan 13",
    "sg:city":"De Haan (wenduine)",
    "sg:classifiers":[
        {
            "category":"Food & Beverages",
            "subcategory":"Chocolate",
            "type":"Retail Goods"
        }
    ],
    "sg:phone":"+32 50 41 45 41",
    "sg:postcode":"8420",
    "sg:province":"West-Vlaanderen",
    "sg:tags":[
        "confectionery",
        "-"
    ],
    "wof:name":"Vandeweghe C",
    "wof:placetype":"venue"
},
  "geometry": {"coordinates":[3.0331459045,51.2727775574],"type":"Point"}
}