{
  "type": "Feature",
  "properties": {
    "iso:country":"BE",
    "sg:address":"Rue Prince-de-li\u00e8ge 68",
    "sg:city":"Li\u00e8ge 1 (grivegn\u00e9e)",
    "sg:orig_category":"Ice-cream parlours",
    "sg:phone":"+32 4 367 61 56",
    "sg:postcode":"4030",
    "sg:province":"Li\u00e8ge",
    "wof:name":"Marechal M",
    "wof:placetype":"venue"
},
  "geometry": {"coordinates":[5.6262030602,50.6296653748],"type":"Point"}
}