{
  "type": "Feature",
  "properties": {
    "addr:full":"Dorpsstraat 10 Tervuren Vlaams-Brabant 3080",
    "addr:housenumber":"10",
    "addr:postcode":"3080",
    "addr:street":"Dorpsstraat",
    "iso:country":"BE",
    "sg:address":"Dorpsstraat 10",
    "sg:city":"Tervuren",
    "sg:orig_category":"Diverse grafische activiteiten",
    "sg:phone":"+32 2 768 22 75",
    "sg:postcode":"3080",
    "sg:province":"Vlaams-Brabant",
    "wof:name":"Studio Nsd",
    "wof:placetype":"venue"
},
  "geometry": {"coordinates":[4.5584859848,50.8350639343],"type":"Point"}
}