{
  "type": "Feature",
  "properties": {
    "iso:country":"BE",
    "sg:address":"Rue Van Helmont 33",
    "sg:city":"Brussel/bruxelles",
    "sg:orig_category":"Catering and organisation de f\u00eates",
    "sg:phone":"+32 2 513 09 28",
    "sg:postcode":"1000",
    "sg:province":"Bruxelles-Capitale",
    "wof:name":"Loven\u00b4s Garden",
    "wof:placetype":"venue"
},
  "geometry": {"coordinates":[4.3464331627,50.8441429138],"type":"Point"}
}