{
  "type": "Feature",
  "properties": {
    "iso:country":"BE",
    "sg:address":"Rue Sainte-anne 1bb",
    "sg:city":"Vresse-sur-semois",
    "sg:orig_category":"Boomkwekerijen",
    "sg:phone":"+32 61 50 11 44",
    "sg:postcode":"5550",
    "sg:province":"Namur",
    "wof:name":"P\u00c9pini\u00c8res Ardennaises",
    "wof:placetype":"venue"
},
  "geometry": {"coordinates":[4.9336900711,49.8729820251],"type":"Point"}
}