{
  "type": "Feature",
  "properties": {
    "iso:country":"BE",
    "sg:address":"Mechelsestweeg 586 A",
    "sg:city":"Vilvoorde",
    "sg:orig_category":"Herstellingen and onderhoud van auto's",
    "sg:phone":"+32 2 255 99 80",
    "sg:postcode":"1800",
    "sg:province":"Vlaams-Brabant",
    "wof:name":"D'iteren Vilvoorde",
    "wof:placetype":"venue"
},
  "geometry": {"coordinates":[4.4427242279,50.9445991516],"type":"Point"}
}