{
  "type": "Feature",
  "properties": {
    "iso:country":"BE",
    "sg:address":"Molendreef 10",
    "sg:city":"Willebroek",
    "sg:orig_category":"Diverse opleidingen and onderwijs",
    "sg:phone":"+32 3 866 54 30",
    "sg:postcode":"2830",
    "sg:province":"Antwerpen",
    "wof:name":"Evoluteam",
    "wof:placetype":"venue"
},
  "geometry": {"coordinates":[4.3863329887,51.0507698059],"type":"Point"}
}