{
  "type": "Feature",
  "properties": {
    "iso:country":"BE",
    "sg:address":"Rue Grande 50",
    "sg:city":"Namen",
    "sg:orig_category":"Sportclubs",
    "sg:phone":"+32 81 40 16 36",
    "sg:postcode":"5100",
    "sg:province":"Namur",
    "wof:name":"Les Lum'\u00c7ons Wierde",
    "wof:placetype":"venue"
},
  "geometry": {"coordinates":[4.8713750839,50.4566345215],"type":"Point"}
}