{
  "type": "Feature",
  "properties": {
    "iso:country":"BE",
    "sg:address":"Rue De Schaerbeek 42",
    "sg:city":"Houffalize",
    "sg:classifiers":[
        {
            "category":"Restaurant",
            "type":"Food & Drink"
        }
    ],
    "sg:phone":"+32 61 28 97 23",
    "sg:postcode":"6660",
    "sg:province":"Luxembourg",
    "sg:tags":[
        "caf\u00e9s"
    ],
    "wof:name":"Statu Quo Taverne",
    "wof:placetype":"venue"
},
  "geometry": {"coordinates":[5.7897901535,50.1321907043],"type":"Point"}
}