{
  "type": "Feature",
  "properties": {
    "addr:full":"Rue Hougaerde 12 Fontaine-l'ev\u00eaque (leernes) Hainaut 6142",
    "addr:housenumber":"12",
    "addr:postcode":"6142",
    "addr:street":"Rue Hougaerde;Hainaut",
    "iso:country":"BE",
    "sg:address":"Rue Hougaerde 12",
    "sg:city":"Fontaine-l'ev\u00eaque (leernes)",
    "sg:classifiers":[
        {
            "category":"Bars & Pubs",
            "type":"Food & Drink"
        }
    ],
    "sg:phone":"+32 71 54 22 32",
    "sg:postcode":"6142",
    "sg:province":"Hainaut",
    "sg:tags":[
        "tavern"
    ],
    "wof:name":"Ferme De La Foret (la)",
    "wof:placetype":"venue"
},
  "geometry": {"coordinates":[-111.9644622803,46.2507972717],"type":"Point"}
}