{
  "type": "Feature",
  "properties": {
    "iso:country":"BE",
    "sg:address":"Route De Falize 54",
    "sg:city":"Malmedy",
    "sg:classifiers":[
        {
            "category":"Building & Trades",
            "subcategory":"Construction",
            "type":"Services"
        }
    ],
    "sg:phone":"+32 80 33 87 77",
    "sg:postcode":"4960",
    "sg:province":"Li\u00e8ge",
    "sg:tags":[
        "paper",
        "hanger"
    ],
    "wof:name":"Servais S",
    "wof:placetype":"venue"
},
  "geometry": {"coordinates":[6.0152850151,50.421661377],"type":"Point"}
}