{
  "type": "Feature",
  "properties": {
    "addr:full":"Rue De La Resistance 8 Awans Li\u00e8ge 4340",
    "addr:housenumber":"8",
    "addr:postcode":"4340",
    "addr:street":"Rue De La Resistance",
    "iso:country":"BE",
    "sg:address":"Rue De La Resistance 8",
    "sg:city":"Awans",
    "sg:orig_category":"Slagers",
    "sg:phone":"+32 4 263 51 14",
    "sg:postcode":"4340",
    "sg:province":"Li\u00e8ge",
    "wof:name":"Marie-p. Verhelle",
    "wof:placetype":"venue"
},
  "geometry": {"coordinates":[5.4735360146,50.6647834778],"type":"Point"}
}