{
  "type": "Feature",
  "properties": {
    "addr:full":"Oudstrijderslei 35 Brasschaat Antwerpen 2930",
    "addr:housenumber":"35",
    "addr:postcode":"2930",
    "addr:street":"Oudstrijderslei",
    "iso:country":"BE",
    "sg:address":"Oudstrijderslei 35",
    "sg:city":"Brasschaat",
    "sg:orig_category":"Services divers aux entreprises. Organisation de salons, expositions and bourses. Agences de publici",
    "sg:phone":"+32 3 641 84 40",
    "sg:postcode":"2930",
    "sg:province":"Antwerpen",
    "wof:name":"Imago Swolfs - Incentives",
    "wof:placetype":"venue"
},
  "geometry": {"coordinates":[4.4653759003,51.2764778137],"type":"Point"}
}