{
  "type": "Feature",
  "properties": {
    "addr:full":"Le Petit Saidon 31 Libramont-chevigny (saint-pierre) Luxembourg 6800",
    "addr:housenumber":"31",
    "addr:postcode":"6800",
    "addr:street":"Libramont-Chevigny Saint-Pierre",
    "iso:country":"BE",
    "sg:address":"Le Petit Saidon 31",
    "sg:city":"Libramont-chevigny (saint-pierre)",
    "sg:classifiers":[
        {
            "category":"Sports & Exercise",
            "subcategory":"Stables",
            "type":"Entertainment"
        }
    ],
    "sg:phone":"+32 61 22 56 82",
    "sg:postcode":"6800",
    "sg:province":"Luxembourg",
    "sg:tags":[
        "riding",
        "school"
    ],
    "wof:name":"Man\u00e8ge Les Petites Terres",
    "wof:placetype":"venue"
},
  "geometry": {"coordinates":[5.4165630341,49.9208831787],"type":"Point"}
}