{
  "type": "Feature",
  "properties": {
    "addr:full":"Boechoutsesteenweg 69 Hove Antwerpen 2540",
    "addr:housenumber":"69",
    "addr:postcode":"2540",
    "addr:street":"Boechoutsesteenweg",
    "iso:country":"BE",
    "sg:address":"Boechoutsesteenweg 69",
    "sg:city":"Hove",
    "sg:orig_category":"Brood, gebak and snoepgoed",
    "sg:phone":"+32 3 455 21 26",
    "sg:postcode":"2540",
    "sg:province":"Antwerpen",
    "wof:name":"Fa. Luikens",
    "wof:placetype":"venue"
},
  "geometry": {"coordinates":[4.4756188393,51.1552276611],"type":"Point"}
}