{
  "type": "Feature",
  "properties": {
    "addr:full":"Grotesteenweg Noord 15 Gent (zwijnaarde) Oost-Vlaanderen 9052",
    "addr:housenumber":"15",
    "addr:postcode":"9052",
    "addr:street":"Grotesteenweg Noord",
    "iso:country":"BE",
    "sg:address":"Grotesteenweg Noord 15",
    "sg:city":"Gent (zwijnaarde)",
    "sg:classifiers":[
        {
            "category":"Shopping",
            "subcategory":"Clothing, Apparel, & Fashions",
            "type":"Retail Goods"
        }
    ],
    "sg:phone":"+32 9 221 07 90",
    "sg:postcode":"9052",
    "sg:province":"Oost-Vlaanderen",
    "sg:tags":[
        "boutique"
    ],
    "wof:name":"Julie",
    "wof:placetype":"venue"
},
  "geometry": {"coordinates":[3.7087869644,51.0569801331],"type":"Point"}
}