{
  "type": "Feature",
  "properties": {
    "iso:country":"BE",
    "sg:address":"Leo De B\u00c9thunelaan 29b2",
    "sg:city":"Aalst",
    "sg:orig_category":"Beheer onroerend goed",
    "sg:phone":"+32 53 71 08 06",
    "sg:postcode":"9300",
    "sg:province":"Oost-Vlaanderen",
    "wof:name":"Immo Van Hee Agnes",
    "wof:placetype":"venue"
},
  "geometry": {"coordinates":[4.0330572128,50.9288902283],"type":"Point"}
}