{
  "type": "Feature",
  "properties": {
    "iso:country":"BE",
    "sg:address":"Zwijnaardsesteenweg 250",
    "sg:city":"Gent",
    "sg:orig_category":"Enseignement maternel and primaire",
    "sg:phone":"+32 9 222 29 04",
    "sg:postcode":"9000",
    "sg:province":"Oost-Vlaanderen",
    "wof:name":"Stedelijke Basisschool",
    "wof:placetype":"venue"
},
  "geometry": {"coordinates":[3.722383976,51.0304603577],"type":"Point"}
}