{
  "type": "Feature",
  "properties": {
    "addr:full":"Avenue Jean De Bologne 36 Bruxelles Bruxelles-Capitale 1020",
    "addr:housenumber":"36",
    "addr:postcode":"1020",
    "addr:street":"Avenue Jean De Bologne",
    "iso:country":"BE",
    "sg:address":"Avenue Jean De Bologne 36",
    "sg:city":"Bruxelles",
    "sg:classifiers":[
        {
            "category":"Real Estate",
            "subcategory":"Architect",
            "type":"Services"
        }
    ],
    "sg:phone":"+32 2 268 39 81",
    "sg:postcode":"1020",
    "sg:province":"Bruxelles-Capitale",
    "wof:name":"Moureau C",
    "wof:placetype":"venue"
},
  "geometry": {"coordinates":[4.3603191376,50.8968658447],"type":"Point"}
}