{
  "type": "Feature",
  "properties": {
    "addr:full":"Route De Williers 18 Florenville Luxembourg 6820",
    "addr:housenumber":"18",
    "addr:postcode":"6820",
    "addr:street":"Route De Williers",
    "iso:country":"BE",
    "sg:address":"Route De Williers 18",
    "sg:city":"Florenville",
    "sg:classifiers":[
        {
            "category":"Building & Trades",
            "subcategory":"Construction",
            "type":"Services"
        }
    ],
    "sg:phone":"+32 61 31 21 77",
    "sg:postcode":"6820",
    "sg:province":"Luxembourg",
    "sg:tags":[
        "installation",
        "-",
        "central",
        "heating"
    ],
    "wof:name":"Hubert R",
    "wof:placetype":"venue"
},
  "geometry": {"coordinates":[5.3131279945,49.6930084229],"type":"Point"}
}