{
  "type": "Feature",
  "properties": {
    "addr:full":"Rommeldonkstraat 7 Evergem Oost-Vlaanderen 9940",
    "addr:housenumber":"7",
    "addr:postcode":"9940",
    "addr:street":"Rommeldonkstraat;Oost-Vlaanderen",
    "iso:country":"BE",
    "sg:address":"Rommeldonkstraat 7",
    "sg:city":"Evergem",
    "sg:orig_category":"Installation \u00e9lectrique r\u00e9sidentielle",
    "sg:phone":"+32 9 357 58 14",
    "sg:postcode":"9940",
    "sg:province":"Oost-Vlaanderen",
    "wof:name":"Hubert Verstraeten",
    "wof:placetype":"venue"
},
  "geometry": {"coordinates":[3.6764230728,51.1205978394],"type":"Point"}
}