{
  "type": "Feature",
  "properties": {
    "iso:country":"BE",
    "sg:address":"Strijbroek 2",
    "sg:city":"Sint-katelijne-waver",
    "sg:classifiers":[
        {
            "category":"Professional",
            "type":"Services"
        }
    ],
    "sg:phone":"+32 15 31 82 01",
    "sg:postcode":"2860",
    "sg:province":"Antwerpen",
    "sg:tags":[
        "packing",
        "-"
    ],
    "wof:name":"Corent",
    "wof:placetype":"venue"
},
  "geometry": {"coordinates":[4.5139818192,51.0620155334],"type":"Point"}
}