{
  "type": "Feature",
  "properties": {
    "addr:full":"Prinses Elisabeth Plein 8 Brussel/bruxelles Bruxelles-Capitale 1030",
    "addr:housenumber":"8",
    "addr:postcode":"1030",
    "addr:street":"Prinses Elisabeth Plein;/",
    "iso:country":"BE",
    "sg:address":"Prinses Elisabeth Plein 8",
    "sg:city":"Brussel/bruxelles",
    "sg:orig_category":"Huishoudapparaten, televisies and radio's MEUBELONTWERP AND -INSTALLATIE Telecommunicatieapparaten",
    "sg:phone":"+32 2 241 15 33",
    "sg:postcode":"1030",
    "sg:province":"Bruxelles-Capitale",
    "wof:name":"Electro-cash",
    "wof:placetype":"venue"
},
  "geometry": {"coordinates":[4.3764719963,50.8719711304],"type":"Point"}
}