{
  "type": "Feature",
  "properties": {
    "iso:country":"BE",
    "sg:address":"Kruyenberg 26",
    "sg:city":"Berlare",
    "sg:classifiers":[
        {
            "category":"Real Estate",
            "subcategory":"Architect",
            "type":"Services"
        }
    ],
    "sg:phone":"+32 52 42 52 56",
    "sg:postcode":"9290",
    "sg:province":"Oost-Vlaanderen",
    "wof:name":"Schelfhout N",
    "wof:placetype":"venue"
},
  "geometry": {"coordinates":[3.9984838963,51.0245552063],"type":"Point"}
}