{
  "type": "Feature",
  "properties": {
    "iso:country":"BE",
    "sg:address":"Mannestraat 85bb",
    "sg:city":"Geel",
    "sg:orig_category":"Elektrische installaties voor woningen",
    "sg:phone":"+32 14 58 37 49",
    "sg:postcode":"2440",
    "sg:province":"Antwerpen",
    "wof:name":"Electro D En J",
    "wof:placetype":"venue"
},
  "geometry": {"coordinates":[5.0129489899,51.1691246033],"type":"Point"}
}