{
  "type": "Feature",
  "properties": {
    "iso:country":"BE",
    "sg:address":"Rue De Henri Chapelle 1",
    "sg:city":"Herve (battice)",
    "sg:classifiers":[
        {
            "category":"Retail",
            "subcategory":"Repair Shop",
            "type":"Services"
        }
    ],
    "sg:phone":"+32 87 66 02 31",
    "sg:postcode":"4651",
    "sg:province":"Li\u00e8ge",
    "sg:tags":[
        "mainten",
        "-",
        "parquet"
    ],
    "wof:name":"Piron Et Huberty",
    "wof:placetype":"venue"
},
  "geometry": {"coordinates":[5.8261928558,50.6460227966],"type":"Point"}
}