{
  "type": "Feature",
  "properties": {
    "addr:full":"Rue Pierre Flamand 41 Braine-l\u00b4alleud Brabant Wallon 1420",
    "addr:housenumber":"41",
    "addr:postcode":"1420",
    "addr:street":"Rue Pierre Flamand;Brabant Wallon",
    "iso:country":"BE",
    "sg:address":"Rue Pierre Flamand 41",
    "sg:city":"Braine-l\u00b4alleud",
    "sg:classifiers":[
        {
            "category":"Personal",
            "subcategory":"Beauty Salon",
            "type":"Services"
        }
    ],
    "sg:phone":"+32 2 384 33 22",
    "sg:postcode":"1420",
    "sg:province":"Brabant Wallon",
    "sg:tags":[
        "de",
        "coiffure"
    ],
    "wof:name":"Coiffure Mambourg",
    "wof:placetype":"venue"
},
  "geometry": {"coordinates":[4.3707737923,50.6865768433],"type":"Point"}
}