{
  "type": "Feature",
  "properties": {
    "addr:full":"Vinkstraat 4 Bocholt Limburg 3950",
    "addr:housenumber":"4",
    "addr:postcode":"3950",
    "addr:street":"Vinkstraat",
    "iso:country":"BE",
    "sg:address":"Vinkstraat 4",
    "sg:city":"Bocholt",
    "sg:classifiers":[
        {
            "category":"Health Services",
            "subcategory":"Health Practitioner",
            "type":"Services"
        }
    ],
    "sg:phone":"+32 89 47 14 89",
    "sg:postcode":"3950",
    "sg:province":"Limburg",
    "sg:tags":[
        "physiotherapist"
    ],
    "wof:name":"Cardinaels Rik",
    "wof:placetype":"venue"
},
  "geometry": {"coordinates":[5.572206974,51.1746444702],"type":"Point"}
}