{
  "type": "Feature",
  "properties": {
    "addr:full":"Rue Defacqz 122 Ath Hainaut 7800",
    "addr:housenumber":"122",
    "addr:postcode":"7800",
    "addr:street":"Rue Defacqz",
    "iso:country":"BE",
    "sg:address":"Rue Defacqz 122",
    "sg:city":"Ath",
    "sg:orig_category":"Dierenartsen",
    "sg:phone":"+32 68 28 14 00",
    "sg:postcode":"7800",
    "sg:province":"Hainaut",
    "wof:name":"Bachy",
    "wof:placetype":"venue"
},
  "geometry": {"coordinates":[3.7844998837,50.6307487488],"type":"Point"}
}