{
  "type": "Feature",
  "properties": {
    "addr:full":"Rue De Landen 57 Hannut Li\u00e8ge 4280",
    "addr:housenumber":"57",
    "addr:postcode":"4280",
    "addr:street":"Rue De Landen",
    "iso:country":"BE",
    "sg:address":"Rue De Landen 57",
    "sg:city":"Hannut",
    "sg:classifiers":[
        {
            "category":"Autos & Motor Vehicles",
            "subcategory":"Fuel & Gas Station",
            "type":"Retail Goods"
        }
    ],
    "sg:phone":"+32 19 51 14 96",
    "sg:postcode":"4280",
    "sg:province":"Li\u00e8ge",
    "sg:tags":[
        "industrial",
        "motor-cars",
        "plastic",
        "rubber",
        "equipment",
        "transport"
    ],
    "wof:name":"Sas Sa",
    "wof:placetype":"venue"
},
  "geometry": {"coordinates":[5.0819168091,50.682762146],"type":"Point"}
}