{
  "type": "Feature",
  "properties": {
    "addr:full":"Scheldestraat 8 Gavere Oost-Vlaanderen 9890",
    "addr:housenumber":"8",
    "addr:postcode":"9890",
    "addr:street":"Scheldestraat",
    "iso:country":"BE",
    "sg:address":"Scheldestraat 8",
    "sg:city":"Gavere",
    "sg:classifiers":[
        {
            "category":"Wholesale",
            "subcategory":"Sporting Goods",
            "type":"Manufacturing & Wholesale Goods"
        }
    ],
    "sg:phone":"+32 9 384 22 85",
    "sg:postcode":"9890",
    "sg:province":"Oost-Vlaanderen",
    "sg:tags":[
        "sport-",
        "kampeermateriaal"
    ],
    "wof:name":"Hans Verloo",
    "wof:placetype":"venue"
},
  "geometry": {"coordinates":[3.6586689949,50.9302711487],"type":"Point"}
}