{
  "type": "Feature",
  "properties": {
    "addr:full":"Rechtstraat 112 Lokeren (eksaarde) Oost-Vlaanderen 9160",
    "addr:housenumber":"112",
    "addr:postcode":"9160",
    "addr:street":"Rechtstraat;Lokeren Eksaarde Oost-Vlaanderen",
    "iso:country":"BE",
    "sg:address":"Rechtstraat 112",
    "sg:city":"Lokeren (eksaarde)",
    "sg:classifiers":[
        {
            "category":"Health Services",
            "subcategory":"Health Practitioner",
            "type":"Services"
        }
    ],
    "sg:phone":"+32 9 346 83 83",
    "sg:postcode":"9160",
    "sg:province":"Oost-Vlaanderen",
    "sg:tags":[
        "therapist",
        "speech"
    ],
    "wof:name":"Van De Putte H",
    "wof:placetype":"venue"
},
  "geometry": {"coordinates":[3.9420850277,51.1419181824],"type":"Point"}
}