{
  "type": "Feature",
  "properties": {
    "addr:full":"Gentsesteenweg 397 Sint-jans-molenbeek/molenbeek-saint-jean Bruxelles-Capitale 1080",
    "addr:housenumber":"397;/",
    "addr:postcode":"1080",
    "addr:street":"Gentsesteenweg;Sint-Jans-Molenbeek",
    "iso:country":"BE",
    "sg:address":"Gentsesteenweg 397",
    "sg:city":"Sint-jans-molenbeek/molenbeek-saint-jean",
    "sg:classifiers":[
        {
            "category":"Food & Beverages",
            "subcategory":"Meat & Fish",
            "type":"Retail Goods"
        }
    ],
    "sg:phone":"+32 2 410 57 62",
    "sg:postcode":"1080",
    "sg:province":"Bruxelles-Capitale",
    "sg:tags":[
        "vi",
        "zeevruchten"
    ],
    "wof:name":"Maison Le Mareyeur",
    "wof:placetype":"venue"
},
  "geometry": {"coordinates":[4.3055300713,50.860660553],"type":"Point"}
}