{
  "type": "Feature",
  "properties": {
    "addr:full":"Rue De La Lhomme 53a Rochefort (jemelle) Namur 5580",
    "addr:housenumber":"53a",
    "addr:postcode":"5580",
    "addr:street":"Rue De La Lhomme",
    "iso:country":"BE",
    "sg:address":"Rue De La Lhomme 53a",
    "sg:city":"Rochefort (jemelle)",
    "sg:classifiers":[
        {
            "category":"Social Services",
            "type":"Services"
        }
    ],
    "sg:phone":"+32 84 21 07 53",
    "sg:postcode":"5580",
    "sg:province":"Namur",
    "wof:name":"Gamedella (maison De Quartier) Asbl",
    "wof:placetype":"venue"
},
  "geometry": {"coordinates":[5.2556657791,50.163066864],"type":"Point"}
}