{
  "type": "Feature",
  "properties": {
    "addr:full":"Rue Profondrieux 36 Ecaussinnes Hainaut 7190",
    "addr:housenumber":"36",
    "addr:postcode":"7190",
    "addr:street":"Rue Profondrieux;Hainaut",
    "iso:country":"BE",
    "sg:address":"Rue Profondrieux 36",
    "sg:city":"Ecaussinnes",
    "sg:orig_category":"Eleveurs de bovins",
    "sg:phone":"+32 67 44 41 23",
    "sg:postcode":"7190",
    "sg:province":"Hainaut",
    "wof:name":"Frans Paindavoine",
    "wof:placetype":"venue"
},
  "geometry": {"coordinates":[4.1281480789,50.5657196045],"type":"Point"}
}