{
  "type": "Feature",
  "properties": {
    "addr:full":"Putstraat 9 Tongeren Limburg 3700",
    "addr:housenumber":"9",
    "addr:postcode":"3700",
    "addr:street":"Putstraat",
    "iso:country":"BE",
    "sg:address":"Putstraat 9",
    "sg:city":"Tongeren",
    "sg:classifiers":[
        {
            "category":"Food & Beverages",
            "subcategory":"Fruits & Vegetables",
            "type":"Retail Goods"
        }
    ],
    "sg:phone":"+32 12 23 17 60",
    "sg:postcode":"3700",
    "sg:province":"Limburg",
    "sg:tags":[
        "l\u00e9gumes"
    ],
    "wof:name":"Jean Lysens",
    "wof:placetype":"venue"
},
  "geometry": {"coordinates":[5.4623389244,50.7792396545],"type":"Point"}
}