{
  "type": "Feature",
  "properties": {
    "iso:country":"BE",
    "sg:address":"Chauss\u00e9e D'audenarde 386",
    "sg:city":"Pecq (h\u00e9rinnes-lez-pecq)",
    "sg:classifiers":[
        {
            "category":"Sports & Exercise",
            "subcategory":"Stables",
            "type":"Entertainment"
        }
    ],
    "sg:phone":"+32 69 55 91 64",
    "sg:postcode":"7742",
    "sg:province":"Hainaut",
    "sg:tags":[
        "riding",
        "school"
    ],
    "wof:name":"Decruyenaere J",
    "wof:placetype":"venue"
},
  "geometry": {"coordinates":[3.3689661026,50.7076568604],"type":"Point"}
}