{
  "type": "Feature",
  "properties": {
    "addr:full":"Avenue Du Val St.georges 11 Namur Namur 5000",
    "addr:housenumber":"11",
    "addr:postcode":"5000",
    "addr:street":"Avenue Du Val St.Georges",
    "iso:country":"BE",
    "sg:address":"Avenue Du Val St.georges 11",
    "sg:city":"Namur",
    "sg:orig_category":"M\u00e9decins and sp\u00e9cialistes",
    "sg:phone":"+32 81 74 29 14",
    "sg:postcode":"5000",
    "sg:province":"Namur",
    "wof:name":"Mirela Seretan",
    "wof:placetype":"venue"
},
  "geometry": {"coordinates":[4.8388609886,50.4617233276],"type":"Point"}
}