{
  "type": "Feature",
  "properties": {
    "addr:full":"Rue De La Station 13 Wavre (limal) Brabant Wallon 1300",
    "addr:housenumber":"13",
    "addr:postcode":"1300",
    "addr:street":"Rue De La Station;Wallon",
    "iso:country":"BE",
    "sg:address":"Rue De La Station 13",
    "sg:city":"Wavre (limal)",
    "sg:classifiers":[
        {
            "category":"Banks & Credit Unions",
            "subcategory":"Investment Brokerage",
            "type":"Services"
        }
    ],
    "sg:phone":"+32 10 40 24 05",
    "sg:postcode":"1300",
    "sg:province":"Brabant Wallon",
    "sg:tags":[
        "jean",
        "casual",
        "wear"
    ],
    "wof:name":"International Cash Sa",
    "wof:placetype":"venue"
},
  "geometry": {"coordinates":[4.5736579895,50.6932563782],"type":"Point"}
}