{
  "type": "Feature",
  "properties": {
    "addr:full":"Charles Michielslaan 174b9 Watermaal-bosvoorde/watermael-boitsfort Bruxelles-Capitale 1170",
    "addr:housenumber":"174b9",
    "addr:postcode":"1170",
    "addr:street":"Michielslaan",
    "iso:country":"BE",
    "sg:address":"Charles Michielslaan 174b9",
    "sg:city":"Watermaal-bosvoorde/watermael-boitsfort",
    "sg:orig_category":"Artsen and specialisten",
    "sg:phone":"+32 2 673 82 52",
    "sg:postcode":"1170",
    "sg:province":"Bruxelles-Capitale",
    "wof:name":"Nadine Borrey",
    "wof:placetype":"venue"
},
  "geometry": {"coordinates":[4.4031748772,50.8146247864],"type":"Point"}
}