{
  "type": "Feature",
  "properties": {
    "addr:full":"Lutgardisstraat 6 Steenokkerzeel Vlaams-Brabant 1820",
    "addr:housenumber":"6",
    "addr:postcode":"1820",
    "addr:street":"Lutgardisstraat",
    "iso:country":"BE",
    "sg:address":"Lutgardisstraat 6",
    "sg:city":"Steenokkerzeel",
    "sg:orig_category":"Groententeelt",
    "sg:phone":"+32 2 751 50 54",
    "sg:postcode":"1820",
    "sg:province":"Vlaams-Brabant",
    "wof:name":"Adriaan Imbrechts",
    "wof:placetype":"venue"
},
  "geometry": {"coordinates":[4.4956569672,50.9337081909],"type":"Point"}
}