{
  "type": "Feature",
  "properties": {
    "iso:country":"BE",
    "sg:address":"Lavoordestraat 53",
    "sg:city":"Wingene",
    "sg:classifiers":[
        {
            "category":"Retail",
            "subcategory":"Repair Shop",
            "type":"Services"
        }
    ],
    "sg:phone":"+32 51 65 66 13",
    "sg:postcode":"8750",
    "sg:province":"West-Vlaanderen",
    "sg:tags":[
        "upholsterer"
    ],
    "wof:name":"Huvaere L",
    "wof:placetype":"venue"
},
  "geometry": {"coordinates":[3.2550599575,51.0705299377],"type":"Point"}
}