{
  "type": "Feature",
  "properties": {
    "addr:full":"Engelsdorfer Strasse 3 Recht Li\u00e8ge 4780",
    "addr:housenumber":"3",
    "addr:postcode":"4780",
    "addr:street":"Engelsdorfer Strasse",
    "iso:country":"BE",
    "sg:address":"Engelsdorfer Strasse 3",
    "sg:city":"Recht",
    "sg:classifiers":[
        {
            "category":"Government",
            "subcategory":"Fire Station",
            "type":"Public Place"
        }
    ],
    "sg:phone":"+32 80 57 04 56",
    "sg:postcode":"4780",
    "sg:province":"Li\u00e8ge",
    "sg:tags":[
        "alloy",
        "light",
        "aluminium",
        "processing"
    ],
    "wof:name":"Temeka P S.p.r.l.",
    "wof:placetype":"venue"
},
  "geometry": {"coordinates":[6.070786953,50.3497123718],"type":"Point"}
}