{
  "type": "Feature",
  "properties": {
    "addr:full":"Leopold Ii Laan 2 Koksijde (oostduinkerke) West-Vlaanderen 8670",
    "addr:housenumber":"2",
    "addr:postcode":"8670",
    "addr:street":"Leopold Ii Laan",
    "iso:country":"BE",
    "sg:address":"Leopold Ii Laan 2",
    "sg:city":"Koksijde (oostduinkerke)",
    "sg:classifiers":[
        {
            "category":"Government",
            "subcategory":"Office",
            "type":"Public Place"
        }
    ],
    "sg:phone":"+32 58 53 21 21",
    "sg:postcode":"8670",
    "sg:province":"West-Vlaanderen",
    "sg:tags":[
        "-",
        "tourism",
        "federation"
    ],
    "wof:name":"Dienst Voor Toerisme Koksijde",
    "wof:placetype":"venue"
},
  "geometry": {"coordinates":[2.6823000908,51.1160392761],"type":"Point"}
}