{
  "type": "Feature",
  "properties": {
    "iso:country":"BE",
    "sg:address":"Watermolenweg 3",
    "sg:city":"Bocholt",
    "sg:orig_category":"Rundveehouders",
    "sg:phone":"+32 89 46 38 54",
    "sg:postcode":"3950",
    "sg:province":"Limburg",
    "wof:name":"Mathieu Boonen",
    "wof:placetype":"venue"
},
  "geometry": {"coordinates":[5.6160769463,51.1806526184],"type":"Point"}
}