{
  "type": "Feature",
  "properties": {
    "iso:country":"BE",
    "sg:address":"Rue De La Fraternit\u00e9 20",
    "sg:city":"Aubange (halanzy)",
    "sg:classifiers":[
        {
            "category":"Health Services",
            "subcategory":"Dentist",
            "type":"Services"
        }
    ],
    "sg:phone":"+32 63 67 56 03",
    "sg:postcode":"6792",
    "sg:province":"Luxembourg",
    "wof:name":"Ligny Martine Mme",
    "wof:placetype":"venue"
},
  "geometry": {"coordinates":[5.7443871498,49.5593109131],"type":"Point"}
}