{
  "type": "Feature",
  "properties": {
    "addr:full":"Plankeweidevoetweg 2 Hasselt Limburg 3500",
    "addr:housenumber":"2",
    "addr:postcode":"3500",
    "addr:street":"Plankeweidevoetweg",
    "iso:country":"BE",
    "sg:address":"Plankeweidevoetweg 2",
    "sg:city":"Hasselt",
    "sg:orig_category":"Sportterreinen and installaties behalve sportcentra",
    "sg:phone":"+32 11 22 78 30",
    "sg:postcode":"3500",
    "sg:province":"Limburg",
    "wof:name":"Maaseiker Watersport Club",
    "wof:placetype":"venue"
},
  "geometry": {"coordinates":[5.3478169441,50.9245948792],"type":"Point"}
}