{
  "type": "Feature",
  "properties": {
    "iso:country":"BE",
    "sg:address":"Rue Du Gonhy 45",
    "sg:city":"Seraing (boncelles)",
    "sg:classifiers":[
        {
            "category":"Shopping",
            "subcategory":"Baby Store",
            "type":"Retail Goods"
        }
    ],
    "sg:postcode":"4100",
    "sg:province":"Li\u00e8ge",
    "sg:tags":[
        "-",
        "accessory"
    ],
    "wof:name":"Baby Planet",
    "wof:placetype":"venue"
},
  "geometry": {"coordinates":[4.4585881233,51.58228302],"type":"Point"}
}