{
  "type": "Feature",
  "properties": {
    "iso:country":"BE",
    "sg:address":"Leemskuilen 31",
    "sg:city":"Vosselaar",
    "sg:classifiers":[
        {
            "category":"Building & Trades",
            "subcategory":"Construction",
            "type":"Services"
        }
    ],
    "sg:phone":"+32 14 61 53 06",
    "sg:postcode":"2350",
    "sg:province":"Antwerpen",
    "sg:tags":[
        "stucco",
        "contractor"
    ],
    "wof:name":"Damen Jos Bvba",
    "wof:placetype":"venue"
},
  "geometry": {"coordinates":[4.8797922134,51.3165397644],"type":"Point"}
}