{
  "type": "Feature",
  "properties": {
    "addr:full":"Rue Grosses Pierres 69 Grace-hollogne Li\u00e8ge 4460",
    "addr:housenumber":"69",
    "addr:postcode":"4460",
    "addr:street":"Rue Grosses Pierres",
    "iso:country":"BE",
    "sg:address":"Rue Grosses Pierres 69",
    "sg:city":"Grace-hollogne",
    "sg:orig_category":"Advocaten and juridische adviseurs",
    "sg:phone":"+32 4 246 44 44",
    "sg:postcode":"4460",
    "sg:province":"Li\u00e8ge",
    "wof:name":"H. Lhoest",
    "wof:placetype":"venue"
},
  "geometry": {"coordinates":[5.4738268852,50.6466827393],"type":"Point"}
}