{
  "type": "Feature",
  "properties": {
    "addr:full":"Avenue Du Chili 18 Charleroi Hainaut 6001",
    "addr:housenumber":"18",
    "addr:postcode":"6001",
    "addr:street":"Avenue Du Chili;Hainaut",
    "iso:country":"BE",
    "sg:address":"Avenue Du Chili 18",
    "sg:city":"Charleroi",
    "sg:orig_category":"Location de logements sociaux",
    "sg:phone":"+32 71 36 81 12",
    "sg:postcode":"6001",
    "sg:province":"Hainaut",
    "wof:name":"Le Foyer Marcinellois",
    "wof:placetype":"venue"
},
  "geometry": {"coordinates":[4.4369029999,50.3808174133],"type":"Point"}
}