{
  "type": "Feature",
  "properties": {
    "iso:country":"BE",
    "sg:address":"Grand-place 38",
    "sg:city":"Mons",
    "sg:classifiers":[
        {
            "category":"Cafe",
            "type":"Food & Drink"
        }
    ],
    "sg:phone":"+32 65 34 06 85",
    "sg:postcode":"7000",
    "sg:province":"Hainaut",
    "sg:tags":[
        "caf\u00e9s"
    ],
    "wof:name":"Caf\u00c9 Comte De Flandre",
    "wof:placetype":"venue"
},
  "geometry": {"coordinates":[3.9519200325,50.4541282654],"type":"Point"}
}