{
  "type": "Feature",
  "properties": {
    "iso:country":"BE",
    "sg:address":"Rue Bousalle 15",
    "sg:city":"Andenne",
    "sg:classifiers":[
        {
            "category":"Arts & Performance",
            "subcategory":"Music",
            "type":"Entertainment"
        }
    ],
    "sg:phone":"+32 85 84 23 72",
    "sg:postcode":"5300",
    "sg:province":"Namur",
    "sg:tags":[
        "disc-jockeys"
    ],
    "wof:name":"Galaxias",
    "wof:placetype":"venue"
},
  "geometry": {"coordinates":[5.1417779922,50.4864044189],"type":"Point"}
}