{
  "type": "Feature",
  "properties": {
    "iso:country":"BE",
    "sg:address":"Stationstr. 78",
    "sg:city":"Gijzegem",
    "sg:classifiers":[
        {
            "category":"Farming",
            "subcategory":"Farm",
            "type":"Manufacturing & Wholesale Goods"
        }
    ],
    "sg:phone":"+32 53 77 75 05",
    "sg:postcode":"9308",
    "sg:province":"Oost-Vlaanderen",
    "sg:tags":[
        "horticulture",
        "agriculture",
        "livestock"
    ],
    "wof:name":"Floru Bvba",
    "wof:placetype":"venue"
},
  "geometry": {"coordinates":[4.0347590446,50.9603500366],"type":"Point"}
}