{
  "type": "Feature",
  "properties": {
    "addr:full":"Kroonstraat 1 Brugge West-Vlaanderen 8000",
    "addr:housenumber":"1",
    "addr:postcode":"8000",
    "addr:street":"Kroonstraat",
    "iso:country":"BE",
    "sg:address":"Kroonstraat 1",
    "sg:city":"Brugge",
    "sg:orig_category":"Huishoudapparaten, televisies and radio's",
    "sg:phone":"+32 50 31 46 54",
    "sg:postcode":"8000",
    "sg:province":"West-Vlaanderen",
    "wof:name":"Masser",
    "wof:placetype":"venue"
},
  "geometry": {"coordinates":[3.2091929913,51.2168045044],"type":"Point"}
}