{
  "type": "Feature",
  "properties": {
    "addr:full":"Grand-place 39 Mons Hainaut 7000",
    "addr:housenumber":"39",
    "addr:postcode":"7000",
    "addr:street":"Grand-Place;Hainaut",
    "iso:country":"BE",
    "sg:address":"Grand-place 39",
    "sg:city":"Mons",
    "sg:classifiers":[
        {
            "category":"Fast Food",
            "type":"Food & Drink"
        }
    ],
    "sg:phone":"+32 65 33 47 37",
    "sg:postcode":"7000",
    "sg:province":"Hainaut",
    "sg:tags":[
        "meeneem",
        "restaurant"
    ],
    "wof:name":"Mcdonald's",
    "wof:placetype":"venue"
},
  "geometry": {"coordinates":[3.9520909786,50.4538764954],"type":"Point"}
}