{
  "type": "Feature",
  "properties": {
    "iso:country":"BE",
    "sg:address":"Rue De La Chapelle 10",
    "sg:city":"Namur",
    "sg:classifiers":[
        {
            "category":"Personal",
            "subcategory":"Beauty Salon",
            "type":"Services"
        }
    ],
    "sg:phone":"+32 81 73 34 18",
    "sg:postcode":"5000",
    "sg:province":"Namur",
    "wof:name":"Parmentier",
    "wof:placetype":"venue"
},
  "geometry": {"coordinates":[4.8420591354,50.463092804],"type":"Point"}
}