{
  "type": "Feature",
  "properties": {
    "iso:country":"BE",
    "sg:address":"Naamsestraat 187",
    "sg:city":"Leuven",
    "sg:classifiers":[
        {
            "category":"Personal",
            "subcategory":"Barber",
            "type":"Services"
        }
    ],
    "sg:phone":"+32 16 23 57 93",
    "sg:postcode":"3000",
    "sg:province":"Vlaams-Brabant",
    "sg:tags":[
        "gentleman",
        "salon",
        "-",
        "hairdressing"
    ],
    "wof:name":"Stroobansts W",
    "wof:placetype":"venue"
},
  "geometry": {"coordinates":[4.6990699768,50.8689537048],"type":"Point"}
}