{
  "type": "Feature",
  "properties": {
    "addr:full":"Homerusstraat 11 Anderlecht/anderlecht Bruxelles-Capitale 1070",
    "addr:housenumber":"11",
    "addr:postcode":"1070",
    "addr:street":"Homerusstraat",
    "iso:country":"BE",
    "sg:address":"Homerusstraat 11",
    "sg:city":"Anderlecht/anderlecht",
    "sg:orig_category":"Landmeters and schatters",
    "sg:phone":"+32 2 522 91 35",
    "sg:postcode":"1070",
    "sg:province":"Bruxelles-Capitale",
    "wof:name":"Bureau Van Audenhove",
    "wof:placetype":"venue"
},
  "geometry": {"coordinates":[4.2864809036,50.8443603516],"type":"Point"}
}