{
  "type": "Feature",
  "properties": {
    "iso:country":"BE",
    "sg:address":"Avenue De L'universit\u00e9 104 Box 6",
    "sg:city":"Bruxelles (ixelles)",
    "sg:classifiers":[
        {
            "category":"Health Services",
            "subcategory":"Health Practitioner",
            "type":"Services"
        }
    ],
    "sg:phone":"+32 2 649 76 07",
    "sg:postcode":"1050",
    "sg:province":"Bruxelles-Capitale",
    "sg:tags":[
        "psychologist"
    ],
    "wof:name":"Ericx U",
    "wof:placetype":"venue"
},
  "geometry": {"coordinates":[4.3846721649,50.8137664795],"type":"Point"}
}