{
  "type": "Feature",
  "properties": {
    "addr:full":"Kempenstraat 89 Diepenbeek Limburg 3590",
    "addr:housenumber":"89",
    "addr:postcode":"3590",
    "addr:street":"Kempenstraat",
    "iso:country":"BE",
    "sg:address":"Kempenstraat 89",
    "sg:city":"Diepenbeek",
    "sg:classifiers":[
        {
            "category":"Building & Trades",
            "subcategory":"Landscaping Services",
            "type":"Services"
        }
    ],
    "sg:phone":"+32 11 32 16 65",
    "sg:postcode":"3590",
    "sg:province":"Limburg",
    "sg:tags":[
        "architect",
        "landscape"
    ],
    "wof:name":"Beelen P",
    "wof:placetype":"venue"
},
  "geometry": {"coordinates":[5.4282159805,50.9239196777],"type":"Point"}
}