{
  "type": "Feature",
  "properties": {
    "iso:country":"BE",
    "sg:address":"Rue Du Viveroux 1",
    "sg:city":"Philippeville",
    "sg:orig_category":"Zand and grindontginning",
    "sg:phone":"+32 71 66 63 10",
    "sg:postcode":"5600",
    "sg:province":"Namur",
    "wof:name":"Dolomie De Villers Gambon",
    "wof:placetype":"venue"
},
  "geometry": {"coordinates":[4.6242198944,50.1718673706],"type":"Point"}
}