{
  "type": "Feature",
  "properties": {
    "addr:full":"Sportstraat 22 Gent Oost-Vlaanderen 9000",
    "addr:housenumber":"22",
    "addr:postcode":"9000",
    "addr:street":"Sportstraat;Oost-Vlaanderen",
    "iso:country":"BE",
    "sg:address":"Sportstraat 22",
    "sg:city":"Gent",
    "sg:classifiers":[
        {
            "category":"Insurance",
            "subcategory":"Insurance Agent",
            "type":"Services"
        }
    ],
    "sg:phone":"+32 9 222 57 81",
    "sg:postcode":"9000",
    "sg:province":"Oost-Vlaanderen",
    "sg:tags":[
        "broker"
    ],
    "wof:name":"Delens R & Zonen",
    "wof:placetype":"venue"
},
  "geometry": {"coordinates":[3.709813118,51.0424804688],"type":"Point"}
}