{
  "type": "Feature",
  "properties": {
    "addr:full":"Boomstraat 65 Bornem Antwerpen 2880",
    "addr:housenumber":"65",
    "addr:postcode":"2880",
    "addr:street":"Boomstraat",
    "iso:country":"BE",
    "sg:address":"Boomstraat 65",
    "sg:city":"Bornem",
    "sg:classifiers":[
        {
            "category":"Shopping",
            "subcategory":"Jewelry",
            "type":"Retail Goods"
        }
    ],
    "sg:phone":"+32 3 889 10 27",
    "sg:postcode":"2880",
    "sg:province":"Antwerpen",
    "sg:tags":[
        "jeweller",
        "-"
    ],
    "wof:name":"Vanderstraeten",
    "wof:placetype":"venue"
},
  "geometry": {"coordinates":[4.2332839966,51.0969085693],"type":"Point"}
}