{
  "type": "Feature",
  "properties": {
    "iso:country":"BE",
    "sg:address":"Avenue Des Princes Braban\u00c7ons 51",
    "sg:city":"Watermaal-bosvoorde",
    "sg:orig_category":"Informaticaconsulenten",
    "sg:phone":"+32 2 672 79 20",
    "sg:postcode":"1170",
    "sg:province":"Bruxelles-Capitale",
    "wof:name":"Dynam'hit",
    "wof:placetype":"venue"
},
  "geometry": {"coordinates":[4.4149990082,50.8101539612],"type":"Point"}
}