{
  "type": "Feature",
  "properties": {
    "iso:country":"BE",
    "sg:address":"Schapenweg 83",
    "sg:city":"Overijse",
    "sg:orig_category":"Producteurs de fruits",
    "sg:phone":"+32 2 687 78 49",
    "sg:postcode":"3090",
    "sg:province":"Vlaams-Brabant",
    "wof:name":"Marcel Charlier",
    "wof:placetype":"venue"
},
  "geometry": {"coordinates":[4.5508542061,50.7943649292],"type":"Point"}
}