{
  "type": "Feature",
  "properties": {
    "addr:full":"Rue Vital Fran\u00c7oisse 205 Charleroi Hainaut 6001",
    "addr:housenumber":"205",
    "addr:postcode":"6001",
    "addr:street":"Rue Vital Franc\u0327Oisse;Hainaut",
    "iso:country":"BE",
    "sg:address":"Rue Vital Fran\u00c7oisse 205",
    "sg:city":"Charleroi",
    "sg:orig_category":"Elektrische installaties voor woningen Industri\u00eble elektrische installaties Procesbesturingssystemen",
    "sg:phone":"+32 71 44 65 11",
    "sg:postcode":"6001",
    "sg:province":"Hainaut",
    "wof:name":"Cegelec Acec",
    "wof:placetype":"venue"
},
  "geometry": {"coordinates":[4.4254899025,50.4038009644],"type":"Point"}
}