{
  "type": "Feature",
  "properties": {
    "addr:full":"Grand-aaz 43 Oupeye Li\u00e8ge 4680",
    "addr:housenumber":"43",
    "addr:postcode":"4680",
    "addr:street":"Grand-Aaz",
    "iso:country":"BE",
    "sg:address":"Grand-aaz 43",
    "sg:city":"Oupeye",
    "sg:classifiers":[
        {
            "category":"Professional",
            "subcategory":"Accounting & Tax Preparation",
            "type":"Services"
        }
    ],
    "sg:phone":"+32 4 278 90 00",
    "sg:postcode":"4680",
    "sg:province":"Li\u00e8ge",
    "sg:tags":[
        "bookkeeper"
    ],
    "wof:name":"Comptabilit\u00e9-fiscalit\u00e9 Jmf Sprl",
    "wof:placetype":"venue"
},
  "geometry": {"coordinates":[5.6106500626,50.7157287598],"type":"Point"}
}