{
  "type": "Feature",
  "properties": {
    "iso:country":"BE",
    "sg:address":"Duinenstraat 170",
    "sg:city":"Oostende",
    "sg:classifiers":[
        {
            "category":"Real Estate",
            "subcategory":"Developer",
            "type":"Services"
        }
    ],
    "sg:phone":"+32 59 80 26 48",
    "sg:postcode":"8400",
    "sg:province":"West-Vlaanderen",
    "sg:tags":[
        "project"
    ],
    "wof:name":"Vanderwee",
    "wof:placetype":"venue"
},
  "geometry": {"coordinates":[2.8595299721,51.2061500549],"type":"Point"}
}