{
  "type": "Feature",
  "properties": {
    "iso:country":"BE",
    "sg:address":"Amerikalei 169-171",
    "sg:city":"Antwerpen",
    "sg:classifiers":[
        {
            "category":"Manufacturing",
            "subcategory":"Building Materials",
            "type":"Manufacturing & Wholesale Goods"
        }
    ],
    "sg:phone":"+32 3 238 72 72",
    "sg:postcode":"2000",
    "sg:province":"Antwerpen",
    "sg:tags":[
        "fixture",
        "store"
    ],
    "wof:name":"Allshop Bvba",
    "wof:placetype":"venue"
},
  "geometry": {"coordinates":[4.3929448128,51.2055778503],"type":"Point"}
}