{
  "type": "Feature",
  "properties": {
    "addr:full":"Wetterse Steenweg 3 Oosterzele Oost-Vlaanderen 9860",
    "addr:housenumber":"3",
    "addr:postcode":"9860",
    "addr:street":"Steenweg;Oost-Vlaanderen",
    "iso:country":"BE",
    "sg:address":"Wetterse Steenweg 3",
    "sg:city":"Oosterzele",
    "sg:classifiers":[
        {
            "category":"Building & Trades",
            "subcategory":"Landscaping Services",
            "type":"Services"
        }
    ],
    "sg:phone":"+32 9 362 59 92",
    "sg:postcode":"9860",
    "sg:province":"Oost-Vlaanderen",
    "sg:tags":[
        "slaughterer"
    ],
    "wof:name":"Gillis R",
    "wof:placetype":"venue"
},
  "geometry": {"coordinates":[3.8102059364,50.9577255249],"type":"Point"}
}