{
  "type": "Feature",
  "properties": {
    "iso:country":"BE",
    "sg:address":"Chauss\u00c9e De Charleroi 91",
    "sg:city":"Charleroi",
    "sg:orig_category":"Services de s\u00e9curit\u00e9 and entreprises de gardiennage. Constructions r\u00e9sidentielles sp\u00e9cifiques",
    "sg:phone":"+32 71 28 76 16",
    "sg:postcode":"6060",
    "sg:province":"Hainaut",
    "wof:name":"G.p.d.s.",
    "wof:placetype":"venue"
},
  "geometry": {"coordinates":[4.4738240242,50.4016075134],"type":"Point"}
}