{
  "type": "Feature",
  "properties": {
    "addr:full":"Avenue Venizelos 42 Anderlecht/anderlecht Bruxelles-Capitale 1070",
    "addr:housenumber":"42",
    "addr:postcode":"1070",
    "addr:street":"Avenue Venizelos",
    "iso:country":"BE",
    "sg:address":"Avenue Venizelos 42",
    "sg:city":"Anderlecht/anderlecht",
    "sg:orig_category":"M\u00e9decins and sp\u00e9cialistes",
    "sg:phone":"+32 2 523 25 04",
    "sg:postcode":"1070",
    "sg:province":"Bruxelles-Capitale",
    "wof:name":"Ren\u00c9 Jacquemyns",
    "wof:placetype":"venue"
},
  "geometry": {"coordinates":[4.2935290337,50.8235321045],"type":"Point"}
}