{
  "type": "Feature",
  "properties": {
    "addr:full":"Damplein 10 Antwerpen Antwerpen 2060",
    "addr:housenumber":"10",
    "addr:postcode":"2060",
    "addr:street":"Damplein",
    "iso:country":"BE",
    "sg:address":"Damplein 10",
    "sg:city":"Antwerpen",
    "sg:orig_category":"Assurances. Bureaux de poste",
    "sg:phone":"+32 3 232 11 53",
    "sg:postcode":"2060",
    "sg:province":"Antwerpen",
    "wof:name":"De Post",
    "wof:placetype":"venue"
},
  "geometry": {"coordinates":[4.4253330231,51.2318992615],"type":"Point"}
}