{
  "type": "Feature",
  "properties": {
    "addr:full":"Bodegemstraat 88 Dilbeek Vlaams-Brabant 1700",
    "addr:housenumber":"88",
    "addr:postcode":"1700",
    "addr:street":"Bodegemstraat",
    "iso:country":"BE",
    "sg:address":"Bodegemstraat 88",
    "sg:city":"Dilbeek",
    "sg:classifiers":[
        {
            "category":"Professional",
            "subcategory":"Management & Consulting",
            "type":"Services"
        }
    ],
    "sg:phone":"+32 2 532 21 12",
    "sg:postcode":"1700",
    "sg:province":"Vlaams-Brabant",
    "sg:tags":[
        "-",
        "processing",
        "data",
        "consultant"
    ],
    "wof:name":"Fv Consult Nv",
    "wof:placetype":"venue"
},
  "geometry": {"coordinates":[4.236782074,50.844997406],"type":"Point"}
}