{
  "type": "Feature",
  "properties": {
    "addr:full":"Rue Du Pirchat 41 Orp-jauche (orp-le-grand) Brabant Wallon 1350",
    "addr:housenumber":"41",
    "addr:postcode":"1350",
    "addr:street":"Rue Du Pirchat",
    "iso:country":"BE",
    "sg:address":"Rue Du Pirchat 41",
    "sg:city":"Orp-jauche (orp-le-grand)",
    "sg:classifiers":[
        {
            "category":"Wholesale",
            "subcategory":"Construction Materials",
            "type":"Manufacturing & Wholesale Goods"
        }
    ],
    "sg:phone":"+32 19 63 46 02",
    "sg:postcode":"1350",
    "sg:province":"Brabant Wallon",
    "sg:tags":[
        "tubing",
        "industrial"
    ],
    "wof:name":"Bis Sprl",
    "wof:placetype":"venue"
},
  "geometry": {"coordinates":[4.97920084,50.6738891602],"type":"Point"}
}