{
  "type": "Feature",
  "properties": {
    "addr:full":"Dr. Van De Perrestraat 251 Geel Antwerpen 2440",
    "addr:housenumber":"251",
    "addr:postcode":"2440",
    "addr:street":"Dr. Van De Perrestraat",
    "iso:country":"BE",
    "sg:address":"Dr. Van De Perrestraat 251",
    "sg:city":"Geel",
    "sg:orig_category":"Advocaten and juridische adviseurs",
    "sg:phone":"+32 14 58 60 44",
    "sg:postcode":"2440",
    "sg:province":"Antwerpen",
    "wof:name":"Min Berghmans",
    "wof:placetype":"venue"
},
  "geometry": {"coordinates":[4.9859571457,51.1790313721],"type":"Point"}
}