{
  "type": "Feature",
  "properties": {
    "addr:full":"Rue Leon Theodor 102 Bruxelles Bruxelles-Capitale 1090",
    "addr:housenumber":"102",
    "addr:postcode":"1090",
    "addr:street":"Rue Leon Theodor",
    "iso:country":"BE",
    "sg:address":"Rue Leon Theodor 102",
    "sg:city":"Bruxelles",
    "sg:classifiers":[
        {
            "category":"Shopping",
            "subcategory":"Pharmacy",
            "type":"Retail Goods"
        }
    ],
    "sg:phone":"+32 2 421 15 11",
    "sg:postcode":"1090",
    "sg:province":"Bruxelles-Capitale",
    "sg:tags":[
        "preparation",
        "pharmaceutical"
    ],
    "wof:name":"Pfizer S.a.",
    "wof:placetype":"venue"
},
  "geometry": {"coordinates":[4.3278031349,50.8759155273],"type":"Point"}
}