{
  "type": "Feature",
  "properties": {
    "iso:country":"BE",
    "sg:address":"Rue C\u00e9sar Franck 13",
    "sg:city":"Welkenraedt",
    "sg:classifiers":[
        {
            "category":"Professional",
            "subcategory":"Accounting & Tax Preparation",
            "type":"Services"
        }
    ],
    "sg:phone":"+32 87 88 19 20",
    "sg:postcode":"4840",
    "sg:province":"Li\u00e8ge",
    "sg:tags":[
        "bookkeeper"
    ],
    "wof:name":"Johnen F",
    "wof:placetype":"venue"
},
  "geometry": {"coordinates":[5.9614748955,50.6632881165],"type":"Point"}
}