{
  "type": "Feature",
  "properties": {
    "iso:country":"BE",
    "sg:address":"Urselweg 55",
    "sg:city":"Maldegem",
    "sg:orig_category":"SMEEDWERK, METAALBEWERKING AND POEDERMETALLURGIE",
    "sg:phone":"+32 50 71 70 87",
    "sg:postcode":"9990",
    "sg:province":"Oost-Vlaanderen",
    "wof:name":"Eeckhout",
    "wof:placetype":"venue"
},
  "geometry": {"coordinates":[3.4660410881,51.174823761],"type":"Point"}
}