{
  "type": "Feature",
  "properties": {
    "addr:full":"Grand'route 252 Flemalle Li\u00e8ge 4400",
    "addr:housenumber":"252",
    "addr:postcode":"4400",
    "addr:street":"Grand'Route",
    "iso:country":"BE",
    "sg:address":"Grand'route 252",
    "sg:city":"Flemalle",
    "sg:orig_category":"M\u00e9decins and sp\u00e9cialistes",
    "sg:phone":"+32 4 233 56 84",
    "sg:postcode":"4400",
    "sg:province":"Li\u00e8ge",
    "wof:name":"Renato Pace",
    "wof:placetype":"venue"
},
  "geometry": {"coordinates":[5.4492239952,50.5986442566],"type":"Point"}
}