{
  "type": "Feature",
  "properties": {
    "iso:country":"BE",
    "sg:address":"A. Heymanstraat 109",
    "sg:city":"Temse",
    "sg:orig_category":"Autoverhuur",
    "sg:phone":"+32 3 771 23 08",
    "sg:postcode":"9140",
    "sg:province":"Oost-Vlaanderen",
    "wof:name":"Kuppens Luc",
    "wof:placetype":"venue"
},
  "geometry": {"coordinates":[4.2143149376,51.1247558594],"type":"Point"}
}