{
  "type": "Feature",
  "properties": {
    "addr:full":"Oudenburgsesteenweg 80 Oostende West-Vlaanderen 8400",
    "addr:housenumber":"80",
    "addr:postcode":"8400",
    "addr:street":"Oudenburgsesteenweg",
    "iso:country":"BE",
    "sg:address":"Oudenburgsesteenweg 80",
    "sg:city":"Oostende",
    "sg:orig_category":"Herstellingswinkels voor diverse persoonlijke and huishoudartikelen",
    "sg:phone":"+32 59 70 33 20",
    "sg:postcode":"8400",
    "sg:province":"West-Vlaanderen",
    "wof:name":"Joseph Demaeght",
    "wof:placetype":"venue"
},
  "geometry": {"coordinates":[2.9588398933,51.2196617126],"type":"Point"}
}