{
  "type": "Feature",
  "properties": {
    "addr:full":"Rue L\u00e9opold 2 Herve Li\u00e8ge 4650",
    "addr:housenumber":"2",
    "addr:postcode":"4650",
    "addr:street":"Rue Le\u0301Opold",
    "iso:country":"BE",
    "sg:address":"Rue L\u00e9opold 2",
    "sg:city":"Herve",
    "sg:classifiers":[
        {
            "category":"Shopping",
            "subcategory":"Beauty & Cosmetics",
            "type":"Retail Goods"
        }
    ],
    "sg:phone":"+32 87 67 47 12",
    "sg:postcode":"4650",
    "sg:province":"Li\u00e8ge",
    "sg:tags":[
        "-",
        "perfumery"
    ],
    "wof:name":"Tiffani",
    "wof:placetype":"venue"
},
  "geometry": {"coordinates":[5.7938899994,50.6395721436],"type":"Point"}
}