{
  "type": "Feature",
  "properties": {
    "addr:full":"Smalle Heerweg 95 Lochristi Oost-Vlaanderen 9080",
    "addr:housenumber":"95",
    "addr:postcode":"9080",
    "addr:street":"Smalle Heerweg",
    "iso:country":"BE",
    "sg:address":"Smalle Heerweg 95",
    "sg:city":"Lochristi",
    "sg:classifiers":[
        {
            "category":"Wholesale",
            "subcategory":"Plants",
            "type":"Manufacturing & Wholesale Goods"
        }
    ],
    "sg:phone":"+32 9 355 55 05",
    "sg:postcode":"9080",
    "sg:province":"Oost-Vlaanderen",
    "sg:tags":[
        "whol",
        "flower",
        "-",
        "grower"
    ],
    "wof:name":"Neven G",
    "wof:placetype":"venue"
},
  "geometry": {"coordinates":[3.8133249283,51.0930519104],"type":"Point"}
}