{
  "type": "Feature",
  "properties": {
    "addr:full":"Nelisveld 1 Kinrooi Limburg 3640",
    "addr:housenumber":"1",
    "addr:postcode":"3640",
    "addr:street":"Nelisveld",
    "iso:country":"BE",
    "sg:address":"Nelisveld 1",
    "sg:city":"Kinrooi",
    "sg:classifiers":[
        {
            "category":"Personal",
            "subcategory":"Beauty Salon",
            "type":"Services"
        }
    ],
    "sg:phone":"+32 89 70 25 47",
    "sg:postcode":"3640",
    "sg:province":"Limburg",
    "sg:tags":[
        "lady",
        "-",
        "hairdressing"
    ],
    "wof:name":"Marie-therese",
    "wof:placetype":"venue"
},
  "geometry": {"coordinates":[5.7396459579,51.1431808472],"type":"Point"}
}