{
  "type": "Feature",
  "properties": {
    "addr:full":"Gemeentestraat 23 Mechelen Antwerpen 2811",
    "addr:housenumber":"23",
    "addr:postcode":"2811",
    "addr:street":"Gemeentestraat",
    "iso:country":"BE",
    "sg:address":"Gemeentestraat 23",
    "sg:city":"Mechelen",
    "sg:orig_category":"Banques and organismes de cr\u00e9dit",
    "sg:phone":"+32 15 41 73 77",
    "sg:postcode":"2811",
    "sg:province":"Antwerpen",
    "wof:name":"Fortis",
    "wof:placetype":"venue"
},
  "geometry": {"coordinates":[4.4441900253,51.0144958496],"type":"Point"}
}