{
  "type": "Feature",
  "properties": {
    "addr:full":"Rue De L\u00b4yser 385 Ans Li\u00e8ge 4430",
    "addr:housenumber":"385",
    "addr:postcode":"4430",
    "addr:street":"Rue De L\u00b4Yser",
    "iso:country":"BE",
    "sg:address":"Rue De L\u00b4yser 385",
    "sg:city":"Ans",
    "sg:orig_category":"Kapsalons",
    "sg:phone":"+32 4 247 57 11",
    "sg:postcode":"4430",
    "sg:province":"Li\u00e8ge",
    "wof:name":"Camille Albane",
    "wof:placetype":"venue"
},
  "geometry": {"coordinates":[5.5138039589,50.6627616882],"type":"Point"}
}