{
  "type": "Feature",
  "properties": {
    "addr:full":"Panoramastraat 24 Holsbeek Vlaams-Brabant 3221",
    "addr:housenumber":"24",
    "addr:postcode":"3221",
    "addr:street":"Panoramastraat",
    "iso:country":"BE",
    "sg:address":"Panoramastraat 24",
    "sg:city":"Holsbeek",
    "sg:orig_category":"Artiesten and kunstenaars",
    "sg:phone":"+32 16 56 37 83",
    "sg:postcode":"3221",
    "sg:province":"Vlaams-Brabant",
    "wof:name":"Leopold Geysen",
    "wof:placetype":"venue"
},
  "geometry": {"coordinates":[4.8221120834,50.9505729675],"type":"Point"}
}