{
  "type": "Feature",
  "properties": {
    "iso:country":"BE",
    "sg:address":"Place Du March\u00e9 57",
    "sg:city":"Jalhay (sart)",
    "sg:classifiers":[
        {
            "category":"Health Services",
            "subcategory":"Health Practitioner",
            "type":"Services"
        }
    ],
    "sg:phone":"+32 87 47 44 30",
    "sg:postcode":"4845",
    "sg:province":"Li\u00e8ge",
    "sg:tags":[
        "osteopath"
    ],
    "wof:name":"Arnoldy Philippe",
    "wof:placetype":"venue"
},
  "geometry": {"coordinates":[5.9721851349,50.5571899414],"type":"Point"}
}