{
  "type": "Feature",
  "properties": {
    "addr:full":"Geldhofstraat 66 Aalst Oost-Vlaanderen 9300",
    "addr:housenumber":"66",
    "addr:postcode":"9300",
    "addr:street":"Geldhofstraat",
    "iso:country":"BE",
    "sg:address":"Geldhofstraat 66",
    "sg:city":"Aalst",
    "sg:orig_category":"Services de Nettoyage and de D\u00e9sinfection",
    "sg:phone":"+32 53 77 48 88",
    "sg:postcode":"9300",
    "sg:province":"Oost-Vlaanderen",
    "wof:name":"Augustin De Schutter",
    "wof:placetype":"venue"
},
  "geometry": {"coordinates":[4.0498561859,50.9490089417],"type":"Point"}
}