{
  "type": "Feature",
  "properties": {
    "addr:full":"Route De Namur 154 Hannut (avin) Li\u00e8ge 4280",
    "addr:housenumber":"154",
    "addr:postcode":"4280",
    "addr:street":"Route De Namur;Avin",
    "iso:country":"BE",
    "sg:address":"Route De Namur 154",
    "sg:city":"Hannut (avin)",
    "sg:classifiers":[
        {
            "category":"Autos & Motor Vehicles",
            "subcategory":"Automobile Sales",
            "type":"Retail Goods"
        }
    ],
    "sg:phone":"+32 19 69 95 95",
    "sg:postcode":"4280",
    "sg:province":"Li\u00e8ge",
    "sg:tags":[
        "delivery",
        "-",
        "used",
        "van",
        "truck"
    ],
    "wof:name":"Wilmet Cars & Trucks",
    "wof:placetype":"venue"
},
  "geometry": {"coordinates":[5.0796570778,50.6173210144],"type":"Point"}
}