{
  "type": "Feature",
  "properties": {
    "addr:full":"Driesstraat 1bc Lokeren Oost-Vlaanderen 9160",
    "addr:housenumber":"1bc",
    "addr:postcode":"9160",
    "addr:street":"Driesstraat",
    "iso:country":"BE",
    "sg:address":"Driesstraat 1bc",
    "sg:city":"Lokeren",
    "sg:orig_category":"Boekhouders",
    "sg:phone":"+32 9 348 08 84",
    "sg:postcode":"9160",
    "sg:province":"Oost-Vlaanderen",
    "wof:name":"Eddy De Meersman",
    "wof:placetype":"venue"
},
  "geometry": {"coordinates":[4.0019140244,51.0953865051],"type":"Point"}
}