{
  "type": "Feature",
  "properties": {
    "addr:full":"Dennenlaan 27 Antwerpen (wilrijk) Antwerpen 2610",
    "addr:housenumber":"27",
    "addr:postcode":"2610",
    "addr:street":"Dennenlaan;Antwerpen",
    "iso:country":"BE",
    "sg:address":"Dennenlaan 27",
    "sg:city":"Antwerpen (wilrijk)",
    "sg:classifiers":[
        {
            "category":"Taxi",
            "type":"Transportation"
        }
    ],
    "sg:phone":"+32 3 286 86 06",
    "sg:postcode":"2610",
    "sg:province":"Antwerpen",
    "sg:tags":[
        "air"
    ],
    "wof:name":"Flying Partners Cv",
    "wof:placetype":"venue"
},
  "geometry": {"coordinates":[4.4074702263,51.1762619019],"type":"Point"}
}