{
  "type": "Feature",
  "properties": {
    "iso:country":"BE",
    "sg:address":"Langelede 96",
    "sg:city":"Wachtebeke",
    "sg:classifiers":[
        {
            "category":"Home & Garden",
            "subcategory":"Building Materials",
            "type":"Retail Goods"
        }
    ],
    "sg:phone":"+32 9 342 79 68",
    "sg:postcode":"9185",
    "sg:province":"Oost-Vlaanderen",
    "sg:tags":[
        "window"
    ],
    "wof:name":"Derasun Bvba",
    "wof:placetype":"venue"
},
  "geometry": {"coordinates":[3.8562560081,51.1902770996],"type":"Point"}
}