{
  "type": "Feature",
  "properties": {
    "addr:full":"Rue Appaum\u00e9e 54 Charleroi (ransart) Hainaut 6043",
    "addr:housenumber":"54",
    "addr:postcode":"6043",
    "addr:street":"Rue Appaume\u0301E",
    "iso:country":"BE",
    "sg:address":"Rue Appaum\u00e9e 54",
    "sg:city":"Charleroi (ransart)",
    "sg:orig_category":"Bonsa\u00ef",
    "sg:phone":"+32 71 36 66 05",
    "sg:postcode":"6043",
    "sg:province":"Hainaut",
    "wof:name":"Bonsa\u00ef Club Carolor\u00e9gien Asbl",
    "wof:placetype":"venue"
},
  "geometry": {"coordinates":[4.4839549065,50.4479637146],"type":"Point"}
}