{
  "type": "Feature",
  "properties": {
    "iso:country":"BE",
    "sg:address":"Daknammolenstraat 94",
    "sg:city":"Lokeren",
    "sg:orig_category":"Paramedische behandelingen",
    "sg:phone":"+32 9 348 64 01",
    "sg:postcode":"9160",
    "sg:province":"Oost-Vlaanderen",
    "wof:name":"C. De Ryck",
    "wof:placetype":"venue"
},
  "geometry": {"coordinates":[3.9922800064,51.1178016663],"type":"Point"}
}