{
  "type": "Feature",
  "properties": {
    "iso:country":"BE",
    "sg:address":"Rue De La Bossi\u00e8re 3",
    "sg:city":"Anh\u00e9e",
    "sg:classifiers":[
        {
            "category":"Professional",
            "subcategory":"Accounting & Tax Preparation",
            "type":"Services"
        }
    ],
    "sg:phone":"+32 82 61 24 52",
    "sg:postcode":"5537",
    "sg:province":"Namur",
    "sg:tags":[
        "bookkeeper"
    ],
    "wof:name":"Tasiaux P",
    "wof:placetype":"venue"
},
  "geometry": {"coordinates":[4.8750801086,50.3176689148],"type":"Point"}
}