{
  "type": "Feature",
  "properties": {
    "addr:full":"Hermanne 26 Durbuy Luxembourg 6941",
    "addr:housenumber":"26",
    "addr:postcode":"6941",
    "addr:street":"Hermanne",
    "iso:country":"BE",
    "sg:address":"Hermanne 26",
    "sg:city":"Durbuy",
    "sg:orig_category":"Rundveehouders",
    "sg:phone":"+32 86 38 81 41",
    "sg:postcode":"6941",
    "sg:province":"Luxembourg",
    "wof:name":"Gathy Edgard & Rene",
    "wof:placetype":"venue"
},
  "geometry": {"coordinates":[5.524184227,50.3770332336],"type":"Point"}
}