{
  "type": "Feature",
  "properties": {
    "addr:full":"Noordersingel 28 Antwerpen (borgerhout) Antwerpen 2140",
    "addr:housenumber":"28",
    "addr:postcode":"2140",
    "addr:street":"Noordersingel",
    "iso:country":"BE",
    "sg:address":"Noordersingel 28",
    "sg:city":"Antwerpen (borgerhout)",
    "sg:classifiers":[
        {
            "category":"Community Center",
            "subcategory":"Youth",
            "type":"Public Place"
        }
    ],
    "sg:phone":"+32 3 217 24 40",
    "sg:postcode":"2140",
    "sg:province":"Antwerpen",
    "sg:tags":[
        "club"
    ],
    "wof:name":"Jeugdcentrum Ter Lo",
    "wof:placetype":"venue"
},
  "geometry": {"coordinates":[4.4205598831,51.2346382141],"type":"Point"}
}