{
  "type": "Feature",
  "properties": {
    "addr:full":"Avenue Jean D'avesnes 1 Mons Hainaut 7000",
    "addr:housenumber":"1",
    "addr:postcode":"7000",
    "addr:street":"Avenue Jean D'Avesnes;Hainaut",
    "iso:country":"BE",
    "sg:address":"Avenue Jean D'avesnes 1",
    "sg:city":"Mons",
    "sg:classifiers":[
        {
            "category":"Professional",
            "subcategory":"Computer Services",
            "type":"Services"
        }
    ],
    "sg:phone":"+32 65 40 11 11",
    "sg:postcode":"7000",
    "sg:province":"Hainaut",
    "sg:tags":[
        "-",
        "processing",
        "data",
        "software"
    ],
    "wof:name":"Integral-tip Group Nv",
    "wof:placetype":"venue"
},
  "geometry": {"coordinates":[3.9489250183,50.447227478],"type":"Point"}
}