{
  "type": "Feature",
  "properties": {
    "addr:full":"Steenweg 126 Lanaken (rekem) Limburg 3621",
    "addr:housenumber":"126",
    "addr:postcode":"3621",
    "addr:street":"Steenweg",
    "iso:country":"BE",
    "sg:address":"Steenweg 126",
    "sg:city":"Lanaken (rekem)",
    "sg:classifiers":[
        {
            "category":"Shopping",
            "subcategory":"Crafts & Fabrics",
            "type":"Retail Goods"
        }
    ],
    "sg:phone":"+32 89 71 30 91",
    "sg:postcode":"3621",
    "sg:province":"Limburg",
    "sg:tags":[
        "silk",
        "-"
    ],
    "wof:name":"De Schaar",
    "wof:placetype":"venue"
},
  "geometry": {"coordinates":[5.685836792,50.9219665527],"type":"Point"}
}