{
  "type": "Feature",
  "properties": {
    "addr:full":"Wondelgemstraat 62 Gent Oost-Vlaanderen 9000",
    "addr:housenumber":"62",
    "addr:postcode":"9000",
    "addr:street":"Wondelgemstraat;Oost-Vlaanderen",
    "iso:country":"BE",
    "sg:address":"Wondelgemstraat 62",
    "sg:city":"Gent",
    "sg:classifiers":[
        {
            "category":"Home & Garden",
            "subcategory":"Carpets & Floor Coverings",
            "type":"Retail Goods"
        }
    ],
    "sg:phone":"+32 9 225 49 15",
    "sg:postcode":"9000",
    "sg:province":"Oost-Vlaanderen",
    "sg:tags":[
        "-",
        "rug"
    ],
    "wof:name":"Sierjacobs Bvba",
    "wof:placetype":"venue"
},
  "geometry": {"coordinates":[3.7103440762,51.0621566772],"type":"Point"}
}