{
  "type": "Feature",
  "properties": {
    "iso:country":"BE",
    "sg:address":"Brugsesteenweg 153a",
    "sg:city":"Roeselare",
    "sg:orig_category":"Jardinage",
    "sg:phone":"+32 51 24 62 23",
    "sg:postcode":"8800",
    "sg:province":"West-Vlaanderen",
    "wof:name":"Eurofish",
    "wof:placetype":"venue"
},
  "geometry": {"coordinates":[3.1215450764,50.9551582336],"type":"Point"}
}