{
  "type": "Feature",
  "properties": {
    "iso:country":"BE",
    "sg:address":"Rue D'assenois 92",
    "sg:city":"Bastogne",
    "sg:orig_category":"Bouwmaterialen Gh",
    "sg:phone":"+32 61 21 18 10",
    "sg:postcode":"6600",
    "sg:province":"Luxembourg",
    "wof:name":"Grandhenry",
    "wof:placetype":"venue"
},
  "geometry": {"coordinates":[5.7083501816,49.9939842224],"type":"Point"}
}