{
  "type": "Feature",
  "properties": {
    "iso:country":"BE",
    "sg:address":"Rue Royale 50",
    "sg:city":"Leuze-en-hainaut (tourpes)",
    "sg:classifiers":[
        {
            "category":"Wholesale",
            "subcategory":"Wine & Distilled Alcoholic Beverages",
            "type":"Manufacturing & Wholesale Goods"
        }
    ],
    "sg:phone":"+32 69 67 11 53",
    "sg:postcode":"7904",
    "sg:province":"Hainaut",
    "sg:tags":[
        "whol",
        "-",
        "spirit",
        "mfg"
    ],
    "wof:name":"Vin Sur Vin",
    "wof:placetype":"venue"
},
  "geometry": {"coordinates":[3.6489169598,50.5744247437],"type":"Point"}
}