{
  "type": "Feature",
  "properties": {
    "iso:country":"BE",
    "sg:address":"Sint-gummarusstraat 6",
    "sg:city":"Antwerpen",
    "sg:classifiers":[
        {
            "category":"Retail",
            "subcategory":"Self-service Laundry",
            "type":"Services"
        }
    ],
    "sg:phone":"+32 3 213 17 97",
    "sg:postcode":"2060",
    "sg:province":"Antwerpen",
    "sg:tags":[
        "-",
        "outfit",
        "communion",
        "wear",
        "bridal",
        "rental",
        "formal"
    ],
    "wof:name":"Cachet Cvba",
    "wof:placetype":"venue"
},
  "geometry": {"coordinates":[4.4190330505,51.2246589661],"type":"Point"}
}