{
  "type": "Feature",
  "properties": {
    "iso:country":"BE",
    "sg:address":"Deken Dolsstraat 75",
    "sg:city":"Hamont-achel",
    "sg:orig_category":"Cr\u00e9meries",
    "sg:phone":"+32 11 62 12 22",
    "sg:postcode":"3930",
    "sg:province":"Limburg",
    "wof:name":"Etienne Meeuwissen",
    "wof:placetype":"venue"
},
  "geometry": {"coordinates":[5.5450549126,51.2511863708],"type":"Point"}
}