{
  "type": "Feature",
  "properties": {
    "iso:country":"BE",
    "sg:address":"Hoogstraat 6",
    "sg:city":"Duffel",
    "sg:classifiers":[
        {
            "category":"Personal",
            "subcategory":"Beauty Salon",
            "type":"Services"
        }
    ],
    "sg:phone":"+32 15 31 21 25",
    "sg:postcode":"2570",
    "sg:province":"Antwerpen",
    "sg:tags":[
        "lady",
        "-",
        "hairdressing"
    ],
    "wof:name":"Dockx E",
    "wof:placetype":"venue"
},
  "geometry": {"coordinates":[4.5151319504,51.094039917],"type":"Point"}
}