{
  "type": "Feature",
  "properties": {
    "addr:full":"Hulstbaan 143 Sint-niklaas (sinaai) Oost-Vlaanderen 9112",
    "addr:housenumber":"143",
    "addr:postcode":"9112",
    "addr:street":"Sint-Niklaas;Oost-Vlaanderen",
    "iso:country":"BE",
    "sg:address":"Hulstbaan 143",
    "sg:city":"Sint-niklaas (sinaai)",
    "sg:classifiers":[
        {
            "category":"Shopping",
            "subcategory":"Bicycles & Sporting Goods",
            "type":"Retail Goods"
        }
    ],
    "sg:phone":"+32 3 772 45 55",
    "sg:postcode":"9112",
    "sg:province":"Oost-Vlaanderen",
    "sg:tags":[
        "-"
    ],
    "wof:name":"Robyn M",
    "wof:placetype":"venue"
},
  "geometry": {"coordinates":[4.0377402306,51.1494216919],"type":"Point"}
}