{
  "type": "Feature",
  "properties": {
    "iso:country":"BE",
    "sg:address":"Ringvaartweg-wondelgem 10",
    "sg:city":"Gent",
    "sg:orig_category":"Ramassage and traitement des d\u00e9chets m\u00e9nagers",
    "sg:phone":"+32 9 257 10 80",
    "sg:postcode":"9032",
    "sg:province":"Oost-Vlaanderen",
    "wof:name":"Fa. Aclagro Recycling",
    "wof:placetype":"venue"
},
  "geometry": {"coordinates":[3.7107329369,51.0608978271],"type":"Point"}
}