{
  "type": "Feature",
  "properties": {
    "iso:country":"BE",
    "sg:address":"Geraardsbergsestraat 76-78",
    "sg:city":"Aalst",
    "sg:orig_category":"Industri\u00eble wasserijen and droogkuis",
    "sg:phone":"+32 53 78 57 32",
    "sg:postcode":"9300",
    "sg:province":"Oost-Vlaanderen",
    "wof:name":"Norge",
    "wof:placetype":"venue"
},
  "geometry": {"coordinates":[4.036907196,50.9334144592],"type":"Point"}
}