{
  "type": "Feature",
  "properties": {
    "iso:country":"BE",
    "sg:address":"Wilgenstraat 26",
    "sg:city":"Olen",
    "sg:classifiers":[
        {
            "category":"Autos & Motor Vehicles",
            "subcategory":"Automobile Sales",
            "type":"Retail Goods"
        }
    ],
    "sg:phone":"+32 14 21 02 76",
    "sg:postcode":"2250",
    "sg:province":"Antwerpen",
    "sg:tags":[
        "ceremony",
        "car"
    ],
    "wof:name":"Gilis-luc",
    "wof:placetype":"venue"
},
  "geometry": {"coordinates":[4.9029841423,51.1627693176],"type":"Point"}
}