{
  "type": "Feature",
  "properties": {
    "iso:country":"BE",
    "sg:address":"Square Coghen 2",
    "sg:city":"Ukkel",
    "sg:orig_category":"Diverse bedrijfsbeheeradviesbureaus",
    "sg:phone":"+32 2 345 21 91",
    "sg:postcode":"1180",
    "sg:province":"Bruxelles-Capitale",
    "wof:name":"Biosyntec",
    "wof:placetype":"venue"
},
  "geometry": {"coordinates":[4.339266777,50.8135070801],"type":"Point"}
}