{
  "type": "Feature",
  "properties": {
    "iso:country":"BE",
    "sg:address":"Rue Grande 23",
    "sg:city":"Farciennes",
    "sg:orig_category":"Rookartikelen",
    "sg:phone":"+32 71 40 38 33",
    "sg:postcode":"6240",
    "sg:province":"Hainaut",
    "wof:name":"Marie Ficheroulle",
    "wof:placetype":"venue"
},
  "geometry": {"coordinates":[4.5516600609,50.426700592],"type":"Point"}
}