{
  "type": "Feature",
  "properties": {
    "iso:country":"BE",
    "sg:address":"Rue Du Ch\u00e2teau 47",
    "sg:city":"Renaix",
    "sg:orig_category":"Non-Classified Establishments",
    "sg:phone":"+32 55 31 33 33",
    "sg:postcode":"9600",
    "sg:province":"Oost-Vlaanderen",
    "wof:name":"De Potter Bvba",
    "wof:placetype":"venue"
},
  "geometry": {"coordinates":[3.5963630676,50.7473831177],"type":"Point"}
}