{
  "type": "Feature",
  "properties": {
    "iso:country":"BE",
    "sg:address":"Kastanjedreef 53",
    "sg:city":"Lochristi",
    "sg:classifiers":[
        {
            "category":"Health Services",
            "subcategory":"Health Practitioner",
            "type":"Services"
        }
    ],
    "sg:phone":"+32 9 355 97 48",
    "sg:postcode":"9080",
    "sg:province":"Oost-Vlaanderen",
    "sg:tags":[
        "physiotherapist"
    ],
    "wof:name":"Neyt L",
    "wof:placetype":"venue"
},
  "geometry": {"coordinates":[3.827534914,51.0832290649],"type":"Point"}
}