{
  "type": "Feature",
  "properties": {
    "addr:full":"Steenstraat 22 Halle Vlaams-Brabant 1500",
    "addr:housenumber":"22",
    "addr:postcode":"1500",
    "addr:street":"Steenstraat",
    "iso:country":"BE",
    "sg:address":"Steenstraat 22",
    "sg:city":"Halle",
    "sg:classifiers":[
        {
            "category":"Building & Trades",
            "subcategory":"Construction",
            "type":"Services"
        }
    ],
    "sg:phone":"+32 2 361 15 39",
    "sg:postcode":"1500",
    "sg:province":"Vlaams-Brabant",
    "sg:tags":[
        "carpenter"
    ],
    "wof:name":"Vandenbosch",
    "wof:placetype":"venue"
},
  "geometry": {"coordinates":[4.2605957985,50.7150917053],"type":"Point"}
}