{
  "type": "Feature",
  "properties": {
    "addr:full":"Place Albert Ier 4 Charleroi Hainaut 6041",
    "addr:housenumber":"4",
    "addr:postcode":"6041",
    "addr:street":"Place Albert Ier;Hainaut",
    "iso:country":"BE",
    "sg:address":"Place Albert Ier 4",
    "sg:city":"Charleroi",
    "sg:orig_category":"Dameskledingzaken",
    "sg:phone":"+32 71 35 32 87",
    "sg:postcode":"6041",
    "sg:province":"Hainaut",
    "wof:name":"Maison Calvin Klein",
    "wof:placetype":"venue"
},
  "geometry": {"coordinates":[4.4409389496,50.4081344604],"type":"Point"}
}