{
  "type": "Feature",
  "properties": {
    "addr:full":"Rue Du Commerce 352 Dour Hainaut 7370",
    "addr:housenumber":"352",
    "addr:postcode":"7370",
    "addr:street":"Rue Du Commerce;Hainaut",
    "iso:country":"BE",
    "sg:address":"Rue Du Commerce 352",
    "sg:city":"Dour",
    "sg:orig_category":"Benzinestations and brandstoffen",
    "sg:phone":"+32 65 65 62 22",
    "sg:postcode":"7370",
    "sg:province":"Hainaut",
    "wof:name":"Elf",
    "wof:placetype":"venue"
},
  "geometry": {"coordinates":[3.7520399094,50.3984107971],"type":"Point"}
}