{
  "type": "Feature",
  "properties": {
    "iso:country":"BE",
    "sg:address":"Oudenaardeweg 15",
    "sg:city":"Maarkedal (etikhove)",
    "sg:classifiers":[
        {
            "category":"Insurance",
            "subcategory":"Insurance Agent",
            "type":"Services"
        }
    ],
    "sg:phone":"+32 55 30 28 81",
    "sg:postcode":"9680",
    "sg:province":"Oost-Vlaanderen",
    "sg:tags":[
        "broker"
    ],
    "wof:name":"All-insurance Nv",
    "wof:placetype":"venue"
},
  "geometry": {"coordinates":[3.6078739166,50.8222312927],"type":"Point"}
}