{
  "type": "Feature",
  "properties": {
    "iso:country":"BE",
    "sg:address":"Luikersteenweg 611b2",
    "sg:city":"Tongeren",
    "sg:orig_category":"Pain, p\u00e2tisseries and confiseries",
    "sg:phone":"+32 12 23 29 45",
    "sg:postcode":"3700",
    "sg:province":"Limburg",
    "wof:name":"Bakkerij Philda",
    "wof:placetype":"venue"
},
  "geometry": {"coordinates":[5.4735898972,50.7632217407],"type":"Point"}
}