{
  "type": "Feature",
  "properties": {
    "iso:country":"BE",
    "sg:address":"Sint-catharinastraat 88",
    "sg:city":"Stabroek",
    "sg:classifiers":[
        {
            "category":"Freight",
            "type":"Transportation"
        }
    ],
    "sg:phone":"+32 3 569 06 09",
    "sg:postcode":"2940",
    "sg:province":"Antwerpen",
    "sg:tags":[
        "-",
        "transport"
    ],
    "wof:name":"Eysackers P",
    "wof:placetype":"venue"
},
  "geometry": {"coordinates":[4.3745927811,51.3307723999],"type":"Point"}
}