{
  "type": "Feature",
  "properties": {
    "iso:country":"BE",
    "sg:address":"Rietweg 1",
    "sg:city":"Hoogstraten",
    "sg:orig_category":"Producteurs de l\u00e9gumes. Producteurs de fruits",
    "sg:phone":"+32 3 315 78 42",
    "sg:postcode":"2328",
    "sg:province":"Antwerpen",
    "wof:name":"Jan Martens",
    "wof:placetype":"venue"
},
  "geometry": {"coordinates":[4.7727608681,51.4735298157],"type":"Point"}
}