{
  "type": "Feature",
  "properties": {
    "addr:full":"Marie-jos\u00c9laan 15 Sint-lambrechts-woluwe/woluwe-saint-lambert Bruxelles-Capitale 1200",
    "addr:housenumber":"15",
    "addr:postcode":"1200",
    "addr:street":"Marie-Jose\u0301Laan",
    "iso:country":"BE",
    "sg:address":"Marie-jos\u00c9laan 15",
    "sg:city":"Sint-lambrechts-woluwe/woluwe-saint-lambert",
    "sg:orig_category":"Zalen voor culturele evenementen",
    "sg:phone":"+32 2 734 02 53",
    "sg:postcode":"1200",
    "sg:province":"Bruxelles-Capitale",
    "wof:name":"Chaos Productions",
    "wof:placetype":"venue"
},
  "geometry": {"coordinates":[4.4134588242,50.8458824158],"type":"Point"}
}