{
  "type": "Feature",
  "properties": {
    "addr:full":"Verschansingstraat 28 Antwerpen Antwerpen 2000",
    "addr:housenumber":"28",
    "addr:postcode":"2000",
    "addr:street":"Verschansingstraat",
    "iso:country":"BE",
    "sg:address":"Verschansingstraat 28",
    "sg:city":"Antwerpen",
    "sg:classifiers":[
        {
            "category":"Shopping",
            "subcategory":"Florist",
            "type":"Retail Goods"
        }
    ],
    "sg:phone":"+32 3 238 62 12",
    "sg:postcode":"2000",
    "sg:province":"Antwerpen",
    "wof:name":"Papaver",
    "wof:placetype":"venue"
},
  "geometry": {"coordinates":[4.3908619881,51.208480835],"type":"Point"}
}