{
  "type": "Feature",
  "properties": {
    "addr:full":"Kolpaartstraat 49 Maarkedal (schorisse) Oost-Vlaanderen 9688",
    "addr:housenumber":"49",
    "addr:postcode":"9688",
    "addr:street":"Kolpaartstraat",
    "iso:country":"BE",
    "sg:address":"Kolpaartstraat 49",
    "sg:city":"Maarkedal (schorisse)",
    "sg:classifiers":[
        {
            "category":"Personal",
            "subcategory":"Beauty Salon",
            "type":"Services"
        }
    ],
    "sg:phone":"+32 55 45 63 65",
    "sg:postcode":"9688",
    "sg:province":"Oost-Vlaanderen",
    "sg:tags":[
        "lady",
        "-",
        "hairdressing"
    ],
    "wof:name":"Kathleen",
    "wof:placetype":"venue"
},
  "geometry": {"coordinates":[3.6742479801,50.7983703613],"type":"Point"}
}