{
  "type": "Feature",
  "properties": {
    "iso:country":"BE",
    "sg:address":"Rue De L'eglise 17",
    "sg:city":"Ittre",
    "sg:orig_category":"Rundveehouders",
    "sg:phone":"+32 67 21 40 50",
    "sg:postcode":"1461",
    "sg:province":"Brabant Wallon",
    "wof:name":"Henri Herman",
    "wof:placetype":"venue"
},
  "geometry": {"coordinates":[4.2985358238,50.651309967],"type":"Point"}
}