{
  "type": "Feature",
  "properties": {
    "addr:full":"Heilluizerweg 2 Rijkevorsel Antwerpen 2310",
    "addr:housenumber":"2",
    "addr:postcode":"2310",
    "addr:street":"Heilluizerweg",
    "iso:country":"BE",
    "sg:address":"Heilluizerweg 2",
    "sg:city":"Rijkevorsel",
    "sg:orig_category":"Dierenartsen",
    "sg:phone":"+32 3 314 34 73",
    "sg:postcode":"2310",
    "sg:province":"Antwerpen",
    "wof:name":"Jozef Laurijssen",
    "wof:placetype":"venue"
},
  "geometry": {"coordinates":[4.7723469734,51.377494812],"type":"Point"}
}