{
  "type": "Feature",
  "properties": {
    "addr:full":"Rue Alfred Defuisseaux 1 Ans (loncin) Li\u00e8ge 4431",
    "addr:housenumber":"1",
    "addr:postcode":"4431",
    "addr:street":"Rue Alfred Defuisseaux",
    "iso:country":"BE",
    "sg:address":"Rue Alfred Defuisseaux 1",
    "sg:city":"Ans (loncin)",
    "sg:classifiers":[
        {
            "category":"Sports & Exercise",
            "subcategory":"Stables",
            "type":"Entertainment"
        }
    ],
    "sg:phone":"+32 4 246 07 73",
    "sg:postcode":"4431",
    "sg:province":"Li\u00e8ge",
    "sg:tags":[
        "riding",
        "school"
    ],
    "wof:name":"Cravache Dor\u00e9e (la)",
    "wof:placetype":"venue"
},
  "geometry": {"coordinates":[5.4938488007,50.66065979],"type":"Point"}
}