{
  "type": "Feature",
  "properties": {
    "addr:full":"Oeselgemstraat 75 Dentergem West-Vlaanderen 8720",
    "addr:housenumber":"75",
    "addr:postcode":"8720",
    "addr:street":"Oeselgemstraat",
    "iso:country":"BE",
    "sg:address":"Oeselgemstraat 75",
    "sg:city":"Dentergem",
    "sg:orig_category":"Landmeters",
    "sg:phone":"+32 56 61 04 26",
    "sg:postcode":"8720",
    "sg:province":"West-Vlaanderen",
    "wof:name":"Adlimex",
    "wof:placetype":"venue"
},
  "geometry": {"coordinates":[3.41624403,50.9306526184],"type":"Point"}
}