{
  "type": "Feature",
  "properties": {
    "iso:country":"BE",
    "sg:address":"Rue Des Deux Eglises 55",
    "sg:city":"Neupre",
    "sg:classifiers":[
        {
            "category":"Food & Beverages",
            "subcategory":"Fruits & Vegetables",
            "type":"Retail Goods"
        }
    ],
    "sg:phone":"+32 4 371 39 76",
    "sg:postcode":"4120",
    "sg:province":"Li\u00e8ge",
    "sg:tags":[
        "l\u00e9gumes"
    ],
    "wof:name":"Marc Kerckhofs",
    "wof:placetype":"venue"
},
  "geometry": {"coordinates":[5.479388237,50.5387992859],"type":"Point"}
}