{
  "type": "Feature",
  "properties": {
    "iso:country":"BE",
    "sg:address":"Oude Schapenbaan 42a",
    "sg:city":"Grimbergen",
    "sg:classifiers":[
        {
            "category":"Building & Trades",
            "subcategory":"Construction",
            "type":"Services"
        }
    ],
    "sg:phone":"+32 2 251 39 34",
    "sg:postcode":"1850",
    "sg:province":"Vlaams-Brabant",
    "sg:tags":[
        "installation",
        "-",
        "central",
        "heating"
    ],
    "wof:name":"De Jongh",
    "wof:placetype":"venue"
},
  "geometry": {"coordinates":[4.3957800865,50.9251823425],"type":"Point"}
}