{
  "type": "Feature",
  "properties": {
    "iso:country":"BE",
    "sg:address":"Rassel 187",
    "sg:city":"Wemmel",
    "sg:classifiers":[
        {
            "category":"Building & Trades",
            "subcategory":"Construction",
            "type":"Services"
        }
    ],
    "sg:phone":"+32 477 65 68 56",
    "sg:postcode":"1780",
    "sg:province":"Vlaams-Brabant",
    "sg:tags":[
        "carpenter"
    ],
    "wof:name":"Adriaens F",
    "wof:placetype":"venue"
},
  "geometry": {"coordinates":[4.2905502319,50.9084205627],"type":"Point"}
}