{
  "type": "Feature",
  "properties": {
    "addr:full":"Fabrieksstraat 145 Overpelt Limburg 3900",
    "addr:housenumber":"145",
    "addr:postcode":"3900",
    "addr:street":"Fabrieksstraat",
    "iso:country":"BE",
    "sg:address":"Fabrieksstraat 145",
    "sg:city":"Overpelt",
    "sg:classifiers":[
        {
            "category":"Military Area",
            "subcategory":"Army Base",
            "type":"Public Place"
        }
    ],
    "sg:phone":"+32 11 66 07 11",
    "sg:postcode":"3900",
    "sg:province":"Limburg",
    "sg:tags":[
        "case",
        "box",
        "bottle"
    ],
    "wof:name":"Overpelt-plascobel Nv",
    "wof:placetype":"venue"
},
  "geometry": {"coordinates":[5.3912210464,51.233581543],"type":"Point"}
}