{
  "type": "Feature",
  "properties": {
    "addr:full":"Toleindestraat 202 Lochristi Oost-Vlaanderen 9080",
    "addr:housenumber":"202",
    "addr:postcode":"9080",
    "addr:street":"Toleindestraat",
    "iso:country":"BE",
    "sg:address":"Toleindestraat 202",
    "sg:city":"Lochristi",
    "sg:orig_category":"Plantes and fleurs Gr",
    "sg:phone":"+32 9 355 69 66",
    "sg:postcode":"9080",
    "sg:province":"Oost-Vlaanderen",
    "wof:name":"Degraeve",
    "wof:placetype":"venue"
},
  "geometry": {"coordinates":[3.899668932,51.0808296204],"type":"Point"}
}