{
  "type": "Feature",
  "properties": {
    "iso:country":"BE",
    "sg:address":"Drie Eikenstraat 7",
    "sg:city":"Herentals (noorderwijk)",
    "sg:classifiers":[
        {
            "category":"Insurance",
            "subcategory":"Insurance Agent",
            "type":"Services"
        }
    ],
    "sg:phone":"+32 478 33 65 24",
    "sg:postcode":"2200",
    "sg:province":"Antwerpen",
    "sg:tags":[
        "broker"
    ],
    "wof:name":"Peeters Consulting Adviesbureau",
    "wof:placetype":"venue"
},
  "geometry": {"coordinates":[4.8240771294,51.1613235474],"type":"Point"}
}