{
  "type": "Feature",
  "properties": {
    "addr:full":"Minnezangerstraat 31 Zedelgem West-Vlaanderen 8211",
    "addr:housenumber":"31",
    "addr:postcode":"8211",
    "addr:street":"Minnezangerstraat",
    "iso:country":"BE",
    "sg:address":"Minnezangerstraat 31",
    "sg:city":"Zedelgem",
    "sg:orig_category":"Emballages en plastique Fab. Emballages en papier and carton Fab",
    "sg:phone":"+32 50 20 04 53",
    "sg:postcode":"8211",
    "sg:province":"West-Vlaanderen",
    "wof:name":"Jofa Verpakingen",
    "wof:placetype":"venue"
},
  "geometry": {"coordinates":[3.0889649391,51.1200408936],"type":"Point"}
}