{
  "type": "Feature",
  "properties": {
    "iso:country":"BE",
    "sg:address":"Rue De La Place 5",
    "sg:city":"Antoing (p\u00e9ronnes-lez-antoing)",
    "sg:classifiers":[
        {
            "category":"Structure",
            "subcategory":"Building",
            "type":"Public Place"
        }
    ],
    "sg:phone":"+32 69 44 54 10",
    "sg:postcode":"7640",
    "sg:province":"Hainaut",
    "sg:tags":[
        "door"
    ],
    "wof:name":"Menuibat Sprl",
    "wof:placetype":"venue"
},
  "geometry": {"coordinates":[3.4541790485,50.552154541],"type":"Point"}
}