{
  "type": "Feature",
  "properties": {
    "iso:country":"BE",
    "sg:address":"Battemsesteenweg 455",
    "sg:city":"Mechelen",
    "sg:orig_category":"Mat\u00e9riel de contr\u00f4le des processus industriels Fab",
    "sg:phone":"+32 15 28 76 70",
    "sg:postcode":"2800",
    "sg:province":"Antwerpen",
    "wof:name":"Basse-ten Systems",
    "wof:placetype":"venue"
},
  "geometry": {"coordinates":[4.4854397774,51.0289268494],"type":"Point"}
}