{
  "type": "Feature",
  "properties": {
    "addr:full":"Avenue Henri De Brouck\u00e8re 44-46 Bruxelles (auderghem) Bruxelles-Capitale 1160",
    "addr:postcode":"44-46;1160",
    "addr:street":"Avenue Henri De Broucke\u0300Re",
    "iso:country":"BE",
    "sg:address":"Avenue Henri De Brouck\u00e8re 44-46",
    "sg:city":"Bruxelles (auderghem)",
    "sg:classifiers":[
        {
            "category":"Building & Trades",
            "subcategory":"Electrical",
            "type":"Services"
        }
    ],
    "sg:phone":"+32 2 675 86 03",
    "sg:postcode":"1160",
    "sg:province":"Bruxelles-Capitale",
    "sg:tags":[
        "electric",
        "-",
        "housewiring",
        "contractor"
    ],
    "wof:name":"Domotique Heroes",
    "wof:placetype":"venue"
},
  "geometry": {"coordinates":[4.4232759476,50.8182754517],"type":"Point"}
}