{
  "type": "Feature",
  "properties": {
    "addr:full":"Chauss\u00c9e D'alsemberg 1031bb Ukkel/uccle Bruxelles-Capitale 1180",
    "addr:postcode":"1031bb;1180",
    "addr:street":"Chausse\u0301E D'Alsemberg",
    "iso:country":"BE",
    "sg:address":"Chauss\u00c9e D'alsemberg 1031bb",
    "sg:city":"Ukkel/uccle",
    "sg:orig_category":"Traitements param\u00e9dicaux",
    "sg:phone":"+32 2 332 13 15",
    "sg:postcode":"1180",
    "sg:province":"Bruxelles-Capitale",
    "wof:name":"G. Simar",
    "wof:placetype":"venue"
},
  "geometry": {"coordinates":[4.3257470131,50.7787322998],"type":"Point"}
}