{
  "type": "Feature",
  "properties": {
    "addr:full":"Stationsstraat 48 Pittem West-Vlaanderen 8740",
    "addr:housenumber":"48",
    "addr:postcode":"8740",
    "addr:street":"Stationsstraat",
    "iso:country":"BE",
    "sg:address":"Stationsstraat 48",
    "sg:city":"Pittem",
    "sg:orig_category":"Instituts de beaut\u00e9",
    "sg:phone":"+32 51 46 54 80",
    "sg:postcode":"8740",
    "sg:province":"West-Vlaanderen",
    "wof:name":"Instituut Belliza",
    "wof:placetype":"venue"
},
  "geometry": {"coordinates":[3.2593851089,50.9916343689],"type":"Point"}
}