{
  "type": "Feature",
  "properties": {
    "addr:full":"Knaptandstraat 79 Sint-niklaas Oost-Vlaanderen 9100",
    "addr:housenumber":"79",
    "addr:postcode":"9100",
    "addr:street":"Knaptandstraat",
    "iso:country":"BE",
    "sg:address":"Knaptandstraat 79",
    "sg:city":"Sint-niklaas",
    "sg:classifiers":[
        {
            "category":"Banks & Credit Unions",
            "subcategory":"Financial Services",
            "type":"Services"
        }
    ],
    "sg:phone":"+32 3 760 17 40",
    "sg:postcode":"9100",
    "sg:province":"Oost-Vlaanderen",
    "sg:tags":[
        "financing"
    ],
    "wof:name":"Waaskrediet Nv",
    "wof:placetype":"venue"
},
  "geometry": {"coordinates":[4.1438269615,51.1591072083],"type":"Point"}
}