{
  "type": "Feature",
  "properties": {
    "iso:country":"BE",
    "sg:address":"Nationalestraat 38",
    "sg:city":"Antwerpen",
    "sg:classifiers":[
        {
            "category":"Restaurant",
            "type":"Food & Drink"
        }
    ],
    "sg:phone":"+32 3 226 92 90",
    "sg:postcode":"2000",
    "sg:province":"Antwerpen",
    "wof:name":"Cammerpoorte",
    "wof:placetype":"venue"
},
  "geometry": {"coordinates":[4.3995699883,51.2164611816],"type":"Point"}
}