{
  "type": "Feature",
  "properties": {
    "iso:country":"BE",
    "sg:address":"Oudestraat 42",
    "sg:city":"Boortmeerbeek",
    "sg:orig_category":"Parfumeries",
    "sg:phone":"+32 16 60 52 72",
    "sg:postcode":"3190",
    "sg:province":"Vlaams-Brabant",
    "wof:name":"Natalia Ringoot",
    "wof:placetype":"venue"
},
  "geometry": {"coordinates":[4.5895838737,50.9679222107],"type":"Point"}
}