{
  "type": "Feature",
  "properties": {
    "iso:country":"BE",
    "sg:address":"Gasmeterstraat 3",
    "sg:city":"Maldegem",
    "sg:orig_category":"Non-Classified Establishments",
    "sg:phone":"+32 50 71 88 62",
    "sg:postcode":"9990",
    "sg:province":"Oost-Vlaanderen",
    "wof:name":"Diamare Belgium Bvba",
    "wof:placetype":"venue"
},
  "geometry": {"coordinates":[3.4394419193,51.2099609375],"type":"Point"}
}