{
  "type": "Feature",
  "properties": {
    "addr:full":"Nijverheidslaan 8 Maldegem Oost-Vlaanderen 9990",
    "addr:housenumber":"8",
    "addr:postcode":"9990",
    "addr:street":"Nijverheidslaan",
    "iso:country":"BE",
    "sg:address":"Nijverheidslaan 8",
    "sg:city":"Maldegem",
    "sg:classifiers":[
        {
            "category":"Airport",
            "subcategory":"International",
            "type":"Transportation"
        }
    ],
    "sg:phone":"+32 50 71 67 75",
    "sg:postcode":"9990",
    "sg:province":"Oost-Vlaanderen",
    "sg:tags":[
        "-",
        "transport"
    ],
    "wof:name":"Versluys Robert En Zoon Bvba",
    "wof:placetype":"venue"
},
  "geometry": {"coordinates":[3.4756519794,51.1955451965],"type":"Point"}
}