{
  "type": "Feature",
  "properties": {
    "addr:full":"Clos Chapelle Aux Champs 30 Box 3040 Bruxelles (woluwe-saint-lambert) Bruxelles-Capitale 1200",
    "addr:housenumber":"30 box",
    "addr:postcode":"3040;1200",
    "addr:street":"Clos Chapelle Aux Champs",
    "iso:country":"BE",
    "sg:address":"Clos Chapelle Aux Champs 30 Box 3040",
    "sg:city":"Bruxelles (woluwe-saint-lambert)",
    "sg:classifiers":[
        {
            "category":"Health Services",
            "subcategory":"Health Practitioner",
            "type":"Services"
        }
    ],
    "sg:phone":"+32 2 764 32 40",
    "sg:postcode":"1200",
    "sg:province":"Bruxelles-Capitale",
    "sg:tags":[
        "therapist",
        "speech"
    ],
    "wof:name":"Centre D'audio-phonologie Cliniques Universitaires St-luc",
    "wof:placetype":"venue"
},
  "geometry": {"coordinates":[4.4498109818,50.8496398926],"type":"Point"}
}