{
  "type": "Feature",
  "properties": {
    "iso:country":"BE",
    "sg:address":"Rue Longue 1",
    "sg:city":"Tournai",
    "sg:orig_category":"S\u00e9curit\u00e9 sociale",
    "sg:phone":"+32 69 64 83 95",
    "sg:postcode":"7502",
    "sg:province":"Hainaut",
    "wof:name":"La Prevoyante",
    "wof:placetype":"venue"
},
  "geometry": {"coordinates":[3.3073990345,50.5744781494],"type":"Point"}
}