{
  "type": "Feature",
  "properties": {
    "addr:full":"Ganzendries 72 Lubbeek (pellenberg) Vlaams-Brabant 3212",
    "addr:housenumber":"72",
    "addr:postcode":"3212",
    "addr:street":"Ganzendries",
    "iso:country":"BE",
    "sg:address":"Ganzendries 72",
    "sg:city":"Lubbeek (pellenberg)",
    "sg:classifiers":[
        {
            "category":"Home & Garden",
            "subcategory":"Household Appliances",
            "type":"Retail Goods"
        }
    ],
    "sg:phone":"+32 16 46 12 90",
    "sg:postcode":"3212",
    "sg:province":"Vlaams-Brabant",
    "sg:tags":[
        "repair",
        "stove",
        "-"
    ],
    "wof:name":"Wauters Gh",
    "wof:placetype":"venue"
},
  "geometry": {"coordinates":[4.7938070297,50.8667411804],"type":"Point"}
}