{
  "type": "Feature",
  "properties": {
    "iso:country":"BE",
    "sg:address":"Pamelstraat-oost 456",
    "sg:city":"Ninove",
    "sg:classifiers":[
        {
            "category":"Home & Garden",
            "subcategory":"Furniture",
            "type":"Retail Goods"
        }
    ],
    "sg:phone":"+32 54 33 57 54",
    "sg:postcode":"9400",
    "sg:province":"Oost-Vlaanderen",
    "sg:tags":[
        "bathroom"
    ],
    "wof:name":"Duson-joly Nv",
    "wof:placetype":"venue"
},
  "geometry": {"coordinates":[4.0377998352,50.8405952454],"type":"Point"}
}