{
  "type": "Feature",
  "properties": {
    "addr:full":"Nestor De Ti\u00e8restraat 129 Oudenaarde Oost-Vlaanderen 9700",
    "addr:housenumber":"129",
    "addr:postcode":"9700",
    "addr:street":"Nestor De Tie\u0300Restraat",
    "iso:country":"BE",
    "sg:address":"Nestor De Ti\u00e8restraat 129",
    "sg:city":"Oudenaarde",
    "sg:classifiers":[
        {
            "category":"Shopping",
            "subcategory":"Jewelry",
            "type":"Retail Goods"
        }
    ],
    "sg:phone":"+32 55 31 25 86",
    "sg:postcode":"9700",
    "sg:province":"Oost-Vlaanderen",
    "sg:tags":[
        "jeweller",
        "-"
    ],
    "wof:name":"De Rijcke P",
    "wof:placetype":"venue"
},
  "geometry": {"coordinates":[3.6185278893,50.8669967651],"type":"Point"}
}