{
  "type": "Feature",
  "properties": {
    "iso:country":"BE",
    "sg:address":"Route De Bastogne 390",
    "sg:city":"Arlon",
    "sg:classifiers":[
        {
            "category":"Insurance",
            "subcategory":"Insurance Agent",
            "type":"Services"
        }
    ],
    "sg:phone":"+32 63 22 06 53",
    "sg:postcode":"6700",
    "sg:province":"Luxembourg",
    "sg:tags":[
        "verzekeringsmakelaars",
        "expert"
    ],
    "wof:name":"Cetex",
    "wof:placetype":"venue"
},
  "geometry": {"coordinates":[5.8135142326,49.6924438477],"type":"Point"}
}