{
  "type": "Feature",
  "properties": {
    "iso:country":"BE",
    "sg:address":"Sint-jan Berchmansstraat 33",
    "sg:city":"Mol",
    "sg:orig_category":"Plomberie, chauffage and installations sanitaires",
    "sg:phone":"+32 14 31 63 87",
    "sg:postcode":"2400",
    "sg:province":"Antwerpen",
    "wof:name":"Lodewijk Vandeweyer",
    "wof:placetype":"venue"
},
  "geometry": {"coordinates":[5.1091299057,51.1857185364],"type":"Point"}
}