{
  "type": "Feature",
  "properties": {
    "addr:full":"Rue Du Mont D'or 14 Tournai Hainaut 7540",
    "addr:housenumber":"14",
    "addr:postcode":"7540",
    "addr:street":"Rue Du Mont D'Or",
    "iso:country":"BE",
    "sg:address":"Rue Du Mont D'or 14",
    "sg:city":"Tournai",
    "sg:orig_category":"Paramedische behandelingen",
    "sg:phone":"+32 69 21 19 81",
    "sg:postcode":"7540",
    "sg:province":"Hainaut",
    "wof:name":"D. Noulette",
    "wof:placetype":"venue"
},
  "geometry": {"coordinates":[3.3412721157,50.6151046753],"type":"Point"}
}