{
  "type": "Feature",
  "properties": {
    "addr:full":"Verheyenplein 18 Beveren Oost-Vlaanderen 9130",
    "addr:housenumber":"18",
    "addr:postcode":"9130",
    "addr:street":"Verheyenplein",
    "iso:country":"BE",
    "sg:address":"Verheyenplein 18",
    "sg:city":"Beveren",
    "sg:orig_category":"Epiceries",
    "sg:phone":"+32 3 773 42 02",
    "sg:postcode":"9130",
    "sg:province":"Oost-Vlaanderen",
    "wof:name":"Myriam Batens",
    "wof:placetype":"venue"
},
  "geometry": {"coordinates":[4.1883878708,51.2555503845],"type":"Point"}
}