{
  "type": "Feature",
  "properties": {
    "iso:country":"BE",
    "sg:address":"Henisstraat 45",
    "sg:city":"Tongeren",
    "sg:classifiers":[
        {
            "category":"Shopping",
            "subcategory":"Crafts & Fabrics",
            "type":"Retail Goods"
        }
    ],
    "sg:phone":"+32 12 23 50 63",
    "sg:postcode":"3700",
    "sg:province":"Limburg",
    "sg:tags":[
        "needlework",
        "lady"
    ],
    "wof:name":"Rachel",
    "wof:placetype":"venue"
},
  "geometry": {"coordinates":[5.46935606,50.7867126465],"type":"Point"}
}