{
  "type": "Feature",
  "properties": {
    "addr:full":"Ooststraat 81 Roeselare West-Vlaanderen 8800",
    "addr:housenumber":"81",
    "addr:postcode":"8800",
    "addr:street":"Ooststraat",
    "iso:country":"BE",
    "sg:address":"Ooststraat 81",
    "sg:city":"Roeselare",
    "sg:orig_category":"V\u00eatements pour Dames. Articles pour b\u00e9b\u00e9s. V\u00eatements pour b\u00e9b\u00e9s and enfants",
    "sg:phone":"+32 51 24 18 59",
    "sg:postcode":"8800",
    "sg:province":"West-Vlaanderen",
    "wof:name":"Tineke Baby",
    "wof:placetype":"venue"
},
  "geometry": {"coordinates":[3.12768507,50.9472465515],"type":"Point"}
}