{
  "type": "Feature",
  "properties": {
    "iso:country":"BE",
    "sg:address":"Edgard Tinelstraat 20",
    "sg:city":"Sint-lievens-houtem",
    "sg:orig_category":"Brood, gebak and snoepgoed",
    "sg:phone":"+32 53 62 95 07",
    "sg:postcode":"9520",
    "sg:province":"Oost-Vlaanderen",
    "wof:name":"Huis Snoopy",
    "wof:placetype":"venue"
},
  "geometry": {"coordinates":[3.860394001,50.9198913574],"type":"Point"}
}