{
  "type": "Feature",
  "properties": {
    "iso:country":"BE",
    "sg:address":"Rue Pierre Michaux 61",
    "sg:city":"Oupeye",
    "sg:orig_category":"Herstellingswinkels voor diverse persoonlijke and huishoudartikelen Installatie van metalen schrijnw",
    "sg:phone":"+32 4 264 53 00",
    "sg:postcode":"4683",
    "sg:province":"Li\u00e8ge",
    "wof:name":"Marinelli",
    "wof:placetype":"venue"
},
  "geometry": {"coordinates":[5.6479959488,50.6924209595],"type":"Point"}
}