{
  "type": "Feature",
  "properties": {
    "iso:country":"BE",
    "sg:address":"Liebaardstraat 186",
    "sg:city":"Waregem",
    "sg:orig_category":"MEUBELONTWERP AND -INSTALLATIE",
    "sg:phone":"+32 56 71 01 14",
    "sg:postcode":"8792",
    "sg:province":"West-Vlaanderen",
    "wof:name":"Keukens Ideal",
    "wof:placetype":"venue"
},
  "geometry": {"coordinates":[3.3561329842,50.8816871643],"type":"Point"}
}