{
  "type": "Feature",
  "properties": {
    "addr:full":"Gentsesteenweg 6 Dendermonde Oost-Vlaanderen 9200",
    "addr:housenumber":"6",
    "addr:postcode":"9200",
    "addr:street":"Gentsesteenweg;Oost-Vlaanderen",
    "iso:country":"BE",
    "sg:address":"Gentsesteenweg 6",
    "sg:city":"Dendermonde",
    "sg:classifiers":[
        {
            "category":"Professional",
            "subcategory":"Accounting & Tax Preparation",
            "type":"Services"
        }
    ],
    "sg:phone":"+32 52 21 05 12",
    "sg:postcode":"9200",
    "sg:province":"Oost-Vlaanderen",
    "sg:tags":[
        "bookkeeper"
    ],
    "wof:name":"Peynshaert Ph",
    "wof:placetype":"venue"
},
  "geometry": {"coordinates":[4.0911040306,51.0319747925],"type":"Point"}
}