{
  "type": "Feature",
  "properties": {
    "iso:country":"BE",
    "sg:address":"Val Des Seigneurs 143 Box 42",
    "sg:city":"Bruxelles (woluwe-saint-pierre)",
    "sg:classifiers":[
        {
            "category":"Health Services",
            "subcategory":"Health Practitioner",
            "type":"Services"
        }
    ],
    "sg:phone":"+32 2 772 90 27",
    "sg:postcode":"1150",
    "sg:province":"Bruxelles-Capitale",
    "sg:tags":[
        "osteopath"
    ],
    "wof:name":"Balducchi C (d.o.)",
    "wof:placetype":"venue"
},
  "geometry": {"coordinates":[4.4575281143,50.8432807922],"type":"Point"}
}