{
  "type": "Feature",
  "properties": {
    "iso:country":"BE",
    "sg:address":"Hertshage 32",
    "sg:city":"Aalst",
    "sg:classifiers":[
        {
            "category":"Health Services",
            "subcategory":"Health Practitioner",
            "type":"Services"
        }
    ],
    "sg:phone":"+32 53 21 63 29",
    "sg:postcode":"9300",
    "sg:province":"Oost-Vlaanderen",
    "sg:tags":[
        "physiotherapist"
    ],
    "wof:name":"Van Neck H",
    "wof:placetype":"venue"
},
  "geometry": {"coordinates":[4.0405578613,50.9459686279],"type":"Point"}
}