{
  "type": "Feature",
  "properties": {
    "addr:full":"Alsembergse Steenweg 123 Sint-gillis/saint-gilles Bruxelles-Capitale 1060",
    "addr:housenumber":"123",
    "addr:postcode":"1060",
    "addr:street":"Alsembergse Steenweg",
    "iso:country":"BE",
    "sg:address":"Alsembergse Steenweg 123",
    "sg:city":"Sint-gillis/saint-gilles",
    "sg:orig_category":"Dansscholen",
    "sg:phone":"+32 2 538 62 45",
    "sg:postcode":"1060",
    "sg:province":"Bruxelles-Capitale",
    "wof:name":"Roberte Goeders",
    "wof:placetype":"venue"
},
  "geometry": {"coordinates":[4.342564106,50.8229179382],"type":"Point"}
}