{
  "type": "Feature",
  "properties": {
    "addr:full":"Rue De La Station 93 Charleroi (jumet) Hainaut 6040",
    "addr:housenumber":"93",
    "addr:postcode":"6040",
    "addr:street":"Rue De La Station",
    "iso:country":"BE",
    "sg:address":"Rue De La Station 93",
    "sg:city":"Charleroi (jumet)",
    "sg:classifiers":[
        {
            "category":"Personal",
            "subcategory":"Beauty Salon",
            "type":"Services"
        }
    ],
    "sg:phone":"+32 71 35 27 77",
    "sg:postcode":"6040",
    "sg:province":"Hainaut",
    "sg:tags":[
        "lady",
        "-",
        "hairdressing"
    ],
    "wof:name":"Diana",
    "wof:placetype":"venue"
},
  "geometry": {"coordinates":[4.433784008,50.4411277771],"type":"Point"}
}