{
  "type": "Feature",
  "properties": {
    "iso:country":"BE",
    "sg:address":"Appelmansstraat 26",
    "sg:city":"Antwerpen",
    "sg:classifiers":[
        {
            "category":"Professional",
            "subcategory":"Accounting & Tax Preparation",
            "type":"Services"
        }
    ],
    "sg:phone":"+32 3 234 22 51",
    "sg:postcode":"2018",
    "sg:province":"Antwerpen",
    "sg:tags":[
        "accountant"
    ],
    "wof:name":"Briels Pecher & Partners Accountants Bvba",
    "wof:placetype":"venue"
},
  "geometry": {"coordinates":[4.4171228409,51.2166061401],"type":"Point"}
}