{
  "type": "Feature",
  "properties": {
    "iso:country":"BE",
    "sg:address":"Voskenslaan 68",
    "sg:city":"Genk",
    "sg:orig_category":"Diverse bedrijfsbeheeradviesbureaus Diverse opleidingen and onderwijs",
    "sg:phone":"+32 89 35 90 40",
    "sg:postcode":"3600",
    "sg:province":"Limburg",
    "wof:name":"Trainingcenter De Belder",
    "wof:placetype":"venue"
},
  "geometry": {"coordinates":[5.5241332054,50.9835472107],"type":"Point"}
}