{
  "type": "Feature",
  "properties": {
    "iso:country":"BE",
    "sg:address":"Sint-gerebernusstraat 30",
    "sg:city":"Geel",
    "sg:orig_category":"Tuinen",
    "sg:phone":"+32 14 53 80 32",
    "sg:postcode":"2440",
    "sg:province":"Antwerpen",
    "wof:name":"Dytricko",
    "wof:placetype":"venue"
},
  "geometry": {"coordinates":[4.9552769661,51.0990905762],"type":"Point"}
}