{
  "type": "Feature",
  "properties": {
    "addr:full":"Kwaadham 12 Gent Oost-Vlaanderen 9000",
    "addr:housenumber":"12",
    "addr:postcode":"9000",
    "addr:street":"Kwaadham;Oost-Vlaanderen",
    "iso:country":"BE",
    "sg:address":"Kwaadham 12",
    "sg:city":"Gent",
    "sg:orig_category":"Agences de publicit\u00e9",
    "sg:phone":"+32 9 224 23 52",
    "sg:postcode":"9000",
    "sg:province":"Oost-Vlaanderen",
    "wof:name":"Angela Verlinden",
    "wof:placetype":"venue"
},
  "geometry": {"coordinates":[3.7284500599,51.0539321899],"type":"Point"}
}