{
  "type": "Feature",
  "properties": {
    "iso:country":"BE",
    "sg:address":"Rue D'oignies 5",
    "sg:city":"Sambreville (tamines)",
    "sg:classifiers":[
        {
            "category":"Shopping",
            "subcategory":"Clothing, Apparel, & Fashions",
            "type":"Retail Goods"
        }
    ],
    "sg:phone":"+32 71 77 22 22",
    "sg:postcode":"5060",
    "sg:province":"Namur",
    "sg:tags":[
        "clothing",
        "-",
        "gentleman"
    ],
    "wof:name":"Crappe M",
    "wof:placetype":"venue"
},
  "geometry": {"coordinates":[4.6139540672,50.4300308228],"type":"Point"}
}