{
  "type": "Feature",
  "properties": {
    "addr:full":"Woestestraat 3a Ruiselede West-Vlaanderen 8755",
    "addr:housenumber":"3a",
    "addr:postcode":"8755",
    "addr:street":"Woestestraat",
    "iso:country":"BE",
    "sg:address":"Woestestraat 3a",
    "sg:city":"Ruiselede",
    "sg:classifiers":[
        {
            "category":"Freight",
            "type":"Transportation"
        }
    ],
    "sg:phone":"+32 51 68 93 04",
    "sg:postcode":"8755",
    "sg:province":"West-Vlaanderen",
    "sg:tags":[
        "-",
        "transport"
    ],
    "wof:name":"Kvl Trans Bvba",
    "wof:placetype":"venue"
},
  "geometry": {"coordinates":[3.383548975,51.0742340088],"type":"Point"}
}