{
  "type": "Feature",
  "properties": {
    "addr:full":"Rue De F\u00c9tinne 57 Li\u00c8ge Li\u00e8ge 4020",
    "addr:housenumber":"57",
    "addr:postcode":"4020",
    "addr:street":"Rue De Fe\u0301Tinne",
    "iso:country":"BE",
    "sg:address":"Rue De F\u00c9tinne 57",
    "sg:city":"Li\u00c8ge",
    "sg:orig_category":"Fotografen and fotostudio's",
    "sg:phone":"+32 4 342 43 02",
    "sg:postcode":"4020",
    "sg:province":"Li\u00e8ge",
    "wof:name":"Quattro",
    "wof:placetype":"venue"
},
  "geometry": {"coordinates":[5.5824990273,50.6259536743],"type":"Point"}
}