{
  "type": "Feature",
  "properties": {
    "addr:full":"Rue Neuve 29 Beloeil Hainaut 7972",
    "addr:housenumber":"29",
    "addr:postcode":"7972",
    "addr:street":"Rue Neuve",
    "iso:country":"BE",
    "sg:address":"Rue Neuve 29",
    "sg:city":"Beloeil",
    "sg:orig_category":"Pharmaciens",
    "sg:phone":"+32 69 68 92 44",
    "sg:postcode":"7972",
    "sg:province":"Hainaut",
    "wof:name":"Caulier",
    "wof:placetype":"venue"
},
  "geometry": {"coordinates":[3.6783509254,50.5624809265],"type":"Point"}
}