{
  "type": "Feature",
  "properties": {
    "iso:country":"BE",
    "sg:address":"Gen\u00c8vestraat 560",
    "sg:city":"Schaarbeek/schaerbeek",
    "sg:classifiers":[
        {
            "category":"Restaurant",
            "type":"Food & Drink"
        }
    ],
    "sg:phone":"+32 2 705 20 93",
    "sg:postcode":"1030",
    "sg:province":"Bruxelles-Capitale",
    "sg:tags":[
        "caf\u00e9s"
    ],
    "wof:name":"Taverne Le Gen\u00c8ve",
    "wof:placetype":"venue"
},
  "geometry": {"coordinates":[4.4075489044,50.8574638367],"type":"Point"}
}