{
  "type": "Feature",
  "properties": {
    "addr:full":"Assenedestr. 4 Ertvelde Oost-Vlaanderen 9940",
    "addr:housenumber":"4",
    "addr:postcode":"9940",
    "addr:street":"Assenedestr.;Oost-Vlaanderen",
    "iso:country":"BE",
    "sg:address":"Assenedestr. 4",
    "sg:city":"Ertvelde",
    "sg:orig_category":"Agriculture and Livestock Business advice and other services Chemicals and Pharmaceuticals",
    "sg:phone":"+32 9 341 97 97",
    "sg:postcode":"9940",
    "sg:province":"Oost-Vlaanderen",
    "wof:name":"Mebrom Sa",
    "wof:placetype":"venue"
},
  "geometry": {"coordinates":[3.7839961052,51.1802520752],"type":"Point"}
}