{
  "type": "Feature",
  "properties": {
    "addr:full":"Rue Du Baudet 7 Bruxelles Bruxelles-Capitale 1000",
    "addr:housenumber":"7",
    "addr:postcode":"1000",
    "addr:street":"Rue Du Baudet",
    "iso:country":"BE",
    "sg:address":"Rue Du Baudet 7",
    "sg:city":"Bruxelles",
    "sg:classifiers":[
        {
            "category":"Shopping",
            "subcategory":"Books",
            "type":"Retail Goods"
        }
    ],
    "sg:phone":"+32 2 513 57 51",
    "sg:postcode":"1000",
    "sg:province":"Bruxelles-Capitale",
    "sg:tags":[
        "bookseller"
    ],
    "wof:name":"Pepperland",
    "wof:placetype":"venue"
},
  "geometry": {"coordinates":[4.3598270416,50.8398475647],"type":"Point"}
}