{
  "type": "Feature",
  "properties": {
    "iso:country":"BE",
    "sg:address":"Boomgaardstraat 12",
    "sg:city":"Aalter",
    "sg:classifiers":[
        {
            "category":"Shopping",
            "subcategory":"Crafts & Fabrics",
            "type":"Retail Goods"
        }
    ],
    "sg:phone":"+32 9 374 26 71",
    "sg:postcode":"9880",
    "sg:province":"Oost-Vlaanderen",
    "sg:tags":[
        "silk",
        "-"
    ],
    "wof:name":"Huis Anneke-soiran",
    "wof:placetype":"venue"
},
  "geometry": {"coordinates":[3.4497210979,51.0855903625],"type":"Point"}
}