{
  "type": "Feature",
  "properties": {
    "iso:country":"BE",
    "sg:address":"Spiegelstraat 20",
    "sg:city":"Sint-truiden",
    "sg:orig_category":"Diensten voor huisdieren",
    "sg:phone":"+32 11 67 13 57",
    "sg:postcode":"3800",
    "sg:province":"Limburg",
    "wof:name":"Hondenkapsalon Mira",
    "wof:placetype":"venue"
},
  "geometry": {"coordinates":[5.1862230301,50.8118095398],"type":"Point"}
}