{
  "type": "Feature",
  "properties": {
    "iso:country":"BE",
    "sg:address":"Zonnestraat 32-34",
    "sg:city":"Aalst",
    "sg:classifiers":[
        {
            "category":"Personal",
            "type":"Services"
        }
    ],
    "sg:phone":"+32 53 21 46 63",
    "sg:postcode":"9300",
    "sg:province":"Oost-Vlaanderen",
    "sg:tags":[
        "party",
        "planning"
    ],
    "wof:name":"Carlton Salons Bvba",
    "wof:placetype":"venue"
},
  "geometry": {"coordinates":[4.0397510529,50.9348602295],"type":"Point"}
}