{
  "type": "Feature",
  "properties": {
    "iso:country":"BE",
    "sg:address":"Rue Du Combattant L. Mahieu 5",
    "sg:city":"Hensies (thulin)",
    "sg:classifiers":[
        {
            "category":"Health Services",
            "subcategory":"Dentist",
            "type":"Services"
        }
    ],
    "sg:phone":"+32 65 69 10 72",
    "sg:postcode":"7350",
    "sg:province":"Hainaut",
    "wof:name":"Legrand L",
    "wof:placetype":"venue"
},
  "geometry": {"coordinates":[3.7415380478,50.4282684326],"type":"Point"}
}