{
  "type": "Feature",
  "properties": {
    "iso:country":"BE",
    "sg:address":"Cardijnstraat 46",
    "sg:city":"Anzegem",
    "sg:orig_category":"Installatie van houten of kunststof schrijnwerk",
    "sg:phone":"+32 56 77 87 78",
    "sg:postcode":"8570",
    "sg:province":"West-Vlaanderen",
    "wof:name":"Etienne Deweer",
    "wof:placetype":"venue"
},
  "geometry": {"coordinates":[3.4025189877,50.8408126831],"type":"Point"}
}