{
  "type": "Feature",
  "properties": {
    "addr:full":"Avenue Chazal 55-57 Bruxelles (schaerbeek) Bruxelles-Capitale 1030",
    "addr:housenumber":"55-57",
    "addr:postcode":"1030",
    "addr:street":"Avenue Chazal",
    "iso:country":"BE",
    "sg:address":"Avenue Chazal 55-57",
    "sg:city":"Bruxelles (schaerbeek)",
    "sg:classifiers":[
        {
            "category":"Autos & Motor Vehicles",
            "subcategory":"Auto Supplies",
            "type":"Retail Goods"
        }
    ],
    "sg:phone":"+32 2 733 91 20",
    "sg:postcode":"1030",
    "sg:province":"Bruxelles-Capitale",
    "sg:tags":[
        "access",
        "automobile",
        "part",
        "-"
    ],
    "wof:name":"Rigole-alvarez Ets",
    "wof:placetype":"venue"
},
  "geometry": {"coordinates":[4.3893971443,50.8550643921],"type":"Point"}
}