{
  "type": "Feature",
  "properties": {
    "iso:country":"BE",
    "sg:address":"Hof Ter Bekestraat 17",
    "sg:city":"Antwerpen",
    "sg:orig_category":"Epiceries",
    "sg:phone":"+32 3 237 72 74",
    "sg:postcode":"2018",
    "sg:province":"Antwerpen",
    "wof:name":"Guido Geerts",
    "wof:placetype":"venue"
},
  "geometry": {"coordinates":[4.3965058327,51.2013015747],"type":"Point"}
}