{
  "type": "Feature",
  "properties": {
    "addr:full":"Tiensestraat 33 Leuven Vlaams-Brabant 3000",
    "addr:housenumber":"33",
    "addr:postcode":"3000",
    "addr:street":"Tiensestraat",
    "iso:country":"BE",
    "sg:address":"Tiensestraat 33",
    "sg:city":"Leuven",
    "sg:classifiers":[
        {
            "category":"Health Services",
            "subcategory":"Dentist",
            "type":"Services"
        }
    ],
    "sg:phone":"+32 16 22 83 87",
    "sg:postcode":"3000",
    "sg:province":"Vlaams-Brabant",
    "wof:name":"Pinxten An",
    "wof:placetype":"venue"
},
  "geometry": {"coordinates":[4.7037930489,50.8780860901],"type":"Point"}
}