{
  "type": "Feature",
  "properties": {
    "iso:country":"BE",
    "sg:address":"Rue Franklin Roosevelt 83",
    "sg:city":"Frameries",
    "sg:orig_category":"Industri\u00eble wasserijen and droogkuis",
    "sg:phone":"+32 65 67 13 28",
    "sg:postcode":"7080",
    "sg:province":"Hainaut",
    "wof:name":"Grand Lavoir Public",
    "wof:placetype":"venue"
},
  "geometry": {"coordinates":[3.8984239101,50.4099082947],"type":"Point"}
}