{
  "type": "Feature",
  "properties": {
    "addr:full":"Georges Gilliotstraat 52 Hemiksem Antwerpen 2620",
    "addr:housenumber":"52",
    "addr:postcode":"2620",
    "addr:street":"Georges Gilliotstraat",
    "iso:country":"BE",
    "sg:address":"Georges Gilliotstraat 52",
    "sg:city":"Hemiksem",
    "sg:classifiers":[
        {
            "category":"Wholesale",
            "subcategory":"Hardware",
            "type":"Manufacturing & Wholesale Goods"
        }
    ],
    "sg:phone":"+32 3 870 00 00",
    "sg:postcode":"2620",
    "sg:province":"Antwerpen",
    "sg:tags":[
        "lubricating",
        "compound"
    ],
    "wof:name":"Champion Motor Oil",
    "wof:placetype":"venue"
},
  "geometry": {"coordinates":[4.3406062126,51.1333351135],"type":"Point"}
}