{
  "type": "Feature",
  "properties": {
    "iso:country":"BE",
    "sg:address":"Kraakbessenlaan 6",
    "sg:city":"Beersel",
    "sg:orig_category":"Fotografen and fotostudio's",
    "sg:phone":"+32 2 380 23 24",
    "sg:postcode":"1652",
    "sg:province":"Vlaams-Brabant",
    "wof:name":"Studio Sacha",
    "wof:placetype":"venue"
},
  "geometry": {"coordinates":[4.3255591393,50.7467193604],"type":"Point"}
}