{
  "type": "Feature",
  "properties": {
    "addr:full":"Rue De Saint-trond 22 Oreye Li\u00e8ge 4360",
    "addr:housenumber":"22",
    "addr:postcode":"4360",
    "addr:street":"Rue De Saint-Trond",
    "iso:country":"BE",
    "sg:address":"Rue De Saint-trond 22",
    "sg:city":"Oreye",
    "sg:classifiers":[
        {
            "category":"Banks & Credit Unions",
            "subcategory":"Investment Brokerage",
            "type":"Services"
        }
    ],
    "sg:phone":"+32 19 67 71 53",
    "sg:postcode":"4360",
    "sg:province":"Li\u00e8ge",
    "sg:tags":[
        "printing",
        "-"
    ],
    "wof:name":"Hesbi-presse Sc",
    "wof:placetype":"venue"
},
  "geometry": {"coordinates":[5.3559398651,50.73072052],"type":"Point"}
}