{
  "type": "Feature",
  "properties": {
    "addr:full":"Blokellestraat 121 Zwevegem West-Vlaanderen 8550",
    "addr:housenumber":"121",
    "addr:postcode":"8550",
    "addr:street":"Blokellestraat",
    "iso:country":"BE",
    "sg:address":"Blokellestraat 121",
    "sg:city":"Zwevegem",
    "sg:orig_category":"Traitement and rev\u00eatement des m\u00e9taux",
    "sg:phone":"+32 56 75 69 01",
    "sg:postcode":"8550",
    "sg:province":"West-Vlaanderen",
    "wof:name":"Fomeco",
    "wof:placetype":"venue"
},
  "geometry": {"coordinates":[3.3497760296,50.8107452393],"type":"Point"}
}