{
  "type": "Feature",
  "properties": {
    "addr:full":"Rue De Philippeville 31 Hamois Namur 5360",
    "addr:housenumber":"31",
    "addr:postcode":"5360",
    "addr:street":"Rue De Philippeville",
    "iso:country":"BE",
    "sg:address":"Rue De Philippeville 31",
    "sg:city":"Hamois",
    "sg:classifiers":[
        {
            "category":"Real Estate",
            "subcategory":"Architect",
            "type":"Services"
        }
    ],
    "sg:phone":"+32 83 61 20 01",
    "sg:postcode":"5360",
    "sg:province":"Namur",
    "wof:name":"Gillard D",
    "wof:placetype":"venue"
},
  "geometry": {"coordinates":[5.1800041199,50.3454627991],"type":"Point"}
}