{
  "type": "Feature",
  "properties": {
    "iso:country":"BE",
    "sg:address":"Bieshoeve 4",
    "sg:city":"Zoersel",
    "sg:orig_category":"Boekhouders",
    "sg:phone":"+32 3 312 28 81",
    "sg:postcode":"2980",
    "sg:province":"Antwerpen",
    "wof:name":"Haesaert Jo",
    "wof:placetype":"venue"
},
  "geometry": {"coordinates":[4.7115402222,51.2770195007],"type":"Point"}
}