{
  "type": "Feature",
  "properties": {
    "iso:country":"BE",
    "sg:address":"Haachtse Steenweg 61",
    "sg:city":"Sint-joost-ten-node/saint-josse-ten-noode",
    "sg:orig_category":"Apotheken",
    "sg:phone":"+32 2 217 42 60",
    "sg:postcode":"1210",
    "sg:province":"Bruxelles-Capitale",
    "wof:name":"P. Marechal/pierre Marechal",
    "wof:placetype":"venue"
},
  "geometry": {"coordinates":[4.368956089,50.8563919067],"type":"Point"}
}