{
  "type": "Feature",
  "properties": {
    "iso:country":"BE",
    "sg:address":"Roeselarestraat 33",
    "sg:city":"Hooglede",
    "sg:orig_category":"Pain, p\u00e2tisseries and confiseries",
    "sg:phone":"+32 51 20 66 48",
    "sg:postcode":"8830",
    "sg:province":"West-Vlaanderen",
    "wof:name":"V. Hillewaere",
    "wof:placetype":"venue"
},
  "geometry": {"coordinates":[3.083933115,50.9765586853],"type":"Point"}
}