{
  "type": "Feature",
  "properties": {
    "addr:full":"Quai Orban 37 Li\u00c8ge Li\u00e8ge 4020",
    "addr:housenumber":"37",
    "addr:postcode":"4020",
    "addr:street":"Quai Orban",
    "iso:country":"BE",
    "sg:address":"Quai Orban 37",
    "sg:city":"Li\u00c8ge",
    "sg:orig_category":"Ordinateurs and \u00e9quipement informatique",
    "sg:phone":"+32 4 344 45 32",
    "sg:postcode":"4020",
    "sg:province":"Li\u00e8ge",
    "wof:name":"Fe. Microsurf",
    "wof:placetype":"venue"
},
  "geometry": {"coordinates":[5.5779919624,50.6341590881],"type":"Point"}
}