{
  "type": "Feature",
  "properties": {
    "iso:country":"BE",
    "sg:address":"Kruishofstraat 74",
    "sg:city":"Antwerpen",
    "sg:orig_category":"Artsen and specialisten",
    "sg:phone":"+32 3 238 00 49",
    "sg:postcode":"2020",
    "sg:province":"Antwerpen",
    "wof:name":"O. Ledegen",
    "wof:placetype":"venue"
},
  "geometry": {"coordinates":[4.394288063,51.1855621338],"type":"Point"}
}