{
  "type": "Feature",
  "properties": {
    "iso:country":"BE",
    "sg:address":"Grendelbaan 9",
    "sg:city":"Diepenbeek",
    "sg:orig_category":"Magasins de r\u00e9parations d'articles personnels et m\u00e9nagers divers. Textiles. Rev\u00eatements de sols and ",
    "sg:phone":"+32 11 32 30 63",
    "sg:postcode":"3590",
    "sg:province":"Limburg",
    "wof:name":"De Ce Floor",
    "wof:placetype":"venue"
},
  "geometry": {"coordinates":[5.4300999641,50.9059906006],"type":"Point"}
}