{
  "type": "Feature",
  "properties": {
    "addr:full":"Blancefloerlaan 181 Antwerpen Antwerpen 2050",
    "addr:housenumber":"181",
    "addr:postcode":"2050",
    "addr:street":"Blancefloerlaan",
    "iso:country":"BE",
    "sg:address":"Blancefloerlaan 181",
    "sg:city":"Antwerpen",
    "sg:classifiers":[
        {
            "category":"Home & Garden",
            "subcategory":"Hardware",
            "type":"Retail Goods"
        }
    ],
    "sg:phone":"+32 3 210 12 11",
    "sg:postcode":"2050",
    "sg:province":"Antwerpen",
    "sg:tags":[
        "fixing",
        "material"
    ],
    "wof:name":"Combori Nv",
    "wof:placetype":"venue"
},
  "geometry": {"coordinates":[4.3726987839,51.2197608948],"type":"Point"}
}