{
  "type": "Feature",
  "properties": {
    "addr:full":"Vekestraat 87 Zemst Vlaams-Brabant 1982",
    "addr:housenumber":"87",
    "addr:postcode":"1982",
    "addr:street":"Vekestraat;Vlaams-Brabant",
    "iso:country":"BE",
    "sg:address":"Vekestraat 87",
    "sg:city":"Zemst",
    "sg:classifiers":[
        {
            "category":"Cafe",
            "type":"Food & Drink"
        }
    ],
    "sg:phone":"+32 15 61 21 25",
    "sg:postcode":"1982",
    "sg:province":"Vlaams-Brabant",
    "sg:tags":[
        "caf\u00e9s"
    ],
    "wof:name":"Martha Walschap",
    "wof:placetype":"venue"
},
  "geometry": {"coordinates":[4.5068621635,50.9651603699],"type":"Point"}
}