{
  "type": "Feature",
  "properties": {
    "addr:full":"Esmoreitlaan 5 Box 74 Antwerpen Antwerpen 2050",
    "addr:housenumber":"5 box 74",
    "addr:postcode":"2050",
    "addr:street":"Esmoreitlaan",
    "iso:country":"BE",
    "sg:address":"Esmoreitlaan 5 Box 74",
    "sg:city":"Antwerpen",
    "sg:classifiers":[
        {
            "category":"Building & Trades",
            "subcategory":"Landscaping Services",
            "type":"Services"
        }
    ],
    "sg:phone":"+32 3 652 08 22",
    "sg:postcode":"2050",
    "sg:province":"Antwerpen",
    "sg:tags":[
        "gardening",
        "garden",
        "maintenance"
    ],
    "wof:name":"Oak Gardens Bvba",
    "wof:placetype":"venue"
},
  "geometry": {"coordinates":[4.3837461472,51.233253479],"type":"Point"}
}