{
  "type": "Feature",
  "properties": {
    "addr:full":"Rue De La Marli\u00e8re 108 Mouscron Hainaut 7700",
    "addr:housenumber":"108",
    "addr:postcode":"7700",
    "addr:street":"Rue De La Marlie\u0300Re",
    "iso:country":"BE",
    "sg:address":"Rue De La Marli\u00e8re 108",
    "sg:city":"Mouscron",
    "sg:classifiers":[
        {
            "category":"Shopping",
            "subcategory":"Books",
            "type":"Retail Goods"
        }
    ],
    "sg:phone":"+32 56 33 39 94",
    "sg:postcode":"7700",
    "sg:province":"Hainaut",
    "sg:tags":[
        "bookseller"
    ],
    "wof:name":"Flipot",
    "wof:placetype":"venue"
},
  "geometry": {"coordinates":[3.2023370266,50.7417945862],"type":"Point"}
}