{
  "type": "Feature",
  "properties": {
    "iso:country":"BE",
    "sg:address":"Ninoofsesteenweg 63",
    "sg:city":"Sint-jans-molenbeek/molenbeek-",
    "sg:orig_category":"Charpentes and couvertures. Collecte and \u00e9puration des eaux us\u00e9es. Plomberie, chauffage and installa",
    "sg:phone":"+32 2 410 28 03",
    "sg:postcode":"1080",
    "sg:province":"Bruxelles-Capitale",
    "wof:name":"De Vis",
    "wof:placetype":"venue"
},
  "geometry": {"coordinates":[4.3324289322,50.8498802185],"type":"Point"}
}