{
  "type": "Feature",
  "properties": {
    "iso:country":"BE",
    "sg:address":"Meershoven 95",
    "sg:city":"Bilzen",
    "sg:classifiers":[
        {
            "category":"Health Services",
            "subcategory":"Health Practitioner",
            "type":"Services"
        }
    ],
    "sg:phone":"+32 89 41 53 34",
    "sg:postcode":"3740",
    "sg:province":"Limburg",
    "sg:tags":[
        "physiotherapist"
    ],
    "wof:name":"Deckers Luc",
    "wof:placetype":"venue"
},
  "geometry": {"coordinates":[5.5277872086,50.8765830994],"type":"Point"}
}