{
  "type": "Feature",
  "properties": {
    "iso:country":"BE",
    "sg:address":"Rue Du Croupet 191",
    "sg:city":"Seraing",
    "sg:classifiers":[
        {
            "category":"Parking",
            "subcategory":"Bicycle",
            "type":"Transportation"
        }
    ],
    "sg:phone":"+32 4 336 54 20",
    "sg:postcode":"4100",
    "sg:province":"Li\u00e8ge",
    "sg:tags":[
        "chiropodist"
    ],
    "wof:name":"Danel M",
    "wof:placetype":"venue"
},
  "geometry": {"coordinates":[5.4999599457,50.5888671875],"type":"Point"}
}