{
  "type": "Feature",
  "properties": {
    "iso:country":"BE",
    "sg:address":"Ledestraat 43",
    "sg:city":"Kaprijke",
    "sg:classifiers":[
        {
            "category":"Restaurant",
            "type":"Food & Drink"
        }
    ],
    "sg:phone":"+32 9 378 13 78",
    "sg:postcode":"9971",
    "sg:province":"Oost-Vlaanderen",
    "sg:tags":[
        "caf\u00e9s"
    ],
    "wof:name":"Taverne Ter Burghgraeve",
    "wof:placetype":"venue"
},
  "geometry": {"coordinates":[3.639811039,51.1826286316],"type":"Point"}
}