{
  "type": "Feature",
  "properties": {
    "addr:full":"Rue Des Pieds D'alouette 51 Namur (naninne) Namur 5100",
    "addr:housenumber":"51",
    "addr:postcode":"5100",
    "addr:street":"Rue Des Pieds D'Alouette",
    "iso:country":"BE",
    "sg:address":"Rue Des Pieds D'alouette 51",
    "sg:city":"Namur (naninne)",
    "sg:classifiers":[
        {
            "category":"Professional",
            "subcategory":"Art Services",
            "type":"Services"
        }
    ],
    "sg:phone":"+32 81 43 53 63",
    "sg:postcode":"5100",
    "sg:province":"Namur",
    "sg:tags":[
        "realization",
        "audio-visual"
    ],
    "wof:name":"Snark Productions Sprl",
    "wof:placetype":"venue"
},
  "geometry": {"coordinates":[4.9220209122,50.4277648926],"type":"Point"}
}