{
  "type": "Feature",
  "properties": {
    "iso:country":"BE",
    "sg:address":"Hoge Buizemont 219",
    "sg:city":"Geraardsbergen",
    "sg:classifiers":[
        {
            "category":"Shopping",
            "subcategory":"Stationery & Office Supplies",
            "type":"Retail Goods"
        }
    ],
    "sg:phone":"+32 54 41 54 00",
    "sg:postcode":"9500",
    "sg:province":"Oost-Vlaanderen",
    "sg:tags":[
        "label"
    ],
    "wof:name":"New Line Studio Bvba",
    "wof:placetype":"venue"
},
  "geometry": {"coordinates":[3.8818740845,50.7661895752],"type":"Point"}
}