{
  "type": "Feature",
  "properties": {
    "addr:full":"Klinkaertstraat 28 Dendermonde Oost-Vlaanderen 9200",
    "addr:housenumber":"28",
    "addr:postcode":"9200",
    "addr:street":"Klinkaertstraat;Oost-Vlaanderen",
    "iso:country":"BE",
    "sg:address":"Klinkaertstraat 28",
    "sg:city":"Dendermonde",
    "sg:orig_category":"Enseignement maternel and primaire",
    "sg:phone":"+32 52 42 32 01",
    "sg:postcode":"9200",
    "sg:province":"Oost-Vlaanderen",
    "wof:name":"Gemeentelijke Basisschool",
    "wof:placetype":"venue"
},
  "geometry": {"coordinates":[4.0226798058,51.000705719],"type":"Point"}
}