{
  "type": "Feature",
  "properties": {
    "addr:full":"Rue De L'eglise 7 Seraing Li\u00e8ge 4100",
    "addr:housenumber":"7",
    "addr:postcode":"4100",
    "addr:street":"Rue De L'Eglise",
    "iso:country":"BE",
    "sg:address":"Rue De L'eglise 7",
    "sg:city":"Seraing",
    "sg:orig_category":"Banques and organismes de cr\u00e9dit",
    "sg:phone":"+32 4 336 73 60",
    "sg:postcode":"4100",
    "sg:province":"Li\u00e8ge",
    "wof:name":"Fortis",
    "wof:placetype":"venue"
},
  "geometry": {"coordinates":[5.5352530479,50.5726394653],"type":"Point"}
}