{
  "type": "Feature",
  "properties": {
    "addr:full":"Rue De La Gare 55 Weismes Li\u00e8ge 4950",
    "addr:housenumber":"55",
    "addr:postcode":"4950",
    "addr:street":"Rue De La Gare",
    "iso:country":"BE",
    "sg:address":"Rue De La Gare 55",
    "sg:city":"Weismes",
    "sg:classifiers":[
        {
            "category":"Health Services",
            "subcategory":"Health Practitioner",
            "type":"Services"
        }
    ],
    "sg:phone":"+32 477 32 01 52",
    "sg:postcode":"4950",
    "sg:province":"Li\u00e8ge",
    "sg:tags":[
        "physiotherapist"
    ],
    "wof:name":"Feller Fr\u00e9d\u00e9ric",
    "wof:placetype":"venue"
},
  "geometry": {"coordinates":[6.1169810295,50.4125862122],"type":"Point"}
}