{
  "type": "Feature",
  "properties": {
    "addr:full":"Noorderlaan 77 Antwerpen Antwerpen 2030",
    "addr:housenumber":"77",
    "addr:postcode":"2030",
    "addr:street":"Noorderlaan",
    "iso:country":"BE",
    "sg:address":"Noorderlaan 77",
    "sg:city":"Antwerpen",
    "sg:orig_category":"Non-Classified Establishments",
    "sg:phone":"+32 3 544 81 50",
    "sg:postcode":"2030",
    "sg:province":"Antwerpen",
    "wof:name":"Aro/central Auto",
    "wof:placetype":"venue"
},
  "geometry": {"coordinates":[4.4197978973,51.253704071],"type":"Point"}
}