{
  "type": "Feature",
  "properties": {
    "addr:full":"Rue Bourgmestre M\u00e9hagnoul 53 Sambreville (falisolle) Namur 5060",
    "addr:housenumber":"53",
    "addr:postcode":"5060",
    "addr:street":"Rue Bourgmestre Me\u0301Hagnoul",
    "iso:country":"BE",
    "sg:address":"Rue Bourgmestre M\u00e9hagnoul 53",
    "sg:city":"Sambreville (falisolle)",
    "sg:classifiers":[
        {
            "category":"Building & Trades",
            "subcategory":"Construction",
            "type":"Services"
        }
    ],
    "sg:phone":"+32 71 77 46 33",
    "sg:postcode":"5060",
    "sg:province":"Namur",
    "sg:tags":[
        "carpenter"
    ],
    "wof:name":"Dewaele H",
    "wof:placetype":"venue"
},
  "geometry": {"coordinates":[4.6285200119,50.4448738098],"type":"Point"}
}