{
  "type": "Feature",
  "properties": {
    "iso:country":"BE",
    "sg:address":"Rue Du Waroux 23b",
    "sg:city":"Liege",
    "sg:orig_category":"Installatie van houten of kunststof schrijnwerk Installatie van metalen schrijnwerk",
    "sg:phone":"+32 4 224 53 53",
    "sg:postcode":"4000",
    "sg:province":"Li\u00e8ge",
    "wof:name":"Europlex",
    "wof:placetype":"venue"
},
  "geometry": {"coordinates":[5.5560121536,50.6437301636],"type":"Point"}
}