{
  "type": "Feature",
  "properties": {
    "iso:country":"BE",
    "sg:address":"Rue De La Hestre 67",
    "sg:city":"Chapelle-lez-herlaimont",
    "sg:classifiers":[
        {
            "category":"Home & Garden",
            "subcategory":"Carpets & Floor Coverings",
            "type":"Retail Goods"
        }
    ],
    "sg:phone":"+32 64 45 12 04",
    "sg:postcode":"7160",
    "sg:province":"Hainaut",
    "sg:tags":[
        "tile"
    ],
    "wof:name":"Chantier Moderne Chapellois",
    "wof:placetype":"venue"
},
  "geometry": {"coordinates":[4.279129982,50.4673995972],"type":"Point"}
}