{
  "type": "Feature",
  "properties": {
    "iso:country":"BE",
    "sg:address":"Hemelshoek 247",
    "sg:city":"Berlaar",
    "sg:orig_category":"Rundveehouders",
    "sg:phone":"+32 3 482 13 05",
    "sg:postcode":"2590",
    "sg:province":"Antwerpen",
    "wof:name":"Alfons Van Dessel",
    "wof:placetype":"venue"
},
  "geometry": {"coordinates":[4.6438379288,51.0976448059],"type":"Point"}
}