{
  "type": "Feature",
  "properties": {
    "iso:country":"BE",
    "sg:address":"Henri Lebbestraat 97",
    "sg:city":"Waregem",
    "sg:classifiers":[
        {
            "category":"Building & Trades",
            "subcategory":"Plumbing",
            "type":"Services"
        }
    ],
    "sg:phone":"+32 56 60 75 22",
    "sg:postcode":"8790",
    "sg:province":"West-Vlaanderen",
    "sg:tags":[
        "contractor"
    ],
    "wof:name":"De Neckere R",
    "wof:placetype":"venue"
},
  "geometry": {"coordinates":[3.4242870808,50.8799705505],"type":"Point"}
}