{
  "type": "Feature",
  "properties": {
    "addr:full":"Lijsterbolstraat 16b4 Kontich Antwerpen 2550",
    "addr:housenumber":"16b4",
    "addr:postcode":"2550",
    "addr:street":"Lijsterbolstraat",
    "iso:country":"BE",
    "sg:address":"Lijsterbolstraat 16b4",
    "sg:city":"Kontich",
    "sg:orig_category":"Afbraak- and draineerwerken",
    "sg:phone":"+32 3 457 43 47",
    "sg:postcode":"2550",
    "sg:province":"Antwerpen",
    "wof:name":"Antwerps Sloopbedrijf",
    "wof:placetype":"venue"
},
  "geometry": {"coordinates":[4.4486298561,51.1296081543],"type":"Point"}
}