{
  "type": "Feature",
  "properties": {
    "iso:country":"BE",
    "sg:address":"Place Du Ch\u00c2telain 49",
    "sg:city":"Elsene/ixelles",
    "sg:orig_category":"Fleurs and plantes",
    "sg:phone":"+32 2 646 66 96",
    "sg:postcode":"1050",
    "sg:province":"Bruxelles-Capitale",
    "wof:name":"Bo Flower",
    "wof:placetype":"venue"
},
  "geometry": {"coordinates":[4.3610777855,50.8250350952],"type":"Point"}
}