{
  "type": "Feature",
  "properties": {
    "addr:full":"Bronstraat 34 Gingelom Limburg 3891",
    "addr:housenumber":"34",
    "addr:postcode":"3891",
    "addr:street":"Bronstraat",
    "iso:country":"BE",
    "sg:address":"Bronstraat 34",
    "sg:city":"Gingelom",
    "sg:orig_category":"Fruitteelt",
    "sg:phone":"+32 11 48 50 18",
    "sg:postcode":"3891",
    "sg:province":"Limburg",
    "wof:name":"Marcelle Bormans",
    "wof:placetype":"venue"
},
  "geometry": {"coordinates":[5.2139010429,50.7514457703],"type":"Point"}
}