{
  "type": "Feature",
  "properties": {
    "iso:country":"BE",
    "sg:address":"Nieuwstraat 1bb",
    "sg:city":"Denderleeuw",
    "sg:orig_category":"Herenkledingzaken",
    "sg:phone":"+32 53 66 71 92",
    "sg:postcode":"9470",
    "sg:province":"Oost-Vlaanderen",
    "wof:name":"Willy Couck",
    "wof:placetype":"venue"
},
  "geometry": {"coordinates":[4.0760931969,50.8812828064],"type":"Point"}
}