{
  "type": "Feature",
  "properties": {
    "addr:full":"Paddevijverstraat 69 Ieper West-Vlaanderen 8900",
    "addr:housenumber":"69",
    "addr:postcode":"8900",
    "addr:street":"Paddevijverstraat",
    "iso:country":"BE",
    "sg:address":"Paddevijverstraat 69",
    "sg:city":"Ieper",
    "sg:orig_category":"Non-Classified Establishments",
    "sg:phone":"+32 57 21 82 79",
    "sg:postcode":"8900",
    "sg:province":"West-Vlaanderen",
    "wof:name":"Cherchye Color",
    "wof:placetype":"venue"
},
  "geometry": {"coordinates":[2.8834059238,50.8691444397],"type":"Point"}
}