{
  "type": "Feature",
  "properties": {
    "iso:country":"BE",
    "sg:address":"Kapellestraat 67",
    "sg:city":"Hamme",
    "sg:orig_category":"Hydroculture",
    "sg:phone":"+32 52 47 71 58",
    "sg:postcode":"9220",
    "sg:province":"Oost-Vlaanderen",
    "wof:name":"Van Den Broeck C",
    "wof:placetype":"venue"
},
  "geometry": {"coordinates":[4.1419467926,51.096031189],"type":"Point"}
}