{
  "type": "Feature",
  "properties": {
    "iso:country":"BE",
    "sg:address":"Cyriel Prie\u00eblsstraat 247",
    "sg:city":"Ninove (aspelare)",
    "sg:classifiers":[
        {
            "category":"Utilities",
            "subcategory":"Refuse",
            "type":"Services"
        }
    ],
    "sg:phone":"+32 54 50 27 57",
    "sg:postcode":"9404",
    "sg:province":"Oost-Vlaanderen",
    "sg:tags":[
        "catering"
    ],
    "wof:name":"Dinner Lux Bvba",
    "wof:placetype":"venue"
},
  "geometry": {"coordinates":[3.956870079,50.843788147],"type":"Point"}
}