{
  "type": "Feature",
  "properties": {
    "iso:country":"BE",
    "sg:address":"Kerkstraat 7",
    "sg:city":"Heist-op-den-berg (itegem)",
    "sg:classifiers":[
        {
            "category":"Bars & Pubs",
            "type":"Food & Drink"
        }
    ],
    "sg:phone":"+32 15 24 12 18",
    "sg:postcode":"2222",
    "sg:province":"Antwerpen",
    "wof:name":"Witpen (de)",
    "wof:placetype":"venue"
},
  "geometry": {"coordinates":[4.7294511795,51.0763893127],"type":"Point"}
}