{
  "type": "Feature",
  "properties": {
    "iso:country":"BE",
    "sg:address":"Rue Des Guillemins 52",
    "sg:city":"Luik (groot)",
    "sg:orig_category":"Hypotheken and hypotheekbanken Verbruikerskredietinstellingen",
    "sg:phone":"+32 4 253 12 98",
    "sg:postcode":"4000",
    "sg:province":"Li\u00e8ge",
    "wof:name":"Fonds Lu Logement Des Familles Nombreuses-wallonie",
    "wof:placetype":"venue"
},
  "geometry": {"coordinates":[5.5672340393,50.6284599304],"type":"Point"}
}