{
  "type": "Feature",
  "properties": {
    "addr:full":"Korte Meer 23 Gent Oost-Vlaanderen 9000",
    "addr:housenumber":"23",
    "addr:postcode":"9000",
    "addr:street":"Korte Meer;Oost-Vlaanderen",
    "iso:country":"BE",
    "sg:address":"Korte Meer 23",
    "sg:city":"Gent",
    "sg:classifiers":[
        {
            "category":"Shopping",
            "subcategory":"Florist",
            "type":"Retail Goods"
        }
    ],
    "sg:phone":"+32 9 223 76 72",
    "sg:postcode":"9000",
    "sg:province":"Oost-Vlaanderen",
    "wof:name":"Boekee",
    "wof:placetype":"venue"
},
  "geometry": {"coordinates":[3.7226650715,51.0508728027],"type":"Point"}
}