{
  "type": "Feature",
  "properties": {
    "iso:country":"BE",
    "sg:address":"Rue De Virelles 20b",
    "sg:city":"Cerfontaine",
    "sg:classifiers":[
        {
            "category":"Building & Trades",
            "subcategory":"Landscaping Services",
            "type":"Services"
        }
    ],
    "sg:phone":"+32 71 64 39 47",
    "sg:postcode":"5630",
    "sg:province":"Namur",
    "sg:tags":[
        "forestry"
    ],
    "wof:name":"Baugnee F",
    "wof:placetype":"venue"
},
  "geometry": {"coordinates":[4.4031229019,50.1668319702],"type":"Point"}
}