{
  "type": "Feature",
  "properties": {
    "addr:full":"Passage Linthout 8 Bruxelles (woluwe-saint-lambert) Bruxelles-Capitale 1200",
    "addr:housenumber":"8",
    "addr:postcode":"1200",
    "addr:street":"Passage Linthout",
    "iso:country":"BE",
    "sg:address":"Passage Linthout 8",
    "sg:city":"Bruxelles (woluwe-saint-lambert)",
    "sg:classifiers":[
        {
            "category":"Shopping",
            "subcategory":"Clothing, Apparel, & Fashions",
            "type":"Retail Goods"
        }
    ],
    "sg:phone":"+32 2 733 82 37",
    "sg:postcode":"1200",
    "sg:province":"Bruxelles-Capitale",
    "sg:tags":[
        "lady",
        "clothing",
        "-"
    ],
    "wof:name":"Chattawak",
    "wof:placetype":"venue"
},
  "geometry": {"coordinates":[4.4024958611,50.840965271],"type":"Point"}
}