{
  "type": "Feature",
  "properties": {
    "addr:full":"Markt 15 Mol Antwerpen 2400",
    "addr:housenumber":"15",
    "addr:postcode":"2400",
    "addr:street":"Markt",
    "iso:country":"BE",
    "sg:address":"Markt 15",
    "sg:city":"Mol",
    "sg:orig_category":"Services fun\u00e9raires",
    "sg:phone":"+32 14 31 52 46",
    "sg:postcode":"2400",
    "sg:province":"Antwerpen",
    "wof:name":"Schillebeeckx A",
    "wof:placetype":"venue"
},
  "geometry": {"coordinates":[5.116517067,51.1846046448],"type":"Point"}
}