{
  "type": "Feature",
  "properties": {
    "addr:full":"Rue De Daussois 1 Walcourt (vogen\u00e9e) Namur 5650",
    "addr:housenumber":"1",
    "addr:postcode":"5650",
    "addr:street":"Rue De Daussois",
    "iso:country":"BE",
    "sg:address":"Rue De Daussois 1",
    "sg:city":"Walcourt (vogen\u00e9e)",
    "sg:classifiers":[
        {
            "category":"Military Area",
            "subcategory":"Air Force Base",
            "type":"Public Place"
        }
    ],
    "sg:phone":"+32 71 61 18 61",
    "sg:postcode":"5650",
    "sg:province":"Namur",
    "sg:tags":[
        "water",
        "treatment"
    ],
    "wof:name":"Codema Industries Sprl",
    "wof:placetype":"venue"
},
  "geometry": {"coordinates":[4.4313349724,50.2514762878],"type":"Point"}
}