{
  "type": "Feature",
  "properties": {
    "addr:full":"Kattebroekstraat 27 Dilbeek Vlaams-Brabant 1700",
    "addr:housenumber":"27",
    "addr:postcode":"1700",
    "addr:street":"Kattebroekstraat",
    "iso:country":"BE",
    "sg:address":"Kattebroekstraat 27",
    "sg:city":"Dilbeek",
    "sg:classifiers":[
        {
            "category":"Health Services",
            "subcategory":"Doctor",
            "type":"Services"
        }
    ],
    "sg:phone":"+32 2 479 31 93",
    "sg:postcode":"1700",
    "sg:province":"Vlaams-Brabant",
    "sg:tags":[
        "medicinephysicians",
        "surgeon"
    ],
    "wof:name":"Blootacker Tom",
    "wof:placetype":"venue"
},
  "geometry": {"coordinates":[4.2662301064,50.8527526855],"type":"Point"}
}