{
  "type": "Feature",
  "properties": {
    "addr:full":"Kartuizersvest 83 Lier Antwerpen 2500",
    "addr:housenumber":"83",
    "addr:postcode":"2500",
    "addr:street":"Kartuizersvest",
    "iso:country":"BE",
    "sg:address":"Kartuizersvest 83",
    "sg:city":"Lier",
    "sg:orig_category":"Slagers",
    "sg:phone":"+32 3 480 40 03",
    "sg:postcode":"2500",
    "sg:province":"Antwerpen",
    "wof:name":"Slagerij Langmans",
    "wof:placetype":"venue"
},
  "geometry": {"coordinates":[4.5701022148,51.1346244812],"type":"Point"}
}