{
  "type": "Feature",
  "properties": {
    "iso:country":"BE",
    "sg:address":"Rue Du Fresnoy 1",
    "sg:city":"Estaimpuis",
    "sg:orig_category":"Slagers",
    "sg:phone":"+32 69 35 13 73",
    "sg:postcode":"7730",
    "sg:province":"Hainaut",
    "wof:name":"Boucherie Luc",
    "wof:placetype":"venue"
},
  "geometry": {"coordinates":[3.2855470181,50.6698570251],"type":"Point"}
}