{
  "type": "Feature",
  "properties": {
    "addr:full":"Cederstraat 21 Mechelen Antwerpen 2800",
    "addr:housenumber":"21",
    "addr:postcode":"2800",
    "addr:street":"Cederstraat",
    "iso:country":"BE",
    "sg:address":"Cederstraat 21",
    "sg:city":"Mechelen",
    "sg:classifiers":[
        {
            "category":"Travel",
            "subcategory":"Travel Agent",
            "type":"Entertainment"
        }
    ],
    "sg:phone":"+32 15 43 00 28",
    "sg:postcode":"2800",
    "sg:province":"Antwerpen",
    "sg:tags":[
        "agency"
    ],
    "wof:name":"Arakea Bvba",
    "wof:placetype":"venue"
},
  "geometry": {"coordinates":[4.4803729057,51.0075035095],"type":"Point"}
}