{
  "type": "Feature",
  "properties": {
    "addr:full":"Demerstraat 103-105 Hasselt Limburg 3500",
    "addr:housenumber":"103-105",
    "addr:postcode":"3500",
    "addr:street":"Demerstraat",
    "iso:country":"BE",
    "sg:address":"Demerstraat 103-105",
    "sg:city":"Hasselt",
    "sg:orig_category":"Tijdelijke werkgelegenheid and uitzendkantoren",
    "sg:phone":"+32 11 26 12 03",
    "sg:postcode":"3500",
    "sg:province":"Limburg",
    "wof:name":"Student @ Creyf\u00b4s",
    "wof:placetype":"venue"
},
  "geometry": {"coordinates":[5.3394618034,50.9336853027],"type":"Point"}
}