{
  "type": "Feature",
  "properties": {
    "iso:country":"BE",
    "sg:address":"Gemeenteplein 2",
    "sg:city":"Keerbergen",
    "sg:orig_category":"Epiceries",
    "sg:phone":"+32 15 51 12 03",
    "sg:postcode":"3140",
    "sg:province":"Vlaams-Brabant",
    "wof:name":"Ecofood",
    "wof:placetype":"venue"
},
  "geometry": {"coordinates":[4.6295819283,51.0034217834],"type":"Point"}
}