{
  "type": "Feature",
  "properties": {
    "iso:country":"BE",
    "sg:address":"Rue De L\u00b4ourthe 4",
    "sg:city":"Liege-centre",
    "sg:classifiers":[
        {
            "category":"Restaurant",
            "type":"Food & Drink"
        }
    ],
    "sg:phone":"+32 4 342 25 86",
    "sg:postcode":"4020",
    "sg:province":"Li\u00e8ge",
    "wof:name":"Restaurant Les Cyclades",
    "wof:placetype":"venue"
},
  "geometry": {"coordinates":[1.1040999889,47.2290115356],"type":"Point"}
}