{
  "type": "Feature",
  "properties": {
    "addr:full":"Place De La Gare 30 Braine-l'alleud Brabant Wallon 1420",
    "addr:housenumber":"30",
    "addr:postcode":"1420",
    "addr:street":"Place De La Gare",
    "iso:country":"BE",
    "sg:address":"Place De La Gare 30",
    "sg:city":"Braine-l'alleud",
    "sg:orig_category":"Brood, gebak and snoepgoed Geschenken and souvenirs",
    "sg:phone":"+32 2 385 16 24",
    "sg:postcode":"1420",
    "sg:province":"Brabant Wallon",
    "wof:name":"Maison Bis-kot",
    "wof:placetype":"venue"
},
  "geometry": {"coordinates":[-0.6888700128,47.3739128113],"type":"Point"}
}