{
  "type": "Feature",
  "properties": {
    "addr:full":"Peperstraat 58 Kortrijk West-Vlaanderen 8501",
    "addr:housenumber":"58",
    "addr:postcode":"8501",
    "addr:street":"Peperstraat",
    "iso:country":"BE",
    "sg:address":"Peperstraat 58",
    "sg:city":"Kortrijk",
    "sg:orig_category":"Elektrische installaties voor woningen",
    "sg:phone":"+32 56 35 24 10",
    "sg:postcode":"8501",
    "sg:province":"West-Vlaanderen",
    "wof:name":"Fa. Vervaecke",
    "wof:placetype":"venue"
},
  "geometry": {"coordinates":[3.2302401066,50.841632843],"type":"Point"}
}