{
  "type": "Feature",
  "properties": {
    "iso:country":"BE",
    "sg:address":"Rue De La Paix 24",
    "sg:city":"Elsene/ixelles",
    "sg:classifiers":[
        {
            "category":"Restaurant",
            "type":"Food & Drink"
        }
    ],
    "sg:phone":"+32 2 512 92 17",
    "sg:postcode":"1050",
    "sg:province":"Bruxelles-Capitale",
    "wof:name":"Taverne Des Grands Lacs",
    "wof:placetype":"venue"
},
  "geometry": {"coordinates":[4.3652038574,50.8359642029],"type":"Point"}
}