{
  "type": "Feature",
  "properties": {
    "addr:full":"Eekhoutstraat 17ba Ardooie West-Vlaanderen 8850",
    "addr:housenumber":"17ba",
    "addr:postcode":"8850",
    "addr:street":"Eekhoutstraat",
    "iso:country":"BE",
    "sg:address":"Eekhoutstraat 17ba",
    "sg:city":"Ardooie",
    "sg:orig_category":"Voertuigen",
    "sg:phone":"+32 51 74 76 77",
    "sg:postcode":"8850",
    "sg:province":"West-Vlaanderen",
    "wof:name":"Nick Verstaen",
    "wof:placetype":"venue"
},
  "geometry": {"coordinates":[3.2013559341,50.9776496887],"type":"Point"}
}