{
  "type": "Feature",
  "properties": {
    "addr:full":"Bomerstraat 22 Peer Limburg 3990",
    "addr:housenumber":"22",
    "addr:postcode":"3990",
    "addr:street":"Bomerstraat",
    "iso:country":"BE",
    "sg:address":"Bomerstraat 22",
    "sg:city":"Peer",
    "sg:classifiers":[
        {
            "category":"Restaurant",
            "type":"Food & Drink"
        }
    ],
    "sg:phone":"+32 11 63 71 78",
    "sg:postcode":"3990",
    "sg:province":"Limburg",
    "wof:name":"L'uno Coll'altro",
    "wof:placetype":"venue"
},
  "geometry": {"coordinates":[5.4446511269,51.1303596497],"type":"Point"}
}