{
  "type": "Feature",
  "properties": {
    "iso:country":"BE",
    "sg:address":"Rue Des Maraichers 5",
    "sg:city":"Li\u00c8ge",
    "sg:orig_category":"M\u00e9decins and sp\u00e9cialistes",
    "sg:phone":"+32 4 343 18 50",
    "sg:postcode":"4020",
    "sg:province":"Li\u00e8ge",
    "wof:name":"Camille Bailleux",
    "wof:placetype":"venue"
},
  "geometry": {"coordinates":[5.5908560753,50.6401634216],"type":"Point"}
}