{
  "type": "Feature",
  "properties": {
    "addr:full":"Eupenerstrasse 35 Raeren/raeren Li\u00e8ge 4731",
    "addr:housenumber":"35",
    "addr:postcode":"4731",
    "addr:street":"Eupenerstrasse",
    "iso:country":"BE",
    "sg:address":"Eupenerstrasse 35",
    "sg:city":"Raeren/raeren",
    "sg:orig_category":"Benzinestations and brandstoffen",
    "sg:phone":"+32 87 85 18 73",
    "sg:postcode":"4731",
    "sg:province":"Li\u00e8ge",
    "wof:name":"Henri Brixhe",
    "wof:placetype":"venue"
},
  "geometry": {"coordinates":[6.0816779137,50.6909446716],"type":"Point"}
}