{
  "type": "Feature",
  "properties": {
    "addr:full":"Rue Du Prince Royal 29 Bruxelles (ixelles) Bruxelles-Capitale 1050",
    "addr:housenumber":"29",
    "addr:postcode":"1050",
    "addr:street":"Rue Du Prince Royal",
    "iso:country":"BE",
    "sg:address":"Rue Du Prince Royal 29",
    "sg:city":"Bruxelles (ixelles)",
    "sg:classifiers":[
        {
            "category":"Home & Garden",
            "subcategory":"Home Furnishings",
            "type":"Retail Goods"
        }
    ],
    "sg:phone":"+32 2 503 33 90",
    "sg:postcode":"1050",
    "sg:province":"Bruxelles-Capitale",
    "sg:tags":[
        "interior",
        "decoration"
    ],
    "wof:name":"Magouna",
    "wof:placetype":"venue"
},
  "geometry": {"coordinates":[4.3624658585,50.8348960876],"type":"Point"}
}