{
  "type": "Feature",
  "properties": {
    "iso:country":"BE",
    "sg:address":"Lindenlaan 246",
    "sg:city":"Beveren (beveren-waas)",
    "sg:classifiers":[
        {
            "category":"Professional",
            "subcategory":"Management & Consulting",
            "type":"Services"
        }
    ],
    "sg:phone":"+32 3 775 41 81",
    "sg:postcode":"9120",
    "sg:province":"Oost-Vlaanderen",
    "sg:tags":[
        "consultant"
    ],
    "wof:name":"On Track Consulting",
    "wof:placetype":"venue"
},
  "geometry": {"coordinates":[4.224489212,51.2082023621],"type":"Point"}
}