{
  "type": "Feature",
  "properties": {
    "addr:full":"Rue De L'eglise Saint-gilles 2 Bruxelles (saint-gilles) Bruxelles-Capitale 1060",
    "addr:housenumber":"2",
    "addr:postcode":"1060",
    "addr:street":"Rue De L'Eglise Saint-Gilles",
    "iso:country":"BE",
    "sg:address":"Rue De L'eglise Saint-gilles 2",
    "sg:city":"Bruxelles (saint-gilles)",
    "sg:classifiers":[
        {
            "category":"Ice Cream",
            "type":"Food & Drink"
        }
    ],
    "sg:phone":"+32 2 537 37 90",
    "sg:postcode":"1060",
    "sg:province":"Bruxelles-Capitale",
    "wof:name":"Capaldi",
    "wof:placetype":"venue"
},
  "geometry": {"coordinates":[4.3421750069,50.83228302],"type":"Point"}
}