{
  "type": "Feature",
  "properties": {
    "addr:full":"Avenue Moscicki 12 Ukkel/uccle Bruxelles-Capitale 1180",
    "addr:housenumber":"12",
    "addr:postcode":"1180",
    "addr:street":"Avenue Moscicki;/",
    "iso:country":"BE",
    "sg:address":"Avenue Moscicki 12",
    "sg:city":"Ukkel/uccle",
    "sg:orig_category":"M\u00e9decins and sp\u00e9cialistes",
    "sg:phone":"+32 2 332 03 30",
    "sg:postcode":"1180",
    "sg:province":"Bruxelles-Capitale",
    "wof:name":"V. Van Den Haute",
    "wof:placetype":"venue"
},
  "geometry": {"coordinates":[4.3633160591,50.8094329834],"type":"Point"}
}