{
  "type": "Feature",
  "properties": {
    "iso:country":"BE",
    "sg:address":"Oud-strijdersstraat 16",
    "sg:city":"Willebroek",
    "sg:orig_category":"M\u00e9decins and sp\u00e9cialistes",
    "sg:phone":"+32 3 886 63 36",
    "sg:postcode":"2830",
    "sg:province":"Antwerpen",
    "wof:name":"Y. Renneberg",
    "wof:placetype":"venue"
},
  "geometry": {"coordinates":[4.3597040176,51.0600509644],"type":"Point"}
}