{
  "type": "Feature",
  "properties": {
    "addr:full":"Square De Mee\u00dbs 29 Brussel/bruxelles Bruxelles-Capitale 1000",
    "addr:housenumber":"29",
    "addr:postcode":"1000",
    "addr:street":"Square De Meeu\u0302S;/",
    "iso:country":"BE",
    "sg:address":"Square De Mee\u00dbs 29",
    "sg:city":"Brussel/bruxelles",
    "sg:classifiers":[
        {
            "category":"Insurance",
            "subcategory":"Life Insurance",
            "type":"Services"
        }
    ],
    "sg:phone":"+32 2 503 21 14",
    "sg:postcode":"1000",
    "sg:province":"Bruxelles-Capitale",
    "sg:tags":[
        "assurance"
    ],
    "wof:name":"Verzekeringen Syban",
    "wof:placetype":"venue"
},
  "geometry": {"coordinates":[4.3701219559,50.8405456543],"type":"Point"}
}