{
  "type": "Feature",
  "properties": {
    "addr:full":"Avenue De La Victoire 18 Neufch\u00e2teau Luxembourg 6840",
    "addr:housenumber":"18",
    "addr:postcode":"6840",
    "addr:street":"Avenue De La",
    "iso:country":"BE",
    "sg:address":"Avenue De La Victoire 18",
    "sg:city":"Neufch\u00e2teau",
    "sg:classifiers":[
        {
            "category":"Retail",
            "subcategory":"Veterinary Services",
            "type":"Services"
        }
    ],
    "sg:phone":"+32 61 27 92 20",
    "sg:postcode":"6840",
    "sg:province":"Luxembourg",
    "sg:tags":[
        "veterinarian"
    ],
    "wof:name":"Arnould C",
    "wof:placetype":"venue"
},
  "geometry": {"coordinates":[5.4390320778,49.8463363647],"type":"Point"}
}