{
  "type": "Feature",
  "properties": {
    "iso:country":"BE",
    "sg:address":"Chemin Du Bon Dieu De Gibloux 74",
    "sg:city":"Waterloo",
    "sg:orig_category":"Instituts de beaut\u00e9",
    "sg:phone":"+32 2 353 18 50",
    "sg:postcode":"1410",
    "sg:province":"Brabant Wallon",
    "wof:name":"Genevi\u00c8ve Vancampenhout",
    "wof:placetype":"venue"
},
  "geometry": {"coordinates":[4.3952641487,50.7042694092],"type":"Point"}
}