{
  "type": "Feature",
  "properties": {
    "iso:country":"BE",
    "sg:address":"Erwetegemstraat 5",
    "sg:city":"Zottegem (erwetegem)",
    "sg:classifiers":[
        {
            "category":"Building & Trades",
            "subcategory":"Landscaping Services",
            "type":"Services"
        }
    ],
    "sg:phone":"+32 9 360 80 16",
    "sg:postcode":"9620",
    "sg:province":"Oost-Vlaanderen",
    "sg:tags":[
        "architect",
        "landscape"
    ],
    "wof:name":"Van Paemel J",
    "wof:placetype":"venue"
},
  "geometry": {"coordinates":[3.8128368855,50.8595237732],"type":"Point"}
}