{
  "type": "Feature",
  "properties": {
    "iso:country":"BE",
    "sg:address":"Elisabethlaan 73",
    "sg:city":"Antwerpen",
    "sg:orig_category":"Diverse bedrijfsbeheeradviesbureaus",
    "sg:phone":"+32 3 230 22 61",
    "sg:postcode":"2600",
    "sg:province":"Antwerpen",
    "wof:name":"Company Services",
    "wof:placetype":"venue"
},
  "geometry": {"coordinates":[4.4232978821,51.1821250916],"type":"Point"}
}