{
  "type": "Feature",
  "properties": {
    "iso:country":"BE",
    "sg:address":"Rue Des Faubourgs 5",
    "sg:city":"Arlon",
    "sg:orig_category":"Electrom\u00e9nager, t\u00e9l\u00e9visions and radios",
    "sg:phone":"+32 63 21 96 67",
    "sg:postcode":"6700",
    "sg:province":"Luxembourg",
    "wof:name":"Peter Pin",
    "wof:placetype":"venue"
},
  "geometry": {"coordinates":[5.8122081757,49.6841087341],"type":"Point"}
}