{
  "type": "Feature",
  "properties": {
    "iso:country":"BE",
    "sg:address":"Lindestraat 42",
    "sg:city":"Herne",
    "sg:orig_category":"Eleveurs de bovins",
    "sg:phone":"+32 2 396 10 70",
    "sg:postcode":"1540",
    "sg:province":"Vlaams-Brabant",
    "wof:name":"Raymonde Nerinckx",
    "wof:placetype":"venue"
},
  "geometry": {"coordinates":[4.0434408188,50.7194824219],"type":"Point"}
}