{
  "type": "Feature",
  "properties": {
    "addr:full":"Rue Bertaux Joseph 55 Charleroi (jumet) Hainaut 6040",
    "addr:housenumber":"55",
    "addr:postcode":"6040",
    "addr:street":"Rue Bertaux Joseph",
    "iso:country":"BE",
    "sg:address":"Rue Bertaux Joseph 55",
    "sg:city":"Charleroi (jumet)",
    "sg:classifiers":[
        {
            "category":"Social Services",
            "subcategory":"Job Training",
            "type":"Services"
        }
    ],
    "sg:phone":"+32 71 35 47 88",
    "sg:postcode":"6040",
    "sg:province":"Hainaut",
    "sg:tags":[
        "personnel"
    ],
    "wof:name":"Eb Consultance Sprl",
    "wof:placetype":"venue"
},
  "geometry": {"coordinates":[4.4370808601,50.4451637268],"type":"Point"}
}