{
  "type": "Feature",
  "properties": {
    "iso:country":"BE",
    "sg:address":"Oude Galgenstraat 40",
    "sg:city":"Kapellen",
    "sg:classifiers":[
        {
            "category":"Freight",
            "type":"Transportation"
        }
    ],
    "sg:phone":"+32 3 664 49 75",
    "sg:postcode":"2950",
    "sg:province":"Antwerpen",
    "sg:tags":[
        "container",
        "-",
        "transport"
    ],
    "wof:name":"Mees",
    "wof:placetype":"venue"
},
  "geometry": {"coordinates":[4.4147648811,51.3436775208],"type":"Point"}
}