{
  "type": "Feature",
  "properties": {
    "addr:full":"Rue De La Roseraie 25 Bruxelles (berchem-sainte-agathe) Bruxelles-Capitale 1082",
    "addr:housenumber":"25",
    "addr:postcode":"1082",
    "addr:street":"Rue De La Roseraie",
    "iso:country":"BE",
    "sg:address":"Rue De La Roseraie 25",
    "sg:city":"Bruxelles (berchem-sainte-agathe)",
    "sg:classifiers":[
        {
            "category":"Real Estate",
            "subcategory":"Real Estate Services",
            "type":"Services"
        }
    ],
    "sg:phone":"+32 2 468 04 54",
    "sg:postcode":"1082",
    "sg:province":"Bruxelles-Capitale",
    "wof:name":"Molineaux Albert",
    "wof:placetype":"venue"
},
  "geometry": {"coordinates":[4.2903752327,50.8613204956],"type":"Point"}
}