{
  "type": "Feature",
  "properties": {
    "iso:country":"BE",
    "sg:address":"Leopold Iii Laan",
    "sg:city":"Hamme",
    "sg:orig_category":"Tuinen",
    "sg:phone":"+32 52 47 98 73",
    "sg:postcode":"9220",
    "sg:province":"Oost-Vlaanderen",
    "wof:name":"Tuinzorg",
    "wof:placetype":"venue"
},
  "geometry": {"coordinates":[4.138794899,51.0907249451],"type":"Point"}
}