{
  "type": "Feature",
  "properties": {
    "iso:country":"BE",
    "sg:address":"Gentstraat 17",
    "sg:city":"Sint-gillis-waas (sint-pauwels)",
    "sg:classifiers":[
        {
            "category":"Bars & Pubs",
            "type":"Food & Drink"
        }
    ],
    "sg:phone":"+32 3 776 61 88",
    "sg:postcode":"9170",
    "sg:province":"Oost-Vlaanderen",
    "wof:name":"Schuttershof",
    "wof:placetype":"venue"
},
  "geometry": {"coordinates":[4.0975961685,51.1920166016],"type":"Point"}
}