{
  "type": "Feature",
  "properties": {
    "iso:country":"BE",
    "sg:address":"Bijkhoevelaan 9",
    "sg:city":"Wijnegem",
    "sg:classifiers":[
        {
            "category":"Home & Garden",
            "subcategory":"Hardware",
            "type":"Retail Goods"
        }
    ],
    "sg:phone":"+32 3 326 28 60",
    "sg:postcode":"2110",
    "sg:province":"Antwerpen",
    "sg:tags":[
        "compressor",
        "air"
    ],
    "wof:name":"Tryges Nv",
    "wof:placetype":"venue"
},
  "geometry": {"coordinates":[4.494407177,51.2324638367],"type":"Point"}
}