{
  "type": "Feature",
  "properties": {
    "addr:full":"Avenue Charles Quint 400 Bruxelles (ganshoren) Bruxelles-Capitale 1083",
    "addr:housenumber":"400",
    "addr:postcode":"1083",
    "addr:street":"Avenue Charles Quint",
    "iso:country":"BE",
    "sg:address":"Avenue Charles Quint 400",
    "sg:city":"Bruxelles (ganshoren)",
    "sg:classifiers":[
        {
            "category":"Professional",
            "subcategory":"Management & Consulting",
            "type":"Services"
        }
    ],
    "sg:phone":"+32 53 67 25 63",
    "sg:postcode":"1083",
    "sg:province":"Bruxelles-Capitale",
    "sg:tags":[
        "-",
        "processing",
        "data",
        "consultant"
    ],
    "wof:name":"Info Quest Sprl",
    "wof:placetype":"venue"
},
  "geometry": {"coordinates":[4.2991089821,50.8720245361],"type":"Point"}
}