{
  "type": "Feature",
  "properties": {
    "addr:full":"Rue Fernand Piron 2a Mons Hainaut 7011",
    "addr:housenumber":"2a",
    "addr:postcode":"7011",
    "addr:street":"Rue Fernand Piron;Hainaut",
    "iso:country":"BE",
    "sg:address":"Rue Fernand Piron 2a",
    "sg:city":"Mons",
    "sg:orig_category":"Loodgieterij, verwarming and sanitaire installaties",
    "sg:phone":"+32 2 268 18 64",
    "sg:postcode":"7011",
    "sg:province":"Hainaut",
    "wof:name":"Ets. Piron",
    "wof:placetype":"venue"
},
  "geometry": {"coordinates":[4.3895797729,50.898399353],"type":"Point"}
}