{
  "type": "Feature",
  "properties": {
    "addr:full":"Rue Baty-des-puissances 1 Jemeppe-sur-sambre Namur 5190",
    "addr:housenumber":"1",
    "addr:postcode":"5190",
    "addr:street":"Rue Baty-Des-Puissances",
    "iso:country":"BE",
    "sg:address":"Rue Baty-des-puissances 1",
    "sg:city":"Jemeppe-sur-sambre",
    "sg:orig_category":"Produits surgel\u00e9s Gr",
    "sg:phone":"+32 71 74 42 68",
    "sg:postcode":"5190",
    "sg:province":"Namur",
    "wof:name":"Covee",
    "wof:placetype":"venue"
},
  "geometry": {"coordinates":[4.6703448296,50.4645042419],"type":"Point"}
}