{
  "type": "Feature",
  "properties": {
    "iso:country":"BE",
    "sg:address":"Roesemslos 17bd",
    "sg:city":"Ternat",
    "sg:orig_category":"Installation \u00e9lectrique r\u00e9sidentielle",
    "sg:phone":"+32 2 582 75 64",
    "sg:postcode":"1742",
    "sg:province":"Vlaams-Brabant",
    "wof:name":"De Meersman En Co",
    "wof:placetype":"venue"
},
  "geometry": {"coordinates":[4.1357159615,50.8686523438],"type":"Point"}
}