{
  "type": "Feature",
  "properties": {
    "iso:country":"BE",
    "sg:address":"Rue De Septembre 7",
    "sg:city":"Jodoigne",
    "sg:classifiers":[
        {
            "category":"Shopping",
            "subcategory":"Clothing, Apparel, & Fashions",
            "type":"Retail Goods"
        }
    ],
    "sg:phone":"+32 10 81 64 39",
    "sg:postcode":"1370",
    "sg:province":"Brabant Wallon",
    "sg:tags":[
        "boutique"
    ],
    "wof:name":"Modana Sa",
    "wof:placetype":"venue"
},
  "geometry": {"coordinates":[4.8771767616,50.7239265442],"type":"Point"}
}