{
  "type": "Feature",
  "properties": {
    "iso:country":"BE",
    "sg:address":"Leopoldstraat 6",
    "sg:city":"Zemst",
    "sg:classifiers":[
        {
            "category":"Farming",
            "subcategory":"Fish & Marine Products",
            "type":"Manufacturing & Wholesale Goods"
        }
    ],
    "sg:phone":"+32 15 61 41 44",
    "sg:postcode":"1980",
    "sg:province":"Vlaams-Brabant",
    "sg:tags":[
        "retail",
        "-",
        "shellfish"
    ],
    "wof:name":"Luc",
    "wof:placetype":"venue"
},
  "geometry": {"coordinates":[4.4623451233,50.9840087891],"type":"Point"}
}