{
  "type": "Feature",
  "properties": {
    "addr:full":"Rue Citadelle 39 Moeskroen/mouscron Hainaut 7712",
    "addr:housenumber":"39",
    "addr:postcode":"7712",
    "addr:street":"Rue Citadelle",
    "iso:country":"BE",
    "sg:address":"Rue Citadelle 39",
    "sg:city":"Moeskroen/mouscron",
    "sg:classifiers":[
        {
            "category":"Personal",
            "subcategory":"Beauty Salon",
            "type":"Services"
        }
    ],
    "sg:phone":"+32 56 34 60 24",
    "sg:postcode":"7712",
    "sg:province":"Hainaut",
    "sg:tags":[
        "de",
        "coiffure"
    ],
    "wof:name":"Coiffure Marie-rose",
    "wof:placetype":"venue"
},
  "geometry": {"coordinates":[3.2535879612,50.714931488],"type":"Point"}
}