{
  "type": "Feature",
  "properties": {
    "iso:country":"BE",
    "sg:address":"Zeedijk-het Zoute 786b4",
    "sg:city":"Knokke-heist",
    "sg:orig_category":"Eclairage et \u00e9quipements du foyer. Meubles D\u00e9taillants, Am\u00e9nagement de B\u00e2timents et de Cuisines",
    "sg:phone":"+32 50 60 66 71",
    "sg:postcode":"8300",
    "sg:province":"West-Vlaanderen",
    "wof:name":"Raffinato",
    "wof:placetype":"venue"
},
  "geometry": {"coordinates":[3.3267199993,51.3504714966],"type":"Point"}
}