{
  "type": "Feature",
  "properties": {
    "addr:full":"Bruinbekestraat 24 Wichelen (schellebelle) Oost-Vlaanderen 9260",
    "addr:housenumber":"24",
    "addr:postcode":"9260",
    "addr:street":"Bruinbekestraat",
    "iso:country":"BE",
    "sg:address":"Bruinbekestraat 24",
    "sg:city":"Wichelen (schellebelle)",
    "sg:classifiers":[
        {
            "category":"Retail",
            "subcategory":"Auto Repair",
            "type":"Services"
        }
    ],
    "sg:phone":"+32 9 369 16 28",
    "sg:postcode":"9260",
    "sg:province":"Oost-Vlaanderen",
    "sg:tags":[
        "garage"
    ],
    "wof:name":"De Creemer C",
    "wof:placetype":"venue"
},
  "geometry": {"coordinates":[3.9517440796,50.9974708557],"type":"Point"}
}