{
  "type": "Feature",
  "properties": {
    "iso:country":"BE",
    "sg:address":"Rue Des R\u00c9sistants 55",
    "sg:city":"Mons",
    "sg:orig_category":"Gespecialiseerde residenti\u00eble bouw Tuinen",
    "sg:phone":"+32 65 35 12 92",
    "sg:postcode":"7030",
    "sg:province":"Hainaut",
    "wof:name":"Dieu Et Julien",
    "wof:placetype":"venue"
},
  "geometry": {"coordinates":[4.0108299255,50.4393882751],"type":"Point"}
}