{
  "type": "Feature",
  "properties": {
    "addr:full":"Zaventemsesteenweg 63 Machelen (diegem) Vlaams-Brabant 1831",
    "addr:housenumber":"63",
    "addr:postcode":"1831",
    "addr:street":"Zaventemsesteenweg",
    "iso:country":"BE",
    "sg:address":"Zaventemsesteenweg 63",
    "sg:city":"Machelen (diegem)",
    "sg:classifiers":[
        {
            "category":"Mining & Drilling",
            "type":"Manufacturing & Wholesale Goods"
        }
    ],
    "sg:phone":"+32 69 25 25 11",
    "sg:postcode":"1831",
    "sg:province":"Vlaams-Brabant",
    "sg:tags":[
        "quarry"
    ],
    "wof:name":"C.c.b. Compagnie Des Ciments Belges S.a.",
    "wof:placetype":"venue"
},
  "geometry": {"coordinates":[3.4895200729,50.5959091187],"type":"Point"}
}