{
  "type": "Feature",
  "properties": {
    "iso:country":"BE",
    "sg:address":"Boulevard Deuxi\u00e8me Arm\u00e9e Britannique 99",
    "sg:city":"Bruxelles (forest)",
    "sg:classifiers":[
        {
            "category":"Airport",
            "subcategory":"International",
            "type":"Transportation"
        }
    ],
    "sg:phone":"+32 2 340 74 74",
    "sg:postcode":"1190",
    "sg:province":"Bruxelles-Capitale",
    "sg:tags":[
        "-",
        "transport"
    ],
    "wof:name":"Transfesa Benelux",
    "wof:placetype":"venue"
},
  "geometry": {"coordinates":[4.3193449974,50.8171806335],"type":"Point"}
}