{
  "type": "Feature",
  "properties": {
    "iso:country":"BE",
    "sg:address":"Moorselbaan 55",
    "sg:city":"Aalst",
    "sg:classifiers":[
        {
            "category":"Food & Beverages",
            "subcategory":"Meat & Fish",
            "type":"Retail Goods"
        }
    ],
    "sg:phone":"+32 53 21 26 15",
    "sg:postcode":"9300",
    "sg:province":"Oost-Vlaanderen",
    "sg:tags":[
        "bedspread",
        "blanket",
        "-"
    ],
    "wof:name":"Petex Bvba",
    "wof:placetype":"venue"
},
  "geometry": {"coordinates":[4.0488767624,50.9413757324],"type":"Point"}
}