{
  "type": "Feature",
  "properties": {
    "addr:full":"Lange Steenstraat 10 Gent Oost-Vlaanderen 9000",
    "addr:housenumber":"10",
    "addr:postcode":"9000",
    "addr:street":"Lange Steenstraat;Oost-Vlaanderen",
    "iso:country":"BE",
    "sg:address":"Lange Steenstraat 10",
    "sg:city":"Gent",
    "sg:classifiers":[
        {
            "category":"Restaurant",
            "type":"Food & Drink"
        }
    ],
    "sg:phone":"+32 9 233 72 24",
    "sg:postcode":"9000",
    "sg:province":"Oost-Vlaanderen",
    "wof:name":"De Geschoeide Karmeliet",
    "wof:placetype":"venue"
},
  "geometry": {"coordinates":[3.7213668823,51.0585289001],"type":"Point"}
}