{
  "type": "Feature",
  "properties": {
    "addr:full":"Avenue Roi Albert 2 Andenne Namur 5300",
    "addr:housenumber":"2",
    "addr:postcode":"5300",
    "addr:street":"Avenue Roi Albert",
    "iso:country":"BE",
    "sg:address":"Avenue Roi Albert 2",
    "sg:city":"Andenne",
    "sg:classifiers":[
        {
            "category":"Bars & Pubs",
            "type":"Food & Drink"
        }
    ],
    "sg:phone":"+32 85 84 19 35",
    "sg:postcode":"5300",
    "sg:province":"Namur",
    "wof:name":"Caves D'artois (aux)",
    "wof:placetype":"venue"
},
  "geometry": {"coordinates":[5.0966291428,50.4911155701],"type":"Point"}
}