{
  "type": "Feature",
  "properties": {
    "addr:full":"Etikhovestraat 19 Maarkedal Oost-Vlaanderen 9680",
    "addr:housenumber":"19",
    "addr:postcode":"9680",
    "addr:street":"Etikhovestraat",
    "iso:country":"BE",
    "sg:address":"Etikhovestraat 19",
    "sg:city":"Maarkedal",
    "sg:classifiers":[
        {
            "category":"Autos & Motor Vehicles",
            "subcategory":"Fuel & Gas Station",
            "type":"Retail Goods"
        }
    ],
    "sg:phone":"+32 55 31 23 48",
    "sg:postcode":"9680",
    "sg:province":"Oost-Vlaanderen",
    "sg:tags":[
        "stations-service",
        "carburants"
    ],
    "wof:name":"Christiane Martens",
    "wof:placetype":"venue"
},
  "geometry": {"coordinates":[3.6238350868,50.8153686523],"type":"Point"}
}