{
  "type": "Feature",
  "properties": {
    "addr:full":"Adriaan Sanderslei 13 Aartselaar Antwerpen 2630",
    "addr:housenumber":"13",
    "addr:postcode":"2630",
    "addr:street":"Adriaan Sanderslei",
    "iso:country":"BE",
    "sg:address":"Adriaan Sanderslei 13",
    "sg:city":"Aartselaar",
    "sg:classifiers":[
        {
            "category":"Retail",
            "subcategory":"Laundry & Dry Cleaning",
            "type":"Services"
        }
    ],
    "sg:phone":"+32 3 887 56 34",
    "sg:postcode":"2630",
    "sg:province":"Antwerpen",
    "sg:tags":[
        "dyer",
        "cleaner"
    ],
    "wof:name":"Reda Bvba",
    "wof:placetype":"venue"
},
  "geometry": {"coordinates":[4.3931808472,51.1324462891],"type":"Point"}
}