{
  "type": "Feature",
  "properties": {
    "addr:full":"Koning Leopoldlaan 77 Maldegem Oost-Vlaanderen 9990",
    "addr:housenumber":"77",
    "addr:postcode":"9990",
    "addr:street":"Koning Leopoldlaan",
    "iso:country":"BE",
    "sg:address":"Koning Leopoldlaan 77",
    "sg:city":"Maldegem",
    "sg:orig_category":"Rev\u00eatements de sols and murs",
    "sg:phone":"+32 50 71 11 05",
    "sg:postcode":"9990",
    "sg:province":"Oost-Vlaanderen",
    "wof:name":"Van Rie Interieur",
    "wof:placetype":"venue"
},
  "geometry": {"coordinates":[3.4629099369,51.2038841248],"type":"Point"}
}