{
  "type": "Feature",
  "properties": {
    "iso:country":"BE",
    "sg:address":"Avenue Fran\u00c7ois Cornesse 3",
    "sg:city":"Aywaille",
    "sg:orig_category":"Juwelen and horloges",
    "sg:phone":"+32 4 384 74 70",
    "sg:postcode":"4920",
    "sg:province":"Li\u00e8ge",
    "wof:name":"Maison Castro",
    "wof:placetype":"venue"
},
  "geometry": {"coordinates":[5.6746530533,50.4745178223],"type":"Point"}
}