{
  "type": "Feature",
  "properties": {
    "addr:full":"Transvaalstraat 22 Waregem West-Vlaanderen 8793",
    "addr:housenumber":"22",
    "addr:postcode":"8793",
    "addr:street":"Transvaalstraat",
    "iso:country":"BE",
    "sg:address":"Transvaalstraat 22",
    "sg:city":"Waregem",
    "sg:classifiers":[
        {
            "category":"Insurance",
            "subcategory":"Insurance Agent",
            "type":"Services"
        }
    ],
    "sg:phone":"+32 56 60 87 85",
    "sg:postcode":"8793",
    "sg:province":"West-Vlaanderen",
    "sg:tags":[
        "verzekeringsmakelaars",
        "expert"
    ],
    "wof:name":"Fa. Bruyneel",
    "wof:placetype":"venue"
},
  "geometry": {"coordinates":[3.4086270332,50.9015045166],"type":"Point"}
}