{
  "type": "Feature",
  "properties": {
    "addr:full":"Bergensesteenweg 104 Sint-pieters-leeuw Vlaams-Brabant 1600",
    "addr:housenumber":"104",
    "addr:postcode":"1600",
    "addr:street":"Bergensesteenweg",
    "iso:country":"BE",
    "sg:address":"Bergensesteenweg 104",
    "sg:city":"Sint-pieters-leeuw",
    "sg:orig_category":"Artsen and specialisten",
    "sg:phone":"+32 2 377 13 45",
    "sg:postcode":"1600",
    "sg:province":"Vlaams-Brabant",
    "wof:name":"Raymond Kneuts",
    "wof:placetype":"venue"
},
  "geometry": {"coordinates":[4.2875900269,50.7992172241],"type":"Point"}
}