{
  "type": "Feature",
  "properties": {
    "addr:full":"Chauss\u00e9e D'alsemberg 1152 Bruxelles (uccle) Bruxelles-Capitale 1180",
    "addr:postcode":"1152;1180",
    "addr:street":"Chausse\u0301E D'Alsemberg",
    "iso:country":"BE",
    "sg:address":"Chauss\u00e9e D'alsemberg 1152",
    "sg:city":"Bruxelles (uccle)",
    "sg:classifiers":[
        {
            "category":"Bars & Pubs",
            "type":"Food & Drink"
        }
    ],
    "sg:phone":"+32 2 332 01 23",
    "sg:postcode":"1180",
    "sg:province":"Bruxelles-Capitale",
    "wof:name":"Bistrot (le)",
    "wof:placetype":"venue"
},
  "geometry": {"coordinates":[4.329873085,50.7870025635],"type":"Point"}
}