{
  "type": "Feature",
  "properties": {
    "addr:full":"Langestraat 170 Aarschot Vlaams-Brabant 3202",
    "addr:housenumber":"170",
    "addr:postcode":"3202",
    "addr:street":"Langestraat",
    "iso:country":"BE",
    "sg:address":"Langestraat 170",
    "sg:city":"Aarschot",
    "sg:classifiers":[
        {
            "category":"Cafe",
            "type":"Food & Drink"
        }
    ],
    "sg:phone":"+32 16 50 01 60",
    "sg:postcode":"3202",
    "sg:province":"Vlaams-Brabant",
    "sg:tags":[
        "caf\u00e9s"
    ],
    "wof:name":"Cornelia Vrancken",
    "wof:placetype":"venue"
},
  "geometry": {"coordinates":[4.9074068069,50.9847297668],"type":"Point"}
}