{
  "type": "Feature",
  "properties": {
    "addr:full":"Avenue Des Sorbiers 5 Tournai Hainaut 7500",
    "addr:housenumber":"5",
    "addr:postcode":"7500",
    "addr:street":"Avenue Des Sorbiers",
    "iso:country":"BE",
    "sg:address":"Avenue Des Sorbiers 5",
    "sg:city":"Tournai",
    "sg:classifiers":[
        {
            "category":"Transit Center",
            "subcategory":"Freight",
            "type":"Transportation"
        }
    ],
    "sg:phone":"+32 69 84 53 33",
    "sg:postcode":"7500",
    "sg:province":"Hainaut",
    "sg:tags":[
        "import",
        "export",
        "-"
    ],
    "wof:name":"Calinou Sa",
    "wof:placetype":"venue"
},
  "geometry": {"coordinates":[3.3761999607,50.609703064],"type":"Point"}
}