{
  "type": "Feature",
  "properties": {
    "addr:full":"Rue Jean Philippe 21 Lasne (ohain) Brabant Wallon 1380",
    "addr:housenumber":"21",
    "addr:postcode":"1380",
    "addr:street":"Rue Jean Philippe;Wallon",
    "iso:country":"BE",
    "sg:address":"Rue Jean Philippe 21",
    "sg:city":"Lasne (ohain)",
    "sg:classifiers":[
        {
            "category":"Building & Trades",
            "subcategory":"Cleaning & Sanitation",
            "type":"Services"
        }
    ],
    "sg:phone":"+32 2 653 26 40",
    "sg:postcode":"1380",
    "sg:province":"Brabant Wallon",
    "sg:tags":[
        "cleaner",
        "window"
    ],
    "wof:name":"A.c. Deville",
    "wof:placetype":"venue"
},
  "geometry": {"coordinates":[4.4578490257,50.7180633545],"type":"Point"}
}