{
  "type": "Feature",
  "properties": {
    "addr:full":"Lemmenshoefstraat 9 Dilsen-stokkem Limburg 3650",
    "addr:housenumber":"9",
    "addr:postcode":"3650",
    "addr:street":"Lemmenshoefstraat",
    "iso:country":"BE",
    "sg:address":"Lemmenshoefstraat 9",
    "sg:city":"Dilsen-stokkem",
    "sg:orig_category":"Installation de menuiserie en bois and plastique",
    "sg:phone":"+32 89 79 26 25",
    "sg:postcode":"3650",
    "sg:province":"Limburg",
    "wof:name":"Hubert Kalders",
    "wof:placetype":"venue"
},
  "geometry": {"coordinates":[5.7119002342,51.0363197327],"type":"Point"}
}