{
  "type": "Feature",
  "properties": {
    "iso:country":"BE",
    "sg:address":"Rue Du Maka 12",
    "sg:city":"Jodoigne (jauchelette)",
    "sg:classifiers":[
        {
            "category":"Building & Trades",
            "subcategory":"Electrical",
            "type":"Services"
        }
    ],
    "sg:phone":"+32 10 84 66 30",
    "sg:postcode":"1370",
    "sg:province":"Brabant Wallon",
    "sg:tags":[
        "electric",
        "-",
        "housewiring",
        "contractor"
    ],
    "wof:name":"Star Light Concept",
    "wof:placetype":"venue"
},
  "geometry": {"coordinates":[4.8427391052,50.6845207214],"type":"Point"}
}