{
  "type": "Feature",
  "properties": {
    "addr:full":"All\u00e9e Du Bourgmestre Miessen 3 Dison (andrimont) Li\u00e8ge 4821",
    "addr:housenumber":"3",
    "addr:postcode":"4821",
    "addr:street":"Alle\u0301E Du Bourgmestre Miessen",
    "iso:country":"BE",
    "sg:address":"All\u00e9e Du Bourgmestre Miessen 3",
    "sg:city":"Dison (andrimont)",
    "sg:classifiers":[
        {
            "category":"Health Services",
            "subcategory":"Health Practitioner",
            "type":"Services"
        }
    ],
    "sg:phone":"+32 87 34 10 01",
    "sg:postcode":"4821",
    "sg:province":"Li\u00e8ge",
    "sg:tags":[
        "physiotherapist"
    ],
    "wof:name":"Frederich Fran\u00e7oise",
    "wof:placetype":"venue"
},
  "geometry": {"coordinates":[5.8697500229,50.606338501],"type":"Point"}
}