{
  "type": "Feature",
  "properties": {
    "addr:full":"Montignystraat 34 Antwerpen Antwerpen 2018",
    "addr:housenumber":"34",
    "addr:postcode":"2018",
    "addr:street":"Montignystraat",
    "iso:country":"BE",
    "sg:address":"Montignystraat 34",
    "sg:city":"Antwerpen",
    "sg:classifiers":[
        {
            "category":"Personal",
            "subcategory":"Beauty Salon",
            "type":"Services"
        }
    ],
    "sg:phone":"+32 3 237 95 80",
    "sg:postcode":"2018",
    "sg:province":"Antwerpen",
    "sg:tags":[
        "child",
        "-",
        "hairdressing"
    ],
    "wof:name":"Rembrandt",
    "wof:placetype":"venue"
},
  "geometry": {"coordinates":[4.3918600082,51.2041397095],"type":"Point"}
}