{
  "type": "Feature",
  "properties": {
    "addr:full":"Zavelputstraat 3 Zwalm (beerlegem) Oost-Vlaanderen 9630",
    "addr:housenumber":"3",
    "addr:postcode":"9630",
    "addr:street":"Zavelputstraat;Beerlegem",
    "iso:country":"BE",
    "sg:address":"Zavelputstraat 3",
    "sg:city":"Zwalm (beerlegem)",
    "sg:classifiers":[
        {
            "category":"Professional",
            "subcategory":"Accounting & Tax Preparation",
            "type":"Services"
        }
    ],
    "sg:phone":"+32 55 49 89 60",
    "sg:postcode":"9630",
    "sg:province":"Oost-Vlaanderen",
    "sg:tags":[
        "bookkeeper"
    ],
    "wof:name":"Schepens M",
    "wof:placetype":"venue"
},
  "geometry": {"coordinates":[3.7196528912,50.9083442688],"type":"Point"}
}