{
  "type": "Feature",
  "properties": {
    "iso:country":"BE",
    "sg:address":"Kazernestraat 13",
    "sg:city":"Sint-truiden",
    "sg:orig_category":"Overheidsdiensten",
    "sg:phone":"+32 11 70 14 14",
    "sg:postcode":"3800",
    "sg:province":"Limburg",
    "wof:name":"Stadsbestuur",
    "wof:placetype":"venue"
},
  "geometry": {"coordinates":[5.182071209,50.8162727356],"type":"Point"}
}