{
  "type": "Feature",
  "properties": {
    "addr:full":"Kerkstraat 21 Waasmunster Oost-Vlaanderen 9250",
    "addr:housenumber":"21",
    "addr:postcode":"9250",
    "addr:street":"Kerkstraat",
    "iso:country":"BE",
    "sg:address":"Kerkstraat 21",
    "sg:city":"Waasmunster",
    "sg:orig_category":"Mus\u00e9es and patrimoine culturel",
    "sg:phone":"+32 9 348 08 58",
    "sg:postcode":"9250",
    "sg:province":"Oost-Vlaanderen",
    "wof:name":"Heemkundig Museum",
    "wof:placetype":"venue"
},
  "geometry": {"coordinates":[4.0842080116,51.1079864502],"type":"Point"}
}