{
  "type": "Feature",
  "properties": {
    "addr:full":"Fonds Des Ch\u00canes 163 Namur Namur 5100",
    "addr:housenumber":"163",
    "addr:postcode":"5100",
    "addr:street":"Des Che\u0302Nes",
    "iso:country":"BE",
    "sg:address":"Fonds Des Ch\u00canes 163",
    "sg:city":"Namur",
    "sg:orig_category":"Artsen and specialisten",
    "sg:phone":"+32 81 46 05 26",
    "sg:postcode":"5100",
    "sg:province":"Namur",
    "wof:name":"V\u00c9ronique De Jong",
    "wof:placetype":"venue"
},
  "geometry": {"coordinates":[4.8519282341,50.4260978699],"type":"Point"}
}