{
  "type": "Feature",
  "properties": {
    "addr:full":"Rue Saint-jacques 4b Binche Hainaut 7130",
    "addr:housenumber":"4b",
    "addr:postcode":"7130",
    "addr:street":"Rue Saint-Jacques",
    "iso:country":"BE",
    "sg:address":"Rue Saint-jacques 4b",
    "sg:city":"Binche",
    "sg:classifiers":[
        {
            "category":"Health Services",
            "subcategory":"Doctor",
            "type":"Services"
        }
    ],
    "sg:phone":"+32 64 33 33 49",
    "sg:postcode":"7130",
    "sg:province":"Hainaut",
    "sg:tags":[
        "medicinephysicians",
        "surgeon"
    ],
    "wof:name":"Basselier S",
    "wof:placetype":"venue"
},
  "geometry": {"coordinates":[4.1650261879,50.4111251831],"type":"Point"}
}