{
  "type": "Feature",
  "properties": {
    "addr:full":"Rue Du G\u00e9n\u00e9ral Bertrand 3 Li\u00e8ge 1 Li\u00e8ge 4000",
    "addr:housenumber":"3;1",
    "addr:postcode":"4000",
    "addr:street":"Rue Du Ge\u0301Ne\u0301Ral Bertrand",
    "iso:country":"BE",
    "sg:address":"Rue Du G\u00e9n\u00e9ral Bertrand 3",
    "sg:city":"Li\u00e8ge 1",
    "sg:classifiers":[
        {
            "category":"Education",
            "subcategory":"School",
            "type":"Public Place"
        }
    ],
    "sg:phone":"+32 4 226 07 51",
    "sg:postcode":"4000",
    "sg:province":"Li\u00e8ge",
    "sg:tags":[
        "primary"
    ],
    "wof:name":"Ecole Saint-s\u00e9pulcre",
    "wof:placetype":"venue"
},
  "geometry": {"coordinates":[5.5588679314,50.6457672119],"type":"Point"}
}