{
  "type": "Feature",
  "properties": {
    "iso:country":"BE",
    "sg:address":"Koerselsesteenweg 75 Box 2",
    "sg:city":"Beringen",
    "sg:classifiers":[
        {
            "category":"Health Services",
            "subcategory":"Dentist",
            "type":"Services"
        }
    ],
    "sg:phone":"+32 11 42 79 91",
    "sg:postcode":"3580",
    "sg:province":"Limburg",
    "wof:name":"Morren Rohnny",
    "wof:placetype":"venue"
},
  "geometry": {"coordinates":[5.2317051888,51.0501060486],"type":"Point"}
}