{
  "type": "Feature",
  "properties": {
    "addr:full":"Boulevard Joseph Tirou 135-5 Charleroi Hainaut 6000",
    "addr:housenumber":"135-5",
    "addr:postcode":"6000",
    "addr:street":"Boulevard Joseph Tirou;Hainaut",
    "iso:country":"BE",
    "sg:address":"Boulevard Joseph Tirou 135-5",
    "sg:city":"Charleroi",
    "sg:classifiers":[
        {
            "category":"Real Estate",
            "subcategory":"Real Estate Services",
            "type":"Services"
        }
    ],
    "sg:phone":"+32 71 30 38 24",
    "sg:postcode":"6000",
    "sg:province":"Hainaut",
    "wof:name":"Bgi",
    "wof:placetype":"venue"
},
  "geometry": {"coordinates":[4.4438791275,50.4078826904],"type":"Point"}
}