{
  "type": "Feature",
  "properties": {
    "iso:country":"BE",
    "sg:address":"Place Bantigny 6",
    "sg:city":"Manage",
    "sg:classifiers":[
        {
            "category":"Health Services",
            "subcategory":"Nursing And Care Facility",
            "type":"Services"
        }
    ],
    "sg:phone":"+32 64 54 87 86",
    "sg:postcode":"7170",
    "sg:province":"Hainaut",
    "sg:tags":[
        "home",
        "rest"
    ],
    "wof:name":"Les Jardins De Scailmont Asbl",
    "wof:placetype":"venue"
},
  "geometry": {"coordinates":[4.2357702255,50.5021209717],"type":"Point"}
}