{
  "type": "Feature",
  "properties": {
    "iso:country":"BE",
    "sg:address":"Generaal Wahislaan 26b16",
    "sg:city":"Schaarbeek/schaerbeek",
    "sg:orig_category":"Boekhouders",
    "sg:phone":"+32 2 726 37 71",
    "sg:postcode":"1030",
    "sg:province":"Bruxelles-Capitale",
    "wof:name":"Evelyne Rottiers",
    "wof:placetype":"venue"
},
  "geometry": {"coordinates":[4.3960371017,50.8590583801],"type":"Point"}
}