{
  "type": "Feature",
  "properties": {
    "addr:full":"Bosstraat 103b Wellen Limburg 3830",
    "addr:housenumber":"103b",
    "addr:postcode":"3830",
    "addr:street":"Bosstraat",
    "iso:country":"BE",
    "sg:address":"Bosstraat 103b",
    "sg:city":"Wellen",
    "sg:orig_category":"Tuinbenodigdheden",
    "sg:phone":"+32 11 37 81 92",
    "sg:postcode":"3830",
    "sg:province":"Limburg",
    "wof:name":"Roland Swennen",
    "wof:placetype":"venue"
},
  "geometry": {"coordinates":[5.3371481895,50.8624954224],"type":"Point"}
}