{
  "type": "Feature",
  "properties": {
    "addr:full":"Chauss\u00e9e De Louvain 15b Beauvechain (hamme-mille) Brabant Wallon 1320",
    "addr:housenumber":"15b",
    "addr:postcode":"1320",
    "addr:street":"Chausse\u0301E De Louvain",
    "iso:country":"BE",
    "sg:address":"Chauss\u00e9e De Louvain 15b",
    "sg:city":"Beauvechain (hamme-mille)",
    "sg:classifiers":[
        {
            "category":"Health Services",
            "subcategory":"Doctor",
            "type":"Services"
        }
    ],
    "sg:phone":"+32 10 86 12 12",
    "sg:postcode":"1320",
    "sg:province":"Brabant Wallon",
    "sg:tags":[
        "medicinephysicians",
        "surgeon"
    ],
    "wof:name":"Everaerts Marie-christine",
    "wof:placetype":"venue"
},
  "geometry": {"coordinates":[4.7921929359,50.7808570862],"type":"Point"}
}