{
  "type": "Feature",
  "properties": {
    "addr:full":"Rue Neuve 5 Braine-le-comte Hainaut 7090",
    "addr:housenumber":"5",
    "addr:postcode":"7090",
    "addr:street":"Rue Neuve",
    "iso:country":"BE",
    "sg:address":"Rue Neuve 5",
    "sg:city":"Braine-le-comte",
    "sg:orig_category":"Installatie van houten of kunststof schrijnwerk",
    "sg:phone":"+32 67 55 37 92",
    "sg:postcode":"7090",
    "sg:province":"Hainaut",
    "wof:name":"Fontaine",
    "wof:placetype":"venue"
},
  "geometry": {"coordinates":[4.1349391937,50.6041603088],"type":"Point"}
}