{
  "type": "Feature",
  "properties": {
    "iso:country":"BE",
    "sg:address":"Vennestraat 279",
    "sg:city":"Genk",
    "sg:orig_category":"M\u00e9decins and sp\u00e9cialistes",
    "sg:phone":"+32 89 35 27 82",
    "sg:postcode":"3600",
    "sg:province":"Limburg",
    "wof:name":"Paul Willems",
    "wof:placetype":"venue"
},
  "geometry": {"coordinates":[5.4898600578,50.9758796692],"type":"Point"}
}