{
  "type": "Feature",
  "properties": {
    "addr:full":"Populierenlaan 49 Aartselaar Antwerpen 2630",
    "addr:housenumber":"49",
    "addr:postcode":"2630",
    "addr:street":"Populierenlaan",
    "iso:country":"BE",
    "sg:address":"Populierenlaan 49",
    "sg:city":"Aartselaar",
    "sg:orig_category":"Loodgieterij, verwarming and sanitaire installaties",
    "sg:phone":"+32 3 888 43 40",
    "sg:postcode":"2630",
    "sg:province":"Antwerpen",
    "wof:name":"W. Andries",
    "wof:placetype":"venue"
},
  "geometry": {"coordinates":[4.3747792244,51.1156768799],"type":"Point"}
}