{
  "type": "Feature",
  "properties": {
    "addr:full":"Leermarkt 30 Box 1 Mechelen Antwerpen 2800",
    "addr:housenumber":"30;1",
    "addr:postcode":"2800",
    "addr:street":"Leermarkt;Box",
    "iso:country":"BE",
    "sg:address":"Leermarkt 30 Box 1",
    "sg:city":"Mechelen",
    "sg:classifiers":[
        {
            "category":"Professional",
            "subcategory":"Accounting & Tax Preparation",
            "type":"Services"
        }
    ],
    "sg:phone":"+32 15 26 29 69",
    "sg:postcode":"2800",
    "sg:province":"Antwerpen",
    "sg:tags":[
        "bookkeeper"
    ],
    "wof:name":"Van Craen P",
    "wof:placetype":"venue"
},
  "geometry": {"coordinates":[4.4824991226,51.0260009766],"type":"Point"}
}