{
  "type": "Feature",
  "properties": {
    "iso:country":"BE",
    "sg:address":"Diestsesteenweg 353",
    "sg:city":"Aarschot",
    "sg:orig_category":"Agences immobili\u00e8res. Promoteurs immobiliers. Services divers aux entreprises",
    "sg:phone":"+32 16 50 90 26",
    "sg:postcode":"3202",
    "sg:province":"Vlaams-Brabant",
    "wof:name":"Huygens Ingenieurs Bureau",
    "wof:placetype":"venue"
},
  "geometry": {"coordinates":[4.8969187737,50.9740180969],"type":"Point"}
}