{
  "type": "Feature",
  "properties": {
    "addr:full":"Rue 't Serstevens 43 Thuin Hainaut 6530",
    "addr:housenumber":"43",
    "addr:postcode":"6530",
    "addr:street":"Rue ' T Serstevens",
    "iso:country":"BE",
    "sg:address":"Rue 't Serstevens 43",
    "sg:city":"Thuin",
    "sg:orig_category":"Banken and kredietinstellingen",
    "sg:phone":"+32 71 59 00 58",
    "sg:postcode":"6530",
    "sg:province":"Hainaut",
    "wof:name":"Fortis",
    "wof:placetype":"venue"
},
  "geometry": {"coordinates":[4.2818689346,50.3416633606],"type":"Point"}
}