{
  "type": "Feature",
  "properties": {
    "addr:full":"Rue De Bruxelles 94 Genappe Brabant Wallon 1472",
    "addr:housenumber":"94",
    "addr:postcode":"1472",
    "addr:street":"Rue De Bruxelles;Wallon",
    "iso:country":"BE",
    "sg:address":"Rue De Bruxelles 94",
    "sg:city":"Genappe",
    "sg:orig_category":"Artiesten and kunstenaars",
    "sg:phone":"+32 67 77 34 47",
    "sg:postcode":"1472",
    "sg:province":"Brabant Wallon",
    "wof:name":"Olivier Leloup",
    "wof:placetype":"venue"
},
  "geometry": {"coordinates":[4.4474749565,50.6152381897],"type":"Point"}
}