{
  "type": "Feature",
  "properties": {
    "addr:full":"Koksijdestraat 6 Veurne West-Vlaanderen 8630",
    "addr:housenumber":"6",
    "addr:postcode":"8630",
    "addr:street":"Koksijdestraat",
    "iso:country":"BE",
    "sg:address":"Koksijdestraat 6",
    "sg:city":"Veurne",
    "sg:orig_category":"Terraces Horeca",
    "sg:phone":"+32 58 31 41 07",
    "sg:postcode":"8630",
    "sg:province":"West-Vlaanderen",
    "wof:name":"Pauwels Nv",
    "wof:placetype":"venue"
},
  "geometry": {"coordinates":[2.6391611099,51.0832633972],"type":"Point"}
}