{
  "type": "Feature",
  "properties": {
    "addr:full":". Lille (groot) Antwerpen 2275",
    "addr:postcode":"2275",
    "addr:street":"Lille Groot Antwerpen",
    "iso:country":"BE",
    "sg:address":".",
    "sg:city":"Lille (groot)",
    "sg:orig_category":"Apotheken",
    "sg:phone":"+32 900 10 500",
    "sg:postcode":"2275",
    "sg:province":"Antwerpen",
    "wof:name":"Apothekers Van Wacht",
    "wof:placetype":"venue"
},
  "geometry": {"coordinates":[4.8245601654,51.2381668091],"type":"Point"}
}