{
  "type": "Feature",
  "properties": {
    "iso:country":"BE",
    "sg:address":"Lentestraat 8",
    "sg:city":"Hasselt",
    "sg:classifiers":[
        {
            "category":"Professional",
            "subcategory":"Management & Consulting",
            "type":"Services"
        }
    ],
    "sg:phone":"+32 11 27 43 57",
    "sg:postcode":"3500",
    "sg:province":"Limburg",
    "sg:tags":[
        "consultant",
        "agency",
        "advertising"
    ],
    "wof:name":"Met Andere Woorden",
    "wof:placetype":"venue"
},
  "geometry": {"coordinates":[5.3443350792,50.9197311401],"type":"Point"}
}