{
  "type": "Feature",
  "properties": {
    "iso:country":"BE",
    "sg:address":"Molenstraat 47",
    "sg:city":"Merelbeke (schelderode)",
    "sg:classifiers":[
        {
            "category":"Science Facility",
            "type":"Public Place"
        }
    ],
    "sg:phone":"+32 9 281 08 51",
    "sg:postcode":"9820",
    "sg:province":"Oost-Vlaanderen",
    "sg:tags":[
        "-",
        "management",
        "data",
        "processing"
    ],
    "wof:name":"Strand Associates",
    "wof:placetype":"venue"
},
  "geometry": {"coordinates":[3.7291309834,50.9679641724],"type":"Point"}
}