{
  "type": "Feature",
  "properties": {
    "iso:country":"BE",
    "sg:address":"Rue Paschal 8",
    "sg:city":"Lobbes",
    "sg:orig_category":"Sportclubs",
    "sg:phone":"+32 71 59 14 23",
    "sg:postcode":"6540",
    "sg:province":"Hainaut",
    "wof:name":"Hector Michel",
    "wof:placetype":"venue"
},
  "geometry": {"coordinates":[4.2692298889,50.3474197388],"type":"Point"}
}