{
  "type": "Feature",
  "properties": {
    "iso:country":"BE",
    "sg:address":"Eksterlaan 4",
    "sg:city":"Brasschaat",
    "sg:classifiers":[
        {
            "category":"Home & Garden",
            "subcategory":"Building Materials",
            "type":"Retail Goods"
        }
    ],
    "sg:phone":"+32 3 653 48 84",
    "sg:postcode":"2930",
    "sg:province":"Antwerpen",
    "sg:tags":[
        "bathroom",
        "installation",
        "accessory"
    ],
    "wof:name":"Hellemans H",
    "wof:placetype":"venue"
},
  "geometry": {"coordinates":[4.5121231079,51.295375824],"type":"Point"}
}