{
  "type": "Feature",
  "properties": {
    "iso:country":"BE",
    "sg:address":"Avenue Bois Le Comte 42",
    "sg:city":"Sprimont (gomz\u00e9-andoumont)",
    "sg:classifiers":[
        {
            "category":"Retail",
            "subcategory":"Auto Rental",
            "type":"Services"
        }
    ],
    "sg:phone":"+32 475 95 51 59",
    "sg:postcode":"4140",
    "sg:province":"Li\u00e8ge",
    "sg:tags":[
        "chauffeur",
        "automobile",
        "driven",
        "-",
        "car"
    ],
    "wof:name":"Trans-mission Officiel-tmo Group",
    "wof:placetype":"venue"
},
  "geometry": {"coordinates":[5.6561131477,50.5471038818],"type":"Point"}
}