{
  "type": "Feature",
  "properties": {
    "addr:full":"Dr\u00e8ve Gustave Fache 3 Box 1 Mouscron (luingne) Hainaut 7700",
    "addr:housenumber":"3;1",
    "addr:postcode":"7700",
    "addr:street":"Dre\u0300Ve Gustave Fache;Box",
    "iso:country":"BE",
    "sg:address":"Dr\u00e8ve Gustave Fache 3 Box 1",
    "sg:city":"Mouscron (luingne)",
    "sg:classifiers":[
        {
            "category":"Insurance",
            "subcategory":"Insurance Agent",
            "type":"Services"
        }
    ],
    "sg:phone":"+32 56 48 18 18",
    "sg:postcode":"7700",
    "sg:province":"Hainaut",
    "sg:tags":[
        "broker"
    ],
    "wof:name":"Sartorius",
    "wof:placetype":"venue"
},
  "geometry": {"coordinates":[3.2145800591,50.7437934875],"type":"Point"}
}