{
  "type": "Feature",
  "properties": {
    "iso:country":"BE",
    "sg:address":"Teniersstraat 67",
    "sg:city":"Vilvoorde",
    "sg:classifiers":[
        {
            "category":"Arena",
            "subcategory":"Sports Club",
            "type":"Entertainment"
        }
    ],
    "sg:phone":"+32 2 253 42 83",
    "sg:postcode":"1800",
    "sg:province":"Vlaams-Brabant",
    "sg:tags":[
        "de"
    ],
    "wof:name":"Strijd En Vreugd",
    "wof:placetype":"venue"
},
  "geometry": {"coordinates":[4.4138641357,50.923915863],"type":"Point"}
}