{
  "type": "Feature",
  "properties": {
    "addr:full":"Eikenlaan 67 Ichtegem West-Vlaanderen 8480",
    "addr:housenumber":"67",
    "addr:postcode":"8480",
    "addr:street":"Eikenlaan",
    "iso:country":"BE",
    "sg:address":"Eikenlaan 67",
    "sg:city":"Ichtegem",
    "sg:classifiers":[
        {
            "category":"Cafe",
            "type":"Food & Drink"
        }
    ],
    "sg:phone":"+32 59 29 07 11",
    "sg:postcode":"8480",
    "sg:province":"West-Vlaanderen",
    "sg:tags":[
        "caf\u00e9s"
    ],
    "wof:name":"Michele Kooy",
    "wof:placetype":"venue"
},
  "geometry": {"coordinates":[3.0322129726,51.1316452026],"type":"Point"}
}