{
  "type": "Feature",
  "properties": {
    "iso:country":"BE",
    "sg:address":"Rue Des Marronniers De Corroy 11a",
    "sg:city":"Gembloux-sur-orneau (corroy-le-ch\u00e2teau)",
    "sg:classifiers":[
        {
            "category":"Health Services",
            "subcategory":"Health Practitioner",
            "type":"Services"
        }
    ],
    "sg:phone":"+32 81 63 40 40",
    "sg:postcode":"5032",
    "sg:province":"Namur",
    "sg:tags":[
        "physiotherapist"
    ],
    "wof:name":"Bauwens L",
    "wof:placetype":"venue"
},
  "geometry": {"coordinates":[4.6531620026,50.537853241],"type":"Point"}
}