{
  "type": "Feature",
  "properties": {
    "addr:full":"Boulevard Cauchy 1 Namur Namur 5000",
    "addr:housenumber":"1",
    "addr:postcode":"5000",
    "addr:street":"Boulevard Cauchy",
    "iso:country":"BE",
    "sg:address":"Boulevard Cauchy 1",
    "sg:city":"Namur",
    "sg:orig_category":"Magasins de r\u00e9parations d'articles personnels et m\u00e9nagers divers",
    "sg:phone":"+32 81 23 14 25",
    "sg:postcode":"5000",
    "sg:province":"Namur",
    "wof:name":"Atelier De Retouches",
    "wof:placetype":"venue"
},
  "geometry": {"coordinates":[4.8689279556,50.4686584473],"type":"Point"}
}