{
  "type": "Feature",
  "properties": {
    "addr:full":"Provincialebaan 94 Buggenhout Oost-Vlaanderen 9255",
    "addr:housenumber":"94",
    "addr:postcode":"9255",
    "addr:street":"Provincialebaan",
    "iso:country":"BE",
    "sg:address":"Provincialebaan 94",
    "sg:city":"Buggenhout",
    "sg:classifiers":[
        {
            "category":"Personal",
            "subcategory":"Beauty Salon",
            "type":"Services"
        }
    ],
    "sg:phone":"+32 52 22 62 02",
    "sg:postcode":"9255",
    "sg:province":"Oost-Vlaanderen",
    "sg:tags":[
        "lady",
        "-",
        "hairdressing"
    ],
    "wof:name":"Jeffrey's International",
    "wof:placetype":"venue"
},
  "geometry": {"coordinates":[4.1871099472,51.0299987793],"type":"Point"}
}