{
  "type": "Feature",
  "properties": {
    "addr:full":"Avenue Louise 375 Bruxelles (ixelles) Bruxelles-Capitale 1050",
    "addr:housenumber":"375",
    "addr:postcode":"1050",
    "addr:street":"Avenue Louise",
    "iso:country":"BE",
    "sg:address":"Avenue Louise 375",
    "sg:city":"Bruxelles (ixelles)",
    "sg:classifiers":[
        {
            "category":"Real Estate",
            "subcategory":"Real Estate Services",
            "type":"Services"
        }
    ],
    "sg:phone":"+32 2 646 95 03",
    "sg:postcode":"1050",
    "sg:province":"Bruxelles-Capitale",
    "wof:name":"Sodenord Sa",
    "wof:placetype":"venue"
},
  "geometry": {"coordinates":[4.3698029518,50.8206291199],"type":"Point"}
}