{
  "type": "Feature",
  "properties": {
    "iso:country":"BE",
    "sg:address":"Torhoutsestraat 3",
    "sg:city":"Oostkamp (ruddervoorde)",
    "sg:classifiers":[
        {
            "category":"Home & Garden",
            "subcategory":"Kitchen Supply",
            "type":"Retail Goods"
        }
    ],
    "sg:phone":"+32 50 27 78 88",
    "sg:postcode":"8020",
    "sg:province":"West-Vlaanderen",
    "sg:tags":[
        "equipment",
        "aircleaning"
    ],
    "wof:name":"Firma Stubbe",
    "wof:placetype":"venue"
},
  "geometry": {"coordinates":[3.2066869736,51.0957336426],"type":"Point"}
}