{
  "type": "Feature",
  "properties": {
    "iso:country":"BE",
    "sg:address":"Ninoofsesteenweg 73",
    "sg:city":"Dilbeek",
    "sg:orig_category":"S\u00e9lection de personnel and placement",
    "sg:phone":"+32 2 568 13 13",
    "sg:postcode":"1700",
    "sg:province":"Vlaams-Brabant",
    "wof:name":"Pharmasearch",
    "wof:placetype":"venue"
},
  "geometry": {"coordinates":[4.2774391174,50.8452377319],"type":"Point"}
}