{
  "type": "Feature",
  "properties": {
    "iso:country":"BE",
    "sg:address":"Rue Is. Meyskens 224",
    "sg:city":"Wemmel",
    "sg:classifiers":[
        {
            "category":"Professional",
            "subcategory":"Computer Services",
            "type":"Services"
        }
    ],
    "sg:phone":"+32 2 531 11 40",
    "sg:postcode":"1780",
    "sg:province":"Vlaams-Brabant",
    "sg:tags":[
        "-",
        "security",
        "processing",
        "data"
    ],
    "wof:name":"Symantec Bvba",
    "wof:placetype":"venue"
},
  "geometry": {"coordinates":[4.3124098778,50.8966712952],"type":"Point"}
}