{
  "type": "Feature",
  "properties": {
    "addr:full":"Rue De La Gare Fleurie Namur (jambes) Namur 5100",
    "addr:postcode":"fleurie;5100",
    "addr:street":"Rue De La Gare",
    "iso:country":"BE",
    "sg:address":"Rue De La Gare Fleurie",
    "sg:city":"Namur (jambes)",
    "sg:classifiers":[
        {
            "category":"Fast Food",
            "type":"Food & Drink"
        }
    ],
    "sg:phone":"+32 81 30 58 36",
    "sg:postcode":"5100",
    "sg:province":"Namur",
    "sg:tags":[
        "fried",
        "stand",
        "potato"
    ],
    "wof:name":"Friterie De La Gare",
    "wof:placetype":"venue"
},
  "geometry": {"coordinates":[4.8750300407,50.4542312622],"type":"Point"}
}