{
  "type": "Feature",
  "properties": {
    "iso:country":"BE",
    "sg:address":"Route De Philippeville 78",
    "sg:city":"Charleroi",
    "sg:orig_category":"Instituts de beaut\u00e9",
    "sg:phone":"+32 71 36 72 16",
    "sg:postcode":"6010",
    "sg:province":"Hainaut",
    "wof:name":"Francoise Matagne",
    "wof:placetype":"venue"
},
  "geometry": {"coordinates":[4.4591608047,50.3907966614],"type":"Point"}
}