{
  "type": "Feature",
  "properties": {
    "iso:country":"BE",
    "sg:address":"Assesteenweg 39",
    "sg:city":"Asse (mollem)",
    "sg:classifiers":[
        {
            "category":"Utilities",
            "subcategory":"Mobile Phone",
            "type":"Services"
        }
    ],
    "sg:phone":"+32 2 454 12 60",
    "sg:postcode":"1730",
    "sg:province":"Vlaams-Brabant",
    "sg:tags":[
        "access",
        "gsm",
        "-",
        "apparatus"
    ],
    "wof:name":"Cetelec Bvba",
    "wof:placetype":"venue"
},
  "geometry": {"coordinates":[4.215982914,50.9160728455],"type":"Point"}
}