{
  "type": "Feature",
  "properties": {
    "iso:country":"BE",
    "sg:address":"Vijfwegstraat 2",
    "sg:city":"Oudenburg",
    "sg:orig_category":"Brood, gebak and snoepgoed",
    "sg:phone":"+32 59 26 60 61",
    "sg:postcode":"8460",
    "sg:province":"West-Vlaanderen",
    "wof:name":"Luc Maene",
    "wof:placetype":"venue"
},
  "geometry": {"coordinates":[3.0023450851,51.1840553284],"type":"Point"}
}