{
  "type": "Feature",
  "properties": {
    "addr:full":"Brusselsesteenweg 383 Asse Vlaams-Brabant 1731",
    "addr:housenumber":"383",
    "addr:postcode":"1731",
    "addr:street":"Brusselsesteenweg",
    "iso:country":"BE",
    "sg:address":"Brusselsesteenweg 383",
    "sg:city":"Asse",
    "sg:orig_category":"Verhuur bouwmachines Verhuur doe-het-zelf materiaal",
    "sg:phone":"+32 2 466 19 05",
    "sg:postcode":"1731",
    "sg:province":"Vlaams-Brabant",
    "wof:name":"Riba Zellik",
    "wof:placetype":"venue"
},
  "geometry": {"coordinates":[4.2545008659,50.8917274475],"type":"Point"}
}