{
  "type": "Feature",
  "properties": {
    "addr:full":"Rue Linette 1 Neupr\u00c9 Li\u00e8ge 4122",
    "addr:housenumber":"1",
    "addr:postcode":"4122",
    "addr:street":"Rue Linette",
    "iso:country":"BE",
    "sg:address":"Rue Linette 1",
    "sg:city":"Neupr\u00c9",
    "sg:orig_category":"Boekhouders",
    "sg:phone":"+32 4 372 00 34",
    "sg:postcode":"4122",
    "sg:province":"Li\u00e8ge",
    "wof:name":"Christian Parisis",
    "wof:placetype":"venue"
},
  "geometry": {"coordinates":[5.5186400414,50.5441703796],"type":"Point"}
}