{
  "type": "Feature",
  "properties": {
    "addr:full":"Rue Barbier 17 Wavre Brabant Wallon 1300",
    "addr:housenumber":"17;1300",
    "addr:street":"Rue Barbier",
    "iso:country":"BE",
    "sg:address":"Rue Barbier 17",
    "sg:city":"Wavre",
    "sg:classifiers":[
        {
            "category":"Shopping",
            "subcategory":"Clothing, Apparel, & Fashions",
            "type":"Retail Goods"
        }
    ],
    "sg:phone":"+32 10 24 82 91",
    "sg:postcode":"1300",
    "sg:province":"Brabant Wallon",
    "sg:tags":[
        "lady",
        "clothing",
        "-"
    ],
    "wof:name":"Cassis",
    "wof:placetype":"venue"
},
  "geometry": {"coordinates":[4.6094508171,50.7157859802],"type":"Point"}
}