{
  "type": "Feature",
  "properties": {
    "addr:full":"Rozenhoek Schilde Antwerpen 2970",
    "addr:postcode":"2970",
    "addr:street":"Rozenhoek",
    "iso:country":"BE",
    "sg:address":"Rozenhoek",
    "sg:city":"Schilde",
    "sg:classifiers":[
        {
            "category":"Arena",
            "subcategory":"Sports Club",
            "type":"Entertainment"
        }
    ],
    "sg:phone":"+32 3 384 27 03",
    "sg:postcode":"2970",
    "sg:province":"Antwerpen",
    "wof:name":"Koninklijke Sportkring",
    "wof:placetype":"venue"
},
  "geometry": {"coordinates":[4.5915818214,51.2279777527],"type":"Point"}
}