{
  "type": "Feature",
  "properties": {
    "addr:full":"Boondaalse Steenweg 6 Elsene/ixelles Bruxelles-Capitale 1050",
    "addr:housenumber":"6",
    "addr:postcode":"1050",
    "addr:street":"Boondaalse Steenweg",
    "iso:country":"BE",
    "sg:address":"Boondaalse Steenweg 6",
    "sg:city":"Elsene/ixelles",
    "sg:orig_category":"Architecten Landmeters",
    "sg:phone":"+32 2 646 29 48",
    "sg:postcode":"1050",
    "sg:province":"Bruxelles-Capitale",
    "wof:name":"Bernard Nicod\u00c8me",
    "wof:placetype":"venue"
},
  "geometry": {"coordinates":[4.3934841156,50.8094520569],"type":"Point"}
}