{
  "type": "Feature",
  "properties": {
    "iso:country":"BE",
    "sg:address":"Rue Henri Lema\u00eetre 23",
    "sg:city":"Namur",
    "sg:classifiers":[
        {
            "category":"Social Services",
            "subcategory":"Job Training",
            "type":"Services"
        }
    ],
    "sg:phone":"+32 81 74 24 48",
    "sg:postcode":"5000",
    "sg:province":"Namur",
    "sg:tags":[
        "personnel"
    ],
    "wof:name":"Piraux A",
    "wof:placetype":"venue"
},
  "geometry": {"coordinates":[4.8539562225,50.4654388428],"type":"Point"}
}