{
  "type": "Feature",
  "properties": {
    "iso:country":"BE",
    "sg:address":"Kortrijksesteenweg 295",
    "sg:city":"Harelbeke",
    "sg:orig_category":"Benzinestations and brandstoffen Herstellingen and onderhoud van auto's Voertuigen",
    "sg:phone":"+32 56 71 38 45",
    "sg:postcode":"8530",
    "sg:province":"West-Vlaanderen",
    "wof:name":"Garage Decock",
    "wof:placetype":"venue"
},
  "geometry": {"coordinates":[3.2922680378,50.8430900574],"type":"Point"}
}