{
  "type": "Feature",
  "properties": {
    "addr:full":"Brielstraat 71 Oosterzele Oost-Vlaanderen 9860",
    "addr:housenumber":"71",
    "addr:postcode":"9860",
    "addr:street":"Brielstraat;Oost-Vlaanderen",
    "iso:country":"BE",
    "sg:address":"Brielstraat 71",
    "sg:city":"Oosterzele",
    "sg:orig_category":"Rundveehouders Varkenskwekers",
    "sg:phone":"+32 9 362 55 71",
    "sg:postcode":"9860",
    "sg:province":"Oost-Vlaanderen",
    "wof:name":"Etienne De Sutter",
    "wof:placetype":"venue"
},
  "geometry": {"coordinates":[3.8103280067,50.9729652405],"type":"Point"}
}