{
  "type": "Feature",
  "properties": {
    "addr:full":"Mechelsesteenweg 826 Vilvoorde Vlaams-Brabant 1800",
    "addr:housenumber":"826",
    "addr:postcode":"1800",
    "addr:street":"Mechelsesteenweg",
    "iso:country":"BE",
    "sg:address":"Mechelsesteenweg 826",
    "sg:city":"Vilvoorde",
    "sg:classifiers":[
        {
            "category":"Manufacturing",
            "subcategory":"Motor Vehicles & Parts",
            "type":"Manufacturing & Wholesale Goods"
        }
    ],
    "sg:phone":"+32 2 252 38 13",
    "sg:postcode":"1800",
    "sg:province":"Vlaams-Brabant",
    "sg:tags":[
        "exhaust",
        "system"
    ],
    "wof:name":"P & L",
    "wof:placetype":"venue"
},
  "geometry": {"coordinates":[4.4511771202,50.9527931213],"type":"Point"}
}