{
  "type": "Feature",
  "properties": {
    "iso:country":"BE",
    "sg:address":"Bezemheidelaan 10",
    "sg:city":"Kalmthout",
    "sg:classifiers":[
        {
            "category":"Insurance",
            "subcategory":"Insurance Agent",
            "type":"Services"
        }
    ],
    "sg:phone":"+32 3 666 87 78",
    "sg:postcode":"2920",
    "sg:province":"Antwerpen",
    "sg:tags":[
        "broker"
    ],
    "wof:name":"Ribbens Verzekeringen Bvba",
    "wof:placetype":"venue"
},
  "geometry": {"coordinates":[4.4743390083,51.3741874695],"type":"Point"}
}