{
  "type": "Feature",
  "properties": {
    "addr:full":"Kruiskerkestraat 14 Ruiselede West-Vlaanderen 8755",
    "addr:housenumber":"14",
    "addr:postcode":"8755",
    "addr:street":"Kruiskerkestraat",
    "iso:country":"BE",
    "sg:address":"Kruiskerkestraat 14",
    "sg:city":"Ruiselede",
    "sg:orig_category":"Enseignement maternel and primaire",
    "sg:phone":"+32 51 68 70 37",
    "sg:postcode":"8755",
    "sg:province":"West-Vlaanderen",
    "wof:name":"Vrije Basisschool",
    "wof:placetype":"venue"
},
  "geometry": {"coordinates":[3.3885359764,51.0664253235],"type":"Point"}
}