{
  "type": "Feature",
  "properties": {
    "addr:full":"Arsenaalstraat 1 Ieper West-Vlaanderen 8900",
    "addr:housenumber":"1",
    "addr:postcode":"8900",
    "addr:street":"Arsenaalstraat",
    "iso:country":"BE",
    "sg:address":"Arsenaalstraat 1",
    "sg:city":"Ieper",
    "sg:orig_category":"Kapsalons",
    "sg:phone":"+32 57 20 80 54",
    "sg:postcode":"8900",
    "sg:province":"West-Vlaanderen",
    "wof:name":"Kapsalon Feeling",
    "wof:placetype":"venue"
},
  "geometry": {"coordinates":[2.8842530251,50.8475151062],"type":"Point"}
}