{
  "type": "Feature",
  "properties": {
    "iso:country":"BE",
    "sg:address":"Place Jean Jacobs 17",
    "sg:city":"Bruxelles",
    "sg:classifiers":[
        {
            "category":"Organizations",
            "subcategory":"Membership Organization",
            "type":"Services"
        }
    ],
    "sg:phone":"+32 2 512 11 99",
    "sg:postcode":"1000",
    "sg:province":"Bruxelles-Capitale",
    "sg:tags":[
        "organisation",
        "tombola"
    ],
    "wof:name":"Tombola Top Top/c.b.u.-b.c.s.",
    "wof:placetype":"venue"
},
  "geometry": {"coordinates":[4.3518590927,50.8348274231],"type":"Point"}
}