{
  "type": "Feature",
  "properties": {
    "addr:full":"Chauss\u00e9e De Tervuren 181 Waterloo Brabant Wallon 1410",
    "addr:housenumber":"181",
    "addr:postcode":"1410",
    "addr:street":"Chausse\u0301E De Tervuren",
    "iso:country":"BE",
    "sg:address":"Chauss\u00e9e De Tervuren 181",
    "sg:city":"Waterloo",
    "sg:orig_category":"Non-Classified Establishments",
    "sg:phone":"+32 2 354 55 15",
    "sg:postcode":"1410",
    "sg:province":"Brabant Wallon",
    "wof:name":"Alansphil Sa",
    "wof:placetype":"venue"
},
  "geometry": {"coordinates":[4.4100937843,50.7146835327],"type":"Point"}
}