{
  "type": "Feature",
  "properties": {
    "iso:country":"BE",
    "sg:address":"Hundelgemsesteenweg 615",
    "sg:city":"Merelbeke",
    "sg:classifiers":[
        {
            "category":"Real Estate",
            "subcategory":"Architect",
            "type":"Services"
        }
    ],
    "sg:phone":"+32 9 324 02 12",
    "sg:postcode":"9820",
    "sg:province":"Oost-Vlaanderen",
    "wof:name":"Garr\u00e9 K",
    "wof:placetype":"venue"
},
  "geometry": {"coordinates":[3.7438390255,50.9798469543],"type":"Point"}
}