{
  "type": "Feature",
  "properties": {
    "iso:country":"BE",
    "sg:address":"Rue De France 87",
    "sg:city":"Erquelinnes (solre-sur-sambre)",
    "sg:classifiers":[
        {
            "category":"Real Estate",
            "subcategory":"Architect",
            "type":"Services"
        }
    ],
    "sg:phone":"+32 71 55 53 84",
    "sg:postcode":"6560",
    "sg:province":"Hainaut",
    "wof:name":"Desalle M",
    "wof:placetype":"venue"
},
  "geometry": {"coordinates":[4.1210989952,50.3031044006],"type":"Point"}
}