{
  "type": "Feature",
  "properties": {
    "iso:country":"BE",
    "sg:address":"Leegstraat 34",
    "sg:city":"Oostrozebeke",
    "sg:classifiers":[
        {
            "category":"Government",
            "subcategory":"City Hall",
            "type":"Public Place"
        }
    ],
    "sg:phone":"+32 56 66 74 72",
    "sg:postcode":"8780",
    "sg:province":"West-Vlaanderen",
    "sg:tags":[
        "interior",
        "painting"
    ],
    "wof:name":"Beel B.v.b.a.",
    "wof:placetype":"venue"
},
  "geometry": {"coordinates":[3.328109026,50.9189224243],"type":"Point"}
}