{
  "type": "Feature",
  "properties": {
    "addr:full":"Brusselsesteenweg 106 Merchtem Vlaams-Brabant 1785",
    "addr:housenumber":"106",
    "addr:postcode":"1785",
    "addr:street":"Brusselsesteenweg",
    "iso:country":"BE",
    "sg:address":"Brusselsesteenweg 106",
    "sg:city":"Merchtem",
    "sg:classifiers":[
        {
            "category":"Cafe",
            "type":"Food & Drink"
        }
    ],
    "sg:phone":"+32 52 37 28 00",
    "sg:postcode":"1785",
    "sg:province":"Vlaams-Brabant",
    "sg:tags":[
        "caf\u00e9s"
    ],
    "wof:name":"Jean Van Malderen",
    "wof:placetype":"venue"
},
  "geometry": {"coordinates":[4.2427210808,50.9519805908],"type":"Point"}
}