{
  "type": "Feature",
  "properties": {
    "iso:country":"BE",
    "sg:address":"Provinciestraat 118",
    "sg:city":"Antwerpen",
    "sg:classifiers":[
        {
            "category":"Restaurant",
            "type":"Food & Drink"
        }
    ],
    "sg:phone":"+32 3 225 02 14",
    "sg:postcode":"2018",
    "sg:province":"Antwerpen",
    "wof:name":"Kertosono",
    "wof:placetype":"venue"
},
  "geometry": {"coordinates":[4.425634861,51.2141494751],"type":"Point"}
}