{
  "type": "Feature",
  "properties": {
    "addr:full":"Chauss\u00c9e Paul Houtart 289 La Louviere Hainaut 7110",
    "addr:housenumber":"289",
    "addr:postcode":"7110",
    "addr:street":"Chausse\u0301E Paul Houtart",
    "iso:country":"BE",
    "sg:address":"Chauss\u00c9e Paul Houtart 289",
    "sg:city":"La Louviere",
    "sg:orig_category":"Brood, gebak and snoepgoed",
    "sg:phone":"+32 64 22 20 02",
    "sg:postcode":"7110",
    "sg:province":"Hainaut",
    "wof:name":"Ets. Wastiau",
    "wof:placetype":"venue"
},
  "geometry": {"coordinates":[4.1570868492,50.4866714478],"type":"Point"}
}