{
  "type": "Feature",
  "properties": {
    "iso:country":"BE",
    "sg:address":"Hippokrateslaan 14",
    "sg:city":"Zaventem",
    "sg:orig_category":"Computers and computerapparatuur Kantoormateriaal",
    "sg:phone":"+32 2 714 71 11",
    "sg:postcode":"1932",
    "sg:province":"Vlaams-Brabant",
    "wof:name":"C.s.c. Computer Sciences",
    "wof:placetype":"venue"
},
  "geometry": {"coordinates":[4.4480037689,50.8543510437],"type":"Point"}
}