{
  "type": "Feature",
  "properties": {
    "iso:country":"BE",
    "sg:address":"Grote Bollostraat 62",
    "sg:city":"Tremelo",
    "sg:classifiers":[
        {
            "category":"Cafe",
            "type":"Food & Drink"
        }
    ],
    "sg:phone":"+32 16 53 02 42",
    "sg:postcode":"3120",
    "sg:province":"Vlaams-Brabant",
    "sg:tags":[
        "caf\u00e9s"
    ],
    "wof:name":"Walter Fioole",
    "wof:placetype":"venue"
},
  "geometry": {"coordinates":[4.7135882378,50.9985580444],"type":"Point"}
}