{
  "type": "Feature",
  "properties": {
    "addr:full":"Franklin Rooseveltlaan 172b3/1 Waregem West-Vlaanderen 8790",
    "addr:housenumber":"172b3 / 1",
    "addr:postcode":"8790",
    "addr:street":"Franklin Rooseveltlaan",
    "iso:country":"BE",
    "sg:address":"Franklin Rooseveltlaan 172b3/1",
    "sg:city":"Waregem",
    "sg:orig_category":"Activit\u00e9s diverses d'imprimerie. Agences de publicit\u00e9",
    "sg:phone":"+32 56 62 51 11",
    "sg:postcode":"8790",
    "sg:province":"West-Vlaanderen",
    "wof:name":"Masters Communication",
    "wof:placetype":"venue"
},
  "geometry": {"coordinates":[3.4412229061,50.874130249],"type":"Point"}
}