{
  "type": "Feature",
  "properties": {
    "addr:full":"Rue Du Xhorre 1 Fl\u00e9malle Li\u00e8ge 4400",
    "addr:housenumber":"1",
    "addr:postcode":"4400",
    "addr:street":"Rue Du Xhorre",
    "iso:country":"BE",
    "sg:address":"Rue Du Xhorre 1",
    "sg:city":"Fl\u00e9malle",
    "sg:classifiers":[
        {
            "category":"Education",
            "subcategory":"School",
            "type":"Public Place"
        }
    ],
    "sg:phone":"+32 4 233 92 53",
    "sg:postcode":"4400",
    "sg:province":"Li\u00e8ge",
    "sg:tags":[
        "primary"
    ],
    "wof:name":"Ecole Communale De La Fontaine",
    "wof:placetype":"venue"
},
  "geometry": {"coordinates":[5.4576430321,50.5693130493],"type":"Point"}
}