{
  "type": "Feature",
  "properties": {
    "addr:full":". Maaseik (groot) Limburg 3680",
    "addr:postcode":"3680",
    "addr:street":"Groot Limburg",
    "iso:country":"BE",
    "sg:address":".",
    "sg:city":"Maaseik (groot)",
    "sg:orig_category":"Apotheken",
    "sg:phone":"+32 900 10 500",
    "sg:postcode":"3680",
    "sg:province":"Limburg",
    "wof:name":"Apothekers Van Wacht",
    "wof:placetype":"venue"
},
  "geometry": {"coordinates":[5.791285038,51.0954208374],"type":"Point"}
}