{
  "type": "Feature",
  "properties": {
    "iso:country":"BE",
    "sg:address":"Roeselaarsestraat 7",
    "sg:city":"Moorslede",
    "sg:classifiers":[
        {
            "category":"Professional",
            "subcategory":"Testing Lab",
            "type":"Services"
        }
    ],
    "sg:phone":"+32 51 77 71 32",
    "sg:postcode":"8890",
    "sg:province":"West-Vlaanderen",
    "sg:tags":[
        "chemist"
    ],
    "wof:name":"Vandeputte S",
    "wof:placetype":"venue"
},
  "geometry": {"coordinates":[3.0607841015,50.8920249939],"type":"Point"}
}