{
  "type": "Feature",
  "properties": {
    "addr:full":"Rue Fl. Letroye 13/32 Wavre Brabant Wallon 1300",
    "addr:housenumber":"13 / 32;1300",
    "addr:street":"Rue Fl. Letroye",
    "iso:country":"BE",
    "sg:address":"Rue Fl. Letroye 13/32",
    "sg:city":"Wavre",
    "sg:orig_category":"Chemicali\u00ebn Gh Drogisterijen",
    "sg:phone":"+32 10 24 51 29",
    "sg:postcode":"1300",
    "sg:province":"Brabant Wallon",
    "wof:name":"La Boutique Du Nettoyage",
    "wof:placetype":"venue"
},
  "geometry": {"coordinates":[4.6133551598,50.7150306702],"type":"Point"}
}