{
  "type": "Feature",
  "properties": {
    "addr:full":"Mooi-boslaan 1 Sint-pieters-woluwe/woluwe-saint-pierre Bruxelles-Capitale 1150",
    "addr:housenumber":"1",
    "addr:postcode":"1150",
    "addr:street":"Mooi-Boslaan;/",
    "iso:country":"BE",
    "sg:address":"Mooi-boslaan 1",
    "sg:city":"Sint-pieters-woluwe/woluwe-saint-pierre",
    "sg:orig_category":"Informaticaconsulenten Werk and personeelsselectie",
    "sg:phone":"+32 2 779 36 00",
    "sg:postcode":"1150",
    "sg:province":"Bruxelles-Capitale",
    "wof:name":"Top European Services",
    "wof:placetype":"venue"
},
  "geometry": {"coordinates":[4.456278801,50.8263626099],"type":"Point"}
}