{
  "type": "Feature",
  "properties": {
    "addr:full":"Werfstraat 108 Brugge West-Vlaanderen 8000",
    "addr:housenumber":"108",
    "addr:postcode":"8000",
    "addr:street":"Werfstraat",
    "iso:country":"BE",
    "sg:address":"Werfstraat 108",
    "sg:city":"Brugge",
    "sg:orig_category":"Zalen voor culturele evenementen",
    "sg:phone":"+32 50 33 05 29",
    "sg:postcode":"8000",
    "sg:province":"West-Vlaanderen",
    "wof:name":"Theater De Werf",
    "wof:placetype":"venue"
},
  "geometry": {"coordinates":[3.2202959061,51.2192268372],"type":"Point"}
}