{
  "type": "Feature",
  "properties": {
    "iso:country":"BE",
    "sg:address":"Oostveldstraat 14",
    "sg:city":"Eeklo",
    "sg:orig_category":"Maroquinerie and articles de voyage",
    "sg:phone":"+32 9 378 19 40",
    "sg:postcode":"9900",
    "sg:province":"Oost-Vlaanderen",
    "wof:name":"Huis Nancy",
    "wof:placetype":"venue"
},
  "geometry": {"coordinates":[3.5770320892,51.1818504333],"type":"Point"}
}