{
  "type": "Feature",
  "properties": {
    "iso:country":"BE",
    "sg:address":"De Dammenlaan 162",
    "sg:city":"Dendermonde",
    "sg:classifiers":[
        {
            "category":"Health Services",
            "subcategory":"Doctor",
            "type":"Services"
        }
    ],
    "sg:phone":"+32 52 21 76 23",
    "sg:postcode":"9200",
    "sg:province":"Oost-Vlaanderen",
    "sg:tags":[
        "medicinephysicians",
        "surgeon"
    ],
    "wof:name":"De Muynck R",
    "wof:placetype":"venue"
},
  "geometry": {"coordinates":[4.0802021027,51.0349617004],"type":"Point"}
}