{
  "type": "Feature",
  "properties": {
    "addr:full":"Van Volxemlaan 235 Vorst/forest Bruxelles-Capitale 1190",
    "addr:housenumber":"235",
    "addr:postcode":"1190",
    "addr:street":"Van Volxemlaan;/ Forest",
    "iso:country":"BE",
    "sg:address":"Van Volxemlaan 235",
    "sg:city":"Vorst/forest",
    "sg:orig_category":"Plaatsen van vloer- and muurbekleding Schilders",
    "sg:phone":"+32 2 345 53 10",
    "sg:postcode":"1190",
    "sg:province":"Bruxelles-Capitale",
    "wof:name":"Ascryl",
    "wof:placetype":"venue"
},
  "geometry": {"coordinates":[4.3260831833,50.8208122253],"type":"Point"}
}