{
  "type": "Feature",
  "properties": {
    "iso:country":"BE",
    "sg:address":"Bloemendael 11",
    "sg:city":"Bi\u00e9v\u00e8ne",
    "sg:classifiers":[
        {
            "category":"Retail",
            "subcategory":"Auto Repair",
            "type":"Services"
        }
    ],
    "sg:phone":"+32 54 58 82 04",
    "sg:postcode":"1547",
    "sg:province":"Vlaams-Brabant",
    "sg:tags":[
        "garage"
    ],
    "wof:name":"Capiau J",
    "wof:placetype":"venue"
},
  "geometry": {"coordinates":[3.9171009064,50.7234191895],"type":"Point"}
}