{
  "type": "Feature",
  "properties": {
    "addr:full":"Lariksenstraat 84 Elsene/ixelles Bruxelles-Capitale 1050",
    "addr:housenumber":"84",
    "addr:postcode":"1050",
    "addr:street":"Lariksenstraat",
    "iso:country":"BE",
    "sg:address":"Lariksenstraat 84",
    "sg:city":"Elsene/ixelles",
    "sg:orig_category":"Artsen and specialisten Paramedische behandelingen",
    "sg:phone":"+32 2 345 67 14",
    "sg:postcode":"1050",
    "sg:province":"Bruxelles-Capitale",
    "wof:name":"S. Kenigsman",
    "wof:placetype":"venue"
},
  "geometry": {"coordinates":[4.3624649048,50.8196525574],"type":"Point"}
}