{
  "type": "Feature",
  "properties": {
    "addr:full":"Waterputdreef 12 Koksijde West-Vlaanderen 8020",
    "addr:housenumber":"12",
    "addr:postcode":"8020",
    "addr:street":"Waterputdreef",
    "iso:country":"BE",
    "sg:address":"Waterputdreef 12",
    "sg:city":"Koksijde",
    "sg:orig_category":"Projectontwikkelaars",
    "sg:phone":"+32 50 27 96 27",
    "sg:postcode":"8020",
    "sg:province":"West-Vlaanderen",
    "wof:name":"Villabouw De Moor",
    "wof:placetype":"venue"
},
  "geometry": {"coordinates":[3.2350599766,51.1533241272],"type":"Point"}
}