{
  "type": "Feature",
  "properties": {
    "iso:country":"BE",
    "sg:address":"Krommewege 31g",
    "sg:city":"Maldegem",
    "sg:orig_category":"Afvalwaterverwerking and ontstoppingsdiensten Huisvuilophaling and -verwerking Loodgieterij, verwarm",
    "sg:phone":"+32 50 71 27 92",
    "sg:postcode":"9990",
    "sg:province":"Oost-Vlaanderen",
    "wof:name":"Cleaning De Br\u00c9e",
    "wof:placetype":"venue"
},
  "geometry": {"coordinates":[3.4675130844,51.1946372986],"type":"Point"}
}