{
  "type": "Feature",
  "properties": {
    "addr:full":"Chemin D'horrues 3 Braine-le-comte Hainaut 7090",
    "addr:housenumber":"3",
    "addr:postcode":"7090",
    "addr:street":"Chemin D'Horrues",
    "iso:country":"BE",
    "sg:address":"Chemin D'horrues 3",
    "sg:city":"Braine-le-comte",
    "sg:orig_category":"Eleveurs de bovins",
    "sg:phone":"+32 67 55 21 05",
    "sg:postcode":"7090",
    "sg:province":"Hainaut",
    "wof:name":"Jean-louis Gustin",
    "wof:placetype":"venue"
},
  "geometry": {"coordinates":[4.1124210358,50.6122894287],"type":"Point"}
}