{
  "type": "Feature",
  "properties": {
    "addr:full":"Boterbloemstraat 7 Houthulst West-Vlaanderen 8650",
    "addr:housenumber":"7",
    "addr:postcode":"8650",
    "addr:street":"Boterbloemstraat",
    "iso:country":"BE",
    "sg:address":"Boterbloemstraat 7",
    "sg:city":"Houthulst",
    "sg:orig_category":"Installation \u00e9lectrique r\u00e9sidentielle",
    "sg:phone":"+32 51 54 47 69",
    "sg:postcode":"8650",
    "sg:province":"West-Vlaanderen",
    "wof:name":"Joseph Dekeyser",
    "wof:placetype":"venue"
},
  "geometry": {"coordinates":[2.9509439468,50.9778862],"type":"Point"}
}