{
  "type": "Feature",
  "properties": {
    "addr:full":"Aarschotsesteenweg 403 Leuven (wilsele) Vlaams-Brabant 3012",
    "addr:housenumber":"403",
    "addr:postcode":"3012",
    "addr:street":"Aarschotsesteenweg",
    "iso:country":"BE",
    "sg:address":"Aarschotsesteenweg 403",
    "sg:city":"Leuven (wilsele)",
    "sg:orig_category":"Articles de jardin. Quincailleries. Machines and mat\u00e9riel agricoles Gr",
    "sg:phone":"+32 16 44 87 49",
    "sg:postcode":"3012",
    "sg:province":"Vlaams-Brabant",
    "wof:name":"Decr\u00c9 Tuinmachines",
    "wof:placetype":"venue"
},
  "geometry": {"coordinates":[4.7203707695,50.9231758118],"type":"Point"}
}