{
  "type": "Feature",
  "properties": {
    "iso:country":"BE",
    "sg:address":"Rue De Scarbotte 7",
    "sg:city":"Seneffe (arquennes)",
    "sg:orig_category":"Non-Classified Establishments",
    "sg:phone":"+32 67 87 83 49",
    "sg:postcode":"7181",
    "sg:province":"Hainaut",
    "wof:name":"Devry Sales & Promotion",
    "wof:placetype":"venue"
},
  "geometry": {"coordinates":[4.2589969635,50.5626296997],"type":"Point"}
}