{
  "type": "Feature",
  "properties": {
    "addr:full":"Lange Zoutstraat 27-29 Aalst Oost-Vlaanderen 9300",
    "addr:housenumber":"27-29",
    "addr:postcode":"9300",
    "addr:street":"Lange Zoutstraat",
    "iso:country":"BE",
    "sg:address":"Lange Zoutstraat 27-29",
    "sg:city":"Aalst",
    "sg:orig_category":"Chaussures",
    "sg:phone":"+32 53 77 13 78",
    "sg:postcode":"9300",
    "sg:province":"Oost-Vlaanderen",
    "wof:name":"Skoll",
    "wof:placetype":"venue"
},
  "geometry": {"coordinates":[4.039293766,50.9371452332],"type":"Point"}
}