{
  "type": "Feature",
  "properties": {
    "iso:country":"BE",
    "sg:address":"Montenegrostraat 173",
    "sg:city":"Vorst/forest",
    "sg:orig_category":"Onderhoud van kantoor- and computeruitrusting",
    "sg:phone":"+32 2 537 86 51",
    "sg:postcode":"1190",
    "sg:province":"Bruxelles-Capitale",
    "wof:name":"Electronics 2000",
    "wof:placetype":"venue"
},
  "geometry": {"coordinates":[4.3303580284,50.82654953],"type":"Point"}
}