{
  "type": "Feature",
  "properties": {
    "addr:full":"Boulevard Du Roi Albert 156 Tournai Hainaut 7500",
    "addr:housenumber":"156",
    "addr:postcode":"7500",
    "addr:street":"Boulevard Du Roi Albert",
    "iso:country":"BE",
    "sg:address":"Boulevard Du Roi Albert 156",
    "sg:city":"Tournai",
    "sg:classifiers":[
        {
            "category":"Communications",
            "subcategory":"Film & Video Production",
            "type":"Services"
        }
    ],
    "sg:phone":"+32 69 84 56 04",
    "sg:postcode":"7500",
    "sg:province":"Hainaut",
    "sg:tags":[
        "sound",
        "recording",
        "studio"
    ],
    "wof:name":"B.h.s.",
    "wof:placetype":"venue"
},
  "geometry": {"coordinates":[3.3890609741,50.600402832],"type":"Point"}
}