{
  "type": "Feature",
  "properties": {
    "addr:full":"Rue Ravenstein 44 Bruxelles Bruxelles-Capitale 1000",
    "addr:housenumber":"44",
    "addr:postcode":"1000",
    "addr:street":"Rue Ravenstein",
    "iso:country":"BE",
    "sg:address":"Rue Ravenstein 44",
    "sg:city":"Bruxelles",
    "sg:classifiers":[
        {
            "category":"Airline",
            "type":"Transportation"
        }
    ],
    "sg:phone":"+32 2 502 82 70",
    "sg:postcode":"1000",
    "sg:province":"Bruxelles-Capitale",
    "wof:name":"China Eastern Airlines",
    "wof:placetype":"venue"
},
  "geometry": {"coordinates":[4.3594450951,50.8449745178],"type":"Point"}
}