{
  "type": "Feature",
  "properties": {
    "addr:full":"Chemin Du Tordoir 7 Soignies (neufvilles) Hainaut 7063",
    "addr:housenumber":"7",
    "addr:postcode":"7063",
    "addr:street":"Chemin Du Tordoir",
    "iso:country":"BE",
    "sg:address":"Chemin Du Tordoir 7",
    "sg:city":"Soignies (neufvilles)",
    "sg:classifiers":[
        {
            "category":"Building & Trades",
            "subcategory":"Landscaping Services",
            "type":"Services"
        }
    ],
    "sg:phone":"+32 67 33 39 46",
    "sg:postcode":"7063",
    "sg:province":"Hainaut",
    "sg:tags":[
        "gardening",
        "garden",
        "maintenance"
    ],
    "wof:name":"Devos M",
    "wof:placetype":"venue"
},
  "geometry": {"coordinates":[3.993940115,50.5837898254],"type":"Point"}
}