{
  "type": "Feature",
  "properties": {
    "addr:full":"Bosdorp 36 Stekene Oost-Vlaanderen 9190",
    "addr:housenumber":"36",
    "addr:postcode":"9190",
    "addr:street":"Bosdorp",
    "iso:country":"BE",
    "sg:address":"Bosdorp 36",
    "sg:city":"Stekene",
    "sg:classifiers":[
        {
            "category":"Insurance",
            "subcategory":"Life Insurance",
            "type":"Services"
        }
    ],
    "sg:phone":"+32 3 779 96 96",
    "sg:postcode":"9190",
    "sg:province":"Oost-Vlaanderen",
    "sg:tags":[
        "assurance"
    ],
    "wof:name":"J. Goossens",
    "wof:placetype":"venue"
},
  "geometry": {"coordinates":[4.0305390358,51.1978721619],"type":"Point"}
}