{
  "type": "Feature",
  "properties": {
    "iso:country":"BE",
    "sg:address":"Rue De L\u00b4eglise 39",
    "sg:city":"Eupen",
    "sg:orig_category":"Meubles D\u00e9taillants, Am\u00e9nagement de B\u00e2timents et de Cuisines",
    "sg:phone":"+32 87 56 16 75",
    "sg:postcode":"4700",
    "sg:province":"Li\u00e8ge",
    "wof:name":"K & K Interiors",
    "wof:placetype":"venue"
},
  "geometry": {"coordinates":[6.0328989029,50.6300888062],"type":"Point"}
}