{
  "type": "Feature",
  "properties": {
    "iso:country":"BE",
    "sg:address":"Gijmelsesteenweg 403",
    "sg:city":"Aarschot",
    "sg:orig_category":"Slagers",
    "sg:phone":"+32 16 56 99 56",
    "sg:postcode":"3201",
    "sg:province":"Vlaams-Brabant",
    "wof:name":"Beenhouwerij Gert",
    "wof:placetype":"venue"
},
  "geometry": {"coordinates":[4.8669338226,51.0117454529],"type":"Point"}
}