{
  "type": "Feature",
  "properties": {
    "iso:country":"BE",
    "sg:address":"Amerikalei 204",
    "sg:city":"Antwerpen",
    "sg:orig_category":"Activit\u00e9s r\u00e9cr\u00e9atives diverses",
    "sg:phone":"+32 3 237 41 79",
    "sg:postcode":"2000",
    "sg:province":"Antwerpen",
    "wof:name":"Bridge Club Ternesse",
    "wof:placetype":"venue"
},
  "geometry": {"coordinates":[4.390463829,51.2053527832],"type":"Point"}
}