{
  "type": "Feature",
  "properties": {
    "iso:country":"BE",
    "sg:address":"Grote Appelstraat 21",
    "sg:city":"Haacht",
    "sg:classifiers":[
        {
            "category":"Recreation",
            "type":"Entertainment"
        }
    ],
    "sg:phone":"+32 16 60 99 21",
    "sg:postcode":"3150",
    "sg:province":"Vlaams-Brabant",
    "sg:tags":[
        "diver",
        "amusement"
    ],
    "wof:name":"Eulaerts Kurt",
    "wof:placetype":"venue"
},
  "geometry": {"coordinates":[4.635324955,50.9814033508],"type":"Point"}
}