{
  "type": "Feature",
  "properties": {
    "iso:country":"BE",
    "sg:address":"Rue De Campine 21a",
    "sg:city":"Li\u00e8ge 1",
    "sg:classifiers":[
        {
            "category":"Health Services",
            "subcategory":"Health Practitioner",
            "type":"Services"
        }
    ],
    "sg:phone":"+32 4 226 04 89",
    "sg:postcode":"4000",
    "sg:province":"Li\u00e8ge",
    "sg:tags":[
        "osteopath"
    ],
    "wof:name":"Muller D (do)",
    "wof:placetype":"venue"
},
  "geometry": {"coordinates":[5.5659160614,50.6479682922],"type":"Point"}
}