{
  "type": "Feature",
  "properties": {
    "addr:full":"Luzery 51 Bastogne Luxembourg 6600",
    "addr:housenumber":"51",
    "addr:postcode":"6600",
    "addr:street":"Luzery",
    "iso:country":"BE",
    "sg:address":"Luzery 51",
    "sg:city":"Bastogne",
    "sg:orig_category":"Installatie van houten of kunststof schrijnwerk",
    "sg:phone":"+32 61 21 55 00",
    "sg:postcode":"6600",
    "sg:province":"Luxembourg",
    "wof:name":"Detaille & Besseling",
    "wof:placetype":"venue"
},
  "geometry": {"coordinates":[5.7239837646,50.0141181946],"type":"Point"}
}