{
  "type": "Feature",
  "properties": {
    "iso:country":"BE",
    "sg:address":"Centre 26",
    "sg:city":"Thimister-clermont (thimister)",
    "sg:classifiers":[
        {
            "category":"Health Services",
            "subcategory":"Health Practitioner",
            "type":"Services"
        }
    ],
    "sg:phone":"+32 87 44 56 47",
    "sg:postcode":"4890",
    "sg:province":"Li\u00e8ge",
    "sg:tags":[
        "physiotherapist"
    ],
    "wof:name":"Somers Veronique",
    "wof:placetype":"venue"
},
  "geometry": {"coordinates":[5.863615036,50.6534843445],"type":"Point"}
}