{
  "type": "Feature",
  "properties": {
    "iso:country":"BE",
    "sg:address":"Rue De La Station 23",
    "sg:city":"Chatelet",
    "sg:classifiers":[
        {
            "category":"Restaurant",
            "type":"Food & Drink"
        }
    ],
    "sg:phone":"+32 71 38 20 57",
    "sg:postcode":"6200",
    "sg:province":"Hainaut",
    "wof:name":"Resto Sohier",
    "wof:placetype":"venue"
},
  "geometry": {"coordinates":[4.5301499367,50.4022903442],"type":"Point"}
}