{
  "type": "Feature",
  "properties": {
    "addr:full":"All\u00e9e Verte 5 La Louvi\u00e8re (saint-vaast) Hainaut 7100",
    "addr:housenumber":"5",
    "addr:postcode":"7100",
    "addr:street":"Alle\u0301E Verte",
    "iso:country":"BE",
    "sg:address":"All\u00e9e Verte 5",
    "sg:city":"La Louvi\u00e8re (saint-vaast)",
    "sg:classifiers":[
        {
            "category":"Bakery",
            "type":"Food & Drink"
        }
    ],
    "sg:phone":"+32 64 28 54 94",
    "sg:postcode":"7100",
    "sg:province":"Hainaut",
    "sg:tags":[
        "confectioner",
        "baker"
    ],
    "wof:name":"Giovannuci P",
    "wof:placetype":"venue"
},
  "geometry": {"coordinates":[4.1899018288,50.4782066345],"type":"Point"}
}