{
  "type": "Feature",
  "properties": {
    "iso:country":"BE",
    "sg:address":"Lindenlaan 80",
    "sg:city":"Evergem (ertvelde)",
    "sg:classifiers":[
        {
            "category":"Shopping",
            "subcategory":"Bicycles & Sporting Goods",
            "type":"Retail Goods"
        }
    ],
    "sg:phone":"+32 9 344 24 14",
    "sg:postcode":"9940",
    "sg:province":"Oost-Vlaanderen",
    "sg:tags":[
        "-"
    ],
    "wof:name":"Van Den Veegaete",
    "wof:placetype":"venue"
},
  "geometry": {"coordinates":[3.7449169159,51.175201416],"type":"Point"}
}