{
  "type": "Feature",
  "properties": {
    "iso:country":"BE",
    "sg:address":"Ijsbergstraat 40-42",
    "sg:city":"Dilbeek (itterbeek)",
    "sg:classifiers":[
        {
            "category":"Banks & Credit Unions",
            "subcategory":"Investment Brokerage",
            "type":"Services"
        }
    ],
    "sg:phone":"+32 2 569 15 27",
    "sg:postcode":"1701",
    "sg:province":"Vlaams-Brabant",
    "sg:tags":[
        "coil",
        "electric",
        "winding"
    ],
    "wof:name":"Arabel Nv",
    "wof:placetype":"venue"
},
  "geometry": {"coordinates":[4.2172179222,50.8355979919],"type":"Point"}
}