{
  "type": "Feature",
  "properties": {
    "addr:full":"Ind Terr Peerterbaan 1310 Bree Limburg 3960",
    "addr:housenumber":"1310",
    "addr:postcode":"3960",
    "addr:street":"Terr Peerterbaan",
    "iso:country":"BE",
    "sg:address":"Ind Terr Peerterbaan 1310",
    "sg:city":"Bree",
    "sg:classifiers":[
        {
            "category":"Manufacturing",
            "subcategory":"Metals",
            "type":"Manufacturing & Wholesale Goods"
        }
    ],
    "sg:phone":"+32 89 46 36 36",
    "sg:postcode":"3960",
    "sg:province":"Limburg",
    "sg:tags":[
        "metallurgy",
        "metalworking",
        "processing"
    ],
    "wof:name":"Heka Metallbearbeitung Nv",
    "wof:placetype":"venue"
},
  "geometry": {"coordinates":[5.5944190025,51.1405677795],"type":"Point"}
}