{
  "type": "Feature",
  "properties": {
    "addr:full":"Molenstraat 52 Antwerpen Antwerpen 2018",
    "addr:housenumber":"52",
    "addr:postcode":"2018",
    "addr:street":"Molenstraat",
    "iso:country":"BE",
    "sg:address":"Molenstraat 52",
    "sg:city":"Antwerpen",
    "sg:orig_category":"Avocats and conseillers juridiques",
    "sg:phone":"+32 3 248 30 41",
    "sg:postcode":"2018",
    "sg:province":"Antwerpen",
    "wof:name":"V\u00c9ronique Pignet",
    "wof:placetype":"venue"
},
  "geometry": {"coordinates":[4.4073691368,51.2066688538],"type":"Point"}
}