{
  "type": "Feature",
  "properties": {
    "addr:full":"Industrieweg 1a Lanaken Limburg 3620",
    "addr:housenumber":"1a",
    "addr:postcode":"3620",
    "addr:street":"Industrieweg",
    "iso:country":"BE",
    "sg:address":"Industrieweg 1a",
    "sg:city":"Lanaken",
    "sg:classifiers":[
        {
            "category":"Structure",
            "subcategory":"Building",
            "type":"Public Place"
        }
    ],
    "sg:phone":"+32 89 71 44 58",
    "sg:postcode":"3620",
    "sg:province":"Limburg",
    "sg:tags":[
        "door"
    ],
    "wof:name":"Nelissen-meuris Bvba",
    "wof:placetype":"venue"
},
  "geometry": {"coordinates":[5.663795948,50.8894538879],"type":"Point"}
}