{
  "type": "Feature",
  "properties": {
    "iso:country":"BE",
    "sg:address":"Gulden-vlieslaan 10",
    "sg:city":"Elsene/ixelles",
    "sg:classifiers":[
        {
            "category":"Bars & Pubs",
            "type":"Food & Drink"
        }
    ],
    "sg:phone":"+32 2 511 26 68",
    "sg:postcode":"1050",
    "sg:province":"Bruxelles-Capitale",
    "sg:tags":[
        "restaurant"
    ],
    "wof:name":"Conway\u00b4s Big Al\u00b4s Sp. Bar",
    "wof:placetype":"venue"
},
  "geometry": {"coordinates":[4.3609509468,50.8377532959],"type":"Point"}
}