{
  "type": "Feature",
  "properties": {
    "iso:country":"BE",
    "sg:address":"Beekstraat 73",
    "sg:city":"Deinze",
    "sg:orig_category":"Ramassage and traitement des d\u00e9chets m\u00e9nagers. Locations de machines and \u00e9quipement pour la construc",
    "sg:phone":"+32 9 386 33 98",
    "sg:postcode":"9800",
    "sg:province":"Oost-Vlaanderen",
    "wof:name":"Adriaan De Pourcq",
    "wof:placetype":"venue"
},
  "geometry": {"coordinates":[3.5835609436,50.9829940796],"type":"Point"}
}