{
  "type": "Feature",
  "properties": {
    "iso:country":"BE",
    "sg:address":"Turnhoutsebaan 366",
    "sg:city":"Schilde",
    "sg:classifiers":[
        {
            "category":"Shopping",
            "subcategory":"Clothing, Apparel, & Fashions",
            "type":"Retail Goods"
        }
    ],
    "sg:phone":"+32 3 383 47 58",
    "sg:postcode":"2970",
    "sg:province":"Antwerpen",
    "sg:tags":[
        "-",
        "haberdashery"
    ],
    "wof:name":"Bobijntje",
    "wof:placetype":"venue"
},
  "geometry": {"coordinates":[4.5871829987,51.2422103882],"type":"Point"}
}