{
  "type": "Feature",
  "properties": {
    "addr:full":"Chemin Du Vieux Pont 54 Leuze-en-hainaut Hainaut 7900",
    "addr:housenumber":"54",
    "addr:postcode":"7900",
    "addr:street":"Chemin Du Vieux Pont",
    "iso:country":"BE",
    "sg:address":"Chemin Du Vieux Pont 54",
    "sg:city":"Leuze-en-hainaut",
    "sg:orig_category":"Computers and computerapparatuur Kantoormateriaal Gh",
    "sg:phone":"+32 69 66 36 61",
    "sg:postcode":"7900",
    "sg:province":"Hainaut",
    "wof:name":"Logal",
    "wof:placetype":"venue"
},
  "geometry": {"coordinates":[3.6267969608,50.6021308899],"type":"Point"}
}