{
  "type": "Feature",
  "properties": {
    "iso:country":"BE",
    "sg:address":"Rue De Medell 162",
    "sg:city":"Amel",
    "sg:orig_category":"V\u00e9hicules automobiles",
    "sg:phone":"+32 80 22 89 56",
    "sg:postcode":"4770",
    "sg:province":"Li\u00e8ge",
    "wof:name":"Garage Thom\u00c9",
    "wof:placetype":"venue"
},
  "geometry": {"coordinates":[6.1689629555,50.3543167114],"type":"Point"}
}