{
  "type": "Feature",
  "properties": {
    "addr:full":"Boelare 80 Eeklo Oost-Vlaanderen 9900",
    "addr:housenumber":"80",
    "addr:postcode":"9900",
    "addr:street":"Boelare",
    "iso:country":"BE",
    "sg:address":"Boelare 80",
    "sg:city":"Eeklo",
    "sg:classifiers":[
        {
            "category":"Cafe",
            "type":"Food & Drink"
        }
    ],
    "sg:phone":"+32 9 377 19 00",
    "sg:postcode":"9900",
    "sg:province":"Oost-Vlaanderen",
    "sg:tags":[
        "caf\u00e9s"
    ],
    "wof:name":"Caf\u00c9 De Corner",
    "wof:placetype":"venue"
},
  "geometry": {"coordinates":[3.566562891,51.1874427795],"type":"Point"}
}