{
  "type": "Feature",
  "properties": {
    "addr:full":"Rue Des Gaulois 2 Ath (meslin - L'ev\u00eaque) Hainaut 7822",
    "addr:housenumber":"2;meslin",
    "addr:postcode":"7822",
    "addr:street":"Rue Des Gaulois;\u0302Que Hainaut",
    "iso:country":"BE",
    "sg:address":"Rue Des Gaulois 2",
    "sg:city":"Ath (meslin - L'ev\u00eaque)",
    "sg:classifiers":[
        {
            "category":"Manufacturing",
            "subcategory":"Metals",
            "type":"Manufacturing & Wholesale Goods"
        }
    ],
    "sg:phone":"+32 68 57 02 26",
    "sg:postcode":"7822",
    "sg:province":"Hainaut",
    "sg:tags":[
        "steel",
        "stainless"
    ],
    "wof:name":"Metalann Sprl",
    "wof:placetype":"venue"
},
  "geometry": {"coordinates":[3.8531649113,50.6538887024],"type":"Point"}
}