{
  "type": "Feature",
  "properties": {
    "iso:country":"BE",
    "sg:address":"Chauss\u00e9e Freddy Terwagne 25",
    "sg:city":"Engis (hermalle-sous-huy)",
    "sg:classifiers":[
        {
            "category":"Professional",
            "subcategory":"Business Services",
            "type":"Services"
        }
    ],
    "sg:phone":"+32 85 31 10 26",
    "sg:postcode":"4480",
    "sg:province":"Li\u00e8ge",
    "sg:tags":[
        "bookkeeping"
    ],
    "wof:name":"Dallemagne-comptable",
    "wof:placetype":"venue"
},
  "geometry": {"coordinates":[5.4045758247,50.582069397],"type":"Point"}
}