{
  "type": "Feature",
  "properties": {
    "iso:country":"BE",
    "sg:address":"Rue L\u00e9on Colleaux 31",
    "sg:city":"Virton (saint-mard)",
    "sg:classifiers":[
        {
            "category":"Professional",
            "subcategory":"Printing & Photocopies",
            "type":"Services"
        }
    ],
    "sg:phone":"+32 63 57 71 58",
    "sg:postcode":"6762",
    "sg:province":"Luxembourg",
    "sg:tags":[
        "-",
        "offset"
    ],
    "wof:name":"Jean-jacques (imprimerie)",
    "wof:placetype":"venue"
},
  "geometry": {"coordinates":[5.5305562019,49.5552597046],"type":"Point"}
}