{
  "type": "Feature",
  "properties": {
    "iso:country":"BE",
    "sg:address":"Korte Zoutstraat 4",
    "sg:city":"Aalst",
    "sg:orig_category":"Pain, p\u00e2tisseries and confiseries",
    "sg:phone":"+32 53 70 19 08",
    "sg:postcode":"9300",
    "sg:province":"Oost-Vlaanderen",
    "wof:name":"Huis Judy",
    "wof:placetype":"venue"
},
  "geometry": {"coordinates":[4.0398359299,50.9361915588],"type":"Point"}
}