{
  "type": "Feature",
  "properties": {
    "addr:full":"Naamsesteenweg 111 Oud-heverlee (blanden) Vlaams-Brabant 3052",
    "addr:housenumber":"111",
    "addr:postcode":"3052",
    "addr:street":"Naamsesteenweg",
    "iso:country":"BE",
    "sg:address":"Naamsesteenweg 111",
    "sg:city":"Oud-heverlee (blanden)",
    "sg:classifiers":[
        {
            "category":"Transit Center",
            "subcategory":"Freight",
            "type":"Transportation"
        }
    ],
    "sg:phone":"+32 16 40 83 89",
    "sg:postcode":"3052",
    "sg:province":"Vlaams-Brabant",
    "sg:tags":[
        "import",
        "export",
        "-"
    ],
    "wof:name":"A P C International Bvba",
    "wof:placetype":"venue"
},
  "geometry": {"coordinates":[4.7032971382,50.820854187],"type":"Point"}
}