{
  "type": "Feature",
  "properties": {
    "iso:country":"BE",
    "sg:address":"Postbus 3",
    "sg:city":"Lokeren1",
    "sg:classifiers":[
        {
            "category":"Communications",
            "subcategory":"Radio Station",
            "type":"Services"
        }
    ],
    "sg:phone":"+32 9 348 89 11",
    "sg:postcode":"9160",
    "sg:province":"Oost-Vlaanderen",
    "sg:tags":[
        "local"
    ],
    "wof:name":"Topradio Abc",
    "wof:placetype":"venue"
},
  "geometry": {"coordinates":[3.9864799976,51.1047401428],"type":"Point"}
}