{
  "type": "Feature",
  "properties": {
    "iso:country":"BE",
    "sg:address":"Josse Impensstraat 33",
    "sg:city":"Schaarbeek/schaerbeek",
    "sg:orig_category":"Zalen voor culturele evenementen",
    "sg:phone":"+32 2 242 56 24",
    "sg:postcode":"1030",
    "sg:province":"Bruxelles-Capitale",
    "wof:name":"Ricochets",
    "wof:placetype":"venue"
},
  "geometry": {"coordinates":[4.3835220337,50.8609848022],"type":"Point"}
}