{
  "type": "Feature",
  "properties": {
    "iso:country":"BE",
    "sg:address":"Heiligenbornstraat 19",
    "sg:city":"Alken",
    "sg:orig_category":"Drukkerijen and copyshops",
    "sg:phone":"+32 11 59 21 27",
    "sg:postcode":"3570",
    "sg:province":"Limburg",
    "wof:name":"Global Marketing 3000",
    "wof:placetype":"venue"
},
  "geometry": {"coordinates":[5.2542710304,50.8716239929],"type":"Point"}
}