{
  "type": "Feature",
  "properties": {
    "iso:country":"BE",
    "sg:address":"Rue De Lobbes 30",
    "sg:city":"Thuin",
    "sg:orig_category":"Diverse bouwafwerking and reiniging Woningbouw",
    "sg:phone":"+32 71 59 29 32",
    "sg:postcode":"6530",
    "sg:province":"Hainaut",
    "wof:name":"Andre Guillaume",
    "wof:placetype":"venue"
},
  "geometry": {"coordinates":[4.2702817917,50.3399162292],"type":"Point"}
}