{
  "type": "Feature",
  "properties": {
    "addr:full":"Pieter Gorusstraat 23 Zele Oost-Vlaanderen 9240",
    "addr:housenumber":"23",
    "addr:postcode":"9240",
    "addr:street":"Pieter Gorusstraat",
    "iso:country":"BE",
    "sg:address":"Pieter Gorusstraat 23",
    "sg:city":"Zele",
    "sg:orig_category":"Experts-comptables",
    "sg:phone":"+32 52 44 97 58",
    "sg:postcode":"9240",
    "sg:province":"Oost-Vlaanderen",
    "wof:name":"Patrick Van Cauter",
    "wof:placetype":"venue"
},
  "geometry": {"coordinates":[4.0629930496,51.0520782471],"type":"Point"}
}