{
  "type": "Feature",
  "properties": {
    "iso:country":"BE",
    "sg:address":"Van Arteveldestraat 75",
    "sg:city":"Antwerpen",
    "sg:classifiers":[
        {
            "category":"Cafe",
            "type":"Food & Drink"
        }
    ],
    "sg:phone":"+32 3 232 84 44",
    "sg:postcode":"2060",
    "sg:province":"Antwerpen",
    "sg:tags":[
        "caf\u00e9s"
    ],
    "wof:name":"Caf\u00c9 't Conincske",
    "wof:placetype":"venue"
},
  "geometry": {"coordinates":[4.4197077751,51.2211494446],"type":"Point"}
}