{
  "type": "Feature",
  "properties": {
    "addr:full":"Hoogstraatseweg 134 Wuustwezel Antwerpen 2990",
    "addr:housenumber":"134",
    "addr:postcode":"2990",
    "addr:street":"Hoogstraatseweg",
    "iso:country":"BE",
    "sg:address":"Hoogstraatseweg 134",
    "sg:city":"Wuustwezel",
    "sg:orig_category":"Bagage and lederwaren Fab SMEEDWERK, METAALBEWERKING AND POEDERMETALLURGIE Sport- and kampeermateria",
    "sg:phone":"+32 3 669 62 95",
    "sg:postcode":"2990",
    "sg:province":"Antwerpen",
    "wof:name":"Horse Boetiek",
    "wof:placetype":"venue"
},
  "geometry": {"coordinates":[4.6699309349,51.4040756226],"type":"Point"}
}