{
  "type": "Feature",
  "properties": {
    "addr:full":"Salvatorstraat 110 Box 2 Hamont-achel (hamont) Limburg 3930",
    "addr:housenumber":"110;2",
    "addr:postcode":"3930",
    "addr:street":"Salvatorstraat;Box",
    "iso:country":"BE",
    "sg:address":"Salvatorstraat 110 Box 2",
    "sg:city":"Hamont-achel (hamont)",
    "sg:classifiers":[
        {
            "category":"Shopping",
            "subcategory":"Florist",
            "type":"Retail Goods"
        }
    ],
    "sg:phone":"+32 11 44 11 12",
    "sg:postcode":"3930",
    "sg:province":"Limburg",
    "wof:name":"Floweringworld.com",
    "wof:placetype":"venue"
},
  "geometry": {"coordinates":[5.5450549126,51.2511863708],"type":"Point"}
}