{
  "type": "Feature",
  "properties": {
    "iso:country":"BE",
    "sg:address":"Burchtstraat 2",
    "sg:city":"Leuven",
    "sg:classifiers":[
        {
            "category":"Building & Trades",
            "subcategory":"Construction",
            "type":"Services"
        }
    ],
    "sg:phone":"+32 16 29 34 59",
    "sg:postcode":"3000",
    "sg:province":"Vlaams-Brabant",
    "sg:tags":[
        "industrial",
        "design"
    ],
    "wof:name":"Deckers P",
    "wof:placetype":"venue"
},
  "geometry": {"coordinates":[4.6966052055,50.8870849609],"type":"Point"}
}