{
  "type": "Feature",
  "properties": {
    "addr:full":"Kleine Zwevezelestraat 3 Lichtervelde West-Vlaanderen 8810",
    "addr:housenumber":"3",
    "addr:postcode":"8810",
    "addr:street":"Zwevezelestraat",
    "iso:country":"BE",
    "sg:address":"Kleine Zwevezelestraat 3",
    "sg:city":"Lichtervelde",
    "sg:orig_category":"Eleveurs de bovins",
    "sg:phone":"+32 51 72 33 68",
    "sg:postcode":"8810",
    "sg:province":"West-Vlaanderen",
    "wof:name":"Dani\u00cbl Kindt",
    "wof:placetype":"venue"
},
  "geometry": {"coordinates":[3.1607730389,51.0433540344],"type":"Point"}
}