{
  "type": "Feature",
  "properties": {
    "iso:country":"BE",
    "sg:address":"Kortrijksepoortstr 234",
    "sg:city":"Gent",
    "sg:classifiers":[
        {
            "category":"Wholesale",
            "subcategory":"Medical Equipment & Supplies",
            "type":"Manufacturing & Wholesale Goods"
        }
    ],
    "sg:phone":"+32 9 225 98 23",
    "sg:postcode":"9000",
    "sg:province":"Oost-Vlaanderen",
    "sg:tags":[
        "instrument",
        "health",
        "-",
        "precision"
    ],
    "wof:name":"Haarkapperscentrale Bauwens Nv",
    "wof:placetype":"venue"
},
  "geometry": {"coordinates":[3.7217450142,51.0444068909],"type":"Point"}
}