{
  "type": "Feature",
  "properties": {
    "addr:full":"Rue Biolley 17 Verviers Li\u00e8ge 4800",
    "addr:housenumber":"17",
    "addr:postcode":"4800",
    "addr:street":"Rue Biolley",
    "iso:country":"BE",
    "sg:address":"Rue Biolley 17",
    "sg:city":"Verviers",
    "sg:classifiers":[
        {
            "category":"Manufacturing",
            "subcategory":"Motor Vehicles & Parts",
            "type":"Manufacturing & Wholesale Goods"
        }
    ],
    "sg:phone":"+32 87 31 28 37",
    "sg:postcode":"4800",
    "sg:province":"Li\u00e8ge",
    "sg:tags":[
        "engine",
        "gasoline",
        "-"
    ],
    "wof:name":"Pauly Andrianne Sprl",
    "wof:placetype":"venue"
},
  "geometry": {"coordinates":[5.8729791641,50.5936737061],"type":"Point"}
}