{
  "type": "Feature",
  "properties": {
    "iso:country":"BE",
    "sg:address":"Groenstraat 31",
    "sg:city":"Zelzate",
    "sg:classifiers":[
        {
            "category":"Autos & Motor Vehicles",
            "subcategory":"Auto Supplies",
            "type":"Retail Goods"
        }
    ],
    "sg:phone":"+32 9 345 66 54",
    "sg:postcode":"9060",
    "sg:province":"Oost-Vlaanderen",
    "sg:tags":[
        "access",
        "automobile",
        "part",
        "-"
    ],
    "wof:name":"Gryp Auto",
    "wof:placetype":"venue"
},
  "geometry": {"coordinates":[3.8075909615,51.1980781555],"type":"Point"}
}