{
  "type": "Feature",
  "properties": {
    "iso:country":"BE",
    "sg:address":"Driesstraat 75",
    "sg:city":"Avelgem",
    "sg:classifiers":[
        {
            "category":"Shopping",
            "subcategory":"Crafts & Fabrics",
            "type":"Retail Goods"
        }
    ],
    "sg:phone":"+32 56 64 90 06",
    "sg:postcode":"8580",
    "sg:province":"West-Vlaanderen",
    "sg:tags":[
        "paints",
        "varnish",
        "-",
        "lacquers",
        "enamel"
    ],
    "wof:name":"Decoratie Rommens",
    "wof:placetype":"venue"
},
  "geometry": {"coordinates":[3.4384601116,50.7796096802],"type":"Point"}
}