{
  "type": "Feature",
  "properties": {
    "iso:country":"BE",
    "sg:address":"Edmond Thieffrylaan 108",
    "sg:city":"Mortsel",
    "sg:orig_category":"Cr\u00e8ches and garderies d'enfants",
    "sg:phone":"+32 3 440 16 80",
    "sg:postcode":"2640",
    "sg:province":"Antwerpen",
    "wof:name":"Tam Tam Club",
    "wof:placetype":"venue"
},
  "geometry": {"coordinates":[4.450109005,51.1663703918],"type":"Point"}
}