{
  "type": "Feature",
  "properties": {
    "iso:country":"BE",
    "sg:address":"Grote Markt 48",
    "sg:city":"Antwerpen",
    "sg:classifiers":[
        {
            "category":"Bars & Pubs",
            "type":"Food & Drink"
        }
    ],
    "sg:phone":"+32 3 293 04 84",
    "sg:postcode":"2000",
    "sg:province":"Antwerpen",
    "wof:name":"Cyrano",
    "wof:placetype":"venue"
},
  "geometry": {"coordinates":[4.4009151459,51.2210540771],"type":"Point"}
}