{
  "type": "Feature",
  "properties": {
    "iso:country":"BE",
    "sg:address":"Bovekerkestraat 46",
    "sg:city":"Koekelare",
    "sg:orig_category":"Plomberie, chauffage and installations sanitaires. Installation \u00e9lectrique r\u00e9sidentielle",
    "sg:phone":"+32 51 70 26 00",
    "sg:postcode":"8680",
    "sg:province":"West-Vlaanderen",
    "wof:name":"Beeckaert Danny",
    "wof:placetype":"venue"
},
  "geometry": {"coordinates":[2.9633500576,51.0647583008],"type":"Point"}
}