{
  "type": "Feature",
  "properties": {
    "iso:country":"BE",
    "sg:address":"Generaal Baron Jacquesstraat 8",
    "sg:city":"Diksmuide",
    "sg:classifiers":[
        {
            "category":"Personal",
            "subcategory":"Beauty Salon",
            "type":"Services"
        }
    ],
    "sg:phone":"+32 51 50 02 77",
    "sg:postcode":"8600",
    "sg:province":"West-Vlaanderen",
    "sg:tags":[
        "lady",
        "-",
        "hairdressing"
    ],
    "wof:name":"Vanhaelewijn",
    "wof:placetype":"venue"
},
  "geometry": {"coordinates":[2.8632740974,51.0332984924],"type":"Point"}
}