{
  "type": "Feature",
  "properties": {
    "iso:country":"BE",
    "sg:address":"Annuntiatenstraat 43",
    "sg:city":"Brugge",
    "sg:orig_category":"Apotheken",
    "sg:phone":"+32 50 33 38 67",
    "sg:postcode":"8000",
    "sg:province":"West-Vlaanderen",
    "wof:name":"Jan Vandeginste",
    "wof:placetype":"venue"
},
  "geometry": {"coordinates":[3.2246129513,51.2158889771],"type":"Point"}
}