{
  "type": "Feature",
  "properties": {
    "addr:full":"Messidorlaan 312 Ukkel/uccle Bruxelles-Capitale 1180",
    "addr:housenumber":"312",
    "addr:postcode":"1180",
    "addr:street":"Messidorlaan;/",
    "iso:country":"BE",
    "sg:address":"Messidorlaan 312",
    "sg:city":"Ukkel/uccle",
    "sg:orig_category":"Advocaten and juridische adviseurs",
    "sg:phone":"+32 2 343 60 40",
    "sg:postcode":"1180",
    "sg:province":"Bruxelles-Capitale",
    "wof:name":"Danielle Cherpion",
    "wof:placetype":"venue"
},
  "geometry": {"coordinates":[4.3521499634,50.8116645813],"type":"Point"}
}