{
  "type": "Feature",
  "properties": {
    "addr:full":"Haverstraat 40 Oostende West-Vlaanderen 8400",
    "addr:housenumber":"40",
    "addr:postcode":"8400",
    "addr:street":"Haverstraat",
    "iso:country":"BE",
    "sg:address":"Haverstraat 40",
    "sg:city":"Oostende",
    "sg:classifiers":[
        {
            "category":"Professional",
            "subcategory":"Accounting & Tax Preparation",
            "type":"Services"
        }
    ],
    "sg:phone":"+32 59 70 49 12",
    "sg:postcode":"8400",
    "sg:province":"West-Vlaanderen",
    "sg:tags":[
        "bookkeeper"
    ],
    "wof:name":"Adbo-kantoor V\u00e9ronique Beauprez",
    "wof:placetype":"venue"
},
  "geometry": {"coordinates":[2.9147279263,51.2193489075],"type":"Point"}
}