{
  "type": "Feature",
  "properties": {
    "iso:country":"BE",
    "sg:address":"Rue El Rowe 10",
    "sg:city":"Sprimont",
    "sg:orig_category":"Eleveurs de bovins",
    "sg:phone":"+32 4 382 16 89",
    "sg:postcode":"4140",
    "sg:province":"Li\u00e8ge",
    "wof:name":"Jean Gobert",
    "wof:placetype":"venue"
},
  "geometry": {"coordinates":[5.6488962173,50.4890632629],"type":"Point"}
}