{
  "type": "Feature",
  "properties": {
    "iso:country":"BE",
    "sg:address":"Rue Denis Deceuster 2",
    "sg:city":"Rixensart",
    "sg:classifiers":[
        {
            "category":"Real Estate",
            "subcategory":"Architect",
            "type":"Services"
        }
    ],
    "sg:phone":"+32 2 653 55 98",
    "sg:postcode":"1330",
    "sg:province":"Brabant Wallon",
    "wof:name":"Zils T",
    "wof:placetype":"venue"
},
  "geometry": {"coordinates":[4.5154428482,50.7118186951],"type":"Point"}
}