{
  "type": "Feature",
  "properties": {
    "addr:full":"Ninoofsesteenweg 317 Dilbeek Vlaams-Brabant 1700",
    "addr:housenumber":"317",
    "addr:postcode":"1700",
    "addr:street":"Ninoofsesteenweg",
    "iso:country":"BE",
    "sg:address":"Ninoofsesteenweg 317",
    "sg:city":"Dilbeek",
    "sg:orig_category":"Installation \u00e9lectrique r\u00e9sidentielle",
    "sg:phone":"+32 2 569 45 01",
    "sg:postcode":"1700",
    "sg:province":"Vlaams-Brabant",
    "wof:name":"J. M. N. Electrotec",
    "wof:placetype":"venue"
},
  "geometry": {"coordinates":[4.262802124,50.84400177],"type":"Point"}
}