{
  "type": "Feature",
  "properties": {
    "iso:country":"BE",
    "sg:address":"Velzekestraat 15",
    "sg:city":"Zottegem",
    "sg:classifiers":[
        {
            "category":"Restaurant",
            "type":"Food & Drink"
        }
    ],
    "sg:phone":"+32 9 360 03 79",
    "sg:postcode":"9620",
    "sg:province":"Oost-Vlaanderen",
    "sg:tags":[
        "caf\u00e9s"
    ],
    "wof:name":"Taverne Jan De Lichte",
    "wof:placetype":"venue"
},
  "geometry": {"coordinates":[3.8006649017,50.8774108887],"type":"Point"}
}