{
  "type": "Feature",
  "properties": {
    "addr:full":"Rue Bruil 34 Quievrain Hainaut 7380",
    "addr:housenumber":"34",
    "addr:postcode":"7380",
    "addr:street":"Rue Bruil;Hainaut",
    "iso:country":"BE",
    "sg:address":"Rue Bruil 34",
    "sg:city":"Quievrain",
    "sg:orig_category":"Elektrische installaties voor woningen",
    "sg:phone":"+32 65 45 72 34",
    "sg:postcode":"7380",
    "sg:province":"Hainaut",
    "wof:name":"Fe. Van Ostaeyen",
    "wof:placetype":"venue"
},
  "geometry": {"coordinates":[3.6764330864,50.4060211182],"type":"Point"}
}