{
  "type": "Feature",
  "properties": {
    "addr:full":"Gheudestraat 49 Anderlecht Bruxelles-Capitale 1070",
    "addr:housenumber":"49",
    "addr:postcode":"1070",
    "addr:street":"Gheudestraat",
    "iso:country":"BE",
    "sg:address":"Gheudestraat 49",
    "sg:city":"Anderlecht",
    "sg:orig_category":"Herstelling leer and schoeisel",
    "sg:phone":"+32 2 529 99 11",
    "sg:postcode":"1070",
    "sg:province":"Bruxelles-Capitale",
    "wof:name":"Mister Mint Services",
    "wof:placetype":"venue"
},
  "geometry": {"coordinates":[4.3356590271,50.8411178589],"type":"Point"}
}