{
  "type": "Feature",
  "properties": {
    "iso:country":"BE",
    "sg:address":"Helmetseplein 7",
    "sg:city":"Schaarbeek/schaerbeek",
    "sg:classifiers":[
        {
            "category":"Restaurant",
            "type":"Food & Drink"
        }
    ],
    "sg:phone":"+32 2 245 08 94",
    "sg:postcode":"1030",
    "sg:province":"Bruxelles-Capitale",
    "wof:name":"Restaurant Le Pascal",
    "wof:placetype":"venue"
},
  "geometry": {"coordinates":[4.3898000717,50.8727035522],"type":"Point"}
}