{
  "type": "Feature",
  "properties": {
    "addr:full":"Place Albert Ier 1 Charleroi Hainaut 6061",
    "addr:housenumber":"1",
    "addr:postcode":"6061",
    "addr:street":"Place Albert Ier;Hainaut",
    "iso:country":"BE",
    "sg:address":"Place Albert Ier 1",
    "sg:city":"Charleroi",
    "sg:classifiers":[
        {
            "category":"Government",
            "subcategory":"Police Station",
            "type":"Public Place"
        }
    ],
    "sg:phone":"+32 71 23 73 95",
    "sg:postcode":"6061",
    "sg:province":"Hainaut",
    "sg:tags":[
        "gendarmerie"
    ],
    "wof:name":"Police F\u00c9d\u00c9rale",
    "wof:placetype":"venue"
},
  "geometry": {"coordinates":[4.4284157753,50.4149475098],"type":"Point"}
}