{
  "type": "Feature",
  "properties": {
    "iso:country":"BE",
    "sg:address":"Kerkplein 2",
    "sg:city":"Bonheiden",
    "sg:orig_category":"Caf\u00e9s. Salles de spectacles",
    "sg:phone":"+32 15 51 58 03",
    "sg:postcode":"2820",
    "sg:province":"Antwerpen",
    "wof:name":"Cult. Centrum Krankhoeve",
    "wof:placetype":"venue"
},
  "geometry": {"coordinates":[4.5475068092,51.0228347778],"type":"Point"}
}