{
  "type": "Feature",
  "properties": {
    "addr:full":"Amerikalei 108 Box 5 Antwerpen Antwerpen 2000",
    "addr:housenumber":"108;5",
    "addr:postcode":"2000",
    "addr:street":"Amerikalei;Box",
    "iso:country":"BE",
    "sg:address":"Amerikalei 108 Box 5",
    "sg:city":"Antwerpen",
    "sg:classifiers":[
        {
            "category":"Professional",
            "subcategory":"Accounting & Tax Preparation",
            "type":"Services"
        }
    ],
    "sg:phone":"+32 3 238 40 15",
    "sg:postcode":"2000",
    "sg:province":"Antwerpen",
    "sg:tags":[
        "accountant"
    ],
    "wof:name":"Koevoets J-p",
    "wof:placetype":"venue"
},
  "geometry": {"coordinates":[4.3956408501,51.2070426941],"type":"Point"}
}