{
  "type": "Feature",
  "properties": {
    "addr:full":"2450 Meerhout (grand) Antwerpen 2450",
    "addr:postcode":"2450;2450",
    "iso:country":"BE",
    "sg:address":"2450",
    "sg:city":"Meerhout (grand)",
    "sg:orig_category":"Pharmaciens",
    "sg:phone":"+32 900 10 500",
    "sg:postcode":"2450",
    "sg:province":"Antwerpen",
    "wof:name":"Pharmacies De Garde",
    "wof:placetype":"venue"
},
  "geometry": {"coordinates":[5.0779151917,51.1319160461],"type":"Point"}
}