{
  "type": "Feature",
  "properties": {
    "addr:full":"Hoogstraat 73 Lokeren Oost-Vlaanderen 9160",
    "addr:housenumber":"73",
    "addr:postcode":"9160",
    "addr:street":"Hoogstraat",
    "iso:country":"BE",
    "sg:address":"Hoogstraat 73",
    "sg:city":"Lokeren",
    "sg:classifiers":[
        {
            "category":"Personal",
            "subcategory":"Beauty Salon",
            "type":"Services"
        }
    ],
    "sg:phone":"+32 9 348 79 76",
    "sg:postcode":"9160",
    "sg:province":"Oost-Vlaanderen",
    "wof:name":"Linea",
    "wof:placetype":"venue"
},
  "geometry": {"coordinates":[3.9698619843,51.1063346863],"type":"Point"}
}