{
  "type": "Feature",
  "properties": {
    "addr:full":"Rue F\u00e9lix Protin 9 Sambreville (auvelais) Namur 5060",
    "addr:housenumber":"9",
    "addr:postcode":"5060",
    "addr:street":"Rue Fe\u0301Lix Protin",
    "iso:country":"BE",
    "sg:address":"Rue F\u00e9lix Protin 9",
    "sg:city":"Sambreville (auvelais)",
    "sg:classifiers":[
        {
            "category":"Shopping",
            "subcategory":"Crafts & Fabrics",
            "type":"Retail Goods"
        }
    ],
    "sg:phone":"+32 71 74 22 75",
    "sg:postcode":"5060",
    "sg:province":"Namur",
    "sg:tags":[
        "graphic",
        "art",
        "supply",
        "-",
        "painting",
        "drawing"
    ],
    "wof:name":"C.e.s. Sprl",
    "wof:placetype":"venue"
},
  "geometry": {"coordinates":[4.6285200119,50.4448738098],"type":"Point"}
}