{
  "type": "Feature",
  "properties": {
    "iso:country":"BE",
    "sg:address":"Neerstalse Steenweg 241",
    "sg:city":"Vorst/forest",
    "sg:orig_category":"Loodgieterij, verwarming and sanitaire installaties",
    "sg:phone":"+32 495 38 81 81",
    "sg:postcode":"1190",
    "sg:province":"Bruxelles-Capitale",
    "wof:name":"Olivier Le Plombier",
    "wof:placetype":"venue"
},
  "geometry": {"coordinates":[4.3134689331,50.8043899536],"type":"Point"}
}