{
  "type": "Feature",
  "properties": {
    "addr:full":"Molenaarstraat 20d Wingene (zwevezele) West-Vlaanderen 8750",
    "addr:housenumber":"20d",
    "addr:postcode":"8750",
    "addr:street":"Molenaarstraat",
    "iso:country":"BE",
    "sg:address":"Molenaarstraat 20d",
    "sg:city":"Wingene (zwevezele)",
    "sg:classifiers":[
        {
            "category":"Manufacturing",
            "subcategory":"Glass & Minerals",
            "type":"Manufacturing & Wholesale Goods"
        }
    ],
    "sg:phone":"+32 51 69 37 41",
    "sg:postcode":"8750",
    "sg:province":"West-Vlaanderen",
    "sg:tags":[
        "automobile",
        "-"
    ],
    "wof:name":"Quality Glasscoating Bvba",
    "wof:placetype":"venue"
},
  "geometry": {"coordinates":[3.2298901081,51.0452919006],"type":"Point"}
}