{
  "type": "Feature",
  "properties": {
    "addr:full":"Duffelaarstraat 9 Kalmthout Antwerpen 2920",
    "addr:housenumber":"9",
    "addr:postcode":"2920",
    "addr:street":"Duffelaarstraat",
    "iso:country":"BE",
    "sg:address":"Duffelaarstraat 9",
    "sg:city":"Kalmthout",
    "sg:classifiers":[
        {
            "category":"Wholesale",
            "subcategory":"Meat",
            "type":"Manufacturing & Wholesale Goods"
        }
    ],
    "sg:phone":"+32 3 666 29 09",
    "sg:postcode":"2920",
    "sg:province":"Antwerpen",
    "sg:tags":[
        "whol",
        "-"
    ],
    "wof:name":"Van Aert-van Hooydonk",
    "wof:placetype":"venue"
},
  "geometry": {"coordinates":[4.5103001595,51.3972816467],"type":"Point"}
}