{
  "type": "Feature",
  "properties": {
    "iso:country":"BE",
    "sg:address":"Van Iseghemlaan 34",
    "sg:city":"Oostende",
    "sg:classifiers":[
        {
            "category":"Shopping",
            "subcategory":"Gifts & Souvenirs",
            "type":"Retail Goods"
        }
    ],
    "sg:phone":"+32 59 51 38 50",
    "sg:postcode":"8400",
    "sg:province":"West-Vlaanderen",
    "sg:tags":[
        "-"
    ],
    "wof:name":"Art Mix Gallery",
    "wof:placetype":"venue"
},
  "geometry": {"coordinates":[2.9163439274,51.2337303162],"type":"Point"}
}