{
  "type": "Feature",
  "properties": {
    "addr:full":"Rue Haute 10 Stavelot Li\u00e8ge 4970",
    "addr:housenumber":"10",
    "addr:postcode":"4970",
    "addr:street":"Rue Haute",
    "iso:country":"BE",
    "sg:address":"Rue Haute 10",
    "sg:city":"Stavelot",
    "sg:orig_category":"Boucheries",
    "sg:phone":"+32 80 86 28 92",
    "sg:postcode":"4970",
    "sg:province":"Li\u00e8ge",
    "wof:name":"Boucherie Dufrais",
    "wof:placetype":"venue"
},
  "geometry": {"coordinates":[5.9303188324,50.3954734802],"type":"Point"}
}