{
  "type": "Feature",
  "properties": {
    "addr:full":"Rijselsestraat 27b Ieper West-Vlaanderen 8900",
    "addr:housenumber":"27b",
    "addr:postcode":"8900",
    "addr:street":"Rijselsestraat",
    "iso:country":"BE",
    "sg:address":"Rijselsestraat 27b",
    "sg:city":"Ieper",
    "sg:classifiers":[
        {
            "category":"Professional",
            "subcategory":"Art Services",
            "type":"Services"
        }
    ],
    "sg:phone":"+32 57 20 64 91",
    "sg:postcode":"8900",
    "sg:province":"West-Vlaanderen",
    "sg:tags":[
        "interior",
        "designer"
    ],
    "wof:name":"Pierco J",
    "wof:placetype":"venue"
},
  "geometry": {"coordinates":[2.8865749836,50.8498039246],"type":"Point"}
}