{
  "type": "Feature",
  "properties": {
    "addr:full":"Route De Bouillon 45 Beauraing Namur 5570",
    "addr:housenumber":"45",
    "addr:postcode":"5570",
    "addr:street":"Route De Bouillon",
    "iso:country":"BE",
    "sg:address":"Route De Bouillon 45",
    "sg:city":"Beauraing",
    "sg:classifiers":[
        {
            "category":"Fast Food",
            "type":"Food & Drink"
        }
    ],
    "sg:phone":"+32 82 71 11 11",
    "sg:postcode":"5570",
    "sg:province":"Namur",
    "sg:tags":[
        "\u00c0",
        "restaurants",
        "emporter",
        "restaurant"
    ],
    "wof:name":"Au Biran",
    "wof:placetype":"venue"
},
  "geometry": {"coordinates":[4.9573578835,50.10887146],"type":"Point"}
}