{
  "type": "Feature",
  "properties": {
    "addr:full":"Av. Bourg. Jean Materne 60 Namur Namur 5100",
    "addr:housenumber":"60",
    "addr:postcode":"5100",
    "addr:street":"Av. Bourg. Jean Materne",
    "iso:country":"BE",
    "sg:address":"Av. Bourg. Jean Materne 60",
    "sg:city":"Namur",
    "sg:classifiers":[
        {
            "category":"Shopping",
            "subcategory":"Clothing, Apparel, & Fashions",
            "type":"Retail Goods"
        }
    ],
    "sg:phone":"+32 81 30 17 37",
    "sg:postcode":"5100",
    "sg:province":"Namur",
    "sg:tags":[
        "v\u00eatements",
        "pour",
        "dame"
    ],
    "wof:name":"Couture Georgette",
    "wof:placetype":"venue"
},
  "geometry": {"coordinates":[4.8713750839,50.4566345215],"type":"Point"}
}