{
  "type": "Feature",
  "properties": {
    "addr:full":"Hoogeind 130 Stabroek Antwerpen 2940",
    "addr:housenumber":"130",
    "addr:postcode":"2940",
    "addr:street":"Hoogeind",
    "iso:country":"BE",
    "sg:address":"Hoogeind 130",
    "sg:city":"Stabroek",
    "sg:orig_category":"Instituts de beaut\u00e9",
    "sg:phone":"+32 3 568 09 94",
    "sg:postcode":"2940",
    "sg:province":"Antwerpen",
    "wof:name":"Beautycenter Bo",
    "wof:placetype":"venue"
},
  "geometry": {"coordinates":[4.3852119446,51.3409881592],"type":"Point"}
}