{
  "type": "Feature",
  "properties": {
    "addr:full":"Zoerselbaan 55 Malle Antwerpen 2390",
    "addr:housenumber":"55",
    "addr:postcode":"2390",
    "addr:street":"Zoerselbaan",
    "iso:country":"BE",
    "sg:address":"Zoerselbaan 55",
    "sg:city":"Malle",
    "sg:orig_category":"Sportclubs",
    "sg:phone":"+32 3 312 15 61",
    "sg:postcode":"2390",
    "sg:province":"Antwerpen",
    "wof:name":"Eendracht",
    "wof:placetype":"venue"
},
  "geometry": {"coordinates":[4.697042942,51.2943840027],"type":"Point"}
}