{
  "type": "Feature",
  "properties": {
    "iso:country":"BE",
    "sg:address":"Cardijnlaan 1 (ring)",
    "sg:city":"Herentals",
    "sg:orig_category":"Non-Classified Establishments",
    "sg:phone":"+32 14 21 35 33",
    "sg:postcode":"2200",
    "sg:province":"Antwerpen",
    "wof:name":"Arc Herentals",
    "wof:placetype":"venue"
},
  "geometry": {"coordinates":[4.840531826,51.1864318848],"type":"Point"}
}