{
  "type": "Feature",
  "properties": {
    "iso:country":"BE",
    "sg:address":"Rue Rond Du Roi Albert 16 Box O",
    "sg:city":"Awans (villers-l'ev\u00eaque)",
    "sg:classifiers":[
        {
            "category":"Health Services",
            "subcategory":"Hospital",
            "type":"Services"
        }
    ],
    "sg:phone":"+32 4 257 50 90",
    "sg:postcode":"4340",
    "sg:province":"Li\u00e8ge",
    "wof:name":"Domaine Des Bles Dores",
    "wof:placetype":"venue"
},
  "geometry": {"coordinates":[5.4620018005,50.663772583],"type":"Point"}
}