{
  "type": "Feature",
  "properties": {
    "addr:full":"Deinzestraat 1 Oudenaarde Oost-Vlaanderen 9700",
    "addr:housenumber":"1",
    "addr:postcode":"9700",
    "addr:street":"Deinzestraat",
    "iso:country":"BE",
    "sg:address":"Deinzestraat 1",
    "sg:city":"Oudenaarde",
    "sg:classifiers":[
        {
            "category":"Professional",
            "subcategory":"Lawyer & Legal Services",
            "type":"Services"
        }
    ],
    "sg:phone":"+32 55 31 71 08",
    "sg:postcode":"9700",
    "sg:province":"Oost-Vlaanderen",
    "wof:name":"Blockeel Luc",
    "wof:placetype":"venue"
},
  "geometry": {"coordinates":[3.5955479145,50.8516845703],"type":"Point"}
}