{
  "type": "Feature",
  "properties": {
    "addr:full":"Markt 28 Box 1 Haacht Vlaams-Brabant 3150",
    "addr:housenumber":"28;1",
    "addr:postcode":"3150",
    "addr:street":"Markt;Box",
    "iso:country":"BE",
    "sg:address":"Markt 28 Box 1",
    "sg:city":"Haacht",
    "sg:classifiers":[
        {
            "category":"Banks & Credit Unions",
            "subcategory":"Investment Brokerage",
            "type":"Services"
        }
    ],
    "sg:phone":"+32 16 60 68 34",
    "sg:postcode":"3150",
    "sg:province":"Vlaams-Brabant",
    "sg:tags":[
        "jean",
        "casual",
        "wear"
    ],
    "wof:name":"Bonetti Fashion",
    "wof:placetype":"venue"
},
  "geometry": {"coordinates":[4.6380047798,50.9768714905],"type":"Point"}
}