{
  "type": "Feature",
  "properties": {
    "addr:full":"Rue Lamarck 115 Li\u00e8ge 1 Li\u00e8ge 4000",
    "addr:housenumber":"115;1",
    "addr:postcode":"4000",
    "addr:street":"Rue Lamarck",
    "iso:country":"BE",
    "sg:address":"Rue Lamarck 115",
    "sg:city":"Li\u00e8ge 1",
    "sg:classifiers":[
        {
            "category":"Banks & Credit Unions",
            "subcategory":"Investment Brokerage",
            "type":"Services"
        }
    ],
    "sg:phone":"+32 4 228 17 37",
    "sg:postcode":"4000",
    "sg:province":"Li\u00e8ge",
    "sg:tags":[
        "repair",
        "-",
        "installation",
        "sanitary",
        "article"
    ],
    "wof:name":"S.r.d.b. Sprl",
    "wof:placetype":"venue"
},
  "geometry": {"coordinates":[5.5930452347,50.6520957947],"type":"Point"}
}