{
  "type": "Feature",
  "properties": {
    "iso:country":"BE",
    "sg:address":"Place Des Sartiaux 12",
    "sg:city":"Saint-ghislain",
    "sg:orig_category":"Herstellingen and onderhoud van auto's",
    "sg:phone":"+32 65 64 27 10",
    "sg:postcode":"7331",
    "sg:province":"Hainaut",
    "wof:name":"Carrosserie Loader & Fils",
    "wof:placetype":"venue"
},
  "geometry": {"coordinates":[3.8255620003,50.4776382446],"type":"Point"}
}