{
  "type": "Feature",
  "properties": {
    "iso:country":"BE",
    "sg:address":"Jezuietenrui 1",
    "sg:city":"Antwerpen",
    "sg:classifiers":[
        {
            "category":"Bars & Pubs",
            "type":"Food & Drink"
        }
    ],
    "sg:phone":"+32 3 234 06 61",
    "sg:postcode":"2000",
    "sg:province":"Antwerpen",
    "wof:name":"Leeuw Van Vlaanderen (de)",
    "wof:placetype":"venue"
},
  "geometry": {"coordinates":[4.402826786,51.220954895],"type":"Point"}
}