{
  "type": "Feature",
  "properties": {
    "addr:full":"De Gerlachekaai 20 Antwerpen Antwerpen 2000",
    "addr:housenumber":"20",
    "addr:postcode":"2000",
    "iso:country":"BE",
    "sg:address":"De Gerlachekaai 20",
    "sg:city":"Antwerpen",
    "sg:classifiers":[
        {
            "category":"Organizations",
            "subcategory":"Political Organization",
            "type":"Services"
        }
    ],
    "sg:phone":"+32 3 244 49 50",
    "sg:postcode":"2000",
    "sg:province":"Antwerpen",
    "sg:tags":[
        "owner",
        "ship"
    ],
    "wof:name":"Portlink Nv",
    "wof:placetype":"venue"
},
  "geometry": {"coordinates":[4.3856258392,51.2085838318],"type":"Point"}
}