{
  "type": "Feature",
  "properties": {
    "iso:country":"BE",
    "sg:address":"Rue Barth\u00e9lemy Molet 16",
    "sg:city":"Sambreville (tamines)",
    "sg:classifiers":[
        {
            "category":"Arts & Performance",
            "subcategory":"Music",
            "type":"Entertainment"
        }
    ],
    "sg:phone":"+32 71 74 17 32",
    "sg:postcode":"5060",
    "sg:province":"Namur",
    "sg:tags":[
        "-",
        "background"
    ],
    "wof:name":"Mouyard R",
    "wof:placetype":"venue"
},
  "geometry": {"coordinates":[4.5897297859,50.4382591248],"type":"Point"}
}