{
  "type": "Feature",
  "properties": {
    "iso:country":"BE",
    "sg:address":"Lourdesstraat 90",
    "sg:city":"Wervik",
    "sg:classifiers":[
        {
            "category":"Insurance",
            "subcategory":"Life Insurance",
            "type":"Services"
        }
    ],
    "sg:phone":"+32 56 51 96 52",
    "sg:postcode":"8940",
    "sg:province":"West-Vlaanderen",
    "sg:tags":[
        "assurance"
    ],
    "wof:name":"E. Vlegels",
    "wof:placetype":"venue"
},
  "geometry": {"coordinates":[3.0832700729,50.8186187744],"type":"Point"}
}