{
  "type": "Feature",
  "properties": {
    "iso:country":"BE",
    "sg:address":"Sint-rijkersstraat 15",
    "sg:city":"Alveringem",
    "sg:classifiers":[
        {
            "category":"Health Services",
            "subcategory":"Dentist",
            "type":"Services"
        }
    ],
    "sg:phone":"+32 58 28 82 91",
    "sg:postcode":"8690",
    "sg:province":"West-Vlaanderen",
    "wof:name":"Dequidt K",
    "wof:placetype":"venue"
},
  "geometry": {"coordinates":[2.7085249424,51.0126457214],"type":"Point"}
}