{
  "type": "Feature",
  "properties": {
    "iso:country":"BE",
    "sg:address":"Weidenstraat 38",
    "sg:city":"Kuurne",
    "sg:orig_category":"Locations de machines and \u00e9quipement pour la construction. Transports routiers de marchandises",
    "sg:phone":"+32 56 71 89 21",
    "sg:postcode":"8520",
    "sg:province":"West-Vlaanderen",
    "wof:name":"Ville De Courtrai",
    "wof:placetype":"venue"
},
  "geometry": {"coordinates":[3.2935700417,50.8522911072],"type":"Point"}
}