{
  "type": "Feature",
  "properties": {
    "iso:country":"BE",
    "sg:address":"Zavelbaan 59",
    "sg:city":"Aalst",
    "sg:orig_category":"Installatie van houten of kunststof schrijnwerk Installatie van metalen schrijnwerk Serres and speci",
    "sg:phone":"+32 53 70 03 51",
    "sg:postcode":"9300",
    "sg:province":"Oost-Vlaanderen",
    "wof:name":"Alu-met",
    "wof:placetype":"venue"
},
  "geometry": {"coordinates":[4.0490479469,50.9503517151],"type":"Point"}
}