{
  "type": "Feature",
  "properties": {
    "iso:country":"BE",
    "sg:address":"Rupsenstraat 16bb",
    "sg:city":"Wingene",
    "sg:classifiers":[
        {
            "category":"Insurance",
            "subcategory":"Insurance Agent",
            "type":"Services"
        }
    ],
    "sg:phone":"+32 51 61 32 00",
    "sg:postcode":"8750",
    "sg:province":"West-Vlaanderen",
    "sg:tags":[
        "verzekeringsmakelaars",
        "expert"
    ],
    "wof:name":"K. Desmet",
    "wof:placetype":"venue"
},
  "geometry": {"coordinates":[3.2231440544,51.0409317017],"type":"Point"}
}