{
  "type": "Feature",
  "properties": {
    "addr:full":"Europark 2030 Houthalen-helchteren (houthalen) Limburg 3530",
    "addr:postcode":"2030;3530",
    "addr:street":"Europark",
    "iso:country":"BE",
    "sg:address":"Europark 2030",
    "sg:city":"Houthalen-helchteren (houthalen)",
    "sg:classifiers":[
        {
            "category":"Manufacturing",
            "subcategory":"Motor Vehicles & Parts",
            "type":"Manufacturing & Wholesale Goods"
        }
    ],
    "sg:phone":"+32 11 81 81 91",
    "sg:postcode":"3530",
    "sg:province":"Limburg",
    "sg:tags":[
        "body",
        "automobile",
        "construction",
        "-"
    ],
    "wof:name":"Covess Nv",
    "wof:placetype":"venue"
},
  "geometry": {"coordinates":[5.3954958916,51.040813446],"type":"Point"}
}