{
  "type": "Feature",
  "properties": {
    "addr:full":"Wapenplein 9b12 Oostende West-Vlaanderen 8400",
    "addr:housenumber":"9b12",
    "addr:postcode":"8400",
    "addr:street":"Wapenplein",
    "iso:country":"BE",
    "sg:address":"Wapenplein 9b12",
    "sg:city":"Oostende",
    "sg:classifiers":[
        {
            "category":"Shopping",
            "subcategory":"Clothing, Apparel, & Fashions",
            "type":"Retail Goods"
        }
    ],
    "sg:phone":"+32 59 70 41 07",
    "sg:postcode":"8400",
    "sg:province":"West-Vlaanderen",
    "sg:tags":[
        "v\u00eatements",
        "pour",
        "dame"
    ],
    "wof:name":"Couture Claire",
    "wof:placetype":"venue"
},
  "geometry": {"coordinates":[2.9176609516,51.2324867249],"type":"Point"}
}