{
  "type": "Feature",
  "properties": {
    "iso:country":"BE",
    "sg:address":"Grote Steenweg 126",
    "sg:city":"Zulte",
    "sg:orig_category":"Fleurs and plantes",
    "sg:phone":"+32 9 388 46 89",
    "sg:postcode":"9870",
    "sg:province":"Oost-Vlaanderen",
    "wof:name":"Huis Ixora",
    "wof:placetype":"venue"
},
  "geometry": {"coordinates":[3.4436409473,50.921661377],"type":"Point"}
}