{
  "type": "Feature",
  "properties": {
    "addr:full":"Henri Torleylaan 9 Beersel Vlaams-Brabant 1654",
    "addr:housenumber":"9",
    "addr:postcode":"1654",
    "addr:street":"Henri Torleylaan",
    "iso:country":"BE",
    "sg:address":"Henri Torleylaan 9",
    "sg:city":"Beersel",
    "sg:orig_category":"Kapsalons",
    "sg:phone":"+32 2 356 72 35",
    "sg:postcode":"1654",
    "sg:province":"Vlaams-Brabant",
    "wof:name":"Herremans J.",
    "wof:placetype":"venue"
},
  "geometry": {"coordinates":[4.2748007774,50.7468757629],"type":"Point"}
}