{
  "type": "Feature",
  "properties": {
    "iso:country":"BE",
    "sg:address":"Boulevard Audent 28",
    "sg:city":"Charleroi",
    "sg:orig_category":"Artsen and specialisten",
    "sg:phone":"+32 71 21 62 02",
    "sg:postcode":"6000",
    "sg:province":"Hainaut",
    "wof:name":"P. Falise",
    "wof:placetype":"venue"
},
  "geometry": {"coordinates":[4.4455738068,50.409412384],"type":"Point"}
}