{
  "type": "Feature",
  "properties": {
    "iso:country":"BE",
    "sg:address":"Aarschotsebaan 1a",
    "sg:city":"Boutersem",
    "sg:classifiers":[
        {
            "category":"Professional",
            "type":"Services"
        }
    ],
    "sg:phone":"+32 16 73 41 80",
    "sg:postcode":"3370",
    "sg:province":"Vlaams-Brabant",
    "sg:tags":[
        "auction",
        "room"
    ],
    "wof:name":"Jomaco Bvba",
    "wof:placetype":"venue"
},
  "geometry": {"coordinates":[4.8205008507,50.8477973938],"type":"Point"}
}