{
  "type": "Feature",
  "properties": {
    "iso:country":"BE",
    "sg:address":"Pater Beckstraat 19",
    "sg:city":"Kortrijk",
    "sg:classifiers":[
        {
            "category":"Health Services",
            "subcategory":"Dentist",
            "type":"Services"
        }
    ],
    "sg:phone":"+32 56 20 13 01",
    "sg:postcode":"8500",
    "sg:province":"West-Vlaanderen",
    "wof:name":"De Schepper K",
    "wof:placetype":"venue"
},
  "geometry": {"coordinates":[3.2654900551,50.8211517334],"type":"Point"}
}