{
  "type": "Feature",
  "properties": {
    "iso:country":"BE",
    "sg:address":"Emile Bockstaellaan 244",
    "sg:city":"Brussel/bruxelles",
    "sg:orig_category":"Openbare veiligheid",
    "sg:phone":"+32 2 517 96 80",
    "sg:postcode":"1020",
    "sg:province":"Bruxelles-Capitale",
    "wof:name":"Police F\u00c9d\u00c9rale/federale Politie",
    "wof:placetype":"venue"
},
  "geometry": {"coordinates":[4.3479990959,50.8762130737],"type":"Point"}
}