{
  "type": "Feature",
  "properties": {
    "addr:full":"Gentse Steenweg 117bi Lokeren Oost-Vlaanderen 9160",
    "addr:housenumber":"117bi",
    "addr:postcode":"9160",
    "addr:street":"Gentse Steenweg",
    "iso:country":"BE",
    "sg:address":"Gentse Steenweg 117bi",
    "sg:city":"Lokeren",
    "sg:orig_category":"Rev\u00eatements de sols and murs. Rev\u00eatements pour sols and murs",
    "sg:phone":"+32 9 349 28 38",
    "sg:postcode":"9160",
    "sg:province":"Oost-Vlaanderen",
    "wof:name":"Gys Benelux",
    "wof:placetype":"venue"
},
  "geometry": {"coordinates":[3.9504609108,51.114780426],"type":"Point"}
}