{
  "type": "Feature",
  "properties": {
    "addr:full":"J.p. Minckelersstraat 84 Leuven Vlaams-Brabant 3000",
    "addr:housenumber":"84",
    "addr:postcode":"3000",
    "addr:street":"J.P. Minckelersstraat",
    "iso:country":"BE",
    "sg:address":"J.p. Minckelersstraat 84",
    "sg:city":"Leuven",
    "sg:classifiers":[
        {
            "category":"Shopping",
            "subcategory":"Computers & Home Electronics",
            "type":"Retail Goods"
        }
    ],
    "sg:phone":"+32 16 23 05 08",
    "sg:postcode":"3000",
    "sg:province":"Vlaams-Brabant",
    "sg:tags":[
        "-",
        "peripheral",
        "processing",
        "data",
        "equipment"
    ],
    "wof:name":"S.v.b.-janssen",
    "wof:placetype":"venue"
},
  "geometry": {"coordinates":[4.7036700249,50.8793869019],"type":"Point"}
}