{
  "type": "Feature",
  "properties": {
    "addr:full":"Aarschotsesteenweg 6b68 Tielt-winge Vlaams-Brabant 3390",
    "addr:housenumber":"6b68",
    "addr:postcode":"3390",
    "addr:street":"Aarschotsesteenweg",
    "iso:country":"BE",
    "sg:address":"Aarschotsesteenweg 6b68",
    "sg:city":"Tielt-winge",
    "sg:orig_category":"Chaussures",
    "sg:phone":"+32 16 63 13 60",
    "sg:postcode":"3390",
    "sg:province":"Vlaams-Brabant",
    "wof:name":"Brantano",
    "wof:placetype":"venue"
},
  "geometry": {"coordinates":[4.8762331009,50.9013748169],"type":"Point"}
}