{
  "type": "Feature",
  "properties": {
    "iso:country":"BE",
    "sg:address":"Avenue Blonden 42",
    "sg:city":"Li\u00e8ge 1",
    "sg:classifiers":[
        {
            "category":"Shopping",
            "subcategory":"Computers & Home Electronics",
            "type":"Retail Goods"
        }
    ],
    "sg:phone":"+32 4 252 42 32",
    "sg:postcode":"4000",
    "sg:province":"Li\u00e8ge",
    "sg:tags":[
        "-",
        "peripheral",
        "processing",
        "data",
        "equipment"
    ],
    "wof:name":"Micro Select",
    "wof:placetype":"venue"
},
  "geometry": {"coordinates":[5.57020998,50.6288414001],"type":"Point"}
}