{
  "type": "Feature",
  "properties": {
    "addr:full":"Rue Des Chapeliers 7 Tournai Hainaut 7500",
    "addr:housenumber":"7",
    "addr:postcode":"7500",
    "addr:street":"Rue Des Chapeliers",
    "iso:country":"BE",
    "sg:address":"Rue Des Chapeliers 7",
    "sg:city":"Tournai",
    "sg:classifiers":[
        {
            "category":"Shopping",
            "subcategory":"Clothing, Apparel, & Fashions",
            "type":"Retail Goods"
        }
    ],
    "sg:phone":"+32 69 22 32 69",
    "sg:postcode":"7500",
    "sg:province":"Hainaut",
    "sg:tags":[
        "boutique"
    ],
    "wof:name":"Look",
    "wof:placetype":"venue"
},
  "geometry": {"coordinates":[3.3899960518,50.606212616],"type":"Point"}
}