{
  "type": "Feature",
  "properties": {
    "addr:full":"Vijversstraat 23 Hasselt Limburg 3500",
    "addr:housenumber":"23",
    "addr:postcode":"3500",
    "addr:street":"Vijversstraat",
    "iso:country":"BE",
    "sg:address":"Vijversstraat 23",
    "sg:city":"Hasselt",
    "sg:orig_category":"Newspapers, magazines, periodicals - Distribution",
    "sg:phone":"+32 11 21 02 44",
    "sg:postcode":"3500",
    "sg:province":"Limburg",
    "wof:name":"Van Den Born S",
    "wof:placetype":"venue"
},
  "geometry": {"coordinates":[5.3536200523,50.9636001587],"type":"Point"}
}