{
  "type": "Feature",
  "properties": {
    "addr:full":"Krijgsbaan 39 Mortsel Antwerpen 2640",
    "addr:housenumber":"39",
    "addr:postcode":"2640",
    "addr:street":"Krijgsbaan",
    "iso:country":"BE",
    "sg:address":"Krijgsbaan 39",
    "sg:city":"Mortsel",
    "sg:classifiers":[
        {
            "category":"Wholesale",
            "subcategory":"Books, Periodicals, & Newspapers",
            "type":"Manufacturing & Wholesale Goods"
        }
    ],
    "sg:phone":"+32 3 443 91 40",
    "sg:postcode":"2640",
    "sg:province":"Antwerpen",
    "sg:tags":[
        "publisher"
    ],
    "wof:name":"Denis & Co",
    "wof:placetype":"venue"
},
  "geometry": {"coordinates":[4.4565491676,51.1758422852],"type":"Point"}
}