{
  "type": "Feature",
  "properties": {
    "iso:country":"BE",
    "sg:address":"Maatheide 1540",
    "sg:city":"Lommel",
    "sg:orig_category":"Non-Classified Establishments",
    "sg:phone":"+32 11 54 59 85",
    "sg:postcode":"3920",
    "sg:province":"Limburg",
    "wof:name":"Van Adrichem",
    "wof:placetype":"venue"
},
  "geometry": {"coordinates":[5.2657299042,51.234539032],"type":"Point"}
}