{
  "type": "Feature",
  "properties": {
    "iso:country":"BE",
    "sg:address":"Boulevard D'avroy 130",
    "sg:city":"Luik",
    "sg:orig_category":"Medische and orthopedische apparaten",
    "sg:phone":"+32 4 221 04 31",
    "sg:postcode":"4000",
    "sg:province":"Li\u00e8ge",
    "wof:name":"L'acoustique M\u00c9dical",
    "wof:placetype":"venue"
},
  "geometry": {"coordinates":[5.5672421455,50.6351623535],"type":"Point"}
}