{
  "type": "Feature",
  "properties": {
    "addr:full":"Rue De Wand 195 Brussel/bruxelles Bruxelles-Capitale 1020",
    "addr:housenumber":"195",
    "addr:postcode":"1020",
    "addr:street":"Rue De Wand;/",
    "iso:country":"BE",
    "sg:address":"Rue De Wand 195",
    "sg:city":"Brussel/bruxelles",
    "sg:classifiers":[
        {
            "category":"Fast Food",
            "type":"Food & Drink"
        }
    ],
    "sg:phone":"+32 2 268 65 49",
    "sg:postcode":"1020",
    "sg:province":"Bruxelles-Capitale",
    "sg:tags":[
        "meeneem",
        "restaurant"
    ],
    "wof:name":"I Fratelli D\u00b4italia",
    "wof:placetype":"venue"
},
  "geometry": {"coordinates":[4.3604359627,50.8996162415],"type":"Point"}
}