{
  "type": "Feature",
  "properties": {
    "addr:full":"Ertbruggestraat 108 Wijnegem Antwerpen 2110",
    "addr:housenumber":"108",
    "addr:postcode":"2110",
    "addr:street":"Ertbruggestraat",
    "iso:country":"BE",
    "sg:address":"Ertbruggestraat 108",
    "sg:city":"Wijnegem",
    "sg:orig_category":"Verhuur textielartikelen and schoenen",
    "sg:phone":"+32 3 354 10 49",
    "sg:postcode":"2110",
    "sg:province":"Antwerpen",
    "wof:name":"Boco",
    "wof:placetype":"venue"
},
  "geometry": {"coordinates":[4.4991540909,51.2277832031],"type":"Point"}
}