{
  "type": "Feature",
  "properties": {
    "addr:full":"Rue De L'escalette 86 Tournai Hainaut 7500",
    "addr:housenumber":"86",
    "addr:postcode":"7500",
    "addr:street":"Rue De L'Escalette",
    "iso:country":"BE",
    "sg:address":"Rue De L'escalette 86",
    "sg:city":"Tournai",
    "sg:classifiers":[
        {
            "category":"Professional",
            "subcategory":"Accounting & Tax Preparation",
            "type":"Services"
        }
    ],
    "sg:phone":"+32 69 84 15 22",
    "sg:postcode":"7500",
    "sg:province":"Hainaut",
    "sg:tags":[
        "accountant"
    ],
    "wof:name":"Dubar J-p",
    "wof:placetype":"venue"
},
  "geometry": {"coordinates":[3.3701620102,50.6168479919],"type":"Point"}
}