{
  "type": "Feature",
  "properties": {
    "iso:country":"BE",
    "sg:address":"Rue Adolphe Sax 40",
    "sg:city":"Dinant",
    "sg:classifiers":[
        {
            "category":"Banks & Credit Unions",
            "subcategory":"Bank",
            "type":"Services"
        }
    ],
    "sg:phone":"+32 82 22 67 20",
    "sg:postcode":"5500",
    "sg:province":"Namur",
    "sg:tags":[
        "savings-banks"
    ],
    "wof:name":"A.d.n. Scris",
    "wof:placetype":"venue"
},
  "geometry": {"coordinates":[4.9109020233,50.261631012],"type":"Point"}
}