{
  "type": "Feature",
  "properties": {
    "addr:full":"Chauss\u00c9e De Willemeau 291 Tournai Hainaut 7500",
    "addr:housenumber":"291",
    "addr:postcode":"7500",
    "addr:street":"Chausse\u0301E De Willemeau",
    "iso:country":"BE",
    "sg:address":"Chauss\u00c9e De Willemeau 291",
    "sg:city":"Tournai",
    "sg:orig_category":"Herstellingen and onderhoud van auto's",
    "sg:phone":"+32 69 23 38 84",
    "sg:postcode":"7500",
    "sg:province":"Hainaut",
    "wof:name":"Modeste De Meulemeester",
    "wof:placetype":"venue"
},
  "geometry": {"coordinates":[3.3679258823,50.5876235962],"type":"Point"}
}