{
  "type": "Feature",
  "properties": {
    "addr:full":"Grand-place 7 Yvoir Namur 5530",
    "addr:housenumber":"7",
    "addr:postcode":"5530",
    "addr:street":"Grand-Place",
    "iso:country":"BE",
    "sg:address":"Grand-place 7",
    "sg:city":"Yvoir",
    "sg:orig_category":"Boucheries",
    "sg:phone":"+32 82 61 33 86",
    "sg:postcode":"5530",
    "sg:province":"Namur",
    "wof:name":"Boucherie De La Place",
    "wof:placetype":"venue"
},
  "geometry": {"coordinates":[4.9436211586,50.3124656677],"type":"Point"}
}