{
  "type": "Feature",
  "properties": {
    "iso:country":"BE",
    "sg:address":"Rue De La Tombe 86",
    "sg:city":"Sombreffe",
    "sg:orig_category":"Plomberie, chauffage and installations sanitaires",
    "sg:phone":"+32 71 88 87 36",
    "sg:postcode":"5140",
    "sg:province":"Namur",
    "wof:name":"Hainalux",
    "wof:placetype":"venue"
},
  "geometry": {"coordinates":[4.5761699677,50.499370575],"type":"Point"}
}