{
  "type": "Feature",
  "properties": {
    "iso:country":"BE",
    "sg:address":"Rue Emile Vandervelde 102",
    "sg:city":"Sambreville",
    "sg:classifiers":[
        {
            "category":"Personal",
            "subcategory":"Beauty Salon",
            "type":"Services"
        }
    ],
    "sg:phone":"+32 71 77 78 82",
    "sg:postcode":"5060",
    "sg:province":"Namur",
    "sg:tags":[
        "de",
        "coiffure"
    ],
    "wof:name":"Carine Ippia",
    "wof:placetype":"venue"
},
  "geometry": {"coordinates":[4.5832247734,50.4397277832],"type":"Point"}
}