{
  "type": "Feature",
  "properties": {
    "addr:full":"Molenzijde 42 Merksplas Antwerpen 2330",
    "addr:housenumber":"42",
    "addr:postcode":"2330",
    "addr:street":"Molenzijde",
    "iso:country":"BE",
    "sg:address":"Molenzijde 42",
    "sg:city":"Merksplas",
    "sg:orig_category":"Poissonniers and \u00e9caillers",
    "sg:phone":"+32 14 63 49 66",
    "sg:postcode":"2330",
    "sg:province":"Antwerpen",
    "wof:name":"Alfons Beckx",
    "wof:placetype":"venue"
},
  "geometry": {"coordinates":[4.8482351303,51.3591308594],"type":"Point"}
}