{
  "type": "Feature",
  "properties": {
    "addr:full":"Kwabrugstraat 100 Kortrijk West-Vlaanderen 8510",
    "addr:housenumber":"100",
    "addr:postcode":"8510",
    "addr:street":"Kwabrugstraat",
    "iso:country":"BE",
    "sg:address":"Kwabrugstraat 100",
    "sg:city":"Kortrijk",
    "sg:orig_category":"Rundveehouders",
    "sg:phone":"+32 56 21 48 42",
    "sg:postcode":"8510",
    "sg:province":"West-Vlaanderen",
    "wof:name":"Robert Vandeputte",
    "wof:placetype":"venue"
},
  "geometry": {"coordinates":[3.2789740562,50.7704162598],"type":"Point"}
}