{
  "type": "Feature",
  "properties": {
    "addr:full":"Vogelmarkt 1 Gent Oost-Vlaanderen 9000",
    "addr:housenumber":"1",
    "addr:postcode":"9000",
    "addr:street":"Vogelmarkt;Oost-Vlaanderen",
    "iso:country":"BE",
    "sg:address":"Vogelmarkt 1",
    "sg:city":"Gent",
    "sg:orig_category":"Dameskledingzaken",
    "sg:phone":"+32 9 225 58 57",
    "sg:postcode":"9000",
    "sg:province":"Oost-Vlaanderen",
    "wof:name":"Solent",
    "wof:placetype":"venue"
},
  "geometry": {"coordinates":[3.7261149883,51.0505104065],"type":"Point"}
}