{
  "type": "Feature",
  "properties": {
    "iso:country":"BE",
    "sg:address":"Rue Du Village 16a",
    "sg:city":"Beauvechain",
    "sg:classifiers":[
        {
            "category":"Building & Trades",
            "subcategory":"Cleaning & Sanitation",
            "type":"Services"
        }
    ],
    "sg:phone":"+32 10 86 16 56",
    "sg:postcode":"1320",
    "sg:province":"Brabant Wallon",
    "sg:tags":[
        "cleaner",
        "window"
    ],
    "wof:name":"Master Clean",
    "wof:placetype":"venue"
},
  "geometry": {"coordinates":[4.7755470276,50.7837104797],"type":"Point"}
}