{
  "type": "Feature",
  "properties": {
    "iso:country":"BE",
    "sg:address":"Rue Des Bl\u00c9s D'or 8",
    "sg:city":"Tubize",
    "sg:orig_category":"Sportclubs",
    "sg:phone":"+32 2 355 21 41",
    "sg:postcode":"1480",
    "sg:province":"Brabant Wallon",
    "wof:name":"Indalo Aventure",
    "wof:placetype":"venue"
},
  "geometry": {"coordinates":[4.2080202103,50.6767158508],"type":"Point"}
}