{
  "type": "Feature",
  "properties": {
    "addr:full":"Place De L'albertine 1-3 Bruxelles Bruxelles-Capitale 1000",
    "addr:housenumber":"1-3",
    "addr:postcode":"1000",
    "addr:street":"Place De L'Albertine",
    "iso:country":"BE",
    "sg:address":"Place De L'albertine 1-3",
    "sg:city":"Bruxelles",
    "sg:classifiers":[
        {
            "category":"Manufacturing",
            "subcategory":"Musical Instruments",
            "type":"Manufacturing & Wholesale Goods"
        }
    ],
    "sg:postcode":"1000",
    "sg:province":"Bruxelles-Capitale",
    "sg:tags":[
        "piano"
    ],
    "wof:name":"Lemca Nv",
    "wof:placetype":"venue"
},
  "geometry": {"coordinates":[4.3551549911,50.8444824219],"type":"Point"}
}