{
  "type": "Feature",
  "properties": {
    "iso:country":"BE",
    "sg:address":"Bellestraat 206",
    "sg:city":"Affligem (essene)",
    "sg:classifiers":[
        {
            "category":"Wholesale",
            "subcategory":"Wine & Distilled Alcoholic Beverages",
            "type":"Manufacturing & Wholesale Goods"
        }
    ],
    "sg:phone":"+32 2 454 04 84",
    "sg:postcode":"1790",
    "sg:province":"Vlaams-Brabant",
    "sg:tags":[
        "whol",
        "-",
        "spirit",
        "mfg"
    ],
    "wof:name":"Ch\u00e2teaux",
    "wof:placetype":"venue"
},
  "geometry": {"coordinates":[4.1279778481,50.8916168213],"type":"Point"}
}