{
  "type": "Feature",
  "properties": {
    "addr:full":"Rue Notre-dame 7 Binche Hainaut 7130",
    "addr:housenumber":"7",
    "addr:postcode":"7130",
    "addr:street":"Rue Notre-Dame",
    "iso:country":"BE",
    "sg:address":"Rue Notre-dame 7",
    "sg:city":"Binche",
    "sg:classifiers":[
        {
            "category":"Retail",
            "subcategory":"Laundry & Dry Cleaning",
            "type":"Services"
        }
    ],
    "sg:phone":"+32 64 33 67 06",
    "sg:postcode":"7130",
    "sg:province":"Hainaut",
    "sg:tags":[
        "dyer",
        "cleaner"
    ],
    "wof:name":"Pressing No 1 Sprl",
    "wof:placetype":"venue"
},
  "geometry": {"coordinates":[4.1652369499,50.4114723206],"type":"Point"}
}