{
  "type": "Feature",
  "properties": {
    "iso:country":"BE",
    "sg:address":"Chauss\u00c9e De Louvain 391",
    "sg:city":"Schaarbeek/schaerbeek",
    "sg:orig_category":"Auto-\u00e9coles",
    "sg:phone":"+32 2 736 59 98",
    "sg:postcode":"1030",
    "sg:province":"Bruxelles-Capitale",
    "wof:name":"Auto-ecole Escam",
    "wof:placetype":"venue"
},
  "geometry": {"coordinates":[4.3909921646,50.8533554077],"type":"Point"}
}