{
  "type": "Feature",
  "properties": {
    "iso:country":"BE",
    "sg:address":"Acaciastraat 14a",
    "sg:city":"Geel",
    "sg:orig_category":"Traitement and rev\u00eatement des m\u00e9taux",
    "sg:phone":"+32 14 86 86 50",
    "sg:postcode":"2440",
    "sg:province":"Antwerpen",
    "wof:name":"Vandecruys J",
    "wof:placetype":"venue"
},
  "geometry": {"coordinates":[5.0130238533,51.1202201843],"type":"Point"}
}