{
  "type": "Feature",
  "properties": {
    "addr:full":"Place Du Perron 1 Andenne Namur 5300",
    "addr:housenumber":"1",
    "addr:postcode":"5300",
    "addr:street":"Place Du Perron",
    "iso:country":"BE",
    "sg:address":"Place Du Perron 1",
    "sg:city":"Andenne",
    "sg:orig_category":"Zalen voor culturele evenementen",
    "sg:phone":"+32 85 84 36 40",
    "sg:postcode":"5300",
    "sg:province":"Namur",
    "wof:name":"Centre Culturel D'andenne",
    "wof:placetype":"venue"
},
  "geometry": {"coordinates":[5.0982599258,50.4864616394],"type":"Point"}
}