{
  "type": "Feature",
  "properties": {
    "addr:full":"Raffisstraat 31 Meeuwen-gruitrode Limburg 3670",
    "addr:housenumber":"31",
    "addr:postcode":"3670",
    "addr:street":"Raffisstraat",
    "iso:country":"BE",
    "sg:address":"Raffisstraat 31",
    "sg:city":"Meeuwen-gruitrode",
    "sg:orig_category":"Installation de menuiserie en bois and plastique",
    "sg:phone":"+32 11 79 38 51",
    "sg:postcode":"3670",
    "sg:province":"Limburg",
    "wof:name":"Jos Vermeyen",
    "wof:placetype":"venue"
},
  "geometry": {"coordinates":[5.4872441292,51.099811554],"type":"Point"}
}