{
  "type": "Feature",
  "properties": {
    "iso:country":"BE",
    "sg:address":"Grand'place 47",
    "sg:city":"Verviers (ensival)",
    "sg:classifiers":[
        {
            "category":"Bakery",
            "type":"Food & Drink"
        }
    ],
    "sg:phone":"+32 87 33 25 78",
    "sg:postcode":"4800",
    "sg:province":"Li\u00e8ge",
    "sg:tags":[
        "confectioner",
        "baker"
    ],
    "wof:name":"Larondelle J-m",
    "wof:placetype":"venue"
},
  "geometry": {"coordinates":[5.842634201,50.5815086365],"type":"Point"}
}