{
  "type": "Feature",
  "properties": {
    "addr:full":"Noordstraat 10 Kontich Antwerpen 2550",
    "addr:housenumber":"10",
    "addr:postcode":"2550",
    "addr:street":"Noordstraat",
    "iso:country":"BE",
    "sg:address":"Noordstraat 10",
    "sg:city":"Kontich",
    "sg:orig_category":"Artsen and specialisten",
    "sg:phone":"+32 3 457 61 91",
    "sg:postcode":"2550",
    "sg:province":"Antwerpen",
    "wof:name":"Herman De Laet",
    "wof:placetype":"venue"
},
  "geometry": {"coordinates":[4.4459271431,51.1361312866],"type":"Point"}
}