{
  "type": "Feature",
  "properties": {
    "iso:country":"BE",
    "sg:address":"Rue Ortmans Hauzeur 16",
    "sg:city":"Verviers",
    "sg:classifiers":[
        {
            "category":"Government",
            "subcategory":"Post Office",
            "type":"Public Place"
        }
    ],
    "sg:phone":"+32 87 34 11 80",
    "sg:postcode":"4800",
    "sg:province":"Li\u00e8ge",
    "sg:tags":[
        "stamp"
    ],
    "wof:name":"Deom Philatelie",
    "wof:placetype":"venue"
},
  "geometry": {"coordinates":[5.8658227921,50.59349823],"type":"Point"}
}