{
  "type": "Feature",
  "properties": {
    "iso:country":"BE",
    "sg:address":"Rue Des Cultivateurs 57",
    "sg:city":"Bruxelles (etterbeek)",
    "sg:classifiers":[
        {
            "category":"Communications",
            "subcategory":"Film & Video Production",
            "type":"Services"
        }
    ],
    "sg:phone":"+32 2 737 10 60",
    "sg:postcode":"1040",
    "sg:province":"Bruxelles-Capitale",
    "sg:tags":[
        "sound",
        "recording",
        "studio"
    ],
    "wof:name":"Double Chantilly",
    "wof:placetype":"venue"
},
  "geometry": {"coordinates":[4.3932080269,50.8310661316],"type":"Point"}
}