{
  "type": "Feature",
  "properties": {
    "iso:country":"BE",
    "sg:address":"Dikkebusseweg 235",
    "sg:city":"Ieper",
    "sg:classifiers":[
        {
            "category":"Retail",
            "subcategory":"Animal Services",
            "type":"Services"
        }
    ],
    "sg:phone":"+32 57 21 77 51",
    "sg:postcode":"8900",
    "sg:province":"West-Vlaanderen",
    "sg:tags":[
        "farrier"
    ],
    "wof:name":"Declercq C",
    "wof:placetype":"venue"
},
  "geometry": {"coordinates":[2.8685030937,50.8402557373],"type":"Point"}
}