{
  "type": "Feature",
  "properties": {
    "iso:country":"BE",
    "sg:address":"Rue Saint-gilles 353",
    "sg:city":"Li\u00e8ge 1",
    "sg:classifiers":[
        {
            "category":"Retail",
            "subcategory":"Repair Shop",
            "type":"Services"
        }
    ],
    "sg:phone":"+32 4 253 30 07",
    "sg:postcode":"4000",
    "sg:province":"Li\u00e8ge",
    "sg:tags":[
        "upholsterer"
    ],
    "wof:name":"Guillemin P",
    "wof:placetype":"venue"
},
  "geometry": {"coordinates":[5.5507779121,50.6333694458],"type":"Point"}
}