{
  "type": "Feature",
  "properties": {
    "addr:full":"Chauss\u00c9e De Charleroi 1 Lasne Brabant Wallon 1380",
    "addr:housenumber":"1",
    "addr:postcode":"1380",
    "addr:street":"Chausse\u0301E De Charleroi",
    "iso:country":"BE",
    "sg:address":"Chauss\u00c9e De Charleroi 1",
    "sg:city":"Lasne",
    "sg:orig_category":"Boekhouders",
    "sg:phone":"+32 2 384 51 68",
    "sg:postcode":"1380",
    "sg:province":"Brabant Wallon",
    "wof:name":"Dominique De Visscher",
    "wof:placetype":"venue"
},
  "geometry": {"coordinates":[4.413561821,50.668094635],"type":"Point"}
}