{
  "type": "Feature",
  "properties": {
    "addr:full":"Grote Straat 115 Riemst (valmeer) Limburg 3770",
    "addr:housenumber":"115",
    "addr:postcode":"3770",
    "addr:street":"Grote Straat",
    "iso:country":"BE",
    "sg:address":"Grote Straat 115",
    "sg:city":"Riemst (valmeer)",
    "sg:classifiers":[
        {
            "category":"Bars & Pubs",
            "type":"Food & Drink"
        }
    ],
    "sg:phone":"+32 12 45 30 40",
    "sg:postcode":"3770",
    "sg:province":"Limburg",
    "wof:name":"Hanezang",
    "wof:placetype":"venue"
},
  "geometry": {"coordinates":[5.5961298943,50.7837905884],"type":"Point"}
}