{
  "type": "Feature",
  "properties": {
    "addr:full":"Dorpsstraat 166 Kortenberg (meerbeek) Vlaams-Brabant 3078",
    "addr:housenumber":"166",
    "addr:postcode":"3078",
    "addr:street":"Dorpsstraat",
    "iso:country":"BE",
    "sg:address":"Dorpsstraat 166",
    "sg:city":"Kortenberg (meerbeek)",
    "sg:classifiers":[
        {
            "category":"Professional",
            "subcategory":"Advertising",
            "type":"Services"
        }
    ],
    "sg:phone":"+32 2 759 53 50",
    "sg:postcode":"3078",
    "sg:province":"Vlaams-Brabant",
    "sg:tags":[
        "painter"
    ],
    "wof:name":"Danoart Belgium",
    "wof:placetype":"venue"
},
  "geometry": {"coordinates":[4.5897068977,50.8823051453],"type":"Point"}
}