{
  "type": "Feature",
  "properties": {
    "iso:country":"BE",
    "sg:address":"Handzamestraat 93b",
    "sg:city":"Kortemark",
    "sg:classifiers":[
        {
            "category":"Professional",
            "subcategory":"Lawyer & Legal Services",
            "type":"Services"
        }
    ],
    "sg:phone":"+32 475 64 56 99",
    "sg:postcode":"8610",
    "sg:province":"West-Vlaanderen",
    "wof:name":"Vandenberghe C",
    "wof:placetype":"venue"
},
  "geometry": {"coordinates":[3.0276329517,51.0289230347],"type":"Point"}
}