{
  "type": "Feature",
  "properties": {
    "iso:country":"BE",
    "sg:address":"Chauss\u00c9e De Renaix 86",
    "sg:city":"Frasnes-lez-anvaing",
    "sg:orig_category":"Sportclubs",
    "sg:phone":"+32 69 86 84 50",
    "sg:postcode":"7912",
    "sg:province":"Hainaut",
    "wof:name":"G.o. Gymclub Frasnois",
    "wof:placetype":"venue"
},
  "geometry": {"coordinates":[3.5797669888,50.7096061707],"type":"Point"}
}