{
  "type": "Feature",
  "properties": {
    "addr:full":"Engelmanshovenstraat 51 Heers Limburg 3870",
    "addr:housenumber":"51",
    "addr:postcode":"3870",
    "addr:street":"Engelmanshovenstraat",
    "iso:country":"BE",
    "sg:address":"Engelmanshovenstraat 51",
    "sg:city":"Heers",
    "sg:orig_category":"Epiceries",
    "sg:phone":"+32 11 48 02 00",
    "sg:postcode":"3870",
    "sg:province":"Limburg",
    "wof:name":"Spar",
    "wof:placetype":"venue"
},
  "geometry": {"coordinates":[5.2727398872,50.7738418579],"type":"Point"}
}