{
  "type": "Feature",
  "properties": {
    "addr:full":"Av. Du G\u00c9n\u00c9ral De Gaulle 36 Mons Hainaut 7000",
    "addr:housenumber":"36",
    "addr:postcode":"7000",
    "addr:street":"Av. Du Ge\u0301Ne\u0301Ral De Gaulle;Hainaut",
    "iso:country":"BE",
    "sg:address":"Av. Du G\u00c9n\u00c9ral De Gaulle 36",
    "sg:city":"Mons",
    "sg:orig_category":"V\u00e9t\u00e9rinaires",
    "sg:phone":"+32 65 84 75 75",
    "sg:postcode":"7000",
    "sg:province":"Hainaut",
    "wof:name":"B. Robette",
    "wof:placetype":"venue"
},
  "geometry": {"coordinates":[3.9473249912,50.4453811646],"type":"Point"}
}