{
  "type": "Feature",
  "properties": {
    "iso:country":"BE",
    "sg:address":"Planche 66",
    "sg:city":"Flobecq",
    "sg:classifiers":[
        {
            "category":"Health Services",
            "subcategory":"Health Practitioner",
            "type":"Services"
        }
    ],
    "sg:phone":"+32 68 44 83 46",
    "sg:postcode":"7880",
    "sg:province":"Hainaut",
    "sg:tags":[
        "physiotherapist"
    ],
    "wof:name":"Mouligneau A-c",
    "wof:placetype":"venue"
},
  "geometry": {"coordinates":[3.7384328842,50.7368049622],"type":"Point"}
}