{
  "type": "Feature",
  "properties": {
    "iso:country":"BE",
    "sg:address":"Rue Alphonse Scouvemont 107",
    "sg:city":"Qui\u00e9vrain (baisieux)",
    "sg:classifiers":[
        {
            "category":"Health Services",
            "subcategory":"Health Practitioner",
            "type":"Services"
        }
    ],
    "sg:phone":"+32 65 45 76 72",
    "sg:postcode":"7380",
    "sg:province":"Hainaut",
    "sg:tags":[
        "physiotherapist"
    ],
    "wof:name":"Hottois Xavier",
    "wof:placetype":"venue"
},
  "geometry": {"coordinates":[3.6965110302,50.3886070251],"type":"Point"}
}