{
  "type": "Feature",
  "properties": {
    "addr:full":"Van Hesedreef 45 Zele Oost-Vlaanderen 9240",
    "addr:housenumber":"45",
    "addr:postcode":"9240",
    "iso:country":"BE",
    "sg:address":"Van Hesedreef 45",
    "sg:city":"Zele",
    "sg:orig_category":"Boucheries",
    "sg:phone":"+32 52 44 51 75",
    "sg:postcode":"9240",
    "sg:province":"Oost-Vlaanderen",
    "wof:name":"G. Merckx",
    "wof:placetype":"venue"
},
  "geometry": {"coordinates":[4.0291638374,51.0638542175],"type":"Point"}
}