{
  "type": "Feature",
  "properties": {
    "iso:country":"BE",
    "sg:address":"Rue Jacobs Fontaine 13",
    "sg:city":"Bruxelles",
    "sg:classifiers":[
        {
            "category":"Health Services",
            "subcategory":"Doctor",
            "type":"Services"
        }
    ],
    "sg:phone":"+32 476 33 29 39",
    "sg:postcode":"1020",
    "sg:province":"Bruxelles-Capitale",
    "sg:tags":[
        "psychotherapist",
        "psychoanalyst"
    ],
    "wof:name":"Smet P",
    "wof:placetype":"venue"
},
  "geometry": {"coordinates":[4.3433427811,50.878200531],"type":"Point"}
}