{
  "type": "Feature",
  "properties": {
    "addr:full":"Frans Beirenslaan 257-261 Borsbeek Antwerpen 2150",
    "addr:postcode":"257-261;2150",
    "addr:street":"Frans Beirenslaan",
    "iso:country":"BE",
    "sg:address":"Frans Beirenslaan 257-261",
    "sg:city":"Borsbeek",
    "sg:classifiers":[
        {
            "category":"Manufacturing",
            "subcategory":"Lumber",
            "type":"Manufacturing & Wholesale Goods"
        }
    ],
    "sg:phone":"+32 3 322 11 81",
    "sg:postcode":"2150",
    "sg:province":"Antwerpen",
    "sg:tags":[
        "timber"
    ],
    "wof:name":"Global Wood Bvba",
    "wof:placetype":"venue"
},
  "geometry": {"coordinates":[4.4836678505,51.2005348206],"type":"Point"}
}