{
  "type": "Feature",
  "properties": {
    "iso:country":"BE",
    "sg:address":"Rue Saules Bastin 14",
    "sg:city":"Aywaille",
    "sg:orig_category":"Elektrische installaties voor woningen",
    "sg:phone":"+32 4 384 71 85",
    "sg:postcode":"4920",
    "sg:province":"Li\u00e8ge",
    "wof:name":"Rino Danesi",
    "wof:placetype":"venue"
},
  "geometry": {"coordinates":[5.7370271683,50.5156860352],"type":"Point"}
}