{
  "type": "Feature",
  "properties": {
    "addr:full":"Schorestraat 18 Middelkerke West-Vlaanderen 8433",
    "addr:housenumber":"18",
    "addr:postcode":"8433",
    "addr:street":"Schorestraat",
    "iso:country":"BE",
    "sg:address":"Schorestraat 18",
    "sg:city":"Middelkerke",
    "sg:orig_category":"Eleveurs de bovins",
    "sg:phone":"+32 51 55 54 29",
    "sg:postcode":"8433",
    "sg:province":"West-Vlaanderen",
    "wof:name":"Gabriel Van Hecke",
    "wof:placetype":"venue"
},
  "geometry": {"coordinates":[2.8475210667,51.1547775269],"type":"Point"}
}