{
  "type": "Feature",
  "properties": {
    "iso:country":"BE",
    "sg:address":"Mennaertstraat 2",
    "sg:city":"Kapelle-op-den-bos",
    "sg:orig_category":"Pharmaciens",
    "sg:phone":"+32 15 71 33 39",
    "sg:postcode":"1880",
    "sg:province":"Vlaams-Brabant",
    "wof:name":"Johan Brock",
    "wof:placetype":"venue"
},
  "geometry": {"coordinates":[4.3508300781,50.988658905],"type":"Point"}
}