{
  "type": "Feature",
  "properties": {
    "iso:country":"BE",
    "sg:address":"Rue Seutin 31",
    "sg:city":"Schaarbeek/schaerbeek",
    "sg:orig_category":"M\u00e9decins and sp\u00e9cialistes",
    "sg:phone":"+32 2 215 73 73",
    "sg:postcode":"1030",
    "sg:province":"Bruxelles-Capitale",
    "wof:name":"Reinelde Poelman",
    "wof:placetype":"venue"
},
  "geometry": {"coordinates":[4.3723387718,50.8591308594],"type":"Point"}
}