{
  "type": "Feature",
  "properties": {
    "addr:full":"Akkerstraat 59 Hooglede West-Vlaanderen 8830",
    "addr:housenumber":"59",
    "addr:postcode":"8830",
    "addr:street":"Akkerstraat",
    "iso:country":"BE",
    "sg:address":"Akkerstraat 59",
    "sg:city":"Hooglede",
    "sg:classifiers":[
        {
            "category":"Professional",
            "subcategory":"Lawyer & Legal Services",
            "type":"Services"
        }
    ],
    "sg:phone":"+32 51 24 56 62",
    "sg:postcode":"8830",
    "sg:province":"West-Vlaanderen",
    "wof:name":"Vanderhaeghe Inge",
    "wof:placetype":"venue"
},
  "geometry": {"coordinates":[3.0733840466,50.9726257324],"type":"Point"}
}