{
  "type": "Feature",
  "properties": {
    "addr:full":"Hogerheistraat 108 Kapelle-op-den-bos Vlaams-Brabant 1880",
    "addr:housenumber":"108",
    "addr:postcode":"1880",
    "addr:street":"Hogerheistraat",
    "iso:country":"BE",
    "sg:address":"Hogerheistraat 108",
    "sg:city":"Kapelle-op-den-bos",
    "sg:orig_category":"Rundveehouders",
    "sg:phone":"+32 15 71 12 18",
    "sg:postcode":"1880",
    "sg:province":"Vlaams-Brabant",
    "wof:name":"Jozef Verheyen",
    "wof:placetype":"venue"
},
  "geometry": {"coordinates":[4.3468108177,51.0023536682],"type":"Point"}
}