{
  "type": "Feature",
  "properties": {
    "iso:country":"BE",
    "sg:address":"Nieuwe Hazendansweg 2",
    "sg:city":"Zonhoven",
    "sg:orig_category":"Editeurs de journaux. Editeurs de revues and p\u00e9riodiques",
    "sg:phone":"+32 475 61 29 99",
    "sg:postcode":"3520",
    "sg:province":"Limburg",
    "wof:name":"Vitrien Maasland Magazien",
    "wof:placetype":"venue"
},
  "geometry": {"coordinates":[5.3946242332,50.9922485352],"type":"Point"}
}