{
  "type": "Feature",
  "properties": {
    "iso:country":"BE",
    "sg:address":"Luikerstraat 75",
    "sg:city":"Sint-truiden",
    "sg:classifiers":[
        {
            "category":"Shopping",
            "subcategory":"Clothing, Apparel, & Fashions",
            "type":"Retail Goods"
        }
    ],
    "sg:phone":"+32 11 68 21 96",
    "sg:postcode":"3800",
    "sg:province":"Limburg",
    "sg:tags":[
        "boutique"
    ],
    "wof:name":"Da Scoby",
    "wof:placetype":"venue"
},
  "geometry": {"coordinates":[5.1924500465,50.8096504211],"type":"Point"}
}