{
  "type": "Feature",
  "properties": {
    "addr:full":"Acaciadreef 30 Keerbergen Vlaams-Brabant 3140",
    "addr:housenumber":"30",
    "addr:postcode":"3140",
    "addr:street":"Acaciadreef",
    "iso:country":"BE",
    "sg:address":"Acaciadreef 30",
    "sg:city":"Keerbergen",
    "sg:orig_category":"Diverse organisaties and verenigingen",
    "sg:phone":"+32 16 53 10 35",
    "sg:postcode":"3140",
    "sg:province":"Vlaams-Brabant",
    "wof:name":"Chiro Keerbergen",
    "wof:placetype":"venue"
},
  "geometry": {"coordinates":[4.6713871956,50.9977035522],"type":"Point"}
}