{
  "type": "Feature",
  "properties": {
    "iso:country":"BE",
    "sg:address":"Vosstraat 27",
    "sg:city":"Boechout",
    "sg:classifiers":[
        {
            "category":"Building & Trades",
            "subcategory":"Landscaping Services",
            "type":"Services"
        }
    ],
    "sg:phone":"+32 3 454 15 94",
    "sg:postcode":"2530",
    "sg:province":"Antwerpen",
    "sg:tags":[
        "gardening",
        "garden",
        "maintenance"
    ],
    "wof:name":"Tuinman (de)",
    "wof:placetype":"venue"
},
  "geometry": {"coordinates":[4.5118632317,51.1618766785],"type":"Point"}
}