{
  "type": "Feature",
  "properties": {
    "iso:country":"BE",
    "sg:address":"Schorbeekstraat 74",
    "sg:city":"Kortrijk",
    "sg:orig_category":"Pluimveekwekers",
    "sg:phone":"+32 56 41 35 17",
    "sg:postcode":"8511",
    "sg:province":"West-Vlaanderen",
    "wof:name":"E. Delepierre",
    "wof:placetype":"venue"
},
  "geometry": {"coordinates":[3.2294929028,50.7684745789],"type":"Point"}
}