{
  "type": "Feature",
  "properties": {
    "addr:full":"Prins Boudewijnln 22 Adegem Oost-Vlaanderen 9991",
    "addr:housenumber":"22",
    "addr:postcode":"9991",
    "addr:street":"Prins Boudewijnln;Oost-Vlaanderen",
    "iso:country":"BE",
    "sg:address":"Prins Boudewijnln 22",
    "sg:city":"Adegem",
    "sg:classifiers":[
        {
            "category":"Farming",
            "subcategory":"Livestock Farm",
            "type":"Manufacturing & Wholesale Goods"
        }
    ],
    "sg:phone":"+32 50 71 16 27",
    "sg:postcode":"9991",
    "sg:province":"Oost-Vlaanderen",
    "sg:tags":[
        "breeding",
        "agriculture",
        "animal"
    ],
    "wof:name":"Van Landschoot G & Zn Nv",
    "wof:placetype":"venue"
},
  "geometry": {"coordinates":[3.4979889393,51.203502655],"type":"Point"}
}