{
  "type": "Feature",
  "properties": {
    "addr:full":"Beversesteenweg 53 Box 2 Roeselare West-Vlaanderen 8800",
    "addr:housenumber":"53;2",
    "addr:postcode":"8800",
    "addr:street":"Beversesteenweg;Box",
    "iso:country":"BE",
    "sg:address":"Beversesteenweg 53 Box 2",
    "sg:city":"Roeselare",
    "sg:classifiers":[
        {
            "category":"Building & Trades",
            "subcategory":"Cleaning & Sanitation",
            "type":"Services"
        }
    ],
    "sg:phone":"+32 51 25 08 46",
    "sg:postcode":"8800",
    "sg:province":"West-Vlaanderen",
    "sg:tags":[
        "fa\u00e7ade",
        "maintenance"
    ],
    "wof:name":"Marka",
    "wof:placetype":"venue"
},
  "geometry": {"coordinates":[3.1337099075,50.9615402222],"type":"Point"}
}