{
  "type": "Feature",
  "properties": {
    "iso:country":"BE",
    "sg:address":"Rue Constant Wauters 68",
    "sg:city":"Grez-doiceau (nethen)",
    "sg:classifiers":[
        {
            "category":"Building & Trades",
            "subcategory":"Construction",
            "type":"Services"
        }
    ],
    "sg:phone":"+32 10 84 33 94",
    "sg:postcode":"1390",
    "sg:province":"Brabant Wallon",
    "sg:tags":[
        "carpenter"
    ],
    "wof:name":"Mouchenier L",
    "wof:placetype":"venue"
},
  "geometry": {"coordinates":[4.6513090134,50.7760124207],"type":"Point"}
}