{
  "type": "Feature",
  "properties": {
    "addr:full":"Chemin De Beurre 20 Fleurus Hainaut 6223",
    "addr:housenumber":"20",
    "addr:postcode":"6223",
    "addr:street":"Chemin De Beurre",
    "iso:country":"BE",
    "sg:address":"Chemin De Beurre 20",
    "sg:city":"Fleurus",
    "sg:orig_category":"Installation de menuiserie en bois and plastique. Constructions r\u00e9sidentielles sp\u00e9cifiques",
    "sg:phone":"+32 71 81 22 37",
    "sg:postcode":"6223",
    "sg:province":"Hainaut",
    "wof:name":"Luc Duchenne",
    "wof:placetype":"venue"
},
  "geometry": {"coordinates":[4.5306172371,50.5195121765],"type":"Point"}
}