{
  "type": "Feature",
  "properties": {
    "addr:full":"Poperingseweg 119 Ieper West-Vlaanderen 8900",
    "addr:housenumber":"119",
    "addr:postcode":"8900",
    "addr:street":"Poperingseweg",
    "iso:country":"BE",
    "sg:address":"Poperingseweg 119",
    "sg:city":"Ieper",
    "sg:classifiers":[
        {
            "category":"Health Services",
            "subcategory":"Doctor",
            "type":"Services"
        }
    ],
    "sg:phone":"+32 57 20 33 38",
    "sg:postcode":"8900",
    "sg:province":"West-Vlaanderen",
    "sg:tags":[
        "medicinephysicians",
        "surgeon"
    ],
    "wof:name":"De Braekeleer H",
    "wof:placetype":"venue"
},
  "geometry": {"coordinates":[2.8634660244,50.8490715027],"type":"Point"}
}