{
  "type": "Feature",
  "properties": {
    "addr:full":"Itterplein 15 Bree Limburg 3960",
    "addr:housenumber":"15",
    "addr:postcode":"3960",
    "addr:street":"Itterplein",
    "iso:country":"BE",
    "sg:address":"Itterplein 15",
    "sg:city":"Bree",
    "sg:orig_category":"Erotische Etablissementen Ruimtes voor conferenties, recepties and feesten",
    "sg:phone":"+32 89 86 46 52",
    "sg:postcode":"3960",
    "sg:province":"Limburg",
    "wof:name":"Brouwershuis",
    "wof:placetype":"venue"
},
  "geometry": {"coordinates":[5.5944190025,51.1405677795],"type":"Point"}
}