{
  "type": "Feature",
  "properties": {
    "addr:full":"Sint-barbarastraat 22 Tienen (kumtich) Vlaams-Brabant 3300",
    "addr:housenumber":"22",
    "addr:postcode":"3300",
    "addr:street":"Sint-Barbarastraat",
    "iso:country":"BE",
    "sg:address":"Sint-barbarastraat 22",
    "sg:city":"Tienen (kumtich)",
    "sg:classifiers":[
        {
            "category":"Health Services",
            "subcategory":"Health Practitioner",
            "type":"Services"
        }
    ],
    "sg:phone":"+32 16 81 82 12",
    "sg:postcode":"3300",
    "sg:province":"Vlaams-Brabant",
    "sg:tags":[
        "physiotherapist"
    ],
    "wof:name":"Bruyninckx Luc",
    "wof:placetype":"venue"
},
  "geometry": {"coordinates":[4.8834238052,50.819103241],"type":"Point"}
}