{
  "type": "Feature",
  "properties": {
    "iso:country":"BE",
    "sg:address":"Steenweg Op Vilvoorde 114a",
    "sg:city":"Opwijk",
    "sg:classifiers":[
        {
            "category":"Retail",
            "subcategory":"Auto Repair",
            "type":"Services"
        }
    ],
    "sg:phone":"+32 52 35 20 97",
    "sg:postcode":"1745",
    "sg:province":"Vlaams-Brabant",
    "sg:tags":[
        "automobile-body"
    ],
    "wof:name":"Buyl A",
    "wof:placetype":"venue"
},
  "geometry": {"coordinates":[4.1935071945,50.9578552246],"type":"Point"}
}