{
  "type": "Feature",
  "properties": {
    "addr:full":"Rue Du Noyer 322 Bruxelles (schaerbeek) Bruxelles-Capitale 1030",
    "addr:housenumber":"322",
    "addr:postcode":"1030",
    "addr:street":"Rue Du Noyer",
    "iso:country":"BE",
    "sg:address":"Rue Du Noyer 322",
    "sg:city":"Bruxelles (schaerbeek)",
    "sg:classifiers":[
        {
            "category":"Social Services",
            "type":"Services"
        }
    ],
    "sg:phone":"+32 2 732 45 23",
    "sg:postcode":"1030",
    "sg:province":"Bruxelles-Capitale",
    "wof:name":"Espaces Libres Africains Centre Amani Asbl",
    "wof:placetype":"venue"
},
  "geometry": {"coordinates":[4.3957619667,50.844417572],"type":"Point"}
}