{
  "type": "Feature",
  "properties": {
    "addr:full":"Rue De L'eglise 36 Beyne-heusay (bellaire) Li\u00e8ge 4610",
    "addr:housenumber":"36",
    "addr:postcode":"4610",
    "addr:street":"Rue De L'Eglise",
    "iso:country":"BE",
    "sg:address":"Rue De L'eglise 36",
    "sg:city":"Beyne-heusay (bellaire)",
    "sg:classifiers":[
        {
            "category":"Bars & Pubs",
            "type":"Food & Drink"
        }
    ],
    "sg:phone":"+32 4 370 18 95",
    "sg:postcode":"4610",
    "sg:province":"Li\u00e8ge",
    "wof:name":"Taverne Du Billard",
    "wof:placetype":"venue"
},
  "geometry": {"coordinates":[5.6657838821,50.6447792053],"type":"Point"}
}