{
  "type": "Feature",
  "properties": {
    "iso:country":"BE",
    "sg:address":"Leuvensesteenweg 467",
    "sg:city":"Kortenberg",
    "sg:orig_category":"Quincailleries. Rev\u00eatements de sols and murs",
    "sg:phone":"+32 2 759 34 02",
    "sg:postcode":"3070",
    "sg:province":"Vlaams-Brabant",
    "wof:name":"Coenaerts",
    "wof:placetype":"venue"
},
  "geometry": {"coordinates":[4.5452618599,50.8888168335],"type":"Point"}
}