{
  "type": "Feature",
  "properties": {
    "addr:full":"Warandestraat 8 Turnhout Antwerpen 2300",
    "addr:housenumber":"8",
    "addr:postcode":"2300",
    "addr:street":"Warandestraat",
    "iso:country":"BE",
    "sg:address":"Warandestraat 8",
    "sg:city":"Turnhout",
    "sg:orig_category":"RESTAURANTS: LIVRAISON \u00c0 DOMICILE. CATERING AND ORGANISATION DE F\u00caTES",
    "sg:phone":"+32 14 42 34 65",
    "sg:postcode":"2300",
    "sg:province":"Antwerpen",
    "wof:name":"Pain - Matin",
    "wof:placetype":"venue"
},
  "geometry": {"coordinates":[4.9468250275,51.3238220215],"type":"Point"}
}