{
  "type": "Feature",
  "properties": {
    "iso:country":"BE",
    "sg:address":"Rue Jennay 172",
    "sg:city":"Gembloux",
    "sg:orig_category":"Eleveurs de bovins",
    "sg:phone":"+32 81 56 60 66",
    "sg:postcode":"5032",
    "sg:province":"Namur",
    "wof:name":"Debilde Alain Et Luc",
    "wof:placetype":"venue"
},
  "geometry": {"coordinates":[4.7334499359,50.5071907043],"type":"Point"}
}