{
  "type": "Feature",
  "properties": {
    "iso:country":"BE",
    "sg:address":"Begoniastraat 25",
    "sg:city":"Nazareth",
    "sg:classifiers":[
        {
            "category":"Cinema",
            "subcategory":"Movie Rental",
            "type":"Entertainment"
        }
    ],
    "sg:phone":"+32 9 385 50 13",
    "sg:postcode":"9810",
    "sg:province":"Oost-Vlaanderen",
    "sg:tags":[
        "de",
        "cassette",
        "location",
        "vid\u00e9o",
        "audio"
    ],
    "wof:name":"Van Den Bossche",
    "wof:placetype":"venue"
},
  "geometry": {"coordinates":[3.6565868855,50.9770736694],"type":"Point"}
}