{
  "type": "Feature",
  "properties": {
    "iso:country":"BE",
    "sg:address":"Deerlijkseweg 141",
    "sg:city":"Waregem",
    "sg:orig_category":"Charpentes and couvertures",
    "sg:phone":"+32 56 60 02 18",
    "sg:postcode":"8790",
    "sg:province":"West-Vlaanderen",
    "wof:name":"Maes Dakwerken",
    "wof:placetype":"venue"
},
  "geometry": {"coordinates":[3.4079899788,50.869178772],"type":"Point"}
}