{
  "type": "Feature",
  "properties": {
    "iso:country":"BE",
    "sg:address":"Edith Cavelllaan 7",
    "sg:city":"Brecht (sint-job-in-'t Goor)",
    "sg:orig_category":"Non-Classified Establishments",
    "sg:phone":"+32 475 24 86 13",
    "sg:postcode":"2960",
    "sg:province":"Antwerpen",
    "wof:name":"International Dance Promotion",
    "wof:placetype":"venue"
},
  "geometry": {"coordinates":[4.5731868744,51.2938041687],"type":"Point"}
}