{
  "type": "Feature",
  "properties": {
    "addr:full":"Wittenonnenstraat 45 Oostende West-Vlaanderen 8400",
    "addr:housenumber":"45",
    "addr:postcode":"8400",
    "addr:street":"Wittenonnenstraat",
    "iso:country":"BE",
    "sg:address":"Wittenonnenstraat 45",
    "sg:city":"Oostende",
    "sg:classifiers":[
        {
            "category":"Shopping",
            "subcategory":"Baby Store",
            "type":"Retail Goods"
        }
    ],
    "sg:phone":"+32 59 51 36 99",
    "sg:postcode":"8400",
    "sg:province":"West-Vlaanderen",
    "sg:tags":[
        "article",
        "b\u00e9b\u00e9s",
        "pour"
    ],
    "wof:name":"Huis Mariquita",
    "wof:placetype":"venue"
},
  "geometry": {"coordinates":[2.9160749912,51.2304801941],"type":"Point"}
}