{
  "type": "Feature",
  "properties": {
    "iso:country":"BE",
    "sg:address":"Rue D'aix La Chapelle 140",
    "sg:city":"Eupen/eupen",
    "sg:classifiers":[
        {
            "category":"Home & Garden",
            "subcategory":"Hardware",
            "type":"Retail Goods"
        }
    ],
    "sg:phone":"+32 87 74 22 80",
    "sg:postcode":"4701",
    "sg:province":"Li\u00e8ge",
    "sg:tags":[
        "quincailleries",
        "bois",
        "gr"
    ],
    "wof:name":"Pohlen",
    "wof:placetype":"venue"
},
  "geometry": {"coordinates":[6.0404901505,50.6520996094],"type":"Point"}
}