{
  "type": "Feature",
  "properties": {
    "addr:full":"Chauss\u00e9e De Nivelles 346 Namur (temploux) Namur 5020",
    "addr:housenumber":"346",
    "addr:postcode":"5020",
    "addr:street":"Chausse\u0301E De Nivelles",
    "iso:country":"BE",
    "sg:address":"Chauss\u00e9e De Nivelles 346",
    "sg:city":"Namur (temploux)",
    "sg:classifiers":[
        {
            "category":"Manufacturing",
            "subcategory":"Metals",
            "type":"Manufacturing & Wholesale Goods"
        }
    ],
    "sg:phone":"+32 81 56 71 21",
    "sg:postcode":"5020",
    "sg:province":"Namur",
    "sg:tags":[
        "ironwork"
    ],
    "wof:name":"Atelier Bodson Pierre",
    "wof:placetype":"venue"
},
  "geometry": {"coordinates":[4.7952418327,50.4352035522],"type":"Point"}
}