{
  "type": "Feature",
  "properties": {
    "iso:country":"BE",
    "sg:address":"Nijverheidsstraat 7",
    "sg:city":"Peer",
    "sg:classifiers":[
        {
            "category":"Building & Trades",
            "subcategory":"Pest Control",
            "type":"Services"
        }
    ],
    "sg:phone":"+32 11 61 08 08",
    "sg:postcode":"3990",
    "sg:province":"Limburg",
    "sg:tags":[
        "painting",
        "contractor"
    ],
    "wof:name":"Woutim Schildersbedrijf Nv",
    "wof:placetype":"venue"
},
  "geometry": {"coordinates":[5.4474849701,51.1384162903],"type":"Point"}
}