{
  "type": "Feature",
  "properties": {
    "iso:country":"BE",
    "sg:address":"Sint Annalaan 21",
    "sg:city":"Grimbergen (groot)",
    "sg:orig_category":"Boissons",
    "sg:phone":"+32 2 268 00 13",
    "sg:postcode":"1853",
    "sg:province":"Vlaams-Brabant",
    "wof:name":"Maxi Vins",
    "wof:placetype":"venue"
},
  "geometry": {"coordinates":[4.3606891632,50.9028244019],"type":"Point"}
}