{
  "type": "Feature",
  "properties": {
    "addr:full":"Vieux Chemin De Musson 2 Aubange Luxembourg 6792",
    "addr:housenumber":"2",
    "addr:postcode":"6792",
    "addr:street":"Vieux Chemin De Musson",
    "iso:country":"BE",
    "sg:address":"Vieux Chemin De Musson 2",
    "sg:city":"Aubange",
    "sg:orig_category":"Dakwerken",
    "sg:phone":"+32 63 67 53 70",
    "sg:postcode":"6792",
    "sg:province":"Luxembourg",
    "wof:name":"Sud Toitures",
    "wof:placetype":"venue"
},
  "geometry": {"coordinates":[5.7317910194,49.5588722229],"type":"Point"}
}