{
  "type": "Feature",
  "properties": {
    "addr:full":"Industrieter. Leuerbroek 1060 Kinrooi Limburg 3640",
    "addr:postcode":"1060 kinrooi;3640",
    "iso:country":"BE",
    "sg:address":"Industrieter. Leuerbroek 1060",
    "sg:city":"Kinrooi",
    "sg:orig_category":"Industri\u00eble and commerci\u00eble bouw",
    "sg:phone":"+32 89 70 31 21",
    "sg:postcode":"3640",
    "sg:province":"Limburg",
    "wof:name":"Amesco",
    "wof:placetype":"venue"
},
  "geometry": {"coordinates":[5.7498631477,51.136505127],"type":"Point"}
}