{
  "type": "Feature",
  "properties": {
    "iso:country":"BE",
    "sg:address":"Rue D'esneux 28",
    "sg:city":"Sprimont",
    "sg:orig_category":"Enseignement maternel and primaire",
    "sg:phone":"+32 4 368 56 31",
    "sg:postcode":"4140",
    "sg:province":"Li\u00e8ge",
    "wof:name":"Ecole Fond. Communale",
    "wof:placetype":"venue"
},
  "geometry": {"coordinates":[5.6286840439,50.5350418091],"type":"Point"}
}