{
  "type": "Feature",
  "properties": {
    "addr:full":"Stationsstraat 5 Zedelgem West-Vlaanderen 8210",
    "addr:housenumber":"5",
    "addr:postcode":"8210",
    "addr:street":"Stationsstraat",
    "iso:country":"BE",
    "sg:address":"Stationsstraat 5",
    "sg:city":"Zedelgem",
    "sg:orig_category":"Artsen and specialisten",
    "sg:phone":"+32 50 82 37 72",
    "sg:postcode":"8210",
    "sg:province":"West-Vlaanderen",
    "wof:name":"Paul Pieraerts",
    "wof:placetype":"venue"
},
  "geometry": {"coordinates":[3.1484949589,51.1379852295],"type":"Point"}
}