{
  "type": "Feature",
  "properties": {
    "iso:country":"BE",
    "sg:address":"Potegemstraat 17 Box 5",
    "sg:city":"Waregem",
    "sg:classifiers":[
        {
            "category":"Professional",
            "subcategory":"Management & Consulting",
            "type":"Services"
        }
    ],
    "sg:phone":"+32 56 60 07 75",
    "sg:postcode":"8790",
    "sg:province":"West-Vlaanderen",
    "sg:tags":[
        "consultant",
        "law"
    ],
    "wof:name":"Kemseke Dewaele Zakenkantoor",
    "wof:placetype":"venue"
},
  "geometry": {"coordinates":[3.4377110004,50.8818626404],"type":"Point"}
}