{
  "type": "Feature",
  "properties": {
    "addr:full":"Parkstraat 19 Oudenaarde Oost-Vlaanderen 9700",
    "addr:housenumber":"19",
    "addr:postcode":"9700",
    "addr:street":"Parkstraat",
    "iso:country":"BE",
    "sg:address":"Parkstraat 19",
    "sg:city":"Oudenaarde",
    "sg:classifiers":[
        {
            "category":"Professional",
            "subcategory":"Art Services",
            "type":"Services"
        }
    ],
    "sg:phone":"+32 55 30 13 24",
    "sg:postcode":"9700",
    "sg:province":"Oost-Vlaanderen",
    "sg:tags":[
        "photographer"
    ],
    "wof:name":"Friethuisje (het)",
    "wof:placetype":"venue"
},
  "geometry": {"coordinates":[3.6098558903,50.8457946777],"type":"Point"}
}