{
  "type": "Feature",
  "properties": {
    "iso:country":"BE",
    "sg:address":"Dorp 16",
    "sg:city":"Scherpenheuvel-zichem",
    "sg:orig_category":"Textiel",
    "sg:phone":"+32 13 77 52 85",
    "sg:postcode":"3272",
    "sg:province":"Vlaams-Brabant",
    "wof:name":"Marleen Corthout",
    "wof:placetype":"venue"
},
  "geometry": {"coordinates":[4.9535331726,51.0087203979],"type":"Point"}
}