{
  "type": "Feature",
  "properties": {
    "addr:full":"Place Communale 14 Court-saint-etienne Brabant Wallon 1490",
    "addr:housenumber":"14;1490",
    "addr:street":"Place Communale",
    "iso:country":"BE",
    "sg:address":"Place Communale 14",
    "sg:city":"Court-saint-etienne",
    "sg:classifiers":[
        {
            "category":"Home & Garden",
            "subcategory":"Home Furnishings",
            "type":"Retail Goods"
        }
    ],
    "sg:phone":"+32 10 61 80 15",
    "sg:postcode":"1490",
    "sg:province":"Brabant Wallon",
    "sg:tags":[
        "interior",
        "decoration"
    ],
    "wof:name":"Archi Deco",
    "wof:placetype":"venue"
},
  "geometry": {"coordinates":[4.5675587654,50.6433792114],"type":"Point"}
}