{
  "type": "Feature",
  "properties": {
    "addr:full":"Rue De La Carri\u00c8re 76 Herstal Li\u00e8ge 4040",
    "addr:housenumber":"76",
    "addr:postcode":"4040",
    "addr:street":"Rue De La Carrie\u0300Re",
    "iso:country":"BE",
    "sg:address":"Rue De La Carri\u00c8re 76",
    "sg:city":"Herstal",
    "sg:orig_category":"Huisdierenkwekers",
    "sg:phone":"+32 496 55 53 20",
    "sg:postcode":"4040",
    "sg:province":"Li\u00e8ge",
    "wof:name":"Beauceron Bois Limite",
    "wof:placetype":"venue"
},
  "geometry": {"coordinates":[5.6073980331,50.6809234619],"type":"Point"}
}