{
  "type": "Feature",
  "properties": {
    "iso:country":"BE",
    "sg:address":"Grote Weg 23",
    "sg:city":"Menen (lauwe)",
    "sg:classifiers":[
        {
            "category":"Health Services",
            "subcategory":"Nursing And Care Facility",
            "type":"Services"
        }
    ],
    "sg:phone":"+32 56 41 38 98",
    "sg:postcode":"8930",
    "sg:province":"West-Vlaanderen",
    "sg:tags":[
        "home",
        "rest"
    ],
    "wof:name":"San Diego Vzw",
    "wof:placetype":"venue"
},
  "geometry": {"coordinates":[3.1747009754,50.7732315063],"type":"Point"}
}