{
  "type": "Feature",
  "properties": {
    "addr:full":"Essendreef 29 Knokke-heist West-Vlaanderen 8300",
    "addr:housenumber":"29",
    "addr:postcode":"8300",
    "addr:street":"Essendreef",
    "iso:country":"BE",
    "sg:address":"Essendreef 29",
    "sg:city":"Knokke-heist",
    "sg:orig_category":"Instituts de beaut\u00e9",
    "sg:phone":"+32 50 62 39 28",
    "sg:postcode":"8300",
    "sg:province":"West-Vlaanderen",
    "wof:name":"Tip Top Nail's",
    "wof:placetype":"venue"
},
  "geometry": {"coordinates":[3.287694931,51.3467254639],"type":"Point"}
}