{
  "type": "Feature",
  "properties": {
    "iso:country":"BE",
    "sg:address":"Koophandelstraat 10",
    "sg:city":"Lokeren",
    "sg:classifiers":[
        {
            "category":"Professional",
            "subcategory":"Management & Consulting",
            "type":"Services"
        }
    ],
    "sg:phone":"+32 9 348 37 94",
    "sg:postcode":"9160",
    "sg:province":"Oost-Vlaanderen",
    "sg:tags":[
        "-",
        "processing",
        "data",
        "consultant"
    ],
    "wof:name":"Deconinck S",
    "wof:placetype":"venue"
},
  "geometry": {"coordinates":[3.989387989,51.1069602966],"type":"Point"}
}