{
  "type": "Feature",
  "properties": {
    "addr:full":"Rue D'hasti\u00c8re 16 Houyet Namur 5560",
    "addr:housenumber":"16",
    "addr:postcode":"5560",
    "addr:street":"Rue D'Hastie \u0300Re",
    "iso:country":"BE",
    "sg:address":"Rue D'hasti\u00c8re 16",
    "sg:city":"Houyet",
    "sg:orig_category":"Eleveurs de bovins",
    "sg:phone":"+32 82 74 43 09",
    "sg:postcode":"5560",
    "sg:province":"Namur",
    "wof:name":"Jose Ottelet",
    "wof:placetype":"venue"
},
  "geometry": {"coordinates":[4.8830327988,50.1693572998],"type":"Point"}
}