{
  "type": "Feature",
  "properties": {
    "iso:country":"BE",
    "sg:address":"Stationstraat 60-62",
    "sg:city":"Turnhout",
    "sg:classifiers":[
        {
            "category":"Health Services",
            "subcategory":"Nursing And Care Facility",
            "type":"Services"
        }
    ],
    "sg:phone":"+32 14 42 66 02",
    "sg:postcode":"2300",
    "sg:province":"Antwerpen",
    "sg:tags":[
        "home"
    ],
    "wof:name":"Palliatieve Zorgen Kempen Ispahan Vzw",
    "wof:placetype":"venue"
},
  "geometry": {"coordinates":[4.9394879341,51.3239746094],"type":"Point"}
}