{
  "type": "Feature",
  "properties": {
    "iso:country":"BE",
    "sg:address":"Edestraat 30",
    "sg:city":"Haaltert",
    "sg:classifiers":[
        {
            "category":"Home & Garden",
            "subcategory":"Hardware",
            "type":"Retail Goods"
        }
    ],
    "sg:phone":"+32 53 83 13 04",
    "sg:postcode":"9450",
    "sg:province":"Oost-Vlaanderen",
    "sg:tags":[
        "-"
    ],
    "wof:name":"Vakman",
    "wof:placetype":"venue"
},
  "geometry": {"coordinates":[3.9945058823,50.9094734192],"type":"Point"}
}