{
  "type": "Feature",
  "properties": {
    "addr:full":"Emiel Banningstraat 26 Antwerpen Antwerpen 2000",
    "addr:housenumber":"26",
    "addr:postcode":"2000",
    "addr:street":"Emiel Banningstraat",
    "iso:country":"BE",
    "sg:address":"Emiel Banningstraat 26",
    "sg:city":"Antwerpen",
    "sg:classifiers":[
        {
            "category":"Personal",
            "subcategory":"Beauty Salon",
            "type":"Services"
        }
    ],
    "sg:phone":"+32 3 237 65 14",
    "sg:postcode":"2000",
    "sg:province":"Antwerpen",
    "sg:tags":[
        "de",
        "coiffure"
    ],
    "wof:name":"Coiffure Henri",
    "wof:placetype":"venue"
},
  "geometry": {"coordinates":[4.3894782066,51.2059898376],"type":"Point"}
}