{
  "type": "Feature",
  "properties": {
    "iso:country":"BE",
    "sg:address":"Lambermontstraat 18",
    "sg:city":"Antwerpen",
    "sg:classifiers":[
        {
            "category":"Sports & Exercise",
            "subcategory":"Swimming Pool",
            "type":"Entertainment"
        }
    ],
    "sg:phone":"+32 3 237 81 46",
    "sg:postcode":"2000",
    "sg:province":"Antwerpen",
    "sg:tags":[
        "tank",
        "septic"
    ],
    "wof:name":"Bacterior Bvba",
    "wof:placetype":"venue"
},
  "geometry": {"coordinates":[4.3983287811,51.2113227844],"type":"Point"}
}