{
  "type": "Feature",
  "properties": {
    "iso:country":"BE",
    "sg:address":"Gistelse Steenweg 101",
    "sg:city":"Brugge",
    "sg:orig_category":"Beautyfarms, relaxatie and lichamelijk welzijn Schoonheidssalons",
    "sg:phone":"+32 50 38 31 44",
    "sg:postcode":"8200",
    "sg:province":"West-Vlaanderen",
    "wof:name":"Instituut Papilio",
    "wof:placetype":"venue"
},
  "geometry": {"coordinates":[3.2051360607,51.2028083801],"type":"Point"}
}