{
  "type": "Feature",
  "properties": {
    "iso:country":"BE",
    "sg:address":"Plaine De Lorette",
    "sg:city":"Vise",
    "sg:classifiers":[
        {
            "category":"Arena",
            "subcategory":"Sports Club",
            "type":"Entertainment"
        }
    ],
    "sg:phone":"+32 2 387 59 16",
    "sg:postcode":"4600",
    "sg:province":"Li\u00e8ge",
    "sg:tags":[
        "de"
    ],
    "wof:name":"Standard Clas Vis\u00c9",
    "wof:placetype":"venue"
},
  "geometry": {"coordinates":[5.697824955,50.7315101624],"type":"Point"}
}