{
  "type": "Feature",
  "properties": {
    "iso:country":"BE",
    "sg:address":"Avenue L\u00e9opold Wiener 98",
    "sg:city":"Bruxelles (watermael-boitsfort)",
    "sg:classifiers":[
        {
            "category":"Health Services",
            "subcategory":"Health Practitioner",
            "type":"Services"
        }
    ],
    "sg:phone":"+32 2 673 28 90",
    "sg:postcode":"1170",
    "sg:province":"Bruxelles-Capitale",
    "sg:tags":[
        "osteopath"
    ],
    "wof:name":"Surny D (d.o.)",
    "wof:placetype":"venue"
},
  "geometry": {"coordinates":[4.4115028381,50.8037757874],"type":"Point"}
}