{
  "type": "Feature",
  "properties": {
    "addr:full":"Rue Fays 87 Saint-nicolas Li\u00e8ge 4420",
    "addr:housenumber":"87",
    "addr:postcode":"4420",
    "addr:street":"Rue Fays",
    "iso:country":"BE",
    "sg:address":"Rue Fays 87",
    "sg:city":"Saint-nicolas",
    "sg:orig_category":"Elektrische installaties voor woningen",
    "sg:phone":"+32 4 247 14 48",
    "sg:postcode":"4420",
    "sg:province":"Li\u00e8ge",
    "wof:name":"Iovino Carlo",
    "wof:placetype":"venue"
},
  "geometry": {"coordinates":[5.520072937,50.6353530884],"type":"Point"}
}