{
  "type": "Feature",
  "properties": {
    "iso:country":"BE",
    "sg:address":"Rue Paradis 27",
    "sg:city":"Vise",
    "sg:classifiers":[
        {
            "category":"Fast Food",
            "type":"Food & Drink"
        }
    ],
    "sg:phone":"+32 4 379 08 11",
    "sg:postcode":"4600",
    "sg:province":"Li\u00e8ge",
    "sg:tags":[
        "\u00c0",
        "emporter",
        "restaurants"
    ],
    "wof:name":"Friterie De Labatoire",
    "wof:placetype":"venue"
},
  "geometry": {"coordinates":[5.6952648163,50.7378158569],"type":"Point"}
}