{
  "type": "Feature",
  "properties": {
    "addr:full":"Nieuwstraat 115 Keerbergen Vlaams-Brabant 3140",
    "addr:housenumber":"115",
    "addr:postcode":"3140",
    "addr:street":"Nieuwstraat",
    "iso:country":"BE",
    "sg:address":"Nieuwstraat 115",
    "sg:city":"Keerbergen",
    "sg:orig_category":"Sportclubs",
    "sg:phone":"+32 15 73 07 95",
    "sg:postcode":"3140",
    "sg:province":"Vlaams-Brabant",
    "wof:name":"Wc Pater Damiaanvrienden",
    "wof:placetype":"venue"
},
  "geometry": {"coordinates":[4.6869850159,51.0027313232],"type":"Point"}
}