{
  "type": "Feature",
  "properties": {
    "addr:full":"Avenue Reine Astrid 11 Rixensart Brabant Wallon 1330",
    "addr:housenumber":"11",
    "addr:postcode":"1330",
    "addr:street":"Avenue Reine Astrid;Wallon",
    "iso:country":"BE",
    "sg:address":"Avenue Reine Astrid 11",
    "sg:city":"Rixensart",
    "sg:orig_category":"Advocaten and juridische adviseurs",
    "sg:phone":"+32 2 654 04 51",
    "sg:postcode":"1330",
    "sg:province":"Brabant Wallon",
    "wof:name":"C. Coomans",
    "wof:placetype":"venue"
},
  "geometry": {"coordinates":[4.5316500664,50.7110176086],"type":"Point"}
}