{
  "type": "Feature",
  "properties": {
    "addr:full":"Haringrodestraat 39 Antwerpen Antwerpen 2018",
    "addr:housenumber":"39",
    "addr:postcode":"2018",
    "addr:street":"Haringrodestraat",
    "iso:country":"BE",
    "sg:address":"Haringrodestraat 39",
    "sg:city":"Antwerpen",
    "sg:classifiers":[
        {
            "category":"Professional",
            "subcategory":"Lawyer & Legal Services",
            "type":"Services"
        }
    ],
    "sg:phone":"+32 3 239 20 16",
    "sg:postcode":"2018",
    "sg:province":"Antwerpen",
    "wof:name":"Le Page Reinhilde",
    "wof:placetype":"venue"
},
  "geometry": {"coordinates":[4.4154009819,51.2023544312],"type":"Point"}
}