{
  "type": "Feature",
  "properties": {
    "addr:full":"Rue Des Rives 24 Bi\u00e8vre Namur 5555",
    "addr:housenumber":"24",
    "addr:postcode":"5555",
    "addr:street":"Rue Des Rives",
    "iso:country":"BE",
    "sg:address":"Rue Des Rives 24",
    "sg:city":"Bi\u00e8vre",
    "sg:classifiers":[
        {
            "category":"Building & Trades",
            "subcategory":"Landscaping Services",
            "type":"Services"
        }
    ],
    "sg:phone":"+32 61 51 16 56",
    "sg:postcode":"5555",
    "sg:province":"Namur",
    "sg:tags":[
        "forestry"
    ],
    "wof:name":"Thomas J P",
    "wof:placetype":"venue"
},
  "geometry": {"coordinates":[5.0261387825,49.9468803406],"type":"Point"}
}