{
  "type": "Feature",
  "properties": {
    "addr:full":"Lodewijk De Raetstraat 49 Lommel Limburg 3920",
    "addr:housenumber":"49",
    "addr:postcode":"3920",
    "addr:street":"Lodewijk De Raetstraat",
    "iso:country":"BE",
    "sg:address":"Lodewijk De Raetstraat 49",
    "sg:city":"Lommel",
    "sg:orig_category":"R\u00e9cup\u00e9ration de mati\u00e8res m\u00e9talliques recyclables and d\u00e9molisseurs de voitures. Pi\u00e8ces and accessoire",
    "sg:phone":"+32 11 55 44 45",
    "sg:postcode":"3920",
    "sg:province":"Limburg",
    "wof:name":"V.p.j.",
    "wof:placetype":"venue"
},
  "geometry": {"coordinates":[5.2819461823,51.2208786011],"type":"Point"}
}