{
  "type": "Feature",
  "properties": {
    "iso:country":"BE",
    "sg:address":"Place De La Gare 42",
    "sg:city":"Mouscron",
    "sg:orig_category":"Non-Classified Establishments",
    "sg:phone":"+32 56 33 04 56",
    "sg:postcode":"7700",
    "sg:province":"Hainaut",
    "wof:name":"Dewitte Tissage Main",
    "wof:placetype":"venue"
},
  "geometry": {"coordinates":[3.2261219025,50.7396354675],"type":"Point"}
}