{
  "type": "Feature",
  "properties": {
    "addr:full":"Rue De La Lib\u00c9ration 16 Braine-le-chateau Brabant Wallon 1440",
    "addr:housenumber":"16",
    "addr:postcode":"1440",
    "addr:street":"Rue De La Libe\u0301Ration;Brabant Wallon",
    "iso:country":"BE",
    "sg:address":"Rue De La Lib\u00c9ration 16",
    "sg:city":"Braine-le-chateau",
    "sg:orig_category":"Opticiens",
    "sg:phone":"+32 2 366 16 58",
    "sg:postcode":"1440",
    "sg:province":"Brabant Wallon",
    "wof:name":"Bernard Quairiaux",
    "wof:placetype":"venue"
},
  "geometry": {"coordinates":[4.2689619064,50.682258606],"type":"Point"}
}