{
  "type": "Feature",
  "properties": {
    "iso:country":"BE",
    "sg:address":"Kuildamstraat 69",
    "sg:city":"Sint-niklaas",
    "sg:classifiers":[
        {
            "category":"Insurance",
            "subcategory":"Life Insurance",
            "type":"Services"
        }
    ],
    "sg:phone":"+32 3 777 48 77",
    "sg:postcode":"9100",
    "sg:province":"Oost-Vlaanderen",
    "sg:tags":[
        "assurance"
    ],
    "wof:name":"Bureau Peiffer",
    "wof:placetype":"venue"
},
  "geometry": {"coordinates":[4.1296110153,51.1798477173],"type":"Point"}
}