{
  "type": "Feature",
  "properties": {
    "iso:country":"BE",
    "sg:address":"M. De Layensplein 3",
    "sg:city":"Leuven",
    "sg:classifiers":[
        {
            "category":"Restaurant",
            "type":"Food & Drink"
        }
    ],
    "sg:phone":"+32 16 22 76 29",
    "sg:postcode":"3000",
    "sg:province":"Vlaams-Brabant",
    "wof:name":"Las Lanzas",
    "wof:placetype":"venue"
},
  "geometry": {"coordinates":[4.7006559372,50.8799362183],"type":"Point"}
}