{
  "type": "Feature",
  "properties": {
    "addr:full":"Zwaluwenstraat 125 Oostende West-Vlaanderen 8400",
    "addr:housenumber":"125",
    "addr:postcode":"8400",
    "addr:street":"Zwaluwenstraat",
    "iso:country":"BE",
    "sg:address":"Zwaluwenstraat 125",
    "sg:city":"Oostende",
    "sg:classifiers":[
        {
            "category":"Arena",
            "subcategory":"Sports Club",
            "type":"Entertainment"
        }
    ],
    "sg:phone":"+32 59 43 31 34",
    "sg:postcode":"8400",
    "sg:province":"West-Vlaanderen",
    "wof:name":"Kung Fu Vlawak",
    "wof:placetype":"venue"
},
  "geometry": {"coordinates":[2.912831068,51.217464447],"type":"Point"}
}