{
  "type": "Feature",
  "properties": {
    "iso:country":"BE",
    "sg:address":"Rue De L'auberge 18",
    "sg:city":"Matagne-la-petite",
    "sg:classifiers":[
        {
            "category":"Retail",
            "subcategory":"Repair Shop",
            "type":"Services"
        }
    ],
    "sg:phone":"+32 60 39 92 93",
    "sg:postcode":"5680",
    "sg:province":"Namur",
    "sg:tags":[
        "agricultural",
        "machinery"
    ],
    "wof:name":"Garage Charlier S.p.r.l.",
    "wof:placetype":"venue"
},
  "geometry": {"coordinates":[4.6476840973,50.1167182922],"type":"Point"}
}