{
  "type": "Feature",
  "properties": {
    "iso:country":"BE",
    "sg:address":"Clamarastraat 1",
    "sg:city":"Lo-reninge (pollinkhove)",
    "sg:orig_category":"Non-Classified Establishments",
    "sg:phone":"+32 58 28 81 55",
    "sg:postcode":"8647",
    "sg:province":"West-Vlaanderen",
    "wof:name":"Butaye L",
    "wof:placetype":"venue"
},
  "geometry": {"coordinates":[2.7101259232,50.9867668152],"type":"Point"}
}