{
  "type": "Feature",
  "properties": {
    "addr:full":"Zoning Industriel De Wandre Li\u00e8ge 1 (wandre) Li\u00e8ge 4020",
    "addr:housenumber":"1",
    "addr:postcode":"4020",
    "addr:street":"Zoning Industriel De Wandre Lie\u0300Ge",
    "iso:country":"BE",
    "sg:address":"Zoning Industriel De Wandre",
    "sg:city":"Li\u00e8ge 1 (wandre)",
    "sg:classifiers":[
        {
            "category":"Manufacturing",
            "subcategory":"Metals",
            "type":"Manufacturing & Wholesale Goods"
        }
    ],
    "sg:phone":"+32 4 362 21 11",
    "sg:postcode":"4020",
    "sg:province":"Li\u00e8ge",
    "sg:tags":[
        "non-ferrous",
        "-"
    ],
    "wof:name":"Vandevinne",
    "wof:placetype":"venue"
},
  "geometry": {"coordinates":[5.5356478691,50.6645088196],"type":"Point"}
}