{
  "type": "Feature",
  "properties": {
    "iso:country":"BE",
    "sg:address":"Willem Telllaan 13",
    "sg:city":"Diksmuide",
    "sg:orig_category":"Rundveehouders",
    "sg:phone":"+32 51 51 06 22",
    "sg:postcode":"8600",
    "sg:province":"West-Vlaanderen",
    "wof:name":"Maurice Verstraete",
    "wof:placetype":"venue"
},
  "geometry": {"coordinates":[2.859926939,51.0312385559],"type":"Point"}
}