{
  "type": "Feature",
  "properties": {
    "addr:full":"Dr Haubenlaan 1 Maasmechelen Limburg 3630",
    "addr:housenumber":"1",
    "addr:postcode":"3630",
    "addr:street":"Dr Haubenlaan",
    "iso:country":"BE",
    "sg:address":"Dr Haubenlaan 1",
    "sg:city":"Maasmechelen",
    "sg:classifiers":[
        {
            "category":"Banks & Credit Unions",
            "subcategory":"Bank",
            "type":"Services"
        }
    ],
    "sg:phone":"+32 11 76 19 60",
    "sg:postcode":"3630",
    "sg:province":"Limburg",
    "wof:name":"Aslk-cger Bank",
    "wof:placetype":"venue"
},
  "geometry": {"coordinates":[5.6959562302,50.9640808105],"type":"Point"}
}