{
  "type": "Feature",
  "properties": {
    "iso:country":"BE",
    "sg:address":"Koenraadstraat 2",
    "sg:city":"Heuvelland",
    "sg:orig_category":"Rundveehouders Varkenskwekers",
    "sg:phone":"+32 57 44 47 27",
    "sg:postcode":"8958",
    "sg:province":"West-Vlaanderen",
    "wof:name":"Eric Vandoolaeghe",
    "wof:placetype":"venue"
},
  "geometry": {"coordinates":[2.7906548977,50.7758712769],"type":"Point"}
}