{
  "type": "Feature",
  "properties": {
    "iso:country":"BE",
    "sg:address":"Brugstraat 18",
    "sg:city":"Landen",
    "sg:orig_category":"Kapsalons",
    "sg:phone":"+32 11 88 44 24",
    "sg:postcode":"3400",
    "sg:province":"Vlaams-Brabant",
    "wof:name":"Coiffure Filip",
    "wof:placetype":"venue"
},
  "geometry": {"coordinates":[5.0817050934,50.7475280762],"type":"Point"}
}