{
  "type": "Feature",
  "properties": {
    "addr:full":"Rue De La Station 44 Anderlues Hainaut 6150",
    "addr:housenumber":"44",
    "addr:postcode":"6150",
    "addr:street":"Rue De La Station",
    "iso:country":"BE",
    "sg:address":"Rue De La Station 44",
    "sg:city":"Anderlues",
    "sg:classifiers":[
        {
            "category":"Shopping",
            "subcategory":"Optician",
            "type":"Retail Goods"
        }
    ],
    "sg:phone":"+32 71 52 74 70",
    "sg:postcode":"6150",
    "sg:province":"Hainaut",
    "sg:tags":[
        "-"
    ],
    "wof:name":"Lacomblez E",
    "wof:placetype":"venue"
},
  "geometry": {"coordinates":[4.2823991776,50.399974823],"type":"Point"}
}