{
  "type": "Feature",
  "properties": {
    "iso:country":"BE",
    "sg:address":"Rue Du Lombard 10",
    "sg:city":"Namur",
    "sg:classifiers":[
        {
            "category":"Social Services",
            "type":"Services"
        }
    ],
    "sg:phone":"+32 81 22 51 49",
    "sg:postcode":"5000",
    "sg:province":"Namur",
    "wof:name":"Consul Nourrissons",
    "wof:placetype":"venue"
},
  "geometry": {"coordinates":[4.8698730469,50.4636993408],"type":"Point"}
}