{
  "type": "Feature",
  "properties": {
    "iso:country":"BE",
    "sg:address":"Rue Du Peuple 80",
    "sg:city":"Frameries (eugies)",
    "sg:classifiers":[
        {
            "category":"Health Services",
            "subcategory":"Health Practitioner",
            "type":"Services"
        }
    ],
    "sg:phone":"+32 65 67 42 64",
    "sg:postcode":"7080",
    "sg:province":"Hainaut",
    "sg:tags":[
        "physiotherapist"
    ],
    "wof:name":"Libert Ch",
    "wof:placetype":"venue"
},
  "geometry": {"coordinates":[3.9013249874,50.4052352905],"type":"Point"}
}