{
  "type": "Feature",
  "properties": {
    "addr:full":"Hoogstraat 236 As Limburg 3668",
    "addr:housenumber":"236",
    "addr:postcode":"3668",
    "addr:street":"Hoogstraat",
    "iso:country":"BE",
    "sg:address":"Hoogstraat 236",
    "sg:city":"As",
    "sg:orig_category":"D\u00e9corateurs d'int\u00e9rieur",
    "sg:phone":"+32 89 65 89 74",
    "sg:postcode":"3668",
    "sg:province":"Limburg",
    "wof:name":"Lutgarde Moors",
    "wof:placetype":"venue"
},
  "geometry": {"coordinates":[5.61024189,51.0233230591],"type":"Point"}
}