{
  "type": "Feature",
  "properties": {
    "iso:country":"BE",
    "sg:address":"Tervurenlaan 177",
    "sg:city":"Sint-pieters-woluwe/woluwe-saint-pierre",
    "sg:orig_category":"Ruimtes voor conferenties, recepties and feesten",
    "sg:phone":"+32 2 734 63 50",
    "sg:postcode":"1150",
    "sg:province":"Bruxelles-Capitale",
    "wof:name":"Cercle Montgomery",
    "wof:placetype":"venue"
},
  "geometry": {"coordinates":[4.4078001976,50.8363876343],"type":"Point"}
}