{
  "type": "Feature",
  "properties": {
    "addr:full":"Hageland 11 De Pinte Oost-Vlaanderen 9840",
    "addr:housenumber":"11",
    "addr:postcode":"9840",
    "addr:street":"Hageland",
    "iso:country":"BE",
    "sg:address":"Hageland 11",
    "sg:city":"De Pinte",
    "sg:orig_category":"Services pour animaux domestiques",
    "sg:phone":"+32 9 281 25 35",
    "sg:postcode":"9840",
    "sg:province":"Oost-Vlaanderen",
    "wof:name":"'t Haegeland",
    "wof:placetype":"venue"
},
  "geometry": {"coordinates":[3.6566979885,50.9814491272],"type":"Point"}
}