{
  "type": "Feature",
  "properties": {
    "iso:country":"BE",
    "sg:address":"Rue Jacques Vallings 5",
    "sg:city":"Evere/evere",
    "sg:orig_category":"Plomberie, chauffage and installations sanitaires",
    "sg:phone":"+32 2 245 69 79",
    "sg:postcode":"1140",
    "sg:province":"Bruxelles-Capitale",
    "wof:name":"Le Beaume Du Sanitaire",
    "wof:placetype":"venue"
},
  "geometry": {"coordinates":[4.3978872299,50.8740272522],"type":"Point"}
}