{
  "type": "Feature",
  "properties": {
    "addr:full":"Chauss\u00c9e De Mons 293 Ath Hainaut 7800",
    "addr:housenumber":"293",
    "addr:postcode":"7800",
    "addr:street":"Chausse\u0301E De Mons",
    "iso:country":"BE",
    "sg:address":"Chauss\u00c9e De Mons 293",
    "sg:city":"Ath",
    "sg:orig_category":"Jeux de hasard",
    "sg:phone":"+32 68 84 09 11",
    "sg:postcode":"7800",
    "sg:province":"Hainaut",
    "wof:name":"Tierc\u00c9 Vincennes",
    "wof:placetype":"venue"
},
  "geometry": {"coordinates":[3.7846109867,50.6191749573],"type":"Point"}
}