{
  "type": "Feature",
  "properties": {
    "iso:country":"BE",
    "sg:address":"Rue De La Vall\u00c9e 7",
    "sg:city":"Bassenge",
    "sg:orig_category":"Dierenartsen",
    "sg:phone":"+32 4 286 36 58",
    "sg:postcode":"4690",
    "sg:province":"Li\u00e8ge",
    "wof:name":"Pascale Cnudde",
    "wof:placetype":"venue"
},
  "geometry": {"coordinates":[5.667069912,50.7956008911],"type":"Point"}
}