{
  "type": "Feature",
  "properties": {
    "addr:full":"Place De La Licourt 12 Herstal Li\u00e8ge 4040",
    "addr:housenumber":"12",
    "addr:postcode":"4040",
    "addr:street":"Place De La Licourt",
    "iso:country":"BE",
    "sg:address":"Place De La Licourt 12",
    "sg:city":"Herstal",
    "sg:classifiers":[
        {
            "category":"Building & Trades",
            "subcategory":"Landscaping Services",
            "type":"Services"
        }
    ],
    "sg:phone":"+32 4 264 89 06",
    "sg:postcode":"4040",
    "sg:province":"Li\u00e8ge",
    "sg:tags":[
        "access",
        "pond",
        "laying-out",
        "-"
    ],
    "wof:name":"Aqua Shop",
    "wof:placetype":"venue"
},
  "geometry": {"coordinates":[5.6391348839,50.6699905396],"type":"Point"}
}