{
  "type": "Feature",
  "properties": {
    "addr:full":"Mechelsesteenweg 83 Dendermonde Oost-Vlaanderen 9200",
    "addr:housenumber":"83",
    "addr:postcode":"9200",
    "addr:street":"Mechelsesteenweg;Oost-Vlaanderen",
    "iso:country":"BE",
    "sg:address":"Mechelsesteenweg 83",
    "sg:city":"Dendermonde",
    "sg:orig_category":"Stations-service and carburants. Entretien and r\u00e9parations de voitures. V\u00e9hicules automobiles",
    "sg:phone":"+32 52 21 11 50",
    "sg:postcode":"9200",
    "sg:province":"Oost-Vlaanderen",
    "wof:name":"Fa. Caudron",
    "wof:placetype":"venue"
},
  "geometry": {"coordinates":[4.1165189743,51.0356521606],"type":"Point"}
}