{
  "type": "Feature",
  "properties": {
    "addr:full":"Rue St-agathe 49a Vresse-sur-semois Namur 5550",
    "addr:housenumber":"49a",
    "addr:postcode":"5550",
    "addr:street":"Rue St-Agathe",
    "iso:country":"BE",
    "sg:address":"Rue St-agathe 49a",
    "sg:city":"Vresse-sur-semois",
    "sg:orig_category":"Salles de spectacles",
    "sg:phone":"+32 61 27 11 70",
    "sg:postcode":"5550",
    "sg:province":"Namur",
    "wof:name":"Th\u00c9\u00c2tre Noisette",
    "wof:placetype":"venue"
},
  "geometry": {"coordinates":[4.9285697937,49.86170578],"type":"Point"}
}