{
  "type": "Feature",
  "properties": {
    "addr:full":"Petrusberg 35 Leuven (heverlee) Vlaams-Brabant 3001",
    "addr:housenumber":"35",
    "addr:postcode":"3001",
    "addr:street":"Petrusberg",
    "iso:country":"BE",
    "sg:address":"Petrusberg 35",
    "sg:city":"Leuven (heverlee)",
    "sg:classifiers":[
        {
            "category":"Professional",
            "subcategory":"Art Services",
            "type":"Services"
        }
    ],
    "sg:phone":"+32 16 40 80 83",
    "sg:postcode":"3001",
    "sg:province":"Vlaams-Brabant",
    "sg:tags":[
        "realization",
        "audio-visual"
    ],
    "wof:name":"Farce Cancan",
    "wof:placetype":"venue"
},
  "geometry": {"coordinates":[4.7175068855,50.8593254089],"type":"Point"}
}