{
  "type": "Feature",
  "properties": {
    "addr:full":"Maastrichterstraat 68 Hasselt Limburg 3500",
    "addr:housenumber":"68",
    "addr:postcode":"3500",
    "addr:street":"Maastrichterstraat",
    "iso:country":"BE",
    "sg:address":"Maastrichterstraat 68",
    "sg:city":"Hasselt",
    "sg:orig_category":"Salles de spectacles",
    "sg:phone":"+32 11 23 41 33",
    "sg:postcode":"3500",
    "sg:province":"Limburg",
    "wof:name":"E. Smellenbergh",
    "wof:placetype":"venue"
},
  "geometry": {"coordinates":[5.3403449059,50.9297294617],"type":"Point"}
}