{
  "type": "Feature",
  "properties": {
    "addr:full":"Vanderstichelenstraat 48 Sint-jans-molenbeek/molenbeek-saint-jean Bruxelles-Capitale 1080",
    "addr:housenumber":"48",
    "addr:postcode":"1080",
    "addr:street":"Vanderstichelenstraat",
    "iso:country":"BE",
    "sg:address":"Vanderstichelenstraat 48",
    "sg:city":"Sint-jans-molenbeek/molenbeek-saint-jean",
    "sg:orig_category":"Persagentschappen",
    "sg:phone":"+32 475 28 71 02",
    "sg:postcode":"1080",
    "sg:province":"Bruxelles-Capitale",
    "wof:name":"Abdelmajid Hakem",
    "wof:placetype":"venue"
},
  "geometry": {"coordinates":[4.3410730362,50.8625068665],"type":"Point"}
}