{
  "type": "Feature",
  "properties": {
    "iso:country":"BE",
    "sg:address":"Ambachtenlaan 21b12",
    "sg:city":"Leuven",
    "sg:orig_category":"Marketingbureaus Marktonderzoekbureaus",
    "sg:phone":"+32 16 74 24 24",
    "sg:postcode":"3001",
    "sg:province":"Vlaams-Brabant",
    "wof:name":"Significant Marketing Research",
    "wof:placetype":"venue"
},
  "geometry": {"coordinates":[4.7154507637,50.846622467],"type":"Point"}
}