{
  "type": "Feature",
  "properties": {
    "addr:full":"Quai De La Maladrerie 8 Bouillon Luxembourg 6830",
    "addr:housenumber":"8",
    "addr:postcode":"6830",
    "addr:street":"Quai De La Maladrerie",
    "iso:country":"BE",
    "sg:address":"Quai De La Maladrerie 8",
    "sg:city":"Bouillon",
    "sg:classifiers":[
        {
            "category":"Travel",
            "subcategory":"Hotels & Motels",
            "type":"Entertainment"
        }
    ],
    "sg:phone":"+32 61 46 78 48",
    "sg:postcode":"6830",
    "sg:province":"Luxembourg",
    "sg:tags":[
        "restaurant"
    ],
    "wof:name":"Le Castel",
    "wof:placetype":"venue"
},
  "geometry": {"coordinates":[5.0709137917,49.7949256897],"type":"Point"}
}