{
  "type": "Feature",
  "properties": {
    "addr:full":"Rue Albert I. 382 Erquelinnes Hainaut 6560",
    "addr:housenumber":"382",
    "addr:postcode":"6560",
    "addr:street":"Rue Albert I.",
    "iso:country":"BE",
    "sg:address":"Rue Albert I. 382",
    "sg:city":"Erquelinnes",
    "sg:classifiers":[
        {
            "category":"Banks & Credit Unions",
            "subcategory":"Bank",
            "type":"Services"
        }
    ],
    "sg:phone":"+32 81 55 54 70",
    "sg:postcode":"6560",
    "sg:province":"Hainaut",
    "wof:name":"Banque Bruxelles Lambert Sa",
    "wof:placetype":"venue"
},
  "geometry": {"coordinates":[4.1207499504,50.3097915649],"type":"Point"}
}