{
  "type": "Feature",
  "properties": {
    "addr:full":"Chemin Vert 68 Ham-sur-heure-nalinnes (nalinnes) Hainaut 6120",
    "addr:housenumber":"68",
    "addr:postcode":"6120",
    "addr:street":"Chemin Vert",
    "iso:country":"BE",
    "sg:address":"Chemin Vert 68",
    "sg:city":"Ham-sur-heure-nalinnes (nalinnes)",
    "sg:classifiers":[
        {
            "category":"Health Services",
            "subcategory":"Doctor",
            "type":"Services"
        }
    ],
    "sg:phone":"+32 71 21 69 40",
    "sg:postcode":"6120",
    "sg:province":"Hainaut",
    "sg:tags":[
        "medicinephysicians",
        "surgeon"
    ],
    "wof:name":"Allard J P",
    "wof:placetype":"venue"
},
  "geometry": {"coordinates":[4.4360628128,50.3449516296],"type":"Point"}
}