{
  "type": "Feature",
  "properties": {
    "addr:full":"Iepersestraat 381 Roeselare West-Vlaanderen 8800",
    "addr:housenumber":"381",
    "addr:postcode":"8800",
    "addr:street":"Iepersestraat",
    "iso:country":"BE",
    "sg:address":"Iepersestraat 381",
    "sg:city":"Roeselare",
    "sg:classifiers":[
        {
            "category":"Professional",
            "subcategory":"Testing Lab",
            "type":"Services"
        }
    ],
    "sg:phone":"+32 51 20 71 11",
    "sg:postcode":"8800",
    "sg:province":"West-Vlaanderen",
    "sg:tags":[
        "chemist"
    ],
    "wof:name":"Van Wesel G",
    "wof:placetype":"venue"
},
  "geometry": {"coordinates":[3.1064889431,50.9358406067],"type":"Point"}
}