{
  "type": "Feature",
  "properties": {
    "iso:country":"BE",
    "sg:address":"Vierwinden 6",
    "sg:city":"Zaventem",
    "sg:classifiers":[
        {
            "category":"Building & Trades",
            "subcategory":"Plumbing",
            "type":"Services"
        }
    ],
    "sg:phone":"+32 2 715 24 44",
    "sg:postcode":"1930",
    "sg:province":"Vlaams-Brabant",
    "sg:tags":[
        "diver",
        "commerce",
        "gr",
        "pour",
        "equipement"
    ],
    "wof:name":"Molimex Refrigeration",
    "wof:placetype":"venue"
},
  "geometry": {"coordinates":[4.48919487,50.8712501526],"type":"Point"}
}