{
  "type": "Feature",
  "properties": {
    "addr:full":"Rue Des Sorbiers 14 Namur (erpent) Namur 5101",
    "addr:housenumber":"14",
    "addr:postcode":"5101",
    "addr:street":"Rue Des Sorbiers",
    "iso:country":"BE",
    "sg:address":"Rue Des Sorbiers 14",
    "sg:city":"Namur (erpent)",
    "sg:classifiers":[
        {
            "category":"Health Services",
            "subcategory":"Health Practitioner",
            "type":"Services"
        }
    ],
    "sg:phone":"+32 81 30 33 86",
    "sg:postcode":"5101",
    "sg:province":"Namur",
    "sg:tags":[
        "physiotherapist"
    ],
    "wof:name":"Laruelle J P",
    "wof:placetype":"venue"
},
  "geometry": {"coordinates":[4.9032950401,50.4562683105],"type":"Point"}
}