{
  "type": "Feature",
  "properties": {
    "iso:country":"BE",
    "sg:address":"Chauss\u00e9e De Charleroi 211",
    "sg:city":"Fleurus",
    "sg:classifiers":[
        {
            "category":"Home & Garden",
            "subcategory":"Household Appliances",
            "type":"Retail Goods"
        }
    ],
    "sg:phone":"+32 71 81 56 53",
    "sg:postcode":"6220",
    "sg:province":"Hainaut",
    "sg:tags":[
        "repair",
        "mainten",
        "-",
        "electric"
    ],
    "wof:name":"Steenweghen",
    "wof:placetype":"venue"
},
  "geometry": {"coordinates":[4.5507559776,50.4820747375],"type":"Point"}
}