{
  "type": "Feature",
  "properties": {
    "addr:full":"Bredestraat 191 Gent (oostakker) Oost-Vlaanderen 9041",
    "addr:housenumber":"191",
    "addr:postcode":"9041",
    "addr:street":"Bredestraat",
    "iso:country":"BE",
    "sg:address":"Bredestraat 191",
    "sg:city":"Gent (oostakker)",
    "sg:classifiers":[
        {
            "category":"Wholesale",
            "subcategory":"Plants",
            "type":"Manufacturing & Wholesale Goods"
        }
    ],
    "sg:phone":"+32 9 251 26 54",
    "sg:postcode":"9041",
    "sg:province":"Oost-Vlaanderen",
    "sg:tags":[
        "whol",
        "flower",
        "-",
        "grower"
    ],
    "wof:name":"De Wulf Roland Bvba",
    "wof:placetype":"venue"
},
  "geometry": {"coordinates":[3.7783870697,51.1061973572],"type":"Point"}
}