{
  "type": "Feature",
  "properties": {
    "iso:country":"BE",
    "sg:address":"Leeuwerikenstraat 48",
    "sg:city":"Leuven (heverlee)",
    "sg:classifiers":[
        {
            "category":"Personal",
            "subcategory":"Beauty Salon",
            "type":"Services"
        }
    ],
    "sg:phone":"+32 16 38 95 53",
    "sg:postcode":"3001",
    "sg:province":"Vlaams-Brabant",
    "wof:name":"Esthetiek Oona",
    "wof:placetype":"venue"
},
  "geometry": {"coordinates":[4.7000570297,50.8607254028],"type":"Point"}
}