{
  "type": "Feature",
  "properties": {
    "iso:country":"BE",
    "sg:address":"Torhoutsestraat 215",
    "sg:city":"Oostkamp",
    "sg:classifiers":[
        {
            "category":"Fast Food",
            "type":"Food & Drink"
        }
    ],
    "sg:phone":"+32 50 28 17 64",
    "sg:postcode":"8020",
    "sg:province":"West-Vlaanderen",
    "sg:tags":[
        "\u00c0",
        "emporter",
        "restaurants"
    ],
    "wof:name":"Frituur De Posterij",
    "wof:placetype":"venue"
},
  "geometry": {"coordinates":[3.1887960434,51.0830459595],"type":"Point"}
}