{
  "type": "Feature",
  "properties": {
    "iso:country":"BE",
    "sg:address":"Mastellenstraat 15",
    "sg:city":"Landen",
    "sg:orig_category":"Eleveurs and marchands de porcs. Eleveurs de bovins",
    "sg:phone":"+32 11 88 11 90",
    "sg:postcode":"3404",
    "sg:province":"Vlaams-Brabant",
    "wof:name":"Coppejans Henri+rene",
    "wof:placetype":"venue"
},
  "geometry": {"coordinates":[5.0921158791,50.7639350891],"type":"Point"}
}