{
  "type": "Feature",
  "properties": {
    "addr:full":"Rue Du Plantis 9 Houyet Namur 5561",
    "addr:housenumber":"9",
    "addr:postcode":"5561",
    "addr:street":"Rue Du Plantis",
    "iso:country":"BE",
    "sg:address":"Rue Du Plantis 9",
    "sg:city":"Houyet",
    "sg:orig_category":"Secretariaatsdiensten",
    "sg:phone":"+32 82 66 68 01",
    "sg:postcode":"5561",
    "sg:province":"Namur",
    "wof:name":"Encres De Chine",
    "wof:placetype":"venue"
},
  "geometry": {"coordinates":[5.0096502304,50.229221344],"type":"Point"}
}