{
  "type": "Feature",
  "properties": {
    "addr:full":"Halstraat 2 Geetbets Vlaams-Brabant 3450",
    "addr:housenumber":"2",
    "addr:postcode":"3450",
    "addr:street":"Halstraat",
    "iso:country":"BE",
    "sg:address":"Halstraat 2",
    "sg:city":"Geetbets",
    "sg:orig_category":"Rundveehouders",
    "sg:phone":"+32 11 58 82 55",
    "sg:postcode":"3450",
    "sg:province":"Vlaams-Brabant",
    "wof:name":"Armand Beeten",
    "wof:placetype":"venue"
},
  "geometry": {"coordinates":[5.088807106,50.8711967468],"type":"Point"}
}