{
  "type": "Feature",
  "properties": {
    "addr:full":"Geldroplaan 1 Dendermonde Oost-Vlaanderen 9200",
    "addr:housenumber":"1",
    "addr:postcode":"9200",
    "addr:street":"Geldroplaan;Oost-Vlaanderen",
    "iso:country":"BE",
    "sg:address":"Geldroplaan 1",
    "sg:city":"Dendermonde",
    "sg:orig_category":"Werk and personeelsselectie",
    "sg:phone":"+32 52 25 91 00",
    "sg:postcode":"9200",
    "sg:province":"Oost-Vlaanderen",
    "wof:name":"Vdab",
    "wof:placetype":"venue"
},
  "geometry": {"coordinates":[4.1001601219,51.0247039795],"type":"Point"}
}