{
  "type": "Feature",
  "properties": {
    "iso:country":"BE",
    "sg:address":"Rue Arthur Warocqu\u00c9 41",
    "sg:city":"La Louviere",
    "sg:orig_category":"Advocaten and juridische adviseurs",
    "sg:phone":"+32 64 21 13 39",
    "sg:postcode":"7100",
    "sg:province":"Hainaut",
    "wof:name":"B. Mairiaux",
    "wof:placetype":"venue"
},
  "geometry": {"coordinates":[4.1917939186,50.4773712158],"type":"Point"}
}