{
  "type": "Feature",
  "properties": {
    "addr:full":"Dirk Boutslaan 11 Leuven Vlaams-Brabant 3000",
    "addr:housenumber":"11",
    "addr:postcode":"3000",
    "addr:street":"Dirk Boutslaan",
    "iso:country":"BE",
    "sg:address":"Dirk Boutslaan 11",
    "sg:city":"Leuven",
    "sg:classifiers":[
        {
            "category":"Shopping",
            "subcategory":"Clothing, Apparel, & Fashions",
            "type":"Retail Goods"
        }
    ],
    "sg:phone":"+32 16 23 51 04",
    "sg:postcode":"3000",
    "sg:province":"Vlaams-Brabant",
    "sg:tags":[
        "lady",
        "clothing",
        "-"
    ],
    "wof:name":"Rodier Dames",
    "wof:placetype":"venue"
},
  "geometry": {"coordinates":[4.6993999481,50.8801651001],"type":"Point"}
}