{
  "type": "Feature",
  "properties": {
    "addr:full":"Avenue J.f. Debecker 114 Bruxelles (woluwe-saint-lambert) Bruxelles-Capitale 1200",
    "addr:housenumber":"114",
    "addr:postcode":"1200",
    "addr:street":"Avenue J.F. Debecker",
    "iso:country":"BE",
    "sg:address":"Avenue J.f. Debecker 114",
    "sg:city":"Bruxelles (woluwe-saint-lambert)",
    "sg:classifiers":[
        {
            "category":"Banks & Credit Unions",
            "subcategory":"Investment Brokerage",
            "type":"Services"
        }
    ],
    "sg:phone":"+32 2 762 31 19",
    "sg:postcode":"1200",
    "sg:province":"Bruxelles-Capitale",
    "sg:tags":[
        "auditor"
    ],
    "wof:name":"Debroux M C",
    "wof:placetype":"venue"
},
  "geometry": {"coordinates":[4.4476008415,50.8457717896],"type":"Point"}
}