{
  "type": "Feature",
  "properties": {
    "iso:country":"BE",
    "sg:address":"Lindelei 202",
    "sg:city":"Hemiksem",
    "sg:classifiers":[
        {
            "category":"Banks & Credit Unions",
            "subcategory":"Bank",
            "type":"Services"
        }
    ],
    "sg:phone":"+32 3 887 90 16",
    "sg:postcode":"2620",
    "sg:province":"Antwerpen",
    "sg:tags":[
        "savings-banks"
    ],
    "wof:name":"Smolders",
    "wof:placetype":"venue"
},
  "geometry": {"coordinates":[4.3453001976,51.1445198059],"type":"Point"}
}