{
  "type": "Feature",
  "properties": {
    "addr:full":"Tiensesteenweg 386 Leuven Vlaams-Brabant 3000",
    "addr:housenumber":"386",
    "addr:postcode":"3000",
    "addr:street":"Tiensesteenweg",
    "iso:country":"BE",
    "sg:address":"Tiensesteenweg 386",
    "sg:city":"Leuven",
    "sg:classifiers":[
        {
            "category":"Recreation",
            "subcategory":"Barbecue",
            "type":"Entertainment"
        }
    ],
    "sg:phone":"+32 16 25 00 15",
    "sg:postcode":"3000",
    "sg:province":"Vlaams-Brabant",
    "sg:tags":[
        "accessory"
    ],
    "wof:name":"Standard Ahz Nv",
    "wof:placetype":"venue"
},
  "geometry": {"coordinates":[4.7407131195,50.8674697876],"type":"Point"}
}