{
  "type": "Feature",
  "properties": {
    "addr:full":"Langstraat 44 Linter Vlaams-Brabant 3350",
    "addr:housenumber":"44",
    "addr:postcode":"3350",
    "addr:street":"Langstraat;Vlaams-Brabant",
    "iso:country":"BE",
    "sg:address":"Langstraat 44",
    "sg:city":"Linter",
    "sg:orig_category":"Eleveurs and marchands de porcs",
    "sg:phone":"+32 16 78 87 11",
    "sg:postcode":"3350",
    "sg:province":"Vlaams-Brabant",
    "wof:name":"Victor Juwe",
    "wof:placetype":"venue"
},
  "geometry": {"coordinates":[5.0492510796,50.7923965454],"type":"Point"}
}