{
  "type": "Feature",
  "properties": {
    "addr:full":"Rue Albert 2 Tournai Hainaut 7540",
    "addr:housenumber":"2",
    "addr:postcode":"7540",
    "addr:street":"Rue Albert",
    "iso:country":"BE",
    "sg:address":"Rue Albert 2",
    "sg:city":"Tournai",
    "sg:orig_category":"R\u00e9parations and entretien de motos. V\u00e9los. Motos",
    "sg:phone":"+32 69 22 17 78",
    "sg:postcode":"7540",
    "sg:province":"Hainaut",
    "wof:name":"Ets. Labehaut",
    "wof:placetype":"venue"
},
  "geometry": {"coordinates":[3.3895730972,50.6266860962],"type":"Point"}
}