{
  "type": "Feature",
  "properties": {
    "iso:country":"BE",
    "sg:address":"Rue Bourgmestre-bribosia 16",
    "sg:city":"Dinant",
    "sg:orig_category":"Maisons de repos and r\u00e9sidences",
    "sg:phone":"+32 82 22 36 07",
    "sg:postcode":"5500",
    "sg:province":"Namur",
    "wof:name":"Home St.vincent",
    "wof:placetype":"venue"
},
  "geometry": {"coordinates":[4.9105219841,50.258644104],"type":"Point"}
}