{
  "type": "Feature",
  "properties": {
    "addr:full":"Rue Du Gouvernement 41bb12 Mons Hainaut 7000",
    "addr:housenumber":"41bb12",
    "addr:postcode":"7000",
    "addr:street":"Rue Du Gouvernement;Hainaut",
    "iso:country":"BE",
    "sg:address":"Rue Du Gouvernement 41bb12",
    "sg:city":"Mons",
    "sg:orig_category":"M\u00e9decins and sp\u00e9cialistes",
    "sg:phone":"+32 65 31 97 95",
    "sg:postcode":"7000",
    "sg:province":"Hainaut",
    "wof:name":"Elie Danvoye",
    "wof:placetype":"venue"
},
  "geometry": {"coordinates":[3.9590768814,50.4554519653],"type":"Point"}
}