{
  "type": "Feature",
  "properties": {
    "iso:country":"BE",
    "sg:address":"Rue Haute 6",
    "sg:city":"Bernissart",
    "sg:orig_category":"Traitements param\u00e9dicaux",
    "sg:phone":"+32 69 57 93 97",
    "sg:postcode":"7321",
    "sg:province":"Hainaut",
    "wof:name":"Jacquet Val\u00c9rie",
    "wof:placetype":"venue"
},
  "geometry": {"coordinates":[3.6596040726,50.4999198914],"type":"Point"}
}