{
  "type": "Feature",
  "properties": {
    "addr:full":"Treemblok 43 Schilde ('s Gravenwezel) Antwerpen 2970",
    "addr:housenumber":"43",
    "addr:postcode":"2970",
    "addr:street":"Treemblok;S",
    "iso:country":"BE",
    "sg:address":"Treemblok 43",
    "sg:city":"Schilde ('s Gravenwezel)",
    "sg:classifiers":[
        {
            "category":"Manufacturing",
            "subcategory":"Paper Products",
            "type":"Manufacturing & Wholesale Goods"
        }
    ],
    "sg:phone":"+32 3 658 39 14",
    "sg:postcode":"2970",
    "sg:province":"Antwerpen",
    "sg:tags":[
        "bookbinding"
    ],
    "wof:name":"Pampiere Werelt",
    "wof:placetype":"venue"
},
  "geometry": {"coordinates":[4.5418028831,51.2515487671],"type":"Point"}
}