{
  "type": "Feature",
  "properties": {
    "iso:country":"BE",
    "sg:address":"Rue Du Parc 7",
    "sg:city":"Soumagne",
    "sg:orig_category":"Enseignement maternel and primaire",
    "sg:phone":"+32 4 377 33 94",
    "sg:postcode":"4632",
    "sg:province":"Li\u00e8ge",
    "wof:name":"Ecole Maternelle Libre",
    "wof:placetype":"venue"
},
  "geometry": {"coordinates":[5.7195267677,50.656452179],"type":"Point"}
}