{
  "type": "Feature",
  "properties": {
    "iso:country":"BE",
    "sg:address":"Chemin Du Haut Bruard 105",
    "sg:city":"Ham-sur-heure-nalinnes",
    "sg:orig_category":"Installation \u00e9lectrique r\u00e9sidentielle",
    "sg:phone":"+32 71 21 66 07",
    "sg:postcode":"6120",
    "sg:province":"Hainaut",
    "wof:name":"Paul Van Winnendaele",
    "wof:placetype":"venue"
},
  "geometry": {"coordinates":[4.4295201302,50.3398132324],"type":"Point"}
}