{
  "type": "Feature",
  "properties": {
    "iso:country":"BE",
    "sg:address":"Rue Haya 4",
    "sg:city":"Clavier",
    "sg:orig_category":"Eleveurs de bovins",
    "sg:phone":"+32 86 34 51 37",
    "sg:postcode":"4560",
    "sg:province":"Li\u00e8ge",
    "wof:name":"Jean-baptiste Remacle",
    "wof:placetype":"venue"
},
  "geometry": {"coordinates":[5.394244194,50.3942832947],"type":"Point"}
}