{
  "type": "Feature",
  "properties": {
    "addr:full":"Rue De La Grand'place 9 Arlon Luxembourg 6700",
    "addr:housenumber":"9",
    "addr:postcode":"6700",
    "addr:street":"Rue De La Grand'Place",
    "iso:country":"BE",
    "sg:address":"Rue De La Grand'place 9",
    "sg:city":"Arlon",
    "sg:orig_category":"Kapsalons",
    "sg:phone":"+32 63 22 69 94",
    "sg:postcode":"6700",
    "sg:province":"Luxembourg",
    "wof:name":"Coiffure Christian",
    "wof:placetype":"venue"
},
  "geometry": {"coordinates":[5.8141531944,49.6842155457],"type":"Point"}
}