{
  "type": "Feature",
  "properties": {
    "addr:full":"Brusselsesteenweg 411 Mechelen Antwerpen 2800",
    "addr:housenumber":"411",
    "addr:postcode":"2800",
    "addr:street":"Brusselsesteenweg",
    "iso:country":"BE",
    "sg:address":"Brusselsesteenweg 411",
    "sg:city":"Mechelen",
    "sg:orig_category":"HUISBRANDOLIE Speciaalzaken",
    "sg:phone":"+32 78 71 90 02",
    "sg:postcode":"2800",
    "sg:province":"Antwerpen",
    "wof:name":"Avo",
    "wof:placetype":"venue"
},
  "geometry": {"coordinates":[4.4741721153,50.9997749329],"type":"Point"}
}