{
  "type": "Feature",
  "properties": {
    "iso:country":"BE",
    "sg:address":"Rue Saint-antoine 5",
    "sg:city":"Namur",
    "sg:orig_category":"Architecten",
    "sg:phone":"+32 81 56 98 92",
    "sg:postcode":"5020",
    "sg:province":"Namur",
    "wof:name":"Aude Franssen",
    "wof:placetype":"venue"
},
  "geometry": {"coordinates":[4.7413868904,50.4798431396],"type":"Point"}
}