{
  "type": "Feature",
  "properties": {
    "iso:country":"BE",
    "sg:address":"G. Vandenheuvelstr. 22",
    "sg:city":"Herselt",
    "sg:classifiers":[
        {
            "category":"Insurance",
            "subcategory":"Insurance Agent",
            "type":"Services"
        }
    ],
    "sg:phone":"+32 16 69 65 65",
    "sg:postcode":"2230",
    "sg:province":"Antwerpen",
    "sg:tags":[
        "verzekeringsmakelaars",
        "expert"
    ],
    "wof:name":"Bureau Van Opstal",
    "wof:placetype":"venue"
},
  "geometry": {"coordinates":[4.8338518143,51.0308876038],"type":"Point"}
}