{
  "type": "Feature",
  "properties": {
    "addr:full":"Zeewindstraat 13-15 Knokke-heist West-Vlaanderen 8301",
    "addr:postcode":"13-15;8301",
    "addr:street":"Zeewindstraat",
    "iso:country":"BE",
    "sg:address":"Zeewindstraat 13-15",
    "sg:city":"Knokke-heist",
    "sg:orig_category":"Watersport-, Sport- and Kampeerbenodigdheden Verhuur",
    "sg:phone":"+32 50 60 03 37",
    "sg:postcode":"8301",
    "sg:province":"West-Vlaanderen",
    "wof:name":"Cyclo-cars Kurt",
    "wof:placetype":"venue"
},
  "geometry": {"coordinates":[3.2639000416,51.3396911621],"type":"Point"}
}