{
  "type": "Feature",
  "properties": {
    "addr:full":"Leeuwerikstraat 37 Gent Oost-Vlaanderen 9000",
    "addr:housenumber":"37",
    "addr:postcode":"9000",
    "addr:street":"Leeuwerikstraat;Oost-Vlaanderen",
    "iso:country":"BE",
    "sg:address":"Leeuwerikstraat 37",
    "sg:city":"Gent",
    "sg:classifiers":[
        {
            "category":"Retail",
            "subcategory":"Repair Shop",
            "type":"Services"
        }
    ],
    "sg:phone":"+32 9 222 40 43",
    "sg:postcode":"9000",
    "sg:province":"Oost-Vlaanderen",
    "sg:tags":[
        "upholsterer"
    ],
    "wof:name":"Wauman A",
    "wof:placetype":"venue"
},
  "geometry": {"coordinates":[3.7087900639,51.0310325623],"type":"Point"}
}