{
  "type": "Feature",
  "properties": {
    "addr:full":"Diestsestraat 223 Leuven Vlaams-Brabant 3000",
    "addr:housenumber":"223",
    "addr:postcode":"3000",
    "addr:street":"Diestsestraat",
    "iso:country":"BE",
    "sg:address":"Diestsestraat 223",
    "sg:city":"Leuven",
    "sg:orig_category":"Pharmaciens",
    "sg:phone":"+32 16 23 77 15",
    "sg:postcode":"3000",
    "sg:province":"Vlaams-Brabant",
    "wof:name":"Davidts",
    "wof:placetype":"venue"
},
  "geometry": {"coordinates":[4.7114009857,50.8818855286],"type":"Point"}
}