{
  "type": "Feature",
  "properties": {
    "addr:full":"Rue Des Charbonnages 100 Chatelet Hainaut 6200",
    "addr:housenumber":"100",
    "addr:postcode":"chatelet;6200",
    "addr:street":"Rue Des Charbonnages",
    "iso:country":"BE",
    "sg:address":"Rue Des Charbonnages 100",
    "sg:city":"Chatelet",
    "sg:orig_category":"Charpentes and couvertures",
    "sg:phone":"+32 71 38 65 12",
    "sg:postcode":"6200",
    "sg:province":"Hainaut",
    "wof:name":"Fievez-roussel",
    "wof:placetype":"venue"
},
  "geometry": {"coordinates":[4.5186228752,50.4213752747],"type":"Point"}
}