{
  "type": "Feature",
  "properties": {
    "iso:country":"BE",
    "sg:address":"Smallestraat 28",
    "sg:city":"Mol",
    "sg:orig_category":"Agences de publicit\u00e9",
    "sg:phone":"+32 14 31 74 33",
    "sg:postcode":"2400",
    "sg:province":"Antwerpen",
    "wof:name":"Reklameatelier A.b.c.",
    "wof:placetype":"venue"
},
  "geometry": {"coordinates":[5.1200199127,51.1892433167],"type":"Point"}
}