{
  "type": "Feature",
  "properties": {
    "iso:country":"BE",
    "sg:address":"Westmeetstraat 61",
    "sg:city":"Koekelare",
    "sg:orig_category":"Non-Classified Establishments",
    "sg:phone":"+32 51 58 34 00",
    "sg:postcode":"8680",
    "sg:province":"West-Vlaanderen",
    "wof:name":"Ossaer M",
    "wof:placetype":"venue"
},
  "geometry": {"coordinates":[2.946737051,51.0912742615],"type":"Point"}
}