{
  "type": "Feature",
  "properties": {
    "iso:country":"BE",
    "sg:address":"Rue Quinaux 9",
    "sg:city":"Bruxelles (schaerbeek)",
    "sg:classifiers":[
        {
            "category":"Arts & Performance",
            "subcategory":"Music",
            "type":"Entertainment"
        }
    ],
    "sg:phone":"+32 2 245 57 07",
    "sg:postcode":"1030",
    "sg:province":"Bruxelles-Capitale",
    "sg:tags":[
        "freelance",
        "musician"
    ],
    "wof:name":"Gospel Live Music",
    "wof:placetype":"venue"
},
  "geometry": {"coordinates":[4.3732538223,50.8683815002],"type":"Point"}
}