{
  "type": "Feature",
  "properties": {
    "addr:full":"Rue Vertbois 25 Saint-nicolas Li\u00e8ge 4420",
    "addr:housenumber":"25",
    "addr:postcode":"4420",
    "addr:street":"Rue Vertbois",
    "iso:country":"BE",
    "sg:address":"Rue Vertbois 25",
    "sg:city":"Saint-nicolas",
    "sg:orig_category":"Plomberie, chauffage and installations sanitaires",
    "sg:phone":"+32 4 247 36 29",
    "sg:postcode":"4420",
    "sg:province":"Li\u00e8ge",
    "wof:name":"Alain Laforet",
    "wof:placetype":"venue"
},
  "geometry": {"coordinates":[5.5242981911,50.6386985779],"type":"Point"}
}