{
  "type": "Feature",
  "properties": {
    "iso:country":"BE",
    "sg:address":"Pimberg 12",
    "sg:city":"Bierbeek",
    "sg:classifiers":[
        {
            "category":"Arena",
            "subcategory":"Sports Club",
            "type":"Entertainment"
        }
    ],
    "sg:phone":"+32 16 46 13 49",
    "sg:postcode":"3360",
    "sg:province":"Vlaams-Brabant",
    "sg:tags":[
        "de"
    ],
    "wof:name":"W.s.c. Lindense Wielervr.",
    "wof:placetype":"venue"
},
  "geometry": {"coordinates":[4.7529802322,50.8673400879],"type":"Point"}
}