{
  "type": "Feature",
  "properties": {
    "iso:country":"BE",
    "sg:address":"Meerlaarstraat 100",
    "sg:city":"Laakdal",
    "sg:orig_category":"Pharmaciens",
    "sg:phone":"+32 13 66 23 05",
    "sg:postcode":"2430",
    "sg:province":"Antwerpen",
    "wof:name":"Apotheek Sauer-meerlaar",
    "wof:placetype":"venue"
},
  "geometry": {"coordinates":[5.0660891533,51.0851020813],"type":"Point"}
}