{
  "type": "Feature",
  "properties": {
    "iso:country":"BE",
    "sg:address":"Av. L\u00e9on Champagne 3",
    "sg:city":"Tubize",
    "sg:classifiers":[
        {
            "category":"Banks & Credit Unions",
            "subcategory":"Bureau De Change",
            "type":"Services"
        }
    ],
    "sg:phone":"+32 2 367 22 30",
    "sg:postcode":"1480",
    "sg:province":"Brabant Wallon",
    "sg:tags":[
        "pressure",
        "differential",
        "gauge"
    ],
    "wof:name":"Istec International B.v",
    "wof:placetype":"venue"
},
  "geometry": {"coordinates":[4.1754570007,50.70911026],"type":"Point"}
}