{
  "type": "Feature",
  "properties": {
    "addr:full":"Schrieksebaan 208 Tremelo Vlaams-Brabant 3120",
    "addr:housenumber":"208",
    "addr:postcode":"3120",
    "addr:street":"Schrieksebaan",
    "iso:country":"BE",
    "sg:address":"Schrieksebaan 208",
    "sg:city":"Tremelo",
    "sg:classifiers":[
        {
            "category":"Bakery",
            "type":"Food & Drink"
        }
    ],
    "sg:phone":"+32 15 23 50 18",
    "sg:postcode":"3120",
    "sg:province":"Vlaams-Brabant",
    "sg:tags":[
        "confectioner",
        "baker"
    ],
    "wof:name":"Rabaut",
    "wof:placetype":"venue"
},
  "geometry": {"coordinates":[4.708313942,51.0064582825],"type":"Point"}
}