{
  "type": "Feature",
  "properties": {
    "iso:country":"BE",
    "sg:address":"Laguitstraat 5",
    "sg:city":"Turnhout",
    "sg:orig_category":"Farmaceutische bereidingen and geneesmiddelen Fab",
    "sg:phone":"+32 14 41 67 39",
    "sg:postcode":"2300",
    "sg:province":"Antwerpen",
    "wof:name":"Mophaco",
    "wof:placetype":"venue"
},
  "geometry": {"coordinates":[4.9450588226,51.342880249],"type":"Point"}
}