{
  "type": "Feature",
  "properties": {
    "addr:full":"Aarschotsesteenweg 523 Leuven (wilsele) Vlaams-Brabant 3012",
    "addr:housenumber":"523",
    "addr:postcode":"3012",
    "addr:street":"Aarschotsesteenweg",
    "iso:country":"BE",
    "sg:address":"Aarschotsesteenweg 523",
    "sg:city":"Leuven (wilsele)",
    "sg:classifiers":[
        {
            "category":"Professional",
            "subcategory":"Art Services",
            "type":"Services"
        }
    ],
    "sg:phone":"+32 16 44 46 70",
    "sg:postcode":"3012",
    "sg:province":"Vlaams-Brabant",
    "sg:tags":[
        "photography",
        "reporting",
        "-"
    ],
    "wof:name":"Loddewykx",
    "wof:placetype":"venue"
},
  "geometry": {"coordinates":[4.7232670784,50.928150177],"type":"Point"}
}