{
  "type": "Feature",
  "properties": {
    "addr:full":"Rue De Philippeville 260 Dinant Namur 5500",
    "addr:housenumber":"260",
    "addr:postcode":"5500",
    "addr:street":"Rue De Philippeville",
    "iso:country":"BE",
    "sg:address":"Rue De Philippeville 260",
    "sg:city":"Dinant",
    "sg:orig_category":"Installation \u00e9lectrique r\u00e9sidentielle",
    "sg:phone":"+32 82 22 51 06",
    "sg:postcode":"5500",
    "sg:province":"Namur",
    "wof:name":"Jean Lhost",
    "wof:placetype":"venue"
},
  "geometry": {"coordinates":[4.894618988,50.2526168823],"type":"Point"}
}