{
  "type": "Feature",
  "properties": {
    "iso:country":"BE",
    "sg:address":"Mechelbaan 477",
    "sg:city":"Putte",
    "sg:orig_category":"Bloemen and planten",
    "sg:phone":"+32 15 75 61 60",
    "sg:postcode":"2580",
    "sg:province":"Antwerpen",
    "wof:name":"Ronny Geens",
    "wof:placetype":"venue"
},
  "geometry": {"coordinates":[4.6303601265,51.0554275513],"type":"Point"}
}