{
  "type": "Feature",
  "properties": {
    "iso:country":"BE",
    "sg:address":"Kasteeldreef 30",
    "sg:city":"Lubbeek",
    "sg:orig_category":"Dierenartsen",
    "sg:phone":"+32 16 35 61 18",
    "sg:postcode":"3210",
    "sg:province":"Vlaams-Brabant",
    "wof:name":"Isabella Houdart",
    "wof:placetype":"venue"
},
  "geometry": {"coordinates":[4.7598290443,50.9016952515],"type":"Point"}
}