{
  "type": "Feature",
  "properties": {
    "addr:full":"Rue Ferrer 9 Hensies Hainaut 7350",
    "addr:housenumber":"9",
    "addr:postcode":"7350",
    "addr:street":"Rue Ferrer",
    "iso:country":"BE",
    "sg:address":"Rue Ferrer 9",
    "sg:city":"Hensies",
    "sg:orig_category":"Slagers",
    "sg:phone":"+32 65 65 63 26",
    "sg:postcode":"7350",
    "sg:province":"Hainaut",
    "wof:name":"Christian Bonte",
    "wof:placetype":"venue"
},
  "geometry": {"coordinates":[3.7403399944,50.4281806946],"type":"Point"}
}