{
  "type": "Feature",
  "properties": {
    "addr:full":"Clarissenstraat 29 Gent Oost-Vlaanderen 9000",
    "addr:housenumber":"29",
    "addr:postcode":"9000",
    "addr:street":"Clarissenstraat;Oost-Vlaanderen",
    "iso:country":"BE",
    "sg:address":"Clarissenstraat 29",
    "sg:city":"Gent",
    "sg:orig_category":"Artsen and specialisten",
    "sg:phone":"+32 9 233 43 04",
    "sg:postcode":"9000",
    "sg:province":"Oost-Vlaanderen",
    "wof:name":"Brigitte Lepage",
    "wof:placetype":"venue"
},
  "geometry": {"coordinates":[3.734705925,51.043800354],"type":"Point"}
}