{
  "type": "Feature",
  "properties": {
    "iso:country":"BE",
    "sg:address":"Havenstraat 26",
    "sg:city":"Oostende",
    "sg:orig_category":"Herstellingen and onderhoud aan huis voor voertuigen",
    "sg:phone":"+32 59 32 15 18",
    "sg:postcode":"8400",
    "sg:province":"West-Vlaanderen",
    "wof:name":"Mobi-wash",
    "wof:placetype":"venue"
},
  "geometry": {"coordinates":[2.9126999378,51.2312583923],"type":"Point"}
}