{
  "type": "Feature",
  "properties": {
    "iso:country":"BE",
    "sg:address":"Rue Des Criquelions 46",
    "sg:city":"Saint-ghislain",
    "sg:orig_category":"Jardinage",
    "sg:phone":"+32 65 64 27 23",
    "sg:postcode":"7331",
    "sg:province":"Hainaut",
    "wof:name":"Willaye F.",
    "wof:placetype":"venue"
},
  "geometry": {"coordinates":[3.8342700005,50.4667739868],"type":"Point"}
}