{
  "type": "Feature",
  "properties": {
    "addr:full":"Avenue Jules Bordet 18 Renaix Oost-Vlaanderen 9600",
    "addr:housenumber":"18",
    "addr:postcode":"9600",
    "addr:street":"Avenue Jules Bordet",
    "iso:country":"BE",
    "sg:address":"Avenue Jules Bordet 18",
    "sg:city":"Renaix",
    "sg:classifiers":[
        {
            "category":"Professional",
            "subcategory":"Computer Services",
            "type":"Services"
        }
    ],
    "sg:phone":"+32 476 26 77 17",
    "sg:postcode":"9600",
    "sg:province":"Oost-Vlaanderen",
    "sg:tags":[
        "-",
        "processing",
        "data",
        "software"
    ],
    "wof:name":"Vdz-pc-tech",
    "wof:placetype":"venue"
},
  "geometry": {"coordinates":[3.5997951031,50.7394104004],"type":"Point"}
}