{
  "type": "Feature",
  "properties": {
    "addr:full":"Chauss\u00e9e De Namur 214 Villers-la-ville (marbais) Brabant Wallon 1495",
    "addr:housenumber":"214",
    "addr:postcode":"1495",
    "addr:street":"Chausse\u0301E De Namur",
    "iso:country":"BE",
    "sg:address":"Chauss\u00e9e De Namur 214",
    "sg:city":"Villers-la-ville (marbais)",
    "sg:classifiers":[
        {
            "category":"Building & Trades",
            "subcategory":"Electrical",
            "type":"Services"
        }
    ],
    "sg:phone":"+32 71 87 67 34",
    "sg:postcode":"1495",
    "sg:province":"Brabant Wallon",
    "sg:tags":[
        "electric",
        "-",
        "housewiring",
        "contractor"
    ],
    "wof:name":"Corman",
    "wof:placetype":"venue"
},
  "geometry": {"coordinates":[4.5028100014,50.5518913269],"type":"Point"}
}