{
  "type": "Feature",
  "properties": {
    "addr:full":"Scholtisplein 21 Maaseik Limburg 3680",
    "addr:housenumber":"21",
    "addr:postcode":"3680",
    "addr:street":"Scholtisplein",
    "iso:country":"BE",
    "sg:address":"Scholtisplein 21",
    "sg:city":"Maaseik",
    "sg:orig_category":"Enseignement maternel and primaire",
    "sg:phone":"+32 89 86 43 25",
    "sg:postcode":"3680",
    "sg:province":"Limburg",
    "wof:name":"B.s.g.o. De Winde",
    "wof:placetype":"venue"
},
  "geometry": {"coordinates":[5.791285038,51.0954208374],"type":"Point"}
}