{
  "type": "Feature",
  "properties": {
    "iso:country":"BE",
    "sg:address":"Chauss\u00e9e De Douai 47",
    "sg:city":"Tournai",
    "sg:classifiers":[
        {
            "category":"Home & Garden",
            "subcategory":"Garden Supply",
            "type":"Retail Goods"
        }
    ],
    "sg:phone":"+32 69 22 22 32",
    "sg:postcode":"7500",
    "sg:province":"Hainaut",
    "wof:name":"Derasse Natur' Element",
    "wof:placetype":"venue"
},
  "geometry": {"coordinates":[3.3792378902,50.5998497009],"type":"Point"}
}