{
  "type": "Feature",
  "properties": {
    "iso:country":"BE",
    "sg:address":"Avenue Oscar Van Goidtsnoven 97",
    "sg:city":"Bruxelles (forest)",
    "sg:classifiers":[
        {
            "category":"Professional",
            "subcategory":"Lawyer & Legal Services",
            "type":"Services"
        }
    ],
    "sg:phone":"+32 2 346 05 76",
    "sg:postcode":"1190",
    "sg:province":"Bruxelles-Capitale",
    "wof:name":"Dumont Jean-paul",
    "wof:placetype":"venue"
},
  "geometry": {"coordinates":[4.3374409676,50.8159675598],"type":"Point"}
}