{
  "type": "Feature",
  "properties": {
    "iso:country":"BE",
    "sg:address":"En Faurieux 54",
    "sg:city":"Herstal",
    "sg:orig_category":"Agences de publicit\u00e9",
    "sg:phone":"+32 4 248 24 42",
    "sg:postcode":"4040",
    "sg:province":"Li\u00e8ge",
    "wof:name":"Raphael Boccardo",
    "wof:placetype":"venue"
},
  "geometry": {"coordinates":[5.627600193,50.6656913757],"type":"Point"}
}