{
  "type": "Feature",
  "properties": {
    "iso:country":"BE",
    "sg:address":"Legen Heirweg 21",
    "sg:city":"Gavere (asper)",
    "sg:orig_category":"Non-Classified Establishments",
    "sg:phone":"+32 9 384 68 69",
    "sg:postcode":"9890",
    "sg:province":"Oost-Vlaanderen",
    "wof:name":"Antonio",
    "wof:placetype":"venue"
},
  "geometry": {"coordinates":[3.6444199085,50.933303833],"type":"Point"}
}