{
  "type": "Feature",
  "properties": {
    "addr:full":"Rue Des Rentiers 125 Haine-saint-paul Hainaut 7100",
    "addr:housenumber":"125",
    "addr:postcode":"7100",
    "addr:street":"Rue Des Rentiers;Hainaut",
    "iso:country":"BE",
    "sg:address":"Rue Des Rentiers 125",
    "sg:city":"Haine-saint-paul",
    "sg:orig_category":"Apparatus, Containers, Tanks And Boilers, Plastic-Coated",
    "sg:phone":"+32 64 26 58 43",
    "sg:postcode":"7100",
    "sg:province":"Hainaut",
    "wof:name":"Atelier De Construction Polyest\u00e8re A.c.p. S.p.r.l.",
    "wof:placetype":"venue"
},
  "geometry": {"coordinates":[4.1850848198,50.4748649597],"type":"Point"}
}