{
  "type": "Feature",
  "properties": {
    "addr:full":"Winterland 21 Kortrijk (heule) West-Vlaanderen 8501",
    "addr:housenumber":"21",
    "addr:postcode":"8501",
    "addr:street":"Winterland",
    "iso:country":"BE",
    "sg:address":"Winterland 21",
    "sg:city":"Kortrijk (heule)",
    "sg:classifiers":[
        {
            "category":"Utilities",
            "subcategory":"Telephone",
            "type":"Services"
        }
    ],
    "sg:phone":"+32 497 46 31 80",
    "sg:postcode":"8501",
    "sg:province":"West-Vlaanderen",
    "sg:tags":[
        "-",
        "internet"
    ],
    "wof:name":"Weblinx",
    "wof:placetype":"venue"
},
  "geometry": {"coordinates":[3.2259409428,50.8393554688],"type":"Point"}
}