{
  "type": "Feature",
  "properties": {
    "addr:full":"Avenue De La Mutualit\u00e9 98/1 Haine-saint-paul Hainaut 7100",
    "addr:housenumber":"98 / 1",
    "addr:postcode":"7100",
    "addr:street":"Avenue De La Mutualite\u0301;Haine-Saint-Paul Hainaut",
    "iso:country":"BE",
    "sg:address":"Avenue De La Mutualit\u00e9 98/1",
    "sg:city":"Haine-saint-paul",
    "sg:classifiers":[
        {
            "category":"Home & Garden",
            "subcategory":"Hardware",
            "type":"Retail Goods"
        }
    ],
    "sg:phone":"+32 64 84 81 48",
    "sg:postcode":"7100",
    "sg:province":"Hainaut",
    "sg:tags":[
        "compressor",
        "air"
    ],
    "wof:name":"Hollaert S.a.",
    "wof:placetype":"venue"
},
  "geometry": {"coordinates":[4.2024002075,50.4656791687],"type":"Point"}
}