{
  "type": "Feature",
  "properties": {
    "iso:country":"BE",
    "sg:address":"Grand\u00b4rue 51",
    "sg:city":"Virton",
    "sg:orig_category":"Textiles. V\u00eatements",
    "sg:phone":"+32 63 57 84 34",
    "sg:postcode":"6760",
    "sg:province":"Luxembourg",
    "wof:name":"Phildar",
    "wof:placetype":"venue"
},
  "geometry": {"coordinates":[5.532143116,49.5684242249],"type":"Point"}
}