{
  "type": "Feature",
  "properties": {
    "iso:country":"BE",
    "sg:address":"Kapelhoekstraat 33",
    "sg:city":"Roeselare",
    "sg:classifiers":[
        {
            "category":"Retail",
            "subcategory":"Auto Rental",
            "type":"Services"
        }
    ],
    "sg:phone":"+32 59 51 31 96",
    "sg:postcode":"8800",
    "sg:province":"West-Vlaanderen",
    "sg:tags":[
        "term",
        "van",
        "cars",
        "-",
        "long",
        "delivery",
        "truck"
    ],
    "wof:name":"Toran Nv",
    "wof:placetype":"venue"
},
  "geometry": {"coordinates":[3.1230149269,50.9443435669],"type":"Point"}
}