{
  "type": "Feature",
  "properties": {
    "iso:country":"BE",
    "sg:address":"Handelsstraat 61-63",
    "sg:city":"Antwerpen",
    "sg:classifiers":[
        {
            "category":"Shopping",
            "subcategory":"Gifts & Souvenirs",
            "type":"Retail Goods"
        }
    ],
    "sg:phone":"+32 3 235 64 27",
    "sg:postcode":"2060",
    "sg:province":"Antwerpen",
    "sg:tags":[
        "-"
    ],
    "wof:name":"Kadoke ('t)",
    "wof:placetype":"venue"
},
  "geometry": {"coordinates":[4.4295759201,51.2238883972],"type":"Point"}
}