{
  "type": "Feature",
  "properties": {
    "iso:country":"BE",
    "sg:address":"Stationsplein 31",
    "sg:city":"Ingelmunster",
    "sg:classifiers":[
        {
            "category":"Cafe",
            "type":"Food & Drink"
        }
    ],
    "sg:phone":"+32 51 32 16 51",
    "sg:postcode":"8770",
    "sg:province":"West-Vlaanderen",
    "sg:tags":[
        "caf\u00e9s"
    ],
    "wof:name":"Hof Van Vlaanderen",
    "wof:placetype":"venue"
},
  "geometry": {"coordinates":[3.2560379505,50.914264679],"type":"Point"}
}