{
  "type": "Feature",
  "properties": {
    "addr:full":"Verenigingstraat 20 Bredene West-Vlaanderen 8450",
    "addr:housenumber":"20",
    "addr:postcode":"8450",
    "addr:street":"Verenigingstraat",
    "iso:country":"BE",
    "sg:address":"Verenigingstraat 20",
    "sg:city":"Bredene",
    "sg:orig_category":"Productie van shows and podiumkunsten",
    "sg:phone":"+32 59 32 27 54",
    "sg:postcode":"8450",
    "sg:province":"West-Vlaanderen",
    "wof:name":"Gemeentelijke Harmonie Bredene",
    "wof:placetype":"venue"
},
  "geometry": {"coordinates":[2.9626560211,51.2276802063],"type":"Point"}
}