{
  "type": "Feature",
  "properties": {
    "addr:full":"Place Du Souvenir 10 Esneux Li\u00e8ge 4130",
    "addr:housenumber":"10",
    "addr:postcode":"4130",
    "addr:street":"Place Du Souvenir",
    "iso:country":"BE",
    "sg:address":"Place Du Souvenir 10",
    "sg:city":"Esneux",
    "sg:orig_category":"S\u00e9curit\u00e9 sociale",
    "sg:phone":"+32 4 388 34 87",
    "sg:postcode":"4130",
    "sg:province":"Li\u00e8ge",
    "wof:name":"Mutualit\u00c9 Socialiste",
    "wof:placetype":"venue"
},
  "geometry": {"coordinates":[5.5669360161,50.5327568054],"type":"Point"}
}