{
  "type": "Feature",
  "properties": {
    "addr:full":"Bruinenveldweg 9 Geetbets Vlaams-Brabant 3454",
    "addr:housenumber":"9",
    "addr:postcode":"3454",
    "addr:street":"Bruinenveldweg",
    "iso:country":"BE",
    "sg:address":"Bruinenveldweg 9",
    "sg:city":"Geetbets",
    "sg:orig_category":"Fruitteelt",
    "sg:phone":"+32 11 58 96 15",
    "sg:postcode":"3454",
    "sg:province":"Vlaams-Brabant",
    "wof:name":"Georges Grauwels",
    "wof:placetype":"venue"
},
  "geometry": {"coordinates":[5.1594529152,50.9010734558],"type":"Point"}
}