{
  "type": "Feature",
  "properties": {
    "iso:country":"BE",
    "sg:address":"Tiensevest 40",
    "sg:city":"Leuven",
    "sg:classifiers":[
        {
            "category":"Health Services",
            "subcategory":"Doctor",
            "type":"Services"
        }
    ],
    "sg:phone":"+32 16 20 85 96",
    "sg:postcode":"3000",
    "sg:province":"Vlaams-Brabant",
    "sg:tags":[
        "psychotherapist",
        "psychoanalyst"
    ],
    "wof:name":"Isw Nv",
    "wof:placetype":"venue"
},
  "geometry": {"coordinates":[4.7150220871,50.8796043396],"type":"Point"}
}