{
  "type": "Feature",
  "properties": {
    "addr:full":"Tenboslaan 86 Hoeilaart Vlaams-Brabant 1560",
    "addr:housenumber":"86",
    "addr:postcode":"1560",
    "addr:street":"Tenboslaan",
    "iso:country":"BE",
    "sg:address":"Tenboslaan 86",
    "sg:city":"Hoeilaart",
    "sg:classifiers":[
        {
            "category":"Wholesale",
            "subcategory":"Medical Equipment & Supplies",
            "type":"Manufacturing & Wholesale Goods"
        }
    ],
    "sg:phone":"+32 2 657 58 61",
    "sg:postcode":"1560",
    "sg:province":"Vlaams-Brabant",
    "sg:tags":[
        "-",
        "imaging"
    ],
    "wof:name":"Davia G Sprl",
    "wof:placetype":"venue"
},
  "geometry": {"coordinates":[4.4887661934,50.7585487366],"type":"Point"}
}