{
  "type": "Feature",
  "properties": {
    "addr:full":"Rue L\u00c9opold 115-117 Dison Li\u00e8ge 4820",
    "addr:postcode":"115-117;4820",
    "addr:street":"Rue Le\u0301Opold",
    "iso:country":"BE",
    "sg:address":"Rue L\u00c9opold 115-117",
    "sg:city":"Dison",
    "sg:orig_category":"Catering and organisation de f\u00eates. Boucheries",
    "sg:phone":"+32 87 33 30 72",
    "sg:postcode":"4820",
    "sg:province":"Li\u00e8ge",
    "wof:name":"Ortmans Traiteur",
    "wof:placetype":"venue"
},
  "geometry": {"coordinates":[5.8491678238,50.6110038757],"type":"Point"}
}