{
  "type": "Feature",
  "properties": {
    "addr:full":"Joseph Depauwstraat 28 Sint-pieters-leeuw Vlaams-Brabant 1600",
    "addr:housenumber":"28",
    "addr:postcode":"1600",
    "addr:street":"Depauwstraat",
    "iso:country":"BE",
    "sg:address":"Joseph Depauwstraat 28",
    "sg:city":"Sint-pieters-leeuw",
    "sg:orig_category":"Supermarch\u00e9s. Alimentation sp\u00e9cialis\u00e9e",
    "sg:phone":"+32 2 331 12 15",
    "sg:postcode":"1600",
    "sg:province":"Vlaams-Brabant",
    "wof:name":"Louis Delhaize",
    "wof:placetype":"venue"
},
  "geometry": {"coordinates":[4.2456917763,50.7780189514],"type":"Point"}
}