{
  "type": "Feature",
  "properties": {
    "addr:full":"Fonteinstraat 40 Haaltert Oost-Vlaanderen 9450",
    "addr:housenumber":"40",
    "addr:postcode":"9450",
    "addr:street":"Fonteinstraat",
    "iso:country":"BE",
    "sg:address":"Fonteinstraat 40",
    "sg:city":"Haaltert",
    "sg:orig_category":"Boekhouders",
    "sg:phone":"+32 53 73 08 17",
    "sg:postcode":"9450",
    "sg:province":"Oost-Vlaanderen",
    "wof:name":"Frank Moerenhout",
    "wof:placetype":"venue"
},
  "geometry": {"coordinates":[4.0082001686,50.8961486816],"type":"Point"}
}