{
  "type": "Feature",
  "properties": {
    "iso:country":"BE",
    "sg:address":"Rue De Chimay 32",
    "sg:city":"Chimay",
    "sg:classifiers":[
        {
            "category":"Cafe",
            "type":"Food & Drink"
        }
    ],
    "sg:phone":"+32 60 37 70 85",
    "sg:postcode":"6461",
    "sg:province":"Hainaut",
    "sg:tags":[
        "caf\u00e9s"
    ],
    "wof:name":"R. Heripret",
    "wof:placetype":"venue"
},
  "geometry": {"coordinates":[4.3305802345,50.0547599792],"type":"Point"}
}