{
  "type": "Feature",
  "properties": {
    "addr:full":"Route De Mons Maubeuge 4 Qu\u00e9vy (havay) Hainaut 7041",
    "addr:housenumber":"4;havay",
    "addr:postcode":"7041",
    "addr:street":"Route De Mons Maubeuge;Hainaut",
    "iso:country":"BE",
    "sg:address":"Route De Mons Maubeuge 4",
    "sg:city":"Qu\u00e9vy (havay)",
    "sg:classifiers":[
        {
            "category":"Food & Beverages",
            "subcategory":"Chocolate",
            "type":"Retail Goods"
        }
    ],
    "sg:phone":"+32 65 56 74 32",
    "sg:postcode":"7041",
    "sg:province":"Hainaut",
    "sg:tags":[
        "confectionery",
        "-"
    ],
    "wof:name":"Leonidas L'ile Aux Delices",
    "wof:placetype":"venue"
},
  "geometry": {"coordinates":[3.9704129696,50.3445930481],"type":"Point"}
}