{
  "type": "Feature",
  "properties": {
    "addr:full":"Place Saint-aubain 12 Namur Namur 5000",
    "addr:housenumber":"12",
    "addr:postcode":"5000",
    "addr:street":"Place Saint-Aubain",
    "iso:country":"BE",
    "sg:address":"Place Saint-aubain 12",
    "sg:city":"Namur",
    "sg:orig_category":"Avocats and conseillers juridiques",
    "sg:phone":"+32 81 22 43 07",
    "sg:postcode":"5000",
    "sg:province":"Namur",
    "wof:name":"S. Collin",
    "wof:placetype":"venue"
},
  "geometry": {"coordinates":[4.8364949226,50.4628334045],"type":"Point"}
}