{
  "type": "Feature",
  "properties": {
    "iso:country":"BE",
    "sg:address":"Hollestraat 52ba",
    "sg:city":"Aalst",
    "sg:orig_category":"Artsen and specialisten",
    "sg:phone":"+32 53 78 92 75",
    "sg:postcode":"9310",
    "sg:province":"Oost-Vlaanderen",
    "wof:name":"C. Van Huffel",
    "wof:placetype":"venue"
},
  "geometry": {"coordinates":[4.1008839607,50.9586982727],"type":"Point"}
}