{
  "type": "Feature",
  "properties": {
    "iso:country":"BE",
    "sg:address":"Rue Lavaulx 7",
    "sg:city":"Donceel",
    "sg:orig_category":"Eleveurs de bovins. Eleveurs and marchands de porcs",
    "sg:phone":"+32 4 250 13 25",
    "sg:postcode":"4357",
    "sg:province":"Li\u00e8ge",
    "wof:name":"Lambert Jaymaert",
    "wof:placetype":"venue"
},
  "geometry": {"coordinates":[5.3566040993,50.6573867798],"type":"Point"}
}