{
  "type": "Feature",
  "properties": {
    "addr:full":"Brugsesteenweg 5 Gent Oost-Vlaanderen 9000",
    "addr:housenumber":"5",
    "addr:postcode":"9000",
    "addr:street":"Brugsesteenweg;Oost-Vlaanderen",
    "iso:country":"BE",
    "sg:address":"Brugsesteenweg 5",
    "sg:city":"Gent",
    "sg:classifiers":[
        {
            "category":"Wholesale",
            "subcategory":"Plants",
            "type":"Manufacturing & Wholesale Goods"
        }
    ],
    "sg:phone":"+32 9 226 36 03",
    "sg:postcode":"9000",
    "sg:province":"Oost-Vlaanderen",
    "sg:tags":[
        "decoration",
        "flower",
        "-"
    ],
    "wof:name":"Bries Bvba",
    "wof:placetype":"venue"
},
  "geometry": {"coordinates":[3.695389986,51.0636711121],"type":"Point"}
}