{
  "type": "Feature",
  "properties": {
    "iso:country":"BE",
    "sg:address":"Avenue Jean Jaur\u00c8s 131",
    "sg:city":"Soumagne",
    "sg:orig_category":"Landmeters",
    "sg:phone":"+32 4 377 38 64",
    "sg:postcode":"4630",
    "sg:province":"Li\u00e8ge",
    "wof:name":"Patrice Desmit",
    "wof:placetype":"venue"
},
  "geometry": {"coordinates":[5.7388801575,50.6341705322],"type":"Point"}
}