{
  "type": "Feature",
  "properties": {
    "addr:full":"Spiegelstraat 6 Tienen Vlaams-Brabant 3300",
    "addr:housenumber":"6",
    "addr:postcode":"3300",
    "addr:street":"Spiegelstraat",
    "iso:country":"BE",
    "sg:address":"Spiegelstraat 6",
    "sg:city":"Tienen",
    "sg:classifiers":[
        {
            "category":"Restaurant",
            "type":"Food & Drink"
        }
    ],
    "sg:phone":"+32 16 81 91 79",
    "sg:postcode":"3300",
    "sg:province":"Vlaams-Brabant",
    "wof:name":"Bistroquet",
    "wof:placetype":"venue"
},
  "geometry": {"coordinates":[4.9387497902,50.8064689636],"type":"Point"}
}