{
  "type": "Feature",
  "properties": {
    "addr:full":"Bethani\u00cblei 147 Brasschaat Antwerpen 2930",
    "addr:housenumber":"147",
    "addr:postcode":"2930",
    "addr:street":"Bethanie\u0308Lei",
    "iso:country":"BE",
    "sg:address":"Bethani\u00cblei 147",
    "sg:city":"Brasschaat",
    "sg:orig_category":"Boucheries",
    "sg:phone":"+32 3 663 42 38",
    "sg:postcode":"2930",
    "sg:province":"Antwerpen",
    "wof:name":"Walter De Clerck",
    "wof:placetype":"venue"
},
  "geometry": {"coordinates":[4.5083928108,51.3174057007],"type":"Point"}
}