{
  "type": "Feature",
  "properties": {
    "iso:country":"BE",
    "sg:address":"Sleidingedorp 33",
    "sg:city":"Evergem",
    "sg:orig_category":"M\u00e9decins and sp\u00e9cialistes",
    "sg:phone":"+32 9 357 49 39",
    "sg:postcode":"9940",
    "sg:province":"Oost-Vlaanderen",
    "wof:name":"Peter Matthys",
    "wof:placetype":"venue"
},
  "geometry": {"coordinates":[3.6793479919,51.1327285767],"type":"Point"}
}