{
  "type": "Feature",
  "properties": {
    "addr:full":"Rue Des Combattants 1 Mouscron Hainaut 7700",
    "addr:housenumber":"1",
    "addr:postcode":"7700",
    "addr:street":"Rue Des Combattants",
    "iso:country":"BE",
    "sg:address":"Rue Des Combattants 1",
    "sg:city":"Mouscron",
    "sg:classifiers":[
        {
            "category":"Shopping",
            "subcategory":"Shoes",
            "type":"Retail Goods"
        }
    ],
    "sg:phone":"+32 56 84 42 30",
    "sg:postcode":"7700",
    "sg:province":"Hainaut",
    "sg:tags":[
        "slipper",
        "-"
    ],
    "wof:name":"Maury",
    "wof:placetype":"venue"
},
  "geometry": {"coordinates":[3.2004520893,50.7410812378],"type":"Point"}
}