{
  "type": "Feature",
  "properties": {
    "addr:full":"Nijverheidsstraat 10 Oostkamp West-Vlaanderen 8020",
    "addr:housenumber":"10",
    "addr:postcode":"8020",
    "addr:street":"Nijverheidsstraat",
    "iso:country":"BE",
    "sg:address":"Nijverheidsstraat 10",
    "sg:city":"Oostkamp",
    "sg:orig_category":"Metaalvrije afvalrecyclage",
    "sg:phone":"+32 50 82 65 32",
    "sg:postcode":"8020",
    "sg:province":"West-Vlaanderen",
    "wof:name":"Galdimop",
    "wof:placetype":"venue"
},
  "geometry": {"coordinates":[3.2574961185,51.1265525818],"type":"Point"}
}