{
  "type": "Feature",
  "properties": {
    "iso:country":"BE",
    "sg:address":"Keerstraat 10",
    "sg:city":"Erpe-mere",
    "sg:orig_category":"Imprimeries and copyshops. Secr\u00e9tariats. Composition and photogravure",
    "sg:phone":"+32 53 82 03 11",
    "sg:postcode":"9420",
    "sg:province":"Oost-Vlaanderen",
    "wof:name":"Het Volk Printing",
    "wof:placetype":"venue"
},
  "geometry": {"coordinates":[3.9468040466,50.9317855835],"type":"Point"}
}