{
  "type": "Feature",
  "properties": {
    "iso:country":"BE",
    "sg:address":"Hoge Kouter 3",
    "sg:city":"Sint-martens-latem",
    "sg:orig_category":"Belastingconsulenten Diverse juridische dienstverlening",
    "sg:phone":"+32 9 281 13 33",
    "sg:postcode":"9830",
    "sg:province":"Oost-Vlaanderen",
    "wof:name":"A.b.f.",
    "wof:placetype":"venue"
},
  "geometry": {"coordinates":[3.6366279125,51.0143013],"type":"Point"}
}