{
  "type": "Feature",
  "properties": {
    "iso:country":"BE",
    "sg:address":"Oude Baan 175",
    "sg:city":"Maasmechelen",
    "sg:orig_category":"Enseignement maternel and primaire",
    "sg:phone":"+32 89 76 47 67",
    "sg:postcode":"3630",
    "sg:province":"Limburg",
    "wof:name":"Vrije Kleuterschool",
    "wof:placetype":"venue"
},
  "geometry": {"coordinates":[5.6923718452,50.9809684753],"type":"Point"}
}