{
  "type": "Feature",
  "properties": {
    "addr:full":"Mechelsesteenweg 207 Zaventem Vlaams-Brabant 1933",
    "addr:housenumber":"207",
    "addr:postcode":"1933",
    "addr:street":"Mechelsesteenweg",
    "iso:country":"BE",
    "sg:address":"Mechelsesteenweg 207",
    "sg:city":"Zaventem",
    "sg:orig_category":"Supermarkten",
    "sg:phone":"+32 2 731 23 54",
    "sg:postcode":"1933",
    "sg:province":"Vlaams-Brabant",
    "wof:name":"Gb Contact",
    "wof:placetype":"venue"
},
  "geometry": {"coordinates":[4.51475811,50.8618202209],"type":"Point"}
}