{
  "type": "Feature",
  "properties": {
    "addr:full":"Avenue Roi Albert 60 Andenne Namur 5300",
    "addr:housenumber":"60",
    "addr:postcode":"5300",
    "addr:street":"Avenue Roi Albert",
    "iso:country":"BE",
    "sg:address":"Avenue Roi Albert 60",
    "sg:city":"Andenne",
    "sg:orig_category":"Entretien and r\u00e9parations de voitures",
    "sg:phone":"+32 85 84 48 65",
    "sg:postcode":"5300",
    "sg:province":"Namur",
    "wof:name":"Carrosserie Andennaise",
    "wof:placetype":"venue"
},
  "geometry": {"coordinates":[5.0999069214,50.4920845032],"type":"Point"}
}