{
  "type": "Feature",
  "properties": {
    "addr:full":"Hippodroomlaan 161 Zaventem (sterrebeek) Vlaams-Brabant 1933",
    "addr:housenumber":"161",
    "addr:postcode":"1933",
    "addr:street":"Hippodroomlaan",
    "iso:country":"BE",
    "sg:address":"Hippodroomlaan 161",
    "sg:city":"Zaventem (sterrebeek)",
    "sg:classifiers":[
        {
            "category":"Health Services",
            "subcategory":"Doctor",
            "type":"Services"
        }
    ],
    "sg:phone":"+32 2 784 30 03",
    "sg:postcode":"1933",
    "sg:province":"Vlaams-Brabant",
    "sg:tags":[
        "medicinephysicians",
        "surgeon"
    ],
    "wof:name":"Goethals Peter",
    "wof:placetype":"venue"
},
  "geometry": {"coordinates":[4.5049109459,50.8504676819],"type":"Point"}
}