{
  "type": "Feature",
  "properties": {
    "iso:country":"BE",
    "sg:address":"Vismarkt 18 Box 3",
    "sg:city":"Tessenderlo",
    "sg:classifiers":[
        {
            "category":"Wholesale",
            "subcategory":"Chemicals & Plastics",
            "type":"Manufacturing & Wholesale Goods"
        }
    ],
    "sg:phone":"+32 13 67 23 46",
    "sg:postcode":"3980",
    "sg:province":"Limburg",
    "sg:tags":[
        "packing"
    ],
    "wof:name":"Printopack Nv",
    "wof:placetype":"venue"
},
  "geometry": {"coordinates":[5.091255188,51.0710372925],"type":"Point"}
}