{
  "type": "Feature",
  "properties": {
    "iso:country":"BE",
    "sg:address":"Oostrozebekestraat 190",
    "sg:city":"Ingelmunster",
    "sg:orig_category":"Dakwerken",
    "sg:phone":"+32 51 31 06 88",
    "sg:postcode":"8770",
    "sg:province":"West-Vlaanderen",
    "wof:name":"Dakwerken Danny Lefevre",
    "wof:placetype":"venue"
},
  "geometry": {"coordinates":[3.271668911,50.9182281494],"type":"Point"}
}