{
  "type": "Feature",
  "properties": {
    "iso:country":"BE",
    "sg:address":"Rue Bonne-fontaine 2",
    "sg:city":"Florennes (hanzinelle)",
    "sg:classifiers":[
        {
            "category":"Real Estate",
            "subcategory":"Architect",
            "type":"Services"
        }
    ],
    "sg:phone":"+32 71 50 51 21",
    "sg:postcode":"5621",
    "sg:province":"Namur",
    "wof:name":"Queriat E",
    "wof:placetype":"venue"
},
  "geometry": {"coordinates":[4.5218901634,50.2940788269],"type":"Point"}
}