{
  "type": "Feature",
  "properties": {
    "addr:full":"Rue Henri Maus 58 Li\u00e8ge 1 Li\u00e8ge 4000",
    "addr:housenumber":"58;1",
    "addr:postcode":"4000",
    "addr:street":"Rue Henri Maus",
    "iso:country":"BE",
    "sg:address":"Rue Henri Maus 58",
    "sg:city":"Li\u00e8ge 1",
    "sg:classifiers":[
        {
            "category":"Personal",
            "subcategory":"Barber",
            "type":"Services"
        }
    ],
    "sg:phone":"+32 4 252 87 35",
    "sg:postcode":"4000",
    "sg:province":"Li\u00e8ge",
    "sg:tags":[
        "gentleman",
        "salon",
        "-",
        "hairdressing"
    ],
    "wof:name":"Jamotte R",
    "wof:placetype":"venue"
},
  "geometry": {"coordinates":[5.5566120148,50.6333427429],"type":"Point"}
}