{
  "type": "Feature",
  "properties": {
    "addr:full":"Schansstraat 66 Heusden-zolder Limburg 3550",
    "addr:housenumber":"66",
    "addr:postcode":"3550",
    "addr:street":"Schansstraat",
    "iso:country":"BE",
    "sg:address":"Schansstraat 66",
    "sg:city":"Heusden-zolder",
    "sg:orig_category":"Architecten",
    "sg:phone":"+32 11 57 25 42",
    "sg:postcode":"3550",
    "sg:province":"Limburg",
    "wof:name":"Ceyssens",
    "wof:placetype":"venue"
},
  "geometry": {"coordinates":[5.2961301804,51.0402297974],"type":"Point"}
}