{
  "type": "Feature",
  "properties": {
    "iso:country":"BE",
    "sg:address":"Rue D'armenti\u00c8res 146",
    "sg:city":"Komen-waasten/comines-warneton",
    "sg:classifiers":[
        {
            "category":"Cafe",
            "type":"Food & Drink"
        }
    ],
    "sg:phone":"+32 56 58 71 21",
    "sg:postcode":"7782",
    "sg:province":"Hainaut",
    "sg:tags":[
        "caf\u00e9s"
    ],
    "wof:name":"Caf\u00c9 Du Stade",
    "wof:placetype":"venue"
},
  "geometry": {"coordinates":[2.8812010288,50.7251358032],"type":"Point"}
}