{
  "type": "Feature",
  "properties": {
    "iso:country":"BE",
    "sg:address":"Oudenaardestraat 19",
    "sg:city":"Anzegem",
    "sg:orig_category":"Installation de menuiserie m\u00e9tallique. Installation de menuiserie en bois and plastique",
    "sg:phone":"+32 56 77 71 44",
    "sg:postcode":"8570",
    "sg:province":"West-Vlaanderen",
    "wof:name":"Van Den Bossshe & Dutoit",
    "wof:placetype":"venue"
},
  "geometry": {"coordinates":[3.4054620266,50.8384628296],"type":"Point"}
}