{
  "type": "Feature",
  "properties": {
    "addr:full":"Rue A. Criquelion 3 Jurbise Hainaut 7050",
    "addr:housenumber":"3",
    "addr:postcode":"7050",
    "addr:street":"Rue A. Criquelion",
    "iso:country":"BE",
    "sg:address":"Rue A. Criquelion 3",
    "sg:city":"Jurbise",
    "sg:orig_category":"Loodgieterij, verwarming and sanitaire installaties",
    "sg:phone":"+32 65 22 94 85",
    "sg:postcode":"7050",
    "sg:province":"Hainaut",
    "wof:name":"Georges Escouflaire",
    "wof:placetype":"venue"
},
  "geometry": {"coordinates":[3.9151980877,50.5188369751],"type":"Point"}
}