{
  "type": "Feature",
  "properties": {
    "iso:country":"BE",
    "sg:address":"Rte De Poix 50",
    "sg:city":"Saint-hubert",
    "sg:classifiers":[
        {
            "category":"Restaurant",
            "type":"Food & Drink"
        }
    ],
    "sg:phone":"+32 61 61 30 22",
    "sg:postcode":"6870",
    "sg:province":"Luxembourg",
    "wof:name":"Le Colombier",
    "wof:placetype":"venue"
},
  "geometry": {"coordinates":[5.3542528152,50.024810791],"type":"Point"}
}