{
  "type": "Feature",
  "properties": {
    "addr:full":"Parkstraat 11b1 Overpelt Limburg 3900",
    "addr:housenumber":"11b1",
    "addr:postcode":"3900",
    "addr:street":"Parkstraat",
    "iso:country":"BE",
    "sg:address":"Parkstraat 11b1",
    "sg:city":"Overpelt",
    "sg:classifiers":[
        {
            "category":"Restaurant",
            "type":"Food & Drink"
        }
    ],
    "sg:phone":"+32 11 66 64 23",
    "sg:postcode":"3900",
    "sg:province":"Limburg",
    "wof:name":"Taverne Curiosa",
    "wof:placetype":"venue"
},
  "geometry": {"coordinates":[5.4039950371,51.193572998],"type":"Point"}
}