{
  "type": "Feature",
  "properties": {
    "iso:country":"BE",
    "sg:address":"Rue Pont-al'fosse 21",
    "sg:city":"Philippeville",
    "sg:orig_category":"V\u00e9t\u00e9rinaires",
    "sg:phone":"+32 71 66 82 64",
    "sg:postcode":"5600",
    "sg:province":"Namur",
    "wof:name":"Serge Stoquart",
    "wof:placetype":"venue"
},
  "geometry": {"coordinates":[4.5856618881,50.1465530396],"type":"Point"}
}