{
  "type": "Feature",
  "properties": {
    "addr:full":"Rue Charles Bouvier 105 Namur (bouge) Namur 5004",
    "addr:housenumber":"105",
    "addr:postcode":"5004",
    "addr:street":"Rue Charles Bouvier",
    "iso:country":"BE",
    "sg:address":"Rue Charles Bouvier 105",
    "sg:city":"Namur (bouge)",
    "sg:classifiers":[
        {
            "category":"Health Services",
            "subcategory":"Doctor",
            "type":"Services"
        }
    ],
    "sg:phone":"+32 81 21 40 61",
    "sg:postcode":"5004",
    "sg:province":"Namur",
    "sg:tags":[
        "medicinephysicians",
        "surgeon"
    ],
    "wof:name":"Le Ngoc Bich",
    "wof:placetype":"venue"
},
  "geometry": {"coordinates":[4.8768119812,50.4789237976],"type":"Point"}
}