{
  "type": "Feature",
  "properties": {
    "iso:country":"BE",
    "sg:address":"Aardeweg 44",
    "sg:city":"Overijse",
    "sg:orig_category":"Producteurs de l\u00e9gumes",
    "sg:phone":"+32 2 687 34 66",
    "sg:postcode":"3090",
    "sg:province":"Vlaams-Brabant",
    "wof:name":"Rene Renders",
    "wof:placetype":"venue"
},
  "geometry": {"coordinates":[4.5647301674,50.803768158],"type":"Point"}
}