{
  "type": "Feature",
  "properties": {
    "addr:full":"Rue Am\u00c9d\u00c9 Bracke 9 Kraainem/kraainem Vlaams-Brabant 1950",
    "addr:housenumber":"9",
    "addr:postcode":"1950",
    "addr:street":"Rue Ame\u0301De\u0301 Bracke",
    "iso:country":"BE",
    "sg:address":"Rue Am\u00c9d\u00c9 Bracke 9",
    "sg:city":"Kraainem/kraainem",
    "sg:orig_category":"Ordinateurs and \u00e9quipement informatique. R\u00e9alisation de programmes and logiciels",
    "sg:phone":"+32 2 720 82 28",
    "sg:postcode":"1950",
    "sg:province":"Vlaams-Brabant",
    "wof:name":"Fastwrite",
    "wof:placetype":"venue"
},
  "geometry": {"coordinates":[4.4545431137,50.8633384705],"type":"Point"}
}