{
  "type": "Feature",
  "properties": {
    "addr:full":"Rue Albert I 2 Anderlues Hainaut 6150",
    "addr:housenumber":"2",
    "addr:postcode":"6150",
    "addr:street":"Rue Albert I",
    "iso:country":"BE",
    "sg:address":"Rue Albert I 2",
    "sg:city":"Anderlues",
    "sg:classifiers":[
        {
            "category":"Personal",
            "subcategory":"Beauty Salon",
            "type":"Services"
        }
    ],
    "sg:phone":"+32 71 54 03 54",
    "sg:postcode":"6150",
    "sg:province":"Hainaut",
    "sg:tags":[
        "lady",
        "-",
        "hairdressing"
    ],
    "wof:name":"Elle & Lui",
    "wof:placetype":"venue"
},
  "geometry": {"coordinates":[4.2712740898,50.4062995911],"type":"Point"}
}