{
  "type": "Feature",
  "properties": {
    "iso:country":"BE",
    "sg:address":"Rue De Haut Bois 32",
    "sg:city":"Gesves (haltinne)",
    "sg:classifiers":[
        {
            "category":"Retail",
            "subcategory":"Auto Repair",
            "type":"Services"
        }
    ],
    "sg:phone":"+32 83 67 79 82",
    "sg:postcode":"5340",
    "sg:province":"Namur",
    "sg:tags":[
        "garage"
    ],
    "wof:name":"Blom L (garage)",
    "wof:placetype":"venue"
},
  "geometry": {"coordinates":[5.0729598999,50.4330673218],"type":"Point"}
}