{
  "type": "Feature",
  "properties": {
    "addr:full":"Kerkstraat 38 Arendonk Antwerpen 2370",
    "addr:housenumber":"38",
    "addr:postcode":"2370",
    "addr:street":"Kerkstraat",
    "iso:country":"BE",
    "sg:address":"Kerkstraat 38",
    "sg:city":"Arendonk",
    "sg:orig_category":"Protection civile",
    "sg:phone":"+32 14 67 76 84",
    "sg:postcode":"2370",
    "sg:province":"Antwerpen",
    "wof:name":"Brandweerkazerne",
    "wof:placetype":"venue"
},
  "geometry": {"coordinates":[5.0846138,51.316783905],"type":"Point"}
}