{
  "type": "Feature",
  "properties": {
    "addr:full":"Rue D'arnelle 11 Longueville Brabant Wallon 1325",
    "addr:housenumber":"11",
    "addr:postcode":"1325",
    "addr:street":"Rue D'Arnelle",
    "iso:country":"BE",
    "sg:address":"Rue D'arnelle 11",
    "sg:city":"Longueville",
    "sg:orig_category":"Schoonheidssalons",
    "sg:phone":"+32 10 88 04 67",
    "sg:postcode":"1325",
    "sg:province":"Brabant Wallon",
    "wof:name":"Antinea",
    "wof:placetype":"venue"
},
  "geometry": {"coordinates":[4.7424240112,50.6996765137],"type":"Point"}
}