{
  "type": "Feature",
  "properties": {
    "iso:country":"BE",
    "sg:address":"Antwerpsesteenweg 189",
    "sg:city":"Leopoldsburg",
    "sg:classifiers":[
        {
            "category":"Retail",
            "subcategory":"Auto Repair",
            "type":"Services"
        }
    ],
    "sg:phone":"+32 11 34 21 47",
    "sg:postcode":"3970",
    "sg:province":"Limburg",
    "sg:tags":[
        "garage"
    ],
    "wof:name":"Auto's Koen",
    "wof:placetype":"venue"
},
  "geometry": {"coordinates":[5.2410049438,51.1332550049],"type":"Point"}
}