{
  "type": "Feature",
  "properties": {
    "iso:country":"BE",
    "sg:address":"(null)",
    "sg:city":"Lo-reninge",
    "sg:classifiers":[
        {
            "category":"Professional",
            "type":"Services"
        }
    ],
    "sg:phone":"+32 57 40 07 71",
    "sg:postcode":"8647",
    "sg:province":"West-Vlaanderen",
    "sg:tags":[
        "aux",
        "diver",
        "personnes"
    ],
    "wof:name":"'t Convent",
    "wof:placetype":"venue"
},
  "geometry": {"coordinates":[2.7487149239,50.9805717468],"type":"Point"}
}