{
  "type": "Feature",
  "properties": {
    "addr:full":"Luikersteenweg 122 Hasselt Limburg 3500",
    "addr:housenumber":"122",
    "addr:postcode":"3500",
    "addr:street":"Luikersteenweg",
    "iso:country":"BE",
    "sg:address":"Luikersteenweg 122",
    "sg:city":"Hasselt",
    "sg:orig_category":"Artsen and specialisten",
    "sg:phone":"+32 11 24 10 00",
    "sg:postcode":"3500",
    "sg:province":"Limburg",
    "wof:name":"Dominique Bouts",
    "wof:placetype":"venue"
},
  "geometry": {"coordinates":[5.3408322334,50.9226799011],"type":"Point"}
}