{
  "type": "Feature",
  "properties": {
    "iso:country":"BE",
    "sg:address":"Zevekotesteenweg 4",
    "sg:city":"Middelkerke",
    "sg:orig_category":"Rundveehouders Varkenskwekers",
    "sg:phone":"+32 59 27 70 08",
    "sg:postcode":"8432",
    "sg:province":"West-Vlaanderen",
    "wof:name":"Eric Strubbe",
    "wof:placetype":"venue"
},
  "geometry": {"coordinates":[2.8845310211,51.1571998596],"type":"Point"}
}