{
  "type": "Feature",
  "properties": {
    "iso:country":"BE",
    "sg:address":"Rue De Fl\u00e9malle",
    "sg:city":"Seraing (jemeppe-sur-meuse)",
    "sg:classifiers":[
        {
            "category":"Bars & Pubs",
            "type":"Food & Drink"
        }
    ],
    "sg:phone":"+32 4 234 18 58",
    "sg:postcode":"4101",
    "sg:province":"Li\u00e8ge",
    "wof:name":"Rectification Li\u00e9geoise",
    "wof:placetype":"venue"
},
  "geometry": {"coordinates":[5.4871602058,50.6064567566],"type":"Point"}
}