{
  "type": "Feature",
  "properties": {
    "addr:full":"Hans Memlingstraat 12 Oostkamp West-Vlaanderen 8020",
    "addr:housenumber":"12",
    "addr:postcode":"8020",
    "addr:street":"Hans Memlingstraat",
    "iso:country":"BE",
    "sg:address":"Hans Memlingstraat 12",
    "sg:city":"Oostkamp",
    "sg:orig_category":"Artiesten and kunstenaars",
    "sg:phone":"+32 50 82 40 69",
    "sg:postcode":"8020",
    "sg:province":"West-Vlaanderen",
    "wof:name":"Riahi",
    "wof:placetype":"venue"
},
  "geometry": {"coordinates":[3.2276890278,51.1365661621],"type":"Point"}
}