{
  "type": "Feature",
  "properties": {
    "addr:full":"Markt 42 Maaseik Limburg 3680",
    "addr:housenumber":"42",
    "addr:postcode":"3680",
    "addr:street":"Markt",
    "iso:country":"BE",
    "sg:address":"Markt 42",
    "sg:city":"Maaseik",
    "sg:classifiers":[
        {
            "category":"Bars & Pubs",
            "type":"Food & Drink"
        }
    ],
    "sg:phone":"+32 89 56 64 90",
    "sg:postcode":"3680",
    "sg:province":"Limburg",
    "wof:name":"Gulden Ster (de)",
    "wof:placetype":"venue"
},
  "geometry": {"coordinates":[5.791258812,51.0949783325],"type":"Point"}
}