{
  "type": "Feature",
  "properties": {
    "iso:country":"BE",
    "sg:address":"Abdijstraat 53",
    "sg:city":"Assenede (oosteeklo)",
    "sg:classifiers":[
        {
            "category":"Professional",
            "subcategory":"Management & Consulting",
            "type":"Services"
        }
    ],
    "sg:phone":"+32 9 373 80 25",
    "sg:postcode":"9968",
    "sg:province":"Oost-Vlaanderen",
    "sg:tags":[
        "tax-consultants"
    ],
    "wof:name":"Moens D",
    "wof:placetype":"venue"
},
  "geometry": {"coordinates":[3.6861350536,51.1753501892],"type":"Point"}
}