{
  "type": "Feature",
  "properties": {
    "iso:country":"BE",
    "sg:address":"Stadsweg 42 A",
    "sg:city":"Geraardsbergen",
    "sg:orig_category":"Baby- and kinderkleding Dameskledingzaken Herenkledingzaken",
    "sg:phone":"+32 54 41 87 93",
    "sg:postcode":"9500",
    "sg:province":"Oost-Vlaanderen",
    "wof:name":"Promo Fashion",
    "wof:placetype":"venue"
},
  "geometry": {"coordinates":[3.8689579964,50.7706298828],"type":"Point"}
}