{
  "type": "Feature",
  "properties": {
    "iso:country":"BE",
    "sg:address":"Meir 12",
    "sg:city":"Rijkevorsel",
    "sg:orig_category":"Geschenken and souvenirs Textiel",
    "sg:phone":"+32 3 309 21 71",
    "sg:postcode":"2310",
    "sg:province":"Antwerpen",
    "wof:name":"Huis Annik",
    "wof:placetype":"venue"
},
  "geometry": {"coordinates":[4.7826809883,51.32862854],"type":"Point"}
}