{
  "type": "Feature",
  "properties": {
    "iso:country":"BE",
    "sg:address":"Rue Int\u00c9rieure 7",
    "sg:city":"Beaumont",
    "sg:orig_category":"Vakantiehuizen",
    "sg:phone":"+32 71 58 98 20",
    "sg:postcode":"6500",
    "sg:province":"Hainaut",
    "wof:name":"D. Van De Sype",
    "wof:placetype":"venue"
},
  "geometry": {"coordinates":[4.2461647987,50.214630127],"type":"Point"}
}