{
  "type": "Feature",
  "properties": {
    "addr:full":"Korhaanstraat 5 Turnhout Antwerpen 2300",
    "addr:housenumber":"5",
    "addr:postcode":"2300",
    "addr:street":"Korhaanstraat",
    "iso:country":"BE",
    "sg:address":"Korhaanstraat 5",
    "sg:city":"Turnhout",
    "sg:classifiers":[
        {
            "category":"Arts & Performance",
            "subcategory":"Symphony",
            "type":"Entertainment"
        }
    ],
    "sg:phone":"+32 14 43 37 97",
    "sg:postcode":"2300",
    "sg:province":"Antwerpen",
    "sg:tags":[
        "orchestra"
    ],
    "wof:name":"Kempische Oratoriumvereniging",
    "wof:placetype":"venue"
},
  "geometry": {"coordinates":[4.9381399155,51.3092269897],"type":"Point"}
}