{
  "type": "Feature",
  "properties": {
    "iso:country":"BE",
    "sg:address":"Rue Du Prol 14b",
    "sg:city":"Renaix",
    "sg:classifiers":[
        {
            "category":"Health Services",
            "subcategory":"Doctor",
            "type":"Services"
        }
    ],
    "sg:phone":"+32 55 20 97 07",
    "sg:postcode":"9600",
    "sg:province":"Oost-Vlaanderen",
    "sg:tags":[
        "medicinephysicians",
        "surgeon"
    ],
    "wof:name":"Hoste Siegfried",
    "wof:placetype":"venue"
},
  "geometry": {"coordinates":[3.6401851177,50.7599449158],"type":"Point"}
}