{
  "type": "Feature",
  "properties": {
    "addr:full":"Land Van Waaslaan 165 Sint-amandsberg Oost-Vlaanderen 9040",
    "addr:housenumber":"165",
    "addr:postcode":"9040",
    "addr:street":"Land Van Waaslaan",
    "iso:country":"BE",
    "sg:address":"Land Van Waaslaan 165",
    "sg:city":"Sint-amandsberg",
    "sg:orig_category":"Balie van Gent. Avocats and conseillers juridiques",
    "sg:phone":"+32 9 229 10 23",
    "sg:postcode":"9040",
    "sg:province":"Oost-Vlaanderen",
    "wof:name":"Buyst Luc",
    "wof:placetype":"venue"
},
  "geometry": {"coordinates":[3.7479860783,51.0588150024],"type":"Point"}
}