{
  "type": "Feature",
  "properties": {
    "iso:country":"BE",
    "sg:address":"Rue Ry D'ao\u00fbt 12",
    "sg:city":"Yvoir (spontin)",
    "sg:classifiers":[
        {
            "category":"Building & Trades",
            "subcategory":"Construction",
            "type":"Services"
        }
    ],
    "sg:phone":"+32 83 69 98 50",
    "sg:postcode":"5530",
    "sg:province":"Namur",
    "sg:tags":[
        "installation",
        "-",
        "central",
        "heating"
    ],
    "wof:name":"Lombet-colen",
    "wof:placetype":"venue"
},
  "geometry": {"coordinates":[4.9861707687,50.3179244995],"type":"Point"}
}