{
  "type": "Feature",
  "properties": {
    "addr:full":"Prins Van Oranjestraat 4 Brasschaat Antwerpen 2930",
    "addr:housenumber":"4",
    "addr:postcode":"2930",
    "addr:street":"Prins Van Oranjestraat",
    "iso:country":"BE",
    "sg:address":"Prins Van Oranjestraat 4",
    "sg:city":"Brasschaat",
    "sg:classifiers":[
        {
            "category":"Arena",
            "subcategory":"Sports Club",
            "type":"Entertainment"
        }
    ],
    "sg:phone":"+32 3 651 71 07",
    "sg:postcode":"2930",
    "sg:province":"Antwerpen",
    "sg:tags":[
        "de"
    ],
    "wof:name":"Kon. Brassch. Duivenbond",
    "wof:placetype":"venue"
},
  "geometry": {"coordinates":[4.5017938614,51.2943077087],"type":"Point"}
}