{
  "type": "Feature",
  "properties": {
    "iso:country":"BE",
    "sg:address":"Tiensesteenweg 112",
    "sg:city":"Leuven (heverlee)",
    "sg:classifiers":[
        {
            "category":"Autos & Motor Vehicles",
            "subcategory":"Motorcycle Sales",
            "type":"Retail Goods"
        }
    ],
    "sg:phone":"+32 16 25 94 83",
    "sg:postcode":"3001",
    "sg:province":"Vlaams-Brabant",
    "sg:tags":[
        "scooter",
        "-",
        "moped"
    ],
    "wof:name":"Tivoli Moto's Bvba",
    "wof:placetype":"venue"
},
  "geometry": {"coordinates":[4.7151021957,50.876373291],"type":"Point"}
}