{
  "type": "Feature",
  "properties": {
    "iso:country":"BE",
    "sg:address":"Dendermondsesteenweg 322",
    "sg:city":"Destelbergen",
    "sg:orig_category":"Mat\u00e9riel de T\u00e9l\u00e9communication. Installation \u00e9lectrique r\u00e9sidentielle",
    "sg:phone":"+32 9 238 31 37",
    "sg:postcode":"9070",
    "sg:province":"Oost-Vlaanderen",
    "wof:name":"Jimco",
    "wof:placetype":"venue"
},
  "geometry": {"coordinates":[3.7896049023,51.0560455322],"type":"Point"}
}