{
  "type": "Feature",
  "properties": {
    "addr:full":"Wegvoeringstraat 25 Wetteren Oost-Vlaanderen 9230",
    "addr:housenumber":"25",
    "addr:postcode":"9230",
    "addr:street":"Wegvoeringstraat",
    "iso:country":"BE",
    "sg:address":"Wegvoeringstraat 25",
    "sg:city":"Wetteren",
    "sg:orig_category":"Kantoormateriaal",
    "sg:phone":"+32 9 369 02 24",
    "sg:postcode":"9230",
    "sg:province":"Oost-Vlaanderen",
    "wof:name":"L. Praet",
    "wof:placetype":"venue"
},
  "geometry": {"coordinates":[3.8877799511,51.0074996948],"type":"Point"}
}