{
  "type": "Feature",
  "properties": {
    "addr:full":"Haachtsesteenweg 879 Evere/evere Bruxelles-Capitale 1140",
    "addr:housenumber":"879",
    "addr:postcode":"1140",
    "addr:street":"Haachtsesteenweg",
    "iso:country":"BE",
    "sg:address":"Haachtsesteenweg 879",
    "sg:city":"Evere/evere",
    "sg:orig_category":"Metaalafval, schrootrecyclage and sloperijen Onderdelen and accessoires voor auto's Voertuigen",
    "sg:phone":"+32 2 242 17 77",
    "sg:postcode":"1140",
    "sg:province":"Bruxelles-Capitale",
    "wof:name":"Suzuki",
    "wof:placetype":"venue"
},
  "geometry": {"coordinates":[4.3981389999,50.87266922],"type":"Point"}
}