{
  "type": "Feature",
  "properties": {
    "iso:country":"BE",
    "sg:address":"Autolei 157",
    "sg:city":"Wommelgem",
    "sg:orig_category":"Kantoormateriaal Gh",
    "sg:phone":"+32 3 366 37 27",
    "sg:postcode":"2160",
    "sg:province":"Antwerpen",
    "wof:name":"Everdata Belgium",
    "wof:placetype":"venue"
},
  "geometry": {"coordinates":[4.4888701439,51.2063598633],"type":"Point"}
}