{
  "type": "Feature",
  "properties": {
    "iso:country":"BE",
    "sg:address":"Preenakker 3 Industriezone D",
    "sg:city":"Merchtem",
    "sg:classifiers":[
        {
            "category":"Wholesale",
            "subcategory":"Medical Equipment & Supplies",
            "type":"Manufacturing & Wholesale Goods"
        }
    ],
    "sg:phone":"+32 52 37 01 09",
    "sg:postcode":"1785",
    "sg:province":"Vlaams-Brabant",
    "sg:tags":[
        "device",
        "emergency"
    ],
    "wof:name":"Importexco S.p.r.l.",
    "wof:placetype":"venue"
},
  "geometry": {"coordinates":[4.2317490578,50.9585723877],"type":"Point"}
}