{
  "type": "Feature",
  "properties": {
    "addr:full":"Oudestraat 34 Bree Limburg 3960",
    "addr:housenumber":"34",
    "addr:postcode":"3960",
    "addr:street":"Oudestraat",
    "iso:country":"BE",
    "sg:address":"Oudestraat 34",
    "sg:city":"Bree",
    "sg:classifiers":[
        {
            "category":"Health Services",
            "subcategory":"Health Practitioner",
            "type":"Services"
        }
    ],
    "sg:phone":"+32 89 46 81 26",
    "sg:postcode":"3960",
    "sg:province":"Limburg",
    "sg:tags":[
        "psychologist"
    ],
    "wof:name":"Claes S",
    "wof:placetype":"venue"
},
  "geometry": {"coordinates":[5.5971307755,51.1378173828],"type":"Point"}
}