{
  "type": "Feature",
  "properties": {
    "addr:full":"Ropstraat 25 Beveren Oost-Vlaanderen 9120",
    "addr:housenumber":"25",
    "addr:postcode":"9120",
    "addr:street":"Ropstraat",
    "iso:country":"BE",
    "sg:address":"Ropstraat 25",
    "sg:city":"Beveren",
    "sg:orig_category":"Eleveurs de volaille. Eleveurs de bovins",
    "sg:phone":"+32 3 775 87 02",
    "sg:postcode":"9120",
    "sg:province":"Oost-Vlaanderen",
    "wof:name":"Jozef Stuer",
    "wof:placetype":"venue"
},
  "geometry": {"coordinates":[4.2296929359,51.1807289124],"type":"Point"}
}