{
  "type": "Feature",
  "properties": {
    "iso:country":"BE",
    "sg:address":"Torhoutse Baan 1",
    "sg:city":"Gistel",
    "sg:orig_category":"Cr\u00e9meries",
    "sg:phone":"+32 59 27 87 63",
    "sg:postcode":"8470",
    "sg:province":"West-Vlaanderen",
    "wof:name":"C Vannieuwenhuyse",
    "wof:placetype":"venue"
},
  "geometry": {"coordinates":[2.9540970325,51.1492271423],"type":"Point"}
}