{
  "type": "Feature",
  "properties": {
    "iso:country":"BE",
    "sg:address":"Brusselsestraat 152",
    "sg:city":"Leuven",
    "sg:orig_category":"Landmeters",
    "sg:phone":"+32 16 20 41 98",
    "sg:postcode":"3000",
    "sg:province":"Vlaams-Brabant",
    "wof:name":"Casier Patrick",
    "wof:placetype":"venue"
},
  "geometry": {"coordinates":[4.6929039955,50.8808555603],"type":"Point"}
}