{
  "type": "Feature",
  "properties": {
    "addr:full":"All\u00c9e Des Peupliers 15 Gerpinnes Hainaut 6280",
    "addr:housenumber":"15",
    "addr:postcode":"6280",
    "addr:street":"Alle\u0301E Des Peupliers;Hainaut",
    "iso:country":"BE",
    "sg:address":"All\u00c9e Des Peupliers 15",
    "sg:city":"Gerpinnes",
    "sg:orig_category":"D\u00e9corateurs d'int\u00e9rieur",
    "sg:phone":"+32 71 22 09 30",
    "sg:postcode":"6280",
    "sg:province":"Hainaut",
    "wof:name":"L.m.",
    "wof:placetype":"venue"
},
  "geometry": {"coordinates":[4.4768509865,50.3478164673],"type":"Point"}
}