{
  "type": "Feature",
  "properties": {
    "addr:full":"Blanc-pignonstraat 183 Moeskroen/mouscron Hainaut 7700",
    "addr:housenumber":"183",
    "addr:postcode":"7700",
    "addr:street":"Moeskroen",
    "iso:country":"BE",
    "sg:address":"Blanc-pignonstraat 183",
    "sg:city":"Moeskroen/mouscron",
    "sg:orig_category":"Paramedische behandelingen",
    "sg:phone":"+32 56 34 25 18",
    "sg:postcode":"7700",
    "sg:province":"Hainaut",
    "wof:name":"M.j. Dehem",
    "wof:placetype":"venue"
},
  "geometry": {"coordinates":[3.2323200703,50.7400932312],"type":"Point"}
}