{
  "type": "Feature",
  "properties": {
    "addr:full":"Zonhoevestraat 1a Bilzen (beverst) Limburg 3740",
    "addr:housenumber":"1a",
    "addr:postcode":"3740",
    "addr:street":"Zonhoevestraat",
    "iso:country":"BE",
    "sg:address":"Zonhoevestraat 1a",
    "sg:city":"Bilzen (beverst)",
    "sg:classifiers":[
        {
            "category":"Home & Garden",
            "subcategory":"Building Materials",
            "type":"Retail Goods"
        }
    ],
    "sg:phone":"+32 89 41 65 16",
    "sg:postcode":"3740",
    "sg:province":"Limburg",
    "sg:tags":[
        "wall",
        "cupboard"
    ],
    "wof:name":"Bollen M",
    "wof:placetype":"venue"
},
  "geometry": {"coordinates":[5.4740400314,50.8901748657],"type":"Point"}
}