{
  "type": "Feature",
  "properties": {
    "iso:country":"BE",
    "sg:address":"Rue De La Croy\u00e8re 55",
    "sg:city":"La Louvi\u00e8re",
    "sg:classifiers":[
        {
            "category":"Personal",
            "subcategory":"Beauty Salon",
            "type":"Services"
        }
    ],
    "sg:phone":"+32 64 21 35 29",
    "sg:postcode":"7100",
    "sg:province":"Hainaut",
    "sg:tags":[
        "lady",
        "-",
        "hairdressing"
    ],
    "wof:name":"Marie-louise",
    "wof:placetype":"venue"
},
  "geometry": {"coordinates":[4.2004871368,50.4887008667],"type":"Point"}
}