{
  "type": "Feature",
  "properties": {
    "iso:country":"BE",
    "sg:address":"Lucas Munichstraat 84",
    "sg:city":"Gent",
    "sg:classifiers":[
        {
            "category":"Professional",
            "subcategory":"Art Services",
            "type":"Services"
        }
    ],
    "sg:phone":"+32 9 224 44 22",
    "sg:postcode":"9000",
    "sg:province":"Oost-Vlaanderen",
    "sg:tags":[
        "graphic",
        "designer"
    ],
    "wof:name":"Vermeire A",
    "wof:placetype":"venue"
},
  "geometry": {"coordinates":[3.7368481159,51.0554695129],"type":"Point"}
}