{
  "type": "Feature",
  "properties": {
    "addr:full":"Sijselestraat 29 Beernem (oedelem) West-Vlaanderen 8730",
    "addr:housenumber":"29",
    "addr:postcode":"8730",
    "addr:street":"Sijselestraat",
    "iso:country":"BE",
    "sg:address":"Sijselestraat 29",
    "sg:city":"Beernem (oedelem)",
    "sg:classifiers":[
        {
            "category":"Real Estate",
            "subcategory":"Architect",
            "type":"Services"
        }
    ],
    "sg:phone":"+32 50 79 13 40",
    "sg:postcode":"8730",
    "sg:province":"West-Vlaanderen",
    "wof:name":"Compernolle P",
    "wof:placetype":"venue"
},
  "geometry": {"coordinates":[3.3408629894,51.143787384],"type":"Point"}
}