{
  "type": "Feature",
  "properties": {
    "addr:full":"Onze Lieve Vrouwstraat 9ba Bilzen Limburg 3740",
    "addr:postcode":"9ba bilzen;3740",
    "addr:street":"Onze Lieve Vrouwstraat",
    "iso:country":"BE",
    "sg:address":"Onze Lieve Vrouwstraat 9ba",
    "sg:city":"Bilzen",
    "sg:classifiers":[
        {
            "category":"Shopping",
            "subcategory":"Clothing, Apparel, & Fashions",
            "type":"Retail Goods"
        }
    ],
    "sg:phone":"+32 89 41 78 77",
    "sg:postcode":"3740",
    "sg:province":"Limburg",
    "sg:tags":[
        "lingerie",
        "sous-v\u00eatements"
    ],
    "wof:name":"Fa. Cocoon",
    "wof:placetype":"venue"
},
  "geometry": {"coordinates":[5.5167350769,50.870136261],"type":"Point"}
}