{
  "type": "Feature",
  "properties": {
    "iso:country":"BE",
    "sg:address":"Leo Duboisstraat 35",
    "sg:city":"Lebbeke",
    "sg:classifiers":[
        {
            "category":"Bars & Pubs",
            "subcategory":"Nightclub",
            "type":"Food & Drink"
        }
    ],
    "sg:phone":"+32 52 41 06 74",
    "sg:postcode":"9280",
    "sg:province":"Oost-Vlaanderen",
    "sg:tags":[
        "nachtclubs",
        "dancing"
    ],
    "wof:name":"Palma",
    "wof:placetype":"venue"
},
  "geometry": {"coordinates":[4.1256828308,50.9997520447],"type":"Point"}
}