{
  "type": "Feature",
  "properties": {
    "iso:country":"BE",
    "sg:address":"Rue De Sart 194a",
    "sg:city":"Stavelot (francorchamps)",
    "sg:classifiers":[
        {
            "category":"Building & Trades",
            "subcategory":"Landscaping Services",
            "type":"Services"
        }
    ],
    "sg:phone":"+32 87 22 55 91",
    "sg:postcode":"4970",
    "sg:province":"Li\u00e8ge",
    "sg:tags":[
        "architect",
        "landscape"
    ],
    "wof:name":"Piette Olivier",
    "wof:placetype":"venue"
},
  "geometry": {"coordinates":[5.9528341293,50.4624252319],"type":"Point"}
}