{
  "type": "Feature",
  "properties": {
    "addr:full":"Schutterijstraat 14 Hechtel-eksel Limburg 3941",
    "addr:housenumber":"14",
    "addr:postcode":"3941",
    "addr:street":"Schutterijstraat",
    "iso:country":"BE",
    "sg:address":"Schutterijstraat 14",
    "sg:city":"Hechtel-eksel",
    "sg:orig_category":"Travaux de pl\u00e2trage",
    "sg:phone":"+32 11 73 60 47",
    "sg:postcode":"3941",
    "sg:province":"Limburg",
    "wof:name":"Ronny Karg",
    "wof:placetype":"venue"
},
  "geometry": {"coordinates":[5.3928489685,51.1582260132],"type":"Point"}
}