{
  "type": "Feature",
  "properties": {
    "addr:full":"Klein Overlaar 8b Hoegaarden Vlaams-Brabant 3320",
    "addr:housenumber":"8b",
    "addr:postcode":"3320",
    "addr:street":"Klein Overlaar",
    "iso:country":"BE",
    "sg:address":"Klein Overlaar 8b",
    "sg:city":"Hoegaarden",
    "sg:orig_category":"Pain, p\u00e2tisseries and confiseries",
    "sg:phone":"+32 16 76 56 10",
    "sg:postcode":"3320",
    "sg:province":"Vlaams-Brabant",
    "wof:name":"Moureau A. & P.",
    "wof:placetype":"venue"
},
  "geometry": {"coordinates":[4.8953709602,50.7795639038],"type":"Point"}
}