{
  "type": "Feature",
  "properties": {
    "addr:full":"Waterstraat 1 Harelbeke (bavikhove) West-Vlaanderen 8531",
    "addr:housenumber":"1",
    "addr:postcode":"8531",
    "addr:street":"Waterstraat",
    "iso:country":"BE",
    "sg:address":"Waterstraat 1",
    "sg:city":"Harelbeke (bavikhove)",
    "sg:classifiers":[
        {
            "category":"Farming",
            "subcategory":"Livestock Farm",
            "type":"Manufacturing & Wholesale Goods"
        }
    ],
    "sg:phone":"+32 56 71 79 96",
    "sg:postcode":"8531",
    "sg:province":"West-Vlaanderen",
    "sg:tags":[
        "buyer"
    ],
    "wof:name":"Amelynck C",
    "wof:placetype":"venue"
},
  "geometry": {"coordinates":[3.2874848843,50.8722915649],"type":"Point"}
}