{
  "type": "Feature",
  "properties": {
    "addr:full":"Welvaartsstr 20 Herentals Antwerpen 2200",
    "addr:housenumber":"20",
    "addr:postcode":"2200",
    "addr:street":"Welvaartsstr",
    "iso:country":"BE",
    "sg:address":"Welvaartsstr 20",
    "sg:city":"Herentals",
    "sg:classifiers":[
        {
            "category":"Professional",
            "type":"Services"
        }
    ],
    "sg:phone":"+32 14 22 05 47",
    "sg:postcode":"2200",
    "sg:province":"Antwerpen",
    "sg:tags":[
        "transport",
        "road"
    ],
    "wof:name":"Jugetra Nv",
    "wof:placetype":"venue"
},
  "geometry": {"coordinates":[4.8027191162,51.1582756042],"type":"Point"}
}