{
  "type": "Feature",
  "properties": {
    "iso:country":"BE",
    "sg:address":"Celestijnenlaan 17 Box 62",
    "sg:city":"Leuven (heverlee)",
    "sg:classifiers":[
        {
            "category":"Real Estate",
            "subcategory":"Architect",
            "type":"Services"
        }
    ],
    "sg:phone":"+32 16 29 12 84",
    "sg:postcode":"3001",
    "sg:province":"Vlaams-Brabant",
    "wof:name":"Mattheus R",
    "wof:placetype":"venue"
},
  "geometry": {"coordinates":[4.6750497818,50.8714866638],"type":"Point"}
}