{
  "type": "Feature",
  "properties": {
    "addr:full":"Chauss\u00c9e De Wavre 1091 Auderghem Bruxelles-Capitale 1160",
    "addr:postcode":"1091;1160",
    "addr:street":"Chausse\u0301E De Wavre",
    "iso:country":"BE",
    "sg:address":"Chauss\u00c9e De Wavre 1091",
    "sg:city":"Auderghem",
    "sg:orig_category":"Herstellingen and onderhoud van auto's Voertuigen",
    "sg:phone":"+32 2 648 06 74",
    "sg:postcode":"1160",
    "sg:province":"Bruxelles-Capitale",
    "wof:name":"Garage Le Souverain",
    "wof:placetype":"venue"
},
  "geometry": {"coordinates":[4.400001049,50.8242607117],"type":"Point"}
}