{
  "type": "Feature",
  "properties": {
    "iso:country":"BE",
    "sg:address":"Kruiskesbos 28",
    "sg:city":"Meise (wolvertem)",
    "sg:classifiers":[
        {
            "category":"Home & Garden",
            "subcategory":"Building Materials",
            "type":"Retail Goods"
        }
    ],
    "sg:phone":"+32 52 30 40 82",
    "sg:postcode":"1861",
    "sg:province":"Vlaams-Brabant",
    "sg:tags":[
        "wall",
        "cupboard"
    ],
    "wof:name":"Van Acoleyen R",
    "wof:placetype":"venue"
},
  "geometry": {"coordinates":[4.3202447891,50.9993972778],"type":"Point"}
}