{
  "type": "Feature",
  "properties": {
    "addr:full":"Stekelbaarsstraat 16 Oosterzele Oost-Vlaanderen 9860",
    "addr:housenumber":"16",
    "addr:postcode":"9860",
    "addr:street":"Stekelbaarsstraat;Oost-Vlaanderen",
    "iso:country":"BE",
    "sg:address":"Stekelbaarsstraat 16",
    "sg:city":"Oosterzele",
    "sg:orig_category":"Geschenken and souvenirs Verlichting and huishoudartikelen",
    "sg:phone":"+32 9 362 09 08",
    "sg:postcode":"9860",
    "sg:province":"Oost-Vlaanderen",
    "wof:name":"Huis Origineel",
    "wof:placetype":"venue"
},
  "geometry": {"coordinates":[3.7775928974,50.960975647],"type":"Point"}
}