{
  "type": "Feature",
  "properties": {
    "addr:full":"Rue De La Vellerie 120 Moeskroen/mouscron Hainaut 7700",
    "addr:housenumber":"120",
    "addr:postcode":"7700",
    "addr:street":"Rue De La Vellerie",
    "iso:country":"BE",
    "sg:address":"Rue De La Vellerie 120",
    "sg:city":"Moeskroen/mouscron",
    "sg:classifiers":[
        {
            "category":"Personal",
            "subcategory":"Beauty Salon",
            "type":"Services"
        }
    ],
    "sg:phone":"+32 56 84 29 92",
    "sg:postcode":"7700",
    "sg:province":"Hainaut",
    "sg:tags":[
        "de",
        "coiffure"
    ],
    "wof:name":"Coiffure Katty",
    "wof:placetype":"venue"
},
  "geometry": {"coordinates":[3.2323200703,50.7400932312],"type":"Point"}
}