{
  "type": "Feature",
  "properties": {
    "addr:full":"Hoornzeelstr 50 Tervuren Vlaams-Brabant 3080",
    "addr:housenumber":"50",
    "addr:postcode":"3080",
    "addr:street":"Hoornzeelstr",
    "iso:country":"BE",
    "sg:address":"Hoornzeelstr 50",
    "sg:city":"Tervuren",
    "sg:classifiers":[
        {
            "category":"Shopping",
            "subcategory":"Luggage & Leather Goods",
            "type":"Retail Goods"
        }
    ],
    "sg:phone":"+32 2 767 24 14",
    "sg:postcode":"3080",
    "sg:province":"Vlaams-Brabant",
    "sg:tags":[
        "shoe"
    ],
    "wof:name":"New Generation Shoes Bvba",
    "wof:placetype":"venue"
},
  "geometry": {"coordinates":[4.5126619339,50.8213119507],"type":"Point"}
}