{
  "type": "Feature",
  "properties": {
    "addr:full":"Koning Boudewijnlaan 4 Hasselt Limburg 3500",
    "addr:housenumber":"4",
    "addr:postcode":"3500",
    "addr:street":"Koning Boudewijnlaan",
    "iso:country":"BE",
    "sg:address":"Koning Boudewijnlaan 4",
    "sg:city":"Hasselt",
    "sg:orig_category":"Drukkerijen and copyshops Kantoormateriaal",
    "sg:phone":"+32 11 26 35 90",
    "sg:postcode":"3500",
    "sg:province":"Limburg",
    "wof:name":"Copyfun",
    "wof:placetype":"venue"
},
  "geometry": {"coordinates":[5.3431711197,50.9330177307],"type":"Point"}
}