{
  "type": "Feature",
  "properties": {
    "addr:full":"Rogierlaan 104 Schaarbeek/schaerbeek Bruxelles-Capitale 1030",
    "addr:housenumber":"104",
    "addr:postcode":"1030",
    "addr:street":"Rogierlaan",
    "iso:country":"BE",
    "sg:address":"Rogierlaan 104",
    "sg:city":"Schaarbeek/schaerbeek",
    "sg:orig_category":"Apotheken",
    "sg:phone":"+32 2 215 99 07",
    "sg:postcode":"1030",
    "sg:province":"Bruxelles-Capitale",
    "wof:name":"Pharbel",
    "wof:placetype":"venue"
},
  "geometry": {"coordinates":[4.3769230843,50.8597106934],"type":"Point"}
}