{
  "type": "Feature",
  "properties": {
    "addr:full":"Rue Ransfort 52 Bruxelles (molenbeek-saint-jean) Bruxelles-Capitale 1080",
    "addr:housenumber":"52",
    "addr:postcode":"1080",
    "addr:street":"Rue Ransfort",
    "iso:country":"BE",
    "sg:address":"Rue Ransfort 52",
    "sg:city":"Bruxelles (molenbeek-saint-jean)",
    "sg:classifiers":[
        {
            "category":"Utilities",
            "subcategory":"Refuse",
            "type":"Services"
        }
    ],
    "sg:phone":"+32 2 410 49 37",
    "sg:postcode":"1080",
    "sg:province":"Bruxelles-Capitale",
    "sg:tags":[
        "removal"
    ],
    "wof:name":"Belgium Mover Sc",
    "wof:placetype":"venue"
},
  "geometry": {"coordinates":[4.3359279633,50.8520851135],"type":"Point"}
}