{
  "type": "Feature",
  "properties": {
    "addr:full":"Rue Des Montis 2 Anhee Namur 5537",
    "addr:housenumber":"2",
    "addr:postcode":"5537",
    "addr:street":"Rue Des Montis;Namur",
    "iso:country":"BE",
    "sg:address":"Rue Des Montis 2",
    "sg:city":"Anhee",
    "sg:orig_category":"Epiceries",
    "sg:phone":"+32 82 69 91 91",
    "sg:postcode":"5537",
    "sg:province":"Namur",
    "wof:name":"Poids D'or",
    "wof:placetype":"venue"
},
  "geometry": {"coordinates":[4.7507710457,50.3003120422],"type":"Point"}
}