{
  "type": "Feature",
  "properties": {
    "iso:country":"BE",
    "sg:address":"Nieuwe Dreef 2",
    "sg:city":"Kalmthout",
    "sg:orig_category":"Drogueries. M\u00e9decines alternatives",
    "sg:phone":"+32 3 666 85 44",
    "sg:postcode":"2920",
    "sg:province":"Antwerpen",
    "wof:name":"Rene Van Hoogendorp",
    "wof:placetype":"venue"
},
  "geometry": {"coordinates":[4.4568080902,51.3889961243],"type":"Point"}
}