{
  "type": "Feature",
  "properties": {
    "addr:full":"Maastrichtersteenweg 120 Tongeren Limburg 3700",
    "addr:housenumber":"120",
    "addr:postcode":"3700",
    "addr:street":"Maastrichtersteenweg",
    "iso:country":"BE",
    "sg:address":"Maastrichtersteenweg 120",
    "sg:city":"Tongeren",
    "sg:classifiers":[
        {
            "category":"Personal",
            "subcategory":"Barber",
            "type":"Services"
        }
    ],
    "sg:phone":"+32 12 23 56 27",
    "sg:postcode":"3700",
    "sg:province":"Limburg",
    "sg:tags":[
        "gentleman",
        "salon",
        "-",
        "hairdressing"
    ],
    "wof:name":"Johnny & Anny & Friends",
    "wof:placetype":"venue"
},
  "geometry": {"coordinates":[5.4805831909,50.7839241028],"type":"Point"}
}