{
  "type": "Feature",
  "properties": {
    "addr:full":"Zilverstraat 2 Eeklo Oost-Vlaanderen 9900",
    "addr:housenumber":"2",
    "addr:postcode":"9900",
    "addr:street":"Zilverstraat",
    "iso:country":"BE",
    "sg:address":"Zilverstraat 2",
    "sg:city":"Eeklo",
    "sg:classifiers":[
        {
            "category":"Professional",
            "subcategory":"Lawyer & Legal Services",
            "type":"Services"
        }
    ],
    "sg:phone":"+32 9 377 58 30",
    "sg:postcode":"9900",
    "sg:province":"Oost-Vlaanderen",
    "wof:name":"Vervaet Frans",
    "wof:placetype":"venue"
},
  "geometry": {"coordinates":[3.5661199093,51.1856994629],"type":"Point"}
}