{
  "type": "Feature",
  "properties": {
    "addr:full":"Rue Des Brasseurs 21 Marche-en-famenne Luxembourg 6900",
    "addr:housenumber":"21",
    "addr:postcode":"6900",
    "addr:street":"Rue Des Brasseurs",
    "iso:country":"BE",
    "sg:address":"Rue Des Brasseurs 21",
    "sg:city":"Marche-en-famenne",
    "sg:classifiers":[
        {
            "category":"Social Services",
            "type":"Services"
        }
    ],
    "sg:phone":"+32 84 31 19 31",
    "sg:postcode":"6900",
    "sg:province":"Luxembourg",
    "wof:name":"Mic-ados A.m.o. Asbl",
    "wof:placetype":"venue"
},
  "geometry": {"coordinates":[5.3458461761,50.2272071838],"type":"Point"}
}