{
  "type": "Feature",
  "properties": {
    "addr:full":"Gaverstraat 55 Laarne Oost-Vlaanderen 9270",
    "addr:housenumber":"55",
    "addr:postcode":"9270",
    "addr:street":"Gaverstraat",
    "iso:country":"BE",
    "sg:address":"Gaverstraat 55",
    "sg:city":"Laarne",
    "sg:orig_category":"Eclairage et \u00e9quipements du foyer. Location de biens divers. Articles textiles and tissus de d\u00e9corat",
    "sg:phone":"+32 9 367 96 00",
    "sg:postcode":"9270",
    "sg:province":"Oost-Vlaanderen",
    "wof:name":"Troch Axel",
    "wof:placetype":"venue"
},
  "geometry": {"coordinates":[3.9226899147,51.0419998169],"type":"Point"}
}