{
  "type": "Feature",
  "properties": {
    "addr:full":"Chauss\u00c9e De Wavre 200b Grez-doiceau Brabant Wallon 1390",
    "addr:housenumber":"200b",
    "addr:postcode":"1390",
    "addr:street":"Chausse\u0301E De Wavre",
    "iso:country":"BE",
    "sg:address":"Chauss\u00c9e De Wavre 200b",
    "sg:city":"Grez-doiceau",
    "sg:orig_category":"Machines-outils Gr",
    "sg:phone":"+32 10 84 49 80",
    "sg:postcode":"1390",
    "sg:province":"Brabant Wallon",
    "wof:name":"Covemi",
    "wof:placetype":"venue"
},
  "geometry": {"coordinates":[4.6775560379,50.7433166504],"type":"Point"}
}