{
  "type": "Feature",
  "properties": {
    "addr:full":"Liersesteenweg 190 Mortsel Antwerpen 2640",
    "addr:housenumber":"190",
    "addr:postcode":"2640",
    "addr:street":"Liersesteenweg",
    "iso:country":"BE",
    "sg:address":"Liersesteenweg 190",
    "sg:city":"Mortsel",
    "sg:classifiers":[
        {
            "category":"Autos & Motor Vehicles",
            "subcategory":"Boat Sales",
            "type":"Retail Goods"
        }
    ],
    "sg:phone":"+32 3 454 19 14",
    "sg:postcode":"2640",
    "sg:province":"Antwerpen",
    "sg:tags":[
        "machine",
        "equipment",
        "blasting"
    ],
    "wof:name":"Abs Nv",
    "wof:placetype":"venue"
},
  "geometry": {"coordinates":[4.4698419571,51.1686630249],"type":"Point"}
}