{
  "type": "Feature",
  "properties": {
    "addr:full":"Monseigneur Senciestraat 13 Halle Vlaams-Brabant 1500",
    "addr:housenumber":"13",
    "addr:postcode":"1500",
    "addr:street":"Monseigneur Senciestraat",
    "iso:country":"BE",
    "sg:address":"Monseigneur Senciestraat 13",
    "sg:city":"Halle",
    "sg:classifiers":[
        {
            "category":"Arena",
            "subcategory":"Sports Club",
            "type":"Entertainment"
        }
    ],
    "sg:phone":"+32 2 360 03 70",
    "sg:postcode":"1500",
    "sg:province":"Vlaams-Brabant",
    "sg:tags":[
        "de"
    ],
    "wof:name":"Halse Aikido Club Musashi",
    "wof:placetype":"venue"
},
  "geometry": {"coordinates":[4.2399101257,50.736869812],"type":"Point"}
}