{
  "type": "Feature",
  "properties": {
    "addr:full":"Avenue De L'arm\u00e9e 138 Bruxelles (etterbeek) Bruxelles-Capitale 1040",
    "addr:housenumber":"138",
    "addr:postcode":"1040",
    "addr:street":"Avenue De L'Arme \u0301E",
    "iso:country":"BE",
    "sg:address":"Avenue De L'arm\u00e9e 138",
    "sg:city":"Bruxelles (etterbeek)",
    "sg:classifiers":[
        {
            "category":"Professional",
            "subcategory":"Testing Lab",
            "type":"Services"
        }
    ],
    "sg:phone":"+32 2 733 18 51",
    "sg:postcode":"1040",
    "sg:province":"Bruxelles-Capitale",
    "sg:tags":[
        "chemist"
    ],
    "wof:name":"Phardup",
    "wof:placetype":"venue"
},
  "geometry": {"coordinates":[4.4026851654,50.8336181641],"type":"Point"}
}