{
  "type": "Feature",
  "properties": {
    "iso:country":"BE",
    "sg:address":"Bommelbekestraat 16",
    "sg:city":"Brugge",
    "sg:classifiers":[
        {
            "category":"Cafe",
            "type":"Food & Drink"
        }
    ],
    "sg:phone":"+32 50 33 45 29",
    "sg:postcode":"8000",
    "sg:province":"West-Vlaanderen",
    "sg:tags":[
        "caf\u00e9s"
    ],
    "wof:name":"Jan Seys",
    "wof:placetype":"venue"
},
  "geometry": {"coordinates":[3.2323958874,51.2319564819],"type":"Point"}
}