{
  "type": "Feature",
  "properties": {
    "iso:country":"BE",
    "sg:address":"Kanaalweg 61",
    "sg:city":"Tessenderlo",
    "sg:classifiers":[
        {
            "category":"Landmark",
            "subcategory":"City Walls",
            "type":"Public Place"
        }
    ],
    "sg:phone":"+32 13 66 65 91",
    "sg:postcode":"3980",
    "sg:province":"Limburg",
    "sg:tags":[
        "section",
        "door",
        "window"
    ],
    "wof:name":"Deferme Bvba",
    "wof:placetype":"venue"
},
  "geometry": {"coordinates":[5.1517281532,51.0745391846],"type":"Point"}
}