{
  "type": "Feature",
  "properties": {
    "addr:full":"Vlamingstraat 2 Poperinge West-Vlaanderen 8970",
    "addr:housenumber":"2",
    "addr:postcode":"8970",
    "addr:street":"Vlamingstraat",
    "iso:country":"BE",
    "sg:address":"Vlamingstraat 2",
    "sg:city":"Poperinge",
    "sg:classifiers":[
        {
            "category":"Bakery",
            "type":"Food & Drink"
        }
    ],
    "sg:phone":"+32 57 33 87 26",
    "sg:postcode":"8970",
    "sg:province":"West-Vlaanderen",
    "sg:tags":[
        "confectioner",
        "baker"
    ],
    "wof:name":"Gouden Bagetje ('t)",
    "wof:placetype":"venue"
},
  "geometry": {"coordinates":[2.7257490158,50.8558120728],"type":"Point"}
}