{
  "type": "Feature",
  "properties": {
    "addr:full":"Westerloseweg 2 Geel Antwerpen 2440",
    "addr:housenumber":"2",
    "addr:postcode":"2440",
    "addr:street":"Westerloseweg",
    "iso:country":"BE",
    "sg:address":"Westerloseweg 2",
    "sg:city":"Geel",
    "sg:classifiers":[
        {
            "category":"Restaurant",
            "type":"Food & Drink"
        }
    ],
    "sg:phone":"+32 14 54 25 80",
    "sg:postcode":"2440",
    "sg:province":"Antwerpen",
    "wof:name":"'t Wolvennest",
    "wof:placetype":"venue"
},
  "geometry": {"coordinates":[4.9440507889,51.0969009399],"type":"Point"}
}