{
  "type": "Feature",
  "properties": {
    "iso:country":"BE",
    "sg:address":"Heerstraat 99",
    "sg:city":"Neerpelt",
    "sg:orig_category":"Produits chimiques Gr",
    "sg:phone":"+32 11 66 62 20",
    "sg:postcode":"3910",
    "sg:province":"Limburg",
    "wof:name":"Cobra Reinigingstechniek",
    "wof:placetype":"venue"
},
  "geometry": {"coordinates":[5.4420371056,51.230255127],"type":"Point"}
}