{
  "type": "Feature",
  "properties": {
    "addr:full":"Stationstr 118 Lochristi (groot) Oost-Vlaanderen 9080",
    "addr:housenumber":"118",
    "addr:postcode":"9080",
    "addr:street":"Lochristi Groot Oost-Vlaanderen",
    "iso:country":"BE",
    "sg:address":"Stationstr 118",
    "sg:city":"Lochristi (groot)",
    "sg:classifiers":[
        {
            "category":"Personal",
            "subcategory":"Beauty Salon",
            "type":"Services"
        }
    ],
    "sg:postcode":"9080",
    "sg:province":"Oost-Vlaanderen",
    "sg:tags":[
        "de",
        "coiffure"
    ],
    "wof:name":"Kristien",
    "wof:placetype":"venue"
},
  "geometry": {"coordinates":[3.8330819607,51.0832252502],"type":"Point"}
}