{
  "type": "Feature",
  "properties": {
    "iso:country":"BE",
    "sg:address":"H. Consciencestraat 17",
    "sg:city":"Ronse",
    "sg:orig_category":"Alternatieve geneeskunde",
    "sg:phone":"+32 55 20 94 76",
    "sg:postcode":"9600",
    "sg:province":"Oost-Vlaanderen",
    "wof:name":"Leta Guy - Baf",
    "wof:placetype":"venue"
},
  "geometry": {"coordinates":[3.6158940792,50.742767334],"type":"Point"}
}