{
  "type": "Feature",
  "properties": {
    "addr:full":"Boulevard General Jacques 148 Bruxelles Bruxelles-Capitale 1050",
    "addr:housenumber":"148",
    "addr:postcode":"1050",
    "addr:street":"Boulevard General Jacques",
    "iso:country":"BE",
    "sg:address":"Boulevard General Jacques 148",
    "sg:city":"Bruxelles",
    "sg:orig_category":"Artists' Colours",
    "sg:phone":"+32 2 648 29 79",
    "sg:postcode":"1050",
    "sg:province":"Bruxelles-Capitale",
    "wof:name":"Jules De Clercq S.p.r.l.",
    "wof:placetype":"venue"
},
  "geometry": {"coordinates":[4.3834781647,50.8203125],"type":"Point"}
}