{
  "type": "Feature",
  "properties": {
    "iso:country":"BE",
    "sg:address":"15 Augustusstraat 1",
    "sg:city":"Zutendaal",
    "sg:classifiers":[
        {
            "category":"Restaurant",
            "type":"Food & Drink"
        }
    ],
    "sg:phone":"+32 89 61 56 21",
    "sg:postcode":"3690",
    "sg:province":"Limburg",
    "wof:name":"Ijssalon D\u00b4artagnan",
    "wof:placetype":"venue"
},
  "geometry": {"coordinates":[5.5742321014,50.9310569763],"type":"Point"}
}