{
  "type": "Feature",
  "properties": {
    "iso:country":"BE",
    "sg:address":"Veldlei 13",
    "sg:city":"Schilde ('s Gravenwezel)",
    "sg:classifiers":[
        {
            "category":"Banks & Credit Unions",
            "subcategory":"Bank",
            "type":"Services"
        }
    ],
    "sg:phone":"+32 3 685 11 07",
    "sg:postcode":"2970",
    "sg:province":"Antwerpen",
    "sg:tags":[
        "savings-banks"
    ],
    "wof:name":"Axa-bank Reussens-cools",
    "wof:placetype":"venue"
},
  "geometry": {"coordinates":[4.5524230003,51.2614212036],"type":"Point"}
}