{
  "type": "Feature",
  "properties": {
    "addr:full":"Avenue Gabrielle Petit 3 Brugelette Hainaut 7940",
    "addr:housenumber":"3",
    "addr:postcode":"7940",
    "addr:street":"Avenue Gabrielle Petit;Hainaut",
    "iso:country":"BE",
    "sg:address":"Avenue Gabrielle Petit 3",
    "sg:city":"Brugelette",
    "sg:classifiers":[
        {
            "category":"Health Services",
            "subcategory":"Health Practitioner",
            "type":"Services"
        }
    ],
    "sg:phone":"+32 68 45 42 81",
    "sg:postcode":"7940",
    "sg:province":"Hainaut",
    "sg:tags":[
        "physiotherapist"
    ],
    "wof:name":"Deproote Fabienne",
    "wof:placetype":"venue"
},
  "geometry": {"coordinates":[3.851418972,50.5942115784],"type":"Point"}
}