{
  "type": "Feature",
  "properties": {
    "iso:country":"BE",
    "sg:address":"Vossenstraat 11",
    "sg:city":"Zaventem (sterrebeek)",
    "sg:classifiers":[
        {
            "category":"Building & Trades",
            "subcategory":"Electrical",
            "type":"Services"
        }
    ],
    "sg:phone":"+32 475 40 38 92",
    "sg:postcode":"1933",
    "sg:province":"Vlaams-Brabant",
    "sg:tags":[
        "electric",
        "-",
        "housewiring",
        "contractor"
    ],
    "wof:name":"Elektriciteitswerken J Van Craenenbroeck",
    "wof:placetype":"venue"
},
  "geometry": {"coordinates":[4.5227508545,50.8720855713],"type":"Point"}
}