{
  "type": "Feature",
  "properties": {
    "addr:full":"Obterrestraat 56 Poperinge West-Vlaanderen 8972",
    "addr:housenumber":"56",
    "addr:postcode":"8972",
    "addr:street":"Obterrestraat",
    "iso:country":"BE",
    "sg:address":"Obterrestraat 56",
    "sg:city":"Poperinge",
    "sg:orig_category":"Travaux de pl\u00e2trage. Construction de maisons. Rev\u00eatements pour sols and murs. Travaux de finition an",
    "sg:phone":"+32 57 30 06 74",
    "sg:postcode":"8972",
    "sg:province":"West-Vlaanderen",
    "wof:name":"Vermeulen Hugo",
    "wof:placetype":"venue"
},
  "geometry": {"coordinates":[2.6525149345,50.8926429749],"type":"Point"}
}