{
  "type": "Feature",
  "properties": {
    "addr:full":"Ertbeekstraat 45b6 Hasselt Limburg 3500",
    "addr:housenumber":"45b6",
    "addr:postcode":"3500",
    "addr:street":"Ertbeekstraat",
    "iso:country":"BE",
    "sg:address":"Ertbeekstraat 45b6",
    "sg:city":"Hasselt",
    "sg:orig_category":"M\u00e9decins and sp\u00e9cialistes",
    "sg:phone":"+32 11 28 16 25",
    "sg:postcode":"3500",
    "sg:province":"Limburg",
    "wof:name":"Nathalie Vandevijver",
    "wof:placetype":"venue"
},
  "geometry": {"coordinates":[5.3268108368,50.9289321899],"type":"Point"}
}