{
  "type": "Feature",
  "properties": {
    "addr:full":"Oranjestraat 40 Scherpenheuvel-zichem Vlaams-Brabant 3271",
    "addr:housenumber":"40",
    "addr:postcode":"3271",
    "addr:street":"Oranjestraat",
    "iso:country":"BE",
    "sg:address":"Oranjestraat 40",
    "sg:city":"Scherpenheuvel-zichem",
    "sg:classifiers":[
        {
            "category":"Personal",
            "subcategory":"Beauty Salon",
            "type":"Services"
        }
    ],
    "sg:phone":"+32 13 77 24 65",
    "sg:postcode":"3271",
    "sg:province":"Vlaams-Brabant",
    "sg:tags":[
        "de",
        "coiffure"
    ],
    "wof:name":"Lea Vandebroeck",
    "wof:placetype":"venue"
},
  "geometry": {"coordinates":[4.9857501984,51.0000610352],"type":"Point"}
}