{
  "type": "Feature",
  "properties": {
    "addr:full":"Violetstraat 34 Geel Antwerpen 2440",
    "addr:housenumber":"34",
    "addr:postcode":"2440",
    "addr:street":"Violetstraat",
    "iso:country":"BE",
    "sg:address":"Violetstraat 34",
    "sg:city":"Geel",
    "sg:orig_category":"Sportclubs",
    "sg:phone":"+32 14 58 01 29",
    "sg:postcode":"2440",
    "sg:province":"Antwerpen",
    "wof:name":"T.c. Olen",
    "wof:placetype":"venue"
},
  "geometry": {"coordinates":[4.9799962044,51.1629943848],"type":"Point"}
}