{
  "type": "Feature",
  "properties": {
    "iso:country":"BE",
    "sg:address":"Rue Bara 210",
    "sg:city":"Anderlecht/anderlecht",
    "sg:orig_category":"Entretien and r\u00e9parations de voitures",
    "sg:phone":"+32 2 521 47 55",
    "sg:postcode":"1070",
    "sg:province":"Bruxelles-Capitale",
    "wof:name":"Garage Cesar",
    "wof:placetype":"venue"
},
  "geometry": {"coordinates":[4.3280720711,50.8329391479],"type":"Point"}
}