{
  "type": "Feature",
  "properties": {
    "addr:full":"Vaderlandstraat 34 Gent Oost-Vlaanderen 9000",
    "addr:housenumber":"34",
    "addr:postcode":"9000",
    "addr:street":"Vaderlandstraat;Oost-Vlaanderen",
    "iso:country":"BE",
    "sg:address":"Vaderlandstraat 34",
    "sg:city":"Gent",
    "sg:orig_category":"Electrom\u00e9nager, t\u00e9l\u00e9visions and radios",
    "sg:phone":"+32 9 220 62 22",
    "sg:postcode":"9000",
    "sg:province":"Oost-Vlaanderen",
    "wof:name":"M.t.c.",
    "wof:placetype":"venue"
},
  "geometry": {"coordinates":[3.7151470184,51.0311851501],"type":"Point"}
}