{
  "type": "Feature",
  "properties": {
    "iso:country":"BE",
    "sg:address":"Bergenstraat 122",
    "sg:city":"Oud-heverlee",
    "sg:orig_category":"Woningbouw",
    "sg:phone":"+32 16 40 32 79",
    "sg:postcode":"3053",
    "sg:province":"Vlaams-Brabant",
    "wof:name":"Solid Construct",
    "wof:placetype":"venue"
},
  "geometry": {"coordinates":[4.7260899544,50.8259506226],"type":"Point"}
}