{
  "type": "Feature",
  "properties": {
    "addr:full":"Vredelaan 123 Zemst Vlaams-Brabant 1982",
    "addr:housenumber":"123",
    "addr:postcode":"1982",
    "addr:street":"Vredelaan;Vlaams-Brabant",
    "iso:country":"BE",
    "sg:address":"Vredelaan 123",
    "sg:city":"Zemst",
    "sg:orig_category":"Pain, p\u00e2tisseries and confiseries",
    "sg:phone":"+32 15 61 47 45",
    "sg:postcode":"1982",
    "sg:province":"Vlaams-Brabant",
    "wof:name":"P. De Kock",
    "wof:placetype":"venue"
},
  "geometry": {"coordinates":[4.474583149,50.9778213501],"type":"Point"}
}