{
  "type": "Feature",
  "properties": {
    "addr:full":"Riijselstraat 65 Menen West-Vlaanderen 8930",
    "addr:housenumber":"65",
    "addr:postcode":"8930",
    "addr:street":"Riijselstraat",
    "iso:country":"BE",
    "sg:address":"Riijselstraat 65",
    "sg:city":"Menen",
    "sg:orig_category":"Disquaires",
    "sg:phone":"+32 56 57 75 14",
    "sg:postcode":"8930",
    "sg:province":"West-Vlaanderen",
    "wof:name":"Canard Bizarre",
    "wof:placetype":"venue"
},
  "geometry": {"coordinates":[3.1226389408,50.7931442261],"type":"Point"}
}