{
  "type": "Feature",
  "properties": {
    "addr:full":"Wetterensteenweg 29 Wetteren Oost-Vlaanderen 9230",
    "addr:housenumber":"29",
    "addr:postcode":"9230",
    "addr:street":"Wetterensteenweg",
    "iso:country":"BE",
    "sg:address":"Wetterensteenweg 29",
    "sg:city":"Wetteren",
    "sg:orig_category":"Dierenartsen",
    "sg:phone":"+32 9 252 36 44",
    "sg:postcode":"9230",
    "sg:province":"Oost-Vlaanderen",
    "wof:name":"Johan De Latthauwer",
    "wof:placetype":"venue"
},
  "geometry": {"coordinates":[3.841643095,51.0089683533],"type":"Point"}
}