{
  "type": "Feature",
  "properties": {
    "iso:country":"BE",
    "sg:address":"Rue Froide Bise 23",
    "sg:city":"Villers-la-ville",
    "sg:classifiers":[
        {
            "category":"Building & Trades",
            "subcategory":"Landscaping Services",
            "type":"Services"
        }
    ],
    "sg:phone":"+32 71 87 97 68",
    "sg:postcode":"1495",
    "sg:province":"Brabant Wallon",
    "sg:tags":[
        "architect",
        "landscape"
    ],
    "wof:name":"Greenliner (the)",
    "wof:placetype":"venue"
},
  "geometry": {"coordinates":[4.5351438522,50.5760612488],"type":"Point"}
}