{
  "type": "Feature",
  "properties": {
    "iso:country":"BE",
    "sg:address":"Avenue Ch. Plisnier 4",
    "sg:city":"Anderlecht (brussel)",
    "sg:orig_category":"Airconditioning and ventilatie Elektrische installaties voor woningen",
    "sg:phone":"+32 477 31 42 33",
    "sg:postcode":"1070",
    "sg:province":"Bruxelles-Capitale",
    "wof:name":"F.c. Electrotechnique",
    "wof:placetype":"venue"
},
  "geometry": {"coordinates":[4.3050570488,50.8399963379],"type":"Point"}
}