{
  "type": "Feature",
  "properties": {
    "iso:country":"BE",
    "sg:address":"Rue Des Carmes 28 A 32",
    "sg:city":"Li\u00e8ge",
    "sg:classifiers":[
        {
            "category":"Banks & Credit Unions",
            "subcategory":"Bank",
            "type":"Services"
        }
    ],
    "sg:phone":"+32 41220700",
    "sg:postcode":"4000",
    "sg:province":"Li\u00e8ge",
    "wof:name":"Banque Du Cr\u00e9dit Li\u00e8geois",
    "wof:placetype":"venue"
},
  "geometry": {"coordinates":[5.5738391876,50.6398506165],"type":"Point"}
}