{
  "type": "Feature",
  "properties": {
    "iso:country":"BE",
    "sg:address":"Avenue Gustave Latinis 9",
    "sg:city":"Schaarbeek/schaerbeek",
    "sg:orig_category":"Articles de sport, camping and jouets Articles de camping and de sport",
    "sg:phone":"+32 2 215 74 03",
    "sg:postcode":"1030",
    "sg:province":"Bruxelles-Capitale",
    "wof:name":"Gym Concept",
    "wof:placetype":"venue"
},
  "geometry": {"coordinates":[4.386657238,50.8672599792],"type":"Point"}
}