{
  "type": "Feature",
  "properties": {
    "iso:country":"BE",
    "sg:address":"Grote Markt 2",
    "sg:city":"Beveren",
    "sg:orig_category":"Offices du tourisme",
    "sg:phone":"+32 3 750 15 80",
    "sg:postcode":"9120",
    "sg:province":"Oost-Vlaanderen",
    "wof:name":"Dienst Voor Toerisme Beveren",
    "wof:placetype":"venue"
},
  "geometry": {"coordinates":[4.2564277649,51.2128791809],"type":"Point"}
}