{
  "type": "Feature",
  "properties": {
    "addr:full":"Spaarzaamheidstraat 14 Hasselt Limburg 3500",
    "addr:housenumber":"14",
    "addr:postcode":"3500",
    "addr:street":"Spaarzaamheidstraat",
    "iso:country":"BE",
    "sg:address":"Spaarzaamheidstraat 14",
    "sg:city":"Hasselt",
    "sg:orig_category":"Eclairage et \u00e9quipements du foyer. Conception d'\u00e9talages and de showrooms",
    "sg:phone":"+32 11 28 11 28",
    "sg:postcode":"3500",
    "sg:province":"Limburg",
    "wof:name":"Karel Thys",
    "wof:placetype":"venue"
},
  "geometry": {"coordinates":[5.3310441971,50.9238777161],"type":"Point"}
}