{
  "type": "Feature",
  "properties": {
    "addr:full":"Boulevard Maurice Lemonnier 94 Bruxelles Bruxelles-Capitale 1000",
    "addr:housenumber":"94",
    "addr:postcode":"1000",
    "addr:street":"Boulevard Maurice Lemonnier",
    "iso:country":"BE",
    "sg:address":"Boulevard Maurice Lemonnier 94",
    "sg:city":"Bruxelles",
    "sg:classifiers":[
        {
            "category":"Health Services",
            "subcategory":"Nursing And Care Facility",
            "type":"Services"
        }
    ],
    "sg:phone":"+32 2 511 45 68",
    "sg:postcode":"1000",
    "sg:province":"Bruxelles-Capitale",
    "sg:tags":[
        "safe"
    ],
    "wof:name":"Rouzeeuw Ch Sprl",
    "wof:placetype":"venue"
},
  "geometry": {"coordinates":[4.3442358971,50.8428344727],"type":"Point"}
}