{
  "type": "Feature",
  "properties": {
    "addr:full":"Kortwagenstraat 67bb Ledegem West-Vlaanderen 8880",
    "addr:housenumber":"67bb",
    "addr:postcode":"8880",
    "addr:street":"Kortwagenstraat",
    "iso:country":"BE",
    "sg:address":"Kortwagenstraat 67bb",
    "sg:city":"Ledegem",
    "sg:orig_category":"Peinture. Rev\u00eatements pour sols and murs",
    "sg:phone":"+32 56 50 22 48",
    "sg:postcode":"8880",
    "sg:province":"West-Vlaanderen",
    "wof:name":"Poll Cokelaere",
    "wof:placetype":"venue"
},
  "geometry": {"coordinates":[3.1273829937,50.8629493713],"type":"Point"}
}