{
  "type": "Feature",
  "properties": {
    "addr:full":"Hingenesteenweg 118 Bornem Antwerpen 2880",
    "addr:housenumber":"118",
    "addr:postcode":"2880",
    "addr:street":"Hingenesteenweg",
    "iso:country":"BE",
    "sg:address":"Hingenesteenweg 118",
    "sg:city":"Bornem",
    "sg:orig_category":"DIVERSE RECREATIEVE ACTIVITEITEN",
    "sg:phone":"+32 3 889 05 82",
    "sg:postcode":"2880",
    "sg:province":"Antwerpen",
    "wof:name":"B.c. Klein Brabant",
    "wof:placetype":"venue"
},
  "geometry": {"coordinates":[4.2531151772,51.1009712219],"type":"Point"}
}