{
  "type": "Feature",
  "properties": {
    "iso:country":"BE",
    "sg:address":"Boulevard De La Constitution 64",
    "sg:city":"Li\u00e8ge 1 (li\u00e8ge 2)",
    "sg:classifiers":[
        {
            "category":"Bars & Pubs",
            "type":"Food & Drink"
        }
    ],
    "sg:phone":"+32 4 341 19 55",
    "sg:postcode":"4020",
    "sg:province":"Li\u00e8ge",
    "wof:name":"Baudelaire (le)",
    "wof:placetype":"venue"
},
  "geometry": {"coordinates":[5.5870661736,50.6435890198],"type":"Point"}
}