{
  "type": "Feature",
  "properties": {
    "addr:full":"Voie Du Roman Pays 46 Ottignies-louvain-la-neuve (louvain-la-neuve) Brabant Wallon 1348",
    "addr:housenumber":"46",
    "addr:postcode":"1348",
    "addr:street":"Voie Du Roman Pays",
    "iso:country":"BE",
    "sg:address":"Voie Du Roman Pays 46",
    "sg:city":"Ottignies-louvain-la-neuve (louvain-la-neuve)",
    "sg:classifiers":[
        {
            "category":"Health Services",
            "subcategory":"Dentist",
            "type":"Services"
        }
    ],
    "sg:phone":"+32 10 45 01 01",
    "sg:postcode":"1348",
    "sg:province":"Brabant Wallon",
    "wof:name":"Namurois Marc",
    "wof:placetype":"venue"
},
  "geometry": {"coordinates":[4.6146697998,50.6671447754],"type":"Point"}
}