{
  "type": "Feature",
  "properties": {
    "iso:country":"BE",
    "sg:address":"Hubert Fr\u00c8re-orbanlaan 355",
    "sg:city":"Gent",
    "sg:classifiers":[
        {
            "category":"Personal",
            "subcategory":"Beauty Salon",
            "type":"Services"
        }
    ],
    "sg:phone":"+32 9 225 97 19",
    "sg:postcode":"9000",
    "sg:province":"Oost-Vlaanderen",
    "sg:tags":[
        "de",
        "coiffure"
    ],
    "wof:name":"Coiffure Richie",
    "wof:placetype":"venue"
},
  "geometry": {"coordinates":[3.735918045,51.0413131714],"type":"Point"}
}