{
  "type": "Feature",
  "properties": {
    "iso:country":"BE",
    "sg:address":"Kanunnik Davidstraat 27",
    "sg:city":"Oostkamp",
    "sg:classifiers":[
        {
            "category":"Building & Trades",
            "subcategory":"Construction",
            "type":"Services"
        }
    ],
    "sg:phone":"+32 50 82 53 87",
    "sg:postcode":"8020",
    "sg:province":"West-Vlaanderen",
    "sg:tags":[
        "installation",
        "-",
        "central",
        "heating"
    ],
    "wof:name":"Depuydt F Bvba",
    "wof:placetype":"venue"
},
  "geometry": {"coordinates":[3.2361750603,51.1367607117],"type":"Point"}
}