{
  "type": "Feature",
  "properties": {
    "iso:country":"BE",
    "sg:address":"Ninoofsesteenweg 51",
    "sg:city":"Haaltert",
    "sg:orig_category":"Installatie van houten of kunststof schrijnwerk MEUBELONTWERP AND -INSTALLATIE",
    "sg:phone":"+32 54 32 62 61",
    "sg:postcode":"9450",
    "sg:province":"Oost-Vlaanderen",
    "wof:name":"Luc Chiau",
    "wof:placetype":"venue"
},
  "geometry": {"coordinates":[4.0215001106,50.8603935242],"type":"Point"}
}