{
  "type": "Feature",
  "properties": {
    "iso:country":"BE",
    "sg:address":"Diestsesteenweg 313",
    "sg:city":"Aarschot",
    "sg:classifiers":[
        {
            "category":"Cafe",
            "type":"Food & Drink"
        }
    ],
    "sg:phone":"+32 16 50 01 10",
    "sg:postcode":"3202",
    "sg:province":"Vlaams-Brabant",
    "sg:tags":[
        "caf\u00e9s"
    ],
    "wof:name":"Luc Willems",
    "wof:placetype":"venue"
},
  "geometry": {"coordinates":[4.8679141998,50.9776535034],"type":"Point"}
}