{
  "type": "Feature",
  "properties": {
    "addr:full":"Rue De Mouhin 8 Waremme Li\u00e8ge 4300",
    "addr:housenumber":"8",
    "addr:postcode":"4300",
    "addr:street":"Rue De Mouhin",
    "iso:country":"BE",
    "sg:address":"Rue De Mouhin 8",
    "sg:city":"Waremme",
    "sg:orig_category":"Artsen and specialisten",
    "sg:phone":"+32 19 32 50 50",
    "sg:postcode":"4300",
    "sg:province":"Li\u00e8ge",
    "wof:name":"Guy Geradon",
    "wof:placetype":"venue"
},
  "geometry": {"coordinates":[5.2490158081,50.7031593323],"type":"Point"}
}