{
  "type": "Feature",
  "properties": {
    "addr:full":"Molenstraat 42 Heusden-zolder (zolder) Limburg 3550",
    "addr:housenumber":"42",
    "addr:postcode":"3550",
    "addr:street":"Molenstraat",
    "iso:country":"BE",
    "sg:address":"Molenstraat 42",
    "sg:city":"Heusden-zolder (zolder)",
    "sg:classifiers":[
        {
            "category":"Food & Beverages",
            "subcategory":"Candy",
            "type":"Retail Goods"
        }
    ],
    "sg:phone":"+32 11 53 69 57",
    "sg:postcode":"3550",
    "sg:province":"Limburg",
    "wof:name":"Molentje ('t)",
    "wof:placetype":"venue"
},
  "geometry": {"coordinates":[5.3133997917,51.0261154175],"type":"Point"}
}