{
  "type": "Feature",
  "properties": {
    "addr:full":"Avenue Albert-mahiels 7 Li\u00c8ge Li\u00e8ge 4020",
    "addr:housenumber":"7",
    "addr:postcode":"4020",
    "addr:street":"Avenue Albert-Mahiels",
    "iso:country":"BE",
    "sg:address":"Avenue Albert-mahiels 7",
    "sg:city":"Li\u00c8ge",
    "sg:orig_category":"M\u00e9decins and sp\u00e9cialistes",
    "sg:phone":"+32 4 341 55 13",
    "sg:postcode":"4020",
    "sg:province":"Li\u00e8ge",
    "wof:name":"Patricia Leroy",
    "wof:placetype":"venue"
},
  "geometry": {"coordinates":[5.5837521553,50.6227264404],"type":"Point"}
}