{
  "type": "Feature",
  "properties": {
    "iso:country":"BE",
    "sg:address":"Route De L'eau Rouge 2bb",
    "sg:city":"Stavelot",
    "sg:orig_category":"Herstellingen and onderhoud van auto's",
    "sg:phone":"+32 80 86 28 35",
    "sg:postcode":"4970",
    "sg:province":"Li\u00e8ge",
    "wof:name":"Balci Fikri",
    "wof:placetype":"venue"
},
  "geometry": {"coordinates":[6.0294508934,50.4262580872],"type":"Point"}
}