{
  "type": "Feature",
  "properties": {
    "iso:country":"BE",
    "sg:address":"Rue De La Dodane 8",
    "sg:city":"Namur",
    "sg:orig_category":"Advocaten and juridische adviseurs",
    "sg:phone":"+32 81 73 50 86",
    "sg:postcode":"5000",
    "sg:province":"Namur",
    "wof:name":"J.p. Babut Du Mares",
    "wof:placetype":"venue"
},
  "geometry": {"coordinates":[4.8539690971,50.467830658],"type":"Point"}
}