{
  "type": "Feature",
  "properties": {
    "addr:full":"Britselei 15 Antwerpen-centrum Antwerpen 2000",
    "addr:housenumber":"15",
    "addr:postcode":"2000",
    "addr:street":"Britselei",
    "iso:country":"BE",
    "sg:address":"Britselei 15",
    "sg:city":"Antwerpen-centrum",
    "sg:classifiers":[
        {
            "category":"Airline",
            "type":"Transportation"
        }
    ],
    "sg:phone":"+32 3 237 17 50",
    "sg:postcode":"2000",
    "sg:province":"Antwerpen",
    "sg:tags":[
        "berlitz"
    ],
    "wof:name":"Berlitz",
    "wof:placetype":"venue"
},
  "geometry": {"coordinates":[4.3935499191,51.218788147],"type":"Point"}
}