{
  "type": "Feature",
  "properties": {
    "iso:country":"BE",
    "sg:address":"Geldmuntstraat 41",
    "sg:city":"Brugge",
    "sg:orig_category":"Maroquinerie and articles de voyage",
    "sg:phone":"+32 50 34 77 40",
    "sg:postcode":"8000",
    "sg:province":"West-Vlaanderen",
    "wof:name":"Kipling",
    "wof:placetype":"venue"
},
  "geometry": {"coordinates":[3.2214419842,51.2084465027],"type":"Point"}
}