{
  "type": "Feature",
  "properties": {
    "addr:full":"Rue Des Betteraves 60 Bruxelles (anderlecht) Bruxelles-Capitale 1070",
    "addr:housenumber":"60",
    "addr:postcode":"1070",
    "addr:street":"Rue Des Betteraves",
    "iso:country":"BE",
    "sg:address":"Rue Des Betteraves 60",
    "sg:city":"Bruxelles (anderlecht)",
    "sg:classifiers":[
        {
            "category":"Farming",
            "subcategory":"Livestock Farm",
            "type":"Manufacturing & Wholesale Goods"
        }
    ],
    "sg:phone":"+32 2 522 19 41",
    "sg:postcode":"1070",
    "sg:province":"Bruxelles-Capitale",
    "sg:tags":[
        "horse"
    ],
    "wof:name":"Amazone Bvba",
    "wof:placetype":"venue"
},
  "geometry": {"coordinates":[4.2616701126,50.82421875],"type":"Point"}
}