{
  "type": "Feature",
  "properties": {
    "addr:full":"Groenestraat 539 Roeselare West-Vlaanderen 8800",
    "addr:housenumber":"539",
    "addr:postcode":"8800",
    "addr:street":"Groenestraat",
    "iso:country":"BE",
    "sg:address":"Groenestraat 539",
    "sg:city":"Roeselare",
    "sg:orig_category":"Paramedische behandelingen",
    "sg:phone":"+32 51 22 66 60",
    "sg:postcode":"8800",
    "sg:province":"West-Vlaanderen",
    "wof:name":"M. Gryffroy",
    "wof:placetype":"venue"
},
  "geometry": {"coordinates":[3.0827970505,50.933681488],"type":"Point"}
}