{
  "type": "Feature",
  "properties": {
    "iso:country":"BE",
    "sg:address":"De Keyserlei 16",
    "sg:city":"Antwerpen",
    "sg:classifiers":[
        {
            "category":"Cafe",
            "type":"Food & Drink"
        }
    ],
    "sg:phone":"+32 3 707 23 65",
    "sg:postcode":"2018",
    "sg:province":"Antwerpen",
    "sg:tags":[
        "snack-bars"
    ],
    "wof:name":"Deli",
    "wof:placetype":"venue"
},
  "geometry": {"coordinates":[4.4163818359,51.2177085876],"type":"Point"}
}