{
  "type": "Feature",
  "properties": {
    "iso:country":"BE",
    "sg:address":"Oranjerielaan 3",
    "sg:city":"Gent",
    "sg:classifiers":[
        {
            "category":"Arena",
            "subcategory":"Sports Club",
            "type":"Entertainment"
        }
    ],
    "sg:phone":"+32 9 226 78 47",
    "sg:postcode":"9030",
    "sg:province":"Oost-Vlaanderen",
    "sg:tags":[
        "de"
    ],
    "wof:name":"Legia Gent B.b.c.",
    "wof:placetype":"venue"
},
  "geometry": {"coordinates":[3.6805610657,51.0707740784],"type":"Point"}
}