{
  "type": "Feature",
  "properties": {
    "addr:full":"Rue Lauvaux 49 Herbeumont Luxembourg 6887",
    "addr:housenumber":"49",
    "addr:postcode":"6887",
    "addr:street":"Rue Lauvaux",
    "iso:country":"BE",
    "sg:address":"Rue Lauvaux 49",
    "sg:city":"Herbeumont",
    "sg:orig_category":"Postkantoren Verzekeringsmakelaars and experts",
    "sg:phone":"+32 61 41 14 23",
    "sg:postcode":"6887",
    "sg:province":"Luxembourg",
    "wof:name":"La Poste",
    "wof:placetype":"venue"
},
  "geometry": {"coordinates":[5.2375397682,49.7810707092],"type":"Point"}
}