{
  "type": "Feature",
  "properties": {
    "addr:full":"Maaseikersteenweg 64 Lanaken Limburg 3620",
    "addr:housenumber":"64",
    "addr:postcode":"3620",
    "addr:street":"Maaseikersteenweg",
    "iso:country":"BE",
    "sg:address":"Maaseikersteenweg 64",
    "sg:city":"Lanaken",
    "sg:classifiers":[
        {
            "category":"Arts & Performance",
            "subcategory":"Music",
            "type":"Entertainment"
        }
    ],
    "sg:phone":"+32 89 73 21 67",
    "sg:postcode":"3620",
    "sg:province":"Limburg",
    "sg:tags":[
        "disc-jockeys"
    ],
    "wof:name":"Music Point Productions",
    "wof:placetype":"venue"
},
  "geometry": {"coordinates":[5.6745100021,50.8919715881],"type":"Point"}
}