{
  "type": "Feature",
  "properties": {
    "addr:full":"Bellemstraat 172b Aalter Oost-Vlaanderen 9881",
    "addr:housenumber":"172b",
    "addr:postcode":"9881",
    "addr:street":"Bellemstraat",
    "iso:country":"BE",
    "sg:address":"Bellemstraat 172b",
    "sg:city":"Aalter",
    "sg:orig_category":"Computers and computerapparatuur Software ontwikkeling and ontwerp",
    "sg:phone":"+32 9 375 34 02",
    "sg:postcode":"9881",
    "sg:province":"Oost-Vlaanderen",
    "wof:name":"Ace Informatics",
    "wof:placetype":"venue"
},
  "geometry": {"coordinates":[3.4772250652,51.0933494568],"type":"Point"}
}