{
  "type": "Feature",
  "properties": {
    "iso:country":"BE",
    "sg:address":"Droogte 139",
    "sg:city":"Evergem",
    "sg:orig_category":"Producteurs de l\u00e9gumes. Plantes and fleurs Gr",
    "sg:phone":"+32 9 357 74 47",
    "sg:postcode":"9940",
    "sg:province":"Oost-Vlaanderen",
    "wof:name":"Kinabalu",
    "wof:placetype":"venue"
},
  "geometry": {"coordinates":[3.717042923,51.1241607666],"type":"Point"}
}