{
  "type": "Feature",
  "properties": {
    "addr:full":"Hasseltsestraat 55 Diest Vlaams-Brabant 3290",
    "addr:housenumber":"55",
    "addr:postcode":"3290",
    "addr:street":"Hasseltsestraat",
    "iso:country":"BE",
    "sg:address":"Hasseltsestraat 55",
    "sg:city":"Diest",
    "sg:orig_category":"Foto-uitrusting",
    "sg:phone":"+32 13 31 11 10",
    "sg:postcode":"3290",
    "sg:province":"Vlaams-Brabant",
    "wof:name":"Piet Melotte",
    "wof:placetype":"venue"
},
  "geometry": {"coordinates":[5.0537128448,50.9806861877],"type":"Point"}
}