{
  "type": "Feature",
  "properties": {
    "addr:full":"Avenue De Wandre 45 Herve Li\u00e8ge 4650",
    "addr:housenumber":"45",
    "addr:postcode":"4650",
    "addr:street":"Avenue De Wandre",
    "iso:country":"BE",
    "sg:address":"Avenue De Wandre 45",
    "sg:city":"Herve",
    "sg:orig_category":"Artsen and specialisten",
    "sg:phone":"+32 87 66 00 05",
    "sg:postcode":"4650",
    "sg:province":"Li\u00e8ge",
    "wof:name":"Olivier Cagot",
    "wof:placetype":"venue"
},
  "geometry": {"coordinates":[5.7946419716,50.6422958374],"type":"Point"}
}