{
  "type": "Feature",
  "properties": {
    "addr:full":"Hulststraat 42 Sint-gillis-waas Oost-Vlaanderen 9170",
    "addr:housenumber":"42",
    "addr:postcode":"9170",
    "addr:street":"Hulststraat",
    "iso:country":"BE",
    "sg:address":"Hulststraat 42",
    "sg:city":"Sint-gillis-waas",
    "sg:orig_category":"Enseignement maternel and primaire",
    "sg:phone":"+32 3 770 70 09",
    "sg:postcode":"9170",
    "sg:province":"Oost-Vlaanderen",
    "wof:name":"Vrije Basisschool",
    "wof:placetype":"venue"
},
  "geometry": {"coordinates":[4.0867109299,51.2569503784],"type":"Point"}
}