{
  "type": "Feature",
  "properties": {
    "iso:country":"BE",
    "sg:address":"Rue Des Orphelins 2",
    "sg:city":"Mons",
    "sg:classifiers":[
        {
            "category":"Health Services",
            "subcategory":"Dentist",
            "type":"Services"
        }
    ],
    "sg:phone":"+32 65 34 95 93",
    "sg:postcode":"7000",
    "sg:province":"Hainaut",
    "wof:name":"Brichart Michel",
    "wof:placetype":"venue"
},
  "geometry": {"coordinates":[3.9475500584,50.4508094788],"type":"Point"}
}