{
  "type": "Feature",
  "properties": {
    "addr:full":"Chauss\u00e9e De Tongres 119 Amay Li\u00e8ge 4540",
    "addr:housenumber":"119",
    "addr:postcode":"4540",
    "addr:street":"Chausse\u0301E De Tongres",
    "iso:country":"BE",
    "sg:address":"Chauss\u00e9e De Tongres 119",
    "sg:city":"Amay",
    "sg:classifiers":[
        {
            "category":"Building & Trades",
            "subcategory":"Electrical",
            "type":"Services"
        }
    ],
    "sg:phone":"+32 85 31 56 83",
    "sg:postcode":"4540",
    "sg:province":"Li\u00e8ge",
    "sg:tags":[
        "electric",
        "-",
        "housewiring",
        "contractor"
    ],
    "wof:name":"Seret C",
    "wof:placetype":"venue"
},
  "geometry": {"coordinates":[5.3089342117,50.5471420288],"type":"Point"}
}