{
  "type": "Feature",
  "properties": {
    "addr:full":"Rue De Fombay 14 Doische Namur 5680",
    "addr:housenumber":"14",
    "addr:postcode":"5680",
    "addr:street":"Rue De Fombay",
    "iso:country":"BE",
    "sg:address":"Rue De Fombay 14",
    "sg:city":"Doische",
    "sg:orig_category":"Boekhouders",
    "sg:phone":"+32 82 67 71 56",
    "sg:postcode":"5680",
    "sg:province":"Namur",
    "wof:name":"Marcel Debouche",
    "wof:placetype":"venue"
},
  "geometry": {"coordinates":[4.6778187752,50.1386413574],"type":"Point"}
}