{
  "type": "Feature",
  "properties": {
    "iso:country":"BE",
    "sg:address":"Moravie 30",
    "sg:city":"Bissegem",
    "sg:classifiers":[
        {
            "category":"Food & Beverages",
            "subcategory":"Groceries & Convenience Stores",
            "type":"Retail Goods"
        }
    ],
    "sg:phone":"+32 56 35 33 67",
    "sg:postcode":"8501",
    "sg:province":"West-Vlaanderen",
    "sg:tags":[
        "product",
        "grain",
        "cereal",
        "related"
    ],
    "wof:name":"Bijenhof Imkers- Bedrijf Bvba",
    "wof:placetype":"venue"
},
  "geometry": {"coordinates":[3.2215340137,50.8127174377],"type":"Point"}
}