{
  "type": "Feature",
  "properties": {
    "addr:full":"Rue De Brionsart 41 Gesves Namur 5340",
    "addr:housenumber":"41",
    "addr:postcode":"5340",
    "addr:street":"Rue De Brionsart",
    "iso:country":"BE",
    "sg:address":"Rue De Brionsart 41",
    "sg:city":"Gesves",
    "sg:orig_category":"Slagers",
    "sg:phone":"+32 83 67 76 84",
    "sg:postcode":"5340",
    "sg:province":"Namur",
    "wof:name":"Jean Walravens",
    "wof:placetype":"venue"
},
  "geometry": {"coordinates":[5.0775098801,50.4190444946],"type":"Point"}
}