{
  "type": "Feature",
  "properties": {
    "addr:full":"Moonenkapelstraat 2 Maaseik Limburg 3680",
    "addr:housenumber":"2",
    "addr:postcode":"3680",
    "addr:street":"Moonenkapelstraat",
    "iso:country":"BE",
    "sg:address":"Moonenkapelstraat 2",
    "sg:city":"Maaseik",
    "sg:orig_category":"Travaux de pl\u00e2trage",
    "sg:phone":"+32 89 86 48 14",
    "sg:postcode":"3680",
    "sg:province":"Limburg",
    "wof:name":"Henricus De Laat",
    "wof:placetype":"venue"
},
  "geometry": {"coordinates":[5.791285038,51.0954208374],"type":"Point"}
}