{
  "type": "Feature",
  "properties": {
    "addr:full":"Rue De La Gare 24 Bertrix Luxembourg 6880",
    "addr:housenumber":"24",
    "addr:postcode":"6880",
    "addr:street":"Rue De La Gare",
    "iso:country":"BE",
    "sg:address":"Rue De La Gare 24",
    "sg:city":"Bertrix",
    "sg:classifiers":[
        {
            "category":"Insurance",
            "subcategory":"Life Insurance",
            "type":"Services"
        }
    ],
    "sg:phone":"+32 61 41 11 60",
    "sg:postcode":"6880",
    "sg:province":"Luxembourg",
    "sg:tags":[
        "assurance"
    ],
    "wof:name":"Bureau Lamock Serge",
    "wof:placetype":"venue"
},
  "geometry": {"coordinates":[5.255469799,49.8549995422],"type":"Point"}
}