{
  "type": "Feature",
  "properties": {
    "iso:country":"BE",
    "sg:address":"Rue D'ecosse 62",
    "sg:city":"Sint-gillis/saint-gilles",
    "sg:orig_category":"Architectes. Etudes techniques and ing\u00e9nierie. Construction de maisons",
    "sg:phone":"+32 2 538 95 25",
    "sg:postcode":"1060",
    "sg:province":"Bruxelles-Capitale",
    "wof:name":"F. Saliez Architecte",
    "wof:placetype":"venue"
},
  "geometry": {"coordinates":[4.3518090248,50.8315315247],"type":"Point"}
}