{
  "type": "Feature",
  "properties": {
    "iso:country":"BE",
    "sg:address":"Rue Du Roi Albert 230",
    "sg:city":"Oupeye",
    "sg:classifiers":[
        {
            "category":"Home & Garden",
            "subcategory":"Home Furnishings",
            "type":"Retail Goods"
        }
    ],
    "sg:phone":"+32 4 264 22 00",
    "sg:postcode":"4680",
    "sg:province":"Li\u00e8ge",
    "sg:tags":[
        "curtain",
        "-",
        "fixture"
    ],
    "wof:name":"Thibert Y",
    "wof:placetype":"venue"
},
  "geometry": {"coordinates":[5.6449518204,50.7105293274],"type":"Point"}
}