{
  "type": "Feature",
  "properties": {
    "addr:full":"Rue Des Combattants 117 La Hulpe Brabant Wallon 1310",
    "addr:housenumber":"117",
    "addr:postcode":"1310",
    "addr:street":"Rue Des Combattants",
    "iso:country":"BE",
    "sg:address":"Rue Des Combattants 117",
    "sg:city":"La Hulpe",
    "sg:orig_category":"Banques and organismes de cr\u00e9dit",
    "sg:phone":"+32 2 653 37 02",
    "sg:postcode":"1310",
    "sg:province":"Brabant Wallon",
    "wof:name":"Dexia",
    "wof:placetype":"venue"
},
  "geometry": {"coordinates":[4.4863491058,50.7307014465],"type":"Point"}
}