{
  "type": "Feature",
  "properties": {
    "addr:full":"Sint-jorisstraat 7 Aalst Oost-Vlaanderen 9300",
    "addr:housenumber":"7",
    "addr:postcode":"9300",
    "addr:street":"Sint-Jorisstraat",
    "iso:country":"BE",
    "sg:address":"Sint-jorisstraat 7",
    "sg:city":"Aalst",
    "sg:orig_category":"Industri\u00eble elektrische installaties Verlichtingsapparaten and elektrische lampen Fab",
    "sg:phone":"+32 53 71 17 75",
    "sg:postcode":"9300",
    "sg:province":"Oost-Vlaanderen",
    "wof:name":"N.s. Light",
    "wof:placetype":"venue"
},
  "geometry": {"coordinates":[4.0387840271,50.9374465942],"type":"Point"}
}