{
  "type": "Feature",
  "properties": {
    "iso:country":"BE",
    "sg:address":"Desguinlei 25",
    "sg:city":"Antwerpen",
    "sg:classifiers":[
        {
            "category":"Arts & Performance",
            "subcategory":"Symphony",
            "type":"Entertainment"
        }
    ],
    "sg:phone":"+32 3 226 35 11",
    "sg:postcode":"2018",
    "sg:province":"Antwerpen",
    "sg:tags":[
        "orchestra"
    ],
    "wof:name":"Beethoven Academie",
    "wof:placetype":"venue"
},
  "geometry": {"coordinates":[4.4034109116,51.1939086914],"type":"Point"}
}