{
  "type": "Feature",
  "properties": {
    "iso:country":"BE",
    "sg:address":"Schipsebos 2",
    "sg:city":"Genk",
    "sg:orig_category":"Journaux",
    "sg:phone":"+32 89 32 41 56",
    "sg:postcode":"3600",
    "sg:province":"Limburg",
    "wof:name":"Kadeau Shop St-jan",
    "wof:placetype":"venue"
},
  "geometry": {"coordinates":[5.519879818,50.9584007263],"type":"Point"}
}