{
  "type": "Feature",
  "properties": {
    "addr:full":"Clos Saint-martin 21 Bruxelles (ganshoren) Bruxelles-Capitale 1083",
    "addr:housenumber":"21",
    "addr:postcode":"1083",
    "addr:street":"Clos Saint-Martin",
    "iso:country":"BE",
    "sg:address":"Clos Saint-martin 21",
    "sg:city":"Bruxelles (ganshoren)",
    "sg:classifiers":[
        {
            "category":"Manufacturing",
            "subcategory":"Paper Products",
            "type":"Manufacturing & Wholesale Goods"
        }
    ],
    "sg:phone":"+32 2 425 93 83",
    "sg:postcode":"1083",
    "sg:province":"Bruxelles-Capitale",
    "sg:tags":[
        "bookbinding"
    ],
    "wof:name":"Taelemans J-l",
    "wof:placetype":"venue"
},
  "geometry": {"coordinates":[4.315653801,50.8712120056],"type":"Point"}
}