{
  "type": "Feature",
  "properties": {
    "iso:country":"BE",
    "sg:address":"Rue Ernest Malvoz 1",
    "sg:city":"Wanze",
    "sg:orig_category":"Apotheken",
    "sg:phone":"+32 85 21 16 78",
    "sg:postcode":"4520",
    "sg:province":"Li\u00e8ge",
    "wof:name":"Pharmacie Populaire",
    "wof:placetype":"venue"
},
  "geometry": {"coordinates":[5.2338638306,50.5497665405],"type":"Point"}
}