{
  "type": "Feature",
  "properties": {
    "addr:full":"Bist 159 Antwerpen Antwerpen 2180",
    "addr:housenumber":"159",
    "addr:postcode":"2180",
    "addr:street":"Bist",
    "iso:country":"BE",
    "sg:address":"Bist 159",
    "sg:city":"Antwerpen",
    "sg:orig_category":"Sportclubs",
    "sg:phone":"+32 3 605 01 77",
    "sg:postcode":"2180",
    "sg:province":"Antwerpen",
    "wof:name":"W.s.c. Tuinwijkvrienden",
    "wof:placetype":"venue"
},
  "geometry": {"coordinates":[4.4182572365,51.2778625488],"type":"Point"}
}