{
  "type": "Feature",
  "properties": {
    "iso:country":"BE",
    "sg:address":"Raapstraat 113",
    "sg:city":"Sint-niklaas",
    "sg:orig_category":"Installation \u00e9lectrique r\u00e9sidentielle. Plomberie, chauffage and installations sanitaires. Collecte a",
    "sg:phone":"+32 3 776 14 42",
    "sg:postcode":"9100",
    "sg:province":"Oost-Vlaanderen",
    "wof:name":"Lek",
    "wof:placetype":"venue"
},
  "geometry": {"coordinates":[4.164662838,51.1721534729],"type":"Point"}
}