{
  "type": "Feature",
  "properties": {
    "iso:country":"BE",
    "sg:address":"Puttekensveldweg 104",
    "sg:city":"Lennik",
    "sg:classifiers":[
        {
            "category":"Arena",
            "subcategory":"Sports Club",
            "type":"Entertainment"
        }
    ],
    "sg:phone":"+32 2 532 16 94",
    "sg:postcode":"1750",
    "sg:province":"Vlaams-Brabant",
    "sg:tags":[
        "terrain",
        "hors",
        "de",
        "installation",
        "sportifs"
    ],
    "wof:name":"Rsc Anderlecht",
    "wof:placetype":"venue"
},
  "geometry": {"coordinates":[4.1269989014,50.8280487061],"type":"Point"}
}