{
  "type": "Feature",
  "properties": {
    "iso:country":"BE",
    "sg:address":"Avenue Albertine 20",
    "sg:city":"Rixensart",
    "sg:orig_category":"Mat\u00e9riel de contr\u00f4le des processus industriels Fab. Conseils en syst\u00e8mes informatiques",
    "sg:phone":"+32 2 653 46 34",
    "sg:postcode":"1330",
    "sg:province":"Brabant Wallon",
    "wof:name":"Bretton Engineering",
    "wof:placetype":"venue"
},
  "geometry": {"coordinates":[4.5373039246,50.7068023682],"type":"Point"}
}