{
  "type": "Feature",
  "properties": {
    "iso:country":"BE",
    "sg:address":"Rue Chevesne 29",
    "sg:city":"Lobbes (sars-la-buissi\u00e8re)",
    "sg:classifiers":[
        {
            "category":"Professional",
            "subcategory":"Accounting & Tax Preparation",
            "type":"Services"
        }
    ],
    "sg:phone":"+32 476 26 25 39",
    "sg:postcode":"6542",
    "sg:province":"Hainaut",
    "sg:tags":[
        "bookkeeper"
    ],
    "wof:name":"Beumier D",
    "wof:placetype":"venue"
},
  "geometry": {"coordinates":[4.2155199051,50.3377914429],"type":"Point"}
}