{
  "type": "Feature",
  "properties": {
    "iso:country":"BE",
    "sg:address":"Rue Du Champ De Tir 3",
    "sg:city":"Malmedy",
    "sg:classifiers":[
        {
            "category":"Parking",
            "subcategory":"Garage",
            "type":"Transportation"
        }
    ],
    "sg:phone":"+32 80 33 86 06",
    "sg:postcode":"4960",
    "sg:province":"Li\u00e8ge",
    "sg:tags":[
        "truck",
        "-",
        "dump",
        "transport"
    ],
    "wof:name":"Kubisch R",
    "wof:placetype":"venue"
},
  "geometry": {"coordinates":[6.0275449753,50.4229507446],"type":"Point"}
}