{
  "type": "Feature",
  "properties": {
    "iso:country":"BE",
    "sg:address":"Karel Verhaegenlaan 59",
    "sg:city":"Kraainem/kraainem",
    "sg:orig_category":"DIVERSE RECREATIEVE ACTIVITEITEN",
    "sg:phone":"+32 2 720 67 60",
    "sg:postcode":"1950",
    "sg:province":"Vlaams-Brabant",
    "wof:name":"Filakra",
    "wof:placetype":"venue"
},
  "geometry": {"coordinates":[4.4578142166,50.8641662598],"type":"Point"}
}