{
  "type": "Feature",
  "properties": {
    "iso:country":"BE",
    "sg:address":"Rue De Limbourg 43ba",
    "sg:city":"Verviers",
    "sg:classifiers":[
        {
            "category":"Cafe",
            "type":"Food & Drink"
        }
    ],
    "sg:phone":"+32 87 31 53 57",
    "sg:postcode":"4800",
    "sg:province":"Li\u00e8ge",
    "sg:tags":[
        "caf\u00e9s"
    ],
    "wof:name":"Aux Caves D'artois",
    "wof:placetype":"venue"
},
  "geometry": {"coordinates":[5.8776679039,50.5979423523],"type":"Point"}
}