{
  "type": "Feature",
  "properties": {
    "iso:country":"BE",
    "sg:address":"Chauss\u00e9e De Tirlemont 3",
    "sg:city":"Wanze",
    "sg:classifiers":[
        {
            "category":"Professional",
            "subcategory":"Lawyer & Legal Services",
            "type":"Services"
        }
    ],
    "sg:phone":"+32 85 31 85 41",
    "sg:postcode":"4520",
    "sg:province":"Li\u00e8ge",
    "wof:name":"Guiot Etienne",
    "wof:placetype":"venue"
},
  "geometry": {"coordinates":[5.2189598083,50.5319213867],"type":"Point"}
}