{
  "type": "Feature",
  "properties": {
    "iso:country":"BE",
    "sg:address":"Oostmalsesteenweg 122",
    "sg:city":"Ranst (emblem)",
    "sg:classifiers":[
        {
            "category":"Home & Garden",
            "subcategory":"Carpets & Floor Coverings",
            "type":"Retail Goods"
        }
    ],
    "sg:phone":"+32 3 485 53 80",
    "sg:postcode":"2520",
    "sg:province":"Antwerpen",
    "sg:tags":[
        "parquet"
    ],
    "wof:name":"Euro-parket",
    "wof:placetype":"venue"
},
  "geometry": {"coordinates":[4.6145701408,51.1672286987],"type":"Point"}
}