{
  "type": "Feature",
  "properties": {
    "iso:country":"BE",
    "sg:address":"Chauss\u00e9e De Marche 659",
    "sg:city":"Namur (wierde)",
    "sg:classifiers":[
        {
            "category":"Building & Trades",
            "subcategory":"Cleaning & Sanitation",
            "type":"Services"
        }
    ],
    "sg:phone":"+32 81 40 19 20",
    "sg:postcode":"5100",
    "sg:province":"Namur",
    "sg:tags":[
        "machine",
        "street",
        "maintenance"
    ],
    "wof:name":"Glutton Div Of Lange Ch Sa",
    "wof:placetype":"venue"
},
  "geometry": {"coordinates":[4.8713750839,50.4566345215],"type":"Point"}
}