{
  "type": "Feature",
  "properties": {
    "iso:country":"BE",
    "sg:address":"Rue Des Moutons 61",
    "sg:city":"Bruxelles (uccle)",
    "sg:classifiers":[
        {
            "category":"Real Estate",
            "subcategory":"Architect",
            "type":"Services"
        }
    ],
    "sg:phone":"+32 2 375 59 47",
    "sg:postcode":"1180",
    "sg:province":"Bruxelles-Capitale",
    "wof:name":"Aron J",
    "wof:placetype":"venue"
},
  "geometry": {"coordinates":[4.338075161,50.7941169739],"type":"Point"}
}