{
  "type": "Feature",
  "properties": {
    "addr:full":"Rombaut Keldermansstraat 9 Edegem Antwerpen 2650",
    "addr:housenumber":"9",
    "addr:postcode":"2650",
    "addr:street":"Rombaut Keldermansstraat",
    "iso:country":"BE",
    "sg:address":"Rombaut Keldermansstraat 9",
    "sg:city":"Edegem",
    "sg:orig_category":"M\u00e9decins and sp\u00e9cialistes",
    "sg:phone":"+32 3 449 28 25",
    "sg:postcode":"2650",
    "sg:province":"Antwerpen",
    "wof:name":"Paul Vermeersch",
    "wof:placetype":"venue"
},
  "geometry": {"coordinates":[4.4429907799,51.1644554138],"type":"Point"}
}