{
  "type": "Feature",
  "properties": {
    "iso:country":"BE",
    "sg:address":"20",
    "sg:city":"Mechelsestraat 1800 Vilvoorde",
    "sg:classifiers":[
        {
            "category":"Travel",
            "subcategory":"Hotels & Motels",
            "type":"Entertainment"
        }
    ],
    "sg:phone":"+32 2 252 04 10",
    "sg:postcode":"20",
    "sg:tags":[
        "hotels",
        "business",
        "restaurant"
    ],
    "wof:name":"Restaurant De Griekse Piraat Nv",
    "wof:placetype":"venue"
},
  "geometry": {"coordinates":[4.4230499268,50.9311141968],"type":"Point"}
}