{
  "type": "Feature",
  "properties": {
    "addr:full":"Steenweg 48 Lanaken Limburg 3621",
    "addr:housenumber":"48",
    "addr:postcode":"3621",
    "addr:street":"Steenweg",
    "iso:country":"BE",
    "sg:address":"Steenweg 48",
    "sg:city":"Lanaken",
    "sg:orig_category":"Supermarch\u00e9s",
    "sg:postcode":"3621",
    "sg:province":"Limburg",
    "wof:name":"Aldi",
    "wof:placetype":"venue"
},
  "geometry": {"coordinates":[5.6838340759,50.9165840149],"type":"Point"}
}