{
  "type": "Feature",
  "properties": {
    "addr:full":"Brusselsesteenweg 51 Lebbeke Oost-Vlaanderen 9280",
    "addr:housenumber":"51",
    "addr:postcode":"9280",
    "addr:street":"Brusselsesteenweg",
    "iso:country":"BE",
    "sg:address":"Brusselsesteenweg 51",
    "sg:city":"Lebbeke",
    "sg:classifiers":[
        {
            "category":"Wholesale",
            "subcategory":"Beer",
            "type":"Manufacturing & Wholesale Goods"
        }
    ],
    "sg:phone":"+32 52 41 14 23",
    "sg:postcode":"9280",
    "sg:province":"Oost-Vlaanderen",
    "sg:tags":[
        "ale",
        "-"
    ],
    "wof:name":"Drankencent De Maeseneir-grepi Nv",
    "wof:placetype":"venue"
},
  "geometry": {"coordinates":[4.1290922165,50.9989700317],"type":"Point"}
}