{
  "type": "Feature",
  "properties": {
    "iso:country":"BE",
    "sg:address":"Dorp 69-71",
    "sg:city":"Assenede (bassevelde)",
    "sg:classifiers":[
        {
            "category":"Health Services",
            "subcategory":"Doctor",
            "type":"Services"
        }
    ],
    "sg:phone":"+32 9 373 82 64",
    "sg:postcode":"9968",
    "sg:province":"Oost-Vlaanderen",
    "sg:tags":[
        "medicinephysicians",
        "surgeon"
    ],
    "wof:name":"De Coninck Ph",
    "wof:placetype":"venue"
},
  "geometry": {"coordinates":[3.6887938976,51.1923027039],"type":"Point"}
}