{
  "type": "Feature",
  "properties": {
    "iso:country":"BE",
    "sg:address":"Baron Ruzettelaan 29",
    "sg:city":"Brugge",
    "sg:orig_category":"Advocaten and juridische adviseurs",
    "sg:phone":"+32 50 37 59 16",
    "sg:postcode":"8310",
    "sg:province":"West-Vlaanderen",
    "wof:name":"M. Maus",
    "wof:placetype":"venue"
},
  "geometry": {"coordinates":[3.231192112,51.1982002258],"type":"Point"}
}