{
  "type": "Feature",
  "properties": {
    "iso:country":"BE",
    "sg:address":"Waasmontstraat 27",
    "sg:city":"Landen",
    "sg:orig_category":"M\u00e9decins and sp\u00e9cialistes",
    "sg:phone":"+32 11 88 26 81",
    "sg:postcode":"3401",
    "sg:province":"Vlaams-Brabant",
    "wof:name":"Micheline Freson",
    "wof:placetype":"venue"
},
  "geometry": {"coordinates":[5.0856947899,50.7252006531],"type":"Point"}
}