{
  "type": "Feature",
  "properties": {
    "iso:country":"BE",
    "sg:address":"Avenue Livingstone 33",
    "sg:city":"Bruxelles",
    "sg:classifiers":[
        {
            "category":"Government",
            "subcategory":"Office",
            "type":"Public Place"
        }
    ],
    "sg:phone":"+32 2 286 51 70",
    "sg:postcode":"1000",
    "sg:province":"Bruxelles-Capitale",
    "sg:tags":[
        "chamber",
        "industry",
        "commerce"
    ],
    "wof:name":"Berlin Business Representation",
    "wof:placetype":"venue"
},
  "geometry": {"coordinates":[4.3782100677,50.8456840515],"type":"Point"}
}