{
  "type": "Feature",
  "properties": {
    "addr:full":"Chauss\u00e9e D'anvers 295 Bruxelles Bruxelles-Capitale 1000",
    "addr:housenumber":"295",
    "addr:postcode":"1000",
    "addr:street":"Chausse\u0301E D'Anvers",
    "iso:country":"BE",
    "sg:address":"Chauss\u00e9e D'anvers 295",
    "sg:city":"Bruxelles",
    "sg:classifiers":[
        {
            "category":"Social Services",
            "type":"Services"
        }
    ],
    "sg:phone":"+32 2 203 34 24",
    "sg:postcode":"1000",
    "sg:province":"Bruxelles-Capitale",
    "wof:name":"Risobrussel",
    "wof:placetype":"venue"
},
  "geometry": {"coordinates":[4.3584418297,50.8656845093],"type":"Point"}
}