{
  "type": "Feature",
  "properties": {
    "addr:full":"Chauss\u00e9e D'eghez\u00e9e 25 La Bruy\u00e8re (saint-denis) Namur 5081",
    "addr:housenumber":"25",
    "addr:postcode":"5081",
    "addr:street":"Chausse\u0301E D'Egheze \u0301E;Bruye\u0300Re Saint-Denis",
    "iso:country":"BE",
    "sg:address":"Chauss\u00e9e D'eghez\u00e9e 25",
    "sg:city":"La Bruy\u00e8re (saint-denis)",
    "sg:classifiers":[
        {
            "category":"Building & Trades",
            "subcategory":"Construction",
            "type":"Services"
        }
    ],
    "sg:phone":"+32 81 56 79 46",
    "sg:postcode":"5081",
    "sg:province":"Namur",
    "sg:tags":[
        "installation",
        "-",
        "central",
        "heating"
    ],
    "wof:name":"Jacquet C Sprl",
    "wof:placetype":"venue"
},
  "geometry": {"coordinates":[4.7865719795,50.5369911194],"type":"Point"}
}