{
  "type": "Feature",
  "properties": {
    "iso:country":"BE",
    "sg:address":"Avenue De Levis Mirepoix 62",
    "sg:city":"Bruxelles (jette)",
    "sg:classifiers":[
        {
            "category":"Food & Beverages",
            "subcategory":"Groceries & Convenience Stores",
            "type":"Retail Goods"
        }
    ],
    "sg:phone":"+32 2 428 58 70",
    "sg:postcode":"1090",
    "sg:province":"Bruxelles-Capitale",
    "sg:tags":[
        "grocer"
    ],
    "wof:name":"Amritsar",
    "wof:placetype":"venue"
},
  "geometry": {"coordinates":[4.3310742378,50.871837616],"type":"Point"}
}