{
  "type": "Feature",
  "properties": {
    "addr:full":"Rue Des Champs Elys\u00e9es 18d Bruxelles (ixelles) Bruxelles-Capitale 1050",
    "addr:housenumber":"18d",
    "addr:postcode":"1050",
    "addr:street":"Rue Des Champs Elyse\u0301Es",
    "iso:country":"BE",
    "sg:address":"Rue Des Champs Elys\u00e9es 18d",
    "sg:city":"Bruxelles (ixelles)",
    "sg:classifiers":[
        {
            "category":"Professional",
            "subcategory":"Art Services",
            "type":"Services"
        }
    ],
    "sg:phone":"+32 2 649 42 12",
    "sg:postcode":"1050",
    "sg:province":"Bruxelles-Capitale",
    "sg:tags":[
        "interior",
        "designer"
    ],
    "wof:name":"Barberis F",
    "wof:placetype":"venue"
},
  "geometry": {"coordinates":[4.3675098419,50.8312988281],"type":"Point"}
}