{
  "type": "Feature",
  "properties": {
    "addr:full":"Gitsestraat 265 Roeselare West-Vlaanderen 8800",
    "addr:housenumber":"265",
    "addr:postcode":"8800",
    "addr:street":"Gitsestraat",
    "iso:country":"BE",
    "sg:address":"Gitsestraat 265",
    "sg:city":"Roeselare",
    "sg:orig_category":"Kapsalons",
    "sg:phone":"+32 51 20 78 77",
    "sg:postcode":"8800",
    "sg:province":"West-Vlaanderen",
    "wof:name":"Coiffure Kristien",
    "wof:placetype":"venue"
},
  "geometry": {"coordinates":[3.117347002,50.9595870972],"type":"Point"}
}