{
  "type": "Feature",
  "properties": {
    "iso:country":"BE",
    "sg:address":"Rue Marie-christine 212",
    "sg:city":"Bruxelles",
    "sg:classifiers":[
        {
            "category":"Retail",
            "subcategory":"Laundry & Dry Cleaning",
            "type":"Services"
        }
    ],
    "sg:phone":"+32 2 424 32 62",
    "sg:postcode":"1020",
    "sg:province":"Bruxelles-Capitale",
    "wof:name":"Eda Sprl",
    "wof:placetype":"venue"
},
  "geometry": {"coordinates":[4.349424839,50.8766975403],"type":"Point"}
}