{
  "type": "Feature",
  "properties": {
    "iso:country":"BE",
    "sg:address":"Lange Meersstraat 24",
    "sg:city":"Sint-gillis-waas",
    "sg:orig_category":"Fruitteelt",
    "sg:phone":"+32 3 773 47 32",
    "sg:postcode":"9170",
    "sg:province":"Oost-Vlaanderen",
    "wof:name":"Domien De Block",
    "wof:placetype":"venue"
},
  "geometry": {"coordinates":[4.1486258507,51.245891571],"type":"Point"}
}