{
  "type": "Feature",
  "properties": {
    "iso:country":"BE",
    "sg:address":"Edward Vlietinckstraat 7",
    "sg:city":"Oostende (stene)",
    "sg:classifiers":[
        {
            "category":"Real Estate",
            "subcategory":"Real Estate Agent",
            "type":"Services"
        }
    ],
    "sg:phone":"+32 59 50 68 87",
    "sg:postcode":"8400",
    "sg:province":"West-Vlaanderen",
    "sg:tags":[
        "importer",
        "champagne",
        "-"
    ],
    "wof:name":"Wijnhuis Douchy",
    "wof:placetype":"venue"
},
  "geometry": {"coordinates":[2.9364879131,51.2069664001],"type":"Point"}
}