{
  "type": "Feature",
  "properties": {
    "iso:country":"BE",
    "sg:address":"Rue De La Colombi\u00c8re 11",
    "sg:city":"Grace-hollogne",
    "sg:classifiers":[
        {
            "category":"Arena",
            "subcategory":"Sports Club",
            "type":"Entertainment"
        }
    ],
    "sg:phone":"+32 4 263 56 28",
    "sg:postcode":"4460",
    "sg:province":"Li\u00e8ge",
    "sg:tags":[
        "terrain",
        "hors",
        "de",
        "installation",
        "sportifs"
    ],
    "wof:name":"R. Daring Club Grace",
    "wof:placetype":"venue"
},
  "geometry": {"coordinates":[5.4963212013,50.646232605],"type":"Point"}
}