{
  "type": "Feature",
  "properties": {
    "addr:full":"Langdries 19 Haaltert Oost-Vlaanderen 9450",
    "addr:housenumber":"19",
    "addr:postcode":"9450",
    "addr:street":"Langdries",
    "iso:country":"BE",
    "sg:address":"Langdries 19",
    "sg:city":"Haaltert",
    "sg:classifiers":[
        {
            "category":"Building & Trades",
            "subcategory":"Construction",
            "type":"Services"
        }
    ],
    "sg:phone":"+32 53 83 10 88",
    "sg:postcode":"9450",
    "sg:province":"Oost-Vlaanderen",
    "sg:tags":[
        "stair"
    ],
    "wof:name":"Muylaert D",
    "wof:placetype":"venue"
},
  "geometry": {"coordinates":[4.0278549194,50.9047088623],"type":"Point"}
}