{
  "type": "Feature",
  "properties": {
    "addr:full":"Rue Anselme Mary 26 Ecaussinnes Hainaut 7190",
    "addr:housenumber":"26",
    "addr:postcode":"7190",
    "addr:street":"Rue Anselme Mary;Hainaut",
    "iso:country":"BE",
    "sg:address":"Rue Anselme Mary 26",
    "sg:city":"Ecaussinnes",
    "sg:orig_category":"Woningbouw",
    "sg:phone":"+32 67 44 45 35",
    "sg:postcode":"7190",
    "sg:province":"Hainaut",
    "wof:name":"Romain Buffe",
    "wof:placetype":"venue"
},
  "geometry": {"coordinates":[4.1494460106,50.5610427856],"type":"Point"}
}