{
  "type": "Feature",
  "properties": {
    "iso:country":"BE",
    "sg:address":"Gelindenstraat 108",
    "sg:city":"Heers",
    "sg:orig_category":"Charpentes and couvertures",
    "sg:phone":"+32 11 48 13 71",
    "sg:postcode":"3870",
    "sg:province":"Limburg",
    "wof:name":"Jemabo",
    "wof:placetype":"venue"
},
  "geometry": {"coordinates":[5.2563419342,50.7415466309],"type":"Point"}
}