{
  "type": "Feature",
  "properties": {
    "iso:country":"BE",
    "sg:address":"Statiestraat 2",
    "sg:city":"Anzegem",
    "sg:orig_category":"Electrom\u00e9nager, t\u00e9l\u00e9visions and radios",
    "sg:phone":"+32 56 68 15 00",
    "sg:postcode":"8570",
    "sg:province":"West-Vlaanderen",
    "wof:name":"Pascal Vandevelde",
    "wof:placetype":"venue"
},
  "geometry": {"coordinates":[3.4814200401,50.83253479],"type":"Point"}
}