{
  "type": "Feature",
  "properties": {
    "addr:full":"Maasstraat 36 Antwerpen Antwerpen 2060",
    "addr:housenumber":"36",
    "addr:postcode":"2060",
    "addr:street":"Maasstraat",
    "iso:country":"BE",
    "sg:address":"Maasstraat 36",
    "sg:city":"Antwerpen",
    "sg:orig_category":"Installation \u00e9lectrique r\u00e9sidentielle",
    "sg:phone":"+32 3 226 56 27",
    "sg:postcode":"2060",
    "sg:province":"Antwerpen",
    "wof:name":"Ref Belgium",
    "wof:placetype":"venue"
},
  "geometry": {"coordinates":[4.4275078773,51.2344322205],"type":"Point"}
}