{
  "type": "Feature",
  "properties": {
    "addr:full":"Haagstraat 25 Dendermonde Oost-Vlaanderen 9200",
    "addr:housenumber":"25",
    "addr:postcode":"9200",
    "addr:street":"Haagstraat;Oost-Vlaanderen",
    "iso:country":"BE",
    "sg:address":"Haagstraat 25",
    "sg:city":"Dendermonde",
    "sg:orig_category":"Fleurs and plantes",
    "sg:phone":"+32 52 22 55 65",
    "sg:postcode":"9200",
    "sg:province":"Oost-Vlaanderen",
    "wof:name":"Sarens J. & Van Biesen G.",
    "wof:placetype":"venue"
},
  "geometry": {"coordinates":[4.1187410355,51.0136413574],"type":"Point"}
}