{
  "type": "Feature",
  "properties": {
    "iso:country":"BE",
    "sg:address":"Keienberg 1",
    "sg:city":"Ninove",
    "sg:classifiers":[
        {
            "category":"Taxi",
            "type":"Transportation"
        }
    ],
    "sg:phone":"+32 54 32 37 76",
    "sg:postcode":"9400",
    "sg:province":"Oost-Vlaanderen",
    "sg:tags":[
        "sp\u00e9ciaux"
    ],
    "wof:name":"Taxi Otte-van Snick",
    "wof:placetype":"venue"
},
  "geometry": {"coordinates":[3.9558401108,50.8509216309],"type":"Point"}
}