{
  "type": "Feature",
  "properties": {
    "iso:country":"BE",
    "sg:address":"Jachthoornlaan 29",
    "sg:city":"Zoersel",
    "sg:classifiers":[
        {
            "category":"Banks & Credit Unions",
            "subcategory":"Investment Brokerage",
            "type":"Services"
        }
    ],
    "sg:phone":"+32 3 309 07 53",
    "sg:postcode":"2980",
    "sg:province":"Antwerpen",
    "sg:tags":[
        "auditor"
    ],
    "wof:name":"Oeyen L Bvba",
    "wof:placetype":"venue"
},
  "geometry": {"coordinates":[4.6975421906,51.2667388916],"type":"Point"}
}