{
  "type": "Feature",
  "properties": {
    "addr:full":"Stationsstraat 52 Waasmunster Oost-Vlaanderen 9250",
    "addr:housenumber":"52",
    "addr:postcode":"9250",
    "addr:street":"Stationsstraat",
    "iso:country":"BE",
    "sg:address":"Stationsstraat 52",
    "sg:city":"Waasmunster",
    "sg:classifiers":[
        {
            "category":"Building & Trades",
            "subcategory":"Construction",
            "type":"Services"
        }
    ],
    "sg:phone":"+32 52 46 38 41",
    "sg:postcode":"9250",
    "sg:province":"Oost-Vlaanderen",
    "sg:tags":[
        "carpenter"
    ],
    "wof:name":"D'hondt G",
    "wof:placetype":"venue"
},
  "geometry": {"coordinates":[4.0964531898,51.1130523682],"type":"Point"}
}