{
  "type": "Feature",
  "properties": {
    "addr:full":"Rue L\u00e9opold 4 Bruxelles Bruxelles-Capitale 1000",
    "addr:housenumber":"4",
    "addr:postcode":"1000",
    "addr:street":"Rue Le\u0301Opold",
    "iso:country":"BE",
    "sg:address":"Rue L\u00e9opold 4",
    "sg:city":"Bruxelles",
    "sg:classifiers":[
        {
            "category":"Arts & Performance",
            "subcategory":"Theater",
            "type":"Entertainment"
        }
    ],
    "sg:phone":"+32 2 229 12 00",
    "sg:postcode":"1000",
    "sg:province":"Bruxelles-Capitale",
    "sg:tags":[
        "concert-halls",
        "theatre"
    ],
    "wof:name":"Munt (de)",
    "wof:placetype":"venue"
},
  "geometry": {"coordinates":[4.3545107841,50.8494796753],"type":"Point"}
}