{
  "type": "Feature",
  "properties": {
    "iso:country":"BE",
    "sg:address":"Gote 33",
    "sg:city":"Ophasselt",
    "sg:classifiers":[
        {
            "category":"Professional",
            "subcategory":"Engineering",
            "type":"Services"
        }
    ],
    "sg:phone":"+32 69 22 23 24",
    "sg:postcode":"9500",
    "sg:province":"Oost-Vlaanderen",
    "sg:tags":[
        "machine",
        "-",
        "environment",
        "equipment",
        "machinery",
        "mechanical"
    ],
    "wof:name":"Anciens Etablissements Fernand Pennequin Et Cie Sprl",
    "wof:placetype":"venue"
},
  "geometry": {"coordinates":[3.3812949657,50.6222915649],"type":"Point"}
}