{
  "type": "Feature",
  "properties": {
    "addr:full":"Pierre Theunisstraat 1b81 Schaarbeek/schaerbeek Bruxelles-Capitale 1030",
    "addr:housenumber":"1b81",
    "addr:postcode":"1030",
    "addr:street":"Pierre Theunisstraat",
    "iso:country":"BE",
    "sg:address":"Pierre Theunisstraat 1b81",
    "sg:city":"Schaarbeek/schaerbeek",
    "sg:orig_category":"Alternatieve geneeskunde",
    "sg:phone":"+32 2 241 62 44",
    "sg:postcode":"1030",
    "sg:province":"Bruxelles-Capitale",
    "wof:name":"Fr\u00c9d\u00c9ric Bosendorf",
    "wof:placetype":"venue"
},
  "geometry": {"coordinates":[4.3892908096,50.8676452637],"type":"Point"}
}