{
  "type": "Feature",
  "properties": {
    "addr:full":"Rue De La Station 1 Plombi\u00e8res (hombourg) Li\u00e8ge 4852",
    "addr:housenumber":"1",
    "addr:postcode":"4852",
    "addr:street":"Rue De La Station",
    "iso:country":"BE",
    "sg:address":"Rue De La Station 1",
    "sg:city":"Plombi\u00e8res (hombourg)",
    "sg:classifiers":[
        {
            "category":"Freight",
            "type":"Transportation"
        }
    ],
    "sg:phone":"+32 87 78 78 21",
    "sg:postcode":"4852",
    "sg:province":"Li\u00e8ge",
    "sg:tags":[
        "-",
        "transport"
    ],
    "wof:name":"Ladry & Fils",
    "wof:placetype":"venue"
},
  "geometry": {"coordinates":[5.919711113,50.7227592468],"type":"Point"}
}