{
  "type": "Feature",
  "properties": {
    "iso:country":"BE",
    "sg:address":"Torenstraat 12b2",
    "sg:city":"Hasselt",
    "sg:orig_category":"Binnenhuisarchitecten",
    "sg:phone":"+32 11 27 28 85",
    "sg:postcode":"3500",
    "sg:province":"Limburg",
    "wof:name":"Internia",
    "wof:placetype":"venue"
},
  "geometry": {"coordinates":[5.3292808533,50.9257011414],"type":"Point"}
}