{
  "type": "Feature",
  "properties": {
    "iso:country":"BE",
    "sg:address":"Aartrijkestraat 229",
    "sg:city":"Torhout",
    "sg:classifiers":[
        {
            "category":"Home & Garden",
            "subcategory":"Building Materials",
            "type":"Retail Goods"
        }
    ],
    "sg:phone":"+32 50 21 10 70",
    "sg:postcode":"8820",
    "sg:province":"West-Vlaanderen",
    "sg:tags":[
        "veranda"
    ],
    "wof:name":"Degrande Daniel & Zn Bvba",
    "wof:placetype":"venue"
},
  "geometry": {"coordinates":[3.0995459557,51.0869865417],"type":"Point"}
}