{
  "type": "Feature",
  "properties": {
    "addr:full":"Nieuwpoortsesteenweg 392 Oostende West-Vlaanderen 8400",
    "addr:housenumber":"392",
    "addr:postcode":"8400",
    "addr:street":"Nieuwpoortsesteenweg",
    "iso:country":"BE",
    "sg:address":"Nieuwpoortsesteenweg 392",
    "sg:city":"Oostende",
    "sg:classifiers":[
        {
            "category":"Bars & Pubs",
            "type":"Food & Drink"
        }
    ],
    "sg:phone":"+32 59 80 55 15",
    "sg:postcode":"8400",
    "sg:province":"West-Vlaanderen",
    "wof:name":"Viking (de)",
    "wof:placetype":"venue"
},
  "geometry": {"coordinates":[2.8928000927,51.2171516418],"type":"Point"}
}