{
  "type": "Feature",
  "properties": {
    "iso:country":"BE",
    "sg:address":"Waterloose Steenweg 1379",
    "sg:city":"Ukkel/uccle",
    "sg:orig_category":"Banken and kredietinstellingen",
    "sg:phone":"+32 2 374 00 12",
    "sg:postcode":"1180",
    "sg:province":"Bruxelles-Capitale",
    "wof:name":"Unibank",
    "wof:placetype":"venue"
},
  "geometry": {"coordinates":[4.375535965,50.7876701355],"type":"Point"}
}