{
  "type": "Feature",
  "properties": {
    "addr:full":"M. Van Der Borghtstraat 45 Putte Antwerpen 2580",
    "addr:housenumber":"45",
    "addr:postcode":"2580",
    "addr:street":"M. Van Der Borghtstraat",
    "iso:country":"BE",
    "sg:address":"M. Van Der Borghtstraat 45",
    "sg:city":"Putte",
    "sg:orig_category":"Brood, gebak and snoepgoed",
    "sg:phone":"+32 15 23 31 75",
    "sg:postcode":"2580",
    "sg:province":"Antwerpen",
    "wof:name":"Heylen-troonbeeckx",
    "wof:placetype":"venue"
},
  "geometry": {"coordinates":[4.6569900513,51.0292205811],"type":"Point"}
}