{
  "type": "Feature",
  "properties": {
    "addr:full":"18 Rue Aux Crameux 4690 Bassenge 18",
    "addr:housenumber":"18;18",
    "addr:postcode":"4690",
    "addr:street":"Rue Aux Crameux",
    "iso:country":"BE",
    "sg:address":"18",
    "sg:city":"Rue Aux Crameux 4690 Bassenge",
    "sg:classifiers":[
        {
            "category":"Manufacturing",
            "subcategory":"Printing",
            "type":"Manufacturing & Wholesale Goods"
        }
    ],
    "sg:phone":"+32 4 286 21 23",
    "sg:postcode":"18",
    "sg:tags":[
        "publishing"
    ],
    "wof:name":"Reliure Industrielle Liegeoise Sa",
    "wof:placetype":"venue"
},
  "geometry": {"coordinates":[5.5712499619,50.7508544922],"type":"Point"}
}