{
  "type": "Feature",
  "properties": {
    "addr:full":"Berlaarbaan 258 Sint-katelijne-waver Antwerpen 2861",
    "addr:housenumber":"258",
    "addr:postcode":"2861",
    "addr:street":"Berlaarbaan",
    "iso:country":"BE",
    "sg:address":"Berlaarbaan 258",
    "sg:city":"Sint-katelijne-waver",
    "sg:orig_category":"Groententeelt",
    "sg:phone":"+32 15 55 15 69",
    "sg:postcode":"2861",
    "sg:province":"Antwerpen",
    "wof:name":"Jozef Uytterhoeven",
    "wof:placetype":"venue"
},
  "geometry": {"coordinates":[4.5480341911,51.0570640564],"type":"Point"}
}