{
  "type": "Feature",
  "properties": {
    "addr:full":"Geraardsbergsesteenweg 36 Melle Oost-Vlaanderen 9090",
    "addr:housenumber":"36",
    "addr:postcode":"9090",
    "addr:street":"Geraardsbergsesteenweg",
    "iso:country":"BE",
    "sg:address":"Geraardsbergsesteenweg 36",
    "sg:city":"Melle",
    "sg:classifiers":[
        {
            "category":"Bars & Pubs",
            "type":"Food & Drink"
        }
    ],
    "sg:phone":"+32 9 252 27 21",
    "sg:postcode":"9090",
    "sg:province":"Oost-Vlaanderen",
    "wof:name":"Lammeken('t)",
    "wof:placetype":"venue"
},
  "geometry": {"coordinates":[3.7984209061,50.9918174744],"type":"Point"}
}