{
  "type": "Feature",
  "properties": {
    "iso:country":"BE",
    "sg:address":"Oude Beestenmarkt 12",
    "sg:city":"Veurne",
    "sg:classifiers":[
        {
            "category":"Personal",
            "subcategory":"Beauty Salon",
            "type":"Services"
        }
    ],
    "sg:phone":"+32 58 31 39 32",
    "sg:postcode":"8630",
    "sg:province":"West-Vlaanderen",
    "sg:tags":[
        "lady",
        "-",
        "hairdressing"
    ],
    "wof:name":"Vogue",
    "wof:placetype":"venue"
},
  "geometry": {"coordinates":[2.6600120068,51.0709953308],"type":"Point"}
}