{
  "type": "Feature",
  "properties": {
    "addr:full":"Rue Des Mini\u00c8res 55 Walcourt Namur 5650",
    "addr:housenumber":"55",
    "addr:postcode":"5650",
    "addr:street":"Rue Des Minie\u0300Res",
    "iso:country":"BE",
    "sg:address":"Rue Des Mini\u00c8res 55",
    "sg:city":"Walcourt",
    "sg:orig_category":"Eleveurs d'animaux domestiques",
    "sg:phone":"+32 71 65 55 19",
    "sg:postcode":"5650",
    "sg:province":"Namur",
    "wof:name":"Elevage De La Mineaudi\u00c8re",
    "wof:placetype":"venue"
},
  "geometry": {"coordinates":[4.4313349724,50.2514762878],"type":"Point"}
}