{
  "type": "Feature",
  "properties": {
    "addr:full":"Rue Major P\u00e9tillon 4 Box 1 Bruxelles (etterbeek) Bruxelles-Capitale 1040",
    "addr:housenumber":"4;1",
    "addr:postcode":"1040",
    "addr:street":"Rue Major Pe\u0301Tillon;Box",
    "iso:country":"BE",
    "sg:address":"Rue Major P\u00e9tillon 4 Box 1",
    "sg:city":"Bruxelles (etterbeek)",
    "sg:classifiers":[
        {
            "category":"Organizations",
            "subcategory":"Professional Association",
            "type":"Services"
        }
    ],
    "sg:phone":"+32 2 734 32 35",
    "sg:postcode":"1040",
    "sg:province":"Bruxelles-Capitale",
    "sg:tags":[
        "trade-union",
        "federation"
    ],
    "wof:name":"Belcamp",
    "wof:placetype":"venue"
},
  "geometry": {"coordinates":[4.4024448395,50.8287963867],"type":"Point"}
}