{
  "type": "Feature",
  "properties": {
    "addr:full":"Rue De La Croix Bande 1 Marche-en-famenne Luxembourg 6900",
    "addr:housenumber":"1",
    "addr:postcode":"6900",
    "addr:street":"Rue De La Croix Bande",
    "iso:country":"BE",
    "sg:address":"Rue De La Croix Bande 1",
    "sg:city":"Marche-en-famenne",
    "sg:classifiers":[
        {
            "category":"Building & Trades",
            "subcategory":"Construction",
            "type":"Services"
        }
    ],
    "sg:phone":"+32 71 30 62 60",
    "sg:postcode":"6900",
    "sg:province":"Luxembourg",
    "sg:tags":[
        "carpenter's",
        "work",
        "supraregional"
    ],
    "wof:name":"Tuyauteries De La Sambre S.a.",
    "wof:placetype":"venue"
},
  "geometry": {"coordinates":[4.4880981445,50.4251937866],"type":"Point"}
}