{
  "type": "Feature",
  "properties": {
    "addr:full":"Brugsesteenweg 302 Roeselare West-Vlaanderen 8800",
    "addr:housenumber":"302",
    "addr:postcode":"8800",
    "addr:street":"Brugsesteenweg",
    "iso:country":"BE",
    "sg:address":"Brugsesteenweg 302",
    "sg:city":"Roeselare",
    "sg:classifiers":[
        {
            "category":"Shopping",
            "subcategory":"Crafts & Fabrics",
            "type":"Retail Goods"
        }
    ],
    "sg:phone":"+32 51 22 63 75",
    "sg:postcode":"8800",
    "sg:province":"West-Vlaanderen",
    "sg:tags":[
        "paints",
        "varnish",
        "-",
        "lacquers",
        "enamel"
    ],
    "wof:name":"Colora Bvba",
    "wof:placetype":"venue"
},
  "geometry": {"coordinates":[3.1208450794,50.9642028809],"type":"Point"}
}