{
  "type": "Feature",
  "properties": {
    "iso:country":"BE",
    "sg:address":"Waalse Kaai 10",
    "sg:city":"Antwerpen",
    "sg:classifiers":[
        {
            "category":"Restaurant",
            "type":"Food & Drink"
        }
    ],
    "sg:phone":"+32 3 237 73 10",
    "sg:postcode":"2000",
    "sg:province":"Antwerpen",
    "wof:name":"Par Hasard",
    "wof:placetype":"venue"
},
  "geometry": {"coordinates":[4.3915657997,51.2120399475],"type":"Point"}
}