{
  "type": "Feature",
  "properties": {
    "iso:country":"BE",
    "sg:address":"Place Gravi\u00c8re 1",
    "sg:city":"Huy",
    "sg:orig_category":"Experts-comptables",
    "sg:phone":"+32 85 84 34 31",
    "sg:postcode":"4500",
    "sg:province":"Li\u00e8ge",
    "wof:name":"Marie Thiry",
    "wof:placetype":"venue"
},
  "geometry": {"coordinates":[5.2400307655,50.5178337097],"type":"Point"}
}