{
  "type": "Feature",
  "properties": {
    "addr:full":"Rue De La Sarriette 11 Ottignies-louvain-la-neuve Brabant Wallon 1348",
    "addr:housenumber":"11",
    "addr:postcode":"1348",
    "addr:street":"Rue De La Sarriette",
    "iso:country":"BE",
    "sg:address":"Rue De La Sarriette 11",
    "sg:city":"Ottignies-louvain-la-neuve",
    "sg:orig_category":"Artsen and specialisten",
    "sg:phone":"+32 10 45 02 74",
    "sg:postcode":"1348",
    "sg:province":"Brabant Wallon",
    "wof:name":"Maria-consuelo Cornejo Montero",
    "wof:placetype":"venue"
},
  "geometry": {"coordinates":[4.6182842255,50.6631164551],"type":"Point"}
}