{
  "type": "Feature",
  "properties": {
    "iso:country":"BE",
    "sg:address":"Oostpoeselstraat 14",
    "sg:city":"Lo-reninge",
    "sg:orig_category":"Rundveehouders Varkenskwekers",
    "sg:phone":"+32 51 54 45 94",
    "sg:postcode":"8647",
    "sg:province":"West-Vlaanderen",
    "wof:name":"Andre Tylleman",
    "wof:placetype":"venue"
},
  "geometry": {"coordinates":[2.8467218876,50.9370536804],"type":"Point"}
}