{
  "type": "Feature",
  "properties": {
    "addr:full":"Grand'route 50a Mont-saint-guibert Brabant Wallon 1435",
    "addr:housenumber":"50a",
    "addr:postcode":"1435",
    "addr:street":"Grand'Route",
    "iso:country":"BE",
    "sg:address":"Grand'route 50a",
    "sg:city":"Mont-saint-guibert",
    "sg:classifiers":[
        {
            "category":"Restaurant",
            "type":"Food & Drink"
        }
    ],
    "sg:phone":"+32 10 65 05 03",
    "sg:postcode":"1435",
    "sg:province":"Brabant Wallon",
    "wof:name":"Magic Castel",
    "wof:placetype":"venue"
},
  "geometry": {"coordinates":[4.6107521057,50.6339874268],"type":"Point"}
}