{
  "type": "Feature",
  "properties": {
    "addr:full":"Huisepontweg 47 Nazareth Oost-Vlaanderen 9810",
    "addr:housenumber":"47",
    "addr:postcode":"9810",
    "addr:street":"Huisepontweg",
    "iso:country":"BE",
    "sg:address":"Huisepontweg 47",
    "sg:city":"Nazareth",
    "sg:orig_category":"Eleveurs and marchands de porcs",
    "sg:phone":"+32 9 386 44 64",
    "sg:postcode":"9810",
    "sg:province":"Oost-Vlaanderen",
    "wof:name":"Noel Goeminne",
    "wof:placetype":"venue"
},
  "geometry": {"coordinates":[3.5664839745,50.9434890747],"type":"Point"}
}