{
  "type": "Feature",
  "properties": {
    "iso:country":"BE",
    "sg:address":"Rue Du Roy 21",
    "sg:city":"Gouvy",
    "sg:orig_category":"Rundveehouders",
    "sg:phone":"+32 80 51 73 19",
    "sg:postcode":"6670",
    "sg:province":"Luxembourg",
    "wof:name":"Rene Boulanger",
    "wof:placetype":"venue"
},
  "geometry": {"coordinates":[5.9249272346,50.1559371948],"type":"Point"}
}