{
  "type": "Feature",
  "properties": {
    "iso:country":"BE",
    "sg:address":"Rue Henry De Rohan Chabot 41",
    "sg:city":"Florennes",
    "sg:classifiers":[
        {
            "category":"Personal",
            "subcategory":"Beauty Salon",
            "type":"Services"
        }
    ],
    "sg:phone":"+32 71 68 79 19",
    "sg:postcode":"5620",
    "sg:province":"Namur",
    "sg:tags":[
        "lady",
        "-",
        "hairdressing"
    ],
    "wof:name":"Benedicte",
    "wof:placetype":"venue"
},
  "geometry": {"coordinates":[4.6175351143,50.2460899353],"type":"Point"}
}