{
  "type": "Feature",
  "properties": {
    "addr:full":"Sint-lievenslaan 33bb Gent Oost-Vlaanderen 9000",
    "addr:housenumber":"33bb",
    "addr:postcode":"9000",
    "addr:street":"Sint-Lievenslaan;Oost-Vlaanderen",
    "iso:country":"BE",
    "sg:address":"Sint-lievenslaan 33bb",
    "sg:city":"Gent",
    "sg:orig_category":"Artsen and specialisten",
    "sg:phone":"+32 9 235 29 82",
    "sg:postcode":"9000",
    "sg:province":"Oost-Vlaanderen",
    "wof:name":"Jan De Vil",
    "wof:placetype":"venue"
},
  "geometry": {"coordinates":[3.7335801125,51.0384101868],"type":"Point"}
}