{
  "type": "Feature",
  "properties": {
    "addr:full":"Avenue Des Cerisiers 14 Bruxelles (schaerbeek) Bruxelles-Capitale 1030",
    "addr:housenumber":"14",
    "addr:postcode":"1030",
    "addr:street":"Avenue Des Cerisiers",
    "iso:country":"BE",
    "sg:address":"Avenue Des Cerisiers 14",
    "sg:city":"Bruxelles (schaerbeek)",
    "sg:classifiers":[
        {
            "category":"Health Services",
            "subcategory":"Doctor",
            "type":"Services"
        }
    ],
    "sg:phone":"+32 2 734 40 78",
    "sg:postcode":"1030",
    "sg:province":"Bruxelles-Capitale",
    "sg:tags":[
        "medicinephysicians",
        "surgeon"
    ],
    "wof:name":"De Meester C",
    "wof:placetype":"venue"
},
  "geometry": {"coordinates":[4.4040088654,50.8488578796],"type":"Point"}
}