{
  "type": "Feature",
  "properties": {
    "addr:full":"Moleneindstraat 45 Maasmechelen Limburg 3630",
    "addr:housenumber":"45",
    "addr:postcode":"3630",
    "addr:street":"Moleneindstraat",
    "iso:country":"BE",
    "sg:address":"Moleneindstraat 45",
    "sg:city":"Maasmechelen",
    "sg:orig_category":"Artiesten and kunstenaars",
    "sg:phone":"+32 89 75 78 26",
    "sg:postcode":"3630",
    "sg:province":"Limburg",
    "wof:name":"Van Himbeeck",
    "wof:placetype":"venue"
},
  "geometry": {"coordinates":[5.6961350441,50.963848114],"type":"Point"}
}