{
  "type": "Feature",
  "properties": {
    "iso:country":"BE",
    "sg:address":"Rue Des Bruy\u00c8res 4",
    "sg:city":"Jurbise",
    "sg:orig_category":"Avocats and conseillers juridiques",
    "sg:phone":"+32 65 22 78 64",
    "sg:postcode":"7050",
    "sg:province":"Hainaut",
    "wof:name":"S. Vall\u00c9e",
    "wof:placetype":"venue"
},
  "geometry": {"coordinates":[3.9291510582,50.5074882507],"type":"Point"}
}