{
  "type": "Feature",
  "properties": {
    "addr:full":"Quai De Mariemont 28 Bruxelles (molenbeek-saint-jean) Bruxelles-Capitale 1080",
    "addr:housenumber":"28",
    "addr:postcode":"1080",
    "addr:street":"Quai De Mariemont",
    "iso:country":"BE",
    "sg:address":"Quai De Mariemont 28",
    "sg:city":"Bruxelles (molenbeek-saint-jean)",
    "sg:classifiers":[
        {
            "category":"Industrial Area",
            "type":"Public Place"
        }
    ],
    "sg:phone":"+32 2 410 41 32",
    "sg:postcode":"1080",
    "sg:province":"Bruxelles-Capitale",
    "sg:tags":[
        "-",
        "oven"
    ],
    "wof:name":"Ceramic Instruments Sprl",
    "wof:placetype":"venue"
},
  "geometry": {"coordinates":[4.3304848671,50.8481063843],"type":"Point"}
}