{
  "type": "Feature",
  "properties": {
    "iso:country":"BE",
    "sg:address":"Grote Baan 44b1",
    "sg:city":"Houthalen-helchteren",
    "sg:orig_category":"Installatie van houten of kunststof schrijnwerk",
    "sg:phone":"+32 11 72 31 03",
    "sg:postcode":"3530",
    "sg:province":"Limburg",
    "wof:name":"Fa. Zoot",
    "wof:placetype":"venue"
},
  "geometry": {"coordinates":[5.3752422333,51.0251808167],"type":"Point"}
}