{
  "type": "Feature",
  "properties": {
    "addr:full":"7000 Mons Hainaut 7000",
    "addr:postcode":"7000;7000",
    "addr:street":"Hainaut",
    "iso:country":"BE",
    "sg:address":"7000",
    "sg:city":"Mons",
    "sg:orig_category":"Grossistes divers",
    "sg:phone":"+32 65 31 97 70",
    "sg:postcode":"7000",
    "sg:province":"Hainaut",
    "wof:name":"Surplus",
    "wof:placetype":"venue"
},
  "geometry": {"coordinates":[3.9657399654,50.4557914734],"type":"Point"}
}