{
  "type": "Feature",
  "properties": {
    "addr:full":"Dijkstraat 7 Bocholt Limburg 3950",
    "addr:housenumber":"7",
    "addr:postcode":"3950",
    "addr:street":"Dijkstraat",
    "iso:country":"BE",
    "sg:address":"Dijkstraat 7",
    "sg:city":"Bocholt",
    "sg:classifiers":[
        {
            "category":"Manufacturing",
            "subcategory":"Wood Products",
            "type":"Manufacturing & Wholesale Goods"
        }
    ],
    "sg:phone":"+32 11 62 10 24",
    "sg:postcode":"3950",
    "sg:province":"Limburg",
    "sg:tags":[
        "derived",
        "timber",
        "component",
        "furniture"
    ],
    "wof:name":"Saunaco Nv",
    "wof:placetype":"venue"
},
  "geometry": {"coordinates":[5.5235991478,51.2135009766],"type":"Point"}
}