{
  "type": "Feature",
  "properties": {
    "addr:full":"Rue Du Petit Servais 3-10 Weismes (faymonville) Li\u00e8ge 4950",
    "addr:housenumber":"3-10",
    "addr:postcode":"4950",
    "addr:street":"Rue Du Petit Servais",
    "iso:country":"BE",
    "sg:address":"Rue Du Petit Servais 3-10",
    "sg:city":"Weismes (faymonville)",
    "sg:classifiers":[
        {
            "category":"Manufacturing",
            "subcategory":"Furniture",
            "type":"Manufacturing & Wholesale Goods"
        }
    ],
    "sg:phone":"+32 80 67 96 01",
    "sg:postcode":"4950",
    "sg:province":"Li\u00e8ge",
    "sg:tags":[
        "made",
        "-",
        "custom"
    ],
    "wof:name":"Giet & Fils Meubles",
    "wof:placetype":"venue"
},
  "geometry": {"coordinates":[6.1417598724,50.405418396],"type":"Point"}
}