{
  "type": "Feature",
  "properties": {
    "iso:country":"BE",
    "sg:address":"Rue Fosty 33",
    "sg:city":"Genappe",
    "sg:orig_category":"Diverse bedrijfsbeheeradviesbureaus",
    "sg:phone":"+32 67 77 23 51",
    "sg:postcode":"1470",
    "sg:province":"Brabant Wallon",
    "wof:name":"Club Du Fosty",
    "wof:placetype":"venue"
},
  "geometry": {"coordinates":[4.5010371208,50.5949478149],"type":"Point"}
}