{
  "type": "Feature",
  "properties": {
    "iso:country":"BE",
    "sg:address":"Fatimawijk 36",
    "sg:city":"Aalst (gijzegem)",
    "sg:classifiers":[
        {
            "category":"Personal",
            "subcategory":"Beauty Salon",
            "type":"Services"
        }
    ],
    "sg:phone":"+32 53 70 16 68",
    "sg:postcode":"9308",
    "sg:province":"Oost-Vlaanderen",
    "sg:tags":[
        "lady",
        "-",
        "hairdressing"
    ],
    "wof:name":"Carla",
    "wof:placetype":"venue"
},
  "geometry": {"coordinates":[4.0497078896,50.9864616394],"type":"Point"}
}