{
  "type": "Feature",
  "properties": {
    "iso:country":"BE",
    "sg:address":"Sint-laurentiuslaan 17",
    "sg:city":"Malle (oostmalle)",
    "sg:classifiers":[
        {
            "category":"Professional",
            "subcategory":"Lawyer & Legal Services",
            "type":"Services"
        }
    ],
    "sg:phone":"+32 3 312 17 24",
    "sg:postcode":"2390",
    "sg:province":"Antwerpen",
    "wof:name":"De Koninck R",
    "wof:placetype":"venue"
},
  "geometry": {"coordinates":[4.7351360321,51.2913322449],"type":"Point"}
}