{
  "type": "Feature",
  "properties": {
    "iso:country":"BE",
    "sg:address":"Prins Albertstraat 13",
    "sg:city":"Brugge (sint-kruis)",
    "sg:classifiers":[
        {
            "category":"Arena",
            "subcategory":"Sports Club",
            "type":"Entertainment"
        }
    ],
    "sg:phone":"+32 50 35 23 20",
    "sg:postcode":"8310",
    "sg:province":"West-Vlaanderen",
    "sg:tags":[
        "martial art",
        "accessory"
    ],
    "wof:name":"Naja Dum Koreaanse Krijgskunstschool Vzw",
    "wof:placetype":"venue"
},
  "geometry": {"coordinates":[3.2427899837,51.2119483948],"type":"Point"}
}