{
  "type": "Feature",
  "properties": {
    "iso:country":"BE",
    "sg:address":"Avenue De Haveskercke 25",
    "sg:city":"Vorst/forest",
    "sg:orig_category":"Enseignement maternel and primaire",
    "sg:phone":"+32 2 343 04 78",
    "sg:postcode":"1190",
    "sg:province":"Bruxelles-Capitale",
    "wof:name":"Ecole Fondamentale Libre",
    "wof:placetype":"venue"
},
  "geometry": {"coordinates":[4.3206782341,50.8059463501],"type":"Point"}
}