{
  "type": "Feature",
  "properties": {
    "iso:country":"BE",
    "sg:address":"Avenue Eug\u00e8ne Mascaux 482",
    "sg:city":"Charleroi (marcinelle)",
    "sg:classifiers":[
        {
            "category":"Professional",
            "subcategory":"Art Services",
            "type":"Services"
        }
    ],
    "sg:phone":"+32 71 36 69 63",
    "sg:postcode":"6001",
    "sg:province":"Hainaut",
    "sg:tags":[
        "photographer"
    ],
    "wof:name":"Photo Shop Match",
    "wof:placetype":"venue"
},
  "geometry": {"coordinates":[4.4448251724,50.3973655701],"type":"Point"}
}