{
  "type": "Feature",
  "properties": {
    "iso:country":"BE",
    "sg:address":"Toekomststraat 11",
    "sg:city":"Nijlen",
    "sg:orig_category":"Fotogravure and zetwerk Postzegels, munten and trofee\u00ebn",
    "sg:phone":"+32 3 480 28 79",
    "sg:postcode":"2560",
    "sg:province":"Antwerpen",
    "wof:name":"Huis Prinzie & Zonen",
    "wof:placetype":"venue"
},
  "geometry": {"coordinates":[4.6257910728,51.1400222778],"type":"Point"}
}