{
  "type": "Feature",
  "properties": {
    "iso:country":"BE",
    "sg:address":"Bellegemsestraat 115",
    "sg:city":"Kortrijk",
    "sg:classifiers":[
        {
            "category":"Shopping",
            "subcategory":"Bicycles & Sporting Goods",
            "type":"Retail Goods"
        }
    ],
    "sg:phone":"+32 56 20 10 35",
    "sg:postcode":"8510",
    "sg:province":"West-Vlaanderen",
    "sg:tags":[
        "article",
        "de",
        "sport",
        "camping"
    ],
    "wof:name":"De Sportboetiek",
    "wof:placetype":"venue"
},
  "geometry": {"coordinates":[3.2887051105,50.7777671814],"type":"Point"}
}