{
  "type": "Feature",
  "properties": {
    "iso:country":"BE",
    "sg:address":"Kroonlaan 248",
    "sg:city":"Elsene/ixelles",
    "sg:orig_category":"Artsen and specialisten",
    "sg:phone":"+32 2 648 27 55",
    "sg:postcode":"1050",
    "sg:province":"Bruxelles-Capitale",
    "wof:name":"Elisa Lopez Hernandez",
    "wof:placetype":"venue"
},
  "geometry": {"coordinates":[4.3833079338,50.8265228271],"type":"Point"}
}