{
  "type": "Feature",
  "properties": {
    "iso:country":"BE",
    "sg:address":"Dr\u00c8ve Marguerite 49",
    "sg:city":"Waterloo",
    "sg:orig_category":"Fotografen and fotostudio's Schilders",
    "sg:phone":"+32 2 351 25 33",
    "sg:postcode":"1410",
    "sg:province":"Brabant Wallon",
    "wof:name":"Raphael Dooms",
    "wof:placetype":"venue"
},
  "geometry": {"coordinates":[4.3742651939,50.7114486694],"type":"Point"}
}