{
  "type": "Feature",
  "properties": {
    "iso:country":"BE",
    "sg:address":"Rue Hov\u00e9mont 118",
    "sg:city":"Theux",
    "sg:classifiers":[
        {
            "category":"Bars & Pubs",
            "type":"Food & Drink"
        }
    ],
    "sg:phone":"+32 87 53 05 98",
    "sg:postcode":"4910",
    "sg:province":"Li\u00e8ge",
    "wof:name":"Waux-hall (le)",
    "wof:placetype":"venue"
},
  "geometry": {"coordinates":[5.8152308464,50.5325698853],"type":"Point"}
}