{
  "type": "Feature",
  "properties": {
    "iso:country":"BE",
    "sg:address":"Terlaemenlaan 42",
    "sg:city":"Heusden-zolder (zolder)",
    "sg:classifiers":[
        {
            "category":"Health Services",
            "subcategory":"Health Practitioner",
            "type":"Services"
        }
    ],
    "sg:phone":"+32 11 53 13 93",
    "sg:postcode":"3550",
    "sg:province":"Limburg",
    "sg:tags":[
        "dietitian"
    ],
    "wof:name":"Gilis B",
    "wof:placetype":"venue"
},
  "geometry": {"coordinates":[5.27212286,51.0084266663],"type":"Point"}
}