{
  "type": "Feature",
  "properties": {
    "iso:country":"BE",
    "sg:address":"Rue Du Bouquet 19",
    "sg:city":"Anderlecht/anderlecht",
    "sg:orig_category":"Rev\u00eatements pour sols and murs. Peinture",
    "sg:phone":"+32 2 521 34 06",
    "sg:postcode":"1070",
    "sg:province":"Bruxelles-Capitale",
    "wof:name":"Pierre Rousseau",
    "wof:placetype":"venue"
},
  "geometry": {"coordinates":[4.2917361259,50.8233985901],"type":"Point"}
}