{
  "type": "Feature",
  "properties": {
    "iso:country":"BE",
    "sg:address":"Frans Van Cauwelaertstraat 25",
    "sg:city":"Roosdaal",
    "sg:classifiers":[
        {
            "category":"Building & Trades",
            "subcategory":"Cleaning & Sanitation",
            "type":"Services"
        }
    ],
    "sg:phone":"+32 54 32 97 53",
    "sg:postcode":"1760",
    "sg:province":"Vlaams-Brabant",
    "sg:tags":[
        "cleaner",
        "window"
    ],
    "wof:name":"Netto-clean Bvba",
    "wof:placetype":"venue"
},
  "geometry": {"coordinates":[4.1104860306,50.818397522],"type":"Point"}
}