{
  "type": "Feature",
  "properties": {
    "iso:country":"BE",
    "sg:address":"Rue Capitaine Crespel 14",
    "sg:city":"Elsene/ixelles",
    "sg:classifiers":[
        {
            "category":"Restaurant",
            "type":"Food & Drink"
        }
    ],
    "sg:phone":"+32 2 513 17 25",
    "sg:postcode":"1050",
    "sg:province":"Bruxelles-Capitale",
    "wof:name":"Korea Seoul",
    "wof:placetype":"venue"
},
  "geometry": {"coordinates":[4.3580899239,50.8357925415],"type":"Point"}
}