{
  "type": "Feature",
  "properties": {
    "addr:full":"Gezellelaan Lichtervelde West-Vlaanderen 8810",
    "addr:postcode":"8810",
    "addr:street":"Gezellelaan",
    "iso:country":"BE",
    "sg:address":"Gezellelaan",
    "sg:city":"Lichtervelde",
    "sg:orig_category":"Beheer van afvalopslag- and stortplaatsen",
    "sg:phone":"+32 51 72 24 83",
    "sg:postcode":"8810",
    "sg:province":"West-Vlaanderen",
    "wof:name":"Containerpark Lichtervelde",
    "wof:placetype":"venue"
},
  "geometry": {"coordinates":[3.1408190727,51.0295333862],"type":"Point"}
}