{
  "type": "Feature",
  "properties": {
    "addr:full":"Ommegangstraat 39 Lochristi Oost-Vlaanderen 9080",
    "addr:housenumber":"39",
    "addr:postcode":"9080",
    "addr:street":"Ommegangstraat",
    "iso:country":"BE",
    "sg:address":"Ommegangstraat 39",
    "sg:city":"Lochristi",
    "sg:classifiers":[
        {
            "category":"Health Services",
            "subcategory":"Health Practitioner",
            "type":"Services"
        }
    ],
    "sg:phone":"+32 9 355 70 10",
    "sg:postcode":"9080",
    "sg:province":"Oost-Vlaanderen",
    "sg:tags":[
        "therapist",
        "speech"
    ],
    "wof:name":"Van Aerschot Christi",
    "wof:placetype":"venue"
},
  "geometry": {"coordinates":[3.8506190777,51.0861663818],"type":"Point"}
}