{
  "type": "Feature",
  "properties": {
    "addr:full":"Oude Koornmarkt 61 Antwerpen Antwerpen 2000",
    "addr:housenumber":"61",
    "addr:postcode":"2000",
    "addr:street":"Oude Koornmarkt",
    "iso:country":"BE",
    "sg:address":"Oude Koornmarkt 61",
    "sg:city":"Antwerpen",
    "sg:classifiers":[
        {
            "category":"Restaurant",
            "type":"Food & Drink"
        }
    ],
    "sg:phone":"+32 3 226 44 63",
    "sg:postcode":"2000",
    "sg:province":"Antwerpen",
    "wof:name":"Kartini",
    "wof:placetype":"venue"
},
  "geometry": {"coordinates":[4.4007019997,51.219379425],"type":"Point"}
}