{
  "type": "Feature",
  "properties": {
    "addr:full":"Rue Adolphe Sax 26 Dinant Namur 5500",
    "addr:housenumber":"26",
    "addr:postcode":"5500",
    "addr:street":"Rue Adolphe Sax",
    "iso:country":"BE",
    "sg:address":"Rue Adolphe Sax 26",
    "sg:city":"Dinant",
    "sg:classifiers":[
        {
            "category":"Restaurant",
            "type":"Food & Drink"
        }
    ],
    "sg:phone":"+32 82 22 66 28",
    "sg:postcode":"5500",
    "sg:province":"Namur",
    "wof:name":"Saveur D'asie",
    "wof:placetype":"venue"
},
  "geometry": {"coordinates":[4.9111661911,50.261428833],"type":"Point"}
}