{
  "type": "Feature",
  "properties": {
    "iso:country":"BE",
    "sg:address":"Booglaan 7",
    "sg:city":"Hoeilaart",
    "sg:classifiers":[
        {
            "category":"Health Services",
            "subcategory":"Health Practitioner",
            "type":"Services"
        }
    ],
    "sg:phone":"+32 2 657 37 57",
    "sg:postcode":"1560",
    "sg:province":"Vlaams-Brabant",
    "sg:tags":[
        "physiotherapist"
    ],
    "wof:name":"Lanssens M-c",
    "wof:placetype":"venue"
},
  "geometry": {"coordinates":[4.4985308647,50.7651062012],"type":"Point"}
}