{
  "type": "Feature",
  "properties": {
    "iso:country":"BE",
    "sg:address":"Vortekoestraat 113",
    "sg:city":"Waasmunster",
    "sg:classifiers":[
        {
            "category":"Farming",
            "subcategory":"Livestock Farm",
            "type":"Manufacturing & Wholesale Goods"
        }
    ],
    "sg:phone":"+32 97722608",
    "sg:postcode":"9250",
    "sg:province":"Oost-Vlaanderen",
    "sg:tags":[
        "buyer"
    ],
    "wof:name":"De Maere L",
    "wof:placetype":"venue"
},
  "geometry": {"coordinates":[4.0477228165,51.126991272],"type":"Point"}
}