{
  "type": "Feature",
  "properties": {
    "addr:full":"Poortakkerstraat 5 Nevele Oost-Vlaanderen 9850",
    "addr:housenumber":"5",
    "addr:postcode":"9850",
    "addr:street":"Poortakkerstraat",
    "iso:country":"BE",
    "sg:address":"Poortakkerstraat 5",
    "sg:city":"Nevele",
    "sg:orig_category":"Eleveurs and marchands de porcs. Eleveurs de bovins",
    "sg:phone":"+32 9 371 58 81",
    "sg:postcode":"9850",
    "sg:province":"Oost-Vlaanderen",
    "wof:name":"Christian Geiregat",
    "wof:placetype":"venue"
},
  "geometry": {"coordinates":[3.5714390278,51.0344848633],"type":"Point"}
}