{
  "type": "Feature",
  "properties": {
    "iso:country":"BE",
    "sg:address":"Emiel Van Dorenlaan 16",
    "sg:city":"Genk",
    "sg:classifiers":[
        {
            "category":"Personal",
            "subcategory":"Barber",
            "type":"Services"
        }
    ],
    "sg:phone":"+32 89 38 00 70",
    "sg:postcode":"3600",
    "sg:province":"Limburg",
    "sg:tags":[
        "gentleman",
        "salon",
        "-",
        "hairdressing"
    ],
    "wof:name":"Vanvinckenroye T",
    "wof:placetype":"venue"
},
  "geometry": {"coordinates":[5.5116801262,50.9841957092],"type":"Point"}
}