{
  "type": "Feature",
  "properties": {
    "addr:full":"Leideveld 27 Maarkedal (schorisse) Oost-Vlaanderen 9688",
    "addr:housenumber":"27",
    "addr:postcode":"9688",
    "addr:street":"Leideveld",
    "iso:country":"BE",
    "sg:address":"Leideveld 27",
    "sg:city":"Maarkedal (schorisse)",
    "sg:classifiers":[
        {
            "category":"Building & Trades",
            "subcategory":"Landscaping Services",
            "type":"Services"
        }
    ],
    "sg:phone":"+32 55 45 74 60",
    "sg:postcode":"9688",
    "sg:province":"Oost-Vlaanderen",
    "sg:tags":[
        "gardening",
        "garden",
        "maintenance"
    ],
    "wof:name":"Tuinen Vincent",
    "wof:placetype":"venue"
},
  "geometry": {"coordinates":[3.6637818813,50.7957801819],"type":"Point"}
}