{
  "type": "Feature",
  "properties": {
    "addr:full":"Avenue G\u00e9n\u00e9ral Bertrand 8 Vis\u00e9 Li\u00e8ge 4600",
    "addr:housenumber":"8",
    "addr:postcode":"4600",
    "addr:street":"Avenue Ge\u0301Ne\u0301Ral Bertrand",
    "iso:country":"BE",
    "sg:address":"Avenue G\u00e9n\u00e9ral Bertrand 8",
    "sg:city":"Vis\u00e9",
    "sg:classifiers":[
        {
            "category":"Health Services",
            "subcategory":"Doctor",
            "type":"Services"
        }
    ],
    "sg:phone":"+32 4 379 11 45",
    "sg:postcode":"4600",
    "sg:province":"Li\u00e8ge",
    "sg:tags":[
        "medicinephysicians",
        "surgeon"
    ],
    "wof:name":"Debruche Michel",
    "wof:placetype":"venue"
},
  "geometry": {"coordinates":[5.696117878,50.7384643555],"type":"Point"}
}