{
  "type": "Feature",
  "properties": {
    "addr:full":"Erondegemdorp 2 Erpe-mere Oost-Vlaanderen 9420",
    "addr:housenumber":"2",
    "addr:postcode":"9420",
    "addr:street":"Erondegemdorp",
    "iso:country":"BE",
    "sg:address":"Erondegemdorp 2",
    "sg:city":"Erpe-mere",
    "sg:orig_category":"Banques and organismes de cr\u00e9dit",
    "sg:phone":"+32 53 80 17 57",
    "sg:postcode":"9420",
    "sg:province":"Oost-Vlaanderen",
    "wof:name":"Fortis",
    "wof:placetype":"venue"
},
  "geometry": {"coordinates":[3.9555211067,50.9402961731],"type":"Point"}
}