{
  "type": "Feature",
  "properties": {
    "addr:full":"Chauss\u00c9e De Louvain 72 Eghezee Namur 5310",
    "addr:housenumber":"72",
    "addr:postcode":"5310",
    "addr:street":"Chausse\u0301E De Louvain;Namur",
    "iso:country":"BE",
    "sg:address":"Chauss\u00c9e De Louvain 72",
    "sg:city":"Eghezee",
    "sg:orig_category":"Instituts de beaut\u00e9",
    "sg:phone":"+32 81 81 12 05",
    "sg:postcode":"5310",
    "sg:province":"Namur",
    "wof:name":"Anne-marie Hance",
    "wof:placetype":"venue"
},
  "geometry": {"coordinates":[4.9040951729,50.5995025635],"type":"Point"}
}