{
  "type": "Feature",
  "properties": {
    "iso:country":"BE",
    "sg:address":"Mechelsestraat 125",
    "sg:city":"Londerzeel",
    "sg:orig_category":"Advocaten and juridische adviseurs",
    "sg:phone":"+32 52 30 38 71",
    "sg:postcode":"1840",
    "sg:province":"Vlaams-Brabant",
    "wof:name":"Ch. De Nijn",
    "wof:placetype":"venue"
},
  "geometry": {"coordinates":[4.3123111725,51.0066566467],"type":"Point"}
}