{
  "type": "Feature",
  "properties": {
    "addr:full":"Sint-michielsstraat 2 Herent Vlaams-Brabant 3020",
    "addr:housenumber":"2",
    "addr:postcode":"3020",
    "addr:street":"Sint-Michielsstraat",
    "iso:country":"BE",
    "sg:address":"Sint-michielsstraat 2",
    "sg:city":"Herent",
    "sg:orig_category":"Artsen and specialisten",
    "sg:phone":"+32 16 48 98 80",
    "sg:postcode":"3020",
    "sg:province":"Vlaams-Brabant",
    "wof:name":"Rubie Tjandramaga",
    "wof:placetype":"venue"
},
  "geometry": {"coordinates":[4.6140980721,50.9012184143],"type":"Point"}
}