{
  "type": "Feature",
  "properties": {
    "addr:full":"Zeelaan 31 De (groot) West-Vlaanderen 8660",
    "addr:housenumber":"31",
    "addr:postcode":"8660",
    "addr:street":"Zeelaan;De Groot West-Vlaanderen",
    "iso:country":"BE",
    "sg:address":"Zeelaan 31",
    "sg:city":"De (groot)",
    "sg:classifiers":[
        {
            "category":"Personal",
            "subcategory":"Beauty Salon",
            "type":"Services"
        }
    ],
    "sg:phone":"+32 58 42 17 54",
    "sg:postcode":"8660",
    "sg:province":"West-Vlaanderen",
    "sg:tags":[
        "de",
        "coiffure"
    ],
    "wof:name":"Coiffure Fauve",
    "wof:placetype":"venue"
},
  "geometry": {"coordinates":[2.5895240307,51.0970726013],"type":"Point"}
}