{
  "type": "Feature",
  "properties": {
    "addr:full":"Rue De L\u00b4abbaye 27 Ath Hainaut 7800",
    "addr:housenumber":"27",
    "addr:postcode":"7800",
    "addr:street":"Rue De L\u00b4Abbaye",
    "iso:country":"BE",
    "sg:address":"Rue De L\u00b4abbaye 27",
    "sg:city":"Ath",
    "sg:orig_category":"HERSTELLING ELEKTRISCHE HUISHOUDAPPARATEN Huishoudapparaten, televisies and radio's",
    "sg:phone":"+32 68 28 59 73",
    "sg:postcode":"7800",
    "sg:province":"Hainaut",
    "wof:name":"Blanchart",
    "wof:placetype":"venue"
},
  "geometry": {"coordinates":[3.7873289585,50.6352348328],"type":"Point"}
}