{
  "type": "Feature",
  "properties": {
    "addr:full":"Place Werth 4 Eupen Li\u00e8ge 4700",
    "addr:housenumber":"4",
    "addr:postcode":"4700",
    "addr:street":"Place Werth",
    "iso:country":"BE",
    "sg:address":"Place Werth 4",
    "sg:city":"Eupen",
    "sg:orig_category":"Equipement photographique",
    "sg:phone":"+32 87 74 22 27",
    "sg:postcode":"4700",
    "sg:province":"Li\u00e8ge",
    "wof:name":"B. & B.",
    "wof:placetype":"venue"
},
  "geometry": {"coordinates":[6.0385270119,50.6328582764],"type":"Point"}
}