{
  "type": "Feature",
  "properties": {
    "addr:full":"Route De La Ferme Mod\u00c8le 80 Verviers Li\u00e8ge 4800",
    "addr:housenumber":"80",
    "addr:postcode":"4800",
    "addr:street":"Route De La Ferme Mode\u0300Le",
    "iso:country":"BE",
    "sg:address":"Route De La Ferme Mod\u00c8le 80",
    "sg:city":"Verviers",
    "sg:orig_category":"Eleveurs de bovins",
    "sg:phone":"+32 87 22 27 11",
    "sg:postcode":"4800",
    "sg:province":"Li\u00e8ge",
    "wof:name":"Alain Boulanger",
    "wof:placetype":"venue"
},
  "geometry": {"coordinates":[5.8761639595,50.5576515198],"type":"Point"}
}