{
  "type": "Feature",
  "properties": {
    "addr:full":"Rue Defacqz 114 Bruxelles (saint-gilles) Bruxelles-Capitale 1060",
    "addr:housenumber":"114",
    "addr:postcode":"1060",
    "addr:street":"Rue Defacqz",
    "iso:country":"BE",
    "sg:address":"Rue Defacqz 114",
    "sg:city":"Bruxelles (saint-gilles)",
    "sg:classifiers":[
        {
            "category":"Health Services",
            "subcategory":"Doctor",
            "type":"Services"
        }
    ],
    "sg:phone":"+32 2 374 96 94",
    "sg:postcode":"1060",
    "sg:province":"Bruxelles-Capitale",
    "sg:tags":[
        "psychotherapist",
        "psychoanalyst"
    ],
    "wof:name":"Huybrechts M",
    "wof:placetype":"venue"
},
  "geometry": {"coordinates":[4.3568778038,50.826499939],"type":"Point"}
}