{
  "type": "Feature",
  "properties": {
    "iso:country":"BE",
    "sg:address":"Parklaan 64",
    "sg:city":"Sint-niklaas",
    "sg:classifiers":[
        {
            "category":"Insurance",
            "subcategory":"Insurance Agent",
            "type":"Services"
        }
    ],
    "sg:phone":"+32 3 777 81 21",
    "sg:postcode":"9100",
    "sg:province":"Oost-Vlaanderen",
    "sg:tags":[
        "broker"
    ],
    "wof:name":"Callaert Verzekeringskantoor",
    "wof:placetype":"venue"
},
  "geometry": {"coordinates":[4.1513772011,51.1586875916],"type":"Point"}
}