{
  "type": "Feature",
  "properties": {
    "addr:full":"Sint-elooisweg 30 Ieper West-Vlaanderen 8902",
    "addr:housenumber":"30",
    "addr:postcode":"8902",
    "addr:street":"Sint-Elooisweg",
    "iso:country":"BE",
    "sg:address":"Sint-elooisweg 30",
    "sg:city":"Ieper",
    "sg:orig_category":"Kinderopvang",
    "sg:phone":"+32 57 20 68 96",
    "sg:postcode":"8902",
    "sg:province":"West-Vlaanderen",
    "wof:name":"Kribbe \u00b4t Paddestoeltje",
    "wof:placetype":"venue"
},
  "geometry": {"coordinates":[2.8783049583,50.8166732788],"type":"Point"}
}