{
  "type": "Feature",
  "properties": {
    "iso:country":"BE",
    "sg:address":"Stationsstraat 97",
    "sg:city":"Damme (sijsele)",
    "sg:classifiers":[
        {
            "category":"Food & Beverages",
            "subcategory":"Dairy",
            "type":"Retail Goods"
        }
    ],
    "sg:phone":"+32 50 78 26 80",
    "sg:postcode":"8340",
    "sg:province":"West-Vlaanderen",
    "sg:tags":[
        "product",
        "-"
    ],
    "wof:name":"Elsje Delicatessen",
    "wof:placetype":"venue"
},
  "geometry": {"coordinates":[3.3166139126,51.2093086243],"type":"Point"}
}