{
  "type": "Feature",
  "properties": {
    "addr:full":"Rue Bois Des Fosses 42 Orp-jauche (enines) Brabant Wallon 1350",
    "addr:housenumber":"42",
    "addr:postcode":"1350",
    "addr:street":"Rue Bois Des Fosses;Enines Brabant Wallon",
    "iso:country":"BE",
    "sg:address":"Rue Bois Des Fosses 42",
    "sg:city":"Orp-jauche (enines)",
    "sg:classifiers":[
        {
            "category":"Banks & Credit Unions",
            "subcategory":"Bureau De Change",
            "type":"Services"
        }
    ],
    "sg:phone":"+32 19 63 73 00",
    "sg:postcode":"1350",
    "sg:province":"Brabant Wallon",
    "sg:tags":[
        "model",
        "scale",
        "-"
    ],
    "wof:name":"Tetraedre Sprl",
    "wof:placetype":"venue"
},
  "geometry": {"coordinates":[4.9293351173,50.6922302246],"type":"Point"}
}