{
  "type": "Feature",
  "properties": {
    "addr:full":"Chauss\u00e9e De Bruxelles 390 Ath Hainaut 7800",
    "addr:housenumber":"390",
    "addr:postcode":"7800",
    "addr:street":"Chausse\u0301E De Bruxelles",
    "iso:country":"BE",
    "sg:address":"Chauss\u00e9e De Bruxelles 390",
    "sg:city":"Ath",
    "sg:classifiers":[
        {
            "category":"Freight",
            "type":"Transportation"
        }
    ],
    "sg:phone":"+32 68 56 84 68",
    "sg:postcode":"7800",
    "sg:province":"Hainaut",
    "sg:tags":[
        "-",
        "transport"
    ],
    "wof:name":"Delhaye P",
    "wof:placetype":"venue"
},
  "geometry": {"coordinates":[3.8196470737,50.6397781372],"type":"Point"}
}