{
  "type": "Feature",
  "properties": {
    "iso:country":"BE",
    "sg:address":"Chemin De Reumont 143",
    "sg:city":"Namur (malonne)",
    "sg:classifiers":[
        {
            "category":"Education",
            "subcategory":"School",
            "type":"Public Place"
        }
    ],
    "sg:phone":"+32 81 44 55 81",
    "sg:postcode":"5020",
    "sg:province":"Namur",
    "sg:tags":[
        "primary"
    ],
    "wof:name":"Les Ecoles Primaire Et Professionnelle D'enseignement Sp\u00e9cial Reumontjoie",
    "wof:placetype":"venue"
},
  "geometry": {"coordinates":[4.8025918007,50.4334831238],"type":"Point"}
}