{
  "type": "Feature",
  "properties": {
    "iso:country":"BE",
    "sg:address":"Torenstraat 109",
    "sg:city":"Rotselaar",
    "sg:classifiers":[
        {
            "category":"Conference Center",
            "type":"Public Place"
        }
    ],
    "sg:phone":"+32 16 44 40 60",
    "sg:postcode":"3110",
    "sg:province":"Vlaams-Brabant",
    "sg:tags":[
        "terrain",
        "vehicle"
    ],
    "wof:name":"Van Criekinge H",
    "wof:placetype":"venue"
},
  "geometry": {"coordinates":[4.7234888077,50.9555053711],"type":"Point"}
}