{
  "type": "Feature",
  "properties": {
    "addr:full":"Hoge Akker 16 Wevelgem West-Vlaanderen 8560",
    "addr:housenumber":"16",
    "addr:postcode":"8560",
    "addr:street":"Hoge Akker",
    "iso:country":"BE",
    "sg:address":"Hoge Akker 16",
    "sg:city":"Wevelgem",
    "sg:orig_category":"Schoonheidssalons",
    "sg:phone":"+32 56 40 19 18",
    "sg:postcode":"8560",
    "sg:province":"West-Vlaanderen",
    "wof:name":"Anne-marie Cadet",
    "wof:placetype":"venue"
},
  "geometry": {"coordinates":[3.1819829941,50.8162117004],"type":"Point"}
}