{
  "type": "Feature",
  "properties": {
    "addr:full":"Verhelststraat 19 Waregem West-Vlaanderen 8790",
    "addr:housenumber":"19",
    "addr:postcode":"8790",
    "addr:street":"Verhelststraat",
    "iso:country":"BE",
    "sg:address":"Verhelststraat 19",
    "sg:city":"Waregem",
    "sg:orig_category":"Newspapers, magazines, periodicals - Distribution",
    "sg:phone":"+32 56 60 05 47",
    "sg:postcode":"8790",
    "sg:province":"West-Vlaanderen",
    "wof:name":"Buyck R",
    "wof:placetype":"venue"
},
  "geometry": {"coordinates":[3.4280409813,50.885848999],"type":"Point"}
}