{
  "type": "Feature",
  "properties": {
    "addr:full":"Hofstraat 77 Middelkerke (westende) West-Vlaanderen 8434",
    "addr:housenumber":"77",
    "addr:postcode":"8434",
    "addr:street":"Hofstraat",
    "iso:country":"BE",
    "sg:address":"Hofstraat 77",
    "sg:city":"Middelkerke (westende)",
    "sg:classifiers":[
        {
            "category":"Professional",
            "subcategory":"Secretarial Services",
            "type":"Services"
        }
    ],
    "sg:phone":"+32 58 24 10 30",
    "sg:postcode":"8434",
    "sg:province":"West-Vlaanderen",
    "sg:tags":[
        "firm"
    ],
    "wof:name":"Soedeko",
    "wof:placetype":"venue"
},
  "geometry": {"coordinates":[2.7569050789,51.1488685608],"type":"Point"}
}