{
  "type": "Feature",
  "properties": {
    "addr:full":"Laarnebaan 24 Destelbergen (heusden) Oost-Vlaanderen 9070",
    "addr:housenumber":"24",
    "addr:postcode":"9070",
    "addr:street":"Laarnebaan",
    "iso:country":"BE",
    "sg:address":"Laarnebaan 24",
    "sg:city":"Destelbergen (heusden)",
    "sg:classifiers":[
        {
            "category":"Farming",
            "subcategory":"Nursery",
            "type":"Manufacturing & Wholesale Goods"
        }
    ],
    "sg:phone":"+32 9 231 66 46",
    "sg:postcode":"9070",
    "sg:province":"Oost-Vlaanderen",
    "sg:tags":[
        "horticultural",
        "automation"
    ],
    "wof:name":"Mereg",
    "wof:placetype":"venue"
},
  "geometry": {"coordinates":[3.8071000576,51.0325241089],"type":"Point"}
}