{
  "type": "Feature",
  "properties": {
    "iso:country":"BE",
    "sg:address":"Avenue Armand Forton 21",
    "sg:city":"Kraainem",
    "sg:classifiers":[
        {
            "category":"Real Estate",
            "subcategory":"Architect",
            "type":"Services"
        }
    ],
    "sg:phone":"+32 477 17 25 11",
    "sg:postcode":"1950",
    "sg:province":"Vlaams-Brabant",
    "wof:name":"Stalmans C",
    "wof:placetype":"venue"
},
  "geometry": {"coordinates":[4.4607210159,50.8609352112],"type":"Point"}
}