{
  "type": "Feature",
  "properties": {
    "addr:full":"Rue Bertrand 50 Andenne Namur 5300",
    "addr:housenumber":"50",
    "addr:postcode":"5300",
    "addr:street":"Rue Bertrand",
    "iso:country":"BE",
    "sg:address":"Rue Bertrand 50",
    "sg:city":"Andenne",
    "sg:classifiers":[
        {
            "category":"Community Center",
            "type":"Public Place"
        }
    ],
    "sg:phone":"+32 85 84 53 54",
    "sg:postcode":"5300",
    "sg:province":"Namur",
    "sg:tags":[
        "medical"
    ],
    "wof:name":"Centre Para-m\u00e9dical",
    "wof:placetype":"venue"
},
  "geometry": {"coordinates":[5.094769001,50.488697052],"type":"Point"}
}