{
  "type": "Feature",
  "properties": {
    "iso:country":"BE",
    "sg:address":"Avenue Houba De Strooper 11",
    "sg:city":"Brussel/bruxelles",
    "sg:orig_category":"Fruits and l\u00e9gumes. Epiceries",
    "sg:phone":"+32 2 478 74 53",
    "sg:postcode":"1020",
    "sg:province":"Bruxelles-Capitale",
    "wof:name":"Sanders-primeurs",
    "wof:placetype":"venue"
},
  "geometry": {"coordinates":[4.3425798416,50.8858070374],"type":"Point"}
}