{
  "type": "Feature",
  "properties": {
    "iso:country":"BE",
    "sg:address":"Rue G\u00e9n\u00e9ral Piron 17",
    "sg:city":"Fernelmont (noville-les-bois)",
    "sg:classifiers":[
        {
            "category":"Building & Trades",
            "subcategory":"Construction",
            "type":"Services"
        }
    ],
    "sg:phone":"+32 81 83 30 38",
    "sg:postcode":"5380",
    "sg:province":"Namur",
    "sg:tags":[
        "carpenter"
    ],
    "wof:name":"Bouffioux Emile Sprl",
    "wof:placetype":"venue"
},
  "geometry": {"coordinates":[4.9844121933,50.5531234741],"type":"Point"}
}