{
  "type": "Feature",
  "properties": {
    "addr:full":"Bredestraat 40 Aalst Oost-Vlaanderen 9300",
    "addr:housenumber":"40",
    "addr:postcode":"9300",
    "addr:street":"Bredestraat",
    "iso:country":"BE",
    "sg:address":"Bredestraat 40",
    "sg:city":"Aalst",
    "sg:orig_category":"M\u00e9decins and sp\u00e9cialistes",
    "sg:phone":"+32 53 70 55 75",
    "sg:postcode":"9300",
    "sg:province":"Oost-Vlaanderen",
    "wof:name":"L. Cleemput",
    "wof:placetype":"venue"
},
  "geometry": {"coordinates":[4.0440359116,50.9482498169],"type":"Point"}
}