{
  "type": "Feature",
  "properties": {
    "addr:full":"Lindekensstraat 2a Herentals (noorderwijk) Antwerpen 2200",
    "addr:housenumber":"2a",
    "addr:postcode":"2200",
    "addr:street":"Lindekensstraat",
    "iso:country":"BE",
    "sg:address":"Lindekensstraat 2a",
    "sg:city":"Herentals (noorderwijk)",
    "sg:classifiers":[
        {
            "category":"Shopping",
            "subcategory":"Clothing, Apparel, & Fashions",
            "type":"Retail Goods"
        }
    ],
    "sg:phone":"+32 14 26 10 21",
    "sg:postcode":"2200",
    "sg:province":"Antwerpen",
    "sg:tags":[
        "boutique"
    ],
    "wof:name":"Cocca's Basic",
    "wof:placetype":"venue"
},
  "geometry": {"coordinates":[4.8360338211,51.1774635315],"type":"Point"}
}