{
  "type": "Feature",
  "properties": {
    "iso:country":"BE",
    "sg:address":"Blijdschapsstraat 81",
    "sg:city":"Anderlecht",
    "sg:orig_category":"Sportclubs",
    "sg:phone":"+32 2 523 86 93",
    "sg:postcode":"1070",
    "sg:province":"Bruxelles-Capitale",
    "wof:name":"Petit Epervier",
    "wof:placetype":"venue"
},
  "geometry": {"coordinates":[4.3114409447,50.8333511353],"type":"Point"}
}