{
  "type": "Feature",
  "properties": {
    "iso:country":"BE",
    "sg:address":"Rue Des Renards 26b12",
    "sg:city":"Thuin",
    "sg:orig_category":"M\u00e9decins and sp\u00e9cialistes",
    "sg:phone":"+32 71 51 99 87",
    "sg:postcode":"6534",
    "sg:province":"Hainaut",
    "wof:name":"Paulette Frin",
    "wof:placetype":"venue"
},
  "geometry": {"coordinates":[4.3607487679,50.3577041626],"type":"Point"}
}