{
  "type": "Feature",
  "properties": {
    "addr:full":"Parc Ind. Des Hauts Sarts Herstal Li\u00e8ge 4040",
    "addr:postcode":"4040",
    "addr:street":"Sarts",
    "iso:country":"BE",
    "sg:address":"Parc Ind. Des Hauts Sarts",
    "sg:city":"Herstal",
    "sg:classifiers":[
        {
            "category":"Wholesale",
            "subcategory":"Painting Supplies",
            "type":"Manufacturing & Wholesale Goods"
        }
    ],
    "sg:phone":"+32 4 248 27 37",
    "sg:postcode":"4040",
    "sg:province":"Li\u00e8ge",
    "sg:tags":[
        "equipment",
        "paint",
        "spraying"
    ],
    "wof:name":"Fallem Sprl",
    "wof:placetype":"venue"
},
  "geometry": {"coordinates":[5.6277627945,50.6893463135],"type":"Point"}
}