{
  "type": "Feature",
  "properties": {
    "addr:full":"Grotstraat 49 Zutendaal Limburg 3690",
    "addr:housenumber":"49",
    "addr:postcode":"3690",
    "addr:street":"Grotstraat",
    "iso:country":"BE",
    "sg:address":"Grotstraat 49",
    "sg:city":"Zutendaal",
    "sg:classifiers":[
        {
            "category":"Real Estate",
            "subcategory":"Architect",
            "type":"Services"
        }
    ],
    "sg:phone":"+32 89 62 20 97",
    "sg:postcode":"3690",
    "sg:province":"Limburg",
    "wof:name":"Strackx P",
    "wof:placetype":"venue"
},
  "geometry": {"coordinates":[5.5539522171,50.9489898682],"type":"Point"}
}