{
  "type": "Feature",
  "properties": {
    "addr:full":"Vroentestraat 22 Diest Vlaams-Brabant 3290",
    "addr:housenumber":"22",
    "addr:postcode":"3290",
    "addr:street":"Vroentestraat",
    "iso:country":"BE",
    "sg:address":"Vroentestraat 22",
    "sg:city":"Diest",
    "sg:orig_category":"Enseignement maternel and primaire",
    "sg:phone":"+32 13 32 69 23",
    "sg:postcode":"3290",
    "sg:province":"Vlaams-Brabant",
    "wof:name":"Gemeentelijke Basisschool",
    "wof:placetype":"venue"
},
  "geometry": {"coordinates":[5.0788850784,51.0010070801],"type":"Point"}
}