{
  "type": "Feature",
  "properties": {
    "iso:country":"BE",
    "sg:address":"Bril 13",
    "sg:city":"Lier",
    "sg:classifiers":[
        {
            "category":"Building & Trades",
            "subcategory":"Electrical",
            "type":"Services"
        }
    ],
    "sg:phone":"+32 3 480 68 67",
    "sg:postcode":"2500",
    "sg:province":"Antwerpen",
    "sg:tags":[
        "electric",
        "-",
        "housewiring",
        "contractor"
    ],
    "wof:name":"Apers B",
    "wof:placetype":"venue"
},
  "geometry": {"coordinates":[4.5720911026,51.1294250488],"type":"Point"}
}