{
  "type": "Feature",
  "properties": {
    "iso:country":"BE",
    "sg:address":"Wijdhagestraat 109",
    "sg:city":"Harelbeke",
    "sg:classifiers":[
        {
            "category":"Building & Trades",
            "subcategory":"Plumbing",
            "type":"Services"
        }
    ],
    "sg:phone":"+32 56 71 88 28",
    "sg:postcode":"8530",
    "sg:province":"West-Vlaanderen",
    "sg:tags":[
        "diver",
        "commerce",
        "gr",
        "pour",
        "equipement"
    ],
    "wof:name":"Delvi Textiles",
    "wof:placetype":"venue"
},
  "geometry": {"coordinates":[3.3169870377,50.8497085571],"type":"Point"}
}