{
  "type": "Feature",
  "properties": {
    "addr:full":"Rue Du Pr\u00c9sident 18 Namur Namur 5000",
    "addr:housenumber":"18",
    "addr:postcode":"5000",
    "addr:street":"Rue Du Pre\u0301Sident",
    "iso:country":"BE",
    "sg:address":"Rue Du Pr\u00c9sident 18",
    "sg:city":"Namur",
    "sg:orig_category":"Chaussures",
    "sg:phone":"+32 81 23 13 11",
    "sg:postcode":"5000",
    "sg:province":"Namur",
    "wof:name":"Les Enfants De Pr\u00c9sidence",
    "wof:placetype":"venue"
},
  "geometry": {"coordinates":[4.863617897,50.4631996155],"type":"Point"}
}