{
  "type": "Feature",
  "properties": {
    "addr:full":"Lodewijk Weijtenstraat 35b6 Schoten Antwerpen 2900",
    "addr:housenumber":"35b6",
    "addr:postcode":"2900",
    "addr:street":"Lodewijk Weijtenstraat",
    "iso:country":"BE",
    "sg:address":"Lodewijk Weijtenstraat 35b6",
    "sg:city":"Schoten",
    "sg:orig_category":"Agences immobili\u00e8res",
    "sg:phone":"+32 3 658 05 67",
    "sg:postcode":"2900",
    "sg:province":"Antwerpen",
    "wof:name":"Guillaume De Pauw",
    "wof:placetype":"venue"
},
  "geometry": {"coordinates":[4.4924111366,51.2515869141],"type":"Point"}
}