{
  "type": "Feature",
  "properties": {
    "addr:full":"5 Oostlaan 8850 Ardooie 5",
    "addr:housenumber":"5",
    "addr:postcode":"8850",
    "addr:street":"Oostlaan",
    "iso:country":"BE",
    "sg:address":"5",
    "sg:city":"Oostlaan 8850 Ardooie",
    "sg:classifiers":[
        {
            "category":"Airport",
            "type":"Transportation"
        }
    ],
    "sg:phone":"+32 51 74 49 31",
    "sg:postcode":"5",
    "sg:tags":[
        "transport",
        "air"
    ],
    "wof:name":"Transport Frans Bevernaegie En Zonen Nv",
    "wof:placetype":"venue"
},
  "geometry": {"coordinates":[3.2022891045,50.9742164612],"type":"Point"}
}