{
  "type": "Feature",
  "properties": {
    "iso:country":"BE",
    "sg:address":"Rue Roture 68",
    "sg:city":"Li\u00c8ge",
    "sg:classifiers":[
        {
            "category":"Restaurant",
            "type":"Food & Drink"
        }
    ],
    "sg:phone":"+32 4 342 64 23",
    "sg:postcode":"4020",
    "sg:province":"Li\u00e8ge",
    "wof:name":"Restaurant Fondue Royale",
    "wof:placetype":"venue"
},
  "geometry": {"coordinates":[5.5823488235,50.6396980286],"type":"Point"}
}