{
  "type": "Feature",
  "properties": {
    "addr:full":"Groenstraat 40 Wervik West-Vlaanderen 8940",
    "addr:housenumber":"40",
    "addr:postcode":"8940",
    "addr:street":"Groenstraat",
    "iso:country":"BE",
    "sg:address":"Groenstraat 40",
    "sg:city":"Wervik",
    "sg:orig_category":"V\u00eatements. Textiles",
    "sg:phone":"+32 56 31 41 86",
    "sg:postcode":"8940",
    "sg:province":"West-Vlaanderen",
    "wof:name":"Phildar",
    "wof:placetype":"venue"
},
  "geometry": {"coordinates":[3.0438840389,50.7794914246],"type":"Point"}
}