{
  "type": "Feature",
  "properties": {
    "iso:country":"BE",
    "sg:address":"Rue De Sesselich 155",
    "sg:city":"Arlon",
    "sg:classifiers":[
        {
            "category":"Social Services",
            "subcategory":"Child Care",
            "type":"Services"
        }
    ],
    "sg:phone":"+32 63 22 12 22",
    "sg:postcode":"6700",
    "sg:province":"Luxembourg",
    "sg:tags":[
        "home"
    ],
    "wof:name":"Home Familial Sa",
    "wof:placetype":"venue"
},
  "geometry": {"coordinates":[5.8095088005,49.672706604],"type":"Point"}
}