{
  "type": "Feature",
  "properties": {
    "iso:country":"BE",
    "sg:address":"Grand Place 35",
    "sg:city":"Leuze-en-hainaut",
    "sg:classifiers":[
        {
            "category":"Bars & Pubs",
            "type":"Food & Drink"
        }
    ],
    "sg:phone":"+32 69 66 40 79",
    "sg:postcode":"7900",
    "sg:province":"Hainaut",
    "sg:tags":[
        "tavern"
    ],
    "wof:name":"Aux Quatre Vents",
    "wof:placetype":"venue"
},
  "geometry": {"coordinates":[3.6179430485,50.5985908508],"type":"Point"}
}