{
  "type": "Feature",
  "properties": {
    "iso:country":"BE",
    "sg:address":"Boterstraat 16",
    "sg:city":"Jabbeke",
    "sg:orig_category":"Verhuur televisie- and audiovisuele apparatuur",
    "sg:phone":"+32 50 81 61 30",
    "sg:postcode":"8490",
    "sg:province":"West-Vlaanderen",
    "wof:name":"Solid Sound",
    "wof:placetype":"venue"
},
  "geometry": {"coordinates":[3.1199860573,51.1743927002],"type":"Point"}
}