{
  "type": "Feature",
  "properties": {
    "iso:country":"BE",
    "sg:address":"Route De Ch\u00c2telet 324",
    "sg:city":"Charleroi",
    "sg:orig_category":"Traitements param\u00e9dicaux",
    "sg:phone":"+32 71 36 80 08",
    "sg:postcode":"6010",
    "sg:province":"Hainaut",
    "wof:name":"G. Denis",
    "wof:placetype":"venue"
},
  "geometry": {"coordinates":[4.471476078,50.3922348022],"type":"Point"}
}