{
  "type": "Feature",
  "properties": {
    "addr:full":"Zandstraat 19 Nazareth Oost-Vlaanderen 9810",
    "addr:housenumber":"19",
    "addr:postcode":"9810",
    "addr:street":"Zandstraat",
    "iso:country":"BE",
    "sg:address":"Zandstraat 19",
    "sg:city":"Nazareth",
    "sg:orig_category":"Artsen and specialisten",
    "sg:phone":"+32 9 385 47 88",
    "sg:postcode":"9810",
    "sg:province":"Oost-Vlaanderen",
    "wof:name":"J. Vercruysse",
    "wof:placetype":"venue"
},
  "geometry": {"coordinates":[3.6341679096,50.9498977661],"type":"Point"}
}