{
  "type": "Feature",
  "properties": {
    "addr:full":"Professor Dewulfstraat 62 Poperinge West-Vlaanderen 8970",
    "addr:housenumber":"62",
    "addr:postcode":"8970",
    "addr:street":"Professor Dewulfstraat",
    "iso:country":"BE",
    "sg:address":"Professor Dewulfstraat 62",
    "sg:city":"Poperinge",
    "sg:orig_category":"Sportclubs",
    "sg:phone":"+32 57 33 55 20",
    "sg:postcode":"8970",
    "sg:province":"West-Vlaanderen",
    "wof:name":"De Verbroedering",
    "wof:placetype":"venue"
},
  "geometry": {"coordinates":[2.7313940525,50.8534812927],"type":"Point"}
}