{
  "type": "Feature",
  "properties": {
    "addr:full":"Doorgangsstraat 8 Ieper West-Vlaanderen 8900",
    "addr:housenumber":"8",
    "addr:postcode":"8900",
    "addr:street":"Doorgangsstraat",
    "iso:country":"BE",
    "sg:address":"Doorgangsstraat 8",
    "sg:city":"Ieper",
    "sg:orig_category":"Fitnesscentra",
    "sg:phone":"+32 57 20 58 54",
    "sg:postcode":"8900",
    "sg:province":"West-Vlaanderen",
    "wof:name":"Stefaan Dai",
    "wof:placetype":"venue"
},
  "geometry": {"coordinates":[2.8792009354,50.8490943909],"type":"Point"}
}