{
  "type": "Feature",
  "properties": {
    "iso:country":"BE",
    "sg:address":"Walputstraat 5b8",
    "sg:city":"Hasselt",
    "sg:orig_category":"M\u00e9decins and sp\u00e9cialistes",
    "sg:phone":"+32 11 22 33 12",
    "sg:postcode":"3500",
    "sg:province":"Limburg",
    "wof:name":"A. De Graaf",
    "wof:placetype":"venue"
},
  "geometry": {"coordinates":[5.3372178078,50.9313583374],"type":"Point"}
}