{
  "type": "Feature",
  "properties": {
    "addr:full":"Aven Ackers 18 Beveren Oost-Vlaanderen 9130",
    "addr:housenumber":"18",
    "addr:postcode":"9130",
    "addr:street":"Aven Ackers",
    "iso:country":"BE",
    "sg:address":"Aven Ackers 18",
    "sg:city":"Beveren",
    "sg:orig_category":"Agences de voyages. Transports terrestres de voyageurs",
    "sg:phone":"+32 3 773 36 65",
    "sg:postcode":"9130",
    "sg:province":"Oost-Vlaanderen",
    "wof:name":"Van Bogget - Jaspers",
    "wof:placetype":"venue"
},
  "geometry": {"coordinates":[4.19018507,51.2502441406],"type":"Point"}
}