{
  "type": "Feature",
  "properties": {
    "addr:full":"Rue P\u00c8re Damien 12 Braine-le-comte Hainaut 7090",
    "addr:housenumber":"12",
    "addr:postcode":"7090",
    "addr:street":"Rue Pe\u0300Re Damien",
    "iso:country":"BE",
    "sg:address":"Rue P\u00c8re Damien 12",
    "sg:city":"Braine-le-comte",
    "sg:orig_category":"Enseignement maternel and primaire",
    "sg:phone":"+32 67 55 48 57",
    "sg:postcode":"7090",
    "sg:province":"Hainaut",
    "wof:name":"E.f.l. Notre-dame",
    "wof:placetype":"venue"
},
  "geometry": {"coordinates":[4.1371798515,50.6117553711],"type":"Point"}
}