{
  "type": "Feature",
  "properties": {
    "addr:full":"Ind.terrein-kanaal-noord 1303 Bree Limburg 3960",
    "addr:housenumber":"1303",
    "addr:postcode":"3960",
    "addr:street":"Bree Limburg",
    "iso:country":"BE",
    "sg:address":"Ind.terrein-kanaal-noord 1303",
    "sg:city":"Bree",
    "sg:orig_category":"Articles textiles and tissus de d\u00e9coration Fab. Location de mat\u00e9riel pour banquets and \u00e9v\u00e9nements",
    "sg:phone":"+32 89 47 26 26",
    "sg:postcode":"3960",
    "sg:province":"Limburg",
    "wof:name":"De Boer Tenten",
    "wof:placetype":"venue"
},
  "geometry": {"coordinates":[5.6272478104,51.1498527527],"type":"Point"}
}