{
  "type": "Feature",
  "properties": {
    "iso:country":"BE",
    "sg:address":"Rootenstraat 29 B8",
    "sg:city":"Genk",
    "sg:orig_category":"Meubles D\u00e9taillants, Am\u00e9nagement de B\u00e2timents et de Cuisines. Eclairage et \u00e9quipements du foyer",
    "sg:phone":"+32 89 35 25 44",
    "sg:postcode":"3600",
    "sg:province":"Limburg",
    "wof:name":"Meylaerts Light Center",
    "wof:placetype":"venue"
},
  "geometry": {"coordinates":[5.4990148544,50.9635848999],"type":"Point"}
}