{
  "type": "Feature",
  "properties": {
    "addr:full":"Rue Des Lavandi\u00c8res 32 Leglise Luxembourg 6860",
    "addr:housenumber":"32",
    "addr:postcode":"6860",
    "addr:street":"Rue Des Lavandie\u0300Res",
    "iso:country":"BE",
    "sg:address":"Rue Des Lavandi\u00c8res 32",
    "sg:city":"Leglise",
    "sg:orig_category":"Eleveurs de bovins",
    "sg:phone":"+32 63 60 12 50",
    "sg:postcode":"6860",
    "sg:province":"Luxembourg",
    "wof:name":"Jean-noel Dumont",
    "wof:placetype":"venue"
},
  "geometry": {"coordinates":[5.6139001846,49.8595695496],"type":"Point"}
}