{
  "type": "Feature",
  "properties": {
    "iso:country":"BE",
    "sg:address":"Wisselstraat 6",
    "sg:city":"Antwerpen",
    "sg:classifiers":[
        {
            "category":"Manufacturing",
            "subcategory":"Tobacco Products",
            "type":"Manufacturing & Wholesale Goods"
        }
    ],
    "sg:phone":"+32 3 232 97 01",
    "sg:postcode":"2000",
    "sg:province":"Antwerpen",
    "sg:tags":[
        "leaf",
        "-"
    ],
    "wof:name":"Philitab Nv",
    "wof:placetype":"venue"
},
  "geometry": {"coordinates":[4.4003920555,51.2217636108],"type":"Point"}
}