{
  "type": "Feature",
  "properties": {
    "addr:full":"Avenue Albert I 53 Huy Li\u00e8ge 4500",
    "addr:housenumber":"53",
    "addr:postcode":"4500",
    "addr:street":"Avenue Albert I",
    "iso:country":"BE",
    "sg:address":"Avenue Albert I 53",
    "sg:city":"Huy",
    "sg:classifiers":[
        {
            "category":"Professional",
            "subcategory":"Art Services",
            "type":"Services"
        }
    ],
    "sg:phone":"+32 85 23 06 42",
    "sg:postcode":"4500",
    "sg:province":"Li\u00e8ge",
    "sg:tags":[
        "sculptor"
    ],
    "wof:name":"Gustin",
    "wof:placetype":"venue"
},
  "geometry": {"coordinates":[5.2343959808,50.5249633789],"type":"Point"}
}