{
  "type": "Feature",
  "properties": {
    "addr:full":"Rue Likenne 63 Saint-nicolas Li\u00e8ge 4420",
    "addr:housenumber":"63",
    "addr:postcode":"4420",
    "addr:street":"Rue Likenne",
    "iso:country":"BE",
    "sg:address":"Rue Likenne 63",
    "sg:city":"Saint-nicolas",
    "sg:orig_category":"Salons de coiffure. Instituts de beaut\u00e9",
    "sg:phone":"+32 4 252 12 83",
    "sg:postcode":"4420",
    "sg:province":"Li\u00e8ge",
    "wof:name":"Coiffure Clara",
    "wof:placetype":"venue"
},
  "geometry": {"coordinates":[5.5424909592,50.6292686462],"type":"Point"}
}