{
  "type": "Feature",
  "properties": {
    "addr:full":"Steenmolenlaan 9 Zonnebeke West-Vlaanderen 8980",
    "addr:housenumber":"9",
    "addr:postcode":"8980",
    "addr:street":"Steenmolenlaan",
    "iso:country":"BE",
    "sg:address":"Steenmolenlaan 9",
    "sg:city":"Zonnebeke",
    "sg:classifiers":[
        {
            "category":"Personal",
            "subcategory":"Beauty Salon",
            "type":"Services"
        }
    ],
    "sg:phone":"+32 57 46 78 50",
    "sg:postcode":"8980",
    "sg:province":"West-Vlaanderen",
    "sg:tags":[
        "de",
        "coiffure"
    ],
    "wof:name":"Frederik Zole",
    "wof:placetype":"venue"
},
  "geometry": {"coordinates":[2.9872550964,50.8730812073],"type":"Point"}
}