{
  "type": "Feature",
  "properties": {
    "iso:country":"BE",
    "sg:address":"Rue De L'h\u00f4tel De Ville 15",
    "sg:city":"Jemeppe-sur-sambre (mornimont)",
    "sg:classifiers":[
        {
            "category":"Professional",
            "subcategory":"Art Services",
            "type":"Services"
        }
    ],
    "sg:phone":"+32 71 78 17 91",
    "sg:postcode":"5190",
    "sg:province":"Namur",
    "sg:tags":[
        "interior",
        "designer"
    ],
    "wof:name":"Muros Sa",
    "wof:placetype":"venue"
},
  "geometry": {"coordinates":[4.7047681808,50.4606933594],"type":"Point"}
}