{
  "type": "Feature",
  "properties": {
    "addr:full":"Rue Saint-s\u00c9bastien 32 Braine-l\u00b4alleud Brabant Wallon 1420",
    "addr:housenumber":"32",
    "addr:postcode":"1420",
    "addr:street":"Rue Saint-Se\u0301Bastien;Brabant Wallon",
    "iso:country":"BE",
    "sg:address":"Rue Saint-s\u00c9bastien 32",
    "sg:city":"Braine-l\u00b4alleud",
    "sg:orig_category":"Instellingen voor probleemkinderen Kindertehuizen",
    "sg:phone":"+32 2 384 14 33",
    "sg:postcode":"1420",
    "sg:province":"Brabant Wallon",
    "wof:name":"Foyer Chez Nous",
    "wof:placetype":"venue"
},
  "geometry": {"coordinates":[4.3768081665,50.6786651611],"type":"Point"}
}