{
  "type": "Feature",
  "properties": {
    "addr:full":"Moleneinde 39 Westerlo (oevel) Antwerpen 2260",
    "addr:housenumber":"39",
    "addr:postcode":"2260",
    "addr:street":"Moleneinde",
    "iso:country":"BE",
    "sg:address":"Moleneinde 39",
    "sg:city":"Westerlo (oevel)",
    "sg:classifiers":[
        {
            "category":"Professional",
            "subcategory":"Computer Services",
            "type":"Services"
        }
    ],
    "sg:phone":"+32 479 59 42 84",
    "sg:postcode":"2260",
    "sg:province":"Antwerpen",
    "sg:tags":[
        "-",
        "processing",
        "data",
        "software"
    ],
    "wof:name":"Bsc",
    "wof:placetype":"venue"
},
  "geometry": {"coordinates":[4.9002809525,51.1455039978],"type":"Point"}
}