{
  "type": "Feature",
  "properties": {
    "iso:country":"BE",
    "sg:address":"Neerlandensestraat 8bc",
    "sg:city":"Zoutleeuw",
    "sg:orig_category":"R\u00e9parations de chaussures and articles en cuir",
    "sg:phone":"+32 11 78 22 67",
    "sg:postcode":"3440",
    "sg:province":"Vlaams-Brabant",
    "wof:name":"Simon Lenaers",
    "wof:placetype":"venue"
},
  "geometry": {"coordinates":[5.0976209641,50.8052024841],"type":"Point"}
}