{
  "type": "Feature",
  "properties": {
    "iso:country":"BE",
    "sg:address":"Rue Antoine Gautier 62",
    "sg:city":"Bruxelles (etterbeek)",
    "sg:classifiers":[
        {
            "category":"Professional",
            "subcategory":"Management & Consulting",
            "type":"Services"
        }
    ],
    "sg:phone":"+32 2 735 73 34",
    "sg:postcode":"1040",
    "sg:province":"Bruxelles-Capitale",
    "sg:tags":[
        "marketing",
        "-",
        "direct",
        "consultant"
    ],
    "wof:name":"Ken Kenny & Mc Kay",
    "wof:placetype":"venue"
},
  "geometry": {"coordinates":[4.3903260231,50.8347892761],"type":"Point"}
}