{
  "type": "Feature",
  "properties": {
    "addr:full":"Chauss\u00c9e De Bruxelles 321 Wavre Brabant Wallon 1300",
    "addr:housenumber":"321;1300",
    "addr:street":"Chausse\u0301E De Bruxelles",
    "iso:country":"BE",
    "sg:address":"Chauss\u00c9e De Bruxelles 321",
    "sg:city":"Wavre",
    "sg:orig_category":"Diverse grafische activiteiten",
    "sg:phone":"+32 10 24 15 15",
    "sg:postcode":"1300",
    "sg:province":"Brabant Wallon",
    "wof:name":"Bureau Publigraph",
    "wof:placetype":"venue"
},
  "geometry": {"coordinates":[4.5927209854,50.7296333313],"type":"Point"}
}