{
  "type": "Feature",
  "properties": {
    "addr:full":"Gestellei 7 Bonheiden Antwerpen 2820",
    "addr:housenumber":"7",
    "addr:postcode":"2820",
    "addr:street":"Gestellei",
    "iso:country":"BE",
    "sg:address":"Gestellei 7",
    "sg:city":"Bonheiden",
    "sg:classifiers":[
        {
            "category":"Autos & Motor Vehicles",
            "subcategory":"Fuel & Gas Station",
            "type":"Retail Goods"
        }
    ],
    "sg:phone":"+32 15 55 37 07",
    "sg:postcode":"2820",
    "sg:province":"Antwerpen",
    "sg:tags":[
        "stations-service",
        "carburants"
    ],
    "wof:name":"Theodoor Schmitz",
    "wof:placetype":"venue"
},
  "geometry": {"coordinates":[4.5238828659,51.0399894714],"type":"Point"}
}