{
  "type": "Feature",
  "properties": {
    "addr:full":"Koning Albert I Laan 46 Wemmel Vlaams-Brabant 1780",
    "addr:housenumber":"46",
    "addr:postcode":"1780",
    "addr:street":"Koning Albert I Laan;Vlaams-Brabant",
    "iso:country":"BE",
    "sg:address":"Koning Albert I Laan 46",
    "sg:city":"Wemmel",
    "sg:classifiers":[
        {
            "category":"Government",
            "subcategory":"Fire Station",
            "type":"Public Place"
        }
    ],
    "sg:phone":"+32 2 461 04 08",
    "sg:postcode":"1780",
    "sg:province":"Vlaams-Brabant",
    "sg:tags":[
        "development",
        "hardware",
        "soft"
    ],
    "wof:name":"Pep Modular Computers Benelux Nv",
    "wof:placetype":"venue"
},
  "geometry": {"coordinates":[4.3190760612,50.8994178772],"type":"Point"}
}