{
  "type": "Feature",
  "properties": {
    "iso:country":"BE",
    "sg:address":"Avenue De Wallonie 33b2c",
    "sg:city":"Charleroi",
    "sg:classifiers":[
        {
            "category":"Cafe",
            "type":"Food & Drink"
        }
    ],
    "sg:phone":"+32 71 46 07 42",
    "sg:postcode":"6044",
    "sg:province":"Hainaut",
    "sg:tags":[
        "caf\u00e9s"
    ],
    "wof:name":"Yvonne Deschryver",
    "wof:placetype":"venue"
},
  "geometry": {"coordinates":[4.3888568878,50.4500846863],"type":"Point"}
}