{
  "type": "Feature",
  "properties": {
    "iso:country":"BE",
    "sg:address":"Wijmenstraat 22",
    "sg:city":"Gent (mariakerke)",
    "sg:classifiers":[
        {
            "category":"Retail",
            "subcategory":"Auto Repair",
            "type":"Services"
        }
    ],
    "sg:phone":"+32 9 236 36 96",
    "sg:postcode":"9030",
    "sg:province":"Oost-Vlaanderen",
    "sg:tags":[
        "automobile-body"
    ],
    "wof:name":"Moerman Guido Bvba",
    "wof:placetype":"venue"
},
  "geometry": {"coordinates":[3.6745951176,51.072933197],"type":"Point"}
}