{
  "type": "Feature",
  "properties": {
    "addr:full":"Rue Lucien Nam\u00cache 30 Namur Namur 5000",
    "addr:housenumber":"30",
    "addr:postcode":"5000",
    "addr:street":"Rue Lucien Name\u0302Che",
    "iso:country":"BE",
    "sg:address":"Rue Lucien Nam\u00cache 30",
    "sg:city":"Namur",
    "sg:orig_category":"Benzinestations and brandstoffen",
    "sg:phone":"+32 81 22 61 86",
    "sg:postcode":"5000",
    "sg:province":"Namur",
    "wof:name":"Dilabel",
    "wof:placetype":"venue"
},
  "geometry": {"coordinates":[4.8686537743,50.467666626],"type":"Point"}
}