{
  "type": "Feature",
  "properties": {
    "addr:full":"Rue De Bouillon 266 Beauraing Namur 5574",
    "addr:housenumber":"266",
    "addr:postcode":"5574",
    "addr:street":"Rue De Bouillon",
    "iso:country":"BE",
    "sg:address":"Rue De Bouillon 266",
    "sg:city":"Beauraing",
    "sg:orig_category":"Installation \u00e9lectrique r\u00e9sidentielle",
    "sg:phone":"+32 82 71 20 72",
    "sg:postcode":"5574",
    "sg:province":"Namur",
    "wof:name":"E.m.s.",
    "wof:placetype":"venue"
},
  "geometry": {"coordinates":[4.9910669327,50.1002426147],"type":"Point"}
}