{
  "type": "Feature",
  "properties": {
    "iso:country":"BE",
    "sg:address":"Chauss\u00e9e De Bruxelles 238",
    "sg:city":"Waterloo",
    "sg:classifiers":[
        {
            "category":"Shopping",
            "subcategory":"Clothing, Apparel, & Fashions",
            "type":"Retail Goods"
        }
    ],
    "sg:phone":"+32 2 351 08 63",
    "sg:postcode":"1410",
    "sg:province":"Brabant Wallon",
    "sg:tags":[
        "lady",
        "clothing",
        "-"
    ],
    "wof:name":"Lili Rose",
    "wof:placetype":"venue"
},
  "geometry": {"coordinates":[4.3982548714,50.7163314819],"type":"Point"}
}