{
  "type": "Feature",
  "properties": {
    "iso:country":"BE",
    "sg:address":"Grand'route 168",
    "sg:city":"Walcourt",
    "sg:orig_category":"Sportclubs",
    "sg:phone":"+32 71 65 58 27",
    "sg:postcode":"5651",
    "sg:province":"Namur",
    "wof:name":"C.s.s. Florennes",
    "wof:placetype":"venue"
},
  "geometry": {"coordinates":[4.4332799911,50.2857818604],"type":"Point"}
}