{
  "type": "Feature",
  "properties": {
    "addr:full":"Hertogenlaan 31 Lubbeek (linden) Vlaams-Brabant 3210",
    "addr:housenumber":"31",
    "addr:postcode":"3210",
    "addr:street":"Hertogenlaan",
    "iso:country":"BE",
    "sg:address":"Hertogenlaan 31",
    "sg:city":"Lubbeek (linden)",
    "sg:classifiers":[
        {
            "category":"Real Estate",
            "subcategory":"Architect",
            "type":"Services"
        }
    ],
    "sg:phone":"+32 16 25 35 05",
    "sg:postcode":"3210",
    "sg:province":"Vlaams-Brabant",
    "wof:name":"Cappelle C",
    "wof:placetype":"venue"
},
  "geometry": {"coordinates":[4.7614388466,50.9056015015],"type":"Point"}
}