{
  "type": "Feature",
  "properties": {
    "addr:full":"Rue Du Boussart 5 Rebecq Brabant Wallon 1430",
    "addr:housenumber":"5",
    "addr:postcode":"1430",
    "addr:street":"Rue Du Boussart",
    "iso:country":"BE",
    "sg:address":"Rue Du Boussart 5",
    "sg:city":"Rebecq",
    "sg:classifiers":[
        {
            "category":"Insurance",
            "subcategory":"Insurance Agent",
            "type":"Services"
        }
    ],
    "sg:phone":"+32 2 395 84 56",
    "sg:postcode":"1430",
    "sg:province":"Brabant Wallon",
    "sg:tags":[
        "verzekeringsmakelaars",
        "expert"
    ],
    "wof:name":"Mdm Buro",
    "wof:placetype":"venue"
},
  "geometry": {"coordinates":[4.1276512146,50.6983833313],"type":"Point"}
}