{
  "type": "Feature",
  "properties": {
    "addr:full":"Emile Derooverstraat 32 Koekelberg/koekelberg Bruxelles-Capitale 1081",
    "addr:housenumber":"32",
    "addr:postcode":"1081",
    "addr:street":"Emile Derooverstraat",
    "iso:country":"BE",
    "sg:address":"Emile Derooverstraat 32",
    "sg:city":"Koekelberg/koekelberg",
    "sg:orig_category":"Persagentschappen",
    "sg:phone":"+32 2 411 12 14",
    "sg:postcode":"1081",
    "sg:province":"Bruxelles-Capitale",
    "wof:name":"Jean-paul Vankeerberghen",
    "wof:placetype":"venue"
},
  "geometry": {"coordinates":[4.3140649796,50.8650588989],"type":"Point"}
}