{
  "type": "Feature",
  "properties": {
    "addr:full":"Pachtgoedstraat 4 Temse Oost-Vlaanderen 9140",
    "addr:housenumber":"4",
    "addr:postcode":"9140",
    "addr:street":"Pachtgoedstraat",
    "iso:country":"BE",
    "sg:address":"Pachtgoedstraat 4",
    "sg:city":"Temse",
    "sg:classifiers":[
        {
            "category":"Manufacturing",
            "subcategory":"Metals",
            "type":"Manufacturing & Wholesale Goods"
        }
    ],
    "sg:phone":"+32 3 777 90 67",
    "sg:postcode":"9140",
    "sg:province":"Oost-Vlaanderen",
    "sg:tags":[
        "steel",
        "stainless"
    ],
    "wof:name":"Alinco Nv",
    "wof:placetype":"venue"
},
  "geometry": {"coordinates":[4.1916589737,51.1478347778],"type":"Point"}
}