{
  "type": "Feature",
  "properties": {
    "addr:full":"Mankemerriestraat 7 Tielt West-Vlaanderen 8700",
    "addr:housenumber":"7",
    "addr:postcode":"8700",
    "addr:street":"Mankemerriestraat",
    "iso:country":"BE",
    "sg:address":"Mankemerriestraat 7",
    "sg:city":"Tielt",
    "sg:orig_category":"Rundveehouders Varkenskwekers",
    "sg:phone":"+32 51 40 58 23",
    "sg:postcode":"8700",
    "sg:province":"West-Vlaanderen",
    "wof:name":"Roger Van Compernolle",
    "wof:placetype":"venue"
},
  "geometry": {"coordinates":[3.3531560898,50.9822120667],"type":"Point"}
}