{
  "type": "Feature",
  "properties": {
    "addr:full":"Langegrachtstraat 17 Borgloon Limburg 3840",
    "addr:housenumber":"17",
    "addr:postcode":"3840",
    "addr:street":"Langegrachtstraat",
    "iso:country":"BE",
    "sg:address":"Langegrachtstraat 17",
    "sg:city":"Borgloon",
    "sg:orig_category":"Fruitteelt",
    "sg:phone":"+32 12 74 73 36",
    "sg:postcode":"3840",
    "sg:province":"Limburg",
    "wof:name":"Willy Ketelslegers",
    "wof:placetype":"venue"
},
  "geometry": {"coordinates":[5.3441700935,50.8012466431],"type":"Point"}
}