{
  "type": "Feature",
  "properties": {
    "addr:full":"Rue Haute Claire 20 Herstal Li\u00e8ge 4040",
    "addr:housenumber":"20",
    "addr:postcode":"4040",
    "addr:street":"Rue Haute Claire",
    "iso:country":"BE",
    "sg:address":"Rue Haute Claire 20",
    "sg:city":"Herstal",
    "sg:classifiers":[
        {
            "category":"Home & Garden",
            "subcategory":"Building Materials",
            "type":"Retail Goods"
        }
    ],
    "sg:phone":"+32 4 278 90 77",
    "sg:postcode":"4040",
    "sg:province":"Li\u00e8ge",
    "sg:tags":[
        "veranda"
    ],
    "wof:name":"Somivane Sa",
    "wof:placetype":"venue"
},
  "geometry": {"coordinates":[5.6246609688,50.6574516296],"type":"Point"}
}