{
  "type": "Feature",
  "properties": {
    "addr:full":"Peter Benoitplein 5b Brussel (brussel) Bruxelles-Capitale 1120",
    "addr:housenumber":"5b",
    "addr:postcode":"1120",
    "addr:street":"Peter Benoitplein",
    "iso:country":"BE",
    "sg:address":"Peter Benoitplein 5b",
    "sg:city":"Brussel (brussel)",
    "sg:orig_category":"Kapsalons",
    "sg:phone":"+32 2 262 23 00",
    "sg:postcode":"1120",
    "sg:province":"Bruxelles-Capitale",
    "wof:name":"Coiffure Artizo",
    "wof:placetype":"venue"
},
  "geometry": {"coordinates":[4.3876619339,50.8955802917],"type":"Point"}
}