{
  "type": "Feature",
  "properties": {
    "addr:full":"Leopold I-laan 86-88 Brugge West-Vlaanderen 8000",
    "addr:postcode":"86-88;8000",
    "addr:street":"Leopold I-Laan",
    "iso:country":"BE",
    "sg:address":"Leopold I-laan 86-88",
    "sg:city":"Brugge",
    "sg:classifiers":[
        {
            "category":"Shopping",
            "subcategory":"Florist",
            "type":"Retail Goods"
        }
    ],
    "sg:phone":"+32 50 31 27 92",
    "sg:postcode":"8000",
    "sg:province":"West-Vlaanderen",
    "wof:name":"Damman Florist",
    "wof:placetype":"venue"
},
  "geometry": {"coordinates":[3.2085928917,51.2151794434],"type":"Point"}
}