{
  "type": "Feature",
  "properties": {
    "addr:full":"Onze-lieve-vrouwestraat 135 Mechelen Antwerpen 2800",
    "addr:housenumber":"135",
    "addr:postcode":"2800",
    "addr:street":"Onze-Lieve-Vrouwestraat",
    "iso:country":"BE",
    "sg:address":"Onze-lieve-vrouwestraat 135",
    "sg:city":"Mechelen",
    "sg:classifiers":[
        {
            "category":"Shopping",
            "subcategory":"Jewelry",
            "type":"Retail Goods"
        }
    ],
    "sg:phone":"+32 15 33 61 64",
    "sg:postcode":"2800",
    "sg:province":"Antwerpen",
    "sg:tags":[
        "jeweller",
        "-"
    ],
    "wof:name":"Van Lil J",
    "wof:placetype":"venue"
},
  "geometry": {"coordinates":[4.481610775,51.0226402283],"type":"Point"}
}