{
  "type": "Feature",
  "properties": {
    "addr:full":"Collegestraat 30 Herentals Antwerpen 2200",
    "addr:housenumber":"30",
    "addr:postcode":"2200",
    "addr:street":"Collegestraat",
    "iso:country":"BE",
    "sg:address":"Collegestraat 30",
    "sg:city":"Herentals",
    "sg:classifiers":[
        {
            "category":"Real Estate",
            "subcategory":"Architect",
            "type":"Services"
        }
    ],
    "sg:phone":"+32 14 22 26 04",
    "sg:postcode":"2200",
    "sg:province":"Antwerpen",
    "wof:name":"Baelus P",
    "wof:placetype":"venue"
},
  "geometry": {"coordinates":[4.8330798149,51.1762428284],"type":"Point"}
}