{
  "type": "Feature",
  "properties": {
    "iso:country":"BE",
    "sg:address":"Mercuriusln. 1",
    "sg:city":"Genk-winterslag",
    "sg:classifiers":[
        {
            "category":"Home & Garden",
            "subcategory":"Furniture",
            "type":"Retail Goods"
        }
    ],
    "sg:phone":"+32 89 50 01 00",
    "sg:postcode":"3600",
    "sg:province":"Limburg",
    "sg:tags":[
        "household",
        "wood"
    ],
    "wof:name":"Ikea Wholesale Belgium",
    "wof:placetype":"venue"
},
  "geometry": {"coordinates":[5.4644050598,50.9868888855],"type":"Point"}
}