{
  "type": "Feature",
  "properties": {
    "iso:country":"BE",
    "sg:address":"Rozelaarstraat 20",
    "sg:city":"Ninove",
    "sg:orig_category":"Quincailleries",
    "sg:phone":"+32 54 33 01 52",
    "sg:postcode":"9400",
    "sg:province":"Oost-Vlaanderen",
    "wof:name":"Danny Van Vreckem",
    "wof:placetype":"venue"
},
  "geometry": {"coordinates":[4.0265769958,50.7890472412],"type":"Point"}
}