{
  "type": "Feature",
  "properties": {
    "addr:full":"Rue Franklin-roosevelt 1 Neufchateau Luxembourg 6840",
    "addr:housenumber":"1",
    "addr:postcode":"6840",
    "addr:street":"Rue Franklin-Roosevelt",
    "iso:country":"BE",
    "sg:address":"Rue Franklin-roosevelt 1",
    "sg:city":"Neufchateau",
    "sg:orig_category":"Chaussures",
    "sg:phone":"+32 61 27 76 90",
    "sg:postcode":"6840",
    "sg:province":"Luxembourg",
    "wof:name":"Shoes In The Box",
    "wof:placetype":"venue"
},
  "geometry": {"coordinates":[5.4349069595,49.8404083252],"type":"Point"}
}