{
  "type": "Feature",
  "properties": {
    "addr:full":"Rue Des Braicheux 249 La Louvi\u00e8re (maurage) Hainaut 7110",
    "addr:housenumber":"249",
    "addr:postcode":"7110",
    "addr:street":"Rue Des Braicheux",
    "iso:country":"BE",
    "sg:address":"Rue Des Braicheux 249",
    "sg:city":"La Louvi\u00e8re (maurage)",
    "sg:classifiers":[
        {
            "category":"Manufacturing",
            "subcategory":"Metals",
            "type":"Manufacturing & Wholesale Goods"
        }
    ],
    "sg:phone":"+32 64 34 29 38",
    "sg:postcode":"7110",
    "sg:province":"Hainaut",
    "sg:tags":[
        "ironwork"
    ],
    "wof:name":"Pistone Ets",
    "wof:placetype":"venue"
},
  "geometry": {"coordinates":[4.1505050659,50.4826698303],"type":"Point"}
}