{
  "type": "Feature",
  "properties": {
    "addr:full":"Parklaan 66b Gent Oost-Vlaanderen 9000",
    "addr:housenumber":"66b",
    "addr:postcode":"9000",
    "addr:street":"Parklaan;Oost-Vlaanderen",
    "iso:country":"BE",
    "sg:address":"Parklaan 66b",
    "sg:city":"Gent",
    "sg:classifiers":[
        {
            "category":"Wholesale",
            "subcategory":"Wine & Distilled Alcoholic Beverages",
            "type":"Manufacturing & Wholesale Goods"
        }
    ],
    "sg:phone":"+32 9 221 46 74",
    "sg:postcode":"9000",
    "sg:province":"Oost-Vlaanderen",
    "sg:tags":[
        "whol",
        "-",
        "spirit",
        "mfg"
    ],
    "wof:name":"Godfroid G",
    "wof:placetype":"venue"
},
  "geometry": {"coordinates":[3.7176320553,51.0348358154],"type":"Point"}
}