{
  "type": "Feature",
  "properties": {
    "iso:country":"BE",
    "sg:address":"Hendekenstraat 55",
    "sg:city":"Bassevelde",
    "sg:classifiers":[
        {
            "category":"Manufacturing",
            "subcategory":"Building Materials",
            "type":"Manufacturing & Wholesale Goods"
        }
    ],
    "sg:phone":"+32 9 373 60 32",
    "sg:postcode":"9968",
    "sg:province":"Oost-Vlaanderen",
    "sg:tags":[
        "packaging",
        "small",
        "chest",
        "wood",
        "gift"
    ],
    "wof:name":"Braet Nv",
    "wof:placetype":"venue"
},
  "geometry": {"coordinates":[3.7121899128,51.2310791016],"type":"Point"}
}