{
  "type": "Feature",
  "properties": {
    "addr:full":"Chauss\u00e9e Brunehault 5 Frameries (eugies) Hainaut 7080",
    "addr:housenumber":"5",
    "addr:postcode":"7080",
    "addr:street":"Chausse\u0301E Brunehault",
    "iso:country":"BE",
    "sg:address":"Chauss\u00e9e Brunehault 5",
    "sg:city":"Frameries (eugies)",
    "sg:orig_category":"Non-Classified Establishments",
    "sg:phone":"+32 65 67 33 35",
    "sg:postcode":"7080",
    "sg:province":"Hainaut",
    "wof:name":"Loiselet Heraut",
    "wof:placetype":"venue"
},
  "geometry": {"coordinates":[3.9013249874,50.4052352905],"type":"Point"}
}