{
  "type": "Feature",
  "properties": {
    "addr:full":"Beukenpark 14 Aalter Oost-Vlaanderen 9880",
    "addr:housenumber":"14",
    "addr:postcode":"9880",
    "addr:street":"Beukenpark",
    "iso:country":"BE",
    "sg:address":"Beukenpark 14",
    "sg:city":"Aalter",
    "sg:orig_category":"Woningbouw",
    "sg:phone":"+32 9 374 68 91",
    "sg:postcode":"9880",
    "sg:province":"Oost-Vlaanderen",
    "wof:name":"Freddy Bonte",
    "wof:placetype":"venue"
},
  "geometry": {"coordinates":[3.4558489323,51.0729637146],"type":"Point"}
}