{
  "type": "Feature",
  "properties": {
    "addr:full":"Avenue Charles-quint 87 Ganshoren Bruxelles-Capitale 1083",
    "addr:housenumber":"87",
    "addr:postcode":"1083",
    "addr:street":"Avenue Charles-Quint",
    "iso:country":"BE",
    "sg:address":"Avenue Charles-quint 87",
    "sg:city":"Ganshoren",
    "sg:orig_category":"Bloemen and planten",
    "sg:phone":"+32 2 425 32 56",
    "sg:postcode":"1083",
    "sg:province":"Bruxelles-Capitale",
    "wof:name":"Fleurs Lea",
    "wof:placetype":"venue"
},
  "geometry": {"coordinates":[4.3115968704,50.8684692383],"type":"Point"}
}