{
  "type": "Feature",
  "properties": {
    "addr:full":"Avenue G\u00c9n\u00c9ral Gracia 36 Profondeville Namur 5170",
    "addr:housenumber":"36",
    "addr:postcode":"5170",
    "addr:street":"Avenue Ge\u0301Ne\u0301Ral Gracia",
    "iso:country":"BE",
    "sg:address":"Avenue G\u00c9n\u00c9ral Gracia 36",
    "sg:city":"Profondeville",
    "sg:classifiers":[
        {
            "category":"Travel",
            "subcategory":"Hotels & Motels",
            "type":"Entertainment"
        }
    ],
    "sg:phone":"+32 81 41 12 61",
    "sg:postcode":"5170",
    "sg:province":"Namur",
    "sg:tags":[
        "van",
        "restaurant",
        "food",
        "fast",
        "feesten",
        "meeneem",
        "organisatie",
        "catering"
    ],
    "wof:name":"Restaurant Le Beauregard",
    "wof:placetype":"venue"
},
  "geometry": {"coordinates":[4.8780250549,50.3883857727],"type":"Point"}
}