{
  "type": "Feature",
  "properties": {
    "addr:full":"Breemputhof 12a Vilvoorde Vlaams-Brabant 1800",
    "addr:housenumber":"12a",
    "addr:postcode":"1800",
    "addr:street":"Breemputhof",
    "iso:country":"BE",
    "sg:address":"Breemputhof 12a",
    "sg:city":"Vilvoorde",
    "sg:classifiers":[
        {
            "category":"Social Services",
            "type":"Services"
        }
    ],
    "sg:phone":"+32 2 253 98 61",
    "sg:postcode":"1800",
    "sg:province":"Vlaams-Brabant",
    "sg:tags":[
        "handicapped",
        "-"
    ],
    "wof:name":"Begeleid Wonen Zennestreek",
    "wof:placetype":"venue"
},
  "geometry": {"coordinates":[4.4086728096,50.9247322083],"type":"Point"}
}