{
  "type": "Feature",
  "properties": {
    "iso:country":"BE",
    "sg:address":"Koningin Fabiolalaan 116",
    "sg:city":"Gent",
    "sg:classifiers":[
        {
            "category":"Social Services",
            "type":"Services"
        }
    ],
    "sg:phone":"+32 9 248 38 11",
    "sg:postcode":"9000",
    "sg:province":"Oost-Vlaanderen",
    "wof:name":"Rijksdienst Voor Pensioenen",
    "wof:placetype":"venue"
},
  "geometry": {"coordinates":[3.6964809895,51.0405502319],"type":"Point"}
}