{
  "type": "Feature",
  "properties": {
    "iso:country":"BE",
    "sg:address":"Rue Augustin Delporte 80",
    "sg:city":"Elsene/ixelles",
    "sg:orig_category":"Epiceries",
    "sg:phone":"+32 2 646 78 36",
    "sg:postcode":"1050",
    "sg:province":"Bruxelles-Capitale",
    "wof:name":"Rala",
    "wof:placetype":"venue"
},
  "geometry": {"coordinates":[4.382417202,50.8235282898],"type":"Point"}
}