{
  "type": "Feature",
  "properties": {
    "iso:country":"BE",
    "sg:address":"Wervikstraat 89",
    "sg:city":"Menen",
    "sg:classifiers":[
        {
            "category":"Fast Food",
            "type":"Food & Drink"
        }
    ],
    "sg:phone":"+32 56 51 99 10",
    "sg:postcode":"8930",
    "sg:province":"West-Vlaanderen",
    "sg:tags":[
        "meeneem",
        "restaurant"
    ],
    "wof:name":"Frituur Alcazar",
    "wof:placetype":"venue"
},
  "geometry": {"coordinates":[3.1108930111,50.7959480286],"type":"Point"}
}