{
  "type": "Feature",
  "properties": {
    "addr:full":"Uikhoverstraat 14 Maasmechelen Limburg 3631",
    "addr:housenumber":"14",
    "addr:postcode":"3631",
    "addr:street":"Uikhoverstraat",
    "iso:country":"BE",
    "sg:address":"Uikhoverstraat 14",
    "sg:city":"Maasmechelen",
    "sg:orig_category":"Meubelzaken, woning- and keukeninrichting",
    "sg:phone":"+32 89 71 51 19",
    "sg:postcode":"3631",
    "sg:province":"Limburg",
    "wof:name":"Jean Bollen",
    "wof:placetype":"venue"
},
  "geometry": {"coordinates":[5.7239232063,50.9423713684],"type":"Point"}
}