{
  "type": "Feature",
  "properties": {
    "addr:full":"Stationsstraat 64 Beveren Oost-Vlaanderen 9120",
    "addr:housenumber":"64",
    "addr:postcode":"9120",
    "addr:street":"Stationsstraat",
    "iso:country":"BE",
    "sg:address":"Stationsstraat 64",
    "sg:city":"Beveren",
    "sg:orig_category":"Boucheries",
    "sg:phone":"+32 3 755 18 97",
    "sg:postcode":"9120",
    "sg:province":"Oost-Vlaanderen",
    "wof:name":"'t Neerhof",
    "wof:placetype":"venue"
},
  "geometry": {"coordinates":[4.2575950623,51.2099914551],"type":"Point"}
}