{
  "type": "Feature",
  "properties": {
    "addr:full":"Gijmelsesteenweg 10 Aarschot Vlaams-Brabant 3200",
    "addr:housenumber":"10",
    "addr:postcode":"3200",
    "addr:street":"Gijmelsesteenweg",
    "iso:country":"BE",
    "sg:address":"Gijmelsesteenweg 10",
    "sg:city":"Aarschot",
    "sg:orig_category":"Cr\u00e9meries",
    "sg:phone":"+32 16 56 77 19",
    "sg:postcode":"3200",
    "sg:province":"Vlaams-Brabant",
    "wof:name":"Theys",
    "wof:placetype":"venue"
},
  "geometry": {"coordinates":[4.8425908089,50.9936904907],"type":"Point"}
}