{
  "type": "Feature",
  "properties": {
    "iso:country":"BE",
    "sg:address":"Vandenpeereboomstraat 30",
    "sg:city":"Halle",
    "sg:classifiers":[
        {
            "category":"Bars & Pubs",
            "type":"Food & Drink"
        }
    ],
    "sg:phone":"+32 2 356 61 69",
    "sg:postcode":"1500",
    "sg:province":"Vlaams-Brabant",
    "wof:name":"Cafe De La Station",
    "wof:placetype":"venue"
},
  "geometry": {"coordinates":[4.2397198677,50.7327690125],"type":"Point"}
}