{
  "type": "Feature",
  "properties": {
    "addr:full":"Pl Aux Foires 2 Durbuy Luxembourg 6940",
    "addr:housenumber":"2",
    "addr:postcode":"6940",
    "addr:street":"Pl Aux Foires",
    "iso:country":"BE",
    "sg:address":"Pl Aux Foires 2",
    "sg:city":"Durbuy",
    "sg:classifiers":[
        {
            "category":"Travel",
            "subcategory":"Hotels & Motels",
            "type":"Entertainment"
        }
    ],
    "sg:phone":"+32 86 21 28 82",
    "sg:postcode":"6940",
    "sg:province":"Luxembourg",
    "sg:tags":[
        "hotels",
        "business",
        "restaurant"
    ],
    "wof:name":"Hotel Jean De Boheme Sa",
    "wof:placetype":"venue"
},
  "geometry": {"coordinates":[5.4551639557,50.3513565063],"type":"Point"}
}