{
  "type": "Feature",
  "properties": {
    "addr:full":"Rue De-clerembault 17 Angleur Li\u00e8ge 4031",
    "addr:housenumber":"17",
    "addr:postcode":"4031",
    "addr:street":"Rue De-Clerembault",
    "iso:country":"BE",
    "sg:address":"Rue De-clerembault 17",
    "sg:city":"Angleur",
    "sg:classifiers":[
        {
            "category":"Airport",
            "subcategory":"General Aviation",
            "type":"Transportation"
        }
    ],
    "sg:phone":"+32 4 367 52 43",
    "sg:postcode":"4031",
    "sg:province":"Li\u00e8ge",
    "sg:tags":[
        "dehumidifiers",
        "air"
    ],
    "wof:name":"Drytec S.a.",
    "wof:placetype":"venue"
},
  "geometry": {"coordinates":[5.599583149,50.6115036011],"type":"Point"}
}