{
  "type": "Feature",
  "properties": {
    "addr:full":"Rue Joseph Wauters 42a Waremme Li\u00e8ge 4300",
    "addr:housenumber":"42a",
    "addr:postcode":"4300",
    "addr:street":"Rue Joseph Wauters",
    "iso:country":"BE",
    "sg:address":"Rue Joseph Wauters 42a",
    "sg:city":"Waremme",
    "sg:classifiers":[
        {
            "category":"Shopping",
            "subcategory":"Clothing, Apparel, & Fashions",
            "type":"Retail Goods"
        }
    ],
    "sg:phone":"+32 19 33 26 96",
    "sg:postcode":"4300",
    "sg:province":"Li\u00e8ge",
    "sg:tags":[
        "lady",
        "clothing",
        "-"
    ],
    "wof:name":"Cool",
    "wof:placetype":"venue"
},
  "geometry": {"coordinates":[5.2531619072,50.6959152222],"type":"Point"}
}