{
  "type": "Feature",
  "properties": {
    "iso:country":"BE",
    "sg:address":"Poolse Winglaan 90",
    "sg:city":"Gent",
    "sg:orig_category":"Diverse bedrijfsbeheeradviesbureaus",
    "sg:phone":"+32 9 221 52 95",
    "sg:postcode":"9051",
    "sg:province":"Oost-Vlaanderen",
    "wof:name":"Mercurius Investment",
    "wof:placetype":"venue"
},
  "geometry": {"coordinates":[3.6993830204,51.0248222351],"type":"Point"}
}