{
  "type": "Feature",
  "properties": {
    "iso:country":"BE",
    "sg:address":"Heusdensteenweg 19",
    "sg:city":"Wetteren",
    "sg:orig_category":"Plomberie, chauffage and installations sanitaires",
    "sg:phone":"+32 9 252 58 63",
    "sg:postcode":"9230",
    "sg:province":"Oost-Vlaanderen",
    "wof:name":"Dirk Goderis",
    "wof:placetype":"venue"
},
  "geometry": {"coordinates":[3.8343141079,51.0103263855],"type":"Point"}
}