{
  "type": "Feature",
  "properties": {
    "addr:full":"Luzernestraat 43 Schaarbeek/schaerbeek Bruxelles-Capitale 1030",
    "addr:housenumber":"43",
    "addr:postcode":"1030",
    "addr:street":"Luzernestraat",
    "iso:country":"BE",
    "sg:address":"Luzernestraat 43",
    "sg:city":"Schaarbeek/schaerbeek",
    "sg:orig_category":"Artsen and specialisten",
    "sg:phone":"+32 2 732 51 99",
    "sg:postcode":"1030",
    "sg:province":"Bruxelles-Capitale",
    "wof:name":"Emmanuel Eeckhout",
    "wof:placetype":"venue"
},
  "geometry": {"coordinates":[4.3929839134,50.8550338745],"type":"Point"}
}