{
  "type": "Feature",
  "properties": {
    "addr:full":"Dreef Ter Panne 2 Brugge West-Vlaanderen 8000",
    "addr:housenumber":"2",
    "addr:postcode":"8000",
    "addr:street":"Dreef Ter Panne",
    "iso:country":"BE",
    "sg:address":"Dreef Ter Panne 2",
    "sg:city":"Brugge",
    "sg:classifiers":[
        {
            "category":"Education",
            "subcategory":"Special Training",
            "type":"Public Place"
        }
    ],
    "sg:phone":"+32 50 47 15 50",
    "sg:postcode":"8000",
    "sg:province":"West-Vlaanderen",
    "sg:tags":[
        "professional"
    ],
    "wof:name":"Technologisch Centrum Bouw",
    "wof:placetype":"venue"
},
  "geometry": {"coordinates":[3.2280209064,51.2312088013],"type":"Point"}
}