{
  "type": "Feature",
  "properties": {
    "iso:country":"BE",
    "sg:address":"Rue Du Stocquy 95",
    "sg:city":"Courcelles",
    "sg:orig_category":"Plomberie, chauffage and installations sanitaires",
    "sg:phone":"+32 71 45 73 08",
    "sg:postcode":"6180",
    "sg:province":"Hainaut",
    "wof:name":"Philippe Vercruysse",
    "wof:placetype":"venue"
},
  "geometry": {"coordinates":[4.3480229378,50.4347305298],"type":"Point"}
}