{
  "type": "Feature",
  "properties": {
    "addr:full":"Rue Elie Puissant 1-3 Namur (vedrin - Daussoulx) Namur 5020",
    "addr:housenumber":"1-3",
    "addr:postcode":"5020",
    "addr:street":"Rue Elie Puissant",
    "iso:country":"BE",
    "sg:address":"Rue Elie Puissant 1-3",
    "sg:city":"Namur (vedrin - Daussoulx)",
    "sg:classifiers":[
        {
            "category":"Structure",
            "subcategory":"Office Building",
            "type":"Public Place"
        }
    ],
    "sg:phone":"+32 81 21 51 26",
    "sg:postcode":"5020",
    "sg:province":"Namur",
    "sg:tags":[
        "roofing",
        "slate"
    ],
    "wof:name":"Rolain M",
    "wof:placetype":"venue"
},
  "geometry": {"coordinates":[4.7952418327,50.4352035522],"type":"Point"}
}