{
  "type": "Feature",
  "properties": {
    "iso:country":"BE",
    "sg:address":"Gouden Kruispunt 4b69",
    "sg:city":"Tielt-winge",
    "sg:orig_category":"Baby- and kinderkleding Dameskledingzaken Herenkledingzaken",
    "sg:phone":"+32 16 63 20 84",
    "sg:postcode":"3390",
    "sg:province":"Vlaams-Brabant",
    "wof:name":"Modemakers",
    "wof:placetype":"venue"
},
  "geometry": {"coordinates":[4.8722681999,50.9039268494],"type":"Point"}
}