{
  "type": "Feature",
  "properties": {
    "addr:full":"Deinzestraat 15 Oudenaarde Oost-Vlaanderen 9700",
    "addr:housenumber":"15",
    "addr:postcode":"9700",
    "addr:street":"Deinzestraat",
    "iso:country":"BE",
    "sg:address":"Deinzestraat 15",
    "sg:city":"Oudenaarde",
    "sg:classifiers":[
        {
            "category":"Bars & Pubs",
            "type":"Food & Drink"
        }
    ],
    "sg:phone":"+32 55 31 84 42",
    "sg:postcode":"9700",
    "sg:province":"Oost-Vlaanderen",
    "wof:name":"The Irish Pipes",
    "wof:placetype":"venue"
},
  "geometry": {"coordinates":[3.5951309204,50.8521652222],"type":"Point"}
}