{
  "type": "Feature",
  "properties": {
    "addr:full":"Rue Du Merlo 6a Box 31 Bruxelles (uccle) Bruxelles-Capitale 1180",
    "addr:housenumber":"6a box 31",
    "addr:postcode":"1180",
    "addr:street":"Rue Du Merlo",
    "iso:country":"BE",
    "sg:address":"Rue Du Merlo 6a Box 31",
    "sg:city":"Bruxelles (uccle)",
    "sg:classifiers":[
        {
            "category":"Building & Trades",
            "subcategory":"Plumbing",
            "type":"Services"
        }
    ],
    "sg:phone":"+32 2 331 54 51",
    "sg:postcode":"1180",
    "sg:province":"Bruxelles-Capitale",
    "sg:tags":[
        "contractor"
    ],
    "wof:name":"Gaspart P",
    "wof:placetype":"venue"
},
  "geometry": {"coordinates":[4.3200850487,50.7987442017],"type":"Point"}
}