{
  "type": "Feature",
  "properties": {
    "addr:full":"Parklaan 57b1 Zaventem Vlaams-Brabant 1930",
    "addr:housenumber":"57b1",
    "addr:postcode":"1930",
    "addr:street":"Parklaan",
    "iso:country":"BE",
    "sg:address":"Parklaan 57b1",
    "sg:city":"Zaventem",
    "sg:orig_category":"Agences d\u00b4interim and personnel temporaire",
    "sg:phone":"+32 2 712 49 90",
    "sg:postcode":"1930",
    "sg:province":"Vlaams-Brabant",
    "wof:name":"Adecco",
    "wof:placetype":"venue"
},
  "geometry": {"coordinates":[4.4743361473,50.8859405518],"type":"Point"}
}