{
  "type": "Feature",
  "properties": {
    "addr:full":"Place De Lille 5 Tournai Hainaut 7500",
    "addr:housenumber":"5",
    "addr:postcode":"7500",
    "addr:street":"Place De Lille",
    "iso:country":"BE",
    "sg:address":"Place De Lille 5",
    "sg:city":"Tournai",
    "sg:classifiers":[
        {
            "category":"Cafe",
            "type":"Food & Drink"
        }
    ],
    "sg:phone":"+32 69 22 00 35",
    "sg:postcode":"7500",
    "sg:province":"Hainaut",
    "sg:tags":[
        "caf\u00e9s"
    ],
    "wof:name":"Caf\u00c9 A La R\u00c9cr\u00c9",
    "wof:placetype":"venue"
},
  "geometry": {"coordinates":[3.3815600872,50.6067848206],"type":"Point"}
}