{
  "type": "Feature",
  "properties": {
    "addr:full":"Rue Cardinal Cardijn 2b10 Oupeye Li\u00e8ge 4680",
    "addr:housenumber":"2b10",
    "addr:postcode":"4680",
    "addr:street":"Rue Cardinal Cardijn",
    "iso:country":"BE",
    "sg:address":"Rue Cardinal Cardijn 2b10",
    "sg:city":"Oupeye",
    "sg:orig_category":"Sportclubs",
    "sg:phone":"+32 4 240 22 13",
    "sg:postcode":"4680",
    "sg:province":"Li\u00e8ge",
    "wof:name":"V.c. Athen\u00c9e Herstal Ii",
    "wof:placetype":"venue"
},
  "geometry": {"coordinates":[5.6500711441,50.7032203674],"type":"Point"}
}