{
  "type": "Feature",
  "properties": {
    "iso:country":"BE",
    "sg:address":"Rue Du Couvent 82bb",
    "sg:city":"Moeskroen/mouscron",
    "sg:orig_category":"Enseignement sup\u00e9rieur",
    "sg:phone":"+32 56 33 29 00",
    "sg:postcode":"7700",
    "sg:province":"Hainaut",
    "wof:name":"I.t.e.h.o.",
    "wof:placetype":"venue"
},
  "geometry": {"coordinates":[3.2323200703,50.7400932312],"type":"Point"}
}