{
  "type": "Feature",
  "properties": {
    "addr:full":"Edingsesteenweg 211 Gooik Vlaams-Brabant 1755",
    "addr:housenumber":"211",
    "addr:postcode":"1755",
    "addr:street":"Edingsesteenweg",
    "iso:country":"BE",
    "sg:address":"Edingsesteenweg 211",
    "sg:city":"Gooik",
    "sg:orig_category":"Epiceries",
    "sg:phone":"+32 2 532 29 47",
    "sg:postcode":"1755",
    "sg:province":"Vlaams-Brabant",
    "wof:name":"Eduard De Bast",
    "wof:placetype":"venue"
},
  "geometry": {"coordinates":[4.1230998039,50.7871284485],"type":"Point"}
}