{
  "type": "Feature",
  "properties": {
    "iso:country":"BE",
    "sg:address":"Cit\u00e9 Ponsay 35",
    "sg:city":"Ouffet (warz\u00e9e)",
    "sg:classifiers":[
        {
            "category":"Professional",
            "subcategory":"Accounting & Tax Preparation",
            "type":"Services"
        }
    ],
    "sg:phone":"+32 86 36 62 60",
    "sg:postcode":"4590",
    "sg:province":"Li\u00e8ge",
    "sg:tags":[
        "bookkeeper"
    ],
    "wof:name":"Pahaut M-t",
    "wof:placetype":"venue"
},
  "geometry": {"coordinates":[5.4314808846,50.4552726746],"type":"Point"}
}