{
  "type": "Feature",
  "properties": {
    "iso:country":"BE",
    "sg:address":"Robert Verbelenstraat 17",
    "sg:city":"Puurs",
    "sg:classifiers":[
        {
            "category":"Insurance",
            "subcategory":"Insurance Agent",
            "type":"Services"
        }
    ],
    "sg:phone":"+32 3 889 22 00",
    "sg:postcode":"2870",
    "sg:province":"Antwerpen",
    "sg:tags":[
        "broker"
    ],
    "wof:name":"De Jonghe M Zakenkantoor Bvba",
    "wof:placetype":"venue"
},
  "geometry": {"coordinates":[4.2763910294,51.0775146484],"type":"Point"}
}