{
  "type": "Feature",
  "properties": {
    "iso:country":"BE",
    "sg:address":"Europark 25",
    "sg:city":"Lanaken",
    "sg:orig_category":"Dameskledingzaken",
    "sg:phone":"+32 89 71 65 50",
    "sg:postcode":"3620",
    "sg:province":"Limburg",
    "wof:name":"Huis Saventino",
    "wof:placetype":"venue"
},
  "geometry": {"coordinates":[5.664334774,50.8832054138],"type":"Point"}
}