{
  "type": "Feature",
  "properties": {
    "addr:full":"Weg Naar As 222 Genk Limburg 3600",
    "addr:housenumber":"222",
    "addr:postcode":"3600",
    "addr:street":"Weg Naar As",
    "iso:country":"BE",
    "sg:address":"Weg Naar As 222",
    "sg:city":"Genk",
    "sg:classifiers":[
        {
            "category":"Fast Food",
            "type":"Food & Drink"
        }
    ],
    "sg:phone":"+32 89 30 57 35",
    "sg:postcode":"3600",
    "sg:province":"Limburg",
    "sg:tags":[
        "\u00c0",
        "restaurants",
        "emporter",
        "restaurant"
    ],
    "wof:name":"Peach Pit",
    "wof:placetype":"venue"
},
  "geometry": {"coordinates":[5.5230908394,50.9760017395],"type":"Point"}
}