{
  "type": "Feature",
  "properties": {
    "addr:full":"Korenbloemstraat 50 Torhout West-Vlaanderen 8820",
    "addr:housenumber":"50",
    "addr:postcode":"8820",
    "addr:street":"Korenbloemstraat",
    "iso:country":"BE",
    "sg:address":"Korenbloemstraat 50",
    "sg:city":"Torhout",
    "sg:orig_category":"Plantes and fleurs Gr",
    "sg:phone":"+32 50 22 16 89",
    "sg:postcode":"8820",
    "sg:province":"West-Vlaanderen",
    "wof:name":"Janssens",
    "wof:placetype":"venue"
},
  "geometry": {"coordinates":[3.1342298985,51.0813140869],"type":"Point"}
}