{
  "type": "Feature",
  "properties": {
    "addr:full":"Moerstraat 66 Wetteren Oost-Vlaanderen 9230",
    "addr:housenumber":"66",
    "addr:postcode":"9230",
    "addr:street":"Moerstraat",
    "iso:country":"BE",
    "sg:address":"Moerstraat 66",
    "sg:city":"Wetteren",
    "sg:orig_category":"Plaatsen van vloer- and muurbekleding Schilders",
    "sg:phone":"+32 9 368 00 78",
    "sg:postcode":"9230",
    "sg:province":"Oost-Vlaanderen",
    "wof:name":"Firmin De Rocker",
    "wof:placetype":"venue"
},
  "geometry": {"coordinates":[3.8808701038,51.0058517456],"type":"Point"}
}