{
  "type": "Feature",
  "properties": {
    "iso:country":"BE",
    "sg:address":"Schipperstraat",
    "sg:city":"Oostende",
    "sg:orig_category":"Loodgieterij, verwarming and sanitaire installaties",
    "sg:phone":"+32 475 34 18 09",
    "sg:postcode":"8400",
    "sg:province":"West-Vlaanderen",
    "wof:name":"Arnold",
    "wof:placetype":"venue"
},
  "geometry": {"coordinates":[2.9204950333,51.2333183289],"type":"Point"}
}