{
  "type": "Feature",
  "properties": {
    "iso:country":"BE",
    "sg:address":"Berkenboslaan 4",
    "sg:city":"Tremelo",
    "sg:orig_category":"Artsen and specialisten",
    "sg:phone":"+32 16 53 46 75",
    "sg:postcode":"3120",
    "sg:province":"Vlaams-Brabant",
    "wof:name":"Marc Eraly",
    "wof:placetype":"venue"
},
  "geometry": {"coordinates":[4.7057728767,50.9930152893],"type":"Point"}
}