{
  "type": "Feature",
  "properties": {
    "iso:country":"BE",
    "sg:address":"Rue De La Ferme Brichant 47",
    "sg:city":"La Louvi\u00e8re (houdeng-aimeries)",
    "sg:classifiers":[
        {
            "category":"Utilities",
            "subcategory":"Natural Gas",
            "type":"Services"
        }
    ],
    "sg:phone":"+32 64 21 62 56",
    "sg:postcode":"7110",
    "sg:province":"Hainaut",
    "sg:tags":[
        "welding"
    ],
    "wof:name":"Cornero O",
    "wof:placetype":"venue"
},
  "geometry": {"coordinates":[4.1505050659,50.4826698303],"type":"Point"}
}