{
  "type": "Feature",
  "properties": {
    "addr:full":"Berlaarsestraat 7 Lier Antwerpen 2500",
    "addr:housenumber":"7",
    "addr:postcode":"2500",
    "addr:street":"Berlaarsestraat",
    "iso:country":"BE",
    "sg:address":"Berlaarsestraat 7",
    "sg:city":"Lier",
    "sg:orig_category":"Dameskledingzaken Kleding",
    "sg:phone":"+32 3 489 34 60",
    "sg:postcode":"2500",
    "sg:province":"Antwerpen",
    "wof:name":"Pas Du Tout",
    "wof:placetype":"venue"
},
  "geometry": {"coordinates":[4.5757260323,51.1301040649],"type":"Point"}
}