{
  "type": "Feature",
  "properties": {
    "addr:full":"Grote-edestraat 66 Blankenberge West-Vlaanderen 8370",
    "addr:housenumber":"66",
    "addr:postcode":"8370",
    "addr:street":"Grote-Edestraat",
    "iso:country":"BE",
    "sg:address":"Grote-edestraat 66",
    "sg:city":"Blankenberge",
    "sg:orig_category":"Supermarch\u00e9s",
    "sg:postcode":"8370",
    "sg:province":"West-Vlaanderen",
    "wof:name":"Aldi",
    "wof:placetype":"venue"
},
  "geometry": {"coordinates":[3.1168060303,51.3077087402],"type":"Point"}
}