{
  "type": "Feature",
  "properties": {
    "addr:full":"Lauweplaats 12 Menen (lauwe) West-Vlaanderen 8930",
    "addr:housenumber":"12",
    "addr:postcode":"8930",
    "addr:street":"Lauweplaats",
    "iso:country":"BE",
    "sg:address":"Lauweplaats 12",
    "sg:city":"Menen (lauwe)",
    "sg:classifiers":[
        {
            "category":"Bakery",
            "type":"Food & Drink"
        }
    ],
    "sg:phone":"+32 56 41 24 02",
    "sg:postcode":"8930",
    "sg:province":"West-Vlaanderen",
    "sg:tags":[
        "confectioner",
        "baker"
    ],
    "wof:name":"Spyckerelle G",
    "wof:placetype":"venue"
},
  "geometry": {"coordinates":[3.1636259556,50.7847633362],"type":"Point"}
}