{
  "type": "Feature",
  "properties": {
    "addr:full":"Halensebaan 68a Diest Vlaams-Brabant 3290",
    "addr:housenumber":"68a",
    "addr:postcode":"3290",
    "addr:street":"Halensebaan",
    "iso:country":"BE",
    "sg:address":"Halensebaan 68a",
    "sg:city":"Diest",
    "sg:classifiers":[
        {
            "category":"Real Estate",
            "subcategory":"Real Estate Services",
            "type":"Services"
        }
    ],
    "sg:phone":"+32 13 31 14 00",
    "sg:postcode":"3290",
    "sg:province":"Vlaams-Brabant",
    "wof:name":"De Piramide",
    "wof:placetype":"venue"
},
  "geometry": {"coordinates":[5.0706958771,50.9723815918],"type":"Point"}
}