{
  "type": "Feature",
  "properties": {
    "addr:full":"Zoning Industriel Bastogne Luxembourg 6600",
    "addr:postcode":"6600",
    "addr:street":"Zoning Industriel",
    "iso:country":"BE",
    "sg:address":"Zoning Industriel",
    "sg:city":"Bastogne",
    "sg:classifiers":[
        {
            "category":"Building & Trades",
            "subcategory":"Landscaping Services",
            "type":"Services"
        }
    ],
    "sg:phone":"+32 61 21 33 02",
    "sg:postcode":"6600",
    "sg:province":"Luxembourg",
    "sg:tags":[
        "forestry"
    ],
    "wof:name":"Exploitations Foresti\u00e8res",
    "wof:placetype":"venue"
},
  "geometry": {"coordinates":[5.7038679123,49.9902877808],"type":"Point"}
}