{
  "type": "Feature",
  "properties": {
    "iso:country":"BE",
    "sg:address":"Matersplein 4",
    "sg:city":"Oudenaarde (mater)",
    "sg:classifiers":[
        {
            "category":"Bars & Pubs",
            "type":"Food & Drink"
        }
    ],
    "sg:phone":"+32 55 23 93 94",
    "sg:postcode":"9700",
    "sg:province":"Oost-Vlaanderen",
    "sg:tags":[
        "tavern"
    ],
    "wof:name":"De Witte Hoeve",
    "wof:placetype":"venue"
},
  "geometry": {"coordinates":[3.6637530327,50.8425979614],"type":"Point"}
}