{
  "type": "Feature",
  "properties": {
    "addr:full":"Rekestraat 106 Geraardsbergen Oost-Vlaanderen 9500",
    "addr:housenumber":"106",
    "addr:postcode":"9500",
    "addr:street":"Rekestraat",
    "iso:country":"BE",
    "sg:address":"Rekestraat 106",
    "sg:city":"Geraardsbergen",
    "sg:orig_category":"Brood, gebak and snoepgoed",
    "sg:phone":"+32 55 42 71 68",
    "sg:postcode":"9500",
    "sg:province":"Oost-Vlaanderen",
    "wof:name":"Somers-van Der Heyden",
    "wof:placetype":"venue"
},
  "geometry": {"coordinates":[3.8843801022,50.7716445923],"type":"Point"}
}