{
  "type": "Feature",
  "properties": {
    "iso:country":"BE",
    "sg:address":"Krommendijk 10",
    "sg:city":"Poppel",
    "sg:orig_category":"Huisdieren and benodigdheden Royal Canin",
    "sg:phone":"+32 14 65 50 39",
    "sg:postcode":"2382",
    "sg:province":"Antwerpen",
    "wof:name":"Cooremans Georges",
    "wof:placetype":"venue"
},
  "geometry": {"coordinates":[5.0430431366,51.446472168],"type":"Point"}
}