{
  "type": "Feature",
  "properties": {
    "iso:country":"BE",
    "sg:address":"Kerkstraat 24",
    "sg:city":"Kapelle-op-den-bos",
    "sg:orig_category":"Caf\u00e9s Zalen voor culturele evenementen",
    "sg:phone":"+32 15 71 02 53",
    "sg:postcode":"1880",
    "sg:province":"Vlaams-Brabant",
    "wof:name":"De Oude Pastorie",
    "wof:placetype":"venue"
},
  "geometry": {"coordinates":[4.3504338264,50.9792289734],"type":"Point"}
}