{
  "type": "Feature",
  "properties": {
    "addr:full":"Viide-olympiadelaan 62 Antwerpen Antwerpen 2020",
    "addr:housenumber":"62",
    "addr:postcode":"2020",
    "addr:street":"Viide-Olympiadelaan",
    "iso:country":"BE",
    "sg:address":"Viide-olympiadelaan 62",
    "sg:city":"Antwerpen",
    "sg:classifiers":[
        {
            "category":"Restaurant",
            "type":"Food & Drink"
        }
    ],
    "sg:phone":"+32 3 238 55 69",
    "sg:postcode":"2020",
    "sg:province":"Antwerpen",
    "wof:name":"Borsalino",
    "wof:placetype":"venue"
},
  "geometry": {"coordinates":[4.3862638474,51.183681488],"type":"Point"}
}