{
  "type": "Feature",
  "properties": {
    "addr:full":"Lochtemanweg 88 Heusden-zolder Limburg 3550",
    "addr:housenumber":"88",
    "addr:postcode":"3550",
    "addr:street":"Lochtemanweg",
    "iso:country":"BE",
    "sg:address":"Lochtemanweg 88",
    "sg:city":"Heusden-zolder",
    "sg:classifiers":[
        {
            "category":"Banks & Credit Unions",
            "subcategory":"Atm",
            "type":"Services"
        }
    ],
    "sg:phone":"+32 11 45 81 81",
    "sg:postcode":"3550",
    "sg:province":"Limburg",
    "sg:tags":[
        "d'entreprises",
        "de",
        "bureau"
    ],
    "wof:name":"Home Assistance",
    "wof:placetype":"venue"
},
  "geometry": {"coordinates":[5.2294440269,51.0301475525],"type":"Point"}
}