{
  "type": "Feature",
  "properties": {
    "iso:country":"BE",
    "sg:address":"Blookstraat 4",
    "sg:city":"Zonhoven",
    "sg:orig_category":"Woningbouw",
    "sg:phone":"+32 11 81 29 38",
    "sg:postcode":"3520",
    "sg:province":"Limburg",
    "wof:name":"Jozef Gorissen",
    "wof:placetype":"venue"
},
  "geometry": {"coordinates":[5.3593258858,51.0064620972],"type":"Point"}
}