{
  "type": "Feature",
  "properties": {
    "iso:country":"BE",
    "sg:address":"Rue Th\u00c9odore Verhaegen 19",
    "sg:city":"Sint-gillis/saint-gilles",
    "sg:orig_category":"Textiles. Linge de maison Fab. Meubles D\u00e9taillants, Am\u00e9nagement de B\u00e2timents et de Cuisines",
    "sg:phone":"+32 2 537 19 89",
    "sg:postcode":"1060",
    "sg:province":"Bruxelles-Capitale",
    "wof:name":"Au Lit D'or",
    "wof:placetype":"venue"
},
  "geometry": {"coordinates":[4.3436570168,50.827495575],"type":"Point"}
}