{
  "type": "Feature",
  "properties": {
    "addr:full":"Dorpsbeekstraat 14 Antwerpen Antwerpen 2040",
    "addr:housenumber":"14",
    "addr:postcode":"2040",
    "addr:street":"Dorpsbeekstraat",
    "iso:country":"BE",
    "sg:address":"Dorpsbeekstraat 14",
    "sg:city":"Antwerpen",
    "sg:orig_category":"Pain, p\u00e2tisseries and confiseries",
    "sg:phone":"+32 3 568 61 40",
    "sg:postcode":"2040",
    "sg:province":"Antwerpen",
    "wof:name":"Elvira Bogaerts",
    "wof:placetype":"venue"
},
  "geometry": {"coordinates":[4.3141150475,51.3429756165],"type":"Point"}
}