{
  "type": "Feature",
  "properties": {
    "iso:country":"BE",
    "sg:address":"Hertendreef 41",
    "sg:city":"Schoten",
    "sg:orig_category":"Produits interm\u00e9diaires Gr",
    "sg:phone":"+32 3 653 13 13",
    "sg:postcode":"2900",
    "sg:province":"Antwerpen",
    "wof:name":"Asa Diam",
    "wof:placetype":"venue"
},
  "geometry": {"coordinates":[4.4950771332,51.2744407654],"type":"Point"}
}