{
  "type": "Feature",
  "properties": {
    "addr:full":"Rue De Malm\u00c9dy 10 Waimes/waimes Li\u00e8ge 4950",
    "addr:housenumber":"10",
    "addr:postcode":"4950",
    "addr:street":"Rue De Malme\u0301Dy",
    "iso:country":"BE",
    "sg:address":"Rue De Malm\u00c9dy 10",
    "sg:city":"Waimes/waimes",
    "sg:orig_category":"Postkantoren Verzekeringsmakelaars and experts",
    "sg:phone":"+32 80 67 90 15",
    "sg:postcode":"4950",
    "sg:province":"Li\u00e8ge",
    "wof:name":"De Post",
    "wof:placetype":"venue"
},
  "geometry": {"coordinates":[6.1406908035,50.4036178589],"type":"Point"}
}