{
  "type": "Feature",
  "properties": {
    "iso:country":"BE",
    "sg:address":"Graaf Van Egmontstraat 26",
    "sg:city":"Antwerpen",
    "sg:classifiers":[
        {
            "category":"Communications",
            "subcategory":"Film & Video Production",
            "type":"Services"
        }
    ],
    "sg:phone":"+32 3 289 55 81",
    "sg:postcode":"2000",
    "sg:province":"Antwerpen",
    "sg:tags":[
        "realisation",
        "-"
    ],
    "wof:name":"Peacock Visual Communication",
    "wof:placetype":"venue"
},
  "geometry": {"coordinates":[4.3939270973,51.2110977173],"type":"Point"}
}