{
  "type": "Feature",
  "properties": {
    "iso:country":"BE",
    "sg:address":"Zuidstraat 22",
    "sg:city":"Ichtegem",
    "sg:classifiers":[
        {
            "category":"Food & Beverages",
            "subcategory":"Chocolate",
            "type":"Retail Goods"
        }
    ],
    "sg:phone":"+32 51 58 15 71",
    "sg:postcode":"8480",
    "sg:province":"West-Vlaanderen",
    "sg:tags":[
        "confectionery",
        "-"
    ],
    "wof:name":"Dehaeze L",
    "wof:placetype":"venue"
},
  "geometry": {"coordinates":[3.032761097,51.102519989],"type":"Point"}
}