{
  "type": "Feature",
  "properties": {
    "addr:full":"Heldenlaan 58 Zottegem Oost-Vlaanderen 9620",
    "addr:housenumber":"58",
    "addr:postcode":"9620",
    "addr:street":"Heldenlaan",
    "iso:country":"BE",
    "sg:address":"Heldenlaan 58",
    "sg:city":"Zottegem",
    "sg:classifiers":[
        {
            "category":"Insurance",
            "subcategory":"Insurance Agent",
            "type":"Services"
        }
    ],
    "sg:phone":"+32 9 361 08 30",
    "sg:postcode":"9620",
    "sg:province":"Oost-Vlaanderen",
    "sg:tags":[
        "broker"
    ],
    "wof:name":"Janssens P Bvba",
    "wof:placetype":"venue"
},
  "geometry": {"coordinates":[3.80945611,50.8715629578],"type":"Point"}
}