{
  "type": "Feature",
  "properties": {
    "addr:full":"Clos Des Pommiers 17 Box 1 La Hulpe Brabant Wallon 1310",
    "addr:housenumber":"17;1",
    "addr:postcode":"1310",
    "addr:street":"Clos Des Pommiers;Box",
    "iso:country":"BE",
    "sg:address":"Clos Des Pommiers 17 Box 1",
    "sg:city":"La Hulpe",
    "sg:classifiers":[
        {
            "category":"Real Estate",
            "subcategory":"Real Estate Services",
            "type":"Services"
        }
    ],
    "sg:phone":"+32 2 653 94 16",
    "sg:postcode":"1310",
    "sg:province":"Brabant Wallon",
    "wof:name":"Ab Real Estate Research Sprl",
    "wof:placetype":"venue"
},
  "geometry": {"coordinates":[4.4938669205,50.7481536865],"type":"Point"}
}