{
  "type": "Feature",
  "properties": {
    "iso:country":"BE",
    "sg:address":"Rue Du Chemin De Fer 20b",
    "sg:city":"Charleroi (gosselies)",
    "sg:classifiers":[
        {
            "category":"Insurance",
            "subcategory":"Insurance Agent",
            "type":"Services"
        }
    ],
    "sg:phone":"+32 71 35 05 95",
    "sg:postcode":"6041",
    "sg:province":"Hainaut",
    "sg:tags":[
        "broker"
    ],
    "wof:name":"Fally M",
    "wof:placetype":"venue"
},
  "geometry": {"coordinates":[4.4237208366,50.4222984314],"type":"Point"}
}