{
  "type": "Feature",
  "properties": {
    "iso:country":"BE",
    "sg:address":"Liersesteenweg 57",
    "sg:city":"Berlaar",
    "sg:orig_category":"Herstellingen and onderhoud van auto's",
    "sg:phone":"+32 3 482 34 81",
    "sg:postcode":"2590",
    "sg:province":"Antwerpen",
    "wof:name":"Carrosserie De Toekomst",
    "wof:placetype":"venue"
},
  "geometry": {"coordinates":[4.6453652382,51.1174964905],"type":"Point"}
}