{
  "type": "Feature",
  "properties": {
    "addr:full":"Oude Pastorijstraat 6 Gavere Oost-Vlaanderen 9890",
    "addr:housenumber":"6",
    "addr:postcode":"9890",
    "addr:street":"Oude Pastorijstraat",
    "iso:country":"BE",
    "sg:address":"Oude Pastorijstraat 6",
    "sg:city":"Gavere",
    "sg:classifiers":[
        {
            "category":"Arena",
            "subcategory":"Sports Club",
            "type":"Entertainment"
        }
    ],
    "sg:phone":"+32 9 384 50 79",
    "sg:postcode":"9890",
    "sg:province":"Oost-Vlaanderen",
    "sg:tags":[
        "de"
    ],
    "wof:name":"W.c. De Scheldevrienden",
    "wof:placetype":"venue"
},
  "geometry": {"coordinates":[3.6825349331,50.9490661621],"type":"Point"}
}