{
  "type": "Feature",
  "properties": {
    "addr:full":"Heiligstraat 116 Hemiksem Antwerpen 2620",
    "addr:housenumber":"116",
    "addr:postcode":"2620",
    "addr:street":"Heiligstraat",
    "iso:country":"BE",
    "sg:address":"Heiligstraat 116",
    "sg:city":"Hemiksem",
    "sg:orig_category":"Traitements param\u00e9dicaux",
    "sg:phone":"+32 3 887 63 42",
    "sg:postcode":"2620",
    "sg:province":"Antwerpen",
    "wof:name":"De Taeye",
    "wof:placetype":"venue"
},
  "geometry": {"coordinates":[4.3486680984,51.1486930847],"type":"Point"}
}