{
  "type": "Feature",
  "properties": {
    "addr:full":"Rue De L'etoile 97 Drogenbos Vlaams-Brabant 1620",
    "addr:housenumber":"97",
    "addr:postcode":"1620",
    "addr:street":"Rue De L'Etoile",
    "iso:country":"BE",
    "sg:address":"Rue De L'etoile 97",
    "sg:city":"Drogenbos",
    "sg:classifiers":[
        {
            "category":"Military Area",
            "subcategory":"Armory",
            "type":"Public Place"
        }
    ],
    "sg:phone":"+32 2 378 30 76",
    "sg:postcode":"1620",
    "sg:province":"Vlaams-Brabant",
    "sg:tags":[
        "blade",
        "industrial",
        "-",
        "knife"
    ],
    "wof:name":"Horstermans Ets",
    "wof:placetype":"venue"
},
  "geometry": {"coordinates":[4.3172268867,50.7902412415],"type":"Point"}
}