{
  "type": "Feature",
  "properties": {
    "addr:full":"Rankhove 4 Herne Vlaams-Brabant 1540",
    "addr:housenumber":"4",
    "addr:postcode":"1540",
    "addr:street":"Rankhove",
    "iso:country":"BE",
    "sg:address":"Rankhove 4",
    "sg:city":"Herne",
    "sg:orig_category":"Eleveurs de bovins",
    "sg:phone":"+32 2 396 24 45",
    "sg:postcode":"1540",
    "sg:province":"Vlaams-Brabant",
    "wof:name":"Marcel Beeckmans",
    "wof:placetype":"venue"
},
  "geometry": {"coordinates":[4.0417590141,50.7151870728],"type":"Point"}
}