{
  "type": "Feature",
  "properties": {
    "addr:full":"Elfnovemberstraat 20 Gent Oost-Vlaanderen 9030",
    "addr:housenumber":"20",
    "addr:postcode":"9030",
    "addr:street":"Elfnovemberstraat;Oost-Vlaanderen",
    "iso:country":"BE",
    "sg:address":"Elfnovemberstraat 20",
    "sg:city":"Gent",
    "sg:orig_category":"Artsen and specialisten",
    "sg:phone":"+32 9 227 19 00",
    "sg:postcode":"9030",
    "sg:province":"Oost-Vlaanderen",
    "wof:name":"R. Derave",
    "wof:placetype":"venue"
},
  "geometry": {"coordinates":[3.6745951176,51.072933197],"type":"Point"}
}