{
  "type": "Feature",
  "properties": {
    "iso:country":"BE",
    "sg:address":"Hogeweg 239",
    "sg:city":"Menen",
    "sg:orig_category":"Bois Gr. Installation de menuiserie en bois and plastique. Quincailleries. Mat\u00e9riaux de construction",
    "sg:phone":"+32 56 51 87 86",
    "sg:postcode":"8930",
    "sg:province":"West-Vlaanderen",
    "wof:name":"Vandecasteele",
    "wof:placetype":"venue"
},
  "geometry": {"coordinates":[3.0961658955,50.7961158752],"type":"Point"}
}