{
  "type": "Feature",
  "properties": {
    "addr:full":"6210 Les Bons Villers Hainaut 6210",
    "addr:postcode":"6210;6210",
    "iso:country":"BE",
    "sg:address":"6210",
    "sg:city":"Les Bons Villers",
    "sg:orig_category":"Pharmaciens",
    "sg:phone":"+32 900 10 500",
    "sg:postcode":"6210",
    "sg:province":"Hainaut",
    "wof:name":"Pharmacies De Garde",
    "wof:placetype":"venue"
},
  "geometry": {"coordinates":[4.4382400513,50.5345115662],"type":"Point"}
}