{
  "type": "Feature",
  "properties": {
    "addr:full":"Avenue De L'araucaria 86 Bruxelles Bruxelles-Capitale 1020",
    "addr:housenumber":"86",
    "addr:postcode":"1020",
    "addr:street":"Avenue De L'Araucaria",
    "iso:country":"BE",
    "sg:address":"Avenue De L'araucaria 86",
    "sg:city":"Bruxelles",
    "sg:classifiers":[
        {
            "category":"Professional",
            "subcategory":"Lawyer & Legal Services",
            "type":"Services"
        }
    ],
    "sg:phone":"+32 2 262 15 57",
    "sg:postcode":"1020",
    "sg:province":"Bruxelles-Capitale",
    "wof:name":"Letellier Vincent",
    "wof:placetype":"venue"
},
  "geometry": {"coordinates":[4.3624401093,50.8973808289],"type":"Point"}
}