{
  "type": "Feature",
  "properties": {
    "addr:full":"Wijper 21 Aarschot (rillaar) Vlaams-Brabant 3202",
    "addr:housenumber":"21",
    "addr:postcode":"3202",
    "addr:street":"Wijper",
    "iso:country":"BE",
    "sg:address":"Wijper 21",
    "sg:city":"Aarschot (rillaar)",
    "sg:classifiers":[
        {
            "category":"Health Services",
            "subcategory":"Health Practitioner",
            "type":"Services"
        }
    ],
    "sg:phone":"+32 16 50 31 96",
    "sg:postcode":"3202",
    "sg:province":"Vlaams-Brabant",
    "sg:tags":[
        "physiotherapist"
    ],
    "wof:name":"Vandalen Anne",
    "wof:placetype":"venue"
},
  "geometry": {"coordinates":[4.8777780533,50.977268219],"type":"Point"}
}