{
  "type": "Feature",
  "properties": {
    "iso:country":"BE",
    "sg:address":"Sint-niklaasstraat 83",
    "sg:city":"Sint-gillis-waas",
    "sg:orig_category":"Zuivelproducten",
    "sg:phone":"+32 3 707 16 01",
    "sg:postcode":"9170",
    "sg:province":"Oost-Vlaanderen",
    "wof:name":"Huis Steyaert",
    "wof:placetype":"venue"
},
  "geometry": {"coordinates":[4.137512207,51.2108612061],"type":"Point"}
}