{
  "type": "Feature",
  "properties": {
    "iso:country":"BE",
    "sg:address":"Karel Van Manderstraat 6",
    "sg:city":"Meulebeke",
    "sg:classifiers":[
        {
            "category":"Social Services",
            "subcategory":"Child Care",
            "type":"Services"
        }
    ],
    "sg:phone":"+32 51 48 56 42",
    "sg:postcode":"8760",
    "sg:province":"West-Vlaanderen",
    "sg:tags":[
        "baby",
        "nursery",
        "day",
        "sitting"
    ],
    "wof:name":"Snoopy",
    "wof:placetype":"venue"
},
  "geometry": {"coordinates":[3.2896668911,50.949672699],"type":"Point"}
}