{
  "type": "Feature",
  "properties": {
    "addr:full":"Dorpstraat 207 Zwijndrecht Antwerpen 2070",
    "addr:housenumber":"207",
    "addr:postcode":"2070",
    "addr:street":"Dorpstraat",
    "iso:country":"BE",
    "sg:address":"Dorpstraat 207",
    "sg:city":"Zwijndrecht",
    "sg:orig_category":"Bloemen and planten",
    "sg:phone":"+32 3 252 76 31",
    "sg:postcode":"2070",
    "sg:province":"Antwerpen",
    "wof:name":"Flora Vandenbosch",
    "wof:placetype":"venue"
},
  "geometry": {"coordinates":[4.3392910957,51.2020454407],"type":"Point"}
}