{
  "type": "Feature",
  "properties": {
    "iso:country":"BE",
    "sg:address":"Rue De Bosnie 63",
    "sg:city":"Sint-gillis/saint-gilles",
    "sg:orig_category":"Cr\u00e8ches and garderies d'enfants",
    "sg:phone":"+32 2 539 31 03",
    "sg:postcode":"1060",
    "sg:province":"Bruxelles-Capitale",
    "wof:name":"Cr\u00c8che Copain-copine",
    "wof:placetype":"venue"
},
  "geometry": {"coordinates":[4.3363637924,50.8279342651],"type":"Point"}
}