{
  "type": "Feature",
  "properties": {
    "iso:country":"BE",
    "sg:address":"Handelslei 189",
    "sg:city":"Zoersel",
    "sg:orig_category":"Reclamebureaus",
    "sg:phone":"+32 3 384 02 72",
    "sg:postcode":"2980",
    "sg:province":"Antwerpen",
    "wof:name":"Re-lance Advertising",
    "wof:placetype":"venue"
},
  "geometry": {"coordinates":[4.6465320587,51.2719955444],"type":"Point"}
}