{
  "type": "Feature",
  "properties": {
    "iso:country":"BE",
    "sg:address":"Rue Ovide Decroly 83",
    "sg:city":"Li\u00c8ge",
    "sg:orig_category":"Advocaten and juridische adviseurs",
    "sg:phone":"+32 4 367 27 82",
    "sg:postcode":"4031",
    "sg:province":"Li\u00e8ge",
    "wof:name":"Roland Viseur",
    "wof:placetype":"venue"
},
  "geometry": {"coordinates":[5.5943927765,50.6117553711],"type":"Point"}
}