{
  "type": "Feature",
  "properties": {
    "iso:country":"BE",
    "sg:address":"Rooi 13",
    "sg:city":"Bilzen",
    "sg:classifiers":[
        {
            "category":"Restaurant",
            "type":"Food & Drink"
        }
    ],
    "sg:phone":"+32 89 51 13 06",
    "sg:postcode":"3740",
    "sg:province":"Limburg",
    "sg:tags":[
        "caf\u00e9s"
    ],
    "wof:name":"Caf\u00c9 Brobos",
    "wof:placetype":"venue"
},
  "geometry": {"coordinates":[5.5045781136,50.8800582886],"type":"Point"}
}