{
  "type": "Feature",
  "properties": {
    "addr:full":"Bertogne 76 Bertogne Luxembourg 6687",
    "addr:housenumber":"76",
    "addr:postcode":"6687",
    "addr:street":"Bertogne",
    "iso:country":"BE",
    "sg:address":"Bertogne 76",
    "sg:city":"Bertogne",
    "sg:orig_category":"Herstellingen and onderhoud van auto's",
    "sg:phone":"+32 61 21 61 08",
    "sg:postcode":"6687",
    "sg:province":"Luxembourg",
    "wof:name":"Garage De La Wiltz",
    "wof:placetype":"venue"
},
  "geometry": {"coordinates":[5.6690077782,50.0839195251],"type":"Point"}
}