{
  "type": "Feature",
  "properties": {
    "iso:country":"BE",
    "sg:address":"Gistelse Steenweg 97",
    "sg:city":"Brugge (sint-andries)",
    "sg:classifiers":[
        {
            "category":"Shopping",
            "subcategory":"Clothing, Apparel, & Fashions",
            "type":"Retail Goods"
        }
    ],
    "sg:phone":"+32 50 39 26 41",
    "sg:postcode":"8200",
    "sg:province":"West-Vlaanderen",
    "sg:tags":[
        "clothing",
        "-",
        "gentleman"
    ],
    "wof:name":"Obsession",
    "wof:placetype":"venue"
},
  "geometry": {"coordinates":[3.2052400112,51.20287323],"type":"Point"}
}