{
  "type": "Feature",
  "properties": {
    "addr:full":"Rue Michel 2 Ohey Brabant Wallon 1360",
    "addr:housenumber":"2",
    "addr:postcode":"1360",
    "addr:street":"Rue Michel;Wallon",
    "iso:country":"BE",
    "sg:address":"Rue Michel 2",
    "sg:city":"Ohey",
    "sg:orig_category":"Entretien and r\u00e9parations de voitures",
    "sg:phone":"+32 81 65 56 25",
    "sg:postcode":"1360",
    "sg:province":"Brabant Wallon",
    "wof:name":"Deterville",
    "wof:placetype":"venue"
},
  "geometry": {"coordinates":[4.8146052361,50.6239395142],"type":"Point"}
}