{
  "type": "Feature",
  "properties": {
    "iso:country":"BE",
    "sg:address":"Rue Les Oies 60",
    "sg:city":"Chaudfontaine (beaufays)",
    "sg:classifiers":[
        {
            "category":"Health Services",
            "subcategory":"Doctor",
            "type":"Services"
        }
    ],
    "sg:phone":"+32 4 368 85 36",
    "sg:postcode":"4052",
    "sg:province":"Li\u00e8ge",
    "sg:tags":[
        "medicinephysicians",
        "surgeon"
    ],
    "wof:name":"Branas Cecilia",
    "wof:placetype":"venue"
},
  "geometry": {"coordinates":[5.620347023,50.5650634766],"type":"Point"}
}