{
  "type": "Feature",
  "properties": {
    "iso:country":"BE",
    "sg:address":"Jules Peurquaetstraat 33",
    "sg:city":"Oostende",
    "sg:classifiers":[
        {
            "category":"Personal",
            "subcategory":"Beauty Salon",
            "type":"Services"
        }
    ],
    "sg:phone":"+32 59 50 41 60",
    "sg:postcode":"8400",
    "sg:province":"West-Vlaanderen",
    "sg:tags":[
        "lady",
        "-",
        "hairdressing"
    ],
    "wof:name":"Marnix Systeme",
    "wof:placetype":"venue"
},
  "geometry": {"coordinates":[2.9111509323,51.225605011],"type":"Point"}
}