{
  "type": "Feature",
  "properties": {
    "addr:full":"Kattesasstraat 5 Nieuwpoort West-Vlaanderen 8620",
    "addr:housenumber":"5",
    "addr:postcode":"8620",
    "addr:street":"Kattesasstraat",
    "iso:country":"BE",
    "sg:address":"Kattesasstraat 5",
    "sg:city":"Nieuwpoort",
    "sg:classifiers":[
        {
            "category":"Utilities",
            "subcategory":"Natural Gas",
            "type":"Services"
        }
    ],
    "sg:phone":"+32 58 23 35 38",
    "sg:postcode":"8620",
    "sg:province":"West-Vlaanderen",
    "sg:tags":[
        "industrial",
        "-"
    ],
    "wof:name":"Lambrecht M",
    "wof:placetype":"venue"
},
  "geometry": {"coordinates":[2.7440500259,51.1346282959],"type":"Point"}
}