{
  "type": "Feature",
  "properties": {
    "addr:full":"Malcensestraat 82 Moeskroen/mouscron Hainaut 7700",
    "addr:housenumber":"82",
    "addr:postcode":"7700",
    "addr:street":"Malcensestraat",
    "iso:country":"BE",
    "sg:address":"Malcensestraat 82",
    "sg:city":"Moeskroen/mouscron",
    "sg:orig_category":"Rundveehouders Varkenskwekers",
    "sg:phone":"+32 56 33 16 24",
    "sg:postcode":"7700",
    "sg:province":"Hainaut",
    "wof:name":"Jean Danel",
    "wof:placetype":"venue"
},
  "geometry": {"coordinates":[3.2323200703,50.7400932312],"type":"Point"}
}