{
  "type": "Feature",
  "properties": {
    "iso:country":"BE",
    "sg:address":"Statiestraat 33",
    "sg:city":"Lint",
    "sg:orig_category":"Beautyfarms, relaxatie and lichamelijk welzijn Schoonheidssalons",
    "sg:phone":"+32 3 455 41 24",
    "sg:postcode":"2547",
    "sg:province":"Antwerpen",
    "wof:name":"Instituut Machteld",
    "wof:placetype":"venue"
},
  "geometry": {"coordinates":[4.4968538284,51.1283187866],"type":"Point"}
}