{
  "type": "Feature",
  "properties": {
    "addr:full":"Avenue Rogier 45 Bruxelles (schaerbeek) Bruxelles-Capitale 1030",
    "addr:housenumber":"45",
    "addr:postcode":"1030",
    "addr:street":"Avenue Rogier",
    "iso:country":"BE",
    "sg:address":"Avenue Rogier 45",
    "sg:city":"Bruxelles (schaerbeek)",
    "sg:classifiers":[
        {
            "category":"Organizations",
            "subcategory":"Political Organization",
            "type":"Services"
        }
    ],
    "sg:phone":"+32 2 215 17 73",
    "sg:postcode":"1030",
    "sg:province":"Bruxelles-Capitale",
    "sg:tags":[
        "charitable",
        "organisation"
    ],
    "wof:name":"St-vincent De Paul (soci\u00e9t\u00e9 De)",
    "wof:placetype":"venue"
},
  "geometry": {"coordinates":[4.373688221,50.8601379395],"type":"Point"}
}