{
  "type": "Feature",
  "properties": {
    "addr:full":"Avenue Des Eperons D\u00b4or 5 Elsene/ixelles Bruxelles-Capitale 1050",
    "addr:housenumber":"5",
    "addr:postcode":"1050",
    "addr:street":"Avenue Des Eperons D\u00b4Or",
    "iso:country":"BE",
    "sg:address":"Avenue Des Eperons D\u00b4or 5",
    "sg:city":"Elsene/ixelles",
    "sg:orig_category":"M\u00e9decins and sp\u00e9cialistes",
    "sg:phone":"+32 2 296 26 77",
    "sg:postcode":"1050",
    "sg:province":"Bruxelles-Capitale",
    "wof:name":"V. Laeremans",
    "wof:placetype":"venue"
},
  "geometry": {"coordinates":[4.373029232,50.825138092],"type":"Point"}
}