{
  "type": "Feature",
  "properties": {
    "iso:country":"BE",
    "sg:address":"Rue Royale 20",
    "sg:city":"Brussels",
    "sg:classifiers":[
        {
            "category":"Industrial Area",
            "type":"Public Place"
        }
    ],
    "sg:phone":"+32 2 729 21 11",
    "sg:postcode":"1000",
    "sg:province":"Bruxelles-Capitale",
    "sg:tags":[
        "large",
        "private"
    ],
    "wof:name":"Gib Sa",
    "wof:placetype":"venue"
},
  "geometry": {"coordinates":[4.4034700394,50.8673934937],"type":"Point"}
}