{
  "type": "Feature",
  "properties": {
    "iso:country":"BE",
    "sg:address":"Champs Elys\u00c9es 4",
    "sg:city":"Ciney",
    "sg:orig_category":"Eleveurs de bovins",
    "sg:phone":"+32 83 23 06 12",
    "sg:postcode":"5590",
    "sg:province":"Namur",
    "wof:name":"Herd Book B.b.b.",
    "wof:placetype":"venue"
},
  "geometry": {"coordinates":[5.0996251106,50.3148384094],"type":"Point"}
}