{
  "type": "Feature",
  "properties": {
    "addr:full":"Quai Godefroid-kurth 12 Li\u00e8ge 1 (li\u00e8ge 2) Li\u00e8ge 4020",
    "addr:housenumber":"12;1;2",
    "addr:postcode":"4020",
    "addr:street":"Quai Godefroid-Kurth",
    "iso:country":"BE",
    "sg:address":"Quai Godefroid-kurth 12",
    "sg:city":"Li\u00e8ge 1 (li\u00e8ge 2)",
    "sg:classifiers":[
        {
            "category":"Professional",
            "subcategory":"Lawyer & Legal Services",
            "type":"Services"
        }
    ],
    "sg:phone":"+32 4 344 96 34",
    "sg:postcode":"4020",
    "sg:province":"Li\u00e8ge",
    "wof:name":"Pev\u00e9e Christine",
    "wof:placetype":"venue"
},
  "geometry": {"coordinates":[5.5876507759,50.6458511353],"type":"Point"}
}