{
  "type": "Feature",
  "properties": {
    "addr:full":"Keringstraat 37 Geraardsbergen Oost-Vlaanderen 9506",
    "addr:housenumber":"37",
    "addr:postcode":"9506",
    "addr:street":"Keringstraat",
    "iso:country":"BE",
    "sg:address":"Keringstraat 37",
    "sg:city":"Geraardsbergen",
    "sg:orig_category":"Pain, p\u00e2tisseries and confiseries",
    "sg:phone":"+32 54 33 43 05",
    "sg:postcode":"9506",
    "sg:province":"Oost-Vlaanderen",
    "wof:name":"Huis Carion",
    "wof:placetype":"venue"
},
  "geometry": {"coordinates":[3.9592730999,50.7908172607],"type":"Point"}
}