{
  "type": "Feature",
  "properties": {
    "addr:full":"Rotterdamstraat 86 Antwerpen Antwerpen 2060",
    "addr:housenumber":"86",
    "addr:postcode":"2060",
    "addr:street":"Rotterdamstraat",
    "iso:country":"BE",
    "sg:address":"Rotterdamstraat 86",
    "sg:city":"Antwerpen",
    "sg:classifiers":[
        {
            "category":"Bars & Pubs",
            "type":"Food & Drink"
        }
    ],
    "sg:phone":"+32 3 233 46 78",
    "sg:postcode":"2060",
    "sg:province":"Antwerpen",
    "wof:name":"Firenze",
    "wof:placetype":"venue"
},
  "geometry": {"coordinates":[4.4203648567,51.2220726013],"type":"Point"}
}