{
  "type": "Feature",
  "properties": {
    "addr:full":"E3 Laan 62 Deinze Vlaams-Brabant 1800",
    "addr:housenumber":"62",
    "addr:postcode":"1800",
    "addr:street":"Laan",
    "iso:country":"BE",
    "sg:address":"E3 Laan 62",
    "sg:city":"Deinze",
    "sg:classifiers":[
        {
            "category":"Professional",
            "type":"Services"
        }
    ],
    "sg:phone":"+32 9 381 51 00",
    "sg:postcode":"1800",
    "sg:province":"Vlaams-Brabant",
    "sg:tags":[
        "transport",
        "road"
    ],
    "wof:name":"G Snel Transport Belgium Nv",
    "wof:placetype":"venue"
},
  "geometry": {"coordinates":[4.4258608818,50.9269294739],"type":"Point"}
}