{
  "type": "Feature",
  "properties": {
    "iso:country":"BE",
    "sg:address":"Pastoriestraat 3",
    "sg:city":"Tremelo (baal)",
    "sg:classifiers":[
        {
            "category":"Food & Beverages",
            "subcategory":"Fruits & Vegetables",
            "type":"Retail Goods"
        }
    ],
    "sg:phone":"+32 16 53 77 98",
    "sg:postcode":"3128",
    "sg:province":"Vlaams-Brabant",
    "sg:tags":[
        "-"
    ],
    "wof:name":"Het Fruithof",
    "wof:placetype":"venue"
},
  "geometry": {"coordinates":[4.7525911331,50.9957542419],"type":"Point"}
}