{
  "type": "Feature",
  "properties": {
    "iso:country":"BE",
    "sg:address":"Avenue Reine Elisabeth 170b8",
    "sg:city":"Andenne",
    "sg:orig_category":"Kapsalons",
    "sg:phone":"+32 85 84 34 15",
    "sg:postcode":"5300",
    "sg:province":"Namur",
    "wof:name":"Coiffure D\u00c9fiance",
    "wof:placetype":"venue"
},
  "geometry": {"coordinates":[5.0858650208,50.4911727905],"type":"Point"}
}