{
  "type": "Feature",
  "properties": {
    "iso:country":"BE",
    "sg:address":"Clos Des Ram\u00e9es 4",
    "sg:city":"Mouscron",
    "sg:classifiers":[
        {
            "category":"Personal",
            "subcategory":"Beauty Salon",
            "type":"Services"
        }
    ],
    "sg:phone":"+32 56 34 29 81",
    "sg:postcode":"7700",
    "sg:province":"Hainaut",
    "wof:name":"Institut De Beaut\u00e9 Good Life",
    "wof:placetype":"venue"
},
  "geometry": {"coordinates":[3.2193899155,50.7500762939],"type":"Point"}
}