{
  "type": "Feature",
  "properties": {
    "addr:full":"Boulevard De La Plaine 2 Bruxelles (ixelles) Bruxelles-Capitale 1050",
    "addr:housenumber":"2",
    "addr:postcode":"1050",
    "addr:street":"Boulevard De La Plaine",
    "iso:country":"BE",
    "sg:address":"Boulevard De La Plaine 2",
    "sg:city":"Bruxelles (ixelles)",
    "sg:classifiers":[
        {
            "category":"Education",
            "subcategory":"Special Training",
            "type":"Public Place"
        }
    ],
    "sg:phone":"+32 2 629 39 08",
    "sg:postcode":"1050",
    "sg:province":"Bruxelles-Capitale",
    "sg:tags":[
        "school",
        "language"
    ],
    "wof:name":"Cvo Kamer Voor Handel & Nijverheid Van Brussel",
    "wof:placetype":"venue"
},
  "geometry": {"coordinates":[4.3929901123,50.8209838867],"type":"Point"}
}