{
  "type": "Feature",
  "properties": {
    "iso:country":"BE",
    "sg:address":"Nonnebossen 24a",
    "sg:city":"Zonnebeke",
    "sg:classifiers":[
        {
            "category":"Food & Beverages",
            "subcategory":"Fruits & Vegetables",
            "type":"Retail Goods"
        }
    ],
    "sg:phone":"+32 57 21 27 41",
    "sg:postcode":"8980",
    "sg:province":"West-Vlaanderen",
    "sg:tags":[
        "-"
    ],
    "wof:name":"De Fruithoeve",
    "wof:placetype":"venue"
},
  "geometry": {"coordinates":[2.9697949886,50.8543891907],"type":"Point"}
}