{
  "type": "Feature",
  "properties": {
    "iso:country":"BE",
    "sg:address":"Avenue Du Champ De Mai 10 Box 33",
    "sg:city":"Waterloo",
    "sg:classifiers":[
        {
            "category":"Banks & Credit Unions",
            "subcategory":"Investment Brokerage",
            "type":"Services"
        }
    ],
    "sg:phone":"+32 2 353 08 98",
    "sg:postcode":"1410",
    "sg:province":"Brabant Wallon",
    "wof:name":"Soci\u00e9t\u00e9 Internationale De Gestion De Portefeuille",
    "wof:placetype":"venue"
},
  "geometry": {"coordinates":[4.388920784,50.7133712769],"type":"Point"}
}