{
  "type": "Feature",
  "properties": {
    "addr:full":"Avenue Eug\u00e8ne Demolder 24 Bruxelles (schaerbeek) Bruxelles-Capitale 1030",
    "addr:housenumber":"24",
    "addr:postcode":"1030",
    "addr:street":"Avenue Euge\u0300Ne Demolder",
    "iso:country":"BE",
    "sg:address":"Avenue Eug\u00e8ne Demolder 24",
    "sg:city":"Bruxelles (schaerbeek)",
    "sg:classifiers":[
        {
            "category":"Professional",
            "subcategory":"Advertising",
            "type":"Services"
        }
    ],
    "sg:postcode":"1030",
    "sg:province":"Bruxelles-Capitale",
    "sg:tags":[
        "studio"
    ],
    "wof:name":"D.v.d.d.d.",
    "wof:placetype":"venue"
},
  "geometry": {"coordinates":[4.3774280548,50.8720092773],"type":"Point"}
}