{
  "type": "Feature",
  "properties": {
    "addr:full":"Rue Du G\u00c9ant 10 Nivelles Brabant Wallon 1400",
    "addr:housenumber":"10",
    "addr:postcode":"1400",
    "addr:street":"Rue Du Ge\u0301Ant",
    "iso:country":"BE",
    "sg:address":"Rue Du G\u00c9ant 10",
    "sg:city":"Nivelles",
    "sg:orig_category":"Tweedehandsgoederen",
    "sg:phone":"+32 67 21 83 00",
    "sg:postcode":"1400",
    "sg:province":"Brabant Wallon",
    "wof:name":"Le Second Look",
    "wof:placetype":"venue"
},
  "geometry": {"coordinates":[4.327188015,50.5985412598],"type":"Point"}
}