{
  "type": "Feature",
  "properties": {
    "addr:full":"Sint-bernadettestraat 2 Gent Oost-Vlaanderen 9040",
    "addr:housenumber":"2",
    "addr:postcode":"9040",
    "addr:street":"Sint-Bernadettestraat;Oost-Vlaanderen",
    "iso:country":"BE",
    "sg:address":"Sint-bernadettestraat 2",
    "sg:city":"Gent",
    "sg:orig_category":"Epiceries. Fruits and l\u00e9gumes Gr",
    "sg:phone":"+32 9 251 11 20",
    "sg:postcode":"9040",
    "sg:province":"Oost-Vlaanderen",
    "wof:name":"Fa. De Vreese",
    "wof:placetype":"venue"
},
  "geometry": {"coordinates":[3.7499549389,51.0682258606],"type":"Point"}
}