{
  "type": "Feature",
  "properties": {
    "iso:country":"BE",
    "sg:address":"Broekzijstraat 58",
    "sg:city":"Lille",
    "sg:orig_category":"Eleveurs de bovins",
    "sg:phone":"+32 14 88 16 14",
    "sg:postcode":"2275",
    "sg:province":"Antwerpen",
    "wof:name":"Willems Gaston & Frieda",
    "wof:placetype":"venue"
},
  "geometry": {"coordinates":[4.8051891327,51.2408866882],"type":"Point"}
}