{
  "type": "Feature",
  "properties": {
    "iso:country":"BE",
    "sg:address":"Boomsestraat 367",
    "sg:city":"Niel",
    "sg:orig_category":"Eclairage et \u00e9quipements du foyer. Rev\u00eatements pour sols and murs. Peinture",
    "sg:phone":"+32 3 844 64 51",
    "sg:postcode":"2845",
    "sg:province":"Antwerpen",
    "wof:name":"Andre Brits",
    "wof:placetype":"venue"
},
  "geometry": {"coordinates":[4.3470191956,51.1001434326],"type":"Point"}
}