{
  "type": "Feature",
  "properties": {
    "addr:full":"Brugsestraat 272 Zedelgem West-Vlaanderen 8210",
    "addr:housenumber":"272",
    "addr:postcode":"8210",
    "addr:street":"Brugsestraat",
    "iso:country":"BE",
    "sg:address":"Brugsestraat 272",
    "sg:city":"Zedelgem",
    "sg:classifiers":[
        {
            "category":"Personal",
            "subcategory":"Beauty Salon",
            "type":"Services"
        }
    ],
    "sg:phone":"+32 50 20 02 54",
    "sg:postcode":"8210",
    "sg:province":"West-Vlaanderen",
    "sg:tags":[
        "lady",
        "-",
        "hairdressing"
    ],
    "wof:name":"Hairline Monique",
    "wof:placetype":"venue"
},
  "geometry": {"coordinates":[3.1469299793,51.1284217834],"type":"Point"}
}