{
  "type": "Feature",
  "properties": {
    "iso:country":"BE",
    "sg:address":"Rue Jan-baptist De Keyzer 112a",
    "sg:city":"Wezembeek-oppem",
    "sg:classifiers":[
        {
            "category":"Professional",
            "subcategory":"Management & Consulting",
            "type":"Services"
        }
    ],
    "sg:phone":"+32 2 784 33 53",
    "sg:postcode":"1970",
    "sg:province":"Vlaams-Brabant",
    "sg:tags":[
        "consultant"
    ],
    "wof:name":"Financi\u00e8re De L'oranger Sa",
    "wof:placetype":"venue"
},
  "geometry": {"coordinates":[4.4882359505,50.8498573303],"type":"Point"}
}