{
  "type": "Feature",
  "properties": {
    "iso:country":"BE",
    "sg:address":"Rue Du Croiseau 22",
    "sg:city":"Ittre",
    "sg:classifiers":[
        {
            "category":"Professional",
            "subcategory":"Accounting & Tax Preparation",
            "type":"Services"
        }
    ],
    "sg:phone":"+32 2 366 40 77",
    "sg:postcode":"1460",
    "sg:province":"Brabant Wallon",
    "sg:tags":[
        "bookkeeper"
    ],
    "wof:name":"Olivier Ph",
    "wof:placetype":"venue"
},
  "geometry": {"coordinates":[4.2414498329,50.6385955811],"type":"Point"}
}