{
  "type": "Feature",
  "properties": {
    "iso:country":"BE",
    "sg:address":"Beho 26",
    "sg:city":"Gouvy (beho)",
    "sg:classifiers":[
        {
            "category":"Health Services",
            "subcategory":"Health Practitioner",
            "type":"Services"
        }
    ],
    "sg:phone":"+32 80 51 07 42",
    "sg:postcode":"6672",
    "sg:province":"Luxembourg",
    "sg:tags":[
        "physiotherapist"
    ],
    "wof:name":"Lengler G",
    "wof:placetype":"venue"
},
  "geometry": {"coordinates":[5.9958620071,50.219455719],"type":"Point"}
}