{
  "type": "Feature",
  "properties": {
    "addr:full":"Oost Poezelstraat 8 Ieper (zuidschote) West-Vlaanderen 8904",
    "addr:housenumber":"8",
    "addr:postcode":"8904",
    "addr:street":"Poezelstraat",
    "iso:country":"BE",
    "sg:address":"Oost Poezelstraat 8",
    "sg:city":"Ieper (zuidschote)",
    "sg:classifiers":[
        {
            "category":"Wholesale",
            "subcategory":"Fruits & Vegetables",
            "type":"Manufacturing & Wholesale Goods"
        }
    ],
    "sg:phone":"+32 51 54 47 84",
    "sg:postcode":"8904",
    "sg:province":"West-Vlaanderen",
    "sg:tags":[
        "whol",
        "-",
        "potato"
    ],
    "wof:name":"Heughebaert F",
    "wof:placetype":"venue"
},
  "geometry": {"coordinates":[2.8668119907,50.9048690796],"type":"Point"}
}