{
  "type": "Feature",
  "properties": {
    "addr:full":"Vosseschijnstraat 142kaai Antwerpen Antwerpen 2030",
    "addr:housenumber":"142kaai",
    "addr:postcode":"2030",
    "addr:street":"Vosseschijnstraat",
    "iso:country":"BE",
    "sg:address":"Vosseschijnstraat 142kaai",
    "sg:city":"Antwerpen",
    "sg:classifiers":[
        {
            "category":"Home & Garden",
            "subcategory":"Hardware",
            "type":"Retail Goods"
        }
    ],
    "sg:phone":"+32 3 542 69 69",
    "sg:postcode":"2030",
    "sg:province":"Antwerpen",
    "sg:tags":[
        "tarpaulin"
    ],
    "wof:name":"Uvo Nv Dekzeilen",
    "wof:placetype":"venue"
},
  "geometry": {"coordinates":[4.3888502121,51.2639389038],"type":"Point"}
}