{
  "type": "Feature",
  "properties": {
    "iso:country":"BE",
    "sg:address":"Rue De L'eglise 13",
    "sg:city":"Welkenraedt/welkenraedt",
    "sg:classifiers":[
        {
            "category":"Fast Food",
            "type":"Food & Drink"
        }
    ],
    "sg:phone":"+32 87 88 30 37",
    "sg:postcode":"4840",
    "sg:province":"Li\u00e8ge",
    "sg:tags":[
        "meeneem",
        "restaurant"
    ],
    "wof:name":"Pita Kreta",
    "wof:placetype":"venue"
},
  "geometry": {"coordinates":[5.9714360237,50.6604194641],"type":"Point"}
}