{
  "type": "Feature",
  "properties": {
    "iso:country":"BE",
    "sg:address":"Rue De Vise 869",
    "sg:city":"Li\u00c8ge",
    "sg:orig_category":"D\u00e9taillants en pi\u00e8ces and accessoires de voitures",
    "sg:phone":"+32 4 370 29 71",
    "sg:postcode":"4020",
    "sg:province":"Li\u00e8ge",
    "wof:name":"Casa Car",
    "wof:placetype":"venue"
},
  "geometry": {"coordinates":[5.6344199181,50.6485900879],"type":"Point"}
}