{
  "type": "Feature",
  "properties": {
    "iso:country":"BE",
    "sg:address":"Avenue Armand Scheitler 58",
    "sg:city":"Sint-pieters-woluwe/woluwe-saint-pierre",
    "sg:orig_category":"M\u00e9decines alternatives",
    "sg:phone":"+32 2 672 47 62",
    "sg:postcode":"1150",
    "sg:province":"Bruxelles-Capitale",
    "wof:name":"Odile Defosse",
    "wof:placetype":"venue"
},
  "geometry": {"coordinates":[4.4161219597,50.823600769],"type":"Point"}
}