{
  "type": "Feature",
  "properties": {
    "addr:full":"Abeeldreef 7 Meulebeke West-Vlaanderen 8760",
    "addr:housenumber":"7",
    "addr:postcode":"8760",
    "addr:street":"Abeeldreef",
    "iso:country":"BE",
    "sg:address":"Abeeldreef 7",
    "sg:city":"Meulebeke",
    "sg:classifiers":[
        {
            "category":"Personal",
            "subcategory":"Beauty Salon",
            "type":"Services"
        }
    ],
    "sg:phone":"+32 51 48 85 14",
    "sg:postcode":"8760",
    "sg:province":"West-Vlaanderen",
    "sg:tags":[
        "de",
        "coiffure"
    ],
    "wof:name":"G. Defour",
    "wof:placetype":"venue"
},
  "geometry": {"coordinates":[3.2829880714,50.9507827759],"type":"Point"}
}