{
  "type": "Feature",
  "properties": {
    "addr:full":"Avenue De Philippeville 210 Charleroi (marcinelle) Hainaut 6001",
    "addr:housenumber":"210",
    "addr:postcode":"6001",
    "addr:street":"Avenue De Philippeville",
    "iso:country":"BE",
    "sg:address":"Avenue De Philippeville 210",
    "sg:city":"Charleroi (marcinelle)",
    "sg:classifiers":[
        {
            "category":"Building & Trades",
            "subcategory":"Electrical",
            "type":"Services"
        }
    ],
    "sg:phone":"+32 71 41 86 75",
    "sg:postcode":"6001",
    "sg:province":"Hainaut",
    "sg:tags":[
        "electric",
        "-",
        "housewiring",
        "contractor"
    ],
    "wof:name":"Ch Services",
    "wof:placetype":"venue"
},
  "geometry": {"coordinates":[4.4530358315,50.3993988037],"type":"Point"}
}