{
  "type": "Feature",
  "properties": {
    "addr:full":"Gentsesteenweg 186 Harelbeke West-Vlaanderen 8530",
    "addr:housenumber":"186",
    "addr:postcode":"8530",
    "addr:street":"Gentsesteenweg",
    "iso:country":"BE",
    "sg:address":"Gentsesteenweg 186",
    "sg:city":"Harelbeke",
    "sg:orig_category":"Meubles D\u00e9taillants, Am\u00e9nagement de B\u00e2timents et de Cuisines. D\u00e9corateurs d'int\u00e9rieur. Machines and ",
    "sg:phone":"+32 56 71 71 00",
    "sg:postcode":"8530",
    "sg:province":"West-Vlaanderen",
    "wof:name":"Bureauinrichtingen Joye",
    "wof:placetype":"venue"
},
  "geometry": {"coordinates":[3.3265209198,50.8642044067],"type":"Point"}
}