{
  "type": "Feature",
  "properties": {
    "iso:country":"BE",
    "sg:address":"Bedrijfsstraat 16",
    "sg:city":"Hasselt",
    "sg:orig_category":"Installation de menuiserie m\u00e9tallique. Bois Gr. Quincailleries. Mat\u00e9riaux de construction Gr",
    "sg:phone":"+32 11 21 25 52",
    "sg:postcode":"3500",
    "sg:province":"Limburg",
    "wof:name":"Betim",
    "wof:placetype":"venue"
},
  "geometry": {"coordinates":[5.3631367683,50.9554862976],"type":"Point"}
}