{
  "type": "Feature",
  "properties": {
    "addr:full":"Ter Stratenweg 2 Ranst-oelegem Antwerpen 2520",
    "addr:housenumber":"2",
    "addr:postcode":"2520",
    "addr:street":"Ter Stratenweg",
    "iso:country":"BE",
    "sg:address":"Ter Stratenweg 2",
    "sg:city":"Ranst-oelegem",
    "sg:classifiers":[
        {
            "category":"Manufacturing",
            "subcategory":"Tools & Machinery",
            "type":"Manufacturing & Wholesale Goods"
        }
    ],
    "sg:phone":"+32 3 475 12 90",
    "sg:postcode":"2520",
    "sg:province":"Antwerpen",
    "sg:tags":[
        "nitride",
        "diamond",
        "cubic",
        "cbn",
        "grinding",
        "boron",
        "flexible",
        "tools"
    ],
    "wof:name":"Diop B.v.b.a",
    "wof:placetype":"venue"
},
  "geometry": {"coordinates":[4.5622401237,51.1892051697],"type":"Point"}
}