{
  "type": "Feature",
  "properties": {
    "iso:country":"BE",
    "sg:address":"Dorpsstraat 9",
    "sg:city":"Laarne",
    "sg:classifiers":[
        {
            "category":"Cafe",
            "type":"Food & Drink"
        }
    ],
    "sg:phone":"+32 9 366 04 81",
    "sg:postcode":"9270",
    "sg:province":"Oost-Vlaanderen",
    "sg:tags":[
        "caf\u00e9s"
    ],
    "wof:name":"Marina Bruyneel",
    "wof:placetype":"venue"
},
  "geometry": {"coordinates":[3.8486340046,51.0295066833],"type":"Point"}
}