{
  "type": "Feature",
  "properties": {
    "iso:country":"BE",
    "sg:address":"Molenstraat 101",
    "sg:city":"Wetteren",
    "sg:orig_category":"Ordinateurs and \u00e9quipement informatique",
    "sg:phone":"+32 9 366 15 18",
    "sg:postcode":"9230",
    "sg:province":"Oost-Vlaanderen",
    "wof:name":"U.s. Connect",
    "wof:placetype":"venue"
},
  "geometry": {"coordinates":[3.8890440464,51.0040054321],"type":"Point"}
}