{
  "type": "Feature",
  "properties": {
    "addr:full":"De Smet De Naeyerlaan 181 Jette Bruxelles-Capitale 1090",
    "addr:housenumber":"181",
    "addr:postcode":"1090",
    "addr:street":"De Smet De Naeyerlaan",
    "iso:country":"BE",
    "sg:address":"De Smet De Naeyerlaan 181",
    "sg:city":"Jette",
    "sg:orig_category":"Artsen and specialisten",
    "sg:phone":"+32 2 424 16 08",
    "sg:postcode":"1090",
    "sg:province":"Bruxelles-Capitale",
    "wof:name":"Quoi Phuong Tran",
    "wof:placetype":"venue"
},
  "geometry": {"coordinates":[4.3295931816,50.8758087158],"type":"Point"}
}