{
  "type": "Feature",
  "properties": {
    "addr:full":"Lenniksebaan 67 Dilbeek (itterbeek) Vlaams-Brabant 1701",
    "addr:housenumber":"67",
    "addr:postcode":"1701",
    "addr:street":"Lenniksebaan",
    "iso:country":"BE",
    "sg:address":"Lenniksebaan 67",
    "sg:city":"Dilbeek (itterbeek)",
    "sg:classifiers":[
        {
            "category":"Home & Garden",
            "subcategory":"Kitchen Supply",
            "type":"Retail Goods"
        }
    ],
    "sg:phone":"+32 2 502 67 04",
    "sg:postcode":"1701",
    "sg:province":"Vlaams-Brabant",
    "sg:tags":[
        "installation"
    ],
    "wof:name":"C-plus-d Sprl",
    "wof:placetype":"venue"
},
  "geometry": {"coordinates":[4.2437491417,50.8179779053],"type":"Point"}
}