{
  "type": "Feature",
  "properties": {
    "iso:country":"BE",
    "sg:address":"Rue Saint-georges 27-29",
    "sg:city":"Elsene",
    "sg:orig_category":"Biblioth\u00e8ques and archives publiques",
    "sg:phone":"+32 2 640 76 33",
    "sg:postcode":"1050",
    "sg:province":"Bruxelles-Capitale",
    "wof:name":"Lectura",
    "wof:placetype":"venue"
},
  "geometry": {"coordinates":[4.3687829971,50.818561554],"type":"Point"}
}