{
  "type": "Feature",
  "properties": {
    "addr:full":"Rue Andr\u00c9-sodar 7 Dinant Namur 5500",
    "addr:housenumber":"7",
    "addr:postcode":"5500",
    "addr:street":"Rue Andre\u0301-Sodar",
    "iso:country":"BE",
    "sg:address":"Rue Andr\u00c9-sodar 7",
    "sg:city":"Dinant",
    "sg:orig_category":"Boekhouders",
    "sg:phone":"+32 82 22 52 46",
    "sg:postcode":"5500",
    "sg:province":"Namur",
    "wof:name":"Jean-olivier Meyfroidt",
    "wof:placetype":"venue"
},
  "geometry": {"coordinates":[4.9095211029,50.2595787048],"type":"Point"}
}