{
  "type": "Feature",
  "properties": {
    "addr:full":"Dr\u00e8ve Du Long Bonnier 4 Bruxelles Bruxelles-Capitale 1020",
    "addr:housenumber":"4",
    "addr:postcode":"1020",
    "addr:street":"Dre\u0300Ve Du Long Bonnier",
    "iso:country":"BE",
    "sg:address":"Dr\u00e8ve Du Long Bonnier 4",
    "sg:city":"Bruxelles",
    "sg:classifiers":[
        {
            "category":"Health Services",
            "subcategory":"Dentist",
            "type":"Services"
        }
    ],
    "sg:phone":"+32 2 262 07 80",
    "sg:postcode":"1020",
    "sg:province":"Bruxelles-Capitale",
    "wof:name":"Menten Albert",
    "wof:placetype":"venue"
},
  "geometry": {"coordinates":[4.3657650948,50.8962364197],"type":"Point"}
}