{
  "type": "Feature",
  "properties": {
    "iso:country":"BE",
    "sg:address":"Avenue Landas 21",
    "sg:city":"Tubize (saintes)",
    "sg:classifiers":[
        {
            "category":"Health Services",
            "subcategory":"Nursing And Care Facility",
            "type":"Services"
        }
    ],
    "sg:postcode":"1480",
    "sg:province":"Brabant Wallon",
    "sg:tags":[
        "safe"
    ],
    "wof:name":"Ets Poisson Sa",
    "wof:placetype":"venue"
},
  "geometry": {"coordinates":[4.1719450951,50.7104911804],"type":"Point"}
}