{
  "type": "Feature",
  "properties": {
    "iso:country":"BE",
    "sg:address":"Petergensfeld 88",
    "sg:city":"Raeren",
    "sg:orig_category":"Epiceries",
    "sg:phone":"+32 87 85 12 95",
    "sg:postcode":"4730",
    "sg:province":"Li\u00e8ge",
    "wof:name":"Haus La Balena",
    "wof:placetype":"venue"
},
  "geometry": {"coordinates":[6.1448078156,50.6634292603],"type":"Point"}
}