{
  "type": "Feature",
  "properties": {
    "addr:full":"Weg Naar Ellikom 185 Meeuwen-gruitrode Limburg 3670",
    "addr:housenumber":"185",
    "addr:postcode":"3670",
    "addr:street":"Weg Naar Ellikom",
    "iso:country":"BE",
    "sg:address":"Weg Naar Ellikom 185",
    "sg:city":"Meeuwen-gruitrode",
    "sg:orig_category":"Eleveurs and marchands de porcs. Eleveurs de bovins",
    "sg:phone":"+32 11 63 40 19",
    "sg:postcode":"3670",
    "sg:province":"Limburg",
    "wof:name":"Johan Van Helden",
    "wof:placetype":"venue"
},
  "geometry": {"coordinates":[5.5212798119,51.117149353],"type":"Point"}
}