{
  "type": "Feature",
  "properties": {
    "addr:full":"Rue Du Parc Industriel 32ba Marche-en-famenne Luxembourg 6900",
    "addr:housenumber":"32ba",
    "addr:postcode":"6900",
    "addr:street":"Rue Du Parc Industriel",
    "iso:country":"BE",
    "sg:address":"Rue Du Parc Industriel 32ba",
    "sg:city":"Marche-en-famenne",
    "sg:orig_category":"Meubelzaken, woning- and keukeninrichting",
    "sg:phone":"+32 84 32 19 11",
    "sg:postcode":"6900",
    "sg:province":"Luxembourg",
    "wof:name":"Tempo",
    "wof:placetype":"venue"
},
  "geometry": {"coordinates":[5.3208727837,50.2178268433],"type":"Point"}
}