{
  "type": "Feature",
  "properties": {
    "addr:full":"Rue Hubert Mangon 33 Remicourt (pousset) Li\u00e8ge 4350",
    "addr:housenumber":"33",
    "addr:postcode":"4350",
    "addr:street":"Rue Hubert Mangon;Pousset",
    "iso:country":"BE",
    "sg:address":"Rue Hubert Mangon 33",
    "sg:city":"Remicourt (pousset)",
    "sg:classifiers":[
        {
            "category":"Home & Garden",
            "subcategory":"Building Materials",
            "type":"Retail Goods"
        }
    ],
    "sg:phone":"+32 19 54 51 75",
    "sg:postcode":"4350",
    "sg:province":"Li\u00e8ge",
    "sg:tags":[
        "shutter"
    ],
    "wof:name":"Biname Didier",
    "wof:placetype":"venue"
},
  "geometry": {"coordinates":[5.3118400574,50.6925392151],"type":"Point"}
}