{
  "type": "Feature",
  "properties": {
    "iso:country":"BE",
    "sg:address":"Meensesteenweg 266b11",
    "sg:city":"Kortrijk",
    "sg:orig_category":"Architecten",
    "sg:phone":"+32 56 35 67 62",
    "sg:postcode":"8501",
    "sg:province":"West-Vlaanderen",
    "wof:name":"Yves Malysse",
    "wof:placetype":"venue"
},
  "geometry": {"coordinates":[3.2307550907,50.824596405],"type":"Point"}
}