{
  "type": "Feature",
  "properties": {
    "iso:country":"BE",
    "sg:address":"Koningsstraat 151",
    "sg:city":"Sint-joost-ten-node/saint-josse-ten-noode",
    "sg:orig_category":"Hypotheken and hypotheekbanken Levensverzekeringsmaatschappijen Verbruikerskredietinstellingen Verze",
    "sg:phone":"+32 2 229 37 11",
    "sg:postcode":"1210",
    "sg:province":"Bruxelles-Capitale",
    "wof:name":"P&v",
    "wof:placetype":"venue"
},
  "geometry": {"coordinates":[4.3661351204,50.8535385132],"type":"Point"}
}