{
  "type": "Feature",
  "properties": {
    "addr:full":"Koningsstraat 151 Sint-joost-ten-node/saint-josse-ten-noode Bruxelles-Capitale 1210",
    "addr:housenumber":"151",
    "addr:postcode":"1210",
    "addr:street":"Koningsstraat;Sint-Joost-Ten-Node /",
    "iso:country":"BE",
    "sg:address":"Koningsstraat 151",
    "sg:city":"Sint-joost-ten-node/saint-josse-ten-noode",
    "sg:orig_category":"Hypotheken and hypotheekbanken Levensverzekeringsmaatschappijen Verbruikerskredietinstellingen Verze",
    "sg:phone":"+32 2 229 37 11",
    "sg:postcode":"1210",
    "sg:province":"Bruxelles-Capitale",
    "wof:name":"P&v",
    "wof:placetype":"venue"
},
  "geometry": {"coordinates":[4.3661351204,50.8535385132],"type":"Point"}
}