{
  "type": "Feature",
  "properties": {
    "iso:country":"BE",
    "sg:address":"Retiesebaan 50",
    "sg:city":"Kasterlee",
    "sg:orig_category":"Schoenen",
    "sg:phone":"+32 14 85 37 86",
    "sg:postcode":"2460",
    "sg:province":"Antwerpen",
    "wof:name":"Noyens",
    "wof:placetype":"venue"
},
  "geometry": {"coordinates":[4.9733338356,51.2415237427],"type":"Point"}
}