{
  "type": "Feature",
  "properties": {
    "iso:country":"BE",
    "sg:address":"Deinzesteenweg 29",
    "sg:city":"Kruishoutem",
    "sg:orig_category":"Rev\u00eatements de sols and murs. Mat\u00e9riaux de construction B\u00e9ton pr\u00eat \u00e0 l'emploi Fab",
    "sg:phone":"+32 9 383 77 79",
    "sg:postcode":"9770",
    "sg:province":"Oost-Vlaanderen",
    "wof:name":"De Snerck",
    "wof:placetype":"venue"
},
  "geometry": {"coordinates":[3.529337883,50.9164237976],"type":"Point"}
}