{
  "type": "Feature",
  "properties": {
    "addr:full":"Stationstraat 116 Ternat Vlaams-Brabant 1740",
    "addr:housenumber":"116",
    "addr:postcode":"1740",
    "addr:street":"Stationstraat",
    "iso:country":"BE",
    "sg:address":"Stationstraat 116",
    "sg:city":"Ternat",
    "sg:classifiers":[
        {
            "category":"Health Services",
            "subcategory":"Doctor",
            "type":"Services"
        }
    ],
    "sg:phone":"+32 2 582 14 28",
    "sg:postcode":"1740",
    "sg:province":"Vlaams-Brabant",
    "sg:tags":[
        "medicinephysicians",
        "surgeon"
    ],
    "wof:name":"Lichtert Willy",
    "wof:placetype":"venue"
},
  "geometry": {"coordinates":[4.1695990562,50.8732261658],"type":"Point"}
}