{
  "type": "Feature",
  "properties": {
    "addr:full":"Genenbosstraat 91 Lummen Limburg 3560",
    "addr:housenumber":"91",
    "addr:postcode":"3560",
    "addr:street":"Genenbosstraat",
    "iso:country":"BE",
    "sg:address":"Genenbosstraat 91",
    "sg:city":"Lummen",
    "sg:orig_category":"Epiceries",
    "sg:phone":"+32 11 45 38 76",
    "sg:postcode":"3560",
    "sg:province":"Limburg",
    "wof:name":"Huis Klein Genoegen",
    "wof:placetype":"venue"
},
  "geometry": {"coordinates":[5.2383899689,51.0165748596],"type":"Point"}
}