{
  "type": "Feature",
  "properties": {
    "iso:country":"BE",
    "sg:address":"Meensesteenweg 246",
    "sg:city":"Roeselare",
    "sg:orig_category":"Artsen and specialisten",
    "sg:phone":"+32 51 22 20 68",
    "sg:postcode":"8800",
    "sg:province":"West-Vlaanderen",
    "wof:name":"Dirk Vuylsteke",
    "wof:placetype":"venue"
},
  "geometry": {"coordinates":[3.1202390194,50.9339027405],"type":"Point"}
}