{
  "type": "Feature",
  "properties": {
    "iso:country":"BE",
    "sg:address":"Munsterstraat 24",
    "sg:city":"Brussel/bruxelles",
    "sg:orig_category":"Geluidsopnames",
    "sg:phone":"+32 2 640 73 36",
    "sg:postcode":"1000",
    "sg:province":"Bruxelles-Capitale",
    "wof:name":"Traffic Jam",
    "wof:placetype":"venue"
},
  "geometry": {"coordinates":[4.3726501465,50.8204574585],"type":"Point"}
}