{
  "type": "Feature",
  "properties": {
    "addr:full":"Dorpsstraat 24 Maasmechelen Limburg 3630",
    "addr:housenumber":"24",
    "addr:postcode":"3630",
    "addr:street":"Dorpsstraat",
    "iso:country":"BE",
    "sg:address":"Dorpsstraat 24",
    "sg:city":"Maasmechelen",
    "sg:orig_category":"Eleveurs and marchands de porcs",
    "sg:phone":"+32 89 77 23 44",
    "sg:postcode":"3630",
    "sg:province":"Limburg",
    "wof:name":"Luc Wintjens",
    "wof:placetype":"venue"
},
  "geometry": {"coordinates":[5.6961350441,50.963848114],"type":"Point"}
}