{
  "type": "Feature",
  "properties": {
    "iso:country":"BE",
    "sg:address":"Anneessensstraat 11ba",
    "sg:city":"Antwerpen",
    "sg:classifiers":[
        {
            "category":"Cafe",
            "type":"Food & Drink"
        }
    ],
    "sg:phone":"+32 3 232 19 36",
    "sg:postcode":"2018",
    "sg:province":"Antwerpen",
    "sg:tags":[
        "caf\u00e9s"
    ],
    "wof:name":"Caf\u00c9 Happy Karaoke",
    "wof:placetype":"venue"
},
  "geometry": {"coordinates":[4.4183301926,51.2186203003],"type":"Point"}
}