{
  "type": "Feature",
  "properties": {
    "iso:country":"BE",
    "sg:address":"Rue Du Bois De Lens 3",
    "sg:city":"Chi\u00c8vres",
    "sg:orig_category":"Installatie van houten of kunststof schrijnwerk",
    "sg:phone":"+32 68 65 83 35",
    "sg:postcode":"7950",
    "sg:province":"Hainaut",
    "wof:name":"Michel Gladieux",
    "wof:placetype":"venue"
},
  "geometry": {"coordinates":[3.8235259056,50.5549545288],"type":"Point"}
}