{
  "type": "Feature",
  "properties": {
    "iso:country":"BE",
    "sg:address":"Keerbaan 140",
    "sg:city":"Wommelgem",
    "sg:classifiers":[
        {
            "category":"Autos & Motor Vehicles",
            "subcategory":"Automobile Sales",
            "type":"Retail Goods"
        }
    ],
    "sg:phone":"+32 3 353 11 53",
    "sg:postcode":"2160",
    "sg:province":"Antwerpen",
    "sg:tags":[
        "car",
        "used",
        "-"
    ],
    "wof:name":"Breugelmans L",
    "wof:placetype":"venue"
},
  "geometry": {"coordinates":[4.5408678055,51.2091751099],"type":"Point"}
}