{
  "type": "Feature",
  "properties": {
    "iso:country":"BE",
    "sg:address":"Lostraat 77bf",
    "sg:city":"Aalter",
    "sg:classifiers":[
        {
            "category":"Food & Beverages",
            "subcategory":"Fruits & Vegetables",
            "type":"Retail Goods"
        }
    ],
    "sg:phone":"+32 9 374 24 11",
    "sg:postcode":"9880",
    "sg:province":"Oost-Vlaanderen",
    "sg:tags":[
        "groenten"
    ],
    "wof:name":"Huis Dendooven",
    "wof:placetype":"venue"
},
  "geometry": {"coordinates":[3.4505119324,51.0791091919],"type":"Point"}
}