{
  "type": "Feature",
  "properties": {
    "addr:full":"Engstraat 70 Beerse Antwerpen 2340",
    "addr:housenumber":"70",
    "addr:postcode":"2340",
    "addr:street":"Engstraat",
    "iso:country":"BE",
    "sg:address":"Engstraat 70",
    "sg:city":"Beerse",
    "sg:orig_category":"Artsen and specialisten",
    "sg:phone":"+32 3 312 39 22",
    "sg:postcode":"2340",
    "sg:province":"Antwerpen",
    "wof:name":"Raf Wouters",
    "wof:placetype":"venue"
},
  "geometry": {"coordinates":[4.7937750816,51.3003234863],"type":"Point"}
}