{
  "type": "Feature",
  "properties": {
    "addr:full":"Universiteitslaan 2 Kortrijk West-Vlaanderen 8500",
    "addr:housenumber":"2",
    "addr:postcode":"8500",
    "addr:street":"Universiteitslaan",
    "iso:country":"BE",
    "sg:address":"Universiteitslaan 2",
    "sg:city":"Kortrijk",
    "sg:classifiers":[
        {
            "category":"Home & Garden",
            "subcategory":"Home Furnishings",
            "type":"Retail Goods"
        }
    ],
    "sg:phone":"+32 56 20 20 73",
    "sg:postcode":"8500",
    "sg:province":"West-Vlaanderen",
    "sg:tags":[
        "interior",
        "decoration"
    ],
    "wof:name":"Multidecor Bvba",
    "wof:placetype":"venue"
},
  "geometry": {"coordinates":[3.2817211151,50.8070487976],"type":"Point"}
}