{
  "type": "Feature",
  "properties": {
    "addr:full":"Parvis Sainte-alix 31 Bruxelles (woluwe-saint-pierre) Bruxelles-Capitale 1150",
    "addr:housenumber":"31",
    "addr:postcode":"1150",
    "addr:street":"Parvis Sainte-Alix",
    "iso:country":"BE",
    "sg:address":"Parvis Sainte-alix 31",
    "sg:city":"Bruxelles (woluwe-saint-pierre)",
    "sg:classifiers":[
        {
            "category":"Building & Trades",
            "subcategory":"Construction",
            "type":"Services"
        }
    ],
    "sg:phone":"+32 2 772 21 08",
    "sg:postcode":"1150",
    "sg:province":"Bruxelles-Capitale",
    "sg:tags":[
        "carpenter"
    ],
    "wof:name":"Lavrys T",
    "wof:placetype":"venue"
},
  "geometry": {"coordinates":[4.4623742104,50.8277549744],"type":"Point"}
}