{
  "type": "Feature",
  "properties": {
    "addr:full":"Tiensesteenweg 384 Leuven Vlaams-Brabant 3000",
    "addr:housenumber":"384",
    "addr:postcode":"3000",
    "addr:street":"Tiensesteenweg",
    "iso:country":"BE",
    "sg:address":"Tiensesteenweg 384",
    "sg:city":"Leuven",
    "sg:classifiers":[
        {
            "category":"Building & Trades",
            "subcategory":"Construction",
            "type":"Services"
        }
    ],
    "sg:phone":"+32 16 25 61 89",
    "sg:postcode":"3000",
    "sg:province":"Vlaams-Brabant",
    "sg:tags":[
        "installation",
        "-",
        "central",
        "heating"
    ],
    "wof:name":"Heating Center Nv",
    "wof:placetype":"venue"
},
  "geometry": {"coordinates":[4.7406740189,50.8675117493],"type":"Point"}
}