{
  "type": "Feature",
  "properties": {
    "addr:full":"Molenstraat 53 Vosselaar Antwerpen 2350",
    "addr:housenumber":"53",
    "addr:postcode":"2350",
    "addr:street":"Molenstraat",
    "iso:country":"BE",
    "sg:address":"Molenstraat 53",
    "sg:city":"Vosselaar",
    "sg:orig_category":"Installation \u00e9lectrique r\u00e9sidentielle",
    "sg:phone":"+32 14 61 40 48",
    "sg:postcode":"2350",
    "sg:province":"Antwerpen",
    "wof:name":"Ronny Segers",
    "wof:placetype":"venue"
},
  "geometry": {"coordinates":[4.8975758553,51.312171936],"type":"Point"}
}