{
  "type": "Feature",
  "properties": {
    "addr:full":"Doornveld 4 Zellik Vlaams-Brabant 1731",
    "addr:housenumber":"4",
    "addr:postcode":"1731",
    "addr:street":"Doornveld",
    "iso:country":"BE",
    "sg:address":"Doornveld 4",
    "sg:city":"Zellik",
    "sg:classifiers":[
        {
            "category":"Bars & Pubs",
            "subcategory":"Oxygen Bar",
            "type":"Food & Drink"
        }
    ],
    "sg:phone":"+32 2 466 15 15",
    "sg:postcode":"1731",
    "sg:province":"Vlaams-Brabant",
    "sg:tags":[
        "compressor",
        "gas"
    ],
    "wof:name":"Olaer Benelux Nv",
    "wof:placetype":"venue"
},
  "geometry": {"coordinates":[4.2704610825,50.8912315369],"type":"Point"}
}