{
  "type": "Feature",
  "properties": {
    "iso:country":"BE",
    "sg:address":"Eygenstraat 27",
    "sg:city":"Huldenberg",
    "sg:orig_category":"Diverse zakelijke dienstverlening",
    "sg:phone":"+32 16 47 31 65",
    "sg:postcode":"3040",
    "sg:province":"Vlaams-Brabant",
    "wof:name":"Azuur",
    "wof:placetype":"venue"
},
  "geometry": {"coordinates":[4.6334037781,50.8193244934],"type":"Point"}
}