{
  "type": "Feature",
  "properties": {
    "iso:country":"BE",
    "sg:address":"Wijnegemhofstraat 45",
    "sg:city":"Kortenberg",
    "sg:orig_category":"Dakwerken",
    "sg:phone":"+32 2 759 56 03",
    "sg:postcode":"3078",
    "sg:province":"Vlaams-Brabant",
    "wof:name":"Michiels",
    "wof:placetype":"venue"
},
  "geometry": {"coordinates":[4.5850281715,50.880897522],"type":"Point"}
}