{
  "type": "Feature",
  "properties": {
    "iso:country":"BE",
    "sg:address":"Place Jules Destr\u00c9e 9ba",
    "sg:city":"Chatelet",
    "sg:orig_category":"Journaux. Tabac",
    "sg:phone":"+32 71 39 22 53",
    "sg:postcode":"6200",
    "sg:province":"Hainaut",
    "wof:name":"Librairie Nouvelle",
    "wof:placetype":"venue"
},
  "geometry": {"coordinates":[4.5155482292,50.3903961182],"type":"Point"}
}