{
  "type": "Feature",
  "properties": {
    "addr:full":"Place De La Victoire 10 Ch\u00e2telet Hainaut 6200",
    "addr:housenumber":"10",
    "addr:postcode":"6200",
    "addr:street":"Place De La",
    "iso:country":"BE",
    "sg:address":"Place De La Victoire 10",
    "sg:city":"Ch\u00e2telet",
    "sg:classifiers":[
        {
            "category":"Food & Beverages",
            "subcategory":"Fruits & Vegetables",
            "type":"Retail Goods"
        }
    ],
    "sg:phone":"+32 71 39 07 27",
    "sg:postcode":"6200",
    "sg:province":"Hainaut",
    "sg:tags":[
        "-"
    ],
    "wof:name":"Corne D'abondance T.m (la)",
    "wof:placetype":"venue"
},
  "geometry": {"coordinates":[4.5179800987,50.4041481018],"type":"Point"}
}