{
  "type": "Feature",
  "properties": {
    "addr:full":"Bikschotestraat 119 Langemark-poelkapelle West-Vlaanderen 8920",
    "addr:housenumber":"119",
    "addr:postcode":"langemark-poelkapelle;8920",
    "addr:street":"Bikschotestraat",
    "iso:country":"BE",
    "sg:address":"Bikschotestraat 119",
    "sg:city":"Langemark-poelkapelle",
    "sg:orig_category":"Airconditioning and ventilatie Elektrische installaties voor woningen Winkelinrichting and handelsui",
    "sg:phone":"+32 57 20 82 06",
    "sg:postcode":"8920",
    "sg:province":"West-Vlaanderen",
    "wof:name":"G.-electricity",
    "wof:placetype":"venue"
},
  "geometry": {"coordinates":[2.919770956,50.9132423401],"type":"Point"}
}