{
  "type": "Feature",
  "properties": {
    "iso:country":"BE",
    "sg:address":"Rue Fran\u00c7ois Dewiest 142",
    "sg:city":"Charleroi",
    "sg:orig_category":"M\u00e9decins and sp\u00e9cialistes",
    "sg:phone":"+32 71 35 58 34",
    "sg:postcode":"6040",
    "sg:province":"Hainaut",
    "wof:name":"Vincent Wery",
    "wof:placetype":"venue"
},
  "geometry": {"coordinates":[4.4149827957,50.4354972839],"type":"Point"}
}