{
  "type": "Feature",
  "properties": {
    "addr:full":"Rue Z\u00c9nobe Gramme 20 Charleroi Hainaut 6000",
    "addr:housenumber":"20",
    "addr:postcode":"6000",
    "addr:street":"Rue Ze\u0301Nobe Gramme;Hainaut",
    "iso:country":"BE",
    "sg:address":"Rue Z\u00c9nobe Gramme 20",
    "sg:city":"Charleroi",
    "sg:orig_category":"M\u00e9decins and sp\u00e9cialistes",
    "sg:phone":"+32 71 32 22 07",
    "sg:postcode":"6000",
    "sg:province":"Hainaut",
    "wof:name":"Alain Bachy",
    "wof:placetype":"venue"
},
  "geometry": {"coordinates":[4.4464321136,50.4152870178],"type":"Point"}
}