{
  "type": "Feature",
  "properties": {
    "addr:full":"Rue Des Pyr\u00e8thres 19 Bruxelles (watermael-boitsfort) Bruxelles-Capitale 1170",
    "addr:housenumber":"19",
    "addr:postcode":"1170",
    "addr:street":"Rue Des Pyre\u0300Thres",
    "iso:country":"BE",
    "sg:address":"Rue Des Pyr\u00e8thres 19",
    "sg:city":"Bruxelles (watermael-boitsfort)",
    "sg:classifiers":[
        {
            "category":"Building & Trades",
            "subcategory":"Pest Control",
            "type":"Services"
        }
    ],
    "sg:phone":"+32 2 675 42 36",
    "sg:postcode":"1170",
    "sg:province":"Bruxelles-Capitale",
    "sg:tags":[
        "painting",
        "contractor"
    ],
    "wof:name":"Pletzers Ph",
    "wof:placetype":"venue"
},
  "geometry": {"coordinates":[4.4237170219,50.8091545105],"type":"Point"}
}