{
  "type": "Feature",
  "properties": {
    "addr:full":"Gentsesteenweg 108 Zele Oost-Vlaanderen 9240",
    "addr:housenumber":"108",
    "addr:postcode":"9240",
    "addr:street":"Gentsesteenweg",
    "iso:country":"BE",
    "sg:address":"Gentsesteenweg 108",
    "sg:city":"Zele",
    "sg:classifiers":[
        {
            "category":"Banks & Credit Unions",
            "subcategory":"Financial Services",
            "type":"Services"
        }
    ],
    "sg:phone":"+32 52 44 73 15",
    "sg:postcode":"9240",
    "sg:province":"Oost-Vlaanderen",
    "sg:tags":[
        "loan",
        "mortgage"
    ],
    "wof:name":"Lange (de)",
    "wof:placetype":"venue"
},
  "geometry": {"coordinates":[4.0209331512,51.0602416992],"type":"Point"}
}