{
  "type": "Feature",
  "properties": {
    "iso:country":"BE",
    "sg:address":"Condijstraat 11",
    "sg:city":"Gooik",
    "sg:orig_category":"Fruitteelt",
    "sg:phone":"+32 54 56 72 49",
    "sg:postcode":"1755",
    "sg:province":"Vlaams-Brabant",
    "wof:name":"Geert Heremans",
    "wof:placetype":"venue"
},
  "geometry": {"coordinates":[4.0775728226,50.7751846313],"type":"Point"}
}