{
  "type": "Feature",
  "properties": {
    "addr:full":"Walheimer Strasse 52 Raeren Li\u00e8ge 4730",
    "addr:housenumber":"52",
    "addr:postcode":"4730",
    "addr:street":"Walheimer Strasse",
    "iso:country":"BE",
    "sg:address":"Walheimer Strasse 52",
    "sg:city":"Raeren",
    "sg:classifiers":[
        {
            "category":"Professional",
            "type":"Services"
        }
    ],
    "sg:phone":"+32 87 85 12 41",
    "sg:postcode":"4730",
    "sg:province":"Li\u00e8ge",
    "sg:tags":[
        "transport"
    ],
    "wof:name":"Paul Kleutgen S.p.r.l.",
    "wof:placetype":"venue"
},
  "geometry": {"coordinates":[6.1432538033,50.6804962158],"type":"Point"}
}