{
  "type": "Feature",
  "properties": {
    "iso:country":"BE",
    "sg:address":"Meelstraat 3",
    "sg:city":"Gent",
    "sg:classifiers":[
        {
            "category":"Wholesale",
            "subcategory":"Beer",
            "type":"Manufacturing & Wholesale Goods"
        }
    ],
    "sg:phone":"+32 9 330 09 01",
    "sg:postcode":"9000",
    "sg:province":"Oost-Vlaanderen",
    "sg:tags":[
        "ale",
        "-"
    ],
    "wof:name":"Van Aken T",
    "wof:placetype":"venue"
},
  "geometry": {"coordinates":[3.7179679871,51.0607299805],"type":"Point"}
}