{
  "type": "Feature",
  "properties": {
    "iso:country":"BE",
    "sg:address":"Katteputstraat 1-2-3",
    "sg:city":"Deinze",
    "sg:orig_category":"Supermarkten",
    "sg:postcode":"9800",
    "sg:province":"Oost-Vlaanderen",
    "wof:name":"Aldi",
    "wof:placetype":"venue"
},
  "geometry": {"coordinates":[3.530174017,50.9863166809],"type":"Point"}
}