{
  "type": "Feature",
  "properties": {
    "iso:country":"BE",
    "sg:address":"Waversesteenweg 19",
    "sg:city":"Hoegaarden",
    "sg:classifiers":[
        {
            "category":"Professional",
            "subcategory":"Management & Consulting",
            "type":"Services"
        }
    ],
    "sg:phone":"+32 16 76 54 27",
    "sg:postcode":"3320",
    "sg:province":"Vlaams-Brabant",
    "sg:tags":[
        "consultant",
        "agency",
        "advertising"
    ],
    "wof:name":"Wostijn Bvba",
    "wof:placetype":"venue"
},
  "geometry": {"coordinates":[4.8442220688,50.7851600647],"type":"Point"}
}