{
  "type": "Feature",
  "properties": {
    "addr:full":"Adjudant Masscheleinlaan 42 Ieper West-Vlaanderen 8900",
    "addr:housenumber":"42",
    "addr:postcode":"8900",
    "addr:street":"Masscheleinlaan",
    "iso:country":"BE",
    "sg:address":"Adjudant Masscheleinlaan 42",
    "sg:city":"Ieper",
    "sg:classifiers":[
        {
            "category":"Professional",
            "subcategory":"Engineering",
            "type":"Services"
        }
    ],
    "sg:phone":"+32 57 20 56 68",
    "sg:postcode":"8900",
    "sg:province":"West-Vlaanderen",
    "sg:tags":[
        "technical",
        "equipment",
        "offices-"
    ],
    "wof:name":"Assitec Bvba",
    "wof:placetype":"venue"
},
  "geometry": {"coordinates":[2.884018898,50.8554153442],"type":"Point"}
}