{
  "type": "Feature",
  "properties": {
    "addr:full":"A. Ruzettelaan 37a Blankenberge West-Vlaanderen 8370",
    "addr:housenumber":"37a",
    "addr:postcode":"8370",
    "addr:street":"A. Ruzettelaan",
    "iso:country":"BE",
    "sg:address":"A. Ruzettelaan 37a",
    "sg:city":"Blankenberge",
    "sg:classifiers":[
        {
            "category":"Travel",
            "subcategory":"Hotels & Motels",
            "type":"Entertainment"
        }
    ],
    "sg:phone":"+32 50 42 94 28",
    "sg:postcode":"8370",
    "sg:province":"West-Vlaanderen",
    "wof:name":"La Temp\u00eate",
    "wof:placetype":"venue"
},
  "geometry": {"coordinates":[3.1384820938,51.3175430298],"type":"Point"}
}