{
  "type": "Feature",
  "properties": {
    "iso:country":"BE",
    "sg:address":"Kruineikestraat 25",
    "sg:city":"Haacht",
    "sg:orig_category":"Banken and kredietinstellingen",
    "sg:phone":"+32 16 60 42 48",
    "sg:postcode":"3150",
    "sg:province":"Vlaams-Brabant",
    "wof:name":"Fortis",
    "wof:placetype":"venue"
},
  "geometry": {"coordinates":[4.644288063,50.9461364746],"type":"Point"}
}