{
  "type": "Feature",
  "properties": {
    "addr:full":"Au Long Pr\u00c9 124 Embourg Li\u00e8ge 4053",
    "addr:housenumber":"124",
    "addr:postcode":"4053",
    "addr:street":"Long Pre\u0301",
    "iso:country":"BE",
    "sg:address":"Au Long Pr\u00c9 124",
    "sg:city":"Embourg",
    "sg:orig_category":"Services de Nettoyage and de D\u00e9sinfection",
    "sg:phone":"+32 475 70 38 90",
    "sg:postcode":"4053",
    "sg:province":"Li\u00e8ge",
    "wof:name":"Revica",
    "wof:placetype":"venue"
},
  "geometry": {"coordinates":[5.6244320869,50.5943565369],"type":"Point"}
}