{
  "type": "Feature",
  "properties": {
    "addr:full":"Rue Des Chanvi\u00e8res 26 Habay (anlier) Luxembourg 6721",
    "addr:housenumber":"26",
    "addr:postcode":"6721",
    "addr:street":"Rue Des Chanvie\u0300Res",
    "iso:country":"BE",
    "sg:address":"Rue Des Chanvi\u00e8res 26",
    "sg:city":"Habay (anlier)",
    "sg:classifiers":[
        {
            "category":"Health Services",
            "subcategory":"Doctor",
            "type":"Services"
        }
    ],
    "sg:phone":"+32 63 42 49 22",
    "sg:postcode":"6721",
    "sg:province":"Luxembourg",
    "sg:tags":[
        "medicinephysicians",
        "surgeon"
    ],
    "wof:name":"Folie Thierry",
    "wof:placetype":"venue"
},
  "geometry": {"coordinates":[5.6207308769,49.772605896],"type":"Point"}
}