{
  "type": "Feature",
  "properties": {
    "addr:full":"Oude Zandstraat 37 Beveren Oost-Vlaanderen 9120",
    "addr:housenumber":"37",
    "addr:postcode":"9120",
    "addr:street":"Oude Zandstraat",
    "iso:country":"BE",
    "sg:address":"Oude Zandstraat 37",
    "sg:city":"Beveren",
    "sg:orig_category":"Pharmaciens",
    "sg:phone":"+32 3 775 44 52",
    "sg:postcode":"9120",
    "sg:province":"Oost-Vlaanderen",
    "wof:name":"Timmermans",
    "wof:placetype":"venue"
},
  "geometry": {"coordinates":[4.2533750534,51.211681366],"type":"Point"}
}