{
  "type": "Feature",
  "properties": {
    "addr:full":"Kolveniersvest 32 Lier Antwerpen 2500",
    "addr:housenumber":"32",
    "addr:postcode":"2500",
    "addr:street":"Kolveniersvest",
    "iso:country":"BE",
    "sg:address":"Kolveniersvest 32",
    "sg:city":"Lier",
    "sg:classifiers":[
        {
            "category":"Restaurant",
            "type":"Food & Drink"
        }
    ],
    "sg:phone":"+32 3 488 14 44",
    "sg:postcode":"2500",
    "sg:province":"Antwerpen",
    "wof:name":"Sari-sari",
    "wof:placetype":"venue"
},
  "geometry": {"coordinates":[4.5667600632,51.1325874329],"type":"Point"}
}