{
  "type": "Feature",
  "properties": {
    "iso:country":"BE",
    "sg:address":"Truweelstraat 146",
    "sg:city":"Sint-niklaas",
    "sg:classifiers":[
        {
            "category":"Cafe",
            "type":"Food & Drink"
        }
    ],
    "sg:phone":"+32 3 776 45 25",
    "sg:postcode":"9100",
    "sg:province":"Oost-Vlaanderen",
    "sg:tags":[
        "caf\u00e9s"
    ],
    "wof:name":"Parochiehuis Familia",
    "wof:placetype":"venue"
},
  "geometry": {"coordinates":[4.1504979134,51.171787262],"type":"Point"}
}