{
  "type": "Feature",
  "properties": {
    "iso:country":"BE",
    "sg:address":"Nijverheidsweg 3",
    "sg:city":"Rijkevorsel",
    "sg:classifiers":[
        {
            "category":"Building & Trades",
            "subcategory":"Cleaning & Sanitation",
            "type":"Services"
        }
    ],
    "sg:phone":"+32 3 314 78 24",
    "sg:postcode":"2310",
    "sg:province":"Antwerpen",
    "sg:tags":[
        "equipment",
        "industrial",
        "maintenance"
    ],
    "wof:name":"Gerrik Nv",
    "wof:placetype":"venue"
},
  "geometry": {"coordinates":[4.7376699448,51.3323516846],"type":"Point"}
}