{
  "type": "Feature",
  "properties": {
    "iso:country":"BE",
    "sg:address":"Godevaert Braemstraat 26",
    "sg:city":"Temse (elversele)",
    "sg:classifiers":[
        {
            "category":"Health Services",
            "subcategory":"Medical Lab",
            "type":"Services"
        }
    ],
    "sg:phone":"+32 52 46 00 63",
    "sg:postcode":"9140",
    "sg:province":"Oost-Vlaanderen",
    "sg:tags":[
        "laboratory",
        "dental"
    ],
    "wof:name":"Orthodontisch Labo Brys-callewaert Bvba",
    "wof:placetype":"venue"
},
  "geometry": {"coordinates":[4.1405901909,51.1142692566],"type":"Point"}
}