{
  "type": "Feature",
  "properties": {
    "addr:full":"Buis 28 Ellezelles (wodecq) Hainaut 7890",
    "addr:housenumber":"28",
    "addr:postcode":"7890",
    "addr:street":"Buis",
    "iso:country":"BE",
    "sg:address":"Buis 28",
    "sg:city":"Ellezelles (wodecq)",
    "sg:classifiers":[
        {
            "category":"Farming",
            "subcategory":"Farm & Veterinary Services",
            "type":"Manufacturing & Wholesale Goods"
        }
    ],
    "sg:phone":"+32 68 44 72 84",
    "sg:postcode":"7890",
    "sg:province":"Hainaut",
    "sg:tags":[
        "agricultural",
        "contractor"
    ],
    "wof:name":"Veys Gilbert & Fils",
    "wof:placetype":"venue"
},
  "geometry": {"coordinates":[3.7385380268,50.7090873718],"type":"Point"}
}