{
  "type": "Feature",
  "properties": {
    "addr:full":"Chauss\u00e9e De Renaix 15 Lessines Hainaut 7860",
    "addr:housenumber":"15",
    "addr:postcode":"7860",
    "addr:street":"Chausse\u0301E De Renaix;Hainaut",
    "iso:country":"BE",
    "sg:address":"Chauss\u00e9e De Renaix 15",
    "sg:city":"Lessines",
    "sg:classifiers":[
        {
            "category":"Retail",
            "subcategory":"Auto Repair",
            "type":"Services"
        }
    ],
    "sg:phone":"+32 68 33 25 55",
    "sg:postcode":"7860",
    "sg:province":"Hainaut",
    "sg:tags":[
        "garage"
    ],
    "wof:name":"Midula (garage)",
    "wof:placetype":"venue"
},
  "geometry": {"coordinates":[3.8239550591,50.712474823],"type":"Point"}
}