{
  "type": "Feature",
  "properties": {
    "iso:country":"BE",
    "sg:address":"Rue Saint-gilles 576",
    "sg:city":"Li\u00e8ge 1",
    "sg:classifiers":[
        {
            "category":"Shopping",
            "subcategory":"Computers & Home Electronics",
            "type":"Retail Goods"
        }
    ],
    "sg:phone":"+32 4 253 43 12",
    "sg:postcode":"4000",
    "sg:province":"Li\u00e8ge",
    "sg:tags":[
        "-",
        "television",
        "radio"
    ],
    "wof:name":"Blaupunkt-groeven",
    "wof:placetype":"venue"
},
  "geometry": {"coordinates":[5.5479698181,50.6330184937],"type":"Point"}
}