{
  "type": "Feature",
  "properties": {
    "iso:country":"BE",
    "sg:address":"Ruiffeleindestraat 12",
    "sg:city":"Zwevegem",
    "sg:orig_category":"Pluimveekwekers",
    "sg:phone":"+32 56 64 49 12",
    "sg:postcode":"8553",
    "sg:province":"West-Vlaanderen",
    "wof:name":"Joseph Verhoest",
    "wof:placetype":"venue"
},
  "geometry": {"coordinates":[3.4504458904,50.7947616577],"type":"Point"}
}