{
  "type": "Feature",
  "properties": {
    "iso:country":"BE",
    "sg:address":"Avenue Charles Woeste 257",
    "sg:city":"Bruxelles (jette)",
    "sg:classifiers":[
        {
            "category":"Health Services",
            "subcategory":"Health Practitioner",
            "type":"Services"
        }
    ],
    "sg:phone":"+32 2 427 17 70",
    "sg:postcode":"1090",
    "sg:province":"Bruxelles-Capitale",
    "sg:tags":[
        "physiotherapist"
    ],
    "wof:name":"Baetens Marc",
    "wof:placetype":"venue"
},
  "geometry": {"coordinates":[4.3345618248,50.8703422546],"type":"Point"}
}