{
  "type": "Feature",
  "properties": {
    "addr:full":"Fort V-straat 12-14 Edegem Antwerpen 2650",
    "addr:postcode":"12-14;2650",
    "addr:street":"V-Straat",
    "iso:country":"BE",
    "sg:address":"Fort V-straat 12-14",
    "sg:city":"Edegem",
    "sg:classifiers":[
        {
            "category":"Banks & Credit Unions",
            "subcategory":"Investment Brokerage",
            "type":"Services"
        }
    ],
    "sg:phone":"+32 3 449 96 74",
    "sg:postcode":"2650",
    "sg:province":"Antwerpen",
    "sg:tags":[
        "raw",
        "stone",
        "material",
        "natural",
        "energy"
    ],
    "wof:name":"Deco Stone Bvba",
    "wof:placetype":"venue"
},
  "geometry": {"coordinates":[4.433218956,51.1717567444],"type":"Point"}
}