{
  "type": "Feature",
  "properties": {
    "iso:country":"BE",
    "sg:address":"Stationsplein 12",
    "sg:city":"Aalst",
    "sg:orig_category":"Mutualities",
    "sg:phone":"+32 78 15 23 10",
    "sg:postcode":"9300",
    "sg:province":"Oost-Vlaanderen",
    "wof:name":"Hospiplan - Hospiplus",
    "wof:placetype":"venue"
},
  "geometry": {"coordinates":[4.0373649597,50.9418144226],"type":"Point"}
}