{
  "type": "Feature",
  "properties": {
    "addr:full":"De Pintelaan 49 Gent Oost-Vlaanderen 9000",
    "addr:housenumber":"49",
    "addr:postcode":"9000",
    "addr:street":"Pintelaan;Oost-Vlaanderen",
    "iso:country":"BE",
    "sg:address":"De Pintelaan 49",
    "sg:city":"Gent",
    "sg:orig_category":"Sportclubs",
    "sg:phone":"+32 9 220 55 06",
    "sg:postcode":"9000",
    "sg:province":"Oost-Vlaanderen",
    "wof:name":"Gentbrugse Zwalmvrienden",
    "wof:placetype":"venue"
},
  "geometry": {"coordinates":[3.7276890278,51.0293655396],"type":"Point"}
}