{
  "type": "Feature",
  "properties": {
    "addr:full":"Plantin En Moretuslei 75 Antwerpen Antwerpen 2018",
    "addr:housenumber":"75",
    "addr:postcode":"2018",
    "addr:street":"Plantin En Moretuslei",
    "iso:country":"BE",
    "sg:address":"Plantin En Moretuslei 75",
    "sg:city":"Antwerpen",
    "sg:classifiers":[
        {
            "category":"Communications",
            "type":"Services"
        }
    ],
    "sg:phone":"+32 3 232 33 12",
    "sg:postcode":"2018",
    "sg:province":"Antwerpen",
    "sg:tags":[
        "translator"
    ],
    "wof:name":"Theys",
    "wof:placetype":"venue"
},
  "geometry": {"coordinates":[4.4247097969,51.2107391357],"type":"Point"}
}