{
  "type": "Feature",
  "properties": {
    "addr:full":"Burg-reuland 135 Burg-reuland/burg-reuland Li\u00e8ge 4790",
    "addr:housenumber":"135;/",
    "addr:postcode":"4790",
    "addr:street":"Burg-Reuland",
    "iso:country":"BE",
    "sg:address":"Burg-reuland 135",
    "sg:city":"Burg-reuland/burg-reuland",
    "sg:orig_category":"Musea and historische gebouwen",
    "sg:phone":"+32 80 32 97 12",
    "sg:postcode":"4790",
    "sg:province":"Li\u00e8ge",
    "wof:name":"Mus\u00c9e Paul Gerardy",
    "wof:placetype":"venue"
},
  "geometry": {"coordinates":[6.1354999542,50.1952514648],"type":"Point"}
}