{
  "type": "Feature",
  "properties": {
    "iso:country":"BE",
    "sg:address":"Lar 4p",
    "sg:city":"Menen (rekkem)",
    "sg:classifiers":[
        {
            "category":"Professional",
            "subcategory":"Management & Consulting",
            "type":"Services"
        }
    ],
    "sg:phone":"+32 56 40 35 28",
    "sg:postcode":"8930",
    "sg:province":"West-Vlaanderen",
    "sg:tags":[
        "tax-consultants"
    ],
    "wof:name":"Verhamme W",
    "wof:placetype":"venue"
},
  "geometry": {"coordinates":[3.1943130493,50.7747154236],"type":"Point"}
}