{
  "type": "Feature",
  "properties": {
    "iso:country":"BE",
    "sg:address":"Industrielaan 23",
    "sg:city":"Hoeselt",
    "sg:classifiers":[
        {
            "category":"Utilities",
            "subcategory":"Fuel Oil & Lpg",
            "type":"Services"
        }
    ],
    "sg:phone":"+32 89 41 43 94",
    "sg:postcode":"3730",
    "sg:province":"Limburg",
    "wof:name":"Baillieux",
    "wof:placetype":"venue"
},
  "geometry": {"coordinates":[5.4894781113,50.8582725525],"type":"Point"}
}