{
  "type": "Feature",
  "properties": {
    "iso:country":"BE",
    "sg:address":"Bremdreef 13",
    "sg:city":"Schoten",
    "sg:classifiers":[
        {
            "category":"Professional",
            "subcategory":"Engineering",
            "type":"Services"
        }
    ],
    "sg:phone":"+32 3 685 12 70",
    "sg:postcode":"2900",
    "sg:province":"Antwerpen",
    "sg:tags":[
        "-"
    ],
    "wof:name":"Technic Design",
    "wof:placetype":"venue"
},
  "geometry": {"coordinates":[4.522977829,51.2691764832],"type":"Point"}
}