{
  "type": "Feature",
  "properties": {
    "iso:country":"BE",
    "sg:address":"Pr\u00e9 Du Fa 6",
    "sg:city":"Ferri\u00e8res",
    "sg:classifiers":[
        {
            "category":"Arena",
            "subcategory":"Sports Club",
            "type":"Entertainment"
        }
    ],
    "sg:phone":"+32 86 40 01 29",
    "sg:postcode":"4190",
    "sg:province":"Li\u00e8ge",
    "wof:name":"R U S Ferri\u00e8re Football",
    "wof:placetype":"venue"
},
  "geometry": {"coordinates":[5.609131813,50.3983612061],"type":"Point"}
}