{
  "type": "Feature",
  "properties": {
    "addr:full":"Kapelstraat 57 Hamont-achel (hamont) Limburg 3930",
    "addr:housenumber":"57",
    "addr:postcode":"3930",
    "addr:street":"Kapelstraat",
    "iso:country":"BE",
    "sg:address":"Kapelstraat 57",
    "sg:city":"Hamont-achel (hamont)",
    "sg:classifiers":[
        {
            "category":"Building & Trades",
            "subcategory":"Electrical",
            "type":"Services"
        }
    ],
    "sg:phone":"+32 11 44 59 51",
    "sg:postcode":"3930",
    "sg:province":"Limburg",
    "sg:tags":[
        "electric",
        "-",
        "housewiring",
        "contractor"
    ],
    "wof:name":"Cardinaels Elektrotechniek",
    "wof:placetype":"venue"
},
  "geometry": {"coordinates":[5.5450549126,51.2511863708],"type":"Point"}
}