{
  "type": "Feature",
  "properties": {
    "iso:country":"BE",
    "sg:address":"Avenue Nandrin 18",
    "sg:city":"Esneux",
    "sg:orig_category":"R\u00e9alisation de programmes and logiciels. Conseils en syst\u00e8mes informatiques. Ordinateurs and \u00e9quipem",
    "sg:phone":"+32 4 380 48 29",
    "sg:postcode":"4130",
    "sg:province":"Li\u00e8ge",
    "wof:name":"Toussaint Informatique",
    "wof:placetype":"venue"
},
  "geometry": {"coordinates":[5.5765910149,50.5440444946],"type":"Point"}
}