{
  "type": "Feature",
  "properties": {
    "addr:full":"Hooibosstraat 8 Tienen (goetsenhoven) Vlaams-Brabant 3300",
    "addr:housenumber":"8",
    "addr:postcode":"3300",
    "addr:street":"Hooibosstraat",
    "iso:country":"BE",
    "sg:address":"Hooibosstraat 8",
    "sg:city":"Tienen (goetsenhoven)",
    "sg:classifiers":[
        {
            "category":"Health Services",
            "subcategory":"Health Practitioner",
            "type":"Services"
        }
    ],
    "sg:phone":"+32 16 78 03 93",
    "sg:postcode":"3300",
    "sg:province":"Vlaams-Brabant",
    "sg:tags":[
        "physiotherapist"
    ],
    "wof:name":"Hubrechts K",
    "wof:placetype":"venue"
},
  "geometry": {"coordinates":[4.930077076,50.8096694946],"type":"Point"}
}