{
  "type": "Feature",
  "properties": {
    "addr:full":"Gangstraat 20 Elsene/ixelles Bruxelles-Capitale 1050",
    "addr:housenumber":"20",
    "addr:postcode":"1050",
    "addr:street":"Gangstraat",
    "iso:country":"BE",
    "sg:address":"Gangstraat 20",
    "sg:city":"Elsene/ixelles",
    "sg:orig_category":"Bouwmaterialen Gh IJzerwaren, bouw- and verfmaterialen Loodgieterij and centrale verwarming Gh",
    "sg:phone":"+32 2 647 99 25",
    "sg:postcode":"1050",
    "sg:province":"Bruxelles-Capitale",
    "wof:name":"Facq",
    "wof:placetype":"venue"
},
  "geometry": {"coordinates":[4.3706140518,50.8299713135],"type":"Point"}
}