{
  "type": "Feature",
  "properties": {
    "iso:country":"BE",
    "sg:address":"Rue Jean Manne",
    "sg:city":"Ghlin",
    "sg:orig_category":"Royal Canin Zuivelproducten",
    "sg:phone":"+32 65 31 42 06",
    "sg:postcode":"7011",
    "sg:province":"Hainaut",
    "wof:name":"Association Dupont-marechal",
    "wof:placetype":"venue"
},
  "geometry": {"coordinates":[3.8969249725,50.4754905701],"type":"Point"}
}