{
  "type": "Feature",
  "properties": {
    "iso:country":"BE",
    "sg:address":"Boulevard Audent 8b6",
    "sg:city":"Charleroi",
    "sg:orig_category":"Avocats and conseillers juridiques",
    "sg:phone":"+32 71 32 97 91",
    "sg:postcode":"6000",
    "sg:province":"Hainaut",
    "wof:name":"Chr. Famerc\u00c9e",
    "wof:placetype":"venue"
},
  "geometry": {"coordinates":[4.4432730675,50.4098510742],"type":"Point"}
}