{
  "type": "Feature",
  "properties": {
    "iso:country":"BE",
    "sg:address":"Plein 63",
    "sg:city":"Kaprijke",
    "sg:orig_category":"Boucheries",
    "sg:phone":"+32 9 373 68 67",
    "sg:postcode":"9970",
    "sg:province":"Oost-Vlaanderen",
    "wof:name":"Willy Lacaeyse",
    "wof:placetype":"venue"
},
  "geometry": {"coordinates":[3.6207399368,51.2180519104],"type":"Point"}
}