{
  "type": "Feature",
  "properties": {
    "iso:country":"BE",
    "sg:address":"Chauss\u00c9e De Li\u00c8ge 19bb",
    "sg:city":"Welkenraedt/welkenraedt",
    "sg:orig_category":"Voertuigen",
    "sg:phone":"+32 87 88 16 79",
    "sg:postcode":"4841",
    "sg:province":"Li\u00e8ge",
    "wof:name":"H. Halleux",
    "wof:placetype":"venue"
},
  "geometry": {"coordinates":[5.9257369041,50.676158905],"type":"Point"}
}