{
  "type": "Feature",
  "properties": {
    "iso:country":"BE",
    "sg:address":"Rue Du Serpont 63",
    "sg:city":"Libramont-chevigny",
    "sg:orig_category":"D\u00e9taillants en pi\u00e8ces and accessoires de voitures",
    "sg:phone":"+32 61 22 44 81",
    "sg:postcode":"6800",
    "sg:province":"Luxembourg",
    "wof:name":"Copet Et Fils",
    "wof:placetype":"venue"
},
  "geometry": {"coordinates":[5.3761348724,49.9199943542],"type":"Point"}
}