{
  "type": "Feature",
  "properties": {
    "addr:full":"Adrien De Gerlachestraat 33 Edegem Antwerpen 2650",
    "addr:housenumber":"33",
    "addr:postcode":"2650",
    "addr:street":"Adrien De Gerlachestraat",
    "iso:country":"BE",
    "sg:address":"Adrien De Gerlachestraat 33",
    "sg:city":"Edegem",
    "sg:classifiers":[
        {
            "category":"Professional",
            "subcategory":"Engineering",
            "type":"Services"
        }
    ],
    "sg:phone":"+32 3 440 44 75",
    "sg:postcode":"2650",
    "sg:province":"Antwerpen",
    "sg:tags":[
        "environmental",
        "technique",
        "-"
    ],
    "wof:name":"F M Consultants Bvba",
    "wof:placetype":"venue"
},
  "geometry": {"coordinates":[4.4405851364,51.1674041748],"type":"Point"}
}