{
  "type": "Feature",
  "properties": {
    "addr:full":"Rue Haut-vin\u00c2ve 6 Seraing Li\u00e8ge 4101",
    "addr:housenumber":"6",
    "addr:postcode":"4101",
    "addr:street":"Rue Haut-Vina\u0302Ve",
    "iso:country":"BE",
    "sg:address":"Rue Haut-vin\u00c2ve 6",
    "sg:city":"Seraing",
    "sg:orig_category":"Drogisterijen IJzerwaren, bouw- and verfmaterialen Textiel Verlichting and huishoudartikelen",
    "sg:phone":"+32 4 234 07 89",
    "sg:postcode":"4101",
    "sg:province":"Li\u00e8ge",
    "wof:name":"Chephel Decor",
    "wof:placetype":"venue"
},
  "geometry": {"coordinates":[5.504196167,50.6159744263],"type":"Point"}
}