{
  "type": "Feature",
  "properties": {
    "iso:country":"BE",
    "sg:address":"Krinkelt 118",
    "sg:city":"B\u00fcllingen (rocherath)",
    "sg:classifiers":[
        {
            "category":"Professional",
            "subcategory":"Management & Consulting",
            "type":"Services"
        }
    ],
    "sg:phone":"+32 80 64 78 74",
    "sg:postcode":"4761",
    "sg:province":"Li\u00e8ge",
    "sg:tags":[
        "consultant",
        "law"
    ],
    "wof:name":"K\u00fcpper A",
    "wof:placetype":"venue"
},
  "geometry": {"coordinates":[6.2963399887,50.4319496155],"type":"Point"}
}