{
  "type": "Feature",
  "properties": {
    "addr:full":"Rue Sart Colin 108 Brunehaut Hainaut 7622",
    "addr:housenumber":"108",
    "addr:postcode":"7622",
    "addr:street":"Rue Sart Colin;Hainaut",
    "iso:country":"BE",
    "sg:address":"Rue Sart Colin 108",
    "sg:city":"Brunehaut",
    "sg:orig_category":"Slagers",
    "sg:phone":"+32 69 34 48 70",
    "sg:postcode":"7622",
    "sg:province":"Hainaut",
    "wof:name":"Christian Devillers",
    "wof:placetype":"venue"
},
  "geometry": {"coordinates":[3.4469599724,50.5208015442],"type":"Point"}
}