{
  "type": "Feature",
  "properties": {
    "iso:country":"BE",
    "sg:address":"Schansstraat 12",
    "sg:city":"Zutendaal",
    "sg:classifiers":[
        {
            "category":"Arena",
            "subcategory":"Sports Club",
            "type":"Entertainment"
        }
    ],
    "sg:phone":"+32 11 68 52 21",
    "sg:postcode":"3601",
    "sg:tags":[
        "de"
    ],
    "wof:name":"Deltaclub The Falcons",
    "wof:placetype":"venue"
},
  "geometry": {"coordinates":[5.5889539719,50.9163322449],"type":"Point"}
}