{
  "type": "Feature",
  "properties": {
    "addr:full":"Rue Des Aduatiques 49 Bruxelles (etterbeek) Bruxelles-Capitale 1040",
    "addr:housenumber":"49",
    "addr:postcode":"1040",
    "addr:street":"Rue Des Aduatiques",
    "iso:country":"BE",
    "sg:address":"Rue Des Aduatiques 49",
    "sg:city":"Bruxelles (etterbeek)",
    "sg:orig_category":"Non-Classified Establishments",
    "sg:phone":"+32 2 736 51 65",
    "sg:postcode":"1040",
    "sg:province":"Bruxelles-Capitale",
    "wof:name":"Didden Eclairage Sprl",
    "wof:placetype":"venue"
},
  "geometry": {"coordinates":[4.402408123,50.837310791],"type":"Point"}
}