{
  "type": "Feature",
  "properties": {
    "addr:full":"Torrestraat 36-38 Wevelgem (gullegem) West-Vlaanderen 8560",
    "addr:postcode":"36-38;8560",
    "addr:street":"Torrestraat",
    "iso:country":"BE",
    "sg:address":"Torrestraat 36-38",
    "sg:city":"Wevelgem (gullegem)",
    "sg:classifiers":[
        {
            "category":"Building & Trades",
            "subcategory":"Electrical",
            "type":"Services"
        }
    ],
    "sg:phone":"+32 56 35 40 36",
    "sg:postcode":"8560",
    "sg:province":"West-Vlaanderen",
    "sg:tags":[
        "electric",
        "-",
        "housewiring",
        "contractor"
    ],
    "wof:name":"Vandeghinste S",
    "wof:placetype":"venue"
},
  "geometry": {"coordinates":[3.2197449207,50.8485031128],"type":"Point"}
}