{
  "type": "Feature",
  "properties": {
    "iso:country":"BE",
    "sg:address":"Rue De La Gare 51",
    "sg:city":"Spiere-helkijn/espierres-helchin",
    "sg:classifiers":[
        {
            "category":"Fast Food",
            "type":"Food & Drink"
        }
    ],
    "sg:phone":"+32 56 45 75 51",
    "sg:postcode":"8587",
    "sg:province":"West-Vlaanderen",
    "sg:tags":[
        "\u00c0",
        "restaurants",
        "emporter",
        "restaurant"
    ],
    "wof:name":"De Peirdeblomme",
    "wof:placetype":"venue"
},
  "geometry": {"coordinates":[3.3816399574,50.7372512817],"type":"Point"}
}