{
  "type": "Feature",
  "properties": {
    "addr:full":"Rue De La Vierge 7 Hotton Luxembourg 6990",
    "addr:housenumber":"7",
    "addr:postcode":"6990",
    "addr:street":"Rue De La Vierge",
    "iso:country":"BE",
    "sg:address":"Rue De La Vierge 7",
    "sg:city":"Hotton",
    "sg:classifiers":[
        {
            "category":"Restaurant",
            "type":"Food & Drink"
        }
    ],
    "sg:phone":"+32 84 46 76 27",
    "sg:postcode":"6990",
    "sg:province":"Luxembourg",
    "wof:name":"La Po\u00cal\u00c9e Du Terroir",
    "wof:placetype":"venue"
},
  "geometry": {"coordinates":[5.4918251038,50.2586936951],"type":"Point"}
}