{
  "type": "Feature",
  "properties": {
    "addr:full":"Chauss\u00e9e De Waterloo 1090 Bruxelles (uccle) Bruxelles-Capitale 1180",
    "addr:postcode":"1090;1180",
    "addr:street":"Chausse\u0301E De Waterloo",
    "iso:country":"BE",
    "sg:address":"Chauss\u00e9e De Waterloo 1090",
    "sg:city":"Bruxelles (uccle)",
    "sg:classifiers":[
        {
            "category":"Shopping",
            "subcategory":"Clothing, Apparel, & Fashions",
            "type":"Retail Goods"
        }
    ],
    "sg:phone":"+32 2 374 18 99",
    "sg:postcode":"1180",
    "sg:province":"Bruxelles-Capitale",
    "sg:tags":[
        "boutique"
    ],
    "wof:name":"Nicole Cadine",
    "wof:placetype":"venue"
},
  "geometry": {"coordinates":[4.375480175,50.7978591919],"type":"Point"}
}