{
  "type": "Feature",
  "properties": {
    "iso:country":"BE",
    "sg:address":"Beekmeersstraat 9",
    "sg:city":"Zwalm",
    "sg:orig_category":"Decoratieve kunst and kunstbenodigdheden Zalen voor culturele evenementen",
    "sg:phone":"+32 55 49 79 89",
    "sg:postcode":"9636",
    "sg:province":"Oost-Vlaanderen",
    "wof:name":"Galerij Hof Ten Doeyer",
    "wof:placetype":"venue"
},
  "geometry": {"coordinates":[3.6956319809,50.8950271606],"type":"Point"}
}