{
  "type": "Feature",
  "properties": {
    "addr:full":"Steenbakkersstraat 1 Oostende West-Vlaanderen 8400",
    "addr:housenumber":"1",
    "addr:postcode":"8400",
    "addr:street":"Steenbakkersstraat",
    "iso:country":"BE",
    "sg:address":"Steenbakkersstraat 1",
    "sg:city":"Oostende",
    "sg:classifiers":[
        {
            "category":"Bakery",
            "type":"Food & Drink"
        }
    ],
    "sg:phone":"+32 59 70 79 48",
    "sg:postcode":"8400",
    "sg:province":"West-Vlaanderen",
    "sg:tags":[
        "confectioner",
        "baker"
    ],
    "wof:name":"Sylvester",
    "wof:placetype":"venue"
},
  "geometry": {"coordinates":[2.90320611,51.2216835022],"type":"Point"}
}