{
  "type": "Feature",
  "properties": {
    "addr:full":"Steenstraat 64ba Kortemark West-Vlaanderen 8610",
    "addr:housenumber":"64ba",
    "addr:postcode":"8610",
    "addr:street":"Steenstraat",
    "iso:country":"BE",
    "sg:address":"Steenstraat 64ba",
    "sg:city":"Kortemark",
    "sg:orig_category":"Eleveurs de bovins",
    "sg:phone":"+32 51 56 76 13",
    "sg:postcode":"8610",
    "sg:province":"West-Vlaanderen",
    "wof:name":"Noel Embo",
    "wof:placetype":"venue"
},
  "geometry": {"coordinates":[2.9794080257,51.044593811],"type":"Point"}
}