{
  "type": "Feature",
  "properties": {
    "iso:country":"BE",
    "sg:address":"Rue De Genleau 72",
    "sg:city":"Lasne (lasne-chapelle-saint-lambert)",
    "sg:classifiers":[
        {
            "category":"Professional",
            "subcategory":"Management & Consulting",
            "type":"Services"
        }
    ],
    "sg:phone":"+32 2 633 40 86",
    "sg:postcode":"1380",
    "sg:province":"Brabant Wallon",
    "sg:tags":[
        "consultant",
        "agency",
        "advertising"
    ],
    "wof:name":"M.b. Factory Sprl",
    "wof:placetype":"venue"
},
  "geometry": {"coordinates":[4.4640250206,50.6854248047],"type":"Point"}
}