{
  "type": "Feature",
  "properties": {
    "addr:full":"Rue De La Balance 14 Philippeville Namur 5600",
    "addr:housenumber":"14",
    "addr:postcode":"5600",
    "addr:street":"Rue De La Balance",
    "iso:country":"BE",
    "sg:address":"Rue De La Balance 14",
    "sg:city":"Philippeville",
    "sg:orig_category":"Instituts de beaut\u00e9. Centres de relaxation and bien-\u00eatre",
    "sg:phone":"+32 71 66 72 10",
    "sg:postcode":"5600",
    "sg:province":"Namur",
    "wof:name":"Centre Josiane M.",
    "wof:placetype":"venue"
},
  "geometry": {"coordinates":[4.5416817665,50.1964836121],"type":"Point"}
}