{
  "type": "Feature",
  "properties": {
    "addr:full":"Puttestraat 2 Tielt-winge Vlaams-Brabant 3390",
    "addr:housenumber":"2",
    "addr:postcode":"3390",
    "addr:street":"Puttestraat",
    "iso:country":"BE",
    "sg:address":"Puttestraat 2",
    "sg:city":"Tielt-winge",
    "sg:orig_category":"Brood, gebak and snoepgoed",
    "sg:phone":"+32 16 63 52 25",
    "sg:postcode":"3390",
    "sg:province":"Vlaams-Brabant",
    "wof:name":"Vandervelpen-lemmens",
    "wof:placetype":"venue"
},
  "geometry": {"coordinates":[4.9160299301,50.9198303223],"type":"Point"}
}