{
  "type": "Feature",
  "properties": {
    "iso:country":"BE",
    "sg:address":"Boomgaard 16",
    "sg:city":"Aalter",
    "sg:classifiers":[
        {
            "category":"Professional",
            "subcategory":"Computer Services",
            "type":"Services"
        }
    ],
    "sg:phone":"+32 9 374 68 43",
    "sg:postcode":"9880",
    "sg:province":"Oost-Vlaanderen",
    "sg:tags":[
        "microsoft"
    ],
    "wof:name":"Standaard Boekhandel Aalter",
    "wof:placetype":"venue"
},
  "geometry": {"coordinates":[3.4482369423,51.0855636597],"type":"Point"}
}