{
  "type": "Feature",
  "properties": {
    "iso:country":"BE",
    "sg:address":"Wijtschotbaan 1",
    "sg:city":"Schoten",
    "sg:orig_category":"Flongs",
    "sg:phone":"+32 3 828 64 96",
    "sg:postcode":"2900",
    "sg:province":"Antwerpen",
    "wof:name":"Modelmakerij G. De Feyter Nv",
    "wof:placetype":"venue"
},
  "geometry": {"coordinates":[4.3378601074,51.177280426],"type":"Point"}
}