{
  "type": "Feature",
  "properties": {
    "addr:full":"Keiweg 6 Zonnebeke West-Vlaanderen 8980",
    "addr:housenumber":"6",
    "addr:postcode":"8980",
    "addr:street":"Keiweg",
    "iso:country":"BE",
    "sg:address":"Keiweg 6",
    "sg:city":"Zonnebeke",
    "sg:orig_category":"Agences de presse",
    "sg:phone":"+32 57 46 84 61",
    "sg:postcode":"8980",
    "sg:province":"West-Vlaanderen",
    "wof:name":"Christian Vandenabeele",
    "wof:placetype":"venue"
},
  "geometry": {"coordinates":[2.9819068909,50.8293418884],"type":"Point"}
}