{
  "type": "Feature",
  "properties": {
    "iso:country":"BE",
    "sg:address":"Markt 14",
    "sg:city":"Scherpenheuvel-zichem (zichem)",
    "sg:classifiers":[
        {
            "category":"Health Services",
            "subcategory":"Health Practitioner",
            "type":"Services"
        }
    ],
    "sg:phone":"+32 13 77 18 26",
    "sg:postcode":"3271",
    "sg:province":"Vlaams-Brabant",
    "sg:tags":[
        "physiotherapist"
    ],
    "wof:name":"Distelmans Etjen",
    "wof:placetype":"venue"
},
  "geometry": {"coordinates":[4.987306118,51.0011367798],"type":"Point"}
}