{
  "type": "Feature",
  "properties": {
    "addr:full":"Palingstraat 24 Puurs Antwerpen 2870",
    "addr:housenumber":"24",
    "addr:postcode":"2870",
    "addr:street":"Palingstraat",
    "iso:country":"BE",
    "sg:address":"Palingstraat 24",
    "sg:city":"Puurs",
    "sg:classifiers":[
        {
            "category":"Professional",
            "subcategory":"Accounting & Tax Preparation",
            "type":"Services"
        }
    ],
    "sg:phone":"+32 3 889 90 00",
    "sg:postcode":"2870",
    "sg:province":"Antwerpen",
    "sg:tags":[
        "accountant"
    ],
    "wof:name":"Runaco Bvba",
    "wof:placetype":"venue"
},
  "geometry": {"coordinates":[4.2794241905,51.0743179321],"type":"Point"}
}