{
  "type": "Feature",
  "properties": {
    "addr:full":"Halloux 108 Limbourg Li\u00e8ge 4830",
    "addr:housenumber":"108",
    "addr:postcode":"4830",
    "iso:country":"BE",
    "sg:address":"Halloux 108",
    "sg:city":"Limbourg",
    "sg:classifiers":[
        {
            "category":"Structure",
            "subcategory":"Office Building",
            "type":"Public Place"
        }
    ],
    "sg:phone":"+32 87 76 20 25",
    "sg:postcode":"4830",
    "sg:province":"Li\u00e8ge",
    "sg:tags":[
        "drawing"
    ],
    "wof:name":"Willems F",
    "wof:placetype":"venue"
},
  "geometry": {"coordinates":[5.9315037727,50.5985641479],"type":"Point"}
}