{
  "type": "Feature",
  "properties": {
    "iso:country":"BE",
    "sg:address":"Rue Albert I 71",
    "sg:city":"Hannut",
    "sg:classifiers":[
        {
            "category":"Shopping",
            "subcategory":"Optician",
            "type":"Retail Goods"
        }
    ],
    "sg:phone":"+32 19 51 38 04",
    "sg:postcode":"4280",
    "sg:province":"Li\u00e8ge",
    "sg:tags":[
        "-"
    ],
    "wof:name":"Lebrun M-p",
    "wof:placetype":"venue"
},
  "geometry": {"coordinates":[5.0826420784,50.6693534851],"type":"Point"}
}