{
  "type": "Feature",
  "properties": {
    "addr:full":"Oostrozebekestraat 305 Meulebeke West-Vlaanderen 8760",
    "addr:housenumber":"305",
    "addr:postcode":"8760",
    "addr:street":"Oostrozebekestraat",
    "iso:country":"BE",
    "sg:address":"Oostrozebekestraat 305",
    "sg:city":"Meulebeke",
    "sg:orig_category":"Installatie van houten of kunststof schrijnwerk MEUBELONTWERP AND -INSTALLATIE",
    "sg:phone":"+32 56 66 70 36",
    "sg:postcode":"8760",
    "sg:province":"West-Vlaanderen",
    "wof:name":"Descheemaeker R",
    "wof:placetype":"venue"
},
  "geometry": {"coordinates":[3.3140978813,50.9310264587],"type":"Point"}
}