{
  "type": "Feature",
  "properties": {
    "addr:full":"Noorderlaan 133 Antwerpen Antwerpen 2030",
    "addr:housenumber":"133",
    "addr:postcode":"2030",
    "addr:street":"Noorderlaan",
    "iso:country":"BE",
    "sg:address":"Noorderlaan 133",
    "sg:city":"Antwerpen",
    "sg:classifiers":[
        {
            "category":"Professional",
            "type":"Services"
        }
    ],
    "sg:phone":"+32 3 540 08 00",
    "sg:postcode":"2030",
    "sg:province":"Antwerpen",
    "sg:tags":[
        "forwarding",
        "agency"
    ],
    "wof:name":"Panalpina World Transport Nv",
    "wof:placetype":"venue"
},
  "geometry": {"coordinates":[4.402130127,51.2644462585],"type":"Point"}
}