{
  "type": "Feature",
  "properties": {
    "iso:country":"BE",
    "sg:address":"Rue Du Grand-babin 42",
    "sg:city":"Namur",
    "sg:orig_category":"M\u00e9decins and sp\u00e9cialistes",
    "sg:phone":"+32 81 44 45 31",
    "sg:postcode":"5020",
    "sg:province":"Namur",
    "wof:name":"M. Mingeot",
    "wof:placetype":"venue"
},
  "geometry": {"coordinates":[4.7952418327,50.4352035522],"type":"Point"}
}