{
  "type": "Feature",
  "properties": {
    "iso:country":"BE",
    "sg:address":"Chauss\u00c9e De Jette 545",
    "sg:city":"Jette/jette",
    "sg:orig_category":"Entretien and r\u00e9parations de voitures",
    "sg:phone":"+32 2 428 42 08",
    "sg:postcode":"1090",
    "sg:province":"Bruxelles-Capitale",
    "wof:name":"Garage Du Miroir",
    "wof:placetype":"venue"
},
  "geometry": {"coordinates":[4.3274440765,50.8700256348],"type":"Point"}
}