{
  "type": "Feature",
  "properties": {
    "addr:full":"Hoogstraat 33 Denderbelle Oost-Vlaanderen 9280",
    "addr:housenumber":"33",
    "addr:postcode":"9280",
    "addr:street":"Hoogstraat;Oost-Vlaanderen",
    "iso:country":"BE",
    "sg:address":"Hoogstraat 33",
    "sg:city":"Denderbelle",
    "sg:orig_category":"R\u00e9cup\u00e9ration de mati\u00e8res m\u00e9talliques recyclables and d\u00e9molisseurs de voitures. Entretien et r\u00e9parati",
    "sg:phone":"+32 53 78 83 03",
    "sg:postcode":"9280",
    "sg:province":"Oost-Vlaanderen",
    "wof:name":"Van Rossem",
    "wof:placetype":"venue"
},
  "geometry": {"coordinates":[4.0916819572,50.98777771],"type":"Point"}
}