{
  "type": "Feature",
  "properties": {
    "iso:country":"BE",
    "sg:address":"De Leonaerdtslaan 24",
    "sg:city":"Hamont-achel",
    "sg:orig_category":"Plomberie, chauffage and installations sanitaires",
    "sg:phone":"+32 11 64 46 27",
    "sg:postcode":"3930",
    "sg:province":"Limburg",
    "wof:name":"Joannes Heynen",
    "wof:placetype":"venue"
},
  "geometry": {"coordinates":[5.4831709862,51.251663208],"type":"Point"}
}