{
  "type": "Feature",
  "properties": {
    "addr:full":"Kerkelare 21 Lovendegem Oost-Vlaanderen 9920",
    "addr:housenumber":"21",
    "addr:postcode":"9920",
    "addr:street":"Kerkelare",
    "iso:country":"BE",
    "sg:address":"Kerkelare 21",
    "sg:city":"Lovendegem",
    "sg:orig_category":"Maisons de repos and r\u00e9sidences",
    "sg:phone":"+32 9 372 82 20",
    "sg:postcode":"9920",
    "sg:province":"Oost-Vlaanderen",
    "wof:name":"Rusthuis Kerkelare",
    "wof:placetype":"venue"
},
  "geometry": {"coordinates":[3.6072371006,51.0934295654],"type":"Point"}
}