{
  "type": "Feature",
  "properties": {
    "addr:full":"Rue Nouvelle Route 46 Engis Li\u00e8ge 4480",
    "addr:postcode":"4480",
    "addr:street":"Rue Nouvelle Route 46",
    "iso:country":"BE",
    "sg:address":"Rue Nouvelle Route 46",
    "sg:city":"Engis",
    "sg:orig_category":"M\u00e9decins and sp\u00e9cialistes",
    "sg:phone":"+32 4 275 59 45",
    "sg:postcode":"4480",
    "sg:province":"Li\u00e8ge",
    "wof:name":"Annick Bourguignon",
    "wof:placetype":"venue"
},
  "geometry": {"coordinates":[5.3995819092,50.583694458],"type":"Point"}
}