{
  "type": "Feature",
  "properties": {
    "addr:full":"Chemin De L\u00b4infante 94 Braine-l\u00b4alleud Brabant Wallon 1420",
    "addr:housenumber":"94",
    "addr:postcode":"1420",
    "addr:street":"Chemin De L\u00b4Infante;Brabant Wallon",
    "iso:country":"BE",
    "sg:address":"Chemin De L\u00b4infante 94",
    "sg:city":"Braine-l\u00b4alleud",
    "sg:orig_category":"Airconditioning and ventilatie",
    "sg:phone":"+32 2 354 54 85",
    "sg:postcode":"1420",
    "sg:province":"Brabant Wallon",
    "wof:name":"Dechaphil",
    "wof:placetype":"venue"
},
  "geometry": {"coordinates":[4.3862128258,50.7038002014],"type":"Point"}
}