{
  "type": "Feature",
  "properties": {
    "iso:country":"BE",
    "sg:address":"Hulstsestraat 35",
    "sg:city":"Kuurne",
    "sg:orig_category":"Non-Classified Establishments",
    "sg:phone":"+32 56 71 67 62",
    "sg:postcode":"8520",
    "sg:province":"West-Vlaanderen",
    "wof:name":"Soetaert A",
    "wof:placetype":"venue"
},
  "geometry": {"coordinates":[3.2877669334,50.8557777405],"type":"Point"}
}