{
  "type": "Feature",
  "properties": {
    "addr:full":"Rue Vanden Corput 33 Bruxelles (forest) Bruxelles-Capitale 1190",
    "addr:housenumber":"33",
    "addr:postcode":"1190",
    "addr:street":"Rue Vanden Corput",
    "iso:country":"BE",
    "sg:address":"Rue Vanden Corput 33",
    "sg:city":"Bruxelles (forest)",
    "sg:classifiers":[
        {
            "category":"Professional",
            "subcategory":"Advertising",
            "type":"Services"
        }
    ],
    "sg:phone":"+32 2 346 68 25",
    "sg:postcode":"1190",
    "sg:province":"Bruxelles-Capitale",
    "sg:tags":[
        "photography"
    ],
    "wof:name":"De Kinder G",
    "wof:placetype":"venue"
},
  "geometry": {"coordinates":[4.3430681229,50.8186607361],"type":"Point"}
}