{
  "type": "Feature",
  "properties": {
    "iso:country":"BE",
    "sg:address":"Rue Camille Lemonnier 23",
    "sg:city":"La Louvi\u00e8re",
    "sg:classifiers":[
        {
            "category":"Professional",
            "subcategory":"Accounting & Tax Preparation",
            "type":"Services"
        }
    ],
    "sg:phone":"+32 64 23 86 00",
    "sg:postcode":"7100",
    "sg:province":"Hainaut",
    "sg:tags":[
        "accountant"
    ],
    "wof:name":"Cabinet D'experts Comptables Ass Francotte Hennebert",
    "wof:placetype":"venue"
},
  "geometry": {"coordinates":[4.1905298233,50.4737892151],"type":"Point"}
}