{
  "type": "Feature",
  "properties": {
    "iso:country":"BE",
    "sg:address":"Chauss\u00c9e De Charleroi 208",
    "sg:city":"Charleroi",
    "sg:orig_category":"Afvalwaterverwerking and ontstoppingsdiensten",
    "sg:phone":"+32 71 33 03 71",
    "sg:postcode":"6061",
    "sg:province":"Hainaut",
    "wof:name":"Allo Service Vidange",
    "wof:placetype":"venue"
},
  "geometry": {"coordinates":[4.4652252197,50.4036712646],"type":"Point"}
}