{
  "type": "Feature",
  "properties": {
    "addr:full":"Rue Longue 16 Baelen/baelen Li\u00e8ge 4837",
    "addr:housenumber":"16",
    "addr:postcode":"4837",
    "addr:street":"Rue Longue",
    "iso:country":"BE",
    "sg:address":"Rue Longue 16",
    "sg:city":"Baelen/baelen",
    "sg:orig_category":"Postkantoren Verzekeringsmakelaars and experts",
    "sg:phone":"+32 87 76 31 46",
    "sg:postcode":"4837",
    "sg:province":"Li\u00e8ge",
    "wof:name":"De Post",
    "wof:placetype":"venue"
},
  "geometry": {"coordinates":[5.969165802,50.6303710938],"type":"Point"}
}