{
  "type": "Feature",
  "properties": {
    "addr:full":"Place Du Baty 26 Tinlot Li\u00e8ge 4557",
    "addr:housenumber":"26",
    "addr:postcode":"4557",
    "addr:street":"Place Du Baty",
    "iso:country":"BE",
    "sg:address":"Place Du Baty 26",
    "sg:city":"Tinlot",
    "sg:orig_category":"Rusthuizen and serviceflats",
    "sg:phone":"+32 85 51 15 33",
    "sg:postcode":"4557",
    "sg:province":"Li\u00e8ge",
    "wof:name":"Home De Seny",
    "wof:placetype":"venue"
},
  "geometry": {"coordinates":[5.4018158913,50.4593772888],"type":"Point"}
}