{
  "type": "Feature",
  "properties": {
    "iso:country":"BE",
    "sg:address":"Rue De M\u00e9rode 13",
    "sg:city":"Bruxelles (saint-gilles)",
    "sg:classifiers":[
        {
            "category":"Food & Beverages",
            "subcategory":"Groceries & Convenience Stores",
            "type":"Retail Goods"
        }
    ],
    "sg:phone":"+32 2 544 16 98",
    "sg:postcode":"1060",
    "sg:province":"Bruxelles-Capitale",
    "sg:tags":[
        "grocer"
    ],
    "wof:name":"S & S Sprl",
    "wof:placetype":"venue"
},
  "geometry": {"coordinates":[4.3404788971,50.8364372253],"type":"Point"}
}