{
  "type": "Feature",
  "properties": {
    "addr:full":"Interleuvenlaan 62 Leuven Vlaams-Brabant 3001",
    "addr:housenumber":"62",
    "addr:postcode":"3001",
    "addr:street":"Interleuvenlaan",
    "iso:country":"BE",
    "sg:address":"Interleuvenlaan 62",
    "sg:city":"Leuven",
    "sg:orig_category":"Informaticaconsulenten Software ontwikkeling and ontwerp",
    "sg:phone":"+32 16 29 02 99",
    "sg:postcode":"3001",
    "sg:province":"Vlaams-Brabant",
    "wof:name":"Vademecum",
    "wof:placetype":"venue"
},
  "geometry": {"coordinates":[4.7360210419,50.849067688],"type":"Point"}
}