{
  "type": "Feature",
  "properties": {
    "addr:full":"Avenue Dolez 125a Bruxelles (uccle) Bruxelles-Capitale 1180",
    "addr:housenumber":"125a",
    "addr:postcode":"1180",
    "addr:street":"Avenue Dolez",
    "iso:country":"BE",
    "sg:address":"Avenue Dolez 125a",
    "sg:city":"Bruxelles (uccle)",
    "sg:classifiers":[
        {
            "category":"Professional",
            "subcategory":"Computer Services",
            "type":"Services"
        }
    ],
    "sg:phone":"+32 2 372 39 94",
    "sg:postcode":"1180",
    "sg:province":"Bruxelles-Capitale",
    "sg:tags":[
        "webdesign",
        "-",
        "internet"
    ],
    "wof:name":"Netgroup",
    "wof:placetype":"venue"
},
  "geometry": {"coordinates":[4.3567008972,50.7824897766],"type":"Point"}
}