{
  "type": "Feature",
  "properties": {
    "iso:country":"BE",
    "sg:address":"Rue Hardu\u00c9mont 59",
    "sg:city":"Verlaine",
    "sg:orig_category":"Production and transformation de viande",
    "sg:phone":"+32 4 259 52 51",
    "sg:postcode":"4537",
    "sg:province":"Li\u00e8ge",
    "wof:name":"Abattoir Bolly",
    "wof:placetype":"venue"
},
  "geometry": {"coordinates":[5.3262968063,50.6288757324],"type":"Point"}
}