{
  "type": "Feature",
  "properties": {
    "addr:full":"Rue D'aywaille 29 Comblain-au-pont Li\u00e8ge 4170",
    "addr:housenumber":"29",
    "addr:postcode":"4170",
    "addr:street":"Rue D'Aywaille",
    "iso:country":"BE",
    "sg:address":"Rue D'aywaille 29",
    "sg:city":"Comblain-au-pont",
    "sg:classifiers":[
        {
            "category":"Travel",
            "subcategory":"Hotels & Motels",
            "type":"Entertainment"
        }
    ],
    "sg:phone":"+32 4 369 39 09",
    "sg:postcode":"4170",
    "sg:province":"Li\u00e8ge",
    "wof:name":"The Outsider",
    "wof:placetype":"venue"
},
  "geometry": {"coordinates":[5.593211174,50.4802894592],"type":"Point"}
}