{
  "type": "Feature",
  "properties": {
    "addr:full":"Statiestraat 8 Staden West-Vlaanderen 8840",
    "addr:housenumber":"8",
    "addr:postcode":"8840",
    "addr:street":"Statiestraat",
    "iso:country":"BE",
    "sg:address":"Statiestraat 8",
    "sg:city":"Staden",
    "sg:classifiers":[
        {
            "category":"Bakery",
            "type":"Food & Drink"
        }
    ],
    "sg:phone":"+32 51 70 56 07",
    "sg:postcode":"8840",
    "sg:province":"West-Vlaanderen",
    "sg:tags":[
        "confectioner",
        "baker"
    ],
    "wof:name":"Jan",
    "wof:placetype":"venue"
},
  "geometry": {"coordinates":[3.0137848854,50.974647522],"type":"Point"}
}