{
  "type": "Feature",
  "properties": {
    "iso:country":"BE",
    "sg:address":"Rue De L\u00b4ath\u00c9n\u00c9e Royal 85b30",
    "sg:city":"Sint-lambrechts-woluwe/woluwe-saint-lambert",
    "sg:orig_category":"Avocats and conseillers juridiques",
    "sg:phone":"+32 2 777 00 00",
    "sg:postcode":"1200",
    "sg:province":"Bruxelles-Capitale",
    "wof:name":"U. Lwowski",
    "wof:placetype":"venue"
},
  "geometry": {"coordinates":[4.4401350021,50.8509750366],"type":"Point"}
}