{
  "type": "Feature",
  "properties": {
    "iso:country":"BE",
    "sg:address":"Kernielerweg 47",
    "sg:city":"Borgloon",
    "sg:orig_category":"Rundveehouders",
    "sg:phone":"+32 12 74 38 84",
    "sg:postcode":"3840",
    "sg:province":"Limburg",
    "wof:name":"Rudi Gregoor",
    "wof:placetype":"venue"
},
  "geometry": {"coordinates":[5.3565912247,50.8072814941],"type":"Point"}
}