{
  "type": "Feature",
  "properties": {
    "addr:full":"Rue Du Parc 11ba Amay Li\u00e8ge 4540",
    "addr:housenumber":"11ba",
    "addr:postcode":"4540",
    "addr:street":"Rue Du Parc",
    "iso:country":"BE",
    "sg:address":"Rue Du Parc 11ba",
    "sg:city":"Amay",
    "sg:orig_category":"Maisons de repos and r\u00e9sidences",
    "sg:phone":"+32 85 31 57 86",
    "sg:postcode":"4540",
    "sg:province":"Li\u00e8ge",
    "wof:name":"Seniorie Du Parc",
    "wof:placetype":"venue"
},
  "geometry": {"coordinates":[5.3180990219,50.5478668213],"type":"Point"}
}