{
  "type": "Feature",
  "properties": {
    "iso:country":"BE",
    "sg:address":"Battelsesteenweg 463",
    "sg:city":"Mechelen",
    "sg:orig_category":"Apotheken",
    "sg:phone":"+32 15 27 15 23",
    "sg:postcode":"2800",
    "sg:province":"Antwerpen",
    "wof:name":"Apotheek De Volksmacht",
    "wof:placetype":"venue"
},
  "geometry": {"coordinates":[4.4493598938,51.0387191772],"type":"Point"}
}