{
  "type": "Feature",
  "properties": {
    "addr:full":"Koning Albertstraat 173 Ravels Antwerpen 2381",
    "addr:housenumber":"173",
    "addr:postcode":"2381",
    "addr:street":"Koning Albertstraat",
    "iso:country":"BE",
    "sg:address":"Koning Albertstraat 173",
    "sg:city":"Ravels",
    "sg:orig_category":"Dierenartsen",
    "sg:phone":"+32 14 65 05 01",
    "sg:postcode":"2381",
    "sg:province":"Antwerpen",
    "wof:name":"Ivo Van Miert",
    "wof:placetype":"venue"
},
  "geometry": {"coordinates":[4.9939131737,51.409778595],"type":"Point"}
}