{
  "type": "Feature",
  "properties": {
    "addr:full":"Grand-rue 67 Aubange (athus) Luxembourg 6791",
    "addr:housenumber":"67",
    "addr:postcode":"6791",
    "addr:street":"Grand-Rue",
    "iso:country":"BE",
    "sg:address":"Grand-rue 67",
    "sg:city":"Aubange (athus)",
    "sg:classifiers":[
        {
            "category":"Personal",
            "subcategory":"Beauty Salon",
            "type":"Services"
        }
    ],
    "sg:phone":"+32 63 38 92 16",
    "sg:postcode":"6791",
    "sg:province":"Luxembourg",
    "sg:tags":[
        "lady",
        "-",
        "hairdressing"
    ],
    "wof:name":"Central Coiffure",
    "wof:placetype":"venue"
},
  "geometry": {"coordinates":[5.8368301392,49.5627288818],"type":"Point"}
}