{
  "type": "Feature",
  "properties": {
    "iso:country":"BE",
    "sg:address":"Rue De Couillet 146",
    "sg:city":"Ch\u00e2telet",
    "sg:classifiers":[
        {
            "category":"Real Estate",
            "subcategory":"Surveying",
            "type":"Services"
        }
    ],
    "sg:phone":"+32 71 39 63 63",
    "sg:postcode":"6200",
    "sg:province":"Hainaut",
    "sg:tags":[
        "lettering",
        "letter"
    ],
    "wof:name":"Graphic Leader Sa",
    "wof:placetype":"venue"
},
  "geometry": {"coordinates":[4.5093340874,50.4014930725],"type":"Point"}
}