{
  "type": "Feature",
  "properties": {
    "iso:country":"BE",
    "sg:address":"Rue Villa Des Roses 13",
    "sg:city":"Gerpinnes",
    "sg:classifiers":[
        {
            "category":"Health Services",
            "subcategory":"Health Practitioner",
            "type":"Services"
        }
    ],
    "sg:phone":"+32 71 31 94 66",
    "sg:postcode":"6280",
    "sg:province":"Hainaut",
    "sg:tags":[
        "physiotherapist"
    ],
    "wof:name":"Flamant Claude",
    "wof:placetype":"venue"
},
  "geometry": {"coordinates":[4.5356330872,50.3340148926],"type":"Point"}
}