{
  "type": "Feature",
  "properties": {
    "addr:full":"Obterrestraat 2 Poperinge West-Vlaanderen 8972",
    "addr:housenumber":"2",
    "addr:postcode":"8972",
    "addr:street":"Obterrestraat",
    "iso:country":"BE",
    "sg:address":"Obterrestraat 2",
    "sg:city":"Poperinge",
    "sg:orig_category":"Boucheries",
    "sg:phone":"+32 57 30 02 72",
    "sg:postcode":"8972",
    "sg:province":"West-Vlaanderen",
    "wof:name":"Bart Walbrou",
    "wof:placetype":"venue"
},
  "geometry": {"coordinates":[2.655755043,50.8907585144],"type":"Point"}
}