{
  "type": "Feature",
  "properties": {
    "addr:full":"Vrijheidstraat 20 Aalst Oost-Vlaanderen 9300",
    "addr:housenumber":"20",
    "addr:postcode":"9300",
    "addr:street":"Vrijheidstraat",
    "iso:country":"BE",
    "sg:address":"Vrijheidstraat 20",
    "sg:city":"Aalst",
    "sg:orig_category":"Agences de voyages",
    "sg:phone":"+32 53 78 70 01",
    "sg:postcode":"9300",
    "sg:province":"Oost-Vlaanderen",
    "wof:name":"Omnia",
    "wof:placetype":"venue"
},
  "geometry": {"coordinates":[4.0350828171,50.940372467],"type":"Point"}
}