{
  "type": "Feature",
  "properties": {
    "addr:full":"Kaboutermansstraat 66 Leuven Vlaams-Brabant 3000",
    "addr:housenumber":"66",
    "addr:postcode":"3000",
    "addr:street":"Kaboutermansstraat",
    "iso:country":"BE",
    "sg:address":"Kaboutermansstraat 66",
    "sg:city":"Leuven",
    "sg:classifiers":[
        {
            "category":"Real Estate",
            "subcategory":"Architect",
            "type":"Services"
        }
    ],
    "sg:phone":"+32 16 23 34 01",
    "sg:postcode":"3000",
    "sg:province":"Vlaams-Brabant",
    "wof:name":"Kenis R",
    "wof:placetype":"venue"
},
  "geometry": {"coordinates":[4.6850161552,50.8815155029],"type":"Point"}
}