{
  "type": "Feature",
  "properties": {
    "iso:country":"BE",
    "sg:address":"Route De Gembloux 358",
    "sg:city":"Eghez\u00c9e",
    "sg:orig_category":"Agences de publicit\u00e9",
    "sg:phone":"+32 81 65 72 26",
    "sg:postcode":"5310",
    "sg:province":"Namur",
    "wof:name":"Christian Colleye",
    "wof:placetype":"venue"
},
  "geometry": {"coordinates":[4.9000458717,50.591129303],"type":"Point"}
}