{
  "type": "Feature",
  "properties": {
    "addr:full":"Pastoor Vaesstraat 37 Mol Antwerpen 2400",
    "addr:housenumber":"37",
    "addr:postcode":"2400",
    "addr:street":"Pastoor Vaesstraat",
    "iso:country":"BE",
    "sg:address":"Pastoor Vaesstraat 37",
    "sg:city":"Mol",
    "sg:orig_category":"Sportclubs",
    "sg:phone":"+32 14 31 21 83",
    "sg:postcode":"2400",
    "sg:province":"Antwerpen",
    "wof:name":"W.s.v. Mol",
    "wof:placetype":"venue"
},
  "geometry": {"coordinates":[5.1516780853,51.1913757324],"type":"Point"}
}