{
  "type": "Feature",
  "properties": {
    "addr:full":"Rue De L'eglise 64-2 Bruxelles (woluwe-saint-pierre) Bruxelles-Capitale 1150",
    "addr:housenumber":"64-2",
    "addr:postcode":"1150",
    "addr:street":"Rue De L'Eglise",
    "iso:country":"BE",
    "sg:address":"Rue De L'eglise 64-2",
    "sg:city":"Bruxelles (woluwe-saint-pierre)",
    "sg:classifiers":[
        {
            "category":"Professional",
            "subcategory":"Management & Consulting",
            "type":"Services"
        }
    ],
    "sg:phone":"+32 2 778 99 15",
    "sg:postcode":"1150",
    "sg:province":"Bruxelles-Capitale",
    "sg:tags":[
        "consultant"
    ],
    "wof:name":"Trading & Consulting",
    "wof:placetype":"venue"
},
  "geometry": {"coordinates":[4.4616689682,50.8410186768],"type":"Point"}
}