{
  "type": "Feature",
  "properties": {
    "iso:country":"BE",
    "sg:address":"Wijnendalestraat 183",
    "sg:city":"Roeselare",
    "sg:orig_category":"Restaurants Ruimtes voor conferenties, recepties and feesten",
    "sg:phone":"+32 51 24 12 22",
    "sg:postcode":"8800",
    "sg:province":"West-Vlaanderen",
    "wof:name":"Paviljoen Feestzaal",
    "wof:placetype":"venue"
},
  "geometry": {"coordinates":[3.1283369064,50.9708824158],"type":"Point"}
}