{
  "type": "Feature",
  "properties": {
    "addr:full":"Rue Trieu Kaisin 239 Charleroi (montignies-sur-sambre) Hainaut 6061",
    "addr:housenumber":"239",
    "addr:postcode":"6061",
    "addr:street":"Rue Trieu Kaisin",
    "iso:country":"BE",
    "sg:address":"Rue Trieu Kaisin 239",
    "sg:city":"Charleroi (montignies-sur-sambre)",
    "sg:classifiers":[
        {
            "category":"Health Services",
            "subcategory":"Health Practitioner",
            "type":"Services"
        }
    ],
    "sg:phone":"+32 71 31 06 78",
    "sg:postcode":"6061",
    "sg:province":"Hainaut",
    "sg:tags":[
        "physiotherapist"
    ],
    "wof:name":"Friedlender Ornella",
    "wof:placetype":"venue"
},
  "geometry": {"coordinates":[4.4859638214,50.4094276428],"type":"Point"}
}