{
  "type": "Feature",
  "properties": {
    "iso:country":"BE",
    "sg:address":"Pont Saint-laurent 17",
    "sg:city":"Verviers",
    "sg:orig_category":"Dameskledingzaken Herenkledingzaken Non-foodwinkels",
    "sg:phone":"+32 87 35 47 21",
    "sg:postcode":"4800",
    "sg:province":"Li\u00e8ge",
    "wof:name":"Top Boutique",
    "wof:placetype":"venue"
},
  "geometry": {"coordinates":[5.8596138954,50.592754364],"type":"Point"}
}