{
  "type": "Feature",
  "properties": {
    "addr:full":"Rue Du Village 33 Lincent Li\u00e8ge 4287",
    "addr:housenumber":"33",
    "addr:postcode":"4287",
    "addr:street":"Rue Du Village",
    "iso:country":"BE",
    "sg:address":"Rue Du Village 33",
    "sg:city":"Lincent",
    "sg:orig_category":"Rundveehouders Varkenskwekers",
    "sg:phone":"+32 19 63 57 54",
    "sg:postcode":"4287",
    "sg:province":"Li\u00e8ge",
    "wof:name":"Pascal Beine",
    "wof:placetype":"venue"
},
  "geometry": {"coordinates":[5.0287380219,50.7112121582],"type":"Point"}
}