{
  "type": "Feature",
  "properties": {
    "iso:country":"BE",
    "sg:address":"Egied De Jonghestraat 71-74",
    "sg:city":"Bornem (hingene)",
    "sg:classifiers":[
        {
            "category":"Health Services",
            "subcategory":"Nursing And Care Facility",
            "type":"Services"
        }
    ],
    "sg:phone":"+32 3 889 37 99",
    "sg:postcode":"2880",
    "sg:province":"Antwerpen",
    "sg:tags":[
        "home",
        "rest"
    ],
    "wof:name":"De Vlietoever Bvba",
    "wof:placetype":"venue"
},
  "geometry": {"coordinates":[4.3025717735,51.1036643982],"type":"Point"}
}