{
  "type": "Feature",
  "properties": {
    "iso:country":"BE",
    "sg:address":"Geraardsbergsestraat 41",
    "sg:city":"Ninove",
    "sg:classifiers":[
        {
            "category":"Retail",
            "subcategory":"Storage",
            "type":"Services"
        }
    ],
    "sg:phone":"+32 54 33 00 36",
    "sg:postcode":"9400",
    "sg:province":"Oost-Vlaanderen",
    "sg:tags":[
        "rack",
        "system"
    ],
    "wof:name":"Provost Nv-sa",
    "wof:placetype":"venue"
},
  "geometry": {"coordinates":[4.0178699493,50.8366317749],"type":"Point"}
}