{
  "type": "Feature",
  "properties": {
    "addr:full":"Hoogmolenwegel 21 Waregem West-Vlaanderen 8790",
    "addr:housenumber":"21",
    "addr:postcode":"8790",
    "addr:street":"Hoogmolenwegel",
    "iso:country":"BE",
    "sg:address":"Hoogmolenwegel 21",
    "sg:city":"Waregem",
    "sg:classifiers":[
        {
            "category":"Autos & Motor Vehicles",
            "subcategory":"Auto Supplies",
            "type":"Retail Goods"
        }
    ],
    "sg:phone":"+32 56 60 42 12",
    "sg:postcode":"8790",
    "sg:province":"West-Vlaanderen",
    "sg:tags":[
        "coupling",
        "trailer"
    ],
    "wof:name":"Nv Gdw Bvba",
    "wof:placetype":"venue"
},
  "geometry": {"coordinates":[3.4121389389,50.880569458],"type":"Point"}
}