{
  "type": "Feature",
  "properties": {
    "addr:full":"Jagersstraat 7 Waregem West-Vlaanderen 8790",
    "addr:housenumber":"7",
    "addr:postcode":"8790",
    "addr:street":"Jagersstraat",
    "iso:country":"BE",
    "sg:address":"Jagersstraat 7",
    "sg:city":"Waregem",
    "sg:classifiers":[
        {
            "category":"Home & Garden",
            "subcategory":"Carpets & Floor Coverings",
            "type":"Retail Goods"
        }
    ],
    "sg:phone":"+32 56 61 05 15",
    "sg:postcode":"8790",
    "sg:province":"West-Vlaanderen",
    "sg:tags":[
        "layer",
        "mosaicists"
    ],
    "wof:name":"Deweer Geert",
    "wof:placetype":"venue"
},
  "geometry": {"coordinates":[3.4511470795,50.8934555054],"type":"Point"}
}