{
  "type": "Feature",
  "properties": {
    "iso:country":"BE",
    "sg:address":"Arianne Laan 7",
    "sg:city":"Bruxelles-saint-josse-ten-noode",
    "sg:classifiers":[
        {
            "category":"Professional",
            "subcategory":"Computer Services",
            "type":"Services"
        }
    ],
    "sg:phone":"+32 2 773 71 11",
    "sg:postcode":"1200",
    "sg:province":"Bruxelles-Capitale",
    "sg:tags":[
        "ontwikkeling",
        "informaticaconsulenten",
        "siemens",
        "fujitsu",
        "computerapparatuur",
        "software"
    ],
    "wof:name":"Trasys",
    "wof:placetype":"venue"
},
  "geometry": {"coordinates":[4.4318118095,50.857711792],"type":"Point"}
}