{
  "type": "Feature",
  "properties": {
    "iso:country":"BE",
    "sg:address":"Hoeksken 91",
    "sg:city":"Sint-lievens-houtem",
    "sg:orig_category":"Eleveurs de bovins",
    "sg:phone":"+32 53 62 45 96",
    "sg:postcode":"9520",
    "sg:province":"Oost-Vlaanderen",
    "wof:name":"Paul Coppens",
    "wof:placetype":"venue"
},
  "geometry": {"coordinates":[3.8397550583,50.9161300659],"type":"Point"}
}