{
  "type": "Feature",
  "properties": {
    "iso:country":"BE",
    "sg:address":"Rue De La Forge 85",
    "sg:city":"Plombieres/plombieres",
    "sg:orig_category":"Rundveehouders",
    "sg:phone":"+32 87 78 64 69",
    "sg:postcode":"4851",
    "sg:province":"Li\u00e8ge",
    "wof:name":"Albert Schyns",
    "wof:placetype":"venue"
},
  "geometry": {"coordinates":[5.9952659607,50.7457046509],"type":"Point"}
}