{
  "type": "Feature",
  "properties": {
    "addr:full":"Zuidlaan 72 Zwalm (roborst) Oost-Vlaanderen 9630",
    "addr:housenumber":"72",
    "addr:postcode":"9630",
    "addr:street":"Zuidlaan;Roborst Oost-Vlaanderen",
    "iso:country":"BE",
    "sg:address":"Zuidlaan 72",
    "sg:city":"Zwalm (roborst)",
    "sg:classifiers":[
        {
            "category":"Manufacturing",
            "subcategory":"Lumber",
            "type":"Manufacturing & Wholesale Goods"
        }
    ],
    "sg:phone":"+32 55 49 90 43",
    "sg:postcode":"9630",
    "sg:province":"Oost-Vlaanderen",
    "sg:tags":[
        "timber"
    ],
    "wof:name":"Van Der Stricht L",
    "wof:placetype":"venue"
},
  "geometry": {"coordinates":[3.7335920334,50.875],"type":"Point"}
}