{
  "type": "Feature",
  "properties": {
    "iso:country":"BE",
    "sg:address":"Chasse De Saint-ghislain 4",
    "sg:city":"Boussu",
    "sg:orig_category":"Boekhouders",
    "sg:phone":"+32 65 79 29 46",
    "sg:postcode":"7300",
    "sg:province":"Hainaut",
    "wof:name":"Benseghir Tadj",
    "wof:placetype":"venue"
},
  "geometry": {"coordinates":[3.7981259823,50.4383926392],"type":"Point"}
}