{
  "type": "Feature",
  "properties": {
    "iso:country":"BE",
    "sg:address":"Crombach 118",
    "sg:city":"Sankt Vith (crombach)",
    "sg:classifiers":[
        {
            "category":"Building & Trades",
            "subcategory":"Electrical",
            "type":"Services"
        }
    ],
    "sg:phone":"+32 80 22 88 71",
    "sg:postcode":"4784",
    "sg:province":"Li\u00e8ge",
    "sg:tags":[
        "electric",
        "-",
        "housewiring",
        "contractor"
    ],
    "wof:name":"Pint P",
    "wof:placetype":"venue"
},
  "geometry": {"coordinates":[6.0675911903,50.2596511841],"type":"Point"}
}