{
  "type": "Feature",
  "properties": {
    "iso:country":"BE",
    "sg:address":"Rue Des Fran\u00e7ais 36",
    "sg:city":"Aiseau-presles (roselies)",
    "sg:classifiers":[
        {
            "category":"Food & Beverages",
            "subcategory":"Groceries & Convenience Stores",
            "type":"Retail Goods"
        }
    ],
    "sg:phone":"+32 71 74 11 16",
    "sg:postcode":"6250",
    "sg:province":"Hainaut",
    "sg:tags":[
        "grocer"
    ],
    "wof:name":"Fatih Sprl",
    "wof:placetype":"venue"
},
  "geometry": {"coordinates":[4.5755171776,50.4276351929],"type":"Point"}
}