{
  "type": "Feature",
  "properties": {
    "addr:full":"Kammenstraat 32 Antwerpen Antwerpen 2000",
    "addr:housenumber":"32",
    "addr:postcode":"2000",
    "addr:street":"Kammenstraat",
    "iso:country":"BE",
    "sg:address":"Kammenstraat 32",
    "sg:city":"Antwerpen",
    "sg:classifiers":[
        {
            "category":"Shopping",
            "subcategory":"Clothing, Apparel, & Fashions",
            "type":"Retail Goods"
        }
    ],
    "sg:phone":"+32 3 226 02 31",
    "sg:postcode":"2000",
    "sg:province":"Antwerpen",
    "sg:tags":[
        "v\u00eatements",
        "pour",
        "dame"
    ],
    "wof:name":"Babes Store",
    "wof:placetype":"venue"
},
  "geometry": {"coordinates":[4.4002971649,51.2174339294],"type":"Point"}
}