{
  "type": "Feature",
  "properties": {
    "iso:country":"BE",
    "sg:address":"Nationalestraat 31",
    "sg:city":"Stekene",
    "sg:classifiers":[
        {
            "category":"Arena",
            "subcategory":"Sports Club",
            "type":"Entertainment"
        }
    ],
    "sg:phone":"+32 3 789 29 73",
    "sg:postcode":"9190",
    "sg:province":"Oost-Vlaanderen",
    "sg:tags":[
        "de"
    ],
    "wof:name":"Vos Reinaert",
    "wof:placetype":"venue"
},
  "geometry": {"coordinates":[4.0774970055,51.2084884644],"type":"Point"}
}