{
  "type": "Feature",
  "properties": {
    "iso:country":"BE",
    "sg:address":"Boulevard Leopold Iii 77",
    "sg:city":"P\u00e9ruwelz",
    "sg:classifiers":[
        {
            "category":"Real Estate",
            "subcategory":"Architect",
            "type":"Services"
        }
    ],
    "sg:phone":"+32 69 77 08 93",
    "sg:postcode":"7600",
    "sg:province":"Hainaut",
    "wof:name":"Stievenart L",
    "wof:placetype":"venue"
},
  "geometry": {"coordinates":[3.5954680443,50.5050697327],"type":"Point"}
}