{
  "type": "Feature",
  "properties": {
    "addr:full":"Waverse Steenweg 119 Elsene/ixelles Bruxelles-Capitale 1050",
    "addr:housenumber":"119",
    "addr:postcode":"1050",
    "addr:street":"Waverse Steenweg",
    "iso:country":"BE",
    "sg:address":"Waverse Steenweg 119",
    "sg:city":"Elsene/ixelles",
    "sg:orig_category":"Brood, gebak and snoepgoed",
    "sg:phone":"+32 2 512 21 60",
    "sg:postcode":"1050",
    "sg:province":"Bruxelles-Capitale",
    "wof:name":"N.e.b.",
    "wof:placetype":"venue"
},
  "geometry": {"coordinates":[4.3699560165,50.8354377747],"type":"Point"}
}