{
  "type": "Feature",
  "properties": {
    "iso:country":"BE",
    "sg:address":"Rue Charles Magnette 7",
    "sg:city":"Virton",
    "sg:classifiers":[
        {
            "category":"Banks & Credit Unions",
            "subcategory":"Bank",
            "type":"Services"
        }
    ],
    "sg:phone":"+32 63 57 84 87",
    "sg:postcode":"6760",
    "sg:province":"Luxembourg",
    "wof:name":"Aslk-cger Bank",
    "wof:placetype":"venue"
},
  "geometry": {"coordinates":[5.5321102142,49.5665016174],"type":"Point"}
}