{
  "type": "Feature",
  "properties": {
    "iso:country":"BE",
    "sg:address":"Turnhoutsebaan 217",
    "sg:city":"Wijnegem",
    "sg:orig_category":"Avocats and conseillers juridiques",
    "sg:phone":"+32 3 353 81 38",
    "sg:postcode":"2110",
    "sg:province":"Antwerpen",
    "wof:name":"M. Van Dyck",
    "wof:placetype":"venue"
},
  "geometry": {"coordinates":[4.5148968697,51.2262001038],"type":"Point"}
}