{
  "type": "Feature",
  "properties": {
    "addr:full":"Stropkaai 5 Gent Oost-Vlaanderen 9000",
    "addr:housenumber":"5",
    "addr:postcode":"9000",
    "addr:street":"Stropkaai;Oost-Vlaanderen",
    "iso:country":"BE",
    "sg:address":"Stropkaai 5",
    "sg:city":"Gent",
    "sg:orig_category":"Pleisterwerk",
    "sg:postcode":"9000",
    "sg:province":"Oost-Vlaanderen",
    "wof:name":"Johnny Demuynck",
    "wof:placetype":"venue"
},
  "geometry": {"coordinates":[3.7277710438,51.0364837646],"type":"Point"}
}