{
  "type": "Feature",
  "properties": {
    "addr:full":"Rue Haute 225 Bruxelles Bruxelles-Capitale 1000",
    "addr:housenumber":"225",
    "addr:postcode":"1000",
    "addr:street":"Rue Haute",
    "iso:country":"BE",
    "sg:address":"Rue Haute 225",
    "sg:city":"Bruxelles",
    "sg:classifiers":[
        {
            "category":"Wholesale",
            "subcategory":"Scrap",
            "type":"Manufacturing & Wholesale Goods"
        }
    ],
    "sg:phone":"+32 2 512 63 39",
    "sg:postcode":"1000",
    "sg:province":"Bruxelles-Capitale",
    "sg:tags":[
        "metal"
    ],
    "wof:name":"Recupermat Jacobs Tony Sc",
    "wof:placetype":"venue"
},
  "geometry": {"coordinates":[4.3483400345,50.8370132446],"type":"Point"}
}