{
  "type": "Feature",
  "properties": {
    "addr:full":"Oude Brusselseweg 76-78 Gent (ledeberg) Oost-Vlaanderen 9050",
    "addr:housenumber":"76-78",
    "addr:postcode":"9050",
    "addr:street":"Oude Brusselseweg",
    "iso:country":"BE",
    "sg:address":"Oude Brusselseweg 76-78",
    "sg:city":"Gent (ledeberg)",
    "sg:orig_category":"Non-Classified Establishments",
    "sg:phone":"+32 9 210 79 79",
    "sg:postcode":"9050",
    "sg:province":"Oost-Vlaanderen",
    "wof:name":"Sofea Bvba",
    "wof:placetype":"venue"
},
  "geometry": {"coordinates":[3.7478239536,51.0411148071],"type":"Point"}
}