{
  "type": "Feature",
  "properties": {
    "iso:country":"BE",
    "sg:address":"Rue Hemricourt 30",
    "sg:city":"Li\u00c8ge",
    "sg:orig_category":"Avocats and conseillers juridiques",
    "sg:phone":"+32 4 252 30 40",
    "sg:postcode":"4000",
    "sg:province":"Li\u00e8ge",
    "wof:name":"P. Counson",
    "wof:placetype":"venue"
},
  "geometry": {"coordinates":[5.5632538795,50.6308784485],"type":"Point"}
}