{
  "type": "Feature",
  "properties": {
    "iso:country":"BE",
    "sg:address":"Chauss\u00e9e De Lasne 18",
    "sg:city":"Rixensart",
    "sg:orig_category":"Newspapers, magazines, periodicals - Publishers",
    "sg:phone":"+32 2 653 20 70",
    "sg:postcode":"1330",
    "sg:province":"Brabant Wallon",
    "wof:name":"Publedis Sa",
    "wof:placetype":"venue"
},
  "geometry": {"coordinates":[4.510035038,50.7071418762],"type":"Point"}
}