{
  "type": "Feature",
  "properties": {
    "iso:country":"BE",
    "sg:address":"Donkstraat 65b",
    "sg:city":"Puurs (ruisbroek)",
    "sg:classifiers":[
        {
            "category":"Building & Trades",
            "subcategory":"Electrical",
            "type":"Services"
        }
    ],
    "sg:phone":"+32 3 886 35 22",
    "sg:postcode":"2870",
    "sg:province":"Antwerpen",
    "sg:tags":[
        "electric",
        "-",
        "housewiring",
        "contractor"
    ],
    "wof:name":"Ruttens Elektro",
    "wof:placetype":"venue"
},
  "geometry": {"coordinates":[4.323843956,51.0891571045],"type":"Point"}
}