{
  "type": "Feature",
  "properties": {
    "iso:country":"BE",
    "sg:address":"Rue Joseph Ii 176",
    "sg:city":"Brussel/bruxelles",
    "sg:orig_category":"Agences de presse",
    "sg:phone":"+32 2 219 24 03",
    "sg:postcode":"1000",
    "sg:province":"Bruxelles-Capitale",
    "wof:name":"John Fraser",
    "wof:placetype":"venue"
},
  "geometry": {"coordinates":[4.3811559677,50.8439559937],"type":"Point"}
}