{
  "type": "Feature",
  "properties": {
    "iso:country":"BE",
    "sg:address":"Olmensebaan 51",
    "sg:city":"Balen",
    "sg:orig_category":"Travaux de pl\u00e2trage. Installation de menuiserie m\u00e9tallique",
    "sg:phone":"+32 14 31 32 66",
    "sg:postcode":"2490",
    "sg:province":"Antwerpen",
    "wof:name":"Joos Weyland",
    "wof:placetype":"venue"
},
  "geometry": {"coordinates":[5.1373419762,51.1710891724],"type":"Point"}
}