{
  "type": "Feature",
  "properties": {
    "iso:country":"BE",
    "sg:address":"Rue De Plainevaux 18",
    "sg:city":"Seraing",
    "sg:classifiers":[
        {
            "category":"Food & Beverages",
            "subcategory":"Supermarket",
            "type":"Retail Goods"
        }
    ],
    "sg:phone":"+32 4 385 11 76",
    "sg:postcode":"4100",
    "sg:province":"Li\u00e8ge",
    "sg:tags":[
        "department",
        "store"
    ],
    "wof:name":"Trafic",
    "wof:placetype":"venue"
},
  "geometry": {"coordinates":[5.5067958832,50.5859794617],"type":"Point"}
}