{
  "type": "Feature",
  "properties": {
    "iso:country":"BE",
    "sg:address":"Grote Steenweg 100",
    "sg:city":"Kontich (waarloos)",
    "sg:classifiers":[
        {
            "category":"Utilities",
            "subcategory":"Natural Gas",
            "type":"Services"
        }
    ],
    "sg:phone":"+32 15 31 12 73",
    "sg:postcode":"2550",
    "sg:province":"Antwerpen",
    "sg:tags":[
        "filter",
        "-",
        "liquid"
    ],
    "wof:name":"Trac Nv",
    "wof:placetype":"venue"
},
  "geometry": {"coordinates":[4.4730300903,51.1360588074],"type":"Point"}
}