{
  "type": "Feature",
  "properties": {
    "iso:country":"BE",
    "sg:address":"Chemin De La Vieille Court 68",
    "sg:city":"Nivelles",
    "sg:orig_category":"Installation de menuiserie m\u00e9tallique. Fabrication and montage de mobilier. Installation de menuiser",
    "sg:phone":"+32 67 33 98 73",
    "sg:postcode":"1400",
    "sg:province":"Brabant Wallon",
    "wof:name":"Lambrechts",
    "wof:placetype":"venue"
},
  "geometry": {"coordinates":[4.339220047,50.5904502869],"type":"Point"}
}