{
  "type": "Feature",
  "properties": {
    "addr:full":"Kortrijksesteenweg 219 Gent-centrum Oost-Vlaanderen 9000",
    "addr:housenumber":"219",
    "addr:postcode":"9000",
    "addr:street":"Kortrijksesteenweg;Oost-Vlaanderen",
    "iso:country":"BE",
    "sg:address":"Kortrijksesteenweg 219",
    "sg:city":"Gent-centrum",
    "sg:orig_category":"Advocaten and juridische adviseurs Balie van Gent",
    "sg:phone":"+32 9 221 70 77",
    "sg:postcode":"9000",
    "sg:province":"Oost-Vlaanderen",
    "wof:name":"De Becker Ann",
    "wof:placetype":"venue"
},
  "geometry": {"coordinates":[3.716711998,51.0394210815],"type":"Point"}
}