{
  "type": "Feature",
  "properties": {
    "addr:full":"Potterstraat 21 Sint-gillis-waas (sint-pauwels) Oost-Vlaanderen 9170",
    "addr:housenumber":"21",
    "addr:postcode":"9170",
    "addr:street":"Potterstraat;Sint-Pauwels",
    "iso:country":"BE",
    "sg:address":"Potterstraat 21",
    "sg:city":"Sint-gillis-waas (sint-pauwels)",
    "sg:classifiers":[
        {
            "category":"Personal",
            "subcategory":"Nail Salon",
            "type":"Services"
        }
    ],
    "sg:phone":"+32 3 776 70 28",
    "sg:postcode":"9170",
    "sg:province":"Oost-Vlaanderen",
    "sg:tags":[
        "pedicure"
    ],
    "wof:name":"Lauwers Instituut",
    "wof:placetype":"venue"
},
  "geometry": {"coordinates":[4.0994138718,51.1925163269],"type":"Point"}
}