{
  "type": "Feature",
  "properties": {
    "addr:full":"P Senesalestraat 70 Kruishoutem Oost-Vlaanderen 9770",
    "addr:housenumber":"70",
    "addr:postcode":"9770",
    "addr:street":"P Senesalestraat",
    "iso:country":"BE",
    "sg:address":"P Senesalestraat 70",
    "sg:city":"Kruishoutem",
    "sg:orig_category":"Schilders",
    "sg:phone":"+32 9 383 63 47",
    "sg:postcode":"9770",
    "sg:province":"Oost-Vlaanderen",
    "wof:name":"D.r. Decor",
    "wof:placetype":"venue"
},
  "geometry": {"coordinates":[3.5285511017,50.8993911743],"type":"Point"}
}