{
  "type": "Feature",
  "properties": {
    "addr:full":"Sinte Apoloniastraat 133 Aalst Oost-Vlaanderen 9300",
    "addr:housenumber":"133",
    "addr:postcode":"9300",
    "addr:street":"Apoloniastraat",
    "iso:country":"BE",
    "sg:address":"Sinte Apoloniastraat 133",
    "sg:city":"Aalst",
    "sg:classifiers":[
        {
            "category":"Building & Trades",
            "subcategory":"Landscaping Services",
            "type":"Services"
        }
    ],
    "sg:phone":"+32 53 77 75 77",
    "sg:postcode":"9300",
    "sg:province":"Oost-Vlaanderen",
    "sg:tags":[
        "nurseryman"
    ],
    "wof:name":"Van Geem Hilaire",
    "wof:placetype":"venue"
},
  "geometry": {"coordinates":[4.0141448975,50.9464035034],"type":"Point"}
}