{
  "type": "Feature",
  "properties": {
    "iso:country":"BE",
    "sg:address":"Kwatrechtsteenweg 156-3",
    "sg:city":"Wetteren",
    "sg:classifiers":[
        {
            "category":"Professional",
            "subcategory":"Art Services",
            "type":"Services"
        }
    ],
    "sg:phone":"+32 9 369 86 63",
    "sg:postcode":"9230",
    "sg:province":"Oost-Vlaanderen",
    "sg:tags":[
        "graphic",
        "designer"
    ],
    "wof:name":"M T M Studio Design",
    "wof:placetype":"venue"
},
  "geometry": {"coordinates":[3.8535699844,50.9981918335],"type":"Point"}
}