{
  "type": "Feature",
  "properties": {
    "addr:full":"Kouterstraat 10 Temse Oost-Vlaanderen 9140",
    "addr:housenumber":"10",
    "addr:postcode":"9140",
    "addr:street":"Kouterstraat",
    "iso:country":"BE",
    "sg:address":"Kouterstraat 10",
    "sg:city":"Temse",
    "sg:classifiers":[
        {
            "category":"Retail",
            "subcategory":"Repair Shop",
            "type":"Services"
        }
    ],
    "sg:phone":"+32 3 771 04 79",
    "sg:postcode":"9140",
    "sg:province":"Oost-Vlaanderen",
    "sg:tags":[
        "-",
        "mainten",
        "watch",
        "clock"
    ],
    "wof:name":"Thierens-van Wauwe",
    "wof:placetype":"venue"
},
  "geometry": {"coordinates":[4.2142281532,51.1274108887],"type":"Point"}
}