{
  "type": "Feature",
  "properties": {
    "iso:country":"BE",
    "sg:address":"Nieuwstraat 36",
    "sg:city":"Willebroek",
    "sg:classifiers":[
        {
            "category":"Shopping",
            "subcategory":"Pets & Pet Supplies",
            "type":"Retail Goods"
        }
    ],
    "sg:phone":"+32 3 886 91 51",
    "sg:postcode":"2830",
    "sg:province":"Antwerpen",
    "sg:tags":[
        "aquarium",
        "accessory"
    ],
    "wof:name":"Aqauria-vijvershop Fauna",
    "wof:placetype":"venue"
},
  "geometry": {"coordinates":[4.3623671532,51.0605430603],"type":"Point"}
}