{
  "type": "Feature",
  "properties": {
    "addr:full":"Rue Pont-\u00c0-la-faulx 49 Peruwelz Hainaut 7600",
    "addr:housenumber":"49",
    "addr:postcode":"7600",
    "addr:street":"Rue Pont-A\u0300-La-Faulx;Hainaut",
    "iso:country":"BE",
    "sg:address":"Rue Pont-\u00c0-la-faulx 49",
    "sg:city":"Peruwelz",
    "sg:orig_category":"Plomberie, chauffage and installations sanitaires",
    "sg:phone":"+32 69 77 32 74",
    "sg:postcode":"7600",
    "sg:province":"Hainaut",
    "wof:name":"Bodson-carrette",
    "wof:placetype":"venue"
},
  "geometry": {"coordinates":[3.5959670544,50.5112571716],"type":"Point"}
}