{
  "type": "Feature",
  "properties": {
    "addr:full":"Rietstraat 40 Mechelen Antwerpen 2800",
    "addr:housenumber":"40",
    "addr:postcode":"2800",
    "addr:street":"Rietstraat",
    "iso:country":"BE",
    "sg:address":"Rietstraat 40",
    "sg:city":"Mechelen",
    "sg:orig_category":"Scenery Stage-, film-, and television",
    "sg:phone":"+32 15 34 86 20",
    "sg:postcode":"2800",
    "sg:province":"Antwerpen",
    "wof:name":"Bb-art",
    "wof:placetype":"venue"
},
  "geometry": {"coordinates":[4.4774308205,50.9991722107],"type":"Point"}
}