{
  "type": "Feature",
  "properties": {
    "iso:country":"BE",
    "sg:address":"Molenheide 20",
    "sg:city":"Zoersel",
    "sg:orig_category":"Brood, gebak and snoepgoed",
    "sg:phone":"+32 3 312 32 39",
    "sg:postcode":"2980",
    "sg:province":"Antwerpen",
    "wof:name":"Ronny Eelen",
    "wof:placetype":"venue"
},
  "geometry": {"coordinates":[4.7115468979,51.2760047913],"type":"Point"}
}