{
  "type": "Feature",
  "properties": {
    "iso:country":"BE",
    "sg:address":"Hollandseweg 19",
    "sg:city":"Wuustwezel",
    "sg:orig_category":"Meubelzaken, woning- and keukeninrichting",
    "sg:phone":"+32 3 314 37 53",
    "sg:postcode":"2990",
    "sg:province":"Antwerpen",
    "wof:name":"Owan Tempur",
    "wof:placetype":"venue"
},
  "geometry": {"coordinates":[4.6970567703,51.4040527344],"type":"Point"}
}