{
  "type": "Feature",
  "properties": {
    "iso:country":"BE",
    "sg:address":"Bellestraat 4",
    "sg:city":"Gijverinkhove",
    "sg:classifiers":[
        {
            "category":"Home & Garden",
            "subcategory":"Furniture",
            "type":"Retail Goods"
        }
    ],
    "sg:phone":"+32 58 29 95 09",
    "sg:postcode":"8691",
    "sg:province":"West-Vlaanderen",
    "sg:tags":[
        "household",
        "wood"
    ],
    "wof:name":"Coemelck Bvba",
    "wof:placetype":"venue"
},
  "geometry": {"coordinates":[2.6705551147,50.9733467102],"type":"Point"}
}