{
  "type": "Feature",
  "properties": {
    "iso:country":"BE",
    "sg:address":"Chauss\u00e9e De Mons 52",
    "sg:city":"Manage",
    "sg:classifiers":[
        {
            "category":"Health Services",
            "subcategory":"Doctor",
            "type":"Services"
        }
    ],
    "sg:phone":"+32 64 54 00 72",
    "sg:postcode":"7170",
    "sg:province":"Hainaut",
    "sg:tags":[
        "medicinephysicians",
        "surgeon"
    ],
    "wof:name":"Lambrechts Cecile",
    "wof:placetype":"venue"
},
  "geometry": {"coordinates":[4.2269968987,50.495388031],"type":"Point"}
}