{
  "type": "Feature",
  "properties": {
    "iso:country":"BE",
    "sg:address":"Regentiestraat 35",
    "sg:city":"Stekene (kemzeke)",
    "sg:classifiers":[
        {
            "category":"Building & Trades",
            "subcategory":"Plumbing",
            "type":"Services"
        }
    ],
    "sg:phone":"+32 3 779 87 80",
    "sg:postcode":"9190",
    "sg:province":"Oost-Vlaanderen",
    "sg:tags":[
        "contractor"
    ],
    "wof:name":"Rotthier L",
    "wof:placetype":"venue"
},
  "geometry": {"coordinates":[4.0724577904,51.2047576904],"type":"Point"}
}