{
  "type": "Feature",
  "properties": {
    "addr:full":"Lippenslaan 12 Knokke-heist West-Vlaanderen 8300",
    "addr:housenumber":"12",
    "addr:postcode":"8300",
    "addr:street":"Lippenslaan",
    "iso:country":"BE",
    "sg:address":"Lippenslaan 12",
    "sg:city":"Knokke-heist",
    "sg:classifiers":[
        {
            "category":"Restaurant",
            "type":"Food & Drink"
        }
    ],
    "sg:phone":"+32 50 60 51 88",
    "sg:postcode":"8300",
    "sg:province":"West-Vlaanderen",
    "wof:name":"China City",
    "wof:placetype":"venue"
},
  "geometry": {"coordinates":[3.2873730659,51.3414878845],"type":"Point"}
}