{
  "type": "Feature",
  "properties": {
    "addr:full":"Rue Piretfontaine 38 Sprimont (dolembreux) Li\u00e8ge 4140",
    "addr:housenumber":"38",
    "addr:postcode":"4140",
    "addr:street":"Rue Piretfontaine",
    "iso:country":"BE",
    "sg:address":"Rue Piretfontaine 38",
    "sg:city":"Sprimont (dolembreux)",
    "sg:classifiers":[
        {
            "category":"Health Services",
            "subcategory":"Health Practitioner",
            "type":"Services"
        }
    ],
    "sg:phone":"+32 4 388 48 40",
    "sg:postcode":"4140",
    "sg:province":"Li\u00e8ge",
    "sg:tags":[
        "psychologist"
    ],
    "wof:name":"Blochousse L",
    "wof:placetype":"venue"
},
  "geometry": {"coordinates":[5.6390562057,50.5382575989],"type":"Point"}
}