{
  "type": "Feature",
  "properties": {
    "iso:country":"BE",
    "sg:address":"Rue Van Opr\u00e9 97",
    "sg:city":"Namur (jambes)",
    "sg:classifiers":[
        {
            "category":"Professional",
            "subcategory":"Art Services",
            "type":"Services"
        }
    ],
    "sg:phone":"+32 2 460 70 00",
    "sg:postcode":"5100",
    "sg:province":"Namur",
    "sg:tags":[
        "photographer",
        "aerial",
        "-"
    ],
    "wof:name":"Walphot Sa",
    "wof:placetype":"venue"
},
  "geometry": {"coordinates":[4.8759670258,50.4609184265],"type":"Point"}
}