{
  "type": "Feature",
  "properties": {
    "addr:full":"All\u00e9e Des Pins 15 Ch\u00e2telet (ch\u00e2telineau) Hainaut 6200",
    "addr:housenumber":"15",
    "addr:postcode":"6200",
    "addr:street":"Alle\u0301E Des Pins",
    "iso:country":"BE",
    "sg:address":"All\u00e9e Des Pins 15",
    "sg:city":"Ch\u00e2telet (ch\u00e2telineau)",
    "sg:classifiers":[
        {
            "category":"Health Services",
            "subcategory":"Health Practitioner",
            "type":"Services"
        }
    ],
    "sg:phone":"+32 71 38 89 21",
    "sg:postcode":"6200",
    "sg:province":"Hainaut",
    "sg:tags":[
        "physiotherapist"
    ],
    "wof:name":"Van Der Elst Isabelle",
    "wof:placetype":"venue"
},
  "geometry": {"coordinates":[4.5101699829,50.425113678],"type":"Point"}
}