{
  "type": "Feature",
  "properties": {
    "iso:country":"BE",
    "sg:address":"Leopold Ii-laan 35",
    "sg:city":"Brugge",
    "sg:orig_category":"Reclamebureaus",
    "sg:phone":"+32 50 33 95 00",
    "sg:postcode":"8000",
    "sg:province":"West-Vlaanderen",
    "wof:name":"Kwink",
    "wof:placetype":"venue"
},
  "geometry": {"coordinates":[3.2173719406,51.2197189331],"type":"Point"}
}