{
  "type": "Feature",
  "properties": {
    "iso:country":"BE",
    "sg:address":"Dokter Jean Jolyplein 2",
    "sg:city":"Etterbeek",
    "sg:orig_category":"Rusthuizen and serviceflats",
    "sg:phone":"+32 2 641 43 25",
    "sg:postcode":"1040",
    "sg:province":"Bruxelles-Capitale",
    "wof:name":"Rust- & Verzorgingstehuis/jardin De La Chasse",
    "wof:placetype":"venue"
},
  "geometry": {"coordinates":[4.3898282051,50.8288536072],"type":"Point"}
}