{
  "type": "Feature",
  "properties": {
    "addr:full":"Rue Du N\u00c9blon 41 Hamoir Li\u00e8ge 4180",
    "addr:housenumber":"41",
    "addr:postcode":"4180",
    "addr:street":"Rue Du Ne\u0301Blon",
    "iso:country":"BE",
    "sg:address":"Rue Du N\u00c9blon 41",
    "sg:city":"Hamoir",
    "sg:orig_category":"Drogisterijen",
    "sg:phone":"+32 86 38 80 85",
    "sg:postcode":"4180",
    "sg:province":"Li\u00e8ge",
    "wof:name":"Maison Legros & Fils",
    "wof:placetype":"venue"
},
  "geometry": {"coordinates":[5.5273241997,50.4264144897],"type":"Point"}
}