{
  "type": "Feature",
  "properties": {
    "addr:full":"Alphenseweg 7ba Baarle-hertog Antwerpen 2387",
    "addr:housenumber":"7ba",
    "addr:postcode":"2387",
    "addr:street":"Alphenseweg",
    "iso:country":"BE",
    "sg:address":"Alphenseweg 7ba",
    "sg:city":"Baarle-hertog",
    "sg:orig_category":"Eleveurs de volaille",
    "sg:phone":"+32 14 69 95 89",
    "sg:postcode":"2387",
    "sg:province":"Antwerpen",
    "wof:name":"Karel Meeuwesen",
    "wof:placetype":"venue"
},
  "geometry": {"coordinates":[4.9378371239,51.4484100342],"type":"Point"}
}