{
  "type": "Feature",
  "properties": {
    "iso:country":"BE",
    "sg:address":"Gasdam 7",
    "sg:city":"Beveren",
    "sg:orig_category":"Installation \u00e9lectrique r\u00e9sidentielle",
    "sg:phone":"+32 3 775 11 41",
    "sg:postcode":"9120",
    "sg:province":"Oost-Vlaanderen",
    "wof:name":"Eku",
    "wof:placetype":"venue"
},
  "geometry": {"coordinates":[4.2610578537,51.207698822],"type":"Point"}
}