{
  "type": "Feature",
  "properties": {
    "iso:country":"BE",
    "sg:address":"Rue De La Station 32",
    "sg:city":"Les Bons Villers (r\u00eaves)",
    "sg:classifiers":[
        {
            "category":"Real Estate",
            "subcategory":"Real Estate Services",
            "type":"Services"
        }
    ],
    "sg:phone":"+32 71 84 06 09",
    "sg:postcode":"6210",
    "sg:province":"Hainaut",
    "wof:name":"Imhotep Sprl",
    "wof:placetype":"venue"
},
  "geometry": {"coordinates":[4.4132118225,50.5411987305],"type":"Point"}
}