{
  "type": "Feature",
  "properties": {
    "addr:full":"Avenue Adolphe Buyl 80 Elsene/ixelles Bruxelles-Capitale 1050",
    "addr:housenumber":"80",
    "addr:postcode":"1050",
    "addr:street":"Avenue Adolphe Buyl",
    "iso:country":"BE",
    "sg:address":"Avenue Adolphe Buyl 80",
    "sg:city":"Elsene/ixelles",
    "sg:orig_category":"Librairies. Journaux. Tabac",
    "sg:phone":"+32 2 647 27 50",
    "sg:postcode":"1050",
    "sg:province":"Bruxelles-Capitale",
    "wof:name":"Couleurs Du Sud",
    "wof:placetype":"venue"
},
  "geometry": {"coordinates":[4.382185936,50.8166656494],"type":"Point"}
}