{
  "type": "Feature",
  "properties": {
    "addr:full":"Meerlaarstraat 119 Box 1 Laakdal (forest) Antwerpen 2430",
    "addr:housenumber":"119;1",
    "addr:postcode":"2430",
    "addr:street":"Meerlaarstraat;Box",
    "iso:country":"BE",
    "sg:address":"Meerlaarstraat 119 Box 1",
    "sg:city":"Laakdal (forest)",
    "sg:classifiers":[
        {
            "category":"Professional",
            "subcategory":"Lawyer & Legal Services",
            "type":"Services"
        }
    ],
    "sg:phone":"+32 13 66 75 17",
    "sg:postcode":"2430",
    "sg:province":"Antwerpen",
    "wof:name":"De Vis Dirk",
    "wof:placetype":"venue"
},
  "geometry": {"coordinates":[5.0891089439,51.0860519409],"type":"Point"}
}