{
  "type": "Feature",
  "properties": {
    "iso:country":"BE",
    "sg:address":"Lieven Gevaertstraat 12",
    "sg:city":"Mortsel",
    "sg:classifiers":[
        {
            "category":"Personal",
            "subcategory":"Beauty Salon",
            "type":"Services"
        }
    ],
    "sg:phone":"+32 3 449 81 09",
    "sg:postcode":"2640",
    "sg:province":"Antwerpen",
    "sg:tags":[
        "lady",
        "-",
        "hairdressing"
    ],
    "wof:name":"Robert Doms Coiffure",
    "wof:placetype":"venue"
},
  "geometry": {"coordinates":[4.4417338371,51.1746635437],"type":"Point"}
}