{
  "type": "Feature",
  "properties": {
    "iso:country":"BE",
    "sg:address":"Rue Des Thiers 5ba",
    "sg:city":"Stavelot",
    "sg:orig_category":"Sportclubs",
    "sg:phone":"+32 87 27 55 76",
    "sg:postcode":"4970",
    "sg:province":"Li\u00e8ge",
    "wof:name":"Badminton Club Malmedy",
    "wof:placetype":"venue"
},
  "geometry": {"coordinates":[5.9518032074,50.4526824951],"type":"Point"}
}