{
  "type": "Feature",
  "properties": {
    "iso:country":"BE",
    "sg:address":"Boulevard Gustave-kleyer 178",
    "sg:city":"Li\u00e8ge 1",
    "sg:classifiers":[
        {
            "category":"Personal",
            "subcategory":"Psychics & Astrologers",
            "type":"Services"
        }
    ],
    "sg:phone":"+32 4 253 07 35",
    "sg:postcode":"4000",
    "sg:province":"Li\u00e8ge",
    "sg:tags":[
        "astrology"
    ],
    "wof:name":"De Lancelle",
    "wof:placetype":"venue"
},
  "geometry": {"coordinates":[5.5621671677,50.6245880127],"type":"Point"}
}