{
  "type": "Feature",
  "properties": {
    "addr:full":"Burg. L. Pussemierstraat 35 Eeklo Oost-Vlaanderen 9900",
    "addr:housenumber":"35",
    "addr:postcode":"9900",
    "addr:street":"Burg.;Pussemierstraat",
    "iso:country":"BE",
    "sg:address":"Burg. L. Pussemierstraat 35",
    "sg:city":"Eeklo",
    "sg:classifiers":[
        {
            "category":"Cafe",
            "type":"Food & Drink"
        }
    ],
    "sg:phone":"+32 9 378 46 47",
    "sg:postcode":"9900",
    "sg:province":"Oost-Vlaanderen",
    "sg:tags":[
        "caf\u00e9s"
    ],
    "wof:name":"Caf\u00c9 De Pussemier",
    "wof:placetype":"venue"
},
  "geometry": {"coordinates":[3.5761370659,51.1889152527],"type":"Point"}
}