{
  "type": "Feature",
  "properties": {
    "addr:full":"Korte Beeldekensstraat 1 Antwerpen Antwerpen 2060",
    "addr:housenumber":"1",
    "addr:postcode":"2060",
    "addr:street":"Korte Beeldekensstraat",
    "iso:country":"BE",
    "sg:address":"Korte Beeldekensstraat 1",
    "sg:city":"Antwerpen",
    "sg:orig_category":"Epiceries",
    "sg:phone":"+32 3 272 58 74",
    "sg:postcode":"2060",
    "sg:province":"Antwerpen",
    "wof:name":"Nash",
    "wof:placetype":"venue"
},
  "geometry": {"coordinates":[4.433535099,51.2217102051],"type":"Point"}
}