{
  "type": "Feature",
  "properties": {
    "iso:country":"BE",
    "sg:address":"Leuzesesteenweg 417",
    "sg:city":"Ronse/renaix",
    "sg:orig_category":"Bouwmaterialen Gh Gespecialiseerde residenti\u00eble bouw Woningbouw",
    "sg:phone":"+32 55 20 87 55",
    "sg:postcode":"9600",
    "sg:province":"Oost-Vlaanderen",
    "wof:name":"Rimbaut Bouwwerken",
    "wof:placetype":"venue"
},
  "geometry": {"coordinates":[3.5894310474,50.7331008911],"type":"Point"}
}