{
  "type": "Feature",
  "properties": {
    "addr:full":"Hogeweg 57 Aalst Oost-Vlaanderen 9320",
    "addr:housenumber":"57",
    "addr:postcode":"9320",
    "addr:street":"Hogeweg",
    "iso:country":"BE",
    "sg:address":"Hogeweg 57",
    "sg:city":"Aalst",
    "sg:orig_category":"Studios photographiques",
    "sg:phone":"+32 53 21 20 91",
    "sg:postcode":"9320",
    "sg:province":"Oost-Vlaanderen",
    "wof:name":"Studio De Vic",
    "wof:placetype":"venue"
},
  "geometry": {"coordinates":[4.0553851128,50.9209976196],"type":"Point"}
}