{
  "type": "Feature",
  "properties": {
    "addr:full":"Chauss\u00c9e De Louvain 109 Eghezee Namur 5310",
    "addr:housenumber":"109",
    "addr:postcode":"5310",
    "addr:street":"Chausse\u0301E De Louvain;Namur",
    "iso:country":"BE",
    "sg:address":"Chauss\u00c9e De Louvain 109",
    "sg:city":"Eghezee",
    "sg:orig_category":"Afval and schroot Gh",
    "sg:phone":"+32 81 81 15 02",
    "sg:postcode":"5310",
    "sg:province":"Namur",
    "wof:name":"Jeannine Jolly",
    "wof:placetype":"venue"
},
  "geometry": {"coordinates":[4.9029140472,50.6001014709],"type":"Point"}
}