{
  "type": "Feature",
  "properties": {
    "iso:country":"BE",
    "sg:address":"Rue De La Poste 37",
    "sg:city":"Bruxelles (saint-josse-ten-noode)",
    "sg:classifiers":[
        {
            "category":"Social Services",
            "type":"Services"
        }
    ],
    "sg:phone":"+32 2 218 23 71",
    "sg:postcode":"1210",
    "sg:province":"Bruxelles-Capitale",
    "wof:name":"Mrax Asbl",
    "wof:placetype":"venue"
},
  "geometry": {"coordinates":[4.3661389351,50.8565406799],"type":"Point"}
}