{
  "type": "Feature",
  "properties": {
    "iso:country":"BE",
    "sg:address":"Tienderstraat 67",
    "sg:city":"Meeuwen-gruitrode",
    "sg:orig_category":"Boucheries",
    "sg:phone":"+32 89 85 72 95",
    "sg:postcode":"3670",
    "sg:province":"Limburg",
    "wof:name":"Leonardus Vandewal",
    "wof:placetype":"venue"
},
  "geometry": {"coordinates":[5.6160469055,51.0877342224],"type":"Point"}
}