{
  "type": "Feature",
  "properties": {
    "addr:full":"Rue Saint-nicolas 37 Namur Namur 5000",
    "addr:housenumber":"37",
    "addr:postcode":"5000",
    "addr:street":"Rue Saint-Nicolas",
    "iso:country":"BE",
    "sg:address":"Rue Saint-nicolas 37",
    "sg:city":"Namur",
    "sg:orig_category":"Vakbonden",
    "sg:phone":"+32 81 23 04 10",
    "sg:postcode":"5000",
    "sg:province":"Namur",
    "wof:name":"S.e.t.c.a.",
    "wof:placetype":"venue"
},
  "geometry": {"coordinates":[4.8714761734,50.4639358521],"type":"Point"}
}