{
  "type": "Feature",
  "properties": {
    "iso:country":"BE",
    "sg:address":"Stationsstraat 40",
    "sg:city":"Zelzate",
    "sg:classifiers":[
        {
            "category":"Health Services",
            "subcategory":"Hospital",
            "type":"Services"
        }
    ],
    "sg:phone":"+32 9 345 93 33",
    "sg:postcode":"9060",
    "sg:province":"Oost-Vlaanderen",
    "wof:name":"Centrum Voor Funktionele Revalidatie Vzw",
    "wof:placetype":"venue"
},
  "geometry": {"coordinates":[3.8082199097,51.1997489929],"type":"Point"}
}