{
  "type": "Feature",
  "properties": {
    "addr:full":"Rue Des Pastures 95 Binche Hainaut 7130",
    "addr:housenumber":"95",
    "addr:postcode":"7130",
    "addr:street":"Rue Des Pastures",
    "iso:country":"BE",
    "sg:address":"Rue Des Pastures 95",
    "sg:city":"Binche",
    "sg:orig_category":"Agences de publicit\u00e9",
    "sg:phone":"+32 64 33 54 53",
    "sg:postcode":"7130",
    "sg:province":"Hainaut",
    "wof:name":"D.f.c.",
    "wof:placetype":"venue"
},
  "geometry": {"coordinates":[4.1713500023,50.4142684937],"type":"Point"}
}