{
  "type": "Feature",
  "properties": {
    "iso:country":"BE",
    "sg:address":"Mutsaardlaan 39",
    "sg:city":"Brussel/bruxelles",
    "sg:orig_category":"Apotheken",
    "sg:phone":"+32 2 262 09 72",
    "sg:postcode":"1020",
    "sg:province":"Bruxelles-Capitale",
    "wof:name":"Pharmacie Mutsaerd",
    "wof:placetype":"venue"
},
  "geometry": {"coordinates":[4.3568367958,50.8970870972],"type":"Point"}
}