{
  "type": "Feature",
  "properties": {
    "addr:full":"Uniestraat 42 Sint-joost-ten-node/saint-josse-ten-noode Bruxelles-Capitale 1210",
    "addr:housenumber":"42",
    "addr:postcode":"1210",
    "addr:street":"Uniestraat",
    "iso:country":"BE",
    "sg:address":"Uniestraat 42",
    "sg:city":"Sint-joost-ten-node/saint-josse-ten-noode",
    "sg:orig_category":"Artsen and specialisten",
    "sg:phone":"+32 2 217 92 15",
    "sg:postcode":"1210",
    "sg:province":"Bruxelles-Capitale",
    "wof:name":"S\u00c9bastien Convent",
    "wof:placetype":"venue"
},
  "geometry": {"coordinates":[4.370639801,50.8525733948],"type":"Point"}
}