{
  "type": "Feature",
  "properties": {
    "addr:full":"Huttegemstraat 48 Zwalm Oost-Vlaanderen 9630",
    "addr:housenumber":"48",
    "addr:postcode":"9630",
    "addr:street":"Huttegemstraat;Oost-Vlaanderen",
    "iso:country":"BE",
    "sg:address":"Huttegemstraat 48",
    "sg:city":"Zwalm",
    "sg:orig_category":"Installation de menuiserie en bois and plastique",
    "sg:phone":"+32 55 49 80 97",
    "sg:postcode":"9630",
    "sg:province":"Oost-Vlaanderen",
    "wof:name":"Eylenbosch Andre",
    "wof:placetype":"venue"
},
  "geometry": {"coordinates":[3.7495338917,50.8601837158],"type":"Point"}
}