{
  "type": "Feature",
  "properties": {
    "iso:country":"BE",
    "sg:address":"Stalenstraat 74",
    "sg:city":"Genk",
    "sg:orig_category":"V\u00eatements pour b\u00e9b\u00e9s and enfants. V\u00eatements pour Dames. V\u00eatements pour Hommes",
    "sg:phone":"+32 89 38 09 16",
    "sg:postcode":"3600",
    "sg:province":"Limburg",
    "wof:name":"Jbc Mode",
    "wof:placetype":"venue"
},
  "geometry": {"coordinates":[5.5185499191,50.9935188293],"type":"Point"}
}