{
  "type": "Feature",
  "properties": {
    "iso:country":"BE",
    "sg:address":"Avenue Andr\u00c9 Gr\u00c9goire 5",
    "sg:city":"Stavelot",
    "sg:orig_category":"Meubles D\u00e9taillants, Am\u00e9nagement de B\u00e2timents et de Cuisines. Installation de menuiserie en bois and",
    "sg:phone":"+32 80 86 26 30",
    "sg:postcode":"4970",
    "sg:province":"Li\u00e8ge",
    "wof:name":"Fontaine Stavelot",
    "wof:placetype":"venue"
},
  "geometry": {"coordinates":[5.9236021042,50.3911094666],"type":"Point"}
}