{
  "type": "Feature",
  "properties": {
    "addr:full":"Rue Du Laminoir 109 Charleroi Hainaut 6060",
    "addr:housenumber":"109",
    "addr:postcode":"6060",
    "addr:street":"Rue Du Laminoir;Hainaut",
    "iso:country":"BE",
    "sg:address":"Rue Du Laminoir 109",
    "sg:city":"Charleroi",
    "sg:orig_category":"Installatie van houten of kunststof schrijnwerk",
    "sg:phone":"+32 71 41 68 18",
    "sg:postcode":"6060",
    "sg:province":"Hainaut",
    "wof:name":"Johnny Hayette",
    "wof:placetype":"venue"
},
  "geometry": {"coordinates":[4.4880981445,50.4251937866],"type":"Point"}
}