{
  "type": "Feature",
  "properties": {
    "addr:full":"Wanzeledorp 16 Lede Oost-Vlaanderen 9340",
    "addr:housenumber":"16",
    "addr:postcode":"9340",
    "addr:street":"Wanzeledorp",
    "iso:country":"BE",
    "sg:address":"Wanzeledorp 16",
    "sg:city":"Lede",
    "sg:orig_category":"Enseignement maternel and primaire",
    "sg:phone":"+32 53 80 32 16",
    "sg:postcode":"9340",
    "sg:province":"Oost-Vlaanderen",
    "wof:name":"Vrije Basisschool",
    "wof:placetype":"venue"
},
  "geometry": {"coordinates":[3.9571199417,50.9748382568],"type":"Point"}
}