{
  "type": "Feature",
  "properties": {
    "addr:full":"Mulkerweg 16 Tongeren Limburg 3700",
    "addr:housenumber":"16",
    "addr:postcode":"3700",
    "addr:street":"Mulkerweg",
    "iso:country":"BE",
    "sg:address":"Mulkerweg 16",
    "sg:city":"Tongeren",
    "sg:classifiers":[
        {
            "category":"Personal",
            "subcategory":"Barber",
            "type":"Services"
        }
    ],
    "sg:phone":"+32 12 23 00 25",
    "sg:postcode":"3700",
    "sg:province":"Limburg",
    "sg:tags":[
        "gentleman",
        "salon",
        "-",
        "hairdressing"
    ],
    "wof:name":"Carolus L",
    "wof:placetype":"venue"
},
  "geometry": {"coordinates":[5.455534935,50.7837562561],"type":"Point"}
}