{
  "type": "Feature",
  "properties": {
    "addr:full":"Chauss\u00c9e D\u00b4alsemberg 764 B Ukkel/uccle Bruxelles-Capitale 1180",
    "addr:housenumber":"764 b",
    "addr:postcode":"1180",
    "addr:street":"Chausse\u0301E D\u00b4Alsemberg;/",
    "iso:country":"BE",
    "sg:address":"Chauss\u00c9e D\u00b4alsemberg 764 B",
    "sg:city":"Ukkel/uccle",
    "sg:orig_category":"Agences d\u00b4interim and personnel temporaire",
    "sg:phone":"+32 2 376 35 25",
    "sg:postcode":"1180",
    "sg:province":"Bruxelles-Capitale",
    "wof:name":"People Interim",
    "wof:placetype":"venue"
},
  "geometry": {"coordinates":[4.3367571831,50.799987793],"type":"Point"}
}