{
  "type": "Feature",
  "properties": {
    "iso:country":"BE",
    "sg:address":"Filip De Pillecynlaan 2",
    "sg:city":"Hamme",
    "sg:orig_category":"Boucheries",
    "sg:phone":"+32 52 47 81 82",
    "sg:postcode":"9220",
    "sg:province":"Oost-Vlaanderen",
    "wof:name":"Benny Monsieur",
    "wof:placetype":"venue"
},
  "geometry": {"coordinates":[4.1522040367,51.0898475647],"type":"Point"}
}