{
  "type": "Feature",
  "properties": {
    "iso:country":"BE",
    "sg:address":"E Beernaertstraat 88",
    "sg:city":"Oostende",
    "sg:classifiers":[
        {
            "category":"Building & Trades",
            "subcategory":"Landscaping Services",
            "type":"Services"
        }
    ],
    "sg:phone":"+32 59 50 30 59",
    "sg:postcode":"8400",
    "sg:province":"West-Vlaanderen",
    "sg:tags":[
        "etude",
        "technique",
        "ing\u00e9nierie"
    ],
    "wof:name":"Haegebaert",
    "wof:placetype":"venue"
},
  "geometry": {"coordinates":[2.9128448963,51.2269020081],"type":"Point"}
}