{
  "type": "Feature",
  "properties": {
    "iso:country":"BE",
    "sg:address":"Beekstraat 53",
    "sg:city":"Assenede",
    "sg:orig_category":"Afbraak- and draineerwerken",
    "sg:phone":"+32 9 373 47 39",
    "sg:postcode":"9968",
    "sg:province":"Oost-Vlaanderen",
    "wof:name":"P. Blomme",
    "wof:placetype":"venue"
},
  "geometry": {"coordinates":[3.6887938976,51.1923027039],"type":"Point"}
}