{
  "type": "Feature",
  "properties": {
    "addr:full":"Bilzersteenweg 16 Riemst Limburg 3770",
    "addr:housenumber":"16",
    "addr:postcode":"3770",
    "addr:street":"Bilzersteenweg",
    "iso:country":"BE",
    "sg:address":"Bilzersteenweg 16",
    "sg:city":"Riemst",
    "sg:classifiers":[
        {
            "category":"Building & Trades",
            "subcategory":"Construction",
            "type":"Services"
        }
    ],
    "sg:phone":"+32 12 45 69 43",
    "sg:postcode":"3770",
    "sg:province":"Limburg",
    "sg:tags":[
        "stucco",
        "contractor"
    ],
    "wof:name":"Castermans Dirk Bvba",
    "wof:placetype":"venue"
},
  "geometry": {"coordinates":[5.5946531296,50.8127708435],"type":"Point"}
}