{
  "type": "Feature",
  "properties": {
    "iso:country":"BE",
    "sg:address":"Gauwelstraat 5",
    "sg:city":"Zwevegem",
    "sg:orig_category":"S\u00e9lection de personnel and placement",
    "sg:phone":"+32 56 64 44 08",
    "sg:postcode":"8551",
    "sg:province":"West-Vlaanderen",
    "wof:name":"Pwa Zwevegem",
    "wof:placetype":"venue"
},
  "geometry": {"coordinates":[3.4099640846,50.7823028564],"type":"Point"}
}