{
  "type": "Feature",
  "properties": {
    "addr:full":"Rue Paquay 96 Seraing Li\u00e8ge 4100",
    "addr:housenumber":"96",
    "addr:postcode":"4100",
    "addr:street":"Rue Paquay",
    "iso:country":"BE",
    "sg:address":"Rue Paquay 96",
    "sg:city":"Seraing",
    "sg:classifiers":[
        {
            "category":"Health Services",
            "subcategory":"Doctor",
            "type":"Services"
        }
    ],
    "sg:phone":"+32 4 336 18 81",
    "sg:postcode":"4100",
    "sg:province":"Li\u00e8ge",
    "sg:tags":[
        "medicinephysicians",
        "surgeon"
    ],
    "wof:name":"Broonen A",
    "wof:placetype":"venue"
},
  "geometry": {"coordinates":[5.5221891403,50.6003646851],"type":"Point"}
}