{
  "type": "Feature",
  "properties": {
    "addr:full":"Rue Solvay 41 Jemeppe-sur-sambre Namur 5190",
    "addr:housenumber":"41",
    "addr:postcode":"5190",
    "addr:street":"Rue Solvay",
    "iso:country":"BE",
    "sg:address":"Rue Solvay 41",
    "sg:city":"Jemeppe-sur-sambre",
    "sg:orig_category":"Verplichte sociale verzekeringen",
    "sg:phone":"+32 71 26 85 88",
    "sg:postcode":"5190",
    "sg:province":"Namur",
    "wof:name":"Mutualit\u00c9 Profess.& Libre",
    "wof:placetype":"venue"
},
  "geometry": {"coordinates":[4.6612968445,50.4494857788],"type":"Point"}
}