{
  "type": "Feature",
  "properties": {
    "addr:full":"Maststraat 41 Essen Antwerpen 2910",
    "addr:housenumber":"41",
    "addr:postcode":"2910",
    "addr:street":"Maststraat",
    "iso:country":"BE",
    "sg:address":"Maststraat 41",
    "sg:city":"Essen",
    "sg:classifiers":[
        {
            "category":"Restaurant",
            "type":"Food & Drink"
        }
    ],
    "sg:phone":"+32 3 677 14 00",
    "sg:postcode":"2910",
    "sg:province":"Antwerpen",
    "wof:name":"De Schouw",
    "wof:placetype":"venue"
},
  "geometry": {"coordinates":[4.4430952072,51.454334259],"type":"Point"}
}