{
  "type": "Feature",
  "properties": {
    "iso:country":"BE",
    "sg:address":"Rue Des Trois Ponts 30",
    "sg:city":"Bruxelles (auderghem)",
    "sg:classifiers":[
        {
            "category":"Sports & Exercise",
            "subcategory":"Gym",
            "type":"Entertainment"
        }
    ],
    "sg:phone":"+32 2 660 42 01",
    "sg:postcode":"1160",
    "sg:province":"Bruxelles-Capitale",
    "sg:tags":[
        "fitness"
    ],
    "wof:name":"Energym",
    "wof:placetype":"venue"
},
  "geometry": {"coordinates":[4.4077739716,50.8205184937],"type":"Point"}
}