{
  "type": "Feature",
  "properties": {
    "addr:full":"Chauss\u00c9e De Nivelles 33 Sombreffe Namur 5140",
    "addr:housenumber":"33",
    "addr:postcode":"5140",
    "addr:street":"Chausse\u0301E De Nivelles",
    "iso:country":"BE",
    "sg:address":"Chauss\u00c9e De Nivelles 33",
    "sg:city":"Sombreffe",
    "sg:orig_category":"Postkantoren Verzekeringsmakelaars and experts",
    "sg:phone":"+32 71 88 81 85",
    "sg:postcode":"5140",
    "sg:province":"Namur",
    "wof:name":"La Poste",
    "wof:placetype":"venue"
},
  "geometry": {"coordinates":[4.6089091301,50.525428772],"type":"Point"}
}