{
  "type": "Feature",
  "properties": {
    "iso:country":"BE",
    "sg:address":"Trompstraat 38",
    "sg:city":"Stekene (kemzeke)",
    "sg:classifiers":[
        {
            "category":"Bars & Pubs",
            "type":"Food & Drink"
        }
    ],
    "sg:phone":"+32 3 789 24 22",
    "sg:postcode":"9190",
    "sg:province":"Oost-Vlaanderen",
    "wof:name":"Sophie Bistro",
    "wof:placetype":"venue"
},
  "geometry": {"coordinates":[4.0591840744,51.232875824],"type":"Point"}
}