{
  "type": "Feature",
  "properties": {
    "addr:full":"Vijfstraten 30 Sint-niklaas Oost-Vlaanderen 9100",
    "addr:housenumber":"30",
    "addr:postcode":"9100",
    "addr:street":"Vijfstraten",
    "iso:country":"BE",
    "sg:address":"Vijfstraten 30",
    "sg:city":"Sint-niklaas",
    "sg:orig_category":"Huisdieren and benodigdheden Royal Canin",
    "sg:phone":"+32 3 776 37 56",
    "sg:postcode":"9100",
    "sg:province":"Oost-Vlaanderen",
    "wof:name":"De Dierenwinkel Bvba",
    "wof:placetype":"venue"
},
  "geometry": {"coordinates":[4.15128088,51.1742782593],"type":"Point"}
}