{
  "type": "Feature",
  "properties": {
    "addr:full":"Leuvenselaan 88 Tienen Vlaams-Brabant 3300",
    "addr:housenumber":"88",
    "addr:postcode":"3300",
    "addr:street":"Leuvenselaan",
    "iso:country":"BE",
    "sg:address":"Leuvenselaan 88",
    "sg:city":"Tienen",
    "sg:classifiers":[
        {
            "category":"Shopping",
            "subcategory":"Jewelry",
            "type":"Retail Goods"
        }
    ],
    "sg:phone":"+32 16 82 33 29",
    "sg:postcode":"3300",
    "sg:province":"Vlaams-Brabant",
    "sg:tags":[
        "jeweller",
        "-"
    ],
    "wof:name":"Palme D'or",
    "wof:placetype":"venue"
},
  "geometry": {"coordinates":[4.9263939857,50.8105888367],"type":"Point"}
}