{
  "type": "Feature",
  "properties": {
    "addr:full":"Place De La Licourt 69 Herstal Li\u00e8ge 4040",
    "addr:housenumber":"69",
    "addr:postcode":"4040",
    "addr:street":"Place De La Licourt",
    "iso:country":"BE",
    "sg:address":"Place De La Licourt 69",
    "sg:city":"Herstal",
    "sg:classifiers":[
        {
            "category":"Health Services",
            "subcategory":"Dentist",
            "type":"Services"
        }
    ],
    "sg:phone":"+32 4 264 72 28",
    "sg:postcode":"4040",
    "sg:province":"Li\u00e8ge",
    "wof:name":"Rion C",
    "wof:placetype":"venue"
},
  "geometry": {"coordinates":[5.6394610405,50.6697463989],"type":"Point"}
}