{
  "type": "Feature",
  "properties": {
    "iso:country":"BE",
    "sg:address":"Kleine Heresteeg 74",
    "sg:city":"Houthalen-helchteren",
    "sg:orig_category":"R\u00e9parations d'appareils \u00e9lectrom\u00e9nagers. Electrom\u00e9nager, t\u00e9l\u00e9visions and radios",
    "sg:phone":"+32 11 52 21 48",
    "sg:postcode":"3530",
    "sg:province":"Limburg",
    "wof:name":"Marcel Gielissen",
    "wof:placetype":"venue"
},
  "geometry": {"coordinates":[5.3803071976,51.0394134521],"type":"Point"}
}