{
  "type": "Feature",
  "properties": {
    "addr:full":"Rue Vx March\u00c9 Aux Grains 47b51 Brussel/bruxelles Bruxelles-Capitale 1000",
    "addr:housenumber":"47b51",
    "addr:postcode":"1000",
    "addr:street":"Rue Vx Marche\u0301 Aux Grains;/",
    "iso:country":"BE",
    "sg:address":"Rue Vx March\u00c9 Aux Grains 47b51",
    "sg:city":"Brussel/bruxelles",
    "sg:orig_category":"Entretien et r\u00e9parations de v\u00e9hicules \u00e0 domicile. Entretien and r\u00e9parations de voitures. R\u00e9cup\u00e9ratio",
    "sg:phone":"+32 2 649 95 26",
    "sg:postcode":"1000",
    "sg:province":"Bruxelles-Capitale",
    "wof:name":"Fe. Radar",
    "wof:placetype":"venue"
},
  "geometry": {"coordinates":[4.3513898849,50.8584594727],"type":"Point"}
}