{
  "type": "Feature",
  "properties": {
    "iso:country":"BE",
    "sg:address":"Gasmeterlaan 210",
    "sg:city":"Gent",
    "sg:orig_category":"Equipements divers pour l\u00b4industrie Gr. Quincaillerie Gr",
    "sg:phone":"+32 9 225 94 67",
    "sg:postcode":"9000",
    "sg:province":"Oost-Vlaanderen",
    "wof:name":"Dezutter",
    "wof:placetype":"venue"
},
  "geometry": {"coordinates":[3.7241010666,51.0674591064],"type":"Point"}
}