{
  "type": "Feature",
  "properties": {
    "addr:full":"Diestseweg 108 Geel Antwerpen 2440",
    "addr:housenumber":"108",
    "addr:postcode":"2440",
    "addr:street":"Diestseweg",
    "iso:country":"BE",
    "sg:address":"Diestseweg 108",
    "sg:city":"Geel",
    "sg:orig_category":"Etalage- and showroomontwerpers",
    "sg:phone":"+32 14 58 00 94",
    "sg:postcode":"2440",
    "sg:province":"Antwerpen",
    "wof:name":"Nancy Bens",
    "wof:placetype":"venue"
},
  "geometry": {"coordinates":[4.993678093,51.1577186584],"type":"Point"}
}