{
  "type": "Feature",
  "properties": {
    "addr:full":"Rue Foss\u00e9 Botton 9 Juprelle (fexhe-slins) Li\u00e8ge 4458",
    "addr:housenumber":"9",
    "addr:postcode":"4458",
    "addr:street":"Rue Fosse\u0301 Botton;Fexhe-Slins",
    "iso:country":"BE",
    "sg:address":"Rue Foss\u00e9 Botton 9",
    "sg:city":"Juprelle (fexhe-slins)",
    "sg:classifiers":[
        {
            "category":"Professional",
            "subcategory":"Accounting & Tax Preparation",
            "type":"Services"
        }
    ],
    "sg:phone":"+32 4 278 73 31",
    "sg:postcode":"4458",
    "sg:province":"Li\u00e8ge",
    "sg:tags":[
        "accountant"
    ],
    "wof:name":"Skivee P",
    "wof:placetype":"venue"
},
  "geometry": {"coordinates":[5.5777859688,50.7171516418],"type":"Point"}
}