{
  "type": "Feature",
  "properties": {
    "iso:country":"BE",
    "sg:address":"Bruggestraat 6",
    "sg:city":"Ruiselede",
    "sg:classifiers":[
        {
            "category":"Health Services",
            "subcategory":"Dentist",
            "type":"Services"
        }
    ],
    "sg:phone":"+32 51 68 98 75",
    "sg:postcode":"8755",
    "sg:province":"West-Vlaanderen",
    "wof:name":"Debaets T",
    "wof:placetype":"venue"
},
  "geometry": {"coordinates":[3.3961338997,51.041847229],"type":"Point"}
}