{
  "type": "Feature",
  "properties": {
    "addr:full":"Rue Konkel 171-18 Bruxelles (woluwe-saint-pierre) Bruxelles-Capitale 1150",
    "addr:postcode":"171-18;woluwe-saint-pierre;1150",
    "addr:street":"Rue Konkel",
    "iso:country":"BE",
    "sg:address":"Rue Konkel 171-18",
    "sg:city":"Bruxelles (woluwe-saint-pierre)",
    "sg:classifiers":[
        {
            "category":"Health Services",
            "subcategory":"Doctor",
            "type":"Services"
        }
    ],
    "sg:phone":"+32 2 779 80 86",
    "sg:postcode":"1150",
    "sg:province":"Bruxelles-Capitale",
    "sg:tags":[
        "medicinephysicians",
        "surgeon"
    ],
    "wof:name":"Brichard B",
    "wof:placetype":"venue"
},
  "geometry": {"coordinates":[4.4501218796,50.8393058777],"type":"Point"}
}