{
  "type": "Feature",
  "properties": {
    "addr:full":"5 Rue Du Bois Brul\u00e9 Couture-st-germain Brabant Wallon 1380",
    "addr:housenumber":"5",
    "addr:postcode":"1380",
    "addr:street":"Rue Du Bois Brule\u0301",
    "iso:country":"BE",
    "sg:address":"5 Rue Du Bois Brul\u00e9",
    "sg:city":"Couture-st-germain",
    "sg:classifiers":[
        {
            "category":"Health Services",
            "subcategory":"Medical Lab",
            "type":"Services"
        }
    ],
    "sg:phone":"+32 2 633 30 50",
    "sg:postcode":"1380",
    "sg:province":"Brabant Wallon",
    "sg:tags":[
        "chemical",
        "pharmaceutical",
        "pharmacy"
    ],
    "wof:name":"Maduco Sprl",
    "wof:placetype":"venue"
},
  "geometry": {"coordinates":[4.4830918312,50.6604957581],"type":"Point"}
}