{
  "type": "Feature",
  "properties": {
    "addr:full":"Rue De Mons 25 Tubize Brabant Wallon 1480",
    "addr:housenumber":"25",
    "addr:postcode":"1480",
    "addr:street":"Rue De Mons;Wallon",
    "iso:country":"BE",
    "sg:address":"Rue De Mons 25",
    "sg:city":"Tubize",
    "sg:classifiers":[
        {
            "category":"Shopping",
            "subcategory":"Bicycles & Sporting Goods",
            "type":"Retail Goods"
        }
    ],
    "sg:phone":"+32 2 366 34 94",
    "sg:postcode":"1480",
    "sg:province":"Brabant Wallon",
    "sg:tags":[
        "sport",
        "-"
    ],
    "wof:name":"Mondial Sport",
    "wof:placetype":"venue"
},
  "geometry": {"coordinates":[4.2038469315,50.6920280457],"type":"Point"}
}