{
  "type": "Feature",
  "properties": {
    "addr:full":"Kruishuisstraat 84 Turnhout Antwerpen 2300",
    "addr:housenumber":"84",
    "addr:postcode":"2300",
    "addr:street":"Kruishuisstraat",
    "iso:country":"BE",
    "sg:address":"Kruishuisstraat 84",
    "sg:city":"Turnhout",
    "sg:orig_category":"Articles pour b\u00e9b\u00e9s. V\u00eatements pour b\u00e9b\u00e9s and enfants",
    "sg:phone":"+32 14 41 66 25",
    "sg:postcode":"2300",
    "sg:province":"Antwerpen",
    "wof:name":"Myriam Rosseau",
    "wof:placetype":"venue"
},
  "geometry": {"coordinates":[4.9405150414,51.3191642761],"type":"Point"}
}