{
  "type": "Feature",
  "properties": {
    "addr:full":"Rue De La Grattine 4b La Louvi\u00e8re Hainaut 7100",
    "addr:housenumber":"4b",
    "addr:postcode":"7100",
    "addr:street":"Rue De La Grattine",
    "iso:country":"BE",
    "sg:address":"Rue De La Grattine 4b",
    "sg:city":"La Louvi\u00e8re",
    "sg:classifiers":[
        {
            "category":"Shopping",
            "subcategory":"Pets & Pet Supplies",
            "type":"Retail Goods"
        }
    ],
    "sg:phone":"+32 64 22 33 34",
    "sg:postcode":"7100",
    "sg:province":"Hainaut",
    "sg:tags":[
        "shop",
        "-"
    ],
    "wof:name":"Tom & Co",
    "wof:placetype":"venue"
},
  "geometry": {"coordinates":[4.2020101547,50.4837913513],"type":"Point"}
}