{
  "type": "Feature",
  "properties": {
    "iso:country":"BE",
    "sg:address":"Treuveld 16",
    "sg:city":"Tervuren (vossem)",
    "sg:classifiers":[
        {
            "category":"Real Estate",
            "subcategory":"Architect",
            "type":"Services"
        }
    ],
    "sg:phone":"+32 2 767 16 52",
    "sg:postcode":"3080",
    "sg:province":"Vlaams-Brabant",
    "wof:name":"Beeckman N",
    "wof:placetype":"venue"
},
  "geometry": {"coordinates":[4.5530171394,50.8311233521],"type":"Point"}
}