{
  "type": "Feature",
  "properties": {
    "addr:full":"Poekedorpstraat 6 Aalter (poeke) Oost-Vlaanderen 9880",
    "addr:housenumber":"6",
    "addr:postcode":"9880",
    "addr:street":"Poekedorpstraat",
    "iso:country":"BE",
    "sg:address":"Poekedorpstraat 6",
    "sg:city":"Aalter (poeke)",
    "sg:classifiers":[
        {
            "category":"Social Services",
            "subcategory":"Child Care",
            "type":"Services"
        }
    ],
    "sg:phone":"+32 51 68 71 74",
    "sg:postcode":"9880",
    "sg:province":"Oost-Vlaanderen",
    "sg:tags":[
        "baby",
        "nursery",
        "day",
        "sitting"
    ],
    "wof:name":"Knuffel",
    "wof:placetype":"venue"
},
  "geometry": {"coordinates":[3.4474289417,51.0396347046],"type":"Point"}
}