{
  "type": "Feature",
  "properties": {
    "iso:country":"BE",
    "sg:address":"Kasteelstraat 10",
    "sg:city":"Ruiselede",
    "sg:orig_category":"Notaires",
    "sg:phone":"+32 51 68 85 20",
    "sg:postcode":"8755",
    "sg:province":"West-Vlaanderen",
    "wof:name":"Christophe Verhaeghe",
    "wof:placetype":"venue"
},
  "geometry": {"coordinates":[3.3963329792,51.0409049988],"type":"Point"}
}