{
  "type": "Feature",
  "properties": {
    "addr:full":"Nieuwstraat 19 Lierde Oost-Vlaanderen 9570",
    "addr:housenumber":"19",
    "addr:postcode":"9570",
    "addr:street":"Nieuwstraat",
    "iso:country":"BE",
    "sg:address":"Nieuwstraat 19",
    "sg:city":"Lierde",
    "sg:orig_category":"Offices du tourisme",
    "sg:phone":"+32 55 43 10 14",
    "sg:postcode":"9570",
    "sg:province":"Oost-Vlaanderen",
    "wof:name":"Dienst Voor Toerisme",
    "wof:placetype":"venue"
},
  "geometry": {"coordinates":[3.8236410618,50.8126411438],"type":"Point"}
}