{
  "type": "Feature",
  "properties": {
    "addr:full":"Stationsstraat 38 Oostkamp West-Vlaanderen 8020",
    "addr:housenumber":"38",
    "addr:postcode":"8020",
    "addr:street":"Stationsstraat",
    "iso:country":"BE",
    "sg:address":"Stationsstraat 38",
    "sg:city":"Oostkamp",
    "sg:classifiers":[
        {
            "category":"Shopping",
            "subcategory":"Clothing, Apparel, & Fashions",
            "type":"Retail Goods"
        }
    ],
    "sg:phone":"+32 50 84 04 24",
    "sg:postcode":"8020",
    "sg:province":"West-Vlaanderen",
    "sg:tags":[
        "boutique"
    ],
    "wof:name":"Milo",
    "wof:placetype":"venue"
},
  "geometry": {"coordinates":[3.2383129597,51.1539421082],"type":"Point"}
}