{
  "type": "Feature",
  "properties": {
    "addr:full":"Rue Du Cheval Blanc 96 Pont-\u00e0-celles (luttre) Hainaut 6238",
    "addr:housenumber":"96",
    "addr:postcode":"6238",
    "addr:street":"Rue Du Cheval Blanc",
    "iso:country":"BE",
    "sg:address":"Rue Du Cheval Blanc 96",
    "sg:city":"Pont-\u00e0-celles (luttre)",
    "sg:classifiers":[
        {
            "category":"Communications",
            "type":"Services"
        }
    ],
    "sg:phone":"+32 71 84 52 95",
    "sg:postcode":"6238",
    "sg:province":"Hainaut",
    "sg:tags":[
        "translator"
    ],
    "wof:name":"Havercroft",
    "wof:placetype":"venue"
},
  "geometry": {"coordinates":[4.3928208351,50.5018577576],"type":"Point"}
}