{
  "type": "Feature",
  "properties": {
    "addr:full":"Malibranstraat 42 Elsene/ixelles Bruxelles-Capitale 1050",
    "addr:housenumber":"42",
    "addr:postcode":"1050",
    "addr:street":"Malibranstraat",
    "iso:country":"BE",
    "sg:address":"Malibranstraat 42",
    "sg:city":"Elsene/ixelles",
    "sg:orig_category":"Brood, gebak and snoepgoed",
    "sg:phone":"+32 2 646 59 78",
    "sg:postcode":"1050",
    "sg:province":"Bruxelles-Capitale",
    "wof:name":"Boulang.-patis. Orientale",
    "wof:placetype":"venue"
},
  "geometry": {"coordinates":[4.3729581833,50.8302383423],"type":"Point"}
}