{
  "type": "Feature",
  "properties": {
    "addr:full":"Stationsstraat 57 Spiere-helkijn/espierres-helchin West-Vlaanderen 8587",
    "addr:housenumber":"57",
    "addr:postcode":"8587",
    "addr:street":"Stationsstraat",
    "iso:country":"BE",
    "sg:address":"Stationsstraat 57",
    "sg:city":"Spiere-helkijn/espierres-helchin",
    "sg:orig_category":"Rundveehouders Varkenskwekers",
    "sg:phone":"+32 56 45 50 03",
    "sg:postcode":"8587",
    "sg:province":"West-Vlaanderen",
    "wof:name":"Godfried Danneels",
    "wof:placetype":"venue"
},
  "geometry": {"coordinates":[3.3820838928,50.7396697998],"type":"Point"}
}