{
  "type": "Feature",
  "properties": {
    "addr:full":"Rue Du Moulin 14 Braine L'alleud (lillois-witterz\u00e9e) Brabant Wallon 1428",
    "addr:housenumber":"14",
    "addr:postcode":"1428",
    "addr:street":"Rue Du Moulin",
    "iso:country":"BE",
    "sg:address":"Rue Du Moulin 14",
    "sg:city":"Braine L'alleud (lillois-witterz\u00e9e)",
    "sg:classifiers":[
        {
            "category":"Professional",
            "subcategory":"Advertising",
            "type":"Services"
        }
    ],
    "sg:phone":"+32 2 387 18 80",
    "sg:postcode":"1428",
    "sg:province":"Brabant Wallon",
    "sg:tags":[
        "bill",
        "-",
        "posting"
    ],
    "wof:name":"Euromobile",
    "wof:placetype":"venue"
},
  "geometry": {"coordinates":[-0.708509028,47.4608650208],"type":"Point"}
}