{
  "type": "Feature",
  "properties": {
    "addr:full":"Oude Vest 95 Dendermonde Oost-Vlaanderen 9200",
    "addr:housenumber":"95",
    "addr:postcode":"9200",
    "addr:street":"Oude Vest;Oost-Vlaanderen",
    "iso:country":"BE",
    "sg:address":"Oude Vest 95",
    "sg:city":"Dendermonde",
    "sg:classifiers":[
        {
            "category":"Home & Garden",
            "subcategory":"Household Appliances",
            "type":"Retail Goods"
        }
    ],
    "sg:phone":"+32 52 21 10 16",
    "sg:postcode":"9200",
    "sg:province":"Oost-Vlaanderen",
    "sg:tags":[
        "repair",
        "mainten",
        "-",
        "electric"
    ],
    "wof:name":"Eeckhoudt Etienne",
    "wof:placetype":"venue"
},
  "geometry": {"coordinates":[4.1031899452,51.0303688049],"type":"Point"}
}