{
  "type": "Feature",
  "properties": {
    "iso:country":"BE",
    "sg:address":"Rue Charles Magnette 3c",
    "sg:city":"Li\u00e8ge 1",
    "sg:classifiers":[
        {
            "category":"Military Area",
            "subcategory":"Air Force Base",
            "type":"Public Place"
        }
    ],
    "sg:phone":"+32 4 223 65 36",
    "sg:postcode":"4000",
    "sg:province":"Li\u00e8ge",
    "sg:tags":[
        "herb",
        "-",
        "medicinal"
    ],
    "wof:name":"Herbier Du Mouton Blanc",
    "wof:placetype":"venue"
},
  "geometry": {"coordinates":[5.5743508339,50.6408996582],"type":"Point"}
}