{
  "type": "Feature",
  "properties": {
    "iso:country":"BE",
    "sg:address":"Rue Pierre-thomas 6b",
    "sg:city":"Bastogne",
    "sg:orig_category":"Bloemen and planten",
    "sg:phone":"+32 61 21 79 21",
    "sg:postcode":"6600",
    "sg:province":"Luxembourg",
    "wof:name":"Savelli",
    "wof:placetype":"venue"
},
  "geometry": {"coordinates":[5.7216701508,50.0080871582],"type":"Point"}
}