{
  "type": "Feature",
  "properties": {
    "iso:country":"BE",
    "sg:address":"Hengelsbroekweg 5",
    "sg:city":"Zonhoven",
    "sg:orig_category":"Producteurs de l\u00e9gumes",
    "sg:phone":"+32 11 82 19 07",
    "sg:postcode":"3520",
    "sg:province":"Limburg",
    "wof:name":"Georges Koonings",
    "wof:placetype":"venue"
},
  "geometry": {"coordinates":[5.4166917801,50.9983863831],"type":"Point"}
}