{
  "type": "Feature",
  "properties": {
    "iso:country":"BE",
    "sg:address":"Stevoortweg 111",
    "sg:city":"Herk-de-stad",
    "sg:orig_category":"Installatie van metalen schrijnwerk",
    "sg:phone":"+32 13 55 38 44",
    "sg:postcode":"3540",
    "sg:province":"Limburg",
    "wof:name":"Pools",
    "wof:placetype":"venue"
},
  "geometry": {"coordinates":[5.1824231148,50.9350738525],"type":"Point"}
}