{
  "type": "Feature",
  "properties": {
    "addr:full":"Rue Haute Marcelle 5 Namur Namur 5000",
    "addr:housenumber":"5",
    "addr:postcode":"5000",
    "addr:street":"Rue Haute Marcelle",
    "iso:country":"BE",
    "sg:address":"Rue Haute Marcelle 5",
    "sg:city":"Namur",
    "sg:classifiers":[
        {
            "category":"Shopping",
            "subcategory":"Clothing, Apparel, & Fashions",
            "type":"Retail Goods"
        }
    ],
    "sg:phone":"+32 81 22 31 71",
    "sg:postcode":"5000",
    "sg:province":"Namur",
    "sg:tags":[
        "-",
        "clothing",
        "child"
    ],
    "wof:name":"Jeux D'enfants",
    "wof:placetype":"venue"
},
  "geometry": {"coordinates":[4.8646969795,50.4643936157],"type":"Point"}
}