{
  "type": "Feature",
  "properties": {
    "addr:full":"Chauss\u00e9e De La Hulpe 324 Bruxelles (watermael-boitsfort) Bruxelles-Capitale 1170",
    "addr:housenumber":"324",
    "addr:postcode":"1170",
    "addr:street":"Chausse\u0301E De La Hulpe",
    "iso:country":"BE",
    "sg:address":"Chauss\u00e9e De La Hulpe 324",
    "sg:city":"Bruxelles (watermael-boitsfort)",
    "sg:classifiers":[
        {
            "category":"Utilities",
            "subcategory":"Telephone",
            "type":"Services"
        }
    ],
    "sg:phone":"+32 2 675 90 07",
    "sg:postcode":"1170",
    "sg:province":"Bruxelles-Capitale",
    "sg:tags":[
        "-",
        "internet"
    ],
    "wof:name":"Concept Advice",
    "wof:placetype":"venue"
},
  "geometry": {"coordinates":[4.4224448204,50.7906570435],"type":"Point"}
}