{
  "type": "Feature",
  "properties": {
    "iso:country":"BE",
    "sg:address":"Alexander Franckstraat 196",
    "sg:city":"Boechout",
    "sg:classifiers":[
        {
            "category":"Wholesale",
            "subcategory":"Tobacco Products",
            "type":"Manufacturing & Wholesale Goods"
        }
    ],
    "sg:phone":"+32 3 454 00 66",
    "sg:postcode":"2530",
    "sg:province":"Antwerpen",
    "sg:tags":[
        "-",
        "biotechnology",
        "installation",
        "equipment"
    ],
    "wof:name":"Sanvertech Nv",
    "wof:placetype":"venue"
},
  "geometry": {"coordinates":[4.5064787865,51.1585922241],"type":"Point"}
}