{
  "type": "Feature",
  "properties": {
    "addr:full":"Beverlosesteenweg 50 Beringen (paal) Limburg 3583",
    "addr:housenumber":"50",
    "addr:postcode":"3583",
    "addr:street":"Beverlosesteenweg",
    "iso:country":"BE",
    "sg:address":"Beverlosesteenweg 50",
    "sg:city":"Beringen (paal)",
    "sg:classifiers":[
        {
            "category":"Health Services",
            "subcategory":"Dentist",
            "type":"Services"
        }
    ],
    "sg:phone":"+32 11 42 29 14",
    "sg:postcode":"3583",
    "sg:province":"Limburg",
    "wof:name":"Smeets Fernand",
    "wof:placetype":"venue"
},
  "geometry": {"coordinates":[5.1706700325,51.0389442444],"type":"Point"}
}