{
  "type": "Feature",
  "properties": {
    "addr:full":"Rijselstraat 47 Mesen/messines West-Vlaanderen 8957",
    "addr:housenumber":"47",
    "addr:postcode":"8957",
    "addr:street":"Rijselstraat",
    "iso:country":"BE",
    "sg:address":"Rijselstraat 47",
    "sg:city":"Mesen/messines",
    "sg:orig_category":"Rundveehouders Varkenskwekers",
    "sg:phone":"+32 57 44 49 19",
    "sg:postcode":"8957",
    "sg:province":"West-Vlaanderen",
    "wof:name":"Eric Dessin",
    "wof:placetype":"venue"
},
  "geometry": {"coordinates":[2.9103999138,50.7586250305],"type":"Point"}
}