{
  "type": "Feature",
  "properties": {
    "iso:country":"BE",
    "sg:address":"All\u00e9e Verte 7",
    "sg:city":"Vis\u00e9",
    "sg:classifiers":[
        {
            "category":"Banks & Credit Unions",
            "subcategory":"Financial Services",
            "type":"Services"
        }
    ],
    "sg:phone":"+32 4 379 40 18",
    "sg:postcode":"4600",
    "sg:province":"Li\u00e8ge",
    "sg:tags":[
        "loan",
        "mortgage"
    ],
    "wof:name":"Bureau Technique Visetois D'assurances",
    "wof:placetype":"venue"
},
  "geometry": {"coordinates":[5.6789550781,50.7343673706],"type":"Point"}
}