{
  "type": "Feature",
  "properties": {
    "addr:full":"Hulleken 71 Evergem Oost-Vlaanderen 9940",
    "addr:housenumber":"71",
    "addr:postcode":"9940",
    "addr:street":"Hulleken;Oost-Vlaanderen",
    "iso:country":"BE",
    "sg:address":"Hulleken 71",
    "sg:city":"Evergem",
    "sg:classifiers":[
        {
            "category":"Education",
            "subcategory":"Dance Studio",
            "type":"Public Place"
        }
    ],
    "sg:phone":"+32 9 357 22 42",
    "sg:postcode":"9940",
    "sg:province":"Oost-Vlaanderen",
    "sg:tags":[
        "pallet"
    ],
    "wof:name":"Wihamij Bv",
    "wof:placetype":"venue"
},
  "geometry": {"coordinates":[3.6780900955,51.1202583313],"type":"Point"}
}