{
  "type": "Feature",
  "properties": {
    "iso:country":"BE",
    "sg:address":"Rue Bois-l\u00b4ev\u00caque 26",
    "sg:city":"Li\u00c8ge",
    "sg:orig_category":"Zalen voor culturele evenementen",
    "sg:phone":"+32 4 253 61 23",
    "sg:postcode":"4000",
    "sg:province":"Li\u00e8ge",
    "wof:name":"Groupov",
    "wof:placetype":"venue"
},
  "geometry": {"coordinates":[5.5607161522,50.628780365],"type":"Point"}
}