{
  "type": "Feature",
  "properties": {
    "addr:full":"Watermolenstraat 1 Lede Oost-Vlaanderen 9340",
    "addr:housenumber":"1",
    "addr:postcode":"9340",
    "addr:street":"Watermolenstraat",
    "iso:country":"BE",
    "sg:address":"Watermolenstraat 1",
    "sg:city":"Lede",
    "sg:orig_category":"Artsen and specialisten",
    "sg:phone":"+32 53 80 32 64",
    "sg:postcode":"9340",
    "sg:province":"Oost-Vlaanderen",
    "wof:name":"Lieve Meuleman",
    "wof:placetype":"venue"
},
  "geometry": {"coordinates":[3.9561889172,50.9730415344],"type":"Point"}
}