{
  "type": "Feature",
  "properties": {
    "addr:full":"Stationsstraat 40 Zaventem Vlaams-Brabant 1930",
    "addr:housenumber":"40",
    "addr:postcode":"1930",
    "addr:street":"Stationsstraat",
    "iso:country":"BE",
    "sg:address":"Stationsstraat 40",
    "sg:city":"Zaventem",
    "sg:orig_category":"Herstelling leer and schoeisel Herstellingswinkels voor diverse persoonlijke and huishoudartikelen",
    "sg:phone":"+32 2 721 09 97",
    "sg:postcode":"1930",
    "sg:province":"Vlaams-Brabant",
    "wof:name":"Mister Minit",
    "wof:placetype":"venue"
},
  "geometry": {"coordinates":[4.4723658562,50.8822822571],"type":"Point"}
}