{
  "type": "Feature",
  "properties": {
    "iso:country":"BE",
    "sg:address":"Av Franklin Roosevelt 138",
    "sg:city":"Bruxelles",
    "sg:orig_category":"Miscellaneous Products",
    "sg:phone":"+32 2 647 04 91",
    "sg:postcode":"1050",
    "sg:province":"Bruxelles-Capitale",
    "wof:name":"Vpc International Sa",
    "wof:placetype":"venue"
},
  "geometry": {"coordinates":[4.3866481781,50.8053970337],"type":"Point"}
}