{
  "type": "Feature",
  "properties": {
    "addr:full":"Beversesteenweg 427 Roeselare West-Vlaanderen 8800",
    "addr:housenumber":"427",
    "addr:postcode":"8800",
    "addr:street":"Beversesteenweg",
    "iso:country":"BE",
    "sg:address":"Beversesteenweg 427",
    "sg:city":"Roeselare",
    "sg:orig_category":"Binnenhuisarchitecten",
    "sg:phone":"+32 51 20 97 86",
    "sg:postcode":"8800",
    "sg:province":"West-Vlaanderen",
    "wof:name":"Bert Desmet Ontwerpsburo",
    "wof:placetype":"venue"
},
  "geometry": {"coordinates":[3.1597049236,50.9739112854],"type":"Point"}
}