{
  "type": "Feature",
  "properties": {
    "iso:country":"BE",
    "sg:address":"Enclos Tesni\u00c8re 1",
    "sg:city":"Neupre",
    "sg:orig_category":"Eleveurs de bovins. Eleveurs and marchands de porcs",
    "sg:phone":"+32 4 371 47 05",
    "sg:postcode":"4122",
    "sg:province":"Li\u00e8ge",
    "wof:name":"Marie Bare",
    "wof:placetype":"venue"
},
  "geometry": {"coordinates":[5.5163421631,50.5403442383],"type":"Point"}
}