{
  "type": "Feature",
  "properties": {
    "addr:full":"Slachthuisstraat 48 Sint-truiden Limburg 3800",
    "addr:housenumber":"48",
    "addr:postcode":"3800",
    "addr:street":"Slachthuisstraat",
    "iso:country":"BE",
    "sg:address":"Slachthuisstraat 48",
    "sg:city":"Sint-truiden",
    "sg:classifiers":[
        {
            "category":"Farming",
            "subcategory":"Crops",
            "type":"Manufacturing & Wholesale Goods"
        }
    ],
    "sg:phone":"+32 11 68 22 78",
    "sg:postcode":"3800",
    "sg:province":"Limburg",
    "sg:tags":[
        "vegetable",
        "fruit",
        "-",
        "grower"
    ],
    "wof:name":"Delwiche",
    "wof:placetype":"venue"
},
  "geometry": {"coordinates":[5.192056179,50.8195381165],"type":"Point"}
}