{
  "type": "Feature",
  "properties": {
    "addr:full":"Rue Du Parc Industriel 4 Amay Li\u00e8ge 4540",
    "addr:housenumber":"4",
    "addr:postcode":"4540",
    "addr:street":"Rue Du Parc Industriel",
    "iso:country":"BE",
    "sg:address":"Rue Du Parc Industriel 4",
    "sg:city":"Amay",
    "sg:classifiers":[
        {
            "category":"Manufacturing",
            "subcategory":"Motor Vehicles & Parts",
            "type":"Manufacturing & Wholesale Goods"
        }
    ],
    "sg:phone":"+32 85 51 96 96",
    "sg:postcode":"4540",
    "sg:province":"Li\u00e8ge",
    "sg:tags":[
        "component",
        "hydraulic"
    ],
    "wof:name":"Doedijns Fluitronics",
    "wof:placetype":"venue"
},
  "geometry": {"coordinates":[5.325401783,50.5449523926],"type":"Point"}
}