{
  "type": "Feature",
  "properties": {
    "iso:country":"BE",
    "sg:address":"Kerselarenweg 7",
    "sg:city":"Herent",
    "sg:orig_category":"Artsen and specialisten",
    "sg:phone":"+32 16 22 72 98",
    "sg:postcode":"3020",
    "sg:province":"Vlaams-Brabant",
    "wof:name":"P. Znamensky",
    "wof:placetype":"venue"
},
  "geometry": {"coordinates":[4.6829171181,50.8946876526],"type":"Point"}
}