{
  "type": "Feature",
  "properties": {
    "addr:full":"Van Goethemstraat 64 Merelbeke Oost-Vlaanderen 9820",
    "addr:housenumber":"64",
    "addr:postcode":"9820",
    "addr:street":"Van Goethemstraat",
    "iso:country":"BE",
    "sg:address":"Van Goethemstraat 64",
    "sg:city":"Merelbeke",
    "sg:orig_category":"Brood, gebak and snoepgoed",
    "sg:phone":"+32 9 230 68 36",
    "sg:postcode":"9820",
    "sg:province":"Oost-Vlaanderen",
    "wof:name":"Bakkerij De Wilde",
    "wof:placetype":"venue"
},
  "geometry": {"coordinates":[3.7598590851,51.0185852051],"type":"Point"}
}