{
  "type": "Feature",
  "properties": {
    "addr:full":"Kerkstraat 2 Lebbeke Oost-Vlaanderen 9280",
    "addr:housenumber":"2",
    "addr:postcode":"9280",
    "addr:street":"Kerkstraat",
    "iso:country":"BE",
    "sg:address":"Kerkstraat 2",
    "sg:city":"Lebbeke",
    "sg:orig_category":"Quincailleries",
    "sg:phone":"+32 52 41 12 85",
    "sg:postcode":"9280",
    "sg:province":"Oost-Vlaanderen",
    "wof:name":"Huis Moens Hugo & Zn",
    "wof:placetype":"venue"
},
  "geometry": {"coordinates":[4.130300045,51.0009040833],"type":"Point"}
}