{
  "type": "Feature",
  "properties": {
    "iso:country":"BE",
    "sg:address":"Rue De Praules 76",
    "sg:city":"Jemeppe-sur-sambre (ham-sur-sambre)",
    "sg:classifiers":[
        {
            "category":"Health Services",
            "subcategory":"Nursing And Care Facility",
            "type":"Services"
        }
    ],
    "sg:phone":"+32 71 78 42 55",
    "sg:postcode":"5190",
    "sg:province":"Namur",
    "sg:tags":[
        "home"
    ],
    "wof:name":"Genot F",
    "wof:placetype":"venue"
},
  "geometry": {"coordinates":[4.6522688866,50.4467430115],"type":"Point"}
}