{
  "type": "Feature",
  "properties": {
    "addr:full":"Oude Pontweg 18 Destelbergen Oost-Vlaanderen 9070",
    "addr:housenumber":"18",
    "addr:postcode":"9070",
    "addr:street":"Oude Pontweg",
    "iso:country":"BE",
    "sg:address":"Oude Pontweg 18",
    "sg:city":"Destelbergen",
    "sg:orig_category":"Rundveehouders",
    "sg:phone":"+32 9 252 13 62",
    "sg:postcode":"9070",
    "sg:province":"Oost-Vlaanderen",
    "wof:name":"Roger Impens",
    "wof:placetype":"venue"
},
  "geometry": {"coordinates":[3.8117849827,51.0050125122],"type":"Point"}
}