{
  "type": "Feature",
  "properties": {
    "iso:country":"BE",
    "sg:address":"Kezelberg 51",
    "sg:city":"Wevelgem (moorsele)",
    "sg:classifiers":[
        {
            "category":"Retail",
            "subcategory":"Auto Rental",
            "type":"Services"
        }
    ],
    "sg:phone":"+32 56 50 91 25",
    "sg:postcode":"8560",
    "sg:province":"West-Vlaanderen",
    "sg:tags":[
        "milking",
        "machine"
    ],
    "wof:name":"Vanraes Gebroeders",
    "wof:placetype":"venue"
},
  "geometry": {"coordinates":[3.1136169434,50.8367462158],"type":"Point"}
}