{
  "type": "Feature",
  "properties": {
    "iso:country":"BE",
    "sg:address":"Koninklijke Baan 321",
    "sg:city":"Koksijde",
    "sg:classifiers":[
        {
            "category":"Professional",
            "type":"Services"
        }
    ],
    "sg:phone":"+32 58 51 80 29",
    "sg:postcode":"8670",
    "sg:province":"West-Vlaanderen",
    "sg:tags":[
        "auction",
        "room"
    ],
    "wof:name":"St-idesbald",
    "wof:placetype":"venue"
},
  "geometry": {"coordinates":[2.6268680096,51.1137161255],"type":"Point"}
}