{
  "type": "Feature",
  "properties": {
    "iso:country":"BE",
    "sg:address":"Klaverbladstraat 12",
    "sg:city":"Lummen",
    "sg:orig_category":"Apparatus, Containers, Boilers, And Tanks Of Steel",
    "sg:phone":"+32 13 53 13 08",
    "sg:postcode":"3560",
    "sg:province":"Limburg",
    "wof:name":"Peca Constructions Nv",
    "wof:placetype":"venue"
},
  "geometry": {"coordinates":[5.2281470299,50.9960289001],"type":"Point"}
}