{
  "type": "Feature",
  "properties": {
    "addr:full":"Wolmarkt 17 Tienen Vlaams-Brabant 3300",
    "addr:housenumber":"17",
    "addr:postcode":"3300",
    "addr:street":"Wolmarkt",
    "iso:country":"BE",
    "sg:address":"Wolmarkt 17",
    "sg:city":"Tienen",
    "sg:classifiers":[
        {
            "category":"Professional",
            "subcategory":"Management & Consulting",
            "type":"Services"
        }
    ],
    "sg:phone":"+32 16 81 64 33",
    "sg:postcode":"3300",
    "sg:province":"Vlaams-Brabant",
    "sg:tags":[
        "consultant",
        "law"
    ],
    "wof:name":"Horembach R",
    "wof:placetype":"venue"
},
  "geometry": {"coordinates":[4.9387669563,50.8056869507],"type":"Point"}
}