{
  "type": "Feature",
  "properties": {
    "iso:country":"BE",
    "sg:address":"Rue Cloquet 21",
    "sg:city":"Braine-l\u00b4alleud",
    "sg:orig_category":"Voedingsspeciaalzaken",
    "sg:phone":"+32 2 384 15 45",
    "sg:postcode":"1420",
    "sg:province":"Brabant Wallon",
    "wof:name":"Equilibres",
    "wof:placetype":"venue"
},
  "geometry": {"coordinates":[4.3679800034,50.6834945679],"type":"Point"}
}