{
  "type": "Feature",
  "properties": {
    "addr:full":"Rue D'harscamp 66 Li\u00e8ge 1 (li\u00e8ge 2) Li\u00e8ge 4020",
    "addr:housenumber":"66;1;2",
    "addr:postcode":"4020",
    "addr:street":"Rue D'Harscamp",
    "iso:country":"BE",
    "sg:address":"Rue D'harscamp 66",
    "sg:city":"Li\u00e8ge 1 (li\u00e8ge 2)",
    "sg:classifiers":[
        {
            "category":"Professional",
            "subcategory":"Art Services",
            "type":"Services"
        }
    ],
    "sg:phone":"+32 4 344 91 70",
    "sg:postcode":"4020",
    "sg:province":"Li\u00e8ge",
    "sg:tags":[
        "-",
        "valuer"
    ],
    "wof:name":"H\u00f4tel Des Ventes Mosan",
    "wof:placetype":"venue"
},
  "geometry": {"coordinates":[5.5822038651,50.6314353943],"type":"Point"}
}