{
  "type": "Feature",
  "properties": {
    "addr:full":"Quai Du Condroz 11 Li\u00c8ge Li\u00e8ge 4020",
    "addr:housenumber":"11",
    "addr:postcode":"4020",
    "addr:street":"Quai Du Condroz",
    "iso:country":"BE",
    "sg:address":"Quai Du Condroz 11",
    "sg:city":"Li\u00c8ge",
    "sg:orig_category":"Avocats and conseillers juridiques",
    "sg:phone":"+32 4 342 30 55",
    "sg:postcode":"4020",
    "sg:province":"Li\u00e8ge",
    "wof:name":"Chantal Dierckx",
    "wof:placetype":"venue"
},
  "geometry": {"coordinates":[5.5832400322,50.6204605103],"type":"Point"}
}