{
  "type": "Feature",
  "properties": {
    "addr:full":"Korte Veerstraat 7 Rumst Antwerpen 2840",
    "addr:housenumber":"7",
    "addr:postcode":"2840",
    "addr:street":"Korte Veerstraat",
    "iso:country":"BE",
    "sg:address":"Korte Veerstraat 7",
    "sg:city":"Rumst",
    "sg:classifiers":[
        {
            "category":"Arena",
            "subcategory":"Sports Club",
            "type":"Entertainment"
        }
    ],
    "sg:phone":"+32 3 844 15 21",
    "sg:postcode":"2840",
    "sg:province":"Antwerpen",
    "sg:tags":[
        "de"
    ],
    "wof:name":"De Rupelspurters Boom",
    "wof:placetype":"venue"
},
  "geometry": {"coordinates":[4.424200058,51.076915741],"type":"Point"}
}