{
  "type": "Feature",
  "properties": {
    "iso:country":"BE",
    "sg:address":"Paradijsstraat 20",
    "sg:city":"Zulte",
    "sg:classifiers":[
        {
            "category":"Health Services",
            "subcategory":"Doctor",
            "type":"Services"
        }
    ],
    "sg:phone":"+32 9 388 96 10",
    "sg:postcode":"9870",
    "sg:province":"Oost-Vlaanderen",
    "sg:tags":[
        "medicinephysicians",
        "surgeon"
    ],
    "wof:name":"De Leye A (mevr)",
    "wof:placetype":"venue"
},
  "geometry": {"coordinates":[3.4560000896,50.9262809753],"type":"Point"}
}