{
  "type": "Feature",
  "properties": {
    "iso:country":"BE",
    "sg:address":"Rue Sonkeu 42",
    "sg:city":"Herve (battice)",
    "sg:classifiers":[
        {
            "category":"Professional",
            "subcategory":"Accounting & Tax Preparation",
            "type":"Services"
        }
    ],
    "sg:phone":"+32 87 66 04 03",
    "sg:postcode":"4651",
    "sg:province":"Li\u00e8ge",
    "sg:tags":[
        "bookkeeper"
    ],
    "wof:name":"Xhaflaire H",
    "wof:placetype":"venue"
},
  "geometry": {"coordinates":[5.8225131035,50.6474494934],"type":"Point"}
}