{
  "type": "Feature",
  "properties": {
    "addr:full":"Rue De Monsville 228 Quaregnon Hainaut 7390",
    "addr:housenumber":"228",
    "addr:postcode":"7390",
    "addr:street":"Rue De Monsville",
    "iso:country":"BE",
    "sg:address":"Rue De Monsville 228",
    "sg:city":"Quaregnon",
    "sg:orig_category":"S\u00e9curit\u00e9 sociale",
    "sg:phone":"+32 65 77 90 61",
    "sg:postcode":"7390",
    "sg:province":"Hainaut",
    "wof:name":"Mutualit\u00c9 Socialiste",
    "wof:placetype":"venue"
},
  "geometry": {"coordinates":[3.8642799854,50.436252594],"type":"Point"}
}