{
  "type": "Feature",
  "properties": {
    "addr:full":"Montagne D'aisemont 6 Wavre Brabant Wallon 1300",
    "addr:housenumber":"6;1300",
    "iso:country":"BE",
    "sg:address":"Montagne D'aisemont 6",
    "sg:city":"Wavre",
    "sg:classifiers":[
        {
            "category":"Shopping",
            "subcategory":"Baby Store",
            "type":"Retail Goods"
        }
    ],
    "sg:phone":"+32 10 22 24 38",
    "sg:postcode":"1300",
    "sg:province":"Brabant Wallon",
    "sg:tags":[
        "article",
        "b\u00e9b\u00e9s",
        "pour"
    ],
    "wof:name":"Maison Du Bapt\u00c8me",
    "wof:placetype":"venue"
},
  "geometry": {"coordinates":[4.6150550842,50.7143287659],"type":"Point"}
}