{
  "type": "Feature",
  "properties": {
    "addr:full":"Beukenhofstraat 38 Anzegem West-Vlaanderen 8570",
    "addr:housenumber":"38",
    "addr:postcode":"8570",
    "addr:street":"Beukenhofstraat",
    "iso:country":"BE",
    "sg:address":"Beukenhofstraat 38",
    "sg:city":"Anzegem",
    "sg:orig_category":"Enseignement maternel and primaire",
    "sg:phone":"+32 56 77 82 81",
    "sg:postcode":"8570",
    "sg:province":"West-Vlaanderen",
    "wof:name":"Gemeentel. Lagere School",
    "wof:placetype":"venue"
},
  "geometry": {"coordinates":[3.3991639614,50.8372764587],"type":"Point"}
}