{
  "type": "Feature",
  "properties": {
    "iso:country":"BE",
    "sg:address":"Woumenstraat 5",
    "sg:city":"Houthulst",
    "sg:orig_category":"Eleveurs and marchands de porcs. Eleveurs de bovins",
    "sg:phone":"+32 51 54 59 19",
    "sg:postcode":"8650",
    "sg:province":"West-Vlaanderen",
    "wof:name":"Andre Willem",
    "wof:placetype":"venue"
},
  "geometry": {"coordinates":[2.890237093,50.9799880981],"type":"Point"}
}