{
  "type": "Feature",
  "properties": {
    "addr:full":"Asterstraat 4 Lovendegem Oost-Vlaanderen 9920",
    "addr:housenumber":"4",
    "addr:postcode":"9920",
    "addr:street":"Asterstraat",
    "iso:country":"BE",
    "sg:address":"Asterstraat 4",
    "sg:city":"Lovendegem",
    "sg:orig_category":"Boucheries",
    "sg:phone":"+32 9 372 68 63",
    "sg:postcode":"9920",
    "sg:province":"Oost-Vlaanderen",
    "wof:name":"Johan Cleppe",
    "wof:placetype":"venue"
},
  "geometry": {"coordinates":[3.6349480152,51.1056022644],"type":"Point"}
}