{
  "type": "Feature",
  "properties": {
    "iso:country":"BE",
    "sg:address":"Gasthuisstraat 51",
    "sg:city":"Brecht",
    "sg:classifiers":[
        {
            "category":"Communications",
            "subcategory":"Television Station",
            "type":"Services"
        }
    ],
    "sg:phone":"+32 3 313 68 58",
    "sg:postcode":"2960",
    "sg:province":"Antwerpen",
    "sg:tags":[
        "video",
        "audio",
        "verhuur"
    ],
    "wof:name":"Cherif's Video Center",
    "wof:placetype":"venue"
},
  "geometry": {"coordinates":[4.6345491409,51.3469696045],"type":"Point"}
}