{
  "type": "Feature",
  "properties": {
    "addr:full":"Sint-willybrordusstraat 13 Hechtel-eksel Limburg 3941",
    "addr:housenumber":"13",
    "addr:postcode":"3941",
    "addr:street":"Sint-Willybrordusstraat",
    "iso:country":"BE",
    "sg:address":"Sint-willybrordusstraat 13",
    "sg:city":"Hechtel-eksel",
    "sg:orig_category":"Bouwmaterialen Gh Dakwerken Installatie van houten of kunststof schrijnwerk",
    "sg:phone":"+32 11 73 48 32",
    "sg:postcode":"3941",
    "sg:province":"Limburg",
    "wof:name":"Soogen",
    "wof:placetype":"venue"
},
  "geometry": {"coordinates":[5.4127511978,51.1588020325],"type":"Point"}
}