{
  "type": "Feature",
  "properties": {
    "iso:country":"BE",
    "sg:address":"Dorpstraat 7",
    "sg:city":"Bree",
    "sg:classifiers":[
        {
            "category":"Arena",
            "subcategory":"Sports Club",
            "type":"Entertainment"
        }
    ],
    "sg:phone":"+32 89 86 47 83",
    "sg:postcode":"3960",
    "sg:province":"Limburg",
    "sg:tags":[
        "de"
    ],
    "wof:name":"D.c. Onder De Toren",
    "wof:placetype":"venue"
},
  "geometry": {"coordinates":[5.6593999863,51.1268882751],"type":"Point"}
}