{
  "type": "Feature",
  "properties": {
    "iso:country":"BE",
    "sg:address":"Kapucijnenvoer 3",
    "sg:city":"Leuven",
    "sg:classifiers":[
        {
            "category":"Cinema",
            "subcategory":"Movie Rental",
            "type":"Entertainment"
        }
    ],
    "sg:phone":"+32 16 20 74 27",
    "sg:postcode":"3000",
    "sg:province":"Vlaams-Brabant",
    "sg:tags":[
        "de",
        "cassette",
        "location",
        "vid\u00e9o",
        "audio"
    ],
    "wof:name":"Homevideo D.l.n.",
    "wof:placetype":"venue"
},
  "geometry": {"coordinates":[4.6931967735,50.8798751831],"type":"Point"}
}