{
  "type": "Feature",
  "properties": {
    "iso:country":"BE",
    "sg:address":"Vinkenlaan 10",
    "sg:city":"Deerlijk",
    "sg:classifiers":[
        {
            "category":"Cafe",
            "type":"Food & Drink"
        }
    ],
    "sg:phone":"+32 56 70 03 96",
    "sg:postcode":"8540",
    "sg:province":"West-Vlaanderen",
    "sg:tags":[
        "caf\u00e9s"
    ],
    "wof:name":"Jose Daems",
    "wof:placetype":"venue"
},
  "geometry": {"coordinates":[3.3660120964,50.859954834],"type":"Point"}
}