{
  "type": "Feature",
  "properties": {
    "addr:full":"Geldenaaksebaan 222 Leuven (heverlee) Vlaams-Brabant 3001",
    "addr:housenumber":"222",
    "addr:postcode":"3001",
    "addr:street":"Geldenaaksebaan",
    "iso:country":"BE",
    "sg:address":"Geldenaaksebaan 222",
    "sg:city":"Leuven (heverlee)",
    "sg:classifiers":[
        {
            "category":"Health Services",
            "subcategory":"Health Practitioner",
            "type":"Services"
        }
    ],
    "sg:phone":"+32 16 40 08 59",
    "sg:postcode":"3001",
    "sg:province":"Vlaams-Brabant",
    "sg:tags":[
        "physiotherapist"
    ],
    "wof:name":"Vanden Auweele Frigyes",
    "wof:placetype":"venue"
},
  "geometry": {"coordinates":[4.7116270065,50.8632202148],"type":"Point"}
}