{
  "type": "Feature",
  "properties": {
    "iso:country":"BE",
    "sg:address":"Rue Van Aa 90",
    "sg:city":"Ixelles",
    "sg:orig_category":"Dakwerken Loodgieterij, verwarming and sanitaire installaties Schoonmaakbedrijven and ongediertebest",
    "sg:phone":"+32 475 25 95 92",
    "sg:postcode":"1050",
    "sg:province":"Bruxelles-Capitale",
    "wof:name":"Bogaert",
    "wof:placetype":"venue"
},
  "geometry": {"coordinates":[4.3715338707,50.8322105408],"type":"Point"}
}