{
  "type": "Feature",
  "properties": {
    "addr:full":"Kasteelstraat 3 Merchtem Vlaams-Brabant 1785",
    "addr:housenumber":"3",
    "addr:postcode":"1785",
    "addr:street":"Kasteelstraat",
    "iso:country":"BE",
    "sg:address":"Kasteelstraat 3",
    "sg:city":"Merchtem",
    "sg:orig_category":"Producteurs de l\u00e9gumes",
    "sg:phone":"+32 2 460 24 20",
    "sg:postcode":"1785",
    "sg:province":"Vlaams-Brabant",
    "wof:name":"Albert De Pooter",
    "wof:placetype":"venue"
},
  "geometry": {"coordinates":[4.2803401947,50.9224014282],"type":"Point"}
}