{
  "type": "Feature",
  "properties": {
    "iso:country":"BE",
    "sg:address":"Rue Dodon\u00c9e 77b8a",
    "sg:city":"Ukkel/uccle",
    "sg:orig_category":"Activit\u00e9s diverses d'imprimerie",
    "sg:phone":"+32 2 344 78 35",
    "sg:postcode":"1180",
    "sg:province":"Bruxelles-Capitale",
    "wof:name":"Xavier Vanheghe",
    "wof:placetype":"venue"
},
  "geometry": {"coordinates":[4.3622531891,50.8134918213],"type":"Point"}
}