{
  "type": "Feature",
  "properties": {
    "addr:full":"Pleisterplaatsstraat 85 Elsene/ixelles Bruxelles-Capitale 1050",
    "addr:housenumber":"85",
    "addr:postcode":"1050",
    "addr:street":"Pleisterplaatsstraat",
    "iso:country":"BE",
    "sg:address":"Pleisterplaatsstraat 85",
    "sg:city":"Elsene/ixelles",
    "sg:orig_category":"Installatie van houten of kunststof schrijnwerk",
    "sg:phone":"+32 2 662 05 62",
    "sg:postcode":"1050",
    "sg:province":"Bruxelles-Capitale",
    "wof:name":"X-stand",
    "wof:placetype":"venue"
},
  "geometry": {"coordinates":[4.3936882019,50.8104438782],"type":"Point"}
}