{
  "type": "Feature",
  "properties": {
    "iso:country":"BE",
    "sg:address":"Stalenstraat 106b108",
    "sg:city":"Genk",
    "sg:orig_category":"HERSTELLING ELEKTRISCHE HUISHOUDAPPARATEN Huishoudapparaten, televisies and radio's",
    "sg:phone":"+32 89 38 04 71",
    "sg:postcode":"3600",
    "sg:province":"Limburg",
    "wof:name":"Meubelen Multiform",
    "wof:placetype":"venue"
},
  "geometry": {"coordinates":[5.5163297653,50.9925193787],"type":"Point"}
}