{
  "type": "Feature",
  "properties": {
    "iso:country":"BE",
    "sg:address":"Emiel Vanderveldestraat 119",
    "sg:city":"Willebroek",
    "sg:classifiers":[
        {
            "category":"Cafe",
            "type":"Food & Drink"
        }
    ],
    "sg:phone":"+32 3 866 06 19",
    "sg:postcode":"2830",
    "sg:province":"Antwerpen",
    "sg:tags":[
        "caf\u00e9s"
    ],
    "wof:name":"Caf\u00c9 't Palmke",
    "wof:placetype":"venue"
},
  "geometry": {"coordinates":[4.354403019,51.0615997314],"type":"Point"}
}