{
  "type": "Feature",
  "properties": {
    "iso:country":"BE",
    "sg:address":"Isabellaplein 12",
    "sg:city":"Scherpenheuvel-zichem (scherpenheuvel)",
    "sg:classifiers":[
        {
            "category":"Shopping",
            "subcategory":"Crafts & Fabrics",
            "type":"Retail Goods"
        }
    ],
    "sg:phone":"+32 13 78 43 78",
    "sg:postcode":"3270",
    "sg:province":"Vlaams-Brabant",
    "sg:tags":[
        "needlework",
        "lady"
    ],
    "wof:name":"Cosy Corner",
    "wof:placetype":"venue"
},
  "geometry": {"coordinates":[4.9769630432,50.9807662964],"type":"Point"}
}