{
  "type": "Feature",
  "properties": {
    "iso:country":"BE",
    "sg:address":"Oudebaan 111",
    "sg:city":"Antwerpen",
    "sg:orig_category":"Woningbouw",
    "sg:phone":"+32 3 827 20 80",
    "sg:postcode":"2610",
    "sg:province":"Antwerpen",
    "wof:name":"Serge Walen",
    "wof:placetype":"venue"
},
  "geometry": {"coordinates":[4.4215531349,51.2272186279],"type":"Point"}
}