{
  "type": "Feature",
  "properties": {
    "iso:country":"BE",
    "sg:address":"Kleine Moorsledestraat 17",
    "sg:city":"Ledegem",
    "sg:orig_category":"Varkenskwekers",
    "sg:phone":"+32 56 50 01 47",
    "sg:postcode":"8880",
    "sg:province":"West-Vlaanderen",
    "wof:name":"Roger Maertens",
    "wof:placetype":"venue"
},
  "geometry": {"coordinates":[3.1092960835,50.8760261536],"type":"Point"}
}