{
  "type": "Feature",
  "properties": {
    "addr:full":"Minderbroedersrui 19 Antwerpen Antwerpen 2000",
    "addr:housenumber":"19",
    "addr:postcode":"2000",
    "addr:street":"Minderbroedersrui",
    "iso:country":"BE",
    "sg:address":"Minderbroedersrui 19",
    "sg:city":"Antwerpen",
    "sg:orig_category":"Maatschappelijke dienstverlening",
    "sg:phone":"+32 3 232 71 81",
    "sg:postcode":"2000",
    "sg:province":"Antwerpen",
    "wof:name":"Centrum Jan Van Rijswijck-jac",
    "wof:placetype":"venue"
},
  "geometry": {"coordinates":[4.4041490555,51.2229347229],"type":"Point"}
}