{
  "type": "Feature",
  "properties": {
    "addr:full":"Steenstraat 38 Brugge West-Vlaanderen 8000",
    "addr:housenumber":"38",
    "addr:postcode":"8000",
    "addr:street":"Steenstraat",
    "iso:country":"BE",
    "sg:address":"Steenstraat 38",
    "sg:city":"Brugge",
    "sg:orig_category":"Banques and organismes de cr\u00e9dit",
    "sg:phone":"+32 50 44 45 11",
    "sg:postcode":"8000",
    "sg:province":"West-Vlaanderen",
    "wof:name":"Kbc",
    "wof:placetype":"venue"
},
  "geometry": {"coordinates":[3.2229399681,51.2074928284],"type":"Point"}
}