{
  "type": "Feature",
  "properties": {
    "iso:country":"BE",
    "sg:address":"Rodesteenstraat 7",
    "sg:city":"Houthulst (merkem)",
    "sg:classifiers":[
        {
            "category":"Building & Trades",
            "subcategory":"Landscaping Services",
            "type":"Services"
        }
    ],
    "sg:phone":"+32 51 54 43 41",
    "sg:postcode":"8650",
    "sg:province":"West-Vlaanderen",
    "sg:tags":[
        "slaughterer"
    ],
    "wof:name":"Laleman M",
    "wof:placetype":"venue"
},
  "geometry": {"coordinates":[2.9509439468,50.9778862],"type":"Point"}
}