{
  "type": "Feature",
  "properties": {
    "iso:country":"BE",
    "sg:address":"Moerstraat 35",
    "sg:city":"Schilde",
    "sg:orig_category":"Film-, tv- and videoproductie",
    "sg:phone":"+32 3 685 05 96",
    "sg:postcode":"2970",
    "sg:province":"Antwerpen",
    "wof:name":"All Aert",
    "wof:placetype":"venue"
},
  "geometry": {"coordinates":[4.5535531044,51.2666473389],"type":"Point"}
}