{
  "type": "Feature",
  "properties": {
    "addr:full":"Dennenweg 76 Zonhoven Limburg 3520",
    "addr:housenumber":"76",
    "addr:postcode":"3520",
    "addr:street":"Dennenweg",
    "iso:country":"BE",
    "sg:address":"Dennenweg 76",
    "sg:city":"Zonhoven",
    "sg:orig_category":"Gespecialiseerde residenti\u00eble bouw",
    "sg:phone":"+32 11 81 84 24",
    "sg:postcode":"3520",
    "sg:province":"Limburg",
    "wof:name":"Boudewijn Bielen",
    "wof:placetype":"venue"
},
  "geometry": {"coordinates":[5.4217000008,50.9796104431],"type":"Point"}
}