{
  "type": "Feature",
  "properties": {
    "addr:full":"Stationsstraat 111 Berlaar Antwerpen 2590",
    "addr:housenumber":"111",
    "addr:postcode":"2590",
    "addr:street":"Stationsstraat",
    "iso:country":"BE",
    "sg:address":"Stationsstraat 111",
    "sg:city":"Berlaar",
    "sg:classifiers":[
        {
            "category":"Home & Garden",
            "subcategory":"Carpets & Floor Coverings",
            "type":"Retail Goods"
        }
    ],
    "sg:phone":"+32 3 422 58 04",
    "sg:postcode":"2590",
    "sg:province":"Antwerpen",
    "sg:tags":[
        "layer",
        "mosaicists"
    ],
    "wof:name":"Heca",
    "wof:placetype":"venue"
},
  "geometry": {"coordinates":[4.6448941231,51.1147918701],"type":"Point"}
}