{
  "type": "Feature",
  "properties": {
    "iso:country":"BE",
    "sg:address":"Avenue Paul Pastur 420",
    "sg:city":"Charleroi",
    "sg:classifiers":[
        {
            "category":"Restaurant",
            "type":"Food & Drink"
        }
    ],
    "sg:phone":"+32 71 43 27 47",
    "sg:postcode":"6032",
    "sg:province":"Hainaut",
    "wof:name":"Le Clos Des Lilas",
    "wof:placetype":"venue"
},
  "geometry": {"coordinates":[4.4249610901,50.4000053406],"type":"Point"}
}