{
  "type": "Feature",
  "properties": {
    "addr:full":"Chauss\u00c9e De Wavre 156 Elsene/ixelles Bruxelles-Capitale 1050",
    "addr:housenumber":"156",
    "addr:postcode":"1050",
    "addr:street":"Chausse\u0301E De Wavre",
    "iso:country":"BE",
    "sg:address":"Chauss\u00c9e De Wavre 156",
    "sg:city":"Elsene/ixelles",
    "sg:orig_category":"Entretien and r\u00e9parations de voitures. V\u00e9hicules automobiles",
    "sg:phone":"+32 2 511 55 75",
    "sg:postcode":"1050",
    "sg:province":"Bruxelles-Capitale",
    "wof:name":"American Automobiles",
    "wof:placetype":"venue"
},
  "geometry": {"coordinates":[4.370223999,50.8357467651],"type":"Point"}
}