{
  "type": "Feature",
  "properties": {
    "iso:country":"BE",
    "sg:address":"Industrieweg 25",
    "sg:city":"Boortmeerbeek",
    "sg:classifiers":[
        {
            "category":"Professional",
            "subcategory":"Engineering",
            "type":"Services"
        }
    ],
    "sg:phone":"+32 16 60 77 60",
    "sg:postcode":"3190",
    "sg:province":"Vlaams-Brabant",
    "sg:tags":[
        "consulting",
        "technology"
    ],
    "wof:name":"Dsi Nv",
    "wof:placetype":"venue"
},
  "geometry": {"coordinates":[4.5851669312,50.9643592834],"type":"Point"}
}