{
  "type": "Feature",
  "properties": {
    "iso:country":"BE",
    "sg:address":"De Schom 38",
    "sg:city":"Genk",
    "sg:orig_category":"Electrom\u00e9nager, t\u00e9l\u00e9visions and radios. R\u00e9parations d'appareils \u00e9lectrom\u00e9nagers",
    "sg:phone":"+32 89 35 68 66",
    "sg:postcode":"3600",
    "sg:province":"Limburg",
    "wof:name":"Klaus Heinze",
    "wof:placetype":"venue"
},
  "geometry": {"coordinates":[5.464220047,50.9500808716],"type":"Point"}
}