{
  "type": "Feature",
  "properties": {
    "iso:country":"BE",
    "sg:address":"Rue Des Archers 4",
    "sg:city":"Mons",
    "sg:orig_category":"Agences immobili\u00e8res. Administration d'immeubles",
    "sg:phone":"+32 65 33 53 20",
    "sg:postcode":"7000",
    "sg:province":"Hainaut",
    "wof:name":"Immo-assistance",
    "wof:placetype":"venue"
},
  "geometry": {"coordinates":[3.9577760696,50.4524497986],"type":"Point"}
}