{
  "type": "Feature",
  "properties": {
    "addr:full":"Rue Biaulettes 3 Libramont-chevigny (moircy) Luxembourg 6800",
    "addr:housenumber":"3",
    "addr:postcode":"6800",
    "addr:street":"Rue Biaulettes;Moircy",
    "iso:country":"BE",
    "sg:address":"Rue Biaulettes 3",
    "sg:city":"Libramont-chevigny (moircy)",
    "sg:classifiers":[
        {
            "category":"Retail",
            "subcategory":"Auto Repair",
            "type":"Services"
        }
    ],
    "sg:phone":"+32 61 68 83 12",
    "sg:postcode":"6800",
    "sg:province":"Luxembourg",
    "sg:tags":[
        "garage"
    ],
    "wof:name":"Grandjean D",
    "wof:placetype":"venue"
},
  "geometry": {"coordinates":[5.4681100845,49.9874038696],"type":"Point"}
}