{
  "type": "Feature",
  "properties": {
    "addr:full":"Vossendaal 5 Geel Antwerpen 2440",
    "addr:housenumber":"5",
    "addr:postcode":"2440",
    "addr:street":"Vossendaal",
    "iso:country":"BE",
    "sg:address":"Vossendaal 5",
    "sg:city":"Geel",
    "sg:orig_category":"Finished goods - metallic Industrial vehicles Metallurgy and Metalworking Motor-cars Rubber Rubber a",
    "sg:phone":"+32 14 58 64 94",
    "sg:postcode":"2440",
    "sg:province":"Antwerpen",
    "wof:name":"Kicken Bandenspecialist Nv",
    "wof:placetype":"venue"
},
  "geometry": {"coordinates":[4.9470028877,51.1249771118],"type":"Point"}
}