{
  "type": "Feature",
  "properties": {
    "iso:country":"BE",
    "sg:address":"Gulmerstraat 91",
    "sg:city":"Kortessem (vliermaalroot)",
    "sg:classifiers":[
        {
            "category":"Insurance",
            "subcategory":"Insurance Agent",
            "type":"Services"
        }
    ],
    "sg:phone":"+32 89 51 41 40",
    "sg:postcode":"3721",
    "sg:province":"Limburg",
    "sg:tags":[
        "broker"
    ],
    "wof:name":"Gielen Stefan Vof",
    "wof:placetype":"venue"
},
  "geometry": {"coordinates":[5.4405522346,50.8582954407],"type":"Point"}
}