{
  "type": "Feature",
  "properties": {
    "addr:full":"Rue Guillaume Stocq 42 Elsene/ixelles Bruxelles-Capitale 1050",
    "addr:housenumber":"42",
    "addr:postcode":"1050",
    "addr:street":"Rue Guillaume Stocq",
    "iso:country":"BE",
    "sg:address":"Rue Guillaume Stocq 42",
    "sg:city":"Elsene/ixelles",
    "sg:orig_category":"Art and fournitures artistiques. Imprimeries and copyshops",
    "sg:phone":"+32 2 646 90 90",
    "sg:postcode":"1050",
    "sg:province":"Bruxelles-Capitale",
    "wof:name":"A.b.c. Europe",
    "wof:placetype":"venue"
},
  "geometry": {"coordinates":[4.3765602112,50.8237991333],"type":"Point"}
}