{
  "type": "Feature",
  "properties": {
    "iso:country":"BE",
    "sg:address":"Schotensteenweg 53b",
    "sg:city":"Brecht",
    "sg:classifiers":[
        {
            "category":"Health Services",
            "subcategory":"Health Practitioner",
            "type":"Services"
        }
    ],
    "sg:phone":"+32 3 636 36 13",
    "sg:postcode":"2960",
    "sg:province":"Antwerpen",
    "sg:tags":[
        "physiotherapist"
    ],
    "wof:name":"De Bevere Johan",
    "wof:placetype":"venue"
},
  "geometry": {"coordinates":[4.6124401093,51.3343200684],"type":"Point"}
}