{
  "type": "Feature",
  "properties": {
    "addr:full":"Hans Memlinclaan 7 Rumst (reet) Antwerpen 2840",
    "addr:housenumber":"7",
    "addr:postcode":"2840",
    "addr:street":"Hans Memlinclaan",
    "iso:country":"BE",
    "sg:address":"Hans Memlinclaan 7",
    "sg:city":"Rumst (reet)",
    "sg:classifiers":[
        {
            "category":"Building & Trades",
            "subcategory":"Plumbing",
            "type":"Services"
        }
    ],
    "sg:phone":"+32 3 888 77 66",
    "sg:postcode":"2840",
    "sg:province":"Antwerpen",
    "sg:tags":[
        "repair",
        "mainten",
        "-",
        "central",
        "heating"
    ],
    "wof:name":"Pintens J",
    "wof:placetype":"venue"
},
  "geometry": {"coordinates":[4.4026470184,51.1016540527],"type":"Point"}
}