{
  "type": "Feature",
  "properties": {
    "addr:full":"Gullegemsestraat 108 Ledegem West-Vlaanderen 8880",
    "addr:housenumber":"108",
    "addr:postcode":"8880",
    "addr:street":"Gullegemsestraat",
    "iso:country":"BE",
    "sg:address":"Gullegemsestraat 108",
    "sg:city":"Ledegem",
    "sg:classifiers":[
        {
            "category":"Cafe",
            "type":"Food & Drink"
        }
    ],
    "sg:phone":"+32 56 50 37 55",
    "sg:postcode":"8880",
    "sg:province":"West-Vlaanderen",
    "sg:tags":[
        "caf\u00e9s"
    ],
    "wof:name":"Caf\u00c9 Germinal",
    "wof:placetype":"venue"
},
  "geometry": {"coordinates":[3.183975935,50.8692398071],"type":"Point"}
}