{
  "type": "Feature",
  "properties": {
    "addr:full":"Overes 105 Peer Limburg 3990",
    "addr:housenumber":"105",
    "addr:postcode":"3990",
    "addr:street":"Overes",
    "iso:country":"BE",
    "sg:address":"Overes 105",
    "sg:city":"Peer",
    "sg:classifiers":[
        {
            "category":"Arena",
            "subcategory":"Sports Club",
            "type":"Entertainment"
        }
    ],
    "sg:phone":"+32 11 79 32 07",
    "sg:postcode":"3990",
    "sg:province":"Limburg",
    "sg:tags":[
        "terrain",
        "hors",
        "de",
        "installation",
        "sportifs"
    ],
    "wof:name":"S.c. Wauberg",
    "wof:placetype":"venue"
},
  "geometry": {"coordinates":[5.4696397781,51.088470459],"type":"Point"}
}