{
  "type": "Feature",
  "properties": {
    "addr:full":"Rue De Lens-saint-remy 20 Braives Li\u00e8ge 4260",
    "addr:housenumber":"20",
    "addr:postcode":"4260",
    "addr:street":"Rue De Lens-Saint-Remy",
    "iso:country":"BE",
    "sg:address":"Rue De Lens-saint-remy 20",
    "sg:city":"Braives",
    "sg:orig_category":"Installation \u00e9lectrique r\u00e9sidentielle",
    "sg:phone":"+32 19 69 92 00",
    "sg:postcode":"4260",
    "sg:province":"Li\u00e8ge",
    "wof:name":"Maurice Withofs",
    "wof:placetype":"venue"
},
  "geometry": {"coordinates":[5.1150379181,50.6327629089],"type":"Point"}
}