{
  "type": "Feature",
  "properties": {
    "iso:country":"BE",
    "sg:address":"Chauss\u00c9e De Haecht 749",
    "sg:city":"Schaarbeek/schaerbeek",
    "sg:orig_category":"Pharmaciens",
    "sg:phone":"+32 2 215 74 43",
    "sg:postcode":"1030",
    "sg:province":"Bruxelles-Capitale",
    "wof:name":"Thierry Delescaille",
    "wof:placetype":"venue"
},
  "geometry": {"coordinates":[4.3946099281,50.8715896606],"type":"Point"}
}