{
  "type": "Feature",
  "properties": {
    "addr:full":"Rue Sainte-walburge 61 Li\u00c8ge Li\u00e8ge 4000",
    "addr:housenumber":"61",
    "addr:postcode":"4000",
    "addr:street":"Rue Sainte-Walburge",
    "iso:country":"BE",
    "sg:address":"Rue Sainte-walburge 61",
    "sg:city":"Li\u00c8ge",
    "sg:orig_category":"Traitements param\u00e9dicaux",
    "sg:phone":"+32 4 224 24 59",
    "sg:postcode":"4000",
    "sg:province":"Li\u00e8ge",
    "wof:name":"Paramedici",
    "wof:placetype":"venue"
},
  "geometry": {"coordinates":[5.5715942383,50.65574646],"type":"Point"}
}