{
  "type": "Feature",
  "properties": {
    "iso:country":"BE",
    "sg:address":"Rue De La Chauss\u00e9e 20",
    "sg:city":"Mons",
    "sg:classifiers":[
        {
            "category":"Utilities",
            "subcategory":"Mobile Phone",
            "type":"Services"
        }
    ],
    "sg:phone":"+32 65 34 07 90",
    "sg:postcode":"7000",
    "sg:province":"Hainaut",
    "sg:tags":[
        "access",
        "gsm",
        "-",
        "apparatus"
    ],
    "wof:name":"Mons G Sprl",
    "wof:placetype":"venue"
},
  "geometry": {"coordinates":[3.9515500069,50.4534683228],"type":"Point"}
}