{
  "type": "Feature",
  "properties": {
    "addr:full":"Rue Du D\u00e9barcad\u00e8re 179 Charleroi (marcinelle) Hainaut 6001",
    "addr:housenumber":"179",
    "addr:postcode":"6001",
    "addr:street":"Rue Du De\u0301Barcade\u0300Re",
    "iso:country":"BE",
    "sg:address":"Rue Du D\u00e9barcad\u00e8re 179",
    "sg:city":"Charleroi (marcinelle)",
    "sg:classifiers":[
        {
            "category":"Education",
            "subcategory":"Special Training",
            "type":"Public Place"
        }
    ],
    "sg:phone":"+32 71 44 72 67",
    "sg:postcode":"6001",
    "sg:province":"Hainaut",
    "sg:tags":[
        "professional"
    ],
    "wof:name":"Ieias",
    "wof:placetype":"venue"
},
  "geometry": {"coordinates":[4.4366297722,50.3767318726],"type":"Point"}
}