{
  "type": "Feature",
  "properties": {
    "iso:country":"BE",
    "sg:address":"8500",
    "sg:city":"Kortrijk",
    "sg:orig_category":"Koerierbedrijven",
    "sg:phone":"+32 70 22 32 34",
    "sg:postcode":"8500",
    "sg:province":"West-Vlaanderen",
    "wof:name":"Koerierdiensten",
    "wof:placetype":"venue"
},
  "geometry": {"coordinates":[3.2800600529,50.817741394],"type":"Point"}
}