{
  "type": "Feature",
  "properties": {
    "addr:full":"Clos De L'ev\u00each\u00e9 9 Tournai (kain) Hainaut 7540",
    "addr:housenumber":"9",
    "addr:postcode":"7540",
    "addr:street":"Clos De L'Eve \u0302Che\u0301",
    "iso:country":"BE",
    "sg:address":"Clos De L'ev\u00each\u00e9 9",
    "sg:city":"Tournai (kain)",
    "sg:classifiers":[
        {
            "category":"Personal",
            "subcategory":"Nail Salon",
            "type":"Services"
        }
    ],
    "sg:phone":"+32 69 23 49 17",
    "sg:postcode":"7540",
    "sg:province":"Hainaut",
    "sg:tags":[
        "pedicure"
    ],
    "wof:name":"Sartorius Ch",
    "wof:placetype":"venue"
},
  "geometry": {"coordinates":[3.3853509426,50.6317100525],"type":"Point"}
}