{
  "type": "Feature",
  "properties": {
    "addr:full":"Chauss\u00e9e D'alsemberg 946 Bruxelles (uccle) Bruxelles-Capitale 1180",
    "addr:housenumber":"946",
    "addr:postcode":"1180",
    "addr:street":"Chausse\u0301E D'Alsemberg",
    "iso:country":"BE",
    "sg:address":"Chauss\u00e9e D'alsemberg 946",
    "sg:city":"Bruxelles (uccle)",
    "sg:classifiers":[
        {
            "category":"Arena",
            "subcategory":"Sports Club",
            "type":"Entertainment"
        }
    ],
    "sg:phone":"+32 2 521 05 78",
    "sg:postcode":"1180",
    "sg:province":"Bruxelles-Capitale",
    "sg:tags":[
        "martial art",
        "accessory"
    ],
    "wof:name":"Judo Club Uccle",
    "wof:placetype":"venue"
},
  "geometry": {"coordinates":[4.3340191841,50.7934341431],"type":"Point"}
}