{
  "type": "Feature",
  "properties": {
    "iso:country":"BE",
    "sg:address":"Brun Cornet 20",
    "sg:city":"Menen",
    "sg:orig_category":"Rev\u00eatements pour sols and murs",
    "sg:phone":"+32 56 40 31 99",
    "sg:postcode":"8930",
    "sg:province":"West-Vlaanderen",
    "wof:name":"Patrick Vanlerberghe",
    "wof:placetype":"venue"
},
  "geometry": {"coordinates":[3.1843791008,50.7723121643],"type":"Point"}
}