{
  "type": "Feature",
  "properties": {
    "iso:country":"BE",
    "sg:address":"Zandvoordedorpstraat 147",
    "sg:city":"Oostende (zandvoorde)",
    "sg:classifiers":[
        {
            "category":"Health Services",
            "subcategory":"Health Practitioner",
            "type":"Services"
        }
    ],
    "sg:phone":"+32 59 26 87 48",
    "sg:postcode":"8400",
    "sg:province":"West-Vlaanderen",
    "sg:tags":[
        "dietitian"
    ],
    "wof:name":"Meseure W",
    "wof:placetype":"venue"
},
  "geometry": {"coordinates":[2.9418840408,51.2152061462],"type":"Point"}
}