{
  "type": "Feature",
  "properties": {
    "iso:country":"BE",
    "sg:address":"Rue Saint-clair 12",
    "sg:city":"Malmedy (bellevaux-lignueville)",
    "sg:classifiers":[
        {
            "category":"Professional",
            "subcategory":"Business Services",
            "type":"Services"
        }
    ],
    "sg:phone":"+32 80 57 10 20",
    "sg:postcode":"4960",
    "sg:province":"Li\u00e8ge",
    "sg:tags":[
        "firm"
    ],
    "wof:name":"M.c. Feyen Secr\u00e9tariat",
    "wof:placetype":"venue"
},
  "geometry": {"coordinates":[6.0556268692,50.3720664978],"type":"Point"}
}