{
  "type": "Feature",
  "properties": {
    "addr:full":"Rue Du Ch\u00e2teau D'eau 12 Charleroi (lodelinsart) Hainaut 6042",
    "addr:housenumber":"12",
    "addr:postcode":"6042",
    "addr:street":"Rue Du Cha\u0302Teau D'Eau",
    "iso:country":"BE",
    "sg:address":"Rue Du Ch\u00e2teau D'eau 12",
    "sg:city":"Charleroi (lodelinsart)",
    "sg:classifiers":[
        {
            "category":"Building & Trades",
            "subcategory":"Electrical",
            "type":"Services"
        }
    ],
    "sg:phone":"+32 71 30 34 04",
    "sg:postcode":"6042",
    "sg:province":"Hainaut",
    "sg:tags":[
        "electric",
        "-",
        "housewiring",
        "contractor"
    ],
    "wof:name":"Rucquoy Ch",
    "wof:placetype":"venue"
},
  "geometry": {"coordinates":[4.4396471977,50.4347724915],"type":"Point"}
}