{
  "type": "Feature",
  "properties": {
    "iso:country":"BE",
    "sg:address":"Jos Reusenslei 18",
    "sg:city":"Borsbeek",
    "sg:orig_category":"Baby- and kinderkleding Dameskledingzaken",
    "sg:phone":"+32 3 321 85 15",
    "sg:postcode":"2150",
    "sg:province":"Antwerpen",
    "wof:name":"Gitty",
    "wof:placetype":"venue"
},
  "geometry": {"coordinates":[4.488202095,51.1935920715],"type":"Point"}
}