{
  "type": "Feature",
  "properties": {
    "addr:full":"Smissenhoek 49 Zottegem (erwetegem) Oost-Vlaanderen 9620",
    "addr:housenumber":"49",
    "addr:postcode":"9620",
    "addr:street":"Smissenhoek",
    "iso:country":"BE",
    "sg:address":"Smissenhoek 49",
    "sg:city":"Zottegem (erwetegem)",
    "sg:classifiers":[
        {
            "category":"Retail",
            "subcategory":"Auto Repair",
            "type":"Services"
        }
    ],
    "sg:phone":"+32 9 360 55 06",
    "sg:postcode":"9620",
    "sg:province":"Oost-Vlaanderen",
    "sg:tags":[
        "garage"
    ],
    "wof:name":"Flamez",
    "wof:placetype":"venue"
},
  "geometry": {"coordinates":[3.8112111092,50.871181488],"type":"Point"}
}