{
  "type": "Feature",
  "properties": {
    "addr:full":"Avenue De L`exposition 264 Jette Bruxelles-Capitale 1090",
    "addr:housenumber":"264",
    "addr:postcode":"1090",
    "addr:street":"Avenue De L`Exposition",
    "iso:country":"BE",
    "sg:address":"Avenue De L`exposition 264",
    "sg:city":"Jette",
    "sg:orig_category":"Articles de sport, camping and jouets Gr",
    "sg:phone":"+32 2 478 07 30",
    "sg:postcode":"1090",
    "sg:province":"Bruxelles-Capitale",
    "wof:name":"Stock Import",
    "wof:placetype":"venue"
},
  "geometry": {"coordinates":[4.3174171448,50.8845901489],"type":"Point"}
}