{
  "type": "Feature",
  "properties": {
    "iso:country":"BE",
    "sg:address":"Leemstraat 69",
    "sg:city":"Malle",
    "sg:orig_category":"Etudes techniques and ing\u00e9nierie. Agences immobili\u00e8res",
    "sg:phone":"+32 3 312 37 76",
    "sg:postcode":"2390",
    "sg:province":"Antwerpen",
    "wof:name":"Verheyen",
    "wof:placetype":"venue"
},
  "geometry": {"coordinates":[4.7007331848,51.3051185608],"type":"Point"}
}