{
  "type": "Feature",
  "properties": {
    "addr:full":"Rue De Tubize 5 Braine-le-chateau Brabant Wallon 1440",
    "addr:housenumber":"5",
    "addr:postcode":"1440",
    "addr:street":"Rue De Tubize;Brabant Wallon",
    "iso:country":"BE",
    "sg:address":"Rue De Tubize 5",
    "sg:city":"Braine-le-chateau",
    "sg:orig_category":"Artsen and specialisten",
    "sg:phone":"+32 2 366 95 26",
    "sg:postcode":"1440",
    "sg:province":"Brabant Wallon",
    "wof:name":"Andr\u00c9 Vienne",
    "wof:placetype":"venue"
},
  "geometry": {"coordinates":[4.2650389671,50.6813926697],"type":"Point"}
}