{
  "type": "Feature",
  "properties": {
    "addr:full":"Paul Krugerstraat 55 Lier Antwerpen 2500",
    "addr:housenumber":"55",
    "addr:postcode":"2500",
    "addr:street":"Paul Krugerstraat",
    "iso:country":"BE",
    "sg:address":"Paul Krugerstraat 55",
    "sg:city":"Lier",
    "sg:classifiers":[
        {
            "category":"Home & Garden",
            "subcategory":"Carpets & Floor Coverings",
            "type":"Retail Goods"
        }
    ],
    "sg:phone":"+32 3 480 10 75",
    "sg:postcode":"2500",
    "sg:province":"Antwerpen",
    "sg:tags":[
        "automobile",
        "-",
        "upholstering",
        "cover"
    ],
    "wof:name":"Kusseneers F",
    "wof:placetype":"venue"
},
  "geometry": {"coordinates":[4.5828371048,51.126411438],"type":"Point"}
}