{
  "type": "Feature",
  "properties": {
    "iso:country":"BE",
    "sg:address":"Bosdel 54",
    "sg:city":"Genk",
    "sg:classifiers":[
        {
            "category":"Shopping",
            "subcategory":"Musical Instruments",
            "type":"Retail Goods"
        }
    ],
    "sg:phone":"+32 89 50 46 69",
    "sg:postcode":"3600",
    "sg:province":"Limburg",
    "sg:tags":[
        "-"
    ],
    "wof:name":"Encore Media Systems Bvba",
    "wof:placetype":"venue"
},
  "geometry": {"coordinates":[5.4784059525,50.9508628845],"type":"Point"}
}