{
  "type": "Feature",
  "properties": {
    "addr:full":"Heidestraat 2 Hoboken Antwerpen 2660",
    "addr:housenumber":"2",
    "addr:postcode":"2660",
    "addr:street":"Heidestraat",
    "iso:country":"BE",
    "sg:address":"Heidestraat 2",
    "sg:city":"Hoboken",
    "sg:orig_category":"Royal Canin. Animaux domestiques and accessoires",
    "sg:phone":"+32 3 829 13 43",
    "sg:postcode":"2660",
    "sg:province":"Antwerpen",
    "wof:name":"Patrache Dierspeciaalzaa",
    "wof:placetype":"venue"
},
  "geometry": {"coordinates":[4.3546061516,51.1738166809],"type":"Point"}
}