{
  "type": "Feature",
  "properties": {
    "addr:full":"Kerkstraat 20 Duffel Antwerpen 2570",
    "addr:housenumber":"20",
    "addr:postcode":"2570",
    "addr:street":"Kerkstraat",
    "iso:country":"BE",
    "sg:address":"Kerkstraat 20",
    "sg:city":"Duffel",
    "sg:classifiers":[
        {
            "category":"Personal",
            "subcategory":"Beauty Salon",
            "type":"Services"
        }
    ],
    "sg:phone":"+32 15 32 13 07",
    "sg:postcode":"2570",
    "sg:province":"Antwerpen",
    "wof:name":"Els",
    "wof:placetype":"venue"
},
  "geometry": {"coordinates":[4.5006318092,51.0950698853],"type":"Point"}
}