{
  "type": "Feature",
  "properties": {
    "iso:country":"BE",
    "sg:address":"Rue Des Chenes 1bb",
    "sg:city":"Aywaille",
    "sg:orig_category":"Artsen and specialisten",
    "sg:phone":"+32 4 384 64 39",
    "sg:postcode":"4920",
    "sg:province":"Li\u00e8ge",
    "wof:name":"Serge Mandeiro",
    "wof:placetype":"venue"
},
  "geometry": {"coordinates":[5.6686778069,50.4529457092],"type":"Point"}
}