{
  "type": "Feature",
  "properties": {
    "addr:full":"Avenue Hoover 63 Rixensart Brabant Wallon 1332",
    "addr:housenumber":"63",
    "addr:postcode":"1332",
    "addr:street":"Avenue Hoover;Wallon",
    "iso:country":"BE",
    "sg:address":"Avenue Hoover 63",
    "sg:city":"Rixensart",
    "sg:orig_category":"Mus\u00e9es and patrimoine culturel",
    "sg:phone":"+32 2 654 19 23",
    "sg:postcode":"1332",
    "sg:province":"Brabant Wallon",
    "wof:name":"Mus\u00c9e Eau & Fontaine",
    "wof:placetype":"venue"
},
  "geometry": {"coordinates":[4.4974551201,50.7170753479],"type":"Point"}
}