{
  "type": "Feature",
  "properties": {
    "addr:full":"Karel De Preterlei 52 Antwerpen (borgerhout) Antwerpen 2140",
    "addr:housenumber":"52",
    "addr:postcode":"2140",
    "addr:street":"Karel De Preterlei",
    "iso:country":"BE",
    "sg:address":"Karel De Preterlei 52",
    "sg:city":"Antwerpen (borgerhout)",
    "sg:classifiers":[
        {
            "category":"Manufacturing",
            "subcategory":"Metals",
            "type":"Manufacturing & Wholesale Goods"
        }
    ],
    "sg:phone":"+32 3 236 59 31",
    "sg:postcode":"2140",
    "sg:province":"Antwerpen",
    "sg:tags":[
        "ornamental",
        "work",
        "-"
    ],
    "wof:name":"Cor-neel",
    "wof:placetype":"venue"
},
  "geometry": {"coordinates":[4.4332199097,51.2137565613],"type":"Point"}
}