{
  "type": "Feature",
  "properties": {
    "addr:full":"Mechelse Steenweg 89 Antwerpen Antwerpen 2018",
    "addr:housenumber":"89",
    "addr:postcode":"2018",
    "addr:street":"Steenweg",
    "iso:country":"BE",
    "sg:address":"Mechelse Steenweg 89",
    "sg:city":"Antwerpen",
    "sg:classifiers":[
        {
            "category":"Shopping",
            "subcategory":"Beauty & Cosmetics",
            "type":"Retail Goods"
        }
    ],
    "sg:phone":"+32 3 226 33 02",
    "sg:postcode":"2018",
    "sg:province":"Antwerpen",
    "sg:tags":[
        "-",
        "perfumery"
    ],
    "wof:name":"Parfleur",
    "wof:placetype":"venue"
},
  "geometry": {"coordinates":[4.4088139534,51.2081184387],"type":"Point"}
}