{
  "type": "Feature",
  "properties": {
    "iso:country":"BE",
    "sg:address":"Route De Mons 1ba",
    "sg:city":"Bernissart",
    "sg:orig_category":"V\u00e9hicules automobiles. Entretien and r\u00e9parations de voitures",
    "sg:phone":"+32 65 62 32 11",
    "sg:postcode":"7322",
    "sg:province":"Hainaut",
    "wof:name":"Garage Regali",
    "wof:placetype":"venue"
},
  "geometry": {"coordinates":[3.7474789619,50.483707428],"type":"Point"}
}