{
  "type": "Feature",
  "properties": {
    "iso:country":"BE",
    "sg:address":"Rue Obecq 69",
    "sg:city":"Waterloo",
    "sg:classifiers":[
        {
            "category":"Health Services",
            "subcategory":"Doctor",
            "type":"Services"
        }
    ],
    "sg:phone":"+32 2 351 11 47",
    "sg:postcode":"1410",
    "sg:province":"Brabant Wallon",
    "sg:tags":[
        "medicinephysicians",
        "surgeon"
    ],
    "wof:name":"Homerin Anne-marie",
    "wof:placetype":"venue"
},
  "geometry": {"coordinates":[4.4040298462,50.7002563477],"type":"Point"}
}