{
  "type": "Feature",
  "properties": {
    "iso:country":"BE",
    "sg:address":"Zavelbaan 27",
    "sg:city":"Aalst",
    "sg:orig_category":"Artsen and specialisten",
    "sg:phone":"+32 53 21 57 48",
    "sg:postcode":"9300",
    "sg:province":"Oost-Vlaanderen",
    "wof:name":"Theo De Graeve",
    "wof:placetype":"venue"
},
  "geometry": {"coordinates":[4.0496778488,50.9496841431],"type":"Point"}
}