{
  "type": "Feature",
  "properties": {
    "addr:full":"Lange Molenstraat 25 Heist-op-den-berg Antwerpen 2220",
    "addr:housenumber":"25",
    "addr:postcode":"2220",
    "addr:street":"Lange Molenstraat",
    "iso:country":"BE",
    "sg:address":"Lange Molenstraat 25",
    "sg:city":"Heist-op-den-berg",
    "sg:orig_category":"Banken and kredietinstellingen",
    "sg:phone":"+32 15 22 05 82",
    "sg:postcode":"2220",
    "sg:province":"Antwerpen",
    "wof:name":"Kbc",
    "wof:placetype":"venue"
},
  "geometry": {"coordinates":[4.7172751427,51.078704834],"type":"Point"}
}