{
  "type": "Feature",
  "properties": {
    "iso:country":"BE",
    "sg:address":"Ter Rivierenwal 2",
    "sg:city":"Bree",
    "sg:orig_category":"Huishoudapparaten, televisies and radio's Speciaalzaken",
    "sg:phone":"+32 89 46 11 14",
    "sg:postcode":"3960",
    "sg:province":"Limburg",
    "wof:name":"V.d.s. Electronics",
    "wof:placetype":"venue"
},
  "geometry": {"coordinates":[5.5948739052,51.1406860352],"type":"Point"}
}