{
  "type": "Feature",
  "properties": {
    "iso:country":"BE",
    "sg:address":"Van Dijckstraat 24",
    "sg:city":"Mortsel",
    "sg:orig_category":"Postkantoren Verzekeringsmakelaars and experts",
    "sg:phone":"+32 3 449 67 25",
    "sg:postcode":"2640",
    "sg:province":"Antwerpen",
    "wof:name":"De Post",
    "wof:placetype":"venue"
},
  "geometry": {"coordinates":[4.4656162262,51.164894104],"type":"Point"}
}