{
  "type": "Feature",
  "properties": {
    "iso:country":"BE",
    "sg:address":"Burgstraat 45",
    "sg:city":"Destelbergen",
    "sg:classifiers":[
        {
            "category":"Building & Trades",
            "subcategory":"Cleaning & Sanitation",
            "type":"Services"
        }
    ],
    "sg:phone":"+32 9 355 91 19",
    "sg:postcode":"9070",
    "sg:province":"Oost-Vlaanderen",
    "sg:tags":[
        "equipment",
        "industrial",
        "maintenance"
    ],
    "wof:name":"Euronet",
    "wof:placetype":"venue"
},
  "geometry": {"coordinates":[3.8349189758,51.0776062012],"type":"Point"}
}