{
  "type": "Feature",
  "properties": {
    "addr:full":"Scherpenbergweg 7 Heuvelland West-Vlaanderen 8958",
    "addr:housenumber":"7",
    "addr:postcode":"8958",
    "addr:street":"Scherpenbergweg",
    "iso:country":"BE",
    "sg:address":"Scherpenbergweg 7",
    "sg:city":"Heuvelland",
    "sg:orig_category":"Installation de menuiserie en bois and plastique",
    "sg:phone":"+32 57 44 85 79",
    "sg:postcode":"8958",
    "sg:province":"West-Vlaanderen",
    "wof:name":"Alain Parez",
    "wof:placetype":"venue"
},
  "geometry": {"coordinates":[2.7849550247,50.7920417786],"type":"Point"}
}