{
  "type": "Feature",
  "properties": {
    "iso:country":"BE",
    "sg:address":"Rue Colonel Tachet Des Combes 5",
    "sg:city":"Yvoir",
    "sg:classifiers":[
        {
            "category":"Bars & Pubs",
            "type":"Food & Drink"
        }
    ],
    "sg:phone":"+32 82 61 40 86",
    "sg:postcode":"5530",
    "sg:province":"Namur",
    "wof:name":"Bocq (du)",
    "wof:placetype":"venue"
},
  "geometry": {"coordinates":[4.8788709641,50.326133728],"type":"Point"}
}