{
  "type": "Feature",
  "properties": {
    "addr:full":"Industriepark 38 Heist-op-den-berg Antwerpen 2220",
    "addr:housenumber":"38",
    "addr:postcode":"2220",
    "addr:street":"Industriepark",
    "iso:country":"BE",
    "sg:address":"Industriepark 38",
    "sg:city":"Heist-op-den-berg",
    "sg:orig_category":"Non-Classified Establishments",
    "sg:phone":"+32 15 25 11 76",
    "sg:postcode":"2220",
    "sg:province":"Antwerpen",
    "wof:name":"Van Dyck Vleeswaren Bvba",
    "wof:placetype":"venue"
},
  "geometry": {"coordinates":[4.714632988,51.0649032593],"type":"Point"}
}