{
  "type": "Feature",
  "properties": {
    "iso:country":"BE",
    "sg:address":"Opdorpstraat 45",
    "sg:city":"Londerzeel",
    "sg:classifiers":[
        {
            "category":"Insurance",
            "subcategory":"Insurance Agent",
            "type":"Services"
        }
    ],
    "sg:phone":"+32 52 33 31 14",
    "sg:postcode":"1840",
    "sg:province":"Vlaams-Brabant",
    "sg:tags":[
        "verzekeringsmakelaars",
        "expert"
    ],
    "wof:name":"Adebo",
    "wof:placetype":"venue"
},
  "geometry": {"coordinates":[4.2407698631,51.0196609497],"type":"Point"}
}