{
  "type": "Feature",
  "properties": {
    "iso:country":"BE",
    "sg:address":"Heirbaan 218",
    "sg:city":"Hamme",
    "sg:orig_category":"Entretien and r\u00e9parations de voitures. V\u00e9hicules automobiles",
    "sg:phone":"+32 52 48 09 37",
    "sg:postcode":"9220",
    "sg:province":"Oost-Vlaanderen",
    "wof:name":"Garage Antoreti",
    "wof:placetype":"venue"
},
  "geometry": {"coordinates":[4.0919189453,51.0753936768],"type":"Point"}
}