{
  "type": "Feature",
  "properties": {
    "iso:country":"BE",
    "sg:address":"Kuipersakkerstraat 11",
    "sg:city":"Schoten",
    "sg:classifiers":[
        {
            "category":"Structure",
            "subcategory":"Office Building",
            "type":"Public Place"
        }
    ],
    "sg:phone":"+32 3 685 26 20",
    "sg:postcode":"2900",
    "sg:province":"Antwerpen",
    "sg:tags":[
        "equipment",
        "alarm",
        "installation",
        "system"
    ],
    "wof:name":"Failsafe B.v.b.a.",
    "wof:placetype":"venue"
},
  "geometry": {"coordinates":[4.5097260475,51.2515525818],"type":"Point"}
}