{
  "type": "Feature",
  "properties": {
    "addr:full":"Kwadenplasstraat 100 Destelbergen Oost-Vlaanderen 9070",
    "addr:housenumber":"100",
    "addr:postcode":"9070",
    "addr:street":"Kwadenplasstraat",
    "iso:country":"BE",
    "sg:address":"Kwadenplasstraat 100",
    "sg:city":"Destelbergen",
    "sg:orig_category":"Installatie van houten of kunststof schrijnwerk",
    "sg:phone":"+32 9 228 47 51",
    "sg:postcode":"9070",
    "sg:province":"Oost-Vlaanderen",
    "wof:name":"Vandelanotte Gebrs",
    "wof:placetype":"venue"
},
  "geometry": {"coordinates":[3.7765340805,51.0627365112],"type":"Point"}
}