{
  "type": "Feature",
  "properties": {
    "addr:full":"Molenstraat 214 Rumst Antwerpen 2840",
    "addr:housenumber":"214",
    "addr:postcode":"2840",
    "addr:street":"Molenstraat",
    "iso:country":"BE",
    "sg:address":"Molenstraat 214",
    "sg:city":"Rumst",
    "sg:classifiers":[
        {
            "category":"Autos & Motor Vehicles",
            "subcategory":"Fuel & Gas Station",
            "type":"Retail Goods"
        }
    ],
    "sg:phone":"+32 3 888 39 40",
    "sg:postcode":"2840",
    "sg:province":"Antwerpen",
    "sg:tags":[
        "stations-service",
        "carburants"
    ],
    "wof:name":"Garage De Boever Hugo",
    "wof:placetype":"venue"
},
  "geometry": {"coordinates":[4.419549942,51.076751709],"type":"Point"}
}