{
  "type": "Feature",
  "properties": {
    "addr:full":"Lakense Laan 47 Jette/jette Bruxelles-Capitale 1090",
    "addr:housenumber":"47",
    "addr:postcode":"1090",
    "addr:street":"Laan",
    "iso:country":"BE",
    "sg:address":"Lakense Laan 47",
    "sg:city":"Jette/jette",
    "sg:orig_category":"Advocaten and juridische adviseurs",
    "sg:phone":"+32 2 427 23 91",
    "sg:postcode":"1090",
    "sg:province":"Bruxelles-Capitale",
    "wof:name":"L. Herickx",
    "wof:placetype":"venue"
},
  "geometry": {"coordinates":[4.3225388527,50.8708190918],"type":"Point"}
}