{
  "type": "Feature",
  "properties": {
    "addr:full":"Rue De La Courbette 1 Honnelles (athis) Hainaut 7387",
    "addr:housenumber":"1",
    "addr:postcode":"7387",
    "addr:street":"Rue De La Courbette",
    "iso:country":"BE",
    "sg:address":"Rue De La Courbette 1",
    "sg:city":"Honnelles (athis)",
    "sg:classifiers":[
        {
            "category":"Health Services",
            "subcategory":"Health Practitioner",
            "type":"Services"
        }
    ],
    "sg:phone":"+32 65 63 42 34",
    "sg:postcode":"7387",
    "sg:province":"Hainaut",
    "sg:tags":[
        "physiotherapist"
    ],
    "wof:name":"De Pauw Val\u00e9rie",
    "wof:placetype":"venue"
},
  "geometry": {"coordinates":[3.6959199905,50.3683853149],"type":"Point"}
}