{
  "type": "Feature",
  "properties": {
    "iso:country":"BE",
    "sg:address":"Rue Soeur De Hasque 5",
    "sg:city":"Li\u00e8ge",
    "sg:classifiers":[
        {
            "category":"Travel",
            "subcategory":"Hotels & Motels",
            "type":"Entertainment"
        }
    ],
    "sg:phone":"+32 4 223 13 23",
    "sg:postcode":"4000",
    "sg:province":"Li\u00e8ge",
    "sg:tags":[
        "hotels",
        "business",
        "restaurant"
    ],
    "wof:name":"La Cite Du Dragon",
    "wof:placetype":"venue"
},
  "geometry": {"coordinates":[5.5736107826,50.6404838562],"type":"Point"}
}