{
  "type": "Feature",
  "properties": {
    "addr:full":"Korenbloemplein 15 Stekene Oost-Vlaanderen 9190",
    "addr:housenumber":"15",
    "addr:postcode":"9190",
    "addr:street":"Korenbloemplein",
    "iso:country":"BE",
    "sg:address":"Korenbloemplein 15",
    "sg:city":"Stekene",
    "sg:classifiers":[
        {
            "category":"Health Services",
            "subcategory":"Nursing And Care Facility",
            "type":"Services"
        }
    ],
    "sg:phone":"+32 3 779 72 43",
    "sg:postcode":"9190",
    "sg:province":"Oost-Vlaanderen",
    "sg:tags":[
        "home"
    ],
    "wof:name":"Herman B",
    "wof:placetype":"venue"
},
  "geometry": {"coordinates":[4.0370841026,51.2078323364],"type":"Point"}
}