{
  "type": "Feature",
  "properties": {
    "iso:country":"BE",
    "sg:address":"Dam 20",
    "sg:city":"Izegem",
    "sg:orig_category":"Kapsalons",
    "sg:phone":"+32 51 30 24 09",
    "sg:postcode":"8870",
    "sg:province":"West-Vlaanderen",
    "wof:name":"Coiffure Chris",
    "wof:placetype":"venue"
},
  "geometry": {"coordinates":[3.2173449993,50.9235267639],"type":"Point"}
}