{
  "type": "Feature",
  "properties": {
    "iso:country":"BE",
    "sg:address":"Verrekijker 2",
    "sg:city":"Wingene",
    "sg:orig_category":"Installatie van houten of kunststof schrijnwerk",
    "sg:phone":"+32 51 65 76 96",
    "sg:postcode":"8750",
    "sg:province":"West-Vlaanderen",
    "wof:name":"Fa. T.g.b.-tallieu",
    "wof:placetype":"venue"
},
  "geometry": {"coordinates":[3.2842259407,51.0550689697],"type":"Point"}
}