{
  "type": "Feature",
  "properties": {
    "addr:full":"Steenhouwersvest 2 Antwerpen Antwerpen 2000",
    "addr:housenumber":"2",
    "addr:postcode":"2000",
    "addr:street":"Steenhouwersvest",
    "iso:country":"BE",
    "sg:address":"Steenhouwersvest 2",
    "sg:city":"Antwerpen",
    "sg:orig_category":"Salles de spectacles",
    "sg:phone":"+32 3 232 02 82",
    "sg:postcode":"2000",
    "sg:province":"Antwerpen",
    "wof:name":"Galerij Muzart",
    "wof:placetype":"venue"
},
  "geometry": {"coordinates":[4.3971009254,51.2181587219],"type":"Point"}
}