{
  "type": "Feature",
  "properties": {
    "iso:country":"BE",
    "sg:address":"Stationstraat 63",
    "sg:city":"Ichtegem",
    "sg:classifiers":[
        {
            "category":"Restaurant",
            "type":"Food & Drink"
        }
    ],
    "sg:phone":"+32 59 29 86 90",
    "sg:postcode":"8480",
    "sg:province":"West-Vlaanderen",
    "wof:name":"Napoli",
    "wof:placetype":"venue"
},
  "geometry": {"coordinates":[3.0219359398,51.1297035217],"type":"Point"}
}