{
  "type": "Feature",
  "properties": {
    "iso:country":"BE",
    "sg:address":"Place Du Monument 22",
    "sg:city":"Spa",
    "sg:orig_category":"RESTAURANTS: H\u00d4TELS",
    "sg:phone":"+32 87 77 11 08",
    "sg:postcode":"4900",
    "sg:province":"Li\u00e8ge",
    "wof:name":"Le Relais",
    "wof:placetype":"venue"
},
  "geometry": {"coordinates":[5.8630180359,50.4919471741],"type":"Point"}
}