{
  "type": "Feature",
  "properties": {
    "iso:country":"BE",
    "sg:address":"Bergstraat 44",
    "sg:city":"Beveren (haasdonk)",
    "sg:classifiers":[
        {
            "category":"Farming",
            "subcategory":"Livestock Farm",
            "type":"Manufacturing & Wholesale Goods"
        }
    ],
    "sg:phone":"+32 3 775 89 51",
    "sg:postcode":"9120",
    "sg:province":"Oost-Vlaanderen",
    "sg:tags":[
        "horse"
    ],
    "wof:name":"Bulteel U",
    "wof:placetype":"venue"
},
  "geometry": {"coordinates":[4.2362508774,51.1741828918],"type":"Point"}
}