{
  "type": "Feature",
  "properties": {
    "addr:full":"Rue Des Chats 8 Bruxelles (berchem-sainte-agathe) Bruxelles-Capitale 1082",
    "addr:housenumber":"8",
    "addr:postcode":"1082",
    "addr:street":"Rue Des Chats",
    "iso:country":"BE",
    "sg:address":"Rue Des Chats 8",
    "sg:city":"Bruxelles (berchem-sainte-agathe)",
    "sg:classifiers":[
        {
            "category":"Health Services",
            "subcategory":"Doctor",
            "type":"Services"
        }
    ],
    "sg:phone":"+32 2 468 54 02",
    "sg:postcode":"1082",
    "sg:province":"Bruxelles-Capitale",
    "sg:tags":[
        "psychotherapist",
        "psychoanalyst"
    ],
    "wof:name":"Moreau D",
    "wof:placetype":"venue"
},
  "geometry": {"coordinates":[4.2811288834,50.8665161133],"type":"Point"}
}