{
  "type": "Feature",
  "properties": {
    "iso:country":"BE",
    "sg:address":"Staatsbaan 42",
    "sg:city":"Bekkevoort (assent)",
    "sg:classifiers":[
        {
            "category":"Building & Trades",
            "subcategory":"Landscaping Services",
            "type":"Services"
        }
    ],
    "sg:phone":"+32 13 31 32 83",
    "sg:postcode":"3460",
    "sg:province":"Vlaams-Brabant",
    "sg:tags":[
        "architect",
        "landscape"
    ],
    "wof:name":"Gardening",
    "wof:placetype":"venue"
},
  "geometry": {"coordinates":[4.985449791,50.9477043152],"type":"Point"}
}