{
  "type": "Feature",
  "properties": {
    "iso:country":"BE",
    "sg:address":"Mechelbaan 337",
    "sg:city":"Putte",
    "sg:classifiers":[
        {
            "category":"Health Services",
            "subcategory":"Nursing And Care Facility",
            "type":"Services"
        }
    ],
    "sg:phone":"+32 15 75 45 77",
    "sg:postcode":"2580",
    "sg:province":"Antwerpen",
    "sg:tags":[
        "home"
    ],
    "wof:name":"De Leebeeck Hilde",
    "wof:placetype":"venue"
},
  "geometry": {"coordinates":[4.6412267685,51.0591125488],"type":"Point"}
}