{
  "type": "Feature",
  "properties": {
    "iso:country":"BE",
    "sg:address":"Rue Hubert Van Vreckom 40",
    "sg:city":"Quaregnon",
    "sg:orig_category":"Drogisterijen",
    "sg:phone":"+32 65 79 18 54",
    "sg:postcode":"7390",
    "sg:province":"Hainaut",
    "wof:name":"Giovanni Caci",
    "wof:placetype":"venue"
},
  "geometry": {"coordinates":[3.856801033,50.4524002075],"type":"Point"}
}