{
  "type": "Feature",
  "properties": {
    "iso:country":"BE",
    "sg:address":"Stationsstraat 10",
    "sg:city":"De Haan (klemskerke)",
    "sg:classifiers":[
        {
            "category":"Bars & Pubs",
            "type":"Food & Drink"
        }
    ],
    "sg:phone":"+32 59 23 50 30",
    "sg:postcode":"8420",
    "sg:province":"West-Vlaanderen",
    "wof:name":"Ancien Coq (l')",
    "wof:placetype":"venue"
},
  "geometry": {"coordinates":[3.0340549946,51.271900177],"type":"Point"}
}