{
  "type": "Feature",
  "properties": {
    "addr:full":"Wijngaardveld 25 Aalst Oost-Vlaanderen 9300",
    "addr:housenumber":"25",
    "addr:postcode":"9300",
    "addr:street":"Wijngaardveld",
    "iso:country":"BE",
    "sg:address":"Wijngaardveld 25",
    "sg:city":"Aalst",
    "sg:orig_category":"Non-Classified Establishments",
    "sg:phone":"+32 53 21 47 58",
    "sg:postcode":"9300",
    "sg:province":"Oost-Vlaanderen",
    "wof:name":"D'haens",
    "wof:placetype":"venue"
},
  "geometry": {"coordinates":[4.0623469353,50.9398574829],"type":"Point"}
}