{
  "type": "Feature",
  "properties": {
    "addr:full":"Rue De Bouillon 417 Beauraing (feschaux) Namur 5570",
    "addr:housenumber":"417",
    "addr:postcode":"5570",
    "addr:street":"Rue De Bouillon",
    "iso:country":"BE",
    "sg:address":"Rue De Bouillon 417",
    "sg:city":"Beauraing (feschaux)",
    "sg:classifiers":[
        {
            "category":"Health Services",
            "subcategory":"Doctor",
            "type":"Services"
        }
    ],
    "sg:phone":"+32 82 71 25 69",
    "sg:postcode":"5570",
    "sg:province":"Namur",
    "sg:tags":[
        "medicinephysicians",
        "surgeon"
    ],
    "wof:name":"Gerard J P",
    "wof:placetype":"venue"
},
  "geometry": {"coordinates":[4.9803199768,50.1055488586],"type":"Point"}
}