{
  "type": "Feature",
  "properties": {
    "addr:full":"Elizabetlaan 109 Knokke-heist (knokke) West-Vlaanderen 8300",
    "addr:housenumber":"109",
    "addr:postcode":"8300",
    "addr:street":"Elizabetlaan",
    "iso:country":"BE",
    "sg:address":"Elizabetlaan 109",
    "sg:city":"Knokke-heist (knokke)",
    "sg:classifiers":[
        {
            "category":"Personal",
            "subcategory":"Nail Salon",
            "type":"Services"
        }
    ],
    "sg:phone":"+32 50 62 17 84",
    "sg:postcode":"8300",
    "sg:province":"West-Vlaanderen",
    "sg:tags":[
        "pedicure"
    ],
    "wof:name":"Instituut Monique",
    "wof:placetype":"venue"
},
  "geometry": {"coordinates":[3.2904679775,51.3471183777],"type":"Point"}
}