{
  "type": "Feature",
  "properties": {
    "iso:country":"BE",
    "sg:address":"Leuvensesteenweg 769",
    "sg:city":"Kortenberg",
    "sg:classifiers":[
        {
            "category":"Real Estate",
            "subcategory":"Real Estate Services",
            "type":"Services"
        }
    ],
    "sg:phone":"+32 2 759 61 87",
    "sg:postcode":"3070",
    "sg:province":"Vlaams-Brabant",
    "wof:name":"Immo-wera Bvba",
    "wof:placetype":"venue"
},
  "geometry": {"coordinates":[4.557849884,50.8902587891],"type":"Point"}
}