{
  "type": "Feature",
  "properties": {
    "addr:full":"Leopoldpark Blankenberge West-Vlaanderen 8370",
    "addr:postcode":"8370",
    "addr:street":"Leopoldpark",
    "iso:country":"BE",
    "sg:address":"Leopoldpark",
    "sg:city":"Blankenberge",
    "sg:orig_category":"Sportterreinen and installaties behalve sportcentra",
    "sg:phone":"+32 50 41 42 40",
    "sg:postcode":"8370",
    "sg:province":"West-Vlaanderen",
    "wof:name":"Mini Crazy Golf",
    "wof:placetype":"venue"
},
  "geometry": {"coordinates":[3.1232800484,51.3136405945],"type":"Point"}
}