{
  "type": "Feature",
  "properties": {
    "addr:full":"Rue En-bois 8 Li\u00e8ge Li\u00e8ge 4000",
    "addr:housenumber":"8",
    "addr:postcode":"4000",
    "addr:street":"Rue En-Bois",
    "iso:country":"BE",
    "sg:address":"Rue En-bois 8",
    "sg:city":"Li\u00e8ge",
    "sg:classifiers":[
        {
            "category":"Wholesale",
            "subcategory":"Home Furnishings",
            "type":"Manufacturing & Wholesale Goods"
        }
    ],
    "sg:phone":"+32 4 226 26 03",
    "sg:postcode":"4000",
    "sg:province":"Li\u00e8ge",
    "sg:tags":[
        "house",
        "paint"
    ],
    "wof:name":"Centrale Des Produits Chimiques Et De Peinture S.a.",
    "wof:placetype":"venue"
},
  "geometry": {"coordinates":[5.5527968407,50.6467666626],"type":"Point"}
}