{
  "type": "Feature",
  "properties": {
    "addr:full":"Grotstraat 26 As Limburg 3665",
    "addr:housenumber":"26",
    "addr:postcode":"3665",
    "addr:street":"Grotstraat",
    "iso:country":"BE",
    "sg:address":"Grotstraat 26",
    "sg:city":"As",
    "sg:classifiers":[
        {
            "category":"Real Estate",
            "subcategory":"Architect",
            "type":"Services"
        }
    ],
    "sg:phone":"+32 89 65 65 36",
    "sg:postcode":"3665",
    "sg:province":"Limburg",
    "wof:name":"Baeten P",
    "wof:placetype":"venue"
},
  "geometry": {"coordinates":[5.5992698669,51.0178413391],"type":"Point"}
}