{
  "type": "Feature",
  "properties": {
    "addr:full":"Jules Besmestraat 5 Koekelberg/koekelberg Bruxelles-Capitale 1081",
    "addr:housenumber":"5",
    "addr:postcode":"1081",
    "addr:street":"Besmestraat",
    "iso:country":"BE",
    "sg:address":"Jules Besmestraat 5",
    "sg:city":"Koekelberg/koekelberg",
    "sg:classifiers":[
        {
            "category":"Fast Food",
            "type":"Food & Drink"
        }
    ],
    "sg:phone":"+32 2 414 29 61",
    "sg:postcode":"1081",
    "sg:province":"Bruxelles-Capitale",
    "sg:tags":[
        "meeneem",
        "restaurant"
    ],
    "wof:name":"L'entr'acte",
    "wof:placetype":"venue"
},
  "geometry": {"coordinates":[4.3245630264,50.8632240295],"type":"Point"}
}