{
  "type": "Feature",
  "properties": {
    "addr:full":"Bld Maurice Lemonnier 64 Brussel/bruxelles Bruxelles-Capitale 1000",
    "addr:housenumber":"64",
    "addr:postcode":"1000",
    "addr:street":"Bld Maurice Lemonnier;/",
    "iso:country":"BE",
    "sg:address":"Bld Maurice Lemonnier 64",
    "sg:city":"Brussel/bruxelles",
    "sg:orig_category":"D\u00e9corateurs d'int\u00e9rieur",
    "sg:phone":"+32 2 513 75 05",
    "sg:postcode":"1000",
    "sg:province":"Bruxelles-Capitale",
    "wof:name":"Barbara Ferret",
    "wof:placetype":"venue"
},
  "geometry": {"coordinates":[4.3448119164,50.8434944153],"type":"Point"}
}