{
  "type": "Feature",
  "properties": {
    "addr:full":"Rue Berkendael 149 Vorst/forest Bruxelles-Capitale 1190",
    "addr:housenumber":"149",
    "addr:postcode":"1190",
    "addr:street":"Rue Berkendael;/ Forest",
    "iso:country":"BE",
    "sg:address":"Rue Berkendael 149",
    "sg:city":"Vorst/forest",
    "sg:classifiers":[
        {
            "category":"Cafe",
            "type":"Food & Drink"
        }
    ],
    "sg:phone":"+32 2 347 24 31",
    "sg:postcode":"1190",
    "sg:province":"Bruxelles-Capitale",
    "sg:tags":[
        "caf\u00e9s"
    ],
    "wof:name":"Brussels Coffee Bar",
    "wof:placetype":"venue"
},
  "geometry": {"coordinates":[4.350561142,50.8168296814],"type":"Point"}
}