{
  "type": "Feature",
  "properties": {
    "addr:full":"Rue Potaarde 153 Bruxelles (berchem-sainte-agathe) Bruxelles-Capitale 1082",
    "addr:housenumber":"153",
    "addr:postcode":"1082",
    "addr:street":"Rue Potaarde",
    "iso:country":"BE",
    "sg:address":"Rue Potaarde 153",
    "sg:city":"Bruxelles (berchem-sainte-agathe)",
    "sg:classifiers":[
        {
            "category":"Health Services",
            "subcategory":"Health Practitioner",
            "type":"Services"
        }
    ],
    "sg:phone":"+32 2 465 15 49",
    "sg:postcode":"1082",
    "sg:province":"Bruxelles-Capitale",
    "sg:tags":[
        "physiotherapist"
    ],
    "wof:name":"Clinquart C",
    "wof:placetype":"venue"
},
  "geometry": {"coordinates":[4.2825889587,50.8622627258],"type":"Point"}
}