{
  "type": "Feature",
  "properties": {
    "iso:country":"BE",
    "sg:address":"Akkerstraat 3",
    "sg:city":"Kapellen",
    "sg:orig_category":"Dakwerken",
    "sg:phone":"+32 3 665 15 28",
    "sg:postcode":"2950",
    "sg:province":"Antwerpen",
    "wof:name":"Van Camp Jos & Zn",
    "wof:placetype":"venue"
},
  "geometry": {"coordinates":[4.4222841263,51.3108253479],"type":"Point"}
}