{
  "type": "Feature",
  "properties": {
    "iso:country":"BE",
    "sg:address":"Rue Du Pav\u00e9 25",
    "sg:city":"Beaumont (barben\u00e7on)",
    "sg:classifiers":[
        {
            "category":"Utilities",
            "subcategory":"Telephone",
            "type":"Services"
        }
    ],
    "sg:phone":"+32 71 58 99 00",
    "sg:postcode":"6500",
    "sg:province":"Hainaut",
    "sg:tags":[
        "-",
        "internet"
    ],
    "wof:name":"Agence K",
    "wof:placetype":"venue"
},
  "geometry": {"coordinates":[4.2828397751,50.2230453491],"type":"Point"}
}