{
  "type": "Feature",
  "properties": {
    "addr:full":"Ninoofsesteenweg 70 Dilbeek Vlaams-Brabant 1700",
    "addr:housenumber":"70",
    "addr:postcode":"1700",
    "addr:street":"Ninoofsesteenweg",
    "iso:country":"BE",
    "sg:address":"Ninoofsesteenweg 70",
    "sg:city":"Dilbeek",
    "sg:orig_category":"Pharmaciens",
    "sg:phone":"+32 2 569 42 14",
    "sg:postcode":"1700",
    "sg:province":"Vlaams-Brabant",
    "wof:name":"Apodil",
    "wof:placetype":"venue"
},
  "geometry": {"coordinates":[4.2782611847,50.845035553],"type":"Point"}
}