{
  "type": "Feature",
  "properties": {
    "addr:full":"Rue De Houffalize 6 Houffalize (nadrin) Luxembourg 6660",
    "addr:housenumber":"6",
    "addr:postcode":"6660",
    "addr:street":"Rue De Houffalize",
    "iso:country":"BE",
    "sg:address":"Rue De Houffalize 6",
    "sg:city":"Houffalize (nadrin)",
    "sg:classifiers":[
        {
            "category":"Shopping",
            "subcategory":"Clothing, Apparel, & Fashions",
            "type":"Retail Goods"
        }
    ],
    "sg:phone":"+32 84 44 43 37",
    "sg:postcode":"6660",
    "sg:province":"Luxembourg",
    "sg:tags":[
        "-",
        "haberdashery"
    ],
    "wof:name":"1001 Id\u00e9es (aux)",
    "wof:placetype":"venue"
},
  "geometry": {"coordinates":[5.7902050018,50.1322784424],"type":"Point"}
}