{
  "type": "Feature",
  "properties": {
    "addr:full":"Beverststraat 19 Bilzen Limburg 3740",
    "addr:housenumber":"19",
    "addr:postcode":"3740",
    "addr:street":"Beverststraat",
    "iso:country":"BE",
    "sg:address":"Beverststraat 19",
    "sg:city":"Bilzen",
    "sg:orig_category":"Herenkledingzaken Maatkleding Fab",
    "sg:phone":"+32 89 41 63 26",
    "sg:postcode":"3740",
    "sg:province":"Limburg",
    "wof:name":"Fa. Appermans-thoonen",
    "wof:placetype":"venue"
},
  "geometry": {"coordinates":[5.4733400345,50.8920097351],"type":"Point"}
}