{
  "type": "Feature",
  "properties": {
    "addr:full":"Wijnputstraat 16 Scherpenheuvel-zichem Vlaams-Brabant 3271",
    "addr:housenumber":"16",
    "addr:postcode":"3271",
    "addr:street":"Wijnputstraat",
    "iso:country":"BE",
    "sg:address":"Wijnputstraat 16",
    "sg:city":"Scherpenheuvel-zichem",
    "sg:orig_category":"Woningbouw",
    "sg:phone":"+32 13 77 45 89",
    "sg:postcode":"3271",
    "sg:province":"Vlaams-Brabant",
    "wof:name":"Mario Degens",
    "wof:placetype":"venue"
},
  "geometry": {"coordinates":[5.0017237663,50.9907646179],"type":"Point"}
}