{
  "type": "Feature",
  "properties": {
    "iso:country":"BE",
    "sg:address":"Rue Pierre Du Diable 34b3",
    "sg:city":"Namur",
    "sg:orig_category":"Medische apparatuur, orthopedische artikelen and prothesen Fab",
    "sg:phone":"+32 81 31 20 49",
    "sg:postcode":"5100",
    "sg:province":"Namur",
    "wof:name":"Pascal Staute",
    "wof:placetype":"venue"
},
  "geometry": {"coordinates":[4.8713750839,50.4566345215],"type":"Point"}
}