{
  "type": "Feature",
  "properties": {
    "addr:full":"Industrielaan 29 Lichtervelde West-Vlaanderen 8810",
    "addr:housenumber":"29",
    "addr:postcode":"8810",
    "addr:street":"Industrielaan",
    "iso:country":"BE",
    "sg:address":"Industrielaan 29",
    "sg:city":"Lichtervelde",
    "sg:orig_category":"Travail and traitement du bois",
    "sg:phone":"+32 51 72 59 62",
    "sg:postcode":"8810",
    "sg:province":"West-Vlaanderen",
    "wof:name":"Woodstok",
    "wof:placetype":"venue"
},
  "geometry": {"coordinates":[3.1185100079,51.0294799805],"type":"Point"}
}