{
  "type": "Feature",
  "properties": {
    "iso:country":"BE",
    "sg:address":"Bevrijdingslaan 232",
    "sg:city":"Gent",
    "sg:orig_category":"Plomberie, chauffage and installations sanitaires",
    "sg:phone":"+32 9 226 20 38",
    "sg:postcode":"9000",
    "sg:province":"Oost-Vlaanderen",
    "wof:name":"Chauffage Coussement",
    "wof:placetype":"venue"
},
  "geometry": {"coordinates":[3.6983931065,51.0627975464],"type":"Point"}
}