{
  "type": "Feature",
  "properties": {
    "addr:full":"Rue De Rixensart 18 Box 5 Rixensart (genval) Brabant Wallon 1332",
    "addr:housenumber":"18;5",
    "addr:postcode":"1332",
    "addr:street":"Rue De Rixensart;Box",
    "iso:country":"BE",
    "sg:address":"Rue De Rixensart 18 Box 5",
    "sg:city":"Rixensart (genval)",
    "sg:classifiers":[
        {
            "category":"Shopping",
            "subcategory":"Antiques",
            "type":"Retail Goods"
        }
    ],
    "sg:phone":"+32 2 653 83 65",
    "sg:postcode":"1332",
    "sg:province":"Brabant Wallon",
    "sg:tags":[
        "restoration"
    ],
    "wof:name":"Transition Sa",
    "wof:placetype":"venue"
},
  "geometry": {"coordinates":[4.5144748688,50.7222442627],"type":"Point"}
}