{
  "type": "Feature",
  "properties": {
    "addr:full":"Vijfhuishoekstraat 18ba Torhout West-Vlaanderen 8820",
    "addr:housenumber":"18ba",
    "addr:postcode":"8820",
    "addr:street":"Vijfhuishoekstraat",
    "iso:country":"BE",
    "sg:address":"Vijfhuishoekstraat 18ba",
    "sg:city":"Torhout",
    "sg:orig_category":"Groententeelt Landmeters",
    "sg:phone":"+32 50 21 64 35",
    "sg:postcode":"8820",
    "sg:province":"West-Vlaanderen",
    "wof:name":"Luc Demeulenaere",
    "wof:placetype":"venue"
},
  "geometry": {"coordinates":[3.0768899918,51.0474662781],"type":"Point"}
}