{
  "type": "Feature",
  "properties": {
    "iso:country":"BE",
    "sg:address":"Hoogstraat 123",
    "sg:city":"Putte",
    "sg:orig_category":"Fleurs and plantes",
    "sg:phone":"+32 15 75 79 49",
    "sg:postcode":"2580",
    "sg:province":"Antwerpen",
    "wof:name":"Roland Geens",
    "wof:placetype":"venue"
},
  "geometry": {"coordinates":[4.6630249023,51.0587730408],"type":"Point"}
}