{
  "type": "Feature",
  "properties": {
    "addr:full":"Rue Charles Rittw\u00e9ger 84 Theux Li\u00e8ge 4910",
    "addr:housenumber":"84",
    "addr:postcode":"4910",
    "addr:street":"Rue Charles Rittwe\u0301Ger",
    "iso:country":"BE",
    "sg:address":"Rue Charles Rittw\u00e9ger 84",
    "sg:city":"Theux",
    "sg:classifiers":[
        {
            "category":"Real Estate",
            "subcategory":"Architect",
            "type":"Services"
        }
    ],
    "sg:phone":"+32 87 53 07 71",
    "sg:postcode":"4910",
    "sg:province":"Li\u00e8ge",
    "wof:name":"Debefve L",
    "wof:placetype":"venue"
},
  "geometry": {"coordinates":[5.8128199577,50.5394210815],"type":"Point"}
}