{
  "type": "Feature",
  "properties": {
    "iso:country":"BE",
    "sg:address":"Pieter Van Reysschootlaan 2",
    "sg:city":"Sint-denijs-westrem",
    "sg:orig_category":"Avocats and conseillers juridiques. Balie van Gent. Avocats and conseillers juridiques",
    "sg:phone":"+32 9 220 20 00",
    "sg:postcode":"9051",
    "sg:province":"Oost-Vlaanderen",
    "wof:name":"Poppe Wim",
    "wof:placetype":"venue"
},
  "geometry": {"coordinates":[3.6839799881,51.0187416077],"type":"Point"}
}