{
  "type": "Feature",
  "properties": {
    "addr:full":"Hoevenzavellaan 38-40 Genk (waterschei) Limburg 3600",
    "addr:postcode":"38-40;waterschei;3600",
    "addr:street":"Hoevenzavellaan",
    "iso:country":"BE",
    "sg:address":"Hoevenzavellaan 38-40",
    "sg:city":"Genk (waterschei)",
    "sg:classifiers":[
        {
            "category":"Shopping",
            "subcategory":"Clothing, Apparel, & Fashions",
            "type":"Retail Goods"
        }
    ],
    "sg:phone":"+32 89 38 23 58",
    "sg:postcode":"3600",
    "sg:province":"Limburg",
    "sg:tags":[
        "boutique"
    ],
    "wof:name":"Kings And Queens & Gringo",
    "wof:placetype":"venue"
},
  "geometry": {"coordinates":[5.5076398849,51.0010604858],"type":"Point"}
}