{
  "type": "Feature",
  "properties": {
    "iso:country":"BE",
    "sg:address":"Chemin De Grambais 20",
    "sg:city":"Nivelles",
    "sg:orig_category":"Rundveehouders",
    "sg:phone":"+32 67 21 22 61",
    "sg:postcode":"1400",
    "sg:province":"Brabant Wallon",
    "wof:name":"Etienne Demeulemeester",
    "wof:placetype":"venue"
},
  "geometry": {"coordinates":[4.2812452316,50.6118659973],"type":"Point"}
}