{
  "type": "Feature",
  "properties": {
    "iso:country":"BE",
    "sg:address":"Zilverberkenlei 12",
    "sg:city":"Brasschaat",
    "sg:orig_category":"Tuinen",
    "sg:phone":"+32 3 663 73 00",
    "sg:postcode":"2930",
    "sg:province":"Antwerpen",
    "wof:name":"Luc Kerstens",
    "wof:placetype":"venue"
},
  "geometry": {"coordinates":[4.5103549957,51.31457901],"type":"Point"}
}