{
  "type": "Feature",
  "properties": {
    "addr:full":"Steenweg 307 Alken Limburg 3570",
    "addr:housenumber":"307",
    "addr:postcode":"3570",
    "addr:street":"Steenweg",
    "iso:country":"BE",
    "sg:address":"Steenweg 307",
    "sg:city":"Alken",
    "sg:orig_category":"Rundveehouders Varkenskwekers",
    "sg:phone":"+32 11 31 21 22",
    "sg:postcode":"3570",
    "sg:province":"Limburg",
    "wof:name":"Paul Debout",
    "wof:placetype":"venue"
},
  "geometry": {"coordinates":[5.2652301788,50.8754196167],"type":"Point"}
}