{
  "type": "Feature",
  "properties": {
    "addr:full":"Chemin Du Bois Du Loup 6 Malmedy (beverc\u00e9) Li\u00e8ge 4960",
    "addr:housenumber":"6",
    "addr:postcode":"4960",
    "addr:street":"Chemin Du Bois Du Loup",
    "iso:country":"BE",
    "sg:address":"Chemin Du Bois Du Loup 6",
    "sg:city":"Malmedy (beverc\u00e9)",
    "sg:classifiers":[
        {
            "category":"Professional",
            "subcategory":"Detective & Security Services",
            "type":"Services"
        }
    ],
    "sg:phone":"+32 80 33 02 31",
    "sg:postcode":"4960",
    "sg:province":"Li\u00e8ge",
    "sg:tags":[
        "-",
        "system",
        "apparatus",
        "surveillance"
    ],
    "wof:name":"Blaise A",
    "wof:placetype":"venue"
},
  "geometry": {"coordinates":[5.9970479012,50.4293479919],"type":"Point"}
}