{
  "type": "Feature",
  "properties": {
    "addr:full":"Kasteelstraat 4 Ruiselede West-Vlaanderen 8755",
    "addr:housenumber":"4",
    "addr:postcode":"8755",
    "addr:street":"Kasteelstraat",
    "iso:country":"BE",
    "sg:address":"Kasteelstraat 4",
    "sg:city":"Ruiselede",
    "sg:classifiers":[
        {
            "category":"Bars & Pubs",
            "type":"Food & Drink"
        }
    ],
    "sg:phone":"+32 51 68 78 39",
    "sg:postcode":"8755",
    "sg:province":"West-Vlaanderen",
    "wof:name":"Pallieter",
    "wof:placetype":"venue"
},
  "geometry": {"coordinates":[3.3966960907,51.0411911011],"type":"Point"}
}