{
  "type": "Feature",
  "properties": {
    "iso:country":"BE",
    "sg:address":"Rue De G\u00e9nimont 7",
    "sg:city":"Rochefort (villers-sur-lesse)",
    "sg:classifiers":[
        {
            "category":"Building & Trades",
            "subcategory":"Construction",
            "type":"Services"
        }
    ],
    "sg:phone":"+32 475 69 25 21",
    "sg:postcode":"5580",
    "sg:province":"Namur",
    "sg:tags":[
        "installation",
        "-",
        "central",
        "heating"
    ],
    "wof:name":"Haquenne E",
    "wof:placetype":"venue"
},
  "geometry": {"coordinates":[5.112033844,50.1237258911],"type":"Point"}
}