{
  "type": "Feature",
  "properties": {
    "addr:full":"Vijverstraat 31 Wetteren Oost-Vlaanderen 9230",
    "addr:housenumber":"31",
    "addr:postcode":"9230",
    "addr:street":"Vijverstraat",
    "iso:country":"BE",
    "sg:address":"Vijverstraat 31",
    "sg:city":"Wetteren",
    "sg:classifiers":[
        {
            "category":"Education",
            "subcategory":"School",
            "type":"Public Place"
        }
    ],
    "sg:phone":"+32 9 369 22 20",
    "sg:postcode":"9230",
    "sg:province":"Oost-Vlaanderen",
    "sg:tags":[
        "secondary"
    ],
    "wof:name":"Middenschool V/h Gemeenschapsonderwijs",
    "wof:placetype":"venue"
},
  "geometry": {"coordinates":[3.8763689995,51.0039405823],"type":"Point"}
}