{
  "type": "Feature",
  "properties": {
    "iso:country":"BE",
    "sg:address":"Jan Verspeyenstraat 3",
    "sg:city":"Gent",
    "sg:orig_category":"Artsen and specialisten",
    "sg:phone":"+32 9 233 55 99",
    "sg:postcode":"9000",
    "sg:province":"Oost-Vlaanderen",
    "wof:name":"Ingeborg Van Trimpont",
    "wof:placetype":"venue"
},
  "geometry": {"coordinates":[3.7124989033,51.0585250854],"type":"Point"}
}