{
  "type": "Feature",
  "properties": {
    "addr:full":"Kraaigemstraat 33ba Assenede Oost-Vlaanderen 9968",
    "addr:housenumber":"33ba",
    "addr:postcode":"9968",
    "addr:street":"Kraaigemstraat",
    "iso:country":"BE",
    "sg:address":"Kraaigemstraat 33ba",
    "sg:city":"Assenede",
    "sg:classifiers":[
        {
            "category":"Insurance",
            "subcategory":"Life Insurance",
            "type":"Services"
        }
    ],
    "sg:phone":"+32 9 373 76 89",
    "sg:postcode":"9968",
    "sg:province":"Oost-Vlaanderen",
    "sg:tags":[
        "assurance"
    ],
    "wof:name":"Kantoor Luc Van De Velde",
    "wof:placetype":"venue"
},
  "geometry": {"coordinates":[3.6796300411,51.2116012573],"type":"Point"}
}