{
  "type": "Feature",
  "properties": {
    "addr:full":"Rue Grande 44 Saint-ghislain Hainaut 7330",
    "addr:housenumber":"44",
    "addr:postcode":"7330",
    "addr:street":"Rue Grande;Hainaut",
    "iso:country":"BE",
    "sg:address":"Rue Grande 44",
    "sg:city":"Saint-ghislain",
    "sg:classifiers":[
        {
            "category":"Retail",
            "subcategory":"Laundry & Dry Cleaning",
            "type":"Services"
        }
    ],
    "sg:phone":"+32 65 78 36 84",
    "sg:postcode":"7330",
    "sg:province":"Hainaut",
    "sg:tags":[
        "knitwear",
        "-"
    ],
    "wof:name":"Thi\u00e9ry Pull",
    "wof:placetype":"venue"
},
  "geometry": {"coordinates":[3.8200170994,50.4460639954],"type":"Point"}
}