{
  "type": "Feature",
  "properties": {
    "addr:full":"Waregemsesteenweg 20 Kruishoutem Oost-Vlaanderen 9770",
    "addr:housenumber":"20",
    "addr:postcode":"9770",
    "addr:street":"Waregemsesteenweg",
    "iso:country":"BE",
    "sg:address":"Waregemsesteenweg 20",
    "sg:city":"Kruishoutem",
    "sg:classifiers":[
        {
            "category":"Manufacturing",
            "subcategory":"Textiles",
            "type":"Manufacturing & Wholesale Goods"
        }
    ],
    "sg:phone":"+32 9 383 57 66",
    "sg:postcode":"9770",
    "sg:province":"Oost-Vlaanderen",
    "sg:tags":[
        "retail",
        "-"
    ],
    "wof:name":"Vanderstichele",
    "wof:placetype":"venue"
},
  "geometry": {"coordinates":[3.5234129429,50.9028968811],"type":"Point"}
}