{
  "type": "Feature",
  "properties": {
    "addr:full":"Tiensesteenweg 277 Bierbeek Vlaams-Brabant 3360",
    "addr:housenumber":"277",
    "addr:postcode":"3360",
    "addr:street":"Tiensesteenweg",
    "iso:country":"BE",
    "sg:address":"Tiensesteenweg 277",
    "sg:city":"Bierbeek",
    "sg:orig_category":"Traitements param\u00e9dicaux",
    "sg:phone":"+32 16 46 35 69",
    "sg:postcode":"3360",
    "sg:province":"Vlaams-Brabant",
    "wof:name":"C. Legroe",
    "wof:placetype":"venue"
},
  "geometry": {"coordinates":[4.7996640205,50.8540039062],"type":"Point"}
}