{
  "type": "Feature",
  "properties": {
    "addr:full":"Driesstraat 11 Affligem Vlaams-Brabant 1790",
    "addr:housenumber":"11",
    "addr:postcode":"1790",
    "addr:street":"Driesstraat",
    "iso:country":"BE",
    "sg:address":"Driesstraat 11",
    "sg:city":"Affligem",
    "sg:orig_category":"Enseignement maternel and primaire",
    "sg:phone":"+32 53 66 60 62",
    "sg:postcode":"1790",
    "sg:province":"Vlaams-Brabant",
    "wof:name":"Gemeentelijke Basisschool",
    "wof:placetype":"venue"
},
  "geometry": {"coordinates":[4.098927021,50.8914527893],"type":"Point"}
}