{
  "type": "Feature",
  "properties": {
    "addr:full":"Chauss\u00c9e De Waterloo 1210 Ukkel/uccle Bruxelles-Capitale 1180",
    "addr:postcode":"1210;1180",
    "addr:street":"Chausse\u0301E De Waterloo",
    "iso:country":"BE",
    "sg:address":"Chauss\u00c9e De Waterloo 1210",
    "sg:city":"Ukkel/uccle",
    "sg:orig_category":"Activit\u00e9s diverses d'imprimerie",
    "sg:phone":"+32 2 374 42 86",
    "sg:postcode":"1180",
    "sg:province":"Bruxelles-Capitale",
    "wof:name":"Annie Sliwka",
    "wof:placetype":"venue"
},
  "geometry": {"coordinates":[4.3738021851,50.7947883606],"type":"Point"}
}