{
  "type": "Feature",
  "properties": {
    "addr:full":"Rue Legrand 8 Tihange Li\u00e8ge 4500",
    "addr:housenumber":"8",
    "addr:postcode":"4500",
    "addr:street":"Rue Legrand",
    "iso:country":"BE",
    "sg:address":"Rue Legrand 8",
    "sg:city":"Tihange",
    "sg:orig_category":"Royal Canin",
    "sg:phone":"+32 85 31 83 38",
    "sg:postcode":"4500",
    "sg:province":"Li\u00e8ge",
    "wof:name":"Moulin Burette",
    "wof:placetype":"venue"
},
  "geometry": {"coordinates":[5.2615199089,50.5322113037],"type":"Point"}
}