{
  "type": "Feature",
  "properties": {
    "iso:country":"BE",
    "sg:address":"Hazelstraat 61",
    "sg:city":"Lichtervelde",
    "sg:orig_category":"Installation \u00e9lectrique r\u00e9sidentielle",
    "sg:phone":"+32 51 72 47 66",
    "sg:postcode":"8810",
    "sg:province":"West-Vlaanderen",
    "wof:name":"Ronny Verleye",
    "wof:placetype":"venue"
},
  "geometry": {"coordinates":[3.1256630421,51.0221748352],"type":"Point"}
}