{
  "type": "Feature",
  "properties": {
    "addr:full":"Rue Du Centre 80b1 Antoing Hainaut 7640",
    "addr:housenumber":"80b1",
    "addr:postcode":"7640",
    "addr:street":"Rue Du Centre",
    "iso:country":"BE",
    "sg:address":"Rue Du Centre 80b1",
    "sg:city":"Antoing",
    "sg:classifiers":[
        {
            "category":"Cafe",
            "type":"Food & Drink"
        }
    ],
    "sg:phone":"+32 69 44 38 31",
    "sg:postcode":"7640",
    "sg:province":"Hainaut",
    "sg:tags":[
        "caf\u00e9s"
    ],
    "wof:name":"Hellin",
    "wof:placetype":"venue"
},
  "geometry": {"coordinates":[3.4542329311,50.5505371094],"type":"Point"}
}