{
  "type": "Feature",
  "properties": {
    "addr:full":"Klappoel 2 Borgloon (groot) Limburg 3840",
    "addr:housenumber":"2",
    "addr:postcode":"3840",
    "addr:street":"Klappoel;Groot Limburg",
    "iso:country":"BE",
    "sg:address":"Klappoel 2",
    "sg:city":"Borgloon (groot)",
    "sg:orig_category":"Bijouteries and horlogeries",
    "sg:phone":"+32 12 74 33 36",
    "sg:postcode":"3840",
    "sg:province":"Limburg",
    "wof:name":"An Martens",
    "wof:placetype":"venue"
},
  "geometry": {"coordinates":[5.3426032066,50.8022842407],"type":"Point"}
}