{
  "type": "Feature",
  "properties": {
    "iso:country":"BE",
    "sg:address":"Sint-catharinastraat 10",
    "sg:city":"Stabroek",
    "sg:orig_category":"Cr\u00e8ches and garderies d'enfants",
    "sg:phone":"+32 3 568 70 19",
    "sg:postcode":"2940",
    "sg:province":"Antwerpen",
    "wof:name":"Kribbe Bongo",
    "wof:placetype":"venue"
},
  "geometry": {"coordinates":[4.3729372025,51.3321685791],"type":"Point"}
}