{
  "type": "Feature",
  "properties": {
    "addr:full":"Melkerijstraat 8 Scherpenheuvel-zichem (averbode) Vlaams-Brabant 3271",
    "addr:housenumber":"8",
    "addr:postcode":"3271",
    "addr:street":"Melkerijstraat",
    "iso:country":"BE",
    "sg:address":"Melkerijstraat 8",
    "sg:city":"Scherpenheuvel-zichem (averbode)",
    "sg:classifiers":[
        {
            "category":"Food & Beverages",
            "subcategory":"Supermarket",
            "type":"Retail Goods"
        }
    ],
    "sg:phone":"+32 13 77 11 65",
    "sg:postcode":"3271",
    "sg:province":"Vlaams-Brabant",
    "sg:tags":[
        "department",
        "store"
    ],
    "wof:name":"Claes",
    "wof:placetype":"venue"
},
  "geometry": {"coordinates":[4.9818639755,51.0264625549],"type":"Point"}
}