{
  "type": "Feature",
  "properties": {
    "addr:full":"Bruggestraat 86-90 Menen West-Vlaanderen 8930",
    "addr:postcode":"86-90;8930",
    "addr:street":"Bruggestraat",
    "iso:country":"BE",
    "sg:address":"Bruggestraat 86-90",
    "sg:city":"Menen",
    "sg:classifiers":[
        {
            "category":"Shopping",
            "subcategory":"Computers & Home Electronics",
            "type":"Retail Goods"
        }
    ],
    "sg:phone":"+32 56 51 13 21",
    "sg:postcode":"8930",
    "sg:province":"West-Vlaanderen",
    "sg:tags":[
        "-",
        "television",
        "radio"
    ],
    "wof:name":"Moerkerke E",
    "wof:placetype":"venue"
},
  "geometry": {"coordinates":[3.122576952,50.7988204956],"type":"Point"}
}