{
  "type": "Feature",
  "properties": {
    "addr:full":"Av. De L'ind\u00c9pend. Belge 36 Koekelberg/koekelberg Bruxelles-Capitale 1081",
    "addr:housenumber":"36",
    "addr:postcode":"1081",
    "addr:street":"Av. De;Belge",
    "iso:country":"BE",
    "sg:address":"Av. De L'ind\u00c9pend. Belge 36",
    "sg:city":"Koekelberg/koekelberg",
    "sg:orig_category":"M\u00e9decins and sp\u00e9cialistes",
    "sg:phone":"+32 2 411 31 67",
    "sg:postcode":"1081",
    "sg:province":"Bruxelles-Capitale",
    "wof:name":"Pierre Dirix",
    "wof:placetype":"venue"
},
  "geometry": {"coordinates":[4.3214521408,50.8639297485],"type":"Point"}
}