{
  "type": "Feature",
  "properties": {
    "addr:full":"Chauss\u00c9e De Waterloo 606 Elsene/ixelles Bruxelles-Capitale 1050",
    "addr:housenumber":"606",
    "addr:postcode":"1050",
    "addr:street":"Chausse\u0301E De Waterloo",
    "iso:country":"BE",
    "sg:address":"Chauss\u00c9e De Waterloo 606",
    "sg:city":"Elsene/ixelles",
    "sg:orig_category":"Traducteurs and interpr\u00e8tes",
    "sg:phone":"+32 2 343 34 32",
    "sg:postcode":"1050",
    "sg:province":"Bruxelles-Capitale",
    "wof:name":"Traduction Kux",
    "wof:placetype":"venue"
},
  "geometry": {"coordinates":[4.3645381927,50.8180465698],"type":"Point"}
}