{
  "type": "Feature",
  "properties": {
    "addr:full":"Avenue Van Kerm 9 Bruxelles (watermael-boitsfort) Bruxelles-Capitale 1170",
    "addr:housenumber":"9",
    "addr:postcode":"1170",
    "addr:street":"Avenue Van Kerm",
    "iso:country":"BE",
    "sg:address":"Avenue Van Kerm 9",
    "sg:city":"Bruxelles (watermael-boitsfort)",
    "sg:classifiers":[
        {
            "category":"Professional",
            "subcategory":"Art Services",
            "type":"Services"
        }
    ],
    "sg:phone":"+32 2 675 18 29",
    "sg:postcode":"1170",
    "sg:province":"Bruxelles-Capitale",
    "sg:tags":[
        "realization",
        "audio-visual"
    ],
    "wof:name":"Triangle 7",
    "wof:placetype":"venue"
},
  "geometry": {"coordinates":[4.4158301353,50.7858505249],"type":"Point"}
}