{
  "type": "Feature",
  "properties": {
    "iso:country":"BE",
    "sg:address":"Kerkeveld 12",
    "sg:city":"Boutersem (honsem)",
    "sg:classifiers":[
        {
            "category":"Personal",
            "subcategory":"Beauty Salon",
            "type":"Services"
        }
    ],
    "sg:phone":"+32 16 73 57 51",
    "sg:postcode":"3370",
    "sg:province":"Vlaams-Brabant",
    "sg:tags":[
        "lady",
        "-",
        "hairdressing"
    ],
    "wof:name":"Deca Haarstudio",
    "wof:placetype":"venue"
},
  "geometry": {"coordinates":[4.811273098,50.8216209412],"type":"Point"}
}