{
  "type": "Feature",
  "properties": {
    "addr:full":"Rue Crimont 5a Ellezelles Hainaut 7890",
    "addr:housenumber":"5a",
    "addr:postcode":"7890",
    "addr:street":"Rue Crimont",
    "iso:country":"BE",
    "sg:address":"Rue Crimont 5a",
    "sg:city":"Ellezelles",
    "sg:classifiers":[
        {
            "category":"Communications",
            "type":"Services"
        }
    ],
    "sg:phone":"+32 68 44 58 45",
    "sg:postcode":"7890",
    "sg:province":"Hainaut",
    "sg:tags":[
        "telecommunication"
    ],
    "wof:name":"Schillebeekx & Partners Sprl",
    "wof:placetype":"venue"
},
  "geometry": {"coordinates":[3.668309927,50.7350196838],"type":"Point"}
}