{
  "type": "Feature",
  "properties": {
    "iso:country":"BE",
    "sg:address":"Liersesteenweg 128bd",
    "sg:city":"Heist-op-den-berg",
    "sg:classifiers":[
        {
            "category":"Food & Beverages",
            "subcategory":"Fruits & Vegetables",
            "type":"Retail Goods"
        }
    ],
    "sg:phone":"+32 15 22 05 05",
    "sg:postcode":"2220",
    "sg:province":"Antwerpen",
    "sg:tags":[
        "l\u00e9gumes"
    ],
    "wof:name":"Groenhuis",
    "wof:placetype":"venue"
},
  "geometry": {"coordinates":[4.7387089729,51.0480003357],"type":"Point"}
}