{
  "type": "Feature",
  "properties": {
    "addr:full":"Wakkensesteenweg 51 Tielt West-Vlaanderen 8700",
    "addr:housenumber":"51",
    "addr:postcode":"8700",
    "addr:street":"Wakkensesteenweg",
    "iso:country":"BE",
    "sg:address":"Wakkensesteenweg 51",
    "sg:city":"Tielt",
    "sg:orig_category":"Eleveurs de bovins. Eleveurs and marchands de porcs",
    "sg:phone":"+32 51 40 75 23",
    "sg:postcode":"8700",
    "sg:province":"West-Vlaanderen",
    "wof:name":"Filip Vander Meulen",
    "wof:placetype":"venue"
},
  "geometry": {"coordinates":[3.3510971069,50.976234436],"type":"Point"}
}