{
  "type": "Feature",
  "properties": {
    "addr:full":"Faubourg-saint-germain 84 Couvin Namur 5660",
    "addr:housenumber":"84",
    "addr:postcode":"5660",
    "addr:street":"Faubourg-Saint-Germain",
    "iso:country":"BE",
    "sg:address":"Faubourg-saint-germain 84",
    "sg:city":"Couvin",
    "sg:orig_category":"Banken and kredietinstellingen",
    "sg:phone":"+32 60 34 00 30",
    "sg:postcode":"5660",
    "sg:province":"Namur",
    "wof:name":"Dexia",
    "wof:placetype":"venue"
},
  "geometry": {"coordinates":[4.493929863,50.0523834229],"type":"Point"}
}