{
  "type": "Feature",
  "properties": {
    "addr:full":"Rue Borgnet 13 Namur Namur 5000",
    "addr:housenumber":"13",
    "addr:postcode":"5000",
    "addr:street":"Rue Borgnet",
    "iso:country":"BE",
    "sg:address":"Rue Borgnet 13",
    "sg:city":"Namur",
    "sg:orig_category":"Notaires",
    "sg:phone":"+32 81 22 21 09",
    "sg:postcode":"5000",
    "sg:province":"Namur",
    "wof:name":"Maison Des Notaires",
    "wof:placetype":"venue"
},
  "geometry": {"coordinates":[4.8666248322,50.4682006836],"type":"Point"}
}