{
  "type": "Feature",
  "properties": {
    "iso:country":"BE",
    "sg:address":"Korbeek Losestraat 15",
    "sg:city":"Bierbeek",
    "sg:classifiers":[
        {
            "category":"Building & Trades",
            "subcategory":"Electrical",
            "type":"Services"
        }
    ],
    "sg:phone":"+32 16 46 45 88",
    "sg:postcode":"3360",
    "sg:province":"Vlaams-Brabant",
    "sg:tags":[
        "electric",
        "-",
        "housewiring",
        "contractor"
    ],
    "wof:name":"Prolight",
    "wof:placetype":"venue"
},
  "geometry": {"coordinates":[4.7523498535,50.8418197632],"type":"Point"}
}