{
  "type": "Feature",
  "properties": {
    "iso:country":"BE",
    "sg:address":"Mechelsesteenweg 373",
    "sg:city":"Herent",
    "sg:orig_category":"Electrom\u00e9nager, t\u00e9l\u00e9visions and radios. Installation \u00e9lectrique r\u00e9sidentielle",
    "sg:phone":"+32 16 22 70 59",
    "sg:postcode":"3020",
    "sg:province":"Vlaams-Brabant",
    "wof:name":"Alfred Parijs",
    "wof:placetype":"venue"
},
  "geometry": {"coordinates":[4.6734228134,50.9042701721],"type":"Point"}
}