{
  "type": "Feature",
  "properties": {
    "addr:full":"Place De La Gare 8 Marche-en-famenne Luxembourg 6900",
    "addr:housenumber":"8",
    "addr:postcode":"6900",
    "addr:street":"Place De La Gare",
    "iso:country":"BE",
    "sg:address":"Place De La Gare 8",
    "sg:city":"Marche-en-famenne",
    "sg:orig_category":"HUISBRANDOLIE",
    "sg:phone":"+32 84 31 13 11",
    "sg:postcode":"6900",
    "sg:province":"Luxembourg",
    "wof:name":"Bouchat",
    "wof:placetype":"venue"
},
  "geometry": {"coordinates":[5.3154768944,50.2035179138],"type":"Point"}
}