{
  "type": "Feature",
  "properties": {
    "addr:full":"Berlarij 2 Lier Antwerpen 2500",
    "addr:housenumber":"2",
    "addr:postcode":"2500",
    "addr:street":"Berlarij",
    "iso:country":"BE",
    "sg:address":"Berlarij 2",
    "sg:city":"Lier",
    "sg:orig_category":"Slagers",
    "sg:phone":"+32 3 480 15 53",
    "sg:postcode":"2500",
    "sg:province":"Antwerpen",
    "wof:name":"Alfons De Boel",
    "wof:placetype":"venue"
},
  "geometry": {"coordinates":[4.5775561333,51.1291160583],"type":"Point"}
}