{
  "type": "Feature",
  "properties": {
    "iso:country":"BE",
    "sg:address":"Vitsenveld 65",
    "sg:city":"Kontich",
    "sg:classifiers":[
        {
            "category":"Health Services",
            "subcategory":"Hospital",
            "type":"Services"
        }
    ],
    "sg:phone":"+32 3 457 82 12",
    "sg:postcode":"2550",
    "sg:province":"Antwerpen",
    "sg:tags":[
        "ambulance"
    ],
    "wof:name":"Ambulance Centrum Kontich",
    "wof:placetype":"venue"
},
  "geometry": {"coordinates":[4.4681677818,51.1231231689],"type":"Point"}
}