{
  "type": "Feature",
  "properties": {
    "addr:full":"Grote Huidevettershoek 3 Gent Oost-Vlaanderen 9000",
    "addr:housenumber":"3",
    "addr:postcode":"9000",
    "addr:street":"Grote Huidevettershoek;Oost-Vlaanderen",
    "iso:country":"BE",
    "sg:address":"Grote Huidevettershoek 3",
    "sg:city":"Gent",
    "sg:orig_category":"Agences de relations publiques",
    "sg:phone":"+32 9 223 43 83",
    "sg:postcode":"9000",
    "sg:province":"Oost-Vlaanderen",
    "wof:name":"Lahaya",
    "wof:placetype":"venue"
},
  "geometry": {"coordinates":[3.7298970222,51.0601005554],"type":"Point"}
}