{
  "type": "Feature",
  "properties": {
    "addr:full":"Stallestraat 290 Ukkel/uccle Bruxelles-Capitale 1180",
    "addr:housenumber":"290",
    "addr:postcode":"1180",
    "addr:street":"Stallestraat;/",
    "iso:country":"BE",
    "sg:address":"Stallestraat 290",
    "sg:city":"Ukkel/uccle",
    "sg:orig_category":"Herstellingen and onderhoud van auto's Voertuigen",
    "sg:phone":"+32 2 333 33 33",
    "sg:postcode":"1180",
    "sg:province":"Bruxelles-Capitale",
    "wof:name":"Garage Peugeot",
    "wof:placetype":"venue"
},
  "geometry": {"coordinates":[4.3215751648,50.7959213257],"type":"Point"}
}