{
  "type": "Feature",
  "properties": {
    "iso:country":"BE",
    "sg:address":"Avenue Des Martyrs 216d",
    "sg:city":"Fleron",
    "sg:orig_category":"Cosmetica and toiletartikelen Schoonheidssalons",
    "sg:phone":"+32 4 358 48 59",
    "sg:postcode":"4620",
    "sg:province":"Li\u00e8ge",
    "wof:name":"Capucine",
    "wof:placetype":"venue"
},
  "geometry": {"coordinates":[5.6810669899,50.614490509],"type":"Point"}
}