{
  "type": "Feature",
  "properties": {
    "addr:full":"Dorpsplein 1 Rotselaar Vlaams-Brabant 3110",
    "addr:housenumber":"1",
    "addr:postcode":"3110",
    "addr:street":"Dorpsplein",
    "iso:country":"BE",
    "sg:address":"Dorpsplein 1",
    "sg:city":"Rotselaar",
    "sg:classifiers":[
        {
            "category":"Bars & Pubs",
            "type":"Food & Drink"
        }
    ],
    "sg:phone":"+32 16 44 65 00",
    "sg:postcode":"3110",
    "sg:province":"Vlaams-Brabant",
    "wof:name":"Zijbeuk (de)",
    "wof:placetype":"venue"
},
  "geometry": {"coordinates":[4.7098879814,50.9513206482],"type":"Point"}
}