{
  "type": "Feature",
  "properties": {
    "iso:country":"BE",
    "sg:address":"Poolse-winglaan 98",
    "sg:city":"Gent (sint-denijs-westrem - Afsnee)",
    "sg:classifiers":[
        {
            "category":"Banks & Credit Unions",
            "subcategory":"Investment Brokerage",
            "type":"Services"
        }
    ],
    "sg:phone":"+32 9 221 80 90",
    "sg:postcode":"9051",
    "sg:province":"Oost-Vlaanderen",
    "sg:tags":[
        "auditor"
    ],
    "wof:name":"Steyaert Jacques",
    "wof:placetype":"venue"
},
  "geometry": {"coordinates":[3.6997220516,51.0256614685],"type":"Point"}
}