{
  "type": "Feature",
  "properties": {
    "iso:country":"BE",
    "sg:address":"Kuikenstraat 117",
    "sg:city":"Drogenbos/drogenbos",
    "sg:orig_category":"Sportclubs",
    "sg:phone":"+32 2 378 01 72",
    "sg:postcode":"1620",
    "sg:province":"Vlaams-Brabant",
    "wof:name":"Ho.y.c.",
    "wof:placetype":"venue"
},
  "geometry": {"coordinates":[4.3144669533,50.7927589417],"type":"Point"}
}