{
  "type": "Feature",
  "properties": {
    "addr:full":"Locquetstraat 10 Mechelen Antwerpen 2811",
    "addr:housenumber":"10",
    "addr:postcode":"2811",
    "addr:street":"Locquetstraat",
    "iso:country":"BE",
    "sg:address":"Locquetstraat 10",
    "sg:city":"Mechelen",
    "sg:orig_category":"M\u00e9decins and sp\u00e9cialistes",
    "sg:phone":"+32 15 41 10 66",
    "sg:postcode":"2811",
    "sg:province":"Antwerpen",
    "wof:name":"Werner Marinus",
    "wof:placetype":"venue"
},
  "geometry": {"coordinates":[4.44150877,51.0173454285],"type":"Point"}
}