{
  "type": "Feature",
  "properties": {
    "addr:full":"Rue De Suisse 14 Sint-gillis/saint-gilles Bruxelles-Capitale 1060",
    "addr:housenumber":"14",
    "addr:postcode":"1060",
    "addr:street":"Rue De Suisse",
    "iso:country":"BE",
    "sg:address":"Rue De Suisse 14",
    "sg:city":"Sint-gillis/saint-gilles",
    "sg:orig_category":"Avocats and conseillers juridiques",
    "sg:phone":"+32 2 538 32 50",
    "sg:postcode":"1060",
    "sg:province":"Bruxelles-Capitale",
    "wof:name":"Dave Jennes",
    "wof:placetype":"venue"
},
  "geometry": {"coordinates":[4.3540081978,50.832649231],"type":"Point"}
}