{
  "type": "Feature",
  "properties": {
    "iso:country":"BE",
    "sg:address":"Rue De L'eglise 27",
    "sg:city":"Kelmis/la Calamine",
    "sg:orig_category":"S\u00e9lection de personnel and placement",
    "sg:phone":"+32 87 63 98 37",
    "sg:postcode":"4720",
    "sg:province":"Li\u00e8ge",
    "wof:name":"Ale Kelmis",
    "wof:placetype":"venue"
},
  "geometry": {"coordinates":[6.0143799782,50.7158050537],"type":"Point"}
}