{
  "type": "Feature",
  "properties": {
    "iso:country":"BE",
    "sg:address":"Ronsesteenweg 23",
    "sg:city":"Russegnies",
    "sg:orig_category":"Entretien et r\u00e9parations de v\u00e9hicules \u00e0 domicile",
    "sg:phone":"+32 69 76 86 99",
    "sg:postcode":"7750",
    "sg:province":"Hainaut",
    "wof:name":"Dewolf Claude",
    "wof:placetype":"venue"
},
  "geometry": {"coordinates":[3.5024280548,50.7453575134],"type":"Point"}
}