{
  "type": "Feature",
  "properties": {
    "addr:full":"Rue Lambaitienne 6 Namur Namur 5100",
    "addr:housenumber":"6",
    "addr:postcode":"5100",
    "addr:street":"Rue Lambaitienne",
    "iso:country":"BE",
    "sg:address":"Rue Lambaitienne 6",
    "sg:city":"Namur",
    "sg:classifiers":[
        {
            "category":"Building & Trades",
            "subcategory":"Landscaping Services",
            "type":"Services"
        }
    ],
    "sg:phone":"+32 81 40 10 85",
    "sg:postcode":"5100",
    "sg:province":"Namur",
    "sg:tags":[
        "etude",
        "technique",
        "ing\u00e9nierie"
    ],
    "wof:name":"B.e.i.n.",
    "wof:placetype":"venue"
},
  "geometry": {"coordinates":[4.8713750839,50.4566345215],"type":"Point"}
}