{
  "type": "Feature",
  "properties": {
    "iso:country":"BE",
    "sg:address":"Stalenstraat 95",
    "sg:city":"Genk (waterschei)",
    "sg:classifiers":[
        {
            "category":"Shopping",
            "subcategory":"Bicycles & Sporting Goods",
            "type":"Retail Goods"
        }
    ],
    "sg:phone":"+32 89 38 26 20",
    "sg:postcode":"3600",
    "sg:province":"Limburg",
    "sg:tags":[
        "sport",
        "-"
    ],
    "wof:name":"Sporthuis Majo Nv",
    "wof:placetype":"venue"
},
  "geometry": {"coordinates":[5.5202422142,50.9946632385],"type":"Point"}
}