{
  "type": "Feature",
  "properties": {
    "addr:full":"Rue Sainte-marie 38 Li\u00e8ge 1 Li\u00e8ge 4000",
    "addr:housenumber":"38;1",
    "addr:postcode":"4000",
    "addr:street":"Rue Sainte-Marie",
    "iso:country":"BE",
    "sg:address":"Rue Sainte-marie 38",
    "sg:city":"Li\u00e8ge 1",
    "sg:classifiers":[
        {
            "category":"Health Services",
            "subcategory":"Health Practitioner",
            "type":"Services"
        }
    ],
    "sg:phone":"+32 4 368 59 36",
    "sg:postcode":"4000",
    "sg:province":"Li\u00e8ge",
    "sg:tags":[
        "physiotherapist"
    ],
    "wof:name":"Remacle Dominique",
    "wof:placetype":"venue"
},
  "geometry": {"coordinates":[5.5647611618,50.6328277588],"type":"Point"}
}