{
  "type": "Feature",
  "properties": {
    "addr:full":"Ysselmeersstraat 16 Ardooie West-Vlaanderen 8850",
    "addr:housenumber":"16",
    "addr:postcode":"8850",
    "addr:street":"Ysselmeersstraat",
    "iso:country":"BE",
    "sg:address":"Ysselmeersstraat 16",
    "sg:city":"Ardooie",
    "sg:orig_category":"Producteurs de l\u00e9gumes",
    "sg:phone":"+32 51 74 47 88",
    "sg:postcode":"8850",
    "sg:province":"West-Vlaanderen",
    "wof:name":"Dirk Devroe",
    "wof:placetype":"venue"
},
  "geometry": {"coordinates":[3.186357975,50.9527740479],"type":"Point"}
}