{
  "type": "Feature",
  "properties": {
    "addr:full":"O.de.k D'exaerdestraat 6a Halle Vlaams-Brabant 1501",
    "addr:housenumber":"6a",
    "addr:postcode":"1501",
    "addr:street":"O.De.K D'Exaerdestraat",
    "iso:country":"BE",
    "sg:address":"O.de.k D'exaerdestraat 6a",
    "sg:city":"Halle",
    "sg:orig_category":"Kapsalons",
    "sg:phone":"+32 2 356 61 27",
    "sg:postcode":"1501",
    "sg:province":"Vlaams-Brabant",
    "wof:name":"Coiffure Maggy",
    "wof:placetype":"venue"
},
  "geometry": {"coordinates":[4.263589859,50.7377891541],"type":"Point"}
}