{
  "type": "Feature",
  "properties": {
    "iso:country":"BE",
    "sg:address":"Westouterstraat 81",
    "sg:city":"Poperinge",
    "sg:orig_category":"Artsen and specialisten",
    "sg:phone":"+32 57 33 52 44",
    "sg:postcode":"8970",
    "sg:province":"West-Vlaanderen",
    "wof:name":"Frank Chielens",
    "wof:placetype":"venue"
},
  "geometry": {"coordinates":[2.7275030613,50.8456726074],"type":"Point"}
}