{
  "type": "Feature",
  "properties": {
    "addr:full":"Weeldestraat 138 Ravels (weelde) Antwerpen 2381",
    "addr:housenumber":"138",
    "addr:postcode":"2381",
    "addr:street":"Weeldestraat",
    "iso:country":"BE",
    "sg:address":"Weeldestraat 138",
    "sg:city":"Ravels (weelde)",
    "sg:classifiers":[
        {
            "category":"Food & Beverages",
            "subcategory":"Groceries & Convenience Stores",
            "type":"Retail Goods"
        }
    ],
    "sg:phone":"+32 14 65 69 76",
    "sg:postcode":"2381",
    "sg:province":"Antwerpen",
    "sg:tags":[
        "grocer"
    ],
    "wof:name":"Van Hees",
    "wof:placetype":"venue"
},
  "geometry": {"coordinates":[5.006374836,51.4099845886],"type":"Point"}
}