{
  "type": "Feature",
  "properties": {
    "iso:country":"BE",
    "sg:address":"Dadizeelsestr 220",
    "sg:city":"Moorslede",
    "sg:classifiers":[
        {
            "category":"Professional",
            "type":"Services"
        }
    ],
    "sg:phone":"+32 56 50 41 60",
    "sg:postcode":"8890",
    "sg:province":"West-Vlaanderen",
    "sg:tags":[
        "transport",
        "road"
    ],
    "wof:name":"Transport De Rudder Nv",
    "wof:placetype":"venue"
},
  "geometry": {"coordinates":[3.0863099098,50.8575706482],"type":"Point"}
}