{
  "type": "Feature",
  "properties": {
    "iso:country":"BE",
    "sg:address":"Rue Beeckman 14",
    "sg:city":"Li\u00c8ge",
    "sg:orig_category":"Grossistes divers",
    "sg:phone":"+32 4 222 32 25",
    "sg:postcode":"4000",
    "sg:province":"Li\u00e8ge",
    "wof:name":"Triprom",
    "wof:placetype":"venue"
},
  "geometry": {"coordinates":[5.5648980141,50.6363792419],"type":"Point"}
}