{
  "type": "Feature",
  "properties": {
    "addr:full":"Jacques Eggermontstraat 10 Gent Oost-Vlaanderen 9050",
    "addr:housenumber":"10",
    "addr:postcode":"9050",
    "addr:street":"Eggermontstraat;Oost-Vlaanderen",
    "iso:country":"BE",
    "sg:address":"Jacques Eggermontstraat 10",
    "sg:city":"Gent",
    "sg:orig_category":"Maroquinerie and articles de voyage. Chaussures",
    "sg:phone":"+32 9 230 87 76",
    "sg:postcode":"9050",
    "sg:province":"Oost-Vlaanderen",
    "wof:name":"Huis Doreen",
    "wof:placetype":"venue"
},
  "geometry": {"coordinates":[3.7411029339,51.0372543335],"type":"Point"}
}