{
  "type": "Feature",
  "properties": {
    "iso:country":"BE",
    "sg:address":"Adinkerkelaan 20",
    "sg:city":"De Panne",
    "sg:orig_category":"Pain, p\u00e2tisseries and confiseries. Epiceries",
    "sg:phone":"+32 58 41 42 09",
    "sg:postcode":"8660",
    "sg:province":"West-Vlaanderen",
    "wof:name":"'t Kruimeltje",
    "wof:placetype":"venue"
},
  "geometry": {"coordinates":[2.5912659168,51.0934944153],"type":"Point"}
}