{
  "type": "Feature",
  "properties": {
    "addr:full":"Eburonenlaan 3 Dilsen-stokkem Limburg 3650",
    "addr:housenumber":"3",
    "addr:postcode":"3650",
    "addr:street":"Eburonenlaan",
    "iso:country":"BE",
    "sg:address":"Eburonenlaan 3",
    "sg:city":"Dilsen-stokkem",
    "sg:orig_category":"Woningbouw",
    "sg:phone":"+32 89 75 45 52",
    "sg:postcode":"3650",
    "sg:province":"Limburg",
    "wof:name":"Deco",
    "wof:placetype":"venue"
},
  "geometry": {"coordinates":[5.7341017723,51.0318031311],"type":"Point"}
}