{
  "type": "Feature",
  "properties": {
    "iso:country":"BE",
    "sg:address":"Van Leriuslaan 112",
    "sg:city":"Boom",
    "sg:orig_category":"Kapsalons",
    "sg:phone":"+32 3 844 41 91",
    "sg:postcode":"2850",
    "sg:province":"Antwerpen",
    "wof:name":"An Verbruggen",
    "wof:placetype":"venue"
},
  "geometry": {"coordinates":[4.3770108223,51.0969696045],"type":"Point"}
}