{
  "type": "Feature",
  "properties": {
    "iso:country":"BE",
    "sg:address":"Rue Montavaux 147 Box 1",
    "sg:city":"Frameries",
    "sg:classifiers":[
        {
            "category":"Food & Beverages",
            "subcategory":"Liquor & Beverages",
            "type":"Retail Goods"
        }
    ],
    "sg:phone":"+32 65 51 05 53",
    "sg:postcode":"7080",
    "sg:province":"Hainaut",
    "sg:tags":[
        "-",
        "spirit",
        "wine"
    ],
    "wof:name":"Tastevin (le)",
    "wof:placetype":"venue"
},
  "geometry": {"coordinates":[3.9116399288,50.4075508118],"type":"Point"}
}