{
  "type": "Feature",
  "properties": {
    "addr:full":"Koningsbaan 86 Putte (beerzel) Antwerpen 2580",
    "addr:housenumber":"86",
    "addr:postcode":"2580",
    "addr:street":"Koningsbaan",
    "iso:country":"BE",
    "sg:address":"Koningsbaan 86",
    "sg:city":"Putte (beerzel)",
    "sg:classifiers":[
        {
            "category":"Home & Garden",
            "subcategory":"Building Materials",
            "type":"Retail Goods"
        }
    ],
    "sg:phone":"+32 15 23 33 74",
    "sg:postcode":"2580",
    "sg:province":"Antwerpen",
    "sg:tags":[
        "aluminium",
        "construction",
        "-"
    ],
    "wof:name":"Veralu",
    "wof:placetype":"venue"
},
  "geometry": {"coordinates":[4.6786251068,51.0526237488],"type":"Point"}
}