{
  "type": "Feature",
  "properties": {
    "addr:full":"Rue Saint-roch 26 Houyet Namur 5560",
    "addr:housenumber":"26",
    "addr:postcode":"5560",
    "addr:street":"Rue Saint-Roch",
    "iso:country":"BE",
    "sg:address":"Rue Saint-roch 26",
    "sg:city":"Houyet",
    "sg:classifiers":[
        {
            "category":"Health Services",
            "subcategory":"Health Practitioner",
            "type":"Services"
        }
    ],
    "sg:phone":"+32 82 66 71 59",
    "sg:postcode":"5560",
    "sg:province":"Namur",
    "sg:tags":[
        "physiotherapist"
    ],
    "wof:name":"Brasseur C Mme",
    "wof:placetype":"venue"
},
  "geometry": {"coordinates":[5.0044789314,50.1887321472],"type":"Point"}
}