{
  "type": "Feature",
  "properties": {
    "iso:country":"BE",
    "sg:address":"Rue D'en Haut 17",
    "sg:city":"Momignies",
    "sg:orig_category":"Quincailleries",
    "sg:phone":"+32 60 51 12 23",
    "sg:postcode":"6590",
    "sg:province":"Hainaut",
    "wof:name":"Ghislaine Monfort",
    "wof:placetype":"venue"
},
  "geometry": {"coordinates":[4.2241849899,50.0360145569],"type":"Point"}
}