{
  "type": "Feature",
  "properties": {
    "addr:full":"Avenue De La For\u00eat De Soignes 328 Rhode-saint-gen\u00e8se Vlaams-Brabant 1640",
    "addr:housenumber":"328",
    "addr:postcode":"1640",
    "addr:street":"Avenue De La Fore\u0302T De Soignes",
    "iso:country":"BE",
    "sg:address":"Avenue De La For\u00eat De Soignes 328",
    "sg:city":"Rhode-saint-gen\u00e8se",
    "sg:classifiers":[
        {
            "category":"Shopping",
            "subcategory":"Musical Instruments",
            "type":"Retail Goods"
        }
    ],
    "sg:phone":"+32 2 358 43 60",
    "sg:postcode":"1640",
    "sg:province":"Vlaams-Brabant",
    "sg:tags":[
        "optical"
    ],
    "wof:name":"Green Optic Sprl",
    "wof:placetype":"venue"
},
  "geometry": {"coordinates":[4.3806738853,50.7574462891],"type":"Point"}
}