{
  "type": "Feature",
  "properties": {
    "addr:full":"Rue Du Commerce 44 Ciney Namur 5590",
    "addr:housenumber":"44",
    "addr:postcode":"5590",
    "addr:street":"Rue Du Commerce",
    "iso:country":"BE",
    "sg:address":"Rue Du Commerce 44",
    "sg:city":"Ciney",
    "sg:orig_category":"Artsen and specialisten",
    "sg:phone":"+32 83 21 53 89",
    "sg:postcode":"5590",
    "sg:province":"Namur",
    "wof:name":"Pascale Vanheule",
    "wof:placetype":"venue"
},
  "geometry": {"coordinates":[5.0984988213,50.294090271],"type":"Point"}
}