{
  "type": "Feature",
  "properties": {
    "addr:full":"Bovenstraat 51 Bornem Antwerpen 2880",
    "addr:housenumber":"51",
    "addr:postcode":"2880",
    "addr:street":"Bovenstraat",
    "iso:country":"BE",
    "sg:address":"Bovenstraat 51",
    "sg:city":"Bornem",
    "sg:classifiers":[
        {
            "category":"Health Services",
            "subcategory":"Health Practitioner",
            "type":"Services"
        }
    ],
    "sg:phone":"+32 3 889 41 75",
    "sg:postcode":"2880",
    "sg:province":"Antwerpen",
    "sg:tags":[
        "physiotherapist"
    ],
    "wof:name":"De Keersmaecker P",
    "wof:placetype":"venue"
},
  "geometry": {"coordinates":[4.1931600571,51.0694007874],"type":"Point"}
}