{
  "type": "Feature",
  "properties": {
    "iso:country":"BE",
    "sg:address":"Chauss\u00c9e De Huy 19-21",
    "sg:city":"Chaumont-gistoux",
    "sg:orig_category":"Salles de conf\u00e9rences and de r\u00e9ceptions. Catering and organisation de f\u00eates",
    "sg:phone":"+32 10 22 58 31",
    "sg:postcode":"1325",
    "sg:province":"Brabant Wallon",
    "wof:name":"Le Canard \u00c0 Trois Pattes",
    "wof:placetype":"venue"
},
  "geometry": {"coordinates":[4.686196804,50.6904716492],"type":"Point"}
}