{
  "type": "Feature",
  "properties": {
    "addr:full":"Brusselbaan 104 Hekelgem Vlaams-Brabant 1790",
    "addr:housenumber":"104",
    "addr:postcode":"1790",
    "addr:street":"Brusselbaan",
    "iso:country":"BE",
    "sg:address":"Brusselbaan 104",
    "sg:city":"Hekelgem",
    "sg:classifiers":[
        {
            "category":"Banks & Credit Unions",
            "subcategory":"Bank",
            "type":"Services"
        }
    ],
    "sg:phone":"+32 53 66 99 73",
    "sg:postcode":"1790",
    "sg:province":"Vlaams-Brabant",
    "wof:name":"Aslk-cger Bank",
    "wof:placetype":"venue"
},
  "geometry": {"coordinates":[4.1058459282,50.9131011963],"type":"Point"}
}