{
  "type": "Feature",
  "properties": {
    "addr:full":"Rue Du Dossay 3 Wandre Li\u00e8ge 4020",
    "addr:housenumber":"3",
    "addr:postcode":"4020",
    "addr:street":"Rue Du Dossay",
    "iso:country":"BE",
    "sg:address":"Rue Du Dossay 3",
    "sg:city":"Wandre",
    "sg:classifiers":[
        {
            "category":"Juice Bar",
            "subcategory":"None",
            "type":"Food & Drink"
        }
    ],
    "sg:phone":"+32 4 345 95 25",
    "sg:postcode":"4020",
    "sg:province":"Li\u00e8ge",
    "sg:tags":[
        "liquid",
        "paraffin"
    ],
    "wof:name":"Avia Belgomazout Liege S.a.",
    "wof:placetype":"venue"
},
  "geometry": {"coordinates":[5.6452250481,50.6711921692],"type":"Point"}
}