{
  "type": "Feature",
  "properties": {
    "iso:country":"BE",
    "sg:address":"Lange Munt 9",
    "sg:city":"Gent",
    "sg:orig_category":"V\u00eatements",
    "sg:phone":"+32 9 223 93 89",
    "sg:postcode":"9000",
    "sg:province":"Oost-Vlaanderen",
    "wof:name":"Gently",
    "wof:placetype":"venue"
},
  "geometry": {"coordinates":[3.7225270271,51.0559425354],"type":"Point"}
}