{
  "type": "Feature",
  "properties": {
    "addr:full":"Beenhouwersstraat 23 Brussel/bruxelles Bruxelles-Capitale 1000",
    "addr:housenumber":"23",
    "addr:postcode":"1000",
    "addr:street":"Beenhouwersstraat;/",
    "iso:country":"BE",
    "sg:address":"Beenhouwersstraat 23",
    "sg:city":"Brussel/bruxelles",
    "sg:classifiers":[
        {
            "category":"Restaurant",
            "type":"Food & Drink"
        }
    ],
    "sg:phone":"+32 2 512 70 22",
    "sg:postcode":"1000",
    "sg:province":"Bruxelles-Capitale",
    "wof:name":"Rest. La Moule Proven\u00c7ale",
    "wof:placetype":"venue"
},
  "geometry": {"coordinates":[4.3542308807,50.8479347229],"type":"Point"}
}