{
  "type": "Feature",
  "properties": {
    "addr:full":"Charlierhelling 12 Blankenberge West-Vlaanderen 8370",
    "addr:housenumber":"12",
    "addr:postcode":"8370",
    "addr:street":"Charlierhelling",
    "iso:country":"BE",
    "sg:address":"Charlierhelling 12",
    "sg:city":"Blankenberge",
    "sg:classifiers":[
        {
            "category":"Bars & Pubs",
            "type":"Food & Drink"
        }
    ],
    "sg:phone":"+32 50 41 18 96",
    "sg:postcode":"8370",
    "sg:province":"West-Vlaanderen",
    "wof:name":"Gilmau",
    "wof:placetype":"venue"
},
  "geometry": {"coordinates":[3.1316599846,51.3165054321],"type":"Point"}
}