{
  "type": "Feature",
  "properties": {
    "addr:full":"Elshoutlaan 32 Brecht Antwerpen 2960",
    "addr:housenumber":"32",
    "addr:postcode":"2960",
    "addr:street":"Elshoutlaan",
    "iso:country":"BE",
    "sg:address":"Elshoutlaan 32",
    "sg:city":"Brecht",
    "sg:orig_category":"Schoonmaakbedrijven and ongediertebestrijding",
    "sg:phone":"+32 3 663 17 30",
    "sg:postcode":"2960",
    "sg:province":"Antwerpen",
    "wof:name":"Merksemse Glazenwasserij",
    "wof:placetype":"venue"
},
  "geometry": {"coordinates":[4.5540537834,51.3049430847],"type":"Point"}
}