{
  "type": "Feature",
  "properties": {
    "addr:full":"Rue De La Coop\u00e9ration 76 Seraing Li\u00e8ge 4100",
    "addr:housenumber":"76",
    "addr:postcode":"4100",
    "addr:street":"Rue De La Coope\u0301Ration",
    "iso:country":"BE",
    "sg:address":"Rue De La Coop\u00e9ration 76",
    "sg:city":"Seraing",
    "sg:classifiers":[
        {
            "category":"Real Estate",
            "subcategory":"Surveying",
            "type":"Services"
        }
    ],
    "sg:phone":"+32 4 337 70 98",
    "sg:postcode":"4100",
    "sg:province":"Li\u00e8ge",
    "sg:tags":[
        "surveyor",
        "land"
    ],
    "wof:name":"Cristodaro S",
    "wof:placetype":"venue"
},
  "geometry": {"coordinates":[5.5062499046,50.5910682678],"type":"Point"}
}