{
  "type": "Feature",
  "properties": {
    "addr:full":"Harensesteenweg 158 Vilvoorde Vlaams-Brabant 1800",
    "addr:housenumber":"158",
    "addr:postcode":"1800",
    "addr:street":"Harensesteenweg",
    "iso:country":"BE",
    "sg:address":"Harensesteenweg 158",
    "sg:city":"Vilvoorde",
    "sg:classifiers":[
        {
            "category":"Organizations",
            "subcategory":"Community Association",
            "type":"Services"
        }
    ],
    "sg:phone":"+32 2 251 71 64",
    "sg:postcode":"1800",
    "sg:province":"Vlaams-Brabant",
    "sg:tags":[
        "organisation"
    ],
    "wof:name":"J.a. 't Zonnetje",
    "wof:placetype":"venue"
},
  "geometry": {"coordinates":[4.4243988991,50.9198379517],"type":"Point"}
}