{
  "type": "Feature",
  "properties": {
    "addr:full":"Ezelstraat 62 Brugge West-Vlaanderen 8000",
    "addr:housenumber":"62",
    "addr:postcode":"8000",
    "addr:street":"Ezelstraat",
    "iso:country":"BE",
    "sg:address":"Ezelstraat 62",
    "sg:city":"Brugge",
    "sg:orig_category":"Chaussures. Articles m\u00e9dicaux and orthop\u00e9diques",
    "sg:phone":"+32 50 33 94 61",
    "sg:postcode":"8000",
    "sg:province":"West-Vlaanderen",
    "wof:name":"Huis Ferla",
    "wof:placetype":"venue"
},
  "geometry": {"coordinates":[3.2181019783,51.2136573792],"type":"Point"}
}