{
  "type": "Feature",
  "properties": {
    "iso:country":"BE",
    "sg:address":"Edingsesteenweg 200",
    "sg:city":"Asse",
    "sg:classifiers":[
        {
            "category":"Cafe",
            "type":"Food & Drink"
        }
    ],
    "sg:phone":"+32 2 452 74 92",
    "sg:postcode":"1730",
    "sg:province":"Vlaams-Brabant",
    "sg:tags":[
        "caf\u00e9s"
    ],
    "wof:name":"E. De Wandeler",
    "wof:placetype":"venue"
},
  "geometry": {"coordinates":[4.1715741158,50.8936233521],"type":"Point"}
}