{
  "type": "Feature",
  "properties": {
    "addr:full":"Wijtschotbaan Schoten 2120",
    "addr:postcode":"2120",
    "addr:street":"Wijtschotbaan",
    "iso:country":"BE",
    "sg:address":"Wijtschotbaan",
    "sg:city":"Schoten",
    "sg:orig_category":"Gestion des d\u00e9charges and sites d\u00e9finitifs de stockage",
    "sg:phone":"+32 3 685 02 72",
    "sg:postcode":"2120",
    "wof:name":"Containerpark Schoten",
    "wof:placetype":"venue"
},
  "geometry": {"coordinates":[4.5063881874,51.2419776917],"type":"Point"}
}