{
  "type": "Feature",
  "properties": {
    "iso:country":"BE",
    "sg:address":"Steenweg Op Aalst 128",
    "sg:city":"Aalst (hofstade)",
    "sg:classifiers":[
        {
            "category":"Personal",
            "subcategory":"Sauna",
            "type":"Services"
        }
    ],
    "sg:phone":"+32 53 77 44 88",
    "sg:postcode":"9308",
    "sg:province":"Oost-Vlaanderen",
    "wof:name":"De Thermen",
    "wof:placetype":"venue"
},
  "geometry": {"coordinates":[4.0347590446,50.9603500366],"type":"Point"}
}