{
  "type": "Feature",
  "properties": {
    "addr:full":"Generaal Deprezstraat 16 Harelbeke West-Vlaanderen 8530",
    "addr:housenumber":"16",
    "addr:postcode":"8530",
    "addr:street":"Generaal Deprezstraat",
    "iso:country":"BE",
    "sg:address":"Generaal Deprezstraat 16",
    "sg:city":"Harelbeke",
    "sg:classifiers":[
        {
            "category":"Health Services",
            "subcategory":"Medical Lab",
            "type":"Services"
        }
    ],
    "sg:phone":"+32 56 23 70 70",
    "sg:postcode":"8530",
    "sg:province":"West-Vlaanderen",
    "sg:tags":[
        "yeast"
    ],
    "wof:name":"Ranson Nv",
    "wof:placetype":"venue"
},
  "geometry": {"coordinates":[3.3128950596,50.8355865479],"type":"Point"}
}