{
  "type": "Feature",
  "properties": {
    "iso:country":"BE",
    "sg:address":"Chauss\u00c9e De Louvain 495",
    "sg:city":"Namur",
    "sg:classifiers":[
        {
            "category":"Fast Food",
            "type":"Food & Drink"
        }
    ],
    "sg:phone":"+32 477 36 89 28",
    "sg:postcode":"5004",
    "sg:province":"Namur",
    "sg:tags":[
        "\u00c0",
        "restaurants",
        "emporter",
        "restaurant"
    ],
    "wof:name":"Friterie Yumbo",
    "wof:placetype":"venue"
},
  "geometry": {"coordinates":[4.8905959129,50.4862785339],"type":"Point"}
}