{
  "type": "Feature",
  "properties": {
    "addr:full":"Rue Du Bassin 2 Verviers (ensival) Li\u00e8ge 4800",
    "addr:housenumber":"2",
    "addr:postcode":"4800",
    "addr:street":"Rue Du Bassin",
    "iso:country":"BE",
    "sg:address":"Rue Du Bassin 2",
    "sg:city":"Verviers (ensival)",
    "sg:classifiers":[
        {
            "category":"Manufacturing",
            "subcategory":"Textiles",
            "type":"Manufacturing & Wholesale Goods"
        }
    ],
    "sg:phone":"+32 87 22 60 34",
    "sg:postcode":"4800",
    "sg:province":"Li\u00e8ge",
    "sg:tags":[
        "machinery"
    ],
    "wof:name":"Delbushaye R",
    "wof:placetype":"venue"
},
  "geometry": {"coordinates":[5.8594508171,50.5917663574],"type":"Point"}
}