{
  "type": "Feature",
  "properties": {
    "iso:country":"BE",
    "sg:address":"Ringlaan 6",
    "sg:city":"Brecht",
    "sg:classifiers":[
        {
            "category":"Transit Center",
            "subcategory":"Freight",
            "type":"Transportation"
        }
    ],
    "sg:phone":"+32 3 330 15 50",
    "sg:postcode":"2960",
    "sg:province":"Antwerpen",
    "sg:tags":[
        "import",
        "export",
        "-"
    ],
    "wof:name":"Yellow Line",
    "wof:placetype":"venue"
},
  "geometry": {"coordinates":[4.6368641853,51.3542938232],"type":"Point"}
}