{
  "type": "Feature",
  "properties": {
    "addr:full":"Kasteellaan 345 Gent Oost-Vlaanderen 9000",
    "addr:housenumber":"345",
    "addr:postcode":"9000",
    "addr:street":"Kasteellaan;Oost-Vlaanderen",
    "iso:country":"BE",
    "sg:address":"Kasteellaan 345",
    "sg:city":"Gent",
    "sg:orig_category":"R\u00e9paration and restauration de meubles",
    "sg:phone":"+32 9 223 72 20",
    "sg:postcode":"9000",
    "sg:province":"Oost-Vlaanderen",
    "wof:name":"Barts Wonderwinkel",
    "wof:placetype":"venue"
},
  "geometry": {"coordinates":[3.7396099567,51.0536460876],"type":"Point"}
}