{
  "type": "Feature",
  "properties": {
    "addr:full":"Rue De La Paix 12 Ecaussinnes (ecaussinnes-d'enghien) Hainaut 7190",
    "addr:housenumber":"12",
    "addr:postcode":"7190",
    "addr:street":"Rue De La Paix;Ecaussinnes-D'Enghien Hainaut",
    "iso:country":"BE",
    "sg:address":"Rue De La Paix 12",
    "sg:city":"Ecaussinnes (ecaussinnes-d'enghien)",
    "sg:classifiers":[
        {
            "category":"Building & Trades",
            "subcategory":"Landscaping Services",
            "type":"Services"
        }
    ],
    "sg:phone":"+32 67 44 46 73",
    "sg:postcode":"7190",
    "sg:province":"Hainaut",
    "sg:tags":[
        "forestry"
    ],
    "wof:name":"Pourtois Hubert",
    "wof:placetype":"venue"
},
  "geometry": {"coordinates":[4.1754550934,50.5718727112],"type":"Point"}
}