{
  "type": "Feature",
  "properties": {
    "addr:full":"Rozenpark 52 Kortrijk West-Vlaanderen 8510",
    "addr:housenumber":"52",
    "addr:postcode":"8510",
    "addr:street":"Rozenpark",
    "iso:country":"BE",
    "sg:address":"Rozenpark 52",
    "sg:city":"Kortrijk",
    "sg:orig_category":"Sportclubs",
    "sg:phone":"+32 56 25 70 62",
    "sg:postcode":"8510",
    "sg:province":"West-Vlaanderen",
    "wof:name":"Ieders Welzijn",
    "wof:placetype":"venue"
},
  "geometry": {"coordinates":[3.2617909908,50.7637367249],"type":"Point"}
}