{
  "type": "Feature",
  "properties": {
    "addr:full":"Begoniastraat 36 Hamont-achel (achel) Limburg 3930",
    "addr:housenumber":"36",
    "addr:postcode":"3930",
    "addr:street":"Begoniastraat",
    "iso:country":"BE",
    "sg:address":"Begoniastraat 36",
    "sg:city":"Hamont-achel (achel)",
    "sg:classifiers":[
        {
            "category":"Food & Beverages",
            "subcategory":"Dairy",
            "type":"Retail Goods"
        }
    ],
    "sg:phone":"+32 11 64 54 09",
    "sg:postcode":"3930",
    "sg:province":"Limburg",
    "sg:tags":[
        "product",
        "-"
    ],
    "wof:name":"Claes A",
    "wof:placetype":"venue"
},
  "geometry": {"coordinates":[5.4839048386,51.2614021301],"type":"Point"}
}