{
  "type": "Feature",
  "properties": {
    "iso:country":"BE",
    "sg:address":"Rue Des Vingt-deux 33",
    "sg:city":"Li\u00c8ge",
    "sg:orig_category":"Alternatieve geneeskunde",
    "sg:phone":"+32 71 50 61 25",
    "sg:postcode":"4000",
    "sg:province":"Li\u00e8ge",
    "wof:name":"Concept Tifene",
    "wof:placetype":"venue"
},
  "geometry": {"coordinates":[5.5693759918,50.6280441284],"type":"Point"}
}