{
  "type": "Feature",
  "properties": {
    "addr:full":"Vijverstraat 3 Zottegem Oost-Vlaanderen 9620",
    "addr:housenumber":"3",
    "addr:postcode":"9620",
    "addr:street":"Vijverstraat",
    "iso:country":"BE",
    "sg:address":"Vijverstraat 3",
    "sg:city":"Zottegem",
    "sg:orig_category":"Entretien and r\u00e9parations de voitures",
    "sg:phone":"+32 9 360 50 13",
    "sg:postcode":"9620",
    "sg:province":"Oost-Vlaanderen",
    "wof:name":"Garage Reynart",
    "wof:placetype":"venue"
},
  "geometry": {"coordinates":[3.8216021061,50.8729362488],"type":"Point"}
}