{
  "type": "Feature",
  "properties": {
    "addr:full":"Aaltervoetweg 1a Ruiselede West-Vlaanderen 8755",
    "addr:housenumber":"1a",
    "addr:postcode":"8755",
    "addr:street":"Aaltervoetweg",
    "iso:country":"BE",
    "sg:address":"Aaltervoetweg 1a",
    "sg:city":"Ruiselede",
    "sg:classifiers":[
        {
            "category":"Farming",
            "subcategory":"Livestock Farm",
            "type":"Manufacturing & Wholesale Goods"
        }
    ],
    "sg:phone":"+32 51 68 62 35",
    "sg:postcode":"8755",
    "sg:province":"West-Vlaanderen",
    "sg:tags":[
        "buyer"
    ],
    "wof:name":"Algoet Bvba",
    "wof:placetype":"venue"
},
  "geometry": {"coordinates":[3.4050679207,51.0529594421],"type":"Point"}
}