{
  "type": "Feature",
  "properties": {
    "iso:country":"BE",
    "sg:address":"Rue Auguste Beernaert 33",
    "sg:city":"Bruxelles (watermael-boitsfort)",
    "sg:classifiers":[
        {
            "category":"Health Services",
            "subcategory":"Doctor",
            "type":"Services"
        }
    ],
    "sg:phone":"+32 2 660 24 99",
    "sg:postcode":"1170",
    "sg:province":"Bruxelles-Capitale",
    "sg:tags":[
        "medicinephysicians",
        "surgeon"
    ],
    "wof:name":"Fostier P",
    "wof:placetype":"venue"
},
  "geometry": {"coordinates":[4.4218521118,50.7916030884],"type":"Point"}
}