{
  "type": "Feature",
  "properties": {
    "iso:country":"BE",
    "sg:address":"Jan Blomstraat 8",
    "sg:city":"Antwerpen",
    "sg:classifiers":[
        {
            "category":"Fast Food",
            "type":"Food & Drink"
        }
    ],
    "sg:phone":"+32 3 226 74 50",
    "sg:postcode":"2000",
    "sg:province":"Antwerpen",
    "sg:tags":[
        "meeneem",
        "restaurant"
    ],
    "wof:name":"Da Giovanni",
    "wof:placetype":"venue"
},
  "geometry": {"coordinates":[4.4005331993,51.2199478149],"type":"Point"}
}