{
  "type": "Feature",
  "properties": {
    "iso:country":"BE",
    "sg:address":"Amerikalei 47",
    "sg:city":"Antwerpen",
    "sg:orig_category":"Enseignement maternel and primaire",
    "sg:phone":"+32 3 237 71 95",
    "sg:postcode":"2000",
    "sg:province":"Antwerpen",
    "wof:name":"Vrije Lagere School",
    "wof:placetype":"venue"
},
  "geometry": {"coordinates":[4.4001979828,51.2077598572],"type":"Point"}
}