{
  "type": "Feature",
  "properties": {
    "addr:full":"Place Albert-ier 17 Nivelles Brabant Wallon 1400",
    "addr:housenumber":"17",
    "addr:postcode":"1400",
    "addr:street":"Place Albert-Ier",
    "iso:country":"BE",
    "sg:address":"Place Albert-ier 17",
    "sg:city":"Nivelles",
    "sg:orig_category":"Banken and kredietinstellingen",
    "sg:phone":"+32 67 84 30 43",
    "sg:postcode":"1400",
    "sg:province":"Brabant Wallon",
    "wof:name":"Caisse Priv\u00c9e Banque",
    "wof:placetype":"venue"
},
  "geometry": {"coordinates":[4.3225598335,50.5977668762],"type":"Point"}
}