{
  "type": "Feature",
  "properties": {
    "addr:full":"Rue Lava 2ba Nandrin Li\u00e8ge 4550",
    "addr:housenumber":"2ba",
    "addr:postcode":"4550",
    "addr:street":"Rue Lava",
    "iso:country":"BE",
    "sg:address":"Rue Lava 2ba",
    "sg:city":"Nandrin",
    "sg:orig_category":"Woningbouw",
    "sg:phone":"+32 85 51 36 34",
    "sg:postcode":"4550",
    "sg:province":"Li\u00e8ge",
    "wof:name":"Leon Simon",
    "wof:placetype":"venue"
},
  "geometry": {"coordinates":[5.3917379379,50.5149040222],"type":"Point"}
}