{
  "type": "Feature",
  "properties": {
    "addr:full":"Fauvillers-centre 69 Fauvillers Luxembourg 6637",
    "addr:housenumber":"69",
    "addr:postcode":"6637",
    "addr:street":"Fauvillers-Centre",
    "iso:country":"BE",
    "sg:address":"Fauvillers-centre 69",
    "sg:city":"Fauvillers",
    "sg:orig_category":"Enseignement maternel and primaire",
    "sg:phone":"+32 63 60 16 48",
    "sg:postcode":"6637",
    "sg:province":"Luxembourg",
    "wof:name":"Ecole Fond. Communale",
    "wof:placetype":"venue"
},
  "geometry": {"coordinates":[5.6666798592,49.8505592346],"type":"Point"}
}