{
  "type": "Feature",
  "properties": {
    "iso:country":"BE",
    "sg:address":"Loystraat 30",
    "sg:city":"Hamme",
    "sg:orig_category":"Plomberie, chauffage and installations sanitaires",
    "sg:phone":"+32 52 47 95 81",
    "sg:postcode":"9220",
    "sg:province":"Oost-Vlaanderen",
    "wof:name":"Fa. Sanigas",
    "wof:placetype":"venue"
},
  "geometry": {"coordinates":[4.1395292282,51.089225769],"type":"Point"}
}