{
  "type": "Feature",
  "properties": {
    "iso:country":"BE",
    "sg:address":"17esk.licht Vliegwezenln 7",
    "sg:city":"Balen",
    "sg:orig_category":"Sportterreinen and installaties behalve sportcentra",
    "sg:phone":"+32 14 81 61 99",
    "sg:postcode":"2490",
    "sg:province":"Antwerpen",
    "wof:name":"Manege Keiheuvel",
    "wof:placetype":"venue"
},
  "geometry": {"coordinates":[5.1680059433,51.1709327698],"type":"Point"}
}