{
  "type": "Feature",
  "properties": {
    "iso:country":"BE",
    "sg:address":"Rue Tollet 5",
    "sg:city":"Oupeye",
    "sg:classifiers":[
        {
            "category":"Professional",
            "subcategory":"Testing Lab",
            "type":"Services"
        }
    ],
    "sg:phone":"+32 4 264 04 46",
    "sg:postcode":"4680",
    "sg:province":"Li\u00e8ge",
    "sg:tags":[
        "chemist"
    ],
    "wof:name":"Pirotte",
    "wof:placetype":"venue"
},
  "geometry": {"coordinates":[5.648455143,50.7044067383],"type":"Point"}
}