{
  "type": "Feature",
  "properties": {
    "addr:full":"Lostraat 148 Roosdaal Vlaams-Brabant 1760",
    "addr:housenumber":"148",
    "addr:postcode":"1760",
    "addr:street":"Lostraat",
    "iso:country":"BE",
    "sg:address":"Lostraat 148",
    "sg:city":"Roosdaal",
    "sg:orig_category":"Telecommunicatieapparaten",
    "sg:phone":"+32 53 68 11 22",
    "sg:postcode":"1760",
    "sg:province":"Vlaams-Brabant",
    "wof:name":"Guldekon",
    "wof:placetype":"venue"
},
  "geometry": {"coordinates":[4.1136097908,50.8432197571],"type":"Point"}
}