{
  "type": "Feature",
  "properties": {
    "iso:country":"BE",
    "sg:address":"Pijlstraat 14",
    "sg:city":"Lommel",
    "sg:classifiers":[
        {
            "category":"Health Services",
            "subcategory":"Health Practitioner",
            "type":"Services"
        }
    ],
    "sg:phone":"+32 11 54 58 18",
    "sg:postcode":"3920",
    "sg:province":"Limburg",
    "sg:tags":[
        "physiotherapist"
    ],
    "wof:name":"De Jong Ludo",
    "wof:placetype":"venue"
},
  "geometry": {"coordinates":[5.3151130676,51.2166061401],"type":"Point"}
}