{
  "type": "Feature",
  "properties": {
    "addr:full":"Grensstraat 34 Zottegem Oost-Vlaanderen 9620",
    "addr:housenumber":"34",
    "addr:postcode":"9620",
    "addr:street":"Grensstraat",
    "iso:country":"BE",
    "sg:address":"Grensstraat 34",
    "sg:city":"Zottegem",
    "sg:classifiers":[
        {
            "category":"Shopping",
            "subcategory":"Clothing, Apparel, & Fashions",
            "type":"Retail Goods"
        }
    ],
    "sg:phone":"+32 9 360 16 95",
    "sg:postcode":"9620",
    "sg:province":"Oost-Vlaanderen",
    "sg:tags":[
        "textile",
        "clothing",
        "clothes"
    ],
    "wof:name":"Inrichtingen Cantaert Bvba",
    "wof:placetype":"venue"
},
  "geometry": {"coordinates":[3.8127200603,50.872718811],"type":"Point"}
}