{
  "type": "Feature",
  "properties": {
    "addr:full":"Kerkstraat 43 Laarne Oost-Vlaanderen 9270",
    "addr:housenumber":"43",
    "addr:postcode":"9270",
    "addr:street":"Kerkstraat",
    "iso:country":"BE",
    "sg:address":"Kerkstraat 43",
    "sg:city":"Laarne",
    "sg:classifiers":[
        {
            "category":"Wholesale",
            "subcategory":"Plants",
            "type":"Manufacturing & Wholesale Goods"
        }
    ],
    "sg:phone":"+32 9 369 29 28",
    "sg:postcode":"9270",
    "sg:province":"Oost-Vlaanderen",
    "sg:tags":[
        "whol",
        "flower",
        "-",
        "grower"
    ],
    "wof:name":"Martens A",
    "wof:placetype":"venue"
},
  "geometry": {"coordinates":[3.8637061119,51.0380592346],"type":"Point"}
}