{
  "type": "Feature",
  "properties": {
    "iso:country":"BE",
    "sg:address":"Oudestraat 1",
    "sg:city":"Kampenhout",
    "sg:orig_category":"Pi\u00e8ces and accessoires de v\u00e9hicules automobiles Entretien and r\u00e9parations de voitures",
    "sg:phone":"+32 16 60 00 72",
    "sg:postcode":"1910",
    "sg:province":"Vlaams-Brabant",
    "wof:name":"Vda Auto-electriciteit",
    "wof:placetype":"venue"
},
  "geometry": {"coordinates":[4.6008400917,50.9607696533],"type":"Point"}
}