{
  "type": "Feature",
  "properties": {
    "iso:country":"BE",
    "sg:address":"Voordries 31",
    "sg:city":"Gent (gentbrugge)",
    "sg:classifiers":[
        {
            "category":"Social Services",
            "subcategory":"Child Care",
            "type":"Services"
        }
    ],
    "sg:phone":"+32 9 232 02 61",
    "sg:postcode":"9050",
    "sg:province":"Oost-Vlaanderen",
    "sg:tags":[
        "baby",
        "nursery",
        "day",
        "sitting"
    ],
    "wof:name":"Groen Drieske ('t)",
    "wof:placetype":"venue"
},
  "geometry": {"coordinates":[3.768419981,51.0418205261],"type":"Point"}
}