{
  "type": "Feature",
  "properties": {
    "iso:country":"BE",
    "sg:address":"Veerhuisdreef 2",
    "sg:city":"Schoten",
    "sg:orig_category":"Artistes ind\u00e9pendants",
    "sg:phone":"+32 3 290 44 95",
    "sg:postcode":"2900",
    "sg:province":"Antwerpen",
    "wof:name":"Pieter Wagemans",
    "wof:placetype":"venue"
},
  "geometry": {"coordinates":[4.5130701065,51.2582893372],"type":"Point"}
}