{
  "type": "Feature",
  "properties": {
    "addr:full":"Rue Francisco Ferrer 102 Saint-nicolas Li\u00e8ge 4420",
    "addr:housenumber":"102",
    "addr:postcode":"4420",
    "addr:street":"Rue Francisco Ferrer;Saint-Nicolas Lie\u0300Ge",
    "iso:country":"BE",
    "sg:address":"Rue Francisco Ferrer 102",
    "sg:city":"Saint-nicolas",
    "sg:orig_category":"Enseignement maternel and primaire",
    "sg:phone":"+32 4 226 50 20",
    "sg:postcode":"4420",
    "sg:province":"Li\u00e8ge",
    "wof:name":"Ecole Fondamentale Libre",
    "wof:placetype":"venue"
},
  "geometry": {"coordinates":[5.5300722122,50.6208953857],"type":"Point"}
}