{
  "type": "Feature",
  "properties": {
    "iso:country":"BE",
    "sg:address":"Rue Haute 14",
    "sg:city":"Assesse",
    "sg:classifiers":[
        {
            "category":"Cafe",
            "type":"Food & Drink"
        }
    ],
    "sg:phone":"+32 83 69 01 21",
    "sg:postcode":"5332",
    "sg:province":"Namur",
    "sg:tags":[
        "caf\u00e9s"
    ],
    "wof:name":"Vanessa Lamort",
    "wof:placetype":"venue"
},
  "geometry": {"coordinates":[4.9603500366,50.3483772278],"type":"Point"}
}