{
  "type": "Feature",
  "properties": {
    "iso:country":"BE",
    "sg:address":"Zuidstraat 29",
    "sg:city":"Wervik",
    "sg:orig_category":"Installation \u00e9lectrique r\u00e9sidentielle",
    "sg:phone":"+32 56 51 49 87",
    "sg:postcode":"8940",
    "sg:province":"West-Vlaanderen",
    "wof:name":"Philippe Van Den Abeele",
    "wof:placetype":"venue"
},
  "geometry": {"coordinates":[3.077078104,50.8082199097],"type":"Point"}
}