{
  "type": "Feature",
  "properties": {
    "iso:country":"BE",
    "sg:address":"Rue Louis Bi\u00c9rin 28",
    "sg:city":"Pepinster",
    "sg:orig_category":"Paramedische behandelingen",
    "sg:phone":"+32 87 46 05 58",
    "sg:postcode":"4860",
    "sg:province":"Li\u00e8ge",
    "wof:name":"M. Arnotte",
    "wof:placetype":"venue"
},
  "geometry": {"coordinates":[5.795691967,50.5686645508],"type":"Point"}
}