{
  "type": "Feature",
  "properties": {
    "addr:full":"Avenue Prince De Li\u00c8ge 41 Namur Namur 5100",
    "addr:housenumber":"41",
    "addr:postcode":"5100",
    "addr:street":"Avenue Prince De Lie\u0300Ge",
    "iso:country":"BE",
    "sg:address":"Avenue Prince De Li\u00c8ge 41",
    "sg:city":"Namur",
    "sg:orig_category":"Supermarch\u00e9s",
    "sg:phone":"+32 81 30 65 40",
    "sg:postcode":"5100",
    "sg:province":"Namur",
    "wof:name":"Delhaize",
    "wof:placetype":"venue"
},
  "geometry": {"coordinates":[4.8713750839,50.4566345215],"type":"Point"}
}