{
  "type": "Feature",
  "properties": {
    "iso:country":"BE",
    "sg:address":"Riemsterweg 9",
    "sg:city":"Bilzen",
    "sg:classifiers":[
        {
            "category":"Professional",
            "subcategory":"Accounting & Tax Preparation",
            "type":"Services"
        }
    ],
    "sg:phone":"+32 89 41 30 50",
    "sg:postcode":"3740",
    "sg:province":"Limburg",
    "sg:tags":[
        "accountant"
    ],
    "wof:name":"Mullens H",
    "wof:placetype":"venue"
},
  "geometry": {"coordinates":[5.5246391296,50.8642311096],"type":"Point"}
}