{
  "type": "Feature",
  "properties": {
    "addr:full":"Diesterstraat 27b204 Sint-truiden Limburg 3800",
    "addr:housenumber":"27b204",
    "addr:postcode":"3800",
    "addr:street":"Diesterstraat",
    "iso:country":"BE",
    "sg:address":"Diesterstraat 27b204",
    "sg:city":"Sint-truiden",
    "sg:orig_category":"Sportclubs",
    "sg:phone":"+32 11 68 58 45",
    "sg:postcode":"3800",
    "sg:province":"Limburg",
    "wof:name":"Leopold T.c. St.truiden",
    "wof:placetype":"venue"
},
  "geometry": {"coordinates":[5.1853461266,50.8175468445],"type":"Point"}
}