{
  "type": "Feature",
  "properties": {
    "iso:country":"BE",
    "sg:address":"Rue D'orl\u00c9ans 20",
    "sg:city":"Charleroi",
    "sg:orig_category":"Pharmaciens",
    "sg:phone":"+32 71 32 08 39",
    "sg:postcode":"6000",
    "sg:province":"Hainaut",
    "wof:name":"Pharmacie Pasquet",
    "wof:placetype":"venue"
},
  "geometry": {"coordinates":[4.4442768097,50.4165420532],"type":"Point"}
}