{
  "type": "Feature",
  "properties": {
    "iso:country":"BE",
    "sg:address":"Rue Rioul 15b3",
    "sg:city":"Huy",
    "sg:orig_category":"Journaux. Tabac",
    "sg:phone":"+32 85 23 16 78",
    "sg:postcode":"4500",
    "sg:province":"Li\u00e8ge",
    "wof:name":"Librairie Vierset",
    "wof:placetype":"venue"
},
  "geometry": {"coordinates":[5.2447161674,50.5239334106],"type":"Point"}
}