{
  "type": "Feature",
  "properties": {
    "iso:country":"BE",
    "sg:address":"Bergensesteenweg 61",
    "sg:city":"Halle",
    "sg:classifiers":[
        {
            "category":"Communications",
            "subcategory":"Film & Video Production",
            "type":"Services"
        }
    ],
    "sg:phone":"+32 2 360 17 83",
    "sg:postcode":"1500",
    "sg:province":"Vlaams-Brabant",
    "sg:tags":[
        "hiring",
        "-"
    ],
    "wof:name":"Video Kik",
    "wof:placetype":"venue"
},
  "geometry": {"coordinates":[4.2326498032,50.7331886292],"type":"Point"}
}