{
  "type": "Feature",
  "properties": {
    "iso:country":"BE",
    "sg:address":"Waterbossen 3",
    "sg:city":"Londerzeel (malderen)",
    "sg:classifiers":[
        {
            "category":"Banks & Credit Unions",
            "subcategory":"Investment Brokerage",
            "type":"Services"
        }
    ],
    "sg:phone":"+32 52 30 43 55",
    "sg:postcode":"1840",
    "sg:province":"Vlaams-Brabant",
    "sg:tags":[
        "auditor"
    ],
    "wof:name":"Derick J",
    "wof:placetype":"venue"
},
  "geometry": {"coordinates":[4.2578458786,51.0166015625],"type":"Point"}
}