{
  "type": "Feature",
  "properties": {
    "iso:country":"BE",
    "sg:address":"Avenue Foch 804",
    "sg:city":"Mons (jemappes)",
    "sg:classifiers":[
        {
            "category":"Manufacturing",
            "subcategory":"Textiles",
            "type":"Manufacturing & Wholesale Goods"
        }
    ],
    "sg:phone":"+32 65 82 25 77",
    "sg:postcode":"7012",
    "sg:province":"Hainaut",
    "sg:tags":[
        "retail",
        "-"
    ],
    "wof:name":"Au Flamand Sprl",
    "wof:placetype":"venue"
},
  "geometry": {"coordinates":[3.8894600868,50.4481964111],"type":"Point"}
}