{
  "type": "Feature",
  "properties": {
    "addr:full":"Fosse Des Biays 55a Libin Luxembourg 6890",
    "addr:housenumber":"55a",
    "addr:postcode":"6890",
    "addr:street":"Fosse",
    "iso:country":"BE",
    "sg:address":"Fosse Des Biays 55a",
    "sg:city":"Libin",
    "sg:classifiers":[
        {
            "category":"Arena",
            "subcategory":"Sports Club",
            "type":"Entertainment"
        }
    ],
    "sg:phone":"+32 61 28 78 33",
    "sg:postcode":"6890",
    "sg:province":"Luxembourg",
    "sg:tags":[
        "martial art",
        "accessory"
    ],
    "wof:name":"Pierre Alexandre Shiatsu",
    "wof:placetype":"venue"
},
  "geometry": {"coordinates":[5.2690758705,49.9817848206],"type":"Point"}
}