{
  "type": "Feature",
  "properties": {
    "addr:full":"Diestersteenweg 11 Hasselt (kermt) Limburg 3510",
    "addr:housenumber":"11",
    "addr:postcode":"3510",
    "addr:street":"Diestersteenweg",
    "iso:country":"BE",
    "sg:address":"Diestersteenweg 11",
    "sg:city":"Hasselt (kermt)",
    "sg:orig_category":"Solariums",
    "sg:phone":"+32 11 25 12 50",
    "sg:postcode":"3510",
    "sg:province":"Limburg",
    "wof:name":"All Wellness Bvba",
    "wof:placetype":"venue"
},
  "geometry": {"coordinates":[5.2359399796,50.947719574],"type":"Point"}
}