{
  "type": "Feature",
  "properties": {
    "addr:full":"Petite Rue Des Loups 27 Anderlecht/anderlecht Bruxelles-Capitale 1070",
    "addr:housenumber":"27",
    "addr:postcode":"1070",
    "addr:street":"Petite Rue Des Loups",
    "iso:country":"BE",
    "sg:address":"Petite Rue Des Loups 27",
    "sg:city":"Anderlecht/anderlecht",
    "sg:orig_category":"Boucheries",
    "sg:phone":"+32 2 521 36 07",
    "sg:postcode":"1070",
    "sg:province":"Bruxelles-Capitale",
    "wof:name":"Boucherie Eddy",
    "wof:placetype":"venue"
},
  "geometry": {"coordinates":[4.2969241142,50.8235397339],"type":"Point"}
}