{
  "type": "Feature",
  "properties": {
    "addr:full":"Rue Chalais 8 Villers-le-bouillet (fize-fontaine) Li\u00e8ge 4530",
    "addr:housenumber":"8",
    "addr:postcode":"4530",
    "addr:street":"Rue Chalais;Fize-Fontaine",
    "iso:country":"BE",
    "sg:address":"Rue Chalais 8",
    "sg:city":"Villers-le-bouillet (fize-fontaine)",
    "sg:classifiers":[
        {
            "category":"Professional",
            "subcategory":"Accounting & Tax Preparation",
            "type":"Services"
        }
    ],
    "sg:phone":"+32 4 259 71 65",
    "sg:postcode":"4530",
    "sg:province":"Li\u00e8ge",
    "sg:tags":[
        "accountant"
    ],
    "wof:name":"Manka H",
    "wof:placetype":"venue"
},
  "geometry": {"coordinates":[5.2868990898,50.5779151917],"type":"Point"}
}