{
  "type": "Feature",
  "properties": {
    "iso:country":"BE",
    "sg:address":"Swertmolenstraat 31",
    "sg:city":"Herent",
    "sg:classifiers":[
        {
            "category":"Real Estate",
            "subcategory":"Architect",
            "type":"Services"
        }
    ],
    "sg:phone":"+32 16 35 66 64",
    "sg:postcode":"3020",
    "sg:province":"Vlaams-Brabant",
    "wof:name":"Hendrickx T",
    "wof:placetype":"venue"
},
  "geometry": {"coordinates":[4.6605191231,50.8951339722],"type":"Point"}
}