{
  "type": "Feature",
  "properties": {
    "addr:full":"Rue De Stassart 47 Bruxelles (ixelles) Bruxelles-Capitale 1050",
    "addr:housenumber":"47",
    "addr:postcode":"1050",
    "addr:street":"Rue De Stassart",
    "iso:country":"BE",
    "sg:address":"Rue De Stassart 47",
    "sg:city":"Bruxelles (ixelles)",
    "sg:classifiers":[
        {
            "category":"Cafe",
            "type":"Food & Drink"
        }
    ],
    "sg:phone":"+32 2 502 71 99",
    "sg:postcode":"1050",
    "sg:province":"Bruxelles-Capitale",
    "sg:tags":[
        "snack-bars"
    ],
    "wof:name":"Loumara",
    "wof:placetype":"venue"
},
  "geometry": {"coordinates":[4.3604240417,50.8364486694],"type":"Point"}
}