{
  "type": "Feature",
  "properties": {
    "addr:full":"Kouterstraat 106 Houthulst (merkem) West-Vlaanderen 8650",
    "addr:housenumber":"106",
    "addr:postcode":"8650",
    "addr:street":"Kouterstraat",
    "iso:country":"BE",
    "sg:address":"Kouterstraat 106",
    "sg:city":"Houthulst (merkem)",
    "sg:classifiers":[
        {
            "category":"Professional",
            "subcategory":"Computer Services",
            "type":"Services"
        }
    ],
    "sg:phone":"+32 51 54 53 62",
    "sg:postcode":"8650",
    "sg:province":"West-Vlaanderen",
    "sg:tags":[
        "-",
        "processing",
        "data",
        "software"
    ],
    "wof:name":"Degrauwe J",
    "wof:placetype":"venue"
},
  "geometry": {"coordinates":[2.8591370583,50.9487876892],"type":"Point"}
}