{
  "type": "Feature",
  "properties": {
    "addr:full":"Kortrijksepoortstr 204 Gent Oost-Vlaanderen 9000",
    "addr:housenumber":"204",
    "addr:postcode":"9000",
    "addr:street":"Oost-Vlaanderen",
    "iso:country":"BE",
    "sg:address":"Kortrijksepoortstr 204",
    "sg:city":"Gent",
    "sg:classifiers":[
        {
            "category":"Personal",
            "subcategory":"Beauty Salon",
            "type":"Services"
        }
    ],
    "sg:phone":"+32 9 225 17 70",
    "sg:postcode":"9000",
    "sg:province":"Oost-Vlaanderen",
    "sg:tags":[
        "de",
        "coiffure"
    ],
    "wof:name":"Zig Zag",
    "wof:placetype":"venue"
},
  "geometry": {"coordinates":[3.7217979431,51.0445976257],"type":"Point"}
}