{
  "type": "Feature",
  "properties": {
    "iso:country":"BE",
    "sg:address":"Avenue Marius Meur\u00c9e 21",
    "sg:city":"Charleroi",
    "sg:orig_category":"Apotheken",
    "sg:phone":"+32 71 36 06 98",
    "sg:postcode":"6001",
    "sg:province":"Hainaut",
    "wof:name":"Anne-marie Frere",
    "wof:placetype":"venue"
},
  "geometry": {"coordinates":[4.4472799301,50.4007835388],"type":"Point"}
}