{
  "type": "Feature",
  "properties": {
    "addr:full":"Rue De La Gendarmerie 43 Nandrin Li\u00e8ge 4550",
    "addr:housenumber":"43",
    "addr:postcode":"4550",
    "addr:street":"Rue De La Gendarmerie",
    "iso:country":"BE",
    "sg:address":"Rue De La Gendarmerie 43",
    "sg:city":"Nandrin",
    "sg:orig_category":"Babyspullen",
    "sg:phone":"+32 85 51 26 67",
    "sg:postcode":"4550",
    "sg:province":"Li\u00e8ge",
    "wof:name":"Michel Keysers",
    "wof:placetype":"venue"
},
  "geometry": {"coordinates":[5.4103322029,50.5062179565],"type":"Point"}
}