{
  "type": "Feature",
  "properties": {
    "iso:country":"BE",
    "sg:address":"Ebdries 38",
    "sg:city":"Aarschot (rillaar)",
    "sg:classifiers":[
        {
            "category":"Professional",
            "subcategory":"Detective & Security Services",
            "type":"Services"
        }
    ],
    "sg:phone":"+32 16 50 05 84",
    "sg:postcode":"3202",
    "sg:province":"Vlaams-Brabant",
    "sg:tags":[
        "installation",
        "alarm",
        "-",
        "system"
    ],
    "wof:name":"P&s Systems",
    "wof:placetype":"venue"
},
  "geometry": {"coordinates":[4.8971290588,50.9706382751],"type":"Point"}
}