{
  "type": "Feature",
  "properties": {
    "iso:country":"BE",
    "sg:address":"Sint-trudostraat 80",
    "sg:city":"Brugge",
    "sg:orig_category":"Woningbouw",
    "sg:phone":"+32 50 35 10 71",
    "sg:postcode":"8310",
    "sg:province":"West-Vlaanderen",
    "wof:name":"Verrecas & Co",
    "wof:placetype":"venue"
},
  "geometry": {"coordinates":[3.2415509224,51.1856040955],"type":"Point"}
}