{
  "type": "Feature",
  "properties": {
    "addr:full":"Route De La G\u00e9ronst\u00e8re 10 Spa Li\u00e8ge 4900",
    "addr:housenumber":"10",
    "addr:postcode":"4900",
    "addr:street":"Route De La Ge\u0301Ronste\u0300Re",
    "iso:country":"BE",
    "sg:address":"Route De La G\u00e9ronst\u00e8re 10",
    "sg:city":"Spa",
    "sg:classifiers":[
        {
            "category":"Museum",
            "type":"Entertainment"
        }
    ],
    "sg:phone":"+32 87 77 14 18",
    "sg:postcode":"4900",
    "sg:province":"Li\u00e8ge",
    "wof:name":"Mus\u00e9e De La Lessive",
    "wof:placetype":"venue"
},
  "geometry": {"coordinates":[5.868434906,50.4885063171],"type":"Point"}
}