{
  "type": "Feature",
  "properties": {
    "addr:full":"Stationsplein 17 Tongeren Limburg 3700",
    "addr:housenumber":"17",
    "addr:postcode":"3700",
    "addr:street":"Stationsplein",
    "iso:country":"BE",
    "sg:address":"Stationsplein 17",
    "sg:city":"Tongeren",
    "sg:orig_category":"Randstad",
    "sg:phone":"+32 12 39 52 60",
    "sg:postcode":"3700",
    "sg:province":"Limburg",
    "wof:name":"Randstad",
    "wof:placetype":"venue"
},
  "geometry": {"coordinates":[5.4715337753,50.7833175659],"type":"Point"}
}