{
  "type": "Feature",
  "properties": {
    "addr:full":"Baljuwstraat 2b7 Beveren Oost-Vlaanderen 9120",
    "addr:housenumber":"2b7",
    "addr:postcode":"9120",
    "addr:street":"Baljuwstraat",
    "iso:country":"BE",
    "sg:address":"Baljuwstraat 2b7",
    "sg:city":"Beveren",
    "sg:classifiers":[
        {
            "category":"Recreation",
            "type":"Entertainment"
        }
    ],
    "sg:phone":"+32 3 775 63 58",
    "sg:postcode":"9120",
    "sg:province":"Oost-Vlaanderen",
    "sg:tags":[
        "diver",
        "amusement"
    ],
    "wof:name":"Ben Janssens",
    "wof:placetype":"venue"
},
  "geometry": {"coordinates":[4.2608118057,51.2099266052],"type":"Point"}
}