{
  "type": "Feature",
  "properties": {
    "addr:full":"Schoonmansveld 40 Puurs Antwerpen 2870",
    "addr:housenumber":"40",
    "addr:postcode":"2870",
    "addr:street":"Schoonmansveld",
    "iso:country":"BE",
    "sg:address":"Schoonmansveld 40",
    "sg:city":"Puurs",
    "sg:orig_category":"Goederenvervoer over de weg",
    "sg:phone":"+32 3 890 73 00",
    "sg:postcode":"2870",
    "sg:province":"Antwerpen",
    "wof:name":"Maas Frans",
    "wof:placetype":"venue"
},
  "geometry": {"coordinates":[4.3304290771,51.0647239685],"type":"Point"}
}