{
  "type": "Feature",
  "properties": {
    "iso:country":"BE",
    "sg:address":"Grand'route 434",
    "sg:city":"Braine L'alleud (lillois-witterz\u00e9e)",
    "sg:classifiers":[
        {
            "category":"Health Services",
            "subcategory":"Health Practitioner",
            "type":"Services"
        }
    ],
    "sg:phone":"+32 2 384 28 80",
    "sg:postcode":"1428",
    "sg:province":"Brabant Wallon",
    "sg:tags":[
        "physiotherapist"
    ],
    "wof:name":"Hubert D",
    "wof:placetype":"venue"
},
  "geometry": {"coordinates":[-0.6584389806,47.4034957886],"type":"Point"}
}