{
  "type": "Feature",
  "properties": {
    "addr:full":"Ruisbroeksesteenweg 214a Sint-pieters-leeuw (ruisbroek) Vlaams-Brabant 1601",
    "addr:housenumber":"214a",
    "addr:postcode":"1601",
    "addr:street":"Ruisbroeksesteenweg",
    "iso:country":"BE",
    "sg:address":"Ruisbroeksesteenweg 214a",
    "sg:city":"Sint-pieters-leeuw (ruisbroek)",
    "sg:classifiers":[
        {
            "category":"Social Services",
            "subcategory":"Job Training",
            "type":"Services"
        }
    ],
    "sg:phone":"+32 2 378 20 38",
    "sg:postcode":"1601",
    "sg:province":"Vlaams-Brabant",
    "sg:tags":[
        "condiment",
        "spice"
    ],
    "wof:name":"Miaguy Spices",
    "wof:placetype":"venue"
},
  "geometry": {"coordinates":[4.2914228439,50.7898101807],"type":"Point"}
}