{
  "type": "Feature",
  "properties": {
    "iso:country":"BE",
    "sg:address":"Lippeloseweg 70",
    "sg:city":"Sint-amands",
    "sg:orig_category":"Producteurs de l\u00e9gumes",
    "sg:phone":"+32 3 889 26 78",
    "sg:postcode":"2890",
    "sg:province":"Antwerpen",
    "wof:name":"Van Assche Fr. & M.",
    "wof:placetype":"venue"
},
  "geometry": {"coordinates":[4.24746418,51.0572052002],"type":"Point"}
}