{
  "type": "Feature",
  "properties": {
    "iso:country":"BE",
    "sg:address":"Rue Emile Delper\u00e9e 13",
    "sg:city":"Huy",
    "sg:classifiers":[
        {
            "category":"Manufacturing",
            "subcategory":"Paper Products",
            "type":"Manufacturing & Wholesale Goods"
        }
    ],
    "sg:phone":"+32 85 21 53 76",
    "sg:postcode":"4500",
    "sg:province":"Li\u00e8ge",
    "sg:tags":[
        "bookbinding"
    ],
    "wof:name":"Lahaut H",
    "wof:placetype":"venue"
},
  "geometry": {"coordinates":[5.2460451126,50.5259666443],"type":"Point"}
}