{
  "type": "Feature",
  "properties": {
    "addr:full":"Begoniastraat 19 Sint-pieters-leeuw Vlaams-Brabant 1600",
    "addr:housenumber":"19",
    "addr:postcode":"1600",
    "addr:street":"Begoniastraat",
    "iso:country":"BE",
    "sg:address":"Begoniastraat 19",
    "sg:city":"Sint-pieters-leeuw",
    "sg:orig_category":"Artiesten and kunstenaars",
    "sg:phone":"+32 2 377 15 13",
    "sg:postcode":"1600",
    "sg:province":"Vlaams-Brabant",
    "wof:name":"Huybrechts",
    "wof:placetype":"venue"
},
  "geometry": {"coordinates":[4.2774419785,50.8056640625],"type":"Point"}
}