{
  "type": "Feature",
  "properties": {
    "addr:full":"L. Bauwensstraat 19b Brugge West-Vlaanderen 8200",
    "addr:housenumber":"19b",
    "addr:postcode":"8200",
    "addr:street":"L. Bauwensstraat",
    "iso:country":"BE",
    "sg:address":"L. Bauwensstraat 19b",
    "sg:city":"Brugge",
    "sg:orig_category":"Plantes and fleurs Fleurs and plantes",
    "sg:phone":"+32 50 31 56 10",
    "sg:postcode":"8200",
    "sg:province":"West-Vlaanderen",
    "wof:name":"Vanderhaeghe",
    "wof:placetype":"venue"
},
  "geometry": {"coordinates":[3.1934869289,51.2133827209],"type":"Point"}
}