{
  "type": "Feature",
  "properties": {
    "addr:full":"Noordstraat 91 Roeselare West-Vlaanderen 8800",
    "addr:housenumber":"91",
    "addr:postcode":"8800",
    "addr:street":"Noordstraat",
    "iso:country":"BE",
    "sg:address":"Noordstraat 91",
    "sg:city":"Roeselare",
    "sg:classifiers":[
        {
            "category":"Restaurant",
            "type":"Food & Drink"
        }
    ],
    "sg:phone":"+32 51 20 54 86",
    "sg:postcode":"8800",
    "sg:province":"West-Vlaanderen",
    "wof:name":"De Ooievaar",
    "wof:placetype":"venue"
},
  "geometry": {"coordinates":[3.1216700077,50.9476165771],"type":"Point"}
}