{
  "type": "Feature",
  "properties": {
    "addr:full":"Luikersteenweg Z/n Lommel Limburg 3920",
    "addr:housenumber":"z / n",
    "addr:postcode":"3920",
    "addr:street":"Luikersteenweg",
    "iso:country":"BE",
    "sg:address":"Luikersteenweg Z/n",
    "sg:city":"Lommel",
    "sg:orig_category":"Sportterreinen and installaties behalve sportcentra",
    "sg:phone":"+32 11 66 24 14",
    "sg:postcode":"3920",
    "sg:province":"Limburg",
    "wof:name":"Stedelijk Motorcrosscentrum Lommel",
    "wof:placetype":"venue"
},
  "geometry": {"coordinates":[5.3089981079,51.2305793762],"type":"Point"}
}