{
  "type": "Feature",
  "properties": {
    "iso:country":"BE",
    "sg:address":"Jan Van Rijswijcklaan 184",
    "sg:city":"Antwerpen",
    "sg:orig_category":"Banken and kredietinstellingen Verbruikerskredietinstellingen",
    "sg:phone":"+32 3 244 55 66",
    "sg:postcode":"2020",
    "sg:province":"Antwerpen",
    "wof:name":"Bank Delen",
    "wof:placetype":"venue"
},
  "geometry": {"coordinates":[4.3955302238,51.189655304],"type":"Point"}
}