{
  "type": "Feature",
  "properties": {
    "addr:full":"Weidestraat 113 Roeselare West-Vlaanderen 8800",
    "addr:housenumber":"113",
    "addr:postcode":"8800",
    "addr:street":"Weidestraat",
    "iso:country":"BE",
    "sg:address":"Weidestraat 113",
    "sg:city":"Roeselare",
    "sg:orig_category":"Instituts de beaut\u00e9",
    "sg:phone":"+32 51 24 27 65",
    "sg:postcode":"8800",
    "sg:province":"West-Vlaanderen",
    "wof:name":"Christine Vandewiele",
    "wof:placetype":"venue"
},
  "geometry": {"coordinates":[3.1042649746,50.9658584595],"type":"Point"}
}