{
  "type": "Feature",
  "properties": {
    "iso:country":"BE",
    "sg:address":"Avenue Du Souverain 7",
    "sg:city":"Watermael-boitsfort (bruxelles)",
    "sg:orig_category":"Assistances juridiques",
    "sg:phone":"+32 2 675 57 07",
    "sg:postcode":"1170",
    "sg:province":"Bruxelles-Capitale",
    "wof:name":"Novamark & Vigneron",
    "wof:placetype":"venue"
},
  "geometry": {"coordinates":[4.4206209183,50.7985534668],"type":"Point"}
}