{
  "type": "Feature",
  "properties": {
    "iso:country":"BE",
    "sg:address":"Kardinaal Cardijnstraat 8",
    "sg:city":"Brugge (sint-andries)",
    "sg:classifiers":[
        {
            "category":"Food & Beverages",
            "subcategory":"Groceries & Convenience Stores",
            "type":"Retail Goods"
        }
    ],
    "sg:phone":"+32 50 38 76 56",
    "sg:postcode":"8200",
    "sg:province":"West-Vlaanderen",
    "sg:tags":[
        "grocer"
    ],
    "wof:name":"Demaecker R",
    "wof:placetype":"venue"
},
  "geometry": {"coordinates":[3.2043979168,51.2016067505],"type":"Point"}
}