{
  "type": "Feature",
  "properties": {
    "iso:country":"BE",
    "sg:address":"Poekestraat 35",
    "sg:city":"Nevele",
    "sg:orig_category":"Varkenskwekers",
    "sg:phone":"+32 9 371 95 31",
    "sg:postcode":"9850",
    "sg:province":"Oost-Vlaanderen",
    "wof:name":"Jos Taveirne",
    "wof:placetype":"venue"
},
  "geometry": {"coordinates":[3.5127398968,51.038143158],"type":"Point"}
}