{
  "type": "Feature",
  "properties": {
    "iso:country":"BE",
    "sg:address":"Rue Charles Jaumotte 36",
    "sg:city":"Wavre",
    "sg:orig_category":"Brood, gebak and snoepgoed",
    "sg:phone":"+32 10 41 01 91",
    "sg:postcode":"1300",
    "sg:province":"Brabant Wallon",
    "wof:name":"Boulangerie Mohimont",
    "wof:placetype":"venue"
},
  "geometry": {"coordinates":[4.5756402016,50.694934845],"type":"Point"}
}