{
  "type": "Feature",
  "properties": {
    "iso:country":"BE",
    "sg:address":"Waversesteenweg 102",
    "sg:city":"Bierbeek (honsem)",
    "sg:classifiers":[
        {
            "category":"Bars & Pubs",
            "type":"Food & Drink"
        }
    ],
    "sg:phone":"+32 16 73 51 06",
    "sg:postcode":"3360",
    "sg:province":"Vlaams-Brabant",
    "wof:name":"Wimbledon",
    "wof:placetype":"venue"
},
  "geometry": {"coordinates":[4.7913751602,50.8122062683],"type":"Point"}
}