{
  "type": "Feature",
  "properties": {
    "iso:country":"BE",
    "sg:address":"Verenigde Natieslaan 10",
    "sg:city":"Oostende",
    "sg:classifiers":[
        {
            "category":"Real Estate",
            "subcategory":"Developer",
            "type":"Services"
        }
    ],
    "sg:phone":"+32 59 70 92 33",
    "sg:postcode":"8400",
    "sg:province":"West-Vlaanderen",
    "sg:tags":[
        "project"
    ],
    "wof:name":"Heughebaert H",
    "wof:placetype":"venue"
},
  "geometry": {"coordinates":[2.918708086,51.2236289978],"type":"Point"}
}