{
  "type": "Feature",
  "properties": {
    "iso:country":"BE",
    "sg:address":"Rue Bosquet 15",
    "sg:city":"Jodoigne",
    "sg:orig_category":"Notaires",
    "sg:phone":"+32 10 81 35 02",
    "sg:postcode":"1370",
    "sg:province":"Brabant Wallon",
    "wof:name":"P. Stoefs",
    "wof:placetype":"venue"
},
  "geometry": {"coordinates":[4.8713579178,50.7240715027],"type":"Point"}
}