{
  "type": "Feature",
  "properties": {
    "addr:full":"Dr. Roosensplein 43b1 Brasschaat Antwerpen 2930",
    "addr:postcode":"2930",
    "iso:country":"BE",
    "sg:address":"Dr. Roosensplein 43b1",
    "sg:city":"Brasschaat",
    "sg:classifiers":[
        {
            "category":"Shopping",
            "subcategory":"Clothing, Apparel, & Fashions",
            "type":"Retail Goods"
        }
    ],
    "sg:phone":"+32 3 651 86 17",
    "sg:postcode":"2930",
    "sg:province":"Antwerpen",
    "sg:tags":[
        "lingerie",
        "sous-v\u00eatements"
    ],
    "wof:name":"Huis Caress",
    "wof:placetype":"venue"
},
  "geometry": {"coordinates":[4.4858131409,51.2874641418],"type":"Point"}
}