{
  "type": "Feature",
  "properties": {
    "iso:country":"BE",
    "sg:address":"Denen 36",
    "sg:city":"Lochristi",
    "sg:classifiers":[
        {
            "category":"Autos & Motor Vehicles",
            "subcategory":"Automobile Sales",
            "type":"Retail Goods"
        }
    ],
    "sg:phone":"+32 9 356 66 30",
    "sg:postcode":"9080",
    "sg:province":"Oost-Vlaanderen",
    "sg:tags":[
        "car",
        "used",
        "-"
    ],
    "wof:name":"Budgetcars",
    "wof:placetype":"venue"
},
  "geometry": {"coordinates":[3.8549320698,51.1015663147],"type":"Point"}
}