{
  "type": "Feature",
  "properties": {
    "iso:country":"BE",
    "sg:address":"Rue Stampia 1",
    "sg:city":"Mettet (saint-g\u00e9rard)",
    "sg:classifiers":[
        {
            "category":"Bars & Pubs",
            "type":"Food & Drink"
        }
    ],
    "sg:phone":"+32 71 79 91 20",
    "sg:postcode":"5640",
    "sg:province":"Namur",
    "wof:name":"Melin",
    "wof:placetype":"venue"
},
  "geometry": {"coordinates":[4.7391610146,50.3461303711],"type":"Point"}
}