{
  "type": "Feature",
  "properties": {
    "iso:country":"BE",
    "sg:address":"Rue Alo\u00efs Den Reep 96",
    "sg:city":"Mouscron",
    "sg:classifiers":[
        {
            "category":"Cafe",
            "type":"Food & Drink"
        }
    ],
    "sg:phone":"+32 56 84 67 70",
    "sg:postcode":"7700",
    "sg:province":"Hainaut",
    "sg:tags":[
        "snack-bars"
    ],
    "wof:name":"Dog Sandwich",
    "wof:placetype":"venue"
},
  "geometry": {"coordinates":[3.2194979191,50.7393798828],"type":"Point"}
}