{
  "type": "Feature",
  "properties": {
    "iso:country":"BE",
    "sg:address":"Kronevoordestraat 36",
    "sg:city":"Kortemark",
    "sg:orig_category":"Electrom\u00e9nager, t\u00e9l\u00e9visions and radios. Installation \u00e9lectrique industrielle. Installation \u00e9lectriqu",
    "sg:phone":"+32 51 56 91 63",
    "sg:postcode":"8610",
    "sg:province":"West-Vlaanderen",
    "wof:name":"Soenen Electro",
    "wof:placetype":"venue"
},
  "geometry": {"coordinates":[3.0028579235,51.0231513977],"type":"Point"}
}