{
  "type": "Feature",
  "properties": {
    "addr:full":"Bulscampveld 8 Beernem West-Vlaanderen 8730",
    "addr:housenumber":"8",
    "addr:postcode":"8730",
    "addr:street":"Bulscampveld",
    "iso:country":"BE",
    "sg:address":"Bulscampveld 8",
    "sg:city":"Beernem",
    "sg:classifiers":[
        {
            "category":"Social Services",
            "subcategory":"Retirement Home",
            "type":"Services"
        }
    ],
    "sg:phone":"+32 50 79 09 59",
    "sg:postcode":"8730",
    "sg:province":"West-Vlaanderen",
    "sg:tags":[
        "society",
        "protection",
        "animal"
    ],
    "wof:name":"Koninklijk Belgisch Verbond Voor Bescherming Van Vogels",
    "wof:placetype":"venue"
},
  "geometry": {"coordinates":[3.2893099785,51.1225700378],"type":"Point"}
}