{
  "type": "Feature",
  "properties": {
    "addr:full":"Rue Emile Claus 28 Bruxelles Bruxelles-Capitale 1050",
    "addr:housenumber":"28",
    "addr:postcode":"1050",
    "addr:street":"Rue Emile Claus",
    "iso:country":"BE",
    "sg:address":"Rue Emile Claus 28",
    "sg:city":"Bruxelles",
    "sg:classifiers":[
        {
            "category":"Professional",
            "subcategory":"Business Services",
            "type":"Services"
        }
    ],
    "sg:phone":"+32 2 643 38 50",
    "sg:postcode":"1050",
    "sg:province":"Bruxelles-Capitale",
    "sg:tags":[
        "body",
        "advice"
    ],
    "wof:name":"Ambassade D'italie",
    "wof:placetype":"venue"
},
  "geometry": {"coordinates":[4.3694877625,50.815952301],"type":"Point"}
}