{
  "type": "Feature",
  "properties": {
    "iso:country":"BE",
    "sg:address":"Rue De La Cath\u00e9drale 70",
    "sg:city":"Li\u00e8ge 1",
    "sg:classifiers":[
        {
            "category":"Professional",
            "subcategory":"Art Services",
            "type":"Services"
        }
    ],
    "sg:phone":"+32 4 223 41 17",
    "sg:postcode":"4000",
    "sg:province":"Li\u00e8ge",
    "sg:tags":[
        "picture",
        "framer"
    ],
    "wof:name":"Art-service Sa",
    "wof:placetype":"venue"
},
  "geometry": {"coordinates":[5.5740208626,50.6423606873],"type":"Point"}
}