{
  "type": "Feature",
  "properties": {
    "addr:full":"Chauss\u00c9e D\u00b4alsemberg 1012 Ukkel/uccle Bruxelles-Capitale 1180",
    "addr:postcode":"1012;1180",
    "addr:street":"Chausse\u0301E D\u00b4Alsemberg",
    "iso:country":"BE",
    "sg:address":"Chauss\u00c9e D\u00b4alsemberg 1012",
    "sg:city":"Ukkel/uccle",
    "sg:orig_category":"V\u00eatements pour b\u00e9b\u00e9s and enfants",
    "sg:phone":"+32 2 332 01 35",
    "sg:postcode":"1180",
    "sg:province":"Bruxelles-Capitale",
    "wof:name":"Les Caprices D\u00b4ambre",
    "wof:placetype":"venue"
},
  "geometry": {"coordinates":[4.3322920799,50.7910079956],"type":"Point"}
}