{
  "type": "Feature",
  "properties": {
    "iso:country":"BE",
    "sg:address":"Rue Des Praules 13",
    "sg:city":"Gembloux-sur-orneau (gembloux)",
    "sg:classifiers":[
        {
            "category":"Farming",
            "subcategory":"Fish & Marine Products",
            "type":"Manufacturing & Wholesale Goods"
        }
    ],
    "sg:phone":"+32 81 60 13 41",
    "sg:postcode":"5030",
    "sg:province":"Namur",
    "sg:tags":[
        "retail",
        "-",
        "shellfish"
    ],
    "wof:name":"Saumon Jean Victor",
    "wof:placetype":"venue"
},
  "geometry": {"coordinates":[4.7102761269,50.5763664246],"type":"Point"}
}