{
  "type": "Feature",
  "properties": {
    "addr:full":"Rue D'aubel 71 Herve (battice) Li\u00e8ge 4651",
    "addr:housenumber":"71",
    "addr:postcode":"4651",
    "addr:street":"Rue D'Aubel",
    "iso:country":"BE",
    "sg:address":"Rue D'aubel 71",
    "sg:city":"Herve (battice)",
    "sg:classifiers":[
        {
            "category":"Manufacturing",
            "subcategory":"Furniture",
            "type":"Manufacturing & Wholesale Goods"
        }
    ],
    "sg:phone":"+32 87 44 60 13",
    "sg:postcode":"4651",
    "sg:province":"Li\u00e8ge",
    "sg:tags":[
        "made",
        "-",
        "custom"
    ],
    "wof:name":"Lejeune D",
    "wof:placetype":"venue"
},
  "geometry": {"coordinates":[5.8286237717,50.6485099792],"type":"Point"}
}