{
  "type": "Feature",
  "properties": {
    "iso:country":"BE",
    "sg:address":"Wouterbos 13",
    "sg:city":"Linkebeek",
    "sg:classifiers":[
        {
            "category":"Government",
            "subcategory":"Office",
            "type":"Public Place"
        }
    ],
    "sg:phone":"+32 2 380 65 97",
    "sg:postcode":"1630",
    "sg:province":"Vlaams-Brabant",
    "sg:tags":[
        "-",
        "tourism",
        "federation"
    ],
    "wof:name":"Art Du Voyage (l')",
    "wof:placetype":"venue"
},
  "geometry": {"coordinates":[4.3439640999,50.7659378052],"type":"Point"}
}