{
  "type": "Feature",
  "properties": {
    "iso:country":"BE",
    "sg:address":"1 Akkerhage",
    "sg:city":"Gent",
    "sg:classifiers":[
        {
            "category":"Travel",
            "subcategory":"Hotels & Motels",
            "type":"Entertainment"
        }
    ],
    "sg:phone":"+32 9 220 02 22",
    "sg:postcode":"9000",
    "sg:province":"Oost-Vlaanderen",
    "sg:tags":[
        "professional",
        "hotels",
        "fair",
        "business",
        "restaurant"
    ],
    "wof:name":"Campagent Nv",
    "wof:placetype":"venue"
},
  "geometry": {"coordinates":[3.734110117,51.0182418823],"type":"Point"}
}