{
  "type": "Feature",
  "properties": {
    "addr:full":"Quai Des Vennes1/ 45-46 Li\u00c8ge Li\u00e8ge 4020",
    "addr:housenumber":"45-46",
    "addr:postcode":"4020",
    "addr:street":"Quai Des Vennes1",
    "iso:country":"BE",
    "sg:address":"Quai Des Vennes1/ 45-46",
    "sg:city":"Li\u00c8ge",
    "sg:orig_category":"Chaussures",
    "sg:phone":"+32 4 349 00 13",
    "sg:postcode":"4020",
    "sg:province":"Li\u00e8ge",
    "wof:name":"Maison Collard Ren\u00c9",
    "wof:placetype":"venue"
},
  "geometry": {"coordinates":[5.6346750259,50.6462516785],"type":"Point"}
}