{
  "type": "Feature",
  "properties": {
    "addr:full":"Kempervendreef 4 Keerbergen Vlaams-Brabant 3140",
    "addr:housenumber":"4",
    "addr:postcode":"3140",
    "addr:street":"Kempervendreef",
    "iso:country":"BE",
    "sg:address":"Kempervendreef 4",
    "sg:city":"Keerbergen",
    "sg:classifiers":[
        {
            "category":"Health Services",
            "subcategory":"Dentist",
            "type":"Services"
        }
    ],
    "sg:phone":"+32 15 52 99 53",
    "sg:postcode":"3140",
    "sg:province":"Vlaams-Brabant",
    "wof:name":"Pieraerts Ilse",
    "wof:placetype":"venue"
},
  "geometry": {"coordinates":[4.6494278908,50.993434906],"type":"Point"}
}