{
  "type": "Feature",
  "properties": {
    "addr:full":"Guido Gezellelaan 53 Kortrijk (heule) West-Vlaanderen 8501",
    "addr:housenumber":"53",
    "addr:postcode":"8501",
    "addr:street":"Guido Gezellelaan",
    "iso:country":"BE",
    "sg:address":"Guido Gezellelaan 53",
    "sg:city":"Kortrijk (heule)",
    "sg:classifiers":[
        {
            "category":"Shopping",
            "subcategory":"Shoes",
            "type":"Retail Goods"
        }
    ],
    "sg:phone":"+32 56 37 00 38",
    "sg:postcode":"8501",
    "sg:province":"West-Vlaanderen",
    "sg:tags":[
        "slipper",
        "-"
    ],
    "wof:name":"Fabies",
    "wof:placetype":"venue"
},
  "geometry": {"coordinates":[3.2387208939,50.8336410522],"type":"Point"}
}