{
  "type": "Feature",
  "properties": {
    "addr:full":"Karel Lodewijk Maenhoutstraat 60 Sint-martens-latem Oost-Vlaanderen 9830",
    "addr:housenumber":"60",
    "addr:postcode":"9830",
    "addr:street":"Karel Lodewijk Maenhoutstraat",
    "iso:country":"BE",
    "sg:address":"Karel Lodewijk Maenhoutstraat 60",
    "sg:city":"Sint-martens-latem",
    "sg:classifiers":[
        {
            "category":"Retail",
            "subcategory":"Event Space",
            "type":"Services"
        }
    ],
    "sg:phone":"+32 9 282 35 68",
    "sg:postcode":"9830",
    "sg:province":"Oost-Vlaanderen",
    "sg:tags":[
        "rental",
        "-",
        "hall"
    ],
    "wof:name":"Leiesymfonie",
    "wof:placetype":"venue"
},
  "geometry": {"coordinates":[3.6447598934,51.0140037537],"type":"Point"}
}