{
  "type": "Feature",
  "properties": {
    "addr:full":"Rue Malev\u00c9 26 Andenne Namur 5300",
    "addr:housenumber":"26",
    "addr:postcode":"5300",
    "addr:street":"Rue Maleve\u0301",
    "iso:country":"BE",
    "sg:address":"Rue Malev\u00c9 26",
    "sg:city":"Andenne",
    "sg:orig_category":"Avocats and conseillers juridiques",
    "sg:phone":"+32 85 84 61 66",
    "sg:postcode":"5300",
    "sg:province":"Namur",
    "wof:name":"J.b. Kefer",
    "wof:placetype":"venue"
},
  "geometry": {"coordinates":[5.0938940048,50.4926261902],"type":"Point"}
}