{
  "type": "Feature",
  "properties": {
    "iso:country":"BE",
    "sg:address":"Binnensteenweg 202",
    "sg:city":"Boechout",
    "sg:classifiers":[
        {
            "category":"Professional",
            "subcategory":"Lawyer & Legal Services",
            "type":"Services"
        }
    ],
    "sg:phone":"+32 3 454 30 37",
    "sg:postcode":"2530",
    "sg:province":"Antwerpen",
    "wof:name":"Dreessen Werner",
    "wof:placetype":"venue"
},
  "geometry": {"coordinates":[4.4929728508,51.1664237976],"type":"Point"}
}