{
  "type": "Feature",
  "properties": {
    "iso:country":"BE",
    "sg:address":"Hoevensebaan 33",
    "sg:city":"Kapellen",
    "sg:classifiers":[
        {
            "category":"Home & Garden",
            "subcategory":"Carpets & Floor Coverings",
            "type":"Retail Goods"
        }
    ],
    "sg:phone":"+32 3 605 17 07",
    "sg:postcode":"2950",
    "sg:province":"Antwerpen",
    "sg:tags":[
        "tile"
    ],
    "wof:name":"Van Den Bleeken A Bvba",
    "wof:placetype":"venue"
},
  "geometry": {"coordinates":[4.4272627831,51.3140068054],"type":"Point"}
}