{
  "type": "Feature",
  "properties": {
    "iso:country":"BE",
    "sg:address":"Prins Albertlaan 86",
    "sg:city":"Izegem",
    "sg:orig_category":"Herstellingen and onderhoud van auto's",
    "sg:phone":"+32 51 30 55 94",
    "sg:postcode":"8870",
    "sg:province":"West-Vlaanderen",
    "wof:name":"Carrosserie Mouton",
    "wof:placetype":"venue"
},
  "geometry": {"coordinates":[3.1909759045,50.9266319275],"type":"Point"}
}