{
  "type": "Feature",
  "properties": {
    "addr:full":"Rue De Tenbosch 88 Bruxelles (ixelles) Bruxelles-Capitale 1050",
    "addr:housenumber":"88",
    "addr:postcode":"1050",
    "addr:street":"Rue De Tenbosch",
    "iso:country":"BE",
    "sg:address":"Rue De Tenbosch 88",
    "sg:city":"Bruxelles (ixelles)",
    "sg:classifiers":[
        {
            "category":"Home & Garden",
            "subcategory":"Carpets & Floor Coverings",
            "type":"Retail Goods"
        }
    ],
    "sg:phone":"+32 2 344 90 68",
    "sg:postcode":"1050",
    "sg:province":"Bruxelles-Capitale",
    "sg:tags":[
        "tile"
    ],
    "wof:name":"Moma Sprl",
    "wof:placetype":"venue"
},
  "geometry": {"coordinates":[4.3620910645,50.8213195801],"type":"Point"}
}