{
  "type": "Feature",
  "properties": {
    "iso:country":"BE",
    "sg:address":"Avenue Van Volxem 79",
    "sg:city":"Vorst/forest",
    "sg:orig_category":"Grossistes divers. Maroquinerie Fab",
    "sg:phone":"+32 2 345 71 54",
    "sg:postcode":"1190",
    "sg:province":"Bruxelles-Capitale",
    "wof:name":"Mc Distribution",
    "wof:placetype":"venue"
},
  "geometry": {"coordinates":[4.3254699707,50.8160514832],"type":"Point"}
}