{
  "type": "Feature",
  "properties": {
    "iso:country":"BE",
    "sg:address":"Frenet 1128",
    "sg:city":"Bertogne",
    "sg:orig_category":"Rundveehouders",
    "sg:phone":"+32 61 21 20 40",
    "sg:postcode":"6686",
    "sg:province":"Luxembourg",
    "wof:name":"Bastin Henri & Paul",
    "wof:placetype":"venue"
},
  "geometry": {"coordinates":[5.6270928383,50.0501556396],"type":"Point"}
}