{
  "type": "Feature",
  "properties": {
    "addr:full":"Rieu Baron 8 La Louvi\u00e8re (houdeng-goegnies) Hainaut 7110",
    "addr:housenumber":"8",
    "addr:postcode":"7110",
    "addr:street":"Baron",
    "iso:country":"BE",
    "sg:address":"Rieu Baron 8",
    "sg:city":"La Louvi\u00e8re (houdeng-goegnies)",
    "sg:classifiers":[
        {
            "category":"Health Services",
            "subcategory":"Health Practitioner",
            "type":"Services"
        }
    ],
    "sg:phone":"+32 64 37 10 72",
    "sg:postcode":"7110",
    "sg:province":"Hainaut",
    "sg:tags":[
        "physiotherapist"
    ],
    "wof:name":"Foucart Joffrey",
    "wof:placetype":"venue"
},
  "geometry": {"coordinates":[4.157351017,50.4893035889],"type":"Point"}
}