{
  "type": "Feature",
  "properties": {
    "iso:country":"BE",
    "sg:address":"Jean-baptiste Now\u00e9lei 68-70",
    "sg:city":"Vilvoorde",
    "sg:classifiers":[
        {
            "category":"Personal",
            "subcategory":"Beauty Salon",
            "type":"Services"
        }
    ],
    "sg:phone":"+32 2 251 55 03",
    "sg:postcode":"1800",
    "sg:province":"Vlaams-Brabant",
    "wof:name":"Maya",
    "wof:placetype":"venue"
},
  "geometry": {"coordinates":[4.4274568558,50.9298553467],"type":"Point"}
}