{
  "type": "Feature",
  "properties": {
    "addr:full":"Brusselsestraat 148 Leuven Vlaams-Brabant 3000",
    "addr:housenumber":"148",
    "addr:postcode":"3000",
    "addr:street":"Brusselsestraat",
    "iso:country":"BE",
    "sg:address":"Brusselsestraat 148",
    "sg:city":"Leuven",
    "sg:classifiers":[
        {
            "category":"Retail",
            "subcategory":"Repair Shop",
            "type":"Services"
        }
    ],
    "sg:phone":"+32 16 22 69 46",
    "sg:postcode":"3000",
    "sg:province":"Vlaams-Brabant",
    "sg:tags":[
        "-",
        "clothing",
        "alteration"
    ],
    "wof:name":"Bobijntje (het)",
    "wof:placetype":"venue"
},
  "geometry": {"coordinates":[4.6930060387,50.8807601929],"type":"Point"}
}