{
  "type": "Feature",
  "properties": {
    "iso:country":"BE",
    "sg:address":"Rue D'anseroeul 6a",
    "sg:city":"Rumes",
    "sg:classifiers":[
        {
            "category":"Home & Garden",
            "subcategory":"Building Materials",
            "type":"Retail Goods"
        }
    ],
    "sg:phone":"+32 69 64 71 41",
    "sg:postcode":"7610",
    "sg:province":"Hainaut",
    "sg:tags":[
        "article",
        "-",
        "do-it-yourself"
    ],
    "wof:name":"Deneubourg D",
    "wof:placetype":"venue"
},
  "geometry": {"coordinates":[3.3051950932,50.5567436218],"type":"Point"}
}