{
  "type": "Feature",
  "properties": {
    "addr:full":"Diksmuidsesteenweg 20 Roeselare West-Vlaanderen 8800",
    "addr:housenumber":"20",
    "addr:postcode":"8800",
    "addr:street":"Diksmuidsesteenweg",
    "iso:country":"BE",
    "sg:address":"Diksmuidsesteenweg 20",
    "sg:city":"Roeselare",
    "sg:orig_category":"Kapsalons",
    "sg:phone":"+32 51 24 94 95",
    "sg:postcode":"8800",
    "sg:province":"West-Vlaanderen",
    "wof:name":"Coiffure Sagi",
    "wof:placetype":"venue"
},
  "geometry": {"coordinates":[3.1188099384,50.9455757141],"type":"Point"}
}