{
  "type": "Feature",
  "properties": {
    "addr:full":"Rue De Joie 116a Li\u00e8ge 1 Li\u00e8ge 4000",
    "addr:housenumber":"116a;1",
    "addr:postcode":"4000",
    "addr:street":"Rue De Joie",
    "iso:country":"BE",
    "sg:address":"Rue De Joie 116a",
    "sg:city":"Li\u00e8ge 1",
    "sg:classifiers":[
        {
            "category":"Professional",
            "subcategory":"Advertising",
            "type":"Services"
        }
    ],
    "sg:phone":"+32 4 254 03 19",
    "sg:postcode":"4000",
    "sg:province":"Li\u00e8ge",
    "sg:tags":[
        "photography"
    ],
    "wof:name":"Adequa",
    "wof:placetype":"venue"
},
  "geometry": {"coordinates":[5.5575881004,50.6281089783],"type":"Point"}
}