{
  "type": "Feature",
  "properties": {
    "addr:full":"Peutersweg 7 Sint-katelijne-waver Antwerpen 2860",
    "addr:housenumber":"7",
    "addr:postcode":"2860",
    "addr:street":"Peutersweg",
    "iso:country":"BE",
    "sg:address":"Peutersweg 7",
    "sg:city":"Sint-katelijne-waver",
    "sg:orig_category":"Groententeelt",
    "sg:phone":"+32 15 55 25 12",
    "sg:postcode":"2860",
    "sg:province":"Antwerpen",
    "wof:name":"Juul Serneels",
    "wof:placetype":"venue"
},
  "geometry": {"coordinates":[4.5185990334,51.0534591675],"type":"Point"}
}