{
  "type": "Feature",
  "properties": {
    "addr:full":"Dionysius Van Leeuwenstraat 12 Borgloon (rijkel) Limburg 3840",
    "addr:housenumber":"12",
    "addr:postcode":"3840",
    "addr:street":"Dionysius Van Leeuwenstraat",
    "iso:country":"BE",
    "sg:address":"Dionysius Van Leeuwenstraat 12",
    "sg:city":"Borgloon (rijkel)",
    "sg:classifiers":[
        {
            "category":"Professional",
            "subcategory":"Accounting & Tax Preparation",
            "type":"Services"
        }
    ],
    "sg:phone":"+32 11 68 38 71",
    "sg:postcode":"3840",
    "sg:province":"Limburg",
    "sg:tags":[
        "bookkeeper"
    ],
    "wof:name":"Wouters Bvba",
    "wof:placetype":"venue"
},
  "geometry": {"coordinates":[5.2602591515,50.8060302734],"type":"Point"}
}