{
  "type": "Feature",
  "properties": {
    "iso:country":"BE",
    "sg:address":"Koninginnelaan 144",
    "sg:city":"Schaarbeek/schaerbeek",
    "sg:orig_category":"Diverse zakelijke dienstverlening",
    "sg:phone":"+32 2 201 14 95",
    "sg:postcode":"1030",
    "sg:province":"Bruxelles-Capitale",
    "wof:name":"Festival Film Fantastique",
    "wof:placetype":"venue"
},
  "geometry": {"coordinates":[4.3683800697,50.8585014343],"type":"Point"}
}