{
  "type": "Feature",
  "properties": {
    "addr:full":"Vismarkt 20 Mechelen Antwerpen 2800",
    "addr:housenumber":"20",
    "addr:postcode":"2800",
    "addr:street":"Vismarkt",
    "iso:country":"BE",
    "sg:address":"Vismarkt 20",
    "sg:city":"Mechelen",
    "sg:classifiers":[
        {
            "category":"Cafe",
            "type":"Food & Drink"
        }
    ],
    "sg:phone":"+32 15 21 29 20",
    "sg:postcode":"2800",
    "sg:province":"Antwerpen",
    "sg:tags":[
        "caf\u00e9s"
    ],
    "wof:name":"'t Verschil",
    "wof:placetype":"venue"
},
  "geometry": {"coordinates":[4.47645998,51.0266685486],"type":"Point"}
}