{
  "type": "Feature",
  "properties": {
    "addr:full":"Hogeschuurstraat 61 Menen West-Vlaanderen 8930",
    "addr:housenumber":"61",
    "addr:postcode":"8930",
    "addr:street":"Hogeschuurstraat",
    "iso:country":"BE",
    "sg:address":"Hogeschuurstraat 61",
    "sg:city":"Menen",
    "sg:orig_category":"Sportclubs",
    "sg:phone":"+32 56 40 09 08",
    "sg:postcode":"8930",
    "sg:province":"West-Vlaanderen",
    "wof:name":"Elk Zijn Recht",
    "wof:placetype":"venue"
},
  "geometry": {"coordinates":[3.1209149361,50.7961845398],"type":"Point"}
}