{
  "type": "Feature",
  "properties": {
    "addr:full":"Dreef 1 Genk Limburg 3600",
    "addr:housenumber":"1",
    "addr:postcode":"3600",
    "addr:street":"Dreef",
    "iso:country":"BE",
    "sg:address":"Dreef 1",
    "sg:city":"Genk",
    "sg:orig_category":"Diverse bedrijfsbeheeradviesbureaus",
    "sg:phone":"+32 89 36 19 77",
    "sg:postcode":"3600",
    "sg:province":"Limburg",
    "wof:name":"Groeneveld & Co",
    "wof:placetype":"venue"
},
  "geometry": {"coordinates":[5.5106811523,50.951259613],"type":"Point"}
}