{
  "type": "Feature",
  "properties": {
    "iso:country":"BE",
    "sg:address":"Chauss\u00e9e De Waterloo 690",
    "sg:city":"Bruxelles (uccle)",
    "sg:classifiers":[
        {
            "category":"Food & Beverages",
            "subcategory":"Fruits & Vegetables",
            "type":"Retail Goods"
        }
    ],
    "sg:phone":"+32 2 646 93 02",
    "sg:postcode":"1180",
    "sg:province":"Bruxelles-Capitale",
    "sg:tags":[
        "-",
        "shirt"
    ],
    "wof:name":"Q-ellos Sa",
    "wof:placetype":"venue"
},
  "geometry": {"coordinates":[4.3669700623,50.8161582947],"type":"Point"}
}