{
  "type": "Feature",
  "properties": {
    "addr:full":"Rue Saint-maur 9 Baelen/baelen Li\u00e8ge 4837",
    "addr:housenumber":"9",
    "addr:postcode":"4837",
    "addr:street":"Rue Saint-Maur",
    "iso:country":"BE",
    "sg:address":"Rue Saint-maur 9",
    "sg:city":"Baelen/baelen",
    "sg:orig_category":"Pain, p\u00e2tisseries and confiseries",
    "sg:phone":"+32 87 88 32 10",
    "sg:postcode":"4837",
    "sg:province":"Li\u00e8ge",
    "wof:name":"La Source Des Manons",
    "wof:placetype":"venue"
},
  "geometry": {"coordinates":[5.9646577835,50.6422843933],"type":"Point"}
}