{
  "type": "Feature",
  "properties": {
    "addr:full":"Hauptstrasse 50 Sankt Vith/saint-vith Li\u00e8ge 4780",
    "addr:housenumber":"50",
    "addr:postcode":"4780",
    "addr:street":"Hauptstrasse",
    "iso:country":"BE",
    "sg:address":"Hauptstrasse 50",
    "sg:city":"Sankt Vith/saint-vith",
    "sg:orig_category":"Kapsalons",
    "sg:phone":"+32 80 22 92 82",
    "sg:postcode":"4780",
    "sg:province":"Li\u00e8ge",
    "wof:name":"Erich Illies",
    "wof:placetype":"venue"
},
  "geometry": {"coordinates":[6.0429549217,50.3349761963],"type":"Point"}
}