{
  "type": "Feature",
  "properties": {
    "iso:country":"BE",
    "sg:address":"Vliegplein 22",
    "sg:city":"Herenthout",
    "sg:classifiers":[
        {
            "category":"Professional",
            "subcategory":"Accounting & Tax Preparation",
            "type":"Services"
        }
    ],
    "sg:phone":"+32 14 51 63 72",
    "sg:postcode":"2270",
    "sg:province":"Antwerpen",
    "sg:tags":[
        "accountant"
    ],
    "wof:name":"De Smet C",
    "wof:placetype":"venue"
},
  "geometry": {"coordinates":[4.7682070732,51.1388397217],"type":"Point"}
}