{
  "type": "Feature",
  "properties": {
    "addr:full":"Bedevaartweg 60 Menen West-Vlaanderen 8930",
    "addr:housenumber":"60",
    "addr:postcode":"8930",
    "addr:street":"Bedevaartweg",
    "iso:country":"BE",
    "sg:address":"Bedevaartweg 60",
    "sg:city":"Menen",
    "sg:orig_category":"Pluimveekwekers Varkenskwekers",
    "sg:phone":"+32 56 41 73 32",
    "sg:postcode":"8930",
    "sg:province":"West-Vlaanderen",
    "wof:name":"Marc Castelain",
    "wof:placetype":"venue"
},
  "geometry": {"coordinates":[3.2086880207,50.7705383301],"type":"Point"}
}