{
  "type": "Feature",
  "properties": {
    "addr:full":"Avenue A Allard 270 Braine-l`alleud Brabant Wallon 1420",
    "addr:housenumber":"270",
    "addr:postcode":"1420",
    "addr:street":"Avenue A Allard;Brabant Wallon",
    "iso:country":"BE",
    "sg:address":"Avenue A Allard 270",
    "sg:city":"Braine-l`alleud",
    "sg:orig_category":"Technische studies and ingenieursactiviteiten",
    "sg:phone":"+32 2 384 22 35",
    "sg:postcode":"1420",
    "sg:province":"Brabant Wallon",
    "wof:name":"Teleman - Petrache",
    "wof:placetype":"venue"
},
  "geometry": {"coordinates":[5.8036999702,45.9799995422],"type":"Point"}
}