{
  "type": "Feature",
  "properties": {
    "iso:country":"BE",
    "sg:address":"Caudenberg",
    "sg:city":"Lierde (sint-maria-lierde)",
    "sg:classifiers":[
        {
            "category":"Arena",
            "subcategory":"Sports Club",
            "type":"Entertainment"
        }
    ],
    "sg:phone":"+32 55 42 56 65",
    "sg:postcode":"9570",
    "sg:province":"Oost-Vlaanderen",
    "wof:name":"F C Maria-lierde",
    "wof:placetype":"venue"
},
  "geometry": {"coordinates":[3.8226299286,50.8173408508],"type":"Point"}
}