{
  "type": "Feature",
  "properties": {
    "iso:country":"BE",
    "sg:address":"Koornstraat 96",
    "sg:city":"Roeselare",
    "sg:classifiers":[
        {
            "category":"Train Station",
            "subcategory":"Rail",
            "type":"Transportation"
        }
    ],
    "sg:phone":"+32 9 230 48 48",
    "sg:postcode":"8800",
    "sg:province":"West-Vlaanderen",
    "sg:tags":[
        "casting",
        "bronze"
    ],
    "wof:name":"Melis Nv",
    "wof:placetype":"venue"
},
  "geometry": {"coordinates":[3.7489800453,51.0393600464],"type":"Point"}
}