{
  "type": "Feature",
  "properties": {
    "addr:full":"Rue Du Moulin D'en Haut 232 Mons (fl\u00e9nu) Hainaut 7012",
    "addr:housenumber":"232",
    "addr:postcode":"7012",
    "addr:street":"Rue Du Moulin D'En Haut",
    "iso:country":"BE",
    "sg:address":"Rue Du Moulin D'en Haut 232",
    "sg:city":"Mons (fl\u00e9nu)",
    "sg:classifiers":[
        {
            "category":"Bakery",
            "type":"Food & Drink"
        }
    ],
    "sg:phone":"+32 65 88 65 85",
    "sg:postcode":"7012",
    "sg:province":"Hainaut",
    "sg:tags":[
        "confectioner",
        "baker"
    ],
    "wof:name":"Pagnotta (la)",
    "wof:placetype":"venue"
},
  "geometry": {"coordinates":[3.8994269371,50.438911438],"type":"Point"}
}