{
  "type": "Feature",
  "properties": {
    "addr:full":"Rue De La Gare 72 Frasnes-lez-anvaing (anvaing) Hainaut 7910",
    "addr:housenumber":"72",
    "addr:postcode":"7910",
    "addr:street":"Rue De La Gare",
    "iso:country":"BE",
    "sg:address":"Rue De La Gare 72",
    "sg:city":"Frasnes-lez-anvaing (anvaing)",
    "sg:classifiers":[
        {
            "category":"Shopping",
            "subcategory":"Florist",
            "type":"Retail Goods"
        }
    ],
    "sg:phone":"+32 69 86 68 61",
    "sg:postcode":"7910",
    "sg:province":"Hainaut",
    "wof:name":"Jardin Fleuri (au)",
    "wof:placetype":"venue"
},
  "geometry": {"coordinates":[3.5654299259,50.6853713989],"type":"Point"}
}