{
  "type": "Feature",
  "properties": {
    "addr:full":"Rue De La Station 46 Herve Li\u00e8ge 4650",
    "addr:housenumber":"46",
    "addr:postcode":"4650",
    "addr:street":"Rue De La Station",
    "iso:country":"BE",
    "sg:address":"Rue De La Station 46",
    "sg:city":"Herve",
    "sg:orig_category":"Kapsalons",
    "sg:phone":"+32 87 67 52 38",
    "sg:postcode":"4650",
    "sg:province":"Li\u00e8ge",
    "wof:name":"Select-tifs",
    "wof:placetype":"venue"
},
  "geometry": {"coordinates":[5.7920999527,50.640537262],"type":"Point"}
}