{
  "type": "Feature",
  "properties": {
    "addr:full":"Boulevard Saint-michel 5 Bruxelles (woluwe-saint-pierre) Bruxelles-Capitale 1150",
    "addr:housenumber":"5",
    "addr:postcode":"1150",
    "addr:street":"Boulevard Saint-Michel",
    "iso:country":"BE",
    "sg:address":"Boulevard Saint-michel 5",
    "sg:city":"Bruxelles (woluwe-saint-pierre)",
    "sg:classifiers":[
        {
            "category":"Communications",
            "type":"Services"
        }
    ],
    "sg:phone":"+32 2 736 25 52",
    "sg:postcode":"1150",
    "sg:province":"Bruxelles-Capitale",
    "sg:tags":[
        "translator"
    ],
    "wof:name":"Advantage International",
    "wof:placetype":"venue"
},
  "geometry": {"coordinates":[4.4066691399,50.8364982605],"type":"Point"}
}