{
  "type": "Feature",
  "properties": {
    "iso:country":"BE",
    "sg:address":"Meulebeeksesteenweg 10",
    "sg:city":"Tielt",
    "sg:orig_category":"Autokeuringen",
    "sg:phone":"+32 51 40 13 64",
    "sg:postcode":"8700",
    "sg:province":"West-Vlaanderen",
    "wof:name":"Autokeuring",
    "wof:placetype":"venue"
},
  "geometry": {"coordinates":[3.3135828972,50.9853286743],"type":"Point"}
}