{
  "type": "Feature",
  "properties": {
    "addr:full":"Dokter H.hyleboslaan 1 Hamme Oost-Vlaanderen 9220",
    "addr:housenumber":"1",
    "addr:postcode":"9220",
    "addr:street":"Dokter H.Hyleboslaan",
    "iso:country":"BE",
    "sg:address":"Dokter H.hyleboslaan 1",
    "sg:city":"Hamme",
    "sg:orig_category":"Enseignement maternel and primaire",
    "sg:phone":"+32 52 47 03 46",
    "sg:postcode":"9220",
    "sg:province":"Oost-Vlaanderen",
    "wof:name":"Vrije Basisschool",
    "wof:placetype":"venue"
},
  "geometry": {"coordinates":[4.1557660103,51.0918006897],"type":"Point"}
}