{
  "type": "Feature",
  "properties": {
    "iso:country":"BE",
    "sg:address":"Rue Des Guillemins 42",
    "sg:city":"Li\u00c8ge",
    "sg:orig_category":"Boucheries. Restaurants livraison \u00e0 domicile",
    "sg:phone":"+32 4 252 45 30",
    "sg:postcode":"4000",
    "sg:province":"Li\u00e8ge",
    "wof:name":"Boucherie Lesecque",
    "wof:placetype":"venue"
},
  "geometry": {"coordinates":[5.5675787926,50.6290206909],"type":"Point"}
}