{
  "type": "Feature",
  "properties": {
    "addr:full":"Tombroekstraat 179 Kortrijk West-Vlaanderen 8510",
    "addr:housenumber":"179",
    "addr:postcode":"8510",
    "addr:street":"Tombroekstraat",
    "iso:country":"BE",
    "sg:address":"Tombroekstraat 179",
    "sg:city":"Kortrijk",
    "sg:orig_category":"Voertuigen",
    "sg:phone":"+32 56 21 55 58",
    "sg:postcode":"8510",
    "sg:province":"West-Vlaanderen",
    "wof:name":"Ronny's Music",
    "wof:placetype":"venue"
},
  "geometry": {"coordinates":[3.2663888931,50.7548103333],"type":"Point"}
}