{
  "type": "Feature",
  "properties": {
    "addr:full":"Hagenbroeksesteenweg 215 Lier Antwerpen 2500",
    "addr:housenumber":"215",
    "addr:postcode":"2500",
    "addr:street":"Hagenbroeksesteenweg",
    "iso:country":"BE",
    "sg:address":"Hagenbroeksesteenweg 215",
    "sg:city":"Lier",
    "sg:classifiers":[
        {
            "category":"Freight",
            "type":"Transportation"
        }
    ],
    "sg:phone":"+32 3 491 90 50",
    "sg:postcode":"2500",
    "sg:province":"Antwerpen",
    "sg:tags":[
        "-",
        "transport"
    ],
    "wof:name":"Vadesco Logistics Bvba",
    "wof:placetype":"venue"
},
  "geometry": {"coordinates":[4.5585689545,51.1521720886],"type":"Point"}
}