{
  "type": "Feature",
  "properties": {
    "iso:country":"BE",
    "sg:address":"Boulevard De La Sauveni\u00c8re 133",
    "sg:city":"Li\u00c8ge",
    "sg:classifiers":[
        {
            "category":"Insurance",
            "subcategory":"Insurance Agent",
            "type":"Services"
        }
    ],
    "sg:phone":"+32 4 223 60 36",
    "sg:postcode":"4000",
    "sg:province":"Li\u00e8ge",
    "sg:tags":[
        "verzekeringsmakelaars",
        "expert"
    ],
    "wof:name":"De Madre, Lenoir & Cie",
    "wof:placetype":"venue"
},
  "geometry": {"coordinates":[5.5679888725,50.6411361694],"type":"Point"}
}