{
  "type": "Feature",
  "properties": {
    "addr:full":"Rue De Loneux 18 Sprimont Li\u00e8ge 4140",
    "addr:housenumber":"18",
    "addr:postcode":"4140",
    "addr:street":"Rue De Loneux",
    "iso:country":"BE",
    "sg:address":"Rue De Loneux 18",
    "sg:city":"Sprimont",
    "sg:orig_category":"Loodgieterij, verwarming and sanitaire installaties",
    "sg:phone":"+32 4 369 27 05",
    "sg:postcode":"4140",
    "sg:province":"Li\u00e8ge",
    "wof:name":"Jacques Amand",
    "wof:placetype":"venue"
},
  "geometry": {"coordinates":[5.5963139534,50.4885215759],"type":"Point"}
}