{
  "type": "Feature",
  "properties": {
    "addr:full":"Ternatsestraat 82 Affligem (essene) Vlaams-Brabant 1790",
    "addr:housenumber":"82",
    "addr:postcode":"1790",
    "addr:street":"Ternatsestraat",
    "iso:country":"BE",
    "sg:address":"Ternatsestraat 82",
    "sg:city":"Affligem (essene)",
    "sg:classifiers":[
        {
            "category":"Building & Trades",
            "subcategory":"Construction",
            "type":"Services"
        }
    ],
    "sg:phone":"+32 2 582 67 02",
    "sg:postcode":"1790",
    "sg:province":"Vlaams-Brabant",
    "sg:tags":[
        "stair"
    ],
    "wof:name":"Van Rossem Nv",
    "wof:placetype":"venue"
},
  "geometry": {"coordinates":[4.1378521919,50.8978004456],"type":"Point"}
}