{
  "type": "Feature",
  "properties": {
    "addr:full":"Lequimelaan 34 Sint-genesius-rode/rhode-saint-gen\u00c8se Vlaams-Brabant 1640",
    "addr:housenumber":"34",
    "addr:postcode":"1640",
    "addr:street":"Lequimelaan",
    "iso:country":"BE",
    "sg:address":"Lequimelaan 34",
    "sg:city":"Sint-genesius-rode/rhode-saint-gen\u00c8se",
    "sg:orig_category":"Artiesten and kunstenaars",
    "sg:phone":"+32 2 358 17 82",
    "sg:postcode":"1640",
    "sg:province":"Vlaams-Brabant",
    "wof:name":"Marie-henriette Schilling",
    "wof:placetype":"venue"
},
  "geometry": {"coordinates":[4.377412796,50.7650489807],"type":"Point"}
}