{
  "type": "Feature",
  "properties": {
    "addr:full":"Haagstraat 24 Gavere (asper) Oost-Vlaanderen 9890",
    "addr:housenumber":"24",
    "addr:postcode":"9890",
    "addr:street":"Haagstraat",
    "iso:country":"BE",
    "sg:address":"Haagstraat 24",
    "sg:city":"Gavere (asper)",
    "sg:classifiers":[
        {
            "category":"Health Services",
            "subcategory":"Health Practitioner",
            "type":"Services"
        }
    ],
    "sg:phone":"+32 9 324 94 70",
    "sg:postcode":"9890",
    "sg:province":"Oost-Vlaanderen",
    "sg:tags":[
        "psychologist"
    ],
    "wof:name":"Ronsse E",
    "wof:placetype":"venue"
},
  "geometry": {"coordinates":[3.6557700634,50.9112510681],"type":"Point"}
}