{
  "type": "Feature",
  "properties": {
    "iso:country":"BE",
    "sg:address":"Heerbaan 43",
    "sg:city":"Gooik (oetingen)",
    "sg:classifiers":[
        {
            "category":"Professional",
            "subcategory":"Management & Consulting",
            "type":"Services"
        }
    ],
    "sg:phone":"+32 54 56 65 92",
    "sg:postcode":"1755",
    "sg:province":"Vlaams-Brabant",
    "sg:tags":[
        "-",
        "processing",
        "data",
        "consultant"
    ],
    "wof:name":"Ebiz@work",
    "wof:placetype":"venue"
},
  "geometry": {"coordinates":[4.0766830444,50.7793731689],"type":"Point"}
}