{
  "type": "Feature",
  "properties": {
    "addr:full":"Place Du Becquerelle 1bb Tournai Hainaut 7500",
    "addr:housenumber":"1bb",
    "addr:postcode":"7500",
    "addr:street":"Place Du Becquerelle",
    "iso:country":"BE",
    "sg:address":"Place Du Becquerelle 1bb",
    "sg:city":"Tournai",
    "sg:orig_category":"Maisons de repos and r\u00e9sidences",
    "sg:phone":"+32 69 89 04 04",
    "sg:postcode":"7500",
    "sg:province":"Hainaut",
    "wof:name":"Home St.georges",
    "wof:placetype":"venue"
},
  "geometry": {"coordinates":[3.3899888992,50.609588623],"type":"Point"}
}