{
  "type": "Feature",
  "properties": {
    "addr:full":"Sint-antoniusstraat 7 Ranst Antwerpen 2520",
    "addr:housenumber":"7",
    "addr:postcode":"2520",
    "addr:street":"Sint-Antoniusstraat",
    "iso:country":"BE",
    "sg:address":"Sint-antoniusstraat 7",
    "sg:city":"Ranst",
    "sg:classifiers":[
        {
            "category":"Professional",
            "subcategory":"Art Services",
            "type":"Services"
        }
    ],
    "sg:phone":"+32 478 25 15 47",
    "sg:postcode":"2520",
    "sg:province":"Antwerpen",
    "sg:tags":[
        "interior",
        "designer"
    ],
    "wof:name":"Paepen S",
    "wof:placetype":"venue"
},
  "geometry": {"coordinates":[4.5484981537,51.1865921021],"type":"Point"}
}