{
  "type": "Feature",
  "properties": {
    "addr:full":"Nijverheidsstraat 40 Dendermonde Oost-Vlaanderen 9200",
    "addr:housenumber":"40",
    "addr:postcode":"9200",
    "addr:street":"Nijverheidsstraat;Oost-Vlaanderen",
    "iso:country":"BE",
    "sg:address":"Nijverheidsstraat 40",
    "sg:city":"Dendermonde",
    "sg:orig_category":"Herstelling and restauratie van meubelen",
    "sg:phone":"+32 52 22 33 29",
    "sg:postcode":"9200",
    "sg:province":"Oost-Vlaanderen",
    "wof:name":"A. Simon",
    "wof:placetype":"venue"
},
  "geometry": {"coordinates":[4.1018090248,51.027961731],"type":"Point"}
}