{
  "type": "Feature",
  "properties": {
    "addr:full":"Chauss\u00c9e De Gand 356 Sint-jans-molenbeek/molenbeek-saint-jean Bruxelles-Capitale 1080",
    "addr:housenumber":"356",
    "addr:postcode":"1080",
    "addr:street":"Chausse\u0301E De Gand",
    "iso:country":"BE",
    "sg:address":"Chauss\u00c9e De Gand 356",
    "sg:city":"Sint-jans-molenbeek/molenbeek-saint-jean",
    "sg:orig_category":"Pharmaciens",
    "sg:phone":"+32 2 410 80 93",
    "sg:postcode":"1080",
    "sg:province":"Bruxelles-Capitale",
    "wof:name":"Cecile Weemaes/c. Weemaes",
    "wof:placetype":"venue"
},
  "geometry": {"coordinates":[4.3212070465,50.8572883606],"type":"Point"}
}