{
  "type": "Feature",
  "properties": {
    "addr:full":"Aalterbaan 164 Maldegem Oost-Vlaanderen 9990",
    "addr:housenumber":"164",
    "addr:postcode":"9990",
    "iso:country":"BE",
    "sg:address":"Aalterbaan 164",
    "sg:city":"Maldegem",
    "sg:orig_category":"Afval and schroot Gh",
    "sg:phone":"+32 50 71 82 45",
    "sg:postcode":"9990",
    "sg:province":"Oost-Vlaanderen",
    "wof:name":"Gino Van Den Heuvel",
    "wof:placetype":"venue"
},
  "geometry": {"coordinates":[3.4530229568,51.1990737915],"type":"Point"}
}