{
  "type": "Feature",
  "properties": {
    "addr:full":"Gentsestraat 61 Aalst Oost-Vlaanderen 9300",
    "addr:housenumber":"61",
    "addr:postcode":"9300",
    "addr:street":"Gentsestraat",
    "iso:country":"BE",
    "sg:address":"Gentsestraat 61",
    "sg:city":"Aalst",
    "sg:orig_category":"Banques and organismes de cr\u00e9dit",
    "sg:phone":"+32 53 77 97 39",
    "sg:postcode":"9300",
    "sg:province":"Oost-Vlaanderen",
    "wof:name":"Kbc",
    "wof:placetype":"venue"
},
  "geometry": {"coordinates":[4.0307941437,50.9378738403],"type":"Point"}
}