{
  "type": "Feature",
  "properties": {
    "addr:full":"Zuidlaan 5 Zele Oost-Vlaanderen 9240",
    "addr:housenumber":"5",
    "addr:postcode":"9240",
    "addr:street":"Zuidlaan",
    "iso:country":"BE",
    "sg:address":"Zuidlaan 5",
    "sg:city":"Zele",
    "sg:classifiers":[
        {
            "category":"Personal",
            "subcategory":"Beauty Salon",
            "type":"Services"
        }
    ],
    "sg:phone":"+32 52 44 50 13",
    "sg:postcode":"9240",
    "sg:province":"Oost-Vlaanderen",
    "sg:tags":[
        "lady",
        "-",
        "hairdressing"
    ],
    "wof:name":"Thir\u00e9",
    "wof:placetype":"venue"
},
  "geometry": {"coordinates":[4.0317077637,51.0643615723],"type":"Point"}
}