{
  "type": "Feature",
  "properties": {
    "iso:country":"BE",
    "sg:address":"Rue De La Reine 4",
    "sg:city":"Namur (vedrin - Daussoulx)",
    "sg:classifiers":[
        {
            "category":"Health Services",
            "subcategory":"Doctor",
            "type":"Services"
        }
    ],
    "sg:phone":"+32 475 71 61 64",
    "sg:postcode":"5020",
    "sg:province":"Namur",
    "sg:tags":[
        "medicinephysicians",
        "surgeon"
    ],
    "wof:name":"Daie K",
    "wof:placetype":"venue"
},
  "geometry": {"coordinates":[4.8811597824,50.4917411804],"type":"Point"}
}