{
  "type": "Feature",
  "properties": {
    "iso:country":"BE",
    "sg:address":"Rue Charles Stiernon 16",
    "sg:city":"Ecaussinnes",
    "sg:orig_category":"Rusthuizen and serviceflats",
    "sg:phone":"+32 67 49 04 20",
    "sg:postcode":"7190",
    "sg:province":"Hainaut",
    "wof:name":"R\u00c9sidence Comme Chez Soi",
    "wof:placetype":"venue"
},
  "geometry": {"coordinates":[4.1539440155,50.5616645813],"type":"Point"}
}