{
  "type": "Feature",
  "properties": {
    "iso:country":"BE",
    "sg:address":"Oudstrijdersstraat 52",
    "sg:city":"Dilbeek",
    "sg:classifiers":[
        {
            "category":"Building & Trades",
            "subcategory":"Construction",
            "type":"Services"
        }
    ],
    "sg:phone":"+32 2 567 91 62",
    "sg:postcode":"1700",
    "sg:province":"Vlaams-Brabant",
    "sg:tags":[
        "glazier"
    ],
    "wof:name":"Bajart G",
    "wof:placetype":"venue"
},
  "geometry": {"coordinates":[4.2664928436,50.8458862305],"type":"Point"}
}