{
  "type": "Feature",
  "properties": {
    "iso:country":"BE",
    "sg:address":"Margensault 64",
    "sg:city":"Thimister-clermont (thimister)",
    "sg:classifiers":[
        {
            "category":"Professional",
            "subcategory":"Business Services",
            "type":"Services"
        }
    ],
    "sg:phone":"+32 87 44 70 60",
    "sg:postcode":"4890",
    "sg:province":"Li\u00e8ge",
    "sg:tags":[
        "automobile",
        "-",
        "assessor"
    ],
    "wof:name":"P Et Ph. Somja Expertises Scprl",
    "wof:placetype":"venue"
},
  "geometry": {"coordinates":[5.8630700111,50.6540870667],"type":"Point"}
}