{
  "type": "Feature",
  "properties": {
    "iso:country":"BE",
    "sg:address":"Kouter 234",
    "sg:city":"Oudergem/auderghem",
    "sg:orig_category":"Artsen and specialisten",
    "sg:phone":"+32 2 672 65 59",
    "sg:postcode":"1160",
    "sg:province":"Bruxelles-Capitale",
    "wof:name":"Suzanne Koopmansch",
    "wof:placetype":"venue"
},
  "geometry": {"coordinates":[4.4201188087,50.8199043274],"type":"Point"}
}