{
  "type": "Feature",
  "properties": {
    "addr:full":"Verbroederingslaan 42 Zelzate Oost-Vlaanderen 9060",
    "addr:housenumber":"42",
    "addr:postcode":"9060",
    "addr:street":"Verbroederingslaan",
    "iso:country":"BE",
    "sg:address":"Verbroederingslaan 42",
    "sg:city":"Zelzate",
    "sg:orig_category":"Pain, p\u00e2tisseries and confiseries",
    "sg:phone":"+32 9 345 62 50",
    "sg:postcode":"9060",
    "sg:province":"Oost-Vlaanderen",
    "wof:name":"Theophile Caus",
    "wof:placetype":"venue"
},
  "geometry": {"coordinates":[3.8140439987,51.195728302],"type":"Point"}
}