{
  "type": "Feature",
  "properties": {
    "iso:country":"BE",
    "sg:address":"Kortrijksteenweg 43",
    "sg:city":"Wingene",
    "sg:classifiers":[
        {
            "category":"Fast Food",
            "type":"Food & Drink"
        }
    ],
    "sg:phone":"+32 51 61 23 91",
    "sg:postcode":"8750",
    "sg:province":"West-Vlaanderen",
    "sg:tags":[
        "huis",
        "aan",
        "levering",
        "meeneem",
        "restaurant"
    ],
    "wof:name":"De Oude Meerlaan",
    "wof:placetype":"venue"
},
  "geometry": {"coordinates":[3.2305619717,51.0251350403],"type":"Point"}
}