{
  "type": "Feature",
  "properties": {
    "addr:full":"Route De Waimes 36 Malmedy Li\u00e8ge 4960",
    "addr:housenumber":"36",
    "addr:postcode":"4960",
    "addr:street":"Route De Waimes",
    "iso:country":"BE",
    "sg:address":"Route De Waimes 36",
    "sg:city":"Malmedy",
    "sg:orig_category":"Pre-press",
    "sg:phone":"+32 80 33 89 89",
    "sg:postcode":"4960",
    "sg:province":"Li\u00e8ge",
    "wof:name":"Publiracing Agency",
    "wof:placetype":"venue"
},
  "geometry": {"coordinates":[6.0576357841,50.4080505371],"type":"Point"}
}