{
  "type": "Feature",
  "properties": {
    "iso:country":"BE",
    "sg:address":"Kosterijstraat 37",
    "sg:city":"Kontich",
    "sg:classifiers":[
        {
            "category":"Arena",
            "subcategory":"Sports Club",
            "type":"Entertainment"
        }
    ],
    "sg:phone":"+32 3 457 48 68",
    "sg:postcode":"2550",
    "sg:province":"Antwerpen",
    "sg:tags":[
        "de"
    ],
    "wof:name":"B.c. Deurne",
    "wof:placetype":"venue"
},
  "geometry": {"coordinates":[4.4538397789,51.1359558105],"type":"Point"}
}