{
  "type": "Feature",
  "properties": {
    "addr:full":"Avenue Des Renoncules 15b2 Waver Brabant Wallon 1300",
    "addr:housenumber":"15b2",
    "addr:postcode":"1300",
    "addr:street":"Avenue Des Renoncules;Wallon",
    "iso:country":"BE",
    "sg:address":"Avenue Des Renoncules 15b2",
    "sg:city":"Waver",
    "sg:orig_category":"Diverse bedrijfsbeheeradviesbureaus",
    "sg:phone":"+32 10 40 24 24",
    "sg:postcode":"1300",
    "sg:province":"Brabant Wallon",
    "wof:name":"European Launching & Assistance Network",
    "wof:placetype":"venue"
},
  "geometry": {"coordinates":[4.6116552353,50.7134132385],"type":"Point"}
}