{
  "type": "Feature",
  "properties": {
    "iso:country":"BE",
    "sg:address":"Lieven Bauwensstraat 21",
    "sg:city":"Anzegem (vichte)",
    "sg:classifiers":[
        {
            "category":"Professional",
            "subcategory":"Computer Services",
            "type":"Services"
        }
    ],
    "sg:phone":"+32 56 77 20 29",
    "sg:postcode":"8570",
    "sg:province":"West-Vlaanderen",
    "sg:tags":[
        "-",
        "processing",
        "data"
    ],
    "wof:name":"Balder Van Eeckhoutte",
    "wof:placetype":"venue"
},
  "geometry": {"coordinates":[3.4047501087,50.8400917053],"type":"Point"}
}