{
  "type": "Feature",
  "properties": {
    "iso:country":"BE",
    "sg:address":"Place De P\u00c2turages 41",
    "sg:city":"Colfontaine",
    "sg:orig_category":"Emballages en plastique Fab",
    "sg:phone":"+32 65 67 41 19",
    "sg:postcode":"7340",
    "sg:province":"Hainaut",
    "wof:name":"Intercommun. Oeuvres Soc.",
    "wof:placetype":"venue"
},
  "geometry": {"coordinates":[3.8477070332,50.4131202698],"type":"Point"}
}