{
  "type": "Feature",
  "properties": {
    "iso:country":"BE",
    "sg:address":"Boomsesteenweg 147",
    "sg:city":"Aartselaar",
    "sg:classifiers":[
        {
            "category":"Health Services",
            "subcategory":"Doctor",
            "type":"Services"
        }
    ],
    "sg:phone":"+32 3 844 78 30",
    "sg:postcode":"2630",
    "sg:province":"Antwerpen",
    "sg:tags":[
        "medicinephysicians",
        "surgeon"
    ],
    "wof:name":"Couckuyt H",
    "wof:placetype":"venue"
},
  "geometry": {"coordinates":[4.3715548515,51.1120033264],"type":"Point"}
}