{
  "type": "Feature",
  "properties": {
    "iso:country":"BE",
    "sg:address":"Pelikaanstraat 102",
    "sg:city":"Oudenaarde",
    "sg:orig_category":"R\u00e9parations de chaussures and articles en cuir",
    "sg:phone":"+32 55 31 75 03",
    "sg:postcode":"9700",
    "sg:province":"Oost-Vlaanderen",
    "wof:name":"Noel Vanden Hautte",
    "wof:placetype":"venue"
},
  "geometry": {"coordinates":[3.63499403,50.870098114],"type":"Point"}
}