{
  "type": "Feature",
  "properties": {
    "iso:country":"BE",
    "sg:address":"Mechelsesteenweg 334",
    "sg:city":"Edegem",
    "sg:classifiers":[
        {
            "category":"Professional",
            "subcategory":"Management & Consulting",
            "type":"Services"
        }
    ],
    "sg:phone":"+32 3 454 42 63",
    "sg:postcode":"2650",
    "sg:province":"Antwerpen",
    "sg:tags":[
        "marketing",
        "-",
        "direct",
        "consultant"
    ],
    "wof:name":"Kada Bvba",
    "wof:placetype":"venue"
},
  "geometry": {"coordinates":[4.4603271484,51.1559448242],"type":"Point"}
}