{
  "type": "Feature",
  "properties": {
    "addr:full":"Rue De L'epargne 37 Mons Hainaut 7000",
    "addr:housenumber":"37",
    "addr:postcode":"7000",
    "addr:street":"Rue De L'Epargne;Hainaut",
    "iso:country":"BE",
    "sg:address":"Rue De L'epargne 37",
    "sg:city":"Mons",
    "sg:classifiers":[
        {
            "category":"Science Facility",
            "type":"Public Place"
        }
    ],
    "sg:phone":"+32 65 84 48 86",
    "sg:postcode":"7000",
    "sg:province":"Hainaut",
    "sg:tags":[
        "-",
        "management",
        "data",
        "processing"
    ],
    "wof:name":"Capis Sprl",
    "wof:placetype":"venue"
},
  "geometry": {"coordinates":[3.9566841125,50.4483757019],"type":"Point"}
}