{
  "type": "Feature",
  "properties": {
    "iso:country":"BE",
    "sg:address":"Route De Tancr\u00e9mont 55",
    "sg:city":"Pepinster",
    "sg:classifiers":[
        {
            "category":"Social Services",
            "type":"Services"
        }
    ],
    "sg:phone":"+32 87 53 02 48",
    "sg:postcode":"4860",
    "sg:province":"Li\u00e8ge",
    "wof:name":"Ligue Des Droits De L'homme",
    "wof:placetype":"venue"
},
  "geometry": {"coordinates":[5.7862820625,50.55235672],"type":"Point"}
}