{
  "type": "Feature",
  "properties": {
    "iso:country":"BE",
    "sg:address":"Westkerkestraat 150",
    "sg:city":"Ichtegem",
    "sg:orig_category":"Eleveurs and marchands de porcs",
    "sg:phone":"+32 59 29 92 75",
    "sg:postcode":"8480",
    "sg:province":"West-Vlaanderen",
    "wof:name":"Emilius Tavernier",
    "wof:placetype":"venue"
},
  "geometry": {"coordinates":[3.0257050991,51.137096405],"type":"Point"}
}