{
  "type": "Feature",
  "properties": {
    "addr:full":"Sint-annalaan 234 Grimbergen (strombeek-bever) Vlaams-Brabant 1853",
    "addr:housenumber":"234",
    "addr:postcode":"1853",
    "addr:street":"Sint-Annalaan",
    "iso:country":"BE",
    "sg:address":"Sint-annalaan 234",
    "sg:city":"Grimbergen (strombeek-bever)",
    "sg:classifiers":[
        {
            "category":"Shopping",
            "subcategory":"Clothing, Apparel, & Fashions",
            "type":"Retail Goods"
        }
    ],
    "sg:phone":"+32 2 267 29 56",
    "sg:postcode":"1853",
    "sg:province":"Vlaams-Brabant",
    "sg:tags":[
        "-",
        "clothing",
        "child"
    ],
    "wof:name":"Yasmine",
    "wof:placetype":"venue"
},
  "geometry": {"coordinates":[4.3556537628,50.9104385376],"type":"Point"}
}