{
  "type": "Feature",
  "properties": {
    "addr:full":"Liersesteenweg 150 Aarschot Vlaams-Brabant 3200",
    "addr:housenumber":"150",
    "addr:postcode":"3200",
    "addr:street":"Liersesteenweg",
    "iso:country":"BE",
    "sg:address":"Liersesteenweg 150",
    "sg:city":"Aarschot",
    "sg:orig_category":"Instituts de beaut\u00e9",
    "sg:phone":"+32 16 56 73 01",
    "sg:postcode":"3200",
    "sg:province":"Vlaams-Brabant",
    "wof:name":"Ann Van Bael",
    "wof:placetype":"venue"
},
  "geometry": {"coordinates":[4.824616909,51.0037536621],"type":"Point"}
}