{
  "type": "Feature",
  "properties": {
    "iso:country":"BE",
    "sg:address":"Avenue Th\u00e9o Verbeeck 71",
    "sg:city":"Bruxelles (anderlecht)",
    "sg:classifiers":[
        {
            "category":"Cemetery",
            "type":"Public Place"
        }
    ],
    "sg:phone":"+32 2 522 08 51",
    "sg:postcode":"1070",
    "sg:province":"Bruxelles-Capitale",
    "sg:tags":[
        "crematory"
    ],
    "wof:name":"Duch\u00eane L Sprl",
    "wof:placetype":"venue"
},
  "geometry": {"coordinates":[4.2957630157,50.8340339661],"type":"Point"}
}