{
  "type": "Feature",
  "properties": {
    "iso:country":"BE",
    "sg:address":"Jozef Dedobbeleerstraat 7",
    "sg:city":"Sint-pieters-leeuw",
    "sg:orig_category":"Producteurs de fruits. Eleveurs de bovins",
    "sg:phone":"+32 2 377 69 25",
    "sg:postcode":"1600",
    "sg:province":"Vlaams-Brabant",
    "wof:name":"Jan Cordijn",
    "wof:placetype":"venue"
},
  "geometry": {"coordinates":[4.230383873,50.7770881653],"type":"Point"}
}