{
  "type": "Feature",
  "properties": {
    "iso:country":"BE",
    "sg:address":"Staatsbaan 91",
    "sg:city":"Adegem",
    "sg:classifiers":[
        {
            "category":"Banks & Credit Unions",
            "subcategory":"Bank",
            "type":"Services"
        }
    ],
    "sg:phone":"+32 50 71 35 66",
    "sg:postcode":"9991",
    "sg:province":"Oost-Vlaanderen",
    "wof:name":"Aslk-cger Bank",
    "wof:placetype":"venue"
},
  "geometry": {"coordinates":[3.4869799614,51.2047042847],"type":"Point"}
}