{
  "type": "Feature",
  "properties": {
    "addr:full":"Kiezelweg 15 Nijlen Antwerpen 2560",
    "addr:housenumber":"15",
    "addr:postcode":"2560",
    "addr:street":"Kiezelweg",
    "iso:country":"BE",
    "sg:address":"Kiezelweg 15",
    "sg:city":"Nijlen",
    "sg:orig_category":"Rev\u00eatements de sols and murs",
    "sg:phone":"+32 3 411 04 55",
    "sg:postcode":"2560",
    "sg:province":"Antwerpen",
    "wof:name":"Wittockx R",
    "wof:placetype":"venue"
},
  "geometry": {"coordinates":[4.6915969849,51.1366691589],"type":"Point"}
}