{
  "type": "Feature",
  "properties": {
    "addr:full":"Jules Destr\u00e9elaan 11 Gent (gentbrugge) Oost-Vlaanderen 9050",
    "addr:housenumber":"11",
    "addr:postcode":"9050",
    "addr:street":"Destre\u0301Elaan",
    "iso:country":"BE",
    "sg:address":"Jules Destr\u00e9elaan 11",
    "sg:city":"Gent (gentbrugge)",
    "sg:classifiers":[
        {
            "category":"Professional",
            "subcategory":"Art Services",
            "type":"Services"
        }
    ],
    "sg:phone":"+32 9 232 49 24",
    "sg:postcode":"9050",
    "sg:province":"Oost-Vlaanderen",
    "sg:tags":[
        "graphic",
        "designer"
    ],
    "wof:name":"B'right Design",
    "wof:placetype":"venue"
},
  "geometry": {"coordinates":[3.7697639465,51.0286521912],"type":"Point"}
}