{
  "type": "Feature",
  "properties": {
    "addr:full":"Lambrechtshoekenlaan 263 Merksem Antwerpen 2170",
    "addr:housenumber":"263",
    "addr:postcode":"2170",
    "addr:street":"Lambrechtshoekenlaan",
    "iso:country":"BE",
    "sg:address":"Lambrechtshoekenlaan 263",
    "sg:city":"Merksem",
    "sg:orig_category":"Huisdieren and benodigdheden Royal Canin",
    "sg:phone":"+32 3 644 51 39",
    "sg:postcode":"2170",
    "sg:province":"Antwerpen",
    "wof:name":"Dierenplezier",
    "wof:placetype":"venue"
},
  "geometry": {"coordinates":[4.4344267845,51.2525558472],"type":"Point"}
}