{
  "type": "Feature",
  "properties": {
    "iso:country":"BE",
    "sg:address":"Place De P\u00e2turages 41",
    "sg:city":"Colfontaine (p\u00e2turages)",
    "sg:classifiers":[
        {
            "category":"Community Center",
            "subcategory":"Youth",
            "type":"Public Place"
        }
    ],
    "sg:phone":"+32 65 67 41 19",
    "sg:postcode":"7340",
    "sg:province":"Hainaut",
    "sg:tags":[
        "workshop",
        "sheltered"
    ],
    "wof:name":"I.o.s.",
    "wof:placetype":"venue"
},
  "geometry": {"coordinates":[3.8477070332,50.4131202698],"type":"Point"}
}