{
  "type": "Feature",
  "properties": {
    "addr:full":"Rue De Tervaete 101 Etterbeek/etterbeek Bruxelles-Capitale 1040",
    "addr:housenumber":"101",
    "addr:postcode":"1040",
    "addr:street":"Rue De Tervaete",
    "iso:country":"BE",
    "sg:address":"Rue De Tervaete 101",
    "sg:city":"Etterbeek/etterbeek",
    "sg:orig_category":"M\u00e9decins and sp\u00e9cialistes",
    "sg:phone":"+32 2 732 57 81",
    "sg:postcode":"1040",
    "sg:province":"Bruxelles-Capitale",
    "wof:name":"Cassart",
    "wof:placetype":"venue"
},
  "geometry": {"coordinates":[4.4014601707,50.8291358948],"type":"Point"}
}