{
  "type": "Feature",
  "properties": {
    "addr:full":"Dennenlaan 33 Zoersel Antwerpen 2980",
    "addr:housenumber":"33",
    "addr:postcode":"2980",
    "addr:street":"Dennenlaan",
    "iso:country":"BE",
    "sg:address":"Dennenlaan 33",
    "sg:city":"Zoersel",
    "sg:orig_category":"Woningbouw",
    "sg:phone":"+32 3 383 06 59",
    "sg:postcode":"2980",
    "sg:province":"Antwerpen",
    "wof:name":"Van Looveren",
    "wof:placetype":"venue"
},
  "geometry": {"coordinates":[4.6251702309,51.2538948059],"type":"Point"}
}