{
  "type": "Feature",
  "properties": {
    "addr:full":"Place Albert Ier 32 Fleurus Hainaut 6220",
    "addr:housenumber":"32",
    "addr:postcode":"6220",
    "addr:street":"Place Albert Ier",
    "iso:country":"BE",
    "sg:address":"Place Albert Ier 32",
    "sg:city":"Fleurus",
    "sg:orig_category":"Banques and organismes de cr\u00e9dit",
    "sg:phone":"+32 71 81 12 36",
    "sg:postcode":"6220",
    "sg:province":"Hainaut",
    "wof:name":"Bbl",
    "wof:placetype":"venue"
},
  "geometry": {"coordinates":[4.5574269295,50.4610137939],"type":"Point"}
}