{
  "type": "Feature",
  "properties": {
    "addr:full":"Veurnseweg 569 Ieper West-Vlaanderen 8906",
    "addr:housenumber":"569",
    "addr:postcode":"8906",
    "addr:street":"Veurnseweg",
    "iso:country":"BE",
    "sg:address":"Veurnseweg 569",
    "sg:city":"Ieper",
    "sg:orig_category":"Kapsalons",
    "sg:phone":"+32 57 42 22 94",
    "sg:postcode":"8906",
    "sg:province":"West-Vlaanderen",
    "wof:name":"Coiffure Martine",
    "wof:placetype":"venue"
},
  "geometry": {"coordinates":[2.8123140335,50.8867454529],"type":"Point"}
}