{
  "type": "Feature",
  "properties": {
    "iso:country":"BE",
    "sg:address":"Westerloseweg 13",
    "sg:city":"Geel",
    "sg:orig_category":"Pain, p\u00e2tisseries and confiseries",
    "sg:phone":"+32 14 54 47 90",
    "sg:postcode":"2440",
    "sg:province":"Antwerpen",
    "wof:name":"Francois Keirsmaekers",
    "wof:placetype":"venue"
},
  "geometry": {"coordinates":[4.9430627823,51.0968933105],"type":"Point"}
}