{
  "type": "Feature",
  "properties": {
    "addr:full":"Rue Chauss\u00c9e 31 Fontaine-l\u00b4ev\u00caque Hainaut 6141",
    "addr:housenumber":"31",
    "addr:postcode":"6141",
    "addr:street":"Rue Chausse\u0301E;Hainaut",
    "iso:country":"BE",
    "sg:address":"Rue Chauss\u00c9e 31",
    "sg:city":"Fontaine-l\u00b4ev\u00caque",
    "sg:orig_category":"Journaux. Librairies. Tabac",
    "sg:phone":"+32 71 52 93 76",
    "sg:postcode":"6141",
    "sg:province":"Hainaut",
    "wof:name":"Librairie Des Trieux",
    "wof:placetype":"venue"
},
  "geometry": {"coordinates":[4.3374938965,50.4395713806],"type":"Point"}
}