{
  "type": "Feature",
  "properties": {
    "iso:country":"BE",
    "sg:address":"Rue Saint-eleuth\u00c8re 32ba",
    "sg:city":"Tournai",
    "sg:orig_category":"Pharmaciens",
    "sg:phone":"+32 69 22 32 18",
    "sg:postcode":"7500",
    "sg:province":"Hainaut",
    "wof:name":"Dominique Destrebecq",
    "wof:placetype":"venue"
},
  "geometry": {"coordinates":[3.3758909702,50.612411499],"type":"Point"}
}