{
  "type": "Feature",
  "properties": {
    "iso:country":"BE",
    "sg:address":"Nieuwland",
    "sg:city":"Aarschot",
    "sg:classifiers":[
        {
            "category":"Manufacturing",
            "subcategory":"Rubber & Plastics",
            "type":"Manufacturing & Wholesale Goods"
        }
    ],
    "sg:phone":"+32 16 56 40 90",
    "sg:postcode":"3200",
    "sg:province":"Vlaams-Brabant",
    "sg:tags":[
        "industrial",
        "-"
    ],
    "wof:name":"Areva Nv",
    "wof:placetype":"venue"
},
  "geometry": {"coordinates":[4.8051109314,50.9756889343],"type":"Point"}
}