{
  "type": "Feature",
  "properties": {
    "addr:full":"Place D'ellignies 2 Beloeil (ellignies-sainte-anne) Hainaut 7972",
    "addr:housenumber":"2",
    "addr:postcode":"7972",
    "addr:street":"Place D'Ellignies",
    "iso:country":"BE",
    "sg:address":"Place D'ellignies 2",
    "sg:city":"Beloeil (ellignies-sainte-anne)",
    "sg:classifiers":[
        {
            "category":"Retail",
            "subcategory":"Veterinary Services",
            "type":"Services"
        }
    ],
    "sg:phone":"+32 69 68 94 22",
    "sg:postcode":"7972",
    "sg:province":"Hainaut",
    "sg:tags":[
        "veterinarian"
    ],
    "wof:name":"Van De Velde M",
    "wof:placetype":"venue"
},
  "geometry": {"coordinates":[3.6726679802,50.5625801086],"type":"Point"}
}