{
  "type": "Feature",
  "properties": {
    "addr:full":"Avenue Du Centenaire 12 Charleroi (montignies-sur-sambre) Hainaut 6061",
    "addr:housenumber":"12",
    "addr:postcode":"6061",
    "addr:street":"Avenue Du Centenaire",
    "iso:country":"BE",
    "sg:address":"Avenue Du Centenaire 12",
    "sg:city":"Charleroi (montignies-sur-sambre)",
    "sg:orig_category":"Non-Classified Establishments",
    "sg:phone":"+32 71 31 11 11",
    "sg:postcode":"6061",
    "sg:province":"Hainaut",
    "wof:name":"Bailleux G Sprl",
    "wof:placetype":"venue"
},
  "geometry": {"coordinates":[4.479224205,50.4014396667],"type":"Point"}
}