{
  "type": "Feature",
  "properties": {
    "addr:full":"Burgemeester Potiaulaan 54 Dendermonde (sint-gillis-bij-dendermonde) Oost-Vlaanderen 9200",
    "addr:housenumber":"54",
    "addr:postcode":"9200",
    "addr:street":"Burgemeester Potiaulaan",
    "iso:country":"BE",
    "sg:address":"Burgemeester Potiaulaan 54",
    "sg:city":"Dendermonde (sint-gillis-bij-dendermonde)",
    "sg:classifiers":[
        {
            "category":"Home & Garden",
            "subcategory":"Building Materials",
            "type":"Retail Goods"
        }
    ],
    "sg:phone":"+32 52 20 17 46",
    "sg:postcode":"9200",
    "sg:province":"Oost-Vlaanderen",
    "sg:tags":[
        "window"
    ],
    "wof:name":"Pieters W",
    "wof:placetype":"venue"
},
  "geometry": {"coordinates":[4.112760067,51.0204963684],"type":"Point"}
}