{
  "type": "Feature",
  "properties": {
    "addr:full":"Oostmalsebaan 24 Sint-lenaarts Antwerpen 2960",
    "addr:housenumber":"24",
    "addr:postcode":"2960",
    "addr:street":"Oostmalsebaan",
    "iso:country":"BE",
    "sg:address":"Oostmalsebaan 24",
    "sg:city":"Sint-lenaarts",
    "sg:orig_category":"Mazda. V\u00e9hicules automobiles. Entretien and r\u00e9parations de voitures. Stations-service and carburants",
    "sg:phone":"+32 3 313 89 09",
    "sg:postcode":"2960",
    "sg:province":"Antwerpen",
    "wof:name":"Garage Van Roy-de Vries",
    "wof:placetype":"venue"
},
  "geometry": {"coordinates":[4.6831998825,51.3420219421],"type":"Point"}
}