{
  "type": "Feature",
  "properties": {
    "iso:country":"BE",
    "sg:address":"Oostendelaan 3",
    "sg:city":"Middelkerke",
    "sg:classifiers":[
        {
            "category":"Cafe",
            "type":"Food & Drink"
        }
    ],
    "sg:phone":"+32 59 31 54 14",
    "sg:postcode":"8430",
    "sg:province":"West-Vlaanderen",
    "sg:tags":[
        "caf\u00e9s"
    ],
    "wof:name":"Caf\u00c9 Picasso",
    "wof:placetype":"venue"
},
  "geometry": {"coordinates":[2.822439909,51.1859397888],"type":"Point"}
}