{
  "type": "Feature",
  "properties": {
    "addr:full":"Septakkers 119 Lommel Limburg 3920",
    "addr:housenumber":"119",
    "addr:postcode":"3920",
    "addr:street":"Septakkers",
    "iso:country":"BE",
    "sg:address":"Septakkers 119",
    "sg:city":"Lommel",
    "sg:classifiers":[
        {
            "category":"Real Estate",
            "subcategory":"Architect",
            "type":"Services"
        }
    ],
    "sg:phone":"+32 11 54 28 53",
    "sg:postcode":"3920",
    "sg:province":"Limburg",
    "wof:name":"Van Beeck W",
    "wof:placetype":"venue"
},
  "geometry": {"coordinates":[5.3326878548,51.2295608521],"type":"Point"}
}