{
  "type": "Feature",
  "properties": {
    "iso:country":"BE",
    "sg:address":"Weegse 57",
    "sg:city":"Evergem",
    "sg:orig_category":"Sportcentra",
    "sg:phone":"+32 9 357 21 20",
    "sg:postcode":"9940",
    "sg:province":"Oost-Vlaanderen",
    "wof:name":"Cocquyt",
    "wof:placetype":"venue"
},
  "geometry": {"coordinates":[3.660836935,51.1231842041],"type":"Point"}
}