{
  "type": "Feature",
  "properties": {
    "addr:full":"Chauss\u00e9e De Bruxelles 292a Nivelles (baulers) Brabant Wallon 1401",
    "addr:housenumber":"292a;1401",
    "addr:street":"Chausse\u0301E De Bruxelles",
    "iso:country":"BE",
    "sg:address":"Chauss\u00e9e De Bruxelles 292a",
    "sg:city":"Nivelles (baulers)",
    "sg:classifiers":[
        {
            "category":"Recreation",
            "subcategory":"Arcade",
            "type":"Entertainment"
        }
    ],
    "sg:phone":"+32 67 77 26 82",
    "sg:postcode":"1401",
    "sg:province":"Brabant Wallon",
    "sg:tags":[
        "machine",
        "amusement"
    ],
    "wof:name":"Automatique Brabant Sprl",
    "wof:placetype":"venue"
},
  "geometry": {"coordinates":[4.349339962,50.6256599426],"type":"Point"}
}