{
  "type": "Feature",
  "properties": {
    "addr:full":"Eikenlaan 32 Zwevegem West-Vlaanderen 8553",
    "addr:housenumber":"32",
    "addr:postcode":"8553",
    "addr:street":"Eikenlaan",
    "iso:country":"BE",
    "sg:address":"Eikenlaan 32",
    "sg:city":"Zwevegem",
    "sg:orig_category":"D\u00e9molition d\u00b4immeubles and terrassements",
    "sg:phone":"+32 56 77 77 74",
    "sg:postcode":"8553",
    "sg:province":"West-Vlaanderen",
    "wof:name":"Dessein Lieven",
    "wof:placetype":"venue"
},
  "geometry": {"coordinates":[3.4151499271,50.808303833],"type":"Point"}
}