{
  "type": "Feature",
  "properties": {
    "addr:full":"Busselen 15 Westerlo (tongerlo) Antwerpen 2260",
    "addr:housenumber":"15",
    "addr:postcode":"2260",
    "addr:street":"Busselen",
    "iso:country":"BE",
    "sg:address":"Busselen 15",
    "sg:city":"Westerlo (tongerlo)",
    "sg:classifiers":[
        {
            "category":"Health Services",
            "subcategory":"Doctor",
            "type":"Services"
        }
    ],
    "sg:phone":"+32 14 26 57 11",
    "sg:postcode":"2260",
    "sg:province":"Antwerpen",
    "sg:tags":[
        "medicinephysicians",
        "surgeon"
    ],
    "wof:name":"Lenaerts M",
    "wof:placetype":"venue"
},
  "geometry": {"coordinates":[4.8704710007,51.1246986389],"type":"Point"}
}