{
  "type": "Feature",
  "properties": {
    "addr:full":"Violierstraat 20 Gent Oost-Vlaanderen 9000",
    "addr:housenumber":"20",
    "addr:postcode":"9000",
    "addr:street":"Violierstraat;Oost-Vlaanderen",
    "iso:country":"BE",
    "sg:address":"Violierstraat 20",
    "sg:city":"Gent",
    "sg:orig_category":"Animations diverses",
    "sg:phone":"+32 9 227 06 33",
    "sg:postcode":"9000",
    "sg:province":"Oost-Vlaanderen",
    "wof:name":"Mike's Discobar - Studio 3000",
    "wof:placetype":"venue"
},
  "geometry": {"coordinates":[3.6945450306,51.0616798401],"type":"Point"}
}