{
  "type": "Feature",
  "properties": {
    "addr:full":"Kapellestraat 77bg15 Tervuren Vlaams-Brabant 3080",
    "addr:housenumber":"77bg15",
    "addr:postcode":"3080",
    "addr:street":"Kapellestraat",
    "iso:country":"BE",
    "sg:address":"Kapellestraat 77bg15",
    "sg:city":"Tervuren",
    "sg:orig_category":"Imprimeries and copyshops",
    "sg:phone":"+32 2 767 41 04",
    "sg:postcode":"3080",
    "sg:province":"Vlaams-Brabant",
    "wof:name":"Claudia De Broyer",
    "wof:placetype":"venue"
},
  "geometry": {"coordinates":[4.5070099831,50.8209152222],"type":"Point"}
}