{
  "type": "Feature",
  "properties": {
    "iso:country":"BE",
    "sg:address":"Carrestraat 25",
    "sg:city":"Koekelare",
    "sg:orig_category":"Domotics",
    "sg:phone":"+32 51 58 41 45",
    "sg:postcode":"8680",
    "sg:province":"West-Vlaanderen",
    "wof:name":"Kali",
    "wof:placetype":"venue"
},
  "geometry": {"coordinates":[2.9666829109,51.0670318604],"type":"Point"}
}