{
  "type": "Feature",
  "properties": {
    "iso:country":"BE",
    "sg:address":"Loksbergenstraat 49",
    "sg:city":"Halen",
    "sg:classifiers":[
        {
            "category":"Health Services",
            "subcategory":"Health Practitioner",
            "type":"Services"
        }
    ],
    "sg:phone":"+32 13 44 11 61",
    "sg:postcode":"3545",
    "sg:province":"Limburg",
    "sg:tags":[
        "physiotherapist"
    ],
    "wof:name":"Dox M",
    "wof:placetype":"venue"
},
  "geometry": {"coordinates":[5.0674748421,50.9331932068],"type":"Point"}
}