{
  "type": "Feature",
  "properties": {
    "iso:country":"BE",
    "sg:address":"Route De Poix 70",
    "sg:city":"Saint-hubert",
    "sg:orig_category":"Fiduciairies",
    "sg:phone":"+32 61 61 15 27",
    "sg:postcode":"6870",
    "sg:province":"Luxembourg",
    "wof:name":"Godenir M",
    "wof:placetype":"venue"
},
  "geometry": {"coordinates":[5.3510308266,50.0235023499],"type":"Point"}
}