{
  "type": "Feature",
  "properties": {
    "addr:full":"Potaardestraat 74unit 19 Niel Antwerpen 2845",
    "addr:housenumber":"74unit 19",
    "addr:postcode":"2845",
    "addr:street":"Potaardestraat",
    "iso:country":"BE",
    "sg:address":"Potaardestraat 74unit 19",
    "sg:city":"Niel",
    "sg:classifiers":[
        {
            "category":"Shopping",
            "subcategory":"Stationery & Office Supplies",
            "type":"Retail Goods"
        }
    ],
    "sg:phone":"+32 3 844 59 07",
    "sg:postcode":"2845",
    "sg:province":"Antwerpen",
    "sg:tags":[
        "furniture"
    ],
    "wof:name":"New Office Nv",
    "wof:placetype":"venue"
},
  "geometry": {"coordinates":[4.3609418869,51.1059036255],"type":"Point"}
}