{
  "type": "Feature",
  "properties": {
    "addr:full":"Kapellstrasse 13a Kelmis Li\u00e8ge 4720",
    "addr:housenumber":"13a",
    "addr:postcode":"4720",
    "addr:street":"Kapellstrasse",
    "iso:country":"BE",
    "sg:address":"Kapellstrasse 13a",
    "sg:city":"Kelmis",
    "sg:classifiers":[
        {
            "category":"Personal",
            "subcategory":"Beauty Salon",
            "type":"Services"
        }
    ],
    "sg:phone":"+32 87 63 15 00",
    "sg:postcode":"4720",
    "sg:province":"Li\u00e8ge",
    "sg:tags":[
        "lady",
        "-",
        "hairdressing"
    ],
    "wof:name":"Hair Styling Center",
    "wof:placetype":"venue"
},
  "geometry": {"coordinates":[6.0132718086,50.7149353027],"type":"Point"}
}