{
  "type": "Feature",
  "properties": {
    "addr:full":"Sint-antionusstraat 1 Essen Antwerpen 2910",
    "addr:housenumber":"1",
    "addr:postcode":"2910",
    "addr:street":"Sint-Antionusstraat",
    "iso:country":"BE",
    "sg:address":"Sint-antionusstraat 1",
    "sg:city":"Essen",
    "sg:orig_category":"Pain, p\u00e2tisseries and confiseries",
    "sg:phone":"+32 3 667 63 00",
    "sg:postcode":"2910",
    "sg:province":"Antwerpen",
    "wof:name":"Bakkerij Bagatelle",
    "wof:placetype":"venue"
},
  "geometry": {"coordinates":[4.4556188583,51.46326828],"type":"Point"}
}