{
  "type": "Feature",
  "properties": {
    "addr:full":"Dikke Lindelaan 2 Brussel/bruxelles Bruxelles-Capitale 1020",
    "addr:housenumber":"2",
    "addr:postcode":"1020",
    "addr:street":"Lindelaan;/",
    "iso:country":"BE",
    "sg:address":"Dikke Lindelaan 2",
    "sg:city":"Brussel/bruxelles",
    "sg:classifiers":[
        {
            "category":"Communications",
            "subcategory":"Radio Station",
            "type":"Services"
        }
    ],
    "sg:phone":"+32 2 741 41 11",
    "sg:postcode":"1020",
    "sg:province":"Bruxelles-Capitale",
    "sg:tags":[
        "diffusion",
        "production",
        "de",
        "programme"
    ],
    "wof:name":"V.r.t.",
    "wof:placetype":"venue"
},
  "geometry": {"coordinates":[4.3465080261,50.8932952881],"type":"Point"}
}