{
  "type": "Feature",
  "properties": {
    "iso:country":"BE",
    "sg:address":"Weststraat 58",
    "sg:city":"Ingelmunster",
    "sg:classifiers":[
        {
            "category":"Insurance",
            "subcategory":"Insurance Agent",
            "type":"Services"
        }
    ],
    "sg:phone":"+32 51 30 47 97",
    "sg:postcode":"8770",
    "sg:province":"West-Vlaanderen",
    "sg:tags":[
        "broker"
    ],
    "wof:name":"Olivier-vanoutrive Cv",
    "wof:placetype":"venue"
},
  "geometry": {"coordinates":[3.2495338917,50.9215583801],"type":"Point"}
}