{
  "type": "Feature",
  "properties": {
    "addr:full":"Stationsstraat 63 Sint-pieters-leeuw Vlaams-Brabant 1601",
    "addr:housenumber":"63",
    "addr:postcode":"1601",
    "addr:street":"Stationsstraat",
    "iso:country":"BE",
    "sg:address":"Stationsstraat 63",
    "sg:city":"Sint-pieters-leeuw",
    "sg:classifiers":[
        {
            "category":"Cafe",
            "type":"Food & Drink"
        }
    ],
    "sg:phone":"+32 2 378 02 87",
    "sg:postcode":"1601",
    "sg:province":"Vlaams-Brabant",
    "sg:tags":[
        "caf\u00e9s"
    ],
    "wof:name":"M-therese Demeyere",
    "wof:placetype":"venue"
},
  "geometry": {"coordinates":[4.2950072289,50.7904014587],"type":"Point"}
}