{
  "type": "Feature",
  "properties": {
    "iso:country":"BE",
    "sg:address":"Rue Guillaume Maisier 37",
    "sg:city":"Limbourg",
    "sg:classifiers":[
        {
            "category":"Insurance",
            "subcategory":"Life Insurance",
            "type":"Services"
        }
    ],
    "sg:phone":"+32 87 76 33 08",
    "sg:postcode":"4830",
    "sg:province":"Li\u00e8ge",
    "sg:tags":[
        "assurance"
    ],
    "wof:name":"P. Dejardin",
    "wof:placetype":"venue"
},
  "geometry": {"coordinates":[5.9407401085,50.6112518311],"type":"Point"}
}