{
  "type": "Feature",
  "properties": {
    "iso:country":"BE",
    "sg:address":"Dorpstraat 110g",
    "sg:city":"Ranst",
    "sg:orig_category":"Beautyfarms, relaxatie and lichamelijk welzijn Schoonheidssalons",
    "sg:phone":"+32 3 480 79 87",
    "sg:postcode":"2520",
    "sg:province":"Antwerpen",
    "wof:name":"Instituut Elle",
    "wof:placetype":"venue"
},
  "geometry": {"coordinates":[4.5996818542,51.1612968445],"type":"Point"}
}