{
  "type": "Feature",
  "properties": {
    "iso:country":"BE",
    "sg:address":"Blauwesteenstraat 87",
    "sg:city":"Kontich",
    "sg:classifiers":[
        {
            "category":"Professional",
            "subcategory":"Testing Lab",
            "type":"Services"
        }
    ],
    "sg:phone":"+32 3 457 78 20",
    "sg:postcode":"2550",
    "sg:province":"Antwerpen",
    "sg:tags":[
        "laboratory",
        "photographic",
        "film"
    ],
    "wof:name":"Rainbow Color Nv",
    "wof:placetype":"venue"
},
  "geometry": {"coordinates":[4.4505882263,51.1266098022],"type":"Point"}
}