{
  "type": "Feature",
  "properties": {
    "addr:full":"Rue Du S\u00e9woir 19a Lens Hainaut 7870",
    "addr:housenumber":"19a",
    "addr:postcode":"7870",
    "addr:street":"Rue Du Se\u0301Woir",
    "iso:country":"BE",
    "sg:address":"Rue Du S\u00e9woir 19a",
    "sg:city":"Lens",
    "sg:classifiers":[
        {
            "category":"Professional",
            "subcategory":"Testing Lab",
            "type":"Services"
        }
    ],
    "sg:phone":"+32 65 22 95 71",
    "sg:postcode":"7870",
    "sg:province":"Hainaut",
    "sg:tags":[
        "chemist"
    ],
    "wof:name":"Frebutte J",
    "wof:placetype":"venue"
},
  "geometry": {"coordinates":[3.9004189968,50.5546455383],"type":"Point"}
}