{
  "type": "Feature",
  "properties": {
    "iso:country":"BE",
    "sg:address":"Rue D\u00c9lestienne 2",
    "sg:city":"Charleroi",
    "sg:orig_category":"Herstelling leer and schoeisel",
    "sg:phone":"+32 71 47 13 30",
    "sg:postcode":"6001",
    "sg:province":"Hainaut",
    "wof:name":"Cordonnerie Patrick",
    "wof:placetype":"venue"
},
  "geometry": {"coordinates":[4.4471201897,50.3994407654],"type":"Point"}
}