{
  "type": "Feature",
  "properties": {
    "iso:country":"BE",
    "sg:address":"Rue Saint-gilles 14",
    "sg:city":"Saint-hubert",
    "sg:orig_category":"V\u00eatements pour Hommes",
    "sg:phone":"+32 61 61 22 58",
    "sg:postcode":"6870",
    "sg:province":"Luxembourg",
    "wof:name":"Boutique Geoffrey",
    "wof:placetype":"venue"
},
  "geometry": {"coordinates":[5.3724918365,50.0261268616],"type":"Point"}
}