{
  "type": "Feature",
  "properties": {
    "addr:full":"Dokter Dejaselaan 22 Schaarbeek/schaerbeek Bruxelles-Capitale 1030",
    "addr:housenumber":"22",
    "addr:postcode":"1030",
    "addr:street":"Dokter Dejaselaan",
    "iso:country":"BE",
    "sg:address":"Dokter Dejaselaan 22",
    "sg:city":"Schaarbeek/schaerbeek",
    "sg:orig_category":"Postkantoren Verzekeringsmakelaars and experts",
    "sg:phone":"+32 2 215 28 85",
    "sg:postcode":"1030",
    "sg:province":"Bruxelles-Capitale",
    "wof:name":"De Post",
    "wof:placetype":"venue"
},
  "geometry": {"coordinates":[4.3895401955,50.8691329956],"type":"Point"}
}