{
  "type": "Feature",
  "properties": {
    "addr:full":"Rue De Liberchies 216 Tournai Hainaut 7532",
    "addr:housenumber":"216",
    "addr:postcode":"7532",
    "addr:street":"Rue De Liberchies",
    "iso:country":"BE",
    "sg:address":"Rue De Liberchies 216",
    "sg:city":"Tournai",
    "sg:orig_category":"Rundveehouders",
    "sg:phone":"+32 69 54 71 59",
    "sg:postcode":"7532",
    "sg:province":"Hainaut",
    "wof:name":"Lucien Soudant",
    "wof:placetype":"venue"
},
  "geometry": {"coordinates":[3.5090808868,50.6097793579],"type":"Point"}
}