{
  "type": "Feature",
  "properties": {
    "addr:full":"Beneluxlaan 1 Zelzate Oost-Vlaanderen 9060",
    "addr:housenumber":"1",
    "addr:postcode":"9060",
    "addr:street":"Beneluxlaan",
    "iso:country":"BE",
    "sg:address":"Beneluxlaan 1",
    "sg:city":"Zelzate",
    "sg:classifiers":[
        {
            "category":"Professional",
            "subcategory":"Business Services",
            "type":"Services"
        }
    ],
    "sg:phone":"+32 9 344 50 23",
    "sg:postcode":"9060",
    "sg:province":"Oost-Vlaanderen",
    "sg:tags":[
        "consultant",
        "custom"
    ],
    "wof:name":"Claeys Zelzate",
    "wof:placetype":"venue"
},
  "geometry": {"coordinates":[3.7997100353,51.2026863098],"type":"Point"}
}