{
  "type": "Feature",
  "properties": {
    "iso:country":"BE",
    "sg:address":"Rue Gospert 112",
    "sg:city":"Eupen",
    "sg:orig_category":"Jeux de hasard. Caf\u00e9s",
    "sg:phone":"+32 87 74 27 66",
    "sg:postcode":"4700",
    "sg:province":"Li\u00e8ge",
    "wof:name":"Pmu",
    "wof:placetype":"venue"
},
  "geometry": {"coordinates":[6.0373778343,50.6328201294],"type":"Point"}
}