{
  "type": "Feature",
  "properties": {
    "iso:country":"BE",
    "sg:address":"Hoevenzavellaan 59",
    "sg:city":"Genk (waterschei)",
    "sg:orig_category":"Newspapers, magazines, periodicals - Distribution",
    "sg:phone":"+32 89 38 26 56",
    "sg:postcode":"3600",
    "sg:province":"Limburg",
    "wof:name":"Vandeschoor J",
    "wof:placetype":"venue"
},
  "geometry": {"coordinates":[5.5071091652,51.0008468628],"type":"Point"}
}