{
  "type": "Feature",
  "properties": {
    "addr:full":"Chemin De Hoevel 19 Baelen Li\u00e8ge 4837",
    "addr:housenumber":"19",
    "addr:postcode":"4837",
    "addr:street":"Chemin De Hoevel",
    "iso:country":"BE",
    "sg:address":"Chemin De Hoevel 19",
    "sg:city":"Baelen",
    "sg:orig_category":"Afbraak- and draineerwerken",
    "sg:phone":"+32 87 76 43 89",
    "sg:postcode":"4837",
    "sg:province":"Li\u00e8ge",
    "wof:name":"Campo & Fils",
    "wof:placetype":"venue"
},
  "geometry": {"coordinates":[5.9735121727,50.6275253296],"type":"Point"}
}