{
  "type": "Feature",
  "properties": {
    "addr:full":"Venderstraat 18 Kinrooi Limburg 3640",
    "addr:housenumber":"18",
    "addr:postcode":"3640",
    "addr:street":"Venderstraat",
    "iso:country":"BE",
    "sg:address":"Venderstraat 18",
    "sg:city":"Kinrooi",
    "sg:orig_category":"Installatie van houten of kunststof schrijnwerk",
    "sg:phone":"+32 89 70 15 34",
    "sg:postcode":"3640",
    "sg:province":"Limburg",
    "wof:name":"Pierre Baens",
    "wof:placetype":"venue"
},
  "geometry": {"coordinates":[5.7355451584,51.1674613953],"type":"Point"}
}