{
  "type": "Feature",
  "properties": {
    "iso:country":"BE",
    "sg:address":"Noordster 18",
    "sg:city":"Kuurne",
    "sg:classifiers":[
        {
            "category":"Banks & Credit Unions",
            "subcategory":"Investment Brokerage",
            "type":"Services"
        }
    ],
    "sg:phone":"+32 56 35 58 60",
    "sg:postcode":"8520",
    "sg:province":"West-Vlaanderen",
    "sg:tags":[
        "fence"
    ],
    "wof:name":"Blondeel P",
    "wof:placetype":"venue"
},
  "geometry": {"coordinates":[3.2675979137,50.8625679016],"type":"Point"}
}