{
  "type": "Feature",
  "properties": {
    "addr:full":"Broelstraat 20 Harelbeke West-Vlaanderen 8530",
    "addr:housenumber":"20",
    "addr:postcode":"8530",
    "addr:street":"Broelstraat",
    "iso:country":"BE",
    "sg:address":"Broelstraat 20",
    "sg:city":"Harelbeke",
    "sg:classifiers":[
        {
            "category":"Military Area",
            "subcategory":"Restricted Area",
            "type":"Public Place"
        }
    ],
    "sg:phone":"+32 56 73 21 21",
    "sg:postcode":"8530",
    "sg:province":"West-Vlaanderen",
    "sg:tags":[
        "mfrs",
        "silo"
    ],
    "wof:name":"Geldof Metaalconstructie Nv",
    "wof:placetype":"venue"
},
  "geometry": {"coordinates":[3.3084290028,50.8596916199],"type":"Point"}
}