{
  "type": "Feature",
  "properties": {
    "addr:full":"Meridiaanlaan 48 Genk (waterschei) Limburg 3600",
    "addr:housenumber":"48",
    "addr:postcode":"3600",
    "addr:street":"Meridiaanlaan",
    "iso:country":"BE",
    "sg:address":"Meridiaanlaan 48",
    "sg:city":"Genk (waterschei)",
    "sg:classifiers":[
        {
            "category":"Retail",
            "subcategory":"Car Wash",
            "type":"Services"
        }
    ],
    "sg:phone":"+32 89 38 04 46",
    "sg:postcode":"3600",
    "sg:province":"Limburg",
    "sg:tags":[
        "automobile",
        "washing",
        "-",
        "truck"
    ],
    "wof:name":"Horun & Nuri",
    "wof:placetype":"venue"
},
  "geometry": {"coordinates":[5.5319328308,51.0007400513],"type":"Point"}
}