{
  "type": "Feature",
  "properties": {
    "iso:country":"BE",
    "sg:address":"Koolmijnlaan 118",
    "sg:city":"Heusden-zolder",
    "sg:orig_category":"Baby- and kinderkleding",
    "sg:phone":"+32 11 57 54 73",
    "sg:postcode":"3550",
    "sg:province":"Limburg",
    "wof:name":"Sema",
    "wof:placetype":"venue"
},
  "geometry": {"coordinates":[5.3022260666,51.0399398804],"type":"Point"}
}