{
  "type": "Feature",
  "properties": {
    "addr:full":"Place Du Vieux March\u00e9 41-50 Enghien Hainaut 7850",
    "addr:postcode":"41-50;7850",
    "addr:street":"Place Du Vieux Marche\u0301;Hainaut",
    "iso:country":"BE",
    "sg:address":"Place Du Vieux March\u00e9 41-50",
    "sg:city":"Enghien",
    "sg:classifiers":[
        {
            "category":"Retail",
            "subcategory":"Funeral Services",
            "type":"Services"
        }
    ],
    "sg:phone":"+32 2 395 33 85",
    "sg:postcode":"7850",
    "sg:province":"Hainaut",
    "sg:tags":[
        "director"
    ],
    "wof:name":"Lucas-durant",
    "wof:placetype":"venue"
},
  "geometry": {"coordinates":[4.044178009,50.6952667236],"type":"Point"}
}