{
  "type": "Feature",
  "properties": {
    "iso:country":"BE",
    "sg:address":"Heidestraat 11",
    "sg:city":"Gooik",
    "sg:orig_category":"Installatie van houten of kunststof schrijnwerk",
    "sg:phone":"+32 54 56 81 49",
    "sg:postcode":"1755",
    "sg:province":"Vlaams-Brabant",
    "wof:name":"Eddy Graser",
    "wof:placetype":"venue"
},
  "geometry": {"coordinates":[4.1062240601,50.7735977173],"type":"Point"}
}