{
  "type": "Feature",
  "properties": {
    "iso:country":"BE",
    "sg:address":"Rue Grande 63",
    "sg:city":"Anhee",
    "sg:orig_category":"R\u00e9parations de chaussures and articles en cuir",
    "sg:phone":"+32 82 61 22 16",
    "sg:postcode":"5537",
    "sg:province":"Namur",
    "wof:name":"Andre Leonard",
    "wof:placetype":"venue"
},
  "geometry": {"coordinates":[4.8770208359,50.3113136292],"type":"Point"}
}