{
  "type": "Feature",
  "properties": {
    "iso:country":"BE",
    "sg:address":"Beekstraat 25",
    "sg:city":"Ronse/renaix",
    "sg:orig_category":"Dakwerken Loodgieterij, verwarming and sanitaire installaties",
    "sg:phone":"+32 55 21 76 24",
    "sg:postcode":"9600",
    "sg:province":"Oost-Vlaanderen",
    "wof:name":"Van Cromphaut Eric",
    "wof:placetype":"venue"
},
  "geometry": {"coordinates":[3.6051089764,50.7505531311],"type":"Point"}
}