{
  "type": "Feature",
  "properties": {
    "addr:full":"Rue Antoine Dansaert 114 Bruxelles Bruxelles-Capitale 1000",
    "addr:housenumber":"114",
    "addr:postcode":"1000",
    "addr:street":"Rue Antoine Dansaert",
    "iso:country":"BE",
    "sg:address":"Rue Antoine Dansaert 114",
    "sg:city":"Bruxelles",
    "sg:classifiers":[
        {
            "category":"Shopping",
            "subcategory":"Books",
            "type":"Retail Goods"
        }
    ],
    "sg:phone":"+32 2 511 71 16",
    "sg:postcode":"1000",
    "sg:province":"Bruxelles-Capitale",
    "sg:tags":[
        "bookseller"
    ],
    "wof:name":"Max",
    "wof:placetype":"venue"
},
  "geometry": {"coordinates":[4.3438258171,50.8519325256],"type":"Point"}
}