{
  "type": "Feature",
  "properties": {
    "addr:full":"Mechelse Steenweg 157 Antwerpen Antwerpen 2018",
    "addr:housenumber":"157",
    "addr:postcode":"2018",
    "addr:street":"Steenweg",
    "iso:country":"BE",
    "sg:address":"Mechelse Steenweg 157",
    "sg:city":"Antwerpen",
    "sg:classifiers":[
        {
            "category":"Real Estate",
            "subcategory":"Real Estate Services",
            "type":"Services"
        }
    ],
    "sg:phone":"+32 3 230 59 39",
    "sg:postcode":"2018",
    "sg:province":"Antwerpen",
    "wof:name":"Immo Berg",
    "wof:placetype":"venue"
},
  "geometry": {"coordinates":[4.410905838,51.2049865723],"type":"Point"}
}