{
  "type": "Feature",
  "properties": {
    "iso:country":"BE",
    "sg:address":"Vindictivelaan 34",
    "sg:city":"Oostende",
    "sg:classifiers":[
        {
            "category":"Bars & Pubs",
            "type":"Food & Drink"
        }
    ],
    "sg:phone":"+32 59 70 24 70",
    "sg:postcode":"8400",
    "sg:province":"West-Vlaanderen",
    "sg:tags":[
        "tavern"
    ],
    "wof:name":"Brasserie De La Gare",
    "wof:placetype":"venue"
},
  "geometry": {"coordinates":[2.9235870838,51.2293701172],"type":"Point"}
}