{
  "type": "Feature",
  "properties": {
    "addr:full":"Rue Des Pr\u00c9s 1 Merbes-le-ch\u00c2teau Hainaut 6567",
    "addr:housenumber":"1",
    "addr:postcode":"6567",
    "addr:street":"Rue Des Pre\u0301S",
    "iso:country":"BE",
    "sg:address":"Rue Des Pr\u00c9s 1",
    "sg:city":"Merbes-le-ch\u00c2teau",
    "sg:orig_category":"Artiesten and kunstenaars",
    "sg:phone":"+32 71 55 76 89",
    "sg:postcode":"6567",
    "sg:province":"Hainaut",
    "wof:name":"Michel Delaere",
    "wof:placetype":"venue"
},
  "geometry": {"coordinates":[4.2119641304,50.3227653503],"type":"Point"}
}