{
  "type": "Feature",
  "properties": {
    "addr:full":"Place L\u00c9on D'andrimont 27 Limbourg Li\u00e8ge 4830",
    "addr:housenumber":"27",
    "addr:postcode":"4830",
    "addr:street":"Place Le\u0301On D'Andrimont",
    "iso:country":"BE",
    "sg:address":"Place L\u00c9on D'andrimont 27",
    "sg:city":"Limbourg",
    "sg:orig_category":"Banques and organismes de cr\u00e9dit",
    "sg:phone":"+32 87 76 21 49",
    "sg:postcode":"4830",
    "sg:province":"Li\u00e8ge",
    "wof:name":"Dreze Banque",
    "wof:placetype":"venue"
},
  "geometry": {"coordinates":[5.9412178993,50.6207809448],"type":"Point"}
}