{
  "type": "Feature",
  "properties": {
    "addr:full":"Pijperzele 71 Zottegem Oost-Vlaanderen 9620",
    "addr:housenumber":"71",
    "addr:postcode":"9620",
    "addr:street":"Pijperzele",
    "iso:country":"BE",
    "sg:address":"Pijperzele 71",
    "sg:city":"Zottegem",
    "sg:orig_category":"Elektrische installaties voor woningen Industri\u00eble elektrische installaties",
    "sg:phone":"+32 55 42 41 25",
    "sg:postcode":"9620",
    "sg:province":"Oost-Vlaanderen",
    "wof:name":"De Smet-van Damme",
    "wof:placetype":"venue"
},
  "geometry": {"coordinates":[3.8112111092,50.871181488],"type":"Point"}
}