{
  "type": "Feature",
  "properties": {
    "addr:full":"Boulevard D\u00b4avroy 55/001 Li\u00c8ge Li\u00e8ge 4000",
    "addr:housenumber":"55 / 001",
    "addr:postcode":"4000",
    "addr:street":"Boulevard D\u00b4Avroy",
    "iso:country":"BE",
    "sg:address":"Boulevard D\u00b4avroy 55/001",
    "sg:city":"Li\u00c8ge",
    "sg:orig_category":"Services divers aux entreprises. Agences immobili\u00e8res",
    "sg:phone":"+32 4 223 38 25",
    "sg:postcode":"4000",
    "sg:province":"Li\u00e8ge",
    "wof:name":"Century 21 Bureau Blavier",
    "wof:placetype":"venue"
},
  "geometry": {"coordinates":[5.5687260628,50.6371192932],"type":"Point"}
}