{
  "type": "Feature",
  "properties": {
    "addr:full":"Dr\u00e8ve Des Chevreuils 2 Braine-le-comte Hainaut 7090",
    "addr:housenumber":"2",
    "addr:postcode":"7090",
    "addr:street":"Dre\u0300Ve Des Chevreuils",
    "iso:country":"BE",
    "sg:address":"Dr\u00e8ve Des Chevreuils 2",
    "sg:city":"Braine-le-comte",
    "sg:classifiers":[
        {
            "category":"Social Services",
            "subcategory":"Child Care",
            "type":"Services"
        }
    ],
    "sg:phone":"+32 67 87 87 72",
    "sg:postcode":"7090",
    "sg:province":"Hainaut",
    "sg:tags":[
        "baby",
        "nursery",
        "day",
        "sitting"
    ],
    "wof:name":"Assoc Gard Enfants Hainaut",
    "wof:placetype":"venue"
},
  "geometry": {"coordinates":[4.1662201881,50.6051139832],"type":"Point"}
}