{
  "type": "Feature",
  "properties": {
    "iso:country":"BE",
    "sg:address":"Rue Vive Al'rue 3",
    "sg:city":"Mettet",
    "sg:classifiers":[
        {
            "category":"Personal",
            "subcategory":"Beauty Salon",
            "type":"Services"
        }
    ],
    "sg:phone":"+32 71 72 78 54",
    "sg:postcode":"5640",
    "sg:province":"Namur",
    "sg:tags":[
        "de",
        "coiffure"
    ],
    "wof:name":"Renee Samson",
    "wof:placetype":"venue"
},
  "geometry": {"coordinates":[4.6789970398,50.2981719971],"type":"Point"}
}