{
  "type": "Feature",
  "properties": {
    "addr:full":"Gerststraat 13 Lommel Limburg 3920",
    "addr:housenumber":"13",
    "addr:postcode":"3920",
    "addr:street":"Gerststraat",
    "iso:country":"BE",
    "sg:address":"Gerststraat 13",
    "sg:city":"Lommel",
    "sg:orig_category":"Eleveurs de bovins",
    "sg:phone":"+32 11 54 44 73",
    "sg:postcode":"3920",
    "sg:province":"Limburg",
    "wof:name":"Bernardus Faes",
    "wof:placetype":"venue"
},
  "geometry": {"coordinates":[5.285738945,51.17993927],"type":"Point"}
}