{
  "type": "Feature",
  "properties": {
    "addr:full":"Rue Marianne 12 Bruxelles (uccle) Bruxelles-Capitale 1180",
    "addr:housenumber":"12",
    "addr:postcode":"1180",
    "addr:street":"Rue Marianne",
    "iso:country":"BE",
    "sg:address":"Rue Marianne 12",
    "sg:city":"Bruxelles (uccle)",
    "sg:classifiers":[
        {
            "category":"Personal",
            "subcategory":"Psychics & Astrologers",
            "type":"Services"
        }
    ],
    "sg:phone":"+32 2 345 31 46",
    "sg:postcode":"1180",
    "sg:province":"Bruxelles-Capitale",
    "sg:tags":[
        "astrology"
    ],
    "wof:name":"Marijan",
    "wof:placetype":"venue"
},
  "geometry": {"coordinates":[4.3521327972,50.8136367798],"type":"Point"}
}