{
  "type": "Feature",
  "properties": {
    "addr:full":"Leopoldstraat 48 Zemst Vlaams-Brabant 1980",
    "addr:housenumber":"48",
    "addr:postcode":"1980",
    "addr:street":"Leopoldstraat;Vlaams-Brabant",
    "iso:country":"BE",
    "sg:address":"Leopoldstraat 48",
    "sg:city":"Zemst",
    "sg:classifiers":[
        {
            "category":"Food & Beverages",
            "subcategory":"Fruits & Vegetables",
            "type":"Retail Goods"
        }
    ],
    "sg:phone":"+32 15 61 25 36",
    "sg:postcode":"1980",
    "sg:province":"Vlaams-Brabant",
    "sg:tags":[
        "-"
    ],
    "wof:name":"Wouters W D M Bvba",
    "wof:placetype":"venue"
},
  "geometry": {"coordinates":[4.4611430168,50.9833869934],"type":"Point"}
}