{
  "type": "Feature",
  "properties": {
    "iso:country":"BE",
    "sg:address":"Rue Fran\u00e7ois Dieudonn\u00e9 35",
    "sg:city":"La Louvi\u00e8re (trivi\u00e8res)",
    "sg:classifiers":[
        {
            "category":"Building & Trades",
            "subcategory":"Plumbing",
            "type":"Services"
        }
    ],
    "sg:phone":"+32 64 21 41 39",
    "sg:postcode":"7100",
    "sg:province":"Hainaut",
    "sg:tags":[
        "contractor"
    ],
    "wof:name":"Rassart J",
    "wof:placetype":"venue"
},
  "geometry": {"coordinates":[4.1850848198,50.4748649597],"type":"Point"}
}