{
  "type": "Feature",
  "properties": {
    "iso:country":"BE",
    "sg:address":"Doornikstraat 8",
    "sg:city":"Oudenaarde",
    "sg:orig_category":"Fournitures de bureau",
    "sg:phone":"+32 55 30 41 13",
    "sg:postcode":"9700",
    "sg:province":"Oost-Vlaanderen",
    "wof:name":"Elebaut-nachtergaele",
    "wof:placetype":"venue"
},
  "geometry": {"coordinates":[3.6075220108,50.8378982544],"type":"Point"}
}