{
  "type": "Feature",
  "properties": {
    "addr:full":"Pl De L'h\u00f4tel De Ville Ch\u00e2telet 6071",
    "addr:postcode":"6071",
    "addr:street":"Pl",
    "iso:country":"BE",
    "sg:address":"Pl De L'h\u00f4tel De Ville",
    "sg:city":"Ch\u00e2telet",
    "sg:classifiers":[
        {
            "category":"Banks & Credit Unions",
            "subcategory":"Bank",
            "type":"Services"
        }
    ],
    "sg:phone":"+32 71 38 77 50",
    "sg:postcode":"6071",
    "wof:name":"Caisse Nationale De, Cr\u00e9dit Professionnel",
    "wof:placetype":"venue"
},
  "geometry": {"coordinates":[116.10958099370001,-31.9040699005],"type":"Point"}
}