{
  "type": "Feature",
  "properties": {
    "iso:country":"BE",
    "sg:address":"Chauss\u00c9e De Mons 115",
    "sg:city":"Ath",
    "sg:classifiers":[
        {
            "category":"Autos & Motor Vehicles",
            "subcategory":"Fuel & Gas Station",
            "type":"Retail Goods"
        }
    ],
    "sg:phone":"+32 68 28 06 94",
    "sg:postcode":"7800",
    "sg:province":"Hainaut",
    "sg:tags":[
        "stations-service",
        "carburants"
    ],
    "wof:name":"Sophie Carlier",
    "wof:placetype":"venue"
},
  "geometry": {"coordinates":[3.7759420872,50.6237106323],"type":"Point"}
}