{
  "type": "Feature",
  "properties": {
    "iso:country":"BE",
    "sg:address":"Heidestatieplein 18",
    "sg:city":"Kalmthout",
    "sg:classifiers":[
        {
            "category":"Bars & Pubs",
            "type":"Food & Drink"
        }
    ],
    "sg:phone":"+32 3 666 46 51",
    "sg:postcode":"2920",
    "sg:province":"Antwerpen",
    "wof:name":"Sandy Caf\u00e9",
    "wof:placetype":"venue"
},
  "geometry": {"coordinates":[4.4596338272,51.3647155762],"type":"Point"}
}