{
  "type": "Feature",
  "properties": {
    "addr:full":"Pandhoevestraat 51 Tremelo Vlaams-Brabant 3128",
    "addr:housenumber":"51",
    "addr:postcode":"3128",
    "addr:street":"Pandhoevestraat",
    "iso:country":"BE",
    "sg:address":"Pandhoevestraat 51",
    "sg:city":"Tremelo",
    "sg:orig_category":"Eleveurs de bovins. Eleveurs and marchands de porcs",
    "sg:phone":"+32 16 53 26 85",
    "sg:postcode":"3128",
    "sg:province":"Vlaams-Brabant",
    "wof:name":"Julien De Roover",
    "wof:placetype":"venue"
},
  "geometry": {"coordinates":[4.751103878,51.0187034607],"type":"Point"}
}