{
  "type": "Feature",
  "properties": {
    "addr:full":"Rue L\u00c9opold I 291 Brussel/bruxelles Bruxelles-Capitale 1020",
    "addr:housenumber":"291",
    "addr:postcode":"1020",
    "addr:street":"Rue Le\u0301Opold I;/",
    "iso:country":"BE",
    "sg:address":"Rue L\u00c9opold I 291",
    "sg:city":"Brussel/bruxelles",
    "sg:orig_category":"M\u00e9decins and sp\u00e9cialistes",
    "sg:phone":"+32 2 420 24 23",
    "sg:postcode":"1020",
    "sg:province":"Bruxelles-Capitale",
    "wof:name":"Dominique Daniel",
    "wof:placetype":"venue"
},
  "geometry": {"coordinates":[4.3406257629,50.8769493103],"type":"Point"}
}