{
  "type": "Feature",
  "properties": {
    "addr:full":"Smissestraat 17 Deinze (sint-martens-leerne) Oost-Vlaanderen 9800",
    "addr:housenumber":"17",
    "addr:postcode":"9800",
    "addr:street":"Smissestraat",
    "iso:country":"BE",
    "sg:address":"Smissestraat 17",
    "sg:city":"Deinze (sint-martens-leerne)",
    "sg:classifiers":[
        {
            "category":"Manufacturing",
            "subcategory":"Wood Products",
            "type":"Manufacturing & Wholesale Goods"
        }
    ],
    "sg:phone":"+32 9 282 78 41",
    "sg:postcode":"9800",
    "sg:province":"Oost-Vlaanderen",
    "sg:tags":[
        "turning",
        "carving"
    ],
    "wof:name":"De Gezelle M-houtsnijwerk",
    "wof:placetype":"venue"
},
  "geometry": {"coordinates":[3.5833659172,51.0112190247],"type":"Point"}
}