{
  "type": "Feature",
  "properties": {
    "iso:country":"BE",
    "sg:address":"Rue Pont De Jallet 62",
    "sg:city":"Ohey",
    "sg:orig_category":"Rundveehouders",
    "sg:phone":"+32 85 61 15 97",
    "sg:postcode":"5352",
    "sg:province":"Namur",
    "wof:name":"Roland Depoorter",
    "wof:placetype":"venue"
},
  "geometry": {"coordinates":[5.1793050766,50.4522247314],"type":"Point"}
}