{
  "type": "Feature",
  "properties": {
    "addr:full":"Rue De Behogne 10 Rochefort Namur 5580",
    "addr:housenumber":"10",
    "addr:postcode":"5580",
    "addr:street":"Rue De Behogne",
    "iso:country":"BE",
    "sg:address":"Rue De Behogne 10",
    "sg:city":"Rochefort",
    "sg:classifiers":[
        {
            "category":"Shopping",
            "subcategory":"Optician",
            "type":"Retail Goods"
        }
    ],
    "sg:phone":"+32 84 21 12 07",
    "sg:postcode":"5580",
    "sg:province":"Namur",
    "sg:tags":[
        "-"
    ],
    "wof:name":"Les Opticiens Griffe Sa",
    "wof:placetype":"venue"
},
  "geometry": {"coordinates":[5.2235898972,50.1603431702],"type":"Point"}
}