{
  "type": "Feature",
  "properties": {
    "addr:full":"Rue Reine Astrid 6 Genappe Brabant Wallon 1473",
    "addr:housenumber":"6",
    "addr:postcode":"1473",
    "addr:street":"Rue Reine Astrid;Wallon",
    "iso:country":"BE",
    "sg:address":"Rue Reine Astrid 6",
    "sg:city":"Genappe",
    "sg:orig_category":"Chaussures",
    "sg:phone":"+32 67 78 04 30",
    "sg:postcode":"1473",
    "sg:province":"Brabant Wallon",
    "wof:name":"Sylvia Poppe",
    "wof:placetype":"venue"
},
  "geometry": {"coordinates":[4.4533262253,50.6308517456],"type":"Point"}
}