{
  "type": "Feature",
  "properties": {
    "iso:country":"BE",
    "sg:address":"Poekestraat 36",
    "sg:city":"Nevele",
    "sg:orig_category":"Afbraak- and draineerwerken",
    "sg:phone":"+32 9 371 55 15",
    "sg:postcode":"9850",
    "sg:province":"Oost-Vlaanderen",
    "wof:name":"Van Bruwaene L",
    "wof:placetype":"venue"
},
  "geometry": {"coordinates":[3.5005500317,51.03647995],"type":"Point"}
}