{
  "type": "Feature",
  "properties": {
    "iso:country":"BE",
    "sg:address":"Chauss\u00e9e Charlemagne 30",
    "sg:city":"Thimister-clermont (thimister)",
    "sg:classifiers":[
        {
            "category":"Personal",
            "subcategory":"Sauna",
            "type":"Services"
        }
    ],
    "sg:phone":"+32 87 44 71 00",
    "sg:postcode":"4890",
    "sg:province":"Li\u00e8ge",
    "wof:name":"Algue Marine",
    "wof:placetype":"venue"
},
  "geometry": {"coordinates":[5.8580989838,50.6463165283],"type":"Point"}
}