{
  "type": "Feature",
  "properties": {
    "iso:country":"BE",
    "sg:address":"Jan De Trochstraat 123",
    "sg:city":"Dilbeek (schepdaal)",
    "sg:classifiers":[
        {
            "category":"Banks & Credit Unions",
            "subcategory":"Investment Brokerage",
            "type":"Services"
        }
    ],
    "sg:phone":"+32 2 581 03 81",
    "sg:postcode":"1703",
    "sg:province":"Vlaams-Brabant",
    "sg:tags":[
        "repair",
        "-",
        "installation",
        "sanitary",
        "article"
    ],
    "wof:name":"De Vriendt Bvba",
    "wof:placetype":"venue"
},
  "geometry": {"coordinates":[4.2045941353,50.8461761475],"type":"Point"}
}