{
  "type": "Feature",
  "properties": {
    "addr:full":"Patronagestrasse 26 Kelmis Li\u00e8ge 4720",
    "addr:housenumber":"26",
    "addr:postcode":"4720",
    "addr:street":"Patronagestrasse",
    "iso:country":"BE",
    "sg:address":"Patronagestrasse 26",
    "sg:city":"Kelmis",
    "sg:classifiers":[
        {
            "category":"Personal",
            "subcategory":"Beauty Salon",
            "type":"Services"
        }
    ],
    "sg:phone":"+32 87 65 90 07",
    "sg:postcode":"4720",
    "sg:province":"Li\u00e8ge",
    "sg:tags":[
        "lady",
        "-",
        "hairdressing"
    ],
    "wof:name":"Marie-therese",
    "wof:placetype":"venue"
},
  "geometry": {"coordinates":[6.0125169754,50.7183303833],"type":"Point"}
}