{
  "type": "Feature",
  "properties": {
    "addr:full":"Rozendaal 63 Geel Antwerpen 2440",
    "addr:housenumber":"63",
    "addr:postcode":"2440",
    "addr:street":"Rozendaal",
    "iso:country":"BE",
    "sg:address":"Rozendaal 63",
    "sg:city":"Geel",
    "sg:classifiers":[
        {
            "category":"Health Services",
            "subcategory":"Health Practitioner",
            "type":"Services"
        }
    ],
    "sg:phone":"+32 14 58 55 17",
    "sg:postcode":"2440",
    "sg:province":"Antwerpen",
    "sg:tags":[
        "physiotherapist"
    ],
    "wof:name":"Vangeel Kristel",
    "wof:placetype":"venue"
},
  "geometry": {"coordinates":[4.9935731888,51.1651763916],"type":"Point"}
}