{
  "type": "Feature",
  "properties": {
    "addr:full":"Antwerpse Heirweg 40 Eeklo Oost-Vlaanderen 9900",
    "addr:housenumber":"40",
    "addr:postcode":"9900",
    "addr:street":"Antwerpse Heirweg",
    "iso:country":"BE",
    "sg:address":"Antwerpse Heirweg 40",
    "sg:city":"Eeklo",
    "sg:orig_category":"Woningbouw",
    "sg:phone":"+32 9 377 14 04",
    "sg:postcode":"9900",
    "sg:province":"Oost-Vlaanderen",
    "wof:name":"Van Wijnsberghe Marc",
    "wof:placetype":"venue"
},
  "geometry": {"coordinates":[3.6040189266,51.1823120117],"type":"Point"}
}