{
  "type": "Feature",
  "properties": {
    "iso:country":"BE",
    "sg:address":"Rue Du Marais 1",
    "sg:city":"Durbuy (barvaux-sur-ourthe)",
    "sg:classifiers":[
        {
            "category":"Health Services",
            "subcategory":"Doctor",
            "type":"Services"
        }
    ],
    "sg:phone":"+32 86 21 10 45",
    "sg:postcode":"6940",
    "sg:province":"Luxembourg",
    "sg:tags":[
        "medicinephysicians",
        "surgeon"
    ],
    "wof:name":"Maillet Jacques",
    "wof:placetype":"venue"
},
  "geometry": {"coordinates":[5.4862527847,50.3483657837],"type":"Point"}
}