{
  "type": "Feature",
  "properties": {
    "iso:country":"BE",
    "sg:address":"Dorpstraat 57",
    "sg:city":"Antwerpen",
    "sg:orig_category":"Drukkerijen and copyshops",
    "sg:phone":"+32 3 568 98 44",
    "sg:postcode":"2040",
    "sg:province":"Antwerpen",
    "wof:name":"Quality",
    "wof:placetype":"venue"
},
  "geometry": {"coordinates":[4.3134999275,51.3459701538],"type":"Point"}
}