{
  "type": "Feature",
  "properties": {
    "addr:full":"Michel Theysstr 6 Diest Vlaams-Brabant 3290",
    "addr:housenumber":"6",
    "addr:postcode":"3290",
    "iso:country":"BE",
    "sg:address":"Michel Theysstr 6",
    "sg:city":"Diest",
    "sg:classifiers":[
        {
            "category":"Travel",
            "subcategory":"Hotels & Motels",
            "type":"Entertainment"
        }
    ],
    "sg:phone":"+32 13 32 76 76",
    "sg:postcode":"3290",
    "sg:province":"Vlaams-Brabant",
    "sg:tags":[
        "hotels",
        "business",
        "restaurant"
    ],
    "wof:name":"Nv Lagoon",
    "wof:placetype":"venue"
},
  "geometry": {"coordinates":[5.0518789291,50.9860916138],"type":"Point"}
}