{
  "type": "Feature",
  "properties": {
    "addr:full":"Kazernelaan 79 Houthalen-helchteren Limburg 3530",
    "addr:housenumber":"79",
    "addr:postcode":"3530",
    "addr:street":"Kazernelaan",
    "iso:country":"BE",
    "sg:address":"Kazernelaan 79",
    "sg:city":"Houthalen-helchteren",
    "sg:orig_category":"Installatie van houten of kunststof schrijnwerk MEUBELONTWERP AND -INSTALLATIE",
    "sg:phone":"+32 11 52 10 65",
    "sg:postcode":"3530",
    "sg:province":"Limburg",
    "wof:name":"Fran\u00c7ois Hermans",
    "wof:placetype":"venue"
},
  "geometry": {"coordinates":[5.3719201088,51.0310020447],"type":"Point"}
}