{
  "type": "Feature",
  "properties": {
    "addr:full":"Rue Des Champs 46 Gembloux-sur-orneau (gembloux) Namur 5030",
    "addr:housenumber":"46",
    "addr:postcode":"5030",
    "addr:street":"Rue Des Champs;Namur",
    "iso:country":"BE",
    "sg:address":"Rue Des Champs 46",
    "sg:city":"Gembloux-sur-orneau (gembloux)",
    "sg:classifiers":[
        {
            "category":"Taxi",
            "type":"Transportation"
        }
    ],
    "sg:phone":"+32 81 61 17 37",
    "sg:postcode":"5030",
    "sg:province":"Namur",
    "sg:tags":[
        "taxicab"
    ],
    "wof:name":"Louis Taxis",
    "wof:placetype":"venue"
},
  "geometry": {"coordinates":[4.6906709671,50.5548591614],"type":"Point"}
}