{
  "type": "Feature",
  "properties": {
    "addr:full":"Sint-jozeflaan 66 Mol Antwerpen 2400",
    "addr:housenumber":"66",
    "addr:postcode":"2400",
    "addr:street":"Sint-Jozeflaan",
    "iso:country":"BE",
    "sg:address":"Sint-jozeflaan 66",
    "sg:city":"Mol",
    "sg:classifiers":[
        {
            "category":"Wholesale",
            "subcategory":"Sporting Goods",
            "type":"Manufacturing & Wholesale Goods"
        }
    ],
    "sg:phone":"+32 14 81 08 17",
    "sg:postcode":"2400",
    "sg:province":"Antwerpen",
    "sg:tags":[
        "sport-",
        "kampeermateriaal"
    ],
    "wof:name":"Tennis Stores",
    "wof:placetype":"venue"
},
  "geometry": {"coordinates":[5.2137541771,51.1947021484],"type":"Point"}
}