{
  "type": "Feature",
  "properties": {
    "iso:country":"BE",
    "sg:address":"Beertsestraat 218",
    "sg:city":"Halle",
    "sg:classifiers":[
        {
            "category":"Professional",
            "subcategory":"Management & Consulting",
            "type":"Services"
        }
    ],
    "sg:phone":"+32 475 34 64 25",
    "sg:postcode":"1500",
    "sg:province":"Vlaams-Brabant",
    "sg:tags":[
        "marketing",
        "-",
        "consultant"
    ],
    "wof:name":"Broodcoorens P",
    "wof:placetype":"venue"
},
  "geometry": {"coordinates":[4.2217321396,50.7324371338],"type":"Point"}
}