{
  "type": "Feature",
  "properties": {
    "iso:country":"BE",
    "sg:address":"25",
    "sg:city":"Rue Daubel 4651 Herve",
    "sg:classifiers":[
        {
            "category":"Wholesale",
            "subcategory":"Medical Equipment & Supplies",
            "type":"Manufacturing & Wholesale Goods"
        }
    ],
    "sg:phone":"+32 87 67 90 89",
    "sg:postcode":"25",
    "sg:tags":[
        "instrument",
        "health",
        "-",
        "precision"
    ],
    "wof:name":"Laboratoire Alain Vaessen",
    "wof:placetype":"venue"
},
  "geometry": {"coordinates":[5.8225131035,50.6474494934],"type":"Point"}
}