{
  "type": "Feature",
  "properties": {
    "iso:country":"BE",
    "sg:address":"Schapenstraat 66",
    "sg:city":"Lennik (sint-martens-lennik)",
    "sg:classifiers":[
        {
            "category":"Health Services",
            "subcategory":"Doctor",
            "type":"Services"
        }
    ],
    "sg:phone":"+32 2 582 80 90",
    "sg:postcode":"1750",
    "sg:province":"Vlaams-Brabant",
    "sg:tags":[
        "medicinephysicians",
        "surgeon"
    ],
    "wof:name":"Everaet Els",
    "wof:placetype":"venue"
},
  "geometry": {"coordinates":[4.1672167778,50.8162765503],"type":"Point"}
}