{
  "type": "Feature",
  "properties": {
    "iso:country":"BE",
    "sg:address":"Haselindestraat 1",
    "sg:city":"Riemst (zichen-zussen-bolder)",
    "sg:classifiers":[
        {
            "category":"Sports & Exercise",
            "subcategory":"Skate Park",
            "type":"Entertainment"
        }
    ],
    "sg:phone":"+32 12 44 13 55",
    "sg:postcode":"3770",
    "sg:province":"Limburg",
    "sg:tags":[
        "mushroom"
    ],
    "wof:name":"Vossen J",
    "wof:placetype":"venue"
},
  "geometry": {"coordinates":[5.601981163,50.7897758484],"type":"Point"}
}