{
  "type": "Feature",
  "properties": {
    "addr:full":"Avenue Clays 59 Schaarbeek/schaerbeek Bruxelles-Capitale 1030",
    "addr:housenumber":"59",
    "addr:postcode":"1030",
    "addr:street":"Avenue Clays",
    "iso:country":"BE",
    "sg:address":"Avenue Clays 59",
    "sg:city":"Schaarbeek/schaerbeek",
    "sg:orig_category":"Journaux. Tabac",
    "sg:phone":"+32 2 216 08 46",
    "sg:postcode":"1030",
    "sg:province":"Bruxelles-Capitale",
    "wof:name":"Librairie Le Rubis",
    "wof:placetype":"venue"
},
  "geometry": {"coordinates":[4.3829660416,50.853767395],"type":"Point"}
}