{
  "type": "Feature",
  "properties": {
    "addr:full":"Stationsstraat 17 Beveren Oost-Vlaanderen 9120",
    "addr:housenumber":"17",
    "addr:postcode":"9120",
    "addr:street":"Stationsstraat",
    "iso:country":"BE",
    "sg:address":"Stationsstraat 17",
    "sg:city":"Beveren",
    "sg:classifiers":[
        {
            "category":"Insurance",
            "subcategory":"Insurance Agent",
            "type":"Services"
        }
    ],
    "sg:phone":"+32 3 750 90 90",
    "sg:postcode":"9120",
    "sg:province":"Oost-Vlaanderen",
    "sg:tags":[
        "verzekeringsmakelaars",
        "expert"
    ],
    "wof:name":"Bosman En Co",
    "wof:placetype":"venue"
},
  "geometry": {"coordinates":[4.2575931549,51.2109642029],"type":"Point"}
}