{
  "type": "Feature",
  "properties": {
    "iso:country":"BE",
    "sg:address":"Kerkstraat 28",
    "sg:city":"Sint-genesius-rode/rhode-saint-genese",
    "sg:orig_category":"Slagers",
    "sg:phone":"+32 2 380 55 64",
    "sg:postcode":"1640",
    "sg:province":"Vlaams-Brabant",
    "wof:name":"Beenhouwerij De Gelas",
    "wof:placetype":"venue"
},
  "geometry": {"coordinates":[4.3478770256,50.744354248],"type":"Point"}
}