{
  "type": "Feature",
  "properties": {
    "iso:country":"BE",
    "sg:address":"Veldstraat 76",
    "sg:city":"Brecht",
    "sg:orig_category":"Rundveehouders",
    "sg:phone":"+32 3 313 71 19",
    "sg:postcode":"2960",
    "sg:province":"Antwerpen",
    "wof:name":"Alois Van Dijck",
    "wof:placetype":"venue"
},
  "geometry": {"coordinates":[4.6415719986,51.358997345],"type":"Point"}
}