{
  "type": "Feature",
  "properties": {
    "addr:full":"Kouterstraat 47 Zele Oost-Vlaanderen 9240",
    "addr:housenumber":"47",
    "addr:postcode":"9240",
    "addr:street":"Kouterstraat",
    "iso:country":"BE",
    "sg:address":"Kouterstraat 47",
    "sg:city":"Zele",
    "sg:classifiers":[
        {
            "category":"Shopping",
            "subcategory":"Beauty & Cosmetics",
            "type":"Retail Goods"
        }
    ],
    "sg:phone":"+32 52 44 45 07",
    "sg:postcode":"9240",
    "sg:province":"Oost-Vlaanderen",
    "sg:tags":[
        "-",
        "perfumery"
    ],
    "wof:name":"Griet Parfumerie",
    "wof:placetype":"venue"
},
  "geometry": {"coordinates":[4.0313692093,51.0656433105],"type":"Point"}
}