{
  "type": "Feature",
  "properties": {
    "iso:country":"BE",
    "sg:address":"Verlorenkost 4",
    "sg:city":"Gistel",
    "sg:orig_category":"Eleveurs de bovins",
    "sg:phone":"+32 59 27 85 04",
    "sg:postcode":"8470",
    "sg:province":"West-Vlaanderen",
    "wof:name":"Georges Haeghebaert",
    "wof:placetype":"venue"
},
  "geometry": {"coordinates":[2.9400479794,51.1793365479],"type":"Point"}
}