{
  "type": "Feature",
  "properties": {
    "iso:country":"BE",
    "sg:address":"Gr\u00fcfflingen 60a",
    "sg:city":"Burg-reuland (thommen)",
    "sg:classifiers":[
        {
            "category":"Health Services",
            "subcategory":"Doctor",
            "type":"Services"
        }
    ],
    "sg:phone":"+32 80 42 03 18",
    "sg:postcode":"4791",
    "sg:province":"Li\u00e8ge",
    "sg:tags":[
        "medicinephysicians",
        "surgeon"
    ],
    "wof:name":"Keus B\u00e9atrice",
    "wof:placetype":"venue"
},
  "geometry": {"coordinates":[6.0883870125,50.2242469788],"type":"Point"}
}