{
  "type": "Feature",
  "properties": {
    "iso:country":"BE",
    "sg:address":"Rue Du Marais 1",
    "sg:city":"Huy",
    "sg:orig_category":"Avocats and conseillers juridiques",
    "sg:phone":"+32 85 21 68 47",
    "sg:postcode":"4500",
    "sg:province":"Li\u00e8ge",
    "wof:name":"P. Bruwier",
    "wof:placetype":"venue"
},
  "geometry": {"coordinates":[5.2466330528,50.5251197815],"type":"Point"}
}