{
  "type": "Feature",
  "properties": {
    "iso:country":"BE",
    "sg:address":"Hendrik Ghijselenstraat 17",
    "sg:city":"Lennik",
    "sg:orig_category":"Studios photographiques",
    "sg:phone":"+32 2 532 15 98",
    "sg:postcode":"1750",
    "sg:province":"Vlaams-Brabant",
    "wof:name":"Pieter Van Den Bossche",
    "wof:placetype":"venue"
},
  "geometry": {"coordinates":[4.1531610489,50.8063201904],"type":"Point"}
}