{
  "type": "Feature",
  "properties": {
    "addr:full":"Rue Du Grand Pr\u00c9 35 Sint-agatha-berchem/berchem-sainte-agathe Bruxelles-Capitale 1082",
    "addr:housenumber":"35",
    "addr:postcode":"1082",
    "addr:street":"Rue Du Grand Pre\u0301;/",
    "iso:country":"BE",
    "sg:address":"Rue Du Grand Pr\u00c9 35",
    "sg:city":"Sint-agatha-berchem/berchem-sainte-agathe",
    "sg:orig_category":"R\u00e9parations de chaussures and articles en cuir",
    "sg:phone":"+32 2 465 47 39",
    "sg:postcode":"1082",
    "sg:province":"Bruxelles-Capitale",
    "wof:name":"Henri Morias",
    "wof:placetype":"venue"
},
  "geometry": {"coordinates":[4.3014512062,50.8581886292],"type":"Point"}
}