{
  "type": "Feature",
  "properties": {
    "iso:country":"BE",
    "sg:address":"Chauss\u00e9e De Bruxelles 333",
    "sg:city":"Charleroi (dampremy)",
    "sg:classifiers":[
        {
            "category":"Home & Garden",
            "subcategory":"Carpets & Floor Coverings",
            "type":"Retail Goods"
        }
    ],
    "sg:phone":"+32 71 32 27 35",
    "sg:postcode":"6020",
    "sg:province":"Hainaut",
    "sg:tags":[
        "tile"
    ],
    "wof:name":"D'onofrio Ets",
    "wof:placetype":"venue"
},
  "geometry": {"coordinates":[4.4401612282,50.4215660095],"type":"Point"}
}