{
  "type": "Feature",
  "properties": {
    "addr:full":"Molenstraat 81 Temse Oost-Vlaanderen 9140",
    "addr:housenumber":"81",
    "addr:postcode":"9140",
    "addr:street":"Molenstraat",
    "iso:country":"BE",
    "sg:address":"Molenstraat 81",
    "sg:city":"Temse",
    "sg:orig_category":"Rev\u00eatements pour sols and murs. Construction de maisons",
    "sg:phone":"+32 3 771 04 96",
    "sg:postcode":"9140",
    "sg:province":"Oost-Vlaanderen",
    "wof:name":"Teugels Bouwbedrijf",
    "wof:placetype":"venue"
},
  "geometry": {"coordinates":[4.1761498451,51.1284484863],"type":"Point"}
}