{
  "type": "Feature",
  "properties": {
    "iso:country":"BE",
    "sg:address":"Rue De Menin 67",
    "sg:city":"Wervik (grand)",
    "sg:orig_category":"Agences Matrimoniales et de Rencontre",
    "sg:phone":"+32 56 53 15 60",
    "sg:postcode":"8940",
    "sg:province":"West-Vlaanderen",
    "wof:name":"Adagio",
    "wof:placetype":"venue"
},
  "geometry": {"coordinates":[3.059830904,50.782119751],"type":"Point"}
}