{
  "type": "Feature",
  "properties": {
    "addr:full":"Tulpenlaan 117 Deerlijk West-Vlaanderen 8540",
    "addr:housenumber":"117",
    "addr:postcode":"8540",
    "addr:street":"Tulpenlaan",
    "iso:country":"BE",
    "sg:address":"Tulpenlaan 117",
    "sg:city":"Deerlijk",
    "sg:orig_category":"Immobili\u00ebnkantoren Verbruikerskredietinstellingen Verzekeringsmakelaars and experts",
    "sg:phone":"+32 56 71 30 68",
    "sg:postcode":"8540",
    "sg:province":"West-Vlaanderen",
    "wof:name":"Immo-assu-fina",
    "wof:placetype":"venue"
},
  "geometry": {"coordinates":[3.3529810905,50.8555374146],"type":"Point"}
}