{
  "type": "Feature",
  "properties": {
    "addr:full":"Amerikalei 169 Antwerpen Antwerpen 2000",
    "addr:housenumber":"169",
    "addr:postcode":"2000",
    "addr:street":"Amerikalei",
    "iso:country":"BE",
    "sg:address":"Amerikalei 169",
    "sg:city":"Antwerpen",
    "sg:orig_category":"Articles m\u00e9talliques ouvr\u00e9s divers Fab. Installation de menuiserie en bois and plastique",
    "sg:phone":"+32 3 216 14 88",
    "sg:postcode":"2000",
    "sg:province":"Antwerpen",
    "wof:name":"All Shop",
    "wof:placetype":"venue"
},
  "geometry": {"coordinates":[4.3929448128,51.2055778503],"type":"Point"}
}