{
  "type": "Feature",
  "properties": {
    "iso:country":"BE",
    "sg:address":"Peperhofstraat 26",
    "sg:city":"Genk",
    "sg:orig_category":"Medische apparatuur, orthopedische artikelen and prothesen Fab",
    "sg:phone":"+32 89 38 24 95",
    "sg:postcode":"3600",
    "sg:province":"Limburg",
    "wof:name":"Maurice Holans",
    "wof:placetype":"venue"
},
  "geometry": {"coordinates":[5.4925508499,51.0027046204],"type":"Point"}
}