{
  "type": "Feature",
  "properties": {
    "addr:full":"Madrasstraat 1 Antwerpen Antwerpen 2030",
    "addr:housenumber":"1",
    "addr:postcode":"2030",
    "addr:street":"Madrasstraat",
    "iso:country":"BE",
    "sg:address":"Madrasstraat 1",
    "sg:city":"Antwerpen",
    "sg:classifiers":[
        {
            "category":"Professional",
            "subcategory":"Employment Agencies",
            "type":"Services"
        }
    ],
    "sg:phone":"+32 3 232 16 95",
    "sg:postcode":"2030",
    "sg:province":"Antwerpen",
    "sg:tags":[
        "shipping"
    ],
    "wof:name":"Proman Agencies (belgium) Nv",
    "wof:placetype":"venue"
},
  "geometry": {"coordinates":[4.4097929001,51.2356033325],"type":"Point"}
}