{
  "type": "Feature",
  "properties": {
    "iso:country":"BE",
    "sg:address":"Robroekstraat 23",
    "sg:city":"Londerzeel (steenhuffel)",
    "sg:classifiers":[
        {
            "category":"Health Services",
            "subcategory":"Doctor",
            "type":"Services"
        }
    ],
    "sg:phone":"+32 52 30 04 63",
    "sg:postcode":"1840",
    "sg:province":"Vlaams-Brabant",
    "sg:tags":[
        "medicinephysicians",
        "surgeon"
    ],
    "wof:name":"De Ridder E",
    "wof:placetype":"venue"
},
  "geometry": {"coordinates":[4.2615189552,50.9920349121],"type":"Point"}
}