{
  "type": "Feature",
  "properties": {
    "iso:country":"BE",
    "sg:address":"Op De Muur 9",
    "sg:city":"Landen",
    "sg:classifiers":[
        {
            "category":"Shopping",
            "subcategory":"Computers & Home Electronics",
            "type":"Retail Goods"
        }
    ],
    "sg:phone":"+32 11 83 12 84",
    "sg:postcode":"3400",
    "sg:province":"Vlaams-Brabant",
    "sg:tags":[
        "personal",
        "-",
        "processing",
        "data"
    ],
    "wof:name":"Peeters Computers",
    "wof:placetype":"venue"
},
  "geometry": {"coordinates":[5.080848217,50.7546730042],"type":"Point"}
}