{
  "type": "Feature",
  "properties": {
    "iso:country":"BE",
    "sg:address":"Avenue Palmerston 27",
    "sg:city":"Brussel/bruxelles",
    "sg:orig_category":"M\u00e9decins and sp\u00e9cialistes",
    "sg:phone":"+32 2 230 67 93",
    "sg:postcode":"1000",
    "sg:province":"Bruxelles-Capitale",
    "wof:name":"Andr\u00c9-georges Molhant",
    "wof:placetype":"venue"
},
  "geometry": {"coordinates":[4.3818240166,50.8466911316],"type":"Point"}
}