{
  "type": "Feature",
  "properties": {
    "iso:country":"BE",
    "sg:address":"Weststraat 59",
    "sg:city":"Waarschoot",
    "sg:classifiers":[
        {
            "category":"Bars & Pubs",
            "type":"Food & Drink"
        }
    ],
    "sg:phone":"+32 9 377 29 66",
    "sg:postcode":"9950",
    "sg:province":"Oost-Vlaanderen",
    "wof:name":"Yvette",
    "wof:placetype":"venue"
},
  "geometry": {"coordinates":[3.5857980251,51.1518669128],"type":"Point"}
}