{
  "type": "Feature",
  "properties": {
    "addr:full":"Chauss\u00c9e De Braine-l'alleud 147 Sint-genesius-rode/rhode-saint-genese Vlaams-Brabant 1640",
    "addr:housenumber":"147",
    "addr:postcode":"1640",
    "addr:street":"Chausse\u0301E De Braine-L'Alleud",
    "iso:country":"BE",
    "sg:address":"Chauss\u00c9e De Braine-l'alleud 147",
    "sg:city":"Sint-genesius-rode/rhode-saint-genese",
    "sg:classifiers":[
        {
            "category":"Fast Food",
            "type":"Food & Drink"
        }
    ],
    "sg:phone":"+32 2 380 02 37",
    "sg:postcode":"1640",
    "sg:province":"Vlaams-Brabant",
    "sg:tags":[
        "de",
        "restaurant",
        "organisation",
        "\u00c0",
        "catering",
        "emporter",
        "f\u00cates",
        "restaurants"
    ],
    "wof:name":"Restaurant De Goede Lucht",
    "wof:placetype":"venue"
},
  "geometry": {"coordinates":[4.3402500153,50.7322311401],"type":"Point"}
}