{
  "type": "Feature",
  "properties": {
    "iso:country":"BE",
    "sg:address":"Woumenweg 224",
    "sg:city":"Diksmuide",
    "sg:orig_category":"Eleveurs and marchands de porcs",
    "sg:phone":"+32 51 50 05 51",
    "sg:postcode":"8600",
    "sg:province":"West-Vlaanderen",
    "wof:name":"Achiel Markey",
    "wof:placetype":"venue"
},
  "geometry": {"coordinates":[2.8679099083,51.0131607056],"type":"Point"}
}