{
  "type": "Feature",
  "properties": {
    "iso:country":"BE",
    "sg:address":"Avenue Paul Deschanel 120",
    "sg:city":"Bruxelles (schaerbeek)",
    "sg:classifiers":[
        {
            "category":"Professional",
            "subcategory":"Art Services",
            "type":"Services"
        }
    ],
    "sg:phone":"+32 2 215 62 40",
    "sg:postcode":"1030",
    "sg:province":"Bruxelles-Capitale",
    "sg:tags":[
        "children's",
        "animation"
    ],
    "wof:name":"Clown Pijama Asbl",
    "wof:placetype":"venue"
},
  "geometry": {"coordinates":[4.3793048859,50.859413147],"type":"Point"}
}