{
  "type": "Feature",
  "properties": {
    "iso:country":"BE",
    "sg:address":"Laagstraat 1",
    "sg:city":"Temse",
    "sg:orig_category":"Installation de menuiserie m\u00e9tallique",
    "sg:phone":"+32 3 771 64 69",
    "sg:postcode":"9140",
    "sg:province":"Oost-Vlaanderen",
    "wof:name":"Necap Construct",
    "wof:placetype":"venue"
},
  "geometry": {"coordinates":[4.1959290504,51.1350898743],"type":"Point"}
}