{
  "type": "Feature",
  "properties": {
    "iso:country":"BE",
    "sg:address":"Vlamingstraat 4",
    "sg:city":"Hoogstraten",
    "sg:classifiers":[
        {
            "category":"Building & Trades",
            "subcategory":"Landscaping Services",
            "type":"Services"
        }
    ],
    "sg:phone":"+32 3 315 08 83",
    "sg:postcode":"2320",
    "sg:province":"Antwerpen",
    "sg:tags":[
        "gardening",
        "garden",
        "maintenance"
    ],
    "wof:name":"Ooms Erik",
    "wof:placetype":"venue"
},
  "geometry": {"coordinates":[4.7150731087,51.396320343],"type":"Point"}
}