{
  "type": "Feature",
  "properties": {
    "iso:country":"BE",
    "sg:address":"Molseweg 138",
    "sg:city":"Geel",
    "sg:orig_category":"Autombile concessionaires",
    "sg:phone":"+32 14 58 88 20",
    "sg:postcode":"2440",
    "sg:province":"Antwerpen",
    "wof:name":"Gar K Haesen",
    "wof:placetype":"venue"
},
  "geometry": {"coordinates":[5.0428352356,51.166683197],"type":"Point"}
}