{
  "type": "Feature",
  "properties": {
    "addr:full":"Noordstraat 137-139 Roeselare West-Vlaanderen 8800",
    "addr:housenumber":"137-139",
    "addr:postcode":"8800",
    "addr:street":"Noordstraat",
    "iso:country":"BE",
    "sg:address":"Noordstraat 137-139",
    "sg:city":"Roeselare",
    "sg:classifiers":[
        {
            "category":"Bus Stop",
            "subcategory":"None",
            "type":"Transportation"
        }
    ],
    "sg:phone":"+32 4 344 00 79",
    "sg:postcode":"8800",
    "sg:province":"West-Vlaanderen",
    "sg:tags":[
        "engraving",
        "workshop"
    ],
    "wof:name":"Thiry Oscar S.a.",
    "wof:placetype":"venue"
},
  "geometry": {"coordinates":[5.5969958305,50.6222724915],"type":"Point"}
}