{
  "type": "Feature",
  "properties": {
    "addr:full":"Hanswijkstraat 5 Boortmeerbeek Vlaams-Brabant 3190",
    "addr:housenumber":"5",
    "addr:postcode":"3190",
    "addr:street":"Hanswijkstraat",
    "iso:country":"BE",
    "sg:address":"Hanswijkstraat 5",
    "sg:city":"Boortmeerbeek",
    "sg:classifiers":[
        {
            "category":"Retail",
            "subcategory":"Event Space",
            "type":"Services"
        }
    ],
    "sg:phone":"+32 15 51 13 60",
    "sg:postcode":"3190",
    "sg:province":"Vlaams-Brabant",
    "sg:tags":[
        "rental",
        "-",
        "hall"
    ],
    "wof:name":"Movri-imbami",
    "wof:placetype":"venue"
},
  "geometry": {"coordinates":[4.5713028908,50.9811553955],"type":"Point"}
}