{
  "type": "Feature",
  "properties": {
    "addr:full":"Warandestraat 83 Waasmunster Oost-Vlaanderen 9250",
    "addr:housenumber":"83",
    "addr:postcode":"9250",
    "addr:street":"Warandestraat",
    "iso:country":"BE",
    "sg:address":"Warandestraat 83",
    "sg:city":"Waasmunster",
    "sg:classifiers":[
        {
            "category":"Health Services",
            "subcategory":"Health Practitioner",
            "type":"Services"
        }
    ],
    "sg:phone":"+32 52 46 09 49",
    "sg:postcode":"9250",
    "sg:province":"Oost-Vlaanderen",
    "sg:tags":[
        "physiotherapist"
    ],
    "wof:name":"Van Cleemput Jos",
    "wof:placetype":"venue"
},
  "geometry": {"coordinates":[4.1307010651,51.1134681702],"type":"Point"}
}