{
  "type": "Feature",
  "properties": {
    "addr:full":"Stationsstraat 9 Blankenberge West-Vlaanderen 8370",
    "addr:housenumber":"9",
    "addr:postcode":"8370",
    "addr:street":"Stationsstraat",
    "iso:country":"BE",
    "sg:address":"Stationsstraat 9",
    "sg:city":"Blankenberge",
    "sg:classifiers":[
        {
            "category":"Wholesale",
            "subcategory":"Books, Periodicals, & Newspapers",
            "type":"Manufacturing & Wholesale Goods"
        }
    ],
    "sg:phone":"+32 50 42 43 05",
    "sg:postcode":"8370",
    "sg:province":"West-Vlaanderen",
    "sg:tags":[
        "publisher"
    ],
    "wof:name":"Callens B",
    "wof:placetype":"venue"
},
  "geometry": {"coordinates":[3.1334779263,51.3136711121],"type":"Point"}
}