{
  "type": "Feature",
  "properties": {
    "addr:full":"Hauptstrasse 31 Raeren Li\u00e8ge 4730",
    "addr:housenumber":"31",
    "addr:postcode":"4730",
    "addr:street":"Hauptstrasse",
    "iso:country":"BE",
    "sg:address":"Hauptstrasse 31",
    "sg:city":"Raeren",
    "sg:classifiers":[
        {
            "category":"Shopping",
            "subcategory":"Crafts & Fabrics",
            "type":"Retail Goods"
        }
    ],
    "sg:phone":"+32 87 85 19 82",
    "sg:postcode":"4730",
    "sg:province":"Li\u00e8ge",
    "sg:tags":[
        "ceramic"
    ],
    "wof:name":"Hasemeier-schopp",
    "wof:placetype":"venue"
},
  "geometry": {"coordinates":[6.1114912033,50.6762084961],"type":"Point"}
}