{
  "type": "Feature",
  "properties": {
    "addr:full":"Albert Kanaalstraat 24 Nijlen Antwerpen 2560",
    "addr:housenumber":"24",
    "addr:postcode":"2560",
    "addr:street":"Albert Kanaalstraat",
    "iso:country":"BE",
    "sg:address":"Albert Kanaalstraat 24",
    "sg:city":"Nijlen",
    "sg:classifiers":[
        {
            "category":"Health Services",
            "subcategory":"Health Practitioner",
            "type":"Services"
        }
    ],
    "sg:phone":"+32 3 411 06 65",
    "sg:postcode":"2560",
    "sg:province":"Antwerpen",
    "sg:tags":[
        "physiotherapist"
    ],
    "wof:name":"Meeus Kristien",
    "wof:placetype":"venue"
},
  "geometry": {"coordinates":[4.6687021255,51.1617012024],"type":"Point"}
}