{
  "type": "Feature",
  "properties": {
    "addr:full":"Tienne \u00c0 Deux Vall\u00c9es 10b28 Nivelles Brabant Wallon 1400",
    "addr:housenumber":"1400",
    "iso:country":"BE",
    "sg:address":"Tienne \u00c0 Deux Vall\u00c9es 10b28",
    "sg:city":"Nivelles",
    "sg:orig_category":"Vakantiehuizen",
    "sg:phone":"+32 67 21 54 59",
    "sg:postcode":"1400",
    "sg:province":"Brabant Wallon",
    "wof:name":"Decock",
    "wof:placetype":"venue"
},
  "geometry": {"coordinates":[4.3380899429,50.5943908691],"type":"Point"}
}