{
  "type": "Feature",
  "properties": {
    "addr:full":"Boulevard D'anvers 42 Bruxelles Bruxelles-Capitale 1000",
    "addr:housenumber":"42",
    "addr:postcode":"1000",
    "addr:street":"Boulevard D'Anvers",
    "iso:country":"BE",
    "sg:address":"Boulevard D'anvers 42",
    "sg:city":"Bruxelles",
    "sg:orig_category":"Epiceries",
    "sg:phone":"+32 2 218 22 41",
    "sg:postcode":"1000",
    "sg:province":"Bruxelles-Capitale",
    "wof:name":"Bal",
    "wof:placetype":"venue"
},
  "geometry": {"coordinates":[4.3493800163,50.8576011658],"type":"Point"}
}