{
  "type": "Feature",
  "properties": {
    "iso:country":"BE",
    "sg:address":"Moeresteenweg 21",
    "sg:city":"De Panne",
    "sg:orig_category":"Boucheries",
    "sg:phone":"+32 58 41 11 57",
    "sg:postcode":"8660",
    "sg:province":"West-Vlaanderen",
    "wof:name":"Filip Debeir",
    "wof:placetype":"venue"
},
  "geometry": {"coordinates":[2.5873420238,51.0627746582],"type":"Point"}
}