{
  "type": "Feature",
  "properties": {
    "iso:country":"BE",
    "sg:address":"Spiekerstraat 12",
    "sg:city":"Veurne",
    "sg:classifiers":[
        {
            "category":"Personal",
            "subcategory":"Nail Salon",
            "type":"Services"
        }
    ],
    "sg:phone":"+32 58 31 38 46",
    "sg:postcode":"8630",
    "sg:province":"West-Vlaanderen",
    "sg:tags":[
        "pedicure"
    ],
    "wof:name":"Van Den Berghe A",
    "wof:placetype":"venue"
},
  "geometry": {"coordinates":[2.6652200222,51.0796546936],"type":"Point"}
}