{
  "type": "Feature",
  "properties": {
    "iso:country":"BE",
    "sg:address":"Dobbelenbergstraat 21",
    "sg:city":"Brussel/bruxelles",
    "sg:orig_category":"Plaatsen van vloer- and muurbekleding Schilders",
    "sg:phone":"+32 2 216 66 76",
    "sg:postcode":"1130",
    "sg:province":"Bruxelles-Capitale",
    "wof:name":"G. Dedriche",
    "wof:placetype":"venue"
},
  "geometry": {"coordinates":[4.422287941,50.9013404846],"type":"Point"}
}