{
  "type": "Feature",
  "properties": {
    "iso:country":"BE",
    "sg:address":"Rue Du Commerce 39",
    "sg:city":"Ciney",
    "sg:orig_category":"Pharmaciens",
    "sg:phone":"+32 83 21 10 45",
    "sg:postcode":"5590",
    "sg:province":"Namur",
    "wof:name":"Pharmacie Du Condroz",
    "wof:placetype":"venue"
},
  "geometry": {"coordinates":[5.0988779068,50.293964386],"type":"Point"}
}