{
  "type": "Feature",
  "properties": {
    "iso:country":"BE",
    "sg:address":"Rue Eug\u00c8ne Cattoir 14",
    "sg:city":"Elsene/ixelles",
    "sg:orig_category":"Salles de conf\u00e9rences and de r\u00e9ceptions",
    "sg:phone":"+32 2 646 57 73",
    "sg:postcode":"1050",
    "sg:province":"Bruxelles-Capitale",
    "wof:name":"Salons Alambic",
    "wof:placetype":"venue"
},
  "geometry": {"coordinates":[4.3876190186,50.8203964233],"type":"Point"}
}