{
  "type": "Feature",
  "properties": {
    "iso:country":"BE",
    "sg:address":"Kloosterstraat 43",
    "sg:city":"Opwijk",
    "sg:classifiers":[
        {
            "category":"Health Services",
            "subcategory":"Nursing And Care Facility",
            "type":"Services"
        }
    ],
    "sg:phone":"+32 52 36 59 40",
    "sg:postcode":"1745",
    "sg:province":"Vlaams-Brabant",
    "sg:tags":[
        "home",
        "rest"
    ],
    "wof:name":"Ocmw Opwijk",
    "wof:placetype":"venue"
},
  "geometry": {"coordinates":[4.1832718849,50.9665565491],"type":"Point"}
}