{
  "type": "Feature",
  "properties": {
    "addr:full":"Beekstraat 25 Antwerpen Antwerpen 2140",
    "addr:housenumber":"25",
    "addr:postcode":"2140",
    "addr:street":"Beekstraat",
    "iso:country":"BE",
    "sg:address":"Beekstraat 25",
    "sg:city":"Antwerpen",
    "sg:orig_category":"Epiceries",
    "sg:phone":"+32 3 271 01 88",
    "sg:postcode":"2140",
    "sg:province":"Antwerpen",
    "wof:name":"Dirk Raeymaeckers",
    "wof:placetype":"venue"
},
  "geometry": {"coordinates":[4.4332199097,51.2137565613],"type":"Point"}
}