{
  "type": "Feature",
  "properties": {
    "iso:country":"BE",
    "sg:address":"Prinsenhof 6",
    "sg:city":"Wetteren (massemen)",
    "sg:classifiers":[
        {
            "category":"Health Services",
            "subcategory":"Health Practitioner",
            "type":"Services"
        }
    ],
    "sg:phone":"+32 9 368 10 26",
    "sg:postcode":"9230",
    "sg:province":"Oost-Vlaanderen",
    "sg:tags":[
        "physiotherapist"
    ],
    "wof:name":"De Moor Claudia",
    "wof:placetype":"venue"
},
  "geometry": {"coordinates":[3.8855400085,51.0070304871],"type":"Point"}
}