{
  "type": "Feature",
  "properties": {
    "iso:country":"BE",
    "sg:address":"Im Kulei 29",
    "sg:city":"Butgenbach",
    "sg:orig_category":"Transports routiers de marchandises",
    "sg:phone":"+32 80 44 57 28",
    "sg:postcode":"4750",
    "sg:province":"Li\u00e8ge",
    "wof:name":"Internationale Transporte Roger Marx",
    "wof:placetype":"venue"
},
  "geometry": {"coordinates":[6.2290410995,50.4470672607],"type":"Point"}
}