{
  "type": "Feature",
  "properties": {
    "iso:country":"BE",
    "sg:address":"Rue De Vis\u00e9 653",
    "sg:city":"Li\u00e8ge 1 (wandre)",
    "sg:classifiers":[
        {
            "category":"Health Services",
            "subcategory":"Doctor",
            "type":"Services"
        }
    ],
    "sg:phone":"+32 4 362 70 25",
    "sg:postcode":"4020",
    "sg:province":"Li\u00e8ge",
    "sg:tags":[
        "medicinephysicians",
        "surgeon"
    ],
    "wof:name":"Gilson Philippe",
    "wof:placetype":"venue"
},
  "geometry": {"coordinates":[5.6601648331,50.6691207886],"type":"Point"}
}