{
  "type": "Feature",
  "properties": {
    "iso:country":"BE",
    "sg:address":"Rue De Namur 99-101",
    "sg:city":"Bruxelles",
    "sg:classifiers":[
        {
            "category":"Shopping",
            "subcategory":"Jewelry",
            "type":"Retail Goods"
        }
    ],
    "sg:phone":"+32 2 511 80 41",
    "sg:postcode":"1000",
    "sg:province":"Bruxelles-Capitale",
    "sg:tags":[
        "jeweller",
        "-"
    ],
    "wof:name":"Garance Joaillier",
    "wof:placetype":"venue"
},
  "geometry": {"coordinates":[4.3614721298,50.8389015198],"type":"Point"}
}