{
  "type": "Feature",
  "properties": {
    "addr:full":"Kerkstraat 153 Blankenberge West-Vlaanderen 8370",
    "addr:housenumber":"153",
    "addr:postcode":"8370",
    "addr:street":"Kerkstraat",
    "iso:country":"BE",
    "sg:address":"Kerkstraat 153",
    "sg:city":"Blankenberge",
    "sg:orig_category":"Openbare veiligheid",
    "sg:phone":"+32 50 41 10 05",
    "sg:postcode":"8370",
    "sg:province":"West-Vlaanderen",
    "wof:name":"Federale Politie/police F\u00c9d\u00c9rale",
    "wof:placetype":"venue"
},
  "geometry": {"coordinates":[3.1335771084,51.3113594055],"type":"Point"}
}