{
  "type": "Feature",
  "properties": {
    "iso:country":"BE",
    "sg:address":"Avenue De L'h\u00e9liport 16 Box 9",
    "sg:city":"Bruxelles",
    "sg:classifiers":[
        {
            "category":"Parking",
            "subcategory":"Lot",
            "type":"Transportation"
        }
    ],
    "sg:phone":"+32 65 35 47 21",
    "sg:postcode":"1000",
    "sg:province":"Bruxelles-Capitale",
    "sg:tags":[
        "parking-places",
        "laying-out"
    ],
    "wof:name":"Z.s. Sprl",
    "wof:placetype":"venue"
},
  "geometry": {"coordinates":[4.3519678116,50.8579750061],"type":"Point"}
}