{
  "type": "Feature",
  "properties": {
    "iso:country":"BE",
    "sg:address":"Ferdinand Lenoirstraat 68",
    "sg:city":"Jette/jette",
    "sg:orig_category":"Beheer van reclamemedia Drukkerijen and copyshops",
    "sg:phone":"+32 2 426 17 53",
    "sg:postcode":"1090",
    "sg:province":"Bruxelles-Capitale",
    "wof:name":"Abc Publicit\u00c9",
    "wof:placetype":"venue"
},
  "geometry": {"coordinates":[4.3310279846,50.8755722046],"type":"Point"}
}