{
  "type": "Feature",
  "properties": {
    "addr:full":"Avenue De La D\u00e9portation 38 Ecaussinnes (ecaussinnes-d'enghien) Hainaut 7190",
    "addr:housenumber":"38",
    "addr:postcode":"7190",
    "addr:street":"Avenue De La De\u0301Portation;Ecaussinnes-D'Enghien Hainaut",
    "iso:country":"BE",
    "sg:address":"Avenue De La D\u00e9portation 38",
    "sg:city":"Ecaussinnes (ecaussinnes-d'enghien)",
    "sg:classifiers":[
        {
            "category":"Banks & Credit Unions",
            "subcategory":"Investment Brokerage",
            "type":"Services"
        }
    ],
    "sg:phone":"+32 67 44 42 38",
    "sg:postcode":"7190",
    "sg:province":"Hainaut",
    "sg:tags":[
        "printing",
        "-"
    ],
    "wof:name":"Grafic Express",
    "wof:placetype":"venue"
},
  "geometry": {"coordinates":[4.1590681076,50.5627632141],"type":"Point"}
}