{
  "type": "Feature",
  "properties": {
    "addr:full":"Kerselaarstraat 34 Merelbeke Oost-Vlaanderen 9820",
    "addr:housenumber":"34",
    "addr:postcode":"9820",
    "addr:street":"Kerselaarstraat",
    "iso:country":"BE",
    "sg:address":"Kerselaarstraat 34",
    "sg:city":"Merelbeke",
    "sg:orig_category":"Agences d'exp\u00e9dition",
    "sg:phone":"+32 9 231 14 64",
    "sg:postcode":"9820",
    "sg:province":"Oost-Vlaanderen",
    "wof:name":"De Trazegnies Freddy",
    "wof:placetype":"venue"
},
  "geometry": {"coordinates":[3.7572660446,50.9883842468],"type":"Point"}
}