{
  "type": "Feature",
  "properties": {
    "addr:full":"All\u00e9e Des Arondes 26 Herstal (vottem) Li\u00e8ge 4041",
    "addr:housenumber":"26",
    "addr:postcode":"4041",
    "addr:street":"Alle\u0301E Des Arondes;Vottem",
    "iso:country":"BE",
    "sg:address":"All\u00e9e Des Arondes 26",
    "sg:city":"Herstal (vottem)",
    "sg:classifiers":[
        {
            "category":"Banks & Credit Unions",
            "subcategory":"Investment Brokerage",
            "type":"Services"
        }
    ],
    "sg:phone":"+32 4 227 13 78",
    "sg:postcode":"4041",
    "sg:province":"Li\u00e8ge",
    "sg:tags":[
        "fence"
    ],
    "wof:name":"Travaux Verts Sa",
    "wof:placetype":"venue"
},
  "geometry": {"coordinates":[5.5849199295,50.6724891663],"type":"Point"}
}