{
  "type": "Feature",
  "properties": {
    "iso:country":"BE",
    "sg:address":"Loostraat 47",
    "sg:city":"Maasmechelen (vucht)",
    "sg:classifiers":[
        {
            "category":"Freight",
            "type":"Transportation"
        }
    ],
    "sg:phone":"+32 475 28 62 70",
    "sg:postcode":"3630",
    "sg:province":"Limburg",
    "sg:tags":[
        "-",
        "transport"
    ],
    "wof:name":"Cst - Roadteam",
    "wof:placetype":"venue"
},
  "geometry": {"coordinates":[5.6961350441,50.963848114],"type":"Point"}
}