{
  "type": "Feature",
  "properties": {
    "addr:full":"Blauwe Gaanweg 53 Kruibeke (bazel) Oost-Vlaanderen 9150",
    "addr:housenumber":"53",
    "addr:postcode":"9150",
    "addr:street":"Blauwe Gaanweg",
    "iso:country":"BE",
    "sg:address":"Blauwe Gaanweg 53",
    "sg:city":"Kruibeke (bazel)",
    "sg:classifiers":[
        {
            "category":"Professional",
            "subcategory":"Management & Consulting",
            "type":"Services"
        }
    ],
    "sg:phone":"+32 475 72 94 36",
    "sg:postcode":"9150",
    "sg:province":"Oost-Vlaanderen",
    "sg:tags":[
        "-",
        "processing",
        "data",
        "consultant"
    ],
    "wof:name":"Marble Consulting Bvba",
    "wof:placetype":"venue"
},
  "geometry": {"coordinates":[4.3020558357,51.1376991272],"type":"Point"}
}