{
  "type": "Feature",
  "properties": {
    "addr:full":"Magerhillestraat 22a Zedelgem West-Vlaanderen 8210",
    "addr:housenumber":"22a",
    "addr:postcode":"8210",
    "addr:street":"Magerhillestraat",
    "iso:country":"BE",
    "sg:address":"Magerhillestraat 22a",
    "sg:city":"Zedelgem",
    "sg:classifiers":[
        {
            "category":"Professional",
            "subcategory":"Engineering",
            "type":"Services"
        }
    ],
    "sg:phone":"+32 50 25 04 51",
    "sg:postcode":"8210",
    "sg:province":"West-Vlaanderen",
    "sg:tags":[
        "workshop"
    ],
    "wof:name":"Pmc Engineering Nv",
    "wof:placetype":"venue"
},
  "geometry": {"coordinates":[3.1458399296,51.1376457214],"type":"Point"}
}