{
  "type": "Feature",
  "properties": {
    "addr:full":"Avenue Du Roi-soldat 30 Anderlecht/anderlecht Bruxelles-Capitale 1070",
    "addr:housenumber":"30",
    "addr:postcode":"1070",
    "addr:street":"Avenue Du Roi-Soldat",
    "iso:country":"BE",
    "sg:address":"Avenue Du Roi-soldat 30",
    "sg:city":"Anderlecht/anderlecht",
    "sg:orig_category":"Avocats and conseillers juridiques",
    "sg:phone":"+32 2 523 35 98",
    "sg:postcode":"1070",
    "sg:province":"Bruxelles-Capitale",
    "wof:name":"A. Van Cauter",
    "wof:placetype":"venue"
},
  "geometry": {"coordinates":[4.3002147675,50.8316192627],"type":"Point"}
}