{
  "type": "Feature",
  "properties": {
    "addr:full":"Moeshofstraat 120 Antwerpen Antwerpen 2170",
    "addr:housenumber":"120",
    "addr:postcode":"2170",
    "addr:street":"Moeshofstraat",
    "iso:country":"BE",
    "sg:address":"Moeshofstraat 120",
    "sg:city":"Antwerpen",
    "sg:classifiers":[
        {
            "category":"Fast Food",
            "type":"Food & Drink"
        }
    ],
    "sg:phone":"+32 3 646 96 57",
    "sg:postcode":"2170",
    "sg:province":"Antwerpen",
    "sg:tags":[
        "meeneem",
        "restaurant"
    ],
    "wof:name":"China House",
    "wof:placetype":"venue"
},
  "geometry": {"coordinates":[4.4505147934,51.246723175],"type":"Point"}
}