{
  "type": "Feature",
  "properties": {
    "addr:full":"Beukenlaan 39 Dendermonde Oost-Vlaanderen 9200",
    "addr:housenumber":"39",
    "addr:postcode":"9200",
    "addr:street":"Beukenlaan;Oost-Vlaanderen",
    "iso:country":"BE",
    "sg:address":"Beukenlaan 39",
    "sg:city":"Dendermonde",
    "sg:classifiers":[
        {
            "category":"Building & Trades",
            "subcategory":"Cleaning & Sanitation",
            "type":"Services"
        }
    ],
    "sg:phone":"+32 52 22 41 97",
    "sg:postcode":"9200",
    "sg:province":"Oost-Vlaanderen",
    "sg:tags":[
        "cleaner",
        "window"
    ],
    "wof:name":"Glazenwasserij Van Den Broeck",
    "wof:placetype":"venue"
},
  "geometry": {"coordinates":[4.1164708138,51.0298919678],"type":"Point"}
}