{
  "type": "Feature",
  "properties": {
    "iso:country":"BE",
    "sg:address":"Stationsstraat 37",
    "sg:city":"Overijse",
    "sg:orig_category":"Herstelling horloges and juwelen Juwelen and horloges",
    "sg:phone":"+32 2 687 73 80",
    "sg:postcode":"3090",
    "sg:province":"Vlaams-Brabant",
    "wof:name":"Zigopa",
    "wof:placetype":"venue"
},
  "geometry": {"coordinates":[4.5353960991,50.7712554932],"type":"Point"}
}