{
  "type": "Feature",
  "properties": {
    "iso:country":"BE",
    "sg:address":"Langestraat 46",
    "sg:city":"Hulshout",
    "sg:orig_category":"Installation de menuiserie m\u00e9tallique",
    "sg:phone":"+32 16 69 90 46",
    "sg:postcode":"2235",
    "sg:province":"Antwerpen",
    "wof:name":"Mario Put",
    "wof:placetype":"venue"
},
  "geometry": {"coordinates":[4.8057727814,51.0390586853],"type":"Point"}
}