{
  "type": "Feature",
  "properties": {
    "iso:country":"BE",
    "sg:address":"Rue Nazareth 13",
    "sg:city":"Herve",
    "sg:orig_category":"Installatie van houten of kunststof schrijnwerk Landbouwmachines Gh Meubelzaken, woning- and keukeni",
    "sg:phone":"+32 87 67 81 97",
    "sg:postcode":"4651",
    "sg:province":"Li\u00e8ge",
    "wof:name":"D\u00c9cor Et Jardin",
    "wof:placetype":"venue"
},
  "geometry": {"coordinates":[5.8010401726,50.6473197937],"type":"Point"}
}