{
  "type": "Feature",
  "properties": {
    "addr:full":"Quai De Longdoz 79 Li\u00e8ge 1 (li\u00e8ge 2) Li\u00e8ge 4020",
    "addr:housenumber":"79;1;2",
    "addr:postcode":"4020",
    "addr:street":"Quai De Longdoz",
    "iso:country":"BE",
    "sg:address":"Quai De Longdoz 79",
    "sg:city":"Li\u00e8ge 1 (li\u00e8ge 2)",
    "sg:classifiers":[
        {
            "category":"Health Services",
            "subcategory":"Nursing And Care Facility",
            "type":"Services"
        }
    ],
    "sg:phone":"+32 4 343 46 01",
    "sg:postcode":"4020",
    "sg:province":"Li\u00e8ge",
    "sg:tags":[
        "home",
        "rest"
    ],
    "wof:name":"Maison Du Parc",
    "wof:placetype":"venue"
},
  "geometry": {"coordinates":[5.5800151825,50.6364440918],"type":"Point"}
}