{
  "type": "Feature",
  "properties": {
    "addr:full":"Rue De Brabant 87-89 Bruxelles (schaerbeek) Bruxelles-Capitale 1030",
    "addr:housenumber":"87-89",
    "addr:postcode":"1030",
    "addr:street":"Rue De Brabant",
    "iso:country":"BE",
    "sg:address":"Rue De Brabant 87-89",
    "sg:city":"Bruxelles (schaerbeek)",
    "sg:classifiers":[
        {
            "category":"Shopping",
            "subcategory":"Gifts & Souvenirs",
            "type":"Retail Goods"
        }
    ],
    "sg:phone":"+32 2 219 77 07",
    "sg:postcode":"1030",
    "sg:province":"Bruxelles-Capitale",
    "sg:tags":[
        "-"
    ],
    "wof:name":"Sofabel",
    "wof:placetype":"venue"
},
  "geometry": {"coordinates":[4.3633651733,50.8606567383],"type":"Point"}
}