{
  "type": "Feature",
  "properties": {
    "addr:full":"Corbiestraat 95 Mol Antwerpen 2400",
    "addr:housenumber":"95",
    "addr:postcode":"2400",
    "addr:street":"Corbiestraat",
    "iso:country":"BE",
    "sg:address":"Corbiestraat 95",
    "sg:city":"Mol",
    "sg:orig_category":"Avocats and conseillers juridiques",
    "sg:phone":"+32 14 31 95 46",
    "sg:postcode":"2400",
    "sg:province":"Antwerpen",
    "wof:name":"M. Vanhoof",
    "wof:placetype":"venue"
},
  "geometry": {"coordinates":[5.1167612076,51.1883964539],"type":"Point"}
}