{
  "type": "Feature",
  "properties": {
    "addr:full":"Fortuinstraat 59 Maldegem Oost-Vlaanderen 9990",
    "addr:housenumber":"59",
    "addr:postcode":"9990",
    "addr:street":"Fortuinstraat",
    "iso:country":"BE",
    "sg:address":"Fortuinstraat 59",
    "sg:city":"Maldegem",
    "sg:orig_category":"Entretien and r\u00e9parations de voitures",
    "sg:phone":"+32 477 30 21 72",
    "sg:postcode":"9990",
    "sg:province":"Oost-Vlaanderen",
    "wof:name":"Garage Vanhecke",
    "wof:placetype":"venue"
},
  "geometry": {"coordinates":[3.4411010742,51.2402954102],"type":"Point"}
}