{
  "type": "Feature",
  "properties": {
    "addr:full":"Chauss\u00c9e De Bruxelles 212c Waterloo Brabant Wallon 1410",
    "addr:housenumber":"212c",
    "addr:postcode":"1410",
    "addr:street":"Chausse\u0301E De Bruxelles",
    "iso:country":"BE",
    "sg:address":"Chauss\u00c9e De Bruxelles 212c",
    "sg:city":"Waterloo",
    "sg:orig_category":"Binnenhuisarchitecten Installatie van houten of kunststof schrijnwerk Woningbouw",
    "sg:phone":"+32 2 351 47 16",
    "sg:postcode":"1410",
    "sg:province":"Brabant Wallon",
    "wof:name":"Bureau Trans-arch",
    "wof:placetype":"venue"
},
  "geometry": {"coordinates":[4.3976540565,50.7182235718],"type":"Point"}
}