{
  "type": "Feature",
  "properties": {
    "iso:country":"BE",
    "sg:address":"Oude Siemerstraat 16",
    "sg:city":"Bilzen (munsterbilzen)",
    "sg:classifiers":[
        {
            "category":"Bars & Pubs",
            "type":"Food & Drink"
        }
    ],
    "sg:phone":"+32 89 50 36 08",
    "sg:postcode":"3740",
    "sg:province":"Limburg",
    "wof:name":"Smid (de)",
    "wof:placetype":"venue"
},
  "geometry": {"coordinates":[5.5226330757,50.8977127075],"type":"Point"}
}