{
  "type": "Feature",
  "properties": {
    "addr:full":"Jan Van Drogenbroeck 37 Sint-amands Antwerpen 2890",
    "addr:housenumber":"37",
    "addr:postcode":"2890",
    "addr:street":"Jan;Drogenbroeck",
    "iso:country":"BE",
    "sg:address":"Jan Van Drogenbroeck 37",
    "sg:city":"Sint-amands",
    "sg:orig_category":"Royal Canin. Services pour animaux domestiques",
    "sg:phone":"+32 52 33 28 13",
    "sg:postcode":"2890",
    "sg:province":"Antwerpen",
    "wof:name":"Wielands",
    "wof:placetype":"venue"
},
  "geometry": {"coordinates":[4.2062039375,51.0567932129],"type":"Point"}
}