{
  "type": "Feature",
  "properties": {
    "addr:full":"Rue De Carajoly 41 Fleurus Hainaut 6224",
    "addr:housenumber":"41",
    "addr:postcode":"6224",
    "addr:street":"Rue De Carajoly",
    "iso:country":"BE",
    "sg:address":"Rue De Carajoly 41",
    "sg:city":"Fleurus",
    "sg:orig_category":"Elektrische installaties voor woningen",
    "sg:phone":"+32 71 81 47 28",
    "sg:postcode":"6224",
    "sg:province":"Hainaut",
    "wof:name":"Giordano Borgu",
    "wof:placetype":"venue"
},
  "geometry": {"coordinates":[4.5751328468,50.4562301636],"type":"Point"}
}