{
  "type": "Feature",
  "properties": {
    "iso:country":"BE",
    "sg:address":"Gemeenteplein 8",
    "sg:city":"Hoegaarden",
    "sg:orig_category":"Boucheries",
    "sg:phone":"+32 16 76 62 79",
    "sg:postcode":"3320",
    "sg:province":"Vlaams-Brabant",
    "wof:name":"Slagerij Vangramberen",
    "wof:placetype":"venue"
},
  "geometry": {"coordinates":[4.887155056,50.7734794617],"type":"Point"}
}