{
  "type": "Feature",
  "properties": {
    "addr:full":"Gentse Steenweg 348 Lokeren Oost-Vlaanderen 9160",
    "addr:housenumber":"348",
    "addr:postcode":"9160",
    "addr:street":"Gentse Steenweg",
    "iso:country":"BE",
    "sg:address":"Gentse Steenweg 348",
    "sg:city":"Lokeren",
    "sg:orig_category":"V\u00e9hicules automobiles",
    "sg:phone":"+32 495 40 25 11",
    "sg:postcode":"9160",
    "sg:province":"Oost-Vlaanderen",
    "wof:name":"Ybo-auto",
    "wof:placetype":"venue"
},
  "geometry": {"coordinates":[3.9164509773,51.1105003357],"type":"Point"}
}