{
  "type": "Feature",
  "properties": {
    "iso:country":"BE",
    "sg:address":"Rue Phocas Lejeune 30",
    "sg:city":"Gembloux",
    "sg:orig_category":"Woningbouw",
    "sg:phone":"+32 81 56 97 56",
    "sg:postcode":"5032",
    "sg:province":"Namur",
    "wof:name":"Nortex",
    "wof:placetype":"venue"
},
  "geometry": {"coordinates":[4.7220830917,50.4997901917],"type":"Point"}
}