{
  "type": "Feature",
  "properties": {
    "iso:country":"BE",
    "sg:address":"Rue Josaphat 104",
    "sg:city":"Schaarbeek/schaerbeek",
    "sg:orig_category":"Boucheries",
    "sg:phone":"+32 2 242 01 81",
    "sg:postcode":"1030",
    "sg:province":"Bruxelles-Capitale",
    "wof:name":"Boucherie Agazar",
    "wof:placetype":"venue"
},
  "geometry": {"coordinates":[4.3742218018,50.8583335876],"type":"Point"}
}