{
  "type": "Feature",
  "properties": {
    "addr:full":"Chauss\u00e9e De Wavre 392 Grez-doiceau Brabant Wallon 1390",
    "addr:housenumber":"392",
    "addr:postcode":"1390",
    "addr:street":"Chausse\u0301E De Wavre",
    "iso:country":"BE",
    "sg:address":"Chauss\u00e9e De Wavre 392",
    "sg:city":"Grez-doiceau",
    "sg:classifiers":[
        {
            "category":"Building & Trades",
            "subcategory":"Construction",
            "type":"Services"
        }
    ],
    "sg:phone":"+32 10 84 49 55",
    "sg:postcode":"1390",
    "sg:province":"Brabant Wallon",
    "sg:tags":[
        "carpenter"
    ],
    "wof:name":"Mabille Masset Sprl",
    "wof:placetype":"venue"
},
  "geometry": {"coordinates":[4.6510519981,50.735408783],"type":"Point"}
}