{
  "type": "Feature",
  "properties": {
    "iso:country":"BE",
    "sg:address":"Rue De La Longue-haie 10",
    "sg:city":"Hamois",
    "sg:orig_category":"Installation \u00e9lectrique r\u00e9sidentielle",
    "sg:phone":"+32 83 21 43 91",
    "sg:postcode":"5360",
    "sg:province":"Namur",
    "wof:name":"E. Poulin",
    "wof:placetype":"venue"
},
  "geometry": {"coordinates":[5.0497488976,50.3393669128],"type":"Point"}
}