{
  "type": "Feature",
  "properties": {
    "iso:country":"BE",
    "sg:address":"Rue Neuve 15",
    "sg:city":"Herve",
    "sg:orig_category":"Journaux. Tabac. Librairies. Fournitures de bureau",
    "sg:phone":"+32 87 66 02 28",
    "sg:postcode":"4650",
    "sg:province":"Li\u00e8ge",
    "wof:name":"La Plume D'oie",
    "wof:placetype":"venue"
},
  "geometry": {"coordinates":[5.7909760475,50.6384429932],"type":"Point"}
}