{
  "type": "Feature",
  "properties": {
    "iso:country":"BE",
    "sg:address":"Hollandstraat 56",
    "sg:city":"Antwerpen",
    "sg:classifiers":[
        {
            "category":"Personal",
            "subcategory":"Psychics & Astrologers",
            "type":"Services"
        }
    ],
    "sg:phone":"+32 477 77 55 49",
    "sg:postcode":"2060",
    "sg:province":"Antwerpen",
    "sg:tags":[
        "astrology"
    ],
    "wof:name":"Batouly",
    "wof:placetype":"venue"
},
  "geometry": {"coordinates":[4.4196228981,51.2231178284],"type":"Point"}
}