{
  "type": "Feature",
  "properties": {
    "addr:full":"Oeyvaersbosch 12 Aartselaar Antwerpen 2630",
    "addr:housenumber":"12",
    "addr:postcode":"2630",
    "addr:street":"Oeyvaersbosch",
    "iso:country":"BE",
    "sg:address":"Oeyvaersbosch 12",
    "sg:city":"Aartselaar",
    "sg:classifiers":[
        {
            "category":"Wholesale",
            "subcategory":"Medical Equipment & Supplies",
            "type":"Manufacturing & Wholesale Goods"
        }
    ],
    "sg:phone":"+32 3 870 11 11",
    "sg:postcode":"2630",
    "sg:province":"Antwerpen",
    "sg:tags":[
        "instrument",
        "apparatus"
    ],
    "wof:name":"Meda Nv",
    "wof:placetype":"venue"
},
  "geometry": {"coordinates":[4.3777461052,51.1227035522],"type":"Point"}
}