{
  "type": "Feature",
  "properties": {
    "addr:full":"Guido Gezellestraat 16b Denderleeuw Oost-Vlaanderen 9470",
    "addr:housenumber":"16b",
    "addr:postcode":"9470",
    "addr:street":"Guido Gezellestraat",
    "iso:country":"BE",
    "sg:address":"Guido Gezellestraat 16b",
    "sg:city":"Denderleeuw",
    "sg:classifiers":[
        {
            "category":"Bars & Pubs",
            "type":"Food & Drink"
        }
    ],
    "sg:phone":"+32 478 77 65 58",
    "sg:postcode":"9470",
    "sg:province":"Oost-Vlaanderen",
    "wof:name":"Moby's",
    "wof:placetype":"venue"
},
  "geometry": {"coordinates":[4.080520153,50.8842697144],"type":"Point"}
}