{
  "type": "Feature",
  "properties": {
    "addr:full":"Moorstraat 8 Puurs Antwerpen 2870",
    "addr:housenumber":"8",
    "addr:postcode":"2870",
    "addr:street":"Moorstraat",
    "iso:country":"BE",
    "sg:address":"Moorstraat 8",
    "sg:city":"Puurs",
    "sg:orig_category":"Groententeelt",
    "sg:phone":"+32 3 886 93 80",
    "sg:postcode":"2870",
    "sg:province":"Antwerpen",
    "wof:name":"Schelfhout G. & H.",
    "wof:placetype":"venue"
},
  "geometry": {"coordinates":[4.3223137856,51.0529937744],"type":"Point"}
}