{
  "type": "Feature",
  "properties": {
    "iso:country":"BE",
    "sg:address":"Hannuitsesteenweg 216",
    "sg:city":"Landen",
    "sg:orig_category":"Artsen and specialisten",
    "sg:phone":"+32 11 83 26 58",
    "sg:postcode":"3401",
    "sg:province":"Vlaams-Brabant",
    "wof:name":"Renaat Mattheus",
    "wof:placetype":"venue"
},
  "geometry": {"coordinates":[5.0810332298,50.732711792],"type":"Point"}
}