{
  "type": "Feature",
  "properties": {
    "iso:country":"BE",
    "sg:address":"Rue De Colnet 1",
    "sg:city":"Charleroi (jumet)",
    "sg:classifiers":[
        {
            "category":"Building & Trades",
            "subcategory":"Construction",
            "type":"Services"
        }
    ],
    "sg:phone":"+32 71 41 98 97",
    "sg:postcode":"6040",
    "sg:province":"Hainaut",
    "sg:tags":[
        "installation",
        "-",
        "central",
        "heating"
    ],
    "wof:name":"Lagneau P",
    "wof:placetype":"venue"
},
  "geometry": {"coordinates":[4.4725809097,50.4424781799],"type":"Point"}
}