{
  "type": "Feature",
  "properties": {
    "addr:full":"Rue De Harz\u00c9 14 La Roche-en-ardenne Luxembourg 6980",
    "addr:housenumber":"14",
    "addr:postcode":"6980",
    "addr:street":"Rue De Harze\u0301",
    "iso:country":"BE",
    "sg:address":"Rue De Harz\u00c9 14",
    "sg:city":"La Roche-en-ardenne",
    "sg:classifiers":[
        {
            "category":"Social Services",
            "subcategory":"Job Training",
            "type":"Services"
        }
    ],
    "sg:phone":"+32 84 41 15 59",
    "sg:postcode":"6980",
    "sg:province":"Luxembourg",
    "sg:tags":[
        "de",
        "terrain",
        "camping"
    ],
    "wof:name":"Camping Benelux",
    "wof:placetype":"venue"
},
  "geometry": {"coordinates":[5.5769510269,50.1895523071],"type":"Point"}
}