{
  "type": "Feature",
  "properties": {
    "iso:country":"BE",
    "sg:address":"Sparrenlaan 6",
    "sg:city":"Brasschaat",
    "sg:orig_category":"Juwelen and horloges",
    "sg:phone":"+32 3 653 02 67",
    "sg:postcode":"2930",
    "sg:province":"Antwerpen",
    "wof:name":"Christophe De Ranter",
    "wof:placetype":"venue"
},
  "geometry": {"coordinates":[4.4566440582,51.2973213196],"type":"Point"}
}