{
  "type": "Feature",
  "properties": {
    "addr:full":"Cuylitsstraat 23 Antwerpen Antwerpen 2018",
    "addr:housenumber":"23",
    "addr:postcode":"2018",
    "addr:street":"Cuylitsstraat",
    "iso:country":"BE",
    "sg:address":"Cuylitsstraat 23",
    "sg:city":"Antwerpen",
    "sg:classifiers":[
        {
            "category":"Health Services",
            "subcategory":"Doctor",
            "type":"Services"
        }
    ],
    "sg:phone":"+32 3 238 51 62",
    "sg:postcode":"2018",
    "sg:province":"Antwerpen",
    "sg:tags":[
        "medicinephysicians",
        "surgeon"
    ],
    "wof:name":"Devriendt P",
    "wof:placetype":"venue"
},
  "geometry": {"coordinates":[4.3939571381,51.2046356201],"type":"Point"}
}