{
  "type": "Feature",
  "properties": {
    "addr:full":"Dr\u00c8ve De Linkebeek 43 Sint-genesius-rode/rhode-saint-genese Vlaams-Brabant 1640",
    "addr:housenumber":"43",
    "addr:postcode":"1640",
    "addr:street":"Dre\u0300Ve De Linkebeek",
    "iso:country":"BE",
    "sg:address":"Dr\u00c8ve De Linkebeek 43",
    "sg:city":"Sint-genesius-rode/rhode-saint-genese",
    "sg:orig_category":"Artistes ind\u00e9pendants",
    "sg:phone":"+32 2 358 15 78",
    "sg:postcode":"1640",
    "sg:province":"Vlaams-Brabant",
    "wof:name":"Marie Lejeune",
    "wof:placetype":"venue"
},
  "geometry": {"coordinates":[4.3730578423,50.7597770691],"type":"Point"}
}