{
  "type": "Feature",
  "properties": {
    "addr:full":"Oude Tervuursebaan 78 Bertem Vlaams-Brabant 3060",
    "addr:housenumber":"78",
    "addr:postcode":"3060",
    "addr:street":"Oude Tervuursebaan",
    "iso:country":"BE",
    "sg:address":"Oude Tervuursebaan 78",
    "sg:city":"Bertem",
    "sg:classifiers":[
        {
            "category":"Professional",
            "subcategory":"Accounting & Tax Preparation",
            "type":"Services"
        }
    ],
    "sg:phone":"+32 16 48 04 21",
    "sg:postcode":"3060",
    "sg:province":"Vlaams-Brabant",
    "sg:tags":[
        "accountant"
    ],
    "wof:name":"Advisers Associates Dfk",
    "wof:placetype":"venue"
},
  "geometry": {"coordinates":[4.6188058853,50.8636016846],"type":"Point"}
}