{
  "type": "Feature",
  "properties": {
    "iso:country":"BE",
    "sg:address":"Rue Du Coll\u00e8ge 2",
    "sg:city":"Verviers",
    "sg:classifiers":[
        {
            "category":"Utilities",
            "subcategory":"Mobile Phone",
            "type":"Services"
        }
    ],
    "sg:phone":"+32 800 33 800",
    "sg:postcode":"4800",
    "sg:province":"Li\u00e8ge",
    "sg:tags":[
        "-",
        "gsm"
    ],
    "wof:name":"Teleboutique Belgacom",
    "wof:placetype":"venue"
},
  "geometry": {"coordinates":[5.8649301529,50.5946006775],"type":"Point"}
}