{
  "type": "Feature",
  "properties": {
    "addr:full":"Gontrode Heirweg 73 Melle Oost-Vlaanderen 9090",
    "addr:housenumber":"73",
    "addr:postcode":"9090",
    "addr:street":"Gontrode Heirweg",
    "iso:country":"BE",
    "sg:address":"Gontrode Heirweg 73",
    "sg:city":"Melle",
    "sg:classifiers":[
        {
            "category":"Manufacturing",
            "subcategory":"Electronics",
            "type":"Manufacturing & Wholesale Goods"
        }
    ],
    "sg:phone":"+32 9 210 40 70",
    "sg:postcode":"9090",
    "sg:province":"Oost-Vlaanderen",
    "sg:tags":[
        "telecommunication",
        "system"
    ],
    "wof:name":"Effect Nv",
    "wof:placetype":"venue"
},
  "geometry": {"coordinates":[3.7669620514,51.0146446228],"type":"Point"}
}