{
  "type": "Feature",
  "properties": {
    "iso:country":"BE",
    "sg:address":"Ch\u00c9e De Philippeville 207bb",
    "sg:city":"Gerpinnes",
    "sg:orig_category":"Electrom\u00e9nager, t\u00e9l\u00e9visions and radios",
    "sg:phone":"+32 71 21 58 71",
    "sg:postcode":"6280",
    "sg:province":"Hainaut",
    "wof:name":"Druart",
    "wof:placetype":"venue"
},
  "geometry": {"coordinates":[4.4755711555,50.3329162598],"type":"Point"}
}