{
  "type": "Feature",
  "properties": {
    "iso:country":"BE",
    "sg:address":"Rue C\u00e9sar Franck 9",
    "sg:city":"Plombi\u00e8res (gemmenich)",
    "sg:classifiers":[
        {
            "category":"Bars & Pubs",
            "type":"Food & Drink"
        }
    ],
    "sg:phone":"+32 87 78 55 19",
    "sg:postcode":"4851",
    "sg:province":"Li\u00e8ge",
    "wof:name":"Kerf Caf\u00e9",
    "wof:placetype":"venue"
},
  "geometry": {"coordinates":[5.9958901405,50.745765686],"type":"Point"}
}