{
  "type": "Feature",
  "properties": {
    "iso:country":"BE",
    "sg:address":"Chauss\u00e9e De Li\u00e8ge 45",
    "sg:city":"Namur (jambes)",
    "sg:classifiers":[
        {
            "category":"Communications",
            "subcategory":"Film & Video Production",
            "type":"Services"
        }
    ],
    "sg:phone":"+32 81 30 15 18",
    "sg:postcode":"5100",
    "sg:province":"Namur",
    "sg:tags":[
        "mirror"
    ],
    "wof:name":"Miroiterie Jamboise Sa",
    "wof:placetype":"venue"
},
  "geometry": {"coordinates":[4.8713750839,50.4566345215],"type":"Point"}
}