{
  "type": "Feature",
  "properties": {
    "iso:country":"BE",
    "sg:address":"Fazantendreef 9",
    "sg:city":"Wuustwezel",
    "sg:orig_category":"Artsen and specialisten",
    "sg:phone":"+32 3 633 27 57",
    "sg:postcode":"2990",
    "sg:province":"Antwerpen",
    "wof:name":"E. Carlier",
    "wof:placetype":"venue"
},
  "geometry": {"coordinates":[4.5503058434,51.34948349],"type":"Point"}
}