{
  "type": "Feature",
  "properties": {
    "addr:full":"Ijzerlaan 24 Etterbeek/etterbeek Bruxelles-Capitale 1040",
    "addr:housenumber":"24",
    "addr:postcode":"1040",
    "addr:street":"Ijzerlaan",
    "iso:country":"BE",
    "sg:address":"Ijzerlaan 24",
    "sg:city":"Etterbeek/etterbeek",
    "sg:orig_category":"Industri\u00eble and commerci\u00eble bouw",
    "sg:phone":"+32 2 733 99 90",
    "sg:postcode":"1040",
    "sg:province":"Bruxelles-Capitale",
    "wof:name":"Soberi International",
    "wof:placetype":"venue"
},
  "geometry": {"coordinates":[4.3962898254,50.8416557312],"type":"Point"}
}