{
  "type": "Feature",
  "properties": {
    "addr:full":"Gezondheidslei 41 Brasschaat Antwerpen 2930",
    "addr:housenumber":"41",
    "addr:postcode":"2930",
    "addr:street":"Gezondheidslei",
    "iso:country":"BE",
    "sg:address":"Gezondheidslei 41",
    "sg:city":"Brasschaat",
    "sg:orig_category":"Plomberie, chauffage and installations sanitaires",
    "sg:phone":"+32 3 664 18 23",
    "sg:postcode":"2930",
    "sg:province":"Antwerpen",
    "wof:name":"Verwarming Moerbeek",
    "wof:placetype":"venue"
},
  "geometry": {"coordinates":[4.4453401566,51.2943305969],"type":"Point"}
}