{
  "type": "Feature",
  "properties": {
    "iso:country":"BE",
    "sg:address":"Park Tremeland 69",
    "sg:city":"Tremelo",
    "sg:classifiers":[
        {
            "category":"Social Services",
            "subcategory":"Job Training",
            "type":"Services"
        }
    ],
    "sg:phone":"+32 16 52 08 62",
    "sg:postcode":"3120",
    "sg:province":"Vlaams-Brabant",
    "sg:tags":[
        "personnel",
        "-selection",
        "recruitment"
    ],
    "wof:name":"Excelerate Bvba",
    "wof:placetype":"venue"
},
  "geometry": {"coordinates":[4.7247900963,51.0051651001],"type":"Point"}
}