{
  "type": "Feature",
  "properties": {
    "addr:full":"Kerkstraat 5 Heers Limburg 3870",
    "addr:housenumber":"5",
    "addr:postcode":"3870",
    "addr:street":"Kerkstraat",
    "iso:country":"BE",
    "sg:address":"Kerkstraat 5",
    "sg:city":"Heers",
    "sg:orig_category":"Huishoudapparaten, televisies and radio's",
    "sg:phone":"+32 11 48 16 07",
    "sg:postcode":"3870",
    "sg:province":"Limburg",
    "wof:name":"Vancattendijck Electro",
    "wof:placetype":"venue"
},
  "geometry": {"coordinates":[5.3048739433,50.7625808716],"type":"Point"}
}