{
  "type": "Feature",
  "properties": {
    "iso:country":"BE",
    "sg:address":"Rue Des Combattants 2",
    "sg:city":"Berloz",
    "sg:orig_category":"Diensten voor huisdieren",
    "sg:phone":"+32 19 32 67 00",
    "sg:postcode":"4257",
    "sg:province":"Li\u00e8ge",
    "wof:name":"Aff\u00dbtage Servideal",
    "wof:placetype":"venue"
},
  "geometry": {"coordinates":[5.1892309189,50.707233429],"type":"Point"}
}