{
  "type": "Feature",
  "properties": {
    "addr:full":"Rue E. Claus 43b2 Elsene/ixelles Bruxelles-Capitale 1050",
    "addr:housenumber":"43b2",
    "addr:postcode":"1050",
    "addr:street":"Rue E. Claus",
    "iso:country":"BE",
    "sg:address":"Rue E. Claus 43b2",
    "sg:city":"Elsene/ixelles",
    "sg:orig_category":"Genealogen",
    "sg:phone":"+32 2 649 57 84",
    "sg:postcode":"1050",
    "sg:province":"Bruxelles-Capitale",
    "wof:name":"Etudes G\u00c9n\u00c9alogiques De Neuville",
    "wof:placetype":"venue"
},
  "geometry": {"coordinates":[4.3687791824,50.8160858154],"type":"Point"}
}