{
  "type": "Feature",
  "properties": {
    "addr:full":"Eindhovenlaan 16 Hasselt Limburg 3500",
    "addr:housenumber":"16",
    "addr:postcode":"3500",
    "addr:street":"Eindhovenlaan",
    "iso:country":"BE",
    "sg:address":"Eindhovenlaan 16",
    "sg:city":"Hasselt",
    "sg:classifiers":[
        {
            "category":"Professional",
            "subcategory":"Accounting & Tax Preparation",
            "type":"Services"
        }
    ],
    "sg:phone":"+32 11 22 41 59",
    "sg:postcode":"3500",
    "sg:province":"Limburg",
    "sg:tags":[
        "accountant"
    ],
    "wof:name":"Guy Marechal",
    "wof:placetype":"venue"
},
  "geometry": {"coordinates":[5.3632879257,50.9461250305],"type":"Point"}
}