{
  "type": "Feature",
  "properties": {
    "iso:country":"BE",
    "sg:address":"Rue Du Fays 50",
    "sg:city":"Fosses-la-ville",
    "sg:orig_category":"Plaatsen van vloer- and muurbekleding Schilders",
    "sg:phone":"+32 71 71 17 24",
    "sg:postcode":"5070",
    "sg:province":"Namur",
    "wof:name":"De Boose Fr\u00c8res",
    "wof:placetype":"venue"
},
  "geometry": {"coordinates":[4.6565170288,50.4047203064],"type":"Point"}
}