{
  "type": "Feature",
  "properties": {
    "iso:country":"BE",
    "sg:address":"Rue Des Dominicains 12",
    "sg:city":"Li\u00e8ge 1",
    "sg:classifiers":[
        {
            "category":"Bars & Pubs",
            "type":"Food & Drink"
        }
    ],
    "sg:phone":"+32 4 222 38 96",
    "sg:postcode":"4000",
    "sg:province":"Li\u00e8ge",
    "sg:tags":[
        "tavern"
    ],
    "wof:name":"Artistes (taverne Des)",
    "wof:placetype":"venue"
},
  "geometry": {"coordinates":[5.5700349808,50.6427116394],"type":"Point"}
}