{
  "type": "Feature",
  "properties": {
    "iso:country":"BE",
    "sg:address":"Rijksweg 213",
    "sg:city":"Wielsbeke",
    "sg:orig_category":"Ramassage and traitement des d\u00e9chets m\u00e9nagers",
    "sg:phone":"+32 56 67 33 70",
    "sg:postcode":"8710",
    "sg:province":"West-Vlaanderen",
    "wof:name":"Matcoglas",
    "wof:placetype":"venue"
},
  "geometry": {"coordinates":[3.3749530315,50.9079208374],"type":"Point"}
}