{
  "type": "Feature",
  "properties": {
    "iso:country":"BE",
    "sg:address":"Kortrijksesteenweg 1266",
    "sg:city":"Gent",
    "sg:orig_category":"Goederenvervoer over de weg Verhuisdiensten",
    "sg:phone":"+32 9 282 28 61",
    "sg:postcode":"9051",
    "sg:province":"Oost-Vlaanderen",
    "wof:name":"Vervaet Dirk",
    "wof:placetype":"venue"
},
  "geometry": {"coordinates":[3.6514649391,51.0148277283],"type":"Point"}
}