{
  "type": "Feature",
  "properties": {
    "iso:country":"BE",
    "sg:address":"Kattestraat 74",
    "sg:city":"Aalst",
    "sg:orig_category":"V\u00eatements pour b\u00e9b\u00e9s and enfants. Chaussures. V\u00eatements pour Hommes. V\u00eatements pour Dames. Maroquine",
    "sg:phone":"+32 53 78 73 47",
    "sg:postcode":"9300",
    "sg:province":"Oost-Vlaanderen",
    "wof:name":"Kipling",
    "wof:placetype":"venue"
},
  "geometry": {"coordinates":[4.0360188484,50.9405097961],"type":"Point"}
}