{
  "type": "Feature",
  "properties": {
    "addr:full":"Oude Burkelwegel 2 Maldegem Oost-Vlaanderen 9990",
    "addr:housenumber":"2",
    "addr:postcode":"9990",
    "addr:street":"Oude Burkelwegel",
    "iso:country":"BE",
    "sg:address":"Oude Burkelwegel 2",
    "sg:city":"Maldegem",
    "sg:orig_category":"Forge, Moulage and Profilage des M\u00e9taux. Installation de menuiserie en bois and plastique",
    "sg:phone":"+32 50 71 54 51",
    "sg:postcode":"9990",
    "sg:province":"Oost-Vlaanderen",
    "wof:name":"Dhoore J.",
    "wof:placetype":"venue"
},
  "geometry": {"coordinates":[3.4249749184,51.1961021423],"type":"Point"}
}