{
  "type": "Feature",
  "properties": {
    "iso:country":"BE",
    "sg:address":"M\u00c9lunestraat 22ba",
    "sg:city":"Comines-warneton",
    "sg:orig_category":"Installatie van metalen schrijnwerk SMEEDWERK, METAALBEWERKING AND POEDERMETALLURGIE",
    "sg:phone":"+32 56 58 77 69",
    "sg:postcode":"7783",
    "sg:province":"Hainaut",
    "wof:name":"Bruno Debacq",
    "wof:placetype":"venue"
},
  "geometry": {"coordinates":[2.8828949928,50.7069244385],"type":"Point"}
}