{
  "type": "Feature",
  "properties": {
    "iso:country":"BE",
    "sg:address":"Industrieweg 2",
    "sg:city":"Antwerpen",
    "sg:orig_category":"Plaatsen van vloer- and muurbekleding Schilders",
    "sg:phone":"+32 3 231 10 95",
    "sg:postcode":"2030",
    "sg:province":"Antwerpen",
    "wof:name":"Van Mieghem",
    "wof:placetype":"venue"
},
  "geometry": {"coordinates":[4.3551578522,51.2505989075],"type":"Point"}
}