{
  "type": "Feature",
  "properties": {
    "iso:country":"BE",
    "sg:address":"Rue Ternard 3",
    "sg:city":"Tubize",
    "sg:classifiers":[
        {
            "category":"Building & Trades",
            "subcategory":"Cleaning & Sanitation",
            "type":"Services"
        }
    ],
    "sg:phone":"+32 2 355 17 74",
    "sg:postcode":"1480",
    "sg:province":"Brabant Wallon",
    "sg:tags":[
        "cleaner",
        "window"
    ],
    "wof:name":"Technic-vitres Sprl",
    "wof:placetype":"venue"
},
  "geometry": {"coordinates":[4.2053480148,50.6894683838],"type":"Point"}
}