{
  "type": "Feature",
  "properties": {
    "iso:country":"BE",
    "sg:address":"Biezenstraat 16",
    "sg:city":"Berlare",
    "sg:orig_category":"Kapsalons",
    "sg:phone":"+32 52 42 55 33",
    "sg:postcode":"9290",
    "sg:province":"Oost-Vlaanderen",
    "wof:name":"Felix Verhofstadt",
    "wof:placetype":"venue"
},
  "geometry": {"coordinates":[4.0002250671,51.0168571472],"type":"Point"}
}