{
  "type": "Feature",
  "properties": {
    "addr:full":"Place Andr\u00e9 Ryckmans 13 Namur Namur 5000",
    "addr:housenumber":"13",
    "addr:postcode":"5000",
    "addr:street":"Place Andre\u0301 Ryckmans",
    "iso:country":"BE",
    "sg:address":"Place Andr\u00e9 Ryckmans 13",
    "sg:city":"Namur",
    "sg:classifiers":[
        {
            "category":"Fast Food",
            "type":"Food & Drink"
        }
    ],
    "sg:phone":"+32 495 76 18 49",
    "sg:postcode":"5000",
    "sg:province":"Namur",
    "sg:tags":[
        "fried",
        "stand",
        "potato"
    ],
    "wof:name":"Autre (l') Fois",
    "wof:placetype":"venue"
},
  "geometry": {"coordinates":[4.8501009941,50.4667167664],"type":"Point"}
}