{
  "type": "Feature",
  "properties": {
    "iso:country":"BE",
    "sg:address":"Place Matt\u00e9otti 35",
    "sg:city":"La Louvi\u00e8re",
    "sg:classifiers":[
        {
            "category":"Insurance",
            "subcategory":"Insurance Agent",
            "type":"Services"
        }
    ],
    "sg:phone":"+32 64 84 88 70",
    "sg:postcode":"7100",
    "sg:province":"Hainaut",
    "sg:tags":[
        "broker"
    ],
    "wof:name":"Jl Malengreaux",
    "wof:placetype":"venue"
},
  "geometry": {"coordinates":[4.1925969124,50.473815918],"type":"Point"}
}