{
  "type": "Feature",
  "properties": {
    "iso:country":"BE",
    "sg:address":"1 Nijverheidslaan",
    "sg:city":"Diest",
    "sg:classifiers":[
        {
            "category":"Professional",
            "subcategory":"Advertising",
            "type":"Services"
        }
    ],
    "sg:phone":"+32 13 32 31 91",
    "sg:postcode":"3290",
    "sg:province":"Vlaams-Brabant",
    "sg:tags":[
        "communication",
        "advice",
        "medium",
        "business"
    ],
    "wof:name":"Mercatron Nv",
    "wof:placetype":"venue"
},
  "geometry": {"coordinates":[5.0482501984,50.9900283813],"type":"Point"}
}