{
  "type": "Feature",
  "properties": {
    "iso:country":"BE",
    "sg:address":"Stationsstraat 53",
    "sg:city":"Kortemark",
    "sg:classifiers":[
        {
            "category":"Bars & Pubs",
            "type":"Food & Drink"
        }
    ],
    "sg:phone":"+32 51 56 62 73",
    "sg:postcode":"8610",
    "sg:province":"West-Vlaanderen",
    "wof:name":"Ons Huis",
    "wof:placetype":"venue"
},
  "geometry": {"coordinates":[3.0435600281,51.0253791809],"type":"Point"}
}