{
  "type": "Feature",
  "properties": {
    "addr:full":"Rekhof 51 Poperinge West-Vlaanderen 8970",
    "addr:housenumber":"51",
    "addr:postcode":"8970",
    "addr:street":"Rekhof",
    "iso:country":"BE",
    "sg:address":"Rekhof 51",
    "sg:city":"Poperinge",
    "sg:orig_category":"Kapsalons",
    "sg:phone":"+32 57 33 58 64",
    "sg:postcode":"8970",
    "sg:province":"West-Vlaanderen",
    "wof:name":"Bettie Keyngnaert",
    "wof:placetype":"venue"
},
  "geometry": {"coordinates":[2.7268650532,50.8524703979],"type":"Point"}
}