{
  "type": "Feature",
  "properties": {
    "addr:full":"Rue Du Chalet 31 Aywaille Li\u00e8ge 4920",
    "addr:housenumber":"31",
    "addr:postcode":"4920",
    "addr:street":"Rue Du Chalet",
    "iso:country":"BE",
    "sg:address":"Rue Du Chalet 31",
    "sg:city":"Aywaille",
    "sg:orig_category":"Benzinestations and brandstoffen",
    "sg:phone":"+32 4 384 48 43",
    "sg:postcode":"4920",
    "sg:province":"Li\u00e8ge",
    "wof:name":"Fe. Laurent",
    "wof:placetype":"venue"
},
  "geometry": {"coordinates":[5.6784701347,50.4702911377],"type":"Point"}
}