{
  "type": "Feature",
  "properties": {
    "iso:country":"BE",
    "sg:address":"Naamsestraat 14",
    "sg:city":"Sint-truiden",
    "sg:orig_category":"Alimentation sp\u00e9cialis\u00e9e",
    "sg:phone":"+32 11 68 18 23",
    "sg:postcode":"3800",
    "sg:province":"Limburg",
    "wof:name":"'t Clockhempoortje",
    "wof:placetype":"venue"
},
  "geometry": {"coordinates":[5.187983036,50.8122634888],"type":"Point"}
}