{
  "type": "Feature",
  "properties": {
    "addr:full":"Heuleplaats 1 Kortrijk (heule) West-Vlaanderen 8501",
    "addr:housenumber":"1",
    "addr:postcode":"8501",
    "addr:street":"Heuleplaats",
    "iso:country":"BE",
    "sg:address":"Heuleplaats 1",
    "sg:city":"Kortrijk (heule)",
    "sg:classifiers":[
        {
            "category":"Bakery",
            "type":"Food & Drink"
        }
    ],
    "sg:phone":"+32 56 35 20 97",
    "sg:postcode":"8501",
    "sg:province":"West-Vlaanderen",
    "sg:tags":[
        "confectioner",
        "baker"
    ],
    "wof:name":"Bossaert N",
    "wof:placetype":"venue"
},
  "geometry": {"coordinates":[3.234680891,50.8433952332],"type":"Point"}
}