{
  "type": "Feature",
  "properties": {
    "addr:full":"Kortrijksesteenweg 19 Gent Oost-Vlaanderen 9000",
    "addr:housenumber":"19",
    "addr:postcode":"9000",
    "addr:street":"Kortrijksesteenweg;Oost-Vlaanderen",
    "iso:country":"BE",
    "sg:address":"Kortrijksesteenweg 19",
    "sg:city":"Gent",
    "sg:orig_category":"Drogisterijen Onderdelen and accessoires voertuigen Gh",
    "sg:phone":"+32 9 222 30 74",
    "sg:postcode":"9000",
    "sg:province":"Oost-Vlaanderen",
    "wof:name":"Kopping",
    "wof:placetype":"venue"
},
  "geometry": {"coordinates":[3.7184760571,51.0412750244],"type":"Point"}
}