{
  "type": "Feature",
  "properties": {
    "addr:full":"Rue De La Boule 40 Quaregnon Hainaut 7390",
    "addr:housenumber":"40",
    "addr:postcode":"7390",
    "addr:street":"Rue De La Boule",
    "iso:country":"BE",
    "sg:address":"Rue De La Boule 40",
    "sg:city":"Quaregnon",
    "sg:classifiers":[
        {
            "category":"Building & Trades",
            "subcategory":"Construction",
            "type":"Services"
        }
    ],
    "sg:phone":"+32 65 67 92 74",
    "sg:postcode":"7390",
    "sg:province":"Hainaut",
    "sg:tags":[
        "asphalt",
        "contractor"
    ],
    "wof:name":"C D C Couvertures & Cd Mat Sprl",
    "wof:placetype":"venue"
},
  "geometry": {"coordinates":[3.8600161076,50.4195365906],"type":"Point"}
}