{
  "type": "Feature",
  "properties": {
    "iso:country":"BE",
    "sg:address":"Rue Du Puits Wagnon 5",
    "sg:city":"Tournai",
    "sg:orig_category":"Opticiens",
    "sg:phone":"+32 69 22 39 53",
    "sg:postcode":"7500",
    "sg:province":"Hainaut",
    "wof:name":"Pierre Clement",
    "wof:placetype":"venue"
},
  "geometry": {"coordinates":[3.3908059597,50.6066322327],"type":"Point"}
}