{
  "type": "Feature",
  "properties": {
    "addr:full":"Route D\u00b4eghez\u00c9e 185 Jemeppe-sur-sambre Namur 5190",
    "addr:housenumber":"185",
    "addr:postcode":"5190",
    "addr:street":"Route D\u00b4Egheze\u0301E",
    "iso:country":"BE",
    "sg:address":"Route D\u00b4eghez\u00c9e 185",
    "sg:city":"Jemeppe-sur-sambre",
    "sg:orig_category":"Entretien and r\u00e9parations de voitures",
    "sg:phone":"+32 71 78 38 34",
    "sg:postcode":"5190",
    "sg:province":"Namur",
    "wof:name":"Garage De L\u00b4orneau",
    "wof:placetype":"venue"
},
  "geometry": {"coordinates":[4.67081213,50.4703445435],"type":"Point"}
}