{
  "type": "Feature",
  "properties": {
    "iso:country":"BE",
    "sg:address":"Cornelis Marckxlaan 17",
    "sg:city":"Kontich",
    "sg:classifiers":[
        {
            "category":"Arena",
            "subcategory":"Sports Club",
            "type":"Entertainment"
        }
    ],
    "sg:phone":"+32 3 457 87 78",
    "sg:postcode":"2550",
    "sg:province":"Antwerpen",
    "sg:tags":[
        "de"
    ],
    "wof:name":"Duffel Basketbalclub",
    "wof:placetype":"venue"
},
  "geometry": {"coordinates":[4.448993206,51.1162338257],"type":"Point"}
}