{
  "type": "Feature",
  "properties": {
    "addr:full":"Rue De La Grotte 13 Mouscron Hainaut 7700",
    "addr:housenumber":"13",
    "addr:postcode":"7700",
    "addr:street":"Rue De La Grotte",
    "iso:country":"BE",
    "sg:address":"Rue De La Grotte 13",
    "sg:city":"Mouscron",
    "sg:classifiers":[
        {
            "category":"Bars & Pubs",
            "type":"Food & Drink"
        }
    ],
    "sg:phone":"+32 56 34 73 27",
    "sg:postcode":"7700",
    "sg:province":"Hainaut",
    "wof:name":"Nouveau Zeno",
    "wof:placetype":"venue"
},
  "geometry": {"coordinates":[3.2013859749,50.7300415039],"type":"Point"}
}