{
  "type": "Feature",
  "properties": {
    "iso:country":"BE",
    "sg:address":"Placette Aux Oignons 5",
    "sg:city":"Tournai",
    "sg:classifiers":[
        {
            "category":"Shopping",
            "subcategory":"Clothing, Apparel, & Fashions",
            "type":"Retail Goods"
        }
    ],
    "sg:phone":"+32 69 76 76 94",
    "sg:postcode":"7500",
    "sg:province":"Hainaut",
    "sg:tags":[
        "underwear",
        "lingerie",
        "-"
    ],
    "wof:name":"Angel",
    "wof:placetype":"venue"
},
  "geometry": {"coordinates":[3.3851680756,50.6079902649],"type":"Point"}
}