{
  "type": "Feature",
  "properties": {
    "iso:country":"BE",
    "sg:address":"Maastrichterstraat 71",
    "sg:city":"Tongeren",
    "sg:orig_category":"Geschenken and souvenirs Speelgoed Verlichting and huishoudartikelen",
    "sg:phone":"+32 12 23 19 69",
    "sg:postcode":"3700",
    "sg:province":"Limburg",
    "wof:name":"Blokker",
    "wof:placetype":"venue"
},
  "geometry": {"coordinates":[5.466837883,50.7821884155],"type":"Point"}
}