{
  "type": "Feature",
  "properties": {
    "addr:full":"Cond\u00e9dreef 28 Kortrijk West-Vlaanderen 8500",
    "addr:housenumber":"28",
    "addr:postcode":"8500",
    "addr:street":"Conde\u0301Dreef",
    "iso:country":"BE",
    "sg:address":"Cond\u00e9dreef 28",
    "sg:city":"Kortrijk",
    "sg:classifiers":[
        {
            "category":"Manufacturing",
            "subcategory":"Textiles",
            "type":"Manufacturing & Wholesale Goods"
        }
    ],
    "sg:phone":"+32 56 22 02 02",
    "sg:postcode":"8500",
    "sg:province":"West-Vlaanderen",
    "sg:tags":[
        "machinery"
    ],
    "wof:name":"Verbeke & Co Bvba",
    "wof:placetype":"venue"
},
  "geometry": {"coordinates":[3.2586870193,50.8191223145],"type":"Point"}
}