{
  "type": "Feature",
  "properties": {
    "iso:country":"BE",
    "sg:address":"Kapelstraat 141",
    "sg:city":"Sint-niklaas",
    "sg:orig_category":"Mat\u00e9riel de contr\u00f4le des processus industriels Fab",
    "sg:phone":"+32 3 776 10 51",
    "sg:postcode":"9100",
    "sg:province":"Oost-Vlaanderen",
    "wof:name":"Jrm",
    "wof:placetype":"venue"
},
  "geometry": {"coordinates":[4.1572561264,51.1517906189],"type":"Point"}
}