{
  "type": "Feature",
  "properties": {
    "addr:full":"Rue Nysten 40 Li\u00e8ge 1 Li\u00e8ge 4000",
    "addr:housenumber":"40;1",
    "addr:postcode":"4000",
    "addr:street":"Rue Nysten",
    "iso:country":"BE",
    "sg:address":"Rue Nysten 40",
    "sg:city":"Li\u00e8ge 1",
    "sg:classifiers":[
        {
            "category":"Professional",
            "subcategory":"Accounting & Tax Preparation",
            "type":"Services"
        }
    ],
    "sg:phone":"+32 4 253 22 22",
    "sg:postcode":"4000",
    "sg:province":"Li\u00e8ge",
    "sg:tags":[
        "accountant"
    ],
    "wof:name":"Geron G",
    "wof:placetype":"venue"
},
  "geometry": {"coordinates":[5.5614271164,50.6334075928],"type":"Point"}
}