{
  "type": "Feature",
  "properties": {
    "iso:country":"BE",
    "sg:address":"Steenweg Op Leopoldsburg 16",
    "sg:city":"Balen",
    "sg:orig_category":"Huisdieren and benodigdheden",
    "sg:phone":"+32 14 81 50 77",
    "sg:postcode":"2490",
    "sg:province":"Antwerpen",
    "wof:name":"Ooms-cuyvers",
    "wof:placetype":"venue"
},
  "geometry": {"coordinates":[5.2379307747,51.1353340149],"type":"Point"}
}