{
  "type": "Feature",
  "properties": {
    "addr:full":"Place Guido Gezelle 32 Bruxelles (ganshoren) Bruxelles-Capitale 1083",
    "addr:housenumber":"32",
    "addr:postcode":"1083",
    "addr:street":"Place Guido Gezelle",
    "iso:country":"BE",
    "sg:address":"Place Guido Gezelle 32",
    "sg:city":"Bruxelles (ganshoren)",
    "sg:classifiers":[
        {
            "category":"Bars & Pubs",
            "type":"Food & Drink"
        }
    ],
    "sg:phone":"+32 2 424 10 25",
    "sg:postcode":"1083",
    "sg:province":"Bruxelles-Capitale",
    "wof:name":"Sports (des)",
    "wof:placetype":"venue"
},
  "geometry": {"coordinates":[4.3134908676,50.8736724854],"type":"Point"}
}