{
  "type": "Feature",
  "properties": {
    "addr:full":"Rue Bronromme 991 Theux Li\u00e8ge 4910",
    "addr:housenumber":"991",
    "addr:postcode":"4910",
    "addr:street":"Rue Bronromme",
    "iso:country":"BE",
    "sg:address":"Rue Bronromme 991",
    "sg:city":"Theux",
    "sg:orig_category":"Eleveurs de bovins",
    "sg:phone":"+32 87 37 60 94",
    "sg:postcode":"4910",
    "sg:province":"Li\u00e8ge",
    "wof:name":"Jean Mack",
    "wof:placetype":"venue"
},
  "geometry": {"coordinates":[5.8081498146,50.4446868896],"type":"Point"}
}