{
  "type": "Feature",
  "properties": {
    "iso:country":"BE",
    "sg:address":"Chauss\u00e9e De Charleroi 359",
    "sg:city":"Fosses-la-ville (le Roux)",
    "sg:classifiers":[
        {
            "category":"Building & Trades",
            "subcategory":"Equipment Rental",
            "type":"Services"
        }
    ],
    "sg:phone":"+32 71 71 16 56",
    "sg:postcode":"5070",
    "sg:province":"Namur",
    "sg:tags":[
        "use",
        "apparatus",
        "tool",
        "-",
        "professional",
        "machines"
    ],
    "wof:name":"L.v.m. Sc",
    "wof:placetype":"venue"
},
  "geometry": {"coordinates":[4.6720647812,50.3931503296],"type":"Point"}
}