{
  "type": "Feature",
  "properties": {
    "addr:full":"Jeugdlaan 131 Heusden-zolder (zolder) Limburg 3550",
    "addr:housenumber":"131",
    "addr:postcode":"3550",
    "addr:street":"Jeugdlaan",
    "iso:country":"BE",
    "sg:address":"Jeugdlaan 131",
    "sg:city":"Heusden-zolder (zolder)",
    "sg:classifiers":[
        {
            "category":"Building & Trades",
            "subcategory":"Landscaping Services",
            "type":"Services"
        }
    ],
    "sg:phone":"+32 11 43 70 14",
    "sg:postcode":"3550",
    "sg:province":"Limburg",
    "sg:tags":[
        "nurseryman"
    ],
    "wof:name":"Vandael P",
    "wof:placetype":"venue"
},
  "geometry": {"coordinates":[5.2527689934,51.0033874512],"type":"Point"}
}