{
  "type": "Feature",
  "properties": {
    "iso:country":"BE",
    "sg:address":"Eerselingenstraat 47",
    "sg:city":"Kasterlee",
    "sg:classifiers":[
        {
            "category":"Sports & Exercise",
            "subcategory":"Sports Center",
            "type":"Entertainment"
        }
    ],
    "sg:phone":"+32 14 55 39 19",
    "sg:postcode":"2460",
    "sg:province":"Antwerpen",
    "sg:tags":[
        "terrain",
        "hors",
        "de",
        "installation",
        "sportifs"
    ],
    "wof:name":"Paula Heylen",
    "wof:placetype":"venue"
},
  "geometry": {"coordinates":[4.9183268547,51.2060089111],"type":"Point"}
}