{
  "type": "Feature",
  "properties": {
    "iso:country":"BE",
    "sg:address":"Caverstraat 3",
    "sg:city":"Jabbeke",
    "sg:orig_category":"Dranken",
    "sg:phone":"+32 50 81 20 01",
    "sg:postcode":"8490",
    "sg:province":"West-Vlaanderen",
    "wof:name":"Noel Bollaert",
    "wof:placetype":"venue"
},
  "geometry": {"coordinates":[3.0926599503,51.1829376221],"type":"Point"}
}