{
  "type": "Feature",
  "properties": {
    "iso:country":"BE",
    "sg:address":"Smaragdlaan 66b1",
    "sg:city":"Schaarbeek/schaerbeek",
    "sg:orig_category":"Boekhouders",
    "sg:phone":"+32 2 736 63 04",
    "sg:postcode":"1030",
    "sg:province":"Bruxelles-Capitale",
    "wof:name":"Eric Chardon",
    "wof:placetype":"venue"
},
  "geometry": {"coordinates":[4.3991131783,50.8528060913],"type":"Point"}
}