{
  "type": "Feature",
  "properties": {
    "iso:country":"BE",
    "sg:address":"Rue De L'artisanat 10",
    "sg:city":"Nivelles",
    "sg:orig_category":"Agences d'exp\u00e9dition",
    "sg:phone":"+32 67 84 06 58",
    "sg:postcode":"1400",
    "sg:province":"Brabant Wallon",
    "wof:name":"Sobimport",
    "wof:placetype":"venue"
},
  "geometry": {"coordinates":[4.3641581535,50.5974731445],"type":"Point"}
}