{
  "type": "Feature",
  "properties": {
    "addr:full":"Bergstraat 90 Sint-katelijne-waver (onze-lieve-vrouw-waver) Antwerpen 2861",
    "addr:housenumber":"90",
    "addr:postcode":"2861",
    "addr:street":"Bergstraat",
    "iso:country":"BE",
    "sg:address":"Bergstraat 90",
    "sg:city":"Sint-katelijne-waver (onze-lieve-vrouw-waver)",
    "sg:classifiers":[
        {
            "category":"Personal",
            "subcategory":"Beauty Salon",
            "type":"Services"
        }
    ],
    "sg:phone":"+32 15 55 08 99",
    "sg:postcode":"2861",
    "sg:province":"Antwerpen",
    "sg:tags":[
        "lady",
        "-",
        "hairdressing"
    ],
    "wof:name":"Greta",
    "wof:placetype":"venue"
},
  "geometry": {"coordinates":[4.553800106,51.0423927307],"type":"Point"}
}