{
  "type": "Feature",
  "properties": {
    "iso:country":"BE",
    "sg:address":"Grand Place 16",
    "sg:city":"Beaumont",
    "sg:classifiers":[
        {
            "category":"Professional",
            "subcategory":"Testing Lab",
            "type":"Services"
        }
    ],
    "sg:phone":"+32 71 58 80 89",
    "sg:postcode":"6500",
    "sg:province":"Hainaut",
    "sg:tags":[
        "chemist"
    ],
    "wof:name":"Vessi\u00e9 G-m",
    "wof:placetype":"venue"
},
  "geometry": {"coordinates":[4.2349200249,50.2375793457],"type":"Point"}
}