{
  "type": "Feature",
  "properties": {
    "addr:full":"Lierseweg 7a Herentals Antwerpen 2200",
    "addr:housenumber":"7a",
    "addr:postcode":"2200",
    "addr:street":"Lierseweg",
    "iso:country":"BE",
    "sg:address":"Lierseweg 7a",
    "sg:city":"Herentals",
    "sg:classifiers":[
        {
            "category":"Real Estate",
            "subcategory":"Architect",
            "type":"Services"
        }
    ],
    "sg:phone":"+32 14 22 61 35",
    "sg:postcode":"2200",
    "sg:province":"Antwerpen",
    "wof:name":"De Cuyper K",
    "wof:placetype":"venue"
},
  "geometry": {"coordinates":[4.8295769691,51.1768569946],"type":"Point"}
}