{
  "type": "Feature",
  "properties": {
    "addr:full":"Edelarendries 77 Merelbeke Oost-Vlaanderen 9820",
    "addr:housenumber":"77",
    "addr:postcode":"9820",
    "addr:street":"Edelarendries",
    "iso:country":"BE",
    "sg:address":"Edelarendries 77",
    "sg:city":"Merelbeke",
    "sg:orig_category":"Metaalbehandeling and -bekleding",
    "sg:phone":"+32 9 362 60 86",
    "sg:postcode":"9820",
    "sg:province":"Oost-Vlaanderen",
    "wof:name":"Van Mullem",
    "wof:placetype":"venue"
},
  "geometry": {"coordinates":[3.7467069626,50.965965271],"type":"Point"}
}