{
  "type": "Feature",
  "properties": {
    "addr:full":"Ons Verlangenstraat 15 Bilzen Limburg 3740",
    "addr:housenumber":"15",
    "addr:postcode":"3740",
    "addr:street":"Verlangenstraat",
    "iso:country":"BE",
    "sg:address":"Ons Verlangenstraat 15",
    "sg:city":"Bilzen",
    "sg:orig_category":"Mat\u00e9riel de contr\u00f4le des processus industriels Fab",
    "sg:phone":"+32 89 51 47 57",
    "sg:postcode":"3740",
    "sg:province":"Limburg",
    "wof:name":"Barthels",
    "wof:placetype":"venue"
},
  "geometry": {"coordinates":[5.4734940529,50.8929328918],"type":"Point"}
}