{
  "type": "Feature",
  "properties": {
    "addr:full":"Avenue De L'ermitage 15 Namur Namur 5000",
    "addr:housenumber":"15",
    "addr:postcode":"5000",
    "addr:street":"Avenue De L'Ermitage",
    "iso:country":"BE",
    "sg:address":"Avenue De L'ermitage 15",
    "sg:city":"Namur",
    "sg:classifiers":[
        {
            "category":"Manufacturing",
            "subcategory":"Textiles",
            "type":"Manufacturing & Wholesale Goods"
        }
    ],
    "sg:phone":"+32 81 87 87 52",
    "sg:postcode":"5000",
    "sg:province":"Namur",
    "sg:tags":[
        "retail",
        "-"
    ],
    "wof:name":"Louise Collection",
    "wof:placetype":"venue"
},
  "geometry": {"coordinates":[4.8502597809,50.4522247314],"type":"Point"}
}