{
  "type": "Feature",
  "properties": {
    "iso:country":"BE",
    "sg:address":"Kasteelstraat 161",
    "sg:city":"Buggenhout",
    "sg:classifiers":[
        {
            "category":"Sports & Exercise",
            "subcategory":"Sports Center",
            "type":"Entertainment"
        }
    ],
    "sg:phone":"+32 52 33 21 61",
    "sg:postcode":"9255",
    "sg:province":"Oost-Vlaanderen",
    "sg:tags":[
        "club",
        "article",
        "de",
        "camping"
    ],
    "wof:name":"Krokkebaas Golfclub",
    "wof:placetype":"venue"
},
  "geometry": {"coordinates":[4.2096571922,51.0014762878],"type":"Point"}
}