{
  "type": "Feature",
  "properties": {
    "iso:country":"BE",
    "sg:address":"Rue D'opprebais 20",
    "sg:city":"Perwez",
    "sg:orig_category":"Enseignement maternel and primaire",
    "sg:phone":"+32 10 88 81 71",
    "sg:postcode":"1360",
    "sg:province":"Brabant Wallon",
    "wof:name":"Ecole Fond. Communale",
    "wof:placetype":"venue"
},
  "geometry": {"coordinates":[4.7840971947,50.6592712402],"type":"Point"}
}