{
  "type": "Feature",
  "properties": {
    "addr:full":"Chemin Du Stayi 8 Bouillon (corbion) Luxembourg 6838",
    "addr:housenumber":"8",
    "addr:postcode":"6838",
    "addr:street":"Chemin Du Stayi",
    "iso:country":"BE",
    "sg:address":"Chemin Du Stayi 8",
    "sg:city":"Bouillon (corbion)",
    "sg:classifiers":[
        {
            "category":"Arena",
            "subcategory":"Sports Club",
            "type":"Entertainment"
        }
    ],
    "sg:phone":"+32 61 46 77 42",
    "sg:postcode":"6838",
    "sg:province":"Luxembourg",
    "wof:name":"Cercle Sportif Corbion",
    "wof:placetype":"venue"
},
  "geometry": {"coordinates":[5.0071702003,49.7973403931],"type":"Point"}
}