{
  "type": "Feature",
  "properties": {
    "addr:full":"Rue Du Centre 1 Gesves Namur 5340",
    "addr:housenumber":"1",
    "addr:postcode":"5340",
    "addr:street":"Rue Du Centre",
    "iso:country":"BE",
    "sg:address":"Rue Du Centre 1",
    "sg:city":"Gesves",
    "sg:orig_category":"HERSTELLING ELEKTRISCHE HUISHOUDAPPARATEN",
    "sg:phone":"+32 83 67 80 87",
    "sg:postcode":"5340",
    "sg:province":"Namur",
    "wof:name":"Claude Hastir",
    "wof:placetype":"venue"
},
  "geometry": {"coordinates":[5.120631218,50.3993644714],"type":"Point"}
}