{
  "type": "Feature",
  "properties": {
    "iso:country":"BE",
    "sg:address":"Prinses Jos. Charlotteln 18b3",
    "sg:city":"Wetteren",
    "sg:classifiers":[
        {
            "category":"Cafe",
            "type":"Food & Drink"
        }
    ],
    "sg:postcode":"9230",
    "sg:province":"Oost-Vlaanderen",
    "sg:tags":[
        "caf\u00e9s"
    ],
    "wof:name":"Frans Kolijn",
    "wof:placetype":"venue"
},
  "geometry": {"coordinates":[3.8781409264,51.0061416626],"type":"Point"}
}