{
  "type": "Feature",
  "properties": {
    "addr:full":"Avenue L\u00e9opold Wiener 34 Bruxelles (watermael-boitsfort) Bruxelles-Capitale 1170",
    "addr:housenumber":"34",
    "addr:postcode":"1170",
    "addr:street":"Avenue Le\u0301Opold Wiener",
    "iso:country":"BE",
    "sg:address":"Avenue L\u00e9opold Wiener 34",
    "sg:city":"Bruxelles (watermael-boitsfort)",
    "sg:classifiers":[
        {
            "category":"Education",
            "subcategory":"School",
            "type":"Public Place"
        }
    ],
    "sg:phone":"+32 2 672 29 75",
    "sg:postcode":"1170",
    "sg:province":"Bruxelles-Capitale",
    "sg:tags":[
        "primary"
    ],
    "wof:name":"Sainte-famille (ecole Fondamentale De La)",
    "wof:placetype":"venue"
},
  "geometry": {"coordinates":[4.4087839127,50.8052749634],"type":"Point"}
}