{
  "type": "Feature",
  "properties": {
    "iso:country":"BE",
    "sg:address":"Neerweg 41",
    "sg:city":"Heist-op-den-berg",
    "sg:orig_category":"Non-Classified Establishments",
    "sg:postcode":"2220",
    "sg:province":"Antwerpen",
    "wof:name":"So C&t Bvba",
    "wof:placetype":"venue"
},
  "geometry": {"coordinates":[4.7185578346,51.079826355],"type":"Point"}
}