{
  "type": "Feature",
  "properties": {
    "addr:full":"Fr\u00e4iheetswee 113 Attert Luxembourg 6717",
    "addr:housenumber":"113",
    "addr:postcode":"6717",
    "addr:street":"Fraeiheetswee",
    "iso:country":"BE",
    "sg:address":"Fr\u00e4iheetswee 113",
    "sg:city":"Attert",
    "sg:classifiers":[
        {
            "category":"Retail",
            "subcategory":"Event Space",
            "type":"Services"
        }
    ],
    "sg:phone":"+32 63 22 14 73",
    "sg:postcode":"6717",
    "sg:province":"Luxembourg",
    "sg:tags":[
        "rental",
        "-",
        "hall"
    ],
    "wof:name":"Cothurne",
    "wof:placetype":"venue"
},
  "geometry": {"coordinates":[5.7888741493,49.7506217957],"type":"Point"}
}