{
  "type": "Feature",
  "properties": {
    "addr:full":"Rue Du Calvaire 54a Charleroi (montignies-sur-sambre) Hainaut 6061",
    "addr:housenumber":"54a",
    "addr:postcode":"6061",
    "addr:street":"Rue Du Calvaire",
    "iso:country":"BE",
    "sg:address":"Rue Du Calvaire 54a",
    "sg:city":"Charleroi (montignies-sur-sambre)",
    "sg:classifiers":[
        {
            "category":"Building & Trades",
            "subcategory":"Construction",
            "type":"Services"
        }
    ],
    "sg:phone":"+32 71 31 04 92",
    "sg:postcode":"6061",
    "sg:province":"Hainaut",
    "sg:tags":[
        "stucco",
        "contractor"
    ],
    "wof:name":"Klescz Sprl",
    "wof:placetype":"venue"
},
  "geometry": {"coordinates":[4.4816699028,50.4033317566],"type":"Point"}
}