{
  "type": "Feature",
  "properties": {
    "iso:country":"BE",
    "sg:address":"Steenstraat 106",
    "sg:city":"Meulebeke",
    "sg:orig_category":"Elektrische installaties voor woningen",
    "sg:phone":"+32 51 48 95 87",
    "sg:postcode":"8760",
    "sg:province":"West-Vlaanderen",
    "wof:name":"Elektro-dirk",
    "wof:placetype":"venue"
},
  "geometry": {"coordinates":[3.2853720188,50.9424858093],"type":"Point"}
}