{
  "type": "Feature",
  "properties": {
    "iso:country":"BE",
    "sg:address":"Dijk 3",
    "sg:city":"Sint-katelijne-waver (onze-lieve-vrouw-waver)",
    "sg:classifiers":[
        {
            "category":"Communications",
            "type":"Services"
        }
    ],
    "sg:phone":"+32 15 76 00 79",
    "sg:postcode":"2861",
    "sg:province":"Antwerpen",
    "sg:tags":[
        "translator"
    ],
    "wof:name":"@d Lib!",
    "wof:placetype":"venue"
},
  "geometry": {"coordinates":[4.5787291527,51.0614051819],"type":"Point"}
}