{
  "type": "Feature",
  "properties": {
    "iso:country":"BE",
    "sg:address":"Rue De Jemeppe 221",
    "sg:city":"Ans",
    "sg:orig_category":"Entretien and r\u00e9parations de voitures",
    "sg:phone":"+32 4 247 24 77",
    "sg:postcode":"4431",
    "sg:province":"Li\u00e8ge",
    "wof:name":"Carrosserie Roberto",
    "wof:placetype":"venue"
},
  "geometry": {"coordinates":[5.4970960617,50.6595802307],"type":"Point"}
}