{
  "type": "Feature",
  "properties": {
    "addr:full":"Galerie Jardin D\u00b4harscamp 4 Namur Namur 5000",
    "addr:housenumber":"4",
    "addr:postcode":"5000",
    "iso:country":"BE",
    "sg:address":"Galerie Jardin D\u00b4harscamp 4",
    "sg:city":"Namur",
    "sg:orig_category":"Voedingsspeciaalzaken",
    "sg:phone":"+32 81 22 75 67",
    "sg:postcode":"5000",
    "sg:province":"Namur",
    "wof:name":"La Maison Des Plantes",
    "wof:placetype":"venue"
},
  "geometry": {"coordinates":[4.869822979,50.4632720947],"type":"Point"}
}