{
  "type": "Feature",
  "properties": {
    "addr:full":"Rue Haute-saive 88 Bl\u00e9gny (saive) Li\u00e8ge 4671",
    "addr:housenumber":"88",
    "addr:postcode":"4671",
    "addr:street":"Rue Haute-Saive",
    "iso:country":"BE",
    "sg:address":"Rue Haute-saive 88",
    "sg:city":"Bl\u00e9gny (saive)",
    "sg:classifiers":[
        {
            "category":"Shopping",
            "subcategory":"Books",
            "type":"Retail Goods"
        }
    ],
    "sg:phone":"+32 4 362 66 57",
    "sg:postcode":"4671",
    "sg:province":"Li\u00e8ge",
    "sg:tags":[
        "bookseller"
    ],
    "wof:name":"Maltus A",
    "wof:placetype":"venue"
},
  "geometry": {"coordinates":[5.6755008698,50.6564025879],"type":"Point"}
}