{
  "type": "Feature",
  "properties": {
    "iso:country":"BE",
    "sg:address":"Tervuursesteenweg 313",
    "sg:city":"Zemst",
    "sg:orig_category":"Banques and organismes de cr\u00e9dit",
    "sg:phone":"+32 15 61 24 67",
    "sg:postcode":"1981",
    "sg:province":"Vlaams-Brabant",
    "wof:name":"Kbc",
    "wof:placetype":"venue"
},
  "geometry": {"coordinates":[4.4945778847,50.9895858765],"type":"Point"}
}