{
  "type": "Feature",
  "properties": {
    "addr:full":"Gudderstraat 24 Groot-gelmen Limburg 3800",
    "addr:housenumber":"24",
    "addr:postcode":"3800",
    "addr:street":"Gudderstraat",
    "iso:country":"BE",
    "sg:address":"Gudderstraat 24",
    "sg:city":"Groot-gelmen",
    "sg:orig_category":"Antiquit\u00e9s",
    "sg:phone":"+32 11 48 41 74",
    "sg:postcode":"3800",
    "sg:province":"Limburg",
    "wof:name":"Antiek Exclusief",
    "wof:placetype":"venue"
},
  "geometry": {"coordinates":[5.2636947632,50.7862091064],"type":"Point"}
}