{
  "type": "Feature",
  "properties": {
    "iso:country":"BE",
    "sg:address":"Rue Maty 16",
    "sg:city":"Namur",
    "sg:orig_category":"Huishoudapparaten, televisies and radio's",
    "sg:phone":"+32 81 58 97 67",
    "sg:postcode":"5101",
    "sg:province":"Namur",
    "wof:name":"Jean Dereppe",
    "wof:placetype":"venue"
},
  "geometry": {"coordinates":[4.904815197,50.4481887817],"type":"Point"}
}