{
  "type": "Feature",
  "properties": {
    "iso:country":"BE",
    "sg:address":"Krijgsbaan 50",
    "sg:city":"Mortsel",
    "sg:classifiers":[
        {
            "category":"Manufacturing",
            "subcategory":"Lumber",
            "type":"Manufacturing & Wholesale Goods"
        }
    ],
    "sg:phone":"+32 3 449 92 58",
    "sg:postcode":"2640",
    "sg:province":"Antwerpen",
    "sg:tags":[
        "timber"
    ],
    "wof:name":"Verachtert F",
    "wof:placetype":"venue"
},
  "geometry": {"coordinates":[4.4573111534,51.1758613586],"type":"Point"}
}