{
  "type": "Feature",
  "properties": {
    "addr:full":"1081 Koekelberg (bruxelles) Bruxelles-Capitale 1081",
    "addr:housenumber":"1081",
    "addr:postcode":"1081",
    "addr:street":"Koekelberg",
    "iso:country":"BE",
    "sg:address":"1081",
    "sg:city":"Koekelberg (bruxelles)",
    "sg:orig_category":"Pharmaciens",
    "sg:phone":"+32 900 10 500",
    "sg:postcode":"1081",
    "sg:province":"Bruxelles-Capitale",
    "wof:name":"Pharmacies De Garde",
    "wof:placetype":"venue"
},
  "geometry": {"coordinates":[4.3315048218,50.8606834412],"type":"Point"}
}