{
  "type": "Feature",
  "properties": {
    "addr:full":"Trierstraat 25 Rue Des Tr\u00e8ves Brussels Bruxelles-Capitale 1040",
    "addr:housenumber":"25",
    "addr:postcode":"1040",
    "addr:street":"Trierstraat;Rue Des Tre\u0300Ves",
    "iso:country":"BE",
    "sg:address":"Trierstraat 25 Rue Des Tr\u00e8ves",
    "sg:city":"Brussels",
    "sg:classifiers":[
        {
            "category":"Banks & Credit Unions",
            "subcategory":"Bank",
            "type":"Services"
        }
    ],
    "sg:postcode":"1040",
    "sg:province":"Bruxelles-Capitale",
    "wof:name":"Gecopar Sa",
    "wof:placetype":"venue"
},
  "geometry": {"coordinates":[4.3496851921,50.8483848572],"type":"Point"}
}