{
  "type": "Feature",
  "properties": {
    "iso:country":"BE",
    "sg:address":"Rue Th\u00c9odore De Cuyper 155b11",
    "sg:city":"Bruxelles",
    "sg:orig_category":"Sportclubs",
    "sg:phone":"+32 2 779 18 46",
    "sg:postcode":"1200",
    "sg:province":"Bruxelles-Capitale",
    "wof:name":"Capricorne",
    "wof:placetype":"venue"
},
  "geometry": {"coordinates":[4.4349479675,50.8518295288],"type":"Point"}
}