{
  "type": "Feature",
  "properties": {
    "iso:country":"BE",
    "sg:address":"U.n.o. Laan 116",
    "sg:city":"Hemiksem",
    "sg:classifiers":[
        {
            "category":"Home & Garden",
            "subcategory":"Home Furnishings",
            "type":"Retail Goods"
        }
    ],
    "sg:phone":"+32 3 877 69 92",
    "sg:postcode":"2620",
    "sg:province":"Antwerpen",
    "sg:tags":[
        "interior",
        "decoration"
    ],
    "wof:name":"Algemene Schilderwerken Geerts",
    "wof:placetype":"venue"
},
  "geometry": {"coordinates":[4.3453731537,51.1389884949],"type":"Point"}
}