{
  "type": "Feature",
  "properties": {
    "addr:full":"Koolstraat 83 Mechelen Antwerpen 2800",
    "addr:housenumber":"83",
    "addr:postcode":"2800",
    "addr:street":"Koolstraat",
    "iso:country":"BE",
    "sg:address":"Koolstraat 83",
    "sg:city":"Mechelen",
    "sg:classifiers":[
        {
            "category":"Personal",
            "subcategory":"Beauty Salon",
            "type":"Services"
        }
    ],
    "sg:phone":"+32 15 26 10 34",
    "sg:postcode":"2800",
    "sg:province":"Antwerpen",
    "wof:name":"Schoonheidshuisje Ingrid",
    "wof:placetype":"venue"
},
  "geometry": {"coordinates":[4.463654995,51.0280456543],"type":"Point"}
}