{
  "type": "Feature",
  "properties": {
    "iso:country":"BE",
    "sg:address":"Rue Du Comt\u00e9 83",
    "sg:city":"Sombreffe (ligny)",
    "sg:classifiers":[
        {
            "category":"Home & Garden",
            "subcategory":"Garden Supply",
            "type":"Retail Goods"
        }
    ],
    "sg:phone":"+32 71 88 65 74",
    "sg:postcode":"5140",
    "sg:province":"Namur",
    "sg:tags":[
        "lawn",
        "mower"
    ],
    "wof:name":"Multim\u00e9ca",
    "wof:placetype":"venue"
},
  "geometry": {"coordinates":[4.5730957985,50.5138702393],"type":"Point"}
}