{
  "type": "Feature",
  "properties": {
    "addr:full":"Minnestraat 7 Bekkevoort Vlaams-Brabant 3460",
    "addr:housenumber":"7",
    "addr:postcode":"3460",
    "addr:street":"Minnestraat",
    "iso:country":"BE",
    "sg:address":"Minnestraat 7",
    "sg:city":"Bekkevoort",
    "sg:orig_category":"Woningbouw",
    "sg:phone":"+32 13 33 54 36",
    "sg:postcode":"3460",
    "sg:province":"Vlaams-Brabant",
    "wof:name":"Bouwbedrijf Zwinnen",
    "wof:placetype":"venue"
},
  "geometry": {"coordinates":[5.0161218643,50.9521217346],"type":"Point"}
}