{
  "type": "Feature",
  "properties": {
    "addr:full":"Somersstraat 19 Antwerpen Antwerpen 2018",
    "addr:housenumber":"19",
    "addr:postcode":"2018",
    "addr:street":"Somersstraat",
    "iso:country":"BE",
    "sg:address":"Somersstraat 19",
    "sg:city":"Antwerpen",
    "sg:orig_category":"Plaatsen van vloer- and muurbekleding",
    "sg:phone":"+32 3 231 02 24",
    "sg:postcode":"2018",
    "sg:province":"Antwerpen",
    "wof:name":"Renzo Borioni",
    "wof:placetype":"venue"
},
  "geometry": {"coordinates":[4.4254879951,51.2117424011],"type":"Point"}
}