{
  "type": "Feature",
  "properties": {
    "addr:full":"Hollandstraat 7 Gooik Vlaams-Brabant 1755",
    "addr:housenumber":"7",
    "addr:postcode":"1755",
    "addr:street":"Hollandstraat",
    "iso:country":"BE",
    "sg:address":"Hollandstraat 7",
    "sg:city":"Gooik",
    "sg:orig_category":"Eleveurs de bovins",
    "sg:phone":"+32 54 56 71 52",
    "sg:postcode":"1755",
    "sg:province":"Vlaams-Brabant",
    "wof:name":"Louis Van Eeckhoudt",
    "wof:placetype":"venue"
},
  "geometry": {"coordinates":[4.0816731453,50.7588691711],"type":"Point"}
}