{
  "type": "Feature",
  "properties": {
    "addr:full":"Herestraat 138 Tienen (oplinter) Vlaams-Brabant 3300",
    "addr:housenumber":"138",
    "addr:postcode":"3300",
    "addr:street":"Herestraat",
    "iso:country":"BE",
    "sg:address":"Herestraat 138",
    "sg:city":"Tienen (oplinter)",
    "sg:classifiers":[
        {
            "category":"Farming",
            "subcategory":"Farm & Veterinary Services",
            "type":"Manufacturing & Wholesale Goods"
        }
    ],
    "sg:phone":"+32 16 81 35 69",
    "sg:postcode":"3300",
    "sg:province":"Vlaams-Brabant",
    "sg:tags":[
        "agricultural",
        "contractor"
    ],
    "wof:name":"Stouthuysen M",
    "wof:placetype":"venue"
},
  "geometry": {"coordinates":[4.9814500809,50.8322525024],"type":"Point"}
}