{
  "type": "Feature",
  "properties": {
    "addr:full":"Rue De La Science 2 Frameries Hainaut 7080",
    "addr:housenumber":"2",
    "addr:postcode":"7080",
    "addr:street":"Rue De La Science",
    "iso:country":"BE",
    "sg:address":"Rue De La Science 2",
    "sg:city":"Frameries",
    "sg:orig_category":"R\u00e9parations d'appareils \u00e9lectrom\u00e9nagers. Mat\u00e9riel de T\u00e9l\u00e9communication. Electrom\u00e9nager, t\u00e9l\u00e9visions ",
    "sg:phone":"+32 65 35 20 16",
    "sg:postcode":"7080",
    "sg:province":"Hainaut",
    "wof:name":"Dour Electro Ets.",
    "wof:placetype":"venue"
},
  "geometry": {"coordinates":[3.9013249874,50.4052352905],"type":"Point"}
}