{
  "type": "Feature",
  "properties": {
    "iso:country":"BE",
    "sg:address":"Jonkershovestraat 196",
    "sg:city":"Houthulst",
    "sg:orig_category":"Rundveehouders",
    "sg:phone":"+32 51 54 43 43",
    "sg:postcode":"8650",
    "sg:province":"West-Vlaanderen",
    "wof:name":"Nestor Beheydt",
    "wof:placetype":"venue"
},
  "geometry": {"coordinates":[2.9257929325,50.9714813232],"type":"Point"}
}