{
  "type": "Feature",
  "properties": {
    "addr:full":"Sint-annaplein 22 Brugge West-Vlaanderen 8000",
    "addr:housenumber":"22",
    "addr:postcode":"8000",
    "addr:street":"Sint-Annaplein",
    "iso:country":"BE",
    "sg:address":"Sint-annaplein 22",
    "sg:city":"Brugge",
    "sg:orig_category":"M\u00e9decins and sp\u00e9cialistes",
    "sg:phone":"+32 50 33 12 56",
    "sg:postcode":"8000",
    "sg:province":"West-Vlaanderen",
    "wof:name":"R. Strubbe",
    "wof:placetype":"venue"
},
  "geometry": {"coordinates":[3.2323429585,51.2124671936],"type":"Point"}
}