{
  "type": "Feature",
  "properties": {
    "addr:full":"Clos Des Sept Bonniers 7 Grez-doiceau (bossut-gottechain) Brabant Wallon 1390",
    "addr:housenumber":"7",
    "addr:postcode":"1390",
    "addr:street":"Clos Des Sept Bonniers;Wallon",
    "iso:country":"BE",
    "sg:address":"Clos Des Sept Bonniers 7",
    "sg:city":"Grez-doiceau (bossut-gottechain)",
    "sg:classifiers":[
        {
            "category":"Health Services",
            "subcategory":"Doctor",
            "type":"Services"
        }
    ],
    "sg:phone":"+32 10 84 55 45",
    "sg:postcode":"1390",
    "sg:province":"Brabant Wallon",
    "sg:tags":[
        "medicinephysicians",
        "surgeon"
    ],
    "wof:name":"Hoang V",
    "wof:placetype":"venue"
},
  "geometry": {"coordinates":[4.6623158455,50.7699050903],"type":"Point"}
}