{
  "type": "Feature",
  "properties": {
    "addr:full":"Rue Ernest Solvay 311 Li\u00e8ge Li\u00e8ge 4000",
    "addr:housenumber":"311",
    "addr:postcode":"4000",
    "addr:street":"Rue Ernest Solvay",
    "iso:country":"BE",
    "sg:address":"Rue Ernest Solvay 311",
    "sg:city":"Li\u00e8ge",
    "sg:classifiers":[
        {
            "category":"Building & Trades",
            "subcategory":"Construction",
            "type":"Services"
        }
    ],
    "sg:phone":"+32 4 231 09 04",
    "sg:postcode":"4000",
    "sg:province":"Li\u00e8ge",
    "sg:tags":[
        "work",
        "public"
    ],
    "wof:name":"Entreprise De Construction Et De Renovation Sa",
    "wof:placetype":"venue"
},
  "geometry": {"coordinates":[5.5487680435,50.6099624634],"type":"Point"}
}