{
  "type": "Feature",
  "properties": {
    "addr:full":"Rue De La Brasserie 3 Perwez Brabant Wallon 1360",
    "addr:housenumber":"3",
    "addr:postcode":"1360",
    "addr:street":"Rue De La Brasserie",
    "iso:country":"BE",
    "sg:address":"Rue De La Brasserie 3",
    "sg:city":"Perwez",
    "sg:classifiers":[
        {
            "category":"Insurance",
            "subcategory":"Life Insurance",
            "type":"Services"
        }
    ],
    "sg:phone":"+32 81 65 54 52",
    "sg:postcode":"1360",
    "sg:province":"Brabant Wallon",
    "sg:tags":[
        "assurance"
    ],
    "wof:name":"B.i.c.",
    "wof:placetype":"venue"
},
  "geometry": {"coordinates":[4.8150310516,50.622303009],"type":"Point"}
}