{
  "type": "Feature",
  "properties": {
    "addr:full":"Kuringersteenweg 511 Hasselt (kuringen) Limburg 3511",
    "addr:housenumber":"511",
    "addr:postcode":"3511",
    "addr:street":"Kuringersteenweg",
    "iso:country":"BE",
    "sg:address":"Kuringersteenweg 511",
    "sg:city":"Hasselt (kuringen)",
    "sg:classifiers":[
        {
            "category":"Transit Center",
            "subcategory":"Freight",
            "type":"Transportation"
        }
    ],
    "sg:phone":"+32 11 35 29 26",
    "sg:postcode":"3511",
    "sg:province":"Limburg",
    "sg:tags":[
        "import",
        "export",
        "-"
    ],
    "wof:name":"Intragent Management Group Bvba",
    "wof:placetype":"venue"
},
  "geometry": {"coordinates":[5.2920398712,50.9425086975],"type":"Point"}
}