{
  "type": "Feature",
  "properties": {
    "addr:full":"Platwijersweg 27 Zonhoven Limburg 3520",
    "addr:housenumber":"27",
    "addr:postcode":"3520",
    "addr:street":"Platwijersweg",
    "iso:country":"BE",
    "sg:address":"Platwijersweg 27",
    "sg:city":"Zonhoven",
    "sg:classifiers":[
        {
            "category":"Retail",
            "subcategory":"Auto Repair",
            "type":"Services"
        }
    ],
    "sg:phone":"+32 475 86 59 95",
    "sg:postcode":"3520",
    "sg:province":"Limburg",
    "sg:tags":[
        "garage"
    ],
    "wof:name":"Smeulders L",
    "wof:placetype":"venue"
},
  "geometry": {"coordinates":[5.3453860283,50.9747123718],"type":"Point"}
}