{
  "type": "Feature",
  "properties": {
    "addr:full":"Hoogstraat 8 Boom Antwerpen 2850",
    "addr:housenumber":"8",
    "addr:postcode":"2850",
    "addr:street":"Hoogstraat",
    "iso:country":"BE",
    "sg:address":"Hoogstraat 8",
    "sg:city":"Boom",
    "sg:orig_category":"Agences d\u00b4interim and personnel temporaire",
    "sg:phone":"+32 3 844 61 70",
    "sg:postcode":"2850",
    "sg:province":"Antwerpen",
    "wof:name":"Dynamic Interim",
    "wof:placetype":"venue"
},
  "geometry": {"coordinates":[4.3647809029,51.0862388611],"type":"Point"}
}