{
  "type": "Feature",
  "properties": {
    "iso:country":"BE",
    "sg:address":"Luikersteenweg 590",
    "sg:city":"Tongeren",
    "sg:classifiers":[
        {
            "category":"Recreation",
            "subcategory":"Dance Hall",
            "type":"Entertainment"
        }
    ],
    "sg:phone":"+32 12 23 24 22",
    "sg:postcode":"3700",
    "sg:province":"Limburg",
    "sg:tags":[
        "discotheque"
    ],
    "wof:name":"Alhambra-romantic",
    "wof:placetype":"venue"
},
  "geometry": {"coordinates":[5.4735560417,50.7634391785],"type":"Point"}
}