{
  "type": "Feature",
  "properties": {
    "iso:country":"BE",
    "sg:address":"Tempelstraat 34",
    "sg:city":"Beerse",
    "sg:orig_category":"Boekhouders",
    "sg:phone":"+32 14 61 51 54",
    "sg:postcode":"2340",
    "sg:province":"Antwerpen",
    "wof:name":"Frans Miechielsen",
    "wof:placetype":"venue"
},
  "geometry": {"coordinates":[4.8513498306,51.3167228699],"type":"Point"}
}