{
  "type": "Feature",
  "properties": {
    "addr:full":"E. Hertecantlaan 1 Berlare Oost-Vlaanderen 9290",
    "addr:housenumber":"1",
    "addr:postcode":"9290",
    "addr:street":"E. Hertecantlaan",
    "iso:country":"BE",
    "sg:address":"E. Hertecantlaan 1",
    "sg:city":"Berlare",
    "sg:orig_category":"Poissonniers and \u00e9caillers",
    "sg:phone":"+32 52 42 23 86",
    "sg:postcode":"9290",
    "sg:province":"Oost-Vlaanderen",
    "wof:name":"Vishandel Traiteur de Grauwe",
    "wof:placetype":"venue"
},
  "geometry": {"coordinates":[4.0061459541,51.0177078247],"type":"Point"}
}