{
  "type": "Feature",
  "properties": {
    "addr:full":"Place Brouez 9 Quaregnon Hainaut 7390",
    "addr:housenumber":"9",
    "addr:postcode":"7390",
    "addr:street":"Place Brouez",
    "iso:country":"BE",
    "sg:address":"Place Brouez 9",
    "sg:city":"Quaregnon",
    "sg:orig_category":"Banques and organismes de cr\u00e9dit",
    "sg:phone":"+32 65 78 69 08",
    "sg:postcode":"7390",
    "sg:province":"Hainaut",
    "wof:name":"Dexia",
    "wof:placetype":"venue"
},
  "geometry": {"coordinates":[3.8493769169,50.4443855286],"type":"Point"}
}