{
  "type": "Feature",
  "properties": {
    "addr:full":"Ieperstraat 43 Heuvelland West-Vlaanderen 8958",
    "addr:housenumber":"43",
    "addr:postcode":"8958",
    "addr:street":"Ieperstraat",
    "iso:country":"BE",
    "sg:address":"Ieperstraat 43",
    "sg:city":"Heuvelland",
    "sg:orig_category":"Herstelling leer and schoeisel",
    "sg:phone":"+32 57 44 43 71",
    "sg:postcode":"8958",
    "sg:province":"West-Vlaanderen",
    "wof:name":"Gilbert Haezebrouck",
    "wof:placetype":"venue"
},
  "geometry": {"coordinates":[2.8872449398,50.7877388],"type":"Point"}
}