{
  "type": "Feature",
  "properties": {
    "addr:full":"Rijschootstraat 4 Evergem Oost-Vlaanderen 9940",
    "addr:housenumber":"4",
    "addr:postcode":"9940",
    "addr:street":"Rijschootstraat;Oost-Vlaanderen",
    "iso:country":"BE",
    "sg:address":"Rijschootstraat 4",
    "sg:city":"Evergem",
    "sg:orig_category":"Beautyfarms, relaxatie and lichamelijk welzijn Schoonheidssalons",
    "sg:phone":"+32 9 343 05 65",
    "sg:postcode":"9940",
    "sg:province":"Oost-Vlaanderen",
    "wof:name":"Instituut Aphrodite",
    "wof:placetype":"venue"
},
  "geometry": {"coordinates":[3.750369072,51.1851577759],"type":"Point"}
}