{
  "type": "Feature",
  "properties": {
    "iso:country":"BE",
    "sg:address":"Marktplein 17",
    "sg:city":"Ardooie",
    "sg:orig_category":"Banken and kredietinstellingen",
    "sg:phone":"+32 51 74 44 85",
    "sg:postcode":"8850",
    "sg:province":"West-Vlaanderen",
    "wof:name":"Mercator Bank",
    "wof:placetype":"venue"
},
  "geometry": {"coordinates":[3.1971800327,50.978553772],"type":"Point"}
}