{
  "type": "Feature",
  "properties": {
    "iso:country":"BE",
    "sg:address":"Rue Des Combattants 16bb",
    "sg:city":"Brunehaut",
    "sg:orig_category":"Traitements param\u00e9dicaux",
    "sg:phone":"+32 69 34 48 25",
    "sg:postcode":"7620",
    "sg:province":"Hainaut",
    "wof:name":"J.f. Delcroix",
    "wof:placetype":"venue"
},
  "geometry": {"coordinates":[3.4214820862,50.5132904053],"type":"Point"}
}