{
  "type": "Feature",
  "properties": {
    "iso:country":"BE",
    "sg:address":"Maurits No\u00ebstraat 1",
    "sg:city":"Oud-heverlee",
    "sg:classifiers":[
        {
            "category":"Bars & Pubs",
            "type":"Food & Drink"
        }
    ],
    "sg:phone":"+32 16 47 01 17",
    "sg:postcode":"3050",
    "sg:province":"Vlaams-Brabant",
    "sg:tags":[
        "tavern"
    ],
    "wof:name":"Kouterbos ('t)",
    "wof:placetype":"venue"
},
  "geometry": {"coordinates":[4.653236866,50.8236122131],"type":"Point"}
}