{
  "type": "Feature",
  "properties": {
    "addr:full":"Doorniksesteenweg 37 Avelgem West-Vlaanderen 8580",
    "addr:housenumber":"37",
    "addr:postcode":"8580",
    "addr:street":"Doorniksesteenweg",
    "iso:country":"BE",
    "sg:address":"Doorniksesteenweg 37",
    "sg:city":"Avelgem",
    "sg:orig_category":"Banques and organismes de cr\u00e9dit",
    "sg:phone":"+32 56 64 70 06",
    "sg:postcode":"8580",
    "sg:province":"West-Vlaanderen",
    "wof:name":"Nagelmackers",
    "wof:placetype":"venue"
},
  "geometry": {"coordinates":[3.4442780018,50.7745742798],"type":"Point"}
}