{
  "type": "Feature",
  "properties": {
    "iso:country":"BE",
    "sg:address":"Sint-corneliusstraat 41b1",
    "sg:city":"Hasselt",
    "sg:orig_category":"Artsen and specialisten",
    "sg:phone":"+32 11 22 52 30",
    "sg:postcode":"3500",
    "sg:province":"Limburg",
    "wof:name":"D. Schroyen",
    "wof:placetype":"venue"
},
  "geometry": {"coordinates":[5.345220089,50.9292526245],"type":"Point"}
}