{
  "type": "Feature",
  "properties": {
    "iso:country":"BE",
    "sg:address":"Meetkerkestraat 2",
    "sg:city":"Zuienkerke",
    "sg:orig_category":"Rev\u00eatements pour sols and murs",
    "sg:phone":"+32 50 41 77 44",
    "sg:postcode":"8377",
    "sg:province":"West-Vlaanderen",
    "wof:name":"Marc Wittevrongel",
    "wof:placetype":"venue"
},
  "geometry": {"coordinates":[3.1564440727,51.2649459839],"type":"Point"}
}