{
  "type": "Feature",
  "properties": {
    "addr:full":"Heerweg 41 Horebeke Oost-Vlaanderen 9667",
    "addr:housenumber":"41",
    "addr:postcode":"9667",
    "addr:street":"Heerweg",
    "iso:country":"BE",
    "sg:address":"Heerweg 41",
    "sg:city":"Horebeke",
    "sg:orig_category":"Transports routiers de marchandises",
    "sg:phone":"+32 55 45 62 22",
    "sg:postcode":"9667",
    "sg:province":"Oost-Vlaanderen",
    "wof:name":"Vindevogel Rene",
    "wof:placetype":"venue"
},
  "geometry": {"coordinates":[3.6882119179,50.8247032166],"type":"Point"}
}