{
  "type": "Feature",
  "properties": {
    "iso:country":"BE",
    "sg:address":"Lombardstraat 24",
    "sg:city":"Brussel/bruxelles",
    "sg:classifiers":[
        {
            "category":"Restaurant",
            "type":"Food & Drink"
        }
    ],
    "sg:phone":"+32 2 502 43 02",
    "sg:postcode":"1000",
    "sg:province":"Bruxelles-Capitale",
    "wof:name":"Le Patin Couffin",
    "wof:placetype":"venue"
},
  "geometry": {"coordinates":[4.3504891396,50.8458518982],"type":"Point"}
}