{
  "type": "Feature",
  "properties": {
    "addr:full":"Bieststraat 233 Boortmeerbeek (hever) Vlaams-Brabant 3191",
    "addr:housenumber":"233",
    "addr:postcode":"3191",
    "addr:street":"Bieststraat",
    "iso:country":"BE",
    "sg:address":"Bieststraat 233",
    "sg:city":"Boortmeerbeek (hever)",
    "sg:classifiers":[
        {
            "category":"Retail",
            "subcategory":"Event Space",
            "type":"Services"
        }
    ],
    "sg:phone":"+32 15 51 30 03",
    "sg:postcode":"3191",
    "sg:province":"Vlaams-Brabant",
    "sg:tags":[
        "rental",
        "-",
        "hall"
    ],
    "wof:name":"Bosuilcentrum",
    "wof:placetype":"venue"
},
  "geometry": {"coordinates":[4.5490899086,50.9831085205],"type":"Point"}
}