{
  "type": "Feature",
  "properties": {
    "addr:full":"Avenue Clemenceau 125 Bruxelles (anderlecht) Bruxelles-Capitale 1070",
    "addr:housenumber":"125",
    "addr:postcode":"1070",
    "addr:street":"Avenue Clemenceau",
    "iso:country":"BE",
    "sg:address":"Avenue Clemenceau 125",
    "sg:city":"Bruxelles (anderlecht)",
    "sg:classifiers":[
        {
            "category":"Personal",
            "subcategory":"Beauty Salon",
            "type":"Services"
        }
    ],
    "sg:phone":"+32 2 523 60 69",
    "sg:postcode":"1070",
    "sg:province":"Bruxelles-Capitale",
    "sg:tags":[
        "lady",
        "-",
        "hairdressing"
    ],
    "wof:name":"Chane",
    "wof:placetype":"venue"
},
  "geometry": {"coordinates":[4.3314609528,50.8420982361],"type":"Point"}
}