{
  "type": "Feature",
  "properties": {
    "addr:full":"Golden Hopestr 1 Drogenbos Vlaams-Brabant 1620",
    "addr:housenumber":"1",
    "addr:postcode":"1620",
    "iso:country":"BE",
    "sg:address":"Golden Hopestr 1",
    "sg:city":"Drogenbos",
    "sg:classifiers":[
        {
            "category":"Manufacturing",
            "subcategory":"Printing",
            "type":"Manufacturing & Wholesale Goods"
        }
    ],
    "sg:phone":"+32 2 378 21 27",
    "sg:postcode":"1620",
    "sg:province":"Vlaams-Brabant",
    "sg:tags":[
        "publishing"
    ],
    "wof:name":"Dereume Printing Company Nv",
    "wof:placetype":"venue"
},
  "geometry": {"coordinates":[4.2922501564,50.7968711853],"type":"Point"}
}