{
  "type": "Feature",
  "properties": {
    "addr:full":"Rue Tienne Du Moine 41 Box 1 Fleurus (wanferc\u00e9e-baulet) Hainaut 6224",
    "addr:housenumber":"41;1",
    "addr:postcode":"6224",
    "addr:street":"Rue Tienne Du Moine;Box",
    "iso:country":"BE",
    "sg:address":"Rue Tienne Du Moine 41 Box 1",
    "sg:city":"Fleurus (wanferc\u00e9e-baulet)",
    "sg:classifiers":[
        {
            "category":"Health Services",
            "subcategory":"Health Practitioner",
            "type":"Services"
        }
    ],
    "sg:phone":"+32 71 81 02 34",
    "sg:postcode":"6224",
    "sg:province":"Hainaut",
    "sg:tags":[
        "physiotherapist"
    ],
    "wof:name":"Janssens G",
    "wof:placetype":"venue"
},
  "geometry": {"coordinates":[4.573196888,50.462802887],"type":"Point"}
}