{
  "type": "Feature",
  "properties": {
    "addr:full":"Neerstraat 19 Zwalm Oost-Vlaanderen 9636",
    "addr:housenumber":"19",
    "addr:postcode":"9636",
    "addr:street":"Neerstraat;Oost-Vlaanderen",
    "iso:country":"BE",
    "sg:address":"Neerstraat 19",
    "sg:city":"Zwalm",
    "sg:classifiers":[
        {
            "category":"Restaurant",
            "type":"Food & Drink"
        }
    ],
    "sg:phone":"+32 55 49 92 19",
    "sg:postcode":"9636",
    "sg:province":"Oost-Vlaanderen",
    "sg:tags":[
        "organisation",
        "de",
        "f\u00eates",
        "catering"
    ],
    "wof:name":"Restaurant Bambi",
    "wof:placetype":"venue"
},
  "geometry": {"coordinates":[3.6888101101,50.8865814209],"type":"Point"}
}