{
  "type": "Feature",
  "properties": {
    "iso:country":"BE",
    "sg:address":"Chauss\u00c9e De Wavre 92",
    "sg:city":"Jodoigne",
    "sg:orig_category":"Entretien and r\u00e9parations de voitures. V\u00e9hicules automobiles",
    "sg:phone":"+32 10 81 43 02",
    "sg:postcode":"1370",
    "sg:province":"Brabant Wallon",
    "wof:name":"Garage Tordoir-grutman",
    "wof:placetype":"venue"
},
  "geometry": {"coordinates":[4.8560419083,50.7249221802],"type":"Point"}
}