{
  "type": "Feature",
  "properties": {
    "iso:country":"BE",
    "sg:address":"Bril 6",
    "sg:city":"Lier",
    "sg:classifiers":[
        {
            "category":"Recreation",
            "type":"Entertainment"
        }
    ],
    "sg:phone":"+32 3 480 77 28",
    "sg:postcode":"2500",
    "sg:province":"Antwerpen",
    "sg:tags":[
        "diver",
        "amusement"
    ],
    "wof:name":"Den Bril",
    "wof:placetype":"venue"
},
  "geometry": {"coordinates":[4.5717720985,51.1292266846],"type":"Point"}
}