{
  "type": "Feature",
  "properties": {
    "addr:full":"Beekboshoek 60 Kontich Antwerpen 2550",
    "addr:housenumber":"60",
    "addr:postcode":"2550",
    "addr:street":"Beekboshoek",
    "iso:country":"BE",
    "sg:address":"Beekboshoek 60",
    "sg:city":"Kontich",
    "sg:orig_category":"Groententeelt",
    "sg:phone":"+32 15 31 81 79",
    "sg:postcode":"2550",
    "sg:province":"Antwerpen",
    "wof:name":"Paul Van De Weyer",
    "wof:placetype":"venue"
},
  "geometry": {"coordinates":[4.4589118958,51.107257843],"type":"Point"}
}