{
  "type": "Feature",
  "properties": {
    "iso:country":"BE",
    "sg:address":"Chauss\u00e9e Paul Houtart 272-1",
    "sg:city":"La Louvi\u00e8re (houdeng-goegnies)",
    "sg:classifiers":[
        {
            "category":"Shopping",
            "subcategory":"Stationery & Office Supplies",
            "type":"Retail Goods"
        }
    ],
    "sg:phone":"+32 64 22 93 77",
    "sg:postcode":"7110",
    "sg:province":"Hainaut",
    "wof:name":"Dubuisson",
    "wof:placetype":"venue"
},
  "geometry": {"coordinates":[4.1580018997,50.4865722656],"type":"Point"}
}