{
  "type": "Feature",
  "properties": {
    "addr:full":"Weg Naar As 21 Genk Limburg 3600",
    "addr:housenumber":"21",
    "addr:postcode":"3600",
    "addr:street":"Weg Naar As",
    "iso:country":"BE",
    "sg:address":"Weg Naar As 21",
    "sg:city":"Genk",
    "sg:classifiers":[
        {
            "category":"Insurance",
            "subcategory":"Insurance Agent",
            "type":"Services"
        }
    ],
    "sg:phone":"+32 89 35 05 11",
    "sg:postcode":"3600",
    "sg:province":"Limburg",
    "sg:tags":[
        "broker"
    ],
    "wof:name":"Aerts Yvo Studieburo",
    "wof:placetype":"venue"
},
  "geometry": {"coordinates":[5.5129380226,50.9667243958],"type":"Point"}
}