{
  "type": "Feature",
  "properties": {
    "addr:full":"Rue De L'etang 105 Bruxelles (etterbeek) Bruxelles-Capitale 1040",
    "addr:housenumber":"105",
    "addr:postcode":"1040",
    "addr:street":"Rue De L'Etang",
    "iso:country":"BE",
    "sg:address":"Rue De L'etang 105",
    "sg:city":"Bruxelles (etterbeek)",
    "sg:classifiers":[
        {
            "category":"Food & Beverages",
            "subcategory":"Meat & Fish",
            "type":"Retail Goods"
        }
    ],
    "sg:phone":"+32 2 647 45 26",
    "sg:postcode":"1040",
    "sg:province":"Bruxelles-Capitale",
    "sg:tags":[
        "bedspread",
        "blanket",
        "-"
    ],
    "wof:name":"Libau (literie)",
    "wof:placetype":"venue"
},
  "geometry": {"coordinates":[4.3519678116,50.8579750061],"type":"Point"}
}