{
  "type": "Feature",
  "properties": {
    "addr:full":"Linnenstraat 11 Meulebeke West-Vlaanderen 8760",
    "addr:housenumber":"11",
    "addr:postcode":"8760",
    "addr:street":"Linnenstraat",
    "iso:country":"BE",
    "sg:address":"Linnenstraat 11",
    "sg:city":"Meulebeke",
    "sg:classifiers":[
        {
            "category":"Train Station",
            "subcategory":"Rail",
            "type":"Transportation"
        }
    ],
    "sg:phone":"+32 51 48 66 44",
    "sg:postcode":"8760",
    "sg:province":"West-Vlaanderen",
    "sg:tags":[
        "bulk",
        "good",
        "-",
        "transport"
    ],
    "wof:name":"Eurotraffic Bvba",
    "wof:placetype":"venue"
},
  "geometry": {"coordinates":[3.3195779324,50.9375724792],"type":"Point"}
}