{
  "type": "Feature",
  "properties": {
    "addr:full":"Torhoutbaan 88 Ichtegem West-Vlaanderen 8480",
    "addr:housenumber":"88",
    "addr:postcode":"8480",
    "addr:street":"Torhoutbaan",
    "iso:country":"BE",
    "sg:address":"Torhoutbaan 88",
    "sg:city":"Ichtegem",
    "sg:classifiers":[
        {
            "category":"Autos & Motor Vehicles",
            "subcategory":"Automobile Sales",
            "type":"Retail Goods"
        }
    ],
    "sg:phone":"+32 478 26 29 38",
    "sg:postcode":"8480",
    "sg:province":"West-Vlaanderen",
    "sg:tags":[
        "car",
        "used",
        "-"
    ],
    "wof:name":"Lexauto Bvba",
    "wof:placetype":"venue"
},
  "geometry": {"coordinates":[3.0437660217,51.093914032],"type":"Point"}
}