{
  "type": "Feature",
  "properties": {
    "iso:country":"BE",
    "sg:address":"Doornpark 8",
    "sg:city":"Beveren (grand) - Flandre Orientale",
    "sg:orig_category":"D\u00e9molition d\u00b4immeubles and terrassements",
    "sg:phone":"+32 3 296 94 69",
    "sg:postcode":"9120",
    "sg:province":"Oost-Vlaanderen",
    "wof:name":"Grondwerken Van Osselaer Marc",
    "wof:placetype":"venue"
},
  "geometry": {"coordinates":[4.2143502235,51.1976356506],"type":"Point"}
}