{
  "type": "Feature",
  "properties": {
    "addr:full":"Komenstraat 31 Heuvelland West-Vlaanderen 8953",
    "addr:housenumber":"31",
    "addr:postcode":"8953",
    "addr:street":"Komenstraat",
    "iso:country":"BE",
    "sg:address":"Komenstraat 31",
    "sg:city":"Heuvelland",
    "sg:orig_category":"Pain, p\u00e2tisseries and confiseries",
    "sg:phone":"+32 57 44 50 19",
    "sg:postcode":"8953",
    "sg:province":"West-Vlaanderen",
    "wof:name":"Bakkerij Kurt",
    "wof:placetype":"venue"
},
  "geometry": {"coordinates":[2.8984498978,50.7668533325],"type":"Point"}
}