{
  "type": "Feature",
  "properties": {
    "addr:full":"Vijverstraat 131 Etterbeek Bruxelles-Capitale 1040",
    "addr:housenumber":"131",
    "addr:postcode":"1040",
    "addr:street":"Vijverstraat",
    "iso:country":"BE",
    "sg:address":"Vijverstraat 131",
    "sg:city":"Etterbeek",
    "sg:orig_category":"Artsen and specialisten",
    "sg:phone":"+32 2 649 38 55",
    "sg:postcode":"1040",
    "sg:province":"Bruxelles-Capitale",
    "wof:name":"B\u00c9n\u00c9dicte Roegiers",
    "wof:placetype":"venue"
},
  "geometry": {"coordinates":[4.3824300766,50.8349304199],"type":"Point"}
}