{
  "type": "Feature",
  "properties": {
    "addr:full":"Rue D\u00b4artois 31 Brussel/bruxelles Bruxelles-Capitale 1000",
    "addr:housenumber":"31",
    "addr:postcode":"1000",
    "addr:street":"Rue D\u00b4Artois;/",
    "iso:country":"BE",
    "sg:address":"Rue D\u00b4artois 31",
    "sg:city":"Brussel/bruxelles",
    "sg:orig_category":"Syst\u00e8mes de t\u00e9l\u00e9communications",
    "sg:phone":"+32 2 502 91 19",
    "sg:postcode":"1000",
    "sg:province":"Bruxelles-Capitale",
    "wof:name":"Fe. Ateck",
    "wof:placetype":"venue"
},
  "geometry": {"coordinates":[4.3424620628,50.8430747986],"type":"Point"}
}