{
  "type": "Feature",
  "properties": {
    "iso:country":"BE",
    "sg:address":"Thier M\u00c8re-dieu 20",
    "sg:city":"Verviers",
    "sg:orig_category":"Quincailleries",
    "sg:phone":"+32 87 33 04 24",
    "sg:postcode":"4800",
    "sg:province":"Li\u00e8ge",
    "wof:name":"Maison Piret-lenain",
    "wof:placetype":"venue"
},
  "geometry": {"coordinates":[5.8687109947,50.5930328369],"type":"Point"}
}