{
  "type": "Feature",
  "properties": {
    "iso:country":"BE",
    "sg:address":"Rue De L'harmonie 46",
    "sg:city":"Verviers",
    "sg:orig_category":"Brood, gebak and snoepgoed",
    "sg:phone":"+32 87 33 06 39",
    "sg:postcode":"4800",
    "sg:province":"Li\u00e8ge",
    "wof:name":"Boulangerie Notre-dame",
    "wof:placetype":"venue"
},
  "geometry": {"coordinates":[5.8755340576,50.5953216553],"type":"Point"}
}