{
  "type": "Feature",
  "properties": {
    "addr:full":"Plankstraat 2 Sint-truiden Limburg 3800",
    "addr:housenumber":"2",
    "addr:postcode":"3800",
    "addr:street":"Plankstraat",
    "iso:country":"BE",
    "sg:address":"Plankstraat 2",
    "sg:city":"Sint-truiden",
    "sg:classifiers":[
        {
            "category":"Cafe",
            "type":"Food & Drink"
        }
    ],
    "sg:phone":"+32 11 68 25 34",
    "sg:postcode":"3800",
    "sg:province":"Limburg",
    "sg:tags":[
        "caf\u00e9s"
    ],
    "wof:name":"Caf\u00c9 Plenkske",
    "wof:placetype":"venue"
},
  "geometry": {"coordinates":[5.1875891685,50.8161506653],"type":"Point"}
}