{
  "type": "Feature",
  "properties": {
    "iso:country":"BE",
    "sg:address":"Waterloose Steenweg 819",
    "sg:city":"Ukkel/uccle",
    "sg:orig_category":"Banken and kredietinstellingen",
    "sg:phone":"+32 2 346 27 50",
    "sg:postcode":"1180",
    "sg:province":"Bruxelles-Capitale",
    "wof:name":"Bbl",
    "wof:placetype":"venue"
},
  "geometry": {"coordinates":[4.3687520027,50.8107681274],"type":"Point"}
}