{
  "type": "Feature",
  "properties": {
    "addr:full":"Overdam 8 Evergem Oost-Vlaanderen 9940",
    "addr:housenumber":"8",
    "addr:postcode":"9940",
    "addr:street":"Overdam;Oost-Vlaanderen",
    "iso:country":"BE",
    "sg:address":"Overdam 8",
    "sg:city":"Evergem",
    "sg:orig_category":"Eleveurs de bovins",
    "sg:phone":"+32 9 253 07 44",
    "sg:postcode":"9940",
    "sg:province":"Oost-Vlaanderen",
    "wof:name":"Rafael Dobbelaere",
    "wof:placetype":"venue"
},
  "geometry": {"coordinates":[3.6801490784,51.0969085693],"type":"Point"}
}