{
  "type": "Feature",
  "properties": {
    "iso:country":"BE",
    "sg:address":"Rue De La Carri\u00e8re 2",
    "sg:city":"Wavre (bierges)",
    "sg:classifiers":[
        {
            "category":"Building & Trades",
            "subcategory":"Landscaping Services",
            "type":"Services"
        }
    ],
    "sg:phone":"+32 10 41 15 99",
    "sg:postcode":"1301",
    "sg:province":"Brabant Wallon",
    "sg:tags":[
        "equipment",
        "swimming",
        "-",
        "pool",
        "contractor"
    ],
    "wof:name":"Monteyne J-p",
    "wof:placetype":"venue"
},
  "geometry": {"coordinates":[4.6010169983,50.7070274353],"type":"Point"}
}