{
  "type": "Feature",
  "properties": {
    "addr:full":"Rue De Bavay 144 Boussu Hainaut 7301",
    "addr:housenumber":"144",
    "addr:postcode":"7301",
    "addr:street":"Rue De Bavay",
    "iso:country":"BE",
    "sg:address":"Rue De Bavay 144",
    "sg:city":"Boussu",
    "sg:orig_category":"Artsen and specialisten",
    "sg:phone":"+32 65 63 04 39",
    "sg:postcode":"7301",
    "sg:province":"Hainaut",
    "wof:name":"S. Ducobu",
    "wof:placetype":"venue"
},
  "geometry": {"coordinates":[3.8059771061,50.4042358398],"type":"Point"}
}