{
  "type": "Feature",
  "properties": {
    "addr:full":"Kortrijksestraat 58 Ardooie West-Vlaanderen 8850",
    "addr:housenumber":"58",
    "addr:postcode":"8850",
    "addr:street":"Kortrijksestraat",
    "iso:country":"BE",
    "sg:address":"Kortrijksestraat 58",
    "sg:city":"Ardooie",
    "sg:orig_category":"Maisons de repos and r\u00e9sidences",
    "sg:phone":"+32 51 74 41 53",
    "sg:postcode":"8850",
    "sg:province":"West-Vlaanderen",
    "wof:name":"Rusthuis St.vincentius",
    "wof:placetype":"venue"
},
  "geometry": {"coordinates":[3.197824955,50.9752998352],"type":"Point"}
}