{
  "type": "Feature",
  "properties": {
    "addr:full":"Assesteenweg 110 Ternat (sint-katherina-lombeek) Vlaams-Brabant 1742",
    "addr:housenumber":"110",
    "addr:postcode":"1742",
    "addr:street":"Assesteenweg",
    "iso:country":"BE",
    "sg:address":"Assesteenweg 110",
    "sg:city":"Ternat (sint-katherina-lombeek)",
    "sg:classifiers":[
        {
            "category":"Autos & Motor Vehicles",
            "subcategory":"Auto Supplies",
            "type":"Retail Goods"
        }
    ],
    "sg:phone":"+32 2 582 50 80",
    "sg:postcode":"1742",
    "sg:province":"Vlaams-Brabant",
    "sg:tags":[
        "access",
        "automobile",
        "part",
        "-"
    ],
    "wof:name":"Autoparts Plus Ternat",
    "wof:placetype":"venue"
},
  "geometry": {"coordinates":[4.163839817,50.8765678406],"type":"Point"}
}