{
  "type": "Feature",
  "properties": {
    "iso:country":"BE",
    "sg:address":"Drongense Steenweg 11",
    "sg:city":"Lovendegem (vinderhoute)",
    "sg:classifiers":[
        {
            "category":"Professional",
            "subcategory":"Accounting & Tax Preparation",
            "type":"Services"
        }
    ],
    "sg:phone":"+32 9 217 07 28",
    "sg:postcode":"9921",
    "sg:province":"Oost-Vlaanderen",
    "sg:tags":[
        "bookkeeper"
    ],
    "wof:name":"Triview Bvba",
    "wof:placetype":"venue"
},
  "geometry": {"coordinates":[3.6381640434,51.085811615],"type":"Point"}
}