{
  "type": "Feature",
  "properties": {
    "iso:country":"BE",
    "sg:address":"Rue Michel Body 10ba",
    "sg:city":"Grace-hollogne",
    "sg:orig_category":"Enseignement maternel and primaire",
    "sg:phone":"+32 4 233 59 56",
    "sg:postcode":"4460",
    "sg:province":"Li\u00e8ge",
    "wof:name":"Ecole Fondamentale Libre",
    "wof:placetype":"venue"
},
  "geometry": {"coordinates":[5.4757270813,50.6310348511],"type":"Point"}
}