{
  "type": "Feature",
  "properties": {
    "iso:country":"BE",
    "sg:address":"Coul\u00c9e 9bb",
    "sg:city":"Pepinster",
    "sg:orig_category":"Dakwerken Loodgieterij, verwarming and sanitaire installaties",
    "sg:phone":"+32 87 46 97 22",
    "sg:postcode":"4860",
    "sg:province":"Li\u00e8ge",
    "wof:name":"Jean-marie Charpentier",
    "wof:placetype":"venue"
},
  "geometry": {"coordinates":[5.7885570526,50.5742607117],"type":"Point"}
}