{
  "type": "Feature",
  "properties": {
    "iso:country":"BE",
    "sg:address":"Rue Sainte-anne 11",
    "sg:city":"Chiny",
    "sg:orig_category":"Eleveurs de bovins",
    "sg:phone":"+32 61 32 95 58",
    "sg:postcode":"6813",
    "sg:province":"Luxembourg",
    "wof:name":"Marcel Zacharie",
    "wof:placetype":"venue"
},
  "geometry": {"coordinates":[5.4571948051,49.7090873718],"type":"Point"}
}