{
  "type": "Feature",
  "properties": {
    "addr:full":"Rue Leopold Ii 23 Les Bons Villers (frasnes-lez-gosselies) Hainaut 6210",
    "addr:housenumber":"23",
    "addr:postcode":"6210",
    "addr:street":"Rue Leopold Ii",
    "iso:country":"BE",
    "sg:address":"Rue Leopold Ii 23",
    "sg:city":"Les Bons Villers (frasnes-lez-gosselies)",
    "sg:classifiers":[
        {
            "category":"Transit Center",
            "subcategory":"Freight",
            "type":"Transportation"
        }
    ],
    "sg:phone":"+32 71 85 26 25",
    "sg:postcode":"6210",
    "sg:province":"Hainaut",
    "sg:tags":[
        "import",
        "export",
        "-"
    ],
    "wof:name":"Euromed",
    "wof:placetype":"venue"
},
  "geometry": {"coordinates":[4.4511561394,50.5378227234],"type":"Point"}
}