{
  "type": "Feature",
  "properties": {
    "addr:full":"Dampoortstraat 82 Gent Oost-Vlaanderen 9000",
    "addr:housenumber":"82",
    "addr:postcode":"9000",
    "addr:street":"Dampoortstraat;Oost-Vlaanderen",
    "iso:country":"BE",
    "sg:address":"Dampoortstraat 82",
    "sg:city":"Gent",
    "sg:orig_category":"R\u00e9parations de chaussures and articles en cuir",
    "sg:phone":"+32 9 223 17 13",
    "sg:postcode":"9000",
    "sg:province":"Oost-Vlaanderen",
    "wof:name":"Huis Vandermeersch",
    "wof:placetype":"venue"
},
  "geometry": {"coordinates":[3.7373011112,51.0568656921],"type":"Point"}
}