{
  "type": "Feature",
  "properties": {
    "addr:full":"Gentsesteenweg 158 Erpe-mere (erpe) Oost-Vlaanderen 9420",
    "addr:housenumber":"158",
    "addr:postcode":"9420",
    "addr:street":"Gentsesteenweg",
    "iso:country":"BE",
    "sg:address":"Gentsesteenweg 158",
    "sg:city":"Erpe-mere (erpe)",
    "sg:classifiers":[
        {
            "category":"Home & Garden",
            "subcategory":"Building Materials",
            "type":"Retail Goods"
        }
    ],
    "sg:phone":"+32 53 80 61 72",
    "sg:postcode":"9420",
    "sg:province":"Oost-Vlaanderen",
    "sg:tags":[
        "granite",
        "stone",
        "natural",
        "marble"
    ],
    "wof:name":"Claus Tegelimport",
    "wof:placetype":"venue"
},
  "geometry": {"coordinates":[3.9806890488,50.9440498352],"type":"Point"}
}