{
  "type": "Feature",
  "properties": {
    "addr:full":"Mechelsesteenweg 91 Dendermonde Oost-Vlaanderen 9200",
    "addr:housenumber":"91",
    "addr:postcode":"9200",
    "addr:street":"Mechelsesteenweg;Oost-Vlaanderen",
    "iso:country":"BE",
    "sg:address":"Mechelsesteenweg 91",
    "sg:city":"Dendermonde",
    "sg:orig_category":"Kwantum Tuinbenodigdheden Verlichting and huishoudartikelen Vloer- and muurbekleding",
    "sg:phone":"+32 52 22 02 31",
    "sg:postcode":"9200",
    "sg:province":"Oost-Vlaanderen",
    "wof:name":"Kwantum",
    "wof:placetype":"venue"
},
  "geometry": {"coordinates":[4.1171560287,51.0358581543],"type":"Point"}
}