{
  "type": "Feature",
  "properties": {
    "iso:country":"BE",
    "sg:address":"Zeelaan 2",
    "sg:city":"Eeklo",
    "sg:orig_category":"Sportclubs Sportterreinen and installaties behalve sportcentra",
    "sg:phone":"+32 9 377 32 95",
    "sg:postcode":"9900",
    "sg:province":"Oost-Vlaanderen",
    "wof:name":"K.f.c. Exc. Balgerhoeke",
    "wof:placetype":"venue"
},
  "geometry": {"coordinates":[3.5259480476,51.1996192932],"type":"Point"}
}