{
  "type": "Feature",
  "properties": {
    "addr:full":"Boskantweg 66 Machelen Vlaams-Brabant 1830",
    "addr:housenumber":"66",
    "addr:postcode":"1830",
    "addr:street":"Boskantweg",
    "iso:country":"BE",
    "sg:address":"Boskantweg 66",
    "sg:city":"Machelen",
    "sg:orig_category":"Sportclubs",
    "sg:phone":"+32 2 251 03 19",
    "sg:postcode":"1830",
    "sg:province":"Vlaams-Brabant",
    "wof:name":"Machelen B.b.c.",
    "wof:placetype":"venue"
},
  "geometry": {"coordinates":[4.4457831383,50.9083061218],"type":"Point"}
}