{
  "type": "Feature",
  "properties": {
    "addr:full":"Rue Vanderborght 116 Jette Bruxelles-Capitale 1090",
    "addr:housenumber":"116",
    "addr:postcode":"1090",
    "addr:street":"Rue Vanderborght",
    "iso:country":"BE",
    "sg:address":"Rue Vanderborght 116",
    "sg:city":"Jette",
    "sg:orig_category":"Agences de presse. Production de films, t\u00e9l\u00e9films and vid\u00e9os",
    "sg:phone":"+32 2 426 35 15",
    "sg:postcode":"1090",
    "sg:province":"Bruxelles-Capitale",
    "wof:name":"Bernard Vervoort",
    "wof:placetype":"venue"
},
  "geometry": {"coordinates":[4.3245310783,50.8689193726],"type":"Point"}
}