{
  "type": "Feature",
  "properties": {
    "addr:full":"Rue Haute 17 Brussel/bruxelles Bruxelles-Capitale 1000",
    "addr:housenumber":"17",
    "addr:postcode":"1000",
    "addr:street":"Rue Haute;/",
    "iso:country":"BE",
    "sg:address":"Rue Haute 17",
    "sg:city":"Brussel/bruxelles",
    "sg:classifiers":[
        {
            "category":"Restaurant",
            "type":"Food & Drink"
        }
    ],
    "sg:phone":"+32 2 513 58 58",
    "sg:postcode":"1000",
    "sg:province":"Bruxelles-Capitale",
    "wof:name":"Les Ann\u00c9es Folles",
    "wof:placetype":"venue"
},
  "geometry": {"coordinates":[4.351998806,50.8418617249],"type":"Point"}
}