{
  "type": "Feature",
  "properties": {
    "iso:country":"BE",
    "sg:address":"Nederenamestraat 10",
    "sg:city":"Oudenaarde",
    "sg:orig_category":"Kapsalons",
    "sg:phone":"+32 55 31 28 63",
    "sg:postcode":"9700",
    "sg:province":"Oost-Vlaanderen",
    "wof:name":"Paul Raevens",
    "wof:placetype":"venue"
},
  "geometry": {"coordinates":[3.6545000076,50.8692207336],"type":"Point"}
}