{
  "type": "Feature",
  "properties": {
    "addr:full":"Rue De Forges Les Eaux 14 Herve (battice) Li\u00e8ge 4651",
    "addr:housenumber":"14",
    "addr:postcode":"4651",
    "addr:street":"Rue De Forges;Eaux",
    "iso:country":"BE",
    "sg:address":"Rue De Forges Les Eaux 14",
    "sg:city":"Herve (battice)",
    "sg:orig_category":"Non-Classified Establishments",
    "sg:phone":"+32 87 67 43 67",
    "sg:postcode":"4651",
    "sg:province":"Li\u00e8ge",
    "wof:name":"March\u00e9 Couvert De Battice Sc",
    "wof:placetype":"venue"
},
  "geometry": {"coordinates":[5.8225131035,50.6474494934],"type":"Point"}
}