{
  "type": "Feature",
  "properties": {
    "iso:country":"BE",
    "sg:address":"Baarleveldestraat 6",
    "sg:city":"Gent (drongen)",
    "sg:classifiers":[
        {
            "category":"Wholesale",
            "subcategory":"Plants",
            "type":"Manufacturing & Wholesale Goods"
        }
    ],
    "sg:phone":"+32 9 226 66 24",
    "sg:postcode":"9031",
    "sg:province":"Oost-Vlaanderen",
    "sg:tags":[
        "whol",
        "flower",
        "-",
        "grower"
    ],
    "wof:name":"Van Der Vennet J",
    "wof:placetype":"venue"
},
  "geometry": {"coordinates":[3.6242110729,51.0397453308],"type":"Point"}
}