{
  "type": "Feature",
  "properties": {
    "iso:country":"BE",
    "sg:address":"Stationlaan 20",
    "sg:city":"Bilzen",
    "sg:classifiers":[
        {
            "category":"Personal",
            "subcategory":"Beauty Salon",
            "type":"Services"
        }
    ],
    "sg:phone":"+32 89 41 30 03",
    "sg:postcode":"3740",
    "sg:province":"Limburg",
    "wof:name":"Nefertiti",
    "wof:placetype":"venue"
},
  "geometry": {"coordinates":[5.5122151375,50.8693809509],"type":"Point"}
}