{
  "type": "Feature",
  "properties": {
    "iso:country":"BE",
    "sg:address":"Sassenbroekstraat 33",
    "sg:city":"Alken",
    "sg:orig_category":"Eleveurs and marchands de porcs. Producteurs de fruits",
    "sg:phone":"+32 11 31 16 04",
    "sg:postcode":"3570",
    "sg:province":"Limburg",
    "wof:name":"Jozef Hendrix",
    "wof:placetype":"venue"
},
  "geometry": {"coordinates":[5.3220009804,50.8833694458],"type":"Point"}
}