{
  "type": "Feature",
  "properties": {
    "iso:country":"BE",
    "sg:address":"Sint-stevenstraat 61",
    "sg:city":"Zelzate",
    "sg:orig_category":"Woningbouw",
    "sg:phone":"+32 9 345 52 06",
    "sg:postcode":"9060",
    "sg:province":"Oost-Vlaanderen",
    "wof:name":"Dani\u00cbl De Coninck",
    "wof:placetype":"venue"
},
  "geometry": {"coordinates":[3.829102993,51.2046813965],"type":"Point"}
}