{
  "type": "Feature",
  "properties": {
    "addr:full":"Avenue Jean-baptiste Nothomb 10 Box 112 Arlon Luxembourg 6700",
    "addr:housenumber":"10",
    "addr:postcode":"6700",
    "addr:street":"Avenue Jean-Baptiste Nothomb;Box 112",
    "iso:country":"BE",
    "sg:address":"Avenue Jean-baptiste Nothomb 10 Box 112",
    "sg:city":"Arlon",
    "sg:classifiers":[
        {
            "category":"Health Services",
            "subcategory":"Health Practitioner",
            "type":"Services"
        }
    ],
    "sg:phone":"+32 63 22 71 37",
    "sg:postcode":"6700",
    "sg:province":"Luxembourg",
    "sg:tags":[
        "physiotherapist"
    ],
    "wof:name":"Fontaine Norbert",
    "wof:placetype":"venue"
},
  "geometry": {"coordinates":[5.8113899231,49.6821327209],"type":"Point"}
}