{
  "type": "Feature",
  "properties": {
    "addr:full":"Franz Courtensstraat 22 Dendermonde Oost-Vlaanderen 9200",
    "addr:housenumber":"22",
    "addr:postcode":"9200",
    "addr:street":"Franz Courtensstraat;Oost-Vlaanderen",
    "iso:country":"BE",
    "sg:address":"Franz Courtensstraat 22",
    "sg:city":"Dendermonde",
    "sg:orig_category":"Disneyland Paris. Agences de voyages",
    "sg:phone":"+32 52 21 39 34",
    "sg:postcode":"9200",
    "sg:province":"Oost-Vlaanderen",
    "wof:name":"V.t.b.",
    "wof:placetype":"venue"
},
  "geometry": {"coordinates":[4.1008448601,51.0322341919],"type":"Point"}
}