{
  "type": "Feature",
  "properties": {
    "addr:full":"Chee De Tervueren 40 Waterloo Brabant Wallon 1410",
    "addr:housenumber":"40",
    "addr:postcode":"1410",
    "addr:street":"Chee;Tervueren",
    "iso:country":"BE",
    "sg:address":"Chee De Tervueren 40",
    "sg:city":"Waterloo",
    "sg:classifiers":[
        {
            "category":"Banks & Credit Unions",
            "subcategory":"Bank",
            "type":"Services"
        }
    ],
    "sg:phone":"+32 2 354 46 16",
    "sg:postcode":"1410",
    "sg:province":"Brabant Wallon",
    "wof:name":"Aslk-cger Bank",
    "wof:placetype":"venue"
},
  "geometry": {"coordinates":[4.4028968811,50.7022514343],"type":"Point"}
}