{
  "type": "Feature",
  "properties": {
    "iso:country":"BE",
    "sg:address":"Begonialaan 16",
    "sg:city":"Wervik",
    "sg:orig_category":"Plaatsen van vloer- and muurbekleding Woningbouw",
    "sg:phone":"+32 56 31 43 52",
    "sg:postcode":"8940",
    "sg:province":"West-Vlaanderen",
    "wof:name":"Verriest",
    "wof:placetype":"venue"
},
  "geometry": {"coordinates":[3.054764986,50.7846336365],"type":"Point"}
}