{
  "type": "Feature",
  "properties": {
    "addr:full":"Schuurhoven 84 Oud-turnhout Antwerpen 2360",
    "addr:housenumber":"84",
    "addr:postcode":"2360",
    "addr:street":"Schuurhoven",
    "iso:country":"BE",
    "sg:address":"Schuurhoven 84",
    "sg:city":"Oud-turnhout",
    "sg:orig_category":"Diverse bouwafwerking and reiniging Gespecialiseerde residenti\u00eble bouw",
    "sg:phone":"+32 14 42 69 59",
    "sg:postcode":"2360",
    "sg:province":"Antwerpen",
    "wof:name":"Ronny Hertogs",
    "wof:placetype":"venue"
},
  "geometry": {"coordinates":[4.9786272049,51.3364181519],"type":"Point"}
}