{
  "type": "Feature",
  "properties": {
    "iso:country":"BE",
    "sg:address":"Meibloemstraat 14",
    "sg:city":"Gent",
    "sg:classifiers":[
        {
            "category":"Manufacturing",
            "subcategory":"Furniture",
            "type":"Manufacturing & Wholesale Goods"
        }
    ],
    "sg:phone":"+32 9 226 29 22",
    "sg:postcode":"9000",
    "sg:province":"Oost-Vlaanderen",
    "sg:tags":[
        "design",
        "-"
    ],
    "wof:name":"Van Den Berghe-pauvers Bvba",
    "wof:placetype":"venue"
},
  "geometry": {"coordinates":[3.6986250877,51.0584945679],"type":"Point"}
}