{
  "type": "Feature",
  "properties": {
    "iso:country":"BE",
    "sg:address":"Pastoor Van Haechtplein 5",
    "sg:city":"Meerhout",
    "sg:orig_category":"Banques and organismes de cr\u00e9dit",
    "sg:phone":"+32 14 36 99 60",
    "sg:postcode":"2450",
    "sg:province":"Antwerpen",
    "wof:name":"Dexia",
    "wof:placetype":"venue"
},
  "geometry": {"coordinates":[5.076364994,51.1320304871],"type":"Point"}
}