{
  "type": "Feature",
  "properties": {
    "iso:country":"BE",
    "sg:address":"Leuvensesteenweg 452",
    "sg:city":"Schaarbeek/schaerbeek",
    "sg:orig_category":"Catering and organisatie van feesten Fast food and meeneem restaurants Restaurants",
    "sg:phone":"+32 2 733 55 95",
    "sg:postcode":"1030",
    "sg:province":"Bruxelles-Capitale",
    "wof:name":"Restaurant Le Poseidon",
    "wof:placetype":"venue"
},
  "geometry": {"coordinates":[4.3899497986,50.8528366089],"type":"Point"}
}