{
  "type": "Feature",
  "properties": {
    "addr:full":"Serpentstraat 129 Oudenaarde Oost-Vlaanderen 9700",
    "addr:housenumber":"129",
    "addr:postcode":"9700",
    "addr:street":"Serpentstraat",
    "iso:country":"BE",
    "sg:address":"Serpentstraat 129",
    "sg:city":"Oudenaarde",
    "sg:orig_category":"Eleveurs de bovins",
    "sg:phone":"+32 55 31 36 92",
    "sg:postcode":"9700",
    "sg:province":"Oost-Vlaanderen",
    "wof:name":"Adiel Deruyck",
    "wof:placetype":"venue"
},
  "geometry": {"coordinates":[3.6084148884,50.8718338013],"type":"Point"}
}