{
  "type": "Feature",
  "properties": {
    "addr:full":"Avenue Marnix 24 Brussels Bruxelles-Capitale 1000",
    "addr:housenumber":"24",
    "addr:postcode":"1000",
    "addr:street":"Avenue Marnix",
    "iso:country":"BE",
    "sg:address":"Avenue Marnix 24",
    "sg:city":"Brussels",
    "sg:classifiers":[
        {
            "category":"Banks & Credit Unions",
            "subcategory":"Bank",
            "type":"Services"
        }
    ],
    "sg:postcode":"1000",
    "sg:province":"Bruxelles-Capitale",
    "wof:name":"Rv Assurances",
    "wof:placetype":"venue"
},
  "geometry": {"coordinates":[5.5789031982,50.616317749],"type":"Point"}
}