{
  "type": "Feature",
  "properties": {
    "iso:country":"BE",
    "sg:address":"Strandlaan 162",
    "sg:city":"Koksijde",
    "sg:classifiers":[
        {
            "category":"Bars & Pubs",
            "type":"Food & Drink"
        }
    ],
    "sg:phone":"+32 58 51 89 72",
    "sg:postcode":"8670",
    "sg:province":"West-Vlaanderen",
    "sg:tags":[
        "tavern"
    ],
    "wof:name":"Atelier En Folie",
    "wof:placetype":"venue"
},
  "geometry": {"coordinates":[2.6166000366,51.1052856445],"type":"Point"}
}