{
  "type": "Feature",
  "properties": {
    "iso:country":"BE",
    "sg:address":"Viadukt 6",
    "sg:city":"Temse",
    "sg:classifiers":[
        {
            "category":"Health Services",
            "subcategory":"Dentist",
            "type":"Services"
        }
    ],
    "sg:phone":"+32 3 771 04 28",
    "sg:postcode":"9140",
    "sg:province":"Oost-Vlaanderen",
    "wof:name":"Weyn Els",
    "wof:placetype":"venue"
},
  "geometry": {"coordinates":[4.2143149376,51.1247558594],"type":"Point"}
}