{
  "type": "Feature",
  "properties": {
    "iso:country":"BE",
    "sg:address":"Staatsbaan 9",
    "sg:city":"Maldegem (adegem)",
    "sg:classifiers":[
        {
            "category":"Utilities",
            "subcategory":"Fuel Oil & Lpg",
            "type":"Services"
        }
    ],
    "sg:phone":"+32 50 71 24 16",
    "sg:postcode":"9991",
    "sg:province":"Oost-Vlaanderen",
    "wof:name":"Cuelenaere Aim\u00e9 & Zn",
    "wof:placetype":"venue"
},
  "geometry": {"coordinates":[3.4774689674,51.2049331665],"type":"Point"}
}