{
  "type": "Feature",
  "properties": {
    "addr:full":"Stationstraat 43 Haacht Vlaams-Brabant 3150",
    "addr:housenumber":"43",
    "addr:postcode":"3150",
    "addr:street":"Stationstraat",
    "iso:country":"BE",
    "sg:address":"Stationstraat 43",
    "sg:city":"Haacht",
    "sg:orig_category":"Industri\u00eble wasserijen and droogkuis",
    "sg:phone":"+32 16 60 32 08",
    "sg:postcode":"3150",
    "sg:province":"Vlaams-Brabant",
    "wof:name":"Aqua Bright",
    "wof:placetype":"venue"
},
  "geometry": {"coordinates":[4.6339621544,50.9768638611],"type":"Point"}
}