{
  "type": "Feature",
  "properties": {
    "addr:full":"Rue Du Ch\u00e2teau 78 Anderlues Hainaut 6150",
    "addr:housenumber":"78",
    "addr:postcode":"6150",
    "addr:street":"Rue Du Cha\u0302Teau",
    "iso:country":"BE",
    "sg:address":"Rue Du Ch\u00e2teau 78",
    "sg:city":"Anderlues",
    "sg:classifiers":[
        {
            "category":"Real Estate",
            "subcategory":"Architect",
            "type":"Services"
        }
    ],
    "sg:phone":"+32 71 52 57 33",
    "sg:postcode":"6150",
    "sg:province":"Hainaut",
    "wof:name":"Bilos P",
    "wof:placetype":"venue"
},
  "geometry": {"coordinates":[4.2722940445,50.4014587402],"type":"Point"}
}