{
  "type": "Feature",
  "properties": {
    "iso:country":"BE",
    "sg:address":"Lochtemanweg 2",
    "sg:city":"Beringen",
    "sg:classifiers":[
        {
            "category":"Food & Beverages",
            "subcategory":"Supermarket",
            "type":"Retail Goods"
        }
    ],
    "sg:phone":"+32 11 45 85 45",
    "sg:postcode":"3580",
    "sg:province":"Limburg",
    "sg:tags":[
        "frozen",
        "-"
    ],
    "wof:name":"Bestfood Grosmarkt",
    "wof:placetype":"venue"
},
  "geometry": {"coordinates":[5.2243900299,51.0379981995],"type":"Point"}
}