{
  "type": "Feature",
  "properties": {
    "addr:full":"Rue De Bransart 136 Namur (malonne) Namur 5020",
    "addr:housenumber":"136",
    "addr:postcode":"5020",
    "addr:street":"Rue De Bransart",
    "iso:country":"BE",
    "sg:address":"Rue De Bransart 136",
    "sg:city":"Namur (malonne)",
    "sg:classifiers":[
        {
            "category":"Retail",
            "subcategory":"Auto Repair",
            "type":"Services"
        }
    ],
    "sg:phone":"+32 81 44 56 51",
    "sg:postcode":"5020",
    "sg:province":"Namur",
    "sg:tags":[
        "automobile-body"
    ],
    "wof:name":"Bransart (carrosserie Du) Sc",
    "wof:placetype":"venue"
},
  "geometry": {"coordinates":[4.7952418327,50.4352035522],"type":"Point"}
}