{
  "type": "Feature",
  "properties": {
    "iso:country":"BE",
    "sg:address":"Dorpsstraat 101",
    "sg:city":"Heusden-zolder",
    "sg:orig_category":"Kantoormateriaal",
    "sg:phone":"+32 11 53 38 95",
    "sg:postcode":"3550",
    "sg:province":"Limburg",
    "wof:name":"Stephan Koopmans",
    "wof:placetype":"venue"
},
  "geometry": {"coordinates":[5.3144397736,51.0230560303],"type":"Point"}
}