{
  "type": "Feature",
  "properties": {
    "iso:country":"BE",
    "sg:address":"Rue Des R\u00c9collets 1",
    "sg:city":"Nivelles",
    "sg:orig_category":"M\u00e9decins and sp\u00e9cialistes",
    "sg:phone":"+32 67 21 32 02",
    "sg:postcode":"1400",
    "sg:province":"Brabant Wallon",
    "wof:name":"R. Lennaertz",
    "wof:placetype":"venue"
},
  "geometry": {"coordinates":[4.3265237808,50.5968017578],"type":"Point"}
}