{
  "type": "Feature",
  "properties": {
    "addr:full":"Rue Victor Delporte 25 Hensies Hainaut 7350",
    "addr:housenumber":"25",
    "addr:postcode":"7350",
    "addr:street":"Rue Victor Delporte",
    "iso:country":"BE",
    "sg:address":"Rue Victor Delporte 25",
    "sg:city":"Hensies",
    "sg:orig_category":"Kantoormateriaal Speelgoed",
    "sg:phone":"+32 65 65 25 30",
    "sg:postcode":"7350",
    "sg:province":"Hainaut",
    "wof:name":"Berthe Dupont",
    "wof:placetype":"venue"
},
  "geometry": {"coordinates":[3.7383449078,50.4274902344],"type":"Point"}
}