{
  "type": "Feature",
  "properties": {
    "iso:country":"BE",
    "sg:address":"Mallekotstraat 81",
    "sg:city":"Lier",
    "sg:classifiers":[
        {
            "category":"Home & Garden",
            "subcategory":"Carpets & Floor Coverings",
            "type":"Retail Goods"
        }
    ],
    "sg:phone":"+32 3 489 08 48",
    "sg:postcode":"2500",
    "sg:province":"Antwerpen",
    "sg:tags":[
        "houses",
        "shed"
    ],
    "wof:name":"Ambo B.v.b.a.",
    "wof:placetype":"venue"
},
  "geometry": {"coordinates":[4.5537037849,51.1445503235],"type":"Point"}
}