{
  "type": "Feature",
  "properties": {
    "addr:full":"Waterloose Steenweg 635 Elsene/ixelles Bruxelles-Capitale 1050",
    "addr:housenumber":"635",
    "addr:postcode":"1050",
    "addr:street":"Waterloose Steenweg",
    "iso:country":"BE",
    "sg:address":"Waterloose Steenweg 635",
    "sg:city":"Elsene/ixelles",
    "sg:orig_category":"Drukkerijen and copyshops Kantoormateriaal",
    "sg:phone":"+32 2 344 89 61",
    "sg:postcode":"1050",
    "sg:province":"Bruxelles-Capitale",
    "wof:name":"I.p.l. Papeterie",
    "wof:placetype":"venue"
},
  "geometry": {"coordinates":[4.3651628494,50.8174324036],"type":"Point"}
}