{
  "type": "Feature",
  "properties": {
    "addr:full":"Rue Haute 28 Qu\u00c9vy Hainaut 7040",
    "addr:housenumber":"28",
    "addr:postcode":"7040",
    "addr:street":"Rue Haute;Hainaut",
    "iso:country":"BE",
    "sg:address":"Rue Haute 28",
    "sg:city":"Qu\u00c9vy",
    "sg:orig_category":"Elektrische installaties voor woningen",
    "sg:phone":"+32 65 56 81 16",
    "sg:postcode":"7040",
    "sg:province":"Hainaut",
    "wof:name":"Jean-francois Couvreur",
    "wof:placetype":"venue"
},
  "geometry": {"coordinates":[3.94688797,50.3603591919],"type":"Point"}
}