{
  "type": "Feature",
  "properties": {
    "iso:country":"BE",
    "sg:address":"Vlasrootstraat 179",
    "sg:city":"Stekene",
    "sg:orig_category":"Eleveurs de bovins",
    "sg:phone":"+32 3 779 78 81",
    "sg:postcode":"9190",
    "sg:province":"Oost-Vlaanderen",
    "wof:name":"Andre Fierens",
    "wof:placetype":"venue"
},
  "geometry": {"coordinates":[4.0649490356,51.1897315979],"type":"Point"}
}