{
  "type": "Feature",
  "properties": {
    "addr:full":"Molenwiel 3 Arendonk Antwerpen 2370",
    "addr:housenumber":"3",
    "addr:postcode":"2370",
    "addr:street":"Molenwiel",
    "iso:country":"BE",
    "sg:address":"Molenwiel 3",
    "sg:city":"Arendonk",
    "sg:orig_category":"Microsoft. Electrom\u00e9nager, t\u00e9l\u00e9visions and radios",
    "sg:phone":"+32 14 67 03 50",
    "sg:postcode":"2370",
    "sg:province":"Antwerpen",
    "wof:name":"Dubois Patrick",
    "wof:placetype":"venue"
},
  "geometry": {"coordinates":[5.0873970985,51.3249740601],"type":"Point"}
}