{
  "type": "Feature",
  "properties": {
    "iso:country":"BE",
    "sg:address":"Place Du Marche 20",
    "sg:city":"Verviers",
    "sg:classifiers":[
        {
            "category":"Recreation",
            "subcategory":"Theme Park",
            "type":"Entertainment"
        }
    ],
    "sg:phone":"+32 87 31 66 30",
    "sg:postcode":"4800",
    "sg:province":"Li\u00e8ge",
    "sg:tags":[
        "paris",
        "disneyland"
    ],
    "wof:name":"Patrice Petit Voyages",
    "wof:placetype":"venue"
},
  "geometry": {"coordinates":[5.8674988747,50.5931663513],"type":"Point"}
}