{
  "type": "Feature",
  "properties": {
    "iso:country":"BE",
    "sg:address":"Brillat-savarinlaan 10",
    "sg:city":"Elsene/ixelles",
    "sg:orig_category":"Speelgoed",
    "sg:phone":"+32 2 640 10 89",
    "sg:postcode":"1050",
    "sg:province":"Bruxelles-Capitale",
    "wof:name":"Maison Ludos",
    "wof:placetype":"venue"
},
  "geometry": {"coordinates":[4.3879160881,50.8171615601],"type":"Point"}
}