{
  "type": "Feature",
  "properties": {
    "addr:full":"Avenue Jacques Sermon 38 Bruxelles (ganshoren) Bruxelles-Capitale 1083",
    "addr:housenumber":"38",
    "addr:postcode":"1083",
    "addr:street":"Avenue Jacques Sermon",
    "iso:country":"BE",
    "sg:address":"Avenue Jacques Sermon 38",
    "sg:city":"Bruxelles (ganshoren)",
    "sg:classifiers":[
        {
            "category":"Banks & Credit Unions",
            "subcategory":"Investment Brokerage",
            "type":"Services"
        }
    ],
    "sg:phone":"+32 2 425 71 14",
    "sg:postcode":"1083",
    "sg:province":"Bruxelles-Capitale",
    "sg:tags":[
        "auditor"
    ],
    "wof:name":"Degeest,van Goethem & Co Bvba",
    "wof:placetype":"venue"
},
  "geometry": {"coordinates":[4.3210778236,50.8687095642],"type":"Point"}
}