{
  "type": "Feature",
  "properties": {
    "iso:country":"BE",
    "sg:address":"Rue De Braine 25",
    "sg:city":"Braine-le-comte",
    "sg:orig_category":"Forge, Moulage and Profilage des M\u00e9taux",
    "sg:phone":"+32 475 87 44 56",
    "sg:postcode":"7090",
    "sg:province":"Hainaut",
    "wof:name":"Ferronnerie D'hennuyeres",
    "wof:placetype":"venue"
},
  "geometry": {"coordinates":[4.0987701416,50.6223297119],"type":"Point"}
}