{
  "type": "Feature",
  "properties": {
    "addr:full":"Langestraat 46 Oostende West-Vlaanderen 8400",
    "addr:housenumber":"46",
    "addr:postcode":"8400",
    "addr:street":"Langestraat",
    "iso:country":"BE",
    "sg:address":"Langestraat 46",
    "sg:city":"Oostende",
    "sg:classifiers":[
        {
            "category":"Building & Trades",
            "subcategory":"Plumbing",
            "type":"Services"
        }
    ],
    "sg:phone":"+32 59 50 72 78",
    "sg:postcode":"8400",
    "sg:province":"West-Vlaanderen",
    "sg:tags":[
        "diver",
        "commerce",
        "gr",
        "pour",
        "equipement"
    ],
    "wof:name":"G.b.c. Association",
    "wof:placetype":"venue"
},
  "geometry": {"coordinates":[2.9160070419,51.2324180603],"type":"Point"}
}