{
  "type": "Feature",
  "properties": {
    "addr:full":"Groenstraat 1 Zwevegem (heestert) West-Vlaanderen 8551",
    "addr:housenumber":"1",
    "addr:postcode":"8551",
    "addr:street":"Groenstraat",
    "iso:country":"BE",
    "sg:address":"Groenstraat 1",
    "sg:city":"Zwevegem (heestert)",
    "sg:classifiers":[
        {
            "category":"Professional",
            "type":"Services"
        }
    ],
    "sg:phone":"+32 56 64 86 82",
    "sg:postcode":"8551",
    "sg:province":"West-Vlaanderen",
    "sg:tags":[
        "industrial",
        "work",
        "-",
        "maintenance"
    ],
    "wof:name":"Demeyere J",
    "wof:placetype":"venue"
},
  "geometry": {"coordinates":[3.4183828831,50.7821922302],"type":"Point"}
}