{
  "type": "Feature",
  "properties": {
    "addr:full":"Rue De Luttre 99 Courcelles (gouy-lez-pi\u00e9ton) Hainaut 6181",
    "addr:housenumber":"99",
    "addr:postcode":"6181",
    "addr:street":"Rue De Luttre",
    "iso:country":"BE",
    "sg:address":"Rue De Luttre 99",
    "sg:city":"Courcelles (gouy-lez-pi\u00e9ton)",
    "sg:classifiers":[
        {
            "category":"Personal",
            "subcategory":"Beauty Salon",
            "type":"Services"
        }
    ],
    "sg:phone":"+32 71 84 26 25",
    "sg:postcode":"6181",
    "sg:province":"Hainaut",
    "sg:tags":[
        "lady",
        "-",
        "hairdressing"
    ],
    "wof:name":"Lady-tif (coiffure)",
    "wof:placetype":"venue"
},
  "geometry": {"coordinates":[4.3359742165,50.4909934998],"type":"Point"}
}