{
  "type": "Feature",
  "properties": {
    "addr:full":"Rue Alphonse Collette 50 Theux Li\u00e8ge 4910",
    "addr:housenumber":"50",
    "addr:postcode":"4910",
    "addr:street":"Rue Alphonse Collette",
    "iso:country":"BE",
    "sg:address":"Rue Alphonse Collette 50",
    "sg:city":"Theux",
    "sg:orig_category":"Epiceries",
    "sg:phone":"+32 87 22 47 17",
    "sg:postcode":"4910",
    "sg:province":"Li\u00e8ge",
    "wof:name":"Supra",
    "wof:placetype":"venue"
},
  "geometry": {"coordinates":[5.8130488396,50.5356216431],"type":"Point"}
}