{
  "type": "Feature",
  "properties": {
    "addr:full":"Rue Chantrenne 3 Momignies Hainaut 6590",
    "addr:housenumber":"3",
    "addr:postcode":"6590",
    "addr:street":"Rue Chantrenne;Hainaut",
    "iso:country":"BE",
    "sg:address":"Rue Chantrenne 3",
    "sg:city":"Momignies",
    "sg:orig_category":"Electrom\u00e9nager, t\u00e9l\u00e9visions and radios",
    "sg:phone":"+32 60 51 11 14",
    "sg:postcode":"6590",
    "sg:province":"Hainaut",
    "wof:name":"Francis Mascre",
    "wof:placetype":"venue"
},
  "geometry": {"coordinates":[4.164285183,50.029750824],"type":"Point"}
}