{
  "type": "Feature",
  "properties": {
    "addr:full":"Schrijnwerkersstraat 8 Antwerpen Antwerpen 2000",
    "addr:housenumber":"8",
    "addr:postcode":"2000",
    "addr:street":"Schrijnwerkersstraat",
    "iso:country":"BE",
    "sg:address":"Schrijnwerkersstraat 8",
    "sg:city":"Antwerpen",
    "sg:classifiers":[
        {
            "category":"Deli",
            "type":"Food & Drink"
        }
    ],
    "sg:phone":"+32 3 231 46 20",
    "sg:postcode":"2000",
    "sg:province":"Antwerpen",
    "sg:tags":[
        "delicatessen"
    ],
    "wof:name":"Oliviers & Co",
    "wof:placetype":"venue"
},
  "geometry": {"coordinates":[4.4034938812,51.2179946899],"type":"Point"}
}