{
  "type": "Feature",
  "properties": {
    "addr:full":"Industriepark 40 Hulshout Antwerpen 2235",
    "addr:housenumber":"40",
    "addr:postcode":"2235",
    "addr:street":"Industriepark",
    "iso:country":"BE",
    "sg:address":"Industriepark 40",
    "sg:city":"Hulshout",
    "sg:classifiers":[
        {
            "category":"Home & Garden",
            "subcategory":"Building Materials",
            "type":"Retail Goods"
        }
    ],
    "sg:phone":"+32 15 22 23 22",
    "sg:postcode":"2235",
    "sg:province":"Antwerpen",
    "sg:tags":[
        "granite",
        "stone",
        "natural",
        "marble"
    ],
    "wof:name":"Dils Bouwcenter",
    "wof:placetype":"venue"
},
  "geometry": {"coordinates":[4.8126020432,51.0795402527],"type":"Point"}
}