{
  "type": "Feature",
  "properties": {
    "iso:country":"BE",
    "sg:address":"Maalbeek 18",
    "sg:city":"Asse",
    "sg:orig_category":"Fleurs and plantes",
    "sg:phone":"+32 2 460 01 38",
    "sg:postcode":"1731",
    "sg:province":"Vlaams-Brabant",
    "wof:name":"Roger Vandersmissen",
    "wof:placetype":"venue"
},
  "geometry": {"coordinates":[4.2791528702,50.8972091675],"type":"Point"}
}