{
  "type": "Feature",
  "properties": {
    "addr:full":"Roosakkerstraat 16 Lanaken Limburg 3620",
    "addr:housenumber":"16",
    "addr:postcode":"3620",
    "addr:street":"Roosakkerstraat",
    "iso:country":"BE",
    "sg:address":"Roosakkerstraat 16",
    "sg:city":"Lanaken",
    "sg:orig_category":"Agences immobili\u00e8res",
    "sg:phone":"+32 89 71 74 04",
    "sg:postcode":"3620",
    "sg:province":"Limburg",
    "wof:name":"Immobili\u00cbn Holtappels",
    "wof:placetype":"venue"
},
  "geometry": {"coordinates":[5.6551351547,50.8912277222],"type":"Point"}
}