{
  "type": "Feature",
  "properties": {
    "addr:full":"Diestersteenweg 45 Nieuwerkerken Limburg 3850",
    "addr:housenumber":"45",
    "addr:postcode":"3850",
    "addr:street":"Diestersteenweg",
    "iso:country":"BE",
    "sg:address":"Diestersteenweg 45",
    "sg:city":"Nieuwerkerken",
    "sg:orig_category":"Eleveurs de bovins",
    "sg:phone":"+32 11 68 46 61",
    "sg:postcode":"3850",
    "sg:province":"Limburg",
    "wof:name":"Marc Lammens",
    "wof:placetype":"venue"
},
  "geometry": {"coordinates":[5.1888551712,50.8589668274],"type":"Point"}
}