{
  "type": "Feature",
  "properties": {
    "addr:full":"Dumortierlaan 115 Knokke-heist West-Vlaanderen 8300",
    "addr:housenumber":"115",
    "addr:postcode":"8300",
    "addr:street":"Dumortierlaan",
    "iso:country":"BE",
    "sg:address":"Dumortierlaan 115",
    "sg:city":"Knokke-heist",
    "sg:orig_category":"Meubles D\u00e9taillants, Am\u00e9nagement de B\u00e2timents et de Cuisines",
    "sg:phone":"+32 50 61 60 07",
    "sg:postcode":"8300",
    "sg:province":"West-Vlaanderen",
    "wof:name":"Meubelen Momentum",
    "wof:placetype":"venue"
},
  "geometry": {"coordinates":[3.287694931,51.3467254639],"type":"Point"}
}