{
  "type": "Feature",
  "properties": {
    "addr:full":"Weverstraat 10 Laakdal Antwerpen 2430",
    "addr:housenumber":"10",
    "addr:postcode":"2430",
    "addr:street":"Weverstraat",
    "iso:country":"BE",
    "sg:address":"Weverstraat 10",
    "sg:city":"Laakdal",
    "sg:orig_category":"Installatie van houten of kunststof schrijnwerk",
    "sg:phone":"+32 14 86 63 78",
    "sg:postcode":"2430",
    "sg:province":"Antwerpen",
    "wof:name":"Desideer Verbruggen",
    "wof:placetype":"venue"
},
  "geometry": {"coordinates":[5.0687851906,51.0857543945],"type":"Point"}
}