{
  "type": "Feature",
  "properties": {
    "iso:country":"BE",
    "sg:address":"Zwevezelestraat 47b2",
    "sg:city":"Lichtervelde",
    "sg:orig_category":"Woningbouw",
    "sg:phone":"+32 51 72 24 29",
    "sg:postcode":"8810",
    "sg:province":"West-Vlaanderen",
    "wof:name":"Georges Cassaert",
    "wof:placetype":"venue"
},
  "geometry": {"coordinates":[3.1469008923,51.0294761658],"type":"Point"}
}