{
  "type": "Feature",
  "properties": {
    "addr:full":"Haachtsesteenweg 544 Kampenhout Vlaams-Brabant 1910",
    "addr:housenumber":"544",
    "addr:postcode":"1910",
    "addr:street":"Haachtsesteenweg",
    "iso:country":"BE",
    "sg:address":"Haachtsesteenweg 544",
    "sg:city":"Kampenhout",
    "sg:classifiers":[
        {
            "category":"Shopping",
            "subcategory":"Stationery & Office Supplies",
            "type":"Retail Goods"
        }
    ],
    "sg:phone":"+32 16 65 62 46",
    "sg:postcode":"1910",
    "sg:province":"Vlaams-Brabant",
    "sg:tags":[
        "fixture"
    ],
    "wof:name":"Studio R.l.",
    "wof:placetype":"venue"
},
  "geometry": {"coordinates":[4.5829057693,50.9503707886],"type":"Point"}
}