{
  "type": "Feature",
  "properties": {
    "addr:full":"Kikvorsstraat 104 Gent Oost-Vlaanderen 9000",
    "addr:housenumber":"104",
    "addr:postcode":"9000",
    "addr:street":"Kikvorsstraat;Oost-Vlaanderen",
    "iso:country":"BE",
    "sg:address":"Kikvorsstraat 104",
    "sg:city":"Gent",
    "sg:classifiers":[
        {
            "category":"Health Services",
            "subcategory":"Health Practitioner",
            "type":"Services"
        }
    ],
    "sg:phone":"+32 9 221 49 42",
    "sg:postcode":"9000",
    "sg:province":"Oost-Vlaanderen",
    "sg:tags":[
        "physiotherapist"
    ],
    "wof:name":"Allyn Margaret",
    "wof:placetype":"venue"
},
  "geometry": {"coordinates":[3.7169690132,51.0236778259],"type":"Point"}
}