{
  "type": "Feature",
  "properties": {
    "addr:full":"Jubelfeestlaan 54 Sint-jans-molenbeek/molenbeek-saint-jean Bruxelles-Capitale 1080",
    "addr:housenumber":"54",
    "addr:postcode":"1080",
    "addr:street":"Jubelfeestlaan",
    "iso:country":"BE",
    "sg:address":"Jubelfeestlaan 54",
    "sg:city":"Sint-jans-molenbeek/molenbeek-saint-jean",
    "sg:orig_category":"Kapsalons",
    "sg:phone":"+32 2 426 22 89",
    "sg:postcode":"1080",
    "sg:province":"Bruxelles-Capitale",
    "wof:name":"Haute Coiffure Leila",
    "wof:placetype":"venue"
},
  "geometry": {"coordinates":[4.3373241425,50.8632659912],"type":"Point"}
}