{
  "type": "Feature",
  "properties": {
    "iso:country":"BE",
    "sg:address":"Industriezone Ekkelgarden 4",
    "sg:city":"Hasselt",
    "sg:classifiers":[
        {
            "category":"Autos & Motor Vehicles",
            "subcategory":"Automobile Sales",
            "type":"Retail Goods"
        }
    ],
    "sg:phone":"+32 11 27 90 00",
    "sg:postcode":"3500",
    "sg:province":"Limburg",
    "sg:tags":[
        "industrial"
    ],
    "wof:name":"Etablissementen Hermans Nv",
    "wof:placetype":"venue"
},
  "geometry": {"coordinates":[5.352493763,50.9066810608],"type":"Point"}
}