{
  "type": "Feature",
  "properties": {
    "iso:country":"BE",
    "sg:address":"Lutlommel 70",
    "sg:city":"Lommel",
    "sg:classifiers":[
        {
            "category":"Building & Trades",
            "subcategory":"Construction",
            "type":"Services"
        }
    ],
    "sg:phone":"+32 11 54 43 05",
    "sg:postcode":"3920",
    "sg:province":"Limburg",
    "sg:tags":[
        "installation",
        "-",
        "central",
        "heating"
    ],
    "wof:name":"Maes J",
    "wof:placetype":"venue"
},
  "geometry": {"coordinates":[5.3373298645,51.2311553955],"type":"Point"}
}