{
  "type": "Feature",
  "properties": {
    "iso:country":"BE",
    "sg:address":"Rue Reine Astrid 61",
    "sg:city":"Tubize",
    "sg:classifiers":[
        {
            "category":"Arena",
            "subcategory":"Sports Club",
            "type":"Entertainment"
        }
    ],
    "sg:phone":"+32 2 390 00 24",
    "sg:postcode":"1480",
    "sg:province":"Brabant Wallon",
    "wof:name":"Tennis Club Tubize Asbl",
    "wof:placetype":"venue"
},
  "geometry": {"coordinates":[4.2017760277,50.6858634949],"type":"Point"}
}