{
  "type": "Feature",
  "properties": {
    "iso:country":"BE",
    "sg:address":"Doelveldstraat 53",
    "sg:city":"Edegem",
    "sg:orig_category":"Informaticaconsulenten",
    "sg:phone":"+32 3 457 88 78",
    "sg:postcode":"2650",
    "sg:province":"Antwerpen",
    "wof:name":"Kluft",
    "wof:placetype":"venue"
},
  "geometry": {"coordinates":[4.4452638626,51.1574363708],"type":"Point"}
}