{
  "type": "Feature",
  "properties": {
    "iso:country":"BE",
    "sg:address":"Rue Bois Mayette 17",
    "sg:city":"Li\u00e8ge 1",
    "sg:classifiers":[
        {
            "category":"Professional",
            "type":"Services"
        }
    ],
    "sg:phone":"+32 4 224 33 35",
    "sg:postcode":"4000",
    "sg:province":"Li\u00e8ge",
    "sg:tags":[
        "entertainer"
    ],
    "wof:name":"Joumadi Ii Theatre",
    "wof:placetype":"venue"
},
  "geometry": {"coordinates":[5.54545784,50.6334533691],"type":"Point"}
}