{
  "type": "Feature",
  "properties": {
    "addr:full":"Rue Haute 340 Bruxelles Bruxelles-Capitale 1000",
    "addr:housenumber":"340",
    "addr:postcode":"1000",
    "addr:street":"Rue Haute",
    "iso:country":"BE",
    "sg:address":"Rue Haute 340",
    "sg:city":"Bruxelles",
    "sg:classifiers":[
        {
            "category":"Utilities",
            "subcategory":"Mobile Phone",
            "type":"Services"
        }
    ],
    "sg:phone":"+32 2 539 22 98",
    "sg:postcode":"1000",
    "sg:province":"Bruxelles-Capitale",
    "sg:tags":[
        "access",
        "gsm",
        "-",
        "apparatus"
    ],
    "wof:name":"Media Plus",
    "wof:placetype":"venue"
},
  "geometry": {"coordinates":[4.3453831673,50.8337936401],"type":"Point"}
}