{
  "type": "Feature",
  "properties": {
    "addr:full":"Rue L\u00e9on Debelle 53 Manage (bois-d'haine) Hainaut 7170",
    "addr:housenumber":"53",
    "addr:postcode":"7170",
    "addr:street":"Rue Le\u0301On Debelle;Hainaut",
    "iso:country":"BE",
    "sg:address":"Rue L\u00e9on Debelle 53",
    "sg:city":"Manage (bois-d'haine)",
    "sg:classifiers":[
        {
            "category":"Professional",
            "subcategory":"Lawyer & Legal Services",
            "type":"Services"
        }
    ],
    "sg:phone":"+32 64 55 55 92",
    "sg:postcode":"7170",
    "sg:province":"Hainaut",
    "wof:name":"Baudour Nathalie",
    "wof:placetype":"venue"
},
  "geometry": {"coordinates":[4.210916996,50.4937095642],"type":"Point"}
}