{
  "type": "Feature",
  "properties": {
    "addr:full":"Chauss\u00c9e De March\u00c9 262 Namur Namur 5100",
    "addr:housenumber":"262",
    "addr:postcode":"5100",
    "addr:street":"Chausse\u0301E De Marche\u0301",
    "iso:country":"BE",
    "sg:address":"Chauss\u00c9e De March\u00c9 262",
    "sg:city":"Namur",
    "sg:orig_category":"Opticiens",
    "sg:phone":"+32 81 30 19 38",
    "sg:postcode":"5100",
    "sg:province":"Namur",
    "wof:name":"Optique Cr\u00c9ations",
    "wof:placetype":"venue"
},
  "geometry": {"coordinates":[4.8713750839,50.4566345215],"type":"Point"}
}