{
  "type": "Feature",
  "properties": {
    "addr:full":"Chauss\u00c9e Paul Houtart 60 La Louviere Hainaut 7110",
    "addr:housenumber":"60",
    "addr:postcode":"7110",
    "addr:street":"Chausse\u0301E Paul Houtart",
    "iso:country":"BE",
    "sg:address":"Chauss\u00c9e Paul Houtart 60",
    "sg:city":"La Louviere",
    "sg:orig_category":"Huisdieren and benodigdheden",
    "sg:phone":"+32 64 28 43 36",
    "sg:postcode":"7110",
    "sg:province":"Hainaut",
    "wof:name":"Aqua Love",
    "wof:placetype":"venue"
},
  "geometry": {"coordinates":[4.1664328575,50.4825210571],"type":"Point"}
}