{
  "type": "Feature",
  "properties": {
    "iso:country":"BE",
    "sg:address":"Falise 10",
    "sg:city":"Olne",
    "sg:orig_category":"Artiesten and kunstenaars",
    "sg:phone":"+32 87 26 77 39",
    "sg:postcode":"4877",
    "sg:province":"Li\u00e8ge",
    "wof:name":"Galerie Christie",
    "wof:placetype":"venue"
},
  "geometry": {"coordinates":[5.746942997,50.5918769836],"type":"Point"}
}