{
  "type": "Feature",
  "properties": {
    "addr:full":"Augustijnenlaan 30 Herentals Antwerpen 2200",
    "addr:housenumber":"30",
    "addr:postcode":"2200",
    "addr:street":"Augustijnenlaan",
    "iso:country":"BE",
    "sg:address":"Augustijnenlaan 30",
    "sg:city":"Herentals",
    "sg:classifiers":[
        {
            "category":"Government",
            "subcategory":"Police Station",
            "type":"Public Place"
        }
    ],
    "sg:phone":"+32 14 28 51 00",
    "sg:postcode":"2200",
    "sg:province":"Antwerpen",
    "sg:tags":[
        "gendarmerie"
    ],
    "wof:name":"Federale Politie",
    "wof:placetype":"venue"
},
  "geometry": {"coordinates":[4.8428177834,51.1764602661],"type":"Point"}
}