{
  "type": "Feature",
  "properties": {
    "addr:full":"Kartuizersstraat 23 Brussel/bruxelles Bruxelles-Capitale 1000",
    "addr:housenumber":"23",
    "addr:postcode":"1000",
    "addr:street":"Kartuizersstraat;/",
    "iso:country":"BE",
    "sg:address":"Kartuizersstraat 23",
    "sg:city":"Brussel/bruxelles",
    "sg:orig_category":"Beheer van reclamemedia Diverse bouwinstallaties Verlichtingsapparaten and elektrische lampen Fab",
    "sg:phone":"+32 2 512 44 64",
    "sg:postcode":"1000",
    "sg:province":"Bruxelles-Capitale",
    "wof:name":"Claude Publicit\u00c9",
    "wof:placetype":"venue"
},
  "geometry": {"coordinates":[4.3462572098,50.8489303589],"type":"Point"}
}