{
  "type": "Feature",
  "properties": {
    "iso:country":"BE",
    "sg:address":"Engsbergseweg 97",
    "sg:city":"Tessenderlo",
    "sg:classifiers":[
        {
            "category":"Building & Trades",
            "subcategory":"Landscaping Services",
            "type":"Services"
        }
    ],
    "sg:phone":"+32 13 32 18 62",
    "sg:postcode":"3980",
    "sg:province":"Limburg",
    "sg:tags":[
        "gardening",
        "garden",
        "maintenance"
    ],
    "wof:name":"Joma Vof Klinkerwerken",
    "wof:placetype":"venue"
},
  "geometry": {"coordinates":[5.0376701355,51.028629303],"type":"Point"}
}