{
  "type": "Feature",
  "properties": {
    "addr:full":"Kievitstraat 2 Genk Limburg 3600",
    "addr:housenumber":"2",
    "addr:postcode":"3600",
    "addr:street":"Kievitstraat",
    "iso:country":"BE",
    "sg:address":"Kievitstraat 2",
    "sg:city":"Genk",
    "sg:orig_category":"Dierenartsen",
    "sg:phone":"+32 89 35 98 00",
    "sg:postcode":"3600",
    "sg:province":"Limburg",
    "wof:name":"Hellemans Magda",
    "wof:placetype":"venue"
},
  "geometry": {"coordinates":[5.4496860504,50.9641571045],"type":"Point"}
}