{
  "type": "Feature",
  "properties": {
    "iso:country":"BE",
    "sg:address":"Bellestraat 68a",
    "sg:city":"Heuvelland (westouter)",
    "sg:classifiers":[
        {
            "category":"Bakery",
            "type":"Food & Drink"
        }
    ],
    "sg:phone":"+32 57 44 89 44",
    "sg:postcode":"8954",
    "sg:province":"West-Vlaanderen",
    "sg:tags":[
        "confectioner",
        "baker"
    ],
    "wof:name":"Paris Croissant",
    "wof:placetype":"venue"
},
  "geometry": {"coordinates":[2.7476201057,50.7867088318],"type":"Point"}
}