{
  "type": "Feature",
  "properties": {
    "addr:full":"Tiensestraat 39 Leuven Vlaams-Brabant 3000",
    "addr:housenumber":"39",
    "addr:postcode":"3000",
    "addr:street":"Tiensestraat",
    "iso:country":"BE",
    "sg:address":"Tiensestraat 39",
    "sg:city":"Leuven",
    "sg:orig_category":"Eclairage et \u00e9quipements du foyer. Textiles. Rev\u00eatements pour sols and murs. Peinture",
    "sg:phone":"+32 16 22 37 46",
    "sg:postcode":"3000",
    "sg:province":"Vlaams-Brabant",
    "wof:name":"Paulus Buelens",
    "wof:placetype":"venue"
},
  "geometry": {"coordinates":[4.7037391663,50.8779602051],"type":"Point"}
}