{
  "type": "Feature",
  "properties": {
    "addr:full":"Zuidzandstraat 12 Brugge West-Vlaanderen 8000",
    "addr:housenumber":"12",
    "addr:postcode":"8000",
    "addr:street":"Zuidzandstraat",
    "iso:country":"BE",
    "sg:address":"Zuidzandstraat 12",
    "sg:city":"Brugge",
    "sg:classifiers":[
        {
            "category":"Real Estate",
            "subcategory":"Real Estate Services",
            "type":"Services"
        }
    ],
    "sg:phone":"+32 50 44 49 49",
    "sg:postcode":"8000",
    "sg:province":"West-Vlaanderen",
    "wof:name":"New Center Immo Brugge",
    "wof:placetype":"venue"
},
  "geometry": {"coordinates":[3.2203550339,51.2056350708],"type":"Point"}
}