{
  "type": "Feature",
  "properties": {
    "addr:full":"Boulevard Joseph Bracops 205b1 Anderlecht Bruxelles-Capitale 1070",
    "addr:housenumber":"205b1",
    "addr:postcode":"1070",
    "addr:street":"Boulevard Joseph Bracops",
    "iso:country":"BE",
    "sg:address":"Boulevard Joseph Bracops 205b1",
    "sg:city":"Anderlecht",
    "sg:orig_category":"Mat\u00e9riel de T\u00e9l\u00e9communication. Syst\u00e8mes de t\u00e9l\u00e9communications",
    "sg:phone":"+32 2 522 83 66",
    "sg:postcode":"1070",
    "sg:province":"Bruxelles-Capitale",
    "wof:name":"Le Las",
    "wof:placetype":"venue"
},
  "geometry": {"coordinates":[4.2821450233,50.8282012939],"type":"Point"}
}