{
  "type": "Feature",
  "properties": {
    "addr:full":"Rue Joseph Bodson 10 Limbourg Li\u00e8ge 4830",
    "addr:housenumber":"10",
    "addr:postcode":"4830",
    "addr:street":"Rue Joseph Bodson",
    "iso:country":"BE",
    "sg:address":"Rue Joseph Bodson 10",
    "sg:city":"Limbourg",
    "sg:classifiers":[
        {
            "category":"Health Services",
            "subcategory":"Dentist",
            "type":"Services"
        }
    ],
    "sg:phone":"+32 87 76 34 60",
    "sg:postcode":"4830",
    "sg:province":"Li\u00e8ge",
    "wof:name":"Junker Marc",
    "wof:placetype":"venue"
},
  "geometry": {"coordinates":[5.9431099892,50.6200408936],"type":"Point"}
}