{
  "type": "Feature",
  "properties": {
    "iso:country":"BE",
    "sg:address":"Poortakkerstr 90",
    "sg:city":"Gent",
    "sg:classifiers":[
        {
            "category":"Professional",
            "subcategory":"Business Services",
            "type":"Services"
        }
    ],
    "sg:phone":"+32 9 243 84 50",
    "sg:postcode":"9051",
    "sg:province":"Oost-Vlaanderen",
    "sg:tags":[
        "travel",
        "fair"
    ],
    "wof:name":"Textirama",
    "wof:placetype":"venue"
},
  "geometry": {"coordinates":[3.6683819294,51.020690918],"type":"Point"}
}