{
  "type": "Feature",
  "properties": {
    "addr:full":"Chemin Des Forsythias 22a Rixensart Brabant Wallon 1330",
    "addr:housenumber":"22a",
    "addr:postcode":"1330",
    "addr:street":"Chemin Des Forsythias;Wallon",
    "iso:country":"BE",
    "sg:address":"Chemin Des Forsythias 22a",
    "sg:city":"Rixensart",
    "sg:classifiers":[
        {
            "category":"Health Services",
            "subcategory":"Health Practitioner",
            "type":"Services"
        }
    ],
    "sg:phone":"+32 2 653 21 27",
    "sg:postcode":"1330",
    "sg:province":"Brabant Wallon",
    "sg:tags":[
        "physiotherapist"
    ],
    "wof:name":"Andre C",
    "wof:placetype":"venue"
},
  "geometry": {"coordinates":[4.5334248543,50.7156486511],"type":"Point"}
}