{
  "type": "Feature",
  "properties": {
    "addr:full":"Chauss\u00c9e De Gilly 102 Charleroi Hainaut 6040",
    "addr:housenumber":"102",
    "addr:postcode":"6040",
    "addr:street":"Chausse\u0301E De Gilly;Hainaut",
    "iso:country":"BE",
    "sg:address":"Chauss\u00c9e De Gilly 102",
    "sg:city":"Charleroi",
    "sg:orig_category":"Enseignement maternel and primaire",
    "sg:phone":"+32 71 35 83 60",
    "sg:postcode":"6040",
    "sg:province":"Hainaut",
    "wof:name":"Ecole Matern. Communale",
    "wof:placetype":"venue"
},
  "geometry": {"coordinates":[4.4482450485,50.4414978027],"type":"Point"}
}