{
  "type": "Feature",
  "properties": {
    "addr:full":"Brusselsesteenweg 559-571 Gent (gentbrugge) Oost-Vlaanderen 9050",
    "addr:housenumber":"559-571",
    "addr:postcode":"9050",
    "addr:street":"Brusselsesteenweg",
    "iso:country":"BE",
    "sg:address":"Brusselsesteenweg 559-571",
    "sg:city":"Gent (gentbrugge)",
    "sg:classifiers":[
        {
            "category":"Shopping",
            "subcategory":"Shoes",
            "type":"Retail Goods"
        }
    ],
    "sg:phone":"+32 9 230 02 11",
    "sg:postcode":"9050",
    "sg:province":"Oost-Vlaanderen",
    "sg:tags":[
        "slipper",
        "-"
    ],
    "wof:name":"Dekens Schoenboetiek Nv",
    "wof:placetype":"venue"
},
  "geometry": {"coordinates":[3.7598669529,51.0324287415],"type":"Point"}
}