{
  "type": "Feature",
  "properties": {
    "iso:country":"BE",
    "sg:address":"Rue Bout-d'en-haut 4",
    "sg:city":"Couvin",
    "sg:orig_category":"Maisons de vacances",
    "sg:phone":"+32 60 34 48 75",
    "sg:postcode":"5660",
    "sg:province":"Namur",
    "wof:name":"F. Van Elsen",
    "wof:placetype":"venue"
},
  "geometry": {"coordinates":[4.4404439926,50.0589332581],"type":"Point"}
}