{
  "type": "Feature",
  "properties": {
    "addr:full":"Rue De Gyppe 55 Sprimont Li\u00e8ge 4140",
    "addr:housenumber":"55",
    "addr:postcode":"4140",
    "addr:street":"Rue De Gyppe",
    "iso:country":"BE",
    "sg:address":"Rue De Gyppe 55",
    "sg:city":"Sprimont",
    "sg:orig_category":"Loodgieterij, verwarming and sanitaire installaties",
    "sg:phone":"+32 4 382 30 68",
    "sg:postcode":"4140",
    "sg:province":"Li\u00e8ge",
    "wof:name":"Edmond Fequenne",
    "wof:placetype":"venue"
},
  "geometry": {"coordinates":[5.6597499847,50.5072059631],"type":"Point"}
}