{
  "type": "Feature",
  "properties": {
    "iso:country":"BE",
    "sg:address":"Rue De La Gare 6",
    "sg:city":"Jurbise",
    "sg:orig_category":"Postkantoren Verzekeringsmakelaars and experts",
    "sg:phone":"+32 65 22 99 15",
    "sg:postcode":"7050",
    "sg:province":"Hainaut",
    "wof:name":"La Poste",
    "wof:placetype":"venue"
},
  "geometry": {"coordinates":[3.9114480019,50.5304489136],"type":"Point"}
}