{
  "type": "Feature",
  "properties": {
    "addr:full":"Wiedauwkaai 49 Gent Oost-Vlaanderen 9000",
    "addr:housenumber":"49",
    "addr:postcode":"9000",
    "addr:street":"Wiedauwkaai;Oost-Vlaanderen",
    "iso:country":"BE",
    "sg:address":"Wiedauwkaai 49",
    "sg:city":"Gent",
    "sg:classifiers":[
        {
            "category":"Professional",
            "subcategory":"Engineering",
            "type":"Services"
        }
    ],
    "sg:phone":"+32 9 257 13 97",
    "sg:postcode":"9000",
    "sg:province":"Oost-Vlaanderen",
    "sg:tags":[
        "environmental",
        "technique",
        "-"
    ],
    "wof:name":"Euras Bvba",
    "wof:placetype":"venue"
},
  "geometry": {"coordinates":[3.726172924,51.0737686157],"type":"Point"}
}