{
  "type": "Feature",
  "properties": {
    "addr:full":"Pierstraat 325 Rumst (reet) Antwerpen 2840",
    "addr:housenumber":"325",
    "addr:postcode":"2840",
    "addr:street":"Pierstraat",
    "iso:country":"BE",
    "sg:address":"Pierstraat 325",
    "sg:city":"Rumst (reet)",
    "sg:classifiers":[
        {
            "category":"Professional",
            "subcategory":"Management & Consulting",
            "type":"Services"
        }
    ],
    "sg:phone":"+32 3 844 19 72",
    "sg:postcode":"2840",
    "sg:province":"Antwerpen",
    "sg:tags":[
        "-",
        "processing",
        "data",
        "consultant"
    ],
    "wof:name":"It Consult",
    "wof:placetype":"venue"
},
  "geometry": {"coordinates":[4.3674240112,51.1099662781],"type":"Point"}
}