{
  "type": "Feature",
  "properties": {
    "iso:country":"BE",
    "sg:address":"Hogesteenweg 14",
    "sg:city":"Grimbergen",
    "sg:classifiers":[
        {
            "category":"Shopping",
            "subcategory":"Jewelry",
            "type":"Retail Goods"
        }
    ],
    "sg:phone":"+32 2 270 92 59",
    "sg:postcode":"1850",
    "sg:province":"Vlaams-Brabant",
    "sg:tags":[
        "jeweller",
        "-"
    ],
    "wof:name":"Van Laer",
    "wof:placetype":"venue"
},
  "geometry": {"coordinates":[4.3719367981,50.9330863953],"type":"Point"}
}