{
  "type": "Feature",
  "properties": {
    "addr:full":"Molenstraat 59 Liedekerke Vlaams-Brabant 1770",
    "addr:housenumber":"59",
    "addr:postcode":"1770",
    "addr:street":"Molenstraat;Vlaams-Brabant",
    "iso:country":"BE",
    "sg:address":"Molenstraat 59",
    "sg:city":"Liedekerke",
    "sg:classifiers":[
        {
            "category":"Personal",
            "subcategory":"Beauty Salon",
            "type":"Services"
        }
    ],
    "sg:phone":"+32 53 66 03 41",
    "sg:postcode":"1770",
    "sg:province":"Vlaams-Brabant",
    "sg:tags":[
        "lady",
        "-",
        "hairdressing"
    ],
    "wof:name":"Krista",
    "wof:placetype":"venue"
},
  "geometry": {"coordinates":[4.0871610641,50.8725891113],"type":"Point"}
}