{
  "type": "Feature",
  "properties": {
    "addr:full":"Elsum 90 Geel Antwerpen 2440",
    "addr:housenumber":"90",
    "addr:postcode":"2440",
    "addr:street":"Elsum",
    "iso:country":"BE",
    "sg:address":"Elsum 90",
    "sg:city":"Geel",
    "sg:classifiers":[
        {
            "category":"Bars & Pubs",
            "type":"Food & Drink"
        }
    ],
    "sg:phone":"+32 495 61 51 42",
    "sg:postcode":"2440",
    "sg:province":"Antwerpen",
    "wof:name":"De Max",
    "wof:placetype":"venue"
},
  "geometry": {"coordinates":[4.9781870842,51.163898468],"type":"Point"}
}