{
  "type": "Feature",
  "properties": {
    "addr:full":"Route De Nam\u00eache 8 Eghez\u00e9e (leuze) Namur 5310",
    "addr:housenumber":"8",
    "addr:postcode":"5310",
    "addr:street":"Route De Name\u0302Che",
    "iso:country":"BE",
    "sg:address":"Route De Nam\u00eache 8",
    "sg:city":"Eghez\u00e9e (leuze)",
    "sg:classifiers":[
        {
            "category":"Arena",
            "subcategory":"Sports Club",
            "type":"Entertainment"
        }
    ],
    "sg:phone":"+32 81 51 23 85",
    "sg:postcode":"5310",
    "sg:province":"Namur",
    "wof:name":"Sports & Culture Asbl",
    "wof:placetype":"venue"
},
  "geometry": {"coordinates":[4.9091119766,50.5601882935],"type":"Point"}
}