{
  "type": "Feature",
  "properties": {
    "addr:full":"Zoerselsteenweg 32 Zoersel Antwerpen 2980",
    "addr:housenumber":"32",
    "addr:postcode":"2980",
    "addr:street":"Zoerselsteenweg",
    "iso:country":"BE",
    "sg:address":"Zoerselsteenweg 32",
    "sg:city":"Zoersel",
    "sg:orig_category":"Beautyfarms, relaxatie and lichamelijk welzijn",
    "sg:phone":"+32 3 384 01 94",
    "sg:postcode":"2980",
    "sg:province":"Antwerpen",
    "wof:name":"Zonnecenter\u00b4t Zomerhuisje",
    "wof:placetype":"venue"
},
  "geometry": {"coordinates":[4.6561322212,51.2611961365],"type":"Point"}
}