{
  "type": "Feature",
  "properties": {
    "iso:country":"BE",
    "sg:address":"Sint-truidersteenweg 140",
    "sg:city":"Hasselt",
    "sg:classifiers":[
        {
            "category":"Retail",
            "subcategory":"Funeral Services",
            "type":"Services"
        }
    ],
    "sg:phone":"+32 11 28 35 88",
    "sg:postcode":"3500",
    "sg:province":"Limburg",
    "sg:tags":[
        "director"
    ],
    "wof:name":"Rouwcentrum Jacques Smeets",
    "wof:placetype":"venue"
},
  "geometry": {"coordinates":[5.3317089081,50.9224815369],"type":"Point"}
}