{
  "type": "Feature",
  "properties": {
    "iso:country":"BE",
    "sg:address":"Chauss\u00c9e De Huy 49",
    "sg:city":"Chaumont-gistoux",
    "sg:orig_category":"Installation de menuiserie en bois and plastique",
    "sg:phone":"+32 10 24 49 66",
    "sg:postcode":"1325",
    "sg:province":"Brabant Wallon",
    "wof:name":"J.f. Snaps",
    "wof:placetype":"venue"
},
  "geometry": {"coordinates":[4.6867961884,50.6901245117],"type":"Point"}
}