{
  "type": "Feature",
  "properties": {
    "iso:country":"BE",
    "sg:address":"Veldkantstraat 119",
    "sg:city":"Grimbergen",
    "sg:classifiers":[
        {
            "category":"Utilities",
            "subcategory":"Electric",
            "type":"Services"
        }
    ],
    "sg:phone":"+32 478 45 44 16",
    "sg:postcode":"1850",
    "sg:province":"Vlaams-Brabant",
    "sg:tags":[
        "energy",
        "renewable"
    ],
    "wof:name":"Hydro Wind Bvba",
    "wof:placetype":"venue"
},
  "geometry": {"coordinates":[4.3800292015,50.9346694946],"type":"Point"}
}