{
  "type": "Feature",
  "properties": {
    "addr:full":"Rue De Bravy 39 Herbeumont Luxembourg 6887",
    "addr:housenumber":"39",
    "addr:postcode":"6887",
    "addr:street":"Rue De Bravy",
    "iso:country":"BE",
    "sg:address":"Rue De Bravy 39",
    "sg:city":"Herbeumont",
    "sg:orig_category":"Rusthuizen and serviceflats",
    "sg:phone":"+32 61 41 14 35",
    "sg:postcode":"6887",
    "sg:province":"Luxembourg",
    "wof:name":"Home D.l. Bonne Esp\u00c9rance",
    "wof:placetype":"venue"
},
  "geometry": {"coordinates":[5.2351732254,49.7719154358],"type":"Point"}
}