{
  "type": "Feature",
  "properties": {
    "addr:full":"Winkelomseheide 122 Geel Antwerpen 2440",
    "addr:housenumber":"122",
    "addr:postcode":"2440",
    "addr:street":"Winkelomseheide",
    "iso:country":"BE",
    "sg:address":"Winkelomseheide 122",
    "sg:city":"Geel",
    "sg:classifiers":[
        {
            "category":"Fast Food",
            "type":"Food & Drink"
        }
    ],
    "sg:phone":"+32 14 58 93 18",
    "sg:postcode":"2440",
    "sg:province":"Antwerpen",
    "sg:tags":[
        "fried",
        "stand",
        "potato"
    ],
    "wof:name":"Dixy's",
    "wof:placetype":"venue"
},
  "geometry": {"coordinates":[5.0106301308,51.1373100281],"type":"Point"}
}