{
  "type": "Feature",
  "properties": {
    "addr:full":"Brusselsesteenweg 359 Mechelen Antwerpen 2800",
    "addr:housenumber":"359",
    "addr:postcode":"2800",
    "addr:street":"Brusselsesteenweg",
    "iso:country":"BE",
    "sg:address":"Brusselsesteenweg 359",
    "sg:city":"Mechelen",
    "sg:orig_category":"Herstellingen and onderhoud van auto's Voertuigen",
    "sg:phone":"+32 15 40 11 11",
    "sg:postcode":"2800",
    "sg:province":"Antwerpen",
    "wof:name":"Mercedes-benz Mechelen",
    "wof:placetype":"venue"
},
  "geometry": {"coordinates":[4.4740982056,51.0043334961],"type":"Point"}
}