{
  "type": "Feature",
  "properties": {
    "iso:country":"BE",
    "sg:address":"Pijnaards 6",
    "sg:city":"Buggenhout",
    "sg:orig_category":"Boekhouders",
    "sg:phone":"+32 52 33 64 68",
    "sg:postcode":"9255",
    "sg:province":"Oost-Vlaanderen",
    "wof:name":"Johan De Backer",
    "wof:placetype":"venue"
},
  "geometry": {"coordinates":[4.2068748474,51.010383606],"type":"Point"}
}