{
  "type": "Feature",
  "properties": {
    "iso:country":"BE",
    "sg:address":"Franklin Rooseveltlaan 14b2",
    "sg:city":"Waregem",
    "sg:orig_category":"Boomkwekerijen",
    "sg:phone":"+32 56 70 61 90",
    "sg:postcode":"8790",
    "sg:province":"West-Vlaanderen",
    "wof:name":"Boomkwekerij Christof",
    "wof:placetype":"venue"
},
  "geometry": {"coordinates":[3.4395239353,50.8822288513],"type":"Point"}
}