{
  "type": "Feature",
  "properties": {
    "iso:country":"BE",
    "sg:address":"Zandstraat 1",
    "sg:city":"Diepenbeek",
    "sg:classifiers":[
        {
            "category":"Retail",
            "subcategory":"Auto Repair",
            "type":"Services"
        }
    ],
    "sg:phone":"+32 11 32 38 63",
    "sg:postcode":"3590",
    "sg:province":"Limburg",
    "sg:tags":[
        "automobile-body"
    ],
    "wof:name":"Vandebroek K",
    "wof:placetype":"venue"
},
  "geometry": {"coordinates":[5.4582700729,50.9242897034],"type":"Point"}
}