{
  "type": "Feature",
  "properties": {
    "addr:full":"Deken De Bolaan 38 Poperinge West-Vlaanderen 8970",
    "addr:housenumber":"38",
    "addr:postcode":"8970",
    "addr:street":"Deken De Bolaan",
    "iso:country":"BE",
    "sg:address":"Deken De Bolaan 38",
    "sg:city":"Poperinge",
    "sg:classifiers":[
        {
            "category":"Professional",
            "subcategory":"Management & Consulting",
            "type":"Services"
        }
    ],
    "sg:phone":"+32 57 33 60 97",
    "sg:postcode":"8970",
    "sg:province":"West-Vlaanderen",
    "sg:tags":[
        "consultant",
        "agency",
        "advertising"
    ],
    "wof:name":"Artoroom",
    "wof:placetype":"venue"
},
  "geometry": {"coordinates":[2.7297151089,50.8501625061],"type":"Point"}
}