{
  "type": "Feature",
  "properties": {
    "addr:full":"Rue De L'orient 151 Bruxelles (etterbeek) Bruxelles-Capitale 1040",
    "addr:housenumber":"151",
    "addr:postcode":"1040",
    "addr:street":"Rue De L'Orient",
    "iso:country":"BE",
    "sg:address":"Rue De L'orient 151",
    "sg:city":"Bruxelles (etterbeek)",
    "sg:classifiers":[
        {
            "category":"Professional",
            "subcategory":"Testing Lab",
            "type":"Services"
        }
    ],
    "sg:phone":"+32 2 648 68 66",
    "sg:postcode":"1040",
    "sg:province":"Bruxelles-Capitale",
    "sg:tags":[
        "chemist"
    ],
    "wof:name":"Pharmacie De L'orient",
    "wof:placetype":"venue"
},
  "geometry": {"coordinates":[4.3850069046,50.8320045471],"type":"Point"}
}