{
  "type": "Feature",
  "properties": {
    "iso:country":"BE",
    "sg:address":"Rue Emile Tumelaire 71",
    "sg:city":"Charleroi",
    "sg:orig_category":"Advocaten and juridische adviseurs",
    "sg:phone":"+32 71 32 56 37",
    "sg:postcode":"6000",
    "sg:province":"Hainaut",
    "wof:name":"Aline Jassogne",
    "wof:placetype":"venue"
},
  "geometry": {"coordinates":[4.450442791,50.4095878601],"type":"Point"}
}