{
  "type": "Feature",
  "properties": {
    "addr:full":"Noordstraat 130-138 Roeselare West-Vlaanderen 8800",
    "addr:housenumber":"130-138",
    "addr:postcode":"8800",
    "addr:street":"Noordstraat",
    "iso:country":"BE",
    "sg:address":"Noordstraat 130-138",
    "sg:city":"Roeselare",
    "sg:orig_category":"Speciaalzaken Telecommunicatieapparaten Telecommunicatiesystemen",
    "sg:phone":"+32 51 20 31 41",
    "sg:postcode":"8800",
    "sg:province":"West-Vlaanderen",
    "wof:name":"Teleshop",
    "wof:placetype":"venue"
},
  "geometry": {"coordinates":[3.1213700771,50.9488220215],"type":"Point"}
}