{
  "type": "Feature",
  "properties": {
    "iso:country":"BE",
    "sg:address":"Otto Veniusstraat 5",
    "sg:city":"Antwerpen",
    "sg:classifiers":[
        {
            "category":"Tea Room",
            "subcategory":"None",
            "type":"Food & Drink"
        }
    ],
    "sg:phone":"+32 3 232 04 26",
    "sg:postcode":"2000",
    "sg:province":"Antwerpen",
    "wof:name":"Pascalino Bvba",
    "wof:placetype":"venue"
},
  "geometry": {"coordinates":[4.4128952026,51.2178230286],"type":"Point"}
}