{
  "type": "Feature",
  "properties": {
    "iso:country":"BE",
    "sg:address":"Rue Saint-laurent 12",
    "sg:city":"Marche-en-famenne",
    "sg:orig_category":"Biens d'occasion",
    "sg:phone":"+32 84 31 61 22",
    "sg:postcode":"6900",
    "sg:province":"Luxembourg",
    "wof:name":"Il Etait Deux Fois",
    "wof:placetype":"venue"
},
  "geometry": {"coordinates":[5.3445692062,50.2274513245],"type":"Point"}
}