{
  "type": "Feature",
  "properties": {
    "addr:full":"Rue D'houdain 9 Mons Hainaut 7000",
    "addr:housenumber":"9",
    "addr:postcode":"7000",
    "addr:street":"Rue D'Houdain;Hainaut",
    "iso:country":"BE",
    "sg:address":"Rue D'houdain 9",
    "sg:city":"Mons",
    "sg:orig_category":"Enseignement sup\u00e9rieur",
    "sg:phone":"+32 65 37 40 30",
    "sg:postcode":"7000",
    "sg:province":"Hainaut",
    "wof:name":"Facult\u00c9 Polytechnique De Mons",
    "wof:placetype":"venue"
},
  "geometry": {"coordinates":[3.9516580105,50.4533348083],"type":"Point"}
}