{
  "type": "Feature",
  "properties": {
    "addr:full":"Rue Sous-les-roches 16 Huy Li\u00e8ge 4500",
    "addr:housenumber":"16",
    "addr:postcode":"4500",
    "addr:street":"Rue Sous-Les-Roches",
    "iso:country":"BE",
    "sg:address":"Rue Sous-les-roches 16",
    "sg:city":"Huy",
    "sg:orig_category":"Installation \u00e9lectrique r\u00e9sidentielle. Meubles Fab. Construction de maisons",
    "sg:phone":"+32 85 21 62 33",
    "sg:postcode":"4500",
    "sg:province":"Li\u00e8ge",
    "wof:name":"Hoff",
    "wof:placetype":"venue"
},
  "geometry": {"coordinates":[5.2285242081,50.534122467],"type":"Point"}
}