{
  "type": "Feature",
  "properties": {
    "iso:country":"BE",
    "sg:address":"Bellmerin 15",
    "sg:city":"Eupen",
    "sg:orig_category":"Bloemen and planten",
    "sg:phone":"+32 87 74 25 25",
    "sg:postcode":"4700",
    "sg:province":"Li\u00e8ge",
    "wof:name":"Hamacher Bloemen",
    "wof:placetype":"venue"
},
  "geometry": {"coordinates":[6.0456299782,50.6204528809],"type":"Point"}
}