{
  "type": "Feature",
  "properties": {
    "addr:full":"Rue Des Petites Sources 16 Marche-en-famenne Luxembourg 6900",
    "addr:housenumber":"16",
    "addr:postcode":"6900",
    "addr:street":"Rue Des Petites Sources",
    "iso:country":"BE",
    "sg:address":"Rue Des Petites Sources 16",
    "sg:city":"Marche-en-famenne",
    "sg:orig_category":"Installation de menuiserie en bois and plastique",
    "sg:phone":"+32 84 31 47 25",
    "sg:postcode":"6900",
    "sg:province":"Luxembourg",
    "wof:name":"Guy Henrotin",
    "wof:placetype":"venue"
},
  "geometry": {"coordinates":[5.3422708511,50.2054176331],"type":"Point"}
}