{
  "type": "Feature",
  "properties": {
    "addr:full":"Kursaal-oosthelling 10 Oostende West-Vlaanderen 8400",
    "addr:housenumber":"10",
    "addr:postcode":"8400",
    "addr:street":"Kursaal-Oosthelling",
    "iso:country":"BE",
    "sg:address":"Kursaal-oosthelling 10",
    "sg:city":"Oostende",
    "sg:orig_category":"Antiek",
    "sg:phone":"+32 59 70 56 47",
    "sg:postcode":"8400",
    "sg:province":"West-Vlaanderen",
    "wof:name":"Huis Rohain",
    "wof:placetype":"venue"
},
  "geometry": {"coordinates":[2.9124801159,51.2325172424],"type":"Point"}
}