{
  "type": "Feature",
  "properties": {
    "addr:full":"Burgstraat 7 Geraardsbergen (overboelare) Oost-Vlaanderen 9500",
    "addr:housenumber":"7",
    "addr:postcode":"9500",
    "addr:street":"Burgstraat",
    "iso:country":"BE",
    "sg:address":"Burgstraat 7",
    "sg:city":"Geraardsbergen (overboelare)",
    "sg:classifiers":[
        {
            "category":"Shopping",
            "subcategory":"Gifts & Souvenirs",
            "type":"Retail Goods"
        }
    ],
    "sg:phone":"+32 54 41 28 61",
    "sg:postcode":"9500",
    "sg:province":"Oost-Vlaanderen",
    "sg:tags":[
        "-"
    ],
    "wof:name":"Flamant G",
    "wof:placetype":"venue"
},
  "geometry": {"coordinates":[3.8629510403,50.7625236511],"type":"Point"}
}