{
  "type": "Feature",
  "properties": {
    "addr:full":"Burgemeester Lemmensstraat 14-16 Hamme (moerzeke) Oost-Vlaanderen 9220",
    "addr:housenumber":"14-16",
    "addr:postcode":"9220",
    "addr:street":"Burgemeester Lemmensstraat",
    "iso:country":"BE",
    "sg:address":"Burgemeester Lemmensstraat 14-16",
    "sg:city":"Hamme (moerzeke)",
    "sg:classifiers":[
        {
            "category":"Autos & Motor Vehicles",
            "subcategory":"Motorcycle Sales",
            "type":"Retail Goods"
        }
    ],
    "sg:phone":"+32 52 47 77 44",
    "sg:postcode":"9220",
    "sg:province":"Oost-Vlaanderen",
    "sg:tags":[
        "motorbike"
    ],
    "wof:name":"D'holda Cv",
    "wof:placetype":"venue"
},
  "geometry": {"coordinates":[4.1542291641,51.0641517639],"type":"Point"}
}