{
  "type": "Feature",
  "properties": {
    "addr:full":"Venelle Des Ch\u00e2taigniers 6 Wavre Brabant Wallon 1300",
    "addr:housenumber":"6;1300",
    "addr:street":"Venelle Des Cha\u0302Taigniers",
    "iso:country":"BE",
    "sg:address":"Venelle Des Ch\u00e2taigniers 6",
    "sg:city":"Wavre",
    "sg:classifiers":[
        {
            "category":"Professional",
            "subcategory":"Management & Consulting",
            "type":"Services"
        }
    ],
    "sg:phone":"+32 10 24 55 45",
    "sg:postcode":"1300",
    "sg:province":"Brabant Wallon",
    "sg:tags":[
        "-",
        "processing",
        "data",
        "consultant"
    ],
    "wof:name":"Syst-md Sprl",
    "wof:placetype":"venue"
},
  "geometry": {"coordinates":[4.6192669868,50.6986541748],"type":"Point"}
}