{
  "type": "Feature",
  "properties": {
    "addr:full":"Stationsstraat 28 Zottegem Oost-Vlaanderen 9620",
    "addr:housenumber":"28",
    "addr:postcode":"9620",
    "addr:street":"Stationsstraat",
    "iso:country":"BE",
    "sg:address":"Stationsstraat 28",
    "sg:city":"Zottegem",
    "sg:classifiers":[
        {
            "category":"Utilities",
            "subcategory":"Mobile Phone",
            "type":"Services"
        }
    ],
    "sg:phone":"+32 9 360 51 12",
    "sg:postcode":"9620",
    "sg:province":"Oost-Vlaanderen",
    "sg:tags":[
        "access",
        "gsm",
        "-",
        "apparatus"
    ],
    "wof:name":"Mobistar Center Zottegem",
    "wof:placetype":"venue"
},
  "geometry": {"coordinates":[3.8128180504,50.8692817688],"type":"Point"}
}