{
  "type": "Feature",
  "properties": {
    "addr:full":"Rue Belliard 85 Etterbeek Bruxelles-Capitale 1040",
    "addr:housenumber":"85",
    "addr:postcode":"1040",
    "addr:street":"Rue Belliard",
    "iso:country":"BE",
    "sg:address":"Rue Belliard 85",
    "sg:city":"Etterbeek",
    "sg:orig_category":"Telecommunicatieapparaten",
    "sg:phone":"+32 2 230 91 77",
    "sg:postcode":"1040",
    "sg:province":"Bruxelles-Capitale",
    "wof:name":"Etoile",
    "wof:placetype":"venue"
},
  "geometry": {"coordinates":[4.3803901672,50.8400001526],"type":"Point"}
}