{
  "type": "Feature",
  "properties": {
    "addr:full":"Rue Defacqz 89 Bruxelles (saint-gilles) Bruxelles-Capitale 1060",
    "addr:housenumber":"89",
    "addr:postcode":"1060",
    "addr:street":"Rue Defacqz",
    "iso:country":"BE",
    "sg:address":"Rue Defacqz 89",
    "sg:city":"Bruxelles (saint-gilles)",
    "sg:classifiers":[
        {
            "category":"Shopping",
            "subcategory":"Books",
            "type":"Retail Goods"
        }
    ],
    "sg:phone":"+32 2 538 55 92",
    "sg:postcode":"1060",
    "sg:province":"Bruxelles-Capitale",
    "sg:tags":[
        "bookseller"
    ],
    "wof:name":"Librairie Defacqz",
    "wof:placetype":"venue"
},
  "geometry": {"coordinates":[4.3568501472,50.8268356323],"type":"Point"}
}