{
  "type": "Feature",
  "properties": {
    "iso:country":"BE",
    "sg:address":"Buurtstraat 82",
    "sg:city":"Maldegem",
    "sg:orig_category":"Installation de menuiserie en bois and plastique",
    "sg:phone":"+32 50 71 42 41",
    "sg:postcode":"9990",
    "sg:province":"Oost-Vlaanderen",
    "wof:name":"Verstringe",
    "wof:placetype":"venue"
},
  "geometry": {"coordinates":[3.432986021,51.219127655],"type":"Point"}
}