{
  "type": "Feature",
  "properties": {
    "iso:country":"BE",
    "sg:address":"Montoyerstraat 17",
    "sg:city":"Brussel/bruxelles",
    "sg:orig_category":"Krantenuitgeverijen Tijdschriftenuitgeverijen",
    "sg:phone":"+32 2 540 90 90",
    "sg:postcode":"1000",
    "sg:province":"Bruxelles-Capitale",
    "wof:name":"Editions European Voice",
    "wof:placetype":"venue"
},
  "geometry": {"coordinates":[4.3687171936,50.8413162231],"type":"Point"}
}