{
  "type": "Feature",
  "properties": {
    "addr:full":"Bovigny 3 Gouvy Luxembourg 6671",
    "addr:housenumber":"3",
    "addr:postcode":"6671",
    "addr:street":"Bovigny",
    "iso:country":"BE",
    "sg:address":"Bovigny 3",
    "sg:city":"Gouvy",
    "sg:orig_category":"Enseignement maternel and primaire",
    "sg:phone":"+32 80 21 45 43",
    "sg:postcode":"6671",
    "sg:province":"Luxembourg",
    "wof:name":"Ecole Fond. Communale",
    "wof:placetype":"venue"
},
  "geometry": {"coordinates":[5.9206929207,50.2257118225],"type":"Point"}
}