{
  "type": "Feature",
  "properties": {
    "addr:full":"Rue Dernier Patard 61 Genappe Brabant Wallon 1470",
    "addr:housenumber":"61",
    "addr:postcode":"1470",
    "addr:street":"Rue Dernier Patard;Wallon",
    "iso:country":"BE",
    "sg:address":"Rue Dernier Patard 61",
    "sg:city":"Genappe",
    "sg:orig_category":"Eleveurs de bovins",
    "sg:phone":"+32 67 77 20 69",
    "sg:postcode":"1470",
    "sg:province":"Brabant Wallon",
    "wof:name":"Fernand Filee",
    "wof:placetype":"venue"
},
  "geometry": {"coordinates":[4.455201149,50.584274292],"type":"Point"}
}