{
  "type": "Feature",
  "properties": {
    "addr:full":"Chauss\u00c9e Du Roeulx Soignies Hainaut 7060",
    "addr:postcode":"7060",
    "addr:street":"Chausse\u0301E Du Roeulx;Hainaut",
    "iso:country":"BE",
    "sg:address":"Chauss\u00c9e Du Roeulx",
    "sg:city":"Soignies",
    "sg:orig_category":"Animaux domestiques and accessoires",
    "sg:phone":"+32 67 33 29 25",
    "sg:postcode":"7060",
    "sg:province":"Hainaut",
    "wof:name":"S.c. Alliance Ble",
    "wof:placetype":"venue"
},
  "geometry": {"coordinates":[4.0751318932,50.5635757446],"type":"Point"}
}