{
  "type": "Feature",
  "properties": {
    "iso:country":"BE",
    "sg:address":"C. Van Manderstraat 1",
    "sg:city":"Antwerpen",
    "sg:classifiers":[
        {
            "category":"Restaurant",
            "type":"Food & Drink"
        }
    ],
    "sg:phone":"+32 3 219 30 60",
    "sg:postcode":"2050",
    "sg:province":"Antwerpen",
    "wof:name":"'t Pleintje",
    "wof:placetype":"venue"
},
  "geometry": {"coordinates":[4.3768029213,51.2308769226],"type":"Point"}
}