{
  "type": "Feature",
  "properties": {
    "iso:country":"BE",
    "sg:address":"Avenue Brugmann 298",
    "sg:city":"Ukkel/uccle",
    "sg:classifiers":[
        {
            "category":"Personal",
            "subcategory":"Beauty Salon",
            "type":"Services"
        }
    ],
    "sg:phone":"+32 2 345 78 56",
    "sg:postcode":"1180",
    "sg:province":"Bruxelles-Capitale",
    "sg:tags":[
        "de",
        "coiffure"
    ],
    "wof:name":"Karine Hembise",
    "wof:placetype":"venue"
},
  "geometry": {"coordinates":[4.3466258049,50.8112258911],"type":"Point"}
}