{
  "type": "Feature",
  "properties": {
    "addr:full":"Boerenweg 30 Eupen Li\u00e8ge 4700",
    "addr:housenumber":"30",
    "addr:postcode":"4700",
    "addr:street":"Boerenweg",
    "iso:country":"BE",
    "sg:address":"Boerenweg 30",
    "sg:city":"Eupen",
    "sg:orig_category":"Quincailleries. Bois Gr",
    "sg:phone":"+32 87 59 68 40",
    "sg:postcode":"4700",
    "sg:province":"Li\u00e8ge",
    "wof:name":"R. Lejeune",
    "wof:placetype":"venue"
},
  "geometry": {"coordinates":[6.0241031647,50.6384353638],"type":"Point"}
}