{
  "type": "Feature",
  "properties": {
    "iso:country":"BE",
    "sg:address":"Willebringsestraat 76",
    "sg:city":"Boutersem",
    "sg:classifiers":[
        {
            "category":"Arena",
            "subcategory":"Sports Club",
            "type":"Entertainment"
        }
    ],
    "sg:phone":"+32 16 73 59 71",
    "sg:postcode":"3370",
    "sg:province":"Vlaams-Brabant",
    "sg:tags":[
        "de"
    ],
    "wof:name":"Vlieg. Wiel Willebringen",
    "wof:placetype":"venue"
},
  "geometry": {"coordinates":[4.8441371918,50.812171936],"type":"Point"}
}