{
  "type": "Feature",
  "properties": {
    "addr:full":"Rue De Genly 103 Frameries Hainaut 7080",
    "addr:housenumber":"103",
    "addr:postcode":"7080",
    "addr:street":"Rue De Genly",
    "iso:country":"BE",
    "sg:address":"Rue De Genly 103",
    "sg:city":"Frameries",
    "sg:orig_category":"Goederenvervoer over de weg",
    "sg:phone":"+32 65 67 36 45",
    "sg:postcode":"7080",
    "sg:province":"Hainaut",
    "wof:name":"Compagnie Des Transports Du Borinage",
    "wof:placetype":"venue"
},
  "geometry": {"coordinates":[3.90417099,50.4059333801],"type":"Point"}
}