{
  "type": "Feature",
  "properties": {
    "addr:full":"Av. Du Prince H\u00c9ritier 26 Sint-lambrechts-woluwe/woluwe-saint-lambert Bruxelles-Capitale 1200",
    "addr:housenumber":"26",
    "addr:postcode":"1200",
    "addr:street":"Av. Du Prince He\u0301Ritier",
    "iso:country":"BE",
    "sg:address":"Av. Du Prince H\u00c9ritier 26",
    "sg:city":"Sint-lambrechts-woluwe/woluwe-saint-lambert",
    "sg:orig_category":"M\u00e9decins and sp\u00e9cialistes",
    "sg:phone":"+32 2 762 69 53",
    "sg:postcode":"1200",
    "sg:province":"Bruxelles-Capitale",
    "wof:name":"R. Majeres",
    "wof:placetype":"venue"
},
  "geometry": {"coordinates":[4.4117689133,50.8411521912],"type":"Point"}
}