{
  "type": "Feature",
  "properties": {
    "iso:country":"BE",
    "sg:address":"Rue Verte 10",
    "sg:city":"Mons",
    "sg:orig_category":"M\u00e9decins and sp\u00e9cialistes",
    "sg:phone":"+32 65 84 19 29",
    "sg:postcode":"7000",
    "sg:province":"Hainaut",
    "wof:name":"Charles Voisot",
    "wof:placetype":"venue"
},
  "geometry": {"coordinates":[3.9549400806,50.4559631348],"type":"Point"}
}