{
  "type": "Feature",
  "properties": {
    "iso:country":"BE",
    "sg:address":"Rue De L'h\u00f4pital Notre-dame 13",
    "sg:city":"Tournai",
    "sg:classifiers":[
        {
            "category":"Education",
            "subcategory":"School",
            "type":"Public Place"
        }
    ],
    "sg:phone":"+32 69 21 31 59",
    "sg:postcode":"7500",
    "sg:province":"Hainaut",
    "sg:tags":[
        "secondary"
    ],
    "wof:name":"Academie Des Beaux-arts De La Ville De Tournai",
    "wof:placetype":"venue"
},
  "geometry": {"coordinates":[3.3902440071,50.6076393127],"type":"Point"}
}