{
  "type": "Feature",
  "properties": {
    "iso:country":"BE",
    "sg:address":"Meeuwerbaan 4",
    "sg:city":"Peer",
    "sg:classifiers":[
        {
            "category":"Retail",
            "subcategory":"Auto Repair",
            "type":"Services"
        }
    ],
    "sg:phone":"+32 11 79 11 56",
    "sg:postcode":"3990",
    "sg:province":"Limburg",
    "sg:tags":[
        "garage"
    ],
    "wof:name":"Kelchtermans Nv",
    "wof:placetype":"venue"
},
  "geometry": {"coordinates":[5.4468941689,51.0783729553],"type":"Point"}
}