{
  "type": "Feature",
  "properties": {
    "iso:country":"BE",
    "sg:address":"Kerkstraat 23",
    "sg:city":"Melle",
    "sg:orig_category":"Jeux de hasard. Tabac. Fournitures de bureau",
    "sg:phone":"+32 9 252 44 70",
    "sg:postcode":"9090",
    "sg:province":"Oost-Vlaanderen",
    "wof:name":"Elysee",
    "wof:placetype":"venue"
},
  "geometry": {"coordinates":[3.8011980057,51.004234314],"type":"Point"}
}