{
  "type": "Feature",
  "properties": {
    "addr:full":"Veeweidestr. 1b Lubbeek Vlaams-Brabant 3210",
    "addr:housenumber":"1b",
    "addr:postcode":"3210",
    "addr:street":"Veeweidestr.",
    "iso:country":"BE",
    "sg:address":"Veeweidestr. 1b",
    "sg:city":"Lubbeek",
    "sg:classifiers":[
        {
            "category":"Bakery",
            "type":"Food & Drink"
        }
    ],
    "sg:phone":"+32 16 25 32 00",
    "sg:postcode":"3210",
    "sg:province":"Vlaams-Brabant",
    "sg:tags":[
        "cake",
        "product",
        "related",
        "bread"
    ],
    "wof:name":"Algemene Aannemingen Verwarmingsinstallaties Cvba",
    "wof:placetype":"venue"
},
  "geometry": {"coordinates":[4.7519378662,50.8922424316],"type":"Point"}
}