{
  "type": "Feature",
  "properties": {
    "iso:country":"BE",
    "sg:address":"Rue Du Croissant 119",
    "sg:city":"Bruxelles (forest)",
    "sg:classifiers":[
        {
            "category":"Professional",
            "subcategory":"Advertising",
            "type":"Services"
        }
    ],
    "sg:phone":"+32 2 534 09 19",
    "sg:postcode":"1190",
    "sg:province":"Bruxelles-Capitale",
    "sg:tags":[
        "clothes"
    ],
    "wof:name":"Acmp-boost Up",
    "wof:placetype":"venue"
},
  "geometry": {"coordinates":[4.3328609467,50.8257255554],"type":"Point"}
}