{
  "type": "Feature",
  "properties": {
    "iso:country":"BE",
    "sg:address":"Rue Des Ruelles 15",
    "sg:city":"Assesse",
    "sg:orig_category":"Brood, gebak and snoepgoed",
    "sg:phone":"+32 83 65 53 48",
    "sg:postcode":"5333",
    "sg:province":"Namur",
    "wof:name":"Gabriel Kesch",
    "wof:placetype":"venue"
},
  "geometry": {"coordinates":[5.0242519379,50.3908119202],"type":"Point"}
}