{
  "type": "Feature",
  "properties": {
    "iso:country":"BE",
    "sg:address":"Comminnestraat 18",
    "sg:city":"Zwevegem",
    "sg:classifiers":[
        {
            "category":"Food & Beverages",
            "subcategory":"Fruits & Vegetables",
            "type":"Retail Goods"
        }
    ],
    "sg:phone":"+32 56 45 63 66",
    "sg:postcode":"8552",
    "sg:tags":[
        "l\u00e9gumes",
        "gr"
    ],
    "wof:name":"Marc Dolphens",
    "wof:placetype":"venue"
},
  "geometry": {"coordinates":[3.3791480064,50.7748832703],"type":"Point"}
}