{
  "type": "Feature",
  "properties": {
    "addr:full":"All\u00c9e Centrale 35 Gerpinnes Hainaut 6280",
    "addr:housenumber":"35",
    "addr:postcode":"6280",
    "addr:street":"Alle\u0301E Centrale;Hainaut",
    "iso:country":"BE",
    "sg:address":"All\u00c9e Centrale 35",
    "sg:city":"Gerpinnes",
    "sg:orig_category":"Drogisterijen",
    "sg:phone":"+32 71 21 62 20",
    "sg:postcode":"6280",
    "sg:province":"Hainaut",
    "wof:name":"Eliana Falconi",
    "wof:placetype":"venue"
},
  "geometry": {"coordinates":[4.47894907,50.3395614624],"type":"Point"}
}