{
  "type": "Feature",
  "properties": {
    "addr:full":"Dorpsstraat 38 Beveren Oost-Vlaanderen 9130",
    "addr:housenumber":"38",
    "addr:postcode":"9130",
    "addr:street":"Dorpsstraat",
    "iso:country":"BE",
    "sg:address":"Dorpsstraat 38",
    "sg:city":"Beveren",
    "sg:classifiers":[
        {
            "category":"Cafe",
            "type":"Food & Drink"
        }
    ],
    "sg:phone":"+32 3 773 29 68",
    "sg:postcode":"9130",
    "sg:province":"Oost-Vlaanderen",
    "sg:tags":[
        "caf\u00e9s"
    ],
    "wof:name":"De Beurs",
    "wof:placetype":"venue"
},
  "geometry": {"coordinates":[4.1745371819,51.2910690308],"type":"Point"}
}