{
  "type": "Feature",
  "properties": {
    "addr:full":"Zewegenstraat 105 Waregem West-Vlaanderen 8790",
    "addr:housenumber":"105",
    "addr:postcode":"8790",
    "addr:street":"Zewegenstraat",
    "iso:country":"BE",
    "sg:address":"Zewegenstraat 105",
    "sg:city":"Waregem",
    "sg:orig_category":"Architecten",
    "sg:phone":"+32 56 61 25 56",
    "sg:postcode":"8790",
    "sg:province":"West-Vlaanderen",
    "wof:name":"Vandenbroucke I",
    "wof:placetype":"venue"
},
  "geometry": {"coordinates":[3.4199490547,50.8875045776],"type":"Point"}
}