{
  "type": "Feature",
  "properties": {
    "iso:country":"BE",
    "sg:address":"Rue De L\u00b4exposition 5",
    "sg:city":"Grace-hollogne",
    "sg:classifiers":[
        {
            "category":"Shopping",
            "subcategory":"Computers & Home Electronics",
            "type":"Retail Goods"
        }
    ],
    "sg:phone":"+32 4 239 70 50",
    "sg:postcode":"4460",
    "sg:province":"Li\u00e8ge",
    "sg:tags":[
        "computerapparatuur",
        "microsoft"
    ],
    "wof:name":"Sherwood",
    "wof:placetype":"venue"
},
  "geometry": {"coordinates":[5.4971818924,50.6527366638],"type":"Point"}
}