{
  "type": "Feature",
  "properties": {
    "addr:full":"Chauss\u00e9e De Gand 79 Bruxelles (molenbeek-saint-jean) Bruxelles-Capitale 1080",
    "addr:housenumber":"79",
    "addr:postcode":"1080",
    "addr:street":"Chausse\u0301E De Gand",
    "iso:country":"BE",
    "sg:address":"Chauss\u00e9e De Gand 79",
    "sg:city":"Bruxelles (molenbeek-saint-jean)",
    "sg:classifiers":[
        {
            "category":"Shopping",
            "subcategory":"Baby Store",
            "type":"Retail Goods"
        }
    ],
    "sg:phone":"+32 2 411 58 72",
    "sg:postcode":"1080",
    "sg:province":"Bruxelles-Capitale",
    "sg:tags":[
        "-",
        "accessory"
    ],
    "wof:name":"Roi Des B\u00e9b\u00e9s Sprl",
    "wof:placetype":"venue"
},
  "geometry": {"coordinates":[4.337061882,50.8540802002],"type":"Point"}
}