{
  "type": "Feature",
  "properties": {
    "addr:full":"Avenue Du G\u00e9n\u00e9ral De Gaulle 103 Mons Hainaut 7000",
    "addr:housenumber":"103",
    "addr:postcode":"7000",
    "addr:street":"Avenue Du Ge\u0301Ne\u0301Ral De Gaulle;Hainaut",
    "iso:country":"BE",
    "sg:address":"Avenue Du G\u00e9n\u00e9ral De Gaulle 103",
    "sg:city":"Mons",
    "sg:classifiers":[
        {
            "category":"Communications",
            "type":"Services"
        }
    ],
    "sg:phone":"+32 65 84 70 66",
    "sg:postcode":"7000",
    "sg:province":"Hainaut",
    "sg:tags":[
        "translator"
    ],
    "wof:name":"Ad Hoc Traductions",
    "wof:placetype":"venue"
},
  "geometry": {"coordinates":[3.9466669559,50.4419975281],"type":"Point"}
}