{
  "type": "Feature",
  "properties": {
    "addr:full":"Schoolstraat 81 Bree Limburg 3960",
    "addr:housenumber":"81",
    "addr:postcode":"3960",
    "addr:street":"Schoolstraat",
    "iso:country":"BE",
    "sg:address":"Schoolstraat 81",
    "sg:city":"Bree",
    "sg:orig_category":"Royal Canin. Souvenirs and objets artisanaux. Fleurs and plantes. Articles de jardin. Animaux domest",
    "sg:phone":"+32 89 46 22 27",
    "sg:postcode":"3960",
    "sg:province":"Limburg",
    "wof:name":"Vanderhoydonk L. Aveve",
    "wof:placetype":"venue"
},
  "geometry": {"coordinates":[5.5896201134,51.1437988281],"type":"Point"}
}