{
  "type": "Feature",
  "properties": {
    "addr:full":"Rue De Neufchateau 2 Bastogne (grand) Luxembourg 6600",
    "addr:housenumber":"2",
    "addr:postcode":"6600",
    "addr:street":"Rue De Neufchateau",
    "iso:country":"BE",
    "sg:address":"Rue De Neufchateau 2",
    "sg:city":"Bastogne (grand)",
    "sg:orig_category":"Banken and kredietinstellingen",
    "sg:phone":"+32 61 21 22 76",
    "sg:postcode":"6600",
    "sg:province":"Luxembourg",
    "wof:name":"Fortis",
    "wof:placetype":"venue"
},
  "geometry": {"coordinates":[5.71519804,50.0001983643],"type":"Point"}
}