{
  "type": "Feature",
  "properties": {
    "iso:country":"BE",
    "sg:address":"Wilgstraat 43",
    "sg:city":"Ganshoren",
    "sg:orig_category":"Agences d'exp\u00e9dition",
    "sg:phone":"+32 2 425 52 66",
    "sg:postcode":"1083",
    "sg:province":"Bruxelles-Capitale",
    "wof:name":"Rosiers R",
    "wof:placetype":"venue"
},
  "geometry": {"coordinates":[4.3196640015,50.8781013489],"type":"Point"}
}