{
  "type": "Feature",
  "properties": {
    "addr:full":"Paalsesteenweg 340 Paal Limburg 3583",
    "addr:housenumber":"340",
    "addr:postcode":"3583",
    "addr:street":"Paalsesteenweg",
    "iso:country":"BE",
    "sg:address":"Paalsesteenweg 340",
    "sg:city":"Paal",
    "sg:orig_category":"Matrassen Fab Meubelzaken, woning- and keukeninrichting",
    "sg:phone":"+32 11 42 30 30",
    "sg:postcode":"3583",
    "sg:province":"Limburg",
    "wof:name":"Donalds Matrassencentrale",
    "wof:placetype":"venue"
},
  "geometry": {"coordinates":[5.1753969193,51.0401382446],"type":"Point"}
}