{
  "type": "Feature",
  "properties": {
    "addr:full":"Booglaan 7 Denderleeuw Oost-Vlaanderen 9473",
    "addr:housenumber":"7",
    "addr:postcode":"9473",
    "addr:street":"Booglaan",
    "iso:country":"BE",
    "sg:address":"Booglaan 7",
    "sg:city":"Denderleeuw",
    "sg:orig_category":"Animations diverses",
    "sg:phone":"+32 53 66 40 40",
    "sg:postcode":"9473",
    "sg:province":"Oost-Vlaanderen",
    "wof:name":"Hooghe Walter",
    "wof:placetype":"venue"
},
  "geometry": {"coordinates":[4.056101799,50.89610672],"type":"Point"}
}