{
  "type": "Feature",
  "properties": {
    "iso:country":"BE",
    "sg:address":"Deinzestraat 134",
    "sg:city":"Dentergem (oeselgem)",
    "sg:classifiers":[
        {
            "category":"Freight",
            "type":"Transportation"
        }
    ],
    "sg:phone":"+32 9 388 65 63",
    "sg:postcode":"8720",
    "sg:province":"West-Vlaanderen",
    "sg:tags":[
        "-",
        "transport"
    ],
    "wof:name":"De Baets Wino Bvba",
    "wof:placetype":"venue"
},
  "geometry": {"coordinates":[3.4469349384,50.9494476318],"type":"Point"}
}