{
  "type": "Feature",
  "properties": {
    "addr:full":"Grote Baan 21 Geetbets (rummen) Vlaams-Brabant 3454",
    "addr:housenumber":"21",
    "addr:postcode":"3454",
    "addr:street":"Grote Baan",
    "iso:country":"BE",
    "sg:address":"Grote Baan 21",
    "sg:city":"Geetbets (rummen)",
    "sg:classifiers":[
        {
            "category":"Professional",
            "subcategory":"Accounting & Tax Preparation",
            "type":"Services"
        }
    ],
    "sg:phone":"+32 11 58 33 04",
    "sg:postcode":"3454",
    "sg:province":"Vlaams-Brabant",
    "sg:tags":[
        "bookkeeper"
    ],
    "wof:name":"Corthouts Ph",
    "wof:placetype":"venue"
},
  "geometry": {"coordinates":[5.164935112,50.8869514465],"type":"Point"}
}