{
  "type": "Feature",
  "properties": {
    "iso:country":"BE",
    "sg:address":"Site G\u00c9othermique Idea",
    "sg:city":"Saint-ghislain",
    "sg:orig_category":"Tuinbenodigdheden",
    "sg:phone":"+32 65 79 36 55",
    "sg:postcode":"7330",
    "sg:province":"Hainaut",
    "wof:name":"Eurover Green Center",
    "wof:placetype":"venue"
},
  "geometry": {"coordinates":[3.8227250576,50.4473495483],"type":"Point"}
}