{
  "type": "Feature",
  "properties": {
    "addr:full":"All\u00c9e Ambiorix 12 Chaudfontaine Li\u00e8ge 4053",
    "addr:housenumber":"12",
    "addr:postcode":"4053",
    "addr:street":"Alle\u0301E Ambiorix",
    "iso:country":"BE",
    "sg:address":"All\u00c9e Ambiorix 12",
    "sg:city":"Chaudfontaine",
    "sg:orig_category":"Artiesten and kunstenaars",
    "sg:phone":"+32 4 367 36 08",
    "sg:postcode":"4053",
    "sg:province":"Li\u00e8ge",
    "wof:name":"Hubert Feguenne",
    "wof:placetype":"venue"
},
  "geometry": {"coordinates":[5.6058511734,50.5892333984],"type":"Point"}
}