{
  "type": "Feature",
  "properties": {
    "addr:full":"Hogestraat 22 Hooglede West-Vlaanderen 8830",
    "addr:housenumber":"22",
    "addr:postcode":"8830",
    "addr:street":"Hogestraat",
    "iso:country":"BE",
    "sg:address":"Hogestraat 22",
    "sg:city":"Hooglede",
    "sg:classifiers":[
        {
            "category":"Cafe",
            "type":"Food & Drink"
        }
    ],
    "sg:phone":"+32 51 20 21 09",
    "sg:postcode":"8830",
    "sg:province":"West-Vlaanderen",
    "sg:tags":[
        "caf\u00e9s"
    ],
    "wof:name":"Isabel Casier",
    "wof:placetype":"venue"
},
  "geometry": {"coordinates":[3.0802190304,50.9796028137],"type":"Point"}
}