{
  "type": "Feature",
  "properties": {
    "iso:country":"BE",
    "sg:address":"Jeugdstraat 5",
    "sg:city":"Diepenbeek",
    "sg:classifiers":[
        {
            "category":"Health Services",
            "subcategory":"Health Practitioner",
            "type":"Services"
        }
    ],
    "sg:phone":"+32 11 33 12 30",
    "sg:postcode":"3590",
    "sg:province":"Limburg",
    "sg:tags":[
        "physiotherapist"
    ],
    "wof:name":"Vanhees Bart",
    "wof:placetype":"venue"
},
  "geometry": {"coordinates":[5.4104089737,50.9116439819],"type":"Point"}
}