{
  "type": "Feature",
  "properties": {
    "iso:country":"BE",
    "sg:address":"Hoek 76",
    "sg:city":"Boom",
    "sg:orig_category":"Non-Classified Establishments",
    "sg:phone":"+32 3 844 45 33",
    "sg:postcode":"2850",
    "sg:province":"Antwerpen",
    "wof:name":"Orbit Light Selection Nv",
    "wof:placetype":"venue"
},
  "geometry": {"coordinates":[4.3774271011,51.0845031738],"type":"Point"}
}