{
  "type": "Feature",
  "properties": {
    "addr:full":"Postbus 84 Essen1 Antwerpen 2910",
    "addr:housenumber":"84 essen1",
    "addr:postcode":"2910",
    "addr:street":"Postbus",
    "iso:country":"BE",
    "sg:address":"Postbus 84",
    "sg:city":"Essen1",
    "sg:classifiers":[
        {
            "category":"Shopping",
            "subcategory":"Catalog Store",
            "type":"Retail Goods"
        }
    ],
    "sg:phone":"+32 3 667 66 06",
    "sg:postcode":"2910",
    "sg:province":"Antwerpen",
    "sg:tags":[
        "mail",
        "order",
        "house"
    ],
    "wof:name":"Large Popmerchandising Bvba",
    "wof:placetype":"venue"
},
  "geometry": {"coordinates":[4.4637198448,51.4488296509],"type":"Point"}
}