{
  "type": "Feature",
  "properties": {
    "addr:full":"Brandstraat 18 Heist-op-den-berg Antwerpen 2221",
    "addr:housenumber":"18",
    "addr:postcode":"2221",
    "addr:street":"Brandstraat",
    "iso:country":"BE",
    "sg:address":"Brandstraat 18",
    "sg:city":"Heist-op-den-berg",
    "sg:orig_category":"Epiceries",
    "sg:phone":"+32 15 22 26 12",
    "sg:postcode":"2221",
    "sg:province":"Antwerpen",
    "wof:name":"Heidi Heylen",
    "wof:placetype":"venue"
},
  "geometry": {"coordinates":[4.7739758492,51.0512428284],"type":"Point"}
}