{
  "type": "Feature",
  "properties": {
    "addr:full":"Avenue Jean Mermoz 22 Charleroi (gosselies) Hainaut 6041",
    "addr:housenumber":"22",
    "addr:postcode":"6041",
    "addr:street":"Avenue Jean Mermoz",
    "iso:country":"BE",
    "sg:address":"Avenue Jean Mermoz 22",
    "sg:city":"Charleroi (gosselies)",
    "sg:classifiers":[
        {
            "category":"Building & Trades",
            "subcategory":"Construction",
            "type":"Services"
        }
    ],
    "sg:phone":"+32 71 35 65 39",
    "sg:postcode":"6041",
    "sg:province":"Hainaut",
    "sg:tags":[
        "duct",
        "underground",
        "ducting"
    ],
    "wof:name":"Conduites & Entreprises Sa",
    "wof:placetype":"venue"
},
  "geometry": {"coordinates":[4.4716668129,50.4763908386],"type":"Point"}
}