{
  "type": "Feature",
  "properties": {
    "addr:full":"Rue D'armenti\u00e8res 336a Comines-warneton (bizet) Hainaut 7783",
    "addr:housenumber":"336a",
    "addr:postcode":"7783",
    "addr:street":"Rue D'Armentie \u0300Res;Bizet Hainaut",
    "iso:country":"BE",
    "sg:address":"Rue D'armenti\u00e8res 336a",
    "sg:city":"Comines-warneton (bizet)",
    "sg:classifiers":[
        {
            "category":"Bars & Pubs",
            "type":"Food & Drink"
        }
    ],
    "sg:phone":"+32 56 58 72 21",
    "sg:postcode":"7783",
    "sg:province":"Hainaut",
    "wof:name":"Ville De Gand",
    "wof:placetype":"venue"
},
  "geometry": {"coordinates":[2.8838949203,50.7066688538],"type":"Point"}
}