{
  "type": "Feature",
  "properties": {
    "addr:full":"Kwadestraat 77 Roeselare West-Vlaanderen 8800",
    "addr:housenumber":"77",
    "addr:postcode":"8800",
    "addr:street":"Kwadestraat",
    "iso:country":"BE",
    "sg:address":"Kwadestraat 77",
    "sg:city":"Roeselare",
    "sg:orig_category":"Sportclubs",
    "sg:phone":"+32 51 21 08 43",
    "sg:postcode":"8800",
    "sg:province":"West-Vlaanderen",
    "wof:name":"Roeselaars.zwemvereniging",
    "wof:placetype":"venue"
},
  "geometry": {"coordinates":[3.1650729179,50.9273300171],"type":"Point"}
}