{
  "type": "Feature",
  "properties": {
    "addr:full":"Stationsstraat 83 Gistel West-Vlaanderen 8470",
    "addr:housenumber":"83",
    "addr:postcode":"8470",
    "addr:street":"Stationsstraat",
    "iso:country":"BE",
    "sg:address":"Stationsstraat 83",
    "sg:city":"Gistel",
    "sg:orig_category":"Openbare veiligheid",
    "sg:phone":"+32 59 27 83 16",
    "sg:postcode":"8470",
    "sg:province":"West-Vlaanderen",
    "wof:name":"Federale Politie/police F\u00c9d\u00c9rale",
    "wof:placetype":"venue"
},
  "geometry": {"coordinates":[2.9628040791,51.1537208557],"type":"Point"}
}