{
  "type": "Feature",
  "properties": {
    "iso:country":"BE",
    "sg:address":"Chauss\u00c9e De Bruxelles 534",
    "sg:city":"Waterloo",
    "sg:classifiers":[
        {
            "category":"Food & Beverages",
            "subcategory":"Meat & Fish",
            "type":"Retail Goods"
        }
    ],
    "sg:phone":"+32 2 354 87 24",
    "sg:postcode":"1410",
    "sg:province":"Brabant Wallon",
    "sg:tags":[
        "vi",
        "zeevruchten"
    ],
    "wof:name":"Poissonnerie Joli-bois",
    "wof:placetype":"venue"
},
  "geometry": {"coordinates":[4.4019789696,50.7016563416],"type":"Point"}
}