{
  "type": "Feature",
  "properties": {
    "iso:country":"BE",
    "sg:address":"Krauwels Bosweg 45",
    "sg:city":"Maaseik",
    "sg:orig_category":"V\u00e9t\u00e9rinaires",
    "sg:phone":"+32 89 56 85 08",
    "sg:postcode":"3680",
    "sg:province":"Limburg",
    "wof:name":"P. Dierickx",
    "wof:placetype":"venue"
},
  "geometry": {"coordinates":[5.7718229294,51.0816841125],"type":"Point"}
}