{
  "type": "Feature",
  "properties": {
    "addr:full":"Rue G\u00e9n\u00e9ral Borlon 3 Erez\u00e9e Luxembourg 6997",
    "addr:housenumber":"3",
    "addr:postcode":"6997",
    "addr:street":"Rue Ge\u0301Ne\u0301Ral Borlon",
    "iso:country":"BE",
    "sg:address":"Rue G\u00e9n\u00e9ral Borlon 3",
    "sg:city":"Erez\u00e9e",
    "sg:classifiers":[
        {
            "category":"Food & Beverages",
            "subcategory":"Groceries & Convenience Stores",
            "type":"Retail Goods"
        }
    ],
    "sg:phone":"+32 86 47 70 61",
    "sg:postcode":"6997",
    "sg:province":"Luxembourg",
    "sg:tags":[
        "grocer"
    ],
    "wof:name":"Garnir-p\u00e9try",
    "wof:placetype":"venue"
},
  "geometry": {"coordinates":[5.5585899353,50.2920684814],"type":"Point"}
}