{
  "type": "Feature",
  "properties": {
    "addr:full":"Rue Du G\u00e9n\u00e9ral De Gaulle 136 Courcelles Hainaut 6180",
    "addr:housenumber":"136",
    "addr:postcode":"6180",
    "addr:street":"Rue Du Ge\u0301Ne\u0301Ral De Gaulle",
    "iso:country":"BE",
    "sg:address":"Rue Du G\u00e9n\u00e9ral De Gaulle 136",
    "sg:city":"Courcelles",
    "sg:classifiers":[
        {
            "category":"Retail",
            "subcategory":"Animal Services",
            "type":"Services"
        }
    ],
    "sg:phone":"+32 71 45 54 69",
    "sg:postcode":"6180",
    "sg:province":"Hainaut",
    "sg:tags":[
        "grooming",
        "-",
        "dog"
    ],
    "wof:name":"Studio Lady",
    "wof:placetype":"venue"
},
  "geometry": {"coordinates":[4.381082058,50.4558334351],"type":"Point"}
}