{
  "type": "Feature",
  "properties": {
    "iso:country":"BE",
    "sg:address":"Edingsesteenweg 237",
    "sg:city":"Asse",
    "sg:classifiers":[
        {
            "category":"Retail",
            "subcategory":"Veterinary Services",
            "type":"Services"
        }
    ],
    "sg:phone":"+32 2 453 00 61",
    "sg:postcode":"1730",
    "sg:province":"Vlaams-Brabant",
    "sg:tags":[
        "veterinarian"
    ],
    "wof:name":"Combes H",
    "wof:placetype":"venue"
},
  "geometry": {"coordinates":[4.1708540916,50.8910064697],"type":"Point"}
}