{
  "type": "Feature",
  "properties": {
    "addr:full":"Prof.o.rubbrechtstraat 25 Poperinge West-Vlaanderen 8972",
    "addr:housenumber":"25",
    "addr:postcode":"8972",
    "addr:street":"Prof.O.Rubbrechtstraat",
    "iso:country":"BE",
    "sg:address":"Prof.o.rubbrechtstraat 25",
    "sg:city":"Poperinge",
    "sg:classifiers":[
        {
            "category":"Cafe",
            "type":"Food & Drink"
        }
    ],
    "sg:phone":"+32 57 30 03 22",
    "sg:postcode":"8972",
    "sg:province":"West-Vlaanderen",
    "sg:tags":[
        "caf\u00e9s"
    ],
    "wof:name":"Patrick Gunst",
    "wof:placetype":"venue"
},
  "geometry": {"coordinates":[2.6248888969,50.9185676575],"type":"Point"}
}