{
  "type": "Feature",
  "properties": {
    "iso:country":"BE",
    "sg:address":"Rue De La Caserne 20",
    "sg:city":"Arlon",
    "sg:orig_category":"Pain, p\u00e2tisseries and confiseries",
    "sg:phone":"+32 63 22 76 81",
    "sg:postcode":"6700",
    "sg:province":"Luxembourg",
    "wof:name":"Paul Sibenaler",
    "wof:placetype":"venue"
},
  "geometry": {"coordinates":[5.8161458969,49.6858444214],"type":"Point"}
}