{
  "type": "Feature",
  "properties": {
    "addr:full":"Reigerslaan 8 Heusden-zolder Limburg 3550",
    "addr:housenumber":"8",
    "addr:postcode":"3550",
    "addr:street":"Reigerslaan",
    "iso:country":"BE",
    "sg:address":"Reigerslaan 8",
    "sg:city":"Heusden-zolder",
    "sg:classifiers":[
        {
            "category":"Personal",
            "subcategory":"Beauty Salon",
            "type":"Services"
        }
    ],
    "sg:phone":"+32 11 25 48 42",
    "sg:postcode":"3550",
    "sg:province":"Limburg",
    "sg:tags":[
        "de",
        "coiffure"
    ],
    "wof:name":"Coiffure k",
    "wof:placetype":"venue"
},
  "geometry": {"coordinates":[5.2652788162,50.9860954285],"type":"Point"}
}