{
  "type": "Feature",
  "properties": {
    "addr:full":"Weidestraat 156 Brugge West-Vlaanderen 8310",
    "addr:housenumber":"156",
    "addr:postcode":"8310",
    "addr:street":"Weidestraat",
    "iso:country":"BE",
    "sg:address":"Weidestraat 156",
    "sg:city":"Brugge",
    "sg:orig_category":"Enseignement secondaire g\u00e9n\u00e9ral",
    "sg:phone":"+32 50 35 57 00",
    "sg:postcode":"8310",
    "sg:province":"West-Vlaanderen",
    "wof:name":"Buso Haverlo",
    "wof:placetype":"venue"
},
  "geometry": {"coordinates":[3.2432079315,51.1932907104],"type":"Point"}
}