{
  "type": "Feature",
  "properties": {
    "addr:full":"Ninoofsesteenweg 347 Ronse/renaix Oost-Vlaanderen 9600",
    "addr:housenumber":"347",
    "addr:postcode":"9600",
    "addr:street":"Ninoofsesteenweg",
    "iso:country":"BE",
    "sg:address":"Ninoofsesteenweg 347",
    "sg:city":"Ronse/renaix",
    "sg:orig_category":"Pleisterwerk",
    "sg:phone":"+32 55 20 85 48",
    "sg:postcode":"9600",
    "sg:province":"Oost-Vlaanderen",
    "wof:name":"Mario De Paepe",
    "wof:placetype":"venue"
},
  "geometry": {"coordinates":[3.5992999077,50.7470397949],"type":"Point"}
}