{
  "type": "Feature",
  "properties": {
    "addr:full":"Essestraat 102 Lede Oost-Vlaanderen 9340",
    "addr:housenumber":"102",
    "addr:postcode":"9340",
    "addr:street":"Essestraat",
    "iso:country":"BE",
    "sg:address":"Essestraat 102",
    "sg:city":"Lede",
    "sg:orig_category":"Gespecialiseerde residenti\u00eble bouw Plaatsen van vloer- and muurbekleding Pleisterwerk Schilders",
    "sg:phone":"+32 53 80 57 30",
    "sg:postcode":"9340",
    "sg:province":"Oost-Vlaanderen",
    "wof:name":"Metaldur",
    "wof:placetype":"venue"
},
  "geometry": {"coordinates":[3.9331400394,50.9537086487],"type":"Point"}
}