{
  "type": "Feature",
  "properties": {
    "iso:country":"BE",
    "sg:address":"Kruideniersstraat 3",
    "sg:city":"Gent",
    "sg:classifiers":[
        {
            "category":"Professional",
            "subcategory":"Accounting & Tax Preparation",
            "type":"Services"
        }
    ],
    "sg:phone":"+32 9 233 51 64",
    "sg:postcode":"9000",
    "sg:province":"Oost-Vlaanderen",
    "sg:tags":[
        "bookkeeper"
    ],
    "wof:name":"Livac Bvba",
    "wof:placetype":"venue"
},
  "geometry": {"coordinates":[3.7310330868,51.0548439026],"type":"Point"}
}