{
  "type": "Feature",
  "properties": {
    "iso:country":"BE",
    "sg:address":"Rue De Marchienne 15",
    "sg:city":"Charleroi",
    "sg:classifiers":[
        {
            "category":"Fast Food",
            "type":"Food & Drink"
        }
    ],
    "sg:phone":"+32 71 32 02 65",
    "sg:postcode":"6000",
    "sg:province":"Hainaut",
    "sg:tags":[
        "meeneem",
        "restaurant"
    ],
    "wof:name":"Le Dragon D'or",
    "wof:placetype":"venue"
},
  "geometry": {"coordinates":[4.4399108887,50.4077682495],"type":"Point"}
}