{
  "type": "Feature",
  "properties": {
    "addr:full":"Rue De Pierrard 15 Virton (latour) Luxembourg 6761",
    "addr:housenumber":"15",
    "addr:postcode":"6761",
    "addr:street":"Rue De Pierrard;Latour",
    "iso:country":"BE",
    "sg:address":"Rue De Pierrard 15",
    "sg:city":"Virton (latour)",
    "sg:classifiers":[
        {
            "category":"Professional",
            "subcategory":"Lawyer & Legal Services",
            "type":"Services"
        }
    ],
    "sg:phone":"+32 63 57 68 21",
    "sg:postcode":"6761",
    "sg:province":"Luxembourg",
    "wof:name":"Nerenhausen S",
    "wof:placetype":"venue"
},
  "geometry": {"coordinates":[5.5484199524,49.5657577515],"type":"Point"}
}