{
  "type": "Feature",
  "properties": {
    "iso:country":"BE",
    "sg:address":"Rue Du Bois 2a",
    "sg:city":"Tournai (gaurain-ramecroix)",
    "sg:classifiers":[
        {
            "category":"Professional",
            "subcategory":"Art Services",
            "type":"Services"
        }
    ],
    "sg:phone":"+32 69 54 69 46",
    "sg:postcode":"7530",
    "sg:province":"Hainaut",
    "sg:tags":[
        "children's",
        "animation"
    ],
    "wof:name":"Mario le Magicien",
    "wof:placetype":"venue"
},
  "geometry": {"coordinates":[3.507545948,50.5985908508],"type":"Point"}
}