{
  "type": "Feature",
  "properties": {
    "addr:full":"Rue Le Lonnoux 2 Zone Industriele Bertrix Luxembourg 6880",
    "addr:housenumber":"2",
    "addr:postcode":"6880",
    "addr:street":"Rue Le Lonnoux;Zone Industriele",
    "iso:country":"BE",
    "sg:address":"Rue Le Lonnoux 2 Zone Industriele",
    "sg:city":"Bertrix",
    "sg:orig_category":"Miscellaneous Products",
    "sg:phone":"+32 61 41 18 16",
    "sg:postcode":"6880",
    "sg:province":"Luxembourg",
    "wof:name":"Le Saupont Asbl",
    "wof:placetype":"venue"
},
  "geometry": {"coordinates":[5.2535948753,49.8544845581],"type":"Point"}
}