{
  "type": "Feature",
  "properties": {
    "addr:full":"Nieuwstraat 6 Kruibeke (rupelmonde) Oost-Vlaanderen 9150",
    "addr:housenumber":"6",
    "addr:postcode":"9150",
    "addr:street":"Nieuwstraat",
    "iso:country":"BE",
    "sg:address":"Nieuwstraat 6",
    "sg:city":"Kruibeke (rupelmonde)",
    "sg:classifiers":[
        {
            "category":"Shopping",
            "subcategory":"Florist",
            "type":"Retail Goods"
        }
    ],
    "sg:phone":"+32 3 774 40 59",
    "sg:postcode":"9150",
    "sg:province":"Oost-Vlaanderen",
    "wof:name":"Primavesi",
    "wof:placetype":"venue"
},
  "geometry": {"coordinates":[4.2869939804,51.1291503906],"type":"Point"}
}