{
  "type": "Feature",
  "properties": {
    "iso:country":"BE",
    "sg:address":"38",
    "sg:city":"Lange Munte 9860 Scheldewindeke",
    "sg:classifiers":[
        {
            "category":"Wholesale",
            "subcategory":"Machinery & Supplies",
            "type":"Manufacturing & Wholesale Goods"
        }
    ],
    "sg:phone":"+32 9 362 75 55",
    "sg:postcode":"38",
    "sg:tags":[
        "food",
        "processing",
        "-",
        "machine",
        "equipment",
        "engineering",
        "mechanical"
    ],
    "wof:name":"Debra-blades Bvba",
    "wof:placetype":"venue"
},
  "geometry": {"coordinates":[3.7676420212,50.930606842],"type":"Point"}
}