{
  "type": "Feature",
  "properties": {
    "iso:country":"BE",
    "sg:address":"Oostmalsesteenweg 2",
    "sg:city":"Rijkevorsel",
    "sg:classifiers":[
        {
            "category":"Restaurant",
            "type":"Food & Drink"
        }
    ],
    "sg:phone":"+32 3 314 86 77",
    "sg:postcode":"2310",
    "sg:province":"Antwerpen",
    "sg:tags":[
        "caf\u00e9s"
    ],
    "wof:name":"Taverne Den Beuk",
    "wof:placetype":"venue"
},
  "geometry": {"coordinates":[4.7591309547,51.3465576172],"type":"Point"}
}