{
  "type": "Feature",
  "properties": {
    "iso:country":"BE",
    "sg:address":"Vredestraat 9",
    "sg:city":"Beerse",
    "sg:orig_category":"Quincailleries",
    "sg:phone":"+32 14 61 10 45",
    "sg:postcode":"2340",
    "sg:province":"Antwerpen",
    "wof:name":"Daneels Ljzerwaren",
    "wof:placetype":"venue"
},
  "geometry": {"coordinates":[4.856651783,51.3199539185],"type":"Point"}
}