{
  "type": "Feature",
  "properties": {
    "iso:country":"BE",
    "sg:address":"Dwarsstraat 6",
    "sg:city":"Oostende",
    "sg:orig_category":"Poissonniers and \u00e9caillers",
    "sg:phone":"+32 59 80 12 80",
    "sg:postcode":"8400",
    "sg:province":"West-Vlaanderen",
    "wof:name":"Huis Antoine",
    "wof:placetype":"venue"
},
  "geometry": {"coordinates":[2.9201979637,51.2319488525],"type":"Point"}
}