{
  "type": "Feature",
  "properties": {
    "addr:full":"Diepestraat 17 Antwerpen Antwerpen 2060",
    "addr:housenumber":"17",
    "addr:postcode":"2060",
    "addr:street":"Diepestraat",
    "iso:country":"BE",
    "sg:address":"Diepestraat 17",
    "sg:city":"Antwerpen",
    "sg:orig_category":"Agences d'exp\u00e9dition",
    "sg:phone":"+32 3 213 09 42",
    "sg:postcode":"2060",
    "sg:province":"Antwerpen",
    "wof:name":"S R S International",
    "wof:placetype":"venue"
},
  "geometry": {"coordinates":[4.4227781296,51.2244758606],"type":"Point"}
}