{
  "type": "Feature",
  "properties": {
    "iso:country":"BE",
    "sg:address":"Rue De La Station 35",
    "sg:city":"Awans",
    "sg:orig_category":"Sportclubs",
    "sg:phone":"+32 4 263 73 75",
    "sg:postcode":"4340",
    "sg:province":"Li\u00e8ge",
    "wof:name":"Club Cyclotouriste",
    "wof:placetype":"venue"
},
  "geometry": {"coordinates":[5.4611282349,50.6615066528],"type":"Point"}
}