{
  "type": "Feature",
  "properties": {
    "iso:country":"BE",
    "sg:address":"Kapelstraat 115",
    "sg:city":"Dilsen-stokkem (stokkem)",
    "sg:orig_category":"Non-Classified Establishments",
    "sg:phone":"+32 89 75 32 72",
    "sg:postcode":"3650",
    "sg:province":"Limburg",
    "wof:name":"Party-tent",
    "wof:placetype":"venue"
},
  "geometry": {"coordinates":[5.727396965,51.0364189148],"type":"Point"}
}