{
  "type": "Feature",
  "properties": {
    "addr:full":"Vrijheidsstraat 54 Harelbeke West-Vlaanderen 8530",
    "addr:housenumber":"54",
    "addr:postcode":"8530",
    "addr:street":"Vrijheidsstraat",
    "iso:country":"BE",
    "sg:address":"Vrijheidsstraat 54",
    "sg:city":"Harelbeke",
    "sg:classifiers":[
        {
            "category":"Personal",
            "subcategory":"Beauty Salon",
            "type":"Services"
        }
    ],
    "sg:phone":"+32 56 71 92 55",
    "sg:postcode":"8530",
    "sg:province":"West-Vlaanderen",
    "sg:tags":[
        "lady",
        "-",
        "hairdressing"
    ],
    "wof:name":"Isabelle",
    "wof:placetype":"venue"
},
  "geometry": {"coordinates":[3.3135020733,50.8498306274],"type":"Point"}
}