{
  "type": "Feature",
  "properties": {
    "iso:country":"BE",
    "sg:address":"Pardostraat 1c",
    "sg:city":"Damme (sijsele)",
    "sg:orig_category":"Non-Classified Establishments",
    "sg:phone":"+32 50 37 47 46",
    "sg:postcode":"8340",
    "sg:province":"West-Vlaanderen",
    "wof:name":"Damse Kaasmakerij",
    "wof:placetype":"venue"
},
  "geometry": {"coordinates":[3.318926096,51.204120636],"type":"Point"}
}