{
  "type": "Feature",
  "properties": {
    "iso:country":"BE",
    "sg:address":"Rue Belle-vue 47",
    "sg:city":"Li\u00c8ge",
    "sg:orig_category":"Brood, gebak and snoepgoed",
    "sg:phone":"+32 4 341 72 62",
    "sg:postcode":"4020",
    "sg:province":"Li\u00e8ge",
    "wof:name":"Au P'tit Gourmand",
    "wof:placetype":"venue"
},
  "geometry": {"coordinates":[5.5635561943,50.6429977417],"type":"Point"}
}