{
  "type": "Feature",
  "properties": {
    "addr:full":"Dokter Theo Tutsstraat 30 Boechout Antwerpen 2530",
    "addr:housenumber":"30",
    "addr:postcode":"2530",
    "addr:street":"Dokter Theo Tutsstraat",
    "iso:country":"BE",
    "sg:address":"Dokter Theo Tutsstraat 30",
    "sg:city":"Boechout",
    "sg:classifiers":[
        {
            "category":"Restaurant",
            "type":"Food & Drink"
        }
    ],
    "sg:phone":"+32 3 455 81 83",
    "sg:postcode":"2530",
    "sg:province":"Antwerpen",
    "wof:name":"Kam Ho",
    "wof:placetype":"venue"
},
  "geometry": {"coordinates":[4.4936828613,51.1617507935],"type":"Point"}
}