{
  "type": "Feature",
  "properties": {
    "iso:country":"BE",
    "sg:address":"Trade Markt 327",
    "sg:city":"Bruxelles",
    "sg:orig_category":"Horloges, m\u00e9taux pr\u00e9cieux and bijoux Gr",
    "sg:phone":"+32 2 476 10 02",
    "sg:postcode":"1020",
    "sg:province":"Bruxelles-Capitale",
    "wof:name":"Brandini Bijoux",
    "wof:placetype":"venue"
},
  "geometry": {"coordinates":[4.3576002121,50.8577003479],"type":"Point"}
}