{
  "type": "Feature",
  "properties": {
    "addr:full":"Oeveren 9 Baelen/baelen Li\u00e8ge 4837",
    "addr:housenumber":"9",
    "addr:postcode":"4837",
    "addr:street":"Oeveren",
    "iso:country":"BE",
    "sg:address":"Oeveren 9",
    "sg:city":"Baelen/baelen",
    "sg:orig_category":"G\u00e9om\u00e8tres",
    "sg:phone":"+32 87 76 64 60",
    "sg:postcode":"4837",
    "sg:province":"Li\u00e8ge",
    "wof:name":"Christoph Gustin",
    "wof:placetype":"venue"
},
  "geometry": {"coordinates":[5.9713401794,50.6319007874],"type":"Point"}
}