{
  "type": "Feature",
  "properties": {
    "iso:country":"BE",
    "sg:address":"Bampstraat 5",
    "sg:city":"Riemst",
    "sg:orig_category":"Rundveehouders Varkenskwekers",
    "sg:phone":"+32 12 45 13 26",
    "sg:postcode":"3770",
    "sg:province":"Limburg",
    "wof:name":"August Huls",
    "wof:placetype":"venue"
},
  "geometry": {"coordinates":[5.5953612328,50.7864112854],"type":"Point"}
}