{
  "type": "Feature",
  "properties": {
    "addr:full":"Grondwetplein 11 Bruxelles (saint-gilles) Bruxelles-Capitale 1060",
    "addr:housenumber":"11",
    "addr:postcode":"1060",
    "addr:street":"Grondwetplein",
    "iso:country":"BE",
    "sg:address":"Grondwetplein 11",
    "sg:city":"Bruxelles (saint-gilles)",
    "sg:classifiers":[
        {
            "category":"Home & Garden",
            "subcategory":"Building Materials",
            "type":"Retail Goods"
        }
    ],
    "sg:phone":"+32 2 520 12 60",
    "sg:postcode":"1060",
    "sg:province":"Bruxelles-Capitale",
    "sg:tags":[
        "granite",
        "stone",
        "natural",
        "marble"
    ],
    "wof:name":"Luso Pierres",
    "wof:placetype":"venue"
},
  "geometry": {"coordinates":[4.3406400681,50.8392066956],"type":"Point"}
}