{
  "type": "Feature",
  "properties": {
    "addr:full":"Chemin De Reumont 135 Namur Namur 5020",
    "addr:housenumber":"135",
    "addr:postcode":"5020",
    "addr:street":"Chemin De Reumont",
    "iso:country":"BE",
    "sg:address":"Chemin De Reumont 135",
    "sg:city":"Namur",
    "sg:orig_category":"Enseignement maternel and primaire. Enseignement secondaire g\u00e9n\u00e9ral",
    "sg:phone":"+32 81 44 55 81",
    "sg:postcode":"5020",
    "sg:province":"Namur",
    "wof:name":"E.p.e.s. Reumonjoie",
    "wof:placetype":"venue"
},
  "geometry": {"coordinates":[4.8032598495,50.4328804016],"type":"Point"}
}