{
  "type": "Feature",
  "properties": {
    "addr:full":"Place Emile Bockstael 5-6 Bruxelles Bruxelles-Capitale 1020",
    "addr:housenumber":"5-6",
    "addr:postcode":"1020",
    "addr:street":"Place Emile Bockstael",
    "iso:country":"BE",
    "sg:address":"Place Emile Bockstael 5-6",
    "sg:city":"Bruxelles",
    "sg:classifiers":[
        {
            "category":"Retail",
            "subcategory":"Animal Services",
            "type":"Services"
        }
    ],
    "sg:phone":"+32 2 425 07 17",
    "sg:postcode":"1020",
    "sg:province":"Bruxelles-Capitale",
    "sg:tags":[
        "breeding",
        "selling",
        "-",
        "dog"
    ],
    "wof:name":"Toutou Sprl",
    "wof:placetype":"venue"
},
  "geometry": {"coordinates":[4.3435950279,50.8702812195],"type":"Point"}
}