{
  "type": "Feature",
  "properties": {
    "iso:country":"BE",
    "sg:address":"Hoogboomsteenweg 24a",
    "sg:city":"Brasschaat",
    "sg:classifiers":[
        {
            "category":"Shopping",
            "subcategory":"Clothing, Apparel, & Fashions",
            "type":"Retail Goods"
        }
    ],
    "sg:phone":"+32 3 651 39 72",
    "sg:postcode":"2930",
    "sg:province":"Antwerpen",
    "sg:tags":[
        "purchase",
        "clothing",
        "-",
        "sale",
        "second-hand"
    ],
    "wof:name":"Paddestoel (de)",
    "wof:placetype":"venue"
},
  "geometry": {"coordinates":[4.4854259491,51.3048934937],"type":"Point"}
}