{
  "type": "Feature",
  "properties": {
    "iso:country":"BE",
    "sg:address":"Pieter Pourbusstraat 1",
    "sg:city":"Brugge",
    "sg:classifiers":[
        {
            "category":"Restaurant",
            "type":"Food & Drink"
        }
    ],
    "sg:phone":"+32 50 34 11 45",
    "sg:postcode":"8000",
    "sg:province":"West-Vlaanderen",
    "wof:name":"Pieter Pourbus",
    "wof:placetype":"venue"
},
  "geometry": {"coordinates":[3.223031044,51.2120895386],"type":"Point"}
}