{
  "type": "Feature",
  "properties": {
    "addr:full":"Abelenlaan 12 Grimbergen (humbeek) Vlaams-Brabant 1851",
    "addr:housenumber":"12",
    "addr:postcode":"1851",
    "addr:street":"Abelenlaan",
    "iso:country":"BE",
    "sg:address":"Abelenlaan 12",
    "sg:city":"Grimbergen (humbeek)",
    "sg:classifiers":[
        {
            "category":"Wholesale",
            "subcategory":"Beer",
            "type":"Manufacturing & Wholesale Goods"
        }
    ],
    "sg:phone":"+32 2 269 54 53",
    "sg:postcode":"1851",
    "sg:province":"Vlaams-Brabant",
    "sg:tags":[
        "ale",
        "-"
    ],
    "wof:name":"Van Lint Bvba",
    "wof:placetype":"venue"
},
  "geometry": {"coordinates":[4.3748879433,50.9642410278],"type":"Point"}
}