{
  "type": "Feature",
  "properties": {
    "addr:full":"Rue De L'ouvrage 3 Namur Namur 5000",
    "addr:housenumber":"3",
    "addr:postcode":"5000",
    "addr:street":"Rue De L'Ouvrage",
    "iso:country":"BE",
    "sg:address":"Rue De L'ouvrage 3",
    "sg:city":"Namur",
    "sg:classifiers":[
        {
            "category":"Restaurant",
            "type":"Food & Drink"
        }
    ],
    "sg:phone":"+32 81 23 16 19",
    "sg:postcode":"5000",
    "sg:province":"Namur",
    "sg:tags":[
        "caf\u00e9s"
    ],
    "wof:name":"Taverne Peanuts",
    "wof:placetype":"venue"
},
  "geometry": {"coordinates":[4.8632640839,50.4646453857],"type":"Point"}
}