{
  "type": "Feature",
  "properties": {
    "addr:full":"Kaaskerkestraat 28 Diksmuide West-Vlaanderen 8600",
    "addr:housenumber":"28",
    "addr:postcode":"8600",
    "addr:street":"Kaaskerkestraat",
    "iso:country":"BE",
    "sg:address":"Kaaskerkestraat 28",
    "sg:city":"Diksmuide",
    "sg:orig_category":"Pi\u00e8ces and accessoires de v\u00e9hicules automobiles D\u00e9taillants en pi\u00e8ces and accessoires de voitures",
    "sg:phone":"+32 51 50 14 56",
    "sg:postcode":"8600",
    "sg:province":"West-Vlaanderen",
    "wof:name":"Fa. Nollet",
    "wof:placetype":"venue"
},
  "geometry": {"coordinates":[2.8271460533,51.0384979248],"type":"Point"}
}