{
  "type": "Feature",
  "properties": {
    "iso:country":"BE",
    "sg:address":"Hofstraat 1",
    "sg:city":"Oostende",
    "sg:classifiers":[
        {
            "category":"Travel",
            "subcategory":"Hotels & Motels",
            "type":"Entertainment"
        }
    ],
    "sg:phone":"+32 59 50 71 83",
    "sg:postcode":"8400",
    "sg:province":"West-Vlaanderen",
    "wof:name":"Telstar",
    "wof:placetype":"venue"
},
  "geometry": {"coordinates":[2.918364048,51.234046936],"type":"Point"}
}