{
  "type": "Feature",
  "properties": {
    "addr:full":"Armand Segerslei 82 Mortsel Antwerpen 2640",
    "addr:housenumber":"82",
    "addr:postcode":"2640",
    "addr:street":"Armand Segerslei",
    "iso:country":"BE",
    "sg:address":"Armand Segerslei 82",
    "sg:city":"Mortsel",
    "sg:classifiers":[
        {
            "category":"Professional",
            "subcategory":"Computer Services",
            "type":"Services"
        }
    ],
    "sg:phone":"+32 3 448 46 22",
    "sg:postcode":"2640",
    "sg:province":"Antwerpen",
    "sg:tags":[
        "webdesign",
        "-",
        "internet"
    ],
    "wof:name":"Vianet",
    "wof:placetype":"venue"
},
  "geometry": {"coordinates":[4.4448289871,51.1705856323],"type":"Point"}
}