{
  "type": "Feature",
  "properties": {
    "iso:country":"BE",
    "sg:address":"Ritmeesterlaan 18",
    "sg:city":"Bredene",
    "sg:classifiers":[
        {
            "category":"Professional",
            "subcategory":"Detective & Security Services",
            "type":"Services"
        }
    ],
    "sg:phone":"+32 59 33 38 30",
    "sg:postcode":"8450",
    "sg:province":"West-Vlaanderen",
    "sg:tags":[
        "-",
        "system",
        "apparatus",
        "surveillance"
    ],
    "wof:name":"Electrotec",
    "wof:placetype":"venue"
},
  "geometry": {"coordinates":[2.9853079319,51.2482337952],"type":"Point"}
}