{
  "type": "Feature",
  "properties": {
    "iso:country":"BE",
    "sg:address":"Rue De La Justice 23a",
    "sg:city":"Oupeye",
    "sg:classifiers":[
        {
            "category":"Health Services",
            "subcategory":"Health Practitioner",
            "type":"Services"
        }
    ],
    "sg:phone":"+32 4 264 61 19",
    "sg:postcode":"4680",
    "sg:province":"Li\u00e8ge",
    "sg:tags":[
        "physiotherapist"
    ],
    "wof:name":"Cops Mureille",
    "wof:placetype":"venue"
},
  "geometry": {"coordinates":[5.6386828423,50.712474823],"type":"Point"}
}