{
  "type": "Feature",
  "properties": {
    "addr:full":"Chauss\u00c9e De Houffalize 5 Bastogne Luxembourg 6600",
    "addr:housenumber":"5",
    "addr:postcode":"6600",
    "addr:street":"Chausse\u0301E De Houffalize",
    "iso:country":"BE",
    "sg:address":"Chauss\u00c9e De Houffalize 5",
    "sg:city":"Bastogne",
    "sg:classifiers":[
        {
            "category":"Restaurant",
            "type":"Food & Drink"
        }
    ],
    "sg:phone":"+32 61 21 39 13",
    "sg:postcode":"6600",
    "sg:province":"Luxembourg",
    "wof:name":"Au Coin Fleuri",
    "wof:placetype":"venue"
},
  "geometry": {"coordinates":[5.7235889435,50.0132637024],"type":"Point"}
}