{
  "type": "Feature",
  "properties": {
    "iso:country":"BE",
    "sg:address":"Square Franklin-delano Roosevelt 12",
    "sg:city":"Mons",
    "sg:classifiers":[
        {
            "category":"Museum",
            "type":"Entertainment"
        }
    ],
    "sg:phone":"+32 65 36 31 64",
    "sg:postcode":"7000",
    "sg:province":"Hainaut",
    "wof:name":"Mus\u00e9e Fran\u00e7ois Duesberg",
    "wof:placetype":"venue"
},
  "geometry": {"coordinates":[3.9451229572,50.4536972046],"type":"Point"}
}