{
  "type": "Feature",
  "properties": {
    "addr:full":"Grote Markt 43 Menen West-Vlaanderen 8930",
    "addr:housenumber":"43",
    "addr:postcode":"8930",
    "addr:street":"Grote Markt",
    "iso:country":"BE",
    "sg:address":"Grote Markt 43",
    "sg:city":"Menen",
    "sg:classifiers":[
        {
            "category":"Cafe",
            "type":"Food & Drink"
        }
    ],
    "sg:phone":"+32 56 51 89 38",
    "sg:postcode":"8930",
    "sg:province":"West-Vlaanderen",
    "sg:tags":[
        "caf\u00e9s"
    ],
    "wof:name":"Caf\u00c9 't Ogenblik",
    "wof:placetype":"venue"
},
  "geometry": {"coordinates":[3.1210100651,50.7960128784],"type":"Point"}
}