{
  "type": "Feature",
  "properties": {
    "iso:country":"BE",
    "sg:address":"Van Naemenstraat 45",
    "sg:city":"Sint-niklaas",
    "sg:orig_category":"Enregistrements sonores",
    "sg:phone":"+32 3 776 27 44",
    "sg:postcode":"9100",
    "sg:province":"Oost-Vlaanderen",
    "wof:name":"Dust Music Productions",
    "wof:placetype":"venue"
},
  "geometry": {"coordinates":[4.1507878304,51.1698265076],"type":"Point"}
}