{
  "type": "Feature",
  "properties": {
    "addr:full":"Veerlestraat 19 Aarschot Vlaams-Brabant 3201",
    "addr:housenumber":"19",
    "addr:postcode":"3201",
    "addr:street":"Veerlestraat",
    "iso:country":"BE",
    "sg:address":"Veerlestraat 19",
    "sg:city":"Aarschot",
    "sg:orig_category":"HUISBRANDOLIE",
    "sg:phone":"+32 13 77 11 66",
    "sg:postcode":"3201",
    "sg:province":"Vlaams-Brabant",
    "wof:name":"Van Passel",
    "wof:placetype":"venue"
},
  "geometry": {"coordinates":[4.9215297699,51.0301017761],"type":"Point"}
}