{
  "type": "Feature",
  "properties": {
    "addr:full":"Rue Vandeweyer 32 Bruxelles (schaerbeek) Bruxelles-Capitale 1030",
    "addr:housenumber":"32",
    "addr:postcode":"1030",
    "addr:street":"Rue Vandeweyer",
    "iso:country":"BE",
    "sg:address":"Rue Vandeweyer 32",
    "sg:city":"Bruxelles (schaerbeek)",
    "sg:classifiers":[
        {
            "category":"Professional",
            "subcategory":"Printing & Photocopies",
            "type":"Services"
        }
    ],
    "sg:phone":"+32 2 241 57 30",
    "sg:postcode":"1030",
    "sg:province":"Bruxelles-Capitale",
    "sg:tags":[
        "-",
        "publishing",
        "desktop"
    ],
    "wof:name":"Heinrich Walgraeve",
    "wof:placetype":"venue"
},
  "geometry": {"coordinates":[4.3683981895,50.8640136719],"type":"Point"}
}