{
  "type": "Feature",
  "properties": {
    "iso:country":"BE",
    "sg:address":"Hameau Du Fourcroix 37",
    "sg:city":"Tournai (blandain - Hertain)",
    "sg:classifiers":[
        {
            "category":"Health Services",
            "subcategory":"Health Practitioner",
            "type":"Services"
        }
    ],
    "sg:phone":"+32 69 35 14 21",
    "sg:postcode":"7522",
    "sg:province":"Hainaut",
    "sg:tags":[
        "physiotherapist"
    ],
    "wof:name":"Strobbe Christine",
    "wof:placetype":"venue"
},
  "geometry": {"coordinates":[3.3250629902,50.6389656067],"type":"Point"}
}