{
  "type": "Feature",
  "properties": {
    "addr:full":"Kempische Steenweg 360 Hasselt Limburg 3500",
    "addr:housenumber":"360",
    "addr:postcode":"3500",
    "addr:street":"Kempische Steenweg",
    "iso:country":"BE",
    "sg:address":"Kempische Steenweg 360",
    "sg:city":"Hasselt",
    "sg:classifiers":[
        {
            "category":"Shopping",
            "subcategory":"Gifts & Souvenirs",
            "type":"Retail Goods"
        }
    ],
    "sg:phone":"+32 11 21 25 33",
    "sg:postcode":"3500",
    "sg:province":"Limburg",
    "sg:tags":[
        "-"
    ],
    "wof:name":"Fereda Homedecoratie",
    "wof:placetype":"venue"
},
  "geometry": {"coordinates":[5.3410902023,50.9396095276],"type":"Point"}
}