{
  "type": "Feature",
  "properties": {
    "addr:full":"Rue Du Chalet 70 Aubange Luxembourg 6792",
    "addr:housenumber":"70",
    "addr:postcode":"6792",
    "addr:street":"Rue Du Chalet",
    "iso:country":"BE",
    "sg:address":"Rue Du Chalet 70",
    "sg:city":"Aubange",
    "sg:classifiers":[
        {
            "category":"Cafe",
            "type":"Food & Drink"
        }
    ],
    "sg:phone":"+32 63 67 53 23",
    "sg:postcode":"6792",
    "sg:province":"Luxembourg",
    "sg:tags":[
        "caf\u00e9s"
    ],
    "wof:name":"Caf\u00c9 Scoop",
    "wof:placetype":"venue"
},
  "geometry": {"coordinates":[5.743519783,49.5567016602],"type":"Point"}
}