{
  "type": "Feature",
  "properties": {
    "addr:full":"Polderstraat 2d Brugge (sint-kruis) West-Vlaanderen 8310",
    "addr:housenumber":"2d",
    "addr:postcode":"8310",
    "addr:street":"Polderstraat",
    "iso:country":"BE",
    "sg:address":"Polderstraat 2d",
    "sg:city":"Brugge (sint-kruis)",
    "sg:classifiers":[
        {
            "category":"Home & Garden",
            "subcategory":"Home Furnishings",
            "type":"Retail Goods"
        }
    ],
    "sg:phone":"+32 50 84 02 09",
    "sg:postcode":"8310",
    "sg:province":"West-Vlaanderen",
    "sg:tags":[
        "curtain",
        "-",
        "fixture"
    ],
    "wof:name":"De Wever",
    "wof:placetype":"venue"
},
  "geometry": {"coordinates":[3.2515289783,51.2145690918],"type":"Point"}
}