{
  "type": "Feature",
  "properties": {
    "addr:full":"Rue De La Princesse 7 La Louvi\u00e8re (trivi\u00e8res) Hainaut 7100",
    "addr:housenumber":"7",
    "addr:postcode":"7100",
    "addr:street":"Rue De La Princesse",
    "iso:country":"BE",
    "sg:address":"Rue De La Princesse 7",
    "sg:city":"La Louvi\u00e8re (trivi\u00e8res)",
    "sg:classifiers":[
        {
            "category":"Health Services",
            "subcategory":"Health Practitioner",
            "type":"Services"
        }
    ],
    "sg:phone":"+32 64 37 03 64",
    "sg:postcode":"7100",
    "sg:province":"Hainaut",
    "sg:tags":[
        "physiotherapist"
    ],
    "wof:name":"Ramos Teixeira Jean-fran\u00e7ois",
    "wof:placetype":"venue"
},
  "geometry": {"coordinates":[4.1850848198,50.4748649597],"type":"Point"}
}