{
  "type": "Feature",
  "properties": {
    "addr:full":"Potterijstraat 12b14 Kortrijk West-Vlaanderen 8500",
    "addr:housenumber":"12b14",
    "addr:postcode":"8500",
    "addr:street":"Potterijstraat",
    "iso:country":"BE",
    "sg:address":"Potterijstraat 12b14",
    "sg:city":"Kortrijk",
    "sg:orig_category":"Electrom\u00e9nager, t\u00e9l\u00e9visions and radios. Location de cassettes vid\u00e9o and audio",
    "sg:phone":"+32 56 20 31 86",
    "sg:postcode":"8500",
    "sg:province":"West-Vlaanderen",
    "wof:name":"Eurostar Videoclub",
    "wof:placetype":"venue"
},
  "geometry": {"coordinates":[3.272190094,50.827419281],"type":"Point"}
}