{
  "type": "Feature",
  "properties": {
    "iso:country":"BE",
    "sg:address":"Vierhoevenstraat 60",
    "sg:city":"Kapellen",
    "sg:orig_category":"Maatkleding Fab",
    "sg:phone":"+32 3 664 70 24",
    "sg:postcode":"2950",
    "sg:province":"Antwerpen",
    "wof:name":"Jessy Orens",
    "wof:placetype":"venue"
},
  "geometry": {"coordinates":[4.4052901268,51.3527183533],"type":"Point"}
}