{
  "type": "Feature",
  "properties": {
    "iso:country":"BE",
    "sg:address":"Steenweg Op Brussel 304",
    "sg:city":"Kraainem/kraainem",
    "sg:orig_category":"Maatschappelijke dienstverlening",
    "sg:phone":"+32 2 767 44 63",
    "sg:postcode":"1950",
    "sg:province":"Vlaams-Brabant",
    "wof:name":"Oeuvre Nat. De L'enfance",
    "wof:placetype":"venue"
},
  "geometry": {"coordinates":[4.4881057739,50.8212852478],"type":"Point"}
}