{
  "type": "Feature",
  "properties": {
    "iso:country":"BE",
    "sg:address":"Eigenstraat 115",
    "sg:city":"Haaltert",
    "sg:orig_category":"Architecten",
    "sg:phone":"+32 53 83 17 66",
    "sg:postcode":"9450",
    "sg:province":"Oost-Vlaanderen",
    "wof:name":"Petra Eeckhout",
    "wof:placetype":"venue"
},
  "geometry": {"coordinates":[4.0269632339,50.8848991394],"type":"Point"}
}