{
  "type": "Feature",
  "properties": {
    "addr:full":"Smisstraat 47 Halle Vlaams-Brabant 1500",
    "addr:housenumber":"47",
    "addr:postcode":"1500",
    "addr:street":"Smisstraat",
    "iso:country":"BE",
    "sg:address":"Smisstraat 47",
    "sg:city":"Halle",
    "sg:orig_category":"Plomberie, chauffage and installations sanitaires",
    "sg:phone":"+32 2 356 69 72",
    "sg:postcode":"1500",
    "sg:province":"Vlaams-Brabant",
    "wof:name":"Georges Benoot",
    "wof:placetype":"venue"
},
  "geometry": {"coordinates":[4.1957521439,50.7603302002],"type":"Point"}
}