{
  "type": "Feature",
  "properties": {
    "addr:full":"Avenue Bonaparte 37 Bruxelles (uccle) Bruxelles-Capitale 1180",
    "addr:housenumber":"37",
    "addr:postcode":"1180",
    "addr:street":"Avenue Bonaparte",
    "iso:country":"BE",
    "sg:address":"Avenue Bonaparte 37",
    "sg:city":"Bruxelles (uccle)",
    "sg:classifiers":[
        {
            "category":"Health Services",
            "subcategory":"Doctor",
            "type":"Services"
        }
    ],
    "sg:phone":"+32 2 374 15 46",
    "sg:postcode":"1180",
    "sg:province":"Bruxelles-Capitale",
    "sg:tags":[
        "medicinephysicians",
        "surgeon"
    ],
    "wof:name":"De Longueville Marc",
    "wof:placetype":"venue"
},
  "geometry": {"coordinates":[4.3638339043,50.7862472534],"type":"Point"}
}