{
  "type": "Feature",
  "properties": {
    "addr:full":"Tongerenstraat 18 Etterbeek Bruxelles-Capitale 1040",
    "addr:housenumber":"18",
    "addr:postcode":"1040",
    "addr:street":"Tongerenstraat",
    "iso:country":"BE",
    "sg:address":"Tongerenstraat 18",
    "sg:city":"Etterbeek",
    "sg:classifiers":[
        {
            "category":"Restaurant",
            "type":"Food & Drink"
        }
    ],
    "sg:phone":"+32 2 733 09 75",
    "sg:postcode":"1040",
    "sg:province":"Bruxelles-Capitale",
    "wof:name":"Muscade",
    "wof:placetype":"venue"
},
  "geometry": {"coordinates":[4.3994932175,50.8397827148],"type":"Point"}
}