{
  "type": "Feature",
  "properties": {
    "iso:country":"BE",
    "sg:address":"Chemin De Neerstalle 96",
    "sg:city":"Bruxelles (forest)",
    "sg:orig_category":"Mayonnaise - Mfg.& Whol",
    "sg:phone":"+32 2 376 50 56",
    "sg:postcode":"1190",
    "sg:province":"Bruxelles-Capitale",
    "wof:name":"Natura Sprl",
    "wof:placetype":"venue"
},
  "geometry": {"coordinates":[4.3149662018,50.8068199158],"type":"Point"}
}