{
  "type": "Feature",
  "properties": {
    "addr:full":"Rue Des Martyrs 54 Verviers Li\u00e8ge 4800",
    "addr:housenumber":"54",
    "addr:postcode":"4800",
    "addr:street":"Rue Des Martyrs",
    "iso:country":"BE",
    "sg:address":"Rue Des Martyrs 54",
    "sg:city":"Verviers",
    "sg:orig_category":"Avocats and conseillers juridiques",
    "sg:phone":"+32 87 33 98 23",
    "sg:postcode":"4800",
    "sg:province":"Li\u00e8ge",
    "wof:name":"Jean-marie Frederick",
    "wof:placetype":"venue"
},
  "geometry": {"coordinates":[5.8630242348,50.5911903381],"type":"Point"}
}