{
  "type": "Feature",
  "properties": {
    "iso:country":"BE",
    "sg:address":"Oude Berg 3",
    "sg:city":"Borgloon",
    "sg:classifiers":[
        {
            "category":"Real Estate",
            "subcategory":"Real Estate Services",
            "type":"Services"
        }
    ],
    "sg:phone":"+32 12 74 25 59",
    "sg:postcode":"3840",
    "sg:province":"Limburg",
    "wof:name":"Immo Willy Bleus",
    "wof:placetype":"venue"
},
  "geometry": {"coordinates":[5.3436160088,50.8004798889],"type":"Point"}
}