{
  "type": "Feature",
  "properties": {
    "addr:full":"Kortrijkseweg 82 Waregem West-Vlaanderen 8791",
    "addr:housenumber":"82",
    "addr:postcode":"8791",
    "addr:street":"Kortrijkseweg",
    "iso:country":"BE",
    "sg:address":"Kortrijkseweg 82",
    "sg:city":"Waregem",
    "sg:orig_category":"Meubelzaken, woning- and keukeninrichting Textiel Verlichting and huishoudartikelen",
    "sg:phone":"+32 56 72 83 80",
    "sg:postcode":"8791",
    "sg:province":"West-Vlaanderen",
    "wof:name":"Ideal Bedding",
    "wof:placetype":"venue"
},
  "geometry": {"coordinates":[3.3364849091,50.8689613342],"type":"Point"}
}