{
  "type": "Feature",
  "properties": {
    "addr:full":"Kortrijkstraat 323 Oudenaarde Oost-Vlaanderen 9700",
    "addr:housenumber":"323",
    "addr:postcode":"9700",
    "addr:street":"Kortrijkstraat",
    "iso:country":"BE",
    "sg:address":"Kortrijkstraat 323",
    "sg:city":"Oudenaarde",
    "sg:orig_category":"Fa\u00e7ade covering",
    "sg:phone":"+32 55 31 31 66",
    "sg:postcode":"9700",
    "sg:province":"Oost-Vlaanderen",
    "wof:name":"Franiver",
    "wof:placetype":"venue"
},
  "geometry": {"coordinates":[3.5753018856,50.8416481018],"type":"Point"}
}