{
  "type": "Feature",
  "properties": {
    "addr:full":"Kraaistraat 22 Mechelen Antwerpen 2800",
    "addr:housenumber":"22",
    "addr:postcode":"2800",
    "addr:street":"Kraaistraat",
    "iso:country":"BE",
    "sg:address":"Kraaistraat 22",
    "sg:city":"Mechelen",
    "sg:orig_category":"Promoteurs immobiliers",
    "sg:phone":"+32 15 21 65 13",
    "sg:postcode":"2800",
    "sg:province":"Antwerpen",
    "wof:name":"Van Geenberghe R.",
    "wof:placetype":"venue"
},
  "geometry": {"coordinates":[4.4691209793,51.0501403809],"type":"Point"}
}