{
  "type": "Feature",
  "properties": {
    "iso:country":"BE",
    "sg:address":"Winkelomstraat 37",
    "sg:city":"Bilzen",
    "sg:orig_category":"Verhuur textielartikelen and schoenen",
    "sg:phone":"+32 89 41 81 37",
    "sg:postcode":"3740",
    "sg:province":"Limburg",
    "wof:name":"Eddy Gerits",
    "wof:placetype":"venue"
},
  "geometry": {"coordinates":[5.5821371078,50.8746910095],"type":"Point"}
}