{
  "type": "Feature",
  "properties": {
    "addr:full":"Jan Van Rijswijcklaan 65 Antwerpen Antwerpen 2018",
    "addr:housenumber":"65",
    "addr:postcode":"2018",
    "addr:street":"Jan Van Rijswijcklaan",
    "iso:country":"BE",
    "sg:address":"Jan Van Rijswijcklaan 65",
    "sg:city":"Antwerpen",
    "sg:classifiers":[
        {
            "category":"Cafe",
            "type":"Food & Drink"
        }
    ],
    "sg:phone":"+32 3 248 26 02",
    "sg:postcode":"2018",
    "sg:province":"Antwerpen",
    "sg:tags":[
        "snack-bars"
    ],
    "wof:name":"Broodjeshuis",
    "wof:placetype":"venue"
},
  "geometry": {"coordinates":[4.4065761566,51.1968612671],"type":"Point"}
}