{
  "type": "Feature",
  "properties": {
    "addr:full":"Gistelse Steenweg 61 Brugge West-Vlaanderen 8200",
    "addr:housenumber":"61",
    "addr:postcode":"8200",
    "addr:street":"Gistelse Steenweg",
    "iso:country":"BE",
    "sg:address":"Gistelse Steenweg 61",
    "sg:city":"Brugge",
    "sg:orig_category":"M\u00e9decins and sp\u00e9cialistes",
    "sg:phone":"+32 50 38 61 82",
    "sg:postcode":"8200",
    "sg:province":"West-Vlaanderen",
    "wof:name":"Jan-alfons Carlier",
    "wof:placetype":"venue"
},
  "geometry": {"coordinates":[3.2068610191,51.2034072876],"type":"Point"}
}