{
  "type": "Feature",
  "properties": {
    "iso:country":"BE",
    "sg:address":"Voorstraat 10",
    "sg:city":"Kortrijk",
    "sg:orig_category":"Brood, gebak and snoepgoed",
    "sg:phone":"+32 56 25 78 28",
    "sg:postcode":"8500",
    "sg:province":"West-Vlaanderen",
    "wof:name":"D\u00c9lifrance Boutique",
    "wof:placetype":"venue"
},
  "geometry": {"coordinates":[3.2710649967,50.8275184631],"type":"Point"}
}