{
  "type": "Feature",
  "properties": {
    "iso:country":"BE",
    "sg:address":"Gierleseweg 36",
    "sg:city":"Beerse",
    "sg:orig_category":"Woningbouw",
    "sg:phone":"+32 14 61 79 18",
    "sg:postcode":"2340",
    "sg:province":"Antwerpen",
    "wof:name":"De Wit Bouw Belgie",
    "wof:placetype":"venue"
},
  "geometry": {"coordinates":[4.8557229042,51.304889679],"type":"Point"}
}