{
  "type": "Feature",
  "properties": {
    "addr:full":"Rue Du Vicinal 25 Manhay Luxembourg 6960",
    "addr:housenumber":"25",
    "addr:postcode":"6960",
    "addr:street":"Rue Du Vicinal",
    "iso:country":"BE",
    "sg:address":"Rue Du Vicinal 25",
    "sg:city":"Manhay",
    "sg:orig_category":"Brood, gebak and snoepgoed",
    "sg:phone":"+32 86 45 60 06",
    "sg:postcode":"6960",
    "sg:province":"Luxembourg",
    "wof:name":"Boulangerie Gourmandise",
    "wof:placetype":"venue"
},
  "geometry": {"coordinates":[5.6744160652,50.2933807373],"type":"Point"}
}