{
  "type": "Feature",
  "properties": {
    "iso:country":"BE",
    "sg:address":"Prudens Van Duysestraat 6",
    "sg:city":"Dendermonde",
    "sg:classifiers":[
        {
            "category":"Education",
            "subcategory":"School",
            "type":"Public Place"
        }
    ],
    "sg:phone":"+32 52 21 39 49",
    "sg:postcode":"9200",
    "sg:province":"Oost-Vlaanderen",
    "sg:tags":[
        "secondary"
    ],
    "wof:name":"St-vincentius",
    "wof:placetype":"venue"
},
  "geometry": {"coordinates":[4.0936732292,51.0309028625],"type":"Point"}
}