{
  "type": "Feature",
  "properties": {
    "addr:full":"Rue Adam 29 Namur (flawinne) Namur 5020",
    "addr:housenumber":"29",
    "addr:postcode":"5020",
    "addr:street":"Rue Adam",
    "iso:country":"BE",
    "sg:address":"Rue Adam 29",
    "sg:city":"Namur (flawinne)",
    "sg:classifiers":[
        {
            "category":"Arena",
            "subcategory":"Sports Club",
            "type":"Entertainment"
        }
    ],
    "sg:phone":"+32 81 73 70 59",
    "sg:postcode":"5020",
    "sg:province":"Namur",
    "sg:tags":[
        "federation"
    ],
    "wof:name":"International Taekwondo F\u00e9deration",
    "wof:placetype":"venue"
},
  "geometry": {"coordinates":[4.7952418327,50.4352035522],"type":"Point"}
}