{
  "type": "Feature",
  "properties": {
    "iso:country":"BE",
    "sg:address":"Molenstraat 43",
    "sg:city":"Gooik",
    "sg:orig_category":"Graanmeel Fab",
    "sg:phone":"+32 54 56 62 31",
    "sg:postcode":"1755",
    "sg:province":"Vlaams-Brabant",
    "wof:name":"Walravens",
    "wof:placetype":"venue"
},
  "geometry": {"coordinates":[4.1299939156,50.7622299194],"type":"Point"}
}