{
  "type": "Feature",
  "properties": {
    "iso:country":"BE",
    "sg:address":"Rue Antoine Br\u00c9art 109",
    "sg:city":"Sint-gillis/saint-gilles",
    "sg:orig_category":"Art and fournitures artistiques. Artistes ind\u00e9pendants",
    "sg:phone":"+32 2 537 60 26",
    "sg:postcode":"1060",
    "sg:province":"Bruxelles-Capitale",
    "wof:name":"Andre Coumans",
    "wof:placetype":"venue"
},
  "geometry": {"coordinates":[4.3450899124,50.8233108521],"type":"Point"}
}