{
  "type": "Feature",
  "properties": {
    "addr:full":"Avenue Prekelinden 70 Bruxelles (woluwe-saint-lambert) Bruxelles-Capitale 1200",
    "addr:housenumber":"70",
    "addr:postcode":"1200",
    "addr:street":"Avenue Prekelinden",
    "iso:country":"BE",
    "sg:address":"Avenue Prekelinden 70",
    "sg:city":"Bruxelles (woluwe-saint-lambert)",
    "sg:classifiers":[
        {
            "category":"Travel",
            "subcategory":"Travel Agent",
            "type":"Entertainment"
        }
    ],
    "sg:phone":"+32 2 736 05 04",
    "sg:postcode":"1200",
    "sg:province":"Bruxelles-Capitale",
    "sg:tags":[
        "agency"
    ],
    "wof:name":"Mercury Travels Sprl",
    "wof:placetype":"venue"
},
  "geometry": {"coordinates":[4.4092741013,50.8423538208],"type":"Point"}
}