{
  "type": "Feature",
  "properties": {
    "addr:full":"Kortrijksestw 283 Harelbeke West-Vlaanderen 8530",
    "addr:housenumber":"283",
    "addr:postcode":"8530",
    "iso:country":"BE",
    "sg:address":"Kortrijksestw 283",
    "sg:city":"Harelbeke",
    "sg:classifiers":[
        {
            "category":"Shopping",
            "subcategory":"Crafts & Fabrics",
            "type":"Retail Goods"
        }
    ],
    "sg:phone":"+32 56 71 24 13",
    "sg:postcode":"8530",
    "sg:province":"West-Vlaanderen",
    "sg:tags":[
        "textile",
        "clothing"
    ],
    "wof:name":"Jos Vanneste Nv",
    "wof:placetype":"venue"
},
  "geometry": {"coordinates":[3.2933158875,50.8438072205],"type":"Point"}
}