{
  "type": "Feature",
  "properties": {
    "iso:country":"BE",
    "sg:address":"Dennenlaan 46",
    "sg:city":"Brecht",
    "sg:orig_category":"D\u00e9corateurs d'int\u00e9rieur",
    "sg:phone":"+32 3 636 02 65",
    "sg:postcode":"2960",
    "sg:province":"Antwerpen",
    "wof:name":"Coenen M.",
    "wof:placetype":"venue"
},
  "geometry": {"coordinates":[4.585422039,51.2978630066],"type":"Point"}
}