{
  "type": "Feature",
  "properties": {
    "addr:full":"Rue Des Brasseurs 33 Tournai Hainaut 7500",
    "addr:housenumber":"33",
    "addr:postcode":"7500",
    "addr:street":"Rue Des Brasseurs",
    "iso:country":"BE",
    "sg:address":"Rue Des Brasseurs 33",
    "sg:city":"Tournai",
    "sg:classifiers":[
        {
            "category":"Building & Trades",
            "subcategory":"Electrical",
            "type":"Services"
        }
    ],
    "sg:phone":"+32 69 21 44 28",
    "sg:postcode":"7500",
    "sg:province":"Hainaut",
    "sg:tags":[
        "electric",
        "-",
        "housewiring",
        "contractor"
    ],
    "wof:name":"Wincq R",
    "wof:placetype":"venue"
},
  "geometry": {"coordinates":[3.4022119045,50.6152877808],"type":"Point"}
}