{
  "type": "Feature",
  "properties": {
    "iso:country":"BE",
    "sg:address":"Chemin De L'aubligneux 12",
    "sg:city":"Couvin",
    "sg:classifiers":[
        {
            "category":"Cafe",
            "type":"Food & Drink"
        }
    ],
    "sg:phone":"+32 60 34 50 94",
    "sg:postcode":"5660",
    "sg:province":"Namur",
    "sg:tags":[
        "caf\u00e9s"
    ],
    "wof:name":"Andree Paquet",
    "wof:placetype":"venue"
},
  "geometry": {"coordinates":[4.4358949661,50.0579719543],"type":"Point"}
}