{
  "type": "Feature",
  "properties": {
    "addr:full":"Rue De L'ecole 115 Voeren/fourons Limburg 3798",
    "addr:housenumber":"115",
    "addr:postcode":"3798",
    "addr:street":"Rue De L'Ecole",
    "iso:country":"BE",
    "sg:address":"Rue De L'ecole 115",
    "sg:city":"Voeren/fourons",
    "sg:classifiers":[
        {
            "category":"Organizations",
            "subcategory":"Community Association",
            "type":"Services"
        }
    ],
    "sg:phone":"+32 4 381 00 13",
    "sg:postcode":"3798",
    "sg:province":"Limburg",
    "sg:tags":[
        "personnel",
        "de",
        "placement",
        "publics",
        "s\u00e9lection"
    ],
    "wof:name":"Gemeentebestuur",
    "wof:placetype":"venue"
},
  "geometry": {"coordinates":[5.7698001862,50.761089325],"type":"Point"}
}