{
  "type": "Feature",
  "properties": {
    "addr:full":"Draaiboomstraat 32 Mol Antwerpen 2400",
    "addr:housenumber":"32",
    "addr:postcode":"2400",
    "addr:street":"Draaiboomstraat",
    "iso:country":"BE",
    "sg:address":"Draaiboomstraat 32",
    "sg:city":"Mol",
    "sg:classifiers":[
        {
            "category":"Shopping",
            "subcategory":"Clothing, Apparel, & Fashions",
            "type":"Retail Goods"
        }
    ],
    "sg:phone":"+32 14 31 77 16",
    "sg:postcode":"2400",
    "sg:province":"Antwerpen",
    "sg:tags":[
        "ondergoed",
        "lingerie"
    ],
    "wof:name":"Monique Vreys",
    "wof:placetype":"venue"
},
  "geometry": {"coordinates":[5.142288208,51.2119789124],"type":"Point"}
}