{
  "type": "Feature",
  "properties": {
    "iso:country":"BE",
    "sg:address":"Trixhe Aux Mini\u00e8res 1",
    "sg:city":"Aywaille",
    "sg:classifiers":[
        {
            "category":"Professional",
            "subcategory":"Art Services",
            "type":"Services"
        }
    ],
    "sg:phone":"+32 4 384 84 20",
    "sg:postcode":"4920",
    "sg:province":"Li\u00e8ge",
    "sg:tags":[
        "picture",
        "framer"
    ],
    "wof:name":"Espace Cadres",
    "wof:placetype":"venue"
},
  "geometry": {"coordinates":[5.6782069206,50.4738540649],"type":"Point"}
}