{
  "type": "Feature",
  "properties": {
    "iso:country":"BE",
    "sg:address":"Meersstraat 96",
    "sg:city":"Destelbergen",
    "sg:orig_category":"Entretien and r\u00e9parations de voitures",
    "sg:phone":"+32 9 230 78 88",
    "sg:postcode":"9070",
    "sg:province":"Oost-Vlaanderen",
    "wof:name":"Garage Vanlaecken",
    "wof:placetype":"venue"
},
  "geometry": {"coordinates":[3.7966780663,51.0384254456],"type":"Point"}
}