{
  "type": "Feature",
  "properties": {
    "iso:country":"BE",
    "sg:address":"Chauss\u00c9e Reine Astrid 33",
    "sg:city":"Braine-l\u00b4alleud",
    "sg:orig_category":"Slagers",
    "sg:phone":"+32 2 384 23 46",
    "sg:postcode":"1420",
    "sg:province":"Brabant Wallon",
    "wof:name":"Boucherie L\u00b4ardennaise",
    "wof:placetype":"venue"
},
  "geometry": {"coordinates":[4.3785018921,50.6857299805],"type":"Point"}
}