{
  "type": "Feature",
  "properties": {
    "iso:country":"BE",
    "sg:address":"Rue Jacques Vandervleet 33",
    "sg:city":"Bruxelles (jette)",
    "sg:classifiers":[
        {
            "category":"Communications",
            "subcategory":"Film & Video Production",
            "type":"Services"
        }
    ],
    "sg:phone":"+32 2 248 12 07",
    "sg:postcode":"1090",
    "sg:province":"Bruxelles-Capitale",
    "sg:tags":[
        "sound",
        "recording",
        "studio"
    ],
    "wof:name":"Ad Hoc Sound Services Sprl",
    "wof:placetype":"venue"
},
  "geometry": {"coordinates":[4.3354468346,50.8720550537],"type":"Point"}
}