{
  "type": "Feature",
  "properties": {
    "addr:full":"Bruggestraat 63 Menen West-Vlaanderen 8930",
    "addr:housenumber":"63",
    "addr:postcode":"8930",
    "addr:street":"Bruggestraat",
    "iso:country":"BE",
    "sg:address":"Bruggestraat 63",
    "sg:city":"Menen",
    "sg:classifiers":[
        {
            "category":"Social Services",
            "type":"Services"
        }
    ],
    "sg:phone":"+32 56 53 03 03",
    "sg:postcode":"8930",
    "sg:province":"West-Vlaanderen",
    "wof:name":"Eigen Woonst Vzw",
    "wof:placetype":"venue"
},
  "geometry": {"coordinates":[3.1226201057,50.7981452942],"type":"Point"}
}