{
  "type": "Feature",
  "properties": {
    "iso:country":"BE",
    "sg:address":"Koolmijnlaan 360",
    "sg:city":"Beringen",
    "sg:orig_category":"Herenkledingzaken Kleding",
    "sg:phone":"+32 11 42 29 18",
    "sg:postcode":"3581",
    "sg:province":"Limburg",
    "wof:name":"Herenkleding Moons",
    "wof:placetype":"venue"
},
  "geometry": {"coordinates":[5.2192339897,51.0776557922],"type":"Point"}
}