{
  "type": "Feature",
  "properties": {
    "iso:country":"BE",
    "sg:address":"Avenue Des D\u00c9mineurs 4",
    "sg:city":"Jette/jette",
    "sg:orig_category":"Salles de conf\u00e9rences and de r\u00e9ceptions",
    "sg:phone":"+32 2 422 07 11",
    "sg:postcode":"1090",
    "sg:province":"Bruxelles-Capitale",
    "wof:name":"Salle Chrystal",
    "wof:placetype":"venue"
},
  "geometry": {"coordinates":[4.3322410583,50.8792572021],"type":"Point"}
}