{
  "type": "Feature",
  "properties": {
    "addr:full":"Vismarkt 37 Lier Antwerpen 2500",
    "addr:housenumber":"37",
    "addr:postcode":"2500",
    "addr:street":"Vismarkt",
    "iso:country":"BE",
    "sg:address":"Vismarkt 37",
    "sg:city":"Lier",
    "sg:orig_category":"Avocats and conseillers juridiques",
    "sg:phone":"+32 3 480 11 17",
    "sg:postcode":"2500",
    "sg:province":"Antwerpen",
    "wof:name":"Birgit Hermans",
    "wof:placetype":"venue"
},
  "geometry": {"coordinates":[4.5719127655,51.1313400269],"type":"Point"}
}