{
  "type": "Feature",
  "properties": {
    "addr:full":"Lindenlaan 16c Evergem (ertvelde) Oost-Vlaanderen 9940",
    "addr:housenumber":"16c",
    "addr:postcode":"9940",
    "addr:street":"Lindenlaan;Ertvelde Oost-Vlaanderen",
    "iso:country":"BE",
    "sg:address":"Lindenlaan 16c",
    "sg:city":"Evergem (ertvelde)",
    "sg:classifiers":[
        {
            "category":"Banks & Credit Unions",
            "subcategory":"Bank",
            "type":"Services"
        }
    ],
    "sg:phone":"+32 9 344 29 67",
    "sg:postcode":"9940",
    "sg:province":"Oost-Vlaanderen",
    "sg:tags":[
        "savings-banks"
    ],
    "wof:name":"Dhooge-van Herreweghe",
    "wof:placetype":"venue"
},
  "geometry": {"coordinates":[3.7457458973,51.1774215698],"type":"Point"}
}