{
  "type": "Feature",
  "properties": {
    "addr:full":"Statiosstraat 94 Sint-niklaas Oost-Vlaanderen 9100",
    "addr:housenumber":"94",
    "addr:postcode":"9100",
    "addr:street":"Statiosstraat",
    "iso:country":"BE",
    "sg:address":"Statiosstraat 94",
    "sg:city":"Sint-niklaas",
    "sg:orig_category":"R\u00e9parations d'appareils \u00e9lectrom\u00e9nagers. Electrom\u00e9nager, t\u00e9l\u00e9visions and radios",
    "sg:phone":"+32 3 777 01 18",
    "sg:postcode":"9100",
    "sg:province":"Oost-Vlaanderen",
    "wof:name":"Handyman",
    "wof:placetype":"venue"
},
  "geometry": {"coordinates":[4.1419091225,51.1684188843],"type":"Point"}
}