{
  "type": "Feature",
  "properties": {
    "addr:full":"Rue Albert I 4 Engis Li\u00e8ge 4480",
    "addr:housenumber":"4",
    "addr:postcode":"4480",
    "addr:street":"Rue Albert I",
    "iso:country":"BE",
    "sg:address":"Rue Albert I 4",
    "sg:city":"Engis",
    "sg:classifiers":[
        {
            "category":"Shopping",
            "subcategory":"Florist",
            "type":"Retail Goods"
        }
    ],
    "sg:phone":"+32 4 275 18 88",
    "sg:postcode":"4480",
    "sg:province":"Li\u00e8ge",
    "wof:name":"Tendres Pens\u00e9es",
    "wof:placetype":"venue"
},
  "geometry": {"coordinates":[5.40538311,50.582359314],"type":"Point"}
}