{
  "type": "Feature",
  "properties": {
    "addr:full":"Stuivenbergstraat 20 Lede Oost-Vlaanderen 9340",
    "addr:housenumber":"20",
    "addr:postcode":"9340",
    "addr:street":"Stuivenbergstraat",
    "iso:country":"BE",
    "sg:address":"Stuivenbergstraat 20",
    "sg:city":"Lede",
    "sg:orig_category":"Astrologen, grafologen and mediums",
    "sg:phone":"+32 53 80 40 52",
    "sg:postcode":"9340",
    "sg:province":"Oost-Vlaanderen",
    "wof:name":"Urania Astrologie",
    "wof:placetype":"venue"
},
  "geometry": {"coordinates":[3.9526209831,50.9750709534],"type":"Point"}
}