{
  "type": "Feature",
  "properties": {
    "iso:country":"BE",
    "sg:address":"Berglaan 19",
    "sg:city":"Anzegem",
    "sg:orig_category":"Parfumeries",
    "sg:phone":"+32 56 68 91 97",
    "sg:postcode":"8570",
    "sg:province":"West-Vlaanderen",
    "wof:name":"Michelle Hardeman",
    "wof:placetype":"venue"
},
  "geometry": {"coordinates":[3.4743540287,50.830947876],"type":"Point"}
}