{
  "type": "Feature",
  "properties": {
    "addr:full":"Place De L'abbaye 15 Comines-warneton (warneton) Hainaut 7784",
    "addr:housenumber":"15",
    "addr:postcode":"7784",
    "addr:street":"Place De L'Abbaye",
    "iso:country":"BE",
    "sg:address":"Place De L'abbaye 15",
    "sg:city":"Comines-warneton (warneton)",
    "sg:classifiers":[
        {
            "category":"Insurance",
            "subcategory":"Insurance Agent",
            "type":"Services"
        }
    ],
    "sg:phone":"+32 56 55 90 55",
    "sg:postcode":"7784",
    "sg:province":"Hainaut",
    "sg:tags":[
        "broker"
    ],
    "wof:name":"Dufour-floor",
    "wof:placetype":"venue"
},
  "geometry": {"coordinates":[2.94947505,50.7527656555],"type":"Point"}
}