{
  "type": "Feature",
  "properties": {
    "addr:full":"Rue D'houdremont 38 Vresse-sur-semois Namur 5550",
    "addr:housenumber":"38",
    "addr:postcode":"5550",
    "addr:street":"Rue D'Houdremont",
    "iso:country":"BE",
    "sg:address":"Rue D'houdremont 38",
    "sg:city":"Vresse-sur-semois",
    "sg:orig_category":"Vins Fab. Distilleries",
    "sg:phone":"+32 61 50 11 33",
    "sg:postcode":"5550",
    "sg:province":"Namur",
    "wof:name":"La Chiquetterie",
    "wof:placetype":"venue"
},
  "geometry": {"coordinates":[4.9198732376,49.925994873],"type":"Point"}
}