{
  "type": "Feature",
  "properties": {
    "addr:full":"Rue De Champ 2ba Eupen Li\u00e8ge 4701",
    "addr:postcode":"4701",
    "addr:street":"Rue De Champ 2Ba",
    "iso:country":"BE",
    "sg:address":"Rue De Champ 2ba",
    "sg:city":"Eupen",
    "sg:classifiers":[
        {
            "category":"Arena",
            "subcategory":"Sports Club",
            "type":"Entertainment"
        }
    ],
    "sg:phone":"+32 87 74 04 24",
    "sg:postcode":"4701",
    "sg:province":"Li\u00e8ge",
    "sg:tags":[
        "de"
    ],
    "wof:name":"H.c. Raeren 76",
    "wof:placetype":"venue"
},
  "geometry": {"coordinates":[6.0461649895,50.6460838318],"type":"Point"}
}