{
  "type": "Feature",
  "properties": {
    "addr:full":"Grote Markt 20 Dendermonde Oost-Vlaanderen 9200",
    "addr:housenumber":"20",
    "addr:postcode":"9200",
    "addr:street":"Grote Markt;Oost-Vlaanderen",
    "iso:country":"BE",
    "sg:address":"Grote Markt 20",
    "sg:city":"Dendermonde",
    "sg:classifiers":[
        {
            "category":"Bars & Pubs",
            "type":"Food & Drink"
        }
    ],
    "sg:phone":"+32 52 22 44 81",
    "sg:postcode":"9200",
    "sg:province":"Oost-Vlaanderen",
    "sg:tags":[
        "tavern"
    ],
    "wof:name":"Barley's",
    "wof:placetype":"venue"
},
  "geometry": {"coordinates":[4.0980501175,51.0307807922],"type":"Point"}
}