{
  "type": "Feature",
  "properties": {
    "iso:country":"BE",
    "sg:address":"Oude Desselgemstraat 11",
    "sg:city":"Waregem",
    "sg:orig_category":"Graphologues, astrologues, voyants and radiesth\u00e9sistes",
    "sg:phone":"+32 56 61 35 38",
    "sg:postcode":"8790",
    "sg:province":"West-Vlaanderen",
    "wof:name":"Enirac",
    "wof:placetype":"venue"
},
  "geometry": {"coordinates":[3.4098670483,50.8808555603],"type":"Point"}
}