{
  "type": "Feature",
  "properties": {
    "iso:country":"BE",
    "sg:address":"Rue Du Noly 34",
    "sg:city":"La Bruy\u00e8re (saint-denis)",
    "sg:classifiers":[
        {
            "category":"Home & Garden",
            "subcategory":"Building Materials",
            "type":"Retail Goods"
        }
    ],
    "sg:phone":"+32 81 56 96 13",
    "sg:postcode":"5081",
    "sg:province":"Namur",
    "sg:tags":[
        "window"
    ],
    "wof:name":"Leroy F",
    "wof:placetype":"venue"
},
  "geometry": {"coordinates":[4.7783169746,50.5321960449],"type":"Point"}
}