{
  "type": "Feature",
  "properties": {
    "addr:full":"Mechelsesteenweg 219 Lier Antwerpen 2500",
    "addr:housenumber":"219",
    "addr:postcode":"2500",
    "addr:street":"Mechelsesteenweg",
    "iso:country":"BE",
    "sg:address":"Mechelsesteenweg 219",
    "sg:city":"Lier",
    "sg:orig_category":"Meubles D\u00e9taillants, Am\u00e9nagement de B\u00e2timents et de Cuisines. D\u00e9corateurs d'int\u00e9rieur. Fournitures d",
    "sg:phone":"+32 3 489 10 63",
    "sg:postcode":"2500",
    "sg:province":"Antwerpen",
    "wof:name":"Tri Offis",
    "wof:placetype":"venue"
},
  "geometry": {"coordinates":[4.5664000511,51.1316413879],"type":"Point"}
}