{
  "type": "Feature",
  "properties": {
    "iso:country":"BE",
    "sg:address":"Sint-andriessteenweg 71",
    "sg:city":"Zottegem",
    "sg:orig_category":"Schoonheidssalons",
    "sg:phone":"+32 9 360 04 67",
    "sg:postcode":"9620",
    "sg:province":"Oost-Vlaanderen",
    "wof:name":"Simone Merchiers",
    "wof:placetype":"venue"
},
  "geometry": {"coordinates":[3.7974669933,50.8680763245],"type":"Point"}
}