{
  "type": "Feature",
  "properties": {
    "iso:country":"BE",
    "sg:address":"Stormestraat 112",
    "sg:city":"Waregem",
    "sg:orig_category":"Articles pour b\u00e9b\u00e9s. V\u00eatements pour b\u00e9b\u00e9s and enfants. V\u00eatements pour Dames",
    "sg:phone":"+32 56 61 12 10",
    "sg:postcode":"8790",
    "sg:province":"West-Vlaanderen",
    "wof:name":"Boboli",
    "wof:placetype":"venue"
},
  "geometry": {"coordinates":[3.4278640747,50.8855476379],"type":"Point"}
}