{
  "type": "Feature",
  "properties": {
    "iso:country":"BE",
    "sg:address":"Antwerpsestraat 9",
    "sg:city":"Boom",
    "sg:orig_category":"Apotheken",
    "sg:phone":"+32 3 888 02 67",
    "sg:postcode":"2850",
    "sg:province":"Antwerpen",
    "wof:name":"Theo Van Assche",
    "wof:placetype":"venue"
},
  "geometry": {"coordinates":[4.365860939,51.0865020752],"type":"Point"}
}