{
  "type": "Feature",
  "properties": {
    "iso:country":"BE",
    "sg:address":"Donkersteeg 20",
    "sg:city":"Gent",
    "sg:orig_category":"V\u00eatements pour Dames. Chaussures",
    "sg:phone":"+32 9 224 41 42",
    "sg:postcode":"9000",
    "sg:province":"Oost-Vlaanderen",
    "wof:name":"Huis Burata Bis",
    "wof:placetype":"venue"
},
  "geometry": {"coordinates":[3.7230908871,51.0545768738],"type":"Point"}
}