{
  "type": "Feature",
  "properties": {
    "iso:country":"BE",
    "sg:address":"Rue Du Chemin De Fer 10",
    "sg:city":"Ecaussinnes",
    "sg:orig_category":"Sportclubs",
    "sg:phone":"+32 67 44 38 35",
    "sg:postcode":"7190",
    "sg:province":"Hainaut",
    "wof:name":"V.t. Braine-le-comte",
    "wof:placetype":"venue"
},
  "geometry": {"coordinates":[4.1752748489,50.548210144],"type":"Point"}
}