{
  "type": "Feature",
  "properties": {
    "addr:full":"Rue Des D\u00c9port\u00c9s 104 Jurbise Hainaut 7050",
    "addr:housenumber":"104",
    "addr:postcode":"7050",
    "addr:street":"Rue Des De\u0301Porte\u0301S",
    "iso:country":"BE",
    "sg:address":"Rue Des D\u00c9port\u00c9s 104",
    "sg:city":"Jurbise",
    "sg:orig_category":"Paramedische behandelingen",
    "sg:phone":"+32 65 22 65 29",
    "sg:postcode":"7050",
    "sg:province":"Hainaut",
    "wof:name":"J. Lagneaux",
    "wof:placetype":"venue"
},
  "geometry": {"coordinates":[3.9499709606,50.5130081177],"type":"Point"}
}