{
  "type": "Feature",
  "properties": {
    "addr:full":"Boulevard Leopold Iii 142 P\u00e9ruwelz Hainaut 7600",
    "addr:housenumber":"142",
    "addr:postcode":"7600",
    "addr:street":"Boulevard Leopold Iii",
    "iso:country":"BE",
    "sg:address":"Boulevard Leopold Iii 142",
    "sg:city":"P\u00e9ruwelz",
    "sg:classifiers":[
        {
            "category":"Health Services",
            "subcategory":"Nursing And Care Facility",
            "type":"Services"
        }
    ],
    "sg:phone":"+32 69 77 69 00",
    "sg:postcode":"7600",
    "sg:province":"Hainaut",
    "sg:tags":[
        "home",
        "rest"
    ],
    "wof:name":"Logis (r\u00e9sidence)",
    "wof:placetype":"venue"
},
  "geometry": {"coordinates":[3.5996870995,50.5019683838],"type":"Point"}
}