{
  "type": "Feature",
  "properties": {
    "iso:country":"BE",
    "sg:address":"Pater Pellensstraat 57",
    "sg:city":"Neerpelt",
    "sg:classifiers":[
        {
            "category":"Building & Trades",
            "subcategory":"Construction",
            "type":"Services"
        }
    ],
    "sg:phone":"+32 11 66 42 60",
    "sg:postcode":"3910",
    "sg:province":"Limburg",
    "sg:tags":[
        "stair"
    ],
    "wof:name":"Rubri",
    "wof:placetype":"venue"
},
  "geometry": {"coordinates":[5.4637751579,51.2333297729],"type":"Point"}
}