{
  "type": "Feature",
  "properties": {
    "addr:full":"Rue Grande 157 Dinant Namur 5500",
    "addr:housenumber":"157",
    "addr:postcode":"5500",
    "addr:street":"Rue Grande",
    "iso:country":"BE",
    "sg:address":"Rue Grande 157",
    "sg:city":"Dinant",
    "sg:classifiers":[
        {
            "category":"Shopping",
            "subcategory":"Gifts & Souvenirs",
            "type":"Retail Goods"
        }
    ],
    "sg:phone":"+32 82 22 72 21",
    "sg:postcode":"5500",
    "sg:province":"Namur",
    "sg:tags":[
        "-"
    ],
    "wof:name":"Aladin",
    "wof:placetype":"venue"
},
  "geometry": {"coordinates":[4.9129309654,50.2604789734],"type":"Point"}
}