{
  "type": "Feature",
  "properties": {
    "iso:country":"BE",
    "sg:address":"Rue M. Lespagne 11",
    "sg:city":"Hastiere",
    "sg:orig_category":"Souvenirs and objets artisanaux. Fleurs and plantes",
    "sg:phone":"+32 82 64 63 81",
    "sg:postcode":"5540",
    "sg:province":"Namur",
    "wof:name":"Aux Joyeux Pr\u00c9sents",
    "wof:placetype":"venue"
},
  "geometry": {"coordinates":[4.8241977692,50.2159805298],"type":"Point"}
}