{
  "type": "Feature",
  "properties": {
    "iso:country":"BE",
    "sg:address":"Rue De Dinant 53",
    "sg:city":"Dinant",
    "sg:orig_category":"Installation de menuiserie en bois and plastique",
    "sg:phone":"+32 82 74 51 34",
    "sg:postcode":"5500",
    "sg:province":"Namur",
    "wof:name":"Marc Pousseur",
    "wof:placetype":"venue"
},
  "geometry": {"coordinates":[4.8956999779,50.2041702271],"type":"Point"}
}