{
  "type": "Feature",
  "properties": {
    "addr:full":"Christinastraat 55 Oostende West-Vlaanderen 8400",
    "addr:housenumber":"55",
    "addr:postcode":"8400",
    "addr:street":"Christinastraat",
    "iso:country":"BE",
    "sg:address":"Christinastraat 55",
    "sg:city":"Oostende",
    "sg:orig_category":"Kapsalons",
    "sg:phone":"+32 59 51 87 58",
    "sg:postcode":"8400",
    "sg:province":"West-Vlaanderen",
    "wof:name":"Kapsalon De Witte Dirk",
    "wof:placetype":"venue"
},
  "geometry": {"coordinates":[2.916629076,51.2309417725],"type":"Point"}
}