{
  "type": "Feature",
  "properties": {
    "iso:country":"BE",
    "sg:address":"Route De Hamoir 10",
    "sg:city":"Durbuy (tohogne)",
    "sg:classifiers":[
        {
            "category":"Health Services",
            "subcategory":"Doctor",
            "type":"Services"
        }
    ],
    "sg:phone":"+32 86 21 32 04",
    "sg:postcode":"6941",
    "sg:province":"Luxembourg",
    "sg:tags":[
        "medicinephysicians",
        "surgeon"
    ],
    "wof:name":"Hogge J-m",
    "wof:placetype":"venue"
},
  "geometry": {"coordinates":[5.5069198608,50.4064331055],"type":"Point"}
}