{
  "type": "Feature",
  "properties": {
    "iso:country":"BE",
    "sg:address":"Hoogland 22",
    "sg:city":"Borsbeek",
    "sg:orig_category":"Producteurs de l\u00e9gumes",
    "sg:phone":"+32 3 321 60 81",
    "sg:postcode":"2150",
    "sg:province":"Antwerpen",
    "wof:name":"Willy Lauwers",
    "wof:placetype":"venue"
},
  "geometry": {"coordinates":[4.4972648621,51.185043335],"type":"Point"}
}