{
  "type": "Feature",
  "properties": {
    "iso:country":"BE",
    "sg:address":"Heuveldreef 4",
    "sg:city":"Wuustwezel",
    "sg:classifiers":[
        {
            "category":"Banks & Credit Unions",
            "subcategory":"Bureau De Change",
            "type":"Services"
        }
    ],
    "sg:phone":"+32 3 669 88 28",
    "sg:postcode":"2990",
    "sg:province":"Antwerpen",
    "sg:tags":[
        "regulating",
        "system"
    ],
    "wof:name":"A.b.s. Elektro",
    "wof:placetype":"venue"
},
  "geometry": {"coordinates":[4.5430431366,51.3884429932],"type":"Point"}
}