{
  "type": "Feature",
  "properties": {
    "addr:full":"Lozenberg 18 Zaventem (sint-stevens-woluwe) Vlaams-Brabant 1932",
    "addr:housenumber":"18",
    "addr:postcode":"1932",
    "addr:street":"Lozenberg",
    "iso:country":"BE",
    "sg:address":"Lozenberg 18",
    "sg:city":"Zaventem (sint-stevens-woluwe)",
    "sg:classifiers":[
        {
            "category":"Science Facility",
            "type":"Public Place"
        }
    ],
    "sg:phone":"+32 2 720 69 00",
    "sg:postcode":"1932",
    "sg:province":"Vlaams-Brabant",
    "sg:tags":[
        "-",
        "management",
        "data",
        "processing"
    ],
    "wof:name":"Fdm Group",
    "wof:placetype":"venue"
},
  "geometry": {"coordinates":[4.4598970413,50.8684883118],"type":"Point"}
}