{
  "type": "Feature",
  "properties": {
    "iso:country":"BE",
    "sg:address":"Rue De La Glaci\u00e8re 11",
    "sg:city":"Bruxelles (saint-gilles)",
    "sg:classifiers":[
        {
            "category":"Manufacturing",
            "subcategory":"Food",
            "type":"Manufacturing & Wholesale Goods"
        }
    ],
    "sg:phone":"+32 2 539 06 16",
    "sg:postcode":"1060",
    "sg:province":"Bruxelles-Capitale",
    "sg:tags":[
        "equipment"
    ],
    "wof:name":"Frisque",
    "wof:placetype":"venue"
},
  "geometry": {"coordinates":[4.3517131805,50.8229789734],"type":"Point"}
}