{
  "type": "Feature",
  "properties": {
    "iso:country":"BE",
    "sg:address":"Rue Du Tram 20",
    "sg:city":"Saint-leger",
    "sg:orig_category":"Eleveurs de bovins",
    "sg:phone":"+32 63 22 61 63",
    "sg:postcode":"6747",
    "sg:province":"Luxembourg",
    "wof:name":"Leonard",
    "wof:placetype":"venue"
},
  "geometry": {"coordinates":[5.7161149979,49.6187477112],"type":"Point"}
}