{
  "type": "Feature",
  "properties": {
    "iso:country":"BE",
    "sg:address":"Wellingstraat 104",
    "sg:city":"Beernem",
    "sg:orig_category":"Goederenvervoer over de weg Varkenskwekers",
    "sg:phone":"+32 50 78 82 73",
    "sg:postcode":"8730",
    "sg:province":"West-Vlaanderen",
    "wof:name":"Robert Verrewaere",
    "wof:placetype":"venue"
},
  "geometry": {"coordinates":[3.3094520569,51.1289596558],"type":"Point"}
}