{
  "type": "Feature",
  "properties": {
    "iso:country":"BE",
    "sg:address":"Kempenstraat 32",
    "sg:city":"Kasterlee",
    "sg:classifiers":[
        {
            "category":"Education",
            "subcategory":"School",
            "type":"Public Place"
        }
    ],
    "sg:phone":"+32 14 85 00 52",
    "sg:postcode":"2460",
    "sg:province":"Antwerpen",
    "sg:tags":[
        "secondary"
    ],
    "wof:name":"Buso De Mast",
    "wof:placetype":"venue"
},
  "geometry": {"coordinates":[4.9590148926,51.235912323],"type":"Point"}
}