{
  "type": "Feature",
  "properties": {
    "addr:full":"Kasteelstraat 58 Retie Antwerpen 2470",
    "addr:housenumber":"58",
    "addr:postcode":"2470",
    "addr:street":"Kasteelstraat",
    "iso:country":"BE",
    "sg:address":"Kasteelstraat 58",
    "sg:city":"Retie",
    "sg:classifiers":[
        {
            "category":"Bars & Pubs",
            "type":"Food & Drink"
        }
    ],
    "sg:phone":"+32 14 37 52 02",
    "sg:postcode":"2470",
    "sg:province":"Antwerpen",
    "sg:tags":[
        "tavern"
    ],
    "wof:name":"De Klyn Hoeve",
    "wof:placetype":"venue"
},
  "geometry": {"coordinates":[5.072851181,51.2663154602],"type":"Point"}
}