{
  "type": "Feature",
  "properties": {
    "iso:country":"BE",
    "sg:address":"Le Celly 2",
    "sg:city":"Sainte-ode",
    "sg:orig_category":"Ziekenhuizen and zorginstellingen Ziekenvervoer",
    "sg:phone":"+32 84 22 51 11",
    "sg:postcode":"6680",
    "sg:province":"Luxembourg",
    "wof:name":"Centre Hospitalier De St.ode",
    "wof:placetype":"venue"
},
  "geometry": {"coordinates":[5.5126600266,50.0667686462],"type":"Point"}
}