{
  "type": "Feature",
  "properties": {
    "iso:country":"BE",
    "sg:address":"Ieperstraat 74",
    "sg:city":"Tielt",
    "sg:classifiers":[
        {
            "category":"Insurance",
            "subcategory":"Insurance Agent",
            "type":"Services"
        }
    ],
    "sg:phone":"+32 51 42 40 20",
    "sg:postcode":"8700",
    "sg:province":"West-Vlaanderen",
    "sg:tags":[
        "broker"
    ],
    "wof:name":"Van Daele & Co Nv",
    "wof:placetype":"venue"
},
  "geometry": {"coordinates":[3.3225369453,50.998085022],"type":"Point"}
}