{
  "type": "Feature",
  "properties": {
    "addr:full":"Kortrijksesteenweg 209 Sint-martens-latem Oost-Vlaanderen 9830",
    "addr:housenumber":"209",
    "addr:postcode":"9830",
    "addr:street":"Kortrijksesteenweg",
    "iso:country":"BE",
    "sg:address":"Kortrijksesteenweg 209",
    "sg:city":"Sint-martens-latem",
    "sg:orig_category":"Werk and personeelsselectie",
    "sg:phone":"+32 9 281 13 86",
    "sg:postcode":"9830",
    "sg:province":"Oost-Vlaanderen",
    "wof:name":"Ago",
    "wof:placetype":"venue"
},
  "geometry": {"coordinates":[3.6298859119,51.0073204041],"type":"Point"}
}