{
  "type": "Feature",
  "properties": {
    "iso:country":"BE",
    "sg:address":"Krijgslaan 188",
    "sg:city":"Gent",
    "sg:classifiers":[
        {
            "category":"Professional",
            "subcategory":"Engineering",
            "type":"Services"
        }
    ],
    "sg:phone":"+32 9 220 01 26",
    "sg:postcode":"9000",
    "sg:province":"Oost-Vlaanderen",
    "sg:tags":[
        "-"
    ],
    "wof:name":"Hydro-rs Bvba",
    "wof:placetype":"venue"
},
  "geometry": {"coordinates":[3.7158839703,51.0276985168],"type":"Point"}
}