{
  "type": "Feature",
  "properties": {
    "iso:country":"BE",
    "sg:address":"Zeypestraat 26",
    "sg:city":"Kampenhout",
    "sg:orig_category":"Sportcentra Sportclubs",
    "sg:phone":"+32 16 65 99 75",
    "sg:postcode":"1910",
    "sg:province":"Vlaams-Brabant",
    "wof:name":"Sporthal De Zeype",
    "wof:placetype":"venue"
},
  "geometry": {"coordinates":[4.5643959045,50.9479446411],"type":"Point"}
}