{
  "type": "Feature",
  "properties": {
    "iso:country":"BE",
    "sg:address":"Ter Merenlaan 50",
    "sg:city":"Zaventem",
    "sg:classifiers":[
        {
            "category":"Arena",
            "subcategory":"Sports Club",
            "type":"Entertainment"
        }
    ],
    "sg:phone":"+32 2 305 40 47",
    "sg:postcode":"1930",
    "sg:province":"Vlaams-Brabant",
    "sg:tags":[
        "terrain",
        "hors",
        "de",
        "installation",
        "sportifs"
    ],
    "wof:name":"K.v.w. Woluwe",
    "wof:placetype":"venue"
},
  "geometry": {"coordinates":[4.4816951752,50.8783149719],"type":"Point"}
}