{
  "type": "Feature",
  "properties": {
    "iso:country":"BE",
    "sg:address":"Eikstraat 28",
    "sg:city":"Roeselare",
    "sg:orig_category":"Kapsalons",
    "sg:phone":"+32 51 22 54 79",
    "sg:postcode":"8800",
    "sg:province":"West-Vlaanderen",
    "wof:name":"D. Delie",
    "wof:placetype":"venue"
},
  "geometry": {"coordinates":[3.1107690334,50.9352226257],"type":"Point"}
}