{
  "type": "Feature",
  "properties": {
    "addr:full":"Briekhoekstraat 15 Wervik West-Vlaanderen 8940",
    "addr:housenumber":"15",
    "addr:postcode":"8940",
    "addr:street":"Briekhoekstraat",
    "iso:country":"BE",
    "sg:address":"Briekhoekstraat 15",
    "sg:city":"Wervik",
    "sg:orig_category":"Meubelzaken, woning- and keukeninrichting",
    "sg:phone":"+32 56 31 14 83",
    "sg:postcode":"8940",
    "sg:province":"West-Vlaanderen",
    "wof:name":"Willem Bruggeman",
    "wof:placetype":"venue"
},
  "geometry": {"coordinates":[3.0336670876,50.7763977051],"type":"Point"}
}