{
  "type": "Feature",
  "properties": {
    "iso:country":"BE",
    "sg:address":"Pl. Duchesse De Brabant 38",
    "sg:city":"Sint-jans-molenbeek/molenbeek-saint-jean",
    "sg:orig_category":"Installation de menuiserie en bois and plastique. Travail and traitement du bois",
    "sg:phone":"+32 2 410 50 34",
    "sg:postcode":"1080",
    "sg:province":"Bruxelles-Capitale",
    "wof:name":"Advanced Build. Technics",
    "wof:placetype":"venue"
},
  "geometry": {"coordinates":[4.3302330971,50.8497467041],"type":"Point"}
}