{
  "type": "Feature",
  "properties": {
    "addr:full":"Markt 13b5 Gistel West-Vlaanderen 8470",
    "addr:housenumber":"13b5",
    "addr:postcode":"8470",
    "addr:street":"Markt",
    "iso:country":"BE",
    "sg:address":"Markt 13b5",
    "sg:city":"Gistel",
    "sg:classifiers":[
        {
            "category":"Cafe",
            "type":"Food & Drink"
        }
    ],
    "sg:phone":"+32 59 27 97 51",
    "sg:postcode":"8470",
    "sg:province":"West-Vlaanderen",
    "sg:tags":[
        "caf\u00e9s"
    ],
    "wof:name":"Margaretha Glacz",
    "wof:placetype":"venue"
},
  "geometry": {"coordinates":[2.9675819874,51.1561508179],"type":"Point"}
}