{
  "type": "Feature",
  "properties": {
    "iso:country":"BE",
    "sg:address":"Driekerkenstraat 103",
    "sg:city":"Kortrijk",
    "sg:classifiers":[
        {
            "category":"Cafe",
            "type":"Food & Drink"
        }
    ],
    "sg:phone":"+32 56 35 52 13",
    "sg:postcode":"8501",
    "sg:province":"West-Vlaanderen",
    "sg:tags":[
        "caf\u00e9s"
    ],
    "wof:name":"Caf\u00c9 De Nieuwe Brug",
    "wof:placetype":"venue"
},
  "geometry": {"coordinates":[3.230576992,50.8193473816],"type":"Point"}
}