{
  "type": "Feature",
  "properties": {
    "addr:full":"Kasteelstraat 76a Lichtervelde West-Vlaanderen 8810",
    "addr:housenumber":"76a",
    "addr:postcode":"8810",
    "addr:street":"Kasteelstraat",
    "iso:country":"BE",
    "sg:address":"Kasteelstraat 76a",
    "sg:city":"Lichtervelde",
    "sg:orig_category":"Afbraak- and draineerwerken",
    "sg:phone":"+32 51 72 37 80",
    "sg:postcode":"8810",
    "sg:province":"West-Vlaanderen",
    "wof:name":"Tack Georges",
    "wof:placetype":"venue"
},
  "geometry": {"coordinates":[3.1476149559,51.0456237793],"type":"Point"}
}