{
  "type": "Feature",
  "properties": {
    "iso:country":"BE",
    "sg:address":"Sint-truidersteenweg 25",
    "sg:city":"Tongeren",
    "sg:classifiers":[
        {
            "category":"Health Services",
            "subcategory":"Health Practitioner",
            "type":"Services"
        }
    ],
    "sg:phone":"+32 12 23 91 67",
    "sg:postcode":"3700",
    "sg:province":"Limburg",
    "sg:tags":[
        "physiotherapist"
    ],
    "wof:name":"Simon Bert",
    "wof:placetype":"venue"
},
  "geometry": {"coordinates":[5.4573287964,50.7795600891],"type":"Point"}
}