{
  "type": "Feature",
  "properties": {
    "addr:full":"Kerkplein 7 Box 5 Lanaken Limburg 3620",
    "addr:housenumber":"7;5",
    "addr:postcode":"3620",
    "addr:street":"Kerkplein;Box",
    "iso:country":"BE",
    "sg:address":"Kerkplein 7 Box 5",
    "sg:city":"Lanaken",
    "sg:classifiers":[
        {
            "category":"Personal",
            "subcategory":"Beauty Salon",
            "type":"Services"
        }
    ],
    "sg:phone":"+32 89 72 39 04",
    "sg:postcode":"3620",
    "sg:province":"Limburg",
    "wof:name":"Nine Inch Nails Vof",
    "wof:placetype":"venue"
},
  "geometry": {"coordinates":[5.6335458755,50.8637809753],"type":"Point"}
}