{
  "type": "Feature",
  "properties": {
    "iso:country":"BE",
    "sg:address":"Bornestraat 60",
    "sg:city":"Leuven",
    "sg:classifiers":[
        {
            "category":"Autos & Motor Vehicles",
            "subcategory":"Fuel & Gas Station",
            "type":"Retail Goods"
        }
    ],
    "sg:phone":"+32 16 22 70 86",
    "sg:postcode":"3012",
    "sg:province":"Vlaams-Brabant",
    "sg:tags":[
        "stations-service",
        "carburants"
    ],
    "wof:name":"Josephina Van Den Ende",
    "wof:placetype":"venue"
},
  "geometry": {"coordinates":[4.6996049881,50.9069442749],"type":"Point"}
}