{
  "type": "Feature",
  "properties": {
    "addr:full":"Rue De La Gland\u00c9e 13 Seraing Li\u00e8ge 4100",
    "addr:housenumber":"13",
    "addr:postcode":"4100",
    "addr:street":"Rue De La Glande\u0301E",
    "iso:country":"BE",
    "sg:address":"Rue De La Gland\u00c9e 13",
    "sg:city":"Seraing",
    "sg:orig_category":"Apotheken",
    "sg:phone":"+32 4 336 59 71",
    "sg:postcode":"4100",
    "sg:province":"Li\u00e8ge",
    "wof:name":"J Lestarquit",
    "wof:placetype":"venue"
},
  "geometry": {"coordinates":[5.4951329231,50.582118988],"type":"Point"}
}