{
  "type": "Feature",
  "properties": {
    "addr:full":"Visitatiestraat 158 Gent Oost-Vlaanderen 9040",
    "addr:housenumber":"158",
    "addr:postcode":"9040",
    "addr:street":"Visitatiestraat;Oost-Vlaanderen",
    "iso:country":"BE",
    "sg:address":"Visitatiestraat 158",
    "sg:city":"Gent",
    "sg:orig_category":"Krantenuitgeverijen Tijdschriftenuitgeverijen",
    "sg:phone":"+32 9 281 14 70",
    "sg:postcode":"9040",
    "sg:province":"Oost-Vlaanderen",
    "wof:name":"Uitgeverij Weka",
    "wof:placetype":"venue"
},
  "geometry": {"coordinates":[3.7495889664,51.0674629211],"type":"Point"}
}