{
  "type": "Feature",
  "properties": {
    "iso:country":"BE",
    "sg:address":"Meerstraat 202",
    "sg:city":"Londerzeel",
    "sg:classifiers":[
        {
            "category":"Autos & Motor Vehicles",
            "subcategory":"Motorcycle Sales",
            "type":"Retail Goods"
        }
    ],
    "sg:phone":"+32 52 31 28 48",
    "sg:postcode":"1840",
    "sg:province":"Vlaams-Brabant",
    "sg:tags":[
        "scooter",
        "-",
        "moped"
    ],
    "wof:name":"T.o.v. Bvba",
    "wof:placetype":"venue"
},
  "geometry": {"coordinates":[4.3130950928,51.01404953],"type":"Point"}
}