{
  "type": "Feature",
  "properties": {
    "iso:country":"BE",
    "sg:address":"Blokstraat 101",
    "sg:city":"Sint-gillis-waas",
    "sg:orig_category":"Huisdieren and benodigdheden Royal Canin Tuinbenodigdheden",
    "sg:phone":"+32 3 770 50 51",
    "sg:postcode":"9170",
    "sg:province":"Oost-Vlaanderen",
    "wof:name":"Van Eynde-de Nocker",
    "wof:placetype":"venue"
},
  "geometry": {"coordinates":[4.1315331459,51.2233734131],"type":"Point"}
}