{
  "type": "Feature",
  "properties": {
    "addr:full":"Liersesteenweg 350 Mechelen Antwerpen 2800",
    "addr:housenumber":"350",
    "addr:postcode":"2800",
    "addr:street":"Liersesteenweg",
    "iso:country":"BE",
    "sg:address":"Liersesteenweg 350",
    "sg:city":"Mechelen",
    "sg:orig_category":"Taxi's Taxi's speciale diensten",
    "sg:phone":"+32 15 27 02 02",
    "sg:postcode":"2800",
    "sg:province":"Antwerpen",
    "wof:name":"Alfra Taxi",
    "wof:placetype":"venue"
},
  "geometry": {"coordinates":[4.4778847694,51.044670105],"type":"Point"}
}