{
  "type": "Feature",
  "properties": {
    "addr:full":"Marktstraat 2 Izegem West-Vlaanderen 8870",
    "addr:housenumber":"2",
    "addr:postcode":"8870",
    "addr:street":"Marktstraat",
    "iso:country":"BE",
    "sg:address":"Marktstraat 2",
    "sg:city":"Izegem",
    "sg:orig_category":"Banken and kredietinstellingen",
    "sg:phone":"+32 51 30 22 47",
    "sg:postcode":"8870",
    "sg:province":"West-Vlaanderen",
    "wof:name":"Kbc",
    "wof:placetype":"venue"
},
  "geometry": {"coordinates":[3.2150540352,50.9178314209],"type":"Point"}
}