{
  "type": "Feature",
  "properties": {
    "iso:country":"BE",
    "sg:address":"Grimstedestraat 53b1",
    "sg:city":"Turnhout",
    "sg:orig_category":"Instituts de beaut\u00e9",
    "sg:phone":"+32 14 43 63 06",
    "sg:postcode":"2300",
    "sg:province":"Antwerpen",
    "wof:name":"Nathalie Wertelaers",
    "wof:placetype":"venue"
},
  "geometry": {"coordinates":[4.9529800415,51.3178749084],"type":"Point"}
}