{
  "type": "Feature",
  "properties": {
    "iso:country":"BE",
    "sg:address":"Muggebergstr 8",
    "sg:city":"Diepenbeek",
    "sg:classifiers":[
        {
            "category":"Manufacturing",
            "subcategory":"Metals",
            "type":"Manufacturing & Wholesale Goods"
        }
    ],
    "sg:phone":"+32 11 33 38 87",
    "sg:postcode":"3590",
    "sg:province":"Limburg",
    "sg:tags":[
        "metallurgy",
        "metalworking",
        "processing"
    ],
    "wof:name":"Amag Nv",
    "wof:placetype":"venue"
},
  "geometry": {"coordinates":[5.4350309372,50.8997154236],"type":"Point"}
}