{
  "type": "Feature",
  "properties": {
    "addr:full":"Stationsstraat 53 Waregem West-Vlaanderen 8790",
    "addr:housenumber":"53",
    "addr:postcode":"8790",
    "addr:street":"Stationsstraat",
    "iso:country":"BE",
    "sg:address":"Stationsstraat 53",
    "sg:city":"Waregem",
    "sg:classifiers":[
        {
            "category":"Shopping",
            "subcategory":"Clothing, Apparel, & Fashions",
            "type":"Retail Goods"
        }
    ],
    "sg:phone":"+32 56 61 40 97",
    "sg:postcode":"8790",
    "sg:province":"West-Vlaanderen",
    "sg:tags":[
        "lady",
        "clothing",
        "-"
    ],
    "wof:name":"Salsa",
    "wof:placetype":"venue"
},
  "geometry": {"coordinates":[3.4304049015,50.8884162903],"type":"Point"}
}