{
  "type": "Feature",
  "properties": {
    "addr:full":"Bredabaan 1007 Brasschaat Antwerpen 2930",
    "addr:housenumber":"1007",
    "addr:postcode":"2930",
    "addr:street":"Bredabaan",
    "iso:country":"BE",
    "sg:address":"Bredabaan 1007",
    "sg:city":"Brasschaat",
    "sg:classifiers":[
        {
            "category":"Insurance",
            "subcategory":"Insurance Agent",
            "type":"Services"
        }
    ],
    "sg:phone":"+32 3 633 21 33",
    "sg:postcode":"2930",
    "sg:province":"Antwerpen",
    "sg:tags":[
        "food",
        "disinfectant",
        "industry",
        "cleaning"
    ],
    "wof:name":"Biesterfeld Belgium Nv",
    "wof:placetype":"venue"
},
  "geometry": {"coordinates":[4.5121498108,51.3122596741],"type":"Point"}
}