{
  "type": "Feature",
  "properties": {
    "iso:country":"BE",
    "sg:address":"Nieuwstraat 20a",
    "sg:city":"Berlare",
    "sg:orig_category":"Cr\u00e8ches and garderies d'enfants",
    "sg:phone":"+32 52 42 36 90",
    "sg:postcode":"9290",
    "sg:province":"Oost-Vlaanderen",
    "wof:name":"Kribbe Clubke",
    "wof:placetype":"venue"
},
  "geometry": {"coordinates":[4.0004448891,51.0275993347],"type":"Point"}
}