{
  "type": "Feature",
  "properties": {
    "iso:country":"BE",
    "sg:address":"Chauss\u00c9e D'enghien 209",
    "sg:city":"Soignies",
    "sg:orig_category":"Rundveehouders",
    "sg:phone":"+32 67 33 40 84",
    "sg:postcode":"7060",
    "sg:province":"Hainaut",
    "wof:name":"Duquesne Jose Et Luc",
    "wof:placetype":"venue"
},
  "geometry": {"coordinates":[4.063929081,50.5880508423],"type":"Point"}
}