{
  "type": "Feature",
  "properties": {
    "addr:full":"Rue De Beaufays 41 Sprimont Li\u00e8ge 4140",
    "addr:housenumber":"41",
    "addr:postcode":"4140",
    "addr:street":"Rue De Beaufays",
    "iso:country":"BE",
    "sg:address":"Rue De Beaufays 41",
    "sg:city":"Sprimont",
    "sg:orig_category":"Royal Canin. Animaux domestiques and accessoires",
    "sg:phone":"+32 475 51 22 53",
    "sg:postcode":"4140",
    "sg:province":"Li\u00e8ge",
    "wof:name":"Bricomarche Sprimont",
    "wof:placetype":"venue"
},
  "geometry": {"coordinates":[5.6573767662,50.5259513855],"type":"Point"}
}