{
  "type": "Feature",
  "properties": {
    "addr:full":"Bergelen 102 Wevelgem West-Vlaanderen 8560",
    "addr:housenumber":"102",
    "addr:postcode":"8560",
    "iso:country":"BE",
    "sg:address":"Bergelen 102",
    "sg:city":"Wevelgem",
    "sg:orig_category":"Ordinateurs and \u00e9quipement informatique. Entretien and r\u00e9parations de machines de bureau and ordinat",
    "sg:phone":"+32 56 42 29 65",
    "sg:postcode":"8560",
    "sg:province":"West-Vlaanderen",
    "wof:name":"Deka Computer",
    "wof:placetype":"venue"
},
  "geometry": {"coordinates":[3.1863958836,50.8377571106],"type":"Point"}
}