{
  "type": "Feature",
  "properties": {
    "iso:country":"BE",
    "sg:address":"Alfons Sifferstraat 44",
    "sg:city":"Zomergem",
    "sg:classifiers":[
        {
            "category":"Health Services",
            "subcategory":"Health Practitioner",
            "type":"Services"
        }
    ],
    "sg:phone":"+32 9 372 78 13",
    "sg:postcode":"9930",
    "sg:province":"Oost-Vlaanderen",
    "sg:tags":[
        "physiotherapist"
    ],
    "wof:name":"Seghers T",
    "wof:placetype":"venue"
},
  "geometry": {"coordinates":[3.5572659969,51.1161613464],"type":"Point"}
}