{
  "type": "Feature",
  "properties": {
    "addr:full":"Bolle Meersstraat 28 Ieper West-Vlaanderen 8906",
    "addr:housenumber":"28",
    "addr:postcode":"8906",
    "addr:street":"Meersstraat",
    "iso:country":"BE",
    "sg:address":"Bolle Meersstraat 28",
    "sg:city":"Ieper",
    "sg:orig_category":"Salles de conf\u00e9rences and de r\u00e9ceptions",
    "sg:phone":"+32 57 42 26 75",
    "sg:postcode":"8906",
    "sg:province":"West-Vlaanderen",
    "wof:name":"Salons Bollemeers",
    "wof:placetype":"venue"
},
  "geometry": {"coordinates":[2.8142209053,50.8856620789],"type":"Point"}
}