{
  "type": "Feature",
  "properties": {
    "iso:country":"BE",
    "sg:address":"Diestsesteenweg 245",
    "sg:city":"Tienen",
    "sg:orig_category":"Boekhouders",
    "sg:phone":"+32 16 81 51 58",
    "sg:postcode":"3300",
    "sg:province":"Vlaams-Brabant",
    "wof:name":"Gaston Gysenbergh",
    "wof:placetype":"venue"
},
  "geometry": {"coordinates":[4.9370031357,50.8205604553],"type":"Point"}
}