{
  "type": "Feature",
  "properties": {
    "addr:full":"Rue Des Fripiers 11 Mons Hainaut 7000",
    "addr:housenumber":"11",
    "addr:postcode":"7000",
    "addr:street":"Rue Des Fripiers;Hainaut",
    "iso:country":"BE",
    "sg:address":"Rue Des Fripiers 11",
    "sg:city":"Mons",
    "sg:classifiers":[
        {
            "category":"Restaurant",
            "type":"Food & Drink"
        }
    ],
    "sg:phone":"+32 65 35 10 35",
    "sg:postcode":"7000",
    "sg:province":"Hainaut",
    "wof:name":"Tea-room Sucr\u00c9-sal\u00c9",
    "wof:placetype":"venue"
},
  "geometry": {"coordinates":[3.9507529736,50.4521903992],"type":"Point"}
}