{
  "type": "Feature",
  "properties": {
    "addr:full":"Rue Du Tricointe 31ba Yvoir Namur 5530",
    "addr:housenumber":"31ba",
    "addr:postcode":"5530",
    "addr:street":"Rue Du Tricointe",
    "iso:country":"BE",
    "sg:address":"Rue Du Tricointe 31ba",
    "sg:city":"Yvoir",
    "sg:orig_category":"Cr\u00e9meries",
    "sg:phone":"+32 82 61 25 05",
    "sg:postcode":"5530",
    "sg:province":"Namur",
    "wof:name":"Francis Crommar",
    "wof:placetype":"venue"
},
  "geometry": {"coordinates":[4.8764591217,50.3309783936],"type":"Point"}
}