{
  "type": "Feature",
  "properties": {
    "addr:full":"Esplanade De L'avenir 1 Seraing Li\u00e8ge 4100",
    "addr:housenumber":"1",
    "addr:postcode":"4100",
    "addr:street":"Esplanade De L'Avenir",
    "iso:country":"BE",
    "sg:address":"Esplanade De L'avenir 1",
    "sg:city":"Seraing",
    "sg:orig_category":"Postkantoren Verzekeringsmakelaars and experts",
    "sg:phone":"+32 4 385 90 10",
    "sg:postcode":"4100",
    "sg:province":"Li\u00e8ge",
    "wof:name":"La Poste",
    "wof:placetype":"venue"
},
  "geometry": {"coordinates":[5.512887001,50.6097640991],"type":"Point"}
}