{
  "type": "Feature",
  "properties": {
    "addr:full":"Baalsesteenweg 48 Begijnendijk Vlaams-Brabant 3130",
    "addr:housenumber":"48",
    "addr:postcode":"3130",
    "addr:street":"Baalsesteenweg",
    "iso:country":"BE",
    "sg:address":"Baalsesteenweg 48",
    "sg:city":"Begijnendijk",
    "sg:orig_category":"Electrom\u00e9nager, t\u00e9l\u00e9visions and radios. R\u00e9parations d'appareils \u00e9lectrom\u00e9nagers",
    "sg:phone":"+32 16 53 30 83",
    "sg:postcode":"3130",
    "sg:province":"Vlaams-Brabant",
    "wof:name":"Elektro Diggi",
    "wof:placetype":"venue"
},
  "geometry": {"coordinates":[4.7781200409,51.0169448853],"type":"Point"}
}