{
  "type": "Feature",
  "properties": {
    "addr:full":"All\u00c9e Du Ch\u00c2teau 2 Verviers Li\u00e8ge 4800",
    "addr:housenumber":"2",
    "addr:postcode":"4800",
    "addr:street":"Alle\u0301E Du Cha\u0302Teau",
    "iso:country":"BE",
    "sg:address":"All\u00c9e Du Ch\u00c2teau 2",
    "sg:city":"Verviers",
    "sg:orig_category":"Installatie van houten of kunststof schrijnwerk",
    "sg:phone":"+32 87 33 63 88",
    "sg:postcode":"4800",
    "sg:province":"Li\u00e8ge",
    "wof:name":"Joseph Martin",
    "wof:placetype":"venue"
},
  "geometry": {"coordinates":[5.8333730698,50.6144523621],"type":"Point"}
}