{
  "type": "Feature",
  "properties": {
    "iso:country":"BE",
    "sg:address":"Legeweg 90",
    "sg:city":"Brugge",
    "sg:classifiers":[
        {
            "category":"Food & Beverages",
            "subcategory":"Fruits & Vegetables",
            "type":"Retail Goods"
        }
    ],
    "sg:phone":"+32 50 31 80 31",
    "sg:postcode":"8200",
    "sg:province":"West-Vlaanderen",
    "sg:tags":[
        "l\u00e9gumes",
        "gr"
    ],
    "wof:name":"Loyson",
    "wof:placetype":"venue"
},
  "geometry": {"coordinates":[3.2007598877,51.2049446106],"type":"Point"}
}