{
  "type": "Feature",
  "properties": {
    "iso:country":"BE",
    "sg:address":"Chauss\u00c9e De Huy 1",
    "sg:city":"Hamois",
    "sg:classifiers":[
        {
            "category":"Wholesale",
            "subcategory":"Farm Supplies",
            "type":"Manufacturing & Wholesale Goods"
        }
    ],
    "sg:phone":"+32 83 69 94 24",
    "sg:postcode":"5360",
    "sg:province":"Namur",
    "sg:tags":[
        "machine",
        "agricoles",
        "mat\u00e9riel",
        "gr"
    ],
    "wof:name":"Van Hooydonk P. & E.",
    "wof:placetype":"venue"
},
  "geometry": {"coordinates":[5.0373048782,50.3472213745],"type":"Point"}
}