{
  "type": "Feature",
  "properties": {
    "iso:country":"BE",
    "sg:address":"Koninklijke Jachtstraat 23",
    "sg:city":"Oudergem/auderghem",
    "sg:orig_category":"Artsen and specialisten",
    "sg:phone":"+32 2 649 86 29",
    "sg:postcode":"1160",
    "sg:province":"Bruxelles-Capitale",
    "wof:name":"Yves Durant",
    "wof:placetype":"venue"
},
  "geometry": {"coordinates":[4.4030990601,50.8215827942],"type":"Point"}
}