{
  "type": "Feature",
  "properties": {
    "iso:country":"BE",
    "sg:address":"Sint-gertrudisplein 14",
    "sg:city":"Bilzen (beverst)",
    "sg:orig_category":"Newspapers, magazines, periodicals - Distribution",
    "sg:phone":"+32 89 41 42 94",
    "sg:postcode":"3740",
    "sg:province":"Limburg",
    "wof:name":"Briers-buntinx",
    "wof:placetype":"venue"
},
  "geometry": {"coordinates":[5.4747838974,50.8913764954],"type":"Point"}
}