{
  "type": "Feature",
  "properties": {
    "addr:full":"Kommanderijstraat 41 Sint-truiden Limburg 3800",
    "addr:housenumber":"41",
    "addr:postcode":"3800",
    "addr:street":"Kommanderijstraat",
    "iso:country":"BE",
    "sg:address":"Kommanderijstraat 41",
    "sg:city":"Sint-truiden",
    "sg:classifiers":[
        {
            "category":"Food & Beverages",
            "subcategory":"Fruits & Vegetables",
            "type":"Retail Goods"
        }
    ],
    "sg:phone":"+32 11 68 83 25",
    "sg:postcode":"3800",
    "sg:province":"Limburg",
    "sg:tags":[
        "-"
    ],
    "wof:name":"Borgs J",
    "wof:placetype":"venue"
},
  "geometry": {"coordinates":[5.2122769356,50.8270111084],"type":"Point"}
}