{
  "type": "Feature",
  "properties": {
    "iso:country":"BE",
    "sg:address":"Maastrichtersteenweg 466",
    "sg:city":"Tongeren",
    "sg:orig_category":"Rundveehouders",
    "sg:phone":"+32 12 23 03 19",
    "sg:postcode":"3700",
    "sg:province":"Limburg",
    "wof:name":"Roger Herlitska",
    "wof:placetype":"venue"
},
  "geometry": {"coordinates":[5.5269751549,50.792640686],"type":"Point"}
}