{
  "type": "Feature",
  "properties": {
    "addr:full":"Rue De L'eglise 17 Brunehaut (rongy) Hainaut 7623",
    "addr:housenumber":"17",
    "addr:postcode":"7623",
    "addr:street":"Rue De L'Eglise;Hainaut",
    "iso:country":"BE",
    "sg:address":"Rue De L'eglise 17",
    "sg:city":"Brunehaut (rongy)",
    "sg:classifiers":[
        {
            "category":"Health Services",
            "subcategory":"Nursing And Care Facility",
            "type":"Services"
        }
    ],
    "sg:phone":"+32 69 34 59 50",
    "sg:postcode":"7623",
    "sg:province":"Hainaut",
    "sg:tags":[
        "home",
        "rest"
    ],
    "wof:name":"Au P'tit Bonheur",
    "wof:placetype":"venue"
},
  "geometry": {"coordinates":[3.3849170208,50.5062866211],"type":"Point"}
}