{
  "type": "Feature",
  "properties": {
    "iso:country":"BE",
    "sg:address":"Meensesteenweg 264",
    "sg:city":"Roeselare",
    "sg:orig_category":"Entretien and r\u00e9parations de voitures. Stations-service and carburants",
    "sg:phone":"+32 51 24 82 04",
    "sg:postcode":"8800",
    "sg:province":"West-Vlaanderen",
    "wof:name":"Esso",
    "wof:placetype":"venue"
},
  "geometry": {"coordinates":[3.1200950146,50.9333610535],"type":"Point"}
}