{
  "type": "Feature",
  "properties": {
    "addr:full":"Rue De La Baronne Lemonnier 45 Rochefort (lavaux-sainte-anne) Namur 5580",
    "addr:housenumber":"45",
    "addr:postcode":"5580",
    "addr:street":"Rue De La Baronne Lemonnier",
    "iso:country":"BE",
    "sg:address":"Rue De La Baronne Lemonnier 45",
    "sg:city":"Rochefort (lavaux-sainte-anne)",
    "sg:classifiers":[
        {
            "category":"Health Services",
            "subcategory":"Health Practitioner",
            "type":"Services"
        }
    ],
    "sg:phone":"+32 84 38 88 07",
    "sg:postcode":"5580",
    "sg:province":"Namur",
    "sg:tags":[
        "physiotherapist"
    ],
    "wof:name":"Rondeaux M",
    "wof:placetype":"venue"
},
  "geometry": {"coordinates":[5.0985121727,50.1154594421],"type":"Point"}
}