{
  "type": "Feature",
  "properties": {
    "addr:full":"Aaklaan 10 Willebroek Antwerpen 2830",
    "addr:housenumber":"10",
    "addr:postcode":"2830",
    "addr:street":"Aaklaan",
    "iso:country":"BE",
    "sg:address":"Aaklaan 10",
    "sg:city":"Willebroek",
    "sg:orig_category":"Sportclubs",
    "sg:phone":"+32 3 886 15 26",
    "sg:postcode":"2830",
    "sg:province":"Antwerpen",
    "wof:name":"B.b.c. Blati Sport",
    "wof:placetype":"venue"
},
  "geometry": {"coordinates":[4.35663414,51.039024353],"type":"Point"}
}