{
  "type": "Feature",
  "properties": {
    "iso:country":"BE",
    "sg:address":"Roeselaarsestraat 648",
    "sg:city":"Izegem",
    "sg:orig_category":"Entretien and r\u00e9parations de voitures",
    "sg:phone":"+32 51 32 08 72",
    "sg:postcode":"8870",
    "sg:province":"West-Vlaanderen",
    "wof:name":"M. Poix",
    "wof:placetype":"venue"
},
  "geometry": {"coordinates":[3.1817700863,50.928440094],"type":"Point"}
}