{
  "type": "Feature",
  "properties": {
    "addr:full":"Roeselarestraat 13 Wevelgem West-Vlaanderen 8560",
    "addr:housenumber":"13",
    "addr:postcode":"8560",
    "addr:street":"Roeselarestraat",
    "iso:country":"BE",
    "sg:address":"Roeselarestraat 13",
    "sg:city":"Wevelgem",
    "sg:classifiers":[
        {
            "category":"Cafe",
            "type":"Food & Drink"
        }
    ],
    "sg:phone":"+32 56 41 84 82",
    "sg:postcode":"8560",
    "sg:province":"West-Vlaanderen",
    "sg:tags":[
        "caf\u00e9s"
    ],
    "wof:name":"Station Caf\u00c9",
    "wof:placetype":"venue"
},
  "geometry": {"coordinates":[3.1808381081,50.8109741211],"type":"Point"}
}