{
  "type": "Feature",
  "properties": {
    "addr:full":"Pl.d\u00c9port.& R\u00c9fractaires 6 Hannut Li\u00e8ge 4280",
    "addr:housenumber":"6",
    "addr:postcode":"4280",
    "iso:country":"BE",
    "sg:address":"Pl.d\u00c9port.& R\u00c9fractaires 6",
    "sg:city":"Hannut",
    "sg:orig_category":"Services pour animaux domestiques",
    "sg:phone":"+32 19 51 32 58",
    "sg:postcode":"4280",
    "sg:province":"Li\u00e8ge",
    "wof:name":"Aristochiem",
    "wof:placetype":"venue"
},
  "geometry": {"coordinates":[5.0859079361,50.6681289673],"type":"Point"}
}