{
  "type": "Feature",
  "properties": {
    "addr:full":"Mechelsesteenweg 51 Kontich Antwerpen 2550",
    "addr:housenumber":"51",
    "addr:postcode":"2550",
    "addr:street":"Mechelsesteenweg",
    "iso:country":"BE",
    "sg:address":"Mechelsesteenweg 51",
    "sg:city":"Kontich",
    "sg:orig_category":"Boissons",
    "sg:phone":"+32 3 457 11 03",
    "sg:postcode":"2550",
    "sg:province":"Antwerpen",
    "wof:name":"Paula Reyniers",
    "wof:placetype":"venue"
},
  "geometry": {"coordinates":[4.446199894,51.1330528259],"type":"Point"}
}