{
  "type": "Feature",
  "properties": {
    "iso:country":"BE",
    "sg:address":"Beukeboomstraat 36",
    "sg:city":"Lummen",
    "sg:classifiers":[
        {
            "category":"Banks & Credit Unions",
            "subcategory":"Investment Brokerage",
            "type":"Services"
        }
    ],
    "sg:phone":"+32 13 52 29 35",
    "sg:postcode":"3560",
    "sg:province":"Limburg",
    "wof:name":"Ciroux Hugo Bvba",
    "wof:placetype":"venue"
},
  "geometry": {"coordinates":[5.1818809509,50.98487854],"type":"Point"}
}