{
  "type": "Feature",
  "properties": {
    "addr:full":"Rue De La Limite 259 Herstal Li\u00e8ge 4041",
    "addr:housenumber":"259",
    "addr:postcode":"4041",
    "addr:street":"Rue De La Limite",
    "iso:country":"BE",
    "sg:address":"Rue De La Limite 259",
    "sg:city":"Herstal",
    "sg:orig_category":"Sportclubs",
    "sg:phone":"+32 4 278 27 25",
    "sg:postcode":"4041",
    "sg:province":"Li\u00e8ge",
    "wof:name":"J.c. Herm\u00c9e",
    "wof:placetype":"venue"
},
  "geometry": {"coordinates":[5.596642971,50.6792411804],"type":"Point"}
}