{
  "type": "Feature",
  "properties": {
    "addr:full":"Heppensteenweg 42 Beringen Limburg 3581",
    "addr:housenumber":"42",
    "addr:postcode":"3581",
    "addr:street":"Heppensteenweg",
    "iso:country":"BE",
    "sg:address":"Heppensteenweg 42",
    "sg:city":"Beringen",
    "sg:orig_category":"Metaalbehandeling and -bekleding",
    "sg:phone":"+32 113347946",
    "sg:postcode":"3581",
    "sg:province":"Limburg",
    "wof:name":"Lemmens",
    "wof:placetype":"venue"
},
  "geometry": {"coordinates":[5.2245221138,51.091583252],"type":"Point"}
}