{
  "type": "Feature",
  "properties": {
    "addr:full":"Dumortierlaan 73b1 Knokke-heist West-Vlaanderen 8300",
    "addr:housenumber":"73b1",
    "addr:postcode":"8300",
    "addr:street":"Dumortierlaan",
    "iso:country":"BE",
    "sg:address":"Dumortierlaan 73b1",
    "sg:city":"Knokke-heist",
    "sg:orig_category":"Verlichting and huishoudartikelen",
    "sg:phone":"+32 50 60 54 88",
    "sg:postcode":"8300",
    "sg:province":"West-Vlaanderen",
    "wof:name":"Huis Norrdal",
    "wof:placetype":"venue"
},
  "geometry": {"coordinates":[3.287694931,51.3467254639],"type":"Point"}
}