{
  "type": "Feature",
  "properties": {
    "addr:full":"Rozestraat 9 Knesselare Oost-Vlaanderen 9910",
    "addr:housenumber":"9",
    "addr:postcode":"9910",
    "addr:street":"Rozestraat;Oost-Vlaanderen",
    "iso:country":"BE",
    "sg:address":"Rozestraat 9",
    "sg:city":"Knesselare",
    "sg:orig_category":"Epiceries",
    "sg:phone":"+32 9 374 26 99",
    "sg:postcode":"9910",
    "sg:province":"Oost-Vlaanderen",
    "wof:name":"Spar",
    "wof:placetype":"venue"
},
  "geometry": {"coordinates":[3.4869260788,51.1290817261],"type":"Point"}
}