{
  "type": "Feature",
  "properties": {
    "addr:full":"Pieter Hauwaertssquare 3b1 Evere Bruxelles-Capitale 1140",
    "addr:housenumber":"3b1",
    "addr:postcode":"1140",
    "addr:street":"Pieter Hauwaertssquare",
    "iso:country":"BE",
    "sg:address":"Pieter Hauwaertssquare 3b1",
    "sg:city":"Evere",
    "sg:orig_category":"Sportclubs",
    "sg:phone":"+32 2 215 16 72",
    "sg:postcode":"1140",
    "sg:province":"Bruxelles-Capitale",
    "wof:name":"R.t.c. Lambermont",
    "wof:placetype":"venue"
},
  "geometry": {"coordinates":[4.4013390541,50.8758087158],"type":"Point"}
}