{
  "type": "Feature",
  "properties": {
    "iso:country":"BE",
    "sg:address":"Kapelstraat 108 Box 1",
    "sg:city":"Heusden-zolder (heusden)",
    "sg:classifiers":[
        {
            "category":"Building & Trades",
            "subcategory":"Construction",
            "type":"Services"
        }
    ],
    "sg:phone":"+32 11 42 77 22",
    "sg:postcode":"3550",
    "sg:province":"Limburg",
    "sg:tags":[
        "installation",
        "-",
        "central",
        "heating"
    ],
    "wof:name":"Ramakers Theo Bvba",
    "wof:placetype":"venue"
},
  "geometry": {"coordinates":[5.2692751884,51.0331497192],"type":"Point"}
}