{
  "type": "Feature",
  "properties": {
    "iso:country":"BE",
    "sg:address":"Rue Lairesse 51",
    "sg:city":"Li\u00e8ge 1 (li\u00e8ge 2)",
    "sg:classifiers":[
        {
            "category":"Real Estate",
            "subcategory":"Architect",
            "type":"Services"
        }
    ],
    "sg:phone":"+32 4 223 75 82",
    "sg:postcode":"4020",
    "sg:province":"Li\u00e8ge",
    "wof:name":"Clotuche P",
    "wof:placetype":"venue"
},
  "geometry": {"coordinates":[5.5857028961,50.6352081299],"type":"Point"}
}