{
  "type": "Feature",
  "properties": {
    "addr:full":"Dreef 149 Maasmechelen Limburg 3630",
    "addr:housenumber":"149",
    "addr:postcode":"3630",
    "addr:street":"Dreef",
    "iso:country":"BE",
    "sg:address":"Dreef 149",
    "sg:city":"Maasmechelen",
    "sg:orig_category":"Enseignement maternel and primaire",
    "sg:phone":"+32 89 75 55 37",
    "sg:postcode":"3630",
    "sg:province":"Limburg",
    "wof:name":"Vrije Lagere School",
    "wof:placetype":"venue"
},
  "geometry": {"coordinates":[5.6961350441,50.963848114],"type":"Point"}
}