{
  "type": "Feature",
  "properties": {
    "addr:full":"Stationsstraat 353 Ichtegem (eernegem) West-Vlaanderen 8480",
    "addr:housenumber":"353",
    "addr:postcode":"8480",
    "addr:street":"Stationsstraat",
    "iso:country":"BE",
    "sg:address":"Stationsstraat 353",
    "sg:city":"Ichtegem (eernegem)",
    "sg:classifiers":[
        {
            "category":"Utilities",
            "subcategory":"Refuse",
            "type":"Services"
        }
    ],
    "sg:phone":"+32 59 29 04 84",
    "sg:postcode":"8480",
    "sg:province":"West-Vlaanderen",
    "sg:tags":[
        "catering"
    ],
    "wof:name":"Marnix Traiteur",
    "wof:placetype":"venue"
},
  "geometry": {"coordinates":[3.0042231083,51.1226844788],"type":"Point"}
}