{
  "type": "Feature",
  "properties": {
    "addr:full":"Chauss\u00e9e De Wavre 802 Bruxelles (etterbeek) Bruxelles-Capitale 1040",
    "addr:housenumber":"802",
    "addr:postcode":"1040",
    "addr:street":"Chausse\u0301E De Wavre",
    "iso:country":"BE",
    "sg:address":"Chauss\u00e9e De Wavre 802",
    "sg:city":"Bruxelles (etterbeek)",
    "sg:orig_category":"Non-Classified Establishments",
    "sg:phone":"+32 2 646 42 62",
    "sg:postcode":"1040",
    "sg:province":"Bruxelles-Capitale",
    "wof:name":"Pumps Company Sprl",
    "wof:placetype":"venue"
},
  "geometry": {"coordinates":[4.3925499916,50.8291282654],"type":"Point"}
}