{
  "type": "Feature",
  "properties": {
    "iso:country":"BE",
    "sg:address":"Wolvendreef 2",
    "sg:city":"Kortrijk",
    "sg:classifiers":[
        {
            "category":"Health Services",
            "subcategory":"Doctor",
            "type":"Services"
        }
    ],
    "sg:phone":"+32 56 32 05 61",
    "sg:postcode":"8500",
    "sg:province":"West-Vlaanderen",
    "sg:tags":[
        "medicinephysicians",
        "surgeon"
    ],
    "wof:name":"Inderadjaja N",
    "wof:placetype":"venue"
},
  "geometry": {"coordinates":[3.2646598816,50.8133811951],"type":"Point"}
}