{
  "type": "Feature",
  "properties": {
    "iso:country":"BE",
    "sg:address":"Kortemarkstraat 142",
    "sg:city":"Lichtervelde",
    "sg:orig_category":"Eleveurs de bovins. Eleveurs and marchands de porcs",
    "sg:phone":"+32 51 72 26 86",
    "sg:postcode":"8810",
    "sg:province":"West-Vlaanderen",
    "wof:name":"Willy Lamsens",
    "wof:placetype":"venue"
},
  "geometry": {"coordinates":[3.1063020229,51.0238952637],"type":"Point"}
}