{
  "type": "Feature",
  "properties": {
    "addr:full":"Oude Godstraat 6 Edegem Antwerpen 2650",
    "addr:housenumber":"6",
    "addr:postcode":"2650",
    "addr:street":"Oude Godstraat",
    "iso:country":"BE",
    "sg:address":"Oude Godstraat 6",
    "sg:city":"Edegem",
    "sg:classifiers":[
        {
            "category":"Shopping",
            "subcategory":"Florist",
            "type":"Retail Goods"
        }
    ],
    "sg:phone":"+32 3 457 89 85",
    "sg:postcode":"2650",
    "sg:province":"Antwerpen",
    "wof:name":"In De Tuin Van Eden",
    "wof:placetype":"venue"
},
  "geometry": {"coordinates":[4.4442939758,51.1582641602],"type":"Point"}
}