{
  "type": "Feature",
  "properties": {
    "iso:country":"BE",
    "sg:address":"Avenue Du Roi Albert 99",
    "sg:city":"Ottignies-louvain-la-neuve",
    "sg:orig_category":"Mat\u00e9riaux de construction Gr",
    "sg:phone":"+32 10 41 54 15",
    "sg:postcode":"1340",
    "sg:province":"Brabant Wallon",
    "wof:name":"Fernand Fievet",
    "wof:placetype":"venue"
},
  "geometry": {"coordinates":[4.5557718277,50.6693992615],"type":"Point"}
}