{
  "type": "Feature",
  "properties": {
    "addr:full":"Ichtegemsestraat 32 Zedelgem (aartrijke) West-Vlaanderen 8211",
    "addr:housenumber":"32",
    "addr:postcode":"8211",
    "addr:street":"Ichtegemsestraat",
    "iso:country":"BE",
    "sg:address":"Ichtegemsestraat 32",
    "sg:city":"Zedelgem (aartrijke)",
    "sg:classifiers":[
        {
            "category":"Community Center",
            "type":"Public Place"
        }
    ],
    "sg:phone":"+32 50 20 98 49",
    "sg:postcode":"8211",
    "sg:province":"West-Vlaanderen",
    "sg:tags":[
        "medical"
    ],
    "wof:name":"Veld ('t) - Revalidatiecentrum Vzw",
    "wof:placetype":"venue"
},
  "geometry": {"coordinates":[3.0889649391,51.1200408936],"type":"Point"}
}