{
  "type": "Feature",
  "properties": {
    "addr:full":"Rue Belle Vue 50 Etalle Luxembourg 6740",
    "addr:housenumber":"50",
    "addr:postcode":"6740",
    "addr:street":"Rue Belle Vue",
    "iso:country":"BE",
    "sg:address":"Rue Belle Vue 50",
    "sg:city":"Etalle",
    "sg:orig_category":"Non-Classified Establishments",
    "sg:phone":"+32 63 45 53 19",
    "sg:postcode":"6740",
    "sg:province":"Luxembourg",
    "wof:name":"Stallbois",
    "wof:placetype":"venue"
},
  "geometry": {"coordinates":[5.6030201912,49.6787109375],"type":"Point"}
}