{
  "type": "Feature",
  "properties": {
    "iso:country":"BE",
    "sg:address":"Bosstraat 244",
    "sg:city":"Sint-pieters-woluwe/woluwe-saint-pierre",
    "sg:orig_category":"Voedingsspeciaalzaken",
    "sg:phone":"+32 2 770 57 35",
    "sg:postcode":"1150",
    "sg:province":"Bruxelles-Capitale",
    "wof:name":"Au Bois Gourmet",
    "wof:placetype":"venue"
},
  "geometry": {"coordinates":[4.4497051239,50.8322715759],"type":"Point"}
}