{
  "type": "Feature",
  "properties": {
    "addr:full":"Route De Souxhon 179 Fl\u00e9malle Li\u00e8ge 4400",
    "addr:housenumber":"179",
    "addr:postcode":"4400",
    "addr:street":"Route De Souxhon",
    "iso:country":"BE",
    "sg:address":"Route De Souxhon 179",
    "sg:city":"Fl\u00e9malle",
    "sg:classifiers":[
        {
            "category":"Professional",
            "subcategory":"Printing & Photocopies",
            "type":"Services"
        }
    ],
    "sg:phone":"+32 4 234 22 00",
    "sg:postcode":"4400",
    "sg:province":"Li\u00e8ge",
    "sg:tags":[
        "-",
        "offset"
    ],
    "wof:name":"Mini-print",
    "wof:placetype":"venue"
},
  "geometry": {"coordinates":[5.4553418159,50.6084403992],"type":"Point"}
}