{
  "type": "Feature",
  "properties": {
    "iso:country":"BE",
    "sg:address":"Rue D'en-haut 41",
    "sg:city":"Yvoir",
    "sg:orig_category":"Eleveurs de bovins",
    "sg:phone":"+32 83 69 90 47",
    "sg:postcode":"5530",
    "sg:province":"Namur",
    "wof:name":"Binon Joseph Et Alain",
    "wof:placetype":"venue"
},
  "geometry": {"coordinates":[4.9083228111,50.352558136],"type":"Point"}
}