{
  "type": "Feature",
  "properties": {
    "iso:country":"BE",
    "sg:address":"Rue De Li\u00c8ge 20ba",
    "sg:city":"Somme-leuze",
    "sg:orig_category":"Openbare veiligheid",
    "sg:phone":"+32 86 32 20 08",
    "sg:postcode":"5377",
    "sg:province":"Namur",
    "wof:name":"Police F\u00c9d\u00c9rale/federale Politie",
    "wof:placetype":"venue"
},
  "geometry": {"coordinates":[5.3711228371,50.3416404724],"type":"Point"}
}