{
  "type": "Feature",
  "properties": {
    "addr:full":"Victor Van Malderlaan 8 Dilbeek Vlaams-Brabant 1700",
    "addr:housenumber":"8",
    "addr:postcode":"1700",
    "addr:street":"Victor Van Malderlaan",
    "iso:country":"BE",
    "sg:address":"Victor Van Malderlaan 8",
    "sg:city":"Dilbeek",
    "sg:classifiers":[
        {
            "category":"Health Services",
            "subcategory":"Health Practitioner",
            "type":"Services"
        }
    ],
    "sg:phone":"+32 2 466 87 50",
    "sg:postcode":"1700",
    "sg:province":"Vlaams-Brabant",
    "sg:tags":[
        "physiotherapist"
    ],
    "wof:name":"Van Bochaute J",
    "wof:placetype":"venue"
},
  "geometry": {"coordinates":[4.2650299072,50.8523712158],"type":"Point"}
}