{
  "type": "Feature",
  "properties": {
    "iso:country":"BE",
    "sg:address":"Avenue Des Pl\u00c9iades 11",
    "sg:city":"Sint-lambrechts-woluwe/woluwe-saint-lambert",
    "sg:orig_category":"Syst\u00e8mes de t\u00e9l\u00e9communications",
    "sg:phone":"+32 2 775 04 50",
    "sg:postcode":"1200",
    "sg:province":"Bruxelles-Capitale",
    "wof:name":"Viatel Belgium",
    "wof:placetype":"venue"
},
  "geometry": {"coordinates":[4.4180250168,50.8539848328],"type":"Point"}
}