{
  "type": "Feature",
  "properties": {
    "iso:country":"BE",
    "sg:address":"Taxanderlei 49",
    "sg:city":"Schoten",
    "sg:classifiers":[
        {
            "category":"Professional",
            "type":"Services"
        }
    ],
    "sg:phone":"+32 3 658 89 20",
    "sg:postcode":"2900",
    "sg:province":"Antwerpen",
    "sg:tags":[
        "entertainer"
    ],
    "wof:name":"Look & Smile Bvba",
    "wof:placetype":"venue"
},
  "geometry": {"coordinates":[4.5220041275,51.2492027283],"type":"Point"}
}