{
  "type": "Feature",
  "properties": {
    "addr:full":"Rue Th\u00c9torique 19 Sint-gillis/saint-gilles Bruxelles-Capitale 1060",
    "addr:housenumber":"19",
    "addr:postcode":"1060",
    "addr:street":"Rue The\u0301Torique",
    "iso:country":"BE",
    "sg:address":"Rue Th\u00c9torique 19",
    "sg:city":"Sint-gillis/saint-gilles",
    "sg:classifiers":[
        {
            "category":"Arena",
            "subcategory":"Sports Club",
            "type":"Entertainment"
        }
    ],
    "sg:phone":"+32 2 537 47 62",
    "sg:postcode":"1060",
    "sg:province":"Bruxelles-Capitale",
    "sg:tags":[
        "de"
    ],
    "wof:name":"Assosiation Francoph D'aikido Asbl",
    "wof:placetype":"venue"
},
  "geometry": {"coordinates":[4.3461899757,50.8275375366],"type":"Point"}
}