{
  "type": "Feature",
  "properties": {
    "addr:full":"Nekkersvlietweg 2a Middelkerke (leffinge) West-Vlaanderen 8432",
    "addr:housenumber":"2a",
    "addr:postcode":"8432",
    "addr:street":"Nekkersvlietweg",
    "iso:country":"BE",
    "sg:address":"Nekkersvlietweg 2a",
    "sg:city":"Middelkerke (leffinge)",
    "sg:classifiers":[
        {
            "category":"Farming",
            "subcategory":"Livestock Farm",
            "type":"Manufacturing & Wholesale Goods"
        }
    ],
    "sg:phone":"+32 59 27 43 22",
    "sg:postcode":"8432",
    "sg:province":"West-Vlaanderen",
    "sg:tags":[
        "buyer"
    ],
    "wof:name":"Genes Diffusion",
    "wof:placetype":"venue"
},
  "geometry": {"coordinates":[2.9183449745,51.1628303528],"type":"Point"}
}