{
  "type": "Feature",
  "properties": {
    "iso:country":"BE",
    "sg:address":"Huinegem 37",
    "sg:city":"Asse",
    "sg:classifiers":[
        {
            "category":"Banks & Credit Unions",
            "subcategory":"Investment Brokerage",
            "type":"Services"
        }
    ],
    "sg:phone":"+32 2 453 02 06",
    "sg:postcode":"1730",
    "sg:province":"Vlaams-Brabant",
    "sg:tags":[
        "auditor"
    ],
    "wof:name":"Daelman Marc",
    "wof:placetype":"venue"
},
  "geometry": {"coordinates":[4.2050571442,50.912689209],"type":"Point"}
}