{
  "type": "Feature",
  "properties": {
    "iso:country":"BE",
    "sg:address":"Bilzersteenweg 58a",
    "sg:city":"Tongeren",
    "sg:classifiers":[
        {
            "category":"Real Estate",
            "subcategory":"Architect",
            "type":"Services"
        }
    ],
    "sg:phone":"+32 12 67 28 82",
    "sg:postcode":"3700",
    "sg:province":"Limburg",
    "wof:name":"Architectenbureau Unicum Bvba",
    "wof:placetype":"venue"
},
  "geometry": {"coordinates":[5.4624271393,50.7854614258],"type":"Point"}
}