{
  "type": "Feature",
  "properties": {
    "iso:country":"BE",
    "sg:address":"Arbeidstraat 1",
    "sg:city":"Aalst",
    "sg:classifiers":[
        {
            "category":"Shopping",
            "subcategory":"Clothing, Apparel, & Fashions",
            "type":"Retail Goods"
        }
    ],
    "sg:phone":"+32 53 70 37 04",
    "sg:postcode":"9300",
    "sg:province":"Oost-Vlaanderen",
    "sg:tags":[
        "lady",
        "clothing",
        "-"
    ],
    "wof:name":"Due Donna",
    "wof:placetype":"venue"
},
  "geometry": {"coordinates":[4.0335431099,50.9378890991],"type":"Point"}
}