{
  "type": "Feature",
  "properties": {
    "addr:full":"Rue De Crahiat Ciney Namur 5590",
    "addr:postcode":"5590",
    "addr:street":"Rue De Crahiat",
    "iso:country":"BE",
    "sg:address":"Rue De Crahiat",
    "sg:city":"Ciney",
    "sg:orig_category":"Royal Canin",
    "sg:phone":"+32 83 21 71 83",
    "sg:postcode":"5590",
    "sg:province":"Namur",
    "wof:name":"Tom & Co",
    "wof:placetype":"venue"
},
  "geometry": {"coordinates":[5.0928478241,50.2878952026],"type":"Point"}
}