{
  "type": "Feature",
  "properties": {
    "addr:full":"Cannaertstraat 35 Kortrijk (marke) West-Vlaanderen 8510",
    "addr:housenumber":"35",
    "addr:postcode":"8510",
    "addr:street":"Cannaertstraat",
    "iso:country":"BE",
    "sg:address":"Cannaertstraat 35",
    "sg:city":"Kortrijk (marke)",
    "sg:classifiers":[
        {
            "category":"Building & Trades",
            "subcategory":"Landscaping Services",
            "type":"Services"
        }
    ],
    "sg:phone":"+32 56 22 91 63",
    "sg:postcode":"8510",
    "sg:province":"West-Vlaanderen",
    "sg:tags":[
        "gardening",
        "garden",
        "maintenance"
    ],
    "wof:name":"Coucke Stefaan",
    "wof:placetype":"venue"
},
  "geometry": {"coordinates":[3.2567400932,50.8008728027],"type":"Point"}
}