{
  "type": "Feature",
  "properties": {
    "addr:full":"Avenue Sergent Vrithoff 2 Namur Namur 5000",
    "addr:housenumber":"2",
    "addr:postcode":"5000",
    "addr:street":"Avenue Sergent Vrithoff",
    "iso:country":"BE",
    "sg:address":"Avenue Sergent Vrithoff 2",
    "sg:city":"Namur",
    "sg:classifiers":[
        {
            "category":"Organizations",
            "subcategory":"Professional Association",
            "type":"Services"
        }
    ],
    "sg:phone":"+32 81 71 71 45",
    "sg:postcode":"5000",
    "sg:province":"Namur",
    "sg:tags":[
        "trade-union",
        "federation"
    ],
    "wof:name":"B.d.t.e.-bureau De D\u00e9veloppement",
    "wof:placetype":"venue"
},
  "geometry": {"coordinates":[4.8485808372,50.4669113159],"type":"Point"}
}