{
  "type": "Feature",
  "properties": {
    "addr:full":"Cayepolder 22 Middelkerke (lombardsijde) West-Vlaanderen 8434",
    "addr:housenumber":"22",
    "addr:postcode":"8434",
    "addr:street":"Cayepolder",
    "iso:country":"BE",
    "sg:address":"Cayepolder 22",
    "sg:city":"Middelkerke (lombardsijde)",
    "sg:classifiers":[
        {
            "category":"Structure",
            "subcategory":"Office Building",
            "type":"Public Place"
        }
    ],
    "sg:phone":"+32 58 24 05 12",
    "sg:postcode":"8434",
    "sg:province":"West-Vlaanderen",
    "sg:tags":[
        "-",
        "type",
        "door",
        "sliding",
        "overhead"
    ],
    "wof:name":"Vande Velde",
    "wof:placetype":"venue"
},
  "geometry": {"coordinates":[2.7595539093,51.1474723816],"type":"Point"}
}