{
  "type": "Feature",
  "properties": {
    "iso:country":"BE",
    "sg:address":"Terbiest 299",
    "sg:city":"Sint-truiden",
    "sg:classifiers":[
        {
            "category":"Bars & Pubs",
            "type":"Food & Drink"
        }
    ],
    "sg:phone":"+32 11 68 61 00",
    "sg:postcode":"3800",
    "sg:province":"Limburg",
    "wof:name":"Schuttershof",
    "wof:placetype":"venue"
},
  "geometry": {"coordinates":[5.2263221741,50.8382835388],"type":"Point"}
}