{
  "type": "Feature",
  "properties": {
    "iso:country":"BE",
    "sg:address":"Andr\u00c9 Dumontlaan 187",
    "sg:city":"Genk",
    "sg:orig_category":"Metaalafval, schrootrecyclage and sloperijen Onderdelen and accessoires voor auto's Voertuigen",
    "sg:phone":"+32 89 38 03 77",
    "sg:postcode":"3600",
    "sg:province":"Limburg",
    "wof:name":"Aspa",
    "wof:placetype":"venue"
},
  "geometry": {"coordinates":[5.5391879082,50.9876174927],"type":"Point"}
}