{
  "type": "Feature",
  "properties": {
    "iso:country":"BE",
    "sg:address":"Rue Abb\u00c9 Gelin 2",
    "sg:city":"Faimes",
    "sg:classifiers":[
        {
            "category":"Sports & Exercise",
            "subcategory":"Sports Center",
            "type":"Entertainment"
        }
    ],
    "sg:phone":"+32 19 32 78 68",
    "sg:postcode":"4317",
    "sg:province":"Li\u00e8ge",
    "sg:tags":[
        "terrain",
        "hors",
        "de",
        "installation",
        "sportifs"
    ],
    "wof:name":"Fabienne Froidcoeur",
    "wof:placetype":"venue"
},
  "geometry": {"coordinates":[5.2618951797,50.6657218933],"type":"Point"}
}