{
  "type": "Feature",
  "properties": {
    "iso:country":"BE",
    "sg:address":"Avenue Des Paveurs 8",
    "sg:city":"Waterloo",
    "sg:orig_category":"Artsen and specialisten",
    "sg:phone":"+32 2 354 88 31",
    "sg:postcode":"1410",
    "sg:province":"Brabant Wallon",
    "wof:name":"Nathalie Gilot",
    "wof:placetype":"venue"
},
  "geometry": {"coordinates":[4.3782391548,50.7087135315],"type":"Point"}
}