{
  "type": "Feature",
  "properties": {
    "iso:country":"BE",
    "sg:address":"Baalsebaan 8",
    "sg:city":"Tremelo",
    "sg:classifiers":[
        {
            "category":"Insurance",
            "subcategory":"Insurance Agent",
            "type":"Services"
        }
    ],
    "sg:phone":"+32 16 53 37 96",
    "sg:postcode":"3120",
    "sg:province":"Vlaams-Brabant",
    "sg:tags":[
        "-",
        "representative"
    ],
    "wof:name":"Cnops Verzekeringen Bvba",
    "wof:placetype":"venue"
},
  "geometry": {"coordinates":[4.7036180496,50.9946365356],"type":"Point"}
}