{
  "type": "Feature",
  "properties": {
    "addr:full":"Sint-trudostraat 7 Lummen (linkhout) Limburg 3560",
    "addr:housenumber":"7",
    "addr:postcode":"3560",
    "addr:street":"Sint-Trudostraat",
    "iso:country":"BE",
    "sg:address":"Sint-trudostraat 7",
    "sg:city":"Lummen (linkhout)",
    "sg:classifiers":[
        {
            "category":"Health Services",
            "subcategory":"Health Practitioner",
            "type":"Services"
        }
    ],
    "sg:phone":"+32 13 46 21 58",
    "sg:postcode":"3560",
    "sg:province":"Limburg",
    "sg:tags":[
        "physiotherapist"
    ],
    "wof:name":"Dederen Anand",
    "wof:placetype":"venue"
},
  "geometry": {"coordinates":[5.1365261078,50.9658164978],"type":"Point"}
}