{
  "type": "Feature",
  "properties": {
    "addr:full":"Barrierstraat 9 Bree Limburg 3960",
    "addr:housenumber":"9",
    "addr:postcode":"3960",
    "addr:street":"Barrierstraat",
    "iso:country":"BE",
    "sg:address":"Barrierstraat 9",
    "sg:city":"Bree",
    "sg:classifiers":[
        {
            "category":"Health Services",
            "subcategory":"Health Practitioner",
            "type":"Services"
        }
    ],
    "sg:phone":"+32 89 46 48 33",
    "sg:postcode":"3960",
    "sg:province":"Limburg",
    "sg:tags":[
        "physiotherapist"
    ],
    "wof:name":"Fiten Hilde",
    "wof:placetype":"venue"
},
  "geometry": {"coordinates":[5.5944190025,51.1405677795],"type":"Point"}
}