{
  "type": "Feature",
  "properties": {
    "addr:full":"Rue Luther 22 Brussel Bruxelles-Capitale 1000",
    "addr:housenumber":"22",
    "addr:postcode":"1000",
    "addr:street":"Rue Luther",
    "iso:country":"BE",
    "sg:address":"Rue Luther 22",
    "sg:city":"Brussel",
    "sg:orig_category":"Agences d'exp\u00e9dition",
    "sg:phone":"+32 2 732 59 37",
    "sg:postcode":"1000",
    "sg:province":"Bruxelles-Capitale",
    "wof:name":"Brussel Research & Consulting",
    "wof:placetype":"venue"
},
  "geometry": {"coordinates":[4.3847842216,50.8503036499],"type":"Point"}
}