{
  "type": "Feature",
  "properties": {
    "addr:full":"Yzerhand 21 Beveren (beveren-waas) Oost-Vlaanderen 9120",
    "addr:housenumber":"21",
    "addr:postcode":"9120",
    "addr:street":"Yzerhand;Oost-Vlaanderen",
    "iso:country":"BE",
    "sg:address":"Yzerhand 21",
    "sg:city":"Beveren (beveren-waas)",
    "sg:classifiers":[
        {
            "category":"Travel",
            "subcategory":"Travel Agent",
            "type":"Entertainment"
        }
    ],
    "sg:phone":"+32 3 750 26 70",
    "sg:postcode":"9120",
    "sg:province":"Oost-Vlaanderen",
    "sg:tags":[
        "agency"
    ],
    "wof:name":"Uniglobe Cosmos Travel",
    "wof:placetype":"venue"
},
  "geometry": {"coordinates":[4.2520971298,51.2154121399],"type":"Point"}
}