{
  "type": "Feature",
  "properties": {
    "addr:full":"Frimbuis 6 Ellezelles Hainaut 7890",
    "addr:housenumber":"6",
    "addr:postcode":"7890",
    "addr:street":"Frimbuis",
    "iso:country":"BE",
    "sg:address":"Frimbuis 6",
    "sg:city":"Ellezelles",
    "sg:orig_category":"Eleveurs de bovins",
    "sg:phone":"+32 68 64 57 32",
    "sg:postcode":"7890",
    "sg:province":"Hainaut",
    "wof:name":"Simon Meunier",
    "wof:placetype":"venue"
},
  "geometry": {"coordinates":[3.7017500401,50.7051506042],"type":"Point"}
}