{
  "type": "Feature",
  "properties": {
    "addr:full":"Chemin Fontaine-l'eveque 77 Nivelles Brabant Wallon 1400",
    "addr:housenumber":"77",
    "addr:postcode":"1400",
    "addr:street":"Chemin Fontaine-L'Eveque",
    "iso:country":"BE",
    "sg:address":"Chemin Fontaine-l'eveque 77",
    "sg:city":"Nivelles",
    "sg:orig_category":"Entretien and r\u00e9parations de voitures",
    "sg:phone":"+32 67 21 35 46",
    "sg:postcode":"1400",
    "sg:province":"Brabant Wallon",
    "wof:name":"Thierry Dehoux",
    "wof:placetype":"venue"
},
  "geometry": {"coordinates":[4.3185210228,50.5820999146],"type":"Point"}
}