{
  "type": "Feature",
  "properties": {
    "iso:country":"BE",
    "sg:address":"Ophovenstraat 45",
    "sg:city":"Opglabbeek",
    "sg:classifiers":[
        {
            "category":"Real Estate",
            "subcategory":"Architect",
            "type":"Services"
        }
    ],
    "sg:phone":"+32 89 85 44 80",
    "sg:postcode":"3660",
    "sg:province":"Limburg",
    "wof:name":"Vanhaeren M",
    "wof:placetype":"venue"
},
  "geometry": {"coordinates":[5.5711641312,51.0436592102],"type":"Point"}
}