{
  "type": "Feature",
  "properties": {
    "addr:full":"Pastorijstraat 3 Ravels Antwerpen 2382",
    "addr:housenumber":"3",
    "addr:postcode":"2382",
    "addr:street":"Pastorijstraat",
    "iso:country":"BE",
    "sg:address":"Pastorijstraat 3",
    "sg:city":"Ravels",
    "sg:classifiers":[
        {
            "category":"Cinema",
            "subcategory":"Movie Rental",
            "type":"Entertainment"
        }
    ],
    "sg:phone":"+32 14 65 71 43",
    "sg:postcode":"2382",
    "sg:province":"Antwerpen",
    "sg:tags":[
        "de",
        "cassette",
        "location",
        "vid\u00e9o",
        "audio"
    ],
    "wof:name":"Myriam Van Ginhoven",
    "wof:placetype":"venue"
},
  "geometry": {"coordinates":[5.041768074,51.4469108582],"type":"Point"}
}