{
  "type": "Feature",
  "properties": {
    "addr:full":"Berkenlaan 21 Aalst Oost-Vlaanderen 9320",
    "addr:housenumber":"21",
    "addr:postcode":"9320",
    "addr:street":"Berkenlaan",
    "iso:country":"BE",
    "sg:address":"Berkenlaan 21",
    "sg:city":"Aalst",
    "sg:orig_category":"Artsen and specialisten",
    "sg:phone":"+32 53 83 46 69",
    "sg:postcode":"9320",
    "sg:province":"Oost-Vlaanderen",
    "wof:name":"Luc Kerchofs",
    "wof:placetype":"venue"
},
  "geometry": {"coordinates":[4.0586910248,50.9868507385],"type":"Point"}
}