{
  "type": "Feature",
  "properties": {
    "addr:full":"Rue Albert I 440 Erquelinnes Hainaut 6560",
    "addr:housenumber":"440",
    "addr:postcode":"6560",
    "addr:street":"Rue Albert I",
    "iso:country":"BE",
    "sg:address":"Rue Albert I 440",
    "sg:city":"Erquelinnes",
    "sg:orig_category":"Winkelinrichting and handelsuitrusting Gh",
    "sg:phone":"+32 71 55 89 09",
    "sg:postcode":"6560",
    "sg:province":"Hainaut",
    "wof:name":"La Maison Des Coiffeurs",
    "wof:placetype":"venue"
},
  "geometry": {"coordinates":[4.1207499504,50.3097915649],"type":"Point"}
}