{
  "type": "Feature",
  "properties": {
    "iso:country":"BE",
    "sg:address":"Wijnputstraat 49",
    "sg:city":"Scherpenheuvel-zichem",
    "sg:orig_category":"Eleveurs and marchands de porcs",
    "sg:phone":"+32 13 78 33 38",
    "sg:postcode":"3271",
    "sg:province":"Vlaams-Brabant",
    "wof:name":"Georges Michiels",
    "wof:placetype":"venue"
},
  "geometry": {"coordinates":[4.9985508919,50.9868087769],"type":"Point"}
}