{
  "type": "Feature",
  "properties": {
    "addr:full":"J. B. Charlierlaan 98 Box 1 Hoeilaart Vlaams-Brabant 1560",
    "addr:housenumber":"98;1",
    "addr:postcode":"1560",
    "addr:street":"J.;Charlierlaan;Box",
    "iso:country":"BE",
    "sg:address":"J. B. Charlierlaan 98 Box 1",
    "sg:city":"Hoeilaart",
    "sg:classifiers":[
        {
            "category":"Professional",
            "subcategory":"Accounting & Tax Preparation",
            "type":"Services"
        }
    ],
    "sg:phone":"+32 2 657 22 91",
    "sg:postcode":"1560",
    "sg:province":"Vlaams-Brabant",
    "sg:tags":[
        "bookkeeper"
    ],
    "wof:name":"Mullie L",
    "wof:placetype":"venue"
},
  "geometry": {"coordinates":[4.4616389275,50.7667274475],"type":"Point"}
}