{
  "type": "Feature",
  "properties": {
    "addr:full":"Itali\u00eblei 135 Box 1 Antwerpen Antwerpen 2000",
    "addr:housenumber":"135;1",
    "addr:postcode":"2000",
    "addr:street":"Italie\u0308Lei;Box",
    "iso:country":"BE",
    "sg:address":"Itali\u00eblei 135 Box 1",
    "sg:city":"Antwerpen",
    "sg:classifiers":[
        {
            "category":"Wholesale",
            "subcategory":"Tobacco Products",
            "type":"Manufacturing & Wholesale Goods"
        }
    ],
    "sg:phone":"+32 3 231 96 50",
    "sg:postcode":"2000",
    "sg:province":"Antwerpen",
    "sg:tags":[
        "import",
        "wood",
        "-"
    ],
    "wof:name":"Stevens & Co Etn Nv",
    "wof:placetype":"venue"
},
  "geometry": {"coordinates":[4.4157090187,51.2249031067],"type":"Point"}
}