{
  "type": "Feature",
  "properties": {
    "iso:country":"BE",
    "sg:address":"Roggelaan 45",
    "sg:city":"Kortrijk",
    "sg:classifiers":[
        {
            "category":"Building & Trades",
            "subcategory":"Pest Control",
            "type":"Services"
        }
    ],
    "sg:phone":"+32 56 25 92 11",
    "sg:postcode":"8500",
    "sg:province":"West-Vlaanderen",
    "sg:tags":[
        "painting",
        "contractor"
    ],
    "wof:name":"Debels B",
    "wof:placetype":"venue"
},
  "geometry": {"coordinates":[3.2961330414,50.8149871826],"type":"Point"}
}