{
  "type": "Feature",
  "properties": {
    "addr:full":"Tongerlostraat 1 Ravels Antwerpen 2380",
    "addr:housenumber":"1",
    "addr:postcode":"2380",
    "addr:street":"Tongerlostraat",
    "iso:country":"BE",
    "sg:address":"Tongerlostraat 1",
    "sg:city":"Ravels",
    "sg:classifiers":[
        {
            "category":"Health Services",
            "subcategory":"Health Practitioner",
            "type":"Services"
        }
    ],
    "sg:phone":"+32 14 65 76 35",
    "sg:postcode":"2380",
    "sg:province":"Antwerpen",
    "sg:tags":[
        "physiotherapist"
    ],
    "wof:name":"Van Eyndhoven Ann",
    "wof:placetype":"venue"
},
  "geometry": {"coordinates":[4.9885859489,51.36460495],"type":"Point"}
}