{
  "type": "Feature",
  "properties": {
    "addr:full":"Industriepark 24 Hulshout Antwerpen 2235",
    "addr:housenumber":"24",
    "addr:postcode":"2235",
    "addr:street":"Industriepark",
    "iso:country":"BE",
    "sg:address":"Industriepark 24",
    "sg:city":"Hulshout",
    "sg:orig_category":"Autoverhuur",
    "sg:phone":"+32 15 22 52 80",
    "sg:postcode":"2235",
    "sg:province":"Antwerpen",
    "wof:name":"Huurwagens Mols",
    "wof:placetype":"venue"
},
  "geometry": {"coordinates":[4.810503006,51.0829658508],"type":"Point"}
}