{
  "type": "Feature",
  "properties": {
    "iso:country":"BE",
    "sg:address":"Rue De Goz\u00e9e 640",
    "sg:city":"Montigny-le-tilleul",
    "sg:classifiers":[
        {
            "category":"Retail",
            "subcategory":"Auto Repair",
            "type":"Services"
        }
    ],
    "sg:phone":"+32 71 51 56 33",
    "sg:postcode":"6110",
    "sg:province":"Hainaut",
    "sg:tags":[
        "garage"
    ],
    "wof:name":"Gautier J",
    "wof:placetype":"venue"
},
  "geometry": {"coordinates":[4.3641262054,50.3637504578],"type":"Point"}
}