{
  "type": "Feature",
  "properties": {
    "addr:full":"Rue Des Augustins 33 Li\u00c8ge Li\u00e8ge 4000",
    "addr:housenumber":"33",
    "addr:postcode":"4000",
    "addr:street":"Rue Des Augustins",
    "iso:country":"BE",
    "sg:address":"Rue Des Augustins 33",
    "sg:city":"Li\u00c8ge",
    "sg:orig_category":"Activit\u00e9s diverses d'imprimerie",
    "sg:phone":"+32 4 222 18 44",
    "sg:postcode":"4000",
    "sg:province":"Li\u00e8ge",
    "wof:name":"Lionel Marbehant",
    "wof:placetype":"venue"
},
  "geometry": {"coordinates":[5.5657291412,50.6352462769],"type":"Point"}
}