{
  "type": "Feature",
  "properties": {
    "addr:full":"Duivenstraat 40 Vosselaar Antwerpen 2350",
    "addr:housenumber":"40",
    "addr:postcode":"2350",
    "addr:street":"Duivenstraat",
    "iso:country":"BE",
    "sg:address":"Duivenstraat 40",
    "sg:city":"Vosselaar",
    "sg:orig_category":"Drukkerijen and copyshops",
    "sg:phone":"+32 14 61 65 03",
    "sg:postcode":"2350",
    "sg:province":"Antwerpen",
    "wof:name":"Grafico",
    "wof:placetype":"venue"
},
  "geometry": {"coordinates":[4.8820471764,51.3008956909],"type":"Point"}
}