{
  "type": "Feature",
  "properties": {
    "addr:full":"Rue Henri Berg\u00c9 44 Schaarbeek/schaerbeek Bruxelles-Capitale 1030",
    "addr:housenumber":"44",
    "addr:postcode":"1030",
    "addr:street":"Rue Henri Berge\u0301",
    "iso:country":"BE",
    "sg:address":"Rue Henri Berg\u00c9 44",
    "sg:city":"Schaarbeek/schaerbeek",
    "sg:classifiers":[
        {
            "category":"Cafe",
            "type":"Food & Drink"
        }
    ],
    "sg:phone":"+32 2 241 98 31",
    "sg:postcode":"1030",
    "sg:province":"Bruxelles-Capitale",
    "sg:tags":[
        "caf\u00e9s"
    ],
    "wof:name":"Taverne D'evere",
    "wof:placetype":"venue"
},
  "geometry": {"coordinates":[4.3756899834,50.8652038574],"type":"Point"}
}