{
  "type": "Feature",
  "properties": {
    "addr:full":"Kouterstraat 104 Houthulst West-Vlaanderen 8650",
    "addr:housenumber":"104",
    "addr:postcode":"8650",
    "addr:street":"Kouterstraat",
    "iso:country":"BE",
    "sg:address":"Kouterstraat 104",
    "sg:city":"Houthulst",
    "sg:orig_category":"Rundveehouders Varkenskwekers",
    "sg:phone":"+32 51 54 40 77",
    "sg:postcode":"8650",
    "sg:province":"West-Vlaanderen",
    "wof:name":"Roger Verhoest",
    "wof:placetype":"venue"
},
  "geometry": {"coordinates":[2.8588929176,50.9489440918],"type":"Point"}
}