{
  "type": "Feature",
  "properties": {
    "addr:full":"Rue Fr\u00e9d\u00e9ric Pelletier 103 Bruxelles (schaerbeek) Bruxelles-Capitale 1030",
    "addr:housenumber":"103",
    "addr:postcode":"1030",
    "addr:street":"Rue Fre\u0301De\u0301Ric Pelletier",
    "iso:country":"BE",
    "sg:address":"Rue Fr\u00e9d\u00e9ric Pelletier 103",
    "sg:city":"Bruxelles (schaerbeek)",
    "sg:orig_category":"Non-Classified Establishments",
    "sg:phone":"+32 2 733 77 05",
    "sg:postcode":"1030",
    "sg:province":"Bruxelles-Capitale",
    "wof:name":"Flament J P",
    "wof:placetype":"venue"
},
  "geometry": {"coordinates":[4.4025759697,50.8458099365],"type":"Point"}
}