{
  "type": "Feature",
  "properties": {
    "iso:country":"BE",
    "sg:address":"Koekoeksdreef 50",
    "sg:city":"Schilde",
    "sg:classifiers":[
        {
            "category":"Banks & Credit Unions",
            "subcategory":"Investment Brokerage",
            "type":"Services"
        }
    ],
    "sg:phone":"+32 3 385 42 94",
    "sg:postcode":"2970",
    "sg:province":"Antwerpen",
    "sg:tags":[
        "auditor"
    ],
    "wof:name":"Spileers D",
    "wof:placetype":"venue"
},
  "geometry": {"coordinates":[4.6184501648,51.2416152954],"type":"Point"}
}