{
  "type": "Feature",
  "properties": {
    "iso:country":"BE",
    "sg:address":"Rue Du Vieux Tilleul 12",
    "sg:city":"Aubel",
    "sg:orig_category":"Pain, p\u00e2tisseries and confiseries",
    "sg:phone":"+32 4 376 72 14",
    "sg:postcode":"4880",
    "sg:province":"Li\u00e8ge",
    "wof:name":"Jocelyne Constant",
    "wof:placetype":"venue"
},
  "geometry": {"coordinates":[5.8531098366,50.7121925354],"type":"Point"}
}