{
  "type": "Feature",
  "properties": {
    "iso:country":"BE",
    "sg:address":"Rue Rioul 13",
    "sg:city":"Huy",
    "sg:classifiers":[
        {
            "category":"Wholesale",
            "subcategory":"Office Equipment",
            "type":"Manufacturing & Wholesale Goods"
        }
    ],
    "sg:phone":"+32 85 21 16 25",
    "sg:postcode":"4500",
    "sg:province":"Li\u00e8ge",
    "sg:tags":[
        "machine",
        "rental",
        "retail",
        "-"
    ],
    "wof:name":"Gonthier V",
    "wof:placetype":"venue"
},
  "geometry": {"coordinates":[5.2443070412,50.5235023499],"type":"Point"}
}