{
  "type": "Feature",
  "properties": {
    "iso:country":"BE",
    "sg:address":"Pont-noord 2",
    "sg:city":"De Pinte (zevergem)",
    "sg:classifiers":[
        {
            "category":"Food & Beverages",
            "subcategory":"Liquor & Beverages",
            "type":"Retail Goods"
        }
    ],
    "sg:phone":"+32 9 385 94 66",
    "sg:postcode":"9840",
    "sg:province":"Oost-Vlaanderen",
    "sg:tags":[
        "-",
        "spirit",
        "wine"
    ],
    "wof:name":"Fattoria (la)",
    "wof:placetype":"venue"
},
  "geometry": {"coordinates":[3.7000570297,50.9843635559],"type":"Point"}
}