{
  "type": "Feature",
  "properties": {
    "iso:country":"BE",
    "sg:address":"Chauss\u00c9e De Dinant 1098",
    "sg:city":"Namur",
    "sg:orig_category":"M\u00e9decins and sp\u00e9cialistes",
    "sg:phone":"+32 81 46 17 94",
    "sg:postcode":"5100",
    "sg:province":"Namur",
    "wof:name":"Patrice Lejuste",
    "wof:placetype":"venue"
},
  "geometry": {"coordinates":[4.8798890114,50.4154815674],"type":"Point"}
}