{
  "type": "Feature",
  "properties": {
    "addr:full":"Chauss\u00e9e De Mons 159 Soignies Hainaut 7060",
    "addr:housenumber":"159",
    "addr:postcode":"7060",
    "addr:street":"Chausse\u0301E De Mons",
    "iso:country":"BE",
    "sg:address":"Chauss\u00e9e De Mons 159",
    "sg:city":"Soignies",
    "sg:classifiers":[
        {
            "category":"Retail",
            "subcategory":"Auto Repair",
            "type":"Services"
        }
    ],
    "sg:phone":"+32 67 33 40 82",
    "sg:postcode":"7060",
    "sg:province":"Hainaut",
    "sg:tags":[
        "automobile-body"
    ],
    "wof:name":"Carrosserie C.p.m.",
    "wof:placetype":"venue"
},
  "geometry": {"coordinates":[4.0611262321,50.5643844604],"type":"Point"}
}