{
  "type": "Feature",
  "properties": {
    "iso:country":"BE",
    "sg:address":"Akkerhage 10",
    "sg:city":"Gent",
    "sg:classifiers":[
        {
            "category":"Banks & Credit Unions",
            "subcategory":"Atm",
            "type":"Services"
        }
    ],
    "sg:phone":"+32 9 241 52 11",
    "sg:postcode":"9000",
    "sg:province":"Oost-Vlaanderen",
    "sg:tags":[
        "d'entreprises",
        "de",
        "bureau"
    ],
    "wof:name":"Bedrijvencentrum Gent",
    "wof:placetype":"venue"
},
  "geometry": {"coordinates":[3.7359280586,51.0176963806],"type":"Point"}
}