{
  "type": "Feature",
  "properties": {
    "iso:country":"BE",
    "sg:address":"Hondstraat 100",
    "sg:city":"Tielt",
    "sg:orig_category":"Cafetarias and selfservice restaurants",
    "sg:phone":"+32 51 40 66 67",
    "sg:postcode":"8700",
    "sg:province":"West-Vlaanderen",
    "wof:name":"Watewy",
    "wof:placetype":"venue"
},
  "geometry": {"coordinates":[3.3105399609,51.0027503967],"type":"Point"}
}