{
  "type": "Feature",
  "properties": {
    "iso:country":"BE",
    "sg:address":"Tapuitstraat 246",
    "sg:city":"Waregem",
    "sg:orig_category":"Hout and afgeleiden Gh Houtbewerking and -behandeling IJzerwaren, bouw- and verfmaterialen",
    "sg:phone":"+32 56 60 21 12",
    "sg:postcode":"8793",
    "sg:province":"West-Vlaanderen",
    "wof:name":"Placabois",
    "wof:placetype":"venue"
},
  "geometry": {"coordinates":[3.3987910748,50.895236969],"type":"Point"}
}