{
  "type": "Feature",
  "properties": {
    "addr:full":"Industriepark Kolmen Alken Limburg 3570",
    "addr:postcode":"3570",
    "addr:street":"Industriepark Kolmen",
    "iso:country":"BE",
    "sg:address":"Industriepark Kolmen",
    "sg:city":"Alken",
    "sg:orig_category":"Non-Classified Establishments",
    "sg:phone":"+32 11 31 13 31",
    "sg:postcode":"3570",
    "sg:province":"Limburg",
    "wof:name":"Alelek",
    "wof:placetype":"venue"
},
  "geometry": {"coordinates":[5.3073601723,50.8763618469],"type":"Point"}
}