{
  "type": "Feature",
  "properties": {
    "iso:country":"BE",
    "sg:address":"Heilig Bloedlaan 250",
    "sg:city":"Hoogstraten",
    "sg:classifiers":[
        {
            "category":"Health Services",
            "subcategory":"Nursing And Care Facility",
            "type":"Services"
        }
    ],
    "sg:phone":"+32 3 340 21 50",
    "sg:postcode":"2320",
    "sg:province":"Antwerpen",
    "sg:tags":[
        "public"
    ],
    "wof:name":"O.c.m.w.",
    "wof:placetype":"venue"
},
  "geometry": {"coordinates":[4.7581658363,51.3967018127],"type":"Point"}
}