{
  "type": "Feature",
  "properties": {
    "iso:country":"BE",
    "sg:address":"Brusselsesteenweg 138",
    "sg:city":"Herent (winksele)",
    "sg:classifiers":[
        {
            "category":"Real Estate",
            "subcategory":"Architect",
            "type":"Services"
        }
    ],
    "sg:phone":"+32 16 48 81 29",
    "sg:postcode":"3020",
    "sg:province":"Vlaams-Brabant",
    "wof:name":"Stevens A",
    "wof:placetype":"venue"
},
  "geometry": {"coordinates":[4.6591420174,50.888584137],"type":"Point"}
}