{
  "type": "Feature",
  "properties": {
    "iso:country":"BE",
    "sg:address":"Stenenmolenstraat 143b2",
    "sg:city":"Mechelen",
    "sg:orig_category":"Sportclubs",
    "sg:phone":"+32 15 41 15 10",
    "sg:postcode":"2800",
    "sg:province":"Antwerpen",
    "wof:name":"Wandelgroep Flamingo",
    "wof:placetype":"venue"
},
  "geometry": {"coordinates":[4.4768719673,51.0094032288],"type":"Point"}
}