{
  "type": "Feature",
  "properties": {
    "addr:full":"En Mi-ville 22 Verviers Li\u00e8ge 4800",
    "addr:housenumber":"22",
    "addr:postcode":"4800",
    "iso:country":"BE",
    "sg:address":"En Mi-ville 22",
    "sg:city":"Verviers",
    "sg:orig_category":"Journaux. Tabac",
    "sg:phone":"+32 87 33 38 05",
    "sg:postcode":"4800",
    "sg:province":"Li\u00e8ge",
    "wof:name":"Librairie Sluysmans",
    "wof:placetype":"venue"
},
  "geometry": {"coordinates":[5.8400321007,50.5813140869],"type":"Point"}
}