{
  "type": "Feature",
  "properties": {
    "addr:full":"Rue Des Rivages 80-81 Dinant Namur 5500",
    "addr:housenumber":"80-81",
    "addr:postcode":"5500",
    "addr:street":"Rue Des Rivages",
    "iso:country":"BE",
    "sg:address":"Rue Des Rivages 80-81",
    "sg:city":"Dinant",
    "sg:classifiers":[
        {
            "category":"Shopping",
            "subcategory":"Bicycles & Sporting Goods",
            "type":"Retail Goods"
        }
    ],
    "sg:phone":"+32 82 22 23 03",
    "sg:postcode":"5500",
    "sg:province":"Namur",
    "sg:tags":[
        "-"
    ],
    "wof:name":"Collin",
    "wof:placetype":"venue"
},
  "geometry": {"coordinates":[4.920320034,50.2489089966],"type":"Point"}
}