{
  "type": "Feature",
  "properties": {
    "iso:country":"BE",
    "sg:address":"Baalhoek 50",
    "sg:city":"Grimbergen (strombeek-bever)",
    "sg:orig_category":"Non-Classified Establishments",
    "sg:phone":"+32 2 267 28 70",
    "sg:postcode":"1853",
    "sg:province":"Vlaams-Brabant",
    "wof:name":"Van Grinsven I",
    "wof:placetype":"venue"
},
  "geometry": {"coordinates":[4.3522191048,50.9045906067],"type":"Point"}
}