{
  "type": "Feature",
  "properties": {
    "iso:country":"BE",
    "sg:address":"Menenstraat 35",
    "sg:city":"Wevelgem",
    "sg:orig_category":"Fleurs and plantes. Pisciculture",
    "sg:phone":"+32 56 41 70 12",
    "sg:postcode":"8560",
    "sg:province":"West-Vlaanderen",
    "wof:name":"Bloem Vijvercentrum Iris",
    "wof:placetype":"venue"
},
  "geometry": {"coordinates":[3.1775178909,50.807384491],"type":"Point"}
}