{
  "type": "Feature",
  "properties": {
    "addr:full":"Schonekeerstraat 205b0101 Menen West-Vlaanderen 8930",
    "addr:postcode":"8930",
    "addr:street":"Schonekeerstraat;West-Vlaanderen",
    "iso:country":"BE",
    "sg:address":"Schonekeerstraat 205b0101",
    "sg:city":"Menen",
    "sg:orig_category":"Plaatsen van vloer- and muurbekleding Schilders",
    "sg:phone":"+32 475 67 43 15",
    "sg:postcode":"8930",
    "sg:province":"West-Vlaanderen",
    "wof:name":"Cokele",
    "wof:placetype":"venue"
},
  "geometry": {"coordinates":[3.1209149361,50.7961845398],"type":"Point"}
}