{
  "type": "Feature",
  "properties": {
    "addr:full":"Chemin Du Comp\u00e8re 20 Gerpinnes (joncret) Hainaut 6280",
    "addr:housenumber":"20",
    "addr:postcode":"6280",
    "addr:street":"Chemin Du Compe\u0300Re",
    "iso:country":"BE",
    "sg:address":"Chemin Du Comp\u00e8re 20",
    "sg:city":"Gerpinnes (joncret)",
    "sg:classifiers":[
        {
            "category":"Sports & Exercise",
            "subcategory":"Stables",
            "type":"Entertainment"
        }
    ],
    "sg:phone":"+32 71 50 20 68",
    "sg:postcode":"6280",
    "sg:province":"Hainaut",
    "sg:tags":[
        "riding",
        "school"
    ],
    "wof:name":"Ecurie Du Comp\u00e8re",
    "wof:placetype":"venue"
},
  "geometry": {"coordinates":[4.506439209,50.356338501],"type":"Point"}
}