{
  "type": "Feature",
  "properties": {
    "iso:country":"BE",
    "sg:address":"Rue Joseph Wettinck 18",
    "sg:city":"Seraing (jemeppe-sur-meuse)",
    "sg:classifiers":[
        {
            "category":"Food & Beverages",
            "subcategory":"Chocolate",
            "type":"Retail Goods"
        }
    ],
    "sg:phone":"+32 4 231 06 43",
    "sg:postcode":"4101",
    "sg:province":"Li\u00e8ge",
    "sg:tags":[
        "confectionery",
        "-"
    ],
    "wof:name":"Isabelle Boutique",
    "wof:placetype":"venue"
},
  "geometry": {"coordinates":[5.5026531219,50.6158370972],"type":"Point"}
}