{
  "type": "Feature",
  "properties": {
    "addr:full":"Kapellebaan 15 Buggenhout Oost-Vlaanderen 9255",
    "addr:housenumber":"15",
    "addr:postcode":"9255",
    "addr:street":"Kapellebaan",
    "iso:country":"BE",
    "sg:address":"Kapellebaan 15",
    "sg:city":"Buggenhout",
    "sg:orig_category":"Hydrants",
    "sg:phone":"+32 3 645 48 05",
    "sg:postcode":"9255",
    "sg:province":"Oost-Vlaanderen",
    "wof:name":"Brabo N.v. Algemene Brandbeveiliging",
    "wof:placetype":"venue"
},
  "geometry": {"coordinates":[4.4532628059,51.2407836914],"type":"Point"}
}