{
  "type": "Feature",
  "properties": {
    "addr:full":"Rue Jonfosse 60 Li\u00c8ge Li\u00e8ge 4000",
    "addr:housenumber":"60",
    "addr:postcode":"4000",
    "addr:street":"Rue Jonfosse",
    "iso:country":"BE",
    "sg:address":"Rue Jonfosse 60",
    "sg:city":"Li\u00c8ge",
    "sg:orig_category":"Beschutte werkplaatsen",
    "sg:phone":"+32 4 222 35 35",
    "sg:postcode":"4000",
    "sg:province":"Li\u00e8ge",
    "wof:name":"Centre Pouplin",
    "wof:placetype":"venue"
},
  "geometry": {"coordinates":[5.562869072,50.6401367188],"type":"Point"}
}