{
  "type": "Feature",
  "properties": {
    "addr:full":"Route Du Lion 99 Braine-l'alleud Brabant Wallon 1420",
    "addr:housenumber":"99",
    "addr:postcode":"1420",
    "addr:street":"Route Du Lion",
    "iso:country":"BE",
    "sg:address":"Route Du Lion 99",
    "sg:city":"Braine-l'alleud",
    "sg:orig_category":"Sportclubs",
    "sg:phone":"+32 2 384 04 83",
    "sg:postcode":"1420",
    "sg:province":"Brabant Wallon",
    "wof:name":"Waterloo Natation",
    "wof:placetype":"venue"
},
  "geometry": {"coordinates":[-0.6697199941,47.4606246948],"type":"Point"}
}