{
  "type": "Feature",
  "properties": {
    "addr:full":"Coupure Links 501 Gent Oost-Vlaanderen 9000",
    "addr:housenumber":"501",
    "addr:postcode":"9000",
    "addr:street":"Coupure Links;Oost-Vlaanderen",
    "iso:country":"BE",
    "sg:address":"Coupure Links 501",
    "sg:city":"Gent",
    "sg:orig_category":"Brood, gebak and snoepgoed",
    "sg:phone":"+32 9 225 47 12",
    "sg:postcode":"9000",
    "sg:province":"Oost-Vlaanderen",
    "wof:name":"Bakkerij Martens",
    "wof:placetype":"venue"
},
  "geometry": {"coordinates":[3.7100389004,51.0502929688],"type":"Point"}
}