{
  "type": "Feature",
  "properties": {
    "addr:full":"Markt 2 Retie Antwerpen 2470",
    "addr:housenumber":"2",
    "addr:postcode":"2470",
    "addr:street":"Markt",
    "iso:country":"BE",
    "sg:address":"Markt 2",
    "sg:city":"Retie",
    "sg:orig_category":"Pharmaciens",
    "sg:phone":"+32 14 37 70 31",
    "sg:postcode":"2470",
    "sg:province":"Antwerpen",
    "wof:name":"Apotheek Bourgeois",
    "wof:placetype":"venue"
},
  "geometry": {"coordinates":[5.0847449303,51.2677078247],"type":"Point"}
}