{
  "type": "Feature",
  "properties": {
    "addr:full":"Koningsbaan 14 Heist-op-den-berg Antwerpen 2220",
    "addr:housenumber":"14",
    "addr:postcode":"2220",
    "addr:street":"Koningsbaan",
    "iso:country":"BE",
    "sg:address":"Koningsbaan 14",
    "sg:city":"Heist-op-den-berg",
    "sg:orig_category":"Plaatsen van vloer- and muurbekleding",
    "sg:phone":"+32 15 23 58 83",
    "sg:postcode":"2220",
    "sg:province":"Antwerpen",
    "wof:name":"Marc Schroeyens",
    "wof:placetype":"venue"
},
  "geometry": {"coordinates":[4.6836252213,51.0480270386],"type":"Point"}
}