{
  "type": "Feature",
  "properties": {
    "addr:full":"Zonnestraat 236 Ronse/renaix Oost-Vlaanderen 9600",
    "addr:housenumber":"236",
    "addr:postcode":"9600",
    "addr:street":"Zonnestraat",
    "iso:country":"BE",
    "sg:address":"Zonnestraat 236",
    "sg:city":"Ronse/renaix",
    "sg:orig_category":"Benzinestations and brandstoffen HUISBRANDOLIE Huishoudapparaten, televisies and radio's",
    "sg:phone":"+32 55 21 40 90",
    "sg:postcode":"9600",
    "sg:province":"Oost-Vlaanderen",
    "wof:name":"Cartona",
    "wof:placetype":"venue"
},
  "geometry": {"coordinates":[3.5811231136,50.748966217],"type":"Point"}
}