{
  "type": "Feature",
  "properties": {
    "addr:full":"Ellestraat 26b1 Gistel West-Vlaanderen 8470",
    "addr:housenumber":"26b1",
    "addr:postcode":"8470",
    "addr:street":"Ellestraat",
    "iso:country":"BE",
    "sg:address":"Ellestraat 26b1",
    "sg:city":"Gistel",
    "sg:orig_category":"M\u00e9decins and sp\u00e9cialistes",
    "sg:phone":"+32 59 27 99 11",
    "sg:postcode":"8470",
    "sg:province":"West-Vlaanderen",
    "wof:name":"Anne Van Cleemput",
    "wof:placetype":"venue"
},
  "geometry": {"coordinates":[2.9729270935,51.1570930481],"type":"Point"}
}