{
  "type": "Feature",
  "properties": {
    "iso:country":"BE",
    "sg:address":"Stationsstraat 86",
    "sg:city":"Jabbeke",
    "sg:classifiers":[
        {
            "category":"Manufacturing",
            "subcategory":"Metals",
            "type":"Manufacturing & Wholesale Goods"
        }
    ],
    "sg:phone":"+32 50 81 10 78",
    "sg:postcode":"8490",
    "sg:province":"West-Vlaanderen",
    "sg:tags":[
        "alloy",
        "construction",
        "lightweight"
    ],
    "wof:name":"Erpa B.v.b.a.",
    "wof:placetype":"venue"
},
  "geometry": {"coordinates":[3.0920510292,51.1942596436],"type":"Point"}
}