{
  "type": "Feature",
  "properties": {
    "addr:full":"Rue De La Wastinne 26 Wavre Brabant Wallon 1301",
    "addr:housenumber":"26;1301",
    "addr:street":"Rue De La Wastinne",
    "iso:country":"BE",
    "sg:address":"Rue De La Wastinne 26",
    "sg:city":"Wavre",
    "sg:orig_category":"Sportclubs",
    "sg:phone":"+32 10 41 46 19",
    "sg:postcode":"1301",
    "sg:province":"Brabant Wallon",
    "wof:name":"Road Runners Wavre",
    "wof:placetype":"venue"
},
  "geometry": {"coordinates":[4.5970611572,50.7075195312],"type":"Point"}
}