{
  "type": "Feature",
  "properties": {
    "iso:country":"BE",
    "sg:address":"Tulpenstraat 43",
    "sg:city":"Houthalen-helchteren (houthalen)",
    "sg:classifiers":[
        {
            "category":"Health Services",
            "subcategory":"Doctor",
            "type":"Services"
        }
    ],
    "sg:phone":"+32 89 38 36 22",
    "sg:postcode":"3530",
    "sg:province":"Limburg",
    "sg:tags":[
        "medicinephysicians",
        "surgeon"
    ],
    "wof:name":"Claes W",
    "wof:placetype":"venue"
},
  "geometry": {"coordinates":[5.4768691063,51.0210418701],"type":"Point"}
}