{
  "type": "Feature",
  "properties": {
    "iso:country":"BE",
    "sg:address":"Chauss\u00c9e D'alsemberg 136",
    "sg:city":"Sint-gillis/saint-gilles",
    "sg:orig_category":"Ordinateurs and \u00e9quipement informatique. Entretien and r\u00e9parations de machines de bureau and ordinat",
    "sg:phone":"+32 2 537 95 73",
    "sg:postcode":"1060",
    "sg:province":"Bruxelles-Capitale",
    "wof:name":"Bureau S.t.a.c.",
    "wof:placetype":"venue"
},
  "geometry": {"coordinates":[4.3428120613,50.8225517273],"type":"Point"}
}