{
  "type": "Feature",
  "properties": {
    "addr:full":"Korkentapstraat 2a Koekelare (zande) West-Vlaanderen 8680",
    "addr:housenumber":"2a",
    "addr:postcode":"8680",
    "addr:street":"Korkentapstraat",
    "iso:country":"BE",
    "sg:address":"Korkentapstraat 2a",
    "sg:city":"Koekelare (zande)",
    "sg:classifiers":[
        {
            "category":"Sports & Exercise",
            "subcategory":"Skate Park",
            "type":"Entertainment"
        }
    ],
    "sg:phone":"+32 59 27 44 53",
    "sg:postcode":"8680",
    "sg:province":"West-Vlaanderen",
    "sg:tags":[
        "mushroom"
    ],
    "wof:name":"Vanslambrouck P",
    "wof:placetype":"venue"
},
  "geometry": {"coordinates":[2.9781599045,51.0901832581],"type":"Point"}
}