{
  "type": "Feature",
  "properties": {
    "iso:country":"BE",
    "sg:address":"Tervuursevest 17-4",
    "sg:city":"Leuven (heverlee)",
    "sg:classifiers":[
        {
            "category":"Retail",
            "subcategory":"Repair Shop",
            "type":"Services"
        }
    ],
    "sg:phone":"+32 16 23 78 98",
    "sg:postcode":"3001",
    "sg:province":"Vlaams-Brabant",
    "sg:tags":[
        "radio",
        "television",
        "-",
        "maintenance"
    ],
    "wof:name":"Van Den Berghe P",
    "wof:placetype":"venue"
},
  "geometry": {"coordinates":[4.6825327873,50.8765487671],"type":"Point"}
}