{
  "type": "Feature",
  "properties": {
    "addr:full":"Rue Gilles Magn\u00e9e 1 Box 27 Ans Li\u00e8ge 4430",
    "addr:housenumber":"1 box 27",
    "addr:postcode":"4430",
    "addr:street":"Rue Gilles Magne\u0301E",
    "iso:country":"BE",
    "sg:address":"Rue Gilles Magn\u00e9e 1 Box 27",
    "sg:city":"Ans",
    "sg:classifiers":[
        {
            "category":"Health Services",
            "subcategory":"Doctor",
            "type":"Services"
        }
    ],
    "sg:phone":"+32 4 263 11 07",
    "sg:postcode":"4430",
    "sg:province":"Li\u00e8ge",
    "sg:tags":[
        "medicinephysicians",
        "surgeon"
    ],
    "wof:name":"Lemaire H",
    "wof:placetype":"venue"
},
  "geometry": {"coordinates":[5.531935215,50.6596717834],"type":"Point"}
}