{
  "type": "Feature",
  "properties": {
    "iso:country":"BE",
    "sg:address":"Rue Uyttenhove 45",
    "sg:city":"Bruxelles",
    "sg:classifiers":[
        {
            "category":"Shopping",
            "subcategory":"Clothing, Apparel, & Fashions",
            "type":"Retail Goods"
        }
    ],
    "sg:phone":"+32 2 420 23 50",
    "sg:postcode":"1090",
    "sg:province":"Bruxelles-Capitale",
    "sg:tags":[
        "textile",
        "clothing",
        "clothes"
    ],
    "wof:name":"Champion Belgium",
    "wof:placetype":"venue"
},
  "geometry": {"coordinates":[4.3369779587,50.8707542419],"type":"Point"}
}