{
  "type": "Feature",
  "properties": {
    "iso:country":"BE",
    "sg:address":"Rue De Tr\u00e8ves 53",
    "sg:city":"Bruxelles (etterbeek)",
    "sg:classifiers":[
        {
            "category":"Personal",
            "subcategory":"Beauty Salon",
            "type":"Services"
        }
    ],
    "sg:phone":"+32 2 285 00 80",
    "sg:postcode":"1040",
    "sg:province":"Bruxelles-Capitale",
    "sg:tags":[
        "product",
        "-",
        "apparatus"
    ],
    "wof:name":"Jean D'estrees/ Moureau",
    "wof:placetype":"venue"
},
  "geometry": {"coordinates":[4.3754558563,50.8429336548],"type":"Point"}
}