{
  "type": "Feature",
  "properties": {
    "addr:full":"Tisseltsesteenweg 33 Willebroek Antwerpen 2830",
    "addr:housenumber":"33",
    "addr:postcode":"2830",
    "addr:street":"Tisseltsesteenweg",
    "iso:country":"BE",
    "sg:address":"Tisseltsesteenweg 33",
    "sg:city":"Willebroek",
    "sg:orig_category":"M\u00e9decins and sp\u00e9cialistes",
    "sg:phone":"+32 3 886 21 21",
    "sg:postcode":"2830",
    "sg:province":"Antwerpen",
    "wof:name":"J. Moorthamers",
    "wof:placetype":"venue"
},
  "geometry": {"coordinates":[4.3579778671,51.052482605],"type":"Point"}
}