{
  "type": "Feature",
  "properties": {
    "iso:country":"BE",
    "sg:address":"Doorniksewijk 174",
    "sg:city":"Kortrijk",
    "sg:classifiers":[
        {
            "category":"Bars & Pubs",
            "type":"Food & Drink"
        }
    ],
    "sg:phone":"+32 56 45 51 66",
    "sg:postcode":"8500",
    "sg:province":"West-Vlaanderen",
    "wof:name":"Stove (de)",
    "wof:placetype":"venue"
},
  "geometry": {"coordinates":[3.2693910599,50.8178596497],"type":"Point"}
}