{
  "type": "Feature",
  "properties": {
    "addr:full":"Rue Rosier Bois 29 Rixensart Brabant Wallon 1331",
    "addr:housenumber":"29",
    "addr:postcode":"1331",
    "addr:street":"Rue Rosier Bois;Wallon",
    "iso:country":"BE",
    "sg:address":"Rue Rosier Bois 29",
    "sg:city":"Rixensart",
    "sg:orig_category":"Rev\u00eatements pour sols and murs. Peinture",
    "sg:phone":"+32 2 654 07 02",
    "sg:postcode":"1331",
    "sg:province":"Brabant Wallon",
    "wof:name":"Peintagor",
    "wof:placetype":"venue"
},
  "geometry": {"coordinates":[4.5418701172,50.7309150696],"type":"Point"}
}