{
  "type": "Feature",
  "properties": {
    "addr:full":"Rue D'aywaille 6 Comblain-au-pont Li\u00e8ge 4170",
    "addr:housenumber":"6",
    "addr:postcode":"4170",
    "addr:street":"Rue D'Aywaille",
    "iso:country":"BE",
    "sg:address":"Rue D'aywaille 6",
    "sg:city":"Comblain-au-pont",
    "sg:classifiers":[
        {
            "category":"Restaurant",
            "type":"Food & Drink"
        }
    ],
    "sg:phone":"+32 4 369 16 04",
    "sg:postcode":"4170",
    "sg:province":"Li\u00e8ge",
    "sg:tags":[
        "caf\u00e9s"
    ],
    "wof:name":"Taverne Des Sports",
    "wof:placetype":"venue"
},
  "geometry": {"coordinates":[5.5910382271,50.4797515869],"type":"Point"}
}