{
  "type": "Feature",
  "properties": {
    "addr:full":"Baanstknokstraat 74 Waregem West-Vlaanderen 8790",
    "addr:housenumber":"74",
    "addr:postcode":"8790",
    "addr:street":"Baanstknokstraat",
    "iso:country":"BE",
    "sg:address":"Baanstknokstraat 74",
    "sg:city":"Waregem",
    "sg:orig_category":"Epiceries",
    "sg:phone":"+32 56 60 31 70",
    "sg:postcode":"8790",
    "sg:province":"West-Vlaanderen",
    "wof:name":"Landy",
    "wof:placetype":"venue"
},
  "geometry": {"coordinates":[3.4110569954,50.891998291],"type":"Point"}
}