{
  "type": "Feature",
  "properties": {
    "addr:full":"Avenue Gaston Mertens 12a Braine-le-ch\u00e2teau (wauthier-braine) Brabant Wallon 1440",
    "addr:housenumber":"12a",
    "addr:postcode":"1440",
    "addr:street":"Avenue Gaston Mertens",
    "iso:country":"BE",
    "sg:address":"Avenue Gaston Mertens 12a",
    "sg:city":"Braine-le-ch\u00e2teau (wauthier-braine)",
    "sg:classifiers":[
        {
            "category":"Retail",
            "subcategory":"Auto Repair",
            "type":"Services"
        }
    ],
    "sg:phone":"+32 2 366 91 95",
    "sg:postcode":"1440",
    "sg:province":"Brabant Wallon",
    "sg:tags":[
        "automobile-body"
    ],
    "wof:name":"Schoonheyt B",
    "wof:placetype":"venue"
},
  "geometry": {"coordinates":[4.2976989746,50.682220459],"type":"Point"}
}