{
  "type": "Feature",
  "properties": {
    "iso:country":"BE",
    "sg:address":"Latemstraat 123",
    "sg:city":"Sint-martens-latem",
    "sg:classifiers":[
        {
            "category":"Health Services",
            "subcategory":"Doctor",
            "type":"Services"
        }
    ],
    "sg:phone":"+32 9 281 17 27",
    "sg:postcode":"9830",
    "sg:province":"Oost-Vlaanderen",
    "sg:tags":[
        "medicinephysicians",
        "surgeon"
    ],
    "wof:name":"De Craene Annick",
    "wof:placetype":"venue"
},
  "geometry": {"coordinates":[3.6299080849,51.0150871277],"type":"Point"}
}