{
  "type": "Feature",
  "properties": {
    "iso:country":"BE",
    "sg:address":"Waregemsesteenweg 94",
    "sg:city":"Kruishoutem (groot)",
    "sg:classifiers":[
        {
            "category":"Restaurant",
            "type":"Food & Drink"
        }
    ],
    "sg:phone":"+32 9 383 01 18",
    "sg:postcode":"9770",
    "sg:province":"Oost-Vlaanderen",
    "wof:name":"'t Pleintje",
    "wof:placetype":"venue"
},
  "geometry": {"coordinates":[3.5166790485,50.9014091492],"type":"Point"}
}