{
  "type": "Feature",
  "properties": {
    "addr:full":"M\u00fcrringen 16a B\u00fcllingen Li\u00e8ge 4760",
    "addr:housenumber":"16a",
    "addr:postcode":"4760",
    "addr:street":"Muerringen",
    "iso:country":"BE",
    "sg:address":"M\u00fcrringen 16a",
    "sg:city":"B\u00fcllingen",
    "sg:orig_category":"Non-Classified Establishments",
    "sg:phone":"+32 80 64 25 86",
    "sg:postcode":"4760",
    "sg:province":"Li\u00e8ge",
    "wof:name":"Velz H",
    "wof:placetype":"venue"
},
  "geometry": {"coordinates":[6.2557492256,50.4061813354],"type":"Point"}
}