{
  "type": "Feature",
  "properties": {
    "addr:full":"Heidestatiestraat 34 Kalmthout Antwerpen 2920",
    "addr:housenumber":"34",
    "addr:postcode":"2920",
    "addr:street":"Heidestatiestraat",
    "iso:country":"BE",
    "sg:address":"Heidestatiestraat 34",
    "sg:city":"Kalmthout",
    "sg:classifiers":[
        {
            "category":"Health Services",
            "subcategory":"Dentist",
            "type":"Services"
        }
    ],
    "sg:phone":"+32 3 666 76 48",
    "sg:postcode":"2920",
    "sg:province":"Antwerpen",
    "wof:name":"Dickers Bart",
    "wof:placetype":"venue"
},
  "geometry": {"coordinates":[4.4632868767,51.3653373718],"type":"Point"}
}