{
  "type": "Feature",
  "properties": {
    "iso:country":"BE",
    "sg:address":"Avenue De Forest 24",
    "sg:city":"Rochefort",
    "sg:orig_category":"Kapsalons",
    "sg:phone":"+32 84 22 32 50",
    "sg:postcode":"5580",
    "sg:province":"Namur",
    "wof:name":"Coiffure Nadia",
    "wof:placetype":"venue"
},
  "geometry": {"coordinates":[5.2219071388,50.1581840515],"type":"Point"}
}