{
  "type": "Feature",
  "properties": {
    "iso:country":"BE",
    "sg:address":"Rue Henry Fays 1a",
    "sg:city":"Anthisnes",
    "sg:orig_category":"Loodgieterij, verwarming and sanitaire installaties Viessmann",
    "sg:phone":"+32 4 383 61 80",
    "sg:postcode":"4160",
    "sg:province":"Li\u00e8ge",
    "wof:name":"Antoine Pere Et Fils",
    "wof:placetype":"venue"
},
  "geometry": {"coordinates":[5.519302845,50.4793739319],"type":"Point"}
}