{
  "type": "Feature",
  "properties": {
    "iso:country":"BE",
    "sg:address":"Avenue Du Bois L'ev\u00eaque 24",
    "sg:city":"Namur (wierde)",
    "sg:orig_category":"Non-Classified Establishments",
    "sg:phone":"+32 81 40 02 30",
    "sg:postcode":"5100",
    "sg:province":"Namur",
    "wof:name":"Salaisons Namuroises",
    "wof:placetype":"venue"
},
  "geometry": {"coordinates":[4.9275531769,50.4427757263],"type":"Point"}
}