{
  "type": "Feature",
  "properties": {
    "iso:country":"BE",
    "sg:address":"Liverpoolstraat 43",
    "sg:city":"Brussel",
    "sg:classifiers":[
        {
            "category":"Professional",
            "subcategory":"Printing & Photocopies",
            "type":"Services"
        }
    ],
    "sg:phone":"+32 2 523 29 83",
    "sg:postcode":"1080",
    "sg:province":"Bruxelles-Capitale",
    "sg:tags":[
        "offset"
    ],
    "wof:name":"Dembla B.v.b.a.",
    "wof:placetype":"venue"
},
  "geometry": {"coordinates":[4.3314518929,50.8456344604],"type":"Point"}
}