{
  "type": "Feature",
  "properties": {
    "iso:country":"BE",
    "sg:address":"Brusselstraat 285",
    "sg:city":"Dilbeek (groot - Bijgaarden)",
    "sg:classifiers":[
        {
            "category":"Education",
            "subcategory":"School",
            "type":"Public Place"
        }
    ],
    "sg:phone":"+32 2 466 28 46",
    "sg:postcode":"1702",
    "sg:province":"Vlaams-Brabant",
    "sg:tags":[
        "secondary"
    ],
    "wof:name":"Zusters Van Don Bosco",
    "wof:placetype":"venue"
},
  "geometry": {"coordinates":[4.2584958076,50.8706321716],"type":"Point"}
}