{
  "type": "Feature",
  "properties": {
    "addr:full":"H Moeremanslaan 101 Dilbeek Vlaams-Brabant 1700",
    "addr:housenumber":"101",
    "addr:postcode":"1700",
    "addr:street":"Moeremanslaan",
    "iso:country":"BE",
    "sg:address":"H Moeremanslaan 101",
    "sg:city":"Dilbeek",
    "sg:orig_category":"Drukkerijen and copyshops",
    "sg:phone":"+32 2 466 82 64",
    "sg:postcode":"1700",
    "sg:province":"Vlaams-Brabant",
    "wof:name":"Graficam Printing",
    "wof:placetype":"venue"
},
  "geometry": {"coordinates":[4.2744908333,50.846912384],"type":"Point"}
}