{
  "type": "Feature",
  "properties": {
    "iso:country":"BE",
    "sg:address":"Rue Du Commerce 15",
    "sg:city":"Wavre",
    "sg:orig_category":"Baby- and kinderkleding",
    "sg:phone":"+32 10 24 26 25",
    "sg:postcode":"1300",
    "sg:province":"Brabant Wallon",
    "wof:name":"Chinouk",
    "wof:placetype":"venue"
},
  "geometry": {"coordinates":[4.6099281311,50.7164344788],"type":"Point"}
}