{
  "type": "Feature",
  "properties": {
    "iso:country":"BE",
    "sg:address":"Daalderstraat 3",
    "sg:city":"Lichtervelde",
    "sg:orig_category":"Rundveehouders Varkenskwekers",
    "sg:phone":"+32 51 72 20 29",
    "sg:postcode":"8810",
    "sg:province":"West-Vlaanderen",
    "wof:name":"Herman Roels",
    "wof:placetype":"venue"
},
  "geometry": {"coordinates":[3.1708250046,51.0168266296],"type":"Point"}
}