{
  "type": "Feature",
  "properties": {
    "addr:full":"Oude Vladslostraat 3 Kortemark West-Vlaanderen 8610",
    "addr:housenumber":"3",
    "addr:postcode":"8610",
    "addr:street":"Oude Vladslostraat",
    "iso:country":"BE",
    "sg:address":"Oude Vladslostraat 3",
    "sg:city":"Kortemark",
    "sg:orig_category":"Rundveehouders",
    "sg:phone":"+32 51 56 60 36",
    "sg:postcode":"8610",
    "sg:province":"West-Vlaanderen",
    "wof:name":"Johan Ameloot",
    "wof:placetype":"venue"
},
  "geometry": {"coordinates":[2.951114893,51.0370864868],"type":"Point"}
}