{
  "type": "Feature",
  "properties": {
    "addr:full":"Rue No\u00ebl Heine 31 Awans Li\u00e8ge 4340",
    "addr:housenumber":"31",
    "addr:postcode":"4340",
    "addr:street":"Rue Noe\u0308L Heine",
    "iso:country":"BE",
    "sg:address":"Rue No\u00ebl Heine 31",
    "sg:city":"Awans",
    "sg:classifiers":[
        {
            "category":"Restaurant",
            "type":"Food & Drink"
        }
    ],
    "sg:phone":"+32 4 247 04 37",
    "sg:postcode":"4340",
    "sg:province":"Li\u00e8ge",
    "sg:tags":[
        "industrial",
        "kitchen",
        "catering"
    ],
    "wof:name":"W\u00e9ry R",
    "wof:placetype":"venue"
},
  "geometry": {"coordinates":[5.4657459259,50.6688537598],"type":"Point"}
}