{
  "type": "Feature",
  "properties": {
    "iso:country":"BE",
    "sg:address":"Tervuursesteenweg 43",
    "sg:city":"Leuven",
    "sg:orig_category":"Kapsalons",
    "sg:phone":"+32 16 22 56 89",
    "sg:postcode":"3001",
    "sg:province":"Vlaams-Brabant",
    "wof:name":"Coiffure Germaine",
    "wof:placetype":"venue"
},
  "geometry": {"coordinates":[4.6814818382,50.8763008118],"type":"Point"}
}