{
  "type": "Feature",
  "properties": {
    "addr:full":"Rue Des Ardennes 342 Beauraing Namur 5570",
    "addr:housenumber":"342",
    "addr:postcode":"5570",
    "addr:street":"Rue Des Ardennes",
    "iso:country":"BE",
    "sg:address":"Rue Des Ardennes 342",
    "sg:city":"Beauraing",
    "sg:orig_category":"V\u00e9t\u00e9rinaires",
    "sg:phone":"+32 82 71 25 20",
    "sg:postcode":"5570",
    "sg:province":"Namur",
    "wof:name":"Marc Bourlon",
    "wof:placetype":"venue"
},
  "geometry": {"coordinates":[4.9469399452,50.1016616821],"type":"Point"}
}