{
  "type": "Feature",
  "properties": {
    "addr:full":"Dentergemstraat 7 Dentergem West-Vlaanderen 8720",
    "addr:housenumber":"7",
    "addr:postcode":"8720",
    "addr:street":"Dentergemstraat",
    "iso:country":"BE",
    "sg:address":"Dentergemstraat 7",
    "sg:city":"Dentergem",
    "sg:classifiers":[
        {
            "category":"Personal",
            "subcategory":"Beauty Salon",
            "type":"Services"
        }
    ],
    "sg:phone":"+32 51 63 41 07",
    "sg:postcode":"8720",
    "sg:province":"West-Vlaanderen",
    "sg:tags":[
        "de",
        "coiffure"
    ],
    "wof:name":"Coiffure Rita",
    "wof:placetype":"venue"
},
  "geometry": {"coordinates":[3.4023420811,50.9464836121],"type":"Point"}
}