{
  "type": "Feature",
  "properties": {
    "iso:country":"BE",
    "sg:address":"Broederl. Weversplein 253",
    "sg:city":"Gent",
    "sg:orig_category":"Apotheken",
    "sg:phone":"+32 9 226 32 48",
    "sg:postcode":"9000",
    "sg:province":"Oost-Vlaanderen",
    "wof:name":"Apotheek Vooruit",
    "wof:placetype":"venue"
},
  "geometry": {"coordinates":[3.6990299225,51.0532493591],"type":"Point"}
}