{
  "type": "Feature",
  "properties": {
    "iso:country":"BE",
    "sg:address":"Kerkbossenstraat 35",
    "sg:city":"Heist-op-den-berg",
    "sg:classifiers":[
        {
            "category":"Personal",
            "subcategory":"Beauty Salon",
            "type":"Services"
        }
    ],
    "sg:phone":"+32 15 24 17 65",
    "sg:postcode":"2220",
    "sg:province":"Antwerpen",
    "sg:tags":[
        "de",
        "coiffure"
    ],
    "wof:name":"Coiffure Julien",
    "wof:placetype":"venue"
},
  "geometry": {"coordinates":[4.7043251991,51.070690155],"type":"Point"}
}