{
  "type": "Feature",
  "properties": {
    "addr:full":"Heid De Bioleux 6 Neupr\u00e9 (plainevaux) Li\u00e8ge 4122",
    "addr:housenumber":"6",
    "addr:postcode":"4122",
    "addr:street":"Heid;Bioleux;Plainevaux",
    "iso:country":"BE",
    "sg:address":"Heid De Bioleux 6",
    "sg:city":"Neupr\u00e9 (plainevaux)",
    "sg:classifiers":[
        {
            "category":"Real Estate",
            "subcategory":"Architect",
            "type":"Services"
        }
    ],
    "sg:phone":"+32 4 372 90 95",
    "sg:postcode":"4122",
    "sg:province":"Li\u00e8ge",
    "wof:name":"Dessart Ph",
    "wof:placetype":"venue"
},
  "geometry": {"coordinates":[5.5085201263,50.5399551392],"type":"Point"}
}