{
  "type": "Feature",
  "properties": {
    "addr:full":"Melselestraat 15 Beveren Oost-Vlaanderen 9120",
    "addr:housenumber":"15",
    "addr:postcode":"9120",
    "addr:street":"Melselestraat",
    "iso:country":"BE",
    "sg:address":"Melselestraat 15",
    "sg:city":"Beveren",
    "sg:orig_category":"Fleurs and plantes. P\u00e9pini\u00e9ristes. Articles de jardin. Jardinage",
    "sg:phone":"+32 3 775 72 47",
    "sg:postcode":"9120",
    "sg:province":"Oost-Vlaanderen",
    "wof:name":"Boomkwekerijen De Wolf",
    "wof:placetype":"venue"
},
  "geometry": {"coordinates":[4.2665882111,51.1939353943],"type":"Point"}
}