{
  "type": "Feature",
  "properties": {
    "iso:country":"BE",
    "sg:address":"Markt 1",
    "sg:city":"Damme",
    "sg:classifiers":[
        {
            "category":"Shopping",
            "subcategory":"Books",
            "type":"Retail Goods"
        }
    ],
    "sg:phone":"+32 50 38 05 43",
    "sg:postcode":"8340",
    "sg:province":"West-Vlaanderen",
    "sg:tags":[
        "bookseller"
    ],
    "wof:name":"Boekenoase (de)",
    "wof:placetype":"venue"
},
  "geometry": {"coordinates":[3.2816390991,51.2517089844],"type":"Point"}
}