{
  "type": "Feature",
  "properties": {
    "iso:country":"BE",
    "sg:address":"Rue De Li\u00c8ge 39",
    "sg:city":"Oreye",
    "sg:orig_category":"Experts-comptables",
    "sg:phone":"+32 19 67 75 81",
    "sg:postcode":"4360",
    "sg:province":"Li\u00e8ge",
    "wof:name":"Alexis Gregoire",
    "wof:placetype":"venue"
},
  "geometry": {"coordinates":[5.3615689278,50.7271881104],"type":"Point"}
}