{
  "type": "Feature",
  "properties": {
    "addr:full":"Rue De L'amiti\u00c9 17 Seraing Li\u00e8ge 4102",
    "addr:housenumber":"17",
    "addr:postcode":"4102",
    "addr:street":"Rue De L'Amitie \u0301",
    "iso:country":"BE",
    "sg:address":"Rue De L'amiti\u00c9 17",
    "sg:city":"Seraing",
    "sg:orig_category":"Diverse bouwafwerking and reiniging Gespecialiseerde residenti\u00eble bouw Installatie van metalen schri",
    "sg:phone":"+32 4 336 86 58",
    "sg:postcode":"4102",
    "sg:province":"Li\u00e8ge",
    "wof:name":"Calicetto Fr\u00c8res",
    "wof:placetype":"venue"
},
  "geometry": {"coordinates":[5.5455131531,50.5811462402],"type":"Point"}
}