{
  "type": "Feature",
  "properties": {
    "iso:country":"BE",
    "sg:address":"Statiestraat 30",
    "sg:city":"Mol",
    "sg:classifiers":[
        {
            "category":"Cafe",
            "type":"Food & Drink"
        }
    ],
    "sg:phone":"+32 14 31 67 59",
    "sg:postcode":"2400",
    "sg:province":"Antwerpen",
    "sg:tags":[
        "snack-bars"
    ],
    "wof:name":"Edal",
    "wof:placetype":"venue"
},
  "geometry": {"coordinates":[5.1182022095,51.1898498535],"type":"Point"}
}