{
  "type": "Feature",
  "properties": {
    "iso:country":"BE",
    "sg:address":"Rue Fran\u00c7ois-hittelet 158",
    "sg:city":"Jemeppe-sur-sambre",
    "sg:orig_category":"Rusthuizen and serviceflats",
    "sg:phone":"+32 71 78 48 59",
    "sg:postcode":"5190",
    "sg:province":"Namur",
    "wof:name":"R\u00c9sidence Bourguignon",
    "wof:placetype":"venue"
},
  "geometry": {"coordinates":[4.664563179,50.4613990784],"type":"Point"}
}