{
  "type": "Feature",
  "properties": {
    "iso:country":"BE",
    "sg:address":"Rue De La Chav\u00e9e 3c",
    "sg:city":"Mettet",
    "sg:classifiers":[
        {
            "category":"Health Services",
            "subcategory":"Health Practitioner",
            "type":"Services"
        }
    ],
    "sg:phone":"+32 71 72 79 23",
    "sg:postcode":"5640",
    "sg:province":"Namur",
    "sg:tags":[
        "physiotherapist"
    ],
    "wof:name":"Dagneaux M",
    "wof:placetype":"venue"
},
  "geometry": {"coordinates":[4.6570601463,50.3175697327],"type":"Point"}
}