{
  "type": "Feature",
  "properties": {
    "iso:country":"BE",
    "sg:address":"Laar 173",
    "sg:city":"Geel",
    "sg:orig_category":"Fleurs and plantes",
    "sg:phone":"+32 14 59 12 08",
    "sg:postcode":"2440",
    "sg:province":"Antwerpen",
    "wof:name":"Liliana Kerckhofs",
    "wof:placetype":"venue"
},
  "geometry": {"coordinates":[5.0165781975,51.1608428955],"type":"Point"}
}