{
  "type": "Feature",
  "properties": {
    "addr:full":"Rue Du Jeu De Balle 1 Houyet (custinne) Namur 5562",
    "addr:housenumber":"1",
    "addr:postcode":"5562",
    "addr:street":"Rue Du Jeu De Balle",
    "iso:country":"BE",
    "sg:address":"Rue Du Jeu De Balle 1",
    "sg:city":"Houyet (custinne)",
    "sg:classifiers":[
        {
            "category":"Banks & Credit Unions",
            "subcategory":"Financial Services",
            "type":"Services"
        }
    ],
    "sg:phone":"+32 82 66 64 66",
    "sg:postcode":"5562",
    "sg:province":"Namur",
    "sg:tags":[
        "loan",
        "mortgage"
    ],
    "wof:name":"Champagne E",
    "wof:placetype":"venue"
},
  "geometry": {"coordinates":[5.0506510735,50.2102928162],"type":"Point"}
}