{
  "type": "Feature",
  "properties": {
    "addr:full":"Elzestraat 26 Beveren Oost-Vlaanderen 9120",
    "addr:housenumber":"26",
    "addr:postcode":"9120",
    "addr:street":"Elzestraat",
    "iso:country":"BE",
    "sg:address":"Elzestraat 26",
    "sg:city":"Beveren",
    "sg:orig_category":"Rev\u00eatements de sols and murs",
    "sg:phone":"+32 3 755 48 69",
    "sg:postcode":"9120",
    "sg:province":"Oost-Vlaanderen",
    "wof:name":"Gert Robert",
    "wof:placetype":"venue"
},
  "geometry": {"coordinates":[4.2295589447,51.2200775146],"type":"Point"}
}