{
  "type": "Feature",
  "properties": {
    "addr:full":"Mechelsesteenweg 2 Mortsel Antwerpen 2640",
    "addr:housenumber":"2",
    "addr:postcode":"2640",
    "addr:street":"Mechelsesteenweg",
    "iso:country":"BE",
    "sg:address":"Mechelsesteenweg 2",
    "sg:city":"Mortsel",
    "sg:classifiers":[
        {
            "category":"Bars & Pubs",
            "type":"Food & Drink"
        }
    ],
    "sg:phone":"+32 3 449 68 50",
    "sg:postcode":"2640",
    "sg:province":"Antwerpen",
    "sg:tags":[
        "tavern"
    ],
    "wof:name":"De Nieuwe Stad",
    "wof:placetype":"venue"
},
  "geometry": {"coordinates":[4.4500808716,51.1695404053],"type":"Point"}
}