{
  "type": "Feature",
  "properties": {
    "iso:country":"BE",
    "sg:address":"Jos Nuytsdreef 4",
    "sg:city":"Brecht",
    "sg:classifiers":[
        {
            "category":"Shopping",
            "subcategory":"Stationery & Office Supplies",
            "type":"Retail Goods"
        }
    ],
    "sg:phone":"+32 3 633 21 88",
    "sg:postcode":"2960",
    "sg:province":"Antwerpen",
    "sg:tags":[
        "partition"
    ],
    "wof:name":"Dillien",
    "wof:placetype":"venue"
},
  "geometry": {"coordinates":[4.5582637787,51.311050415],"type":"Point"}
}