{
  "type": "Feature",
  "properties": {
    "iso:country":"BE",
    "sg:address":"Rue De L\u00b4ermitage 66",
    "sg:city":"Neupre",
    "sg:orig_category":"M\u00e9decins and sp\u00e9cialistes",
    "sg:phone":"+32 4 371 55 34",
    "sg:postcode":"4121",
    "sg:province":"Li\u00e8ge",
    "wof:name":"B. Detroz",
    "wof:placetype":"venue"
},
  "geometry": {"coordinates":[5.4676790237,50.5547828674],"type":"Point"}
}