{
  "type": "Feature",
  "properties": {
    "iso:country":"BE",
    "sg:address":"Rue De La Station 54",
    "sg:city":"Walhain (tourinnes-saint-lambert)",
    "sg:classifiers":[
        {
            "category":"Professional",
            "subcategory":"Employment Agencies",
            "type":"Services"
        }
    ],
    "sg:phone":"+32 10 41 48 28",
    "sg:postcode":"1457",
    "sg:province":"Brabant Wallon",
    "sg:tags":[
        "-",
        "processing",
        "data"
    ],
    "wof:name":"Ez-it",
    "wof:placetype":"venue"
},
  "geometry": {"coordinates":[4.7240161896,50.6267318726],"type":"Point"}
}