{
  "type": "Feature",
  "properties": {
    "addr:full":"Godveerdegemstraat 207 Zottegem Oost-Vlaanderen 9620",
    "addr:housenumber":"207",
    "addr:postcode":"9620",
    "addr:street":"Godveerdegemstraat",
    "iso:country":"BE",
    "sg:address":"Godveerdegemstraat 207",
    "sg:city":"Zottegem",
    "sg:classifiers":[
        {
            "category":"Retail",
            "subcategory":"Auto Repair",
            "type":"Services"
        }
    ],
    "sg:phone":"+32 9 360 23 83",
    "sg:postcode":"9620",
    "sg:province":"Oost-Vlaanderen",
    "sg:tags":[
        "garage"
    ],
    "wof:name":"De Vroe G",
    "wof:placetype":"venue"
},
  "geometry": {"coordinates":[3.8283069134,50.8637046814],"type":"Point"}
}