{
  "type": "Feature",
  "properties": {
    "addr:full":"Route De Genval 132 Lasne (ohain) Brabant Wallon 1380",
    "addr:housenumber":"132",
    "addr:postcode":"1380",
    "addr:street":"Route De Genval;Wallon",
    "iso:country":"BE",
    "sg:address":"Route De Genval 132",
    "sg:city":"Lasne (ohain)",
    "sg:classifiers":[
        {
            "category":"Food & Beverages",
            "subcategory":"Liquor & Beverages",
            "type":"Retail Goods"
        }
    ],
    "sg:phone":"+32 2 653 80 70",
    "sg:postcode":"1380",
    "sg:province":"Brabant Wallon",
    "sg:tags":[
        "-",
        "spirit",
        "wine"
    ],
    "wof:name":"Debeuf J",
    "wof:placetype":"venue"
},
  "geometry": {"coordinates":[4.483235836,50.6850166321],"type":"Point"}
}