{
  "type": "Feature",
  "properties": {
    "addr:full":"Avenue Du Luxembourg 41 Li\u00e8ge 1 (li\u00e8ge 2) Li\u00e8ge 4020",
    "addr:housenumber":"41;1;2",
    "addr:postcode":"4020",
    "addr:street":"Avenue Du Luxembourg",
    "iso:country":"BE",
    "sg:address":"Avenue Du Luxembourg 41",
    "sg:city":"Li\u00e8ge 1 (li\u00e8ge 2)",
    "sg:classifiers":[
        {
            "category":"Professional",
            "type":"Services"
        }
    ],
    "sg:phone":"+32 4 222 15 50",
    "sg:postcode":"4020",
    "sg:province":"Li\u00e8ge",
    "sg:tags":[
        "entertainer"
    ],
    "wof:name":"Ness Sprl",
    "wof:placetype":"venue"
},
  "geometry": {"coordinates":[5.5881209373,50.622592926],"type":"Point"}
}