{
  "type": "Feature",
  "properties": {
    "addr:full":"Kaai 9 Geraardsbergen Oost-Vlaanderen 9500",
    "addr:housenumber":"9",
    "addr:postcode":"9500",
    "addr:street":"Kaai",
    "iso:country":"BE",
    "sg:address":"Kaai 9",
    "sg:city":"Geraardsbergen",
    "sg:orig_category":"Brood, gebak and snoepgoed",
    "sg:phone":"+32 54 42 34 16",
    "sg:postcode":"9500",
    "sg:province":"Oost-Vlaanderen",
    "wof:name":"Bakkerij Kaai 9",
    "wof:placetype":"venue"
},
  "geometry": {"coordinates":[3.8802070618,50.7722358704],"type":"Point"}
}