{
  "type": "Feature",
  "properties": {
    "addr:full":"Fruithoflaan 7 Lier (koningshooikt) Antwerpen 2500",
    "addr:housenumber":"7",
    "addr:postcode":"2500",
    "addr:street":"Fruithoflaan",
    "iso:country":"BE",
    "sg:address":"Fruithoflaan 7",
    "sg:city":"Lier (koningshooikt)",
    "sg:classifiers":[
        {
            "category":"Banks & Credit Unions",
            "subcategory":"Investment Brokerage",
            "type":"Services"
        }
    ],
    "sg:phone":"+32 3 482 49 68",
    "sg:postcode":"2500",
    "sg:province":"Antwerpen",
    "wof:name":"Daytraderplaza Bvba",
    "wof:placetype":"venue"
},
  "geometry": {"coordinates":[4.6094141006,51.0897102356],"type":"Point"}
}