{
  "type": "Feature",
  "properties": {
    "addr:full":"Lepelstraat 89 Laarne Oost-Vlaanderen 9270",
    "addr:housenumber":"89",
    "addr:postcode":"9270",
    "addr:street":"Lepelstraat",
    "iso:country":"BE",
    "sg:address":"Lepelstraat 89",
    "sg:city":"Laarne",
    "sg:orig_category":"Herstellingen and onderhoud van auto's",
    "sg:phone":"+32 9 369 21 24",
    "sg:postcode":"9270",
    "sg:province":"Oost-Vlaanderen",
    "wof:name":"Van Herreweghe Marc",
    "wof:placetype":"venue"
},
  "geometry": {"coordinates":[3.8538448811,51.0350341797],"type":"Point"}
}