{
  "type": "Feature",
  "properties": {
    "iso:country":"BE",
    "sg:address":"Van Benedenlaan 31",
    "sg:city":"Mechelen",
    "sg:orig_category":"Landmeters and schatters",
    "sg:phone":"+32 15 42 29 92",
    "sg:postcode":"2800",
    "sg:province":"Antwerpen",
    "wof:name":"Willem Putters",
    "wof:placetype":"venue"
},
  "geometry": {"coordinates":[4.4755220413,51.0213661194],"type":"Point"}
}