{
  "type": "Feature",
  "properties": {
    "iso:country":"BE",
    "sg:address":"Dennenstraat 2",
    "sg:city":"Zemst (elewijt)",
    "sg:classifiers":[
        {
            "category":"Building & Trades",
            "subcategory":"Construction",
            "type":"Services"
        }
    ],
    "sg:phone":"+32 15 43 34 38",
    "sg:postcode":"1982",
    "sg:province":"Vlaams-Brabant",
    "sg:tags":[
        "ceiling"
    ],
    "wof:name":"Renovall Bvba",
    "wof:placetype":"venue"
},
  "geometry": {"coordinates":[4.4980359077,50.9733276367],"type":"Point"}
}