{
  "type": "Feature",
  "properties": {
    "addr:full":"Volksv. Tahonstraat 23 Kortrijk West-Vlaanderen 8500",
    "addr:housenumber":"23",
    "addr:postcode":"8500",
    "addr:street":"Tahonstraat",
    "iso:country":"BE",
    "sg:address":"Volksv. Tahonstraat 23",
    "sg:city":"Kortrijk",
    "sg:orig_category":"Woningbouw",
    "sg:phone":"+32 56 21 77 19",
    "sg:postcode":"8500",
    "sg:province":"West-Vlaanderen",
    "wof:name":"Brepal",
    "wof:placetype":"venue"
},
  "geometry": {"coordinates":[3.2650549412,50.827999115],"type":"Point"}
}