{
  "type": "Feature",
  "properties": {
    "addr:full":"Rue Charlier 6 Lasne Brabant Wallon 1380",
    "addr:housenumber":"6",
    "addr:postcode":"1380",
    "addr:street":"Rue Charlier",
    "iso:country":"BE",
    "sg:address":"Rue Charlier 6",
    "sg:city":"Lasne",
    "sg:orig_category":"Activit\u00e9s r\u00e9cr\u00e9atives diverses",
    "sg:phone":"+32 2 633 40 15",
    "sg:postcode":"1380",
    "sg:province":"Brabant Wallon",
    "wof:name":"L'atelier Des Loisirs",
    "wof:placetype":"venue"
},
  "geometry": {"coordinates":[4.4957299232,50.6704330444],"type":"Point"}
}