{
  "type": "Feature",
  "properties": {
    "addr:full":"Rue Du Pont-du-roy 14 Couvin Namur 5660",
    "addr:housenumber":"14",
    "addr:postcode":"5660",
    "addr:street":"Rue Du Pont-Du-Roy",
    "iso:country":"BE",
    "sg:address":"Rue Du Pont-du-roy 14",
    "sg:city":"Couvin",
    "sg:orig_category":"Benzinestations and brandstoffen Herstellingen and onderhoud van auto's",
    "sg:phone":"+32 60 34 68 34",
    "sg:postcode":"5660",
    "sg:province":"Namur",
    "wof:name":"Dealer Wanet & Fils",
    "wof:placetype":"venue"
},
  "geometry": {"coordinates":[4.5009160042,50.04246521],"type":"Point"}
}