{
  "type": "Feature",
  "properties": {
    "iso:country":"BE",
    "sg:address":"Zwijgershoek 5",
    "sg:city":"Sint-niklaas",
    "sg:orig_category":"Kapsalons",
    "sg:phone":"+32 3 776 36 54",
    "sg:postcode":"9100",
    "sg:province":"Oost-Vlaanderen",
    "wof:name":"Coiffure Jeunesse",
    "wof:placetype":"venue"
},
  "geometry": {"coordinates":[4.1442699432,51.166229248],"type":"Point"}
}