{
  "type": "Feature",
  "properties": {
    "addr:full":"Opheldingsweg 29-31 Zonhoven Limburg 3520",
    "addr:postcode":"29-31 zonhoven;3520",
    "iso:country":"BE",
    "sg:address":"Opheldingsweg 29-31",
    "sg:city":"Zonhoven",
    "sg:orig_category":"Produits chimiques Equipement divers pour commerces Gr",
    "sg:phone":"+32 11 81 91 41",
    "sg:postcode":"3520",
    "sg:province":"Limburg",
    "wof:name":"Bielen Produkten",
    "wof:placetype":"venue"
},
  "geometry": {"coordinates":[5.3566761017,50.980342865],"type":"Point"}
}