{
  "type": "Feature",
  "properties": {
    "addr:full":"Chauss\u00e9e De Marche 431 Namur (erpent) Namur 5101",
    "addr:housenumber":"431",
    "addr:postcode":"5101",
    "addr:street":"Chausse\u0301E De Marche",
    "iso:country":"BE",
    "sg:address":"Chauss\u00e9e De Marche 431",
    "sg:city":"Namur (erpent)",
    "sg:classifiers":[
        {
            "category":"Food & Beverages",
            "subcategory":"Fruits & Vegetables",
            "type":"Retail Goods"
        }
    ],
    "sg:phone":"+32 81 30 63 63",
    "sg:postcode":"5101",
    "sg:province":"Namur",
    "sg:tags":[
        "-"
    ],
    "wof:name":"Fruiland",
    "wof:placetype":"venue"
},
  "geometry": {"coordinates":[4.8955302238,50.4481391907],"type":"Point"}
}