{
  "type": "Feature",
  "properties": {
    "addr:full":"Place De Tourpes 12a Leuze-en-hainaut (tourpes) Hainaut 7904",
    "addr:housenumber":"12a",
    "addr:postcode":"7904",
    "addr:street":"Place De Tourpes",
    "iso:country":"BE",
    "sg:address":"Place De Tourpes 12a",
    "sg:city":"Leuze-en-hainaut (tourpes)",
    "sg:classifiers":[
        {
            "category":"Food & Beverages",
            "subcategory":"Groceries & Convenience Stores",
            "type":"Retail Goods"
        }
    ],
    "sg:phone":"+32 69 67 13 39",
    "sg:postcode":"7904",
    "sg:province":"Hainaut",
    "sg:tags":[
        "grocer"
    ],
    "wof:name":"Linda (superette)",
    "wof:placetype":"venue"
},
  "geometry": {"coordinates":[3.6541540623,50.5708389282],"type":"Point"}
}