{
  "type": "Feature",
  "properties": {
    "iso:country":"BE",
    "sg:address":"Technologielaan 11 Box 102",
    "sg:city":"Leuven (heverlee)",
    "sg:classifiers":[
        {
            "category":"Professional",
            "subcategory":"Computer Services",
            "type":"Services"
        }
    ],
    "sg:phone":"+32 16 38 11 22",
    "sg:postcode":"3001",
    "sg:province":"Vlaams-Brabant",
    "sg:tags":[
        "-",
        "processing",
        "data",
        "software"
    ],
    "wof:name":"Visionwize Nv",
    "wof:placetype":"venue"
},
  "geometry": {"coordinates":[4.7310180664,50.8532218933],"type":"Point"}
}