{
  "type": "Feature",
  "properties": {
    "addr:full":"Isabellapl 2 Scherpenheuvel Vlaams-Brabant 3270",
    "addr:housenumber":"2",
    "addr:postcode":"3270",
    "addr:street":"Isabellapl",
    "iso:country":"BE",
    "sg:address":"Isabellapl 2",
    "sg:city":"Scherpenheuvel",
    "sg:classifiers":[
        {
            "category":"Banks & Credit Unions",
            "subcategory":"Bank",
            "type":"Services"
        }
    ],
    "sg:phone":"+32 13 77 29 77",
    "sg:postcode":"3270",
    "sg:province":"Vlaams-Brabant",
    "wof:name":"Gemeentekrediet",
    "wof:placetype":"venue"
},
  "geometry": {"coordinates":[4.9769630432,50.9807662964],"type":"Point"}
}