{
  "type": "Feature",
  "properties": {
    "iso:country":"BE",
    "sg:address":"Les Ruelles 2",
    "sg:city":"Lobbes (mont-sainte-genevi\u00e8ve)",
    "sg:classifiers":[
        {
            "category":"Shopping",
            "subcategory":"Antiques",
            "type":"Retail Goods"
        }
    ],
    "sg:phone":"+32 71 59 59 66",
    "sg:postcode":"6540",
    "sg:province":"Hainaut",
    "wof:name":"Derestiat B",
    "wof:placetype":"venue"
},
  "geometry": {"coordinates":[4.2354521751,50.371547699],"type":"Point"}
}