{
  "type": "Feature",
  "properties": {
    "addr:full":"Guido Gezellestraat 56 Denderleeuw Oost-Vlaanderen 9470",
    "addr:housenumber":"56",
    "addr:postcode":"9470",
    "addr:street":"Guido Gezellestraat",
    "iso:country":"BE",
    "sg:address":"Guido Gezellestraat 56",
    "sg:city":"Denderleeuw",
    "sg:orig_category":"Equipement photographique. Mat\u00e9riel de T\u00e9l\u00e9communication",
    "sg:phone":"+32 53 67 14 20",
    "sg:postcode":"9470",
    "sg:province":"Oost-Vlaanderen",
    "wof:name":"Studio Bronselaer",
    "wof:placetype":"venue"
},
  "geometry": {"coordinates":[4.0784521103,50.8860664368],"type":"Point"}
}