{
  "type": "Feature",
  "properties": {
    "addr:full":"Bruggesteenweg 84 Hooglede (gits) West-Vlaanderen 8830",
    "addr:housenumber":"84",
    "addr:postcode":"8830",
    "addr:street":"Bruggesteenweg",
    "iso:country":"BE",
    "sg:address":"Bruggesteenweg 84",
    "sg:city":"Hooglede (gits)",
    "sg:classifiers":[
        {
            "category":"Home & Garden",
            "subcategory":"Home Furnishings",
            "type":"Retail Goods"
        }
    ],
    "sg:phone":"+32 51 24 37 13",
    "sg:postcode":"8830",
    "sg:province":"West-Vlaanderen",
    "sg:tags":[
        "interior",
        "decoration"
    ],
    "wof:name":"Decogids",
    "wof:placetype":"venue"
},
  "geometry": {"coordinates":[3.0897738934,50.9804496765],"type":"Point"}
}