{
  "type": "Feature",
  "properties": {
    "addr:full":"Sleepstraat 139 Gent Oost-Vlaanderen 9000",
    "addr:housenumber":"139",
    "addr:postcode":"9000",
    "addr:street":"Sleepstraat;Oost-Vlaanderen",
    "iso:country":"BE",
    "sg:address":"Sleepstraat 139",
    "sg:city":"Gent",
    "sg:orig_category":"Pharmaciens",
    "sg:phone":"+32 9 225 05 56",
    "sg:postcode":"9000",
    "sg:province":"Oost-Vlaanderen",
    "wof:name":"Patricia Vanderstylen",
    "wof:placetype":"venue"
},
  "geometry": {"coordinates":[3.727298975,51.0623016357],"type":"Point"}
}