{
  "type": "Feature",
  "properties": {
    "addr:full":"Onze-lieve-vrouwstraat 78 Oud-heverlee Vlaams-Brabant 3052",
    "addr:housenumber":"78",
    "addr:postcode":"3052",
    "addr:street":"Onze-Lieve-Vrouwstraat",
    "iso:country":"BE",
    "sg:address":"Onze-lieve-vrouwstraat 78",
    "sg:city":"Oud-heverlee",
    "sg:orig_category":"M\u00e9decins and sp\u00e9cialistes",
    "sg:phone":"+32 16 40 17 67",
    "sg:postcode":"3052",
    "sg:province":"Vlaams-Brabant",
    "wof:name":"O. Van Cleynenbreugel",
    "wof:placetype":"venue"
},
  "geometry": {"coordinates":[4.6992311478,50.8271102905],"type":"Point"}
}