{
  "type": "Feature",
  "properties": {
    "addr:full":"Zwevegemsestraat 85-87 Harelbeke West-Vlaanderen 8530",
    "addr:housenumber":"85-87",
    "addr:postcode":"8530",
    "addr:street":"Zwevegemsestraat",
    "iso:country":"BE",
    "sg:address":"Zwevegemsestraat 85-87",
    "sg:city":"Harelbeke",
    "sg:orig_category":"Non-Classified Establishments",
    "sg:phone":"+32 56 21 06 43",
    "sg:postcode":"8530",
    "sg:province":"West-Vlaanderen",
    "wof:name":"C.d. Tingieterij",
    "wof:placetype":"venue"
},
  "geometry": {"coordinates":[3.3201699257,50.8272171021],"type":"Point"}
}