{
  "type": "Feature",
  "properties": {
    "addr:full":"Kruisweg 1 Wuustwezel Antwerpen 2990",
    "addr:housenumber":"1",
    "addr:postcode":"2990",
    "addr:street":"Kruisweg",
    "iso:country":"BE",
    "sg:address":"Kruisweg 1",
    "sg:city":"Wuustwezel",
    "sg:orig_category":"Maisons de vacances",
    "sg:phone":"+32 3 669 76 16",
    "sg:postcode":"2990",
    "sg:province":"Antwerpen",
    "wof:name":"Joosen & Zonen",
    "wof:placetype":"venue"
},
  "geometry": {"coordinates":[4.5914840698,51.4009361267],"type":"Point"}
}