{
  "type": "Feature",
  "properties": {
    "iso:country":"BE",
    "sg:address":"Rue Paul Pastur 17",
    "sg:city":"Fleurus",
    "sg:classifiers":[
        {
            "category":"Arena",
            "subcategory":"Sports Club",
            "type":"Entertainment"
        }
    ],
    "sg:phone":"+32 71 81 20 32",
    "sg:postcode":"6224",
    "sg:province":"Hainaut",
    "sg:tags":[
        "de"
    ],
    "wof:name":"Royal Courrier Sp. Baulet",
    "wof:placetype":"venue"
},
  "geometry": {"coordinates":[4.5790028572,50.4624710083],"type":"Point"}
}