{
  "type": "Feature",
  "properties": {
    "iso:country":"BE",
    "sg:address":"Lange Dreef 46",
    "sg:city":"Bonheiden (rijmenam)",
    "sg:classifiers":[
        {
            "category":"Health Services",
            "subcategory":"Dentist",
            "type":"Services"
        }
    ],
    "sg:phone":"+32 15 51 58 20",
    "sg:postcode":"2820",
    "sg:province":"Antwerpen",
    "wof:name":"Torsin Anneleen",
    "wof:placetype":"venue"
},
  "geometry": {"coordinates":[4.5496602058,51.0218009949],"type":"Point"}
}