{
  "type": "Feature",
  "properties": {
    "iso:country":"BE",
    "sg:address":"Kortrijksesteenweg 269",
    "sg:city":"Gent",
    "sg:classifiers":[
        {
            "category":"Real Estate",
            "subcategory":"Real Estate Services",
            "type":"Services"
        }
    ],
    "sg:phone":"+32 9 245 24 24",
    "sg:postcode":"9000",
    "sg:province":"Oost-Vlaanderen",
    "wof:name":"Axel Lenaerts Vastgoedmakelaars Bvba",
    "wof:placetype":"venue"
},
  "geometry": {"coordinates":[3.7158949375,51.0383720398],"type":"Point"}
}