{
  "type": "Feature",
  "properties": {
    "addr:full":"Esplanade 24pb Bruxelles Bruxelles-Capitale 1020",
    "addr:postcode":"1020",
    "addr:street":"Esplanade 24Pb",
    "iso:country":"BE",
    "sg:address":"Esplanade 24pb",
    "sg:city":"Bruxelles",
    "sg:classifiers":[
        {
            "category":"Sports & Exercise",
            "subcategory":"Playing Field",
            "type":"Entertainment"
        }
    ],
    "sg:postcode":"1020",
    "sg:province":"Bruxelles-Capitale",
    "sg:tags":[
        "sports-grounds",
        "access",
        "-",
        "laying"
    ],
    "wof:name":"Junckers - Buro & Design Center Bv",
    "wof:placetype":"venue"
},
  "geometry": {"coordinates":[4.3434820175,50.900226593],"type":"Point"}
}