{
  "type": "Feature",
  "properties": {
    "iso:country":"BE",
    "sg:address":"Immerzeeldreef 9",
    "sg:city":"Aalst",
    "sg:orig_category":"Brood, gebak and snoepgoed",
    "sg:phone":"+32 53 21 53 78",
    "sg:postcode":"9300",
    "sg:province":"Oost-Vlaanderen",
    "wof:name":"Hans Bonnaerens",
    "wof:placetype":"venue"
},
  "geometry": {"coordinates":[4.0670690536,50.9285736084],"type":"Point"}
}