{
  "type": "Feature",
  "properties": {
    "iso:country":"BE",
    "sg:address":"Albert I Laan 247",
    "sg:city":"Nieuwpoort",
    "sg:orig_category":"Alimentation sp\u00e9cialis\u00e9e",
    "sg:phone":"+32 58 24 11 84",
    "sg:postcode":"8620",
    "sg:province":"West-Vlaanderen",
    "wof:name":"Delicatessen Deltomme",
    "wof:placetype":"venue"
},
  "geometry": {"coordinates":[2.713301897,51.1470565796],"type":"Point"}
}