{
  "type": "Feature",
  "properties": {
    "addr:full":"Lierselei 31 Malle (oostmalle) Antwerpen 2390",
    "addr:housenumber":"31",
    "addr:postcode":"2390",
    "addr:street":"Lierselei",
    "iso:country":"BE",
    "sg:address":"Lierselei 31",
    "sg:city":"Malle (oostmalle)",
    "sg:classifiers":[
        {
            "category":"Shopping",
            "subcategory":"Clothing, Apparel, & Fashions",
            "type":"Retail Goods"
        }
    ],
    "sg:phone":"+32 3 312 00 74",
    "sg:postcode":"2390",
    "sg:province":"Antwerpen",
    "sg:tags":[
        "lady",
        "clothing",
        "-"
    ],
    "wof:name":"Melis (huis)",
    "wof:placetype":"venue"
},
  "geometry": {"coordinates":[4.7331800461,51.2991523743],"type":"Point"}
}