{
  "type": "Feature",
  "properties": {
    "addr:full":"Rue Campinaire 56 Aiseau-presles Hainaut 6250",
    "addr:housenumber":"56",
    "addr:postcode":"6250",
    "addr:street":"Rue Campinaire;Hainaut",
    "iso:country":"BE",
    "sg:address":"Rue Campinaire 56",
    "sg:city":"Aiseau-presles",
    "sg:orig_category":"Plomberie, chauffage and installations sanitaires",
    "sg:phone":"+32 71 40 33 93",
    "sg:postcode":"6250",
    "sg:province":"Hainaut",
    "wof:name":"Renaud Charles",
    "wof:placetype":"venue"
},
  "geometry": {"coordinates":[4.5463199615,50.4170761108],"type":"Point"}
}