{
  "type": "Feature",
  "properties": {
    "addr:full":"Rue De L'avenir 19 Gr\u00e2ce-hollogne (gr\u00e2ce-berleur) Li\u00e8ge 4460",
    "addr:housenumber":"19",
    "addr:postcode":"4460",
    "addr:street":"Rue De L'Avenir;Gra\u0302Ce-Berleur",
    "iso:country":"BE",
    "sg:address":"Rue De L'avenir 19",
    "sg:city":"Gr\u00e2ce-hollogne (gr\u00e2ce-berleur)",
    "sg:classifiers":[
        {
            "category":"Retail",
            "subcategory":"Auto Repair",
            "type":"Services"
        }
    ],
    "sg:phone":"+32 4 246 28 77",
    "sg:postcode":"4460",
    "sg:province":"Li\u00e8ge",
    "sg:tags":[
        "automobile-body"
    ],
    "wof:name":"Moreau (carrosserie)",
    "wof:placetype":"venue"
},
  "geometry": {"coordinates":[5.4967188835,50.6543502808],"type":"Point"}
}