{
  "type": "Feature",
  "properties": {
    "addr:full":"Maliestraat 50 Elsene/ixelles Bruxelles-Capitale 1050",
    "addr:housenumber":"50",
    "addr:postcode":"1050",
    "addr:street":"Maliestraat",
    "iso:country":"BE",
    "sg:address":"Maliestraat 50",
    "sg:city":"Elsene/ixelles",
    "sg:orig_category":"Benzinestations and brandstoffen",
    "sg:phone":"+32 2 538 48 76",
    "sg:postcode":"1050",
    "sg:province":"Bruxelles-Capitale",
    "wof:name":"Total",
    "wof:placetype":"venue"
},
  "geometry": {"coordinates":[4.3595142365,50.8218078613],"type":"Point"}
}