{
  "type": "Feature",
  "properties": {
    "addr:full":"Brugsesteenweg 30 Eeklo Oost-Vlaanderen 9900",
    "addr:housenumber":"30",
    "addr:postcode":"9900",
    "addr:street":"Brugsesteenweg",
    "iso:country":"BE",
    "sg:address":"Brugsesteenweg 30",
    "sg:city":"Eeklo",
    "sg:classifiers":[
        {
            "category":"Insurance",
            "subcategory":"Insurance Agent",
            "type":"Services"
        }
    ],
    "sg:phone":"+32 9 377 46 33",
    "sg:postcode":"9900",
    "sg:province":"Oost-Vlaanderen",
    "sg:tags":[
        "verzekeringsmakelaars",
        "expert"
    ],
    "wof:name":"Albert Declercq",
    "wof:placetype":"venue"
},
  "geometry": {"coordinates":[3.5388689041,51.195350647],"type":"Point"}
}