{
  "type": "Feature",
  "properties": {
    "addr:full":"Kapellestraat 13 Aalst Oost-Vlaanderen 9300",
    "addr:housenumber":"13",
    "addr:postcode":"9300",
    "addr:street":"Kapellestraat",
    "iso:country":"BE",
    "sg:address":"Kapellestraat 13",
    "sg:city":"Aalst",
    "sg:orig_category":"Avocats and conseillers juridiques",
    "sg:phone":"+32 53 77 41 66",
    "sg:postcode":"9300",
    "sg:province":"Oost-Vlaanderen",
    "wof:name":"Paul Saeys",
    "wof:placetype":"venue"
},
  "geometry": {"coordinates":[4.0429601669,50.9359741211],"type":"Point"}
}