{
  "type": "Feature",
  "properties": {
    "iso:country":"BE",
    "sg:address":"Rue Du Bois Jacquet 94b",
    "sg:city":"Espierres-helchin (espierres)",
    "sg:classifiers":[
        {
            "category":"Autos & Motor Vehicles",
            "subcategory":"Recreational Vehicle Sales",
            "type":"Retail Goods"
        }
    ],
    "sg:phone":"+32 56 45 60 46",
    "sg:postcode":"8587",
    "sg:province":"West-Vlaanderen",
    "sg:tags":[
        "caravan",
        "accessory"
    ],
    "wof:name":"Vercovan Nv",
    "wof:placetype":"venue"
},
  "geometry": {"coordinates":[3.3338449001,50.7287826538],"type":"Point"}
}