{
  "type": "Feature",
  "properties": {
    "addr:full":"Rue Blaes 33 Bruxelles Bruxelles-Capitale 1000",
    "addr:housenumber":"33",
    "addr:postcode":"1000",
    "addr:street":"Rue Blaes",
    "iso:country":"BE",
    "sg:address":"Rue Blaes 33",
    "sg:city":"Bruxelles",
    "sg:classifiers":[
        {
            "category":"Shopping",
            "subcategory":"Antiques",
            "type":"Retail Goods"
        }
    ],
    "sg:phone":"+32 2 512 80 60",
    "sg:postcode":"1000",
    "sg:province":"Bruxelles-Capitale",
    "wof:name":"Ars Islamica",
    "wof:placetype":"venue"
},
  "geometry": {"coordinates":[4.3499660492,50.840423584],"type":"Point"}
}