{
  "type": "Feature",
  "properties": {
    "iso:country":"BE",
    "sg:address":"Rue Trieu Del Croix 35",
    "sg:city":"Cerfontaine",
    "sg:orig_category":"Traitements param\u00e9dicaux",
    "sg:phone":"+32 71 64 46 11",
    "sg:postcode":"5630",
    "sg:province":"Namur",
    "wof:name":"Brancourt",
    "wof:placetype":"venue"
},
  "geometry": {"coordinates":[4.4460668564,50.1906394958],"type":"Point"}
}