{
  "type": "Feature",
  "properties": {
    "addr:full":"Perreveld 28 Opwijk Vlaams-Brabant 1745",
    "addr:housenumber":"28",
    "addr:postcode":"1745",
    "addr:street":"Perreveld",
    "iso:country":"BE",
    "sg:address":"Perreveld 28",
    "sg:city":"Opwijk",
    "sg:classifiers":[
        {
            "category":"Professional",
            "subcategory":"Accounting & Tax Preparation",
            "type":"Services"
        }
    ],
    "sg:phone":"+32 52 35 73 40",
    "sg:postcode":"1745",
    "sg:province":"Vlaams-Brabant",
    "sg:tags":[
        "accountant"
    ],
    "wof:name":"Valere Huysegoms",
    "wof:placetype":"venue"
},
  "geometry": {"coordinates":[4.1699619293,50.9635848999],"type":"Point"}
}