{
  "type": "Feature",
  "properties": {
    "addr:full":"Quai Du Vignoble 30 Comblain-au-pont Li\u00e8ge 4170",
    "addr:housenumber":"30",
    "addr:postcode":"4170",
    "addr:street":"Quai Du Vignoble",
    "iso:country":"BE",
    "sg:address":"Quai Du Vignoble 30",
    "sg:city":"Comblain-au-pont",
    "sg:orig_category":"Drukkerijen and copyshops",
    "sg:phone":"+32 4 369 12 38",
    "sg:postcode":"4170",
    "sg:province":"Li\u00e8ge",
    "wof:name":"Ernest Eischenne",
    "wof:placetype":"venue"
},
  "geometry": {"coordinates":[5.5845370293,50.476398468],"type":"Point"}
}