{
  "type": "Feature",
  "properties": {
    "addr:full":"Rue De L'ath\u00c9n\u00c9e 38 Tournai Hainaut 7500",
    "addr:housenumber":"38",
    "addr:postcode":"7500",
    "addr:street":"Rue De L'Athe \u0301Ne\u0301E",
    "iso:country":"BE",
    "sg:address":"Rue De L'ath\u00c9n\u00c9e 38",
    "sg:city":"Tournai",
    "sg:orig_category":"Avocats and conseillers juridiques",
    "sg:phone":"+32 69 21 43 07",
    "sg:postcode":"7500",
    "sg:province":"Hainaut",
    "wof:name":"G. Lef\u00c8bvre",
    "wof:placetype":"venue"
},
  "geometry": {"coordinates":[3.3956151009,50.60987854],"type":"Point"}
}