{
  "type": "Feature",
  "properties": {
    "addr:full":"Warandeberg 52 Wezembeek-oppem Vlaams-Brabant 1970",
    "addr:housenumber":"52",
    "addr:postcode":"1970",
    "addr:street":"Warandeberg",
    "iso:country":"BE",
    "sg:address":"Warandeberg 52",
    "sg:city":"Wezembeek-oppem",
    "sg:classifiers":[
        {
            "category":"Social Services",
            "subcategory":"Job Training",
            "type":"Services"
        }
    ],
    "sg:phone":"+32 2 782 10 09",
    "sg:postcode":"1970",
    "sg:province":"Vlaams-Brabant",
    "sg:tags":[
        "de",
        "terrain",
        "camping"
    ],
    "wof:name":"Royal Camping R3 - Cb",
    "wof:placetype":"venue"
},
  "geometry": {"coordinates":[4.4823479652,50.8569908142],"type":"Point"}
}