{
  "type": "Feature",
  "properties": {
    "iso:country":"BE",
    "sg:address":"Grand'place 5",
    "sg:city":"Saint-ghislain",
    "sg:classifiers":[
        {
            "category":"Bars & Pubs",
            "type":"Food & Drink"
        }
    ],
    "sg:phone":"+32 65 78 43 26",
    "sg:postcode":"7330",
    "sg:province":"Hainaut",
    "wof:name":"Arcades (les)",
    "wof:placetype":"venue"
},
  "geometry": {"coordinates":[3.8205890656,50.4484443665],"type":"Point"}
}