{
  "type": "Feature",
  "properties": {
    "addr:full":"Beertegemstraat 26 Zingem Oost-Vlaanderen 9750",
    "addr:housenumber":"26",
    "addr:postcode":"9750",
    "addr:street":"Beertegemstraat;Oost-Vlaanderen",
    "iso:country":"BE",
    "sg:address":"Beertegemstraat 26",
    "sg:city":"Zingem",
    "sg:orig_category":"Woningbouw",
    "sg:phone":"+32 9 384 67 92",
    "sg:postcode":"9750",
    "sg:province":"Oost-Vlaanderen",
    "wof:name":"Clauwaert J",
    "wof:placetype":"venue"
},
  "geometry": {"coordinates":[3.6100199223,50.919090271],"type":"Point"}
}