{
  "type": "Feature",
  "properties": {
    "iso:country":"BE",
    "sg:address":"Craenevenne 23",
    "sg:city":"Genk",
    "sg:classifiers":[
        {
            "category":"Personal",
            "subcategory":"Tattoo Parlor",
            "type":"Services"
        }
    ],
    "sg:phone":"+32 89 30 44 66",
    "sg:postcode":"3600",
    "sg:province":"Limburg",
    "sg:tags":[
        "tattooists"
    ],
    "wof:name":"Needlewitch Tattoes",
    "wof:placetype":"venue"
},
  "geometry": {"coordinates":[5.4300050735,50.9641571045],"type":"Point"}
}