{
  "type": "Feature",
  "properties": {
    "iso:country":"BE",
    "sg:address":"Chauss\u00c9e De Bruxelles 2",
    "sg:city":"Tournai",
    "sg:classifiers":[
        {
            "category":"Bars & Pubs",
            "subcategory":"Nightclub",
            "type":"Food & Drink"
        }
    ],
    "sg:postcode":"7534",
    "sg:province":"Hainaut",
    "sg:tags":[
        "nachtclubs",
        "dancing"
    ],
    "wof:name":"Barry Reve",
    "wof:placetype":"venue"
},
  "geometry": {"coordinates":[3.4043450356,50.6060409546],"type":"Point"}
}