{
  "type": "Feature",
  "properties": {
    "iso:country":"BE",
    "sg:address":"Route De Villers 19",
    "sg:city":"Anthisnes (hody)",
    "sg:classifiers":[
        {
            "category":"Manufacturing",
            "subcategory":"Textiles",
            "type":"Manufacturing & Wholesale Goods"
        }
    ],
    "sg:phone":"+32 4 383 98 20",
    "sg:postcode":"4162",
    "sg:province":"Li\u00e8ge",
    "sg:tags":[
        "refractory",
        "material"
    ],
    "wof:name":"Saint Gobain Materieux Ceramiques Sa",
    "wof:placetype":"venue"
},
  "geometry": {"coordinates":[5.5004739761,50.4883041382],"type":"Point"}
}