{
  "type": "Feature",
  "properties": {
    "addr:full":"Rue Des R\u00f4tisseurs 8 Huy Li\u00e8ge 4500",
    "addr:housenumber":"8",
    "addr:postcode":"4500",
    "addr:street":"Rue Des Ro\u0302Tisseurs",
    "iso:country":"BE",
    "sg:address":"Rue Des R\u00f4tisseurs 8",
    "sg:city":"Huy",
    "sg:classifiers":[
        {
            "category":"Manufacturing",
            "subcategory":"Building Materials",
            "type":"Manufacturing & Wholesale Goods"
        }
    ],
    "sg:phone":"+32 85 21 44 82",
    "sg:postcode":"4500",
    "sg:province":"Li\u00e8ge",
    "sg:tags":[
        "wig",
        "hairworks"
    ],
    "wof:name":"Dabompr\u00e9",
    "wof:placetype":"venue"
},
  "geometry": {"coordinates":[5.2403759956,50.5189933777],"type":"Point"}
}