{
  "type": "Feature",
  "properties": {
    "iso:country":"BE",
    "sg:address":"Minderbroedersplein 1",
    "sg:city":"Sint-truiden",
    "sg:classifiers":[
        {
            "category":"Bars & Pubs",
            "type":"Food & Drink"
        }
    ],
    "sg:phone":"+32 11 69 67 19",
    "sg:postcode":"3800",
    "sg:province":"Limburg",
    "wof:name":"Little Rock",
    "wof:placetype":"venue"
},
  "geometry": {"coordinates":[5.1860389709,50.8141098022],"type":"Point"}
}