{
  "type": "Feature",
  "properties": {
    "addr:full":"Werthplatz 11 Eupen Li\u00e8ge 4700",
    "addr:housenumber":"11",
    "addr:postcode":"4700",
    "addr:street":"Werthplatz",
    "iso:country":"BE",
    "sg:address":"Werthplatz 11",
    "sg:city":"Eupen",
    "sg:classifiers":[
        {
            "category":"Cafe",
            "type":"Food & Drink"
        }
    ],
    "sg:phone":"+32 87 74 41 98",
    "sg:postcode":"4700",
    "sg:province":"Li\u00e8ge",
    "sg:tags":[
        "snack-bars"
    ],
    "wof:name":"Trait D'union Sandwicherie",
    "wof:placetype":"venue"
},
  "geometry": {"coordinates":[6.0385708809,50.6322746277],"type":"Point"}
}