{
  "type": "Feature",
  "properties": {
    "addr:full":"Statieplein 3 Anzegem West-Vlaanderen 8570",
    "addr:housenumber":"3",
    "addr:postcode":"8570",
    "addr:street":"Statieplein",
    "iso:country":"BE",
    "sg:address":"Statieplein 3",
    "sg:city":"Anzegem",
    "sg:orig_category":"Treinen and spoorwegen",
    "sg:phone":"+32 56 68 81 46",
    "sg:postcode":"8570",
    "sg:province":"West-Vlaanderen",
    "wof:name":"Station Anzegem",
    "wof:placetype":"venue"
},
  "geometry": {"coordinates":[3.494052887,50.8263168335],"type":"Point"}
}