{
  "type": "Feature",
  "properties": {
    "iso:country":"BE",
    "sg:address":"Boekhoutstraat 10",
    "sg:city":"Oosterzele",
    "sg:classifiers":[
        {
            "category":"Real Estate",
            "subcategory":"Architect",
            "type":"Services"
        }
    ],
    "sg:phone":"+32 9 362 11 01",
    "sg:postcode":"9860",
    "sg:province":"Oost-Vlaanderen",
    "wof:name":"Van De Loock A",
    "wof:placetype":"venue"
},
  "geometry": {"coordinates":[3.8353559971,50.9403419495],"type":"Point"}
}