{
  "type": "Feature",
  "properties": {
    "iso:country":"BE",
    "sg:address":"Chauss\u00e9e D'alsemberg 43",
    "sg:city":"Linkebeek",
    "sg:classifiers":[
        {
            "category":"Health Services",
            "subcategory":"Nursing And Care Facility",
            "type":"Services"
        }
    ],
    "sg:phone":"+32 2 377 08 19",
    "sg:postcode":"1630",
    "sg:province":"Vlaams-Brabant",
    "sg:tags":[
        "home",
        "rest"
    ],
    "wof:name":"Avondvrede",
    "wof:placetype":"venue"
},
  "geometry": {"coordinates":[4.3260631561,50.7768630981],"type":"Point"}
}