{
  "type": "Feature",
  "properties": {
    "iso:country":"BE",
    "sg:address":"Rue De Linkebeek 31",
    "sg:city":"Ukkel/uccle",
    "sg:orig_category":"DIVERSE RECREATIEVE ACTIVITEITEN",
    "sg:phone":"+32 2 332 10 58",
    "sg:postcode":"1180",
    "sg:province":"Bruxelles-Capitale",
    "wof:name":"Centre Artisanal La Gaumette",
    "wof:placetype":"venue"
},
  "geometry": {"coordinates":[4.3277001381,50.7799797058],"type":"Point"}
}