{
  "type": "Feature",
  "properties": {
    "iso:country":"BE",
    "sg:address":"Strikkeweg 8",
    "sg:city":"Merksplas",
    "sg:orig_category":"Varkenskwekers",
    "sg:phone":"+32 14 63 43 23",
    "sg:postcode":"2330",
    "sg:province":"Antwerpen",
    "wof:name":"Louis Van Mechelen",
    "wof:placetype":"venue"
},
  "geometry": {"coordinates":[4.8773870468,51.3983917236],"type":"Point"}
}