{
  "type": "Feature",
  "properties": {
    "addr:full":"Schrieksebaan 53 Tremelo Vlaams-Brabant 3120",
    "addr:housenumber":"53",
    "addr:postcode":"3120",
    "addr:street":"Schrieksebaan",
    "iso:country":"BE",
    "sg:address":"Schrieksebaan 53",
    "sg:city":"Tremelo",
    "sg:classifiers":[
        {
            "category":"Deli",
            "type":"Food & Drink"
        }
    ],
    "sg:phone":"+32 16 53 55 78",
    "sg:postcode":"3120",
    "sg:province":"Vlaams-Brabant",
    "sg:tags":[
        "delicatessen"
    ],
    "wof:name":"Damiaantje",
    "wof:placetype":"venue"
},
  "geometry": {"coordinates":[4.7064142227,50.9929199219],"type":"Point"}
}