{
  "type": "Feature",
  "properties": {
    "addr:full":"Stationsstraat 103 Eeklo Oost-Vlaanderen 9900",
    "addr:housenumber":"103",
    "addr:postcode":"9900",
    "addr:street":"Stationsstraat",
    "iso:country":"BE",
    "sg:address":"Stationsstraat 103",
    "sg:city":"Eeklo",
    "sg:classifiers":[
        {
            "category":"Cafe",
            "type":"Food & Drink"
        }
    ],
    "sg:phone":"+32 9 378 26 86",
    "sg:postcode":"9900",
    "sg:province":"Oost-Vlaanderen",
    "sg:tags":[
        "caf\u00e9s"
    ],
    "wof:name":"Caf\u00c9 De Proeverij",
    "wof:placetype":"venue"
},
  "geometry": {"coordinates":[3.5728640556,51.1823005676],"type":"Point"}
}