{
  "type": "Feature",
  "properties": {
    "addr:full":"Rue Vigna 104ba Andenne Namur 5300",
    "addr:postcode":"5300",
    "addr:street":"Rue Vigna 104Ba",
    "iso:country":"BE",
    "sg:address":"Rue Vigna 104ba",
    "sg:city":"Andenne",
    "sg:orig_category":"Foto-uitrusting Fotografen and fotostudio's",
    "sg:phone":"+32 85 82 62 93",
    "sg:postcode":"5300",
    "sg:province":"Namur",
    "wof:name":"Studio Gramtinne",
    "wof:placetype":"venue"
},
  "geometry": {"coordinates":[5.0982642174,50.4863739014],"type":"Point"}
}