{
  "type": "Feature",
  "properties": {
    "iso:country":"BE",
    "sg:address":"Paviljoenweg 99",
    "sg:city":"Gent (sint-amandsberg)",
    "sg:classifiers":[
        {
            "category":"Health Services",
            "subcategory":"Dentist",
            "type":"Services"
        }
    ],
    "sg:phone":"+32 9 238 16 16",
    "sg:postcode":"9040",
    "sg:province":"Oost-Vlaanderen",
    "wof:name":"Verrue Veerle",
    "wof:placetype":"venue"
},
  "geometry": {"coordinates":[3.757281065,51.069278717],"type":"Point"}
}