{
  "type": "Feature",
  "properties": {
    "iso:country":"BE",
    "sg:address":"Rue De L'yser 9",
    "sg:city":"Tournai",
    "sg:classifiers":[
        {
            "category":"Personal",
            "subcategory":"Beauty Salon",
            "type":"Services"
        }
    ],
    "sg:phone":"+32 69 23 48 15",
    "sg:postcode":"7500",
    "sg:province":"Hainaut",
    "wof:name":"Femina Beaute",
    "wof:placetype":"venue"
},
  "geometry": {"coordinates":[3.3861761093,50.6079597473],"type":"Point"}
}