{
  "type": "Feature",
  "properties": {
    "addr:full":"Smetledestr 55 Wetteren Oost-Vlaanderen 9230",
    "addr:housenumber":"55",
    "addr:postcode":"9230",
    "addr:street":"Smetledestr",
    "iso:country":"BE",
    "sg:address":"Smetledestr 55",
    "sg:city":"Wetteren",
    "sg:classifiers":[
        {
            "category":"Farming",
            "subcategory":"Farm",
            "type":"Manufacturing & Wholesale Goods"
        }
    ],
    "sg:phone":"+32 9 369 02 37",
    "sg:postcode":"9230",
    "sg:province":"Oost-Vlaanderen",
    "sg:tags":[
        "horticulture",
        "agriculture",
        "livestock"
    ],
    "wof:name":"Calle Steven M.",
    "wof:placetype":"venue"
},
  "geometry": {"coordinates":[3.8993339539,50.995262146],"type":"Point"}
}