{
  "type": "Feature",
  "properties": {
    "iso:country":"BE",
    "sg:address":"Heibrikstraat 54",
    "sg:city":"Hoeselt",
    "sg:orig_category":"Installation de menuiserie en bois and plastique. Fabrication and montage de mobilier",
    "sg:phone":"+32 89 51 43 31",
    "sg:postcode":"3730",
    "sg:province":"Limburg",
    "wof:name":"Bruno Geelen",
    "wof:placetype":"venue"
},
  "geometry": {"coordinates":[5.4778399467,50.8547668457],"type":"Point"}
}