{
  "type": "Feature",
  "properties": {
    "iso:country":"BE",
    "sg:address":"Rue De La Sablonniere 9",
    "sg:city":"Li\u00c8ge",
    "sg:orig_category":"Agences immobili\u00e8res",
    "sg:phone":"+32 4 361 35 72",
    "sg:postcode":"4031",
    "sg:province":"Li\u00e8ge",
    "wof:name":"Alain Deprez",
    "wof:placetype":"venue"
},
  "geometry": {"coordinates":[5.570374012,50.5934143066],"type":"Point"}
}