{
  "type": "Feature",
  "properties": {
    "addr:full":"Prins Boudewijnstraat 8 Roeselare West-Vlaanderen 8800",
    "addr:housenumber":"8",
    "addr:postcode":"8800",
    "addr:street":"Prins Boudewijnstraat",
    "iso:country":"BE",
    "sg:address":"Prins Boudewijnstraat 8",
    "sg:city":"Roeselare",
    "sg:classifiers":[
        {
            "category":"Social Services",
            "subcategory":"Job Training",
            "type":"Services"
        }
    ],
    "sg:phone":"+32 51 69 80 11",
    "sg:postcode":"8800",
    "sg:province":"West-Vlaanderen",
    "sg:tags":[
        "coordinator",
        "safety"
    ],
    "wof:name":"Safety Control Team Bvba",
    "wof:placetype":"venue"
},
  "geometry": {"coordinates":[3.1253960133,50.9590606689],"type":"Point"}
}