{
  "type": "Feature",
  "properties": {
    "iso:country":"BE",
    "sg:address":"23a Peter Benoitlaan",
    "sg:city":"Brugge",
    "sg:classifiers":[
        {
            "category":"Manufacturing",
            "subcategory":"Printing",
            "type":"Manufacturing & Wholesale Goods"
        }
    ],
    "sg:phone":"+32 50 81 66 75",
    "sg:postcode":"8200",
    "sg:province":"West-Vlaanderen",
    "sg:tags":[
        "publishing"
    ],
    "wof:name":"Euro Graphic Services",
    "wof:placetype":"venue"
},
  "geometry": {"coordinates":[3.2060799599,51.2091445923],"type":"Point"}
}