{
  "type": "Feature",
  "properties": {
    "addr:full":"Jean Volderslaan 36 Sint-gillis/saint-gilles Bruxelles-Capitale 1060",
    "addr:housenumber":"36",
    "addr:postcode":"1060",
    "addr:street":"Jean Volderslaan",
    "iso:country":"BE",
    "sg:address":"Jean Volderslaan 36",
    "sg:city":"Sint-gillis/saint-gilles",
    "sg:orig_category":"Kapsalons",
    "sg:phone":"+32 2 537 90 25",
    "sg:postcode":"1060",
    "sg:province":"Bruxelles-Capitale",
    "wof:name":"Coiffure Celes",
    "wof:placetype":"venue"
},
  "geometry": {"coordinates":[4.3434848785,50.8319244385],"type":"Point"}
}