{
  "type": "Feature",
  "properties": {
    "iso:country":"BE",
    "sg:address":"Handelsstraat 27",
    "sg:city":"Londerzeel (malderen)",
    "sg:classifiers":[
        {
            "category":"Health Services",
            "subcategory":"Health Practitioner",
            "type":"Services"
        }
    ],
    "sg:phone":"+32 52 33 16 42",
    "sg:postcode":"1840",
    "sg:province":"Vlaams-Brabant",
    "sg:tags":[
        "physiotherapist"
    ],
    "wof:name":"Mertens-vogt",
    "wof:placetype":"venue"
},
  "geometry": {"coordinates":[4.2366518974,51.0150604248],"type":"Point"}
}