{
  "type": "Feature",
  "properties": {
    "addr:full":"All\u00e9e Centrale Jumet Hainaut 6040",
    "addr:postcode":"6040",
    "addr:street":"Alle\u0301E Centrale;Hainaut",
    "iso:country":"BE",
    "sg:address":"All\u00e9e Centrale",
    "sg:city":"Jumet",
    "sg:classifiers":[
        {
            "category":"Manufacturing",
            "subcategory":"Wood Products",
            "type":"Manufacturing & Wholesale Goods"
        }
    ],
    "sg:phone":"+32 71 37 37 48",
    "sg:postcode":"6040",
    "sg:province":"Hainaut",
    "sg:tags":[
        "professional",
        "furniture"
    ],
    "wof:name":"Deltenre Factory Sa",
    "wof:placetype":"venue"
},
  "geometry": {"coordinates":[4.4558048248,50.4553108215],"type":"Point"}
}