{
  "type": "Feature",
  "properties": {
    "addr:full":"Rue Du Ny 4 Hotton Luxembourg 6990",
    "addr:housenumber":"4",
    "addr:postcode":"6990",
    "addr:street":"Rue Du Ny",
    "iso:country":"BE",
    "sg:address":"Rue Du Ny 4",
    "sg:city":"Hotton",
    "sg:orig_category":"Bouwmaterialen Gh",
    "sg:phone":"+32 84 46 60 42",
    "sg:postcode":"6990",
    "sg:province":"Luxembourg",
    "wof:name":"Sogemat",
    "wof:placetype":"venue"
},
  "geometry": {"coordinates":[5.4411530495,50.282787323],"type":"Point"}
}