{
  "type": "Feature",
  "properties": {
    "iso:country":"BE",
    "sg:address":"Groenestraat 40b",
    "sg:city":"Alveringem (izenberge)",
    "sg:classifiers":[
        {
            "category":"Utilities",
            "subcategory":"Natural Gas",
            "type":"Services"
        }
    ],
    "sg:phone":"+32 58 29 95 99",
    "sg:postcode":"8691",
    "sg:province":"West-Vlaanderen",
    "sg:tags":[
        "welding"
    ],
    "wof:name":"Serpieters Philips Construct",
    "wof:placetype":"venue"
},
  "geometry": {"coordinates":[2.6652259827,50.9685592651],"type":"Point"}
}