{
  "type": "Feature",
  "properties": {
    "iso:country":"BE",
    "sg:address":"Grand\u00b4place 1",
    "sg:city":"Quaregnon",
    "sg:orig_category":"Algemeen secundair onderwijs Technisch and beroeps secundair onderwijs",
    "sg:phone":"+32 65 77 72 68",
    "sg:postcode":"7390",
    "sg:province":"Hainaut",
    "wof:name":"Inst. Enseign. Secondaire",
    "wof:placetype":"venue"
},
  "geometry": {"coordinates":[3.8649039268,50.4432868958],"type":"Point"}
}