{
  "type": "Feature",
  "properties": {
    "iso:country":"BE",
    "sg:address":"Grand Route 420",
    "sg:city":"Flemalle",
    "sg:orig_category":"HERSTELLING ELEKTRISCHE HUISHOUDAPPARATEN Huishoudapparaten, televisies and radio's Telecommunicatie",
    "sg:phone":"+32 4 234 27 91",
    "sg:postcode":"4400",
    "sg:province":"Li\u00e8ge",
    "wof:name":"Eldi",
    "wof:placetype":"venue"
},
  "geometry": {"coordinates":[5.4793639183,50.6030845642],"type":"Point"}
}