{
  "type": "Feature",
  "properties": {
    "iso:country":"BE",
    "sg:address":"Rue Jourdan 131",
    "sg:city":"Saint-gilles",
    "sg:orig_category":"Epiceries",
    "sg:phone":"+32 2 538 15 39",
    "sg:postcode":"1060",
    "sg:province":"Bruxelles-Capitale",
    "wof:name":"Night Shop New York Traders",
    "wof:placetype":"venue"
},
  "geometry": {"coordinates":[4.3492150307,50.8320960999],"type":"Point"}
}