{
  "type": "Feature",
  "properties": {
    "addr:full":"Chauss\u00c9e De Thuin 361 Anderlues Hainaut 6150",
    "addr:housenumber":"361",
    "addr:postcode":"6150",
    "addr:street":"Chausse\u0301E De Thuin",
    "iso:country":"BE",
    "sg:address":"Chauss\u00c9e De Thuin 361",
    "sg:city":"Anderlues",
    "sg:orig_category":"Pain, p\u00e2tisseries and confiseries",
    "sg:phone":"+32 71 52 95 54",
    "sg:postcode":"6150",
    "sg:province":"Hainaut",
    "wof:name":"Jean Dubois",
    "wof:placetype":"venue"
},
  "geometry": {"coordinates":[4.2824368477,50.3907318115],"type":"Point"}
}