{
  "type": "Feature",
  "properties": {
    "iso:country":"BE",
    "sg:address":"Kouterstraat 131",
    "sg:city":"Beveren",
    "sg:orig_category":"Transports routiers de marchandises",
    "sg:phone":"+32 3 750 99 99",
    "sg:postcode":"9120",
    "sg:province":"Oost-Vlaanderen",
    "wof:name":"Van Lokeren Transport",
    "wof:placetype":"venue"
},
  "geometry": {"coordinates":[4.1790652275,51.218170166],"type":"Point"}
}