{
  "type": "Feature",
  "properties": {
    "addr:full":"Lindemeers 5 Beernem West-Vlaanderen 8730",
    "addr:housenumber":"5",
    "addr:postcode":"8730",
    "addr:street":"Lindemeers",
    "iso:country":"BE",
    "sg:address":"Lindemeers 5",
    "sg:city":"Beernem",
    "sg:orig_category":"Rev\u00eatements pour sols and murs. Peinture",
    "sg:phone":"+32 50 78 13 17",
    "sg:postcode":"8730",
    "sg:province":"West-Vlaanderen",
    "wof:name":"Nico Schelstraete",
    "wof:placetype":"venue"
},
  "geometry": {"coordinates":[3.3317089081,51.1737136841],"type":"Point"}
}