{
  "type": "Feature",
  "properties": {
    "addr:full":"Rue Du Chateau-fort 12 Rouvroy Luxembourg 6767",
    "addr:housenumber":"12",
    "addr:postcode":"6767",
    "addr:street":"Rue Du Chateau-Fort",
    "iso:country":"BE",
    "sg:address":"Rue Du Chateau-fort 12",
    "sg:city":"Rouvroy",
    "sg:orig_category":"Rundveehouders",
    "sg:phone":"+32 63 57 82 71",
    "sg:postcode":"6767",
    "sg:province":"Luxembourg",
    "wof:name":"Premont",
    "wof:placetype":"venue"
},
  "geometry": {"coordinates":[5.472799778,49.5442199707],"type":"Point"}
}