{
  "type": "Feature",
  "properties": {
    "addr:full":"Rue Des D\u00c9port\u00c9s 111 Tubize Brabant Wallon 1480",
    "addr:housenumber":"111",
    "addr:postcode":"1480",
    "addr:street":"Rue Des De\u0301Porte\u0301S;Wallon",
    "iso:country":"BE",
    "sg:address":"Rue Des D\u00c9port\u00c9s 111",
    "sg:city":"Tubize",
    "sg:orig_category":"Divers amusement Huishoudapparaten, televisies and radio's Verlichting and huishoudartikelen",
    "sg:phone":"+32 2 355 40 67",
    "sg:postcode":"1480",
    "sg:province":"Brabant Wallon",
    "wof:name":"Songs And Music",
    "wof:placetype":"venue"
},
  "geometry": {"coordinates":[4.2211689949,50.6947784424],"type":"Point"}
}