{
  "type": "Feature",
  "properties": {
    "addr:full":"Prins Leopoldlei 106 Mortsel Antwerpen 2640",
    "addr:housenumber":"106",
    "addr:postcode":"2640",
    "addr:street":"Prins Leopoldlei",
    "iso:country":"BE",
    "sg:address":"Prins Leopoldlei 106",
    "sg:city":"Mortsel",
    "sg:classifiers":[
        {
            "category":"Cafe",
            "type":"Food & Drink"
        }
    ],
    "sg:phone":"+32 3 440 33 03",
    "sg:postcode":"2640",
    "sg:province":"Antwerpen",
    "sg:tags":[
        "caf\u00e9s"
    ],
    "wof:name":"Cafe Manger Koen",
    "wof:placetype":"venue"
},
  "geometry": {"coordinates":[4.4525079727,51.1680297852],"type":"Point"}
}