{
  "type": "Feature",
  "properties": {
    "addr:full":"Gentseweg 583 Waregem West-Vlaanderen 8793",
    "addr:housenumber":"583",
    "addr:postcode":"8793",
    "addr:street":"Gentseweg",
    "iso:country":"BE",
    "sg:address":"Gentseweg 583",
    "sg:city":"Waregem",
    "sg:orig_category":"Passagiersvervoer over de weg",
    "sg:phone":"+32 56 60 19 34",
    "sg:postcode":"8793",
    "sg:province":"West-Vlaanderen",
    "wof:name":"Parmentier Autobus",
    "wof:placetype":"venue"
},
  "geometry": {"coordinates":[3.4005770683,50.8992462158],"type":"Point"}
}