{
  "type": "Feature",
  "properties": {
    "iso:country":"BE",
    "sg:address":"Rue Des Cyclistes Fronti\u00c8res 24",
    "sg:city":"Vise",
    "sg:orig_category":"Airconditioning and ventilatie Elektrische installaties voor woningen Loodgieterij and centrale verw",
    "sg:phone":"+32 4 379 63 93",
    "sg:postcode":"4600",
    "sg:province":"Li\u00e8ge",
    "wof:name":"Douin +",
    "wof:placetype":"venue"
},
  "geometry": {"coordinates":[5.7067060471,50.74609375],"type":"Point"}
}