{
  "type": "Feature",
  "properties": {
    "addr:full":"Rue Fran\u00c7ois Sadin 9 La Louviere Hainaut 7110",
    "addr:housenumber":"9",
    "addr:postcode":"7110",
    "addr:street":"Rue Franc\u0327Ois Sadin",
    "iso:country":"BE",
    "sg:address":"Rue Fran\u00c7ois Sadin 9",
    "sg:city":"La Louviere",
    "sg:orig_category":"Grands magasins",
    "sg:phone":"+32 64 84 81 18",
    "sg:postcode":"7110",
    "sg:province":"Hainaut",
    "wof:name":"Lesatex",
    "wof:placetype":"venue"
},
  "geometry": {"coordinates":[4.1512298584,50.4831581116],"type":"Point"}
}