{
  "type": "Feature",
  "properties": {
    "addr:full":"Hulstersestraat 238 Wielsbeke (ooigem) West-Vlaanderen 8710",
    "addr:housenumber":"238",
    "addr:postcode":"8710",
    "addr:street":"Hulstersestraat;Ooigem",
    "iso:country":"BE",
    "sg:address":"Hulstersestraat 238",
    "sg:city":"Wielsbeke (ooigem)",
    "sg:classifiers":[
        {
            "category":"Building & Trades",
            "subcategory":"Plumbing",
            "type":"Services"
        }
    ],
    "sg:phone":"+32 56 66 33 61",
    "sg:postcode":"8710",
    "sg:province":"West-Vlaanderen",
    "sg:tags":[
        "repair",
        "mainten",
        "-",
        "central",
        "heating"
    ],
    "wof:name":"Derveaux-vanackere C",
    "wof:placetype":"venue"
},
  "geometry": {"coordinates":[3.3173239231,50.9041404724],"type":"Point"}
}