{
  "type": "Feature",
  "properties": {
    "addr:full":"Tervuursevest 60 Leuven Vlaams-Brabant 3000",
    "addr:housenumber":"60",
    "addr:postcode":"3000",
    "addr:street":"Tervuursevest",
    "iso:country":"BE",
    "sg:address":"Tervuursevest 60",
    "sg:city":"Leuven",
    "sg:classifiers":[
        {
            "category":"Restaurant",
            "type":"Food & Drink"
        }
    ],
    "sg:phone":"+32 16 22 86 72",
    "sg:postcode":"3000",
    "sg:province":"Vlaams-Brabant",
    "wof:name":"De Waaiberg",
    "wof:placetype":"venue"
},
  "geometry": {"coordinates":[4.6956171989,50.869682312],"type":"Point"}
}