{
  "type": "Feature",
  "properties": {
    "addr:full":"Rue Rodolphe Delval 33 Courcelles (trazegnies) Hainaut 6183",
    "addr:housenumber":"33",
    "addr:postcode":"6183",
    "addr:street":"Rue Rodolphe Delval",
    "iso:country":"BE",
    "sg:address":"Rue Rodolphe Delval 33",
    "sg:city":"Courcelles (trazegnies)",
    "sg:classifiers":[
        {
            "category":"Retail",
            "subcategory":"Repair Shop",
            "type":"Services"
        }
    ],
    "sg:phone":"+32 71 45 68 34",
    "sg:postcode":"6183",
    "sg:province":"Hainaut",
    "sg:tags":[
        "radio",
        "television",
        "-",
        "maintenance"
    ],
    "wof:name":"Gilbert",
    "wof:placetype":"venue"
},
  "geometry": {"coordinates":[4.3293838501,50.4633407593],"type":"Point"}
}