{
  "type": "Feature",
  "properties": {
    "addr:full":"Corneel De Ceusterstraat 8 Machelen (diegem) Vlaams-Brabant 1831",
    "addr:housenumber":"8",
    "addr:postcode":"1831",
    "addr:street":"Ceusterstraat",
    "iso:country":"BE",
    "sg:address":"Corneel De Ceusterstraat 8",
    "sg:city":"Machelen (diegem)",
    "sg:classifiers":[
        {
            "category":"Building & Trades",
            "subcategory":"Plumbing",
            "type":"Services"
        }
    ],
    "sg:phone":"+32 2 721 47 67",
    "sg:postcode":"1831",
    "sg:province":"Vlaams-Brabant",
    "sg:tags":[
        "contractor"
    ],
    "wof:name":"Verhulst F",
    "wof:placetype":"venue"
},
  "geometry": {"coordinates":[4.4404191971,50.8926811218],"type":"Point"}
}