{
  "type": "Feature",
  "properties": {
    "addr:full":"Avenue De Spa 10 Verviers Li\u00e8ge 4800",
    "addr:housenumber":"10",
    "addr:postcode":"4800",
    "addr:street":"Avenue De Spa",
    "iso:country":"BE",
    "sg:address":"Avenue De Spa 10",
    "sg:city":"Verviers",
    "sg:orig_category":"Services de recherches and bureaux de d\u00e9tectives. Evaluation and estimation de biens immobiliers. G\u00e9",
    "sg:phone":"+32 87 22 71 63",
    "sg:postcode":"4800",
    "sg:province":"Li\u00e8ge",
    "wof:name":"F. Boxho",
    "wof:placetype":"venue"
},
  "geometry": {"coordinates":[5.862267971,50.5840301514],"type":"Point"}
}