{
  "type": "Feature",
  "properties": {
    "iso:country":"BE",
    "sg:address":"Naamsesteenweg 33",
    "sg:city":"Leuven (heverlee)",
    "sg:classifiers":[
        {
            "category":"Shopping",
            "subcategory":"Bicycles & Sporting Goods",
            "type":"Retail Goods"
        }
    ],
    "sg:phone":"+32 16 22 85 36",
    "sg:postcode":"3001",
    "sg:province":"Vlaams-Brabant",
    "sg:tags":[
        "-"
    ],
    "wof:name":"Niclaes Geert Bvba",
    "wof:placetype":"venue"
},
  "geometry": {"coordinates":[4.6975669861,50.8671798706],"type":"Point"}
}