{
  "type": "Feature",
  "properties": {
    "addr:full":"Rue Monseigneur Beyls 62 Renaix Oost-Vlaanderen 9600",
    "addr:housenumber":"62",
    "addr:postcode":"9600",
    "addr:street":"Rue Monseigneur Beyls",
    "iso:country":"BE",
    "sg:address":"Rue Monseigneur Beyls 62",
    "sg:city":"Renaix",
    "sg:classifiers":[
        {
            "category":"Home & Garden",
            "subcategory":"Building Materials",
            "type":"Retail Goods"
        }
    ],
    "sg:phone":"+32 496 27 97 15",
    "sg:postcode":"9600",
    "sg:province":"Oost-Vlaanderen",
    "sg:tags":[
        "window"
    ],
    "wof:name":"Destercke",
    "wof:placetype":"venue"
},
  "geometry": {"coordinates":[3.6212608814,50.7418937683],"type":"Point"}
}