{
  "type": "Feature",
  "properties": {
    "addr:full":"Avenue Houba De Strooper 608 Bruxelles Bruxelles-Capitale 1020",
    "addr:housenumber":"608",
    "addr:postcode":"1020",
    "addr:street":"Avenue Houba De Strooper",
    "iso:country":"BE",
    "sg:address":"Avenue Houba De Strooper 608",
    "sg:city":"Bruxelles",
    "sg:classifiers":[
        {
            "category":"Home & Garden",
            "subcategory":"Building Materials",
            "type":"Retail Goods"
        }
    ],
    "sg:phone":"+32 2 478 62 65",
    "sg:postcode":"1020",
    "sg:province":"Bruxelles-Capitale",
    "sg:tags":[
        "article",
        "-",
        "do-it-yourself"
    ],
    "wof:name":"De Smedt-de Passe-vite",
    "wof:placetype":"venue"
},
  "geometry": {"coordinates":[4.330698967,50.8945732117],"type":"Point"}
}