{
  "type": "Feature",
  "properties": {
    "iso:country":"BE",
    "sg:address":"Place Du Saucy 8",
    "sg:city":"Esneux",
    "sg:orig_category":"Maisons de repos and r\u00e9sidences",
    "sg:phone":"+32 4 388 10 98",
    "sg:postcode":"4130",
    "sg:province":"Li\u00e8ge",
    "wof:name":"Home L'eau Vive",
    "wof:placetype":"venue"
},
  "geometry": {"coordinates":[5.5850901604,50.5695991516],"type":"Point"}
}