{
  "type": "Feature",
  "properties": {
    "iso:country":"BE",
    "sg:address":"Kapellestr 37",
    "sg:city":"Deinze (groot)",
    "sg:orig_category":"Kapsalons",
    "sg:phone":"+32 9 386 15 50",
    "sg:postcode":"9800",
    "sg:province":"Oost-Vlaanderen",
    "wof:name":"Studio B",
    "wof:placetype":"venue"
},
  "geometry": {"coordinates":[3.5479300022,50.9813995361],"type":"Point"}
}