{
  "type": "Feature",
  "properties": {
    "addr:full":"Stationsplein Roeselare West-Vlaanderen 8800",
    "addr:postcode":"8800",
    "addr:street":"Stationsplein",
    "iso:country":"BE",
    "sg:address":"Stationsplein",
    "sg:city":"Roeselare",
    "sg:orig_category":"Transports ferroviaires",
    "sg:phone":"+32 51 24 06 41",
    "sg:postcode":"8800",
    "sg:province":"West-Vlaanderen",
    "wof:name":"Station Roeselare",
    "wof:placetype":"venue"
},
  "geometry": {"coordinates":[3.1297049522,50.9487457275],"type":"Point"}
}