{
  "type": "Feature",
  "properties": {
    "addr:full":"Avenue Henri Semal 35 Genappe Brabant Wallon 1470",
    "addr:housenumber":"35",
    "addr:postcode":"1470",
    "addr:street":"Avenue Henri Semal;Wallon",
    "iso:country":"BE",
    "sg:address":"Avenue Henri Semal 35",
    "sg:city":"Genappe",
    "sg:classifiers":[
        {
            "category":"Recreation",
            "subcategory":"Fishing",
            "type":"Entertainment"
        }
    ],
    "sg:phone":"+32 67 77 30 78",
    "sg:postcode":"1470",
    "sg:province":"Brabant Wallon",
    "sg:tags":[
        "tackle"
    ],
    "wof:name":"L'anneau Du Pecheur",
    "wof:placetype":"venue"
},
  "geometry": {"coordinates":[4.4471101761,50.6120185852],"type":"Point"}
}