{
  "type": "Feature",
  "properties": {
    "iso:country":"BE",
    "sg:address":"Ruelle Du Couvent 12",
    "sg:city":"Brunehaut (laplaigne)",
    "sg:classifiers":[
        {
            "category":"Health Services",
            "subcategory":"Nursing And Care Facility",
            "type":"Services"
        }
    ],
    "sg:phone":"+32 69 34 64 66",
    "sg:postcode":"7622",
    "sg:province":"Hainaut",
    "sg:tags":[
        "home"
    ],
    "wof:name":"Chaval L",
    "wof:placetype":"venue"
},
  "geometry": {"coordinates":[3.4469599724,50.5208015442],"type":"Point"}
}