{
  "type": "Feature",
  "properties": {
    "iso:country":"BE",
    "sg:address":"Rue Du Bourrelier 7",
    "sg:city":"Jurbise",
    "sg:orig_category":"Rundveehouders",
    "sg:phone":"+32 65 22 98 01",
    "sg:postcode":"7050",
    "sg:province":"Hainaut",
    "wof:name":"Jean Soil",
    "wof:placetype":"venue"
},
  "geometry": {"coordinates":[3.9256999493,50.5348434448],"type":"Point"}
}