{
  "type": "Feature",
  "properties": {
    "iso:country":"BE",
    "sg:address":"Zolderstraat 10",
    "sg:city":"Hasselt (kermt)",
    "sg:classifiers":[
        {
            "category":"Arts & Performance",
            "subcategory":"Music",
            "type":"Entertainment"
        }
    ],
    "sg:phone":"+32 11 25 32 81",
    "sg:postcode":"3510",
    "sg:province":"Limburg",
    "sg:tags":[
        "disc-jockeys"
    ],
    "wof:name":"Elema",
    "wof:placetype":"venue"
},
  "geometry": {"coordinates":[5.2419810295,50.9691963196],"type":"Point"}
}