{
  "type": "Feature",
  "properties": {
    "iso:country":"BE",
    "sg:address":"Avenue De Roodebeek 125",
    "sg:city":"Schaarbeek/schaerbeek",
    "sg:orig_category":"Travaux de finition and nettoyage de b\u00e2timents. Services de Nettoyage and de D\u00e9sinfection",
    "sg:phone":"+32 2 736 89 76",
    "sg:postcode":"1030",
    "sg:province":"Bruxelles-Capitale",
    "wof:name":"L'hygi\u00c8ne",
    "wof:placetype":"venue"
},
  "geometry": {"coordinates":[4.4003539085,50.8484153748],"type":"Point"}
}