{
  "type": "Feature",
  "properties": {
    "iso:country":"BE",
    "sg:address":"Rue De La Tourelle 59 Box 3",
    "sg:city":"Bruxelles (etterbeek)",
    "sg:classifiers":[
        {
            "category":"Arts & Performance",
            "subcategory":"Music",
            "type":"Entertainment"
        }
    ],
    "sg:phone":"+32 2 230 47 66",
    "sg:postcode":"1040",
    "sg:province":"Bruxelles-Capitale",
    "sg:tags":[
        "freelance",
        "musician"
    ],
    "wof:name":"Botev V",
    "wof:placetype":"venue"
},
  "geometry": {"coordinates":[4.3839731216,50.8377761841],"type":"Point"}
}