{
  "type": "Feature",
  "properties": {
    "iso:country":"BE",
    "sg:address":"Grote Parijsstraat 7",
    "sg:city":"Zemst",
    "sg:orig_category":"Beheer onroerend goed",
    "sg:phone":"+32 15 61 07 12",
    "sg:postcode":"1980",
    "sg:province":"Vlaams-Brabant",
    "wof:name":"Marimmo",
    "wof:placetype":"venue"
},
  "geometry": {"coordinates":[4.4304728508,50.9921607971],"type":"Point"}
}