{
  "type": "Feature",
  "properties": {
    "iso:country":"BE",
    "sg:address":"Mechelsesteenweg 1062",
    "sg:city":"Herent",
    "sg:orig_category":"Diverse meubelen Fab Meubelzaken, woning- and keukeninrichting",
    "sg:phone":"+32 16 48 19 98",
    "sg:postcode":"3020",
    "sg:province":"Vlaams-Brabant",
    "wof:name":"Deluca-design",
    "wof:placetype":"venue"
},
  "geometry": {"coordinates":[4.6489782333,50.9196052551],"type":"Point"}
}