{
  "type": "Feature",
  "properties": {
    "iso:country":"BE",
    "sg:address":"Rue Du D\u00c9p\u00d4t 17",
    "sg:city":"Chatelet",
    "sg:orig_category":"Dakwerken",
    "sg:phone":"+32 71 39 27 02",
    "sg:postcode":"6200",
    "sg:province":"Hainaut",
    "wof:name":"Toiturhome",
    "wof:placetype":"venue"
},
  "geometry": {"coordinates":[4.5315008163,50.4026031494],"type":"Point"}
}