{
  "type": "Feature",
  "properties": {
    "addr:full":"Rue Des Combattants 122 Beloeil (ellignies-sainte-anne) Hainaut 7972",
    "addr:housenumber":"122",
    "addr:postcode":"7972",
    "addr:street":"Rue Des Combattants",
    "iso:country":"BE",
    "sg:address":"Rue Des Combattants 122",
    "sg:city":"Beloeil (ellignies-sainte-anne)",
    "sg:classifiers":[
        {
            "category":"Retail",
            "subcategory":"Veterinary Services",
            "type":"Services"
        }
    ],
    "sg:phone":"+32 477 20 29 60",
    "sg:postcode":"7972",
    "sg:province":"Hainaut",
    "sg:tags":[
        "veterinarian"
    ],
    "wof:name":"Dubois Nathalie Sprl",
    "wof:placetype":"venue"
},
  "geometry": {"coordinates":[3.711149931,50.5530281067],"type":"Point"}
}