{
  "type": "Feature",
  "properties": {
    "addr:full":"Rue Lucien-burnotte 17 Neufchateau Luxembourg 6840",
    "addr:housenumber":"17",
    "addr:postcode":"6840",
    "addr:street":"Rue Lucien-Burnotte",
    "iso:country":"BE",
    "sg:address":"Rue Lucien-burnotte 17",
    "sg:city":"Neufchateau",
    "sg:orig_category":"Dameskledingzaken Herenkledingzaken",
    "sg:phone":"+32 61 27 70 63",
    "sg:postcode":"6840",
    "sg:province":"Luxembourg",
    "wof:name":"A. Boulanger & Fils",
    "wof:placetype":"venue"
},
  "geometry": {"coordinates":[5.4356780052,49.8407325745],"type":"Point"}
}