{
  "type": "Feature",
  "properties": {
    "addr:full":"Boulevard Jean-de-wilde 18 Li\u00c8ge Li\u00e8ge 4000",
    "addr:housenumber":"18",
    "addr:postcode":"4000",
    "addr:street":"Boulevard Jean-De-Wilde",
    "iso:country":"BE",
    "sg:address":"Boulevard Jean-de-wilde 18",
    "sg:city":"Li\u00c8ge",
    "sg:orig_category":"Assurances. Bureaux de poste",
    "sg:phone":"+32 4 226 16 68",
    "sg:postcode":"4000",
    "sg:province":"Li\u00e8ge",
    "wof:name":"La Poste",
    "wof:placetype":"venue"
},
  "geometry": {"coordinates":[5.5673398972,50.6599235535],"type":"Point"}
}