{
  "type": "Feature",
  "properties": {
    "iso:country":"BE",
    "sg:address":"Filomenastraat 25",
    "sg:city":"Antwerpen",
    "sg:classifiers":[
        {
            "category":"Arts & Performance",
            "subcategory":"Art Gallery",
            "type":"Entertainment"
        }
    ],
    "sg:phone":"+32 3 218 68 54",
    "sg:postcode":"2018",
    "sg:province":"Antwerpen",
    "wof:name":"Paljas Galerij",
    "wof:placetype":"venue"
},
  "geometry": {"coordinates":[4.4293341637,51.2060661316],"type":"Point"}
}