{
  "type": "Feature",
  "properties": {
    "addr:full":"Lombaardstraat 15 Ieper West-Vlaanderen 8900",
    "addr:housenumber":"15",
    "addr:postcode":"8900",
    "addr:street":"Lombaardstraat",
    "iso:country":"BE",
    "sg:address":"Lombaardstraat 15",
    "sg:city":"Ieper",
    "sg:orig_category":"Kapsalons",
    "sg:phone":"+32 57 20 29 23",
    "sg:postcode":"8900",
    "sg:province":"West-Vlaanderen",
    "wof:name":"Coiffure Elys\u00c9e",
    "wof:placetype":"venue"
},
  "geometry": {"coordinates":[2.8869299889,50.8475570679],"type":"Point"}
}