{
  "type": "Feature",
  "properties": {
    "addr:full":"Heidedreef 43 Schilde Antwerpen 2970",
    "addr:housenumber":"43",
    "addr:postcode":"2970",
    "addr:street":"Heidedreef",
    "iso:country":"BE",
    "sg:address":"Heidedreef 43",
    "sg:city":"Schilde",
    "sg:orig_category":"Artsen and specialisten",
    "sg:phone":"+32 3 353 07 37",
    "sg:postcode":"2970",
    "sg:province":"Antwerpen",
    "wof:name":"Yves Gerard",
    "wof:placetype":"venue"
},
  "geometry": {"coordinates":[4.5581350327,51.2363204956],"type":"Point"}
}