{
  "type": "Feature",
  "properties": {
    "addr:full":"Rue Du Pairois 71 Morlanwelz (carni\u00e8res) Hainaut 7141",
    "addr:housenumber":"71",
    "addr:postcode":"7141",
    "addr:street":"Rue Du Pairois",
    "iso:country":"BE",
    "sg:address":"Rue Du Pairois 71",
    "sg:city":"Morlanwelz (carni\u00e8res)",
    "sg:classifiers":[
        {
            "category":"Health Services",
            "subcategory":"Doctor",
            "type":"Services"
        }
    ],
    "sg:phone":"+32 64 44 60 14",
    "sg:postcode":"7141",
    "sg:province":"Hainaut",
    "sg:tags":[
        "medicinephysicians",
        "surgeon"
    ],
    "wof:name":"Arnould P",
    "wof:placetype":"venue"
},
  "geometry": {"coordinates":[4.2646450996,50.4421386719],"type":"Point"}
}