{
  "type": "Feature",
  "properties": {
    "addr:full":"Remylaan 4 Leuven Vlaams-Brabant 3000",
    "addr:housenumber":"4",
    "addr:postcode":"3000",
    "addr:street":"Remylaan",
    "iso:country":"BE",
    "sg:address":"Remylaan 4",
    "sg:city":"Leuven",
    "sg:classifiers":[
        {
            "category":"Shopping",
            "subcategory":"Crafts & Fabrics",
            "type":"Retail Goods"
        }
    ],
    "sg:phone":"+32 16 24 85 11",
    "sg:postcode":"3000",
    "sg:province":"Vlaams-Brabant",
    "sg:tags":[
        "adhesive"
    ],
    "wof:name":"Remy Industries Nv",
    "wof:placetype":"venue"
},
  "geometry": {"coordinates":[4.7036700249,50.8793869019],"type":"Point"}
}