{
  "type": "Feature",
  "properties": {
    "addr:full":"Rue De L'ath\u00c9n\u00c9e 10 Elsene/ixelles Bruxelles-Capitale 1050",
    "addr:housenumber":"10",
    "addr:postcode":"1050",
    "addr:street":"Rue De L'Athe \u0301Ne\u0301E",
    "iso:country":"BE",
    "sg:address":"Rue De L'ath\u00c9n\u00c9e 10",
    "sg:city":"Elsene/ixelles",
    "sg:classifiers":[
        {
            "category":"Cafe",
            "type":"Food & Drink"
        }
    ],
    "sg:phone":"+32 2 512 58 79",
    "sg:postcode":"1050",
    "sg:province":"Bruxelles-Capitale",
    "sg:tags":[
        "caf\u00e9s"
    ],
    "wof:name":"Xiii Oxy Bar",
    "wof:placetype":"venue"
},
  "geometry": {"coordinates":[4.3648061752,50.8351287842],"type":"Point"}
}