{
  "type": "Feature",
  "properties": {
    "iso:country":"BE",
    "sg:address":"Auguste Reyerslaan 41b8",
    "sg:city":"Schaarbeek/schaerbeek",
    "sg:orig_category":"Advocaten and juridische adviseurs",
    "sg:phone":"+32 2 734 79 26",
    "sg:postcode":"1030",
    "sg:province":"Bruxelles-Capitale",
    "wof:name":"J.m. Hauspie",
    "wof:placetype":"venue"
},
  "geometry": {"coordinates":[4.3999519348,50.8525505066],"type":"Point"}
}