{
  "type": "Feature",
  "properties": {
    "iso:country":"BE",
    "sg:address":"Rue Julien Ghuysen 50",
    "sg:city":"Bl\u00e9gny (trembleur)",
    "sg:classifiers":[
        {
            "category":"Health Services",
            "subcategory":"Health Practitioner",
            "type":"Services"
        }
    ],
    "sg:phone":"+32 4 387 49 18",
    "sg:postcode":"4670",
    "sg:province":"Li\u00e8ge",
    "sg:tags":[
        "physiotherapist"
    ],
    "wof:name":"Joblin L",
    "wof:placetype":"venue"
},
  "geometry": {"coordinates":[5.7287960052,50.6697692871],"type":"Point"}
}