{
  "type": "Feature",
  "properties": {
    "addr:full":"Corneliusstr 46 Lebbeke (groot) Oost-Vlaanderen 9280",
    "addr:housenumber":"46",
    "addr:postcode":"9280",
    "addr:street":"Corneliusstr;Groot Oost-Vlaanderen",
    "iso:country":"BE",
    "sg:address":"Corneliusstr 46",
    "sg:city":"Lebbeke (groot)",
    "sg:classifiers":[
        {
            "category":"Personal",
            "subcategory":"Beauty Salon",
            "type":"Services"
        }
    ],
    "sg:phone":"+32 52 41 28 91",
    "sg:postcode":"9280",
    "sg:province":"Oost-Vlaanderen",
    "sg:tags":[
        "de",
        "coiffure"
    ],
    "wof:name":"Conny",
    "wof:placetype":"venue"
},
  "geometry": {"coordinates":[4.0898280144,50.9990196228],"type":"Point"}
}