{
  "type": "Feature",
  "properties": {
    "iso:country":"BE",
    "sg:address":"Kleine Hemelweg 18a",
    "sg:city":"Zonhoven",
    "sg:classifiers":[
        {
            "category":"Shopping",
            "subcategory":"Bicycles & Sporting Goods",
            "type":"Retail Goods"
        }
    ],
    "sg:phone":"+32 11 81 67 30",
    "sg:postcode":"3520",
    "sg:province":"Limburg",
    "sg:tags":[
        "article",
        "de",
        "sport",
        "camping"
    ],
    "wof:name":"Knappen",
    "wof:placetype":"venue"
},
  "geometry": {"coordinates":[5.3629188538,50.984172821],"type":"Point"}
}