{
  "type": "Feature",
  "properties": {
    "addr:full":"Klakkedellestraat 63 Sint-lambrechts-woluwe/woluwe-saint-lambert Bruxelles-Capitale 1200",
    "addr:housenumber":"63",
    "addr:postcode":"1200",
    "addr:street":"Klakkedellestraat",
    "iso:country":"BE",
    "sg:address":"Klakkedellestraat 63",
    "sg:city":"Sint-lambrechts-woluwe/woluwe-saint-lambert",
    "sg:orig_category":"Public-relationsbureaus Reclamebureaus",
    "sg:phone":"+32 2 772 20 50",
    "sg:postcode":"1200",
    "sg:province":"Bruxelles-Capitale",
    "wof:name":"Communication Services",
    "wof:placetype":"venue"
},
  "geometry": {"coordinates":[4.4442000389,50.8481826782],"type":"Point"}
}