{
  "type": "Feature",
  "properties": {
    "iso:country":"BE",
    "sg:address":"Rue Van Opr\u00c9 95",
    "sg:city":"Namur",
    "sg:classifiers":[
        {
            "category":"Insurance",
            "subcategory":"Life Insurance",
            "type":"Services"
        }
    ],
    "sg:phone":"+32 81 33 18 11",
    "sg:postcode":"5100",
    "sg:province":"Namur",
    "sg:tags":[
        "compagnies",
        "habitation",
        "assurance",
        "vie"
    ],
    "wof:name":"Royale Belge",
    "wof:placetype":"venue"
},
  "geometry": {"coordinates":[4.8759188652,50.4607429504],"type":"Point"}
}