{
  "type": "Feature",
  "properties": {
    "addr:full":"13 Rue Du Tige Herstal Li\u00e8ge 4040",
    "addr:housenumber":"13",
    "addr:postcode":"4040",
    "addr:street":"Rue Du Tige",
    "iso:country":"BE",
    "sg:address":"13 Rue Du Tige",
    "sg:city":"Herstal",
    "sg:classifiers":[
        {
            "category":"Manufacturing",
            "subcategory":"Metals",
            "type":"Manufacturing & Wholesale Goods"
        }
    ],
    "sg:phone":"+32 4 248 88 11",
    "sg:postcode":"4040",
    "sg:province":"Li\u00e8ge",
    "sg:tags":[
        "-",
        "machine",
        "equipment",
        "engineering",
        "machinery",
        "mechanical"
    ],
    "wof:name":"New Lachaussee Sa",
    "wof:placetype":"venue"
},
  "geometry": {"coordinates":[5.6352419853,50.6710014343],"type":"Point"}
}