{
  "type": "Feature",
  "properties": {
    "addr:full":"Ter Kamerenstraat 46 Sint-lambrechts-woluwe/woluwe-saint-lambert Bruxelles-Capitale 1200",
    "addr:housenumber":"46",
    "addr:postcode":"1200",
    "addr:street":"Ter Kamerenstraat",
    "iso:country":"BE",
    "sg:address":"Ter Kamerenstraat 46",
    "sg:city":"Sint-lambrechts-woluwe/woluwe-saint-lambert",
    "sg:orig_category":"Geluidsopnames",
    "sg:phone":"+32 2 762 04 46",
    "sg:postcode":"1200",
    "sg:province":"Bruxelles-Capitale",
    "wof:name":"Fe. Terpsichore",
    "wof:placetype":"venue"
},
  "geometry": {"coordinates":[4.4246401787,50.8393821716],"type":"Point"}
}