{
  "type": "Feature",
  "properties": {
    "iso:country":"BE",
    "sg:address":"Rue Des Iles 30",
    "sg:city":"Florenville",
    "sg:orig_category":"Installation de menuiserie en bois and plastique",
    "sg:phone":"+32 61 31 42 20",
    "sg:postcode":"6821",
    "sg:province":"Luxembourg",
    "wof:name":"Roger Belva",
    "wof:placetype":"venue"
},
  "geometry": {"coordinates":[5.3206720352,49.7125091553],"type":"Point"}
}