{
  "type": "Feature",
  "properties": {
    "iso:country":"BE",
    "sg:address":"Chauss\u00e9e De Lannoy 27",
    "sg:city":"Tournai (froyennes)",
    "sg:classifiers":[
        {
            "category":"Health Services",
            "subcategory":"Health Practitioner",
            "type":"Services"
        }
    ],
    "sg:phone":"+32 69 84 77 68",
    "sg:postcode":"7503",
    "sg:province":"Hainaut",
    "sg:tags":[
        "physiotherapist"
    ],
    "wof:name":"Moreau Martine",
    "wof:placetype":"venue"
},
  "geometry": {"coordinates":[3.3603489399,50.619052887],"type":"Point"}
}