{
  "type": "Feature",
  "properties": {
    "addr:full":"Chemin De Naast 12 Braine-le-comte Hainaut 7090",
    "addr:housenumber":"12",
    "addr:postcode":"7090",
    "addr:street":"Chemin De Naast",
    "iso:country":"BE",
    "sg:address":"Chemin De Naast 12",
    "sg:city":"Braine-le-comte",
    "sg:orig_category":"Eleveurs de bovins",
    "sg:phone":"+32 67 55 24 64",
    "sg:postcode":"7090",
    "sg:province":"Hainaut",
    "wof:name":"Wilfried Maes",
    "wof:placetype":"venue"
},
  "geometry": {"coordinates":[4.1257519722,50.5823898315],"type":"Point"}
}