{
  "type": "Feature",
  "properties": {
    "addr:full":"Molenstraat 33 Grimbergen (beigem) Vlaams-Brabant 1852",
    "addr:housenumber":"33",
    "addr:postcode":"1852",
    "addr:street":"Molenstraat",
    "iso:country":"BE",
    "sg:address":"Molenstraat 33",
    "sg:city":"Grimbergen (beigem)",
    "sg:classifiers":[
        {
            "category":"Real Estate",
            "subcategory":"Architect",
            "type":"Services"
        }
    ],
    "sg:phone":"+32 2 269 52 73",
    "sg:postcode":"1852",
    "sg:province":"Vlaams-Brabant",
    "wof:name":"Van Den Broeck Wouter",
    "wof:placetype":"venue"
},
  "geometry": {"coordinates":[4.3684282303,50.9579772949],"type":"Point"}
}