{
  "type": "Feature",
  "properties": {
    "addr:full":"Rogery 54 Gouvy Luxembourg 6671",
    "addr:housenumber":"54",
    "addr:postcode":"6671",
    "addr:street":"Rogery",
    "iso:country":"BE",
    "sg:address":"Rogery 54",
    "sg:city":"Gouvy",
    "sg:orig_category":"Eleveurs de bovins",
    "sg:phone":"+32 80 21 55 43",
    "sg:postcode":"6671",
    "sg:province":"Luxembourg",
    "wof:name":"Michel Remacle",
    "wof:placetype":"venue"
},
  "geometry": {"coordinates":[5.9497151375,50.2418785095],"type":"Point"}
}