{
  "type": "Feature",
  "properties": {
    "iso:country":"BE",
    "sg:address":"Rue A-l'eau 39",
    "sg:city":"Gembloux",
    "sg:orig_category":"Elektrische installaties voor woningen",
    "sg:phone":"+32 81 61 58 32",
    "sg:postcode":"5030",
    "sg:province":"Namur",
    "wof:name":"Eric Stenuit",
    "wof:placetype":"venue"
},
  "geometry": {"coordinates":[4.6888790131,50.5509796143],"type":"Point"}
}