{
  "type": "Feature",
  "properties": {
    "iso:country":"BE",
    "sg:address":"Rue Henri Alexandre 4",
    "sg:city":"Ans",
    "sg:orig_category":"Dierenartsen",
    "sg:phone":"+32 4 246 44 57",
    "sg:postcode":"4430",
    "sg:province":"Li\u00e8ge",
    "wof:name":"Serge Simonis",
    "wof:placetype":"venue"
},
  "geometry": {"coordinates":[5.5359802246,50.6654891968],"type":"Point"}
}