{
  "type": "Feature",
  "properties": {
    "addr:full":"Steenweg 113 Box 2 Alken Limburg 3570",
    "addr:housenumber":"113;2",
    "addr:postcode":"3570",
    "addr:street":"Steenweg;Box",
    "iso:country":"BE",
    "sg:address":"Steenweg 113 Box 2",
    "sg:city":"Alken",
    "sg:classifiers":[
        {
            "category":"Professional",
            "subcategory":"Art Services",
            "type":"Services"
        }
    ],
    "sg:phone":"+32 11 72 82 58",
    "sg:postcode":"3570",
    "sg:province":"Limburg",
    "sg:tags":[
        "realization",
        "audio-visual"
    ],
    "wof:name":"Concept Design",
    "wof:placetype":"venue"
},
  "geometry": {"coordinates":[5.2913517952,50.8895378113],"type":"Point"}
}