{
  "type": "Feature",
  "properties": {
    "addr:full":"Rue Des Egalots 2-4 Fosses-la-ville Namur 5070",
    "addr:housenumber":"2-4",
    "addr:postcode":"5070",
    "addr:street":"Rue Des Egalots",
    "iso:country":"BE",
    "sg:address":"Rue Des Egalots 2-4",
    "sg:city":"Fosses-la-ville",
    "sg:orig_category":"Articles de jardin",
    "sg:phone":"+32 81 21 22 39",
    "sg:postcode":"5070",
    "sg:province":"Namur",
    "wof:name":"Corriat",
    "wof:placetype":"venue"
},
  "geometry": {"coordinates":[4.6962051392,50.3955154419],"type":"Point"}
}