{
  "type": "Feature",
  "properties": {
    "addr:full":"Rue De Neerpede 225 Anderlecht Bruxelles-Capitale 1070",
    "addr:housenumber":"225",
    "addr:postcode":"1070",
    "addr:street":"Rue De Neerpede",
    "iso:country":"BE",
    "sg:address":"Rue De Neerpede 225",
    "sg:city":"Anderlecht",
    "sg:orig_category":"Pharmaciens",
    "sg:phone":"+32 2 522 47 00",
    "sg:postcode":"1070",
    "sg:province":"Bruxelles-Capitale",
    "wof:name":"Pharmacie Duch\u00cane",
    "wof:placetype":"venue"
},
  "geometry": {"coordinates":[4.2888889313,50.8308982849],"type":"Point"}
}