{
  "type": "Feature",
  "properties": {
    "addr:full":"Kapellenstraat 9 Glabbeek (glabbeek-zuurbemde) Vlaams-Brabant 3380",
    "addr:housenumber":"9",
    "addr:postcode":"3380",
    "addr:street":"Kapellenstraat",
    "iso:country":"BE",
    "sg:address":"Kapellenstraat 9",
    "sg:city":"Glabbeek (glabbeek-zuurbemde)",
    "sg:classifiers":[
        {
            "category":"Personal",
            "subcategory":"Beauty Salon",
            "type":"Services"
        }
    ],
    "sg:phone":"+32 16 77 02 94",
    "sg:postcode":"3380",
    "sg:province":"Vlaams-Brabant",
    "sg:tags":[
        "lady",
        "-",
        "hairdressing"
    ],
    "wof:name":"Tinne",
    "wof:placetype":"venue"
},
  "geometry": {"coordinates":[4.9449520111,50.8817405701],"type":"Point"}
}