{
  "type": "Feature",
  "properties": {
    "iso:country":"BE",
    "sg:address":"Marktplein 68",
    "sg:city":"Harelbeke",
    "sg:orig_category":"Solariums",
    "sg:phone":"+32 56 72 96 71",
    "sg:postcode":"8530",
    "sg:province":"West-Vlaanderen",
    "wof:name":"Chic",
    "wof:placetype":"venue"
},
  "geometry": {"coordinates":[3.30904603,50.8556556702],"type":"Point"}
}