{
  "type": "Feature",
  "properties": {
    "addr:full":"Avenue Des Pl\u00e9iades 19 Bruxelles (woluwe-saint-lambert) Bruxelles-Capitale 1200",
    "addr:housenumber":"19",
    "addr:postcode":"1200",
    "addr:street":"Avenue Des Ple\u0301Iades",
    "iso:country":"BE",
    "sg:address":"Avenue Des Pl\u00e9iades 19",
    "sg:city":"Bruxelles (woluwe-saint-lambert)",
    "sg:classifiers":[
        {
            "category":"Landmark",
            "subcategory":"City Walls",
            "type":"Public Place"
        }
    ],
    "sg:phone":"+32 2 770 81 90",
    "sg:postcode":"1200",
    "sg:province":"Bruxelles-Capitale",
    "sg:tags":[
        "covering"
    ],
    "wof:name":"Muraspec",
    "wof:placetype":"venue"
},
  "geometry": {"coordinates":[4.4190731049,50.8543243408],"type":"Point"}
}