{
  "type": "Feature",
  "properties": {
    "addr:full":"Rue Saint-charles 21 Charleroi Hainaut 6061",
    "addr:housenumber":"21",
    "addr:postcode":"6061",
    "addr:street":"Rue Saint-Charles;Hainaut",
    "iso:country":"BE",
    "sg:address":"Rue Saint-charles 21",
    "sg:city":"Charleroi",
    "sg:orig_category":"Plomberie, chauffage and installations sanitaires",
    "sg:phone":"+32 71 30 04 24",
    "sg:postcode":"6061",
    "sg:province":"Hainaut",
    "wof:name":"Centrathern",
    "wof:placetype":"venue"
},
  "geometry": {"coordinates":[4.4581398964,50.4067382812],"type":"Point"}
}