{
  "type": "Feature",
  "properties": {
    "addr:full":"Rue Lucas 9 Ottignies-louvain-la-neuve Brabant Wallon 1340",
    "addr:housenumber":"9",
    "addr:postcode":"1340",
    "addr:street":"Rue Lucas",
    "iso:country":"BE",
    "sg:address":"Rue Lucas 9",
    "sg:city":"Ottignies-louvain-la-neuve",
    "sg:orig_category":"Gespecialiseerde residenti\u00eble bouw",
    "sg:phone":"+32 10 41 70 79",
    "sg:postcode":"1340",
    "sg:province":"Brabant Wallon",
    "wof:name":"Travetan",
    "wof:placetype":"venue"
},
  "geometry": {"coordinates":[4.5694551468,50.6672935486],"type":"Point"}
}