{
  "type": "Feature",
  "properties": {
    "addr:full":"Herentalsebaan 356 Wommelgem Antwerpen 2160",
    "addr:housenumber":"356",
    "addr:postcode":"2160",
    "addr:street":"Herentalsebaan",
    "iso:country":"BE",
    "sg:address":"Herentalsebaan 356",
    "sg:city":"Wommelgem",
    "sg:classifiers":[
        {
            "category":"Farming",
            "subcategory":"Livestock Farm",
            "type":"Manufacturing & Wholesale Goods"
        }
    ],
    "sg:phone":"+32 3 321 01 19",
    "sg:postcode":"2160",
    "sg:province":"Antwerpen",
    "sg:tags":[
        "buyer"
    ],
    "wof:name":"Willems M",
    "wof:placetype":"venue"
},
  "geometry": {"coordinates":[4.5027999878,51.1958312988],"type":"Point"}
}