{
  "type": "Feature",
  "properties": {
    "addr:full":"Rue Sainte-marguerite 43ba Li\u00c8ge Li\u00e8ge 4000",
    "addr:housenumber":"43ba",
    "addr:postcode":"4000",
    "addr:street":"Rue Sainte-Marguerite",
    "iso:country":"BE",
    "sg:address":"Rue Sainte-marguerite 43ba",
    "sg:city":"Li\u00c8ge",
    "sg:orig_category":"Verplichte sociale verzekeringen",
    "sg:phone":"+32 4 226 14 21",
    "sg:postcode":"4000",
    "sg:province":"Li\u00e8ge",
    "wof:name":"Mutualit\u00c9 Chr\u00c9tienne",
    "wof:placetype":"venue"
},
  "geometry": {"coordinates":[5.5617189407,50.6454162598],"type":"Point"}
}