{
  "type": "Feature",
  "properties": {
    "addr:full":"Sint-maria Aalterstraat 58 Aalter Oost-Vlaanderen 9880",
    "addr:housenumber":"58",
    "addr:postcode":"9880",
    "addr:street":"Aalterstraat",
    "iso:country":"BE",
    "sg:address":"Sint-maria Aalterstraat 58",
    "sg:city":"Aalter",
    "sg:orig_category":"Non-Classified Establishments",
    "sg:phone":"+32 9 374 22 91",
    "sg:postcode":"9880",
    "sg:province":"Oost-Vlaanderen",
    "wof:name":"Vanko Electric",
    "wof:placetype":"venue"
},
  "geometry": {"coordinates":[3.3886299133,51.0929031372],"type":"Point"}
}