{
  "type": "Feature",
  "properties": {
    "addr:full":"Stationsplein 4 Kortrijk West-Vlaanderen 8500",
    "addr:housenumber":"4",
    "addr:postcode":"8500",
    "addr:street":"Stationsplein",
    "iso:country":"BE",
    "sg:address":"Stationsplein 4",
    "sg:city":"Kortrijk",
    "sg:classifiers":[
        {
            "category":"Professional",
            "subcategory":"Employment Agencies",
            "type":"Services"
        }
    ],
    "sg:phone":"+32 51 24 95 67",
    "sg:postcode":"8500",
    "sg:province":"West-Vlaanderen",
    "sg:tags":[
        "temping",
        "-",
        "manual"
    ],
    "wof:name":"Etape",
    "wof:placetype":"venue"
},
  "geometry": {"coordinates":[3.2640399933,50.8259544373],"type":"Point"}
}