{
  "type": "Feature",
  "properties": {
    "iso:country":"BE",
    "sg:address":"Place Verte 46/50",
    "sg:city":"Verviers",
    "sg:classifiers":[
        {
            "category":"Fast Food",
            "type":"Food & Drink"
        }
    ],
    "sg:phone":"+32 87 33 02 00",
    "sg:postcode":"4801",
    "sg:province":"Li\u00e8ge",
    "sg:tags":[
        "\u00c0",
        "emporter",
        "restaurants"
    ],
    "wof:name":"Qiock Hamburger Restaurant",
    "wof:placetype":"venue"
},
  "geometry": {"coordinates":[5.8618907928,50.5926361084],"type":"Point"}
}