{
  "type": "Feature",
  "properties": {
    "addr:full":"Weg Naar Dilsen 26ba Maaseik Limburg 3680",
    "addr:housenumber":"26ba",
    "addr:postcode":"3680",
    "addr:street":"Weg Naar Dilsen",
    "iso:country":"BE",
    "sg:address":"Weg Naar Dilsen 26ba",
    "sg:city":"Maaseik",
    "sg:orig_category":"M\u00e9decins and sp\u00e9cialistes",
    "sg:phone":"+32 89 86 58 00",
    "sg:postcode":"3680",
    "sg:province":"Limburg",
    "wof:name":"J. Streignart",
    "wof:placetype":"venue"
},
  "geometry": {"coordinates":[5.791285038,51.0954208374],"type":"Point"}
}