{
  "type": "Feature",
  "properties": {
    "addr:full":"Avenue Du Progr\u00c8s 27 Sambreville Namur 5060",
    "addr:housenumber":"27",
    "addr:postcode":"5060",
    "addr:street":"Avenue Du Progre\u0300S",
    "iso:country":"BE",
    "sg:address":"Avenue Du Progr\u00c8s 27",
    "sg:city":"Sambreville",
    "sg:orig_category":"M\u00e9decins and sp\u00e9cialistes",
    "sg:phone":"+32 71 76 16 74",
    "sg:postcode":"5060",
    "sg:province":"Namur",
    "wof:name":"D. Chaumont",
    "wof:placetype":"venue"
},
  "geometry": {"coordinates":[4.6285200119,50.4448738098],"type":"Point"}
}