{
  "type": "Feature",
  "properties": {
    "addr:full":"Rue Des Tilleuls 14 Mont-saint-guibert Brabant Wallon 1435",
    "addr:housenumber":"14",
    "addr:postcode":"1435",
    "addr:street":"Rue Des Tilleuls",
    "iso:country":"BE",
    "sg:address":"Rue Des Tilleuls 14",
    "sg:city":"Mont-saint-guibert",
    "sg:classifiers":[
        {
            "category":"Cafe",
            "type":"Food & Drink"
        }
    ],
    "sg:phone":"+32 10 65 55 14",
    "sg:postcode":"1435",
    "sg:province":"Brabant Wallon",
    "sg:tags":[
        "caf\u00e9s"
    ],
    "wof:name":"Caf\u00c9 Des P\u00cacheurs",
    "wof:placetype":"venue"
},
  "geometry": {"coordinates":[4.6180000305,50.6333389282],"type":"Point"}
}