{
  "type": "Feature",
  "properties": {
    "addr:full":"Markt 8 Lokeren Oost-Vlaanderen 9160",
    "addr:housenumber":"8",
    "addr:postcode":"9160",
    "addr:street":"Markt",
    "iso:country":"BE",
    "sg:address":"Markt 8",
    "sg:city":"Lokeren",
    "sg:orig_category":"Banken and kredietinstellingen",
    "sg:phone":"+32 9 348 23 85",
    "sg:postcode":"9160",
    "sg:province":"Oost-Vlaanderen",
    "wof:name":"Kbc",
    "wof:placetype":"venue"
},
  "geometry": {"coordinates":[3.9864850044,51.1047401428],"type":"Point"}
}