{
  "type": "Feature",
  "properties": {
    "addr:full":"Chauss\u00e9e De Bruxelles 238 Waterloo Brabant Wallon 1410",
    "addr:housenumber":"238",
    "addr:postcode":"1410",
    "addr:street":"Chausse\u0301E De Bruxelles",
    "iso:country":"BE",
    "sg:address":"Chauss\u00e9e De Bruxelles 238",
    "sg:city":"Waterloo",
    "sg:classifiers":[
        {
            "category":"Personal",
            "subcategory":"Shoe Repair & Shine",
            "type":"Services"
        }
    ],
    "sg:phone":"+32 2 351 12 11",
    "sg:postcode":"1410",
    "sg:province":"Brabant Wallon",
    "sg:tags":[
        "shoemaker"
    ],
    "wof:name":"Cordonnerie Du Kiosque",
    "wof:placetype":"venue"
},
  "geometry": {"coordinates":[4.3982548714,50.7163314819],"type":"Point"}
}