{
  "type": "Feature",
  "properties": {
    "addr:full":"Rue D'arlon 50 Brussel/bruxelles Bruxelles-Capitale 1000",
    "addr:housenumber":"50",
    "addr:postcode":"1000",
    "addr:street":"Rue D'Arlon;/",
    "iso:country":"BE",
    "sg:address":"Rue D'arlon 50",
    "sg:city":"Brussel/bruxelles",
    "sg:orig_category":"Agences de relations publiques",
    "sg:phone":"+32 2 280 17 90",
    "sg:postcode":"1000",
    "sg:province":"Bruxelles-Capitale",
    "wof:name":"Countryw. Porter Novelli",
    "wof:placetype":"venue"
},
  "geometry": {"coordinates":[4.3724761009,50.8403549194],"type":"Point"}
}