{
  "type": "Feature",
  "properties": {
    "addr:full":"Vosdonkenstraat 5 Herselt Antwerpen 2230",
    "addr:housenumber":"5",
    "addr:postcode":"2230",
    "addr:street":"Vosdonkenstraat",
    "iso:country":"BE",
    "sg:address":"Vosdonkenstraat 5",
    "sg:city":"Herselt",
    "sg:orig_category":"Travaux de pl\u00e2trage",
    "sg:phone":"+32 16 69 66 56",
    "sg:postcode":"2230",
    "sg:province":"Antwerpen",
    "wof:name":"V.h. Pleisterwerken",
    "wof:placetype":"venue"
},
  "geometry": {"coordinates":[4.8252038956,51.046913147],"type":"Point"}
}