{
  "type": "Feature",
  "properties": {
    "addr:full":"Rue Haute 20 Rebecq (rebecq-rognon) Brabant Wallon 1430",
    "addr:housenumber":"20",
    "addr:postcode":"1430",
    "addr:street":"Rue Haute;Wallon",
    "iso:country":"BE",
    "sg:address":"Rue Haute 20",
    "sg:city":"Rebecq (rebecq-rognon)",
    "sg:classifiers":[
        {
            "category":"Building & Trades",
            "subcategory":"Plumbing",
            "type":"Services"
        }
    ],
    "sg:phone":"+32 67 63 73 41",
    "sg:postcode":"1430",
    "sg:province":"Brabant Wallon",
    "sg:tags":[
        "repair",
        "mainten",
        "-",
        "central",
        "heating"
    ],
    "wof:name":"Laus Ets",
    "wof:placetype":"venue"
},
  "geometry": {"coordinates":[4.1298809052,50.6485023499],"type":"Point"}
}