{
  "type": "Feature",
  "properties": {
    "addr:full":"Place Saint-remacle 7 Stavelot Li\u00e8ge 4970",
    "addr:housenumber":"7",
    "addr:postcode":"4970",
    "addr:street":"Place Saint-Remacle",
    "iso:country":"BE",
    "sg:address":"Place Saint-remacle 7",
    "sg:city":"Stavelot",
    "sg:classifiers":[
        {
            "category":"Insurance",
            "subcategory":"Insurance Agent",
            "type":"Services"
        }
    ],
    "sg:phone":"+32 80 86 24 94",
    "sg:postcode":"4970",
    "sg:province":"Li\u00e8ge",
    "sg:tags":[
        "broker"
    ],
    "wof:name":"Lievens Robert Sprl",
    "wof:placetype":"venue"
},
  "geometry": {"coordinates":[5.9300928116,50.3949317932],"type":"Point"}
}