{
  "type": "Feature",
  "properties": {
    "iso:country":"BE",
    "sg:address":"Mercatorpad 6 Box 102",
    "sg:city":"Leuven",
    "sg:classifiers":[
        {
            "category":"Communications",
            "type":"Services"
        }
    ],
    "sg:phone":"+32 16 22 41 33",
    "sg:postcode":"3000",
    "sg:province":"Vlaams-Brabant",
    "sg:tags":[
        "translator"
    ],
    "wof:name":"Magnus D",
    "wof:placetype":"venue"
},
  "geometry": {"coordinates":[4.6974568367,50.883014679],"type":"Point"}
}