{
  "type": "Feature",
  "properties": {
    "addr:full":"Chauss\u00e9e De Lodelinsart 88 Charleroi (gilly) Hainaut 6060",
    "addr:housenumber":"88",
    "addr:postcode":"6060",
    "addr:street":"Chausse\u0301E De Lodelinsart",
    "iso:country":"BE",
    "sg:address":"Chauss\u00e9e De Lodelinsart 88",
    "sg:city":"Charleroi (gilly)",
    "sg:classifiers":[
        {
            "category":"Home & Garden",
            "subcategory":"Hardware",
            "type":"Retail Goods"
        }
    ],
    "sg:phone":"+32 71 41 10 59",
    "sg:postcode":"6060",
    "sg:province":"Hainaut",
    "sg:tags":[
        "-"
    ],
    "wof:name":"Gianadda-menin Sprl",
    "wof:placetype":"venue"
},
  "geometry": {"coordinates":[4.4499931335,50.4214515686],"type":"Point"}
}