{
  "type": "Feature",
  "properties": {
    "addr:full":"Rue Sainte-anne 41 Waterloo Brabant Wallon 1410",
    "addr:housenumber":"41",
    "addr:postcode":"1410",
    "addr:street":"Rue Sainte-Anne",
    "iso:country":"BE",
    "sg:address":"Rue Sainte-anne 41",
    "sg:city":"Waterloo",
    "sg:orig_category":"Enseignement maternel and primaire",
    "sg:phone":"+32 2 354 70 38",
    "sg:postcode":"1410",
    "sg:province":"Brabant Wallon",
    "wof:name":"Ecole Fondamentale Libre",
    "wof:placetype":"venue"
},
  "geometry": {"coordinates":[4.4068198204,50.6967315674],"type":"Point"}
}