{
  "type": "Feature",
  "properties": {
    "addr:full":"Nijverheidsweg 4 Merelbeke Oost-Vlaanderen 9820",
    "addr:housenumber":"4",
    "addr:postcode":"9820",
    "addr:street":"Nijverheidsweg",
    "iso:country":"BE",
    "sg:address":"Nijverheidsweg 4",
    "sg:city":"Merelbeke",
    "sg:classifiers":[
        {
            "category":"Building & Trades",
            "subcategory":"Construction",
            "type":"Services"
        }
    ],
    "sg:phone":"+32 9 232 07 02",
    "sg:postcode":"9820",
    "sg:province":"Oost-Vlaanderen",
    "sg:tags":[
        "roofing",
        "material",
        "-"
    ],
    "wof:name":"D'hossche J.p.",
    "wof:placetype":"venue"
},
  "geometry": {"coordinates":[3.7337501049,51.0011482239],"type":"Point"}
}