{
  "type": "Feature",
  "properties": {
    "addr:full":"Rue De Custinne 100 Ciney Namur 5590",
    "addr:housenumber":"100",
    "addr:postcode":"5590",
    "addr:street":"Rue De Custinne",
    "iso:country":"BE",
    "sg:address":"Rue De Custinne 100",
    "sg:city":"Ciney",
    "sg:orig_category":"Tuinen",
    "sg:phone":"+32 83 21 56 81",
    "sg:postcode":"5590",
    "sg:province":"Namur",
    "wof:name":"Chabotier M.",
    "wof:placetype":"venue"
},
  "geometry": {"coordinates":[5.1022520065,50.297088623],"type":"Point"}
}