{
  "type": "Feature",
  "properties": {
    "iso:country":"BE",
    "sg:address":"Boulevard De La Sauveni\u00e8re 122",
    "sg:city":"Li\u00e8ge 1",
    "sg:classifiers":[
        {
            "category":"Travel",
            "subcategory":"Travel Agent",
            "type":"Entertainment"
        }
    ],
    "sg:phone":"+32 4 221 30 70",
    "sg:postcode":"4000",
    "sg:province":"Li\u00e8ge",
    "sg:tags":[
        "agency"
    ],
    "wof:name":"Altitudes",
    "wof:placetype":"venue"
},
  "geometry": {"coordinates":[5.5660219193,50.6420783997],"type":"Point"}
}