{
  "type": "Feature",
  "properties": {
    "addr:full":"Oude Antwerpsebaan 63b2 Mechelen Antwerpen 2800",
    "addr:housenumber":"63b2",
    "addr:postcode":"2800",
    "addr:street":"Oude Antwerpsebaan",
    "iso:country":"BE",
    "sg:address":"Oude Antwerpsebaan 63b2",
    "sg:city":"Mechelen",
    "sg:orig_category":"Sportclubs",
    "sg:phone":"+32 15 27 32 58",
    "sg:postcode":"2800",
    "sg:province":"Antwerpen",
    "wof:name":"W.c. B.m.x. Dennenteam",
    "wof:placetype":"venue"
},
  "geometry": {"coordinates":[4.4689722061,51.0410995483],"type":"Point"}
}