{
  "type": "Feature",
  "properties": {
    "iso:country":"BE",
    "sg:address":"Rue De France 43",
    "sg:city":"Rochefort",
    "sg:classifiers":[
        {
            "category":"Health Services",
            "subcategory":"Health Practitioner",
            "type":"Services"
        }
    ],
    "sg:phone":"+32 84 22 18 72",
    "sg:postcode":"5580",
    "sg:province":"Namur",
    "sg:tags":[
        "physiotherapist"
    ],
    "wof:name":"Delporte Vincent",
    "wof:placetype":"venue"
},
  "geometry": {"coordinates":[5.2193450928,50.1567802429],"type":"Point"}
}