{
  "type": "Feature",
  "properties": {
    "iso:country":"BE",
    "sg:address":"Rue Rogier 18",
    "sg:city":"Chimay",
    "sg:orig_category":"Pain, p\u00e2tisseries and confiseries",
    "sg:phone":"+32 60 21 15 35",
    "sg:postcode":"6460",
    "sg:province":"Hainaut",
    "wof:name":"Boulangerie Waschoor",
    "wof:placetype":"venue"
},
  "geometry": {"coordinates":[4.3170509338,50.0493278503],"type":"Point"}
}