{
  "type": "Feature",
  "properties": {
    "addr:full":"Rue De La Mutualit\u00c9 121 Ukkel Bruxelles-Capitale 1180",
    "addr:housenumber":"121",
    "addr:postcode":"1180",
    "addr:street":"Rue De La Mutualite\u0301",
    "iso:country":"BE",
    "sg:address":"Rue De La Mutualit\u00c9 121",
    "sg:city":"Ukkel",
    "sg:orig_category":"Agences d'exp\u00e9dition",
    "sg:phone":"+32 2 343 49 51",
    "sg:postcode":"1180",
    "sg:province":"Bruxelles-Capitale",
    "wof:name":"Yousif F",
    "wof:placetype":"venue"
},
  "geometry": {"coordinates":[4.3447809219,50.8113365173],"type":"Point"}
}