{
  "type": "Feature",
  "properties": {
    "addr:full":"Wolfstr 68 Alken Limburg 3570",
    "addr:housenumber":"68",
    "addr:postcode":"3570",
    "addr:street":"Wolfstr",
    "iso:country":"BE",
    "sg:address":"Wolfstr 68",
    "sg:city":"Alken",
    "sg:classifiers":[
        {
            "category":"Professional",
            "type":"Services"
        }
    ],
    "sg:phone":"+32 11 59 95 30",
    "sg:postcode":"3570",
    "sg:province":"Limburg",
    "sg:tags":[
        "transport",
        "road"
    ],
    "wof:name":"Penxten-mommen Nv",
    "wof:placetype":"venue"
},
  "geometry": {"coordinates":[5.2617301941,50.8672218323],"type":"Point"}
}