{
  "type": "Feature",
  "properties": {
    "iso:country":"BE",
    "sg:address":"Eigenlostraat 21",
    "sg:city":"Sint-niklaas",
    "sg:classifiers":[
        {
            "category":"Shopping",
            "subcategory":"Books",
            "type":"Retail Goods"
        }
    ],
    "sg:phone":"+32 3 780 62 62",
    "sg:postcode":"9100",
    "sg:province":"Oost-Vlaanderen",
    "sg:tags":[
        "bookseller"
    ],
    "wof:name":"Swets Blackwell Nv",
    "wof:placetype":"venue"
},
  "geometry": {"coordinates":[4.1829271317,51.1480484009],"type":"Point"}
}