{
  "type": "Feature",
  "properties": {
    "addr:full":"Avenue Des Traquets 23 Oudergem/auderghem Bruxelles-Capitale 1160",
    "addr:housenumber":"23",
    "addr:postcode":"1160",
    "addr:street":"Avenue Des Traquets;/",
    "iso:country":"BE",
    "sg:address":"Avenue Des Traquets 23",
    "sg:city":"Oudergem/auderghem",
    "sg:orig_category":"M\u00e9decins and sp\u00e9cialistes",
    "sg:phone":"+32 2 662 27 71",
    "sg:postcode":"1160",
    "sg:province":"Bruxelles-Capitale",
    "wof:name":"J.p. Desaedeleer",
    "wof:placetype":"venue"
},
  "geometry": {"coordinates":[4.4153199196,50.8205451965],"type":"Point"}
}