{
  "type": "Feature",
  "properties": {
    "iso:country":"BE",
    "sg:address":"Lepelstraat 125",
    "sg:city":"Lommel",
    "sg:orig_category":"Avocats and conseillers juridiques",
    "sg:phone":"+32 11 54 65 92",
    "sg:postcode":"3920",
    "sg:province":"Limburg",
    "wof:name":"Staf Van Den Brande",
    "wof:placetype":"venue"
},
  "geometry": {"coordinates":[5.3085598946,51.2342185974],"type":"Point"}
}