{
  "type": "Feature",
  "properties": {
    "addr:full":"Rue Saint-marcoult 2b02 Silly Hainaut 7830",
    "addr:housenumber":"2b02",
    "addr:postcode":"7830",
    "addr:street":"Rue Saint-Marcoult",
    "iso:country":"BE",
    "sg:address":"Rue Saint-marcoult 2b02",
    "sg:city":"Silly",
    "sg:classifiers":[
        {
            "category":"Insurance",
            "subcategory":"Insurance Agent",
            "type":"Services"
        }
    ],
    "sg:phone":"+32 68 55 13 30",
    "sg:postcode":"7830",
    "sg:province":"Hainaut",
    "sg:tags":[
        "verzekeringsmakelaars",
        "expert"
    ],
    "wof:name":"R. Loicq",
    "wof:placetype":"venue"
},
  "geometry": {"coordinates":[3.9302890301,50.6516227722],"type":"Point"}
}