{
  "type": "Feature",
  "properties": {
    "addr:full":"Kerkstraat 1 Sint-lievens-houtem Oost-Vlaanderen 9521",
    "addr:housenumber":"1",
    "addr:postcode":"9521",
    "addr:street":"Kerkstraat;Oost-Vlaanderen",
    "iso:country":"BE",
    "sg:address":"Kerkstraat 1",
    "sg:city":"Sint-lievens-houtem",
    "sg:orig_category":"Traitements param\u00e9dicaux",
    "sg:phone":"+32 53 62 26 87",
    "sg:postcode":"9521",
    "sg:province":"Oost-Vlaanderen",
    "wof:name":"P. Van Waeyenbergh",
    "wof:placetype":"venue"
},
  "geometry": {"coordinates":[3.881788969,50.9264183044],"type":"Point"}
}