{
  "type": "Feature",
  "properties": {
    "addr:full":"Reihagenstraat 17 Dendermonde (baasrode) Oost-Vlaanderen 9200",
    "addr:housenumber":"17",
    "addr:postcode":"9200",
    "addr:street":"Reihagenstraat",
    "iso:country":"BE",
    "sg:address":"Reihagenstraat 17",
    "sg:city":"Dendermonde (baasrode)",
    "sg:classifiers":[
        {
            "category":"Bars & Pubs",
            "type":"Food & Drink"
        }
    ],
    "sg:phone":"+32 52 39 99 80",
    "sg:postcode":"9200",
    "sg:province":"Oost-Vlaanderen",
    "wof:name":"Adec Sport",
    "wof:placetype":"venue"
},
  "geometry": {"coordinates":[4.0983099937,51.0315208435],"type":"Point"}
}