{
  "type": "Feature",
  "properties": {
    "iso:country":"BE",
    "sg:address":"Mechelse Plein 17",
    "sg:city":"Antwerpen",
    "sg:classifiers":[
        {
            "category":"Cafe",
            "type":"Food & Drink"
        }
    ],
    "sg:phone":"+32 3 231 24 69",
    "sg:postcode":"2000",
    "sg:province":"Antwerpen",
    "sg:tags":[
        "caf\u00e9s"
    ],
    "wof:name":"Caf\u00c9 Pallieterke",
    "wof:placetype":"venue"
},
  "geometry": {"coordinates":[4.4081530571,51.2101745605],"type":"Point"}
}