{
  "type": "Feature",
  "properties": {
    "iso:country":"BE",
    "sg:address":"Aarschotsesteenweg 65",
    "sg:city":"Leuven",
    "sg:orig_category":"Installation de menuiserie m\u00e9tallique",
    "sg:phone":"+32 16 44 55 39",
    "sg:postcode":"3012",
    "sg:province":"Vlaams-Brabant",
    "wof:name":"Werkhuizen Holemans",
    "wof:placetype":"venue"
},
  "geometry": {"coordinates":[4.7102861404,50.9033546448],"type":"Point"}
}