{
  "type": "Feature",
  "properties": {
    "iso:country":"BE",
    "sg:address":"Hoenderstraat 42",
    "sg:city":"Wetteren",
    "sg:classifiers":[
        {
            "category":"Bakery",
            "type":"Food & Drink"
        }
    ],
    "sg:phone":"+32 9 369 23 66",
    "sg:postcode":"9230",
    "sg:province":"Oost-Vlaanderen",
    "sg:tags":[
        "confectioner",
        "baker"
    ],
    "wof:name":"Bontinck Bvba",
    "wof:placetype":"venue"
},
  "geometry": {"coordinates":[3.8825180531,51.0039863586],"type":"Point"}
}