{
  "type": "Feature",
  "properties": {
    "addr:full":"Dirk Boutsstraat 10 Maaseik Limburg 3680",
    "addr:housenumber":"10",
    "addr:postcode":"3680",
    "addr:street":"Dirk Boutsstraat",
    "iso:country":"BE",
    "sg:address":"Dirk Boutsstraat 10",
    "sg:city":"Maaseik",
    "sg:classifiers":[
        {
            "category":"Social Services",
            "type":"Services"
        }
    ],
    "sg:phone":"+32 89 56 53 31",
    "sg:postcode":"3680",
    "sg:province":"Limburg",
    "wof:name":"Home Relindis",
    "wof:placetype":"venue"
},
  "geometry": {"coordinates":[5.7944931984,51.0994949341],"type":"Point"}
}