{
  "type": "Feature",
  "properties": {
    "iso:country":"BE",
    "sg:address":"Dorpsstraat 64be/3",
    "sg:city":"Heist-op-den-berg",
    "sg:orig_category":"Boekhouders",
    "sg:phone":"+32 15 25 15 98",
    "sg:postcode":"2221",
    "sg:province":"Antwerpen",
    "wof:name":"Jan De Haes",
    "wof:placetype":"venue"
},
  "geometry": {"coordinates":[4.7739758492,51.0512428284],"type":"Point"}
}