{
  "type": "Feature",
  "properties": {
    "addr:full":"Rue De Magn\u00e9e 49 Fl\u00e9ron Li\u00e8ge 4620",
    "addr:housenumber":"49",
    "addr:postcode":"4620",
    "addr:street":"Rue De Magne\u0301E",
    "iso:country":"BE",
    "sg:address":"Rue De Magn\u00e9e 49",
    "sg:city":"Fl\u00e9ron",
    "sg:classifiers":[
        {
            "category":"Bakery",
            "type":"Food & Drink"
        }
    ],
    "sg:phone":"+32 4 358 94 86",
    "sg:postcode":"4620",
    "sg:province":"Li\u00e8ge",
    "sg:tags":[
        "confectioner",
        "baker"
    ],
    "wof:name":"Gourmandine (la)",
    "wof:placetype":"venue"
},
  "geometry": {"coordinates":[5.6820287704,50.6132621765],"type":"Point"}
}