{
  "type": "Feature",
  "properties": {
    "addr:full":"Kempstraat 94 Gent Oost-Vlaanderen 9000",
    "addr:housenumber":"94",
    "addr:postcode":"9000",
    "addr:street":"Kempstraat;Oost-Vlaanderen",
    "iso:country":"BE",
    "sg:address":"Kempstraat 94",
    "sg:city":"Gent",
    "sg:classifiers":[
        {
            "category":"Communications",
            "type":"Services"
        }
    ],
    "sg:phone":"+32 9 236 68 50",
    "sg:postcode":"9000",
    "sg:province":"Oost-Vlaanderen",
    "sg:tags":[
        "translator"
    ],
    "wof:name":"Valaskova J",
    "wof:placetype":"venue"
},
  "geometry": {"coordinates":[3.6913371086,51.0681800842],"type":"Point"}
}