{
  "type": "Feature",
  "properties": {
    "iso:country":"BE",
    "sg:address":"Leuvensesteenweg 223a",
    "sg:city":"Beernem",
    "sg:classifiers":[
        {
            "category":"Arena",
            "subcategory":"Sports Club",
            "type":"Entertainment"
        }
    ],
    "sg:phone":"+32 16 63 24 28",
    "sg:postcode":"3390",
    "sg:province":"Vlaams-Brabant",
    "sg:tags":[
        "de"
    ],
    "wof:name":"Sc Willempie - Vrienden - Lubbeek",
    "wof:placetype":"venue"
},
  "geometry": {"coordinates":[4.9038281441,50.9413642883],"type":"Point"}
}