{
  "type": "Feature",
  "properties": {
    "addr:full":"Burgemeester Bertenplein 12 Poperinge West-Vlaanderen 8970",
    "addr:housenumber":"12",
    "addr:postcode":"8970",
    "addr:street":"Burgemeester Bertenplein",
    "iso:country":"BE",
    "sg:address":"Burgemeester Bertenplein 12",
    "sg:city":"Poperinge",
    "sg:orig_category":"Secr\u00e9tariats sociaux",
    "sg:phone":"+32 57 33 32 96",
    "sg:postcode":"8970",
    "sg:province":"West-Vlaanderen",
    "wof:name":"Admb",
    "wof:placetype":"venue"
},
  "geometry": {"coordinates":[2.7254910469,50.8539047241],"type":"Point"}
}