{
  "type": "Feature",
  "properties": {
    "addr:full":"Place Villers-st.-amand 16 Ath Hainaut 7812",
    "addr:housenumber":"16",
    "addr:postcode":"7812",
    "addr:street":"Place Villers-St.-Amand",
    "iso:country":"BE",
    "sg:address":"Place Villers-st.-amand 16",
    "sg:city":"Ath",
    "sg:classifiers":[
        {
            "category":"Insurance",
            "subcategory":"Insurance Agent",
            "type":"Services"
        }
    ],
    "sg:phone":"+32 68 28 31 85",
    "sg:postcode":"7812",
    "sg:province":"Hainaut",
    "sg:tags":[
        "verzekeringsmakelaars",
        "expert"
    ],
    "wof:name":"Vandemeulebroecke",
    "wof:placetype":"venue"
},
  "geometry": {"coordinates":[3.7299630642,50.6218299866],"type":"Point"}
}