{
  "type": "Feature",
  "properties": {
    "addr:full":"Route De Mons 192 Quaregnon Hainaut 7390",
    "addr:housenumber":"192",
    "addr:postcode":"7390",
    "addr:street":"Route De Mons",
    "iso:country":"BE",
    "sg:address":"Route De Mons 192",
    "sg:city":"Quaregnon",
    "sg:orig_category":"V\u00e9hicules automobiles. Entretien and r\u00e9parations de voitures",
    "sg:phone":"+32 65 78 36 71",
    "sg:postcode":"7390",
    "sg:province":"Hainaut",
    "wof:name":"Garage Mac Motor",
    "wof:placetype":"venue"
},
  "geometry": {"coordinates":[3.8463981152,50.4404335022],"type":"Point"}
}