{
  "type": "Feature",
  "properties": {
    "iso:country":"BE",
    "sg:address":"Rue Tielemans 2",
    "sg:city":"Brussel/bruxelles",
    "sg:orig_category":"Mat\u00e9riel pour plomberie and chauffage Quincailleries. Mat\u00e9riaux de construction Gr",
    "sg:phone":"+32 2 428 11 80",
    "sg:postcode":"1020",
    "sg:province":"Bruxelles-Capitale",
    "wof:name":"Facq",
    "wof:placetype":"venue"
},
  "geometry": {"coordinates":[4.3476500511,50.8751716614],"type":"Point"}
}