{
  "type": "Feature",
  "properties": {
    "addr:full":"Poverstraat 2 Asse Vlaams-Brabant 1731",
    "addr:housenumber":"2",
    "addr:postcode":"1731",
    "addr:street":"Poverstraat",
    "iso:country":"BE",
    "sg:address":"Poverstraat 2",
    "sg:city":"Asse",
    "sg:orig_category":"Groenten and fruit Gh",
    "sg:phone":"+32 2 460 59 52",
    "sg:postcode":"1731",
    "sg:province":"Vlaams-Brabant",
    "wof:name":"Nicolas Roelandts",
    "wof:placetype":"venue"
},
  "geometry": {"coordinates":[4.2772359848,50.8989143372],"type":"Point"}
}