{
  "type": "Feature",
  "properties": {
    "iso:country":"BE",
    "sg:address":"Archimedeslaan 38",
    "sg:city":"Edegem",
    "sg:orig_category":"Architectes",
    "sg:phone":"+32 3 457 49 31",
    "sg:postcode":"2650",
    "sg:province":"Antwerpen",
    "wof:name":"Didier Neyrinck",
    "wof:placetype":"venue"
},
  "geometry": {"coordinates":[4.4414739609,51.1510314941],"type":"Point"}
}