{
  "type": "Feature",
  "properties": {
    "addr:full":"Chauss\u00c9e De Charleroi 143 Sint-gillis/saint-gilles Bruxelles-Capitale 1060",
    "addr:housenumber":"143",
    "addr:postcode":"1060",
    "addr:street":"Chausse\u0301E De Charleroi",
    "iso:country":"BE",
    "sg:address":"Chauss\u00c9e De Charleroi 143",
    "sg:city":"Sint-gillis/saint-gilles",
    "sg:orig_category":"Avocats and conseillers juridiques",
    "sg:phone":"+32 2 534 07 21",
    "sg:postcode":"1060",
    "sg:province":"Bruxelles-Capitale",
    "wof:name":"Sylvie Th\u00c9ron",
    "wof:placetype":"venue"
},
  "geometry": {"coordinates":[4.3550639153,50.8279533386],"type":"Point"}
}