{
  "type": "Feature",
  "properties": {
    "iso:country":"BE",
    "sg:address":"Lusambostraat 76",
    "sg:city":"Brussel",
    "sg:classifiers":[
        {
            "category":"Shopping Center",
            "type":"Public Place"
        }
    ],
    "sg:phone":"+32 2 332 29 00",
    "sg:postcode":"1190",
    "sg:province":"Bruxelles-Capitale",
    "sg:tags":[
        "aluminium",
        "section"
    ],
    "wof:name":"Alcan Belgium Nv",
    "wof:placetype":"venue"
},
  "geometry": {"coordinates":[4.3119001389,50.800868988],"type":"Point"}
}