{
  "type": "Feature",
  "properties": {
    "addr:full":"Melkerijstraat 49 Wommelgem Antwerpen 2160",
    "addr:housenumber":"49",
    "addr:postcode":"2160",
    "addr:street":"Melkerijstraat",
    "iso:country":"BE",
    "sg:address":"Melkerijstraat 49",
    "sg:city":"Wommelgem",
    "sg:orig_category":"Entretien and r\u00e9parations de voitures",
    "sg:phone":"+32 3 353 76 50",
    "sg:postcode":"2160",
    "sg:province":"Antwerpen",
    "wof:name":"Garage Schalbroeck",
    "wof:placetype":"venue"
},
  "geometry": {"coordinates":[4.5245761871,51.1988601685],"type":"Point"}
}