{
  "type": "Feature",
  "properties": {
    "iso:country":"BE",
    "sg:address":"Speelstraat 24",
    "sg:city":"Zingem",
    "sg:classifiers":[
        {
            "category":"Freight",
            "type":"Transportation"
        }
    ],
    "sg:phone":"+32 9 384 20 08",
    "sg:postcode":"9750",
    "sg:province":"Oost-Vlaanderen",
    "sg:tags":[
        "-",
        "transport"
    ],
    "wof:name":"Gincotrans Bvba",
    "wof:placetype":"venue"
},
  "geometry": {"coordinates":[3.664951086,50.8973121643],"type":"Point"}
}