{
  "type": "Feature",
  "properties": {
    "addr:full":"Enclos Tesni\u00c8re 1 Neupre Li\u00e8ge 4122",
    "addr:housenumber":"1",
    "addr:postcode":"4122",
    "addr:street":"Enclos Tesnie\u0300Re",
    "iso:country":"BE",
    "sg:address":"Enclos Tesni\u00c8re 1",
    "sg:city":"Neupre",
    "sg:orig_category":"Organisations and associations. Services pour animaux domestiques",
    "sg:phone":"+32 4 371 43 21",
    "sg:postcode":"4122",
    "sg:province":"Li\u00e8ge",
    "wof:name":"Animal Sans Logis",
    "wof:placetype":"venue"
},
  "geometry": {"coordinates":[5.5163421631,50.5403442383],"type":"Point"}
}