{
  "type": "Feature",
  "properties": {
    "iso:country":"BE",
    "sg:address":"Oostereindestraat 87",
    "sg:city":"Lummen",
    "sg:classifiers":[
        {
            "category":"Health Services",
            "subcategory":"Health Practitioner",
            "type":"Services"
        }
    ],
    "sg:phone":"+32 13 53 27 08",
    "sg:postcode":"3560",
    "sg:province":"Limburg",
    "sg:tags":[
        "therapist",
        "speech"
    ],
    "wof:name":"Praktijk Voor Stottertherapie",
    "wof:placetype":"venue"
},
  "geometry": {"coordinates":[5.2036170959,50.9896697998],"type":"Point"}
}