{
  "type": "Feature",
  "properties": {
    "addr:full":"Schuttersstraat 10 Beringen Limburg 3580",
    "addr:housenumber":"10",
    "addr:postcode":"3580",
    "addr:street":"Schuttersstraat",
    "iso:country":"BE",
    "sg:address":"Schuttersstraat 10",
    "sg:city":"Beringen",
    "sg:classifiers":[
        {
            "category":"Arena",
            "subcategory":"Sports Club",
            "type":"Entertainment"
        }
    ],
    "sg:phone":"+32 11 42 16 91",
    "sg:postcode":"3580",
    "sg:province":"Limburg",
    "sg:tags":[
        "terrain",
        "hors",
        "de",
        "installation",
        "sportifs"
    ],
    "wof:name":"R.k. Golling",
    "wof:placetype":"venue"
},
  "geometry": {"coordinates":[5.2325258255,51.0507202148],"type":"Point"}
}