{
  "type": "Feature",
  "properties": {
    "addr:full":"Route Nationale-4 45 Nassogne Luxembourg 6951",
    "addr:housenumber":"45",
    "addr:postcode":"6951",
    "addr:street":"Route Nationale-4",
    "iso:country":"BE",
    "sg:address":"Route Nationale-4 45",
    "sg:city":"Nassogne",
    "sg:classifiers":[
        {
            "category":"Fast Food",
            "type":"Food & Drink"
        }
    ],
    "sg:phone":"+32 84 34 41 65",
    "sg:postcode":"6951",
    "sg:province":"Luxembourg",
    "sg:tags":[
        "huis",
        "aan",
        "levering",
        "meeneem",
        "restaurant"
    ],
    "wof:name":"L'auberge Ardennaise",
    "wof:placetype":"venue"
},
  "geometry": {"coordinates":[5.4151701927,50.1667518616],"type":"Point"}
}