{
  "type": "Feature",
  "properties": {
    "iso:country":"BE",
    "sg:address":"Sint-amandsstraat 16 Box 1",
    "sg:city":"Grimbergen (strombeek-bever)",
    "sg:orig_category":"Solariums",
    "sg:phone":"+32 2 261 14 04",
    "sg:postcode":"1853",
    "sg:province":"Vlaams-Brabant",
    "wof:name":"Go Sun",
    "wof:placetype":"venue"
},
  "geometry": {"coordinates":[4.357460022,50.9092903137],"type":"Point"}
}