{
  "type": "Feature",
  "properties": {
    "iso:country":"BE",
    "sg:address":"Bergstr 13",
    "sg:city":"Heist",
    "sg:classifiers":[
        {
            "category":"Banks & Credit Unions",
            "subcategory":"Bank",
            "type":"Services"
        }
    ],
    "sg:phone":"+32 15 24 44 61",
    "sg:postcode":"3100",
    "wof:name":"Aslk-cger Bank",
    "wof:placetype":"venue"
},
  "geometry": {"coordinates":[15.6157693863,48.2139549255],"type":"Point"}
}