{
  "type": "Feature",
  "properties": {
    "iso:country":"BE",
    "sg:address":"Steenweg Op Turnhout 4",
    "sg:city":"Merksplas",
    "sg:classifiers":[
        {
            "category":"Shopping",
            "subcategory":"Clothing, Apparel, & Fashions",
            "type":"Retail Goods"
        }
    ],
    "sg:phone":"+32 14 63 49 90",
    "sg:postcode":"2330",
    "sg:province":"Antwerpen",
    "sg:tags":[
        "v\u00eatements",
        "pour",
        "dame"
    ],
    "wof:name":"Huis Papaja",
    "wof:placetype":"venue"
},
  "geometry": {"coordinates":[4.8646521568,51.3537864685],"type":"Point"}
}