{
  "type": "Feature",
  "properties": {
    "addr:full":"Rue De La Ferme 88 Bruxelles (saint-josse-ten-noode) Bruxelles-Capitale 1210",
    "addr:housenumber":"88",
    "addr:postcode":"1210",
    "addr:street":"Rue De La Ferme",
    "iso:country":"BE",
    "sg:address":"Rue De La Ferme 88",
    "sg:city":"Bruxelles (saint-josse-ten-noode)",
    "sg:classifiers":[
        {
            "category":"Freight",
            "type":"Transportation"
        }
    ],
    "sg:phone":"+32 2 217 46 73",
    "sg:postcode":"1210",
    "sg:province":"Bruxelles-Capitale",
    "sg:tags":[
        "-",
        "transport"
    ],
    "wof:name":"Trans Loverd\u00e9",
    "wof:placetype":"venue"
},
  "geometry": {"coordinates":[4.3772759438,50.8520126343],"type":"Point"}
}