{
  "type": "Feature",
  "properties": {
    "iso:country":"BE",
    "sg:address":"Kwadeweg 24",
    "sg:city":"Oudenburg",
    "sg:orig_category":"Rundveehouders Varkenskwekers",
    "sg:phone":"+32 59 23 54 31",
    "sg:postcode":"8460",
    "sg:province":"West-Vlaanderen",
    "wof:name":"Rudy Van Raemdonck",
    "wof:placetype":"venue"
},
  "geometry": {"coordinates":[3.0216100216,51.2195701599],"type":"Point"}
}