{
  "type": "Feature",
  "properties": {
    "iso:country":"BE",
    "sg:address":"Rue De La Roche 59",
    "sg:city":"Hotton (hampteau)",
    "sg:classifiers":[
        {
            "category":"Shopping",
            "subcategory":"Bicycles & Sporting Goods",
            "type":"Retail Goods"
        }
    ],
    "sg:phone":"+32 84 46 63 52",
    "sg:postcode":"6990",
    "sg:province":"Luxembourg",
    "sg:tags":[
        "tyre"
    ],
    "wof:name":"Tout Pneu",
    "wof:placetype":"venue"
},
  "geometry": {"coordinates":[5.473528862,50.2573471069],"type":"Point"}
}