{
  "type": "Feature",
  "properties": {
    "iso:country":"BE",
    "sg:address":"Place Henry-de-la-lindi 22",
    "sg:city":"Vresse-sur-semois",
    "sg:classifiers":[
        {
            "category":"Restaurant",
            "type":"Food & Drink"
        }
    ],
    "sg:phone":"+32 61 50 16 76",
    "sg:postcode":"5550",
    "sg:province":"Namur",
    "wof:name":"Glacier Le Chantilly",
    "wof:placetype":"venue"
},
  "geometry": {"coordinates":[4.9336900711,49.8729820251],"type":"Point"}
}