{
  "type": "Feature",
  "properties": {
    "addr:full":"Madrasstraat 5 Antwerpen Antwerpen 2030",
    "addr:housenumber":"5",
    "addr:postcode":"2030",
    "addr:street":"Madrasstraat",
    "iso:country":"BE",
    "sg:address":"Madrasstraat 5",
    "sg:city":"Antwerpen",
    "sg:classifiers":[
        {
            "category":"Utilities",
            "type":"Services"
        }
    ],
    "sg:phone":"+32 3 231 36 36",
    "sg:postcode":"2030",
    "sg:province":"Antwerpen",
    "sg:tags":[
        "raw",
        "energy",
        "material"
    ],
    "wof:name":"De Wit Ch Nv",
    "wof:placetype":"venue"
},
  "geometry": {"coordinates":[4.4110789299,51.2356033325],"type":"Point"}
}