{
  "type": "Feature",
  "properties": {
    "addr:full":"Rue Haudion 22 Tournai Hainaut 7522",
    "addr:housenumber":"22",
    "addr:postcode":"7522",
    "addr:street":"Rue Haudion",
    "iso:country":"BE",
    "sg:address":"Rue Haudion 22",
    "sg:city":"Tournai",
    "sg:orig_category":"Secretariaatsdiensten",
    "sg:phone":"+32 69 84 05 53",
    "sg:postcode":"7522",
    "sg:province":"Hainaut",
    "wof:name":"Agence Trapeze",
    "wof:placetype":"venue"
},
  "geometry": {"coordinates":[3.3198740482,50.6291007996],"type":"Point"}
}