{
  "type": "Feature",
  "properties": {
    "addr:full":"Luythegge 14 Meeuwen-gruitrode Limburg 3670",
    "addr:housenumber":"14",
    "addr:postcode":"3670",
    "addr:street":"Luythegge",
    "iso:country":"BE",
    "sg:address":"Luythegge 14",
    "sg:city":"Meeuwen-gruitrode",
    "sg:orig_category":"Installation de menuiserie en bois and plastique",
    "sg:phone":"+32 11 79 19 15",
    "sg:postcode":"3670",
    "sg:province":"Limburg",
    "wof:name":"Rudi Schoofs",
    "wof:placetype":"venue"
},
  "geometry": {"coordinates":[5.5108962059,51.1122817993],"type":"Point"}
}