{
  "type": "Feature",
  "properties": {
    "iso:country":"BE",
    "sg:address":"Chauss\u00e9e D'herseaux 39",
    "sg:city":"Estaimpuis",
    "sg:classifiers":[
        {
            "category":"Building & Trades",
            "subcategory":"Pest Control",
            "type":"Services"
        }
    ],
    "sg:phone":"+32 56 48 98 89",
    "sg:postcode":"7730",
    "sg:province":"Hainaut",
    "sg:tags":[
        "painting",
        "contractor"
    ],
    "wof:name":"Lepers J M",
    "wof:placetype":"venue"
},
  "geometry": {"coordinates":[3.2644560337,50.7159843445],"type":"Point"}
}