{
  "type": "Feature",
  "properties": {
    "addr:full":"Stationsstraat 32 Zwevegem 8552",
    "addr:housenumber":"32",
    "addr:postcode":"8552",
    "addr:street":"Stationsstraat",
    "iso:country":"BE",
    "sg:address":"Stationsstraat 32",
    "sg:city":"Zwevegem",
    "sg:orig_category":"Forge, Moulage and Profilage des M\u00e9taux",
    "sg:phone":"+32 56 64 77 96",
    "sg:postcode":"8552",
    "wof:name":"Libberecht Dirck",
    "wof:placetype":"venue"
},
  "geometry": {"coordinates":[3.3966441154,50.7720031738],"type":"Point"}
}