{
  "type": "Feature",
  "properties": {
    "iso:country":"BE",
    "sg:address":"Rue De Linthout 93",
    "sg:city":"Schaarbeek/schaerbeek",
    "sg:orig_category":"M\u00e9decins and sp\u00e9cialistes",
    "sg:phone":"+32 2 736 38 49",
    "sg:postcode":"1030",
    "sg:province":"Bruxelles-Capitale",
    "wof:name":"Michel Vanhalewyn",
    "wof:placetype":"venue"
},
  "geometry": {"coordinates":[4.3999700546,50.8438835144],"type":"Point"}
}