{
  "type": "Feature",
  "properties": {
    "iso:country":"BE",
    "sg:address":"Avenue Paul Terlinden 23",
    "sg:city":"Rixensart",
    "sg:classifiers":[
        {
            "category":"Community Center",
            "subcategory":"Youth",
            "type":"Public Place"
        }
    ],
    "sg:phone":"+32 2 653 82 68",
    "sg:postcode":"1330",
    "sg:province":"Brabant Wallon",
    "sg:tags":[
        "club"
    ],
    "wof:name":"Archeolo J",
    "wof:placetype":"venue"
},
  "geometry": {"coordinates":[4.5335860252,50.7131004333],"type":"Point"}
}