{
  "type": "Feature",
  "properties": {
    "addr:full":"Pellaarstraat 30 Lille Antwerpen 2275",
    "addr:housenumber":"30",
    "addr:postcode":"2275",
    "addr:street":"Pellaarstraat",
    "iso:country":"BE",
    "sg:address":"Pellaarstraat 30",
    "sg:city":"Lille",
    "sg:orig_category":"Elektrische installaties voor woningen",
    "sg:phone":"+32 14 55 77 97",
    "sg:postcode":"2275",
    "sg:province":"Antwerpen",
    "wof:name":"Robert Geudens",
    "wof:placetype":"venue"
},
  "geometry": {"coordinates":[4.868461132,51.2774581909],"type":"Point"}
}