{
  "type": "Feature",
  "properties": {
    "addr:full":"J.-b. Vanp\u00c9straat 56 Vorst/forest Bruxelles-Capitale 1190",
    "addr:housenumber":"56",
    "addr:postcode":"1190",
    "addr:street":"J.-B. Vanpe\u0301Straat;/ Forest",
    "iso:country":"BE",
    "sg:address":"J.-b. Vanp\u00c9straat 56",
    "sg:city":"Vorst/forest",
    "sg:classifiers":[
        {
            "category":"Restaurant",
            "type":"Food & Drink"
        }
    ],
    "sg:phone":"+32 2 332 19 98",
    "sg:postcode":"1190",
    "sg:province":"Bruxelles-Capitale",
    "sg:tags":[
        "organisatie",
        "feesten",
        "van",
        "catering"
    ],
    "wof:name":"C\u00b4era Una Volta Da Mimmo",
    "wof:placetype":"venue"
},
  "geometry": {"coordinates":[4.3193898201,50.8096542358],"type":"Point"}
}