{
  "type": "Feature",
  "properties": {
    "iso:country":"BE",
    "sg:address":"Pannestraat 86",
    "sg:city":"Veurne",
    "sg:classifiers":[
        {
            "category":"Food & Beverages",
            "subcategory":"Fruits & Vegetables",
            "type":"Retail Goods"
        }
    ],
    "sg:phone":"+32 58 31 59 56",
    "sg:postcode":"8630",
    "sg:province":"West-Vlaanderen",
    "sg:tags":[
        "l\u00e9gumes"
    ],
    "wof:name":"Luc Debacker",
    "wof:placetype":"venue"
},
  "geometry": {"coordinates":[2.6568899155,51.0752182007],"type":"Point"}
}