{
  "type": "Feature",
  "properties": {
    "iso:country":"BE",
    "sg:address":"Koning Albert I Straat 121a",
    "sg:city":"Lebbeke",
    "sg:classifiers":[
        {
            "category":"Airport",
            "subcategory":"International",
            "type":"Transportation"
        }
    ],
    "sg:phone":"+32 52 41 53 73",
    "sg:postcode":"9280",
    "sg:province":"Oost-Vlaanderen",
    "sg:tags":[
        "-",
        "transport"
    ],
    "wof:name":"Devotrans Bvba",
    "wof:placetype":"venue"
},
  "geometry": {"coordinates":[4.1390428543,50.9982948303],"type":"Point"}
}