{
  "type": "Feature",
  "properties": {
    "addr:full":"Buitenstraat 40 De Klinge Oost-Vlaanderen 9170",
    "addr:housenumber":"40",
    "addr:postcode":"9170",
    "addr:street":"Buitenstraat;De Klinge Oost-Vlaanderen",
    "iso:country":"BE",
    "sg:address":"Buitenstraat 40",
    "sg:city":"De Klinge",
    "sg:orig_category":"Huisdieren and benodigdheden Royal Canin",
    "sg:phone":"+32 3 707 06 85",
    "sg:postcode":"9170",
    "sg:province":"Oost-Vlaanderen",
    "wof:name":"Toisy",
    "wof:placetype":"venue"
},
  "geometry": {"coordinates":[4.1255750656,51.2189941406],"type":"Point"}
}