{
  "type": "Feature",
  "properties": {
    "iso:country":"BE",
    "sg:address":"Hauwaart 88",
    "sg:city":"Oudenaarde (mater)",
    "sg:classifiers":[
        {
            "category":"Food & Beverages",
            "subcategory":"Fruits & Vegetables",
            "type":"Retail Goods"
        }
    ],
    "sg:phone":"+32 55 45 65 52",
    "sg:postcode":"9700",
    "sg:province":"Oost-Vlaanderen",
    "sg:tags":[
        "-"
    ],
    "wof:name":"Mdm Fruitpoort",
    "wof:placetype":"venue"
},
  "geometry": {"coordinates":[3.677628994,50.8308448792],"type":"Point"}
}