{
  "type": "Feature",
  "properties": {
    "addr:full":"Grote Ieperstraat 11 Wevelgem West-Vlaanderen 8560",
    "addr:housenumber":"11",
    "addr:postcode":"8560",
    "addr:street":"Grote Ieperstraat",
    "iso:country":"BE",
    "sg:address":"Grote Ieperstraat 11",
    "sg:city":"Wevelgem",
    "sg:orig_category":"Entretien and r\u00e9parations de machines de bureau and ordinateurs. Services de Nettoyage and de D\u00e9sinf",
    "sg:phone":"+32 56 41 00 30",
    "sg:postcode":"8560",
    "sg:province":"West-Vlaanderen",
    "wof:name":"Geldhof N",
    "wof:placetype":"venue"
},
  "geometry": {"coordinates":[3.2072429657,50.8355293274],"type":"Point"}
}