{
  "type": "Feature",
  "properties": {
    "addr:full":"Rue De L'arbre B\u00c9nit 129 Elsene/ixelles Bruxelles-Capitale 1050",
    "addr:housenumber":"129",
    "addr:postcode":"1050",
    "addr:street":"Rue De L'Arbre Be\u0301Nit",
    "iso:country":"BE",
    "sg:address":"Rue De L'arbre B\u00c9nit 129",
    "sg:city":"Elsene/ixelles",
    "sg:orig_category":"Artistes ind\u00e9pendants",
    "sg:phone":"+32 2 647 47 26",
    "sg:postcode":"1050",
    "sg:province":"Bruxelles-Capitale",
    "wof:name":"A. Gomila Solar",
    "wof:placetype":"venue"
},
  "geometry": {"coordinates":[4.3638682365,50.8302383423],"type":"Point"}
}