{
  "type": "Feature",
  "properties": {
    "addr:full":"Rue Mellery 54 Bruxelles Bruxelles-Capitale 1020",
    "addr:housenumber":"54",
    "addr:postcode":"1020",
    "addr:street":"Rue Mellery",
    "iso:country":"BE",
    "sg:address":"Rue Mellery 54",
    "sg:city":"Bruxelles",
    "sg:orig_category":"Farmaceutische producten Gh",
    "sg:phone":"+32 2 474 03 30",
    "sg:postcode":"1020",
    "sg:province":"Bruxelles-Capitale",
    "wof:name":"Orthogese",
    "wof:placetype":"venue"
},
  "geometry": {"coordinates":[4.3581237793,50.8805198669],"type":"Point"}
}