{
  "type": "Feature",
  "properties": {
    "iso:country":"BE",
    "sg:address":"Zavelweg 29",
    "sg:city":"Willebroek",
    "sg:classifiers":[
        {
            "category":"Building & Trades",
            "subcategory":"Construction",
            "type":"Services"
        }
    ],
    "sg:phone":"+32 3 866 04 60",
    "sg:postcode":"2830",
    "sg:province":"Antwerpen",
    "sg:tags":[
        "ceiling"
    ],
    "wof:name":"Reyntiens R",
    "wof:placetype":"venue"
},
  "geometry": {"coordinates":[4.3584017754,51.0675086975],"type":"Point"}
}