{
  "type": "Feature",
  "properties": {
    "addr:full":"Dorpsstraat 18 Beveren (kieldrecht) Oost-Vlaanderen 9130",
    "addr:housenumber":"18",
    "addr:postcode":"9130",
    "addr:street":"Dorpsstraat",
    "iso:country":"BE",
    "sg:address":"Dorpsstraat 18",
    "sg:city":"Beveren (kieldrecht)",
    "sg:classifiers":[
        {
            "category":"Banks & Credit Unions",
            "subcategory":"Investment Brokerage",
            "type":"Services"
        }
    ],
    "sg:phone":"+32 3 773 40 51",
    "sg:postcode":"9130",
    "sg:province":"Oost-Vlaanderen",
    "sg:tags":[
        "printing",
        "-"
    ],
    "wof:name":"Cleiren A",
    "wof:placetype":"venue"
},
  "geometry": {"coordinates":[4.1751790047,51.2901268005],"type":"Point"}
}