{
  "type": "Feature",
  "properties": {
    "addr:full":"Paradis 34 Ellezelles (wodecq) Hainaut 7890",
    "addr:housenumber":"34",
    "addr:postcode":"7890",
    "addr:street":"Paradis",
    "iso:country":"BE",
    "sg:address":"Paradis 34",
    "sg:city":"Ellezelles (wodecq)",
    "sg:classifiers":[
        {
            "category":"Personal",
            "subcategory":"Shoe Repair & Shine",
            "type":"Services"
        }
    ],
    "sg:phone":"+32 68 54 23 82",
    "sg:postcode":"7890",
    "sg:province":"Hainaut",
    "sg:tags":[
        "shoemaker"
    ],
    "wof:name":"Cambier H",
    "wof:placetype":"venue"
},
  "geometry": {"coordinates":[3.7064659595,50.7347679138],"type":"Point"}
}