{
  "type": "Feature",
  "properties": {
    "addr:full":"Grote Doelstraat 1ba Bonheiden Antwerpen 2820",
    "addr:housenumber":"1ba",
    "addr:postcode":"2820",
    "addr:street":"Grote Doelstraat",
    "iso:country":"BE",
    "sg:address":"Grote Doelstraat 1ba",
    "sg:city":"Bonheiden",
    "sg:classifiers":[
        {
            "category":"Cafe",
            "type":"Food & Drink"
        }
    ],
    "sg:phone":"+32 15 52 84 73",
    "sg:postcode":"2820",
    "sg:province":"Antwerpen",
    "sg:tags":[
        "caf\u00e9s"
    ],
    "wof:name":"Olympia",
    "wof:placetype":"venue"
},
  "geometry": {"coordinates":[4.556139946,51.0260696411],"type":"Point"}
}