{
  "type": "Feature",
  "properties": {
    "addr:full":"Duinhoekstraat 9 De Panne West-Vlaanderen 8660",
    "addr:housenumber":"9",
    "addr:postcode":"8660",
    "addr:street":"Duinhoekstraat",
    "iso:country":"BE",
    "sg:address":"Duinhoekstraat 9",
    "sg:city":"De Panne",
    "sg:orig_category":"Supermarch\u00e9s",
    "sg:phone":"+32 58 41 20 04",
    "sg:postcode":"8660",
    "sg:province":"West-Vlaanderen",
    "wof:name":"Ad Delhaize",
    "wof:placetype":"venue"
},
  "geometry": {"coordinates":[2.5983929634,51.084854126],"type":"Point"}
}