{
  "type": "Feature",
  "properties": {
    "addr:full":"6 P.i. Chaineux Li\u00e8ge 4650",
    "addr:postcode":"4650",
    "addr:street":"P.I. Chaineux",
    "iso:country":"BE",
    "sg:address":"6 P.i.",
    "sg:city":"Chaineux",
    "sg:classifiers":[
        {
            "category":"Professional",
            "type":"Services"
        }
    ],
    "sg:phone":"+32 87 31 31 87",
    "sg:postcode":"4650",
    "sg:province":"Li\u00e8ge",
    "sg:tags":[
        "transport",
        "road"
    ],
    "wof:name":"Transport Wertz",
    "wof:placetype":"venue"
},
  "geometry": {"coordinates":[5.7943401337,50.6393814087],"type":"Point"}
}