{
  "type": "Feature",
  "properties": {
    "iso:country":"BE",
    "sg:address":"Hulleken 29",
    "sg:city":"Evergem",
    "sg:orig_category":"Entretien and r\u00e9parations de voitures. V\u00e9hicules automobiles",
    "sg:phone":"+32 9 357 66 33",
    "sg:postcode":"9940",
    "sg:province":"Oost-Vlaanderen",
    "wof:name":"Garage Bauwens",
    "wof:placetype":"venue"
},
  "geometry": {"coordinates":[3.6850430965,51.1176300049],"type":"Point"}
}