{
  "type": "Feature",
  "properties": {
    "addr:full":"Avenue Du Centenaire 274 Charleroi (montignies-sur-sambre) Hainaut 6061",
    "addr:housenumber":"274",
    "addr:postcode":"6061",
    "addr:street":"Avenue Du Centenaire",
    "iso:country":"BE",
    "sg:address":"Avenue Du Centenaire 274",
    "sg:city":"Charleroi (montignies-sur-sambre)",
    "sg:classifiers":[
        {
            "category":"Retail",
            "subcategory":"Auto Repair",
            "type":"Services"
        }
    ],
    "sg:phone":"+32 71 32 23 52",
    "sg:postcode":"6061",
    "sg:province":"Hainaut",
    "sg:tags":[
        "garage"
    ],
    "wof:name":"Durant D",
    "wof:placetype":"venue"
},
  "geometry": {"coordinates":[4.4795150757,50.4009437561],"type":"Point"}
}