{
  "type": "Feature",
  "properties": {
    "iso:country":"BE",
    "sg:address":"Kloosterstraat 27",
    "sg:city":"Zingem",
    "sg:orig_category":"Dierenartsen",
    "sg:phone":"+32 9 383 59 51",
    "sg:postcode":"9750",
    "sg:province":"Oost-Vlaanderen",
    "wof:name":"Marc De Paermentier",
    "wof:placetype":"venue"
},
  "geometry": {"coordinates":[3.5877430439,50.9013710022],"type":"Point"}
}