{
  "type": "Feature",
  "properties": {
    "addr:full":"Abelestraat 66 Izegem West-Vlaanderen 8870",
    "addr:housenumber":"66",
    "addr:postcode":"8870",
    "addr:street":"Abelestraat",
    "iso:country":"BE",
    "sg:address":"Abelestraat 66",
    "sg:city":"Izegem",
    "sg:classifiers":[
        {
            "category":"Sports & Exercise",
            "subcategory":"Skate Park",
            "type":"Entertainment"
        }
    ],
    "sg:phone":"+32 51 30 32 85",
    "sg:postcode":"8870",
    "sg:province":"West-Vlaanderen",
    "sg:tags":[
        "mushroom"
    ],
    "wof:name":"Demeulenaere N",
    "wof:placetype":"venue"
},
  "geometry": {"coordinates":[3.1886460781,50.9208068848],"type":"Point"}
}