{
  "type": "Feature",
  "properties": {
    "addr:full":"Nieuwe Steenweg 305 De Haan West-Vlaanderen 8420",
    "addr:housenumber":"305",
    "addr:postcode":"8420",
    "addr:street":"Nieuwe Steenweg",
    "iso:country":"BE",
    "sg:address":"Nieuwe Steenweg 305",
    "sg:city":"De Haan",
    "sg:orig_category":"Brood, gebak and snoepgoed",
    "sg:phone":"+32 59 23 32 49",
    "sg:postcode":"8420",
    "sg:province":"West-Vlaanderen",
    "wof:name":"Bakkerij Pascal",
    "wof:placetype":"venue"
},
  "geometry": {"coordinates":[3.0335969925,51.2682876587],"type":"Point"}
}