{
  "type": "Feature",
  "properties": {
    "iso:country":"BE",
    "sg:address":"Meerweg 255",
    "sg:city":"Sint-pieters-leeuw (ruisbroek)",
    "sg:classifiers":[
        {
            "category":"Retail",
            "subcategory":"Animal Services",
            "type":"Services"
        }
    ],
    "sg:phone":"+32 2 377 26 21",
    "sg:postcode":"1601",
    "sg:province":"Vlaams-Brabant",
    "sg:tags":[
        "grooming",
        "-",
        "dog"
    ],
    "wof:name":"Hoeveke ('t)",
    "wof:placetype":"venue"
},
  "geometry": {"coordinates":[4.2802000046,50.7805938721],"type":"Point"}
}