{
  "type": "Feature",
  "properties": {
    "iso:country":"BE",
    "sg:address":"Rue Albert Premier 64",
    "sg:city":"La Louviere",
    "sg:orig_category":"Bagage and lederwaren",
    "sg:phone":"+32 64 22 16 56",
    "sg:postcode":"7100",
    "sg:province":"Hainaut",
    "wof:name":"Gilance",
    "wof:placetype":"venue"
},
  "geometry": {"coordinates":[4.1856532097,50.4756622314],"type":"Point"}
}