{
  "type": "Feature",
  "properties": {
    "iso:country":"BE",
    "sg:address":"Eksaardserijweg 167",
    "sg:city":"Gent (oostakker)",
    "sg:classifiers":[
        {
            "category":"Building & Trades",
            "subcategory":"Pest Control",
            "type":"Services"
        }
    ],
    "sg:phone":"+32 9 251 67 41",
    "sg:postcode":"9041",
    "sg:province":"Oost-Vlaanderen",
    "sg:tags":[
        "painting",
        "contractor"
    ],
    "wof:name":"P.i.c. & Partners Nv",
    "wof:placetype":"venue"
},
  "geometry": {"coordinates":[3.7764010429,51.0934295654],"type":"Point"}
}