{
  "type": "Feature",
  "properties": {
    "addr:full":"Chauss\u00c9e De Roodebeek 314 Bruxelles Bruxelles-Capitale 1200",
    "addr:housenumber":"314",
    "addr:postcode":"1200",
    "addr:street":"Chausse\u0301E De Roodebeek",
    "iso:country":"BE",
    "sg:address":"Chauss\u00c9e De Roodebeek 314",
    "sg:city":"Bruxelles",
    "sg:orig_category":"Activit\u00e9s r\u00e9cr\u00e9atives diverses",
    "sg:phone":"+32 2 761 28 39",
    "sg:postcode":"1200",
    "sg:province":"Bruxelles-Capitale",
    "wof:name":"Caissa Woluw\u00c9",
    "wof:placetype":"venue"
},
  "geometry": {"coordinates":[4.422533989,50.8493041992],"type":"Point"}
}