{
  "type": "Feature",
  "properties": {
    "iso:country":"BE",
    "sg:address":"Rue Des Bonniers 20",
    "sg:city":"Lobbes",
    "sg:orig_category":"Dierenartsen",
    "sg:phone":"+32 71 59 47 98",
    "sg:postcode":"6540",
    "sg:province":"Hainaut",
    "wof:name":"Jean-paul Jansen",
    "wof:placetype":"venue"
},
  "geometry": {"coordinates":[4.2732219696,50.3633079529],"type":"Point"}
}