{
  "type": "Feature",
  "properties": {
    "iso:country":"BE",
    "sg:address":"Houtbulckstraat 2a",
    "sg:city":"Deinze",
    "sg:orig_category":"Forge, Moulage and Profilage des M\u00e9taux",
    "sg:phone":"+32 51 63 62 30",
    "sg:postcode":"9800",
    "sg:province":"Oost-Vlaanderen",
    "wof:name":"Tack",
    "wof:placetype":"venue"
},
  "geometry": {"coordinates":[3.4454400539,50.981880188],"type":"Point"}
}