{
  "type": "Feature",
  "properties": {
    "addr:full":"Kerkstraat 72 Lokeren Oost-Vlaanderen 9160",
    "addr:housenumber":"72",
    "addr:postcode":"9160",
    "addr:street":"Kerkstraat",
    "iso:country":"BE",
    "sg:address":"Kerkstraat 72",
    "sg:city":"Lokeren",
    "sg:classifiers":[
        {
            "category":"Organizations",
            "subcategory":"Professional Association",
            "type":"Services"
        }
    ],
    "sg:phone":"+32 9 339 12 49",
    "sg:postcode":"9160",
    "sg:province":"Oost-Vlaanderen",
    "sg:tags":[
        "trade-union",
        "federation"
    ],
    "wof:name":"Vegebe-nubelt-belgapom",
    "wof:placetype":"venue"
},
  "geometry": {"coordinates":[3.9942209721,51.1026344299],"type":"Point"}
}