{
  "type": "Feature",
  "properties": {
    "addr:full":"Rue Edouard Colson 81 Ans Li\u00e8ge 4431",
    "addr:housenumber":"81",
    "addr:postcode":"4431",
    "addr:street":"Rue Edouard Colson",
    "iso:country":"BE",
    "sg:address":"Rue Edouard Colson 81",
    "sg:city":"Ans",
    "sg:orig_category":"Speciaalzaken Vloer- and muurbekleding",
    "sg:phone":"+32 4 263 44 53",
    "sg:postcode":"4431",
    "sg:province":"Li\u00e8ge",
    "wof:name":"Gielen-wauters & Fils",
    "wof:placetype":"venue"
},
  "geometry": {"coordinates":[5.5034351349,50.6668319702],"type":"Point"}
}