{
  "type": "Feature",
  "properties": {
    "addr:full":"Ramskapellestraat 53 Nieuwpoort West-Vlaanderen 8620",
    "addr:housenumber":"53",
    "addr:postcode":"8620",
    "addr:street":"Ramskapellestraat",
    "iso:country":"BE",
    "sg:address":"Ramskapellestraat 53",
    "sg:city":"Nieuwpoort",
    "sg:orig_category":"Voertuigen",
    "sg:phone":"+32 58 23 54 23",
    "sg:postcode":"8620",
    "sg:province":"West-Vlaanderen",
    "wof:name":"Garage Goderis",
    "wof:placetype":"venue"
},
  "geometry": {"coordinates":[2.7629349232,51.1117935181],"type":"Point"}
}