{
  "type": "Feature",
  "properties": {
    "iso:country":"BE",
    "sg:address":"Oosteinde 15",
    "sg:city":"Lochristi",
    "sg:classifiers":[
        {
            "category":"Insurance",
            "subcategory":"Insurance Agent",
            "type":"Services"
        }
    ],
    "sg:phone":"+32 9 355 68 40",
    "sg:postcode":"9080",
    "sg:province":"Oost-Vlaanderen",
    "sg:tags":[
        "verzekeringsmakelaars",
        "expert"
    ],
    "wof:name":"Van Renterghem",
    "wof:placetype":"venue"
},
  "geometry": {"coordinates":[3.8654859066,51.1336555481],"type":"Point"}
}