{
  "type": "Feature",
  "properties": {
    "addr:full":"Rue Val\u00e8re Mabille 52 Box 3 Morlanwelz (morlanwelz-mariemont) Hainaut 7140",
    "addr:housenumber":"52;3",
    "addr:postcode":"7140",
    "addr:street":"Rue Vale\u0300Re Mabille;Box",
    "iso:country":"BE",
    "sg:address":"Rue Val\u00e8re Mabille 52 Box 3",
    "sg:city":"Morlanwelz (morlanwelz-mariemont)",
    "sg:classifiers":[
        {
            "category":"Health Services",
            "subcategory":"Health Practitioner",
            "type":"Services"
        }
    ],
    "sg:phone":"+32 64 22 62 74",
    "sg:postcode":"7140",
    "sg:province":"Hainaut",
    "sg:tags":[
        "therapist",
        "speech"
    ],
    "wof:name":"Armand N",
    "wof:placetype":"venue"
},
  "geometry": {"coordinates":[4.223074913,50.4557037354],"type":"Point"}
}