{
  "type": "Feature",
  "properties": {
    "iso:country":"BE",
    "sg:address":"Dinantstraat 4",
    "sg:city":"Middelkerke",
    "sg:orig_category":"Cr\u00e9meries",
    "sg:phone":"+32 50 71 96 81",
    "sg:postcode":"9992",
    "sg:province":"Oost-Vlaanderen",
    "wof:name":"D'hont",
    "wof:placetype":"venue"
},
  "geometry": {"coordinates":[2.8186399937,51.1875190735],"type":"Point"}
}