{
  "type": "Feature",
  "properties": {
    "iso:country":"BE",
    "sg:address":"Rue Saint-paul 10",
    "sg:city":"Li\u00c8ge",
    "sg:orig_category":"Brood, gebak and snoepgoed",
    "sg:phone":"+32 4 223 45 56",
    "sg:postcode":"4000",
    "sg:province":"Li\u00e8ge",
    "wof:name":"P\u00c2tisserie Stoffels",
    "wof:placetype":"venue"
},
  "geometry": {"coordinates":[5.5726652145,50.6399688721],"type":"Point"}
}