{
  "type": "Feature",
  "properties": {
    "addr:full":"Roerdompstraat 30 Diepenbeek Limburg 3590",
    "addr:housenumber":"30",
    "addr:postcode":"3590",
    "addr:street":"Roerdompstraat",
    "iso:country":"BE",
    "sg:address":"Roerdompstraat 30",
    "sg:city":"Diepenbeek",
    "sg:orig_category":"Boekhouders",
    "sg:phone":"+32 11 22 64 13",
    "sg:postcode":"3590",
    "sg:province":"Limburg",
    "wof:name":"Denise Van Gutschoven",
    "wof:placetype":"venue"
},
  "geometry": {"coordinates":[5.4262909889,50.9415855408],"type":"Point"}
}