{
  "type": "Feature",
  "properties": {
    "addr:full":"Lommelsebaan 5ba Hechtel-eksel Limburg 3940",
    "addr:housenumber":"5ba",
    "addr:postcode":"3940",
    "addr:street":"Lommelsebaan",
    "iso:country":"BE",
    "sg:address":"Lommelsebaan 5ba",
    "sg:city":"Hechtel-eksel",
    "sg:classifiers":[
        {
            "category":"Manufacturing",
            "subcategory":"Textiles",
            "type":"Manufacturing & Wholesale Goods"
        }
    ],
    "sg:phone":"+32 11 73 54 79",
    "sg:postcode":"3940",
    "sg:province":"Limburg",
    "wof:name":"Modestoffen Jacqueline",
    "wof:placetype":"venue"
},
  "geometry": {"coordinates":[5.364795208,51.1255340576],"type":"Point"}
}