{
  "type": "Feature",
  "properties": {
    "addr:full":"Duivenstraat 88 Oud-heverlee (haasrode) Vlaams-Brabant 3053",
    "addr:housenumber":"88",
    "addr:postcode":"3053",
    "addr:street":"Duivenstraat",
    "iso:country":"BE",
    "sg:address":"Duivenstraat 88",
    "sg:city":"Oud-heverlee (haasrode)",
    "sg:classifiers":[
        {
            "category":"Building & Trades",
            "subcategory":"Landscaping Services",
            "type":"Services"
        }
    ],
    "sg:phone":"+32 16 40 10 68",
    "sg:postcode":"3053",
    "sg:province":"Vlaams-Brabant",
    "sg:tags":[
        "gardening",
        "garden",
        "maintenance"
    ],
    "wof:name":"Fluyt J",
    "wof:placetype":"venue"
},
  "geometry": {"coordinates":[4.7121548653,50.8417396545],"type":"Point"}
}