{
  "type": "Feature",
  "properties": {
    "iso:country":"BE",
    "sg:address":"Nijverheidslaan 9",
    "sg:city":"Maldegem",
    "sg:orig_category":"Software ontwikkeling and ontwerp",
    "sg:phone":"+32 50 72 04 54",
    "sg:postcode":"9990",
    "sg:province":"Oost-Vlaanderen",
    "wof:name":"Top Solution Development",
    "wof:placetype":"venue"
},
  "geometry": {"coordinates":[3.4760708809,51.1954421997],"type":"Point"}
}