{
  "type": "Feature",
  "properties": {
    "iso:country":"BE",
    "sg:address":"Londerzeelseweg 108",
    "sg:city":"Kapelle-op-den-bos (ramsdonk)",
    "sg:classifiers":[
        {
            "category":"Building & Trades",
            "subcategory":"Construction",
            "type":"Services"
        }
    ],
    "sg:phone":"+32 15 71 47 02",
    "sg:postcode":"1880",
    "sg:province":"Vlaams-Brabant",
    "sg:tags":[
        "carpenter"
    ],
    "wof:name":"Peeters Bouw & Interieur Bvba",
    "wof:placetype":"venue"
},
  "geometry": {"coordinates":[4.3446979523,51.013004303],"type":"Point"}
}