{
  "type": "Feature",
  "properties": {
    "addr:full":"Rue De La Brasserie 1 Brunehaut (guignies) Hainaut 7620",
    "addr:housenumber":"1",
    "addr:postcode":"7620",
    "addr:street":"Rue De La Brasserie;Guignies Hainaut",
    "iso:country":"BE",
    "sg:address":"Rue De La Brasserie 1",
    "sg:city":"Brunehaut (guignies)",
    "sg:classifiers":[
        {
            "category":"Shopping",
            "subcategory":"Pets & Pet Supplies",
            "type":"Retail Goods"
        }
    ],
    "sg:phone":"+32 69 64 94 20",
    "sg:postcode":"7620",
    "sg:province":"Hainaut",
    "sg:tags":[
        "shop",
        "-"
    ],
    "wof:name":"Vincent Gilbert",
    "wof:placetype":"venue"
},
  "geometry": {"coordinates":[3.3725280762,50.5482063293],"type":"Point"}
}