{
  "type": "Feature",
  "properties": {
    "iso:country":"BE",
    "sg:address":"Statielei 66",
    "sg:city":"Mortsel",
    "sg:orig_category":"Vegetable Growing Machines",
    "sg:phone":"+32 52 48 34 95",
    "sg:postcode":"2640",
    "sg:province":"Antwerpen",
    "wof:name":"De Clippeleir Tuinbouwmachines",
    "wof:placetype":"venue"
},
  "geometry": {"coordinates":[4.1697888374,51.0491676331],"type":"Point"}
}