{
  "type": "Feature",
  "properties": {
    "iso:country":"BE",
    "sg:address":"Kastelein 86",
    "sg:city":"Turnhout",
    "sg:classifiers":[
        {
            "category":"Organizations",
            "subcategory":"Community Association",
            "type":"Services"
        }
    ],
    "sg:phone":"+32 14 55 69 38",
    "sg:postcode":"2300",
    "sg:province":"Antwerpen",
    "sg:tags":[
        "box",
        "cardboard"
    ],
    "wof:name":"Corrutech Nv",
    "wof:placetype":"venue"
},
  "geometry": {"coordinates":[4.9450831413,51.3394317627],"type":"Point"}
}