{
  "type": "Feature",
  "properties": {
    "iso:country":"BE",
    "sg:address":"Verdunstraat 438",
    "sg:city":"Brussel/bruxelles",
    "sg:orig_category":"Sportclubs",
    "sg:phone":"+32 2 241 57 61",
    "sg:postcode":"1130",
    "sg:province":"Bruxelles-Capitale",
    "wof:name":"Badminton Club Evere",
    "wof:placetype":"venue"
},
  "geometry": {"coordinates":[4.4189968109,50.8925514221],"type":"Point"}
}