{
  "type": "Feature",
  "properties": {
    "iso:country":"BE",
    "sg:address":"Moerstraat 13",
    "sg:city":"Zomergem",
    "sg:classifiers":[
        {
            "category":"Building & Trades",
            "subcategory":"Electrical",
            "type":"Services"
        }
    ],
    "sg:phone":"+32 9 372 82 22",
    "sg:postcode":"9930",
    "sg:province":"Oost-Vlaanderen",
    "sg:tags":[
        "electric",
        "-",
        "housewiring",
        "contractor"
    ],
    "wof:name":"Fobelets",
    "wof:placetype":"venue"
},
  "geometry": {"coordinates":[3.5718100071,51.09897995],"type":"Point"}
}