{
  "type": "Feature",
  "properties": {
    "addr:full":"Brielensestraat 13 Ieper (brielen) West-Vlaanderen 8900",
    "addr:housenumber":"13",
    "addr:postcode":"8900",
    "addr:street":"Brielensestraat",
    "iso:country":"BE",
    "sg:address":"Brielensestraat 13",
    "sg:city":"Ieper (brielen)",
    "sg:classifiers":[
        {
            "category":"Home & Garden",
            "subcategory":"Building Materials",
            "type":"Retail Goods"
        }
    ],
    "sg:phone":"+32 57 21 93 46",
    "sg:postcode":"8900",
    "sg:province":"West-Vlaanderen",
    "sg:tags":[
        "bathroom",
        "installation",
        "accessory"
    ],
    "wof:name":"Rosseeuw P",
    "wof:placetype":"venue"
},
  "geometry": {"coordinates":[2.8487179279,50.86668396],"type":"Point"}
}