{
  "type": "Feature",
  "properties": {
    "iso:country":"BE",
    "sg:address":"Vannypen street, 75",
    "sg:city":"Brussels",
    "sg:classifiers":[
        {
            "category":"Professional",
            "subcategory":"Computer Services",
            "type":"Services"
        }
    ],
    "sg:postcode":"1160",
    "sg:tags":[
        "wines",
        "reviews",
        "wine-tourism",
        "restaurants"
    ],
    "sg:website":"http://www.vinogusto.com/en",
    "wof:name":"Vinogusto.com",
    "wof:placetype":"venue"
},
  "geometry": {"coordinates":[4.4390046,50.8085929],"type":"Point"}
}