{
  "type": "Feature",
  "properties": {
    "addr:full":"Affligemdreef 11bb Aalst Oost-Vlaanderen 9300",
    "addr:housenumber":"11bb",
    "addr:postcode":"9300",
    "addr:street":"Affligemdreef",
    "iso:country":"BE",
    "sg:address":"Affligemdreef 11bb",
    "sg:city":"Aalst",
    "sg:orig_category":"Activit\u00e9s diverses d'imprimerie",
    "sg:phone":"+32 53 77 51 21",
    "sg:postcode":"9300",
    "sg:province":"Oost-Vlaanderen",
    "wof:name":"Fa. Perplex",
    "wof:placetype":"venue"
},
  "geometry": {"coordinates":[4.0611009598,50.93176651],"type":"Point"}
}