{
  "type": "Feature",
  "properties": {
    "addr:full":"Bollostraat 10 Heist-op-den-berg Antwerpen 2220",
    "addr:housenumber":"10",
    "addr:postcode":"2220",
    "addr:street":"Bollostraat",
    "iso:country":"BE",
    "sg:address":"Bollostraat 10",
    "sg:city":"Heist-op-den-berg",
    "sg:orig_category":"Bloemen and planten",
    "sg:phone":"+32 15 22 03 74",
    "sg:postcode":"2220",
    "sg:province":"Antwerpen",
    "wof:name":"Sempervivum",
    "wof:placetype":"venue"
},
  "geometry": {"coordinates":[4.7268829346,51.0366210938],"type":"Point"}
}