{
  "type": "Feature",
  "properties": {
    "iso:country":"BE",
    "sg:address":"Begijnenmeers 57",
    "sg:city":"Liedekerke",
    "sg:orig_category":"Winkelinrichting and handelsuitrusting Gh",
    "sg:phone":"+32 54 34 17 37",
    "sg:postcode":"1770",
    "sg:province":"Vlaams-Brabant",
    "wof:name":"Guldekon Baresto",
    "wof:placetype":"venue"
},
  "geometry": {"coordinates":[4.0896658897,50.8838424683],"type":"Point"}
}