{
  "type": "Feature",
  "properties": {
    "addr:full":"Battelsesteenweg 455e Mechelen Antwerpen 2800",
    "addr:housenumber":"455e",
    "addr:postcode":"2800",
    "addr:street":"Battelsesteenweg",
    "iso:country":"BE",
    "sg:address":"Battelsesteenweg 455e",
    "sg:city":"Mechelen",
    "sg:orig_category":"Software ontwikkeling and ontwerp",
    "sg:phone":"+32 15 28 09 95",
    "sg:postcode":"2800",
    "sg:province":"Antwerpen",
    "wof:name":"T.r. Systems Inc",
    "wof:placetype":"venue"
},
  "geometry": {"coordinates":[4.450094223,51.0380706787],"type":"Point"}
}