{
  "type": "Feature",
  "properties": {
    "addr:full":"Rue Des M\u00c9sanges 15 Bertrix Luxembourg 6880",
    "addr:housenumber":"15",
    "addr:postcode":"6880",
    "addr:street":"Rue Des Me\u0301Sanges",
    "iso:country":"BE",
    "sg:address":"Rue Des M\u00c9sanges 15",
    "sg:city":"Bertrix",
    "sg:classifiers":[
        {
            "category":"Personal",
            "subcategory":"Beauty Salon",
            "type":"Services"
        }
    ],
    "sg:phone":"+32 61 41 15 84",
    "sg:postcode":"6880",
    "sg:province":"Luxembourg",
    "sg:tags":[
        "de",
        "coiffure"
    ],
    "wof:name":"Marie-paule Wanlin",
    "wof:placetype":"venue"
},
  "geometry": {"coordinates":[5.2618198395,49.8494529724],"type":"Point"}
}