{
  "type": "Feature",
  "properties": {
    "addr:full":"Rijselstraat 184 Menen West-Vlaanderen 8930",
    "addr:housenumber":"184",
    "addr:postcode":"8930",
    "addr:street":"Rijselstraat",
    "iso:country":"BE",
    "sg:address":"Rijselstraat 184",
    "sg:city":"Menen",
    "sg:classifiers":[
        {
            "category":"Shopping",
            "subcategory":"Gifts & Souvenirs",
            "type":"Retail Goods"
        }
    ],
    "sg:phone":"+32 56 53 20 35",
    "sg:postcode":"8930",
    "sg:province":"West-Vlaanderen",
    "sg:tags":[
        "-"
    ],
    "wof:name":"Jural Liquidations",
    "wof:placetype":"venue"
},
  "geometry": {"coordinates":[3.1262419224,50.7896995544],"type":"Point"}
}