{
  "type": "Feature",
  "properties": {
    "iso:country":"BE",
    "sg:address":"Rue De La Consolation 12-14",
    "sg:city":"Schaarbeek/schaerbeek",
    "sg:orig_category":"Plomberie, chauffage and installations sanitaires",
    "sg:phone":"+32 2 241 85 92",
    "sg:postcode":"1030",
    "sg:province":"Bruxelles-Capitale",
    "wof:name":"Sanifluides",
    "wof:placetype":"venue"
},
  "geometry": {"coordinates":[4.3762612343,50.856880188],"type":"Point"}
}