{
  "type": "Feature",
  "properties": {
    "iso:country":"BE",
    "sg:address":"Ieperstraat 218",
    "sg:city":"Heuvelland (wijtschate)",
    "sg:classifiers":[
        {
            "category":"Personal",
            "subcategory":"Barber",
            "type":"Services"
        }
    ],
    "sg:phone":"+32 57 44 64 58",
    "sg:postcode":"8953",
    "sg:province":"West-Vlaanderen",
    "sg:tags":[
        "gentleman",
        "salon",
        "-",
        "hairdressing"
    ],
    "wof:name":"Avanti Coiffure",
    "wof:placetype":"venue"
},
  "geometry": {"coordinates":[2.8949561119,50.7689781189],"type":"Point"}
}