{
  "type": "Feature",
  "properties": {
    "addr:full":"Heirbaan 173 Hamme Oost-Vlaanderen 9220",
    "addr:housenumber":"173",
    "addr:postcode":"9220",
    "addr:street":"Heirbaan",
    "iso:country":"BE",
    "sg:address":"Heirbaan 173",
    "sg:city":"Hamme",
    "sg:classifiers":[
        {
            "category":"Professional",
            "subcategory":"Management & Consulting",
            "type":"Services"
        }
    ],
    "sg:phone":"+32 52 22 66 66",
    "sg:postcode":"9220",
    "sg:province":"Oost-Vlaanderen",
    "sg:tags":[
        "consultant"
    ],
    "wof:name":"Sofia Cv",
    "wof:placetype":"venue"
},
  "geometry": {"coordinates":[4.0909090042,51.0801315308],"type":"Point"}
}