{
  "type": "Feature",
  "properties": {
    "addr:full":"Voie Du Roman Pays 48a Ottignies-louvain-la-neuve (louvain-la-neuve) Brabant Wallon 1348",
    "addr:housenumber":"48a",
    "addr:postcode":"1348",
    "addr:street":"Voie Du Roman Pays",
    "iso:country":"BE",
    "sg:address":"Voie Du Roman Pays 48a",
    "sg:city":"Ottignies-louvain-la-neuve (louvain-la-neuve)",
    "sg:classifiers":[
        {
            "category":"Home & Garden",
            "subcategory":"Carpets & Floor Coverings",
            "type":"Retail Goods"
        }
    ],
    "sg:phone":"+32 10 45 95 28",
    "sg:postcode":"1348",
    "sg:province":"Brabant Wallon",
    "sg:tags":[
        "-"
    ],
    "wof:name":"Dynamic D\u00e9cors",
    "wof:placetype":"venue"
},
  "geometry": {"coordinates":[4.6148629189,50.6669616699],"type":"Point"}
}