{
  "type": "Feature",
  "properties": {
    "iso:country":"BE",
    "sg:address":"Industriegebied Booiebos 6",
    "sg:city":"Drongen",
    "sg:classifiers":[
        {
            "category":"Food & Beverages",
            "subcategory":"Chocolate",
            "type":"Retail Goods"
        }
    ],
    "sg:phone":"+32 9 282 55 11",
    "sg:postcode":"9031",
    "sg:province":"Oost-Vlaanderen",
    "sg:tags":[
        "base"
    ],
    "wof:name":"Barry Callebaut N.v. Belgium",
    "wof:placetype":"venue"
},
  "geometry": {"coordinates":[3.5969519615,51.0402107239],"type":"Point"}
}