{
  "type": "Feature",
  "properties": {
    "addr:full":"Laagstraat 2 Ardooie West-Vlaanderen 8851",
    "addr:housenumber":"2",
    "addr:postcode":"8851",
    "addr:street":"Laagstraat",
    "iso:country":"BE",
    "sg:address":"Laagstraat 2",
    "sg:city":"Ardooie",
    "sg:orig_category":"Fruitteelt Groententeelt",
    "sg:phone":"+32 51 74 42 03",
    "sg:postcode":"8851",
    "sg:province":"West-Vlaanderen",
    "wof:name":"Egied Deboosere",
    "wof:placetype":"venue"
},
  "geometry": {"coordinates":[3.2127571106,51.0042686462],"type":"Point"}
}