{
  "type": "Feature",
  "properties": {
    "iso:country":"BE",
    "sg:address":"Rue Brogniez 43",
    "sg:city":"Anderlecht",
    "sg:orig_category":"V\u00eatements pour b\u00e9b\u00e9s and enfants. V\u00eatements pour Dames. V\u00eatements pour Hommes",
    "sg:phone":"+32 2 524 08 18",
    "sg:postcode":"1070",
    "sg:province":"Bruxelles-Capitale",
    "wof:name":"Heurotex",
    "wof:placetype":"venue"
},
  "geometry": {"coordinates":[4.3372511864,50.8420066833],"type":"Point"}
}