{
  "type": "Feature",
  "properties": {
    "iso:country":"BE",
    "sg:address":"Rue Wiots 12",
    "sg:city":"Tournai",
    "sg:orig_category":"Catering and organisation de f\u00eates",
    "sg:phone":"+32 69 54 79 19",
    "sg:postcode":"7530",
    "sg:province":"Hainaut",
    "wof:name":"Marc Callens",
    "wof:placetype":"venue"
},
  "geometry": {"coordinates":[3.4845468998,50.5904769897],"type":"Point"}
}