{
  "type": "Feature",
  "properties": {
    "addr:full":"Goedlevenstraat 123 Gent (oostakker) Oost-Vlaanderen 9041",
    "addr:housenumber":"123",
    "addr:postcode":"9041",
    "addr:street":"Goedlevenstraat",
    "iso:country":"BE",
    "sg:address":"Goedlevenstraat 123",
    "sg:city":"Gent (oostakker)",
    "sg:classifiers":[
        {
            "category":"Health Services",
            "subcategory":"Health Practitioner",
            "type":"Services"
        }
    ],
    "sg:phone":"+32 9 251 14 48",
    "sg:postcode":"9041",
    "sg:province":"Oost-Vlaanderen",
    "sg:tags":[
        "physiotherapist"
    ],
    "wof:name":"De Cock Alma",
    "wof:placetype":"venue"
},
  "geometry": {"coordinates":[3.767676115,51.0752563477],"type":"Point"}
}