{
  "type": "Feature",
  "properties": {
    "addr:full":"Rue Du Rouge Clo\u00cetre 1bb La Hulpe Brabant Wallon 1310",
    "addr:housenumber":"1bb",
    "addr:postcode":"1310",
    "addr:street":"Rue Du Rouge Cloi\u0302Tre",
    "iso:country":"BE",
    "sg:address":"Rue Du Rouge Clo\u00cetre 1bb",
    "sg:city":"La Hulpe",
    "sg:classifiers":[
        {
            "category":"Insurance",
            "subcategory":"Insurance Agent",
            "type":"Services"
        }
    ],
    "sg:phone":"+32 2 652 14 02",
    "sg:postcode":"1310",
    "sg:province":"Brabant Wallon",
    "sg:tags":[
        "verzekeringsmakelaars",
        "expert"
    ],
    "wof:name":"Charlier Jacqueline",
    "wof:placetype":"venue"
},
  "geometry": {"coordinates":[4.4896559715,50.7490234375],"type":"Point"}
}