{
  "type": "Feature",
  "properties": {
    "addr:full":"Wondelgemstraat 190 Gent Oost-Vlaanderen 9000",
    "addr:housenumber":"190",
    "addr:postcode":"9000",
    "addr:street":"Wondelgemstraat;Oost-Vlaanderen",
    "iso:country":"BE",
    "sg:address":"Wondelgemstraat 190",
    "sg:city":"Gent",
    "sg:classifiers":[
        {
            "category":"Shopping",
            "subcategory":"Gifts & Souvenirs",
            "type":"Retail Goods"
        }
    ],
    "sg:phone":"+32 9 225 60 54",
    "sg:postcode":"9000",
    "sg:province":"Oost-Vlaanderen",
    "sg:tags":[
        "-"
    ],
    "wof:name":"Canasi Trading",
    "wof:placetype":"venue"
},
  "geometry": {"coordinates":[3.7094790936,51.0647735596],"type":"Point"}
}