{
  "type": "Feature",
  "properties": {
    "addr:full":"Wildendries 26ba Ninove Oost-Vlaanderen 9404",
    "addr:housenumber":"26ba",
    "addr:postcode":"9404",
    "addr:street":"Wildendries",
    "iso:country":"BE",
    "sg:address":"Wildendries 26ba",
    "sg:city":"Ninove",
    "sg:orig_category":"Eleveurs and marchands de porcs. Eleveurs de bovins",
    "sg:phone":"+32 54 32 61 91",
    "sg:postcode":"9404",
    "sg:province":"Oost-Vlaanderen",
    "wof:name":"Albert De Vos",
    "wof:placetype":"venue"
},
  "geometry": {"coordinates":[3.9570000172,50.8419036865],"type":"Point"}
}