{
  "type": "Feature",
  "properties": {
    "addr:full":"Mechelsesteenweg 270 Kontich Antwerpen 2550",
    "addr:housenumber":"270",
    "addr:postcode":"2550",
    "addr:street":"Mechelsesteenweg",
    "iso:country":"BE",
    "sg:address":"Mechelsesteenweg 270",
    "sg:city":"Kontich",
    "sg:orig_category":"Benzinestations and brandstoffen Voertuigen",
    "sg:phone":"+32 3 457 11 46",
    "sg:postcode":"2550",
    "sg:province":"Antwerpen",
    "wof:name":"Autobedrijf Rudy",
    "wof:placetype":"venue"
},
  "geometry": {"coordinates":[4.4496951103,51.1232299805],"type":"Point"}
}