{
  "type": "Feature",
  "properties": {
    "iso:country":"BE",
    "sg:address":"Rue Des Ecoles 10",
    "sg:city":"Yvoir",
    "sg:orig_category":"Paramedische behandelingen Schoonheidssalons",
    "sg:phone":"+32 82 61 43 56",
    "sg:postcode":"5530",
    "sg:province":"Namur",
    "wof:name":"Christel Delahaut",
    "wof:placetype":"venue"
},
  "geometry": {"coordinates":[4.9426932335,50.3135452271],"type":"Point"}
}