{
  "type": "Feature",
  "properties": {
    "addr:full":"Pastoor De Meerleerstraat 107 Sint-niklaas Oost-Vlaanderen 9100",
    "addr:housenumber":"107",
    "addr:postcode":"9100",
    "addr:street":"Pastoor De Meerleerstraat",
    "iso:country":"BE",
    "sg:address":"Pastoor De Meerleerstraat 107",
    "sg:city":"Sint-niklaas",
    "sg:classifiers":[
        {
            "category":"Professional",
            "subcategory":"Art Services",
            "type":"Services"
        }
    ],
    "sg:phone":"+32 3 777 27 06",
    "sg:postcode":"9100",
    "sg:province":"Oost-Vlaanderen",
    "sg:tags":[
        "-",
        "painter",
        "artist"
    ],
    "wof:name":"Vael R",
    "wof:placetype":"venue"
},
  "geometry": {"coordinates":[4.1344461441,51.1596031189],"type":"Point"}
}