{
  "type": "Feature",
  "properties": {
    "addr:full":"Karmelietenlaan 10 Kortrijk West-Vlaanderen 8500",
    "addr:housenumber":"10",
    "addr:postcode":"8500",
    "addr:street":"Karmelietenlaan",
    "iso:country":"BE",
    "sg:address":"Karmelietenlaan 10",
    "sg:city":"Kortrijk",
    "sg:classifiers":[
        {
            "category":"Real Estate",
            "subcategory":"Architect",
            "type":"Services"
        }
    ],
    "sg:phone":"+32 56 22 07 92",
    "sg:postcode":"8500",
    "sg:province":"West-Vlaanderen",
    "wof:name":"Deconinck B",
    "wof:placetype":"venue"
},
  "geometry": {"coordinates":[3.2630829811,50.8220214844],"type":"Point"}
}