{
  "type": "Feature",
  "properties": {
    "iso:country":"BE",
    "sg:address":"Dr\u00c8ve Richelle 156",
    "sg:city":"Waterloo",
    "sg:orig_category":"Alimentation sp\u00e9cialis\u00e9e. Supermarch\u00e9s",
    "sg:phone":"+32 2 354 27 37",
    "sg:postcode":"1410",
    "sg:province":"Brabant Wallon",
    "wof:name":"Louis Delhaize",
    "wof:placetype":"venue"
},
  "geometry": {"coordinates":[4.416364193,50.70470047],"type":"Point"}
}