{
  "type": "Feature",
  "properties": {
    "iso:country":"BE",
    "sg:address":"Avenue De Longwy 333",
    "sg:city":"Arlon",
    "sg:orig_category":"Peinture. Eclairage et \u00e9quipements du foyer. Rev\u00eatements pour sols and murs",
    "sg:phone":"+32 63 23 25 95",
    "sg:postcode":"6700",
    "sg:province":"Luxembourg",
    "wof:name":"Galasso",
    "wof:placetype":"venue"
},
  "geometry": {"coordinates":[5.8239488602,49.6726074219],"type":"Point"}
}