{
  "type": "Feature",
  "properties": {
    "iso:country":"BE",
    "sg:address":"Korte Wolvenstraat 3",
    "sg:city":"Anderlecht",
    "sg:orig_category":"Software ontwikkeling and ontwerp",
    "sg:phone":"+32 2 523 96 38",
    "sg:postcode":"1070",
    "sg:province":"Bruxelles-Capitale",
    "wof:name":"Codasy",
    "wof:placetype":"venue"
},
  "geometry": {"coordinates":[4.295935154,50.8237838745],"type":"Point"}
}