{
  "type": "Feature",
  "properties": {
    "addr:full":"Puyveldestraat 42ba Sint-gillis-waas Oost-Vlaanderen 9170",
    "addr:housenumber":"42ba",
    "addr:postcode":"9170",
    "addr:street":"Puyveldestraat",
    "iso:country":"BE",
    "sg:address":"Puyveldestraat 42ba",
    "sg:city":"Sint-gillis-waas",
    "sg:orig_category":"Koekjes, gebak and taart Fab",
    "sg:phone":"+32 3 789 15 84",
    "sg:postcode":"9170",
    "sg:province":"Oost-Vlaanderen",
    "wof:name":"Mama\u00b4s Koekje",
    "wof:placetype":"venue"
},
  "geometry": {"coordinates":[4.0640192032,51.1841087341],"type":"Point"}
}