{
  "type": "Feature",
  "properties": {
    "addr:full":"Rue Des Wagnons 15 Qui\u00c9vrain Hainaut 7380",
    "addr:housenumber":"15",
    "addr:postcode":"7380",
    "addr:street":"Rue Des Wagnons",
    "iso:country":"BE",
    "sg:address":"Rue Des Wagnons 15",
    "sg:city":"Qui\u00c9vrain",
    "sg:orig_category":"Installation \u00e9lectrique r\u00e9sidentielle",
    "sg:phone":"+32 65 43 12 35",
    "sg:postcode":"7380",
    "sg:province":"Hainaut",
    "wof:name":"K-elec",
    "wof:placetype":"venue"
},
  "geometry": {"coordinates":[3.6839280128,50.4042396545],"type":"Point"}
}