{
  "type": "Feature",
  "properties": {
    "iso:country":"BE",
    "sg:address":"Sint-sixtusstraat 96",
    "sg:city":"Poperinge",
    "sg:orig_category":"Rundveehouders Varkenskwekers",
    "sg:phone":"+32 57 33 65 53",
    "sg:postcode":"8970",
    "sg:province":"West-Vlaanderen",
    "wof:name":"Johan Dejonckheere",
    "wof:placetype":"venue"
},
  "geometry": {"coordinates":[2.7172100544,50.8809051514],"type":"Point"}
}