{
  "type": "Feature",
  "properties": {
    "iso:country":"BE",
    "sg:address":"Dorpsstraat 59b4",
    "sg:city":"Stekene",
    "sg:orig_category":"Animations diverses",
    "sg:phone":"+32 3 789 06 49",
    "sg:postcode":"9190",
    "sg:province":"Oost-Vlaanderen",
    "wof:name":"Discobar De Lacher Guido",
    "wof:placetype":"venue"
},
  "geometry": {"coordinates":[4.0394701958,51.204460144],"type":"Point"}
}