{
  "type": "Feature",
  "properties": {
    "iso:country":"BE",
    "sg:address":"Rue Des Gen\u00c9vriers 64",
    "sg:city":"Brussel/bruxelles",
    "sg:orig_category":"G\u00e9om\u00e8tres",
    "sg:phone":"+32 2 478 37 92",
    "sg:postcode":"1020",
    "sg:province":"Bruxelles-Capitale",
    "wof:name":"Julien Nellissen",
    "wof:placetype":"venue"
},
  "geometry": {"coordinates":[4.3325901031,50.9002494812],"type":"Point"}
}