{
  "type": "Feature",
  "properties": {
    "addr:full":"Rue Charles-magnette 1 Virton Luxembourg 6760",
    "addr:housenumber":"1",
    "addr:postcode":"6760",
    "addr:street":"Rue Charles-Magnette",
    "iso:country":"BE",
    "sg:address":"Rue Charles-magnette 1",
    "sg:city":"Virton",
    "sg:orig_category":"D\u00e9taillants en pi\u00e8ces and accessoires de voitures. Mat\u00e9riel de T\u00e9l\u00e9communication",
    "sg:phone":"+32 63 58 10 22",
    "sg:postcode":"6760",
    "sg:province":"Luxembourg",
    "wof:name":"Electrauto",
    "wof:placetype":"venue"
},
  "geometry": {"coordinates":[5.5325798988,49.56640625],"type":"Point"}
}