{
  "type": "Feature",
  "properties": {
    "iso:country":"BE",
    "sg:address":"Rue Des Pr\u00c8s 60",
    "sg:city":"Liege",
    "sg:orig_category":"Fer and acier Fab",
    "sg:phone":"+32 4 362 23 23",
    "sg:postcode":"4000",
    "sg:province":"Li\u00e8ge",
    "wof:name":"Mottard",
    "wof:placetype":"venue"
},
  "geometry": {"coordinates":[5.5568699837,50.6160507202],"type":"Point"}
}