{
  "type": "Feature",
  "properties": {
    "addr:full":"Trekschurenstraat 159 Hasselt Limburg 3500",
    "addr:housenumber":"159",
    "addr:postcode":"3500",
    "addr:street":"Trekschurenstraat",
    "iso:country":"BE",
    "sg:address":"Trekschurenstraat 159",
    "sg:city":"Hasselt",
    "sg:classifiers":[
        {
            "category":"Food & Beverages",
            "subcategory":"Fruits & Vegetables",
            "type":"Retail Goods"
        }
    ],
    "sg:phone":"+32 11 28 36 18",
    "sg:postcode":"3500",
    "sg:province":"Limburg",
    "sg:tags":[
        "groenten"
    ],
    "wof:name":"Patricia Neven",
    "wof:placetype":"venue"
},
  "geometry": {"coordinates":[5.3424959183,50.9066085815],"type":"Point"}
}