{
  "type": "Feature",
  "properties": {
    "iso:country":"BE",
    "sg:address":"Rue Albert De 't Serclaes 64",
    "sg:city":"Dison (andrimont)",
    "sg:classifiers":[
        {
            "category":"Personal",
            "subcategory":"Beauty Salon",
            "type":"Services"
        }
    ],
    "sg:phone":"+32 87 31 24 03",
    "sg:postcode":"4821",
    "sg:province":"Li\u00e8ge",
    "wof:name":"Evelyne",
    "wof:placetype":"venue"
},
  "geometry": {"coordinates":[5.8542990685,50.6094284058],"type":"Point"}
}