{
  "type": "Feature",
  "properties": {
    "iso:country":"BE",
    "sg:address":"Sleidinge Dorp 15",
    "sg:city":"Evergem (sleidinge)",
    "sg:classifiers":[
        {
            "category":"Bakery",
            "type":"Food & Drink"
        }
    ],
    "sg:phone":"+32 9 357 31 71",
    "sg:postcode":"9940",
    "sg:province":"Oost-Vlaanderen",
    "sg:tags":[
        "confectioner",
        "baker"
    ],
    "wof:name":"Cocquyt R",
    "wof:placetype":"venue"
},
  "geometry": {"coordinates":[3.7075910568,51.1089019775],"type":"Point"}
}