{
  "type": "Feature",
  "properties": {
    "addr:full":"Kattestraat 8 Landen Vlaams-Brabant 3400",
    "addr:housenumber":"8",
    "addr:postcode":"3400",
    "addr:street":"Kattestraat",
    "iso:country":"BE",
    "sg:address":"Kattestraat 8",
    "sg:city":"Landen",
    "sg:orig_category":"Biens d'occasion. Epiceries. Eclairage et \u00e9quipements du foyer",
    "sg:phone":"+32 11 88 13 88",
    "sg:postcode":"3400",
    "sg:province":"Vlaams-Brabant",
    "wof:name":"Oxfam Wereldwinkel",
    "wof:placetype":"venue"
},
  "geometry": {"coordinates":[5.0790939331,50.7550086975],"type":"Point"}
}