{
  "type": "Feature",
  "properties": {
    "iso:country":"BE",
    "sg:address":"Lindestraat 44",
    "sg:city":"Wortegem-petegem (petegem-aan-de-schelde)",
    "sg:classifiers":[
        {
            "category":"Home & Garden",
            "subcategory":"Garden Supply",
            "type":"Retail Goods"
        }
    ],
    "sg:phone":"+32 55 30 35 84",
    "sg:postcode":"9790",
    "sg:province":"Oost-Vlaanderen",
    "sg:tags":[
        "lawn",
        "mower"
    ],
    "wof:name":"Farinon E",
    "wof:placetype":"venue"
},
  "geometry": {"coordinates":[3.5560760498,50.8384094238],"type":"Point"}
}