{
  "type": "Feature",
  "properties": {
    "iso:country":"BE",
    "sg:address":"Avenue Reine Astrid 16",
    "sg:city":"Namur",
    "sg:classifiers":[
        {
            "category":"Arena",
            "subcategory":"Sports Club",
            "type":"Entertainment"
        }
    ],
    "sg:phone":"+32 81 20 04 83",
    "sg:postcode":"5000",
    "sg:province":"Namur",
    "wof:name":"Shorin-mon-ju-jutsu",
    "wof:placetype":"venue"
},
  "geometry": {"coordinates":[4.8569698334,50.4621505737],"type":"Point"}
}