{
  "type": "Feature",
  "properties": {
    "addr:full":"Gasthuisstraat 57 Poperinge West-Vlaanderen 8970",
    "addr:housenumber":"57",
    "addr:postcode":"8970",
    "addr:street":"Gasthuisstraat",
    "iso:country":"BE",
    "sg:address":"Gasthuisstraat 57",
    "sg:city":"Poperinge",
    "sg:orig_category":"Newspapers, magazines, periodicals - Publishers",
    "sg:phone":"+32 57 34 65 11",
    "sg:postcode":"8970",
    "sg:province":"West-Vlaanderen",
    "wof:name":"Krant Van West-vlaanderen (de)",
    "wof:placetype":"venue"
},
  "geometry": {"coordinates":[2.7226839066,50.8555107117],"type":"Point"}
}