{
  "type": "Feature",
  "properties": {
    "addr:full":"Turnhoutsebaan 55 Schilde Antwerpen 2970",
    "addr:housenumber":"55",
    "addr:postcode":"2970",
    "addr:street":"Turnhoutsebaan",
    "iso:country":"BE",
    "sg:address":"Turnhoutsebaan 55",
    "sg:city":"Schilde",
    "sg:orig_category":"Artsen and specialisten",
    "sg:phone":"+32 3 385 29 99",
    "sg:postcode":"2970",
    "sg:province":"Antwerpen",
    "wof:name":"L. Van Breusegem",
    "wof:placetype":"venue"
},
  "geometry": {"coordinates":[4.5695018768,51.2364616394],"type":"Point"}
}