{
  "type": "Feature",
  "properties": {
    "addr:full":"Terhulpensteenweg 391 Overijse Vlaams-Brabant 3090",
    "addr:housenumber":"391",
    "addr:postcode":"3090",
    "addr:street":"Terhulpensteenweg",
    "iso:country":"BE",
    "sg:address":"Terhulpensteenweg 391",
    "sg:city":"Overijse",
    "sg:orig_category":"Benzinestations and brandstoffen",
    "sg:phone":"+32 2 687 64 95",
    "sg:postcode":"3090",
    "sg:province":"Vlaams-Brabant",
    "wof:name":"Jet",
    "wof:placetype":"venue"
},
  "geometry": {"coordinates":[4.5252709389,50.7532119751],"type":"Point"}
}