{
  "type": "Feature",
  "properties": {
    "addr:full":"Torhoutsesteenweg 130 Oostende West-Vlaanderen 8400",
    "addr:housenumber":"130",
    "addr:postcode":"8400",
    "addr:street":"Torhoutsesteenweg",
    "iso:country":"BE",
    "sg:address":"Torhoutsesteenweg 130",
    "sg:city":"Oostende",
    "sg:orig_category":"Agences immobili\u00e8res",
    "sg:phone":"+32 59 80 87 80",
    "sg:postcode":"8400",
    "sg:province":"West-Vlaanderen",
    "wof:name":"Cocoon",
    "wof:placetype":"venue"
},
  "geometry": {"coordinates":[2.9084560871,51.2213134766],"type":"Point"}
}