{
  "type": "Feature",
  "properties": {
    "iso:country":"BE",
    "sg:address":"Walgracht 26",
    "sg:city":"Evergem",
    "sg:classifiers":[
        {
            "category":"Manufacturing",
            "subcategory":"Paper Products",
            "type":"Manufacturing & Wholesale Goods"
        }
    ],
    "sg:phone":"+32 9 253 13 37",
    "sg:postcode":"9940",
    "sg:province":"Oost-Vlaanderen",
    "sg:tags":[
        "bookbinding"
    ],
    "wof:name":"Sepeli Nv",
    "wof:placetype":"venue"
},
  "geometry": {"coordinates":[3.7408299446,51.1387557983],"type":"Point"}
}