{
  "type": "Feature",
  "properties": {
    "addr:full":"Eikvarenweg 13 Gent Oost-Vlaanderen 9031",
    "addr:housenumber":"13",
    "addr:postcode":"9031",
    "addr:street":"Eikvarenweg;Oost-Vlaanderen",
    "iso:country":"BE",
    "sg:address":"Eikvarenweg 13",
    "sg:city":"Gent",
    "sg:classifiers":[
        {
            "category":"Landmark",
            "subcategory":"Marketplace",
            "type":"Public Place"
        }
    ],
    "sg:phone":"+32 9 236 14 93",
    "sg:postcode":"9031",
    "sg:province":"Oost-Vlaanderen",
    "sg:tags":[
        "commerce",
        "gr",
        "equipement",
        "de",
        "pour",
        "divers",
        "biens",
        "location",
        "diver"
    ],
    "wof:name":"Pierrot",
    "wof:placetype":"venue"
},
  "geometry": {"coordinates":[3.639400959,51.0471076965],"type":"Point"}
}