{
  "type": "Feature",
  "properties": {
    "addr:full":"Rijksweg 182 Wielsbeke West-Vlaanderen 8710",
    "addr:housenumber":"182",
    "addr:postcode":"8710",
    "addr:street":"Rijksweg;West-Vlaanderen",
    "iso:country":"BE",
    "sg:address":"Rijksweg 182",
    "sg:city":"Wielsbeke",
    "sg:classifiers":[
        {
            "category":"Professional",
            "subcategory":"Lawyer & Legal Services",
            "type":"Services"
        }
    ],
    "sg:phone":"+32 56 61 45 36",
    "sg:postcode":"8710",
    "sg:province":"West-Vlaanderen",
    "wof:name":"Arslijder W",
    "wof:placetype":"venue"
},
  "geometry": {"coordinates":[3.3826389313,50.9101753235],"type":"Point"}
}