{
  "type": "Feature",
  "properties": {
    "iso:country":"BE",
    "sg:address":"Rue De La Station 61",
    "sg:city":"Thimister-clermont (thimister)",
    "sg:classifiers":[
        {
            "category":"Wholesale",
            "subcategory":"Wine & Distilled Alcoholic Beverages",
            "type":"Manufacturing & Wholesale Goods"
        }
    ],
    "sg:phone":"+32 87 44 84 96",
    "sg:postcode":"4890",
    "sg:province":"Li\u00e8ge",
    "sg:tags":[
        "whol",
        "-",
        "spirit",
        "mfg"
    ],
    "wof:name":"Goffart D Sprl",
    "wof:placetype":"venue"
},
  "geometry": {"coordinates":[5.8726568222,50.6538848877],"type":"Point"}
}