{
  "type": "Feature",
  "properties": {
    "addr:full":"Avenue Schlogel 53ba Ciney Namur 5590",
    "addr:housenumber":"53ba",
    "addr:postcode":"5590",
    "addr:street":"Avenue Schlogel",
    "iso:country":"BE",
    "sg:address":"Avenue Schlogel 53ba",
    "sg:city":"Ciney",
    "sg:orig_category":"M\u00e9decins and sp\u00e9cialistes",
    "sg:phone":"+32 83 21 23 08",
    "sg:postcode":"5590",
    "sg:province":"Namur",
    "wof:name":"Fernand Limet",
    "wof:placetype":"venue"
},
  "geometry": {"coordinates":[5.1083860397,50.2981834412],"type":"Point"}
}