{
  "type": "Feature",
  "properties": {
    "addr:full":"Kortrijksesteenweg 381 Gent Oost-Vlaanderen 9000",
    "addr:housenumber":"381",
    "addr:postcode":"9000",
    "addr:street":"Kortrijksesteenweg;Oost-Vlaanderen",
    "iso:country":"BE",
    "sg:address":"Kortrijksesteenweg 381",
    "sg:city":"Gent",
    "sg:classifiers":[
        {
            "category":"Professional",
            "subcategory":"Lawyer & Legal Services",
            "type":"Services"
        }
    ],
    "sg:phone":"+32 9 245 64 42",
    "sg:postcode":"9000",
    "sg:province":"Oost-Vlaanderen",
    "wof:name":"Van Acker Els",
    "wof:placetype":"venue"
},
  "geometry": {"coordinates":[3.7158210278,51.0374565125],"type":"Point"}
}