{
  "type": "Feature",
  "properties": {
    "addr:full":"Stationsstraat 76 Eeklo Oost-Vlaanderen 9900",
    "addr:housenumber":"76",
    "addr:postcode":"9900",
    "addr:street":"Stationsstraat",
    "iso:country":"BE",
    "sg:address":"Stationsstraat 76",
    "sg:city":"Eeklo",
    "sg:classifiers":[
        {
            "category":"Professional",
            "subcategory":"Art Services",
            "type":"Services"
        }
    ],
    "sg:phone":"+32 9 377 10 54",
    "sg:postcode":"9900",
    "sg:province":"Oost-Vlaanderen",
    "sg:tags":[
        "photographer"
    ],
    "wof:name":"Focilux",
    "wof:placetype":"venue"
},
  "geometry": {"coordinates":[3.5713939667,51.1823425293],"type":"Point"}
}