{
  "type": "Feature",
  "properties": {
    "addr:full":"Chauss\u00c9e De Charleroi 673 Fleurus Hainaut 6220",
    "addr:housenumber":"673",
    "addr:postcode":"6220",
    "addr:street":"Chausse\u0301E De Charleroi",
    "iso:country":"BE",
    "sg:address":"Chauss\u00c9e De Charleroi 673",
    "sg:city":"Fleurus",
    "sg:orig_category":"Meubles D\u00e9taillants, Am\u00e9nagement de B\u00e2timents et de Cuisines",
    "sg:phone":"+32 71 81 37 56",
    "sg:postcode":"6220",
    "sg:province":"Hainaut",
    "wof:name":"Meubles Mobilec",
    "wof:placetype":"venue"
},
  "geometry": {"coordinates":[4.5383300781,50.4679107666],"type":"Point"}
}