{
  "type": "Feature",
  "properties": {
    "addr:full":"Koning Ridderdijk 6 Middelkerke (westende) West-Vlaanderen 8434",
    "addr:housenumber":"6",
    "addr:postcode":"8434",
    "addr:street":"Koning Ridderdijk",
    "iso:country":"BE",
    "sg:address":"Koning Ridderdijk 6",
    "sg:city":"Middelkerke (westende)",
    "sg:classifiers":[
        {
            "category":"Shopping",
            "subcategory":"Bicycles & Sporting Goods",
            "type":"Retail Goods"
        }
    ],
    "sg:phone":"+32 59 30 54 54",
    "sg:postcode":"8434",
    "sg:province":"West-Vlaanderen",
    "sg:tags":[
        "-"
    ],
    "wof:name":"Eddy",
    "wof:placetype":"venue"
},
  "geometry": {"coordinates":[2.7569050789,51.1488685608],"type":"Point"}
}