{
  "type": "Feature",
  "properties": {
    "addr:full":"Baron Ruzettelaan 279 Brugge (assebroek) West-Vlaanderen 8310",
    "addr:housenumber":"279",
    "addr:postcode":"8310",
    "addr:street":"Baron Ruzettelaan",
    "iso:country":"BE",
    "sg:address":"Baron Ruzettelaan 279",
    "sg:city":"Brugge (assebroek)",
    "sg:classifiers":[
        {
            "category":"Home & Garden",
            "subcategory":"Furniture",
            "type":"Retail Goods"
        }
    ],
    "sg:phone":"+32 50 36 36 36",
    "sg:postcode":"8310",
    "sg:province":"West-Vlaanderen",
    "sg:tags":[
        "-"
    ],
    "wof:name":"Duyvejonck Alles Voor Uw Kantoor",
    "wof:placetype":"venue"
},
  "geometry": {"coordinates":[3.2333679199,51.1895484924],"type":"Point"}
}