{
  "type": "Feature",
  "properties": {
    "addr:full":"Rue De La Falise 22 Namur Namur 5000",
    "addr:housenumber":"22",
    "addr:postcode":"5000",
    "addr:street":"Rue De La Falise",
    "iso:country":"BE",
    "sg:address":"Rue De La Falise 22",
    "sg:city":"Namur",
    "sg:classifiers":[
        {
            "category":"Insurance",
            "subcategory":"Life Insurance",
            "type":"Services"
        }
    ],
    "sg:phone":"+32 81 22 26 79",
    "sg:postcode":"5000",
    "sg:province":"Namur",
    "sg:tags":[
        "assurance"
    ],
    "wof:name":"Bureau Bruno Jeulin",
    "wof:placetype":"venue"
},
  "geometry": {"coordinates":[4.8692622185,50.4751396179],"type":"Point"}
}