{
  "type": "Feature",
  "properties": {
    "addr:full":"Rue De March\u00c9 16b3 Nandrin Li\u00e8ge 4550",
    "addr:housenumber":"16b3",
    "addr:postcode":"4550",
    "addr:street":"Rue De Marche\u0301",
    "iso:country":"BE",
    "sg:address":"Rue De March\u00c9 16b3",
    "sg:city":"Nandrin",
    "sg:classifiers":[
        {
            "category":"Shopping",
            "subcategory":"Clothing, Apparel, & Fashions",
            "type":"Retail Goods"
        }
    ],
    "sg:phone":"+32 85 51 37 77",
    "sg:postcode":"4550",
    "sg:province":"Li\u00e8ge",
    "sg:tags":[
        "ondergoed",
        "lingerie"
    ],
    "wof:name":"Comme Un Pr\u00c9ambule",
    "wof:placetype":"venue"
},
  "geometry": {"coordinates":[5.441010952,50.5418548584],"type":"Point"}
}