{
  "type": "Feature",
  "properties": {
    "addr:full":"Koningin Astridplein 26 Kruibeke Oost-Vlaanderen 9150",
    "addr:housenumber":"26",
    "addr:postcode":"9150",
    "addr:street":"Koningin Astridplein",
    "iso:country":"BE",
    "sg:address":"Koningin Astridplein 26",
    "sg:city":"Kruibeke",
    "sg:classifiers":[
        {
            "category":"Shopping Center",
            "type":"Public Place"
        }
    ],
    "sg:phone":"+32 3 744 06 08",
    "sg:postcode":"9150",
    "sg:province":"Oost-Vlaanderen",
    "sg:tags":[
        "enseignement",
        "formation"
    ],
    "wof:name":"Mees & Joni",
    "wof:placetype":"venue"
},
  "geometry": {"coordinates":[4.2996168137,51.1466407776],"type":"Point"}
}