{
  "type": "Feature",
  "properties": {
    "iso:country":"BE",
    "sg:address":"Chauss\u00c9e De Charleroi 96",
    "sg:city":"Namur",
    "sg:classifiers":[
        {
            "category":"Cafe",
            "type":"Food & Drink"
        }
    ],
    "sg:phone":"+32 81 74 65 39",
    "sg:postcode":"5000",
    "sg:province":"Namur",
    "sg:tags":[
        "caf\u00e9s"
    ],
    "wof:name":"Safari Club",
    "wof:placetype":"venue"
},
  "geometry": {"coordinates":[4.8400511742,50.4617881775],"type":"Point"}
}