{
  "type": "Feature",
  "properties": {
    "addr:full":"Godshuisln 13 Roeselare West-Vlaanderen 8800",
    "addr:housenumber":"13",
    "addr:postcode":"8800",
    "addr:street":"Godshuisln",
    "iso:country":"BE",
    "sg:address":"Godshuisln 13",
    "sg:city":"Roeselare",
    "sg:classifiers":[
        {
            "category":"Manufacturing",
            "subcategory":"Chemicals & Compounds",
            "type":"Manufacturing & Wholesale Goods"
        }
    ],
    "sg:phone":"+32 51 24 88 88",
    "sg:postcode":"8800",
    "sg:province":"West-Vlaanderen",
    "sg:tags":[
        "pharmaceutical",
        "chemistry",
        "-",
        "by-product"
    ],
    "wof:name":"Boca-paint Nv",
    "wof:placetype":"venue"
},
  "geometry": {"coordinates":[3.1230149269,50.9443435669],"type":"Point"}
}