{
  "type": "Feature",
  "properties": {
    "addr:full":"Roosendijk 107 Neerpelt Limburg 3910",
    "addr:housenumber":"107",
    "addr:postcode":"3910",
    "iso:country":"BE",
    "sg:address":"Roosendijk 107",
    "sg:city":"Neerpelt",
    "sg:classifiers":[
        {
            "category":"Building & Trades",
            "subcategory":"Construction",
            "type":"Services"
        }
    ],
    "sg:phone":"+32 11 64 92 21",
    "sg:postcode":"3910",
    "sg:province":"Limburg",
    "sg:tags":[
        "installation",
        "-",
        "central",
        "heating"
    ],
    "wof:name":"Hendrikx",
    "wof:placetype":"venue"
},
  "geometry": {"coordinates":[5.4541640282,51.2168083191],"type":"Point"}
}