{
  "type": "Feature",
  "properties": {
    "iso:country":"BE",
    "sg:address":"Avenue E Mounier 87",
    "sg:city":"Brussel/bruxelles",
    "sg:orig_category":"Fitnesscentra Sportcentra Sportclubs Sportterreinen and installaties behalve sportcentra",
    "sg:phone":"+32 2 762 85 22",
    "sg:postcode":"1200",
    "sg:province":"Bruxelles-Capitale",
    "wof:name":"Centre Sportif De La Woluwe",
    "wof:placetype":"venue"
},
  "geometry": {"coordinates":[4.4252500534,50.8438148499],"type":"Point"}
}