{
  "type": "Feature",
  "properties": {
    "iso:country":"BE",
    "sg:address":"Alf. Moerenhoutstraat 67",
    "sg:city":"Overijse",
    "sg:orig_category":"Installation de menuiserie en bois and plastique. Installation de menuiserie m\u00e9tallique",
    "sg:phone":"+32 2 687 42 18",
    "sg:postcode":"3090",
    "sg:province":"Vlaams-Brabant",
    "wof:name":"De Sutter En Zoon",
    "wof:placetype":"venue"
},
  "geometry": {"coordinates":[4.5294489861,50.7654571533],"type":"Point"}
}