{
  "type": "Feature",
  "properties": {
    "addr:full":"Rue Du Ch\u00e2teau Bourlu 6 Ath Hainaut 7800",
    "addr:housenumber":"6",
    "addr:postcode":"7800",
    "addr:street":"Rue Du Cha\u0302Teau Bourlu",
    "iso:country":"BE",
    "sg:address":"Rue Du Ch\u00e2teau Bourlu 6",
    "sg:city":"Ath",
    "sg:classifiers":[
        {
            "category":"Professional",
            "subcategory":"Lawyer & Legal Services",
            "type":"Services"
        }
    ],
    "sg:phone":"+32 68 28 24 76",
    "sg:postcode":"7800",
    "sg:province":"Hainaut",
    "wof:name":"Deramaix Jean",
    "wof:placetype":"venue"
},
  "geometry": {"coordinates":[3.7794981003,50.6311531067],"type":"Point"}
}