{
  "type": "Feature",
  "properties": {
    "addr:full":"Aarschotsesteenweg 58 Tielt-winge Vlaams-Brabant 3390",
    "addr:housenumber":"58",
    "addr:postcode":"3390",
    "addr:street":"Aarschotsesteenweg",
    "iso:country":"BE",
    "sg:address":"Aarschotsesteenweg 58",
    "sg:city":"Tielt-winge",
    "sg:classifiers":[
        {
            "category":"Food & Beverages",
            "subcategory":"Fruits & Vegetables",
            "type":"Retail Goods"
        }
    ],
    "sg:phone":"+32 16 64 04 15",
    "sg:postcode":"3390",
    "sg:province":"Vlaams-Brabant",
    "sg:tags":[
        "l\u00e9gumes"
    ],
    "wof:name":"Versland",
    "wof:placetype":"venue"
},
  "geometry": {"coordinates":[4.8762331009,50.9013748169],"type":"Point"}
}