{
  "type": "Feature",
  "properties": {
    "iso:country":"BE",
    "sg:address":"Boileaulaan 14",
    "sg:city":"Etterbeek/etterbeek",
    "sg:orig_category":"Persagentschappen",
    "sg:phone":"+32 2 735 74 91",
    "sg:postcode":"1040",
    "sg:province":"Bruxelles-Capitale",
    "wof:name":"Robert Taylor",
    "wof:placetype":"venue"
},
  "geometry": {"coordinates":[4.4058470726,50.8321990967],"type":"Point"}
}