{
  "type": "Feature",
  "properties": {
    "addr:full":"Nijverheidslaan 1539 Opglabbeek Limburg 3660",
    "addr:postcode":"1539 opglabbeek;3660",
    "addr:street":"Nijverheidslaan",
    "iso:country":"BE",
    "sg:address":"Nijverheidslaan 1539",
    "sg:city":"Opglabbeek",
    "sg:classifiers":[
        {
            "category":"Building & Trades",
            "subcategory":"Construction",
            "type":"Services"
        }
    ],
    "sg:phone":"+32 89 85 38 62",
    "sg:postcode":"3660",
    "sg:province":"Limburg",
    "sg:tags":[
        "en",
        "la",
        "el\u00e9ments",
        "pour",
        "fab",
        "b\u00e9ton"
    ],
    "wof:name":"Dautzenberg P.",
    "wof:placetype":"venue"
},
  "geometry": {"coordinates":[5.5516600609,51.0441055298],"type":"Point"}
}