{
  "type": "Feature",
  "properties": {
    "addr:full":"Avenue Jules Gathy 10 Grez-doiceau Brabant Wallon 1390",
    "addr:housenumber":"10",
    "addr:postcode":"1390",
    "addr:street":"Avenue Jules Gathy",
    "iso:country":"BE",
    "sg:address":"Avenue Jules Gathy 10",
    "sg:city":"Grez-doiceau",
    "sg:orig_category":"Eleveurs de bovins",
    "sg:phone":"+32 10 84 40 10",
    "sg:postcode":"1390",
    "sg:province":"Brabant Wallon",
    "wof:name":"Michel Socquet",
    "wof:placetype":"venue"
},
  "geometry": {"coordinates":[4.6962428093,50.7626304626],"type":"Point"}
}