{
  "type": "Feature",
  "properties": {
    "addr:full":"Leeuwerikstraat 20 Maaseik Limburg 3680",
    "addr:housenumber":"20",
    "addr:postcode":"3680",
    "addr:street":"Leeuwerikstraat",
    "iso:country":"BE",
    "sg:address":"Leeuwerikstraat 20",
    "sg:city":"Maaseik",
    "sg:orig_category":"Artiestenbureaus",
    "sg:phone":"+32 89 56 75 57",
    "sg:postcode":"3680",
    "sg:province":"Limburg",
    "wof:name":"Maestro Music Productions",
    "wof:placetype":"venue"
},
  "geometry": {"coordinates":[5.8055391312,51.1075706482],"type":"Point"}
}