{
  "type": "Feature",
  "properties": {
    "iso:country":"BE",
    "sg:address":"Rue D'austravant 7b11",
    "sg:city":"Chimay",
    "sg:orig_category":"Baby- and kinderkleding Dameskledingzaken Herenkledingzaken",
    "sg:phone":"+32 60 21 13 28",
    "sg:postcode":"6460",
    "sg:province":"Hainaut",
    "wof:name":"Maison Delid",
    "wof:placetype":"venue"
},
  "geometry": {"coordinates":[4.3145060539,50.0481872559],"type":"Point"}
}