{
  "type": "Feature",
  "properties": {
    "iso:country":"BE",
    "sg:address":"Chemin Des Vall\u00c9es 2",
    "sg:city":"Ath",
    "sg:orig_category":"Entretien and r\u00e9parations de voitures",
    "sg:phone":"+32 68 28 23 70",
    "sg:postcode":"7812",
    "sg:province":"Hainaut",
    "wof:name":"Garage Vanden Avenne",
    "wof:placetype":"venue"
},
  "geometry": {"coordinates":[3.7168750763,50.6487159729],"type":"Point"}
}