{
  "type": "Feature",
  "properties": {
    "addr:full":"Moravie 30 Kortrijk (bissegem) West-Vlaanderen 8501",
    "addr:housenumber":"30",
    "addr:postcode":"8501",
    "addr:street":"Moravie",
    "iso:country":"BE",
    "sg:address":"Moravie 30",
    "sg:city":"Kortrijk (bissegem)",
    "sg:classifiers":[
        {
            "category":"Utilities",
            "subcategory":"Natural Gas",
            "type":"Services"
        }
    ],
    "sg:phone":"+32 56 35 33 67",
    "sg:postcode":"8501",
    "sg:province":"West-Vlaanderen",
    "sg:tags":[
        "apiculture",
        "accessory"
    ],
    "wof:name":"Bijenhof-imkersbedrijf Bvba-sprl",
    "wof:placetype":"venue"
},
  "geometry": {"coordinates":[3.2215340137,50.8127174377],"type":"Point"}
}