{
  "type": "Feature",
  "properties": {
    "addr:full":"Chauss\u00e9e D'andenne 11 Hamois (emptinne) Namur 5363",
    "addr:housenumber":"11",
    "addr:postcode":"5363",
    "addr:street":"Chausse\u0301E D'Andenne",
    "iso:country":"BE",
    "sg:address":"Chauss\u00e9e D'andenne 11",
    "sg:city":"Hamois (emptinne)",
    "sg:classifiers":[
        {
            "category":"Structure",
            "subcategory":"Bridge",
            "type":"Public Place"
        }
    ],
    "sg:phone":"+32 83 61 15 68",
    "sg:postcode":"5363",
    "sg:province":"Namur",
    "sg:tags":[
        "sanitary",
        "cabin",
        "unit"
    ],
    "wof:name":"Camille Warzee Ets",
    "wof:placetype":"venue"
},
  "geometry": {"coordinates":[5.1049118042,50.347038269],"type":"Point"}
}