{
  "type": "Feature",
  "properties": {
    "iso:country":"BE",
    "sg:address":"Kroonlaan 449",
    "sg:city":"Elsene/ixelles",
    "sg:orig_category":"Natuursteenbewerking Speciaalzaken Vloer- and muurbekleding",
    "sg:phone":"+32 2 648 32 40",
    "sg:postcode":"1050",
    "sg:province":"Bruxelles-Capitale",
    "wof:name":"Granibel",
    "wof:placetype":"venue"
},
  "geometry": {"coordinates":[4.3908572197,50.8162612915],"type":"Point"}
}