{
  "type": "Feature",
  "properties": {
    "addr:full":"Graafjanstraat 37 Assenede Oost-Vlaanderen 9961",
    "addr:housenumber":"37",
    "addr:postcode":"9961",
    "addr:street":"Graafjanstraat",
    "iso:country":"BE",
    "sg:address":"Graafjanstraat 37",
    "sg:city":"Assenede",
    "sg:orig_category":"Eleveurs and marchands de porcs",
    "sg:phone":"+32 9 373 78 34",
    "sg:postcode":"9961",
    "sg:province":"Oost-Vlaanderen",
    "wof:name":"Aime Matthijs",
    "wof:placetype":"venue"
},
  "geometry": {"coordinates":[3.7533829212,51.2274360657],"type":"Point"}
}