{
  "type": "Feature",
  "properties": {
    "addr:full":"Maarschalk Plumerlaan 113b Ieper West-Vlaanderen 8900",
    "addr:housenumber":"113b",
    "addr:postcode":"8900",
    "addr:street":"Maarschalk Plumerlaan",
    "iso:country":"BE",
    "sg:address":"Maarschalk Plumerlaan 113b",
    "sg:city":"Ieper",
    "sg:classifiers":[
        {
            "category":"Arena",
            "subcategory":"Sports Club",
            "type":"Entertainment"
        }
    ],
    "sg:phone":"+32 57 20 28 38",
    "sg:postcode":"8900",
    "sg:province":"West-Vlaanderen",
    "wof:name":"Utopia Snookercenter Bvba",
    "wof:placetype":"venue"
},
  "geometry": {"coordinates":[2.8818750381,50.8552055359],"type":"Point"}
}