{
  "type": "Feature",
  "properties": {
    "iso:country":"BE",
    "sg:address":"Rue Saint-pierre 2",
    "sg:city":"Aywaille",
    "sg:orig_category":"Woningbouw",
    "sg:phone":"+32 4 384 52 91",
    "sg:postcode":"4920",
    "sg:province":"Li\u00e8ge",
    "wof:name":"Marijean",
    "wof:placetype":"venue"
},
  "geometry": {"coordinates":[5.676527977,50.4740982056],"type":"Point"}
}