{
  "type": "Feature",
  "properties": {
    "iso:country":"BE",
    "sg:address":"Koningin Elisabethlaan 38",
    "sg:city":"Gent",
    "sg:classifiers":[
        {
            "category":"Professional",
            "subcategory":"Art Services",
            "type":"Services"
        }
    ],
    "sg:phone":"+32 9 230 98 58",
    "sg:postcode":"9000",
    "sg:province":"Oost-Vlaanderen",
    "sg:tags":[
        "photography",
        "reporting",
        "-"
    ],
    "wof:name":"De Lembre A-s",
    "wof:placetype":"venue"
},
  "geometry": {"coordinates":[3.7145519257,51.0376358032],"type":"Point"}
}