{
  "type": "Feature",
  "properties": {
    "iso:country":"BE",
    "sg:address":"Oude Koornmarkt 8",
    "sg:city":"Antwerpen",
    "sg:orig_category":"Brood, gebak and snoepgoed",
    "sg:phone":"+32 3 232 56 34",
    "sg:postcode":"2000",
    "sg:province":"Antwerpen",
    "wof:name":"Pralines Devina",
    "wof:placetype":"venue"
},
  "geometry": {"coordinates":[4.3994531631,51.2204093933],"type":"Point"}
}