{
  "type": "Feature",
  "properties": {
    "addr:full":"Rue Du Laid-patard 6 Nivelles Brabant Wallon 1401",
    "addr:housenumber":"6;1401",
    "addr:street":"Rue Du Laid-Patard",
    "iso:country":"BE",
    "sg:address":"Rue Du Laid-patard 6",
    "sg:city":"Nivelles",
    "sg:orig_category":"Eleveurs de bovins",
    "sg:phone":"+32 67 21 73 70",
    "sg:postcode":"1401",
    "sg:province":"Brabant Wallon",
    "wof:name":"Joel Blockeel",
    "wof:placetype":"venue"
},
  "geometry": {"coordinates":[4.3389229774,50.6186408997],"type":"Point"}
}