{
  "type": "Feature",
  "properties": {
    "iso:country":"BE",
    "sg:address":"Spanjestraat 15",
    "sg:city":"Roeselare",
    "sg:orig_category":"Loodgieterij and centrale verwarming Gh Verhuur bouwmachines",
    "sg:phone":"+32 51 22 84 97",
    "sg:postcode":"8800",
    "sg:province":"West-Vlaanderen",
    "wof:name":"Lefevere",
    "wof:placetype":"venue"
},
  "geometry": {"coordinates":[3.1326129436,50.9468345642],"type":"Point"}
}