{
  "type": "Feature",
  "properties": {
    "iso:country":"BE",
    "sg:address":"Veldstraat 9",
    "sg:city":"Westerlo",
    "sg:orig_category":"Quincailleries",
    "sg:phone":"+32 14 26 47 71",
    "sg:postcode":"2260",
    "sg:province":"Antwerpen",
    "wof:name":"Brico",
    "wof:placetype":"venue"
},
  "geometry": {"coordinates":[4.9112768173,51.0883636475],"type":"Point"}
}