{
  "type": "Feature",
  "properties": {
    "addr:full":"Kleigroeveerf 18 Evere/evere Bruxelles-Capitale 1140",
    "addr:housenumber":"18",
    "addr:postcode":"1140",
    "addr:street":"Kleigroeveerf",
    "iso:country":"BE",
    "sg:address":"Kleigroeveerf 18",
    "sg:city":"Evere/evere",
    "sg:orig_category":"Diverse persoonlijke diensten",
    "sg:phone":"+32 2 705 40 40",
    "sg:postcode":"1140",
    "sg:province":"Bruxelles-Capitale",
    "wof:name":"Maurizio Fiorelli",
    "wof:placetype":"venue"
},
  "geometry": {"coordinates":[4.4154701233,50.8558578491],"type":"Point"}
}