{
  "type": "Feature",
  "properties": {
    "addr:full":"Avenue Des Combattants 54 Ottignies-louvain-la-neuve (ottignies) Brabant Wallon 1340",
    "addr:housenumber":"54",
    "addr:postcode":"1340",
    "addr:street":"Avenue Des Combattants",
    "iso:country":"BE",
    "sg:address":"Avenue Des Combattants 54",
    "sg:city":"Ottignies-louvain-la-neuve (ottignies)",
    "sg:classifiers":[
        {
            "category":"Insurance",
            "subcategory":"Insurance Agent",
            "type":"Services"
        }
    ],
    "sg:phone":"+32 10 41 32 13",
    "sg:postcode":"1340",
    "sg:province":"Brabant Wallon",
    "sg:tags":[
        "broker"
    ],
    "wof:name":"Bidoul Andr\u00e9 Sprl",
    "wof:placetype":"venue"
},
  "geometry": {"coordinates":[4.5686321259,50.667640686],"type":"Point"}
}