{
  "type": "Feature",
  "properties": {
    "addr:full":"Kemelstraat 46 Stekene Oost-Vlaanderen 9190",
    "addr:housenumber":"46",
    "addr:postcode":"9190",
    "addr:street":"Kemelstraat",
    "iso:country":"BE",
    "sg:address":"Kemelstraat 46",
    "sg:city":"Stekene",
    "sg:orig_category":"Non-Classified Establishments",
    "sg:phone":"+32 3 779 84 46",
    "sg:postcode":"9190",
    "sg:province":"Oost-Vlaanderen",
    "wof:name":"Vermeylen W",
    "wof:placetype":"venue"
},
  "geometry": {"coordinates":[4.0355348587,51.2384109497],"type":"Point"}
}