{
  "type": "Feature",
  "properties": {
    "addr:full":"Rue Courtejoie 13f Ciney Namur 5590",
    "addr:housenumber":"13f",
    "addr:postcode":"5590",
    "addr:street":"Rue Courtejoie",
    "iso:country":"BE",
    "sg:address":"Rue Courtejoie 13f",
    "sg:city":"Ciney",
    "sg:classifiers":[
        {
            "category":"Food & Beverages",
            "subcategory":"Chocolate",
            "type":"Retail Goods"
        }
    ],
    "sg:phone":"+32 83 21 63 45",
    "sg:postcode":"5590",
    "sg:province":"Namur",
    "sg:tags":[
        "confectionery",
        "-"
    ],
    "wof:name":"Leonidas",
    "wof:placetype":"venue"
},
  "geometry": {"coordinates":[5.1011338234,50.294921875],"type":"Point"}
}