{
  "type": "Feature",
  "properties": {
    "addr:full":"Kortrijksesteenweg 33 Gent Oost-Vlaanderen 9000",
    "addr:housenumber":"33",
    "addr:postcode":"9000",
    "addr:street":"Kortrijksesteenweg;Oost-Vlaanderen",
    "iso:country":"BE",
    "sg:address":"Kortrijksesteenweg 33",
    "sg:city":"Gent",
    "sg:orig_category":"Bloemen and planten",
    "sg:phone":"+32 9 220 27 37",
    "sg:postcode":"9000",
    "sg:province":"Oost-Vlaanderen",
    "wof:name":"Huis Vivaldi",
    "wof:placetype":"venue"
},
  "geometry": {"coordinates":[3.7180809975,51.0409240723],"type":"Point"}
}