{
  "type": "Feature",
  "properties": {
    "addr:full":"Rue De La Station 39 Florenville Luxembourg 6820",
    "addr:housenumber":"39",
    "addr:postcode":"6820",
    "addr:street":"Rue De La Station",
    "iso:country":"BE",
    "sg:address":"Rue De La Station 39",
    "sg:city":"Florenville",
    "sg:classifiers":[
        {
            "category":"Real Estate",
            "subcategory":"Architect",
            "type":"Services"
        }
    ],
    "sg:phone":"+32 61 31 20 29",
    "sg:postcode":"6820",
    "sg:province":"Luxembourg",
    "wof:name":"Boutefeu Y",
    "wof:placetype":"venue"
},
  "geometry": {"coordinates":[5.3175301552,49.7000770569],"type":"Point"}
}