{
  "type": "Feature",
  "properties": {
    "iso:country":"BE",
    "sg:address":"Maalderijstraat 30",
    "sg:city":"Mortsel",
    "sg:classifiers":[
        {
            "category":"Health Services",
            "subcategory":"Nursing And Care Facility",
            "type":"Services"
        }
    ],
    "sg:phone":"+32 3 216 07 36",
    "sg:postcode":"2640",
    "sg:province":"Antwerpen",
    "sg:tags":[
        "home"
    ],
    "wof:name":"Straetemans G",
    "wof:placetype":"venue"
},
  "geometry": {"coordinates":[4.4587011337,51.1637840271],"type":"Point"}
}