{
  "type": "Feature",
  "properties": {
    "iso:country":"BE",
    "sg:address":"Romestraat 11",
    "sg:city":"Oostende",
    "sg:classifiers":[
        {
            "category":"Museum",
            "type":"Entertainment"
        }
    ],
    "sg:phone":"+32 59 50 81 18",
    "sg:postcode":"8400",
    "sg:province":"West-Vlaanderen",
    "wof:name":"Prov Museum Voor Moderne Kunst",
    "wof:placetype":"venue"
},
  "geometry": {"coordinates":[2.9144320488,51.2256813049],"type":"Point"}
}