{
  "type": "Feature",
  "properties": {
    "iso:country":"BE",
    "sg:address":"Bld De La Sauveni\u00c8re 164",
    "sg:city":"Li\u00c8ge",
    "sg:orig_category":"Dameskledingzaken",
    "sg:phone":"+32 4 232 19 17",
    "sg:postcode":"4000",
    "sg:province":"Li\u00e8ge",
    "wof:name":"Yoann International",
    "wof:placetype":"venue"
},
  "geometry": {"coordinates":[5.5676760674,50.6407241821],"type":"Point"}
}