{
  "type": "Feature",
  "properties": {
    "addr:full":"Rue Richard Vandevelde 114 Bruxelles (schaerbeek) Bruxelles-Capitale 1030",
    "addr:housenumber":"114",
    "addr:postcode":"1030",
    "addr:street":"Rue Richard Vandevelde",
    "iso:country":"BE",
    "sg:address":"Rue Richard Vandevelde 114",
    "sg:city":"Bruxelles (schaerbeek)",
    "sg:orig_category":"Autombile concessionaires",
    "sg:phone":"+32 2 216 49 36",
    "sg:postcode":"1030",
    "sg:province":"Bruxelles-Capitale",
    "wof:name":"St-michel Sprl",
    "wof:placetype":"venue"
},
  "geometry": {"coordinates":[4.3917441368,50.8720169067],"type":"Point"}
}