{
  "type": "Feature",
  "properties": {
    "iso:country":"BE",
    "sg:address":"Avenue Des Sports 57",
    "sg:city":"Leuze-en-hainaut",
    "sg:classifiers":[
        {
            "category":"Cafe",
            "type":"Food & Drink"
        }
    ],
    "sg:phone":"+32 69 66 40 19",
    "sg:postcode":"7900",
    "sg:province":"Hainaut",
    "sg:tags":[
        "caf\u00e9s"
    ],
    "wof:name":"Caf\u00c9 Au Break",
    "wof:placetype":"venue"
},
  "geometry": {"coordinates":[3.6155400276,50.5892829895],"type":"Point"}
}