{
  "type": "Feature",
  "properties": {
    "addr:full":"Rue De Savoie 6 Binche Hainaut 7130",
    "addr:housenumber":"6",
    "addr:postcode":"7130",
    "addr:street":"Rue De Savoie",
    "iso:country":"BE",
    "sg:address":"Rue De Savoie 6",
    "sg:city":"Binche",
    "sg:classifiers":[
        {
            "category":"Education",
            "subcategory":"University",
            "type":"Public Place"
        }
    ],
    "sg:phone":"+32 64 34 20 93",
    "sg:postcode":"7130",
    "sg:province":"Hainaut",
    "sg:tags":[
        "adult"
    ],
    "wof:name":"Institut Sup\u00e9rieur Plus Oultre",
    "wof:placetype":"venue"
},
  "geometry": {"coordinates":[4.1673169136,50.4133644104],"type":"Point"}
}