{
  "type": "Feature",
  "properties": {
    "addr:full":"Gaversesteenweg 883 Merelbeke Oost-Vlaanderen 9820",
    "addr:housenumber":"883",
    "addr:postcode":"9820",
    "addr:street":"Gaversesteenweg",
    "iso:country":"BE",
    "sg:address":"Gaversesteenweg 883",
    "sg:city":"Merelbeke",
    "sg:orig_category":"Agences de marketing",
    "sg:phone":"+32 9 384 96 78",
    "sg:postcode":"9820",
    "sg:province":"Oost-Vlaanderen",
    "wof:name":"Fluor",
    "wof:placetype":"venue"
},
  "geometry": {"coordinates":[3.719219923,50.9737091064],"type":"Point"}
}