{
  "type": "Feature",
  "properties": {
    "iso:country":"BE",
    "sg:address":"Schoterweg 235",
    "sg:city":"Tessenderlo",
    "sg:classifiers":[
        {
            "category":"Bars & Pubs",
            "type":"Food & Drink"
        }
    ],
    "sg:phone":"+32 13 66 13 65",
    "sg:postcode":"3980",
    "sg:province":"Limburg",
    "wof:name":"Hoekske ('t)",
    "wof:placetype":"venue"
},
  "geometry": {"coordinates":[5.0284900665,51.0672798157],"type":"Point"}
}