{
  "type": "Feature",
  "properties": {
    "addr:full":"Route De La Bruy\u00e8re 1 Eghez\u00e9e Namur 5310",
    "addr:housenumber":"1",
    "addr:postcode":"5310",
    "addr:street":"Route De La Bruye\u0300Re;Namur",
    "iso:country":"BE",
    "sg:address":"Route De La Bruy\u00e8re 1",
    "sg:city":"Eghez\u00e9e",
    "sg:classifiers":[
        {
            "category":"Landmark",
            "subcategory":"Memorial",
            "type":"Public Place"
        }
    ],
    "sg:phone":"+32 81 81 31 64",
    "sg:postcode":"5310",
    "sg:province":"Namur",
    "sg:tags":[
        "-",
        "monument"
    ],
    "wof:name":"Art & Sepultures",
    "wof:placetype":"venue"
},
  "geometry": {"coordinates":[4.9113211632,50.585269928],"type":"Point"}
}