{
  "type": "Feature",
  "properties": {
    "iso:country":"BE",
    "sg:address":"Bakkeroothoek 9",
    "sg:city":"Jabbeke",
    "sg:orig_category":"Instituts de beaut\u00e9",
    "sg:phone":"+32 50 39 36 76",
    "sg:postcode":"8490",
    "sg:province":"West-Vlaanderen",
    "wof:name":"Caroline",
    "wof:placetype":"venue"
},
  "geometry": {"coordinates":[3.1400420666,51.1910400391],"type":"Point"}
}