{
  "type": "Feature",
  "properties": {
    "iso:country":"BE",
    "sg:address":"Harensesteenweg 163",
    "sg:city":"Vilvoorde",
    "sg:orig_category":"Kapsalons",
    "sg:phone":"+32 2 251 80 56",
    "sg:postcode":"1800",
    "sg:province":"Vlaams-Brabant",
    "wof:name":"Coiffure Albertine",
    "wof:placetype":"venue"
},
  "geometry": {"coordinates":[4.424246788,50.9197235107],"type":"Point"}
}