{
  "type": "Feature",
  "properties": {
    "iso:country":"BE",
    "sg:address":"Schupstraat 21",
    "sg:city":"Antwerpen",
    "sg:classifiers":[
        {
            "category":"Shopping",
            "subcategory":"Jewelry",
            "type":"Retail Goods"
        }
    ],
    "sg:phone":"+32 3 202 32 90",
    "sg:postcode":"2018",
    "sg:province":"Antwerpen",
    "sg:tags":[
        "diamond",
        "-"
    ],
    "wof:name":"Diatrada",
    "wof:placetype":"venue"
},
  "geometry": {"coordinates":[4.4176988602,51.2143783569],"type":"Point"}
}