{
  "type": "Feature",
  "properties": {
    "iso:country":"BE",
    "sg:address":"Izegemsestraat 412ba",
    "sg:city":"Kortrijk",
    "sg:orig_category":"Produits surgel\u00e9s Gr",
    "sg:phone":"+32 56 37 03 82",
    "sg:postcode":"8501",
    "sg:province":"West-Vlaanderen",
    "wof:name":"Frozen Foods Commercial",
    "wof:placetype":"venue"
},
  "geometry": {"coordinates":[3.2514240742,50.8543510437],"type":"Point"}
}