{
  "type": "Feature",
  "properties": {
    "iso:country":"BE",
    "sg:address":"Leemstraat 160",
    "sg:city":"Sint-katelijne-waver",
    "sg:orig_category":"Producteurs de l\u00e9gumes",
    "sg:phone":"+32 15 75 62 26",
    "sg:postcode":"2861",
    "sg:province":"Antwerpen",
    "wof:name":"Rene Cornelis",
    "wof:placetype":"venue"
},
  "geometry": {"coordinates":[4.595705986,51.0538864136],"type":"Point"}
}