{
  "type": "Feature",
  "properties": {
    "addr:full":"Boomsesteenweg 275-279 Antwerpen Antwerpen 2020",
    "addr:housenumber":"275-279",
    "addr:postcode":"2020",
    "addr:street":"Boomsesteenweg",
    "iso:country":"BE",
    "sg:address":"Boomsesteenweg 275-279",
    "sg:city":"Antwerpen",
    "sg:orig_category":"Supermarkten",
    "sg:postcode":"2020",
    "sg:province":"Antwerpen",
    "wof:name":"Aldi",
    "wof:placetype":"venue"
},
  "geometry": {"coordinates":[4.3877630234,51.1880226135],"type":"Point"}
}