{
  "type": "Feature",
  "properties": {
    "addr:full":"Hegstraat 59 Maasmechelen (boorsem) Limburg 3631",
    "addr:housenumber":"59",
    "addr:postcode":"3631",
    "addr:street":"Hegstraat",
    "iso:country":"BE",
    "sg:address":"Hegstraat 59",
    "sg:city":"Maasmechelen (boorsem)",
    "sg:classifiers":[
        {
            "category":"Parking",
            "subcategory":"Lot",
            "type":"Transportation"
        }
    ],
    "sg:phone":"+32 89 76 07 01",
    "sg:postcode":"3631",
    "sg:province":"Limburg",
    "sg:tags":[
        "parking-places",
        "laying-out"
    ],
    "wof:name":"S De Keyser Bvba",
    "wof:placetype":"venue"
},
  "geometry": {"coordinates":[5.7239232063,50.9423713684],"type":"Point"}
}