{
  "type": "Feature",
  "properties": {
    "addr:full":"Place Verstappen 22 Charleroi Hainaut 6030",
    "addr:housenumber":"22",
    "addr:postcode":"6030",
    "addr:street":"Place Verstappen;Hainaut",
    "iso:country":"BE",
    "sg:address":"Place Verstappen 22",
    "sg:city":"Charleroi",
    "sg:orig_category":"Sportclubs Sportterreinen and installaties behalve sportcentra",
    "sg:phone":"+32 71 51 90 15",
    "sg:postcode":"6030",
    "sg:province":"Hainaut",
    "wof:name":"F.c. Pavillon Dochard",
    "wof:placetype":"venue"
},
  "geometry": {"coordinates":[4.3939700127,50.4006309509],"type":"Point"}
}