{
  "type": "Feature",
  "properties": {
    "iso:country":"BE",
    "sg:address":"Smidsestraat 8",
    "sg:city":"Dendermonde (grembergen)",
    "sg:classifiers":[
        {
            "category":"Building & Trades",
            "subcategory":"Plumbing",
            "type":"Services"
        }
    ],
    "sg:phone":"+32 52 21 85 28",
    "sg:postcode":"9200",
    "sg:province":"Oost-Vlaanderen",
    "sg:tags":[
        "repair",
        "mainten",
        "-",
        "central",
        "heating"
    ],
    "wof:name":"Mouton Gebr",
    "wof:placetype":"venue"
},
  "geometry": {"coordinates":[4.1069588661,51.0539970398],"type":"Point"}
}