{
  "type": "Feature",
  "properties": {
    "addr:full":"Kasteellaan 12 Nevele Oost-Vlaanderen 9850",
    "addr:housenumber":"12",
    "addr:postcode":"9850",
    "addr:street":"Kasteellaan",
    "iso:country":"BE",
    "sg:address":"Kasteellaan 12",
    "sg:city":"Nevele",
    "sg:orig_category":"Elektrische installaties voor woningen",
    "sg:phone":"+32 9 371 71 11",
    "sg:postcode":"9850",
    "sg:province":"Oost-Vlaanderen",
    "wof:name":"Carlos De Vogelaere",
    "wof:placetype":"venue"
},
  "geometry": {"coordinates":[3.5756130219,51.0582847595],"type":"Point"}
}