{
  "type": "Feature",
  "properties": {
    "addr:full":"Rue Neuve 3 Tournai Hainaut 7502",
    "addr:housenumber":"3",
    "addr:postcode":"7502",
    "addr:street":"Rue Neuve",
    "iso:country":"BE",
    "sg:address":"Rue Neuve 3",
    "sg:city":"Tournai",
    "sg:orig_category":"Diverse bouwafwerking and reiniging Gespecialiseerde residenti\u00eble bouw",
    "sg:phone":"+32 69 64 95 07",
    "sg:postcode":"7502",
    "sg:province":"Hainaut",
    "wof:name":"Casterman & Fils",
    "wof:placetype":"venue"
},
  "geometry": {"coordinates":[3.3004410267,50.6235542297],"type":"Point"}
}