{
  "type": "Feature",
  "properties": {
    "addr:full":"Meulebroekenlaan 10b12 Staden West-Vlaanderen 8840",
    "addr:housenumber":"10b12",
    "addr:postcode":"8840",
    "addr:street":"Meulebroekenlaan",
    "iso:country":"BE",
    "sg:address":"Meulebroekenlaan 10b12",
    "sg:city":"Staden",
    "sg:orig_category":"Experts-comptables",
    "sg:phone":"+32 51 20 95 60",
    "sg:postcode":"8840",
    "sg:province":"West-Vlaanderen",
    "wof:name":"Maurits Heemeryck",
    "wof:placetype":"venue"
},
  "geometry": {"coordinates":[3.0617780685,50.9419326782],"type":"Point"}
}