{
  "type": "Feature",
  "properties": {
    "iso:country":"BE",
    "sg:address":"Rue D'ellemelle 43bb",
    "sg:city":"Tinlot",
    "sg:orig_category":"Boekhouders Schoenen",
    "sg:phone":"+32 85 51 21 20",
    "sg:postcode":"4557",
    "sg:province":"Li\u00e8ge",
    "wof:name":"Bernard Panier",
    "wof:placetype":"venue"
},
  "geometry": {"coordinates":[5.4124379158,50.4602584839],"type":"Point"}
}