{
  "type": "Feature",
  "properties": {
    "iso:country":"BE",
    "sg:address":"Kleempstraat 43",
    "sg:city":"Laarne",
    "sg:classifiers":[
        {
            "category":"Professional",
            "subcategory":"Management & Consulting",
            "type":"Services"
        }
    ],
    "sg:phone":"+32 9 366 58 19",
    "sg:postcode":"9270",
    "sg:province":"Oost-Vlaanderen",
    "sg:tags":[
        "-",
        "processing",
        "data",
        "consultant"
    ],
    "wof:name":"Revive Business Bvba",
    "wof:placetype":"venue"
},
  "geometry": {"coordinates":[3.8596129417,51.027961731],"type":"Point"}
}