{
  "type": "Feature",
  "properties": {
    "addr:full":"Henri-joseph Genessestr. 1 Anderlecht Bruxelles-Capitale 1070",
    "addr:housenumber":"1",
    "addr:postcode":"1070",
    "addr:street":"Genessestr.",
    "iso:country":"BE",
    "sg:address":"Henri-joseph Genessestr. 1",
    "sg:city":"Anderlecht",
    "sg:orig_category":"Telecommunicatiesystemen",
    "sg:phone":"+32 2 525 55 50",
    "sg:postcode":"1070",
    "sg:province":"Bruxelles-Capitale",
    "wof:name":"Fa. Tenovis/fe. Tenovis",
    "wof:placetype":"venue"
},
  "geometry": {"coordinates":[4.3105778694,50.8228302002],"type":"Point"}
}