{
  "type": "Feature",
  "properties": {
    "addr:full":"Brusselsesteenweg 420 Wetteren Oost-Vlaanderen 9230",
    "addr:housenumber":"420",
    "addr:postcode":"9230",
    "addr:street":"Brusselsesteenweg",
    "iso:country":"BE",
    "sg:address":"Brusselsesteenweg 420",
    "sg:city":"Wetteren",
    "sg:orig_category":"Travaux de finition and nettoyage de b\u00e2timents. Constructions r\u00e9sidentielles sp\u00e9cifiques",
    "sg:phone":"+32 9 366 47 27",
    "sg:postcode":"9230",
    "sg:province":"Oost-Vlaanderen",
    "wof:name":"Dirk Temmerman",
    "wof:placetype":"venue"
},
  "geometry": {"coordinates":[3.8660490513,50.973865509],"type":"Point"}
}