{
  "type": "Feature",
  "properties": {
    "iso:country":"BE",
    "sg:address":"Lintsesteenweg 141",
    "sg:city":"Hove",
    "sg:classifiers":[
        {
            "category":"Building & Trades",
            "subcategory":"Landscaping Services",
            "type":"Services"
        }
    ],
    "sg:phone":"+32 3 454 44 24",
    "sg:postcode":"2540",
    "sg:province":"Antwerpen",
    "sg:tags":[
        "gardening",
        "garden",
        "maintenance"
    ],
    "wof:name":"Outdoors",
    "wof:placetype":"venue"
},
  "geometry": {"coordinates":[4.4817171097,51.1509170532],"type":"Point"}
}