{
  "type": "Feature",
  "properties": {
    "iso:country":"BE",
    "sg:address":"Rue Houchettes 23",
    "sg:city":"Wellin",
    "sg:classifiers":[
        {
            "category":"Home & Garden",
            "subcategory":"Home Furnishings",
            "type":"Retail Goods"
        }
    ],
    "sg:phone":"+32 84 38 96 70",
    "sg:postcode":"6920",
    "sg:province":"Luxembourg",
    "sg:tags":[
        "-",
        "furniture"
    ],
    "wof:name":"Simon Meubles Sprl",
    "wof:placetype":"venue"
},
  "geometry": {"coordinates":[5.1219758987,50.0791511536],"type":"Point"}
}