{
  "type": "Feature",
  "properties": {
    "addr:full":"Noordstraat 21 Maldegem Oost-Vlaanderen 9990",
    "addr:housenumber":"21",
    "addr:postcode":"9990",
    "addr:street":"Noordstraat",
    "iso:country":"BE",
    "sg:address":"Noordstraat 21",
    "sg:city":"Maldegem",
    "sg:orig_category":"Apotheken",
    "sg:phone":"+32 50 71 13 55",
    "sg:postcode":"9990",
    "sg:province":"Oost-Vlaanderen",
    "wof:name":"Johan Lippens",
    "wof:placetype":"venue"
},
  "geometry": {"coordinates":[3.4481348991,51.2100944519],"type":"Point"}
}