{
  "type": "Feature",
  "properties": {
    "iso:country":"BE",
    "sg:address":"Rue De La Fontaine 9",
    "sg:city":"Charleroi",
    "sg:orig_category":"Boekhouders",
    "sg:phone":"+32 71 32 15 91",
    "sg:postcode":"6031",
    "sg:province":"Hainaut",
    "wof:name":"Cabiaux Pierre-yves",
    "wof:placetype":"venue"
},
  "geometry": {"coordinates":[4.4820709229,50.4011726379],"type":"Point"}
}