{
  "type": "Feature",
  "properties": {
    "addr:full":"Bergenstraat 60 Oostkamp West-Vlaanderen 8020",
    "addr:housenumber":"60",
    "addr:postcode":"8020",
    "addr:street":"Bergenstraat",
    "iso:country":"BE",
    "sg:address":"Bergenstraat 60",
    "sg:city":"Oostkamp",
    "sg:orig_category":"Eleveurs d'animaux domestiques. Transports routiers de marchandises",
    "sg:phone":"+32 50 27 55 37",
    "sg:postcode":"8020",
    "sg:province":"West-Vlaanderen",
    "wof:name":"Haras Hoeve Wiliane",
    "wof:placetype":"venue"
},
  "geometry": {"coordinates":[3.1728839874,51.089515686],"type":"Point"}
}