{
  "type": "Feature",
  "properties": {
    "addr:full":"Winninglaan 13 Temse Oost-Vlaanderen 9140",
    "addr:housenumber":"13",
    "addr:postcode":"9140",
    "addr:street":"Winninglaan",
    "iso:country":"BE",
    "sg:address":"Winninglaan 13",
    "sg:city":"Temse",
    "sg:classifiers":[
        {
            "category":"Autos & Motor Vehicles",
            "subcategory":"Fuel & Gas Station",
            "type":"Retail Goods"
        }
    ],
    "sg:phone":"+32 3 710 95 95",
    "sg:postcode":"9140",
    "sg:province":"Oost-Vlaanderen",
    "sg:tags":[
        "press",
        "industrial"
    ],
    "wof:name":"Phi Technologies Nv",
    "wof:placetype":"venue"
},
  "geometry": {"coordinates":[4.1934452057,51.1354446411],"type":"Point"}
}