{
  "type": "Feature",
  "properties": {
    "addr:full":"Rue Du Laveu 26 Li\u00e8ge 1 Li\u00e8ge 4000",
    "addr:housenumber":"26;1",
    "addr:postcode":"4000",
    "addr:street":"Rue Du Laveu",
    "iso:country":"BE",
    "sg:address":"Rue Du Laveu 26",
    "sg:city":"Li\u00e8ge 1",
    "sg:classifiers":[
        {
            "category":"Banks & Credit Unions",
            "subcategory":"Bank",
            "type":"Services"
        }
    ],
    "sg:phone":"+32 4 252 44 64",
    "sg:postcode":"4000",
    "sg:province":"Li\u00e8ge",
    "sg:tags":[
        "savings-banks"
    ],
    "wof:name":"Centea",
    "wof:placetype":"venue"
},
  "geometry": {"coordinates":[5.5569500923,50.630241394],"type":"Point"}
}