{
  "type": "Feature",
  "properties": {
    "iso:country":"BE",
    "sg:address":"Hofkwartier 19",
    "sg:city":"Herentals",
    "sg:classifiers":[
        {
            "category":"Shopping",
            "subcategory":"Stationery & Office Supplies",
            "type":"Retail Goods"
        }
    ],
    "sg:phone":"+32 14 21 42 42",
    "sg:postcode":"2200",
    "sg:province":"Antwerpen",
    "sg:tags":[
        "-"
    ],
    "wof:name":"De Peuter L & Co Nv",
    "wof:placetype":"venue"
},
  "geometry": {"coordinates":[4.8354492188,51.1785850525],"type":"Point"}
}