{
  "type": "Feature",
  "properties": {
    "iso:country":"BE",
    "sg:address":"Rue Ernest Martel 20",
    "sg:city":"Ecaussinnes",
    "sg:orig_category":"Fotografen and fotostudio's",
    "sg:phone":"+32 67 48 52 17",
    "sg:postcode":"7190",
    "sg:province":"Hainaut",
    "wof:name":"Philippe Tonglet",
    "wof:placetype":"venue"
},
  "geometry": {"coordinates":[4.1650829315,50.5665512085],"type":"Point"}
}