{
  "type": "Feature",
  "properties": {
    "iso:country":"BE",
    "sg:address":"Place Nestor Outer 16",
    "sg:city":"Virton",
    "sg:classifiers":[
        {
            "category":"Shopping",
            "subcategory":"Beauty & Cosmetics",
            "type":"Retail Goods"
        }
    ],
    "sg:phone":"+32 63 58 15 38",
    "sg:postcode":"6760",
    "sg:province":"Luxembourg",
    "sg:tags":[
        "-",
        "perfumery"
    ],
    "wof:name":"Cit\u00e9 Parfumerie (la)",
    "wof:placetype":"venue"
},
  "geometry": {"coordinates":[5.5323262215,49.5676193237],"type":"Point"}
}