{
  "type": "Feature",
  "properties": {
    "addr:full":"Langemarkseweg 23 Ieper West-Vlaanderen 8904",
    "addr:housenumber":"23",
    "addr:postcode":"8904",
    "addr:street":"Langemarkseweg",
    "iso:country":"BE",
    "sg:address":"Langemarkseweg 23",
    "sg:city":"Ieper",
    "sg:orig_category":"Eleveurs and marchands de porcs",
    "sg:phone":"+32 57 48 82 81",
    "sg:postcode":"8904",
    "sg:province":"West-Vlaanderen",
    "wof:name":"Henk Tommelin",
    "wof:placetype":"venue"
},
  "geometry": {"coordinates":[2.8885080814,50.9005088806],"type":"Point"}
}