{
  "type": "Feature",
  "properties": {
    "iso:country":"BE",
    "sg:address":"Rue Nicolas Schnock 2",
    "sg:city":"Arlon",
    "sg:orig_category":"Slagers",
    "sg:phone":"+32 63 22 51 26",
    "sg:postcode":"6700",
    "sg:province":"Luxembourg",
    "wof:name":"Eric Dhaeze",
    "wof:placetype":"venue"
},
  "geometry": {"coordinates":[5.8142871857,49.6858901978],"type":"Point"}
}