{
  "type": "Feature",
  "properties": {
    "addr:full":"Rue Du Castillon 1 La Louviere Hainaut 7100",
    "addr:housenumber":"1",
    "addr:postcode":"7100",
    "addr:street":"Rue Du Castillon",
    "iso:country":"BE",
    "sg:address":"Rue Du Castillon 1",
    "sg:city":"La Louviere",
    "sg:orig_category":"Kruideniers Voedingsspeciaalzaken",
    "sg:phone":"+32 64 28 41 13",
    "sg:postcode":"7100",
    "sg:province":"Hainaut",
    "wof:name":"Rosetta Nuotatore",
    "wof:placetype":"venue"
},
  "geometry": {"coordinates":[4.1850848198,50.4748649597],"type":"Point"}
}