{
  "type": "Feature",
  "properties": {
    "iso:country":"BE",
    "sg:address":"Vleminkstraat 52",
    "sg:city":"Aarschot",
    "sg:orig_category":"Eleveurs de bovins",
    "sg:phone":"+32 16 56 44 38",
    "sg:postcode":"3201",
    "sg:province":"Vlaams-Brabant",
    "wof:name":"Joel Verdonck",
    "wof:placetype":"venue"
},
  "geometry": {"coordinates":[4.8704400063,51.0133934021],"type":"Point"}
}