{
  "type": "Feature",
  "properties": {
    "iso:country":"BE",
    "sg:address":"Eikeldreef 9",
    "sg:city":"Sint-martens-latem",
    "sg:classifiers":[
        {
            "category":"Health Services",
            "subcategory":"Doctor",
            "type":"Services"
        }
    ],
    "sg:phone":"+32 9 282 85 73",
    "sg:postcode":"9830",
    "sg:province":"Oost-Vlaanderen",
    "sg:tags":[
        "medicinephysicians",
        "surgeon"
    ],
    "wof:name":"De Scheerder Ivan",
    "wof:placetype":"venue"
},
  "geometry": {"coordinates":[3.6285200119,51.0175552368],"type":"Point"}
}