{
  "type": "Feature",
  "properties": {
    "addr:full":"Posthoornstraat 36 Beringen Limburg 3580",
    "addr:housenumber":"36",
    "addr:postcode":"3580",
    "addr:street":"Posthoornstraat",
    "iso:country":"BE",
    "sg:address":"Posthoornstraat 36",
    "sg:city":"Beringen",
    "sg:orig_category":"Magasins de r\u00e9parations d'articles personnels et m\u00e9nagers divers. V\u00eatements sur mesure Fab",
    "sg:phone":"+32 11 45 42 60",
    "sg:postcode":"3580",
    "sg:province":"Limburg",
    "wof:name":"Gaby's Sartory",
    "wof:placetype":"venue"
},
  "geometry": {"coordinates":[5.2275710106,51.0489006042],"type":"Point"}
}