{
  "type": "Feature",
  "properties": {
    "addr:full":"Poederleesteenweg 90 Kasterlee Antwerpen 2460",
    "addr:housenumber":"90",
    "addr:postcode":"2460",
    "addr:street":"Poederleesteenweg",
    "iso:country":"BE",
    "sg:address":"Poederleesteenweg 90",
    "sg:city":"Kasterlee",
    "sg:orig_category":"Goederenvervoer over de weg",
    "sg:phone":"+32 14 55 23 25",
    "sg:postcode":"2460",
    "sg:province":"Antwerpen",
    "wof:name":"E. Claes - Verwimp",
    "wof:placetype":"venue"
},
  "geometry": {"coordinates":[4.9671049118,51.2406616211],"type":"Point"}
}