{
  "type": "Feature",
  "properties": {
    "iso:country":"BE",
    "sg:address":"Albert I Laan 75",
    "sg:city":"Nieuwpoort",
    "sg:orig_category":"Kapsalons",
    "sg:phone":"+32 58 24 00 17",
    "sg:postcode":"8620",
    "sg:province":"West-Vlaanderen",
    "wof:name":"Coiffure Maracasa",
    "wof:placetype":"venue"
},
  "geometry": {"coordinates":[2.7333099842,51.1423377991],"type":"Point"}
}