{
  "type": "Feature",
  "properties": {
    "addr:full":"Avenue Montefiore 86 Esneux Li\u00e8ge 4130",
    "addr:housenumber":"86",
    "addr:postcode":"4130",
    "addr:street":"Avenue Montefiore",
    "iso:country":"BE",
    "sg:address":"Avenue Montefiore 86",
    "sg:city":"Esneux",
    "sg:classifiers":[
        {
            "category":"Home & Garden",
            "subcategory":"Carpets & Floor Coverings",
            "type":"Retail Goods"
        }
    ],
    "sg:phone":"+32 4 380 48 18",
    "sg:postcode":"4130",
    "sg:province":"Li\u00e8ge",
    "sg:tags":[
        "layer",
        "mosaicists"
    ],
    "wof:name":"Van Bossuyt Thierry & Fils-socatil",
    "wof:placetype":"venue"
},
  "geometry": {"coordinates":[5.558054924,50.5319290161],"type":"Point"}
}