{
  "type": "Feature",
  "properties": {
    "addr:full":"Pieter Pourbusstraat 7 Brugge West-Vlaanderen 8000",
    "addr:housenumber":"7",
    "addr:postcode":"8000",
    "addr:street":"Pieter Pourbusstraat",
    "iso:country":"BE",
    "sg:address":"Pieter Pourbusstraat 7",
    "sg:city":"Brugge",
    "sg:classifiers":[
        {
            "category":"Health Services",
            "subcategory":"Health Practitioner",
            "type":"Services"
        }
    ],
    "sg:phone":"+32 50 33 55 35",
    "sg:postcode":"8000",
    "sg:province":"West-Vlaanderen",
    "sg:tags":[
        "physiotherapist"
    ],
    "wof:name":"Vanooteghem H",
    "wof:placetype":"venue"
},
  "geometry": {"coordinates":[3.22301507,51.2119598389],"type":"Point"}
}