{
  "type": "Feature",
  "properties": {
    "addr:full":"Beekstraat 14 Gent Oost-Vlaanderen 9030",
    "addr:housenumber":"14",
    "addr:postcode":"9030",
    "addr:street":"Beekstraat;Oost-Vlaanderen",
    "iso:country":"BE",
    "sg:address":"Beekstraat 14",
    "sg:city":"Gent",
    "sg:orig_category":"Boekhouders",
    "sg:phone":"+32 9 227 03 23",
    "sg:postcode":"9030",
    "sg:province":"Oost-Vlaanderen",
    "wof:name":"Eddie Schaut",
    "wof:placetype":"venue"
},
  "geometry": {"coordinates":[3.6628320217,51.073764801],"type":"Point"}
}