{
  "type": "Feature",
  "properties": {
    "iso:country":"BE",
    "sg:address":"Rue Du Pr\u00c9au 5",
    "sg:city":"Bernissart",
    "sg:orig_category":"Caravanes and remorques. Terrains de camping",
    "sg:phone":"+32 69 57 71 14",
    "sg:postcode":"7321",
    "sg:province":"Hainaut",
    "wof:name":"Camping Du Preau",
    "wof:placetype":"venue"
},
  "geometry": {"coordinates":[3.6735908985,50.4789962769],"type":"Point"}
}