{
  "type": "Feature",
  "properties": {
    "iso:country":"BE",
    "sg:address":"Rue Du Luxembourg 93a",
    "sg:city":"Marche-en-famenne",
    "sg:classifiers":[
        {
            "category":"Banks & Credit Unions",
            "subcategory":"Financial Services",
            "type":"Services"
        }
    ],
    "sg:phone":"+32 84 31 10 45",
    "sg:postcode":"6900",
    "sg:province":"Luxembourg",
    "sg:tags":[
        "loan",
        "mortgage"
    ],
    "wof:name":"Parisse & Pochet",
    "wof:placetype":"venue"
},
  "geometry": {"coordinates":[5.345925808,50.2204208374],"type":"Point"}
}