{
  "type": "Feature",
  "properties": {
    "iso:country":"BE",
    "sg:address":"Rue Du Ruisseau 1",
    "sg:city":"Arlon",
    "sg:orig_category":"Rundveehouders",
    "sg:phone":"+32 63 22 57 92",
    "sg:postcode":"6700",
    "sg:province":"Luxembourg",
    "wof:name":"Georges Nerenhausen",
    "wof:placetype":"venue"
},
  "geometry": {"coordinates":[5.8401532173,49.6812133789],"type":"Point"}
}