{
  "type": "Feature",
  "properties": {
    "addr:full":"Wilstraat 37 Tongeren (rutten) Limburg 3700",
    "addr:housenumber":"37",
    "addr:postcode":"3700",
    "addr:street":"Wilstraat",
    "iso:country":"BE",
    "sg:address":"Wilstraat 37",
    "sg:city":"Tongeren (rutten)",
    "sg:classifiers":[
        {
            "category":"Food & Beverages",
            "subcategory":"Meat & Fish",
            "type":"Retail Goods"
        }
    ],
    "sg:phone":"+32 12 23 16 51",
    "sg:postcode":"3700",
    "sg:province":"Limburg",
    "sg:tags":[
        "-",
        "livestock"
    ],
    "wof:name":"Loverix Nv",
    "wof:placetype":"venue"
},
  "geometry": {"coordinates":[5.4636240005,50.7807197571],"type":"Point"}
}