{
  "type": "Feature",
  "properties": {
    "iso:country":"BE",
    "sg:address":"Rue De La Chav\u00e9e 10",
    "sg:city":"Couvin (frasnes)",
    "sg:classifiers":[
        {
            "category":"Retail",
            "subcategory":"Funeral Services",
            "type":"Services"
        }
    ],
    "sg:phone":"+32 60 31 13 35",
    "sg:postcode":"5660",
    "sg:province":"Namur",
    "sg:tags":[
        "director"
    ],
    "wof:name":"Gilson-bourtembourg Fun\u00e9raille Sprl",
    "wof:placetype":"venue"
},
  "geometry": {"coordinates":[4.5056061745,50.0815238953],"type":"Point"}
}