{
  "type": "Feature",
  "properties": {
    "addr:full":"Avenue Albert 197 Vorst/forest Bruxelles-Capitale 1190",
    "addr:housenumber":"197",
    "addr:postcode":"1190",
    "addr:street":"Avenue Albert;/ Forest",
    "iso:country":"BE",
    "sg:address":"Avenue Albert 197",
    "sg:city":"Vorst/forest",
    "sg:orig_category":"M\u00e9decins and sp\u00e9cialistes",
    "sg:phone":"+32 2 346 01 88",
    "sg:postcode":"1190",
    "sg:province":"Bruxelles-Capitale",
    "wof:name":"Fran\u00c7oise De Moor",
    "wof:placetype":"venue"
},
  "geometry": {"coordinates":[4.3460860252,50.8169555664],"type":"Point"}
}