{
  "type": "Feature",
  "properties": {
    "iso:country":"BE",
    "sg:address":"Achterstraat 22a",
    "sg:city":"Evergem",
    "sg:classifiers":[
        {
            "category":"Park",
            "subcategory":"Town Common",
            "type":"Public Place"
        }
    ],
    "sg:phone":"+32 9 344 61 98",
    "sg:postcode":"9940",
    "sg:province":"Oost-Vlaanderen",
    "sg:tags":[
        "caf\u00e9s",
        "animation",
        "diverses"
    ],
    "wof:name":"Eddy Wally",
    "wof:placetype":"venue"
},
  "geometry": {"coordinates":[3.7453079224,51.1804084778],"type":"Point"}
}