{
  "type": "Feature",
  "properties": {
    "iso:country":"BE",
    "sg:address":"Zijlaan 11",
    "sg:city":"Ukkel/uccle",
    "sg:orig_category":"Installatie van houten of kunststof schrijnwerk Installatie van metalen schrijnwerk",
    "sg:phone":"+32 2 375 23 79",
    "sg:postcode":"1180",
    "sg:province":"Bruxelles-Capitale",
    "wof:name":"Aluconfort",
    "wof:placetype":"venue"
},
  "geometry": {"coordinates":[4.3727788925,50.7965202332],"type":"Point"}
}