{
  "type": "Feature",
  "properties": {
    "addr:full":"Kallobaan 218 Beveren (beveren-waas) Oost-Vlaanderen 9120",
    "addr:housenumber":"218",
    "addr:postcode":"9120",
    "addr:street":"Beveren Beveren-Waas Oost-Vlaanderen",
    "iso:country":"BE",
    "sg:address":"Kallobaan 218",
    "sg:city":"Beveren (beveren-waas)",
    "sg:orig_category":"Newspapers, magazines, periodicals - Distribution",
    "sg:phone":"+32 3 775 64 13",
    "sg:postcode":"9120",
    "sg:province":"Oost-Vlaanderen",
    "wof:name":"Van Hove H",
    "wof:placetype":"venue"
},
  "geometry": {"coordinates":[4.2558631897,51.2226028442],"type":"Point"}
}