{
  "type": "Feature",
  "properties": {
    "addr:full":"Boulevard D'anvers 15 Brussel/bruxelles Bruxelles-Capitale 1000",
    "addr:housenumber":"15",
    "addr:postcode":"1000",
    "addr:street":"Boulevard D'Anvers;/",
    "iso:country":"BE",
    "sg:address":"Boulevard D'anvers 15",
    "sg:city":"Brussel/bruxelles",
    "sg:classifiers":[
        {
            "category":"Fast Food",
            "type":"Food & Drink"
        }
    ],
    "sg:phone":"+32 2 217 71 82",
    "sg:postcode":"1000",
    "sg:province":"Bruxelles-Capitale",
    "sg:tags":[
        "\u00c0",
        "restaurants",
        "emporter",
        "restaurant"
    ],
    "wof:name":"Restaurant Paros",
    "wof:placetype":"venue"
},
  "geometry": {"coordinates":[4.3536581993,50.8563156128],"type":"Point"}
}