{
  "type": "Feature",
  "properties": {
    "addr:full":"Achilles Musschestraat 67 Gent Oost-Vlaanderen 9000",
    "addr:housenumber":"67",
    "addr:postcode":"9000",
    "addr:street":"Musschestraat;Oost-Vlaanderen",
    "iso:country":"BE",
    "sg:address":"Achilles Musschestraat 67",
    "sg:city":"Gent",
    "sg:classifiers":[
        {
            "category":"Health Services",
            "subcategory":"Dentist",
            "type":"Services"
        }
    ],
    "sg:phone":"+32 9 221 17 38",
    "sg:postcode":"9000",
    "sg:province":"Oost-Vlaanderen",
    "wof:name":"De Craene Genevieve",
    "wof:placetype":"venue"
},
  "geometry": {"coordinates":[3.7226469517,51.0320854187],"type":"Point"}
}