{
  "type": "Feature",
  "properties": {
    "iso:country":"BE",
    "sg:address":"Steenweg 17",
    "sg:city":"Alken",
    "sg:orig_category":"Epiceries",
    "sg:phone":"+32 11 31 62 82",
    "sg:postcode":"3570",
    "sg:province":"Limburg",
    "wof:name":"Sylvain Engelen",
    "wof:placetype":"venue"
},
  "geometry": {"coordinates":[5.2706098557,50.8781585693],"type":"Point"}
}