{
  "type": "Feature",
  "properties": {
    "addr:full":"Diesterbaan 37 Herentals Antwerpen 2200",
    "addr:housenumber":"37",
    "addr:postcode":"2200",
    "addr:street":"Diesterbaan",
    "iso:country":"BE",
    "sg:address":"Diesterbaan 37",
    "sg:city":"Herentals",
    "sg:orig_category":"Dakwerken",
    "sg:phone":"+32 14 26 23 14",
    "sg:postcode":"2200",
    "sg:province":"Antwerpen",
    "wof:name":"W.p.n. Onderhoudswerken",
    "wof:placetype":"venue"
},
  "geometry": {"coordinates":[4.8420681953,51.1335144043],"type":"Point"}
}