{
  "type": "Feature",
  "properties": {
    "iso:country":"BE",
    "sg:address":"Ieperstraat 216",
    "sg:city":"Staden",
    "sg:orig_category":"Eleveurs and marchands de porcs",
    "sg:phone":"+32 51 70 13 02",
    "sg:postcode":"8840",
    "sg:province":"West-Vlaanderen",
    "wof:name":"Vandamme Walter & Annie",
    "wof:placetype":"venue"
},
  "geometry": {"coordinates":[2.9869909286,50.9535713196],"type":"Point"}
}