{
  "type": "Feature",
  "properties": {
    "addr:full":"Stenenkruisbosweg 1 Rotselaar (wezemaal) Vlaams-Brabant 3111",
    "addr:housenumber":"1",
    "addr:postcode":"3111",
    "addr:street":"Stenenkruisbosweg",
    "iso:country":"BE",
    "sg:address":"Stenenkruisbosweg 1",
    "sg:city":"Rotselaar (wezemaal)",
    "sg:classifiers":[
        {
            "category":"Cafe",
            "type":"Food & Drink"
        }
    ],
    "sg:phone":"+32 16 58 13 18",
    "sg:postcode":"3111",
    "sg:province":"Vlaams-Brabant",
    "sg:tags":[
        "snack-bars"
    ],
    "wof:name":"Piccolo",
    "wof:placetype":"venue"
},
  "geometry": {"coordinates":[4.7547087669,50.9484176636],"type":"Point"}
}