{
  "type": "Feature",
  "properties": {
    "iso:country":"BE",
    "sg:address":"Rue Paul Pastur 11",
    "sg:city":"Ath",
    "sg:orig_category":"Algemeen secundair onderwijs Technisch and beroeps secundair onderwijs",
    "sg:phone":"+32 68 26 46 50",
    "sg:postcode":"7800",
    "sg:province":"Hainaut",
    "wof:name":"Inst. Prov. Ens. Second.",
    "wof:placetype":"venue"
},
  "geometry": {"coordinates":[3.7749519348,50.6228103638],"type":"Point"}
}