{
  "type": "Feature",
  "properties": {
    "iso:country":"BE",
    "sg:address":"Rue De L'echauffouree 11",
    "sg:city":"Mouscron",
    "sg:classifiers":[
        {
            "category":"Shopping",
            "subcategory":"Luggage & Leather Goods",
            "type":"Retail Goods"
        }
    ],
    "sg:phone":"+32 56 33 05 07",
    "sg:postcode":"7700",
    "sg:province":"Hainaut",
    "sg:tags":[
        "container",
        "air-freight"
    ],
    "wof:name":"Transfluvia Nv",
    "wof:placetype":"venue"
},
  "geometry": {"coordinates":[3.1822490692,50.7528762817],"type":"Point"}
}