{
  "type": "Feature",
  "properties": {
    "addr:full":"Stoktsestraat 46 Turnhout Antwerpen 2300",
    "addr:housenumber":"46",
    "addr:postcode":"2300",
    "addr:street":"Stoktsestraat",
    "iso:country":"BE",
    "sg:address":"Stoktsestraat 46",
    "sg:city":"Turnhout",
    "sg:orig_category":"Epiceries",
    "sg:phone":"+32 14 41 31 34",
    "sg:postcode":"2300",
    "sg:province":"Antwerpen",
    "wof:name":"Segers A. & Destenay H.",
    "wof:placetype":"venue"
},
  "geometry": {"coordinates":[4.9159269333,51.326259613],"type":"Point"}
}