{
  "type": "Feature",
  "properties": {
    "iso:country":"BE",
    "sg:address":"Gen. Baron Jacquesstraat 59",
    "sg:city":"Diksmuide",
    "sg:classifiers":[
        {
            "category":"Shopping",
            "subcategory":"Clothing, Apparel, & Fashions",
            "type":"Retail Goods"
        }
    ],
    "sg:phone":"+32 51 50 04 66",
    "sg:postcode":"8600",
    "sg:province":"West-Vlaanderen",
    "sg:tags":[
        "v\u00eatements",
        "pour",
        "dame"
    ],
    "wof:name":"Boetiek Guiny",
    "wof:placetype":"venue"
},
  "geometry": {"coordinates":[2.8602190018,51.0335044861],"type":"Point"}
}