{
  "type": "Feature",
  "properties": {
    "addr:full":"Florivalstraat 18 Huldenberg (ottenburg) Vlaams-Brabant 3040",
    "addr:housenumber":"18",
    "addr:postcode":"3040",
    "addr:street":"Florivalstraat",
    "iso:country":"BE",
    "sg:address":"Florivalstraat 18",
    "sg:city":"Huldenberg (ottenburg)",
    "sg:classifiers":[
        {
            "category":"Fast Food",
            "type":"Food & Drink"
        }
    ],
    "sg:phone":"+32 16 47 16 08",
    "sg:postcode":"3040",
    "sg:province":"Vlaams-Brabant",
    "sg:tags":[
        "fried",
        "stand",
        "potato"
    ],
    "wof:name":"Richard",
    "wof:placetype":"venue"
},
  "geometry": {"coordinates":[4.6227259636,50.7541389465],"type":"Point"}
}