{
  "type": "Feature",
  "properties": {
    "addr:full":"Herdersstraat 71ba Roeselare West-Vlaanderen 8800",
    "addr:housenumber":"71ba",
    "addr:postcode":"8800",
    "addr:street":"Herdersstraat",
    "iso:country":"BE",
    "sg:address":"Herdersstraat 71ba",
    "sg:city":"Roeselare",
    "sg:orig_category":"Installatie van houten of kunststof schrijnwerk",
    "sg:phone":"+32 51 20 35 30",
    "sg:postcode":"8800",
    "sg:province":"West-Vlaanderen",
    "wof:name":"Gebroeders Vandecappelle",
    "wof:placetype":"venue"
},
  "geometry": {"coordinates":[3.143611908,50.9400062561],"type":"Point"}
}