{
  "type": "Feature",
  "properties": {
    "addr:full":"Het Laar 4 Lille (gierle) Antwerpen 2275",
    "addr:housenumber":"4",
    "addr:postcode":"2275",
    "addr:street":"Het Laar",
    "iso:country":"BE",
    "sg:address":"Het Laar 4",
    "sg:city":"Lille (gierle)",
    "sg:classifiers":[
        {
            "category":"Shopping",
            "subcategory":"Books",
            "type":"Retail Goods"
        }
    ],
    "sg:phone":"+32 14 44 01 61",
    "sg:postcode":"2275",
    "sg:province":"Antwerpen",
    "sg:tags":[
        "bookseller"
    ],
    "wof:name":"Books & Home",
    "wof:placetype":"venue"
},
  "geometry": {"coordinates":[4.862994194,51.2854995728],"type":"Point"}
}