{
  "type": "Feature",
  "properties": {
    "addr:full":"Rue Du M\u00e9ny 5 Esneux (tilff) Li\u00e8ge 4130",
    "addr:housenumber":"5",
    "addr:postcode":"4130",
    "addr:street":"Rue Du Me\u0301Ny",
    "iso:country":"BE",
    "sg:address":"Rue Du M\u00e9ny 5",
    "sg:city":"Esneux (tilff)",
    "sg:classifiers":[
        {
            "category":"Health Services",
            "subcategory":"Doctor",
            "type":"Services"
        }
    ],
    "sg:phone":"+32 4 388 28 46",
    "sg:postcode":"4130",
    "sg:province":"Li\u00e8ge",
    "sg:tags":[
        "medicinephysicians",
        "surgeon"
    ],
    "wof:name":"Martin Didier",
    "wof:placetype":"venue"
},
  "geometry": {"coordinates":[5.5963168144,50.5603141785],"type":"Point"}
}