{
  "type": "Feature",
  "properties": {
    "iso:country":"BE",
    "sg:address":"Rue Des Chass. Ardennais 27",
    "sg:city":"Leglise",
    "sg:orig_category":"Epiceries",
    "sg:phone":"+32 63 60 01 82",
    "sg:postcode":"6860",
    "sg:province":"Luxembourg",
    "wof:name":"S. Lemaire",
    "wof:placetype":"venue"
},
  "geometry": {"coordinates":[5.5912618637,49.8548164368],"type":"Point"}
}