{
  "type": "Feature",
  "properties": {
    "addr:full":"Voorne 47 Zoersel Antwerpen 2980",
    "addr:housenumber":"47",
    "addr:postcode":"2980",
    "addr:street":"Voorne",
    "iso:country":"BE",
    "sg:address":"Voorne 47",
    "sg:city":"Zoersel",
    "sg:classifiers":[
        {
            "category":"Professional",
            "subcategory":"Management & Consulting",
            "type":"Services"
        }
    ],
    "sg:phone":"+32 3 385 02 34",
    "sg:postcode":"2980",
    "sg:province":"Antwerpen",
    "sg:tags":[
        "tax-consultants"
    ],
    "wof:name":"Meesters Ch",
    "wof:placetype":"venue"
},
  "geometry": {"coordinates":[4.713435173,51.269985199],"type":"Point"}
}