{
  "type": "Feature",
  "properties": {
    "iso:country":"BE",
    "sg:address":"Malmedyerstrasse 20",
    "sg:city":"B\u00dctgenbach/b\u00dctgenbach",
    "sg:orig_category":"RESTAURANTS: RESTAURANTS FAST FOOD AND \u00c0 EMPORTER. CAF\u00c9S",
    "sg:phone":"+32 80 44 59 49",
    "sg:postcode":"4750",
    "sg:province":"Li\u00e8ge",
    "wof:name":"Au Rendez-vous",
    "wof:placetype":"venue"
},
  "geometry": {"coordinates":[6.2206501961,50.457408905],"type":"Point"}
}