{
  "type": "Feature",
  "properties": {
    "iso:country":"BE",
    "sg:address":"Mechelsesteenweg 2",
    "sg:city":"Mortsel",
    "sg:orig_category":"RESTAURANTS: CAF\u00c9S",
    "sg:phone":"+32 3 449 68 50",
    "sg:postcode":"2640",
    "sg:province":"Antwerpen",
    "wof:name":"Taverne Tivoli",
    "wof:placetype":"venue"
},
  "geometry": {"coordinates":[4.4500808716,51.1695404053],"type":"Point"}
}