{
  "type": "Feature",
  "properties": {
    "addr:full":"Stationsstraat 127 Deerlijk West-Vlaanderen 8540",
    "addr:housenumber":"127",
    "addr:postcode":"8540",
    "addr:street":"Stationsstraat",
    "iso:country":"BE",
    "sg:address":"Stationsstraat 127",
    "sg:city":"Deerlijk",
    "sg:orig_category":"Kapsalons",
    "sg:phone":"+32 56 77 53 34",
    "sg:postcode":"8540",
    "sg:province":"West-Vlaanderen",
    "wof:name":"Coiffure Chris & Claudine",
    "wof:placetype":"venue"
},
  "geometry": {"coordinates":[3.3510129452,50.8464317322],"type":"Point"}
}