{
  "type": "Feature",
  "properties": {
    "addr:full":"Avenue De Nancy 39 Li\u00e8ge 1 (li\u00e8ge 2) Li\u00e8ge 4020",
    "addr:housenumber":"39;1;2",
    "addr:postcode":"4020",
    "addr:street":"Avenue De Nancy",
    "iso:country":"BE",
    "sg:address":"Avenue De Nancy 39",
    "sg:city":"Li\u00e8ge 1 (li\u00e8ge 2)",
    "sg:classifiers":[
        {
            "category":"Fast Food",
            "type":"Food & Drink"
        }
    ],
    "sg:phone":"+32 4 344 19 68",
    "sg:postcode":"4020",
    "sg:province":"Li\u00e8ge",
    "sg:tags":[
        "fried",
        "stand",
        "potato"
    ],
    "wof:name":"Louis Friterie",
    "wof:placetype":"venue"
},
  "geometry": {"coordinates":[5.6014909744,50.6453323364],"type":"Point"}
}