{
  "type": "Feature",
  "properties": {
    "iso:country":"BE",
    "sg:address":"Fond De Bondry 20b1",
    "sg:city":"Ottignies-louvain-la-neuve",
    "sg:classifiers":[
        {
            "category":"Arena",
            "subcategory":"Sports Club",
            "type":"Entertainment"
        }
    ],
    "sg:phone":"+32 10 40 03 12",
    "sg:postcode":"1342",
    "sg:province":"Brabant Wallon",
    "sg:tags":[
        "de"
    ],
    "wof:name":"F.o.h.c.-u.c.l.",
    "wof:placetype":"venue"
},
  "geometry": {"coordinates":[4.571475029,50.6792144775],"type":"Point"}
}