{
  "type": "Feature",
  "properties": {
    "iso:country":"BE",
    "sg:address":"Kapelleveldstraat 8",
    "sg:city":"Erpe-mere",
    "sg:orig_category":"Plomberie, chauffage and installations sanitaires",
    "sg:phone":"+32 53 83 17 48",
    "sg:postcode":"9420",
    "sg:province":"Oost-Vlaanderen",
    "wof:name":"Luc Redant",
    "wof:placetype":"venue"
},
  "geometry": {"coordinates":[3.9703280926,50.9159431458],"type":"Point"}
}