{
  "type": "Feature",
  "properties": {
    "iso:country":"BE",
    "sg:address":"Bruno'sstraat 31",
    "sg:city":"Oud-turnhout",
    "sg:orig_category":"Eleveurs de bovins",
    "sg:phone":"+32 14 41 32 58",
    "sg:postcode":"2360",
    "sg:province":"Antwerpen",
    "wof:name":"Frans Hertogs",
    "wof:placetype":"venue"
},
  "geometry": {"coordinates":[4.9868969917,51.3333625793],"type":"Point"}
}