{
  "type": "Feature",
  "properties": {
    "addr:full":"Rue De La Coul\u00c9e 26a Trois-ponts Li\u00e8ge 4983",
    "addr:housenumber":"26a",
    "addr:postcode":"4983",
    "addr:street":"Rue De La Coule\u0301E",
    "iso:country":"BE",
    "sg:address":"Rue De La Coul\u00c9e 26a",
    "sg:city":"Trois-ponts",
    "sg:orig_category":"Vakantiehuizen",
    "sg:phone":"+32 80 68 46 60",
    "sg:postcode":"4983",
    "sg:province":"Li\u00e8ge",
    "wof:name":"D. Counson",
    "wof:placetype":"venue"
},
  "geometry": {"coordinates":[5.8275151253,50.3570747375],"type":"Point"}
}