{
  "type": "Feature",
  "properties": {
    "iso:country":"BE",
    "sg:address":"Verkortingstraat 11",
    "sg:city":"Leuven",
    "sg:orig_category":"Vertalers and tolken",
    "sg:phone":"+32 16 20 79 38",
    "sg:postcode":"3000",
    "sg:province":"Vlaams-Brabant",
    "wof:name":"Babes Rodica",
    "wof:placetype":"venue"
},
  "geometry": {"coordinates":[4.69977808,50.8691558838],"type":"Point"}
}