{
  "type": "Feature",
  "properties": {
    "iso:country":"BE",
    "sg:address":"Rue Cayauderie 50",
    "sg:city":"Charleroi",
    "sg:orig_category":"Brood, gebak and snoepgoed",
    "sg:phone":"+32 71 41 84 52",
    "sg:postcode":"6000",
    "sg:province":"Hainaut",
    "wof:name":"P\u00c2tisserie Fauquet",
    "wof:placetype":"venue"
},
  "geometry": {"coordinates":[4.458840847,50.4230461121],"type":"Point"}
}