{
  "type": "Feature",
  "properties": {
    "iso:country":"BE",
    "sg:address":"Lindestraat 100",
    "sg:city":"Zottegem",
    "sg:orig_category":"Onderdelen and accessoires voor auto's Telecommunicatieapparaten",
    "sg:phone":"+32 9 360 46 45",
    "sg:postcode":"9620",
    "sg:province":"Oost-Vlaanderen",
    "wof:name":"Car Technics",
    "wof:placetype":"venue"
},
  "geometry": {"coordinates":[3.8112111092,50.871181488],"type":"Point"}
}