{
  "type": "Feature",
  "properties": {
    "iso:country":"BE",
    "sg:address":"Lijsterweg 3",
    "sg:city":"Nijlen",
    "sg:classifiers":[
        {
            "category":"Shopping",
            "subcategory":"Jewelry",
            "type":"Retail Goods"
        }
    ],
    "sg:phone":"+32 3 480 12 96",
    "sg:postcode":"2560",
    "sg:province":"Antwerpen",
    "sg:tags":[
        "fab",
        "bijou"
    ],
    "wof:name":"August Lens",
    "wof:placetype":"venue"
},
  "geometry": {"coordinates":[4.619820118,51.1526222229],"type":"Point"}
}