{
  "type": "Feature",
  "properties": {
    "addr:full":"Spoorwegstraat 2 Ingelmunster West-Vlaanderen 8770",
    "addr:housenumber":"2",
    "addr:postcode":"8770",
    "addr:street":"Spoorwegstraat",
    "iso:country":"BE",
    "sg:address":"Spoorwegstraat 2",
    "sg:city":"Ingelmunster",
    "sg:orig_category":"HUISBRANDOLIE",
    "sg:phone":"+32 51 30 24 57",
    "sg:postcode":"8770",
    "sg:province":"West-Vlaanderen",
    "wof:name":"Brandstoffen Windels",
    "wof:placetype":"venue"
},
  "geometry": {"coordinates":[3.2548089027,50.9132575989],"type":"Point"}
}