{
  "type": "Feature",
  "properties": {
    "addr:full":"Trapstraat 2 Zottegem Oost-Vlaanderen 9620",
    "addr:housenumber":"2",
    "addr:postcode":"9620",
    "addr:street":"Trapstraat",
    "iso:country":"BE",
    "sg:address":"Trapstraat 2",
    "sg:city":"Zottegem",
    "sg:classifiers":[
        {
            "category":"Real Estate",
            "subcategory":"Architect",
            "type":"Services"
        }
    ],
    "sg:phone":"+32 9 360 04 34",
    "sg:postcode":"9620",
    "sg:province":"Oost-Vlaanderen",
    "wof:name":"Michiels I",
    "wof:placetype":"venue"
},
  "geometry": {"coordinates":[3.8104600906,50.8688163757],"type":"Point"}
}