{
  "type": "Feature",
  "properties": {
    "addr:full":"Vloedstraat 15 Roeselare West-Vlaanderen 8800",
    "addr:housenumber":"15",
    "addr:postcode":"8800",
    "addr:street":"Vloedstraat",
    "iso:country":"BE",
    "sg:address":"Vloedstraat 15",
    "sg:city":"Roeselare",
    "sg:classifiers":[
        {
            "category":"Manufacturing",
            "subcategory":"Metals",
            "type":"Manufacturing & Wholesale Goods"
        }
    ],
    "sg:phone":"+32 51 24 83 51",
    "sg:postcode":"8800",
    "sg:province":"West-Vlaanderen",
    "sg:tags":[
        "work",
        "sheet"
    ],
    "wof:name":"Intec Bvba",
    "wof:placetype":"venue"
},
  "geometry": {"coordinates":[3.1540699005,50.9727096558],"type":"Point"}
}