{
  "type": "Feature",
  "properties": {
    "iso:country":"BE",
    "sg:address":"T\u00b4kintstraat 1",
    "sg:city":"Brussel/bruxelles",
    "sg:orig_category":"Dansscholen",
    "sg:phone":"+32 2 511 11 01",
    "sg:postcode":"1000",
    "sg:province":"Bruxelles-Capitale",
    "wof:name":"Four You-4 U",
    "wof:placetype":"venue"
},
  "geometry": {"coordinates":[4.3432350159,50.8478813171],"type":"Point"}
}