{
  "type": "Feature",
  "properties": {
    "addr:full":"Beekstraat 20 Oud-heverlee Vlaams-Brabant 3051",
    "addr:housenumber":"20",
    "addr:postcode":"3051",
    "addr:street":"Beekstraat",
    "iso:country":"BE",
    "sg:address":"Beekstraat 20",
    "sg:city":"Oud-heverlee",
    "sg:orig_category":"M\u00e9decins and sp\u00e9cialistes",
    "sg:phone":"+32 16 47 73 06",
    "sg:postcode":"3051",
    "sg:province":"Vlaams-Brabant",
    "wof:name":"M. Boeykens",
    "wof:placetype":"venue"
},
  "geometry": {"coordinates":[4.6502971649,50.8029251099],"type":"Point"}
}