{
  "type": "Feature",
  "properties": {
    "addr:full":"Renbaanlaan 122 Elsene/ixelles Bruxelles-Capitale 1050",
    "addr:housenumber":"122",
    "addr:postcode":"1050",
    "addr:street":"Renbaanlaan",
    "iso:country":"BE",
    "sg:address":"Renbaanlaan 122",
    "sg:city":"Elsene/ixelles",
    "sg:orig_category":"Opsporingsdiensten and detectivebureaus",
    "sg:phone":"+32 2 647 47 81",
    "sg:postcode":"1050",
    "sg:province":"Bruxelles-Capitale",
    "wof:name":"Robert Louvigny",
    "wof:placetype":"venue"
},
  "geometry": {"coordinates":[4.3767261505,50.820980072],"type":"Point"}
}