{
  "type": "Feature",
  "properties": {
    "iso:country":"BE",
    "sg:address":"Kapelstraat 31",
    "sg:city":"Pellenberg",
    "sg:classifiers":[
        {
            "category":"Wholesale",
            "subcategory":"Farm Supplies",
            "type":"Manufacturing & Wholesale Goods"
        }
    ],
    "sg:phone":"+32 16 62 21 77",
    "sg:postcode":"3212",
    "sg:province":"Vlaams-Brabant",
    "sg:tags":[
        "-",
        "machine",
        "equipment",
        "engineering",
        "machinery",
        "mechanical",
        "agriculture"
    ],
    "wof:name":"Ver Pasteels Hans & Dirk",
    "wof:placetype":"venue"
},
  "geometry": {"coordinates":[4.7935709953,50.8767051697],"type":"Point"}
}