{
  "type": "Feature",
  "properties": {
    "iso:country":"BE",
    "sg:address":"gapaardstraat 37",
    "sg:city":"Ardooie",
    "sg:classifiers":[
        {
            "category":"Professional",
            "subcategory":"Computer Services",
            "type":"Services"
        }
    ],
    "sg:postcode":"8850",
    "sg:tags":[
        "webhosting",
        "domainnames",
        "it-consultancy"
    ],
    "sg:website":"http://www.surion.be",
    "wof:name":"Surion",
    "wof:placetype":"venue"
},
  "geometry": {"coordinates":[3.172488,50.965653],"type":"Point"}
}