{
  "type": "Feature",
  "properties": {
    "iso:country":"BE",
    "sg:address":"Heeldstraat 67",
    "sg:city":"Genk",
    "sg:classifiers":[
        {
            "category":"Insurance",
            "subcategory":"Insurance Agent",
            "type":"Services"
        }
    ],
    "sg:phone":"+32 89 36 78 01",
    "sg:postcode":"3600",
    "sg:province":"Limburg",
    "sg:tags":[
        "broker"
    ],
    "wof:name":"Klaps E",
    "wof:placetype":"venue"
},
  "geometry": {"coordinates":[5.5286879539,50.9726982117],"type":"Point"}
}