{
  "type": "Feature",
  "properties": {
    "iso:country":"BE",
    "sg:address":"Pittemsestraat 58d",
    "sg:city":"Ardooie",
    "sg:classifiers":[
        {
            "category":"Professional",
            "subcategory":"Engineering",
            "type":"Services"
        }
    ],
    "sg:phone":"+32 51 46 64 77",
    "sg:postcode":"8850",
    "sg:province":"West-Vlaanderen",
    "sg:tags":[
        "precision"
    ],
    "wof:name":"Vitalo Tech Center",
    "wof:placetype":"venue"
},
  "geometry": {"coordinates":[3.2355899811,50.9813652039],"type":"Point"}
}