{
  "type": "Feature",
  "properties": {
    "addr:full":"Leuvensesteenweg 115 Boortmeerbeek Vlaams-Brabant 3191",
    "addr:housenumber":"115",
    "addr:postcode":"3191",
    "addr:street":"Leuvensesteenweg",
    "iso:country":"BE",
    "sg:address":"Leuvensesteenweg 115",
    "sg:city":"Boortmeerbeek",
    "sg:classifiers":[
        {
            "category":"Fast Food",
            "type":"Food & Drink"
        }
    ],
    "sg:phone":"+32 15 52 07 20",
    "sg:postcode":"3191",
    "sg:province":"Vlaams-Brabant",
    "sg:tags":[
        "\u00c0",
        "restaurants",
        "emporter",
        "restaurant"
    ],
    "wof:name":"Greenfield's",
    "wof:placetype":"venue"
},
  "geometry": {"coordinates":[4.545363903,50.9862976074],"type":"Point"}
}