{
  "type": "Feature",
  "properties": {
    "iso:country":"BE",
    "sg:address":"Kievitstraat 43",
    "sg:city":"Hamont-achel (hamont)",
    "sg:classifiers":[
        {
            "category":"Utilities",
            "subcategory":"Sewage",
            "type":"Services"
        }
    ],
    "sg:phone":"+32 11 44 74 58",
    "sg:postcode":"3930",
    "sg:province":"Limburg",
    "sg:tags":[
        "acoustic",
        "consultant"
    ],
    "wof:name":"Keizer & Partners Lawaaibestrijding Bvba",
    "wof:placetype":"venue"
},
  "geometry": {"coordinates":[5.5450549126,51.2511863708],"type":"Point"}
}