{
  "type": "Feature",
  "properties": {
    "iso:country":"BE",
    "sg:address":"Heiendestr 18",
    "sg:city":"Lokeren",
    "sg:orig_category":"Kapsalons",
    "sg:phone":"+32 9 348 24 30",
    "sg:postcode":"9160",
    "sg:province":"Oost-Vlaanderen",
    "wof:name":"Gianni's Kapsalon",
    "wof:placetype":"venue"
},
  "geometry": {"coordinates":[3.9577410221,51.0856628418],"type":"Point"}
}