{
  "type": "Feature",
  "properties": {
    "addr:full":"Velodromstraat 106 Liedekerke Vlaams-Brabant 1770",
    "addr:housenumber":"106",
    "addr:postcode":"1770",
    "addr:street":"Velodromstraat;Vlaams-Brabant",
    "iso:country":"BE",
    "sg:address":"Velodromstraat 106",
    "sg:city":"Liedekerke",
    "sg:orig_category":"Woningbouw",
    "sg:phone":"+32 53 66 45 35",
    "sg:postcode":"1770",
    "sg:province":"Vlaams-Brabant",
    "wof:name":"Gvh Construct",
    "wof:placetype":"venue"
},
  "geometry": {"coordinates":[4.0936088562,50.8672180176],"type":"Point"}
}