{
  "type": "Feature",
  "properties": {
    "addr:full":"Grand-rue 33 Morlanwelz Hainaut 7140",
    "addr:housenumber":"33",
    "addr:postcode":"7140",
    "addr:street":"Grand-Rue",
    "iso:country":"BE",
    "sg:address":"Grand-rue 33",
    "sg:city":"Morlanwelz",
    "sg:orig_category":"Apotheken",
    "sg:phone":"+32 64 44 21 87",
    "sg:postcode":"7140",
    "sg:province":"Hainaut",
    "wof:name":"Pharmacie Familia",
    "wof:placetype":"venue"
},
  "geometry": {"coordinates":[4.2448129654,50.4553451538],"type":"Point"}
}