{
  "type": "Feature",
  "properties": {
    "addr:full":"Avenue D'azebois 102 Charleroi (gosselies) Hainaut 6041",
    "addr:housenumber":"102",
    "addr:postcode":"6041",
    "addr:street":"Avenue D'Azebois",
    "iso:country":"BE",
    "sg:address":"Avenue D'azebois 102",
    "sg:city":"Charleroi (gosselies)",
    "sg:classifiers":[
        {
            "category":"Health Services",
            "subcategory":"Doctor",
            "type":"Services"
        }
    ],
    "sg:phone":"+32 71 35 37 22",
    "sg:postcode":"6041",
    "sg:province":"Hainaut",
    "sg:tags":[
        "medicinephysicians",
        "surgeon"
    ],
    "wof:name":"Honnorez M",
    "wof:placetype":"venue"
},
  "geometry": {"coordinates":[4.425716877,50.4735145569],"type":"Point"}
}