{
  "type": "Feature",
  "properties": {
    "addr:full":"Rue Du M\u00d4le 14 Braine-l\u00b4alleud Brabant Wallon 1420",
    "addr:housenumber":"14",
    "addr:postcode":"1420",
    "addr:street":"Rue Du Mo\u0302Le;Brabant Wallon",
    "iso:country":"BE",
    "sg:address":"Rue Du M\u00d4le 14",
    "sg:city":"Braine-l\u00b4alleud",
    "sg:orig_category":"Schoenen",
    "sg:phone":"+32 2 384 62 48",
    "sg:postcode":"1420",
    "sg:province":"Brabant Wallon",
    "wof:name":"Capucine",
    "wof:placetype":"venue"
},
  "geometry": {"coordinates":[4.3708639145,50.6841850281],"type":"Point"}
}