{
  "type": "Feature",
  "properties": {
    "iso:country":"BE",
    "sg:address":"Oostendse Baan 6",
    "sg:city":"Gistel",
    "sg:orig_category":"Journaux. Tabac. Jeux de hasard. Blanchisseries and teintureries",
    "sg:phone":"+32 59 27 93 59",
    "sg:postcode":"8470",
    "sg:province":"West-Vlaanderen",
    "wof:name":"De Kiosk",
    "wof:placetype":"venue"
},
  "geometry": {"coordinates":[2.9537529945,51.1498184204],"type":"Point"}
}