{
  "type": "Feature",
  "properties": {
    "iso:country":"BE",
    "sg:address":"Heidestraat 40",
    "sg:city":"Destelbergen (heusden)",
    "sg:classifiers":[
        {
            "category":"Utilities",
            "subcategory":"Natural Gas",
            "type":"Services"
        }
    ],
    "sg:phone":"+32 9 230 30 67",
    "sg:postcode":"9070",
    "sg:province":"Oost-Vlaanderen",
    "sg:tags":[
        "welding"
    ],
    "wof:name":"Bovyn E",
    "wof:placetype":"venue"
},
  "geometry": {"coordinates":[3.8054900169,51.0322799683],"type":"Point"}
}