{
  "type": "Feature",
  "properties": {
    "addr:full":"Reinaertgalerij 32 Sint-niklaas Oost-Vlaanderen 9100",
    "addr:housenumber":"32",
    "addr:postcode":"9100",
    "addr:street":"Reinaertgalerij",
    "iso:country":"BE",
    "sg:address":"Reinaertgalerij 32",
    "sg:city":"Sint-niklaas",
    "sg:classifiers":[
        {
            "category":"Tea Room",
            "subcategory":"None",
            "type":"Food & Drink"
        }
    ],
    "sg:phone":"+32 3 766 39 40",
    "sg:postcode":"9100",
    "sg:province":"Oost-Vlaanderen",
    "wof:name":"Julie's",
    "wof:placetype":"venue"
},
  "geometry": {"coordinates":[4.1516499519,51.150138855],"type":"Point"}
}