{
  "type": "Feature",
  "properties": {
    "addr:full":"Blarenbergln 21 Mechelen Antwerpen 2800",
    "addr:housenumber":"21",
    "addr:postcode":"2800",
    "addr:street":"Blarenbergln",
    "iso:country":"BE",
    "sg:address":"Blarenbergln 21",
    "sg:city":"Mechelen",
    "sg:classifiers":[
        {
            "category":"Wholesale",
            "subcategory":"Drugs",
            "type":"Manufacturing & Wholesale Goods"
        }
    ],
    "sg:phone":"+32 15 29 49 50",
    "sg:postcode":"2800",
    "sg:province":"Antwerpen",
    "sg:tags":[
        "chemical",
        "pharmaceutical"
    ],
    "wof:name":"Internatio Nv",
    "wof:placetype":"venue"
},
  "geometry": {"coordinates":[4.4509840012,51.0521621704],"type":"Point"}
}