{
  "type": "Feature",
  "properties": {
    "iso:country":"BE",
    "sg:address":"Avenue Parc Scientifique 0",
    "sg:city":"Frameries",
    "sg:classifiers":[
        {
            "category":"Wholesale",
            "subcategory":"Sporting Goods",
            "type":"Manufacturing & Wholesale Goods"
        }
    ],
    "sg:phone":"+32 65 67 40 73",
    "sg:postcode":"7080",
    "sg:province":"Hainaut",
    "sg:tags":[
        "sport-",
        "kampeermateriaal"
    ],
    "wof:name":"Mons Nautic",
    "wof:placetype":"venue"
},
  "geometry": {"coordinates":[3.9013249874,50.4052352905],"type":"Point"}
}