{
  "type": "Feature",
  "properties": {
    "addr:full":"Bossaersstraat 71 Brasschaat Antwerpen 2930",
    "addr:housenumber":"71",
    "addr:postcode":"2930",
    "addr:street":"Bossaersstraat",
    "iso:country":"BE",
    "sg:address":"Bossaersstraat 71",
    "sg:city":"Brasschaat",
    "sg:classifiers":[
        {
            "category":"Building & Trades",
            "subcategory":"Construction",
            "type":"Services"
        }
    ],
    "sg:phone":"+32 3 633 23 24",
    "sg:postcode":"2930",
    "sg:province":"Antwerpen",
    "sg:tags":[
        "ceiling"
    ],
    "wof:name":"Bevam Cvba",
    "wof:placetype":"venue"
},
  "geometry": {"coordinates":[4.5235562325,51.3218154907],"type":"Point"}
}