{
  "type": "Feature",
  "properties": {
    "iso:country":"BE",
    "sg:address":"La Place 8",
    "sg:city":"Corroy-le-grand",
    "sg:classifiers":[
        {
            "category":"Building & Trades",
            "subcategory":"Construction",
            "type":"Services"
        }
    ],
    "sg:phone":"+32 475 60 90 04",
    "sg:postcode":"1325",
    "sg:province":"Brabant Wallon",
    "sg:tags":[
        "surveyor",
        "-"
    ],
    "wof:name":"Aas Consult Sprl",
    "wof:placetype":"venue"
},
  "geometry": {"coordinates":[4.6509628296,50.6799812317],"type":"Point"}
}