{
  "type": "Feature",
  "properties": {
    "iso:country":"BE",
    "sg:address":"Turnhoutsebaan 343",
    "sg:city":"Antwerpen",
    "sg:classifiers":[
        {
            "category":"Farming",
            "subcategory":"Livestock Farm",
            "type":"Manufacturing & Wholesale Goods"
        }
    ],
    "sg:phone":"+32 58 22 39 00",
    "sg:postcode":"2140",
    "sg:province":"Antwerpen",
    "sg:tags":[
        "breeding",
        "agriculture",
        "animal"
    ],
    "wof:name":"Gadus Nv",
    "wof:placetype":"venue"
},
  "geometry": {"coordinates":[2.764508009,51.1287498474],"type":"Point"}
}