{
  "type": "Feature",
  "properties": {
    "addr:full":"Rue Du Jardinage 44 Sint-agatha-berchem/berchem-sainte-agathe Bruxelles-Capitale 1082",
    "addr:housenumber":"44",
    "addr:postcode":"1082",
    "addr:street":"Rue Du Jardinage;/",
    "iso:country":"BE",
    "sg:address":"Rue Du Jardinage 44",
    "sg:city":"Sint-agatha-berchem/berchem-sainte-agathe",
    "sg:orig_category":"M\u00e9decins and sp\u00e9cialistes",
    "sg:phone":"+32 2 468 07 87",
    "sg:postcode":"1082",
    "sg:province":"Bruxelles-Capitale",
    "wof:name":"C. Van Hoecke",
    "wof:placetype":"venue"
},
  "geometry": {"coordinates":[4.2955269814,50.8555908203],"type":"Point"}
}