{
  "type": "Feature",
  "properties": {
    "iso:country":"BE",
    "sg:address":"Generaal De Ceuninckstraat 139",
    "sg:city":"Mechelen",
    "sg:classifiers":[
        {
            "category":"Health Services",
            "subcategory":"Dentist",
            "type":"Services"
        }
    ],
    "sg:phone":"+32 15 20 88 37",
    "sg:postcode":"2800",
    "sg:province":"Antwerpen",
    "wof:name":"Hens L Mevr",
    "wof:placetype":"venue"
},
  "geometry": {"coordinates":[4.476831913,51.0356216431],"type":"Point"}
}