{
  "type": "Feature",
  "properties": {
    "addr:full":"Oordegemkouter 118 Lede Oost-Vlaanderen 9340",
    "addr:housenumber":"118",
    "addr:postcode":"9340",
    "addr:street":"Oordegemkouter",
    "iso:country":"BE",
    "sg:address":"Oordegemkouter 118",
    "sg:city":"Lede",
    "sg:orig_category":"Producteurs de l\u00e9gumes",
    "sg:phone":"+32 9 369 34 43",
    "sg:postcode":"9340",
    "sg:province":"Oost-Vlaanderen",
    "wof:name":"Andre Keppens",
    "wof:placetype":"venue"
},
  "geometry": {"coordinates":[3.9100899696,50.9613456726],"type":"Point"}
}