{
  "type": "Feature",
  "properties": {
    "addr:full":"Grand-place 5 Paliseul Luxembourg 6850",
    "addr:housenumber":"5",
    "addr:postcode":"6850",
    "addr:street":"Grand-Place",
    "iso:country":"BE",
    "sg:address":"Grand-place 5",
    "sg:city":"Paliseul",
    "sg:orig_category":"Epiceries",
    "sg:phone":"+32 61 53 36 76",
    "sg:postcode":"6850",
    "sg:province":"Luxembourg",
    "wof:name":"Louis Delhaize",
    "wof:placetype":"venue"
},
  "geometry": {"coordinates":[5.1353559494,49.9033088684],"type":"Point"}
}