{
  "type": "Feature",
  "properties": {
    "addr:full":"Molenstraat 71 Aalst Oost-Vlaanderen 9300",
    "addr:housenumber":"71",
    "addr:postcode":"9300",
    "addr:street":"Molenstraat",
    "iso:country":"BE",
    "sg:address":"Molenstraat 71",
    "sg:city":"Aalst",
    "sg:orig_category":"Eclairage et \u00e9quipements du foyer. Art and fournitures artistiques",
    "sg:phone":"+32 53 71 09 18",
    "sg:postcode":"9300",
    "sg:province":"Oost-Vlaanderen",
    "wof:name":"Inlijstingen New Style",
    "wof:placetype":"venue"
},
  "geometry": {"coordinates":[4.0429859161,50.9396781921],"type":"Point"}
}