{
  "type": "Feature",
  "properties": {
    "addr:full":"Gladiolenstraat 30 Box 1 Roeselare West-Vlaanderen 8800",
    "addr:housenumber":"30;1",
    "addr:postcode":"8800",
    "addr:street":"Gladiolenstraat;Box",
    "iso:country":"BE",
    "sg:address":"Gladiolenstraat 30 Box 1",
    "sg:city":"Roeselare",
    "sg:classifiers":[
        {
            "category":"Arts & Performance",
            "subcategory":"Music",
            "type":"Entertainment"
        }
    ],
    "sg:phone":"+32 51 24 06 64",
    "sg:postcode":"8800",
    "sg:province":"West-Vlaanderen",
    "sg:tags":[
        "disc-jockeys"
    ],
    "wof:name":"Anders Met Klank",
    "wof:placetype":"venue"
},
  "geometry": {"coordinates":[3.1316270828,50.9408302307],"type":"Point"}
}