{
  "type": "Feature",
  "properties": {
    "addr:full":"Chauss\u00c9e De Bruxelles 170 Charleroi Hainaut 6040",
    "addr:housenumber":"170",
    "addr:postcode":"6040",
    "addr:street":"Chausse\u0301E De Bruxelles;Hainaut",
    "iso:country":"BE",
    "sg:address":"Chauss\u00c9e De Bruxelles 170",
    "sg:city":"Charleroi",
    "sg:orig_category":"Souvenirs and objets artisanaux",
    "sg:phone":"+32 71 35 97 02",
    "sg:postcode":"6040",
    "sg:province":"Hainaut",
    "wof:name":"Sechi",
    "wof:placetype":"venue"
},
  "geometry": {"coordinates":[4.4373779297,50.4422569275],"type":"Point"}
}