{
  "type": "Feature",
  "properties": {
    "addr:full":"Chauss\u00e9e De Gand 1220 Bruxelles (berchem-sainte-agathe) Bruxelles-Capitale 1082",
    "addr:postcode":"1220;berchem-sainte-agathe;1082",
    "addr:street":"Chausse\u0301E De Gand",
    "iso:country":"BE",
    "sg:address":"Chauss\u00e9e De Gand 1220",
    "sg:city":"Bruxelles (berchem-sainte-agathe)",
    "sg:classifiers":[
        {
            "category":"Personal",
            "subcategory":"Barber",
            "type":"Services"
        }
    ],
    "sg:phone":"+32 2 469 28 65",
    "sg:postcode":"1082",
    "sg:province":"Bruxelles-Capitale",
    "sg:tags":[
        "gentleman",
        "salon",
        "-",
        "hairdressing"
    ],
    "wof:name":"Bastin Coiffure",
    "wof:placetype":"venue"
},
  "geometry": {"coordinates":[4.2955961227,50.8657035828],"type":"Point"}
}