{
  "type": "Feature",
  "properties": {
    "addr:full":"Rue St.donat 1 Mettet Namur 5640",
    "addr:housenumber":"1",
    "addr:postcode":"5640",
    "addr:street":"Rue St.Donat",
    "iso:country":"BE",
    "sg:address":"Rue St.donat 1",
    "sg:city":"Mettet",
    "sg:orig_category":"Benzinestations and brandstoffen Caf\u00e9s",
    "sg:phone":"+32 71 72 77 70",
    "sg:postcode":"5640",
    "sg:province":"Namur",
    "wof:name":"Esso",
    "wof:placetype":"venue"
},
  "geometry": {"coordinates":[4.6573610306,50.303981781],"type":"Point"}
}