{
  "type": "Feature",
  "properties": {
    "addr:full":"Rue Joseph Wauters 8 Estinnes (haulchin) Hainaut 7120",
    "addr:housenumber":"8",
    "addr:postcode":"7120",
    "addr:street":"Rue Joseph Wauters",
    "iso:country":"BE",
    "sg:address":"Rue Joseph Wauters 8",
    "sg:city":"Estinnes (haulchin)",
    "sg:classifiers":[
        {
            "category":"Health Services",
            "subcategory":"Health Practitioner",
            "type":"Services"
        }
    ],
    "sg:phone":"+32 65 59 01 01",
    "sg:postcode":"7120",
    "sg:province":"Hainaut",
    "sg:tags":[
        "physiotherapist"
    ],
    "wof:name":"Miroir Fran\u00e7oise",
    "wof:placetype":"venue"
},
  "geometry": {"coordinates":[4.0845069885,50.3864326477],"type":"Point"}
}