{
  "type": "Feature",
  "properties": {
    "iso:country":"BE",
    "sg:address":"Voskenslaan 137",
    "sg:city":"Gand",
    "sg:orig_category":"Traitement and rev\u00eatement des m\u00e9taux. Quincaillerie Gr",
    "sg:phone":"+32 9 222 31 12",
    "sg:postcode":"9000",
    "sg:province":"Oost-Vlaanderen",
    "wof:name":"Levin",
    "wof:placetype":"venue"
},
  "geometry": {"coordinates":[3.7070150375,51.0313911438],"type":"Point"}
}