{
  "type": "Feature",
  "properties": {
    "addr:full":"Rue Du Bultia 40 Gerpinnes Hainaut 6280",
    "addr:housenumber":"40",
    "addr:postcode":"6280",
    "addr:street":"Rue Du Bultia;Hainaut",
    "iso:country":"BE",
    "sg:address":"Rue Du Bultia 40",
    "sg:city":"Gerpinnes",
    "sg:orig_category":"Elektrische installaties voor woningen",
    "sg:phone":"+32 71 21 35 12",
    "sg:postcode":"6280",
    "sg:province":"Hainaut",
    "wof:name":"Freddy Cordemans",
    "wof:placetype":"venue"
},
  "geometry": {"coordinates":[4.474793911,50.3436164856],"type":"Point"}
}