{
  "type": "Feature",
  "properties": {
    "addr:full":"Chauss\u00e9e De Vleurgat 272 Bruxelles (ixelles) Bruxelles-Capitale 1050",
    "addr:housenumber":"272",
    "addr:postcode":"1050",
    "addr:street":"Chausse\u0301E De Vleurgat",
    "iso:country":"BE",
    "sg:address":"Chauss\u00e9e De Vleurgat 272",
    "sg:city":"Bruxelles (ixelles)",
    "sg:classifiers":[
        {
            "category":"Home & Garden",
            "subcategory":"Home Furnishings",
            "type":"Retail Goods"
        }
    ],
    "sg:phone":"+32 2 647 32 03",
    "sg:postcode":"1050",
    "sg:province":"Bruxelles-Capitale",
    "sg:tags":[
        "interior",
        "decoration"
    ],
    "wof:name":"Emporium Decoration",
    "wof:placetype":"venue"
},
  "geometry": {"coordinates":[4.3663840294,50.8189964294],"type":"Point"}
}