{
  "type": "Feature",
  "properties": {
    "addr:full":"Rue De Goz\u00e9e 30 Montigny-le-tilleul Hainaut 6110",
    "addr:housenumber":"30",
    "addr:postcode":"6110",
    "addr:street":"Rue De Goze\u0301E",
    "iso:country":"BE",
    "sg:address":"Rue De Goz\u00e9e 30",
    "sg:city":"Montigny-le-tilleul",
    "sg:classifiers":[
        {
            "category":"Shopping",
            "subcategory":"Antiques",
            "type":"Retail Goods"
        }
    ],
    "sg:phone":"+32 71 56 14 84",
    "sg:postcode":"6110",
    "sg:province":"Hainaut",
    "wof:name":"Antiquit\u00e9s Europ\u00e9ennes",
    "wof:placetype":"venue"
},
  "geometry": {"coordinates":[4.385863781,50.390007019],"type":"Point"}
}