{
  "type": "Feature",
  "properties": {
    "addr:full":"Rue Fran\u00c7ois Andr\u00c9 279 Quaregnon Hainaut 7390",
    "addr:housenumber":"279",
    "addr:postcode":"7390",
    "addr:street":"Rue Franc\u0327Ois Andre\u0301",
    "iso:country":"BE",
    "sg:address":"Rue Fran\u00c7ois Andr\u00c9 279",
    "sg:city":"Quaregnon",
    "sg:orig_category":"Afbraak- and draineerwerken",
    "sg:phone":"+32 65 77 86 31",
    "sg:postcode":"7390",
    "sg:province":"Hainaut",
    "wof:name":"Ets. Demoulin",
    "wof:placetype":"venue"
},
  "geometry": {"coordinates":[3.8715910912,50.4356384277],"type":"Point"}
}