{
  "type": "Feature",
  "properties": {
    "addr:full":"Ch De Tongres 505 Liege Li\u00e8ge 4000",
    "addr:housenumber":"505",
    "addr:postcode":"4000",
    "addr:street":"Ch De Tongres",
    "iso:country":"BE",
    "sg:address":"Ch De Tongres 505",
    "sg:city":"Liege",
    "sg:orig_category":"Imprimeries and copyshops",
    "sg:phone":"+32 4 247 39 64",
    "sg:postcode":"4000",
    "sg:province":"Li\u00e8ge",
    "wof:name":"B.g.s.",
    "wof:placetype":"venue"
},
  "geometry": {"coordinates":[5.5431852341,50.6798286438],"type":"Point"}
}