{
  "type": "Feature",
  "properties": {
    "addr:full":"Meersstraat 55 Gent-centrum Oost-Vlaanderen 9000",
    "addr:housenumber":"55",
    "addr:postcode":"9000",
    "addr:street":"Meersstraat;Oost-Vlaanderen",
    "iso:country":"BE",
    "sg:address":"Meersstraat 55",
    "sg:city":"Gent-centrum",
    "sg:orig_category":"Advocaten and juridische adviseurs Balie van Gent Boekhouders",
    "sg:phone":"+32 9 220 16 39",
    "sg:postcode":"9000",
    "sg:province":"Oost-Vlaanderen",
    "wof:name":"Cassiman Diederik",
    "wof:placetype":"venue"
},
  "geometry": {"coordinates":[3.7151401043,51.0407524109],"type":"Point"}
}