{
  "type": "Feature",
  "properties": {
    "iso:country":"BE",
    "sg:address":"Stuivenbergvaart 33",
    "sg:city":"Mechelen",
    "sg:classifiers":[
        {
            "category":"Real Estate",
            "subcategory":"Architect",
            "type":"Services"
        }
    ],
    "sg:phone":"+32 15 43 62 43",
    "sg:postcode":"2800",
    "sg:province":"Antwerpen",
    "wof:name":"De Lausnay S",
    "wof:placetype":"venue"
},
  "geometry": {"coordinates":[4.4600038528,51.0253105164],"type":"Point"}
}