{
  "type": "Feature",
  "properties": {
    "addr:full":"Avenue Marie De Hongrie 107 Ganshoren/ganshoren Bruxelles-Capitale 1083",
    "addr:housenumber":"107",
    "addr:postcode":"1083",
    "addr:street":"Avenue Marie De Hongrie",
    "iso:country":"BE",
    "sg:address":"Avenue Marie De Hongrie 107",
    "sg:city":"Ganshoren/ganshoren",
    "sg:orig_category":"Studios photographiques",
    "sg:phone":"+32 2 465 07 93",
    "sg:postcode":"1083",
    "sg:province":"Bruxelles-Capitale",
    "wof:name":"Alain Cuyx",
    "wof:placetype":"venue"
},
  "geometry": {"coordinates":[4.3019227982,50.8721847534],"type":"Point"}
}