{
  "type": "Feature",
  "properties": {
    "iso:country":"BE",
    "sg:address":"Statiestraat 38",
    "sg:city":"Ternat",
    "sg:classifiers":[
        {
            "category":"Professional",
            "subcategory":"Lawyer & Legal Services",
            "type":"Services"
        }
    ],
    "sg:phone":"+32 2 582 11 10",
    "sg:postcode":"1740",
    "sg:province":"Vlaams-Brabant",
    "wof:name":"Bourguignon Dirk",
    "wof:placetype":"venue"
},
  "geometry": {"coordinates":[4.1747279167,50.8705825806],"type":"Point"}
}