{
  "type": "Feature",
  "properties": {
    "addr:full":"Adrien Dezaegerplein 12ba Willebroek Antwerpen 2830",
    "addr:housenumber":"12ba",
    "addr:postcode":"2830",
    "addr:street":"Adrien Dezaegerplein",
    "iso:country":"BE",
    "sg:address":"Adrien Dezaegerplein 12ba",
    "sg:city":"Willebroek",
    "sg:orig_category":"Enseignement maternel and primaire",
    "sg:phone":"+32 3 886 66 39",
    "sg:postcode":"2830",
    "sg:province":"Antwerpen",
    "wof:name":"Basisschool",
    "wof:placetype":"venue"
},
  "geometry": {"coordinates":[4.3500847816,51.051235199],"type":"Point"}
}