{
  "type": "Feature",
  "properties": {
    "addr:full":"Boomstraat 52 Bornem Antwerpen 2880",
    "addr:housenumber":"52",
    "addr:postcode":"2880",
    "addr:street":"Boomstraat",
    "iso:country":"BE",
    "sg:address":"Boomstraat 52",
    "sg:city":"Bornem",
    "sg:orig_category":"Pain, p\u00e2tisseries and confiseries",
    "sg:phone":"+32 3 889 39 46",
    "sg:postcode":"2880",
    "sg:province":"Antwerpen",
    "wof:name":"Bakkerij P&m",
    "wof:placetype":"venue"
},
  "geometry": {"coordinates":[4.2332382202,51.0978164673],"type":"Point"}
}