{
  "type": "Feature",
  "properties": {
    "addr:full":"Cyriel De Grootelaan 20 Middelkerke West-Vlaanderen 8430",
    "addr:housenumber":"20",
    "addr:postcode":"8430",
    "addr:street":"Cyriel De Grootelaan",
    "iso:country":"BE",
    "sg:address":"Cyriel De Grootelaan 20",
    "sg:city":"Middelkerke",
    "sg:orig_category":"M\u00e9decins and sp\u00e9cialistes",
    "sg:phone":"+32 59 30 02 30",
    "sg:postcode":"8430",
    "sg:province":"West-Vlaanderen",
    "wof:name":"Guido Mulier",
    "wof:placetype":"venue"
},
  "geometry": {"coordinates":[2.8199520111,51.1881446838],"type":"Point"}
}