{
  "type": "Feature",
  "properties": {
    "addr:full":"Groeneschild 58 Heers Limburg 3870",
    "addr:housenumber":"58",
    "addr:postcode":"3870",
    "addr:street":"Groeneschild",
    "iso:country":"BE",
    "sg:address":"Groeneschild 58",
    "sg:city":"Heers",
    "sg:orig_category":"Fruitteelt",
    "sg:phone":"+32 11 48 70 82",
    "sg:postcode":"3870",
    "sg:province":"Limburg",
    "wof:name":"Leo Thewis",
    "wof:placetype":"venue"
},
  "geometry": {"coordinates":[5.2856278419,50.7668266296],"type":"Point"}
}