{
  "type": "Feature",
  "properties": {
    "iso:country":"BE",
    "sg:address":"Rue Des Grog\u00c8res 22bb",
    "sg:city":"Charleroi",
    "sg:orig_category":"Travaux d\u00b4installation divers. Lampes and appareils \u00e9lectriques Fab",
    "sg:phone":"+32 71 47 97 16",
    "sg:postcode":"6001",
    "sg:province":"Hainaut",
    "wof:name":"Immobili\u00c8re Durant",
    "wof:placetype":"venue"
},
  "geometry": {"coordinates":[4.4308619499,50.3983688354],"type":"Point"}
}