{
  "type": "Feature",
  "properties": {
    "iso:country":"BE",
    "sg:address":"Rue De Renaix 135",
    "sg:city":"Ellezelles",
    "sg:classifiers":[
        {
            "category":"Utilities",
            "subcategory":"Fuel Oil & Lpg",
            "type":"Services"
        }
    ],
    "sg:phone":"+32 68 54 25 13",
    "sg:postcode":"7890",
    "sg:province":"Hainaut",
    "wof:name":"Fontaine Jacques Ets",
    "wof:placetype":"venue"
},
  "geometry": {"coordinates":[3.6533970833,50.7324867249],"type":"Point"}
}