{
  "type": "Feature",
  "properties": {
    "addr:full":"Hoevestraat 19 Kortrijk West-Vlaanderen 8500",
    "addr:housenumber":"19",
    "addr:postcode":"8500",
    "addr:street":"Hoevestraat",
    "iso:country":"BE",
    "sg:address":"Hoevestraat 19",
    "sg:city":"Kortrijk",
    "sg:classifiers":[
        {
            "category":"Food & Beverages",
            "subcategory":"Fruits & Vegetables",
            "type":"Retail Goods"
        }
    ],
    "sg:phone":"+32 56 21 04 62",
    "sg:postcode":"8500",
    "sg:province":"West-Vlaanderen",
    "sg:tags":[
        "l\u00e9gumes"
    ],
    "wof:name":"Aardappelen Delmotte",
    "wof:placetype":"venue"
},
  "geometry": {"coordinates":[3.2928578854,50.8315925598],"type":"Point"}
}