{
  "type": "Feature",
  "properties": {
    "addr:full":"Van Stralenstraat 49 Antwerpen Antwerpen 2060",
    "addr:housenumber":"49",
    "addr:postcode":"2060",
    "addr:street":"Van Stralenstraat",
    "iso:country":"BE",
    "sg:address":"Van Stralenstraat 49",
    "sg:city":"Antwerpen",
    "sg:classifiers":[
        {
            "category":"Organizations",
            "subcategory":"Political Organization",
            "type":"Services"
        }
    ],
    "sg:phone":"+32 3 485 86 10",
    "sg:postcode":"2060",
    "sg:province":"Antwerpen",
    "sg:tags":[
        "owner",
        "ship"
    ],
    "wof:name":"Afro Liner Services Nv",
    "wof:placetype":"venue"
},
  "geometry": {"coordinates":[4.4194250107,51.2225036621],"type":"Point"}
}