{
  "type": "Feature",
  "properties": {
    "addr:full":"Rue De Bas\u00c8cles 9 Beloeil Hainaut 7971",
    "addr:housenumber":"9",
    "addr:postcode":"7971",
    "addr:street":"Rue De Base\u0300Cles",
    "iso:country":"BE",
    "sg:address":"Rue De Bas\u00c8cles 9",
    "sg:city":"Beloeil",
    "sg:orig_category":"Eleveurs de bovins",
    "sg:phone":"+32 69 57 60 68",
    "sg:postcode":"7971",
    "sg:province":"Hainaut",
    "wof:name":"Victor Dubois",
    "wof:placetype":"venue"
},
  "geometry": {"coordinates":[3.6527299881,50.5324897766],"type":"Point"}
}