{
  "type": "Feature",
  "properties": {
    "addr:full":"Square Pr\u00c9vost Delaunay 113 Brussel/bruxelles Bruxelles-Capitale 1030",
    "addr:housenumber":"113",
    "addr:postcode":"1030",
    "addr:street":"Square;Delaunay;/",
    "iso:country":"BE",
    "sg:address":"Square Pr\u00c9vost Delaunay 113",
    "sg:city":"Brussel/bruxelles",
    "sg:orig_category":"Grossistes divers",
    "sg:phone":"+32 2 216 05 02",
    "sg:postcode":"1030",
    "sg:province":"Bruxelles-Capitale",
    "wof:name":"Full Service",
    "wof:placetype":"venue"
},
  "geometry": {"coordinates":[4.3911409378,50.8591079712],"type":"Point"}
}