{
  "type": "Feature",
  "properties": {
    "addr:full":"Theet 23 Hamme Oost-Vlaanderen 9220",
    "addr:housenumber":"23",
    "addr:postcode":"9220",
    "addr:street":"Theet",
    "iso:country":"BE",
    "sg:address":"Theet 23",
    "sg:city":"Hamme",
    "sg:orig_category":"Installatie van houten of kunststof schrijnwerk MEUBELONTWERP AND -INSTALLATIE",
    "sg:phone":"+32 52 48 00 92",
    "sg:postcode":"9220",
    "sg:province":"Oost-Vlaanderen",
    "wof:name":"Formakeukens Smet",
    "wof:placetype":"venue"
},
  "geometry": {"coordinates":[4.13144207,51.0811347961],"type":"Point"}
}