{
  "type": "Feature",
  "properties": {
    "iso:country":"BE",
    "sg:address":"Kroonlaan 71",
    "sg:city":"Elsene/ixelles",
    "sg:classifiers":[
        {
            "category":"Fast Food",
            "type":"Food & Drink"
        }
    ],
    "sg:phone":"+32 2 647 79 42",
    "sg:postcode":"1050",
    "sg:province":"Bruxelles-Capitale",
    "sg:tags":[
        "meeneem",
        "restaurant"
    ],
    "wof:name":"Frituur Bompa",
    "wof:placetype":"venue"
},
  "geometry": {"coordinates":[4.3790669441,50.8295898438],"type":"Point"}
}