{
  "type": "Feature",
  "properties": {
    "addr:full":"Breendonkstraat 306 A Willebroek Antwerpen 2830",
    "addr:housenumber":"306 a",
    "addr:postcode":"2830",
    "addr:street":"Breendonkstraat",
    "iso:country":"BE",
    "sg:address":"Breendonkstraat 306 A",
    "sg:city":"Willebroek",
    "sg:orig_category":"V\u00e9hicules automobiles. Entretien and r\u00e9parations de voitures",
    "sg:phone":"+32 3 886 93 79",
    "sg:postcode":"2830",
    "sg:province":"Antwerpen",
    "wof:name":"Lenaerts & Zoon Garage",
    "wof:placetype":"venue"
},
  "geometry": {"coordinates":[4.3390731812,51.0449867249],"type":"Point"}
}