{
  "type": "Feature",
  "properties": {
    "iso:country":"BE",
    "sg:address":"Baron Joostensstraat 7",
    "sg:city":"Antwerpen",
    "sg:classifiers":[
        {
            "category":"Real Estate",
            "subcategory":"Architect",
            "type":"Services"
        }
    ],
    "sg:phone":"+32 3 230 84 89",
    "sg:postcode":"2018",
    "sg:province":"Antwerpen",
    "wof:name":"Louwyck L",
    "wof:placetype":"venue"
},
  "geometry": {"coordinates":[4.4236841202,51.2101364136],"type":"Point"}
}