{
  "type": "Feature",
  "properties": {
    "addr:full":"Rue De Soignies 410 Ath Hainaut 7811",
    "addr:housenumber":"410",
    "addr:postcode":"7811",
    "addr:street":"Rue De Soignies",
    "iso:country":"BE",
    "sg:address":"Rue De Soignies 410",
    "sg:city":"Ath",
    "sg:orig_category":"Diverse bouwafwerking and reiniging Industri\u00eble and commerci\u00eble bouw",
    "sg:phone":"+32 68 28 62 28",
    "sg:postcode":"7811",
    "sg:province":"Hainaut",
    "wof:name":"Bureau William",
    "wof:placetype":"venue"
},
  "geometry": {"coordinates":[3.8159689903,50.6116752625],"type":"Point"}
}