{
  "type": "Feature",
  "properties": {
    "addr:full":"Rue Du Tilleul 397b5 Evere/evere Bruxelles-Capitale 1140",
    "addr:housenumber":"397b5",
    "addr:postcode":"1140",
    "addr:street":"Rue Du Tilleul",
    "iso:country":"BE",
    "sg:address":"Rue Du Tilleul 397b5",
    "sg:city":"Evere/evere",
    "sg:orig_category":"Installation de menuiserie en bois and plastique",
    "sg:phone":"+32 2 215 76 97",
    "sg:postcode":"1140",
    "sg:province":"Bruxelles-Capitale",
    "wof:name":"Batisud",
    "wof:placetype":"venue"
},
  "geometry": {"coordinates":[4.39731884,50.8671531677],"type":"Point"}
}