{
  "type": "Feature",
  "properties": {
    "iso:country":"BE",
    "sg:address":"Dokter Haekstraat 16",
    "sg:city":"Dendermonde",
    "sg:orig_category":"Boucheries",
    "sg:phone":"+32 52 21 25 53",
    "sg:postcode":"9200",
    "sg:province":"Oost-Vlaanderen",
    "wof:name":"Tom Van Cauwenberghe",
    "wof:placetype":"venue"
},
  "geometry": {"coordinates":[4.1065092087,51.0538139343],"type":"Point"}
}