{
  "type": "Feature",
  "properties": {
    "addr:full":"Ring 9 Essen Antwerpen 2910",
    "addr:housenumber":"9",
    "addr:postcode":"2910",
    "addr:street":"Ring",
    "iso:country":"BE",
    "sg:address":"Ring 9",
    "sg:city":"Essen",
    "sg:classifiers":[
        {
            "category":"Banks & Credit Unions",
            "subcategory":"Bureau De Change",
            "type":"Services"
        }
    ],
    "sg:phone":"+32 3 677 28 85",
    "sg:postcode":"2910",
    "sg:province":"Antwerpen",
    "sg:tags":[
        "measuring",
        "control",
        "apparatus"
    ],
    "wof:name":"Magic Flow",
    "wof:placetype":"venue"
},
  "geometry": {"coordinates":[4.4752597809,51.461101532],"type":"Point"}
}