{
  "type": "Feature",
  "properties": {
    "iso:country":"BE",
    "sg:address":"Kapiteinstraat 145",
    "sg:city":"Gent",
    "sg:orig_category":"Slagers",
    "sg:phone":"+32 9 253 80 93",
    "sg:postcode":"9000",
    "sg:province":"Oost-Vlaanderen",
    "wof:name":"Beenhouwerij Dirk",
    "wof:placetype":"venue"
},
  "geometry": {"coordinates":[3.7211999893,51.0883216858],"type":"Point"}
}