{
  "type": "Feature",
  "properties": {
    "iso:country":"BE",
    "sg:address":"Rue De La Procession 78",
    "sg:city":"Anderlecht/anderlecht",
    "sg:orig_category":"Formation permanente",
    "sg:phone":"+32 2 522 25 86",
    "sg:postcode":"1070",
    "sg:province":"Bruxelles-Capitale",
    "wof:name":"Cours Prom. Soc. Erasme",
    "wof:placetype":"venue"
},
  "geometry": {"coordinates":[4.3026909828,50.8348999023],"type":"Point"}
}