{
  "type": "Feature",
  "properties": {
    "addr:full":"Koningin Fabiolalaan 8 Knokke-heist (knokke) West-Vlaanderen 8300",
    "addr:housenumber":"8",
    "addr:postcode":"8300",
    "addr:street":"Koningin Fabiolalaan",
    "iso:country":"BE",
    "sg:address":"Koningin Fabiolalaan 8",
    "sg:city":"Knokke-heist (knokke)",
    "sg:classifiers":[
        {
            "category":"Real Estate",
            "subcategory":"Architect",
            "type":"Services"
        }
    ],
    "sg:phone":"+32 50 60 19 22",
    "sg:postcode":"8300",
    "sg:province":"West-Vlaanderen",
    "wof:name":"Van Acker H",
    "wof:placetype":"venue"
},
  "geometry": {"coordinates":[3.287694931,51.3467254639],"type":"Point"}
}