{
  "type": "Feature",
  "properties": {
    "addr:full":"Lindestraat 12 Alveringem West-Vlaanderen 8691",
    "addr:housenumber":"12",
    "addr:postcode":"8691",
    "addr:street":"Lindestraat",
    "iso:country":"BE",
    "sg:address":"Lindestraat 12",
    "sg:city":"Alveringem",
    "sg:orig_category":"Eleveurs and marchands de porcs",
    "sg:phone":"+32 57 30 06 55",
    "sg:postcode":"8691",
    "sg:province":"West-Vlaanderen",
    "wof:name":"Georges Rosseel",
    "wof:placetype":"venue"
},
  "geometry": {"coordinates":[2.666574955,50.9520263672],"type":"Point"}
}