{
  "type": "Feature",
  "properties": {
    "addr:full":"Nachtegaalstraat 2 Izegem West-Vlaanderen 8870",
    "addr:housenumber":"2",
    "addr:postcode":"8870",
    "addr:street":"Nachtegaalstraat",
    "iso:country":"BE",
    "sg:address":"Nachtegaalstraat 2",
    "sg:city":"Izegem",
    "sg:classifiers":[
        {
            "category":"Autos & Motor Vehicles",
            "subcategory":"Boat Sales",
            "type":"Retail Goods"
        }
    ],
    "sg:phone":"+32 51 31 85 10",
    "sg:postcode":"8870",
    "sg:province":"West-Vlaanderen",
    "sg:tags":[
        "balloon"
    ],
    "wof:name":"Balloon-art",
    "wof:placetype":"venue"
},
  "geometry": {"coordinates":[3.2318789959,50.9272422791],"type":"Point"}
}