{
  "type": "Feature",
  "properties": {
    "addr:full":"Begonialaan 13 Harelbeke (hulste) West-Vlaanderen 8531",
    "addr:housenumber":"13",
    "addr:postcode":"8531",
    "addr:street":"Begonialaan",
    "iso:country":"BE",
    "sg:address":"Begonialaan 13",
    "sg:city":"Harelbeke (hulste)",
    "sg:classifiers":[
        {
            "category":"Building & Trades",
            "subcategory":"Pest Control",
            "type":"Services"
        }
    ],
    "sg:phone":"+32 56 70 16 34",
    "sg:postcode":"8531",
    "sg:province":"West-Vlaanderen",
    "sg:tags":[
        "painting",
        "contractor"
    ],
    "wof:name":"Coudenys J",
    "wof:placetype":"venue"
},
  "geometry": {"coordinates":[3.2914149761,50.8870239258],"type":"Point"}
}