{
  "type": "Feature",
  "properties": {
    "iso:country":"BE",
    "sg:address":"Veldbloemenlaan 4",
    "sg:city":"Bertem",
    "sg:orig_category":"Charpentes and couvertures",
    "sg:phone":"+32 2 767 03 21",
    "sg:postcode":"3061",
    "sg:province":"Vlaams-Brabant",
    "wof:name":"Luc Verhoeven",
    "wof:placetype":"venue"
},
  "geometry": {"coordinates":[4.5914940834,50.8443603516],"type":"Point"}
}