{
  "type": "Feature",
  "properties": {
    "iso:country":"BE",
    "sg:address":"Kerkstraat 14",
    "sg:city":"Koksijde",
    "sg:orig_category":"M\u00e9decins and sp\u00e9cialistes",
    "sg:phone":"+32 58 51 54 39",
    "sg:postcode":"8670",
    "sg:province":"West-Vlaanderen",
    "wof:name":"Roland Decroos",
    "wof:placetype":"venue"
},
  "geometry": {"coordinates":[2.6521189213,51.1033172607],"type":"Point"}
}