{
  "type": "Feature",
  "properties": {
    "addr:full":"Rue Du Moulin 1 Froidchapelle Hainaut 6440",
    "addr:housenumber":"1",
    "addr:postcode":"6440",
    "addr:street":"Rue Du Moulin",
    "iso:country":"BE",
    "sg:address":"Rue Du Moulin 1",
    "sg:city":"Froidchapelle",
    "sg:orig_category":"Herstellingen and onderhoud van auto's",
    "sg:phone":"+32 60 41 27 76",
    "sg:postcode":"6440",
    "sg:province":"Hainaut",
    "wof:name":"Garage Mellaerts",
    "wof:placetype":"venue"
},
  "geometry": {"coordinates":[4.3274312019,50.15184021],"type":"Point"}
}