{
  "type": "Feature",
  "properties": {
    "iso:country":"BE",
    "sg:address":"Place Saint-vincent 18",
    "sg:city":"Walhain (nil-saint-vincent-saint-martin)",
    "sg:classifiers":[
        {
            "category":"Professional",
            "subcategory":"Lawyer & Legal Services",
            "type":"Services"
        }
    ],
    "sg:phone":"+32 10 65 51 35",
    "sg:postcode":"1457",
    "sg:province":"Brabant Wallon",
    "sg:tags":[
        "notary"
    ],
    "wof:name":"De Burlet L",
    "wof:placetype":"venue"
},
  "geometry": {"coordinates":[4.672317028,50.6396217346],"type":"Point"}
}