{
  "type": "Feature",
  "properties": {
    "iso:country":"BE",
    "sg:address":"Rue Saint-l\u00e9onard 448",
    "sg:city":"Li\u00e8ge 1",
    "sg:classifiers":[
        {
            "category":"Utilities",
            "subcategory":"Natural Gas",
            "type":"Services"
        }
    ],
    "sg:phone":"+32 4 227 68 31",
    "sg:postcode":"4000",
    "sg:province":"Li\u00e8ge",
    "sg:tags":[
        "welding"
    ],
    "wof:name":"Art-m\u00e9tal-li\u00e8ge",
    "wof:placetype":"venue"
},
  "geometry": {"coordinates":[5.6011338234,50.6529693604],"type":"Point"}
}