{
  "type": "Feature",
  "properties": {
    "addr:full":"Rue De L'aub\u00e9pine 8 Neupr\u00e9 (plainevaux) Li\u00e8ge 4122",
    "addr:housenumber":"8",
    "addr:postcode":"4122",
    "addr:street":"Rue De L'Aube \u0301Pine;Plainevaux",
    "iso:country":"BE",
    "sg:address":"Rue De L'aub\u00e9pine 8",
    "sg:city":"Neupr\u00e9 (plainevaux)",
    "sg:classifiers":[
        {
            "category":"Personal",
            "subcategory":"Beauty Salon",
            "type":"Services"
        }
    ],
    "sg:phone":"+32 474 25 51 09",
    "sg:postcode":"4122",
    "sg:province":"Li\u00e8ge",
    "sg:tags":[
        "lady",
        "-",
        "hairdressing"
    ],
    "wof:name":"Union Coiffeurs Belgique",
    "wof:placetype":"venue"
},
  "geometry": {"coordinates":[5.5277428627,50.5408973694],"type":"Point"}
}