{
  "type": "Feature",
  "properties": {
    "iso:country":"BE",
    "sg:address":"Rozenkranslaan 134",
    "sg:city":"Genk",
    "sg:classifiers":[
        {
            "category":"Building & Trades",
            "subcategory":"Equipment Rental",
            "type":"Services"
        }
    ],
    "sg:phone":"+32 89 35 29 64",
    "sg:postcode":"3600",
    "sg:province":"Limburg",
    "sg:tags":[
        "sound",
        "-",
        "system"
    ],
    "wof:name":"Franssens B",
    "wof:placetype":"venue"
},
  "geometry": {"coordinates":[5.4837770462,50.9568595886],"type":"Point"}
}