{
  "type": "Feature",
  "properties": {
    "addr:full":"Herderstraat 23 Gent Oost-Vlaanderen 9000",
    "addr:housenumber":"23",
    "addr:postcode":"9000",
    "addr:street":"Herderstraat;Oost-Vlaanderen",
    "iso:country":"BE",
    "sg:address":"Herderstraat 23",
    "sg:city":"Gent",
    "sg:classifiers":[
        {
            "category":"Building & Trades",
            "subcategory":"Plumbing",
            "type":"Services"
        }
    ],
    "sg:phone":"+32 9 228 84 73",
    "sg:postcode":"9000",
    "sg:province":"Oost-Vlaanderen",
    "sg:tags":[
        "pipe",
        "drain",
        "unblocking"
    ],
    "wof:name":"Algemene Ruimingswerken Sanico",
    "wof:placetype":"venue"
},
  "geometry": {"coordinates":[3.7021100521,51.057182312],"type":"Point"}
}