{
  "type": "Feature",
  "properties": {
    "iso:country":"BE",
    "sg:address":"Rue D'hornu 231",
    "sg:city":"Colfontaine",
    "sg:orig_category":"Location d'articles de sport, de sport nautique and de camping. Agences immobili\u00e8res",
    "sg:phone":"+32 65 78 00 97",
    "sg:postcode":"7340",
    "sg:province":"Hainaut",
    "wof:name":"Alain Henry Vacances C\u00d4te Sud",
    "wof:placetype":"venue"
},
  "geometry": {"coordinates":[3.8391280174,50.4296264648],"type":"Point"}
}