{
  "type": "Feature",
  "properties": {
    "iso:country":"BE",
    "sg:address":"Grand'route 132",
    "sg:city":"Crisnee",
    "sg:orig_category":"Entretien and r\u00e9parations de voitures. D\u00e9taillants en pi\u00e8ces and accessoires de voitures. V\u00e9hicules ",
    "sg:phone":"+32 19 67 71 65",
    "sg:postcode":"4367",
    "sg:province":"Li\u00e8ge",
    "wof:name":"Langenaeken",
    "wof:placetype":"venue"
},
  "geometry": {"coordinates":[5.3976302147,50.7166290283],"type":"Point"}
}