{
  "type": "Feature",
  "properties": {
    "addr:full":"Runkstersteenweg 339 Hasselt Limburg 3500",
    "addr:housenumber":"339",
    "addr:postcode":"3500",
    "addr:street":"Runkstersteenweg",
    "iso:country":"BE",
    "sg:address":"Runkstersteenweg 339",
    "sg:city":"Hasselt",
    "sg:classifiers":[
        {
            "category":"Home & Garden",
            "subcategory":"Building Materials",
            "type":"Retail Goods"
        }
    ],
    "sg:phone":"+32 11 27 33 08",
    "sg:postcode":"3500",
    "sg:province":"Limburg",
    "sg:tags":[
        "shutter"
    ],
    "wof:name":"Vandepoel Bvba",
    "wof:placetype":"venue"
},
  "geometry": {"coordinates":[5.3064131737,50.9238815308],"type":"Point"}
}