{
  "type": "Feature",
  "properties": {
    "iso:country":"BE",
    "sg:address":"Paalsesteenweg 55b1",
    "sg:city":"Beringen",
    "sg:classifiers":[
        {
            "category":"Fast Food",
            "type":"Food & Drink"
        }
    ],
    "sg:phone":"+32 11 42 09 44",
    "sg:postcode":"3580",
    "sg:province":"Limburg",
    "sg:tags":[
        "\u00c0",
        "emporter",
        "restaurants"
    ],
    "wof:name":"Rudi Hendrix",
    "wof:placetype":"venue"
},
  "geometry": {"coordinates":[5.2089800835,51.0457305908],"type":"Point"}
}