{
  "type": "Feature",
  "properties": {
    "iso:country":"BE",
    "sg:address":"Rue Du Palais 56",
    "sg:city":"Li\u00e8ge 1",
    "sg:classifiers":[
        {
            "category":"Insurance",
            "subcategory":"Insurance Agent",
            "type":"Services"
        }
    ],
    "sg:phone":"+32 4 223 63 13",
    "sg:postcode":"4000",
    "sg:province":"Li\u00e8ge",
    "sg:tags":[
        "broker"
    ],
    "wof:name":"Dodeigne Et Henry",
    "wof:placetype":"venue"
},
  "geometry": {"coordinates":[5.5745072365,50.6467285156],"type":"Point"}
}