{
  "type": "Feature",
  "properties": {
    "addr:full":"Steenweg 218 Diepenbeek Limburg 3590",
    "addr:housenumber":"218",
    "addr:postcode":"3590",
    "addr:street":"Steenweg",
    "iso:country":"BE",
    "sg:address":"Steenweg 218",
    "sg:city":"Diepenbeek",
    "sg:orig_category":"V\u00e9hicules automobiles",
    "sg:phone":"+32 11 23 19 32",
    "sg:postcode":"3590",
    "sg:province":"Limburg",
    "wof:name":"Autohandel Freddy",
    "wof:placetype":"venue"
},
  "geometry": {"coordinates":[5.3761692047,50.9230232239],"type":"Point"}
}