{
  "type": "Feature",
  "properties": {
    "addr:full":"Avenue Bruy\u00c8re Du Loup 8 La Hulpe Brabant Wallon 1310",
    "addr:housenumber":"8",
    "addr:postcode":"1310",
    "addr:street":"Avenue Bruye\u0300Re Du Loup",
    "iso:country":"BE",
    "sg:address":"Avenue Bruy\u00c8re Du Loup 8",
    "sg:city":"La Hulpe",
    "sg:orig_category":"Technische studies and ingenieursactiviteiten",
    "sg:phone":"+32 2 654 16 22",
    "sg:postcode":"1310",
    "sg:province":"Brabant Wallon",
    "wof:name":"Geoconcept",
    "wof:placetype":"venue"
},
  "geometry": {"coordinates":[4.4727430344,50.7311401367],"type":"Point"}
}