{
  "type": "Feature",
  "properties": {
    "addr:full":"Nijverheidslaan 3 Geluwe West-Vlaanderen 8940",
    "addr:housenumber":"3",
    "addr:postcode":"8940",
    "addr:street":"Nijverheidslaan",
    "iso:country":"BE",
    "sg:address":"Nijverheidslaan 3",
    "sg:city":"Geluwe",
    "sg:classifiers":[
        {
            "category":"Structure",
            "subcategory":"Warehouse",
            "type":"Public Place"
        }
    ],
    "sg:phone":"+32 3 664 26 96",
    "sg:postcode":"8940",
    "sg:province":"West-Vlaanderen",
    "sg:tags":[
        "chiller",
        "air-conditioning",
        "system"
    ],
    "wof:name":"De Bruyn Werkhuizen Nv",
    "wof:placetype":"venue"
},
  "geometry": {"coordinates":[4.42588377,51.2869796753],"type":"Point"}
}