{
  "type": "Feature",
  "properties": {
    "addr:full":"Oude Oostmallebaan 69 Beerse Antwerpen 2340",
    "addr:housenumber":"69",
    "addr:postcode":"2340",
    "addr:street":"Oude Oostmallebaan",
    "iso:country":"BE",
    "sg:address":"Oude Oostmallebaan 69",
    "sg:city":"Beerse",
    "sg:classifiers":[
        {
            "category":"Arena",
            "subcategory":"Sports Club",
            "type":"Entertainment"
        }
    ],
    "sg:phone":"+32 14 61 52 59",
    "sg:postcode":"2340",
    "sg:province":"Antwerpen",
    "sg:tags":[
        "de"
    ],
    "wof:name":"Wandelclub \u00b4t Beerke",
    "wof:placetype":"venue"
},
  "geometry": {"coordinates":[4.8284769058,51.316242218],"type":"Point"}
}