{
  "type": "Feature",
  "properties": {
    "addr:full":"Terlo 127 Kasterlee Antwerpen 2460",
    "addr:housenumber":"127",
    "addr:postcode":"2460",
    "iso:country":"BE",
    "sg:address":"Terlo 127",
    "sg:city":"Kasterlee",
    "sg:orig_category":"Rundveehouders",
    "sg:phone":"+32 14 85 13 02",
    "sg:postcode":"2460",
    "sg:province":"Antwerpen",
    "wof:name":"Frans Vennekens",
    "wof:placetype":"venue"
},
  "geometry": {"coordinates":[4.9987797737,51.2491226196],"type":"Point"}
}