{
  "type": "Feature",
  "properties": {
    "iso:country":"BE",
    "sg:address":"Dorpsstraat 146",
    "sg:city":"Stabroek",
    "sg:orig_category":"Apotheken",
    "sg:phone":"+32 3 568 67 67",
    "sg:postcode":"2940",
    "sg:province":"Antwerpen",
    "wof:name":"Verlinden",
    "wof:placetype":"venue"
},
  "geometry": {"coordinates":[4.3715209961,51.3346061707],"type":"Point"}
}