{
  "type": "Feature",
  "properties": {
    "iso:country":"BE",
    "sg:address":"Dubbelhofstraat 9",
    "sg:city":"Sint-niklaas (belsele)",
    "sg:orig_category":"Non-Classified Establishments",
    "sg:phone":"+32 3 722 02 33",
    "sg:postcode":"9111",
    "sg:province":"Oost-Vlaanderen",
    "wof:name":"Facom Bvba",
    "wof:placetype":"venue"
},
  "geometry": {"coordinates":[4.0803599358,51.1407775879],"type":"Point"}
}