{
  "type": "Feature",
  "properties": {
    "iso:country":"BE",
    "sg:address":"Rue Gatti De Gamond 126 Box 8",
    "sg:city":"Bruxelles (uccle)",
    "sg:classifiers":[
        {
            "category":"Communications",
            "type":"Services"
        }
    ],
    "sg:phone":"+32 2 332 36 16",
    "sg:postcode":"1180",
    "sg:province":"Bruxelles-Capitale",
    "sg:tags":[
        "translator"
    ],
    "wof:name":"Exacto Sensu Sprl",
    "wof:placetype":"venue"
},
  "geometry": {"coordinates":[4.3278961182,50.8024406433],"type":"Point"}
}