{
  "type": "Feature",
  "properties": {
    "iso:country":"BE",
    "sg:address":"Karel Keymolenstraat 70",
    "sg:city":"Lennik",
    "sg:orig_category":"M\u00e9decins and sp\u00e9cialistes",
    "sg:phone":"+32 2 532 13 06",
    "sg:postcode":"1750",
    "sg:province":"Vlaams-Brabant",
    "wof:name":"Alain Van Laethem",
    "wof:placetype":"venue"
},
  "geometry": {"coordinates":[4.1506800652,50.8079566956],"type":"Point"}
}