{
  "type": "Feature",
  "properties": {
    "addr:full":"Lode De Boningestraat 11 Wevelgem West-Vlaanderen 8560",
    "addr:housenumber":"11",
    "addr:postcode":"8560",
    "addr:street":"Lode De Boningestraat",
    "iso:country":"BE",
    "sg:address":"Lode De Boningestraat 11",
    "sg:city":"Wevelgem",
    "sg:orig_category":"Poissonniers and \u00e9caillers",
    "sg:phone":"+32 56 41 17 29",
    "sg:postcode":"8560",
    "sg:province":"West-Vlaanderen",
    "wof:name":"Verhulst",
    "wof:placetype":"venue"
},
  "geometry": {"coordinates":[3.183398962,50.8092498779],"type":"Point"}
}