{
  "type": "Feature",
  "properties": {
    "addr:full":"Dorpstraat 58 Wichelen Oost-Vlaanderen 9260",
    "addr:housenumber":"58",
    "addr:postcode":"9260",
    "addr:street":"Dorpstraat",
    "iso:country":"BE",
    "sg:address":"Dorpstraat 58",
    "sg:city":"Wichelen",
    "sg:orig_category":"Artsen and specialisten",
    "sg:phone":"+32 9 369 62 52",
    "sg:postcode":"9260",
    "sg:province":"Oost-Vlaanderen",
    "wof:name":"E. Verhulst",
    "wof:placetype":"venue"
},
  "geometry": {"coordinates":[3.9716579914,51.0137825012],"type":"Point"}
}