{
  "type": "Feature",
  "properties": {
    "addr:full":"Nolimpark 1020 Overpelt Limburg 3900",
    "addr:postcode":"1020 overpelt;3900",
    "addr:street":"Nolimpark",
    "iso:country":"BE",
    "sg:address":"Nolimpark 1020",
    "sg:city":"Overpelt",
    "sg:orig_category":"Verlichting and huishoudartikelen",
    "sg:phone":"+32 11 64 98 06",
    "sg:postcode":"3900",
    "sg:province":"Limburg",
    "wof:name":"G.b. Products Belgi\u00cb",
    "wof:placetype":"venue"
},
  "geometry": {"coordinates":[5.4235649109,51.2117614746],"type":"Point"}
}