{
  "type": "Feature",
  "properties": {
    "iso:country":"BE",
    "sg:address":"Schansstraat 1",
    "sg:city":"Laakdal",
    "sg:orig_category":"Producteurs de l\u00e9gumes",
    "sg:phone":"+32 14 84 13 03",
    "sg:postcode":"2431",
    "sg:province":"Antwerpen",
    "wof:name":"Georges Bries",
    "wof:placetype":"venue"
},
  "geometry": {"coordinates":[4.9629778862,51.0644683838],"type":"Point"}
}