{
  "type": "Feature",
  "properties": {
    "iso:country":"BE",
    "sg:address":"Engelstraat 18",
    "sg:city":"Ichtegem",
    "sg:classifiers":[
        {
            "category":"Bakery",
            "type":"Food & Drink"
        }
    ],
    "sg:phone":"+32 51 58 05 28",
    "sg:postcode":"8480",
    "sg:province":"West-Vlaanderen",
    "sg:tags":[
        "confectioner",
        "baker"
    ],
    "wof:name":"De Fijnproever",
    "wof:placetype":"venue"
},
  "geometry": {"coordinates":[3.0128450394,51.0931129456],"type":"Point"}
}