{
  "type": "Feature",
  "properties": {
    "iso:country":"BE",
    "sg:address":"Haachtse Steenweg 6",
    "sg:city":"Sint-joost-ten-node/saint-josse-ten-noode",
    "sg:orig_category":"Kapsalons",
    "sg:phone":"+32 2 218 22 30",
    "sg:postcode":"1210",
    "sg:province":"Bruxelles-Capitale",
    "wof:name":"Coiffure Intern. Canane",
    "wof:placetype":"venue"
},
  "geometry": {"coordinates":[4.3666238785,50.854637146],"type":"Point"}
}