{
  "type": "Feature",
  "properties": {
    "iso:country":"BE",
    "sg:address":"Nieuwstraat 9",
    "sg:city":"Sint-niklaas",
    "sg:orig_category":"Beheer onroerend goed Immobili\u00ebnkantoren",
    "sg:phone":"+32 3 777 64 06",
    "sg:postcode":"9100",
    "sg:province":"Oost-Vlaanderen",
    "wof:name":"Beau & Fleming",
    "wof:placetype":"venue"
},
  "geometry": {"coordinates":[4.1390480995,51.1638298035],"type":"Point"}
}