{
  "type": "Feature",
  "properties": {
    "addr:full":"Vossekotstraat 19 Meulebeke West-Vlaanderen 8760",
    "addr:housenumber":"19",
    "addr:postcode":"8760",
    "addr:street":"Vossekotstraat",
    "iso:country":"BE",
    "sg:address":"Vossekotstraat 19",
    "sg:city":"Meulebeke",
    "sg:orig_category":"Eleveurs de bovins. Eleveurs and marchands de porcs",
    "sg:phone":"+32 51 40 05 89",
    "sg:postcode":"8760",
    "sg:province":"West-Vlaanderen",
    "wof:name":"Marc Vandermeulen",
    "wof:placetype":"venue"
},
  "geometry": {"coordinates":[3.332775116,50.9627799988],"type":"Point"}
}