{
  "type": "Feature",
  "properties": {
    "iso:country":"BE",
    "sg:address":"Beukenlaan 3",
    "sg:city":"Hoeilaart",
    "sg:classifiers":[
        {
            "category":"Health Services",
            "subcategory":"Doctor",
            "type":"Services"
        }
    ],
    "sg:phone":"+32 2 657 22 02",
    "sg:postcode":"1560",
    "sg:province":"Vlaams-Brabant",
    "sg:tags":[
        "orthopedist"
    ],
    "wof:name":"Fernadez E.",
    "wof:placetype":"venue"
},
  "geometry": {"coordinates":[4.4946770668,50.7647361755],"type":"Point"}
}