{
  "type": "Feature",
  "properties": {
    "addr:full":"P.d. Vanhoutestraat 5 Kortemark West-Vlaanderen 8610",
    "addr:housenumber":"5",
    "addr:postcode":"8610",
    "addr:street":"Vanhoutestraat",
    "iso:country":"BE",
    "sg:address":"P.d. Vanhoutestraat 5",
    "sg:city":"Kortemark",
    "sg:classifiers":[
        {
            "category":"Cafe",
            "type":"Food & Drink"
        }
    ],
    "sg:phone":"+32 51 56 74 94",
    "sg:postcode":"8610",
    "sg:province":"West-Vlaanderen",
    "sg:tags":[
        "caf\u00e9s"
    ],
    "wof:name":"De Zwaan",
    "wof:placetype":"venue"
},
  "geometry": {"coordinates":[3.0424449444,51.028503418],"type":"Point"}
}