{
  "type": "Feature",
  "properties": {
    "addr:full":"Schupstraat 9-11 Antwerpen Antwerpen 2018",
    "addr:housenumber":"9-11",
    "addr:postcode":"2018",
    "addr:street":"Schupstraat",
    "iso:country":"BE",
    "sg:address":"Schupstraat 9-11",
    "sg:city":"Antwerpen",
    "sg:orig_category":"Non-Classified Establishments",
    "sg:phone":"+32 3 226 04 64",
    "sg:postcode":"2018",
    "sg:province":"Antwerpen",
    "wof:name":"Hedadiam Diamonds Bvba",
    "wof:placetype":"venue"
},
  "geometry": {"coordinates":[4.4183797836,51.2143249512],"type":"Point"}
}