{
  "type": "Feature",
  "properties": {
    "addr:full":"Rue Du Moulin 11 Quevy Hainaut 7041",
    "addr:housenumber":"11",
    "addr:postcode":"7041",
    "addr:street":"Rue Du Moulin;Hainaut",
    "iso:country":"BE",
    "sg:address":"Rue Du Moulin 11",
    "sg:city":"Quevy",
    "sg:orig_category":"Postkantoren Verzekeringsmakelaars and experts",
    "sg:phone":"+32 65 58 64 10",
    "sg:postcode":"7041",
    "sg:province":"Hainaut",
    "wof:name":"La Poste",
    "wof:placetype":"venue"
},
  "geometry": {"coordinates":[4.0323238373,50.3785934448],"type":"Point"}
}