{
  "type": "Feature",
  "properties": {
    "iso:country":"BE",
    "sg:address":"Boulevard De La Sauveni\u00e8re 112",
    "sg:city":"Li\u00e8ge 1",
    "sg:classifiers":[
        {
            "category":"Real Estate",
            "subcategory":"Architect",
            "type":"Services"
        }
    ],
    "sg:phone":"+32 4 221 43 04",
    "sg:postcode":"4000",
    "sg:province":"Li\u00e8ge",
    "wof:name":"Gilles T",
    "wof:placetype":"venue"
},
  "geometry": {"coordinates":[5.5656061172,50.6425056458],"type":"Point"}
}