{
  "type": "Feature",
  "properties": {
    "addr:full":"Rue De La Gare 12 Qui\u00e9vrain Hainaut 7380",
    "addr:housenumber":"12",
    "addr:postcode":"7380",
    "addr:street":"Rue De La Gare",
    "iso:country":"BE",
    "sg:address":"Rue De La Gare 12",
    "sg:city":"Qui\u00e9vrain",
    "sg:classifiers":[
        {
            "category":"Shopping",
            "subcategory":"Computers & Home Electronics",
            "type":"Retail Goods"
        }
    ],
    "sg:phone":"+32 65 43 13 01",
    "sg:postcode":"7380",
    "sg:province":"Hainaut",
    "sg:tags":[
        "-",
        "television",
        "radio"
    ],
    "wof:name":"Rolland Techno-son",
    "wof:placetype":"venue"
},
  "geometry": {"coordinates":[3.6849439144,50.4083099365],"type":"Point"}
}