{
  "type": "Feature",
  "properties": {
    "iso:country":"BE",
    "sg:address":"Sint-kornelisplein 12",
    "sg:city":"Horebeke",
    "sg:orig_category":"Slagers",
    "sg:phone":"+32 55 45 55 39",
    "sg:postcode":"9667",
    "sg:province":"Oost-Vlaanderen",
    "wof:name":"Gentil Bauters",
    "wof:placetype":"venue"
},
  "geometry": {"coordinates":[3.6976380348,50.834602356],"type":"Point"}
}