{
  "type": "Feature",
  "properties": {
    "iso:country":"BE",
    "sg:address":"Slachthuisstraat 17",
    "sg:city":"Turnhout",
    "sg:classifiers":[
        {
            "category":"Building & Trades",
            "subcategory":"Construction",
            "type":"Services"
        }
    ],
    "sg:phone":"+32 14 43 81 81",
    "sg:postcode":"2300",
    "sg:province":"Antwerpen",
    "sg:tags":[
        "interior",
        "work"
    ],
    "wof:name":"Labburint Van Sande Nv",
    "wof:placetype":"venue"
},
  "geometry": {"coordinates":[4.9246530533,51.3053283691],"type":"Point"}
}