{
  "type": "Feature",
  "properties": {
    "iso:country":"BE",
    "sg:address":"Arthur Van Laethemstraat 19",
    "sg:city":"Gent",
    "sg:orig_category":"Artsen and specialisten",
    "sg:phone":"+32 9 230 07 05",
    "sg:postcode":"9050",
    "sg:province":"Oost-Vlaanderen",
    "wof:name":"Paul De Porre",
    "wof:placetype":"venue"
},
  "geometry": {"coordinates":[3.7704870701,51.0314559937],"type":"Point"}
}