{
  "type": "Feature",
  "properties": {
    "addr:full":"Nieuwstraat 26 Kruishoutem Oost-Vlaanderen 9770",
    "addr:housenumber":"26",
    "addr:postcode":"9770",
    "addr:street":"Nieuwstraat",
    "iso:country":"BE",
    "sg:address":"Nieuwstraat 26",
    "sg:city":"Kruishoutem",
    "sg:orig_category":"Afbraak- and draineerwerken Bouwmaterialen Gh Huisvuilophaling and -verwerking Stortklaar beton Fab",
    "sg:phone":"+32 9 383 50 42",
    "sg:postcode":"9770",
    "sg:province":"Oost-Vlaanderen",
    "wof:name":"De Snerck",
    "wof:placetype":"venue"
},
  "geometry": {"coordinates":[3.5287299156,50.908870697],"type":"Point"}
}