{
  "type": "Feature",
  "properties": {
    "addr:full":"Meensesteenweg 780 Roeselare West-Vlaanderen 8800",
    "addr:housenumber":"780",
    "addr:postcode":"8800",
    "addr:street":"Meensesteenweg",
    "iso:country":"BE",
    "sg:address":"Meensesteenweg 780",
    "sg:city":"Roeselare",
    "sg:orig_category":"Etalage- and showroomontwerpers",
    "sg:phone":"+32 56 50 96 06",
    "sg:postcode":"8800",
    "sg:province":"West-Vlaanderen",
    "wof:name":"Erna Hemelaere",
    "wof:placetype":"venue"
},
  "geometry": {"coordinates":[3.113861084,50.8919830322],"type":"Point"}
}