{
  "type": "Feature",
  "properties": {
    "addr:full":"Rue De La Clef 74 Herve Li\u00e8ge 4650",
    "addr:housenumber":"74",
    "addr:postcode":"4650",
    "addr:street":"Rue De La Clef",
    "iso:country":"BE",
    "sg:address":"Rue De La Clef 74",
    "sg:city":"Herve",
    "sg:orig_category":"Entretien and r\u00e9parations de voitures",
    "sg:phone":"+32 87 66 01 61",
    "sg:postcode":"4650",
    "sg:province":"Li\u00e8ge",
    "wof:name":"J.r. Auto",
    "wof:placetype":"venue"
},
  "geometry": {"coordinates":[5.7829198837,50.6389083862],"type":"Point"}
}