{
  "type": "Feature",
  "properties": {
    "addr:full":"Vogelzangstraat 29f Heist-op-den-berg (itegem) Antwerpen 2222",
    "addr:housenumber":"29f",
    "addr:postcode":"2222",
    "addr:street":"Vogelzangstraat",
    "iso:country":"BE",
    "sg:address":"Vogelzangstraat 29f",
    "sg:city":"Heist-op-den-berg (itegem)",
    "sg:classifiers":[
        {
            "category":"Shopping",
            "subcategory":"Bicycles & Sporting Goods",
            "type":"Retail Goods"
        }
    ],
    "sg:phone":"+32 15 24 23 26",
    "sg:postcode":"2222",
    "sg:province":"Antwerpen",
    "sg:tags":[
        "sport",
        "-"
    ],
    "wof:name":"Id Sport",
    "wof:placetype":"venue"
},
  "geometry": {"coordinates":[4.7292399406,51.1032218933],"type":"Point"}
}