{
  "type": "Feature",
  "properties": {
    "addr:full":"Krombeekweg 40/1 Heist-op-den-berg Antwerpen 2222",
    "addr:housenumber":"40 / 1",
    "addr:postcode":"2222",
    "addr:street":"Krombeekweg",
    "iso:country":"BE",
    "sg:address":"Krombeekweg 40/1",
    "sg:city":"Heist-op-den-berg",
    "sg:orig_category":"Mat\u00e9riaux de construction Constructions r\u00e9sidentielles sp\u00e9cifiques. Travaux de finition and nettoyag",
    "sg:phone":"+32 15 24 45 70",
    "sg:postcode":"2222",
    "sg:province":"Antwerpen",
    "wof:name":"De Rijck",
    "wof:placetype":"venue"
},
  "geometry": {"coordinates":[4.7292399406,51.1032218933],"type":"Point"}
}