{
  "type": "Feature",
  "properties": {
    "addr:full":"Dokter Derolaan 10 Geraardsbergen Oost-Vlaanderen 9500",
    "addr:housenumber":"10",
    "addr:postcode":"9500",
    "addr:street":"Dokter Derolaan",
    "iso:country":"BE",
    "sg:address":"Dokter Derolaan 10",
    "sg:city":"Geraardsbergen",
    "sg:orig_category":"Herenkledingzaken",
    "sg:phone":"+32 54 41 68 42",
    "sg:postcode":"9500",
    "sg:province":"Oost-Vlaanderen",
    "wof:name":"Van Noten Top Fashion",
    "wof:placetype":"venue"
},
  "geometry": {"coordinates":[3.9031670094,50.7614440918],"type":"Point"}
}