{
  "type": "Feature",
  "properties": {
    "addr:full":"Bruggestraat 37 Menen West-Vlaanderen 8930",
    "addr:housenumber":"37",
    "addr:postcode":"8930",
    "addr:street":"Bruggestraat",
    "iso:country":"BE",
    "sg:address":"Bruggestraat 37",
    "sg:city":"Menen",
    "sg:orig_category":"Opticiens",
    "sg:phone":"+32 56 53 19 32",
    "sg:postcode":"8930",
    "sg:province":"West-Vlaanderen",
    "wof:name":"Brilcenter",
    "wof:placetype":"venue"
},
  "geometry": {"coordinates":[3.1222090721,50.7974014282],"type":"Point"}
}