{
  "type": "Feature",
  "properties": {
    "addr:full":"Rue Perg\u00c8re 14 Braine-l'alleud Brabant Wallon 1420",
    "addr:housenumber":"14",
    "addr:postcode":"1420",
    "addr:street":"Rue Perge\u0300Re",
    "iso:country":"BE",
    "sg:address":"Rue Perg\u00c8re 14",
    "sg:city":"Braine-l'alleud",
    "sg:orig_category":"Woningbouw",
    "sg:phone":"+32 2 384 73 44",
    "sg:postcode":"1420",
    "sg:province":"Brabant Wallon",
    "wof:name":"Jean-pierre Vermorgen",
    "wof:placetype":"venue"
},
  "geometry": {"coordinates":[-0.8572289944,47.3877601624],"type":"Point"}
}