{
  "type": "Feature",
  "properties": {
    "iso:country":"BE",
    "sg:address":"Sint-jorisstraat 3",
    "sg:city":"Brugge",
    "sg:orig_category":"Cabinets d\u00b4huissiers",
    "sg:phone":"+32 50 33 15 91",
    "sg:postcode":"8000",
    "sg:province":"West-Vlaanderen",
    "wof:name":"E. Vynck",
    "wof:placetype":"venue"
},
  "geometry": {"coordinates":[3.2223670483,51.2123832703],"type":"Point"}
}