{
  "type": "Feature",
  "properties": {
    "addr:full":"Rue De La Bravoure 1214 Jette/jette Bruxelles-Capitale 1090",
    "addr:postcode":"1214;1090",
    "addr:street":"Rue De La Bravoure",
    "iso:country":"BE",
    "sg:address":"Rue De La Bravoure 1214",
    "sg:city":"Jette/jette",
    "sg:orig_category":"Entretien and r\u00e9parations de voitures",
    "sg:phone":"+32 2 425 53 45",
    "sg:postcode":"1090",
    "sg:province":"Bruxelles-Capitale",
    "wof:name":"Garage Leunis",
    "wof:placetype":"venue"
},
  "geometry": {"coordinates":[4.3375501633,50.8779296875],"type":"Point"}
}