{
  "type": "Feature",
  "properties": {
    "addr:full":"Wijgmaalsesteenweg 6 Leuven (wilsele) Vlaams-Brabant 3012",
    "addr:housenumber":"6",
    "addr:postcode":"3012",
    "addr:street":"Wijgmaalsesteenweg",
    "iso:country":"BE",
    "sg:address":"Wijgmaalsesteenweg 6",
    "sg:city":"Leuven (wilsele)",
    "sg:orig_category":"Non-Classified Establishments",
    "sg:phone":"+32 16 20 38 24",
    "sg:postcode":"3012",
    "sg:province":"Vlaams-Brabant",
    "wof:name":"Vanderbiest Bvba",
    "wof:placetype":"venue"
},
  "geometry": {"coordinates":[4.7073540688,50.9041862488],"type":"Point"}
}