{
  "type": "Feature",
  "properties": {
    "iso:country":"BE",
    "sg:address":"Quatre Vents 15",
    "sg:city":"Lessines",
    "sg:orig_category":"Installation de menuiserie en bois and plastique",
    "sg:phone":"+32 68 33 11 47",
    "sg:postcode":"7863",
    "sg:province":"Hainaut",
    "wof:name":"Gerard Vancrombrughe",
    "wof:placetype":"venue"
},
  "geometry": {"coordinates":[3.8162000179,50.7310905457],"type":"Point"}
}