{
  "type": "Feature",
  "properties": {
    "iso:country":"BE",
    "sg:address":"Rue Du Tombeu 4",
    "sg:city":"Hannut (moxhe)",
    "sg:classifiers":[
        {
            "category":"Retail",
            "subcategory":"Veterinary Services",
            "type":"Services"
        }
    ],
    "sg:phone":"+32 19 69 96 02",
    "sg:postcode":"4280",
    "sg:province":"Li\u00e8ge",
    "sg:tags":[
        "veterinarian"
    ],
    "wof:name":"Bourguignon A",
    "wof:placetype":"venue"
},
  "geometry": {"coordinates":[5.0826392174,50.6309738159],"type":"Point"}
}