{
  "type": "Feature",
  "properties": {
    "iso:country":"BE",
    "sg:address":"Quai Saint-l\u00c9onard 84b15",
    "sg:city":"Li\u00c8ge",
    "sg:orig_category":"Maatschappelijke dienstverlening",
    "sg:phone":"+32 4 227 74 67",
    "sg:postcode":"4000",
    "sg:province":"Li\u00e8ge",
    "wof:name":"Petits Ruisseaux",
    "wof:placetype":"venue"
},
  "geometry": {"coordinates":[5.5996441841,50.6503791809],"type":"Point"}
}