{
  "type": "Feature",
  "properties": {
    "addr:full":"Statieplein 6 Anzegem West-Vlaanderen 8570",
    "addr:housenumber":"6",
    "addr:postcode":"8570",
    "addr:street":"Statieplein",
    "iso:country":"BE",
    "sg:address":"Statieplein 6",
    "sg:city":"Anzegem",
    "sg:classifiers":[
        {
            "category":"Health Services",
            "subcategory":"Dentist",
            "type":"Services"
        }
    ],
    "sg:phone":"+32 56 68 00 33",
    "sg:postcode":"8570",
    "sg:province":"West-Vlaanderen",
    "wof:name":"Beel A",
    "wof:placetype":"venue"
},
  "geometry": {"coordinates":[3.4930710793,50.8261947632],"type":"Point"}
}