{
  "type": "Feature",
  "properties": {
    "addr:full":"Driekerkenstraat 51 Kortrijk (bissegem) West-Vlaanderen 8501",
    "addr:housenumber":"51",
    "addr:postcode":"8501",
    "addr:street":"Driekerkenstraat",
    "iso:country":"BE",
    "sg:address":"Driekerkenstraat 51",
    "sg:city":"Kortrijk (bissegem)",
    "sg:classifiers":[
        {
            "category":"Professional",
            "subcategory":"Accounting & Tax Preparation",
            "type":"Services"
        }
    ],
    "sg:phone":"+32 56 37 30 03",
    "sg:postcode":"8501",
    "sg:province":"West-Vlaanderen",
    "sg:tags":[
        "accountant"
    ],
    "wof:name":"Lejaegere A",
    "wof:placetype":"venue"
},
  "geometry": {"coordinates":[3.2288188934,50.8215293884],"type":"Point"}
}