{
  "type": "Feature",
  "properties": {
    "iso:country":"BE",
    "sg:address":"Rue Maubray 11",
    "sg:city":"Pecq",
    "sg:classifiers":[
        {
            "category":"Retail",
            "subcategory":"Funeral Services",
            "type":"Services"
        }
    ],
    "sg:phone":"+32 69 55 63 52",
    "sg:postcode":"7740",
    "sg:province":"Hainaut",
    "sg:tags":[
        "director"
    ],
    "wof:name":"Mathon Andre",
    "wof:placetype":"venue"
},
  "geometry": {"coordinates":[3.3303170204,50.6871566772],"type":"Point"}
}