{
  "type": "Feature",
  "properties": {
    "iso:country":"BE",
    "sg:address":"Avenue Van Volxem 525",
    "sg:city":"Bruxelles (forest)",
    "sg:classifiers":[
        {
            "category":"Social Services",
            "type":"Services"
        }
    ],
    "sg:phone":"+32 2 539 43 60",
    "sg:postcode":"1190",
    "sg:province":"Bruxelles-Capitale",
    "wof:name":"Entraide Culture Asbl",
    "wof:placetype":"venue"
},
  "geometry": {"coordinates":[4.3299870491,50.8292808533],"type":"Point"}
}