{
  "type": "Feature",
  "properties": {
    "addr:full":"Antwerpse Steenweg 127 Hemiksem Antwerpen 2620",
    "addr:housenumber":"127",
    "addr:postcode":"2620",
    "addr:street":"Antwerpse Steenweg",
    "iso:country":"BE",
    "sg:address":"Antwerpse Steenweg 127",
    "sg:city":"Hemiksem",
    "sg:classifiers":[
        {
            "category":"Building & Trades",
            "subcategory":"Electrical",
            "type":"Services"
        }
    ],
    "sg:phone":"+32 3 877 43 62",
    "sg:postcode":"2620",
    "sg:province":"Antwerpen",
    "sg:tags":[
        "electric",
        "-",
        "housewiring",
        "contractor"
    ],
    "wof:name":"V.d.b. Elektro",
    "wof:placetype":"venue"
},
  "geometry": {"coordinates":[4.3383917809,51.146522522],"type":"Point"}
}