{
  "type": "Feature",
  "properties": {
    "addr:full":"Wezestraat 2 Ardooie West-Vlaanderen 8850",
    "addr:housenumber":"2",
    "addr:postcode":"8850",
    "addr:street":"Wezestraat",
    "iso:country":"BE",
    "sg:address":"Wezestraat 2",
    "sg:city":"Ardooie",
    "sg:orig_category":"Enseignement secondaire technique and professionnel. Enseignement secondaire g\u00e9n\u00e9ral",
    "sg:phone":"+32 51 74 46 84",
    "sg:postcode":"8850",
    "sg:province":"West-Vlaanderen",
    "wof:name":"Inst. Heilige Kindsheid",
    "wof:placetype":"venue"
},
  "geometry": {"coordinates":[3.203316927,50.9762687683],"type":"Point"}
}