{
  "type": "Feature",
  "properties": {
    "iso:country":"BE",
    "sg:address":"Rue H\u00c9l\u00c8ne Ryckmans 3",
    "sg:city":"Sint-jans-molenbeek/molenbeek-saint-jean",
    "sg:orig_category":"Installation de menuiserie en bois and plastique",
    "sg:phone":"+32 2 411 40 55",
    "sg:postcode":"1080",
    "sg:province":"Bruxelles-Capitale",
    "wof:name":"Rodrigues",
    "wof:placetype":"venue"
},
  "geometry": {"coordinates":[4.340944767,50.8569793701],"type":"Point"}
}