{
  "type": "Feature",
  "properties": {
    "addr:full":"Hagedoornlaan 111 Ukkel/uccle Bruxelles-Capitale 1180",
    "addr:housenumber":"111",
    "addr:postcode":"1180",
    "addr:street":"Hagedoornlaan;/",
    "iso:country":"BE",
    "sg:address":"Hagedoornlaan 111",
    "sg:city":"Ukkel/uccle",
    "sg:orig_category":"Immobili\u00ebnkantoren Vrachtvervoer",
    "sg:phone":"+32 2 375 65 75",
    "sg:postcode":"1180",
    "sg:province":"Bruxelles-Capitale",
    "wof:name":"Vergels",
    "wof:placetype":"venue"
},
  "geometry": {"coordinates":[4.3717980385,50.7742462158],"type":"Point"}
}