{
  "type": "Feature",
  "properties": {
    "iso:country":"BE",
    "sg:address":"Marie- Christinestraat 172",
    "sg:city":"Brussel/bruxelles",
    "sg:orig_category":"HERSTELLING ELEKTRISCHE HUISHOUDAPPARATEN Huishoudapparaten, televisies and radio's Telecommunicatie",
    "sg:phone":"+32 2 428 98 21",
    "sg:postcode":"1020",
    "sg:province":"Bruxelles-Capitale",
    "wof:name":"Kr\u00cbfel",
    "wof:placetype":"venue"
},
  "geometry": {"coordinates":[4.3515849113,50.8760414124],"type":"Point"}
}