{
  "type": "Feature",
  "properties": {
    "iso:country":"BE",
    "sg:address":"Moeskroenstraat 413",
    "sg:city":"Menen",
    "sg:orig_category":"Entretien and r\u00e9parations de voitures",
    "sg:phone":"+32 56 41 66 54",
    "sg:postcode":"8930",
    "sg:province":"West-Vlaanderen",
    "wof:name":"Menauto",
    "wof:placetype":"venue"
},
  "geometry": {"coordinates":[3.1592879295,50.7869644165],"type":"Point"}
}