{
  "type": "Feature",
  "properties": {
    "iso:country":"BE",
    "sg:address":"Rue Du Mont Saint-aubert 37",
    "sg:city":"Tournai (kain)",
    "sg:classifiers":[
        {
            "category":"Social Services",
            "type":"Services"
        }
    ],
    "sg:phone":"+32 69 23 20 17",
    "sg:postcode":"7540",
    "sg:province":"Hainaut",
    "wof:name":"L'alouette-centre De Jour",
    "wof:placetype":"venue"
},
  "geometry": {"coordinates":[3.3991110325,50.6403694153],"type":"Point"}
}