{
  "type": "Feature",
  "properties": {
    "addr:full":"Leopold I-laan 94 Brugge West-Vlaanderen 8000",
    "addr:housenumber":"94",
    "addr:postcode":"8000",
    "addr:street":"Leopold I-Laan",
    "iso:country":"BE",
    "sg:address":"Leopold I-laan 94",
    "sg:city":"Brugge",
    "sg:orig_category":"Schoonheidssalons",
    "sg:phone":"+32 50 31 35 12",
    "sg:postcode":"8000",
    "sg:province":"West-Vlaanderen",
    "wof:name":"Daelemans E",
    "wof:placetype":"venue"
},
  "geometry": {"coordinates":[3.2084488869,51.2149085999],"type":"Point"}
}