{
  "type": "Feature",
  "properties": {
    "iso:country":"BE",
    "sg:address":"Sint-willebrordusstraat 50",
    "sg:city":"Brecht",
    "sg:orig_category":"Winkelinrichting and handelsuitrusting Gh",
    "sg:phone":"+32 3 663 65 50",
    "sg:postcode":"2960",
    "sg:province":"Antwerpen",
    "wof:name":"Frank's Cosmetica",
    "wof:placetype":"venue"
},
  "geometry": {"coordinates":[4.6009459496,51.3423919678],"type":"Point"}
}