{
  "type": "Feature",
  "properties": {
    "iso:country":"BE",
    "sg:address":"Rue Des Temples 1b2",
    "sg:city":"Berloz",
    "sg:orig_category":"Artsen and specialisten",
    "sg:phone":"+32 19 33 16 83",
    "sg:postcode":"4257",
    "sg:province":"Li\u00e8ge",
    "wof:name":"Sophie Jacquart",
    "wof:placetype":"venue"
},
  "geometry": {"coordinates":[5.2098388672,50.7050285339],"type":"Point"}
}