{
  "type": "Feature",
  "properties": {
    "iso:country":"BE",
    "sg:address":"Tulpinstraat 57",
    "sg:city":"Hasselt",
    "sg:orig_category":"Agences d'exp\u00e9dition",
    "sg:phone":"+32 11 21 09 17",
    "sg:postcode":"3500",
    "sg:province":"Limburg",
    "wof:name":"Louis Van Rompaey",
    "wof:placetype":"venue"
},
  "geometry": {"coordinates":[5.3638877869,50.9590682983],"type":"Point"}
}