{
  "type": "Feature",
  "properties": {
    "iso:country":"BE",
    "sg:address":"Daknammolenstraat 78",
    "sg:city":"Lokeren",
    "sg:classifiers":[
        {
            "category":"Building & Trades",
            "subcategory":"Landscaping Services",
            "type":"Services"
        }
    ],
    "sg:phone":"+32 9 348 21 62",
    "sg:postcode":"9160",
    "sg:province":"Oost-Vlaanderen",
    "sg:tags":[
        "architect",
        "landscape"
    ],
    "wof:name":"Clays R",
    "wof:placetype":"venue"
},
  "geometry": {"coordinates":[3.997975111,51.1233520508],"type":"Point"}
}