{
  "type": "Feature",
  "properties": {
    "addr:full":"Diestsevest 14 Leuven Vlaams-Brabant 3000",
    "addr:housenumber":"14",
    "addr:postcode":"3000",
    "addr:street":"Diestsevest",
    "iso:country":"BE",
    "sg:address":"Diestsevest 14",
    "sg:city":"Leuven",
    "sg:orig_category":"Belastingconsulenten Diverse juridische dienstverlening Sociale secretariaten",
    "sg:phone":"+32 16 24 53 80",
    "sg:postcode":"3000",
    "sg:province":"Vlaams-Brabant",
    "wof:name":"Sbb",
    "wof:placetype":"venue"
},
  "geometry": {"coordinates":[4.7140460014,50.8826942444],"type":"Point"}
}