{
  "type": "Feature",
  "properties": {
    "addr:full":"Steenweg Op Oosthoven 319 Turnhout Antwerpen 2300",
    "addr:housenumber":"319",
    "addr:postcode":"2300",
    "addr:street":"Steenweg Op Oosthoven",
    "iso:country":"BE",
    "sg:address":"Steenweg Op Oosthoven 319",
    "sg:city":"Turnhout",
    "sg:classifiers":[
        {
            "category":"Professional",
            "subcategory":"Accounting & Tax Preparation",
            "type":"Services"
        }
    ],
    "sg:phone":"+32 14 41 37 57",
    "sg:postcode":"2300",
    "sg:province":"Antwerpen",
    "sg:tags":[
        "accountant"
    ],
    "wof:name":"Lauwers M",
    "wof:placetype":"venue"
},
  "geometry": {"coordinates":[4.9651699066,51.3349380493],"type":"Point"}
}