{
  "type": "Feature",
  "properties": {
    "iso:country":"BE",
    "sg:address":"Napoleonkaai 29",
    "sg:city":"Antwerpen",
    "sg:classifiers":[
        {
            "category":"Restaurant",
            "type":"Food & Drink"
        }
    ],
    "sg:phone":"+32 3 231 35 49",
    "sg:postcode":"2000",
    "sg:province":"Antwerpen",
    "sg:tags":[
        "caf\u00e9s"
    ],
    "wof:name":"Taverne Bilitis",
    "wof:placetype":"venue"
},
  "geometry": {"coordinates":[4.4093408585,51.2300453186],"type":"Point"}
}