{
  "type": "Feature",
  "properties": {
    "iso:country":"BE",
    "sg:address":"Eug\u00c8ne Gilbertstraat 8",
    "sg:city":"Leuven",
    "sg:classifiers":[
        {
            "category":"Arena",
            "subcategory":"Sports Club",
            "type":"Entertainment"
        }
    ],
    "sg:phone":"+32 16 23 47 21",
    "sg:postcode":"3000",
    "sg:province":"Vlaams-Brabant",
    "sg:tags":[
        "terrain",
        "hors",
        "de",
        "installation",
        "sportifs"
    ],
    "wof:name":"R.c. Leuven",
    "wof:placetype":"venue"
},
  "geometry": {"coordinates":[4.6828789711,50.8856315613],"type":"Point"}
}