{
  "type": "Feature",
  "properties": {
    "addr:full":"Poelbergstraat 28 Scherpenheuvel-zichem (scherpenheuvel) Vlaams-Brabant 3270",
    "addr:housenumber":"28",
    "addr:postcode":"3270",
    "addr:street":"Poelbergstraat",
    "iso:country":"BE",
    "sg:address":"Poelbergstraat 28",
    "sg:city":"Scherpenheuvel-zichem (scherpenheuvel)",
    "sg:classifiers":[
        {
            "category":"Personal",
            "subcategory":"Tattoo Parlor",
            "type":"Services"
        }
    ],
    "sg:phone":"+32 13 77 77 37",
    "sg:postcode":"3270",
    "sg:province":"Vlaams-Brabant",
    "sg:tags":[
        "tattooists"
    ],
    "wof:name":"Needles And Pins Tattooshop",
    "wof:placetype":"venue"
},
  "geometry": {"coordinates":[4.9441800117,50.963104248],"type":"Point"}
}