{
  "type": "Feature",
  "properties": {
    "iso:country":"BE",
    "sg:address":"Crapaurue 175",
    "sg:city":"Verviers",
    "sg:classifiers":[
        {
            "category":"Insurance",
            "subcategory":"Life Insurance",
            "type":"Services"
        }
    ],
    "sg:phone":"+32 87 35 55 01",
    "sg:postcode":"4800",
    "sg:province":"Li\u00e8ge",
    "sg:tags":[
        "assurance"
    ],
    "wof:name":"Partners Assurances",
    "wof:placetype":"venue"
},
  "geometry": {"coordinates":[5.8625788689,50.5924911499],"type":"Point"}
}