{
  "type": "Feature",
  "properties": {
    "iso:country":"BE",
    "sg:address":"Ketsebroek 8",
    "sg:city":"Kaprijke",
    "sg:orig_category":"Eleveurs de bovins",
    "sg:phone":"+32 9 377 13 38",
    "sg:postcode":"9971",
    "sg:province":"Oost-Vlaanderen",
    "wof:name":"Firmin De Smet",
    "wof:placetype":"venue"
},
  "geometry": {"coordinates":[3.608453989,51.2018318176],"type":"Point"}
}