{
  "type": "Feature",
  "properties": {
    "iso:country":"BE",
    "sg:address":"Achtel 18",
    "sg:city":"Rijkevorsel",
    "sg:orig_category":"Rundveehouders Varkenskwekers",
    "sg:phone":"+32 3 314 55 58",
    "sg:postcode":"2310",
    "sg:province":"Antwerpen",
    "wof:name":"Jozef Verheyen",
    "wof:placetype":"venue"
},
  "geometry": {"coordinates":[4.760931015,51.3694419861],"type":"Point"}
}