{
  "type": "Feature",
  "properties": {
    "addr:full":"Schoonstraat 3 Evergem Oost-Vlaanderen 9940",
    "addr:housenumber":"3",
    "addr:postcode":"9940",
    "addr:street":"Schoonstraat;Oost-Vlaanderen",
    "iso:country":"BE",
    "sg:address":"Schoonstraat 3",
    "sg:city":"Evergem",
    "sg:orig_category":"Goederenvervoer over de weg",
    "sg:phone":"+32 9 253 93 06",
    "sg:postcode":"9940",
    "sg:province":"Oost-Vlaanderen",
    "wof:name":"Adriatico Trans",
    "wof:placetype":"venue"
},
  "geometry": {"coordinates":[3.6982800961,51.1103973389],"type":"Point"}
}