{
  "type": "Feature",
  "properties": {
    "addr:full":"Ramstraat 3 Blankenberge West-Vlaanderen 8370",
    "addr:housenumber":"3",
    "addr:postcode":"8370",
    "addr:street":"Ramstraat",
    "iso:country":"BE",
    "sg:address":"Ramstraat 3",
    "sg:city":"Blankenberge",
    "sg:classifiers":[
        {
            "category":"Arena",
            "subcategory":"Sports Club",
            "type":"Entertainment"
        }
    ],
    "sg:phone":"+32 50 41 90 09",
    "sg:postcode":"8370",
    "sg:province":"West-Vlaanderen",
    "sg:tags":[
        "de"
    ],
    "wof:name":"T.k. De Blauwe Reiger",
    "wof:placetype":"venue"
},
  "geometry": {"coordinates":[3.1482698917,51.3021202087],"type":"Point"}
}