{
  "type": "Feature",
  "properties": {
    "addr:full":"Rue De Tergn\u00e9e 164 Farciennes Hainaut 6240",
    "addr:housenumber":"164",
    "addr:postcode":"6240",
    "addr:street":"Rue De Tergne\u0301E",
    "iso:country":"BE",
    "sg:address":"Rue De Tergn\u00e9e 164",
    "sg:city":"Farciennes",
    "sg:classifiers":[
        {
            "category":"Shopping",
            "subcategory":"Pets & Pet Supplies",
            "type":"Retail Goods"
        }
    ],
    "sg:phone":"+32 71 39 00 83",
    "sg:postcode":"6240",
    "sg:province":"Hainaut",
    "sg:tags":[
        "-",
        "foundry"
    ],
    "wof:name":"Belgarena",
    "wof:placetype":"venue"
},
  "geometry": {"coordinates":[4.5611810684,50.4371070862],"type":"Point"}
}