{
  "type": "Feature",
  "properties": {
    "addr:full":"Prins Leopoldstraat 14 Brugge (sint-kruis) West-Vlaanderen 8310",
    "addr:housenumber":"14",
    "addr:postcode":"8310",
    "addr:street":"Prins Leopoldstraat",
    "iso:country":"BE",
    "sg:address":"Prins Leopoldstraat 14",
    "sg:city":"Brugge (sint-kruis)",
    "sg:classifiers":[
        {
            "category":"Home & Garden",
            "subcategory":"Home Furnishings",
            "type":"Retail Goods"
        }
    ],
    "sg:phone":"+32 50 35 49 84",
    "sg:postcode":"8310",
    "sg:province":"West-Vlaanderen",
    "sg:tags":[
        "-",
        "furniture"
    ],
    "wof:name":"Cocquyt Meubelen Nv",
    "wof:placetype":"venue"
},
  "geometry": {"coordinates":[3.2484049797,51.2130584717],"type":"Point"}
}