{
  "type": "Feature",
  "properties": {
    "addr:full":"Rue De L\u00b4ypr\u00c9au 9 Ronse/renaix Oost-Vlaanderen 9600",
    "addr:housenumber":"9",
    "addr:postcode":"9600",
    "addr:street":"Rue De L\u00b4Ypre\u0301Au",
    "iso:country":"BE",
    "sg:address":"Rue De L\u00b4ypr\u00c9au 9",
    "sg:city":"Ronse/renaix",
    "sg:orig_category":"V\u00eatements pour Dames. Articles pour b\u00e9b\u00e9s. V\u00eatements pour b\u00e9b\u00e9s and enfants",
    "sg:phone":"+32 55 21 53 26",
    "sg:postcode":"9600",
    "sg:province":"Oost-Vlaanderen",
    "wof:name":"Pr\u00c9maman",
    "wof:placetype":"venue"
},
  "geometry": {"coordinates":[3.600071907,50.7449684143],"type":"Point"}
}