{
  "type": "Feature",
  "properties": {
    "iso:country":"BE",
    "sg:address":"Kalanderlaan 5",
    "sg:city":"Watermaal-bosvoorde/watermael-boitsfort",
    "sg:orig_category":"Advocaten and juridische adviseurs",
    "sg:phone":"+32 2 675 39 70",
    "sg:postcode":"1170",
    "sg:province":"Bruxelles-Capitale",
    "wof:name":"D. Lambot",
    "wof:placetype":"venue"
},
  "geometry": {"coordinates":[4.4019098282,50.7989501953],"type":"Point"}
}