{
  "type": "Feature",
  "properties": {
    "addr:full":"Route D'eupen 19 Baelen/baelen Li\u00e8ge 4837",
    "addr:housenumber":"19",
    "addr:postcode":"4837",
    "addr:street":"Route D'Eupen",
    "iso:country":"BE",
    "sg:address":"Route D'eupen 19",
    "sg:city":"Baelen/baelen",
    "sg:orig_category":"V\u00e9hicules automobiles. D\u00e9taillants en pi\u00e8ces and accessoires de voitures. Entretien and r\u00e9parations ",
    "sg:phone":"+32 87 76 24 49",
    "sg:postcode":"4837",
    "sg:province":"Li\u00e8ge",
    "wof:name":"Marcel Kirch",
    "wof:placetype":"venue"
},
  "geometry": {"coordinates":[5.9756531715,50.6300430298],"type":"Point"}
}