{
  "type": "Feature",
  "properties": {
    "addr:full":"Sasstraat 1 Hasselt Limburg 3500",
    "addr:housenumber":"1",
    "addr:postcode":"3500",
    "addr:street":"Sasstraat",
    "iso:country":"BE",
    "sg:address":"Sasstraat 1",
    "sg:city":"Hasselt",
    "sg:orig_category":"Gedistilleerde dranken and aperitieven Fab Wijnen Fab",
    "sg:phone":"+32 11 22 31 74",
    "sg:postcode":"3500",
    "sg:province":"Limburg",
    "wof:name":"Smeets Hasselt",
    "wof:placetype":"venue"
},
  "geometry": {"coordinates":[5.3580489159,50.9380989075],"type":"Point"}
}