{
  "type": "Feature",
  "properties": {
    "iso:country":"BE",
    "sg:address":"Havenlaan 90",
    "sg:city":"Brussel/bruxelles",
    "sg:orig_category":"Metaalafval, schrootrecyclage and sloperijen",
    "sg:phone":"+32 2 420 73 91",
    "sg:postcode":"1000",
    "sg:province":"Bruxelles-Capitale",
    "wof:name":"Auto Galerie Sedat",
    "wof:placetype":"venue"
},
  "geometry": {"coordinates":[4.3510909081,50.866230011],"type":"Point"}
}