{
  "type": "Feature",
  "properties": {
    "iso:country":"BE",
    "sg:address":"Place D'hastedon 4",
    "sg:city":"Namur",
    "sg:orig_category":"Advocaten and juridische adviseurs",
    "sg:phone":"+32 81 73 10 93",
    "sg:postcode":"5000",
    "sg:province":"Namur",
    "wof:name":"M. Pieters",
    "wof:placetype":"venue"
},
  "geometry": {"coordinates":[4.8524532318,50.4707107544],"type":"Point"}
}