{
  "type": "Feature",
  "properties": {
    "iso:country":"BE",
    "sg:address":"Markt 10",
    "sg:city":"Londerzeel",
    "sg:classifiers":[
        {
            "category":"Cafe",
            "type":"Food & Drink"
        }
    ],
    "sg:phone":"+32 52 30 01 93",
    "sg:postcode":"1840",
    "sg:province":"Vlaams-Brabant",
    "sg:tags":[
        "caf\u00e9s"
    ],
    "wof:name":"Joannes Siemons",
    "wof:placetype":"venue"
},
  "geometry": {"coordinates":[4.3024048805,51.0011901855],"type":"Point"}
}