{
  "type": "Feature",
  "properties": {
    "addr:full":"Rue Gaucheret 144 Schaarbeek/schaerbeek Bruxelles-Capitale 1030",
    "addr:housenumber":"144",
    "addr:postcode":"1030",
    "addr:street":"Rue Gaucheret",
    "iso:country":"BE",
    "sg:address":"Rue Gaucheret 144",
    "sg:city":"Schaarbeek/schaerbeek",
    "sg:orig_category":"Catering and organisation de f\u00eates",
    "sg:phone":"+32 2 201 02 75",
    "sg:postcode":"1030",
    "sg:province":"Bruxelles-Capitale",
    "wof:name":"D.a.",
    "wof:placetype":"venue"
},
  "geometry": {"coordinates":[4.361770153,50.8659934998],"type":"Point"}
}