{
  "type": "Feature",
  "properties": {
    "iso:country":"BE",
    "sg:address":"Stationstraat 82",
    "sg:city":"Turnhout",
    "sg:classifiers":[
        {
            "category":"Education",
            "subcategory":"Special Training",
            "type":"Public Place"
        }
    ],
    "sg:phone":"+32 14 42 53 75",
    "sg:postcode":"2300",
    "sg:province":"Antwerpen",
    "sg:tags":[
        "-",
        "processing",
        "data"
    ],
    "wof:name":"Computeracademie",
    "wof:placetype":"venue"
},
  "geometry": {"coordinates":[4.9403100014,51.3242111206],"type":"Point"}
}