{
  "type": "Feature",
  "properties": {
    "iso:country":"BE",
    "sg:address":"J.b. De Greefsquare 5-6",
    "sg:city":"Oudergem/auderghem",
    "sg:orig_category":"Drukkerijen and copyshops",
    "sg:phone":"+32 2 660 28 35",
    "sg:postcode":"1160",
    "sg:province":"Bruxelles-Capitale",
    "wof:name":"Imprimerie Guy Mottiaux",
    "wof:placetype":"venue"
},
  "geometry": {"coordinates":[4.4251499176,50.8167381287],"type":"Point"}
}