{
  "type": "Feature",
  "properties": {
    "addr:full":"Avenue Louise 483 Bruxelles Bruxelles-Capitale 1050",
    "addr:housenumber":"483",
    "addr:postcode":"1050",
    "addr:street":"Avenue Louise",
    "iso:country":"BE",
    "sg:address":"Avenue Louise 483",
    "sg:city":"Bruxelles",
    "sg:classifiers":[
        {
            "category":"Travel",
            "subcategory":"Travel Agent",
            "type":"Entertainment"
        }
    ],
    "sg:phone":"+32 2 640 23 23",
    "sg:postcode":"1050",
    "sg:province":"Bruxelles-Capitale",
    "sg:tags":[
        "incentive"
    ],
    "wof:name":"Wooloomooloo S.a",
    "wof:placetype":"venue"
},
  "geometry": {"coordinates":[4.3712491989,50.81690979],"type":"Point"}
}