{
  "type": "Feature",
  "properties": {
    "iso:country":"BE",
    "sg:address":"Rue De P\u00e9ruwelz 12a",
    "sg:city":"Bernissart (blaton)",
    "sg:classifiers":[
        {
            "category":"Building & Trades",
            "subcategory":"Landscaping Services",
            "type":"Services"
        }
    ],
    "sg:phone":"+32 69 67 03 53",
    "sg:postcode":"7321",
    "sg:province":"Hainaut",
    "sg:tags":[
        "gardening",
        "garden",
        "maintenance"
    ],
    "wof:name":"De Vriendt D",
    "wof:placetype":"venue"
},
  "geometry": {"coordinates":[3.6611618996,50.5015869141],"type":"Point"}
}