{
  "type": "Feature",
  "properties": {
    "addr:full":"Veldstraat 17 Aalst Oost-Vlaanderen 9300",
    "addr:housenumber":"17",
    "addr:postcode":"9300",
    "addr:street":"Veldstraat",
    "iso:country":"BE",
    "sg:address":"Veldstraat 17",
    "sg:city":"Aalst",
    "sg:classifiers":[
        {
            "category":"Personal",
            "type":"Services"
        }
    ],
    "sg:phone":"+32 53 21 33 78",
    "sg:postcode":"9300",
    "sg:province":"Oost-Vlaanderen",
    "sg:tags":[
        "clothing",
        "men's",
        "tailor",
        "-"
    ],
    "wof:name":"Hendrickx L",
    "wof:placetype":"venue"
},
  "geometry": {"coordinates":[4.0361838341,50.9424743652],"type":"Point"}
}