{
  "type": "Feature",
  "properties": {
    "iso:country":"BE",
    "sg:address":"Lijsterstraat 1",
    "sg:city":"Nazareth",
    "sg:classifiers":[
        {
            "category":"Communications",
            "type":"Services"
        }
    ],
    "sg:phone":"+32 9 385 61 15",
    "sg:postcode":"9810",
    "sg:province":"Oost-Vlaanderen",
    "sg:tags":[
        "translator"
    ],
    "wof:name":"Ajda Vertalingen",
    "wof:placetype":"venue"
},
  "geometry": {"coordinates":[3.6191949844,50.9569587708],"type":"Point"}
}