{
  "type": "Feature",
  "properties": {
    "addr:full":"Haspershovenstr 6 Overpelt Limburg 3900",
    "addr:housenumber":"6",
    "addr:postcode":"3900",
    "addr:street":"Haspershovenstr",
    "iso:country":"BE",
    "sg:address":"Haspershovenstr 6",
    "sg:city":"Overpelt",
    "sg:classifiers":[
        {
            "category":"Professional",
            "subcategory":"Business Services",
            "type":"Services"
        }
    ],
    "sg:phone":"+32 11 64 18 31",
    "sg:postcode":"3900",
    "sg:province":"Limburg",
    "sg:tags":[
        "instrument",
        "advice",
        "-",
        "precision",
        "equipment",
        "health"
    ],
    "wof:name":"Dental Labo Brands Bvba",
    "wof:placetype":"venue"
},
  "geometry": {"coordinates":[5.42937994,51.2247505188],"type":"Point"}
}