{
  "type": "Feature",
  "properties": {
    "addr:full":"Rue Des Bas Sarts 61 Seraing Li\u00e8ge 4100",
    "addr:housenumber":"61",
    "addr:postcode":"4100",
    "addr:street":"Rue Des Bas Sarts",
    "iso:country":"BE",
    "sg:address":"Rue Des Bas Sarts 61",
    "sg:city":"Seraing",
    "sg:classifiers":[
        {
            "category":"Health Services",
            "subcategory":"Nursing And Care Facility",
            "type":"Services"
        }
    ],
    "sg:phone":"+32 4 337 08 89",
    "sg:postcode":"4100",
    "sg:province":"Li\u00e8ge",
    "sg:tags":[
        "home",
        "rest"
    ],
    "wof:name":"Chalet",
    "wof:placetype":"venue"
},
  "geometry": {"coordinates":[5.4884958267,50.597454071],"type":"Point"}
}