{
  "type": "Feature",
  "properties": {
    "iso:country":"BE",
    "sg:address":"Route De Barvaux 4",
    "sg:city":"Somme-leuze (heure)",
    "sg:classifiers":[
        {
            "category":"Real Estate",
            "subcategory":"Surveying",
            "type":"Services"
        }
    ],
    "sg:phone":"+32 86 32 22 15",
    "sg:postcode":"5377",
    "sg:province":"Namur",
    "sg:tags":[
        "surveyor",
        "land"
    ],
    "wof:name":"Roussel A",
    "wof:placetype":"venue"
},
  "geometry": {"coordinates":[5.2946600914,50.2971687317],"type":"Point"}
}