{
  "type": "Feature",
  "properties": {
    "iso:country":"BE",
    "sg:address":"Waregemseweg 146",
    "sg:city":"Wortegem-petegem (wortegem)",
    "sg:classifiers":[
        {
            "category":"Home & Garden",
            "subcategory":"Carpets & Floor Coverings",
            "type":"Retail Goods"
        }
    ],
    "sg:phone":"+32 56 69 42 00",
    "sg:postcode":"9790",
    "sg:province":"Oost-Vlaanderen",
    "sg:tags":[
        "house",
        "prefabricated"
    ],
    "wof:name":"Danilith-delmulle",
    "wof:placetype":"venue"
},
  "geometry": {"coordinates":[3.4789509773,50.8639297485],"type":"Point"}
}