{
  "type": "Feature",
  "properties": {
    "iso:country":"BE",
    "sg:address":"Kantweg 26",
    "sg:city":"Malle",
    "sg:orig_category":"Kruideniers Voedingsspeciaalzaken",
    "sg:phone":"+32 3 312 05 06",
    "sg:postcode":"2390",
    "sg:province":"Antwerpen",
    "wof:name":"Kanthoeve",
    "wof:placetype":"venue"
},
  "geometry": {"coordinates":[4.7240490913,51.3157272339],"type":"Point"}
}