{
  "type": "Feature",
  "properties": {
    "addr:full":"Wingenestraat 12 Aalter Oost-Vlaanderen 9880",
    "addr:housenumber":"12",
    "addr:postcode":"9880",
    "addr:street":"Wingenestraat",
    "iso:country":"BE",
    "sg:address":"Wingenestraat 12",
    "sg:city":"Aalter",
    "sg:classifiers":[
        {
            "category":"Cafe",
            "type":"Food & Drink"
        }
    ],
    "sg:phone":"+32 9 374 09 40",
    "sg:postcode":"9880",
    "sg:province":"Oost-Vlaanderen",
    "sg:tags":[
        "caf\u00e9s"
    ],
    "wof:name":"Helena Van Den Bussche",
    "wof:placetype":"venue"
},
  "geometry": {"coordinates":[3.3609399796,51.088973999],"type":"Point"}
}