{
  "type": "Feature",
  "properties": {
    "addr:full":"Planchestraat 62 Vloesberg/flobecq Hainaut 7880",
    "addr:housenumber":"62",
    "addr:postcode":"7880",
    "addr:street":"Planchestraat;Hainaut",
    "iso:country":"BE",
    "sg:address":"Planchestraat 62",
    "sg:city":"Vloesberg/flobecq",
    "sg:orig_category":"Herstelling horloges and juwelen Juwelen and horloges",
    "sg:phone":"+32 68 44 82 35",
    "sg:postcode":"7880",
    "sg:province":"Hainaut",
    "wof:name":"Andre Buidin",
    "wof:placetype":"venue"
},
  "geometry": {"coordinates":[3.7384300232,50.7368011475],"type":"Point"}
}