{
  "type": "Feature",
  "properties": {
    "addr:full":"Rootenstraat 8b52 Genk Limburg 3600",
    "addr:housenumber":"8b52",
    "addr:postcode":"3600",
    "addr:street":"Rootenstraat",
    "iso:country":"BE",
    "sg:address":"Rootenstraat 8b52",
    "sg:city":"Genk",
    "sg:orig_category":"Opticiens",
    "sg:phone":"+32 89 35 31 83",
    "sg:postcode":"3600",
    "sg:province":"Limburg",
    "wof:name":"Optiek Roterman",
    "wof:placetype":"venue"
},
  "geometry": {"coordinates":[5.5032610893,50.9652328491],"type":"Point"}
}