{
  "type": "Feature",
  "properties": {
    "addr:full":"Groenpark 30 De Pinte Oost-Vlaanderen 9840",
    "addr:housenumber":"30",
    "addr:postcode":"9840",
    "addr:street":"Groenpark",
    "iso:country":"BE",
    "sg:address":"Groenpark 30",
    "sg:city":"De Pinte",
    "sg:classifiers":[
        {
            "category":"Health Services",
            "subcategory":"Doctor",
            "type":"Services"
        }
    ],
    "sg:phone":"+32 9 282 34 69",
    "sg:postcode":"9840",
    "sg:province":"Oost-Vlaanderen",
    "sg:tags":[
        "medicinephysicians",
        "surgeon"
    ],
    "wof:name":"D'halluin F",
    "wof:placetype":"venue"
},
  "geometry": {"coordinates":[3.6475009918,50.9941673279],"type":"Point"}
}