{
  "type": "Feature",
  "properties": {
    "iso:country":"BE",
    "sg:address":"Rue Bouvier-washer 7",
    "sg:city":"Kraainem/kraainem",
    "sg:orig_category":"Producteurs de fruits",
    "sg:phone":"+32 2 782 03 78",
    "sg:postcode":"1950",
    "sg:province":"Vlaams-Brabant",
    "wof:name":"Raoul Nevens",
    "wof:placetype":"venue"
},
  "geometry": {"coordinates":[4.4683828354,50.8484764099],"type":"Point"}
}