{
  "type": "Feature",
  "properties": {
    "iso:country":"BE",
    "sg:address":"Paardestraat 48",
    "sg:city":"Erpe-mere",
    "sg:orig_category":"Installatie van houten of kunststof schrijnwerk",
    "sg:phone":"+32 53 80 25 39",
    "sg:postcode":"9420",
    "sg:province":"Oost-Vlaanderen",
    "wof:name":"Eddy Janssens",
    "wof:placetype":"venue"
},
  "geometry": {"coordinates":[3.9347031116,50.9381408691],"type":"Point"}
}