{
  "type": "Feature",
  "properties": {
    "iso:country":"BE",
    "sg:address":"Sint-pieter 61",
    "sg:city":"Lanaken (rekem)",
    "sg:classifiers":[
        {
            "category":"Professional",
            "subcategory":"Management & Consulting",
            "type":"Services"
        }
    ],
    "sg:phone":"+32 89 71 63 98",
    "sg:postcode":"3621",
    "sg:province":"Limburg",
    "sg:tags":[
        "consultant",
        "agency",
        "advertising"
    ],
    "wof:name":"Alert Bvba",
    "wof:placetype":"venue"
},
  "geometry": {"coordinates":[5.700220108,50.9237518311],"type":"Point"}
}