{
  "type": "Feature",
  "properties": {
    "iso:country":"BE",
    "sg:address":"Chant-des-oiseaux 1",
    "sg:city":"Couvin",
    "sg:orig_category":"Instituts pour adultes moins valides. Entreprises de travail adapt\u00e9",
    "sg:phone":"+32 60 34 70 09",
    "sg:postcode":"5660",
    "sg:province":"Namur",
    "wof:name":"Les Goelands",
    "wof:placetype":"venue"
},
  "geometry": {"coordinates":[4.4979538918,50.0542678833],"type":"Point"}
}