{
  "type": "Feature",
  "properties": {
    "addr:full":"Rechtestraat 42 Kortenberg Vlaams-Brabant 3071",
    "addr:housenumber":"42",
    "addr:postcode":"3071",
    "addr:street":"Rechtestraat;Vlaams-Brabant",
    "iso:country":"BE",
    "sg:address":"Rechtestraat 42",
    "sg:city":"Kortenberg",
    "sg:orig_category":"Fotografen and fotostudio's",
    "sg:phone":"+32 2 759 40 01",
    "sg:postcode":"3071",
    "sg:province":"Vlaams-Brabant",
    "wof:name":"Jozef Verhoogen",
    "wof:placetype":"venue"
},
  "geometry": {"coordinates":[4.590531826,50.9085502625],"type":"Point"}
}