{
  "type": "Feature",
  "properties": {
    "addr:full":"Rue De L'eglise 14 Verlaine Li\u00e8ge 4537",
    "addr:housenumber":"14",
    "addr:postcode":"4537",
    "addr:street":"Rue De L'Eglise",
    "iso:country":"BE",
    "sg:address":"Rue De L'eglise 14",
    "sg:city":"Verlaine",
    "sg:classifiers":[
        {
            "category":"Professional",
            "subcategory":"Accounting & Tax Preparation",
            "type":"Services"
        }
    ],
    "sg:phone":"+32 4 336 21 77",
    "sg:postcode":"4537",
    "sg:province":"Li\u00e8ge",
    "sg:tags":[
        "bookkeeper"
    ],
    "wof:name":"Tibo A",
    "wof:placetype":"venue"
},
  "geometry": {"coordinates":[5.3179340363,50.6085319519],"type":"Point"}
}