{
  "type": "Feature",
  "properties": {
    "addr:full":"Olympische Dreef 15 Anderlecht Bruxelles-Capitale 1070",
    "addr:housenumber":"15",
    "addr:postcode":"1070",
    "addr:street":"Olympische Dreef",
    "iso:country":"BE",
    "sg:address":"Olympische Dreef 15",
    "sg:city":"Anderlecht",
    "sg:classifiers":[
        {
            "category":"Government",
            "subcategory":"Fire Station",
            "type":"Public Place"
        }
    ],
    "sg:phone":"+32 2 558 55 54",
    "sg:postcode":"1070",
    "sg:province":"Bruxelles-Capitale",
    "sg:tags":[
        "packard",
        "nec",
        "bell"
    ],
    "wof:name":"Cora Anderlecht",
    "wof:placetype":"venue"
},
  "geometry": {"coordinates":[4.2767281532,50.8199539185],"type":"Point"}
}