{
  "type": "Feature",
  "properties": {
    "iso:country":"BE",
    "sg:address":"Chauss\u00e9e De Charleroi 91",
    "sg:city":"Charleroi (gilly)",
    "sg:classifiers":[
        {
            "category":"Professional",
            "subcategory":"Engineering",
            "type":"Services"
        }
    ],
    "sg:phone":"+32 71 28 76 14",
    "sg:postcode":"6060",
    "sg:province":"Hainaut",
    "sg:tags":[
        "-"
    ],
    "wof:name":"Ace",
    "wof:placetype":"venue"
},
  "geometry": {"coordinates":[4.4738240242,50.4016075134],"type":"Point"}
}