{
  "type": "Feature",
  "properties": {
    "addr:full":"Rue De La Loi 11 La Louviere Hainaut 7100",
    "addr:housenumber":"11",
    "addr:postcode":"7100",
    "addr:street":"Rue De La Loi",
    "iso:country":"BE",
    "sg:address":"Rue De La Loi 11",
    "sg:city":"La Louviere",
    "sg:classifiers":[
        {
            "category":"Personal",
            "subcategory":"Beauty Salon",
            "type":"Services"
        }
    ],
    "sg:phone":"+32 64 22 63 08",
    "sg:postcode":"7100",
    "sg:province":"Hainaut",
    "sg:tags":[
        "de",
        "coiffure"
    ],
    "wof:name":"Coiffure Paolo",
    "wof:placetype":"venue"
},
  "geometry": {"coordinates":[4.1864719391,50.4782295227],"type":"Point"}
}