{
  "type": "Feature",
  "properties": {
    "addr:full":"Rue Hector Denis 132 Saint-nicolas Li\u00e8ge 4420",
    "addr:housenumber":"132",
    "addr:postcode":"4420",
    "addr:street":"Rue Hector Denis",
    "iso:country":"BE",
    "sg:address":"Rue Hector Denis 132",
    "sg:city":"Saint-nicolas",
    "sg:orig_category":"Services de Nettoyage and de D\u00e9sinfection",
    "sg:phone":"+32 4 263 82 71",
    "sg:postcode":"4420",
    "sg:province":"Li\u00e8ge",
    "wof:name":"Net-o-vac",
    "wof:placetype":"venue"
},
  "geometry": {"coordinates":[5.5270190239,50.6433448792],"type":"Point"}
}