{
  "type": "Feature",
  "properties": {
    "iso:country":"BE",
    "sg:address":"Zuivelmarkt 40",
    "sg:city":"Hasselt",
    "sg:orig_category":"Journaux. Tabac",
    "sg:phone":"+32 11 22 60 68",
    "sg:postcode":"3500",
    "sg:province":"Limburg",
    "wof:name":"Aktua Press",
    "wof:placetype":"venue"
},
  "geometry": {"coordinates":[5.3398370743,50.9316253662],"type":"Point"}
}