{
  "type": "Feature",
  "properties": {
    "iso:country":"BE",
    "sg:address":"Novillesquare 3b2",
    "sg:city":"Koekelberg/koekelberg",
    "sg:orig_category":"Artsen and specialisten",
    "sg:phone":"+32 2 414 25 30",
    "sg:postcode":"1081",
    "sg:province":"Bruxelles-Capitale",
    "wof:name":"Danielle Watelet",
    "wof:placetype":"venue"
},
  "geometry": {"coordinates":[4.3343892097,50.859336853],"type":"Point"}
}