{
  "type": "Feature",
  "properties": {
    "iso:country":"BE",
    "sg:address":"Avenue L\u00e9on Delcoigne 11",
    "sg:city":"Leuze-en-hainaut",
    "sg:classifiers":[
        {
            "category":"Social Services",
            "type":"Services"
        }
    ],
    "sg:phone":"+32 69 66 55 73",
    "sg:postcode":"7900",
    "sg:province":"Hainaut",
    "wof:name":"Foyer Leuzois Sc (le)",
    "wof:placetype":"venue"
},
  "geometry": {"coordinates":[3.6146359444,50.5965156555],"type":"Point"}
}