{
  "type": "Feature",
  "properties": {
    "addr:full":"Vichtseweg 142 Waregem West-Vlaanderen 8790",
    "addr:housenumber":"142",
    "addr:postcode":"8790",
    "iso:country":"BE",
    "sg:address":"Vichtseweg 142",
    "sg:city":"Waregem",
    "sg:orig_category":"Produits surgel\u00e9s Gr",
    "sg:phone":"+32 56 77 71 71",
    "sg:postcode":"8790",
    "sg:province":"West-Vlaanderen",
    "wof:name":"De Witte",
    "wof:placetype":"venue"
},
  "geometry": {"coordinates":[3.4084630013,50.8548698425],"type":"Point"}
}