{
  "type": "Feature",
  "properties": {
    "addr:full":"Rue Spintay 50 Verviers Li\u00e8ge 4800",
    "addr:housenumber":"50",
    "addr:postcode":"4800",
    "addr:street":"Rue Spintay",
    "iso:country":"BE",
    "sg:address":"Rue Spintay 50",
    "sg:city":"Verviers",
    "sg:orig_category":"Apotheken",
    "sg:phone":"+32 87 33 45 89",
    "sg:postcode":"4800",
    "sg:province":"Li\u00e8ge",
    "wof:name":"Pharmacie Populaire",
    "wof:placetype":"venue"
},
  "geometry": {"coordinates":[5.8594508171,50.5917663574],"type":"Point"}
}