{
  "type": "Feature",
  "properties": {
    "addr:full":"Ivoz-ramet 5 Flemalle Li\u00e8ge 4400",
    "addr:housenumber":"5",
    "addr:postcode":"4400",
    "addr:street":"Ivoz-Ramet",
    "iso:country":"BE",
    "sg:address":"Ivoz-ramet 5",
    "sg:city":"Flemalle",
    "sg:orig_category":"Travaux d'isolation. Agences d'exp\u00e9dition. Appareils de pulv\u00e9risation Fab",
    "sg:phone":"+32 4 336 72 82",
    "sg:postcode":"4400",
    "sg:province":"Li\u00e8ge",
    "wof:name":"R.n.i.",
    "wof:placetype":"venue"
},
  "geometry": {"coordinates":[5.4632678032,50.5883255005],"type":"Point"}
}