{
  "type": "Feature",
  "properties": {
    "addr:full":"Route D'insepr\u00e9 44 Namur (malonne) Namur 5020",
    "addr:housenumber":"44",
    "addr:postcode":"5020",
    "addr:street":"Route D'Insepre \u0301",
    "iso:country":"BE",
    "sg:address":"Route D'insepr\u00e9 44",
    "sg:city":"Namur (malonne)",
    "sg:classifiers":[
        {
            "category":"Health Services",
            "subcategory":"Health Practitioner",
            "type":"Services"
        }
    ],
    "sg:phone":"+32 81 44 47 75",
    "sg:postcode":"5020",
    "sg:province":"Namur",
    "sg:tags":[
        "physiotherapist"
    ],
    "wof:name":"Wiame Th\u00e9r\u00e8se",
    "wof:placetype":"venue"
},
  "geometry": {"coordinates":[4.8080191612,50.422668457],"type":"Point"}
}