{
  "type": "Feature",
  "properties": {
    "addr:full":"Rue De Scoumont 30 Pont-\u00c0-celles Hainaut 6230",
    "addr:housenumber":"30",
    "addr:postcode":"6230",
    "addr:street":"Rue De Scoumont",
    "iso:country":"BE",
    "sg:address":"Rue De Scoumont 30",
    "sg:city":"Pont-\u00c0-celles",
    "sg:orig_category":"Loodgieterij, verwarming and sanitaire installaties",
    "sg:phone":"+32 67 87 80 28",
    "sg:postcode":"6230",
    "sg:province":"Hainaut",
    "wof:name":"Lacroix",
    "wof:placetype":"venue"
},
  "geometry": {"coordinates":[4.32041502,50.5403862],"type":"Point"}
}