{
  "type": "Feature",
  "properties": {
    "iso:country":"BE",
    "sg:address":"Eendendreef 5",
    "sg:city":"Oud-turnhout",
    "sg:orig_category":"Beheer onroerend goed",
    "sg:phone":"+32 14 45 14 14",
    "sg:postcode":"2360",
    "sg:province":"Antwerpen",
    "wof:name":"Hl-invest",
    "wof:placetype":"venue"
},
  "geometry": {"coordinates":[5.0304579735,51.3126487732],"type":"Point"}
}