{
  "type": "Feature",
  "properties": {
    "iso:country":"BE",
    "sg:address":"Voorne 13",
    "sg:city":"Zoersel",
    "sg:orig_category":"R\u00e9alisation de programmes and logiciels",
    "sg:phone":"+32 3 309 95 82",
    "sg:postcode":"2980",
    "sg:province":"Antwerpen",
    "wof:name":"J.l.c. Mailing",
    "wof:placetype":"venue"
},
  "geometry": {"coordinates":[4.7018370628,51.2685966492],"type":"Point"}
}