{
  "type": "Feature",
  "properties": {
    "iso:country":"BE",
    "sg:address":"Wittepaalstraat 37",
    "sg:city":"Gent",
    "sg:orig_category":"Bloemen and planten Gh",
    "sg:phone":"+32 9 222 15 08",
    "sg:postcode":"9051",
    "sg:province":"Oost-Vlaanderen",
    "wof:name":"De Bruycker",
    "wof:placetype":"venue"
},
  "geometry": {"coordinates":[3.6683819294,51.020690918],"type":"Point"}
}