{
  "type": "Feature",
  "properties": {
    "iso:country":"BE",
    "sg:address":"Brekelen 8",
    "sg:city":"Wuustwezel",
    "sg:orig_category":"Woningbouw",
    "sg:phone":"+32 3 669 90 58",
    "sg:postcode":"2990",
    "sg:province":"Antwerpen",
    "wof:name":"Bouwwerken A Van De Pol",
    "wof:placetype":"venue"
},
  "geometry": {"coordinates":[4.5874738693,51.3882675171],"type":"Point"}
}