{
  "type": "Feature",
  "properties": {
    "addr:full":"Avenue Des Hortensias 5 Sint-genesius-rode/rhode-saint-genese Vlaams-Brabant 1640",
    "addr:housenumber":"5",
    "addr:postcode":"1640",
    "addr:street":"Avenue Des Hortensias",
    "iso:country":"BE",
    "sg:address":"Avenue Des Hortensias 5",
    "sg:city":"Sint-genesius-rode/rhode-saint-genese",
    "sg:orig_category":"Studios photographiques",
    "sg:phone":"+32 2 358 12 30",
    "sg:postcode":"1640",
    "sg:province":"Vlaams-Brabant",
    "wof:name":"Lucas Van Lieshout",
    "wof:placetype":"venue"
},
  "geometry": {"coordinates":[4.3749990463,50.7492294312],"type":"Point"}
}