{
  "type": "Feature",
  "properties": {
    "addr:full":"Quai Godefroid Kurth 80 Li\u00c8ge Li\u00e8ge 4020",
    "addr:housenumber":"80",
    "addr:postcode":"4020",
    "addr:street":"Quai Godefroid Kurth",
    "iso:country":"BE",
    "sg:address":"Quai Godefroid Kurth 80",
    "sg:city":"Li\u00c8ge",
    "sg:orig_category":"Elektrische installaties voor woningen",
    "sg:phone":"+32 4 342 45 31",
    "sg:postcode":"4020",
    "sg:province":"Li\u00e8ge",
    "wof:name":"Snijders Electro",
    "wof:placetype":"venue"
},
  "geometry": {"coordinates":[5.5946960449,50.6471214294],"type":"Point"}
}