{
  "type": "Feature",
  "properties": {
    "iso:country":"BE",
    "sg:address":"Rue De Namur 34",
    "sg:city":"Ch\u00e2telet",
    "sg:classifiers":[
        {
            "category":"Personal",
            "subcategory":"Beauty Salon",
            "type":"Services"
        }
    ],
    "sg:phone":"+32 71 38 68 16",
    "sg:postcode":"6200",
    "sg:province":"Hainaut",
    "sg:tags":[
        "lady",
        "-",
        "hairdressing"
    ],
    "wof:name":"Mireille Coiffure",
    "wof:placetype":"venue"
},
  "geometry": {"coordinates":[4.5302109718,50.4010543823],"type":"Point"}
}