{
  "type": "Feature",
  "properties": {
    "iso:country":"BE",
    "sg:address":"Avenue Des Alli\u00e9s 11",
    "sg:city":"Charleroi",
    "sg:classifiers":[
        {
            "category":"Organizations",
            "subcategory":"Community Association",
            "type":"Services"
        }
    ],
    "sg:phone":"+32 71 32 45 31",
    "sg:postcode":"6000",
    "sg:province":"Hainaut",
    "sg:tags":[
        "cultural"
    ],
    "wof:name":"Paix Sur Terre",
    "wof:placetype":"venue"
},
  "geometry": {"coordinates":[4.4400210381,50.4109077454],"type":"Point"}
}