{
  "type": "Feature",
  "properties": {
    "addr:full":"Liersesteenweg 44 Grobbendonk Antwerpen 2280",
    "addr:housenumber":"44",
    "addr:postcode":"2280",
    "addr:street":"Liersesteenweg",
    "iso:country":"BE",
    "sg:address":"Liersesteenweg 44",
    "sg:city":"Grobbendonk",
    "sg:orig_category":"Loodgieterij, verwarming and sanitaire installaties",
    "sg:phone":"+32 14 51 24 15",
    "sg:postcode":"2280",
    "sg:province":"Antwerpen",
    "wof:name":"Luypaerts Guido",
    "wof:placetype":"venue"
},
  "geometry": {"coordinates":[4.7392601967,51.1721954346],"type":"Point"}
}