{
  "type": "Feature",
  "properties": {
    "addr:full":"Louis Van Bauwelstraat 20 Heist-op-den-berg Antwerpen 2222",
    "addr:housenumber":"20",
    "addr:postcode":"2222",
    "addr:street":"Louis Van Bauwelstraat",
    "iso:country":"BE",
    "sg:address":"Louis Van Bauwelstraat 20",
    "sg:city":"Heist-op-den-berg",
    "sg:orig_category":"Boucheries",
    "sg:phone":"+32 14 26 09 27",
    "sg:postcode":"2222",
    "sg:province":"Antwerpen",
    "wof:name":"Julien Martens",
    "wof:placetype":"venue"
},
  "geometry": {"coordinates":[4.796459198,51.106136322],"type":"Point"}
}