{
  "type": "Feature",
  "properties": {
    "iso:country":"BE",
    "sg:address":"Molenstraat 31",
    "sg:city":"Aalst (hofstade)",
    "sg:classifiers":[
        {
            "category":"Building & Trades",
            "subcategory":"Pest Control",
            "type":"Services"
        }
    ],
    "sg:phone":"+32 53 77 89 71",
    "sg:postcode":"9308",
    "sg:province":"Oost-Vlaanderen",
    "sg:tags":[
        "industry",
        "-",
        "plastic"
    ],
    "wof:name":"Huylebroeck Gebr Bvba",
    "wof:placetype":"venue"
},
  "geometry": {"coordinates":[4.0412797928,50.9389457703],"type":"Point"}
}