{
  "type": "Feature",
  "properties": {
    "addr:full":"Fonteinstraat 75 Box 9 Leuven Vlaams-Brabant 3000",
    "addr:housenumber":"75;9",
    "addr:postcode":"3000",
    "addr:street":"Fonteinstraat;Box",
    "iso:country":"BE",
    "sg:address":"Fonteinstraat 75 Box 9",
    "sg:city":"Leuven",
    "sg:classifiers":[
        {
            "category":"Personal",
            "subcategory":"Beauty Salon",
            "type":"Services"
        }
    ],
    "sg:phone":"+32 16 20 23 28",
    "sg:postcode":"3000",
    "sg:province":"Vlaams-Brabant",
    "sg:tags":[
        "lady",
        "-",
        "hairdressing"
    ],
    "wof:name":"Fanity",
    "wof:placetype":"venue"
},
  "geometry": {"coordinates":[4.6937851906,50.8834609985],"type":"Point"}
}