{
  "type": "Feature",
  "properties": {
    "iso:country":"BE",
    "sg:address":"Kerkstraat 38",
    "sg:city":"Lovendegem",
    "sg:orig_category":"Rev\u00eatements pour sols and murs. Peinture. Installation de serres, double vitrage and fen\u00eatres",
    "sg:phone":"+32 9 372 04 90",
    "sg:postcode":"9920",
    "sg:province":"Oost-Vlaanderen",
    "wof:name":"Kurt Cosyn",
    "wof:placetype":"venue"
},
  "geometry": {"coordinates":[3.6089301109,51.094329834],"type":"Point"}
}