{
  "type": "Feature",
  "properties": {
    "iso:country":"BE",
    "sg:address":"Wezelhoevenweg 40",
    "sg:city":"Mol",
    "sg:classifiers":[
        {
            "category":"Building & Trades",
            "subcategory":"Landscaping Services",
            "type":"Services"
        }
    ],
    "sg:phone":"+32 14 81 75 32",
    "sg:postcode":"2400",
    "sg:province":"Antwerpen",
    "sg:tags":[
        "access",
        "pond",
        "laying-out",
        "-"
    ],
    "wof:name":"Van Baelen",
    "wof:placetype":"venue"
},
  "geometry": {"coordinates":[5.183716774,51.1858253479],"type":"Point"}
}