{
  "type": "Feature",
  "properties": {
    "addr:full":"Grand-rue 48 Moeskroen/mouscron Hainaut 7700",
    "addr:housenumber":"48",
    "addr:postcode":"7700",
    "addr:street":"Grand-Rue",
    "iso:country":"BE",
    "sg:address":"Grand-rue 48",
    "sg:city":"Moeskroen/mouscron",
    "sg:orig_category":"Pharmaciens",
    "sg:phone":"+32 56 33 04 97",
    "sg:postcode":"7700",
    "sg:province":"Hainaut",
    "wof:name":"Multipharma",
    "wof:placetype":"venue"
},
  "geometry": {"coordinates":[3.2323200703,50.7400932312],"type":"Point"}
}