{
  "type": "Feature",
  "properties": {
    "addr:full":"Chauss\u00e9e De Louvain 259 Bruxelles (saint-josse-ten-noode) Bruxelles-Capitale 1210",
    "addr:housenumber":"259",
    "addr:postcode":"1210",
    "addr:street":"Chausse\u0301E De Louvain",
    "iso:country":"BE",
    "sg:address":"Chauss\u00e9e De Louvain 259",
    "sg:city":"Bruxelles (saint-josse-ten-noode)",
    "sg:classifiers":[
        {
            "category":"Bakery",
            "type":"Food & Drink"
        }
    ],
    "sg:phone":"+32 2 735 44 56",
    "sg:postcode":"1210",
    "sg:province":"Bruxelles-Capitale",
    "sg:tags":[
        "confectioner",
        "baker"
    ],
    "wof:name":"Valisette (la)",
    "wof:placetype":"venue"
},
  "geometry": {"coordinates":[4.383190155,50.8511695862],"type":"Point"}
}