{
  "type": "Feature",
  "properties": {
    "iso:country":"BE",
    "sg:address":"Diepestraat 2",
    "sg:city":"Lovendegem",
    "sg:classifiers":[
        {
            "category":"Bars & Pubs",
            "type":"Food & Drink"
        }
    ],
    "sg:phone":"+32 9 372 62 57",
    "sg:postcode":"9920",
    "sg:province":"Oost-Vlaanderen",
    "wof:name":"Oude Paardestal (de)",
    "wof:placetype":"venue"
},
  "geometry": {"coordinates":[3.6046450138,51.0947990417],"type":"Point"}
}