{
  "type": "Feature",
  "properties": {
    "addr:full":"Rue Lambert Dewonck 30 Ans (alleur) Li\u00e8ge 4432",
    "addr:housenumber":"30",
    "addr:postcode":"4432",
    "addr:street":"Rue Lambert Dewonck",
    "iso:country":"BE",
    "sg:address":"Rue Lambert Dewonck 30",
    "sg:city":"Ans (alleur)",
    "sg:classifiers":[
        {
            "category":"Personal",
            "subcategory":"Barber",
            "type":"Services"
        }
    ],
    "sg:phone":"+32 4 263 37 24",
    "sg:postcode":"4432",
    "sg:province":"Li\u00e8ge",
    "sg:tags":[
        "gentleman",
        "salon",
        "-",
        "hairdressing"
    ],
    "wof:name":"Regency",
    "wof:placetype":"venue"
},
  "geometry": {"coordinates":[5.5135269165,50.6706466675],"type":"Point"}
}