{
  "type": "Feature",
  "properties": {
    "iso:country":"BE",
    "sg:address":"Schuurwaverstraat 46",
    "sg:city":"Scherpenheuvel-zichem",
    "sg:classifiers":[
        {
            "category":"Insurance",
            "subcategory":"Life Insurance",
            "type":"Services"
        }
    ],
    "sg:phone":"+32 13 77 59 75",
    "sg:postcode":"3270",
    "sg:province":"Vlaams-Brabant",
    "sg:tags":[
        "assurance"
    ],
    "wof:name":"J. Van Aerschot",
    "wof:placetype":"venue"
},
  "geometry": {"coordinates":[4.9665150642,50.9783477783],"type":"Point"}
}