{
  "type": "Feature",
  "properties": {
    "addr:full":"Lange Leemstraat 51 Box 14 Antwerpen Antwerpen 2018",
    "addr:housenumber":"51 box 14",
    "addr:postcode":"2018",
    "addr:street":"Lange Leemstraat",
    "iso:country":"BE",
    "sg:address":"Lange Leemstraat 51 Box 14",
    "sg:city":"Antwerpen",
    "sg:classifiers":[
        {
            "category":"Retail",
            "subcategory":"Event Space",
            "type":"Services"
        }
    ],
    "sg:phone":"+32 3 289 73 96",
    "sg:postcode":"2018",
    "sg:province":"Antwerpen",
    "sg:tags":[
        "organisation"
    ],
    "wof:name":"Kachoui L",
    "wof:placetype":"venue"
},
  "geometry": {"coordinates":[4.4110431671,51.2092628479],"type":"Point"}
}