{
  "type": "Feature",
  "properties": {
    "iso:country":"BE",
    "sg:address":"Rue Centrale 34",
    "sg:city":"Weismes (robertville)",
    "sg:classifiers":[
        {
            "category":"Health Services",
            "subcategory":"Dentist",
            "type":"Services"
        }
    ],
    "sg:phone":"+32 80 44 85 85",
    "sg:postcode":"4950",
    "sg:province":"Li\u00e8ge",
    "wof:name":"Dupont C\u00e9cile",
    "wof:placetype":"venue"
},
  "geometry": {"coordinates":[6.1229548454,50.4548187256],"type":"Point"}
}