{
  "type": "Feature",
  "properties": {
    "iso:country":"BE",
    "sg:address":"Mandeweg 21",
    "sg:city":"Sint-laureins",
    "sg:orig_category":"Aanleg van opritten and terreinen bij woningen Plaatsen van vloer- and muurbekleding",
    "sg:phone":"+32 9 379 85 41",
    "sg:postcode":"9982",
    "sg:province":"Oost-Vlaanderen",
    "wof:name":"Geert D\u00b4hoore",
    "wof:placetype":"venue"
},
  "geometry": {"coordinates":[3.5660800934,51.2483177185],"type":"Point"}
}