{
  "type": "Feature",
  "properties": {
    "addr:full":"Avenue Arthur-tagnon 2 Paliseul Luxembourg 6850",
    "addr:housenumber":"2",
    "addr:postcode":"6850",
    "addr:street":"Avenue Arthur-Tagnon",
    "iso:country":"BE",
    "sg:address":"Avenue Arthur-tagnon 2",
    "sg:city":"Paliseul",
    "sg:orig_category":"Enseignement maternel and primaire",
    "sg:phone":"+32 61 53 46 76",
    "sg:postcode":"6850",
    "sg:province":"Luxembourg",
    "wof:name":"Ecole Primaire Libre",
    "wof:placetype":"venue"
},
  "geometry": {"coordinates":[5.1349849701,49.9033889771],"type":"Point"}
}