{
  "type": "Feature",
  "properties": {
    "iso:country":"BE",
    "sg:address":"Avenue De La Joyeuse Entr\u00e9e 82",
    "sg:city":"Mons",
    "sg:classifiers":[
        {
            "category":"Insurance",
            "subcategory":"Insurance Agent",
            "type":"Services"
        }
    ],
    "sg:phone":"+32 65 34 80 84",
    "sg:postcode":"7000",
    "sg:province":"Hainaut",
    "sg:tags":[
        "broker"
    ],
    "wof:name":"Pelateri P (bureau)",
    "wof:placetype":"venue"
},
  "geometry": {"coordinates":[3.9522509575,50.4547271729],"type":"Point"}
}