{
  "type": "Feature",
  "properties": {
    "addr:full":"Honegemstraat 101 Erpe-mere (erpe) Oost-Vlaanderen 9420",
    "addr:housenumber":"101",
    "addr:postcode":"9420",
    "addr:street":"Honegemstraat",
    "iso:country":"BE",
    "sg:address":"Honegemstraat 101",
    "sg:city":"Erpe-mere (erpe)",
    "sg:classifiers":[
        {
            "category":"Personal",
            "subcategory":"Beauty Salon",
            "type":"Services"
        }
    ],
    "sg:phone":"+32 53 70 92 69",
    "sg:postcode":"9420",
    "sg:province":"Oost-Vlaanderen",
    "wof:name":"Adelante",
    "wof:placetype":"venue"
},
  "geometry": {"coordinates":[3.998085022,50.9509773254],"type":"Point"}
}