{
  "type": "Feature",
  "properties": {
    "addr:full":"Industrieweg 21 Lanaken Limburg 3620",
    "addr:housenumber":"21",
    "addr:postcode":"3620",
    "addr:street":"Industrieweg",
    "iso:country":"BE",
    "sg:address":"Industrieweg 21",
    "sg:city":"Lanaken",
    "sg:classifiers":[
        {
            "category":"Home & Garden",
            "subcategory":"Kitchen Supply",
            "type":"Retail Goods"
        }
    ],
    "sg:phone":"+32 89 71 77 11",
    "sg:postcode":"3620",
    "sg:province":"Limburg",
    "sg:tags":[
        "installation"
    ],
    "wof:name":"Thomas Leicht Keukens Nv",
    "wof:placetype":"venue"
},
  "geometry": {"coordinates":[5.6678318977,50.891418457],"type":"Point"}
}