{
  "type": "Feature",
  "properties": {
    "addr:full":"Bovenstraat 36 Riemst (kanne) Limburg 3770",
    "addr:housenumber":"36",
    "addr:postcode":"3770",
    "addr:street":"Bovenstraat",
    "iso:country":"BE",
    "sg:address":"Bovenstraat 36",
    "sg:city":"Riemst (kanne)",
    "sg:classifiers":[
        {
            "category":"Bakery",
            "type":"Food & Drink"
        }
    ],
    "sg:phone":"+32 12 45 17 75",
    "sg:postcode":"3770",
    "sg:province":"Limburg",
    "sg:tags":[
        "confectioner",
        "baker"
    ],
    "wof:name":"Daemen G",
    "wof:placetype":"venue"
},
  "geometry": {"coordinates":[5.6738438606,50.8118133545],"type":"Point"}
}