{
  "type": "Feature",
  "properties": {
    "iso:country":"BE",
    "sg:address":"Hauptstrasse 73",
    "sg:city":"Raeren",
    "sg:classifiers":[
        {
            "category":"Shopping",
            "subcategory":"Florist",
            "type":"Retail Goods"
        }
    ],
    "sg:phone":"+32 87 85 08 53",
    "sg:postcode":"4730",
    "sg:province":"Li\u00e8ge",
    "wof:name":"Blumenscheune",
    "wof:placetype":"venue"
},
  "geometry": {"coordinates":[6.1129288673,50.6746749878],"type":"Point"}
}