{
  "type": "Feature",
  "properties": {
    "addr:full":"Rue Du Parc 7 Tournai Hainaut 7500",
    "addr:housenumber":"7",
    "addr:postcode":"7500",
    "addr:street":"Rue Du Parc",
    "iso:country":"BE",
    "sg:address":"Rue Du Parc 7",
    "sg:city":"Tournai",
    "sg:classifiers":[
        {
            "category":"Professional",
            "subcategory":"Management & Consulting",
            "type":"Services"
        }
    ],
    "sg:phone":"+32 69 21 05 15",
    "sg:postcode":"7500",
    "sg:province":"Hainaut",
    "sg:tags":[
        "consultant"
    ],
    "wof:name":"Tournai Centre Ville Asbl",
    "wof:placetype":"venue"
},
  "geometry": {"coordinates":[3.3872520924,50.6088409424],"type":"Point"}
}