{
  "type": "Feature",
  "properties": {
    "iso:country":"BE",
    "sg:address":"Ronseweg 126",
    "sg:city":"Oudenaarde",
    "sg:orig_category":"Non-Classified Establishments",
    "sg:phone":"+32 55 31 44 23",
    "sg:postcode":"9700",
    "sg:province":"Oost-Vlaanderen",
    "wof:name":"Hensey",
    "wof:placetype":"venue"
},
  "geometry": {"coordinates":[3.6040151119,50.822769165],"type":"Point"}
}