{
  "type": "Feature",
  "properties": {
    "iso:country":"BE",
    "sg:address":"Rue Joseph Wauters 81",
    "sg:city":"Charleroi",
    "sg:orig_category":"Pain, p\u00e2tisseries and confiseries",
    "sg:phone":"+32 71 31 77 27",
    "sg:postcode":"6020",
    "sg:province":"Hainaut",
    "wof:name":"Pascal Dumont",
    "wof:placetype":"venue"
},
  "geometry": {"coordinates":[4.4309887886,50.4158935547],"type":"Point"}
}