{
  "type": "Feature",
  "properties": {
    "iso:country":"BE",
    "sg:address":"Svinkxstraat 18",
    "sg:city":"Koksijde",
    "sg:orig_category":"Graan, zaad and dierenvoeding Gh",
    "sg:phone":"+32 58 51 66 46",
    "sg:postcode":"8670",
    "sg:province":"West-Vlaanderen",
    "wof:name":"E & P Petfood",
    "wof:placetype":"venue"
},
  "geometry": {"coordinates":[2.6195130348,51.0906677246],"type":"Point"}
}