{
  "type": "Feature",
  "properties": {
    "addr:full":"Terlaenenstraat 35 Huldenberg (ottenburg) Vlaams-Brabant 3040",
    "addr:housenumber":"35",
    "addr:postcode":"3040",
    "addr:street":"Terlaenenstraat",
    "iso:country":"BE",
    "sg:address":"Terlaenenstraat 35",
    "sg:city":"Huldenberg (ottenburg)",
    "sg:classifiers":[
        {
            "category":"Health Services",
            "subcategory":"Medical Lab",
            "type":"Services"
        }
    ],
    "sg:phone":"+32 16 47 38 46",
    "sg:postcode":"3040",
    "sg:province":"Vlaams-Brabant",
    "sg:tags":[
        "laboratory",
        "dental"
    ],
    "wof:name":"Dental Restoration Art",
    "wof:placetype":"venue"
},
  "geometry": {"coordinates":[4.6113948822,50.7524909973],"type":"Point"}
}