{
  "type": "Feature",
  "properties": {
    "iso:country":"BE",
    "sg:address":"Chauss\u00e9e De Charleroi 579",
    "sg:city":"Waterloo",
    "sg:classifiers":[
        {
            "category":"Food & Beverages",
            "subcategory":"Supermarket",
            "type":"Retail Goods"
        }
    ],
    "sg:phone":"+32 2 389 27 11",
    "sg:postcode":"1410",
    "sg:province":"Brabant Wallon",
    "sg:tags":[
        "department",
        "store"
    ],
    "wof:name":"Bigg's Sa",
    "wof:placetype":"venue"
},
  "geometry": {"coordinates":[4.4088602066,50.6873626709],"type":"Point"}
}