{
  "type": "Feature",
  "properties": {
    "iso:country":"BE",
    "sg:address":"Rue De Blaregnies 13",
    "sg:city":"Qu\u00e9vy (aulnois)",
    "sg:classifiers":[
        {
            "category":"Sports & Exercise",
            "subcategory":"Stables",
            "type":"Entertainment"
        }
    ],
    "sg:phone":"+32 65 56 71 12",
    "sg:postcode":"7040",
    "sg:province":"Hainaut",
    "sg:tags":[
        "riding",
        "school"
    ],
    "wof:name":"Centre Equestre La Ferme Du Moulin",
    "wof:placetype":"venue"
},
  "geometry": {"coordinates":[3.9024240971,50.3436164856],"type":"Point"}
}