{
  "type": "Feature",
  "properties": {
    "addr:full":"Nijverheidskaai 232 Anderlecht Bruxelles-Capitale 1070",
    "addr:housenumber":"232",
    "addr:postcode":"1070",
    "addr:street":"Nijverheidskaai",
    "iso:country":"BE",
    "sg:address":"Nijverheidskaai 232",
    "sg:city":"Anderlecht",
    "sg:orig_category":"Huisvuilophaling and -verwerking Metaalvrije afvalrecyclage Opslagvoorzieningen",
    "sg:phone":"+32 2 521 45 75",
    "sg:postcode":"1070",
    "sg:province":"Bruxelles-Capitale",
    "wof:name":"R\u00c9cup\u00c9ration De Papiers",
    "wof:placetype":"venue"
},
  "geometry": {"coordinates":[4.318901062,50.8383598328],"type":"Point"}
}