{
  "type": "Feature",
  "properties": {
    "addr:full":"Roeselaarsestraat 127 Izegem West-Vlaanderen 8870",
    "addr:housenumber":"127",
    "addr:postcode":"8870",
    "addr:street":"Roeselaarsestraat",
    "iso:country":"BE",
    "sg:address":"Roeselaarsestraat 127",
    "sg:city":"Izegem",
    "sg:classifiers":[
        {
            "category":"Government",
            "subcategory":"Fire Station",
            "type":"Public Place"
        }
    ],
    "sg:phone":"+32 51 31 95 31",
    "sg:postcode":"8870",
    "sg:province":"West-Vlaanderen",
    "sg:tags":[
        "water",
        "restoration",
        "damage"
    ],
    "wof:name":"Schoonmaakbedrijf Degryse",
    "wof:placetype":"venue"
},
  "geometry": {"coordinates":[3.2062060833,50.919960022],"type":"Point"}
}