{
  "type": "Feature",
  "properties": {
    "iso:country":"BE",
    "sg:address":"Kennedylaan 6/8",
    "sg:city":"Tongeren",
    "sg:orig_category":"Enregistrements sonores. Location d'appareils audio-visuels",
    "sg:phone":"+32 12 23 37 12",
    "sg:postcode":"3700",
    "sg:province":"Limburg",
    "wof:name":"R.s. Geluidstechniek",
    "wof:placetype":"venue"
},
  "geometry": {"coordinates":[5.4620227814,50.7726516724],"type":"Point"}
}