{
  "type": "Feature",
  "properties": {
    "iso:country":"BE",
    "sg:address":"Kruibeke Steenweg 51",
    "sg:city":"Beveren (beveren-waas)",
    "sg:classifiers":[
        {
            "category":"Education",
            "subcategory":"School",
            "type":"Public Place"
        }
    ],
    "sg:phone":"+32 3 775 99 42",
    "sg:postcode":"9120",
    "sg:province":"Oost-Vlaanderen",
    "sg:tags":[
        "primary"
    ],
    "wof:name":"Kleuterschool Puithoek",
    "wof:placetype":"venue"
},
  "geometry": {"coordinates":[4.2624368668,51.2048797607],"type":"Point"}
}