{
  "type": "Feature",
  "properties": {
    "addr:full":"Tenbosch 2 Bruxelles Bruxelles-Capitale 1000",
    "addr:housenumber":"2",
    "addr:postcode":"1000",
    "addr:street":"Tenbosch",
    "iso:country":"BE",
    "sg:address":"Tenbosch 2",
    "sg:city":"Bruxelles",
    "sg:classifiers":[
        {
            "category":"Bars & Pubs",
            "type":"Food & Drink"
        }
    ],
    "sg:phone":"+32 2 646 23 77",
    "sg:postcode":"1000",
    "sg:province":"Bruxelles-Capitale",
    "sg:tags":[
        "tavern"
    ],
    "wof:name":"Number Two",
    "wof:placetype":"venue"
},
  "geometry": {"coordinates":[4.3667340279,50.8240013123],"type":"Point"}
}