{
  "type": "Feature",
  "properties": {
    "addr:full":"Muntstraat 15 Leuven Vlaams-Brabant 3000",
    "addr:housenumber":"15",
    "addr:postcode":"3000",
    "addr:street":"Muntstraat",
    "iso:country":"BE",
    "sg:address":"Muntstraat 15",
    "sg:city":"Leuven",
    "sg:classifiers":[
        {
            "category":"Bars & Pubs",
            "type":"Food & Drink"
        }
    ],
    "sg:phone":"+32 16 22 09 23",
    "sg:postcode":"3000",
    "sg:province":"Vlaams-Brabant",
    "sg:tags":[
        "tavern"
    ],
    "wof:name":"Kansel (de)",
    "wof:placetype":"venue"
},
  "geometry": {"coordinates":[4.7025718689,50.8782615662],"type":"Point"}
}