{
  "type": "Feature",
  "properties": {
    "iso:country":"BE",
    "sg:address":"Route De La Marache 4",
    "sg:city":"Lasne",
    "sg:orig_category":"Catering and organisatie van feesten Fast food and meeneem restaurants Restaurants",
    "sg:phone":"+32 2 633 13 74",
    "sg:postcode":"1380",
    "sg:province":"Brabant Wallon",
    "wof:name":"Auberge De La Roseraie",
    "wof:placetype":"venue"
},
  "geometry": {"coordinates":[4.483235836,50.6850166321],"type":"Point"}
}