{
  "type": "Feature",
  "properties": {
    "iso:country":"BE",
    "sg:address":"Rue De La Digue 18",
    "sg:city":"Charleroi",
    "sg:orig_category":"Artsen and specialisten",
    "sg:phone":"+32 71 33 21 01",
    "sg:postcode":"6000",
    "sg:province":"Hainaut",
    "wof:name":"Duc Tran Huu",
    "wof:placetype":"venue"
},
  "geometry": {"coordinates":[4.4382338524,50.410533905],"type":"Point"}
}