{
  "type": "Feature",
  "properties": {
    "iso:country":"BE",
    "sg:address":"Zuidstraat 210",
    "sg:city":"Ichtegem",
    "sg:orig_category":"Varkenskwekers",
    "sg:phone":"+32 50 20 10 01",
    "sg:postcode":"8480",
    "sg:province":"West-Vlaanderen",
    "wof:name":"Livinus Volcke",
    "wof:placetype":"venue"
},
  "geometry": {"coordinates":[3.055175066,51.111038208],"type":"Point"}
}