{
  "type": "Feature",
  "properties": {
    "addr:full":"Rue F\u00c9lix Delchambre 1 Faimes Li\u00e8ge 4317",
    "addr:housenumber":"1",
    "addr:postcode":"4317",
    "addr:street":"Rue Fe\u0301Lix Delchambre",
    "iso:country":"BE",
    "sg:address":"Rue F\u00c9lix Delchambre 1",
    "sg:city":"Faimes",
    "sg:orig_category":"Eleveurs de bovins",
    "sg:phone":"+32 19 56 63 67",
    "sg:postcode":"4317",
    "sg:province":"Li\u00e8ge",
    "wof:name":"De Marneffe Jacques & Fsls",
    "wof:placetype":"venue"
},
  "geometry": {"coordinates":[5.2432479858,50.6334381104],"type":"Point"}
}