{
  "type": "Feature",
  "properties": {
    "addr:full":"Steenakkerdr 4 Destelbergen Oost-Vlaanderen 9120",
    "addr:housenumber":"4",
    "addr:postcode":"9120",
    "addr:street":"Steenakkerdr",
    "iso:country":"BE",
    "sg:address":"Steenakkerdr 4",
    "sg:city":"Destelbergen",
    "sg:classifiers":[
        {
            "category":"Banks & Credit Unions",
            "subcategory":"Bank",
            "type":"Services"
        }
    ],
    "sg:phone":"+32 52 28 34 14",
    "sg:postcode":"9120",
    "sg:province":"Oost-Vlaanderen",
    "wof:name":"Famibank",
    "wof:placetype":"venue"
},
  "geometry": {"coordinates":[4.2362699509,51.2149009705],"type":"Point"}
}