{
  "type": "Feature",
  "properties": {
    "addr:full":"Wilderenlaan 14 Sint-truiden Limburg 3803",
    "addr:housenumber":"14",
    "addr:postcode":"3803",
    "addr:street":"Wilderenlaan",
    "iso:country":"BE",
    "sg:address":"Wilderenlaan 14",
    "sg:city":"Sint-truiden",
    "sg:classifiers":[
        {
            "category":"Sports & Exercise",
            "subcategory":"Sports Center",
            "type":"Entertainment"
        }
    ],
    "sg:phone":"+32 11 68 52 50",
    "sg:postcode":"3803",
    "sg:province":"Limburg",
    "sg:tags":[
        "terrain",
        "hors",
        "de",
        "installation",
        "sportifs"
    ],
    "wof:name":"Ruitershoeve",
    "wof:placetype":"venue"
},
  "geometry": {"coordinates":[5.14351511,50.8200912476],"type":"Point"}
}