{
  "type": "Feature",
  "properties": {
    "iso:country":"BE",
    "sg:address":"Zweepstraat 1",
    "sg:city":"Oud-turnhout",
    "sg:orig_category":"Diverse grafische activiteiten Drukkerijen and copyshops Fotogravure and zetwerk Secretariaatsdienst",
    "sg:phone":"+32 14 45 45 00",
    "sg:postcode":"2360",
    "sg:province":"Antwerpen",
    "wof:name":"Zetten",
    "wof:placetype":"venue"
},
  "geometry": {"coordinates":[4.9919967651,51.3132743835],"type":"Point"}
}