{
  "type": "Feature",
  "properties": {
    "addr:full":"Rue Jean-baptiste Decock 25-27 Bruxelles (molenbeek-saint-jean) Bruxelles-Capitale 1080",
    "addr:housenumber":"25-27",
    "addr:postcode":"1080",
    "addr:street":"Rue Jean-Baptiste Decock",
    "iso:country":"BE",
    "sg:address":"Rue Jean-baptiste Decock 25-27",
    "sg:city":"Bruxelles (molenbeek-saint-jean)",
    "sg:classifiers":[
        {
            "category":"Building & Trades",
            "subcategory":"Construction",
            "type":"Services"
        }
    ],
    "sg:phone":"+32 2 410 45 48",
    "sg:postcode":"1080",
    "sg:province":"Bruxelles-Capitale",
    "sg:tags":[
        "tool",
        "cutting"
    ],
    "wof:name":"C.b.v. Precisal-mooser Sa",
    "wof:placetype":"venue"
},
  "geometry": {"coordinates":[4.3275718689,50.8518943787],"type":"Point"}
}