{
  "type": "Feature",
  "properties": {
    "iso:country":"BE",
    "sg:address":"Av Moli\u00e8re 256",
    "sg:city":"Bruxelles",
    "sg:classifiers":[
        {
            "category":"Professional",
            "subcategory":"Advertising",
            "type":"Services"
        }
    ],
    "sg:phone":"+32 2 345 90 70",
    "sg:postcode":"1180",
    "sg:province":"Bruxelles-Capitale",
    "sg:tags":[
        "information",
        "medium",
        "communication"
    ],
    "wof:name":"Kompass Benelux",
    "wof:placetype":"venue"
},
  "geometry": {"coordinates":[4.3580589294,50.815574646],"type":"Point"}
}