{
  "type": "Feature",
  "properties": {
    "iso:country":"BE",
    "sg:address":"Riemesteenweg 54",
    "sg:city":"Evergem",
    "sg:classifiers":[
        {
            "category":"Restaurant",
            "type":"Food & Drink"
        }
    ],
    "sg:phone":"+32 9 344 75 44",
    "sg:postcode":"9940",
    "sg:province":"Oost-Vlaanderen",
    "sg:tags":[
        "caf\u00e9s"
    ],
    "wof:name":"Taverne Rita",
    "wof:placetype":"venue"
},
  "geometry": {"coordinates":[3.7606129646,51.1768455505],"type":"Point"}
}