{
  "type": "Feature",
  "properties": {
    "iso:country":"BE",
    "sg:address":"Rue De La Bruy\u00e8re 157",
    "sg:city":"Rixensart (genval)",
    "sg:classifiers":[
        {
            "category":"Professional",
            "subcategory":"Computer Services",
            "type":"Services"
        }
    ],
    "sg:phone":"+32 2 652 04 02",
    "sg:postcode":"1332",
    "sg:province":"Brabant Wallon",
    "sg:tags":[
        "-",
        "processing",
        "data",
        "software"
    ],
    "wof:name":"Biac Sprl",
    "wof:placetype":"venue"
},
  "geometry": {"coordinates":[4.4884037971,50.72448349],"type":"Point"}
}