{
  "type": "Feature",
  "properties": {
    "addr:full":"Roerdomplei 34 Kapellen Antwerpen 2950",
    "addr:housenumber":"34",
    "addr:postcode":"2950",
    "addr:street":"Roerdomplei",
    "iso:country":"BE",
    "sg:address":"Roerdomplei 34",
    "sg:city":"Kapellen",
    "sg:classifiers":[
        {
            "category":"Health Services",
            "subcategory":"Health Practitioner",
            "type":"Services"
        }
    ],
    "sg:phone":"+32 3 666 42 94",
    "sg:postcode":"2950",
    "sg:province":"Antwerpen",
    "sg:tags":[
        "osteopath"
    ],
    "wof:name":"Goovaerts L",
    "wof:placetype":"venue"
},
  "geometry": {"coordinates":[4.481274128,51.3399658203],"type":"Point"}
}