{
  "type": "Feature",
  "properties": {
    "iso:country":"BE",
    "sg:address":"Mariakerkelaan 373-375",
    "sg:city":"Oostende",
    "sg:classifiers":[
        {
            "category":"Health Services",
            "subcategory":"Dentist",
            "type":"Services"
        }
    ],
    "sg:phone":"+32 59 50 07 63",
    "sg:postcode":"8400",
    "sg:province":"West-Vlaanderen",
    "wof:name":"Tack K",
    "wof:placetype":"venue"
},
  "geometry": {"coordinates":[2.8910999298,51.2131690979],"type":"Point"}
}