{
  "type": "Feature",
  "properties": {
    "addr:full":"Leeuwerikstraat 4 Vleteren (westvleteren) West-Vlaanderen 8640",
    "addr:housenumber":"4",
    "addr:postcode":"8640",
    "addr:street":"Leeuwerikstraat",
    "iso:country":"BE",
    "sg:address":"Leeuwerikstraat 4",
    "sg:city":"Vleteren (westvleteren)",
    "sg:classifiers":[
        {
            "category":"Autos & Motor Vehicles",
            "subcategory":"Automobile Sales",
            "type":"Retail Goods"
        }
    ],
    "sg:phone":"+32 57 21 99 50",
    "sg:postcode":"8640",
    "sg:province":"West-Vlaanderen",
    "sg:tags":[
        "car",
        "used",
        "-"
    ],
    "wof:name":"Trendmobiel",
    "wof:placetype":"venue"
},
  "geometry": {"coordinates":[2.695661068,50.8964881897],"type":"Point"}
}