{
  "type": "Feature",
  "properties": {
    "addr:full":"Doornzele Dries 89 Evergem Oost-Vlaanderen 9940",
    "addr:housenumber":"89",
    "addr:postcode":"9940",
    "addr:street":"Dries;Oost-Vlaanderen",
    "iso:country":"BE",
    "sg:address":"Doornzele Dries 89",
    "sg:city":"Evergem",
    "sg:orig_category":"Artsen and specialisten",
    "sg:phone":"+32 9 253 16 36",
    "sg:postcode":"9940",
    "sg:province":"Oost-Vlaanderen",
    "wof:name":"Guido Housen",
    "wof:placetype":"venue"
},
  "geometry": {"coordinates":[3.7667639256,51.1441116333],"type":"Point"}
}