{
  "type": "Feature",
  "properties": {
    "iso:country":"BE",
    "sg:address":"Zonnebekestraat 87a",
    "sg:city":"Langemark-poelkapelle",
    "sg:orig_category":"Jardinage",
    "sg:phone":"+32 57 48 70 82",
    "sg:postcode":"8920",
    "sg:province":"West-Vlaanderen",
    "wof:name":"Patrick Vinckier - Decruw",
    "wof:placetype":"venue"
},
  "geometry": {"coordinates":[2.919770956,50.9132423401],"type":"Point"}
}