{
  "type": "Feature",
  "properties": {
    "iso:country":"BE",
    "sg:address":"Chauss\u00c9e De Bruxelles 181",
    "sg:city":"Wemmel/wemmel",
    "sg:orig_category":"Cabinets d\u00b4huissiers",
    "sg:phone":"+32 2 461 14 24",
    "sg:postcode":"1780",
    "sg:province":"Vlaams-Brabant",
    "wof:name":"Ann Verrezen",
    "wof:placetype":"venue"
},
  "geometry": {"coordinates":[4.3086299896,50.9016494751],"type":"Point"}
}