{
  "type": "Feature",
  "properties": {
    "iso:country":"BE",
    "sg:address":"Sur Le Try 18bb",
    "sg:city":"Herve",
    "sg:orig_category":"Biens d'occasion",
    "sg:phone":"+32 87 67 88 54",
    "sg:postcode":"4650",
    "sg:province":"Li\u00e8ge",
    "wof:name":"T\u00c9l\u00c9-entraide",
    "wof:placetype":"venue"
},
  "geometry": {"coordinates":[5.800825119,50.6433906555],"type":"Point"}
}