{
  "type": "Feature",
  "properties": {
    "iso:country":"BE",
    "sg:address":"Alfons Jeurissenstraat 11",
    "sg:city":"Diepenbeek",
    "sg:classifiers":[
        {
            "category":"Insurance",
            "subcategory":"Insurance Agent",
            "type":"Services"
        }
    ],
    "sg:phone":"+32 11 35 21 38",
    "sg:postcode":"3590",
    "sg:province":"Limburg",
    "sg:tags":[
        "verzekeringsmakelaars",
        "expert"
    ],
    "wof:name":"G.r.m.",
    "wof:placetype":"venue"
},
  "geometry": {"coordinates":[5.4158649445,50.9229316711],"type":"Point"}
}