{
  "type": "Feature",
  "properties": {
    "addr:full":"Hoevelei 98 Aartselaar Antwerpen 2630",
    "addr:housenumber":"98",
    "addr:postcode":"2630",
    "addr:street":"Hoevelei",
    "iso:country":"BE",
    "sg:address":"Hoevelei 98",
    "sg:city":"Aartselaar",
    "sg:classifiers":[
        {
            "category":"Health Services",
            "subcategory":"Health Practitioner",
            "type":"Services"
        }
    ],
    "sg:phone":"+32 3 887 55 70",
    "sg:postcode":"2630",
    "sg:province":"Antwerpen",
    "sg:tags":[
        "physiotherapist"
    ],
    "wof:name":"Vermant W",
    "wof:placetype":"venue"
},
  "geometry": {"coordinates":[4.3822989464,51.1382598877],"type":"Point"}
}