{
  "type": "Feature",
  "properties": {
    "addr:full":"Rue De Wattimez 52 Rumes Hainaut 7618",
    "addr:housenumber":"52",
    "addr:postcode":"7618",
    "addr:street":"Rue De Wattimez",
    "iso:country":"BE",
    "sg:address":"Rue De Wattimez 52",
    "sg:city":"Rumes",
    "sg:orig_category":"Travaux de pl\u00e2trage. Travaux de finition and nettoyage de b\u00e2timents. Quincailleries. Construction de",
    "sg:phone":"+32 69 64 03 92",
    "sg:postcode":"7618",
    "sg:province":"Hainaut",
    "wof:name":"Allard M.",
    "wof:placetype":"venue"
},
  "geometry": {"coordinates":[3.3488030434,50.5446510315],"type":"Point"}
}