{
  "type": "Feature",
  "properties": {
    "iso:country":"BE",
    "sg:address":"Les Quinze Bonniers",
    "sg:city":"Fl\u00e9malle",
    "sg:classifiers":[
        {
            "category":"Education",
            "subcategory":"School",
            "type":"Public Place"
        }
    ],
    "sg:phone":"+32 4 275 57 27",
    "sg:postcode":"4400",
    "sg:province":"Li\u00e8ge",
    "sg:tags":[
        "primary"
    ],
    "wof:name":"Ecole De Xv Bonniers",
    "wof:placetype":"venue"
},
  "geometry": {"coordinates":[5.4390850067,50.6026496887],"type":"Point"}
}