{
  "type": "Feature",
  "properties": {
    "iso:country":"BE",
    "sg:address":"Rue De Fer 11",
    "sg:city":"Namur",
    "sg:classifiers":[
        {
            "category":"Shopping",
            "subcategory":"Clothing, Apparel, & Fashions",
            "type":"Retail Goods"
        }
    ],
    "sg:phone":"+32 81 24 19 47",
    "sg:postcode":"5000",
    "sg:province":"Namur",
    "sg:tags":[
        "boutique"
    ],
    "wof:name":"Naf Naf",
    "wof:placetype":"venue"
},
  "geometry": {"coordinates":[4.8648300171,50.4652404785],"type":"Point"}
}