{
  "type": "Feature",
  "properties": {
    "iso:country":"BE",
    "sg:address":"Pompeloerestraat 32",
    "sg:city":"Sint-katelijne-waver",
    "sg:classifiers":[
        {
            "category":"Building & Trades",
            "subcategory":"Landscaping Services",
            "type":"Services"
        }
    ],
    "sg:phone":"+32 15 31 88 74",
    "sg:postcode":"2860",
    "sg:province":"Antwerpen",
    "sg:tags":[
        "gardening",
        "garden",
        "maintenance"
    ],
    "wof:name":"Van Looy",
    "wof:placetype":"venue"
},
  "geometry": {"coordinates":[4.5159378052,51.0811042786],"type":"Point"}
}