{
  "type": "Feature",
  "properties": {
    "iso:country":"BE",
    "sg:address":"Grote Spouwenstraat 38",
    "sg:city":"Bilzen",
    "sg:orig_category":"Rundveehouders",
    "sg:phone":"+32 12 45 24 87",
    "sg:postcode":"3740",
    "sg:province":"Limburg",
    "wof:name":"Roland Daerden",
    "wof:placetype":"venue"
},
  "geometry": {"coordinates":[5.5576381683,50.8321037292],"type":"Point"}
}