{
  "type": "Feature",
  "properties": {
    "addr:full":"Meenseweg 154 Ieper West-Vlaanderen 8900",
    "addr:housenumber":"154",
    "addr:postcode":"8900",
    "addr:street":"Meenseweg",
    "iso:country":"BE",
    "sg:address":"Meenseweg 154",
    "sg:city":"Ieper",
    "sg:classifiers":[
        {
            "category":"Retail",
            "subcategory":"Veterinary Services",
            "type":"Services"
        }
    ],
    "sg:phone":"+32 57 20 74 58",
    "sg:postcode":"8900",
    "sg:province":"West-Vlaanderen",
    "sg:tags":[
        "veterinarian"
    ],
    "wof:name":"Carpentier J-j",
    "wof:placetype":"venue"
},
  "geometry": {"coordinates":[2.9078779221,50.8483581543],"type":"Point"}
}