{
  "type": "Feature",
  "properties": {
    "addr:full":"Rue Du Bois Sauvage 17 Bruxelles Bruxelles-Capitale 1000",
    "addr:housenumber":"17",
    "addr:postcode":"1000",
    "addr:street":"Rue Du Bois Sauvage",
    "iso:country":"BE",
    "sg:address":"Rue Du Bois Sauvage 17",
    "sg:city":"Bruxelles",
    "sg:classifiers":[
        {
            "category":"Banks & Credit Unions",
            "subcategory":"Investment Brokerage",
            "type":"Services"
        }
    ],
    "sg:phone":"+32 2 227 54 50",
    "sg:postcode":"1000",
    "sg:province":"Bruxelles-Capitale",
    "wof:name":"Cie Mob. & Fonciere Du Bois Sa",
    "wof:placetype":"venue"
},
  "geometry": {"coordinates":[4.3610620499,50.8479881287],"type":"Point"}
}