{
  "type": "Feature",
  "properties": {
    "iso:country":"BE",
    "sg:address":"Hendrik Baelskaai 7",
    "sg:city":"Oostende",
    "sg:classifiers":[
        {
            "category":"Building & Trades",
            "subcategory":"Construction",
            "type":"Services"
        }
    ],
    "sg:postcode":"8400",
    "sg:province":"West-Vlaanderen",
    "sg:tags":[
        "stair"
    ],
    "wof:name":"Schockaert Smederij Constructie",
    "wof:placetype":"venue"
},
  "geometry": {"coordinates":[2.9321548939,51.2351341248],"type":"Point"}
}