{
  "type": "Feature",
  "properties": {
    "iso:country":"BE",
    "sg:address":"Rue De La Buchaye 19",
    "sg:city":"Bertrix",
    "sg:orig_category":"Elektrische installaties voor woningen",
    "sg:phone":"+32 61 41 34 68",
    "sg:postcode":"6880",
    "sg:province":"Luxembourg",
    "wof:name":"Daniel Goffinet",
    "wof:placetype":"venue"
},
  "geometry": {"coordinates":[5.2665090561,49.8500938416],"type":"Point"}
}