{
  "type": "Feature",
  "properties": {
    "addr:full":"Noordstraat 45 Maldegem Oost-Vlaanderen 9990",
    "addr:housenumber":"45",
    "addr:postcode":"9990",
    "addr:street":"Noordstraat",
    "iso:country":"BE",
    "sg:address":"Noordstraat 45",
    "sg:city":"Maldegem",
    "sg:orig_category":"Beautyfarms, relaxatie and lichamelijk welzijn Kapsalons Schoonheidssalons",
    "sg:phone":"+32 50 71 48 12",
    "sg:postcode":"9990",
    "sg:province":"Oost-Vlaanderen",
    "wof:name":"Coiffure Cleo",
    "wof:placetype":"venue"
},
  "geometry": {"coordinates":[3.4476139545,51.210647583],"type":"Point"}
}