{
  "type": "Feature",
  "properties": {
    "addr:full":"Mechelsesteenweg 327 Bonheiden Antwerpen 2820",
    "addr:housenumber":"327",
    "addr:postcode":"2820",
    "addr:street":"Mechelsesteenweg",
    "iso:country":"BE",
    "sg:address":"Mechelsesteenweg 327",
    "sg:city":"Bonheiden",
    "sg:orig_category":"Non-Classified Establishments",
    "sg:phone":"+32 15 55 80 86",
    "sg:postcode":"2820",
    "sg:province":"Antwerpen",
    "wof:name":"Nutrisan",
    "wof:placetype":"venue"
},
  "geometry": {"coordinates":[4.5173249245,51.0318984985],"type":"Point"}
}