{
  "type": "Feature",
  "properties": {
    "iso:country":"BE",
    "sg:address":"Spuibeekweg 25",
    "sg:city":"Keerbergen",
    "sg:classifiers":[
        {
            "category":"Utilities",
            "subcategory":"Telephone",
            "type":"Services"
        }
    ],
    "sg:phone":"+32 15 51 62 50",
    "sg:postcode":"3140",
    "sg:province":"Vlaams-Brabant",
    "sg:tags":[
        "-",
        "internet"
    ],
    "wof:name":"Arion Communications Bvba",
    "wof:placetype":"venue"
},
  "geometry": {"coordinates":[4.6159849167,51.0011062622],"type":"Point"}
}