{
  "type": "Feature",
  "properties": {
    "iso:country":"BE",
    "sg:address":"Martelaarslaan 248",
    "sg:city":"Gent",
    "sg:classifiers":[
        {
            "category":"Health Services",
            "subcategory":"Dentist",
            "type":"Services"
        }
    ],
    "sg:phone":"+32 9 223 65 64",
    "sg:postcode":"9000",
    "sg:province":"Oost-Vlaanderen",
    "wof:name":"Declercq Didier",
    "wof:placetype":"venue"
},
  "geometry": {"coordinates":[3.7112751007,51.0471458435],"type":"Point"}
}