{
  "type": "Feature",
  "properties": {
    "addr:full":"Chauss\u00e9e De Louvain 920 Namur (cognel\u00e9e) Namur 5022",
    "addr:housenumber":"920",
    "addr:postcode":"5022",
    "addr:street":"Chausse\u0301E De Louvain",
    "iso:country":"BE",
    "sg:address":"Chauss\u00e9e De Louvain 920",
    "sg:city":"Namur (cognel\u00e9e)",
    "sg:classifiers":[
        {
            "category":"Home & Garden",
            "subcategory":"Building Materials",
            "type":"Retail Goods"
        }
    ],
    "sg:phone":"+32 81 20 01 96",
    "sg:postcode":"5022",
    "sg:province":"Namur",
    "sg:tags":[
        "window"
    ],
    "wof:name":"D.f.c. Ch\u00e2ssis",
    "wof:placetype":"venue"
},
  "geometry": {"coordinates":[4.902985096,50.513671875],"type":"Point"}
}