{
  "type": "Feature",
  "properties": {
    "iso:country":"BE",
    "sg:address":"Clos De La Qui\u00e8vre 3",
    "sg:city":"Mouscron",
    "sg:classifiers":[
        {
            "category":"Health Services",
            "subcategory":"Doctor",
            "type":"Services"
        }
    ],
    "sg:phone":"+32 56 33 30 87",
    "sg:postcode":"7700",
    "sg:province":"Hainaut",
    "sg:tags":[
        "medicinephysicians",
        "surgeon"
    ],
    "wof:name":"Jonckheere P",
    "wof:placetype":"venue"
},
  "geometry": {"coordinates":[3.1941039562,50.7419776917],"type":"Point"}
}