{
  "type": "Feature",
  "properties": {
    "addr:full":"Smidsestraat 88 Gent Oost-Vlaanderen 9000",
    "addr:housenumber":"88",
    "addr:postcode":"9000",
    "addr:street":"Smidsestraat;Oost-Vlaanderen",
    "iso:country":"BE",
    "sg:address":"Smidsestraat 88",
    "sg:city":"Gent",
    "sg:classifiers":[
        {
            "category":"Social Services",
            "subcategory":"Child Care",
            "type":"Services"
        }
    ],
    "sg:phone":"+32 9 221 68 31",
    "sg:postcode":"9000",
    "sg:province":"Oost-Vlaanderen",
    "sg:tags":[
        "baby",
        "nursery",
        "day",
        "sitting"
    ],
    "wof:name":"De Speeldoos (st-pietersinstituut)",
    "wof:placetype":"venue"
},
  "geometry": {"coordinates":[3.7131319046,51.0388526917],"type":"Point"}
}