{
  "type": "Feature",
  "properties": {
    "addr:full":"Roeselaarsestraat 14 Izegem West-Vlaanderen 8870",
    "addr:housenumber":"14",
    "addr:postcode":"8870",
    "addr:street":"Roeselaarsestraat",
    "iso:country":"BE",
    "sg:address":"Roeselaarsestraat 14",
    "sg:city":"Izegem",
    "sg:classifiers":[
        {
            "category":"Communications",
            "subcategory":"Film & Video Production",
            "type":"Services"
        }
    ],
    "sg:phone":"+32 51 31 42 14",
    "sg:postcode":"8870",
    "sg:province":"West-Vlaanderen",
    "sg:tags":[
        "platen",
        "cassette",
        "cd's"
    ],
    "wof:name":"Huis Future Sound",
    "wof:placetype":"venue"
},
  "geometry": {"coordinates":[3.2136800289,50.918094635],"type":"Point"}
}