{
  "type": "Feature",
  "properties": {
    "addr:full":"Tasschestraat 23 Ardooie West-Vlaanderen 8850",
    "addr:housenumber":"23",
    "addr:postcode":"8850",
    "addr:street":"Tasschestraat",
    "iso:country":"BE",
    "sg:address":"Tasschestraat 23",
    "sg:city":"Ardooie",
    "sg:classifiers":[
        {
            "category":"Building & Trades",
            "subcategory":"Electrical",
            "type":"Services"
        }
    ],
    "sg:phone":"+32 51 22 13 08",
    "sg:postcode":"8850",
    "sg:province":"West-Vlaanderen",
    "sg:tags":[
        "electric",
        "-",
        "housewiring",
        "contractor"
    ],
    "wof:name":"Stragier B",
    "wof:placetype":"venue"
},
  "geometry": {"coordinates":[3.1710700989,50.9536933899],"type":"Point"}
}