{
  "type": "Feature",
  "properties": {
    "addr:full":"Ch D'ophain 263 Braine-l'alleud Brabant Wallon 1420",
    "addr:housenumber":"263",
    "addr:postcode":"1420",
    "addr:street":"D'Ophain",
    "iso:country":"BE",
    "sg:address":"Ch D'ophain 263",
    "sg:city":"Braine-l'alleud",
    "sg:classifiers":[
        {
            "category":"Building & Trades",
            "subcategory":"Construction",
            "type":"Services"
        }
    ],
    "sg:phone":"+32 2 384 30 90",
    "sg:postcode":"1420",
    "sg:province":"Brabant Wallon",
    "sg:tags":[
        "work",
        "public"
    ],
    "wof:name":"Espaces Verts Deckers Sprl",
    "wof:placetype":"venue"
},
  "geometry": {"coordinates":[8.2241401672,46.8130912781],"type":"Point"}
}