{
  "type": "Feature",
  "properties": {
    "addr:full":"Rue Du Progr\u00c8s 76b57 Schaarbeek/schaerbeek Bruxelles-Capitale 1030",
    "addr:housenumber":"76b57",
    "addr:postcode":"1030",
    "addr:street":"Rue Du Progre\u0300S",
    "iso:country":"BE",
    "sg:address":"Rue Du Progr\u00c8s 76b57",
    "sg:city":"Schaarbeek/schaerbeek",
    "sg:orig_category":"Epiceries",
    "sg:phone":"+32 2 203 22 05",
    "sg:postcode":"1030",
    "sg:province":"Bruxelles-Capitale",
    "wof:name":"Jamil Brothers",
    "wof:placetype":"venue"
},
  "geometry": {"coordinates":[4.3600111008,50.8610153198],"type":"Point"}
}