{
  "type": "Feature",
  "properties": {
    "addr:full":"Keizer Karelstraat 25 Box 1 Brugge West-Vlaanderen 8000",
    "addr:housenumber":"25;1",
    "addr:postcode":"8000",
    "addr:street":"Keizer Karelstraat;Box",
    "iso:country":"BE",
    "sg:address":"Keizer Karelstraat 25 Box 1",
    "sg:city":"Brugge",
    "sg:classifiers":[
        {
            "category":"Professional",
            "subcategory":"Computer Services",
            "type":"Services"
        }
    ],
    "sg:phone":"+32 50 31 39 45",
    "sg:postcode":"8000",
    "sg:province":"West-Vlaanderen",
    "sg:tags":[
        "-",
        "processing",
        "data",
        "software"
    ],
    "wof:name":"Ihc Group Nv",
    "wof:placetype":"venue"
},
  "geometry": {"coordinates":[3.211566925,51.2124404907],"type":"Point"}
}