{
  "type": "Feature",
  "properties": {
    "addr:full":"Oordegemkouter 41 Lede Oost-Vlaanderen 9340",
    "addr:housenumber":"41",
    "addr:postcode":"9340",
    "addr:street":"Oordegemkouter",
    "iso:country":"BE",
    "sg:address":"Oordegemkouter 41",
    "sg:city":"Lede",
    "sg:orig_category":"Banques and organismes de cr\u00e9dit",
    "sg:phone":"+32 9 366 07 58",
    "sg:postcode":"9340",
    "sg:province":"Oost-Vlaanderen",
    "wof:name":"Bacob",
    "wof:placetype":"venue"
},
  "geometry": {"coordinates":[3.9048080444,50.9582519531],"type":"Point"}
}