{
  "type": "Feature",
  "properties": {
    "addr:full":"Edward Vlietinckstraat 22 Oostende (stene) West-Vlaanderen 8400",
    "addr:housenumber":"22",
    "addr:postcode":"8400",
    "addr:street":"Vlietinckstraat",
    "iso:country":"BE",
    "sg:address":"Edward Vlietinckstraat 22",
    "sg:city":"Oostende (stene)",
    "sg:classifiers":[
        {
            "category":"Freight",
            "type":"Transportation"
        }
    ],
    "sg:phone":"+32 59 56 06 60",
    "sg:postcode":"8400",
    "sg:province":"West-Vlaanderen",
    "sg:tags":[
        "-",
        "transport"
    ],
    "wof:name":"Ito",
    "wof:placetype":"venue"
},
  "geometry": {"coordinates":[2.9396650791,51.2083892822],"type":"Point"}
}