{
  "type": "Feature",
  "properties": {
    "addr:full":"Chauss\u00c9e De Waremme 33ba Huy Li\u00e8ge 4500",
    "addr:housenumber":"33ba",
    "addr:postcode":"4500",
    "addr:street":"Chausse\u0301E De Waremme",
    "iso:country":"BE",
    "sg:address":"Chauss\u00c9e De Waremme 33ba",
    "sg:city":"Huy",
    "sg:orig_category":"Studios photographiques",
    "sg:phone":"+32 85 25 44 74",
    "sg:postcode":"4500",
    "sg:province":"Li\u00e8ge",
    "wof:name":"Alexander Von Buxhoeveden",
    "wof:placetype":"venue"
},
  "geometry": {"coordinates":[5.2323679924,50.5288162231],"type":"Point"}
}