{
  "type": "Feature",
  "properties": {
    "addr:full":"Wirtzfeld 101 B\u00dcllingen/bullange Li\u00e8ge 4761",
    "addr:housenumber":"101",
    "addr:postcode":"4761",
    "addr:street":"Wirtzfeld",
    "iso:country":"BE",
    "sg:address":"Wirtzfeld 101",
    "sg:city":"B\u00dcllingen/bullange",
    "sg:orig_category":"Rundveehouders",
    "sg:phone":"+32 80 64 76 26",
    "sg:postcode":"4761",
    "sg:province":"Li\u00e8ge",
    "wof:name":"Paul Hilgers",
    "wof:placetype":"venue"
},
  "geometry": {"coordinates":[6.2963399887,50.4319496155],"type":"Point"}
}