{
  "type": "Feature",
  "properties": {
    "addr:full":"Stationsstraat 42 Kortemark West-Vlaanderen 8610",
    "addr:housenumber":"42",
    "addr:postcode":"8610",
    "addr:street":"Stationsstraat",
    "iso:country":"BE",
    "sg:address":"Stationsstraat 42",
    "sg:city":"Kortemark",
    "sg:classifiers":[
        {
            "category":"Shopping",
            "subcategory":"Bicycles & Sporting Goods",
            "type":"Retail Goods"
        }
    ],
    "sg:phone":"+32 51 56 62 82",
    "sg:postcode":"8610",
    "sg:province":"West-Vlaanderen",
    "sg:tags":[
        "sport",
        "-"
    ],
    "wof:name":"Godderis Sport & Wear",
    "wof:placetype":"venue"
},
  "geometry": {"coordinates":[3.0420498848,51.0253181458],"type":"Point"}
}