{
  "type": "Feature",
  "properties": {
    "iso:country":"BE",
    "sg:address":"Reningelstseweg 30",
    "sg:city":"Poperinge",
    "sg:orig_category":"V\u00e9t\u00e9rinaires",
    "sg:phone":"+32 57 33 54 26",
    "sg:postcode":"8970",
    "sg:province":"West-Vlaanderen",
    "wof:name":"Annic Derore",
    "wof:placetype":"venue"
},
  "geometry": {"coordinates":[2.7380020618,50.8431854248],"type":"Point"}
}