{
  "type": "Feature",
  "properties": {
    "addr:full":"Stalenstraat 40b Genk (waterschei) Limburg 3600",
    "addr:housenumber":"40b",
    "addr:postcode":"3600",
    "addr:street":"Stalenstraat",
    "iso:country":"BE",
    "sg:address":"Stalenstraat 40b",
    "sg:city":"Genk (waterschei)",
    "sg:classifiers":[
        {
            "category":"Personal",
            "subcategory":"Beauty Salon",
            "type":"Services"
        }
    ],
    "sg:phone":"+32 89 38 60 53",
    "sg:postcode":"3600",
    "sg:province":"Limburg",
    "wof:name":"Karin",
    "wof:placetype":"venue"
},
  "geometry": {"coordinates":[5.5195641518,50.9945526123],"type":"Point"}
}