{
  "type": "Feature",
  "properties": {
    "iso:country":"BE",
    "sg:address":"Westvleterseweg 42",
    "sg:city":"Poperinge",
    "sg:orig_category":"Rundveehouders Varkenskwekers",
    "sg:phone":"+32 57 33 70 37",
    "sg:postcode":"8970",
    "sg:province":"West-Vlaanderen",
    "wof:name":"Martin Descamps",
    "wof:placetype":"venue"
},
  "geometry": {"coordinates":[2.7361309528,50.8740653992],"type":"Point"}
}