{
  "type": "Feature",
  "properties": {
    "addr:full":"Meir 3 Rijkevorsel Antwerpen 2310",
    "addr:housenumber":"3",
    "addr:postcode":"2310",
    "addr:street":"Meir",
    "iso:country":"BE",
    "sg:address":"Meir 3",
    "sg:city":"Rijkevorsel",
    "sg:classifiers":[
        {
            "category":"Bars & Pubs",
            "type":"Food & Drink"
        }
    ],
    "sg:phone":"+32 3 312 04 51",
    "sg:postcode":"2310",
    "sg:province":"Antwerpen",
    "wof:name":"Vrienden Kring",
    "wof:placetype":"venue"
},
  "geometry": {"coordinates":[4.7821941376,51.3282585144],"type":"Point"}
}