{
  "type": "Feature",
  "properties": {
    "addr:full":"Hoogstraat 65 Wolvertem Vlaams-Brabant 1861",
    "addr:housenumber":"65",
    "addr:postcode":"1861",
    "addr:street":"Hoogstraat",
    "iso:country":"BE",
    "sg:address":"Hoogstraat 65",
    "sg:city":"Wolvertem",
    "sg:classifiers":[
        {
            "category":"Building & Trades",
            "subcategory":"Plumbing",
            "type":"Services"
        }
    ],
    "sg:phone":"+32 2 270 20 12",
    "sg:postcode":"1861",
    "sg:province":"Vlaams-Brabant",
    "sg:tags":[
        "diver",
        "commerce",
        "gr",
        "pour",
        "equipement"
    ],
    "wof:name":"Euro Coffee Contractors",
    "wof:placetype":"venue"
},
  "geometry": {"coordinates":[4.3125047684,50.9533691406],"type":"Point"}
}