{
  "type": "Feature",
  "properties": {
    "iso:country":"BE",
    "sg:address":"Rue Haute Marcelle 12",
    "sg:city":"Namur",
    "sg:orig_category":"Pain, p\u00e2tisseries and confiseries",
    "sg:phone":"+32 81 23 13 63",
    "sg:postcode":"5000",
    "sg:province":"Namur",
    "wof:name":"Maison Art De Praslin",
    "wof:placetype":"venue"
},
  "geometry": {"coordinates":[4.8644609451,50.4646492004],"type":"Point"}
}