{
  "type": "Feature",
  "properties": {
    "iso:country":"BE",
    "sg:address":"Rue Paschal 15",
    "sg:city":"Lobbes",
    "sg:orig_category":"Rusthuizen and serviceflats",
    "sg:phone":"+32 71 59 03 90",
    "sg:postcode":"6540",
    "sg:province":"Hainaut",
    "wof:name":"Maison De La Visitation",
    "wof:placetype":"venue"
},
  "geometry": {"coordinates":[4.2697820663,50.3476867676],"type":"Point"}
}