{
  "type": "Feature",
  "properties": {
    "addr:full":"Rue De Verviers 101 Herve (chaineux) Li\u00e8ge 4650",
    "addr:housenumber":"101",
    "addr:postcode":"4650",
    "addr:street":"Rue De Verviers",
    "iso:country":"BE",
    "sg:address":"Rue De Verviers 101",
    "sg:city":"Herve (chaineux)",
    "sg:classifiers":[
        {
            "category":"Building & Trades",
            "subcategory":"Construction",
            "type":"Services"
        }
    ],
    "sg:phone":"+32 87 67 98 89",
    "sg:postcode":"4650",
    "sg:province":"Li\u00e8ge",
    "sg:tags":[
        "carpenter"
    ],
    "wof:name":"Grosjean R",
    "wof:placetype":"venue"
},
  "geometry": {"coordinates":[5.8218231201,50.6328887939],"type":"Point"}
}