{
  "type": "Feature",
  "properties": {
    "addr:full":"Plasstraat 63b2 Stabroek Antwerpen 2940",
    "addr:housenumber":"63b2",
    "addr:postcode":"2940",
    "addr:street":"Plasstraat",
    "iso:country":"BE",
    "sg:address":"Plasstraat 63b2",
    "sg:city":"Stabroek",
    "sg:orig_category":"Artsen and specialisten",
    "sg:phone":"+32 3 605 17 52",
    "sg:postcode":"2940",
    "sg:province":"Antwerpen",
    "wof:name":"Philippe Du Jardin",
    "wof:placetype":"venue"
},
  "geometry": {"coordinates":[4.4124650955,51.3044471741],"type":"Point"}
}