{
  "type": "Feature",
  "properties": {
    "iso:country":"BE",
    "sg:address":"Eduard Anseelestraat 7b5",
    "sg:city":"Willebroek",
    "sg:orig_category":"Boissons",
    "sg:phone":"+32 3 886 56 80",
    "sg:postcode":"2830",
    "sg:province":"Antwerpen",
    "wof:name":"E. Van Der Seypen",
    "wof:placetype":"venue"
},
  "geometry": {"coordinates":[4.3576831818,51.0635185242],"type":"Point"}
}