{
  "type": "Feature",
  "properties": {
    "addr:full":"Ind.terrein-kanaal-noord 1432 Bree Limburg 3960",
    "addr:postcode":"1432 bree;3960",
    "iso:country":"BE",
    "sg:address":"Ind.terrein-kanaal-noord 1432",
    "sg:city":"Bree",
    "sg:orig_category":"Meubelzaken, woning- and keukeninrichting",
    "sg:phone":"+32 89 46 72 60",
    "sg:postcode":"3960",
    "sg:province":"Limburg",
    "wof:name":"Tti",
    "wof:placetype":"venue"
},
  "geometry": {"coordinates":[5.6246638298,51.142868042],"type":"Point"}
}