{
  "type": "Feature",
  "properties": {
    "iso:country":"BE",
    "sg:address":"Rue Du Ch\u00cane",
    "sg:city":"Vise",
    "sg:orig_category":"Fleurs and plantes",
    "sg:phone":"+32 4 264 24 65",
    "sg:postcode":"4680",
    "sg:province":"Li\u00e8ge",
    "wof:name":"Yvette Fleurs",
    "wof:placetype":"venue"
},
  "geometry": {"coordinates":[5.6444120407,50.7089729309],"type":"Point"}
}