{
  "type": "Feature",
  "properties": {
    "iso:country":"BE",
    "sg:address":"Norbertinessenlaan 24",
    "sg:city":"Neerpelt",
    "sg:classifiers":[
        {
            "category":"Professional",
            "subcategory":"Computer Services",
            "type":"Services"
        }
    ],
    "sg:phone":"+32 11 80 55 99",
    "sg:postcode":"3910",
    "sg:province":"Limburg",
    "sg:tags":[
        "network"
    ],
    "wof:name":"Lambrecht Networking Solutions",
    "wof:placetype":"venue"
},
  "geometry": {"coordinates":[5.4326291084,51.2305717468],"type":"Point"}
}