{
  "type": "Feature",
  "properties": {
    "addr:full":"Jozef Mertensstraat 26 Dilbeek (groot - Bijgaarden) Vlaams-Brabant 1702",
    "addr:housenumber":"26;1702",
    "addr:street":"Jozef Mertensstraat;Groot Bijgaarden Vlaams-Brabant",
    "iso:country":"BE",
    "sg:address":"Jozef Mertensstraat 26",
    "sg:city":"Dilbeek (groot - Bijgaarden)",
    "sg:classifiers":[
        {
            "category":"Wholesale",
            "subcategory":"Auto Parts",
            "type":"Manufacturing & Wholesale Goods"
        }
    ],
    "sg:phone":"+32 2 463 44 84",
    "sg:postcode":"1702",
    "sg:province":"Vlaams-Brabant",
    "sg:tags":[
        "refrigerating"
    ],
    "wof:name":"Belgicold",
    "wof:placetype":"venue"
},
  "geometry": {"coordinates":[4.2594261169,50.8728065491],"type":"Point"}
}