{
  "type": "Feature",
  "properties": {
    "addr:full":"Relaisstraat 57 Elsene Bruxelles-Capitale 1050",
    "addr:housenumber":"57",
    "addr:postcode":"1050",
    "addr:street":"Relaisstraat",
    "iso:country":"BE",
    "sg:address":"Relaisstraat 57",
    "sg:city":"Elsene",
    "sg:orig_category":"Huisdieren and benodigdheden Royal Canin",
    "sg:phone":"+32 2 675 36 21",
    "sg:postcode":"1050",
    "sg:province":"Bruxelles-Capitale",
    "wof:name":"Tom & Co",
    "wof:placetype":"venue"
},
  "geometry": {"coordinates":[4.3928952217,50.8113059998],"type":"Point"}
}