{
  "type": "Feature",
  "properties": {
    "addr:full":"Rue Saint-gilles 39 Li\u00c8ge Li\u00e8ge 4000",
    "addr:housenumber":"39",
    "addr:postcode":"4000",
    "addr:street":"Rue Saint-Gilles",
    "iso:country":"BE",
    "sg:address":"Rue Saint-gilles 39",
    "sg:city":"Li\u00c8ge",
    "sg:classifiers":[
        {
            "category":"Fast Food",
            "type":"Food & Drink"
        }
    ],
    "sg:phone":"+32 4 222 27 25",
    "sg:postcode":"4000",
    "sg:province":"Li\u00e8ge",
    "sg:tags":[
        "meeneem",
        "restaurant"
    ],
    "wof:name":"Restaurant Sun-li",
    "wof:placetype":"venue"
},
  "geometry": {"coordinates":[5.566904068,50.6393356323],"type":"Point"}
}