{
  "type": "Feature",
  "properties": {
    "addr:full":"Rue A. Snoeck 9 Verviers Li\u00e8ge 4800",
    "addr:housenumber":"9",
    "addr:postcode":"4800",
    "addr:street":"Rue A. Snoeck",
    "iso:country":"BE",
    "sg:address":"Rue A. Snoeck 9",
    "sg:city":"Verviers",
    "sg:orig_category":"Epiceries",
    "sg:phone":"+32 87 33 67 18",
    "sg:postcode":"4800",
    "sg:province":"Li\u00e8ge",
    "wof:name":"J. Gillon",
    "wof:placetype":"venue"
},
  "geometry": {"coordinates":[5.8594508171,50.5917663574],"type":"Point"}
}