{
  "type": "Feature",
  "properties": {
    "addr:full":"Rue De Beaufays 24a Trooz (for\u00eat) Li\u00e8ge 4870",
    "addr:housenumber":"24a",
    "addr:postcode":"4870",
    "addr:street":"Rue De Beaufays;Fore\u0302T",
    "iso:country":"BE",
    "sg:address":"Rue De Beaufays 24a",
    "sg:city":"Trooz (for\u00eat)",
    "sg:classifiers":[
        {
            "category":"Health Services",
            "subcategory":"Health Practitioner",
            "type":"Services"
        }
    ],
    "sg:phone":"+32 476 56 03 75",
    "sg:postcode":"4870",
    "sg:province":"Li\u00e8ge",
    "sg:tags":[
        "psychologist"
    ],
    "wof:name":"Vendy E",
    "wof:placetype":"venue"
},
  "geometry": {"coordinates":[5.6636371613,50.5583343506],"type":"Point"}
}