{
  "type": "Feature",
  "properties": {
    "iso:country":"BE",
    "sg:address":"Boulevard De La Woluwe 46 Box 8",
    "sg:city":"Bruxelles (woluwe-saint-lambert)",
    "sg:classifiers":[
        {
            "category":"Social Services",
            "subcategory":"Job Training",
            "type":"Services"
        }
    ],
    "sg:phone":"+32 2 778 63 30",
    "sg:postcode":"1200",
    "sg:province":"Bruxelles-Capitale",
    "sg:tags":[
        "personnel"
    ],
    "wof:name":"Educam Vzw",
    "wof:placetype":"venue"
},
  "geometry": {"coordinates":[4.4354801178,50.8394889832],"type":"Point"}
}