{
  "type": "Feature",
  "properties": {
    "iso:country":"BE",
    "sg:address":"Plantenweg 6",
    "sg:city":"Deerlijk",
    "sg:orig_category":"Pleisterwerk Woningbouw",
    "sg:phone":"+32 56 71 99 36",
    "sg:postcode":"8540",
    "sg:province":"West-Vlaanderen",
    "wof:name":"Vergote & Co",
    "wof:placetype":"venue"
},
  "geometry": {"coordinates":[3.3476901054,50.8392715454],"type":"Point"}
}