{
  "type": "Feature",
  "properties": {
    "addr:full":"Rue Abb\u00c9 Dossogne 36 Stavelot Li\u00e8ge 4970",
    "addr:housenumber":"36",
    "addr:postcode":"4970",
    "addr:street":"Rue Abbe\u0301 Dossogne",
    "iso:country":"BE",
    "sg:address":"Rue Abb\u00c9 Dossogne 36",
    "sg:city":"Stavelot",
    "sg:classifiers":[
        {
            "category":"Sports & Exercise",
            "subcategory":"Sports Center",
            "type":"Entertainment"
        }
    ],
    "sg:phone":"+32 87 27 58 10",
    "sg:postcode":"4970",
    "sg:province":"Li\u00e8ge",
    "sg:tags":[
        "terrain",
        "hors",
        "de",
        "installation",
        "sportifs"
    ],
    "wof:name":"Pist.fond Hockai Claessen",
    "wof:placetype":"venue"
},
  "geometry": {"coordinates":[5.9749732018,50.4775848389],"type":"Point"}
}