{
  "type": "Feature",
  "properties": {
    "addr:full":"Kerkhof Van Brussellaan 35 Evere/evere Bruxelles-Capitale 1140",
    "addr:housenumber":"35",
    "addr:postcode":"1140",
    "addr:street":"Kerkhof Van Brussellaan",
    "iso:country":"BE",
    "sg:address":"Kerkhof Van Brussellaan 35",
    "sg:city":"Evere/evere",
    "sg:orig_category":"Postkantoren",
    "sg:phone":"+32 2 726 60 47",
    "sg:postcode":"1140",
    "sg:province":"Bruxelles-Capitale",
    "wof:name":"De Post",
    "wof:placetype":"venue"
},
  "geometry": {"coordinates":[4.4149570465,50.860080719],"type":"Point"}
}