{
  "type": "Feature",
  "properties": {
    "iso:country":"BE",
    "sg:address":"Route De Ramillies 147",
    "sg:city":"Eghezee",
    "sg:classifiers":[
        {
            "category":"Arena",
            "subcategory":"Sports Club",
            "type":"Entertainment"
        }
    ],
    "sg:phone":"+32 81 81 30 40",
    "sg:postcode":"5310",
    "sg:province":"Namur",
    "sg:tags":[
        "de"
    ],
    "wof:name":"B.c. Perwez-eghez\u00c9e",
    "wof:placetype":"venue"
},
  "geometry": {"coordinates":[4.9136900902,50.5994415283],"type":"Point"}
}