{
  "type": "Feature",
  "properties": {
    "iso:country":"BE",
    "sg:address":"Rue De Berz\u00c9e 91",
    "sg:city":"Walcourt",
    "sg:orig_category":"Installation de menuiserie en bois and plastique. Services fun\u00e9raires",
    "sg:phone":"+32 71 61 13 23",
    "sg:postcode":"5651",
    "sg:province":"Namur",
    "wof:name":"Raoul Legros",
    "wof:placetype":"venue"
},
  "geometry": {"coordinates":[4.4262080193,50.2824401855],"type":"Point"}
}