{
  "type": "Feature",
  "properties": {
    "addr:full":"Gasthuisstraat 24 Merchtem Vlaams-Brabant 1785",
    "addr:housenumber":"24",
    "addr:postcode":"1785",
    "addr:street":"Gasthuisstraat",
    "iso:country":"BE",
    "sg:address":"Gasthuisstraat 24",
    "sg:city":"Merchtem",
    "sg:classifiers":[
        {
            "category":"Shopping",
            "subcategory":"Hobbies, Toys, & Games",
            "type":"Retail Goods"
        }
    ],
    "sg:phone":"+32 52 37 41 15",
    "sg:postcode":"1785",
    "sg:province":"Vlaams-Brabant",
    "sg:tags":[
        "toy",
        "-"
    ],
    "wof:name":"Domino",
    "wof:placetype":"venue"
},
  "geometry": {"coordinates":[4.2311310768,50.9618721008],"type":"Point"}
}