{
  "type": "Feature",
  "properties": {
    "iso:country":"BE",
    "sg:address":"Vennestraat 15",
    "sg:city":"Gent",
    "sg:orig_category":"Verplichte sociale verzekeringen",
    "sg:phone":"+32 9 220 48 86",
    "sg:postcode":"9051",
    "sg:province":"Oost-Vlaanderen",
    "wof:name":"Liberale Mutualiteit",
    "wof:placetype":"venue"
},
  "geometry": {"coordinates":[3.6703000069,51.0244979858],"type":"Point"}
}