{
  "type": "Feature",
  "properties": {
    "iso:country":"BE",
    "sg:address":"Rue Des Augustins 42",
    "sg:city":"Huy",
    "sg:classifiers":[
        {
            "category":"Professional",
            "subcategory":"Lawyer & Legal Services",
            "type":"Services"
        }
    ],
    "sg:phone":"+32 85 21 71 88",
    "sg:postcode":"4500",
    "sg:province":"Li\u00e8ge",
    "wof:name":"Bernard Y",
    "wof:placetype":"venue"
},
  "geometry": {"coordinates":[5.243265152,50.5219955444],"type":"Point"}
}