{
  "type": "Feature",
  "properties": {
    "addr:full":"Rue Vandenboogaerde 46 Sint-jans-molenbeek/molenbeek-saint-jean Bruxelles-Capitale 1080",
    "addr:housenumber":"46",
    "addr:postcode":"1080",
    "addr:street":"Rue Vandenboogaerde",
    "iso:country":"BE",
    "sg:address":"Rue Vandenboogaerde 46",
    "sg:city":"Sint-jans-molenbeek/molenbeek-saint-jean",
    "sg:orig_category":"M\u00e9decins and sp\u00e9cialistes",
    "sg:phone":"+32 2 425 11 55",
    "sg:postcode":"1080",
    "sg:province":"Bruxelles-Capitale",
    "wof:name":"Nusyn Appelboom",
    "wof:placetype":"venue"
},
  "geometry": {"coordinates":[4.3399009705,50.8622398376],"type":"Point"}
}