{
  "type": "Feature",
  "properties": {
    "iso:country":"BE",
    "sg:address":"Beukenlaan 8",
    "sg:city":"De Haan (klemskerke)",
    "sg:classifiers":[
        {
            "category":"Social Services",
            "type":"Services"
        }
    ],
    "sg:phone":"+32 59 23 51 53",
    "sg:postcode":"8420",
    "sg:province":"West-Vlaanderen",
    "wof:name":"Anonieme Toxicomanen Vzw",
    "wof:placetype":"venue"
},
  "geometry": {"coordinates":[3.0255839825,51.2588043213],"type":"Point"}
}