{
  "type": "Feature",
  "properties": {
    "addr:full":"Herreweg 25 Brakel (nederbrakel) Oost-Vlaanderen 9660",
    "addr:housenumber":"25",
    "addr:postcode":"9660",
    "addr:street":"Herreweg",
    "iso:country":"BE",
    "sg:address":"Herreweg 25",
    "sg:city":"Brakel (nederbrakel)",
    "sg:classifiers":[
        {
            "category":"Insurance",
            "subcategory":"Insurance Agent",
            "type":"Services"
        }
    ],
    "sg:phone":"+32 55 42 53 29",
    "sg:postcode":"9660",
    "sg:province":"Oost-Vlaanderen",
    "sg:tags":[
        "-",
        "representative"
    ],
    "wof:name":"Vandewalle S",
    "wof:placetype":"venue"
},
  "geometry": {"coordinates":[3.7577550411,50.7998771667],"type":"Point"}
}