{
  "type": "Feature",
  "properties": {
    "addr:full":"Heiligenbornstraat 19 Alken Limburg 3570",
    "addr:housenumber":"19",
    "addr:postcode":"3570",
    "addr:street":"Heiligenbornstraat",
    "iso:country":"BE",
    "sg:address":"Heiligenbornstraat 19",
    "sg:city":"Alken",
    "sg:classifiers":[
        {
            "category":"Autos & Motor Vehicles",
            "subcategory":"Automobile Sales",
            "type":"Retail Goods"
        }
    ],
    "sg:phone":"+32 11 31 11 60",
    "sg:postcode":"3570",
    "sg:province":"Limburg",
    "sg:tags":[
        "car",
        "used",
        "-"
    ],
    "wof:name":"Goovaerts",
    "wof:placetype":"venue"
},
  "geometry": {"coordinates":[5.2542710304,50.8716239929],"type":"Point"}
}