{
  "type": "Feature",
  "properties": {
    "addr:full":"Rue Des Goutteaux 50 Charleroi Hainaut 6043",
    "addr:housenumber":"50",
    "addr:postcode":"6043",
    "addr:street":"Rue Des Goutteaux;Hainaut",
    "iso:country":"BE",
    "sg:address":"Rue Des Goutteaux 50",
    "sg:city":"Charleroi",
    "sg:orig_category":"Installation de menuiserie m\u00e9tallique. Installation de menuiserie en bois and plastique",
    "sg:phone":"+32 71 35 83 70",
    "sg:postcode":"6043",
    "sg:province":"Hainaut",
    "wof:name":"Pierre Etienne",
    "wof:placetype":"venue"
},
  "geometry": {"coordinates":[4.408343792,50.4378929138],"type":"Point"}
}