{
  "type": "Feature",
  "properties": {
    "addr:full":"Chauss\u00c9e De Tongres 283 Liege Li\u00e8ge 4000",
    "addr:housenumber":"283",
    "addr:postcode":"4000",
    "addr:street":"Chausse\u0301E De Tongres",
    "iso:country":"BE",
    "sg:address":"Chauss\u00c9e De Tongres 283",
    "sg:city":"Liege",
    "sg:orig_category":"Immobili\u00ebnkantoren",
    "sg:phone":"+32 4 263 67 07",
    "sg:postcode":"4000",
    "sg:province":"Li\u00e8ge",
    "wof:name":"Immo Cosse",
    "wof:placetype":"venue"
},
  "geometry": {"coordinates":[5.5492367744,50.6709976196],"type":"Point"}
}