{
  "type": "Feature",
  "properties": {
    "iso:country":"BE",
    "sg:address":"Wondelgemstraat 111",
    "sg:city":"Gent",
    "sg:orig_category":"Huishoudapparaten, televisies and radio's",
    "sg:phone":"+32 9 223 17 91",
    "sg:postcode":"9000",
    "sg:province":"Oost-Vlaanderen",
    "wof:name":"St.amandsbazar",
    "wof:placetype":"venue"
},
  "geometry": {"coordinates":[3.7098259926,51.0631065369],"type":"Point"}
}