{
  "type": "Feature",
  "properties": {
    "iso:country":"BE",
    "sg:address":"Rue Philippe Monnoyer 47",
    "sg:city":"Courcelles",
    "sg:classifiers":[
        {
            "category":"Community Center",
            "type":"Public Place"
        }
    ],
    "sg:phone":"+32 71 45 59 45",
    "sg:postcode":"6180",
    "sg:province":"Hainaut",
    "sg:tags":[
        "medical"
    ],
    "wof:name":"Centre De M\u00e9decine Sp\u00e9cialis\u00e9e",
    "wof:placetype":"venue"
},
  "geometry": {"coordinates":[4.3766818047,50.4622344971],"type":"Point"}
}