{
  "type": "Feature",
  "properties": {
    "iso:country":"BE",
    "sg:address":"Astridplein 12a",
    "sg:city":"Grobbendonk",
    "sg:classifiers":[
        {
            "category":"Recreation",
            "subcategory":"Fishing",
            "type":"Entertainment"
        }
    ],
    "sg:phone":"+32 14 51 22 96",
    "sg:postcode":"2280",
    "sg:province":"Antwerpen",
    "sg:tags":[
        "tackle"
    ],
    "wof:name":"Mastico Bvba",
    "wof:placetype":"venue"
},
  "geometry": {"coordinates":[4.7395200729,51.1921081543],"type":"Point"}
}