{
  "type": "Feature",
  "properties": {
    "addr:full":"Rue Du Ruau 20 Eghezee Namur 5310",
    "addr:housenumber":"20",
    "addr:postcode":"5310",
    "addr:street":"Rue Du Ruau;Namur",
    "iso:country":"BE",
    "sg:address":"Rue Du Ruau 20",
    "sg:city":"Eghezee",
    "sg:orig_category":"Eleveurs and marchands de porcs. Eleveurs de bovins",
    "sg:phone":"+32 81 81 13 94",
    "sg:postcode":"5310",
    "sg:province":"Namur",
    "wof:name":"Johan Dhondt",
    "wof:placetype":"venue"
},
  "geometry": {"coordinates":[4.9310898781,50.5988044739],"type":"Point"}
}