{
  "type": "Feature",
  "properties": {
    "addr:full":"Bredabaan 613 Wuustwezel Antwerpen 2990",
    "addr:housenumber":"613",
    "addr:postcode":"2990",
    "addr:street":"Bredabaan",
    "iso:country":"BE",
    "sg:address":"Bredabaan 613",
    "sg:city":"Wuustwezel",
    "sg:orig_category":"Cr\u00e8ches and garderies d'enfants",
    "sg:phone":"+32 3 669 58 03",
    "sg:postcode":"2990",
    "sg:province":"Antwerpen",
    "wof:name":"\u00b4t Kapoentje",
    "wof:placetype":"venue"
},
  "geometry": {"coordinates":[4.5796179771,51.3799667358],"type":"Point"}
}