{
  "type": "Feature",
  "properties": {
    "addr:full":"Sint-truidersteenweg 471 Borgloon (hoepertingen) Limburg 3840",
    "addr:housenumber":"471",
    "addr:postcode":"3840",
    "addr:street":"Sint-Truidersteenweg",
    "iso:country":"BE",
    "sg:address":"Sint-truidersteenweg 471",
    "sg:city":"Borgloon (hoepertingen)",
    "sg:classifiers":[
        {
            "category":"Professional",
            "subcategory":"Art Services",
            "type":"Services"
        }
    ],
    "sg:phone":"+32 12 67 10 30",
    "sg:postcode":"3840",
    "sg:province":"Limburg",
    "sg:tags":[
        "photographer",
        "-",
        "portrait"
    ],
    "wof:name":"Foto Diffusion Bvba",
    "wof:placetype":"venue"
},
  "geometry": {"coordinates":[5.2756547928,50.8070831299],"type":"Point"}
}