{
  "type": "Feature",
  "properties": {
    "addr:full":"Herebaan-west 1b1 Houthalen-helchteren Limburg 3530",
    "addr:housenumber":"1b1",
    "addr:postcode":"3530",
    "addr:street":"Herebaan-West",
    "iso:country":"BE",
    "sg:address":"Herebaan-west 1b1",
    "sg:city":"Houthalen-helchteren",
    "sg:orig_category":"Sportclubs",
    "sg:phone":"+32 11 60 33 68",
    "sg:postcode":"3530",
    "sg:province":"Limburg",
    "wof:name":"Olympia Houthalen",
    "wof:placetype":"venue"
},
  "geometry": {"coordinates":[5.3719201088,51.0310020447],"type":"Point"}
}