{
  "type": "Feature",
  "properties": {
    "addr:full":"Rue De Luxembourg 24 Leglise Luxembourg 6860",
    "addr:housenumber":"24",
    "addr:postcode":"6860",
    "addr:street":"Rue De Luxembourg",
    "iso:country":"BE",
    "sg:address":"Rue De Luxembourg 24",
    "sg:city":"Leglise",
    "sg:orig_category":"Pharmaciens",
    "sg:phone":"+32 63 43 35 77",
    "sg:postcode":"6860",
    "sg:province":"Luxembourg",
    "wof:name":"F. Demasy",
    "wof:placetype":"venue"
},
  "geometry": {"coordinates":[5.5372848511,49.7998771667],"type":"Point"}
}