{
  "type": "Feature",
  "properties": {
    "iso:country":"BE",
    "sg:address":"Rue D\u00b4aubel 39",
    "sg:city":"Herve",
    "sg:orig_category":"Architectes",
    "sg:phone":"+32 87 67 53 91",
    "sg:postcode":"4651",
    "sg:province":"Li\u00e8ge",
    "wof:name":"Val\u00c9rie Herckens",
    "wof:placetype":"venue"
},
  "geometry": {"coordinates":[5.7714061737,50.6893539429],"type":"Point"}
}