{
  "type": "Feature",
  "properties": {
    "addr:full":"Rue Du Bola 13 Herve Li\u00e8ge 4650",
    "addr:housenumber":"13",
    "addr:postcode":"4650",
    "addr:street":"Rue Du Bola",
    "iso:country":"BE",
    "sg:address":"Rue Du Bola 13",
    "sg:city":"Herve",
    "sg:orig_category":"Dakwerken Loodgieterij, verwarming and sanitaire installaties",
    "sg:phone":"+32 87 33 19 41",
    "sg:postcode":"4650",
    "sg:province":"Li\u00e8ge",
    "wof:name":"Hurlet",
    "wof:placetype":"venue"
},
  "geometry": {"coordinates":[5.8079881668,50.6066360474],"type":"Point"}
}