{
  "type": "Feature",
  "properties": {
    "addr:full":"Poelstraat 7b2 Oostkamp West-Vlaanderen 8020",
    "addr:housenumber":"7b2",
    "addr:postcode":"8020",
    "addr:street":"Poelstraat",
    "iso:country":"BE",
    "sg:address":"Poelstraat 7b2",
    "sg:city":"Oostkamp",
    "sg:classifiers":[
        {
            "category":"Arena",
            "subcategory":"Sports Club",
            "type":"Entertainment"
        }
    ],
    "sg:phone":"+32 50 84 04 86",
    "sg:postcode":"8020",
    "sg:province":"West-Vlaanderen",
    "sg:tags":[
        "de"
    ],
    "wof:name":"B.c. Ombesa",
    "wof:placetype":"venue"
},
  "geometry": {"coordinates":[3.2349750996,51.1591911316],"type":"Point"}
}