{
  "type": "Feature",
  "properties": {
    "iso:country":"BE",
    "sg:address":"Meenseweg 153",
    "sg:city":"Ieper",
    "sg:classifiers":[
        {
            "category":"Wholesale",
            "subcategory":"Vending Machines",
            "type":"Manufacturing & Wholesale Goods"
        }
    ],
    "sg:phone":"+32 57 20 83 47",
    "sg:postcode":"8900",
    "sg:province":"West-Vlaanderen",
    "sg:tags":[
        "automobile",
        "-",
        "radiator"
    ],
    "wof:name":"Ieper Radiatoren",
    "wof:placetype":"venue"
},
  "geometry": {"coordinates":[2.9043560028,50.8500366211],"type":"Point"}
}