{
  "type": "Feature",
  "properties": {
    "iso:country":"BE",
    "sg:address":"Boogstraat 3",
    "sg:city":"Beerse",
    "sg:orig_category":"Plaatsen van vloer- and muurbekleding",
    "sg:phone":"+32 3 309 07 96",
    "sg:postcode":"2340",
    "sg:province":"Antwerpen",
    "wof:name":"Jan Goolaerts",
    "wof:placetype":"venue"
},
  "geometry": {"coordinates":[4.7825088501,51.3002815247],"type":"Point"}
}