{
  "type": "Feature",
  "properties": {
    "iso:country":"BE",
    "sg:address":"Zuidstraat 5",
    "sg:city":"Beringen (beverlo)",
    "sg:classifiers":[
        {
            "category":"Personal",
            "subcategory":"Barber",
            "type":"Services"
        }
    ],
    "sg:phone":"+32 11 34 40 35",
    "sg:postcode":"3581",
    "sg:province":"Limburg",
    "sg:tags":[
        "gentleman",
        "salon",
        "-",
        "hairdressing"
    ],
    "wof:name":"Pascal",
    "wof:placetype":"venue"
},
  "geometry": {"coordinates":[5.2180871964,51.08644104],"type":"Point"}
}