{
  "type": "Feature",
  "properties": {
    "addr:full":"Avenue Massenet 19 Vorst/forest Bruxelles-Capitale 1190",
    "addr:housenumber":"19",
    "addr:postcode":"1190",
    "addr:street":"Avenue Massenet;/ Forest",
    "iso:country":"BE",
    "sg:address":"Avenue Massenet 19",
    "sg:city":"Vorst/forest",
    "sg:orig_category":"Avocats and conseillers juridiques",
    "sg:phone":"+32 2 340 75 78",
    "sg:postcode":"1190",
    "sg:province":"Bruxelles-Capitale",
    "wof:name":"Anne Bestard",
    "wof:placetype":"venue"
},
  "geometry": {"coordinates":[4.332942009,50.820854187],"type":"Point"}
}