{
  "type": "Feature",
  "properties": {
    "iso:country":"BE",
    "sg:address":"Meirveld 52",
    "sg:city":"Lede",
    "sg:orig_category":"Quincailleries",
    "sg:phone":"+32 53 80 50 78",
    "sg:postcode":"9340",
    "sg:province":"Oost-Vlaanderen",
    "wof:name":"Marc Van Der Biest",
    "wof:placetype":"venue"
},
  "geometry": {"coordinates":[3.9785070419,50.9728889465],"type":"Point"}
}