{
  "type": "Feature",
  "properties": {
    "addr:full":"Guido Gezellelaan 109 Roeselare West-Vlaanderen 8800",
    "addr:housenumber":"109",
    "addr:postcode":"8800",
    "addr:street":"Guido Gezellelaan",
    "iso:country":"BE",
    "sg:address":"Guido Gezellelaan 109",
    "sg:city":"Roeselare",
    "sg:orig_category":"Oldtimers",
    "sg:phone":"+32 51 22 51 68",
    "sg:postcode":"8800",
    "sg:province":"West-Vlaanderen",
    "wof:name":"Vermaut Nv",
    "wof:placetype":"venue"
},
  "geometry": {"coordinates":[3.1431701183,50.9396896362],"type":"Point"}
}