{
  "type": "Feature",
  "properties": {
    "addr:full":"Hermelijnlaan 31 Schoten Antwerpen 2900",
    "addr:housenumber":"31",
    "addr:postcode":"2900",
    "addr:street":"Hermelijnlaan",
    "iso:country":"BE",
    "sg:address":"Hermelijnlaan 31",
    "sg:city":"Schoten",
    "sg:orig_category":"Artiesten and kunstenaars",
    "sg:phone":"+32 3 658 19 87",
    "sg:postcode":"2900",
    "sg:province":"Antwerpen",
    "wof:name":"Marc Mylemans",
    "wof:placetype":"venue"
},
  "geometry": {"coordinates":[4.5164670944,51.267780304],"type":"Point"}
}