{
  "type": "Feature",
  "properties": {
    "addr:full":"Sint-antoniusstraat 9 Maasmechelen Limburg 3631",
    "addr:housenumber":"9",
    "addr:postcode":"3631",
    "addr:street":"Sint-Antoniusstraat",
    "iso:country":"BE",
    "sg:address":"Sint-antoniusstraat 9",
    "sg:city":"Maasmechelen",
    "sg:orig_category":"Diverse bouwafwerking and reiniging",
    "sg:phone":"+32 89 71 64 24",
    "sg:postcode":"3631",
    "sg:province":"Limburg",
    "wof:name":"Jean Bringmans",
    "wof:placetype":"venue"
},
  "geometry": {"coordinates":[5.7318987846,50.9335289001],"type":"Point"}
}