{
  "type": "Feature",
  "properties": {
    "iso:country":"BE",
    "sg:address":"Chauss\u00e9e De Mons 30",
    "sg:city":"Nivelles",
    "sg:classifiers":[
        {
            "category":"Organizations",
            "subcategory":"Professional Association",
            "type":"Services"
        }
    ],
    "sg:phone":"+32 67 21 16 37",
    "sg:postcode":"1400",
    "sg:province":"Brabant Wallon",
    "sg:tags":[
        "organisation",
        "seminar"
    ],
    "wof:name":"Ferme Du Bois D'arpes (la)",
    "wof:placetype":"venue"
},
  "geometry": {"coordinates":[4.3183851242,50.5936737061],"type":"Point"}
}