{
  "type": "Feature",
  "properties": {
    "iso:country":"BE",
    "sg:address":"Rue Boveroth 41",
    "sg:city":"Baelen/baelen",
    "sg:orig_category":"Eleveurs de bovins",
    "sg:phone":"+32 87 55 33 54",
    "sg:postcode":"4837",
    "sg:province":"Li\u00e8ge",
    "wof:name":"Rene Schyns-keutgens",
    "wof:placetype":"venue"
},
  "geometry": {"coordinates":[5.9976091385,50.6156959534],"type":"Point"}
}