{
  "type": "Feature",
  "properties": {
    "addr:full":"Avenue Jef Lambeaux 38 Sint-gillis/saint-gilles Bruxelles-Capitale 1060",
    "addr:housenumber":"38",
    "addr:postcode":"1060",
    "addr:street":"Avenue Jef Lambeaux",
    "iso:country":"BE",
    "sg:address":"Avenue Jef Lambeaux 38",
    "sg:city":"Sint-gillis/saint-gilles",
    "sg:orig_category":"V\u00e9t\u00e9rinaires",
    "sg:phone":"+32 2 538 27 65",
    "sg:postcode":"1060",
    "sg:province":"Bruxelles-Capitale",
    "wof:name":"Philippe Dodion",
    "wof:placetype":"venue"
},
  "geometry": {"coordinates":[4.3467469215,50.8231430054],"type":"Point"}
}