{
  "type": "Feature",
  "properties": {
    "iso:country":"BE",
    "sg:address":"Rue Anatole France 39",
    "sg:city":"Bruxelles (schaerbeek)",
    "sg:orig_category":"Non-Classified Establishments",
    "sg:phone":"+32 2 245 45 50",
    "sg:postcode":"1030",
    "sg:province":"Bruxelles-Capitale",
    "wof:name":"Efde Products-hdl Cleaner Sa",
    "wof:placetype":"venue"
},
  "geometry": {"coordinates":[4.3838510513,50.8780784607],"type":"Point"}
}