{
  "type": "Feature",
  "properties": {
    "iso:country":"BE",
    "sg:address":"Corbusch 6",
    "sg:city":"Baelen/baelen",
    "sg:orig_category":"Rundveehouders Varkenskwekers",
    "sg:phone":"+32 87 89 02 15",
    "sg:postcode":"4837",
    "sg:province":"Li\u00e8ge",
    "wof:name":"Raymond Muellender",
    "wof:placetype":"venue"
},
  "geometry": {"coordinates":[5.9771571159,50.6423835754],"type":"Point"}
}