{
  "type": "Feature",
  "properties": {
    "addr:full":"Rue Richard Carlier 43 Ham-sur-heure-nalinnes (ham-sur-heure) Hainaut 6120",
    "addr:housenumber":"43",
    "addr:postcode":"6120",
    "addr:street":"Rue Richard Carlier",
    "iso:country":"BE",
    "sg:address":"Rue Richard Carlier 43",
    "sg:city":"Ham-sur-heure-nalinnes (ham-sur-heure)",
    "sg:classifiers":[
        {
            "category":"Personal",
            "subcategory":"Beauty Salon",
            "type":"Services"
        }
    ],
    "sg:phone":"+32 71 21 47 41",
    "sg:postcode":"6120",
    "sg:province":"Hainaut",
    "sg:tags":[
        "lady",
        "-",
        "hairdressing"
    ],
    "wof:name":"Ghislaine",
    "wof:placetype":"venue"
},
  "geometry": {"coordinates":[4.3872900009,50.3219146729],"type":"Point"}
}