{
  "type": "Feature",
  "properties": {
    "iso:country":"BE",
    "sg:address":"Rue Le Halleux 28",
    "sg:city":"Nandrin",
    "sg:orig_category":"Eleveurs de bovins",
    "sg:phone":"+32 4 371 40 30",
    "sg:postcode":"4550",
    "sg:province":"Li\u00e8ge",
    "wof:name":"Raphael Van Den Bergh",
    "wof:placetype":"venue"
},
  "geometry": {"coordinates":[5.4386792183,50.5184326172],"type":"Point"}
}