{
  "type": "Feature",
  "properties": {
    "addr:full":"Ter Walle 5 Aalter Oost-Vlaanderen 9880",
    "addr:housenumber":"5",
    "addr:postcode":"9880",
    "addr:street":"Ter Walle",
    "iso:country":"BE",
    "sg:address":"Ter Walle 5",
    "sg:city":"Aalter",
    "sg:classifiers":[
        {
            "category":"Real Estate",
            "subcategory":"Architect",
            "type":"Services"
        }
    ],
    "sg:phone":"+32 9 374 24 17",
    "sg:postcode":"9880",
    "sg:province":"Oost-Vlaanderen",
    "wof:name":"Verhaegen W",
    "wof:placetype":"venue"
},
  "geometry": {"coordinates":[3.4381780624,51.1006317139],"type":"Point"}
}