{
  "type": "Feature",
  "properties": {
    "iso:country":"BE",
    "sg:address":"Rue Bois L'ev\u00eaque 26-28",
    "sg:city":"Li\u00e8ge 1",
    "sg:classifiers":[
        {
            "category":"Arts & Performance",
            "subcategory":"Theater",
            "type":"Entertainment"
        }
    ],
    "sg:phone":"+32 4 253 61 23",
    "sg:postcode":"4000",
    "sg:province":"Li\u00e8ge",
    "sg:tags":[
        "group",
        "theatre"
    ],
    "wof:name":"Groupov Asbl",
    "wof:placetype":"venue"
},
  "geometry": {"coordinates":[5.5606241226,50.6286964417],"type":"Point"}
}