{
  "type": "Feature",
  "properties": {
    "addr:full":"Rue Du Pont 30 A Hamoir Li\u00e8ge 4180",
    "addr:housenumber":"30 a",
    "addr:postcode":"4180",
    "addr:street":"Rue Du Pont",
    "iso:country":"BE",
    "sg:address":"Rue Du Pont 30 A",
    "sg:city":"Hamoir",
    "sg:classifiers":[
        {
            "category":"Banks & Credit Unions",
            "subcategory":"Bank",
            "type":"Services"
        }
    ],
    "sg:phone":"+32 86 38 86 90",
    "sg:postcode":"4180",
    "sg:province":"Li\u00e8ge",
    "wof:name":"Aslk-cger Bank",
    "wof:placetype":"venue"
},
  "geometry": {"coordinates":[5.5333948135,50.4266281128],"type":"Point"}
}