{
  "type": "Feature",
  "properties": {
    "addr:full":"Chauss\u00c9e Freddy Terwagne 5 Amay Li\u00e8ge 4540",
    "addr:housenumber":"5",
    "addr:postcode":"4540",
    "addr:street":"Chausse\u0301E Freddy Terwagne",
    "iso:country":"BE",
    "sg:address":"Chauss\u00c9e Freddy Terwagne 5",
    "sg:city":"Amay",
    "sg:orig_category":"Eclairage et \u00e9quipements du foyer",
    "sg:phone":"+32 85 31 26 21",
    "sg:postcode":"4540",
    "sg:province":"Li\u00e8ge",
    "wof:name":"Claude Cherriere",
    "wof:placetype":"venue"
},
  "geometry": {"coordinates":[5.3191628456,50.5485725403],"type":"Point"}
}