{
  "type": "Feature",
  "properties": {
    "addr:full":"Rue De La Gare 33 Komen-waasten/comines-warneton Hainaut 7780",
    "addr:housenumber":"33;7780",
    "addr:street":"Rue De La Gare",
    "iso:country":"BE",
    "sg:address":"Rue De La Gare 33",
    "sg:city":"Komen-waasten/comines-warneton",
    "sg:orig_category":"Opticiens",
    "sg:phone":"+32 56 55 42 30",
    "sg:postcode":"7780",
    "sg:province":"Hainaut",
    "wof:name":"Optiek Leterme",
    "wof:placetype":"venue"
},
  "geometry": {"coordinates":[2.9971749783,50.7715950012],"type":"Point"}
}