{
  "type": "Feature",
  "properties": {
    "iso:country":"BE",
    "sg:address":"Verzusteringslaan 10",
    "sg:city":"Temse",
    "sg:classifiers":[
        {
            "category":"Professional",
            "subcategory":"Detective & Security Services",
            "type":"Services"
        }
    ],
    "sg:phone":"+32 3 771 51 39",
    "sg:postcode":"9140",
    "sg:province":"Oost-Vlaanderen",
    "sg:tags":[
        "installation",
        "alarm",
        "-",
        "system"
    ],
    "wof:name":"Jafra",
    "wof:placetype":"venue"
},
  "geometry": {"coordinates":[4.2251300812,51.1267776489],"type":"Point"}
}