{
  "type": "Feature",
  "properties": {
    "addr:full":"Rue Hanesse 25 Andenne Namur 5300",
    "addr:housenumber":"25",
    "addr:postcode":"5300",
    "addr:street":"Rue Hanesse",
    "iso:country":"BE",
    "sg:address":"Rue Hanesse 25",
    "sg:city":"Andenne",
    "sg:orig_category":"Immobili\u00ebnkantoren",
    "sg:phone":"+32 85 84 19 72",
    "sg:postcode":"5300",
    "sg:province":"Namur",
    "wof:name":"Rent House",
    "wof:placetype":"venue"
},
  "geometry": {"coordinates":[5.0970849991,50.4858436584],"type":"Point"}
}