{
  "type": "Feature",
  "properties": {
    "iso:country":"BE",
    "sg:address":"Rue Du Ch\u00e2teau",
    "sg:city":"Hotton (fronville)",
    "sg:classifiers":[
        {
            "category":"Manufacturing",
            "subcategory":"Furniture",
            "type":"Manufacturing & Wholesale Goods"
        }
    ],
    "sg:phone":"+32 84 46 76 53",
    "sg:postcode":"6990",
    "sg:province":"Luxembourg",
    "sg:tags":[
        "made",
        "-",
        "custom"
    ],
    "wof:name":"De Harlez M",
    "wof:placetype":"venue"
},
  "geometry": {"coordinates":[5.399960041,50.3041648865],"type":"Point"}
}