{
  "type": "Feature",
  "properties": {
    "addr:full":"Rue Des Sarrazins 11 Andenne Namur 5300",
    "addr:housenumber":"11",
    "addr:postcode":"5300",
    "addr:street":"Rue Des Sarrazins",
    "iso:country":"BE",
    "sg:address":"Rue Des Sarrazins 11",
    "sg:city":"Andenne",
    "sg:orig_category":"Artistes ind\u00e9pendants",
    "sg:phone":"+32 81 58 95 51",
    "sg:postcode":"5300",
    "sg:province":"Namur",
    "wof:name":"David Little",
    "wof:placetype":"venue"
},
  "geometry": {"coordinates":[5.0182099342,50.46118927],"type":"Point"}
}