{
  "type": "Feature",
  "properties": {
    "iso:country":"BE",
    "sg:address":"Rue De Nivelles 74",
    "sg:city":"Rixensart",
    "sg:orig_category":"Kapsalons",
    "sg:phone":"+32 2 653 14 77",
    "sg:postcode":"1330",
    "sg:province":"Brabant Wallon",
    "wof:name":"Guy Houet",
    "wof:placetype":"venue"
},
  "geometry": {"coordinates":[4.5114340782,50.7022743225],"type":"Point"}
}