{
  "type": "Feature",
  "properties": {
    "iso:country":"BE",
    "sg:address":"Rue Du Commerce 40",
    "sg:city":"Andenne",
    "sg:classifiers":[
        {
            "category":"Shopping",
            "subcategory":"Gifts & Souvenirs",
            "type":"Retail Goods"
        }
    ],
    "sg:phone":"+32 85 84 15 20",
    "sg:postcode":"5300",
    "sg:province":"Namur",
    "sg:tags":[
        "-"
    ],
    "wof:name":"Leonidas",
    "wof:placetype":"venue"
},
  "geometry": {"coordinates":[5.0967321396,50.4910087585],"type":"Point"}
}