{
  "type": "Feature",
  "properties": {
    "iso:country":"BE",
    "sg:address":"Serskampsteenweg 243",
    "sg:city":"Wetteren",
    "sg:orig_category":"P\u00e9pini\u00e9ristes",
    "sg:phone":"+32 9 369 70 95",
    "sg:postcode":"9230",
    "sg:province":"Oost-Vlaanderen",
    "wof:name":"Gerard & Dirk De Troy",
    "wof:placetype":"venue"
},
  "geometry": {"coordinates":[3.9021821022,50.9994773865],"type":"Point"}
}