{
  "type": "Feature",
  "properties": {
    "addr:full":"Kruisstraat 19 Meeuwen-gruitrode Limburg 3670",
    "addr:housenumber":"19",
    "addr:postcode":"3670",
    "addr:street":"Kruisstraat",
    "iso:country":"BE",
    "sg:address":"Kruisstraat 19",
    "sg:city":"Meeuwen-gruitrode",
    "sg:orig_category":"Epiceries",
    "sg:phone":"+32 11 79 22 26",
    "sg:postcode":"3670",
    "sg:province":"Limburg",
    "wof:name":"Philomena Eerdekens",
    "wof:placetype":"venue"
},
  "geometry": {"coordinates":[5.5211172104,51.0897941589],"type":"Point"}
}