{
  "type": "Feature",
  "properties": {
    "iso:country":"BE",
    "sg:address":"Nieuwe Baan 56",
    "sg:city":"Laakdal (forest)",
    "sg:classifiers":[
        {
            "category":"Food & Beverages",
            "subcategory":"Groceries & Convenience Stores",
            "type":"Retail Goods"
        }
    ],
    "sg:phone":"+32 13 66 26 33",
    "sg:postcode":"2430",
    "sg:province":"Antwerpen",
    "sg:tags":[
        "grocer"
    ],
    "wof:name":"Vandeven T",
    "wof:placetype":"venue"
},
  "geometry": {"coordinates":[5.0341601372,51.0774497986],"type":"Point"}
}