{
  "type": "Feature",
  "properties": {
    "addr:full":"Rue D'angleterre 9 Charleroi Hainaut 6000",
    "addr:housenumber":"9",
    "addr:postcode":"6000",
    "addr:street":"Rue D'Angleterre;Hainaut",
    "iso:country":"BE",
    "sg:address":"Rue D'angleterre 9",
    "sg:city":"Charleroi",
    "sg:classifiers":[
        {
            "category":"Professional",
            "subcategory":"Lawyer & Legal Services",
            "type":"Services"
        }
    ],
    "sg:phone":"+32 71 32 52 56",
    "sg:postcode":"6000",
    "sg:province":"Hainaut",
    "wof:name":"Gailly Marcel",
    "wof:placetype":"venue"
},
  "geometry": {"coordinates":[4.4443669319,50.4160881042],"type":"Point"}
}