{
  "type": "Feature",
  "properties": {
    "iso:country":"BE",
    "sg:address":"Avenue Androm\u00c8de 110",
    "sg:city":"Sint-lambrechts-woluwe/woluwe-saint-lambert",
    "sg:orig_category":"Epiceries",
    "sg:phone":"+32 2 772 68 52",
    "sg:postcode":"1200",
    "sg:province":"Bruxelles-Capitale",
    "wof:name":"Passage Androm\u00c8de",
    "wof:placetype":"venue"
},
  "geometry": {"coordinates":[4.4236559868,50.852645874],"type":"Point"}
}