{
  "type": "Feature",
  "properties": {
    "addr:full":"Ladeuze 3 Maarkedal (etikhove) Oost-Vlaanderen 9680",
    "addr:housenumber":"3",
    "addr:postcode":"9680",
    "addr:street":"Ladeuze",
    "iso:country":"BE",
    "sg:address":"Ladeuze 3",
    "sg:city":"Maarkedal (etikhove)",
    "sg:classifiers":[
        {
            "category":"Retail",
            "subcategory":"Event Space",
            "type":"Services"
        }
    ],
    "sg:phone":"+32 55 31 10 93",
    "sg:postcode":"9680",
    "sg:province":"Oost-Vlaanderen",
    "sg:tags":[
        "rental",
        "-",
        "hall"
    ],
    "wof:name":"Ladeuze Nv",
    "wof:placetype":"venue"
},
  "geometry": {"coordinates":[3.6247329712,50.8192672729],"type":"Point"}
}