{
  "type": "Feature",
  "properties": {
    "iso:country":"BE",
    "sg:address":"Chauss\u00c9e De Waterloo 729",
    "sg:city":"Ukkel/uccle",
    "sg:orig_category":"Kapsalons",
    "sg:phone":"+32 2 345 71 36",
    "sg:postcode":"1180",
    "sg:province":"Bruxelles-Capitale",
    "wof:name":"Louis Garnier",
    "wof:placetype":"venue"
},
  "geometry": {"coordinates":[4.3673171997,50.8143959045],"type":"Point"}
}