{
  "type": "Feature",
  "properties": {
    "iso:country":"BE",
    "sg:address":"Antwerpsestraat 83",
    "sg:city":"Mortsel",
    "sg:orig_category":"Meubelzaken, woning- and keukeninrichting",
    "sg:phone":"+32 3 448 08 15",
    "sg:postcode":"2640",
    "sg:province":"Antwerpen",
    "wof:name":"Master Stock",
    "wof:placetype":"venue"
},
  "geometry": {"coordinates":[4.4457187653,51.172492981],"type":"Point"}
}