{
  "type": "Feature",
  "properties": {
    "addr:full":"Barelstraat 213 Bornem Antwerpen 2880",
    "addr:housenumber":"213",
    "addr:postcode":"2880",
    "addr:street":"Barelstraat",
    "iso:country":"BE",
    "sg:address":"Barelstraat 213",
    "sg:city":"Bornem",
    "sg:orig_category":"Boucheries",
    "sg:phone":"+32 3 889 68 72",
    "sg:postcode":"2880",
    "sg:province":"Antwerpen",
    "wof:name":"Paula Daelemans",
    "wof:placetype":"venue"
},
  "geometry": {"coordinates":[4.2356119156,51.0839576721],"type":"Point"}
}