{
  "type": "Feature",
  "properties": {
    "addr:full":"Kerkhove 2 Bever Vlaams-Brabant 1547",
    "addr:housenumber":"2",
    "addr:postcode":"1547",
    "addr:street":"Kerkhove;Vlaams-Brabant",
    "iso:country":"BE",
    "sg:address":"Kerkhove 2",
    "sg:city":"Bever",
    "sg:classifiers":[
        {
            "category":"Government",
            "subcategory":"Fire Station",
            "type":"Public Place"
        }
    ],
    "sg:phone":"+32 54 58 61 29",
    "sg:postcode":"1547",
    "sg:province":"Vlaams-Brabant",
    "sg:tags":[
        "supraregional",
        "plant",
        "installation",
        "heating"
    ],
    "wof:name":"All-fa B.v.b.a.",
    "wof:placetype":"venue"
},
  "geometry": {"coordinates":[3.9383060932,50.7159538269],"type":"Point"}
}