{
  "type": "Feature",
  "properties": {
    "iso:country":"BE",
    "sg:address":"Rue G\u00e9rard Waelkens 22",
    "sg:city":"Geer",
    "sg:classifiers":[
        {
            "category":"Retail",
            "subcategory":"Auto Repair",
            "type":"Services"
        }
    ],
    "sg:phone":"+32 19 58 84 82",
    "sg:postcode":"4250",
    "sg:province":"Li\u00e8ge",
    "sg:tags":[
        "garage"
    ],
    "wof:name":"Menten J",
    "wof:placetype":"venue"
},
  "geometry": {"coordinates":[5.1661319733,50.6682701111],"type":"Point"}
}