{
  "type": "Feature",
  "properties": {
    "addr:full":"Grote Lindestraat 27-1 Hasselt Limburg 3500",
    "addr:housenumber":"27-1",
    "addr:postcode":"3500",
    "addr:street":"Grote Lindestraat",
    "iso:country":"BE",
    "sg:address":"Grote Lindestraat 27-1",
    "sg:city":"Hasselt",
    "sg:classifiers":[
        {
            "category":"Professional",
            "subcategory":"Accounting & Tax Preparation",
            "type":"Services"
        }
    ],
    "sg:phone":"+32 11 27 05 75",
    "sg:postcode":"3500",
    "sg:province":"Limburg",
    "sg:tags":[
        "accountant"
    ],
    "wof:name":"Ramakers F",
    "wof:placetype":"venue"
},
  "geometry": {"coordinates":[5.3240327835,50.9194488525],"type":"Point"}
}