{
  "type": "Feature",
  "properties": {
    "iso:country":"BE",
    "sg:address":"Avenue Du Centenaire 306",
    "sg:city":"Charleroi",
    "sg:orig_category":"Diverse bedrijfsbeheeradviesbureaus",
    "sg:phone":"+32 71 32 48 13",
    "sg:postcode":"6061",
    "sg:province":"Hainaut",
    "wof:name":"Experience Team Services",
    "wof:placetype":"venue"
},
  "geometry": {"coordinates":[4.4795150757,50.4009437561],"type":"Point"}
}