{
  "type": "Feature",
  "properties": {
    "addr:full":"Grendelbaan 52-54 Diepenbeek Limburg 3590",
    "addr:postcode":"52-54 diepenbeek;3590",
    "addr:street":"Grendelbaan",
    "iso:country":"BE",
    "sg:address":"Grendelbaan 52-54",
    "sg:city":"Diepenbeek",
    "sg:orig_category":"Quincaillerie Gr",
    "sg:phone":"+32 11 35 04 30",
    "sg:postcode":"3590",
    "sg:province":"Limburg",
    "wof:name":"Steditek",
    "wof:placetype":"venue"
},
  "geometry": {"coordinates":[5.4350800514,50.903678894],"type":"Point"}
}