{
  "type": "Feature",
  "properties": {
    "iso:country":"BE",
    "sg:address":"Jozef De Bomstraat 52",
    "sg:city":"Antwerpen",
    "sg:classifiers":[
        {
            "category":"Building & Trades",
            "subcategory":"Plumbing",
            "type":"Services"
        }
    ],
    "sg:phone":"+32 3 237 85 80",
    "sg:postcode":"2018",
    "sg:province":"Antwerpen",
    "sg:tags":[
        "contractor"
    ],
    "wof:name":"Permanent-positif Bvba",
    "wof:placetype":"venue"
},
  "geometry": {"coordinates":[4.4058680534,51.2061843872],"type":"Point"}
}