{
  "type": "Feature",
  "properties": {
    "iso:country":"BE",
    "sg:address":"Rue De Cond\u00c9 16",
    "sg:city":"Leuze-en-hainaut",
    "sg:orig_category":"Installation de serres, double vitrage and fen\u00eatres. Rev\u00eatements pour sols and murs. Peinture",
    "sg:phone":"+32 69 66 26 55",
    "sg:postcode":"7900",
    "sg:province":"Hainaut",
    "wof:name":"Vitrerie De Leuze",
    "wof:placetype":"venue"
},
  "geometry": {"coordinates":[3.6182239056,50.597454071],"type":"Point"}
}