{
  "type": "Feature",
  "properties": {
    "addr:full":"Chauss\u00c9e D'audenarde 157 Pecq Hainaut 7742",
    "addr:housenumber":"157",
    "addr:postcode":"7742",
    "addr:street":"Chausse\u0301E D'Audenarde",
    "iso:country":"BE",
    "sg:address":"Chauss\u00c9e D'audenarde 157",
    "sg:city":"Pecq",
    "sg:orig_category":"Artsen and specialisten",
    "sg:phone":"+32 69 55 66 07",
    "sg:postcode":"7742",
    "sg:province":"Hainaut",
    "wof:name":"Bernard Leroy",
    "wof:placetype":"venue"
},
  "geometry": {"coordinates":[3.3613779545,50.6910896301],"type":"Point"}
}