{
  "type": "Feature",
  "properties": {
    "addr:full":"Kerkstraat 124 Temse (tielrode) Oost-Vlaanderen 9140",
    "addr:housenumber":"124",
    "addr:postcode":"9140",
    "addr:street":"Kerkstraat",
    "iso:country":"BE",
    "sg:address":"Kerkstraat 124",
    "sg:city":"Temse (tielrode)",
    "sg:classifiers":[
        {
            "category":"Health Services",
            "subcategory":"Doctor",
            "type":"Services"
        }
    ],
    "sg:phone":"+32 3 771 53 84",
    "sg:postcode":"9140",
    "sg:province":"Oost-Vlaanderen",
    "sg:tags":[
        "medicinephysicians",
        "surgeon"
    ],
    "wof:name":"Hendrickx Karl",
    "wof:placetype":"venue"
},
  "geometry": {"coordinates":[4.174434185,51.1217308044],"type":"Point"}
}