{
  "type": "Feature",
  "properties": {
    "addr:full":"Gentse Steenweg 9 Lokeren Oost-Vlaanderen 9160",
    "addr:housenumber":"9",
    "addr:postcode":"9160",
    "addr:street":"Gentse Steenweg",
    "iso:country":"BE",
    "sg:address":"Gentse Steenweg 9",
    "sg:city":"Lokeren",
    "sg:classifiers":[
        {
            "category":"Shopping",
            "subcategory":"Bicycles & Sporting Goods",
            "type":"Retail Goods"
        }
    ],
    "sg:phone":"+32 9 348 15 69",
    "sg:postcode":"9160",
    "sg:province":"Oost-Vlaanderen",
    "sg:tags":[
        "-"
    ],
    "wof:name":"Motorama",
    "wof:placetype":"venue"
},
  "geometry": {"coordinates":[3.9687299728,51.1099586487],"type":"Point"}
}