{
  "type": "Feature",
  "properties": {
    "iso:country":"BE",
    "sg:address":"\u00b4s Graventafelstraat 58",
    "sg:city":"Zonnebeke",
    "sg:orig_category":"Producteurs de l\u00e9gumes",
    "sg:phone":"+32 51 77 80 76",
    "sg:postcode":"8980",
    "sg:province":"West-Vlaanderen",
    "wof:name":"Eric Pauwelyn",
    "wof:placetype":"venue"
},
  "geometry": {"coordinates":[2.9872550964,50.8730812073],"type":"Point"}
}