{
  "type": "Feature",
  "properties": {
    "addr:full":"Rue De La Prison 2 La Hulpe Brabant Wallon 1310",
    "addr:housenumber":"2",
    "addr:postcode":"1310",
    "addr:street":"Rue De La Prison",
    "iso:country":"BE",
    "sg:address":"Rue De La Prison 2",
    "sg:city":"La Hulpe",
    "sg:classifiers":[
        {
            "category":"Retail",
            "subcategory":"Animal Services",
            "type":"Services"
        }
    ],
    "sg:phone":"+32 2 652 16 82",
    "sg:postcode":"1310",
    "sg:province":"Brabant Wallon",
    "sg:tags":[
        "farrier"
    ],
    "wof:name":"Ennouni Redouane",
    "wof:placetype":"venue"
},
  "geometry": {"coordinates":[4.4655570984,50.7233352661],"type":"Point"}
}