{
  "type": "Feature",
  "properties": {
    "addr:full":"Route De L'etat 301 Lasne Brabant Wallon 1380",
    "addr:housenumber":"301",
    "addr:postcode":"1380",
    "addr:street":"Route De L'Etat",
    "iso:country":"BE",
    "sg:address":"Route De L'etat 301",
    "sg:city":"Lasne",
    "sg:orig_category":"Slagers",
    "sg:phone":"+32 2 633 13 26",
    "sg:postcode":"1380",
    "sg:province":"Brabant Wallon",
    "wof:name":"Boucherie Pascal",
    "wof:placetype":"venue"
},
  "geometry": {"coordinates":[4.4617218971,50.6611251831],"type":"Point"}
}