{
  "type": "Feature",
  "properties": {
    "iso:country":"BE",
    "sg:address":"Burg. Felix De Bethuneln 1",
    "sg:city":"Kortrijk",
    "sg:orig_category":"Boekhouders",
    "sg:phone":"+32 56 25 90 38",
    "sg:postcode":"8500",
    "sg:province":"West-Vlaanderen",
    "wof:name":"Micheline Vanhee",
    "wof:placetype":"venue"
},
  "geometry": {"coordinates":[3.254488945,50.8219795227],"type":"Point"}
}