{
  "type": "Feature",
  "properties": {
    "iso:country":"BE",
    "sg:address":"Fauvillers-centre 77",
    "sg:city":"Fauvillers",
    "sg:orig_category":"Instellingen voor mindervalide volwassenen",
    "sg:phone":"+32 63 60 08 00",
    "sg:postcode":"6637",
    "sg:province":"Luxembourg",
    "wof:name":"La Maison De Volaiville",
    "wof:placetype":"venue"
},
  "geometry": {"coordinates":[5.6666331291,49.8507423401],"type":"Point"}
}