{
  "type": "Feature",
  "properties": {
    "iso:country":"BE",
    "sg:address":"Rue Joseph Pierco 12",
    "sg:city":"Nandrin",
    "sg:orig_category":"Boucheries",
    "sg:phone":"+32 85 51 12 85",
    "sg:postcode":"4550",
    "sg:province":"Li\u00e8ge",
    "wof:name":"Serge Sombaert",
    "wof:placetype":"venue"
},
  "geometry": {"coordinates":[5.370320797,50.5091552734],"type":"Point"}
}