{
  "type": "Feature",
  "properties": {
    "iso:country":"BE",
    "sg:address":"Brugsestraat 26",
    "sg:city":"Oostkamp",
    "sg:orig_category":"Industri\u00eble wasserijen and droogkuis",
    "sg:phone":"+32 50 82 55 88",
    "sg:postcode":"8020",
    "sg:province":"West-Vlaanderen",
    "wof:name":"Droogkuis Aneca-st.andr\u00c9",
    "wof:placetype":"venue"
},
  "geometry": {"coordinates":[3.2358798981,51.1553726196],"type":"Point"}
}