{
  "type": "Feature",
  "properties": {
    "addr:full":"Rue Du Chalet 22 Aywaille Li\u00e8ge 4920",
    "addr:housenumber":"22",
    "addr:postcode":"4920",
    "addr:street":"Rue Du Chalet",
    "iso:country":"BE",
    "sg:address":"Rue Du Chalet 22",
    "sg:city":"Aywaille",
    "sg:orig_category":"M\u00e9decines alternatives",
    "sg:phone":"+32 4 384 71 82",
    "sg:postcode":"4920",
    "sg:province":"Li\u00e8ge",
    "wof:name":"Jean-marc Delvaux",
    "wof:placetype":"venue"
},
  "geometry": {"coordinates":[5.6784701347,50.4702911377],"type":"Point"}
}