{
  "type": "Feature",
  "properties": {
    "addr:full":"Naamsesteenweg 79 Oud-heverlee Vlaams-Brabant 3052",
    "addr:housenumber":"79",
    "addr:postcode":"3052",
    "addr:street":"Naamsesteenweg",
    "iso:country":"BE",
    "sg:address":"Naamsesteenweg 79",
    "sg:city":"Oud-heverlee",
    "sg:orig_category":"Boucheries",
    "sg:phone":"+32 16 40 08 04",
    "sg:postcode":"3052",
    "sg:province":"Vlaams-Brabant",
    "wof:name":"Schroeven Rudy En Peter",
    "wof:placetype":"venue"
},
  "geometry": {"coordinates":[4.7015018463,50.8269958496],"type":"Point"}
}