{
  "type": "Feature",
  "properties": {
    "iso:country":"BE",
    "sg:address":"Jef Vandermeulenstraat 59",
    "sg:city":"Gent",
    "sg:orig_category":"Artsen and specialisten",
    "sg:phone":"+32 9 230 24 57",
    "sg:postcode":"9050",
    "sg:province":"Oost-Vlaanderen",
    "wof:name":"P. Behaeghe",
    "wof:placetype":"venue"
},
  "geometry": {"coordinates":[3.7573349476,51.0415916443],"type":"Point"}
}