{
  "type": "Feature",
  "properties": {
    "iso:country":"BE",
    "sg:address":"Bd Du Triomphe 172",
    "sg:city":"Bruxelles",
    "sg:classifiers":[
        {
            "category":"Banks & Credit Unions",
            "subcategory":"Financial Services",
            "type":"Services"
        }
    ],
    "sg:phone":"+32 2 533 75 75",
    "sg:postcode":"1160",
    "sg:province":"Bruxelles-Capitale",
    "sg:tags":[
        "banking",
        "finance",
        "insurance"
    ],
    "wof:name":"Europ Assistance Belgium Sa",
    "wof:placetype":"venue"
},
  "geometry": {"coordinates":[4.4030051231,50.8182754517],"type":"Point"}
}