{
  "type": "Feature",
  "properties": {
    "addr:full":"Beukenstraat 4 Olen Antwerpen 2250",
    "addr:housenumber":"4",
    "addr:postcode":"2250",
    "addr:street":"Beukenstraat",
    "iso:country":"BE",
    "sg:address":"Beukenstraat 4",
    "sg:city":"Olen",
    "sg:classifiers":[
        {
            "category":"Home & Garden",
            "subcategory":"Household Appliances",
            "type":"Retail Goods"
        }
    ],
    "sg:phone":"+32 14 26 71 83",
    "sg:postcode":"2250",
    "sg:province":"Antwerpen",
    "sg:tags":[
        "repair",
        "mainten",
        "-",
        "electric"
    ],
    "wof:name":"Van Looy Electro",
    "wof:placetype":"venue"
},
  "geometry": {"coordinates":[4.8463702202,51.1465644836],"type":"Point"}
}