{
  "type": "Feature",
  "properties": {
    "addr:full":"Nijverheidsstraat 91-95 Dikkelvenne Oost-Vlaanderen 9890",
    "addr:housenumber":"91-95",
    "addr:postcode":"9890",
    "addr:street":"Nijverheidsstraat;Oost-Vlaanderen",
    "iso:country":"BE",
    "sg:address":"Nijverheidsstraat 91-95",
    "sg:city":"Dikkelvenne",
    "sg:orig_category":"Aluminium-Steel-Glass Fa\u00e7ades",
    "sg:phone":"+32 9 389 99 10",
    "sg:postcode":"9890",
    "sg:province":"Oost-Vlaanderen",
    "wof:name":"Belgo Metal Permasteelisa Group Nv",
    "wof:placetype":"venue"
},
  "geometry": {"coordinates":[3.6784958839,50.9219512939],"type":"Point"}
}