{
  "type": "Feature",
  "properties": {
    "iso:country":"BE",
    "sg:address":"Opoeterseweg 78",
    "sg:city":"Maaseik",
    "sg:classifiers":[
        {
            "category":"Cafe",
            "type":"Food & Drink"
        }
    ],
    "sg:phone":"+32 89 86 30 28",
    "sg:postcode":"3680",
    "sg:province":"Limburg",
    "sg:tags":[
        "caf\u00e9s"
    ],
    "wof:name":"De Smied Van Berg",
    "wof:placetype":"venue"
},
  "geometry": {"coordinates":[5.791285038,51.0954208374],"type":"Point"}
}