{
  "type": "Feature",
  "properties": {
    "addr:full":"Edward Dekosterstraat 64 Evere Vlaams-Brabant 1830",
    "addr:housenumber":"64",
    "addr:postcode":"1830",
    "addr:street":"Edward Dekosterstraat",
    "iso:country":"BE",
    "sg:address":"Edward Dekosterstraat 64",
    "sg:city":"Evere",
    "sg:orig_category":"Diensten voor huisdieren",
    "sg:phone":"+32 2 241 88 01",
    "sg:postcode":"1830",
    "sg:province":"Vlaams-Brabant",
    "wof:name":"Dog Style",
    "wof:placetype":"venue"
},
  "geometry": {"coordinates":[4.403635025,50.8782272339],"type":"Point"}
}