{
  "type": "Feature",
  "properties": {
    "iso:country":"BE",
    "sg:address":"Rue Louvi\u00c8re 61",
    "sg:city":"Tournai",
    "sg:orig_category":"Paramedische behandelingen",
    "sg:phone":"+32 69 54 82 44",
    "sg:postcode":"7530",
    "sg:province":"Hainaut",
    "wof:name":"M.p. Delcroix",
    "wof:placetype":"venue"
},
  "geometry": {"coordinates":[3.4959840775,50.5858192444],"type":"Point"}
}