{
  "type": "Feature",
  "properties": {
    "iso:country":"BE",
    "sg:address":"Bosstraat 10",
    "sg:city":"Bocholt",
    "sg:orig_category":"Industri\u00eble and commerci\u00eble bouw Woningbouw",
    "sg:phone":"+32 89 46 64 39",
    "sg:postcode":"3950",
    "sg:province":"Limburg",
    "wof:name":"Clauwers",
    "wof:placetype":"venue"
},
  "geometry": {"coordinates":[5.5528597832,51.1815605164],"type":"Point"}
}