{
  "type": "Feature",
  "properties": {
    "addr:full":"Rue Du Couvent 35 Rixensart Brabant Wallon 1332",
    "addr:housenumber":"35",
    "addr:postcode":"1332",
    "addr:street":"Rue Du Couvent;Wallon",
    "iso:country":"BE",
    "sg:address":"Rue Du Couvent 35",
    "sg:city":"Rixensart",
    "sg:orig_category":"Plomberie, chauffage and installations sanitaires",
    "sg:phone":"+32 2 653 60 72",
    "sg:postcode":"1332",
    "sg:province":"Brabant Wallon",
    "wof:name":"Chauffage L.r.t.",
    "wof:placetype":"venue"
},
  "geometry": {"coordinates":[4.4959287643,50.7136383057],"type":"Point"}
}