{
  "type": "Feature",
  "properties": {
    "addr:full":"Blekerijstraat 75 Box 18 Gent Oost-Vlaanderen 9000",
    "addr:housenumber":"75 box 18",
    "addr:postcode":"9000",
    "addr:street":"Blekerijstraat;Oost-Vlaanderen",
    "iso:country":"BE",
    "sg:address":"Blekerijstraat 75 Box 18",
    "sg:city":"Gent",
    "sg:classifiers":[
        {
            "category":"Professional",
            "subcategory":"Detective & Security Services",
            "type":"Services"
        }
    ],
    "sg:phone":"+32 9 224 02 25",
    "sg:postcode":"9000",
    "sg:province":"Oost-Vlaanderen",
    "sg:tags":[
        "door",
        "videophones",
        "operating",
        "equipment"
    ],
    "wof:name":"Electrobuild Gent",
    "wof:placetype":"venue"
},
  "geometry": {"coordinates":[3.7326099873,51.0597686768],"type":"Point"}
}