{
  "type": "Feature",
  "properties": {
    "iso:country":"BE",
    "sg:address":"Bazelstraat 61",
    "sg:city":"Kruibeke",
    "sg:classifiers":[
        {
            "category":"Home & Garden",
            "subcategory":"Furniture",
            "type":"Retail Goods"
        }
    ],
    "sg:phone":"+32 9 386 17 93",
    "sg:postcode":"9150",
    "sg:province":"Oost-Vlaanderen",
    "sg:tags":[
        "designer"
    ],
    "wof:name":"Mdc-meubelen B.v.b.a.",
    "wof:placetype":"venue"
},
  "geometry": {"coordinates":[3.494412899,50.9553871155],"type":"Point"}
}