{
  "type": "Feature",
  "properties": {
    "addr:full":"Chemin De Rouheid 20 Verviers (heusy) Li\u00e8ge 4802",
    "addr:housenumber":"20",
    "addr:postcode":"4802",
    "addr:street":"Chemin De Rouheid",
    "iso:country":"BE",
    "sg:address":"Chemin De Rouheid 20",
    "sg:city":"Verviers (heusy)",
    "sg:classifiers":[
        {
            "category":"Professional",
            "subcategory":"Management & Consulting",
            "type":"Services"
        }
    ],
    "sg:phone":"+32 87 22 91 27",
    "sg:postcode":"4802",
    "sg:province":"Li\u00e8ge",
    "sg:tags":[
        "consultant"
    ],
    "wof:name":"J G Consult Sprl",
    "wof:placetype":"venue"
},
  "geometry": {"coordinates":[5.875038147,50.5789833069],"type":"Point"}
}