{
  "type": "Feature",
  "properties": {
    "iso:country":"BE",
    "sg:address":"Paulusstraat 18",
    "sg:city":"Herk-de-stad (berbroek)",
    "sg:classifiers":[
        {
            "category":"Building & Trades",
            "subcategory":"Construction",
            "type":"Services"
        }
    ],
    "sg:phone":"+32 13 55 18 55",
    "sg:postcode":"3540",
    "sg:province":"Limburg",
    "sg:tags":[
        "installation",
        "-",
        "central",
        "heating"
    ],
    "wof:name":"Vandereycken",
    "wof:placetype":"venue"
},
  "geometry": {"coordinates":[5.2109827995,50.9509963989],"type":"Point"}
}