{
  "type": "Feature",
  "properties": {
    "iso:country":"BE",
    "sg:address":"Kerkplein 25b6",
    "sg:city":"Zaventem",
    "sg:orig_category":"Organisation de salons, expositions and bourses. Services divers aux entreprises",
    "sg:phone":"+32 2 725 33 08",
    "sg:postcode":"1930",
    "sg:province":"Vlaams-Brabant",
    "wof:name":"Meisser Expo",
    "wof:placetype":"venue"
},
  "geometry": {"coordinates":[4.4730057716,50.8816452026],"type":"Point"}
}