{
  "type": "Feature",
  "properties": {
    "iso:country":"BE",
    "sg:address":"Ch. De Ninove 1136",
    "sg:city":"Sint-jans-molenbeek/molenbeek-",
    "sg:orig_category":"Mat\u00e9riel de T\u00e9l\u00e9communication. Syst\u00e8mes de t\u00e9l\u00e9communications. D\u00e9taillants en pi\u00e8ces and accessoires",
    "sg:phone":"+32 2 524 25 82",
    "sg:postcode":"1080",
    "sg:province":"Bruxelles-Capitale",
    "wof:name":"Arwac Business",
    "wof:placetype":"venue"
},
  "geometry": {"coordinates":[4.284828186,50.8455963135],"type":"Point"}
}