{
  "type": "Feature",
  "properties": {
    "iso:country":"BE",
    "sg:address":"Luxemburger Strasse 69",
    "sg:city":"Sankt Vith",
    "sg:orig_category":"Oldtimers",
    "sg:phone":"+32 80 22 83 89",
    "sg:postcode":"4780",
    "sg:province":"Li\u00e8ge",
    "wof:name":"Braquet",
    "wof:placetype":"venue"
},
  "geometry": {"coordinates":[6.1193141937,50.2735061646],"type":"Point"}
}