{
  "type": "Feature",
  "properties": {
    "addr:full":"Lange Van Ruusbroecstraat 59 Antwerpen Antwerpen 2018",
    "addr:housenumber":"59",
    "addr:postcode":"2018",
    "addr:street":"Lange Van Ruusbroecstraat",
    "iso:country":"BE",
    "sg:address":"Lange Van Ruusbroecstraat 59",
    "sg:city":"Antwerpen",
    "sg:classifiers":[
        {
            "category":"Professional",
            "subcategory":"Art Services",
            "type":"Services"
        }
    ],
    "sg:phone":"+32 3 238 22 17",
    "sg:postcode":"2018",
    "sg:province":"Antwerpen",
    "sg:tags":[
        "realization",
        "audio-visual"
    ],
    "wof:name":"Cue-cam",
    "wof:placetype":"venue"
},
  "geometry": {"coordinates":[4.4281101227,51.2085533142],"type":"Point"}
}