{
  "type": "Feature",
  "properties": {
    "iso:country":"BE",
    "sg:address":"Rue Haute 16",
    "sg:city":"Wavre",
    "sg:orig_category":"Pain, p\u00e2tisseries and confiseries",
    "sg:phone":"+32 10 24 34 10",
    "sg:postcode":"1300",
    "sg:province":"Brabant Wallon",
    "wof:name":"Van De Kerkhove J.",
    "wof:placetype":"venue"
},
  "geometry": {"coordinates":[4.6094517708,50.7165222168],"type":"Point"}
}