{
  "type": "Feature",
  "properties": {
    "iso:country":"BE",
    "sg:address":"Zuidlaan 28",
    "sg:city":"Zwalm",
    "sg:orig_category":"Pain, p\u00e2tisseries and confiseries",
    "sg:phone":"+32 55 49 77 19",
    "sg:postcode":"9630",
    "sg:province":"Oost-Vlaanderen",
    "wof:name":"Isabelle",
    "wof:placetype":"venue"
},
  "geometry": {"coordinates":[3.7329030037,50.8781547546],"type":"Point"}
}