{
  "type": "Feature",
  "properties": {
    "addr:full":"Rue De Roblet 4 Chaumont-gistoux Brabant Wallon 1325",
    "addr:housenumber":"4",
    "addr:postcode":"1325",
    "addr:street":"Rue De Roblet",
    "iso:country":"BE",
    "sg:address":"Rue De Roblet 4",
    "sg:city":"Chaumont-gistoux",
    "sg:classifiers":[
        {
            "category":"Government",
            "subcategory":"Customs House",
            "type":"Public Place"
        }
    ],
    "sg:phone":"+32 10 88 93 10",
    "sg:postcode":"1325",
    "sg:province":"Brabant Wallon",
    "sg:tags":[
        "affair",
        "consulting",
        "management",
        "european"
    ],
    "wof:name":"Bureau Euro Consult S.c.",
    "wof:placetype":"venue"
},
  "geometry": {"coordinates":[4.7223548889,50.6729545593],"type":"Point"}
}