{
  "type": "Feature",
  "properties": {
    "iso:country":"BE",
    "sg:address":"Avenue De L\u00b4europe 5",
    "sg:city":"Leuze-en-hainaut",
    "sg:orig_category":"Herstellingen and onderhoud van auto's",
    "sg:phone":"+32 69 66 55 58",
    "sg:postcode":"7903",
    "sg:province":"Hainaut",
    "wof:name":"Garage Phil-occas",
    "wof:placetype":"venue"
},
  "geometry": {"coordinates":[3.6526470184,50.6048545837],"type":"Point"}
}