{
  "type": "Feature",
  "properties": {
    "addr:full":"Rue Th\u00c9odore Verhaegen 6 Sint-gillis/saint-gilles Bruxelles-Capitale 1060",
    "addr:housenumber":"6",
    "addr:postcode":"1060",
    "addr:street":"Rue The\u0301Odore Verhaegen",
    "iso:country":"BE",
    "sg:address":"Rue Th\u00c9odore Verhaegen 6",
    "sg:city":"Sint-gillis/saint-gilles",
    "sg:orig_category":"Enseignement secondaire technique and professionnel. Enseignement secondaire g\u00e9n\u00e9ral",
    "sg:phone":"+32 2 537 99 80",
    "sg:postcode":"1060",
    "sg:province":"Bruxelles-Capitale",
    "wof:name":"Institut Filles De Marie",
    "wof:placetype":"venue"
},
  "geometry": {"coordinates":[4.3437819481,50.8271026611],"type":"Point"}
}