{
  "type": "Feature",
  "properties": {
    "iso:country":"BE",
    "sg:address":"Ankerslaan 1a",
    "sg:city":"Gent (ledeberg)",
    "sg:classifiers":[
        {
            "category":"Professional",
            "subcategory":"Detective & Security Services",
            "type":"Services"
        }
    ],
    "sg:phone":"+32 9 232 00 04",
    "sg:postcode":"9050",
    "sg:province":"Oost-Vlaanderen",
    "sg:tags":[
        "agency"
    ],
    "wof:name":"European Detective Agency/vanloo",
    "wof:placetype":"venue"
},
  "geometry": {"coordinates":[3.7492129803,51.0376319885],"type":"Point"}
}