{
  "type": "Feature",
  "properties": {
    "addr:full":"Steenweg Op Papenbroek 1 Diest Vlaams-Brabant 3290",
    "addr:housenumber":"1",
    "addr:postcode":"3290",
    "addr:street":"Steenweg Op Papenbroek",
    "iso:country":"BE",
    "sg:address":"Steenweg Op Papenbroek 1",
    "sg:city":"Diest",
    "sg:orig_category":"Catering and organisation de f\u00eates",
    "sg:phone":"+32 497 20 90 89",
    "sg:postcode":"3290",
    "sg:province":"Vlaams-Brabant",
    "wof:name":"Verogin",
    "wof:placetype":"venue"
},
  "geometry": {"coordinates":[5.0566701889,50.9776268005],"type":"Point"}
}