{
  "type": "Feature",
  "properties": {
    "iso:country":"BE",
    "sg:address":"Marktstraat 2",
    "sg:city":"Kortrijk (marke)",
    "sg:classifiers":[
        {
            "category":"Professional",
            "subcategory":"Detective & Security Services",
            "type":"Services"
        }
    ],
    "sg:phone":"+32 56 21 41 68",
    "sg:postcode":"8510",
    "sg:province":"West-Vlaanderen",
    "sg:tags":[
        "installation",
        "alarm",
        "-",
        "system"
    ],
    "wof:name":"Quartier",
    "wof:placetype":"venue"
},
  "geometry": {"coordinates":[3.234926939,50.8092956543],"type":"Point"}
}