{
  "type": "Feature",
  "properties": {
    "addr:full":"Stationsstraat 28 Kapellen Antwerpen 2950",
    "addr:housenumber":"28",
    "addr:postcode":"2950",
    "addr:street":"Stationsstraat",
    "iso:country":"BE",
    "sg:address":"Stationsstraat 28",
    "sg:city":"Kapellen",
    "sg:orig_category":"Quincailleries. Quincaillerie Gr",
    "sg:phone":"+32 3 664 24 76",
    "sg:postcode":"2950",
    "sg:province":"Antwerpen",
    "wof:name":"Karl Lodewyckx",
    "wof:placetype":"venue"
},
  "geometry": {"coordinates":[4.4311637878,51.3141059875],"type":"Point"}
}