{
  "type": "Feature",
  "properties": {
    "iso:country":"BE",
    "sg:address":"Donksesteenweg 86",
    "sg:city":"Brasschaat",
    "sg:classifiers":[
        {
            "category":"Professional",
            "subcategory":"Computer Services",
            "type":"Services"
        }
    ],
    "sg:phone":"+32 3 652 08 48",
    "sg:postcode":"2930",
    "sg:province":"Antwerpen",
    "sg:tags":[
        "-",
        "processing",
        "data"
    ],
    "wof:name":"Unidec",
    "wof:placetype":"venue"
},
  "geometry": {"coordinates":[4.4770560265,51.2856521606],"type":"Point"}
}