{
  "type": "Feature",
  "properties": {
    "iso:country":"BE",
    "sg:address":"Markt 15",
    "sg:city":"Lokeren",
    "sg:classifiers":[
        {
            "category":"Restaurant",
            "type":"Food & Drink"
        }
    ],
    "sg:phone":"+32 9 349 02 40",
    "sg:postcode":"9160",
    "sg:province":"Oost-Vlaanderen",
    "wof:name":"Rich",
    "wof:placetype":"venue"
},
  "geometry": {"coordinates":[3.9887759686,51.1049461365],"type":"Point"}
}