{
  "type": "Feature",
  "properties": {
    "iso:country":"BE",
    "sg:address":"Rijselstraat 57 A",
    "sg:city":"Brugge",
    "sg:orig_category":"Immobili\u00ebnkantoren",
    "sg:phone":"+32 50 39 53 95",
    "sg:postcode":"8200",
    "sg:province":"West-Vlaanderen",
    "wof:name":"Merit",
    "wof:placetype":"venue"
},
  "geometry": {"coordinates":[3.2116639614,51.1888809204],"type":"Point"}
}