{
  "type": "Feature",
  "properties": {
    "addr:full":"Rue Du Cheval Godet 84 Nivelles Brabant Wallon 1400",
    "addr:housenumber":"84",
    "addr:postcode":"1400",
    "addr:street":"Rue Du Cheval Godet",
    "iso:country":"BE",
    "sg:address":"Rue Du Cheval Godet 84",
    "sg:city":"Nivelles",
    "sg:classifiers":[
        {
            "category":"Health Services",
            "subcategory":"Health Practitioner",
            "type":"Services"
        }
    ],
    "sg:phone":"+32 67 21 73 11",
    "sg:postcode":"1400",
    "sg:province":"Brabant Wallon",
    "sg:tags":[
        "therapist",
        "speech"
    ],
    "wof:name":"Terreur",
    "wof:placetype":"venue"
},
  "geometry": {"coordinates":[4.3216900826,50.6047897339],"type":"Point"}
}