{
  "type": "Feature",
  "properties": {
    "addr:full":"Tongersestraat 375 Borgloon Limburg 3840",
    "addr:housenumber":"375",
    "addr:postcode":"3840",
    "addr:street":"Tongersestraat",
    "iso:country":"BE",
    "sg:address":"Tongersestraat 375",
    "sg:city":"Borgloon",
    "sg:classifiers":[
        {
            "category":"Food & Beverages",
            "subcategory":"Groceries & Convenience Stores",
            "type":"Retail Goods"
        }
    ],
    "sg:phone":"+32 12 74 37 07",
    "sg:postcode":"3840",
    "sg:province":"Limburg",
    "sg:tags":[
        "grocer"
    ],
    "wof:name":"Slegers J-m",
    "wof:placetype":"venue"
},
  "geometry": {"coordinates":[5.3479499817,50.8024787903],"type":"Point"}
}