{
  "type": "Feature",
  "properties": {
    "addr:full":"Holstraat 59 Liedekerke Vlaams-Brabant 1770",
    "addr:housenumber":"59",
    "addr:postcode":"1770",
    "addr:street":"Holstraat;Vlaams-Brabant",
    "iso:country":"BE",
    "sg:address":"Holstraat 59",
    "sg:city":"Liedekerke",
    "sg:orig_category":"Gespecialiseerde residenti\u00eble bouw",
    "sg:phone":"+32 53 68 07 08",
    "sg:postcode":"1770",
    "sg:province":"Vlaams-Brabant",
    "wof:name":"Luc Bracke",
    "wof:placetype":"venue"
},
  "geometry": {"coordinates":[4.0716099739,50.8568611145],"type":"Point"}
}