{
  "type": "Feature",
  "properties": {
    "addr:full":"Betekomsesteenweg 120 Aarschot Vlaams-Brabant 3200",
    "addr:housenumber":"120",
    "addr:postcode":"3200",
    "addr:street":"Betekomsesteenweg",
    "iso:country":"BE",
    "sg:address":"Betekomsesteenweg 120",
    "sg:city":"Aarschot",
    "sg:classifiers":[
        {
            "category":"Retail",
            "subcategory":"Auto Repair",
            "type":"Services"
        }
    ],
    "sg:phone":"+32 16 56 38 39",
    "sg:postcode":"3200",
    "sg:province":"Vlaams-Brabant",
    "sg:tags":[
        "garage"
    ],
    "wof:name":"Skoda/merckx Jos Bvba",
    "wof:placetype":"venue"
},
  "geometry": {"coordinates":[4.8128600121,50.9902076721],"type":"Point"}
}