{
  "type": "Feature",
  "properties": {
    "addr:full":"Jezusstraat 44b Antwerpen Antwerpen 2000",
    "addr:housenumber":"44b",
    "addr:postcode":"2000",
    "addr:street":"Jezusstraat",
    "iso:country":"BE",
    "sg:address":"Jezusstraat 44b",
    "sg:city":"Antwerpen",
    "sg:classifiers":[
        {
            "category":"Professional",
            "subcategory":"Employment Agencies",
            "type":"Services"
        }
    ],
    "sg:phone":"+32 70 23 32 26",
    "sg:postcode":"2000",
    "sg:province":"Antwerpen",
    "sg:tags":[
        "temping",
        "-",
        "manual"
    ],
    "wof:name":"Adecco Hospitality",
    "wof:placetype":"venue"
},
  "geometry": {"coordinates":[4.4147410393,51.2195091248],"type":"Point"}
}