{
  "type": "Feature",
  "properties": {
    "addr:full":"Passendalestraat 205 Zonnebeke West-Vlaanderen 8980",
    "addr:housenumber":"205",
    "addr:postcode":"8980",
    "addr:street":"Passendalestraat",
    "iso:country":"BE",
    "sg:address":"Passendalestraat 205",
    "sg:city":"Zonnebeke",
    "sg:classifiers":[
        {
            "category":"Personal",
            "subcategory":"Beauty Salon",
            "type":"Services"
        }
    ],
    "sg:phone":"+32 51 77 27 50",
    "sg:postcode":"8980",
    "sg:province":"West-Vlaanderen",
    "sg:tags":[
        "de",
        "coiffure"
    ],
    "wof:name":"Salon Dynamique",
    "wof:placetype":"venue"
},
  "geometry": {"coordinates":[3.0089900494,50.887348175],"type":"Point"}
}