{
  "type": "Feature",
  "properties": {
    "addr:full":"Place Henri Berger 11 Wavre Brabant Wallon 1300",
    "addr:housenumber":"11;1300",
    "addr:street":"Place Henri Berger",
    "iso:country":"BE",
    "sg:address":"Place Henri Berger 11",
    "sg:city":"Wavre",
    "sg:classifiers":[
        {
            "category":"Shopping",
            "subcategory":"Gifts & Souvenirs",
            "type":"Retail Goods"
        }
    ],
    "sg:phone":"+32 10 22 87 84",
    "sg:postcode":"1300",
    "sg:province":"Brabant Wallon",
    "sg:tags":[
        "-"
    ],
    "wof:name":"Casa",
    "wof:placetype":"venue"
},
  "geometry": {"coordinates":[4.605905056,50.7155990601],"type":"Point"}
}