{
  "type": "Feature",
  "properties": {
    "iso:country":"BE",
    "sg:address":"Rijksweg 537 A",
    "sg:city":"Maasmechelen",
    "sg:orig_category":"Bloemen and planten Geschenken and souvenirs Huisdieren and benodigdheden Royal Canin Tuinbenodigdhe",
    "sg:phone":"+32 89 76 58 10",
    "sg:postcode":"3630",
    "sg:province":"Limburg",
    "wof:name":"Aveve. Maasmechelen",
    "wof:placetype":"venue"
},
  "geometry": {"coordinates":[5.6932902336,50.948299408],"type":"Point"}
}