{
  "type": "Feature",
  "properties": {
    "addr:full":"Overdemerstraat 109 Hasselt (kuringen) Limburg 3511",
    "addr:housenumber":"109",
    "addr:postcode":"3511",
    "addr:street":"Overdemerstraat",
    "iso:country":"BE",
    "sg:address":"Overdemerstraat 109",
    "sg:city":"Hasselt (kuringen)",
    "sg:classifiers":[
        {
            "category":"Building & Trades",
            "subcategory":"Construction",
            "type":"Services"
        }
    ],
    "sg:phone":"+32 11 25 01 80",
    "sg:postcode":"3511",
    "sg:province":"Limburg",
    "sg:tags":[
        "stucco",
        "contractor"
    ],
    "wof:name":"Massin P",
    "wof:placetype":"venue"
},
  "geometry": {"coordinates":[5.3123722076,50.9516105652],"type":"Point"}
}