{
  "type": "Feature",
  "properties": {
    "addr:full":"Boulevard Isabelle Brunell 2-1 Namur Namur 5000",
    "addr:housenumber":"2-1",
    "addr:postcode":"5000",
    "addr:street":"Boulevard Isabelle Brunell",
    "iso:country":"BE",
    "sg:address":"Boulevard Isabelle Brunell 2-1",
    "sg:city":"Namur",
    "sg:classifiers":[
        {
            "category":"Professional",
            "subcategory":"Lawyer & Legal Services",
            "type":"Services"
        }
    ],
    "sg:phone":"+32 81 22 55 34",
    "sg:postcode":"5000",
    "sg:province":"Namur",
    "wof:name":"Brix Fran\u00e7oise",
    "wof:placetype":"venue"
},
  "geometry": {"coordinates":[4.8724918365,50.4629516602],"type":"Point"}
}