{
  "type": "Feature",
  "properties": {
    "iso:country":"BE",
    "sg:address":"Brusselstraat 193",
    "sg:city":"Dilbeek",
    "sg:orig_category":"Banken and kredietinstellingen",
    "sg:phone":"+32 2 466 48 98",
    "sg:postcode":"1702",
    "sg:province":"Vlaams-Brabant",
    "wof:name":"Bbl",
    "wof:placetype":"venue"
},
  "geometry": {"coordinates":[4.2656598091,50.8710403442],"type":"Point"}
}