{
  "type": "Feature",
  "properties": {
    "addr:full":"Rondplein 12 Mol Antwerpen 2400",
    "addr:housenumber":"12",
    "addr:postcode":"2400",
    "addr:street":"Rondplein",
    "iso:country":"BE",
    "sg:address":"Rondplein 12",
    "sg:city":"Mol",
    "sg:orig_category":"Banques and organismes de cr\u00e9dit",
    "sg:phone":"+32 14 31 64 07",
    "sg:postcode":"2400",
    "sg:province":"Antwerpen",
    "wof:name":"Centea",
    "wof:placetype":"venue"
},
  "geometry": {"coordinates":[5.1165409088,51.1871643066],"type":"Point"}
}