{
  "type": "Feature",
  "properties": {
    "addr:full":"Rue De La Fraide 9 Mons Hainaut 7033",
    "addr:housenumber":"9",
    "addr:postcode":"7033",
    "addr:street":"Rue De La Fraide;Hainaut",
    "iso:country":"BE",
    "sg:address":"Rue De La Fraide 9",
    "sg:city":"Mons",
    "sg:orig_category":"Avocats and conseillers juridiques",
    "sg:phone":"+32 65 33 62 82",
    "sg:postcode":"7033",
    "sg:province":"Hainaut",
    "wof:name":"Sylviane Pichu\u00c8que",
    "wof:placetype":"venue"
},
  "geometry": {"coordinates":[3.9253261089,50.4366378784],"type":"Point"}
}