{
  "type": "Feature",
  "properties": {
    "addr:full":"Rue Des Combattants 19-21 Tournai (kain) Hainaut 7540",
    "addr:postcode":"19-21;7540",
    "addr:street":"Rue Des Combattants",
    "iso:country":"BE",
    "sg:address":"Rue Des Combattants 19-21",
    "sg:city":"Tournai (kain)",
    "sg:classifiers":[
        {
            "category":"Retail",
            "subcategory":"Repair Shop",
            "type":"Services"
        }
    ],
    "sg:phone":"+32 69 22 74 25",
    "sg:postcode":"7540",
    "sg:province":"Hainaut",
    "sg:tags":[
        "radio",
        "television",
        "-",
        "maintenance"
    ],
    "wof:name":"Leveugle-winberg Ets",
    "wof:placetype":"venue"
},
  "geometry": {"coordinates":[3.3770060539,50.6367225647],"type":"Point"}
}