{
  "type": "Feature",
  "properties": {
    "addr:full":"Rue Saint-laurent 249 Li\u00c8ge Li\u00e8ge 4000",
    "addr:housenumber":"249",
    "addr:postcode":"4000",
    "addr:street":"Rue Saint-Laurent",
    "iso:country":"BE",
    "sg:address":"Rue Saint-laurent 249",
    "sg:city":"Li\u00c8ge",
    "sg:orig_category":"Installation \u00e9lectrique r\u00e9sidentielle",
    "sg:phone":"+32 4 254 17 47",
    "sg:postcode":"4000",
    "sg:province":"Li\u00e8ge",
    "wof:name":"I.d. Ka",
    "wof:placetype":"venue"
},
  "geometry": {"coordinates":[5.5521659851,50.6356620789],"type":"Point"}
}