{
  "type": "Feature",
  "properties": {
    "addr:full":"Rue Saint-martin 47 Tournai Hainaut 7500",
    "addr:housenumber":"47",
    "addr:postcode":"7500",
    "addr:street":"Rue Saint-Martin",
    "iso:country":"BE",
    "sg:address":"Rue Saint-martin 47",
    "sg:city":"Tournai",
    "sg:classifiers":[
        {
            "category":"Sports & Exercise",
            "subcategory":"Swimming Pool",
            "type":"Entertainment"
        }
    ],
    "sg:phone":"+32 69 21 15 83",
    "sg:postcode":"7500",
    "sg:province":"Hainaut",
    "sg:tags":[
        "organisaties",
        "verenigingen",
        "diverse",
        "diver",
        "amusement"
    ],
    "wof:name":"Cr\u00c9a Th\u00c9\u00c2tre",
    "wof:placetype":"venue"
},
  "geometry": {"coordinates":[3.38667202,50.6046066284],"type":"Point"}
}