{
  "type": "Feature",
  "properties": {
    "iso:country":"BE",
    "sg:address":"Charleslei 27",
    "sg:city":"Brasschaat",
    "sg:orig_category":"Messageries",
    "sg:phone":"+32 3 651 67 55",
    "sg:postcode":"2930",
    "sg:province":"Antwerpen",
    "wof:name":"Maria Loos",
    "wof:placetype":"venue"
},
  "geometry": {"coordinates":[4.4721679688,51.2919006348],"type":"Point"}
}