{
  "type": "Feature",
  "properties": {
    "iso:country":"BE",
    "sg:address":"Avenue Du Progr\u00c8s 9",
    "sg:city":"Seraing",
    "sg:orig_category":"Experts-comptables",
    "sg:phone":"+32 4 337 82 71",
    "sg:postcode":"4100",
    "sg:province":"Li\u00e8ge",
    "wof:name":"Andre Lefebvre",
    "wof:placetype":"venue"
},
  "geometry": {"coordinates":[5.5059738159,50.5828704834],"type":"Point"}
}