{
  "type": "Feature",
  "properties": {
    "addr:full":"Avenue De La Rousseli\u00e8re 69 Li\u00e8ge 1 (jupille-sur-meuse) Li\u00e8ge 4020",
    "addr:housenumber":"69;1",
    "addr:postcode":"4020",
    "addr:street":"Avenue De La Rousselie\u0300Re;Jupille-Sur-Meuse Lie\u0300Ge",
    "iso:country":"BE",
    "sg:address":"Avenue De La Rousseli\u00e8re 69",
    "sg:city":"Li\u00e8ge 1 (jupille-sur-meuse)",
    "sg:classifiers":[
        {
            "category":"Health Services",
            "subcategory":"Doctor",
            "type":"Services"
        }
    ],
    "sg:phone":"+32 4 365 98 61",
    "sg:postcode":"4020",
    "sg:province":"Li\u00e8ge",
    "sg:tags":[
        "medicinephysicians",
        "surgeon"
    ],
    "wof:name":"Lema\u00eetre J",
    "wof:placetype":"venue"
},
  "geometry": {"coordinates":[5.6398329735,50.6275100708],"type":"Point"}
}