{
  "type": "Feature",
  "properties": {
    "addr:full":"Rue Des Ursulines 1b48 Namur Namur 5000",
    "addr:housenumber":"1b48",
    "addr:postcode":"5000",
    "addr:street":"Rue Des Ursulines",
    "iso:country":"BE",
    "sg:address":"Rue Des Ursulines 1b48",
    "sg:city":"Namur",
    "sg:orig_category":"Alternatieve geneeskunde",
    "sg:phone":"+32 81 22 44 27",
    "sg:postcode":"5000",
    "sg:province":"Namur",
    "wof:name":"Ost\u00c9opathe Bracke Dirk",
    "wof:placetype":"venue"
},
  "geometry": {"coordinates":[4.8615989685,50.4681282043],"type":"Point"}
}