{
  "type": "Feature",
  "properties": {
    "iso:country":"BE",
    "sg:address":"Rue De La Cambre 2",
    "sg:city":"Sint-lambrechts-woluwe/woluwe-saint-lambert",
    "sg:orig_category":"G\u00e9om\u00e8tres. Architectes",
    "sg:phone":"+32 2 771 16 76",
    "sg:postcode":"1200",
    "sg:province":"Bruxelles-Capitale",
    "wof:name":"Raymond Verhelst",
    "wof:placetype":"venue"
},
  "geometry": {"coordinates":[4.431453228,50.8393859863],"type":"Point"}
}