{
  "type": "Feature",
  "properties": {
    "iso:country":"BE",
    "sg:address":"Adolf Buylstraat 38",
    "sg:city":"Oostende",
    "sg:orig_category":"Chaussures",
    "sg:phone":"+32 59 70 90 38",
    "sg:postcode":"8400",
    "sg:province":"West-Vlaanderen",
    "wof:name":"Luigi",
    "wof:placetype":"venue"
},
  "geometry": {"coordinates":[2.9155390263,51.2312698364],"type":"Point"}
}