{
  "type": "Feature",
  "properties": {
    "iso:country":"BE",
    "sg:address":"Heirbaan 2",
    "sg:city":"Galmaarden",
    "sg:orig_category":"Gespecialiseerde residenti\u00eble bouw",
    "sg:phone":"+32 54 33 09 33",
    "sg:postcode":"1570",
    "sg:province":"Vlaams-Brabant",
    "wof:name":"Luc De Borre",
    "wof:placetype":"venue"
},
  "geometry": {"coordinates":[3.9594259262,50.7783355713],"type":"Point"}
}