{
  "type": "Feature",
  "properties": {
    "iso:country":"BE",
    "sg:address":"Avenue Reine Astrid 11",
    "sg:city":"Waremme",
    "sg:orig_category":"Banques and organismes de cr\u00e9dit",
    "sg:phone":"+32 19 32 65 65",
    "sg:postcode":"4300",
    "sg:province":"Li\u00e8ge",
    "wof:name":"Citibank",
    "wof:placetype":"venue"
},
  "geometry": {"coordinates":[5.2518610954,50.6953010559],"type":"Point"}
}