{
  "type": "Feature",
  "properties": {
    "iso:country":"BE",
    "sg:address":"Rue Comte D'ursel 24",
    "sg:city":"Durbuy",
    "sg:orig_category":"Slagers",
    "sg:phone":"+32 86 21 16 28",
    "sg:postcode":"6940",
    "sg:province":"Luxembourg",
    "wof:name":"Boucherie Bodson",
    "wof:placetype":"venue"
},
  "geometry": {"coordinates":[5.454146862,50.3516311646],"type":"Point"}
}