{
  "type": "Feature",
  "properties": {
    "addr:full":"Sint-michielstraat 90 Tielt West-Vlaanderen 8700",
    "addr:housenumber":"90",
    "addr:postcode":"8700",
    "addr:street":"Sint-Michielstraat",
    "iso:country":"BE",
    "sg:address":"Sint-michielstraat 90",
    "sg:city":"Tielt",
    "sg:orig_category":"Decoratieve kunst and kunstbenodigdheden",
    "sg:phone":"+32 51 40 45 85",
    "sg:postcode":"8700",
    "sg:province":"West-Vlaanderen",
    "wof:name":"Classic-arts",
    "wof:placetype":"venue"
},
  "geometry": {"coordinates":[3.3217248917,50.9976615906],"type":"Point"}
}