{
  "type": "Feature",
  "properties": {
    "iso:country":"BE",
    "sg:address":"Grendelbaan 20",
    "sg:city":"Diepenbeek",
    "sg:classifiers":[
        {
            "category":"Autos & Motor Vehicles",
            "subcategory":"Automobile Sales",
            "type":"Retail Goods"
        }
    ],
    "sg:phone":"+32 11 74 06 51",
    "sg:postcode":"3590",
    "sg:province":"Limburg",
    "sg:tags":[
        "car",
        "used",
        "-"
    ],
    "wof:name":"Auto's Ronny",
    "wof:placetype":"venue"
},
  "geometry": {"coordinates":[5.4317150116,50.9051818848],"type":"Point"}
}