{
  "type": "Feature",
  "properties": {
    "addr:full":"Frans Van Ryhovelaan 91 Gent Oost-Vlaanderen 9000",
    "addr:housenumber":"91",
    "addr:postcode":"9000",
    "addr:street":"Frans Van Ryhovelaan;Oost-Vlaanderen",
    "iso:country":"BE",
    "sg:address":"Frans Van Ryhovelaan 91",
    "sg:city":"Gent",
    "sg:orig_category":"Begrafeniswezen",
    "sg:phone":"+32 9 226 46 00",
    "sg:postcode":"9000",
    "sg:province":"Oost-Vlaanderen",
    "wof:name":"Dekens",
    "wof:placetype":"venue"
},
  "geometry": {"coordinates":[3.7074389458,51.069065094],"type":"Point"}
}