{
  "type": "Feature",
  "properties": {
    "iso:country":"BE",
    "sg:address":"Grote Negenbundersstraat 33b",
    "sg:city":"Hasselt (kuringen)",
    "sg:classifiers":[
        {
            "category":"Health Services",
            "subcategory":"Health Practitioner",
            "type":"Services"
        }
    ],
    "sg:phone":"+32 11 85 12 39",
    "sg:postcode":"3511",
    "sg:province":"Limburg",
    "sg:tags":[
        "physiotherapist"
    ],
    "wof:name":"Carmans Natalie",
    "wof:placetype":"venue"
},
  "geometry": {"coordinates":[5.3034238815,50.9432487488],"type":"Point"}
}