{
  "type": "Feature",
  "properties": {
    "addr:full":"Rue Basse 13 Vise Li\u00e8ge 4600",
    "addr:housenumber":"13",
    "addr:postcode":"4600",
    "addr:street":"Rue Basse",
    "iso:country":"BE",
    "sg:address":"Rue Basse 13",
    "sg:city":"Vise",
    "sg:orig_category":"Verplichte sociale verzekeringen",
    "sg:phone":"+32 4 379 70 80",
    "sg:postcode":"4600",
    "sg:province":"Li\u00e8ge",
    "wof:name":"Entente Mutuel. Vis\u00c9toise",
    "wof:placetype":"venue"
},
  "geometry": {"coordinates":[5.6940908432,50.7345542908],"type":"Point"}
}