{
  "type": "Feature",
  "properties": {
    "iso:country":"BE",
    "sg:address":"Rue De La Ceinture 2",
    "sg:city":"Herstal",
    "sg:orig_category":"Non-Classified Establishments",
    "sg:phone":"+32 4 264 51 24",
    "sg:postcode":"4040",
    "sg:province":"Li\u00e8ge",
    "wof:name":"Ets Joiris Christian Sprl",
    "wof:placetype":"venue"
},
  "geometry": {"coordinates":[5.6381998062,50.6924285889],"type":"Point"}
}