{
  "type": "Feature",
  "properties": {
    "addr:full":"Zuidzandstraat 45 Brugge West-Vlaanderen 8000",
    "addr:housenumber":"45",
    "addr:postcode":"8000",
    "addr:street":"Zuidzandstraat",
    "iso:country":"BE",
    "sg:address":"Zuidzandstraat 45",
    "sg:city":"Brugge",
    "sg:classifiers":[
        {
            "category":"Restaurant",
            "type":"Food & Drink"
        }
    ],
    "sg:phone":"+32 50 33 21 54",
    "sg:postcode":"8000",
    "sg:province":"West-Vlaanderen",
    "wof:name":"China",
    "wof:placetype":"venue"
},
  "geometry": {"coordinates":[3.2183380127,51.2049751282],"type":"Point"}
}