{
  "type": "Feature",
  "properties": {
    "addr:full":"Wolfshaegen 113 Huldenberg (neerijse) Vlaams-Brabant 3040",
    "addr:housenumber":"113",
    "addr:postcode":"3040",
    "addr:street":"Wolfshaegen",
    "iso:country":"BE",
    "sg:address":"Wolfshaegen 113",
    "sg:city":"Huldenberg (neerijse)",
    "sg:classifiers":[
        {
            "category":"Shopping",
            "subcategory":"Computers & Home Electronics",
            "type":"Retail Goods"
        }
    ],
    "sg:phone":"+32 16 47 75 09",
    "sg:postcode":"3040",
    "sg:province":"Vlaams-Brabant",
    "sg:tags":[
        "-",
        "television",
        "radio"
    ],
    "wof:name":"De Keyser",
    "wof:placetype":"venue"
},
  "geometry": {"coordinates":[4.6242818832,50.7878036499],"type":"Point"}
}