{
  "type": "Feature",
  "properties": {
    "addr:full":"Nutstraat 1 Wellen Limburg 3830",
    "addr:housenumber":"1",
    "addr:postcode":"3830",
    "addr:street":"Nutstraat",
    "iso:country":"BE",
    "sg:address":"Nutstraat 1",
    "sg:city":"Wellen",
    "sg:orig_category":"Epiceries",
    "sg:phone":"+32 12 74 17 33",
    "sg:postcode":"3830",
    "sg:province":"Limburg",
    "wof:name":"Louis Delhaize",
    "wof:placetype":"venue"
},
  "geometry": {"coordinates":[5.3394460678,50.835773468],"type":"Point"}
}