{
  "type": "Feature",
  "properties": {
    "iso:country":"BE",
    "sg:address":"Chauss\u00e9e De Devant La Ville 1",
    "sg:city":"P\u00e9ruwelz (callenelle)",
    "sg:classifiers":[
        {
            "category":"Home & Garden",
            "subcategory":"Building Materials",
            "type":"Retail Goods"
        }
    ],
    "sg:phone":"+32 69 77 10 60",
    "sg:postcode":"7604",
    "sg:province":"Hainaut",
    "sg:tags":[
        "article",
        "-",
        "do-it-yourself"
    ],
    "wof:name":"Multi-stock (bm-stock)",
    "wof:placetype":"venue"
},
  "geometry": {"coordinates":[3.5216109753,50.530834198],"type":"Point"}
}