{
  "type": "Feature",
  "properties": {
    "addr:full":"Stijn Streuvelslaan 8 Lichtervelde West-Vlaanderen 8810",
    "addr:housenumber":"8",
    "addr:postcode":"8810",
    "addr:street":"Stijn Streuvelslaan",
    "iso:country":"BE",
    "sg:address":"Stijn Streuvelslaan 8",
    "sg:city":"Lichtervelde",
    "sg:orig_category":"Voertuigen",
    "sg:phone":"+32 51 72 44 68",
    "sg:postcode":"8810",
    "sg:province":"West-Vlaanderen",
    "wof:name":"Auto's Cool",
    "wof:placetype":"venue"
},
  "geometry": {"coordinates":[3.132997036,51.035243988],"type":"Point"}
}