{
  "type": "Feature",
  "properties": {
    "addr:full":"Bd Anspach 194-198 Bruxelles Bruxelles-Capitale 1000",
    "addr:postcode":"194-198;1000",
    "addr:street":"Bd Anspach",
    "iso:country":"BE",
    "sg:address":"Bd Anspach 194-198",
    "sg:city":"Bruxelles",
    "sg:classifiers":[
        {
            "category":"Banks & Credit Unions",
            "subcategory":"Financial Services",
            "type":"Services"
        }
    ],
    "sg:phone":"+32 2 502 58 56",
    "sg:postcode":"1000",
    "sg:province":"Bruxelles-Capitale",
    "sg:tags":[
        "banking",
        "insurance",
        "institution",
        "finance"
    ],
    "wof:name":"Banque Commerciale Du Maroc",
    "wof:placetype":"venue"
},
  "geometry": {"coordinates":[4.3469052315,50.8454437256],"type":"Point"}
}