{
  "type": "Feature",
  "properties": {
    "addr:full":"Heistraat 4ba Hoogstraten Antwerpen 2322",
    "addr:housenumber":"4ba",
    "addr:postcode":"2322",
    "addr:street":"Heistraat",
    "iso:country":"BE",
    "sg:address":"Heistraat 4ba",
    "sg:city":"Hoogstraten",
    "sg:orig_category":"Rundveehouders",
    "sg:phone":"+32 3 314 82 58",
    "sg:postcode":"2322",
    "sg:province":"Antwerpen",
    "wof:name":"Jozef Stoffels",
    "wof:placetype":"venue"
},
  "geometry": {"coordinates":[4.7485260963,51.4145698547],"type":"Point"}
}