{
  "type": "Feature",
  "properties": {
    "addr:full":"Rue De La Maladrie 5 Neufch\u00e2teau (longlier) Luxembourg 6840",
    "addr:housenumber":"5",
    "addr:postcode":"6840",
    "addr:street":"Rue De La Maladrie",
    "iso:country":"BE",
    "sg:address":"Rue De La Maladrie 5",
    "sg:city":"Neufch\u00e2teau (longlier)",
    "sg:classifiers":[
        {
            "category":"Shopping",
            "subcategory":"Pets & Pet Supplies",
            "type":"Retail Goods"
        }
    ],
    "sg:phone":"+32 61 27 87 59",
    "sg:postcode":"6840",
    "sg:province":"Luxembourg",
    "sg:tags":[
        "shop",
        "-"
    ],
    "wof:name":"Mme Bayet Nelly (jardin Des Animaux)",
    "wof:placetype":"venue"
},
  "geometry": {"coordinates":[5.4346451759,49.8411598206],"type":"Point"}
}