{
  "type": "Feature",
  "properties": {
    "iso:country":"BE",
    "sg:address":"Garenstraat 31",
    "sg:city":"Heusden-zolder (heusden)",
    "sg:classifiers":[
        {
            "category":"Shopping",
            "subcategory":"Baby Store",
            "type":"Retail Goods"
        }
    ],
    "sg:phone":"+32 11 42 16 26",
    "sg:postcode":"3550",
    "sg:province":"Limburg",
    "sg:tags":[
        "midwife"
    ],
    "wof:name":"Corthouts G",
    "wof:placetype":"venue"
},
  "geometry": {"coordinates":[5.27231884,51.0366020203],"type":"Point"}
}