{
  "type": "Feature",
  "properties": {
    "addr:full":"Steenweg Naar Halle 47 Sint-genesius-rode Vlaams-Brabant 1640",
    "addr:housenumber":"47",
    "addr:postcode":"1640",
    "addr:street":"Steenweg Naar Halle",
    "iso:country":"BE",
    "sg:address":"Steenweg Naar Halle 47",
    "sg:city":"Sint-genesius-rode",
    "sg:orig_category":"Loodgieterij, verwarming and sanitaire installaties",
    "sg:phone":"+32 2 381 21 23",
    "sg:postcode":"1640",
    "sg:province":"Vlaams-Brabant",
    "wof:name":"Junkers",
    "wof:placetype":"venue"
},
  "geometry": {"coordinates":[4.3441591263,50.7446899414],"type":"Point"}
}