{
  "type": "Feature",
  "properties": {
    "iso:country":"BE",
    "sg:address":"Houwerstraat 2",
    "sg:city":"Antwerpen",
    "sg:orig_category":"Kapsalons",
    "sg:phone":"+32 3 233 80 45",
    "sg:postcode":"2060",
    "sg:province":"Antwerpen",
    "wof:name":"Kapstudio",
    "wof:placetype":"venue"
},
  "geometry": {"coordinates":[4.4155778885,51.2252540588],"type":"Point"}
}