{
  "type": "Feature",
  "properties": {
    "addr:full":"Nijverheidsstraat 78 Wommelgem Antwerpen 2160",
    "addr:housenumber":"78",
    "addr:postcode":"2160",
    "addr:street":"Nijverheidsstraat",
    "iso:country":"BE",
    "sg:address":"Nijverheidsstraat 78",
    "sg:city":"Wommelgem",
    "sg:classifiers":[
        {
            "category":"Manufacturing",
            "subcategory":"Rubber & Plastics",
            "type":"Manufacturing & Wholesale Goods"
        }
    ],
    "sg:phone":"+32 3 353 83 86",
    "sg:postcode":"2160",
    "sg:province":"Antwerpen",
    "sg:tags":[
        "machine",
        "appliance",
        "welding"
    ],
    "wof:name":"Alimex Nv",
    "wof:placetype":"venue"
},
  "geometry": {"coordinates":[4.5086212158,51.2113227844],"type":"Point"}
}