{
  "type": "Feature",
  "properties": {
    "iso:country":"BE",
    "sg:address":"Gebr. Persoonsstraat 16",
    "sg:city":"Haacht",
    "sg:orig_category":"Enregistrements sonores",
    "sg:phone":"+32 16 60 79 36",
    "sg:postcode":"3150",
    "sg:province":"Vlaams-Brabant",
    "wof:name":"Studio A.m.p.",
    "wof:placetype":"venue"
},
  "geometry": {"coordinates":[4.6380047798,50.9768714905],"type":"Point"}
}