{
  "type": "Feature",
  "properties": {
    "addr:full":"Oude Markt 32 Overpelt Limburg 3583",
    "addr:housenumber":"32",
    "addr:postcode":"3583",
    "addr:street":"Oude Markt",
    "iso:country":"BE",
    "sg:address":"Oude Markt 32",
    "sg:city":"Overpelt",
    "sg:classifiers":[
        {
            "category":"Banks & Credit Unions",
            "subcategory":"Bank",
            "type":"Services"
        }
    ],
    "sg:phone":"+32 11 64 30 91",
    "sg:postcode":"3583",
    "sg:province":"Limburg",
    "wof:name":"Banque Bruxelles Lambert Sa",
    "wof:placetype":"venue"
},
  "geometry": {"coordinates":[5.4233980179,51.2120285034],"type":"Point"}
}