{
  "type": "Feature",
  "properties": {
    "addr:full":"Rue Delcour 5 Onhaye Namur 5520",
    "addr:housenumber":"5",
    "addr:postcode":"5520",
    "addr:street":"Rue Delcour",
    "iso:country":"BE",
    "sg:address":"Rue Delcour 5",
    "sg:city":"Onhaye",
    "sg:classifiers":[
        {
            "category":"Banks & Credit Unions",
            "subcategory":"Investment Brokerage",
            "type":"Services"
        }
    ],
    "sg:phone":"+32 82 68 83 34",
    "sg:postcode":"5520",
    "sg:province":"Namur",
    "sg:tags":[
        "pension"
    ],
    "wof:name":"Ferme Des Oiseaux",
    "wof:placetype":"venue"
},
  "geometry": {"coordinates":[4.7643098831,50.2405471802],"type":"Point"}
}