{
  "type": "Feature",
  "properties": {
    "addr:full":"Route De Go\u00c9 92 Limbourg Li\u00e8ge 4830",
    "addr:housenumber":"92",
    "addr:postcode":"4830",
    "addr:street":"Route De Goe\u0301",
    "iso:country":"BE",
    "sg:address":"Route De Go\u00c9 92",
    "sg:city":"Limbourg",
    "sg:orig_category":"Sportclubs",
    "sg:phone":"+32 87 76 51 73",
    "sg:postcode":"4830",
    "sg:province":"Li\u00e8ge",
    "wof:name":"Royal Dolhain V\u00c9lo",
    "wof:placetype":"venue"
},
  "geometry": {"coordinates":[5.949203968,50.6090812683],"type":"Point"}
}