{
  "type": "Feature",
  "properties": {
    "addr:full":"Avenue Fostier 13 Ronse/renaix Oost-Vlaanderen 9600",
    "addr:housenumber":"13",
    "addr:postcode":"9600",
    "addr:street":"Avenue Fostier",
    "iso:country":"BE",
    "sg:address":"Avenue Fostier 13",
    "sg:city":"Ronse/renaix",
    "sg:classifiers":[
        {
            "category":"Cinema",
            "subcategory":"Movie Rental",
            "type":"Entertainment"
        }
    ],
    "sg:phone":"+32 55 21 27 22",
    "sg:postcode":"9600",
    "sg:province":"Oost-Vlaanderen",
    "sg:tags":[
        "de",
        "cassette",
        "location",
        "vid\u00e9o",
        "audio"
    ],
    "wof:name":"Video 99",
    "wof:placetype":"venue"
},
  "geometry": {"coordinates":[3.5992999077,50.7470397949],"type":"Point"}
}