{
  "type": "Feature",
  "properties": {
    "iso:country":"BE",
    "sg:address":"Zandstraat 19",
    "sg:city":"Wijnegem",
    "sg:orig_category":"Administration d'immeubles",
    "sg:phone":"+32 3 354 22 54",
    "sg:postcode":"2110",
    "sg:province":"Antwerpen",
    "wof:name":"Dirk Uytdenhouwen",
    "wof:placetype":"venue"
},
  "geometry": {"coordinates":[4.5141777992,51.2296524048],"type":"Point"}
}