{
  "type": "Feature",
  "properties": {
    "addr:full":"Lippenslaan 72b41 Knokke-heist West-Vlaanderen 8300",
    "addr:housenumber":"72b41",
    "addr:postcode":"8300",
    "addr:street":"Lippenslaan",
    "iso:country":"BE",
    "sg:address":"Lippenslaan 72b41",
    "sg:city":"Knokke-heist",
    "sg:orig_category":"Rev\u00eatements pour sols and murs. Peinture",
    "sg:phone":"+32 50 60 68 23",
    "sg:postcode":"8300",
    "sg:province":"West-Vlaanderen",
    "wof:name":"Deco Trade",
    "wof:placetype":"venue"
},
  "geometry": {"coordinates":[3.2882208824,51.3440704346],"type":"Point"}
}