{
  "type": "Feature",
  "properties": {
    "addr:full":"Quai Du Condroz 15 Li\u00e8ge 1 (li\u00e8ge 2) Li\u00e8ge 4020",
    "addr:housenumber":"15;1;2",
    "addr:postcode":"4020",
    "addr:street":"Quai Du Condroz",
    "iso:country":"BE",
    "sg:address":"Quai Du Condroz 15",
    "sg:city":"Li\u00e8ge 1 (li\u00e8ge 2)",
    "sg:classifiers":[
        {
            "category":"Education",
            "subcategory":"School",
            "type":"Public Place"
        }
    ],
    "sg:phone":"+32 4 341 11 28",
    "sg:postcode":"4020",
    "sg:province":"Li\u00e8ge",
    "sg:tags":[
        "secondary"
    ],
    "wof:name":"Ecole De L'industrie & De L'automobile",
    "wof:placetype":"venue"
},
  "geometry": {"coordinates":[5.5840730667,50.6202735901],"type":"Point"}
}