{
  "type": "Feature",
  "properties": {
    "iso:country":"BE",
    "sg:address":"Westmallebaan 22",
    "sg:city":"Zoersel",
    "sg:orig_category":"Goederenvervoer over de weg",
    "sg:phone":"+32 3 312 20 97",
    "sg:postcode":"2980",
    "sg:province":"Antwerpen",
    "wof:name":"Dandor",
    "wof:placetype":"venue"
},
  "geometry": {"coordinates":[4.7123532295,51.2722816467],"type":"Point"}
}