{
  "type": "Feature",
  "properties": {
    "addr:full":"Beselarestraat 6 Wervik (geluwe) West-Vlaanderen 8940",
    "addr:housenumber":"6",
    "addr:postcode":"8940",
    "addr:street":"Beselarestraat",
    "iso:country":"BE",
    "sg:address":"Beselarestraat 6",
    "sg:city":"Wervik (geluwe)",
    "sg:classifiers":[
        {
            "category":"Insurance",
            "subcategory":"Insurance Agent",
            "type":"Services"
        }
    ],
    "sg:phone":"+32 56 51 31 86",
    "sg:postcode":"8940",
    "sg:province":"West-Vlaanderen",
    "sg:tags":[
        "broker"
    ],
    "wof:name":"Ghekiere Nv",
    "wof:placetype":"venue"
},
  "geometry": {"coordinates":[3.0764489174,50.8108901978],"type":"Point"}
}