{
  "type": "Feature",
  "properties": {
    "addr:full":"Rue Eug\u00e8ne Delvaux 43 Gembloux-sur-orneau (gembloux) Namur 5030",
    "addr:housenumber":"43",
    "addr:postcode":"5030",
    "addr:street":"Rue Euge\u0300Ne Delvaux;Namur",
    "iso:country":"BE",
    "sg:address":"Rue Eug\u00e8ne Delvaux 43",
    "sg:city":"Gembloux-sur-orneau (gembloux)",
    "sg:classifiers":[
        {
            "category":"Parking",
            "subcategory":"Bicycle",
            "type":"Transportation"
        }
    ],
    "sg:phone":"+32 81 61 46 18",
    "sg:postcode":"5030",
    "sg:province":"Namur",
    "sg:tags":[
        "chiropodist"
    ],
    "wof:name":"De Maesschalck G",
    "wof:placetype":"venue"
},
  "geometry": {"coordinates":[4.6743822098,50.5919303894],"type":"Point"}
}