{
  "type": "Feature",
  "properties": {
    "addr:full":"Doelstraat 39 Hoegaarden Vlaams-Brabant 3320",
    "addr:housenumber":"39",
    "addr:postcode":"3320",
    "addr:street":"Doelstraat",
    "iso:country":"BE",
    "sg:address":"Doelstraat 39",
    "sg:city":"Hoegaarden",
    "sg:classifiers":[
        {
            "category":"Cafe",
            "type":"Food & Drink"
        }
    ],
    "sg:phone":"+32 16 76 56 79",
    "sg:postcode":"3320",
    "sg:province":"Vlaams-Brabant",
    "sg:tags":[
        "caf\u00e9s"
    ],
    "wof:name":"De Kluis",
    "wof:placetype":"venue"
},
  "geometry": {"coordinates":[4.8913660049,50.7742271423],"type":"Point"}
}