{
  "type": "Feature",
  "properties": {
    "addr:full":"Chemin De La Loge 58 Soignies (horrues) Hainaut 7060",
    "addr:housenumber":"58",
    "addr:postcode":"7060",
    "addr:street":"Chemin De La Loge",
    "iso:country":"BE",
    "sg:address":"Chemin De La Loge 58",
    "sg:city":"Soignies (horrues)",
    "sg:classifiers":[
        {
            "category":"Building & Trades",
            "subcategory":"Construction",
            "type":"Services"
        }
    ],
    "sg:phone":"+32 67 45 81 49",
    "sg:postcode":"7060",
    "sg:province":"Hainaut",
    "sg:tags":[
        "carpenter"
    ],
    "wof:name":"Lebrun Freres (menuiserie) Sprl",
    "wof:placetype":"venue"
},
  "geometry": {"coordinates":[4.0724000931,50.5779037476],"type":"Point"}
}