{
  "type": "Feature",
  "properties": {
    "addr:full":"Maastrichtlaan 4 Vilvoorde Vlaams-Brabant 1800",
    "addr:housenumber":"4",
    "addr:postcode":"1800",
    "addr:street":"Maastrichtlaan",
    "iso:country":"BE",
    "sg:address":"Maastrichtlaan 4",
    "sg:city":"Vilvoorde",
    "sg:classifiers":[
        {
            "category":"Shopping",
            "subcategory":"Computers & Home Electronics",
            "type":"Retail Goods"
        }
    ],
    "sg:phone":"+32 2 253 94 76",
    "sg:postcode":"1800",
    "sg:province":"Vlaams-Brabant",
    "sg:tags":[
        "-",
        "processing",
        "data",
        "cleaning"
    ],
    "wof:name":"Handyclean Sa",
    "wof:placetype":"venue"
},
  "geometry": {"coordinates":[4.3986949921,50.9164161682],"type":"Point"}
}