{
  "type": "Feature",
  "properties": {
    "addr:full":"Rue A. Mazy 16 Namur Namur 5000",
    "addr:housenumber":"16",
    "addr:postcode":"5000",
    "addr:street":"Rue A. Mazy",
    "iso:country":"BE",
    "sg:address":"Rue A. Mazy 16",
    "sg:city":"Namur",
    "sg:orig_category":"Herstelling horloges and juwelen Juwelen and horloges",
    "sg:phone":"+32 81 73 40 76",
    "sg:postcode":"5000",
    "sg:province":"Namur",
    "wof:name":"Ghenne Bijouterie",
    "wof:placetype":"venue"
},
  "geometry": {"coordinates":[4.8617630005,50.4657287598],"type":"Point"}
}