{
  "type": "Feature",
  "properties": {
    "iso:country":"BE",
    "sg:address":"Avenue Winston Churchill 57",
    "sg:city":"Morlanwelz",
    "sg:orig_category":"Dakwerken Loodgieterij, verwarming and sanitaire installaties",
    "sg:phone":"+32 64 45 80 50",
    "sg:postcode":"7140",
    "sg:province":"Hainaut",
    "wof:name":"Joly Toitures",
    "wof:placetype":"venue"
},
  "geometry": {"coordinates":[4.229886055,50.4575309753],"type":"Point"}
}