{
  "type": "Feature",
  "properties": {
    "iso:country":"BE",
    "sg:address":"Dokter Willemsstraat 92",
    "sg:city":"Hasselt",
    "sg:classifiers":[
        {
            "category":"Social Services",
            "subcategory":"Child Care",
            "type":"Services"
        }
    ],
    "sg:phone":"+32 11 23 94 09",
    "sg:postcode":"3500",
    "sg:province":"Limburg",
    "sg:tags":[
        "baby",
        "nursery",
        "day",
        "sitting"
    ],
    "wof:name":"Buitenschoolse Opvang Hasselt",
    "wof:placetype":"venue"
},
  "geometry": {"coordinates":[5.3343000412,50.9310417175],"type":"Point"}
}