{
  "type": "Feature",
  "properties": {
    "addr:full":"Grand'place 22 P\u00e9ruwelz Hainaut 7600",
    "addr:housenumber":"22",
    "addr:postcode":"7600",
    "addr:street":"Grand'Place",
    "iso:country":"BE",
    "sg:address":"Grand'place 22",
    "sg:city":"P\u00e9ruwelz",
    "sg:classifiers":[
        {
            "category":"Bars & Pubs",
            "type":"Food & Drink"
        }
    ],
    "sg:phone":"+32 69 77 66 07",
    "sg:postcode":"7600",
    "sg:province":"Hainaut",
    "wof:name":"Commerce (le)",
    "wof:placetype":"venue"
},
  "geometry": {"coordinates":[3.5923399925,50.5101509094],"type":"Point"}
}