{
  "type": "Feature",
  "properties": {
    "iso:country":"BE",
    "sg:address":"Avenue De Fr\u00e9 215",
    "sg:city":"Bruxelles (uccle)",
    "sg:classifiers":[
        {
            "category":"Personal",
            "subcategory":"Beauty Salon",
            "type":"Services"
        }
    ],
    "sg:phone":"+32 2 374 06 49",
    "sg:postcode":"1180",
    "sg:province":"Bruxelles-Capitale",
    "sg:tags":[
        "lady",
        "-",
        "hairdressing"
    ],
    "wof:name":"Marin J M",
    "wof:placetype":"venue"
},
  "geometry": {"coordinates":[4.3585100174,50.8040504456],"type":"Point"}
}