{
  "type": "Feature",
  "properties": {
    "addr:full":"Quai Saint-l\u00c9onard 36bd Li\u00c8ge Li\u00e8ge 4000",
    "addr:housenumber":"36bd",
    "addr:postcode":"4000",
    "addr:street":"Quai Saint-Le\u0301Onard",
    "iso:country":"BE",
    "sg:address":"Quai Saint-l\u00c9onard 36bd",
    "sg:city":"Li\u00c8ge",
    "sg:orig_category":"Autoverhuur Verzekeringsmakelaars and experts",
    "sg:phone":"+32 4 227 92 33",
    "sg:postcode":"4000",
    "sg:province":"Li\u00e8ge",
    "wof:name":"M.f. Diffusion",
    "wof:placetype":"venue"
},
  "geometry": {"coordinates":[5.5910701752,50.6479072571],"type":"Point"}
}