{
  "type": "Feature",
  "properties": {
    "addr:full":"Ooigemstraat 37 Oostrozebeke West-Vlaanderen 8780",
    "addr:housenumber":"37",
    "addr:postcode":"8780",
    "addr:street":"Ooigemstraat",
    "iso:country":"BE",
    "sg:address":"Ooigemstraat 37",
    "sg:city":"Oostrozebeke",
    "sg:orig_category":"Non-Classified Establishments",
    "sg:phone":"+32 56 66 63 07",
    "sg:postcode":"8780",
    "sg:province":"West-Vlaanderen",
    "wof:name":"Gekiere G",
    "wof:placetype":"venue"
},
  "geometry": {"coordinates":[3.3245038986,50.9101982117],"type":"Point"}
}