{
  "type": "Feature",
  "properties": {
    "addr:full":"Square Ambiorix 32 Bruxelles Bruxelles-Capitale 1000",
    "addr:housenumber":"32",
    "addr:postcode":"1000",
    "addr:street":"Square Ambiorix",
    "iso:country":"BE",
    "sg:address":"Square Ambiorix 32",
    "sg:city":"Bruxelles",
    "sg:classifiers":[
        {
            "category":"Health Services",
            "subcategory":"Dentist",
            "type":"Services"
        }
    ],
    "sg:phone":"+32 2 230 88 86",
    "sg:postcode":"1000",
    "sg:province":"Bruxelles-Capitale",
    "wof:name":"Soukias Yves",
    "wof:placetype":"venue"
},
  "geometry": {"coordinates":[4.3835000992,50.8461494446],"type":"Point"}
}