{
  "type": "Feature",
  "properties": {
    "addr:full":"Diesterstraat 56 Tessenderlo Limburg 3980",
    "addr:housenumber":"56",
    "addr:postcode":"3980",
    "addr:street":"Diesterstraat",
    "iso:country":"BE",
    "sg:address":"Diesterstraat 56",
    "sg:city":"Tessenderlo",
    "sg:classifiers":[
        {
            "category":"Professional",
            "type":"Services"
        }
    ],
    "sg:phone":"+32 13 67 62 11",
    "sg:postcode":"3980",
    "sg:province":"Limburg",
    "sg:tags":[
        "equipment",
        "installation",
        "restaurants"
    ],
    "wof:name":"Europa 2000 Nv",
    "wof:placetype":"venue"
},
  "geometry": {"coordinates":[5.0883188248,51.0642929077],"type":"Point"}
}