{
  "type": "Feature",
  "properties": {
    "iso:country":"BE",
    "sg:address":"Rue Berckmans 64",
    "sg:city":"Bruxelles (saint-gilles)",
    "sg:classifiers":[
        {
            "category":"Real Estate",
            "subcategory":"Real Estate Services",
            "type":"Services"
        }
    ],
    "sg:phone":"+32 2 539 01 05",
    "sg:postcode":"1060",
    "sg:province":"Bruxelles-Capitale",
    "wof:name":"Sopico",
    "wof:placetype":"venue"
},
  "geometry": {"coordinates":[4.3540520668,50.8316764832],"type":"Point"}
}