{
  "type": "Feature",
  "properties": {
    "addr:full":"Leuvensesteenweg 29 Mechelen Antwerpen 2800",
    "addr:housenumber":"29",
    "addr:postcode":"2800",
    "addr:street":"Leuvensesteenweg",
    "iso:country":"BE",
    "sg:address":"Leuvensesteenweg 29",
    "sg:city":"Mechelen",
    "sg:classifiers":[
        {
            "category":"Cafe",
            "type":"Food & Drink"
        }
    ],
    "sg:phone":"+32 15 41 20 43",
    "sg:postcode":"2800",
    "sg:province":"Antwerpen",
    "sg:tags":[
        "caf\u00e9s"
    ],
    "wof:name":"City's Caf\u00c9",
    "wof:placetype":"venue"
},
  "geometry": {"coordinates":[4.4911341667,51.0207862854],"type":"Point"}
}