{
  "type": "Feature",
  "properties": {
    "iso:country":"BE",
    "sg:address":"Rue Paul Pastur 297",
    "sg:city":"Quaregnon",
    "sg:orig_category":"Activit\u00e9s diverses d'imprimerie",
    "sg:phone":"+32 65 77 93 25",
    "sg:postcode":"7390",
    "sg:province":"Hainaut",
    "wof:name":"Bureau Clovis",
    "wof:placetype":"venue"
},
  "geometry": {"coordinates":[3.8575260639,50.4484176636],"type":"Point"}
}