{
  "type": "Feature",
  "properties": {
    "iso:country":"BE",
    "sg:address":"Rue Bas-comogne 25",
    "sg:city":"Jemeppe-sur-sambre",
    "sg:orig_category":"V\u00e9t\u00e9rinaires",
    "sg:phone":"+32 71 78 72 18",
    "sg:postcode":"5190",
    "sg:province":"Namur",
    "wof:name":"Gerard Lorand",
    "wof:placetype":"venue"
},
  "geometry": {"coordinates":[4.6556692123,50.4667167664],"type":"Point"}
}