{
  "type": "Feature",
  "properties": {
    "addr:full":"Kazerneweg 3 Moorslede West-Vlaanderen 8890",
    "addr:housenumber":"3",
    "addr:postcode":"8890",
    "addr:street":"Kazerneweg",
    "iso:country":"BE",
    "sg:address":"Kazerneweg 3",
    "sg:city":"Moorslede",
    "sg:classifiers":[
        {
            "category":"Insurance",
            "subcategory":"Insurance Agent",
            "type":"Services"
        }
    ],
    "sg:phone":"+32 51 77 06 56",
    "sg:postcode":"8890",
    "sg:province":"West-Vlaanderen",
    "sg:tags":[
        "verzekeringsmakelaars",
        "expert"
    ],
    "wof:name":"Philiep Stragier",
    "wof:placetype":"venue"
},
  "geometry": {"coordinates":[3.0835719109,50.9087028503],"type":"Point"}
}