{
  "type": "Feature",
  "properties": {
    "addr:full":"Rue Vin\u00e2ve 162 Li\u00e8ge 1 (grivegn\u00e9e) Li\u00e8ge 4030",
    "addr:housenumber":"162;1",
    "addr:postcode":"4030",
    "addr:street":"Rue Vina\u0302Ve",
    "iso:country":"BE",
    "sg:address":"Rue Vin\u00e2ve 162",
    "sg:city":"Li\u00e8ge 1 (grivegn\u00e9e)",
    "sg:classifiers":[
        {
            "category":"Building & Trades",
            "subcategory":"Pest Control",
            "type":"Services"
        }
    ],
    "sg:phone":"+32 4 367 60 88",
    "sg:postcode":"4030",
    "sg:province":"Li\u00e8ge",
    "sg:tags":[
        "painting",
        "contractor"
    ],
    "wof:name":"Gc Peint Sprl",
    "wof:placetype":"venue"
},
  "geometry": {"coordinates":[5.6089468002,50.6164360046],"type":"Point"}
}