{
  "type": "Feature",
  "properties": {
    "addr:full":"Vrijwilligerslei 7 Brasschaat Antwerpen 2930",
    "addr:housenumber":"7",
    "addr:postcode":"2930",
    "addr:street":"Vrijwilligerslei",
    "iso:country":"BE",
    "sg:address":"Vrijwilligerslei 7",
    "sg:city":"Brasschaat",
    "sg:orig_category":"Motorfietsen",
    "sg:phone":"+32 3 665 10 03",
    "sg:postcode":"2930",
    "sg:province":"Antwerpen",
    "wof:name":"Blommaert",
    "wof:placetype":"venue"
},
  "geometry": {"coordinates":[4.4451370239,51.2919692993],"type":"Point"}
}