{
  "type": "Feature",
  "properties": {
    "addr:full":"Jean D'ardennestraat 54 Elsene/ixelles Bruxelles-Capitale 1050",
    "addr:housenumber":"54",
    "addr:postcode":"1050",
    "addr:street":"Jean D'Ardennestraat",
    "iso:country":"BE",
    "sg:address":"Jean D'ardennestraat 54",
    "sg:city":"Elsene/ixelles",
    "sg:orig_category":"Dierenartsen",
    "sg:phone":"+32 2 511 96 26",
    "sg:postcode":"1050",
    "sg:province":"Bruxelles-Capitale",
    "wof:name":"Christiane Loeman",
    "wof:placetype":"venue"
},
  "geometry": {"coordinates":[4.3619232178,50.831615448],"type":"Point"}
}