{
  "type": "Feature",
  "properties": {
    "iso:country":"BE",
    "sg:address":"Dijkstraat 24",
    "sg:city":"Lokeren",
    "sg:orig_category":"Lampes and appareils \u00e9lectriques Fab. Travaux d\u00b4installation divers. Agences de publicit\u00e9",
    "sg:phone":"+32 9 349 63 13",
    "sg:postcode":"9160",
    "sg:province":"Oost-Vlaanderen",
    "wof:name":"Publi Cochemtra",
    "wof:placetype":"venue"
},
  "geometry": {"coordinates":[4.0248851776,51.0928230286],"type":"Point"}
}