{
  "type": "Feature",
  "properties": {
    "addr:full":"Rue Du Hableau 13 Rochefort Namur 5580",
    "addr:housenumber":"13",
    "addr:postcode":"5580",
    "addr:street":"Rue Du Hableau",
    "iso:country":"BE",
    "sg:address":"Rue Du Hableau 13",
    "sg:city":"Rochefort",
    "sg:orig_category":"Landmeters",
    "sg:phone":"+32 84 21 14 04",
    "sg:postcode":"5580",
    "sg:province":"Namur",
    "wof:name":"Jean-luc Nandance",
    "wof:placetype":"venue"
},
  "geometry": {"coordinates":[5.2253460884,50.1579017639],"type":"Point"}
}