{
  "type": "Feature",
  "properties": {
    "iso:country":"BE",
    "sg:address":"Place Albert I 14",
    "sg:city":"La Bruy\u00e8re (saint-denis)",
    "sg:classifiers":[
        {
            "category":"Food & Beverages",
            "subcategory":"Groceries & Convenience Stores",
            "type":"Retail Goods"
        }
    ],
    "sg:phone":"+32 81 56 83 92",
    "sg:postcode":"5081",
    "sg:province":"Namur",
    "sg:tags":[
        "grocer"
    ],
    "wof:name":"Challes F",
    "wof:placetype":"venue"
},
  "geometry": {"coordinates":[4.7831149101,50.5349159241],"type":"Point"}
}