{
  "type": "Feature",
  "properties": {
    "addr:full":"Stationsstraat 178 B11 Herzele Oost-Vlaanderen 9550",
    "addr:housenumber":"178 b11",
    "addr:postcode":"9550",
    "addr:street":"Stationsstraat;Oost-Vlaanderen",
    "iso:country":"BE",
    "sg:address":"Stationsstraat 178 B11",
    "sg:city":"Herzele",
    "sg:orig_category":"Assistances juridiques. Conseillers fiscaux",
    "sg:phone":"+32 53 62 95 38",
    "sg:postcode":"9550",
    "sg:province":"Oost-Vlaanderen",
    "wof:name":"Bureau D'hoker & Co",
    "wof:placetype":"venue"
},
  "geometry": {"coordinates":[3.8927550316,50.8844261169],"type":"Point"}
}