{
  "type": "Feature",
  "properties": {
    "addr:full":"Rue De Jausse 88 Namur (naninne) Namur 5100",
    "addr:housenumber":"88",
    "addr:postcode":"5100",
    "addr:street":"Rue De Jausse",
    "iso:country":"BE",
    "sg:address":"Rue De Jausse 88",
    "sg:city":"Namur (naninne)",
    "sg:classifiers":[
        {
            "category":"Health Services",
            "subcategory":"Health Practitioner",
            "type":"Services"
        }
    ],
    "sg:phone":"+32 81 40 07 28",
    "sg:postcode":"5100",
    "sg:province":"Namur",
    "sg:tags":[
        "physiotherapist"
    ],
    "wof:name":"Servais Agnes",
    "wof:placetype":"venue"
},
  "geometry": {"coordinates":[4.8713750839,50.4566345215],"type":"Point"}
}