{
  "type": "Feature",
  "properties": {
    "addr:full":"Dries 2 Brugge (assebroek) West-Vlaanderen 8310",
    "addr:housenumber":"2",
    "addr:postcode":"8310",
    "addr:street":"Dries",
    "iso:country":"BE",
    "sg:address":"Dries 2",
    "sg:city":"Brugge (assebroek)",
    "sg:classifiers":[
        {
            "category":"Bars & Pubs",
            "type":"Food & Drink"
        }
    ],
    "sg:phone":"+32 50 37 36 37",
    "sg:postcode":"8310",
    "sg:province":"West-Vlaanderen",
    "wof:name":"Cafetaria Daverloo",
    "wof:placetype":"venue"
},
  "geometry": {"coordinates":[3.2493131161,51.1928443909],"type":"Point"}
}