{
  "type": "Feature",
  "properties": {
    "addr:full":"Chemin Des Dames 15 Hannut Li\u00e8ge 4280",
    "addr:housenumber":"15",
    "addr:postcode":"4280",
    "addr:street":"Chemin Des Dames",
    "iso:country":"BE",
    "sg:address":"Chemin Des Dames 15",
    "sg:city":"Hannut",
    "sg:orig_category":"Notaires",
    "sg:phone":"+32 19 51 13 06",
    "sg:postcode":"4280",
    "sg:province":"Li\u00e8ge",
    "wof:name":"Charles Wauters",
    "wof:placetype":"venue"
},
  "geometry": {"coordinates":[5.0777101517,50.6663589478],"type":"Point"}
}