{
  "type": "Feature",
  "properties": {
    "addr:full":"Korspelheidestraat 34 Beringen Limburg 3582",
    "addr:housenumber":"34",
    "addr:postcode":"3582",
    "addr:street":"Korspelheidestraat",
    "iso:country":"BE",
    "sg:address":"Korspelheidestraat 34",
    "sg:city":"Beringen",
    "sg:orig_category":"Installation \u00e9lectrique r\u00e9sidentielle",
    "sg:phone":"+32 11 43 18 31",
    "sg:postcode":"3582",
    "sg:province":"Limburg",
    "wof:name":"Tadeusz Wachowiak",
    "wof:placetype":"venue"
},
  "geometry": {"coordinates":[5.2708749771,51.0595359802],"type":"Point"}
}