{
  "type": "Feature",
  "properties": {
    "addr:full":"Wervikstraat 108 Menen West-Vlaanderen 8930",
    "addr:housenumber":"108",
    "addr:postcode":"8930",
    "addr:street":"Wervikstraat",
    "iso:country":"BE",
    "sg:address":"Wervikstraat 108",
    "sg:city":"Menen",
    "sg:orig_category":"Etalage- and showroomontwerpers MEUBELONTWERP AND -INSTALLATIE",
    "sg:phone":"+32 56 53 07 98",
    "sg:postcode":"8930",
    "sg:province":"West-Vlaanderen",
    "wof:name":"Cuisines Boffi-k 20",
    "wof:placetype":"venue"
},
  "geometry": {"coordinates":[3.1109540462,50.7955741882],"type":"Point"}
}