{
  "type": "Feature",
  "properties": {
    "iso:country":"BE",
    "sg:address":"Lombardenvest 74",
    "sg:city":"Antwerpen",
    "sg:classifiers":[
        {
            "category":"Shopping",
            "subcategory":"Gifts & Souvenirs",
            "type":"Retail Goods"
        }
    ],
    "sg:phone":"+32 3 233 32 33",
    "sg:postcode":"2000",
    "sg:province":"Antwerpen",
    "sg:tags":[
        "-"
    ],
    "wof:name":"Vizio - Deco Bvba",
    "wof:placetype":"venue"
},
  "geometry": {"coordinates":[4.4036707878,51.2172698975],"type":"Point"}
}