{
  "type": "Feature",
  "properties": {
    "addr:full":"Hoekje 7 Waarschoot Oost-Vlaanderen 9950",
    "addr:housenumber":"7",
    "addr:postcode":"9950",
    "addr:street":"Hoekje",
    "iso:country":"BE",
    "sg:address":"Hoekje 7",
    "sg:city":"Waarschoot",
    "sg:classifiers":[
        {
            "category":"Home & Garden",
            "subcategory":"Hardware",
            "type":"Retail Goods"
        }
    ],
    "sg:phone":"+32 9 377 55 05",
    "sg:postcode":"9950",
    "sg:province":"Oost-Vlaanderen",
    "sg:tags":[
        "machine",
        "horticultural"
    ],
    "wof:name":"Vdw Constructie Bvba",
    "wof:placetype":"venue"
},
  "geometry": {"coordinates":[3.6157059669,51.1545906067],"type":"Point"}
}