{
  "type": "Feature",
  "properties": {
    "iso:country":"BE",
    "sg:address":"Gasthuisheide 31",
    "sg:city":"Geel",
    "sg:classifiers":[
        {
            "category":"Professional",
            "subcategory":"Management & Consulting",
            "type":"Services"
        }
    ],
    "sg:phone":"+32 14 59 00 89",
    "sg:postcode":"2440",
    "sg:province":"Antwerpen",
    "sg:tags":[
        "consultant"
    ],
    "wof:name":"G-tec",
    "wof:placetype":"venue"
},
  "geometry": {"coordinates":[5.0134501457,51.1291275024],"type":"Point"}
}