{
  "type": "Feature",
  "properties": {
    "iso:country":"BE",
    "sg:address":"Hoogstraat 45",
    "sg:city":"Haaltert",
    "sg:orig_category":"Parfumeries",
    "sg:phone":"+32 53 83 26 36",
    "sg:postcode":"9450",
    "sg:province":"Oost-Vlaanderen",
    "wof:name":"Parfumerie Paris",
    "wof:placetype":"venue"
},
  "geometry": {"coordinates":[4.0040488243,50.8996810913],"type":"Point"}
}