{
  "type": "Feature",
  "properties": {
    "iso:country":"BE",
    "sg:address":"Oude-heidestraat 18",
    "sg:city":"Hasselt",
    "sg:classifiers":[
        {
            "category":"Cafe",
            "type":"Food & Drink"
        }
    ],
    "sg:phone":"+32 11 24 15 61",
    "sg:postcode":"3511",
    "sg:province":"Limburg",
    "sg:tags":[
        "caf\u00e9s"
    ],
    "wof:name":"Joseph Gilissen",
    "wof:placetype":"venue"
},
  "geometry": {"coordinates":[5.3319602013,50.9490585327],"type":"Point"}
}