{
  "type": "Feature",
  "properties": {
    "iso:country":"BE",
    "sg:address":"Pierstraat 333",
    "sg:city":"Rumst (reet)",
    "sg:classifiers":[
        {
            "category":"Personal",
            "subcategory":"Nail Salon",
            "type":"Services"
        }
    ],
    "sg:phone":"+32 3 888 93 99",
    "sg:postcode":"2840",
    "sg:province":"Antwerpen",
    "sg:tags":[
        "pedicure"
    ],
    "wof:name":"Boden I",
    "wof:placetype":"venue"
},
  "geometry": {"coordinates":[4.3668308258,51.1099662781],"type":"Point"}
}