{
  "type": "Feature",
  "properties": {
    "addr:full":"Hemelrijk 45 Ninove Oost-Vlaanderen 9402",
    "addr:housenumber":"45",
    "addr:postcode":"9402",
    "addr:street":"Hemelrijk",
    "iso:country":"BE",
    "sg:address":"Hemelrijk 45",
    "sg:city":"Ninove",
    "sg:orig_category":"S\u00e9curit\u00e9 sociale",
    "sg:phone":"+32 54 33 77 65",
    "sg:postcode":"9402",
    "sg:province":"Oost-Vlaanderen",
    "wof:name":"Bond Moyson",
    "wof:placetype":"venue"
},
  "geometry": {"coordinates":[4.0395750999,50.8249015808],"type":"Point"}
}