{
  "type": "Feature",
  "properties": {
    "iso:country":"BE",
    "sg:address":"Kapellelaan 52",
    "sg:city":"Leuven (wilsele)",
    "sg:orig_category":"Newspapers, magazines, periodicals - Distribution",
    "sg:phone":"+32 16 29 03 88",
    "sg:postcode":"3012",
    "sg:province":"Vlaams-Brabant",
    "wof:name":"Nico (dagbladhandel)",
    "wof:placetype":"venue"
},
  "geometry": {"coordinates":[4.6985559464,50.8954124451],"type":"Point"}
}