{
  "type": "Feature",
  "properties": {
    "iso:country":"BE",
    "sg:address":"Rue De La Province 41",
    "sg:city":"Seraing",
    "sg:orig_category":"M\u00e9decins and sp\u00e9cialistes",
    "sg:phone":"+32 4 337 04 28",
    "sg:postcode":"4100",
    "sg:province":"Li\u00e8ge",
    "wof:name":"L\u00c9on Guyon",
    "wof:placetype":"venue"
},
  "geometry": {"coordinates":[5.5063328743,50.612701416],"type":"Point"}
}