{
  "type": "Feature",
  "properties": {
    "addr:full":"President Kennedypark 16 Kortrijk West-Vlaanderen 8500",
    "addr:housenumber":"16",
    "addr:postcode":"8500",
    "addr:street":"President Kennedypark",
    "iso:country":"BE",
    "sg:address":"President Kennedypark 16",
    "sg:city":"Kortrijk",
    "sg:classifiers":[
        {
            "category":"Retail",
            "subcategory":"Auto Rental",
            "type":"Services"
        }
    ],
    "sg:phone":"+32 56 20 23 96",
    "sg:postcode":"8500",
    "sg:province":"West-Vlaanderen",
    "sg:tags":[
        "automobile",
        "-",
        "car",
        "self-drive"
    ],
    "wof:name":"Konvert Service",
    "wof:placetype":"venue"
},
  "geometry": {"coordinates":[3.272521019,50.8000564575],"type":"Point"}
}