{
  "type": "Feature",
  "properties": {
    "addr:full":"Vleyminckshoek 40 Sint-niklaas Oost-Vlaanderen 9100",
    "addr:housenumber":"40",
    "addr:postcode":"9100",
    "addr:street":"Vleyminckshoek",
    "iso:country":"BE",
    "sg:address":"Vleyminckshoek 40",
    "sg:city":"Sint-niklaas",
    "sg:classifiers":[
        {
            "category":"Manufacturing",
            "subcategory":"Metals",
            "type":"Manufacturing & Wholesale Goods"
        }
    ],
    "sg:phone":"+32 3 778 11 61",
    "sg:postcode":"9100",
    "sg:province":"Oost-Vlaanderen",
    "sg:tags":[
        "-",
        "machine",
        "equipment",
        "engineering",
        "machinery",
        "mechanical"
    ],
    "wof:name":"Constructiebedrijf De Mol Nv",
    "wof:placetype":"venue"
},
  "geometry": {"coordinates":[4.1161899567,51.1752548218],"type":"Point"}
}