{
  "type": "Feature",
  "properties": {
    "addr:full":"Turnhoutsebaan 5 Dessel Antwerpen 2480",
    "addr:housenumber":"5",
    "addr:postcode":"2480",
    "addr:street":"Turnhoutsebaan",
    "iso:country":"BE",
    "sg:address":"Turnhoutsebaan 5",
    "sg:city":"Dessel",
    "sg:orig_category":"Dranken Gh",
    "sg:phone":"+32 14 37 70 18",
    "sg:postcode":"2480",
    "sg:province":"Antwerpen",
    "wof:name":"Fa. Verwimp",
    "wof:placetype":"venue"
},
  "geometry": {"coordinates":[5.1126098633,51.2408599854],"type":"Point"}
}