{
  "type": "Feature",
  "properties": {
    "addr:full":"Steenweg Op Merchtem 66 Opwijk Vlaams-Brabant 1745",
    "addr:housenumber":"66",
    "addr:postcode":"1745",
    "addr:street":"Steenweg Op Merchtem",
    "iso:country":"BE",
    "sg:address":"Steenweg Op Merchtem 66",
    "sg:city":"Opwijk",
    "sg:classifiers":[
        {
            "category":"Professional",
            "subcategory":"Management & Consulting",
            "type":"Services"
        }
    ],
    "sg:phone":"+32 52 35 04 76",
    "sg:postcode":"1745",
    "sg:province":"Vlaams-Brabant",
    "sg:tags":[
        "consultant",
        "agency",
        "advertising"
    ],
    "wof:name":"Jmj Company Nv",
    "wof:placetype":"venue"
},
  "geometry": {"coordinates":[4.1974787712,50.9661560059],"type":"Point"}
}