{
  "type": "Feature",
  "properties": {
    "addr:full":"Begonialaan 11 De Pinte Oost-Vlaanderen 9840",
    "addr:housenumber":"11",
    "addr:postcode":"9840",
    "addr:street":"Begonialaan",
    "iso:country":"BE",
    "sg:address":"Begonialaan 11",
    "sg:city":"De Pinte",
    "sg:classifiers":[
        {
            "category":"Health Services",
            "subcategory":"Doctor",
            "type":"Services"
        }
    ],
    "sg:phone":"+32 9 282 00 29",
    "sg:postcode":"9840",
    "sg:province":"Oost-Vlaanderen",
    "sg:tags":[
        "medicinephysicians",
        "surgeon"
    ],
    "wof:name":"Cnudde C",
    "wof:placetype":"venue"
},
  "geometry": {"coordinates":[3.6557068825,50.9955635071],"type":"Point"}
}