{
  "type": "Feature",
  "properties": {
    "addr:full":"Kempenstraat 19 Mol Antwerpen 2400",
    "addr:housenumber":"19",
    "addr:postcode":"2400",
    "addr:street":"Kempenstraat",
    "iso:country":"BE",
    "sg:address":"Kempenstraat 19",
    "sg:city":"Mol",
    "sg:orig_category":"M\u00e9decines alternatives",
    "sg:phone":"+32 14 32 06 30",
    "sg:postcode":"2400",
    "sg:province":"Antwerpen",
    "wof:name":"Ils Deckx",
    "wof:placetype":"venue"
},
  "geometry": {"coordinates":[5.133043766,51.1998558044],"type":"Point"}
}