{
  "type": "Feature",
  "properties": {
    "iso:country":"BE",
    "sg:address":"Nijverheidsstraat 7",
    "sg:city":"Brecht",
    "sg:orig_category":"Installatie van houten of kunststof schrijnwerk Installatie van metalen schrijnwerk",
    "sg:phone":"+32 3 663 16 34",
    "sg:postcode":"2960",
    "sg:province":"Antwerpen",
    "wof:name":"M.d.c.",
    "wof:placetype":"venue"
},
  "geometry": {"coordinates":[4.5535011292,51.2989120483],"type":"Point"}
}