{
  "type": "Feature",
  "properties": {
    "addr:full":"Industrieweg 13a Merelbeke Oost-Vlaanderen 9820",
    "addr:housenumber":"13a",
    "addr:postcode":"9820",
    "addr:street":"Industrieweg",
    "iso:country":"BE",
    "sg:address":"Industrieweg 13a",
    "sg:city":"Merelbeke",
    "sg:orig_category":"Traitement and rev\u00eatement des m\u00e9taux",
    "sg:phone":"+32 9 252 55 14",
    "sg:postcode":"9820",
    "sg:province":"Oost-Vlaanderen",
    "wof:name":"Mecaron",
    "wof:placetype":"venue"
},
  "geometry": {"coordinates":[3.7677819729,50.9882965088],"type":"Point"}
}