{
  "type": "Feature",
  "properties": {
    "addr:full":"Rue D' Ensival 4 Verviers Li\u00e8ge 4800",
    "addr:housenumber":"4",
    "addr:postcode":"4800",
    "addr:street":"Rue D ' Ensival",
    "iso:country":"BE",
    "sg:address":"Rue D' Ensival 4",
    "sg:city":"Verviers",
    "sg:orig_category":"Tabac",
    "sg:phone":"+32 87 34 08 24",
    "sg:postcode":"4800",
    "sg:province":"Li\u00e8ge",
    "wof:name":"Tabac-sun",
    "wof:placetype":"venue"
},
  "geometry": {"coordinates":[5.8551368713,50.5888442993],"type":"Point"}
}