{
  "type": "Feature",
  "properties": {
    "iso:country":"BE",
    "sg:address":"Gentse Steenweg 328",
    "sg:city":"Lokeren",
    "sg:orig_category":"Non-Classified Establishments",
    "sg:phone":"+32 9 355 56 35",
    "sg:postcode":"9160",
    "sg:province":"Oost-Vlaanderen",
    "wof:name":"Imschoot Voeders Bvba",
    "wof:placetype":"venue"
},
  "geometry": {"coordinates":[3.9199581146,51.1107940674],"type":"Point"}
}