{
  "type": "Feature",
  "properties": {
    "iso:country":"BE",
    "sg:address":"Avenue De La Lib\u00c9ration 23",
    "sg:city":"Sambreville",
    "sg:orig_category":"Journaux. Articles de camping and de sport. Librairies",
    "sg:phone":"+32 71 77 46 04",
    "sg:postcode":"5060",
    "sg:province":"Namur",
    "wof:name":"Central Sports",
    "wof:placetype":"venue"
},
  "geometry": {"coordinates":[4.6285200119,50.4448738098],"type":"Point"}
}