{
  "type": "Feature",
  "properties": {
    "addr:full":"Kasteelstraat 49 Herzele Oost-Vlaanderen 9550",
    "addr:housenumber":"49",
    "addr:postcode":"9550",
    "addr:street":"Kasteelstraat;Oost-Vlaanderen",
    "iso:country":"BE",
    "sg:address":"Kasteelstraat 49",
    "sg:city":"Herzele",
    "sg:orig_category":"Woningbouw",
    "sg:phone":"+32 53 62 38 28",
    "sg:postcode":"9550",
    "sg:province":"Oost-Vlaanderen",
    "wof:name":"Gaston De Prez",
    "wof:placetype":"venue"
},
  "geometry": {"coordinates":[3.9099700451,50.8708763123],"type":"Point"}
}