{
  "type": "Feature",
  "properties": {
    "iso:country":"BE",
    "sg:address":"Rue Hansez 12",
    "sg:city":"Olne",
    "sg:classifiers":[
        {
            "category":"Health Services",
            "subcategory":"Nursing And Care Facility",
            "type":"Services"
        }
    ],
    "sg:phone":"+32 87 26 74 28",
    "sg:postcode":"4877",
    "sg:province":"Li\u00e8ge",
    "sg:tags":[
        "home"
    ],
    "wof:name":"A Campo M",
    "wof:placetype":"venue"
},
  "geometry": {"coordinates":[5.7291579247,50.5886764526],"type":"Point"}
}