{
  "type": "Feature",
  "properties": {
    "iso:country":"BE",
    "sg:address":"Tiensestraat 41d",
    "sg:city":"Zoutleeuw",
    "sg:orig_category":"Sportclubs",
    "sg:phone":"+32 11 22 21 80",
    "sg:postcode":"3440",
    "sg:province":"Vlaams-Brabant",
    "wof:name":"Immer Vooruit",
    "wof:placetype":"venue"
},
  "geometry": {"coordinates":[5.0985341072,50.8358268738],"type":"Point"}
}