{
  "type": "Feature",
  "properties": {
    "addr:full":"Avenue H. Liebrecht 76 Jette Bruxelles-Capitale 1090",
    "addr:housenumber":"76",
    "addr:postcode":"1090",
    "addr:street":"Avenue H. Liebrecht",
    "iso:country":"BE",
    "sg:address":"Avenue H. Liebrecht 76",
    "sg:city":"Jette",
    "sg:orig_category":"Etablissements Erotiques",
    "sg:phone":"+32 2 479 34 96",
    "sg:postcode":"1090",
    "sg:province":"Bruxelles-Capitale",
    "wof:name":"Institue H.d.",
    "wof:placetype":"venue"
},
  "geometry": {"coordinates":[4.3178339005,50.8906898499],"type":"Point"}
}