{
  "type": "Feature",
  "properties": {
    "addr:full":"Poelstraat 230 Merelbeke (bottelare) Oost-Vlaanderen 9820",
    "addr:housenumber":"230",
    "addr:postcode":"9820",
    "addr:street":"Poelstraat",
    "iso:country":"BE",
    "sg:address":"Poelstraat 230",
    "sg:city":"Merelbeke (bottelare)",
    "sg:classifiers":[
        {
            "category":"Home & Garden",
            "subcategory":"Home Furnishings",
            "type":"Retail Goods"
        }
    ],
    "sg:phone":"+32 9 362 55 20",
    "sg:postcode":"9820",
    "sg:province":"Oost-Vlaanderen",
    "sg:tags":[
        "curtain",
        "-",
        "fixture"
    ],
    "wof:name":"Bastiaansen Bvba",
    "wof:placetype":"venue"
},
  "geometry": {"coordinates":[3.7619829178,50.9676208496],"type":"Point"}
}