{
  "type": "Feature",
  "properties": {
    "iso:country":"BE",
    "sg:address":"Filips Van De Elzaslaan 88",
    "sg:city":"Kortrijk",
    "sg:orig_category":"Schoonheidssalons",
    "sg:phone":"+32 56 22 70 84",
    "sg:postcode":"8500",
    "sg:province":"West-Vlaanderen",
    "wof:name":"Marleen Vandemoortele",
    "wof:placetype":"venue"
},
  "geometry": {"coordinates":[3.2767601013,50.8217163086],"type":"Point"}
}