{
  "type": "Feature",
  "properties": {
    "iso:country":"BE",
    "sg:address":"Karrestraat 238-a",
    "sg:city":"Herent",
    "sg:classifiers":[
        {
            "category":"Building & Trades",
            "subcategory":"Landscaping Services",
            "type":"Services"
        }
    ],
    "sg:phone":"+32 16 20 62 34",
    "sg:postcode":"3020",
    "sg:province":"Vlaams-Brabant",
    "sg:tags":[
        "gardening",
        "garden",
        "maintenance"
    ],
    "wof:name":"Artoos",
    "wof:placetype":"venue"
},
  "geometry": {"coordinates":[4.6694779396,50.9242897034],"type":"Point"}
}