{
  "type": "Feature",
  "properties": {
    "addr:full":"Av Du Couronnement 129 Bruxelles Bruxelles-Capitale 1200",
    "addr:housenumber":"129",
    "addr:postcode":"1200",
    "addr:street":"Av Du Couronnement",
    "iso:country":"BE",
    "sg:address":"Av Du Couronnement 129",
    "sg:city":"Bruxelles",
    "sg:classifiers":[
        {
            "category":"Shopping",
            "subcategory":"Computers & Home Electronics",
            "type":"Retail Goods"
        }
    ],
    "sg:phone":"+32 2 255 82 10",
    "sg:postcode":"1200",
    "sg:province":"Bruxelles-Capitale",
    "sg:tags":[
        "equipment",
        "electrical",
        "component",
        "electric",
        "electronic"
    ],
    "wof:name":"Ets Charles Focquet & Cie Sa",
    "wof:placetype":"venue"
},
  "geometry": {"coordinates":[4.4115848541,50.8422241211],"type":"Point"}
}