{
  "type": "Feature",
  "properties": {
    "iso:country":"BE",
    "sg:address":"Rue De Wand 170b",
    "sg:city":"Brussel/bruxelles",
    "sg:orig_category":"Slagers",
    "sg:phone":"+32 2 268 73 73",
    "sg:postcode":"1020",
    "sg:province":"Bruxelles-Capitale",
    "wof:name":"Picobello",
    "wof:placetype":"venue"
},
  "geometry": {"coordinates":[4.3604049683,50.9010620117],"type":"Point"}
}