{
  "type": "Feature",
  "properties": {
    "iso:country":"BE",
    "sg:address":"Collegelaan 17",
    "sg:city":"Essen",
    "sg:orig_category":"Transports routiers de marchandises",
    "sg:phone":"+32 3 677 02 80",
    "sg:postcode":"2910",
    "sg:province":"Antwerpen",
    "wof:name":"Shanatrans",
    "wof:placetype":"venue"
},
  "geometry": {"coordinates":[4.4323320389,51.4320831299],"type":"Point"}
}