{
  "type": "Feature",
  "properties": {
    "addr:full":"Avenue Georges Marchal 21 Rixensart Brabant Wallon 1330",
    "addr:housenumber":"21",
    "addr:postcode":"1330",
    "addr:street":"Avenue Georges Marchal;Wallon",
    "iso:country":"BE",
    "sg:address":"Avenue Georges Marchal 21",
    "sg:city":"Rixensart",
    "sg:classifiers":[
        {
            "category":"Real Estate",
            "subcategory":"Real Estate Services",
            "type":"Services"
        }
    ],
    "sg:phone":"+32 2 652 11 22",
    "sg:postcode":"1330",
    "sg:province":"Brabant Wallon",
    "wof:name":"Perspectives Sprl",
    "wof:placetype":"venue"
},
  "geometry": {"coordinates":[4.5289697647,50.71352005],"type":"Point"}
}