{
  "type": "Feature",
  "properties": {
    "addr:full":"Rue Henri Elsen 11 Heinsch Luxembourg 6700",
    "addr:housenumber":"11",
    "addr:postcode":"6700",
    "addr:street":"Rue Henri Elsen",
    "iso:country":"BE",
    "sg:address":"Rue Henri Elsen 11",
    "sg:city":"Heinsch",
    "sg:classifiers":[
        {
            "category":"Home & Garden",
            "subcategory":"Kitchen Supply",
            "type":"Retail Goods"
        }
    ],
    "sg:phone":"+32 63 22 40 51",
    "sg:postcode":"6700",
    "sg:province":"Luxembourg",
    "sg:tags":[
        "fitted"
    ],
    "wof:name":"Blum Fr\u00e8res S.p.r.l.",
    "wof:placetype":"venue"
},
  "geometry": {"coordinates":[5.7476921082,49.697845459],"type":"Point"}
}