{
  "type": "Feature",
  "properties": {
    "iso:country":"BE",
    "sg:address":"Hellebeemden 10",
    "sg:city":"Hasselt",
    "sg:classifiers":[
        {
            "category":"Communications",
            "subcategory":"Film & Video Production",
            "type":"Services"
        }
    ],
    "sg:phone":"+32 11 28 68 28",
    "sg:postcode":"3500",
    "sg:province":"Limburg",
    "sg:tags":[
        "glass",
        "cutting",
        "mirror"
    ],
    "wof:name":"Lerobel-leroi Glas Nv",
    "wof:placetype":"venue"
},
  "geometry": {"coordinates":[5.3382678032,50.9120483398],"type":"Point"}
}