{
  "type": "Feature",
  "properties": {
    "addr:full":"Provinciaal Domein Beersel Vlaams-Brabant 1654",
    "addr:postcode":"1654",
    "addr:street":"Vlaams-Brabant",
    "iso:country":"BE",
    "sg:address":"Provinciaal Domein",
    "sg:city":"Beersel",
    "sg:classifiers":[
        {
            "category":"Restaurant",
            "type":"Food & Drink"
        }
    ],
    "sg:phone":"+32 2 380 04 87",
    "sg:postcode":"1654",
    "sg:province":"Vlaams-Brabant",
    "wof:name":"Taverne Boelekewis",
    "wof:placetype":"venue"
},
  "geometry": {"coordinates":[4.2793898582,50.7429847717],"type":"Point"}
}