{
  "type": "Feature",
  "properties": {
    "iso:country":"BE",
    "sg:address":"Groenkloosterstraat 18ba",
    "sg:city":"Bilzen",
    "sg:classifiers":[
        {
            "category":"Arena",
            "subcategory":"Sports Club",
            "type":"Entertainment"
        }
    ],
    "sg:phone":"+32 11 41 50 69",
    "sg:postcode":"3740",
    "sg:province":"Limburg",
    "sg:tags":[
        "terrain",
        "hors",
        "de",
        "installation",
        "sportifs"
    ],
    "wof:name":"Sk. Munsterbilzen",
    "wof:placetype":"venue"
},
  "geometry": {"coordinates":[5.5294260979,50.8883132935],"type":"Point"}
}