{
  "type": "Feature",
  "properties": {
    "iso:country":"BE",
    "sg:address":"Logen 129",
    "sg:city":"Geel",
    "sg:classifiers":[
        {
            "category":"Building & Trades",
            "subcategory":"Landscaping Services",
            "type":"Services"
        }
    ],
    "sg:phone":"+32 14 58 15 79",
    "sg:postcode":"2440",
    "sg:province":"Antwerpen",
    "sg:tags":[
        "-",
        "lopping",
        "work",
        "tree",
        "felling"
    ],
    "wof:name":"Bostra",
    "wof:placetype":"venue"
},
  "geometry": {"coordinates":[5.0068268776,51.1683120728],"type":"Point"}
}