{
  "type": "Feature",
  "properties": {
    "iso:country":"BE",
    "sg:address":"Steenhouwersvest 27",
    "sg:city":"Antwerpen",
    "sg:classifiers":[
        {
            "category":"Professional",
            "subcategory":"Advertising",
            "type":"Services"
        }
    ],
    "sg:phone":"+32 3 232 88 90",
    "sg:postcode":"2000",
    "sg:province":"Antwerpen",
    "sg:tags":[
        "item",
        "-",
        "business",
        "gift",
        "promotional"
    ],
    "wof:name":"De Cognatheek",
    "wof:placetype":"venue"
},
  "geometry": {"coordinates":[4.3983020782,51.2180175781],"type":"Point"}
}