{
  "type": "Feature",
  "properties": {
    "addr:full":"Wilsonstraat 21 Sint-katelijne-waver Antwerpen 2860",
    "addr:housenumber":"21",
    "addr:postcode":"2860",
    "addr:street":"Wilsonstraat",
    "iso:country":"BE",
    "sg:address":"Wilsonstraat 21",
    "sg:city":"Sint-katelijne-waver",
    "sg:orig_category":"Tuinen",
    "sg:phone":"+32 15 32 14 95",
    "sg:postcode":"2860",
    "sg:province":"Antwerpen",
    "wof:name":"Hobeco",
    "wof:placetype":"venue"
},
  "geometry": {"coordinates":[4.5338549614,51.0720748901],"type":"Point"}
}