{
  "type": "Feature",
  "properties": {
    "iso:country":"BE",
    "sg:address":"Corduwanierstraat 11",
    "sg:city":"Gent",
    "sg:orig_category":"Pensions de famille",
    "sg:phone":"+32 9 225 17 05",
    "sg:postcode":"9000",
    "sg:province":"Oost-Vlaanderen",
    "wof:name":"In's Inn",
    "wof:placetype":"venue"
},
  "geometry": {"coordinates":[3.7223870754,51.0576286316],"type":"Point"}
}