{
  "type": "Feature",
  "properties": {
    "addr:full":"Basilieklaan 104 Sint-agatha-berchem/berchem-sa Bruxelles-Capitale 1082",
    "addr:housenumber":"104",
    "addr:postcode":"1082",
    "addr:street":"Basilieklaan",
    "iso:country":"BE",
    "sg:address":"Basilieklaan 104",
    "sg:city":"Sint-agatha-berchem/berchem-sa",
    "sg:orig_category":"Banken and kredietinstellingen",
    "sg:phone":"+32 2 465 68 64",
    "sg:postcode":"1082",
    "sg:province":"Bruxelles-Capitale",
    "wof:name":"Fortis",
    "wof:placetype":"venue"
},
  "geometry": {"coordinates":[4.3056797981,50.8648414612],"type":"Point"}
}