{
  "type": "Feature",
  "properties": {
    "addr:full":"Duffelsesteenweg 119 Sint-katelijne-waver Antwerpen 2860",
    "addr:housenumber":"119",
    "addr:postcode":"2860",
    "addr:street":"Duffelsesteenweg",
    "iso:country":"BE",
    "sg:address":"Duffelsesteenweg 119",
    "sg:city":"Sint-katelijne-waver",
    "sg:orig_category":"Boekhouders",
    "sg:phone":"+32 15 31 00 34",
    "sg:postcode":"2860",
    "sg:province":"Antwerpen",
    "wof:name":"Filip De Backer",
    "wof:placetype":"venue"
},
  "geometry": {"coordinates":[4.5243229866,51.0817298889],"type":"Point"}
}