{
  "type": "Feature",
  "properties": {
    "addr:full":"Steenovenstraat 18 Waregem West-Vlaanderen 8790",
    "addr:housenumber":"18",
    "addr:postcode":"8790",
    "addr:street":"Steenovenstraat",
    "iso:country":"BE",
    "sg:address":"Steenovenstraat 18",
    "sg:city":"Waregem",
    "sg:orig_category":"Eleveurs de bovins",
    "sg:phone":"+32 56 60 76 86",
    "sg:postcode":"8790",
    "sg:province":"West-Vlaanderen",
    "wof:name":"Jacques Verschelde",
    "wof:placetype":"venue"
},
  "geometry": {"coordinates":[3.4484510422,50.8659439087],"type":"Point"}
}