{
  "type": "Feature",
  "properties": {
    "addr:full":"Avenue Des Combattants 38 Gembloux Namur 5030",
    "addr:housenumber":"38",
    "addr:postcode":"5030",
    "addr:street":"Avenue Des Combattants;Namur",
    "iso:country":"BE",
    "sg:address":"Avenue Des Combattants 38",
    "sg:city":"Gembloux",
    "sg:orig_category":"Avocats and conseillers juridiques",
    "sg:phone":"+32 81 61 18 15",
    "sg:postcode":"5030",
    "sg:province":"Namur",
    "wof:name":"V. Renier",
    "wof:placetype":"venue"
},
  "geometry": {"coordinates":[4.6998801231,50.5598297119],"type":"Point"}
}