{
  "type": "Feature",
  "properties": {
    "iso:country":"BE",
    "sg:address":"Grote Markt 31",
    "sg:city":"Diest",
    "sg:orig_category":"S\u00e9curit\u00e9 sociale",
    "sg:phone":"+32 13 33 41 61",
    "sg:postcode":"3290",
    "sg:province":"Vlaams-Brabant",
    "wof:name":"Socialist. Mutualiteit",
    "wof:placetype":"venue"
},
  "geometry": {"coordinates":[5.0505099297,50.9844055176],"type":"Point"}
}