{
  "type": "Feature",
  "properties": {
    "addr:full":"Nijverheidsstraat 3 Westerlo (oevel) Antwerpen 2260",
    "addr:housenumber":"3",
    "addr:postcode":"2260",
    "addr:street":"Nijverheidsstraat",
    "iso:country":"BE",
    "sg:address":"Nijverheidsstraat 3",
    "sg:city":"Westerlo (oevel)",
    "sg:classifiers":[
        {
            "category":"Banks & Credit Unions",
            "subcategory":"Investment Brokerage",
            "type":"Services"
        }
    ],
    "sg:phone":"+32 14 58 75 71",
    "sg:postcode":"2260",
    "sg:province":"Antwerpen",
    "sg:tags":[
        "remediation",
        "soil",
        "protection"
    ],
    "wof:name":"Jet Inter",
    "wof:placetype":"venue"
},
  "geometry": {"coordinates":[4.9291410446,51.135723114],"type":"Point"}
}