{
  "type": "Feature",
  "properties": {
    "iso:country":"BE",
    "sg:address":"Kortrijkstraat",
    "sg:city":"Wevelgem (groot)",
    "sg:orig_category":"V\u00eatements pour b\u00e9b\u00e9s and enfants. V\u00eatements pour Dames. V\u00eatements pour Hommes",
    "sg:phone":"+32 56 42 53 63",
    "sg:postcode":"8560",
    "sg:province":"West-Vlaanderen",
    "wof:name":"E5 Mode",
    "wof:placetype":"venue"
},
  "geometry": {"coordinates":[3.2070300579,50.815864563],"type":"Point"}
}