{
  "type": "Feature",
  "properties": {
    "addr:full":"Dendermondsesteenweg 142 Gent Oost-Vlaanderen 9000",
    "addr:housenumber":"142",
    "addr:postcode":"9000",
    "addr:street":"Dendermondsesteenweg;Oost-Vlaanderen",
    "iso:country":"BE",
    "sg:address":"Dendermondsesteenweg 142",
    "sg:city":"Gent",
    "sg:orig_category":"M\u00e9decins and sp\u00e9cialistes",
    "sg:phone":"+32 9 228 41 32",
    "sg:postcode":"9000",
    "sg:province":"Oost-Vlaanderen",
    "wof:name":"Koenraad Verhofstadt",
    "wof:placetype":"venue"
},
  "geometry": {"coordinates":[3.7436978817,51.0535469055],"type":"Point"}
}