{
  "type": "Feature",
  "properties": {
    "iso:country":"BE",
    "sg:address":"Rue Du Moulin 64ba",
    "sg:city":"Philippeville",
    "sg:classifiers":[
        {
            "category":"Arena",
            "subcategory":"Sports Club",
            "type":"Entertainment"
        }
    ],
    "sg:phone":"+32 71 66 66 63",
    "sg:postcode":"5600",
    "sg:province":"Namur",
    "sg:tags":[
        "terrain",
        "hors",
        "de",
        "installation",
        "sportifs"
    ],
    "wof:name":"Etoile Sportive",
    "wof:placetype":"venue"
},
  "geometry": {"coordinates":[4.536962986,50.1921424866],"type":"Point"}
}