{
  "type": "Feature",
  "properties": {
    "iso:country":"BE",
    "sg:address":"Antoine Dansaertstraat 150",
    "sg:city":"Brussel/bruxelles",
    "sg:orig_category":"Telecommunicatiesystemen",
    "sg:phone":"+32 2 503 32 54",
    "sg:postcode":"1000",
    "sg:province":"Bruxelles-Capitale",
    "wof:name":"Nasir International Shop",
    "wof:placetype":"venue"
},
  "geometry": {"coordinates":[4.3428311348,50.8523826599],"type":"Point"}
}