{
  "type": "Feature",
  "properties": {
    "addr:full":"Chauss\u00c9e D'enghien 248 Tubize Brabant Wallon 1480",
    "addr:housenumber":"248",
    "addr:postcode":"1480",
    "addr:street":"Chausse\u0301E D'Enghien;Wallon",
    "iso:country":"BE",
    "sg:address":"Chauss\u00c9e D'enghien 248",
    "sg:city":"Tubize",
    "sg:orig_category":"Entretien and r\u00e9parations de voitures. Stations-service and carburants",
    "sg:phone":"+32 2 355 83 59",
    "sg:postcode":"1480",
    "sg:province":"Brabant Wallon",
    "wof:name":"Texaco",
    "wof:placetype":"venue"
},
  "geometry": {"coordinates":[4.1591801643,50.7063598633],"type":"Point"}
}