{
  "type": "Feature",
  "properties": {
    "addr:full":"All\u00c9e Verte 62 Vise Li\u00e8ge 4600",
    "addr:housenumber":"62",
    "addr:postcode":"4600",
    "addr:street":"Alle\u0301E Verte",
    "iso:country":"BE",
    "sg:address":"All\u00c9e Verte 62",
    "sg:city":"Vise",
    "sg:orig_category":"Pi\u00e8ces and accessoires de v\u00e9hicules automobiles V\u00e9hicules automobiles",
    "sg:phone":"+32 4 379 22 31",
    "sg:postcode":"4600",
    "sg:province":"Li\u00e8ge",
    "wof:name":"Vise-motor",
    "wof:placetype":"venue"
},
  "geometry": {"coordinates":[5.6790509224,50.7355384827],"type":"Point"}
}