{
  "type": "Feature",
  "properties": {
    "iso:country":"BE",
    "sg:address":"Lombaardstraat 7",
    "sg:city":"Sint-katelijne-waver",
    "sg:orig_category":"Producteurs de l\u00e9gumes",
    "sg:phone":"+32 15 55 24 75",
    "sg:postcode":"2860",
    "sg:province":"Antwerpen",
    "wof:name":"Jan Van Asch",
    "wof:placetype":"venue"
},
  "geometry": {"coordinates":[4.5263128281,51.0558815002],"type":"Point"}
}