{
  "type": "Feature",
  "properties": {
    "addr:full":"Rue De Charleroi 24bb Fontaine-l'eveque Hainaut 6140",
    "addr:housenumber":"24bb",
    "addr:postcode":"6140",
    "addr:street":"Rue De Charleroi;Hainaut",
    "iso:country":"BE",
    "sg:address":"Rue De Charleroi 24bb",
    "sg:city":"Fontaine-l'eveque",
    "sg:classifiers":[
        {
            "category":"Communications",
            "subcategory":"Television Station",
            "type":"Services"
        }
    ],
    "sg:phone":"+32 71 54 41 59",
    "sg:postcode":"6140",
    "sg:province":"Hainaut",
    "sg:tags":[
        "video",
        "audio",
        "verhuur"
    ],
    "wof:name":"Vid\u00c9o Plus",
    "wof:placetype":"venue"
},
  "geometry": {"coordinates":[4.3309459686,50.4070205688],"type":"Point"}
}