{
  "type": "Feature",
  "properties": {
    "addr:full":"Boulevard Auguste Reyers 107 Box 3 Bruxelles (schaerbeek) Bruxelles-Capitale 1030",
    "addr:housenumber":"107;3",
    "addr:postcode":"1030",
    "addr:street":"Boulevard Auguste Reyers;Box",
    "iso:country":"BE",
    "sg:address":"Boulevard Auguste Reyers 107 Box 3",
    "sg:city":"Bruxelles (schaerbeek)",
    "sg:classifiers":[
        {
            "category":"Professional",
            "subcategory":"Lawyer & Legal Services",
            "type":"Services"
        }
    ],
    "sg:phone":"+32 2 736 18 82",
    "sg:postcode":"1030",
    "sg:province":"Bruxelles-Capitale",
    "wof:name":"Souvereyns Jan",
    "wof:placetype":"venue"
},
  "geometry": {"coordinates":[4.4008078575,50.850818634],"type":"Point"}
}