{
  "type": "Feature",
  "properties": {
    "iso:country":"BE",
    "sg:address":"Brugstraat 2",
    "sg:city":"Lokeren",
    "sg:orig_category":"Paramedische behandelingen",
    "sg:phone":"+32 9 348 93 13",
    "sg:postcode":"9160",
    "sg:province":"Oost-Vlaanderen",
    "wof:name":"Solidariteit V. Het Gezin",
    "wof:placetype":"venue"
},
  "geometry": {"coordinates":[3.99584198,51.102394104],"type":"Point"}
}