{
  "type": "Feature",
  "properties": {
    "addr:full":"Rue Arthur Dubois 23 Pont-a-celles Hainaut 6230",
    "addr:housenumber":"23",
    "addr:postcode":"6230",
    "addr:street":"Rue Arthur Dubois",
    "iso:country":"BE",
    "sg:address":"Rue Arthur Dubois 23",
    "sg:city":"Pont-a-celles",
    "sg:classifiers":[
        {
            "category":"Insurance",
            "subcategory":"Insurance Agent",
            "type":"Services"
        }
    ],
    "sg:phone":"+32 71 35 36 29",
    "sg:postcode":"6230",
    "sg:province":"Hainaut",
    "sg:tags":[
        "verzekeringsmakelaars",
        "expert"
    ],
    "wof:name":"Bertrand",
    "wof:placetype":"venue"
},
  "geometry": {"coordinates":[4.3707361221,50.507106781],"type":"Point"}
}