{
  "type": "Feature",
  "properties": {
    "iso:country":"BE",
    "sg:address":"Kievitstraat 11",
    "sg:city":"Waregem",
    "sg:orig_category":"Plaatsen van vloer- and muurbekleding",
    "sg:phone":"+32 56 60 90 80",
    "sg:postcode":"8790",
    "sg:province":"West-Vlaanderen",
    "wof:name":"Vandenborre",
    "wof:placetype":"venue"
},
  "geometry": {"coordinates":[3.4503550529,50.9029159546],"type":"Point"}
}