{
  "type": "Feature",
  "properties": {
    "addr:full":"Rue De La Gare 15 Box 4 Weismes Li\u00e8ge 4950",
    "addr:housenumber":"15;4",
    "addr:postcode":"4950",
    "addr:street":"Rue De La Gare;Box",
    "iso:country":"BE",
    "sg:address":"Rue De La Gare 15 Box 4",
    "sg:city":"Weismes",
    "sg:classifiers":[
        {
            "category":"Health Services",
            "subcategory":"Doctor",
            "type":"Services"
        }
    ],
    "sg:phone":"+32 80 67 88 16",
    "sg:postcode":"4950",
    "sg:province":"Li\u00e8ge",
    "sg:tags":[
        "medicinephysicians",
        "surgeon"
    ],
    "wof:name":"Delobbe Alain",
    "wof:placetype":"venue"
},
  "geometry": {"coordinates":[6.1131749153,50.4143333435],"type":"Point"}
}