{
  "type": "Feature",
  "properties": {
    "iso:country":"BE",
    "sg:address":"Hasseltsesteenweg 480",
    "sg:city":"Sint-truiden",
    "sg:classifiers":[
        {
            "category":"Building & Trades",
            "subcategory":"Electrical",
            "type":"Services"
        }
    ],
    "sg:phone":"+32 11 59 75 02",
    "sg:postcode":"3800",
    "sg:province":"Limburg",
    "sg:tags":[
        "electric",
        "-",
        "housewiring",
        "contractor"
    ],
    "wof:name":"Elektriciteitswerken Quintiens",
    "wof:placetype":"venue"
},
  "geometry": {"coordinates":[5.2024002075,50.8291053772],"type":"Point"}
}