{
  "type": "Feature",
  "properties": {
    "addr:full":"Henri Jasparlaan 3 Middelkerke West-Vlaanderen 8434",
    "addr:housenumber":"3",
    "addr:postcode":"8434",
    "addr:street":"Henri Jasparlaan",
    "iso:country":"BE",
    "sg:address":"Henri Jasparlaan 3",
    "sg:city":"Middelkerke",
    "sg:classifiers":[
        {
            "category":"Restaurant",
            "type":"Food & Drink"
        }
    ],
    "sg:phone":"+32 58 23 96 38",
    "sg:postcode":"8434",
    "sg:province":"West-Vlaanderen",
    "sg:tags":[
        "caf\u00e9s"
    ],
    "wof:name":"Danny's Taverne",
    "wof:placetype":"venue"
},
  "geometry": {"coordinates":[2.7677400112,51.1627311707],"type":"Point"}
}