{
  "type": "Feature",
  "properties": {
    "iso:country":"BE",
    "sg:address":"Zeedijk-centrum 488",
    "sg:city":"Koksijde",
    "sg:orig_category":"Chaussures",
    "sg:phone":"+32 58 51 36 11",
    "sg:postcode":"8670",
    "sg:province":"West-Vlaanderen",
    "wof:name":"Huis Lymarc",
    "wof:placetype":"venue"
},
  "geometry": {"coordinates":[2.6750299931,51.1339111328],"type":"Point"}
}