{
  "type": "Feature",
  "properties": {
    "addr:full":"Chemin Des Grands Rus 10 Verviers Li\u00e8ge 4802",
    "addr:housenumber":"10",
    "addr:postcode":"4802",
    "addr:street":"Chemin Des Grands Rus",
    "iso:country":"BE",
    "sg:address":"Chemin Des Grands Rus 10",
    "sg:city":"Verviers",
    "sg:orig_category":"M\u00e9decins and sp\u00e9cialistes",
    "sg:phone":"+32 87 22 94 49",
    "sg:postcode":"4802",
    "sg:province":"Li\u00e8ge",
    "wof:name":"Jean Lourtie",
    "wof:placetype":"venue"
},
  "geometry": {"coordinates":[5.8853559494,50.5749130249],"type":"Point"}
}