{
  "type": "Feature",
  "properties": {
    "addr:full":"Berenhoek 9 Haaltert Oost-Vlaanderen 9450",
    "addr:housenumber":"9",
    "addr:postcode":"9450",
    "addr:street":"Berenhoek",
    "iso:country":"BE",
    "sg:address":"Berenhoek 9",
    "sg:city":"Haaltert",
    "sg:orig_category":"Pluimveekwekers",
    "sg:phone":"+32 53 62 30 67",
    "sg:postcode":"9450",
    "sg:province":"Oost-Vlaanderen",
    "wof:name":"Livinus De Hainaut",
    "wof:placetype":"venue"
},
  "geometry": {"coordinates":[3.9569020271,50.8726844788],"type":"Point"}
}