{
  "type": "Feature",
  "properties": {
    "iso:country":"BE",
    "sg:address":"Rue Nizette 12",
    "sg:city":"Aubange",
    "sg:orig_category":"Travaux de pl\u00e2trage",
    "sg:phone":"+32 63 38 92 28",
    "sg:postcode":"6790",
    "sg:province":"Luxembourg",
    "wof:name":"Rene Sala",
    "wof:placetype":"venue"
},
  "geometry": {"coordinates":[5.7890129089,49.5577888489],"type":"Point"}
}