{
  "type": "Feature",
  "properties": {
    "iso:country":"BE",
    "sg:address":"Nieuwe Steenweg 126",
    "sg:city":"Heers",
    "sg:orig_category":"Fruitteelt Varkenskwekers",
    "sg:phone":"+32 11 48 58 66",
    "sg:postcode":"3870",
    "sg:province":"Limburg",
    "wof:name":"Valere Robijns",
    "wof:placetype":"venue"
},
  "geometry": {"coordinates":[5.2927641869,50.7523269653],"type":"Point"}
}