{
  "type": "Feature",
  "properties": {
    "addr:full":"Rue Fond De Soheit 116 Tinlot (soheit-tinlot) Li\u00e8ge 4557",
    "addr:housenumber":"116",
    "addr:postcode":"4557",
    "addr:street":"Rue Fond De Soheit;Soheit-Tinlot",
    "iso:country":"BE",
    "sg:address":"Rue Fond De Soheit 116",
    "sg:city":"Tinlot (soheit-tinlot)",
    "sg:classifiers":[
        {
            "category":"Insurance",
            "subcategory":"Insurance Agent",
            "type":"Services"
        }
    ],
    "sg:phone":"+32 85 51 35 34",
    "sg:postcode":"4557",
    "sg:province":"Li\u00e8ge",
    "sg:tags":[
        "broker"
    ],
    "wof:name":"Select Pm Assurances Sprl",
    "wof:placetype":"venue"
},
  "geometry": {"coordinates":[5.387239933,50.47838974],"type":"Point"}
}