{
  "type": "Feature",
  "properties": {
    "iso:country":"BE",
    "sg:address":"Ren\u00c9 Gobertlaan 14b3",
    "sg:city":"Ukkel/uccle",
    "sg:orig_category":"Advocaten and juridische adviseurs",
    "sg:phone":"+32 2 375 03 67",
    "sg:postcode":"1180",
    "sg:province":"Bruxelles-Capitale",
    "wof:name":"Cl. Verhaegen",
    "wof:placetype":"venue"
},
  "geometry": {"coordinates":[4.3695468903,50.8082809448],"type":"Point"}
}