{
  "type": "Feature",
  "properties": {
    "iso:country":"BE",
    "sg:address":"Lijsterweg 31",
    "sg:city":"Ravels",
    "sg:orig_category":"Elektrische installaties voor woningen Telecommunicatieapparaten",
    "sg:phone":"+32 14 65 72 30",
    "sg:postcode":"2380",
    "sg:province":"Antwerpen",
    "wof:name":"Vosters",
    "wof:placetype":"venue"
},
  "geometry": {"coordinates":[5.0097141266,51.3718338013],"type":"Point"}
}