{
  "type": "Feature",
  "properties": {
    "addr:full":"Middenstraat 26 Beringen (koersel) Limburg 3582",
    "addr:housenumber":"26",
    "addr:postcode":"3582",
    "addr:street":"Middenstraat",
    "iso:country":"BE",
    "sg:address":"Middenstraat 26",
    "sg:city":"Beringen (koersel)",
    "sg:classifiers":[
        {
            "category":"Utilities",
            "subcategory":"Telephone",
            "type":"Services"
        }
    ],
    "sg:phone":"+32 11 42 91 82",
    "sg:postcode":"3582",
    "sg:province":"Limburg",
    "sg:tags":[
        "karting",
        "accessory"
    ],
    "wof:name":"Schepers Racing Service Bvba",
    "wof:placetype":"venue"
},
  "geometry": {"coordinates":[5.2708749771,51.0595359802],"type":"Point"}
}