{
  "type": "Feature",
  "properties": {
    "addr:full":"Uikhoverstraat 16 Maasmechelen (uikhoven) Limburg 3631",
    "addr:housenumber":"16",
    "addr:postcode":"3631",
    "addr:street":"Uikhoverstraat",
    "iso:country":"BE",
    "sg:address":"Uikhoverstraat 16",
    "sg:city":"Maasmechelen (uikhoven)",
    "sg:classifiers":[
        {
            "category":"Home & Garden",
            "subcategory":"Kitchen Supply",
            "type":"Retail Goods"
        }
    ],
    "sg:phone":"+32 89 71 15 11",
    "sg:postcode":"3631",
    "sg:province":"Limburg",
    "sg:tags":[
        "installation"
    ],
    "wof:name":"Bollen F",
    "wof:placetype":"venue"
},
  "geometry": {"coordinates":[5.7239232063,50.9423713684],"type":"Point"}
}