{
  "type": "Feature",
  "properties": {
    "addr:full":"Polderdijkweg 8 Antwerpen Antwerpen 2030",
    "addr:housenumber":"8",
    "addr:postcode":"2030",
    "addr:street":"Polderdijkweg",
    "iso:country":"BE",
    "sg:address":"Polderdijkweg 8",
    "sg:city":"Antwerpen",
    "sg:classifiers":[
        {
            "category":"Cafe",
            "type":"Food & Drink"
        }
    ],
    "sg:phone":"+32 3 541 04 15",
    "sg:postcode":"2030",
    "sg:province":"Antwerpen",
    "sg:tags":[
        "caf\u00e9s"
    ],
    "wof:name":"Caf\u00c9 Spek & Eieren",
    "wof:placetype":"venue"
},
  "geometry": {"coordinates":[4.343462944,51.2634544373],"type":"Point"}
}