{
  "type": "Feature",
  "properties": {
    "addr:full":"Warande 31 Wachtebeke Oost-Vlaanderen 9185",
    "addr:housenumber":"31",
    "addr:postcode":"9185",
    "addr:street":"Warande",
    "iso:country":"BE",
    "sg:address":"Warande 31",
    "sg:city":"Wachtebeke",
    "sg:classifiers":[
        {
            "category":"Professional",
            "subcategory":"Testing Lab",
            "type":"Services"
        }
    ],
    "sg:phone":"+32 9 345 92 86",
    "sg:postcode":"9185",
    "sg:province":"Oost-Vlaanderen",
    "sg:tags":[
        "chemist"
    ],
    "wof:name":"D'heer K",
    "wof:placetype":"venue"
},
  "geometry": {"coordinates":[3.8415389061,51.1595115662],"type":"Point"}
}