{
  "type": "Feature",
  "properties": {
    "addr:full":"Kapellensteenweg 170 Kalmthout Antwerpen 2920",
    "addr:housenumber":"170",
    "addr:postcode":"2920",
    "addr:street":"Kapellensteenweg",
    "iso:country":"BE",
    "sg:address":"Kapellensteenweg 170",
    "sg:city":"Kalmthout",
    "sg:orig_category":"Artsen and specialisten",
    "sg:phone":"+32 3 666 05 05",
    "sg:postcode":"2920",
    "sg:province":"Antwerpen",
    "wof:name":"Consultatiebur.jonge Kind",
    "wof:placetype":"venue"
},
  "geometry": {"coordinates":[4.4747700691,51.3826637268],"type":"Point"}
}