{
  "type": "Feature",
  "properties": {
    "addr:full":"Begijnhoflaan 464 Gent Oost-Vlaanderen 9000",
    "addr:housenumber":"464",
    "addr:postcode":"9000",
    "addr:street":"Begijnhoflaan;Oost-Vlaanderen",
    "iso:country":"BE",
    "sg:address":"Begijnhoflaan 464",
    "sg:city":"Gent",
    "sg:classifiers":[
        {
            "category":"Manufacturing",
            "subcategory":"Printing",
            "type":"Manufacturing & Wholesale Goods"
        }
    ],
    "sg:phone":"+32 9 267 04 11",
    "sg:postcode":"9000",
    "sg:province":"Oost-Vlaanderen",
    "sg:tags":[
        "house",
        "book"
    ],
    "wof:name":"Snoeck-ducaju & Zoon Nv",
    "wof:placetype":"venue"
},
  "geometry": {"coordinates":[3.7096738815,51.0575141907],"type":"Point"}
}