{
  "type": "Feature",
  "properties": {
    "addr:full":"Rue Des Papillards 41 Beyne-heusay Li\u00e8ge 4610",
    "addr:housenumber":"41",
    "addr:postcode":"4610",
    "addr:street":"Rue Des Papillards",
    "iso:country":"BE",
    "sg:address":"Rue Des Papillards 41",
    "sg:city":"Beyne-heusay",
    "sg:orig_category":"Woningbouw",
    "sg:phone":"+32 4 362 28 18",
    "sg:postcode":"4610",
    "sg:province":"Li\u00e8ge",
    "wof:name":"Bati-budget",
    "wof:placetype":"venue"
},
  "geometry": {"coordinates":[5.6646699905,50.6377067566],"type":"Point"}
}