{
  "type": "Feature",
  "properties": {
    "addr:full":"Rue De Ch\u00ean\u00e9e 53 Li\u00e8ge 1 (angleur) Li\u00e8ge 4031",
    "addr:housenumber":"53;1",
    "addr:postcode":"4031",
    "addr:street":"Rue De Che\u0302Ne\u0301E",
    "iso:country":"BE",
    "sg:address":"Rue De Ch\u00ean\u00e9e 53",
    "sg:city":"Li\u00e8ge 1 (angleur)",
    "sg:classifiers":[
        {
            "category":"Wholesale",
            "subcategory":"Hardware",
            "type":"Manufacturing & Wholesale Goods"
        }
    ],
    "sg:phone":"+32 4 278 68 07",
    "sg:postcode":"4031",
    "sg:province":"Li\u00e8ge",
    "sg:tags":[
        "lubricating",
        "compound"
    ],
    "wof:name":"Orapi-alittex Centre D'affaires Dony",
    "wof:placetype":"venue"
},
  "geometry": {"coordinates":[5.6062760353,50.6106338501],"type":"Point"}
}