{
  "type": "Feature",
  "properties": {
    "addr:full":"Clos De L'aronelle 15 Genappe (ways) Brabant Wallon 1474",
    "addr:housenumber":"15",
    "addr:postcode":"1474",
    "addr:street":"Clos De L'Aronelle;Ways",
    "iso:country":"BE",
    "sg:address":"Clos De L'aronelle 15",
    "sg:city":"Genappe (ways)",
    "sg:classifiers":[
        {
            "category":"Shopping",
            "subcategory":"Antiques",
            "type":"Retail Goods"
        }
    ],
    "sg:phone":"+32 67 79 16 14",
    "sg:postcode":"1474",
    "sg:province":"Brabant Wallon",
    "sg:tags":[
        "restoration"
    ],
    "wof:name":"Scarcez E",
    "wof:placetype":"venue"
},
  "geometry": {"coordinates":[4.4518480301,50.6173286438],"type":"Point"}
}