{
  "type": "Feature",
  "properties": {
    "iso:country":"BE",
    "sg:address":"Ambachtslaan 1061",
    "sg:city":"Peer",
    "sg:classifiers":[
        {
            "category":"Autos & Motor Vehicles",
            "subcategory":"Motorcycle Sales",
            "type":"Retail Goods"
        }
    ],
    "sg:phone":"+32 11 63 68 52",
    "sg:postcode":"3990",
    "sg:province":"Limburg",
    "sg:tags":[
        "automobile",
        "brake",
        "-",
        "truck"
    ],
    "wof:name":"Truck- En Busservice Nv",
    "wof:placetype":"venue"
},
  "geometry": {"coordinates":[5.4689011574,51.1339378357],"type":"Point"}
}