{
  "type": "Feature",
  "properties": {
    "addr:full":"Place De Saint-job 4 Bruxelles (uccle) Bruxelles-Capitale 1180",
    "addr:housenumber":"4",
    "addr:postcode":"1180",
    "addr:street":"Place De Saint-Job",
    "iso:country":"BE",
    "sg:address":"Place De Saint-job 4",
    "sg:city":"Bruxelles (uccle)",
    "sg:classifiers":[
        {
            "category":"Retail",
            "subcategory":"Veterinary Services",
            "type":"Services"
        }
    ],
    "sg:phone":"+32 2 374 79 76",
    "sg:postcode":"1180",
    "sg:province":"Bruxelles-Capitale",
    "sg:tags":[
        "veterinarian"
    ],
    "wof:name":"Delannois F",
    "wof:placetype":"venue"
},
  "geometry": {"coordinates":[4.3658099174,50.7938842773],"type":"Point"}
}