{
  "type": "Feature",
  "properties": {
    "iso:country":"BE",
    "sg:address":"Regenbeek 44",
    "sg:city":"Roeselare",
    "sg:orig_category":"Epuration des eaux",
    "sg:phone":"+32 51 24 60 57",
    "sg:postcode":"8800",
    "sg:province":"West-Vlaanderen",
    "wof:name":"Desotec",
    "wof:placetype":"venue"
},
  "geometry": {"coordinates":[3.1709940434,50.9354438782],"type":"Point"}
}