{
  "type": "Feature",
  "properties": {
    "iso:country":"BE",
    "sg:address":"Rue De La Broche De Fer 153",
    "sg:city":"Mouscron (herseaux)",
    "sg:classifiers":[
        {
            "category":"Education",
            "subcategory":"School",
            "type":"Public Place"
        }
    ],
    "sg:phone":"+32 56 33 25 04",
    "sg:postcode":"7712",
    "sg:province":"Hainaut",
    "sg:tags":[
        "primary"
    ],
    "wof:name":"Ecole St-jean Baptiste",
    "wof:placetype":"venue"
},
  "geometry": {"coordinates":[3.2178380489,50.7146492004],"type":"Point"}
}