{
  "type": "Feature",
  "properties": {
    "addr:full":"Grote Steenweg 194 Zoutleeuw Vlaams-Brabant 3440",
    "addr:housenumber":"194",
    "addr:postcode":"3440",
    "addr:street":"Grote Steenweg;Vlaams-Brabant",
    "iso:country":"BE",
    "sg:address":"Grote Steenweg 194",
    "sg:city":"Zoutleeuw",
    "sg:orig_category":"Herstellingen and onderhoud van auto's",
    "sg:phone":"+32 11 78 15 26",
    "sg:postcode":"3440",
    "sg:province":"Vlaams-Brabant",
    "wof:name":"Roger Morren",
    "wof:placetype":"venue"
},
  "geometry": {"coordinates":[5.1251897812,50.8098678589],"type":"Point"}
}