{
  "type": "Feature",
  "properties": {
    "iso:country":"BE",
    "sg:address":"Welvaartstraat 112",
    "sg:city":"Berlaar",
    "sg:orig_category":"Transports routiers de marchandises",
    "sg:phone":"+32 3 482 12 14",
    "sg:postcode":"2590",
    "sg:province":"Antwerpen",
    "wof:name":"Transport Geert De Belser",
    "wof:placetype":"venue"
},
  "geometry": {"coordinates":[4.6417880058,51.1012077332],"type":"Point"}
}