{
  "type": "Feature",
  "properties": {
    "iso:country":"BE",
    "sg:address":"Rue De L\u00b4isle 26",
    "sg:city":"Seraing",
    "sg:orig_category":"M\u00e9decins and sp\u00e9cialistes",
    "sg:phone":"+32 4 231 21 09",
    "sg:postcode":"4101",
    "sg:province":"Li\u00e8ge",
    "wof:name":"Hong Phuong Do Thi",
    "wof:placetype":"venue"
},
  "geometry": {"coordinates":[5.4995770454,50.6171798706],"type":"Point"}
}