{
  "type": "Feature",
  "properties": {
    "iso:country":"BE",
    "sg:address":"Thioux 15",
    "sg:city":"Malmedy/malmedy",
    "sg:orig_category":"Rundveehouders",
    "sg:phone":"+32 80 33 01 33",
    "sg:postcode":"4960",
    "sg:province":"Li\u00e8ge",
    "wof:name":"Leopold Dumoulin",
    "wof:placetype":"venue"
},
  "geometry": {"coordinates":[5.9922227859,50.3880157471],"type":"Point"}
}