{
  "type": "Feature",
  "properties": {
    "iso:country":"BE",
    "sg:address":"Bergense Steenweg 1106",
    "sg:city":"Anderlecht/anderlecht",
    "sg:classifiers":[
        {
            "category":"Fast Food",
            "type":"Food & Drink"
        }
    ],
    "sg:phone":"+32 2 524 05 07",
    "sg:postcode":"1070",
    "sg:province":"Bruxelles-Capitale",
    "sg:tags":[
        "meeneem",
        "restaurant"
    ],
    "wof:name":"Le Rustic",
    "wof:placetype":"venue"
},
  "geometry": {"coordinates":[4.2942810059,50.821231842],"type":"Point"}
}