{
  "type": "Feature",
  "properties": {
    "addr:full":"Hoogeind 91 Stabroek Antwerpen 2940",
    "addr:housenumber":"91",
    "addr:postcode":"2940",
    "addr:street":"Hoogeind",
    "iso:country":"BE",
    "sg:address":"Hoogeind 91",
    "sg:city":"Stabroek",
    "sg:classifiers":[
        {
            "category":"Health Services",
            "subcategory":"Doctor",
            "type":"Services"
        }
    ],
    "sg:phone":"+32 3 568 73 23",
    "sg:postcode":"2940",
    "sg:province":"Antwerpen",
    "sg:tags":[
        "medicinephysicians",
        "surgeon"
    ],
    "wof:name":"Cuypers Luc",
    "wof:placetype":"venue"
},
  "geometry": {"coordinates":[4.3820500374,51.3395614624],"type":"Point"}
}