{
  "type": "Feature",
  "properties": {
    "addr:full":"Boulevard Emile Bockstael 418 Brussel/bruxelles Bruxelles-Capitale 1020",
    "addr:housenumber":"418",
    "addr:postcode":"1020",
    "addr:street":"Boulevard Emile Bockstael;/",
    "iso:country":"BE",
    "sg:address":"Boulevard Emile Bockstael 418",
    "sg:city":"Brussel/bruxelles",
    "sg:classifiers":[
        {
            "category":"Insurance",
            "subcategory":"Life Insurance",
            "type":"Services"
        }
    ],
    "sg:phone":"+32 2 479 00 99",
    "sg:postcode":"1020",
    "sg:province":"Bruxelles-Capitale",
    "sg:tags":[
        "assurance"
    ],
    "wof:name":"Steylemans Assurances",
    "wof:placetype":"venue"
},
  "geometry": {"coordinates":[4.3446598053,50.8837776184],"type":"Point"}
}