{
  "type": "Feature",
  "properties": {
    "iso:country":"BE",
    "sg:address":"Chauss\u00c9e Des Forges 2",
    "sg:city":"Chauss\u00c9e Des Forges 2",
    "sg:classifiers":[
        {
            "category":"Fast Food",
            "type":"Food & Drink"
        }
    ],
    "sg:phone":"+32 85 25 13 15",
    "sg:postcode":"4500",
    "sg:province":"Li\u00e8ge",
    "sg:tags":[
        "\u00c0",
        "emporter",
        "restaurants"
    ],
    "wof:name":"Friterie Les Forges",
    "wof:placetype":"venue"
},
  "geometry": {"coordinates":[5.241604805,50.4983673096],"type":"Point"}
}