{
  "type": "Feature",
  "properties": {
    "addr:full":"Vossensteert 190 Brugge West-Vlaanderen 8310",
    "addr:housenumber":"190",
    "addr:postcode":"8310",
    "iso:country":"BE",
    "sg:address":"Vossensteert 190",
    "sg:city":"Brugge",
    "sg:orig_category":"Plomberie, chauffage and installations sanitaires",
    "sg:phone":"+32 50 36 01 15",
    "sg:postcode":"8310",
    "sg:province":"West-Vlaanderen",
    "wof:name":"Vander Stock Luc",
    "wof:placetype":"venue"
},
  "geometry": {"coordinates":[3.2660880089,51.2056312561],"type":"Point"}
}