{
  "type": "Feature",
  "properties": {
    "addr:full":"Rozendaalstraat 10 Alveringem West-Vlaanderen 8690",
    "addr:housenumber":"10",
    "addr:postcode":"8690",
    "addr:street":"Rozendaalstraat",
    "iso:country":"BE",
    "sg:address":"Rozendaalstraat 10",
    "sg:city":"Alveringem",
    "sg:classifiers":[
        {
            "category":"Cafe",
            "type":"Food & Drink"
        }
    ],
    "sg:phone":"+32 58 28 92 74",
    "sg:postcode":"8690",
    "sg:province":"West-Vlaanderen",
    "sg:tags":[
        "caf\u00e9s"
    ],
    "wof:name":"Laura Deman",
    "wof:placetype":"venue"
},
  "geometry": {"coordinates":[2.7174630165,51.0138130188],"type":"Point"}
}