{
  "type": "Feature",
  "properties": {
    "addr:full":"Staatsbaan 79 Kortemark West-Vlaanderen 8610",
    "addr:housenumber":"79",
    "addr:postcode":"8610",
    "addr:street":"Staatsbaan",
    "iso:country":"BE",
    "sg:address":"Staatsbaan 79",
    "sg:city":"Kortemark",
    "sg:classifiers":[
        {
            "category":"Building & Trades",
            "subcategory":"Construction",
            "type":"Services"
        }
    ],
    "sg:phone":"+32 51 56 70 57",
    "sg:postcode":"8610",
    "sg:province":"West-Vlaanderen",
    "sg:tags":[
        "carpenter"
    ],
    "wof:name":"Pollet Willy & Zn Bvba",
    "wof:placetype":"venue"
},
  "geometry": {"coordinates":[3.0393910408,51.0218391418],"type":"Point"}
}