{
  "type": "Feature",
  "properties": {
    "iso:country":"BE",
    "sg:address":"Alsembergse Steenweg 155",
    "sg:city":"Vorst/forest",
    "sg:orig_category":"Slagers",
    "sg:phone":"+32 2 537 61 23",
    "sg:postcode":"1190",
    "sg:province":"Bruxelles-Capitale",
    "wof:name":"Boucherie Stefan",
    "wof:placetype":"venue"
},
  "geometry": {"coordinates":[4.3421058655,50.8218765259],"type":"Point"}
}