{
  "type": "Feature",
  "properties": {
    "addr:full":"Ezelstraat 37 Brugge West-Vlaanderen 8000",
    "addr:housenumber":"37",
    "addr:postcode":"8000",
    "addr:street":"Ezelstraat",
    "iso:country":"BE",
    "sg:address":"Ezelstraat 37",
    "sg:city":"Brugge",
    "sg:orig_category":"Artiesten and kunstenaars Decoratieve kunst and kunstbenodigdheden",
    "sg:phone":"+32 50 33 28 61",
    "sg:postcode":"8000",
    "sg:province":"West-Vlaanderen",
    "wof:name":"Idee",
    "wof:placetype":"venue"
},
  "geometry": {"coordinates":[3.2190380096,51.2124824524],"type":"Point"}
}