{
  "type": "Feature",
  "properties": {
    "addr:full":"Rue Berr\u00e9 24 Bruxelles (jette) Bruxelles-Capitale 1090",
    "addr:housenumber":"24",
    "addr:postcode":"1090",
    "addr:street":"Rue Berre\u0301",
    "iso:country":"BE",
    "sg:address":"Rue Berr\u00e9 24",
    "sg:city":"Bruxelles (jette)",
    "sg:classifiers":[
        {
            "category":"Health Services",
            "subcategory":"Dentist",
            "type":"Services"
        }
    ],
    "sg:phone":"+32 2 426 46 69",
    "sg:postcode":"1090",
    "sg:province":"Bruxelles-Capitale",
    "wof:name":"Van De Gucht Robert",
    "wof:placetype":"venue"
},
  "geometry": {"coordinates":[4.337061882,50.8726005554],"type":"Point"}
}