{
  "type": "Feature",
  "properties": {
    "iso:country":"BE",
    "sg:address":"Hundelgemsesteenweg 331",
    "sg:city":"Gent",
    "sg:orig_category":"Isolatiewerk",
    "sg:phone":"+32 9 232 27 54",
    "sg:postcode":"9050",
    "sg:province":"Oost-Vlaanderen",
    "wof:name":"Johan Burms",
    "wof:placetype":"venue"
},
  "geometry": {"coordinates":[3.7482330799,51.026348114],"type":"Point"}
}