{
  "type": "Feature",
  "properties": {
    "iso:country":"BE",
    "sg:address":"Majoor Woodstraat 18",
    "sg:city":"Oostkamp",
    "sg:orig_category":"Pharmaciens",
    "sg:phone":"+32 50 82 28 83",
    "sg:postcode":"8020",
    "sg:province":"West-Vlaanderen",
    "wof:name":"H Vermeulen",
    "wof:placetype":"venue"
},
  "geometry": {"coordinates":[3.2341880798,51.1546058655],"type":"Point"}
}