{
  "type": "Feature",
  "properties": {
    "iso:country":"BE",
    "sg:address":"Impedorp 57",
    "sg:city":"Lede (impe)",
    "sg:classifiers":[
        {
            "category":"Personal",
            "subcategory":"Beauty Salon",
            "type":"Services"
        }
    ],
    "sg:phone":"+32 53 80 16 19",
    "sg:postcode":"9340",
    "sg:province":"Oost-Vlaanderen",
    "sg:tags":[
        "lady",
        "-",
        "hairdressing"
    ],
    "wof:name":"Van Den Broecke J",
    "wof:placetype":"venue"
},
  "geometry": {"coordinates":[3.9519510269,50.961353302],"type":"Point"}
}