{
  "type": "Feature",
  "properties": {
    "iso:country":"BE",
    "sg:address":"Graanmarkt 15",
    "sg:city":"Antwerpen",
    "sg:classifiers":[
        {
            "category":"Bars & Pubs",
            "type":"Food & Drink"
        }
    ],
    "sg:phone":"+32 3 233 14 08",
    "sg:postcode":"2000",
    "sg:province":"Antwerpen",
    "sg:tags":[
        "tavern"
    ],
    "wof:name":"Houten Clara Nv",
    "wof:placetype":"venue"
},
  "geometry": {"coordinates":[4.4090180397,51.21616745],"type":"Point"}
}