{
  "type": "Feature",
  "properties": {
    "addr:full":"Molenheide 63 Zemst Vlaams-Brabant 1981",
    "addr:housenumber":"63",
    "addr:postcode":"1981",
    "addr:street":"Molenheide;Vlaams-Brabant",
    "iso:country":"BE",
    "sg:address":"Molenheide 63",
    "sg:city":"Zemst",
    "sg:orig_category":"Artsen and specialisten",
    "sg:phone":"+32 15 61 54 98",
    "sg:postcode":"1981",
    "sg:province":"Vlaams-Brabant",
    "wof:name":"Frans Piessens",
    "wof:placetype":"venue"
},
  "geometry": {"coordinates":[4.5251998901,50.9904975891],"type":"Point"}
}