{
  "type": "Feature",
  "properties": {
    "iso:country":"BE",
    "sg:address":"Koning Leopoldlaan 157",
    "sg:city":"Lommel",
    "sg:orig_category":"Installation de serres, double vitrage and fen\u00eatres",
    "sg:phone":"+32 11 54 43 20",
    "sg:postcode":"3920",
    "sg:province":"Limburg",
    "wof:name":"Henri Rademakers",
    "wof:placetype":"venue"
},
  "geometry": {"coordinates":[5.3266320229,51.2306861877],"type":"Point"}
}