{
  "type": "Feature",
  "properties": {
    "iso:country":"BE",
    "sg:address":"Populierenstraat 2",
    "sg:city":"Lummen",
    "sg:classifiers":[
        {
            "category":"Building & Trades",
            "subcategory":"Construction",
            "type":"Services"
        }
    ],
    "sg:phone":"+32 13 52 14 51",
    "sg:postcode":"3560",
    "sg:province":"Limburg",
    "sg:tags":[
        "installation",
        "-",
        "central",
        "heating"
    ],
    "wof:name":"Santermans",
    "wof:placetype":"venue"
},
  "geometry": {"coordinates":[5.1734900475,50.9805488586],"type":"Point"}
}