{
  "type": "Feature",
  "properties": {
    "addr:full":"Route De Walhorn 14 Lontzen Li\u00e8ge 4711",
    "addr:housenumber":"14",
    "addr:postcode":"4711",
    "addr:street":"Route De Walhorn",
    "iso:country":"BE",
    "sg:address":"Route De Walhorn 14",
    "sg:city":"Lontzen",
    "sg:orig_category":"Avocats and conseillers juridiques",
    "sg:phone":"+32 87 63 00 54",
    "sg:postcode":"4711",
    "sg:province":"Li\u00e8ge",
    "wof:name":"Rudolf Meessen",
    "wof:placetype":"venue"
},
  "geometry": {"coordinates":[6.047369957,50.6752853394],"type":"Point"}
}