{
  "type": "Feature",
  "properties": {
    "iso:country":"BE",
    "sg:address":"Rue Du Pont 7",
    "sg:city":"Tournai",
    "sg:classifiers":[
        {
            "category":"Shopping",
            "subcategory":"Clothing, Apparel, & Fashions",
            "type":"Retail Goods"
        }
    ],
    "sg:phone":"+32 69 21 01 51",
    "sg:postcode":"7500",
    "sg:province":"Hainaut",
    "sg:tags":[
        "lingerie",
        "sous-v\u00eatements"
    ],
    "wof:name":"Maison F\u00c9minit\u00c9",
    "wof:placetype":"venue"
},
  "geometry": {"coordinates":[3.393709898,50.6070098877],"type":"Point"}
}