{
  "type": "Feature",
  "properties": {
    "iso:country":"BE",
    "sg:address":"Rue Douffet 3",
    "sg:city":"Li\u00c8ge",
    "sg:orig_category":"M\u00e9decins and sp\u00e9cialistes",
    "sg:phone":"+32 4 343 56 30",
    "sg:postcode":"4020",
    "sg:province":"Li\u00e8ge",
    "wof:name":"Alfred Mativa",
    "wof:placetype":"venue"
},
  "geometry": {"coordinates":[5.5852980614,50.6365432739],"type":"Point"}
}