{
  "type": "Feature",
  "properties": {
    "addr:full":"Europark-oost 13 Sint-niklaas Oost-Vlaanderen 9100",
    "addr:housenumber":"13",
    "addr:postcode":"9100",
    "addr:street":"Europark-Oost",
    "iso:country":"BE",
    "sg:address":"Europark-oost 13",
    "sg:city":"Sint-niklaas",
    "sg:orig_category":"Installatie van metalen schrijnwerk SMEEDWERK, METAALBEWERKING AND POEDERMETALLURGIE",
    "sg:phone":"+32 3 776 24 48",
    "sg:postcode":"9100",
    "sg:province":"Oost-Vlaanderen",
    "wof:name":"Thor",
    "wof:placetype":"venue"
},
  "geometry": {"coordinates":[4.1727881432,51.1637077332],"type":"Point"}
}