{
  "type": "Feature",
  "properties": {
    "addr:full":"Eeuwlaan 45 Grimbergen Vlaams-Brabant 1850",
    "addr:housenumber":"45",
    "addr:postcode":"1850",
    "addr:street":"Eeuwlaan",
    "iso:country":"BE",
    "sg:address":"Eeuwlaan 45",
    "sg:city":"Grimbergen",
    "sg:orig_category":"M\u00e9decins and sp\u00e9cialistes",
    "sg:phone":"+32 2 252 25 05",
    "sg:postcode":"1850",
    "sg:province":"Vlaams-Brabant",
    "wof:name":"W. Ramon",
    "wof:placetype":"venue"
},
  "geometry": {"coordinates":[4.3921051025,50.9280891418],"type":"Point"}
}