{
  "type": "Feature",
  "properties": {
    "iso:country":"BE",
    "sg:address":"Route De Gosselies 568",
    "sg:city":"Heppignies",
    "sg:classifiers":[
        {
            "category":"Building & Trades",
            "subcategory":"Construction",
            "type":"Services"
        }
    ],
    "sg:phone":"+32 71 35 17 67",
    "sg:postcode":"6220",
    "sg:province":"Hainaut",
    "sg:tags":[
        "machine",
        "hiring"
    ],
    "wof:name":"Groupe Lambert International Gli S.a.",
    "wof:placetype":"venue"
},
  "geometry": {"coordinates":[4.4888529778,50.4654808044],"type":"Point"}
}