{
  "type": "Feature",
  "properties": {
    "iso:country":"BE",
    "sg:address":"Velodroomstraat 210",
    "sg:city":"Boom",
    "sg:classifiers":[
        {
            "category":"Health Services",
            "subcategory":"Doctor",
            "type":"Services"
        }
    ],
    "sg:phone":"+32 3 821 33 50",
    "sg:postcode":"2850",
    "sg:province":"Antwerpen",
    "sg:tags":[
        "medicinephysicians",
        "surgeon"
    ],
    "wof:name":"Beckstedde Inge",
    "wof:placetype":"venue"
},
  "geometry": {"coordinates":[4.3734807968,51.0926208496],"type":"Point"}
}