{
  "type": "Feature",
  "properties": {
    "addr:full":"Industrieterrein Kanaal-noord 1150 Bree Limburg 3960",
    "addr:postcode":"1150;3960",
    "addr:street":"Industrieterrein Kanaal-Noord",
    "iso:country":"BE",
    "sg:address":"Industrieterrein Kanaal-noord 1150",
    "sg:city":"Bree",
    "sg:classifiers":[
        {
            "category":"Utilities",
            "subcategory":"Recycling",
            "type":"Services"
        }
    ],
    "sg:phone":"+32 89 46 14 75",
    "sg:postcode":"3960",
    "sg:province":"Limburg",
    "wof:name":"Goijens Recycling Nv",
    "wof:placetype":"venue"
},
  "geometry": {"coordinates":[5.6246638298,51.142868042],"type":"Point"}
}