{
  "type": "Feature",
  "properties": {
    "iso:country":"BE",
    "sg:address":"Stockeu 1",
    "sg:city":"Stavelot",
    "sg:orig_category":"Quincailleries. Travaux de pl\u00e2trage",
    "sg:phone":"+32 80 88 05 52",
    "sg:postcode":"4970",
    "sg:province":"Li\u00e8ge",
    "wof:name":"J S Construction",
    "wof:placetype":"venue"
},
  "geometry": {"coordinates":[5.9351229668,50.3860931396],"type":"Point"}
}