{
  "type": "Feature",
  "properties": {
    "addr:full":"Molenzicht 12 Arendonk Antwerpen 2370",
    "addr:housenumber":"12",
    "addr:postcode":"2370",
    "addr:street":"Molenzicht",
    "iso:country":"BE",
    "sg:address":"Molenzicht 12",
    "sg:city":"Arendonk",
    "sg:orig_category":"Radioproductie and uitzendingen",
    "sg:phone":"+32 14 67 12 18",
    "sg:postcode":"2370",
    "sg:province":"Antwerpen",
    "wof:name":"Radio O.t.",
    "wof:placetype":"venue"
},
  "geometry": {"coordinates":[5.0915989876,51.326461792],"type":"Point"}
}