{
  "type": "Feature",
  "properties": {
    "addr:full":"Rue Des Alli\u00e9s 20 Chapelle-lez-herlaimont Hainaut 7160",
    "addr:housenumber":"20",
    "addr:postcode":"7160",
    "addr:street":"Rue Des Allie\u0301S",
    "iso:country":"BE",
    "sg:address":"Rue Des Alli\u00e9s 20",
    "sg:city":"Chapelle-lez-herlaimont",
    "sg:classifiers":[
        {
            "category":"Health Services",
            "subcategory":"Dentist",
            "type":"Services"
        }
    ],
    "sg:phone":"+32 64 44 53 39",
    "sg:postcode":"7160",
    "sg:province":"Hainaut",
    "wof:name":"Dumonceau J-p",
    "wof:placetype":"venue"
},
  "geometry": {"coordinates":[4.2783069611,50.4700469971],"type":"Point"}
}