{
  "type": "Feature",
  "properties": {
    "iso:country":"BE",
    "sg:address":"Rue De La-roche 51bb",
    "sg:city":"Hotton",
    "sg:orig_category":"Enseignement maternel and primaire",
    "sg:phone":"+32 84 46 71 08",
    "sg:postcode":"6990",
    "sg:province":"Luxembourg",
    "wof:name":"Ecole Fond. Communale",
    "wof:placetype":"venue"
},
  "geometry": {"coordinates":[5.4722590446,50.2578201294],"type":"Point"}
}