{
  "type": "Feature",
  "properties": {
    "iso:country":"BE",
    "sg:address":"Dijlestraat 68",
    "sg:city":"Keerbergen",
    "sg:orig_category":"Software ontwikkeling and ontwerp",
    "sg:phone":"+32 15 52 02 62",
    "sg:postcode":"3140",
    "sg:province":"Vlaams-Brabant",
    "wof:name":"Compulog",
    "wof:placetype":"venue"
},
  "geometry": {"coordinates":[4.6325211525,50.9964027405],"type":"Point"}
}