{
  "type": "Feature",
  "properties": {
    "iso:country":"BE",
    "sg:address":"Bavelstraat 30",
    "sg:city":"Rijkevorsel",
    "sg:classifiers":[
        {
            "category":"Communications",
            "subcategory":"Television Station",
            "type":"Services"
        }
    ],
    "sg:phone":"+32 3 314 74 75",
    "sg:postcode":"2310",
    "sg:province":"Antwerpen",
    "sg:tags":[
        "report",
        "video"
    ],
    "wof:name":"Jef Vdl Cv",
    "wof:placetype":"venue"
},
  "geometry": {"coordinates":[4.763171196,51.3517189026],"type":"Point"}
}