{
  "type": "Feature",
  "properties": {
    "iso:country":"BE",
    "sg:address":"Onze-lieve-vrouwplein 21",
    "sg:city":"Kruibeke",
    "sg:orig_category":"DIENSTEN VOOR TELECOMMUNICATIE Elektriciteitsproductie and -distributie Gasproductie and -distributi",
    "sg:phone":"+32 78 35 35 35",
    "sg:postcode":"9150",
    "sg:province":"Oost-Vlaanderen",
    "wof:name":"Electrabel",
    "wof:placetype":"venue"
},
  "geometry": {"coordinates":[4.3127961159,51.1709594727],"type":"Point"}
}