{
  "type": "Feature",
  "properties": {
    "iso:country":"BE",
    "sg:address":"Avenue Des Pervenches 6",
    "sg:city":"Montigny-le-tilleul",
    "sg:orig_category":"Administration d'immeubles",
    "sg:phone":"+32 71 51 70 71",
    "sg:postcode":"6110",
    "sg:province":"Hainaut",
    "wof:name":"Sogim - Syndic",
    "wof:placetype":"venue"
},
  "geometry": {"coordinates":[4.3589172363,50.3809204102],"type":"Point"}
}