{
  "type": "Feature",
  "properties": {
    "addr:full":"Chauss\u00c9e De Waterloo 431 Sint-gillis/saint-gilles Bruxelles-Capitale 1060",
    "addr:housenumber":"431",
    "addr:postcode":"1060",
    "addr:street":"Chausse\u0301E De Waterloo",
    "iso:country":"BE",
    "sg:address":"Chauss\u00c9e De Waterloo 431",
    "sg:city":"Sint-gillis/saint-gilles",
    "sg:orig_category":"Fleurs and plantes",
    "sg:phone":"+32 2 344 04 42",
    "sg:postcode":"1060",
    "sg:province":"Bruxelles-Capitale",
    "wof:name":"Imece Yalcin",
    "wof:placetype":"venue"
},
  "geometry": {"coordinates":[4.3538222313,50.8225898743],"type":"Point"}
}