{
  "type": "Feature",
  "properties": {
    "iso:country":"BE",
    "sg:address":"Rue Docteur Vermer 33",
    "sg:city":"Beauraing",
    "sg:orig_category":"Cr\u00e9dits divers",
    "sg:postcode":"5570",
    "sg:province":"Namur",
    "wof:name":"Postomat Beauraing",
    "wof:placetype":"venue"
},
  "geometry": {"coordinates":[4.9587368965,50.1096954346],"type":"Point"}
}