{
  "type": "Feature",
  "properties": {
    "addr:full":"Rue Des Bruy\u00e8res 32 Sombreffe Namur 5140",
    "addr:housenumber":"32",
    "addr:postcode":"5140",
    "addr:street":"Rue Des Bruye\u0300Res",
    "iso:country":"BE",
    "sg:address":"Rue Des Bruy\u00e8res 32",
    "sg:city":"Sombreffe",
    "sg:classifiers":[
        {
            "category":"Farming",
            "subcategory":"Farm & Veterinary Services",
            "type":"Manufacturing & Wholesale Goods"
        }
    ],
    "sg:phone":"+32 71 88 57 47",
    "sg:postcode":"5140",
    "sg:province":"Namur",
    "sg:tags":[
        "agricultural",
        "contractor"
    ],
    "wof:name":"Ferme A Cochin",
    "wof:placetype":"venue"
},
  "geometry": {"coordinates":[4.5938940048,50.5507202148],"type":"Point"}
}