{
  "type": "Feature",
  "properties": {
    "addr:full":"Aalstersesteenweg 183 Ninove Oost-Vlaanderen 9400",
    "addr:housenumber":"183",
    "addr:postcode":"9400",
    "addr:street":"Aalstersesteenweg",
    "iso:country":"BE",
    "sg:address":"Aalstersesteenweg 183",
    "sg:city":"Ninove",
    "sg:classifiers":[
        {
            "category":"Cafe",
            "type":"Food & Drink"
        }
    ],
    "sg:phone":"+32 54 32 17 67",
    "sg:postcode":"9400",
    "sg:province":"Oost-Vlaanderen",
    "sg:tags":[
        "caf\u00e9s"
    ],
    "wof:name":"Jose Vijverman",
    "wof:placetype":"venue"
},
  "geometry": {"coordinates":[4.029654026,50.8443222046],"type":"Point"}
}