{
  "type": "Feature",
  "properties": {
    "addr:full":"Grimbertlaan 33 Schoten Antwerpen 2900",
    "addr:housenumber":"33",
    "addr:postcode":"2900",
    "addr:street":"Grimbertlaan",
    "iso:country":"BE",
    "sg:address":"Grimbertlaan 33",
    "sg:city":"Schoten",
    "sg:classifiers":[
        {
            "category":"Insurance",
            "subcategory":"Insurance Agent",
            "type":"Services"
        }
    ],
    "sg:phone":"+32 3 658 82 35",
    "sg:postcode":"2900",
    "sg:province":"Antwerpen",
    "sg:tags":[
        "verzekeringsmakelaars",
        "expert"
    ],
    "wof:name":"Vergu",
    "wof:placetype":"venue"
},
  "geometry": {"coordinates":[4.5189142227,51.2680511475],"type":"Point"}
}