{
  "type": "Feature",
  "properties": {
    "addr:full":"Schomstraat 110 Beringen Limburg 3582",
    "addr:housenumber":"110",
    "addr:postcode":"3582",
    "addr:street":"Schomstraat",
    "iso:country":"BE",
    "sg:address":"Schomstraat 110",
    "sg:city":"Beringen",
    "sg:orig_category":"Imprimeries and copyshops",
    "sg:phone":"+32 11 42 09 71",
    "sg:postcode":"3582",
    "sg:province":"Limburg",
    "wof:name":"Filip Lemmens",
    "wof:placetype":"venue"
},
  "geometry": {"coordinates":[5.2708749771,51.0595359802],"type":"Point"}
}