{
  "type": "Feature",
  "properties": {
    "iso:country":"BE",
    "sg:address":"Boulevard Du Quatre-mars 37",
    "sg:city":"Ronse/renaix",
    "sg:orig_category":"Installation de menuiserie en bois and plastique. Quincailleries",
    "sg:phone":"+32 55 20 90 65",
    "sg:postcode":"9600",
    "sg:province":"Oost-Vlaanderen",
    "wof:name":"Maes",
    "wof:placetype":"venue"
},
  "geometry": {"coordinates":[3.5955450535,50.7406845093],"type":"Point"}
}