{
  "type": "Feature",
  "properties": {
    "addr:full":"Rue De L'eglise 21 Verviers Li\u00e8ge 4801",
    "addr:housenumber":"21",
    "addr:postcode":"4801",
    "addr:street":"Rue De L'Eglise",
    "iso:country":"BE",
    "sg:address":"Rue De L'eglise 21",
    "sg:city":"Verviers",
    "sg:orig_category":"Herstellingen and onderhoud van auto's",
    "sg:phone":"+32 87 31 06 86",
    "sg:postcode":"4801",
    "sg:province":"Li\u00e8ge",
    "wof:name":"Kremer Jules Et Dominique",
    "wof:placetype":"venue"
},
  "geometry": {"coordinates":[5.8946709633,50.5915031433],"type":"Point"}
}