{
  "type": "Feature",
  "properties": {
    "addr:full":"Rue Du Foss\u00e9 Aux Loups 28b Bruxelles Bruxelles-Capitale 1000",
    "addr:housenumber":"28b",
    "addr:postcode":"1000",
    "addr:street":"Rue Du Fosse\u0301 Aux Loups",
    "iso:country":"BE",
    "sg:address":"Rue Du Foss\u00e9 Aux Loups 28b",
    "sg:city":"Bruxelles",
    "sg:classifiers":[
        {
            "category":"Shopping",
            "subcategory":"Clothing, Apparel, & Fashions",
            "type":"Retail Goods"
        }
    ],
    "sg:phone":"+32 2 219 79 97",
    "sg:postcode":"1000",
    "sg:province":"Bruxelles-Capitale",
    "sg:tags":[
        "underwear",
        "lingerie",
        "-"
    ],
    "wof:name":"Folies De Sade (les)",
    "wof:placetype":"venue"
},
  "geometry": {"coordinates":[4.3542342186,50.8505058289],"type":"Point"}
}