{
  "type": "Feature",
  "properties": {
    "addr:full":"Rue Haute 139 Soumagne Li\u00e8ge 4633",
    "addr:housenumber":"139",
    "addr:postcode":"4633",
    "addr:street":"Rue Haute",
    "iso:country":"BE",
    "sg:address":"Rue Haute 139",
    "sg:city":"Soumagne",
    "sg:orig_category":"Varkenskwekers",
    "sg:phone":"+32 4 377 26 22",
    "sg:postcode":"4633",
    "sg:province":"Li\u00e8ge",
    "wof:name":"M Derkenne",
    "wof:placetype":"venue"
},
  "geometry": {"coordinates":[5.7484059334,50.6466941833],"type":"Point"}
}