{
  "type": "Feature",
  "properties": {
    "addr:full":"Hoogte Honderdplein 10b1 Vorst/forest Bruxelles-Capitale 1190",
    "addr:housenumber":"10b1",
    "addr:postcode":"1190",
    "addr:street":"Hoogte Honderdplein;/ Forest",
    "iso:country":"BE",
    "sg:address":"Hoogte Honderdplein 10b1",
    "sg:city":"Vorst/forest",
    "sg:orig_category":"Artsen and specialisten",
    "sg:phone":"+32 2 343 82 62",
    "sg:postcode":"1190",
    "sg:province":"Bruxelles-Capitale",
    "wof:name":"Nelly Doyen",
    "wof:placetype":"venue"
},
  "geometry": {"coordinates":[4.3375320435,50.8169212341],"type":"Point"}
}