{
  "type": "Feature",
  "properties": {
    "addr:full":"Rue Du Calvaire 300 Li\u00c8ge Li\u00e8ge 4000",
    "addr:housenumber":"300",
    "addr:postcode":"4000",
    "addr:street":"Rue Du Calvaire",
    "iso:country":"BE",
    "sg:address":"Rue Du Calvaire 300",
    "sg:city":"Li\u00c8ge",
    "sg:classifiers":[
        {
            "category":"Fast Food",
            "type":"Food & Drink"
        }
    ],
    "sg:phone":"+32 4 226 68 83",
    "sg:postcode":"4000",
    "sg:province":"Li\u00e8ge",
    "sg:tags":[
        "meeneem",
        "restaurant"
    ],
    "wof:name":"Friterie Du Calvaire",
    "wof:placetype":"venue"
},
  "geometry": {"coordinates":[5.5426840782,50.638961792],"type":"Point"}
}