{
  "type": "Feature",
  "properties": {
    "iso:country":"BE",
    "sg:address":"Rue Des Ecomines 2",
    "sg:city":"Spa",
    "sg:orig_category":"Pain, p\u00e2tisseries and confiseries",
    "sg:phone":"+32 87 77 13 31",
    "sg:postcode":"4900",
    "sg:province":"Li\u00e8ge",
    "wof:name":"Jean Arloff",
    "wof:placetype":"venue"
},
  "geometry": {"coordinates":[5.8662719727,50.4908828735],"type":"Point"}
}