{
  "type": "Feature",
  "properties": {
    "addr:full":"Voort 23 Hoogstraten Antwerpen 2328",
    "addr:housenumber":"23",
    "addr:postcode":"2328",
    "addr:street":"Voort",
    "iso:country":"BE",
    "sg:address":"Voort 23",
    "sg:city":"Hoogstraten",
    "sg:orig_category":"Artsen and specialisten",
    "sg:phone":"+32 3 315 84 64",
    "sg:postcode":"2328",
    "sg:province":"Antwerpen",
    "wof:name":"J. Clymans",
    "wof:placetype":"venue"
},
  "geometry": {"coordinates":[4.7961878777,51.4682731628],"type":"Point"}
}