{
  "type": "Feature",
  "properties": {
    "addr:full":"Visserij 199 Gent Oost-Vlaanderen 9000",
    "addr:housenumber":"199",
    "addr:postcode":"9000",
    "addr:street":"Visserij;Oost-Vlaanderen",
    "iso:country":"BE",
    "sg:address":"Visserij 199",
    "sg:city":"Gent",
    "sg:orig_category":"Activit\u00e9s diverses d'imprimerie",
    "sg:phone":"+32 9 233 49 59",
    "sg:postcode":"9000",
    "sg:province":"Oost-Vlaanderen",
    "wof:name":"Md Media",
    "wof:placetype":"venue"
},
  "geometry": {"coordinates":[3.7399311066,51.0432128906],"type":"Point"}
}