{
  "type": "Feature",
  "properties": {
    "iso:country":"BE",
    "sg:address":"Menenstraat 18",
    "sg:city":"Sint-jans-molenbeek/molenbeek-saint-jean",
    "sg:orig_category":"Artiesten and kunstenaars",
    "sg:phone":"+32 2 414 28 86",
    "sg:postcode":"1080",
    "sg:province":"Bruxelles-Capitale",
    "wof:name":"M.l. Noullez",
    "wof:placetype":"venue"
},
  "geometry": {"coordinates":[4.3284368515,50.8561897278],"type":"Point"}
}