{
  "type": "Feature",
  "properties": {
    "iso:country":"BE",
    "sg:address":"Albert I Laan 102ba/1",
    "sg:city":"Nieuwpoort",
    "sg:orig_category":"Pain, p\u00e2tisseries and confiseries",
    "sg:phone":"+32 58 24 00 46",
    "sg:postcode":"8620",
    "sg:province":"West-Vlaanderen",
    "wof:name":"Bakkerij Croissy",
    "wof:placetype":"venue"
},
  "geometry": {"coordinates":[2.7215049267,51.1500892639],"type":"Point"}
}