{
  "type": "Feature",
  "properties": {
    "addr:full":"Larenstraat 1 Lummen Limburg 3560",
    "addr:housenumber":"1",
    "addr:postcode":"3560",
    "addr:street":"Larenstraat",
    "iso:country":"BE",
    "sg:address":"Larenstraat 1",
    "sg:city":"Lummen",
    "sg:orig_category":"Plaatsen van vloer- and muurbekleding Schilders",
    "sg:phone":"+32 13 52 32 24",
    "sg:postcode":"3560",
    "sg:province":"Limburg",
    "wof:name":"Eddy Meuwis",
    "wof:placetype":"venue"
},
  "geometry": {"coordinates":[5.1802501678,51.0015983582],"type":"Point"}
}