{
  "type": "Feature",
  "properties": {
    "iso:country":"BE",
    "sg:address":"Antwerpsestraat 131",
    "sg:city":"Niel",
    "sg:classifiers":[
        {
            "category":"Bakery",
            "type":"Food & Drink"
        }
    ],
    "sg:phone":"+32 3 888 14 54",
    "sg:postcode":"2845",
    "sg:province":"Antwerpen",
    "sg:tags":[
        "confectioner",
        "baker"
    ],
    "wof:name":"Broodboetiek Van Der Velde",
    "wof:placetype":"venue"
},
  "geometry": {"coordinates":[4.3317728043,51.1103477478],"type":"Point"}
}