{
  "type": "Feature",
  "properties": {
    "addr:full":"Avenue De L'hippodrome 10 Elsene/ixelles Bruxelles-Capitale 1050",
    "addr:housenumber":"10",
    "addr:postcode":"1050",
    "addr:street":"Avenue De L'Hippodrome",
    "iso:country":"BE",
    "sg:address":"Avenue De L'hippodrome 10",
    "sg:city":"Elsene/ixelles",
    "sg:orig_category":"Boekhouders",
    "sg:phone":"+32 2 649 03 46",
    "sg:postcode":"1050",
    "sg:province":"Bruxelles-Capitale",
    "wof:name":"Piron A.",
    "wof:placetype":"venue"
},
  "geometry": {"coordinates":[4.374341011,50.823551178],"type":"Point"}
}