{
  "type": "Feature",
  "properties": {
    "addr:full":"Rue Du Champ Des Vignes 40 Lasne Brabant Wallon 1380",
    "addr:housenumber":"40",
    "addr:postcode":"1380",
    "addr:street":"Rue Du Champ Des Vignes",
    "iso:country":"BE",
    "sg:address":"Rue Du Champ Des Vignes 40",
    "sg:city":"Lasne",
    "sg:orig_category":"Rusthuizen and serviceflats",
    "sg:phone":"+32 2 634 00 00",
    "sg:postcode":"1380",
    "sg:province":"Brabant Wallon",
    "wof:name":"R\u00c9sidence Lasnoise",
    "wof:placetype":"venue"
},
  "geometry": {"coordinates":[4.4854698181,50.6897697449],"type":"Point"}
}