{
  "type": "Feature",
  "properties": {
    "addr:full":"Golflaan 34 Sint-martens-latem Oost-Vlaanderen 9830",
    "addr:housenumber":"34",
    "addr:postcode":"9830",
    "addr:street":"Golflaan",
    "iso:country":"BE",
    "sg:address":"Golflaan 34",
    "sg:city":"Sint-martens-latem",
    "sg:classifiers":[
        {
            "category":"Building & Trades",
            "subcategory":"Pest Control",
            "type":"Services"
        }
    ],
    "sg:phone":"+32 9 282 29 61",
    "sg:postcode":"9830",
    "sg:province":"Oost-Vlaanderen",
    "sg:tags":[
        "painting",
        "contractor"
    ],
    "wof:name":"Myncke Fernand",
    "wof:placetype":"venue"
},
  "geometry": {"coordinates":[3.6307621002,51.0113716125],"type":"Point"}
}