{
  "type": "Feature",
  "properties": {
    "addr:full":"Quai De L\u00b4industrie 119 Sint-jans-molenbeek/molenbeek-saint-jean Bruxelles-Capitale 1080",
    "addr:housenumber":"119;/",
    "addr:postcode":"1080",
    "addr:street":"Quai De L\u00b4Industrie;Sint-Jans-Molenbeek",
    "iso:country":"BE",
    "sg:address":"Quai De L\u00b4industrie 119",
    "sg:city":"Sint-jans-molenbeek/molenbeek-saint-jean",
    "sg:orig_category":"Agences d'exp\u00e9dition",
    "sg:phone":"+32 2 526 11 11",
    "sg:postcode":"1080",
    "sg:province":"Bruxelles-Capitale",
    "wof:name":"Iii King",
    "wof:placetype":"venue"
},
  "geometry": {"coordinates":[4.3275551796,50.8455963135],"type":"Point"}
}