{
  "type": "Feature",
  "properties": {
    "addr:full":"Justus Lipsiusstraat 18 Leuven Vlaams-Brabant 3000",
    "addr:housenumber":"18",
    "addr:postcode":"3000",
    "addr:street":"Justus Lipsiusstraat",
    "iso:country":"BE",
    "sg:address":"Justus Lipsiusstraat 18",
    "sg:city":"Leuven",
    "sg:orig_category":"Advocaten and juridische adviseurs",
    "sg:phone":"+32 16 22 24 73",
    "sg:postcode":"3000",
    "sg:province":"Vlaams-Brabant",
    "wof:name":"L. Vannoote",
    "wof:placetype":"venue"
},
  "geometry": {"coordinates":[4.7116332054,50.8797340393],"type":"Point"}
}