{
  "type": "Feature",
  "properties": {
    "addr:full":"Kerkstraat 31 Zomergem Oost-Vlaanderen 9930",
    "addr:housenumber":"31",
    "addr:postcode":"9930",
    "addr:street":"Kerkstraat",
    "iso:country":"BE",
    "sg:address":"Kerkstraat 31",
    "sg:city":"Zomergem",
    "sg:orig_category":"V\u00eatements de travail and protection Fab. V\u00eatements",
    "sg:phone":"+32 9 372 70 64",
    "sg:postcode":"9930",
    "sg:province":"Oost-Vlaanderen",
    "wof:name":"Van Hecke Bedrijfskleding",
    "wof:placetype":"venue"
},
  "geometry": {"coordinates":[3.5557730198,51.118221283],"type":"Point"}
}