{
  "type": "Feature",
  "properties": {
    "iso:country":"BE",
    "sg:address":"Generaal Deprezstraat 120",
    "sg:city":"Harelbeke",
    "sg:classifiers":[
        {
            "category":"Parking",
            "subcategory":"Bicycle",
            "type":"Transportation"
        }
    ],
    "sg:phone":"+32 56 22 82 30",
    "sg:postcode":"8530",
    "sg:province":"West-Vlaanderen",
    "sg:tags":[
        "chiropodist"
    ],
    "wof:name":"Dorine D",
    "wof:placetype":"venue"
},
  "geometry": {"coordinates":[3.3141849041,50.8336372375],"type":"Point"}
}