{
  "type": "Feature",
  "properties": {
    "iso:country":"BE",
    "sg:address":"Grand-rue 76",
    "sg:city":"Arlon",
    "sg:classifiers":[
        {
            "category":"Bakery",
            "type":"Food & Drink"
        }
    ],
    "sg:phone":"+32 63 44 64 51",
    "sg:postcode":"6700",
    "sg:province":"Luxembourg",
    "sg:tags":[
        "confectioner",
        "baker"
    ],
    "wof:name":"Didier Tradition",
    "wof:placetype":"venue"
},
  "geometry": {"coordinates":[5.8126749992,49.6823234558],"type":"Point"}
}