{
  "type": "Feature",
  "properties": {
    "addr:full":"Chauss\u00e9e De Gilly 239 Fleurus Hainaut 6220",
    "addr:housenumber":"239",
    "addr:postcode":"6220",
    "addr:street":"Chausse\u0301E De Gilly",
    "iso:country":"BE",
    "sg:address":"Chauss\u00e9e De Gilly 239",
    "sg:city":"Fleurus",
    "sg:classifiers":[
        {
            "category":"Home & Garden",
            "subcategory":"Building Materials",
            "type":"Retail Goods"
        }
    ],
    "sg:phone":"+32 71 35 30 35",
    "sg:postcode":"6220",
    "sg:province":"Hainaut",
    "sg:tags":[
        "house"
    ],
    "wof:name":"Chalets De Pauw",
    "wof:placetype":"venue"
},
  "geometry": {"coordinates":[4.521168232,50.4490432739],"type":"Point"}
}