{
  "type": "Feature",
  "properties": {
    "iso:country":"BE",
    "sg:address":"Morville 28",
    "sg:city":"Durbuy",
    "sg:orig_category":"Agences de publicit\u00e9",
    "sg:phone":"+32 86 21 37 12",
    "sg:postcode":"6940",
    "sg:province":"Luxembourg",
    "wof:name":"Fe. Debecker",
    "wof:placetype":"venue"
},
  "geometry": {"coordinates":[5.4543361664,50.3515777588],"type":"Point"}
}