{
  "type": "Feature",
  "properties": {
    "iso:country":"BE",
    "sg:address":"Nonnebossen 17",
    "sg:city":"Zonnebeke",
    "sg:classifiers":[
        {
            "category":"Building & Trades",
            "subcategory":"Construction",
            "type":"Services"
        }
    ],
    "sg:phone":"+32 57 46 83 11",
    "sg:postcode":"8980",
    "sg:province":"West-Vlaanderen",
    "sg:tags":[
        "carpenter"
    ],
    "wof:name":"Verhaeghe A",
    "wof:placetype":"venue"
},
  "geometry": {"coordinates":[2.9706270695,50.8560371399],"type":"Point"}
}