{
  "type": "Feature",
  "properties": {
    "iso:country":"BE",
    "sg:address":"Engelstraat 21",
    "sg:city":"Gent (sint-amandsberg)",
    "sg:classifiers":[
        {
            "category":"Personal",
            "subcategory":"Barber",
            "type":"Services"
        }
    ],
    "sg:phone":"+32 9 228 10 41",
    "sg:postcode":"9040",
    "sg:province":"Oost-Vlaanderen",
    "sg:tags":[
        "gentleman",
        "salon",
        "-",
        "hairdressing"
    ],
    "wof:name":"Ferrari",
    "wof:placetype":"venue"
},
  "geometry": {"coordinates":[3.7500700951,51.056022644],"type":"Point"}
}