{
  "type": "Feature",
  "properties": {
    "iso:country":"BE",
    "sg:address":"Hoefstadstraat 75",
    "sg:city":"Genk",
    "sg:classifiers":[
        {
            "category":"Bakery",
            "type":"Food & Drink"
        }
    ],
    "sg:phone":"+32 89 35 29 03",
    "sg:postcode":"3600",
    "sg:province":"Limburg",
    "sg:tags":[
        "confectioner",
        "baker"
    ],
    "wof:name":"Wijnen Bakkerij",
    "wof:placetype":"venue"
},
  "geometry": {"coordinates":[5.503385067,50.9793243408],"type":"Point"}
}