{
  "type": "Feature",
  "properties": {
    "iso:country":"BE",
    "sg:address":"Eug\u00c8ne Toussaintstraat 91",
    "sg:city":"Jette/jette",
    "sg:orig_category":"Artsen and specialisten",
    "sg:phone":"+32 2 425 03 50",
    "sg:postcode":"1090",
    "sg:province":"Bruxelles-Capitale",
    "wof:name":"Jean Heijmans",
    "wof:placetype":"venue"
},
  "geometry": {"coordinates":[4.32147789,50.8790397644],"type":"Point"}
}