{
  "type": "Feature",
  "properties": {
    "iso:country":"BE",
    "sg:address":"Vossenberg 10",
    "sg:city":"Damme",
    "sg:orig_category":"Diverse persoonlijke diensten Dranken Immobili\u00ebnkantoren",
    "sg:phone":"+32 50 37 50 39",
    "sg:postcode":"8340",
    "sg:province":"West-Vlaanderen",
    "wof:name":"Peter Van Den Eynde",
    "wof:placetype":"venue"
},
  "geometry": {"coordinates":[3.3047111034,51.2028999329],"type":"Point"}
}