{
  "type": "Feature",
  "properties": {
    "addr:full":"Rue De Saint-l\u00c9ger 1 Mouscron Hainaut 7711",
    "addr:housenumber":"1",
    "addr:postcode":"7711",
    "addr:street":"Rue De Saint-Le\u0301Ger",
    "iso:country":"BE",
    "sg:address":"Rue De Saint-l\u00c9ger 1",
    "sg:city":"Mouscron",
    "sg:orig_category":"Immobili\u00ebnkantoren Verzekeringsmakelaars and experts",
    "sg:phone":"+32 56 48 90 94",
    "sg:postcode":"7711",
    "sg:province":"Hainaut",
    "wof:name":"Despatures Bernard",
    "wof:placetype":"venue"
},
  "geometry": {"coordinates":[3.3034539223,50.7274398804],"type":"Point"}
}