{
  "type": "Feature",
  "properties": {
    "iso:country":"BE",
    "sg:address":"Grote Markt 56",
    "sg:city":"Zelzate",
    "sg:orig_category":"Chaussures. Maroquinerie and articles de voyage",
    "sg:phone":"+32 9 345 52 87",
    "sg:postcode":"9060",
    "sg:province":"Oost-Vlaanderen",
    "wof:name":"Schoenen De Vos",
    "wof:placetype":"venue"
},
  "geometry": {"coordinates":[3.8103950024,51.2005081177],"type":"Point"}
}