{
  "type": "Feature",
  "properties": {
    "iso:country":"BE",
    "sg:address":"Noordlaan 12 A",
    "sg:city":"Torhout",
    "sg:orig_category":"Telecommunicatieapparaten",
    "sg:phone":"+32 50 22 12 12",
    "sg:postcode":"8820",
    "sg:province":"West-Vlaanderen",
    "wof:name":"Fonitel Communicatie",
    "wof:placetype":"venue"
},
  "geometry": {"coordinates":[3.1052899361,51.0742378235],"type":"Point"}
}