{
  "type": "Feature",
  "properties": {
    "addr:full":"Rue De Jausselette 53 Perwez Brabant Wallon 1360",
    "addr:housenumber":"53",
    "addr:postcode":"1360",
    "addr:street":"Rue De Jausselette",
    "iso:country":"BE",
    "sg:address":"Rue De Jausselette 53",
    "sg:city":"Perwez",
    "sg:orig_category":"Schoonmaakbedrijven and ongediertebestrijding",
    "sg:phone":"+32 81 65 73 51",
    "sg:postcode":"1360",
    "sg:province":"Brabant Wallon",
    "wof:name":"S.n.i.p.",
    "wof:placetype":"venue"
},
  "geometry": {"coordinates":[4.8412637711,50.6194572449],"type":"Point"}
}