{
  "type": "Feature",
  "properties": {
    "iso:country":"BE",
    "sg:address":"Dulgaardstraat 6",
    "sg:city":"Bilzen (munsterbilzen)",
    "sg:classifiers":[
        {
            "category":"Wholesale",
            "subcategory":"Plants",
            "type":"Manufacturing & Wholesale Goods"
        }
    ],
    "sg:phone":"+32 89 41 38 64",
    "sg:postcode":"3740",
    "sg:province":"Limburg",
    "sg:tags":[
        "whol",
        "flower",
        "-",
        "grower"
    ],
    "wof:name":"Lathouwers",
    "wof:placetype":"venue"
},
  "geometry": {"coordinates":[5.5367779732,50.8871154785],"type":"Point"}
}