{
  "type": "Feature",
  "properties": {
    "addr:full":"Pitsemburglaan 3 Edegem Antwerpen 2650",
    "addr:housenumber":"3",
    "addr:postcode":"2650",
    "addr:street":"Pitsemburglaan",
    "iso:country":"BE",
    "sg:address":"Pitsemburglaan 3",
    "sg:city":"Edegem",
    "sg:classifiers":[
        {
            "category":"Professional",
            "subcategory":"Accounting & Tax Preparation",
            "type":"Services"
        }
    ],
    "sg:phone":"+32 3 457 46 45",
    "sg:postcode":"2650",
    "sg:province":"Antwerpen",
    "sg:tags":[
        "accountant"
    ],
    "wof:name":"Pollet C",
    "wof:placetype":"venue"
},
  "geometry": {"coordinates":[4.4427862167,51.1601905823],"type":"Point"}
}