{
  "type": "Feature",
  "properties": {
    "iso:country":"BE",
    "sg:address":"Avenue Rogier 18",
    "sg:city":"Li\u00c8ge",
    "sg:orig_category":"M\u00e9decins and sp\u00e9cialistes",
    "sg:phone":"+32 4 252 81 99",
    "sg:postcode":"4000",
    "sg:province":"Li\u00e8ge",
    "wof:name":"Nebojsa Popovic",
    "wof:placetype":"venue"
},
  "geometry": {"coordinates":[5.5697131157,50.6319236755],"type":"Point"}
}