{
  "type": "Feature",
  "properties": {
    "iso:country":"BE",
    "sg:address":"Karel De Stoutelaan 158",
    "sg:city":"Brugge",
    "sg:classifiers":[
        {
            "category":"Health Services",
            "subcategory":"Health Practitioner",
            "type":"Services"
        }
    ],
    "sg:phone":"+32 50 31 93 73",
    "sg:postcode":"8000",
    "sg:province":"West-Vlaanderen",
    "sg:tags":[
        "physiotherapist"
    ],
    "wof:name":"Ysenbrandt Bart",
    "wof:placetype":"venue"
},
  "geometry": {"coordinates":[3.2051439285,51.2153053284],"type":"Point"}
}