{
  "type": "Feature",
  "properties": {
    "iso:country":"BE",
    "sg:address":"Slekkestraat 5",
    "sg:city":"Kortrijk",
    "sg:orig_category":"Agences d'exp\u00e9dition",
    "sg:phone":"+32 56 22 99 13",
    "sg:postcode":"8510",
    "sg:province":"West-Vlaanderen",
    "wof:name":"Hkr Cv",
    "wof:placetype":"venue"
},
  "geometry": {"coordinates":[3.242276907,50.8037109375],"type":"Point"}
}