{
  "type": "Feature",
  "properties": {
    "addr:full":"Oudstrijdersstraat 11 Ranst Antwerpen 2520",
    "addr:housenumber":"11",
    "addr:postcode":"2520",
    "addr:street":"Oudstrijdersstraat",
    "iso:country":"BE",
    "sg:address":"Oudstrijdersstraat 11",
    "sg:city":"Ranst",
    "sg:orig_category":"Installation de menuiserie en bois and plastique",
    "sg:phone":"+32 496 41 49 99",
    "sg:postcode":"2520",
    "sg:province":"Antwerpen",
    "wof:name":"Matze",
    "wof:placetype":"venue"
},
  "geometry": {"coordinates":[4.5951452255,51.2114677429],"type":"Point"}
}