{
  "type": "Feature",
  "properties": {
    "iso:country":"BE",
    "sg:address":"Rue Grand-vin\u00c2ve 22",
    "sg:city":"Seraing",
    "sg:orig_category":"Boucheries",
    "sg:phone":"+32 4 233 82 55",
    "sg:postcode":"4101",
    "sg:province":"Li\u00e8ge",
    "wof:name":"Les Halles De Victoria",
    "wof:placetype":"venue"
},
  "geometry": {"coordinates":[5.5057168007,50.6162910461],"type":"Point"}
}