{
  "type": "Feature",
  "properties": {
    "addr:full":"Durmen 283 Zele Oost-Vlaanderen 9240",
    "addr:housenumber":"283",
    "addr:postcode":"9240",
    "addr:street":"Durmen",
    "iso:country":"BE",
    "sg:address":"Durmen 283",
    "sg:city":"Zele",
    "sg:classifiers":[
        {
            "category":"Professional",
            "subcategory":"Accounting & Tax Preparation",
            "type":"Services"
        }
    ],
    "sg:phone":"+32 52 45 11 96",
    "sg:postcode":"9240",
    "sg:province":"Oost-Vlaanderen",
    "sg:tags":[
        "accountant"
    ],
    "wof:name":"Tony Moreels",
    "wof:placetype":"venue"
},
  "geometry": {"coordinates":[4.0613059998,51.0880661011],"type":"Point"}
}