{
  "type": "Feature",
  "properties": {
    "addr:full":"Plezantstraat 133 Sint-niklaas Oost-Vlaanderen 9100",
    "addr:housenumber":"133",
    "addr:postcode":"9100",
    "addr:street":"Plezantstraat",
    "iso:country":"BE",
    "sg:address":"Plezantstraat 133",
    "sg:city":"Sint-niklaas",
    "sg:classifiers":[
        {
            "category":"Insurance",
            "subcategory":"Insurance Agent",
            "type":"Services"
        }
    ],
    "sg:phone":"+32 3 776 60 14",
    "sg:postcode":"9100",
    "sg:province":"Oost-Vlaanderen",
    "sg:tags":[
        "broker"
    ],
    "wof:name":"Veireman Bvba",
    "wof:placetype":"venue"
},
  "geometry": {"coordinates":[4.1342158318,51.1669540405],"type":"Point"}
}