{
  "type": "Feature",
  "properties": {
    "iso:country":"BE",
    "sg:address":"Chauss\u00e9e De Soignies 58",
    "sg:city":"Le Roeulx",
    "sg:classifiers":[
        {
            "category":"Freight",
            "type":"Transportation"
        }
    ],
    "sg:phone":"+32 64 77 59 27",
    "sg:postcode":"7070",
    "sg:province":"Hainaut",
    "sg:tags":[
        "-",
        "transport"
    ],
    "wof:name":"T.s.c. Transports & Genie",
    "wof:placetype":"venue"
},
  "geometry": {"coordinates":[4.1044111252,50.5107269287],"type":"Point"}
}