{
  "type": "Feature",
  "properties": {
    "addr:full":"Liersesteenweg 254 Heist-op-den-berg Antwerpen 2220",
    "addr:housenumber":"254",
    "addr:postcode":"2220",
    "addr:street":"Liersesteenweg",
    "iso:country":"BE",
    "sg:address":"Liersesteenweg 254",
    "sg:city":"Heist-op-den-berg",
    "sg:classifiers":[
        {
            "category":"Health Services",
            "subcategory":"Health Practitioner",
            "type":"Services"
        }
    ],
    "sg:phone":"+32 15 25 07 58",
    "sg:postcode":"2220",
    "sg:province":"Antwerpen",
    "sg:tags":[
        "physiotherapist"
    ],
    "wof:name":"Buls P",
    "wof:placetype":"venue"
},
  "geometry": {"coordinates":[4.7001829147,51.0672912598],"type":"Point"}
}