{
  "type": "Feature",
  "properties": {
    "iso:country":"BE",
    "sg:address":"Rue De Namur 7",
    "sg:city":"Philippeville",
    "sg:classifiers":[
        {
            "category":"Shopping",
            "subcategory":"Clothing, Apparel, & Fashions",
            "type":"Retail Goods"
        }
    ],
    "sg:phone":"+32 71 66 61 97",
    "sg:postcode":"5600",
    "sg:province":"Namur",
    "sg:tags":[
        "lady",
        "clothing",
        "-"
    ],
    "wof:name":"Henrard G",
    "wof:placetype":"venue"
},
  "geometry": {"coordinates":[4.5444908142,50.1966362],"type":"Point"}
}