{
  "type": "Feature",
  "properties": {
    "iso:country":"BE",
    "sg:address":"Slaghoutstraat 8",
    "sg:city":"Genk",
    "sg:orig_category":"Jardinage. Fleurs and plantes",
    "sg:phone":"+32 89 30 43 90",
    "sg:postcode":"3600",
    "sg:province":"Limburg",
    "wof:name":"Peter Prenen",
    "wof:placetype":"venue"
},
  "geometry": {"coordinates":[5.482583046,50.925201416],"type":"Point"}
}