{
  "type": "Feature",
  "properties": {
    "addr:full":"Avenue Du Cimeti\u00e8re De Bruxelles 29 Bruxelles (evere) Bruxelles-Capitale 1140",
    "addr:housenumber":"29",
    "addr:postcode":"1140",
    "addr:street":"Avenue Du Cimetie\u0300Re De Bruxelles",
    "iso:country":"BE",
    "sg:address":"Avenue Du Cimeti\u00e8re De Bruxelles 29",
    "sg:city":"Bruxelles (evere)",
    "sg:classifiers":[
        {
            "category":"Health Services",
            "subcategory":"Doctor",
            "type":"Services"
        }
    ],
    "sg:phone":"+32 2 726 71 81",
    "sg:postcode":"1140",
    "sg:province":"Bruxelles-Capitale",
    "sg:tags":[
        "medicinephysicians",
        "surgeon"
    ],
    "wof:name":"Gosset Christophe",
    "wof:placetype":"venue"
},
  "geometry": {"coordinates":[4.4148278236,50.8599700928],"type":"Point"}
}