{
  "type": "Feature",
  "properties": {
    "iso:country":"BE",
    "sg:address":"Boulevard De L'humanit\u00e9 104",
    "sg:city":"Bruxelles (forest)",
    "sg:classifiers":[
        {
            "category":"Mining & Drilling",
            "type":"Manufacturing & Wholesale Goods"
        }
    ],
    "sg:phone":"+32 2 344 02 13",
    "sg:postcode":"1190",
    "sg:province":"Bruxelles-Capitale",
    "sg:tags":[
        "boring",
        "well"
    ],
    "wof:name":"Smet F & C",
    "wof:placetype":"venue"
},
  "geometry": {"coordinates":[4.3150248528,50.820728302],"type":"Point"}
}