{
  "type": "Feature",
  "properties": {
    "iso:country":"BE",
    "sg:address":"Grenadierslaan 8b4",
    "sg:city":"Elsene/ixelles",
    "sg:orig_category":"Beheer onroerend goed",
    "sg:phone":"+32 2 673 90 82",
    "sg:postcode":"1050",
    "sg:province":"Bruxelles-Capitale",
    "wof:name":"De Maegd",
    "wof:placetype":"venue"
},
  "geometry": {"coordinates":[4.3905677795,50.810344696],"type":"Point"}
}