{
  "type": "Feature",
  "properties": {
    "iso:country":"BE",
    "sg:address":"Antwerpsesteenweg 365",
    "sg:city":"Brussel/bruxelles",
    "sg:orig_category":"Artsen and specialisten",
    "sg:phone":"+32 2 203 34 03",
    "sg:postcode":"1000",
    "sg:province":"Bruxelles-Capitale",
    "wof:name":"Yves Labar",
    "wof:placetype":"venue"
},
  "geometry": {"coordinates":[4.3591871262,50.8677558899],"type":"Point"}
}