{
  "type": "Feature",
  "properties": {
    "addr:full":"Woluwestraat 4 Machelen Vlaams-Brabant 1830",
    "addr:housenumber":"4",
    "addr:postcode":"1830",
    "addr:street":"Woluwestraat",
    "iso:country":"BE",
    "sg:address":"Woluwestraat 4",
    "sg:city":"Machelen",
    "sg:orig_category":"Postkantoren Verzekeringsmakelaars and experts",
    "sg:phone":"+32 2 251 19 72",
    "sg:postcode":"1830",
    "sg:province":"Vlaams-Brabant",
    "wof:name":"De Post",
    "wof:placetype":"venue"
},
  "geometry": {"coordinates":[4.4332971573,50.91248703],"type":"Point"}
}