{
  "type": "Feature",
  "properties": {
    "addr:full":"Rue De L\u00b4eglise Saint Martin 136 Bruxelles Bruxelles-Capitale 1083",
    "addr:housenumber":"136",
    "addr:postcode":"1083",
    "addr:street":"Rue De L\u00b4Eglise Saint",
    "iso:country":"BE",
    "sg:address":"Rue De L\u00b4eglise Saint Martin 136",
    "sg:city":"Bruxelles",
    "sg:orig_category":"Huisdieren and benodigdheden",
    "sg:phone":"+32 2 425 65 69",
    "sg:postcode":"1083",
    "sg:province":"Bruxelles-Capitale",
    "wof:name":"Le Martin P\u00cacheur",
    "wof:placetype":"venue"
},
  "geometry": {"coordinates":[4.3133587837,50.873260498],"type":"Point"}
}