{
  "type": "Feature",
  "properties": {
    "addr:full":"Rue Esseghem 76 Bruxelles (jette) Bruxelles-Capitale 1090",
    "addr:housenumber":"76",
    "addr:postcode":"1090",
    "addr:street":"Rue Esseghem",
    "iso:country":"BE",
    "sg:address":"Rue Esseghem 76",
    "sg:city":"Bruxelles (jette)",
    "sg:classifiers":[
        {
            "category":"Personal",
            "subcategory":"Nail Salon",
            "type":"Services"
        }
    ],
    "sg:phone":"+32 2 428 57 68",
    "sg:postcode":"1090",
    "sg:province":"Bruxelles-Capitale",
    "sg:tags":[
        "pedicure"
    ],
    "wof:name":"Doumont E",
    "wof:placetype":"venue"
},
  "geometry": {"coordinates":[4.3361301422,50.8769874573],"type":"Point"}
}