{
  "type": "Feature",
  "properties": {
    "addr:full":"Rue De Husquet 85 Dison Li\u00e8ge 4820",
    "addr:housenumber":"85",
    "addr:postcode":"4820",
    "addr:street":"Rue De Husquet",
    "iso:country":"BE",
    "sg:address":"Rue De Husquet 85",
    "sg:city":"Dison",
    "sg:orig_category":"Boekhouders",
    "sg:phone":"+32 87 33 51 87",
    "sg:postcode":"4820",
    "sg:province":"Li\u00e8ge",
    "wof:name":"Cataldo Ferrara",
    "wof:placetype":"venue"
},
  "geometry": {"coordinates":[5.8442292213,50.6067085266],"type":"Point"}
}