{
  "type": "Feature",
  "properties": {
    "addr:full":"Rue Puits-en-sock 48-50 Li\u00c8ge Li\u00e8ge 4020",
    "addr:postcode":"48-50;4020",
    "addr:street":"Rue Puits-En-Sock",
    "iso:country":"BE",
    "sg:address":"Rue Puits-en-sock 48-50",
    "sg:city":"Li\u00c8ge",
    "sg:classifiers":[
        {
            "category":"Personal",
            "subcategory":"Beauty Salon",
            "type":"Services"
        }
    ],
    "sg:phone":"+32 4 343 76 30",
    "sg:postcode":"4020",
    "sg:province":"Li\u00e8ge",
    "sg:tags":[
        "de",
        "coiffure"
    ],
    "wof:name":"Beauty Space",
    "wof:placetype":"venue"
},
  "geometry": {"coordinates":[5.5831432343,50.6404075623],"type":"Point"}
}