{
  "type": "Feature",
  "properties": {
    "addr:full":"Rue De Verviers 29 Li\u00c8ge Li\u00e8ge 4020",
    "addr:housenumber":"29",
    "addr:postcode":"4020",
    "addr:street":"Rue De Verviers",
    "iso:country":"BE",
    "sg:address":"Rue De Verviers 29",
    "sg:city":"Li\u00c8ge",
    "sg:orig_category":"Artsen and specialisten",
    "sg:phone":"+32 4 343 38 05",
    "sg:postcode":"4020",
    "sg:province":"Li\u00e8ge",
    "wof:name":"Fernand Scherber",
    "wof:placetype":"venue"
},
  "geometry": {"coordinates":[5.5854029655,50.623249054],"type":"Point"}
}