{
  "type": "Feature",
  "properties": {
    "addr:full":"Sint-jansbergstraat 7 Halen Limburg 3545",
    "addr:housenumber":"7",
    "addr:postcode":"3545",
    "addr:street":"Sint-Jansbergstraat",
    "iso:country":"BE",
    "sg:address":"Sint-jansbergstraat 7",
    "sg:city":"Halen",
    "sg:classifiers":[
        {
            "category":"Insurance",
            "subcategory":"Insurance Agent",
            "type":"Services"
        }
    ],
    "sg:phone":"+32 13 44 35 50",
    "sg:postcode":"3545",
    "sg:province":"Limburg",
    "sg:tags":[
        "verzekeringsmakelaars",
        "expert"
    ],
    "wof:name":"Bureau Jara",
    "wof:placetype":"venue"
},
  "geometry": {"coordinates":[5.1127400398,50.9482154846],"type":"Point"}
}