{
  "type": "Feature",
  "properties": {
    "addr:full":"Wortegemstraat 14 Oudenaarde Oost-Vlaanderen 9700",
    "addr:housenumber":"14",
    "addr:postcode":"9700",
    "addr:street":"Wortegemstraat",
    "iso:country":"BE",
    "sg:address":"Wortegemstraat 14",
    "sg:city":"Oudenaarde",
    "sg:orig_category":"Enseignement maternel and primaire",
    "sg:phone":"+32 55 31 70 66",
    "sg:postcode":"9700",
    "sg:province":"Oost-Vlaanderen",
    "wof:name":"Basisschool",
    "wof:placetype":"venue"
},
  "geometry": {"coordinates":[3.5938880444,50.8516998291],"type":"Point"}
}