{
  "type": "Feature",
  "properties": {
    "addr:full":"Ambachtsweg 1 Gingelom Limburg 3890",
    "addr:housenumber":"1",
    "addr:postcode":"3890",
    "addr:street":"Ambachtsweg",
    "iso:country":"BE",
    "sg:address":"Ambachtsweg 1",
    "sg:city":"Gingelom",
    "sg:classifiers":[
        {
            "category":"Home & Garden",
            "subcategory":"Kitchen Supply",
            "type":"Retail Goods"
        }
    ],
    "sg:phone":"+32 11 83 25 70",
    "sg:postcode":"3890",
    "sg:province":"Limburg",
    "sg:tags":[
        "installation"
    ],
    "wof:name":"Aquabathrooms",
    "wof:placetype":"venue"
},
  "geometry": {"coordinates":[5.1249141693,50.7356338501],"type":"Point"}
}