{
  "type": "Feature",
  "properties": {
    "addr:full":"Raymond Beaucarnestraat 121 Moeskroen/mouscron Hainaut 7700",
    "addr:housenumber":"121",
    "addr:postcode":"7700",
    "addr:street":"Beaucarnestraat",
    "iso:country":"BE",
    "sg:address":"Raymond Beaucarnestraat 121",
    "sg:city":"Moeskroen/mouscron",
    "sg:orig_category":"Voertuigen",
    "sg:phone":"+32 56 33 45 88",
    "sg:postcode":"7700",
    "sg:province":"Hainaut",
    "wof:name":"J.f. Valaeys",
    "wof:placetype":"venue"
},
  "geometry": {"coordinates":[3.2440268993,50.7448425293],"type":"Point"}
}