{
  "type": "Feature",
  "properties": {
    "addr:full":"Stationsstraat 6 Sint-truiden Limburg 3800",
    "addr:housenumber":"6",
    "addr:postcode":"3800",
    "addr:street":"Stationsstraat",
    "iso:country":"BE",
    "sg:address":"Stationsstraat 6",
    "sg:city":"Sint-truiden",
    "sg:classifiers":[
        {
            "category":"Autos & Motor Vehicles",
            "subcategory":"Boat Sales",
            "type":"Retail Goods"
        }
    ],
    "sg:phone":"+32 11 72 35 90",
    "sg:postcode":"3800",
    "sg:province":"Limburg",
    "sg:tags":[
        "balloon"
    ],
    "wof:name":"Ballonneke",
    "wof:placetype":"venue"
},
  "geometry": {"coordinates":[5.1794028282,50.8158416748],"type":"Point"}
}