{
  "type": "Feature",
  "properties": {
    "addr:full":"Ommegangstraat 15 Kluisbergen Oost-Vlaanderen 9690",
    "addr:housenumber":"15",
    "addr:postcode":"9690",
    "addr:street":"Ommegangstraat",
    "iso:country":"BE",
    "sg:address":"Ommegangstraat 15",
    "sg:city":"Kluisbergen",
    "sg:classifiers":[
        {
            "category":"Arena",
            "subcategory":"Sports Club",
            "type":"Entertainment"
        }
    ],
    "sg:phone":"+32 55 38 87 69",
    "sg:postcode":"9690",
    "sg:province":"Oost-Vlaanderen",
    "sg:tags":[
        "terrain",
        "hors",
        "de",
        "installation",
        "sportifs"
    ],
    "wof:name":"Kwaremont Sportief",
    "wof:placetype":"venue"
},
  "geometry": {"coordinates":[3.5239078999,50.7788314819],"type":"Point"}
}