{
  "type": "Feature",
  "properties": {
    "iso:country":"BE",
    "sg:address":"Bleregemstraat 130",
    "sg:city":"Affligem",
    "sg:orig_category":"Installatie van houten of kunststof schrijnwerk Installatie van metalen schrijnwerk",
    "sg:phone":"+32 53 66 71 94",
    "sg:postcode":"1790",
    "sg:province":"Vlaams-Brabant",
    "wof:name":"Alu P V C Antoine",
    "wof:placetype":"venue"
},
  "geometry": {"coordinates":[4.1167030334,50.9183692932],"type":"Point"}
}