{
  "type": "Feature",
  "properties": {
    "iso:country":"BE",
    "sg:address":"Houbenstraat 23",
    "sg:city":"Kortenberg",
    "sg:orig_category":"Peinture. Eclairage et \u00e9quipements du foyer. Rev\u00eatements pour sols and murs",
    "sg:phone":"+32 2 758 02 40",
    "sg:postcode":"3070",
    "sg:province":"Vlaams-Brabant",
    "wof:name":"Sherwin Paint. & Decorat.",
    "wof:placetype":"venue"
},
  "geometry": {"coordinates":[4.535091877,50.889289856],"type":"Point"}
}