{
  "type": "Feature",
  "properties": {
    "addr:full":"Plein 64 Vloesberg/flobecq Hainaut 7880",
    "addr:housenumber":"64",
    "addr:postcode":"7880",
    "addr:street":"Plein",
    "iso:country":"BE",
    "sg:address":"Plein 64",
    "sg:city":"Vloesberg/flobecq",
    "sg:classifiers":[
        {
            "category":"Fast Food",
            "type":"Food & Drink"
        }
    ],
    "sg:phone":"+32 68 44 92 02",
    "sg:postcode":"7880",
    "sg:province":"Hainaut",
    "sg:tags":[
        "meeneem",
        "restaurant"
    ],
    "wof:name":"La Friterie Mac Dani\u00cbl",
    "wof:placetype":"venue"
},
  "geometry": {"coordinates":[3.7384300232,50.7368011475],"type":"Point"}
}