{
  "type": "Feature",
  "properties": {
    "iso:country":"BE",
    "sg:address":"Chauss\u00e9e De Waterloo 1110",
    "sg:city":"Bruxelles (uccle)",
    "sg:classifiers":[
        {
            "category":"Home & Garden",
            "subcategory":"Carpets & Floor Coverings",
            "type":"Retail Goods"
        }
    ],
    "sg:phone":"+32 2 375 52 32",
    "sg:postcode":"1180",
    "sg:province":"Bruxelles-Capitale",
    "sg:tags":[
        "parquet"
    ],
    "wof:name":"Tout Parquet Ransy Et Fr\u00e8res Sprl",
    "wof:placetype":"venue"
},
  "geometry": {"coordinates":[4.3754138947,50.7973403931],"type":"Point"}
}