{
  "type": "Feature",
  "properties": {
    "addr:full":"Rue Albert Ier 280 Erquelinnes Hainaut 6560",
    "addr:housenumber":"280",
    "addr:postcode":"6560",
    "addr:street":"Rue Albert Ier",
    "iso:country":"BE",
    "sg:address":"Rue Albert Ier 280",
    "sg:city":"Erquelinnes",
    "sg:orig_category":"Banques and organismes de cr\u00e9dit",
    "sg:phone":"+32 71 55 77 22",
    "sg:postcode":"6560",
    "sg:province":"Hainaut",
    "wof:name":"Citibank",
    "wof:placetype":"venue"
},
  "geometry": {"coordinates":[4.1146459579,50.3052864075],"type":"Point"}
}