{
  "type": "Feature",
  "properties": {
    "addr:full":"Clos De La Caranda 18 Waterloo Brabant Wallon 1410",
    "addr:housenumber":"18",
    "addr:postcode":"1410",
    "addr:street":"Clos De La Caranda",
    "iso:country":"BE",
    "sg:address":"Clos De La Caranda 18",
    "sg:city":"Waterloo",
    "sg:orig_category":"Artsen and specialisten",
    "sg:phone":"+32 2 351 06 92",
    "sg:postcode":"1410",
    "sg:province":"Brabant Wallon",
    "wof:name":"Longomo Emponza",
    "wof:placetype":"venue"
},
  "geometry": {"coordinates":[4.365776062,50.7091827393],"type":"Point"}
}