{
  "type": "Feature",
  "properties": {
    "addr:full":"Rue Principale 8 Clavier (terwagne) Li\u00e8ge 4560",
    "addr:housenumber":"8",
    "addr:postcode":"4560",
    "addr:street":"Rue Principale;Terwagne",
    "iso:country":"BE",
    "sg:address":"Rue Principale 8",
    "sg:city":"Clavier (terwagne)",
    "sg:classifiers":[
        {
            "category":"Health Services",
            "subcategory":"Doctor",
            "type":"Services"
        }
    ],
    "sg:phone":"+32 85 41 33 83",
    "sg:postcode":"4560",
    "sg:province":"Li\u00e8ge",
    "sg:tags":[
        "medicinephysicians",
        "surgeon"
    ],
    "wof:name":"Darimont Philippe",
    "wof:placetype":"venue"
},
  "geometry": {"coordinates":[5.3502559662,50.4450187683],"type":"Point"}
}