{
  "type": "Feature",
  "properties": {
    "iso:country":"BE",
    "sg:address":"Tweehuizenweg 77",
    "sg:city":"Sint-lambrechts-woluwe/woluwe-saint-lambert",
    "sg:orig_category":"Sportclubs",
    "sg:phone":"+32 2 772 24 96",
    "sg:postcode":"1200",
    "sg:province":"Bruxelles-Capitale",
    "wof:name":"Wolu Blue Devils Bxl",
    "wof:placetype":"venue"
},
  "geometry": {"coordinates":[4.4272279739,50.8515968323],"type":"Point"}
}