{
  "type": "Feature",
  "properties": {
    "iso:country":"BE",
    "sg:address":"Heikant 23",
    "sg:city":"Hamont-achel",
    "sg:classifiers":[
        {
            "category":"Banks & Credit Unions",
            "subcategory":"Investment Brokerage",
            "type":"Services"
        }
    ],
    "sg:phone":"+32 11 64 58 72",
    "sg:postcode":"3930",
    "sg:province":"Limburg",
    "sg:tags":[
        "appliance",
        "examination",
        "gynaecologist"
    ],
    "wof:name":"Gynetics Medical Products Nv",
    "wof:placetype":"venue"
},
  "geometry": {"coordinates":[5.4703841209,51.2773323059],"type":"Point"}
}