{
  "type": "Feature",
  "properties": {
    "addr:full":"Neerbroek 109b18 Zwijndrecht Antwerpen 2070",
    "addr:housenumber":"109b18",
    "addr:postcode":"2070",
    "addr:street":"Neerbroek",
    "iso:country":"BE",
    "sg:address":"Neerbroek 109b18",
    "sg:city":"Zwijndrecht",
    "sg:orig_category":"Woningbouw",
    "sg:phone":"+32 3 253 09 97",
    "sg:postcode":"2070",
    "sg:province":"Antwerpen",
    "wof:name":"Construbel",
    "wof:placetype":"venue"
},
  "geometry": {"coordinates":[4.3390622139,51.2210197449],"type":"Point"}
}