{
  "type": "Feature",
  "properties": {
    "iso:country":"BE",
    "sg:address":"Emiel Clauslaan 67",
    "sg:city":"Deinze (astene)",
    "sg:classifiers":[
        {
            "category":"Real Estate",
            "subcategory":"Architect",
            "type":"Services"
        }
    ],
    "sg:phone":"+32 9 386 20 82",
    "sg:postcode":"9800",
    "sg:province":"Oost-Vlaanderen",
    "wof:name":"Saverys B",
    "wof:placetype":"venue"
},
  "geometry": {"coordinates":[3.5274240971,50.9844474792],"type":"Point"}
}