{
  "type": "Feature",
  "properties": {
    "iso:country":"BE",
    "sg:address":"Lindenlaan 68",
    "sg:city":"Beerse",
    "sg:classifiers":[
        {
            "category":"Shopping",
            "subcategory":"Bicycles & Sporting Goods",
            "type":"Retail Goods"
        }
    ],
    "sg:phone":"+32 14 61 15 29",
    "sg:postcode":"2340",
    "sg:province":"Antwerpen",
    "sg:tags":[
        "article",
        "de",
        "sport",
        "camping"
    ],
    "wof:name":"Huis De Visser",
    "wof:placetype":"venue"
},
  "geometry": {"coordinates":[4.8502831459,51.3191719055],"type":"Point"}
}