{
  "type": "Feature",
  "properties": {
    "iso:country":"BE",
    "sg:address":"Houtemstraat 54",
    "sg:city":"Heuvelland",
    "sg:orig_category":"Eleveurs de bovins. Eleveurs and marchands de porcs",
    "sg:phone":"+32 57 44 50 90",
    "sg:postcode":"8953",
    "sg:province":"West-Vlaanderen",
    "wof:name":"Gilbert Duflo",
    "wof:placetype":"venue"
},
  "geometry": {"coordinates":[2.8820250034,50.7857894897],"type":"Point"}
}