{
  "type": "Feature",
  "properties": {
    "iso:country":"BE",
    "sg:address":"Molenstraat 22",
    "sg:city":"Zonnebeke",
    "sg:orig_category":"Huishoudapparaten, televisies and radio's",
    "sg:phone":"+32 51 77 06 26",
    "sg:postcode":"8980",
    "sg:province":"West-Vlaanderen",
    "wof:name":"Luc Decadt",
    "wof:placetype":"venue"
},
  "geometry": {"coordinates":[3.021531105,50.9017982483],"type":"Point"}
}