{
  "type": "Feature",
  "properties": {
    "iso:country":"BE",
    "sg:address":"Leestsesteenweg 42",
    "sg:city":"Mechelen",
    "sg:orig_category":"Parfumeries. Instituts de beaut\u00e9",
    "sg:phone":"+32 475 62 55 98",
    "sg:postcode":"2800",
    "sg:province":"Antwerpen",
    "wof:name":"Instituut Christel",
    "wof:placetype":"venue"
},
  "geometry": {"coordinates":[4.4384651184,51.0394058228],"type":"Point"}
}