{
  "type": "Feature",
  "properties": {
    "addr:full":"Rue De La Clef 46b1 Soumagne Li\u00e8ge 4633",
    "addr:housenumber":"46b1",
    "addr:postcode":"4633",
    "addr:street":"Rue De La Clef",
    "iso:country":"BE",
    "sg:address":"Rue De La Clef 46b1",
    "sg:city":"Soumagne",
    "sg:orig_category":"Benzinestations and brandstoffen",
    "sg:phone":"+32 4 377 44 04",
    "sg:postcode":"4633",
    "sg:province":"Li\u00e8ge",
    "wof:name":"Eco + Petrochimicla",
    "wof:placetype":"venue"
},
  "geometry": {"coordinates":[5.7550969124,50.636302948],"type":"Point"}
}