{
  "type": "Feature",
  "properties": {
    "iso:country":"BE",
    "sg:address":"Erasmuslaan 36",
    "sg:city":"Hasselt",
    "sg:orig_category":"Fotografen and fotostudio's",
    "sg:phone":"+32 11 22 88 91",
    "sg:postcode":"3500",
    "sg:province":"Limburg",
    "wof:name":"Guido Raedschelders",
    "wof:placetype":"venue"
},
  "geometry": {"coordinates":[5.35435009,50.9490318298],"type":"Point"}
}