{
  "type": "Feature",
  "properties": {
    "iso:country":"BE",
    "sg:address":"De Klerckstraat 41",
    "sg:city":"Knokke-heist (knokke)",
    "sg:classifiers":[
        {
            "category":"Airport",
            "subcategory":"International",
            "type":"Transportation"
        }
    ],
    "sg:phone":"+32 50 62 35 79",
    "sg:postcode":"8300",
    "sg:province":"West-Vlaanderen",
    "sg:tags":[
        "-",
        "transport"
    ],
    "wof:name":"Alan Franklin Transport Nv",
    "wof:placetype":"venue"
},
  "geometry": {"coordinates":[3.2948288918,51.3406105042],"type":"Point"}
}