{
  "type": "Feature",
  "properties": {
    "addr:full":"Boekhoutstraat 20 Gingelom Limburg 3890",
    "addr:housenumber":"20",
    "addr:postcode":"3890",
    "addr:street":"Boekhoutstraat",
    "iso:country":"BE",
    "sg:address":"Boekhoutstraat 20",
    "sg:city":"Gingelom",
    "sg:orig_category":"Fruitteelt",
    "sg:phone":"+32 11 48 50 39",
    "sg:postcode":"3890",
    "sg:province":"Limburg",
    "wof:name":"Armand Herckens",
    "wof:placetype":"venue"
},
  "geometry": {"coordinates":[5.232872963,50.7465705872],"type":"Point"}
}