{
  "type": "Feature",
  "properties": {
    "iso:country":"BE",
    "sg:address":"Dijkstraat 43",
    "sg:city":"Dendermonde",
    "sg:orig_category":"M\u00e9decins and sp\u00e9cialistes",
    "sg:phone":"+32 52 21 52 53",
    "sg:postcode":"9200",
    "sg:province":"Oost-Vlaanderen",
    "wof:name":"Gezondheidscentrum",
    "wof:placetype":"venue"
},
  "geometry": {"coordinates":[4.1010761261,51.0306625366],"type":"Point"}
}