{
  "type": "Feature",
  "properties": {
    "addr:full":"Rue Du Cheval Blanc 78 Plombieres/plombieres Li\u00e8ge 4852",
    "addr:housenumber":"78",
    "addr:postcode":"4852",
    "addr:street":"Rue Du Cheval Blanc",
    "iso:country":"BE",
    "sg:address":"Rue Du Cheval Blanc 78",
    "sg:city":"Plombieres/plombieres",
    "sg:orig_category":"HERSTELLING ELEKTRISCHE HUISHOUDAPPARATEN",
    "sg:phone":"+32 87 78 43 37",
    "sg:postcode":"4852",
    "sg:province":"Li\u00e8ge",
    "wof:name":"Electro-home Service",
    "wof:placetype":"venue"
},
  "geometry": {"coordinates":[5.9467201233,50.7356910706],"type":"Point"}
}