{
  "type": "Feature",
  "properties": {
    "iso:country":"BE",
    "sg:address":"Zandstraat 2",
    "sg:city":"Zemst",
    "sg:orig_category":"Sportcentra",
    "sg:phone":"+32 15 61 04 16",
    "sg:postcode":"1981",
    "sg:province":"Vlaams-Brabant",
    "wof:name":"Sporthal Hofstade Heide",
    "wof:placetype":"venue"
},
  "geometry": {"coordinates":[4.4962787628,50.9865112305],"type":"Point"}
}