{
  "type": "Feature",
  "properties": {
    "iso:country":"BE",
    "sg:address":"Rue Royale 55",
    "sg:city":"Brussel/bruxelles",
    "sg:orig_category":"Agences immobili\u00e8res. Administration d'immeubles. Services divers aux entreprises",
    "sg:phone":"+32 2 219 23 33",
    "sg:postcode":"1000",
    "sg:province":"Bruxelles-Capitale",
    "wof:name":"Bureau Toby",
    "wof:placetype":"venue"
},
  "geometry": {"coordinates":[4.363902092,50.8493156433],"type":"Point"}
}