{
  "type": "Feature",
  "properties": {
    "iso:country":"BE",
    "sg:address":"Karel Bulsstraat 12",
    "sg:city":"Brussel/bruxelles",
    "sg:orig_category":"Geschenken and souvenirs Verlichting and huishoudartikelen",
    "sg:phone":"+32 2 512 14 64",
    "sg:postcode":"1000",
    "sg:province":"Bruxelles-Capitale",
    "wof:name":"Belgium Lace",
    "wof:placetype":"venue"
},
  "geometry": {"coordinates":[4.3521351814,50.8461303711],"type":"Point"}
}