{
  "type": "Feature",
  "properties": {
    "addr:full":"Rue Cahos 47 Tournai Hainaut 7520",
    "addr:housenumber":"47",
    "addr:postcode":"7520",
    "addr:street":"Rue Cahos",
    "iso:country":"BE",
    "sg:address":"Rue Cahos 47",
    "sg:city":"Tournai",
    "sg:classifiers":[
        {
            "category":"Restaurant",
            "type":"Food & Drink"
        }
    ],
    "sg:phone":"+32 69 35 25 94",
    "sg:postcode":"7520",
    "sg:province":"Hainaut",
    "sg:tags":[
        "organisation",
        "de",
        "f\u00eates",
        "catering"
    ],
    "wof:name":"La Petite Assiette",
    "wof:placetype":"venue"
},
  "geometry": {"coordinates":[3.2488980293,50.6511535645],"type":"Point"}
}