{
  "type": "Feature",
  "properties": {
    "iso:country":"BE",
    "sg:address":"Rue Des Waibes 62",
    "sg:city":"Lobbes",
    "sg:orig_category":"Maisons de vacances",
    "sg:phone":"+32 71 59 02 63",
    "sg:postcode":"6540",
    "sg:province":"Hainaut",
    "wof:name":"Druenne",
    "wof:placetype":"venue"
},
  "geometry": {"coordinates":[4.2785029411,50.3609962463],"type":"Point"}
}