{
  "type": "Feature",
  "properties": {
    "addr:full":"Vesten 11 Geraardsbergen Oost-Vlaanderen 9500",
    "addr:housenumber":"11",
    "addr:postcode":"9500",
    "addr:street":"Vesten",
    "iso:country":"BE",
    "sg:address":"Vesten 11",
    "sg:city":"Geraardsbergen",
    "sg:classifiers":[
        {
            "category":"Industrial Area",
            "type":"Public Place"
        }
    ],
    "sg:phone":"+32 54 41 24 17",
    "sg:postcode":"9500",
    "sg:province":"Oost-Vlaanderen",
    "sg:tags":[
        "-",
        "lighting"
    ],
    "wof:name":"Gfm Nv",
    "wof:placetype":"venue"
},
  "geometry": {"coordinates":[3.8853058815,50.7719535828],"type":"Point"}
}