{
  "type": "Feature",
  "properties": {
    "iso:country":"BE",
    "sg:address":"Pedestraat 70",
    "sg:city":"Sint-pieters-leeuw (vlezenbeek)",
    "sg:classifiers":[
        {
            "category":"Professional",
            "type":"Services"
        }
    ],
    "sg:phone":"+32 2 569 31 95",
    "sg:postcode":"1602",
    "sg:province":"Vlaams-Brabant",
    "sg:tags":[
        "forestry",
        "agriculture",
        "-",
        "auctioneer"
    ],
    "wof:name":"Schoukens M Cv",
    "wof:placetype":"venue"
},
  "geometry": {"coordinates":[4.2238998413,50.8160362244],"type":"Point"}
}