{
  "type": "Feature",
  "properties": {
    "iso:country":"BE",
    "sg:address":"Bommelsrede 61",
    "sg:city":"Destelbergen",
    "sg:orig_category":"Rundveehouders Varkenskwekers",
    "sg:phone":"+32 9 252 13 36",
    "sg:postcode":"9070",
    "sg:province":"Oost-Vlaanderen",
    "wof:name":"Arsene Boterdaele",
    "wof:placetype":"venue"
},
  "geometry": {"coordinates":[3.832930088,51.0016784668],"type":"Point"}
}