{
  "type": "Feature",
  "properties": {
    "iso:country":"BE",
    "sg:address":"Rue Jean Vinois 16",
    "sg:city":"Ellezelles",
    "sg:orig_category":"R\u00e9parations d'appareils \u00e9lectrom\u00e9nagers. Electrom\u00e9nager, t\u00e9l\u00e9visions and radios. Mat\u00e9riel de T\u00e9l\u00e9com",
    "sg:phone":"+32 68 54 26 44",
    "sg:postcode":"7890",
    "sg:province":"Hainaut",
    "wof:name":"G. Vandorpe",
    "wof:placetype":"venue"
},
  "geometry": {"coordinates":[3.681137085,50.7331008911],"type":"Point"}
}