{
  "type": "Feature",
  "properties": {
    "iso:country":"BE",
    "sg:address":"Lamoraal Van Egmontstr. 23",
    "sg:city":"Gent",
    "sg:orig_category":"Antiquit\u00e9s",
    "sg:phone":"+32 9 220 76 36",
    "sg:postcode":"9000",
    "sg:province":"Oost-Vlaanderen",
    "wof:name":"Huis Bouckaert",
    "wof:placetype":"venue"
},
  "geometry": {"coordinates":[3.7170519829,51.0390586853],"type":"Point"}
}