{
  "type": "Feature",
  "properties": {
    "addr:full":"Latemdreef 51 Zwalm Oost-Vlaanderen 9630",
    "addr:housenumber":"51",
    "addr:postcode":"9630",
    "addr:street":"Latemdreef;Oost-Vlaanderen",
    "iso:country":"BE",
    "sg:address":"Latemdreef 51",
    "sg:city":"Zwalm",
    "sg:orig_category":"Dakwerken",
    "sg:phone":"+32 55 49 64 15",
    "sg:postcode":"9630",
    "sg:province":"Oost-Vlaanderen",
    "wof:name":"Peter Polfliet",
    "wof:placetype":"venue"
},
  "geometry": {"coordinates":[3.7150220871,50.8911247253],"type":"Point"}
}