{
  "type": "Feature",
  "properties": {
    "addr:full":"Rue De La Terre \u00e0 Briques 5 Tournai (blandain - Hertain) Hainaut 7522",
    "addr:housenumber":"5",
    "addr:postcode":"7522",
    "addr:street":"Rue De La Terre A\u0300 Briques;Hainaut",
    "iso:country":"BE",
    "sg:address":"Rue De La Terre \u00e0 Briques 5",
    "sg:city":"Tournai (blandain - Hertain)",
    "sg:classifiers":[
        {
            "category":"Shopping",
            "subcategory":"Pets & Pet Supplies",
            "type":"Retail Goods"
        }
    ],
    "sg:phone":"+32 69 21 45 23",
    "sg:postcode":"7522",
    "sg:province":"Hainaut",
    "sg:tags":[
        "aquarium",
        "accessory"
    ],
    "wof:name":"Mille Poissons (aux)",
    "wof:placetype":"venue"
},
  "geometry": {"coordinates":[3.3337230682,50.6075363159],"type":"Point"}
}