{
  "type": "Feature",
  "properties": {
    "addr:full":"Groenekeitse 1 Edingen/enghien Hainaut 7850",
    "addr:housenumber":"1",
    "addr:postcode":"7850",
    "addr:street":"Groenekeitse",
    "iso:country":"BE",
    "sg:address":"Groenekeitse 1",
    "sg:city":"Edingen/enghien",
    "sg:orig_category":"Rundveehouders",
    "sg:phone":"+32 2 395 72 07",
    "sg:postcode":"7850",
    "sg:province":"Hainaut",
    "wof:name":"Leo Decoster",
    "wof:placetype":"venue"
},
  "geometry": {"coordinates":[4.0187511444,50.6727981567],"type":"Point"}
}