{
  "type": "Feature",
  "properties": {
    "iso:country":"BE",
    "sg:address":"Lindeweg 3",
    "sg:city":"Zoutleeuw",
    "sg:orig_category":"Fruitteelt",
    "sg:phone":"+32 11 78 25 59",
    "sg:postcode":"3440",
    "sg:province":"Vlaams-Brabant",
    "wof:name":"Lucien Wouters",
    "wof:placetype":"venue"
},
  "geometry": {"coordinates":[5.1297821999,50.8474769592],"type":"Point"}
}