{
  "type": "Feature",
  "properties": {
    "iso:country":"BE",
    "sg:address":"Avenue De L'ind\u00e9pendance Belge 33",
    "sg:city":"Bruxelles (koekelberg)",
    "sg:classifiers":[
        {
            "category":"Professional",
            "subcategory":"Art Services",
            "type":"Services"
        }
    ],
    "sg:phone":"+32 2 414 88 80",
    "sg:postcode":"1081",
    "sg:province":"Bruxelles-Capitale",
    "sg:tags":[
        "interior",
        "designer"
    ],
    "wof:name":"Burgelman F",
    "wof:placetype":"venue"
},
  "geometry": {"coordinates":[4.3219919205,50.8635787964],"type":"Point"}
}