{
  "type": "Feature",
  "properties": {
    "iso:country":"BE",
    "sg:address":"Rue Grande 152",
    "sg:city":"Quievrain",
    "sg:orig_category":"Enseignement maternel and primaire",
    "sg:phone":"+32 65 43 09 40",
    "sg:postcode":"7380",
    "sg:province":"Hainaut",
    "wof:name":"Ecole Fond. Communale",
    "wof:placetype":"venue"
},
  "geometry": {"coordinates":[3.682915926,50.4057235718],"type":"Point"}
}