{
  "type": "Feature",
  "properties": {
    "addr:full":"Kapellenstrasse 31 Butgenbach Li\u00e8ge 4750",
    "addr:housenumber":"31",
    "addr:postcode":"4750",
    "addr:street":"Kapellenstrasse",
    "iso:country":"BE",
    "sg:address":"Kapellenstrasse 31",
    "sg:city":"Butgenbach",
    "sg:orig_category":"Location d'articles de sport, de sport nautique and de camping",
    "sg:phone":"+32 80 44 76 00",
    "sg:postcode":"4750",
    "sg:province":"Li\u00e8ge",
    "wof:name":"Sport & Freizit Heck",
    "wof:placetype":"venue"
},
  "geometry": {"coordinates":[6.2043948174,50.4263038635],"type":"Point"}
}