{
  "type": "Feature",
  "properties": {
    "addr:full":"Mechelseweg 92 Kapelle-op-den-bos Vlaams-Brabant 1880",
    "addr:housenumber":"92",
    "addr:postcode":"1880",
    "addr:street":"Mechelseweg",
    "iso:country":"BE",
    "sg:address":"Mechelseweg 92",
    "sg:city":"Kapelle-op-den-bos",
    "sg:orig_category":"Postkantoren Verzekeringsmakelaars and experts",
    "sg:phone":"+32 15 71 12 29",
    "sg:postcode":"1880",
    "sg:province":"Vlaams-Brabant",
    "wof:name":"De Post",
    "wof:placetype":"venue"
},
  "geometry": {"coordinates":[4.3538570404,51.0136070251],"type":"Point"}
}