{
  "type": "Feature",
  "properties": {
    "iso:country":"BE",
    "sg:address":"Stationsstraat 62",
    "sg:city":"Aalter",
    "sg:classifiers":[
        {
            "category":"Retail",
            "subcategory":"Repair Shop",
            "type":"Services"
        }
    ],
    "sg:phone":"+32 9 374 38 83",
    "sg:postcode":"9880",
    "sg:province":"Oost-Vlaanderen",
    "sg:tags":[
        "photographic",
        "equipment",
        "-",
        "accessory"
    ],
    "wof:name":"Foto Robby Smessaert",
    "wof:placetype":"venue"
},
  "geometry": {"coordinates":[3.4480400085,51.0856399536],"type":"Point"}
}