{
  "type": "Feature",
  "properties": {
    "addr:full":"Massemsesteenweg 323 Wetteren Oost-Vlaanderen 9230",
    "addr:housenumber":"323",
    "addr:postcode":"9230",
    "addr:street":"Massemsesteenweg",
    "iso:country":"BE",
    "sg:address":"Massemsesteenweg 323",
    "sg:city":"Wetteren",
    "sg:classifiers":[
        {
            "category":"Farming",
            "subcategory":"Livestock Farm",
            "type":"Manufacturing & Wholesale Goods"
        }
    ],
    "sg:phone":"+32 9 369 80 35",
    "sg:postcode":"9230",
    "sg:province":"Oost-Vlaanderen",
    "sg:tags":[
        "buyer"
    ],
    "wof:name":"De Lathauwer B",
    "wof:placetype":"venue"
},
  "geometry": {"coordinates":[3.8682360649,50.9757194519],"type":"Point"}
}