{
  "type": "Feature",
  "properties": {
    "addr:full":"Square De La Charit\u00e9 Sur Loire 1 Namur (w\u00e9pion) Namur 5100",
    "addr:housenumber":"1",
    "addr:postcode":"5100",
    "addr:street":"Square De La Charite\u0301 Sur Loire",
    "iso:country":"BE",
    "sg:address":"Square De La Charit\u00e9 Sur Loire 1",
    "sg:city":"Namur (w\u00e9pion)",
    "sg:classifiers":[
        {
            "category":"Professional",
            "subcategory":"Accounting & Tax Preparation",
            "type":"Services"
        }
    ],
    "sg:phone":"+32 81 46 14 72",
    "sg:postcode":"5100",
    "sg:province":"Namur",
    "sg:tags":[
        "bookkeeper"
    ],
    "wof:name":"Dubuisson M",
    "wof:placetype":"venue"
},
  "geometry": {"coordinates":[4.8789901733,50.4059143066],"type":"Point"}
}