{
  "type": "Feature",
  "properties": {
    "addr:full":"Viaductstraat 20 Sint-truiden Limburg 3800",
    "addr:housenumber":"20",
    "addr:postcode":"3800",
    "addr:street":"Viaductstraat",
    "iso:country":"BE",
    "sg:address":"Viaductstraat 20",
    "sg:city":"Sint-truiden",
    "sg:classifiers":[
        {
            "category":"Health Services",
            "subcategory":"Dentist",
            "type":"Services"
        }
    ],
    "sg:phone":"+32 11 68 88 66",
    "sg:postcode":"3800",
    "sg:province":"Limburg",
    "wof:name":"Beerten G",
    "wof:placetype":"venue"
},
  "geometry": {"coordinates":[5.1810278893,50.8204231262],"type":"Point"}
}