{
  "type": "Feature",
  "properties": {
    "iso:country":"BE",
    "sg:address":"Oude Kuringerbaan 117",
    "sg:city":"Hasselt",
    "sg:orig_category":"G\u00e9om\u00e8tres",
    "sg:phone":"+32 11 25 35 87",
    "sg:postcode":"3500",
    "sg:province":"Limburg",
    "wof:name":"Jozef Stessens",
    "wof:placetype":"venue"
},
  "geometry": {"coordinates":[5.3212761879,50.9357147217],"type":"Point"}
}