{
  "type": "Feature",
  "properties": {
    "iso:country":"BE",
    "sg:address":"Rue Pierre Fontaine 35",
    "sg:city":"Lessines (papignies)",
    "sg:classifiers":[
        {
            "category":"Building & Trades",
            "subcategory":"Landscaping Services",
            "type":"Services"
        }
    ],
    "sg:phone":"+32 68 33 14 06",
    "sg:postcode":"7861",
    "sg:province":"Hainaut",
    "sg:tags":[
        "-",
        "lopping",
        "work",
        "tree",
        "felling"
    ],
    "wof:name":"Bourgeois S",
    "wof:placetype":"venue"
},
  "geometry": {"coordinates":[3.8204929829,50.6884040833],"type":"Point"}
}