{
  "type": "Feature",
  "properties": {
    "iso:country":"BE",
    "sg:address":"Merksplasseweg 22",
    "sg:city":"Beerse",
    "sg:orig_category":"Gespecialiseerde residenti\u00eble bouw Woningbouw",
    "sg:phone":"+32 14 61 10 17",
    "sg:postcode":"2340",
    "sg:province":"Antwerpen",
    "wof:name":"Koster Mainil Serge",
    "wof:placetype":"venue"
},
  "geometry": {"coordinates":[4.855659008,51.330291748],"type":"Point"}
}