{
  "type": "Feature",
  "properties": {
    "iso:country":"BE",
    "sg:address":"Chauss\u00e9e De Gand 426",
    "sg:city":"Bruxelles (molenbeek-saint-jean)",
    "sg:classifiers":[
        {
            "category":"Shopping",
            "subcategory":"Used Merchandise",
            "type":"Retail Goods"
        }
    ],
    "sg:phone":"+32 2 415 94 44",
    "sg:postcode":"1080",
    "sg:province":"Bruxelles-Capitale",
    "sg:tags":[
        "salvage",
        "surplus"
    ],
    "wof:name":"Solderie Du Karreveld",
    "wof:placetype":"venue"
},
  "geometry": {"coordinates":[4.3172020912,50.8579483032],"type":"Point"}
}