{
  "type": "Feature",
  "properties": {
    "iso:country":"BE",
    "sg:address":"Gistelsteenweg 2b",
    "sg:city":"Jabbeke",
    "sg:classifiers":[
        {
            "category":"Home & Garden",
            "subcategory":"Carpets & Floor Coverings",
            "type":"Retail Goods"
        }
    ],
    "sg:phone":"+32 50 38 04 22",
    "sg:postcode":"8490",
    "sg:province":"West-Vlaanderen",
    "sg:tags":[
        "parquet"
    ],
    "wof:name":"Reyserhove",
    "wof:placetype":"venue"
},
  "geometry": {"coordinates":[3.1105320454,51.1793174744],"type":"Point"}
}