{
  "type": "Feature",
  "properties": {
    "addr:full":"Chauss\u00c9e Brunehault 210 Binche Hainaut 7134",
    "addr:housenumber":"210",
    "addr:postcode":"7134",
    "addr:street":"Chausse\u0301E Brunehault",
    "iso:country":"BE",
    "sg:address":"Chauss\u00c9e Brunehault 210",
    "sg:city":"Binche",
    "sg:orig_category":"Kapsalons",
    "sg:phone":"+32 64 33 43 22",
    "sg:postcode":"7134",
    "sg:province":"Hainaut",
    "wof:name":"J. Chambon",
    "wof:placetype":"venue"
},
  "geometry": {"coordinates":[4.1832418442,50.4281692505],"type":"Point"}
}