{
  "type": "Feature",
  "properties": {
    "iso:country":"BE",
    "sg:address":"Stationsstraat 268",
    "sg:city":"Liedekerke",
    "sg:classifiers":[
        {
            "category":"Health Services",
            "subcategory":"Dentist",
            "type":"Services"
        }
    ],
    "sg:phone":"+32 53 66 56 71",
    "sg:postcode":"1770",
    "sg:province":"Vlaams-Brabant",
    "wof:name":"Deneve L",
    "wof:placetype":"venue"
},
  "geometry": {"coordinates":[4.0924887657,50.8783340454],"type":"Point"}
}