{
  "type": "Feature",
  "properties": {
    "addr:full":"Menenstraat 507 Wevelgem West-Vlaanderen 8560",
    "addr:housenumber":"507",
    "addr:postcode":"8560",
    "addr:street":"Menenstraat",
    "iso:country":"BE",
    "sg:address":"Menenstraat 507",
    "sg:city":"Wevelgem",
    "sg:orig_category":"Rundveehouders",
    "sg:phone":"+32 56 41 21 84",
    "sg:postcode":"8560",
    "sg:province":"West-Vlaanderen",
    "wof:name":"Maria David",
    "wof:placetype":"venue"
},
  "geometry": {"coordinates":[3.1493599415,50.8013305664],"type":"Point"}
}