{
  "type": "Feature",
  "properties": {
    "addr:full":"Astridplein 3 Grobbendonk Antwerpen 2280",
    "addr:housenumber":"3",
    "addr:postcode":"2280",
    "addr:street":"Astridplein",
    "iso:country":"BE",
    "sg:address":"Astridplein 3",
    "sg:city":"Grobbendonk",
    "sg:orig_category":"Openbare bibliotheken and archieven",
    "sg:phone":"+32 14 51 61 43",
    "sg:postcode":"2280",
    "sg:province":"Antwerpen",
    "wof:name":"Openbare Bibliotheek",
    "wof:placetype":"venue"
},
  "geometry": {"coordinates":[4.7395200729,51.1921081543],"type":"Point"}
}