{
  "type": "Feature",
  "properties": {
    "addr:full":"Rue Bassenge 7 Li\u00c8ge Li\u00e8ge 4000",
    "addr:housenumber":"7",
    "addr:postcode":"4000",
    "addr:street":"Rue Bassenge",
    "iso:country":"BE",
    "sg:address":"Rue Bassenge 7",
    "sg:city":"Li\u00c8ge",
    "sg:orig_category":"Postkantoren Verzekeringsmakelaars and experts",
    "sg:phone":"+32 4 223 30 86",
    "sg:postcode":"4000",
    "sg:province":"Li\u00e8ge",
    "wof:name":"La Poste",
    "wof:placetype":"venue"
},
  "geometry": {"coordinates":[5.5600628853,50.6362876892],"type":"Point"}
}