{
  "type": "Feature",
  "properties": {
    "addr:full":"Renier Sniedersstraat 65 Turnhout Antwerpen 2300",
    "addr:housenumber":"65",
    "addr:postcode":"2300",
    "addr:street":"Renier Sniedersstraat",
    "iso:country":"BE",
    "sg:address":"Renier Sniedersstraat 65",
    "sg:city":"Turnhout",
    "sg:orig_category":"Blanchisserie, Nettoyage \u00e0 Sec and Salons-Lavoirs. Blanchisseries and teintureries",
    "sg:phone":"+32 14 41 65 66",
    "sg:postcode":"2300",
    "sg:province":"Antwerpen",
    "wof:name":"Wassalon Gudrun",
    "wof:placetype":"venue"
},
  "geometry": {"coordinates":[4.9407458305,51.3237762451],"type":"Point"}
}