{
  "type": "Feature",
  "properties": {
    "addr:full":"Maspelt 26 Burg-reuland (thommen) Li\u00e8ge 4791",
    "addr:housenumber":"26",
    "addr:postcode":"4791",
    "addr:street":"Maspelt;Thommen",
    "iso:country":"BE",
    "sg:address":"Maspelt 26",
    "sg:city":"Burg-reuland (thommen)",
    "sg:classifiers":[
        {
            "category":"Wholesale",
            "subcategory":"Hardware",
            "type":"Manufacturing & Wholesale Goods"
        }
    ],
    "sg:phone":"+32 80 32 95 29",
    "sg:postcode":"4791",
    "sg:province":"Li\u00e8ge",
    "sg:tags":[
        "lubricating",
        "compound"
    ],
    "wof:name":"Wangen J",
    "wof:placetype":"venue"
},
  "geometry": {"coordinates":[6.0944099426,50.2024497986],"type":"Point"}
}