{
  "type": "Feature",
  "properties": {
    "addr:full":"Araucarialaan 109 Brussel/bruxelles Bruxelles-Capitale 1020",
    "addr:housenumber":"109",
    "addr:postcode":"1020",
    "addr:street":"Araucarialaan;/",
    "iso:country":"BE",
    "sg:address":"Araucarialaan 109",
    "sg:city":"Brussel/bruxelles",
    "sg:orig_category":"Artsen and specialisten",
    "sg:phone":"+32 2 268 22 76",
    "sg:postcode":"1020",
    "sg:province":"Bruxelles-Capitale",
    "wof:name":"Jacqueline Andr\u00c9",
    "wof:placetype":"venue"
},
  "geometry": {"coordinates":[4.3628649712,50.8968925476],"type":"Point"}
}