{
  "type": "Feature",
  "properties": {
    "addr:full":"Albert I-square 28b10 Anderlecht Bruxelles-Capitale 1070",
    "addr:housenumber":"28b10",
    "addr:postcode":"1070",
    "addr:street":"I-Square",
    "iso:country":"BE",
    "sg:address":"Albert I-square 28b10",
    "sg:city":"Anderlecht",
    "sg:orig_category":"Artsen and specialisten",
    "sg:phone":"+32 2 522 87 96",
    "sg:postcode":"1070",
    "sg:province":"Bruxelles-Capitale",
    "wof:name":"Laurette Nyadjea",
    "wof:placetype":"venue"
},
  "geometry": {"coordinates":[4.3223719597,50.8387832642],"type":"Point"}
}