{
  "type": "Feature",
  "properties": {
    "addr:full":"Lenniksebaan 144 Dilbeek (itterbeek) Vlaams-Brabant 1701",
    "addr:housenumber":"144",
    "addr:postcode":"1701",
    "addr:street":"Lenniksebaan",
    "iso:country":"BE",
    "sg:address":"Lenniksebaan 144",
    "sg:city":"Dilbeek (itterbeek)",
    "sg:classifiers":[
        {
            "category":"Building & Trades",
            "subcategory":"Pest Control",
            "type":"Services"
        }
    ],
    "sg:phone":"+32 2 567 06 20",
    "sg:postcode":"1701",
    "sg:province":"Vlaams-Brabant",
    "sg:tags":[
        "painting",
        "contractor"
    ],
    "wof:name":"Van Loo",
    "wof:placetype":"venue"
},
  "geometry": {"coordinates":[4.2389512062,50.8185043335],"type":"Point"}
}