{
  "type": "Feature",
  "properties": {
    "addr:full":"Bernard Van Hoolstraat 6 Lier Antwerpen 2500",
    "addr:housenumber":"6",
    "addr:postcode":"2500",
    "addr:street":"Bernard Van Hoolstraat",
    "iso:country":"BE",
    "sg:address":"Bernard Van Hoolstraat 6",
    "sg:city":"Lier",
    "sg:orig_category":"Services fun\u00e9raires",
    "sg:phone":"+32 3 488 15 17",
    "sg:postcode":"2500",
    "sg:province":"Antwerpen",
    "wof:name":"Ceremonie Hazenbosch",
    "wof:placetype":"venue"
},
  "geometry": {"coordinates":[4.6106500626,51.0956420898],"type":"Point"}
}