{
  "type": "Feature",
  "properties": {
    "iso:country":"BE",
    "sg:address":"Vijftien Augustusstraat 28 Box 615_e",
    "sg:city":"Zutendaal",
    "sg:classifiers":[
        {
            "category":"Personal",
            "subcategory":"Beauty Salon",
            "type":"Services"
        }
    ],
    "sg:phone":"+32 89 61 16 36",
    "sg:postcode":"3690",
    "sg:province":"Limburg",
    "sg:tags":[
        "lady",
        "-",
        "hairdressing"
    ],
    "wof:name":"Annie & Maurice",
    "wof:placetype":"venue"
},
  "geometry": {"coordinates":[5.5731167793,50.9314651489],"type":"Point"}
}