{
  "type": "Feature",
  "properties": {
    "addr:full":"Sint Tillostraat 5 Izegem West-Vlaanderen 8870",
    "addr:housenumber":"5",
    "addr:postcode":"8870",
    "addr:street":"Tillostraat",
    "iso:country":"BE",
    "sg:address":"Sint Tillostraat 5",
    "sg:city":"Izegem",
    "sg:orig_category":"HERSTELLING ELEKTRISCHE HUISHOUDAPPARATEN Huishoudapparaten, televisies and radio's",
    "sg:phone":"+32 51 31 54 65",
    "sg:postcode":"8870",
    "sg:province":"West-Vlaanderen",
    "wof:name":"Kupperbusch Service",
    "wof:placetype":"venue"
},
  "geometry": {"coordinates":[3.2132239342,50.9169197083],"type":"Point"}
}