{
  "type": "Feature",
  "properties": {
    "iso:country":"BE",
    "sg:address":"Ninoofsesteenweg 142",
    "sg:city":"Pepingen",
    "sg:orig_category":"Royal Canin. Animaux domestiques and accessoires",
    "sg:phone":"+32 2 356 56 23",
    "sg:postcode":"1670",
    "sg:province":"Vlaams-Brabant",
    "wof:name":"Van Cutsem",
    "wof:placetype":"venue"
},
  "geometry": {"coordinates":[4.1564340591,50.7594833374],"type":"Point"}
}