{
  "type": "Feature",
  "properties": {
    "addr:full":"Rue De La Cure 7 Le Roeulx (ville-sur-haine) Hainaut 7070",
    "addr:housenumber":"7",
    "addr:postcode":"7070",
    "addr:street":"Rue De La Cure",
    "iso:country":"BE",
    "sg:address":"Rue De La Cure 7",
    "sg:city":"Le Roeulx (ville-sur-haine)",
    "sg:classifiers":[
        {
            "category":"Building & Trades",
            "subcategory":"Cleaning & Sanitation",
            "type":"Services"
        }
    ],
    "sg:phone":"+32 64 66 53 07",
    "sg:postcode":"7070",
    "sg:province":"Hainaut",
    "sg:tags":[
        "blast"
    ],
    "wof:name":"Hero & Fils",
    "wof:placetype":"venue"
},
  "geometry": {"coordinates":[4.0626659393,50.4967002869],"type":"Point"}
}