{
  "type": "Feature",
  "properties": {
    "iso:country":"BE",
    "sg:address":"Groenstraat 46",
    "sg:city":"Duffel",
    "sg:orig_category":"Maatschappelijke dienstverlening",
    "sg:phone":"+32 15 31 31 62",
    "sg:postcode":"2570",
    "sg:province":"Antwerpen",
    "wof:name":"Rode Kruis Duffel",
    "wof:placetype":"venue"
},
  "geometry": {"coordinates":[4.4860048294,51.0877723694],"type":"Point"}
}