{
  "type": "Feature",
  "properties": {
    "iso:country":"BE",
    "sg:address":"Strateneinde 21",
    "sg:city":"Westerlo",
    "sg:orig_category":"Eleveurs and marchands de porcs. Eleveurs de bovins",
    "sg:phone":"+32 14 26 53 45",
    "sg:postcode":"2260",
    "sg:province":"Antwerpen",
    "wof:name":"Ferdinand Helsen",
    "wof:placetype":"venue"
},
  "geometry": {"coordinates":[4.8429398537,51.1106109619],"type":"Point"}
}