{
  "type": "Feature",
  "properties": {
    "iso:country":"BE",
    "sg:address":"Tervuursesteenweg 796",
    "sg:city":"Zemst (elewijt)",
    "sg:classifiers":[
        {
            "category":"Professional",
            "subcategory":"Computer Services",
            "type":"Services"
        }
    ],
    "sg:phone":"+32 15 62 05 43",
    "sg:postcode":"1982",
    "sg:province":"Vlaams-Brabant",
    "sg:tags":[
        "-",
        "processing",
        "data"
    ],
    "wof:name":"Hoefman G",
    "wof:placetype":"venue"
},
  "geometry": {"coordinates":[4.4975538254,50.9585533142],"type":"Point"}
}