{
  "type": "Feature",
  "properties": {
    "addr:full":"Jacoletstraat 24 Leopoldsburg Limburg 3970",
    "addr:housenumber":"24",
    "addr:postcode":"3970",
    "addr:street":"Jacoletstraat",
    "iso:country":"BE",
    "sg:address":"Jacoletstraat 24",
    "sg:city":"Leopoldsburg",
    "sg:orig_category":"Epiceries",
    "sg:phone":"+32 11 34 23 15",
    "sg:postcode":"3970",
    "sg:province":"Limburg",
    "wof:name":"Cash Fresh",
    "wof:placetype":"venue"
},
  "geometry": {"coordinates":[5.2615299225,51.1163406372],"type":"Point"}
}