{
  "type": "Feature",
  "properties": {
    "addr:full":"Gentsesteenweg 152 Deinze Oost-Vlaanderen 9800",
    "addr:housenumber":"152",
    "addr:postcode":"9800",
    "addr:street":"Gentsesteenweg",
    "iso:country":"BE",
    "sg:address":"Gentsesteenweg 152",
    "sg:city":"Deinze",
    "sg:classifiers":[
        {
            "category":"Shopping",
            "subcategory":"Clothing, Apparel, & Fashions",
            "type":"Retail Goods"
        }
    ],
    "sg:phone":"+32 9 386 83 50",
    "sg:postcode":"9800",
    "sg:province":"Oost-Vlaanderen",
    "sg:tags":[
        "large",
        "-",
        "clothing",
        "sale-rooms"
    ],
    "wof:name":"Landgraaf",
    "wof:placetype":"venue"
},
  "geometry": {"coordinates":[3.5434188843,50.9805679321],"type":"Point"}
}