{
  "type": "Feature",
  "properties": {
    "addr:full":"Stationslaan 38 Tongeren Limburg 3700",
    "addr:housenumber":"38",
    "addr:postcode":"3700",
    "addr:street":"Stationslaan",
    "iso:country":"BE",
    "sg:address":"Stationslaan 38",
    "sg:city":"Tongeren",
    "sg:classifiers":[
        {
            "category":"Cafe",
            "type":"Food & Drink"
        }
    ],
    "sg:phone":"+32 12 39 23 25",
    "sg:postcode":"3700",
    "sg:province":"Limburg",
    "sg:tags":[
        "snack-bars"
    ],
    "wof:name":"Okkus",
    "wof:placetype":"venue"
},
  "geometry": {"coordinates":[5.4725518227,50.7835655212],"type":"Point"}
}