{
  "type": "Feature",
  "properties": {
    "iso:country":"BE",
    "sg:address":"Rue Mattot 62",
    "sg:city":"Waterloo",
    "sg:orig_category":"M\u00e9decins and sp\u00e9cialistes",
    "sg:phone":"+32 2 354 82 86",
    "sg:postcode":"1410",
    "sg:province":"Brabant Wallon",
    "wof:name":"Rico Zinga",
    "wof:placetype":"venue"
},
  "geometry": {"coordinates":[4.3791379929,50.7127609253],"type":"Point"}
}