{
  "type": "Feature",
  "properties": {
    "addr:full":"Lagesteenweg 94 Grimbergen Vlaams-Brabant 1850",
    "addr:housenumber":"94",
    "addr:postcode":"1850",
    "addr:street":"Lagesteenweg",
    "iso:country":"BE",
    "sg:address":"Lagesteenweg 94",
    "sg:city":"Grimbergen",
    "sg:orig_category":"M\u00e9decins and sp\u00e9cialistes",
    "sg:phone":"+32 2 270 40 21",
    "sg:postcode":"1850",
    "sg:province":"Vlaams-Brabant",
    "wof:name":"H.e. Camerlynck",
    "wof:placetype":"venue"
},
  "geometry": {"coordinates":[4.3651847839,50.9326782227],"type":"Point"}
}