{
  "type": "Feature",
  "properties": {
    "addr:full":"Rue Al Savatte 15 Awans (oth\u00e9e) Li\u00e8ge 4340",
    "addr:housenumber":"15",
    "addr:postcode":"4340",
    "addr:street":"Rue Al Savatte;Othe\u0301E",
    "iso:country":"BE",
    "sg:address":"Rue Al Savatte 15",
    "sg:city":"Awans (oth\u00e9e)",
    "sg:classifiers":[
        {
            "category":"Farming",
            "subcategory":"Farm & Veterinary Services",
            "type":"Manufacturing & Wholesale Goods"
        }
    ],
    "sg:phone":"+32 4 257 44 00",
    "sg:postcode":"4340",
    "sg:province":"Li\u00e8ge",
    "sg:tags":[
        "agricultural",
        "contractor"
    ],
    "wof:name":"Geromi Sprl",
    "wof:placetype":"venue"
},
  "geometry": {"coordinates":[5.4652819633,50.7285079956],"type":"Point"}
}