{
  "type": "Feature",
  "properties": {
    "addr:full":"Sint-jansplein 8 Kontich Antwerpen 2550",
    "addr:housenumber":"8",
    "addr:postcode":"2550",
    "addr:street":"Sint-Jansplein",
    "iso:country":"BE",
    "sg:address":"Sint-jansplein 8",
    "sg:city":"Kontich",
    "sg:orig_category":"Openbare bibliotheken and archieven",
    "sg:phone":"+32 3 450 78 31",
    "sg:postcode":"2550",
    "sg:province":"Antwerpen",
    "wof:name":"Gemeentelijke Bibliotheek",
    "wof:placetype":"venue"
},
  "geometry": {"coordinates":[4.4467368126,51.1338577271],"type":"Point"}
}