{
  "type": "Feature",
  "properties": {
    "addr:full":"Geraardsbergsestraat 236 Aalst Oost-Vlaanderen 9300",
    "addr:housenumber":"236",
    "addr:postcode":"9300",
    "addr:street":"Geraardsbergsestraat",
    "iso:country":"BE",
    "sg:address":"Geraardsbergsestraat 236",
    "sg:city":"Aalst",
    "sg:orig_category":"Banken and kredietinstellingen",
    "sg:phone":"+32 53 77 98 97",
    "sg:postcode":"9300",
    "sg:province":"Oost-Vlaanderen",
    "wof:name":"Bbl",
    "wof:placetype":"venue"
},
  "geometry": {"coordinates":[4.0351772308,50.9284477234],"type":"Point"}
}