{
  "type": "Feature",
  "properties": {
    "iso:country":"BE",
    "sg:address":"Heidestraat 53 A",
    "sg:city":"Sint-katherina-lombeek",
    "sg:orig_category":"Royal Canin. Animaux domestiques and accessoires",
    "sg:phone":"+32 2 582 61 11",
    "sg:postcode":"1742",
    "sg:province":"Vlaams-Brabant",
    "wof:name":"Ps. Van Der Perre",
    "wof:placetype":"venue"
},
  "geometry": {"coordinates":[4.1432957649,50.8698234558],"type":"Point"}
}