{
  "type": "Feature",
  "properties": {
    "addr:full":"Place De Frasnes 1 Les Bons Villers Hainaut 6210",
    "addr:housenumber":"1",
    "addr:postcode":"6210",
    "addr:street":"Place De Frasnes",
    "iso:country":"BE",
    "sg:address":"Place De Frasnes 1",
    "sg:city":"Les Bons Villers",
    "sg:orig_category":"Openbare veiligheid",
    "sg:phone":"+32 71 85 00 95",
    "sg:postcode":"6210",
    "sg:province":"Hainaut",
    "wof:name":"Police F\u00c9d\u00c9rale/federale Politie",
    "wof:placetype":"venue"
},
  "geometry": {"coordinates":[4.4511561394,50.5378227234],"type":"Point"}
}