{
  "type": "Feature",
  "properties": {
    "iso:country":"BE",
    "sg:address":"Rue De La Roche",
    "sg:city":"Rendeux",
    "sg:classifiers":[
        {
            "category":"Shopping",
            "subcategory":"Books",
            "type":"Retail Goods"
        }
    ],
    "sg:phone":"+32 84 47 77 14",
    "sg:postcode":"6987",
    "sg:province":"Luxembourg",
    "sg:tags":[
        "bookseller"
    ],
    "wof:name":"Librairie Nouvel Horizon Sprl",
    "wof:placetype":"venue"
},
  "geometry": {"coordinates":[5.5122351646,50.2331161499],"type":"Point"}
}