{
  "type": "Feature",
  "properties": {
    "addr:full":"Manestraat 31 Izegem West-Vlaanderen 8870",
    "addr:housenumber":"31",
    "addr:postcode":"8870",
    "addr:street":"Manestraat",
    "iso:country":"BE",
    "sg:address":"Manestraat 31",
    "sg:city":"Izegem",
    "sg:orig_category":"Groententeelt",
    "sg:phone":"+32 51 30 28 94",
    "sg:postcode":"8870",
    "sg:province":"West-Vlaanderen",
    "wof:name":"Willy Swaenepoel",
    "wof:placetype":"venue"
},
  "geometry": {"coordinates":[3.1905219555,50.9449272156],"type":"Point"}
}