{
  "type": "Feature",
  "properties": {
    "addr:full":"Place Gilles G\u00c9rard 9 Herstal Li\u00e8ge 4041",
    "addr:housenumber":"9",
    "addr:postcode":"4041",
    "addr:street":"Place Gilles Ge\u0301Rard",
    "iso:country":"BE",
    "sg:address":"Place Gilles G\u00c9rard 9",
    "sg:city":"Herstal",
    "sg:orig_category":"Banques and organismes de cr\u00e9dit",
    "sg:phone":"+32 4 227 30 22",
    "sg:postcode":"4041",
    "sg:province":"Li\u00e8ge",
    "wof:name":"Fortis",
    "wof:placetype":"venue"
},
  "geometry": {"coordinates":[5.585624218,50.6724205017],"type":"Point"}
}