{
  "type": "Feature",
  "properties": {
    "iso:country":"BE",
    "sg:address":"Sart D'avette 15",
    "sg:city":"Flemalle",
    "sg:classifiers":[
        {
            "category":"Bakery",
            "type":"Food & Drink"
        }
    ],
    "sg:phone":"+32 4 275 14 53",
    "sg:postcode":"4400",
    "sg:province":"Li\u00e8ge",
    "sg:tags":[
        "fresh",
        "pastry",
        "bread"
    ],
    "wof:name":"Le Fournil De Michel S.a.",
    "wof:placetype":"venue"
},
  "geometry": {"coordinates":[5.4116511345,50.6000099182],"type":"Point"}
}