{
  "type": "Feature",
  "properties": {
    "addr:full":"Rue D'alvau 30 Mont-saint-guibert Brabant Wallon 1435",
    "addr:housenumber":"30",
    "addr:postcode":"1435",
    "addr:street":"Rue D'Alvau",
    "iso:country":"BE",
    "sg:address":"Rue D'alvau 30",
    "sg:city":"Mont-saint-guibert",
    "sg:orig_category":"Schoonmaakbedrijven and ongediertebestrijding",
    "sg:phone":"+32 10 65 10 03",
    "sg:postcode":"1435",
    "sg:province":"Brabant Wallon",
    "wof:name":"Steve-mac-clean",
    "wof:placetype":"venue"
},
  "geometry": {"coordinates":[4.6264410019,50.6343536377],"type":"Point"}
}