{
  "type": "Feature",
  "properties": {
    "iso:country":"BE",
    "sg:address":"Astridlaan 167",
    "sg:city":"Geraardsbergen",
    "sg:orig_category":"Betonnen bouwelementen Fab",
    "sg:phone":"+32 54 41 18 64",
    "sg:postcode":"9500",
    "sg:province":"Oost-Vlaanderen",
    "wof:name":"Duffeleer Beton",
    "wof:placetype":"venue"
},
  "geometry": {"coordinates":[3.8745100498,50.78125],"type":"Point"}
}