{
  "type": "Feature",
  "properties": {
    "addr:full":"Rue Du Doyard 20 Bastogne Luxembourg 6600",
    "addr:housenumber":"20",
    "addr:postcode":"6600",
    "addr:street":"Rue Du Doyard",
    "iso:country":"BE",
    "sg:address":"Rue Du Doyard 20",
    "sg:city":"Bastogne",
    "sg:orig_category":"V\u00e9t\u00e9rinaires",
    "sg:phone":"+32 61 21 36 30",
    "sg:postcode":"6600",
    "sg:province":"Luxembourg",
    "wof:name":"Joseph Weinquin",
    "wof:placetype":"venue"
},
  "geometry": {"coordinates":[5.7217359543,50.0145568848],"type":"Point"}
}