{
  "type": "Feature",
  "properties": {
    "iso:country":"BE",
    "sg:address":"Maastrichtersteenweg 1",
    "sg:city":"Riemst",
    "sg:orig_category":"Elektrische installaties voor woningen",
    "sg:phone":"+32 12 45 26 40",
    "sg:postcode":"3770",
    "sg:province":"Limburg",
    "wof:name":"Firmin Daniels",
    "wof:placetype":"venue"
},
  "geometry": {"coordinates":[5.595225811,50.8119888306],"type":"Point"}
}