{
  "type": "Feature",
  "properties": {
    "addr:full":"Vranksberg 13 Huldenberg Vlaams-Brabant 3040",
    "addr:housenumber":"13",
    "addr:postcode":"3040",
    "addr:street":"Vranksberg",
    "iso:country":"BE",
    "sg:address":"Vranksberg 13",
    "sg:city":"Huldenberg",
    "sg:orig_category":"S\u00e9lection de personnel and placement",
    "sg:phone":"+32 16 47 35 47",
    "sg:postcode":"3040",
    "sg:province":"Vlaams-Brabant",
    "wof:name":"Adviesbureau Van Asbrouck",
    "wof:placetype":"venue"
},
  "geometry": {"coordinates":[4.5987010002,50.8017921448],"type":"Point"}
}