{
  "type": "Feature",
  "properties": {
    "iso:country":"BE",
    "sg:address":"Broekstraat 91",
    "sg:city":"Buggenhout",
    "sg:orig_category":"Herstellingen and onderhoud van auto's",
    "sg:phone":"+32 52 35 23 65",
    "sg:postcode":"9255",
    "sg:province":"Oost-Vlaanderen",
    "wof:name":"Koenraad Van Hove",
    "wof:placetype":"venue"
},
  "geometry": {"coordinates":[4.1677398682,50.988368988],"type":"Point"}
}