{
  "type": "Feature",
  "properties": {
    "addr:full":"Nassaustraat 12-14 Antwerpen Antwerpen 2000",
    "addr:housenumber":"12-14",
    "addr:postcode":"2000",
    "addr:street":"Nassaustraat",
    "iso:country":"BE",
    "sg:address":"Nassaustraat 12-14",
    "sg:city":"Antwerpen",
    "sg:classifiers":[
        {
            "category":"Shopping",
            "subcategory":"Bicycles & Sporting Goods",
            "type":"Retail Goods"
        }
    ],
    "sg:phone":"+32 3 233 31 31",
    "sg:postcode":"2000",
    "sg:province":"Antwerpen",
    "sg:tags":[
        "article",
        "de",
        "sport",
        "camping"
    ],
    "wof:name":"Landtmeters & Co",
    "wof:placetype":"venue"
},
  "geometry": {"coordinates":[4.4050149918,51.2307853699],"type":"Point"}
}