{
  "type": "Feature",
  "properties": {
    "iso:country":"BE",
    "sg:address":"Ringlaan 11",
    "sg:city":"Houthalen-helchteren (houthalen)",
    "sg:classifiers":[
        {
            "category":"Professional",
            "subcategory":"Lawyer & Legal Services",
            "type":"Services"
        }
    ],
    "sg:phone":"+32 11 52 41 35",
    "sg:postcode":"3530",
    "sg:province":"Limburg",
    "wof:name":"Vorias E",
    "wof:placetype":"venue"
},
  "geometry": {"coordinates":[5.3789348602,51.0317878723],"type":"Point"}
}