{
  "type": "Feature",
  "properties": {
    "iso:country":"BE",
    "sg:address":"Veldstraat 74",
    "sg:city":"Menen",
    "sg:orig_category":"Rundveehouders",
    "sg:phone":"+32 56 51 13 19",
    "sg:postcode":"8930",
    "sg:province":"West-Vlaanderen",
    "wof:name":"Eddy Schouteten",
    "wof:placetype":"venue"
},
  "geometry": {"coordinates":[3.0868139267,50.8001670837],"type":"Point"}
}