{
  "type": "Feature",
  "properties": {
    "iso:country":"BE",
    "sg:address":"195-203 Rue Haute",
    "sg:city":"Bruxelles",
    "sg:classifiers":[
        {
            "category":"Shopping",
            "subcategory":"Clothing, Apparel, & Fashions",
            "type":"Retail Goods"
        }
    ],
    "sg:phone":"+32 2 511 69 35",
    "sg:postcode":"1000",
    "sg:province":"Bruxelles-Capitale",
    "sg:tags":[
        "textile",
        "clothing",
        "clothes"
    ],
    "wof:name":"Le Grand Specialiste Du Vetement Michiels Sprl",
    "wof:placetype":"venue"
},
  "geometry": {"coordinates":[4.3501200676,50.8385009766],"type":"Point"}
}