{
  "type": "Feature",
  "properties": {
    "iso:country":"BE",
    "sg:address":"Avenue De Sumatra 41",
    "sg:city":"Ukkel/uccle",
    "sg:orig_category":"Avocats and conseillers juridiques",
    "sg:phone":"+32 2 375 70 76",
    "sg:postcode":"1180",
    "sg:province":"Bruxelles-Capitale",
    "wof:name":"N. Lannoy",
    "wof:placetype":"venue"
},
  "geometry": {"coordinates":[4.3599629402,50.8040390015],"type":"Point"}
}