{
  "type": "Feature",
  "properties": {
    "iso:country":"BE",
    "sg:address":"Nationale Straat 49- 52",
    "sg:city":"Antwerpen-centrum",
    "sg:orig_category":"Huisdieren and benodigdheden",
    "sg:phone":"+32 3 226 88 05",
    "sg:postcode":"2000",
    "sg:province":"Antwerpen",
    "wof:name":"Tom & Co",
    "wof:placetype":"venue"
},
  "geometry": {"coordinates":[4.399353981,51.2160377502],"type":"Point"}
}