{
  "type": "Feature",
  "properties": {
    "addr:full":"Lange Herentalsestraat 20-26 Antwerpen Antwerpen 2018",
    "addr:postcode":"20-26;2018",
    "addr:street":"Lange Herentalsestraat",
    "iso:country":"BE",
    "sg:address":"Lange Herentalsestraat 20-26",
    "sg:city":"Antwerpen",
    "sg:classifiers":[
        {
            "category":"Manufacturing",
            "subcategory":"Electronics",
            "type":"Manufacturing & Wholesale Goods"
        }
    ],
    "sg:phone":"+32 3 221 36 70",
    "sg:postcode":"2018",
    "sg:province":"Antwerpen",
    "sg:tags":[
        "telecommunication",
        "system"
    ],
    "wof:name":"International Technology Contractors Nv",
    "wof:placetype":"venue"
},
  "geometry": {"coordinates":[4.4171638489,51.215587616],"type":"Point"}
}