{
  "type": "Feature",
  "properties": {
    "iso:country":"BE",
    "sg:address":"Rue Saint-roch 2",
    "sg:city":"Neufchateau",
    "sg:orig_category":"Foto-uitrusting Fotografen and fotostudio's",
    "sg:phone":"+32 61 27 00 19",
    "sg:postcode":"6840",
    "sg:province":"Luxembourg",
    "wof:name":"Atelier Photo",
    "wof:placetype":"venue"
},
  "geometry": {"coordinates":[5.4342699051,49.8417701721],"type":"Point"}
}