{
  "type": "Feature",
  "properties": {
    "addr:full":"Laambeekstraat 11 Lummen Limburg 3560",
    "addr:housenumber":"11",
    "addr:postcode":"3560",
    "addr:street":"Laambeekstraat",
    "iso:country":"BE",
    "sg:address":"Laambeekstraat 11",
    "sg:city":"Lummen",
    "sg:orig_category":"Brood, gebak and snoepgoed",
    "sg:phone":"+32 13 52 33 26",
    "sg:postcode":"3560",
    "sg:province":"Limburg",
    "wof:name":"Els Deferm",
    "wof:placetype":"venue"
},
  "geometry": {"coordinates":[5.2250099182,50.990146637],"type":"Point"}
}