{
  "type": "Feature",
  "properties": {
    "addr:full":"Rue Des Bruy\u00c8res 7 Fernelmont Namur 5380",
    "addr:housenumber":"7",
    "addr:postcode":"5380",
    "addr:street":"Rue Des Bruye\u0300Res",
    "iso:country":"BE",
    "sg:address":"Rue Des Bruy\u00c8res 7",
    "sg:city":"Fernelmont",
    "sg:orig_category":"Installatie van houten of kunststof schrijnwerk MEUBELONTWERP AND -INSTALLATIE",
    "sg:phone":"+32 81 83 53 31",
    "sg:postcode":"5380",
    "sg:province":"Namur",
    "wof:name":"Daniel Martin",
    "wof:placetype":"venue"
},
  "geometry": {"coordinates":[4.9772028923,50.5778884888],"type":"Point"}
}