{
  "type": "Feature",
  "properties": {
    "iso:country":"BE",
    "sg:address":"Cornelius Sneyssenlaan 13",
    "sg:city":"Merelbeke",
    "sg:orig_category":"Gespecialiseerde residenti\u00eble bouw",
    "sg:phone":"+32 9 232 36 96",
    "sg:postcode":"9820",
    "sg:province":"Oost-Vlaanderen",
    "wof:name":"Hutsebout F",
    "wof:placetype":"venue"
},
  "geometry": {"coordinates":[3.7456190586,50.9888038635],"type":"Point"}
}