{
  "type": "Feature",
  "properties": {
    "addr:full":"Culostraat 12 Bierbeek Vlaams-Brabant 3360",
    "addr:housenumber":"12",
    "addr:postcode":"3360",
    "addr:street":"Culostraat",
    "iso:country":"BE",
    "sg:address":"Culostraat 12",
    "sg:city":"Bierbeek",
    "sg:orig_category":"Traitements param\u00e9dicaux",
    "sg:phone":"+32 16 72 02 88",
    "sg:postcode":"3360",
    "sg:province":"Vlaams-Brabant",
    "wof:name":"Het Leuvens Kruis",
    "wof:placetype":"venue"
},
  "geometry": {"coordinates":[4.7866611481,50.8062896729],"type":"Point"}
}