{
  "type": "Feature",
  "properties": {
    "iso:country":"BE",
    "sg:address":"Hooirt 47",
    "sg:city":"Hamme",
    "sg:orig_category":"Epiceries",
    "sg:phone":"+32 52 47 75 42",
    "sg:postcode":"9220",
    "sg:province":"Oost-Vlaanderen",
    "wof:name":"H. Portaels",
    "wof:placetype":"venue"
},
  "geometry": {"coordinates":[4.137966156,51.0863838196],"type":"Point"}
}