{
  "type": "Feature",
  "properties": {
    "iso:country":"BE",
    "sg:address":"Peperstraat 21",
    "sg:city":"Tienen",
    "sg:classifiers":[
        {
            "category":"Home & Garden",
            "subcategory":"Household Appliances",
            "type":"Retail Goods"
        }
    ],
    "sg:phone":"+32 16 82 10 83",
    "sg:postcode":"3300",
    "sg:province":"Vlaams-Brabant",
    "sg:tags":[
        "repair",
        "mainten",
        "-",
        "electric"
    ],
    "wof:name":"Klein Magazijn Bvba",
    "wof:placetype":"venue"
},
  "geometry": {"coordinates":[4.9378581047,50.8061561584],"type":"Point"}
}