{
  "type": "Feature",
  "properties": {
    "addr:full":"Quai Des Ardennes 9 Li\u00c8ge Li\u00e8ge 4020",
    "addr:housenumber":"9",
    "addr:postcode":"4020",
    "addr:street":"Quai Des Ardennes",
    "iso:country":"BE",
    "sg:address":"Quai Des Ardennes 9",
    "sg:city":"Li\u00c8ge",
    "sg:classifiers":[
        {
            "category":"Banks & Credit Unions",
            "subcategory":"Investment Brokerage",
            "type":"Services"
        }
    ],
    "sg:phone":"+32 4 343 42 00",
    "sg:postcode":"4020",
    "sg:province":"Li\u00e8ge",
    "sg:tags":[
        "machine",
        "mat\u00e9riel",
        "de",
        "bureau",
        "gr"
    ],
    "wof:name":"Dataco",
    "wof:placetype":"venue"
},
  "geometry": {"coordinates":[5.5842480659,50.6217651367],"type":"Point"}
}