{
  "type": "Feature",
  "properties": {
    "iso:country":"BE",
    "sg:address":"Duffelsesteenweg 166",
    "sg:city":"Kontich",
    "sg:classifiers":[
        {
            "category":"Food & Beverages",
            "subcategory":"Supermarket",
            "type":"Retail Goods"
        }
    ],
    "sg:phone":"+32 3 451 82 82",
    "sg:postcode":"2550",
    "sg:province":"Antwerpen",
    "sg:tags":[
        "frozen",
        "-"
    ],
    "wof:name":"Triple F Nv",
    "wof:placetype":"venue"
},
  "geometry": {"coordinates":[4.4641227722,51.1222305298],"type":"Point"}
}