{
  "type": "Feature",
  "properties": {
    "iso:country":"BE",
    "sg:address":"Kriekelsheuvelstraat 28",
    "sg:city":"Maaseik",
    "sg:orig_category":"Woningbouw",
    "sg:phone":"+32 89 56 45 01",
    "sg:postcode":"3680",
    "sg:province":"Limburg",
    "wof:name":"Peter Arits",
    "wof:placetype":"venue"
},
  "geometry": {"coordinates":[5.7753100395,51.1049957275],"type":"Point"}
}