{
  "type": "Feature",
  "properties": {
    "addr:full":"Juliaan Dillensstraat 52 Antwerpen Antwerpen 2018",
    "addr:housenumber":"52",
    "addr:postcode":"2018",
    "addr:street":"Juliaan Dillensstraat",
    "iso:country":"BE",
    "sg:address":"Juliaan Dillensstraat 52",
    "sg:city":"Antwerpen",
    "sg:classifiers":[
        {
            "category":"Professional",
            "subcategory":"Advertising",
            "type":"Services"
        }
    ],
    "sg:phone":"+32 3 238 80 75",
    "sg:postcode":"2018",
    "sg:province":"Antwerpen",
    "sg:tags":[
        "bill",
        "-",
        "posting"
    ],
    "wof:name":"Affichage Erauw",
    "wof:placetype":"venue"
},
  "geometry": {"coordinates":[4.395761013,51.1983604431],"type":"Point"}
}