{
  "type": "Feature",
  "properties": {
    "iso:country":"BE",
    "sg:address":"Rue Des Moulins 19",
    "sg:city":"Hognoul",
    "sg:orig_category":"Animaux domestiques and accessoires",
    "sg:phone":"+32 4 257 64 77",
    "sg:postcode":"4342",
    "sg:province":"Li\u00e8ge",
    "wof:name":"Tom & Co",
    "wof:placetype":"venue"
},
  "geometry": {"coordinates":[5.4654431343,50.6838150024],"type":"Point"}
}