{
  "type": "Feature",
  "properties": {
    "addr:full":"Charlotteborgerallee 37 Aachen 52068",
    "addr:housenumber":"37",
    "addr:postcode":"52068",
    "addr:street":"Charlotteborgerallee",
    "iso:country":"BE",
    "sg:address":"Charlotteborgerallee 37",
    "sg:city":"Aachen",
    "sg:classifiers":[
        {
            "category":"Autos & Motor Vehicles",
            "subcategory":"Automobile Sales",
            "type":"Retail Goods"
        }
    ],
    "sg:postcode":"52068",
    "sg:tags":[
        "delivery",
        "-",
        "used",
        "van",
        "truck"
    ],
    "wof:name":"Truck Center Rony Bvba",
    "wof:placetype":"venue"
},
  "geometry": {"coordinates":[6.088490963,50.778137207],"type":"Point"}
}