{
  "type": "Feature",
  "properties": {
    "iso:country":"BE",
    "sg:address":"Westerlaan 100",
    "sg:city":"Waregem",
    "sg:orig_category":"Diverse zakelijke dienstverlening",
    "sg:phone":"+32 56 60 22 41",
    "sg:postcode":"8790",
    "sg:province":"West-Vlaanderen",
    "wof:name":"Johan De Smet",
    "wof:placetype":"venue"
},
  "geometry": {"coordinates":[3.4224789143,50.8895263672],"type":"Point"}
}