{
  "type": "Feature",
  "properties": {
    "addr:full":"Calvariebergstraat 10 Brugge West-Vlaanderen 8000",
    "addr:housenumber":"10",
    "addr:postcode":"8000",
    "addr:street":"Calvariebergstraat",
    "iso:country":"BE",
    "sg:address":"Calvariebergstraat 10",
    "sg:city":"Brugge",
    "sg:classifiers":[
        {
            "category":"Travel",
            "subcategory":"Hotels & Motels",
            "type":"Entertainment"
        }
    ],
    "sg:phone":"+32 50 49 02 49",
    "sg:postcode":"8000",
    "sg:province":"West-Vlaanderen",
    "wof:name":"Bed & Breakfast Bvba",
    "wof:placetype":"venue"
},
  "geometry": {"coordinates":[3.2252800465,51.2185897827],"type":"Point"}
}