{
  "type": "Feature",
  "properties": {
    "iso:country":"BE",
    "sg:address":"Rue Du Onze Novembre 3",
    "sg:city":"Chimay",
    "sg:orig_category":"Herstellingen and onderhoud van auto's",
    "sg:phone":"+32 60 21 10 78",
    "sg:postcode":"6460",
    "sg:province":"Hainaut",
    "wof:name":"Garage Wauthier",
    "wof:placetype":"venue"
},
  "geometry": {"coordinates":[4.3104839325,50.0482597351],"type":"Point"}
}