{
  "type": "Feature",
  "properties": {
    "iso:country":"BE",
    "sg:address":"Rue Van-cutsem 33ba",
    "sg:city":"Jemeppe-sur-sambre",
    "sg:orig_category":"Artsen and specialisten",
    "sg:phone":"+32 71 78 71 70",
    "sg:postcode":"5190",
    "sg:province":"Namur",
    "wof:name":"A. Demeuse",
    "wof:placetype":"venue"
},
  "geometry": {"coordinates":[4.6602921486,50.4654655457],"type":"Point"}
}