{
  "type": "Feature",
  "properties": {
    "iso:country":"BE",
    "sg:address":"Rue De La Vall\u00c9e 36",
    "sg:city":"Elsene/ixelles",
    "sg:orig_category":"M\u00e9decins and sp\u00e9cialistes",
    "sg:phone":"+32 2 649 49 47",
    "sg:postcode":"1050",
    "sg:province":"Bruxelles-Capitale",
    "wof:name":"Sergio Hassid",
    "wof:placetype":"venue"
},
  "geometry": {"coordinates":[4.3713297844,50.8246841431],"type":"Point"}
}