{
  "type": "Feature",
  "properties": {
    "addr:full":"Koninklijke Baan 143 Koksijde West-Vlaanderen 8670",
    "addr:housenumber":"143",
    "addr:postcode":"8670",
    "addr:street":"Koninklijke Baan",
    "iso:country":"BE",
    "sg:address":"Koninklijke Baan 143",
    "sg:city":"Koksijde",
    "sg:classifiers":[
        {
            "category":"Shopping",
            "subcategory":"Clothing, Apparel, & Fashions",
            "type":"Retail Goods"
        }
    ],
    "sg:phone":"+32 58 51 60 37",
    "sg:postcode":"8670",
    "sg:province":"West-Vlaanderen",
    "sg:tags":[
        "ondergoed",
        "lingerie"
    ],
    "wof:name":"Monroe",
    "wof:placetype":"venue"
},
  "geometry": {"coordinates":[2.6337020397,51.1199150085],"type":"Point"}
}