{
  "type": "Feature",
  "properties": {
    "iso:country":"BE",
    "sg:address":"Rue Des Merlettes 5",
    "sg:city":"Thuin (goz\u00e9e)",
    "sg:classifiers":[
        {
            "category":"Health Services",
            "subcategory":"Health Practitioner",
            "type":"Services"
        }
    ],
    "sg:phone":"+32 71 51 14 84",
    "sg:postcode":"6534",
    "sg:province":"Hainaut",
    "sg:tags":[
        "physiotherapist"
    ],
    "wof:name":"Walewyns J-l",
    "wof:placetype":"venue"
},
  "geometry": {"coordinates":[4.3684248924,50.3541412354],"type":"Point"}
}