{
  "type": "Feature",
  "properties": {
    "iso:country":"BE",
    "sg:address":"Te Nijverdoncklaan 27",
    "sg:city":"Edegem",
    "sg:classifiers":[
        {
            "category":"Restaurant",
            "type":"Food & Drink"
        }
    ],
    "sg:phone":"+32 3 449 28 85",
    "sg:postcode":"2650",
    "sg:province":"Antwerpen",
    "sg:tags":[
        "industrial",
        "kitchen",
        "catering"
    ],
    "wof:name":"Multi Food Service",
    "wof:placetype":"venue"
},
  "geometry": {"coordinates":[4.4247112274,51.1647415161],"type":"Point"}
}