{
  "type": "Feature",
  "properties": {
    "iso:country":"BE",
    "sg:address":"Nijverheidsstraat 7",
    "sg:city":"Oevel",
    "sg:classifiers":[
        {
            "category":"Manufacturing",
            "subcategory":"Paper Products",
            "type":"Manufacturing & Wholesale Goods"
        }
    ],
    "sg:phone":"+32 3 830 00 48",
    "sg:postcode":"2260",
    "sg:province":"Antwerpen",
    "sg:tags":[
        "adhesive",
        "processing"
    ],
    "wof:name":"Vegram Graphics Nv",
    "wof:placetype":"venue"
},
  "geometry": {"coordinates":[4.3890638351,51.157333374],"type":"Point"}
}