{
  "type": "Feature",
  "properties": {
    "addr:full":"Kruibekestraat 2 Kruibeke Oost-Vlaanderen 9150",
    "addr:housenumber":"2",
    "addr:postcode":"9150",
    "addr:street":"Kruibekestraat",
    "iso:country":"BE",
    "sg:address":"Kruibekestraat 2",
    "sg:city":"Kruibeke",
    "sg:orig_category":"Banques and organismes de cr\u00e9dit",
    "sg:phone":"+32 3 740 02 00",
    "sg:postcode":"9150",
    "sg:province":"Oost-Vlaanderen",
    "wof:name":"Kbc",
    "wof:placetype":"venue"
},
  "geometry": {"coordinates":[4.2982668877,51.147819519],"type":"Point"}
}