{
  "type": "Feature",
  "properties": {
    "addr:full":"Rue Roblet 20-24 Nivelles Brabant Wallon 1400",
    "addr:postcode":"20-24;1400",
    "addr:street":"Rue Roblet",
    "iso:country":"BE",
    "sg:address":"Rue Roblet 20-24",
    "sg:city":"Nivelles",
    "sg:classifiers":[
        {
            "category":"Real Estate",
            "subcategory":"Surveying",
            "type":"Services"
        }
    ],
    "sg:phone":"+32 67 21 02 24",
    "sg:postcode":"1400",
    "sg:province":"Brabant Wallon",
    "sg:tags":[
        "lettering",
        "letter"
    ],
    "wof:name":"Lahey D",
    "wof:placetype":"venue"
},
  "geometry": {"coordinates":[4.3303508759,50.598285675],"type":"Point"}
}