{
  "type": "Feature",
  "properties": {
    "addr:full":"Rue Joseph-jean Merlot 27 Ans Li\u00e8ge 4430",
    "addr:housenumber":"27",
    "addr:postcode":"4430",
    "addr:street":"Rue Joseph-Jean Merlot",
    "iso:country":"BE",
    "sg:address":"Rue Joseph-jean Merlot 27",
    "sg:city":"Ans",
    "sg:classifiers":[
        {
            "category":"Professional",
            "subcategory":"Computer Services",
            "type":"Services"
        }
    ],
    "sg:phone":"+32 4 239 21 51",
    "sg:postcode":"4430",
    "sg:province":"Li\u00e8ge",
    "sg:tags":[
        "network"
    ],
    "wof:name":"Delcour Informatique",
    "wof:placetype":"venue"
},
  "geometry": {"coordinates":[5.5180540085,50.6570663452],"type":"Point"}
}