{
  "type": "Feature",
  "properties": {
    "addr:full":"Rue Raide Vall\u00e9e 158a Wanze (moha) Li\u00e8ge 4520",
    "addr:housenumber":"158a",
    "addr:postcode":"4520",
    "addr:street":"Rue Raide Valle\u0301E",
    "iso:country":"BE",
    "sg:address":"Rue Raide Vall\u00e9e 158a",
    "sg:city":"Wanze (moha)",
    "sg:classifiers":[
        {
            "category":"Building & Trades",
            "subcategory":"Electrical",
            "type":"Services"
        }
    ],
    "sg:phone":"+32 85 23 31 85",
    "sg:postcode":"4520",
    "sg:province":"Li\u00e8ge",
    "sg:tags":[
        "electric",
        "-",
        "housewiring",
        "contractor"
    ],
    "wof:name":"Rz Electricite Generale Sprl",
    "wof:placetype":"venue"
},
  "geometry": {"coordinates":[5.1706271172,50.5463752747],"type":"Point"}
}