{
  "type": "Feature",
  "properties": {
    "addr:full":"Molenakkerstraat 32 Wuustwezel Antwerpen 2990",
    "addr:housenumber":"32",
    "addr:postcode":"2990",
    "addr:street":"Molenakkerstraat",
    "iso:country":"BE",
    "sg:address":"Molenakkerstraat 32",
    "sg:city":"Wuustwezel",
    "sg:classifiers":[
        {
            "category":"Building & Trades",
            "subcategory":"Construction",
            "type":"Services"
        }
    ],
    "sg:phone":"+32 3 669 82 34",
    "sg:postcode":"2990",
    "sg:province":"Antwerpen",
    "sg:tags":[
        "commerce",
        "equipement",
        "de",
        "\u00e9v\u00e9nements",
        "pour",
        "banquet",
        "mat\u00e9riel",
        "location",
        "diver"
    ],
    "wof:name":"Fa. Aerts",
    "wof:placetype":"venue"
},
  "geometry": {"coordinates":[4.640941143,51.3939323425],"type":"Point"}
}