{
  "type": "Feature",
  "properties": {
    "iso:country":"BE",
    "sg:address":"Torhoutsestraat 18",
    "sg:city":"Oostkamp (ruddervoorde)",
    "sg:classifiers":[
        {
            "category":"Shopping",
            "subcategory":"Stationery & Office Supplies",
            "type":"Retail Goods"
        }
    ],
    "sg:phone":"+32 50 27 72 34",
    "sg:postcode":"8020",
    "sg:province":"West-Vlaanderen",
    "wof:name":"Verplancke Huis",
    "wof:placetype":"venue"
},
  "geometry": {"coordinates":[3.2062690258,51.0949134827],"type":"Point"}
}