{
  "type": "Feature",
  "properties": {
    "addr:full":"Lambertus Coolsstraat 11 Middelkerke West-Vlaanderen 8433",
    "addr:housenumber":"11",
    "addr:postcode":"8433",
    "addr:street":"Lambertus Coolsstraat",
    "iso:country":"BE",
    "sg:address":"Lambertus Coolsstraat 11",
    "sg:city":"Middelkerke",
    "sg:orig_category":"M\u00e9decins and sp\u00e9cialistes",
    "sg:phone":"+32 59 31 15 75",
    "sg:postcode":"8433",
    "sg:province":"West-Vlaanderen",
    "wof:name":"S. Daese",
    "wof:placetype":"venue"
},
  "geometry": {"coordinates":[2.8428800106,51.1548233032],"type":"Point"}
}