{
  "type": "Feature",
  "properties": {
    "addr:full":"Alfred Algoetstraat 14 Lennik Vlaams-Brabant 1750",
    "addr:housenumber":"14;1750",
    "addr:street":"Algoetstraat;Vlaams-Brabant",
    "iso:country":"BE",
    "sg:address":"Alfred Algoetstraat 14",
    "sg:city":"Lennik",
    "sg:classifiers":[
        {
            "category":"Restaurant",
            "type":"Food & Drink"
        }
    ],
    "sg:phone":"+32 2 532 35 33",
    "sg:postcode":"1750",
    "sg:province":"Vlaams-Brabant",
    "wof:name":"The Klimop",
    "wof:placetype":"venue"
},
  "geometry": {"coordinates":[4.1564102173,50.8059539795],"type":"Point"}
}