{
  "type": "Feature",
  "properties": {
    "iso:country":"BE",
    "sg:address":"Rue De Fer 28",
    "sg:city":"Namur",
    "sg:orig_category":"Electrom\u00e9nager, t\u00e9l\u00e9visions and radios",
    "sg:phone":"+32 81 22 54 67",
    "sg:postcode":"5000",
    "sg:province":"Namur",
    "wof:name":"Video Square",
    "wof:placetype":"venue"
},
  "geometry": {"coordinates":[4.8654141426,50.4656066895],"type":"Point"}
}