{
  "type": "Feature",
  "properties": {
    "addr:full":"Rue Michel Beckers 31 Vise Li\u00e8ge 4601",
    "addr:housenumber":"31",
    "addr:postcode":"4601",
    "addr:street":"Rue Michel Beckers",
    "iso:country":"BE",
    "sg:address":"Rue Michel Beckers 31",
    "sg:city":"Vise",
    "sg:orig_category":"Beautyfarms, relaxatie and lichamelijk welzijn Schoonheidssalons",
    "sg:phone":"+32 4 379 69 19",
    "sg:postcode":"4601",
    "sg:province":"Li\u00e8ge",
    "wof:name":"Nicole Franssen",
    "wof:placetype":"venue"
},
  "geometry": {"coordinates":[5.6874017715,50.6957092285],"type":"Point"}
}