{
  "type": "Feature",
  "properties": {
    "addr:full":"Heidestraat 45 Waasmunster Oost-Vlaanderen 9250",
    "addr:housenumber":"45",
    "addr:postcode":"9250",
    "addr:street":"Heidestraat",
    "iso:country":"BE",
    "sg:address":"Heidestraat 45",
    "sg:city":"Waasmunster",
    "sg:orig_category":"Artsen and specialisten",
    "sg:phone":"+32 52 46 16 36",
    "sg:postcode":"9250",
    "sg:province":"Oost-Vlaanderen",
    "wof:name":"Frank Smet",
    "wof:placetype":"venue"
},
  "geometry": {"coordinates":[4.119685173,51.1307983398],"type":"Point"}
}