{
  "type": "Feature",
  "properties": {
    "iso:country":"BE",
    "sg:address":"Hospitaalstraat 18",
    "sg:city":"Beringen",
    "sg:orig_category":"Avocats and conseillers juridiques",
    "sg:phone":"+32 11 45 43 91",
    "sg:postcode":"3582",
    "sg:province":"Limburg",
    "wof:name":"Gert Goffin",
    "wof:placetype":"venue"
},
  "geometry": {"coordinates":[5.2163729668,51.0656166077],"type":"Point"}
}