{
  "type": "Feature",
  "properties": {
    "addr:full":"Boomkinsstraat 283 Hasselt Limburg 3500",
    "addr:housenumber":"283",
    "addr:postcode":"3500",
    "addr:street":"Boomkinsstraat",
    "iso:country":"BE",
    "sg:address":"Boomkinsstraat 283",
    "sg:city":"Hasselt",
    "sg:orig_category":"Kapsalons",
    "sg:phone":"+32 11 28 38 68",
    "sg:postcode":"3500",
    "sg:province":"Limburg",
    "wof:name":"Coiffure Hassania",
    "wof:placetype":"venue"
},
  "geometry": {"coordinates":[5.3263788223,50.9188728333],"type":"Point"}
}