{
  "type": "Feature",
  "properties": {
    "addr:full":"Hooidonck 38 Zandhoven Antwerpen 2240",
    "addr:housenumber":"38",
    "addr:postcode":"2240",
    "addr:street":"Hooidonck",
    "iso:country":"BE",
    "sg:address":"Hooidonck 38",
    "sg:city":"Zandhoven",
    "sg:orig_category":"Catering and organisation de f\u00eates",
    "sg:phone":"+32 3 484 49 03",
    "sg:postcode":"2240",
    "sg:province":"Antwerpen",
    "wof:name":"Lenglez Roger Traiteur",
    "wof:placetype":"venue"
},
  "geometry": {"coordinates":[4.6833767891,51.2375602722],"type":"Point"}
}