{
  "type": "Feature",
  "properties": {
    "addr:full":"Rue D'yernawe 1 Verlaine Li\u00e8ge 4537",
    "addr:housenumber":"1",
    "addr:postcode":"4537",
    "addr:street":"Rue D'Yernawe",
    "iso:country":"BE",
    "sg:address":"Rue D'yernawe 1",
    "sg:city":"Verlaine",
    "sg:classifiers":[
        {
            "category":"Professional",
            "type":"Services"
        }
    ],
    "sg:phone":"+32 4 259 60 15",
    "sg:postcode":"4537",
    "sg:province":"Li\u00e8ge",
    "sg:tags":[
        "aux",
        "diver",
        "personnes"
    ],
    "wof:name":"Jacques Robert",
    "wof:placetype":"venue"
},
  "geometry": {"coordinates":[5.3145470619,50.5888519287],"type":"Point"}
}