{
  "type": "Feature",
  "properties": {
    "iso:country":"BE",
    "sg:address":"Rue Du Bailli 36",
    "sg:city":"Brussel/bruxelles",
    "sg:orig_category":"Boucheries",
    "sg:phone":"+32 2 648 72 46",
    "sg:postcode":"1000",
    "sg:province":"Bruxelles-Capitale",
    "wof:name":"Boucherie Patrick",
    "wof:placetype":"venue"
},
  "geometry": {"coordinates":[4.3620858192,50.8265838623],"type":"Point"}
}