{
  "type": "Feature",
  "properties": {
    "iso:country":"BE",
    "sg:address":"Rond Punt 7",
    "sg:city":"Alken",
    "sg:orig_category":"Installatie van houten of kunststof schrijnwerk",
    "sg:phone":"+32 11 31 29 01",
    "sg:postcode":"3570",
    "sg:province":"Limburg",
    "wof:name":"Luc America",
    "wof:placetype":"venue"
},
  "geometry": {"coordinates":[5.274310112,50.8736495972],"type":"Point"}
}