{
  "type": "Feature",
  "properties": {
    "iso:country":"BE",
    "sg:address":"Pl. Quartier St.-jacques 22",
    "sg:city":"Braine-l'alleud",
    "sg:orig_category":"Apotheken",
    "sg:phone":"+32 2 384 46 00",
    "sg:postcode":"1420",
    "sg:province":"Brabant Wallon",
    "wof:name":"C. Parvais",
    "wof:placetype":"venue"
},
  "geometry": {"coordinates":[19.1364707947,51.9225082397],"type":"Point"}
}