{
  "type": "Feature",
  "properties": {
    "addr:full":"Molenstraat 30b11 Genk Limburg 3600",
    "addr:housenumber":"30b11",
    "addr:postcode":"3600",
    "addr:street":"Molenstraat",
    "iso:country":"BE",
    "sg:address":"Molenstraat 30b11",
    "sg:city":"Genk",
    "sg:orig_category":"D\u00e9corateurs d'int\u00e9rieur",
    "sg:phone":"+32 89 35 15 56",
    "sg:postcode":"3600",
    "sg:province":"Limburg",
    "wof:name":"Lambrechts Erik",
    "wof:placetype":"venue"
},
  "geometry": {"coordinates":[5.5019378662,50.9642028809],"type":"Point"}
}