{
  "type": "Feature",
  "properties": {
    "addr:full":"Stationsstraat 1b4 Neerpelt Limburg 3910",
    "addr:housenumber":"1b4",
    "addr:postcode":"3910",
    "addr:street":"Stationsstraat",
    "iso:country":"BE",
    "sg:address":"Stationsstraat 1b4",
    "sg:city":"Neerpelt",
    "sg:orig_category":"Tijdelijke werkgelegenheid and uitzendkantoren",
    "sg:phone":"+32 11 80 11 00",
    "sg:postcode":"3910",
    "sg:province":"Limburg",
    "wof:name":"Actief Interim",
    "wof:placetype":"venue"
},
  "geometry": {"coordinates":[5.4346342087,51.2282943726],"type":"Point"}
}