{
  "type": "Feature",
  "properties": {
    "addr:full":"Maalse Steenweg 37 Brugge (sint-kruis) West-Vlaanderen 8310",
    "addr:housenumber":"37",
    "addr:postcode":"8310",
    "addr:street":"Maalse Steenweg",
    "iso:country":"BE",
    "sg:address":"Maalse Steenweg 37",
    "sg:city":"Brugge (sint-kruis)",
    "sg:classifiers":[
        {
            "category":"Autos & Motor Vehicles",
            "subcategory":"Boat Sales",
            "type":"Retail Goods"
        }
    ],
    "sg:phone":"+32 50 35 72 49",
    "sg:postcode":"8310",
    "sg:province":"West-Vlaanderen",
    "sg:tags":[
        "balloon"
    ],
    "wof:name":"Ballonneke ('t)",
    "wof:placetype":"venue"
},
  "geometry": {"coordinates":[3.2438819408,51.2106056213],"type":"Point"}
}