{
  "type": "Feature",
  "properties": {
    "iso:country":"BE",
    "sg:address":"Alexisplein 15",
    "sg:city":"Poperinge",
    "sg:orig_category":"Enseignement maternel and primaire",
    "sg:phone":"+32 57 30 05 33",
    "sg:postcode":"8972",
    "sg:province":"West-Vlaanderen",
    "wof:name":"Vrije Basisschool",
    "wof:placetype":"venue"
},
  "geometry": {"coordinates":[2.6573059559,50.8920707703],"type":"Point"}
}