{
  "type": "Feature",
  "properties": {
    "addr:full":"Nieuwe Baan 43 Beveren (vrasene) Oost-Vlaanderen 9120",
    "addr:housenumber":"43",
    "addr:postcode":"9120",
    "addr:street":"Nieuwe Baan",
    "iso:country":"BE",
    "sg:address":"Nieuwe Baan 43",
    "sg:city":"Beveren (vrasene)",
    "sg:classifiers":[
        {
            "category":"Personal",
            "subcategory":"Beauty Salon",
            "type":"Services"
        }
    ],
    "sg:phone":"+32 3 775 95 12",
    "sg:postcode":"9120",
    "sg:province":"Oost-Vlaanderen",
    "sg:tags":[
        "lady",
        "-",
        "hairdressing"
    ],
    "wof:name":"Marc",
    "wof:placetype":"venue"
},
  "geometry": {"coordinates":[4.1937952042,51.2217445374],"type":"Point"}
}