{
  "type": "Feature",
  "properties": {
    "addr:full":"Stationlaan 32 Bilzen Limburg 3740",
    "addr:housenumber":"32",
    "addr:postcode":"3740",
    "addr:street":"Stationlaan",
    "iso:country":"BE",
    "sg:address":"Stationlaan 32",
    "sg:city":"Bilzen",
    "sg:orig_category":"M\u00e9decins and sp\u00e9cialistes",
    "sg:phone":"+32 89 41 52 13",
    "sg:postcode":"3740",
    "sg:province":"Limburg",
    "wof:name":"Liesbet Rubens",
    "wof:placetype":"venue"
},
  "geometry": {"coordinates":[5.5115361214,50.8690719604],"type":"Point"}
}