{
  "type": "Feature",
  "properties": {
    "iso:country":"BE",
    "sg:address":"Denstraat 85",
    "sg:city":"Dendermonde (grembergen)",
    "sg:classifiers":[
        {
            "category":"Building & Trades",
            "subcategory":"Pest Control",
            "type":"Services"
        }
    ],
    "sg:phone":"+32 52 21 67 08",
    "sg:postcode":"9200",
    "sg:province":"Oost-Vlaanderen",
    "sg:tags":[
        "painting",
        "contractor"
    ],
    "wof:name":"Dierickx J",
    "wof:placetype":"venue"
},
  "geometry": {"coordinates":[4.1250782013,51.0607032776],"type":"Point"}
}