{
  "type": "Feature",
  "properties": {
    "addr:full":"Pastoor Soeteweystraat 10 Mortsel Antwerpen 2640",
    "addr:housenumber":"10",
    "addr:postcode":"2640",
    "addr:street":"Pastoor Soeteweystraat",
    "iso:country":"BE",
    "sg:address":"Pastoor Soeteweystraat 10",
    "sg:city":"Mortsel",
    "sg:orig_category":"Secretariaatsdiensten",
    "sg:phone":"+32 3 454 33 16",
    "sg:postcode":"2640",
    "sg:province":"Antwerpen",
    "wof:name":"Fa. Graphic",
    "wof:placetype":"venue"
},
  "geometry": {"coordinates":[4.4740900993,51.1707115173],"type":"Point"}
}