{
  "type": "Feature",
  "properties": {
    "iso:country":"BE",
    "sg:address":"Rue Rogier 13",
    "sg:city":"Namur",
    "sg:classifiers":[
        {
            "category":"Retail",
            "subcategory":"Repair Shop",
            "type":"Services"
        }
    ],
    "sg:phone":"+32 81 22 30 25",
    "sg:postcode":"5000",
    "sg:province":"Namur",
    "sg:tags":[
        "machine",
        "sewing",
        "-"
    ],
    "wof:name":"Parisi Etablissements",
    "wof:placetype":"venue"
},
  "geometry": {"coordinates":[4.8662590981,50.467880249],"type":"Point"}
}