{
  "type": "Feature",
  "properties": {
    "addr:full":"Ferdinand Elbersstraat 20 Sint-jans-molenbeek/molenbeek-saint-jean Bruxelles-Capitale 1080",
    "addr:housenumber":"20",
    "addr:postcode":"1080",
    "addr:street":"Ferdinand Elbersstraat",
    "iso:country":"BE",
    "sg:address":"Ferdinand Elbersstraat 20",
    "sg:city":"Sint-jans-molenbeek/molenbeek-saint-jean",
    "sg:orig_category":"Rusthuizen and serviceflats",
    "sg:phone":"+32 2 465 24 17",
    "sg:postcode":"1080",
    "sg:province":"Bruxelles-Capitale",
    "wof:name":"O.c.m.w. Arcadia",
    "wof:placetype":"venue"
},
  "geometry": {"coordinates":[4.2937021255,50.8552398682],"type":"Point"}
}