{
  "type": "Feature",
  "properties": {
    "iso:country":"BE",
    "sg:address":"Kerkstraat 245",
    "sg:city":"Blankenberge",
    "sg:classifiers":[
        {
            "category":"Insurance",
            "subcategory":"Insurance Agent",
            "type":"Services"
        }
    ],
    "sg:phone":"+32 50 42 90 12",
    "sg:postcode":"8370",
    "sg:province":"West-Vlaanderen",
    "sg:tags":[
        "broker"
    ],
    "wof:name":"Bernaert P",
    "wof:placetype":"venue"
},
  "geometry": {"coordinates":[3.1368870735,51.3086433411],"type":"Point"}
}