{
  "type": "Feature",
  "properties": {
    "addr:full":"Oostbroekstraat 16 Houthulst West-Vlaanderen 8650",
    "addr:housenumber":"16",
    "addr:postcode":"8650",
    "addr:street":"Oostbroekstraat",
    "iso:country":"BE",
    "sg:address":"Oostbroekstraat 16",
    "sg:city":"Houthulst",
    "sg:orig_category":"Rev\u00eatements pour sols and murs. Construction de maisons",
    "sg:phone":"+32 51 54 54 73",
    "sg:postcode":"8650",
    "sg:province":"West-Vlaanderen",
    "wof:name":"Borra G.",
    "wof:placetype":"venue"
},
  "geometry": {"coordinates":[2.9509439468,50.9778862],"type":"Point"}
}