{
  "type": "Feature",
  "properties": {
    "iso:country":"BE",
    "sg:address":"Place Des Guillemins 21",
    "sg:city":"Li\u00c8ge",
    "sg:classifiers":[
        {
            "category":"Cafe",
            "type":"Food & Drink"
        }
    ],
    "sg:phone":"+32 4 253 28 38",
    "sg:postcode":"4000",
    "sg:province":"Li\u00e8ge",
    "sg:tags":[
        "caf\u00e9s"
    ],
    "wof:name":"Caf\u00c9 Le Transeurop",
    "wof:placetype":"venue"
},
  "geometry": {"coordinates":[5.5666251183,50.6254234314],"type":"Point"}
}