{
  "type": "Feature",
  "properties": {
    "addr:full":"Rue Des Canadiens 212 Mons (hyon) Hainaut 7022",
    "addr:housenumber":"212",
    "addr:postcode":"7022",
    "addr:street":"Rue Des Canadiens",
    "iso:country":"BE",
    "sg:address":"Rue Des Canadiens 212",
    "sg:city":"Mons (hyon)",
    "sg:classifiers":[
        {
            "category":"Building & Trades",
            "subcategory":"Cleaning & Sanitation",
            "type":"Services"
        }
    ],
    "sg:phone":"+32 65 31 29 26",
    "sg:postcode":"7022",
    "sg:province":"Hainaut",
    "wof:name":"Mersch G",
    "wof:placetype":"venue"
},
  "geometry": {"coordinates":[3.9554300308,50.4336509705],"type":"Point"}
}