{
  "type": "Feature",
  "properties": {
    "iso:country":"BE",
    "sg:address":"Driesstraat 59",
    "sg:city":"Zwevegem",
    "sg:orig_category":"V\u00eatements pour Hommes. V\u00eatements sur mesure Fab",
    "sg:phone":"+32 56 45 61 20",
    "sg:postcode":"8554",
    "sg:province":"West-Vlaanderen",
    "wof:name":"Mortier Kleding",
    "wof:placetype":"venue"
},
  "geometry": {"coordinates":[3.3635320663,50.7582931519],"type":"Point"}
}