{
  "type": "Feature",
  "properties": {
    "iso:country":"BE",
    "sg:address":"Rue Du Pont Du Christ 54",
    "sg:city":"Wavre",
    "sg:orig_category":"Diverse producten Fab Fotogravure and zetwerk Herstelling leer and schoeisel Herstellingswinkels voo",
    "sg:phone":"+32 10 22 62 58",
    "sg:postcode":"1300",
    "sg:province":"Brabant Wallon",
    "wof:name":"Mister Mint",
    "wof:placetype":"venue"
},
  "geometry": {"coordinates":[4.6089630127,50.7159919739],"type":"Point"}
}