{
  "type": "Feature",
  "properties": {
    "iso:country":"BE",
    "sg:address":"Heuvelstraat 36",
    "sg:city":"Lanaken",
    "sg:orig_category":"Electrom\u00e9nager, t\u00e9l\u00e9visions and radios",
    "sg:phone":"+32 89 72 15 17",
    "sg:postcode":"3620",
    "sg:province":"Limburg",
    "wof:name":"Geeraerts Software",
    "wof:placetype":"venue"
},
  "geometry": {"coordinates":[5.6514000893,50.8921737671],"type":"Point"}
}