{
  "type": "Feature",
  "properties": {
    "addr:full":"Thier Des Malades 7ba Huy Li\u00e8ge 4500",
    "addr:housenumber":"7ba",
    "addr:postcode":"4500",
    "addr:street":"Thier Des Malades",
    "iso:country":"BE",
    "sg:address":"Thier Des Malades 7ba",
    "sg:city":"Huy",
    "sg:orig_category":"Dameskledingzaken",
    "sg:phone":"+32 85 25 36 83",
    "sg:postcode":"4500",
    "sg:province":"Li\u00e8ge",
    "wof:name":"Maison Zakar\u00b4in",
    "wof:placetype":"venue"
},
  "geometry": {"coordinates":[5.244301796,50.5342674255],"type":"Point"}
}