{
  "type": "Feature",
  "properties": {
    "addr:full":"Boomsesteenweg 960 Aartselaar Antwerpen 2630",
    "addr:housenumber":"960",
    "addr:postcode":"2630",
    "addr:street":"Boomsesteenweg",
    "iso:country":"BE",
    "sg:address":"Boomsesteenweg 960",
    "sg:city":"Aartselaar",
    "sg:orig_category":"V\u00eatements",
    "sg:phone":"+32 3 877 42 58",
    "sg:postcode":"2630",
    "sg:province":"Antwerpen",
    "wof:name":"Pelsland",
    "wof:placetype":"venue"
},
  "geometry": {"coordinates":[4.3704500198,51.1114311218],"type":"Point"}
}