{
  "type": "Feature",
  "properties": {
    "iso:country":"BE",
    "sg:address":"Rue Saint-hubert 4",
    "sg:city":"Arlon",
    "sg:orig_category":"Epiceries",
    "sg:phone":"+32 63 22 28 17",
    "sg:postcode":"6700",
    "sg:province":"Luxembourg",
    "wof:name":"Marie Mertens",
    "wof:placetype":"venue"
},
  "geometry": {"coordinates":[5.8030028343,49.6840896606],"type":"Point"}
}