{
  "type": "Feature",
  "properties": {
    "addr:full":"Jan Breydellaan 31 Brugge (sint-andries) West-Vlaanderen 8200",
    "addr:housenumber":"31",
    "addr:postcode":"8200",
    "addr:street":"Jan Breydellaan",
    "iso:country":"BE",
    "sg:address":"Jan Breydellaan 31",
    "sg:city":"Brugge (sint-andries)",
    "sg:orig_category":"Newspapers, magazines, periodicals - Distribution",
    "sg:phone":"+32 50 32 09 63",
    "sg:postcode":"8200",
    "sg:province":"West-Vlaanderen",
    "wof:name":"Krantenweelde",
    "wof:placetype":"venue"
},
  "geometry": {"coordinates":[3.2087519169,51.2069702148],"type":"Point"}
}