{
  "type": "Feature",
  "properties": {
    "iso:country":"BE",
    "sg:address":"Mosveldstraat 2a",
    "sg:city":"Haaltert",
    "sg:classifiers":[
        {
            "category":"Building & Trades",
            "subcategory":"Pest Control",
            "type":"Services"
        }
    ],
    "sg:phone":"+32 53 83 74 08",
    "sg:postcode":"9450",
    "sg:province":"Oost-Vlaanderen",
    "sg:tags":[
        "painting",
        "contractor"
    ],
    "wof:name":"Vijverman W",
    "wof:placetype":"venue"
},
  "geometry": {"coordinates":[3.9732398987,50.88829422],"type":"Point"}
}