{
  "type": "Feature",
  "properties": {
    "iso:country":"BE",
    "sg:address":"Handelslei 72",
    "sg:city":"Zoersel",
    "sg:orig_category":"Enseignement maternel and primaire",
    "sg:phone":"+32 3 383 30 37",
    "sg:postcode":"2980",
    "sg:province":"Antwerpen",
    "wof:name":"Vrije Basisschool",
    "wof:placetype":"venue"
},
  "geometry": {"coordinates":[4.6484470367,51.2730941772],"type":"Point"}
}