{
  "type": "Feature",
  "properties": {
    "iso:country":"BE",
    "sg:address":"Moortelhoekstraat 8",
    "sg:city":"Sint-niklaas",
    "sg:orig_category":"Installation de menuiserie en bois and plastique",
    "sg:phone":"+32 3 772 59 92",
    "sg:postcode":"9111",
    "sg:province":"Oost-Vlaanderen",
    "wof:name":"Thoen Gebrs",
    "wof:placetype":"venue"
},
  "geometry": {"coordinates":[4.0958771706,51.159160614],"type":"Point"}
}