{
  "type": "Feature",
  "properties": {
    "iso:country":"BE",
    "sg:address":"Kalkoenstraat 6",
    "sg:city":"Moorslede",
    "sg:classifiers":[
        {
            "category":"Manufacturing",
            "subcategory":"Tobacco Products",
            "type":"Manufacturing & Wholesale Goods"
        }
    ],
    "sg:phone":"+32 51 77 81 10",
    "sg:postcode":"8890",
    "sg:province":"West-Vlaanderen",
    "sg:tags":[
        "soil",
        "peat"
    ],
    "wof:name":"Leenknecht Jacky Bvba",
    "wof:placetype":"venue"
},
  "geometry": {"coordinates":[3.0958271027,50.8977012634],"type":"Point"}
}