{
  "type": "Feature",
  "properties": {
    "addr:full":"Gentsesteenweg 62 Asse Vlaams-Brabant 1730",
    "addr:housenumber":"62",
    "addr:postcode":"1730",
    "addr:street":"Gentsesteenweg",
    "iso:country":"BE",
    "sg:address":"Gentsesteenweg 62",
    "sg:city":"Asse",
    "sg:classifiers":[
        {
            "category":"Health Services",
            "subcategory":"Doctor",
            "type":"Services"
        }
    ],
    "sg:phone":"+32 2 452 44 99",
    "sg:postcode":"1730",
    "sg:province":"Vlaams-Brabant",
    "sg:tags":[
        "medicinephysicians",
        "surgeon"
    ],
    "wof:name":"Janssens Sven",
    "wof:placetype":"venue"
},
  "geometry": {"coordinates":[4.1821551323,50.9199714661],"type":"Point"}
}