{
  "type": "Feature",
  "properties": {
    "iso:country":"BE",
    "sg:address":"Venetielaan 40",
    "sg:city":"Harelbeke",
    "sg:classifiers":[
        {
            "category":"Building & Trades",
            "subcategory":"Construction",
            "type":"Services"
        }
    ],
    "sg:phone":"+32 3 827 39 45",
    "sg:postcode":"8530",
    "sg:province":"West-Vlaanderen",
    "sg:tags":[
        "swimming-pool"
    ],
    "wof:name":"Plastex Nv",
    "wof:placetype":"venue"
},
  "geometry": {"coordinates":[4.3686218262,51.159362793],"type":"Point"}
}