{
  "type": "Feature",
  "properties": {
    "iso:country":"BE",
    "sg:address":"Fortstraat 25",
    "sg:city":"Berlare",
    "sg:orig_category":"Diverse bouwafwerking and reiniging Industri\u00eble wasserijen and droogkuis",
    "sg:phone":"+32 9 367 53 75",
    "sg:postcode":"9290",
    "sg:province":"Oost-Vlaanderen",
    "wof:name":"Danyshop",
    "wof:placetype":"venue"
},
  "geometry": {"coordinates":[3.952559948,51.0467147827],"type":"Point"}
}