{
  "type": "Feature",
  "properties": {
    "iso:country":"BE",
    "sg:address":"Bilzersteenweg 4",
    "sg:city":"Riemst",
    "sg:classifiers":[
        {
            "category":"Food & Beverages",
            "subcategory":"Supermarket",
            "type":"Retail Goods"
        }
    ],
    "sg:phone":"+32 12 45 15 86",
    "sg:postcode":"3770",
    "sg:province":"Limburg",
    "sg:tags":[
        "department",
        "store"
    ],
    "wof:name":"Superette Indi",
    "wof:placetype":"venue"
},
  "geometry": {"coordinates":[5.5950222015,50.8122558594],"type":"Point"}
}