{
  "type": "Feature",
  "properties": {
    "iso:country":"BE",
    "sg:address":"Rue Des 4 Bras 70",
    "sg:city":"Lobbes",
    "sg:classifiers":[
        {
            "category":"Arena",
            "subcategory":"Sports Club",
            "type":"Entertainment"
        }
    ],
    "sg:phone":"+32 71 59 06 39",
    "sg:postcode":"6540",
    "sg:province":"Hainaut",
    "sg:tags":[
        "de"
    ],
    "wof:name":"V.c. Le Scavin",
    "wof:placetype":"venue"
},
  "geometry": {"coordinates":[4.2723298073,50.360408783],"type":"Point"}
}