{
  "type": "Feature",
  "properties": {
    "addr:full":"Avenue Adolphe Schattens 34 Box 1 Waterloo Brabant Wallon 1410",
    "addr:housenumber":"34;1",
    "addr:postcode":"1410",
    "addr:street":"Avenue Adolphe Schattens;Box",
    "iso:country":"BE",
    "sg:address":"Avenue Adolphe Schattens 34 Box 1",
    "sg:city":"Waterloo",
    "sg:classifiers":[
        {
            "category":"Professional",
            "subcategory":"Engineering",
            "type":"Services"
        }
    ],
    "sg:phone":"+32 2 384 14 47",
    "sg:postcode":"1410",
    "sg:province":"Brabant Wallon",
    "sg:tags":[
        "-"
    ],
    "wof:name":"V.t.a. Sprl",
    "wof:placetype":"venue"
},
  "geometry": {"coordinates":[4.392370224,50.7142028809],"type":"Point"}
}