{
  "type": "Feature",
  "properties": {
    "iso:country":"BE",
    "sg:address":"Aalterstraat 3",
    "sg:city":"Aalter",
    "sg:orig_category":"M\u00e9decins and sp\u00e9cialistes",
    "sg:phone":"+32 9 374 14 64",
    "sg:postcode":"9880",
    "sg:province":"Oost-Vlaanderen",
    "wof:name":"G. Van Haecke",
    "wof:placetype":"venue"
},
  "geometry": {"coordinates":[3.4599859715,51.0682411194],"type":"Point"}
}