{
  "type": "Feature",
  "properties": {
    "addr:full":"Rue De La Station 13 Paliseul Luxembourg 6850",
    "addr:housenumber":"13",
    "addr:postcode":"6850",
    "addr:street":"Rue De La Station",
    "iso:country":"BE",
    "sg:address":"Rue De La Station 13",
    "sg:city":"Paliseul",
    "sg:classifiers":[
        {
            "category":"Shopping",
            "subcategory":"Books",
            "type":"Retail Goods"
        }
    ],
    "sg:phone":"+32 61 53 43 69",
    "sg:postcode":"6850",
    "sg:province":"Luxembourg",
    "sg:tags":[
        "bookseller"
    ],
    "wof:name":"Librairie 2000",
    "wof:placetype":"venue"
},
  "geometry": {"coordinates":[5.1324939728,49.9026451111],"type":"Point"}
}