{
  "type": "Feature",
  "properties": {
    "addr:full":"Mieregemstraat 41 Merchtem Vlaams-Brabant 1785",
    "addr:housenumber":"41",
    "addr:postcode":"1785",
    "addr:street":"Mieregemstraat",
    "iso:country":"BE",
    "sg:address":"Mieregemstraat 41",
    "sg:city":"Merchtem",
    "sg:orig_category":"Boucheries",
    "sg:phone":"+32 52 37 10 23",
    "sg:postcode":"1785",
    "sg:province":"Vlaams-Brabant",
    "wof:name":"Jonckers",
    "wof:placetype":"venue"
},
  "geometry": {"coordinates":[4.2314190865,50.9566879272],"type":"Point"}
}