{
  "type": "Feature",
  "properties": {
    "addr:full":"Rue Haie De Barse 4 Modave Li\u00e8ge 4577",
    "addr:housenumber":"4",
    "addr:postcode":"4577",
    "addr:street":"Rue Haie De Barse",
    "iso:country":"BE",
    "sg:address":"Rue Haie De Barse 4",
    "sg:city":"Modave",
    "sg:orig_category":"Dakwerken Loodgieterij and centrale verwarming Gh Loodgieterij, verwarming and sanitaire installatie",
    "sg:phone":"+32 85 41 23 63",
    "sg:postcode":"4577",
    "sg:province":"Li\u00e8ge",
    "wof:name":"Messere",
    "wof:placetype":"venue"
},
  "geometry": {"coordinates":[5.2979922295,50.4443855286],"type":"Point"}
}