{
  "type": "Feature",
  "properties": {
    "iso:country":"BE",
    "sg:address":"Rue De L'auflette 129",
    "sg:city":"Mons (cuesmes)",
    "sg:classifiers":[
        {
            "category":"Home & Garden",
            "subcategory":"Garden Supply",
            "type":"Retail Goods"
        }
    ],
    "sg:phone":"+32 65 35 15 57",
    "sg:postcode":"7033",
    "sg:province":"Hainaut",
    "sg:tags":[
        "machine",
        "agricultural",
        "-"
    ],
    "wof:name":"Renvillard",
    "wof:placetype":"venue"
},
  "geometry": {"coordinates":[3.9094619751,50.4430770874],"type":"Point"}
}