{
  "type": "Feature",
  "properties": {
    "addr:full":"Sint-michielsstraat 41 Brussel/bruxelles Bruxelles-Capitale 1000",
    "addr:housenumber":"41",
    "addr:postcode":"1000",
    "addr:street":"Sint-Michielsstraat;/",
    "iso:country":"BE",
    "sg:address":"Sint-michielsstraat 41",
    "sg:city":"Brussel/bruxelles",
    "sg:orig_category":"Musea and historische gebouwen",
    "sg:phone":"+32 2 219 11 83",
    "sg:postcode":"1000",
    "sg:province":"Bruxelles-Capitale",
    "wof:name":"L'autre Mus\u00c9e",
    "wof:placetype":"venue"
},
  "geometry": {"coordinates":[4.3559379578,50.8517799377],"type":"Point"}
}