{
  "type": "Feature",
  "properties": {
    "addr:full":"Kollegestraat 15 Geel Antwerpen 2440",
    "addr:housenumber":"15",
    "addr:postcode":"2440",
    "addr:street":"Kollegestraat",
    "iso:country":"BE",
    "sg:address":"Kollegestraat 15",
    "sg:city":"Geel",
    "sg:orig_category":"Enseignement maternel and primaire",
    "sg:phone":"+32 14 56 26 56",
    "sg:postcode":"2440",
    "sg:province":"Antwerpen",
    "wof:name":"Vrije Basisschool",
    "wof:placetype":"venue"
},
  "geometry": {"coordinates":[4.9935221672,51.1607818604],"type":"Point"}
}