{
  "type": "Feature",
  "properties": {
    "iso:country":"BE",
    "sg:address":"Rekkemstraat 62",
    "sg:city":"Lauwe",
    "sg:classifiers":[
        {
            "category":"Building & Trades",
            "subcategory":"Construction",
            "type":"Services"
        }
    ],
    "sg:phone":"+32 56 41 75 97",
    "sg:postcode":"8930",
    "sg:province":"West-Vlaanderen",
    "sg:tags":[
        "carpenter's",
        "work",
        "supraregional"
    ],
    "wof:name":"Coeman Henri B.v.b.a.",
    "wof:placetype":"venue"
},
  "geometry": {"coordinates":[3.1769459248,50.7932281494],"type":"Point"}
}