{
  "type": "Feature",
  "properties": {
    "addr:full":"Rue Charles Rittw\u00e9ger 196 Theux Li\u00e8ge 4910",
    "addr:housenumber":"196",
    "addr:postcode":"4910",
    "addr:street":"Rue Charles Rittwe\u0301Ger",
    "iso:country":"BE",
    "sg:address":"Rue Charles Rittw\u00e9ger 196",
    "sg:city":"Theux",
    "sg:classifiers":[
        {
            "category":"Social Services",
            "subcategory":"Child Care",
            "type":"Services"
        }
    ],
    "sg:phone":"+32 87 54 27 23",
    "sg:postcode":"4910",
    "sg:province":"Li\u00e8ge",
    "sg:tags":[
        "baby",
        "nursery",
        "day",
        "sitting"
    ],
    "wof:name":"Marmousets (cr\u00eache Les)",
    "wof:placetype":"venue"
},
  "geometry": {"coordinates":[5.8128199577,50.5394210815],"type":"Point"}
}