{
  "type": "Feature",
  "properties": {
    "addr:full":"Rue D'hoves 8 Silly Hainaut 7830",
    "addr:housenumber":"8",
    "addr:postcode":"7830",
    "addr:street":"Rue D'Hoves",
    "iso:country":"BE",
    "sg:address":"Rue D'hoves 8",
    "sg:city":"Silly",
    "sg:orig_category":"Enseignement maternel and primaire",
    "sg:phone":"+32 67 45 86 85",
    "sg:postcode":"7830",
    "sg:province":"Hainaut",
    "wof:name":"Ecole Fond. Communale",
    "wof:placetype":"venue"
},
  "geometry": {"coordinates":[4.0361409187,50.670211792],"type":"Point"}
}