{
  "type": "Feature",
  "properties": {
    "addr:full":"Rumoldusstraat 66b Dilbeek (schepdaal) Vlaams-Brabant 1703",
    "addr:housenumber":"66b",
    "addr:postcode":"1703",
    "addr:street":"Rumoldusstraat",
    "iso:country":"BE",
    "sg:address":"Rumoldusstraat 66b",
    "sg:city":"Dilbeek (schepdaal)",
    "sg:classifiers":[
        {
            "category":"Professional",
            "subcategory":"Management & Consulting",
            "type":"Services"
        }
    ],
    "sg:phone":"+32 2 569 36 88",
    "sg:postcode":"1703",
    "sg:province":"Vlaams-Brabant",
    "sg:tags":[
        "consultant"
    ],
    "wof:name":"V Demeulenaere & Associates",
    "wof:placetype":"venue"
},
  "geometry": {"coordinates":[4.1968011856,50.8403625488],"type":"Point"}
}