{
  "type": "Feature",
  "properties": {
    "iso:country":"BE",
    "sg:address":"Zomerlaan 4",
    "sg:city":"Middelkerke",
    "sg:orig_category":"Pensions de famille",
    "sg:phone":"+32 59 31 27 52",
    "sg:postcode":"8434",
    "sg:province":"West-Vlaanderen",
    "wof:name":"Vandenbulcke L.",
    "wof:placetype":"venue"
},
  "geometry": {"coordinates":[2.7569050789,51.1488685608],"type":"Point"}
}