{
  "type": "Feature",
  "properties": {
    "addr:full":"Steenweg Naar Eigenbrakel 8 Beersel (alsemberg) Vlaams-Brabant 1652",
    "addr:housenumber":"8",
    "addr:postcode":"1652",
    "addr:street":"Steenweg Naar Eigenbrakel",
    "iso:country":"BE",
    "sg:address":"Steenweg Naar Eigenbrakel 8",
    "sg:city":"Beersel (alsemberg)",
    "sg:orig_category":"Newspapers, magazines, periodicals - Distribution",
    "sg:phone":"+32 2 380 32 23",
    "sg:postcode":"1652",
    "sg:province":"Vlaams-Brabant",
    "wof:name":"Gamma",
    "wof:placetype":"venue"
},
  "geometry": {"coordinates":[4.3377361298,50.7408294678],"type":"Point"}
}