{
  "type": "Feature",
  "properties": {
    "addr:full":"Bergstraat 53 Heist-op-den-berg Antwerpen 2220",
    "addr:housenumber":"53",
    "addr:postcode":"2220",
    "addr:street":"Bergstraat",
    "iso:country":"BE",
    "sg:address":"Bergstraat 53",
    "sg:city":"Heist-op-den-berg",
    "sg:orig_category":"Non-Classified Establishments",
    "sg:phone":"+32 15 24 12 06",
    "sg:postcode":"2220",
    "sg:province":"Antwerpen",
    "wof:name":"Dijkmans",
    "wof:placetype":"venue"
},
  "geometry": {"coordinates":[4.7230491638,51.07579422],"type":"Point"}
}