{
  "type": "Feature",
  "properties": {
    "addr:full":"Place De Ligny 18 Sombreffe Namur 5140",
    "addr:housenumber":"18",
    "addr:postcode":"5140",
    "addr:street":"Place De Ligny",
    "iso:country":"BE",
    "sg:address":"Place De Ligny 18",
    "sg:city":"Sombreffe",
    "sg:classifiers":[
        {
            "category":"Arena",
            "subcategory":"Sports Club",
            "type":"Entertainment"
        }
    ],
    "sg:phone":"+32 71 88 94 29",
    "sg:postcode":"5140",
    "sg:province":"Namur",
    "sg:tags":[
        "de"
    ],
    "wof:name":"E.b.c. Ligny",
    "wof:placetype":"venue"
},
  "geometry": {"coordinates":[4.5738511086,50.5123901367],"type":"Point"}
}