{
  "type": "Feature",
  "properties": {
    "iso:country":"BE",
    "sg:address":"Hoogstraat 110",
    "sg:city":"Deerlijk",
    "sg:classifiers":[
        {
            "category":"Retail",
            "subcategory":"Veterinary Services",
            "type":"Services"
        }
    ],
    "sg:phone":"+32 56 72 54 91",
    "sg:postcode":"8540",
    "sg:province":"West-Vlaanderen",
    "sg:tags":[
        "veterinarian"
    ],
    "wof:name":"Wallays J",
    "wof:placetype":"venue"
},
  "geometry": {"coordinates":[3.3546180725,50.8541030884],"type":"Point"}
}