{
  "type": "Feature",
  "properties": {
    "addr:full":"Oude Veurnestraat 83 Ieper West-Vlaanderen 8900",
    "addr:housenumber":"83",
    "addr:postcode":"8900",
    "addr:street":"Oude Veurnestraat",
    "iso:country":"BE",
    "sg:address":"Oude Veurnestraat 83",
    "sg:city":"Ieper",
    "sg:orig_category":"Imprimeries and copyshops",
    "sg:phone":"+32 57 21 32 40",
    "sg:postcode":"8900",
    "sg:province":"West-Vlaanderen",
    "wof:name":"Frans Victoor",
    "wof:placetype":"venue"
},
  "geometry": {"coordinates":[2.8714699745,50.8576889038],"type":"Point"}
}