{
  "type": "Feature",
  "properties": {
    "iso:country":"BE",
    "sg:address":"Markt 19",
    "sg:city":"Maaseik",
    "sg:classifiers":[
        {
            "category":"Restaurant",
            "type":"Food & Drink"
        }
    ],
    "sg:phone":"+32 89 56 40 89",
    "sg:postcode":"3680",
    "sg:province":"Limburg",
    "wof:name":"Tiffany's",
    "wof:placetype":"venue"
},
  "geometry": {"coordinates":[5.791893959,51.094291687],"type":"Point"}
}