{
  "type": "Feature",
  "properties": {
    "addr:full":"Onze-lieve-vrouwstraat 40 Herent Vlaams-Brabant 3020",
    "addr:housenumber":"40",
    "addr:postcode":"3020",
    "addr:street":"Onze-Lieve-Vrouwstraat",
    "iso:country":"BE",
    "sg:address":"Onze-lieve-vrouwstraat 40",
    "sg:city":"Herent",
    "sg:orig_category":"Epiceries",
    "sg:phone":"+32 16 22 76 26",
    "sg:postcode":"3020",
    "sg:province":"Vlaams-Brabant",
    "wof:name":"G. Saelens",
    "wof:placetype":"venue"
},
  "geometry": {"coordinates":[4.673625946,50.9062957764],"type":"Point"}
}