{
  "type": "Feature",
  "properties": {
    "iso:country":"BE",
    "sg:address":"Rue Des Francs Arquebusiers 2 A",
    "sg:city":"Vise",
    "sg:orig_category":"Electrom\u00e9nager, t\u00e9l\u00e9visions and radios. R\u00e9parations d'appareils \u00e9lectrom\u00e9nagers",
    "sg:phone":"+32 4 379 58 66",
    "sg:postcode":"4600",
    "sg:province":"Li\u00e8ge",
    "wof:name":"Phillippsen Tv-m\u00c9nager",
    "wof:placetype":"venue"
},
  "geometry": {"coordinates":[5.6938929558,50.7378196716],"type":"Point"}
}