{
  "type": "Feature",
  "properties": {
    "iso:country":"BE",
    "sg:address":"Desselgemsestraat 3",
    "sg:city":"Wielsbeke",
    "sg:orig_category":"Herstellingen and onderhoud van auto's",
    "sg:phone":"+32 56 66 64 57",
    "sg:postcode":"8710",
    "sg:province":"West-Vlaanderen",
    "wof:name":"Garage Cuyle",
    "wof:placetype":"venue"
},
  "geometry": {"coordinates":[3.3370079994,50.8930587769],"type":"Point"}
}