{
  "type": "Feature",
  "properties": {
    "addr:full":"Avenue De La Basilique 35 P\u00e9ruwelz (bon-secours) Hainaut 7603",
    "addr:housenumber":"35",
    "addr:postcode":"7603",
    "addr:street":"Avenue De La Basilique",
    "iso:country":"BE",
    "sg:address":"Avenue De La Basilique 35",
    "sg:city":"P\u00e9ruwelz (bon-secours)",
    "sg:classifiers":[
        {
            "category":"Shopping",
            "subcategory":"Books",
            "type":"Retail Goods"
        }
    ],
    "sg:phone":"+32 69 77 01 59",
    "sg:postcode":"7603",
    "sg:province":"Hainaut",
    "sg:tags":[
        "bookseller"
    ],
    "wof:name":"Graffiti (librairie)",
    "wof:placetype":"venue"
},
  "geometry": {"coordinates":[3.6048619747,50.4986610413],"type":"Point"}
}