{
  "type": "Feature",
  "properties": {
    "iso:country":"BE",
    "sg:address":"Visitatiestraat 5",
    "sg:city":"Gent (sint-amandsberg)",
    "sg:classifiers":[
        {
            "category":"Education",
            "subcategory":"School",
            "type":"Public Place"
        }
    ],
    "sg:phone":"+32 9 228 34 62",
    "sg:postcode":"9040",
    "sg:province":"Oost-Vlaanderen",
    "sg:tags":[
        "secondary"
    ],
    "wof:name":"Sint-janscollege",
    "wof:placetype":"venue"
},
  "geometry": {"coordinates":[3.7483429909,51.0626182556],"type":"Point"}
}