{
  "type": "Feature",
  "properties": {
    "iso:country":"BE",
    "sg:address":"Rue Des Francs Arquebusiers 24",
    "sg:city":"Vis\u00e9",
    "sg:classifiers":[
        {
            "category":"Insurance",
            "subcategory":"Insurance Agent",
            "type":"Services"
        }
    ],
    "sg:phone":"+32 4 374 22 22",
    "sg:postcode":"4600",
    "sg:province":"Li\u00e8ge",
    "sg:tags":[
        "broker"
    ],
    "wof:name":"Gouverneur & Mathias Assurances Sa",
    "wof:placetype":"venue"
},
  "geometry": {"coordinates":[5.6939630508,50.7389144897],"type":"Point"}
}