{
  "type": "Feature",
  "properties": {
    "addr:full":"Ramerstraat 56 Roosdaal Vlaams-Brabant 1760",
    "addr:housenumber":"56",
    "addr:postcode":"1760",
    "addr:street":"Ramerstraat",
    "iso:country":"BE",
    "sg:address":"Ramerstraat 56",
    "sg:city":"Roosdaal",
    "sg:classifiers":[
        {
            "category":"Freight",
            "type":"Transportation"
        }
    ],
    "sg:phone":"+32 54 33 27 76",
    "sg:postcode":"1760",
    "sg:province":"Vlaams-Brabant",
    "sg:tags":[
        "-",
        "transport"
    ],
    "wof:name":"Transbelpa Bvba",
    "wof:placetype":"venue"
},
  "geometry": {"coordinates":[4.0744271278,50.8435707092],"type":"Point"}
}