{
  "type": "Feature",
  "properties": {
    "addr:full":"Blaasveldstraat 24 Willebroek Antwerpen 2830",
    "addr:housenumber":"24",
    "addr:postcode":"2830",
    "addr:street":"Blaasveldstraat",
    "iso:country":"BE",
    "sg:address":"Blaasveldstraat 24",
    "sg:city":"Willebroek",
    "sg:orig_category":"Banques and organismes de cr\u00e9dit",
    "sg:phone":"+32 3 860 19 00",
    "sg:postcode":"2830",
    "sg:province":"Antwerpen",
    "wof:name":"Dexia",
    "wof:placetype":"venue"
},
  "geometry": {"coordinates":[4.3597521782,51.034576416],"type":"Point"}
}