{
  "type": "Feature",
  "properties": {
    "addr:full":"Paradis 7bd Aywaille Li\u00e8ge 4920",
    "addr:postcode":"4920",
    "iso:country":"BE",
    "sg:address":"Paradis 7bd",
    "sg:city":"Aywaille",
    "sg:orig_category":"Woningbouw",
    "sg:phone":"+32 86 43 39 40",
    "sg:postcode":"4920",
    "sg:province":"Li\u00e8ge",
    "wof:name":"Ellipse",
    "wof:placetype":"venue"
},
  "geometry": {"coordinates":[5.6889500618,50.4190101624],"type":"Point"}
}