{
  "type": "Feature",
  "properties": {
    "addr:full":"Schrijnwerkersstraat 9 Hasselt Limburg 3500",
    "addr:housenumber":"9",
    "addr:postcode":"3500",
    "addr:street":"Schrijnwerkersstraat",
    "iso:country":"BE",
    "sg:address":"Schrijnwerkersstraat 9",
    "sg:city":"Hasselt",
    "sg:orig_category":"Eclairage et \u00e9quipements du foyer. Souvenirs and objets artisanaux",
    "sg:phone":"+32 11 23 21 60",
    "sg:postcode":"3500",
    "sg:province":"Limburg",
    "wof:name":"Het Keersken",
    "wof:placetype":"venue"
},
  "geometry": {"coordinates":[5.3360390663,50.9317169189],"type":"Point"}
}