{
  "type": "Feature",
  "properties": {
    "iso:country":"BE",
    "sg:address":"Avenue Du Griffon 15",
    "sg:city":"Braine-le-comte (hennuy\u00e8res)",
    "sg:classifiers":[
        {
            "category":"Professional",
            "subcategory":"Detective & Security Services",
            "type":"Services"
        }
    ],
    "sg:phone":"+32 475 44 00 38",
    "sg:postcode":"7090",
    "sg:province":"Hainaut",
    "sg:tags":[
        "agency"
    ],
    "wof:name":"Bureau D'enqu\u00eates",
    "wof:placetype":"venue"
},
  "geometry": {"coordinates":[4.1967730522,50.6374702454],"type":"Point"}
}