{
  "type": "Feature",
  "properties": {
    "addr:full":"Rue Henin 66 Farciennes (groot) Hainaut 6240",
    "addr:housenumber":"66",
    "addr:postcode":"6240",
    "addr:street":"Rue Henin;Groot Hainaut",
    "iso:country":"BE",
    "sg:address":"Rue Henin 66",
    "sg:city":"Farciennes (groot)",
    "sg:orig_category":"Bierproductie and Brouwerijen Dranken",
    "sg:phone":"+32 71 39 43 39",
    "sg:postcode":"6240",
    "sg:province":"Hainaut",
    "wof:name":"Trentin Benoit",
    "wof:placetype":"venue"
},
  "geometry": {"coordinates":[4.5459752083,50.4275588989],"type":"Point"}
}