{
  "type": "Feature",
  "properties": {
    "iso:country":"BE",
    "sg:address":"Rue Du Pr\u00e9v\u00f4t 144",
    "sg:city":"Bruxelles (ixelles)",
    "sg:classifiers":[
        {
            "category":"Professional",
            "subcategory":"Printing & Photocopies",
            "type":"Services"
        }
    ],
    "sg:phone":"+32 2 345 92 22",
    "sg:postcode":"1050",
    "sg:province":"Bruxelles-Capitale",
    "sg:tags":[
        "-",
        "publishing",
        "desktop"
    ],
    "wof:name":"Faravel P",
    "wof:placetype":"venue"
},
  "geometry": {"coordinates":[4.3623671532,50.8203353882],"type":"Point"}
}