{
  "type": "Feature",
  "properties": {
    "addr:full":"Assesteenweg 26 Ternat Vlaams-Brabant 1740",
    "addr:housenumber":"26",
    "addr:postcode":"1740",
    "addr:street":"Assesteenweg",
    "iso:country":"BE",
    "sg:address":"Assesteenweg 26",
    "sg:city":"Ternat",
    "sg:classifiers":[
        {
            "category":"Restaurant",
            "type":"Food & Drink"
        }
    ],
    "sg:phone":"+32 2 582 31 14",
    "sg:postcode":"1740",
    "sg:province":"Vlaams-Brabant",
    "wof:name":"De Morette",
    "wof:placetype":"venue"
},
  "geometry": {"coordinates":[4.1678609848,50.885219574],"type":"Point"}
}