{
  "type": "Feature",
  "properties": {
    "addr:full":"Rue De La Tasni\u00e8re 63 Rixensart (genval) Brabant Wallon 1332",
    "addr:housenumber":"63",
    "addr:postcode":"1332",
    "addr:street":"Rue De La Tasnie\u0300Re",
    "iso:country":"BE",
    "sg:address":"Rue De La Tasni\u00e8re 63",
    "sg:city":"Rixensart (genval)",
    "sg:classifiers":[
        {
            "category":"Professional",
            "subcategory":"Lawyer & Legal Services",
            "type":"Services"
        }
    ],
    "sg:phone":"+32 2 653 24 42",
    "sg:postcode":"1332",
    "sg:province":"Brabant Wallon",
    "wof:name":"Fotaras Nicole",
    "wof:placetype":"venue"
},
  "geometry": {"coordinates":[4.505423069,50.7273216248],"type":"Point"}
}