{
  "type": "Feature",
  "properties": {
    "addr:full":"Bellegemsestraat 41 Kortrijk West-Vlaanderen 8510",
    "addr:housenumber":"41",
    "addr:postcode":"8510",
    "addr:street":"Bellegemsestraat",
    "iso:country":"BE",
    "sg:address":"Bellegemsestraat 41",
    "sg:city":"Kortrijk",
    "sg:orig_category":"Apotheken",
    "sg:phone":"+32 56 21 08 76",
    "sg:postcode":"8510",
    "sg:province":"West-Vlaanderen",
    "wof:name":"Guido Vanhoutte",
    "wof:placetype":"venue"
},
  "geometry": {"coordinates":[3.2828960419,50.7776260376],"type":"Point"}
}