{
  "type": "Feature",
  "properties": {
    "iso:country":"BE",
    "sg:address":"Hoogstraat 22",
    "sg:city":"Ronse",
    "sg:classifiers":[
        {
            "category":"Restaurant",
            "type":"Food & Drink"
        }
    ],
    "sg:phone":"+32 55 20 90 46",
    "sg:postcode":"9600",
    "sg:province":"Oost-Vlaanderen",
    "wof:name":"La Belle Epoque",
    "wof:placetype":"venue"
},
  "geometry": {"coordinates":[3.5968499184,50.7455787659],"type":"Point"}
}