{
  "type": "Feature",
  "properties": {
    "addr:full":"Kerkstraat 67 Riemst Limburg 3770",
    "addr:housenumber":"67",
    "addr:postcode":"3770",
    "addr:street":"Kerkstraat",
    "iso:country":"BE",
    "sg:address":"Kerkstraat 67",
    "sg:city":"Riemst",
    "sg:orig_category":"Glaszetten and glaswerk",
    "sg:phone":"+32 12 45 13 40",
    "sg:postcode":"3770",
    "sg:province":"Limburg",
    "wof:name":"Vos",
    "wof:placetype":"venue"
},
  "geometry": {"coordinates":[5.5969901085,50.8109016418],"type":"Point"}
}