{
  "type": "Feature",
  "properties": {
    "addr:full":"Akkerstraat 91 Temse Oost-Vlaanderen 9140",
    "addr:housenumber":"91",
    "addr:postcode":"9140",
    "addr:street":"Akkerstraat",
    "iso:country":"BE",
    "sg:address":"Akkerstraat 91",
    "sg:city":"Temse",
    "sg:classifiers":[
        {
            "category":"Recreation",
            "type":"Entertainment"
        }
    ],
    "sg:phone":"+32 477 24 22 01",
    "sg:postcode":"9140",
    "sg:province":"Oost-Vlaanderen",
    "sg:tags":[
        "diver",
        "amusement"
    ],
    "wof:name":"Discobar Jack & Jill",
    "wof:placetype":"venue"
},
  "geometry": {"coordinates":[4.2135000229,51.1273002625],"type":"Point"}
}