{
  "type": "Feature",
  "properties": {
    "iso:country":"BE",
    "sg:address":"Rue L\u00c9opold 38",
    "sg:city":"Charleroi",
    "sg:orig_category":"Kapsalons",
    "sg:phone":"+32 71 37 31 54",
    "sg:postcode":"6041",
    "sg:province":"Hainaut",
    "wof:name":"Cr\u00c9a Style",
    "wof:placetype":"venue"
},
  "geometry": {"coordinates":[4.4427142143,50.4064826965],"type":"Point"}
}