{
  "type": "Feature",
  "properties": {
    "iso:country":"BE",
    "sg:address":"Chrysantenlaan 12",
    "sg:city":"Ternat",
    "sg:classifiers":[
        {
            "category":"Cafe",
            "type":"Food & Drink"
        }
    ],
    "sg:phone":"+32 2 582 26 73",
    "sg:postcode":"1740",
    "sg:province":"Vlaams-Brabant",
    "sg:tags":[
        "caf\u00e9s"
    ],
    "wof:name":"Philippe Wijns",
    "wof:placetype":"venue"
},
  "geometry": {"coordinates":[4.1884980202,50.8743591309],"type":"Point"}
}