{
  "type": "Feature",
  "properties": {
    "addr:full":"Gentse Steenweg 114 Zottegem (grotenberge) Oost-Vlaanderen 9620",
    "addr:housenumber":"114",
    "addr:postcode":"9620",
    "addr:street":"Gentse Steenweg",
    "iso:country":"BE",
    "sg:address":"Gentse Steenweg 114",
    "sg:city":"Zottegem (grotenberge)",
    "sg:classifiers":[
        {
            "category":"Wholesale",
            "subcategory":"Medical Equipment & Supplies",
            "type":"Manufacturing & Wholesale Goods"
        }
    ],
    "sg:phone":"+32 9 360 28 81",
    "sg:postcode":"9620",
    "sg:province":"Oost-Vlaanderen",
    "sg:tags":[
        "aid",
        "hearing"
    ],
    "wof:name":"Audiologische Dienst",
    "wof:placetype":"venue"
},
  "geometry": {"coordinates":[3.8351869583,50.8722381592],"type":"Point"}
}