{
  "type": "Feature",
  "properties": {
    "addr:full":"Rue De Bruxelles 10 Wavre Brabant Wallon 1300",
    "addr:housenumber":"10;1300",
    "addr:street":"Rue De Bruxelles",
    "iso:country":"BE",
    "sg:address":"Rue De Bruxelles 10",
    "sg:city":"Wavre",
    "sg:classifiers":[
        {
            "category":"Insurance",
            "subcategory":"Insurance Agent",
            "type":"Services"
        }
    ],
    "sg:phone":"+32 10 22 33 00",
    "sg:postcode":"1300",
    "sg:province":"Brabant Wallon",
    "sg:tags":[
        "verzekeringsmakelaars",
        "expert"
    ],
    "wof:name":"Assurances Du Brabant",
    "wof:placetype":"venue"
},
  "geometry": {"coordinates":[4.6107010841,50.7175827026],"type":"Point"}
}