{
  "type": "Feature",
  "properties": {
    "iso:country":"BE",
    "sg:address":"Libbelstraat 18",
    "sg:city":"Heusden-zolder",
    "sg:orig_category":"D\u00e9molition d\u00b4immeubles and terrassements",
    "sg:phone":"+32 11 53 35 72",
    "sg:postcode":"3550",
    "sg:province":"Limburg",
    "wof:name":"Vanheel Valere",
    "wof:placetype":"venue"
},
  "geometry": {"coordinates":[5.3139648438,51.0231018066],"type":"Point"}
}