{
  "type": "Feature",
  "properties": {
    "iso:country":"BE",
    "sg:address":"Rue Ad. Vandenschrieck 77",
    "sg:city":"Jette/jette",
    "sg:orig_category":"S\u00e9lection de personnel and placement",
    "sg:phone":"+32 2 423 14 82",
    "sg:postcode":"1090",
    "sg:province":"Bruxelles-Capitale",
    "wof:name":"Ale Jette",
    "wof:placetype":"venue"
},
  "geometry": {"coordinates":[4.3256001472,50.8785133362],"type":"Point"}
}