{
  "type": "Feature",
  "properties": {
    "addr:full":"Voshol 6a Lokeren Oost-Vlaanderen 9160",
    "addr:housenumber":"6a",
    "addr:postcode":"9160",
    "addr:street":"Voshol",
    "iso:country":"BE",
    "sg:address":"Voshol 6a",
    "sg:city":"Lokeren",
    "sg:orig_category":"Betonnen bouwelementen Fab Gespecialiseerde residenti\u00eble bouw",
    "sg:phone":"+32 9 340 55 00",
    "sg:postcode":"9160",
    "sg:province":"Oost-Vlaanderen",
    "wof:name":"De Waal Palen",
    "wof:placetype":"venue"
},
  "geometry": {"coordinates":[4.0131421089,51.0871238708],"type":"Point"}
}