{
  "type": "Feature",
  "properties": {
    "addr:full":"Leemweg 56 Sint-laureins Oost-Vlaanderen 9980",
    "addr:housenumber":"56",
    "addr:postcode":"9980",
    "addr:street":"Leemweg",
    "iso:country":"BE",
    "sg:address":"Leemweg 56",
    "sg:city":"Sint-laureins",
    "sg:classifiers":[
        {
            "category":"Personal",
            "subcategory":"Beauty Salon",
            "type":"Services"
        }
    ],
    "sg:phone":"+32 9 379 06 66",
    "sg:postcode":"9980",
    "sg:province":"Oost-Vlaanderen",
    "sg:tags":[
        "lady",
        "-",
        "hairdressing"
    ],
    "wof:name":"Corry",
    "wof:placetype":"venue"
},
  "geometry": {"coordinates":[3.522644043,51.23802948],"type":"Point"}
}