{
  "type": "Feature",
  "properties": {
    "addr:full":"Hondzochtstraat 26 Pepingen (bellingen) Vlaams-Brabant 1674",
    "addr:housenumber":"26",
    "addr:postcode":"1674",
    "addr:street":"Hondzochtstraat",
    "iso:country":"BE",
    "sg:address":"Hondzochtstraat 26",
    "sg:city":"Pepingen (bellingen)",
    "sg:classifiers":[
        {
            "category":"Building & Trades",
            "subcategory":"Landscaping Services",
            "type":"Services"
        }
    ],
    "sg:phone":"+32 2 356 80 12",
    "sg:postcode":"1674",
    "sg:province":"Vlaams-Brabant",
    "sg:tags":[
        "gardening",
        "garden",
        "maintenance"
    ],
    "wof:name":"Niels J",
    "wof:placetype":"venue"
},
  "geometry": {"coordinates":[4.1679549217,50.7276039124],"type":"Point"}
}