{
  "type": "Feature",
  "properties": {
    "addr:full":"Haachtsebaan 85 Keerbergen Vlaams-Brabant 3140",
    "addr:housenumber":"85",
    "addr:postcode":"3140",
    "addr:street":"Haachtsebaan",
    "iso:country":"BE",
    "sg:address":"Haachtsebaan 85",
    "sg:city":"Keerbergen",
    "sg:classifiers":[
        {
            "category":"Bars & Pubs",
            "type":"Food & Drink"
        }
    ],
    "sg:phone":"+32 15 52 93 36",
    "sg:postcode":"3140",
    "sg:province":"Vlaams-Brabant",
    "sg:tags":[
        "tavern"
    ],
    "wof:name":"Kasteel (het)",
    "wof:placetype":"venue"
},
  "geometry": {"coordinates":[4.6350479126,51.0001144409],"type":"Point"}
}