{
  "type": "Feature",
  "properties": {
    "iso:country":"BE",
    "sg:address":"Schoolstraat 78",
    "sg:city":"Wijnegem",
    "sg:orig_category":"Sportclubs",
    "sg:phone":"+32 3 353 83 60",
    "sg:postcode":"2110",
    "sg:province":"Antwerpen",
    "wof:name":"Verbroederingsbond",
    "wof:placetype":"venue"
},
  "geometry": {"coordinates":[4.5217218399,51.230052948],"type":"Point"}
}