{
  "type": "Feature",
  "properties": {
    "iso:country":"BE",
    "sg:address":"Tremelobaan 109",
    "sg:city":"Keerbergen",
    "sg:orig_category":"Boekhouders",
    "sg:phone":"+32 15 73 06 20",
    "sg:postcode":"3140",
    "sg:province":"Vlaams-Brabant",
    "wof:name":"Gis\u00c8le Caes",
    "wof:placetype":"venue"
},
  "geometry": {"coordinates":[4.6609339714,50.9976730347],"type":"Point"}
}