{
  "type": "Feature",
  "properties": {
    "addr:full":"Waregemstraat 115-117 Waregem (desselgem) West-Vlaanderen 8792",
    "addr:housenumber":"115-117",
    "addr:postcode":"8792",
    "addr:street":"Waregemstraat",
    "iso:country":"BE",
    "sg:address":"Waregemstraat 115-117",
    "sg:city":"Waregem (desselgem)",
    "sg:classifiers":[
        {
            "category":"Retail",
            "subcategory":"Auto Repair",
            "type":"Services"
        }
    ],
    "sg:phone":"+32 56 60 91 08",
    "sg:postcode":"8792",
    "sg:province":"West-Vlaanderen",
    "sg:tags":[
        "automobile-body"
    ],
    "wof:name":"Blockeel C",
    "wof:placetype":"venue"
},
  "geometry": {"coordinates":[3.3729128838,50.8819274902],"type":"Point"}
}