{
  "type": "Feature",
  "properties": {
    "iso:country":"BE",
    "sg:address":"Laurierstraat 32",
    "sg:city":"Lebbeke",
    "sg:orig_category":"Boucheries",
    "sg:phone":"+32 52 41 03 49",
    "sg:postcode":"9280",
    "sg:province":"Oost-Vlaanderen",
    "wof:name":"Raymond Van Cauter",
    "wof:placetype":"venue"
},
  "geometry": {"coordinates":[4.1295337677,50.9989776611],"type":"Point"}
}