{
  "type": "Feature",
  "properties": {
    "iso:country":"BE",
    "sg:address":"Kweekstraat 24",
    "sg:city":"Ingelmunster",
    "sg:orig_category":"Installatie van houten of kunststof schrijnwerk",
    "sg:phone":"+32 51 31 48 62",
    "sg:postcode":"8770",
    "sg:province":"West-Vlaanderen",
    "wof:name":"Defreyne",
    "wof:placetype":"venue"
},
  "geometry": {"coordinates":[3.2722959518,50.8992767334],"type":"Point"}
}