{
  "type": "Feature",
  "properties": {
    "addr:full":"Parkstraat 34 Kortenberg Vlaams-Brabant 3070",
    "addr:housenumber":"34",
    "addr:postcode":"3070",
    "addr:street":"Parkstraat;Vlaams-Brabant",
    "iso:country":"BE",
    "sg:address":"Parkstraat 34",
    "sg:city":"Kortenberg",
    "sg:classifiers":[
        {
            "category":"Wholesale",
            "subcategory":"Medical Equipment & Supplies",
            "type":"Manufacturing & Wholesale Goods"
        }
    ],
    "sg:phone":"+32 2 759 42 52",
    "sg:postcode":"3070",
    "sg:province":"Vlaams-Brabant",
    "sg:tags":[
        "instrument",
        "apparatus"
    ],
    "wof:name":"J.j. Maes Sygma Sa-nv",
    "wof:placetype":"venue"
},
  "geometry": {"coordinates":[4.5417299271,50.8901138306],"type":"Point"}
}