{
  "type": "Feature",
  "properties": {
    "addr:full":"Route De Sor\u00c9e 1ba Ohey Namur 5350",
    "addr:housenumber":"1ba",
    "addr:postcode":"5350",
    "addr:street":"Route De Sore\u0301E",
    "iso:country":"BE",
    "sg:address":"Route De Sor\u00c9e 1ba",
    "sg:city":"Ohey",
    "sg:orig_category":"Rundveehouders",
    "sg:phone":"+32 85 61 14 82",
    "sg:postcode":"5350",
    "sg:province":"Namur",
    "wof:name":"Marcel Toussaint",
    "wof:placetype":"venue"
},
  "geometry": {"coordinates":[5.1258101463,50.4296760559],"type":"Point"}
}