{
  "type": "Feature",
  "properties": {
    "iso:country":"BE",
    "sg:address":"Leopold Ii Laan 243",
    "sg:city":"Koekelberg",
    "sg:orig_category":"Schoonmaakbedrijven and ongediertebestrijding",
    "sg:phone":"+32 2 426 51 61",
    "sg:postcode":"1081",
    "sg:province":"Bruxelles-Capitale",
    "wof:name":"Bianca Services",
    "wof:placetype":"venue"
},
  "geometry": {"coordinates":[4.3326559067,50.8629112244],"type":"Point"}
}