{
  "type": "Feature",
  "properties": {
    "addr:full":"Rue Du Centre 1 Somme-leuze Namur 5377",
    "addr:housenumber":"1",
    "addr:postcode":"5377",
    "addr:street":"Rue Du Centre",
    "iso:country":"BE",
    "sg:address":"Rue Du Centre 1",
    "sg:city":"Somme-leuze",
    "sg:orig_category":"Openbare veiligheid",
    "sg:phone":"+32 86 32 37 70",
    "sg:postcode":"5377",
    "sg:province":"Namur",
    "wof:name":"Police F\u00c9d\u00c9rale/federale Politie",
    "wof:placetype":"venue"
},
  "geometry": {"coordinates":[5.3411860466,50.2794303894],"type":"Point"}
}