{
  "type": "Feature",
  "properties": {
    "addr:full":"Marktstraat 14 Oudenburg West-Vlaanderen 8460",
    "addr:housenumber":"14",
    "addr:postcode":"8460",
    "addr:street":"Marktstraat",
    "iso:country":"BE",
    "sg:address":"Marktstraat 14",
    "sg:city":"Oudenburg",
    "sg:classifiers":[
        {
            "category":"Personal",
            "subcategory":"Beauty Salon",
            "type":"Services"
        }
    ],
    "sg:phone":"+32 59 26 69 24",
    "sg:postcode":"8460",
    "sg:province":"West-Vlaanderen",
    "sg:tags":[
        "de",
        "coiffure"
    ],
    "wof:name":"Coiffure Rachel",
    "wof:placetype":"venue"
},
  "geometry": {"coordinates":[3.0058889389,51.1855125427],"type":"Point"}
}