{
  "type": "Feature",
  "properties": {
    "iso:country":"BE",
    "sg:address":"Uitkerkestraat 6",
    "sg:city":"Blankenberge (uitkerke)",
    "sg:classifiers":[
        {
            "category":"Food & Beverages",
            "subcategory":"Liquor & Beverages",
            "type":"Retail Goods"
        }
    ],
    "sg:phone":"+32 50 41 86 84",
    "sg:postcode":"8370",
    "sg:province":"West-Vlaanderen",
    "sg:tags":[
        "-",
        "spirit",
        "wine"
    ],
    "wof:name":"D J Wine-diffusion",
    "wof:placetype":"venue"
},
  "geometry": {"coordinates":[3.1383390427,51.3071098328],"type":"Point"}
}