{
  "type": "Feature",
  "properties": {
    "addr:full":"Boomlaarstraat 232 Box 2 Lier Antwerpen 2500",
    "addr:housenumber":"232;2",
    "addr:postcode":"2500",
    "addr:street":"Boomlaarstraat;Box",
    "iso:country":"BE",
    "sg:address":"Boomlaarstraat 232 Box 2",
    "sg:city":"Lier",
    "sg:classifiers":[
        {
            "category":"Professional",
            "subcategory":"Accounting & Tax Preparation",
            "type":"Services"
        }
    ],
    "sg:phone":"+32 3 480 20 77",
    "sg:postcode":"2500",
    "sg:province":"Antwerpen",
    "sg:tags":[
        "bookkeeper"
    ],
    "wof:name":"Dyck D",
    "wof:placetype":"venue"
},
  "geometry": {"coordinates":[4.5521059036,51.1318740845],"type":"Point"}
}