{
  "type": "Feature",
  "properties": {
    "addr:full":"Avenue Auguste Jassogne 9 Waterloo Brabant Wallon 1410",
    "addr:housenumber":"9",
    "addr:postcode":"1410",
    "addr:street":"Avenue Auguste Jassogne",
    "iso:country":"BE",
    "sg:address":"Avenue Auguste Jassogne 9",
    "sg:city":"Waterloo",
    "sg:classifiers":[
        {
            "category":"Government",
            "subcategory":"Fire Station",
            "type":"Public Place"
        }
    ],
    "sg:phone":"+32 2 354 33 06",
    "sg:postcode":"1410",
    "sg:province":"Brabant Wallon",
    "sg:tags":[
        "installation",
        "-",
        "air conditioning"
    ],
    "wof:name":"C R C Sa",
    "wof:placetype":"venue"
},
  "geometry": {"coordinates":[4.3805708885,50.7110023499],"type":"Point"}
}