{
  "type": "Feature",
  "properties": {
    "iso:country":"BE",
    "sg:address":"Gaston Coudyserstraat 1",
    "sg:city":"Anderlecht",
    "sg:orig_category":"Dakwerken Schoonmaakbedrijven and ongediertebestrijding",
    "sg:phone":"+32 2 527 06 66",
    "sg:postcode":"1070",
    "sg:province":"Bruxelles-Capitale",
    "wof:name":"Francois Gillade",
    "wof:placetype":"venue"
},
  "geometry": {"coordinates":[4.27957201,50.8373832703],"type":"Point"}
}