{
  "type": "Feature",
  "properties": {
    "addr:full":"Avenue General Michel 1b Charleroi Hainaut 6000",
    "addr:housenumber":"1b",
    "addr:postcode":"6000",
    "addr:street":"Avenue General Michel;Hainaut",
    "iso:country":"BE",
    "sg:address":"Avenue General Michel 1b",
    "sg:city":"Charleroi",
    "sg:orig_category":"High-Tech Training Courses",
    "sg:phone":"+32 71 31 46 10",
    "sg:postcode":"6000",
    "sg:province":"Hainaut",
    "wof:name":"Cunic A.s.b.l.",
    "wof:placetype":"venue"
},
  "geometry": {"coordinates":[4.4504227638,50.4104766846],"type":"Point"}
}