{
  "type": "Feature",
  "properties": {
    "iso:country":"BE",
    "sg:address":"Berlarij 106",
    "sg:city":"Lier",
    "sg:classifiers":[
        {
            "category":"Shopping",
            "subcategory":"Bicycles & Sporting Goods",
            "type":"Retail Goods"
        }
    ],
    "sg:phone":"+32 3 488 10 67",
    "sg:postcode":"2500",
    "sg:province":"Antwerpen",
    "sg:tags":[
        "sport",
        "-"
    ],
    "wof:name":"Fanshop Football Fanatics",
    "wof:placetype":"venue"
},
  "geometry": {"coordinates":[4.5814990997,51.1282615662],"type":"Point"}
}