{
  "type": "Feature",
  "properties": {
    "addr:full":"Fernand Cocqplein 8 Elsene/ixelles Bruxelles-Capitale 1050",
    "addr:housenumber":"8",
    "addr:postcode":"1050",
    "addr:street":"Fernand Cocqplein",
    "iso:country":"BE",
    "sg:address":"Fernand Cocqplein 8",
    "sg:city":"Elsene/ixelles",
    "sg:orig_category":"Foto-uitrusting",
    "sg:phone":"+32 2 512 15 44",
    "sg:postcode":"1050",
    "sg:province":"Bruxelles-Capitale",
    "wof:name":"Maison Kelecom",
    "wof:placetype":"venue"
},
  "geometry": {"coordinates":[4.3662161827,50.8331604004],"type":"Point"}
}