{
  "type": "Feature",
  "properties": {
    "addr:full":"Rue De Bastogne 124 Aywaille (harz\u00e9) Li\u00e8ge 4920",
    "addr:housenumber":"124",
    "addr:postcode":"4920",
    "addr:street":"Rue De Bastogne",
    "iso:country":"BE",
    "sg:address":"Rue De Bastogne 124",
    "sg:city":"Aywaille (harz\u00e9)",
    "sg:classifiers":[
        {
            "category":"Personal",
            "subcategory":"Beauty Salon",
            "type":"Services"
        }
    ],
    "sg:phone":"+32 4 384 72 73",
    "sg:postcode":"4920",
    "sg:province":"Li\u00e8ge",
    "sg:tags":[
        "lady",
        "-",
        "hairdressing"
    ],
    "wof:name":"Ad Coiffure",
    "wof:placetype":"venue"
},
  "geometry": {"coordinates":[5.6782069206,50.4738540649],"type":"Point"}
}