{
  "type": "Feature",
  "properties": {
    "addr:full":"Rue De Huy 30 Waremme Li\u00e8ge 4300",
    "addr:housenumber":"30",
    "addr:postcode":"4300",
    "addr:street":"Rue De Huy",
    "iso:country":"BE",
    "sg:address":"Rue De Huy 30",
    "sg:city":"Waremme",
    "sg:classifiers":[
        {
            "category":"Social Services",
            "subcategory":"Retirement Home",
            "type":"Services"
        }
    ],
    "sg:phone":"+32 19 32 49 99",
    "sg:postcode":"4300",
    "sg:province":"Li\u00e8ge",
    "sg:tags":[
        "compagnies",
        "vie",
        "assurance",
        "habitation"
    ],
    "wof:name":"Hamburg Mannheimer",
    "wof:placetype":"venue"
},
  "geometry": {"coordinates":[5.2513017654,50.6932296753],"type":"Point"}
}