{
  "type": "Feature",
  "properties": {
    "addr:full":"Smisstraat 112 Tervuren Vlaams-Brabant 3080",
    "addr:housenumber":"112",
    "addr:postcode":"3080",
    "addr:street":"Smisstraat",
    "iso:country":"BE",
    "sg:address":"Smisstraat 112",
    "sg:city":"Tervuren",
    "sg:orig_category":"Diverse bedrijfsbeheeradviesbureaus",
    "sg:phone":"+32 2 767 64 74",
    "sg:postcode":"3080",
    "sg:province":"Vlaams-Brabant",
    "wof:name":"Hubertus Kal Consultants",
    "wof:placetype":"venue"
},
  "geometry": {"coordinates":[4.5475549698,50.8329734802],"type":"Point"}
}