{
  "type": "Feature",
  "properties": {
    "iso:country":"BE",
    "sg:address":"Pothoekstraat 136",
    "sg:city":"Antwerpen",
    "sg:classifiers":[
        {
            "category":"Social Services",
            "type":"Services"
        }
    ],
    "sg:phone":"+32 3 236 21 25",
    "sg:postcode":"2060",
    "sg:province":"Antwerpen",
    "wof:name":"Woonwijzer-noord",
    "wof:placetype":"venue"
},
  "geometry": {"coordinates":[4.43689394,51.2251396179],"type":"Point"}
}