{
  "type": "Feature",
  "properties": {
    "addr:full":"Berlaarsestraat 10 Lier Antwerpen 2500",
    "addr:housenumber":"10",
    "addr:postcode":"2500",
    "addr:street":"Berlaarsestraat",
    "iso:country":"BE",
    "sg:address":"Berlaarsestraat 10",
    "sg:city":"Lier",
    "sg:orig_category":"Baby- and kinderkleding",
    "sg:phone":"+32 3 489 10 69",
    "sg:postcode":"2500",
    "sg:province":"Antwerpen",
    "wof:name":"Huis Ollie & Fie",
    "wof:placetype":"venue"
},
  "geometry": {"coordinates":[4.5766010284,51.1295204163],"type":"Point"}
}