{
  "type": "Feature",
  "properties": {
    "iso:country":"BE",
    "sg:address":"Rue De Strichon 58",
    "sg:city":"Villers-la-ville",
    "sg:orig_category":"Woningbouw",
    "sg:phone":"+32 71 87 65 92",
    "sg:postcode":"1495",
    "sg:province":"Brabant Wallon",
    "wof:name":"Carrsol",
    "wof:placetype":"venue"
},
  "geometry": {"coordinates":[4.5588498116,50.577960968],"type":"Point"}
}