{
  "type": "Feature",
  "properties": {
    "iso:country":"BE",
    "sg:address":"Place Albert-elisabeth 46",
    "sg:city":"Saint-ghislain",
    "sg:orig_category":"RESTAURANTS: CAF\u00c9S",
    "sg:phone":"+32 65 79 34 79",
    "sg:postcode":"7330",
    "sg:province":"Hainaut",
    "wof:name":"Taverne Le Classic",
    "wof:placetype":"venue"
},
  "geometry": {"coordinates":[3.818819046,50.443321228],"type":"Point"}
}