{
  "type": "Feature",
  "properties": {
    "iso:country":"BE",
    "sg:address":"Rue Sans Souci 5",
    "sg:city":"Bruxelles (ixelles)",
    "sg:classifiers":[
        {
            "category":"Professional",
            "subcategory":"Art Services",
            "type":"Services"
        }
    ],
    "sg:phone":"+32 2 647 69 24",
    "sg:postcode":"1050",
    "sg:province":"Bruxelles-Capitale",
    "sg:tags":[
        "-",
        "painter",
        "artist"
    ],
    "wof:name":"Wollner S",
    "wof:placetype":"venue"
},
  "geometry": {"coordinates":[4.3721699715,50.8330116272],"type":"Point"}
}