{
  "type": "Feature",
  "properties": {
    "addr:full":"Industriepark Noord 3 Sint-niklaas Oost-Vlaanderen 9100",
    "addr:housenumber":"3",
    "addr:postcode":"9100",
    "addr:street":"Industriepark Noord",
    "iso:country":"BE",
    "sg:address":"Industriepark Noord 3",
    "sg:city":"Sint-niklaas",
    "sg:classifiers":[
        {
            "category":"Home & Garden",
            "subcategory":"Furniture",
            "type":"Retail Goods"
        }
    ],
    "sg:phone":"+32 3 766 88 75",
    "sg:postcode":"9100",
    "sg:province":"Oost-Vlaanderen",
    "sg:tags":[
        "fab",
        "meubelen",
        "diverse"
    ],
    "wof:name":"Kast - Id",
    "wof:placetype":"venue"
},
  "geometry": {"coordinates":[4.1661381721,51.1464271545],"type":"Point"}
}