{
  "type": "Feature",
  "properties": {
    "iso:country":"BE",
    "sg:address":"Fleriskotstraat 88",
    "sg:city":"Middelkerke",
    "sg:orig_category":"Producteurs de l\u00e9gumes. Eleveurs and marchands de porcs",
    "sg:phone":"+32 59 30 00 43",
    "sg:postcode":"8431",
    "sg:province":"West-Vlaanderen",
    "wof:name":"Johan En Dirk Pittery",
    "wof:placetype":"venue"
},
  "geometry": {"coordinates":[2.832075119,51.1768417358],"type":"Point"}
}