{
  "type": "Feature",
  "properties": {
    "iso:country":"BE",
    "sg:address":"Sint-pietersplein 8b2/2",
    "sg:city":"Oostkamp",
    "sg:orig_category":"Drukkerijen and copyshops",
    "sg:phone":"+32 50 82 31 84",
    "sg:postcode":"8020",
    "sg:province":"West-Vlaanderen",
    "wof:name":"Ferdinand Demuyt",
    "wof:placetype":"venue"
},
  "geometry": {"coordinates":[3.2333500385,51.1545715332],"type":"Point"}
}