{
  "type": "Feature",
  "properties": {
    "iso:country":"BE",
    "sg:address":"Gasthuisbosdreef 20",
    "sg:city":"Tongeren",
    "sg:classifiers":[
        {
            "category":"Manufacturing",
            "subcategory":"Metals",
            "type":"Manufacturing & Wholesale Goods"
        }
    ],
    "sg:phone":"+32 12 23 47 38",
    "sg:postcode":"3700",
    "sg:province":"Limburg",
    "sg:tags":[
        "polishing"
    ],
    "wof:name":"Nassen Bvba",
    "wof:placetype":"venue"
},
  "geometry": {"coordinates":[5.4532170296,50.7924575806],"type":"Point"}
}