{
  "type": "Feature",
  "properties": {
    "iso:country":"BE",
    "sg:address":"Bergwegel 21",
    "sg:city":"Merelbeke",
    "sg:classifiers":[
        {
            "category":"Health Services",
            "subcategory":"Health Practitioner",
            "type":"Services"
        }
    ],
    "sg:phone":"+32 9 231 74 21",
    "sg:postcode":"9820",
    "sg:province":"Oost-Vlaanderen",
    "sg:tags":[
        "physiotherapist"
    ],
    "wof:name":"Remue C",
    "wof:placetype":"venue"
},
  "geometry": {"coordinates":[3.7388699055,50.9890060425],"type":"Point"}
}