{
  "type": "Feature",
  "properties": {
    "iso:country":"BE",
    "sg:address":"Rue De La Bass\u00e9e 1b",
    "sg:city":"Mouscron (luingne)",
    "sg:classifiers":[
        {
            "category":"Freight",
            "type":"Transportation"
        }
    ],
    "sg:phone":"+32 56 84 74 20",
    "sg:postcode":"7700",
    "sg:province":"Hainaut",
    "sg:tags":[
        "-",
        "transport"
    ],
    "wof:name":"Dhondt Logistics",
    "wof:placetype":"venue"
},
  "geometry": {"coordinates":[3.2542850971,50.7452659607],"type":"Point"}
}