{
  "type": "Feature",
  "properties": {
    "addr:full":"Rue Du Pont-pavot 23 Frasnes Namur 5660",
    "addr:housenumber":"23",
    "addr:postcode":"5660",
    "addr:street":"Rue Du Pont-Pavot;Frasnes Namur",
    "iso:country":"BE",
    "sg:address":"Rue Du Pont-pavot 23",
    "sg:city":"Frasnes",
    "sg:classifiers":[
        {
            "category":"Autos & Motor Vehicles",
            "subcategory":"Automobile Sales",
            "type":"Retail Goods"
        }
    ],
    "sg:phone":"+32 60 31 10 01",
    "sg:postcode":"5660",
    "sg:province":"Namur",
    "sg:tags":[
        "equipment",
        "motor-cars",
        "transport"
    ],
    "wof:name":"Denonvauto Sa",
    "wof:placetype":"venue"
},
  "geometry": {"coordinates":[4.5198869705,50.0866279602],"type":"Point"}
}