{
  "type": "Feature",
  "properties": {
    "addr:full":"Rue Jean-joseph Piret 90 Gerpinnes Hainaut 6280",
    "addr:housenumber":"90",
    "addr:postcode":"6280",
    "addr:street":"Rue Jean-Joseph Piret;Hainaut",
    "iso:country":"BE",
    "sg:address":"Rue Jean-joseph Piret 90",
    "sg:city":"Gerpinnes",
    "sg:orig_category":"Maisons de repos and r\u00e9sidences",
    "sg:phone":"+32 71 50 43 02",
    "sg:postcode":"6280",
    "sg:province":"Hainaut",
    "wof:name":"Home De Joncret",
    "wof:placetype":"venue"
},
  "geometry": {"coordinates":[4.4992599487,50.3438682556],"type":"Point"}
}