{
  "type": "Feature",
  "properties": {
    "addr:full":"Dam 13b2 Kortrijk West-Vlaanderen 8500",
    "addr:housenumber":"13b2",
    "addr:postcode":"8500",
    "addr:street":"Dam",
    "iso:country":"BE",
    "sg:address":"Dam 13b2",
    "sg:city":"Kortrijk",
    "sg:classifiers":[
        {
            "category":"Professional",
            "subcategory":"Accounting & Tax Preparation",
            "type":"Services"
        }
    ],
    "sg:phone":"+32 56 22 01 14",
    "sg:postcode":"8500",
    "sg:province":"West-Vlaanderen",
    "sg:tags":[
        "accountant"
    ],
    "wof:name":"Yves Dekegeleer",
    "wof:placetype":"venue"
},
  "geometry": {"coordinates":[3.2642700672,50.8319740295],"type":"Point"}
}