{
  "type": "Feature",
  "properties": {
    "addr:full":"Kan. Van Tichelenlaan 9 Stabroek Antwerpen 2940",
    "addr:housenumber":"9",
    "addr:postcode":"2940",
    "addr:street":"Kan. Van Tichelenlaan",
    "iso:country":"BE",
    "sg:address":"Kan. Van Tichelenlaan 9",
    "sg:city":"Stabroek",
    "sg:orig_category":"Sportclubs",
    "sg:phone":"+32 3 568 10 02",
    "sg:postcode":"2940",
    "sg:province":"Antwerpen",
    "wof:name":"K.c. Hoevenen",
    "wof:placetype":"venue"
},
  "geometry": {"coordinates":[4.3766560555,51.329990387],"type":"Point"}
}