{
  "type": "Feature",
  "properties": {
    "addr:full":"Cardijnlaan 21 Herenthout Antwerpen 2270",
    "addr:housenumber":"21",
    "addr:postcode":"2270",
    "addr:street":"Cardijnlaan",
    "iso:country":"BE",
    "sg:address":"Cardijnlaan 21",
    "sg:city":"Herenthout",
    "sg:orig_category":"HUISBRANDOLIE Royal Canin Tuinbenodigdheden",
    "sg:phone":"+32 14 51 12 96",
    "sg:postcode":"2270",
    "sg:province":"Antwerpen",
    "wof:name":"Buts Jan",
    "wof:placetype":"venue"
},
  "geometry": {"coordinates":[4.7619872093,51.1413803101],"type":"Point"}
}