{
  "type": "Feature",
  "properties": {
    "addr:full":"Hoge Bokstraat 134 Sint-niklaas Oost-Vlaanderen 9111",
    "addr:housenumber":"134",
    "addr:postcode":"9111",
    "addr:street":"Hoge Bokstraat",
    "iso:country":"BE",
    "sg:address":"Hoge Bokstraat 134",
    "sg:city":"Sint-niklaas",
    "sg:orig_category":"Artiesten and kunstenaars",
    "sg:phone":"+32 3 765 15 66",
    "sg:postcode":"9111",
    "sg:province":"Oost-Vlaanderen",
    "wof:name":"Guy Dhondt",
    "wof:placetype":"venue"
},
  "geometry": {"coordinates":[4.1126589775,51.1661949158],"type":"Point"}
}