{
  "type": "Feature",
  "properties": {
    "iso:country":"BE",
    "sg:address":"Rue Des Bouchers 2",
    "sg:city":"Martelange",
    "sg:orig_category":"Slagers",
    "sg:phone":"+32 63 60 01 33",
    "sg:postcode":"6630",
    "sg:province":"Luxembourg",
    "wof:name":"Schmit",
    "wof:placetype":"venue"
},
  "geometry": {"coordinates":[5.739648819,49.8319206238],"type":"Point"}
}