{
  "type": "Feature",
  "properties": {
    "addr:full":"Molenslag 38 Lovendegem (vinderhoute) Oost-Vlaanderen 9921",
    "addr:housenumber":"38",
    "addr:postcode":"9921",
    "addr:street":"Molenslag",
    "iso:country":"BE",
    "sg:address":"Molenslag 38",
    "sg:city":"Lovendegem (vinderhoute)",
    "sg:classifiers":[
        {
            "category":"Building & Trades",
            "subcategory":"Construction",
            "type":"Services"
        }
    ],
    "sg:phone":"+32 9 236 25 54",
    "sg:postcode":"9921",
    "sg:province":"Oost-Vlaanderen",
    "sg:tags":[
        "work",
        "waterproofing"
    ],
    "wof:name":"De Bosscher D",
    "wof:placetype":"venue"
},
  "geometry": {"coordinates":[3.6214039326,51.083656311],"type":"Point"}
}