{
  "type": "Feature",
  "properties": {
    "iso:country":"BE",
    "sg:address":"Lar",
    "sg:city":"Menen (rekkem)",
    "sg:classifiers":[
        {
            "category":"Airport",
            "subcategory":"International",
            "type":"Transportation"
        }
    ],
    "sg:phone":"+32 56 41 98 48",
    "sg:postcode":"8930",
    "sg:province":"West-Vlaanderen",
    "sg:tags":[
        "-",
        "transport"
    ],
    "wof:name":"Fritz A Ups Company",
    "wof:placetype":"venue"
},
  "geometry": {"coordinates":[3.1944880486,50.7747917175],"type":"Point"}
}