{
  "type": "Feature",
  "properties": {
    "addr:full":"Chauss\u00e9e De Namur 2 Nivelles Brabant Wallon 1400",
    "addr:housenumber":"2",
    "addr:postcode":"1400",
    "addr:street":"Chausse\u0301E De Namur",
    "iso:country":"BE",
    "sg:address":"Chauss\u00e9e De Namur 2",
    "sg:city":"Nivelles",
    "sg:classifiers":[
        {
            "category":"Parking",
            "subcategory":"Lot",
            "type":"Transportation"
        }
    ],
    "sg:phone":"+32 67 21 28 06",
    "sg:postcode":"1400",
    "sg:province":"Brabant Wallon",
    "sg:tags":[
        "parking-places",
        "laying-out"
    ],
    "wof:name":"Vallons",
    "wof:placetype":"venue"
},
  "geometry": {"coordinates":[4.3426218033,50.5990943909],"type":"Point"}
}