{
  "type": "Feature",
  "properties": {
    "iso:country":"BE",
    "sg:address":"Wijnendale- Stationstraat 69",
    "sg:city":"Torhout",
    "sg:orig_category":"Kapsalons",
    "sg:phone":"+32 50 21 15 86",
    "sg:postcode":"8820",
    "sg:province":"West-Vlaanderen",
    "wof:name":"Coiffure Reflexion",
    "wof:placetype":"venue"
},
  "geometry": {"coordinates":[3.1050899029,51.0647201538],"type":"Point"}
}