{
  "type": "Feature",
  "properties": {
    "iso:country":"BE",
    "sg:address":"Augustina Peutermanstraat 5",
    "sg:city":"Wevelgem",
    "sg:classifiers":[
        {
            "category":"Professional",
            "subcategory":"Accounting & Tax Preparation",
            "type":"Services"
        }
    ],
    "sg:phone":"+32 56 42 30 46",
    "sg:postcode":"8560",
    "sg:province":"West-Vlaanderen",
    "sg:tags":[
        "bookkeeper"
    ],
    "wof:name":"Dekeyzer I",
    "wof:placetype":"venue"
},
  "geometry": {"coordinates":[3.1830880642,50.8032264709],"type":"Point"}
}