{
  "type": "Feature",
  "properties": {
    "addr:full":"Av Des Eaux Vives 13 Genval Brabant Wallon 1332",
    "addr:housenumber":"13",
    "addr:postcode":"1332",
    "addr:street":"Av Des Eaux Vives",
    "iso:country":"BE",
    "sg:address":"Av Des Eaux Vives 13",
    "sg:city":"Genval",
    "sg:classifiers":[
        {
            "category":"Home & Garden",
            "subcategory":"Furniture",
            "type":"Retail Goods"
        }
    ],
    "sg:phone":"+32 2 653 13 79",
    "sg:postcode":"1332",
    "sg:province":"Brabant Wallon",
    "sg:tags":[
        "wood"
    ],
    "wof:name":"Itb Sa",
    "wof:placetype":"venue"
},
  "geometry": {"coordinates":[4.5105528831,50.7300033569],"type":"Point"}
}