{
  "type": "Feature",
  "properties": {
    "iso:country":"BE",
    "sg:address":"Rue De L'eglise 5",
    "sg:city":"Wavre (bierges)",
    "sg:classifiers":[
        {
            "category":"Utilities",
            "subcategory":"Telephone",
            "type":"Services"
        }
    ],
    "sg:phone":"+32 10 40 27 25",
    "sg:postcode":"1301",
    "sg:province":"Brabant Wallon",
    "sg:tags":[
        "-",
        "internet"
    ],
    "wof:name":"Gr\u00e9 \u00e0 Gr\u00e9 Sprl",
    "wof:placetype":"venue"
},
  "geometry": {"coordinates":[4.5795311928,50.7167320251],"type":"Point"}
}