{
  "type": "Feature",
  "properties": {
    "addr:full":"Heidestraat 239 Zwijndrecht Antwerpen 2070",
    "addr:housenumber":"239",
    "addr:postcode":"2070",
    "addr:street":"Heidestraat",
    "iso:country":"BE",
    "sg:address":"Heidestraat 239",
    "sg:city":"Zwijndrecht",
    "sg:classifiers":[
        {
            "category":"Cafe",
            "type":"Food & Drink"
        }
    ],
    "sg:phone":"+32 3 253 15 34",
    "sg:postcode":"2070",
    "sg:province":"Antwerpen",
    "sg:tags":[
        "caf\u00e9s"
    ],
    "wof:name":"Caf\u00c9 De Ster",
    "wof:placetype":"venue"
},
  "geometry": {"coordinates":[4.3330698013,51.2100105286],"type":"Point"}
}