{
  "type": "Feature",
  "properties": {
    "iso:country":"BE",
    "sg:address":"Rue De March\u00c9 16b1",
    "sg:city":"Nandrin",
    "sg:orig_category":"Herstellingen and onderhoud van auto's",
    "sg:phone":"+32 85 51 35 60",
    "sg:postcode":"4550",
    "sg:province":"Li\u00e8ge",
    "wof:name":"Pressing Car",
    "wof:placetype":"venue"
},
  "geometry": {"coordinates":[5.441010952,50.5418548584],"type":"Point"}
}