{
  "type": "Feature",
  "properties": {
    "addr:full":"Buurtstraat 50 Maldegem Oost-Vlaanderen 9990",
    "addr:housenumber":"50",
    "addr:postcode":"9990",
    "addr:street":"Buurtstraat",
    "iso:country":"BE",
    "sg:address":"Buurtstraat 50",
    "sg:city":"Maldegem",
    "sg:orig_category":"Kapsalons",
    "sg:phone":"+32 50 71 93 07",
    "sg:postcode":"9990",
    "sg:province":"Oost-Vlaanderen",
    "wof:name":"Coiffure Mireille",
    "wof:placetype":"venue"
},
  "geometry": {"coordinates":[3.4379479885,51.2183914185],"type":"Point"}
}