{
  "type": "Feature",
  "properties": {
    "addr:full":"Avenue Du Roi Albert 114 Bruxelles (berchem-sainte-agathe) Bruxelles-Capitale 1082",
    "addr:housenumber":"114",
    "addr:postcode":"1082",
    "addr:street":"Avenue Du Roi Albert",
    "iso:country":"BE",
    "sg:address":"Avenue Du Roi Albert 114",
    "sg:city":"Bruxelles (berchem-sainte-agathe)",
    "sg:classifiers":[
        {
            "category":"Arts & Performance",
            "subcategory":"Music",
            "type":"Entertainment"
        }
    ],
    "sg:phone":"+32 2 465 68 95",
    "sg:postcode":"1082",
    "sg:province":"Bruxelles-Capitale",
    "sg:tags":[
        "freelance",
        "musician"
    ],
    "wof:name":"De Ridder J",
    "wof:placetype":"venue"
},
  "geometry": {"coordinates":[4.2909359932,50.8657913208],"type":"Point"}
}