{
  "type": "Feature",
  "properties": {
    "iso:country":"BE",
    "sg:address":"Den Hert 6",
    "sg:city":"Lille",
    "sg:orig_category":"Advocaten and juridische adviseurs",
    "sg:phone":"+32 14 41 04 53",
    "sg:postcode":"2275",
    "sg:province":"Antwerpen",
    "wof:name":"P. Willems",
    "wof:placetype":"venue"
},
  "geometry": {"coordinates":[4.7858099937,51.2629814148],"type":"Point"}
}