{
  "type": "Feature",
  "properties": {
    "addr:full":"Wommelgemsteenweg 18 Wijnegem Antwerpen 2110",
    "addr:housenumber":"18",
    "addr:postcode":"2110",
    "addr:street":"Wommelgemsteenweg",
    "iso:country":"BE",
    "sg:address":"Wommelgemsteenweg 18",
    "sg:city":"Wijnegem",
    "sg:classifiers":[
        {
            "category":"Social Services",
            "subcategory":"Job Training",
            "type":"Services"
        }
    ],
    "sg:phone":"+32 3 320 82 90",
    "sg:postcode":"2110",
    "sg:province":"Antwerpen",
    "sg:tags":[
        "personnel"
    ],
    "wof:name":"Cevora Vzw",
    "wof:placetype":"venue"
},
  "geometry": {"coordinates":[4.5204701424,51.2265739441],"type":"Point"}
}