{
  "type": "Feature",
  "properties": {
    "addr:full":"Trammezandlei 113 Antwerpen Antwerpen 2170",
    "addr:housenumber":"113",
    "addr:postcode":"2170",
    "addr:street":"Trammezandlei",
    "iso:country":"BE",
    "sg:address":"Trammezandlei 113",
    "sg:city":"Antwerpen",
    "sg:classifiers":[
        {
            "category":"Cafe",
            "type":"Food & Drink"
        }
    ],
    "sg:phone":"+32 3 645 80 32",
    "sg:postcode":"2170",
    "sg:province":"Antwerpen",
    "sg:tags":[
        "caf\u00e9s"
    ],
    "wof:name":"Verelst",
    "wof:placetype":"venue"
},
  "geometry": {"coordinates":[4.4505147934,51.246723175],"type":"Point"}
}