{
  "type": "Feature",
  "properties": {
    "addr:full":"Sint-elooisstraat 107 Oostkamp West-Vlaanderen 8020",
    "addr:housenumber":"107",
    "addr:postcode":"8020",
    "addr:street":"Sint-Elooisstraat",
    "iso:country":"BE",
    "sg:address":"Sint-elooisstraat 107",
    "sg:city":"Oostkamp",
    "sg:orig_category":"Dranken",
    "sg:phone":"+32 50 82 42 27",
    "sg:postcode":"8020",
    "sg:province":"West-Vlaanderen",
    "wof:name":"Notterdam",
    "wof:placetype":"venue"
},
  "geometry": {"coordinates":[3.2350599766,51.1533241272],"type":"Point"}
}