{
  "type": "Feature",
  "properties": {
    "addr:full":"Rue Du Temple 25 La Louviere Hainaut 7100",
    "addr:housenumber":"25",
    "addr:postcode":"7100",
    "addr:street":"Rue Du Temple",
    "iso:country":"BE",
    "sg:address":"Rue Du Temple 25",
    "sg:city":"La Louviere",
    "sg:orig_category":"Installatie van metalen schrijnwerk Plaatsen van vloer- and muurbekleding Schilders Verlichting and ",
    "sg:phone":"+32 64 26 62 46",
    "sg:postcode":"7100",
    "sg:province":"Hainaut",
    "wof:name":"Lauranou-decor",
    "wof:placetype":"venue"
},
  "geometry": {"coordinates":[4.1877851486,50.4756660461],"type":"Point"}
}