{
  "type": "Feature",
  "properties": {
    "iso:country":"BE",
    "sg:address":"Chauss\u00e9e De Lille 80",
    "sg:city":"Mouscron",
    "sg:classifiers":[
        {
            "category":"Food & Beverages",
            "subcategory":"Chocolate",
            "type":"Retail Goods"
        }
    ],
    "sg:phone":"+32 56 48 69 64",
    "sg:postcode":"7700",
    "sg:province":"Hainaut",
    "sg:tags":[
        "delivered",
        "-",
        "non-food"
    ],
    "wof:name":"Shopping Home",
    "wof:placetype":"venue"
},
  "geometry": {"coordinates":[3.1945269108,50.7566184998],"type":"Point"}
}