{
  "type": "Feature",
  "properties": {
    "addr:full":"71 Rue De Pieton 6183 Courcelles 71",
    "addr:housenumber":"71;71",
    "addr:postcode":"6183",
    "addr:street":"Rue De Pieton;Courcelles",
    "iso:country":"BE",
    "sg:address":"71",
    "sg:city":"Rue De Pieton 6183 Courcelles",
    "sg:classifiers":[
        {
            "category":"Building & Trades",
            "subcategory":"Construction",
            "type":"Services"
        }
    ],
    "sg:phone":"+32 71 46 00 10",
    "sg:postcode":"71",
    "sg:tags":[
        "work",
        "public"
    ],
    "wof:name":"Hullbridge Associated Sa",
    "wof:placetype":"venue"
},
  "geometry": {"coordinates":[4.3208961487,50.453327179],"type":"Point"}
}