{
  "type": "Feature",
  "properties": {
    "iso:country":"BE",
    "sg:address":"Rue De La Silentiaire 2",
    "sg:city":"Paliseul",
    "sg:classifiers":[
        {
            "category":"Cafe",
            "type":"Food & Drink"
        }
    ],
    "sg:phone":"+32 61 53 34 37",
    "sg:postcode":"6852",
    "sg:province":"Luxembourg",
    "sg:tags":[
        "caf\u00e9s"
    ],
    "wof:name":"Jeanne Lambot",
    "wof:placetype":"venue"
},
  "geometry": {"coordinates":[5.1785240173,49.9646186829],"type":"Point"}
}