{
  "type": "Feature",
  "properties": {
    "iso:country":"BE",
    "sg:address":"Rue De France 6",
    "sg:city":"Genappe",
    "sg:orig_category":"V\u00e9t\u00e9rinaires",
    "sg:phone":"+32 67 78 09 81",
    "sg:postcode":"1470",
    "sg:province":"Brabant Wallon",
    "wof:name":"Caroline Cajot",
    "wof:placetype":"venue"
},
  "geometry": {"coordinates":[4.4496312141,50.6098136902],"type":"Point"}
}