{
  "type": "Feature",
  "properties": {
    "iso:country":"BE",
    "sg:address":"Rue Georges Jouret 13",
    "sg:city":"Flobecq",
    "sg:classifiers":[
        {
            "category":"Health Services",
            "subcategory":"Health Practitioner",
            "type":"Services"
        }
    ],
    "sg:phone":"+32 68 44 81 50",
    "sg:postcode":"7880",
    "sg:province":"Hainaut",
    "sg:tags":[
        "therapist",
        "speech"
    ],
    "wof:name":"Menart Anne",
    "wof:placetype":"venue"
},
  "geometry": {"coordinates":[3.7438709736,50.7386703491],"type":"Point"}
}