{
  "type": "Feature",
  "properties": {
    "iso:country":"BE",
    "sg:address":"Rue Abb\u00c9-dujardin 3",
    "sg:city":"Onhaye",
    "sg:classifiers":[
        {
            "category":"Cafe",
            "type":"Food & Drink"
        }
    ],
    "sg:phone":"+32 82 64 65 44",
    "sg:postcode":"5520",
    "sg:province":"Namur",
    "sg:tags":[
        "caf\u00e9s"
    ],
    "wof:name":"Caf\u00c9 Le Fer \u00c0 Cheval",
    "wof:placetype":"venue"
},
  "geometry": {"coordinates":[4.837375164,50.2424087524],"type":"Point"}
}