{
  "type": "Feature",
  "properties": {
    "iso:country":"BE",
    "sg:address":"Rue Du Dur 10",
    "sg:city":"Charleroi",
    "sg:orig_category":"M\u00e9decins and sp\u00e9cialistes",
    "sg:phone":"+32 71 31 11 24",
    "sg:postcode":"6061",
    "sg:province":"Hainaut",
    "wof:name":"Jean-yves Hindlet",
    "wof:placetype":"venue"
},
  "geometry": {"coordinates":[4.4713158607,50.4026260376],"type":"Point"}
}